{
  "type": "Feature",
  "properties": {
    "addr:full":"Avgd Ronda Nord, 320 Catarroja Valencia 46470",
    "addr:housenumber":"320",
    "addr:postcode":"46470",
    "addr:street":"Ronda Nord",
    "iso:country":"ES",
    "sg:address":"Avgd Ronda Nord, 320",
    "sg:city":"Catarroja",
    "sg:orig_category":"Importaci\u00d3n",
    "sg:phone":"+34 961 26 49 77",
    "sg:postcode":"46470",
    "sg:province":"Valencia",
    "wof:name":"Yague Importaciones S.l.",
    "wof:placetype":"venue"
},
  "geometry": {"coordinates":[-0.4035184085,39.4027366638],"type":"Point"}
}