{
  "type": "Feature",
  "properties": {
    "iso:country":"ES",
    "sg:address":"Calle de Anselmo Perez De Brito, 10",
    "sg:city":"Santa Cruz Palma",
    "sg:orig_category":"Consultas M\u00c9dicas",
    "sg:phone":"+34 922 41 13 98",
    "sg:postcode":"38700",
    "sg:province":"Santa Cruz De Tenerife",
    "wof:name":"Centro Medico Cemepal S.l.",
    "wof:placetype":"venue"
},
  "geometry": {"coordinates":[-17.764093399,28.6839332581],"type":"Point"}
}