{
  "type": "Feature",
  "properties": {
    "iso:country":"ES",
    "sg:address":"Calle de Jose Antonio (de), 39",
    "sg:city":"Boadilla Del Monte",
    "sg:orig_category":"Alimentaci\u00d3n Animal (fabricaci\u00d3n, Al Por Mayor)",
    "sg:phone":"+34 916 32 00 73",
    "sg:postcode":"28660",
    "sg:province":"Madrid",
    "wof:name":"Polcan C.b",
    "wof:placetype":"venue"
},
  "geometry": {"coordinates":[-3.8781681061,40.4065322876],"type":"Point"}
}