{
  "type": "Feature",
  "properties": {
    "iso:country":"ES",
    "sg:address":"Rua Juan De Anges, 8",
    "sg:city":"Ourense",
    "sg:orig_category":"Lavado, Limpieza De Veh\u00cdculos",
    "sg:phone":"+34 988 25 29 53",
    "sg:postcode":"32002",
    "sg:province":"Ourense",
    "wof:name":"Alfonso Constantino Castro Somoza Y Otros S. Cv.",
    "wof:placetype":"venue"
},
  "geometry": {"coordinates":[-7.8757076263,42.3427619934],"type":"Point"}
}