{
  "type": "Feature",
  "properties": {
    "addr:full":"Avda Remedios (de Los), 6 Colmenar Viejo Madrid 28770",
    "addr:postcode":"28770",
    "addr:street":"Avda Remedios De Los",
    "iso:country":"ES",
    "sg:address":"Avda Remedios (de Los), 6",
    "sg:city":"Colmenar Viejo",
    "sg:orig_category":"Zapatos (al Por Menor)",
    "sg:phone":"+34 918 45 04 46",
    "sg:postcode":"28770",
    "sg:province":"Madrid",
    "wof:name":"Aparicio Vizcaino Miguel",
    "wof:placetype":"venue"
},
  "geometry": {"coordinates":[-3.769944191,40.6657943726],"type":"Point"}
}