{
  "type": "Feature",
  "properties": {
    "addr:full":"Pl Espanya (d'), 19 Santa Barbara Tarragona 43570",
    "addr:postcode":"43570",
    "addr:street":"Pl",
    "iso:country":"ES",
    "sg:address":"Pl Espanya (d'), 19",
    "sg:city":"Santa Barbara",
    "sg:orig_category":"Asociaciones Humanitarias, De Cooperaci\u00d3n, De Acci\u00d3n Social",
    "sg:phone":"+34 977 71 70 20",
    "sg:postcode":"43570",
    "sg:province":"Tarragona",
    "wof:name":"Associacio De Dones Planeres",
    "wof:placetype":"venue"
},
  "geometry": {"coordinates":[0.493837297,40.7161102295],"type":"Point"}
}