{
  "type": "Feature",
  "properties": {
    "iso:country":"ES",
    "sg:address":"Calle de Mayor, 26",
    "sg:city":"Arenas -areeta",
    "sg:orig_category":"Carnicer\u00cdas, Carnicer\u00cdas",
    "sg:phone":"+34 944 80 23 73",
    "sg:postcode":"48930",
    "sg:province":"Vizcaya",
    "wof:name":"Jaunene S.l.",
    "wof:placetype":"venue"
},
  "geometry": {"coordinates":[-3.0116980076,43.3265419006],"type":"Point"}
}