{
  "type": "Feature",
  "properties": {
    "addr:full":"Iglesia De Arriba, S/n Vega Asturias 33391",
    "addr:housenumber":"s / n",
    "addr:postcode":"33391",
    "addr:street":"Asturias",
    "iso:country":"ES",
    "sg:address":"Iglesia De Arriba, S/n",
    "sg:city":"Vega",
    "sg:orig_category":"M\u00c9dicos: Estomatolog\u00cda",
    "sg:phone":"+34 985 13 63 38",
    "sg:postcode":"33391",
    "sg:province":"Asturias",
    "wof:name":"Roces Quiros Celestino",
    "wof:placetype":"venue"
},
  "geometry": {"coordinates":[-5.6513209343,43.4914054871],"type":"Point"}
}