{
  "type": "Feature",
  "properties": {
    "iso:country":"ES",
    "sg:address":"Av Sant Jordi (de), 18",
    "sg:city":"Torredembarra",
    "sg:orig_category":"Chapister\u00cda",
    "sg:phone":"+34 977 64 37 56",
    "sg:postcode":"43830",
    "sg:province":"Tarragona",
    "wof:name":"Taller Planxisteria Guggi S.l.",
    "wof:placetype":"venue"
},
  "geometry": {"coordinates":[1.3969399929,41.1475105286],"type":"Point"}
}