{
  "type": "Feature",
  "properties": {
    "iso:country":"ES",
    "sg:address":"Calle de Circunde, 9",
    "sg:city":"Logro\u00f1o",
    "sg:orig_category":"Suministros Para Hoteles",
    "sg:phone":"+34 941 26 13 58",
    "sg:postcode":"26006",
    "sg:province":"La Rioja",
    "wof:name":"Hotel Hogar S.a.",
    "wof:placetype":"venue"
},
  "geometry": {"coordinates":[-2.4034461975,42.456237793],"type":"Point"}
}