{
  "type": "Feature",
  "properties": {
    "iso:country":"ES",
    "sg:address":"Calle de Ramiro De Maeztu, 6",
    "sg:city":"Santa Cruz De Tenerife",
    "sg:orig_category":"Zapatos (al Por Menor)",
    "sg:phone":"+34 922 20 17 05",
    "sg:postcode":"38007",
    "sg:province":"Santa Cruz De Tenerife",
    "wof:name":"Gonzalez Mendez Juan Antonio",
    "wof:placetype":"venue"
},
  "geometry": {"coordinates":[-16.2652835846,28.4581737518],"type":"Point"}
}