{
  "type": "Feature",
  "properties": {
    "addr:full":"Avgd Hispanitat, 1 Alzira Valencia 46600",
    "addr:housenumber":"1",
    "addr:postcode":"46600",
    "addr:street":"Hispanitat",
    "iso:country":"ES",
    "sg:address":"Avgd Hispanitat, 1",
    "sg:city":"Alzira",
    "sg:orig_category":"Partidos Pol\u00cdticos",
    "sg:phone":"+34 962 41 13 00",
    "sg:postcode":"46600",
    "sg:province":"Valencia",
    "wof:name":"Partido Socialista Obrero Espa\u00f1ol",
    "wof:placetype":"venue"
},
  "geometry": {"coordinates":[-0.4394710064,39.1491622925],"type":"Point"}
}