{
  "type": "Feature",
  "properties": {
    "iso:country":"ES",
    "sg:address":"Pl Lluis Perpinya, 28",
    "sg:city":"Granollers",
    "sg:orig_category":"Institutos De Belleza",
    "sg:phone":"+34 938 79 18 22",
    "sg:postcode":"08401",
    "sg:province":"Barcelona",
    "wof:name":"Granollers Sol S.c.p.",
    "wof:placetype":"venue"
},
  "geometry": {"coordinates":[2.2897269726,41.6091537476],"type":"Point"}
}