{
  "type": "Feature",
  "properties": {
    "addr:full":"Carr Guerrillero Romeu, 3 Quart Poblet Valencia 46930",
    "addr:housenumber":"3",
    "addr:postcode":"46930",
    "addr:street":"Carr Guerrillero Romeu;Poblet",
    "iso:country":"ES",
    "sg:address":"Carr Guerrillero Romeu, 3",
    "sg:city":"Quart Poblet",
    "sg:orig_category":"Alimentaci\u00d3n General (al Por Menor)",
    "sg:phone":"+34 961 54 79 68",
    "sg:postcode":"46930",
    "sg:province":"Valencia",
    "wof:name":"Lopez Lopez Maria",
    "wof:placetype":"venue"
},
  "geometry": {"coordinates":[-0.4463950098,39.4818878174],"type":"Point"}
}