{
  "type": "Feature",
  "properties": {
    "addr:full":"Calle de Cuenca, 2 Palacios De Goda \u00c1vila 05297",
    "addr:housenumber":"2",
    "addr:postcode":"05297",
    "addr:street":"Calle De Cuenca;A\u0301Vila",
    "iso:country":"ES",
    "sg:address":"Calle de Cuenca, 2",
    "sg:city":"Palacios De Goda",
    "sg:orig_category":"Transporte En General",
    "sg:phone":"+34 920 30 81 52",
    "sg:postcode":"05297",
    "sg:province":"\u00c1vila",
    "wof:name":"Llorente Romo Maria De Los Angeles",
    "wof:placetype":"venue"
},
  "geometry": {"coordinates":[-4.7841010094,41.1176338196],"type":"Point"}
}