{
  "type": "Feature",
  "properties": {
    "addr:full":"Plaz Juan Carlos I, 14 Puebla Calzada Badajoz 06490",
    "addr:housenumber":"14",
    "addr:postcode":"06490",
    "addr:street":"Plaz Juan Carlos I;Calzada Badajoz",
    "iso:country":"ES",
    "sg:address":"Plaz Juan Carlos I, 14",
    "sg:city":"Puebla Calzada",
    "sg:orig_category":"Edici\u00d3n De Diarios, Revistas, Boletines",
    "sg:phone":"+34 924 45 72 43",
    "sg:postcode":"06490",
    "sg:province":"Badajoz",
    "wof:name":"Ediciones Deneb S.l.",
    "wof:placetype":"venue"
},
  "geometry": {"coordinates":[-6.6236538887,38.8914833069],"type":"Point"}
}