{
  "type": "Feature",
  "properties": {
    "addr:full":"Avgd Sant Ignasi Loiola, 110 Badalona Barcelona 08912",
    "addr:housenumber":"110",
    "addr:postcode":"08912",
    "addr:street":"Loiola",
    "iso:country":"ES",
    "sg:address":"Avgd Sant Ignasi Loiola, 110",
    "sg:city":"Badalona",
    "sg:orig_category":"Peritos En C\u00c1lculo Inmobiliario, Industrial Y De Fondos De Comercio",
    "sg:phone":"+34 933 99 46 61",
    "sg:postcode":"08912",
    "sg:province":"Barcelona",
    "wof:name":"Salvat Assessors S.l.",
    "wof:placetype":"venue"
},
  "geometry": {"coordinates":[2.2455089092,41.4444770813],"type":"Point"}
}