{
  "type": "Feature",
  "properties": {
    "iso:country":"ES",
    "sg:address":"Avda Costa Del Sol, 14",
    "sg:city":"Almu\u00f1ecar",
    "sg:orig_category":"Albergues",
    "sg:phone":"+34 958 63 01 23",
    "sg:postcode":"18690",
    "sg:province":"Granada",
    "wof:name":"Rivas Guardia Francisco",
    "wof:placetype":"venue"
},
  "geometry": {"coordinates":[-3.6922318935,36.7360916138],"type":"Point"}
}