{
  "type": "Feature",
  "properties": {
    "addr:full":"Ctra Guixa, 15 Vic Barcelona 08500",
    "addr:housenumber":"15",
    "addr:postcode":"08500",
    "addr:street":"Ctra Guixa",
    "iso:country":"ES",
    "sg:address":"Ctra Guixa, 15",
    "sg:city":"Vic",
    "sg:orig_category":"Ropa Para Se\u00d1oras Y Caballeros (al Por Menor)",
    "sg:phone":"+34 938 85 52 63",
    "sg:postcode":"08500",
    "sg:province":"Barcelona",
    "wof:name":"Perez Cervera Jose",
    "wof:placetype":"venue"
},
  "geometry": {"coordinates":[2.2526490688,41.9242668152],"type":"Point"}
}