{
  "type": "Feature",
  "properties": {
    "iso:country":"ES",
    "sg:address":"Av Bisbe Llompart, 31",
    "sg:city":"Inca",
    "sg:orig_category":"M\u00c9dicos: Estomatolog\u00cda",
    "sg:phone":"+34 971 50 55 34",
    "sg:postcode":"07300",
    "sg:province":"Islas Baleares",
    "wof:name":"Bennasar Verger Catalina",
    "wof:placetype":"venue"
},
  "geometry": {"coordinates":[2.9086310863,39.7203025818],"type":"Point"}
}