{
  "type": "Feature",
  "properties": {
    "iso:country":"ES",
    "sg:address":"Plaz Vieja, 3",
    "sg:city":"Abaran",
    "sg:orig_category":"Farmacias",
    "sg:phone":"+34 968 77 00 37",
    "sg:postcode":"30550",
    "sg:province":"Murcia",
    "wof:name":"Farmacia Ruiz Gomez C.b.",
    "wof:placetype":"venue"
},
  "geometry": {"coordinates":[-1.4006530046,38.2030754089],"type":"Point"}
}