{
  "type": "Feature",
  "properties": {
    "iso:country":"ES",
    "sg:address":"Carrer de Llauradors, 13",
    "sg:city":"Campello",
    "sg:orig_category":"Empresarios",
    "sg:phone":"+34 965 63 02 17",
    "sg:postcode":"03560",
    "sg:province":"Alicante",
    "wof:name":"Pe\u00f1alver Bel Agustin",
    "wof:placetype":"venue"
},
  "geometry": {"coordinates":[-0.4039190114,38.4276199341],"type":"Point"}
}