{
  "type": "Feature",
  "properties": {
    "addr:full":"Calle de San Miguel, S/n Cervera Del Rio Alhama La Rioja 26520",
    "addr:housenumber":"s / n",
    "addr:postcode":"26520",
    "addr:street":"Calle De San Miguel;Alhama;Rioja",
    "iso:country":"ES",
    "sg:address":"Calle de San Miguel, S/n",
    "sg:city":"Cervera Del Rio Alhama",
    "sg:orig_category":"Centros De Educaci\u00d3n Especial",
    "sg:phone":"+34 941 19 81 56",
    "sg:postcode":"26520",
    "sg:province":"La Rioja",
    "wof:name":"Comunidad Autonoma De La Rioja",
    "wof:placetype":"venue"
},
  "geometry": {"coordinates":[-1.9519569874,42.0057830811],"type":"Point"}
}