{
  "type": "Feature",
  "properties": {
    "iso:country":"ES",
    "sg:address":"Calle de Guillermo De Osma, 3",
    "sg:city":"Madrid",
    "sg:orig_category":"Florister\u00cdas",
    "sg:phone":"+34 914 74 61 22",
    "sg:postcode":"28045",
    "sg:province":"Madrid",
    "wof:name":"Maurin Perez Maria Rosa",
    "wof:placetype":"venue"
},
  "geometry": {"coordinates":[-3.6954400539,40.3939361572],"type":"Point"}
}