{
  "type": "Feature",
  "properties": {
    "iso:country":"ES",
    "sg:address":"Plaz Maria Beneyto (escriptora), 5",
    "sg:city":"Valencia",
    "sg:orig_category":"Material Y Suministros Para Dentistas, Cirujanos",
    "sg:phone":"+34 963 15 21 30",
    "sg:postcode":"46008",
    "sg:province":"Valencia",
    "wof:name":"Proclival S.l.",
    "wof:placetype":"venue"
},
  "geometry": {"coordinates":[-0.3843440115,39.4763755798],"type":"Point"}
}