{
  "type": "Feature",
  "properties": {
    "addr:full":"Rua Manuel Belando, 14 Ferrol La Coru\u00f1a 15404",
    "addr:housenumber":"14",
    "addr:postcode":"15404",
    "addr:street":"Rua Manuel Belando;La Corun\u0303A",
    "iso:country":"ES",
    "sg:address":"Rua Manuel Belando, 14",
    "sg:city":"Ferrol",
    "sg:orig_category":"Relojer\u00cda (al Por Menor, Reparaci\u00d3n)",
    "sg:phone":"+34 981 31 24 22",
    "sg:postcode":"15404",
    "sg:province":"La Coru\u00f1a",
    "wof:name":"Dopico Prieto Alfredo",
    "wof:placetype":"venue"
},
  "geometry": {"coordinates":[-8.217250824,43.491569519],"type":"Point"}
}