{
  "type": "Feature",
  "properties": {
    "addr:full":"Calle de Cartagena, 3 Valencia Valencia 46018",
    "addr:housenumber":"3",
    "addr:postcode":"46018",
    "addr:street":"Calle De Cartagena",
    "iso:country":"ES",
    "sg:address":"Calle de Cartagena, 3",
    "sg:city":"Valencia",
    "sg:orig_category":"Comercio De Piezas De Recambio Y De Accesorios De Veh\u00cdculos, Veh\u00cdculos Industriales",
    "sg:phone":"+34 963 85 24 17",
    "sg:postcode":"46018",
    "sg:province":"Valencia",
    "wof:name":"Enrique Requena S. L.",
    "wof:placetype":"venue"
},
  "geometry": {"coordinates":[-0.3937009871,39.4706611633],"type":"Point"}
}