{
  "type": "Feature",
  "properties": {
    "addr:full":"Calle de Bando De La Huerta, 4 San Miguel Murcia 30008",
    "addr:housenumber":"4",
    "addr:postcode":"30008",
    "addr:street":"Calle De Bando De La Huerta",
    "iso:country":"ES",
    "sg:address":"Calle de Bando De La Huerta, 4",
    "sg:city":"San Miguel",
    "sg:orig_category":"M\u00c9dicos: Cardiolog\u00cda Y Afecciones Cardiovasculares",
    "sg:phone":"+34 968 23 64 62",
    "sg:postcode":"30008",
    "sg:province":"Murcia",
    "wof:name":"Sanchez Puerta C.b.",
    "wof:placetype":"venue"
},
  "geometry": {"coordinates":[-1.1298867464,37.9834747314],"type":"Point"}
}