{
  "type": "Feature",
  "properties": {
    "iso:country":"ES",
    "sg:address":"Mercat Carmel, S/n",
    "sg:city":"Barcelona",
    "sg:orig_category":"Ahumados Y Salazones",
    "sg:phone":"+34 933 57 56 49",
    "sg:postcode":"08032",
    "sg:province":"Barcelona",
    "wof:name":"Margeli Ayora Ignacio",
    "wof:placetype":"venue"
},
  "geometry": {"coordinates":[2.1578700542,41.4244384766],"type":"Point"}
}