{
  "type": "Feature",
  "properties": {
    "iso:country":"ES",
    "sg:address":"Pacios, 26",
    "sg:city":"Pacios",
    "sg:orig_category":"Promotores Constructores",
    "sg:phone":"+34 982 45 24 36",
    "sg:postcode":"27540",
    "sg:province":"Lugo",
    "wof:name":"Otero Aldao S.l.",
    "wof:placetype":"venue"
},
  "geometry": {"coordinates":[-7.3761467934,43.2584915161],"type":"Point"}
}