{
  "type": "Feature",
  "properties": {
    "addr:full":"Plaz Mancha, 3 Chinchilla Monte-aragon Albacete 02520",
    "addr:housenumber":"3",
    "addr:postcode":"02520",
    "addr:street":"Mancha;Monte-Aragon",
    "iso:country":"ES",
    "sg:address":"Plaz Mancha, 3",
    "sg:city":"Chinchilla Monte-aragon",
    "sg:orig_category":"Restaurantes",
    "sg:phone":"+34 967 26 04 36",
    "sg:postcode":"02520",
    "sg:province":"Albacete",
    "wof:name":"Dalimol S.l.",
    "wof:placetype":"venue"
},
  "geometry": {"coordinates":[-1.7232949734,38.9209251404],"type":"Point"}
}