{
  "type": "Feature",
  "properties": {
    "addr:full":"Av Verge Montserrat, 15 Prat Llobregat Barcelona 08820",
    "addr:housenumber":"15",
    "addr:postcode":"08820",
    "addr:street":"Av Verge Montserrat;Llobregat",
    "iso:country":"ES",
    "sg:address":"Av Verge Montserrat, 15",
    "sg:city":"Prat Llobregat",
    "sg:orig_category":"Venta, Alquiler De V\u00cddeo",
    "sg:phone":"+34 933 79 13 89",
    "sg:postcode":"08820",
    "sg:province":"Barcelona",
    "wof:name":"Vega Barros Dolores",
    "wof:placetype":"venue"
},
  "geometry": {"coordinates":[2.1022059917,41.3284072876],"type":"Point"}
}