{
  "type": "Feature",
  "properties": {
    "addr:full":"Calle de Reyes Magos, 3 Madrid Madrid 28009",
    "addr:housenumber":"3",
    "addr:postcode":"28009",
    "addr:street":"Calle De Reyes Magos",
    "iso:country":"ES",
    "sg:address":"Calle de Reyes Magos, 3",
    "sg:city":"Madrid",
    "sg:orig_category":"Asociaciones, Organismos Culturales Y Socioeducativos",
    "sg:phone":"+34 915 74 87 92",
    "sg:postcode":"28009",
    "sg:province":"Madrid",
    "wof:name":"Asociacion De Antiguos Alumnos",
    "wof:placetype":"venue"
},
  "geometry": {"coordinates":[-3.6742134094,40.4121665955],"type":"Point"}
}