{
  "type": "Feature",
  "properties": {
    "iso:country":"ES",
    "sg:address":"Avda Fernando Conde, 130",
    "sg:city":"Estrada",
    "sg:orig_category":"Chapister\u00cda",
    "sg:phone":"+34 986 57 05 02",
    "sg:postcode":"36680",
    "sg:province":"Pontevedra",
    "wof:name":"Brey Cami\u00f1a Maria Angeles",
    "wof:placetype":"venue"
},
  "geometry": {"coordinates":[-8.4762420654,42.6902542114],"type":"Point"}
}