{
  "type": "Feature",
  "properties": {
    "iso:country":"ES",
    "sg:address":"Avda Maritima, 130",
    "sg:city":"Santa Cruz Palma",
    "sg:orig_category":"Bazares, Art\u00cdculos De Limpieza Y De Cocina (al Por Menor)",
    "sg:phone":"+34 922 41 33 01",
    "sg:postcode":"38700",
    "sg:province":"Santa Cruz De Tenerife",
    "wof:name":"Almaturist S.l.",
    "wof:placetype":"venue"
},
  "geometry": {"coordinates":[-17.7628726959,28.6845798492],"type":"Point"}
}