{
  "type": "Feature",
  "properties": {
    "addr:full":"Calle de Uria, 2 Luarca Asturias 33700",
    "addr:housenumber":"2",
    "addr:postcode":"33700",
    "addr:street":"Calle De Uria",
    "iso:country":"ES",
    "sg:address":"Calle de Uria, 2",
    "sg:city":"Luarca",
    "sg:orig_category":"Loter\u00cda Y T\u00d3mbola",
    "sg:phone":"+34 985 47 07 12",
    "sg:postcode":"33700",
    "sg:province":"Asturias",
    "wof:name":"Perez Perez Jose",
    "wof:placetype":"venue"
},
  "geometry": {"coordinates":[-6.5352864265,43.5435752869],"type":"Point"}
}