{
  "type": "Feature",
  "properties": {
    "iso:country":"ES",
    "sg:address":"Carrer de Rec, 22",
    "sg:city":"Barcelona",
    "sg:orig_category":"Ropa Para Se\u00d1oras Y Caballeros (al Por Menor)",
    "sg:phone":"+34 933 19 07 56",
    "sg:postcode":"08003",
    "sg:province":"Barcelona",
    "wof:name":"Scazziotta  Paola Andrea",
    "wof:placetype":"venue"
},
  "geometry": {"coordinates":[2.1823680401,41.3855361938],"type":"Point"}
}