{
  "type": "Feature",
  "properties": {
    "addr:full":"Calle de Lisboa, 247 Sevilla Sevilla 41006",
    "addr:housenumber":"247",
    "addr:postcode":"41006",
    "addr:street":"Calle De Lisboa",
    "iso:country":"ES",
    "sg:address":"Calle de Lisboa, 247",
    "sg:city":"Sevilla",
    "sg:orig_category":"Concepci\u00d3n Y Realizaci\u00d3n De Maquetas Profesionales Y Prototipos",
    "sg:phone":"+34 954 64 58 31",
    "sg:postcode":"41006",
    "sg:province":"Sevilla",
    "wof:name":"Sanchez Sacristan Fernando",
    "wof:placetype":"venue"
},
  "geometry": {"coordinates":[-5.953081131,37.3700218201],"type":"Point"}
}