{
  "type": "Feature",
  "properties": {
    "addr:full":"Cmn. La Sabina, S/n Valera Abajo Cuenca 16120",
    "addr:housenumber":"s / n",
    "addr:postcode":"16120",
    "addr:street":"Cmn. La Sabina;Abajo",
    "iso:country":"ES",
    "sg:address":"Cmn. La Sabina, S/n",
    "sg:city":"Valera Abajo",
    "sg:orig_category":"Empresas De Carpinter\u00cda De Madera",
    "sg:phone":"+34 969 20 81 06",
    "sg:postcode":"16120",
    "sg:province":"Cuenca",
    "wof:name":"Carpinteria Hermanos Moya S.l.",
    "wof:placetype":"venue"
},
  "geometry": {"coordinates":[-2.1576440334,39.7695198059],"type":"Point"}
}