{
  "type": "Feature",
  "properties": {
    "iso:country":"ES",
    "sg:address":"Sta Teresa Jornet, S/n",
    "sg:city":"Merida",
    "sg:orig_category":"Autob\u00das (explotaci\u00d3n Y Servicios De)",
    "sg:phone":"+34 924 33 06 84",
    "sg:postcode":"06800",
    "sg:province":"Badajoz",
    "wof:name":"Lusitania Bus S.a.l.",
    "wof:placetype":"venue"
},
  "geometry": {"coordinates":[-6.3415088654,38.911026001],"type":"Point"}
}