{
  "type": "Feature",
  "properties": {
    "iso:country":"ES",
    "sg:address":"Calle de Bailen, 4",
    "sg:city":"Valladolid",
    "sg:orig_category":"M\u00c9dicos: Neumolog\u00cda",
    "sg:phone":"+34 983 30 91 79",
    "sg:postcode":"47004",
    "sg:province":"Valladolid",
    "wof:name":"Puyo Gil Miguel Luis",
    "wof:placetype":"venue"
},
  "geometry": {"coordinates":[-4.7254066467,41.6460380554],"type":"Point"}
}