{
  "type": "Feature",
  "properties": {
    "iso:country":"ES",
    "sg:address":"Rua Dr. Carlos Colmeiro Laforet, 5",
    "sg:city":"Vigo",
    "sg:orig_category":"Art\u00cdculos De Regalo (al Por Menor)",
    "sg:phone":"+34 986 43 08 77",
    "sg:postcode":"36203",
    "sg:province":"Pontevedra",
    "wof:name":"Exclusivas Adeley S.l.",
    "wof:placetype":"venue"
},
  "geometry": {"coordinates":[-8.7187366486,42.2339248657],"type":"Point"}
}