{
  "type": "Feature",
  "properties": {
    "iso:country":"ES",
    "sg:address":"Carrer de Sant Rafael, 22",
    "sg:city":"Pego",
    "sg:orig_category":"Cooperativas Agr\u00cdcolas",
    "sg:phone":"+34 966 40 05 20",
    "sg:postcode":"03780",
    "sg:province":"Alicante",
    "wof:name":"Cooperativa Agricola De Pego Coop. V.",
    "wof:placetype":"venue"
},
  "geometry": {"coordinates":[-0.1140749976,38.8409385681],"type":"Point"}
}