{
  "type": "Feature",
  "properties": {
    "addr:full":"Calle de Republica Argentina, 6 Alcala Henares Madrid 28805",
    "addr:housenumber":"6",
    "addr:postcode":"28805",
    "addr:street":"Calle De Republica Argentina",
    "iso:country":"ES",
    "sg:address":"Calle de Republica Argentina, 6",
    "sg:city":"Alcala Henares",
    "sg:orig_category":"Asesor\u00cda Fiscal Y Jur\u00cddica",
    "sg:phone":"+34 918 83 11 62",
    "sg:postcode":"28805",
    "sg:province":"Madrid",
    "wof:name":"Bav Asesores Y Consultores S.l.",
    "wof:placetype":"venue"
},
  "geometry": {"coordinates":[-3.3631000519,40.4861030579],"type":"Point"}
}