{
  "type": "Feature",
  "properties": {
    "iso:country":"ES",
    "sg:address":"Dormitaleria, 5",
    "sg:city":"Iru\u00f1a",
    "sg:orig_category":"Cine (producci\u00d3n, Realizaci\u00d3n)",
    "sg:phone":"+34 948 22 95 17",
    "sg:postcode":"31001",
    "sg:province":"Navarra",
    "wof:name":"Ederbide S.l.",
    "wof:placetype":"venue"
},
  "geometry": {"coordinates":[-1.6411019564,42.8192138672],"type":"Point"}
}