{
  "type": "Feature",
  "properties": {
    "iso:country":"ES",
    "sg:address":"Calle de Fidalgo, 9",
    "sg:city":"Valencia",
    "sg:classifiers":[
        {
            "category":"Personal",
            "subcategory":"Barber",
            "type":"Services"
        }
    ],
    "sg:phone":"+34 963 40 80 76",
    "sg:postcode":"46009",
    "sg:province":"Valencia",
    "sg:tags":[
        "caballeros",
        "de",
        "peluqueros"
    ],
    "wof:name":"Cidalgo Peluqueria Hombres C B",
    "wof:placetype":"venue"
},
  "geometry": {"coordinates":[-0.3872080147,39.4872627258],"type":"Point"}
}