{
  "type": "Feature",
  "properties": {
    "addr:full":"C/ Alfonso Xii, 5 Elche Alicante 03203",
    "addr:housenumber":"5",
    "addr:postcode":"03203",
    "addr:street":"C / Alfonso Xii",
    "iso:country":"ES",
    "sg:address":"C/ Alfonso Xii, 5",
    "sg:city":"Elche",
    "sg:orig_category":"Electrodom\u00c9sticos (al Por Menor)",
    "sg:phone":"+34 966 61 05 99",
    "sg:postcode":"03203",
    "sg:province":"Alicante",
    "wof:name":"Electroprogreso S.l.",
    "wof:placetype":"venue"
},
  "geometry": {"coordinates":[-0.6990659833,38.264881134],"type":"Point"}
}