{
  "type": "Feature",
  "properties": {
    "addr:full":"Uno De Mayo, 31 Massamagrell Valencia 46130",
    "addr:housenumber":"31",
    "addr:postcode":"46130",
    "addr:street":"Mayo",
    "iso:country":"ES",
    "sg:address":"Uno De Mayo, 31",
    "sg:city":"Massamagrell",
    "sg:orig_category":"Cl\u00cdnicas M\u00c9dicas",
    "sg:phone":"+34 961 45 21 90",
    "sg:postcode":"46130",
    "sg:province":"Valencia",
    "wof:name":"Experior S.l.",
    "wof:placetype":"venue"
},
  "geometry": {"coordinates":[-0.3329139948,39.5671310425],"type":"Point"}
}