{
  "type": "Feature",
  "properties": {
    "iso:country":"ES",
    "sg:address":"Hort De Soriano, 16",
    "sg:city":"P.i. Masia Del Juez",
    "sg:orig_category":"Fabricaci\u00d3n De Moldes Y Modelos",
    "sg:phone":"+34 961 58 81 56",
    "sg:postcode":"46900",
    "sg:province":"Valencia",
    "wof:name":"Moldes Matrimol S.l.",
    "wof:placetype":"venue"
},
  "geometry": {"coordinates":[-0.4623290002,39.441619873],"type":"Point"}
}