{
  "type": "Feature",
  "properties": {
    "addr:full":"Calle de Jorge Juan, 84 Madrid Madrid 28009",
    "addr:housenumber":"84",
    "addr:postcode":"madrid;28009",
    "addr:street":"Calle De Jorge Juan",
    "iso:country":"ES",
    "sg:address":"Calle de Jorge Juan, 84",
    "sg:city":"Madrid",
    "sg:orig_category":"M\u00c9dicos: Estomatolog\u00cda",
    "sg:phone":"+34 915 76 63 43",
    "sg:postcode":"28009",
    "sg:province":"Madrid",
    "wof:name":"Canals Badia Cristina",
    "wof:placetype":"venue"
},
  "geometry": {"coordinates":[-3.6750609875,40.4231948853],"type":"Point"}
}