{
  "type": "Feature",
  "properties": {
    "addr:full":"Calle de Santo Domingo De La Calzada, 4 Arnedo La Rioja 26580",
    "addr:housenumber":"4",
    "addr:postcode":"26580",
    "addr:street":"Calle De Santo Domingo De La Calzada;Rioja",
    "iso:country":"ES",
    "sg:address":"Calle de Santo Domingo De La Calzada, 4",
    "sg:city":"Arnedo",
    "sg:orig_category":"Bancos",
    "sg:phone":"+34 941 38 11 62",
    "sg:postcode":"26580",
    "sg:province":"La Rioja",
    "sg:website":"www.bancovasconia.com",
    "wof:name":"Banco De Vasconia",
    "wof:placetype":"venue"
},
  "geometry": {"coordinates":[-2.1003160477,42.2262840271],"type":"Point"}
}