{
  "type": "Feature",
  "properties": {
    "iso:country":"ES",
    "sg:address":"Avda Fueros, 11",
    "sg:city":"Madrid",
    "sg:orig_category":"Poller\u00cda Y Caza (al Por Menor)",
    "sg:phone":"+34 917 92 37 36",
    "sg:postcode":"28041",
    "sg:province":"Madrid",
    "wof:name":"Sanz Sanz Alicia",
    "wof:placetype":"venue"
},
  "geometry": {"coordinates":[-3.6907229424,40.3703651428],"type":"Point"}
}