{
  "type": "Feature",
  "properties": {
    "addr:full":"Carrer de Rossello, 37 Barcelona Barcelona 08029",
    "addr:housenumber":"37",
    "addr:postcode":"08029",
    "addr:street":"Carrer De Rossello",
    "iso:country":"ES",
    "sg:address":"Carrer de Rossello, 37",
    "sg:city":"Barcelona",
    "sg:orig_category":"Farmacias",
    "sg:phone":"+34 934 30 77 25",
    "sg:postcode":"08029",
    "sg:province":"Barcelona",
    "wof:name":"Farmacia Varela S.c.p.",
    "wof:placetype":"venue"
},
  "geometry": {"coordinates":[2.1444129944,41.3837623596],"type":"Point"}
}