{
  "type": "Feature",
  "properties": {
    "addr:full":"Ramon Y Cajal, 32 Traiguera Castell\u00f3n 12330",
    "addr:housenumber":"32",
    "addr:postcode":"12330",
    "addr:street":"Ramon Y Cajal;Castello\u0301N",
    "iso:country":"ES",
    "sg:address":"Ramon Y Cajal, 32",
    "sg:city":"Traiguera",
    "sg:orig_category":"Maquinaria Para Industrias Diversas",
    "sg:phone":"+34 964 49 51 87",
    "sg:postcode":"12330",
    "sg:province":"Castell\u00f3n",
    "wof:name":"Gauxachs Cervera Rogelia",
    "wof:placetype":"venue"
},
  "geometry": {"coordinates":[0.2872470021,40.523815155],"type":"Point"}
}