{
  "type": "Feature",
  "properties": {
    "addr:full":"Gta Quevedo, 7 Madrid Madrid 28015",
    "addr:housenumber":"7",
    "addr:postcode":"madrid;28015",
    "addr:street":"Gta Quevedo",
    "iso:country":"ES",
    "sg:address":"Gta Quevedo, 7",
    "sg:city":"Madrid",
    "sg:orig_category":"Abogados",
    "sg:phone":"+34 914 11 48 43",
    "sg:postcode":"28015",
    "sg:province":"Madrid",
    "sg:website":"www.ilsabogados.com",
    "wof:name":"Garcia-carrasco Garcia Amador",
    "wof:placetype":"venue"
},
  "geometry": {"coordinates":[-3.7039980888,40.4336967468],"type":"Point"}
}