{
  "type": "Feature",
  "properties": {
    "addr:full":"Avda Coru\u00d1a (da), 100 Lugo Lugo 27003",
    "addr:housenumber":"100",
    "addr:postcode":"27003",
    "addr:street":"Avda Corun\u0303A Da",
    "iso:country":"ES",
    "sg:address":"Avda Coru\u00d1a (da), 100",
    "sg:city":"Lugo",
    "sg:orig_category":"Peluquer\u00cdas",
    "sg:phone":"+34 982 25 43 36",
    "sg:postcode":"27003",
    "sg:province":"Lugo",
    "wof:name":"Syret-spa S.l.",
    "wof:placetype":"venue"
},
  "geometry": {"coordinates":[-7.5608611107,43.0179634094],"type":"Point"}
}