{
  "type": "Feature",
  "properties": {
    "iso:country":"ES",
    "sg:address":"Calle de San Vicente Paul, 3",
    "sg:city":"Sobradiel",
    "sg:orig_category":"Asilos De Ancianos. Centros Privados",
    "sg:phone":"+34 976 13 92 95",
    "sg:postcode":"50629",
    "sg:province":"Zaragoza",
    "wof:name":"Hijas De La Caridad De San Vicente Paul",
    "wof:placetype":"venue"
},
  "geometry": {"coordinates":[-1.0388139486,41.7388267517],"type":"Point"}
}