{
  "type": "Feature",
  "properties": {
    "iso:country":"ES",
    "sg:address":"Calle de Hispanidad, 7",
    "sg:city":"Pto. Rosario",
    "sg:orig_category":"Loter\u00cda Y T\u00d3mbola",
    "sg:phone":"+34 928 53 17 05",
    "sg:postcode":"35600",
    "sg:province":"Las Palmas",
    "wof:name":"Alonso Patallo Valeron Maria Del Carmen",
    "wof:placetype":"venue"
},
  "geometry": {"coordinates":[-13.8564195633,28.5005664825],"type":"Point"}
}