{
  "type": "Feature",
  "properties": {
    "iso:country":"ES",
    "sg:address":"Calle de Maestro Palau, 2",
    "sg:city":"Valencia",
    "sg:orig_category":"Peluqueros: De Se\u00d1oras",
    "sg:phone":"+34 963 91 52 98",
    "sg:postcode":"46008",
    "sg:province":"Valencia",
    "wof:name":"De Blas Sabino Amparo",
    "wof:placetype":"venue"
},
  "geometry": {"coordinates":[-0.3842310011,39.4716644287],"type":"Point"}
}