{
  "type": "Feature",
  "properties": {
    "iso:country":"ES",
    "sg:address":"Ctra Barcelona, 138",
    "sg:city":"Sabadell",
    "sg:orig_category":"Sociedades, Compa\u00d1\u00cdas Aseguradoras",
    "sg:phone":"+34 937 12 20 42",
    "sg:postcode":"08205",
    "sg:province":"Barcelona",
    "wof:name":"Pujals I Associats S.l.",
    "wof:placetype":"venue"
},
  "geometry": {"coordinates":[2.1054399014,41.5408782959],"type":"Point"}
}