{
  "type": "Feature",
  "properties": {
    "iso:country":"ES",
    "sg:address":"Rio Guadalevin (pi El Fuerte), S/n",
    "sg:city":"Ronda",
    "sg:orig_category":"Pompas F\u00danebres, Inhumaciones Y Cremaciones",
    "sg:phone":"+34 952 87 57 36",
    "sg:postcode":"29400",
    "sg:province":"M\u00e1laga",
    "wof:name":"Gestiones Ronde\u00f1as S.l.",
    "wof:placetype":"venue"
},
  "geometry": {"coordinates":[-5.1619439125,36.7519760132],"type":"Point"}
}