{
  "type": "Feature",
  "properties": {
    "iso:country":"ES",
    "sg:address":"Carrer de Gabriel Miro, 23",
    "sg:city":"Ondara",
    "sg:orig_category":"Arquitectos",
    "sg:phone":"+34 965 76 72 41",
    "sg:postcode":"03760",
    "sg:province":"Alicante",
    "wof:name":"Gaggio Fieschi Edith",
    "wof:placetype":"venue"
},
  "geometry": {"coordinates":[0.0239560008,38.8264350891],"type":"Point"}
}