{
  "type": "Feature",
  "properties": {
    "iso:country":"ES",
    "sg:address":"C/ Ciutat De Cartagena, 26",
    "sg:city":"Paterna",
    "sg:orig_category":"Fabricaci\u00d3n De Etiquetas",
    "sg:phone":"+34 961 32 30 13",
    "sg:postcode":"46988",
    "sg:province":"Valencia",
    "sg:website":"www.varmys.com",
    "wof:name":"Varmys S. A.",
    "wof:placetype":"venue"
},
  "geometry": {"coordinates":[-0.4709019959,39.5104484558],"type":"Point"}
}