{
  "type": "Feature",
  "properties": {
    "addr:full":"Calle de Rio Marches, 70 Poligono Sta M. De Benquerencia Toledo 45007",
    "addr:housenumber":"70 poligono",
    "addr:postcode":"45007",
    "addr:street":"Calle De Rio Marches;Sta M. De Benquerencia",
    "iso:country":"ES",
    "sg:address":"Calle de Rio Marches, 70",
    "sg:city":"Poligono Sta M. De Benquerencia",
    "sg:orig_category":"Autob\u00das (explotaci\u00d3n Y Servicios De)",
    "sg:phone":"+34 925 24 05 83",
    "sg:postcode":"45007",
    "sg:province":"Toledo",
    "wof:name":"Rubicar Tours S.a.",
    "wof:placetype":"venue"
},
  "geometry": {"coordinates":[-3.9474089146,39.8690643311],"type":"Point"}
}