{
  "type": "Feature",
  "properties": {
    "addr:full":"Avda Requejo, 8 Zamora Zamora 49012",
    "addr:housenumber":"8",
    "addr:postcode":"49012",
    "addr:street":"Avda Requejo",
    "iso:country":"ES",
    "sg:address":"Avda Requejo, 8",
    "sg:city":"Zamora",
    "sg:orig_category":"M\u00c9dicos: Estomatolog\u00cda",
    "sg:phone":"+34 980 67 08 23",
    "sg:postcode":"49012",
    "sg:province":"Zamora",
    "wof:name":"Rio Rodriguez Maria Del Carmen Del",
    "wof:placetype":"venue"
},
  "geometry": {"coordinates":[-5.7366728783,41.5099372864],"type":"Point"}
}