{
  "type": "Feature",
  "properties": {
    "addr:full":"Avda America, 6 Madrid Madrid 28028",
    "addr:housenumber":"6",
    "addr:postcode":"28028",
    "addr:street":"Avda America",
    "iso:country":"ES",
    "sg:address":"Avda America, 6",
    "sg:city":"Madrid",
    "sg:orig_category":"Fabricaci\u00d3n De Mantequilla (al Por Mayor)",
    "sg:phone":"+34 913 55 77 00",
    "sg:postcode":"28028",
    "sg:province":"Madrid",
    "wof:name":"Martin Hernandez Juan Jose",
    "wof:placetype":"venue"
},
  "geometry": {"coordinates":[-3.6763820648,40.4377403259],"type":"Point"}
}