{
  "type": "Feature",
  "properties": {
    "iso:country":"ES",
    "sg:address":"Calle de Domingo J Navarro, 5",
    "sg:city":"Palmas De Gran Canaria",
    "sg:orig_category":"Molduras, Junquillos, Listones Y Molduras Perforadas",
    "sg:phone":"+34 928 37 12 28",
    "sg:postcode":"35002",
    "sg:province":"Las Palmas",
    "wof:name":"Cruz Martinez Segundo",
    "wof:placetype":"venue"
},
  "geometry": {"coordinates":[-15.4179410934,28.1071414948],"type":"Point"}
}