{
  "type": "Feature",
  "properties": {
    "iso:country":"ES",
    "sg:address":"Avda Padre Mendez, S/n",
    "sg:city":"Almeria",
    "sg:orig_category":"Refiner\u00cdas De Petr\u00d3leo",
    "sg:phone":"+34 950 22 39 91",
    "sg:postcode":"04006",
    "sg:province":"Almer\u00eda",
    "wof:name":"Repsol Ypf S.a.",
    "wof:placetype":"venue"
},
  "geometry": {"coordinates":[-2.4512989521,36.8398551941],"type":"Point"}
}