{
  "type": "Feature",
  "properties": {
    "addr:full":"Avda Julio Arenillas, 38 Navalperal Pinares \u00c1vila 05240",
    "addr:housenumber":"38",
    "addr:postcode":"05240",
    "addr:street":"Avda Julio Arenillas;A\u0301Vila",
    "iso:country":"ES",
    "sg:address":"Avda Julio Arenillas, 38",
    "sg:city":"Navalperal Pinares",
    "sg:orig_category":"Doctores En Medicina",
    "sg:phone":"+34 918 98 05 95",
    "sg:postcode":"05240",
    "sg:province":"\u00c1vila",
    "wof:name":"Yague Nieto Maria Victoria",
    "wof:placetype":"venue"
},
  "geometry": {"coordinates":[-4.4119229317,40.591545105],"type":"Point"}
}