{
  "type": "Feature",
  "properties": {
    "iso:country":"ES",
    "sg:address":"Carrer de Santa Coloma, 86",
    "sg:city":"Barcelona",
    "sg:orig_category":"Papeler\u00cdas: Art\u00cdculos (al Por Mayor)",
    "sg:phone":"+34 933 45 02 08",
    "sg:postcode":"08030",
    "sg:province":"Barcelona",
    "wof:name":"Andreu Figueras S.a.",
    "wof:placetype":"venue"
},
  "geometry": {"coordinates":[2.1967408657,41.4473953247],"type":"Point"}
}