{
  "type": "Feature",
  "properties": {
    "addr:full":"Eras, 1 Zagra Granada 18311",
    "addr:housenumber":"1",
    "addr:postcode":"18311",
    "addr:street":"Eras",
    "iso:country":"ES",
    "sg:address":"Eras, 1",
    "sg:city":"Zagra",
    "sg:orig_category":"Iglesia Cat\u00d3lica",
    "sg:phone":"+34 958 31 40 36",
    "sg:postcode":"18311",
    "sg:province":"Granada",
    "wof:name":"Sede Provincial De Madrid Hijas De S Jose Provincia De Castilla",
    "wof:placetype":"venue"
},
  "geometry": {"coordinates":[-4.1681790352,37.253276825],"type":"Point"}
}