{
  "type": "Feature",
  "properties": {
    "iso:country":"ES",
    "sg:address":"Avda Mallorca, 12",
    "sg:city":"Matas-pinar-monte Rozas",
    "sg:orig_category":"Empresas De Labores Complejas De Carga Y Descarga, Montaje Con Elevadores",
    "sg:phone":"+34 916 37 12 72",
    "sg:postcode":"28290",
    "sg:province":"Madrid",
    "wof:name":"Sociedad Espa\u00f1ola De Obras, Trabajos Submarinos Y Maritimos S.a",
    "wof:placetype":"venue"
},
  "geometry": {"coordinates":[-3.8985788822,40.5563697815],"type":"Point"}
}