{
  "type": "Feature",
  "properties": {
    "iso:country":"ES",
    "sg:address":"Ctra Canal, S/n",
    "sg:city":"Moraleda Zafayona",
    "sg:orig_category":"Estancos",
    "sg:phone":"+34 958 44 31 38",
    "sg:postcode":"18370",
    "sg:province":"Granada",
    "wof:name":"Garballo Ordo\u00f1ez Rafael",
    "wof:placetype":"venue"
},
  "geometry": {"coordinates":[-3.9638440609,37.1681404114],"type":"Point"}
}