{
  "type": "Feature",
  "properties": {
    "addr:full":"Plaz Pau Casals (de), 6 Partija-santa Monica Madrid 28529",
    "addr:postcode":"28529",
    "iso:country":"ES",
    "sg:address":"Plaz Pau Casals (de), 6",
    "sg:city":"Partija-santa Monica",
    "sg:orig_category":"Peluqueros: De Se\u00d1oras",
    "sg:phone":"+34 913 01 20 92",
    "sg:postcode":"28529",
    "sg:province":"Madrid",
    "wof:name":"Utrilla Esteo Carmen",
    "wof:placetype":"venue"
},
  "geometry": {"coordinates":[-3.5102670193,40.314289093],"type":"Point"}
}