{
  "type": "Feature",
  "properties": {
    "addr:full":"Rua Cabeza De Manzaneda, 2 Ourense Ourense 32005",
    "addr:housenumber":"2",
    "addr:postcode":"32005",
    "addr:street":"Rua Cabeza De Manzaneda",
    "iso:country":"ES",
    "sg:address":"Rua Cabeza De Manzaneda, 2",
    "sg:city":"Ourense",
    "sg:orig_category":"Reposter\u00cdas",
    "sg:phone":"+34 988 22 25 62",
    "sg:postcode":"32005",
    "sg:province":"Ourense",
    "wof:name":"Panaderia Sabucedo S.l.",
    "wof:placetype":"venue"
},
  "geometry": {"coordinates":[-7.8619508743,42.3355445862],"type":"Point"}
}