{
  "type": "Feature",
  "properties": {
    "addr:full":"Plaz Angel, 1 Salamanca Salamanca 37001",
    "addr:housenumber":"1",
    "addr:postcode":"37001",
    "addr:street":"Angel",
    "iso:country":"ES",
    "sg:address":"Plaz Angel, 1",
    "sg:city":"Salamanca",
    "sg:orig_category":"M\u00c9dicos: Cirug\u00cda Urol\u00d3gica",
    "sg:phone":"+34 923 26 63 64",
    "sg:postcode":"37001",
    "sg:province":"Salamanca",
    "wof:name":"Diaz Alferez Francisco",
    "wof:placetype":"venue"
},
  "geometry": {"coordinates":[-5.6627931595,40.9641647339],"type":"Point"}
}