{
  "type": "Feature",
  "properties": {
    "iso:country":"ES",
    "sg:address":"Carrer de Rubio I Ors, 199",
    "sg:city":"Cornella Llobregat",
    "sg:orig_category":"Sociedades, Compa\u00d1\u00cdas Aseguradoras",
    "sg:phone":"+34 933 77 77 92",
    "sg:postcode":"08940",
    "sg:province":"Barcelona",
    "wof:name":"La Preventiva S.a.",
    "wof:placetype":"venue"
},
  "geometry": {"coordinates":[2.0748419762,41.3529014587],"type":"Point"}
}