{
  "type": "Feature",
  "properties": {
    "iso:country":"ES",
    "sg:address":"Rbla Paisos Catalans (dels), 73",
    "sg:city":"Mas Rampinyo",
    "sg:orig_category":"Alquiler De V\u00cddeo",
    "sg:phone":"+34 935 65 10 66",
    "sg:postcode":"08110",
    "sg:province":"Barcelona",
    "wof:name":"Contreras Ramirez Jose",
    "wof:placetype":"venue"
},
  "geometry": {"coordinates":[2.1817660332,41.4890899658],"type":"Point"}
}