{
  "type": "Feature",
  "properties": {
    "iso:country":"ES",
    "sg:address":"G.v. Corts Catalanes, 1092",
    "sg:city":"Barcelona",
    "sg:orig_category":"Cer\u00c1micas: Material Y Suministros",
    "sg:phone":"+34 933 08 76 54",
    "sg:postcode":"08020",
    "sg:province":"Barcelona",
    "wof:name":"Galindo Gibbon David Ignacio",
    "wof:placetype":"venue"
},
  "geometry": {"coordinates":[2.203318119,41.4151649475],"type":"Point"}
}