{
  "type": "Feature",
  "properties": {
    "addr:full":"Calle de Doctor Carracido, 31 Almeria Almer\u00eda 04005",
    "addr:housenumber":"31",
    "addr:postcode":"04005",
    "addr:street":"Calle De Doctor Carracido",
    "iso:country":"ES",
    "sg:address":"Calle de Doctor Carracido, 31",
    "sg:city":"Almeria",
    "sg:orig_category":"Casas Con Estructura De Madera",
    "sg:phone":"+34 950 22 88 95",
    "sg:postcode":"04005",
    "sg:province":"Almer\u00eda",
    "sg:website":"www.andaluzadebungalows.com",
    "wof:name":"Andaluza De Bungalows S.l",
    "wof:placetype":"venue"
},
  "geometry": {"coordinates":[-2.4538838863,36.8409690857],"type":"Point"}
}