{
  "type": "Feature",
  "properties": {
    "addr:full":"Calle de Florencia, 6 Bahia De Javea Alicante 03730",
    "addr:housenumber":"6",
    "addr:postcode":"03730",
    "addr:street":"Calle De Florencia;Bahia De Javea Alicante",
    "iso:country":"ES",
    "sg:address":"Calle de Florencia, 6",
    "sg:city":"Bahia De Javea",
    "sg:orig_category":"Librer\u00cdas",
    "sg:phone":"+34 966 46 24 51",
    "sg:postcode":"03730",
    "sg:province":"Alicante",
    "wof:name":"A.machado Libros",
    "wof:placetype":"venue"
},
  "geometry": {"coordinates":[0.1663361043,38.7888031006],"type":"Point"}
}