{
  "type": "Feature",
  "properties": {
    "iso:country":"ES",
    "sg:address":"Las Lomas, 82",
    "sg:city":"Valdelafuente",
    "sg:orig_category":"Empresarios",
    "sg:phone":"+34 987 25 27 54",
    "sg:postcode":"24227",
    "sg:province":"Le\u00f3n",
    "wof:name":"Garcia Gonzalez Eduardo",
    "wof:placetype":"venue"
},
  "geometry": {"coordinates":[-5.5330891609,42.5957946777],"type":"Point"}
}