{
  "type": "Feature",
  "properties": {
    "addr:full":"Calle de Robledillo, S/n Carde\u00f1a C\u00f3rdoba 14445",
    "addr:housenumber":"s / n",
    "addr:postcode":"14445",
    "addr:street":"Calle De Robledillo;Co\u0301Rdoba",
    "iso:country":"ES",
    "sg:address":"Calle de Robledillo, S/n",
    "sg:city":"Carde\u00f1a",
    "sg:orig_category":"Empresas De Electricidad En General",
    "sg:phone":"+34 957 17 41 74",
    "sg:postcode":"14445",
    "sg:province":"C\u00f3rdoba",
    "wof:name":"Empresa Electrica Martin Silva Pozo S.l.",
    "wof:placetype":"venue"
},
  "geometry": {"coordinates":[-4.3233571053,38.2727775574],"type":"Point"}
}