{
  "type": "Feature",
  "properties": {
    "iso:country":"ES",
    "sg:address":"Carr Havana, L', 8",
    "sg:city":"Vilanova I La Geltru",
    "sg:orig_category":"Artesan\u00cda",
    "sg:phone":"+34 938 93 03 51",
    "sg:postcode":"08800",
    "sg:province":"Barcelona",
    "sg:website":"www.intermonosfam.org",
    "wof:name":"Fundacio Intermon",
    "wof:placetype":"venue"
},
  "geometry": {"coordinates":[1.724421978,41.2213134766],"type":"Point"}
}