{
  "type": "Feature",
  "properties": {
    "iso:country":"ES",
    "sg:address":"Av J.a.clave, 30",
    "sg:city":"Mao",
    "sg:orig_category":"Transportes Por Carretera: Lotes Completos, Mercanc\u00cdas Diversas",
    "sg:phone":"+34 971 36 90 28",
    "sg:postcode":"07702",
    "sg:province":"Islas Baleares",
    "wof:name":"Hiper Manacor S.a.",
    "wof:placetype":"venue"
},
  "geometry": {"coordinates":[4.265625,39.8903694153],"type":"Point"}
}