{
  "type": "Feature",
  "properties": {
    "addr:full":"Pla\u00c7 Ribera (de La), 1 Algemesi Valencia 46680",
    "addr:postcode":"46680",
    "addr:street":"Ribera;La 1",
    "iso:country":"ES",
    "sg:address":"Pla\u00c7 Ribera (de La), 1",
    "sg:city":"Algemesi",
    "sg:orig_category":"Sociedades, Compa\u00d1\u00cdas Aseguradoras",
    "sg:phone":"+34 962 42 10 79",
    "sg:postcode":"46680",
    "sg:province":"Valencia",
    "wof:name":"Lopez Talens Joaquin",
    "wof:placetype":"venue"
},
  "geometry": {"coordinates":[-0.4313729107,39.2159690857],"type":"Point"}
}