{
  "type": "Feature",
  "properties": {
    "iso:country":"ES",
    "sg:address":"Carrer de Pere Des Bosch, 6",
    "sg:city":"Cabrera Mar",
    "sg:orig_category":"Deportes N\u00c1uticos, Acu\u00c1ticos Y Subacu\u00c1ticos: Art\u00cdculos Y Equipo (al Por Menor)",
    "sg:phone":"+34 937 50 05 82",
    "sg:postcode":"08349",
    "sg:province":"Barcelona",
    "wof:name":"Santana Race Group S.l.",
    "wof:placetype":"venue"
},
  "geometry": {"coordinates":[2.3953330517,41.5282669067],"type":"Point"}
}