{
  "type": "Feature",
  "properties": {
    "iso:country":"ES",
    "sg:address":"Barr Cinca (del), 16",
    "sg:city":"Grado",
    "sg:orig_category":"Hoteles",
    "sg:phone":"+34 974 30 40 35",
    "sg:postcode":"22390",
    "sg:province":"Huesca",
    "wof:name":"Las Acacias Del Cinca S.l.",
    "wof:placetype":"venue"
},
  "geometry": {"coordinates":[0.2227389961,42.1511497498],"type":"Point"}
}