{
  "type": "Feature",
  "properties": {
    "iso:country":"ES",
    "sg:address":"Carrer de Salvador Casas, 13",
    "sg:city":"Olesa Montserrat",
    "sg:orig_category":"Florister\u00cdas",
    "sg:phone":"+34 937 75 70 11",
    "sg:postcode":"08640",
    "sg:province":"Barcelona",
    "wof:name":"Banque Piqueres Olga",
    "wof:placetype":"venue"
},
  "geometry": {"coordinates":[1.8924590349,41.5442085266],"type":"Point"}
}