{
  "type": "Feature",
  "properties": {
    "addr:full":"Calle de Acera Recoletos, 2 Valladolid Valladolid 47004",
    "addr:housenumber":"2",
    "addr:postcode":"47004",
    "addr:street":"Calle De Acera Recoletos",
    "iso:country":"ES",
    "sg:address":"Calle de Acera Recoletos, 2",
    "sg:city":"Valladolid",
    "sg:orig_category":"Caf\u00c9s, Bares, Cervecer\u00cdas",
    "sg:phone":"+34 983 39 10 58",
    "sg:postcode":"47004",
    "sg:province":"Valladolid",
    "wof:name":"Espectaculos Continental S.l.",
    "wof:placetype":"venue"
},
  "geometry": {"coordinates":[-4.729010582,41.6479072571],"type":"Point"}
}