{
  "type": "Feature",
  "properties": {
    "addr:full":"Calle de Irun, 6 Errenteria Guip\u00f9zcoa 20100",
    "addr:housenumber":"6",
    "addr:postcode":"20100",
    "addr:street":"Calle De Irun;Guipu\u0300Zcoa",
    "iso:country":"ES",
    "sg:address":"Calle de Irun, 6",
    "sg:city":"Errenteria",
    "sg:orig_category":"Molduras, Junquillos, Listones Y Molduras Perforadas",
    "sg:phone":"+34 943 51 00 00",
    "sg:postcode":"20100",
    "sg:province":"Guip\u00f9zcoa",
    "wof:name":"Blanco Morlan Jose Ramon",
    "wof:placetype":"venue"
},
  "geometry": {"coordinates":[-1.9034110308,43.3157348633],"type":"Point"}
}