{
  "type": "Feature",
  "properties": {
    "iso:country":"ES",
    "sg:address":"Carr Estepar, De S', 17",
    "sg:city":"Cala Millor",
    "sg:orig_category":"Limpieza Industrial",
    "sg:phone":"+34 971 58 52 06",
    "sg:postcode":"07560",
    "sg:province":"Islas Baleares",
    "sg:website":"www.lavanderira-perez.com",
    "wof:name":"Lavanderia Perez S.l.",
    "wof:placetype":"venue"
},
  "geometry": {"coordinates":[3.3875029087,39.6077919006],"type":"Point"}
}