{
  "type": "Feature",
  "properties": {
    "iso:country":"ES",
    "sg:address":"Pl Democracia, S/n",
    "sg:city":"Mora D'ebre",
    "sg:orig_category":"Sindicatos De Trabajadores",
    "sg:phone":"+34 977 40 00 23",
    "sg:postcode":"43740",
    "sg:province":"Tarragona",
    "wof:name":"Unio General De Treballadors De Catalunya",
    "wof:placetype":"venue"
},
  "geometry": {"coordinates":[1.2540999651,41.1169281006],"type":"Point"}
}