{
  "type": "Feature",
  "properties": {
    "addr:full":"Ctra Alcolea Del Pinar, 36 Urbanitzacio Sol I Vista Tarragona 43206",
    "addr:housenumber":"36",
    "addr:postcode":"43206",
    "addr:street":"Ctra Alcolea Del Pinar;Urbanitzacio;I Vista",
    "iso:country":"ES",
    "sg:address":"Ctra Alcolea Del Pinar, 36",
    "sg:city":"Urbanitzacio Sol I Vista",
    "sg:orig_category":"Planchado",
    "sg:phone":"+34 977 31 03 15",
    "sg:postcode":"43206",
    "sg:province":"Tarragona",
    "wof:name":"Gonzalez Valle Florencio",
    "wof:placetype":"venue"
},
  "geometry": {"coordinates":[1.1039400101,41.1745300293],"type":"Point"}
}