{
  "type": "Feature",
  "properties": {
    "iso:country":"ES",
    "sg:address":"Carrer de Tenerife, 52",
    "sg:city":"Sabadell",
    "sg:orig_category":"Farmacias",
    "sg:phone":"+34 937 26 44 20",
    "sg:postcode":"08205",
    "sg:province":"Barcelona",
    "wof:name":"Viles Utjes Alejo",
    "wof:placetype":"venue"
},
  "geometry": {"coordinates":[2.0874950886,41.5449333191],"type":"Point"}
}