{
  "type": "Feature",
  "properties": {
    "iso:country":"ES",
    "sg:address":"Carrer de Amposta, S/n",
    "sg:city":"Torreforta",
    "sg:orig_category":"Loter\u00cda Y T\u00d3mbola",
    "sg:phone":"+34 977 55 05 78",
    "sg:postcode":"43006",
    "sg:province":"Tarragona",
    "wof:name":"Plana Monne Isabel",
    "wof:placetype":"venue"
},
  "geometry": {"coordinates":[1.2161049843,41.1195297241],"type":"Point"}
}