{
  "type": "Feature",
  "properties": {
    "addr:full":"Poli Industrial Alces, S/n Alcazar S. Juan Ciudad Real 13600",
    "addr:housenumber":"s / n",
    "addr:postcode":"13600",
    "addr:street":"Alcazar S. Juan Ciudad Real",
    "iso:country":"ES",
    "sg:address":"Poli Industrial Alces, S/n",
    "sg:city":"Alcazar S. Juan",
    "sg:orig_category":"Fabricaci\u00d3n De Tapices Y Moquetas Para Suelos Y Paredes",
    "sg:phone":"+34 926 58 80 93",
    "sg:postcode":"13600",
    "sg:province":"Ciudad Real",
    "wof:name":"Alces S.l. Industrias Del Plastico",
    "wof:placetype":"venue"
},
  "geometry": {"coordinates":[-3.9272627831,38.9860954285],"type":"Point"}
}