{
  "type": "Feature",
  "properties": {
    "addr:full":"Calle de Rio Duero (del), 30 Colmenar Viejo Madrid 28770",
    "addr:postcode":"28770",
    "addr:street":"Calle De Rio Duero Del",
    "iso:country":"ES",
    "sg:address":"Calle de Rio Duero (del), 30",
    "sg:city":"Colmenar Viejo",
    "sg:classifiers":[
        {
            "category":"Casinos & Gambling",
            "type":"Entertainment"
        }
    ],
    "sg:phone":"+34 918 45 48 46",
    "sg:postcode":"28770",
    "sg:province":"Madrid",
    "sg:tags":[
        "locale",
        "de",
        "juego"
    ],
    "wof:name":"El Oeste De Colmenar S.l",
    "wof:placetype":"venue"
},
  "geometry": {"coordinates":[-3.77196908,40.6633262634],"type":"Point"}
}