{
  "type": "Feature",
  "properties": {
    "addr:full":"Avda Alicante, 27 Denia Alicante 03700",
    "addr:housenumber":"27",
    "addr:postcode":"03700",
    "addr:street":"Avda Alicante",
    "iso:country":"ES",
    "sg:address":"Avda Alicante, 27",
    "sg:city":"Denia",
    "sg:orig_category":"Pintura Y Barniz (al Por Menor)",
    "sg:phone":"+34 965 78 89 22",
    "sg:postcode":"03700",
    "sg:province":"Alicante",
    "wof:name":"Decoraciones Ansar S.l.",
    "wof:placetype":"venue"
},
  "geometry": {"coordinates":[0.0999199972,38.8387756348],"type":"Point"}
}