{
  "type": "Feature",
  "properties": {
    "iso:country":"ES",
    "sg:address":"Carrer de Blanquerna, 47",
    "sg:city":"Palma",
    "sg:orig_category":"Fabricaci\u00d3n, Venta De Cuadros, Accesorios Para Enmarcar",
    "sg:phone":"+34 971 29 80 82",
    "sg:postcode":"07003",
    "sg:province":"Islas Baleares",
    "wof:name":"Sampol Sampol Antonio",
    "wof:placetype":"venue"
},
  "geometry": {"coordinates":[2.6489810944,39.581363678],"type":"Point"}
}