{
  "type": "Feature",
  "properties": {
    "addr:full":"Calle de Yunque, 6 Leganes Madrid 28...",
    "addr:housenumber":"6;28 ...",
    "addr:street":"Calle De Yunque;Madrid",
    "iso:country":"ES",
    "sg:address":"Calle de Yunque, 6",
    "sg:city":"Leganes",
    "sg:orig_category":"Centros Empresariales",
    "sg:phone":"+34 912 08 90 00",
    "sg:postcode":"28...",
    "sg:province":"Madrid",
    "wof:name":"Laboratorios De Control Femosa S.a.",
    "wof:placetype":"venue"
},
  "geometry": {"coordinates":[-3.8021528721,40.3430404663],"type":"Point"}
}