{
  "type": "Feature",
  "properties": {
    "iso:country":"ES",
    "sg:address":"Grup Zubiria Ybarra Tomas, 10",
    "sg:city":"Bilbao",
    "sg:orig_category":"Abogados",
    "sg:phone":"+34 944 45 49 43",
    "sg:postcode":"48007",
    "sg:province":"Vizcaya",
    "wof:name":"Echevarria Zabala Maria Concepcion",
    "wof:placetype":"venue"
},
  "geometry": {"coordinates":[-2.9171390533,43.265499115],"type":"Point"}
}