{
  "type": "Feature",
  "properties": {
    "iso:country":"ES",
    "sg:address":"Calle de Cervantes, 5",
    "sg:city":"Alconchel",
    "sg:classifiers":[
        {
            "category":"Taxi",
            "type":"Transportation"
        }
    ],
    "sg:phone":"+34 924 42 00 78",
    "sg:postcode":"06131",
    "sg:province":"Badajoz",
    "wof:name":"Bodion Gonzalez Adolfo",
    "wof:placetype":"venue"
},
  "geometry": {"coordinates":[-7.0695381165,38.515586853],"type":"Point"}
}