{
  "type": "Feature",
  "properties": {
    "iso:country":"ES",
    "sg:address":"Playa Getares, S/n",
    "sg:city":"Algeciras",
    "sg:orig_category":"Reposter\u00cdas",
    "sg:phone":"+34 956 60 30 99",
    "sg:postcode":"11207",
    "sg:province":"C\u00e1diz",
    "wof:name":"Panaderia Y Pasteleria Selva S.l.",
    "wof:placetype":"venue"
},
  "geometry": {"coordinates":[-5.4444608688,36.0982589722],"type":"Point"}
}