{
  "type": "Feature",
  "properties": {
    "addr:full":"Pol Atalayas, S/n Alacant Alicante 03...",
    "addr:housenumber":"/ n;03 ...",
    "addr:street":"Atalayas S;Alicante",
    "iso:country":"ES",
    "sg:address":"Pol Atalayas, S/n",
    "sg:city":"Alacant",
    "sg:orig_category":"Puros, Cigarrillos Y Tabaco (fabricaci\u00d3n, Al Por Mayor)",
    "sg:phone":"+34 965 23 36 00",
    "sg:postcode":"03...",
    "sg:province":"Alicante",
    "sg:website":"www.altadis.com",
    "wof:name":"Altadis S.a.",
    "wof:placetype":"venue"
},
  "geometry": {"coordinates":[-0.4810059965,38.3452033997],"type":"Point"}
}