{
  "type": "Feature",
  "properties": {
    "iso:country":"ES",
    "sg:address":"Calle de Calera, 25",
    "sg:city":"Moguer",
    "sg:orig_category":"Fabricaci\u00d3n Y Venta De Autocares Y Autobuses",
    "sg:phone":"+34 959 37 24 89",
    "sg:postcode":"21800",
    "sg:province":"Huelva",
    "wof:name":"Carpes Marquez Antonio",
    "wof:placetype":"venue"
},
  "geometry": {"coordinates":[-6.8339986801,37.275100708],"type":"Point"}
}