{
  "type": "Feature",
  "properties": {
    "addr:full":"Carrer de Malgrat, 29 Mataro Barcelona 08303",
    "addr:housenumber":"29",
    "addr:postcode":"08303",
    "addr:street":"Carrer De Malgrat",
    "iso:country":"ES",
    "sg:address":"Carrer de Malgrat, 29",
    "sg:city":"Mataro",
    "sg:orig_category":"Restaurantes",
    "sg:phone":"+34 937 98 78 31",
    "sg:postcode":"08303",
    "sg:province":"Barcelona",
    "wof:name":"Perez Serrano Araceli",
    "wof:placetype":"venue"
},
  "geometry": {"coordinates":[2.4288599491,41.5488433838],"type":"Point"}
}