{
  "type": "Feature",
  "properties": {
    "addr:full":"Plaz Reina Maria Cristina, S/n Ribadesella Asturias 33560",
    "addr:housenumber":"s / n",
    "addr:postcode":"33560",
    "iso:country":"ES",
    "sg:address":"Plaz Reina Maria Cristina, S/n",
    "sg:city":"Ribadesella",
    "sg:orig_category":"Arquitectos",
    "sg:phone":"+34 985 85 78 19",
    "sg:postcode":"33560",
    "sg:province":"Asturias",
    "wof:name":"Sanchez Arg\u00fcelles Ricardo",
    "wof:placetype":"venue"
},
  "geometry": {"coordinates":[-5.0588421822,43.461894989],"type":"Point"}
}