{
  "type": "Feature",
  "properties": {
    "addr:full":"Santiago Ramon Y Cajal, 5 Zaragoza Zaragoza 50004",
    "addr:housenumber":"5",
    "addr:postcode":"50004",
    "addr:street":"Santiago Ramon Y Cajal",
    "iso:country":"ES",
    "sg:address":"Santiago Ramon Y Cajal, 5",
    "sg:city":"Zaragoza",
    "sg:orig_category":"M\u00c9dicos: Estomatolog\u00cda",
    "sg:phone":"+34 976 43 94 75",
    "sg:postcode":"50004",
    "sg:province":"Zaragoza",
    "wof:name":"Garcia Vallejo Jesus",
    "wof:placetype":"venue"
},
  "geometry": {"coordinates":[-1.1210638285,41.7710342407],"type":"Point"}
}