{
  "type": "Feature",
  "properties": {
    "iso:country":"ES",
    "sg:address":"Calle de Jose Abascal, 24",
    "sg:city":"Madrid",
    "sg:orig_category":"\u00d3ptica: Instrumentos (fabricaci\u00d3n)",
    "sg:phone":"+34 914 47 35 29",
    "sg:postcode":"28003",
    "sg:province":"Madrid",
    "wof:name":"Cuota Gonzalez Salvador",
    "wof:placetype":"venue"
},
  "geometry": {"coordinates":[-3.6959409714,40.4381141663],"type":"Point"}
}