{
  "type": "Feature",
  "properties": {
    "addr:full":"Calle de Emilio Rivero, 56 Villar Rey Badajoz 06192",
    "addr:housenumber":"56",
    "addr:postcode":"06192",
    "addr:street":"Calle De Emilio Rivero",
    "iso:country":"ES",
    "sg:address":"Calle de Emilio Rivero, 56",
    "sg:city":"Villar Rey",
    "sg:orig_category":"Centros De Coordinaci\u00d3n",
    "sg:phone":"+34 924 41 46 11",
    "sg:postcode":"06192",
    "sg:province":"Badajoz",
    "wof:name":"Gestora De Servicios Para Estancos S.l.",
    "wof:placetype":"venue"
},
  "geometry": {"coordinates":[-6.8484778404,39.1318626404],"type":"Point"}
}