{
  "type": "Feature",
  "properties": {
    "addr:full":"Calle de Obelisco, 7 Zamora Zamora 49027",
    "addr:housenumber":"7",
    "addr:postcode":"49027",
    "addr:street":"Calle De Obelisco",
    "iso:country":"ES",
    "sg:address":"Calle de Obelisco, 7",
    "sg:city":"Zamora",
    "sg:orig_category":"Carnicer\u00cdas, Carnicer\u00cdas",
    "sg:phone":"+34 980 52 42 07",
    "sg:postcode":"49027",
    "sg:province":"Zamora",
    "wof:name":"Martin Campo Ildefonso",
    "wof:placetype":"venue"
},
  "geometry": {"coordinates":[-5.7619724274,41.5066375732],"type":"Point"}
}