{
  "type": "Feature",
  "properties": {
    "addr:full":"Tejeria, 21 Iru\u00f1a Navarra 31001",
    "addr:housenumber":"21",
    "addr:postcode":"31001",
    "addr:street":"Tejeria",
    "iso:country":"ES",
    "sg:address":"Tejeria, 21",
    "sg:city":"Iru\u00f1a",
    "sg:orig_category":"Droguer\u00cdas (al Por Menor)",
    "sg:phone":"+34 948 22 37 45",
    "sg:postcode":"31001",
    "sg:province":"Navarra",
    "wof:name":"Madoz Ansorena Visitacion",
    "wof:placetype":"venue"
},
  "geometry": {"coordinates":[-1.6407200098,42.8169136047],"type":"Point"}
}