{
  "type": "Feature",
  "properties": {
    "addr:full":"Av Meridiana, 422 Barcelona Barcelona 08030",
    "addr:housenumber":"422",
    "addr:postcode":"08030",
    "addr:street":"Meridiana",
    "iso:country":"ES",
    "sg:address":"Av Meridiana, 422",
    "sg:city":"Barcelona",
    "sg:orig_category":"\u00d3ptica: Instrumentos (fabricaci\u00d3n)",
    "sg:phone":"+34 933 11 31 02",
    "sg:postcode":"08030",
    "sg:province":"Barcelona",
    "wof:name":"Marcet Fernandez Ignacio",
    "wof:placetype":"venue"
},
  "geometry": {"coordinates":[2.1835970879,41.4326591492],"type":"Point"}
}