{
  "type": "Feature",
  "properties": {
    "iso:country":"ES",
    "sg:address":"Carrer de Tamarit, 173",
    "sg:city":"Barcelona",
    "sg:orig_category":"Muebles, Minoristas",
    "sg:phone":"+34 934 23 59 17",
    "sg:postcode":"08015",
    "sg:province":"Barcelona",
    "wof:name":"Moncunill Cirera Victoria",
    "wof:placetype":"venue"
},
  "geometry": {"coordinates":[2.1613900661,41.3791542053],"type":"Point"}
}