{
  "type": "Feature",
  "properties": {
    "addr:full":"Calle de Gran Via, 6 Salamanca Salamanca 37001",
    "addr:housenumber":"6",
    "addr:postcode":"37001",
    "addr:street":"Calle De Gran Via",
    "iso:country":"ES",
    "sg:address":"Calle de Gran Via, 6",
    "sg:city":"Salamanca",
    "sg:orig_category":"Material Y Suministros Para Peluquer\u00cda",
    "sg:phone":"+34 923 21 69 33",
    "sg:postcode":"37001",
    "sg:province":"Salamanca",
    "wof:name":"Cande-alberto S.l.",
    "wof:placetype":"venue"
},
  "geometry": {"coordinates":[-5.6594638824,40.967086792],"type":"Point"}
}