{
  "type": "Feature",
  "properties": {
    "iso:country":"ES",
    "sg:address":"Autovia(p Campollano), 6",
    "sg:city":"Albacete",
    "sg:orig_category":"Transportes Por V\u00cdas Navegables",
    "sg:phone":"+34 967 52 29 60",
    "sg:postcode":"02006",
    "sg:province":"Albacete",
    "wof:name":"Autobuses Alsina S.l.",
    "wof:placetype":"venue"
},
  "geometry": {"coordinates":[-1.9031590223,38.9876213074],"type":"Point"}
}