{
  "type": "Feature",
  "properties": {
    "addr:full":"Calle de Padre Feijoo, 1 Rua De Valdeorras Ourense 32350",
    "addr:housenumber":"1",
    "addr:postcode":"32350",
    "addr:street":"Calle De Padre Feijoo;Rua De",
    "iso:country":"ES",
    "sg:address":"Calle de Padre Feijoo, 1",
    "sg:city":"Rua De Valdeorras",
    "sg:orig_category":"Sociedades, Compa\u00d1\u00cdas Aseguradoras",
    "sg:phone":"+34 988 33 60 47",
    "sg:postcode":"32350",
    "sg:province":"Ourense",
    "wof:name":"Mapfre Servicios De Informatica S.a.",
    "wof:placetype":"venue"
},
  "geometry": {"coordinates":[-7.1205739975,42.392490387],"type":"Point"}
}