{
  "type": "Feature",
  "properties": {
    "addr:full":"Avda Reina Mercedes, 49 Sevilla Sevilla 41012",
    "addr:housenumber":"49",
    "addr:postcode":"41012",
    "addr:street":"Avda Reina Mercedes",
    "iso:country":"ES",
    "sg:address":"Avda Reina Mercedes, 49",
    "sg:city":"Sevilla",
    "sg:orig_category":"M\u00c9dicos: Psiquiatr\u00cda",
    "sg:phone":"+34 954 23 57 03",
    "sg:postcode":"41012",
    "sg:province":"Sevilla",
    "wof:name":"Blanco Picabia Ildefonso",
    "wof:placetype":"venue"
},
  "geometry": {"coordinates":[-5.9860072136,37.3581085205],"type":"Point"}
}