{
  "type": "Feature",
  "properties": {
    "iso:country":"ES",
    "sg:address":"Carrer de Rossello, 278",
    "sg:city":"Barcelona",
    "sg:orig_category":"Periodistas Profesionales",
    "sg:phone":"+34 934 58 60 82",
    "sg:postcode":"08037",
    "sg:province":"Barcelona",
    "wof:name":"Ibarz Ibarz Maria Mercedes",
    "wof:placetype":"venue"
},
  "geometry": {"coordinates":[2.1650240421,41.3989295959],"type":"Point"}
}