{
  "type": "Feature",
  "properties": {
    "addr:full":"Urb Playa Mogro, S/n Mogro Cantabria 39310",
    "addr:housenumber":"s",
    "addr:postcode":"39310",
    "addr:street":"Urb Playa Mogro;/ N",
    "iso:country":"ES",
    "sg:address":"Urb Playa Mogro, S/n",
    "sg:city":"Mogro",
    "sg:orig_category":"Cervecer\u00cdas",
    "sg:phone":"+34 942 57 66 88",
    "sg:postcode":"39310",
    "sg:province":"Cantabria",
    "wof:name":"Mogro Cerveceria S.l.",
    "wof:placetype":"venue"
},
  "geometry": {"coordinates":[-3.973938942,43.4362640381],"type":"Point"}
}