{
  "type": "Feature",
  "properties": {
    "iso:country":"ES",
    "sg:address":"Carrer de Torrent, 82",
    "sg:city":"Terrassa",
    "sg:orig_category":"Telas Y Sedas (al Por Menor)",
    "sg:phone":"+34 937 33 24 84",
    "sg:postcode":"08225",
    "sg:province":"Barcelona",
    "wof:name":"Antonio Redo S.l.",
    "wof:placetype":"venue"
},
  "geometry": {"coordinates":[2.0063734055,41.5715827942],"type":"Point"}
}