{
  "type": "Feature",
  "properties": {
    "addr:full":"Calle de General Sanjurjo, 10 Barajas \u00c1vila 05635",
    "addr:housenumber":"10",
    "addr:postcode":"05635",
    "addr:street":"Calle De General Sanjurjo",
    "iso:country":"ES",
    "sg:address":"Calle de General Sanjurjo, 10",
    "sg:city":"Barajas",
    "sg:orig_category":"Molduras, Junquillos, Listones Y Molduras Perforadas",
    "sg:phone":"+34 920 34 81 95",
    "sg:postcode":"05635",
    "sg:province":"\u00c1vila",
    "wof:name":"Arrabe Veneros Miguel Angel",
    "wof:placetype":"venue"
},
  "geometry": {"coordinates":[-5.1443538666,40.363697052],"type":"Point"}
}