{
  "type": "Feature",
  "properties": {
    "addr:full":"Calle de Historiador Diago, 11 Valencia Valencia 46007",
    "addr:housenumber":"11",
    "addr:postcode":"46007",
    "addr:street":"Calle De Historiador Diago",
    "iso:country":"ES",
    "sg:address":"Calle de Historiador Diago, 11",
    "sg:city":"Valencia",
    "sg:orig_category":"Inform\u00c1tica (estudios, Servicios, Asesor\u00cda, Formaci\u00d3n)",
    "sg:phone":"+34 963 84 04 09",
    "sg:postcode":"46007",
    "sg:province":"Valencia",
    "wof:name":"Ingenieria Y Marketing S. A.",
    "wof:placetype":"venue"
},
  "geometry": {"coordinates":[-0.3842279911,39.4671516418],"type":"Point"}
}