{
  "type": "Feature",
  "properties": {
    "iso:country":"ES",
    "sg:address":"Calle de Sorribas, 24",
    "sg:city":"Miranda Ebro",
    "sg:orig_category":"Carnicer\u00cdas, Carnicer\u00cdas",
    "sg:phone":"+34 947 31 09 64",
    "sg:postcode":"09200",
    "sg:province":"Burgos",
    "wof:name":"Ortiz De Pinedo Ruiz De Loizaga Victor",
    "wof:placetype":"venue"
},
  "geometry": {"coordinates":[-2.9489688873,42.6859588623],"type":"Point"}
}