{
  "type": "Feature",
  "properties": {
    "addr:full":"Trva Florian Docampo, 1 Zamora Zamora 49002",
    "addr:housenumber":"1",
    "addr:postcode":"49002",
    "addr:street":"Trva Florian Docampo",
    "iso:country":"ES",
    "sg:address":"Trva Florian Docampo, 1",
    "sg:city":"Zamora",
    "sg:orig_category":"Empresas De Desmonte",
    "sg:phone":"+34 980 51 57 16",
    "sg:postcode":"49002",
    "sg:province":"Zamora",
    "wof:name":"Martin Alonso Valentin",
    "wof:placetype":"venue"
},
  "geometry": {"coordinates":[-5.7457342148,41.5033302307],"type":"Point"}
}