{
  "type": "Feature",
  "properties": {
    "iso:country":"ES",
    "sg:address":"Avda Fuentemar (de), 16",
    "sg:city":"Coslada",
    "sg:orig_category":"Piscinas, Material, Suministros (al Por Menor)",
    "sg:phone":"+34 916 73 30 36",
    "sg:postcode":"28820",
    "sg:province":"Madrid",
    "wof:name":"Kamari Servis S.l.",
    "wof:placetype":"venue"
},
  "geometry": {"coordinates":[-3.548279047,40.4326133728],"type":"Point"}
}