{
  "type": "Feature",
  "properties": {
    "addr:full":"Calle de Pascual Orozco, 11 Alacant Alicante 03006",
    "addr:postcode":"03006",
    "addr:street":"Calle De Pascual Orozco",
    "iso:country":"ES",
    "sg:address":"Calle de Pascual Orozco, 11",
    "sg:city":"Alacant",
    "sg:orig_category":"Peluqueros: De Se\u00d1oras",
    "sg:phone":"+34 965 28 57 61",
    "sg:postcode":"03006",
    "sg:province":"Alicante",
    "wof:name":"Peluqueria Jomarmi S.l.",
    "wof:placetype":"venue"
},
  "geometry": {"coordinates":[-0.4993720055,38.3438529968],"type":"Point"}
}