{
  "type": "Feature",
  "properties": {
    "addr:full":"Carrer de Francesc Layret, S/n Molins Rei Barcelona 08750",
    "addr:housenumber":"s / n",
    "addr:postcode":"08750",
    "addr:street":"Carrer De Francesc Layret;Barcelona",
    "iso:country":"ES",
    "sg:address":"Carrer de Francesc Layret, S/n",
    "sg:city":"Molins Rei",
    "sg:orig_category":"Supermercados Y Hipermercados",
    "sg:phone":"+34 936 80 12 77",
    "sg:postcode":"08750",
    "sg:province":"Barcelona",
    "sg:website":"www.capraboacasa.com",
    "wof:name":"Caprabo S.a.",
    "wof:placetype":"venue"
},
  "geometry": {"coordinates":[2.0238699913,41.4044418335],"type":"Point"}
}