{
  "type": "Feature",
  "properties": {
    "addr:full":"Calle de San Francisco, 16 Castellon Castell\u00f3n 12002",
    "addr:housenumber":"16",
    "addr:postcode":"12002",
    "addr:street":"Calle De San Francisco",
    "iso:country":"ES",
    "sg:address":"Calle de San Francisco, 16",
    "sg:city":"Castellon",
    "sg:orig_category":"Bisuter\u00cda, Joyer\u00cda, Relojer\u00cda (al Por Menor)",
    "sg:phone":"+34 964 25 08 09",
    "sg:postcode":"12002",
    "sg:province":"Castell\u00f3n",
    "wof:name":"Rubio Ramos Salvador",
    "wof:placetype":"venue"
},
  "geometry": {"coordinates":[-0.0412890017,39.9838981628],"type":"Point"}
}