{
  "type": "Feature",
  "properties": {
    "addr:full":"Avda Santa Cruz, 117 San Isidro Santa Cruz De Tenerife 38611",
    "addr:housenumber":"117",
    "addr:postcode":"38611",
    "addr:street":"Avda Santa Cruz",
    "iso:country":"ES",
    "sg:address":"Avda Santa Cruz, 117",
    "sg:city":"San Isidro",
    "sg:orig_category":"Ortopedia General",
    "sg:phone":"+34 922 39 03 49",
    "sg:postcode":"38611",
    "sg:province":"Santa Cruz De Tenerife",
    "wof:name":"Sedano Bocos Manuel",
    "wof:placetype":"venue"
},
  "geometry": {"coordinates":[-16.5574264526,28.0765724182],"type":"Point"}
}