{
  "type": "Feature",
  "properties": {
    "addr:full":"Carretera De Mancha Real-cazorla, 33 Bedmar Ja\u00e9n 23537",
    "addr:housenumber":"33",
    "addr:postcode":"23537",
    "addr:street":"Carretera De Mancha Real-Cazorla",
    "iso:country":"ES",
    "sg:address":"Carretera De Mancha Real-cazorla, 33",
    "sg:city":"Bedmar",
    "sg:orig_category":"Negocio De Materiales De Construcci\u00d3n",
    "sg:phone":"+34 953 76 01 55",
    "sg:postcode":"23537",
    "sg:province":"Ja\u00e9n",
    "wof:name":"Hermanos Latorre Linde Cdad",
    "wof:placetype":"venue"
},
  "geometry": {"coordinates":[-3.414618969,37.8240966797],"type":"Point"}
}