{
  "type": "Feature",
  "properties": {
    "addr:full":"Calle de Doctor Lanuza, 14 Chiva Valencia 46370",
    "addr:housenumber":"14",
    "addr:postcode":"46370",
    "addr:street":"Calle De Doctor Lanuza",
    "iso:country":"ES",
    "sg:address":"Calle de Doctor Lanuza, 14",
    "sg:city":"Chiva",
    "sg:orig_category":"Electrodom\u00c9sticos (fabricaci\u00d3n, Al Por Mayor)",
    "sg:phone":"+34 962 52 05 05",
    "sg:postcode":"46370",
    "sg:province":"Valencia",
    "wof:name":"Electro-hogar Chiva S.l.",
    "wof:placetype":"venue"
},
  "geometry": {"coordinates":[-0.7170833945,39.4725608826],"type":"Point"}
}