{
  "type": "Feature",
  "properties": {
    "addr:full":"Calle de Ingeniero Emiliano Saizar, 8 Santomera Murcia 30140",
    "addr:housenumber":"8",
    "addr:postcode":"30140",
    "addr:street":"Calle De;Emiliano Saizar",
    "iso:country":"ES",
    "sg:address":"Calle de Ingeniero Emiliano Saizar, 8",
    "sg:city":"Santomera",
    "sg:orig_category":"Alimentaci\u00d3n General (al Por Menor)",
    "sg:phone":"+34 968 86 33 95",
    "sg:postcode":"30140",
    "sg:province":"Murcia",
    "wof:name":"Amparo Establecimientos S.l",
    "wof:placetype":"venue"
},
  "geometry": {"coordinates":[-1.0480164289,38.0591125488],"type":"Point"}
}