{
  "type": "Feature",
  "properties": {
    "iso:country":"ES",
    "sg:address":"Ctra. Morella, Km. 0002,6",
    "sg:city":"Castello Plana",
    "sg:orig_category":"Empresas De Carpinter\u00cda De Madera",
    "sg:phone":"+34 964 73 04 16",
    "sg:postcode":"12004",
    "sg:province":"Castell\u00f3n",
    "wof:name":"Zarazaga Gomez Antonia",
    "wof:placetype":"venue"
},
  "geometry": {"coordinates":[-0.0469201989,39.988735199],"type":"Point"}
}