{
  "type": "Feature",
  "properties": {
    "addr:full":"Calle de Clara Del Rey, 44 Madrid Madrid 28002",
    "addr:housenumber":"44",
    "addr:postcode":"madrid;28002",
    "addr:street":"Calle De Clara Del Rey",
    "iso:country":"ES",
    "sg:address":"Calle de Clara Del Rey, 44",
    "sg:city":"Madrid",
    "sg:orig_category":"Caf\u00c9s, Bares, Cervecer\u00cdas",
    "sg:phone":"+34 914 13 41 31",
    "sg:postcode":"28002",
    "sg:province":"Madrid",
    "wof:name":"Gutierrez-solana Martinez Vidal",
    "wof:placetype":"venue"
},
  "geometry": {"coordinates":[-3.6684248447,40.4449615479],"type":"Point"}
}