{
  "type": "Feature",
  "properties": {
    "addr:full":"Pl Ajuntament, 29 Hospitalet Llobregat Barcelona 08901",
    "addr:housenumber":"29",
    "addr:postcode":"08901",
    "addr:street":"Pl Ajuntament",
    "iso:country":"ES",
    "sg:address":"Pl Ajuntament, 29",
    "sg:city":"Hospitalet Llobregat",
    "sg:orig_category":"Cajas De Ahorro",
    "sg:phone":"+34 933 38 92 38",
    "sg:postcode":"08901",
    "sg:province":"Barcelona",
    "wof:name":"Caixa D'estalvis Del Penedes",
    "wof:placetype":"venue"
},
  "geometry": {"coordinates":[2.0993700027,41.359588623],"type":"Point"}
}