{
  "type": "Feature",
  "properties": {
    "addr:full":"Carrer de Beniarres, 3 Banyets Alicante 03560",
    "addr:housenumber":"3",
    "addr:postcode":"03560",
    "addr:street":"Carrer De Beniarres;Alicante",
    "iso:country":"ES",
    "sg:address":"Carrer de Beniarres, 3",
    "sg:city":"Banyets",
    "sg:orig_category":"Fabricaci\u00d3n Y Distribuci\u00d3n De Colas, Masillas Y Encoladoras",
    "sg:phone":"+34 965 63 01 04",
    "sg:postcode":"03560",
    "sg:province":"Alicante",
    "wof:name":"Compa\u00f1 Poveda Jose",
    "wof:placetype":"venue"
},
  "geometry": {"coordinates":[-0.3906340003,38.4271888733],"type":"Point"}
}