{
  "type": "Feature",
  "properties": {
    "iso:country":"ES",
    "sg:address":"Carr Pau Casals, 48",
    "sg:city":"Vidreres",
    "sg:orig_category":"Producci\u00d3n, Comercio De Cereales",
    "sg:phone":"+34 972 85 01 14",
    "sg:postcode":"17411",
    "sg:province":"Girona",
    "wof:name":"Dalemus Alsina Jose",
    "wof:placetype":"venue"
},
  "geometry": {"coordinates":[2.7805418968,41.7906723022],"type":"Point"}
}