{
  "type": "Feature",
  "properties": {
    "addr:full":"Calle de Juan Labrador, 6 Toledo Toledo 45001",
    "addr:housenumber":"6",
    "addr:postcode":"45001",
    "addr:street":"Calle De Juan Labrador",
    "iso:country":"ES",
    "sg:address":"Calle de Juan Labrador, 6",
    "sg:city":"Toledo",
    "sg:orig_category":"Expertos Contables, Revisores De Cuentas",
    "sg:phone":"+34 925 25 39 85",
    "sg:postcode":"45001",
    "sg:province":"Toledo",
    "wof:name":"Granatula S.l.",
    "wof:placetype":"venue"
},
  "geometry": {"coordinates":[-4.0215711594,39.8576507568],"type":"Point"}
}