{
  "type": "Feature",
  "properties": {
    "iso:country":"ES",
    "sg:address":"Pl Weyler, 1",
    "sg:city":"Manacor",
    "sg:orig_category":"Panader\u00cdas, Panader\u00cdas",
    "sg:phone":"+34 971 55 41 50",
    "sg:postcode":"07500",
    "sg:province":"Islas Baleares",
    "wof:name":"Lloret Segura Adoracion",
    "wof:placetype":"venue"
},
  "geometry": {"coordinates":[3.2103888988,39.5689926147],"type":"Point"}
}