{
  "type": "Feature",
  "properties": {
    "iso:country":"ES",
    "sg:address":"Carretera Lorca, S/n",
    "sg:city":"Vera",
    "sg:orig_category":"Mec\u00c1nico Del Autom\u00d3vil",
    "sg:phone":"+34 950 39 01 27",
    "sg:postcode":"04620",
    "sg:province":"Almer\u00eda",
    "wof:name":"Luis Cano Garcia S.l.",
    "wof:placetype":"venue"
},
  "geometry": {"coordinates":[-1.8714840412,37.2498016357],"type":"Point"}
}