{
  "type": "Feature",
  "properties": {
    "iso:country":"ES",
    "sg:address":"Carrer de Portaferrissa, 11",
    "sg:city":"Barcelona",
    "sg:orig_category":"Abogados",
    "sg:phone":"+34 933 01 46 85",
    "sg:postcode":"08002",
    "sg:province":"Barcelona",
    "wof:name":"Baques-gabasa Advocats S.c.p.",
    "wof:placetype":"venue"
},
  "geometry": {"coordinates":[2.1727020741,41.383556366],"type":"Point"}
}