{
  "type": "Feature",
  "properties": {
    "addr:full":"Calle de Viera Y Clavijo, 15 Palmas De Gran Canaria Las Palmas 35002",
    "addr:housenumber":"15",
    "addr:postcode":"35002",
    "addr:street":"Calle De Viera Y Clavijo",
    "iso:country":"ES",
    "sg:address":"Calle de Viera Y Clavijo, 15",
    "sg:city":"Palmas De Gran Canaria",
    "sg:orig_category":"Ropa Para Ni\u00d1os (al Por Menor)",
    "sg:phone":"+34 928 43 10 87",
    "sg:postcode":"35002",
    "sg:province":"Las Palmas",
    "sg:website":"www.gocco.es",
    "wof:name":"Gocco Confeg S.a.",
    "wof:placetype":"venue"
},
  "geometry": {"coordinates":[-15.4181213379,28.1067657471],"type":"Point"}
}