{
  "type": "Feature",
  "properties": {
    "addr:full":"La Noria, 31 Fuengirola M\u00e1laga 29640",
    "addr:housenumber":"31",
    "addr:postcode":"29640",
    "addr:street":"La Noria;Ma\u0301Laga",
    "iso:country":"ES",
    "sg:address":"La Noria, 31",
    "sg:city":"Fuengirola",
    "sg:orig_category":"Centros P\u00dablicos De Formaci\u00d3n Profesional Y T\u00c9cnica",
    "sg:phone":"+34 952 46 87 46",
    "sg:postcode":"29640",
    "sg:province":"M\u00e1laga",
    "wof:name":"Ilustre Colegio De Procuradores De Malaga",
    "wof:placetype":"venue"
},
  "geometry": {"coordinates":[-4.6330537796,36.5426368713],"type":"Point"}
}