{
  "type": "Feature",
  "properties": {
    "iso:country":"ES",
    "sg:address":"Carr Ignasi Iglesias, 44",
    "sg:city":"Badalona",
    "sg:orig_category":"Institutos M\u00c9dicos",
    "sg:phone":"+34 933 84 63 93",
    "sg:postcode":"08912",
    "sg:province":"Barcelona",
    "wof:name":"Iriteb S. A.",
    "wof:placetype":"venue"
},
  "geometry": {"coordinates":[2.2441720963,41.4478683472],"type":"Point"}
}