{
  "type": "Feature",
  "properties": {
    "iso:country":"ES",
    "sg:address":"Calle de Carratala, 8",
    "sg:city":"Alacant",
    "sg:orig_category":"Procuradores",
    "sg:phone":"+34 965 13 57 73",
    "sg:postcode":"03007",
    "sg:province":"Alicante",
    "wof:name":"Dabrowski  Daniel Janusz",
    "wof:placetype":"venue"
},
  "geometry": {"coordinates":[-0.4964239001,38.3428153992],"type":"Point"}
}