{
  "type": "Feature",
  "properties": {
    "addr:full":"Avda San Pedro De Alcantara, 16 Caceres C\u00e1ceres 10001",
    "addr:housenumber":"16",
    "addr:postcode":"10001",
    "addr:street":"Avda San Pedro De Alcantara;Ca\u0301Ceres",
    "iso:country":"ES",
    "sg:address":"Avda San Pedro De Alcantara, 16",
    "sg:city":"Caceres",
    "sg:orig_category":"Trajes Y Adornos De Boda (confecci\u00d3n, Al Por Menor)",
    "sg:phone":"+34 927 22 00 25",
    "sg:postcode":"10001",
    "sg:province":"C\u00e1ceres",
    "wof:name":"Mellado Pozas Yolanda",
    "wof:placetype":"venue"
},
  "geometry": {"coordinates":[-6.3800578117,39.4714279175],"type":"Point"}
}