{
  "type": "Feature",
  "properties": {
    "iso:country":"ES",
    "sg:address":"Calle de Malmasin, 7",
    "sg:city":"Bilbao",
    "sg:orig_category":"Lateros",
    "sg:phone":"+34 944 15 37 53",
    "sg:postcode":"48003",
    "sg:province":"Vizcaya",
    "sg:website":"www.garbijet.com",
    "wof:name":"Garbi Jet S.l.",
    "wof:placetype":"venue"
},
  "geometry": {"coordinates":[-2.9229810238,43.2405090332],"type":"Point"}
}