{
  "type": "Feature",
  "properties": {
    "addr:full":"Calle de Ramon Y Cajal, 7 Santa Cruz De Mudela Ciudad Real 13730",
    "addr:housenumber":"7",
    "addr:postcode":"13730",
    "addr:street":"Calle De Ramon Y Cajal",
    "iso:country":"ES",
    "sg:address":"Calle de Ramon Y Cajal, 7",
    "sg:city":"Santa Cruz De Mudela",
    "sg:orig_category":"Bebidas",
    "sg:phone":"+34 926 34 23 06",
    "sg:postcode":"13730",
    "sg:province":"Ciudad Real",
    "wof:name":"Laguna Camacho Vicente",
    "wof:placetype":"venue"
},
  "geometry": {"coordinates":[-3.4637300968,38.6388587952],"type":"Point"}
}