{
  "type": "Feature",
  "properties": {
    "addr:full":"Calle de Pesquera, 6 Torrejon Ardoz Madrid 28850",
    "addr:housenumber":"6",
    "addr:postcode":"28850",
    "addr:street":"Calle De Pesquera",
    "iso:country":"ES",
    "sg:address":"Calle de Pesquera, 6",
    "sg:city":"Torrejon Ardoz",
    "sg:orig_category":"Encuadernaci\u00d3n E Impresi\u00d3n De Folletos",
    "sg:phone":"+34 916 75 19 05",
    "sg:postcode":"28850",
    "sg:province":"Madrid",
    "wof:name":"Cuadrado Calvo Maria Esther",
    "wof:placetype":"venue"
},
  "geometry": {"coordinates":[-3.4788210392,40.4577026367],"type":"Point"}
}