{
  "type": "Feature",
  "properties": {
    "iso:country":"ES",
    "sg:address":"Pase Andalucia (de), 50",
    "sg:city":"Espejo",
    "sg:orig_category":"Librer\u00cdas",
    "sg:phone":"+34 957 38 71 71",
    "sg:postcode":"14830",
    "sg:province":"C\u00f3rdoba",
    "wof:name":"Algaba Sanchez Jose Maria",
    "wof:placetype":"venue"
},
  "geometry": {"coordinates":[-4.5521273613,37.668056488],"type":"Point"}
}