{
  "type": "Feature",
  "properties": {
    "addr:full":"Plaz Colon (de), 7 Galapagar Madrid 28260",
    "addr:postcode":"28260",
    "iso:country":"ES",
    "sg:address":"Plaz Colon (de), 7",
    "sg:city":"Galapagar",
    "sg:orig_category":"Retoques De Vestidos",
    "sg:phone":"+34 918 58 03 40",
    "sg:postcode":"28260",
    "sg:province":"Madrid",
    "wof:name":"Tijeras Y Dedal",
    "wof:placetype":"venue"
},
  "geometry": {"coordinates":[-4.0020170212,40.5765609741],"type":"Point"}
}