{
  "type": "Feature",
  "properties": {
    "iso:country":"ES",
    "sg:address":"Avda Nuestro Padre Jesus Cautivo, 43",
    "sg:city":"Fuengirola",
    "sg:orig_category":"Agencias Y Agentes Comerciales, Representantes",
    "sg:phone":"+34 952 58 26 39",
    "sg:postcode":"29640",
    "sg:province":"M\u00e1laga",
    "wof:name":"Comunidad De Propietarios Edificio Fenix",
    "wof:placetype":"venue"
},
  "geometry": {"coordinates":[-4.6132779121,36.5563545227],"type":"Point"}
}