{
  "type": "Feature",
  "properties": {
    "addr:full":"Pla\u00c7 Creu, 19 Igualada Barcelona 08700",
    "addr:housenumber":"19",
    "addr:postcode":"08700",
    "addr:street":"Creu",
    "iso:country":"ES",
    "sg:address":"Pla\u00c7 Creu, 19",
    "sg:city":"Igualada",
    "sg:orig_category":"Inversiones",
    "sg:phone":"+34 938 04 46 32",
    "sg:postcode":"08700",
    "sg:province":"Barcelona",
    "wof:name":"Inversions Norso 2022 S.l.",
    "wof:placetype":"venue"
},
  "geometry": {"coordinates":[1.6129490137,41.5849189758],"type":"Point"}
}