{
  "type": "Feature",
  "properties": {
    "iso:country":"ES",
    "sg:address":"Avda Buenos Aires, S/n",
    "sg:city":"Porri\u00f1o",
    "sg:orig_category":"Fabricaci\u00d3n De Art\u00cdculos Y Equipos Deportivos Y De Ocio",
    "sg:phone":"+34 986 33 00 87",
    "sg:postcode":"36400",
    "sg:province":"Pontevedra",
    "sg:website":"www.zico.es",
    "wof:name":"Zico Espa\u00f1a S. L.",
    "wof:placetype":"venue"
},
  "geometry": {"coordinates":[-8.624912262,42.1624832153],"type":"Point"}
}