{
  "type": "Feature",
  "properties": {
    "addr:full":"Avda America, 2 Madrid Madrid 28028",
    "addr:housenumber":"2",
    "addr:postcode":"28028",
    "addr:street":"Avda America",
    "iso:country":"ES",
    "sg:address":"Avda America, 2",
    "sg:city":"Madrid",
    "sg:orig_category":"Caf\u00c9s, Bares, Cervecer\u00cdas",
    "sg:phone":"+34 913 55 08 73",
    "sg:postcode":"28028",
    "sg:province":"Madrid",
    "wof:name":"Rio Lerma S.l.",
    "wof:placetype":"venue"
},
  "geometry": {"coordinates":[-3.6770050526,40.4374275208],"type":"Point"}
}