{
  "type": "Feature",
  "properties": {
    "addr:full":"Calle de Ezpondoa, 6 Burlada Navarra 31600",
    "addr:housenumber":"6",
    "addr:postcode":"31600",
    "addr:street":"Calle De Ezpondoa",
    "iso:country":"ES",
    "sg:address":"Calle de Ezpondoa, 6",
    "sg:city":"Burlada",
    "sg:orig_category":"Empresas De Portes Y Mensajer\u00cda",
    "sg:phone":"+34 948 24 68 71",
    "sg:postcode":"31600",
    "sg:province":"Navarra",
    "wof:name":"Rios Mensajeria S.l",
    "wof:placetype":"venue"
},
  "geometry": {"coordinates":[-1.6176990271,42.8237915039],"type":"Point"}
}