{
  "type": "Feature",
  "properties": {
    "addr:full":"Calle de Sevilla (de), 8 Fuenlabrada Madrid 28944",
    "addr:housenumber":"8",
    "addr:postcode":"28944",
    "addr:street":"Calle De Sevilla De",
    "iso:country":"ES",
    "sg:address":"Calle de Sevilla (de), 8",
    "sg:city":"Fuenlabrada",
    "sg:orig_category":"Panader\u00cdas, Panader\u00cdas",
    "sg:phone":"+34 916 06 52 03",
    "sg:postcode":"28944",
    "sg:province":"Madrid",
    "wof:name":"Castro Garcia Enrique",
    "wof:placetype":"venue"
},
  "geometry": {"coordinates":[-3.7966520786,40.2915306091],"type":"Point"}
}