{
  "type": "Feature",
  "properties": {
    "iso:country":"ES",
    "sg:address":"Carrer de Calabria, 127",
    "sg:city":"Barcelona",
    "sg:orig_category":"Supermercados Y Hipermercados",
    "sg:phone":"+34 933 25 94 21",
    "sg:postcode":"08015",
    "sg:province":"Barcelona",
    "wof:name":"Aranda Lucas Jose Antonio",
    "wof:placetype":"venue"
},
  "geometry": {"coordinates":[2.153421402,41.3809089661],"type":"Point"}
}