{
  "type": "Feature",
  "properties": {
    "iso:country":"ES",
    "sg:address":"Plaz San Julian, 3",
    "sg:city":"Carrion De Los Condes",
    "sg:orig_category":"Asesor\u00cda Fiscal Y Jur\u00cddica",
    "sg:phone":"+34 979 88 08 96",
    "sg:postcode":"34120",
    "sg:province":"Palencia",
    "sg:website":"www.paginasamarillas.es",
    "wof:name":"Izquierdo Cuadrado Bego\u00f1a",
    "wof:placetype":"venue"
},
  "geometry": {"coordinates":[-4.6031517982,42.3396453857],"type":"Point"}
}