{
  "type": "Feature",
  "properties": {
    "iso:country":"ES",
    "sg:address":"Avda Marcial Llorente (de), 9",
    "sg:city":"Pelayos Presa",
    "sg:orig_category":"Carpinteros",
    "sg:phone":"+34 918 64 44 72",
    "sg:postcode":"28696",
    "sg:province":"Madrid",
    "wof:name":"Vensima Pvc S.l",
    "wof:placetype":"venue"
},
  "geometry": {"coordinates":[-4.3229942322,40.3628768921],"type":"Point"}
}