{
  "type": "Feature",
  "properties": {
    "addr:full":"Calle de Diecinueve De Abril, 9 S. Miguel Salinas Alicante 03193",
    "addr:housenumber":"9",
    "addr:postcode":"03193",
    "addr:street":"Calle De Diecinueve De Abril;S. Miguel Salinas Alicante",
    "iso:country":"ES",
    "sg:address":"Calle de Diecinueve De Abril, 9",
    "sg:city":"S. Miguel Salinas",
    "sg:orig_category":"Alquiler De V\u00cddeo",
    "sg:phone":"+34 965 72 08 41",
    "sg:postcode":"03193",
    "sg:province":"Alicante",
    "wof:name":"Lamela Martin Maria Del Carmen",
    "wof:placetype":"venue"
},
  "geometry": {"coordinates":[-0.7889748812,37.9781532288],"type":"Point"}
}