{
  "type": "Feature",
  "properties": {
    "iso:country":"ES",
    "sg:address":"Pl Unio, 4",
    "sg:city":"Esparreguera",
    "sg:orig_category":"Alquiler De V\u00cddeo",
    "sg:phone":"+34 937 79 58 86",
    "sg:postcode":"08292",
    "sg:province":"Barcelona",
    "wof:name":"Esparraguera Video Digital,s.l.",
    "wof:placetype":"venue"
},
  "geometry": {"coordinates":[1.8704040051,41.5358581543],"type":"Point"}
}