{
  "type": "Feature",
  "properties": {
    "iso:country":"ES",
    "sg:address":"Calle de Serrano, 13",
    "sg:city":"Madrid",
    "sg:orig_category":"Museos",
    "sg:phone":"+34 914 31 68 40",
    "sg:postcode":"28001",
    "sg:province":"Madrid",
    "sg:website":"www.man.es",
    "wof:name":"Museo Arqueologico Nacional",
    "wof:placetype":"venue"
},
  "geometry": {"coordinates":[-3.688450098,40.4229278564],"type":"Point"}
}