{
  "type": "Feature",
  "properties": {
    "addr:full":"Calle de Fontan, 17 Oviedo Asturias 33009",
    "addr:housenumber":"17",
    "addr:postcode":"33009",
    "addr:street":"Calle De Fontan",
    "iso:country":"ES",
    "sg:address":"Calle de Fontan, 17",
    "sg:city":"Oviedo",
    "sg:orig_category":"Agencias De Viajes",
    "sg:phone":"+34 985 21 43 66",
    "sg:postcode":"33009",
    "sg:province":"Asturias",
    "sg:website":"www.viajescrisol.com",
    "wof:name":"Viajes Crisol S A",
    "wof:placetype":"venue"
},
  "geometry": {"coordinates":[-5.8463582993,43.360042572],"type":"Point"}
}