{
  "type": "Feature",
  "properties": {
    "addr:full":"Carrer de Sant Vicent, 48 Campello Alicante 03560",
    "addr:housenumber":"48",
    "addr:postcode":"03560",
    "addr:street":"Carrer De Sant Vicent",
    "iso:country":"ES",
    "sg:address":"Carrer de Sant Vicent, 48",
    "sg:city":"Campello",
    "sg:orig_category":"Heladeros",
    "sg:phone":"+34 965 63 02 99",
    "sg:postcode":"03560",
    "sg:province":"Alicante",
    "wof:name":"Pikostore S.l.",
    "wof:placetype":"venue"
},
  "geometry": {"coordinates":[-0.3893820047,38.4276199341],"type":"Point"}
}