{
  "type": "Feature",
  "properties": {
    "addr:full":"Avda Andalucia (de), 142 Coria Rio Sevilla 41100",
    "addr:housenumber":"142",
    "addr:postcode":"41100",
    "addr:street":"Avda Andalucia De;Rio Sevilla",
    "iso:country":"ES",
    "sg:address":"Avda Andalucia (de), 142",
    "sg:city":"Coria Rio",
    "sg:orig_category":"Art\u00cdculos De Decoraci\u00d3n",
    "sg:phone":"+34 954 77 00 89",
    "sg:postcode":"41100",
    "sg:province":"Sevilla",
    "wof:name":"Orteagro S.l.",
    "wof:placetype":"venue"
},
  "geometry": {"coordinates":[-6.0497951508,37.2850151062],"type":"Point"}
}