{
  "type": "Feature",
  "properties": {
    "iso:country":"ES",
    "sg:address":"Calle de San Orencio, 14",
    "sg:city":"Huesca",
    "sg:orig_category":"Bisuter\u00cda, Joyer\u00cda, Relojer\u00cda (al Por Menor)",
    "sg:phone":"+34 974 22 47 36",
    "sg:postcode":"22001",
    "sg:province":"Huesca",
    "wof:name":"Bailin Fontana Francisco",
    "wof:placetype":"venue"
},
  "geometry": {"coordinates":[-0.4073246121,42.1367607117],"type":"Point"}
}