{
  "type": "Feature",
  "properties": {
    "addr:full":"Calle de Galicia, 22 Palmas De Gran Canaria Las Palmas 35006",
    "addr:postcode":"35006",
    "addr:street":"Calle De Galicia 22",
    "iso:country":"ES",
    "sg:address":"Calle de Galicia, 22",
    "sg:city":"Palmas De Gran Canaria",
    "sg:orig_category":"Aud\u00cdfonos",
    "sg:phone":"+34 928 24 15 73",
    "sg:postcode":"35006",
    "sg:province":"Las Palmas",
    "wof:name":"Hernandez Ferrera Gemma Isabel",
    "wof:placetype":"venue"
},
  "geometry": {"coordinates":[-15.4332227707,28.1326370239],"type":"Point"}
}