{
  "type": "Feature",
  "properties": {
    "iso:country":"ES",
    "sg:address":"Calle de San Martin, 9",
    "sg:city":"Donostia-san Sebastian",
    "sg:orig_category":"M\u00c9dicos: Ginecolog\u00cda Y Obstetricia",
    "sg:phone":"+34 943 42 48 38",
    "sg:postcode":"20005",
    "sg:province":"Guip\u00f9zcoa",
    "wof:name":"Urbieta Garagorri Luis",
    "wof:placetype":"venue"
},
  "geometry": {"coordinates":[-1.9805710316,43.3178291321],"type":"Point"}
}