{
  "type": "Feature",
  "properties": {
    "iso:country":"ES",
    "sg:address":"Calle de Joaquin Blume, 11",
    "sg:city":"Palmas De Gran Canaria",
    "sg:orig_category":"Alimentaci\u00d3n General (al Por Menor)",
    "sg:phone":"+34 928 20 62 91",
    "sg:postcode":"35011",
    "sg:province":"Las Palmas",
    "wof:name":"Armas Brisson Jose Matias",
    "wof:placetype":"venue"
},
  "geometry": {"coordinates":[-15.4372205734,28.1216106415],"type":"Point"}
}