{
  "type": "Feature",
  "properties": {
    "addr:full":"Calle de Peru, 12 Jerez De La Frontera C\u00e1diz 11407",
    "addr:housenumber":"12",
    "addr:postcode":"11407",
    "addr:street":"Calle De Peru",
    "iso:country":"ES",
    "sg:address":"Calle de Peru, 12",
    "sg:city":"Jerez De La Frontera",
    "sg:orig_category":"Inmobiliaria (agencias)",
    "sg:phone":"+34 956 18 47 97",
    "sg:postcode":"11407",
    "sg:province":"C\u00e1diz",
    "sg:website":"www.urbis.com",
    "wof:name":"Inmobiliaria Urbis S.a.",
    "wof:placetype":"venue"
},
  "geometry": {"coordinates":[-6.124396801,36.7016334534],"type":"Point"}
}