{
  "type": "Feature",
  "properties": {
    "addr:full":"Carr Federico Garcia Lorca, 16 Alfas Pi Alicante 03580",
    "addr:housenumber":"16",
    "addr:postcode":"03580",
    "addr:street":"Carr Federico Garcia Lorca",
    "iso:country":"ES",
    "sg:address":"Carr Federico Garcia Lorca, 16",
    "sg:city":"Alfas Pi",
    "sg:orig_category":"Laboratorios Y Trabajos De Fotograf\u00cda, V\u00cddeo Y Cine",
    "sg:phone":"+34 965 88 86 44",
    "sg:postcode":"03580",
    "sg:province":"Alicante",
    "wof:name":"Gonzalez Garcia Yolanda",
    "wof:placetype":"venue"
},
  "geometry": {"coordinates":[-0.1017083973,38.5791435242],"type":"Point"}
}