{
  "type": "Feature",
  "properties": {
    "iso:country":"ES",
    "sg:address":"Avda Mejico, S/n",
    "sg:city":"Huelva",
    "sg:orig_category":"Marroquiner\u00cda (confecci\u00d3n)",
    "sg:phone":"+34 959 35 90 98",
    "sg:postcode":"21001",
    "sg:province":"Huelva",
    "wof:name":"Gonzalez Benzal Isabel",
    "wof:placetype":"venue"
},
  "geometry": {"coordinates":[-6.9495940208,37.256313324],"type":"Point"}
}