{
  "type": "Feature",
  "properties": {
    "addr:full":"Co Del Tojanco, S/n Villaviudas Palencia 34249",
    "addr:housenumber":"s",
    "addr:postcode":"34249",
    "addr:street":"/ N",
    "iso:country":"ES",
    "sg:address":"Co Del Tojanco, S/n",
    "sg:city":"Villaviudas",
    "sg:orig_category":"Cr\u00cda De Animales",
    "sg:phone":"+34 979 78 81 47",
    "sg:postcode":"34249",
    "sg:province":"Palencia",
    "wof:name":"Roman Rubio Jesus",
    "wof:placetype":"venue"
},
  "geometry": {"coordinates":[-4.3416252136,41.9639205933],"type":"Point"}
}