{
  "type": "Feature",
  "properties": {
    "addr:full":"Calle de Doctor Juan Dominguez Perez, 40 Palmas De Gran Canaria Las Palmas 35008",
    "addr:postcode":"35008",
    "addr:street":"Calle De Doctor Juan Dominguez Perez 40",
    "iso:country":"ES",
    "sg:address":"Calle de Doctor Juan Dominguez Perez, 40",
    "sg:city":"Palmas De Gran Canaria",
    "sg:orig_category":"Transportes Mar\u00cdtimos",
    "sg:phone":"+34 928 46 12 70",
    "sg:postcode":"35008",
    "sg:province":"Las Palmas",
    "wof:name":"Transportes Los Calas S.a.",
    "wof:placetype":"venue"
},
  "geometry": {"coordinates":[-15.4102573395,28.1615657806],"type":"Point"}
}