{
  "type": "Feature",
  "properties": {
    "iso:country":"ES",
    "sg:address":"Avda Monforte De Lemos, 105",
    "sg:city":"Madrid",
    "sg:orig_category":"Electrodom\u00c9sticos (fabricaci\u00d3n, Al Por Mayor)",
    "sg:phone":"+34 917 30 18 37",
    "sg:postcode":"28029",
    "sg:province":"Madrid",
    "wof:name":"Kirpalani  Mukesh Parsam",
    "wof:placetype":"venue"
},
  "geometry": {"coordinates":[-3.7060229778,40.4788246155],"type":"Point"}
}