{
  "type": "Feature",
  "properties": {
    "addr:full":"Calle de Placido Pe\u00d1a, 27 Vilalba Lugo 27800",
    "addr:housenumber":"27",
    "addr:postcode":"27800",
    "addr:street":"Calle De Placido Pen\u0303A",
    "iso:country":"ES",
    "sg:address":"Calle de Placido Pe\u00d1a, 27",
    "sg:city":"Vilalba",
    "sg:orig_category":"Panader\u00cdas, Panader\u00cdas",
    "sg:phone":"+34 982 51 17 34",
    "sg:postcode":"27800",
    "sg:province":"Lugo",
    "wof:name":"Ana Maria Gra\u00f1a Rego Y Maria Jesus Souto Villares Cdad",
    "wof:placetype":"venue"
},
  "geometry": {"coordinates":[-7.6786823273,43.3003425598],"type":"Point"}
}