{
  "type": "Feature",
  "properties": {
    "addr:full":"Calle de Luis Felipe Gomez Wanguemert, 26 Llanos De Aridane Santa Cruz De Tenerife 38760",
    "addr:housenumber":"26",
    "addr:postcode":"38760",
    "addr:street":"Calle De Luis Felipe Gomez Wanguemert",
    "iso:country":"ES",
    "sg:address":"Calle de Luis Felipe Gomez Wanguemert, 26",
    "sg:city":"Llanos De Aridane",
    "sg:orig_category":"Abogados",
    "sg:phone":"+34 922 46 31 63",
    "sg:postcode":"38760",
    "sg:province":"Santa Cruz De Tenerife",
    "wof:name":"Cutillas Fernandez Antonio Javier",
    "wof:placetype":"venue"
},
  "geometry": {"coordinates":[-17.9085597992,28.6563796997],"type":"Point"}
}