{
  "type": "Feature",
  "properties": {
    "addr:full":"Calle de Medina De Pomar, 1 Bilbao Vizcaya 48012",
    "addr:housenumber":"1",
    "addr:postcode":"48012",
    "addr:street":"Calle De Medina De Pomar",
    "iso:country":"ES",
    "sg:address":"Calle de Medina De Pomar, 1",
    "sg:city":"Bilbao",
    "sg:orig_category":"Productos Qu\u00cdmicos (fabricaci\u00d3n, Al Por Mayor)",
    "sg:phone":"+34 944 10 48 56",
    "sg:postcode":"48012",
    "sg:province":"Vizcaya",
    "wof:name":"Quimica Del Jarama S.a.",
    "wof:placetype":"venue"
},
  "geometry": {"coordinates":[-2.9378483295,43.2515945435],"type":"Point"}
}