{
  "type": "Feature",
  "properties": {
    "addr:full":"Carrer de Joan Miro, 40 Mataro Barcelona 08304",
    "addr:housenumber":"40",
    "addr:postcode":"08304",
    "addr:street":"Carrer De Joan Miro",
    "iso:country":"ES",
    "sg:address":"Carrer de Joan Miro, 40",
    "sg:city":"Mataro",
    "sg:orig_category":"Comercio De Piezas De Recambio Y De Accesorios De Veh\u00cdculos, Veh\u00cdculos Industriales",
    "sg:phone":"+34 937 96 18 10",
    "sg:postcode":"08304",
    "sg:province":"Barcelona",
    "wof:name":"Auto Guillermo S.a.",
    "wof:placetype":"venue"
},
  "geometry": {"coordinates":[2.4511818886,41.5500564575],"type":"Point"}
}