{
  "type": "Feature",
  "properties": {
    "addr:full":"Calle de Ramon Y Cajal, 92 Sonseca Toledo 45100",
    "addr:housenumber":"92",
    "addr:postcode":"45100",
    "addr:street":"Calle De Ramon Y Cajal",
    "iso:country":"ES",
    "sg:address":"Calle de Ramon Y Cajal, 92",
    "sg:city":"Sonseca",
    "sg:orig_category":"Cristaler\u00cdas",
    "sg:phone":"+34 925 38 07 14",
    "sg:postcode":"45100",
    "sg:province":"Toledo",
    "wof:name":"Cristason S. L.",
    "wof:placetype":"venue"
},
  "geometry": {"coordinates":[-3.9715600014,39.6809043884],"type":"Point"}
}