{
  "type": "Feature",
  "properties": {
    "addr:full":"Padre Tomas De Burgui, 2 Iru\u00f1a Navarra 31014",
    "addr:housenumber":"2",
    "addr:postcode":"31014",
    "addr:street":"Padre Tomas De Burgui",
    "iso:country":"ES",
    "sg:address":"Padre Tomas De Burgui, 2",
    "sg:city":"Iru\u00f1a",
    "sg:orig_category":"Moquetas, Alfombras (al Por Menor)",
    "sg:phone":"+34 948 12 83 12",
    "sg:postcode":"31014",
    "sg:province":"Navarra",
    "wof:name":"Ramon Brieva Jose Luis",
    "wof:placetype":"venue"
},
  "geometry": {"coordinates":[-1.6460720301,42.830116272],"type":"Point"}
}