{
  "type": "Feature",
  "properties": {
    "addr:full":"Calle de Bernabe Soriano, 13 Jaen Ja\u00e9n 23001",
    "addr:housenumber":"13;jae\u0301n",
    "addr:postcode":"23001",
    "addr:street":"Calle De Bernabe Soriano",
    "iso:country":"ES",
    "sg:address":"Calle de Bernabe Soriano, 13",
    "sg:city":"Jaen",
    "sg:orig_category":"Inmobiliaria (agencias)",
    "sg:phone":"+34 953 24 50 70",
    "sg:postcode":"23001",
    "sg:province":"Ja\u00e9n",
    "wof:name":"Pacheco De Pablo Francisco Javier",
    "wof:placetype":"venue"
},
  "geometry": {"coordinates":[-3.7880754471,37.766582489],"type":"Point"}
}