{
  "type": "Feature",
  "properties": {
    "iso:country":"ES",
    "sg:address":"Aralar, 15",
    "sg:city":"Iru\u00f1a",
    "sg:orig_category":"Imprenta",
    "sg:phone":"+34 948 15 30 60",
    "sg:postcode":"31004",
    "sg:province":"Navarra",
    "wof:name":"Graficas Baja Navarra S.l.",
    "wof:placetype":"venue"
},
  "geometry": {"coordinates":[-1.635226965,42.8135261536],"type":"Point"}
}