{
  "type": "Feature",
  "properties": {
    "iso:country":"ES",
    "sg:address":"Calle de Excelentisima Diputacion, 41",
    "sg:city":"Balsicas",
    "sg:orig_category":"Mec\u00c1nico Del Autom\u00d3vil",
    "sg:phone":"+34 968 58 00 12",
    "sg:postcode":"30591",
    "sg:province":"Murcia",
    "wof:name":"Ruiz Garcia Jose Luis",
    "wof:placetype":"venue"
},
  "geometry": {"coordinates":[-0.9601349831,37.8188285828],"type":"Point"}
}