{
  "type": "Feature",
  "properties": {
    "iso:country":"ES",
    "sg:address":"Pase Delicias, 31",
    "sg:city":"Madrid",
    "sg:orig_category":"Bisuter\u00cda, Joyer\u00cda, Relojer\u00cda (al Por Menor)",
    "sg:phone":"+34 914 67 23 46",
    "sg:postcode":"28045",
    "sg:province":"Madrid",
    "wof:name":"Gracia Sanchez Jose",
    "wof:placetype":"venue"
},
  "geometry": {"coordinates":[-3.6916639805,40.4041404724],"type":"Point"}
}