{
  "type": "Feature",
  "properties": {
    "iso:country":"ES",
    "sg:address":"Ctra. Riudellots, S/n",
    "sg:city":"Cassa Selva",
    "sg:orig_category":"Materias Pl\u00c1sticas: Productos De Consumo Masivo (fabricaci\u00d3n, Al Por Mayor)",
    "sg:phone":"+34 972 46 05 67",
    "sg:postcode":"17244",
    "sg:province":"Girona",
    "sg:website":"www.inplacsa.com",
    "wof:name":"Inplacsa",
    "wof:placetype":"venue"
},
  "geometry": {"coordinates":[2.8574225903,41.8936882019],"type":"Point"}
}