{
  "type": "Feature",
  "properties": {
    "iso:country":"ES",
    "sg:address":"Calle de Lugo, 19",
    "sg:city":"Zaragoza",
    "sg:orig_category":"Electricidad: Instaladores",
    "sg:phone":"+34 976 27 63 01",
    "sg:postcode":"50007",
    "sg:province":"Zaragoza",
    "wof:name":"Mainar Sopesens Fernando",
    "wof:placetype":"venue"
},
  "geometry": {"coordinates":[-0.8854629993,41.6270675659],"type":"Point"}
}