{
  "type": "Feature",
  "properties": {
    "iso:country":"ES",
    "sg:address":"Pase Bachilleres, 2",
    "sg:city":"Toledo",
    "sg:orig_category":"Procuradores",
    "sg:phone":"+34 925 22 11 04",
    "sg:postcode":"45003",
    "sg:province":"Toledo",
    "wof:name":"Gomez De Salazar Garcia Galiano Maria Mercedes",
    "wof:placetype":"venue"
},
  "geometry": {"coordinates":[-4.0256662369,39.8692092896],"type":"Point"}
}