{
  "type": "Feature",
  "properties": {
    "addr:full":"Calle de Comarca Campo Ara\u00d1uelo, S/n Caceres C\u00e1ceres 10001",
    "addr:housenumber":"s",
    "addr:postcode":"10001",
    "addr:street":"Calle De Comarca Campo Aran\u0303Uelo;/ N;Ca\u0301Ceres",
    "iso:country":"ES",
    "sg:address":"Calle de Comarca Campo Ara\u00d1uelo, S/n",
    "sg:city":"Caceres",
    "sg:orig_category":"Asociaciones, Organismos Culturales Y Socioeducativos",
    "sg:phone":"+34 927 23 17 15",
    "sg:postcode":"10001",
    "sg:province":"C\u00e1ceres",
    "wof:name":"Club Social La Sierrilla",
    "wof:placetype":"venue"
},
  "geometry": {"coordinates":[-6.4048948288,39.4812088013],"type":"Point"}
}