{
  "type": "Feature",
  "properties": {
    "iso:country":"ES",
    "sg:address":"Calle de Puentezuelas, 49",
    "sg:city":"Granada",
    "sg:orig_category":"Ropa Para Se\u00d1oras (al Por Menor)",
    "sg:phone":"+34 958 52 10 20",
    "sg:postcode":"18002",
    "sg:province":"Granada",
    "wof:name":"Martinez Mu\u00f1oz Claudia",
    "wof:placetype":"venue"
},
  "geometry": {"coordinates":[-3.6031389236,37.1748504639],"type":"Point"}
}