{
  "type": "Feature",
  "properties": {
    "addr:full":"Carrer de Nou, 14 Vic Barcelona 08500",
    "addr:housenumber":"14",
    "addr:postcode":"08500",
    "addr:street":"Carrer De Nou",
    "iso:country":"ES",
    "sg:address":"Carrer de Nou, 14",
    "sg:city":"Vic",
    "sg:orig_category":"Reposter\u00cdas",
    "sg:phone":"+34 938 86 04 19",
    "sg:postcode":"08500",
    "sg:province":"Barcelona",
    "wof:name":"Anfruns Garriga Manel",
    "wof:placetype":"venue"
},
  "geometry": {"coordinates":[2.2559936047,41.9320297241],"type":"Point"}
}