{
  "type": "Feature",
  "properties": {
    "addr:full":"Calle de Cueva, S/n Tudela Duero Valladolid 47320",
    "addr:postcode":"47320",
    "addr:street":"Calle De Cueva S / N",
    "iso:country":"ES",
    "sg:address":"Calle de Cueva, S/n",
    "sg:city":"Tudela Duero",
    "sg:orig_category":"Hielo Artificial (fabricaci\u00d3n, Distribuci\u00d3n)",
    "sg:phone":"+34 983 52 00 31",
    "sg:postcode":"47320",
    "sg:province":"Valladolid",
    "wof:name":"Helados Chefi S.l.",
    "wof:placetype":"venue"
},
  "geometry": {"coordinates":[-4.585287571,41.5886077881],"type":"Point"}
}