{
  "type": "Feature",
  "properties": {
    "iso:country":"ES",
    "sg:address":"Avda Portugal, 69",
    "sg:city":"Salamanca",
    "sg:orig_category":"Audiovisuales (producci\u00d3n, Edici\u00d3n, Realizaci\u00d3n)",
    "sg:phone":"+34 923 22 07 83",
    "sg:postcode":"37005",
    "sg:province":"Salamanca",
    "wof:name":"Pedro Villar Producciones S.l.",
    "wof:placetype":"venue"
},
  "geometry": {"coordinates":[-5.6591300964,40.9713783264],"type":"Point"}
}