{
  "type": "Feature",
  "properties": {
    "iso:country":"ES",
    "sg:address":"Carrer de Foners, 56",
    "sg:city":"Palma",
    "sg:orig_category":"Bisuteros (fabricaci\u00d3n, Al Por Mayor)",
    "sg:phone":"+34 971 46 58 04",
    "sg:postcode":"07006",
    "sg:province":"Islas Baleares",
    "wof:name":"Sauvage Valentin Hugo",
    "wof:placetype":"venue"
},
  "geometry": {"coordinates":[2.6625659466,39.5673446655],"type":"Point"}
}