{
  "type": "Feature",
  "properties": {
    "addr:full":"Avgd Albufera, De S', 59 Platja De Muro Islas Baleares 07440",
    "addr:postcode":"07440",
    "iso:country":"ES",
    "sg:address":"Avgd Albufera, De S', 59",
    "sg:city":"Platja De Muro",
    "sg:orig_category":"Bazares, Art\u00cdculos De Limpieza Y De Cocina (al Por Menor)",
    "sg:phone":"+34 971 89 27 92",
    "sg:postcode":"07440",
    "sg:province":"Islas Baleares",
    "wof:name":"Monfort Montoya Maria Mercedes",
    "wof:placetype":"venue"
},
  "geometry": {"coordinates":[3.1188130379,39.8013267517],"type":"Point"}
}