{
  "type": "Feature",
  "properties": {
    "addr:full":"Rua Manuel Nu\u00d1ez, 2 Vigo Pontevedra 36203",
    "addr:housenumber":"2",
    "addr:postcode":"36203",
    "addr:street":"Rua Manuel Nun\u0303Ez",
    "iso:country":"ES",
    "sg:address":"Rua Manuel Nu\u00d1ez, 2",
    "sg:city":"Vigo",
    "sg:orig_category":"Centros De Coordinaci\u00d3n",
    "sg:phone":"+34 986 22 41 57",
    "sg:postcode":"36203",
    "sg:province":"Pontevedra",
    "wof:name":"Vitalia Vida S.a.",
    "wof:placetype":"venue"
},
  "geometry": {"coordinates":[-8.7201852798,42.2357139587],"type":"Point"}
}