{
  "type": "Feature",
  "properties": {
    "iso:country":"ES",
    "sg:address":"Calle de Menendez Pelayo, 21",
    "sg:city":"Pozuelos De Calatrava",
    "sg:classifiers":[
        {
            "category":"Taxi",
            "type":"Transportation"
        }
    ],
    "sg:phone":"+34 926 83 20 19",
    "sg:postcode":"13191",
    "sg:province":"Ciudad Real",
    "wof:name":"Sanchez Perez Francisco",
    "wof:placetype":"venue"
},
  "geometry": {"coordinates":[-4.1692070961,38.8977432251],"type":"Point"}
}