{
  "type": "Feature",
  "properties": {
    "iso:country":"ES",
    "sg:address":"Ctra. Nijar, Km. 0014,0",
    "sg:city":"Retamar",
    "sg:orig_category":"Comercio De Carburantes",
    "sg:phone":"+34 950 20 82 40",
    "sg:postcode":"04130",
    "sg:province":"Almer\u00eda",
    "wof:name":"Area De Servicios Retamar S.l.",
    "wof:placetype":"venue"
},
  "geometry": {"coordinates":[-2.30702281,36.8521308899],"type":"Point"}
}