{
  "type": "Feature",
  "properties": {
    "iso:country":"ES",
    "sg:address":"Carrer de Amadeu Torner, 109",
    "sg:city":"Hospitalet Llobregat",
    "sg:orig_category":"Artes Gr\u00c1ficas, Artes Pl\u00c1sticas: Material Y Suministros (al Por Menor)",
    "sg:phone":"+34 934 22 20 20",
    "sg:postcode":"08902",
    "sg:province":"Barcelona",
    "wof:name":"Gambro Healthcare Catalunya S.l.",
    "wof:placetype":"venue"
},
  "geometry": {"coordinates":[2.1217000484,41.3632202148],"type":"Point"}
}