{
  "type": "Feature",
  "properties": {
    "addr:full":"Calle de Historiador Chabas, 6 Javea Alicante 03730",
    "addr:housenumber":"6",
    "addr:postcode":"03730",
    "addr:street":"Calle De Historiador Chabas",
    "iso:country":"ES",
    "sg:address":"Calle de Historiador Chabas, 6",
    "sg:city":"Javea",
    "sg:orig_category":"Caf\u00c9s, Bares, Cervecer\u00cdas",
    "sg:phone":"+34 965 79 66 78",
    "sg:postcode":"03730",
    "sg:province":"Alicante",
    "wof:name":"Diego Y Segarra S.l.",
    "wof:placetype":"venue"
},
  "geometry": {"coordinates":[0.1675200015,38.7913894653],"type":"Point"}
}