{
  "type": "Feature",
  "properties": {
    "addr:full":"Calle de Feria (la), 13 Andujar Ja\u00e9n 23740",
    "addr:housenumber":"13",
    "addr:postcode":"23740",
    "addr:street":"Calle De Feria La",
    "iso:country":"ES",
    "sg:address":"Calle de Feria (la), 13",
    "sg:city":"Andujar",
    "sg:orig_category":"Cr\u00cda De Animales",
    "sg:phone":"+34 953 50 11 42",
    "sg:postcode":"23740",
    "sg:province":"Ja\u00e9n",
    "wof:name":"Flores Sanchez Pedro",
    "wof:placetype":"venue"
},
  "geometry": {"coordinates":[-4.0552492142,38.0370407104],"type":"Point"}
}