{
  "type": "Feature",
  "properties": {
    "iso:country":"ES",
    "sg:address":"Calle de Doctor Monserrat, 18",
    "sg:city":"Valencia",
    "sg:orig_category":"Electrodom\u00c9sticos (fabricaci\u00d3n, Al Por Mayor)",
    "sg:phone":"+34 963 91 85 98",
    "sg:postcode":"46008",
    "sg:province":"Valencia",
    "wof:name":"Representaciones Pico Andres S.l.",
    "wof:placetype":"venue"
},
  "geometry": {"coordinates":[-0.596681416,39.3590736389],"type":"Point"}
}