{
  "type": "Feature",
  "properties": {
    "addr:full":"Carrer de Corsega, 288 Barcelona Barcelona 08008",
    "addr:housenumber":"288",
    "addr:postcode":"08008",
    "addr:street":"Carrer De Corsega",
    "iso:country":"ES",
    "sg:address":"Carrer de Corsega, 288",
    "sg:city":"Barcelona",
    "sg:orig_category":"Asociaciones, Instituciones De Consumidores Y Usuarios",
    "sg:phone":"+34 934 12 63 92",
    "sg:postcode":"08008",
    "sg:province":"Barcelona",
    "wof:name":"Asociacion De Usuarios De Servicios Bancarios",
    "wof:placetype":"venue"
},
  "geometry": {"coordinates":[2.1572780609,41.3949623108],"type":"Point"}
}