{
  "type": "Feature",
  "properties": {
    "addr:full":"Calle de Mar Mediterraneo, 1 Meloneras Las Palmas 35100",
    "addr:housenumber":"1",
    "addr:postcode":"35100",
    "addr:street":"Calle De Mar Mediterraneo;Las Palmas",
    "iso:country":"ES",
    "sg:address":"Calle de Mar Mediterraneo, 1",
    "sg:city":"Meloneras",
    "sg:orig_category":"Ropa Para Se\u00d1oras Y Caballeros (al Por Menor)",
    "sg:phone":"+34 928 14 60 46",
    "sg:postcode":"35100",
    "sg:province":"Las Palmas",
    "wof:name":"Time Progress. S.l.",
    "wof:placetype":"venue"
},
  "geometry": {"coordinates":[-15.6051845551,27.7433929443],"type":"Point"}
}