{
  "type": "Feature",
  "properties": {
    "iso:country":"ES",
    "sg:address":"Calle de Rosa De Luxemburgo, 30",
    "sg:city":"Santa Fe",
    "sg:orig_category":"Muebles",
    "sg:phone":"+34 958 51 11 11",
    "sg:postcode":"18320",
    "sg:province":"Granada",
    "wof:name":"Yassydia S.l.",
    "wof:placetype":"venue"
},
  "geometry": {"coordinates":[-3.7231590748,37.1900215149],"type":"Point"}
}