{
  "type": "Feature",
  "properties": {
    "iso:country":"ES",
    "sg:address":"Carr Ventura Sabater, 1",
    "sg:city":"Begur",
    "sg:orig_category":"Notarios",
    "sg:phone":"+34 972 62 45 16",
    "sg:postcode":"17255",
    "sg:province":"Girona",
    "wof:name":"Quiroga Martinez Maria Del Camino",
    "wof:placetype":"venue"
},
  "geometry": {"coordinates":[3.2071299553,41.9541053772],"type":"Point"}
}