{
  "type": "Feature",
  "properties": {
    "addr:full":"Plaz Espa\u00d1a, 11 Badajoz Badajoz 06002",
    "addr:housenumber":"11",
    "addr:postcode":"06002",
    "addr:street":"Plaz Espan\u0303A",
    "iso:country":"ES",
    "sg:address":"Plaz Espa\u00d1a, 11",
    "sg:city":"Badajoz",
    "sg:orig_category":"Farmacias",
    "sg:phone":"+34 924 22 27 50",
    "sg:postcode":"06002",
    "sg:province":"Badajoz",
    "wof:name":"Lopez Blanco Joaquin",
    "wof:placetype":"venue"
},
  "geometry": {"coordinates":[-6.9704709053,38.8782463074],"type":"Point"}
}