{
  "type": "Feature",
  "properties": {
    "addr:full":"Ctra Badajoz, Km. 0057,1 San Marcos Badajoz 06200",
    "addr:postcode":"06200",
    "addr:street":"Ctra Badajoz Km. 0057,1",
    "iso:country":"ES",
    "sg:address":"Ctra Badajoz, Km. 0057,1",
    "sg:city":"San Marcos",
    "sg:orig_category":"Frutas Y Legumbres Frescas (al Por Mayor)",
    "sg:phone":"+34 924 66 28 13",
    "sg:postcode":"06200",
    "sg:province":"Badajoz",
    "wof:name":"Sociedad Agraria De Transformacion Olivas De Barros",
    "wof:placetype":"venue"
},
  "geometry": {"coordinates":[-6.4123888016,38.6829681396],"type":"Point"}
}