{
  "type": "Feature",
  "properties": {
    "iso:country":"ES",
    "sg:address":"Calle de Francisco Alonso, 5",
    "sg:city":"Elda",
    "sg:orig_category":"Material Y Suministros Para Imprenta E Industrias Gr\u00c1ficas",
    "sg:phone":"+34 966 98 05 58",
    "sg:postcode":"03600",
    "sg:province":"Alicante",
    "wof:name":"Impreselda S.l.",
    "wof:placetype":"venue"
},
  "geometry": {"coordinates":[-0.7903491259,38.4802589417],"type":"Point"}
}