{
  "type": "Feature",
  "properties": {
    "iso:country":"ES",
    "sg:address":"Avda Camino Viejo De Torrent, S/n",
    "sg:city":"Alaquas",
    "sg:orig_category":"Cerrajer\u00cda, Ferrallista",
    "sg:phone":"+34 961 51 90 00",
    "sg:postcode":"46970",
    "sg:province":"Valencia",
    "wof:name":"Tableros Ferrer S.a.",
    "wof:placetype":"venue"
},
  "geometry": {"coordinates":[-0.4578439891,39.4546356201],"type":"Point"}
}