{
  "type": "Feature",
  "properties": {
    "addr:full":"Calle de Nicaragua, 4 Motril Granada 18600",
    "addr:housenumber":"4",
    "addr:postcode":"18600",
    "addr:street":"Calle De Nicaragua",
    "iso:country":"ES",
    "sg:address":"Calle de Nicaragua, 4",
    "sg:city":"Motril",
    "sg:classifiers":[
        {
            "category":"Communications",
            "type":"Services"
        }
    ],
    "sg:phone":"+34 958 60 31 11",
    "sg:postcode":"18600",
    "sg:province":"Granada",
    "sg:tags":[
        "televisiones",
        "y",
        "radio"
    ],
    "sg:website":"www.ondacero.es",
    "wof:name":"Uniprex-onda Cero",
    "wof:placetype":"venue"
},
  "geometry": {"coordinates":[-3.5146739483,36.7440834045],"type":"Point"}
}