{
  "type": "Feature",
  "properties": {
    "addr:full":"Avda Pantano, 25 Anna Valencia 46820",
    "addr:housenumber":"25",
    "addr:postcode":"46820",
    "addr:street":"Avda Pantano",
    "iso:country":"ES",
    "sg:address":"Avda Pantano, 25",
    "sg:city":"Anna",
    "sg:orig_category":"Venta, Alquiler De Toldos",
    "sg:phone":"+34 962 21 10 50",
    "sg:postcode":"46820",
    "sg:province":"Valencia",
    "wof:name":"Lico Podio S.l",
    "wof:placetype":"venue"
},
  "geometry": {"coordinates":[-0.6423419714,39.020942688],"type":"Point"}
}