{
  "type": "Feature",
  "properties": {
    "addr:full":"Ctra. Portugal, Km. 0292,0 Miajadas C\u00e1ceres 10100",
    "addr:postcode":"10100",
    "addr:street":"Ctra. Portugal Km. 0292,0;Ca\u0301Ceres",
    "iso:country":"ES",
    "sg:address":"Ctra. Portugal, Km. 0292,0",
    "sg:city":"Miajadas",
    "sg:orig_category":"Distribuci\u00d3n De Petr\u00d3leo Y Derivados",
    "sg:phone":"+34 927 34 76 06",
    "sg:postcode":"10100",
    "sg:province":"C\u00e1ceres",
    "wof:name":"Estacion De Servicio Elex S.a.",
    "wof:placetype":"venue"
},
  "geometry": {"coordinates":[-5.9082989693,39.1555213928],"type":"Point"}
}