{
  "type": "Feature",
  "properties": {
    "iso:country":"ES",
    "sg:address":"Calle de Madrid, 16",
    "sg:city":"Fuensalida",
    "sg:orig_category":"Promotores Constructores",
    "sg:phone":"+34 925 78 44 14",
    "sg:postcode":"45510",
    "sg:province":"Toledo",
    "wof:name":"Hernandez Hernandez Angel",
    "wof:placetype":"venue"
},
  "geometry": {"coordinates":[-4.2064948082,40.0581855774],"type":"Point"}
}