{
  "type": "Feature",
  "properties": {
    "iso:country":"ES",
    "sg:address":"Calle de Gladiolo, 2",
    "sg:city":"Getafe",
    "sg:orig_category":"Plomeros",
    "sg:phone":"+34 916 81 92 29",
    "sg:postcode":"28903",
    "sg:province":"Madrid",
    "wof:name":"Sideras Instalaciones S.l.",
    "wof:placetype":"venue"
},
  "geometry": {"coordinates":[-3.7253570557,40.316608429],"type":"Point"}
}