{
  "type": "Feature",
  "properties": {
    "iso:country":"ES",
    "sg:address":"Avda Barcelona, S/n",
    "sg:city":"Vinaros",
    "sg:orig_category":"Empresas De Carpinter\u00cda De Madera",
    "sg:phone":"+34 964 45 20 61",
    "sg:postcode":"12500",
    "sg:province":"Castell\u00f3n",
    "wof:name":"Gargallo Orti Valeriano",
    "wof:placetype":"venue"
},
  "geometry": {"coordinates":[0.4745000005,40.4757003784],"type":"Point"}
}