{
  "type": "Feature",
  "properties": {
    "addr:full":"Calle de Guadiana, 14 Madrid Madrid 28002",
    "addr:housenumber":"14",
    "addr:postcode":"madrid;28002",
    "addr:street":"Calle De Guadiana",
    "iso:country":"ES",
    "sg:address":"Calle de Guadiana, 14",
    "sg:city":"Madrid",
    "sg:orig_category":"Barcos",
    "sg:phone":"+34 917 45 19 29",
    "sg:postcode":"28002",
    "sg:province":"Madrid",
    "wof:name":"J.j.ferrer Y Asociados S.l.",
    "wof:placetype":"venue"
},
  "geometry": {"coordinates":[-3.6848158836,40.4480857849],"type":"Point"}
}