{
  "type": "Feature",
  "properties": {
    "addr:full":"Ctra. Nacional 340, Km. 0103,0 Torreblanca Castell\u00f3n 12596",
    "addr:postcode":"12596",
    "addr:street":"Ctra. Nacional 340 Km. 0103,0;Castello\u0301N",
    "iso:country":"ES",
    "sg:address":"Ctra. Nacional 340, Km. 0103,0",
    "sg:city":"Torreblanca",
    "sg:orig_category":"Venta, Montaje De Neum\u00c1ticos",
    "sg:phone":"+34 964 42 10 88",
    "sg:postcode":"12596",
    "sg:province":"Castell\u00f3n",
    "wof:name":"Pueyo Sanmartin Jose Miguel",
    "wof:placetype":"venue"
},
  "geometry": {"coordinates":[0.1960400045,40.2205581665],"type":"Point"}
}