{
  "type": "Feature",
  "properties": {
    "iso:country":"ES",
    "sg:address":"Avda Region Murciana, 113",
    "sg:city":"Carril De La Enera",
    "sg:orig_category":"Delegados, Agentes De Tr\u00c1nsito, Auxiliares De Transporte Internacional",
    "sg:phone":"+34 968 25 73 83",
    "sg:postcode":"30011",
    "sg:province":"Murcia",
    "wof:name":"Martinez Ros E Hijos S.l.",
    "wof:placetype":"venue"
},
  "geometry": {"coordinates":[-1.1055790186,37.9783668518],"type":"Point"}
}