{
  "type": "Feature",
  "properties": {
    "iso:country":"ES",
    "sg:address":"Carrer de Industria, 180",
    "sg:city":"Barcelona",
    "sg:orig_category":"Ingenieros Asesor\u00cda",
    "sg:phone":"+34 934 55 14 20",
    "sg:postcode":"08025",
    "sg:province":"Barcelona",
    "wof:name":"Hipotesis Alternativa",
    "wof:placetype":"venue"
},
  "geometry": {"coordinates":[2.175770998,41.4104804993],"type":"Point"}
}