{
  "type": "Feature",
  "properties": {
    "addr:full":"La Maquinista (ciutat Asuncion), 53 Barcelona Barcelona 08030",
    "addr:housenumber":"53",
    "addr:postcode":"08030",
    "addr:street":"Ciutat Asuncion",
    "iso:country":"ES",
    "sg:address":"La Maquinista (ciutat Asuncion), 53",
    "sg:city":"Barcelona",
    "sg:orig_category":"Zapatos (al Por Menor)",
    "sg:phone":"+34 933 60 82 41",
    "sg:postcode":"08030",
    "sg:province":"Barcelona",
    "sg:website":"www.zhanedifference.com",
    "wof:name":"Zhane Condal S.l.",
    "wof:placetype":"venue"
},
  "geometry": {"coordinates":[2.1966180801,41.4378700256],"type":"Point"}
}