{
  "type": "Feature",
  "properties": {
    "addr:full":"Calle de Gallarraga, 11 Sodupe Vizcaya 48830",
    "addr:housenumber":"11",
    "addr:postcode":"48830",
    "addr:street":"Calle De Gallarraga",
    "iso:country":"ES",
    "sg:address":"Calle de Gallarraga, 11",
    "sg:city":"Sodupe",
    "sg:orig_category":"Sindicatos De Trabajadores",
    "sg:phone":"+34 946 39 83 75",
    "sg:postcode":"48830",
    "sg:province":"Vizcaya",
    "wof:name":"Euzko Langillen Alkartasuna",
    "wof:placetype":"venue"
},
  "geometry": {"coordinates":[-3.0484542847,43.2007598877],"type":"Point"}
}