{
  "type": "Feature",
  "properties": {
    "addr:full":"Av El Textil, 75 Ontinyent Valencia 46870",
    "addr:housenumber":"75",
    "addr:postcode":"46870",
    "addr:street":"Av El Textil",
    "iso:country":"ES",
    "sg:address":"Av El Textil, 75",
    "sg:city":"Ontinyent",
    "sg:orig_category":"Art\u00cdculos De Limpieza Y De Cocina (fabricaci\u00d3n, Al Por Mayor)",
    "sg:phone":"+34 962 91 19 57",
    "sg:postcode":"46870",
    "sg:province":"Valencia",
    "sg:website":"www.mopatex.com",
    "wof:name":"Mopatex S.a.",
    "wof:placetype":"venue"
},
  "geometry": {"coordinates":[-0.597375989,38.8257751465],"type":"Point"}
}