{
  "type": "Feature",
  "properties": {
    "iso:country":"ES",
    "sg:address":"Calle de San Juan, 6",
    "sg:city":"Oviedo",
    "sg:orig_category":"Hoteles",
    "sg:phone":"+34 985 22 08 40",
    "sg:postcode":"33003",
    "sg:province":"Asturias",
    "wof:name":"Hijos De Serafin Garcia Garcia S.l.",
    "wof:placetype":"venue"
},
  "geometry": {"coordinates":[-5.8421068192,43.3615722656],"type":"Point"}
}