{
  "type": "Feature",
  "properties": {
    "addr:full":"Calle de Tenderina, 44 Oviedo Asturias 33010",
    "addr:housenumber":"44",
    "addr:postcode":"33010",
    "addr:street":"Calle De Tenderina",
    "iso:country":"ES",
    "sg:address":"Calle de Tenderina, 44",
    "sg:city":"Oviedo",
    "sg:orig_category":"Alquiler De V\u00cddeo",
    "sg:phone":"+34 985 20 10 65",
    "sg:postcode":"33010",
    "sg:province":"Asturias",
    "wof:name":"Cesar Luis Gonzalez Mendez Y Belen Gonzalez Granda Cdad.",
    "wof:placetype":"venue"
},
  "geometry": {"coordinates":[-5.8349328041,43.3646736145],"type":"Point"}
}