{
  "type": "Feature",
  "properties": {
    "iso:country":"ES",
    "sg:address":"Carrer de Industria, 124",
    "sg:city":"Barcelona",
    "sg:orig_category":"Promotores Constructores",
    "sg:phone":"+34 934 55 78 62",
    "sg:postcode":"08025",
    "sg:province":"Barcelona",
    "wof:name":"Quadreny I Jaume Construccions S.l.",
    "wof:placetype":"venue"
},
  "geometry": {"coordinates":[2.1725540161,41.4079704285],"type":"Point"}
}