{
  "type": "Feature",
  "properties": {
    "addr:full":"Psaj Olmedo, S/n Zamora Zamora 49015",
    "addr:housenumber":"s",
    "addr:postcode":"49015",
    "addr:street":"/ N",
    "iso:country":"ES",
    "sg:address":"Psaj Olmedo, S/n",
    "sg:city":"Zamora",
    "sg:orig_category":"Panader\u00cdas, Panader\u00cdas",
    "sg:phone":"+34 980 53 30 35",
    "sg:postcode":"49015",
    "sg:province":"Zamora",
    "wof:name":"Lucas Martinez Maria Transito",
    "wof:placetype":"venue"
},
  "geometry": {"coordinates":[-5.7457342148,41.5033302307],"type":"Point"}
}