{
  "type": "Feature",
  "properties": {
    "iso:country":"ES",
    "sg:address":"Calle de Canovas Del Castillo, 28",
    "sg:city":"Solana",
    "sg:orig_category":"Cristaler\u00cdas",
    "sg:phone":"+34 926 63 51 05",
    "sg:postcode":"13240",
    "sg:province":"Ciudad Real",
    "wof:name":"Solcristal Instalaciones S.l.",
    "wof:placetype":"venue"
},
  "geometry": {"coordinates":[-3.2335603237,38.9428710938],"type":"Point"}
}