{
  "type": "Feature",
  "properties": {
    "iso:country":"ES",
    "sg:address":"Carrer de Magi Albert Cassanyes, S/n",
    "sg:city":"Sitges",
    "sg:orig_category":"Ropa Para Se\u00d1oras Y Caballeros (al Por Menor)",
    "sg:phone":"+34 938 11 12 36",
    "sg:postcode":"08870",
    "sg:province":"Barcelona",
    "wof:name":"Papia Scp",
    "wof:placetype":"venue"
},
  "geometry": {"coordinates":[1.8035449982,41.2452392578],"type":"Point"}
}