{
  "type": "Feature",
  "properties": {
    "addr:full":"Mercat Sants, S/n Barcelona Barcelona 08014",
    "addr:housenumber":"s / n",
    "addr:postcode":"08014",
    "iso:country":"ES",
    "sg:address":"Mercat Sants, S/n",
    "sg:city":"Barcelona",
    "sg:orig_category":"Carnicer\u00cdas, Carnicer\u00cdas",
    "sg:phone":"+34 934 91 50 22",
    "sg:postcode":"08014",
    "sg:province":"Barcelona",
    "wof:name":"Gomez Martinez Carme",
    "wof:placetype":"venue"
},
  "geometry": {"coordinates":[2.1388864517,41.375125885],"type":"Point"}
}