{
  "type": "Feature",
  "properties": {
    "iso:country":"ES",
    "sg:address":"Calle de Joaquin Lorenzo, 50",
    "sg:city":"Madrid",
    "sg:orig_category":"Tintes (fabricaci\u00d3n, Al Por Mayor)",
    "sg:phone":"+34 913 16 95 14",
    "sg:postcode":"28035",
    "sg:province":"Madrid",
    "wof:name":"Morla Mu\u00f1iz Emigdio",
    "wof:placetype":"venue"
},
  "geometry": {"coordinates":[-3.7286839485,40.474609375],"type":"Point"}
}