{
  "type": "Feature",
  "properties": {
    "addr:full":"Plaz San Nicolas, 22 Avila \u00c1vila 05002",
    "addr:housenumber":"22",
    "addr:postcode":"05002",
    "addr:street":"Plaz San Nicolas;A\u0301Vila",
    "iso:country":"ES",
    "sg:address":"Plaz San Nicolas, 22",
    "sg:city":"Avila",
    "sg:orig_category":"Asesor\u00cda Fiscal Y Jur\u00cddica",
    "sg:phone":"+34 920 21 35 97",
    "sg:postcode":"05002",
    "sg:province":"\u00c1vila",
    "wof:name":"Gestisegur Avila 2005 S.l.",
    "wof:placetype":"venue"
},
  "geometry": {"coordinates":[-4.7018289566,40.6530914307],"type":"Point"}
}