{
  "type": "Feature",
  "properties": {
    "iso:country":"ES",
    "sg:address":"Carrer de Balmes, 177",
    "sg:city":"Barcelona",
    "sg:orig_category":"Centros Empresariales",
    "sg:phone":"+34 932 38 42 78",
    "sg:postcode":"08006",
    "sg:province":"Barcelona",
    "wof:name":"Bauparquet S.l.",
    "wof:placetype":"venue"
},
  "geometry": {"coordinates":[2.1534090042,41.3961677551],"type":"Point"}
}