{
  "type": "Feature",
  "properties": {
    "addr:full":"Ctra Torrejon (de), Km. 0018,0 Ajalvir Madrid 28864",
    "addr:postcode":"28864",
    "addr:street":"Ctra Torrejon De Km. 0018,0",
    "iso:country":"ES",
    "sg:address":"Ctra Torrejon (de), Km. 0018,0",
    "sg:city":"Ajalvir",
    "sg:orig_category":"Maquinaria Para Industrias Diversas",
    "sg:phone":"+34 918 84 45 31",
    "sg:postcode":"28864",
    "sg:province":"Madrid",
    "sg:website":"www.implementos.com",
    "wof:name":"Implementos S. A.",
    "wof:placetype":"venue"
},
  "geometry": {"coordinates":[-3.4813530445,40.5243835449],"type":"Point"}
}