{
  "type": "Feature",
  "properties": {
    "addr:full":"Calle de Gran Via De Agustin Arguelles, S/n Ribadesella Asturias 33560",
    "addr:housenumber":"s / n",
    "addr:postcode":"33560",
    "addr:street":"Calle De Gran Via De Agustin Arguelles",
    "iso:country":"ES",
    "sg:address":"Calle de Gran Via De Agustin Arguelles, S/n",
    "sg:city":"Ribadesella",
    "sg:orig_category":"Carnicer\u00cdas, Carnicer\u00cdas",
    "sg:phone":"+34 985 85 76 26",
    "sg:postcode":"33560",
    "sg:province":"Asturias",
    "wof:name":"Aramburu Campillo Emiliano",
    "wof:placetype":"venue"
},
  "geometry": {"coordinates":[-5.0586709976,43.4622459412],"type":"Point"}
}