{
  "type": "Feature",
  "properties": {
    "addr:full":"Pol Ind El Portal, S/n Jerez C\u00e1diz 11408",
    "addr:housenumber":"s",
    "addr:postcode":"11408",
    "addr:street":"El Portal;/ N",
    "iso:country":"ES",
    "sg:address":"Pol Ind El Portal, S/n",
    "sg:city":"Jerez",
    "sg:orig_category":"Transportes Internacionales",
    "sg:phone":"+34 956 14 38 49",
    "sg:postcode":"11408",
    "sg:province":"C\u00e1diz",
    "sg:website":"www.tranimarsa.com",
    "wof:name":"Transportes Nicolas Martin S.a.",
    "wof:placetype":"venue"
},
  "geometry": {"coordinates":[-6.1592831612,36.6686592102],"type":"Point"}
}