{
  "type": "Feature",
  "properties": {
    "iso:country":"ES",
    "sg:address":"Carrer de Enric Granados, 112",
    "sg:city":"Barcelona",
    "sg:orig_category":"Artesan\u00cda",
    "sg:phone":"+34 932 37 59 78",
    "sg:postcode":"08008",
    "sg:province":"Barcelona",
    "wof:name":"Spiegel Martin Rosa Maria",
    "wof:placetype":"venue"
},
  "geometry": {"coordinates":[2.1545100212,41.3939437866],"type":"Point"}
}