{
  "type": "Feature",
  "properties": {
    "iso:country":"ES",
    "sg:address":"Carrer de Barcelona, 27",
    "sg:city":"Gava",
    "sg:orig_category":"Transformaci\u00d3n De Materias Pl\u00c1sticas",
    "sg:phone":"+34 936 38 17 61",
    "sg:postcode":"08850",
    "sg:province":"Barcelona",
    "wof:name":"Complementos Sanitarios S.a.",
    "wof:placetype":"venue"
},
  "geometry": {"coordinates":[2.0055398941,41.2995185852],"type":"Point"}
}