{
  "type": "Feature",
  "properties": {
    "addr:full":"Poligono Ind. El Zarrin, S/n Espina Asturias 33891",
    "addr:housenumber":"s / n",
    "addr:postcode":"33891",
    "addr:street":"Poligono Ind. El Zarrin",
    "iso:country":"ES",
    "sg:address":"Poligono Ind. El Zarrin, S/n",
    "sg:city":"Espina",
    "sg:orig_category":"Material Y Suministros Para Veterinarios",
    "sg:phone":"+34 985 83 72 34",
    "sg:postcode":"33891",
    "sg:province":"Asturias",
    "wof:name":"Agricola Y Veterinaria Falo Sl",
    "wof:placetype":"venue"
},
  "geometry": {"coordinates":[-5.9832577705,43.2504386902],"type":"Point"}
}