{
  "type": "Feature",
  "properties": {
    "iso:country":"ES",
    "sg:address":"Iru\u00d1eko Etorbidea, Km. 0038,0",
    "sg:city":"Arbizu",
    "sg:orig_category":"Venta, Instalaci\u00d3n De Cocinas",
    "sg:phone":"+34 948 46 05 81",
    "sg:postcode":"31839",
    "sg:province":"Navarra",
    "wof:name":"Izar-ondo S. L.",
    "wof:placetype":"venue"
},
  "geometry": {"coordinates":[-2.0385990143,42.9161338806],"type":"Point"}
}