{
  "type": "Feature",
  "properties": {
    "iso:country":"ES",
    "sg:address":"Calle de Santa Maria Micaela, 6",
    "sg:city":"Valencia",
    "sg:orig_category":"Peluquer\u00cdas",
    "sg:phone":"+34 963 85 09 43",
    "sg:postcode":"46008",
    "sg:province":"Valencia",
    "wof:name":"Jarques Pel S.l.",
    "wof:placetype":"venue"
},
  "geometry": {"coordinates":[-0.3915320039,39.4724349976],"type":"Point"}
}