{
  "type": "Feature",
  "properties": {
    "iso:country":"ES",
    "sg:address":"Calle de Principe Felipe, 7",
    "sg:city":"Fuensanta Martos",
    "sg:orig_category":"Papeler\u00cdas, Librer\u00cdas",
    "sg:phone":"+34 953 56 51 53",
    "sg:postcode":"23610",
    "sg:province":"Ja\u00e9n",
    "wof:name":"Espinosa Luque Francisco",
    "wof:placetype":"venue"
},
  "geometry": {"coordinates":[-3.9063050747,37.6471443176],"type":"Point"}
}