{
  "type": "Feature",
  "properties": {
    "addr:full":"Calle de Clara Del Rey, 22 Madrid Madrid 28002",
    "addr:housenumber":"22",
    "addr:postcode":"madrid;28002",
    "addr:street":"Calle De Clara Del Rey",
    "iso:country":"ES",
    "sg:address":"Calle de Clara Del Rey, 22",
    "sg:city":"Madrid",
    "sg:orig_category":"Desinfecci\u00d3n, Desinsectaci\u00d3n, Desratizaci\u00d3n",
    "sg:phone":"+34 914 13 70 07",
    "sg:postcode":"28002",
    "sg:province":"Madrid",
    "wof:name":"Tecmena S.l.",
    "wof:placetype":"venue"
},
  "geometry": {"coordinates":[-3.6708700657,40.441860199],"type":"Point"}
}