{
  "type": "Feature",
  "properties": {
    "iso:country":"ES",
    "sg:address":"Avda Jose Barrionuevo Pe\u00d1a, 52",
    "sg:city":"Berja",
    "sg:orig_category":"Inmobiliaria (agencias)",
    "sg:phone":"+34 950 49 11 36",
    "sg:postcode":"04760",
    "sg:province":"Almer\u00eda",
    "wof:name":"Escamilla Sanchez Manuel",
    "wof:placetype":"venue"
},
  "geometry": {"coordinates":[-2.9436490536,36.8405075073],"type":"Point"}
}