{
  "type": "Feature",
  "properties": {
    "addr:full":"Calle de Gran Via, 12 Cehegin Murcia 30430",
    "addr:housenumber":"12",
    "addr:postcode":"30430",
    "addr:street":"Calle De Gran Via",
    "iso:country":"ES",
    "sg:address":"Calle de Gran Via, 12",
    "sg:city":"Cehegin",
    "sg:orig_category":"Servicios De Telecomunicaciones",
    "sg:phone":"+34 968 74 14 31",
    "sg:postcode":"30430",
    "sg:province":"Murcia",
    "wof:name":"Eurotel Sur",
    "wof:placetype":"venue"
},
  "geometry": {"coordinates":[-1.7976038456,38.0933990479],"type":"Point"}
}