{
  "type": "Feature",
  "properties": {
    "addr:full":"Calle de Real, 8 Corral Almaguer Toledo 45880",
    "addr:housenumber":"8",
    "addr:postcode":"45880",
    "addr:street":"Calle De Real",
    "iso:country":"ES",
    "sg:address":"Calle de Real, 8",
    "sg:city":"Corral Almaguer",
    "sg:orig_category":"Electrodom\u00c9sticos (al Por Menor)",
    "sg:phone":"+34 925 19 12 26",
    "sg:postcode":"45880",
    "sg:province":"Toledo",
    "wof:name":"Electrodomesticos De La Torre Soto S.l.",
    "wof:placetype":"venue"
},
  "geometry": {"coordinates":[-3.171765089,39.7648849487],"type":"Point"}
}