{
  "type": "Feature",
  "properties": {
    "addr:full":"Pla\u00c7 Historiador Llado I Ferragut, 3 Salines Islas Baleares 07640",
    "addr:housenumber":"3",
    "addr:postcode":"07640",
    "addr:street":"Ferragut",
    "iso:country":"ES",
    "sg:address":"Pla\u00c7 Historiador Llado I Ferragut, 3",
    "sg:city":"Salines",
    "sg:orig_category":"Quincaller\u00cda (al Por Menor)",
    "sg:phone":"+34 971 64 94 67",
    "sg:postcode":"07640",
    "sg:province":"Islas Baleares",
    "wof:name":"Sanchez Cozar Pascual",
    "wof:placetype":"venue"
},
  "geometry": {"coordinates":[3.0506649017,39.3386764526],"type":"Point"}
}