{
  "type": "Feature",
  "properties": {
    "addr:full":"Calle de Kareaga Goikoa, 20 Basauri Vizcaya 48970",
    "addr:housenumber":"20",
    "addr:postcode":"48970",
    "addr:street":"Calle De Kareaga Goikoa",
    "iso:country":"ES",
    "sg:address":"Calle de Kareaga Goikoa, 20",
    "sg:city":"Basauri",
    "sg:orig_category":"Bisuter\u00cda, Joyer\u00cda, Relojer\u00cda (al Por Menor)",
    "sg:phone":"+34 944 26 40 76",
    "sg:postcode":"48970",
    "sg:province":"Vizcaya",
    "wof:name":"Taller Joyeria Juan",
    "wof:placetype":"venue"
},
  "geometry": {"coordinates":[-2.8958480358,43.2380638123],"type":"Point"}
}