{
  "type": "Feature",
  "properties": {
    "addr:full":"Calle de Viriato, 22 Madrid Madrid 28010",
    "addr:housenumber":"22",
    "addr:postcode":"madrid;28010",
    "addr:street":"Calle De Viriato",
    "iso:country":"ES",
    "sg:address":"Calle de Viriato, 22",
    "sg:city":"Madrid",
    "sg:orig_category":"Agencias Y Asesores De Publicidad",
    "sg:phone":"+34 913 19 83 28",
    "sg:postcode":"28010",
    "sg:province":"Madrid",
    "wof:name":"Central De Producers Madrid S.l.",
    "wof:placetype":"venue"
},
  "geometry": {"coordinates":[-3.7015779018,40.4357719421],"type":"Point"}
}