{
  "type": "Feature",
  "properties": {
    "iso:country":"ES",
    "sg:address":"Calle de Avila, 6",
    "sg:city":"Bilbao",
    "sg:orig_category":"Quincaller\u00cda (al Por Menor)",
    "sg:phone":"+34 944 10 26 38",
    "sg:postcode":"48012",
    "sg:province":"Vizcaya",
    "wof:name":"Agustina Marquez Perez",
    "wof:placetype":"venue"
},
  "geometry": {"coordinates":[-2.9395577908,43.2569580078],"type":"Point"}
}