{
  "type": "Feature",
  "properties": {
    "iso:country":"ES",
    "sg:address":"Avda Carabanchel Alto, 126",
    "sg:city":"Madrid",
    "sg:orig_category":"Mec\u00c1nico Del Autom\u00d3vil",
    "sg:phone":"+34 915 08 89 69",
    "sg:postcode":"28044",
    "sg:province":"Madrid",
    "wof:name":"Victor Zumajo Feliciano",
    "wof:placetype":"venue"
},
  "geometry": {"coordinates":[-3.753549099,40.3662109375],"type":"Point"}
}