{
  "type": "Feature",
  "properties": {
    "iso:country":"ES",
    "sg:address":"Carrer de Arago, 69",
    "sg:city":"Barcelona",
    "sg:orig_category":"Renovaci\u00d3n Inmobiliaria",
    "sg:phone":"+34 932 26 60 53",
    "sg:postcode":"08015",
    "sg:province":"Barcelona",
    "wof:name":"Construcciones Novisa S.c.p.",
    "wof:placetype":"venue"
},
  "geometry": {"coordinates":[2.1498930454,41.3810844421],"type":"Point"}
}