{
  "type": "Feature",
  "properties": {
    "addr:full":"Avda Cuenca (de), 65 Villarta Cuenca 16280",
    "addr:housenumber":"65",
    "addr:postcode":"16280",
    "addr:street":"Avda Cuenca De",
    "iso:country":"ES",
    "sg:address":"Avda Cuenca (de), 65",
    "sg:city":"Villarta",
    "sg:orig_category":"Empresas De Carpinter\u00cda De Madera",
    "sg:phone":"+34 962 18 93 17",
    "sg:postcode":"16280",
    "sg:province":"Cuenca",
    "wof:name":"Miguel Honrubia Pedro Esteban",
    "wof:placetype":"venue"
},
  "geometry": {"coordinates":[-1.651698947,39.4426307678],"type":"Point"}
}