{
  "type": "Feature",
  "properties": {
    "addr:full":"Crt Montealegre, S/n Bonete Albacete 02691",
    "addr:housenumber":"s / n",
    "addr:postcode":"02691",
    "addr:street":"Crt Montealegre",
    "iso:country":"ES",
    "sg:address":"Crt Montealegre, S/n",
    "sg:city":"Bonete",
    "sg:orig_category":"Productores Recolectores, Venta Directa De Vinos",
    "sg:phone":"+34 967 33 40 27",
    "sg:postcode":"02691",
    "sg:province":"Albacete",
    "wof:name":"Cooperativa Del Campo Vinicola",
    "wof:placetype":"venue"
},
  "geometry": {"coordinates":[-1.3362489939,38.8742408752],"type":"Point"}
}