{
  "type": "Feature",
  "properties": {
    "iso:country":"ES",
    "sg:address":"Luga Pino (el), 128",
    "sg:city":"Perdoma",
    "sg:orig_category":"Centros Empresariales",
    "sg:phone":"+34 922 30 82 70",
    "sg:postcode":"38315",
    "sg:province":"Santa Cruz De Tenerife",
    "wof:name":"Labrador Hernandez Francisco",
    "wof:placetype":"venue"
},
  "geometry": {"coordinates":[-16.5055618286,28.3659114838],"type":"Point"}
}