{
  "type": "Feature",
  "properties": {
    "addr:full":"Calle de Longuera (la), 29 Longuera Santa Cruz De Tenerife 38418",
    "addr:housenumber":"29",
    "addr:postcode":"38418",
    "addr:street":"Calle De Longuera La",
    "iso:country":"ES",
    "sg:address":"Calle de Longuera (la), 29",
    "sg:city":"Longuera",
    "sg:orig_category":"Confiter\u00cdas, Chocolater\u00cdas (al Por Menor)",
    "sg:phone":"+34 922 36 33 98",
    "sg:postcode":"38418",
    "sg:province":"Santa Cruz De Tenerife",
    "wof:name":"Morgana Viajes, S.l.",
    "wof:placetype":"venue"
},
  "geometry": {"coordinates":[-16.577249527,28.3975143433],"type":"Point"}
}