{
  "type": "Feature",
  "properties": {
    "addr:full":"Carr Nou, 22 S. Julia Llor Girona 17164",
    "addr:housenumber":"22",
    "addr:postcode":"17164",
    "addr:street":"Carr Nou;S. Julia Llor",
    "iso:country":"ES",
    "sg:address":"Carr Nou, 22",
    "sg:city":"S. Julia Llor",
    "sg:orig_category":"Empresas De Desmonte",
    "sg:phone":"+34 972 42 08 69",
    "sg:postcode":"17164",
    "sg:province":"Girona",
    "wof:name":"Soler Berenguer Pedro",
    "wof:placetype":"venue"
},
  "geometry": {"coordinates":[2.6612849236,41.9692802429],"type":"Point"}
}