{
  "type": "Feature",
  "properties": {
    "addr:full":"Ctr. Matas Verdes, Km. 0000,8 S. Clemente Cuenca 16600",
    "addr:postcode":"16600",
    "addr:street":"Verdes Km. 0000,8 S. Clemente Cuenca",
    "iso:country":"ES",
    "sg:address":"Ctr. Matas Verdes, Km. 0000,8",
    "sg:city":"S. Clemente",
    "sg:orig_category":"Negocio De Materiales De Construcci\u00d3n",
    "sg:phone":"+34 969 30 02 44",
    "sg:postcode":"16600",
    "sg:province":"Cuenca",
    "wof:name":"Bloques Molero Ruiz S.l.",
    "wof:placetype":"venue"
},
  "geometry": {"coordinates":[-2.4270188808,39.3993186951],"type":"Point"}
}