{
  "type": "Feature",
  "properties": {
    "addr:full":"Calle de Hospital, 4 Tembleque Toledo 45780",
    "addr:housenumber":"4",
    "addr:postcode":"45780",
    "addr:street":"Calle De Hospital",
    "iso:country":"ES",
    "sg:address":"Calle de Hospital, 4",
    "sg:city":"Tembleque",
    "sg:orig_category":"Cajas De Ahorro",
    "sg:phone":"+34 925 14 50 31",
    "sg:postcode":"45780",
    "sg:province":"Toledo",
    "wof:name":"Caja De Ahorros De Castilla La Mancha",
    "wof:placetype":"venue"
},
  "geometry": {"coordinates":[-3.5054628849,39.6958885193],"type":"Point"}
}