{
  "type": "Feature",
  "properties": {
    "iso:country":"ES",
    "sg:address":"Calle de Rosa Luxemburgo, S/n",
    "sg:city":"Madrid",
    "sg:orig_category":"Asesor\u00cda Fiscal Y Jur\u00cddica",
    "sg:phone":"+34 913 07 01 34",
    "sg:postcode":"28023",
    "sg:province":"Madrid",
    "wof:name":"Aseconfis Consultores S.l",
    "wof:placetype":"venue"
},
  "geometry": {"coordinates":[-3.7739014626,40.4504852295],"type":"Point"}
}