{
  "type": "Feature",
  "properties": {
    "addr:full":"Rua Ramon Gonzalez, 17 Porri\u00f1o Pontevedra 36400",
    "addr:housenumber":"17",
    "addr:postcode":"36400",
    "addr:street":"Rua Ramon Gonzalez",
    "iso:country":"ES",
    "sg:address":"Rua Ramon Gonzalez, 17",
    "sg:city":"Porri\u00f1o",
    "sg:orig_category":"Droguer\u00cdas (al Por Menor)",
    "sg:phone":"+34 986 33 68 07",
    "sg:postcode":"36400",
    "sg:province":"Pontevedra",
    "wof:name":"Solleiro Alvarez Maria De Las Mercedes",
    "wof:placetype":"venue"
},
  "geometry": {"coordinates":[-8.6211462021,42.1611289978],"type":"Point"}
}