{
  "type": "Feature",
  "properties": {
    "iso:country":"ES",
    "sg:address":"Carrer de Pardo, 4",
    "sg:city":"Barcelona",
    "sg:orig_category":"Farmacias",
    "sg:phone":"+34 933 52 60 58",
    "sg:postcode":"08027",
    "sg:province":"Barcelona",
    "wof:name":"Jorba Ylla Maria Antonia",
    "wof:placetype":"venue"
},
  "geometry": {"coordinates":[2.1826159954,41.4258575439],"type":"Point"}
}