{
  "type": "Feature",
  "properties": {
    "iso:country":"ES",
    "sg:address":"Calle de Villaviciosa, 28",
    "sg:city":"Madrid",
    "sg:orig_category":"Droguer\u00cdas (al Por Menor)",
    "sg:phone":"+34 917 11 14 76",
    "sg:postcode":"28024",
    "sg:province":"Madrid",
    "wof:name":"V Coronado E Hijos S. A.",
    "wof:placetype":"venue"
},
  "geometry": {"coordinates":[-3.7688291073,40.3979492188],"type":"Point"}
}