{
  "type": "Feature",
  "properties": {
    "addr:full":"Calle de Candeleria, 18 Sevilla Sevilla 41006",
    "addr:housenumber":"18",
    "addr:postcode":"41006",
    "addr:street":"Calle De Candeleria",
    "iso:country":"ES",
    "sg:address":"Calle de Candeleria, 18",
    "sg:city":"Sevilla",
    "sg:orig_category":"Estancos",
    "sg:phone":"+34 954 63 30 00",
    "sg:postcode":"41006",
    "sg:province":"Sevilla",
    "wof:name":"Martin Trigo Fernando Manuel",
    "wof:placetype":"venue"
},
  "geometry": {"coordinates":[-5.9538903236,37.3819541931],"type":"Point"}
}