{
  "type": "Feature",
  "properties": {
    "iso:country":"ES",
    "sg:address":"Calle de Escuelas Nuevas, 2",
    "sg:city":"Villamayor",
    "sg:orig_category":"Electricidad (montaje, Ensamblaje De Componentes)",
    "sg:phone":"+34 976 58 95 62",
    "sg:postcode":"50162",
    "sg:province":"Zaragoza",
    "wof:name":"Mayoral Fernando Ezequiel",
    "wof:placetype":"venue"
},
  "geometry": {"coordinates":[-0.7715489864,41.6864700317],"type":"Point"}
}