{
  "type": "Feature",
  "properties": {
    "addr:full":"Calle de Ronda, 52 Fuentesauco Zamora 49400",
    "addr:housenumber":"52",
    "addr:postcode":"49400",
    "addr:street":"Calle De Ronda;Zamora",
    "iso:country":"ES",
    "sg:address":"Calle de Ronda, 52",
    "sg:city":"Fuentesauco",
    "sg:orig_category":"Empresas De Carpinter\u00cda De Madera",
    "sg:phone":"+34 980 60 04 46",
    "sg:postcode":"49400",
    "sg:province":"Zamora",
    "wof:name":"Juanes Corrales Pablo",
    "wof:placetype":"venue"
},
  "geometry": {"coordinates":[-5.4998059273,41.2299461365],"type":"Point"}
}