{
  "type": "Feature",
  "properties": {
    "addr:full":"Barr Pacios, 53 Toiriz Lugo 27593",
    "addr:housenumber":"53",
    "addr:postcode":"27593",
    "addr:street":"Pacios",
    "iso:country":"ES",
    "sg:address":"Barr Pacios, 53",
    "sg:city":"Toiriz",
    "sg:orig_category":"Alquiler De Veh\u00cdculos: Turismos Y Utilitarios",
    "sg:phone":"+34 982 45 24 20",
    "sg:postcode":"27593",
    "sg:province":"Lugo",
    "wof:name":"Gil-quiroga Alvarez Antonio",
    "wof:placetype":"venue"
},
  "geometry": {"coordinates":[-7.5966382027,42.5668106079],"type":"Point"}
}