{
  "type": "Feature",
  "properties": {
    "addr:full":"Calle de Doctor Vicente Zaragoza, 73 Valencia Valencia 46020",
    "addr:housenumber":"73",
    "addr:postcode":"46020",
    "addr:street":"Calle De Doctor Vicente Zaragoza",
    "iso:country":"ES",
    "sg:address":"Calle de Doctor Vicente Zaragoza, 73",
    "sg:city":"Valencia",
    "sg:orig_category":"Restaurantes: Restauraci\u00d3n R\u00c1pida Y Autoservicio",
    "sg:phone":"+34 963 93 50 19",
    "sg:postcode":"46020",
    "sg:province":"Valencia",
    "wof:name":"Castellano Guillen Manuel",
    "wof:placetype":"venue"
},
  "geometry": {"coordinates":[-0.3584772944,39.4837417603],"type":"Point"}
}