{
  "type": "Feature",
  "properties": {
    "addr:full":"Florent, 1 Confrides Alicante 03817",
    "addr:housenumber":"1",
    "addr:postcode":"03817",
    "addr:street":"Florent",
    "iso:country":"ES",
    "sg:address":"Florent, 1",
    "sg:city":"Confrides",
    "sg:orig_category":"Pintores",
    "sg:phone":"+34 965 88 59 13",
    "sg:postcode":"03817",
    "sg:province":"Alicante",
    "wof:name":"Carrasco Baeza Juan Manuel",
    "wof:placetype":"venue"
},
  "geometry": {"coordinates":[-0.271389991,38.6844902039],"type":"Point"}
}