{
  "type": "Feature",
  "properties": {
    "addr:full":"Calle de Jose Ortega Y Gasset, 43 Madrid Madrid 28006",
    "addr:housenumber":"43",
    "addr:postcode":"madrid;28006",
    "addr:street":"Calle De Jose Ortega Y Gasset",
    "iso:country":"ES",
    "sg:address":"Calle de Jose Ortega Y Gasset, 43",
    "sg:city":"Madrid",
    "sg:orig_category":"Agencias Y Asesores De Publicidad",
    "sg:phone":"+34 913 09 60 23",
    "sg:postcode":"28006",
    "sg:province":"Madrid",
    "wof:name":"Open Imagen S.l.",
    "wof:placetype":"venue"
},
  "geometry": {"coordinates":[-3.6779689789,40.4301528931],"type":"Point"}
}