{
  "type": "Feature",
  "properties": {
    "iso:country":"ES",
    "sg:address":"Ctra Zorrotza-kastrexana, 34",
    "sg:city":"Bilbao",
    "sg:orig_category":"Panader\u00cdas, Panader\u00cdas",
    "sg:phone":"+34 944 41 09 71",
    "sg:postcode":"48013",
    "sg:province":"Vizcaya",
    "wof:name":"Panificadora Saiz Hermanos S.l.",
    "wof:placetype":"venue"
},
  "geometry": {"coordinates":[-2.9740419388,43.2735786438],"type":"Point"}
}