{
  "type": "Feature",
  "properties": {
    "iso:country":"ES",
    "sg:address":"Carr Gabriel Miro, 12",
    "sg:city":"Alfas Pi",
    "sg:orig_category":"Chapister\u00cda",
    "sg:phone":"+34 965 88 82 17",
    "sg:postcode":"03580",
    "sg:province":"Alicante",
    "wof:name":"Guijarro Nadal Lorenzo Andres",
    "wof:placetype":"venue"
},
  "geometry": {"coordinates":[-0.1004452035,38.578327179],"type":"Point"}
}