{
  "type": "Feature",
  "properties": {
    "iso:country":"ES",
    "sg:address":"Huesca (p I Prado), S/n",
    "sg:city":"Merida",
    "sg:orig_category":"Empresas De Carpinter\u00cda Met\u00c1lica",
    "sg:phone":"+34 924 37 80 79",
    "sg:postcode":"06800",
    "sg:province":"Badajoz",
    "wof:name":"Metalicas Galpe S.l.",
    "wof:placetype":"venue"
},
  "geometry": {"coordinates":[-6.3863339424,38.9282112122],"type":"Point"}
}