{
  "type": "Feature",
  "properties": {
    "addr:full":"Carr Cecili Metel, 81 Pollen\u00e7a Islas Baleares 07460",
    "addr:housenumber":"81",
    "addr:postcode":"07460",
    "addr:street":"Carr Cecili Metel",
    "iso:country":"ES",
    "sg:address":"Carr Cecili Metel, 81",
    "sg:city":"Pollen\u00e7a",
    "sg:orig_category":"Mec\u00c1nico Del Autom\u00d3vil",
    "sg:phone":"+34 971 53 06 98",
    "sg:postcode":"07460",
    "sg:province":"Islas Baleares",
    "wof:name":"Autoventa Pollensa S.l.",
    "wof:placetype":"venue"
},
  "geometry": {"coordinates":[3.0375914574,39.8799629211],"type":"Point"}
}