{
  "type": "Feature",
  "properties": {
    "iso:country":"ES",
    "sg:address":"Avgd Asturies, D', 23",
    "sg:city":"Soller",
    "sg:orig_category":"Alimentaci\u00d3n General (al Por Menor)",
    "sg:phone":"+34 971 63 11 71",
    "sg:postcode":"07100",
    "sg:province":"Islas Baleares",
    "wof:name":"Pe\u00f1as Cifre Maria",
    "wof:placetype":"venue"
},
  "geometry": {"coordinates":[2.7171030045,39.770740509],"type":"Point"}
}