{
  "type": "Feature",
  "properties": {
    "addr:full":"Carrer de Bailen, 240 Barcelona Barcelona 08037",
    "addr:housenumber":"240",
    "addr:postcode":"08037",
    "addr:street":"Carrer De Bailen",
    "iso:country":"ES",
    "sg:address":"Carrer de Bailen, 240",
    "sg:city":"Barcelona",
    "sg:orig_category":"Agencias Y Agentes Comerciales, Representantes",
    "sg:phone":"+34 932 13 31 99",
    "sg:postcode":"08037",
    "sg:province":"Barcelona",
    "wof:name":"Caymari Capsal Juan",
    "wof:placetype":"venue"
},
  "geometry": {"coordinates":[2.1621360779,41.4035148621],"type":"Point"}
}