{
  "type": "Feature",
  "properties": {
    "addr:full":"Luga Carballal, S/n Carballal La Coru\u00f1a 15684",
    "addr:housenumber":"s",
    "addr:postcode":"15684",
    "addr:street":"/ N Carballal La Corun\u0303A",
    "iso:country":"ES",
    "sg:address":"Luga Carballal, S/n",
    "sg:city":"Carballal",
    "sg:orig_category":"Tractores Agr\u00cdcolas Y Remolques",
    "sg:phone":"+34 981 69 50 44",
    "sg:postcode":"15684",
    "sg:province":"La Coru\u00f1a",
    "wof:name":"Puente Mui\u00f1o Camilo",
    "wof:placetype":"venue"
},
  "geometry": {"coordinates":[-8.5441894531,43.1243057251],"type":"Point"}
}