{
  "type": "Feature",
  "properties": {
    "addr:full":"Plaz Espa\u00d1a, 1 Gines Sevilla 41960",
    "addr:housenumber":"1",
    "addr:postcode":"41960",
    "addr:street":"Plaz Espan\u0303A;Sevilla",
    "iso:country":"ES",
    "sg:address":"Plaz Espa\u00d1a, 1",
    "sg:city":"Gines",
    "sg:orig_category":"Asociaciones, Organismos Culturales Y Socioeducativos",
    "sg:phone":"+34 954 71 43 19",
    "sg:postcode":"41960",
    "sg:province":"Sevilla",
    "wof:name":"Circulo Recreatico Cultural",
    "wof:placetype":"venue"
},
  "geometry": {"coordinates":[-6.0780119896,37.3871688843],"type":"Point"}
}