{
  "type": "Feature",
  "properties": {
    "iso:country":"ES",
    "sg:address":"Calle de Ronda De Altair, 21",
    "sg:city":"Dos Hermanas",
    "sg:orig_category":"Agencias Y Agentes Comerciales, Representantes",
    "sg:phone":"+34 955 66 66 66",
    "sg:postcode":"41700",
    "sg:province":"Sevilla",
    "wof:name":"Interaceite S.l.",
    "wof:placetype":"venue"
},
  "geometry": {"coordinates":[-5.9281339645,37.2829055786],"type":"Point"}
}