{
  "type": "Feature",
  "properties": {
    "addr:full":"Avda Paris, 6 Arenal Alicante 03730",
    "addr:housenumber":"6",
    "addr:postcode":"03730",
    "addr:street":"Avda Paris",
    "iso:country":"ES",
    "sg:address":"Avda Paris, 6",
    "sg:city":"Arenal",
    "sg:orig_category":"Cajas De Ahorro",
    "sg:phone":"+34 965 79 04 23",
    "sg:postcode":"03730",
    "sg:province":"Alicante",
    "sg:website":"www.canamurcia.es",
    "wof:name":"Caja De Ahorros De Murcia",
    "wof:placetype":"venue"
},
  "geometry": {"coordinates":[0.1668650061,38.7890739441],"type":"Point"}
}