{
  "type": "Feature",
  "properties": {
    "addr:full":"Calle de Plata (del), 1 Fuenlabrada Madrid 28944",
    "addr:housenumber":"1",
    "addr:postcode":"28944",
    "addr:street":"Calle De Plata Del",
    "iso:country":"ES",
    "sg:address":"Calle de Plata (del), 1",
    "sg:city":"Fuenlabrada",
    "sg:orig_category":"Florister\u00cdas",
    "sg:phone":"+34 916 97 16 38",
    "sg:postcode":"28944",
    "sg:province":"Madrid",
    "wof:name":"Gonzalez Lopez Juliana",
    "wof:placetype":"venue"
},
  "geometry": {"coordinates":[-3.7891719341,40.2838973999],"type":"Point"}
}