{
  "type": "Feature",
  "properties": {
    "addr:full":"Calle de Cid, 12 Miranda Ebro Burgos 09200",
    "addr:housenumber":"12",
    "addr:postcode":"09200",
    "addr:street":"Calle De Cid",
    "iso:country":"ES",
    "sg:address":"Calle de Cid, 12",
    "sg:city":"Miranda Ebro",
    "sg:orig_category":"Muebles, Minoristas",
    "sg:phone":"+34 947 31 02 44",
    "sg:postcode":"09200",
    "sg:province":"Burgos",
    "wof:name":"Miguel Mardones Ricardo",
    "wof:placetype":"venue"
},
  "geometry": {"coordinates":[-2.9441754818,42.6860466003],"type":"Point"}
}