{
  "type": "Feature",
  "properties": {
    "iso:country":"ES",
    "sg:address":"Calle de Londres, 59",
    "sg:city":"Madrid",
    "sg:orig_category":"Inversiones",
    "sg:phone":"+34 913 61 45 40",
    "sg:postcode":"28028",
    "sg:province":"Madrid",
    "wof:name":"Internacional De Mercados Financieros",
    "wof:placetype":"venue"
},
  "geometry": {"coordinates":[-3.6653280258,40.4319953918],"type":"Point"}
}