{
  "type": "Feature",
  "properties": {
    "addr:full":"Poli Industrial, S/n Arguedas Navarra 31513",
    "addr:housenumber":"/ n",
    "addr:postcode":"31513",
    "addr:street":"Industrial",
    "iso:country":"ES",
    "sg:address":"Poli Industrial, S/n",
    "sg:city":"Arguedas",
    "sg:orig_category":"Congelados: Productos Alimentarios (fabricaci\u00d3n, Al Por Mayor)",
    "sg:phone":"+34 948 83 05 63",
    "sg:postcode":"31513",
    "sg:province":"Navarra",
    "wof:name":"Congelados De Navarra S.a.",
    "wof:placetype":"venue"
},
  "geometry": {"coordinates":[-1.6175489426,42.1869659424],"type":"Point"}
}