{
  "type": "Feature",
  "properties": {
    "iso:country":"ES",
    "sg:address":"Fray Luis De Leon, 2",
    "sg:city":"Alhaurin Torre",
    "sg:orig_category":"Agencias Y Agentes Comerciales, Representantes",
    "sg:phone":"+34 952 96 36 60",
    "sg:postcode":"29130",
    "sg:province":"M\u00e1laga",
    "wof:name":"1944 Representaciones L.f. Blanco S.l.",
    "wof:placetype":"venue"
},
  "geometry": {"coordinates":[-4.607259,36.734581],"type":"Point"}
}