{
  "type": "Feature",
  "properties": {
    "iso:country":"ES",
    "sg:address":"Carretera De La Fuensanta, 108",
    "sg:city":"Villanueva Arzobispo",
    "sg:orig_category":"Delegados, Agentes De Tr\u00c1nsito, Auxiliares De Transporte Internacional",
    "sg:phone":"+34 953 45 00 65",
    "sg:postcode":"23330",
    "sg:province":"Ja\u00e9n",
    "wof:name":"Agri-aridos Villanueva S.l.",
    "wof:placetype":"venue"
},
  "geometry": {"coordinates":[-3.0052318573,38.1645431519],"type":"Point"}
}