{
  "type": "Feature",
  "properties": {
    "addr:full":"Rbla Poblenou, 116 Barcelona Barcelona 08005",
    "addr:housenumber":"116",
    "addr:postcode":"08005",
    "addr:street":"Rbla Poblenou",
    "iso:country":"ES",
    "sg:address":"Rbla Poblenou, 116",
    "sg:city":"Barcelona",
    "sg:orig_category":"Cajas De Ahorro",
    "sg:phone":"+34 933 00 00 54",
    "sg:postcode":"08005",
    "sg:province":"Barcelona",
    "sg:website":"www.bancaja.es",
    "wof:name":"Caja De Ahorros De Valencia Castellon Y Alicante, Bancaja",
    "wof:placetype":"venue"
},
  "geometry": {"coordinates":[2.1987080574,41.4032402039],"type":"Point"}
}