{
  "type": "Feature",
  "properties": {
    "iso:country":"ES",
    "sg:address":"Calle de Calvo Sotelo, 7",
    "sg:city":"Santo\u00f1a",
    "sg:orig_category":"Asesor\u00cda Fiscal Y Jur\u00cddica",
    "sg:phone":"+34 942 66 09 84",
    "sg:postcode":"39740",
    "sg:province":"Cantabria",
    "wof:name":"Asesoria Gorostiaga S.l.",
    "wof:placetype":"venue"
},
  "geometry": {"coordinates":[-3.4572980404,43.4436340332],"type":"Point"}
}