{
  "type": "Feature",
  "properties": {
    "iso:country":"ES",
    "sg:address":"Calle de Fuente Alamo, S/n",
    "sg:city":"Coru\u00d1a",
    "sg:classifiers":[
        {
            "category":"Taxi",
            "type":"Transportation"
        }
    ],
    "sg:phone":"+34 981 14 06 57",
    "sg:postcode":"15010",
    "sg:province":"La Coru\u00f1a",
    "wof:name":"Asociacion Local De Trabajadores Autonomos De Autotaxis",
    "wof:placetype":"venue"
},
  "geometry": {"coordinates":[-8.4187898636,43.3608131409],"type":"Point"}
}