{
  "type": "Feature",
  "properties": {
    "addr:full":"Calle de Doctor Bonardell, 42 Alcazar S. Juan Ciudad Real 13600",
    "addr:housenumber":"42",
    "addr:postcode":"13600",
    "addr:street":"Calle De Doctor Bonardell;Alcazar S. Juan Ciudad Real",
    "iso:country":"ES",
    "sg:address":"Calle de Doctor Bonardell, 42",
    "sg:city":"Alcazar S. Juan",
    "sg:orig_category":"Inform\u00c1tica (estudios, Servicios, Asesor\u00cda, Formaci\u00d3n)",
    "sg:phone":"+34 926 54 67 41",
    "sg:postcode":"13600",
    "sg:province":"Ciudad Real",
    "wof:name":"Meyca S.a.",
    "wof:placetype":"venue"
},
  "geometry": {"coordinates":[-3.2134234905,39.3889465332],"type":"Point"}
}