{
  "type": "Feature",
  "properties": {
    "addr:full":"Calle de Geranio, 4 Monta\u00e7a Los Velez Las Palmas 35259",
    "addr:housenumber":"4",
    "addr:postcode":"35259",
    "addr:street":"Calle De Geranio;Los",
    "iso:country":"ES",
    "sg:address":"Calle de Geranio, 4",
    "sg:city":"Monta\u00e7a Los Velez",
    "sg:orig_category":"Frutas Y Legumbres Frescas (al Por Mayor)",
    "sg:phone":"+34 928 78 08 61",
    "sg:postcode":"35259",
    "sg:province":"Las Palmas",
    "wof:name":"Silva Diaz Rafael",
    "wof:placetype":"venue"
},
  "geometry": {"coordinates":[-15.5986890793,27.7602348328],"type":"Point"}
}