{
  "type": "Feature",
  "properties": {
    "iso:country":"ES",
    "sg:address":"Calle de Carmen, 4",
    "sg:city":"Logro\u00f1o",
    "sg:orig_category":"Loter\u00cda Y T\u00d3mbola",
    "sg:phone":"+34 941 25 13 73",
    "sg:postcode":"26001",
    "sg:province":"La Rioja",
    "wof:name":"Alda Lumbreras Maria Del Carmen",
    "wof:placetype":"venue"
},
  "geometry": {"coordinates":[-2.4436113834,42.465839386],"type":"Point"}
}