{
  "type": "Feature",
  "properties": {
    "iso:country":"ES",
    "sg:address":"Carr Cami De Corbins, 16",
    "sg:city":"Lleida",
    "sg:orig_category":"Reposter\u00cdas",
    "sg:phone":"+34 973 23 80 64",
    "sg:postcode":"25005",
    "sg:province":"Lleida",
    "wof:name":"Reig Morell Josep Maria",
    "wof:placetype":"venue"
},
  "geometry": {"coordinates":[0.6354110241,41.6235542297],"type":"Point"}
}