{
  "type": "Feature",
  "properties": {
    "iso:country":"ES",
    "sg:address":"Avda Santa Cruz, 104",
    "sg:city":"San Isidro",
    "sg:orig_category":"Bisuter\u00cda, Joyer\u00cda, Relojer\u00cda (al Por Menor)",
    "sg:phone":"+34 922 39 06 70",
    "sg:postcode":"38611",
    "sg:province":"Santa Cruz De Tenerife",
    "wof:name":"Cabrera Gonzalez Isabel",
    "wof:placetype":"venue"
},
  "geometry": {"coordinates":[-16.5576686859,28.0772800446],"type":"Point"}
}