{
  "type": "Feature",
  "properties": {
    "addr:full":"Plzl Barrio, 11 Montijo Badajoz 06480",
    "addr:postcode":"06480",
    "iso:country":"ES",
    "sg:address":"Plzl Barrio, 11",
    "sg:city":"Montijo",
    "sg:orig_category":"Carnicer\u00cdas, Carnicer\u00cdas",
    "sg:phone":"+34 924 45 50 06",
    "sg:postcode":"06480",
    "sg:province":"Badajoz",
    "wof:name":"Carniceria Martinez Crespo Cb",
    "wof:placetype":"venue"
},
  "geometry": {"coordinates":[-6.6062841415,38.9077644348],"type":"Point"}
}