{
  "type": "Feature",
  "properties": {
    "iso:country":"ES",
    "sg:address":"Carrer de Pedreres, 10",
    "sg:city":"Barcelona",
    "sg:orig_category":"Electricidad: Instaladores",
    "sg:phone":"+34 934 41 08 95",
    "sg:postcode":"08004",
    "sg:province":"Barcelona",
    "wof:name":"Lahuerta Jarque Emilio",
    "wof:placetype":"venue"
},
  "geometry": {"coordinates":[2.1589961052,41.3724937439],"type":"Point"}
}