{
  "type": "Feature",
  "properties": {
    "iso:country":"ES",
    "sg:address":"Avda Calvo Sotelo, 26",
    "sg:city":"Solares",
    "sg:orig_category":"Ropa Para Se\u00d1oras Y Caballeros (al Por Menor)",
    "sg:phone":"+34 942 52 09 74",
    "sg:postcode":"39710",
    "sg:province":"Cantabria",
    "wof:name":"Otero Fraile Maria Teresa",
    "wof:placetype":"venue"
},
  "geometry": {"coordinates":[-3.7402191162,43.38463974],"type":"Point"}
}