{
  "type": "Feature",
  "properties": {
    "iso:country":"ES",
    "sg:address":"Calle de Baden De Rico Lucas, 2",
    "sg:city":"Pinoso",
    "sg:orig_category":"Supermercados Y Hipermercados",
    "sg:phone":"+34 965 47 75 64",
    "sg:postcode":"03650",
    "sg:province":"Alicante",
    "wof:name":"Consum Sociedad Cooperativa Limitada",
    "wof:placetype":"venue"
},
  "geometry": {"coordinates":[-1.04185009,38.4011001587],"type":"Point"}
}