{
  "type": "Feature",
  "properties": {
    "iso:country":"ES",
    "sg:address":"Avda Burgo De Osma, S/n",
    "sg:city":"Almazan",
    "sg:orig_category":"Negocio De Granos Y Harinas",
    "sg:phone":"+34 975 30 04 70",
    "sg:postcode":"42200",
    "sg:province":"Soria",
    "wof:name":"Harinas Martirena S.l.",
    "wof:placetype":"venue"
},
  "geometry": {"coordinates":[-2.5381538868,41.4847755432],"type":"Point"}
}