{
  "type": "Feature",
  "properties": {
    "iso:country":"ES",
    "sg:address":"Calle de Arxentina, 29",
    "sg:city":"Esfarrapada",
    "sg:orig_category":"Ingeniero",
    "sg:phone":"+34 986 34 79 96",
    "sg:postcode":"36470",
    "sg:province":"Pontevedra",
    "wof:name":"Abas Estudios E Proxectos Agrarios S.l.",
    "wof:placetype":"venue"
},
  "geometry": {"coordinates":[-8.556605,42.100868],"type":"Point"}
}