{
  "type": "Feature",
  "properties": {
    "iso:country":"ES",
    "sg:address":"Calle de Mayor (c), 16",
    "sg:city":"Casar",
    "sg:orig_category":"Molduras, Junquillos, Listones Y Molduras Perforadas",
    "sg:phone":"+34 949 33 66 68",
    "sg:postcode":"19170",
    "sg:province":"Guadalajara",
    "wof:name":"Fernandez Sanz Rogelio",
    "wof:placetype":"venue"
},
  "geometry": {"coordinates":[-3.4283480644,40.7030715942],"type":"Point"}
}