{
  "type": "Feature",
  "properties": {
    "iso:country":"ES",
    "sg:address":"Calle de Juan Bravo, 25",
    "sg:city":"Madrid",
    "sg:orig_category":"Ingenier\u00cda, Centros De Estudios (diversos)",
    "sg:phone":"+34 915 64 23 76",
    "sg:postcode":"28006",
    "sg:province":"Madrid",
    "wof:name":"Oyarzabal Y Velarde Alberto De",
    "wof:placetype":"venue"
},
  "geometry": {"coordinates":[-3.6801869869,40.4328804016],"type":"Point"}
}