{
  "type": "Feature",
  "properties": {
    "iso:country":"ES",
    "sg:address":"Calle de Victoria, 20",
    "sg:city":"Malaga",
    "sg:orig_category":"Material Y Suministros Para Fotocopiadoras, Reprograf\u00cda",
    "sg:phone":"+34 952 21 87 46",
    "sg:postcode":"29012",
    "sg:province":"M\u00e1laga",
    "wof:name":"Fernandez Gutierrez Francisco Jose",
    "wof:placetype":"venue"
},
  "geometry": {"coordinates":[-4.4162487984,36.7236747742],"type":"Point"}
}