{
  "type": "Feature",
  "properties": {
    "iso:country":"ES",
    "sg:address":"Carrer de Lluis Sole Sabaris, 25",
    "sg:city":"Gava",
    "sg:orig_category":"Sociedades, Compa\u00d1\u00cdas Aseguradoras",
    "sg:phone":"+34 936 38 35 41",
    "sg:postcode":"08850",
    "sg:province":"Barcelona",
    "wof:name":"Garcia Castellanos Cesar",
    "wof:placetype":"venue"
},
  "geometry": {"coordinates":[1.9978679419,41.3015403748],"type":"Point"}
}