{
  "type": "Feature",
  "properties": {
    "iso:country":"ES",
    "sg:address":"Calle de Cotanda, 1",
    "sg:city":"Valencia",
    "sg:orig_category":"Procuradores",
    "sg:phone":"+34 963 52 08 13",
    "sg:postcode":"46002",
    "sg:province":"Valencia",
    "wof:name":"Perez Samper Florentina",
    "wof:placetype":"venue"
},
  "geometry": {"coordinates":[-0.3773837984,39.4712371826],"type":"Point"}
}