{
  "type": "Feature",
  "properties": {
    "iso:country":"ES",
    "sg:address":"Calle de Peru, 7",
    "sg:city":"Sevilla",
    "sg:orig_category":"Ingenier\u00cda, Centros De Estudios (diversos)",
    "sg:phone":"+34 954 23 06 28",
    "sg:postcode":"41012",
    "sg:province":"Sevilla",
    "wof:name":"Equipain S.a.",
    "wof:placetype":"venue"
},
  "geometry": {"coordinates":[-5.9883899689,37.3537368774],"type":"Point"}
}