{
  "type": "Feature",
  "properties": {
    "iso:country":"ES",
    "sg:address":"Calle de Impresor Monfort, 15",
    "sg:city":"Valencia",
    "sg:orig_category":"Bisuter\u00cda, Joyer\u00cda, Relojer\u00cda (al Por Menor)",
    "sg:phone":"+34 963 78 39 39",
    "sg:postcode":"46018",
    "sg:province":"Valencia",
    "wof:name":"Cano 96 S. L.",
    "wof:placetype":"venue"
},
  "geometry": {"coordinates":[-0.3943780065,39.4622955322],"type":"Point"}
}