{
  "type": "Feature",
  "properties": {
    "addr:full":"Calle de Gran Via, 10 Madrid Madrid 28013",
    "addr:housenumber":"10",
    "addr:postcode":"madrid;28013",
    "addr:street":"Calle De Gran Via",
    "iso:country":"ES",
    "sg:address":"Calle de Gran Via, 10",
    "sg:city":"Madrid",
    "sg:orig_category":"Material Y Accesorios Para Bisuter\u00cda Y Joyer\u00cda",
    "sg:phone":"+34 915 21 54 00",
    "sg:postcode":"28013",
    "sg:province":"Madrid",
    "wof:name":"Brooking Joyero S.l.",
    "wof:placetype":"venue"
},
  "geometry": {"coordinates":[-3.6986339092,40.4195823669],"type":"Point"}
}