{
  "type": "Feature",
  "properties": {
    "addr:full":"Calle de Diputacion Foral De Alava, 16 Vitoria-gasteiz \u00c1lava 01001",
    "addr:housenumber":"16",
    "addr:postcode":"01001",
    "addr:street":"Calle De Diputacion Foral De Alava",
    "iso:country":"ES",
    "sg:address":"Calle de Diputacion Foral De Alava, 16",
    "sg:city":"Vitoria-gasteiz",
    "sg:orig_category":"Agencias Y Asesores De Publicidad",
    "sg:phone":"+34 945 12 09 25",
    "sg:postcode":"01001",
    "sg:province":"\u00c1lava",
    "sg:website":"www.imaggen.com",
    "wof:name":"Imaggen S.c.",
    "wof:placetype":"venue"
},
  "geometry": {"coordinates":[-2.6746258736,42.8470001221],"type":"Point"}
}