{
  "type": "Feature",
  "properties": {
    "addr:full":"Calle de Real, 15 Matamorosa Cantabria 39200",
    "addr:housenumber":"15",
    "addr:postcode":"39200",
    "addr:street":"Calle De Real",
    "iso:country":"ES",
    "sg:address":"Calle de Real, 15",
    "sg:city":"Matamorosa",
    "sg:orig_category":"Alimentaci\u00d3n General (al Por Menor)",
    "sg:phone":"+34 942 77 10 14",
    "sg:postcode":"39200",
    "sg:province":"Cantabria",
    "wof:name":"Cabria Lopez Maria Isabel",
    "wof:placetype":"venue"
},
  "geometry": {"coordinates":[-4.1464438438,42.9850349426],"type":"Point"}
}