{
  "type": "Feature",
  "properties": {
    "iso:country":"ES",
    "sg:address":"Calle de Reyes Magos, 25",
    "sg:city":"S. Fernando",
    "sg:orig_category":"Panader\u00cdas, Panader\u00cdas",
    "sg:phone":"+34 956 59 00 34",
    "sg:postcode":"11100",
    "sg:province":"C\u00e1diz",
    "wof:name":"Garcia Guzman Josefa",
    "wof:placetype":"venue"
},
  "geometry": {"coordinates":[-6.1888442039,36.4730567932],"type":"Point"}
}