{
  "type": "Feature",
  "properties": {
    "iso:country":"ES",
    "sg:address":"Ctra. Ledesma-zamora, Km. 0042,0",
    "sg:city":"Moraleja Sayago",
    "sg:orig_category":"Cr\u00cda De Animales",
    "sg:phone":"+34 980 56 40 00",
    "sg:postcode":"49177",
    "sg:province":"Zamora",
    "wof:name":"Miguel Mu\u00f1oz Navarro Y Otros C.b.",
    "wof:placetype":"venue"
},
  "geometry": {"coordinates":[-6.0035939217,41.1692390442],"type":"Point"}
}