{
  "type": "Feature",
  "properties": {
    "iso:country":"ES",
    "sg:address":"Avda Los Huetos, 28",
    "sg:city":"Vitoria-gasteiz",
    "sg:orig_category":"Peluqueros: De Se\u00d1oras",
    "sg:phone":"+34 945 22 41 58",
    "sg:postcode":"01010",
    "sg:province":"\u00c1lava",
    "wof:name":"Maria Elena Murua I\u00f1iguez De Fieredia",
    "wof:placetype":"venue"
},
  "geometry": {"coordinates":[-2.7038779259,42.854801178],"type":"Point"}
}