{
  "type": "Feature",
  "properties": {
    "addr:full":"Avda Eulogio Fernandez, 18 Barco Ourense 32300",
    "addr:housenumber":"18",
    "addr:postcode":"32300",
    "addr:street":"Avda Eulogio Fernandez",
    "iso:country":"ES",
    "sg:address":"Avda Eulogio Fernandez, 18",
    "sg:city":"Barco",
    "sg:orig_category":"Sociedades, Compa\u00d1\u00cdas Aseguradoras",
    "sg:phone":"+34 988 32 10 89",
    "sg:postcode":"32300",
    "sg:province":"Ourense",
    "wof:name":"Seguros Catalana Occidente S.a. De Seguros Y Reaseguros",
    "wof:placetype":"venue"
},
  "geometry": {"coordinates":[-6.9871549606,42.4171485901],"type":"Point"}
}