{
  "type": "Feature",
  "properties": {
    "iso:country":"ES",
    "sg:address":"Carrer de Extremadura, 1",
    "sg:city":"Cambrils",
    "sg:orig_category":"Pintura Y Barniz (al Por Menor)",
    "sg:phone":"+34 977 36 62 37",
    "sg:postcode":"43850",
    "sg:province":"Tarragona",
    "wof:name":"Bonet Robert Oscar",
    "wof:placetype":"venue"
},
  "geometry": {"coordinates":[1.0565010309,41.0687522888],"type":"Point"}
}