{
  "type": "Feature",
  "properties": {
    "addr:full":"Calle de Puente Duque, Km. 0000,2 Hoyos Espino \u00c1vila 05634",
    "addr:postcode":"05634",
    "addr:street":"Calle De Puente Duque Km. 0000,2;A\u0301Vila",
    "iso:country":"ES",
    "sg:address":"Calle de Puente Duque, Km. 0000,2",
    "sg:city":"Hoyos Espino",
    "sg:orig_category":"Alquiler De Casas Y Habitaciones Amuebladas",
    "sg:phone":"+34 920 34 91 79",
    "sg:postcode":"05634",
    "sg:province":"\u00c1vila",
    "wof:name":"Alonso Garcia Guillermo",
    "wof:placetype":"venue"
},
  "geometry": {"coordinates":[-5.1786808968,40.3570594788],"type":"Point"}
}