{
  "type": "Feature",
  "properties": {
    "iso:country":"ES",
    "sg:address":"Carrer de Pintor Fortuny, 1",
    "sg:city":"Viladecans",
    "sg:orig_category":"Mec\u00c1nica General",
    "sg:phone":"+34 936 58 55 18",
    "sg:postcode":"08840",
    "sg:province":"Barcelona",
    "wof:name":"Ascensores Francisco Calahorro Berrio S.l.",
    "wof:placetype":"venue"
},
  "geometry": {"coordinates":[2.0222754478,41.3188247681],"type":"Point"}
}