{
  "type": "Feature",
  "properties": {
    "iso:country":"ES",
    "sg:address":"Calle de Corredera, 28",
    "sg:city":"Almodovar Campo",
    "sg:orig_category":"Centros De Educaci\u00d3n Especial",
    "sg:phone":"+34 926 48 32 25",
    "sg:postcode":"13580",
    "sg:province":"Ciudad Real",
    "wof:name":"Colegio Publico Maestro Juan De Avila",
    "wof:placetype":"venue"
},
  "geometry": {"coordinates":[-4.1789674759,38.7078590393],"type":"Point"}
}