{
  "type": "Feature",
  "properties": {
    "iso:country":"ES",
    "sg:address":"Calle de Baza, S/n",
    "sg:city":"Albolote",
    "sg:orig_category":"Cristaler\u00cdas",
    "sg:phone":"+34 958 46 52 03",
    "sg:postcode":"18220",
    "sg:province":"Granada",
    "sg:website":"www.euro-glass.com",
    "wof:name":"Euro Glass System S.l",
    "wof:placetype":"venue"
},
  "geometry": {"coordinates":[-3.6438014507,37.2280883789],"type":"Point"}
}