{
  "type": "Feature",
  "properties": {
    "addr:full":"Carrer de Quatre De Novembre, 12 Poligon Industrial De Can Valero Islas Baleares 07011",
    "addr:housenumber":"12",
    "addr:postcode":"07011",
    "addr:street":"Carrer De Quatre De Novembre;Islas",
    "iso:country":"ES",
    "sg:address":"Carrer de Quatre De Novembre, 12",
    "sg:city":"Poligon Industrial De Can Valero",
    "sg:orig_category":"Servicios Diversos",
    "sg:phone":"+34 971 75 00 57",
    "sg:postcode":"07011",
    "sg:province":"Islas Baleares",
    "wof:name":"Bennasar Perello Mateo",
    "wof:placetype":"venue"
},
  "geometry": {"coordinates":[2.6271300316,39.5906105042],"type":"Point"}
}