{
  "type": "Feature",
  "properties": {
    "addr:full":"Avda Galicia, 369 Fuentes Nuevas Le\u00f3n 24411",
    "addr:housenumber":"369",
    "addr:postcode":"24411",
    "addr:street":"Avda Galicia;Leo\u0301N",
    "iso:country":"ES",
    "sg:address":"Avda Galicia, 369",
    "sg:city":"Fuentes Nuevas",
    "sg:orig_category":"Ense\u00d1anza, Formaci\u00d3n Profesional: Aprendizaje",
    "sg:phone":"+34 987 45 50 51",
    "sg:postcode":"24411",
    "sg:province":"Le\u00f3n",
    "wof:name":"Mancomunidad De Municipios De La Comarca De Ponferrada",
    "wof:placetype":"venue"
},
  "geometry": {"coordinates":[-6.6485543251,42.5705986023],"type":"Point"}
}