{
  "type": "Feature",
  "properties": {
    "iso:country":"ES",
    "sg:address":"Calle de Cueto Alto, S/n",
    "sg:city":"Llanes",
    "sg:orig_category":"Turismo: Lugares, Circuitos Y Curiosidades",
    "sg:phone":"+34 985 40 24 85",
    "sg:postcode":"33500",
    "sg:province":"Asturias",
    "wof:name":"Servicios Del Principado S.a.u.",
    "wof:placetype":"venue"
},
  "geometry": {"coordinates":[-4.7565369606,43.4198913574],"type":"Point"}
}