{
  "type": "Feature",
  "properties": {
    "addr:full":"Carr D'en Jaume I El Conqueridor, 11 Ontinyent Valencia 46870",
    "addr:housenumber":"11",
    "addr:postcode":"46870",
    "addr:street":"Carr D'En Jaume I El Conqueridor",
    "iso:country":"ES",
    "sg:address":"Carr D'en Jaume I El Conqueridor, 11",
    "sg:city":"Ontinyent",
    "sg:orig_category":"Administradores De Bienes Y Delegados De Comunidades De Propietarios",
    "sg:phone":"+34 962 38 62 96",
    "sg:postcode":"46870",
    "sg:province":"Valencia",
    "wof:name":"Comunidad De Propietarios Jaime I El Conquistador",
    "wof:placetype":"venue"
},
  "geometry": {"coordinates":[-0.6094059944,38.8210830688],"type":"Point"}
}