{
  "type": "Feature",
  "properties": {
    "addr:full":"Calle de Doctor Quintero, S/n Valverde Santa Cruz De Tenerife 38910",
    "addr:housenumber":"/ n",
    "addr:postcode":"38910",
    "addr:street":"Calle De Doctor Quintero S",
    "iso:country":"ES",
    "sg:address":"Calle de Doctor Quintero, S/n",
    "sg:city":"Valverde",
    "sg:orig_category":"Frutas, Legumbres Frescas Y Tempranas (al Por Menor)",
    "sg:phone":"+34 922 55 02 80",
    "sg:postcode":"38910",
    "sg:province":"Santa Cruz De Tenerife",
    "wof:name":"Padron Armas Juan",
    "wof:placetype":"venue"
},
  "geometry": {"coordinates":[-17.9160919189,27.8088169098],"type":"Point"}
}