{
  "type": "Feature",
  "properties": {
    "addr:full":"Bizkaia Kalea, 4 Zarautz Guip\u00f9zcoa 20800",
    "addr:housenumber":"4",
    "addr:postcode":"20800",
    "addr:street":"Bizkaia Kalea;Guipu\u0300Zcoa",
    "iso:country":"ES",
    "sg:address":"Bizkaia Kalea, 4",
    "sg:city":"Zarautz",
    "sg:orig_category":"Plomeros",
    "sg:phone":"+34 943 89 00 69",
    "sg:postcode":"20800",
    "sg:province":"Guip\u00f9zcoa",
    "wof:name":"Urbide C.b.",
    "wof:placetype":"venue"
},
  "geometry": {"coordinates":[-2.1765329838,43.2835884094],"type":"Point"}
}