{
  "type": "Feature",
  "properties": {
    "iso:country":"ES",
    "sg:address":"Poligono Industrial, S/n",
    "sg:city":"Pol. Ind. Onzonilla",
    "sg:orig_category":"Armas Y Municiones (fabricaci\u00d3n, Al Por Mayor)",
    "sg:phone":"+34 987 21 84 62",
    "sg:postcode":"24231",
    "sg:province":"Le\u00f3n",
    "wof:name":"Roce 13 S.l.",
    "wof:placetype":"venue"
},
  "geometry": {"coordinates":[-5.5844950676,42.5004310608],"type":"Point"}
}