{
  "type": "Feature",
  "properties": {
    "addr:full":"Luga Hoya Del Pedregal, 35 Almatriche Alto Las Palmas 35018",
    "addr:housenumber":"35",
    "addr:postcode":"35018",
    "addr:street":"Del Pedregal",
    "iso:country":"ES",
    "sg:address":"Luga Hoya Del Pedregal, 35",
    "sg:city":"Almatriche Alto",
    "sg:orig_category":"Mec\u00c1nico Del Autom\u00d3vil",
    "sg:phone":"+34 928 66 70 53",
    "sg:postcode":"35018",
    "sg:province":"Las Palmas",
    "wof:name":"Aleman Miranda Ignacia",
    "wof:placetype":"venue"
},
  "geometry": {"coordinates":[-15.4300060272,28.1248226166],"type":"Point"}
}