{
  "type": "Feature",
  "properties": {
    "addr:full":"Avda Constitucion, 59 Medina Campo Valladolid 47400",
    "addr:housenumber":"59",
    "addr:postcode":"47400",
    "addr:street":"Avda Constitucion",
    "iso:country":"ES",
    "sg:address":"Avda Constitucion, 59",
    "sg:city":"Medina Campo",
    "sg:orig_category":"Muebles, Minoristas",
    "sg:phone":"+34 983 83 76 77",
    "sg:postcode":"47400",
    "sg:province":"Valladolid",
    "sg:website":"www.grupo-grancasa.com",
    "wof:name":"Jojugus Sl",
    "wof:placetype":"venue"
},
  "geometry": {"coordinates":[-4.913184166,41.3120155334],"type":"Point"}
}