{
  "type": "Feature",
  "properties": {
    "addr:full":"Carrer de Frederic Mompou, 5 Terrassa Barcelona 08226",
    "addr:housenumber":"5",
    "addr:postcode":"08226",
    "addr:street":"Carrer De Frederic Mompou",
    "iso:country":"ES",
    "sg:address":"Carrer de Frederic Mompou, 5",
    "sg:city":"Terrassa",
    "sg:orig_category":"Inmobiliaria (agencias)",
    "sg:phone":"+34 937 83 75 88",
    "sg:postcode":"08226",
    "sg:province":"Barcelona",
    "wof:name":"Comunidad De Propietarios Frederic Mompou 5",
    "wof:placetype":"venue"
},
  "geometry": {"coordinates":[2.0281291008,41.5759277344],"type":"Point"}
}