{
  "type": "Feature",
  "properties": {
    "iso:country":"ES",
    "sg:address":"Zorzale\u00f1a(p I El Perrero), 21",
    "sg:city":"Albaida Aljarafe",
    "sg:orig_category":"\u00c1rboles Frutales",
    "sg:phone":"+34 954 11 00 36",
    "sg:postcode":"41809",
    "sg:province":"Sevilla",
    "wof:name":"Olivarera Albaida Del Aljarafe S.c.a.",
    "wof:placetype":"venue"
},
  "geometry": {"coordinates":[-6.1658987999,37.4270706177],"type":"Point"}
}