{
  "type": "Feature",
  "properties": {
    "addr:full":"Calle de Mayor (salobral (el)), 9 Salobral Albacete 02140",
    "addr:postcode":"02140",
    "addr:street":"Calle De Mayor;El;Salobral",
    "iso:country":"ES",
    "sg:address":"Calle de Mayor (salobral (el)), 9",
    "sg:city":"Salobral",
    "sg:orig_category":"Cajas Para Embalar",
    "sg:phone":"+34 967 27 16 46",
    "sg:postcode":"02140",
    "sg:province":"Albacete",
    "wof:name":"Caja Rural De Albacete",
    "wof:placetype":"venue"
},
  "geometry": {"coordinates":[-1.9627039433,38.8379936218],"type":"Point"}
}