{
  "type": "Feature",
  "properties": {
    "iso:country":"ES",
    "sg:address":"Calle de Virgen Del Pilar, 40",
    "sg:city":"Ubeda",
    "sg:orig_category":"Negocio De Materiales De Construcci\u00d3n",
    "sg:phone":"+34 953 79 28 87",
    "sg:postcode":"23400",
    "sg:province":"Ja\u00e9n",
    "wof:name":"Robles Herrera Andres",
    "wof:placetype":"venue"
},
  "geometry": {"coordinates":[-3.3728981018,38.0181770325],"type":"Point"}
}