{
  "type": "Feature",
  "properties": {
    "iso:country":"ES",
    "sg:address":"La Carrera, S/n",
    "sg:city":"La Carrera",
    "sg:orig_category":"Fabricaci\u00d3n, Comercio De Muebles Para Ni\u00d1os",
    "sg:phone":"+34 985 74 13 33",
    "sg:postcode":"33519",
    "sg:province":"Asturias",
    "wof:name":"Fabrica De Muebles Viella S.l.",
    "wof:placetype":"venue"
},
  "geometry": {"coordinates":[-5.6250481606,43.442855835],"type":"Point"}
}