{
  "type": "Feature",
  "properties": {
    "addr:full":"Calle de Juan Xxiii, 6 Torreblanca Castell\u00f3n 12596",
    "addr:housenumber":"6",
    "addr:postcode":"12596",
    "addr:street":"Calle De Juan Xxiii;Castello\u0301N",
    "iso:country":"ES",
    "sg:address":"Calle de Juan Xxiii, 6",
    "sg:city":"Torreblanca",
    "sg:orig_category":"Quincaller\u00cda (al Por Menor)",
    "sg:phone":"+34 964 42 08 61",
    "sg:postcode":"12596",
    "sg:province":"Castell\u00f3n",
    "wof:name":"Gomez Garcia Jose",
    "wof:placetype":"venue"
},
  "geometry": {"coordinates":[0.1983959973,40.217956543],"type":"Point"}
}