{
  "type": "Feature",
  "properties": {
    "iso:country":"ES",
    "sg:address":"Calle de Paeque, 13",
    "sg:city":"Alalpardo",
    "sg:orig_category":"Panader\u00cda Industrial: Panes, Boller\u00cda (al Por Menor)",
    "sg:phone":"+34 916 20 23 08",
    "sg:postcode":"28130",
    "sg:province":"Madrid",
    "wof:name":"Adipan S.a",
    "wof:placetype":"venue"
},
  "geometry": {"coordinates":[-3.470032692,40.6334609985],"type":"Point"}
}