{
  "type": "Feature",
  "properties": {
    "iso:country":"ES",
    "sg:address":"Calle de Pascual Y Genis, 3",
    "sg:city":"Valencia",
    "sg:orig_category":"Inmobiliaria (agencias)",
    "sg:phone":"+34 963 51 62 55",
    "sg:postcode":"46002",
    "sg:province":"Valencia",
    "wof:name":"Albiach Servicios Inmobiliaros S.l.",
    "wof:placetype":"venue"
},
  "geometry": {"coordinates":[-0.3738785088,39.4701766968],"type":"Point"}
}