{
  "type": "Feature",
  "properties": {
    "iso:country":"ES",
    "sg:address":"Cra Madrid-cadiz-pi Llave Andaluc, Km. 0296,0",
    "sg:city":"Bailen",
    "sg:orig_category":"Agentes, Concesionarios Y Sucursales De Veh\u00cdculos",
    "sg:phone":"+34 953 67 15 25",
    "sg:postcode":"23710",
    "sg:province":"Ja\u00e9n",
    "wof:name":"Automoviles Isabel S.l",
    "wof:placetype":"venue"
},
  "geometry": {"coordinates":[-3.7710540295,38.0965309143],"type":"Point"}
}