{
  "type": "Feature",
  "properties": {
    "iso:country":"ES",
    "sg:address":"Coron, 18",
    "sg:city":"Coron",
    "sg:orig_category":"Semiller\u00cdas",
    "sg:phone":"+34 986 56 11 37",
    "sg:postcode":"36629",
    "sg:province":"Pontevedra",
    "wof:name":"Vazquez Oubi\u00f1a Luis",
    "wof:placetype":"venue"
},
  "geometry": {"coordinates":[-8.808968544,42.5699424744],"type":"Point"}
}