{
  "type": "Feature",
  "properties": {
    "addr:full":"Ctra Cadiz-malaga, Km. 0154,0 Estepona M\u00e1laga 29680",
    "addr:postcode":"29680",
    "addr:street":"Ctra Cadiz-Malaga Km. 0154,0;Ma\u0301Laga",
    "iso:country":"ES",
    "sg:address":"Ctra Cadiz-malaga, Km. 0154,0",
    "sg:city":"Estepona",
    "sg:orig_category":"Distribuci\u00d3n De Petr\u00d3leo Y Derivados",
    "sg:phone":"+34 952 80 71 51",
    "sg:postcode":"29680",
    "sg:province":"M\u00e1laga",
    "wof:name":"Explotaciones Herrero S.l.",
    "wof:placetype":"venue"
},
  "geometry": {"coordinates":[-5.1452140808,36.4275817871],"type":"Point"}
}