{
  "type": "Feature",
  "properties": {
    "addr:full":"Cno. Malatones, 66 Algete Madrid 28110",
    "addr:housenumber":"66",
    "addr:postcode":"28110",
    "addr:street":"Malatones",
    "iso:country":"ES",
    "sg:address":"Cno. Malatones, 66",
    "sg:city":"Algete",
    "sg:orig_category":"Organismos De Reclutamiento",
    "sg:phone":"+34 916 28 91 39",
    "sg:postcode":"28110",
    "sg:province":"Madrid",
    "wof:name":"Norkom Empresas Profesionales Sl",
    "wof:placetype":"venue"
},
  "geometry": {"coordinates":[-3.4999940395,40.5979003906],"type":"Point"}
}