{
  "type": "Feature",
  "properties": {
    "addr:full":"Calle de Juan Rios Garcia, Doctor, 21 Melilla Melilla 52003",
    "addr:housenumber":"21",
    "addr:postcode":"52003",
    "addr:street":"Calle De Juan Rios Garcia Doctor",
    "iso:country":"ES",
    "sg:address":"Calle de Juan Rios Garcia, Doctor, 21",
    "sg:city":"Melilla",
    "sg:orig_category":"Electrodom\u00c9sticos (fabricaci\u00d3n, Al Por Mayor)",
    "sg:phone":"+34 952 68 12 81",
    "sg:postcode":"52003",
    "sg:province":"Melilla",
    "wof:name":"Casa Ros S. A.",
    "wof:placetype":"venue"
},
  "geometry": {"coordinates":[-2.955919981,35.3033714294],"type":"Point"}
}