{
  "type": "Feature",
  "properties": {
    "iso:country":"ES",
    "sg:address":"Luis Santangel, 2",
    "sg:city":"Museros",
    "sg:orig_category":"Fabricaci\u00d3n, Venta, Instalaci\u00d3n De R\u00d3tulos, De R\u00d3tulos Luminosos",
    "sg:phone":"+34 961 49 52 03",
    "sg:postcode":"46136",
    "sg:province":"Valencia",
    "wof:name":"Deconeon S.l.",
    "wof:placetype":"venue"
},
  "geometry": {"coordinates":[-0.333178997,39.5593528748],"type":"Point"}
}