{
  "type": "Feature",
  "properties": {
    "iso:country":"ES",
    "sg:address":"Carrer de Ciutat D'elx, 24",
    "sg:city":"Barcelona",
    "sg:orig_category":"Quincaller\u00cda (al Por Menor)",
    "sg:phone":"+34 933 52 90 93",
    "sg:postcode":"08027",
    "sg:province":"Barcelona",
    "wof:name":"Martinez Verdu Pilar",
    "wof:placetype":"venue"
},
  "geometry": {"coordinates":[2.1907556057,41.4217567444],"type":"Point"}
}