{
  "type": "Feature",
  "properties": {
    "iso:country":"ES",
    "sg:address":"Urb Puerta De Hierro, 2",
    "sg:city":"Rodeo",
    "sg:orig_category":"Bebidas",
    "sg:phone":"+34 952 45 20 43",
    "sg:postcode":"29100",
    "sg:province":"M\u00e1laga",
    "wof:name":"Lucena Caro Francisco",
    "wof:placetype":"venue"
},
  "geometry": {"coordinates":[-4.7576842308,36.659740448],"type":"Point"}
}