{
  "type": "Feature",
  "properties": {
    "iso:country":"ES",
    "sg:address":"Plaz Constitucion, 5",
    "sg:city":"Cangas",
    "sg:orig_category":"Panader\u00cdas, Panader\u00cdas",
    "sg:phone":"+34 986 30 20 33",
    "sg:postcode":"36940",
    "sg:province":"Pontevedra",
    "wof:name":"Iglesias Rodal Lourdes",
    "wof:placetype":"venue"
},
  "geometry": {"coordinates":[-8.8184690475,42.2741928101],"type":"Point"}
}