{
  "type": "Feature",
  "properties": {
    "iso:country":"ES",
    "sg:address":"Avda E. Mtnez Garrido-alcalde, 77",
    "sg:city":"Vigo",
    "sg:orig_category":"Contenedores (mercanc\u00cdas)",
    "sg:phone":"+34 986 37 27 06",
    "sg:postcode":"36205",
    "sg:province":"Pontevedra",
    "wof:name":"Transportes Mi Paquito S.l.",
    "wof:placetype":"venue"
},
  "geometry": {"coordinates":[-8.7078924179,42.2242851257],"type":"Point"}
}