{
  "type": "Feature",
  "properties": {
    "iso:country":"ES",
    "sg:address":"Rbla San Julian (de), 56",
    "sg:city":"Teruel",
    "sg:orig_category":"Empresas De Carpinter\u00cda De Madera",
    "sg:phone":"+34 978 60 66 54",
    "sg:postcode":"44003",
    "sg:province":"Teruel",
    "wof:name":"Carpinteria San Julian S.a.l.",
    "wof:placetype":"venue"
},
  "geometry": {"coordinates":[-1.1000239849,40.342212677],"type":"Point"}
}