{
  "type": "Feature",
  "properties": {
    "addr:full":"Rua De Fabrica, 13 Fabrica La Coru\u00f1a 15680",
    "addr:housenumber":"13",
    "addr:postcode":"15680",
    "addr:street":"Rua De Fabrica;La Corun\u0303A",
    "iso:country":"ES",
    "sg:address":"Rua De Fabrica, 13",
    "sg:city":"Fabrica",
    "sg:orig_category":"Ropa Para Beb\u00c9s Y Ni\u00d1os (confecci\u00d3n, Al Por Mayor)",
    "sg:phone":"+34 981 68 18 16",
    "sg:postcode":"15680",
    "sg:province":"La Coru\u00f1a",
    "wof:name":"Ruibal Santos Maria Pilar",
    "wof:placetype":"venue"
},
  "geometry": {"coordinates":[-8.4072790146,43.0771408081],"type":"Point"}
}