{
  "type": "Feature",
  "properties": {
    "iso:country":"ES",
    "sg:address":"Osintxu Auzoa, 139",
    "sg:city":"Osintxu",
    "sg:orig_category":"Distribuci\u00d3n De Petr\u00d3leo Y Derivados",
    "sg:phone":"+34 943 76 53 74",
    "sg:postcode":"20580",
    "sg:province":"Guip\u00f9zcoa",
    "wof:name":"Muniola S.l.",
    "wof:placetype":"venue"
},
  "geometry": {"coordinates":[-2.4046969414,43.1560211182],"type":"Point"}
}