{
  "type": "Feature",
  "properties": {
    "iso:country":"ES",
    "sg:address":"Ctra Calaf (de), S/n",
    "sg:city":"Ponts",
    "sg:orig_category":"Mec\u00c1nico Del Autom\u00d3vil",
    "sg:phone":"+34 973 46 00 34",
    "sg:postcode":"25740",
    "sg:province":"Lleida",
    "wof:name":"Call Pons Salvador",
    "wof:placetype":"venue"
},
  "geometry": {"coordinates":[1.1891249418,41.912021637],"type":"Point"}
}