{
  "type": "Feature",
  "properties": {
    "addr:full":"Ctra Cuestilla (la), 29 Cuestilla Las Palmas 35414",
    "addr:housenumber":"29",
    "addr:postcode":"35414",
    "addr:street":"Ctra Cuestilla La;Las Palmas",
    "iso:country":"ES",
    "sg:address":"Ctra Cuestilla (la), 29",
    "sg:city":"Cuestilla",
    "sg:orig_category":"Compraventa De Antig\u00dcedades",
    "sg:phone":"+34 928 62 73 72",
    "sg:postcode":"35414",
    "sg:province":"Las Palmas",
    "wof:name":"Baez Rodriguez Jorge Roberto",
    "wof:placetype":"venue"
},
  "geometry": {"coordinates":[-15.5317401886,28.146730423],"type":"Point"}
}