{
  "type": "Feature",
  "properties": {
    "addr:full":"Carr Pare Soler, 6 Lleida Lleida 25003",
    "addr:housenumber":"6",
    "addr:postcode":"25003",
    "addr:street":"Carr Pare Soler",
    "iso:country":"ES",
    "sg:address":"Carr Pare Soler, 6",
    "sg:city":"Lleida",
    "sg:orig_category":"Marketing Directo",
    "sg:phone":"+34 973 28 14 66",
    "sg:postcode":"25003",
    "sg:province":"Lleida",
    "wof:name":"Divulgacion Publicitaria Comercial S.l.",
    "wof:placetype":"venue"
},
  "geometry": {"coordinates":[0.6171370149,41.6132621765],"type":"Point"}
}