{
  "type": "Feature",
  "properties": {
    "iso:country":"ES",
    "sg:address":"Calle de Canteros (de Los), 5",
    "sg:city":"Colmenar Viejo",
    "sg:orig_category":"Chapister\u00cda",
    "sg:phone":"+34 918 46 16 18",
    "sg:postcode":"28770",
    "sg:province":"Madrid",
    "wof:name":"Habecar Talleres S.l.",
    "wof:placetype":"venue"
},
  "geometry": {"coordinates":[-3.7606406212,40.6623840332],"type":"Point"}
}