{
  "type": "Feature",
  "properties": {
    "addr:full":"Calle de General Serrano, 8 Santa Cruz De Tenerife Santa Cruz De Tenerife 38004",
    "addr:housenumber":"8",
    "addr:postcode":"38004",
    "addr:street":"Calle De General Serrano",
    "iso:country":"ES",
    "sg:address":"Calle de General Serrano, 8",
    "sg:city":"Santa Cruz De Tenerife",
    "sg:orig_category":"M\u00c9dicos: Ginecolog\u00cda Y Obstetricia",
    "sg:phone":"+34 922 27 38 07",
    "sg:postcode":"38004",
    "sg:province":"Santa Cruz De Tenerife",
    "wof:name":"Mendez Mora Domingo Ramon",
    "wof:placetype":"venue"
},
  "geometry": {"coordinates":[-16.2566986084,28.4663219452],"type":"Point"}
}