{
  "type": "Feature",
  "properties": {
    "addr:full":"Pso D'atzavares, 34 Elche Alicante 03203",
    "addr:housenumber":"34",
    "addr:postcode":"03203",
    "addr:street":"Pso D'Atzavares",
    "iso:country":"ES",
    "sg:address":"Pso D'atzavares, 34",
    "sg:city":"Elche",
    "sg:orig_category":"Ferreter\u00cda (diversos)",
    "sg:phone":"+34 965 40 66 19",
    "sg:postcode":"03203",
    "sg:province":"Alicante",
    "wof:name":"Hafele Herrajes Espa\u00f1a S.l.",
    "wof:placetype":"venue"
},
  "geometry": {"coordinates":[-0.6616439819,38.263710022],"type":"Point"}
}