{
  "type": "Feature",
  "properties": {
    "iso:country":"ES",
    "sg:address":"Avda Gri\u00d1on, 6",
    "sg:city":"Humanes De Madrid",
    "sg:orig_category":"Agentes, Concesionarios Y Sucursales De Veh\u00cdculos",
    "sg:phone":"+34 916 04 05 69",
    "sg:postcode":"28970",
    "sg:province":"Madrid",
    "wof:name":"Encabo Andrino Eugenio",
    "wof:placetype":"venue"
},
  "geometry": {"coordinates":[-3.8335299492,40.2463378906],"type":"Point"}
}