{
  "type": "Feature",
  "properties": {
    "iso:country":"ES",
    "sg:address":"Avda Mijas, 5",
    "sg:city":"Fuengirola",
    "sg:orig_category":"Procuradores",
    "sg:phone":"+34 952 46 14 53",
    "sg:postcode":"29640",
    "sg:province":"M\u00e1laga",
    "wof:name":"Lopez Alvarez Antonio Jose",
    "wof:placetype":"venue"
},
  "geometry": {"coordinates":[-4.6273999214,36.5418014526],"type":"Point"}
}