{
  "type": "Feature",
  "properties": {
    "iso:country":"ES",
    "sg:address":"Calle de Juan De Austria, 83",
    "sg:city":"Pto. Rosario",
    "sg:orig_category":"Alimentaci\u00d3n General (al Por Menor)",
    "sg:phone":"+34 928 53 31 65",
    "sg:postcode":"35600",
    "sg:province":"Las Palmas",
    "wof:name":"Distribuciones Rosibel Fuerteagarete,s.l.",
    "wof:placetype":"venue"
},
  "geometry": {"coordinates":[-13.8488988876,28.5028495789],"type":"Point"}
}