{
  "type": "Feature",
  "properties": {
    "addr:full":"Carrer de Llevant, S/n Montcada Centre Barcelona 08110",
    "addr:housenumber":"s / n",
    "addr:postcode":"08110",
    "addr:street":"Carrer De Llevant",
    "iso:country":"ES",
    "sg:address":"Carrer de Llevant, S/n",
    "sg:city":"Montcada Centre",
    "sg:orig_category":"Molduras, Junquillos, Listones Y Molduras Perforadas",
    "sg:phone":"+34 935 64 41 83",
    "sg:postcode":"08110",
    "sg:province":"Barcelona",
    "wof:name":"Calvente Delgado Alfonso",
    "wof:placetype":"venue"
},
  "geometry": {"coordinates":[2.1877300739,41.4773292542],"type":"Point"}
}