{
  "type": "Feature",
  "properties": {
    "iso:country":"ES",
    "sg:address":"Cruz De Barkazio, 6",
    "sg:city":"Iru\u00f1a",
    "sg:orig_category":"Tintes (fabricaci\u00d3n, Al Por Mayor)",
    "sg:phone":"+34 948 31 50 50",
    "sg:postcode":"31014",
    "sg:province":"Navarra",
    "wof:name":"Tintorerias Navarras S.l.",
    "wof:placetype":"venue"
},
  "geometry": {"coordinates":[-1.6487079859,42.8271751404],"type":"Point"}
}