{
  "type": "Feature",
  "properties": {
    "iso:country":"ES",
    "sg:address":"Pl Font (de La), 2",
    "sg:city":"Montornes Centre",
    "sg:orig_category":"Droguer\u00cdas (al Por Menor)",
    "sg:phone":"+34 935 68 09 39",
    "sg:postcode":"08170",
    "sg:province":"Barcelona",
    "wof:name":"Elvira Primero Benito",
    "wof:placetype":"venue"
},
  "geometry": {"coordinates":[2.263917923,41.5419197083],"type":"Point"}
}