{
  "type": "Feature",
  "properties": {
    "iso:country":"ES",
    "sg:address":"Pg Fabra I Puig, 274",
    "sg:city":"Barcelona",
    "sg:orig_category":"Asociaciones, Organismos Culturales Y Socioeducativos",
    "sg:phone":"+34 934 20 66 51",
    "sg:postcode":"08031",
    "sg:province":"Barcelona",
    "wof:name":"Ajuntament De Barcelona",
    "wof:placetype":"venue"
},
  "geometry": {"coordinates":[2.1732904911,41.4303359985],"type":"Point"}
}