{
  "type": "Feature",
  "properties": {
    "iso:country":"ES",
    "sg:address":"Rbla Marina, S/n",
    "sg:city":"Hospitalet Llobregat",
    "sg:orig_category":"Charcuter\u00cdas (al Por Mayor)",
    "sg:phone":"+34 933 36 45 60",
    "sg:postcode":"08907",
    "sg:province":"Barcelona",
    "wof:name":"Ciria Bravo Jose",
    "wof:placetype":"venue"
},
  "geometry": {"coordinates":[2.1112101078,41.3508987427],"type":"Point"}
}