{
  "type": "Feature",
  "properties": {
    "addr:full":"Carrer de Parellades, 40 Sitges Barcelona 08870",
    "addr:housenumber":"40",
    "addr:postcode":"08870",
    "addr:street":"Carrer De Parellades",
    "iso:country":"ES",
    "sg:address":"Carrer de Parellades, 40",
    "sg:city":"Sitges",
    "sg:orig_category":"Cajas De Ahorro",
    "sg:phone":"+34 938 94 91 37",
    "sg:postcode":"08870",
    "sg:province":"Barcelona",
    "sg:website":"www.caixasabadell.es",
    "wof:name":"Caixa D'estalvis Sabadell",
    "wof:placetype":"venue"
},
  "geometry": {"coordinates":[1.8079960346,41.2364578247],"type":"Point"}
}