{
  "type": "Feature",
  "properties": {
    "iso:country":"ES",
    "sg:address":"Carrer de Marina, 27",
    "sg:city":"Mallorquines",
    "sg:orig_category":"Colchones (fabricaci\u00d3n, Al Por Mayor, Al Por Menor)",
    "sg:phone":"+34 934 69 29 55",
    "sg:postcode":"08390",
    "sg:province":"Barcelona",
    "wof:name":"Tarrago Fageda Ramon",
    "wof:placetype":"venue"
},
  "geometry": {"coordinates":[2.2785899639,41.4666290283],"type":"Point"}
}