{
  "type": "Feature",
  "properties": {
    "iso:country":"ES",
    "sg:address":"Carr Jaume I, 30",
    "sg:city":"Girona",
    "sg:orig_category":"Asesor\u00cda Sobre Comunicaci\u00d3n De Empresas",
    "sg:phone":"+34 972 41 09 75",
    "sg:postcode":"17001",
    "sg:province":"Girona",
    "wof:name":"Maso & Fustero Assessors Associats S. L.",
    "wof:placetype":"venue"
},
  "geometry": {"coordinates":[2.8203120232,41.9844322205],"type":"Point"}
}