{
  "type": "Feature",
  "properties": {
    "iso:country":"ES",
    "sg:address":"Major, 3",
    "sg:city":"Castellbo",
    "sg:orig_category":"Administraciones Regionales, Departamentales Y Locales",
    "sg:phone":"+34 973 35 21 57",
    "sg:postcode":"25712",
    "sg:province":"Lleida",
    "wof:name":"Entidad Local Menor Valle Y Villa Castellbo. Sant Andreu",
    "wof:placetype":"venue"
},
  "geometry": {"coordinates":[1.3543889523,42.3749885559],"type":"Point"}
}