{
  "type": "Feature",
  "properties": {
    "addr:full":"Carrer de Vapor Gordils, 3 Mataro Barcelona 08304",
    "addr:housenumber":"3",
    "addr:postcode":"08304",
    "addr:street":"Carrer De Vapor Gordils",
    "iso:country":"ES",
    "sg:address":"Carrer de Vapor Gordils, 3",
    "sg:city":"Mataro",
    "sg:orig_category":"Hilaturas, Hilos Y Actividades Relacionadas",
    "sg:phone":"+34 937 90 49 70",
    "sg:postcode":"08304",
    "sg:province":"Barcelona",
    "wof:name":"Sanchez Escalzo David",
    "wof:placetype":"venue"
},
  "geometry": {"coordinates":[2.4529910088,41.5523300171],"type":"Point"}
}