{
  "type": "Feature",
  "properties": {
    "addr:full":"Avda Gernikako Arbola, 62 Barakaldo Vizcaya 48902",
    "addr:housenumber":"62",
    "addr:postcode":"48902",
    "addr:street":"Avda Gernikako Arbola",
    "iso:country":"ES",
    "sg:address":"Avda Gernikako Arbola, 62",
    "sg:city":"Barakaldo",
    "sg:orig_category":"Ense\u00d1anza Variada",
    "sg:phone":"+34 944 38 71 38",
    "sg:postcode":"48902",
    "sg:province":"Vizcaya",
    "wof:name":"Manuel Miguel Hierro Gutierrez",
    "wof:placetype":"venue"
},
  "geometry": {"coordinates":[-2.9987800121,43.2942123413],"type":"Point"}
}