{
  "type": "Feature",
  "properties": {
    "iso:country":"ES",
    "sg:address":"Torrent D'en Pregaria, 7",
    "sg:city":"Mataro",
    "sg:orig_category":"Bisuter\u00cda, Joyer\u00cda, Relojer\u00cda (al Por Menor)",
    "sg:phone":"+34 937 57 38 79",
    "sg:postcode":"08304",
    "sg:province":"Barcelona",
    "wof:name":"Aurum S.c.c.l.",
    "wof:placetype":"venue"
},
  "geometry": {"coordinates":[2.4405415058,41.5529747009],"type":"Point"}
}