{
  "type": "Feature",
  "properties": {
    "addr:full":"Calle de Jumilla, 70 Yecla Murcia 30510",
    "addr:housenumber":"70",
    "addr:postcode":"30510",
    "addr:street":"Calle De Jumilla",
    "iso:country":"ES",
    "sg:address":"Calle de Jumilla, 70",
    "sg:city":"Yecla",
    "sg:orig_category":"Reposter\u00cdas",
    "sg:phone":"+34 968 79 41 22",
    "sg:postcode":"30510",
    "sg:province":"Murcia",
    "wof:name":"Fernandez Lopez Antonio",
    "wof:placetype":"venue"
},
  "geometry": {"coordinates":[-1.1217410564,38.6127319336],"type":"Point"}
}