{
  "type": "Feature",
  "properties": {
    "iso:country":"ES",
    "sg:address":"Bo. Bakiola, 53",
    "sg:city":"Arrankudiaga",
    "sg:orig_category":"Rectificaci\u00d3n, Mecanizado, Fresado",
    "sg:phone":"+34 946 48 00 30",
    "sg:postcode":"48498",
    "sg:province":"Vizcaya",
    "wof:name":"Talleres Herland S.l.",
    "wof:placetype":"venue"
},
  "geometry": {"coordinates":[-2.9109690189,43.1784095764],"type":"Point"}
}