{
  "type": "Feature",
  "properties": {
    "addr:full":"Avda Puerto, 45 Sada La Coru\u00f1a 15160",
    "addr:housenumber":"45",
    "addr:postcode":"15160",
    "addr:street":"Avda Puerto;La",
    "iso:country":"ES",
    "sg:address":"Avda Puerto, 45",
    "sg:city":"Sada",
    "sg:orig_category":"Restaurantes",
    "sg:phone":"+34 981 62 35 03",
    "sg:postcode":"15160",
    "sg:province":"La Coru\u00f1a",
    "wof:name":"Diez Area Juan",
    "wof:placetype":"venue"
},
  "geometry": {"coordinates":[-8.2478904724,43.3630409241],"type":"Point"}
}