{
  "type": "Feature",
  "properties": {
    "iso:country":"ES",
    "sg:address":"Carr Hernan Cortes, 25",
    "sg:city":"Burjassot",
    "sg:orig_category":"Empresas De Carpinter\u00cda De Madera",
    "sg:phone":"+34 963 90 28 17",
    "sg:postcode":"46100",
    "sg:province":"Valencia",
    "wof:name":"Rubio Drac Miguel Juan",
    "wof:placetype":"venue"
},
  "geometry": {"coordinates":[-0.4176790118,39.5117912292],"type":"Point"}
}