{
  "type": "Feature",
  "properties": {
    "addr:full":"Rua Vazquez De Parga, 4 Carballo La Coru\u00f1a 15100",
    "addr:housenumber":"4",
    "addr:postcode":"15100",
    "addr:street":"Rua Vazquez De Parga;La Corun\u0303A",
    "iso:country":"ES",
    "sg:address":"Rua Vazquez De Parga, 4",
    "sg:city":"Carballo",
    "sg:orig_category":"Peluqueros: De Se\u00d1oras",
    "sg:phone":"+34 981 70 04 61",
    "sg:postcode":"15100",
    "sg:province":"La Coru\u00f1a",
    "wof:name":"Cabeza Torres Maria Jose",
    "wof:placetype":"venue"
},
  "geometry": {"coordinates":[-8.686293602,43.2203025818],"type":"Point"}
}