{
  "type": "Feature",
  "properties": {
    "iso:country":"ES",
    "sg:address":"Calle de Obispo Gonzalez, 11",
    "sg:city":"Jaen",
    "sg:orig_category":"Florister\u00cdas",
    "sg:phone":"+34 953 23 33 47",
    "sg:postcode":"23002",
    "sg:province":"Ja\u00e9n",
    "wof:name":"Cano Cardenas Rita Maria",
    "wof:placetype":"venue"
},
  "geometry": {"coordinates":[-3.7916209698,37.7641372681],"type":"Point"}
}