{
  "type": "Feature",
  "properties": {
    "addr:full":"Calle de Aladino, 17 Torremolinos M\u00e1laga 29620",
    "addr:housenumber":"17",
    "addr:postcode":"29620",
    "addr:street":"Calle De Aladino;Ma\u0301Laga",
    "iso:country":"ES",
    "sg:address":"Calle de Aladino, 17",
    "sg:city":"Torremolinos",
    "sg:orig_category":"M\u00c9dicos: Estomatolog\u00cda",
    "sg:phone":"+34 952 38 55 24",
    "sg:postcode":"29620",
    "sg:province":"M\u00e1laga",
    "wof:name":"Suils Ciudad Carlos",
    "wof:placetype":"venue"
},
  "geometry": {"coordinates":[-4.5055499077,36.6099739075],"type":"Point"}
}