{
  "type": "Feature",
  "properties": {
    "iso:country":"ES",
    "sg:address":"Avda Nia Coca, 13",
    "sg:city":"Aspe",
    "sg:orig_category":"Electrodom\u00c9sticos (al Por Menor)",
    "sg:phone":"+34 965 49 08 78",
    "sg:postcode":"03680",
    "sg:province":"Alicante",
    "wof:name":"Gras Electrodomesticos S.l.",
    "wof:placetype":"venue"
},
  "geometry": {"coordinates":[-0.761820972,38.3427696228],"type":"Point"}
}