{
  "type": "Feature",
  "properties": {
    "iso:country":"ES",
    "sg:address":"Avgd Blondel, 54",
    "sg:city":"Lleida",
    "sg:orig_category":"Agentes Generales De Seguros",
    "sg:phone":"+34 973 27 80 58",
    "sg:postcode":"25002",
    "sg:province":"Lleida",
    "wof:name":"Moix Monta\u00f1ola Jose Maria",
    "wof:placetype":"venue"
},
  "geometry": {"coordinates":[0.6246899962,41.6130867004],"type":"Point"}
}