{
  "type": "Feature",
  "properties": {
    "iso:country":"ES",
    "sg:address":"Calle de Alicante, 105",
    "sg:city":"San Vicente Del Raspeig-sant Vicent Del Raspeig",
    "sg:orig_category":"Papeler\u00cdas, Librer\u00cdas",
    "sg:phone":"+34 965 67 13 89",
    "sg:postcode":"03690",
    "sg:province":"Alicante",
    "wof:name":"Perez Izquierdo Jose Daniel",
    "wof:placetype":"venue"
},
  "geometry": {"coordinates":[-0.5081877112,38.3851165771],"type":"Point"}
}