{
  "type": "Feature",
  "properties": {
    "iso:country":"ES",
    "sg:address":"Calle de Filipinas, 4",
    "sg:city":"Gijon",
    "sg:orig_category":"Promotores Constructores",
    "sg:phone":"+34 985 32 46 06",
    "sg:postcode":"33212",
    "sg:province":"Asturias",
    "wof:name":"Gonzalez Moran Emilio",
    "wof:placetype":"venue"
},
  "geometry": {"coordinates":[-5.694067955,43.5395812988],"type":"Point"}
}