{
  "type": "Feature",
  "properties": {
    "addr:full":"Calle de Infanta Mercedes, 55 Madrid Madrid 28020",
    "addr:housenumber":"55",
    "addr:postcode":"madrid;28020",
    "addr:street":"Calle De Infanta Mercedes",
    "iso:country":"ES",
    "sg:address":"Calle de Infanta Mercedes, 55",
    "sg:city":"Madrid",
    "sg:classifiers":[
        {
            "category":"Personal",
            "subcategory":"Barber",
            "type":"Services"
        }
    ],
    "sg:phone":"+34 915 70 15 86",
    "sg:postcode":"28020",
    "sg:province":"Madrid",
    "sg:tags":[
        "caballeros",
        "de",
        "peluqueros"
    ],
    "wof:name":"Porras Lopez Francisco",
    "wof:placetype":"venue"
},
  "geometry": {"coordinates":[-3.697247982,40.4589805603],"type":"Point"}
}