{
  "type": "Feature",
  "properties": {
    "iso:country":"ES",
    "sg:address":"Calle de Goleta, 28",
    "sg:city":"Pasito Blanco",
    "sg:orig_category":"Inmobiliaria (agencias)",
    "sg:phone":"+34 928 14 34 25",
    "sg:postcode":"35100",
    "sg:province":"Las Palmas",
    "wof:name":"Manna S.l",
    "wof:placetype":"venue"
},
  "geometry": {"coordinates":[-15.6225013733,27.7482299805],"type":"Point"}
}