{
  "type": "Feature",
  "properties": {
    "iso:country":"ES",
    "sg:address":"Av. Valladolid, 37",
    "sg:city":"Madrid",
    "sg:orig_category":"Empresas De Limpieza",
    "sg:phone":"+34 915 59 63 67",
    "sg:postcode":"28008",
    "sg:province":"Madrid",
    "wof:name":"Iman Limpieza Y Mantenimiento De Oficinas S. A.",
    "wof:placetype":"venue"
},
  "geometry": {"coordinates":[-3.7291910648,40.4273605347],"type":"Point"}
}