{
  "type": "Feature",
  "properties": {
    "iso:country":"ES",
    "sg:address":"Calle de Murriarte, 23",
    "sg:city":"Samaniego",
    "sg:orig_category":"Producci\u00d3n, Venta De Productos De Agricultura Biol\u00d3gica",
    "sg:phone":"+34 945 06 31 74",
    "sg:postcode":"01307",
    "sg:province":"\u00c1lava",
    "wof:name":"Cesar Saenz De Samaniego Zu\u00f1eda",
    "wof:placetype":"venue"
},
  "geometry": {"coordinates":[-2.6756649017,42.5692481995],"type":"Point"}
}