{
  "type": "Feature",
  "properties": {
    "iso:country":"ES",
    "sg:address":"Calle de San Patricio, 10",
    "sg:city":"Catedral",
    "sg:orig_category":"Ense\u00d1anza: Comercio, Gesti\u00d3n, Inform\u00c1tica",
    "sg:phone":"+34 968 21 50 62",
    "sg:postcode":"30004",
    "sg:province":"Murcia",
    "wof:name":"Academia Centro Murcia S.l",
    "wof:placetype":"venue"
},
  "geometry": {"coordinates":[-1.131067,37.983486],"type":"Point"}
}