{
  "type": "Feature",
  "properties": {
    "iso:country":"ES",
    "sg:address":"Ctra San Julian, 83",
    "sg:city":"Teruel",
    "sg:orig_category":"Cerrajer\u00cda, Ferrallista",
    "sg:phone":"+34 978 60 48 24",
    "sg:postcode":"44003",
    "sg:province":"Teruel",
    "wof:name":"Estructura Mantenimiento E Instalaciones",
    "wof:placetype":"venue"
},
  "geometry": {"coordinates":[-1.1016390324,40.3379707336],"type":"Point"}
}