{
  "type": "Feature",
  "properties": {
    "addr:full":"Av Rei En Jaume, 151 Cardedeu Barcelona 08440",
    "addr:housenumber":"151",
    "addr:postcode":"08440",
    "addr:street":"Av Rei En Jaume",
    "iso:country":"ES",
    "sg:address":"Av Rei En Jaume, 151",
    "sg:city":"Cardedeu",
    "sg:orig_category":"Quincaller\u00cda (al Por Menor)",
    "sg:phone":"+34 938 46 11 46",
    "sg:postcode":"08440",
    "sg:province":"Barcelona",
    "wof:name":"Elfeca S.l.",
    "wof:placetype":"venue"
},
  "geometry": {"coordinates":[2.3579499722,41.6369781494],"type":"Point"}
}