{
  "type": "Feature",
  "properties": {
    "iso:country":"ES",
    "sg:address":"Calle de Avila, 8",
    "sg:city":"Bilbao",
    "sg:orig_category":"Estancos",
    "sg:phone":"+34 944 21 23 40",
    "sg:postcode":"48012",
    "sg:province":"Vizcaya",
    "wof:name":"Idoia Percebal Alonso",
    "wof:placetype":"venue"
},
  "geometry": {"coordinates":[-2.9395740032,43.2567558289],"type":"Point"}
}