{
  "type": "Feature",
  "properties": {
    "addr:full":"Ptda Secanet, S/n Agost Alicante 03698",
    "addr:housenumber":"s",
    "addr:postcode":"03698",
    "addr:street":"Ptda Secanet;/ N",
    "iso:country":"ES",
    "sg:address":"Ptda Secanet, S/n",
    "sg:city":"Agost",
    "sg:orig_category":"Arboricultura Y Producci\u00d3n De Frutas",
    "sg:phone":"+34 965 69 13 63",
    "sg:postcode":"03698",
    "sg:province":"Alicante",
    "wof:name":"Pascual Hermanos S.a.",
    "wof:placetype":"venue"
},
  "geometry": {"coordinates":[-0.6398239732,38.439239502],"type":"Point"}
}