{
  "type": "Feature",
  "properties": {
    "addr:full":"Calle de Isabel Colbrand, 6 Madrid Madrid 28050",
    "addr:housenumber":"6",
    "addr:postcode":"28050",
    "addr:street":"Calle De Isabel Colbrand",
    "iso:country":"ES",
    "sg:address":"Calle de Isabel Colbrand, 6",
    "sg:city":"Madrid",
    "sg:orig_category":"Centros Empresariales",
    "sg:phone":"+34 913 58 82 08",
    "sg:postcode":"28050",
    "sg:province":"Madrid",
    "wof:name":"Least Cost Routing Telecom S.l.",
    "wof:placetype":"venue"
},
  "geometry": {"coordinates":[-3.6715488434,40.5140686035],"type":"Point"}
}