{
  "type": "Feature",
  "properties": {
    "addr:full":"Calle de Acorazado Espa\u00d1a, 12 Corralejo Las Palmas 35660",
    "addr:housenumber":"12",
    "addr:postcode":"35660",
    "addr:street":"Calle De Acorazado Espan\u0303A",
    "iso:country":"ES",
    "sg:address":"Calle de Acorazado Espa\u00d1a, 12",
    "sg:city":"Corralejo",
    "sg:orig_category":"Bancos",
    "sg:phone":"+34 928 86 72 65",
    "sg:postcode":"35660",
    "sg:province":"Las Palmas",
    "wof:name":"Master Locutorios S.a.",
    "wof:placetype":"venue"
},
  "geometry": {"coordinates":[-13.8696575165,28.7371997833],"type":"Point"}
}