{
  "type": "Feature",
  "properties": {
    "iso:country":"ES",
    "sg:address":"Carrer de Goya, 4",
    "sg:city":"Playa Muchavista",
    "sg:orig_category":"Doctores En Medicina",
    "sg:phone":"+34 965 65 25 43",
    "sg:postcode":"03560",
    "sg:province":"Alicante",
    "wof:name":"Font Martinez Manuel",
    "wof:placetype":"venue"
},
  "geometry": {"coordinates":[-0.4050090015,38.410774231],"type":"Point"}
}