{
  "type": "Feature",
  "properties": {
    "iso:country":"ES",
    "sg:address":"Avda Reconquista, 14",
    "sg:city":"Toledo",
    "sg:orig_category":"Farmacias",
    "sg:phone":"+34 925 22 03 89",
    "sg:postcode":"45004",
    "sg:province":"Toledo",
    "wof:name":"Farmacia Reconquista C.b.",
    "wof:placetype":"venue"
},
  "geometry": {"coordinates":[-4.0283207893,39.8656921387],"type":"Point"}
}