{
  "type": "Feature",
  "properties": {
    "addr:full":"Calle de San Hermenegildo, 19 Madrid Madrid 28015",
    "addr:housenumber":"19",
    "addr:postcode":"madrid;28015",
    "addr:street":"Calle De San Hermenegildo",
    "iso:country":"ES",
    "sg:address":"Calle de San Hermenegildo, 19",
    "sg:city":"Madrid",
    "sg:orig_category":"Institutos De Belleza",
    "sg:phone":"+34 915 48 29 72",
    "sg:postcode":"28015",
    "sg:province":"Madrid",
    "wof:name":"Centro De Relajacion Integral Kiroconfort S.l.",
    "wof:placetype":"venue"
},
  "geometry": {"coordinates":[-3.7084729671,40.4281959534],"type":"Point"}
}