{
  "type": "Feature",
  "properties": {
    "iso:country":"ES",
    "sg:address":"Pase Cervantes, 7",
    "sg:city":"Vitoria-gasteiz",
    "sg:orig_category":"Arquitectos",
    "sg:phone":"+34 945 13 37 26",
    "sg:postcode":"01007",
    "sg:province":"\u00c1lava",
    "wof:name":"Marimon Alava Enrique",
    "wof:placetype":"venue"
},
  "geometry": {"coordinates":[-2.6909899712,42.8382415771],"type":"Point"}
}