{
  "type": "Feature",
  "properties": {
    "iso:country":"ES",
    "sg:address":"Calle de Argumosa, 1",
    "sg:city":"Torrelavega",
    "sg:orig_category":"Zapatos (al Por Mayor)",
    "sg:phone":"+34 942 88 15 28",
    "sg:postcode":"39300",
    "sg:province":"Cantabria",
    "wof:name":"Diego Jauregui Armando De",
    "wof:placetype":"venue"
},
  "geometry": {"coordinates":[-4.0474624634,43.3493766785],"type":"Point"}
}