{
  "type": "Feature",
  "properties": {
    "iso:country":"ES",
    "sg:address":"Avda Fuente Nueva (de La), 14",
    "sg:city":"San Sebastian De Los Reyes",
    "sg:orig_category":"Inform\u00c1tica: Material Y Suministros",
    "sg:phone":"+34 916 54 21 41",
    "sg:postcode":"28700",
    "sg:province":"Madrid",
    "wof:name":"Domino Amjet Iberica S.a.",
    "wof:placetype":"venue"
},
  "geometry": {"coordinates":[-3.6121480465,40.547618866],"type":"Point"}
}