{
  "type": "Feature",
  "properties": {
    "addr:full":"Carrer de Aljub, De S', 1 Santanyi Islas Baleares 07650",
    "addr:housenumber":"1",
    "addr:postcode":"07650",
    "addr:street":"Carrer De Aljub De S '",
    "iso:country":"ES",
    "sg:address":"Carrer de Aljub, De S', 1",
    "sg:city":"Santanyi",
    "sg:orig_category":"Reposter\u00cdas",
    "sg:phone":"+34 971 65 37 38",
    "sg:postcode":"07650",
    "sg:province":"Islas Baleares",
    "wof:name":"Cuellar Garcia Pedro Antonio",
    "wof:placetype":"venue"
},
  "geometry": {"coordinates":[2.9117100239,39.6136398315],"type":"Point"}
}