{
  "type": "Feature",
  "properties": {
    "iso:country":"ES",
    "sg:address":"Estd Masustegi, 17",
    "sg:city":"Bilbao",
    "sg:orig_category":"Promotores Constructores",
    "sg:phone":"+34 944 41 99 71",
    "sg:postcode":"48002",
    "sg:province":"Vizcaya",
    "wof:name":"Puertas Navarro Raul",
    "wof:placetype":"venue"
},
  "geometry": {"coordinates":[-2.9540650845,43.2556915283],"type":"Point"}
}