{
  "type": "Feature",
  "properties": {
    "iso:country":"ES",
    "sg:address":"Calle de Doctor Montero, 3",
    "sg:city":"Valladolid",
    "sg:orig_category":"Supermercados Y Hipermercados",
    "sg:phone":"+34 983 20 18 52",
    "sg:postcode":"47005",
    "sg:province":"Valladolid",
    "wof:name":"Cenco S. A.",
    "wof:placetype":"venue"
},
  "geometry": {"coordinates":[-4.7151498795,41.6503295898],"type":"Point"}
}