{
  "type": "Feature",
  "properties": {
    "iso:country":"ES",
    "sg:address":"Ctra Vila-sana, Km. 0489,0",
    "sg:city":"Golmes",
    "sg:orig_category":"Fabricaci\u00d3n De Bibliotecas Y Estanter\u00cdas",
    "sg:phone":"+34 973 60 02 50",
    "sg:postcode":"25241",
    "sg:province":"Lleida",
    "sg:website":"www.mecasystem.com",
    "wof:name":"Meca System S. L.",
    "wof:placetype":"venue"
},
  "geometry": {"coordinates":[0.9307550192,41.6376152039],"type":"Point"}
}