{
  "type": "Feature",
  "properties": {
    "addr:full":"Calle de Mayor, 8 Cortiguera Cantabria 39350",
    "addr:housenumber":"8",
    "addr:postcode":"39350",
    "addr:street":"Calle De Mayor",
    "iso:country":"ES",
    "sg:address":"Calle de Mayor, 8",
    "sg:city":"Cortiguera",
    "sg:orig_category":"Molduras, Junquillos, Listones Y Molduras Perforadas",
    "sg:phone":"+34 942 81 02 04",
    "sg:postcode":"39350",
    "sg:province":"Cantabria",
    "wof:name":"Herrera Gomez Avelino",
    "wof:placetype":"venue"
},
  "geometry": {"coordinates":[-4.0422420502,43.4083938599],"type":"Point"}
}