{
  "type": "Feature",
  "properties": {
    "iso:country":"ES",
    "sg:address":"Ctr. Madrid-soria, S/n",
    "sg:city":"Jadraque",
    "sg:orig_category":"Empresas De Carpinter\u00cda De Madera",
    "sg:phone":"+34 949 89 04 27",
    "sg:postcode":"19240",
    "sg:province":"Guadalajara",
    "wof:name":"Garcia Ortega Pablo",
    "wof:placetype":"venue"
},
  "geometry": {"coordinates":[-2.8409426212,41.0839042664],"type":"Point"}
}