{
  "type": "Feature",
  "properties": {
    "iso:country":"ES",
    "sg:address":"Calle de Benito Perez Galdos, 36",
    "sg:city":"Cotillo El",
    "sg:orig_category":"Art\u00cdculos De Aluminio",
    "sg:phone":"+34 928 53 87 83",
    "sg:postcode":"35650",
    "sg:province":"Las Palmas",
    "wof:name":"Gonzalez Bordon Gabriel",
    "wof:placetype":"venue"
},
  "geometry": {"coordinates":[-14.0095481873,28.684387207],"type":"Point"}
}