{
  "type": "Feature",
  "properties": {
    "iso:country":"ES",
    "sg:address":"Cami Martines (les), 131",
    "sg:city":"Terrassa",
    "sg:orig_category":"Centros Empresariales",
    "sg:phone":"+34 937 88 99 22",
    "sg:postcode":"08223",
    "sg:province":"Barcelona",
    "wof:name":"Garcia Riter Susana",
    "wof:placetype":"venue"
},
  "geometry": {"coordinates":[1.9992297888,41.5403366089],"type":"Point"}
}