{
  "type": "Feature",
  "properties": {
    "addr:full":"Carr Horta, 17 Almenar Lleida 25126",
    "addr:housenumber":"17",
    "addr:postcode":"25126",
    "addr:street":"Carr Horta",
    "iso:country":"ES",
    "sg:address":"Carr Horta, 17",
    "sg:city":"Almenar",
    "sg:orig_category":"Peluquer\u00cdas, Peluquer\u00cda Mixta",
    "sg:phone":"+34 973 77 07 05",
    "sg:postcode":"25126",
    "sg:province":"Lleida",
    "wof:name":"Sorolla Raedo Maria Gloria",
    "wof:placetype":"venue"
},
  "geometry": {"coordinates":[0.5697230101,41.7961807251],"type":"Point"}
}