{
  "type": "Feature",
  "properties": {
    "iso:country":"ES",
    "sg:address":"Carr San Juan De Ribera, 48",
    "sg:city":"Canals",
    "sg:orig_category":"Centros De Educaci\u00d3n Especial",
    "sg:phone":"+34 962 24 51 44",
    "sg:postcode":"46650",
    "sg:province":"Valencia",
    "wof:name":"Ayuntamiento De Canals Escuela De Adultos",
    "wof:placetype":"venue"
},
  "geometry": {"coordinates":[-0.5792818069,38.962310791],"type":"Point"}
}