{
  "type": "Feature",
  "properties": {
    "addr:full":"Pol Ind Sepes, 14 Melilla Melilla 52006",
    "addr:housenumber":"14",
    "addr:postcode":"52006",
    "addr:street":"Sepes",
    "iso:country":"ES",
    "sg:address":"Pol Ind Sepes, 14",
    "sg:city":"Melilla",
    "sg:orig_category":"Muebles, Minoristas",
    "sg:phone":"+34 952 67 12 35",
    "sg:postcode":"52006",
    "sg:province":"Melilla",
    "wof:name":"Novo Muebles",
    "wof:placetype":"venue"
},
  "geometry": {"coordinates":[-2.9383699894,35.2764587402],"type":"Point"}
}