{
  "type": "Feature",
  "properties": {
    "addr:full":"Carrer de Freneria, 4 Barcelona Barcelona 08002",
    "addr:housenumber":"4",
    "addr:postcode":"08002",
    "addr:street":"Carrer De Freneria",
    "iso:country":"ES",
    "sg:address":"Carrer de Freneria, 4",
    "sg:city":"Barcelona",
    "sg:orig_category":"Art\u00cdculos De Regalo (al Por Menor)",
    "sg:phone":"+34 933 15 28 56",
    "sg:postcode":"08002",
    "sg:province":"Barcelona",
    "sg:website":"www.cristalia.com",
    "wof:name":"Nuria Grau S.l.",
    "wof:placetype":"venue"
},
  "geometry": {"coordinates":[2.177642107,41.3836288452],"type":"Point"}
}