{
  "type": "Feature",
  "properties": {
    "addr:full":"Calle de Benigafull, 28 Vall D'uixo Castell\u00f3n 12600",
    "addr:housenumber":"28",
    "addr:postcode":"12600",
    "addr:street":"Calle De Benigafull",
    "iso:country":"ES",
    "sg:address":"Calle de Benigafull, 28",
    "sg:city":"Vall D'uixo",
    "sg:orig_category":"Servicios De Telecomunicaciones",
    "sg:phone":"+34 964 66 75 04",
    "sg:postcode":"12600",
    "sg:province":"Castell\u00f3n",
    "wof:name":"Onda Wap Telecomunicaciones S.l.",
    "wof:placetype":"venue"
},
  "geometry": {"coordinates":[-0.2341724038,39.8229751587],"type":"Point"}
}