{
  "type": "Feature",
  "properties": {
    "iso:country":"ES",
    "sg:address":"Calle de Churruca, 5",
    "sg:city":"Madrid",
    "sg:orig_category":"Centros M\u00c9dicos Y Sociales, Dispensarios",
    "sg:phone":"+34 915 32 89 32",
    "sg:postcode":"28004",
    "sg:province":"Madrid",
    "wof:name":"Castillo Recarte Jose Luis",
    "wof:placetype":"venue"
},
  "geometry": {"coordinates":[-3.7007517815,40.4270019531],"type":"Point"}
}