{
  "type": "Feature",
  "properties": {
    "addr:full":"Calle de Costa Del Sol, 10 Madrid Madrid 28033",
    "addr:housenumber":"10",
    "addr:postcode":"madrid;28033",
    "addr:street":"Calle De Costa Del Sol",
    "iso:country":"ES",
    "sg:address":"Calle de Costa Del Sol, 10",
    "sg:city":"Madrid",
    "sg:orig_category":"Centros Comerciales Y Grandes Tiendas",
    "sg:phone":"+34 913 81 44 26",
    "sg:postcode":"28033",
    "sg:province":"Madrid",
    "wof:name":"Li  Pinxu",
    "wof:placetype":"venue"
},
  "geometry": {"coordinates":[-3.6524531841,40.4733009338],"type":"Point"}
}