{
  "type": "Feature",
  "properties": {
    "addr:full":"Av Portmany, De, 1 S. Antoni Portmany Islas Baleares 07820",
    "addr:postcode":"07820",
    "addr:street":"Av Portmany De 1 S. Antoni Portmany",
    "iso:country":"ES",
    "sg:address":"Av Portmany, De, 1",
    "sg:city":"S. Antoni Portmany",
    "sg:orig_category":"Alquiler De Veh\u00cdculos: Turismos Y Utilitarios",
    "sg:phone":"+34 971 34 55 52",
    "sg:postcode":"07820",
    "sg:province":"Islas Baleares",
    "sg:website":"www.karolviajes.com",
    "wof:name":"Karol Agencias De Viajes S. A.",
    "wof:placetype":"venue"
},
  "geometry": {"coordinates":[1.5188339949,39.1094055176],"type":"Point"}
}