{
  "type": "Feature",
  "properties": {
    "addr:full":"Calle de Berenguer Mallol, 9 Valencia Valencia 46022",
    "addr:housenumber":"9",
    "addr:postcode":"46022",
    "addr:street":"Calle De Berenguer Mallol",
    "iso:country":"ES",
    "sg:address":"Calle de Berenguer Mallol, 9",
    "sg:city":"Valencia",
    "sg:orig_category":"Bebidas",
    "sg:phone":"+34 963 30 57 47",
    "sg:postcode":"46022",
    "sg:province":"Valencia",
    "wof:name":"Garcia Montesinos Francisco",
    "wof:placetype":"venue"
},
  "geometry": {"coordinates":[-0.3450976014,39.4652137756],"type":"Point"}
}