{
  "type": "Feature",
  "properties": {
    "iso:country":"ES",
    "sg:address":"Avda Portugal (de), 72",
    "sg:city":"Ourense",
    "sg:orig_category":"Zapatos (al Por Menor)",
    "sg:phone":"+34 988 24 66 94",
    "sg:postcode":"32002",
    "sg:province":"Ourense",
    "wof:name":"Ficuciello Osorio Maria Del Pilar",
    "wof:placetype":"venue"
},
  "geometry": {"coordinates":[-7.8704810143,42.3353805542],"type":"Point"}
}