{
  "type": "Feature",
  "properties": {
    "iso:country":"ES",
    "sg:address":"Avda Espa\u00d1a De, 36",
    "sg:city":"Torremolinos",
    "sg:orig_category":"Asesor\u00cda Fiscal Y Jur\u00cddica",
    "sg:phone":"+34 952 38 88 52",
    "sg:postcode":"29620",
    "sg:province":"M\u00e1laga",
    "wof:name":"Asesoria Dominguez Hoz S.l.",
    "wof:placetype":"venue"
},
  "geometry": {"coordinates":[-4.5102648735,36.6032752991],"type":"Point"}
}