{
  "type": "Feature",
  "properties": {
    "iso:country":"ES",
    "sg:address":"Av Europa, 201",
    "sg:city":"Hospitalet Llobregat",
    "sg:orig_category":"Prot\u00c9sicos Dentales",
    "sg:phone":"+34 933 35 64 14",
    "sg:postcode":"08907",
    "sg:province":"Barcelona",
    "wof:name":"Laboratorio Dental Jl S.l.",
    "wof:placetype":"venue"
},
  "geometry": {"coordinates":[2.1127500534,41.356628418],"type":"Point"}
}