{
  "type": "Feature",
  "properties": {
    "iso:country":"ES",
    "sg:address":"Cust Del Portillo De San Andres, 9",
    "sg:city":"Benavente",
    "sg:orig_category":"Art\u00cdculos De Decoraci\u00d3n",
    "sg:phone":"+34 980 63 65 56",
    "sg:postcode":"49600",
    "sg:province":"Zamora",
    "wof:name":"Vidal Mateos Francisco",
    "wof:placetype":"venue"
},
  "geometry": {"coordinates":[-5.6774291992,41.9989585876],"type":"Point"}
}