{
  "type": "Feature",
  "properties": {
    "addr:full":"Calle de Alcala, 4 Alborea Albacete 02215",
    "addr:housenumber":"4",
    "addr:postcode":"02215",
    "addr:street":"Calle De Alcala",
    "iso:country":"ES",
    "sg:address":"Calle de Alcala, 4",
    "sg:city":"Alborea",
    "sg:orig_category":"Producci\u00d3n, Comercio De Cereales",
    "sg:phone":"+34 967 47 70 97",
    "sg:postcode":"02215",
    "sg:province":"Albacete",
    "wof:name":"Pardo Montejo Jose",
    "wof:placetype":"venue"
},
  "geometry": {"coordinates":[-1.3947989941,39.2775230408],"type":"Point"}
}