{
  "type": "Feature",
  "properties": {
    "iso:country":"ES",
    "sg:address":"Calle de Convento, 19",
    "sg:city":"Villoruela",
    "sg:orig_category":"Cester\u00cda (fabricaci\u00d3n)",
    "sg:phone":"+34 923 35 61 30",
    "sg:postcode":"37339",
    "sg:province":"Salamanca",
    "wof:name":"Artesania Sanchez Chamorro S.l.",
    "wof:placetype":"venue"
},
  "geometry": {"coordinates":[-5.3910942078,41.008972168],"type":"Point"}
}