{
  "type": "Feature",
  "properties": {
    "iso:country":"ES",
    "sg:address":"Ctra Estacion, 1",
    "sg:city":"Calpe",
    "sg:orig_category":"Mec\u00c1nico Del Autom\u00d3vil",
    "sg:phone":"+34 965 83 87 24",
    "sg:postcode":"03710",
    "sg:province":"Alicante",
    "wof:name":"Uwe Werkstatt S.l",
    "wof:placetype":"venue"
},
  "geometry": {"coordinates":[0.0350859985,38.6471824646],"type":"Point"}
}