{
  "type": "Feature",
  "properties": {
    "iso:country":"ES",
    "sg:address":"Calle de Pintor Lorenzo Casanova, 2",
    "sg:city":"Alacant",
    "sg:orig_category":"Abogados",
    "sg:phone":"+34 965 92 57 67",
    "sg:postcode":"03003",
    "sg:province":"Alicante",
    "wof:name":"Amerigo Asin Luis Carlos",
    "wof:placetype":"venue"
},
  "geometry": {"coordinates":[-0.4909796119,38.3414382935],"type":"Point"}
}