{
  "type": "Feature",
  "properties": {
    "iso:country":"ES",
    "sg:address":"Calle de Juan Talavera Heredia, 56",
    "sg:city":"Sevilla",
    "sg:orig_category":"Alimentaci\u00d3n General (al Por Menor)",
    "sg:phone":"+34 954 63 56 45",
    "sg:postcode":"41006",
    "sg:province":"Sevilla",
    "wof:name":"Jimenez Del Rio Jose Maria",
    "wof:placetype":"venue"
},
  "geometry": {"coordinates":[-5.9530849457,37.3705482483],"type":"Point"}
}