{
  "type": "Feature",
  "properties": {
    "addr:full":"Calle de Carmen (el), 10 Noja Cantabria 39180",
    "addr:housenumber":"10",
    "addr:postcode":"39180",
    "addr:street":"Calle De Carmen El",
    "iso:country":"ES",
    "sg:address":"Calle de Carmen (el), 10",
    "sg:city":"Noja",
    "sg:orig_category":"Postigos, Persianas Y Celos\u00cdas",
    "sg:phone":"+34 942 67 50 47",
    "sg:postcode":"39180",
    "sg:province":"Cantabria",
    "wof:name":"Garcia Cerrato Pedro",
    "wof:placetype":"venue"
},
  "geometry": {"coordinates":[-3.5298745632,43.4741706848],"type":"Point"}
}