{
  "type": "Feature",
  "properties": {
    "addr:full":"Praz Igrexa (da), 11 Barco Ourense 32300",
    "addr:housenumber":"11",
    "addr:postcode":"32300",
    "addr:street":"Praz Igrexa Da",
    "iso:country":"ES",
    "sg:address":"Praz Igrexa (da), 11",
    "sg:city":"Barco",
    "sg:orig_category":"Restaurantes",
    "sg:phone":"+34 988 32 01 45",
    "sg:postcode":"32300",
    "sg:province":"Ourense",
    "wof:name":"Restaurante San Mauro S.l.",
    "wof:placetype":"venue"
},
  "geometry": {"coordinates":[-6.9837059975,42.4104614258],"type":"Point"}
}