{
  "type": "Feature",
  "properties": {
    "addr:full":"Plaz Maria Guerrero, S/n Malaga M\u00e1laga 29012",
    "addr:postcode":"29012",
    "addr:street":"Guerrero S / N;Ma\u0301Laga",
    "iso:country":"ES",
    "sg:address":"Plaz Maria Guerrero, S/n",
    "sg:city":"Malaga",
    "sg:orig_category":"Organismos De Desarrollo",
    "sg:phone":"+34 952 22 30 92",
    "sg:postcode":"29012",
    "sg:province":"M\u00e1laga",
    "sg:website":"www.ciedes.es",
    "wof:name":"Fundacion Ciedes-plan Estrategico",
    "wof:placetype":"venue"
},
  "geometry": {"coordinates":[-4.4172430038,36.7227516174],"type":"Point"}
}