{
  "type": "Feature",
  "properties": {
    "addr:full":"Calle de Celleruelo, 3 Pola De Siero Asturias 33510",
    "addr:housenumber":"3",
    "addr:postcode":"33510",
    "addr:street":"Calle De Celleruelo",
    "iso:country":"ES",
    "sg:address":"Calle de Celleruelo, 3",
    "sg:city":"Pola De Siero",
    "sg:orig_category":"Bisuter\u00cda, Joyer\u00cda, Relojer\u00cda (al Por Menor)",
    "sg:phone":"+34 985 72 51 74",
    "sg:postcode":"33510",
    "sg:province":"Asturias",
    "wof:name":"Elena Bembibre C.b.",
    "wof:placetype":"venue"
},
  "geometry": {"coordinates":[-5.6614427567,43.393119812],"type":"Point"}
}