{
  "type": "Feature",
  "properties": {
    "addr:full":"Av Montserrat, 66 Pineda Mar Barcelona 08397",
    "addr:housenumber":"66",
    "addr:postcode":"08397",
    "addr:street":"Av Montserrat;Barcelona",
    "iso:country":"ES",
    "sg:address":"Av Montserrat, 66",
    "sg:city":"Pineda Mar",
    "sg:orig_category":"Asociaciones Y Clubs Deportivos",
    "sg:phone":"+34 937 67 12 84",
    "sg:postcode":"08397",
    "sg:province":"Barcelona",
    "wof:name":"Sotillo Bueno Felisa",
    "wof:placetype":"venue"
},
  "geometry": {"coordinates":[2.6872711182,41.6248092651],"type":"Point"}
}