{
  "type": "Feature",
  "properties": {
    "addr:full":"Calle de Inmaculada Concepcion, 19 Madrid Madrid 28019",
    "addr:housenumber":"19",
    "addr:postcode":"madrid;28019",
    "addr:street":"Calle De Inmaculada Concepcion",
    "iso:country":"ES",
    "sg:address":"Calle de Inmaculada Concepcion, 19",
    "sg:city":"Madrid",
    "sg:orig_category":"Loter\u00cda Y T\u00d3mbola",
    "sg:phone":"+34 915 69 50 75",
    "sg:postcode":"28019",
    "sg:province":"Madrid",
    "wof:name":"Albores Lopez Julio",
    "wof:placetype":"venue"
},
  "geometry": {"coordinates":[-3.7120959759,40.393283844],"type":"Point"}
}