{
  "type": "Feature",
  "properties": {
    "addr:full":"Avda Federico Garcia Lorca, 87 Almeria Almer\u00eda 04004",
    "addr:housenumber":"87",
    "addr:postcode":"04004",
    "addr:street":"Avda Federico Garcia Lorca",
    "iso:country":"ES",
    "sg:address":"Avda Federico Garcia Lorca, 87",
    "sg:city":"Almeria",
    "sg:orig_category":"Colchones (fabricaci\u00d3n, Al Por Mayor, Al Por Menor)",
    "sg:phone":"+34 950 26 02 11",
    "sg:postcode":"04004",
    "sg:province":"Almer\u00eda",
    "wof:name":"Exclusivas Del Mobiliario S.l.",
    "wof:placetype":"venue"
},
  "geometry": {"coordinates":[-2.4588990211,36.840839386],"type":"Point"}
}