{
  "type": "Feature",
  "properties": {
    "addr:full":"Calle de Galileo, 2 Binefar Huesca 22500",
    "addr:housenumber":"2",
    "addr:postcode":"22500",
    "addr:street":"Calle De Galileo",
    "iso:country":"ES",
    "sg:address":"Calle de Galileo, 2",
    "sg:city":"Binefar",
    "sg:orig_category":"Florister\u00cdas",
    "sg:phone":"+34 974 43 14 26",
    "sg:postcode":"22500",
    "sg:province":"Huesca",
    "wof:name":"Abad Llanas Maria Elena",
    "wof:placetype":"venue"
},
  "geometry": {"coordinates":[0.296786,41.851109],"type":"Point"}
}