{
  "type": "Feature",
  "properties": {
    "iso:country":"ES",
    "sg:address":"Carrer de Llerona, 7",
    "sg:city":"Garriga",
    "sg:orig_category":"Molduras, Junquillos, Listones Y Molduras Perforadas",
    "sg:phone":"+34 938 41 85 87",
    "sg:postcode":"08530",
    "sg:province":"Barcelona",
    "wof:name":"Lloret Ribalta Climent",
    "wof:placetype":"venue"
},
  "geometry": {"coordinates":[2.2840340137,41.6843757629],"type":"Point"}
}