{
  "type": "Feature",
  "properties": {
    "iso:country":"ES",
    "sg:address":"Castilla-leon Pol Ind Tarazona, S/n",
    "sg:city":"Tarazona",
    "sg:orig_category":"Transportes Por Carretera: Lotes Completos, Mercanc\u00cdas Diversas",
    "sg:phone":"+34 976 64 34 73",
    "sg:postcode":"50500",
    "sg:province":"Zaragoza",
    "wof:name":"Juste Lainez Pedro",
    "wof:placetype":"venue"
},
  "geometry": {"coordinates":[-1.722843051,41.9045448303],"type":"Point"}
}