{
  "type": "Feature",
  "properties": {
    "addr:full":"Calle de Corredera, 1 Arroyomolinos C\u00e1ceres 10161",
    "addr:housenumber":"1",
    "addr:postcode":"10161",
    "addr:street":"Calle De Corredera",
    "iso:country":"ES",
    "sg:address":"Calle de Corredera, 1",
    "sg:city":"Arroyomolinos",
    "sg:orig_category":"Estancos",
    "sg:phone":"+34 927 38 50 44",
    "sg:postcode":"10161",
    "sg:province":"C\u00e1ceres",
    "wof:name":"Paredes Gil Andres",
    "wof:placetype":"venue"
},
  "geometry": {"coordinates":[-6.1613850594,39.1829185486],"type":"Point"}
}