{
  "type": "Feature",
  "properties": {
    "iso:country":"ES",
    "sg:address":"Carrer de Cal Bolet, 31",
    "sg:city":"Vilafranca Penedes",
    "sg:orig_category":"Asociaciones Humanitarias, De Cooperaci\u00d3n, De Acci\u00d3n Social",
    "sg:phone":"+34 938 90 15 84",
    "sg:postcode":"08720",
    "sg:province":"Barcelona",
    "wof:name":"Asociacion De Minusvalidos De Barcelona",
    "wof:placetype":"venue"
},
  "geometry": {"coordinates":[1.7008783817,41.3432731628],"type":"Point"}
}