{
  "type": "Feature",
  "properties": {
    "addr:full":"Calle de Rafael Beca Mateos, 4 Sevilla Sevilla 41007",
    "addr:housenumber":"4",
    "addr:postcode":"41007",
    "addr:street":"Calle De Rafael Beca Mateos",
    "iso:country":"ES",
    "sg:address":"Calle de Rafael Beca Mateos, 4",
    "sg:city":"Sevilla",
    "sg:orig_category":"Inmobiliaria (agencias)",
    "sg:phone":"+34 954 51 61 83",
    "sg:postcode":"41007",
    "sg:province":"Sevilla",
    "wof:name":"Probigraf S.a.",
    "wof:placetype":"venue"
},
  "geometry": {"coordinates":[-5.9518938065,37.3926544189],"type":"Point"}
}