{
  "type": "Feature",
  "properties": {
    "iso:country":"ES",
    "sg:address":"L'esglesia, 18",
    "sg:city":"Vinalesa",
    "sg:orig_category":"Procuradores",
    "sg:phone":"+34 961 48 00 72",
    "sg:postcode":"46114",
    "sg:province":"Valencia",
    "wof:name":"Cabrera Sebastian Bego\u00f1a",
    "wof:placetype":"venue"
},
  "geometry": {"coordinates":[-0.3691169918,39.5359649658],"type":"Point"}
}