{
  "type": "Feature",
  "properties": {
    "iso:country":"ES",
    "sg:address":"Avda Txori Erri, 22",
    "sg:city":"Basozabal",
    "sg:orig_category":"Molduras, Junquillos, Listones Y Molduras Perforadas",
    "sg:phone":"+34 944 53 22 37",
    "sg:postcode":"48150",
    "sg:province":"Vizcaya",
    "wof:name":"Castro Rodulfo Josefa",
    "wof:placetype":"venue"
},
  "geometry": {"coordinates":[-2.9280600548,43.2992897034],"type":"Point"}
}