{
  "type": "Feature",
  "properties": {
    "iso:country":"ES",
    "sg:address":"Calle de Txapinene, 1",
    "sg:city":"Donostia-san Sebastian",
    "sg:orig_category":"Peluquer\u00cdas, Peluquer\u00cda Mixta",
    "sg:phone":"+34 943 35 73 49",
    "sg:postcode":"20017",
    "sg:province":"Guip\u00f9zcoa",
    "wof:name":"Ana Isabel Gutierro Llanos",
    "wof:placetype":"venue"
},
  "geometry": {"coordinates":[-1.9343998432,43.3159217834],"type":"Point"}
}