{
  "type": "Feature",
  "properties": {
    "iso:country":"ES",
    "sg:address":"Calle de San Miguel, 9",
    "sg:city":"Zaragoza",
    "sg:orig_category":"Zapatos (al Por Menor)",
    "sg:phone":"+34 976 23 35 35",
    "sg:postcode":"50001",
    "sg:province":"Zaragoza",
    "wof:name":"Martinez Alcalde Felicidad",
    "wof:placetype":"venue"
},
  "geometry": {"coordinates":[-0.8802530169,41.6509628296],"type":"Point"}
}