{
  "type": "Feature",
  "properties": {
    "addr:full":"C/ Falaguera, 10 Paterna Valencia 46980",
    "addr:housenumber":"10",
    "addr:postcode":"46980",
    "addr:street":"C / Falaguera",
    "iso:country":"ES",
    "sg:address":"C/ Falaguera, 10",
    "sg:city":"Paterna",
    "sg:orig_category":"Telas Para Tapizar, Cortinas, Pasamaner\u00cda (fabricaci\u00d3n, Al Por Mayor)",
    "sg:phone":"+34 961 35 71 50",
    "sg:postcode":"46980",
    "sg:province":"Valencia",
    "wof:name":"Flecos Valencia S.l.",
    "wof:placetype":"venue"
},
  "geometry": {"coordinates":[-0.4329690039,39.5130119324],"type":"Point"}
}