{
  "type": "Feature",
  "properties": {
    "addr:full":"Avda Constitucion (la), 6 Villablino Le\u00f3n 24100",
    "addr:housenumber":"6",
    "addr:postcode":"24100",
    "addr:street":"Avda Constitucion La",
    "iso:country":"ES",
    "sg:address":"Avda Constitucion (la), 6",
    "sg:city":"Villablino",
    "sg:orig_category":"Farmacias",
    "sg:phone":"+34 987 47 00 14",
    "sg:postcode":"24100",
    "sg:province":"Le\u00f3n",
    "wof:name":"Tome Otero Manuel Antonio",
    "wof:placetype":"venue"
},
  "geometry": {"coordinates":[-6.3190889359,42.9396781921],"type":"Point"}
}