{
  "type": "Feature",
  "properties": {
    "addr:full":"Calle de Errekaleor, S/n Vitoria-gasteiz \u00c1lava 01006",
    "addr:housenumber":"s",
    "addr:postcode":"01006",
    "addr:street":"Calle De Errekaleor;/ N",
    "iso:country":"ES",
    "sg:address":"Calle de Errekaleor, S/n",
    "sg:city":"Vitoria-gasteiz",
    "sg:orig_category":"Centros De Educaci\u00d3n Especial",
    "sg:phone":"+34 945 14 62 12",
    "sg:postcode":"01006",
    "sg:province":"\u00c1lava",
    "wof:name":"Asociacion Vecinos De Erreklaeor",
    "wof:placetype":"venue"
},
  "geometry": {"coordinates":[-2.6542568207,42.8364601135],"type":"Point"}
}