{
  "type": "Feature",
  "properties": {
    "iso:country":"ES",
    "sg:address":"Calle de Nueva, 29",
    "sg:city":"Elda",
    "sg:orig_category":"Agencias De Viajes",
    "sg:phone":"+34 965 39 61 62",
    "sg:postcode":"03600",
    "sg:province":"Alicante",
    "sg:website":"www.grupo4.es",
    "wof:name":"Viajes Grupo 4 S. A.",
    "wof:placetype":"venue"
},
  "geometry": {"coordinates":[-0.7978389859,38.4774589539],"type":"Point"}
}