{
  "type": "Feature",
  "properties": {
    "addr:full":"Calle de Jose Rufino Olaso, 21 Valle Trapaga Vizcaya 48510",
    "addr:housenumber":"21",
    "addr:postcode":"48510",
    "addr:street":"Calle De Jose Rufino Olaso;Trapaga",
    "iso:country":"ES",
    "sg:address":"Calle de Jose Rufino Olaso, 21",
    "sg:city":"Valle Trapaga",
    "sg:orig_category":"Pescader\u00cdas (al Por Menor)",
    "sg:phone":"+34 944 92 19 97",
    "sg:postcode":"48510",
    "sg:province":"Vizcaya",
    "wof:name":"Joseba Mikel Correa Linero",
    "wof:placetype":"venue"
},
  "geometry": {"coordinates":[-3.0365600586,43.3028564453],"type":"Point"}
}