{
  "type": "Feature",
  "properties": {
    "iso:country":"ES",
    "sg:address":"Calle de Selva Florida, 1",
    "sg:city":"Purchil",
    "sg:orig_category":"Lencer\u00cda Femenina, Corseter\u00cda, Trajes De Ba\u00d1o (al Por Menor)",
    "sg:phone":"+34 958 43 26 18",
    "sg:postcode":"18193",
    "sg:province":"Granada",
    "wof:name":"Garcia Barranco Maria Rosa",
    "wof:placetype":"venue"
},
  "geometry": {"coordinates":[-3.666023016,37.1722145081],"type":"Point"}
}