{
  "type": "Feature",
  "properties": {
    "iso:country":"ES",
    "sg:address":"Rond San Miguel, 11",
    "sg:city":"Vezdemarban",
    "sg:orig_category":"Confecci\u00d3n (fabricaci\u00d3n, Al Por Mayor)",
    "sg:phone":"+34 980 69 54 43",
    "sg:postcode":"49840",
    "sg:province":"Zamora",
    "wof:name":"Cooperativa La Esperanza",
    "wof:placetype":"venue"
},
  "geometry": {"coordinates":[-5.3655118942,41.653427124],"type":"Point"}
}