{
  "type": "Feature",
  "properties": {
    "iso:country":"ES",
    "sg:address":"Rua Campi\u00d1o De San Francisco (do), 5",
    "sg:city":"Santiago De Compostela",
    "sg:orig_category":"Establecimientos De Cura, Prevenci\u00d3n Y Readaptaci\u00d3n",
    "sg:phone":"+34 981 58 74 12",
    "sg:postcode":"15705",
    "sg:province":"La Coru\u00f1a",
    "wof:name":"Patronato Da Fundacion Monte Do Gozo",
    "wof:placetype":"venue"
},
  "geometry": {"coordinates":[-8.5459909439,42.8831558228],"type":"Point"}
}