{
  "type": "Feature",
  "properties": {
    "iso:country":"ES",
    "sg:address":"Calle de Mayor, 43",
    "sg:city":"Cari\u00f1ena",
    "sg:orig_category":"Alquiler De V\u00cddeo",
    "sg:phone":"+34 976 62 02 78",
    "sg:postcode":"50400",
    "sg:province":"Zaragoza",
    "wof:name":"Lahuerta Pe S.c.",
    "wof:placetype":"venue"
},
  "geometry": {"coordinates":[-1.2244089842,41.3381881714],"type":"Point"}
}