{
  "type": "Feature",
  "properties": {
    "iso:country":"ES",
    "sg:address":"Calle de Horno De Los Bizcochos, 14",
    "sg:city":"Toledo",
    "sg:orig_category":"Abogados",
    "sg:phone":"+34 925 22 46 74",
    "sg:postcode":"45001",
    "sg:province":"Toledo",
    "wof:name":"Conde Martin De Hijas Pedro",
    "wof:placetype":"venue"
},
  "geometry": {"coordinates":[-4.0210762024,39.8578910828],"type":"Point"}
}