{
  "type": "Feature",
  "properties": {
    "addr:full":"Calle de Roger De Lauria, 18 Valencia Valencia 46002",
    "addr:housenumber":"18",
    "addr:postcode":"46002",
    "addr:street":"Calle De Roger De Lauria",
    "iso:country":"ES",
    "sg:address":"Calle de Roger De Lauria, 18",
    "sg:city":"Valencia",
    "sg:orig_category":"Asociaciones Y Clubs Deportivos",
    "sg:phone":"+34 963 94 12 52",
    "sg:postcode":"46002",
    "sg:province":"Valencia",
    "sg:website":"www.base.net",
    "wof:name":"Orero Sport S.l.",
    "wof:placetype":"venue"
},
  "geometry": {"coordinates":[-0.373589009,39.4690170288],"type":"Point"}
}