{
  "type": "Feature",
  "properties": {
    "addr:full":"Calle de Pianista Amparo Iturbi, 32 Valencia Valencia 46007",
    "addr:housenumber":"32",
    "addr:postcode":"46007",
    "addr:street":"Calle De Pianista Amparo Iturbi",
    "iso:country":"ES",
    "sg:address":"Calle de Pianista Amparo Iturbi, 32",
    "sg:city":"Valencia",
    "sg:orig_category":"Pe\u00d1as Y Asociaciones Varias",
    "sg:phone":"+34 963 41 63 18",
    "sg:postcode":"46007",
    "sg:province":"Valencia",
    "wof:name":"Sociedad Cooperativa De Viviendas Para Agentes Comerciales Empleados Y Familiares Y Afectivos Seccio",
    "wof:placetype":"venue"
},
  "geometry": {"coordinates":[-0.3828229904,39.4548873901],"type":"Point"}
}