{
  "type": "Feature",
  "properties": {
    "addr:full":"M. Heredia, 6 Malaga M\u00e1laga 29001",
    "addr:housenumber":"6",
    "addr:postcode":"29001",
    "addr:street":"Heredia;Ma\u0301Laga",
    "iso:country":"ES",
    "sg:address":"M. Heredia, 6",
    "sg:city":"Malaga",
    "sg:orig_category":"Servicios De Telecomunicaciones",
    "sg:phone":"+34 952 06 07 32",
    "sg:postcode":"29001",
    "sg:province":"M\u00e1laga",
    "wof:name":"Jazztel Telecomunicaciones",
    "wof:placetype":"venue"
},
  "geometry": {"coordinates":[-4.4234309196,36.7165527344],"type":"Point"}
}