{
  "type": "Feature",
  "properties": {
    "addr:full":"Calle de Mayor, 11 Mondejar Guadalajara 19110",
    "addr:housenumber":"11",
    "addr:postcode":"19110",
    "addr:street":"Calle De Mayor",
    "iso:country":"ES",
    "sg:address":"Calle de Mayor, 11",
    "sg:city":"Mondejar",
    "sg:orig_category":"Iglesia Cat\u00d3lica",
    "sg:phone":"+34 949 38 55 25",
    "sg:postcode":"19110",
    "sg:province":"Guadalajara",
    "wof:name":"Parroquia De Santa Maria Magdalena",
    "wof:placetype":"venue"
},
  "geometry": {"coordinates":[-3.1088709831,40.3233222961],"type":"Point"}
}