{
  "type": "Feature",
  "properties": {
    "iso:country":"ES",
    "sg:address":"Calle de Puerta Del Sol, 4",
    "sg:city":"Illescas",
    "sg:orig_category":"Papeler\u00cdas: Art\u00cdculos (al Por Mayor)",
    "sg:phone":"+34 925 54 04 26",
    "sg:postcode":"45200",
    "sg:province":"Toledo",
    "wof:name":"Teo Galan S.l.",
    "wof:placetype":"venue"
},
  "geometry": {"coordinates":[-3.8468909264,40.1233062744],"type":"Point"}
}