{
  "type": "Feature",
  "properties": {
    "iso:country":"ES",
    "sg:address":"Carrer de Pineda, 30",
    "sg:city":"Torreblanca Ii",
    "sg:orig_category":"Instalaci\u00d3n, Reparaci\u00d3n De Ascensores Y Montacargas",
    "sg:phone":"+34 938 28 07 89",
    "sg:postcode":"08233",
    "sg:province":"Barcelona",
    "wof:name":"Elbe Bages Sl",
    "wof:placetype":"venue"
},
  "geometry": {"coordinates":[1.9253100157,41.6024246216],"type":"Point"}
}