{
  "type": "Feature",
  "properties": {
    "iso:country":"ES",
    "sg:address":"Calle de Conde De Santa Barbara De Lugones, 19",
    "sg:city":"Pola De Siero",
    "sg:orig_category":"Bazares, Art\u00cdculos De Limpieza Y De Cocina (al Por Menor)",
    "sg:phone":"+34 985 72 02 43",
    "sg:postcode":"33510",
    "sg:province":"Asturias",
    "wof:name":"Tous Pascual Mercedes",
    "wof:placetype":"venue"
},
  "geometry": {"coordinates":[-5.6619114876,43.3930053711],"type":"Point"}
}