{
  "type": "Feature",
  "properties": {
    "addr:full":"Av Ovidi Montllor, 2 Aldaia Valencia 46960",
    "addr:housenumber":"2",
    "addr:postcode":"46960",
    "addr:street":"Av Ovidi Montllor",
    "iso:country":"ES",
    "sg:address":"Av Ovidi Montllor, 2",
    "sg:city":"Aldaia",
    "sg:orig_category":"Mec\u00c1nico Del Autom\u00d3vil",
    "sg:phone":"+34 961 51 45 10",
    "sg:postcode":"46960",
    "sg:province":"Valencia",
    "wof:name":"Europauto S.l.",
    "wof:placetype":"venue"
},
  "geometry": {"coordinates":[-0.4636000097,39.4708824158],"type":"Point"}
}