{
  "type": "Feature",
  "properties": {
    "addr:full":"Av Lleida, 37 Santa Anna-tio Barcelona 08338",
    "addr:housenumber":"37",
    "addr:postcode":"08338",
    "addr:street":"Av Lleida",
    "iso:country":"ES",
    "sg:address":"Av Lleida, 37",
    "sg:city":"Santa Anna-tio",
    "sg:orig_category":"Transportes Por Carretera: Lotes Completos, Mercanc\u00cdas Diversas",
    "sg:phone":"+34 937 51 16 21",
    "sg:postcode":"08338",
    "sg:province":"Barcelona",
    "wof:name":"Premia Peritius S.l.",
    "wof:placetype":"venue"
},
  "geometry": {"coordinates":[2.3503201008,41.5011787415],"type":"Point"}
}