{
  "type": "Feature",
  "properties": {
    "iso:country":"ES",
    "sg:address":"Barcia, 16",
    "sg:city":"Lara\u00f1o",
    "sg:orig_category":"Entrega Y Recogida (servicios)",
    "sg:phone":"+34 981 53 74 48",
    "sg:postcode":"15896",
    "sg:province":"La Coru\u00f1a",
    "wof:name":"Novadisgan S.l.",
    "wof:placetype":"venue"
},
  "geometry": {"coordinates":[-8.6102218628,42.8763961792],"type":"Point"}
}