{
  "type": "Feature",
  "properties": {
    "iso:country":"ES",
    "sg:address":"Avgd Juan Ramon Jimenez, 10",
    "sg:city":"Barri De Porta",
    "sg:orig_category":"Empresas De Carpinter\u00cda Met\u00c1lica",
    "sg:phone":"+34 961 54 07 96",
    "sg:postcode":"46930",
    "sg:province":"Valencia",
    "wof:name":"Cercaval S. L.",
    "wof:placetype":"venue"
},
  "geometry": {"coordinates":[-0.4601689875,39.47706604],"type":"Point"}
}