{
  "type": "Feature",
  "properties": {
    "addr:full":"Vilares, 6 Vilares Lugo 27866",
    "addr:housenumber":"6",
    "addr:postcode":"27866",
    "addr:street":"Vilares",
    "iso:country":"ES",
    "sg:address":"Vilares, 6",
    "sg:city":"Vilares",
    "sg:orig_category":"Chapister\u00cda",
    "sg:phone":"+34 982 55 90 27",
    "sg:postcode":"27866",
    "sg:province":"Lugo",
    "wof:name":"Autos Ramba Hermanos Ramos S.l.",
    "wof:placetype":"venue"
},
  "geometry": {"coordinates":[-7.2747268677,43.05651474],"type":"Point"}
}