{
  "type": "Feature",
  "properties": {
    "iso:country":"ES",
    "sg:address":"Calle de Corredera, 53",
    "sg:city":"Toro",
    "sg:orig_category":"Servicios De Telecomunicaciones",
    "sg:phone":"+34 980 69 11 73",
    "sg:postcode":"49800",
    "sg:province":"Zamora",
    "wof:name":"Conecta Castilla Y Leon S.l",
    "wof:placetype":"venue"
},
  "geometry": {"coordinates":[-5.3915672302,41.5247764587],"type":"Point"}
}