{
  "type": "Feature",
  "properties": {
    "iso:country":"ES",
    "sg:address":"Puerto Rey, S/n",
    "sg:city":"Garrucha",
    "sg:orig_category":"Promotores Constructores",
    "sg:phone":"+34 950 13 32 03",
    "sg:postcode":"04630",
    "sg:province":"Almer\u00eda",
    "wof:name":"Obrascon Huarte Lain S.a.",
    "wof:placetype":"venue"
},
  "geometry": {"coordinates":[-1.8204389811,37.188293457],"type":"Point"}
}