{
  "type": "Feature",
  "properties": {
    "iso:country":"ES",
    "sg:address":"Avda Constitucion, 5",
    "sg:city":"Alacant",
    "sg:orig_category":"Laboratorios Y Trabajos De Fotograf\u00cda, V\u00cddeo Y Cine",
    "sg:phone":"+34 965 14 01 69",
    "sg:postcode":"03002",
    "sg:province":"Alicante",
    "wof:name":"Chimpu S.l.",
    "wof:placetype":"venue"
},
  "geometry": {"coordinates":[-0.4857870042,38.3471603394],"type":"Point"}
}