{
  "type": "Feature",
  "properties": {
    "iso:country":"ES",
    "sg:address":"Calle de Convento, 18",
    "sg:city":"Cuevas Almanzora",
    "sg:orig_category":"Carnicer\u00cdas, Carnicer\u00cdas",
    "sg:phone":"+34 950 45 64 53",
    "sg:postcode":"04610",
    "sg:province":"Almer\u00eda",
    "wof:name":"Beltran Navarro Pedro",
    "wof:placetype":"venue"
},
  "geometry": {"coordinates":[-1.8781139851,37.2911911011],"type":"Point"}
}