{
  "type": "Feature",
  "properties": {
    "addr:full":"Ctra Toledo Avila, Km. 0038,2 Val De Santo Domingo Toledo 45519",
    "addr:postcode":"45519",
    "addr:street":"Ctra Toledo Avila Km. 0038,2",
    "iso:country":"ES",
    "sg:address":"Ctra Toledo Avila, Km. 0038,2",
    "sg:city":"Val De Santo Domingo",
    "sg:orig_category":"Poller\u00cda Y Caza (al Por Menor)",
    "sg:phone":"+34 925 78 90 15",
    "sg:postcode":"45519",
    "sg:province":"Toledo",
    "wof:name":"Koki Sociedad Coop.limitada",
    "wof:placetype":"venue"
},
  "geometry": {"coordinates":[-4.2703337669,40.0481987],"type":"Point"}
}