{
  "type": "Feature",
  "properties": {
    "addr:full":"Calle de General Amor, 3 Palencia Palencia 34005",
    "addr:housenumber":"3",
    "addr:postcode":"34005",
    "addr:street":"Calle De General Amor",
    "iso:country":"ES",
    "sg:address":"Calle de General Amor, 3",
    "sg:city":"Palencia",
    "sg:orig_category":"Pintores",
    "sg:phone":"+34 979 74 09 13",
    "sg:postcode":"34005",
    "sg:province":"Palencia",
    "wof:name":"Oliva Rodriguez Rafael",
    "wof:placetype":"venue"
},
  "geometry": {"coordinates":[-4.5337119102,42.0091781616],"type":"Point"}
}