{
  "type": "Feature",
  "properties": {
    "iso:country":"ES",
    "sg:address":"Calle de Julian Besteiro, S/n",
    "sg:city":"Guadalajara",
    "sg:orig_category":"Asociaciones Y Clubs Deportivos",
    "sg:phone":"+34 949 20 20 81",
    "sg:postcode":"19004",
    "sg:province":"Guadalajara",
    "wof:name":"Club Deportivo Guadalajara",
    "wof:placetype":"venue"
},
  "geometry": {"coordinates":[-3.1881840229,40.6349143982],"type":"Point"}
}