{
  "type": "Feature",
  "properties": {
    "addr:full":"Calle de Landaburu, 7 Barakaldo Vizcaya 48902",
    "addr:housenumber":"7",
    "addr:postcode":"48902",
    "addr:street":"Calle De Landaburu",
    "iso:country":"ES",
    "sg:address":"Calle de Landaburu, 7",
    "sg:city":"Barakaldo",
    "sg:orig_category":"Procuradores",
    "sg:phone":"+34 944 18 01 34",
    "sg:postcode":"48902",
    "sg:province":"Vizcaya",
    "wof:name":"Jesus Fuente Lavin",
    "wof:placetype":"venue"
},
  "geometry": {"coordinates":[-2.987432003,43.2941627502],"type":"Point"}
}