{
  "type": "Feature",
  "properties": {
    "addr:full":"Rua Calvo Sotelo, 11 Sarria Lugo 27600",
    "addr:housenumber":"11",
    "addr:postcode":"27600",
    "addr:street":"Rua Calvo Sotelo",
    "iso:country":"ES",
    "sg:address":"Rua Calvo Sotelo, 11",
    "sg:city":"Sarria",
    "sg:orig_category":"Suministros Y Materiales Industriales",
    "sg:phone":"+34 982 53 07 01",
    "sg:postcode":"27600",
    "sg:province":"Lugo",
    "wof:name":"European Hadwar Sistem S.l.",
    "wof:placetype":"venue"
},
  "geometry": {"coordinates":[-7.4169998169,42.7830467224],"type":"Point"}
}