{
  "type": "Feature",
  "properties": {
    "addr:full":"Calle de Burgos, 4 Parla Madrid 28980",
    "addr:housenumber":"4",
    "addr:postcode":"28980",
    "addr:street":"Calle De Burgos",
    "iso:country":"ES",
    "sg:address":"Calle de Burgos, 4",
    "sg:city":"Parla",
    "sg:orig_category":"Casquer\u00cda (al Por Menor)",
    "sg:phone":"+34 916 98 20 35",
    "sg:postcode":"28980",
    "sg:province":"Madrid",
    "wof:name":"Valiente Rosco Antonia",
    "wof:placetype":"venue"
},
  "geometry": {"coordinates":[-3.7663619518,40.2414588928],"type":"Point"}
}