{
  "type": "Feature",
  "properties": {
    "iso:country":"ES",
    "sg:address":"Beato Nicolas Factor, 2",
    "sg:city":"Canals",
    "sg:orig_category":"Iglesia Cat\u00d3lica",
    "sg:phone":"+34 962 24 09 92",
    "sg:postcode":"46650",
    "sg:province":"Valencia",
    "wof:name":"Parroquia De San Antonio Abad",
    "wof:placetype":"venue"
},
  "geometry": {"coordinates":[-0.5855659842,38.9598693848],"type":"Point"}
}