{
  "type": "Feature",
  "properties": {
    "iso:country":"ES",
    "sg:address":"Rua Das Longas, 11",
    "sg:city":"Cerdedo",
    "sg:classifiers":[
        {
            "category":"Taxi",
            "type":"Transportation"
        }
    ],
    "sg:phone":"+34 986 75 31 43",
    "sg:postcode":"36130",
    "sg:province":"Pontevedra",
    "wof:name":"Obelleiro Gamallo Jose",
    "wof:placetype":"venue"
},
  "geometry": {"coordinates":[-8.3930892944,42.5329322815],"type":"Point"}
}