{
  "type": "Feature",
  "properties": {
    "iso:country":"ES",
    "sg:address":"R. Oliva, 29",
    "sg:city":"Malaga",
    "sg:orig_category":"T\u00c9cnicos Veterinarios",
    "sg:phone":"+34 952 24 26 48",
    "sg:postcode":"29004",
    "sg:province":"M\u00e1laga",
    "wof:name":"Fiorito Nistico Laura",
    "wof:placetype":"venue"
},
  "geometry": {"coordinates":[-4.4644651413,36.6659584045],"type":"Point"}
}