{
  "type": "Feature",
  "properties": {
    "addr:full":"Calle de Retuerto, S/n San Vicente De Barakaldo Vizcaya 48903",
    "addr:housenumber":"s / n",
    "addr:postcode":"48903",
    "addr:street":"Calle De Retuerto",
    "iso:country":"ES",
    "sg:address":"Calle de Retuerto, S/n",
    "sg:city":"San Vicente De Barakaldo",
    "sg:orig_category":"Acero: Productos Sider\u00dargicos Y Transformados (fabricaci\u00d3n, Negocio)",
    "sg:phone":"+34 944 90 43 00",
    "sg:postcode":"48903",
    "sg:province":"Vizcaya",
    "wof:name":"Hierros Calzada S. L.",
    "wof:placetype":"venue"
},
  "geometry": {"coordinates":[-3.0083589554,43.2885894775],"type":"Point"}
}