{
  "type": "Feature",
  "properties": {
    "addr:full":"Gremi De Passamaners(p I Son Rossynol), 8 Pol.ind.son Castello Islas Baleares 07009",
    "addr:housenumber":"8",
    "addr:postcode":"07009",
    "addr:street":"P;Rossynol;Islas",
    "iso:country":"ES",
    "sg:address":"Gremi De Passamaners(p I Son Rossynol), 8",
    "sg:city":"Pol.ind.son Castello",
    "sg:orig_category":"Electricidad, Electr\u00d3nica: Suministros (al Por Menor)",
    "sg:phone":"+34 971 77 14 58",
    "sg:postcode":"07009",
    "sg:province":"Islas Baleares",
    "sg:website":"www.dahlberg-sa.com",
    "wof:name":"Dahlberg S. A.",
    "wof:placetype":"venue"
},
  "geometry": {"coordinates":[2.6741399765,39.6011390686],"type":"Point"}
}