{
  "type": "Feature",
  "properties": {
    "addr:full":"Avda Guadarrama, 20 Majadahonda Madrid 28220",
    "addr:housenumber":"20",
    "addr:postcode":"28220",
    "addr:street":"Avda Guadarrama",
    "iso:country":"ES",
    "sg:address":"Avda Guadarrama, 20",
    "sg:city":"Majadahonda",
    "sg:orig_category":"Arquitectos",
    "sg:phone":"+34 916 34 05 87",
    "sg:postcode":"28220",
    "sg:province":"Madrid",
    "wof:name":"Herranz Carmona Fernando",
    "wof:placetype":"venue"
},
  "geometry": {"coordinates":[-3.8793139458,40.4788284302],"type":"Point"}
}