{
  "type": "Feature",
  "properties": {
    "addr:full":"Calle de Arenas Del Rey, S/n Madrid Madrid 28041",
    "addr:housenumber":"s / n",
    "addr:postcode":"28041",
    "addr:street":"Calle De Arenas Del Rey",
    "iso:country":"ES",
    "sg:address":"Calle de Arenas Del Rey, S/n",
    "sg:city":"Madrid",
    "sg:orig_category":"Transportes Por Carretera: Lotes Completos, Mercanc\u00cdas Diversas",
    "sg:phone":"+34 913 17 52 32",
    "sg:postcode":"28041",
    "sg:province":"Madrid",
    "wof:name":"Alvarez Cantiz Maria Isabel",
    "wof:placetype":"venue"
},
  "geometry": {"coordinates":[-3.7009029388,40.3652381897],"type":"Point"}
}