{
  "type": "Feature",
  "properties": {
    "addr:full":"Calle de Rosa, 13 Alba Yeltes Salamanca 37478",
    "addr:housenumber":"13",
    "addr:postcode":"37478",
    "addr:street":"Calle De Rosa;Yeltes",
    "iso:country":"ES",
    "sg:address":"Calle de Rosa, 13",
    "sg:city":"Alba Yeltes",
    "sg:orig_category":"Iglesia Cat\u00d3lica",
    "sg:phone":"+34 923 48 45 04",
    "sg:postcode":"37478",
    "sg:province":"Salamanca",
    "wof:name":"Obispado De Ciudad Rodrigo",
    "wof:placetype":"venue"
},
  "geometry": {"coordinates":[-6.3164138794,40.6730690002],"type":"Point"}
}