{
  "type": "Feature",
  "properties": {
    "iso:country":"ES",
    "sg:address":"Calle de Real, 2",
    "sg:city":"Molinos",
    "sg:orig_category":"Artesan\u00cda Y Trabajos Manuales: Suministros (al Por Menor)",
    "sg:phone":"+34 918 55 02 41",
    "sg:postcode":"28460",
    "sg:province":"Madrid",
    "sg:website":"www.mamaravi.com",
    "wof:name":"Camara Mendez Maria Del Carmen",
    "wof:placetype":"venue"
},
  "geometry": {"coordinates":[-4.0729379654,40.7156600952],"type":"Point"}
}