{
  "type": "Feature",
  "properties": {
    "addr:full":"Calle de Laurel (el), 6 Cordoba C\u00f3rdoba 14006",
    "addr:housenumber":"6",
    "addr:postcode":"14006",
    "addr:street":"Calle De Laurel El;Co\u0301Rdoba",
    "iso:country":"ES",
    "sg:address":"Calle de Laurel (el), 6",
    "sg:city":"Cordoba",
    "sg:orig_category":"Ense\u00d1anza Variada",
    "sg:phone":"+34 957 27 63 81",
    "sg:postcode":"14006",
    "sg:province":"C\u00f3rdoba",
    "wof:name":"Cum.laude S.ca",
    "wof:placetype":"venue"
},
  "geometry": {"coordinates":[-4.7820849419,37.897895813],"type":"Point"}
}