{
  "type": "Feature",
  "properties": {
    "iso:country":"ES",
    "sg:address":"Carrer de Fluvia, 24",
    "sg:city":"Barcelona",
    "sg:orig_category":"Molduras, Junquillos, Listones Y Molduras Perforadas",
    "sg:phone":"+34 933 08 22 72",
    "sg:postcode":"08019",
    "sg:province":"Barcelona",
    "wof:name":"Gayoso Gayoso Jorge",
    "wof:placetype":"venue"
},
  "geometry": {"coordinates":[2.209872961,41.4049682617],"type":"Point"}
}