{
  "type": "Feature",
  "properties": {
    "addr:full":"Zurbano, S/n Zurbano \u00c1lava 01192",
    "addr:housenumber":"s / n",
    "addr:postcode":"01192",
    "addr:street":"Zurbano;Zurbano A\u0301Lava",
    "iso:country":"ES",
    "sg:address":"Zurbano, S/n",
    "sg:city":"Zurbano",
    "sg:orig_category":"Producci\u00d3n De Abonos Y De Fertilizantes",
    "sg:phone":"+34 945 27 45 99",
    "sg:postcode":"01192",
    "sg:province":"\u00c1lava",
    "wof:name":"Sociedad Cooperativa Anoga",
    "wof:placetype":"venue"
},
  "geometry": {"coordinates":[-2.5449340343,42.8497543335],"type":"Point"}
}