{
  "type": "Feature",
  "properties": {
    "iso:country":"ES",
    "sg:address":"Rastro, S/n",
    "sg:city":"Almazan",
    "sg:orig_category":"Organizaciones Internacionales",
    "sg:phone":"+34 975 31 80 01",
    "sg:postcode":"42200",
    "sg:province":"Soria",
    "wof:name":"Cruz Roja Espa\u00f1ola",
    "wof:placetype":"venue"
},
  "geometry": {"coordinates":[-2.5333049297,41.4877433777],"type":"Point"}
}