{
  "type": "Feature",
  "properties": {
    "addr:full":"Avda Jose Maria Fernandez, 38 Le\u00f3n Le\u00f3n 24006",
    "addr:housenumber":"38",
    "addr:postcode":"24006",
    "addr:street":"Avda Jose Maria Fernandez;Leo\u0301N",
    "iso:country":"ES",
    "sg:address":"Avda Jose Maria Fernandez, 38",
    "sg:city":"Le\u00f3n",
    "sg:orig_category":"Ropa Para Se\u00d1oras (al Por Menor)",
    "sg:phone":"+34 987 25 05 62",
    "sg:postcode":"24006",
    "sg:province":"Le\u00f3n",
    "wof:name":"Matos Sogo Jose",
    "wof:placetype":"venue"
},
  "geometry": {"coordinates":[-5.5621562004,42.5989456177],"type":"Point"}
}