{
  "type": "Feature",
  "properties": {
    "iso:country":"ES",
    "sg:address":"Calle de Escuelas, S/n",
    "sg:city":"Chillaron Cuenca",
    "sg:classifiers":[
        {
            "category":"Communications",
            "type":"Services"
        }
    ],
    "sg:phone":"+34 969 27 32 53",
    "sg:postcode":"16190",
    "sg:province":"Cuenca",
    "sg:tags":[
        "televisiones",
        "y",
        "radio"
    ],
    "wof:name":"Ceso Telecomunicaciones S.l.",
    "wof:placetype":"venue"
},
  "geometry": {"coordinates":[-2.2229750156,40.1071815491],"type":"Point"}
}