{
  "type": "Feature",
  "properties": {
    "iso:country":"ES",
    "sg:address":"Villafranca, 5",
    "sg:city":"Iru\u00f1a",
    "sg:orig_category":"Carnicer\u00cdas, Carnicer\u00cdas",
    "sg:phone":"+34 948 12 72 82",
    "sg:postcode":"31015",
    "sg:province":"Navarra",
    "wof:name":"Garro Echarri Catalina",
    "wof:placetype":"venue"
},
  "geometry": {"coordinates":[-1.6289507151,42.8325576782],"type":"Point"}
}