{
  "type": "Feature",
  "properties": {
    "addr:full":"Pol Industrial Heras, S/n Heras Cantabria 39792",
    "addr:housenumber":"s / n",
    "addr:postcode":"39792",
    "addr:street":"Industrial Heras",
    "iso:country":"ES",
    "sg:address":"Pol Industrial Heras, S/n",
    "sg:city":"Heras",
    "sg:orig_category":"Materias Pl\u00c1sticas: Productos De Consumo Masivo (fabricaci\u00d3n, Al Por Mayor)",
    "sg:phone":"+34 942 51 72 41",
    "sg:postcode":"39792",
    "sg:province":"Cantabria",
    "wof:name":"Envases Del Cantabrico S.l.",
    "wof:placetype":"venue"
},
  "geometry": {"coordinates":[-3.7661499977,43.4118690491],"type":"Point"}
}