{
  "type": "Feature",
  "properties": {
    "iso:country":"ES",
    "sg:address":"Av Las Escuelas, 3",
    "sg:city":"Tazona",
    "sg:orig_category":"Autob\u00das (explotaci\u00d3n Y Servicios De)",
    "sg:phone":"+34 967 41 36 93",
    "sg:postcode":"02437",
    "sg:province":"Albacete",
    "wof:name":"Saez Navarro Pedro",
    "wof:placetype":"venue"
},
  "geometry": {"coordinates":[-1.9066929817,38.306968689],"type":"Point"}
}