{
  "type": "Feature",
  "properties": {
    "iso:country":"ES",
    "sg:address":"Avda Sierra (de La), 15",
    "sg:city":"San Sebastian De Los Reyes",
    "sg:orig_category":"Cl\u00cdnicas M\u00c9dicas",
    "sg:phone":"+34 916 51 06 97",
    "sg:postcode":"28700",
    "sg:province":"Madrid",
    "wof:name":"Centro Clinico Bruselas S.l.",
    "wof:placetype":"venue"
},
  "geometry": {"coordinates":[-3.6321620941,40.5512390137],"type":"Point"}
}