{
  "type": "Feature",
  "properties": {
    "addr:full":"Carrer de Ballester, 26 Barcelona Barcelona 08023",
    "addr:housenumber":"26",
    "addr:postcode":"08023",
    "addr:street":"Carrer De Ballester",
    "iso:country":"ES",
    "sg:address":"Carrer de Ballester, 26",
    "sg:city":"Barcelona",
    "sg:orig_category":"Muebles, Minoristas",
    "sg:phone":"+34 932 13 91 66",
    "sg:postcode":"08023",
    "sg:province":"Barcelona",
    "wof:name":"C.p.f. S.l.",
    "wof:placetype":"venue"
},
  "geometry": {"coordinates":[2.1460080147,41.4068031311],"type":"Point"}
}