{
  "type": "Feature",
  "properties": {
    "iso:country":"ES",
    "sg:address":"Rua Luis Antonio Mestre, 22",
    "sg:city":"Grove",
    "sg:orig_category":"Inversiones",
    "sg:phone":"+34 986 73 36 05",
    "sg:postcode":"36980",
    "sg:province":"Pontevedra",
    "wof:name":"On Line Inversores S.l.",
    "wof:placetype":"venue"
},
  "geometry": {"coordinates":[-8.86282444,42.4956588745],"type":"Point"}
}