{
  "type": "Feature",
  "properties": {
    "addr:full":"Av Carrilet, 72 Castell D'aro Girona 17249",
    "addr:housenumber":"72",
    "addr:postcode":"17249",
    "addr:street":"Av Carrilet",
    "iso:country":"ES",
    "sg:address":"Av Carrilet, 72",
    "sg:city":"Castell D'aro",
    "sg:orig_category":"Ense\u00d1anza, Formaci\u00d3n Profesional: Aprendizaje",
    "sg:phone":"+34 972 82 51 51",
    "sg:postcode":"17249",
    "sg:province":"Girona",
    "wof:name":"Ajuntamnet Castell-platja D'aro",
    "wof:placetype":"venue"
},
  "geometry": {"coordinates":[3.02876544,41.8133850098],"type":"Point"}
}