{
  "type": "Feature",
  "properties": {
    "addr:full":"Avda Agustin Balsamo, 1 Algeciras C\u00e1diz 11203",
    "addr:housenumber":"1;ca\u0301diz",
    "addr:postcode":"11203",
    "addr:street":"Avda Agustin Balsamo",
    "iso:country":"ES",
    "sg:address":"Avda Agustin Balsamo, 1",
    "sg:city":"Algeciras",
    "sg:orig_category":"Mec\u00c1nico Del Autom\u00d3vil",
    "sg:phone":"+34 956 66 83 13",
    "sg:postcode":"11203",
    "sg:province":"C\u00e1diz",
    "wof:name":"Neumaticos Sur Andalucia S. L.",
    "wof:placetype":"venue"
},
  "geometry": {"coordinates":[-5.448674202,36.1273612976],"type":"Point"}
}