{
  "type": "Feature",
  "properties": {
    "iso:country":"ES",
    "sg:address":"Cmno Okendotegi De, 54",
    "sg:city":"Donostia-san Sebastian",
    "sg:orig_category":"Producci\u00d3n De Sidra",
    "sg:phone":"+34 943 55 70 70",
    "sg:postcode":"20014",
    "sg:province":"Guip\u00f9zcoa",
    "wof:name":"Zapiain Go\u00f1i Miguel",
    "wof:placetype":"venue"
},
  "geometry": {"coordinates":[-1.9551210403,43.287776947],"type":"Point"}
}