{
  "type": "Feature",
  "properties": {
    "addr:full":"Ctra Madrid, Km. 0345,0 Cieza Murcia 30530",
    "addr:postcode":"30530",
    "addr:street":"Ctra Madrid Km. 0345,0",
    "iso:country":"ES",
    "sg:address":"Ctra Madrid, Km. 0345,0",
    "sg:city":"Cieza",
    "sg:orig_category":"Frutas Y Legumbres Frescas (al Por Mayor)",
    "sg:phone":"+34 968 76 08 24",
    "sg:postcode":"30530",
    "sg:province":"Murcia",
    "sg:website":"cofrufiesa.com",
    "wof:name":"Alimentos Del Mediterraneo S. Coop.",
    "wof:placetype":"venue"
},
  "geometry": {"coordinates":[-1.4880698919,38.3245124817],"type":"Point"}
}