{
  "type": "Feature",
  "properties": {
    "addr:full":"Rua Matias Lopez, 3 Sarria Lugo 27600",
    "addr:housenumber":"3",
    "addr:postcode":"27600",
    "addr:street":"Rua Matias Lopez",
    "iso:country":"ES",
    "sg:address":"Rua Matias Lopez, 3",
    "sg:city":"Sarria",
    "sg:orig_category":"Caf\u00c9s, Bares, Cervecer\u00cdas",
    "sg:phone":"+34 982 53 05 02",
    "sg:postcode":"27600",
    "sg:province":"Lugo",
    "wof:name":"Lopez Castro Angela Donvina",
    "wof:placetype":"venue"
},
  "geometry": {"coordinates":[-7.4133491516,42.7794494629],"type":"Point"}
}