{
  "type": "Feature",
  "properties": {
    "addr:full":"Pase Independencia (la), S/n Pilas Sevilla 41840",
    "addr:postcode":"41840",
    "addr:street":"Independencia La S / N",
    "iso:country":"ES",
    "sg:address":"Pase Independencia (la), S/n",
    "sg:city":"Pilas",
    "sg:orig_category":"Producci\u00d3n, Comercio De Cereales",
    "sg:phone":"+34 954 75 11 17",
    "sg:postcode":"41840",
    "sg:province":"Sevilla",
    "wof:name":"Ferquicer S.l.",
    "wof:placetype":"venue"
},
  "geometry": {"coordinates":[-6.3054537773,37.3111801147],"type":"Point"}
}