{
  "type": "Feature",
  "properties": {
    "addr:full":"Calle de Ezequiel Solana, 6 Madrid Madrid 28017",
    "addr:housenumber":"6",
    "addr:postcode":"28017",
    "addr:street":"Calle De Ezequiel Solana",
    "iso:country":"ES",
    "sg:address":"Calle de Ezequiel Solana, 6",
    "sg:city":"Madrid",
    "sg:orig_category":"M\u00c9dicos: Estomatolog\u00cda",
    "sg:phone":"+34 913 68 18 03",
    "sg:postcode":"28017",
    "sg:province":"Madrid",
    "wof:name":"Miranda Fascinetto Maria Paulina",
    "wof:placetype":"venue"
},
  "geometry": {"coordinates":[-3.6471159458,40.433216095],"type":"Point"}
}