{
  "type": "Feature",
  "properties": {
    "iso:country":"ES",
    "sg:address":"Avda Serrada, S/n",
    "sg:city":"Valdestillas",
    "sg:orig_category":"Frutas, Legumbres Frescas Y Tempranas (al Por Menor)",
    "sg:phone":"+34 983 55 10 17",
    "sg:postcode":"47240",
    "sg:province":"Valladolid",
    "wof:name":"Mu\u00f1ozval S.l.",
    "wof:placetype":"venue"
},
  "geometry": {"coordinates":[-4.7721838951,41.4765968323],"type":"Point"}
}