{
  "type": "Feature",
  "properties": {
    "iso:country":"ES",
    "sg:address":"Avda Montero Rios, 9031",
    "sg:city":"Bueu",
    "sg:orig_category":"Carnicer\u00cdas, Carnicer\u00cdas",
    "sg:phone":"+34 986 32 40 08",
    "sg:postcode":"36930",
    "sg:province":"Pontevedra",
    "wof:name":"Soli\u00f1o Nores Jose Luis",
    "wof:placetype":"venue"
},
  "geometry": {"coordinates":[-8.7789392471,42.3288383484],"type":"Point"}
}