{
  "type": "Feature",
  "properties": {
    "addr:full":"Fianteira (vilalonga), 85 Fianteira Pontevedra 36990",
    "addr:housenumber":"85",
    "addr:postcode":"36990",
    "addr:street":"Vilalonga",
    "iso:country":"ES",
    "sg:address":"Fianteira (vilalonga), 85",
    "sg:city":"Fianteira",
    "sg:orig_category":"Empresas De Limpieza",
    "sg:phone":"+34 986 74 21 43",
    "sg:postcode":"36990",
    "sg:province":"Pontevedra",
    "wof:name":"Limpiezas Honegger S.l.",
    "wof:placetype":"venue"
},
  "geometry": {"coordinates":[-8.8619022369,42.4462432861],"type":"Point"}
}