{
  "type": "Feature",
  "properties": {
    "iso:country":"ES",
    "sg:address":"Calle de Coso, S/n",
    "sg:city":"Chillaron Del Rey",
    "sg:orig_category":"Venta, Instalaci\u00d3n De Cocinas",
    "sg:phone":"+34 949 35 74 50",
    "sg:postcode":"19128",
    "sg:province":"Guadalajara",
    "wof:name":"Romero Corredor Jesus",
    "wof:placetype":"venue"
},
  "geometry": {"coordinates":[-2.6906805038,40.5963096619],"type":"Point"}
}