{
  "type": "Feature",
  "properties": {
    "iso:country":"ES",
    "sg:address":"Calle de Francisco Climent, 2",
    "sg:city":"Valencia",
    "sg:orig_category":"Promotores Constructores",
    "sg:phone":"+34 963 80 67 34",
    "sg:postcode":"46007",
    "sg:province":"Valencia",
    "wof:name":"Alerce Soluciones Constructivas Sl",
    "wof:placetype":"venue"
},
  "geometry": {"coordinates":[-0.3864476085,39.455909729],"type":"Point"}
}