{
  "type": "Feature",
  "properties": {
    "addr:full":"Calle de Leopoldo Lugones, 30 Malaga M\u00e1laga 29004",
    "addr:housenumber":"30",
    "addr:postcode":"29004",
    "addr:street":"Calle De Leopoldo Lugones;Ma\u0301Laga",
    "iso:country":"ES",
    "sg:address":"Calle de Leopoldo Lugones, 30",
    "sg:city":"Malaga",
    "sg:orig_category":"Albergues",
    "sg:phone":"+34 952 24 76 76",
    "sg:postcode":"29004",
    "sg:province":"M\u00e1laga",
    "wof:name":"Fantasy Regalos Y Complementos S.l.",
    "wof:placetype":"venue"
},
  "geometry": {"coordinates":[-4.4885268211,36.696308136],"type":"Point"}
}