{
  "type": "Feature",
  "properties": {
    "iso:country":"ES",
    "sg:address":"Calle de Fuente Del Arca (de La), 19",
    "sg:city":"Talamanca De Jarama",
    "sg:orig_category":"Administraciones Regionales, Departamentales Y Locales",
    "sg:phone":"+34 918 41 70 07",
    "sg:postcode":"28160",
    "sg:province":"Madrid",
    "wof:name":"Ayuntamiento Talamanca Del Jarama",
    "wof:placetype":"venue"
},
  "geometry": {"coordinates":[-3.5105679035,40.745223999],"type":"Point"}
}