{
  "type": "Feature",
  "properties": {
    "addr:full":"Avda Golf, S/n Roca Llisa Islas Baleares 07800",
    "addr:housenumber":"/ n",
    "addr:postcode":"07800",
    "addr:street":"Golf;Llisa",
    "iso:country":"ES",
    "sg:address":"Avda Golf, S/n",
    "sg:city":"Roca Llisa",
    "sg:classifiers":[
        {
            "category":"Sports & Exercise",
            "subcategory":"Golf",
            "type":"Entertainment"
        }
    ],
    "sg:phone":"+34 971 19 60 52",
    "sg:postcode":"07800",
    "sg:province":"Islas Baleares",
    "sg:tags":[
        "y",
        "de",
        "campos",
        "clases"
    ],
    "wof:name":"Inmuebles Y Construcciones Del Golf De Ibiza S.a.",
    "wof:placetype":"venue"
},
  "geometry": {"coordinates":[1.4188899994,38.9061164856],"type":"Point"}
}