{
  "type": "Feature",
  "properties": {
    "iso:country":"ES",
    "sg:address":"Calle de Arroyo Fontarron, 183",
    "sg:city":"Madrid",
    "sg:orig_category":"Limpieza Y Vaciado De Fosas",
    "sg:phone":"+34 913 71 33 05",
    "sg:postcode":"28030",
    "sg:province":"Madrid",
    "wof:name":"Limpiezas Las Herencias Castellanas S.l.",
    "wof:placetype":"venue"
},
  "geometry": {"coordinates":[-3.6440336704,40.3980941772],"type":"Point"}
}