{
  "type": "Feature",
  "properties": {
    "addr:full":"Avda Blasco Iba\u00d1ez, 55 Valencia Valencia 46021",
    "addr:housenumber":"55",
    "addr:postcode":"46021",
    "addr:street":"Avda Blasco Iban\u0303Ez",
    "iso:country":"ES",
    "sg:address":"Avda Blasco Iba\u00d1ez, 55",
    "sg:city":"Valencia",
    "sg:orig_category":"Internados & Ense\u00d1anza Privada",
    "sg:phone":"+34 963 69 58 54",
    "sg:postcode":"46021",
    "sg:province":"Valencia",
    "wof:name":"Colegio Mayor San Francisco Javier Padres Reparadores",
    "wof:placetype":"venue"
},
  "geometry": {"coordinates":[-0.3506659865,39.4753913879],"type":"Point"}
}