{
  "type": "Feature",
  "properties": {
    "iso:country":"ES",
    "sg:address":"Calle de Javier Lasso De La Vega, 8",
    "sg:city":"Sevilla",
    "sg:orig_category":"Expertos Contables",
    "sg:phone":"+34 954 50 03 01",
    "sg:postcode":"41...",
    "sg:province":"Sevilla",
    "wof:name":"Contsa Corporacion Empresarial S.a.",
    "wof:placetype":"venue"
},
  "geometry": {"coordinates":[-5.9950428009,37.3937110901],"type":"Point"}
}