{
  "type": "Feature",
  "properties": {
    "iso:country":"ES",
    "sg:address":"Pg Germanies (de Les), 43",
    "sg:city":"Gandia",
    "sg:orig_category":"Asesor\u00cda Sobre Comunicaci\u00d3n De Empresas",
    "sg:phone":"+34 962 87 66 99",
    "sg:postcode":"46700",
    "sg:province":"Valencia",
    "wof:name":"Asesoria Garrigos S.l.",
    "wof:placetype":"venue"
},
  "geometry": {"coordinates":[-0.1937536001,38.9673576355],"type":"Point"}
}