{
  "type": "Feature",
  "properties": {
    "addr:full":"Avgd De Juan Sebastian Elcano, 34 Benicarlo Castell\u00f3n 12580",
    "addr:housenumber":"34",
    "addr:postcode":"12580",
    "addr:street":"Sebastian Elcano",
    "iso:country":"ES",
    "sg:address":"Avgd De Juan Sebastian Elcano, 34",
    "sg:city":"Benicarlo",
    "sg:orig_category":"Venta, Montaje De Neum\u00c1ticos",
    "sg:phone":"+34 964 46 19 92",
    "sg:postcode":"12580",
    "sg:province":"Castell\u00f3n",
    "wof:name":"Leon Morgado Manuel",
    "wof:placetype":"venue"
},
  "geometry": {"coordinates":[0.4042100012,40.4457893372],"type":"Point"}
}