{
  "type": "Feature",
  "properties": {
    "iso:country":"ES",
    "sg:address":"Calle de Caba, 9",
    "sg:city":"Albacete",
    "sg:orig_category":"Fisioterapia",
    "sg:phone":"+34 967 51 26 33",
    "sg:postcode":"02001",
    "sg:province":"Albacete",
    "wof:name":"Fisioalba S.%.",
    "wof:placetype":"venue"
},
  "geometry": {"coordinates":[-1.8579926491,38.9932518005],"type":"Point"}
}