{
  "type": "Feature",
  "properties": {
    "iso:country":"ES",
    "sg:address":"Avda Ricardo Soriano, 4",
    "sg:city":"Marbella",
    "sg:orig_category":"Detectives, Agentes Investigadores Privados",
    "sg:phone":"+34 952 82 98 75",
    "sg:postcode":"29600",
    "sg:province":"M\u00e1laga",
    "wof:name":"Rudiez Capapey Jose Maria",
    "wof:placetype":"venue"
},
  "geometry": {"coordinates":[-4.8870692253,36.5096549988],"type":"Point"}
}