{
  "type": "Feature",
  "properties": {
    "iso:country":"ES",
    "sg:address":"Calle de Embajadores, 98",
    "sg:city":"Madrid",
    "sg:orig_category":"Promotores Constructores",
    "sg:phone":"+34 915 17 29 57",
    "sg:postcode":"28012",
    "sg:province":"Madrid",
    "wof:name":"Nielfa S.l",
    "wof:placetype":"venue"
},
  "geometry": {"coordinates":[-3.7008359432,40.4025993347],"type":"Point"}
}