{
  "type": "Feature",
  "properties": {
    "addr:full":"Carrer de Hospital, 25 Cambrils Tarragona 43850",
    "addr:housenumber":"25",
    "addr:postcode":"43850",
    "addr:street":"Carrer De Hospital",
    "iso:country":"ES",
    "sg:address":"Carrer de Hospital, 25",
    "sg:city":"Cambrils",
    "sg:orig_category":"Cester\u00cda (fabricaci\u00d3n)",
    "sg:phone":"+34 977 36 07 24",
    "sg:postcode":"43850",
    "sg:province":"Tarragona",
    "wof:name":"Rovira Juncosa Maria",
    "wof:placetype":"venue"
},
  "geometry": {"coordinates":[1.0528399944,41.0740203857],"type":"Point"}
}