{
  "type": "Feature",
  "properties": {
    "addr:full":"Carretera De Anso, S/n Berdun Huesca 22770",
    "addr:housenumber":"s / n",
    "addr:postcode":"22770",
    "addr:street":"Carretera De Anso",
    "iso:country":"ES",
    "sg:address":"Carretera De Anso, S/n",
    "sg:city":"Berdun",
    "sg:orig_category":"Producci\u00d3n, Comercio De Cereales",
    "sg:phone":"+34 974 37 17 98",
    "sg:postcode":"22770",
    "sg:province":"Huesca",
    "wof:name":"Borau Borau Alfredo",
    "wof:placetype":"venue"
},
  "geometry": {"coordinates":[-0.8587790132,42.6023368835],"type":"Point"}
}