{
  "type": "Feature",
  "properties": {
    "addr:full":"Y Pol Noain-esquiroz, 4 Noain Navarra 31110",
    "addr:housenumber":"4",
    "addr:postcode":"31110",
    "addr:street":"Noain-Esquiroz",
    "iso:country":"ES",
    "sg:address":"Y Pol Noain-esquiroz, 4",
    "sg:city":"Noain",
    "sg:orig_category":"Art\u00cdculos De Limpieza Y De Cocina (fabricaci\u00d3n, Al Por Mayor)",
    "sg:phone":"+34 948 36 80 00",
    "sg:postcode":"31110",
    "sg:province":"Navarra",
    "sg:website":"www.sumals.com",
    "wof:name":"Suministros Alf S.a.",
    "wof:placetype":"venue"
},
  "geometry": {"coordinates":[-1.6338239908,42.7598800659],"type":"Point"}
}