{
  "type": "Feature",
  "properties": {
    "iso:country":"ES",
    "sg:address":"Calle de Pedro Ecija, 30",
    "sg:city":"Molina Segura",
    "sg:orig_category":"Tapiceros Y Tapiceros",
    "sg:phone":"+34 968 64 52 31",
    "sg:postcode":"30500",
    "sg:province":"Murcia",
    "wof:name":"Gonzalez Ba\u00f1os Isabel Maria",
    "wof:placetype":"venue"
},
  "geometry": {"coordinates":[-1.2119740248,38.0535736084],"type":"Point"}
}