{
  "type": "Feature",
  "properties": {
    "addr:full":"Plaz Santa Barbara, 1 Mieres Asturias 33600",
    "addr:housenumber":"1",
    "addr:postcode":"33600",
    "addr:street":"Santa Barbara",
    "iso:country":"ES",
    "sg:address":"Plaz Santa Barbara, 1",
    "sg:city":"Mieres",
    "sg:orig_category":"Panader\u00cdas, Panader\u00cdas",
    "sg:phone":"+34 985 45 22 38",
    "sg:postcode":"33600",
    "sg:province":"Asturias",
    "wof:name":"Garcia Gonzalez Manuel Alfredo",
    "wof:placetype":"venue"
},
  "geometry": {"coordinates":[-5.7782812119,43.2518196106],"type":"Point"}
}