{
  "type": "Feature",
  "properties": {
    "iso:country":"ES",
    "sg:address":"Pase Padre Faustino Calvo, 1",
    "sg:city":"Palencia",
    "sg:orig_category":"Molduras, Junquillos, Listones Y Molduras Perforadas",
    "sg:phone":"+34 979 74 91 91",
    "sg:postcode":"34005",
    "sg:province":"Palencia",
    "wof:name":"Pastor Borge Pedro",
    "wof:placetype":"venue"
},
  "geometry": {"coordinates":[-4.5386948586,42.0067977905],"type":"Point"}
}