{
  "type": "Feature",
  "properties": {
    "addr:full":"Carrer de Alcover, 16 Reus Tarragona 43203",
    "addr:housenumber":"16",
    "addr:postcode":"43203",
    "addr:street":"Carrer De Alcover",
    "iso:country":"ES",
    "sg:address":"Carrer de Alcover, 16",
    "sg:city":"Reus",
    "sg:orig_category":"Molduras, Junquillos, Listones Y Molduras Perforadas",
    "sg:phone":"+34 977 34 16 21",
    "sg:postcode":"43203",
    "sg:province":"Tarragona",
    "wof:name":"Fernandez Pujol Yolanda",
    "wof:placetype":"venue"
},
  "geometry": {"coordinates":[1.1133639812,41.1602401733],"type":"Point"}
}