{
  "type": "Feature",
  "properties": {
    "addr:full":"Calle de Real, 5 Rozas De Madrid Madrid 28230",
    "addr:housenumber":"5",
    "addr:postcode":"28230",
    "addr:street":"Calle De Real",
    "iso:country":"ES",
    "sg:address":"Calle de Real, 5",
    "sg:city":"Rozas De Madrid",
    "sg:orig_category":"Cervecer\u00cdas",
    "sg:phone":"+34 916 30 17 04",
    "sg:postcode":"28230",
    "sg:province":"Madrid",
    "wof:name":"Barrafija Cochabamba 21 S.l.",
    "wof:placetype":"venue"
},
  "geometry": {"coordinates":[-3.8739318848,40.4928321838],"type":"Point"}
}