{
  "type": "Feature",
  "properties": {
    "iso:country":"ES",
    "sg:address":"Foia, 6",
    "sg:city":"Algemesi",
    "sg:orig_category":"Art\u00cdculos De Limpieza Y De Cocina (fabricaci\u00d3n, Al Por Mayor)",
    "sg:phone":"+34 962 42 21 46",
    "sg:postcode":"46680",
    "sg:province":"Valencia",
    "wof:name":"Albert Campos Jose Luis",
    "wof:placetype":"venue"
},
  "geometry": {"coordinates":[-0.4313729107,39.2159690857],"type":"Point"}
}