{
  "type": "Feature",
  "properties": {
    "iso:country":"ES",
    "sg:address":"Carrer de Tanger, 82",
    "sg:city":"Barcelona",
    "sg:orig_category":"Edici\u00d3n De Diarios, Revistas, Boletines",
    "sg:phone":"+34 933 09 59 14",
    "sg:postcode":"08018",
    "sg:province":"Barcelona",
    "sg:website":"www.edicionesglenat.es",
    "wof:name":"Ediciones Glenat Espa\u00d1a S.l.",
    "wof:placetype":"venue"
},
  "geometry": {"coordinates":[2.1920940876,41.4017906189],"type":"Point"}
}