{
  "type": "Feature",
  "properties": {
    "addr:full":"Pda Pla, S/n Benlloch Castell\u00f3n 12181",
    "addr:housenumber":"s / n",
    "addr:postcode":"12181",
    "addr:street":"Pda Pla",
    "iso:country":"ES",
    "sg:address":"Pda Pla, S/n",
    "sg:city":"Benlloch",
    "sg:orig_category":"Agricultores, Agricultores",
    "sg:phone":"+34 964 33 90 83",
    "sg:postcode":"12181",
    "sg:province":"Castell\u00f3n",
    "wof:name":"Uve S.a",
    "wof:placetype":"venue"
},
  "geometry": {"coordinates":[0.0277290009,40.2115058899],"type":"Point"}
}