{
  "type": "Feature",
  "properties": {
    "addr:full":"Calle de Gonzalez Serrano, 3 Badajoz Badajoz 06006",
    "addr:housenumber":"3",
    "addr:postcode":"06006",
    "addr:street":"Calle De Gonzalez Serrano",
    "iso:country":"ES",
    "sg:address":"Calle de Gonzalez Serrano, 3",
    "sg:city":"Badajoz",
    "sg:orig_category":"M\u00c9dicos: Psiquiatr\u00cda",
    "sg:phone":"+34 924 27 61 12",
    "sg:postcode":"06006",
    "sg:province":"Badajoz",
    "wof:name":"Gonzalez Gonzalez Antonio Pascual",
    "wof:placetype":"venue"
},
  "geometry": {"coordinates":[-6.9851722717,38.8910140991],"type":"Point"}
}