{
  "type": "Feature",
  "properties": {
    "addr:full":"Vitoria-estella, 28 Sant. Kanpezu \u00c1lava 01110",
    "addr:housenumber":"28",
    "addr:postcode":"01110",
    "addr:street":"Vitoria-Estella",
    "iso:country":"ES",
    "sg:address":"Vitoria-estella, 28",
    "sg:city":"Sant. Kanpezu",
    "sg:orig_category":"Suministros Para Carrocer\u00cdas",
    "sg:phone":"+34 945 41 50 74",
    "sg:postcode":"01110",
    "sg:province":"\u00c1lava",
    "wof:name":"Llinas Mahugo Ivan",
    "wof:placetype":"venue"
},
  "geometry": {"coordinates":[-2.3467669487,42.6726036072],"type":"Point"}
}