{
  "type": "Feature",
  "properties": {
    "iso:country":"ES",
    "sg:address":"Carrer de Verge De Las Maravillas, 21",
    "sg:city":"Mataro",
    "sg:orig_category":"Peluqueros: De Se\u00d1oras",
    "sg:phone":"+34 937 57 69 35",
    "sg:postcode":"08303",
    "sg:province":"Barcelona",
    "wof:name":"Toro Escabia Maria Josefa",
    "wof:placetype":"venue"
},
  "geometry": {"coordinates":[2.425839901,41.5406608582],"type":"Point"}
}