{
  "type": "Feature",
  "properties": {
    "addr:full":"Plaz Cardenal Belluga, 11 Dolores Alicante 03150",
    "addr:housenumber":"11",
    "addr:postcode":"03150",
    "addr:street":"Plaz Cardenal Belluga",
    "iso:country":"ES",
    "sg:address":"Plaz Cardenal Belluga, 11",
    "sg:city":"Dolores",
    "sg:orig_category":"Panader\u00cdas, Panader\u00cdas",
    "sg:phone":"+34 965 72 63 23",
    "sg:postcode":"03150",
    "sg:province":"Alicante",
    "wof:name":"Garcia Rueda Jose",
    "wof:placetype":"venue"
},
  "geometry": {"coordinates":[-0.769069016,38.139503479],"type":"Point"}
}