{
  "type": "Feature",
  "properties": {
    "addr:full":"Carrer de Pere Iv, 128 Barcelona Barcelona 08005",
    "addr:housenumber":"128",
    "addr:postcode":"08005",
    "addr:street":"Carrer De Pere Iv",
    "iso:country":"ES",
    "sg:address":"Carrer de Pere Iv, 128",
    "sg:city":"Barcelona",
    "sg:orig_category":"Droguer\u00cdas (al Por Menor)",
    "sg:phone":"+34 933 09 02 00",
    "sg:postcode":"08005",
    "sg:province":"Barcelona",
    "wof:name":"Balius Y Cia S. L.",
    "wof:placetype":"venue"
},
  "geometry": {"coordinates":[2.1958642006,41.4005432129],"type":"Point"}
}