{
  "type": "Feature",
  "properties": {
    "iso:country":"ES",
    "sg:address":"Avda Casado Del Alisal, 17",
    "sg:city":"Palencia",
    "sg:orig_category":"Juristas",
    "sg:phone":"+34 979 70 63 42",
    "sg:postcode":"34001",
    "sg:province":"Palencia",
    "wof:name":"Gestinver Consultores S.l.",
    "wof:placetype":"venue"
},
  "geometry": {"coordinates":[-4.5307979584,42.0130004883],"type":"Point"}
}