{
  "type": "Feature",
  "properties": {
    "iso:country":"ES",
    "sg:address":"Calle de Maximiliano Thous, 14",
    "sg:city":"Valencia",
    "sg:orig_category":"Carnicer\u00cdas, Carnicer\u00cdas",
    "sg:phone":"+34 963 66 11 10",
    "sg:postcode":"46009",
    "sg:province":"Valencia",
    "wof:name":"Serrano Martin Alberto Gabriel",
    "wof:placetype":"venue"
},
  "geometry": {"coordinates":[-0.374868989,39.4876861572],"type":"Point"}
}