{
  "type": "Feature",
  "properties": {
    "addr:full":"Calle de Serna La, S/n Malaga M\u00e1laga 29002",
    "addr:postcode":"29002",
    "addr:street":"Calle De Serna La S / N;Ma\u0301Laga",
    "iso:country":"ES",
    "sg:address":"Calle de Serna La, S/n",
    "sg:city":"Malaga",
    "sg:orig_category":"Pescader\u00cdas (al Por Menor)",
    "sg:phone":"+34 952 34 77 14",
    "sg:postcode":"29002",
    "sg:province":"M\u00e1laga",
    "wof:name":"Caballero Fusteros Jose Manuel",
    "wof:placetype":"venue"
},
  "geometry": {"coordinates":[-4.42933321,36.7139282227],"type":"Point"}
}