{
  "type": "Feature",
  "properties": {
    "iso:country":"ES",
    "sg:address":"Calle de San Blas, 9",
    "sg:city":"Arnedo",
    "sg:orig_category":"Electrodom\u00c9sticos (al Por Menor)",
    "sg:phone":"+34 941 38 27 04",
    "sg:postcode":"26580",
    "sg:province":"La Rioja",
    "wof:name":"Martinez Alamos Fernando",
    "wof:placetype":"venue"
},
  "geometry": {"coordinates":[-2.0972878933,42.2267303467],"type":"Point"}
}