{
  "type": "Feature",
  "properties": {
    "iso:country":"ES",
    "sg:address":"C, S/n",
    "sg:city":"Santiago De Compostela",
    "sg:orig_category":"Confiter\u00cda, Galletas Y Pastas, Chocolater\u00cda (al Por Mayor)",
    "sg:phone":"+34 981 58 59 33",
    "sg:postcode":"15890",
    "sg:province":"La Coru\u00f1a",
    "wof:name":"General De Distribucion Fiestasa S.l.",
    "wof:placetype":"venue"
},
  "geometry": {"coordinates":[-8.5247297287,42.9182815552],"type":"Point"}
}