{
  "type": "Feature",
  "properties": {
    "addr:full":"Calle de Real, 102 Lanjaron Granada 18420",
    "addr:housenumber":"102",
    "addr:postcode":"18420",
    "addr:street":"Calle De Real",
    "iso:country":"ES",
    "sg:address":"Calle de Real, 102",
    "sg:city":"Lanjaron",
    "sg:orig_category":"Loter\u00cda Y T\u00d3mbola",
    "sg:phone":"+34 958 77 20 25",
    "sg:postcode":"18420",
    "sg:province":"Granada",
    "wof:name":"Alvarez Lozano Ines",
    "wof:placetype":"venue"
},
  "geometry": {"coordinates":[-3.4827980995,36.9178199768],"type":"Point"}
}