{
  "type": "Feature",
  "properties": {
    "iso:country":"ES",
    "sg:address":"Avda Corts Valencianes, De Les, 39",
    "sg:city":"Valencia",
    "sg:orig_category":"Inform\u00c1tica (estudios, Servicios, Asesor\u00cda, Formaci\u00d3n)",
    "sg:phone":"+34 963 39 44 40",
    "sg:postcode":"46015",
    "sg:province":"Valencia",
    "sg:website":"www.tao.es",
    "wof:name":"Gedas Iberia S.a.",
    "wof:placetype":"venue"
},
  "geometry": {"coordinates":[-0.3769130111,39.4687919617],"type":"Point"}
}