{
  "type": "Feature",
  "properties": {
    "iso:country":"ES",
    "sg:address":"Pl. Constitucion, 5",
    "sg:city":"Valdefuentes",
    "sg:orig_category":"Molduras, Junquillos, Listones Y Molduras Perforadas",
    "sg:phone":"+34 927 38 80 32",
    "sg:postcode":"10180",
    "sg:province":"C\u00e1ceres",
    "wof:name":"Olmos Rodriguez Juana",
    "wof:placetype":"venue"
},
  "geometry": {"coordinates":[-6.1210389137,39.2774887085],"type":"Point"}
}