{
  "type": "Feature",
  "properties": {
    "addr:full":"Avda Federico Garcia Lorca, 39 Salobre\u00f1a Granada 18680",
    "addr:housenumber":"39 salobren\u0303a",
    "addr:postcode":"18680",
    "addr:street":"Avda Federico Garcia Lorca",
    "iso:country":"ES",
    "sg:address":"Avda Federico Garcia Lorca, 39",
    "sg:city":"Salobre\u00f1a",
    "sg:orig_category":"Pizzer\u00cdas",
    "sg:phone":"+34 958 82 83 70",
    "sg:postcode":"18680",
    "sg:province":"Granada",
    "wof:name":"Holdynandy Servicios S.l.",
    "wof:placetype":"venue"
},
  "geometry": {"coordinates":[-3.5860390663,36.7408218384],"type":"Point"}
}