{
  "type": "Feature",
  "properties": {
    "addr:full":"Carrer de Gran De Sant Andreu, 345 Barcelona Barcelona 08030",
    "addr:housenumber":"345",
    "addr:postcode":"08030",
    "addr:street":"Carrer De Gran De Sant Andreu",
    "iso:country":"ES",
    "sg:address":"Carrer de Gran De Sant Andreu, 345",
    "sg:city":"Barcelona",
    "sg:orig_category":"Inmobiliaria (agencias)",
    "sg:phone":"+34 933 46 41 00",
    "sg:postcode":"08030",
    "sg:province":"Barcelona",
    "wof:name":"Nuevacasa Castro S.l",
    "wof:placetype":"venue"
},
  "geometry": {"coordinates":[2.1888189316,41.4379272461],"type":"Point"}
}