{
  "type": "Feature",
  "properties": {
    "iso:country":"ES",
    "sg:address":"Calle de Jose Ramirez, 72",
    "sg:city":"Cartuja Baja",
    "sg:orig_category":"Agencias Y Agentes Comerciales, Representantes",
    "sg:phone":"+34 976 50 02 06",
    "sg:postcode":"50720",
    "sg:province":"Zaragoza",
    "wof:name":"Benavente Portoles Antonio",
    "wof:placetype":"venue"
},
  "geometry": {"coordinates":[-0.8263970017,41.6046943665],"type":"Point"}
}