{
  "type": "Feature",
  "properties": {
    "iso:country":"ES",
    "sg:address":"La Constitucion, 3",
    "sg:city":"Vecilla Curue\u00f1o",
    "sg:orig_category":"Administraciones Regionales, Departamentales Y Locales",
    "sg:phone":"+34 987 74 11 61",
    "sg:postcode":"24840",
    "sg:province":"Le\u00f3n",
    "wof:name":"Ayuntamiento La Vecilla De Curue\u00f1o",
    "wof:placetype":"venue"
},
  "geometry": {"coordinates":[-5.407658577,42.8475494385],"type":"Point"}
}