{
  "type": "Feature",
  "properties": {
    "addr:full":"Carr Rosas (de Las), 13 Manises Valencia 46940",
    "addr:housenumber":"13",
    "addr:postcode":"46940",
    "addr:street":"Carr Rosas De Las",
    "iso:country":"ES",
    "sg:address":"Carr Rosas (de Las), 13",
    "sg:city":"Manises",
    "sg:orig_category":"Fabricaci\u00d3n De Enlosados, Soler\u00cdas",
    "sg:phone":"+34 961 52 30 57",
    "sg:postcode":"46940",
    "sg:province":"Valencia",
    "sg:website":"www.leop.avec.com",
    "wof:name":"Leopoldo Mora S.l.",
    "wof:placetype":"venue"
},
  "geometry": {"coordinates":[-0.4645780027,39.4914894104],"type":"Point"}
}