{
  "type": "Feature",
  "properties": {
    "iso:country":"ES",
    "sg:address":"Calle de Magdalena, 18",
    "sg:city":"Oviedo",
    "sg:orig_category":"Ropa Para Beb\u00c9s Y Ni\u00d1os (confecci\u00d3n, Al Por Mayor)",
    "sg:phone":"+34 985 21 19 03",
    "sg:postcode":"33009",
    "sg:province":"Asturias",
    "wof:name":"Alvarez Puente Blanca Nieves",
    "wof:placetype":"venue"
},
  "geometry": {"coordinates":[-5.8450689316,43.3597793579],"type":"Point"}
}