{
  "type": "Feature",
  "properties": {
    "iso:country":"ES",
    "sg:address":"Avda Primero De Mayo, 6",
    "sg:city":"Linares",
    "sg:orig_category":"Ropa Para Se\u00d1oras Y Caballeros (al Por Menor)",
    "sg:phone":"+34 953 65 07 81",
    "sg:postcode":"23700",
    "sg:province":"Ja\u00e9n",
    "wof:name":"Casas Arellano Valentina",
    "wof:placetype":"venue"
},
  "geometry": {"coordinates":[-3.6213440895,38.1048431396],"type":"Point"}
}