{
  "type": "Feature",
  "properties": {
    "addr:full":"Calle de Conde De Salvatierra, 20 Valencia Valencia 46004",
    "addr:housenumber":"20",
    "addr:postcode":"46004",
    "addr:street":"Calle De Conde De Salvatierra",
    "iso:country":"ES",
    "sg:address":"Calle de Conde De Salvatierra, 20",
    "sg:city":"Valencia",
    "sg:orig_category":"Muebles, Minoristas",
    "sg:phone":"+34 963 52 39 91",
    "sg:postcode":"46004",
    "sg:province":"Valencia",
    "sg:website":"www.mueblesrustikos.com",
    "wof:name":"Leste S. A.",
    "wof:placetype":"venue"
},
  "geometry": {"coordinates":[-0.3682079911,39.4696846008],"type":"Point"}
}