{
  "type": "Feature",
  "properties": {
    "iso:country":"ES",
    "sg:address":"Calle de Quart, 128",
    "sg:city":"Valencia",
    "sg:orig_category":"Administradores De Bienes Y Delegados De Comunidades De Propietarios",
    "sg:phone":"+34 963 84 73 16",
    "sg:postcode":"46008",
    "sg:province":"Valencia",
    "wof:name":"Fernandez Reina Jose Luis",
    "wof:placetype":"venue"
},
  "geometry": {"coordinates":[-0.3909130096,39.47473526],"type":"Point"}
}