{
  "type": "Feature",
  "properties": {
    "addr:full":"Impresores, S/n Boadilla Madrid 28660",
    "addr:housenumber":"/ n",
    "addr:postcode":"28660",
    "addr:street":"Impresores S",
    "iso:country":"ES",
    "sg:address":"Impresores, S/n",
    "sg:city":"Boadilla",
    "sg:orig_category":"Comercio De Piezas De Recambio Y De Accesorios De Veh\u00cdculos, Veh\u00cdculos Industriales",
    "sg:phone":"+34 916 32 47 60",
    "sg:postcode":"28660",
    "sg:province":"Madrid",
    "wof:name":"Accemovil S.a.",
    "wof:placetype":"venue"
},
  "geometry": {"coordinates":[-3.8450667858,40.3962211609],"type":"Point"}
}