{
  "type": "Feature",
  "properties": {
    "addr:full":"Poli Industrial Ibarria, S/n Alsasua Navarra 31800",
    "addr:housenumber":"s / n",
    "addr:postcode":"31800",
    "iso:country":"ES",
    "sg:address":"Poli Industrial Ibarria, S/n",
    "sg:city":"Alsasua",
    "sg:orig_category":"Empresas De Hormig\u00d3n, Hormig\u00d3n Armado Y Pretensado",
    "sg:phone":"+34 948 46 80 00",
    "sg:postcode":"31800",
    "sg:province":"Navarra",
    "sg:website":"www.nortenph.com",
    "wof:name":"Norten Prefabricados De Hormigon S.l.",
    "wof:placetype":"venue"
},
  "geometry": {"coordinates":[-2.1696588993,42.8959083557],"type":"Point"}
}