{
  "type": "Feature",
  "properties": {
    "iso:country":"ES",
    "sg:address":"Calle de Dr Gonzalez Hierro, 1",
    "sg:city":"Guadalajara",
    "sg:orig_category":"Farmacias",
    "sg:phone":"+34 949 22 10 59",
    "sg:postcode":"19002",
    "sg:province":"Guadalajara",
    "wof:name":"Ibarra Lopez Manuel",
    "wof:placetype":"venue"
},
  "geometry": {"coordinates":[-3.1624441147,40.6236114502],"type":"Point"}
}