{
  "type": "Feature",
  "properties": {
    "addr:full":"Avda Lugo, S/n Palas Rei Lugo 27200",
    "addr:housenumber":"s / n",
    "addr:postcode":"27200",
    "addr:street":"Avda Lugo",
    "iso:country":"ES",
    "sg:address":"Avda Lugo, S/n",
    "sg:city":"Palas Rei",
    "sg:orig_category":"Cerrajer\u00cda, Ferrallista",
    "sg:phone":"+34 982 38 00 49",
    "sg:postcode":"27200",
    "sg:province":"Lugo",
    "wof:name":"Garcia Sanchez Alfonso",
    "wof:placetype":"venue"
},
  "geometry": {"coordinates":[-7.8687338829,42.8742141724],"type":"Point"}
}