{
  "type": "Feature",
  "properties": {
    "addr:full":"Avda Jose Ribera, 12 Malaga M\u00e1laga 29010",
    "addr:housenumber":"12",
    "addr:postcode":"29010",
    "addr:street":"Avda Jose Ribera;Ma\u0301Laga",
    "iso:country":"ES",
    "sg:address":"Avda Jose Ribera, 12",
    "sg:city":"Malaga",
    "sg:orig_category":"Mec\u00c1nico Del Autom\u00d3vil",
    "sg:phone":"+34 952 27 71 91",
    "sg:postcode":"29010",
    "sg:province":"M\u00e1laga",
    "wof:name":"Zambudio Ruiz Jose",
    "wof:placetype":"venue"
},
  "geometry": {"coordinates":[-4.4720335007,36.7209320068],"type":"Point"}
}