{
  "type": "Feature",
  "properties": {
    "addr:full":"Calle de Caballero Villarroel, 7 Badajoz Badajoz 06010",
    "addr:housenumber":"7",
    "addr:postcode":"06010",
    "addr:street":"Calle De Caballero Villarroel",
    "iso:country":"ES",
    "sg:address":"Calle de Caballero Villarroel, 7",
    "sg:city":"Badajoz",
    "sg:orig_category":"Alimentaci\u00d3n General (al Por Menor)",
    "sg:phone":"+34 924 23 55 28",
    "sg:postcode":"06010",
    "sg:province":"Badajoz",
    "wof:name":"Alvarez De Lara Galan Felix",
    "wof:placetype":"venue"
},
  "geometry": {"coordinates":[-6.9626121521,38.8689155579],"type":"Point"}
}