{
  "type": "Feature",
  "properties": {
    "addr:full":"Calle de Serrerias, 2 Molina Segura Murcia 30500",
    "addr:housenumber":"2",
    "addr:postcode":"30500",
    "addr:street":"Calle De Serrerias",
    "iso:country":"ES",
    "sg:address":"Calle de Serrerias, 2",
    "sg:city":"Molina Segura",
    "sg:orig_category":"Reposter\u00cdas",
    "sg:phone":"+34 968 64 08 66",
    "sg:postcode":"30500",
    "sg:province":"Murcia",
    "wof:name":"Ramon Gil Asuncion",
    "wof:placetype":"venue"
},
  "geometry": {"coordinates":[-1.2144069672,38.0569381714],"type":"Point"}
}