{
  "type": "Feature",
  "properties": {
    "iso:country":"ES",
    "sg:address":"Calle de Candasnos De, 8",
    "sg:city":"Fraga",
    "sg:orig_category":"Centros Empresariales",
    "sg:phone":"+34 974 47 08 97",
    "sg:postcode":"22520",
    "sg:province":"Huesca",
    "wof:name":"Rivera Lara Irene",
    "wof:placetype":"venue"
},
  "geometry": {"coordinates":[0.3405410945,41.5224266052],"type":"Point"}
}