{
  "type": "Feature",
  "properties": {
    "addr:full":"Calle de Severo Ochoa, 6 Pola De Lena Asturias 33630",
    "addr:housenumber":"6",
    "addr:postcode":"33630",
    "addr:street":"Calle De Severo Ochoa",
    "iso:country":"ES",
    "sg:address":"Calle de Severo Ochoa, 6",
    "sg:city":"Pola De Lena",
    "sg:orig_category":"Promotores Constructores",
    "sg:phone":"+34 985 49 36 61",
    "sg:postcode":"33630",
    "sg:province":"Asturias",
    "wof:name":"Construcciones Candido Sanchez S.l.",
    "wof:placetype":"venue"
},
  "geometry": {"coordinates":[-5.8301868439,43.1603660583],"type":"Point"}
}