{
  "type": "Feature",
  "properties": {
    "iso:country":"ES",
    "sg:address":"Calle de Menendez Pelayo, 48",
    "sg:city":"Linares",
    "sg:orig_category":"M\u00c9dicos: Cardiolog\u00cda Y Afecciones Cardiovasculares",
    "sg:phone":"+34 953 69 31 61",
    "sg:postcode":"23700",
    "sg:province":"Ja\u00e9n",
    "wof:name":"Feria Herrera Antonio",
    "wof:placetype":"venue"
},
  "geometry": {"coordinates":[-3.6301960945,38.0945663452],"type":"Point"}
}