{
  "type": "Feature",
  "properties": {
    "iso:country":"ES",
    "sg:address":"Carrer de Call, 15",
    "sg:city":"Barcelona",
    "sg:orig_category":"Monedas, Medallas",
    "sg:phone":"+34 933 17 28 76",
    "sg:postcode":"08002",
    "sg:province":"Barcelona",
    "wof:name":"G\u00fcibas Abella Jorge",
    "wof:placetype":"venue"
},
  "geometry": {"coordinates":[2.1761391163,41.3823127747],"type":"Point"}
}