{
  "type": "Feature",
  "properties": {
    "addr:full":"Calle de Red (la), 1 Mijares \u00c1vila 05461",
    "addr:housenumber":"1",
    "addr:postcode":"05461",
    "addr:street":"Calle De Red La;A\u0301Vila",
    "iso:country":"ES",
    "sg:address":"Calle de Red (la), 1",
    "sg:city":"Mijares",
    "sg:orig_category":"Trabajos De Soldaduras",
    "sg:phone":"+34 920 38 51 55",
    "sg:postcode":"05461",
    "sg:province":"\u00c1vila",
    "wof:name":"Sanchez Diaz Eliseo",
    "wof:placetype":"venue"
},
  "geometry": {"coordinates":[-4.8370528221,40.2981147766],"type":"Point"}
}