{
  "type": "Feature",
  "properties": {
    "addr:full":"Calle de Santa Fe, 10 Toledo Toledo 45001",
    "addr:housenumber":"10",
    "addr:postcode":"45001",
    "addr:street":"Calle De Santa Fe",
    "iso:country":"ES",
    "sg:address":"Calle de Santa Fe, 10",
    "sg:city":"Toledo",
    "sg:orig_category":"Cervecer\u00cdas",
    "sg:phone":"+34 925 21 30 06",
    "sg:postcode":"45001",
    "sg:province":"Toledo",
    "wof:name":"Buenaventura Del Alamo S.l.",
    "wof:placetype":"venue"
},
  "geometry": {"coordinates":[-4.0205221176,39.8597183228],"type":"Point"}
}