{
  "type": "Feature",
  "properties": {
    "addr:full":"Ctra Aldea, Km. 0020,0 Tortosa Tarragona 43500",
    "addr:postcode":"43500",
    "addr:street":"Ctra Aldea Km. 0020,0",
    "iso:country":"ES",
    "sg:address":"Ctra Aldea, Km. 0020,0",
    "sg:city":"Tortosa",
    "sg:orig_category":"Florister\u00cdas",
    "sg:phone":"+34 977 44 66 20",
    "sg:postcode":"43500",
    "sg:province":"Tarragona",
    "wof:name":"Garden La Sinia S.l.",
    "wof:placetype":"venue"
},
  "geometry": {"coordinates":[0.5209109783,40.8127632141],"type":"Point"}
}