{
  "type": "Feature",
  "properties": {
    "addr:full":"Bardenas, 6 Fusti\u00d1ana Navarra 31510",
    "addr:housenumber":"6",
    "addr:postcode":"31510",
    "addr:street":"Bardenas",
    "iso:country":"ES",
    "sg:address":"Bardenas, 6",
    "sg:city":"Fusti\u00d1ana",
    "sg:orig_category":"Supermercados Y Hipermercados",
    "sg:phone":"+34 948 84 06 88",
    "sg:postcode":"31510",
    "sg:province":"Navarra",
    "wof:name":"Oviedo Jordan Pablo",
    "wof:placetype":"venue"
},
  "geometry": {"coordinates":[-1.4860190153,42.0207633972],"type":"Point"}
}