{
  "type": "Feature",
  "properties": {
    "iso:country":"ES",
    "sg:address":"Avda Eladio Perlado, 37",
    "sg:city":"Burgos",
    "sg:orig_category":"Comercio De Piezas De Recambio Y De Accesorios De Veh\u00cdculos, Veh\u00cdculos Industriales",
    "sg:phone":"+34 947 47 04 07",
    "sg:postcode":"09007",
    "sg:province":"Burgos",
    "wof:name":"Auto Repuestos Jose S.l.",
    "wof:placetype":"venue"
},
  "geometry": {"coordinates":[-3.6668319702,42.3498687744],"type":"Point"}
}