{
  "type": "Feature",
  "properties": {
    "iso:country":"ES",
    "sg:address":"Rbla Sant Jordi (de), 63",
    "sg:city":"Ripollet",
    "sg:orig_category":"Peluqueros: De Se\u00d1oras",
    "sg:phone":"+34 936 91 38 59",
    "sg:postcode":"08291",
    "sg:province":"Barcelona",
    "wof:name":"Escuder Perruquers S.l.",
    "wof:placetype":"venue"
},
  "geometry": {"coordinates":[2.1634740829,41.4961013794],"type":"Point"}
}