{
  "type": "Feature",
  "properties": {
    "iso:country":"ES",
    "sg:address":"Avgd Marina, 13",
    "sg:city":"Alcudia",
    "sg:orig_category":"Alquiler De Veh\u00cdculos: Turismos Y Utilitarios",
    "sg:phone":"+34 971 54 52 36",
    "sg:postcode":"07400",
    "sg:province":"Islas Baleares",
    "wof:name":"Arbona Servera Francisco",
    "wof:placetype":"venue"
},
  "geometry": {"coordinates":[3.1140670776,39.8525924683],"type":"Point"}
}