{
  "type": "Feature",
  "properties": {
    "iso:country":"ES",
    "sg:address":"Avda Constitucion, 38",
    "sg:city":"Don Benito",
    "sg:orig_category":"Ropa Y Accesorios",
    "sg:phone":"+34 924 80 54 67",
    "sg:postcode":"06400",
    "sg:province":"Badajoz",
    "wof:name":"By Company Los Tejanos S.l.",
    "wof:placetype":"venue"
},
  "geometry": {"coordinates":[-5.8627138138,38.9662666321],"type":"Point"}
}