{
  "type": "Feature",
  "properties": {
    "iso:country":"ES",
    "sg:address":"Afores, S/n",
    "sg:city":"S. Joan Del Pas",
    "sg:orig_category":"Poller\u00cda Y Caza (al Por Menor)",
    "sg:phone":"+34 977 57 30 97",
    "sg:postcode":"43559",
    "sg:province":"Tarragona",
    "wof:name":"Germans Castell Xx S.l.",
    "wof:placetype":"venue"
},
  "geometry": {"coordinates":[0.3652699888,40.6278533936],"type":"Point"}
}