{
  "type": "Feature",
  "properties": {
    "iso:country":"ES",
    "sg:address":"Calle de Arquitecto Reguera, 13",
    "sg:city":"Oviedo",
    "sg:orig_category":"Peluqueros: De Se\u00d1oras",
    "sg:phone":"+34 985 24 12 81",
    "sg:postcode":"33004",
    "sg:province":"Asturias",
    "wof:name":"Alonso Ojanguren Julia",
    "wof:placetype":"venue"
},
  "geometry": {"coordinates":[-5.8555560112,43.3647041321],"type":"Point"}
}