{
  "type": "Feature",
  "properties": {
    "addr:full":"Calle de Ventana, 1 Santa Olalla Toledo 45530",
    "addr:housenumber":"1",
    "addr:postcode":"45530",
    "addr:street":"Calle De Ventana",
    "iso:country":"ES",
    "sg:address":"Calle de Ventana, 1",
    "sg:city":"Santa Olalla",
    "sg:orig_category":"Fabricaci\u00d3n De Muebles",
    "sg:phone":"+34 925 74 42 26",
    "sg:postcode":"45530",
    "sg:province":"Toledo",
    "wof:name":"Santa-cruz Perez Miguel Angel",
    "wof:placetype":"venue"
},
  "geometry": {"coordinates":[-4.4244670868,40.0287055969],"type":"Point"}
}