{
  "type": "Feature",
  "properties": {
    "iso:country":"ES",
    "sg:address":"Calle de Nenufar, 4",
    "sg:city":"Madrid",
    "sg:orig_category":"Cl\u00cdnicas Dentales",
    "sg:phone":"+34 915 70 03 96",
    "sg:postcode":"28039",
    "sg:province":"Madrid",
    "wof:name":"Dient 3 S.l.",
    "wof:placetype":"venue"
},
  "geometry": {"coordinates":[-3.702548027,40.4622154236],"type":"Point"}
}