{
  "type": "Feature",
  "properties": {
    "iso:country":"ES",
    "sg:address":"Calle de Carmen, 9",
    "sg:city":"Alcaudete",
    "sg:orig_category":"Loter\u00cda Y T\u00d3mbola",
    "sg:phone":"+34 953 70 85 58",
    "sg:postcode":"23660",
    "sg:province":"Ja\u00e9n",
    "wof:name":"Ortega Osuna Francisca",
    "wof:placetype":"venue"
},
  "geometry": {"coordinates":[-4.085477829,37.5907707214],"type":"Point"}
}