{
  "type": "Feature",
  "properties": {
    "addr:full":"Rua Medico D. Jose Mato, 3 Vigo Pontevedra 36210",
    "addr:housenumber":"3",
    "addr:postcode":"36210",
    "addr:street":"Rua Medico D. Jose Mato",
    "iso:country":"ES",
    "sg:address":"Rua Medico D. Jose Mato, 3",
    "sg:city":"Vigo",
    "sg:orig_category":"Peluquer\u00cdas, Peluquer\u00cda Mixta",
    "sg:phone":"+34 986 20 15 09",
    "sg:postcode":"36210",
    "sg:province":"Pontevedra",
    "wof:name":"Peluqueria Dona C.b.",
    "wof:placetype":"venue"
},
  "geometry": {"coordinates":[-8.734128952,42.2192306519],"type":"Point"}
}