{
  "type": "Feature",
  "properties": {
    "addr:full":"Calle de Guitarrista Tarrega, 20 Castellon Castell\u00f3n 12003",
    "addr:housenumber":"20",
    "addr:postcode":"12003",
    "addr:street":"Calle De Guitarrista Tarrega",
    "iso:country":"ES",
    "sg:address":"Calle de Guitarrista Tarrega, 20",
    "sg:city":"Castellon",
    "sg:orig_category":"Librer\u00cdas",
    "sg:phone":"+34 964 22 95 00",
    "sg:postcode":"12003",
    "sg:province":"Castell\u00f3n",
    "wof:name":"Llibreria Castello S.l.",
    "wof:placetype":"venue"
},
  "geometry": {"coordinates":[-0.0355320014,39.98279953],"type":"Point"}
}