{
  "type": "Feature",
  "properties": {
    "iso:country":"ES",
    "sg:address":"Rua San Pedro, 41",
    "sg:city":"Monforte De Lemos",
    "sg:orig_category":"Molduras, Junquillos, Listones Y Molduras Perforadas",
    "sg:phone":"+34 982 41 12 95",
    "sg:postcode":"27400",
    "sg:province":"Lugo",
    "wof:name":"Martinez Perez Martin",
    "wof:placetype":"venue"
},
  "geometry": {"coordinates":[-7.5053792,42.5249481201],"type":"Point"}
}