{
  "type": "Feature",
  "properties": {
    "addr:full":"Carr Cor De Maria, 7 Girona Girona 17002",
    "addr:housenumber":"7",
    "addr:postcode":"17002",
    "addr:street":"Carr Cor De Maria",
    "iso:country":"ES",
    "sg:address":"Carr Cor De Maria, 7",
    "sg:city":"Girona",
    "sg:orig_category":"Arquitectos",
    "sg:phone":"+34 972 21 35 52",
    "sg:postcode":"17002",
    "sg:province":"Girona",
    "wof:name":"Crous Grabuleda I Riera Arquit",
    "wof:placetype":"venue"
},
  "geometry": {"coordinates":[2.8185150623,41.9757194519],"type":"Point"}
}