{
  "type": "Feature",
  "properties": {
    "iso:country":"ES",
    "sg:address":"Av Catalunya, 57",
    "sg:city":"S. Adria Besos",
    "sg:orig_category":"Asociaciones Y Clubs Deportivos",
    "sg:phone":"+34 933 81 55 80",
    "sg:postcode":"08930",
    "sg:province":"Barcelona",
    "wof:name":"Melero Castro Isidoro",
    "wof:placetype":"venue"
},
  "geometry": {"coordinates":[2.2182600498,41.4310417175],"type":"Point"}
}