{
  "type": "Feature",
  "properties": {
    "iso:country":"ES",
    "sg:address":"Calle de Zumel, 4",
    "sg:city":"Madrid",
    "sg:orig_category":"Pescader\u00cdas (al Por Menor)",
    "sg:phone":"+34 913 04 10 71",
    "sg:postcode":"28037",
    "sg:province":"Madrid",
    "wof:name":"Rodriguez Fuentes Jose",
    "wof:placetype":"venue"
},
  "geometry": {"coordinates":[-3.6262040138,40.4285812378],"type":"Point"}
}