{
  "type": "Feature",
  "properties": {
    "iso:country":"ES",
    "sg:address":"Carrer de Conflent, 74",
    "sg:city":"Vendrell",
    "sg:orig_category":"Asesor\u00cda Para La Organizaci\u00d3n Y Gesti\u00d3n Del Transporte",
    "sg:phone":"+34 977 66 36 32",
    "sg:postcode":"43700",
    "sg:province":"Tarragona",
    "wof:name":"Construccions M. Garrido S.l.",
    "wof:placetype":"venue"
},
  "geometry": {"coordinates":[1.5244870186,41.2209587097],"type":"Point"}
}