{
  "type": "Feature",
  "properties": {
    "addr:full":"Carrer de Enric Morera, 18 Manresa Barcelona 08243",
    "addr:housenumber":"18",
    "addr:postcode":"08243",
    "addr:street":"Carrer De Enric Morera",
    "iso:country":"ES",
    "sg:address":"Carrer de Enric Morera, 18",
    "sg:city":"Manresa",
    "sg:orig_category":"Sellos De Goma Y Met\u00c1licos",
    "sg:phone":"+34 938 77 45 94",
    "sg:postcode":"08243",
    "sg:province":"Barcelona",
    "wof:name":"Sola Sensada Ramon",
    "wof:placetype":"venue"
},
  "geometry": {"coordinates":[1.8339289427,41.7388381958],"type":"Point"}
}