{
  "type": "Feature",
  "properties": {
    "iso:country":"ES",
    "sg:address":"Carrer de Falconera, 6",
    "sg:city":"Empuriabrava",
    "sg:orig_category":"Inmobiliaria (agencias)",
    "sg:phone":"+34 972 45 00 23",
    "sg:postcode":"17487",
    "sg:province":"Girona",
    "wof:name":"Sanllehi Fages Maria Del Carmen",
    "wof:placetype":"venue"
},
  "geometry": {"coordinates":[3.1070549488,42.2568092346],"type":"Point"}
}