{
  "type": "Feature",
  "properties": {
    "addr:full":"Calle de Se\u00d1ores De Torres, 14 Rincon Soto La Rioja 26550",
    "addr:housenumber":"14",
    "addr:postcode":"26550",
    "addr:street":"Calle De Sen\u0303Ores De Torres;Rioja",
    "iso:country":"ES",
    "sg:address":"Calle de Se\u00d1ores De Torres, 14",
    "sg:city":"Rincon Soto",
    "sg:orig_category":"Empresas De Carpinter\u00cda De Madera",
    "sg:phone":"+34 941 16 01 59",
    "sg:postcode":"26550",
    "sg:province":"La Rioja",
    "wof:name":"Medrano Llorente Jose Miguel",
    "wof:placetype":"venue"
},
  "geometry": {"coordinates":[-1.8479100466,42.2331848145],"type":"Point"}
}