{
  "type": "Feature",
  "properties": {
    "iso:country":"ES",
    "sg:address":"Bo. Nord, S/n",
    "sg:city":"Lli\u00e7a Amunt",
    "sg:orig_category":"Jardiner\u00cdas, Vegetales, Art\u00cdculos De Jardiner\u00cda (al Por Menor)",
    "sg:phone":"+34 938 41 46 54",
    "sg:postcode":"08186",
    "sg:province":"Barcelona",
    "wof:name":"Jardineria Pedrerol S.cv.",
    "wof:placetype":"venue"
},
  "geometry": {"coordinates":[2.2382690907,41.612449646],"type":"Point"}
}