{
  "type": "Feature",
  "properties": {
    "iso:country":"ES",
    "sg:address":"Combat Bruch, 10",
    "sg:city":"Figueres",
    "sg:orig_category":"Ingeniero",
    "sg:phone":"+34 972 50 28 03",
    "sg:postcode":"17600",
    "sg:province":"Girona",
    "wof:name":"Bartrolich De Ribalta Jose",
    "wof:placetype":"venue"
},
  "geometry": {"coordinates":[2.9581100941,42.2656898499],"type":"Point"}
}