{
  "type": "Feature",
  "properties": {
    "addr:full":"Avda Conde De Guadalhorce, 69 Aviles Asturias 33401",
    "addr:housenumber":"69",
    "addr:postcode":"33401",
    "addr:street":"Avda Conde De Guadalhorce",
    "iso:country":"ES",
    "sg:address":"Avda Conde De Guadalhorce, 69",
    "sg:city":"Aviles",
    "sg:orig_category":"Distribuci\u00d3n De Petr\u00d3leo Y Derivados",
    "sg:phone":"+34 985 52 31 84",
    "sg:postcode":"33401",
    "sg:province":"Asturias",
    "sg:website":"www.cepsa.es",
    "wof:name":"Estacion De Servicio Los Canapes S.a.",
    "wof:placetype":"venue"
},
  "geometry": {"coordinates":[-5.9226927757,43.5680541992],"type":"Point"}
}