{
  "type": "Feature",
  "properties": {
    "addr:full":"Calle de Postas, 39 Vitoria-gasteiz \u00c1lava 01004",
    "addr:housenumber":"39",
    "addr:postcode":"01004",
    "addr:street":"Calle De Postas",
    "iso:country":"ES",
    "sg:address":"Calle de Postas, 39",
    "sg:city":"Vitoria-gasteiz",
    "sg:orig_category":"Cooperativas Agr\u00cdcolas",
    "sg:phone":"+34 945 26 52 00",
    "sg:postcode":"01004",
    "sg:province":"\u00c1lava",
    "wof:name":"Cooperativa Vitoriana De La Vivienda",
    "wof:placetype":"venue"
},
  "geometry": {"coordinates":[-2.6675200462,42.8456306458],"type":"Point"}
}