{
  "type": "Feature",
  "properties": {
    "iso:country":"ES",
    "sg:address":"Escultor Estevez, 7",
    "sg:city":"La Orotava",
    "sg:orig_category":"Caf\u00c9s, Bares, Cervecer\u00cdas",
    "sg:phone":"+34 922 33 24 54",
    "sg:postcode":"38300",
    "sg:province":"Santa Cruz De Tenerife",
    "wof:name":"Luis Garcia Francisco",
    "wof:placetype":"venue"
},
  "geometry": {"coordinates":[-16.5189990997,28.3903846741],"type":"Point"}
}