{
  "type": "Feature",
  "properties": {
    "addr:full":"Ctra Navalcarnero-chinchon (de), Km. 0016,5 Serranillos Del Valle Madrid 28979",
    "addr:postcode":"28979",
    "addr:street":"Ctra Navalcarnero-Chinchon De Km. 0016,5",
    "iso:country":"ES",
    "sg:address":"Ctra Navalcarnero-chinchon (de), Km. 0016,5",
    "sg:city":"Serranillos Del Valle",
    "sg:orig_category":"Semiller\u00cdas",
    "sg:phone":"+34 918 13 84 17",
    "sg:postcode":"28979",
    "sg:province":"Madrid",
    "wof:name":"Yepes Vergara Tomas",
    "wof:placetype":"venue"
},
  "geometry": {"coordinates":[-3.8855578899,40.2084465027],"type":"Point"}
}