{
  "type": "Feature",
  "properties": {
    "addr:full":"Playa De La Concha, S/n Oropesa Mar Castell\u00f3n 12594",
    "addr:housenumber":"s / n",
    "addr:postcode":"12594",
    "addr:street":"Playa De La Concha",
    "iso:country":"ES",
    "sg:address":"Playa De La Concha, S/n",
    "sg:city":"Oropesa Mar",
    "sg:orig_category":"Zonas De Acampada, Aparcamiento Para Caravanas",
    "sg:phone":"+34 964 31 02 06",
    "sg:postcode":"12594",
    "sg:province":"Castell\u00f3n",
    "wof:name":"Camping Voramar",
    "wof:placetype":"venue"
},
  "geometry": {"coordinates":[-0.0456800014,39.9851417542],"type":"Point"}
}