{
  "type": "Feature",
  "properties": {
    "iso:country":"ES",
    "sg:address":"Calle de Juventino Nieto Blanco, 34",
    "sg:city":"Talavera Reina",
    "sg:orig_category":"Inversiones",
    "sg:phone":"+34 925 82 27 73",
    "sg:postcode":"45600",
    "sg:province":"Toledo",
    "wof:name":"Montero Ferreyra Manuel",
    "wof:placetype":"venue"
},
  "geometry": {"coordinates":[-4.8210959435,39.9684715271],"type":"Point"}
}