{
  "type": "Feature",
  "properties": {
    "iso:country":"ES",
    "sg:address":"Arca-el Pino, 5",
    "sg:city":"Pino-pedrouzo",
    "sg:orig_category":"Marmolistas Funerarios",
    "sg:phone":"+34 981 51 13 96",
    "sg:postcode":"15821",
    "sg:province":"La Coru\u00f1a",
    "wof:name":"Pompas Funebres Europeas S.l.",
    "wof:placetype":"venue"
},
  "geometry": {"coordinates":[-8.3636646271,42.9042625427],"type":"Point"}
}