{
  "type": "Feature",
  "properties": {
    "addr:full":"Carrer de Costa I Fornaguera, 53 Calella Barcelona 08370",
    "addr:housenumber":"53",
    "addr:postcode":"08370",
    "addr:street":"Carrer De Costa I Fornaguera",
    "iso:country":"ES",
    "sg:address":"Carrer de Costa I Fornaguera, 53",
    "sg:city":"Calella",
    "sg:orig_category":"Abogados",
    "sg:phone":"+34 937 69 08 99",
    "sg:postcode":"08370",
    "sg:province":"Barcelona",
    "wof:name":"Pont Clapes Jorge",
    "wof:placetype":"venue"
},
  "geometry": {"coordinates":[2.6663470268,41.6164550781],"type":"Point"}
}