{
  "type": "Feature",
  "properties": {
    "iso:country":"ES",
    "sg:address":"Carrer de Cor De Jesus, 22",
    "sg:city":"Crevillent",
    "sg:orig_category":"M\u00c1quinas De Coser Y De Hacer Punto (al Por Mayor)",
    "sg:phone":"+34 965 40 07 39",
    "sg:postcode":"03330",
    "sg:province":"Alicante",
    "wof:name":"Maquinas De Coser Y Cortar S.l.",
    "wof:placetype":"venue"
},
  "geometry": {"coordinates":[-0.8059260249,38.2482185364],"type":"Point"}
}