{
  "type": "Feature",
  "properties": {
    "addr:full":"Calle de Manuel De Falla, 5 Pozuelo De Alarcon Madrid 28224",
    "addr:housenumber":"5",
    "addr:postcode":"28224",
    "addr:street":"Calle De Manuel De Falla",
    "iso:country":"ES",
    "sg:address":"Calle de Manuel De Falla, 5",
    "sg:city":"Pozuelo De Alarcon",
    "sg:orig_category":"Marketing Telef\u00d3nico",
    "sg:phone":"+34 913 51 46 63",
    "sg:postcode":"28224",
    "sg:province":"Madrid",
    "wof:name":"Rey Suarez Bego\u00f1a",
    "wof:placetype":"venue"
},
  "geometry": {"coordinates":[-3.8150188923,40.4552612305],"type":"Point"}
}