{
  "type": "Feature",
  "properties": {
    "addr:full":"Calle de Progreso, 339 Valencia Valencia 46011",
    "addr:housenumber":"339",
    "addr:postcode":"46011",
    "addr:street":"Calle De Progreso",
    "iso:country":"ES",
    "sg:address":"Calle de Progreso, 339",
    "sg:city":"Valencia",
    "sg:orig_category":"Lecher\u00cdas",
    "sg:phone":"+34 963 55 25 55",
    "sg:postcode":"46011",
    "sg:province":"Valencia",
    "wof:name":"Puleva Food S.l.",
    "wof:placetype":"venue"
},
  "geometry": {"coordinates":[-0.3291099966,39.4732284546],"type":"Point"}
}