{
  "type": "Feature",
  "properties": {
    "iso:country":"ES",
    "sg:address":"Plaz San Nicolas, 3",
    "sg:city":"Madrigal Altas Torres",
    "sg:orig_category":"Cajas De Ahorro",
    "sg:phone":"+34 920 32 05 14",
    "sg:postcode":"05220",
    "sg:province":"\u00c1vila",
    "wof:name":"Caja De Avila",
    "wof:placetype":"venue"
},
  "geometry": {"coordinates":[-5.0226411819,41.0942344666],"type":"Point"}
}