{
  "type": "Feature",
  "properties": {
    "addr:full":"Cmno. Lorito, S/n Sepulveda Segovia 40300",
    "addr:housenumber":"/ n",
    "addr:postcode":"40300",
    "addr:street":"Lorito S",
    "iso:country":"ES",
    "sg:address":"Cmno. Lorito, S/n",
    "sg:city":"Sepulveda",
    "sg:orig_category":"Complementos De Vestir (al Por Menor)",
    "sg:phone":"+34 921 12 17 25",
    "sg:postcode":"40300",
    "sg:province":"Segovia",
    "wof:name":"Modas Marblanc S.l.l.",
    "wof:placetype":"venue"
},
  "geometry": {"coordinates":[-3.7487390041,41.2972755432],"type":"Point"}
}