{
  "type": "Feature",
  "properties": {
    "iso:country":"ES",
    "sg:address":"Plaz Espa\u00d1a (de), 2",
    "sg:city":"Cartagena",
    "sg:orig_category":"\u00d3ptica: Instrumentos (fabricaci\u00d3n)",
    "sg:phone":"+34 968 50 94 36",
    "sg:postcode":"30201",
    "sg:province":"Murcia",
    "sg:website":"www.visionlab.es",
    "wof:name":"Visionlab S.a.",
    "wof:placetype":"venue"
},
  "geometry": {"coordinates":[-0.9856517911,37.6039543152],"type":"Point"}
}