{
  "type": "Feature",
  "properties": {
    "iso:country":"ES",
    "sg:address":"Ctra Catral, Km. 0004,2",
    "sg:city":"San Jose",
    "sg:orig_category":"Transportes Por V\u00cdas Navegables",
    "sg:phone":"+34 965 31 04 10",
    "sg:postcode":"03360",
    "sg:province":"Alicante",
    "wof:name":"Transandreu S.a.",
    "wof:placetype":"venue"
},
  "geometry": {"coordinates":[-0.8739690185,38.126083374],"type":"Point"}
}