{
  "type": "Feature",
  "properties": {
    "addr:full":"Calle de Merineros (los), 22 Soria Soria 42001",
    "addr:housenumber":"22",
    "addr:postcode":"42001",
    "addr:street":"Calle De Merineros Los",
    "iso:country":"ES",
    "sg:address":"Calle de Merineros (los), 22",
    "sg:city":"Soria",
    "sg:orig_category":"Electrodom\u00c9sticos (al Por Menor)",
    "sg:phone":"+34 975 21 16 62",
    "sg:postcode":"42001",
    "sg:province":"Soria",
    "wof:name":"Nilo S.c.",
    "wof:placetype":"venue"
},
  "geometry": {"coordinates":[-2.4745090008,41.7670402527],"type":"Point"}
}