{
  "type": "Feature",
  "properties": {
    "addr:full":"Calle de Linares, 22 Valladolid Valladolid 47010",
    "addr:housenumber":"22",
    "addr:postcode":"47010",
    "addr:street":"Calle De Linares",
    "iso:country":"ES",
    "sg:address":"Calle de Linares, 22",
    "sg:city":"Valladolid",
    "sg:orig_category":"Cr\u00cda De Animales",
    "sg:phone":"+34 983 25 22 43",
    "sg:postcode":"47010",
    "sg:province":"Valladolid",
    "wof:name":"Mano Gonzalez Anibal De La",
    "wof:placetype":"venue"
},
  "geometry": {"coordinates":[-4.7206401825,41.6617622375],"type":"Point"}
}