{
  "type": "Feature",
  "properties": {
    "iso:country":"ES",
    "sg:address":"Calle de Virgen De Guadalupe, 33",
    "sg:city":"Ibi",
    "sg:orig_category":"Empresas De Pintura Y Revestimientos",
    "sg:phone":"+34 965 55 09 69",
    "sg:postcode":"03440",
    "sg:province":"Alicante",
    "wof:name":"Sola Azor Francisco",
    "wof:placetype":"venue"
},
  "geometry": {"coordinates":[-0.5797234774,38.6200523376],"type":"Point"}
}