{
  "type": "Feature",
  "properties": {
    "addr:full":"Calle de Santa Maria, 14 Huelva Huelva 21003",
    "addr:housenumber":"14",
    "addr:postcode":"21003",
    "addr:street":"Calle De Santa Maria",
    "iso:country":"ES",
    "sg:address":"Calle de Santa Maria, 14",
    "sg:city":"Huelva",
    "sg:orig_category":"M\u00c9dicos: Ginecolog\u00cda Y Obstetricia",
    "sg:phone":"+34 959 28 40 71",
    "sg:postcode":"21003",
    "sg:province":"Huelva",
    "wof:name":"Ladrero Madrid Diego Alfonso",
    "wof:placetype":"venue"
},
  "geometry": {"coordinates":[-6.949734211,37.2537307739],"type":"Point"}
}