{
  "type": "Feature",
  "properties": {
    "addr:full":"Calle de Sierra Gador, 60 Madrid Madrid 28031",
    "addr:housenumber":"60",
    "addr:postcode":"madrid;28031",
    "addr:street":"Calle De Sierra Gador",
    "iso:country":"ES",
    "sg:address":"Calle de Sierra Gador, 60",
    "sg:city":"Madrid",
    "sg:orig_category":"Art\u00cdculos De Regalo (al Por Menor)",
    "sg:phone":"+34 917 78 90 51",
    "sg:postcode":"28031",
    "sg:province":"Madrid",
    "wof:name":"Sanchez Villalba Jose Luis",
    "wof:placetype":"venue"
},
  "geometry": {"coordinates":[-3.6176791191,40.3807220459],"type":"Point"}
}