{
  "type": "Feature",
  "properties": {
    "iso:country":"ES",
    "sg:address":"Calle de Cuesta, S/n",
    "sg:city":"Trevelez",
    "sg:orig_category":"Psic\u00d3logos",
    "sg:phone":"+34 958 85 85 28",
    "sg:postcode":"18417",
    "sg:province":"Granada",
    "wof:name":"Mendoza Torres Candida",
    "wof:placetype":"venue"
},
  "geometry": {"coordinates":[-3.2658245564,37.0016670227],"type":"Point"}
}