{
  "type": "Feature",
  "properties": {
    "iso:country":"ES",
    "sg:address":"Carr Galeries Comercials, S/n",
    "sg:city":"Angles",
    "sg:orig_category":"Sociedades, Compa\u00d1\u00cdas Aseguradoras",
    "sg:phone":"+34 972 42 02 15",
    "sg:postcode":"17160",
    "sg:province":"Girona",
    "wof:name":"Costa Coll Joaquim",
    "wof:placetype":"venue"
},
  "geometry": {"coordinates":[2.6347820759,41.9582252502],"type":"Point"}
}