{
  "type": "Feature",
  "properties": {
    "addr:full":"Calle de Tutor, 51 Madrid Madrid 28008",
    "addr:housenumber":"51",
    "addr:postcode":"madrid;28008",
    "addr:street":"Calle De Tutor",
    "iso:country":"ES",
    "sg:address":"Calle de Tutor, 51",
    "sg:city":"Madrid",
    "sg:orig_category":"Tintes (fabricaci\u00d3n, Al Por Mayor)",
    "sg:phone":"+34 915 44 60 10",
    "sg:postcode":"28008",
    "sg:province":"Madrid",
    "wof:name":"Alonso Espada Meliton",
    "wof:placetype":"venue"
},
  "geometry": {"coordinates":[-3.718354702,40.431438446],"type":"Point"}
}