{
  "type": "Feature",
  "properties": {
    "iso:country":"ES",
    "sg:address":"G.v. Corts Catalanes, 538",
    "sg:city":"Barcelona",
    "sg:orig_category":"Asilos De Ancianos. Centros Privados",
    "sg:phone":"+34 934 54 84 64",
    "sg:postcode":"08011",
    "sg:province":"Barcelona",
    "wof:name":"Montero Marti Juana Maria",
    "wof:placetype":"venue"
},
  "geometry": {"coordinates":[2.1596601009,41.382522583],"type":"Point"}
}