{
  "type": "Feature",
  "properties": {
    "iso:country":"ES",
    "sg:address":"Avda Independencia, 14",
    "sg:city":"Illueca",
    "sg:classifiers":[
        {
            "category":"Taxi",
            "type":"Transportation"
        }
    ],
    "sg:phone":"+34 976 82 02 08",
    "sg:postcode":"50250",
    "sg:province":"Zaragoza",
    "wof:name":"Gaspar Vicente Antonio Jose",
    "wof:placetype":"venue"
},
  "geometry": {"coordinates":[-1.6253689528,41.538066864],"type":"Point"}
}