{
  "type": "Feature",
  "properties": {
    "addr:full":"Uriz, S/n Lakuntza Navarra 31830",
    "addr:postcode":"31830",
    "addr:street":"S / N Lakuntza Navarra",
    "iso:country":"ES",
    "sg:address":"Uriz, S/n",
    "sg:city":"Lakuntza",
    "sg:orig_category":"Muebles Y Accesorios Para Cocinas Y Cuartos De Ba\u00d1o (al Por Menor)",
    "sg:phone":"+34 948 57 60 68",
    "sg:postcode":"31830",
    "sg:province":"Navarra",
    "wof:name":"Lopetegi Equipamiento Integral De Espacios Sl",
    "wof:placetype":"venue"
},
  "geometry": {"coordinates":[-2.0240540504,42.922328949],"type":"Point"}
}