{
  "type": "Feature",
  "properties": {
    "addr:full":"Calle de Regimiento De Toledo, 26 Zamora Zamora 49012",
    "addr:housenumber":"26",
    "addr:postcode":"49012",
    "addr:street":"Calle De Regimiento De Toledo",
    "iso:country":"ES",
    "sg:address":"Calle de Regimiento De Toledo, 26",
    "sg:city":"Zamora",
    "sg:orig_category":"Librer\u00cdas",
    "sg:phone":"+34 980 51 21 22",
    "sg:postcode":"49012",
    "sg:province":"Zamora",
    "wof:name":"Rodriguez Fernandez Hermelinda",
    "wof:placetype":"venue"
},
  "geometry": {"coordinates":[-5.7372961044,41.509979248],"type":"Point"}
}