{
  "type": "Feature",
  "properties": {
    "addr:full":"Ctra. Esc Panticosa, S/n Escarrilla Huesca 22660",
    "addr:housenumber":"s / n",
    "addr:postcode":"22660",
    "addr:street":"Ctra. Esc Panticosa",
    "iso:country":"ES",
    "sg:address":"Ctra. Esc Panticosa, S/n",
    "sg:city":"Escarrilla",
    "sg:orig_category":"Cajas De Ahorro",
    "sg:phone":"+34 974 48 74 60",
    "sg:postcode":"22660",
    "sg:province":"Huesca",
    "wof:name":"Caja De Ahorros De La Inmaculada",
    "wof:placetype":"venue"
},
  "geometry": {"coordinates":[-0.3142879903,42.7360267639],"type":"Point"}
}