{
  "type": "Feature",
  "properties": {
    "iso:country":"ES",
    "sg:address":"Calle de Chavero, 1",
    "sg:city":"Usagre",
    "sg:orig_category":"Centros Empresariales",
    "sg:phone":"+34 924 58 51 71",
    "sg:postcode":"06290",
    "sg:province":"Badajoz",
    "wof:name":"Santana Camara S.l.",
    "wof:placetype":"venue"
},
  "geometry": {"coordinates":[-6.1653752327,38.3571929932],"type":"Point"}
}