{
  "type": "Feature",
  "properties": {
    "addr:full":"Calle de Numancia, 34 Cantalejo Segovia 40320",
    "addr:housenumber":"34",
    "addr:postcode":"40320",
    "addr:street":"Calle De Numancia",
    "iso:country":"ES",
    "sg:address":"Calle de Numancia, 34",
    "sg:city":"Cantalejo",
    "sg:classifiers":[
        {
            "category":"Taxi",
            "type":"Transportation"
        }
    ],
    "sg:phone":"+34 921 52 10 23",
    "sg:postcode":"40320",
    "sg:province":"Segovia",
    "wof:name":"Garcia Sanz Valentina",
    "wof:placetype":"venue"
},
  "geometry": {"coordinates":[-3.9290161133,41.2571640015],"type":"Point"}
}