{
  "type": "Feature",
  "properties": {
    "iso:country":"ES",
    "sg:address":"Av Sant Jordi, 27",
    "sg:city":"Reus",
    "sg:orig_category":"Agentes Generales De Seguros",
    "sg:phone":"+34 977 12 70 26",
    "sg:postcode":"43201",
    "sg:province":"Tarragona",
    "wof:name":"Monforte Teixido Carles",
    "wof:placetype":"venue"
},
  "geometry": {"coordinates":[1.1102819443,41.161075592],"type":"Point"}
}