{
  "type": "Feature",
  "properties": {
    "addr:full":"Calle de Serapio Mugica, 17 Irun Guip\u00f9zcoa 20302",
    "addr:housenumber":"17",
    "addr:postcode":"20302",
    "addr:street":"Calle De Serapio Mugica;Guipu\u0300Zcoa",
    "iso:country":"ES",
    "sg:address":"Calle de Serapio Mugica, 17",
    "sg:city":"Irun",
    "sg:orig_category":"Caf\u00c9s (al Por Menor)",
    "sg:phone":"+34 943 00 34 16",
    "sg:postcode":"20302",
    "sg:province":"Guip\u00f9zcoa",
    "wof:name":"Irun Expres Cafe, S.l",
    "wof:placetype":"venue"
},
  "geometry": {"coordinates":[-1.7959799767,43.3381500244],"type":"Point"}
}