{
  "type": "Feature",
  "properties": {
    "addr:full":"Carr Ildefonso Fierro, 34 Pu\u00e7ol Valencia 46530",
    "addr:housenumber":"34",
    "addr:postcode":"46530",
    "addr:street":"Carr Ildefonso Fierro",
    "iso:country":"ES",
    "sg:address":"Carr Ildefonso Fierro, 34",
    "sg:city":"Pu\u00e7ol",
    "sg:orig_category":"Asociaciones Y Clubs Deportivos",
    "sg:phone":"+34 961 42 30 87",
    "sg:postcode":"46530",
    "sg:province":"Valencia",
    "wof:name":"Auto Baviera S.l",
    "wof:placetype":"venue"
},
  "geometry": {"coordinates":[-0.3072049916,39.6189613342],"type":"Point"}
}