{
  "type": "Feature",
  "properties": {
    "addr:full":"Calle de Picos De Herrera, 4 Tarazona Zaragoza 50500",
    "addr:housenumber":"4",
    "addr:postcode":"50500",
    "addr:street":"Calle De Picos De Herrera",
    "iso:country":"ES",
    "sg:address":"Calle de Picos De Herrera, 4",
    "sg:city":"Tarazona",
    "sg:classifiers":[
        {
            "category":"Taxi",
            "type":"Transportation"
        }
    ],
    "sg:phone":"+34 976 64 30 02",
    "sg:postcode":"50500",
    "sg:province":"Zaragoza",
    "wof:name":"Ma\u00f1ero Carrasco Manuel",
    "wof:placetype":"venue"
},
  "geometry": {"coordinates":[-1.7259949446,41.8986434937],"type":"Point"}
}