{
  "type": "Feature",
  "properties": {
    "iso:country":"ES",
    "sg:address":"Calle de Arturo Soria, 105",
    "sg:city":"Madrid",
    "sg:orig_category":"Institutos M\u00c9dicos",
    "sg:phone":"+34 914 16 75 91",
    "sg:postcode":"28043",
    "sg:province":"Madrid",
    "wof:name":"Instituto Medico De Oftalmologia Sl",
    "wof:placetype":"venue"
},
  "geometry": {"coordinates":[-3.6519436836,40.4502105713],"type":"Point"}
}