{
  "type": "Feature",
  "properties": {
    "addr:full":"Urb San Blas, 7 Brea De Aragon Zaragoza 50246",
    "addr:housenumber":"7",
    "addr:postcode":"50246",
    "addr:street":"San Blas",
    "iso:country":"ES",
    "sg:address":"Urb San Blas, 7",
    "sg:city":"Brea De Aragon",
    "sg:orig_category":"Confecci\u00d3n De Zapatos",
    "sg:phone":"+34 976 82 40 78",
    "sg:postcode":"50246",
    "sg:province":"Zaragoza",
    "wof:name":"The Yellow Stone Company S.l.",
    "wof:placetype":"venue"
},
  "geometry": {"coordinates":[-1.5998699665,41.5209693909],"type":"Point"}
}