{
  "type": "Feature",
  "properties": {
    "iso:country":"ES",
    "sg:address":"Calle de T, 6",
    "sg:city":"Mutiloabeiti",
    "sg:orig_category":"Fachadas",
    "sg:phone":"+34 948 24 03 21",
    "sg:postcode":"31192",
    "sg:province":"Navarra",
    "wof:name":"Altura Eder S.l.",
    "wof:placetype":"venue"
},
  "geometry": {"coordinates":[-1.6345165968,42.8069572449],"type":"Point"}
}