{
  "type": "Feature",
  "properties": {
    "addr:full":"Ctra Canillas, 134 Madrid Madrid 28043",
    "addr:housenumber":"134",
    "addr:postcode":"28043",
    "addr:street":"Ctra Canillas",
    "iso:country":"ES",
    "sg:address":"Ctra Canillas, 134",
    "sg:city":"Madrid",
    "sg:orig_category":"Promotores Constructores",
    "sg:phone":"+34 913 88 94 26",
    "sg:postcode":"28043",
    "sg:province":"Madrid",
    "wof:name":"Crc Obras Y Servicios S.l.",
    "wof:placetype":"venue"
},
  "geometry": {"coordinates":[-3.6412270069,40.4649009705],"type":"Point"}
}