{
  "type": "Feature",
  "properties": {
    "addr:full":"Calle de Ciudad De Mula, 8 Valencia Valencia 46021",
    "addr:housenumber":"8",
    "addr:postcode":"46021",
    "addr:street":"Calle De Ciudad De Mula",
    "iso:country":"ES",
    "sg:address":"Calle de Ciudad De Mula, 8",
    "sg:city":"Valencia",
    "sg:orig_category":"Iglesia Cat\u00d3lica",
    "sg:phone":"+34 963 93 26 00",
    "sg:postcode":"46021",
    "sg:province":"Valencia",
    "wof:name":"Parroquia San Leandro",
    "wof:placetype":"venue"
},
  "geometry": {"coordinates":[-0.3547019958,39.4744529724],"type":"Point"}
}