{
  "type": "Feature",
  "properties": {
    "addr:full":"Calle de Evora, 27 Jerez De La Frontera C\u00e1diz 11402",
    "addr:housenumber":"27",
    "addr:postcode":"11402",
    "addr:street":"Calle De Evora",
    "iso:country":"ES",
    "sg:address":"Calle de Evora, 27",
    "sg:city":"Jerez De La Frontera",
    "sg:orig_category":"Estancos",
    "sg:phone":"+34 956 33 15 17",
    "sg:postcode":"11402",
    "sg:province":"C\u00e1diz",
    "wof:name":"Morales Vallejo Carmen",
    "wof:placetype":"venue"
},
  "geometry": {"coordinates":[-6.1343560219,36.6815872192],"type":"Point"}
}