{
  "type": "Feature",
  "properties": {
    "addr:full":"Plaz Gutierrez Semprun, 4 Valladolid Valladolid 47012",
    "addr:housenumber":"4",
    "addr:postcode":"47012",
    "addr:street":"Plaz;Semprun",
    "iso:country":"ES",
    "sg:address":"Plaz Gutierrez Semprun, 4",
    "sg:city":"Valladolid",
    "sg:orig_category":"Comerciantes Al Por Mayor De Vinos, Licores Y Alcoholes",
    "sg:phone":"+34 983 39 02 13",
    "sg:postcode":"47012",
    "sg:province":"Valladolid",
    "wof:name":"Trejo Gutierrez Francisco",
    "wof:placetype":"venue"
},
  "geometry": {"coordinates":[-4.7160611153,41.6413917542],"type":"Point"}
}