{
  "type": "Feature",
  "properties": {
    "iso:country":"ES",
    "sg:address":"Igualtat(pol Ind Granja Vila), 27",
    "sg:city":"Reus",
    "sg:orig_category":"Maquinaria Para Industrias Diversas",
    "sg:phone":"+34 977 77 37 27",
    "sg:postcode":"43206",
    "sg:province":"Tarragona",
    "wof:name":"Vaytrans S.a.",
    "wof:placetype":"venue"
},
  "geometry": {"coordinates":[1.1205699444,41.1629066467],"type":"Point"}
}