{
  "type": "Feature",
  "properties": {
    "addr:full":"Calle de Murcia, 2 Angeles Madrid 28223",
    "addr:housenumber":"2",
    "addr:postcode":"28223",
    "addr:street":"Calle De Murcia",
    "iso:country":"ES",
    "sg:address":"Calle de Murcia, 2",
    "sg:city":"Angeles",
    "sg:orig_category":"Asesor\u00cda Fiscal Y Jur\u00cddica",
    "sg:phone":"+34 915 18 58 58",
    "sg:postcode":"28223",
    "sg:province":"Madrid",
    "wof:name":"Delmar Asesores S.l.",
    "wof:placetype":"venue"
},
  "geometry": {"coordinates":[-3.7788119316,40.4046974182],"type":"Point"}
}