{
  "type": "Feature",
  "properties": {
    "addr:full":"Calle de San Miguel, 11 Arcos Frontera C\u00e1diz 11630",
    "addr:housenumber":"11",
    "addr:postcode":"11630",
    "addr:street":"Calle De San Miguel",
    "iso:country":"ES",
    "sg:address":"Calle de San Miguel, 11",
    "sg:city":"Arcos Frontera",
    "sg:orig_category":"Notarios",
    "sg:phone":"+34 956 71 72 70",
    "sg:postcode":"11630",
    "sg:province":"C\u00e1diz",
    "wof:name":"Cotorruelo Sanchez Manuel Ignacio",
    "wof:placetype":"venue"
},
  "geometry": {"coordinates":[-5.8112487793,36.750541687],"type":"Point"}
}