{
  "type": "Feature",
  "properties": {
    "addr:full":"Carr Quatre Cases, 5 Palafrugell Girona 17200",
    "addr:housenumber":"5",
    "addr:postcode":"17200",
    "addr:street":"Carr Quatre Cases",
    "iso:country":"ES",
    "sg:address":"Carr Quatre Cases, 5",
    "sg:city":"Palafrugell",
    "sg:orig_category":"Mercer\u00cda, Lencer\u00cda (al Por Menor)",
    "sg:phone":"+34 972 30 11 11",
    "sg:postcode":"17200",
    "sg:province":"Girona",
    "wof:name":"Daranas Castello Miguel",
    "wof:placetype":"venue"
},
  "geometry": {"coordinates":[3.1631259918,41.9166297913],"type":"Point"}
}