{
  "type": "Feature",
  "properties": {
    "addr:full":"Carrer de Montserrat, 7 S. Just Desvern Barcelona 08960",
    "addr:housenumber":"7",
    "addr:postcode":"08960",
    "addr:street":"Carrer De Montserrat",
    "iso:country":"ES",
    "sg:address":"Carrer de Montserrat, 7",
    "sg:city":"S. Just Desvern",
    "sg:orig_category":"Centros Empresariales",
    "sg:phone":"+34 933 71 28 12",
    "sg:postcode":"08960",
    "sg:province":"Barcelona",
    "wof:name":"Collado Armengol Albert",
    "wof:placetype":"venue"
},
  "geometry": {"coordinates":[2.0757091045,41.381401062],"type":"Point"}
}