{
  "type": "Feature",
  "properties": {
    "iso:country":"ES",
    "sg:address":"Calle de Cartagena, 35",
    "sg:city":"Algar",
    "sg:orig_category":"Comercio De Piezas De Recambio Y De Accesorios De Veh\u00cdculos, Veh\u00cdculos Industriales",
    "sg:phone":"+34 968 13 63 13",
    "sg:postcode":"30366",
    "sg:province":"Murcia",
    "wof:name":"Todo Tuning, S.l.",
    "wof:placetype":"venue"
},
  "geometry": {"coordinates":[-0.8702639937,37.6461181641],"type":"Point"}
}