{
  "type": "Feature",
  "properties": {
    "addr:full":"Calle de Antonio Zerolo, 1 Palmas De Gran Canaria Las Palmas 35005",
    "addr:housenumber":"1",
    "addr:postcode":"35005",
    "addr:street":"Calle De Antonio Zerolo",
    "iso:country":"ES",
    "sg:address":"Calle de Antonio Zerolo, 1",
    "sg:city":"Palmas De Gran Canaria",
    "sg:orig_category":"Importaci\u00d3n",
    "sg:phone":"+34 928 24 02 79",
    "sg:postcode":"35005",
    "sg:province":"Las Palmas",
    "wof:name":"Osborne Distribuidora S.a.",
    "wof:placetype":"venue"
},
  "geometry": {"coordinates":[-15.4334535599,28.128074646],"type":"Point"}
}