{
  "type": "Feature",
  "properties": {
    "iso:country":"ES",
    "sg:address":"Plaz Mayor, 7",
    "sg:city":"Valladolid",
    "sg:orig_category":"Cl\u00cdnicas Dentales",
    "sg:phone":"+34 983 37 15 48",
    "sg:postcode":"47001",
    "sg:province":"Valladolid",
    "wof:name":"Adana Jimenez Alejandro",
    "wof:placetype":"venue"
},
  "geometry": {"coordinates":[-4.7281761169,41.6516990662],"type":"Point"}
}