{
  "type": "Feature",
  "properties": {
    "addr:full":"Calle de Pintor Ribera, 14 Oviedo Asturias 33011",
    "addr:housenumber":"14",
    "addr:postcode":"33011",
    "addr:street":"Calle De Pintor Ribera",
    "iso:country":"ES",
    "sg:address":"Calle de Pintor Ribera, 14",
    "sg:city":"Oviedo",
    "sg:orig_category":"Promotores Constructores",
    "sg:phone":"+34 985 11 40 38",
    "sg:postcode":"33011",
    "sg:province":"Asturias",
    "wof:name":"Antico Aplicaciones Decorativas S.l.",
    "wof:placetype":"venue"
},
  "geometry": {"coordinates":[-5.8373389244,43.3698425293],"type":"Point"}
}