{
  "type": "Feature",
  "properties": {
    "iso:country":"ES",
    "sg:address":"Av Hispanidad, S/n",
    "sg:city":"Merida",
    "sg:orig_category":"Autob\u00das (explotaci\u00d3n Y Servicios De)",
    "sg:phone":"+34 924 37 14 03",
    "sg:postcode":"06800",
    "sg:province":"Badajoz",
    "wof:name":"Lineas Extreme\u00f1as De Autobuses S. A.",
    "wof:placetype":"venue"
},
  "geometry": {"coordinates":[-6.3464841843,38.916053772],"type":"Point"}
}