{
  "type": "Feature",
  "properties": {
    "iso:country":"ES",
    "sg:address":"Av Meridiana, 237",
    "sg:city":"Barcelona",
    "sg:orig_category":"Asesor\u00cda Fiscal Y Jur\u00cddica",
    "sg:phone":"+34 934 08 33 15",
    "sg:postcode":"08027",
    "sg:province":"Barcelona",
    "wof:name":"Frama Gestion S.c.p.",
    "wof:placetype":"venue"
},
  "geometry": {"coordinates":[2.1867148876,41.4192695618],"type":"Point"}
}