{
  "type": "Feature",
  "properties": {
    "iso:country":"ES",
    "sg:address":"Calle de Ca\u00d1erias, 6",
    "sg:city":"Bilar",
    "sg:orig_category":"Productores Recolectores, Venta Directa De Vinos",
    "sg:phone":"+34 945 60 40 03",
    "sg:postcode":"01309",
    "sg:province":"\u00c1lava",
    "wof:name":"Perez Virgala Miguel Angel",
    "wof:placetype":"venue"
},
  "geometry": {"coordinates":[-2.5449695587,42.5693511963],"type":"Point"}
}