{
  "type": "Feature",
  "properties": {
    "addr:full":"Carrer de Mayor, 7 Guardamar Segura Alicante 03140",
    "addr:housenumber":"7",
    "addr:postcode":"03140",
    "addr:street":"Carrer De Mayor",
    "iso:country":"ES",
    "sg:address":"Carrer de Mayor, 7",
    "sg:city":"Guardamar Segura",
    "sg:orig_category":"Zapatos (al Por Menor)",
    "sg:phone":"+34 965 72 75 10",
    "sg:postcode":"03140",
    "sg:province":"Alicante",
    "wof:name":"Romano De Los Santos Manuela",
    "wof:placetype":"venue"
},
  "geometry": {"coordinates":[-0.6540290117,38.086681366],"type":"Point"}
}