{
  "type": "Feature",
  "properties": {
    "addr:full":"Calle de Sierra De Guadarrama (de La), 35 Poligono De San Fernando De Henares Madrid 28830",
    "addr:housenumber":"35",
    "addr:postcode":"28830",
    "addr:street":"Calle De Sierra De Guadarrama De La",
    "iso:country":"ES",
    "sg:address":"Calle de Sierra De Guadarrama (de La), 35",
    "sg:city":"Poligono De San Fernando De Henares",
    "sg:orig_category":"Construcciones Met\u00c1licas",
    "sg:phone":"+34 916 76 04 96",
    "sg:postcode":"28830",
    "sg:province":"Madrid",
    "sg:website":"www.conmetal.es",
    "wof:name":"Conmetal S.a.",
    "wof:placetype":"venue"
},
  "geometry": {"coordinates":[-3.4998459816,40.451423645],"type":"Point"}
}