{
  "type": "Feature",
  "properties": {
    "addr:full":"Calle de Bellavista, 21 Coru\u00d1a La Coru\u00f1a 15010",
    "addr:housenumber":"21",
    "addr:postcode":"15010",
    "addr:street":"Calle De Bellavista;La Corun\u0303A",
    "iso:country":"ES",
    "sg:address":"Calle de Bellavista, 21",
    "sg:city":"Coru\u00d1a",
    "sg:orig_category":"Mec\u00c1nico Del Autom\u00d3vil",
    "sg:phone":"+34 981 26 03 87",
    "sg:postcode":"15010",
    "sg:province":"La Coru\u00f1a",
    "wof:name":"Castro Villamor Luis",
    "wof:placetype":"venue"
},
  "geometry": {"coordinates":[-8.4202375412,43.3636512756],"type":"Point"}
}