{
  "type": "Feature",
  "properties": {
    "iso:country":"ES",
    "sg:address":"Carrer de Granollers (de), S/n",
    "sg:city":"Montornes Nord",
    "sg:orig_category":"Confiter\u00cda, Galletas Y Pastas, Chocolater\u00cda (al Por Mayor)",
    "sg:phone":"+34 935 71 91 00",
    "sg:postcode":"08170",
    "sg:province":"Barcelona",
    "wof:name":"United Biscuits Iberia S.l.",
    "wof:placetype":"venue"
},
  "geometry": {"coordinates":[2.2681469917,41.5568847656],"type":"Point"}
}