{
  "type": "Feature",
  "properties": {
    "addr:full":"Carretera Montalbo, S/n Palomares Del Campo Cuenca 16160",
    "addr:housenumber":"s / n",
    "addr:postcode":"16160",
    "addr:street":"Carretera Montalbo",
    "iso:country":"ES",
    "sg:address":"Carretera Montalbo, S/n",
    "sg:city":"Palomares Del Campo",
    "sg:orig_category":"Mec\u00c1nico Del Autom\u00d3vil",
    "sg:phone":"+34 969 27 77 23",
    "sg:postcode":"16160",
    "sg:province":"Cuenca",
    "wof:name":"Martino Lopez Jose Antonio",
    "wof:placetype":"venue"
},
  "geometry": {"coordinates":[-2.598692894,39.9463806152],"type":"Point"}
}