{
  "type": "Feature",
  "properties": {
    "iso:country":"ES",
    "sg:address":"Poli Fortiz, S/n",
    "sg:city":"Huelva",
    "sg:orig_category":"Molduras, Junquillos, Listones Y Molduras Perforadas",
    "sg:phone":"+34 959 22 94 14",
    "sg:postcode":"21007",
    "sg:province":"Huelva",
    "wof:name":"Alvarez Cardoso Jose",
    "wof:placetype":"venue"
},
  "geometry": {"coordinates":[-6.8994493484,37.2885742188],"type":"Point"}
}