{
  "type": "Feature",
  "properties": {
    "iso:country":"ES",
    "sg:address":"Calle de Matias Padron, 21",
    "sg:city":"Palmas De Gran Canaria",
    "sg:orig_category":"Cerrajer\u00cda, Ferrallista",
    "sg:phone":"+34 928 24 44 26",
    "sg:postcode":"35004",
    "sg:province":"Las Palmas",
    "wof:name":"Gorayeb Farkuh Alfredo",
    "wof:placetype":"venue"
},
  "geometry": {"coordinates":[-15.4244194031,28.1180171967],"type":"Point"}
}