{
  "type": "Feature",
  "properties": {
    "addr:full":"Carrer de Ferran Puig, 35 Barcelona Barcelona 08023",
    "addr:housenumber":"35",
    "addr:postcode":"08023",
    "addr:street":"Carrer De Ferran Puig",
    "iso:country":"ES",
    "sg:address":"Carrer de Ferran Puig, 35",
    "sg:city":"Barcelona",
    "sg:orig_category":"Arquitectos",
    "sg:phone":"+34 932 11 18 24",
    "sg:postcode":"08023",
    "sg:province":"Barcelona",
    "wof:name":"Balari Mu\u00f1oz Jorge",
    "wof:placetype":"venue"
},
  "geometry": {"coordinates":[2.1453840733,41.4085655212],"type":"Point"}
}