{
  "type": "Feature",
  "properties": {
    "iso:country":"ES",
    "sg:address":"Av Gatassa, 137",
    "sg:city":"Mataro",
    "sg:orig_category":"Restaurantes",
    "sg:phone":"+34 937 57 21 46",
    "sg:postcode":"08303",
    "sg:province":"Barcelona",
    "wof:name":"Maria Carmen Y Familia S.l.",
    "wof:placetype":"venue"
},
  "geometry": {"coordinates":[2.4255878925,41.5399551392],"type":"Point"}
}