{
  "type": "Feature",
  "properties": {
    "addr:full":"Carrer de Castellbell, 18 Barcelona Barcelona 08030",
    "addr:housenumber":"18",
    "addr:postcode":"08030",
    "addr:street":"Carrer De Castellbell",
    "iso:country":"ES",
    "sg:address":"Carrer de Castellbell, 18",
    "sg:city":"Barcelona",
    "sg:orig_category":"Confecci\u00d3n (fabricaci\u00d3n, Al Por Mayor)",
    "sg:phone":"+34 933 11 85 19",
    "sg:postcode":"08030",
    "sg:province":"Barcelona",
    "wof:name":"Sanchez Gambin Dolores",
    "wof:placetype":"venue"
},
  "geometry": {"coordinates":[2.1860411167,41.43359375],"type":"Point"}
}