{
  "type": "Feature",
  "properties": {
    "addr:full":"Carrer de Watt, 12 Barcelona Barcelona 08014",
    "addr:housenumber":"12",
    "addr:postcode":"08014",
    "addr:street":"Carrer De Watt",
    "iso:country":"ES",
    "sg:address":"Carrer de Watt, 12",
    "sg:city":"Barcelona",
    "sg:orig_category":"Centros Empresariales",
    "sg:phone":"+34 932 98 95 50",
    "sg:postcode":"08014",
    "sg:province":"Barcelona",
    "wof:name":"Chumpitaz Rivero Flor Beatriz",
    "wof:placetype":"venue"
},
  "geometry": {"coordinates":[2.139934063,41.3758201599],"type":"Point"}
}