{
  "type": "Feature",
  "properties": {
    "iso:country":"ES",
    "sg:address":"Calle de Sabino Arana Kalea, 21",
    "sg:city":"Berango",
    "sg:orig_category":"Frutas, Legumbres Frescas Y Tempranas (al Por Menor)",
    "sg:phone":"+34 946 68 24 31",
    "sg:postcode":"48640",
    "sg:province":"Vizcaya",
    "wof:name":"Dominguez Bayon Antonia",
    "wof:placetype":"venue"
},
  "geometry": {"coordinates":[-2.9992039204,43.3663597107],"type":"Point"}
}