{
  "type": "Feature",
  "properties": {
    "addr:full":"Calle de San Vicente Martir, 208 Valencia Valencia 46007",
    "addr:housenumber":"208",
    "addr:postcode":"46007",
    "addr:street":"Calle De San Vicente Martir",
    "iso:country":"ES",
    "sg:address":"Calle de San Vicente Martir, 208",
    "sg:city":"Valencia",
    "sg:orig_category":"Agencias De Relaciones P\u00dablicas",
    "sg:phone":"+34 963 41 81 62",
    "sg:postcode":"46007",
    "sg:province":"Valencia",
    "sg:website":"www.elgabinete.com",
    "wof:name":"El Gabinete De R.r.p.p. Y Comunicacion S.a.",
    "wof:placetype":"venue"
},
  "geometry": {"coordinates":[-0.3834399879,39.4587516785],"type":"Point"}
}