{
  "type": "Feature",
  "properties": {
    "addr:full":"Calle de Alfonso Xiii, 17 Dolores Murcia 30310",
    "addr:housenumber":"17",
    "addr:postcode":"30310",
    "addr:street":"Calle De Alfonso Xiii",
    "iso:country":"ES",
    "sg:address":"Calle de Alfonso Xiii, 17",
    "sg:city":"Dolores",
    "sg:classifiers":[
        {
            "category":"Autos & Motor Vehicles",
            "subcategory":"Automobile Sales",
            "type":"Retail Goods"
        }
    ],
    "sg:phone":"+34 968 51 41 10",
    "sg:postcode":"30310",
    "sg:province":"Murcia",
    "wof:name":"Auto Escuela Brasilia S.l.",
    "wof:placetype":"venue"
},
  "geometry": {"coordinates":[-1.0030888319,37.6388893127],"type":"Point"}
}