{
  "type": "Feature",
  "properties": {
    "addr:full":"Corao, 14 Abamia Asturias 33556",
    "addr:housenumber":"14",
    "addr:postcode":"33556",
    "addr:street":"Corao;Asturias",
    "iso:country":"ES",
    "sg:address":"Corao, 14",
    "sg:city":"Abamia",
    "sg:orig_category":"Suministros Para Hoteles",
    "sg:phone":"+34 985 94 02 60",
    "sg:postcode":"33556",
    "sg:province":"Asturias",
    "wof:name":"Cibrian Puvillones Sonia",
    "wof:placetype":"venue"
},
  "geometry": {"coordinates":[-4.9671940804,43.3350143433],"type":"Point"}
}