{
  "type": "Feature",
  "properties": {
    "addr:full":"Calle de Nueva, 12 Santa Ana La Real Huelva 21359",
    "addr:housenumber":"12",
    "addr:postcode":"21359",
    "addr:street":"Calle De Nueva",
    "iso:country":"ES",
    "sg:address":"Calle de Nueva, 12",
    "sg:city":"Santa Ana La Real",
    "sg:orig_category":"Farmacias",
    "sg:phone":"+34 959 12 24 24",
    "sg:postcode":"21359",
    "sg:province":"Huelva",
    "wof:name":"Lancha Lancha Maria Lourdes",
    "wof:placetype":"venue"
},
  "geometry": {"coordinates":[-6.7246780396,37.8645744324],"type":"Point"}
}