{
  "type": "Feature",
  "properties": {
    "iso:country":"ES",
    "sg:address":"Calle de Ezequiel Solana, 83",
    "sg:city":"Madrid",
    "sg:orig_category":"Electricidad Veh\u00cdculo",
    "sg:phone":"+34 914 07 05 05",
    "sg:postcode":"28017",
    "sg:province":"Madrid",
    "wof:name":"Lopez Mu\u00f1oz Cristobal",
    "wof:placetype":"venue"
},
  "geometry": {"coordinates":[-3.6426229477,40.4280014038],"type":"Point"}
}