{
  "type": "Feature",
  "properties": {
    "iso:country":"ES",
    "sg:address":"Pda. Salada, S/n",
    "sg:city":"Artesa Lleida",
    "sg:orig_category":"Pintura, Barniz, Productos Asimilables (fabricaci\u00d3n, Al Por Mayor)",
    "sg:phone":"+34 973 16 76 58",
    "sg:postcode":"25150",
    "sg:province":"Lleida",
    "wof:name":"Hot-pint S.l.",
    "wof:placetype":"venue"
},
  "geometry": {"coordinates":[0.6257824898,41.614151001],"type":"Point"}
}