{
  "type": "Feature",
  "properties": {
    "iso:country":"ES",
    "sg:address":"Calle de Marques De Teverga, 5",
    "sg:city":"Oviedo",
    "sg:orig_category":"Institutos De Belleza",
    "sg:phone":"+34 985 24 32 00",
    "sg:postcode":"33005",
    "sg:province":"Asturias",
    "wof:name":"Valdes Nomparte Carmen",
    "wof:placetype":"venue"
},
  "geometry": {"coordinates":[-5.8554491997,43.3621139526],"type":"Point"}
}