{
  "type": "Feature",
  "properties": {
    "iso:country":"ES",
    "sg:address":"Rua Curros Enriquez (de), 9",
    "sg:city":"Santiago De Compostela",
    "sg:orig_category":"Abogados",
    "sg:phone":"+34 981 55 36 81",
    "sg:postcode":"15702",
    "sg:province":"La Coru\u00f1a",
    "wof:name":"Fraguela Y Sagastizal S.c.",
    "wof:placetype":"venue"
},
  "geometry": {"coordinates":[-8.5420618057,42.8749504089],"type":"Point"}
}