{
  "type": "Feature",
  "properties": {
    "iso:country":"ES",
    "sg:address":"Calle de Garcia Lorca, 14",
    "sg:city":"Cullar-vega",
    "sg:orig_category":"Guarder\u00cdas",
    "sg:phone":"+34 958 58 58 58",
    "sg:postcode":"18195",
    "sg:province":"Granada",
    "wof:name":"Centro Infantil La Rueda C.b.",
    "wof:placetype":"venue"
},
  "geometry": {"coordinates":[-3.6738491058,37.1547317505],"type":"Point"}
}