{
  "type": "Feature",
  "properties": {
    "addr:full":"Kale Nagusia, 55 Andoain Guip\u00f9zcoa 20140",
    "addr:housenumber":"55",
    "addr:postcode":"20140",
    "addr:street":"Kale Nagusia;Guipu\u0300Zcoa",
    "iso:country":"ES",
    "sg:address":"Kale Nagusia, 55",
    "sg:city":"Andoain",
    "sg:orig_category":"Plomeros",
    "sg:phone":"+34 943 59 25 02",
    "sg:postcode":"20140",
    "sg:province":"Guip\u00f9zcoa",
    "wof:name":"Dorronsoro Iturriza Juan Jose",
    "wof:placetype":"venue"
},
  "geometry": {"coordinates":[-2.0200839043,43.2191047668],"type":"Point"}
}