{
  "type": "Feature",
  "properties": {
    "iso:country":"ES",
    "sg:address":"Pg. E. Prat Riba, 6",
    "sg:city":"El Masnou",
    "sg:orig_category":"Estancos",
    "sg:phone":"+34 935 55 00 50",
    "sg:postcode":"08320",
    "sg:province":"Barcelona",
    "wof:name":"Rossell Funoy Francisco",
    "wof:placetype":"venue"
},
  "geometry": {"coordinates":[2.3180449009,41.4787750244],"type":"Point"}
}