{
  "type": "Feature",
  "properties": {
    "addr:full":"Rua Montemaior, 10 Verin Ourense 32600",
    "addr:housenumber":"10",
    "addr:postcode":"32600",
    "addr:street":"Rua Montemaior",
    "iso:country":"ES",
    "sg:address":"Rua Montemaior, 10",
    "sg:city":"Verin",
    "sg:orig_category":"Radiocomunicaciones, Telefon\u00cda M\u00d3vil, Radiomensajer\u00cda: Servicios, Comercializaci\u00d3n",
    "sg:phone":"+34 988 41 40 00",
    "sg:postcode":"32600",
    "sg:province":"Ourense",
    "wof:name":"Radio Popular S.a.",
    "wof:placetype":"venue"
},
  "geometry": {"coordinates":[-7.4370827675,41.939994812],"type":"Point"}
}