{
  "type": "Feature",
  "properties": {
    "addr:full":"Carrer de Lepant, 276 Barcelona Barcelona 08013",
    "addr:housenumber":"276",
    "addr:postcode":"08013",
    "addr:street":"Carrer De Lepant",
    "iso:country":"ES",
    "sg:address":"Carrer de Lepant, 276",
    "sg:city":"Barcelona",
    "sg:orig_category":"Fabricaci\u00d3n, Importaci\u00d3n, Venta De Material De Telefon\u00cda, Peritelefon\u00cda",
    "sg:phone":"+34 932 65 64 38",
    "sg:postcode":"08013",
    "sg:province":"Barcelona",
    "wof:name":"Inty Raymi Comunicacio S.l.",
    "wof:placetype":"venue"
},
  "geometry": {"coordinates":[2.1769928932,41.4044380188],"type":"Point"}
}