{
  "type": "Feature",
  "properties": {
    "iso:country":"ES",
    "sg:address":"Calle de Mayor, 71",
    "sg:city":"Almaden",
    "sg:orig_category":"Agencias De Viajes",
    "sg:phone":"+34 926 71 02 04",
    "sg:postcode":"13400",
    "sg:province":"Ciudad Real",
    "sg:website":"www.viajesmontesur.net",
    "wof:name":"Azogue Tours S.l.",
    "wof:placetype":"venue"
},
  "geometry": {"coordinates":[-4.8337240219,38.7758407593],"type":"Point"}
}