{
  "type": "Feature",
  "properties": {
    "addr:full":"Calle de Mayor, 22 Biescas Huesca 22630",
    "addr:housenumber":"22",
    "addr:postcode":"22630",
    "addr:street":"Calle De Mayor",
    "iso:country":"ES",
    "sg:address":"Calle de Mayor, 22",
    "sg:city":"Biescas",
    "sg:orig_category":"Quiropr\u00c1cticos",
    "sg:phone":"+34 974 49 55 21",
    "sg:postcode":"22630",
    "sg:province":"Huesca",
    "wof:name":"Casta\u00f1er Molinero Ana Maria",
    "wof:placetype":"venue"
},
  "geometry": {"coordinates":[-0.3197749853,42.6286354065],"type":"Point"}
}