{
  "type": "Feature",
  "properties": {
    "addr:full":"Calle de Puente Colgante, 38 Valladolid Valladolid 47006",
    "addr:housenumber":"38",
    "addr:postcode":"47006",
    "addr:street":"Calle De Puente Colgante",
    "iso:country":"ES",
    "sg:address":"Calle de Puente Colgante, 38",
    "sg:city":"Valladolid",
    "sg:orig_category":"Peluqueros: De Se\u00d1oras",
    "sg:phone":"+34 983 27 75 60",
    "sg:postcode":"47006",
    "sg:province":"Valladolid",
    "wof:name":"Perez Gonzalez Luis Andres",
    "wof:placetype":"venue"
},
  "geometry": {"coordinates":[-4.7380189896,41.6408996582],"type":"Point"}
}