{
  "type": "Feature",
  "properties": {
    "iso:country":"ES",
    "sg:address":"Calle de Breton De Los Herreros, 45",
    "sg:city":"Madrid",
    "sg:orig_category":"Administradores De Bienes Y Delegados De Comunidades De Propietarios",
    "sg:phone":"+34 913 99 51 92",
    "sg:postcode":"28003",
    "sg:province":"Madrid",
    "wof:name":"Yanes Gomez Luis",
    "wof:placetype":"venue"
},
  "geometry": {"coordinates":[-3.6964299679,40.4396057129],"type":"Point"}
}