{
  "type": "Feature",
  "properties": {
    "iso:country":"ES",
    "sg:address":"Calle de Mayor, 29",
    "sg:city":"Cartagena",
    "sg:orig_category":"Urbanistas",
    "sg:phone":"+34 968 52 59 14",
    "sg:postcode":"30201",
    "sg:province":"Murcia",
    "wof:name":"Promocion Del Mar S. A.",
    "wof:placetype":"venue"
},
  "geometry": {"coordinates":[-0.9156429768,37.600566864],"type":"Point"}
}