{
  "type": "Feature",
  "properties": {
    "iso:country":"ES",
    "sg:address":"Avda Ana De Viya, 7",
    "sg:city":"Cadiz",
    "sg:orig_category":"Abogados",
    "sg:phone":"+34 956 25 58 18",
    "sg:postcode":"11009",
    "sg:province":"C\u00e1diz",
    "wof:name":"Lopez Villalta Antonio",
    "wof:placetype":"venue"
},
  "geometry": {"coordinates":[-6.2798280716,36.5117034912],"type":"Point"}
}