{
  "type": "Feature",
  "properties": {
    "addr:full":"Calle de Bolsa, 14 Madrid Madrid 28012",
    "addr:housenumber":"14",
    "addr:postcode":"madrid;28012",
    "addr:street":"Calle De Bolsa",
    "iso:country":"ES",
    "sg:address":"Calle de Bolsa, 14",
    "sg:city":"Madrid",
    "sg:orig_category":"Pe\u00d1as Y Asociaciones Varias",
    "sg:phone":"+34 902 24 40 00",
    "sg:postcode":"28012",
    "sg:province":"Madrid",
    "wof:name":"Fundacion Plan International Espa\u00d1a",
    "wof:placetype":"venue"
},
  "geometry": {"coordinates":[-3.7054502964,40.4150009155],"type":"Point"}
}