{
  "type": "Feature",
  "properties": {
    "addr:full":"Carrer de Bereng Tornamira, 7 Palma Islas Baleares 07012",
    "addr:housenumber":"7",
    "addr:postcode":"07012",
    "addr:street":"Carrer De Bereng Tornamira",
    "iso:country":"ES",
    "sg:address":"Carrer de Bereng Tornamira, 7",
    "sg:city":"Palma",
    "sg:orig_category":"Alquiler De Veh\u00cdculos: Turismos Y Utilitarios",
    "sg:phone":"+34 971 71 10 48",
    "sg:postcode":"07012",
    "sg:province":"Islas Baleares",
    "sg:website":"www.autoscastello.com",
    "wof:name":"Tomeueen S.l",
    "wof:placetype":"venue"
},
  "geometry": {"coordinates":[2.6437900066,39.5716934204],"type":"Point"}
}