{
  "type": "Feature",
  "properties": {
    "addr:full":"Calle de Fonfria, 3 Potes Cantabria 39570",
    "addr:housenumber":"3",
    "addr:postcode":"39570",
    "addr:street":"Calle De Fonfria",
    "iso:country":"ES",
    "sg:address":"Calle de Fonfria, 3",
    "sg:city":"Potes",
    "sg:orig_category":"Cl\u00cdnicas Dentales",
    "sg:phone":"+34 942 73 10 83",
    "sg:postcode":"39570",
    "sg:province":"Cantabria",
    "wof:name":"Amigo Cabria Maria Dolores",
    "wof:placetype":"venue"
},
  "geometry": {"coordinates":[-4.6299862862,43.1538505554],"type":"Point"}
}