{
  "type": "Feature",
  "properties": {
    "iso:country":"ES",
    "sg:address":"Calle de Juan Pablo Bonet, 20",
    "sg:city":"Zaragoza",
    "sg:orig_category":"Bisuter\u00cda, Joyer\u00cda, Relojer\u00cda (al Por Menor)",
    "sg:phone":"+34 976 27 40 34",
    "sg:postcode":"50006",
    "sg:province":"Zaragoza",
    "wof:name":"Obede Mallen Maria Lucia",
    "wof:placetype":"venue"
},
  "geometry": {"coordinates":[-0.8886253834,41.6405334473],"type":"Point"}
}