{
  "type": "Feature",
  "properties": {
    "iso:country":"ES",
    "sg:address":"Plaz Constitucion (de La), S/n",
    "sg:city":"Navarrevisca",
    "sg:orig_category":"Empresas De Electricidad En General",
    "sg:phone":"+34 920 28 90 03",
    "sg:postcode":"05115",
    "sg:province":"\u00c1vila",
    "wof:name":"Electra La Honorina S.l.",
    "wof:placetype":"venue"
},
  "geometry": {"coordinates":[-4.8952589035,40.3646850586],"type":"Point"}
}