{
  "type": "Feature",
  "properties": {
    "iso:country":"ES",
    "sg:address":"Calle de Pirineos, 14",
    "sg:city":"Teruel",
    "sg:orig_category":"Empresas De Vigilancia, Guardia Y Protecci\u00d3n",
    "sg:phone":"+34 978 60 71 91",
    "sg:postcode":"44003",
    "sg:province":"Teruel",
    "sg:website":"www.prosegur.es",
    "wof:name":"Prosegur Transportes Blindados S. A.",
    "wof:placetype":"venue"
},
  "geometry": {"coordinates":[-1.1032700539,40.346157074],"type":"Point"}
}