{
  "type": "Feature",
  "properties": {
    "iso:country":"ES",
    "sg:address":"Coop Vrg Riansares, S/n",
    "sg:city":"Tarancon",
    "sg:orig_category":"Peluquer\u00cdas, Peluquer\u00cda Mixta",
    "sg:phone":"+34 969 32 47 57",
    "sg:postcode":"16400",
    "sg:province":"Cuenca",
    "wof:name":"Salcedo Moreno Rafaela",
    "wof:placetype":"venue"
},
  "geometry": {"coordinates":[-3.0049140453,40.0147743225],"type":"Point"}
}