{
  "type": "Feature",
  "properties": {
    "iso:country":"ES",
    "sg:address":"Carrer de Mila, 76",
    "sg:city":"Santa Coloma De Gramenet",
    "sg:orig_category":"Reposter\u00cdas",
    "sg:phone":"+34 934 68 44 05",
    "sg:postcode":"08921",
    "sg:province":"Barcelona",
    "wof:name":"Barna Pa S.l.",
    "wof:placetype":"venue"
},
  "geometry": {"coordinates":[2.2195980549,41.4553985596],"type":"Point"}
}