{
  "type": "Feature",
  "properties": {
    "iso:country":"ES",
    "sg:address":"Carrer de Francesc Llunell, 41",
    "sg:city":"Esplugues Llobregat",
    "sg:orig_category":"Pod\u00d3logos: Pedicuros",
    "sg:phone":"+34 934 73 90 57",
    "sg:postcode":"08950",
    "sg:province":"Barcelona",
    "wof:name":"Reverte Collado Pedro",
    "wof:placetype":"venue"
},
  "geometry": {"coordinates":[2.085860014,41.3731956482],"type":"Point"}
}