{
  "type": "Feature",
  "properties": {
    "iso:country":"ES",
    "sg:address":"Calle de General Tamayo, 12",
    "sg:city":"Almeria",
    "sg:orig_category":"Lencer\u00cda Femenina, Corseter\u00cda, Trajes De Ba\u00d1o (al Por Menor)",
    "sg:phone":"+34 950 26 86 67",
    "sg:postcode":"04004",
    "sg:province":"Almer\u00eda",
    "wof:name":"Almacenes Enlo S.l.",
    "wof:placetype":"venue"
},
  "geometry": {"coordinates":[-2.462852478,36.836933136],"type":"Point"}
}