{
  "type": "Feature",
  "properties": {
    "iso:country":"ES",
    "sg:address":"Carr Sant Cristofol, 2",
    "sg:city":"Eivissa",
    "sg:orig_category":"Fabricaci\u00d3n De Muebles Y De Accesorios De Cuartos De Ba\u00d1o",
    "sg:phone":"+34 971 19 16 41",
    "sg:postcode":"07800",
    "sg:province":"Islas Baleares",
    "wof:name":"Sanchez Gomez Vicente",
    "wof:placetype":"venue"
},
  "geometry": {"coordinates":[1.4291679859,38.9127006531],"type":"Point"}
}