{
  "type": "Feature",
  "properties": {
    "addr:full":"Pl. Diplodocus, 2 Badalona Barcelona 08911",
    "addr:housenumber":"2",
    "addr:postcode":"08911",
    "addr:street":"Pl. Diplodocus",
    "iso:country":"ES",
    "sg:address":"Pl. Diplodocus, 2",
    "sg:city":"Badalona",
    "sg:orig_category":"Estancos",
    "sg:phone":"+34 933 89 59 97",
    "sg:postcode":"08911",
    "sg:province":"Barcelona",
    "wof:name":"Ambrosio Cadena Herminio",
    "wof:placetype":"venue"
},
  "geometry": {"coordinates":[2.2601411343,41.4563484192],"type":"Point"}
}