{
  "type": "Feature",
  "properties": {
    "addr:full":"Calle de Adelfas (las), 23 Monte Alto C\u00f3rdoba 14100",
    "addr:housenumber":"23",
    "addr:postcode":"14100",
    "addr:street":"Calle De Adelfas Las;Co\u0301Rdoba",
    "iso:country":"ES",
    "sg:address":"Calle de Adelfas (las), 23",
    "sg:city":"Monte Alto",
    "sg:orig_category":"Delegados, Agentes De Tr\u00c1nsito, Auxiliares De Transporte Internacional",
    "sg:phone":"+34 957 30 08 63",
    "sg:postcode":"14100",
    "sg:province":"C\u00f3rdoba",
    "wof:name":"Transportes Montse Y Alonso S.l.",
    "wof:placetype":"venue"
},
  "geometry": {"coordinates":[-4.9374890327,37.6685142517],"type":"Point"}
}