{
  "type": "Feature",
  "properties": {
    "iso:country":"ES",
    "sg:address":"Calle de Virgen De La Soledad, 21",
    "sg:city":"Guadalajara",
    "sg:orig_category":"Asociaciones Y Clubs Deportivos",
    "sg:phone":"+34 949 21 28 07",
    "sg:postcode":"19003",
    "sg:province":"Guadalajara",
    "wof:name":"Desarrollo E Inversiones Premium 1s.l.",
    "wof:placetype":"venue"
},
  "geometry": {"coordinates":[-3.1654000282,40.6277999878],"type":"Point"}
}