{
  "type": "Feature",
  "properties": {
    "iso:country":"ES",
    "sg:address":"Calle de Hoya De La Mora, 20",
    "sg:city":"Granada",
    "sg:orig_category":"Promotores Constructores",
    "sg:phone":"+34 958 12 03 15",
    "sg:postcode":"18008",
    "sg:province":"Granada",
    "wof:name":"Gea-21 S.a.",
    "wof:placetype":"venue"
},
  "geometry": {"coordinates":[-3.5846040249,37.1619567871],"type":"Point"}
}