{
  "type": "Feature",
  "properties": {
    "addr:full":"Calle de Matiko, 35 Bilbao Vizcaya 48007",
    "addr:housenumber":"35",
    "addr:postcode":"48007",
    "addr:street":"Calle De Matiko",
    "iso:country":"ES",
    "sg:address":"Calle de Matiko, 35",
    "sg:city":"Bilbao",
    "sg:orig_category":"M\u00c9dicos: Estomatolog\u00cda",
    "sg:phone":"+34 944 46 51 51",
    "sg:postcode":"48007",
    "sg:province":"Vizcaya",
    "wof:name":"Ruiz Ruiz Carmelo",
    "wof:placetype":"venue"
},
  "geometry": {"coordinates":[-2.921681881,43.2666511536],"type":"Point"}
}