{
  "type": "Feature",
  "properties": {
    "iso:country":"ES",
    "sg:address":"Calle de Principe De Vergara, 211",
    "sg:city":"Madrid",
    "sg:orig_category":"Seguridad En El Trabajo Y Prevenci\u00d3n De Riesgos Laborales",
    "sg:phone":"+34 914 11 07 37",
    "sg:postcode":"28002",
    "sg:province":"Madrid",
    "wof:name":"Pronutel S.l.",
    "wof:placetype":"venue"
},
  "geometry": {"coordinates":[-3.6777999401,40.4512252808],"type":"Point"}
}