{
  "type": "Feature",
  "properties": {
    "iso:country":"ES",
    "sg:address":"Calle de Enrique Mari\u00d1as Romero Periodista, 11",
    "sg:city":"Coru\u00d1a",
    "sg:classifiers":[
        {
            "category":"Personal",
            "subcategory":"Barber",
            "type":"Services"
        }
    ],
    "sg:phone":"+34 981 13 74 06",
    "sg:postcode":"15009",
    "sg:province":"A Coru\u00f1a",
    "sg:tags":[
        "caballeros",
        "de",
        "peluqueros"
    ],
    "wof:name":"Valoria Fernandez Marisol",
    "wof:placetype":"venue"
},
  "geometry": {"coordinates":[-8.4045228958,43.3400688171],"type":"Point"}
}