{
  "type": "Feature",
  "properties": {
    "iso:country":"ES",
    "sg:address":"Carrer de Irlanda, 34",
    "sg:city":"Barcelona",
    "sg:orig_category":"Estancos",
    "sg:phone":"+34 933 46 50 02",
    "sg:postcode":"08030",
    "sg:province":"Barcelona",
    "wof:name":"Collins Jones Enrique Octavio",
    "wof:placetype":"venue"
},
  "geometry": {"coordinates":[2.1859109402,41.4315490723],"type":"Point"}
}