{
  "type": "Feature",
  "properties": {
    "addr:full":"Avda Juan Carlos I, Km. 0109,0 Avila \u00c1vila 05004",
    "addr:postcode":"05004",
    "addr:street":"Avda Juan Carlos I Km. 0109,0;A\u0301Vila",
    "iso:country":"ES",
    "sg:address":"Avda Juan Carlos I, Km. 0109,0",
    "sg:city":"Avila",
    "sg:orig_category":"Ropa Para Caballeros (al Por Menor)",
    "sg:phone":"+34 920 21 90 65",
    "sg:postcode":"05004",
    "sg:province":"\u00c1vila",
    "sg:website":"www.spf.com",
    "wof:name":"Cortefiel S.a.",
    "wof:placetype":"venue"
},
  "geometry": {"coordinates":[-4.656484127,40.6688957214],"type":"Point"}
}