{
  "type": "Feature",
  "properties": {
    "addr:full":"Calle de Constitucion, 31 Zarza Granadilla C\u00e1ceres 10710",
    "addr:housenumber":"31;granadilla",
    "addr:postcode":"10710",
    "addr:street":"Calle De Constitucion;Ca\u0301Ceres",
    "iso:country":"ES",
    "sg:address":"Calle de Constitucion, 31",
    "sg:city":"Zarza Granadilla",
    "sg:orig_category":"Contenedores (mercanc\u00cdas)",
    "sg:phone":"+34 927 48 60 83",
    "sg:postcode":"10710",
    "sg:province":"C\u00e1ceres",
    "wof:name":"Transportes Los Mellis S.l.",
    "wof:placetype":"venue"
},
  "geometry": {"coordinates":[-6.0463480949,40.2390441895],"type":"Point"}
}