{
  "type": "Feature",
  "properties": {
    "addr:full":"Calle de San Pascual, 55 Albatera Alicante 03340",
    "addr:housenumber":"55",
    "addr:postcode":"03340",
    "addr:street":"Calle De San Pascual",
    "iso:country":"ES",
    "sg:address":"Calle de San Pascual, 55",
    "sg:city":"Albatera",
    "sg:orig_category":"Ropa Y Art\u00cdculos Pre",
    "sg:phone":"+34 965 48 62 94",
    "sg:postcode":"03340",
    "sg:province":"Alicante",
    "wof:name":"Berna Ca\u00f1avate Carmelo",
    "wof:placetype":"venue"
},
  "geometry": {"coordinates":[-0.8659989834,38.1809692383],"type":"Point"}
}