{
  "type": "Feature",
  "properties": {
    "iso:country":"ES",
    "sg:address":"Calle de Diego De Leon, 69",
    "sg:city":"Madrid",
    "sg:orig_category":"Trabajos De Perforaciones, Sondeos, Construcci\u00d3n De Pozos",
    "sg:phone":"+34 913 09 08 96",
    "sg:postcode":"28006",
    "sg:province":"Madrid",
    "wof:name":"Sonpetrol Espa A S.a.",
    "wof:placetype":"venue"
},
  "geometry": {"coordinates":[-3.6750395298,40.4345436096],"type":"Point"}
}