{
  "type": "Feature",
  "properties": {
    "addr:full":"Calle de Alfredo Marquerie, 5 Madrid Madrid 28034",
    "addr:housenumber":"5",
    "addr:postcode":"28034",
    "addr:street":"Calle De Alfredo Marquerie",
    "iso:country":"ES",
    "sg:address":"Calle de Alfredo Marquerie, 5",
    "sg:city":"Madrid",
    "sg:orig_category":"Agencias Y Agentes Comerciales, Representantes",
    "sg:phone":"+34 917 30 19 17",
    "sg:postcode":"28034",
    "sg:province":"Madrid",
    "wof:name":"Lorenzo Perez Angel",
    "wof:placetype":"venue"
},
  "geometry": {"coordinates":[-3.696821928,40.4867401123],"type":"Point"}
}