{
  "type": "Feature",
  "properties": {
    "addr:full":"Calle de Juan Xxiii, 12 Prejano La Rioja 26589",
    "addr:housenumber":"12",
    "addr:postcode":"26589",
    "addr:street":"Calle De Juan Xxiii;Rioja",
    "iso:country":"ES",
    "sg:address":"Calle de Juan Xxiii, 12",
    "sg:city":"Prejano",
    "sg:orig_category":"Molduras, Junquillos, Listones Y Molduras Perforadas",
    "sg:phone":"+34 941 39 90 72",
    "sg:postcode":"26589",
    "sg:province":"La Rioja",
    "wof:name":"Bobadilla Sota Angel",
    "wof:placetype":"venue"
},
  "geometry": {"coordinates":[-2.2366919518,42.2125053406],"type":"Point"}
}