{
  "type": "Feature",
  "properties": {
    "addr:full":"Cust San Vicente, 8 Madrid Madrid 28008",
    "addr:housenumber":"8",
    "addr:postcode":"madrid;28008",
    "addr:street":"San Vicente",
    "iso:country":"ES",
    "sg:address":"Cust San Vicente, 8",
    "sg:city":"Madrid",
    "sg:orig_category":"Alimentaci\u00d3n General (al Por Menor)",
    "sg:phone":"+34 915 42 87 16",
    "sg:postcode":"28008",
    "sg:province":"Madrid",
    "wof:name":"Qin  Mei",
    "wof:placetype":"venue"
},
  "geometry": {"coordinates":[-3.7142379284,40.4213905334],"type":"Point"}
}