{
  "type": "Feature",
  "properties": {
    "iso:country":"ES",
    "sg:address":"Carrer de Pere Iv, 101",
    "sg:city":"Barcelona",
    "sg:orig_category":"Molduras, Junquillos, Listones Y Molduras Perforadas",
    "sg:phone":"+34 934 85 47 48",
    "sg:postcode":"08018",
    "sg:province":"Barcelona",
    "wof:name":"Juanola Duran Eloi",
    "wof:placetype":"venue"
},
  "geometry": {"coordinates":[2.1943540573,41.3989257812],"type":"Point"}
}