{
  "type": "Feature",
  "properties": {
    "addr:full":"Calle de Gertrudis Gomez De Avellaneda, 11 Estacion Madrid 28400",
    "addr:housenumber":"11 estacion",
    "addr:postcode":"28400",
    "addr:street":"Calle De Gertrudis Gomez De Avellaneda",
    "iso:country":"ES",
    "sg:address":"Calle de Gertrudis Gomez De Avellaneda, 11",
    "sg:city":"Estacion",
    "sg:orig_category":"Prendas De Cuero Y De Piel (al Por Menor)",
    "sg:phone":"+34 918 49 99 65",
    "sg:postcode":"28400",
    "sg:province":"Madrid",
    "wof:name":"Abel Perez Clementina",
    "wof:placetype":"venue"
},
  "geometry": {"coordinates":[-3.700346,40.416691],"type":"Point"}
}