{
  "type": "Feature",
  "properties": {
    "iso:country":"ES",
    "sg:address":"Calle de Maria Tubau, 6",
    "sg:city":"Madrid",
    "sg:orig_category":"Importaci\u00d3n",
    "sg:phone":"+34 913 58 85 85",
    "sg:postcode":"28050",
    "sg:province":"Madrid",
    "sg:website":"www.crymsa.com",
    "wof:name":"Crymsa",
    "wof:placetype":"venue"
},
  "geometry": {"coordinates":[-3.6734969616,40.513507843],"type":"Point"}
}