{
  "type": "Feature",
  "properties": {
    "iso:country":"ES",
    "sg:address":"Calle de Cardenal Carvajal, 2",
    "sg:city":"Badajoz",
    "sg:orig_category":"Sindicatos De Trabajadores",
    "sg:phone":"+34 924 24 98 15",
    "sg:postcode":"06001",
    "sg:province":"Badajoz",
    "wof:name":"Mca-ugt",
    "wof:placetype":"venue"
},
  "geometry": {"coordinates":[-6.9728322029,38.8802337646],"type":"Point"}
}