{
  "type": "Feature",
  "properties": {
    "addr:full":"Calle de Tomas Capelo, 6 Sant Joan D'alacant Alicante 03550",
    "addr:housenumber":"6",
    "addr:postcode":"03550",
    "addr:street":"Calle De Tomas Capelo",
    "iso:country":"ES",
    "sg:address":"Calle de Tomas Capelo, 6",
    "sg:city":"Sant Joan D'alacant",
    "sg:orig_category":"Asesor\u00cda Fiscal Y Jur\u00cddica",
    "sg:phone":"+34 965 65 90 55",
    "sg:postcode":"03550",
    "sg:province":"Alicante",
    "wof:name":"M Y S Asesores S.c.",
    "wof:placetype":"venue"
},
  "geometry": {"coordinates":[-0.4322516024,38.3986282349],"type":"Point"}
}