{
  "type": "Feature",
  "properties": {
    "addr:full":"Calle de Bidebarrieta, 29 Llodio \u00c1lava 01400",
    "addr:housenumber":"29",
    "addr:postcode":"01400",
    "addr:street":"Calle De Bidebarrieta",
    "iso:country":"ES",
    "sg:address":"Calle de Bidebarrieta, 29",
    "sg:city":"Llodio",
    "sg:orig_category":"Electricidad Veh\u00cdculo",
    "sg:phone":"+34 946 72 07 65",
    "sg:postcode":"01400",
    "sg:province":"\u00c1lava",
    "wof:name":"Autoelectricidad Ibar-lau S.c.",
    "wof:placetype":"venue"
},
  "geometry": {"coordinates":[-2.9446389675,43.1480712891],"type":"Point"}
}