{
  "type": "Feature",
  "properties": {
    "iso:country":"ES",
    "sg:address":"Avda Hermanos Bou, 38",
    "sg:city":"Castellon",
    "sg:orig_category":"T\u00c9cnicos Veterinarios",
    "sg:phone":"+34 964 23 64 95",
    "sg:postcode":"12003",
    "sg:province":"Castell\u00f3n",
    "wof:name":"Monfort Llorca Jose Carlos",
    "wof:placetype":"venue"
},
  "geometry": {"coordinates":[-0.0077,39.9836883545],"type":"Point"}
}