{
  "type": "Feature",
  "properties": {
    "iso:country":"ES",
    "sg:address":"Ctra General Barzana, S/n",
    "sg:city":"Barzana",
    "sg:classifiers":[
        {
            "category":"Taxi",
            "type":"Transportation"
        }
    ],
    "sg:phone":"+34 985 76 81 06",
    "sg:postcode":"33117",
    "sg:province":"Asturias",
    "wof:name":"Barrio Viejo Francisco",
    "wof:placetype":"venue"
},
  "geometry": {"coordinates":[-5.9834308624,43.1733856201],"type":"Point"}
}