{
  "type": "Feature",
  "properties": {
    "addr:full":"Carrer de Aribau, 40 Barcelona Barcelona 08011",
    "addr:housenumber":"40",
    "addr:postcode":"08011",
    "addr:street":"Carrer De Aribau",
    "iso:country":"ES",
    "sg:address":"Carrer de Aribau, 40",
    "sg:city":"Barcelona",
    "sg:orig_category":"\u00d3ptica: Instrumentos (fabricaci\u00d3n)",
    "sg:phone":"+34 934 54 01 75",
    "sg:postcode":"08011",
    "sg:province":"Barcelona",
    "wof:name":"Masia Gomez Vicente",
    "wof:placetype":"venue"
},
  "geometry": {"coordinates":[2.1606040001,41.3876533508],"type":"Point"}
}