{
  "type": "Feature",
  "properties": {
    "addr:full":"Calle de Llano San Ramon, 3 Marbella M\u00e1laga 29600",
    "addr:housenumber":"3",
    "addr:postcode":"29600",
    "addr:street":"Calle De Llano San Ramon;Ma\u0301Laga",
    "iso:country":"ES",
    "sg:address":"Calle de Llano San Ramon, 3",
    "sg:city":"Marbella",
    "sg:orig_category":"Inversiones",
    "sg:phone":"+34 952 86 50 53",
    "sg:postcode":"29600",
    "sg:province":"M\u00e1laga",
    "wof:name":"Inversiones San Carlos S.l.",
    "wof:placetype":"venue"
},
  "geometry": {"coordinates":[-4.8819169998,36.5080032349],"type":"Point"}
}