{
  "type": "Feature",
  "properties": {
    "addr:full":"Calle de Adolfo Suarez De Figueroa, 5 Estepona M\u00e1laga 29680",
    "addr:housenumber":"5",
    "addr:postcode":"29680",
    "addr:street":"Calle De Adolfo Suarez De Figueroa",
    "iso:country":"ES",
    "sg:address":"Calle de Adolfo Suarez De Figueroa, 5",
    "sg:city":"Estepona",
    "sg:orig_category":"Supermercados Y Hipermercados",
    "sg:phone":"+34 952 79 18 27",
    "sg:postcode":"29680",
    "sg:province":"M\u00e1laga",
    "wof:name":"Alimentacion Fercat S.l.",
    "wof:placetype":"venue"
},
  "geometry": {"coordinates":[-5.1445941925,36.4259719849],"type":"Point"}
}