{
  "type": "Feature",
  "properties": {
    "addr:full":"Calle de Antonio Machado, 53 Torres Cotillas Murcia 30565",
    "addr:housenumber":"53",
    "addr:postcode":"30565",
    "addr:street":"Calle De Antonio Machado",
    "iso:country":"ES",
    "sg:address":"Calle de Antonio Machado, 53",
    "sg:city":"Torres Cotillas",
    "sg:orig_category":"Mercer\u00cda, Lencer\u00cda (al Por Menor)",
    "sg:phone":"+34 968 62 33 79",
    "sg:postcode":"30565",
    "sg:province":"Murcia",
    "wof:name":"Fernandez Torres Amadora",
    "wof:placetype":"venue"
},
  "geometry": {"coordinates":[-1.2425086498,38.0278511047],"type":"Point"}
}