{
  "type": "Feature",
  "properties": {
    "iso:country":"ES",
    "sg:address":"General, 1",
    "sg:city":"Pobladura Somoza",
    "sg:orig_category":"Conservas De Legumbres (fabricaci\u00d3n, Al Por Mayor)",
    "sg:phone":"+34 987 68 41 28",
    "sg:postcode":"24512",
    "sg:province":"Le\u00f3n",
    "wof:name":"Conservas Artesanas De Villafranca S.l.",
    "wof:placetype":"venue"
},
  "geometry": {"coordinates":[-6.7514939308,42.7020530701],"type":"Point"}
}