{
  "type": "Feature",
  "properties": {
    "iso:country":"ES",
    "sg:address":"Calle de Don German Cabrero, 19",
    "sg:city":"Valverde Camino",
    "sg:orig_category":"Enfermeras: Consultas, Atenci\u00d3n A Domicilio",
    "sg:phone":"+34 959 55 09 48",
    "sg:postcode":"21600",
    "sg:province":"Huelva",
    "wof:name":"Limpo Becerra Pedro",
    "wof:placetype":"venue"
},
  "geometry": {"coordinates":[-6.7572507858,37.5743141174],"type":"Point"}
}