{
  "type": "Feature",
  "properties": {
    "addr:full":"Calle de Salvador Minguijon, 35 Zaragoza Zaragoza 50002",
    "addr:housenumber":"35",
    "addr:postcode":"50002",
    "addr:street":"Calle De Salvador Minguijon",
    "iso:country":"ES",
    "sg:address":"Calle de Salvador Minguijon, 35",
    "sg:city":"Zaragoza",
    "sg:orig_category":"Molduras, Junquillos, Listones Y Molduras Perforadas",
    "sg:phone":"+34 976 20 18 82",
    "sg:postcode":"50002",
    "sg:province":"Zaragoza",
    "wof:name":"Cubero Aguado Jose Luis",
    "wof:placetype":"venue"
},
  "geometry": {"coordinates":[-0.8615580201,41.6485214233],"type":"Point"}
}