{
  "type": "Feature",
  "properties": {
    "iso:country":"ES",
    "sg:address":"Carrer de Balmes, 5",
    "sg:city":"S. Cugat Valles",
    "sg:orig_category":"Agencias Y Agentes Comerciales, Representantes",
    "sg:phone":"+34 936 75 59 06",
    "sg:postcode":"08172",
    "sg:province":"Barcelona",
    "wof:name":"I.jaume Joan S.c.p",
    "wof:placetype":"venue"
},
  "geometry": {"coordinates":[2.084939003,41.47133255],"type":"Point"}
}