{
  "type": "Feature",
  "properties": {
    "iso:country":"ES",
    "sg:address":"Calle de Escorredor, L', 9",
    "sg:city":"Burriana",
    "sg:orig_category":"Comerciantes Al Por Mayor De Vinos, Licores Y Alcoholes",
    "sg:phone":"+34 964 51 03 93",
    "sg:postcode":"12530",
    "sg:province":"Castell\u00f3n",
    "wof:name":"Valero Branchadell Rafael",
    "wof:placetype":"venue"
},
  "geometry": {"coordinates":[-0.0861279964,39.8888702393],"type":"Point"}
}