{
  "type": "Feature",
  "properties": {
    "iso:country":"ES",
    "sg:address":"Calle de Delicias, 3",
    "sg:city":"Arenales De San Gregorio",
    "sg:orig_category":"Producci\u00d3n De Abonos Y De Fertilizantes",
    "sg:phone":"+34 926 58 40 42",
    "sg:postcode":"13619",
    "sg:province":"Ciudad Real",
    "wof:name":"Marcos-alberca Martinez Martin",
    "wof:placetype":"venue"
},
  "geometry": {"coordinates":[-3.0310795307,39.3088607788],"type":"Point"}
}