{
  "type": "Feature",
  "properties": {
    "addr:full":"Calle de Arzobispo De Castro, 13 Burgos Burgos 09007",
    "addr:housenumber":"13",
    "addr:postcode":"09007",
    "addr:street":"Calle De Arzobispo De Castro",
    "iso:country":"ES",
    "sg:address":"Calle de Arzobispo De Castro, 13",
    "sg:city":"Burgos",
    "sg:orig_category":"Peluquer\u00cdas, Peluquer\u00cda Mixta",
    "sg:phone":"+34 947 21 42 73",
    "sg:postcode":"09007",
    "sg:province":"Burgos",
    "wof:name":"Gil Melero Maria Pilar",
    "wof:placetype":"venue"
},
  "geometry": {"coordinates":[-3.668746233,42.3522872925],"type":"Point"}
}