{
  "type": "Feature",
  "properties": {
    "addr:full":"Calle de Ceron, 1 Jaen Ja\u00e9n 23004",
    "addr:housenumber":"1;jae\u0301n",
    "addr:postcode":"23004",
    "addr:street":"Calle De Ceron",
    "iso:country":"ES",
    "sg:address":"Calle de Ceron, 1",
    "sg:city":"Jaen",
    "sg:orig_category":"Postigos, Persianas Y Celos\u00cdas",
    "sg:phone":"+34 953 23 44 76",
    "sg:postcode":"23004",
    "sg:province":"Ja\u00e9n",
    "wof:name":"Colmenero Carrillo Joaquin",
    "wof:placetype":"venue"
},
  "geometry": {"coordinates":[-3.7898190022,37.7655601501],"type":"Point"}
}