{
  "type": "Feature",
  "properties": {
    "addr:full":"Calle de Nueva Avenida, 33 Villapalacios Albacete 02350",
    "addr:postcode":"02350",
    "addr:street":"Calle De;Avenida 33",
    "iso:country":"ES",
    "sg:address":"Calle de Nueva Avenida, 33",
    "sg:city":"Villapalacios",
    "sg:orig_category":"Empresas De Carpinter\u00cda Met\u00c1lica",
    "sg:phone":"+34 967 39 81 86",
    "sg:postcode":"02350",
    "sg:province":"Albacete",
    "wof:name":"Romero Sanchez Jose Vicente",
    "wof:placetype":"venue"
},
  "geometry": {"coordinates":[-2.631248951,38.5766906738],"type":"Point"}
}