{
  "type": "Feature",
  "properties": {
    "addr:full":"Carrer de Urals, 4 Sabadell Barcelona 08207",
    "addr:housenumber":"4",
    "addr:postcode":"08207",
    "addr:street":"Carrer De Urals",
    "iso:country":"ES",
    "sg:address":"Carrer de Urals, 4",
    "sg:city":"Sabadell",
    "sg:orig_category":"Reposter\u00cdas",
    "sg:phone":"+34 937 16 69 29",
    "sg:postcode":"08207",
    "sg:province":"Barcelona",
    "wof:name":"Sempere Sabater Juan Manuel",
    "wof:placetype":"venue"
},
  "geometry": {"coordinates":[2.0916099548,41.5724411011],"type":"Point"}
}