{
  "type": "Feature",
  "properties": {
    "iso:country":"ES",
    "sg:address":"Pol Ind Magdalena, 9",
    "sg:city":"Castello Plana",
    "sg:classifiers":[
        {
            "category":"Casinos & Gambling",
            "type":"Entertainment"
        }
    ],
    "sg:phone":"+34 964 24 49 05",
    "sg:postcode":"12004",
    "sg:province":"Castell\u00f3n",
    "sg:tags":[
        "locale",
        "de",
        "juego"
    ],
    "sg:website":"www.gleis.es",
    "wof:name":"Gleis 2000 S.l.",
    "wof:placetype":"venue"
},
  "geometry": {"coordinates":[-0.0360242017,39.9860687256],"type":"Point"}
}