{
  "type": "Feature",
  "properties": {
    "iso:country":"ES",
    "sg:address":"Pgno Indust. Forques, 2",
    "sg:city":"Onda",
    "sg:orig_category":"Asesor\u00cda Para La Organizaci\u00d3n Y Gesti\u00d3n Del Transporte",
    "sg:phone":"+34 964 60 13 74",
    "sg:postcode":"12200",
    "sg:province":"Castell\u00f3n",
    "wof:name":"Transportes Joaquin Aguilella S.l.",
    "wof:placetype":"venue"
},
  "geometry": {"coordinates":[-0.2620640099,39.9651794434],"type":"Point"}
}