{
  "type": "Feature",
  "properties": {
    "iso:country":"ES",
    "sg:address":"Rua Lopez De Neira, 8",
    "sg:city":"Vigo",
    "sg:orig_category":"Asociaciones Y Clubs Deportivos",
    "sg:phone":"+34 986 43 68 39",
    "sg:postcode":"36202",
    "sg:province":"Pontevedra",
    "wof:name":"Mercagol S.l.",
    "wof:placetype":"venue"
},
  "geometry": {"coordinates":[-8.7241067886,42.23695755],"type":"Point"}
}