{
  "type": "Feature",
  "properties": {
    "addr:full":"Calle de Alta, 14 Moriles C\u00f3rdoba 14510",
    "addr:housenumber":"14",
    "addr:postcode":"14510",
    "addr:street":"Calle De Alta",
    "iso:country":"ES",
    "sg:address":"Calle de Alta, 14",
    "sg:city":"Moriles",
    "sg:orig_category":"Asistencia Domiciliaria",
    "sg:phone":"+34 957 53 73 71",
    "sg:postcode":"14510",
    "sg:province":"C\u00f3rdoba",
    "wof:name":"Servicios Sociosanitarios Sociedad Cooperativa Andaluza",
    "wof:placetype":"venue"
},
  "geometry": {"coordinates":[-4.6084651947,37.4366264343],"type":"Point"}
}