{
  "type": "Feature",
  "properties": {
    "addr:full":"Plaz Roma, 2 Valencia Valencia 46018",
    "addr:housenumber":"2",
    "addr:postcode":"46018",
    "addr:street":"Roma",
    "iso:country":"ES",
    "sg:address":"Plaz Roma, 2",
    "sg:city":"Valencia",
    "sg:orig_category":"Molduras, Junquillos, Listones Y Molduras Perforadas",
    "sg:phone":"+34 963 70 07 27",
    "sg:postcode":"46018",
    "sg:province":"Valencia",
    "wof:name":"Lopez Risue\u00f1o Esteban Miguel",
    "wof:placetype":"venue"
},
  "geometry": {"coordinates":[-0.3769130111,39.4687919617],"type":"Point"}
}