{
  "type": "Feature",
  "properties": {
    "addr:full":"Calle de Capitan Ignacio De La Moneda, 9 Baena C\u00f3rdoba 14850",
    "addr:housenumber":"9",
    "addr:postcode":"14850",
    "addr:street":"Calle De Capitan Ignacio De La Moneda",
    "iso:country":"ES",
    "sg:address":"Calle de Capitan Ignacio De La Moneda, 9",
    "sg:city":"Baena",
    "sg:orig_category":"Electricidad: Instaladores",
    "sg:phone":"+34 957 67 06 75",
    "sg:postcode":"14850",
    "sg:province":"C\u00f3rdoba",
    "wof:name":"Alvarez Onieva S.l.",
    "wof:placetype":"venue"
},
  "geometry": {"coordinates":[-4.3210225105,37.6197319031],"type":"Point"}
}