{
  "type": "Feature",
  "properties": {
    "iso:country":"ES",
    "sg:address":"Rua Rosalia De Castro, 70",
    "sg:city":"Pontevedra",
    "sg:orig_category":"Electricidad Veh\u00cdculo",
    "sg:phone":"+34 986 85 08 41",
    "sg:postcode":"36001",
    "sg:province":"Pontevedra",
    "wof:name":"Talleres M.iglesias E Hijos S.l.",
    "wof:placetype":"venue"
},
  "geometry": {"coordinates":[-8.6501293182,42.4265785217],"type":"Point"}
}