{
  "type": "Feature",
  "properties": {
    "iso:country":"ES",
    "sg:address":"Luga Veri\u00d1a De Abajo, S/n",
    "sg:city":"Veri\u00e7a De Abajo",
    "sg:orig_category":"Montaje (empresas De)",
    "sg:phone":"+34 985 30 85 34",
    "sg:postcode":"33691",
    "sg:province":"Asturias",
    "sg:website":"www.montrasa.com",
    "wof:name":"Montrasa Maessa Asturias S.l.",
    "wof:placetype":"venue"
},
  "geometry": {"coordinates":[-5.7485799789,43.5202865601],"type":"Point"}
}