{
  "type": "Feature",
  "properties": {
    "addr:full":"Calle de Antonio Maura, 20 Madrid Madrid 28014",
    "addr:housenumber":"20",
    "addr:postcode":"madrid;28014",
    "addr:street":"Calle De Antonio Maura",
    "iso:country":"ES",
    "sg:address":"Calle de Antonio Maura, 20",
    "sg:city":"Madrid",
    "sg:orig_category":"Bancos",
    "sg:phone":"+34 915 32 62 03",
    "sg:postcode":"28014",
    "sg:province":"Madrid",
    "wof:name":"Deutsche Bank S.a.e.",
    "wof:placetype":"venue"
},
  "geometry": {"coordinates":[-3.6894843578,40.4165878296],"type":"Point"}
}