{
  "type": "Feature",
  "properties": {
    "iso:country":"ES",
    "sg:address":"Calle de Vasco De Gama, 12",
    "sg:city":"Salamanca",
    "sg:orig_category":"Fabricaci\u00d3n De Juguetes Autom\u00c1ticos",
    "sg:phone":"+34 923 25 00 67",
    "sg:postcode":"37004",
    "sg:province":"Salamanca",
    "wof:name":"Gonzalez Hernandez Pablo",
    "wof:placetype":"venue"
},
  "geometry": {"coordinates":[-5.6564540863,40.9719390869],"type":"Point"}
}