{
  "type": "Feature",
  "properties": {
    "iso:country":"ES",
    "sg:address":"Calle de Artekalea, 3",
    "sg:city":"Gernika-lumo",
    "sg:orig_category":"Molduras, Junquillos, Listones Y Molduras Perforadas",
    "sg:phone":"+34 946 25 45 85",
    "sg:postcode":"48300",
    "sg:province":"Vizcaya",
    "wof:name":"Urquidi Imaz Jon",
    "wof:placetype":"venue"
},
  "geometry": {"coordinates":[-2.6782810688,43.3155860901],"type":"Point"}
}