{
  "type": "Feature",
  "properties": {
    "iso:country":"ES",
    "sg:address":"Calle de Fabulista Samaniego, 8",
    "sg:city":"Navaridas",
    "sg:orig_category":"Promotores Constructores",
    "sg:phone":"+34 945 60 51 22",
    "sg:postcode":"01307",
    "sg:province":"\u00c1lava",
    "wof:name":"Construcciones Majuelo Ortiz S.a.",
    "wof:placetype":"venue"
},
  "geometry": {"coordinates":[-2.6686489582,42.5500984192],"type":"Point"}
}