{
  "type": "Feature",
  "properties": {
    "addr:full":"Calle de Alta, 23 Castro Rio C\u00f3rdoba 14840",
    "addr:housenumber":"23",
    "addr:postcode":"14840",
    "addr:street":"Calle De Alta;Rio Co\u0301Rdoba",
    "iso:country":"ES",
    "sg:address":"Calle de Alta, 23",
    "sg:city":"Castro Rio",
    "sg:orig_category":"Cajas Para Embalar",
    "sg:phone":"+34 957 37 01 50",
    "sg:postcode":"14840",
    "sg:province":"C\u00f3rdoba",
    "wof:name":"Caja Rural De Cordoba",
    "wof:placetype":"venue"
},
  "geometry": {"coordinates":[-4.4831814766,37.6909141541],"type":"Point"}
}