{
  "type": "Feature",
  "properties": {
    "iso:country":"ES",
    "sg:address":"Carrer de Havana (l'), 112",
    "sg:city":"Deltebre",
    "sg:orig_category":"Promotores Constructores",
    "sg:phone":"+34 977 48 05 71",
    "sg:postcode":"43580",
    "sg:province":"Tarragona",
    "wof:name":"Miralles Masdeu Leonardo",
    "wof:placetype":"venue"
},
  "geometry": {"coordinates":[0.7323480248,40.7147026062],"type":"Point"}
}