{
  "type": "Feature",
  "properties": {
    "iso:country":"ES",
    "sg:address":"Barr Baular (el), 9",
    "sg:city":"Mimetiz",
    "sg:orig_category":"Escayola Y Productos De Escayola (fabricaci\u00d3n, Al Por Mayor)",
    "sg:phone":"+34 946 39 13 99",
    "sg:postcode":"48860",
    "sg:province":"Vizcaya",
    "wof:name":"Nu\u00f1ez Navarro Jose Antonio",
    "wof:placetype":"venue"
},
  "geometry": {"coordinates":[-3.1296989918,43.2133483887],"type":"Point"}
}