{
  "type": "Feature",
  "properties": {
    "addr:full":"Tafalla, 30 Iru\u00f1a Navarra 31003",
    "addr:housenumber":"30",
    "addr:postcode":"31003",
    "addr:street":"Tafalla",
    "iso:country":"ES",
    "sg:address":"Tafalla, 30",
    "sg:city":"Iru\u00f1a",
    "sg:orig_category":"Prot\u00c9sicos Dentales",
    "sg:phone":"+34 948 23 00 40",
    "sg:postcode":"31003",
    "sg:province":"Navarra",
    "wof:name":"Ezquieta Iturralde Cesar Javier",
    "wof:placetype":"venue"
},
  "geometry": {"coordinates":[-1.6405229568,42.8104171753],"type":"Point"}
}