{
  "type": "Feature",
  "properties": {
    "addr:full":"Carrer de Terol, 19 Barcelona Barcelona 08012",
    "addr:housenumber":"19",
    "addr:postcode":"08012",
    "addr:street":"Carrer De Terol",
    "iso:country":"ES",
    "sg:address":"Carrer de Terol, 19",
    "sg:city":"Barcelona",
    "sg:orig_category":"Muebles, Minoristas",
    "sg:phone":"+34 932 13 62 84",
    "sg:postcode":"08012",
    "sg:province":"Barcelona",
    "wof:name":"Caceres Morella Josep",
    "wof:placetype":"venue"
},
  "geometry": {"coordinates":[2.1577908993,41.4028701782],"type":"Point"}
}