{
  "type": "Feature",
  "properties": {
    "iso:country":"ES",
    "sg:address":"Calle de Sanchez Barcaiztegui, 20",
    "sg:city":"Madrid",
    "sg:orig_category":"Perfumer\u00cda (al Por Menor)",
    "sg:phone":"+34 915 52 92 82",
    "sg:postcode":"28007",
    "sg:province":"Madrid",
    "wof:name":"Eco Madrid S.a.",
    "wof:placetype":"venue"
},
  "geometry": {"coordinates":[-3.6746449471,40.4037666321],"type":"Point"}
}