{
  "type": "Feature",
  "properties": {
    "iso:country":"ES",
    "sg:address":"Calle de Santa Barbara, 2",
    "sg:city":"Monzon",
    "sg:orig_category":"Bancos",
    "sg:phone":"+34 974 41 69 04",
    "sg:postcode":"22400",
    "sg:province":"Huesca",
    "wof:name":"Barclays Bank S.a.e.",
    "wof:placetype":"venue"
},
  "geometry": {"coordinates":[0.1903219968,41.9116516113],"type":"Point"}
}