{
  "type": "Feature",
  "properties": {
    "iso:country":"ES",
    "sg:address":"Ptge Llubi (particular), 9",
    "sg:city":"Palma",
    "sg:orig_category":"Revestimientos Diversos",
    "sg:phone":"+34 971 47 03 13",
    "sg:postcode":"07008",
    "sg:province":"Islas Baleares",
    "wof:name":"Pulimentos Garcia De La Fuente E Hijos S.l",
    "wof:placetype":"venue"
},
  "geometry": {"coordinates":[2.676459074,39.5804252625],"type":"Point"}
}