{
  "type": "Feature",
  "properties": {
    "addr:full":"Calle de Jose Zorrilla, 107 Segovia Segovia 40002",
    "addr:housenumber":"107",
    "addr:postcode":"40002",
    "addr:street":"Calle De Jose Zorrilla",
    "iso:country":"ES",
    "sg:address":"Calle de Jose Zorrilla, 107",
    "sg:city":"Segovia",
    "sg:orig_category":"Colchones (fabricaci\u00d3n, Al Por Mayor, Al Por Menor)",
    "sg:phone":"+34 921 42 23 74",
    "sg:postcode":"40002",
    "sg:province":"Segovia",
    "sg:website":"www.paginasamarillas.es",
    "wof:name":"Hernandez Cuesta Ana",
    "wof:placetype":"venue"
},
  "geometry": {"coordinates":[-4.1141109467,40.9386405945],"type":"Point"}
}