{
  "type": "Feature",
  "properties": {
    "addr:full":"Calle de Avena (de La), 24 Leganes Madrid 28914",
    "addr:housenumber":"24",
    "addr:postcode":"28914",
    "addr:street":"Calle De Avena De La",
    "iso:country":"ES",
    "sg:address":"Calle de Avena (de La), 24",
    "sg:city":"Leganes",
    "sg:orig_category":"Gr\u00daas, Montacargas Y Elevadores Para Astilleros",
    "sg:phone":"+34 916 93 21 12",
    "sg:postcode":"28914",
    "sg:province":"Madrid",
    "wof:name":"Sistemas Forza S.l.",
    "wof:placetype":"venue"
},
  "geometry": {"coordinates":[-3.754668951,40.322303772],"type":"Point"}
}