{
  "type": "Feature",
  "properties": {
    "addr:full":"Carr Enric Granados, 6 Mollerussa Lleida 25230",
    "addr:housenumber":"6",
    "addr:postcode":"25230",
    "addr:street":"Carr Enric Granados",
    "iso:country":"ES",
    "sg:address":"Carr Enric Granados, 6",
    "sg:city":"Mollerussa",
    "sg:orig_category":"Empresas De Portes Y Mensajer\u00cda",
    "sg:phone":"+34 973 60 21 96",
    "sg:postcode":"25230",
    "sg:province":"Lleida",
    "wof:name":"Diaz Marti Andres",
    "wof:placetype":"venue"
},
  "geometry": {"coordinates":[0.8991810083,41.6287918091],"type":"Point"}
}