{
  "type": "Feature",
  "properties": {
    "iso:country":"ES",
    "sg:address":"Rua Principe, 34",
    "sg:city":"Vigo",
    "sg:orig_category":"Arquitectos",
    "sg:phone":"+34 986 22 81 54",
    "sg:postcode":"36202",
    "sg:province":"Pontevedra",
    "wof:name":"Estudio De Arquitectura Zaballa Y Carballas Sl",
    "wof:placetype":"venue"
},
  "geometry": {"coordinates":[-8.7227935791,42.2367248535],"type":"Point"}
}