{
  "type": "Feature",
  "properties": {
    "addr:full":"Ms C. Verdaguer, 1 Sarria Ter Girona 17840",
    "addr:housenumber":"1",
    "addr:postcode":"17840",
    "addr:street":"Verdaguer;Ter",
    "iso:country":"ES",
    "sg:address":"Ms C. Verdaguer, 1",
    "sg:city":"Sarria Ter",
    "sg:orig_category":"Guarder\u00cdas",
    "sg:phone":"+34 972 17 16 07",
    "sg:postcode":"17840",
    "sg:province":"Girona",
    "wof:name":"Ajuntament De Sarria De Ter",
    "wof:placetype":"venue"
},
  "geometry": {"coordinates":[2.6767344475,42.1778182983],"type":"Point"}
}