{
  "type": "Feature",
  "properties": {
    "addr:full":"Avgd Pere Mas I Reus, S/n Platja D'alcudia Islas Baleares 07408",
    "addr:housenumber":"s / n",
    "addr:postcode":"07408",
    "addr:street":"D'Alcudia",
    "iso:country":"ES",
    "sg:address":"Avgd Pere Mas I Reus, S/n",
    "sg:city":"Platja D'alcudia",
    "sg:orig_category":"Peleter\u00cdas",
    "sg:phone":"+34 971 89 11 61",
    "sg:postcode":"07408",
    "sg:province":"Islas Baleares",
    "wof:name":"Artigues Arrom Pedro",
    "wof:placetype":"venue"
},
  "geometry": {"coordinates":[3.1220273972,39.8523139954],"type":"Point"}
}