{
  "type": "Feature",
  "properties": {
    "addr:full":"Zuloagas-tarren Kalea, 1 Eibar Guip\u00f9zcoa 20600",
    "addr:housenumber":"1",
    "addr:postcode":"20600",
    "addr:street":"Zuloagas-Tarren Kalea;Guipu\u0300Zcoa",
    "iso:country":"ES",
    "sg:address":"Zuloagas-tarren Kalea, 1",
    "sg:city":"Eibar",
    "sg:orig_category":"Ropa Para Se\u00d1oras Y Caballeros (al Por Menor)",
    "sg:phone":"+34 943 20 22 33",
    "sg:postcode":"20600",
    "sg:province":"Guip\u00f9zcoa",
    "wof:name":"Valenciaga  Lasuen, C.b.",
    "wof:placetype":"venue"
},
  "geometry": {"coordinates":[-2.4705960751,43.1858024597],"type":"Point"}
}