{
  "type": "Feature",
  "properties": {
    "iso:country":"ES",
    "sg:address":"Avda Libia (de), 29",
    "sg:city":"Cordoba",
    "sg:orig_category":"Distribuci\u00d3n De Petr\u00d3leo Y Derivados",
    "sg:phone":"+34 957 25 60 05",
    "sg:postcode":"14010",
    "sg:province":"C\u00f3rdoba",
    "sg:website":"www.cepsa.es",
    "wof:name":"Estacion De Servicio Ca\u00f1ero S.l.",
    "wof:placetype":"venue"
},
  "geometry": {"coordinates":[-4.7607350349,37.8898468018],"type":"Point"}
}