{
  "type": "Feature",
  "properties": {
    "addr:full":"Calle de Ramon Y Cajal, 56 Rute C\u00f3rdoba 14960",
    "addr:housenumber":"56",
    "addr:postcode":"14960",
    "addr:street":"Calle De Ramon Y Cajal;Co\u0301Rdoba",
    "iso:country":"ES",
    "sg:address":"Calle de Ramon Y Cajal, 56",
    "sg:city":"Rute",
    "sg:classifiers":[
        {
            "category":"Autos & Motor Vehicles",
            "subcategory":"Automobile Sales",
            "type":"Retail Goods"
        }
    ],
    "sg:phone":"+34 957 53 91 01",
    "sg:postcode":"14960",
    "sg:province":"C\u00f3rdoba",
    "wof:name":"Molina Porras Antonio Mateo",
    "wof:placetype":"venue"
},
  "geometry": {"coordinates":[-4.368639946,37.3263473511],"type":"Point"}
}