{
  "type": "Feature",
  "properties": {
    "iso:country":"ES",
    "sg:address":"Pase Castellana, 107",
    "sg:city":"Madrid",
    "sg:orig_category":"Institutos De Belleza",
    "sg:phone":"+34 915 56 13 52",
    "sg:postcode":"28046",
    "sg:province":"Madrid",
    "sg:website":"www.jofer.com",
    "wof:name":"Alfainterbautex S.l.",
    "wof:placetype":"venue"
},
  "geometry": {"coordinates":[-3.6908864975,40.4547691345],"type":"Point"}
}