{
  "type": "Feature",
  "properties": {
    "iso:country":"ES",
    "sg:address":"Avda Talgo, 206",
    "sg:city":"Madrid",
    "sg:orig_category":"Cervecer\u00cdas",
    "sg:phone":"+34 913 07 11 06",
    "sg:postcode":"28023",
    "sg:province":"Madrid",
    "wof:name":"Sociedad Cervecera De Venta Y Consumo S.l.",
    "wof:placetype":"venue"
},
  "geometry": {"coordinates":[-3.7835879326,40.4475860596],"type":"Point"}
}