{
  "type": "Feature",
  "properties": {
    "iso:country":"ES",
    "sg:address":"Barriada De Las Flores, S/n",
    "sg:city":"Coin",
    "sg:orig_category":"Cementerios",
    "sg:phone":"+34 952 45 31 29",
    "sg:postcode":"29100",
    "sg:province":"M\u00e1laga",
    "wof:name":"Ayuntamiento De Coin",
    "wof:placetype":"venue"
},
  "geometry": {"coordinates":[-4.7484517097,36.6660003662],"type":"Point"}
}