{
  "type": "Feature",
  "properties": {
    "iso:country":"ES",
    "sg:address":"Calle de Cortes (las), S/n",
    "sg:city":"San Javier",
    "sg:orig_category":"Armaduras De Hormig\u00d3n",
    "sg:phone":"+34 968 19 14 17",
    "sg:postcode":"30730",
    "sg:province":"Murcia",
    "wof:name":"Estructuras Lopez S.l.",
    "wof:placetype":"venue"
},
  "geometry": {"coordinates":[-0.8331158161,37.8058624268],"type":"Point"}
}