{
  "type": "Feature",
  "properties": {
    "iso:country":"ES",
    "sg:address":"Calle de Constitucion, 77",
    "sg:city":"Langreo",
    "sg:orig_category":"Peluqueros: De Se\u00d1oras",
    "sg:phone":"+34 985 69 82 55",
    "sg:postcode":"33900",
    "sg:province":"Asturias",
    "wof:name":"Tuya Allende Gerardo Y Beatriz C. B.",
    "wof:placetype":"venue"
},
  "geometry": {"coordinates":[-5.6809368134,43.2936286926],"type":"Point"}
}