{
  "type": "Feature",
  "properties": {
    "iso:country":"ES",
    "sg:address":"Ptda La Pedrera, S/n",
    "sg:city":"Albaida",
    "sg:orig_category":"Mensajer\u00cda Express, Portes Internacionales",
    "sg:phone":"+34 962 90 08 09",
    "sg:postcode":"46860",
    "sg:province":"Valencia",
    "sg:website":"www.halcourier.es",
    "wof:name":"Mensalcon S.l.",
    "wof:placetype":"venue"
},
  "geometry": {"coordinates":[-0.5085080266,38.828742981],"type":"Point"}
}