{
  "type": "Feature",
  "properties": {
    "addr:full":"Calle de San Jose, 5 Bisaurri Huesca 22470",
    "addr:housenumber":"5",
    "addr:postcode":"22470",
    "addr:street":"Calle De San Jose",
    "iso:country":"ES",
    "sg:address":"Calle de San Jose, 5",
    "sg:city":"Bisaurri",
    "sg:orig_category":"Cr\u00cda De Animales",
    "sg:phone":"+34 974 55 31 13",
    "sg:postcode":"22470",
    "sg:province":"Huesca",
    "wof:name":"Mora Saura Jose Antonio",
    "wof:placetype":"venue"
},
  "geometry": {"coordinates":[0.5065799952,42.4970932007],"type":"Point"}
}