{
  "type": "Feature",
  "properties": {
    "addr:full":"Calle de Juan Florez, 104 Coru\u00d1a La Coru\u00f1a 15005",
    "addr:housenumber":"104",
    "addr:postcode":"15005",
    "addr:street":"Calle De Juan Florez;Corun\u0303A",
    "iso:country":"ES",
    "sg:address":"Calle de Juan Florez, 104",
    "sg:city":"Coru\u00d1a",
    "sg:orig_category":"Inform\u00c1tica (estudios, Servicios, Asesor\u00cda, Formaci\u00d3n)",
    "sg:phone":"+34 981 27 96 63",
    "sg:postcode":"15005",
    "sg:province":"La Coru\u00f1a",
    "wof:name":"Esposito Dopico Maria Del Pilar",
    "wof:placetype":"venue"
},
  "geometry": {"coordinates":[-8.4080610275,43.3630180359],"type":"Point"}
}