{
  "type": "Feature",
  "properties": {
    "addr:full":"Carrer de Joan Pere Fontanella, 45 Granollers Barcelona 08401",
    "addr:housenumber":"45",
    "addr:postcode":"08401",
    "addr:street":"Carrer De Joan Pere Fontanella",
    "iso:country":"ES",
    "sg:address":"Carrer de Joan Pere Fontanella, 45",
    "sg:city":"Granollers",
    "sg:orig_category":"Lavado, Limpieza De Veh\u00cdculos",
    "sg:phone":"+34 938 79 40 21",
    "sg:postcode":"08401",
    "sg:province":"Barcelona",
    "wof:name":"Arpinet S.s.p.",
    "wof:placetype":"venue"
},
  "geometry": {"coordinates":[2.2832257748,41.605255127],"type":"Point"}
}