{
  "type": "Feature",
  "properties": {
    "iso:country":"ES",
    "sg:address":"Avda Menendez Pelayo, 35",
    "sg:city":"Sevilla",
    "sg:orig_category":"\u00d3ptica: Instrumentos (fabricaci\u00d3n)",
    "sg:phone":"+34 954 42 05 55",
    "sg:postcode":"41003",
    "sg:province":"Sevilla",
    "wof:name":"Union Industrial De Opticas S.a.",
    "wof:placetype":"venue"
},
  "geometry": {"coordinates":[-5.9853987694,37.3869018555],"type":"Point"}
}