{
  "type": "Feature",
  "properties": {
    "addr:full":"Calle de Merineros (los), 18 Soria Soria 42001",
    "addr:housenumber":"18",
    "addr:postcode":"42001",
    "addr:street":"Calle De Merineros Los",
    "iso:country":"ES",
    "sg:address":"Calle de Merineros (los), 18",
    "sg:city":"Soria",
    "sg:orig_category":"Fisioterapia",
    "sg:phone":"+34 975 21 24 76",
    "sg:postcode":"42001",
    "sg:province":"Soria",
    "wof:name":"Garcia Jimenez Maria Teresa",
    "wof:placetype":"venue"
},
  "geometry": {"coordinates":[-2.4745090008,41.7670402527],"type":"Point"}
}