{
  "type": "Feature",
  "properties": {
    "iso:country":"ES",
    "sg:address":"Calle de Cabreros, 58",
    "sg:city":"Rociana Condado",
    "sg:orig_category":"Negocio De Materiales De Construcci\u00d3n",
    "sg:phone":"+34 959 41 71 63",
    "sg:postcode":"21720",
    "sg:province":"Huelva",
    "wof:name":"Rodriguez Padilla David",
    "wof:placetype":"venue"
},
  "geometry": {"coordinates":[-6.5954546928,37.3074684143],"type":"Point"}
}