{
  "type": "Feature",
  "properties": {
    "addr:full":"Ctra. Benasque, 7 Barbastro Huesca 22300",
    "addr:housenumber":"7",
    "addr:postcode":"22300",
    "addr:street":"Ctra. Benasque",
    "iso:country":"ES",
    "sg:address":"Ctra. Benasque, 7",
    "sg:city":"Barbastro",
    "sg:orig_category":"Suministros Para Hoteles",
    "sg:phone":"+34 974 31 24 08",
    "sg:postcode":"22300",
    "sg:province":"Huesca",
    "wof:name":"Comercial Enate S.l.",
    "wof:placetype":"venue"
},
  "geometry": {"coordinates":[0.1309449971,42.0378265381],"type":"Point"}
}