{
  "type": "Feature",
  "properties": {
    "iso:country":"ES",
    "sg:address":"Calle de Abadia De Arbas, S/n",
    "sg:city":"Viadangos De Arbas",
    "sg:orig_category":"Cr\u00cda De Animales",
    "sg:phone":"+34 987 69 80 88",
    "sg:postcode":"24688",
    "sg:province":"Le\u00f3n",
    "wof:name":"Gregorio Tascon C.b.",
    "wof:placetype":"venue"
},
  "geometry": {"coordinates":[-5.5717520714,42.5998764038],"type":"Point"}
}