{
  "type": "Feature",
  "properties": {
    "iso:country":"ES",
    "sg:address":"Avda Martinez De Velasco, 30",
    "sg:city":"Huesca",
    "sg:orig_category":"Peluquer\u00cdas, Peluquer\u00cda Mixta",
    "sg:phone":"+34 974 21 40 87",
    "sg:postcode":"22004",
    "sg:province":"Huesca",
    "wof:name":"Sanagustin Ara Visitacion",
    "wof:placetype":"venue"
},
  "geometry": {"coordinates":[-0.4160580039,42.1332321167],"type":"Point"}
}