{
  "type": "Feature",
  "properties": {
    "addr:full":"Plaz Toros Vieja, 3 Tarazona Zaragoza 50500",
    "addr:housenumber":"3",
    "addr:postcode":"50500",
    "addr:street":"Vieja",
    "iso:country":"ES",
    "sg:address":"Plaz Toros Vieja, 3",
    "sg:city":"Tarazona",
    "sg:orig_category":"M\u00c9dicos: Medicina General Orientada A La Homeopat\u00cda",
    "sg:phone":"+34 976 64 26 55",
    "sg:postcode":"50500",
    "sg:province":"Zaragoza",
    "wof:name":"Ciordia Garcia Maria Luisa",
    "wof:placetype":"venue"
},
  "geometry": {"coordinates":[-1.722843051,41.9045448303],"type":"Point"}
}