{
  "type": "Feature",
  "properties": {
    "iso:country":"ES",
    "sg:address":"Carrer de Alarcon, 31",
    "sg:city":"Barcelona",
    "sg:orig_category":"Mec\u00c1nico Del Autom\u00d3vil",
    "sg:phone":"+34 934 29 27 58",
    "sg:postcode":"08035",
    "sg:province":"Barcelona",
    "wof:name":"Barcelo Coronado Luis",
    "wof:placetype":"venue"
},
  "geometry": {"coordinates":[2.1527869701,41.4273872375],"type":"Point"}
}