{
  "type": "Feature",
  "properties": {
    "iso:country":"ES",
    "sg:address":"Calle de Juan Vazquez Rengifo, 1",
    "sg:city":"Velez-malaga",
    "sg:orig_category":"Alimentaci\u00d3n General (al Por Menor)",
    "sg:phone":"+34 952 50 69 63",
    "sg:postcode":"29700",
    "sg:province":"M\u00e1laga",
    "wof:name":"Santiago Perez Maria Del Carmen",
    "wof:placetype":"venue"
},
  "geometry": {"coordinates":[-4.1004362106,36.7783088684],"type":"Point"}
}