{
  "type": "Feature",
  "properties": {
    "addr:full":"Calle de Mencey Bencomo, 37 Santa Cruz De Tenerife Santa Cruz De Tenerife 38008",
    "addr:housenumber":"37",
    "addr:postcode":"38008",
    "addr:street":"Calle De Mencey Bencomo",
    "iso:country":"ES",
    "sg:address":"Calle de Mencey Bencomo, 37",
    "sg:city":"Santa Cruz De Tenerife",
    "sg:orig_category":"Centros P\u00dablicos De Formaci\u00d3n Profesional Y T\u00c9cnica",
    "sg:phone":"+34 922 23 21 20",
    "sg:postcode":"38008",
    "sg:province":"Santa Cruz De Tenerife",
    "wof:name":"Colegio Tinerfe\u00f1o De Arbitros De Futbol",
    "wof:placetype":"venue"
},
  "geometry": {"coordinates":[-16.2727279663,28.4698181152],"type":"Point"}
}