{
  "type": "Feature",
  "properties": {
    "addr:full":"Jose Luis I\u00d1arra Pasealekua, 32 Arrasate Guip\u00f9zcoa 20500",
    "addr:housenumber":"32",
    "addr:postcode":"20500",
    "addr:street":"Jose;In\u0303Arra Pasealekua;Guipu\u0300Zcoa",
    "iso:country":"ES",
    "sg:address":"Jose Luis I\u00d1arra Pasealekua, 32",
    "sg:city":"Arrasate",
    "sg:orig_category":"Asociaciones Y Clubs Deportivos",
    "sg:phone":"+34 943 79 97 02",
    "sg:postcode":"20500",
    "sg:province":"Guip\u00f9zcoa",
    "wof:name":"Club De Ajedrez San Andres De Arrasate",
    "wof:placetype":"venue"
},
  "geometry": {"coordinates":[-2.4872460365,43.0684890747],"type":"Point"}
}