{
  "type": "Feature",
  "properties": {
    "iso:country":"ES",
    "sg:address":"Plaza Del Castro, 6",
    "sg:city":"Padron",
    "sg:orig_category":"Sociedades, Compa\u00d1\u00cdas Aseguradoras",
    "sg:phone":"+34 981 81 08 00",
    "sg:postcode":"15900",
    "sg:province":"La Coru\u00f1a",
    "wof:name":"Correduria De Seguros Mendez S.l.",
    "wof:placetype":"venue"
},
  "geometry": {"coordinates":[-8.6602935791,42.7379112244],"type":"Point"}
}