{
  "type": "Feature",
  "properties": {
    "addr:full":"Avda Aragon De, 134 Fraga Huesca 22520",
    "addr:housenumber":"134",
    "addr:postcode":"22520",
    "addr:street":"Avda Aragon De",
    "iso:country":"ES",
    "sg:address":"Avda Aragon De, 134",
    "sg:city":"Fraga",
    "sg:orig_category":"Reposter\u00cdas",
    "sg:phone":"+34 974 47 04 91",
    "sg:postcode":"22520",
    "sg:province":"Huesca",
    "wof:name":"Lax Rodriguez Esther",
    "wof:placetype":"venue"
},
  "geometry": {"coordinates":[0.3337970078,41.52003479],"type":"Point"}
}