{
  "type": "Feature",
  "properties": {
    "iso:country":"ES",
    "sg:address":"Avgd Blasco Iba\u00d1ez, 23",
    "sg:city":"Paterna",
    "sg:orig_category":"Enfermeras: Consultas, Atenci\u00d3n A Domicilio",
    "sg:phone":"+34 961 38 32 68",
    "sg:postcode":"46980",
    "sg:province":"Valencia",
    "wof:name":"Benlloch Araix Amparo",
    "wof:placetype":"venue"
},
  "geometry": {"coordinates":[-0.4373269975,39.4991989136],"type":"Point"}
}