{
  "type": "Feature",
  "properties": {
    "addr:full":"G.v. Lopez De Haro D. Diego, 42 Bilbao Vizcaya 48011",
    "addr:housenumber":"42",
    "addr:postcode":"48011",
    "addr:street":"Lopez De Haro D. Diego",
    "iso:country":"ES",
    "sg:address":"G.v. Lopez De Haro D. Diego, 42",
    "sg:city":"Bilbao",
    "sg:orig_category":"Inversiones",
    "sg:phone":"+34 944 23 08 86",
    "sg:postcode":"48011",
    "sg:province":"Vizcaya",
    "sg:website":"www.indosuez.es",
    "wof:name":"Indosuez Norte S.a.",
    "wof:placetype":"venue"
},
  "geometry": {"coordinates":[-2.9366340637,43.2634925842],"type":"Point"}
}