{
  "type": "Feature",
  "properties": {
    "iso:country":"ES",
    "sg:address":"Calle de Don Ramon Menendez Pidal, 5",
    "sg:city":"Madrid",
    "sg:orig_category":"Ense\u00d1anza Superior Privada",
    "sg:phone":"+34 915 33 59 54",
    "sg:postcode":"28040",
    "sg:province":"Madrid",
    "wof:name":"St Lawrence University",
    "wof:placetype":"venue"
},
  "geometry": {"coordinates":[-3.728276968,40.4476890564],"type":"Point"}
}