{
  "type": "Feature",
  "properties": {
    "iso:country":"ES",
    "sg:address":"Carrer de Muntaner, 371",
    "sg:city":"Barcelona",
    "sg:orig_category":"M\u00c9dicos: Psiquiatr\u00cda",
    "sg:phone":"+34 932 00 00 90",
    "sg:postcode":"08021",
    "sg:province":"Barcelona",
    "wof:name":"Martinez Pina Angel",
    "wof:placetype":"venue"
},
  "geometry": {"coordinates":[2.1430199146,41.3989143372],"type":"Point"}
}