{
  "type": "Feature",
  "properties": {
    "addr:full":"Calle de Don Casto Martin, 2 Ventas Con Pe\u00e7a Aguilera Toledo 45127",
    "addr:housenumber":"2",
    "addr:postcode":"45127",
    "addr:street":"Calle De Don Casto Martin",
    "iso:country":"ES",
    "sg:address":"Calle de Don Casto Martin, 2",
    "sg:city":"Ventas Con Pe\u00e7a Aguilera",
    "sg:orig_category":"Iglesia Cat\u00d3lica",
    "sg:phone":"+34 925 41 81 80",
    "sg:postcode":"45127",
    "sg:province":"Toledo",
    "wof:name":"Parroquia De San Pedro Apostol",
    "wof:placetype":"venue"
},
  "geometry": {"coordinates":[-4.2271547318,39.613658905],"type":"Point"}
}