{
  "type": "Feature",
  "properties": {
    "addr:full":"Pla\u00c7 Orient, 1 Inca Islas Baleares 07300",
    "addr:postcode":"07300",
    "iso:country":"ES",
    "sg:address":"Pla\u00c7 Orient, 1",
    "sg:city":"Inca",
    "sg:orig_category":"Importaci\u00d3n, Exportaci\u00d3n Y Comercios De Productos Textiles",
    "sg:phone":"+34 971 50 16 38",
    "sg:postcode":"07300",
    "sg:province":"Islas Baleares",
    "wof:name":"Ramis Martinez Juan",
    "wof:placetype":"venue"
},
  "geometry": {"coordinates":[2.9091899395,39.7197418213],"type":"Point"}
}