{
  "type": "Feature",
  "properties": {
    "iso:country":"ES",
    "sg:address":"Calle de Sofia, 205",
    "sg:city":"Madrid",
    "sg:orig_category":"Asociaciones Y Clubs Deportivos",
    "sg:phone":"+34 917 60 03 80",
    "sg:postcode":"28022",
    "sg:province":"Madrid",
    "wof:name":"Fun Fit S.l.",
    "wof:placetype":"venue"
},
  "geometry": {"coordinates":[-3.6017019749,40.429069519],"type":"Point"}
}