{
  "type": "Feature",
  "properties": {
    "iso:country":"ES",
    "sg:address":"Ctra. Logro\u00f1o-vitoria, S/n",
    "sg:city":"Buradon Gatzaga",
    "sg:orig_category":"Distribuci\u00d3n De Petr\u00d3leo Y Derivados",
    "sg:phone":"+34 945 33 72 29",
    "sg:postcode":"01339",
    "sg:province":"\u00c1lava",
    "wof:name":"Santamaria Guenaga Fernando",
    "wof:placetype":"venue"
},
  "geometry": {"coordinates":[-2.831099987,42.63463974],"type":"Point"}
}