{
  "type": "Feature",
  "properties": {
    "addr:full":"Calle de Rosario, 2 Fortuna Murcia 30620",
    "addr:housenumber":"2",
    "addr:postcode":"30620",
    "addr:street":"Calle De Rosario",
    "iso:country":"ES",
    "sg:address":"Calle de Rosario, 2",
    "sg:city":"Fortuna",
    "sg:orig_category":"Farmacias",
    "sg:phone":"+34 968 68 50 48",
    "sg:postcode":"30620",
    "sg:province":"Murcia",
    "wof:name":"Sanchez Garcia Gines",
    "wof:placetype":"venue"
},
  "geometry": {"coordinates":[-1.122913003,38.1796531677],"type":"Point"}
}