{
  "type": "Feature",
  "properties": {
    "iso:country":"ES",
    "sg:address":"Calle de Manuel Lekuona, 11",
    "sg:city":"Donostia-san Sebastian",
    "sg:orig_category":"Centros Empresariales",
    "sg:phone":"+34 943 31 61 20",
    "sg:postcode":"20018",
    "sg:province":"Guip\u00f9zcoa",
    "wof:name":"Meditest S.l.",
    "wof:placetype":"venue"
},
  "geometry": {"coordinates":[-2.0075850487,43.3092803955],"type":"Point"}
}