{
  "type": "Feature",
  "properties": {
    "iso:country":"ES",
    "sg:address":"Bromo (p I Calonge), 22",
    "sg:city":"Sevilla",
    "sg:orig_category":"Ropa Para Beb\u00c9s Y Ni\u00d1os (confecci\u00d3n, Al Por Mayor)",
    "sg:phone":"+34 954 43 53 53",
    "sg:postcode":"41007",
    "sg:province":"Sevilla",
    "wof:name":"Garcia Montaner Jose Maria",
    "wof:placetype":"venue"
},
  "geometry": {"coordinates":[-5.9540910721,37.4096260071],"type":"Point"}
}