{
  "type": "Feature",
  "properties": {
    "addr:full":"Calle de Juslibol, 6 Zaragoza Zaragoza 50015",
    "addr:housenumber":"6",
    "addr:postcode":"50015",
    "addr:street":"Calle De Juslibol",
    "iso:country":"ES",
    "sg:address":"Calle de Juslibol, 6",
    "sg:city":"Zaragoza",
    "sg:orig_category":"Venta, Instalaci\u00d3n De Calefacci\u00d3n",
    "sg:phone":"+34 976 73 67 35",
    "sg:postcode":"50015",
    "sg:province":"Zaragoza",
    "wof:name":"Gracia Roy Jose Maria",
    "wof:placetype":"venue"
},
  "geometry": {"coordinates":[-0.8719779849,41.6705474854],"type":"Point"}
}