{
  "type": "Feature",
  "properties": {
    "addr:full":"Avda Mediterraneo, 4 Vitoria-gasteiz \u00c1lava 01010",
    "addr:housenumber":"4",
    "addr:postcode":"01010",
    "addr:street":"Avda Mediterraneo",
    "iso:country":"ES",
    "sg:address":"Avda Mediterraneo, 4",
    "sg:city":"Vitoria-gasteiz",
    "sg:orig_category":"Electricidad: Instaladores",
    "sg:phone":"+34 945 24 01 38",
    "sg:postcode":"01010",
    "sg:province":"\u00c1lava",
    "wof:name":"Retelet Montajes Elelctricos S.l.",
    "wof:placetype":"venue"
},
  "geometry": {"coordinates":[-2.6939098835,42.8468780518],"type":"Point"}
}