{
  "type": "Feature",
  "properties": {
    "addr:full":"Calle de Union, 35 Malaga M\u00e1laga 29006",
    "addr:housenumber":"35",
    "addr:postcode":"29006",
    "addr:street":"Calle De;Malaga Ma\u0301Laga",
    "iso:country":"ES",
    "sg:address":"Calle de Union, 35",
    "sg:city":"Malaga",
    "sg:orig_category":"Asilos De Ancianos. Centros Privados",
    "sg:phone":"+34 952 33 63 03",
    "sg:postcode":"29006",
    "sg:province":"M\u00e1laga",
    "wof:name":"Asociacion De Pensionistas Y Jubilados Antonio Martelo Seneca",
    "wof:placetype":"venue"
},
  "geometry": {"coordinates":[-4.4380125999,36.7111854553],"type":"Point"}
}