{
  "type": "Feature",
  "properties": {
    "addr:full":"Calle de Laguna, 39 Coru\u00d1a La Coru\u00f1a 15009",
    "addr:housenumber":"39",
    "addr:postcode":"15009",
    "addr:street":"Calle De Laguna;Corun\u0303A",
    "iso:country":"ES",
    "sg:address":"Calle de Laguna, 39",
    "sg:city":"Coru\u00d1a",
    "sg:orig_category":"Mercer\u00cda, Lencer\u00cda (al Por Menor)",
    "sg:phone":"+34 981 28 80 69",
    "sg:postcode":"15009",
    "sg:province":"La Coru\u00f1a",
    "wof:name":"Penas Novoa Manuel",
    "wof:placetype":"venue"
},
  "geometry": {"coordinates":[-8.3966293335,43.3512306213],"type":"Point"}
}