{
  "type": "Feature",
  "properties": {
    "iso:country":"ES",
    "sg:address":"Avda Constitucion, 51",
    "sg:city":"Onil",
    "sg:orig_category":"Agencias Y Agentes Comerciales, Representantes",
    "sg:phone":"+34 965 56 47 07",
    "sg:postcode":"03430",
    "sg:province":"Alicante",
    "wof:name":"Garcia Molina Mario",
    "wof:placetype":"venue"
},
  "geometry": {"coordinates":[-0.6732379794,38.6301765442],"type":"Point"}
}