{
  "type": "Feature",
  "properties": {
    "iso:country":"ES",
    "sg:address":"Av Riells, 30",
    "sg:city":"Escala",
    "sg:orig_category":"Muebles, Minoristas",
    "sg:phone":"+34 972 77 31 91",
    "sg:postcode":"17130",
    "sg:province":"Girona",
    "wof:name":"Escala Mobel C.b.",
    "wof:placetype":"venue"
},
  "geometry": {"coordinates":[3.1335110664,42.1169128418],"type":"Point"}
}