{
  "type": "Feature",
  "properties": {
    "addr:full":"Av Madrid, 46 Barcelona Barcelona 08028",
    "addr:housenumber":"46",
    "addr:postcode":"08028",
    "addr:street":"Av Madrid",
    "iso:country":"ES",
    "sg:address":"Av Madrid, 46",
    "sg:city":"Barcelona",
    "sg:orig_category":"Estilistas Y Estudios De Estilo De Corte Y Confecci\u00d3n",
    "sg:phone":"+34 934 90 72 33",
    "sg:postcode":"08028",
    "sg:province":"Barcelona",
    "wof:name":"Garcia Fenero Joaquin",
    "wof:placetype":"venue"
},
  "geometry": {"coordinates":[2.1254138947,41.3772087097],"type":"Point"}
}