{
  "type": "Feature",
  "properties": {
    "addr:full":"Calle de Ramona Martin 'artista', S/n Cristianos Santa Cruz De Tenerife 38650",
    "addr:housenumber":"s / n",
    "addr:postcode":"38650",
    "addr:street":"Calle De Ramona Martin ' Artista '",
    "iso:country":"ES",
    "sg:address":"Calle de Ramona Martin 'artista', S/n",
    "sg:city":"Cristianos",
    "sg:orig_category":"Cl\u00cdnicas Dentales",
    "sg:phone":"+34 922 75 07 99",
    "sg:postcode":"38650",
    "sg:province":"Santa Cruz De Tenerife",
    "wof:name":"Pracean S.l",
    "wof:placetype":"venue"
},
  "geometry": {"coordinates":[-16.2584075928,28.4695129395],"type":"Point"}
}