{
  "type": "Feature",
  "properties": {
    "iso:country":"ES",
    "sg:address":"Avda Diputacion, 101",
    "sg:city":"Algeciras",
    "sg:orig_category":"Molduras, Junquillos, Listones Y Molduras Perforadas",
    "sg:phone":"+34 956 66 02 84",
    "sg:postcode":"11205",
    "sg:province":"C\u00e1diz",
    "wof:name":"Mata Juarez Fernando",
    "wof:placetype":"venue"
},
  "geometry": {"coordinates":[-5.4453730583,36.1574859619],"type":"Point"}
}