{
  "type": "Feature",
  "properties": {
    "iso:country":"ES",
    "sg:address":"Calle de Asuncion, 63",
    "sg:city":"Molina Segura",
    "sg:orig_category":"Abogados",
    "sg:phone":"+34 968 64 27 31",
    "sg:postcode":"30500",
    "sg:province":"Murcia",
    "wof:name":"Zambudio Ortiz Jesus",
    "wof:placetype":"venue"
},
  "geometry": {"coordinates":[-1.2117960453,38.0557060242],"type":"Point"}
}