{
  "type": "Feature",
  "properties": {
    "iso:country":"ES",
    "sg:address":"Calle de Verge De La Mar, 17",
    "sg:city":"Pinedo",
    "sg:orig_category":"Consultas M\u00c9dicas",
    "sg:phone":"+34 963 24 87 49",
    "sg:postcode":"46012",
    "sg:province":"Valencia",
    "wof:name":"Peris Planells Inmaculada",
    "wof:placetype":"venue"
},
  "geometry": {"coordinates":[-0.2913190126,39.3012657166],"type":"Point"}
}