{
  "type": "Feature",
  "properties": {
    "iso:country":"ES",
    "sg:address":"Carrer de Onofre Jaume, 14",
    "sg:city":"Palma",
    "sg:orig_category":"Escayola Y Productos De Escayola (fabricaci\u00d3n, Al Por Mayor)",
    "sg:phone":"+34 971 24 15 55",
    "sg:postcode":"07008",
    "sg:province":"Islas Baleares",
    "wof:name":"Prolitmar 2002 S.l.",
    "wof:placetype":"venue"
},
  "geometry": {"coordinates":[2.670871973,39.5815582275],"type":"Point"}
}