{
  "type": "Feature",
  "properties": {
    "iso:country":"ES",
    "sg:address":"Pl Vila De Madrid, 3",
    "sg:city":"Barcelona",
    "sg:orig_category":"Bisuter\u00cda, Joyer\u00cda, Relojer\u00cda (al Por Menor)",
    "sg:phone":"+34 933 18 08 90",
    "sg:postcode":"08002",
    "sg:province":"Barcelona",
    "wof:name":"Colper S.l.",
    "wof:placetype":"venue"
},
  "geometry": {"coordinates":[2.1726529598,41.3844642639],"type":"Point"}
}