{
  "type": "Feature",
  "properties": {
    "addr:full":"Calle de Fraga, 62 Velilla Cinca Huesca 22528",
    "addr:housenumber":"62",
    "addr:postcode":"22528",
    "addr:street":"Calle De Fraga",
    "iso:country":"ES",
    "sg:address":"Calle de Fraga, 62",
    "sg:city":"Velilla Cinca",
    "sg:orig_category":"Cajas Para Embalar",
    "sg:phone":"+34 974 46 13 14",
    "sg:postcode":"22528",
    "sg:province":"Huesca",
    "wof:name":"Caja Rural Aragonesa Y De Los Pirineos",
    "wof:placetype":"venue"
},
  "geometry": {"coordinates":[0.2609930038,41.5856895447],"type":"Point"}
}