{
  "type": "Feature",
  "properties": {
    "addr:full":"Calle de Lope De Vega, 7 Getxo Vizcaya 48930",
    "addr:housenumber":"7",
    "addr:postcode":"48930",
    "addr:street":"Calle De Lope De Vega",
    "iso:country":"ES",
    "sg:address":"Calle de Lope De Vega, 7",
    "sg:city":"Getxo",
    "sg:orig_category":"Peluqueros: De Se\u00d1oras",
    "sg:phone":"+34 944 64 53 97",
    "sg:postcode":"48930",
    "sg:province":"Vizcaya",
    "wof:name":"Angeles Atela Uriguen",
    "wof:placetype":"venue"
},
  "geometry": {"coordinates":[-3.0084240437,43.3289642334],"type":"Point"}
}