{
  "type": "Feature",
  "properties": {
    "addr:full":"Casadelas, 20 Noicela La Coru\u00f1a 15105",
    "addr:housenumber":"20",
    "addr:postcode":"15105",
    "addr:street":"Casadelas;La Corun\u0303A",
    "iso:country":"ES",
    "sg:address":"Casadelas, 20",
    "sg:city":"Noicela",
    "sg:orig_category":"Molduras, Junquillos, Listones Y Molduras Perforadas",
    "sg:phone":"+34 981 73 95 21",
    "sg:postcode":"15105",
    "sg:province":"La Coru\u00f1a",
    "wof:name":"Castro Regueria Maria Elisa",
    "wof:placetype":"venue"
},
  "geometry": {"coordinates":[-8.605348587,43.3203735352],"type":"Point"}
}