{
  "type": "Feature",
  "properties": {
    "iso:country":"ES",
    "sg:address":"Carrer de Joan Torras, 8",
    "sg:city":"Barcelona",
    "sg:orig_category":"Muebles, Minoristas",
    "sg:phone":"+34 933 46 93 13",
    "sg:postcode":"08030",
    "sg:province":"Barcelona",
    "wof:name":"Muebles Chip S.cv.",
    "wof:placetype":"venue"
},
  "geometry": {"coordinates":[2.1902461052,41.4375686646],"type":"Point"}
}