{
  "type": "Feature",
  "properties": {
    "addr:full":"Calle de Cervantes, 49 Cheste Valencia 46380",
    "addr:housenumber":"49",
    "addr:postcode":"46380",
    "addr:street":"Calle De Cervantes",
    "iso:country":"ES",
    "sg:address":"Calle de Cervantes, 49",
    "sg:city":"Cheste",
    "sg:orig_category":"Promotores Constructores",
    "sg:phone":"+34 962 51 26 97",
    "sg:postcode":"46380",
    "sg:province":"Valencia",
    "wof:name":"Crumacon S.l.",
    "wof:placetype":"venue"
},
  "geometry": {"coordinates":[-0.6877881289,39.4922904968],"type":"Point"}
}