{
  "type": "Feature",
  "properties": {
    "iso:country":"ES",
    "sg:address":"Cmno Torres (las), 99",
    "sg:city":"Zaragoza",
    "sg:orig_category":"Centros M\u00c9dicos Y Sociales, Dispensarios",
    "sg:phone":"+34 976 25 54 11",
    "sg:postcode":"50007",
    "sg:province":"Zaragoza",
    "wof:name":"Castellote Laborda Piedad",
    "wof:placetype":"venue"
},
  "geometry": {"coordinates":[-0.8848209977,41.6403388977],"type":"Point"}
}