{
  "type": "Feature",
  "properties": {
    "addr:full":"Carrer de Ferran, 34 Barcelona Barcelona 08...",
    "addr:housenumber":"34",
    "addr:street":"Carrer De Ferran",
    "iso:country":"ES",
    "sg:address":"Carrer de Ferran, 34",
    "sg:city":"Barcelona",
    "sg:orig_category":"Alimentaci\u00d3n General (al Por Menor)",
    "sg:phone":"+34 934 02 77 30",
    "sg:postcode":"08...",
    "sg:province":"Barcelona",
    "wof:name":"Ajuntament De Barcelona",
    "wof:placetype":"venue"
},
  "geometry": {"coordinates":[2.176060915,41.3818283081],"type":"Point"}
}