{
  "type": "Feature",
  "properties": {
    "addr:full":"Calle de Xaudaro, 13 Madrid Madrid 28034",
    "addr:housenumber":"13",
    "addr:postcode":"madrid;28034",
    "addr:street":"Calle De Xaudaro",
    "iso:country":"ES",
    "sg:address":"Calle de Xaudaro, 13",
    "sg:city":"Madrid",
    "sg:orig_category":"Venta, Instalaci\u00d3n De Calefacci\u00d3n",
    "sg:phone":"+34 917 28 04 60",
    "sg:postcode":"28034",
    "sg:province":"Madrid",
    "wof:name":"Snell Servicios Globales S.a.",
    "wof:placetype":"venue"
},
  "geometry": {"coordinates":[-3.6911530495,40.4893264771],"type":"Point"}
}