{
  "type": "Feature",
  "properties": {
    "iso:country":"ES",
    "sg:address":"Pg Saladar, 35",
    "sg:city":"Denia",
    "sg:orig_category":"Inmobiliaria (agencias)",
    "sg:phone":"+34 966 42 43 46",
    "sg:postcode":"03700",
    "sg:province":"Alicante",
    "wof:name":"Bernabeu Terol Jorge",
    "wof:placetype":"venue"
},
  "geometry": {"coordinates":[0.1071129963,38.8375740051],"type":"Point"}
}