{
  "type": "Feature",
  "properties": {
    "addr:full":"Calle de Lagasca, 61 Madrid Madrid 28001",
    "addr:housenumber":"61",
    "addr:postcode":"madrid;28001",
    "addr:street":"Calle De Lagasca",
    "iso:country":"ES",
    "sg:address":"Calle de Lagasca, 61",
    "sg:city":"Madrid",
    "sg:orig_category":"Ropa Para Beb\u00c9s Y Ni\u00d1os (confecci\u00d3n, Al Por Mayor)",
    "sg:phone":"+34 914 35 64 68",
    "sg:postcode":"28001",
    "sg:province":"Madrid",
    "sg:website":"www.laocaloca.com",
    "wof:name":"Suarez Gonzalez-mayo Miriam",
    "wof:placetype":"venue"
},
  "geometry": {"coordinates":[-3.6850605011,40.428188324],"type":"Point"}
}