{
  "type": "Feature",
  "properties": {
    "addr:full":"Calle de Bolta\u00d1a, 12 Barbastro Huesca 22300",
    "addr:housenumber":"12",
    "addr:postcode":"22300",
    "addr:street":"Calle De Boltan\u0303A",
    "iso:country":"ES",
    "sg:address":"Calle de Bolta\u00d1a, 12",
    "sg:city":"Barbastro",
    "sg:orig_category":"Venta, Instalaci\u00d3n, Mantenimiento De Chimeneas De Interior Y Accesorios",
    "sg:phone":"+34 974 31 32 32",
    "sg:postcode":"22300",
    "sg:province":"Huesca",
    "wof:name":"Marmoles Mata S.l.",
    "wof:placetype":"venue"
},
  "geometry": {"coordinates":[0.1329745948,42.0414047241],"type":"Point"}
}