{
  "type": "Feature",
  "properties": {
    "iso:country":"ES",
    "sg:address":"Calle de Mayor, 35",
    "sg:city":"Santiba\u00e7ez De Vidriales",
    "sg:orig_category":"Estancos",
    "sg:phone":"+34 980 64 83 00",
    "sg:postcode":"49610",
    "sg:province":"Zamora",
    "wof:name":"Martinez Blanco Lucia",
    "wof:placetype":"venue"
},
  "geometry": {"coordinates":[-6.0140490532,42.0751304626],"type":"Point"}
}