{
  "type": "Feature",
  "properties": {
    "addr:full":"Calle de Lavadero De La Cruz, 2 Granada Granada 18001",
    "addr:housenumber":"2",
    "addr:postcode":"18001",
    "addr:street":"Calle De Lavadero De La Cruz",
    "iso:country":"ES",
    "sg:address":"Calle de Lavadero De La Cruz, 2",
    "sg:city":"Granada",
    "sg:orig_category":"Tapiceros Y Tapiceros",
    "sg:phone":"+34 958 28 06 51",
    "sg:postcode":"18001",
    "sg:province":"Granada",
    "wof:name":"Fornell Sanchez Dionisio",
    "wof:placetype":"venue"
},
  "geometry": {"coordinates":[-3.6013450623,37.1807403564],"type":"Point"}
}