{
  "type": "Feature",
  "properties": {
    "iso:country":"ES",
    "sg:address":"Calle de Dionisio Guardiola, 4",
    "sg:city":"Albacete",
    "sg:orig_category":"Ropa Para Se\u00d1oras (al Por Menor)",
    "sg:phone":"+34 967 52 37 30",
    "sg:postcode":"02002",
    "sg:province":"Albacete",
    "wof:name":"Gonzalez Quevedo Paloma",
    "wof:placetype":"venue"
},
  "geometry": {"coordinates":[-1.8547971249,38.991191864],"type":"Point"}
}