{
  "type": "Feature",
  "properties": {
    "addr:full":"Calle de Lopez Del Vallado, 8 Oviedo Asturias 33010",
    "addr:housenumber":"8",
    "addr:postcode":"33010",
    "addr:street":"Calle De Lopez Del Vallado",
    "iso:country":"ES",
    "sg:address":"Calle de Lopez Del Vallado, 8",
    "sg:city":"Oviedo",
    "sg:orig_category":"Zapatos (al Por Menor)",
    "sg:phone":"+34 985 22 09 42",
    "sg:postcode":"33010",
    "sg:province":"Asturias",
    "wof:name":"Velazquez Calzon Maria Cruz",
    "wof:placetype":"venue"
},
  "geometry": {"coordinates":[-5.8335399628,43.3632774353],"type":"Point"}
}