{
  "type": "Feature",
  "properties": {
    "iso:country":"ES",
    "sg:address":"Calle de Saturnino Lopez Novoa, 4",
    "sg:city":"Huesca",
    "sg:classifiers":[
        {
            "category":"Personal",
            "subcategory":"Barber",
            "type":"Services"
        }
    ],
    "sg:phone":"+34 974 22 79 33",
    "sg:postcode":"22005",
    "sg:province":"Huesca",
    "sg:tags":[
        "caballeros",
        "de",
        "peluqueros"
    ],
    "wof:name":"Martin Lopez Sebastian",
    "wof:placetype":"venue"
},
  "geometry": {"coordinates":[-0.4078229964,42.1323318481],"type":"Point"}
}