{
  "type": "Feature",
  "properties": {
    "iso:country":"ES",
    "sg:address":"Calle de Brianda De Olivera, 11",
    "sg:city":"Le\u00f3n",
    "sg:orig_category":"Psic\u00d3logos",
    "sg:phone":"+34 987 20 60 90",
    "sg:postcode":"24005",
    "sg:province":"Le\u00f3n",
    "wof:name":"Pedrazuela Gonzalez Alicia",
    "wof:placetype":"venue"
},
  "geometry": {"coordinates":[-5.5676031113,42.5883255005],"type":"Point"}
}