{
  "type": "Feature",
  "properties": {
    "iso:country":"ES",
    "sg:address":"Calle de Porto Lagos, 11",
    "sg:city":"Alcorcon",
    "sg:orig_category":"Abogados",
    "sg:phone":"+34 916 10 60 69",
    "sg:postcode":"28924",
    "sg:province":"Madrid",
    "wof:name":"Rodriguez Garcia Juan Luis",
    "wof:placetype":"venue"
},
  "geometry": {"coordinates":[-3.8185989857,40.3484916687],"type":"Point"}
}