{
  "type": "Feature",
  "properties": {
    "addr:full":"Plaz Manuel Hernandez Tejina, 1 Tejina Santa Cruz De Tenerife 38260",
    "addr:housenumber":"1",
    "addr:postcode":"38260",
    "addr:street":"Manuel Hernandez Tejina",
    "iso:country":"ES",
    "sg:address":"Plaz Manuel Hernandez Tejina, 1",
    "sg:city":"Tejina",
    "sg:orig_category":"Centros M\u00c9dicos Y Sociales, Dispensarios",
    "sg:phone":"+34 922 54 32 59",
    "sg:postcode":"38260",
    "sg:province":"Santa Cruz De Tenerife",
    "wof:name":"Wadi S.l.",
    "wof:placetype":"venue"
},
  "geometry": {"coordinates":[-16.3589172363,28.533788681],"type":"Point"}
}