{
  "type": "Feature",
  "properties": {
    "iso:country":"ES",
    "sg:address":"Calle de Agustina De Aragon, 51",
    "sg:city":"Valencia",
    "sg:orig_category":"Reparaci\u00d3n, Mantenimiento De Instrumentos Y Accesorios De M\u00dasica",
    "sg:phone":"+34 963 77 06 47",
    "sg:postcode":"46017",
    "sg:province":"Valencia",
    "sg:website":"www.codsc.com/obrac",
    "wof:name":"Carbo Romero Salvador",
    "wof:placetype":"venue"
},
  "geometry": {"coordinates":[-0.3878990114,39.4546813965],"type":"Point"}
}