{
  "type": "Feature",
  "properties": {
    "addr:full":"Calle de Nicolas Sanchez, 103 Madrid Madrid 28026",
    "addr:housenumber":"103",
    "addr:postcode":"28026",
    "addr:street":"Calle De Nicolas Sanchez",
    "iso:country":"ES",
    "sg:address":"Calle de Nicolas Sanchez, 103",
    "sg:city":"Madrid",
    "sg:orig_category":"Zapatos: Material, Suministros, Accesorios (fabricaci\u00d3n, Al Por Mayor)",
    "sg:phone":"+34 914 75 48 78",
    "sg:postcode":"28026",
    "sg:province":"Madrid",
    "wof:name":"Robledo Hermanos Y Compa\u00f1ia S. L.",
    "wof:placetype":"venue"
},
  "geometry": {"coordinates":[-3.7054131031,40.3817214966],"type":"Point"}
}