{
  "type": "Feature",
  "properties": {
    "iso:country":"ES",
    "sg:address":"Pase Duque De Mandas, 35",
    "sg:city":"Donostia-san Sebastian",
    "sg:orig_category":"Abogados",
    "sg:phone":"+34 943 32 72 58",
    "sg:postcode":"20012",
    "sg:province":"Guip\u00f9zcoa",
    "wof:name":"Zaldua Azurmendi Carlos",
    "wof:placetype":"venue"
},
  "geometry": {"coordinates":[-1.9746290445,43.3177452087],"type":"Point"}
}