{
  "type": "Feature",
  "properties": {
    "addr:full":"Calle de San Fernando, 14 Quintanar Orden Toledo 45800",
    "addr:housenumber":"14",
    "addr:postcode":"45800",
    "addr:street":"Calle De San Fernando",
    "iso:country":"ES",
    "sg:address":"Calle de San Fernando, 14",
    "sg:city":"Quintanar Orden",
    "sg:orig_category":"Fisioterapia",
    "sg:phone":"+34 925 18 21 25",
    "sg:postcode":"45800",
    "sg:province":"Toledo",
    "wof:name":"Rodriguez Flores Jose",
    "wof:placetype":"venue"
},
  "geometry": {"coordinates":[-3.0446300507,39.5926208496],"type":"Point"}
}