{
  "type": "Feature",
  "properties": {
    "addr:full":"Carr Mendizabal, 119 Burjassot Valencia 46100",
    "addr:housenumber":"119",
    "addr:postcode":"46100",
    "addr:street":"Carr Mendizabal",
    "iso:country":"ES",
    "sg:address":"Carr Mendizabal, 119",
    "sg:city":"Burjassot",
    "sg:orig_category":"Telas Y Sedas (al Por Menor)",
    "sg:phone":"+34 963 63 96 75",
    "sg:postcode":"46100",
    "sg:province":"Valencia",
    "wof:name":"Anton Almenar Vicente",
    "wof:placetype":"venue"
},
  "geometry": {"coordinates":[-0.4166730046,39.5136528015],"type":"Point"}
}