{
  "type": "Feature",
  "properties": {
    "iso:country":"ES",
    "sg:address":"Calle de Clara Del Rey, 47",
    "sg:city":"Madrid",
    "sg:orig_category":"Distribuci\u00d3n De Petr\u00d3leo Y Derivados",
    "sg:phone":"+34 915 19 44 48",
    "sg:postcode":"28002",
    "sg:province":"Madrid",
    "sg:website":"www.cepsa.es",
    "wof:name":"Poste Clara Del Rey S.l.",
    "wof:placetype":"venue"
},
  "geometry": {"coordinates":[-3.6687705517,40.4437141418],"type":"Point"}
}