{
  "type": "Feature",
  "properties": {
    "addr:full":"Avda Andalucia (de), 79 Padul Granada 18640",
    "addr:housenumber":"79",
    "addr:postcode":"18640",
    "addr:street":"Avda Andalucia De",
    "iso:country":"ES",
    "sg:address":"Avda Andalucia (de), 79",
    "sg:city":"Padul",
    "sg:orig_category":"Bancos",
    "sg:phone":"+34 958 79 01 05",
    "sg:postcode":"18640",
    "sg:province":"Granada",
    "wof:name":"Caja Rural De Granada",
    "wof:placetype":"venue"
},
  "geometry": {"coordinates":[-3.6262180805,37.0228118896],"type":"Point"}
}