{
  "type": "Feature",
  "properties": {
    "addr:full":"Calle de Santiago, 2 Padron La Coru\u00f1a 15900",
    "addr:housenumber":"2",
    "addr:postcode":"15900",
    "addr:street":"Calle De Santiago;Padron La Corun\u0303A",
    "iso:country":"ES",
    "sg:address":"Calle de Santiago, 2",
    "sg:city":"Padron",
    "sg:orig_category":"Comercio, Reparaci\u00d3n De Bicicletas, De Motocicletas, De Accesorios",
    "sg:phone":"+34 981 81 01 52",
    "sg:postcode":"15900",
    "sg:province":"La Coru\u00f1a",
    "wof:name":"Casa Grobas S. A.",
    "wof:placetype":"venue"
},
  "geometry": {"coordinates":[-8.6624803543,42.7390518188],"type":"Point"}
}