{
  "type": "Feature",
  "properties": {
    "addr:full":"Rbla Rambla Nova, 106 Tarragona Tarragona 43001",
    "addr:housenumber":"106",
    "addr:postcode":"43001",
    "addr:street":"Rambla Nova",
    "iso:country":"ES",
    "sg:address":"Rbla Rambla Nova, 106",
    "sg:city":"Tarragona",
    "sg:orig_category":"Doctores En Medicina",
    "sg:phone":"+34 977 21 22 03",
    "sg:postcode":"43001",
    "sg:province":"Tarragona",
    "wof:name":"Ribe Perez De Burgos Luis",
    "wof:placetype":"venue"
},
  "geometry": {"coordinates":[1.2541049719,41.1169281006],"type":"Point"}
}