{
  "type": "Feature",
  "properties": {
    "iso:country":"ES",
    "sg:address":"Estda. Centro(manzos), S/n",
    "sg:city":"Louredo",
    "sg:orig_category":"Ense\u00d1anza, Formaci\u00d3n Profesional: Aprendizaje",
    "sg:phone":"+34 988 26 59 45",
    "sg:postcode":"32577",
    "sg:province":"Ourense",
    "wof:name":"Ayuntamiento De Maside",
    "wof:placetype":"venue"
},
  "geometry": {"coordinates":[-8.0051307678,42.4068374634],"type":"Point"}
}