{
  "type": "Feature",
  "properties": {
    "iso:country":"ES",
    "sg:address":"Ciud R.-valdepe\u00f1as, Km. 0200,5",
    "sg:city":"Pozuelo Calatrava",
    "sg:orig_category":"Fabricaci\u00d3n De Mobiliario De Oficina",
    "sg:phone":"+34 926 84 01 28",
    "sg:postcode":"13179",
    "sg:province":"Ciudad Real",
    "wof:name":"Manufacturas Chacon Sanchez S.l.",
    "wof:placetype":"venue"
},
  "geometry": {"coordinates":[-3.9272627831,38.9860954285],"type":"Point"}
}