{
  "type": "Feature",
  "properties": {
    "addr:full":"Avda Aguirre Lehendakari, 165 Bilbao Vizcaya 48015",
    "addr:housenumber":"165",
    "addr:postcode":"48015",
    "addr:street":"Avda Aguirre Lehendakari",
    "iso:country":"ES",
    "sg:address":"Avda Aguirre Lehendakari, 165",
    "sg:city":"Bilbao",
    "sg:orig_category":"Laboratorios Y Cl\u00cdnicas Veterinarias",
    "sg:phone":"+34 944 05 87 64",
    "sg:postcode":"48015",
    "sg:province":"Vizcaya",
    "wof:name":"Jose Javier Mediavilla Alonso",
    "wof:placetype":"venue"
},
  "geometry": {"coordinates":[-2.9619829655,43.2796478271],"type":"Point"}
}