{
  "type": "Feature",
  "properties": {
    "iso:country":"ES",
    "sg:address":"Laias, 32",
    "sg:city":"Laias",
    "sg:orig_category":"Centros Empresariales",
    "sg:phone":"+34 988 40 00 78",
    "sg:postcode":"32459",
    "sg:province":"Ourense",
    "wof:name":"Vazquez Velo Jose Manuel",
    "wof:placetype":"venue"
},
  "geometry": {"coordinates":[-8.0925722122,42.2746047974],"type":"Point"}
}