{
  "type": "Feature",
  "properties": {
    "addr:full":"Carrer de Narcis Fors, 9 Lloret Mar Girona 17310",
    "addr:housenumber":"9",
    "addr:postcode":"17310",
    "addr:street":"Carrer De Narcis Fors",
    "iso:country":"ES",
    "sg:address":"Carrer de Narcis Fors, 9",
    "sg:city":"Lloret Mar",
    "sg:orig_category":"Complementos De Vestir (al Por Menor)",
    "sg:phone":"+34 972 36 59 18",
    "sg:postcode":"17310",
    "sg:province":"Girona",
    "wof:name":"Clemente Soliba Esther",
    "wof:placetype":"venue"
},
  "geometry": {"coordinates":[2.8482398987,41.7024688721],"type":"Point"}
}