{
  "type": "Feature",
  "properties": {
    "iso:country":"ES",
    "sg:address":"Carr Alfred Pere\u00d1a, 56",
    "sg:city":"Lleida",
    "sg:orig_category":"Centros M\u00c9dicos Y Sociales, Dispensarios",
    "sg:phone":"+34 973 23 68 46",
    "sg:postcode":"25004",
    "sg:province":"Lleida",
    "sg:website":"www.ccmprevencion.com",
    "wof:name":"Central De Control Medico S.l.",
    "wof:placetype":"venue"
},
  "geometry": {"coordinates":[0.6243939996,41.6222763062],"type":"Point"}
}