{
  "type": "Feature",
  "properties": {
    "iso:country":"ES",
    "sg:address":"Rond San Francisco (de), S/n",
    "sg:city":"Lucena",
    "sg:orig_category":"Panader\u00cdas, Panader\u00cdas",
    "sg:phone":"+34 957 50 04 91",
    "sg:postcode":"14900",
    "sg:province":"C\u00f3rdoba",
    "wof:name":"Impaluc S.l.",
    "wof:placetype":"venue"
},
  "geometry": {"coordinates":[-4.4873490334,37.4135398865],"type":"Point"}
}