{
  "type": "Feature",
  "properties": {
    "addr:full":"Calle de Torre Isunza, S/n Almendralejo Badajoz 06200",
    "addr:housenumber":"s / n",
    "addr:postcode":"06200",
    "addr:street":"Calle De Torre Isunza",
    "iso:country":"ES",
    "sg:address":"Calle de Torre Isunza, S/n",
    "sg:city":"Almendralejo",
    "sg:orig_category":"Transportes Por Carretera: Lotes Completos, Mercanc\u00cdas Diversas",
    "sg:phone":"+34 924 66 62 74",
    "sg:postcode":"06200",
    "sg:province":"Badajoz",
    "wof:name":"Cruz Y Halcon S.l.",
    "wof:placetype":"venue"
},
  "geometry": {"coordinates":[-6.4068241119,38.6845092773],"type":"Point"}
}