{
  "type": "Feature",
  "properties": {
    "iso:country":"ES",
    "sg:address":"Calle de San Mariano, 109",
    "sg:city":"Madrid",
    "sg:orig_category":"Fabricaci\u00d3n, Venta, Instalaci\u00d3n De R\u00d3tulos, De R\u00d3tulos Luminosos",
    "sg:phone":"+34 917 42 70 54",
    "sg:postcode":"28022",
    "sg:province":"Madrid",
    "wof:name":"Yaneluz S.l.",
    "wof:placetype":"venue"
},
  "geometry": {"coordinates":[-3.6088147163,40.4361076355],"type":"Point"}
}