{
  "type": "Feature",
  "properties": {
    "addr:full":"Calle de Mencey Bentenuya, S/n Santa Cruz De Tenerife Santa Cruz De Tenerife 38008",
    "addr:housenumber":"s / n",
    "addr:postcode":"38008",
    "addr:street":"Calle De Mencey Bentenuya",
    "iso:country":"ES",
    "sg:address":"Calle de Mencey Bentenuya, S/n",
    "sg:city":"Santa Cruz De Tenerife",
    "sg:orig_category":"Iglesia Cat\u00d3lica",
    "sg:phone":"+34 922 20 00 25",
    "sg:postcode":"38008",
    "sg:province":"Santa Cruz De Tenerife",
    "wof:name":"Parroquia San Gerardo",
    "wof:placetype":"venue"
},
  "geometry": {"coordinates":[-16.2736225128,28.4712142944],"type":"Point"}
}