{
  "type": "Feature",
  "properties": {
    "iso:country":"ES",
    "sg:address":"Calle de Bravo, 1",
    "sg:city":"Medina Campo",
    "sg:orig_category":"Bancos",
    "sg:phone":"+34 983 81 27 21",
    "sg:postcode":"47400",
    "sg:province":"Valladolid",
    "wof:name":"Banco Caixa Geral S.a.",
    "wof:placetype":"venue"
},
  "geometry": {"coordinates":[-4.9156289101,41.3065681458],"type":"Point"}
}