{
  "type": "Feature",
  "properties": {
    "addr:full":"Calle de Pastora, 5 Alzira Valencia 46600",
    "addr:housenumber":"5",
    "addr:postcode":"46600",
    "addr:street":"Calle De Pastora",
    "iso:country":"ES",
    "sg:address":"Calle de Pastora, 5",
    "sg:city":"Alzira",
    "sg:orig_category":"Centros Empresariales",
    "sg:phone":"+34 962 41 54 82",
    "sg:postcode":"46600",
    "sg:province":"Valencia",
    "wof:name":"Ferrer Ballester Sergio",
    "wof:placetype":"venue"
},
  "geometry": {"coordinates":[-0.4361200035,39.1514778137],"type":"Point"}
}