{
  "type": "Feature",
  "properties": {
    "iso:country":"ES",
    "sg:address":"Calle de San Pascual, 92",
    "sg:city":"Yecla",
    "sg:orig_category":"Fabricaci\u00d3n De Muebles",
    "sg:phone":"+34 968 75 19 32",
    "sg:postcode":"30510",
    "sg:province":"Murcia",
    "wof:name":"Dama Dise\u00f1o S.l.",
    "wof:placetype":"venue"
},
  "geometry": {"coordinates":[-1.1110169888,38.6129684448],"type":"Point"}
}