{
  "type": "Feature",
  "properties": {
    "addr:full":"Carretera, S/n Estrada Lugo 27146",
    "addr:housenumber":"s / n",
    "addr:postcode":"27146",
    "addr:street":"Carretera;Estrada Lugo",
    "iso:country":"ES",
    "sg:address":"Carretera, S/n",
    "sg:city":"Estrada",
    "sg:orig_category":"Arenas, Guijarros Y Granulados",
    "sg:phone":"+34 982 15 02 86",
    "sg:postcode":"27146",
    "sg:province":"Lugo",
    "wof:name":"Condesmo S.a.",
    "wof:placetype":"venue"
},
  "geometry": {"coordinates":[-7.4751148224,43.0153236389],"type":"Point"}
}