{
  "type": "Feature",
  "properties": {
    "iso:country":"ES",
    "sg:address":"Plaz Pepe Ubis, 8",
    "sg:city":"Vitoria-gasteiz",
    "sg:orig_category":"Molduras, Junquillos, Listones Y Molduras Perforadas",
    "sg:phone":"+34 945 28 10 99",
    "sg:postcode":"01003",
    "sg:province":"\u00c1lava",
    "wof:name":"Rosa Veronica Vera Santana",
    "wof:placetype":"venue"
},
  "geometry": {"coordinates":[-2.6593139172,42.8474349976],"type":"Point"}
}