{
  "type": "Feature",
  "properties": {
    "iso:country":"ES",
    "sg:address":"Calle de Victoria, 17",
    "sg:city":"Olvera",
    "sg:orig_category":"Ense\u00d1anza: Profesiones Art\u00cdsticas",
    "sg:phone":"+34 956 13 06 55",
    "sg:postcode":"11690",
    "sg:province":"C\u00e1diz",
    "wof:name":"Maqueda Porra Gabriel",
    "wof:placetype":"venue"
},
  "geometry": {"coordinates":[-5.2633461952,36.9348258972],"type":"Point"}
}