{
  "type": "Feature",
  "properties": {
    "addr:full":"Calle de Sevilla, 39 Jerez De La Frontera C\u00e1diz 11402",
    "addr:housenumber":"39",
    "addr:postcode":"11402",
    "addr:street":"Calle De Sevilla",
    "iso:country":"ES",
    "sg:address":"Calle de Sevilla, 39",
    "sg:city":"Jerez De La Frontera",
    "sg:orig_category":"Agentes Generales De Seguros",
    "sg:phone":"+34 956 32 25 52",
    "sg:postcode":"11402",
    "sg:province":"C\u00e1diz",
    "wof:name":"Mingorance Paez Adelaida",
    "wof:placetype":"venue"
},
  "geometry": {"coordinates":[-6.136578083,36.6899108887],"type":"Point"}
}