{
  "type": "Feature",
  "properties": {
    "addr:full":"Calle de Jara, 18 Cartagena Murcia 30201",
    "addr:housenumber":"18",
    "addr:postcode":"30201",
    "addr:street":"Calle De Jara",
    "iso:country":"ES",
    "sg:address":"Calle de Jara, 18",
    "sg:city":"Cartagena",
    "sg:orig_category":"Asesor\u00cda Fiscal Y Jur\u00cddica",
    "sg:phone":"+34 968 12 29 67",
    "sg:postcode":"30201",
    "sg:province":"Murcia",
    "wof:name":"Aldea Asesores S.l.",
    "wof:placetype":"venue"
},
  "geometry": {"coordinates":[-0.9860736728,37.6015930176],"type":"Point"}
}