{
  "type": "Feature",
  "properties": {
    "addr:full":"Calle de Mancha (la), 17 Pto. Rosario Las Palmas 35600",
    "addr:housenumber":"17",
    "addr:postcode":"35600",
    "addr:street":"Calle De Mancha La;Pto. Rosario Las",
    "iso:country":"ES",
    "sg:address":"Calle de Mancha (la), 17",
    "sg:city":"Pto. Rosario",
    "sg:orig_category":"Asociaciones, Organismos Culturales Y Socioeducativos",
    "sg:phone":"+34 928 85 83 95",
    "sg:postcode":"35600",
    "sg:province":"Las Palmas",
    "wof:name":"Asociacion Fuerteventura Contra El Cancer",
    "wof:placetype":"venue"
},
  "geometry": {"coordinates":[-13.8655948639,28.4984226227],"type":"Point"}
}