{
  "type": "Feature",
  "properties": {
    "iso:country":"ES",
    "sg:address":"Calle de Juan Aparicio, 6",
    "sg:city":"Don Benito",
    "sg:orig_category":"Artes Gr\u00c1ficas, Artes Pl\u00c1sticas (curso)",
    "sg:phone":"+34 924 80 02 31",
    "sg:postcode":"06400",
    "sg:province":"Badajoz",
    "wof:name":"Graficas Sanchez Trejo S.l.",
    "wof:placetype":"venue"
},
  "geometry": {"coordinates":[-5.8640789986,38.9562911987],"type":"Point"}
}