{
  "type": "Feature",
  "properties": {
    "addr:full":"Rond Zamenhof, 75 Sabadell Barcelona 08201",
    "addr:housenumber":"75",
    "addr:postcode":"08201",
    "addr:street":"Zamenhof",
    "iso:country":"ES",
    "sg:address":"Rond Zamenhof, 75",
    "sg:city":"Sabadell",
    "sg:orig_category":"Abogados",
    "sg:phone":"+34 937 27 73 95",
    "sg:postcode":"08201",
    "sg:province":"Barcelona",
    "wof:name":"Soriano Rodriguez Manuel",
    "wof:placetype":"venue"
},
  "geometry": {"coordinates":[2.1028299332,41.5512008667],"type":"Point"}
}