{
  "type": "Feature",
  "properties": {
    "iso:country":"ES",
    "sg:address":"Calle de Sierra De Albarracin (de La), 3",
    "sg:city":"Poligono De San Fernando De Henares",
    "sg:orig_category":"Mec\u00c1nico Del Autom\u00d3vil",
    "sg:phone":"+34 916 56 71 16",
    "sg:postcode":"28830",
    "sg:province":"Madrid",
    "wof:name":"Meca Rodriguez Carlos Antonio",
    "wof:placetype":"venue"
},
  "geometry": {"coordinates":[-3.5092658997,40.4506416321],"type":"Point"}
}