{
  "type": "Feature",
  "properties": {
    "iso:country":"ES",
    "sg:address":"Ctra Lleida, 9",
    "sg:city":"Ponts",
    "sg:orig_category":"Peluquer\u00cdas, Peluquer\u00cda Mixta",
    "sg:phone":"+34 973 46 21 04",
    "sg:postcode":"25740",
    "sg:province":"Lleida",
    "wof:name":"Vilella Sole Roser",
    "wof:placetype":"venue"
},
  "geometry": {"coordinates":[1.1844700575,41.9152526855],"type":"Point"}
}