{
  "type": "Feature",
  "properties": {
    "addr:full":"Calle de Virgen De Consolacion, 23 Utrera Sevilla 41710",
    "addr:housenumber":"23",
    "addr:postcode":"41710",
    "addr:street":"Calle De Virgen De Consolacion",
    "iso:country":"ES",
    "sg:address":"Calle de Virgen De Consolacion, 23",
    "sg:city":"Utrera",
    "sg:orig_category":"Zapatos (al Por Menor)",
    "sg:phone":"+34 954 86 01 67",
    "sg:postcode":"41710",
    "sg:province":"Sevilla",
    "wof:name":"Ruiz Carrion Consuelo",
    "wof:placetype":"venue"
},
  "geometry": {"coordinates":[-5.7791371346,37.1823997498],"type":"Point"}
}