{
  "type": "Feature",
  "properties": {
    "iso:country":"ES",
    "sg:address":"Carrer de Padilla, 378",
    "sg:city":"Barcelona",
    "sg:orig_category":"Farmacias",
    "sg:phone":"+34 934 55 82 45",
    "sg:postcode":"08025",
    "sg:province":"Barcelona",
    "wof:name":"Labarta Marques Xavier",
    "wof:placetype":"venue"
},
  "geometry": {"coordinates":[2.1693298817,41.411857605],"type":"Point"}
}