{
  "type": "Feature",
  "properties": {
    "iso:country":"ES",
    "sg:address":"Calle de Sargentos Provisionales, 56",
    "sg:city":"Lanzahita",
    "sg:orig_category":"Molduras, Junquillos, Listones Y Molduras Perforadas",
    "sg:phone":"+34 920 37 87 83",
    "sg:postcode":"05490",
    "sg:province":"\u00c1vila",
    "wof:name":"Alonso Hernandez Jose",
    "wof:placetype":"venue"
},
  "geometry": {"coordinates":[-4.9342727661,40.2056312561],"type":"Point"}
}