{
  "type": "Feature",
  "properties": {
    "iso:country":"ES",
    "sg:address":"Calle de Independencia, 14",
    "sg:city":"Valladolid",
    "sg:orig_category":"Centros P\u00dablicos De Formaci\u00d3n Profesional Y T\u00c9cnica",
    "sg:phone":"+34 983 39 12 76",
    "sg:postcode":"47004",
    "sg:province":"Valladolid",
    "wof:name":"Colegio Oficial De Graduados Sociales De Madrid",
    "wof:placetype":"venue"
},
  "geometry": {"coordinates":[-4.7241988182,41.6446723938],"type":"Point"}
}