{
  "type": "Feature",
  "properties": {
    "addr:full":"Rbla Nostra Senyora, 17 Vilafranca Penedes Barcelona 08720",
    "addr:housenumber":"17",
    "addr:postcode":"08720",
    "addr:street":"Rbla Nostra Senyora;Penedes Barcelona",
    "iso:country":"ES",
    "sg:address":"Rbla Nostra Senyora, 17",
    "sg:city":"Vilafranca Penedes",
    "sg:orig_category":"Asesor\u00cda Fiscal Y Jur\u00cddica",
    "sg:phone":"+34 938 90 41 11",
    "sg:postcode":"08720",
    "sg:province":"Barcelona",
    "wof:name":"Asesoria Comptages S.l.",
    "wof:placetype":"venue"
},
  "geometry": {"coordinates":[1.7007316351,41.3455543518],"type":"Point"}
}