{
  "type": "Feature",
  "properties": {
    "addr:full":"Pg Zona Franca, 165 Barcelona Barcelona 08038",
    "addr:housenumber":"165",
    "addr:postcode":"08038",
    "addr:street":"Pg Zona Franca",
    "iso:country":"ES",
    "sg:address":"Pg Zona Franca, 165",
    "sg:city":"Barcelona",
    "sg:orig_category":"Discapacitados",
    "sg:phone":"+34 933 31 20 93",
    "sg:postcode":"08038",
    "sg:province":"Barcelona",
    "wof:name":"Asproseat",
    "wof:placetype":"venue"
},
  "geometry": {"coordinates":[2.1388969421,41.3601760864],"type":"Point"}
}