{
  "type": "Feature",
  "properties": {
    "iso:country":"ES",
    "sg:address":"Calle de General Ricardos, 25",
    "sg:city":"Madrid",
    "sg:orig_category":"Servicios Gsm",
    "sg:phone":"+34 914 28 09 90",
    "sg:postcode":"28019",
    "sg:province":"Madrid",
    "sg:website":"carstore.es",
    "wof:name":"Car Store S.l.",
    "wof:placetype":"venue"
},
  "geometry": {"coordinates":[-3.7185809612,40.3961410522],"type":"Point"}
}