{
  "type": "Feature",
  "properties": {
    "addr:full":"Calle de Gonzalez Abarca, 8 Aviles Asturias 33401",
    "addr:housenumber":"8",
    "addr:postcode":"33401",
    "addr:street":"Calle De Gonzalez Abarca",
    "iso:country":"ES",
    "sg:address":"Calle de Gonzalez Abarca, 8",
    "sg:city":"Aviles",
    "sg:orig_category":"Inmobiliaria (agencias)",
    "sg:phone":"+34 985 52 03 92",
    "sg:postcode":"33401",
    "sg:province":"Asturias",
    "sg:website":"www.mrbit.es/nuevaera",
    "wof:name":"Intermediadiacion Inmobiliaria Sabugo S.l.",
    "wof:placetype":"venue"
},
  "geometry": {"coordinates":[-5.9252638817,43.5590209961],"type":"Point"}
}