{
  "type": "Feature",
  "properties": {
    "iso:country":"ES",
    "sg:address":"Calle de General Espartero, 147",
    "sg:city":"Alacant",
    "sg:orig_category":"Peluqueros: De Se\u00d1oras",
    "sg:phone":"+34 965 24 65 58",
    "sg:postcode":"03014",
    "sg:province":"Alicante",
    "wof:name":"Perez Valdonedo Valeriana",
    "wof:placetype":"venue"
},
  "geometry": {"coordinates":[-0.4832839966,38.3667259216],"type":"Point"}
}