{
  "type": "Feature",
  "properties": {
    "addr:full":"Calle de Francisco Silvela, 47 Madrid Madrid 28028",
    "addr:housenumber":"47",
    "addr:postcode":"madrid;28028",
    "addr:street":"Calle De Francisco Silvela",
    "iso:country":"ES",
    "sg:address":"Calle de Francisco Silvela, 47",
    "sg:city":"Madrid",
    "sg:orig_category":"Agencias De Trabajo Temporal",
    "sg:phone":"+34 914 44 85 40",
    "sg:postcode":"28028",
    "sg:province":"Madrid",
    "sg:website":"www.adecco.es",
    "wof:name":"Adecco E.t.t. S.a.",
    "wof:placetype":"venue"
},
  "geometry": {"coordinates":[-3.6730885506,40.4329681396],"type":"Point"}
}