{
  "type": "Feature",
  "properties": {
    "iso:country":"ES",
    "sg:address":"A Ponte, S/n",
    "sg:city":"Ledesma",
    "sg:orig_category":"Electrodom\u00c9sticos (al Por Menor)",
    "sg:phone":"+34 981 51 40 13",
    "sg:postcode":"15882",
    "sg:province":"La Coru\u00f1a",
    "wof:name":"Barcala Mosquera Perfecto",
    "wof:placetype":"venue"
},
  "geometry": {"coordinates":[-8.3638143539,42.8032646179],"type":"Point"}
}