{
  "type": "Feature",
  "properties": {
    "addr:full":"Avda Espa\u00d1a, 39 Cedeira La Coru\u00f1a 15350",
    "addr:housenumber":"39",
    "addr:postcode":"15350",
    "addr:street":"Avda Espan\u0303A;La Corun\u0303A",
    "iso:country":"ES",
    "sg:address":"Avda Espa\u00d1a, 39",
    "sg:city":"Cedeira",
    "sg:orig_category":"Navegaci\u00d3n (equipos Fluviales)",
    "sg:phone":"+34 981 48 08 14",
    "sg:postcode":"15350",
    "sg:province":"La Coru\u00f1a",
    "wof:name":"Ricardo Villar Arrivi Y Maria Graciela Martinez Martinez C.b.",
    "wof:placetype":"venue"
},
  "geometry": {"coordinates":[-8.0515298843,43.659702301],"type":"Point"}
}