{
  "type": "Feature",
  "properties": {
    "iso:country":"ES",
    "sg:address":"El Monte, 78",
    "sg:city":"Ba\u00f1ugues",
    "sg:orig_category":"Ingenier\u00cda, Centros De Estudios (diversos)",
    "sg:phone":"+34 985 88 30 65",
    "sg:postcode":"33448",
    "sg:province":"Asturias",
    "wof:name":"Curuxona S.l.u",
    "wof:placetype":"venue"
},
  "geometry": {"coordinates":[-5.8596291542,43.6257591248],"type":"Point"}
}