{
  "type": "Feature",
  "properties": {
    "iso:country":"ES",
    "sg:address":"Calle de Florida, S/n",
    "sg:city":"Puebla Sanabria",
    "sg:orig_category":"Reposter\u00cdas",
    "sg:phone":"+34 980 62 01 05",
    "sg:postcode":"49300",
    "sg:province":"Zamora",
    "wof:name":"Rodriguez Boyano Manuel",
    "wof:placetype":"venue"
},
  "geometry": {"coordinates":[-6.634665966,42.0544586182],"type":"Point"}
}