{
  "type": "Feature",
  "properties": {
    "addr:full":"Avda Oscar Espla, 25 Alacant Alicante 03007",
    "addr:housenumber":"25",
    "addr:postcode":"03007",
    "addr:street":"Avda Oscar Espla",
    "iso:country":"ES",
    "sg:address":"Avda Oscar Espla, 25",
    "sg:city":"Alacant",
    "sg:orig_category":"Mutuas De Seguros",
    "sg:phone":"+34 965 98 44 95",
    "sg:postcode":"03007",
    "sg:province":"Alicante",
    "wof:name":"Mutua Universal Mugenat Matepss N 10",
    "wof:placetype":"venue"
},
  "geometry": {"coordinates":[-0.4944080114,38.3415870667],"type":"Point"}
}