{
  "type": "Feature",
  "properties": {
    "addr:full":"Kale Nagusia, 40 Beasain Guip\u00f9zcoa 20200",
    "addr:housenumber":"40",
    "addr:postcode":"20200",
    "addr:street":"Kale Nagusia;Guipu\u0300Zcoa",
    "iso:country":"ES",
    "sg:address":"Kale Nagusia, 40",
    "sg:city":"Beasain",
    "sg:orig_category":"Hielo Artificial (fabricaci\u00d3n, Distribuci\u00d3n)",
    "sg:phone":"+34 943 88 39 02",
    "sg:postcode":"20200",
    "sg:province":"Guip\u00f9zcoa",
    "wof:name":"Iba\u00f1ez Iba\u00f1ez Fernando",
    "wof:placetype":"venue"
},
  "geometry": {"coordinates":[-2.1787092686,43.0540428162],"type":"Point"}
}