{
  "type": "Feature",
  "properties": {
    "addr:full":"Calle de Fuertes Acevedo, 90 Oviedo Asturias 33006",
    "addr:housenumber":"90",
    "addr:postcode":"33006",
    "addr:street":"Calle De Fuertes Acevedo",
    "iso:country":"ES",
    "sg:address":"Calle de Fuertes Acevedo, 90",
    "sg:city":"Oviedo",
    "sg:orig_category":"Loter\u00cda Y T\u00d3mbola",
    "sg:phone":"+34 985 23 16 56",
    "sg:postcode":"33006",
    "sg:province":"Asturias",
    "wof:name":"Garzo Alvarado Gemma",
    "wof:placetype":"venue"
},
  "geometry": {"coordinates":[-5.869849205,43.3581809998],"type":"Point"}
}