{
  "type": "Feature",
  "properties": {
    "iso:country":"ES",
    "sg:address":"Calle de Infante Don Juan Manuel, 14",
    "sg:city":"Yecla",
    "sg:orig_category":"Peluquer\u00cdas, Peluquer\u00cda Mixta",
    "sg:phone":"+34 968 75 39 35",
    "sg:postcode":"30510",
    "sg:province":"Murcia",
    "wof:name":"Alonso Ortega Adoracion",
    "wof:placetype":"venue"
},
  "geometry": {"coordinates":[-1.1095963717,38.6047897339],"type":"Point"}
}