{
  "type": "Feature",
  "properties": {
    "iso:country":"ES",
    "sg:address":"Pl. Espa\u00f1a, 12",
    "sg:city":"Torremenga",
    "sg:orig_category":"Administraciones Regionales, Departamentales Y Locales",
    "sg:phone":"+34 927 46 03 35",
    "sg:postcode":"10413",
    "sg:province":"C\u00e1ceres",
    "wof:name":"Ayuntamiento De Torremenga",
    "wof:placetype":"venue"
},
  "geometry": {"coordinates":[-5.7751779556,40.046962738],"type":"Point"}
}