{
  "type": "Feature",
  "properties": {
    "addr:full":"Carrer de Cobalt, 119 Hospitalet Llobregat Barcelona 08907",
    "addr:housenumber":"119",
    "addr:postcode":"08907",
    "addr:street":"Carrer De Cobalt",
    "iso:country":"ES",
    "sg:address":"Carrer de Cobalt, 119",
    "sg:city":"Hospitalet Llobregat",
    "sg:orig_category":"Aluminio Y Aleaciones (producci\u00d3n, Transformaci\u00d3n, Negocio)",
    "sg:phone":"+34 933 37 93 12",
    "sg:postcode":"08907",
    "sg:province":"Barcelona",
    "sg:website":"www.alumafel.es",
    "wof:name":"Alumafel S. A.",
    "wof:placetype":"venue"
},
  "geometry": {"coordinates":[2.1055672169,41.3570480347],"type":"Point"}
}