{
  "type": "Feature",
  "properties": {
    "addr:full":"Calle de Salamanca, 38 Valencia Valencia 46005",
    "addr:housenumber":"38",
    "addr:postcode":"46005",
    "addr:street":"Calle De Salamanca",
    "iso:country":"ES",
    "sg:address":"Calle de Salamanca, 38",
    "sg:city":"Valencia",
    "sg:orig_category":"Asilos De Ancianos. Centros Privados",
    "sg:phone":"+34 963 73 87 99",
    "sg:postcode":"46005",
    "sg:province":"Valencia",
    "wof:name":"Asociacion De Pensionistas De Hidroelectrica Espa\u00f1ola",
    "wof:placetype":"venue"
},
  "geometry": {"coordinates":[-0.3635745943,39.465171814],"type":"Point"}
}