{
  "type": "Feature",
  "properties": {
    "iso:country":"ES",
    "sg:address":"Avda Cid Campeador, 65",
    "sg:city":"Burgos",
    "sg:orig_category":"Molduras, Junquillos, Listones Y Molduras Perforadas",
    "sg:phone":"+34 947 22 10 82",
    "sg:postcode":"09005",
    "sg:province":"Burgos",
    "wof:name":"Perez Serrano Jorge Pablo",
    "wof:placetype":"venue"
},
  "geometry": {"coordinates":[-3.6963169575,42.3494796753],"type":"Point"}
}