{
  "type": "Feature",
  "properties": {
    "iso:country":"ES",
    "sg:address":"Calle de San Ignacio De Loyola, 20",
    "sg:city":"Valencia",
    "sg:orig_category":"M\u00c9dicos: Estomatolog\u00cda",
    "sg:phone":"+34 963 82 11 10",
    "sg:postcode":"46008",
    "sg:province":"Valencia",
    "wof:name":"Guisasola Lerma Estefania",
    "wof:placetype":"venue"
},
  "geometry": {"coordinates":[-0.390496999,39.4735069275],"type":"Point"}
}