{
  "type": "Feature",
  "properties": {
    "addr:full":"Avda Josa, 2 Moraleja Vino Zamora 49150",
    "addr:housenumber":"2",
    "addr:postcode":"49150",
    "addr:street":"Avda Josa;Zamora",
    "iso:country":"ES",
    "sg:address":"Avda Josa, 2",
    "sg:city":"Moraleja Vino",
    "sg:orig_category":"Droguer\u00cdas (al Por Menor)",
    "sg:phone":"+34 980 57 11 50",
    "sg:postcode":"49150",
    "sg:province":"Zamora",
    "wof:name":"Perez Garcia Zacarias",
    "wof:placetype":"venue"
},
  "geometry": {"coordinates":[-5.6559848785,41.4633331299],"type":"Point"}
}