{
  "type": "Feature",
  "properties": {
    "iso:country":"ES",
    "sg:address":"Huerto Carolina, 23",
    "sg:city":"Cox",
    "sg:orig_category":"Frutas Y Legumbres Frescas (al Por Mayor)",
    "sg:phone":"+34 965 36 02 81",
    "sg:postcode":"03350",
    "sg:province":"Alicante",
    "wof:name":"Gomez Cerdan Antonio Francisco",
    "wof:placetype":"venue"
},
  "geometry": {"coordinates":[-0.8830590248,38.1412315369],"type":"Point"}
}