{
  "type": "Feature",
  "properties": {
    "addr:full":"Calle de Alcalde Casal Aboy, 10 Tui Pontevedra 36700",
    "addr:housenumber":"10",
    "addr:postcode":"36700",
    "addr:street":"Calle De Alcalde Casal Aboy",
    "iso:country":"ES",
    "sg:address":"Calle de Alcalde Casal Aboy, 10",
    "sg:city":"Tui",
    "sg:orig_category":"Agencias Y Agentes Comerciales, Representantes",
    "sg:phone":"+34 986 60 14 25",
    "sg:postcode":"36700",
    "sg:province":"Pontevedra",
    "wof:name":"Iglesias Senn Roberto",
    "wof:placetype":"venue"
},
  "geometry": {"coordinates":[-8.6465520859,42.0511054993],"type":"Point"}
}