{
  "type": "Feature",
  "properties": {
    "addr:full":"Carr Gladiol, 33 Pont D'inca Islas Baleares 07009",
    "addr:housenumber":"33",
    "addr:postcode":"07009",
    "addr:street":"Carr Gladiol;Pont D'Inca",
    "iso:country":"ES",
    "sg:address":"Carr Gladiol, 33",
    "sg:city":"Pont D'inca",
    "sg:orig_category":"Molduras, Junquillos, Listones Y Molduras Perforadas",
    "sg:phone":"+34 971 60 11 64",
    "sg:postcode":"07009",
    "sg:province":"Islas Baleares",
    "wof:name":"Hidalgo De La Rosa Juan Manuel",
    "wof:placetype":"venue"
},
  "geometry": {"coordinates":[2.9091899395,39.7197418213],"type":"Point"}
}