{
  "type": "Feature",
  "properties": {
    "addr:full":"Calle de Poeta Martin Garrido, 21 Burgos Burgos 09007",
    "addr:housenumber":"21",
    "addr:postcode":"09007",
    "addr:street":"Calle De Poeta Martin Garrido",
    "iso:country":"ES",
    "sg:address":"Calle de Poeta Martin Garrido, 21",
    "sg:city":"Burgos",
    "sg:orig_category":"Alimentaci\u00d3n General (al Por Menor)",
    "sg:phone":"+34 947 22 05 40",
    "sg:postcode":"09007",
    "sg:province":"Burgos",
    "wof:name":"Guerra Guerra Cleto",
    "wof:placetype":"venue"
},
  "geometry": {"coordinates":[-3.6691009998,42.3551139832],"type":"Point"}
}