{
  "type": "Feature",
  "properties": {
    "addr:full":"Calle de Duque Del Sevillano, 5 Madrid Madrid 28032",
    "addr:housenumber":"5",
    "addr:postcode":"28032",
    "addr:street":"Calle De Duque Del Sevillano",
    "iso:country":"ES",
    "sg:address":"Calle de Duque Del Sevillano, 5",
    "sg:city":"Madrid",
    "sg:orig_category":"Guarder\u00cdas",
    "sg:phone":"+34 917 76 91 24",
    "sg:postcode":"28032",
    "sg:province":"Madrid",
    "wof:name":"Villa De Madrid Maria Dolores",
    "wof:placetype":"venue"
},
  "geometry": {"coordinates":[-3.6068189144,40.4028701782],"type":"Point"}
}