{
  "type": "Feature",
  "properties": {
    "addr:full":"Calle de Madrigueras, S/n Iniesta Cuenca 16235",
    "addr:housenumber":"s / n",
    "addr:postcode":"16235",
    "addr:street":"Calle De Madrigueras",
    "iso:country":"ES",
    "sg:address":"Calle de Madrigueras, S/n",
    "sg:city":"Iniesta",
    "sg:orig_category":"Empresas De Carpinter\u00cda Met\u00c1lica",
    "sg:phone":"+34 967 49 04 84",
    "sg:postcode":"16235",
    "sg:province":"Cuenca",
    "wof:name":"Soriano Pardo Jose Maria",
    "wof:placetype":"venue"
},
  "geometry": {"coordinates":[-1.7510303259,39.4401245117],"type":"Point"}
}