{
  "type": "Feature",
  "properties": {
    "addr:full":"Avgd Vicente Andres Estelles, S/n Burjassot Valencia 46100",
    "addr:housenumber":"s",
    "addr:postcode":"46100",
    "addr:street":"/ N",
    "iso:country":"ES",
    "sg:address":"Avgd Vicente Andres Estelles, S/n",
    "sg:city":"Burjassot",
    "sg:orig_category":"Caf\u00c9s, Bares, Cervecer\u00cdas",
    "sg:phone":"+34 963 63 09 99",
    "sg:postcode":"46100",
    "sg:province":"Valencia",
    "wof:name":"Instalaciones Tormagal S.l.",
    "wof:placetype":"venue"
},
  "geometry": {"coordinates":[-0.420498997,39.5088539124],"type":"Point"}
}