{
  "type": "Feature",
  "properties": {
    "addr:full":"Calle de Pesca (la), 4 Pto. Rosario Las Palmas 35600",
    "addr:housenumber":"4",
    "addr:postcode":"35600",
    "addr:street":"Calle De Pesca La;Pto. Rosario Las",
    "iso:country":"ES",
    "sg:address":"Calle de Pesca (la), 4",
    "sg:city":"Pto. Rosario",
    "sg:orig_category":"Extinci\u00d3n De Incendios: Material Y Suministros (fabricaci\u00d3n, Al Por Mayor)",
    "sg:phone":"+34 928 85 80 21",
    "sg:postcode":"35600",
    "sg:province":"Las Palmas",
    "wof:name":"Fireman System S.l.",
    "wof:placetype":"venue"
},
  "geometry": {"coordinates":[-13.8476085663,28.5031356812],"type":"Point"}
}