{
  "type": "Feature",
  "properties": {
    "iso:country":"ES",
    "sg:address":"Ctra Santa Creu De Calafell, Km. 0009,5",
    "sg:city":"S. Boi Llobregat",
    "sg:orig_category":"M\u00c1rmoles, Granitos Y Piedras Naturales",
    "sg:phone":"+34 936 30 57 52",
    "sg:postcode":"08830",
    "sg:province":"Barcelona",
    "wof:name":"Marmoles Marquez S.l.",
    "wof:placetype":"venue"
},
  "geometry": {"coordinates":[2.0449779034,41.3480606079],"type":"Point"}
}