{
  "type": "Feature",
  "properties": {
    "addr:full":"Carrer de Maravall, 30 Benidorm Alicante 03500",
    "addr:housenumber":"30",
    "addr:postcode":"03500",
    "addr:street":"Carrer De Maravall",
    "iso:country":"ES",
    "sg:address":"Carrer de Maravall, 30",
    "sg:city":"Benidorm",
    "sg:orig_category":"Telefon\u00cda: Instaladores Varios",
    "sg:phone":"+34 965 85 57 77",
    "sg:postcode":"03500",
    "sg:province":"Alicante",
    "wof:name":"Harman Enterprise S.l.",
    "wof:placetype":"venue"
},
  "geometry": {"coordinates":[-0.1333519965,38.5406455994],"type":"Point"}
}