{
  "type": "Feature",
  "properties": {
    "addr:full":"Carr Manuel De Falla, 2 Eivissa Islas Baleares 07800",
    "addr:housenumber":"2",
    "addr:postcode":"07800",
    "addr:street":"Carr Manuel De Falla",
    "iso:country":"ES",
    "sg:address":"Carr Manuel De Falla, 2",
    "sg:city":"Eivissa",
    "sg:orig_category":"Supermercados Y Hipermercados",
    "sg:phone":"+34 971 30 60 76",
    "sg:postcode":"07800",
    "sg:province":"Islas Baleares",
    "wof:name":"Costa Serra Juan",
    "wof:placetype":"venue"
},
  "geometry": {"coordinates":[1.4092669487,38.8944625854],"type":"Point"}
}