{
  "type": "Feature",
  "properties": {
    "addr:full":"Avda Murcia, 5 Cabezo Torres Murcia 30110",
    "addr:housenumber":"5",
    "addr:postcode":"30110",
    "addr:street":"Avda Murcia",
    "iso:country":"ES",
    "sg:address":"Avda Murcia, 5",
    "sg:city":"Cabezo Torres",
    "sg:orig_category":"Zapatos (al Por Menor)",
    "sg:phone":"+34 968 30 83 15",
    "sg:postcode":"30110",
    "sg:province":"Murcia",
    "wof:name":"Duran Montesinos Maria Carmen",
    "wof:placetype":"venue"
},
  "geometry": {"coordinates":[-1.1240509748,38.0233573914],"type":"Point"}
}