{
  "type": "Feature",
  "properties": {
    "iso:country":"ES",
    "sg:address":"Circunvalacion, 48",
    "sg:city":"Granada",
    "sg:orig_category":"Ropa Para Se\u00d1oras (al Por Menor)",
    "sg:phone":"+34 958 13 07 25",
    "sg:postcode":"18007",
    "sg:province":"Granada",
    "wof:name":"Carrasco Ramos Fernando",
    "wof:placetype":"venue"
},
  "geometry": {"coordinates":[-3.5975089073,37.1594314575],"type":"Point"}
}