{
  "type": "Feature",
  "properties": {
    "iso:country":"ES",
    "sg:address":"Carrer de Centre, 14",
    "sg:city":"Garriga",
    "sg:orig_category":"Electrodom\u00c9sticos (al Por Menor)",
    "sg:phone":"+34 938 71 58 52",
    "sg:postcode":"08530",
    "sg:province":"Barcelona",
    "sg:website":"www.redelite.es",
    "wof:name":"Maso Sitges Josep",
    "wof:placetype":"venue"
},
  "geometry": {"coordinates":[2.2854731083,41.6856613159],"type":"Point"}
}