{
  "type": "Feature",
  "properties": {
    "addr:full":"Calle de Escritor Jose Espa\u00d1a, S/n Granada Granada 18015",
    "addr:housenumber":"s / n",
    "addr:postcode":"18015",
    "addr:street":"Calle De Escritor Jose Espan\u0303A",
    "iso:country":"ES",
    "sg:address":"Calle de Escritor Jose Espa\u00d1a, S/n",
    "sg:city":"Granada",
    "sg:orig_category":"Chapister\u00cda",
    "sg:phone":"+34 958 29 57 66",
    "sg:postcode":"18015",
    "sg:province":"Granada",
    "wof:name":"Gonzalez Iba\u00f1ez Manuel",
    "wof:placetype":"venue"
},
  "geometry": {"coordinates":[-3.6381177902,37.1914291382],"type":"Point"}
}