{
  "type": "Feature",
  "properties": {
    "addr:full":"Calle de San Isidro, 16 Badajoz Badajoz 06004",
    "addr:housenumber":"16",
    "addr:postcode":"06004",
    "addr:street":"Calle De San Isidro",
    "iso:country":"ES",
    "sg:address":"Calle de San Isidro, 16",
    "sg:city":"Badajoz",
    "sg:orig_category":"Comercio De Cuadros, L\u00c1minas Y Reproducciones De Obras De Arte",
    "sg:phone":"+34 924 25 32 12",
    "sg:postcode":"06004",
    "sg:province":"Badajoz",
    "wof:name":"Garcia Mantecon Miguel Angel",
    "wof:placetype":"venue"
},
  "geometry": {"coordinates":[-6.976088047,38.8707847595],"type":"Point"}
}