{
  "type": "Feature",
  "properties": {
    "addr:full":"Calle de Alberto Fernandez, S/n Valladolid Valladolid 47010",
    "addr:housenumber":"s / n",
    "addr:postcode":"47010",
    "addr:street":"Calle De Alberto Fernandez",
    "iso:country":"ES",
    "sg:address":"Calle de Alberto Fernandez, S/n",
    "sg:city":"Valladolid",
    "sg:orig_category":"Molduras, Junquillos, Listones Y Molduras Perforadas",
    "sg:phone":"+34 983 31 05 50",
    "sg:postcode":"47010",
    "sg:province":"Valladolid",
    "wof:name":"Cote Villanueva Rafael",
    "wof:placetype":"venue"
},
  "geometry": {"coordinates":[-4.7247900963,41.6641311646],"type":"Point"}
}