{
  "type": "Feature",
  "properties": {
    "iso:country":"ES",
    "sg:address":"Avda Jesus Rescatado (de), 12",
    "sg:city":"Cordoba",
    "sg:orig_category":"Fabricaci\u00d3n De Su\u00c9ters Y Chalecos De Punto",
    "sg:phone":"+34 957 76 47 91",
    "sg:postcode":"14007",
    "sg:province":"C\u00f3rdoba",
    "wof:name":"Diaz Rubio Francisca",
    "wof:placetype":"venue"
},
  "geometry": {"coordinates":[-4.761493206,37.890712738],"type":"Point"}
}