{
  "type": "Feature",
  "properties": {
    "addr:full":"Carr Raval, 12 Blanes Girona 17300",
    "addr:housenumber":"12",
    "addr:postcode":"17300",
    "addr:street":"Carr Raval",
    "iso:country":"ES",
    "sg:address":"Carr Raval, 12",
    "sg:city":"Blanes",
    "sg:orig_category":"Librer\u00cdas",
    "sg:phone":"+34 972 33 03 31",
    "sg:postcode":"17300",
    "sg:province":"Girona",
    "wof:name":"Utset Alum Dolors",
    "wof:placetype":"venue"
},
  "geometry": {"coordinates":[2.7921669483,41.676399231],"type":"Point"}
}