{
  "type": "Feature",
  "properties": {
    "iso:country":"ES",
    "sg:address":"Cra. S. Coloma, S/n",
    "sg:city":"Riudarenes",
    "sg:orig_category":"Molduras, Junquillos, Listones Y Molduras Perforadas",
    "sg:phone":"+34 972 16 45 33",
    "sg:postcode":"17421",
    "sg:province":"Girona",
    "wof:name":"Aranda Paz Angel",
    "wof:placetype":"venue"
},
  "geometry": {"coordinates":[2.6994683743,41.8405303955],"type":"Point"}
}