{
  "type": "Feature",
  "properties": {
    "addr:full":"Calle de Gran Via, 31 Madrid Madrid 28013",
    "addr:housenumber":"31",
    "addr:postcode":"madrid;28013",
    "addr:street":"Calle De Gran Via",
    "iso:country":"ES",
    "sg:address":"Calle de Gran Via, 31",
    "sg:city":"Madrid",
    "sg:orig_category":"Sindicatos Y Colegios Profesionales",
    "sg:phone":"+34 915 21 61 05",
    "sg:postcode":"28013",
    "sg:province":"Madrid",
    "wof:name":"Asociacion De Interpretes Nipones",
    "wof:placetype":"venue"
},
  "geometry": {"coordinates":[-3.7037320137,40.4200973511],"type":"Point"}
}