{
  "type": "Feature",
  "properties": {
    "addr:full":"Calle de Malecon, S/n Tembleque Toledo 45780",
    "addr:housenumber":"s",
    "addr:postcode":"45780",
    "addr:street":"Calle De Malecon;/ N",
    "iso:country":"ES",
    "sg:address":"Calle de Malecon, S/n",
    "sg:city":"Tembleque",
    "sg:orig_category":"Estudios, Instalaci\u00d3n De Climatizaci\u00d3n",
    "sg:phone":"+34 925 14 52 33",
    "sg:postcode":"45780",
    "sg:province":"Toledo",
    "wof:name":"Rodriguez Pinardo Jose Luis",
    "wof:placetype":"venue"
},
  "geometry": {"coordinates":[-3.5006439686,39.6992111206],"type":"Point"}
}