{
  "type": "Feature",
  "properties": {
    "iso:country":"ES",
    "sg:address":"Calle de Hermanas Bronte, 2",
    "sg:city":"Malaga",
    "sg:orig_category":"Bisuter\u00cda, Joyer\u00cda, Relojer\u00cda (al Por Menor)",
    "sg:phone":"+34 952 23 01 46",
    "sg:postcode":"29004",
    "sg:province":"M\u00e1laga",
    "wof:name":"Comercial Nisan S.a.",
    "wof:placetype":"venue"
},
  "geometry": {"coordinates":[-4.4732441902,36.6876449585],"type":"Point"}
}