{
  "type": "Feature",
  "properties": {
    "addr:full":"Calle de Iba\u00d1ez De Bilbao, 12 Bilbao Vizcaya 48001",
    "addr:housenumber":"12",
    "addr:postcode":"48001",
    "addr:street":"Calle De Iban\u0303Ez De Bilbao",
    "iso:country":"ES",
    "sg:address":"Calle de Iba\u00d1ez De Bilbao, 12",
    "sg:city":"Bilbao",
    "sg:orig_category":"Comidas Por Encargo, Organizaci\u00d3n De Recepciones",
    "sg:phone":"+34 944 24 02 48",
    "sg:postcode":"48001",
    "sg:province":"Vizcaya",
    "wof:name":"Equipo 7 Restauracion S.a.",
    "wof:placetype":"venue"
},
  "geometry": {"coordinates":[-2.9271149635,43.2630996704],"type":"Point"}
}