{
  "type": "Feature",
  "properties": {
    "addr:full":"Calle de Ezpondoa, 13 Burlada Navarra 31600",
    "addr:housenumber":"13",
    "addr:postcode":"31600",
    "addr:street":"Calle De Ezpondoa",
    "iso:country":"ES",
    "sg:address":"Calle de Ezpondoa, 13",
    "sg:city":"Burlada",
    "sg:orig_category":"Frutas, Legumbres Frescas Y Tempranas (al Por Menor)",
    "sg:phone":"+34 948 15 16 52",
    "sg:postcode":"31600",
    "sg:province":"Navarra",
    "wof:name":"Percaz Bados Ignacio Pablo",
    "wof:placetype":"venue"
},
  "geometry": {"coordinates":[-1.6180210114,42.8230361938],"type":"Point"}
}