{
  "type": "Feature",
  "properties": {
    "addr:full":"Calle de Miguel Delibes, 5 Zubia Granada 18140",
    "addr:housenumber":"5",
    "addr:postcode":"18140",
    "addr:street":"Calle De Miguel Delibes",
    "iso:country":"ES",
    "sg:address":"Calle de Miguel Delibes, 5",
    "sg:city":"Zubia",
    "sg:orig_category":"Instalaci\u00d3n, Reparaci\u00d3n De Ascensores Y Montacargas",
    "sg:phone":"+34 958 59 09 87",
    "sg:postcode":"18140",
    "sg:province":"Granada",
    "wof:name":"Ascensores Erga S.l.u.",
    "wof:placetype":"venue"
},
  "geometry": {"coordinates":[-3.5840637684,37.1213111877],"type":"Point"}
}