{
  "type": "Feature",
  "properties": {
    "iso:country":"ES",
    "sg:address":"Carrer de Pin I Soler, 3",
    "sg:city":"Tarragona",
    "sg:orig_category":"Higiene, Belleza: Art\u00cdculos (al Por Menor)",
    "sg:phone":"+34 977 21 81 75",
    "sg:postcode":"43002",
    "sg:province":"Tarragona",
    "wof:name":"Salazar Mena Antonio",
    "wof:placetype":"venue"
},
  "geometry": {"coordinates":[1.2497400045,41.1197547913],"type":"Point"}
}