{
  "type": "Feature",
  "properties": {
    "iso:country":"ES",
    "sg:address":"Av Diagonal, 704",
    "sg:city":"Barcelona",
    "sg:orig_category":"Asociaciones, Organismos Culturales Y Socioeducativos",
    "sg:phone":"+34 932 80 28 22",
    "sg:postcode":"08034",
    "sg:province":"Barcelona",
    "wof:name":"Tribuna Barcelona",
    "wof:placetype":"venue"
},
  "geometry": {"coordinates":[2.1097209454,41.3843955994],"type":"Point"}
}