{
  "type": "Feature",
  "properties": {
    "iso:country":"ES",
    "sg:address":"Calle de Reguera De Tomateros, 103",
    "sg:city":"Madrid",
    "sg:orig_category":"Internados & Ense\u00d1anza Privada",
    "sg:phone":"+34 917 85 63 68",
    "sg:postcode":"28053",
    "sg:province":"Madrid",
    "wof:name":"Sociedad Cooperativa Esenco",
    "wof:placetype":"venue"
},
  "geometry": {"coordinates":[-3.6576058865,40.3701934814],"type":"Point"}
}