{
  "type": "Feature",
  "properties": {
    "iso:country":"ES",
    "sg:address":"Avda Emilio Castelar, 102",
    "sg:city":"S. Pedro Pinatar",
    "sg:orig_category":"Carnicer\u00cdas, Carnicer\u00cdas",
    "sg:phone":"+34 968 18 70 83",
    "sg:postcode":"30740",
    "sg:province":"Murcia",
    "wof:name":"El Kilo Y Medio S.l.",
    "wof:placetype":"venue"
},
  "geometry": {"coordinates":[-0.7872610092,37.8280830383],"type":"Point"}
}