{
  "type": "Feature",
  "properties": {
    "iso:country":"ES",
    "sg:address":"Calle de Sierra Albarracin, 3",
    "sg:city":"Arganda",
    "sg:orig_category":"Librer\u00cdas",
    "sg:phone":"+34 902 19 55 51",
    "sg:postcode":"28500",
    "sg:province":"Madrid",
    "wof:name":"Ediciones Del Laberinto S.l.",
    "wof:placetype":"venue"
},
  "geometry": {"coordinates":[-3.474998951,40.3057594299],"type":"Point"}
}