{
  "type": "Feature",
  "properties": {
    "addr:full":"Avgd Balmes, 3 Lleida Lleida 25006",
    "addr:housenumber":"3",
    "addr:postcode":"25006",
    "addr:street":"Avgd Balmes",
    "iso:country":"ES",
    "sg:address":"Avgd Balmes, 3",
    "sg:city":"Lleida",
    "sg:orig_category":"Bancos",
    "sg:phone":"+34 973 26 90 11",
    "sg:postcode":"25006",
    "sg:province":"Lleida",
    "sg:website":"www.bancsabadell.com",
    "wof:name":"Banc Sabadell S.a.",
    "wof:placetype":"venue"
},
  "geometry": {"coordinates":[0.5619999766,41.6497535706],"type":"Point"}
}