{
  "type": "Feature",
  "properties": {
    "addr:full":"Calle de Grande, 62 Adeje Santa Cruz De Tenerife 38670",
    "addr:housenumber":"62",
    "addr:postcode":"38670",
    "addr:street":"Calle De Grande",
    "iso:country":"ES",
    "sg:address":"Calle de Grande, 62",
    "sg:city":"Adeje",
    "sg:orig_category":"Telas Y Sedas (al Por Menor)",
    "sg:phone":"+34 922 71 08 68",
    "sg:postcode":"38670",
    "sg:province":"Santa Cruz De Tenerife",
    "sg:website":"teleropa@terra.es",
    "wof:name":"Teleropa S.l.",
    "wof:placetype":"venue"
},
  "geometry": {"coordinates":[-16.7257328033,28.1207637787],"type":"Point"}
}