{
  "type": "Feature",
  "properties": {
    "iso:country":"ES",
    "sg:address":"Calle de Hierro, 9",
    "sg:city":"Madrid",
    "sg:orig_category":"Electricidad, Electr\u00d3nica: Material Y Suministros (al Por Mayor)",
    "sg:phone":"+34 915 39 43 30",
    "sg:postcode":"28045",
    "sg:province":"Madrid",
    "wof:name":"Nucliber Sa",
    "wof:placetype":"venue"
},
  "geometry": {"coordinates":[-3.6893200874,40.3887519836],"type":"Point"}
}