{
  "type": "Feature",
  "properties": {
    "addr:full":"Avda Salobrar, 12 Jaraiz Vera C\u00e1ceres 10400",
    "addr:housenumber":"12",
    "addr:postcode":"10400",
    "addr:street":"Avda Salobrar",
    "iso:country":"ES",
    "sg:address":"Avda Salobrar, 12",
    "sg:city":"Jaraiz Vera",
    "sg:orig_category":"Supermercados Y Hipermercados",
    "sg:phone":"+34 927 46 11 29",
    "sg:postcode":"10400",
    "sg:province":"C\u00e1ceres",
    "wof:name":"Alimentacion Goria S.l.",
    "wof:placetype":"venue"
},
  "geometry": {"coordinates":[-5.7516183853,40.060005188],"type":"Point"}
}