{
  "type": "Feature",
  "properties": {
    "addr:full":"Avgd Alfons Xiii, 542 Badalona Barcelona 08913",
    "addr:housenumber":"542",
    "addr:postcode":"08913",
    "addr:street":"Alfons Xiii",
    "iso:country":"ES",
    "sg:address":"Avgd Alfons Xiii, 542",
    "sg:city":"Badalona",
    "sg:orig_category":"Cajas De Ahorro",
    "sg:phone":"+34 933 99 30 00",
    "sg:postcode":"08913",
    "sg:province":"Barcelona",
    "wof:name":"Caixa D'estalvis I Pensions De Barcelona",
    "wof:placetype":"venue"
},
  "geometry": {"coordinates":[2.2198140621,41.4351043701],"type":"Point"}
}