{
  "type": "Feature",
  "properties": {
    "iso:country":"ES",
    "sg:address":"Calle de Concepcion, 8",
    "sg:city":"Torrevieja",
    "sg:orig_category":"Peluquer\u00cdas, Peluquer\u00cda Mixta",
    "sg:phone":"+34 965 71 11 97",
    "sg:postcode":"03180",
    "sg:province":"Alicante",
    "wof:name":"Arrabal Mendoza Vanesa",
    "wof:placetype":"venue"
},
  "geometry": {"coordinates":[-0.6827700138,37.9765701294],"type":"Point"}
}