{
  "type": "Feature",
  "properties": {
    "iso:country":"ES",
    "sg:address":"Calle de Editor Manuel Aguilar, 2",
    "sg:city":"Valencia",
    "sg:orig_category":"Papeler\u00cdas, Librer\u00cdas",
    "sg:phone":"+34 963 92 53 49",
    "sg:postcode":"46001",
    "sg:province":"Valencia",
    "wof:name":"Sebastia Juste Desamparados",
    "wof:placetype":"venue"
},
  "geometry": {"coordinates":[-0.3799470067,39.4728775024],"type":"Point"}
}