{
  "type": "Feature",
  "properties": {
    "addr:full":"Calle de Santa Isabel, 35 Santa Isabel Vizcaya 48003",
    "addr:housenumber":"35",
    "addr:postcode":"48003",
    "addr:street":"Calle De Santa Isabel",
    "iso:country":"ES",
    "sg:address":"Calle de Santa Isabel, 35",
    "sg:city":"Santa Isabel",
    "sg:orig_category":"Obras Y Organismos Sociales",
    "sg:phone":"+34 944 15 37 89",
    "sg:postcode":"48003",
    "sg:province":"Vizcaya",
    "wof:name":"Asociacion Askabide-liberacion",
    "wof:placetype":"venue"
},
  "geometry": {"coordinates":[-2.6983869076,43.2204284668],"type":"Point"}
}