{
  "type": "Feature",
  "properties": {
    "iso:country":"ES",
    "sg:address":"Calle de Virgen Del Portillo, 9",
    "sg:city":"Madrid",
    "sg:orig_category":"Fabricaci\u00d3n De Bolsos Y Bolsos De Tela",
    "sg:phone":"+34 914 04 16 95",
    "sg:postcode":"28027",
    "sg:province":"Madrid",
    "wof:name":"Comercial De Sacos Y Cordeleria S.l.",
    "wof:placetype":"venue"
},
  "geometry": {"coordinates":[-3.654900074,40.435710907],"type":"Point"}
}