{
  "type": "Feature",
  "properties": {
    "iso:country":"ES",
    "sg:address":"Cm\u00d1o Revolta, 7",
    "sg:city":"Gandara",
    "sg:orig_category":"Negocio De Madera",
    "sg:phone":"+34 981 38 65 78",
    "sg:postcode":"15572",
    "sg:province":"La Coru\u00f1a",
    "wof:name":"Grandal Casteleiro Jose Manuel Francisco",
    "wof:placetype":"venue"
},
  "geometry": {"coordinates":[-8.1602964401,43.4693870544],"type":"Point"}
}