{
  "type": "Feature",
  "properties": {
    "iso:country":"ES",
    "sg:address":"Calle de Ancha, 54",
    "sg:city":"Palma Rio",
    "sg:orig_category":"Centros Comerciales Y Grandes Tiendas",
    "sg:phone":"+34 957 71 00 52",
    "sg:postcode":"14700",
    "sg:province":"C\u00f3rdoba",
    "wof:name":"Makdoom  Alardi",
    "wof:placetype":"venue"
},
  "geometry": {"coordinates":[-5.2792978287,37.6982574463],"type":"Point"}
}