{
  "type": "Feature",
  "properties": {
    "addr:full":"Calle de San Guillermo, 8 Obanos Navarra 31151",
    "addr:housenumber":"8",
    "addr:postcode":"31151",
    "addr:street":"Calle De San Guillermo",
    "iso:country":"ES",
    "sg:address":"Calle de San Guillermo, 8",
    "sg:city":"Obanos",
    "sg:orig_category":"Inform\u00c1tica, Ofim\u00c1tica (estudios, Asesor\u00cda, Ingenier\u00cda, Formaci\u00d3n)",
    "sg:phone":"+34 948 34 42 04",
    "sg:postcode":"31151",
    "sg:province":"Navarra",
    "sg:website":"www.halleysistemas.com",
    "wof:name":"Aznar Go\u00f1i Agapito Sanchez Anton Martin Aller Mara\u00f1on Oscar Larraga Mendoza Rosario S.cv.",
    "wof:placetype":"venue"
},
  "geometry": {"coordinates":[-1.7850270271,42.6786842346],"type":"Point"}
}