{
  "type": "Feature",
  "properties": {
    "iso:country":"ES",
    "sg:address":"Calle de Empedrada, 8",
    "sg:city":"Jerez De La Frontera",
    "sg:orig_category":"Transporte En General",
    "sg:phone":"+34 956 34 35 93",
    "sg:postcode":"11401",
    "sg:province":"C\u00e1diz",
    "wof:name":"Siles Puerto Juan Pedro",
    "wof:placetype":"venue"
},
  "geometry": {"coordinates":[-6.1331691742,36.6785011292],"type":"Point"}
}