{
  "type": "Feature",
  "properties": {
    "addr:full":"Calle de Cervantes, 5 Arjona Ja\u00e9n 23760",
    "addr:housenumber":"5",
    "addr:postcode":"23760",
    "addr:street":"Calle De Cervantes;Jae\u0301N",
    "iso:country":"ES",
    "sg:address":"Calle de Cervantes, 5",
    "sg:city":"Arjona",
    "sg:orig_category":"Promotores Constructores",
    "sg:phone":"+34 953 52 33 87",
    "sg:postcode":"23760",
    "sg:province":"Ja\u00e9n",
    "wof:name":"Moreno Messia Bibian",
    "wof:placetype":"venue"
},
  "geometry": {"coordinates":[-4.0554533005,37.9363594055],"type":"Point"}
}