{
  "type": "Feature",
  "properties": {
    "iso:country":"ES",
    "sg:address":"Plaz Mayor, S/n",
    "sg:city":"Cigales",
    "sg:orig_category":"Estancos",
    "sg:phone":"+34 983 58 00 83",
    "sg:postcode":"47270",
    "sg:province":"Valladolid",
    "wof:name":"Pinacho San Jose Florentino",
    "wof:placetype":"venue"
},
  "geometry": {"coordinates":[-4.699119091,41.7584762573],"type":"Point"}
}