{
  "type": "Feature",
  "properties": {
    "addr:full":"Carr Pi I Margall, 28 Lleida Lleida 25004",
    "addr:housenumber":"28",
    "addr:postcode":"25004",
    "addr:street":"Carr Pi I Margall",
    "iso:country":"ES",
    "sg:address":"Carr Pi I Margall, 28",
    "sg:city":"Lleida",
    "sg:orig_category":"Confecci\u00d3n De Trajes Para Se\u00d1oras",
    "sg:phone":"+34 973 24 16 47",
    "sg:postcode":"25004",
    "sg:province":"Lleida",
    "wof:name":"Vidal Bullo Magdalena",
    "wof:placetype":"venue"
},
  "geometry": {"coordinates":[0.6279969811,41.621055603],"type":"Point"}
}