{
  "type": "Feature",
  "properties": {
    "addr:full":"Calle de Nueva Avenida, 12 Alfoquia Almer\u00eda 04650",
    "addr:postcode":"04650",
    "addr:street":"Calle De;Avenida 12 Alfoquia Almeri\u0301A",
    "iso:country":"ES",
    "sg:address":"Calle de Nueva Avenida, 12",
    "sg:city":"Alfoquia",
    "sg:orig_category":"Carnicer\u00cdas, Carnicer\u00cdas",
    "sg:phone":"+34 950 44 90 88",
    "sg:postcode":"04650",
    "sg:province":"Almer\u00eda",
    "wof:name":"Carnica Aguila Y Sanchez S.l.",
    "wof:placetype":"venue"
},
  "geometry": {"coordinates":[-2.0336489677,37.35364151],"type":"Point"}
}