{
  "type": "Feature",
  "properties": {
    "iso:country":"ES",
    "sg:address":"Calle de Virgen Del Carmen, 34",
    "sg:city":"Donostia-san Sebastian",
    "sg:orig_category":"Pescader\u00cdas (al Por Menor)",
    "sg:phone":"+34 943 27 77 05",
    "sg:postcode":"20012",
    "sg:province":"Guip\u00f9zcoa",
    "wof:name":"Arantza Gracia Martin",
    "wof:placetype":"venue"
},
  "geometry": {"coordinates":[-1.9694613218,43.3176078796],"type":"Point"}
}