{
  "type": "Feature",
  "properties": {
    "addr:full":"Avda Galicia De, S/n Luarca Asturias 33700",
    "addr:housenumber":"/ n",
    "addr:postcode":"33700",
    "addr:street":"Avda Galicia De S",
    "iso:country":"ES",
    "sg:address":"Avda Galicia De, S/n",
    "sg:city":"Luarca",
    "sg:orig_category":"Mec\u00c1nico Del Autom\u00d3vil",
    "sg:phone":"+34 985 64 04 73",
    "sg:postcode":"33700",
    "sg:province":"Asturias",
    "wof:name":"Talleres Mecanicos Lopez C.b.",
    "wof:placetype":"venue"
},
  "geometry": {"coordinates":[-6.5397100449,43.5404701233],"type":"Point"}
}