{
  "type": "Feature",
  "properties": {
    "addr:full":"Poli Can Font De La Parera, S/n Santa Agnes De Malanyanes Barcelona 08430",
    "addr:housenumber":"s / n",
    "addr:postcode":"08430",
    "addr:street":"Parera",
    "iso:country":"ES",
    "sg:address":"Poli Can Font De La Parera, S/n",
    "sg:city":"Santa Agnes De Malanyanes",
    "sg:orig_category":"Ferreter\u00cda (diversos)",
    "sg:phone":"+34 938 42 28 45",
    "sg:postcode":"08430",
    "sg:province":"Barcelona",
    "wof:name":"Tyr Metales S.l.",
    "wof:placetype":"venue"
},
  "geometry": {"coordinates":[2.3271899223,41.5984611511],"type":"Point"}
}