{
  "type": "Feature",
  "properties": {
    "addr:full":"Calle de Cervantes, 56 Parador Hortichuelas Almer\u00eda 04721",
    "addr:housenumber":"56",
    "addr:postcode":"04721",
    "addr:street":"Calle De Cervantes;Almeri\u0301A",
    "iso:country":"ES",
    "sg:address":"Calle de Cervantes, 56",
    "sg:city":"Parador Hortichuelas",
    "sg:orig_category":"Promotores Constructores",
    "sg:phone":"+34 950 34 00 20",
    "sg:postcode":"04721",
    "sg:province":"Almer\u00eda",
    "wof:name":"Bordalas Montes Jose",
    "wof:placetype":"venue"
},
  "geometry": {"coordinates":[-2.0289900303,36.8726501465],"type":"Point"}
}