{
  "type": "Feature",
  "properties": {
    "addr:full":"Carrer de Murcia, 47 S. Boi Llobregat Barcelona 08830",
    "addr:housenumber":"47",
    "addr:postcode":"08830",
    "addr:street":"Carrer De Murcia",
    "iso:country":"ES",
    "sg:address":"Carrer de Murcia, 47",
    "sg:city":"S. Boi Llobregat",
    "sg:orig_category":"Animales (al Por Menor)",
    "sg:phone":"+34 936 40 16 97",
    "sg:postcode":"08830",
    "sg:province":"Barcelona",
    "wof:name":"Euro-aviram S.l.",
    "wof:placetype":"venue"
},
  "geometry": {"coordinates":[2.0420799255,41.3285903931],"type":"Point"}
}