{
  "type": "Feature",
  "properties": {
    "iso:country":"ES",
    "sg:address":"Po. Inmaculada, 66",
    "sg:city":"Estella",
    "sg:orig_category":"Instalaci\u00d3n De Sanitarios",
    "sg:phone":"+34 948 55 49 55",
    "sg:postcode":"31200",
    "sg:province":"Navarra",
    "wof:name":"Servirecord S.l.",
    "wof:placetype":"venue"
},
  "geometry": {"coordinates":[-2.0343000889,42.6718025208],"type":"Point"}
}