{
  "type": "Feature",
  "properties": {
    "iso:country":"ES",
    "sg:address":"Calle de Primitivo Aguado, 26",
    "sg:city":"Iscar",
    "sg:orig_category":"Asociaciones, Organismos Culturales Y Socioeducativos",
    "sg:phone":"+34 983 62 06 21",
    "sg:postcode":"47420",
    "sg:province":"Valladolid",
    "wof:name":"Asociacion Juvenil El Castillo",
    "wof:placetype":"venue"
},
  "geometry": {"coordinates":[-4.5304970741,41.3601036072],"type":"Point"}
}