{
  "type": "Feature",
  "properties": {
    "iso:country":"ES",
    "sg:address":"Calle de Key Mu\u00d1oz, 1",
    "sg:city":"Icod De Los Vinos",
    "sg:orig_category":"Asesor\u00cda Sobre Comunicaci\u00d3n De Empresas",
    "sg:phone":"+34 922 81 08 00",
    "sg:postcode":"38430",
    "sg:province":"Santa Cruz De Tenerife",
    "wof:name":"Asociacion Profesional De Peque\u00f1os Y Medianos Empresarios",
    "wof:placetype":"venue"
},
  "geometry": {"coordinates":[-16.7187843323,28.3676166534],"type":"Point"}
}