{
  "type": "Feature",
  "properties": {
    "addr:full":"Calle de Vado (del), 21 Tres Cantos Madrid 28760",
    "addr:housenumber":"21",
    "addr:postcode":"28760",
    "addr:street":"Calle De Vado Del",
    "iso:country":"ES",
    "sg:address":"Calle de Vado (del), 21",
    "sg:city":"Tres Cantos",
    "sg:orig_category":"Talleres: Ropa A Medida",
    "sg:phone":"+34 918 03 39 09",
    "sg:postcode":"28760",
    "sg:province":"Madrid",
    "sg:website":"www.ka-international.com",
    "wof:name":"Ortiz Gonzalez Beatriz S.l.n.e.",
    "wof:placetype":"venue"
},
  "geometry": {"coordinates":[-3.7012810707,40.5978012085],"type":"Point"}
}