{
  "type": "Feature",
  "properties": {
    "iso:country":"ES",
    "sg:address":"Poligono Agrinasa, S/n",
    "sg:city":"Cadrete",
    "sg:orig_category":"Mantenimiento Industrial",
    "sg:phone":"+34 976 12 62 35",
    "sg:postcode":"50420",
    "sg:province":"Zaragoza",
    "wof:name":"Mecanicas Indados S.l.",
    "wof:placetype":"venue"
},
  "geometry": {"coordinates":[-0.9601830244,41.5556411743],"type":"Point"}
}