{
  "type": "Feature",
  "properties": {
    "addr:full":"Calle de San Borondon, 79 Playa Honda Las Palmas 35509",
    "addr:housenumber":"79",
    "addr:postcode":"35509",
    "addr:street":"Calle De San Borondon",
    "iso:country":"ES",
    "sg:address":"Calle de San Borondon, 79",
    "sg:city":"Playa Honda",
    "sg:orig_category":"Bancos",
    "sg:phone":"+34 928 82 18 24",
    "sg:postcode":"35509",
    "sg:province":"Las Palmas",
    "wof:name":"Banco Popular Espa\u00f1ol S.a.",
    "wof:placetype":"venue"
},
  "geometry": {"coordinates":[-13.5923452377,28.9531612396],"type":"Point"}
}