{
  "type": "Feature",
  "properties": {
    "addr:full":"Calle de Arzobispo Elias Yanes, 44 San Lazaro Santa Cruz De Tenerife 38206",
    "addr:housenumber":"44",
    "addr:postcode":"38206",
    "addr:street":"Calle De Arzobispo Elias Yanes",
    "iso:country":"ES",
    "sg:address":"Calle de Arzobispo Elias Yanes, 44",
    "sg:city":"San Lazaro",
    "sg:orig_category":"Inversiones",
    "sg:phone":"+34 922 31 55 80",
    "sg:postcode":"38206",
    "sg:province":"Santa Cruz De Tenerife",
    "wof:name":"Cima Canarias, S.l.",
    "wof:placetype":"venue"
},
  "geometry": {"coordinates":[-16.2548561096,28.4698104858],"type":"Point"}
}