{
  "type": "Feature",
  "properties": {
    "iso:country":"ES",
    "sg:address":"Carr Sant Sebastia (de), 2",
    "sg:city":"Aspa",
    "sg:orig_category":"Aceites Y Grasas Alimentarias (fabricaci\u00d3n, Al Por Mayor)",
    "sg:phone":"+34 973 12 20 81",
    "sg:postcode":"25151",
    "sg:province":"Lleida",
    "wof:name":"Torrent Carre Herminia",
    "wof:placetype":"venue"
},
  "geometry": {"coordinates":[0.6725360155,41.4953269958],"type":"Point"}
}