{
  "type": "Feature",
  "properties": {
    "addr:full":"Calle de Luis Ulloa Pereira, 4 Zamora Zamora 49015",
    "addr:housenumber":"4",
    "addr:postcode":"49015",
    "addr:street":"Calle De Luis Ulloa Pereira",
    "iso:country":"ES",
    "sg:address":"Calle de Luis Ulloa Pereira, 4",
    "sg:city":"Zamora",
    "sg:orig_category":"M\u00c9dicos: Cirug\u00cda Maxilofacial",
    "sg:phone":"+34 980 53 42 00",
    "sg:postcode":"49015",
    "sg:province":"Zamora",
    "wof:name":"Centro Oral Y Maxilofacial Buccal S.l.",
    "wof:placetype":"venue"
},
  "geometry": {"coordinates":[-5.7402248383,41.505607605],"type":"Point"}
}