{
  "type": "Feature",
  "properties": {
    "iso:country":"ES",
    "sg:address":"Calle de Maestro Falla, 14",
    "sg:city":"S. Pedro Pinatar",
    "sg:orig_category":"Pescader\u00cdas (al Por Mayor)",
    "sg:phone":"+34 968 17 93 80",
    "sg:postcode":"30740",
    "sg:province":"Murcia",
    "wof:name":"Bluefin Tuna S.l.",
    "wof:placetype":"venue"
},
  "geometry": {"coordinates":[-0.7921350002,37.832736969],"type":"Point"}
}