{
  "type": "Feature",
  "properties": {
    "iso:country":"ES",
    "sg:address":"Calle de Perez Bayer, S/n",
    "sg:city":"Valencia",
    "sg:orig_category":"Deportes Y Ocio: Art\u00cdculos Y Equipos (al Por Mayor)",
    "sg:phone":"+34 963 51 50 28",
    "sg:postcode":"46002",
    "sg:province":"Valencia",
    "wof:name":"Latoya Sport S.l.",
    "wof:placetype":"venue"
},
  "geometry": {"coordinates":[-0.3717750013,39.4697723389],"type":"Point"}
}