{
  "type": "Feature",
  "properties": {
    "iso:country":"ES",
    "sg:address":"Calle de General Franco, 115",
    "sg:city":"Guitiriz",
    "sg:orig_category":"Electricidad Veh\u00cdculo",
    "sg:phone":"+34 982 37 02 53",
    "sg:postcode":"27300",
    "sg:province":"Lugo",
    "wof:name":"Carro Mosquera Antonio",
    "wof:placetype":"venue"
},
  "geometry": {"coordinates":[-7.8988189697,43.1811637878],"type":"Point"}
}