{
  "type": "Feature",
  "properties": {
    "iso:country":"ES",
    "sg:address":"Carrer de Cort (de La), 66",
    "sg:city":"Valls",
    "sg:orig_category":"Librer\u00cdas",
    "sg:phone":"+34 977 60 12 05",
    "sg:postcode":"43800",
    "sg:province":"Tarragona",
    "wof:name":"Secall Roca Julia",
    "wof:placetype":"venue"
},
  "geometry": {"coordinates":[1.2499899864,41.2855987549],"type":"Point"}
}