{
  "type": "Feature",
  "properties": {
    "iso:country":"ES",
    "sg:address":"San Bartolome Kalea, 28",
    "sg:city":"Elgoibar",
    "sg:orig_category":"Zapatos (al Por Menor)",
    "sg:phone":"+34 943 74 43 45",
    "sg:postcode":"20870",
    "sg:province":"Guip\u00f9zcoa",
    "wof:name":"Gonzalez Mediavilla Maria Eugenia",
    "wof:placetype":"venue"
},
  "geometry": {"coordinates":[-2.4158146381,43.2150039673],"type":"Point"}
}