{
  "type": "Feature",
  "properties": {
    "iso:country":"ES",
    "sg:address":"Carrer de Segre, 49",
    "sg:city":"Barcelona",
    "sg:orig_category":"Peluquer\u00cdas, Peluquer\u00cda Mixta",
    "sg:phone":"+34 932 74 00 06",
    "sg:postcode":"08030",
    "sg:province":"Barcelona",
    "wof:name":"Hidalgo Poza Cristina",
    "wof:placetype":"venue"
},
  "geometry": {"coordinates":[2.1931080818,41.4330749512],"type":"Point"}
}