{
  "type": "Feature",
  "properties": {
    "addr:full":"Calle de Perez Oliva, 6 Yebenes Toledo 45470",
    "addr:housenumber":"6",
    "addr:postcode":"45470",
    "addr:street":"Calle De Perez Oliva",
    "iso:country":"ES",
    "sg:address":"Calle de Perez Oliva, 6",
    "sg:city":"Yebenes",
    "sg:orig_category":"Cristaler\u00cdas",
    "sg:phone":"+34 925 32 01 62",
    "sg:postcode":"45470",
    "sg:province":"Toledo",
    "wof:name":"Due\u00f1as Ramirez Miguel Angel",
    "wof:placetype":"venue"
},
  "geometry": {"coordinates":[-3.8644459248,39.582408905],"type":"Point"}
}