{
  "type": "Feature",
  "properties": {
    "iso:country":"ES",
    "sg:address":"Calle de Oriental, 20",
    "sg:city":"Gijon",
    "sg:orig_category":"Molduras, Junquillos, Listones Y Molduras Perforadas",
    "sg:phone":"+34 985 32 30 56",
    "sg:postcode":"33213",
    "sg:province":"Asturias",
    "wof:name":"Linares Fernandez Celestino",
    "wof:placetype":"venue"
},
  "geometry": {"coordinates":[-5.6968002319,43.539352417],"type":"Point"}
}