{
  "type": "Feature",
  "properties": {
    "iso:country":"ES",
    "sg:address":"Calle de Gonzalo Gallas, 37",
    "sg:city":"Granada",
    "sg:orig_category":"Doctores En Medicina",
    "sg:phone":"+34 958 27 19 54",
    "sg:postcode":"18003",
    "sg:province":"Granada",
    "wof:name":"Quesada Mu\u00f1oz Adolfo",
    "wof:placetype":"venue"
},
  "geometry": {"coordinates":[-3.6117389202,37.1816596985],"type":"Point"}
}