{
  "type": "Feature",
  "properties": {
    "addr:full":"Ctra Cuevas Bajas, Km. 0029,0 Cuevas San Marcos M\u00e1laga 29210",
    "addr:postcode":"29210",
    "addr:street":"Ctra Cuevas Bajas Km. 0029,0 Cuevas",
    "iso:country":"ES",
    "sg:address":"Ctra Cuevas Bajas, Km. 0029,0",
    "sg:city":"Cuevas San Marcos",
    "sg:orig_category":"Distribuci\u00d3n De Petr\u00d3leo Y Derivados",
    "sg:phone":"+34 952 72 85 56",
    "sg:postcode":"29210",
    "sg:province":"M\u00e1laga",
    "sg:website":"www.cepsa.es",
    "wof:name":"Gasolinera El Martillo S.l.",
    "wof:placetype":"venue"
},
  "geometry": {"coordinates":[-4.4189538956,37.2673568726],"type":"Point"}
}