{
  "type": "Feature",
  "properties": {
    "addr:full":"Escuelas, S/n Castrocontrigo Le\u00f3n 24735",
    "addr:housenumber":"s",
    "addr:postcode":"24735",
    "addr:street":"Escuelas;/ N Castrocontrigo Leo\u0301N",
    "iso:country":"ES",
    "sg:address":"Escuelas, S/n",
    "sg:city":"Castrocontrigo",
    "sg:orig_category":"Centros De Educaci\u00d3n Especial",
    "sg:phone":"+34 987 66 02 14",
    "sg:postcode":"24735",
    "sg:province":"Le\u00f3n",
    "wof:name":"Colegio Publico Comarcal",
    "wof:placetype":"venue"
},
  "geometry": {"coordinates":[-6.1874289513,42.1867446899],"type":"Point"}
}