{
  "type": "Feature",
  "properties": {
    "addr:full":"O Casal Do Mouro(ambroa), S/n Casal Do Mouro A Coru\u00f1a 15313",
    "addr:housenumber":"s",
    "addr:postcode":"15313",
    "addr:street":"O Casal Do Mouro Ambroa;/ N Casal Do Mouro A Corun\u0303A",
    "iso:country":"ES",
    "sg:address":"O Casal Do Mouro(ambroa), S/n",
    "sg:city":"Casal Do Mouro",
    "sg:orig_category":"Lecher\u00cdas",
    "sg:phone":"+34 981 77 63 01",
    "sg:postcode":"15313",
    "sg:province":"A Coru\u00f1a",
    "wof:name":"San Tirso De Ambroa Sociedad Cooperativa",
    "wof:placetype":"venue"
},
  "geometry": {"coordinates":[-8.0591535568,43.2852058411],"type":"Point"}
}