{
  "type": "Feature",
  "properties": {
    "iso:country":"ES",
    "sg:address":"Avda Paz, 167",
    "sg:city":"Yecla",
    "sg:orig_category":"Carnicer\u00cdas, Carnicer\u00cdas",
    "sg:phone":"+34 968 79 29 06",
    "sg:postcode":"30510",
    "sg:province":"Murcia",
    "wof:name":"Puche Perez Francisco Jose",
    "wof:placetype":"venue"
},
  "geometry": {"coordinates":[-1.1281789541,38.6151237488],"type":"Point"}
}