{
  "type": "Feature",
  "properties": {
    "iso:country":"ES",
    "sg:address":"Calle de Cruz De Lola, 5",
    "sg:city":"Corral Almaguer",
    "sg:orig_category":"Agricultores, Agricultores",
    "sg:phone":"+34 925 19 08 38",
    "sg:postcode":"45880",
    "sg:province":"Toledo",
    "wof:name":"Hermanos Lominchar S.a.t.",
    "wof:placetype":"venue"
},
  "geometry": {"coordinates":[-3.1751344204,39.761138916],"type":"Point"}
}