{
  "type": "Feature",
  "properties": {
    "addr:full":"Calle de Guevara, 10 Santander Cantabria 39001",
    "addr:housenumber":"10",
    "addr:postcode":"39001",
    "addr:street":"Calle De Guevara",
    "iso:country":"ES",
    "sg:address":"Calle de Guevara, 10",
    "sg:city":"Santander",
    "sg:orig_category":"Venta, Alquiler De Instrumentos Y Accesorios De M\u00dasica",
    "sg:phone":"+34 942 22 71 62",
    "sg:postcode":"39001",
    "sg:province":"Cantabria",
    "sg:website":"www.polimusica.es",
    "wof:name":"Bazar Musical S. A.",
    "wof:placetype":"venue"
},
  "geometry": {"coordinates":[-3.8092710972,43.4635505676],"type":"Point"}
}