{
  "type": "Feature",
  "properties": {
    "addr:full":"Avda Guadarrama, 2 Majadahonda Madrid 28220",
    "addr:housenumber":"2",
    "addr:postcode":"28220",
    "addr:street":"Avda Guadarrama",
    "iso:country":"ES",
    "sg:address":"Avda Guadarrama, 2",
    "sg:city":"Majadahonda",
    "sg:orig_category":"Inmobiliaria (agencias)",
    "sg:phone":"+34 916 38 02 44",
    "sg:postcode":"28220",
    "sg:province":"Madrid",
    "wof:name":"Garcia Guarido Maria Antonia",
    "wof:placetype":"venue"
},
  "geometry": {"coordinates":[-3.8721811771,40.4802818298],"type":"Point"}
}