{
  "type": "Feature",
  "properties": {
    "iso:country":"ES",
    "sg:address":"Calle de Virgen De Guia, S/n",
    "sg:city":"Hinojosa Del Duque",
    "sg:orig_category":"Negocio De Madera",
    "sg:phone":"+34 957 14 21 25",
    "sg:postcode":"14270",
    "sg:province":"C\u00f3rdoba",
    "wof:name":"Maderas De Hinojosa S.l.",
    "wof:placetype":"venue"
},
  "geometry": {"coordinates":[-5.1362538338,38.4939994812],"type":"Point"}
}