{
  "type": "Feature",
  "properties": {
    "iso:country":"ES",
    "sg:address":"Avda Rosalia De Castro (de), 44",
    "sg:city":"Santiago De Compostela",
    "sg:orig_category":"Centros Empresariales",
    "sg:phone":"+34 981 55 31 17",
    "sg:postcode":"15706",
    "sg:province":"La Coru\u00f1a",
    "wof:name":"Nor Prevencion S.l.",
    "wof:placetype":"venue"
},
  "geometry": {"coordinates":[-8.5513811111,42.8750419617],"type":"Point"}
}