{
  "type": "Feature",
  "properties": {
    "iso:country":"ES",
    "sg:address":"Plaz Rafael Alberti, 8",
    "sg:city":"Ansoain",
    "sg:orig_category":"Peluquer\u00cdas, Peluquer\u00cda Mixta",
    "sg:phone":"+34 948 14 22 22",
    "sg:postcode":"31013",
    "sg:province":"Navarra",
    "wof:name":"Izpura Perez Ana Maria",
    "wof:placetype":"venue"
},
  "geometry": {"coordinates":[-1.6428203583,42.8335227966],"type":"Point"}
}