{
  "type": "Feature",
  "properties": {
    "addr:full":"Plaz Mayor, 14 Iniesta Cuenca 16235",
    "addr:housenumber":"14",
    "addr:postcode":"16235",
    "addr:street":"Plaz Mayor",
    "iso:country":"ES",
    "sg:address":"Plaz Mayor, 14",
    "sg:city":"Iniesta",
    "sg:orig_category":"Reposter\u00cdas",
    "sg:phone":"+34 967 49 01 08",
    "sg:postcode":"16235",
    "sg:province":"Cuenca",
    "wof:name":"Lopez Correa Gabriel",
    "wof:placetype":"venue"
},
  "geometry": {"coordinates":[-1.7448840141,39.4404411316],"type":"Point"}
}