{
  "type": "Feature",
  "properties": {
    "iso:country":"ES",
    "sg:address":"Barrio El Soto, 103",
    "sg:city":"Iruz",
    "sg:orig_category":"Ense\u00d1anza, Formaci\u00d3n Profesional: Aprendizaje",
    "sg:phone":"+34 942 59 70 50",
    "sg:postcode":"39697",
    "sg:province":"Cantabria",
    "wof:name":"Obispado De Santander",
    "wof:placetype":"venue"
},
  "geometry": {"coordinates":[-3.9474210739,43.2660255432],"type":"Point"}
}