{
  "type": "Feature",
  "properties": {
    "iso:country":"ES",
    "sg:address":"Calle de Mayor, 1",
    "sg:city":"Tafalla",
    "sg:orig_category":"Ropa Para Ni\u00d1os (al Por Menor)",
    "sg:phone":"+34 948 70 04 47",
    "sg:postcode":"31300",
    "sg:province":"Navarra",
    "wof:name":"Martino Martino Braulio",
    "wof:placetype":"venue"
},
  "geometry": {"coordinates":[-1.6755779982,42.5275878906],"type":"Point"}
}