{
  "type": "Feature",
  "properties": {
    "addr:full":"Calle de Tomas De Iriarte, 9 Arguineguin Las Palmas 35120",
    "addr:housenumber":"9",
    "addr:postcode":"35120",
    "addr:street":"Calle De Tomas De Iriarte;Palmas",
    "iso:country":"ES",
    "sg:address":"Calle de Tomas De Iriarte, 9",
    "sg:city":"Arguineguin",
    "sg:orig_category":"Cl\u00cdnicas Dentales",
    "sg:phone":"+34 928 15 02 62",
    "sg:postcode":"35120",
    "sg:province":"Las Palmas",
    "wof:name":"Garcia Perez Silvia Esther",
    "wof:placetype":"venue"
},
  "geometry": {"coordinates":[-15.6829957962,27.7604484558],"type":"Point"}
}