{
  "type": "Feature",
  "properties": {
    "addr:full":"Rbla Catalunya, 68 Barcelona Barcelona 08007",
    "addr:housenumber":"68",
    "addr:postcode":"08007",
    "addr:street":"Rbla Catalunya",
    "iso:country":"ES",
    "sg:address":"Rbla Catalunya, 68",
    "sg:city":"Barcelona",
    "sg:orig_category":"Albergues",
    "sg:phone":"+34 932 15 42 53",
    "sg:postcode":"08007",
    "sg:province":"Barcelona",
    "sg:website":"www.cromaticabcn.com",
    "wof:name":"Cromatica Regalos S.l.",
    "wof:placetype":"venue"
},
  "geometry": {"coordinates":[2.1629300117,41.3917732239],"type":"Point"}
}