{
  "type": "Feature",
  "properties": {
    "iso:country":"ES",
    "sg:address":"Carrer de Pedregar, 6",
    "sg:city":"Sabadell",
    "sg:orig_category":"Arquitectos",
    "sg:phone":"+34 937 45 16 80",
    "sg:postcode":"08202",
    "sg:province":"Barcelona",
    "wof:name":"Gorina I Farres Arquitectes S.l.",
    "wof:placetype":"venue"
},
  "geometry": {"coordinates":[2.1091051102,41.5467681885],"type":"Point"}
}