{
  "type": "Feature",
  "properties": {
    "addr:full":"Carrer de Pallars, 164 Barcelona Barcelona 08005",
    "addr:housenumber":"164",
    "addr:postcode":"08005",
    "addr:street":"Carrer De Pallars",
    "iso:country":"ES",
    "sg:address":"Carrer de Pallars, 164",
    "sg:city":"Barcelona",
    "sg:orig_category":"M\u00c1quinas De Coser Y De Hacer Punto (al Por Mayor)",
    "sg:phone":"+34 933 00 17 75",
    "sg:postcode":"08005",
    "sg:province":"Barcelona",
    "wof:name":"Sanchez Martinez Jose",
    "wof:placetype":"venue"
},
  "geometry": {"coordinates":[2.1957650185,41.399433136],"type":"Point"}
}