{
  "type": "Feature",
  "properties": {
    "iso:country":"ES",
    "sg:address":"Avda Ris, 61",
    "sg:city":"Noja",
    "sg:orig_category":"Inmobiliaria (agencias)",
    "sg:phone":"+34 942 67 54 32",
    "sg:postcode":"39180",
    "sg:province":"Cantabria",
    "wof:name":"Giannitrapani Ulacia Alberto",
    "wof:placetype":"venue"
},
  "geometry": {"coordinates":[-3.5284490585,43.4797515869],"type":"Point"}
}