{
  "type": "Feature",
  "properties": {
    "iso:country":"ES",
    "sg:address":"Calle de Fray Diego De Cadiz, 28",
    "sg:city":"Sevilla",
    "sg:orig_category":"Empresas De Carpinter\u00cda De Madera",
    "sg:phone":"+34 954 38 96 07",
    "sg:postcode":"41003",
    "sg:province":"Sevilla",
    "wof:name":"Celdran Alvarez Jose Antonio",
    "wof:placetype":"venue"
},
  "geometry": {"coordinates":[-5.9870457649,37.4005699158],"type":"Point"}
}