{
  "type": "Feature",
  "properties": {
    "addr:full":"Calle de Rodriguez San Pedro, 47 Madrid Madrid 28015",
    "addr:housenumber":"47",
    "addr:postcode":"madrid;28015",
    "addr:street":"Calle De Rodriguez San Pedro",
    "iso:country":"ES",
    "sg:address":"Calle de Rodriguez San Pedro, 47",
    "sg:city":"Madrid",
    "sg:orig_category":"Farmacias",
    "sg:phone":"+34 915 49 65 75",
    "sg:postcode":"28015",
    "sg:province":"Madrid",
    "wof:name":"Carril Batalla Maria Teresa",
    "wof:placetype":"venue"
},
  "geometry": {"coordinates":[-3.7139019966,40.4316711426],"type":"Point"}
}