{
  "type": "Feature",
  "properties": {
    "iso:country":"ES",
    "sg:address":"Rond Campoamor-campoamor, 1",
    "sg:city":"Dehesa Campoamor",
    "sg:orig_category":"Inmobiliaria (agencias)",
    "sg:phone":"+34 965 32 06 36",
    "sg:postcode":"03189",
    "sg:province":"Alicante",
    "wof:name":"Agencia Inmobiliaria Henarejos C.b.",
    "wof:placetype":"venue"
},
  "geometry": {"coordinates":[-0.4810059965,38.3452033997],"type":"Point"}
}