{
  "type": "Feature",
  "properties": {
    "addr:full":"Calle de Pere Morell, S/n Alzira Valencia 46600",
    "addr:housenumber":"s / n",
    "addr:postcode":"46600",
    "addr:street":"Calle De Pere Morell",
    "iso:country":"ES",
    "sg:address":"Calle de Pere Morell, S/n",
    "sg:city":"Alzira",
    "sg:orig_category":"Deportes Y Programas De Aventura",
    "sg:phone":"+34 962 40 03 26",
    "sg:postcode":"46600",
    "sg:province":"Valencia",
    "wof:name":"Club De Correr La Rabosa",
    "wof:placetype":"venue"
},
  "geometry": {"coordinates":[-0.4401189983,39.1487541199],"type":"Point"}
}