{
  "type": "Feature",
  "properties": {
    "addr:full":"Calle de Angel, 10 Albu\u00f1ol Granada 18700",
    "addr:housenumber":"10",
    "addr:postcode":"18700",
    "addr:street":"Calle De Angel",
    "iso:country":"ES",
    "sg:address":"Calle de Angel, 10",
    "sg:city":"Albu\u00f1ol",
    "sg:orig_category":"Cr\u00cda De Animales",
    "sg:phone":"+34 958 82 61 25",
    "sg:postcode":"18700",
    "sg:province":"Granada",
    "wof:name":"Garcia Diaz Juan",
    "wof:placetype":"venue"
},
  "geometry": {"coordinates":[-3.2040436268,36.7918128967],"type":"Point"}
}