{
  "type": "Feature",
  "properties": {
    "addr:full":"Carr Moli, 2 Osso Sio Lleida 25318",
    "addr:housenumber":"2",
    "addr:postcode":"25318",
    "addr:street":"Carr Moli",
    "iso:country":"ES",
    "sg:address":"Carr Moli, 2",
    "sg:city":"Osso Sio",
    "sg:orig_category":"Art\u00cdculos De Madera (fabricaci\u00d3n Y Al Por Mayor)",
    "sg:phone":"+34 973 39 27 37",
    "sg:postcode":"25318",
    "sg:province":"Lleida",
    "wof:name":"Balasch Tolosa Joan",
    "wof:placetype":"venue"
},
  "geometry": {"coordinates":[1.1215180159,41.776927948],"type":"Point"}
}