{
  "type": "Feature",
  "properties": {
    "addr:full":"Calle de Colombia, 12 Madrid Madrid 28016",
    "addr:housenumber":"12",
    "addr:postcode":"madrid;28016",
    "addr:street":"Calle De Colombia",
    "iso:country":"ES",
    "sg:address":"Calle de Colombia, 12",
    "sg:city":"Madrid",
    "sg:orig_category":"Agencias Y Agentes Comerciales, Representantes",
    "sg:phone":"+34 913 44 14 74",
    "sg:postcode":"28016",
    "sg:province":"Madrid",
    "wof:name":"Cior S.l.",
    "wof:placetype":"venue"
},
  "geometry": {"coordinates":[-3.6760599613,40.4570808411],"type":"Point"}
}