{
  "type": "Feature",
  "properties": {
    "addr:full":"Calle de Manifestacion, 13 Zaragoza Zaragoza 50003",
    "addr:housenumber":"13",
    "addr:postcode":"50003",
    "addr:street":"Calle De Manifestacion",
    "iso:country":"ES",
    "sg:address":"Calle de Manifestacion, 13",
    "sg:city":"Zaragoza",
    "sg:orig_category":"Molduras, Junquillos, Listones Y Molduras Perforadas",
    "sg:phone":"+34 976 29 70 20",
    "sg:postcode":"50003",
    "sg:province":"Zaragoza",
    "wof:name":"Sanchez Cordoba S.c.",
    "wof:placetype":"venue"
},
  "geometry": {"coordinates":[-0.8810380101,41.656124115],"type":"Point"}
}