{
  "type": "Feature",
  "properties": {
    "iso:country":"ES",
    "sg:address":"Calle de Caunedo, 30",
    "sg:city":"Madrid",
    "sg:orig_category":"Cl\u00cdnicas Dentales",
    "sg:phone":"+34 913 04 91 75",
    "sg:postcode":"28037",
    "sg:province":"Madrid",
    "wof:name":"Clinica El Carmen Cdad.",
    "wof:placetype":"venue"
},
  "geometry": {"coordinates":[-3.6347417831,40.4377441406],"type":"Point"}
}