{
  "type": "Feature",
  "properties": {
    "iso:country":"ES",
    "sg:address":"Mcdo Nuevo, S/n",
    "sg:city":"Iru\u00f1a",
    "sg:orig_category":"Reposter\u00cdas",
    "sg:phone":"+34 948 23 39 75",
    "sg:postcode":"31004",
    "sg:province":"Navarra",
    "wof:name":"Burguete Baredelena Alfonso",
    "wof:placetype":"venue"
},
  "geometry": {"coordinates":[-1.6437540054,42.81275177],"type":"Point"}
}