{
  "type": "Feature",
  "properties": {
    "iso:country":"ES",
    "sg:address":"Calle de Manuel De Falla, 4",
    "sg:city":"Morales Toro",
    "sg:orig_category":"Formaci\u00d3n Continuada (variada)",
    "sg:phone":"+34 980 69 67 34",
    "sg:postcode":"49810",
    "sg:province":"Zamora",
    "wof:name":"Ayuntamiento De Morales De Toro",
    "wof:placetype":"venue"
},
  "geometry": {"coordinates":[-5.3067340851,41.5374908447],"type":"Point"}
}