{
  "type": "Feature",
  "properties": {
    "iso:country":"ES",
    "sg:address":"Ptda Jubalcoy, 140",
    "sg:city":"Elche",
    "sg:orig_category":"Fabricaci\u00d3n De Enlosados, Soler\u00cdas",
    "sg:phone":"+34 965 42 19 98",
    "sg:postcode":"03295",
    "sg:province":"Alicante",
    "wof:name":"Pavimentos Elche Logistic",
    "wof:placetype":"venue"
},
  "geometry": {"coordinates":[-0.6350679994,38.2515106201],"type":"Point"}
}