{
  "type": "Feature",
  "properties": {
    "iso:country":"ES",
    "sg:address":"Calle de Serventia (la), S/n",
    "sg:city":"Matorral",
    "sg:orig_category":"Oficinas: Suministros Para (fabricaci\u00d3n, Al Por Mayor)",
    "sg:phone":"+34 928 86 10 20",
    "sg:postcode":"35610",
    "sg:province":"Las Palmas",
    "wof:name":"Suministradora Canaria De Oficina S.l.",
    "wof:placetype":"venue"
},
  "geometry": {"coordinates":[-13.8783950806,28.4352455139],"type":"Point"}
}