{
  "type": "Feature",
  "properties": {
    "addr:full":"Calle de Ricardo Ortiz, 4 Madrid Madrid 28017",
    "addr:housenumber":"4",
    "addr:postcode":"28017",
    "addr:street":"Calle De Ricardo Ortiz",
    "iso:country":"ES",
    "sg:address":"Calle de Ricardo Ortiz, 4",
    "sg:city":"Madrid",
    "sg:orig_category":"Ingenier\u00cda, Centros De Estudios (diversos)",
    "sg:phone":"+34 913 14 19 17",
    "sg:postcode":"28017",
    "sg:province":"Madrid",
    "wof:name":"Actividades De Tecnologia Y Proyectos S.a.",
    "wof:placetype":"venue"
},
  "geometry": {"coordinates":[-3.657999754,40.4302330017],"type":"Point"}
}