{
  "type": "Feature",
  "properties": {
    "addr:full":"Trva Avenida De Madrid, 7 Logro\u00f1o La Rioja 26006",
    "addr:housenumber":"7",
    "addr:postcode":"26006",
    "addr:street":"Avenida De Madrid;Rioja",
    "iso:country":"ES",
    "sg:address":"Trva Avenida De Madrid, 7",
    "sg:city":"Logro\u00f1o",
    "sg:orig_category":"Fotograf\u00cda Art\u00cdstica Y Retratos",
    "sg:phone":"+34 941 49 94 31",
    "sg:postcode":"26006",
    "sg:province":"La Rioja",
    "wof:name":"Fotocenter Rioja S.a.",
    "wof:placetype":"venue"
},
  "geometry": {"coordinates":[-2.4506618977,42.4399375916],"type":"Point"}
}