{
  "type": "Feature",
  "properties": {
    "addr:full":"Avda Soldevilla Vazquez, 16 Posadas C\u00f3rdoba 14730",
    "addr:housenumber":"16;co\u0301rdoba",
    "addr:postcode":"14730",
    "addr:street":"Avda Soldevilla Vazquez",
    "iso:country":"ES",
    "sg:address":"Avda Soldevilla Vazquez, 16",
    "sg:city":"Posadas",
    "sg:orig_category":"Aparatos E Instalaci\u00d3n De Regad\u00cdos",
    "sg:phone":"+34 957 63 06 63",
    "sg:postcode":"14730",
    "sg:province":"C\u00f3rdoba",
    "wof:name":"Pulido Aguilar Jesus",
    "wof:placetype":"venue"
},
  "geometry": {"coordinates":[-97.78224945069999,45.7040786743],"type":"Point"}
}