{
  "type": "Feature",
  "properties": {
    "addr:full":"Plaz Centro Segoviano De Madrid (del), 4 Segovia Segovia 40004",
    "addr:postcode":"40004",
    "addr:street":"Plaz",
    "iso:country":"ES",
    "sg:address":"Plaz Centro Segoviano De Madrid (del), 4",
    "sg:city":"Segovia",
    "sg:orig_category":"Negocio De Madera",
    "sg:phone":"+34 921 42 13 23",
    "sg:postcode":"40004",
    "sg:province":"Segovia",
    "wof:name":"Gutierrez Torrego Mariano",
    "wof:placetype":"venue"
},
  "geometry": {"coordinates":[-4.1009368896,40.9435691833],"type":"Point"}
}