{
  "type": "Feature",
  "properties": {
    "addr:full":"Carrer de Velazquez, 40 Palleja Barcelona 08780",
    "addr:housenumber":"40",
    "addr:postcode":"08780",
    "addr:street":"Carrer De Velazquez",
    "iso:country":"ES",
    "sg:address":"Carrer de Velazquez, 40",
    "sg:city":"Palleja",
    "sg:orig_category":"Alquiler De V\u00cddeo",
    "sg:phone":"+34 936 63 01 16",
    "sg:postcode":"08780",
    "sg:province":"Barcelona",
    "wof:name":"Rivas Ramos Juana",
    "wof:placetype":"venue"
},
  "geometry": {"coordinates":[1.9996199608,41.4240989685],"type":"Point"}
}