{
  "type": "Feature",
  "properties": {
    "iso:country":"ES",
    "sg:address":"Via Julia, 119",
    "sg:city":"Barcelona",
    "sg:orig_category":"\u00d3ptica: Instrumentos (fabricaci\u00d3n)",
    "sg:phone":"+34 932 76 91 66",
    "sg:postcode":"08042",
    "sg:province":"Barcelona",
    "wof:name":"H2o Optical S.l.",
    "wof:placetype":"venue"
},
  "geometry": {"coordinates":[2.1777141094,41.4424819946],"type":"Point"}
}