{
  "type": "Feature",
  "properties": {
    "addr:full":"Calle de Granada, 24 Do\u00e7a Mencia C\u00f3rdoba 14860",
    "addr:housenumber":"24",
    "addr:postcode":"14860",
    "addr:street":"Calle De Granada;Co\u0301Rdoba",
    "iso:country":"ES",
    "sg:address":"Calle de Granada, 24",
    "sg:city":"Do\u00e7a Mencia",
    "sg:orig_category":"Notarios",
    "sg:phone":"+34 957 67 61 71",
    "sg:postcode":"14860",
    "sg:province":"C\u00f3rdoba",
    "wof:name":"Priego Sancho Rosalia",
    "wof:placetype":"venue"
},
  "geometry": {"coordinates":[-4.3577737808,37.5546150208],"type":"Point"}
}