{
  "type": "Feature",
  "properties": {
    "addr:full":"Carrer de Sarriera, 42 Vilafranca Penedes Barcelona 08720",
    "addr:housenumber":"42",
    "addr:postcode":"08720",
    "addr:street":"Carrer De Sarriera",
    "iso:country":"ES",
    "sg:address":"Carrer de Sarriera, 42",
    "sg:city":"Vilafranca Penedes",
    "sg:orig_category":"Productos Fitosanitarios (negocio, Aplicaci\u00d3n)",
    "sg:phone":"+34 938 90 36 22",
    "sg:postcode":"08720",
    "sg:province":"Barcelona",
    "wof:name":"Agrosystem S.a.",
    "wof:placetype":"venue"
},
  "geometry": {"coordinates":[1.7051662207,41.344783783],"type":"Point"}
}