{
  "type": "Feature",
  "properties": {
    "iso:country":"ES",
    "sg:address":"Plaz Zaldiaran, 16",
    "sg:city":"Vitoria-gasteiz",
    "sg:orig_category":"Librer\u00cdas",
    "sg:phone":"+34 945 24 33 99",
    "sg:postcode":"01012",
    "sg:province":"\u00c1lava",
    "wof:name":"Moreno Alcaraz Jose Antonio",
    "wof:placetype":"venue"
},
  "geometry": {"coordinates":[-2.6783568859,42.851146698],"type":"Point"}
}