{
  "type": "Feature",
  "properties": {
    "addr:full":"Calle de Garay Juan De, 6 Bilbao Vizcaya 48003",
    "addr:housenumber":"6",
    "addr:postcode":"48003",
    "addr:street":"Calle De Garay Juan De",
    "iso:country":"ES",
    "sg:address":"Calle de Garay Juan De, 6",
    "sg:city":"Bilbao",
    "sg:orig_category":"Ense\u00d1anza, Formaci\u00d3n Profesional: Aprendizaje",
    "sg:phone":"+34 944 22 17 76",
    "sg:postcode":"48003",
    "sg:province":"Vizcaya",
    "wof:name":"Delegacion Del Instituto Social De Las Fuerzas Armadas",
    "wof:placetype":"venue"
},
  "geometry": {"coordinates":[-2.9250490665,43.2430305481],"type":"Point"}
}