{
  "type": "Feature",
  "properties": {
    "addr:full":"Calle de Luciano Lopez Ferrer, 3 Villena Alicante 03400",
    "addr:housenumber":"3",
    "addr:postcode":"03400",
    "addr:street":"Calle De Luciano Lopez Ferrer",
    "iso:country":"ES",
    "sg:address":"Calle de Luciano Lopez Ferrer, 3",
    "sg:city":"Villena",
    "sg:orig_category":"Librer\u00cdas",
    "sg:phone":"+34 965 80 61 32",
    "sg:postcode":"03400",
    "sg:province":"Alicante",
    "wof:name":"Hurtado Carrera Juan Lorenzo",
    "wof:placetype":"venue"
},
  "geometry": {"coordinates":[-0.8652819991,38.6315231323],"type":"Point"}
}