{
  "type": "Feature",
  "properties": {
    "addr:full":"Carrer de Valero, 12 Barcelona Barcelona 08021",
    "addr:housenumber":"12",
    "addr:postcode":"08021",
    "addr:street":"Carrer De Valero",
    "iso:country":"ES",
    "sg:address":"Carrer de Valero, 12",
    "sg:city":"Barcelona",
    "sg:orig_category":"Controles De Edificaci\u00d3n (construcci\u00d3n, Seguridad)",
    "sg:phone":"+34 932 01 95 73",
    "sg:postcode":"08021",
    "sg:province":"Barcelona",
    "wof:name":"Comunidad De Propietarios Valero 12",
    "wof:placetype":"venue"
},
  "geometry": {"coordinates":[2.1388239861,41.3961181641],"type":"Point"}
}