{
  "type": "Feature",
  "properties": {
    "addr:full":"Pg Mallorca, 14 Palma Islas Baleares 07012",
    "addr:housenumber":"14",
    "addr:postcode":"07012",
    "addr:street":"Pg Mallorca",
    "iso:country":"ES",
    "sg:address":"Pg Mallorca, 14",
    "sg:city":"Palma",
    "sg:orig_category":"Peluquer\u00cdas, Peluquer\u00cda Mixta",
    "sg:phone":"+34 971 46 70 21",
    "sg:postcode":"07012",
    "sg:province":"Islas Baleares",
    "wof:name":"Segura Cortes Francisco",
    "wof:placetype":"venue"
},
  "geometry": {"coordinates":[2.6424660683,39.5726966858],"type":"Point"}
}