{
  "type": "Feature",
  "properties": {
    "iso:country":"ES",
    "sg:address":"Carrer de Valencia, 245",
    "sg:city":"Barcelona",
    "sg:orig_category":"M\u00c9dicos: Estomatolog\u00cda",
    "sg:phone":"+34 902 30 36 36",
    "sg:postcode":"08007",
    "sg:province":"Barcelona",
    "sg:website":"www.ocaeurope.com",
    "wof:name":"Orthodontic S.a.",
    "wof:placetype":"venue"
},
  "geometry": {"coordinates":[2.1627459526,41.392414093],"type":"Point"}
}