{
  "type": "Feature",
  "properties": {
    "addr:full":"Carrer de Miramar, 31 Roda De Bara Tarragona 43883",
    "addr:housenumber":"31",
    "addr:postcode":"43883",
    "addr:street":"Carrer De Miramar",
    "iso:country":"ES",
    "sg:address":"Carrer de Miramar, 31",
    "sg:city":"Roda De Bara",
    "sg:orig_category":"Inform\u00c1tica (estudios, Servicios, Asesor\u00cda, Formaci\u00d3n)",
    "sg:phone":"+34 977 80 96 02",
    "sg:postcode":"43883",
    "sg:province":"Tarragona",
    "wof:name":"Grupalia Internet S.a.",
    "wof:placetype":"venue"
},
  "geometry": {"coordinates":[1.4559899569,41.1848487854],"type":"Point"}
}