{
  "type": "Feature",
  "properties": {
    "addr:full":"Calle de Luis Fuentes Bejarano, S/n Sevilla Sevilla 41020",
    "addr:housenumber":"s / n",
    "addr:postcode":"41020",
    "addr:street":"Calle De Luis Fuentes Bejarano",
    "iso:country":"ES",
    "sg:address":"Calle de Luis Fuentes Bejarano, S/n",
    "sg:city":"Sevilla",
    "sg:orig_category":"Electricidad, Electr\u00d3nica: Suministros (al Por Menor)",
    "sg:phone":"+34 954 26 00 56",
    "sg:postcode":"41020",
    "sg:province":"Sevilla",
    "wof:name":"Visa Sur S.l.",
    "wof:placetype":"venue"
},
  "geometry": {"coordinates":[-5.9451708794,37.4085235596],"type":"Point"}
}