{
  "type": "Feature",
  "properties": {
    "addr:full":"Carrer de Tresols, 28 Gava Barcelona 08850",
    "addr:housenumber":"28",
    "addr:postcode":"08850",
    "addr:street":"Carrer De Tresols",
    "iso:country":"ES",
    "sg:address":"Carrer de Tresols, 28",
    "sg:city":"Gava",
    "sg:orig_category":"Frutas, Legumbres Frescas Y Tempranas (al Por Menor)",
    "sg:phone":"+34 936 62 19 27",
    "sg:postcode":"08850",
    "sg:province":"Barcelona",
    "wof:name":"Figueras Olle Pedro",
    "wof:placetype":"venue"
},
  "geometry": {"coordinates":[2.0009989738,41.3065490723],"type":"Point"}
}