{
  "type": "Feature",
  "properties": {
    "iso:country":"ES",
    "sg:address":"Carrer de Joan Miro, 22",
    "sg:city":"S. Adria Besos",
    "sg:orig_category":"Comercio De Piezas De Recambio Y De Accesorios De Veh\u00cdculos, Veh\u00cdculos Industriales",
    "sg:phone":"+34 934 62 22 22",
    "sg:postcode":"08930",
    "sg:province":"Barcelona",
    "wof:name":"Industrial Arcol S.a.",
    "wof:placetype":"venue"
},
  "geometry": {"coordinates":[2.230424881,41.429813385],"type":"Point"}
}