{
  "type": "Feature",
  "properties": {
    "iso:country":"ES",
    "sg:address":"Calle de Mayor, 39",
    "sg:city":"Pozo Almoguera",
    "sg:orig_category":"Sanatorios M\u00c9dico",
    "sg:phone":"+34 949 38 00 59",
    "sg:postcode":"19112",
    "sg:province":"Guadalajara",
    "wof:name":"Ayuntamiento Del Pozo De Almoguera",
    "wof:placetype":"venue"
},
  "geometry": {"coordinates":[-3.0290439129,40.3427009583],"type":"Point"}
}