{
  "type": "Feature",
  "properties": {
    "iso:country":"ES",
    "sg:address":"Carr Baix, 8",
    "sg:city":"Mercadal",
    "sg:orig_category":"Panader\u00cdas, Panader\u00cdas",
    "sg:phone":"+34 971 37 50 74",
    "sg:postcode":"07740",
    "sg:province":"Islas Baleares",
    "wof:name":"Pastisseria Ca'n Pons S.l",
    "wof:placetype":"venue"
},
  "geometry": {"coordinates":[4.1529397964,40.00730896],"type":"Point"}
}