{
  "type": "Feature",
  "properties": {
    "iso:country":"ES",
    "sg:address":"Av Valencia, 12",
    "sg:city":"Pu\u00e7ol",
    "sg:orig_category":"Bancos",
    "sg:phone":"+34 961 46 48 15",
    "sg:postcode":"46530",
    "sg:province":"Valencia",
    "wof:name":"Banco Popular Espa\u00f1ol",
    "wof:placetype":"venue"
},
  "geometry": {"coordinates":[-0.3062790036,39.6172218323],"type":"Point"}
}