{
  "type": "Feature",
  "properties": {
    "iso:country":"ES",
    "sg:address":"Avda Endarlaza Hiribidea, 9",
    "sg:city":"Irun",
    "sg:orig_category":"Alimentaci\u00d3n General (al Por Menor)",
    "sg:phone":"+34 943 62 10 49",
    "sg:postcode":"20305",
    "sg:province":"Guip\u00f9zcoa",
    "wof:name":"Solis Coscojuela Maria Del Carmen",
    "wof:placetype":"venue"
},
  "geometry": {"coordinates":[-1.7622300386,43.3427085876],"type":"Point"}
}