{
  "type": "Feature",
  "properties": {
    "addr:full":"Av Isidor Macabich, 42 Eivissa Islas Baleares 07800",
    "addr:housenumber":"42",
    "addr:postcode":"07800",
    "addr:street":"Av Isidor Macabich",
    "iso:country":"ES",
    "sg:address":"Av Isidor Macabich, 42",
    "sg:city":"Eivissa",
    "sg:orig_category":"Caf\u00c9s, Bares, Cervecer\u00cdas",
    "sg:phone":"+34 971 31 56 11",
    "sg:postcode":"07800",
    "sg:province":"Islas Baleares",
    "wof:name":"Costa Roig Jose",
    "wof:placetype":"venue"
},
  "geometry": {"coordinates":[1.4265660048,38.9101791382],"type":"Point"}
}