{
  "type": "Feature",
  "properties": {
    "addr:full":"Calle de Rio Valdecarza, 9 Poligono Sta M. De Benquerencia Toledo 45007",
    "addr:housenumber":"9 poligono",
    "addr:postcode":"45007",
    "addr:street":"Calle De Rio Valdecarza;Sta M. De Benquerencia",
    "iso:country":"ES",
    "sg:address":"Calle de Rio Valdecarza, 9",
    "sg:city":"Poligono Sta M. De Benquerencia",
    "sg:orig_category":"Puros, Cigarrillos Y Tabaco (fabricaci\u00d3n, Al Por Mayor)",
    "sg:phone":"+34 925 23 33 89",
    "sg:postcode":"45007",
    "sg:province":"Toledo",
    "wof:name":"Lopez Seco Jose Miguel",
    "wof:placetype":"venue"
},
  "geometry": {"coordinates":[-4.0244760513,39.8567771912],"type":"Point"}
}