{
  "type": "Feature",
  "properties": {
    "iso:country":"ES",
    "sg:address":"Calle de Evora, 1",
    "sg:city":"Jerez De La Frontera",
    "sg:orig_category":"Empresas De Pintura Y Revestimientos",
    "sg:phone":"+34 956 33 39 20",
    "sg:postcode":"11402",
    "sg:province":"C\u00e1diz",
    "wof:name":"Rubiales Rios Francisco",
    "wof:placetype":"venue"
},
  "geometry": {"coordinates":[-6.134803772,36.6811485291],"type":"Point"}
}