{
  "type": "Feature",
  "properties": {
    "addr:full":"Rua Ande, Km. 0234,6 Ande Pontevedra 36619",
    "addr:postcode":"36619",
    "addr:street":"Rua Ande Km. 0234,6",
    "iso:country":"ES",
    "sg:address":"Rua Ande, Km. 0234,6",
    "sg:city":"Ande",
    "sg:orig_category":"Distribuci\u00d3n De Petr\u00d3leo Y Derivados",
    "sg:phone":"+34 986 51 27 03",
    "sg:postcode":"36619",
    "sg:province":"Pontevedra",
    "wof:name":"Galpgest Petrogal Estaciones De Servicio S.l.u.",
    "wof:placetype":"venue"
},
  "geometry": {"coordinates":[-8.7645044327,42.5797958374],"type":"Point"}
}