{
  "type": "Feature",
  "properties": {
    "addr:full":"Calle de Villa De Rota, 12 Cordoba C\u00f3rdoba 14005",
    "addr:housenumber":"12",
    "addr:postcode":"14005",
    "addr:street":"Calle De Villa De Rota;Co\u0301Rdoba",
    "iso:country":"ES",
    "sg:address":"Calle de Villa De Rota, 12",
    "sg:city":"Cordoba",
    "sg:orig_category":"Farmacias",
    "sg:phone":"+34 957 41 24 04",
    "sg:postcode":"14005",
    "sg:province":"C\u00f3rdoba",
    "wof:name":"Gonzalez Galan Rafaela",
    "wof:placetype":"venue"
},
  "geometry": {"coordinates":[-4.7901139259,37.8863983154],"type":"Point"}
}