{
  "type": "Feature",
  "properties": {
    "addr:full":"Afores, S/n Casavells Girona 17121",
    "addr:housenumber":"s / n",
    "addr:postcode":"17121",
    "addr:street":"Afores",
    "iso:country":"ES",
    "sg:address":"Afores, S/n",
    "sg:city":"Casavells",
    "sg:orig_category":"Cr\u00cda De Animales",
    "sg:phone":"+34 972 63 03 85",
    "sg:postcode":"17121",
    "sg:province":"Girona",
    "wof:name":"Agricola Rovira Pont S.c.",
    "wof:placetype":"venue"
},
  "geometry": {"coordinates":[3.0325880051,42.0000495911],"type":"Point"}
}