{
  "type": "Feature",
  "properties": {
    "iso:country":"ES",
    "sg:address":"Carrer de Bailen, 189",
    "sg:city":"Barcelona",
    "sg:orig_category":"Fabricaci\u00d3n De Muebles",
    "sg:phone":"+34 934 59 14 66",
    "sg:postcode":"08037",
    "sg:province":"Barcelona",
    "wof:name":"3p Mobel 3 S. L.",
    "wof:placetype":"venue"
},
  "geometry": {"coordinates":[2.164371,41.401634],"type":"Point"}
}