{
  "type": "Feature",
  "properties": {
    "addr:full":"Calle de Santa Barbara, 54 Nules Castell\u00f3n 12520",
    "addr:housenumber":"54",
    "addr:postcode":"12520",
    "addr:street":"Calle De Santa Barbara",
    "iso:country":"ES",
    "sg:address":"Calle de Santa Barbara, 54",
    "sg:city":"Nules",
    "sg:orig_category":"Electricidad: Instaladores",
    "sg:phone":"+34 964 67 07 95",
    "sg:postcode":"12520",
    "sg:province":"Castell\u00f3n",
    "wof:name":"Hueso Ripolles Jose",
    "wof:placetype":"venue"
},
  "geometry": {"coordinates":[-0.1570529938,39.8544425964],"type":"Point"}
}