{
  "type": "Feature",
  "properties": {
    "addr:full":"Calle de Augusto Junquera, 3 Oviedo Asturias 33012",
    "addr:housenumber":"3",
    "addr:postcode":"33012",
    "addr:street":"Calle De Augusto Junquera",
    "iso:country":"ES",
    "sg:address":"Calle de Augusto Junquera, 3",
    "sg:city":"Oviedo",
    "sg:orig_category":"Aparatos, Sistemas De Tele",
    "sg:phone":"+34 985 11 86 41",
    "sg:postcode":"33012",
    "sg:province":"Asturias",
    "sg:website":"www.plettac-seguridad.com",
    "wof:name":"Plettac Seguridad Y Sistemas S.a.",
    "wof:placetype":"venue"
},
  "geometry": {"coordinates":[-5.8529729843,43.3702507019],"type":"Point"}
}