{
  "type": "Feature",
  "properties": {
    "iso:country":"ES",
    "sg:address":"Avda Portugal (de), 89",
    "sg:city":"Ourense",
    "sg:orig_category":"Peluquer\u00cdas, Peluquer\u00cda Mixta",
    "sg:phone":"+34 988 25 36 78",
    "sg:postcode":"32002",
    "sg:province":"Ourense",
    "wof:name":"Rodriguez Estevez Juan Carlos",
    "wof:placetype":"venue"
},
  "geometry": {"coordinates":[-7.8693008423,42.3336219788],"type":"Point"}
}