{
  "type": "Feature",
  "properties": {
    "iso:country":"ES",
    "sg:address":"Calle de Maria Jesus Los Arcos, S/n",
    "sg:city":"Carcar",
    "sg:orig_category":"Centros De Educaci\u00d3n Especial",
    "sg:phone":"+34 948 67 47 73",
    "sg:postcode":"31579",
    "sg:province":"Navarra",
    "wof:name":"Ayuntamiento De Carcar",
    "wof:placetype":"venue"
},
  "geometry": {"coordinates":[-1.97831738,42.3937530518],"type":"Point"}
}