{
  "type": "Feature",
  "properties": {
    "addr:full":"Carrer de Joan Guell, 43 Barcelona Barcelona 08028",
    "addr:housenumber":"43",
    "addr:postcode":"08028",
    "addr:street":"Carrer De Joan Guell",
    "iso:country":"ES",
    "sg:address":"Carrer de Joan Guell, 43",
    "sg:city":"Barcelona",
    "sg:orig_category":"Comit\u00c9s De Organizaci\u00d3n De Exposiciones, Ferias, Salones",
    "sg:phone":"+34 934 91 47 68",
    "sg:postcode":"08028",
    "sg:province":"Barcelona",
    "wof:name":"Protocol Congressos S.l.",
    "wof:placetype":"venue"
},
  "geometry": {"coordinates":[2.1335029602,41.3779754639],"type":"Point"}
}