{
  "type": "Feature",
  "properties": {
    "addr:full":"Avda Beiramar, 25 Vigo Pontevedra 36202",
    "addr:housenumber":"25",
    "addr:postcode":"36202",
    "addr:street":"Avda Beiramar",
    "iso:country":"ES",
    "sg:address":"Avda Beiramar, 25",
    "sg:city":"Vigo",
    "sg:orig_category":"Congelados: Productos Alimentarios (al Por Menor)",
    "sg:phone":"+34 986 21 00 53",
    "sg:postcode":"36202",
    "sg:province":"Pontevedra",
    "wof:name":"Laplaza De Congelados S.a.",
    "wof:placetype":"venue"
},
  "geometry": {"coordinates":[-8.7357120514,42.2303657532],"type":"Point"}
}