{
  "type": "Feature",
  "properties": {
    "iso:country":"ES",
    "sg:address":"Calle de Isaac Albeniz, 34",
    "sg:city":"Alcala Guadaira",
    "sg:orig_category":"Alquiler De Veh\u00cdculos: Turismos Y Utilitarios",
    "sg:phone":"+34 955 61 34 06",
    "sg:postcode":"41500",
    "sg:province":"Sevilla",
    "wof:name":"Autocares Gomez Racero S.l.",
    "wof:placetype":"venue"
},
  "geometry": {"coordinates":[-5.8443388939,37.3428001404],"type":"Point"}
}