{
  "type": "Feature",
  "properties": {
    "addr:full":"Pl. Cde Rodezno, 8 Iru\u00f1a Navarra 31003",
    "addr:housenumber":"8",
    "addr:postcode":"31003",
    "addr:street":"Pl. Cde Rodezno",
    "iso:country":"ES",
    "sg:address":"Pl. Cde Rodezno, 8",
    "sg:city":"Iru\u00f1a",
    "sg:orig_category":"Asesor\u00cda De Comercio Exterior",
    "sg:phone":"+34 948 15 05 40",
    "sg:postcode":"31003",
    "sg:province":"Navarra",
    "wof:name":"Marketplace Consulting S.l.",
    "wof:placetype":"venue"
},
  "geometry": {"coordinates":[-1.6437540054,42.81275177],"type":"Point"}
}