{
  "type": "Feature",
  "properties": {
    "addr:full":"Pl Tirant Lo Blanc, 4 Barcelona Barcelona 08005",
    "addr:housenumber":"4",
    "addr:postcode":"08005",
    "addr:street":"Pl;Lo",
    "iso:country":"ES",
    "sg:address":"Pl Tirant Lo Blanc, 4",
    "sg:city":"Barcelona",
    "sg:orig_category":"Cajas De Ahorro",
    "sg:phone":"+34 932 21 97 94",
    "sg:postcode":"08005",
    "sg:province":"Barcelona",
    "wof:name":"Caixa D'estalvis I Pensions De Barcelona",
    "wof:placetype":"venue"
},
  "geometry": {"coordinates":[2.2008800507,41.392364502],"type":"Point"}
}