{
  "type": "Feature",
  "properties": {
    "iso:country":"ES",
    "sg:address":"Carrer de Bruc, 127",
    "sg:city":"Barcelona",
    "sg:orig_category":"M\u00c9dicos: Psiquiatr\u00cda",
    "sg:phone":"+34 934 58 37 44",
    "sg:postcode":"08037",
    "sg:province":"Barcelona",
    "wof:name":"Alfonso Simon Manuel",
    "wof:placetype":"venue"
},
  "geometry": {"coordinates":[2.1659104824,41.3970375061],"type":"Point"}
}