{
  "type": "Feature",
  "properties": {
    "addr:full":"Calle de Neptuno, 42 San Javier Murcia 30730",
    "addr:housenumber":"42",
    "addr:postcode":"30730",
    "addr:street":"Calle De Neptuno",
    "iso:country":"ES",
    "sg:address":"Calle de Neptuno, 42",
    "sg:city":"San Javier",
    "sg:orig_category":"Asociaciones Humanitarias, De Cooperaci\u00d3n, De Acci\u00d3n Social",
    "sg:phone":"+34 968 19 07 70",
    "sg:postcode":"30730",
    "sg:province":"Murcia",
    "sg:website":"www.aidemar.es",
    "wof:name":"Asociacion Aidemar",
    "wof:placetype":"venue"
},
  "geometry": {"coordinates":[-0.8307029009,37.7991409302],"type":"Point"}
}