{
  "type": "Feature",
  "properties": {
    "iso:country":"ES",
    "sg:address":"C/ Gongora, 2",
    "sg:city":"Alcoi",
    "sg:orig_category":"Promotores Constructores",
    "sg:phone":"+34 965 33 92 91",
    "sg:postcode":"03803",
    "sg:province":"Alicante",
    "wof:name":"Cadena Video Mania Sl",
    "wof:placetype":"venue"
},
  "geometry": {"coordinates":[-0.477737993,38.7025947571],"type":"Point"}
}