{
  "type": "Feature",
  "properties": {
    "iso:country":"ES",
    "sg:address":"Urb Nueva Isleta, S/n",
    "sg:city":"Palmas De Gran Canaria",
    "sg:orig_category":"Agencias Y Agentes Comerciales, Representantes",
    "sg:phone":"+34 928 46 96 19",
    "sg:postcode":"35009",
    "sg:province":"Las Palmas",
    "wof:name":"Sanchez Bola\u00f1os Jose Francisco",
    "wof:placetype":"venue"
},
  "geometry": {"coordinates":[-15.4287443161,28.1555099487],"type":"Point"}
}