{
  "type": "Feature",
  "properties": {
    "iso:country":"ES",
    "sg:address":"Calle de Guzman El Bueno (de), 14",
    "sg:city":"Alcobendas",
    "sg:orig_category":"Aparatos, Material Y Suministros Para Laboratorios",
    "sg:phone":"+34 916 61 28 75",
    "sg:postcode":"28108",
    "sg:province":"Madrid",
    "sg:website":"www.tamepasa.com",
    "wof:name":"Tamepa S.a.",
    "wof:placetype":"venue"
},
  "geometry": {"coordinates":[-3.6225941181,40.5358009338],"type":"Point"}
}