{
  "type": "Feature",
  "properties": {
    "iso:country":"ES",
    "sg:address":"Calle de San Millan, 40",
    "sg:city":"Eratsun",
    "sg:orig_category":"Centros De Educaci\u00d3n Especial",
    "sg:phone":"+34 948 61 51 39",
    "sg:postcode":"31748",
    "sg:province":"Navarra",
    "wof:name":"Colegio Publico De Eratsun",
    "wof:placetype":"venue"
},
  "geometry": {"coordinates":[-1.797391057,43.0835800171],"type":"Point"}
}