{
  "type": "Feature",
  "properties": {
    "iso:country":"ES",
    "sg:address":"Calle de Comedias, 21",
    "sg:city":"Antequera",
    "sg:orig_category":"Alimentaci\u00d3n General (al Por Menor)",
    "sg:phone":"+34 952 84 29 05",
    "sg:postcode":"29200",
    "sg:province":"M\u00e1laga",
    "wof:name":"Martin Ligero Jose",
    "wof:placetype":"venue"
},
  "geometry": {"coordinates":[-4.5607452393,37.0187797546],"type":"Point"}
}