{
  "type": "Feature",
  "properties": {
    "iso:country":"ES",
    "sg:address":"Calle de Urbanos (los), 1",
    "sg:city":"Cenicero",
    "sg:orig_category":"Iglesia Cat\u00d3lica",
    "sg:phone":"+34 941 45 41 79",
    "sg:postcode":"26350",
    "sg:province":"La Rioja",
    "wof:name":"Parroquia De San Martin",
    "wof:placetype":"venue"
},
  "geometry": {"coordinates":[-2.6431241035,42.4804840088],"type":"Point"}
}