{
  "type": "Feature",
  "properties": {
    "addr:full":"Calle de Arnao, 3 Palmas De Gran Canaria Las Palmas 35009",
    "addr:housenumber":"3",
    "addr:postcode":"35009",
    "addr:street":"Calle De Arnao",
    "iso:country":"ES",
    "sg:address":"Calle de Arnao, 3",
    "sg:city":"Palmas De Gran Canaria",
    "sg:orig_category":"Asociaciones, Organismos Culturales Y Socioeducativos",
    "sg:phone":"+34 928 46 78 78",
    "sg:postcode":"35009",
    "sg:province":"Las Palmas",
    "wof:name":"Asociacion De Pensionistas Piedra Ventayga",
    "wof:placetype":"venue"
},
  "geometry": {"coordinates":[-15.4282007217,28.1530456543],"type":"Point"}
}