{
  "type": "Feature",
  "properties": {
    "iso:country":"ES",
    "sg:address":"Pl Lesseps, 9",
    "sg:city":"Barcelona",
    "sg:classifiers":[
        {
            "category":"Personal",
            "subcategory":"Barber",
            "type":"Services"
        }
    ],
    "sg:phone":"+34 932 37 10 54",
    "sg:postcode":"08023",
    "sg:province":"Barcelona",
    "sg:tags":[
        "caballeros",
        "de",
        "peluqueros"
    ],
    "wof:name":"Flotats Costa Jose Maria",
    "wof:placetype":"venue"
},
  "geometry": {"coordinates":[2.1499979496,41.4072380066],"type":"Point"}
}