{
  "type": "Feature",
  "properties": {
    "addr:full":"Las Eras, S/n Villaquilambre Le\u00f3n 24008",
    "addr:housenumber":"s / n",
    "addr:postcode":"24008",
    "addr:street":"Las Eras",
    "iso:country":"ES",
    "sg:address":"Las Eras, S/n",
    "sg:city":"Villaquilambre",
    "sg:orig_category":"Centros De Educaci\u00d3n Especial",
    "sg:phone":"+34 987 28 31 13",
    "sg:postcode":"24008",
    "sg:province":"Le\u00f3n",
    "wof:name":"Colegio Rural Agrupado De Navatejera",
    "wof:placetype":"venue"
},
  "geometry": {"coordinates":[-5.5608458519,42.6484794617],"type":"Point"}
}