{
  "type": "Feature",
  "properties": {
    "iso:country":"ES",
    "sg:address":"Calapatanes, S/n",
    "sg:city":"Cretas",
    "sg:orig_category":"Cr\u00cda De Cerdos",
    "sg:phone":"+34 978 76 90 64",
    "sg:postcode":"44623",
    "sg:province":"Teruel",
    "wof:name":"Peggy-farm S.l.",
    "wof:placetype":"venue"
},
  "geometry": {"coordinates":[0.2130800039,40.929309845],"type":"Point"}
}