{
  "type": "Feature",
  "properties": {
    "addr:full":"Cmno Soledad (la), S/n Mora Rubielos Teruel 44400",
    "addr:postcode":"44400",
    "addr:street":"Cmno Soledad La S / N",
    "iso:country":"ES",
    "sg:address":"Cmno Soledad (la), S/n",
    "sg:city":"Mora Rubielos",
    "sg:orig_category":"Fabrica De Charcuter\u00cda",
    "sg:phone":"+34 978 80 04 37",
    "sg:postcode":"44400",
    "sg:province":"Teruel",
    "sg:website":"www.sierrademora.com",
    "wof:name":"Sierra De Mora S.l.",
    "wof:placetype":"venue"
},
  "geometry": {"coordinates":[-0.7552589774,40.2504005432],"type":"Point"}
}