{
  "type": "Feature",
  "properties": {
    "iso:country":"ES",
    "sg:address":"Carrer de Marques De Campo, 37",
    "sg:city":"Denia",
    "sg:orig_category":"Asesor\u00cda Fiscal Y Jur\u00cddica",
    "sg:phone":"+34 965 78 52 63",
    "sg:postcode":"03700",
    "sg:province":"Alicante",
    "wof:name":"Asesoria Y Gestoria Diba S.l.",
    "wof:placetype":"venue"
},
  "geometry": {"coordinates":[0.1100848988,38.8408126831],"type":"Point"}
}