{
  "type": "Feature",
  "properties": {
    "iso:country":"ES",
    "sg:address":"Arroyo Fresnedoso, S/n",
    "sg:city":"Moraleja",
    "sg:orig_category":"Confecci\u00d3n De Trajes De Ba\u00d1o Y De Ropa De Playa",
    "sg:phone":"+34 927 66 40 03",
    "sg:postcode":"10840",
    "sg:province":"C\u00e1ceres",
    "wof:name":"Beach Diffusion 2000 S.l.",
    "wof:placetype":"venue"
},
  "geometry": {"coordinates":[-6.6462488174,40.0604553223],"type":"Point"}
}