{
  "type": "Feature",
  "properties": {
    "iso:country":"ES",
    "sg:address":"Avda Juan Carlos I, 5",
    "sg:city":"Parla",
    "sg:orig_category":"Bibliotecas, Mediatecas",
    "sg:phone":"+34 916 99 96 45",
    "sg:postcode":"28980",
    "sg:province":"Madrid",
    "sg:website":"www.obrasocialcajamadrid.org",
    "wof:name":"Gecesa Gestion De Centros Culturales S.a",
    "wof:placetype":"venue"
},
  "geometry": {"coordinates":[-3.7721068859,40.2339820862],"type":"Point"}
}