{
  "type": "Feature",
  "properties": {
    "addr:full":"Calle de Manuel Franco Cubeiro, 19 Torremolinos M\u00e1laga 29620",
    "addr:housenumber":"19",
    "addr:postcode":"29620",
    "addr:street":"Calle De Manuel Franco Cubeiro;Ma\u0301Laga",
    "iso:country":"ES",
    "sg:address":"Calle de Manuel Franco Cubeiro, 19",
    "sg:city":"Torremolinos",
    "sg:orig_category":"Ferreter\u00cda (diversos)",
    "sg:phone":"+34 952 05 21 24",
    "sg:postcode":"29620",
    "sg:province":"M\u00e1laga",
    "wof:name":"Efansa Malaga S.l.",
    "wof:placetype":"venue"
},
  "geometry": {"coordinates":[-4.5173082352,36.6126022339],"type":"Point"}
}