{
  "type": "Feature",
  "properties": {
    "iso:country":"ES",
    "sg:address":"Plaz Merced, 19",
    "sg:city":"Malaga",
    "sg:orig_category":"Sociedades, Compa\u00d1\u00cdas Aseguradoras",
    "sg:phone":"+34 952 21 69 43",
    "sg:postcode":"29012",
    "sg:province":"M\u00e1laga",
    "wof:name":"Guadalai Am Sl",
    "wof:placetype":"venue"
},
  "geometry": {"coordinates":[-4.4117789268,36.7286949158],"type":"Point"}
}