{
  "type": "Feature",
  "properties": {
    "iso:country":"ES",
    "sg:address":"C/ Fray Luis De Leon, 26",
    "sg:city":"Elche",
    "sg:orig_category":"Electrodom\u00c9sticos (al Por Menor)",
    "sg:phone":"+34 965 45 85 50",
    "sg:postcode":"03203",
    "sg:province":"Alicante",
    "wof:name":"Ferreteria Agullo S.a",
    "wof:placetype":"venue"
},
  "geometry": {"coordinates":[-0.6969500184,38.2582435608],"type":"Point"}
}