{
  "type": "Feature",
  "properties": {
    "iso:country":"ES",
    "sg:address":"Calle de Mar Baltico, 5",
    "sg:city":"Mairena Aljarafe",
    "sg:orig_category":"Centros Empresariales",
    "sg:phone":"+34 954 18 56 24",
    "sg:postcode":"41927",
    "sg:province":"Sevilla",
    "sg:website":"www.aforcade.com",
    "wof:name":"Aforcade Innovacion",
    "wof:placetype":"venue"
},
  "geometry": {"coordinates":[-6.0377378464,37.3478279114],"type":"Point"}
}