{
  "type": "Feature",
  "properties": {
    "addr:full":"Avda Colmenar Viejo (de), 9 San Sebastian De Los Reyes Madrid 28700",
    "addr:postcode":"28700",
    "addr:street":"Avda Colmenar",
    "iso:country":"ES",
    "sg:address":"Avda Colmenar Viejo (de), 9",
    "sg:city":"San Sebastian De Los Reyes",
    "sg:orig_category":"Ropa Para Ni\u00d1os (al Por Menor)",
    "sg:phone":"+34 916 53 37 92",
    "sg:postcode":"28700",
    "sg:province":"Madrid",
    "wof:name":"A Dieta C.b.",
    "wof:placetype":"venue"
},
  "geometry": {"coordinates":[-3.5989151001,40.5939674377],"type":"Point"}
}