{
  "type": "Feature",
  "properties": {
    "addr:full":"Calle de Palma (la), S/n Puigmoreno Teruel 44660",
    "addr:postcode":"44660",
    "addr:street":"Calle De Palma La S / N",
    "iso:country":"ES",
    "sg:address":"Calle de Palma (la), S/n",
    "sg:city":"Puigmoreno",
    "sg:orig_category":"Cajas De Ahorro",
    "sg:phone":"+34 978 83 80 94",
    "sg:postcode":"44660",
    "sg:province":"Teruel",
    "wof:name":"Caja De Ahorros De La Inmaculada",
    "wof:placetype":"venue"
},
  "geometry": {"coordinates":[-0.2500289977,41.1078109741],"type":"Point"}
}