{
  "type": "Feature",
  "properties": {
    "iso:country":"ES",
    "sg:address":"Ptge Xavier Montsalvatge, 9",
    "sg:city":"Tarragona",
    "sg:orig_category":"Promotores Constructores",
    "sg:phone":"+34 977 22 12 35",
    "sg:postcode":"43005",
    "sg:province":"Tarragona",
    "wof:name":"Crevestiments I Construccions Mirador S.l.",
    "wof:placetype":"venue"
},
  "geometry": {"coordinates":[1.2390160561,41.1118164062],"type":"Point"}
}