{
  "type": "Feature",
  "properties": {
    "iso:country":"ES",
    "sg:address":"Calle de Bravo Murillo, 267",
    "sg:city":"Madrid",
    "sg:orig_category":"Oficinas Y Gesti\u00d3n De Inmuebles",
    "sg:phone":"+34 915 72 02 54",
    "sg:postcode":"28020",
    "sg:province":"Madrid",
    "sg:website":"www.home.worldine.es/gccmoral",
    "wof:name":"Diez Ucar Jesus",
    "wof:placetype":"venue"
},
  "geometry": {"coordinates":[-3.6992959976,40.4597244263],"type":"Point"}
}