{
  "type": "Feature",
  "properties": {
    "iso:country":"ES",
    "sg:address":"Avda Constitucion, 7",
    "sg:city":"Tobarra",
    "sg:orig_category":"Asesor\u00cda Fiscal Y Jur\u00cddica",
    "sg:phone":"+34 967 32 84 40",
    "sg:postcode":"02500",
    "sg:province":"Albacete",
    "wof:name":"Ramirez Belmonte Sebastian",
    "wof:placetype":"venue"
},
  "geometry": {"coordinates":[-1.6870189905,38.5924682617],"type":"Point"}
}