{
  "type": "Feature",
  "properties": {
    "addr:full":"Nobel-espiritu Santo, 2 Cambre La Coru\u00f1a 15650",
    "addr:housenumber":"2",
    "addr:postcode":"15650",
    "addr:street":"Santo;La Corun\u0303A",
    "iso:country":"ES",
    "sg:address":"Nobel-espiritu Santo, 2",
    "sg:city":"Cambre",
    "sg:orig_category":"Pantallas, Mamparas Y Accesorios (fabricaci\u00d3n)",
    "sg:phone":"+34 981 64 90 38",
    "sg:postcode":"15650",
    "sg:province":"La Coru\u00f1a",
    "wof:name":"Pantallas Quique S.l.",
    "wof:placetype":"venue"
},
  "geometry": {"coordinates":[-8.3069343567,43.2885551453],"type":"Point"}
}