{
  "type": "Feature",
  "properties": {
    "addr:full":"Calle de San Juan, 20 Cehegin Murcia 30430",
    "addr:housenumber":"20",
    "addr:postcode":"30430",
    "addr:street":"Calle De San Juan",
    "iso:country":"ES",
    "sg:address":"Calle de San Juan, 20",
    "sg:city":"Cehegin",
    "sg:orig_category":"Reposter\u00cdas",
    "sg:phone":"+34 968 74 06 19",
    "sg:postcode":"30430",
    "sg:province":"Murcia",
    "wof:name":"Gil Martinez Juan De Dios",
    "wof:placetype":"venue"
},
  "geometry": {"coordinates":[-1.7970319986,38.0903816223],"type":"Point"}
}