{
  "type": "Feature",
  "properties": {
    "addr:full":"Calle de Mercedes (las), 17 Arenas -areeta Vizcaya 48930",
    "addr:housenumber":"17;areeta",
    "addr:postcode":"48930",
    "addr:street":"Calle De Mercedes Las",
    "iso:country":"ES",
    "sg:address":"Calle de Mercedes (las), 17",
    "sg:city":"Arenas -areeta",
    "sg:orig_category":"Muebles, Minoristas",
    "sg:phone":"+34 944 63 86 91",
    "sg:postcode":"48930",
    "sg:province":"Vizcaya",
    "wof:name":"Goyoaga Decoracion S.l.",
    "wof:placetype":"venue"
},
  "geometry": {"coordinates":[-3.014122963,43.3265342712],"type":"Point"}
}