{
  "type": "Feature",
  "properties": {
    "iso:country":"ES",
    "sg:address":"Calle de Toledo, 38",
    "sg:city":"Getafe",
    "sg:orig_category":"Centros De Coordinaci\u00d3n",
    "sg:phone":"+34 916 84 22 22",
    "sg:postcode":"28901",
    "sg:province":"Madrid",
    "wof:name":"Martin Herrera & Fraga S.l.",
    "wof:placetype":"venue"
},
  "geometry": {"coordinates":[-3.7337911129,40.3013420105],"type":"Point"}
}