{
  "type": "Feature",
  "properties": {
    "addr:full":"C/ Filet De Fora, 86 Elche Alicante 03203",
    "addr:housenumber":"86",
    "addr:postcode":"03203",
    "addr:street":"C / Filet De Fora",
    "iso:country":"ES",
    "sg:address":"C/ Filet De Fora, 86",
    "sg:city":"Elche",
    "sg:orig_category":"Farmacias",
    "sg:phone":"+34 965 45 23 74",
    "sg:postcode":"03203",
    "sg:province":"Alicante",
    "wof:name":"Vazquez Albentosa Carmen",
    "wof:placetype":"venue"
},
  "geometry": {"coordinates":[-0.6964979768,38.2604904175],"type":"Point"}
}