{
  "type": "Feature",
  "properties": {
    "iso:country":"ES",
    "sg:address":"Calle de Lorenzo Menendez, 2",
    "sg:city":"Cangas Narcea",
    "sg:orig_category":"Sanatorios M\u00c9dico",
    "sg:phone":"+34 985 81 24 59",
    "sg:postcode":"33800",
    "sg:province":"Asturias",
    "wof:name":"Insalud-atencion Primaria Area Ii-hospital Carmen Y Severo Ochoa",
    "wof:placetype":"venue"
},
  "geometry": {"coordinates":[-6.5471878052,43.175907135],"type":"Point"}
}