{
  "type": "Feature",
  "properties": {
    "addr:full":"Calle de Republica Dominicana, 20 Jerez De Los Caballeros Badajoz 06380",
    "addr:housenumber":"20",
    "addr:postcode":"06380",
    "addr:street":"Calle De Republica Dominicana",
    "iso:country":"ES",
    "sg:address":"Calle de Republica Dominicana, 20",
    "sg:city":"Jerez De Los Caballeros",
    "sg:orig_category":"Contables",
    "sg:phone":"+34 924 73 19 57",
    "sg:postcode":"06380",
    "sg:province":"Badajoz",
    "wof:name":"Asconytelib S.l.",
    "wof:placetype":"venue"
},
  "geometry": {"coordinates":[-6.7763323784,38.3229179382],"type":"Point"}
}