{
  "type": "Feature",
  "properties": {
    "addr:full":"Brocense, 11 Brozas C\u00e1ceres 10950",
    "addr:housenumber":"11",
    "addr:postcode":"10950",
    "addr:street":"Brocense;Ca\u0301Ceres",
    "iso:country":"ES",
    "sg:address":"Brocense, 11",
    "sg:city":"Brozas",
    "sg:orig_category":"Zapatos (al Por Menor)",
    "sg:phone":"+34 927 39 55 48",
    "sg:postcode":"10950",
    "sg:province":"C\u00e1ceres",
    "wof:name":"Castellano Rosado Justa",
    "wof:placetype":"venue"
},
  "geometry": {"coordinates":[-6.778263092,39.6116027832],"type":"Point"}
}