{
  "type": "Feature",
  "properties": {
    "addr:full":"Ctra Circunvalacion, 8 Ubeda Ja\u00e9n 23400",
    "addr:housenumber":"8",
    "addr:postcode":"23400",
    "addr:street":"Ctra Circunvalacion;Jae\u0301N",
    "iso:country":"ES",
    "sg:address":"Ctra Circunvalacion, 8",
    "sg:city":"Ubeda",
    "sg:orig_category":"Ingeniero",
    "sg:phone":"+34 953 75 75 19",
    "sg:postcode":"23400",
    "sg:province":"Ja\u00e9n",
    "wof:name":"Robles Valenzuela Jose",
    "wof:placetype":"venue"
},
  "geometry": {"coordinates":[-3.3697609901,38.0198097229],"type":"Point"}
}