{
  "type": "Feature",
  "properties": {
    "iso:country":"ES",
    "sg:address":"Carrer de Frederica Montseny, 27",
    "sg:city":"Sant Feliu Llobregat",
    "sg:orig_category":"Peluqueros: De Se\u00d1oras",
    "sg:phone":"+34 936 85 19 21",
    "sg:postcode":"08980",
    "sg:province":"Barcelona",
    "wof:name":"Mejia Santiago Maria",
    "wof:placetype":"venue"
},
  "geometry": {"coordinates":[2.0560491085,41.3864326477],"type":"Point"}
}