{
  "type": "Feature",
  "properties": {
    "iso:country":"ES",
    "sg:address":"Plaz Verdura, S/n",
    "sg:city":"Nava Rey",
    "sg:orig_category":"Bibliotecas, Mediatecas",
    "sg:phone":"+34 983 85 02 93",
    "sg:postcode":"47500",
    "sg:province":"Valladolid",
    "wof:name":"Ayuntamiento De Nava Del Rey",
    "wof:placetype":"venue"
},
  "geometry": {"coordinates":[-5.0809907913,41.331035614],"type":"Point"}
}