{
  "type": "Feature",
  "properties": {
    "iso:country":"ES",
    "sg:address":"Pg Maragall, 97",
    "sg:city":"Barcelona",
    "sg:orig_category":"Administradores De Bienes Y Delegados De Comunidades De Propietarios",
    "sg:phone":"+34 933 47 11 35",
    "sg:postcode":"08041",
    "sg:province":"Barcelona",
    "wof:name":"Fincas Elite S.l.",
    "wof:placetype":"venue"
},
  "geometry": {"coordinates":[2.1804289818,41.4182357788],"type":"Point"}
}