{
  "type": "Feature",
  "properties": {
    "addr:full":"Rua Valentin Viqueira, 20 Vilagarcia Pontevedra 36610",
    "addr:housenumber":"20",
    "addr:postcode":"36610",
    "addr:street":"Rua Valentin Viqueira",
    "iso:country":"ES",
    "sg:address":"Rua Valentin Viqueira, 20",
    "sg:city":"Vilagarcia",
    "sg:orig_category":"Estudios Y Construcci\u00d3n De Acuarios Y Viveros",
    "sg:phone":"+34 986 50 09 34",
    "sg:postcode":"36610",
    "sg:province":"Pontevedra",
    "wof:name":"Abelenda Ba\u00f1os Ramon",
    "wof:placetype":"venue"
},
  "geometry": {"coordinates":[-8.7755,42.617664],"type":"Point"}
}