{
  "type": "Feature",
  "properties": {
    "addr:full":"Calle de San Andres, 7 Malaga M\u00e1laga 29002",
    "addr:housenumber":"7",
    "addr:postcode":"29002",
    "addr:street":"Calle De San Andres;Ma\u0301Laga",
    "iso:country":"ES",
    "sg:address":"Calle de San Andres, 7",
    "sg:city":"Malaga",
    "sg:orig_category":"Locales Y Clases De Danza",
    "sg:phone":"+34 952 60 27 86",
    "sg:postcode":"29002",
    "sg:province":"M\u00e1laga",
    "wof:name":"Sanchez Perez Jesus",
    "wof:placetype":"venue"
},
  "geometry": {"coordinates":[-4.4270138741,36.7131576538],"type":"Point"}
}