{
  "type": "Feature",
  "properties": {
    "addr:full":"Calle de Avila, 12 Sotogrande C\u00e1diz 11310",
    "addr:housenumber":"12",
    "addr:postcode":"11310",
    "addr:street":"Calle De Avila;Ca\u0301Diz",
    "iso:country":"ES",
    "sg:address":"Calle de Avila, 12",
    "sg:city":"Sotogrande",
    "sg:orig_category":"Centros De Coordinaci\u00d3n",
    "sg:phone":"+34 956 79 59 87",
    "sg:postcode":"11310",
    "sg:province":"C\u00e1diz",
    "wof:name":"Fosholi Inversiones S.l.",
    "wof:placetype":"venue"
},
  "geometry": {"coordinates":[-5.3082709312,36.2754745483],"type":"Point"}
}