{
  "type": "Feature",
  "properties": {
    "addr:full":"Plaz Reyes Catolicos, 6 Puerto Cruz Santa Cruz De Tenerife 38400",
    "addr:housenumber":"6",
    "addr:postcode":"38400",
    "addr:street":"Plaz Reyes Catolicos;Cruz",
    "iso:country":"ES",
    "sg:address":"Plaz Reyes Catolicos, 6",
    "sg:city":"Puerto Cruz",
    "sg:orig_category":"Perfumer\u00cda, Art\u00cdculos De Ba\u00d1o (fabricaci\u00d3n, Al Por Mayor)",
    "sg:phone":"+34 922 38 29 95",
    "sg:postcode":"38400",
    "sg:province":"Santa Cruz De Tenerife",
    "wof:name":"Thakursons S.l.",
    "wof:placetype":"venue"
},
  "geometry": {"coordinates":[-16.5453357697,28.4170131683],"type":"Point"}
}