{
  "type": "Feature",
  "properties": {
    "addr:full":"Carrer de Santander, S/n Barcelona Barcelona 08020",
    "addr:housenumber":"s / n",
    "addr:postcode":"08020",
    "addr:street":"Carrer De Santander",
    "iso:country":"ES",
    "sg:address":"Carrer de Santander, S/n",
    "sg:city":"Barcelona",
    "sg:orig_category":"Cooperativas Agr\u00cdcolas",
    "sg:phone":"+34 933 13 68 46",
    "sg:postcode":"08020",
    "sg:province":"Barcelona",
    "wof:name":"Cooperativa De Viviendas Nuestra Se\u00f1ora De La Fe",
    "wof:placetype":"venue"
},
  "geometry": {"coordinates":[2.2021551132,41.4276733398],"type":"Point"}
}