{
  "type": "Feature",
  "properties": {
    "iso:country":"ES",
    "sg:address":"Rua Carlos Casas, 8",
    "sg:city":"Sanxenxo",
    "sg:orig_category":"Cobro De Pr\u00c9stamos",
    "sg:phone":"+34 986 69 10 77",
    "sg:postcode":"36960",
    "sg:province":"Pontevedra",
    "wof:name":"Diputacion Provincial De Pontevedra-oral",
    "wof:placetype":"venue"
},
  "geometry": {"coordinates":[-8.8077373505,42.4010429382],"type":"Point"}
}