{
  "type": "Feature",
  "properties": {
    "iso:country":"ES",
    "sg:address":"Plaz Apostoles, 3",
    "sg:city":"Catedral",
    "sg:orig_category":"Abogados",
    "sg:phone":"+34 968 21 31 11",
    "sg:postcode":"30001",
    "sg:province":"Murcia",
    "wof:name":"Lacarcel Toledo Javier",
    "wof:placetype":"venue"
},
  "geometry": {"coordinates":[-1.1302490234,37.9829597473],"type":"Point"}
}