{
  "type": "Feature",
  "properties": {
    "iso:country":"ES",
    "sg:address":"Plaz San Francisco, 9",
    "sg:city":"Cartagena",
    "sg:orig_category":"Agencias De Viajes",
    "sg:phone":"+34 968 52 40 00",
    "sg:postcode":"30202",
    "sg:province":"Murcia",
    "sg:website":"www.viajeseci.es",
    "wof:name":"Viajes El Corte Ingles S.a.",
    "wof:placetype":"venue"
},
  "geometry": {"coordinates":[-0.9838269949,37.6024208069],"type":"Point"}
}