{
  "type": "Feature",
  "properties": {
    "iso:country":"ES",
    "sg:address":"Avda Paz (la), 29",
    "sg:city":"Peralta",
    "sg:orig_category":"Conservas De Legumbres (fabricaci\u00d3n, Al Por Mayor)",
    "sg:phone":"+34 948 75 03 26",
    "sg:postcode":"31350",
    "sg:province":"Navarra",
    "wof:name":"Conservas Guindumar S. A.",
    "wof:placetype":"venue"
},
  "geometry": {"coordinates":[-1.8057060242,42.338924408],"type":"Point"}
}