{
  "type": "Feature",
  "properties": {
    "addr:full":"Calle de Barahona, 3 Le\u00f3n Le\u00f3n 24003",
    "addr:housenumber":"3",
    "addr:postcode":"24003",
    "addr:street":"Calle De Barahona;Leo\u0301N",
    "iso:country":"ES",
    "sg:address":"Calle de Barahona, 3",
    "sg:city":"Le\u00f3n",
    "sg:orig_category":"Farmacias",
    "sg:phone":"+34 987 20 61 24",
    "sg:postcode":"24003",
    "sg:province":"Le\u00f3n",
    "wof:name":"Gonzalez Gonzalez Patricia",
    "wof:placetype":"venue"
},
  "geometry": {"coordinates":[-5.5678052902,42.5936355591],"type":"Point"}
}