{
  "type": "Feature",
  "properties": {
    "iso:country":"ES",
    "sg:address":"Guarnicioneros, 25",
    "sg:city":"Tomelloso",
    "sg:orig_category":"Promotores Constructores",
    "sg:phone":"+34 926 50 11 56",
    "sg:postcode":"13700",
    "sg:province":"Ciudad Real",
    "wof:name":"Manuel J.rodriguez 2005 Pomociones Y Construcciones",
    "wof:placetype":"venue"
},
  "geometry": {"coordinates":[-3.0075790882,39.1561546326],"type":"Point"}
}