{
  "type": "Feature",
  "properties": {
    "iso:country":"ES",
    "sg:address":"Calle de San Quirce, 9",
    "sg:city":"Valladolid",
    "sg:orig_category":"Florister\u00cdas",
    "sg:phone":"+34 983 33 92 35",
    "sg:postcode":"47003",
    "sg:province":"Valladolid",
    "wof:name":"Neches Palacios Belen",
    "wof:placetype":"venue"
},
  "geometry": {"coordinates":[-4.7285971642,41.656917572],"type":"Point"}
}