{
  "type": "Feature",
  "properties": {
    "iso:country":"ES",
    "sg:address":"Carr Holanda, 49",
    "sg:city":"Badalona",
    "sg:orig_category":"Ropa Para Caballeros Y Se\u00d1oras (al Por Mayor)",
    "sg:phone":"+34 933 95 64 64",
    "sg:postcode":"08917",
    "sg:province":"Barcelona",
    "wof:name":"Dosis Mode S.l.",
    "wof:placetype":"venue"
},
  "geometry": {"coordinates":[2.2230000496,41.458984375],"type":"Point"}
}