{
  "type": "Feature",
  "properties": {
    "addr:full":"Calle de C(campollano), 6 Albacete Albacete 02006",
    "addr:housenumber":"6",
    "addr:postcode":"02006",
    "addr:street":"Calle De C Campollano",
    "iso:country":"ES",
    "sg:address":"Calle de C(campollano), 6",
    "sg:city":"Albacete",
    "sg:orig_category":"Transportes Por V\u00cdas Navegables",
    "sg:phone":"+34 967 52 19 87",
    "sg:postcode":"02006",
    "sg:province":"Albacete",
    "wof:name":"Transportes Naturil S. L.",
    "wof:placetype":"venue"
},
  "geometry": {"coordinates":[-1.8419630527,39.0247383118],"type":"Point"}
}