{
  "type": "Feature",
  "properties": {
    "addr:full":"Calle de Don Jaime I, 43 Zaragoza Zaragoza 50003",
    "addr:housenumber":"43",
    "addr:postcode":"50003",
    "addr:street":"Calle De Don Jaime I",
    "iso:country":"ES",
    "sg:address":"Calle de Don Jaime I, 43",
    "sg:city":"Zaragoza",
    "sg:orig_category":"Peluqueros: De Se\u00d1oras",
    "sg:phone":"+34 976 20 12 15",
    "sg:postcode":"50003",
    "sg:province":"Zaragoza",
    "wof:name":"Gil Pascua Alicia",
    "wof:placetype":"venue"
},
  "geometry": {"coordinates":[-0.8770496249,41.6548652649],"type":"Point"}
}