{
  "type": "Feature",
  "properties": {
    "addr:full":"Avda Ricardo Soriano, 35 Marbella M\u00e1laga 29600",
    "addr:housenumber":"35",
    "addr:postcode":"29600",
    "addr:street":"Avda Ricardo Soriano;Ma\u0301Laga",
    "iso:country":"ES",
    "sg:address":"Avda Ricardo Soriano, 35",
    "sg:city":"Marbella",
    "sg:orig_category":"Ense\u00d1anza Variada",
    "sg:phone":"+34 952 77 65 51",
    "sg:postcode":"29600",
    "sg:province":"M\u00e1laga",
    "wof:name":"Academia Marapolis S.cv.",
    "wof:placetype":"venue"
},
  "geometry": {"coordinates":[-4.8925457001,36.5102996826],"type":"Point"}
}