{
  "type": "Feature",
  "properties": {
    "addr:full":"Carrer de Bernat Vidal I Tomas, 60 Santanyi Islas Baleares 07650",
    "addr:housenumber":"60",
    "addr:postcode":"07650",
    "addr:street":"Carrer De Bernat Vidal I Tomas",
    "iso:country":"ES",
    "sg:address":"Carrer de Bernat Vidal I Tomas, 60",
    "sg:city":"Santanyi",
    "sg:orig_category":"Empresas De Pintura Y Revestimientos",
    "sg:phone":"+34 971 65 36 26",
    "sg:postcode":"07650",
    "sg:province":"Islas Baleares",
    "wof:name":"Pons Fullana Andres",
    "wof:placetype":"venue"
},
  "geometry": {"coordinates":[3.1319680214,39.3519325256],"type":"Point"}
}