{
  "type": "Feature",
  "properties": {
    "iso:country":"ES",
    "sg:address":"Carrer de Ventallo, 27",
    "sg:city":"Barcelona",
    "sg:orig_category":"Ebanistas Y Talladores De Muebles Y Objetos De Arte",
    "sg:phone":"+34 932 19 30 96",
    "sg:postcode":"08025",
    "sg:province":"Barcelona",
    "wof:name":"Fuentes Fernandez Mercedes",
    "wof:placetype":"venue"
},
  "geometry": {"coordinates":[2.1657640934,41.407535553],"type":"Point"}
}