{
  "type": "Feature",
  "properties": {
    "addr:full":"Calle de Linares, 13 Ceuta Ceuta 51001",
    "addr:housenumber":"13",
    "addr:postcode":"51001",
    "addr:street":"Calle De Linares",
    "iso:country":"ES",
    "sg:address":"Calle de Linares, 13",
    "sg:city":"Ceuta",
    "sg:orig_category":"Molduras, Junquillos, Listones Y Molduras Perforadas",
    "sg:phone":"+34 956 51 83 07",
    "sg:postcode":"51001",
    "sg:province":"Ceuta",
    "wof:name":"Rios Gomez Esteban",
    "wof:placetype":"venue"
},
  "geometry": {"coordinates":[-5.3033738136,35.8911247253],"type":"Point"}
}