{
  "type": "Feature",
  "properties": {
    "addr:full":"Calle de Jaime I El Conquistador, S/n Parla Madrid 28980",
    "addr:housenumber":"s",
    "addr:postcode":"28980",
    "addr:street":"Calle De Jaime I El Conquistador;/ N",
    "iso:country":"ES",
    "sg:address":"Calle de Jaime I El Conquistador, S/n",
    "sg:city":"Parla",
    "sg:orig_category":"Sanatorios M\u00c9dico",
    "sg:phone":"+34 916 98 29 04",
    "sg:postcode":"28980",
    "sg:province":"Madrid",
    "wof:name":"Organismo Autonomo De Informatica Y Comunicaciones De La Comunidad De Madrid",
    "wof:placetype":"venue"
},
  "geometry": {"coordinates":[-3.7624521255,40.2349395752],"type":"Point"}
}