{
  "type": "Feature",
  "properties": {
    "iso:country":"ES",
    "sg:address":"Calle de Principal, 4",
    "sg:city":"Madrid",
    "sg:orig_category":"Centros De Educaci\u00d3n Especial",
    "sg:phone":"+34 917 95 62 70",
    "sg:postcode":"28021",
    "sg:province":"Madrid",
    "wof:name":"C.i.e. Sociedad Cooperativa Madrile\u00f1a",
    "wof:placetype":"venue"
},
  "geometry": {"coordinates":[-3.6993639469,40.33385849],"type":"Point"}
}