{
  "type": "Feature",
  "properties": {
    "addr:full":"Carrer de Vall D'ordesa, 18 Barcelona Barcelona 08031",
    "addr:housenumber":"18",
    "addr:postcode":"08031",
    "addr:street":"Carrer De Vall D'Ordesa",
    "iso:country":"ES",
    "sg:address":"Carrer de Vall D'ordesa, 18",
    "sg:city":"Barcelona",
    "sg:orig_category":"Peleter\u00cdas",
    "sg:phone":"+34 933 57 29 64",
    "sg:postcode":"08031",
    "sg:province":"Barcelona",
    "wof:name":"Gonzalez Hernandez Francisco",
    "wof:placetype":"venue"
},
  "geometry": {"coordinates":[2.1655726433,41.4312057495],"type":"Point"}
}