{
  "type": "Feature",
  "properties": {
    "iso:country":"ES",
    "sg:address":"Calle de Nardiz Tar Jon, 63",
    "sg:city":"Bermeo",
    "sg:orig_category":"Carnicer\u00cdas, Carnicer\u00cdas",
    "sg:phone":"+34 946 88 02 01",
    "sg:postcode":"48370",
    "sg:province":"Vizcaya",
    "wof:name":"Lourdes Alegria E Hijos C.b",
    "wof:placetype":"venue"
},
  "geometry": {"coordinates":[-2.7252030373,43.4199867249],"type":"Point"}
}