{
  "type": "Feature",
  "properties": {
    "iso:country":"ES",
    "sg:address":"Plaz Santa Teresa, 12",
    "sg:city":"Avila",
    "sg:orig_category":"Fotograf\u00cda Art\u00cdstica Y Retratos",
    "sg:phone":"+34 920 22 12 03",
    "sg:postcode":"05001",
    "sg:province":"\u00c1vila",
    "wof:name":"Prieto Diaz Jose Ramon",
    "wof:placetype":"venue"
},
  "geometry": {"coordinates":[-4.6959981918,40.6539802551],"type":"Point"}
}