{
  "type": "Feature",
  "properties": {
    "iso:country":"ES",
    "sg:address":"Carrer de Marques Senia, 39",
    "sg:city":"Palma",
    "sg:orig_category":"Promotores Constructores",
    "sg:phone":"+34 971 45 06 87",
    "sg:postcode":"07014",
    "sg:province":"Islas Baleares",
    "wof:name":"Viajes Sidetours S.a.",
    "wof:placetype":"venue"
},
  "geometry": {"coordinates":[2.6293520927,39.5680961609],"type":"Point"}
}