{
  "type": "Feature",
  "properties": {
    "addr:full":"C/ Paraires, 4 Inca Islas Baleares 07300",
    "addr:housenumber":"4",
    "addr:postcode":"07300",
    "addr:street":"C / Paraires",
    "iso:country":"ES",
    "sg:address":"C/ Paraires, 4",
    "sg:city":"Inca",
    "sg:orig_category":"Abogados",
    "sg:phone":"+34 971 50 45 11",
    "sg:postcode":"07300",
    "sg:province":"Islas Baleares",
    "wof:name":"Bestard Comas Jaime",
    "wof:placetype":"venue"
},
  "geometry": {"coordinates":[2.9105908871,39.7218856812],"type":"Point"}
}