{
  "type": "Feature",
  "properties": {
    "addr:full":"Calle de Arzobispo Fabian Y Fuero, 40 Valencia Valencia 46009",
    "addr:housenumber":"40",
    "addr:postcode":"46009",
    "addr:street":"Calle De Arzobispo Fabian Y Fuero",
    "iso:country":"ES",
    "sg:address":"Calle de Arzobispo Fabian Y Fuero, 40",
    "sg:city":"Valencia",
    "sg:orig_category":"Imprenta",
    "sg:phone":"+34 963 40 10 13",
    "sg:postcode":"46009",
    "sg:province":"Valencia",
    "wof:name":"Graficas Casacuberta Sl",
    "wof:placetype":"venue"
},
  "geometry": {"coordinates":[-0.3829087913,39.4835395813],"type":"Point"}
}