{
  "type": "Feature",
  "properties": {
    "iso:country":"ES",
    "sg:address":"Las Granjas, S/n",
    "sg:city":"Casillas Ranera",
    "sg:orig_category":"Poller\u00cda Y Caza (al Por Menor)",
    "sg:phone":"+34 969 36 60 74",
    "sg:postcode":"16321",
    "sg:province":"Cuenca",
    "wof:name":"Castellano Valenciana De Negocios S.l.",
    "wof:placetype":"venue"
},
  "geometry": {"coordinates":[-1.2688939571,39.7801818848],"type":"Point"}
}