{
  "type": "Feature",
  "properties": {
    "addr:full":"Calle de Finlandia, 17 Alcala Henares Madrid 28802",
    "addr:housenumber":"17",
    "addr:postcode":"28802",
    "addr:street":"Calle De Finlandia",
    "iso:country":"ES",
    "sg:address":"Calle de Finlandia, 17",
    "sg:city":"Alcala Henares",
    "sg:orig_category":"Cajas Y Embalajes De Pl\u00c1stico",
    "sg:phone":"+34 918 81 32 46",
    "sg:postcode":"28802",
    "sg:province":"Madrid",
    "wof:name":"Lupacks.l.",
    "wof:placetype":"venue"
},
  "geometry": {"coordinates":[-3.3817200661,40.4810676575],"type":"Point"}
}