{
  "type": "Feature",
  "properties": {
    "addr:full":"Laurel, 1 Aljaraque Huelva 21110",
    "addr:housenumber":"1",
    "addr:postcode":"21110",
    "addr:street":"Laurel",
    "iso:country":"ES",
    "sg:address":"Laurel, 1",
    "sg:city":"Aljaraque",
    "sg:orig_category":"Asesor\u00cda Sobre Comunicaci\u00d3n De Empresas",
    "sg:phone":"+34 959 52 15 06",
    "sg:postcode":"21110",
    "sg:province":"Huelva",
    "wof:name":"Albendin Moya Juan Jose",
    "wof:placetype":"venue"
},
  "geometry": {"coordinates":[-7.0069699287,37.2833480835],"type":"Point"}
}