{
  "type": "Feature",
  "properties": {
    "iso:country":"ES",
    "sg:address":"Avda Corts Valencianes, De Les, 2",
    "sg:city":"Valencia",
    "sg:orig_category":"Arboricultura Y Producci\u00d3n De Frutas",
    "sg:phone":"+34 963 46 62 43",
    "sg:postcode":"46...",
    "sg:province":"Valencia",
    "wof:name":"Bocchi Fruit-trade Spain S.a.",
    "wof:placetype":"venue"
},
  "geometry": {"coordinates":[-0.3769130111,39.4687919617],"type":"Point"}
}