{
  "type": "Feature",
  "properties": {
    "iso:country":"ES",
    "sg:address":"Calle de Labayo, 39",
    "sg:city":"San Vitero",
    "sg:orig_category":"Empresas De Carpinter\u00cda Met\u00c1lica",
    "sg:phone":"+34 980 68 22 60",
    "sg:postcode":"49523",
    "sg:province":"Zamora",
    "wof:name":"Gar-fi Carpinteria Metalica S.l.",
    "wof:placetype":"venue"
},
  "geometry": {"coordinates":[-6.3491191864,41.7743797302],"type":"Point"}
}