{
  "type": "Feature",
  "properties": {
    "addr:full":"Calle de Callejuelas Altas, 93 Mancha Real Ja\u00e9n 23100",
    "addr:housenumber":"93",
    "addr:postcode":"23100",
    "addr:street":"Calle De Callejuelas Altas",
    "iso:country":"ES",
    "sg:address":"Calle de Callejuelas Altas, 93",
    "sg:city":"Mancha Real",
    "sg:orig_category":"Armas Y Municiones (fabricaci\u00d3n, Al Por Mayor)",
    "sg:phone":"+34 953 35 25 03",
    "sg:postcode":"23100",
    "sg:province":"Ja\u00e9n",
    "wof:name":"Cozar Tello Francisco",
    "wof:placetype":"venue"
},
  "geometry": {"coordinates":[-3.608246088,37.7851257324],"type":"Point"}
}