{
  "type": "Feature",
  "properties": {
    "addr:full":"O Vilar, 73 Guisamo La Coru\u00f1a 15640",
    "addr:housenumber":"73",
    "addr:postcode":"15640",
    "addr:street":"O Vilar;La Corun\u0303A",
    "iso:country":"ES",
    "sg:address":"O Vilar, 73",
    "sg:city":"Guisamo",
    "sg:orig_category":"Charcuter\u00cdas (al Por Menor)",
    "sg:phone":"+34 981 79 51 26",
    "sg:postcode":"15640",
    "sg:province":"La Coru\u00f1a",
    "wof:name":"Carnicas O Chilero S.l.",
    "wof:placetype":"venue"
},
  "geometry": {"coordinates":[-8.2682237625,43.2997894287],"type":"Point"}
}