{
  "type": "Feature",
  "properties": {
    "addr:full":"Calle de Solana, 42 Torrejon Ardoz Madrid 28850",
    "addr:housenumber":"42",
    "addr:postcode":"28850",
    "addr:street":"Calle De Solana",
    "iso:country":"ES",
    "sg:address":"Calle de Solana, 42",
    "sg:city":"Torrejon Ardoz",
    "sg:orig_category":"Estudios, Instalaci\u00d3n De Climatizaci\u00d3n",
    "sg:phone":"+34 916 75 75 50",
    "sg:postcode":"28850",
    "sg:province":"Madrid",
    "sg:website":"www.luymar.com",
    "wof:name":"Estudio Tecnico Luymar S.l.",
    "wof:placetype":"venue"
},
  "geometry": {"coordinates":[-3.4637670517,40.4553489685],"type":"Point"}
}