{
  "type": "Feature",
  "properties": {
    "addr:full":"Avda Fernandez Albor, 19 Guarda Pontevedra 36780",
    "addr:housenumber":"19",
    "addr:postcode":"36780",
    "addr:street":"Avda Fernandez Albor",
    "iso:country":"ES",
    "sg:address":"Avda Fernandez Albor, 19",
    "sg:city":"Guarda",
    "sg:orig_category":"Restaurantes",
    "sg:phone":"+34 986 61 04 74",
    "sg:postcode":"36780",
    "sg:province":"Pontevedra",
    "wof:name":"Baz Vicente Maria Del Carmen",
    "wof:placetype":"venue"
},
  "geometry": {"coordinates":[-8.880030632,41.8913154602],"type":"Point"}
}