{
  "type": "Feature",
  "properties": {
    "iso:country":"ES",
    "sg:address":"Avda Quevedo, 6",
    "sg:city":"Le\u00f3n",
    "sg:orig_category":"Bancos",
    "sg:phone":"+34 987 23 65 93",
    "sg:postcode":"24009",
    "sg:province":"Le\u00f3n",
    "sg:website":"www.gruposantander.es",
    "wof:name":"Bt Espa\u00d1a Compa\u00d1ia De Servicios Globales De Telecomunicaciones S.a.u.",
    "wof:placetype":"venue"
},
  "geometry": {"coordinates":[-5.584209919,42.6005592346],"type":"Point"}
}