{
  "type": "Feature",
  "properties": {
    "addr:full":"Avda Sants De La Pedra, 59 Sagunt Valencia 46500",
    "addr:housenumber":"59",
    "addr:postcode":"46500",
    "addr:street":"Avda Sants De La Pedra",
    "iso:country":"ES",
    "sg:address":"Avda Sants De La Pedra, 59",
    "sg:city":"Sagunt",
    "sg:orig_category":"Agentes Generales De Seguros",
    "sg:phone":"+34 962 66 19 90",
    "sg:postcode":"46500",
    "sg:province":"Valencia",
    "wof:name":"Cebrian Esteve Miguel",
    "wof:placetype":"venue"
},
  "geometry": {"coordinates":[-0.2759689987,39.6818695068],"type":"Point"}
}