{
  "type": "Feature",
  "properties": {
    "iso:country":"ES",
    "sg:address":"Pase Teruel, 36",
    "sg:city":"Zaragoza",
    "sg:orig_category":"Abogados",
    "sg:phone":"+34 976 23 94 87",
    "sg:postcode":"50004",
    "sg:province":"Zaragoza",
    "wof:name":"Rodriguez Fernandez Antonio Miguel",
    "wof:placetype":"venue"
},
  "geometry": {"coordinates":[-0.8923249841,41.6483078003],"type":"Point"}
}