{
  "type": "Feature",
  "properties": {
    "iso:country":"ES",
    "sg:address":"Calle de Medio Celemin (del), 6",
    "sg:city":"Meco",
    "sg:orig_category":"Bricolaje, Herramientas (al Por Menor)",
    "sg:phone":"+34 918 86 14 43",
    "sg:postcode":"28880",
    "sg:province":"Madrid",
    "wof:name":"Cordoba Aguilera Antonio",
    "wof:placetype":"venue"
},
  "geometry": {"coordinates":[-3.3288209438,40.5534667969],"type":"Point"}
}