{
  "type": "Feature",
  "properties": {
    "addr:full":"Pase Corona (la), 7 Sabi\u00f1anigo Huesca 22600",
    "addr:housenumber":"7",
    "addr:postcode":"22600",
    "addr:street":"Corona La",
    "iso:country":"ES",
    "sg:address":"Pase Corona (la), 7",
    "sg:city":"Sabi\u00f1anigo",
    "sg:orig_category":"Ingeniero",
    "sg:phone":"+34 974 48 12 61",
    "sg:postcode":"22600",
    "sg:province":"Huesca",
    "wof:name":"Bernues Visus Jose Ignacio",
    "wof:placetype":"venue"
},
  "geometry": {"coordinates":[-0.3662390113,42.52526474],"type":"Point"}
}