{
  "type": "Feature",
  "properties": {
    "iso:country":"ES",
    "sg:address":"Ctra Sant Feliu De Guixols, 40",
    "sg:city":"Font De La Polvora",
    "sg:orig_category":"Iglesia Cat\u00d3lica",
    "sg:phone":"+34 972 21 18 63",
    "sg:postcode":"17004",
    "sg:province":"Girona",
    "wof:name":"Parroquia Palol D'onyar-vila-roja",
    "wof:placetype":"venue"
},
  "geometry": {"coordinates":[2.8422400951,41.9735031128],"type":"Point"}
}