{
  "type": "Feature",
  "properties": {
    "iso:country":"ES",
    "sg:address":"El Caminon, S/n",
    "sg:city":"Villaquilambre",
    "sg:orig_category":"Empresas De Carpinter\u00cda",
    "sg:phone":"+34 987 28 17 18",
    "sg:postcode":"24008",
    "sg:province":"Le\u00f3n",
    "wof:name":"Pinto Carre\u00f1o Isidoro",
    "wof:placetype":"venue"
},
  "geometry": {"coordinates":[-5.555150032,42.6466674805],"type":"Point"}
}