{
  "type": "Feature",
  "properties": {
    "iso:country":"ES",
    "sg:address":"Avda Rioja De (la), 2",
    "sg:city":"Logro\u00f1o",
    "sg:orig_category":"\u00d3ptica: Instrumentos (fabricaci\u00d3n)",
    "sg:phone":"+34 941 22 05 26",
    "sg:postcode":"26001",
    "sg:province":"La Rioja",
    "wof:name":"Rodriguez Mozo Maria Concepcion",
    "wof:placetype":"venue"
},
  "geometry": {"coordinates":[-2.446862936,42.4651184082],"type":"Point"}
}