{
  "type": "Feature",
  "properties": {
    "addr:full":"Calle de Dean Hervas, 4 Torralba Calatrava Ciudad Real 13160",
    "addr:housenumber":"4",
    "addr:postcode":"13160",
    "addr:street":"Calle De;Hervas",
    "iso:country":"ES",
    "sg:address":"Calle de Dean Hervas, 4",
    "sg:city":"Torralba Calatrava",
    "sg:orig_category":"Panader\u00cdas, Panader\u00cdas",
    "sg:phone":"+34 926 81 02 29",
    "sg:postcode":"13160",
    "sg:province":"Ciudad Real",
    "wof:name":"Gonca S.l.",
    "wof:placetype":"venue"
},
  "geometry": {"coordinates":[-3.7518837452,39.017414093],"type":"Point"}
}