{
  "type": "Feature",
  "properties": {
    "iso:country":"ES",
    "sg:address":"Calle de Teide, 20",
    "sg:city":"Azuqueca Henares",
    "sg:orig_category":"\u00d3ptica: Instrumentos (fabricaci\u00d3n)",
    "sg:phone":"+34 949 26 46 90",
    "sg:postcode":"19200",
    "sg:province":"Guadalajara",
    "wof:name":"Discoda S.l.",
    "wof:placetype":"venue"
},
  "geometry": {"coordinates":[-3.2594459057,40.5701522827],"type":"Point"}
}