{
  "type": "Feature",
  "properties": {
    "addr:full":"Calle de Doctor Esquerdo, 171 Madrid Madrid 28007",
    "addr:housenumber":"171",
    "addr:postcode":"28007",
    "addr:street":"Calle De Doctor Esquerdo",
    "iso:country":"ES",
    "sg:address":"Calle de Doctor Esquerdo, 171",
    "sg:city":"Madrid",
    "sg:orig_category":"Librer\u00cdas",
    "sg:phone":"+34 915 74 20 92",
    "sg:postcode":"28007",
    "sg:province":"Madrid",
    "wof:name":"Seijo Garcia Concepcion",
    "wof:placetype":"venue"
},
  "geometry": {"coordinates":[-3.6699080467,40.4078826904],"type":"Point"}
}