{
  "type": "Feature",
  "properties": {
    "iso:country":"ES",
    "sg:address":"Esglesia, S/n",
    "sg:city":"Cabo",
    "sg:orig_category":"Administraciones Regionales, Departamentales Y Locales",
    "sg:phone":"+34 973 38 33 20",
    "sg:postcode":"25794",
    "sg:province":"Lleida",
    "wof:name":"Ayuntamiento De Cabo. Pujal",
    "wof:placetype":"venue"
},
  "geometry": {"coordinates":[1.2465531826,42.23620224],"type":"Point"}
}