{
  "type": "Feature",
  "properties": {
    "iso:country":"ES",
    "sg:address":"Lusqui\u00f1os, S/n",
    "sg:city":"Lusqui\u00f1os",
    "sg:orig_category":"Comadronas",
    "sg:phone":"+34 986 85 97 21",
    "sg:postcode":"36158",
    "sg:province":"Pontevedra",
    "wof:name":"Justo Pazos Olga",
    "wof:placetype":"venue"
},
  "geometry": {"coordinates":[-8.601433754,42.4093666077],"type":"Point"}
}