{
  "type": "Feature",
  "properties": {
    "addr:full":"Carrer de Guifre El Pilos, 6 Gava Barcelona 08850",
    "addr:housenumber":"6",
    "addr:postcode":"08850",
    "addr:street":"Carrer De Guifre El Pilos",
    "iso:country":"ES",
    "sg:address":"Carrer de Guifre El Pilos, 6",
    "sg:city":"Gava",
    "sg:orig_category":"Empresarios Y Productoras De Espect\u00c1culos",
    "sg:phone":"+34 936 38 90 45",
    "sg:postcode":"08850",
    "sg:province":"Barcelona",
    "sg:website":"www.stepbcn.com",
    "wof:name":"Step Sponsoring Tv Event P S.l.",
    "wof:placetype":"venue"
},
  "geometry": {"coordinates":[1.9959529638,41.3062705994],"type":"Point"}
}