{
  "type": "Feature",
  "properties": {
    "iso:country":"ES",
    "sg:address":"Carrer de Contralmirall Ferragut, S/n",
    "sg:city":"Magaluf",
    "sg:orig_category":"Molduras, Junquillos, Listones Y Molduras Perforadas",
    "sg:phone":"+34 971 13 06 83",
    "sg:postcode":"07181",
    "sg:province":"Islas Baleares",
    "wof:name":"Ashbolt Adrian Y Otro Cdad",
    "wof:placetype":"venue"
},
  "geometry": {"coordinates":[2.5325810909,39.5102081299],"type":"Point"}
}