{
  "type": "Feature",
  "properties": {
    "addr:full":"Cost Pols, 5 Palma Islas Baleares 07003",
    "addr:housenumber":"5",
    "addr:postcode":"07003",
    "addr:street":"Pols",
    "iso:country":"ES",
    "sg:address":"Cost Pols, 5",
    "sg:city":"Palma",
    "sg:orig_category":"Empresarios Y Productoras De Espect\u00c1culos",
    "sg:phone":"+34 971 22 73 68",
    "sg:postcode":"07003",
    "sg:province":"Islas Baleares",
    "sg:website":"www.arsfestum.com",
    "wof:name":"Ars Festum S.l.",
    "wof:placetype":"venue"
},
  "geometry": {"coordinates":[2.6515200138,39.5728263855],"type":"Point"}
}