{
  "type": "Feature",
  "properties": {
    "addr:full":"B. Serna, 2 Iru\u00f1a Navarra 31005",
    "addr:housenumber":"2",
    "addr:postcode":"31005",
    "addr:street":"B. Serna",
    "iso:country":"ES",
    "sg:address":"B. Serna, 2",
    "sg:city":"Iru\u00f1a",
    "sg:orig_category":"Molduras, Junquillos, Listones Y Molduras Perforadas",
    "sg:phone":"+34 948 15 37 95",
    "sg:postcode":"31005",
    "sg:province":"Navarra",
    "wof:name":"Fernandez Dieguez Dario",
    "wof:placetype":"venue"
},
  "geometry": {"coordinates":[-1.6437540054,42.81275177],"type":"Point"}
}