{
  "type": "Feature",
  "properties": {
    "addr:full":"Pla\u00c7 Ricard Vi\u00d1es, 5 Lleida Lleida 25006",
    "addr:housenumber":"5",
    "addr:postcode":"25006",
    "addr:street":"Vin\u0303Es",
    "iso:country":"ES",
    "sg:address":"Pla\u00c7 Ricard Vi\u00d1es, 5",
    "sg:city":"Lleida",
    "sg:orig_category":"M\u00c9dicos: Estomatolog\u00cda",
    "sg:phone":"+34 973 24 35 96",
    "sg:postcode":"25006",
    "sg:province":"Lleida",
    "wof:name":"Florensa Oribe Xavier",
    "wof:placetype":"venue"
},
  "geometry": {"coordinates":[0.6186609864,41.6185684204],"type":"Point"}
}