{
  "type": "Feature",
  "properties": {
    "iso:country":"ES",
    "sg:address":"Calle de Luis Doreste Silva, 60",
    "sg:city":"Palmas De Gran Canaria",
    "sg:orig_category":"Abogados",
    "sg:phone":"+34 928 24 44 52",
    "sg:postcode":"35004",
    "sg:province":"Las Palmas",
    "wof:name":"Fundacion Canaria Sociosanitaria",
    "wof:placetype":"venue"
},
  "geometry": {"coordinates":[-15.4245958328,28.1200122833],"type":"Point"}
}