{
  "type": "Feature",
  "properties": {
    "iso:country":"ES",
    "sg:address":"Mitarte Kalea, 10",
    "sg:city":"Aretxabaleta",
    "sg:orig_category":"Platos Preparados Refrigerados (fabricaci\u00d3n, Al Por Mayor)",
    "sg:phone":"+34 943 77 06 12",
    "sg:postcode":"20550",
    "sg:province":"Guip\u00f9zcoa",
    "wof:name":"Morales Abarrategi Sonia",
    "wof:placetype":"venue"
},
  "geometry": {"coordinates":[-2.504160881,43.0340805054],"type":"Point"}
}