{
  "type": "Feature",
  "properties": {
    "iso:country":"ES",
    "sg:address":"Carr El Penedes, 73",
    "sg:city":"Lleida",
    "sg:orig_category":"V\u00c1lvulas",
    "sg:phone":"+34 973 24 48 48",
    "sg:postcode":"25005",
    "sg:province":"Lleida",
    "wof:name":"M.k.s. Control Y Regulacion De Fluidos S.l.",
    "wof:placetype":"venue"
},
  "geometry": {"coordinates":[0.6247169971,41.628364563],"type":"Point"}
}