{
  "type": "Feature",
  "properties": {
    "iso:country":"ES",
    "sg:address":"Calle de Universidad, 31",
    "sg:city":"Burgo Osma",
    "sg:orig_category":"Ense\u00d1anza, Formaci\u00d3n Profesional: Aprendizaje",
    "sg:phone":"+34 975 34 03 97",
    "sg:postcode":"42300",
    "sg:province":"Soria",
    "wof:name":"Direccion General De Trafico",
    "wof:placetype":"venue"
},
  "geometry": {"coordinates":[-3.0742990971,41.5880050659],"type":"Point"}
}