{
  "type": "Feature",
  "properties": {
    "iso:country":"ES",
    "sg:address":"Calle de Teniente Coronel Picazo, 1",
    "sg:city":"Minglanilla",
    "sg:orig_category":"Producci\u00d3n De Champi\u00d1ones",
    "sg:phone":"+34 962 18 72 63",
    "sg:postcode":"16260",
    "sg:province":"Cuenca",
    "wof:name":"Peraile Tinaut Jose Antonio",
    "wof:placetype":"venue"
},
  "geometry": {"coordinates":[-1.5950709581,39.5347938538],"type":"Point"}
}