{
  "type": "Feature",
  "properties": {
    "iso:country":"ES",
    "sg:address":"Avda Valle De Esgueva, 16",
    "sg:city":"Valladolid",
    "sg:classifiers":[
        {
            "category":"Personal",
            "subcategory":"Barber",
            "type":"Services"
        }
    ],
    "sg:phone":"+34 983 26 72 64",
    "sg:postcode":"47011",
    "sg:province":"Valladolid",
    "sg:tags":[
        "caballeros",
        "de",
        "peluqueros"
    ],
    "wof:name":"Isla Narganes Enedina",
    "wof:placetype":"venue"
},
  "geometry": {"coordinates":[-4.7060389519,41.6595306396],"type":"Point"}
}