{
  "type": "Feature",
  "properties": {
    "addr:full":"Calle de Titania, 21 Madrid Madrid 28043",
    "addr:housenumber":"21",
    "addr:postcode":"madrid;28043",
    "addr:street":"Calle De Titania",
    "iso:country":"ES",
    "sg:address":"Calle de Titania, 21",
    "sg:city":"Madrid",
    "sg:orig_category":"Grafistas",
    "sg:phone":"+34 913 88 75 22",
    "sg:postcode":"28043",
    "sg:province":"Madrid",
    "wof:name":"Diseno Grafico Idea 2 S.l.",
    "wof:placetype":"venue"
},
  "geometry": {"coordinates":[-3.6570870876,40.4594459534],"type":"Point"}
}