{
  "type": "Feature",
  "properties": {
    "addr:full":"Carrer de Artes, 4 Manresa Barcelona 08243",
    "addr:housenumber":"4",
    "addr:postcode":"08243",
    "addr:street":"Carrer De Artes",
    "iso:country":"ES",
    "sg:address":"Carrer de Artes, 4",
    "sg:city":"Manresa",
    "sg:orig_category":"Cintas, Balduques Y Cierres De Tela (fabricaci\u00d3n, Al Por Mayor)",
    "sg:phone":"+34 938 74 40 98",
    "sg:postcode":"08243",
    "sg:province":"Barcelona",
    "sg:website":"www.byetsa.es",
    "wof:name":"Bieses Y Elementos Textiles S.a.",
    "wof:placetype":"venue"
},
  "geometry": {"coordinates":[1.8402869701,41.7343177795],"type":"Point"}
}