{
  "type": "Feature",
  "properties": {
    "addr:full":"Carrer de Ceramica, 4 Esparreguera Barcelona 08292",
    "addr:housenumber":"4",
    "addr:postcode":"08292",
    "addr:street":"Carrer De Ceramica",
    "iso:country":"ES",
    "sg:address":"Carrer de Ceramica, 4",
    "sg:city":"Esparreguera",
    "sg:orig_category":"Escaparatistas, Decoradores",
    "sg:phone":"+34 937 77 85 02",
    "sg:postcode":"08292",
    "sg:province":"Barcelona",
    "wof:name":"Myrurgia S.a.",
    "wof:placetype":"venue"
},
  "geometry": {"coordinates":[1.8762799501,41.5253601074],"type":"Point"}
}