{
  "type": "Feature",
  "properties": {
    "addr:full":"Calle de Tronchon, 2 Alca\u00f1iz Teruel 44600",
    "addr:housenumber":"2",
    "addr:postcode":"44600",
    "addr:street":"Calle De Tronchon",
    "iso:country":"ES",
    "sg:address":"Calle de Tronchon, 2",
    "sg:city":"Alca\u00f1iz",
    "sg:orig_category":"Peluquer\u00cdas, Peluquer\u00cda Mixta",
    "sg:phone":"+34 978 87 05 76",
    "sg:postcode":"44600",
    "sg:province":"Teruel",
    "wof:name":"Camacho Garcia Isabel",
    "wof:placetype":"venue"
},
  "geometry": {"coordinates":[-0.1403889954,41.0530204773],"type":"Point"}
}