{
  "type": "Feature",
  "properties": {
    "iso:country":"ES",
    "sg:address":"Ctra Pe\u00d1aranda, S/n",
    "sg:city":"Alba Tormes",
    "sg:orig_category":"Mec\u00c1nico Del Autom\u00d3vil",
    "sg:phone":"+34 923 30 09 65",
    "sg:postcode":"37800",
    "sg:province":"Salamanca",
    "wof:name":"Talleres Electricos Lucas S.l.",
    "wof:placetype":"venue"
},
  "geometry": {"coordinates":[-5.5058341026,40.827495575],"type":"Point"}
}