{
  "type": "Feature",
  "properties": {
    "iso:country":"ES",
    "sg:address":"Calle de Poeta Paredes, 8",
    "sg:city":"Cordoba",
    "sg:orig_category":"Contenedores (mercanc\u00cdas)",
    "sg:phone":"+34 957 27 80 17",
    "sg:postcode":"14012",
    "sg:province":"C\u00f3rdoba",
    "wof:name":"Bravo Alcantara Francisco",
    "wof:placetype":"venue"
},
  "geometry": {"coordinates":[-4.8052229881,37.9170684814],"type":"Point"}
}