{
  "type": "Feature",
  "properties": {
    "addr:full":"Calle de Laurel, 14 Conjunto Residencial Murcia 30100",
    "addr:housenumber":"14",
    "addr:postcode":"30100",
    "addr:street":"Calle De Laurel",
    "iso:country":"ES",
    "sg:address":"Calle de Laurel, 14",
    "sg:city":"Conjunto Residencial",
    "sg:orig_category":"Peluquer\u00cdas, Peluquer\u00cda Mixta",
    "sg:phone":"+34 968 83 49 06",
    "sg:postcode":"30100",
    "sg:province":"Murcia",
    "wof:name":"Andres Sanchez Leticia",
    "wof:placetype":"venue"
},
  "geometry": {"coordinates":[-1.1622318029,38.0149421692],"type":"Point"}
}