{
  "type": "Feature",
  "properties": {
    "iso:country":"ES",
    "sg:address":"Leyre-leire Kalea, 4",
    "sg:city":"Iru\u00f1a",
    "sg:orig_category":"Locales Deportivos",
    "sg:phone":"+34 948 22 68 15",
    "sg:postcode":"31002",
    "sg:province":"Navarra",
    "wof:name":"Aqua Sport Navarra S.l.",
    "wof:placetype":"venue"
},
  "geometry": {"coordinates":[-1.6367496252,42.8156013489],"type":"Point"}
}