{
  "type": "Feature",
  "properties": {
    "iso:country":"ES",
    "sg:address":"Barr Can Negre, 18",
    "sg:city":"Can Negre",
    "sg:orig_category":"Empresas De Carpinter\u00cda De Madera",
    "sg:phone":"+34 971 19 02 60",
    "sg:postcode":"07819",
    "sg:province":"Islas Baleares",
    "wof:name":"Antonio Garcia Cardenas Y Otros Cdad.",
    "wof:placetype":"venue"
},
  "geometry": {"coordinates":[2.8577105999,39.5341796875],"type":"Point"}
}