{
  "type": "Feature",
  "properties": {
    "iso:country":"ES",
    "sg:address":"Ctra Playas, 104",
    "sg:city":"Playa Honda",
    "sg:orig_category":"Alquiler De Apartamentos",
    "sg:phone":"+34 928 82 34 70",
    "sg:postcode":"35509",
    "sg:province":"Las Palmas",
    "wof:name":"Bejeque S.l.",
    "wof:placetype":"venue"
},
  "geometry": {"coordinates":[-13.5969276428,28.9507198334],"type":"Point"}
}