{
  "type": "Feature",
  "properties": {
    "iso:country":"ES",
    "sg:address":"Calle de Aduana, 13",
    "sg:city":"Irun",
    "sg:orig_category":"Sindicatos De Trabajadores",
    "sg:phone":"+34 943 61 72 47",
    "sg:postcode":"20303",
    "sg:province":"Guip\u00f9zcoa",
    "wof:name":"Mca-ugt",
    "wof:placetype":"venue"
},
  "geometry": {"coordinates":[-1.7973792553,43.3400650024],"type":"Point"}
}