{
  "type": "Feature",
  "properties": {
    "addr:full":"Carrer de Sant Cristofol, 19 Manresa Barcelona 08243",
    "addr:housenumber":"19",
    "addr:postcode":"08243",
    "addr:street":"Carrer De Sant Cristofol",
    "iso:country":"ES",
    "sg:address":"Carrer de Sant Cristofol, 19",
    "sg:city":"Manresa",
    "sg:orig_category":"Panader\u00cdas, Panader\u00cdas",
    "sg:phone":"+34 938 77 23 40",
    "sg:postcode":"08243",
    "sg:province":"Barcelona",
    "wof:name":"Sobrevias Servet Salvador",
    "wof:placetype":"venue"
},
  "geometry": {"coordinates":[1.8359099627,41.7300338745],"type":"Point"}
}