{
  "type": "Feature",
  "properties": {
    "addr:full":"Calle de Mundaiz, 10 Donostia-san Sebastian Guip\u00f9zcoa 20012",
    "addr:housenumber":"10",
    "addr:postcode":"20012",
    "addr:street":"Calle De Mundaiz",
    "iso:country":"ES",
    "sg:address":"Calle de Mundaiz, 10",
    "sg:city":"Donostia-san Sebastian",
    "sg:orig_category":"Psic\u00d3logos",
    "sg:phone":"+34 943 28 57 05",
    "sg:postcode":"20012",
    "sg:province":"Guip\u00f9zcoa",
    "wof:name":"Isasti Arregui Maria Elena",
    "wof:placetype":"venue"
},
  "geometry": {"coordinates":[-1.9764809608,43.315120697],"type":"Point"}
}