{
  "type": "Feature",
  "properties": {
    "addr:full":"Calle de Sepulveda (de), 6 Alcobendas Madrid 28108",
    "addr:postcode":"28108",
    "addr:street":"Calle De Sepulveda De 6",
    "iso:country":"ES",
    "sg:address":"Calle de Sepulveda (de), 6",
    "sg:city":"Alcobendas",
    "sg:orig_category":"Negocio De Madera",
    "sg:phone":"+34 916 61 64 68",
    "sg:postcode":"28108",
    "sg:province":"Madrid",
    "wof:name":"Tableros Martinez C.b.",
    "wof:placetype":"venue"
},
  "geometry": {"coordinates":[-3.6549623013,40.5277519226],"type":"Point"}
}