{
  "type": "Feature",
  "properties": {
    "addr:full":"Calle de General Yague, 15 Llanos De Aridane Santa Cruz De Tenerife 38760",
    "addr:housenumber":"15",
    "addr:postcode":"38760",
    "addr:street":"Calle De General Yague",
    "iso:country":"ES",
    "sg:address":"Calle de General Yague, 15",
    "sg:city":"Llanos De Aridane",
    "sg:orig_category":"Alquiler De Veh\u00cdculos: Turismos Y Utilitarios",
    "sg:phone":"+34 922 46 33 90",
    "sg:postcode":"38760",
    "sg:province":"Santa Cruz De Tenerife",
    "wof:name":"Autos Soyka S.l.",
    "wof:placetype":"venue"
},
  "geometry": {"coordinates":[-17.9127178192,28.6560401917],"type":"Point"}
}