{
  "type": "Feature",
  "properties": {
    "iso:country":"ES",
    "sg:address":"Calle de Felipe Ii, 14",
    "sg:city":"Ciudad Real",
    "sg:orig_category":"Promotores Constructores",
    "sg:phone":"+34 926 22 94 94",
    "sg:postcode":"13003",
    "sg:province":"Ciudad Real",
    "wof:name":"Comunidad Propietarios Calle Felipe Ii",
    "wof:placetype":"venue"
},
  "geometry": {"coordinates":[-3.9216940403,38.9892921448],"type":"Point"}
}