{
  "type": "Feature",
  "properties": {
    "addr:full":"Calle de Fray Ceferino, 24 Oviedo Asturias 33001",
    "addr:housenumber":"24",
    "addr:postcode":"33001",
    "addr:street":"Calle De Fray Ceferino",
    "iso:country":"ES",
    "sg:address":"Calle de Fray Ceferino, 24",
    "sg:city":"Oviedo",
    "sg:orig_category":"Asociaciones, Organismos Culturales Y Socioeducativos",
    "sg:phone":"+34 985 21 08 82",
    "sg:postcode":"33001",
    "sg:province":"Asturias",
    "wof:name":"Centro Riojano De Asturias",
    "wof:placetype":"venue"
},
  "geometry": {"coordinates":[-5.8505821228,43.3667144775],"type":"Point"}
}