{
  "type": "Feature",
  "properties": {
    "addr:full":"Carrer de Pin I Soler, 8 Tarragona Tarragona 43002",
    "addr:housenumber":"8",
    "addr:postcode":"43002",
    "addr:street":"Carrer De Pin I Soler",
    "iso:country":"ES",
    "sg:address":"Carrer de Pin I Soler, 8",
    "sg:city":"Tarragona",
    "sg:orig_category":"Mec\u00c1nico Del Autom\u00d3vil",
    "sg:phone":"+34 977 21 79 59",
    "sg:postcode":"43002",
    "sg:province":"Tarragona",
    "wof:name":"Sans Camilo S.c.c.l.",
    "wof:placetype":"venue"
},
  "geometry": {"coordinates":[1.2486890554,41.1189537048],"type":"Point"}
}