{
  "type": "Feature",
  "properties": {
    "iso:country":"ES",
    "sg:address":"Barr Usila, 2",
    "sg:city":"Ugao-miraballes",
    "sg:orig_category":"Montaje (empresas De)",
    "sg:phone":"+34 946 48 13 20",
    "sg:postcode":"48490",
    "sg:province":"Vizcaya",
    "wof:name":"Montajes Idimer S.l.",
    "wof:placetype":"venue"
},
  "geometry": {"coordinates":[-2.9033401012,43.1840133667],"type":"Point"}
}