{
  "type": "Feature",
  "properties": {
    "addr:full":"Calle de Muralla De La, 9 Aviles Asturias 33401",
    "addr:housenumber":"9",
    "addr:postcode":"33401",
    "addr:street":"Calle De Muralla De La",
    "iso:country":"ES",
    "sg:address":"Calle de Muralla De La, 9",
    "sg:city":"Aviles",
    "sg:orig_category":"Psic\u00d3logos",
    "sg:phone":"+34 985 52 19 62",
    "sg:postcode":"33401",
    "sg:province":"Asturias",
    "wof:name":"Garcia Perez Maria Luisa",
    "wof:placetype":"venue"
},
  "geometry": {"coordinates":[-5.9233851433,43.5573005676],"type":"Point"}
}