{
  "type": "Feature",
  "properties": {
    "addr:full":"Ctra. Nnal. Seiscientos Uno, Km. 0052,0 Cuellar Segovia 40200",
    "addr:postcode":"40200",
    "addr:street":"Ctra. Nnal.;Uno Km. 0052,0;Segovia",
    "iso:country":"ES",
    "sg:address":"Ctra. Nnal. Seiscientos Uno, Km. 0052,0",
    "sg:city":"Cuellar",
    "sg:orig_category":"Empresarios",
    "sg:phone":"+34 921 14 07 26",
    "sg:postcode":"40200",
    "sg:province":"Segovia",
    "wof:name":"Mariano Rico S. L.",
    "wof:placetype":"venue"
},
  "geometry": {"coordinates":[-4.3119688034,41.4013137817],"type":"Point"}
}