{
  "type": "Feature",
  "properties": {
    "addr:full":"Carrer de Bosseria, 7 Palma Islas Baleares 07001",
    "addr:housenumber":"7",
    "addr:postcode":"07001",
    "addr:street":"Carrer De Bosseria",
    "iso:country":"ES",
    "sg:address":"Carrer de Bosseria, 7",
    "sg:city":"Palma",
    "sg:orig_category":"Marroquiner\u00cda (confecci\u00d3n)",
    "sg:phone":"+34 971 40 47 57",
    "sg:postcode":"07001",
    "sg:province":"Islas Baleares",
    "wof:name":"Scuba Bahia S.l.",
    "wof:placetype":"venue"
},
  "geometry": {"coordinates":[2.6519620419,39.5707931519],"type":"Point"}
}