{
  "type": "Feature",
  "properties": {
    "addr:full":"Pol Ind Sector Veinte, S/n Almeria Almer\u00eda 04009",
    "addr:housenumber":"s / n",
    "addr:postcode":"04009",
    "addr:street":"Veinte",
    "iso:country":"ES",
    "sg:address":"Pol Ind Sector Veinte, S/n",
    "sg:city":"Almeria",
    "sg:orig_category":"Talleres De Corte Y Confecci\u00d3n",
    "sg:phone":"+34 950 22 51 96",
    "sg:postcode":"04009",
    "sg:province":"Almer\u00eda",
    "wof:name":"Confecciones Reymar S.l.",
    "wof:placetype":"venue"
},
  "geometry": {"coordinates":[-2.3886790276,36.8506851196],"type":"Point"}
}