{
  "type": "Feature",
  "properties": {
    "addr:full":"Avda Compromiso De Caspe, S/n Zaragoza Zaragoza 50002",
    "addr:housenumber":"s / n",
    "addr:postcode":"50002",
    "addr:street":"Avda Compromiso De Caspe",
    "iso:country":"ES",
    "sg:address":"Avda Compromiso De Caspe, S/n",
    "sg:city":"Zaragoza",
    "sg:orig_category":"Piscinas, Accesorios, Suministros (fabricaci\u00d3n, Al Por Mayor)",
    "sg:phone":"+34 976 59 79 55",
    "sg:postcode":"50002",
    "sg:province":"Zaragoza",
    "wof:name":"Stadium Las Fuentes S. A.",
    "wof:placetype":"venue"
},
  "geometry": {"coordinates":[-0.8703340292,41.6460838318],"type":"Point"}
}