{
  "type": "Feature",
  "properties": {
    "iso:country":"ES",
    "sg:address":"Carrer de Goya, 73",
    "sg:city":"Mataro",
    "sg:orig_category":"Fabricaci\u00d3n, Venta De Cuadros, Accesorios Para Enmarcar",
    "sg:phone":"+34 937 99 22 00",
    "sg:postcode":"08302",
    "sg:province":"Barcelona",
    "wof:name":"Hernandez Guell Oriol",
    "wof:placetype":"venue"
},
  "geometry": {"coordinates":[2.4352850914,41.5378608704],"type":"Point"}
}