{
  "type": "Feature",
  "properties": {
    "addr:full":"Carr Ramon Y Cajal, De, 39 Carcaixent Valencia 46740",
    "addr:housenumber":"39",
    "addr:postcode":"46740",
    "addr:street":"Carr Ramon Y Cajal De",
    "iso:country":"ES",
    "sg:address":"Carr Ramon Y Cajal, De, 39",
    "sg:city":"Carcaixent",
    "sg:orig_category":"Caf\u00c9s, Bares, Cervecer\u00cdas",
    "sg:phone":"+34 962 43 17 91",
    "sg:postcode":"46740",
    "sg:province":"Valencia",
    "wof:name":"Perez Rosalen Milagros",
    "wof:placetype":"venue"
},
  "geometry": {"coordinates":[-0.447454989,39.1232910156],"type":"Point"}
}