{
  "type": "Feature",
  "properties": {
    "iso:country":"ES",
    "sg:address":"Calle de Doctor Mara\u00d1on, 5",
    "sg:city":"Valverde Camino",
    "sg:orig_category":"Restaurantes",
    "sg:phone":"+34 959 55 50 36",
    "sg:postcode":"21600",
    "sg:province":"Huelva",
    "wof:name":"Alvarez Garcia Francisco Javier",
    "wof:placetype":"venue"
},
  "geometry": {"coordinates":[-6.7487592697,37.5747413635],"type":"Point"}
}