{
  "type": "Feature",
  "properties": {
    "iso:country":"ES",
    "sg:address":"C/ Vila De Madrid, 45",
    "sg:city":"Paterna",
    "sg:orig_category":"Charcuter\u00cdas (al Por Mayor)",
    "sg:phone":"+34 961 34 11 12",
    "sg:postcode":"46988",
    "sg:province":"Valencia",
    "wof:name":"Carnicas Serrano S.l.",
    "wof:placetype":"venue"
},
  "geometry": {"coordinates":[-0.4687919915,39.5216217041],"type":"Point"}
}