{
  "type": "Feature",
  "properties": {
    "addr:full":"Calle de Agua, 21 Berja Almer\u00eda 04760",
    "addr:housenumber":"21",
    "addr:postcode":"04760",
    "addr:street":"Calle De Agua",
    "iso:country":"ES",
    "sg:address":"Calle de Agua, 21",
    "sg:city":"Berja",
    "sg:orig_category":"Fisioterapia",
    "sg:phone":"+34 950 49 16 39",
    "sg:postcode":"04760",
    "sg:province":"Almer\u00eda",
    "wof:name":"Cespedes Lopez Francisco Javier",
    "wof:placetype":"venue"
},
  "geometry": {"coordinates":[-2.9487359524,36.8463668823],"type":"Point"}
}