{
  "type": "Feature",
  "properties": {
    "iso:country":"ES",
    "sg:address":"Rua Progreso (do), 11",
    "sg:city":"Ourense",
    "sg:orig_category":"Promotores Constructores",
    "sg:phone":"+34 988 25 16 39",
    "sg:postcode":"32005",
    "sg:province":"Ourense",
    "wof:name":"Elementos Para La Construccion Xeixalvo S.l.unipersonal",
    "wof:placetype":"venue"
},
  "geometry": {"coordinates":[-7.864967823,42.3308486938],"type":"Point"}
}