{
  "type": "Feature",
  "properties": {
    "iso:country":"ES",
    "sg:address":"Pol. Ind. Rio Do Pozo, S/n",
    "sg:city":"Naron",
    "sg:orig_category":"Construcciones Met\u00c1licas",
    "sg:phone":"+34 981 39 70 65",
    "sg:postcode":"15578",
    "sg:province":"La Coru\u00f1a",
    "wof:name":"Artabro Sandeu S.l.",
    "wof:placetype":"venue"
},
  "geometry": {"coordinates":[-8.1807661057,43.5370521545],"type":"Point"}
}