{
  "type": "Feature",
  "properties": {
    "addr:full":"Calle de Real, 18 Linea De La Concepcion C\u00e1diz 11300",
    "addr:housenumber":"18",
    "addr:postcode":"11300",
    "addr:street":"Calle De Real;Ca\u0301Diz",
    "iso:country":"ES",
    "sg:address":"Calle de Real, 18",
    "sg:city":"Linea De La Concepcion",
    "sg:orig_category":"Inmobiliaria (agencias)",
    "sg:phone":"+34 956 17 30 40",
    "sg:postcode":"11300",
    "sg:province":"C\u00e1diz",
    "sg:website":"impulsalalinea@wanadoo.es",
    "wof:name":"Impulsa La Linea S.l.",
    "wof:placetype":"venue"
},
  "geometry": {"coordinates":[-5.3490409851,36.16173172],"type":"Point"}
}