{
  "type": "Feature",
  "properties": {
    "iso:country":"ES",
    "sg:address":"Calle de Alfarerias Bajas, 7",
    "sg:city":"Villarrobledo",
    "sg:orig_category":"Ropa Para Se\u00d1oras (al Por Menor)",
    "sg:phone":"+34 967 14 58 72",
    "sg:postcode":"02600",
    "sg:province":"Albacete",
    "wof:name":"Acento Moda S.l.",
    "wof:placetype":"venue"
},
  "geometry": {"coordinates":[-2.6028416157,39.2676315308],"type":"Point"}
}