{
  "type": "Feature",
  "properties": {
    "addr:full":"Calle de Ignacio Gomez Millan, 2 Palomares Rio Sevilla 41928",
    "addr:housenumber":"2",
    "addr:postcode":"41928",
    "addr:street":"Calle De Ignacio Gomez Millan;Rio Sevilla",
    "iso:country":"ES",
    "sg:address":"Calle de Ignacio Gomez Millan, 2",
    "sg:city":"Palomares Rio",
    "sg:orig_category":"Ropa Para Se\u00d1oras Y Caballeros (al Por Menor)",
    "sg:phone":"+34 955 76 44 06",
    "sg:postcode":"41928",
    "sg:province":"Sevilla",
    "wof:name":"Sanchez Sanchez Maria Teresa",
    "wof:placetype":"venue"
},
  "geometry": {"coordinates":[-6.0594229698,37.3220024109],"type":"Point"}
}