{
  "type": "Feature",
  "properties": {
    "addr:full":"Avda Fuente Nueva (de La), 6 San Sebastian De Los Reyes Madrid 28700",
    "addr:postcode":"28700",
    "addr:street":"Avda Fuente Nueva De La 6",
    "iso:country":"ES",
    "sg:address":"Avda Fuente Nueva (de La), 6",
    "sg:city":"San Sebastian De Los Reyes",
    "sg:orig_category":"Mec\u00c1nico Del Autom\u00d3vil",
    "sg:phone":"+34 916 53 61 92",
    "sg:postcode":"28700",
    "sg:province":"Madrid",
    "wof:name":"Industrial De Vehiculos S.l.",
    "wof:placetype":"venue"
},
  "geometry": {"coordinates":[-3.6137769222,40.5480499268],"type":"Point"}
}