{
  "type": "Feature",
  "properties": {
    "addr:full":"C/ Penedes, 7 Cerdanyola Valles Barcelona 08290",
    "addr:housenumber":"7",
    "addr:postcode":"08290",
    "addr:street":"C / Penedes;Valles Barcelona",
    "iso:country":"ES",
    "sg:address":"C/ Penedes, 7",
    "sg:city":"Cerdanyola Valles",
    "sg:orig_category":"Contenedores (mercanc\u00cdas)",
    "sg:phone":"+34 936 92 22 04",
    "sg:postcode":"08290",
    "sg:province":"Barcelona",
    "wof:name":"Valderrama Brualla Adolfo",
    "wof:placetype":"venue"
},
  "geometry": {"coordinates":[2.130546093,41.4942436218],"type":"Point"}
}