{
  "type": "Feature",
  "properties": {
    "addr:full":"Calle de San Juan, 28 Malaga M\u00e1laga 29005",
    "addr:housenumber":"28",
    "addr:postcode":"29005",
    "addr:street":"Calle De San Juan;Ma\u0301Laga",
    "iso:country":"ES",
    "sg:address":"Calle de San Juan, 28",
    "sg:city":"Malaga",
    "sg:orig_category":"Retoques De Vestidos",
    "sg:phone":"+34 952 22 40 53",
    "sg:postcode":"29005",
    "sg:province":"M\u00e1laga",
    "wof:name":"Elvira Juste Soledad",
    "wof:placetype":"venue"
},
  "geometry": {"coordinates":[-4.4236102104,36.7199554443],"type":"Point"}
}