{
  "type": "Feature",
  "properties": {
    "addr:full":"Calle de Almirante Boado Endeiza, 9 Arrecife Las Palmas 35500",
    "addr:housenumber":"9",
    "addr:postcode":"35500",
    "addr:street":"Calle De Almirante Boado Endeiza",
    "iso:country":"ES",
    "sg:address":"Calle de Almirante Boado Endeiza, 9",
    "sg:city":"Arrecife",
    "sg:orig_category":"Ingenier\u00cda, Centros De Estudios (industria)",
    "sg:phone":"+34 928 82 40 04",
    "sg:postcode":"35500",
    "sg:province":"Las Palmas",
    "wof:name":"Crisal Ingenieria S.l.",
    "wof:placetype":"venue"
},
  "geometry": {"coordinates":[-13.5551204681,28.9583778381],"type":"Point"}
}