{
  "type": "Feature",
  "properties": {
    "iso:country":"ES",
    "sg:address":"Calle de General Mola, 1",
    "sg:city":"Cervera Pisuerga",
    "sg:orig_category":"Florister\u00cdas",
    "sg:phone":"+34 979 87 04 28",
    "sg:postcode":"34840",
    "sg:province":"Palencia",
    "wof:name":"Michelena Revuelta Maria Luisa",
    "wof:placetype":"venue"
},
  "geometry": {"coordinates":[-4.4982390404,42.8679275513],"type":"Point"}
}