{
  "type": "Feature",
  "properties": {
    "iso:country":"ES",
    "sg:address":"Calle de Castillo De Azuaga, 7",
    "sg:city":"Badajoz",
    "sg:orig_category":"Agencias Y Agentes Comerciales, Representantes",
    "sg:phone":"+34 924 27 78 87",
    "sg:postcode":"06006",
    "sg:province":"Badajoz",
    "wof:name":"Gomez Fernandez-aguado Francisco Frutos",
    "wof:placetype":"venue"
},
  "geometry": {"coordinates":[-6.9925060272,38.8841896057],"type":"Point"}
}