{
  "type": "Feature",
  "properties": {
    "addr:full":"Carrer de Fontanelles, 26 Fontanelles Barcelona 08510",
    "addr:housenumber":"26",
    "addr:postcode":"08510",
    "addr:street":"Carrer De Fontanelles",
    "iso:country":"ES",
    "sg:address":"Carrer de Fontanelles, 26",
    "sg:city":"Fontanelles",
    "sg:orig_category":"Fabricaci\u00d3n De Harinas, S\u00c9molas, Productos De Elaboraci\u00d3n Del Grano",
    "sg:phone":"+34 938 54 09 27",
    "sg:postcode":"08510",
    "sg:province":"Barcelona",
    "wof:name":"Moli Muntada S.l.",
    "wof:placetype":"venue"
},
  "geometry": {"coordinates":[2.3007199764,41.9688186646],"type":"Point"}
}