{
  "type": "Feature",
  "properties": {
    "addr:full":"Carr Ave Maria, 1 Alfara De Algimia Valencia 46148",
    "addr:housenumber":"1",
    "addr:postcode":"46148",
    "addr:street":"Carr Ave Maria",
    "iso:country":"ES",
    "sg:address":"Carr Ave Maria, 1",
    "sg:city":"Alfara De Algimia",
    "sg:orig_category":"Aguas (distribuci\u00d3n, Servicios)",
    "sg:phone":"+34 962 62 50 00",
    "sg:postcode":"46148",
    "sg:province":"Valencia",
    "wof:name":"Sociedad Espa\u00f1ola De Abastecimientos S.a.",
    "wof:placetype":"venue"
},
  "geometry": {"coordinates":[-0.3624440134,39.7540664673],"type":"Point"}
}