{
  "type": "Feature",
  "properties": {
    "addr:full":"Calle de Pablo Casals, 6 Marbella M\u00e1laga 29600",
    "addr:housenumber":"6",
    "addr:postcode":"29600",
    "addr:street":"Calle De Pablo Casals;Ma\u0301Laga",
    "iso:country":"ES",
    "sg:address":"Calle de Pablo Casals, 6",
    "sg:city":"Marbella",
    "sg:orig_category":"M\u00c9dicos: Estomatolog\u00cda",
    "sg:phone":"+34 952 86 29 99",
    "sg:postcode":"29600",
    "sg:province":"M\u00e1laga",
    "wof:name":"Pariente El Grably Karina",
    "wof:placetype":"venue"
},
  "geometry": {"coordinates":[-4.8936080933,36.5092468262],"type":"Point"}
}