{
  "type": "Feature",
  "properties": {
    "addr:full":"Av Manuel Girona, 28 Castelldefels Barcelona 08860",
    "addr:housenumber":"28",
    "addr:postcode":"08860",
    "addr:street":"Av Manuel Girona",
    "iso:country":"ES",
    "sg:address":"Av Manuel Girona, 28",
    "sg:city":"Castelldefels",
    "sg:orig_category":"Art\u00cdculos De Decoraci\u00d3n",
    "sg:phone":"+34 936 65 09 41",
    "sg:postcode":"08860",
    "sg:province":"Barcelona",
    "wof:name":"Torres Aranda C.b.",
    "wof:placetype":"venue"
},
  "geometry": {"coordinates":[1.9825450182,41.2856636047],"type":"Point"}
}