{
  "type": "Feature",
  "properties": {
    "addr:full":"Pl Sant Salvador, 17 Sabadell Barcelona 08202",
    "addr:housenumber":"17",
    "addr:postcode":"08202",
    "addr:street":"Pl Sant Salvador",
    "iso:country":"ES",
    "sg:address":"Pl Sant Salvador, 17",
    "sg:city":"Sabadell",
    "sg:orig_category":"Iglesia Cat\u00d3lica",
    "sg:phone":"+34 937 25 73 49",
    "sg:postcode":"08202",
    "sg:province":"Barcelona",
    "wof:name":"Parroquia San Salvador",
    "wof:placetype":"venue"
},
  "geometry": {"coordinates":[2.1165590286,41.5494842529],"type":"Point"}
}