{
  "type": "Feature",
  "properties": {
    "iso:country":"ES",
    "sg:address":"Carrer de Violeta, 21",
    "sg:city":"Vendrell",
    "sg:orig_category":"Electrodom\u00c9sticos (al Por Menor)",
    "sg:phone":"+34 977 66 60 03",
    "sg:postcode":"43700",
    "sg:province":"Tarragona",
    "wof:name":"Tecnicos Asociados Miralles S.l.",
    "wof:placetype":"venue"
},
  "geometry": {"coordinates":[1.5191099644,41.2301483154],"type":"Point"}
}