{
  "type": "Feature",
  "properties": {
    "iso:country":"ES",
    "sg:address":"Calle de Oro, S/n",
    "sg:city":"Valladolid",
    "sg:orig_category":"Contenedores (mercanc\u00cdas)",
    "sg:phone":"+34 983 20 02 02",
    "sg:postcode":"47012",
    "sg:province":"Valladolid",
    "wof:name":"Transportes Duco S.l.",
    "wof:placetype":"venue"
},
  "geometry": {"coordinates":[-4.7059688568,41.6159591675],"type":"Point"}
}