{
  "type": "Feature",
  "properties": {
    "addr:full":"Rua Antonio Palacios, 145 Porri\u00f1o Pontevedra 36400",
    "addr:housenumber":"145",
    "addr:postcode":"36400",
    "addr:street":"Rua Antonio Palacios",
    "iso:country":"ES",
    "sg:address":"Rua Antonio Palacios, 145",
    "sg:city":"Porri\u00f1o",
    "sg:orig_category":"Cl\u00cdnicas M\u00c9dicas",
    "sg:phone":"+34 986 33 49 90",
    "sg:postcode":"36400",
    "sg:province":"Pontevedra",
    "wof:name":"Clinica Del Condado S. L.",
    "wof:placetype":"venue"
},
  "geometry": {"coordinates":[-8.6159791946,42.1605491638],"type":"Point"}
}