{
  "type": "Feature",
  "properties": {
    "addr:full":"Carrer de Cuba, 5 Mataro Barcelona 08302",
    "addr:housenumber":"5",
    "addr:postcode":"08302",
    "addr:street":"Carrer De Cuba",
    "iso:country":"ES",
    "sg:address":"Carrer de Cuba, 5",
    "sg:city":"Mataro",
    "sg:orig_category":"Psic\u00d3logos",
    "sg:phone":"+34 937 41 47 23",
    "sg:postcode":"08302",
    "sg:province":"Barcelona",
    "wof:name":"Schirado Ljubetic Maria Cristina",
    "wof:placetype":"venue"
},
  "geometry": {"coordinates":[2.4399180412,41.5379562378],"type":"Point"}
}