{
  "type": "Feature",
  "properties": {
    "iso:country":"ES",
    "sg:address":"Avda I(p Campollano), 25",
    "sg:city":"Albacete",
    "sg:orig_category":"Confecci\u00d3n : Material, Suministros Y Accesorios",
    "sg:phone":"+34 967 21 12 25",
    "sg:postcode":"02006",
    "sg:province":"Albacete",
    "wof:name":"Cortebies Textiles S.l.",
    "wof:placetype":"venue"
},
  "geometry": {"coordinates":[-1.8999890089,38.9776191711],"type":"Point"}
}