{
  "type": "Feature",
  "properties": {
    "iso:country":"ES",
    "sg:address":"Luga Poligono Industrial De Roces, S/n",
    "sg:city":"Gijon",
    "sg:orig_category":"Comercio De Mobiliario De Oficina",
    "sg:phone":"+34 985 30 70 11",
    "sg:postcode":"33211",
    "sg:province":"Asturias",
    "sg:website":"www.apsanet.com",
    "wof:name":"Almacenes Pumarin S. A.",
    "wof:placetype":"venue"
},
  "geometry": {"coordinates":[-5.6852426529,43.5228233337],"type":"Point"}
}