{
  "type": "Feature",
  "properties": {
    "iso:country":"ES",
    "sg:address":"Zuberoa Kalea, 6",
    "sg:city":"Zarautz",
    "sg:orig_category":"Discapacitados",
    "sg:phone":"+34 943 83 43 85",
    "sg:postcode":"20800",
    "sg:province":"Guip\u00f9zcoa",
    "wof:name":"Atzegi",
    "wof:placetype":"venue"
},
  "geometry": {"coordinates":[-2.1723749638,43.2800636292],"type":"Point"}
}