{
  "type": "Feature",
  "properties": {
    "addr:full":"Partida Calvari, S/n Amposta Tarragona 43870",
    "addr:housenumber":"/ n",
    "addr:postcode":"43870",
    "addr:street":"Partida Calvari S",
    "iso:country":"ES",
    "sg:address":"Partida Calvari, S/n",
    "sg:city":"Amposta",
    "sg:orig_category":"Construcciones Met\u00c1licas",
    "sg:phone":"+34 977 70 15 01",
    "sg:postcode":"43870",
    "sg:province":"Tarragona",
    "wof:name":"Construccions Metaliques Ebromar S.l.",
    "wof:placetype":"venue"
},
  "geometry": {"coordinates":[0.5797849894,40.7130432129],"type":"Point"}
}