{
  "type": "Feature",
  "properties": {
    "addr:full":"Carr Ciutat De Laval, 23 Gandia Valencia 46700",
    "addr:housenumber":"23",
    "addr:postcode":"46700",
    "addr:street":"Carr Ciutat De Laval;Valencia",
    "iso:country":"ES",
    "sg:address":"Carr Ciutat De Laval, 23",
    "sg:city":"Gandia",
    "sg:orig_category":"Inform\u00c1tica (estudios, Servicios, Asesor\u00cda, Formaci\u00d3n)",
    "sg:phone":"+34 962 95 04 40",
    "sg:postcode":"46700",
    "sg:province":"Valencia",
    "sg:website":"www.igbinformatica.com",
    "wof:name":"Igb Informatica S.l.",
    "wof:placetype":"venue"
},
  "geometry": {"coordinates":[-0.1913339943,38.960735321],"type":"Point"}
}