{
  "type": "Feature",
  "properties": {
    "iso:country":"ES",
    "sg:address":"Avda Espa\u00d1a (de), 115",
    "sg:city":"Coslada",
    "sg:orig_category":"Ense\u00d1anza Secundaria: Colegios Y Escuelas Privadas",
    "sg:phone":"+34 916 71 07 84",
    "sg:postcode":"28820",
    "sg:province":"Madrid",
    "wof:name":"Comunidad Autonoma De Madrid-centros De Educacion",
    "wof:placetype":"venue"
},
  "geometry": {"coordinates":[-3.5507779121,40.422000885],"type":"Point"}
}