{
  "type": "Feature",
  "properties": {
    "addr:full":"Avda Juan Carlos I, 1 Torre-pacheco Murcia 30700",
    "addr:housenumber":"1",
    "addr:postcode":"30700",
    "addr:street":"Avda Juan Carlos I",
    "iso:country":"ES",
    "sg:address":"Avda Juan Carlos I, 1",
    "sg:city":"Torre-pacheco",
    "sg:orig_category":"Bazares, Art\u00cdculos De Limpieza Y De Cocina (al Por Menor)",
    "sg:phone":"+34 968 57 98 09",
    "sg:postcode":"30700",
    "sg:province":"Murcia",
    "wof:name":"Zhou  Ling Pin",
    "wof:placetype":"venue"
},
  "geometry": {"coordinates":[-0.9534909725,37.744228363],"type":"Point"}
}