{
  "type": "Feature",
  "properties": {
    "iso:country":"ES",
    "sg:address":"Avda Padre Isla, 7",
    "sg:city":"Le\u00f3n",
    "sg:orig_category":"Caf\u00c9s, Bares, Cervecer\u00cdas",
    "sg:phone":"+34 987 23 89 98",
    "sg:postcode":"24002",
    "sg:province":"Le\u00f3n",
    "wof:name":"Ouriarhni  Ghariba",
    "wof:placetype":"venue"
},
  "geometry": {"coordinates":[-5.5728750229,42.5992393494],"type":"Point"}
}