{
  "type": "Feature",
  "properties": {
    "iso:country":"ES",
    "sg:address":"Carrer de Emporda, 22",
    "sg:city":"S. Quirze Valles",
    "sg:orig_category":"Aceros Especiales",
    "sg:phone":"+34 937 21 30 15",
    "sg:postcode":"08192",
    "sg:province":"Barcelona",
    "wof:name":"Thyssen Iberica S.a.",
    "wof:placetype":"venue"
},
  "geometry": {"coordinates":[2.0790579319,41.5414237976],"type":"Point"}
}