{
  "type": "Feature",
  "properties": {
    "addr:full":"Carr Conquista, 78 Badalona Barcelona 08912",
    "addr:housenumber":"78",
    "addr:postcode":"08912",
    "addr:street":"Carr Conquista",
    "iso:country":"ES",
    "sg:address":"Carr Conquista, 78",
    "sg:city":"Badalona",
    "sg:orig_category":"Doctores En Medicina",
    "sg:phone":"+34 933 83 11 57",
    "sg:postcode":"08912",
    "sg:province":"Barcelona",
    "wof:name":"Coves Figueras Maria Jose",
    "wof:placetype":"venue"
},
  "geometry": {"coordinates":[2.2426640987,41.4463233948],"type":"Point"}
}