{
  "type": "Feature",
  "properties": {
    "addr:full":"Carr Torras I Bages, 119 Badalona Barcelona 08912",
    "addr:housenumber":"119",
    "addr:postcode":"08912",
    "addr:street":"Carr Torras I Bages",
    "iso:country":"ES",
    "sg:address":"Carr Torras I Bages, 119",
    "sg:city":"Badalona",
    "sg:orig_category":"Florister\u00cdas",
    "sg:phone":"+34 933 99 34 08",
    "sg:postcode":"08912",
    "sg:province":"Barcelona",
    "wof:name":"Mosimoll S. A.",
    "wof:placetype":"venue"
},
  "geometry": {"coordinates":[2.2396399975,41.4459114075],"type":"Point"}
}