{
  "type": "Feature",
  "properties": {
    "iso:country":"ES",
    "sg:address":"Calle de Coca, S/n",
    "sg:city":"Moron Frontera",
    "sg:orig_category":"Imprenta",
    "sg:phone":"+34 955 85 14 22",
    "sg:postcode":"41530",
    "sg:province":"Sevilla",
    "wof:name":"Carrillo Martinez Jose Maria",
    "wof:placetype":"venue"
},
  "geometry": {"coordinates":[-5.4462404251,37.1219100952],"type":"Point"}
}