{
  "type": "Feature",
  "properties": {
    "iso:country":"ES",
    "sg:address":"Calle de Juan Carlos I, 67",
    "sg:city":"Parra",
    "sg:orig_category":"Bancos",
    "sg:phone":"+34 924 68 25 56",
    "sg:postcode":"06176",
    "sg:province":"Badajoz",
    "sg:website":"www.bancapueyo.es",
    "wof:name":"Banca Pueyo S.a.",
    "wof:placetype":"venue"
},
  "geometry": {"coordinates":[-6.6228318214,38.5267791748],"type":"Point"}
}