{
  "type": "Feature",
  "properties": {
    "addr:full":"Luga Carretera De Granada, S/n Guadix Granada 18500",
    "addr:postcode":"18500",
    "addr:street":"Carretera De Granada S / N",
    "iso:country":"ES",
    "sg:address":"Luga Carretera De Granada, S/n",
    "sg:city":"Guadix",
    "sg:orig_category":"Mec\u00c1nico Del Autom\u00d3vil",
    "sg:phone":"+34 958 66 03 80",
    "sg:postcode":"18500",
    "sg:province":"Granada",
    "wof:name":"Taller De Automoviles Sierra Nevada Sdad.coop.anda.",
    "wof:placetype":"venue"
},
  "geometry": {"coordinates":[-3.1343688965,37.303894043],"type":"Point"}
}