{
  "type": "Feature",
  "properties": {
    "iso:country":"ES",
    "sg:address":"Plaz Fuerte (del), 12",
    "sg:city":"Calatayud",
    "sg:orig_category":"Ropa Para Se\u00d1oras (al Por Menor)",
    "sg:phone":"+34 976 88 15 75",
    "sg:postcode":"50300",
    "sg:province":"Zaragoza",
    "wof:name":"Lajusticia Solanas Pilar",
    "wof:placetype":"venue"
},
  "geometry": {"coordinates":[-1.6394540071,41.3522415161],"type":"Point"}
}