{
  "type": "Feature",
  "properties": {
    "addr:full":"Carr Andalucia, 36 Andratx Islas Baleares 07150",
    "addr:housenumber":"36",
    "addr:postcode":"07150",
    "addr:street":"Carr Andalucia",
    "iso:country":"ES",
    "sg:address":"Carr Andalucia, 36",
    "sg:city":"Andratx",
    "sg:orig_category":"Jardiner\u00cdas, Vegetales, Art\u00cdculos De Jardiner\u00cda (al Por Menor)",
    "sg:phone":"+34 971 13 77 27",
    "sg:postcode":"07150",
    "sg:province":"Islas Baleares",
    "wof:name":"Tirado Martin Fernando",
    "wof:placetype":"venue"
},
  "geometry": {"coordinates":[2.4228799343,39.5626411438],"type":"Point"}
}