{
  "type": "Feature",
  "properties": {
    "addr:full":"Calle de Soldado Valle Almazan, S/n Ceuta Ceuta 51002",
    "addr:housenumber":"s / n",
    "addr:postcode":"51002",
    "addr:street":"Calle De Soldado Valle Almazan",
    "iso:country":"ES",
    "sg:address":"Calle de Soldado Valle Almazan, S/n",
    "sg:city":"Ceuta",
    "sg:orig_category":"Chapister\u00cda",
    "sg:phone":"+34 956 50 31 62",
    "sg:postcode":"51002",
    "sg:province":"Ceuta",
    "wof:name":"Industrias Y Reparaciones Hermanos Mu\u00d1oz S.l.",
    "wof:placetype":"venue"
},
  "geometry": {"coordinates":[-5.3299298286,35.8878097534],"type":"Point"}
}