{
  "type": "Feature",
  "properties": {
    "addr:full":"Empalme, 48 Empalme Pontevedra 36990",
    "addr:housenumber":"48",
    "addr:postcode":"36990",
    "addr:street":"Empalme",
    "iso:country":"ES",
    "sg:address":"Empalme, 48",
    "sg:city":"Empalme",
    "sg:orig_category":"M\u00c9dicos: Estomatolog\u00cda",
    "sg:phone":"+34 986 74 34 40",
    "sg:postcode":"36990",
    "sg:province":"Pontevedra",
    "wof:name":"Garcia Gonzalez, Eugenio 000805100r S.l.n.e.",
    "wof:placetype":"venue"
},
  "geometry": {"coordinates":[-8.8619022369,42.4462432861],"type":"Point"}
}