{
  "type": "Feature",
  "properties": {
    "addr:full":"Carrer de Barcelona, 285 Sant Vicen\u00c7 Dels Horts Barcelona 08620",
    "addr:housenumber":"285",
    "addr:postcode":"08620",
    "addr:street":"Carrer De Barcelona",
    "iso:country":"ES",
    "sg:address":"Carrer de Barcelona, 285",
    "sg:city":"Sant Vicen\u00c7 Dels Horts",
    "sg:orig_category":"Agencias De Viajes",
    "sg:phone":"+34 936 56 72 02",
    "sg:postcode":"08620",
    "sg:province":"Barcelona",
    "sg:website":"www.halconviajes.es",
    "wof:name":"Viajes Halcon S.a.",
    "wof:placetype":"venue"
},
  "geometry": {"coordinates":[2.0068171024,41.399974823],"type":"Point"}
}