{
  "type": "Feature",
  "properties": {
    "addr:full":"Calle de Jacinto Benavente, 59 San Vicente Del Raspeig-sant Vicent Del Raspeig Alicante 03690",
    "addr:housenumber":"59",
    "addr:postcode":"03690",
    "addr:street":"Calle De Jacinto Benavente",
    "iso:country":"ES",
    "sg:address":"Calle de Jacinto Benavente, 59",
    "sg:city":"San Vicente Del Raspeig-sant Vicent Del Raspeig",
    "sg:orig_category":"Mec\u00c1nico Del Autom\u00d3vil",
    "sg:phone":"+34 965 66 14 20",
    "sg:postcode":"03690",
    "sg:province":"Alicante",
    "wof:name":"Torregrosa Gomis Juan Ramon",
    "wof:placetype":"venue"
},
  "geometry": {"coordinates":[-0.5319820046,38.3991508484],"type":"Point"}
}