{
  "type": "Feature",
  "properties": {
    "addr:full":"Calle de Leopoldo Pardines, 36 Petrer Alicante 03610",
    "addr:housenumber":"36",
    "addr:postcode":"03610",
    "addr:street":"Calle De Leopoldo Pardines",
    "iso:country":"ES",
    "sg:address":"Calle de Leopoldo Pardines, 36",
    "sg:city":"Petrer",
    "sg:orig_category":"Panader\u00cdas, Panader\u00cdas",
    "sg:phone":"+34 965 37 05 31",
    "sg:postcode":"03610",
    "sg:province":"Alicante",
    "wof:name":"Vidal Prats Jose Antonio",
    "wof:placetype":"venue"
},
  "geometry": {"coordinates":[-0.7717030048,38.4832496643],"type":"Point"}
}