{
  "type": "Feature",
  "properties": {
    "iso:country":"ES",
    "sg:address":"Ctra. Robledo Chavela-valdemaqueda, Km. 0002,0",
    "sg:city":"Robledo Chavela",
    "sg:orig_category":"Aguas (distribuci\u00d3n, Servicios)",
    "sg:phone":"+34 918 99 84 51",
    "sg:postcode":"28294",
    "sg:province":"Madrid",
    "wof:name":"Aqualia Gestion Integral Del Agua S.a.",
    "wof:placetype":"venue"
},
  "geometry": {"coordinates":[-4.3570981026,40.460231781],"type":"Point"}
}