{
  "type": "Feature",
  "properties": {
    "iso:country":"ES",
    "sg:address":"Carrer de Famadas, 19",
    "sg:city":"Hospitalet Llobregat",
    "sg:orig_category":"Grafistas",
    "sg:phone":"+34 902 15 33 25",
    "sg:postcode":"08907",
    "sg:province":"Barcelona",
    "sg:website":"www.gruposifu.com",
    "wof:name":"Serveis Integrals De Finques Urbanes S.l.",
    "wof:placetype":"venue"
},
  "geometry": {"coordinates":[2.102410078,41.34998703],"type":"Point"}
}