{
  "type": "Feature",
  "properties": {
    "iso:country":"ES",
    "sg:address":"Zirkuitu Ibilbidea - Camino Del Circuito, 16",
    "sg:city":"Oztaran",
    "sg:orig_category":"Artes Gr\u00c1ficas, Artes Pl\u00c1sticas (curso)",
    "sg:phone":"+34 943 37 60 77",
    "sg:postcode":"20160",
    "sg:province":"Guip\u00f9zcoa",
    "sg:website":"www.herza.net",
    "wof:name":"Herza Ivc S.l.",
    "wof:placetype":"venue"
},
  "geometry": {"coordinates":[-2.020414114,43.2698173523],"type":"Point"}
}