{
  "type": "Feature",
  "properties": {
    "iso:country":"ES",
    "sg:address":"Avda Ramon Y Cajal, 21",
    "sg:city":"Marbella",
    "sg:orig_category":"Cl\u00cdnicas Dentales",
    "sg:phone":"+34 952 82 53 18",
    "sg:postcode":"29600",
    "sg:province":"M\u00e1laga",
    "wof:name":"Alberola Morejon Elena",
    "wof:placetype":"venue"
},
  "geometry": {"coordinates":[-4.8839221001,36.5083198547],"type":"Point"}
}