{
  "type": "Feature",
  "properties": {
    "addr:full":"Praz Fonte Dos Ranchos, 19 Lugo Lugo 27004",
    "addr:housenumber":"19",
    "addr:postcode":"27004",
    "addr:street":"Praz Fonte Dos Ranchos",
    "iso:country":"ES",
    "sg:address":"Praz Fonte Dos Ranchos, 19",
    "sg:city":"Lugo",
    "sg:orig_category":"Psicoterapeutas",
    "sg:phone":"+34 982 21 72 58",
    "sg:postcode":"27004",
    "sg:province":"Lugo",
    "wof:name":"Castro Liz Ana",
    "wof:placetype":"venue"
},
  "geometry": {"coordinates":[-7.569381237,43.0095176697],"type":"Point"}
}