{
  "type": "Feature",
  "properties": {
    "iso:country":"ES",
    "sg:address":"Calle de Doctor Fleming, 11",
    "sg:city":"Ejea De Los Caballeros",
    "sg:orig_category":"Reposter\u00cdas",
    "sg:phone":"+34 976 66 13 57",
    "sg:postcode":"50600",
    "sg:province":"Zaragoza",
    "wof:name":"Panaderia Laita S. C.",
    "wof:placetype":"venue"
},
  "geometry": {"coordinates":[-1.1368591785,42.1264724731],"type":"Point"}
}