{
  "type": "Feature",
  "properties": {
    "iso:country":"ES",
    "sg:address":"Calle de Ulises, S/n",
    "sg:city":"Pilar Horadada",
    "sg:orig_category":"Control T\u00c9cnico De Veh\u00cdculos",
    "sg:phone":"+34 965 97 60 68",
    "sg:postcode":"03190",
    "sg:province":"Alicante",
    "wof:name":"Pistas Iteuve S. A.",
    "wof:placetype":"venue"
},
  "geometry": {"coordinates":[-0.4810059965,38.3452033997],"type":"Point"}
}