{
  "type": "Feature",
  "properties": {
    "iso:country":"ES",
    "sg:address":"Calle de Juan Ramon Jimenez, 9",
    "sg:city":"Gallardos",
    "sg:orig_category":"Servicios De Telecomunicaciones",
    "sg:phone":"+34 950 39 88 19",
    "sg:postcode":"04280",
    "sg:province":"Almer\u00eda",
    "wof:name":"Garcia Hernandez Jose Francisco",
    "wof:placetype":"venue"
},
  "geometry": {"coordinates":[-1.9397890568,37.1677284241],"type":"Point"}
}