{
  "type": "Feature",
  "properties": {
    "addr:full":"Ptge Maneu, 3 Palma Islas Baleares 07002",
    "addr:housenumber":"3",
    "addr:postcode":"07002",
    "addr:street":"Ptge Maneu",
    "iso:country":"ES",
    "sg:address":"Ptge Maneu, 3",
    "sg:city":"Palma",
    "sg:orig_category":"Tapicer\u00cdas",
    "sg:phone":"+34 971 71 97 07",
    "sg:postcode":"07002",
    "sg:province":"Islas Baleares",
    "wof:name":"Rodriguez Gomez Manuel",
    "wof:placetype":"venue"
},
  "geometry": {"coordinates":[2.6561861038,39.5720672607],"type":"Point"}
}