{
  "type": "Feature",
  "properties": {
    "addr:full":"Mayor-nagusia Kalea, 5 Iru\u00f1a Navarra 31001",
    "addr:housenumber":"5",
    "addr:postcode":"31001",
    "addr:street":"Mayor-Nagusia Kalea",
    "iso:country":"ES",
    "sg:address":"Mayor-nagusia Kalea, 5",
    "sg:city":"Iru\u00f1a",
    "sg:orig_category":"Ropa Para Caballeros (al Por Menor)",
    "sg:phone":"+34 948 22 28 45",
    "sg:postcode":"31001",
    "sg:province":"Navarra",
    "wof:name":"Artazcoz Loperena Pedro",
    "wof:placetype":"venue"
},
  "geometry": {"coordinates":[-1.7042343616,42.8231315613],"type":"Point"}
}