{
  "type": "Feature",
  "properties": {
    "addr:full":"Calle de Oro, 24 Valladolid Valladolid 47012",
    "addr:housenumber":"24",
    "addr:postcode":"47012",
    "addr:street":"Calle De Oro",
    "iso:country":"ES",
    "sg:address":"Calle de Oro, 24",
    "sg:city":"Valladolid",
    "sg:orig_category":"Contables",
    "sg:phone":"+34 983 30 48 95",
    "sg:postcode":"47012",
    "sg:province":"Valladolid",
    "wof:name":"Mateos Casado Lidia",
    "wof:placetype":"venue"
},
  "geometry": {"coordinates":[-4.7004418373,41.618598938],"type":"Point"}
}