{
  "type": "Feature",
  "properties": {
    "iso:country":"ES",
    "sg:address":"Barrena Kalea, 8",
    "sg:city":"Eibar",
    "sg:orig_category":"Electricidad Veh\u00cdculo",
    "sg:phone":"+34 943 12 06 01",
    "sg:postcode":"20600",
    "sg:province":"Guip\u00f9zcoa",
    "wof:name":"Romero Horrillo Aquilino",
    "wof:placetype":"venue"
},
  "geometry": {"coordinates":[-2.4580490589,43.1895103455],"type":"Point"}
}