{
  "type": "Feature",
  "properties": {
    "iso:country":"ES",
    "sg:address":"Carrer de Modolell, 6",
    "sg:city":"Barcelona",
    "sg:orig_category":"Asesores De Gesti\u00d3n Del Patrimonio",
    "sg:phone":"+34 932 01 89 75",
    "sg:postcode":"08021",
    "sg:province":"Barcelona",
    "wof:name":"Padrol Munte S.l.",
    "wof:placetype":"venue"
},
  "geometry": {"coordinates":[2.1375648975,41.3956604004],"type":"Point"}
}