{
  "type": "Feature",
  "properties": {
    "iso:country":"ES",
    "sg:address":"Guadalmina Baja, 1",
    "sg:city":"San Pedro Alcantara",
    "sg:orig_category":"Aguas (distribuci\u00d3n, Servicios)",
    "sg:phone":"+34 952 88 59 00",
    "sg:postcode":"29670",
    "sg:province":"M\u00e1laga",
    "wof:name":"Marina Enterprises S.a.",
    "wof:placetype":"venue"
},
  "geometry": {"coordinates":[-4.9902391434,36.4866333008],"type":"Point"}
}