{
  "type": "Feature",
  "properties": {
    "addr:full":"Pla\u00c7 Catalunya, 3 Salt Girona 17190",
    "addr:housenumber":"3",
    "addr:postcode":"17190",
    "iso:country":"ES",
    "sg:address":"Pla\u00c7 Catalunya, 3",
    "sg:city":"Salt",
    "sg:orig_category":"Sociedades, Compa\u00d1\u00cdas Aseguradoras",
    "sg:phone":"+34 972 24 41 51",
    "sg:postcode":"17190",
    "sg:province":"Girona",
    "wof:name":"Roman Santiago Santiago",
    "wof:placetype":"venue"
},
  "geometry": {"coordinates":[2.7985711098,41.9750785828],"type":"Point"}
}