{
  "type": "Feature",
  "properties": {
    "iso:country":"ES",
    "sg:address":"Avda Region Murciana, S/n",
    "sg:city":"Carril De La Enera",
    "sg:orig_category":"Agencias De Viajes",
    "sg:phone":"+34 968 34 04 48",
    "sg:postcode":"30011",
    "sg:province":"Murcia",
    "sg:website":"www.viajeseroski.es",
    "wof:name":"Viajes Eroski S.a.",
    "wof:placetype":"venue"
},
  "geometry": {"coordinates":[-1.1121939421,37.9820289612],"type":"Point"}
}