{
  "type": "Feature",
  "properties": {
    "addr:full":"Carr Almogavers, S/n Sant Joan De Palamos Girona 17230",
    "addr:housenumber":"s",
    "addr:postcode":"17230",
    "addr:street":"Carr Almogavers;/ N",
    "iso:country":"ES",
    "sg:address":"Carr Almogavers, S/n",
    "sg:city":"Sant Joan De Palamos",
    "sg:orig_category":"Centros De Educaci\u00d3n Especial",
    "sg:phone":"+34 972 31 57 69",
    "sg:postcode":"17230",
    "sg:province":"Girona",
    "wof:name":"Col.legi Public D'educacio Especial Els Angels",
    "wof:placetype":"venue"
},
  "geometry": {"coordinates":[3.1232550144,41.8651199341],"type":"Point"}
}