{
  "type": "Feature",
  "properties": {
    "iso:country":"ES",
    "sg:address":"Calle de Miguel Gallo, 13",
    "sg:city":"Carde\u00f1a",
    "sg:orig_category":"Alimentaci\u00d3n Animal (fabricaci\u00d3n, Al Por Mayor)",
    "sg:phone":"+34 957 17 44 45",
    "sg:postcode":"14445",
    "sg:province":"C\u00f3rdoba",
    "wof:name":"Pascual Aranda S.a.",
    "wof:placetype":"venue"
},
  "geometry": {"coordinates":[-4.3242049217,38.271270752],"type":"Point"}
}