{
  "type": "Feature",
  "properties": {
    "iso:country":"ES",
    "sg:address":"Carrer de Paris, 58",
    "sg:city":"Barcelona",
    "sg:orig_category":"Asesor\u00cda Fiscal Y Jur\u00cddica",
    "sg:phone":"+34 934 19 08 15",
    "sg:postcode":"08029",
    "sg:province":"Barcelona",
    "wof:name":"Elite Gestion Empresarial S.l.",
    "wof:placetype":"venue"
},
  "geometry": {"coordinates":[2.1443591118,41.3867607117],"type":"Point"}
}