{
  "type": "Feature",
  "properties": {
    "addr:full":"Rua Soutomaior, 4 Vigo Pontevedra 36209",
    "addr:housenumber":"4",
    "addr:postcode":"36209",
    "addr:street":"Rua Soutomaior",
    "iso:country":"ES",
    "sg:address":"Rua Soutomaior, 4",
    "sg:city":"Vigo",
    "sg:orig_category":"Loter\u00cda Y T\u00d3mbola",
    "sg:phone":"+34 986 20 18 46",
    "sg:postcode":"36209",
    "sg:province":"Pontevedra",
    "wof:name":"Rodriguez Merino Victoria",
    "wof:placetype":"venue"
},
  "geometry": {"coordinates":[-8.7484321594,42.2168922424],"type":"Point"}
}