{
  "type": "Feature",
  "properties": {
    "iso:country":"ES",
    "sg:address":"Bda. Juan Xxiii, S/n",
    "sg:city":"Medina-sidonia",
    "sg:orig_category":"Confiter\u00cdas, Chocolater\u00cdas (al Por Menor)",
    "sg:phone":"+34 956 41 13 42",
    "sg:postcode":"11170",
    "sg:province":"C\u00e1diz",
    "wof:name":"Rodriguez Bola\u00f1os Rafael",
    "wof:placetype":"venue"
},
  "geometry": {"coordinates":[-5.9282741547,36.463180542],"type":"Point"}
}