{
  "type": "Feature",
  "properties": {
    "addr:full":"Veigamui\u00f1os, 96 Proba Ourense 32317",
    "addr:housenumber":"96",
    "addr:postcode":"32317",
    "addr:street":"Veigamuin\u0303Os",
    "iso:country":"ES",
    "sg:address":"Veigamui\u00f1os, 96",
    "sg:city":"Proba",
    "sg:orig_category":"Transportes Por Carretera: Lotes Completos, Mercanc\u00cdas Diversas",
    "sg:phone":"+34 988 32 08 04",
    "sg:postcode":"32317",
    "sg:province":"Ourense",
    "wof:name":"Dominguez Gonzalez Jose Manuel",
    "wof:placetype":"venue"
},
  "geometry": {"coordinates":[-7.0044908524,42.4339256287],"type":"Point"}
}