{
  "type": "Feature",
  "properties": {
    "addr:full":"Avda Marques De La Vega De Armijo, 13 Montilla C\u00f3rdoba 14550",
    "addr:housenumber":"13",
    "addr:postcode":"14550",
    "addr:street":"Avda Marques De La Vega De Armijo;Co\u0301Rdoba",
    "iso:country":"ES",
    "sg:address":"Avda Marques De La Vega De Armijo, 13",
    "sg:city":"Montilla",
    "sg:orig_category":"Contenedores (mercanc\u00cdas)",
    "sg:phone":"+34 957 66 44 18",
    "sg:postcode":"14550",
    "sg:province":"C\u00f3rdoba",
    "wof:name":"Transportes Castro Perez S.l.",
    "wof:placetype":"venue"
},
  "geometry": {"coordinates":[-4.6341109276,37.5922393799],"type":"Point"}
}