{
  "type": "Feature",
  "properties": {
    "addr:full":"Calle de Parroco Antonio Gomez Villalobos, 133 Sevilla Sevilla 41006",
    "addr:housenumber":"133",
    "addr:postcode":"41006",
    "addr:street":"Calle De Parroco Antonio Gomez Villalobos",
    "iso:country":"ES",
    "sg:address":"Calle de Parroco Antonio Gomez Villalobos, 133",
    "sg:city":"Sevilla",
    "sg:orig_category":"Molduras, Junquillos, Listones Y Molduras Perforadas",
    "sg:phone":"+34 954 92 30 26",
    "sg:postcode":"41006",
    "sg:province":"Sevilla",
    "wof:name":"Sistelcom-telemensaje S.a.",
    "wof:placetype":"venue"
},
  "geometry": {"coordinates":[-5.9519062042,37.3706550598],"type":"Point"}
}