{
  "type": "Feature",
  "properties": {
    "addr:full":"Avda Blas Infante (de), 29 Almeria Almer\u00eda 04006",
    "addr:housenumber":"29",
    "addr:postcode":"04006",
    "addr:street":"Avda Blas Infante De",
    "iso:country":"ES",
    "sg:address":"Avda Blas Infante (de), 29",
    "sg:city":"Almeria",
    "sg:orig_category":"Cl\u00cdnicas M\u00c9dicas",
    "sg:phone":"+34 950 22 90 31",
    "sg:postcode":"04006",
    "sg:province":"Almer\u00eda",
    "wof:name":"Domme  Olivier",
    "wof:placetype":"venue"
},
  "geometry": {"coordinates":[-2.4522690773,36.8412094116],"type":"Point"}
}