{
  "type": "Feature",
  "properties": {
    "iso:country":"ES",
    "sg:address":"Avda Doctor Gomez Ferrer, 51",
    "sg:city":"Alfafar",
    "sg:orig_category":"Molduras, Junquillos, Listones Y Molduras Perforadas",
    "sg:phone":"+34 963 75 60 52",
    "sg:postcode":"46910",
    "sg:province":"Valencia",
    "wof:name":"Alonso Chinesta Vicente Ignacio",
    "wof:placetype":"venue"
},
  "geometry": {"coordinates":[-0.3926376998,39.4262580872],"type":"Point"}
}