{
  "type": "Feature",
  "properties": {
    "addr:full":"Carrer de Zurbano, 9 Sabadell Barcelona 08201",
    "addr:housenumber":"9",
    "addr:postcode":"08201",
    "addr:street":"Carrer De Zurbano",
    "iso:country":"ES",
    "sg:address":"Carrer de Zurbano, 9",
    "sg:city":"Sabadell",
    "sg:orig_category":"Empresas De Carpinter\u00cda",
    "sg:phone":"+34 937 25 01 90",
    "sg:postcode":"08201",
    "sg:province":"Barcelona",
    "wof:name":"Meta%isteria Clasic S. Cv.",
    "wof:placetype":"venue"
},
  "geometry": {"coordinates":[2.1103520393,41.5406341553],"type":"Point"}
}