{
  "type": "Feature",
  "properties": {
    "addr:full":"Carrer de Arizala, 71 Barcelona Barcelona 08028",
    "addr:housenumber":"71",
    "addr:postcode":"08028",
    "addr:street":"Carrer De Arizala",
    "iso:country":"ES",
    "sg:address":"Carrer de Arizala, 71",
    "sg:city":"Barcelona",
    "sg:orig_category":"Farmacias",
    "sg:phone":"+34 934 40 45 22",
    "sg:postcode":"08028",
    "sg:province":"Barcelona",
    "wof:name":"Pamias Mu\u00f1oz Francisco",
    "wof:placetype":"venue"
},
  "geometry": {"coordinates":[2.1233620644,41.3786697388],"type":"Point"}
}