{
  "type": "Feature",
  "properties": {
    "iso:country":"ES",
    "sg:address":"Pase Julia (la), 29",
    "sg:city":"Palencia",
    "sg:orig_category":"Sociedades, Compa\u00d1\u00cdas Aseguradoras",
    "sg:phone":"+34 979 72 69 37",
    "sg:postcode":"34004",
    "sg:province":"Palencia",
    "wof:name":"Herrezuelo Pedrosa Juan Carlos",
    "wof:placetype":"venue"
},
  "geometry": {"coordinates":[-4.5305519104,42.0005836487],"type":"Point"}
}