{
  "type": "Feature",
  "properties": {
    "iso:country":"ES",
    "sg:address":"Avda Manzanares, 86",
    "sg:city":"Madrid",
    "sg:orig_category":"Agencias Y Agentes Comerciales, Representantes",
    "sg:phone":"+34 914 60 42 46",
    "sg:postcode":"28019",
    "sg:province":"Madrid",
    "wof:name":"Hernandez Rivera Carmen",
    "wof:placetype":"venue"
},
  "geometry": {"coordinates":[-3.7213430405,40.3998680115],"type":"Point"}
}