{
  "type": "Feature",
  "properties": {
    "addr:full":"Calle de Gustavo Adolfo Becquer, 9 Arme\u00d1ime Santa Cruz De Tenerife 38678",
    "addr:housenumber":"9",
    "addr:postcode":"38678",
    "addr:street":"Calle De Gustavo Adolfo Becquer",
    "iso:country":"ES",
    "sg:address":"Calle de Gustavo Adolfo Becquer, 9",
    "sg:city":"Arme\u00d1ime",
    "sg:orig_category":"Tapiceros Y Tapiceros",
    "sg:phone":"+34 922 74 09 00",
    "sg:postcode":"38678",
    "sg:province":"Santa Cruz De Tenerife",
    "wof:name":"Canarias Decohotel S.l.",
    "wof:placetype":"venue"
},
  "geometry": {"coordinates":[-16.7560024261,28.1283512115],"type":"Point"}
}