{
  "type": "Feature",
  "properties": {
    "iso:country":"ES",
    "sg:address":"Rio Ardachon, S/n",
    "sg:city":"Fuengirola",
    "sg:orig_category":"Automatizaci\u00d3n De Procesos Industriales Y De Edificaci\u00d3n (estudios, Instalaci\u00d3n)",
    "sg:phone":"+34 952 47 22 49",
    "sg:postcode":"29640",
    "sg:province":"M\u00e1laga",
    "wof:name":"Garcia Ruiz Andres",
    "wof:placetype":"venue"
},
  "geometry": {"coordinates":[-4.6393914223,36.5419158936],"type":"Point"}
}