{
  "type": "Feature",
  "properties": {
    "iso:country":"ES",
    "sg:address":"Avda Paris, S/n",
    "sg:city":"Mojacar",
    "sg:orig_category":"Sanatorios M\u00c9dico",
    "sg:phone":"+34 950 47 89 88",
    "sg:postcode":"04638",
    "sg:province":"Almer\u00eda",
    "wof:name":"Servicio Andaluz De Salud",
    "wof:placetype":"venue"
},
  "geometry": {"coordinates":[-1.8527799845,37.1398086548],"type":"Point"}
}