{
  "type": "Feature",
  "properties": {
    "addr:full":"Ctra. Ugijar, S/n Cadiar Granada 18440",
    "addr:housenumber":"s",
    "addr:postcode":"18440",
    "addr:street":"Ctra. Ugijar;/ N Cadiar",
    "iso:country":"ES",
    "sg:address":"Ctra. Ugijar, S/n",
    "sg:city":"Cadiar",
    "sg:orig_category":"Residencias De Turismo, Residencias Hoteleras",
    "sg:phone":"+34 958 76 89 00",
    "sg:postcode":"18440",
    "sg:province":"Granada",
    "wof:name":"Montoro Moron Antonio",
    "wof:placetype":"venue"
},
  "geometry": {"coordinates":[-3.1770789623,36.9463195801],"type":"Point"}
}