{
  "type": "Feature",
  "properties": {
    "addr:full":"Calle de Lopez De Hoyos, 83 Madrid Madrid 28002",
    "addr:housenumber":"83",
    "addr:postcode":"madrid;28002",
    "addr:street":"Calle De Lopez De Hoyos",
    "iso:country":"ES",
    "sg:address":"Calle de Lopez De Hoyos, 83",
    "sg:city":"Madrid",
    "sg:orig_category":"Parafarmacias",
    "sg:phone":"+34 914 15 06 43",
    "sg:postcode":"28002",
    "sg:province":"Madrid",
    "wof:name":"Canton Garcia-vidal Rafael",
    "wof:placetype":"venue"
},
  "geometry": {"coordinates":[-3.6738100052,40.4445304871],"type":"Point"}
}