{
  "type": "Feature",
  "properties": {
    "iso:country":"ES",
    "sg:address":"Calle de Gil Gonzalez Davila, S/n",
    "sg:city":"Salamanca",
    "sg:orig_category":"Supermercados Y Hipermercados",
    "sg:phone":"+34 923 19 16 01",
    "sg:postcode":"37008",
    "sg:province":"Salamanca",
    "wof:name":"Nieto Hernandez Elias",
    "wof:placetype":"venue"
},
  "geometry": {"coordinates":[-5.6887450218,40.956237793],"type":"Point"}
}