{
  "type": "Feature",
  "properties": {
    "iso:country":"ES",
    "sg:address":"Pase San Gregorio, 71",
    "sg:city":"Puertollano",
    "sg:orig_category":"Supermercados Y Hipermercados",
    "sg:phone":"+34 926 43 01 79",
    "sg:postcode":"13500",
    "sg:province":"Ciudad Real",
    "wof:name":"Qualia Lacteos S.l.u.",
    "wof:placetype":"venue"
},
  "geometry": {"coordinates":[-4.1026639938,38.6896324158],"type":"Point"}
}