{
  "type": "Feature",
  "properties": {
    "addr:full":"Carrer de Reding (de), 44 Tarragona Tarragona 43001",
    "addr:housenumber":"44",
    "addr:postcode":"43001",
    "addr:street":"Carrer De Reding De",
    "iso:country":"ES",
    "sg:address":"Carrer de Reding (de), 44",
    "sg:city":"Tarragona",
    "sg:orig_category":"Producci\u00d3n, Distribuci\u00d3n De Electricidad",
    "sg:phone":"+34 977 22 43 52",
    "sg:postcode":"43001",
    "sg:province":"Tarragona",
    "wof:name":"Mestre Ferre Josefa",
    "wof:placetype":"venue"
},
  "geometry": {"coordinates":[1.247871995,41.1162910461],"type":"Point"}
}