{
  "type": "Feature",
  "properties": {
    "addr:full":"Calle de Rector Marin Ocete, 6 Granada Granada 18014",
    "addr:housenumber":"6",
    "addr:postcode":"18014",
    "addr:street":"Calle De Rector Marin Ocete",
    "iso:country":"ES",
    "sg:address":"Calle de Rector Marin Ocete, 6",
    "sg:city":"Granada",
    "sg:orig_category":"Inmobiliaria (agencias)",
    "sg:phone":"+34 958 27 59 51",
    "sg:postcode":"18014",
    "sg:province":"Granada",
    "wof:name":"Grupo Empresarial M B S.l.",
    "wof:placetype":"venue"
},
  "geometry": {"coordinates":[-3.6065700054,37.1842765808],"type":"Point"}
}