{
  "type": "Feature",
  "properties": {
    "iso:country":"ES",
    "sg:address":"Calle de Concordia, 51",
    "sg:city":"Vall D'uixo",
    "sg:orig_category":"Peluquer\u00cdas, Peluquer\u00cda Mixta",
    "sg:phone":"+34 964 69 15 74",
    "sg:postcode":"12600",
    "sg:province":"Castell\u00f3n",
    "wof:name":"Garcia Pedro Dolores",
    "wof:placetype":"venue"
},
  "geometry": {"coordinates":[-0.2350405008,39.8264961243],"type":"Point"}
}