{
  "type": "Feature",
  "properties": {
    "iso:country":"ES",
    "sg:address":"Calle de Santa Engracia, 147",
    "sg:city":"Madrid",
    "sg:orig_category":"Abogados",
    "sg:phone":"+34 915 53 76 71",
    "sg:postcode":"28003",
    "sg:province":"Madrid",
    "wof:name":"Campos Carvajal Jose Javier",
    "wof:placetype":"venue"
},
  "geometry": {"coordinates":[-3.7027170658,40.4437065125],"type":"Point"}
}