{
  "type": "Feature",
  "properties": {
    "addr:full":"Calle de Domingo Hergueta, 7 Haro La Rioja 26200",
    "addr:housenumber":"7",
    "addr:postcode":"26200",
    "addr:street":"Calle De Domingo Hergueta",
    "iso:country":"ES",
    "sg:address":"Calle de Domingo Hergueta, 7",
    "sg:city":"Haro",
    "sg:classifiers":[
        {
            "category":"Personal",
            "subcategory":"Barber",
            "type":"Services"
        }
    ],
    "sg:phone":"+34 941 31 00 12",
    "sg:postcode":"26200",
    "sg:province":"La Rioja",
    "sg:tags":[
        "caballeros",
        "de",
        "peluqueros"
    ],
    "wof:name":"Rios Villanueva Mari Vega",
    "wof:placetype":"venue"
},
  "geometry": {"coordinates":[-2.8482987881,42.5725708008],"type":"Point"}
}