{
  "type": "Feature",
  "properties": {
    "iso:country":"ES",
    "sg:address":"Calle de Montera, 4",
    "sg:city":"Mazarron",
    "sg:orig_category":"Peluquer\u00cdas, Peluquer\u00cda Mixta",
    "sg:phone":"+34 968 59 22 89",
    "sg:postcode":"30870",
    "sg:province":"Murcia",
    "wof:name":"Ruiz Romero Maria",
    "wof:placetype":"venue"
},
  "geometry": {"coordinates":[-1.3114540577,37.599521637],"type":"Point"}
}