{
  "type": "Feature",
  "properties": {
    "addr:full":"Jose Artetxe Kalea, 13 Azpeitia Guip\u00f9zcoa 20730",
    "addr:housenumber":"13",
    "addr:postcode":"20730",
    "addr:street":"Jose Artetxe Kalea;Guipu\u0300Zcoa",
    "iso:country":"ES",
    "sg:address":"Jose Artetxe Kalea, 13",
    "sg:city":"Azpeitia",
    "sg:orig_category":"Bisuter\u00cda, Joyer\u00cda, Relojer\u00cda (al Por Menor)",
    "sg:phone":"+34 943 15 76 13",
    "sg:postcode":"20730",
    "sg:province":"Guip\u00f9zcoa",
    "wof:name":"Lucke  Amy",
    "wof:placetype":"venue"
},
  "geometry": {"coordinates":[-2.2674939632,43.1818656921],"type":"Point"}
}