{
  "type": "Feature",
  "properties": {
    "iso:country":"ES",
    "sg:address":"Av Juli Garreta, 26",
    "sg:city":"S. Feliu Guixols",
    "sg:orig_category":"Arquitectos",
    "sg:phone":"+34 972 32 24 61",
    "sg:postcode":"17220",
    "sg:province":"Girona",
    "wof:name":"Lobo Serra Mario",
    "wof:placetype":"venue"
},
  "geometry": {"coordinates":[3.0277280807,41.7803649902],"type":"Point"}
}