{
  "type": "Feature",
  "properties": {
    "addr:full":"Calle de Bailen, 32 Malaga M\u00e1laga 29009",
    "addr:housenumber":"32",
    "addr:postcode":"29009",
    "addr:street":"Calle De Bailen;Ma\u0301Laga",
    "iso:country":"ES",
    "sg:address":"Calle de Bailen, 32",
    "sg:city":"Malaga",
    "sg:orig_category":"Telefon\u00cda: Instaladores Varios",
    "sg:phone":"+34 952 07 08 64",
    "sg:postcode":"29009",
    "sg:province":"M\u00e1laga",
    "wof:name":"Eze  Maxwell",
    "wof:placetype":"venue"
},
  "geometry": {"coordinates":[-4.4337849617,36.7246284485],"type":"Point"}
}