{
  "type": "Feature",
  "properties": {
    "addr:full":"Plaz Julio Lazurtegui, 8 Ponferrada Le\u00f3n 24400",
    "addr:housenumber":"8",
    "addr:postcode":"24400",
    "addr:street":"Lazurtegui",
    "iso:country":"ES",
    "sg:address":"Plaz Julio Lazurtegui, 8",
    "sg:city":"Ponferrada",
    "sg:orig_category":"Abogados",
    "sg:phone":"+34 987 42 53 86",
    "sg:postcode":"24400",
    "sg:province":"Le\u00f3n",
    "wof:name":"Sanchez Gonzalez Juan Manuel",
    "wof:placetype":"venue"
},
  "geometry": {"coordinates":[-6.5982608795,42.5478591919],"type":"Point"}
}