{
  "type": "Feature",
  "properties": {
    "addr:full":"Molina (urb. Can Miret), 5 Pungoles Barcelona 08459",
    "addr:housenumber":"5",
    "addr:postcode":"08459",
    "addr:street":"Pungoles Barcelona",
    "iso:country":"ES",
    "sg:address":"Molina (urb. Can Miret), 5",
    "sg:city":"Pungoles",
    "sg:orig_category":"Jardiner\u00cdas, Vegetales, Art\u00cdculos De Jardiner\u00cda (al Por Menor)",
    "sg:phone":"+34 938 45 27 01",
    "sg:postcode":"08459",
    "sg:province":"Barcelona",
    "sg:website":"www.peatmoss.es",
    "wof:name":"Peat Mos S.l.",
    "wof:placetype":"venue"
},
  "geometry": {"coordinates":[2.400949955,41.6733512878],"type":"Point"}
}