{
  "type": "Feature",
  "properties": {
    "iso:country":"ES",
    "sg:address":"Ctra Malaga (de), 47",
    "sg:city":"Granada",
    "sg:orig_category":"Supermercados Y Hipermercados",
    "sg:phone":"+34 958 28 50 36",
    "sg:postcode":"18015",
    "sg:province":"Granada",
    "wof:name":"Supergran S. A.",
    "wof:placetype":"venue"
},
  "geometry": {"coordinates":[-3.6271591187,37.1893730164],"type":"Point"}
}