{
  "type": "Feature",
  "properties": {
    "addr:full":"Ctra Alicante, Km. 0238,0 Tavernes Valldigna Valencia 46760",
    "addr:postcode":"46760",
    "addr:street":"Ctra Alicante Km. 0238,0",
    "iso:country":"ES",
    "sg:address":"Ctra Alicante, Km. 0238,0",
    "sg:city":"Tavernes Valldigna",
    "sg:orig_category":"Distribuci\u00d3n De Petr\u00d3leo Y Derivados",
    "sg:phone":"+34 962 83 75 82",
    "sg:postcode":"46760",
    "sg:province":"Valencia",
    "wof:name":"Desmond White S.l.",
    "wof:placetype":"venue"
},
  "geometry": {"coordinates":[-0.2594090104,39.0749702454],"type":"Point"}
}