{
  "type": "Feature",
  "properties": {
    "addr:full":"Calle de Italia, 14 Pinto Madrid 28320",
    "addr:housenumber":"14",
    "addr:postcode":"28320",
    "addr:street":"Calle De Italia",
    "iso:country":"ES",
    "sg:address":"Calle de Italia, 14",
    "sg:city":"Pinto",
    "sg:orig_category":"Centros Empresariales",
    "sg:phone":"+34 916 91 16 00",
    "sg:postcode":"28320",
    "sg:province":"Madrid",
    "wof:name":"Aserpinto S.a.",
    "wof:placetype":"venue"
},
  "geometry": {"coordinates":[-3.6958184242,40.2513427734],"type":"Point"}
}