{
  "type": "Feature",
  "properties": {
    "addr:full":"Calle de Montera, 9 Madrid Madrid 28013",
    "addr:housenumber":"9",
    "addr:postcode":"madrid;28013",
    "addr:street":"Calle De Montera",
    "iso:country":"ES",
    "sg:address":"Calle de Montera, 9",
    "sg:city":"Madrid",
    "sg:orig_category":"Administradores De Bienes Y Delegados De Comunidades De Propietarios",
    "sg:phone":"+34 915 32 62 16",
    "sg:postcode":"28013",
    "sg:province":"Madrid",
    "wof:name":"Mangas Gutierrez Roberto",
    "wof:placetype":"venue"
},
  "geometry": {"coordinates":[-3.7030589581,40.4175491333],"type":"Point"}
}