{
  "type": "Feature",
  "properties": {
    "iso:country":"ES",
    "sg:address":"Calle de Gernikako Arbola, 11",
    "sg:city":"Vitoria-gasteiz",
    "sg:orig_category":"Asociaciones, Organismos Culturales Y Socioeducativos",
    "sg:phone":"+34 945 27 29 34",
    "sg:postcode":"01010",
    "sg:province":"\u00c1lava",
    "wof:name":"Centro Gallego De Vitoria",
    "wof:placetype":"venue"
},
  "geometry": {"coordinates":[-2.6998240948,42.8534507751],"type":"Point"}
}