{
  "type": "Feature",
  "properties": {
    "iso:country":"ES",
    "sg:address":"Calle de Poeta Llorente, 156",
    "sg:city":"Pobla Vallbona",
    "sg:orig_category":"Electricidad Veh\u00cdculo",
    "sg:phone":"+34 962 76 08 06",
    "sg:postcode":"46185",
    "sg:province":"Valencia",
    "wof:name":"Talleres Temp S.l.",
    "wof:placetype":"venue"
},
  "geometry": {"coordinates":[-0.5534440279,39.5925750732],"type":"Point"}
}