{
  "type": "Feature",
  "properties": {
    "iso:country":"ES",
    "sg:address":"Calle de Arquimedes, 47",
    "sg:city":"Fuenlabrada",
    "sg:orig_category":"Madera Para Construcci\u00d3n E Industria",
    "sg:phone":"+34 916 06 87 07",
    "sg:postcode":"28946",
    "sg:province":"Madrid",
    "wof:name":"Calero Parquet S.l.",
    "wof:placetype":"venue"
},
  "geometry": {"coordinates":[-3.7780032158,40.2832107544],"type":"Point"}
}