{
  "type": "Feature",
  "properties": {
    "iso:country":"ES",
    "sg:address":"Calle de Guaxara, 16",
    "sg:city":"Secadero",
    "sg:orig_category":"Venta, Instalaci\u00d3n, Reparaci\u00d3n De Antenas Para Televisi\u00d3n",
    "sg:phone":"+34 928 33 02 01",
    "sg:postcode":"35015",
    "sg:province":"Las Palmas",
    "wof:name":"Barreto Ortiz Pablo Jose",
    "wof:placetype":"venue"
},
  "geometry": {"coordinates":[-15.4232616425,28.095746994],"type":"Point"}
}