{
  "type": "Feature",
  "properties": {
    "addr:full":"Calle de Cristo De La Sed, 25 Sevilla Sevilla 41005",
    "addr:housenumber":"25",
    "addr:postcode":"41005",
    "addr:street":"Calle De Cristo De La Sed",
    "iso:country":"ES",
    "sg:address":"Calle de Cristo De La Sed, 25",
    "sg:city":"Sevilla",
    "sg:orig_category":"Cer\u00c1mica Art\u00cdstica Y Decorativa",
    "sg:phone":"+34 954 57 08 20",
    "sg:postcode":"41005",
    "sg:province":"Sevilla",
    "wof:name":"Ruiz Gil S.l.",
    "wof:placetype":"venue"
},
  "geometry": {"coordinates":[-5.9673194885,37.3831253052],"type":"Point"}
}