{
  "type": "Feature",
  "properties": {
    "iso:country":"ES",
    "sg:address":"Carrer de Castellvi, 4",
    "sg:city":"Cal Rubio",
    "sg:orig_category":"Aguas (distribuci\u00d3n, Servicios)",
    "sg:phone":"+34 938 98 00 93",
    "sg:postcode":"08730",
    "sg:province":"Barcelona",
    "wof:name":"Font Aiguaviva S.c.p.",
    "wof:placetype":"venue"
},
  "geometry": {"coordinates":[1.6629099846,41.3209686279],"type":"Point"}
}