{
  "type": "Feature",
  "properties": {
    "addr:full":"C/ Padro, 143 Ripollet Barcelona 08291",
    "addr:housenumber":"143",
    "addr:postcode":"08291",
    "addr:street":"C / Padro",
    "iso:country":"ES",
    "sg:address":"C/ Padro, 143",
    "sg:city":"Ripollet",
    "sg:orig_category":"M\u00c9dicos: Pediatr\u00cda. Enfermedades De Los Ni\u00d1os",
    "sg:phone":"+34 935 80 54 56",
    "sg:postcode":"08291",
    "sg:province":"Barcelona",
    "wof:name":"Turmo Marti Julio",
    "wof:placetype":"venue"
},
  "geometry": {"coordinates":[2.1621088982,41.5016593933],"type":"Point"}
}