{
  "type": "Feature",
  "properties": {
    "iso:country":"ES",
    "sg:address":"Plaz Rubia (la), 8",
    "sg:city":"Segovia",
    "sg:orig_category":"Centros De Coordinaci\u00d3n",
    "sg:phone":"+34 921 46 02 78",
    "sg:postcode":"40001",
    "sg:province":"Segovia",
    "wof:name":"Martin De Vidales De Andres Mariano",
    "wof:placetype":"venue"
},
  "geometry": {"coordinates":[-4.1222100258,40.9505577087],"type":"Point"}
}