{
  "type": "Feature",
  "properties": {
    "iso:country":"ES",
    "sg:address":"Avda San Sebastian, 132",
    "sg:city":"Santa Cruz De Tenerife",
    "sg:orig_category":"M\u00c9dicos: Pediatr\u00cda. Enfermedades De Los Ni\u00d1os",
    "sg:phone":"+34 922 22 37 96",
    "sg:postcode":"38005",
    "sg:province":"Santa Cruz De Tenerife",
    "wof:name":"Lopez Samblas Juan Pedro",
    "wof:placetype":"venue"
},
  "geometry": {"coordinates":[-16.2581386566,28.4633598328],"type":"Point"}
}