{
  "type": "Feature",
  "properties": {
    "addr:full":"Avda Breton De Los Herreros, 17 Haro La Rioja 26200",
    "addr:housenumber":"17",
    "addr:postcode":"26200",
    "addr:street":"Avda Breton De Los Herreros",
    "iso:country":"ES",
    "sg:address":"Avda Breton De Los Herreros, 17",
    "sg:city":"Haro",
    "sg:orig_category":"Escultores, Estatuarios E Imagineros",
    "sg:phone":"+34 941 31 02 56",
    "sg:postcode":"26200",
    "sg:province":"La Rioja",
    "wof:name":"Perez Fernandez Rafael",
    "wof:placetype":"venue"
},
  "geometry": {"coordinates":[-2.8575499058,42.573928833],"type":"Point"}
}