{
  "type": "Feature",
  "properties": {
    "iso:country":"ES",
    "sg:address":"Avgd Balmes, 16",
    "sg:city":"Lleida",
    "sg:orig_category":"Loter\u00cda Y T\u00d3mbola",
    "sg:phone":"+34 973 27 06 12",
    "sg:postcode":"25006",
    "sg:province":"Lleida",
    "wof:name":"Garcia Llop Francisca",
    "wof:placetype":"venue"
},
  "geometry": {"coordinates":[0.6202250123,41.617603302],"type":"Point"}
}