{
  "type": "Feature",
  "properties": {
    "iso:country":"ES",
    "sg:address":"Carrer de Terra Baixa, 45",
    "sg:city":"Hospitalet Llobregat",
    "sg:orig_category":"Molduras, Junquillos, Listones Y Molduras Perforadas",
    "sg:phone":"+34 932 61 27 58",
    "sg:postcode":"08901",
    "sg:province":"Barcelona",
    "wof:name":"Romero Rodriguez Eugenio",
    "wof:placetype":"venue"
},
  "geometry": {"coordinates":[2.114923954,41.3671150208],"type":"Point"}
}