{
  "type": "Feature",
  "properties": {
    "iso:country":"ES",
    "sg:address":"Pl Catalunya (de), 27",
    "sg:city":"Batea",
    "sg:orig_category":"Empresarios",
    "sg:phone":"+34 977 43 01 07",
    "sg:postcode":"43786",
    "sg:province":"Tarragona",
    "wof:name":"Paladella Valen S.l.",
    "wof:placetype":"venue"
},
  "geometry": {"coordinates":[0.3117809892,41.0942153931],"type":"Point"}
}