{
  "type": "Feature",
  "properties": {
    "addr:full":"Calle de Elexondo Kalea, 17 Amurrio \u00c1lava 01470",
    "addr:housenumber":"17",
    "addr:postcode":"01470",
    "addr:street":"Calle De Elexondo Kalea",
    "iso:country":"ES",
    "sg:address":"Calle de Elexondo Kalea, 17",
    "sg:city":"Amurrio",
    "sg:orig_category":"Pr\u00c9stamos Personales E Hipotecarios",
    "sg:phone":"+34 945 89 23 12",
    "sg:postcode":"01470",
    "sg:province":"\u00c1lava",
    "wof:name":"Registro De La Propiedad",
    "wof:placetype":"venue"
},
  "geometry": {"coordinates":[-2.9997570515,43.0529899597],"type":"Point"}
}