{
  "type": "Feature",
  "properties": {
    "addr:full":"Calle de Eugenia De Montijo, 60 Madrid Madrid 28025",
    "addr:housenumber":"60",
    "addr:postcode":"madrid;28025",
    "addr:street":"Calle De Eugenia De Montijo",
    "iso:country":"ES",
    "sg:address":"Calle de Eugenia De Montijo, 60",
    "sg:city":"Madrid",
    "sg:orig_category":"Molduras, Junquillos, Listones Y Molduras Perforadas",
    "sg:phone":"+34 914 66 50 01",
    "sg:postcode":"28025",
    "sg:province":"Madrid",
    "wof:name":"Salcedo Quesada Magnolia",
    "wof:placetype":"venue"
},
  "geometry": {"coordinates":[-3.7458379269,40.3803367615],"type":"Point"}
}