{
  "type": "Feature",
  "properties": {
    "addr:full":"Urkizu Pasealekua, 6 Eibar Guip\u00f9zcoa 20600",
    "addr:housenumber":"6",
    "addr:postcode":"20600",
    "addr:street":"Urkizu Pasealekua;Guipu\u0300Zcoa",
    "iso:country":"ES",
    "sg:address":"Urkizu Pasealekua, 6",
    "sg:city":"Eibar",
    "sg:orig_category":"Edici\u00d3n De Diarios, Revistas, Boletines",
    "sg:phone":"+34 943 12 09 59",
    "sg:postcode":"20600",
    "sg:province":"Guip\u00f9zcoa",
    "wof:name":"Arriola Iriondo Ane Maite",
    "wof:placetype":"venue"
},
  "geometry": {"coordinates":[-2.4640836716,43.1859130859],"type":"Point"}
}