{
  "type": "Feature",
  "properties": {
    "addr:full":"Avda Constitucion, 14 Mazarron Murcia 30870",
    "addr:housenumber":"14",
    "addr:postcode":"30870",
    "addr:street":"Avda Constitucion",
    "iso:country":"ES",
    "sg:address":"Avda Constitucion, 14",
    "sg:city":"Mazarron",
    "sg:orig_category":"Muebles, Minoristas",
    "sg:phone":"+34 968 59 02 33",
    "sg:postcode":"30870",
    "sg:province":"Murcia",
    "wof:name":"Automuebles Ure\u00f1a S.l.",
    "wof:placetype":"venue"
},
  "geometry": {"coordinates":[-1.31777215,37.6009979248],"type":"Point"}
}