{
  "type": "Feature",
  "properties": {
    "iso:country":"ES",
    "sg:address":"Calle de Rosario, 64",
    "sg:city":"Cabeza Buey",
    "sg:orig_category":"Fabrica De Cer\u00c1micas",
    "sg:phone":"+34 924 60 00 76",
    "sg:postcode":"06600",
    "sg:province":"Badajoz",
    "wof:name":"Cooperativa De Ceramica Nuestra Se\u00f1ora De Belen",
    "wof:placetype":"venue"
},
  "geometry": {"coordinates":[-5.2197828293,38.7185554504],"type":"Point"}
}