{
  "type": "Feature",
  "properties": {
    "iso:country":"ES",
    "sg:address":"Calle de Cendeja, 23",
    "sg:city":"San Juan De Muskiz",
    "sg:orig_category":"Electricidad: Instaladores",
    "sg:phone":"+34 946 70 61 80",
    "sg:postcode":"48550",
    "sg:province":"Vizcaya",
    "wof:name":"Saavedra Iba\u00f1ez Fernando",
    "wof:placetype":"venue"
},
  "geometry": {"coordinates":[-3.1194965839,43.3216438293],"type":"Point"}
}