{
  "type": "Feature",
  "properties": {
    "iso:country":"ES",
    "sg:address":"Carr Josep Tur I Llaneras, 8",
    "sg:city":"Eivissa",
    "sg:orig_category":"Carnicer\u00cdas, Carnicer\u00cdas",
    "sg:phone":"+34 971 39 30 28",
    "sg:postcode":"07800",
    "sg:province":"Islas Baleares",
    "wof:name":"Perez Yelo Purificacion",
    "wof:placetype":"venue"
},
  "geometry": {"coordinates":[1.4133399725,38.9031715393],"type":"Point"}
}