{
  "type": "Feature",
  "properties": {
    "addr:full":"Carr Alfred Pere\u00d1a, 70 Lleida Lleida 25004",
    "addr:housenumber":"70",
    "addr:postcode":"25004",
    "addr:street":"Carr Alfred Peren\u0303A",
    "iso:country":"ES",
    "sg:address":"Carr Alfred Pere\u00d1a, 70",
    "sg:city":"Lleida",
    "sg:orig_category":"Ropa Para Se\u00d1oras (al Por Menor)",
    "sg:phone":"+34 973 23 60 55",
    "sg:postcode":"25004",
    "sg:province":"Lleida",
    "wof:name":"In Tot S.c.p.",
    "wof:placetype":"venue"
},
  "geometry": {"coordinates":[0.6249657273,41.622718811],"type":"Point"}
}