{
  "type": "Feature",
  "properties": {
    "iso:country":"ES",
    "sg:address":"Calle de Arroyo De Las Pilillas, 8",
    "sg:city":"Madrid",
    "sg:orig_category":"Estilistas Y Estudios De Estilo De Corte Y Confecci\u00d3n",
    "sg:phone":"+34 914 39 54 31",
    "sg:postcode":"28030",
    "sg:province":"Madrid",
    "wof:name":"Diaz Bravo Venerando",
    "wof:placetype":"venue"
},
  "geometry": {"coordinates":[-3.6518085003,40.4068260193],"type":"Point"}
}