{
  "type": "Feature",
  "properties": {
    "iso:country":"ES",
    "sg:address":"Schez. Oca\u00f1a, 27",
    "sg:city":"Bejar",
    "sg:orig_category":"Farmacias",
    "sg:phone":"+34 923 40 24 66",
    "sg:postcode":"37700",
    "sg:province":"Salamanca",
    "wof:name":"Sanchez Mu\u00d1oz Maria Antonia",
    "wof:placetype":"venue"
},
  "geometry": {"coordinates":[-5.7683081627,40.3866577148],"type":"Point"}
}