{
  "type": "Feature",
  "properties": {
    "iso:country":"ES",
    "sg:address":"Ctra Sant Cugat, 28",
    "sg:city":"Barcelona",
    "sg:orig_category":"Arquitectos",
    "sg:phone":"+34 934 18 56 58",
    "sg:postcode":"08035",
    "sg:province":"Barcelona",
    "wof:name":"Garcia Montoya Miguel",
    "wof:placetype":"venue"
},
  "geometry": {"coordinates":[2.1388556957,41.419757843],"type":"Point"}
}