{
  "type": "Feature",
  "properties": {
    "addr:full":"Calle de Mendez Nu\u00d1ez, 8 Coria Rio Sevilla 41100",
    "addr:housenumber":"8",
    "addr:postcode":"41100",
    "addr:street":"Calle De Mendez Nun\u0303Ez;Rio Sevilla",
    "iso:country":"ES",
    "sg:address":"Calle de Mendez Nu\u00d1ez, 8",
    "sg:city":"Coria Rio",
    "sg:orig_category":"Zapatos (al Por Menor)",
    "sg:phone":"+34 954 77 46 70",
    "sg:postcode":"41100",
    "sg:province":"Sevilla",
    "wof:name":"Mu\u00f1oz Centeno Rafael",
    "wof:placetype":"venue"
},
  "geometry": {"coordinates":[-6.0515332222,37.2848320007],"type":"Point"}
}