{
  "type": "Feature",
  "properties": {
    "addr:full":"Carrer de Unio, 15 Palma Islas Baleares 07001",
    "addr:housenumber":"15",
    "addr:postcode":"07001",
    "addr:street":"Carrer De Unio",
    "iso:country":"ES",
    "sg:address":"Carrer de Unio, 15",
    "sg:city":"Palma",
    "sg:orig_category":"Camiser\u00cda Y Ropa Interior Masculina (al Por Menor)",
    "sg:phone":"+34 971 71 64 20",
    "sg:postcode":"07001",
    "sg:province":"Islas Baleares",
    "wof:name":"Garsaud  Andre Robert",
    "wof:placetype":"venue"
},
  "geometry": {"coordinates":[2.6485319138,39.5716590881],"type":"Point"}
}