{
  "type": "Feature",
  "properties": {
    "iso:country":"ES",
    "sg:address":"Avda Luz, 33",
    "sg:city":"Malaga",
    "sg:orig_category":"Estancos",
    "sg:phone":"+34 952 17 03 05",
    "sg:postcode":"29004",
    "sg:province":"M\u00e1laga",
    "wof:name":"Fernandez Guirado Rafael",
    "wof:placetype":"venue"
},
  "geometry": {"coordinates":[-4.4551858902,36.6971588135],"type":"Point"}
}