{
  "type": "Feature",
  "properties": {
    "iso:country":"ES",
    "sg:address":"Pg Mata, 1",
    "sg:city":"Reus",
    "sg:orig_category":"M\u00c9dicos: Geriatr\u00cda, Gerontolog\u00cda (enfermedades De La Tercera Edad)",
    "sg:phone":"+34 977 32 01 67",
    "sg:postcode":"43202",
    "sg:province":"Tarragona",
    "wof:name":"Llar Geriatrica Residencia Verde De Lourdes",
    "wof:placetype":"venue"
},
  "geometry": {"coordinates":[1.1022839546,41.161190033],"type":"Point"}
}