{
  "type": "Feature",
  "properties": {
    "addr:full":"Pg Hivern, S/n Calonge Girona 17251",
    "addr:housenumber":"s / n",
    "addr:postcode":"17251",
    "addr:street":"Pg Hivern",
    "iso:country":"ES",
    "sg:address":"Pg Hivern, S/n",
    "sg:city":"Calonge",
    "sg:orig_category":"Peluquer\u00cdas",
    "sg:phone":"+34 972 66 10 74",
    "sg:postcode":"17251",
    "sg:province":"Girona",
    "wof:name":"Darder Saballs Pilar",
    "wof:placetype":"venue"
},
  "geometry": {"coordinates":[3.0765450001,41.8615570068],"type":"Point"}
}