{
  "type": "Feature",
  "properties": {
    "addr:full":"Carrer de Valencia, 411 Barcelona Barcelona 08013",
    "addr:housenumber":"411",
    "addr:postcode":"08013",
    "addr:street":"Carrer De Valencia",
    "iso:country":"ES",
    "sg:address":"Carrer de Valencia, 411",
    "sg:city":"Barcelona",
    "sg:orig_category":"Carnicer\u00cdas, Carnicer\u00cdas",
    "sg:phone":"+34 934 58 25 94",
    "sg:postcode":"08013",
    "sg:province":"Barcelona",
    "wof:name":"Emuslan Perpose Rosalina",
    "wof:placetype":"venue"
},
  "geometry": {"coordinates":[2.1749770641,41.4015731812],"type":"Point"}
}