{
  "type": "Feature",
  "properties": {
    "addr:full":"Avda Madrid, 39 Daroca Zaragoza 50360",
    "addr:housenumber":"39",
    "addr:postcode":"50360",
    "addr:street":"Avda Madrid",
    "iso:country":"ES",
    "sg:address":"Avda Madrid, 39",
    "sg:city":"Daroca",
    "sg:orig_category":"Cooperativas Agr\u00cdcolas",
    "sg:phone":"+34 976 80 02 77",
    "sg:postcode":"50360",
    "sg:province":"Zaragoza",
    "wof:name":"Cooperativa Del Campo Santo Tomas De Aquino",
    "wof:placetype":"venue"
},
  "geometry": {"coordinates":[-1.4178349972,41.1106414795],"type":"Point"}
}