{
  "type": "Feature",
  "properties": {
    "iso:country":"ES",
    "sg:address":"Avda Baron De Carcer, 29",
    "sg:city":"Valencia",
    "sg:orig_category":"Bisuter\u00cda, Joyer\u00cda, Relojer\u00cda (al Por Menor)",
    "sg:phone":"+34 963 52 57 02",
    "sg:postcode":"46001",
    "sg:province":"Valencia",
    "wof:name":"Guillermo Vives S.l.",
    "wof:placetype":"venue"
},
  "geometry": {"coordinates":[-0.3795399964,39.4715766907],"type":"Point"}
}