{
  "type": "Feature",
  "properties": {
    "iso:country":"ES",
    "sg:address":"Calle de Jaraiz, 10",
    "sg:city":"Almendralejo",
    "sg:orig_category":"Prensas Industriales",
    "sg:phone":"+34 924 66 65 44",
    "sg:postcode":"06200",
    "sg:province":"Badajoz",
    "wof:name":"Garcia Ballesteros Diego",
    "wof:placetype":"venue"
},
  "geometry": {"coordinates":[-6.4101629257,38.6784858704],"type":"Point"}
}