{
  "type": "Feature",
  "properties": {
    "addr:full":"Calle de Andalucia, 1 Armilla Granada 18100",
    "addr:housenumber":"1",
    "addr:postcode":"18100",
    "addr:street":"Calle De Andalucia",
    "iso:country":"ES",
    "sg:address":"Calle de Andalucia, 1",
    "sg:city":"Armilla",
    "sg:orig_category":"M\u00c9dicos: Estomatolog\u00cda",
    "sg:phone":"+34 958 57 02 90",
    "sg:postcode":"18100",
    "sg:province":"Granada",
    "wof:name":"Vilchez Diaz Miguel Angel",
    "wof:placetype":"venue"
},
  "geometry": {"coordinates":[-3.6274969578,37.1422615051],"type":"Point"}
}