{
  "type": "Feature",
  "properties": {
    "iso:country":"ES",
    "sg:address":"Santa Mar\u00eda De Mellid, S/n",
    "sg:city":"Melide",
    "sg:orig_category":"Alimentaci\u00d3n General (al Por Menor)",
    "sg:phone":"+34 981 50 54 03",
    "sg:postcode":"15800",
    "sg:province":"La Coru\u00f1a",
    "wof:name":"Barreiro Parrado Jesus",
    "wof:placetype":"venue"
},
  "geometry": {"coordinates":[-8.0182342529,42.9104537964],"type":"Point"}
}