{
  "type": "Feature",
  "properties": {
    "iso:country":"ES",
    "sg:address":"Real Almadraba, S/n",
    "sg:city":"Barbate Franco",
    "sg:orig_category":"Laboratorios Y Cl\u00cdnicas Veterinarias",
    "sg:phone":"+34 956 43 12 70",
    "sg:postcode":"11160",
    "sg:province":"C\u00e1diz",
    "wof:name":"Guerrero Moreno Maria Del Pilar",
    "wof:placetype":"venue"
},
  "geometry": {"coordinates":[-5.9251914024,36.188129425],"type":"Point"}
}