{
  "type": "Feature",
  "properties": {
    "addr:full":"Calle de Mayor, 4 Tordehumos Valladolid 47830",
    "addr:housenumber":"4",
    "addr:postcode":"47830",
    "addr:street":"Calle De Mayor",
    "iso:country":"ES",
    "sg:address":"Calle de Mayor, 4",
    "sg:city":"Tordehumos",
    "sg:orig_category":"Asociaciones, Organismos Culturales Y Socioeducativos",
    "sg:phone":"+34 983 71 45 86",
    "sg:postcode":"47830",
    "sg:province":"Valladolid",
    "wof:name":"Asociacion Cultural Para El Desarrollo Del Sequillo",
    "wof:placetype":"venue"
},
  "geometry": {"coordinates":[-5.1583185196,41.8143730164],"type":"Point"}
}