{
  "type": "Feature",
  "properties": {
    "addr:full":"Avda Espa\u00d1a, 122 Estepona M\u00e1laga 29680",
    "addr:housenumber":"122",
    "addr:postcode":"29680",
    "addr:street":"Avda Espan\u0303A",
    "iso:country":"ES",
    "sg:address":"Avda Espa\u00d1a, 122",
    "sg:city":"Estepona",
    "sg:orig_category":"Cajas Para Embalar",
    "sg:phone":"+34 952 80 87 15",
    "sg:postcode":"29680",
    "sg:province":"M\u00e1laga",
    "wof:name":"Cajamar",
    "wof:placetype":"venue"
},
  "geometry": {"coordinates":[-5.1446890831,36.4248695374],"type":"Point"}
}