{
  "type": "Feature",
  "properties": {
    "iso:country":"ES",
    "sg:address":"Rua Comercio, 26",
    "sg:city":"Noia",
    "sg:orig_category":"Art\u00cdculos De Decoraci\u00d3n",
    "sg:phone":"+34 981 82 29 01",
    "sg:postcode":"15200",
    "sg:province":"La Coru\u00f1a",
    "wof:name":"Abeijon Moledo Jose Maria",
    "wof:placetype":"venue"
},
  "geometry": {"coordinates":[-8.887542,42.783573],"type":"Point"}
}