{
  "type": "Feature",
  "properties": {
    "addr:full":"Ctra General Del Norte, 47 Cantillo Santa Cruz De Tenerife 38350",
    "addr:housenumber":"47",
    "addr:postcode":"38350",
    "addr:street":"Ctra General Del Norte",
    "iso:country":"ES",
    "sg:address":"Ctra General Del Norte, 47",
    "sg:city":"Cantillo",
    "sg:classifiers":[
        {
            "category":"Personal",
            "subcategory":"Barber",
            "type":"Services"
        }
    ],
    "sg:phone":"+34 922 57 27 12",
    "sg:postcode":"38350",
    "sg:province":"Santa Cruz De Tenerife",
    "sg:tags":[
        "caballeros",
        "de",
        "peluqueros"
    ],
    "wof:name":"Huet  Alan",
    "wof:placetype":"venue"
},
  "geometry": {"coordinates":[-16.4174289703,28.4756546021],"type":"Point"}
}