{
  "type": "Feature",
  "properties": {
    "iso:country":"ES",
    "sg:address":"Fortuna-murcia, 1",
    "sg:city":"Fortuna",
    "sg:orig_category":"Reparaciones Y Remolcado De Veh\u00cdculos",
    "sg:phone":"+34 968 68 59 01",
    "sg:postcode":"30620",
    "sg:province":"Murcia",
    "wof:name":"Eurosistemas Modulares",
    "wof:placetype":"venue"
},
  "geometry": {"coordinates":[-1.1266340017,38.1826553345],"type":"Point"}
}