{
  "type": "Feature",
  "properties": {
    "addr:full":"Calle de Nueva, 27 Motril Granada 18600",
    "addr:housenumber":"27",
    "addr:postcode":"18600",
    "addr:street":"Calle De Nueva",
    "iso:country":"ES",
    "sg:address":"Calle de Nueva, 27",
    "sg:city":"Motril",
    "sg:orig_category":"Muebles Y Accesorios Para Cocinas Y Cuartos De Ba\u00d1o (al Por Menor)",
    "sg:phone":"+34 958 60 03 92",
    "sg:postcode":"18600",
    "sg:province":"Granada",
    "sg:website":"www.cocinahogar.com",
    "wof:name":"Cocinahogar Estudio S.l.",
    "wof:placetype":"venue"
},
  "geometry": {"coordinates":[-3.5181660652,36.7475662231],"type":"Point"}
}