{
  "type": "Feature",
  "properties": {
    "addr:full":"Calle de Ciscar, 36 Valencia Valencia 46005",
    "addr:housenumber":"36",
    "addr:postcode":"46005",
    "addr:street":"Calle De Ciscar",
    "iso:country":"ES",
    "sg:address":"Calle de Ciscar, 36",
    "sg:city":"Valencia",
    "sg:orig_category":"Audiovisuales (producci\u00d3n, Edici\u00d3n, Realizaci\u00d3n)",
    "sg:phone":"+34 963 34 33 63",
    "sg:postcode":"46005",
    "sg:province":"Valencia",
    "wof:name":"Black Maria S.l.l.",
    "wof:placetype":"venue"
},
  "geometry": {"coordinates":[-0.3652949929,39.4652061462],"type":"Point"}
}