{
  "type": "Feature",
  "properties": {
    "addr:full":"Carrer de Escornalbou, 40 Barcelona Barcelona 08041",
    "addr:housenumber":"40",
    "addr:postcode":"08041",
    "addr:street":"Carrer De Escornalbou",
    "iso:country":"ES",
    "sg:address":"Carrer de Escornalbou, 40",
    "sg:city":"Barcelona",
    "sg:orig_category":"Construcciones Prefabricadas Y Desmontables",
    "sg:phone":"+34 934 35 40 80",
    "sg:postcode":"08041",
    "sg:province":"Barcelona",
    "wof:name":"Copanel 2002 S.l.",
    "wof:placetype":"venue"
},
  "geometry": {"coordinates":[2.1778950691,41.4178619385],"type":"Point"}
}