{
  "type": "Feature",
  "properties": {
    "addr:full":"Pase Fernando El Catolico, 43 Zaragoza Zaragoza 50006",
    "addr:housenumber":"43",
    "addr:postcode":"50006",
    "addr:street":"Fernando El Catolico",
    "iso:country":"ES",
    "sg:address":"Pase Fernando El Catolico, 43",
    "sg:city":"Zaragoza",
    "sg:orig_category":"Modistas",
    "sg:phone":"+34 976 35 81 03",
    "sg:postcode":"50006",
    "sg:province":"Zaragoza",
    "wof:name":"Studio Carlos S.cv.",
    "wof:placetype":"venue"
},
  "geometry": {"coordinates":[-0.8955860138,41.6397895813],"type":"Point"}
}