{
  "type": "Feature",
  "properties": {
    "iso:country":"ES",
    "sg:address":"Avda Constitucion, 170",
    "sg:city":"Villena",
    "sg:orig_category":"Molduras, Junquillos, Listones Y Molduras Perforadas",
    "sg:phone":"+34 965 80 63 26",
    "sg:postcode":"03400",
    "sg:province":"Alicante",
    "wof:name":"Lopez Torres Virtudes",
    "wof:placetype":"venue"
},
  "geometry": {"coordinates":[-0.86817801,38.6407203674],"type":"Point"}
}