{
  "type": "Feature",
  "properties": {
    "addr:full":"Calle de Antonio Machado, 1 Torre Mar M\u00e1laga 29740",
    "addr:housenumber":"1",
    "addr:postcode":"29740",
    "addr:street":"Calle De Antonio Machado;Ma\u0301Laga",
    "iso:country":"ES",
    "sg:address":"Calle de Antonio Machado, 1",
    "sg:city":"Torre Mar",
    "sg:orig_category":"Art\u00cdculos De Regalo (al Por Menor)",
    "sg:phone":"+34 952 54 48 99",
    "sg:postcode":"29740",
    "sg:province":"M\u00e1laga",
    "wof:name":"Martin Molina Francisco",
    "wof:placetype":"venue"
},
  "geometry": {"coordinates":[-4.0980286598,36.7401542664],"type":"Point"}
}