{
  "type": "Feature",
  "properties": {
    "addr:full":"Calle de Huete, 55 Ceuti Murcia 30562",
    "addr:housenumber":"55",
    "addr:postcode":"30562",
    "addr:street":"Calle De Huete",
    "iso:country":"ES",
    "sg:address":"Calle de Huete, 55",
    "sg:city":"Ceuti",
    "sg:orig_category":"Ropa Para Caballeros (al Por Menor)",
    "sg:phone":"+34 968 69 36 04",
    "sg:postcode":"30562",
    "sg:province":"Murcia",
    "wof:name":"Centro Modas Jose Maria Nieto S.l.",
    "wof:placetype":"venue"
},
  "geometry": {"coordinates":[-1.2719370127,38.0791015625],"type":"Point"}
}