{
  "type": "Feature",
  "properties": {
    "iso:country":"ES",
    "sg:address":"Calle de Escuelas, 8",
    "sg:city":"Solana De Rioalmar",
    "sg:orig_category":"Centros De Educaci\u00d3n Especial",
    "sg:phone":"+34 920 23 22 18",
    "sg:postcode":"05144",
    "sg:province":"\u00c1vila",
    "wof:name":"Centro Rural Agrupado La Sierra-m.educacion Y Ciencia",
    "wof:placetype":"venue"
},
  "geometry": {"coordinates":[-5.0090789795,40.7382698059],"type":"Point"}
}