{
  "type": "Feature",
  "properties": {
    "iso:country":"ES",
    "sg:address":"Rua Ponte (da), 76",
    "sg:city":"Lalin",
    "sg:orig_category":"Almacenes Frigor\u00cdficos",
    "sg:phone":"+34 986 78 12 84",
    "sg:postcode":"36500",
    "sg:province":"Pontevedra",
    "wof:name":"Instalaciones Frigorificas Carrera S.c.",
    "wof:placetype":"venue"
},
  "geometry": {"coordinates":[-8.1130685806,42.6647605896],"type":"Point"}
}