{
  "type": "Feature",
  "properties": {
    "addr:full":"Avda Monforte De Lemos, 109 Madrid Madrid 28029",
    "addr:housenumber":"109",
    "addr:postcode":"28029",
    "addr:street":"Avda Monforte De Lemos",
    "iso:country":"ES",
    "sg:address":"Avda Monforte De Lemos, 109",
    "sg:city":"Madrid",
    "sg:orig_category":"Asociaciones Y Clubs Deportivos",
    "sg:phone":"+34 913 78 00 05",
    "sg:postcode":"28029",
    "sg:province":"Madrid",
    "wof:name":"Victor String S.l.",
    "wof:placetype":"venue"
},
  "geometry": {"coordinates":[-3.7072069645,40.4785766602],"type":"Point"}
}