{
  "type": "Feature",
  "properties": {
    "addr:full":"Av. Scho Fuerte, 28 Iru\u00f1a Navarra 31008",
    "addr:housenumber":"28",
    "addr:postcode":"31008",
    "addr:street":"Av. Scho Fuerte",
    "iso:country":"ES",
    "sg:address":"Av. Scho Fuerte, 28",
    "sg:city":"Iru\u00f1a",
    "sg:orig_category":"Ense\u00d1anza Superior Privada",
    "sg:phone":"+34 948 25 26 50",
    "sg:postcode":"31008",
    "sg:province":"Navarra",
    "wof:name":"Orden De La Compa\u00f1ia De Maria Nuestra Se\u00f1ora",
    "wof:placetype":"venue"
},
  "geometry": {"coordinates":[-1.6611410379,42.8117103577],"type":"Point"}
}