{
  "type": "Feature",
  "properties": {
    "addr:full":"Calle de Alfareria, 93 Sevilla Sevilla 41010",
    "addr:housenumber":"93",
    "addr:postcode":"41010",
    "addr:street":"Calle De Alfareria",
    "iso:country":"ES",
    "sg:address":"Calle de Alfareria, 93",
    "sg:city":"Sevilla",
    "sg:orig_category":"Pescader\u00cdas (al Por Menor)",
    "sg:phone":"+34 954 33 12 43",
    "sg:postcode":"41010",
    "sg:province":"Sevilla",
    "wof:name":"Machuca Rodriguez Antonio",
    "wof:placetype":"venue"
},
  "geometry": {"coordinates":[-6.006708622,37.3871612549],"type":"Point"}
}