{
  "type": "Feature",
  "properties": {
    "addr:full":"Calle de Hinojosas, 2 Puertollano Ciudad Real 13500",
    "addr:housenumber":"2",
    "addr:postcode":"13500",
    "addr:street":"Calle De Hinojosas",
    "iso:country":"ES",
    "sg:address":"Calle de Hinojosas, 2",
    "sg:city":"Puertollano",
    "sg:orig_category":"Empresarios",
    "sg:phone":"+34 926 41 30 33",
    "sg:postcode":"13500",
    "sg:province":"Ciudad Real",
    "wof:name":"Fundacion Fuente Agria",
    "wof:placetype":"venue"
},
  "geometry": {"coordinates":[-4.4305090904,38.735748291],"type":"Point"}
}