{
  "type": "Feature",
  "properties": {
    "addr:full":"Avda Madrid (de), 153 Xinzo De Limia Ourense 32630",
    "addr:housenumber":"153",
    "addr:postcode":"32630",
    "addr:street":"Avda Madrid De",
    "iso:country":"ES",
    "sg:address":"Avda Madrid (de), 153",
    "sg:city":"Xinzo De Limia",
    "sg:orig_category":"Negocio De Madera",
    "sg:phone":"+34 988 46 24 49",
    "sg:postcode":"32630",
    "sg:province":"Ourense",
    "wof:name":"Tejada Pelaez Jesus",
    "wof:placetype":"venue"
},
  "geometry": {"coordinates":[-7.715845108,42.0596084595],"type":"Point"}
}