{
  "type": "Feature",
  "properties": {
    "iso:country":"ES",
    "sg:address":"Plaz Mercado, S/n",
    "sg:city":"Unquera",
    "sg:orig_category":"Electrodom\u00c9sticos (al Por Menor)",
    "sg:phone":"+34 942 71 71 27",
    "sg:postcode":"39560",
    "sg:province":"Cantabria",
    "wof:name":"Hermanos Junco S. L.",
    "wof:placetype":"venue"
},
  "geometry": {"coordinates":[-4.5151238441,43.3745231628],"type":"Point"}
}