{
  "type": "Feature",
  "properties": {
    "iso:country":"ES",
    "sg:address":"Calle de Mayor, 343",
    "sg:city":"Raal",
    "sg:orig_category":"\u00d3ptica: Instrumentos (fabricaci\u00d3n)",
    "sg:phone":"+34 968 87 01 99",
    "sg:postcode":"30139",
    "sg:province":"Murcia",
    "wof:name":"Optica El Raal S.l.l.",
    "wof:placetype":"venue"
},
  "geometry": {"coordinates":[-1.0174707174,38.0459480286],"type":"Point"}
}