{
  "type": "Feature",
  "properties": {
    "iso:country":"ES",
    "sg:address":"Serra D'espada, 18",
    "sg:city":"Aldaia",
    "sg:orig_category":"Complementos De Vestir (al Por Menor)",
    "sg:phone":"+34 961 50 81 68",
    "sg:postcode":"46960",
    "sg:province":"Valencia",
    "wof:name":"Abanicos Aparisi S.l.",
    "wof:placetype":"venue"
},
  "geometry": {"coordinates":[-0.469085,39.472645],"type":"Point"}
}