{
  "type": "Feature",
  "properties": {
    "addr:full":"Calle de Pablo Gorosabel Kalea, 40 Tolosa Guip\u00f9zcoa 20400",
    "addr:housenumber":"40",
    "addr:postcode":"20400",
    "addr:street":"Calle De Pablo Gorosabel Kalea;Guipu\u0300Zcoa",
    "iso:country":"ES",
    "sg:address":"Calle de Pablo Gorosabel Kalea, 40",
    "sg:city":"Tolosa",
    "sg:orig_category":"Asesor\u00cda De Formaci\u00d3n Y Gesti\u00d3n De Personal",
    "sg:phone":"+34 943 65 42 46",
    "sg:postcode":"20400",
    "sg:province":"Guip\u00f9zcoa",
    "wof:name":"Tapia Jimenez I\u00f1aki",
    "wof:placetype":"venue"
},
  "geometry": {"coordinates":[-2.0734500885,43.1398620605],"type":"Point"}
}