{
  "type": "Feature",
  "properties": {
    "addr:full":"Carrer de Frares, 2 S. Joan Despi Barcelona 08970",
    "addr:housenumber":"2",
    "addr:postcode":"08970",
    "addr:street":"Carrer De Frares;S. Joan Despi",
    "iso:country":"ES",
    "sg:address":"Carrer de Frares, 2",
    "sg:city":"S. Joan Despi",
    "sg:orig_category":"Molduras, Junquillos, Listones Y Molduras Perforadas",
    "sg:phone":"+34 933 73 79 06",
    "sg:postcode":"08970",
    "sg:province":"Barcelona",
    "wof:name":"Lorido Ramos Enrique",
    "wof:placetype":"venue"
},
  "geometry": {"coordinates":[2.0758728981,41.3695602417],"type":"Point"}
}