{
  "type": "Feature",
  "properties": {
    "iso:country":"ES",
    "sg:address":"Calle de Travieso, 32",
    "sg:city":"Palmas De Gran Canaria",
    "sg:orig_category":"Inmobiliaria (agencias)",
    "sg:phone":"+34 928 36 98 98",
    "sg:postcode":"35002",
    "sg:province":"Las Palmas",
    "wof:name":"Medina Hernandez Freya Micaela",
    "wof:placetype":"venue"
},
  "geometry": {"coordinates":[-15.4171667099,28.1048698425],"type":"Point"}
}