{
  "type": "Feature",
  "properties": {
    "addr:full":"Alam Colon, 12 Malaga M\u00e1laga 29001",
    "addr:housenumber":"12",
    "addr:postcode":"29001",
    "addr:street":"Alam Colon;Ma\u0301Laga",
    "iso:country":"ES",
    "sg:address":"Alam Colon, 12",
    "sg:city":"Malaga",
    "sg:orig_category":"Asesor\u00cda De Formaci\u00d3n Y Gesti\u00d3n De Personal",
    "sg:phone":"+34 952 22 27 44",
    "sg:postcode":"29001",
    "sg:province":"M\u00e1laga",
    "wof:name":"Lunas Manchado Maria Victoria",
    "wof:placetype":"venue"
},
  "geometry": {"coordinates":[-4.4247279167,36.715221405],"type":"Point"}
}