{
  "type": "Feature",
  "properties": {
    "iso:country":"ES",
    "sg:address":"Calle de Malagon, 9",
    "sg:city":"Madrid",
    "sg:orig_category":"Venta, Instalaci\u00d3n, Reparaci\u00d3n De Antenas Para Televisi\u00d3n",
    "sg:phone":"+34 913 81 49 45",
    "sg:postcode":"28043",
    "sg:province":"Madrid",
    "wof:name":"Telyme S.l.",
    "wof:placetype":"venue"
},
  "geometry": {"coordinates":[-3.6389770508,40.4679145813],"type":"Point"}
}