{
  "type": "Feature",
  "properties": {
    "iso:country":"ES",
    "sg:address":"Rua Castor Sanchez, 15",
    "sg:city":"Vilagarcia",
    "sg:orig_category":"Zapatos (al Por Menor)",
    "sg:phone":"+34 986 50 84 42",
    "sg:postcode":"36600",
    "sg:province":"Pontevedra",
    "wof:name":"Fernandez Sumay S.l.",
    "wof:placetype":"venue"
},
  "geometry": {"coordinates":[-8.7647857666,42.5976715088],"type":"Point"}
}