{
  "type": "Feature",
  "properties": {
    "iso:country":"ES",
    "sg:address":"Carrer de Ruben Dario, 9",
    "sg:city":"Palma",
    "sg:orig_category":"Compraventa De Antig\u00dcedades",
    "sg:phone":"+34 971 72 30 75",
    "sg:postcode":"07012",
    "sg:province":"Islas Baleares",
    "wof:name":"Sagrera Caldentey Miguel",
    "wof:placetype":"venue"
},
  "geometry": {"coordinates":[2.6450989246,39.575428009],"type":"Point"}
}