{
  "type": "Feature",
  "properties": {
    "iso:country":"ES",
    "sg:address":"Avda Carlota Alessandri, 220",
    "sg:city":"Torremolinos",
    "sg:orig_category":"Inmobiliaria (agencias)",
    "sg:phone":"+34 952 05 80 37",
    "sg:postcode":"29620",
    "sg:province":"M\u00e1laga",
    "wof:name":"Ubicaciones Andalucia S.l.",
    "wof:placetype":"venue"
},
  "geometry": {"coordinates":[-4.5108780861,36.6060714722],"type":"Point"}
}