{
  "type": "Feature",
  "properties": {
    "iso:country":"ES",
    "sg:address":"Calle de Francisco Javier Sauquillo (de), 1",
    "sg:city":"Mostoles",
    "sg:orig_category":"Aparcamientos (infraestructuras, Accesorios)",
    "sg:phone":"+34 916 13 55 48",
    "sg:postcode":"28932",
    "sg:province":"Madrid",
    "wof:name":"Garaje Francisco Javier Sauquillo C.b.",
    "wof:placetype":"venue"
},
  "geometry": {"coordinates":[-3.8555750847,40.3319740295],"type":"Point"}
}