{
  "type": "Feature",
  "properties": {
    "iso:country":"ES",
    "sg:address":"Calle de Do\u00d1a Jimena, 13",
    "sg:city":"Roda",
    "sg:orig_category":"Escayola Y Productos De Escayola (fabricaci\u00d3n, Al Por Mayor)",
    "sg:phone":"+34 967 44 34 24",
    "sg:postcode":"02630",
    "sg:province":"Albacete",
    "wof:name":"Clemente Martinez Eugenio",
    "wof:placetype":"venue"
},
  "geometry": {"coordinates":[-2.1617689133,39.2064208984],"type":"Point"}
}