{
  "type": "Feature",
  "properties": {
    "iso:country":"ES",
    "sg:address":"Santa Catalina, 8",
    "sg:city":"Lucena",
    "sg:orig_category":"Comadronas",
    "sg:phone":"+34 957 50 09 95",
    "sg:postcode":"14900",
    "sg:province":"C\u00f3rdoba",
    "wof:name":"Montoya Linde Librada",
    "wof:placetype":"venue"
},
  "geometry": {"coordinates":[-4.4876170158,37.4093971252],"type":"Point"}
}