{
  "type": "Feature",
  "properties": {
    "addr:full":"Calle de Santiago, 22 Albacete Albacete 02005",
    "addr:housenumber":"22",
    "addr:postcode":"02005",
    "addr:street":"Calle De Santiago",
    "iso:country":"ES",
    "sg:address":"Calle de Santiago, 22",
    "sg:city":"Albacete",
    "sg:orig_category":"Comerciantes Al Por Mayor De Vinos, Licores Y Alcoholes",
    "sg:phone":"+34 967 52 21 08",
    "sg:postcode":"02005",
    "sg:province":"Albacete",
    "wof:name":"Alfaro Reolid Jose Luis",
    "wof:placetype":"venue"
},
  "geometry": {"coordinates":[-1.8641915321,39.0008773804],"type":"Point"}
}