{
  "type": "Feature",
  "properties": {
    "iso:country":"ES",
    "sg:address":"Carrer de Anselm Clave, 3",
    "sg:city":"Cambrils",
    "sg:orig_category":"Delegados, Agentes De Tr\u00c1nsito, Auxiliares De Transporte Internacional",
    "sg:phone":"+34 977 36 54 12",
    "sg:postcode":"43850",
    "sg:province":"Tarragona",
    "wof:name":"Avellan Perez Eloy",
    "wof:placetype":"venue"
},
  "geometry": {"coordinates":[1.0504430532,41.0739479065],"type":"Point"}
}