{
  "type": "Feature",
  "properties": {
    "iso:country":"ES",
    "sg:address":"Avda Amaia, 22",
    "sg:city":"Leioa",
    "sg:orig_category":"Frutas, Legumbres Frescas Y Tempranas (al Por Menor)",
    "sg:phone":"+34 944 63 70 84",
    "sg:postcode":"48940",
    "sg:province":"Vizcaya",
    "wof:name":"Felix Carazo Arauzo",
    "wof:placetype":"venue"
},
  "geometry": {"coordinates":[-3.0058350563,43.3278579712],"type":"Point"}
}