{
  "type": "Feature",
  "properties": {
    "addr:full":"Ctra Valdegalindo, S/n Villamediana Iregua La Rioja 26142",
    "addr:housenumber":"s / n",
    "addr:postcode":"26142",
    "addr:street":"Ctra Valdegalindo;Villamediana Iregua;Rioja",
    "iso:country":"ES",
    "sg:address":"Ctra Valdegalindo, S/n",
    "sg:city":"Villamediana Iregua",
    "sg:orig_category":"Muebles, Minoristas",
    "sg:phone":"+34 941 43 51 07",
    "sg:postcode":"26142",
    "sg:province":"La Rioja",
    "wof:name":"Leon Hermanos Sociedad Anonima",
    "wof:placetype":"venue"
},
  "geometry": {"coordinates":[-2.417953968,42.4283485413],"type":"Point"}
}