{
  "type": "Feature",
  "properties": {
    "addr:full":"Calle de Generalisimo, S/n Tabara Zamora 49140",
    "addr:housenumber":"s / n",
    "addr:postcode":"49140",
    "addr:street":"Calle De Generalisimo",
    "iso:country":"ES",
    "sg:address":"Calle de Generalisimo, S/n",
    "sg:city":"Tabara",
    "sg:orig_category":"Plomeros",
    "sg:phone":"+34 980 59 03 84",
    "sg:postcode":"49140",
    "sg:province":"Zamora",
    "wof:name":"Fresno Fernandez Antonio",
    "wof:placetype":"venue"
},
  "geometry": {"coordinates":[-5.9617667198,41.8226509094],"type":"Point"}
}