{
  "type": "Feature",
  "properties": {
    "iso:country":"ES",
    "sg:address":"Calle de San Marcos (de), 9",
    "sg:city":"Rivas Vaciamadrid",
    "sg:orig_category":"Molduras, Junquillos, Listones Y Molduras Perforadas",
    "sg:phone":"+34 916 70 37 78",
    "sg:postcode":"28529",
    "sg:province":"Madrid",
    "wof:name":"Sanchez Alvarez Armando",
    "wof:placetype":"venue"
},
  "geometry": {"coordinates":[-3.5102670193,40.314289093],"type":"Point"}
}