{
  "type": "Feature",
  "properties": {
    "iso:country":"ES",
    "sg:address":"Crri Chornos, S/n",
    "sg:city":"Arboleja",
    "sg:orig_category":"Diarios, Revistas Y Boletines (distribuidores)",
    "sg:phone":"+34 968 29 54 66",
    "sg:postcode":"30009",
    "sg:province":"Murcia",
    "wof:name":"Cerezo Ortin Maria Angeles",
    "wof:placetype":"venue"
},
  "geometry": {"coordinates":[-1.1528439522,37.9883460999],"type":"Point"}
}