{
  "type": "Feature",
  "properties": {
    "iso:country":"ES",
    "sg:address":"Rua Marques De Valladares, 12",
    "sg:city":"Vigo",
    "sg:orig_category":"Agentes Generales De Seguros",
    "sg:phone":"+34 986 22 15 39",
    "sg:postcode":"36201",
    "sg:province":"Pontevedra",
    "wof:name":"Collazo Pazo Mercedes",
    "wof:placetype":"venue"
},
  "geometry": {"coordinates":[-8.7226285934,42.2381210327],"type":"Point"}
}