{
  "type": "Feature",
  "properties": {
    "iso:country":"ES",
    "sg:address":"Calle de San Agustin, 10",
    "sg:city":"Mutriku",
    "sg:orig_category":"Alquiler De V\u00cddeo",
    "sg:phone":"+34 943 19 50 25",
    "sg:postcode":"20830",
    "sg:province":"Guip\u00f9zcoa",
    "wof:name":"Elu Arruti Francisco Javier",
    "wof:placetype":"venue"
},
  "geometry": {"coordinates":[-2.3854689598,43.3060531616],"type":"Point"}
}