{
  "type": "Feature",
  "properties": {
    "iso:country":"ES",
    "sg:address":"Pl Doctor Letamendi, 3",
    "sg:city":"Barcelona",
    "sg:orig_category":"Agencias Y Asesores De Publicidad",
    "sg:phone":"+34 934 51 08 88",
    "sg:postcode":"08007",
    "sg:province":"Barcelona",
    "wof:name":"Gabcom Scp",
    "wof:placetype":"venue"
},
  "geometry": {"coordinates":[2.1609649658,41.3885383606],"type":"Point"}
}