{
  "type": "Feature",
  "properties": {
    "iso:country":"ES",
    "sg:address":"Urbanizacion Los Acebos, 13",
    "sg:city":"Carbajal Legua",
    "sg:orig_category":"Arquitectos",
    "sg:phone":"+34 987 28 85 35",
    "sg:postcode":"24196",
    "sg:province":"Le\u00f3n",
    "wof:name":"Biain Gonzalez Amelia",
    "wof:placetype":"venue"
},
  "geometry": {"coordinates":[-5.5979170799,42.6399269104],"type":"Point"}
}