{
  "type": "Feature",
  "properties": {
    "addr:full":"Calle de San Sebastian, 5 Santander Cantabria 39001",
    "addr:housenumber":"5",
    "addr:postcode":"39001",
    "addr:street":"Calle De San Sebastian",
    "iso:country":"ES",
    "sg:address":"Calle de San Sebastian, 5",
    "sg:city":"Santander",
    "sg:orig_category":"Caf\u00c9s, Bares, Cervecer\u00cdas",
    "sg:phone":"+34 942 22 14 32",
    "sg:postcode":"39001",
    "sg:province":"Cantabria",
    "wof:name":"Martin Magaldi Joaquin",
    "wof:placetype":"venue"
},
  "geometry": {"coordinates":[-3.8073890209,43.4654197693],"type":"Point"}
}