{
  "type": "Feature",
  "properties": {
    "iso:country":"ES",
    "sg:address":"Cra. Tarragona-lleida, Km. 0042,4",
    "sg:city":"Espluga Francoli",
    "sg:orig_category":"Fabricaci\u00d3n Y Venta De Volquetes Y Remolques",
    "sg:phone":"+34 977 87 04 73",
    "sg:postcode":"43440",
    "sg:province":"Tarragona",
    "wof:name":"Industrias Mapra S.c.p.",
    "wof:placetype":"venue"
},
  "geometry": {"coordinates":[1.0992749929,41.3950653076],"type":"Point"}
}