{
  "type": "Feature",
  "properties": {
    "addr:full":"D Mangrane, S/n Jesus Tarragona 43590",
    "addr:housenumber":"s / n",
    "addr:postcode":"43590",
    "iso:country":"ES",
    "sg:address":"D Mangrane, S/n",
    "sg:city":"Jesus",
    "sg:orig_category":"Iglesia Cat\u00d3lica",
    "sg:phone":"+34 977 50 09 95",
    "sg:postcode":"43590",
    "sg:province":"Tarragona",
    "wof:name":"Bisbat De Tortosa",
    "wof:placetype":"venue"
},
  "geometry": {"coordinates":[0.5113700032,40.8257141113],"type":"Point"}
}