{
  "type": "Feature",
  "properties": {
    "addr:full":"Calle de Lopez Del Vallado, 5 Oviedo Asturias 33010",
    "addr:housenumber":"5",
    "addr:postcode":"33010",
    "addr:street":"Calle De Lopez Del Vallado",
    "iso:country":"ES",
    "sg:address":"Calle de Lopez Del Vallado, 5",
    "sg:city":"Oviedo",
    "sg:orig_category":"Electricidad (montaje, Ensamblaje De Componentes)",
    "sg:phone":"+34 985 20 28 88",
    "sg:postcode":"33010",
    "sg:province":"Asturias",
    "wof:name":"Garcia Fernandez Manuel",
    "wof:placetype":"venue"
},
  "geometry": {"coordinates":[-5.8343429565,43.3633155823],"type":"Point"}
}