{
  "type": "Feature",
  "properties": {
    "addr:full":"Calle de Bellavista, 22 Zaragoza Zaragoza 50007",
    "addr:housenumber":"22",
    "addr:postcode":"50007",
    "addr:street":"Calle De Bellavista",
    "iso:country":"ES",
    "sg:address":"Calle de Bellavista, 22",
    "sg:city":"Zaragoza",
    "sg:orig_category":"Rectificaci\u00d3n, Mecanizado, Fresado",
    "sg:phone":"+34 976 27 60 12",
    "sg:postcode":"50007",
    "sg:province":"Zaragoza",
    "wof:name":"Rectificados Marzal S.l.",
    "wof:placetype":"venue"
},
  "geometry": {"coordinates":[-0.8775349855,41.6356201172],"type":"Point"}
}