{
  "type": "Feature",
  "properties": {
    "iso:country":"ES",
    "sg:address":"Carrer de Antoni Soler Hospital, 1",
    "sg:city":"Viladecavalls",
    "sg:orig_category":"Centros De Reservas Hoteleras",
    "sg:phone":"+34 937 80 51 01",
    "sg:postcode":"08232",
    "sg:province":"Barcelona",
    "sg:website":"www.ristol.com",
    "wof:name":"Sant Lluis De Ristol S.l.",
    "wof:placetype":"venue"
},
  "geometry": {"coordinates":[1.9540849924,41.5552368164],"type":"Point"}
}