{
  "type": "Feature",
  "properties": {
    "iso:country":"ES",
    "sg:address":"Calle de Visconti, 9",
    "sg:city":"Tarazona",
    "sg:orig_category":"Tapicer\u00cdas",
    "sg:phone":"+34 976 64 09 64",
    "sg:postcode":"50500",
    "sg:province":"Zaragoza",
    "wof:name":"Quilez Delgado Tomas",
    "wof:placetype":"venue"
},
  "geometry": {"coordinates":[-1.7247190475,41.9044837952],"type":"Point"}
}