{
  "type": "Feature",
  "properties": {
    "iso:country":"ES",
    "sg:address":"Avda Zamora, S/n",
    "sg:city":"Tordesillas",
    "sg:orig_category":"Herradores, Herreros, Carreteros",
    "sg:phone":"+34 983 77 08 83",
    "sg:postcode":"47100",
    "sg:province":"Valladolid",
    "wof:name":"Vecillas Santos S.l.",
    "wof:placetype":"venue"
},
  "geometry": {"coordinates":[-5.0041518211,41.5031700134],"type":"Point"}
}