{
  "type": "Feature",
  "properties": {
    "addr:full":"Calle de Cabo Alomar Blanes, 14 Palma Islas Baleares 07010",
    "addr:housenumber":"14",
    "addr:postcode":"07010",
    "addr:street":"Calle De Cabo Alomar Blanes",
    "iso:country":"ES",
    "sg:address":"Calle de Cabo Alomar Blanes, 14",
    "sg:city":"Palma",
    "sg:orig_category":"Promotores Constructores",
    "sg:phone":"+34 971 20 68 21",
    "sg:postcode":"07010",
    "sg:province":"Islas Baleares",
    "wof:name":"Construcciones Emba S. A.",
    "wof:placetype":"venue"
},
  "geometry": {"coordinates":[2.6471085548,39.5857009888],"type":"Point"}
}