{
  "type": "Feature",
  "properties": {
    "addr:full":"Carrer de Recs, 26 Reus Tarragona 43201",
    "addr:housenumber":"26",
    "addr:postcode":"43201",
    "addr:street":"Carrer De Recs",
    "iso:country":"ES",
    "sg:address":"Carrer de Recs, 26",
    "sg:city":"Reus",
    "sg:orig_category":"Material Y Suministros Para Fotocopiadoras, Reprograf\u00cda",
    "sg:phone":"+34 977 31 56 60",
    "sg:postcode":"43201",
    "sg:province":"Tarragona",
    "wof:name":"Ramon Bergada Mecanitzacio D'oficines S.l.",
    "wof:placetype":"venue"
},
  "geometry": {"coordinates":[1.1051540375,41.1571388245],"type":"Point"}
}