{
  "type": "Feature",
  "properties": {
    "addr:full":"C/ Diagonal, 41 Cerdanyola Valles Barcelona 08290",
    "addr:housenumber":"41",
    "addr:postcode":"08290",
    "addr:street":"C / Diagonal;Valles Barcelona",
    "iso:country":"ES",
    "sg:address":"C/ Diagonal, 41",
    "sg:city":"Cerdanyola Valles",
    "sg:orig_category":"Centros De Educaci\u00d3n Especial",
    "sg:phone":"+34 936 92 27 42",
    "sg:postcode":"08290",
    "sg:province":"Barcelona",
    "wof:name":"Ceip Serraparera",
    "wof:placetype":"venue"
},
  "geometry": {"coordinates":[2.132584095,41.4947433472],"type":"Point"}
}