{
  "type": "Feature",
  "properties": {
    "iso:country":"ES",
    "sg:address":"Plaz Bib-rambla (de), 15",
    "sg:city":"Granada",
    "sg:orig_category":"Caf\u00c9s, Bares, Cervecer\u00cdas",
    "sg:phone":"+34 958 52 19 97",
    "sg:postcode":"18001",
    "sg:province":"Granada",
    "sg:website":"www.cafediroma.com",
    "wof:name":"Rubi\u00f1o Martos S.l.",
    "wof:placetype":"venue"
},
  "geometry": {"coordinates":[-3.600071907,37.1756782532],"type":"Point"}
}