{
  "type": "Feature",
  "properties": {
    "iso:country":"ES",
    "sg:address":"Plaz Gilberto Quijano, 1",
    "sg:city":"Torrelavega",
    "sg:orig_category":"Ense\u00d1anza: Profesiones Art\u00cdsticas",
    "sg:phone":"+34 942 89 05 97",
    "sg:postcode":"39300",
    "sg:province":"Cantabria",
    "wof:name":"Herrero Marcos Neftali",
    "wof:placetype":"venue"
},
  "geometry": {"coordinates":[-4.0520391464,43.34897995],"type":"Point"}
}