{
  "type": "Feature",
  "properties": {
    "addr:full":"Calle de Isla Corcega, 18 Puerto Valencia 46520",
    "addr:housenumber":"18",
    "addr:postcode":"46520",
    "addr:street":"Calle De Isla Corcega",
    "iso:country":"ES",
    "sg:address":"Calle de Isla Corcega, 18",
    "sg:city":"Puerto",
    "sg:orig_category":"Ropa Para Ni\u00d1os (al Por Menor)",
    "sg:phone":"+34 962 68 16 37",
    "sg:postcode":"46520",
    "sg:province":"Valencia",
    "wof:name":"Estornell Huguet Carolina",
    "wof:placetype":"venue"
},
  "geometry": {"coordinates":[-0.2135940045,39.6638717651],"type":"Point"}
}