{
  "type": "Feature",
  "properties": {
    "addr:full":"Calle de Cobalto, 121 Valladolid Valladolid 47012",
    "addr:housenumber":"121",
    "addr:postcode":"47012",
    "addr:street":"Calle De Cobalto",
    "iso:country":"ES",
    "sg:address":"Calle de Cobalto, 121",
    "sg:city":"Valladolid",
    "sg:orig_category":"Ebanister\u00cda",
    "sg:phone":"+34 983 30 70 92",
    "sg:postcode":"47012",
    "sg:province":"Valladolid",
    "wof:name":"Adrados Mendez Carlos",
    "wof:placetype":"venue"
},
  "geometry": {"coordinates":[-4.7044382095,41.6211166382],"type":"Point"}
}