{
  "type": "Feature",
  "properties": {
    "iso:country":"ES",
    "sg:address":"Plaz Santo Domingo, 4",
    "sg:city":"San Miguel",
    "sg:orig_category":"Inmobiliaria (agencias)",
    "sg:phone":"+34 968 20 47 59",
    "sg:postcode":"30008",
    "sg:province":"Murcia",
    "wof:name":"Navarro Palazon Antonio",
    "wof:placetype":"venue"
},
  "geometry": {"coordinates":[-1.1287599802,37.987411499],"type":"Point"}
}