{
  "type": "Feature",
  "properties": {
    "iso:country":"ES",
    "sg:address":"Calle de Solsona, 9",
    "sg:city":"Madrid",
    "sg:orig_category":"Prot\u00c9sicos Dentales",
    "sg:phone":"+34 917 66 65 28",
    "sg:postcode":"28033",
    "sg:province":"Madrid",
    "wof:name":"Mu\u00f1oz Pereira Daniel",
    "wof:placetype":"venue"
},
  "geometry": {"coordinates":[-3.6514320374,40.4721374512],"type":"Point"}
}