{
  "type": "Feature",
  "properties": {
    "iso:country":"ES",
    "sg:address":"Plaz San Telmo, 2",
    "sg:city":"Palencia",
    "sg:orig_category":"Venta, Instalaci\u00d3n, Reparaci\u00d3n De Antenas Para Televisi\u00d3n",
    "sg:phone":"+34 979 71 11 15",
    "sg:postcode":"34004",
    "sg:province":"Palencia",
    "wof:name":"Delta Comunicaciones Palencia S.l.",
    "wof:placetype":"venue"
},
  "geometry": {"coordinates":[-4.5209488869,41.996673584],"type":"Point"}
}