{
  "type": "Feature",
  "properties": {
    "addr:full":"Calle de San Antonio, 4 Ciudad Real Ciudad Real 13003",
    "addr:housenumber":"4",
    "addr:postcode":"13003",
    "addr:street":"Calle De San Antonio",
    "iso:country":"ES",
    "sg:address":"Calle de San Antonio, 4",
    "sg:city":"Ciudad Real",
    "sg:orig_category":"Promotores Constructores",
    "sg:phone":"+34 926 22 76 77",
    "sg:postcode":"13003",
    "sg:province":"Ciudad Real",
    "wof:name":"Concasa Gestion 2010 S.l.",
    "wof:placetype":"venue"
},
  "geometry": {"coordinates":[-3.9242351055,38.9903755188],"type":"Point"}
}