{
  "type": "Feature",
  "properties": {
    "addr:full":"Calle de Cruz De La, 1 Bilbao Vizcaya 48005",
    "addr:housenumber":"1",
    "addr:postcode":"48005",
    "addr:street":"Calle De Cruz De La",
    "iso:country":"ES",
    "sg:address":"Calle de Cruz De La, 1",
    "sg:city":"Bilbao",
    "sg:orig_category":"Loter\u00cda Y T\u00d3mbola",
    "sg:phone":"+34 944 15 19 47",
    "sg:postcode":"48005",
    "sg:province":"Vizcaya",
    "wof:name":"Gomez Salazar Maria Del Carmen",
    "wof:placetype":"venue"
},
  "geometry": {"coordinates":[-2.8724930286,43.2338142395],"type":"Point"}
}