{
  "type": "Feature",
  "properties": {
    "iso:country":"ES",
    "sg:address":"Carrer de Mossen Cinto Verdaguer, 26",
    "sg:city":"Manlleu",
    "sg:orig_category":"Materias Pl\u00c1sticas: Art\u00cdculos Para La Industria",
    "sg:phone":"+34 938 51 08 89",
    "sg:postcode":"08560",
    "sg:province":"Barcelona",
    "wof:name":"Castell Prat Jose",
    "wof:placetype":"venue"
},
  "geometry": {"coordinates":[2.288517952,42.0013923645],"type":"Point"}
}