{
  "type": "Feature",
  "properties": {
    "addr:full":"Calle de Alfonso Xiii, 38 Parla Madrid 28980",
    "addr:housenumber":"38",
    "addr:postcode":"28980",
    "addr:street":"Calle De Alfonso Xiii",
    "iso:country":"ES",
    "sg:address":"Calle de Alfonso Xiii, 38",
    "sg:city":"Parla",
    "sg:orig_category":"Fabricaci\u00d3n, Venta, Instalaci\u00d3n De R\u00d3tulos, De R\u00d3tulos Luminosos",
    "sg:phone":"+34 916 98 62 47",
    "sg:postcode":"28980",
    "sg:province":"Madrid",
    "wof:name":"Martos Lasso De La Vega Santos",
    "wof:placetype":"venue"
},
  "geometry": {"coordinates":[-3.7628278732,40.2332038879],"type":"Point"}
}