{
  "type": "Feature",
  "properties": {
    "addr:full":"Avda Canto Coral, S/n Borja Zaragoza 50540",
    "addr:housenumber":"s / n",
    "addr:postcode":"50540",
    "addr:street":"Avda Canto Coral",
    "iso:country":"ES",
    "sg:address":"Avda Canto Coral, S/n",
    "sg:city":"Borja",
    "sg:orig_category":"Polideportivos",
    "sg:phone":"+34 976 85 25 05",
    "sg:postcode":"50540",
    "sg:province":"Zaragoza",
    "wof:name":"Ayuntamiento De Borja",
    "wof:placetype":"venue"
},
  "geometry": {"coordinates":[-1.523332119,41.8319664001],"type":"Point"}
}