{
  "type": "Feature",
  "properties": {
    "iso:country":"ES",
    "sg:address":"Calle de Espejo, 18",
    "sg:city":"Galvez",
    "sg:orig_category":"T\u00c9cnicos Veterinarios",
    "sg:phone":"+34 925 40 00 41",
    "sg:postcode":"45164",
    "sg:province":"Toledo",
    "wof:name":"Bejerano Rodriguez Maria Pilar",
    "wof:placetype":"venue"
},
  "geometry": {"coordinates":[-4.273499012,39.7014884949],"type":"Point"}
}