{
  "type": "Feature",
  "properties": {
    "addr:full":"Ctra. Galapagar-las Rozas, Km. 0014,8 Galapagar Madrid 28260",
    "addr:postcode":"28260",
    "addr:street":"Ctra. Galapagar-Las Rozas Km. 0014,8",
    "iso:country":"ES",
    "sg:address":"Ctra. Galapagar-las Rozas, Km. 0014,8",
    "sg:city":"Galapagar",
    "sg:orig_category":"Pizzer\u00cdas",
    "sg:phone":"+34 918 58 66 08",
    "sg:postcode":"28260",
    "sg:province":"Madrid",
    "wof:name":"Castillo Carpintero Leoncio",
    "wof:placetype":"venue"
},
  "geometry": {"coordinates":[-4.0020170212,40.5765609741],"type":"Point"}
}