{
  "type": "Feature",
  "properties": {
    "iso:country":"ES",
    "sg:address":"Calle de Serrano, 2",
    "sg:city":"Madrid",
    "sg:orig_category":"Confecci\u00d3n De Trajes Para Se\u00d1oras",
    "sg:phone":"+34 914 31 87 21",
    "sg:postcode":"28001",
    "sg:province":"Madrid",
    "wof:name":"Zorrilla Y Cia. S. L.",
    "wof:placetype":"venue"
},
  "geometry": {"coordinates":[-3.6884000301,40.4207954407],"type":"Point"}
}