{
  "type": "Feature",
  "properties": {
    "addr:full":"Calle de Cardenal Herranz Casado, 22 Baena C\u00f3rdoba 14850",
    "addr:housenumber":"22",
    "addr:postcode":"14850",
    "addr:street":"Calle De Cardenal Herranz Casado",
    "iso:country":"ES",
    "sg:address":"Calle de Cardenal Herranz Casado, 22",
    "sg:city":"Baena",
    "sg:orig_category":"Iglesia Cat\u00d3lica",
    "sg:phone":"+34 957 67 06 16",
    "sg:postcode":"14850",
    "sg:province":"C\u00f3rdoba",
    "wof:name":"Parroquia Santa Maria La Mayor",
    "wof:placetype":"venue"
},
  "geometry": {"coordinates":[-4.2948884964,37.6670646667],"type":"Point"}
}