{
  "type": "Feature",
  "properties": {
    "addr:full":"Calle de Comercio, 5 Toledo Toledo 45001",
    "addr:housenumber":"5",
    "addr:postcode":"45001",
    "addr:street":"Calle De Comercio",
    "iso:country":"ES",
    "sg:address":"Calle de Comercio, 5",
    "sg:city":"Toledo",
    "sg:orig_category":"Fabrica De Cer\u00c1micas",
    "sg:phone":"+34 925 22 22 61",
    "sg:postcode":"45001",
    "sg:province":"Toledo",
    "wof:name":"Martin Garcia Maria Julia",
    "wof:placetype":"venue"
},
  "geometry": {"coordinates":[-4.0233502388,39.8583488464],"type":"Point"}
}