{
  "type": "Feature",
  "properties": {
    "iso:country":"ES",
    "sg:address":"Rua Real, 12",
    "sg:city":"Pontevedra",
    "sg:orig_category":"Marroquiner\u00cda (confecci\u00d3n)",
    "sg:phone":"+34 986 85 13 77",
    "sg:postcode":"36002",
    "sg:province":"Pontevedra",
    "wof:name":"Vieitez Gonzalez Gerardo",
    "wof:placetype":"venue"
},
  "geometry": {"coordinates":[-8.6448221207,42.4329681396],"type":"Point"}
}