{
  "type": "Feature",
  "properties": {
    "iso:country":"ES",
    "sg:address":"Carr Olot, 25",
    "sg:city":"Besalu",
    "sg:orig_category":"Sales (al Por Mayor)",
    "sg:phone":"+34 972 59 16 13",
    "sg:postcode":"17850",
    "sg:province":"Girona",
    "sg:website":"www.platspreparatsangelina.com",
    "wof:name":"Plats Preparats Angelina S.l.",
    "wof:placetype":"venue"
},
  "geometry": {"coordinates":[2.6976718903,42.2003211975],"type":"Point"}
}