{
  "type": "Feature",
  "properties": {
    "addr:full":"Calle de Real De Burgos, 16 Valladolid Valladolid 47011",
    "addr:housenumber":"16",
    "addr:postcode":"47011",
    "addr:street":"Calle De Real De Burgos",
    "iso:country":"ES",
    "sg:address":"Calle de Real De Burgos, 16",
    "sg:city":"Valladolid",
    "sg:orig_category":"Trabajos De Soldaduras",
    "sg:phone":"+34 983 25 19 35",
    "sg:postcode":"47011",
    "sg:province":"Valladolid",
    "wof:name":"Alisolpa S.l.",
    "wof:placetype":"venue"
},
  "geometry": {"coordinates":[-4.7187986374,41.6584510803],"type":"Point"}
}