{
  "type": "Feature",
  "properties": {
    "addr:full":"Trav De Gracia, 117 Barcelona Barcelona 08012",
    "addr:housenumber":"117",
    "addr:postcode":"08012",
    "addr:street":"Trav De Gracia",
    "iso:country":"ES",
    "sg:address":"Trav De Gracia, 117",
    "sg:city":"Barcelona",
    "sg:orig_category":"Laboratorios Y Cl\u00cdnicas Veterinarias",
    "sg:phone":"+34 932 17 08 94",
    "sg:postcode":"08012",
    "sg:province":"Barcelona",
    "wof:name":"Sanz Maudes Emilia",
    "wof:placetype":"venue"
},
  "geometry": {"coordinates":[2.1547250748,41.3995780945],"type":"Point"}
}