{
  "type": "Feature",
  "properties": {
    "addr:full":"Plaz Constitucion, S/n Terque Almer\u00eda 04569",
    "addr:postcode":"04569",
    "addr:street":"Constitucion S / N Terque Almeri\u0301A",
    "iso:country":"ES",
    "sg:address":"Plaz Constitucion, S/n",
    "sg:city":"Terque",
    "sg:orig_category":"Molduras, Junquillos, Listones Y Molduras Perforadas",
    "sg:phone":"+34 950 64 33 06",
    "sg:postcode":"04569",
    "sg:province":"Almer\u00eda",
    "wof:name":"Mullor Garcia Jose Antonio",
    "wof:placetype":"venue"
},
  "geometry": {"coordinates":[-2.597192049,36.9839782715],"type":"Point"}
}