{
  "type": "Feature",
  "properties": {
    "addr:full":"Calle de Chile, 3 Utrera Sevilla 41710",
    "addr:housenumber":"3",
    "addr:postcode":"41710",
    "addr:street":"Calle De Chile",
    "iso:country":"ES",
    "sg:address":"Calle de Chile, 3",
    "sg:city":"Utrera",
    "sg:orig_category":"Reposter\u00cdas",
    "sg:phone":"+34 955 86 44 50",
    "sg:postcode":"41710",
    "sg:province":"Sevilla",
    "wof:name":"Palacios Avala Carmen",
    "wof:placetype":"venue"
},
  "geometry": {"coordinates":[-5.7854709625,37.1808700562],"type":"Point"}
}