{
  "type": "Feature",
  "properties": {
    "addr:full":"Rua Carmen (do), 14 Carballi\u00f1o Ourense 32500",
    "addr:housenumber":"14",
    "addr:postcode":"32500",
    "addr:street":"Rua Carmen Do",
    "iso:country":"ES",
    "sg:address":"Rua Carmen (do), 14",
    "sg:city":"Carballi\u00f1o",
    "sg:orig_category":"Peluqueros: De Se\u00d1oras",
    "sg:phone":"+34 988 27 49 43",
    "sg:postcode":"32500",
    "sg:province":"Ourense",
    "wof:name":"Dobarro Crespo Luisa",
    "wof:placetype":"venue"
},
  "geometry": {"coordinates":[-8.0779943466,42.4294815063],"type":"Point"}
}