{
  "type": "Feature",
  "properties": {
    "addr:full":"Calle de Campo, 5 Soria Soria 42001",
    "addr:housenumber":"5",
    "addr:postcode":"42001",
    "addr:street":"Calle De Campo",
    "iso:country":"ES",
    "sg:address":"Calle de Campo, 5",
    "sg:city":"Soria",
    "sg:orig_category":"Sindicatos De Trabajadores",
    "sg:phone":"+34 975 22 20 86",
    "sg:postcode":"42001",
    "sg:province":"Soria",
    "wof:name":"Sindicato De Enfermeria (satse",
    "wof:placetype":"venue"
},
  "geometry": {"coordinates":[-2.4707798958,41.7685508728],"type":"Point"}
}