{
  "type": "Feature",
  "properties": {
    "iso:country":"ES",
    "sg:address":"Calle de Rios Rosas, 12",
    "sg:city":"Madrid",
    "sg:orig_category":"Organismos Y Centros De Vacaciones Y Esparcimiento Para Ni\u00d1os Y Adolescentes",
    "sg:phone":"+34 913 99 10 35",
    "sg:postcode":"28003",
    "sg:province":"Madrid",
    "wof:name":"Arranz Del Barrio Maria De La Cruz",
    "wof:placetype":"venue"
},
  "geometry": {"coordinates":[-3.702855587,40.4420471191],"type":"Point"}
}