{
  "type": "Feature",
  "properties": {
    "addr:full":"Calle de Santo (el), 18 Villamartin C\u00e1diz 11650",
    "addr:housenumber":"18",
    "addr:postcode":"11650",
    "addr:street":"Calle De Santo El;Ca\u0301Diz",
    "iso:country":"ES",
    "sg:address":"Calle de Santo (el), 18",
    "sg:city":"Villamartin",
    "sg:orig_category":"Bancos",
    "sg:phone":"+34 956 73 11 10",
    "sg:postcode":"11650",
    "sg:province":"C\u00e1diz",
    "wof:name":"Banco Vitalicio De Espa\u00d1a C.a.",
    "wof:placetype":"venue"
},
  "geometry": {"coordinates":[-5.6426692009,36.8602790833],"type":"Point"}
}