{
  "type": "Feature",
  "properties": {
    "addr:full":"Pl. A. S. Casanovas, 3 Sort Lleida 25560",
    "addr:housenumber":"3",
    "addr:postcode":"25560",
    "addr:street":"Pl. A. S. Casanovas",
    "iso:country":"ES",
    "sg:address":"Pl. A. S. Casanovas, 3",
    "sg:city":"Sort",
    "sg:orig_category":"Peluquer\u00cdas, Peluquer\u00cda Mixta",
    "sg:phone":"+34 973 62 00 44",
    "sg:postcode":"25560",
    "sg:province":"Lleida",
    "wof:name":"Farre Gasia Maria Pilar",
    "wof:placetype":"venue"
},
  "geometry": {"coordinates":[1.1303800344,42.4112358093],"type":"Point"}
}