{
  "type": "Feature",
  "properties": {
    "addr:full":"Calle de Estalajes, 41 Azuaga Badajoz 06920",
    "addr:housenumber":"41",
    "addr:postcode":"06920",
    "addr:street":"Calle De Estalajes",
    "iso:country":"ES",
    "sg:address":"Calle de Estalajes, 41",
    "sg:city":"Azuaga",
    "sg:orig_category":"Telas Y Sedas (al Por Menor)",
    "sg:phone":"+34 924 89 07 93",
    "sg:postcode":"06920",
    "sg:province":"Badajoz",
    "wof:name":"Montosa Alarcon Jose",
    "wof:placetype":"venue"
},
  "geometry": {"coordinates":[-5.6836190224,38.2613792419],"type":"Point"}
}