{
  "type": "Feature",
  "properties": {
    "addr:full":"Calle de Ancha Del Carmen, 41 Malaga M\u00e1laga 29002",
    "addr:housenumber":"41",
    "addr:postcode":"29002",
    "addr:street":"Calle De Ancha Del Carmen;Ma\u0301Laga",
    "iso:country":"ES",
    "sg:address":"Calle de Ancha Del Carmen, 41",
    "sg:city":"Malaga",
    "sg:orig_category":"Carnicer\u00cdas, Carnicer\u00cdas",
    "sg:phone":"+34 952 31 05 98",
    "sg:postcode":"29002",
    "sg:province":"M\u00e1laga",
    "wof:name":"Mancera Canalejo Maria Josefa",
    "wof:placetype":"venue"
},
  "geometry": {"coordinates":[-4.4285945892,36.7143669128],"type":"Point"}
}