{
  "type": "Feature",
  "properties": {
    "addr:full":"Pase La Epitafia, 3 Briviesca Burgos 09240",
    "addr:housenumber":"3",
    "addr:postcode":"09240",
    "iso:country":"ES",
    "sg:address":"Pase La Epitafia, 3",
    "sg:city":"Briviesca",
    "sg:orig_category":"Administradores De Bienes Y Delegados De Comunidades De Propietarios",
    "sg:phone":"+34 947 59 28 44",
    "sg:postcode":"09240",
    "sg:province":"Burgos",
    "wof:name":"Comunidad De Propietarios Pasaje Epitafia N\u00ba3-port 4",
    "wof:placetype":"venue"
},
  "geometry": {"coordinates":[-3.3240199089,42.5523300171],"type":"Point"}
}