{
  "type": "Feature",
  "properties": {
    "addr:full":"Cmno Circunvalacion (de), S/n Castro Rei Lugo 27250",
    "addr:postcode":"27250",
    "addr:street":"Cmno Circunvalacion De S / N",
    "iso:country":"ES",
    "sg:address":"Cmno Circunvalacion (de), S/n",
    "sg:city":"Castro Rei",
    "sg:orig_category":"Maquinaria Para Industrias Diversas",
    "sg:phone":"+34 982 31 40 11",
    "sg:postcode":"27250",
    "sg:province":"Lugo",
    "wof:name":"Talleres Agricolas Pe\u00f1a S.l.",
    "wof:placetype":"venue"
},
  "geometry": {"coordinates":[-7.4004621506,43.209941864],"type":"Point"}
}