{
  "type": "Feature",
  "properties": {
    "iso:country":"ES",
    "sg:address":"Avda Juan Carlos I, S/n",
    "sg:city":"Puntal",
    "sg:orig_category":"Fabricaci\u00d3n, Venta, Instalaci\u00d3n De R\u00d3tulos, De R\u00d3tulos Luminosos",
    "sg:phone":"+34 968 30 75 95",
    "sg:postcode":"30100",
    "sg:province":"Murcia",
    "wof:name":"Visotec Espa\u00f1a S.l.",
    "wof:placetype":"venue"
},
  "geometry": {"coordinates":[-1.154328227,38.013130188],"type":"Point"}
}