{
  "type": "Feature",
  "properties": {
    "iso:country":"ES",
    "sg:address":"Carr Jaume Pons Marti, 12",
    "sg:city":"Girona",
    "sg:orig_category":"Bares, Piano",
    "sg:phone":"+34 872 08 01 45",
    "sg:postcode":"17004",
    "sg:province":"Girona",
    "wof:name":"Sunset Jazz-club S.l.l",
    "wof:placetype":"venue"
},
  "geometry": {"coordinates":[2.8241920471,41.9888916016],"type":"Point"}
}