{
  "type": "Feature",
  "properties": {
    "addr:full":"Calle de Santa Susana, 41 Oviedo Asturias 33007",
    "addr:housenumber":"41",
    "addr:postcode":"33007",
    "addr:street":"Calle De Santa Susana",
    "iso:country":"ES",
    "sg:address":"Calle de Santa Susana, 41",
    "sg:city":"Oviedo",
    "sg:orig_category":"Abogados",
    "sg:phone":"+34 985 23 16 85",
    "sg:postcode":"33007",
    "sg:province":"Asturias",
    "wof:name":"Suarez Tamargo Manuel",
    "wof:placetype":"venue"
},
  "geometry": {"coordinates":[-5.8529295921,43.3613204956],"type":"Point"}
}