{
  "type": "Feature",
  "properties": {
    "iso:country":"ES",
    "sg:address":"Calle de Beneficiado Jose Estupi\u00d1an, 34",
    "sg:city":"Goro",
    "sg:orig_category":"Electrodom\u00c9sticos (fabricaci\u00d3n, Al Por Mayor)",
    "sg:phone":"+34 928 70 07 38",
    "sg:postcode":"35215",
    "sg:province":"Las Palmas",
    "wof:name":"Codilamar S.l.",
    "wof:placetype":"venue"
},
  "geometry": {"coordinates":[-15.398223877,27.9939899445],"type":"Point"}
}