{
  "type": "Feature",
  "properties": {
    "addr:full":"Ctra. General, S/n Navelgas Asturias 33873",
    "addr:postcode":"33873",
    "addr:street":"Ctra. General S / N Navelgas Asturias",
    "iso:country":"ES",
    "sg:address":"Ctra. General, S/n",
    "sg:city":"Navelgas",
    "sg:orig_category":"Negocio De Madera",
    "sg:phone":"+34 985 80 60 01",
    "sg:postcode":"33873",
    "sg:province":"Asturias",
    "wof:name":"Bravo Fernandez Santos",
    "wof:placetype":"venue"
},
  "geometry": {"coordinates":[-6.5324959755,43.4251785278],"type":"Point"}
}