{
  "type": "Feature",
  "properties": {
    "iso:country":"ES",
    "sg:address":"Calle de Fuente (de La), 3",
    "sg:city":"Totana",
    "sg:orig_category":"Bares, Piano",
    "sg:phone":"+34 968 42 43 32",
    "sg:postcode":"30850",
    "sg:province":"Murcia",
    "wof:name":"Woods  Lisa",
    "wof:placetype":"venue"
},
  "geometry": {"coordinates":[-1.4992457628,37.7715415955],"type":"Point"}
}