{
  "type": "Feature",
  "properties": {
    "addr:full":"Calle de Maria De Guzman, 51 Madrid Madrid 28003",
    "addr:housenumber":"51",
    "addr:postcode":"madrid;28003",
    "addr:street":"Calle De Maria De Guzman",
    "iso:country":"ES",
    "sg:address":"Calle de Maria De Guzman, 51",
    "sg:city":"Madrid",
    "sg:orig_category":"Carnicer\u00cdas, Carnicer\u00cdas",
    "sg:phone":"+34 915 33 23 68",
    "sg:postcode":"28003",
    "sg:province":"Madrid",
    "wof:name":"Guerrero Moran Jose Luis",
    "wof:placetype":"venue"
},
  "geometry": {"coordinates":[-3.6977260113,40.4441833496],"type":"Point"}
}