{
  "type": "Feature",
  "properties": {
    "addr:full":"Av. Arquitecte E. Ferres I Puig, 49 Vilassar Barcelona 08340",
    "addr:housenumber":"49",
    "addr:postcode":"08340",
    "addr:street":"Av. Arquitecte E. Ferres I Puig",
    "iso:country":"ES",
    "sg:address":"Av. Arquitecte E. Ferres I Puig, 49",
    "sg:city":"Vilassar",
    "sg:orig_category":"Laboratorios Y Cl\u00cdnicas Veterinarias",
    "sg:phone":"+34 937 59 85 65",
    "sg:postcode":"08340",
    "sg:province":"Barcelona",
    "wof:name":"Anvet S. L.",
    "wof:placetype":"venue"
},
  "geometry": {"coordinates":[2.3838303089,41.5041503906],"type":"Point"}
}