{
  "type": "Feature",
  "properties": {
    "addr:full":"Plaz Virgen Del Sol, 4 Adamuz C\u00f3rdoba 14430",
    "addr:housenumber":"4",
    "addr:postcode":"14430",
    "addr:street":"Plaz Virgen Del Sol",
    "iso:country":"ES",
    "sg:address":"Plaz Virgen Del Sol, 4",
    "sg:city":"Adamuz",
    "sg:orig_category":"Cooperativas Agr\u00cdcolas",
    "sg:phone":"+34 957 16 63 13",
    "sg:postcode":"14430",
    "sg:province":"C\u00f3rdoba",
    "wof:name":"Caja Rural Nuestra Madre Del Sol",
    "wof:placetype":"venue"
},
  "geometry": {"coordinates":[-4.5246610641,38.0278129578],"type":"Point"}
}