{
  "type": "Feature",
  "properties": {
    "iso:country":"ES",
    "sg:address":"Carr Mendez Nu\u00d1ez, 32",
    "sg:city":"Figueres",
    "sg:orig_category":"Agentes Generales De Seguros",
    "sg:phone":"+34 972 50 44 46",
    "sg:postcode":"17600",
    "sg:province":"Girona",
    "wof:name":"Buixo Serra Jaume",
    "wof:placetype":"venue"
},
  "geometry": {"coordinates":[2.9659149647,42.2642059326],"type":"Point"}
}