{
  "type": "Feature",
  "properties": {
    "iso:country":"ES",
    "sg:address":"Carrer de Garcilaso, 178",
    "sg:city":"Barcelona",
    "sg:orig_category":"Ropa Para Se\u00d1oras Y Caballeros (al Por Menor)",
    "sg:phone":"+34 933 49 21 85",
    "sg:postcode":"08027",
    "sg:province":"Barcelona",
    "wof:name":"Camilleri Losa Blanca Isabel",
    "wof:placetype":"venue"
},
  "geometry": {"coordinates":[2.1807510853,41.4236335754],"type":"Point"}
}