{
  "type": "Feature",
  "properties": {
    "iso:country":"ES",
    "sg:address":"Carrer de Ramelleres, 3",
    "sg:city":"Barcelona",
    "sg:orig_category":"\u00d3ptica: Instrumentos (fabricaci\u00d3n)",
    "sg:phone":"+34 933 18 29 96",
    "sg:postcode":"08001",
    "sg:province":"Barcelona",
    "wof:name":"Vilardebo Marco Maria Assumpta",
    "wof:placetype":"venue"
},
  "geometry": {"coordinates":[2.1691660881,41.3838424683],"type":"Point"}
}