{
  "type": "Feature",
  "properties": {
    "addr:full":"Calle de Tentudia, 1 Sevilla Sevilla 41018",
    "addr:housenumber":"1",
    "addr:postcode":"41018",
    "addr:street":"Calle De Tentudia",
    "iso:country":"ES",
    "sg:address":"Calle de Tentudia, 1",
    "sg:city":"Sevilla",
    "sg:orig_category":"Ingenier\u00cda, Centros De Estudios (diversos)",
    "sg:phone":"+34 954 53 08 97",
    "sg:postcode":"41018",
    "sg:province":"Sevilla",
    "wof:name":"Martin Rivero Manuel Jesus",
    "wof:placetype":"venue"
},
  "geometry": {"coordinates":[-5.9822387695,37.3817710876],"type":"Point"}
}