{
  "type": "Feature",
  "properties": {
    "addr:full":"Calle de Lomita, 33 Churriana M\u00e1laga 29140",
    "addr:housenumber":"33",
    "addr:postcode":"29140",
    "addr:street":"Calle De Lomita",
    "iso:country":"ES",
    "sg:address":"Calle de Lomita, 33",
    "sg:city":"Churriana",
    "sg:orig_category":"Agencias Y Agentes Comerciales, Representantes",
    "sg:phone":"+34 952 62 12 49",
    "sg:postcode":"29140",
    "sg:province":"M\u00e1laga",
    "wof:name":"Representaciones Fernandez E Hijos S.l.",
    "wof:placetype":"venue"
},
  "geometry": {"coordinates":[-4.5020170212,36.6667861938],"type":"Point"}
}