{
  "type": "Feature",
  "properties": {
    "iso:country":"ES",
    "sg:address":"Calle de Franchy Roca, 11",
    "sg:city":"Doctoral",
    "sg:orig_category":"Asociaciones Y Clubs Deportivos",
    "sg:phone":"+34 928 79 10 34",
    "sg:postcode":"35110",
    "sg:province":"Las Palmas",
    "wof:name":"Asociacion Ornitologica Club De Canaricultura El Capirote",
    "wof:placetype":"venue"
},
  "geometry": {"coordinates":[-15.4538202286,27.8337249756],"type":"Point"}
}