{
  "type": "Feature",
  "properties": {
    "iso:country":"ES",
    "sg:address":"Avda Ferrol, 21",
    "sg:city":"Pontedeume",
    "sg:orig_category":"Caf\u00c9s, Bares, Cervecer\u00cdas",
    "sg:phone":"+34 981 43 18 04",
    "sg:postcode":"15600",
    "sg:province":"La Coru\u00f1a",
    "wof:name":"Dobarrio Dominguez Jose Luis",
    "wof:placetype":"venue"
},
  "geometry": {"coordinates":[-8.1744127274,43.4092597961],"type":"Point"}
}