{
  "type": "Feature",
  "properties": {
    "addr:full":"Plaz Mossen Sorell, 11 Valencia Valencia 46003",
    "addr:housenumber":"11",
    "addr:postcode":"46003",
    "addr:street":"Sorell",
    "iso:country":"ES",
    "sg:address":"Plaz Mossen Sorell, 11",
    "sg:city":"Valencia",
    "sg:orig_category":"Mercer\u00cda, Lencer\u00cda (al Por Menor)",
    "sg:phone":"+34 963 91 28 45",
    "sg:postcode":"46003",
    "sg:province":"Valencia",
    "wof:name":"Tornero Piqueras Maria Pilar",
    "wof:placetype":"venue"
},
  "geometry": {"coordinates":[-0.380230993,39.4779319763],"type":"Point"}
}