{
  "type": "Feature",
  "properties": {
    "iso:country":"ES",
    "sg:address":"Calle de Fundacion Jado Kalea, 10",
    "sg:city":"Erandio",
    "sg:orig_category":"Caf\u00c9s, Bares, Cervecer\u00cdas",
    "sg:phone":"+34 944 67 43 71",
    "sg:postcode":"48950",
    "sg:province":"Vizcaya",
    "sg:website":"www.xixili-cafe.com",
    "wof:name":"Xixili, Proyecto 2001, S.l.",
    "wof:placetype":"venue"
},
  "geometry": {"coordinates":[-2.9762246609,43.3035926819],"type":"Point"}
}