{
  "type": "Feature",
  "properties": {
    "addr:full":"Barrio Quintana, S/n Silio Cantabria 39438",
    "addr:housenumber":"s",
    "addr:postcode":"39438",
    "addr:street":"Barrio Quintana;/ N",
    "iso:country":"ES",
    "sg:address":"Barrio Quintana, S/n",
    "sg:city":"Silio",
    "sg:orig_category":"Empresas De Desmonte",
    "sg:phone":"+34 942 82 82 94",
    "sg:postcode":"39438",
    "sg:province":"Cantabria",
    "wof:name":"Saiz Navamuel Luis",
    "wof:placetype":"venue"
},
  "geometry": {"coordinates":[-4.0330238342,43.1446037292],"type":"Point"}
}