{
  "type": "Feature",
  "properties": {
    "addr:full":"Av Pau (de La), 10 Morell Tarragona 43760",
    "addr:housenumber":"10",
    "addr:postcode":"43760",
    "addr:street":"Av Pau De La",
    "iso:country":"ES",
    "sg:address":"Av Pau (de La), 10",
    "sg:city":"Morell",
    "sg:orig_category":"Electricidad: Instaladores",
    "sg:phone":"+34 977 84 12 50",
    "sg:postcode":"43760",
    "sg:province":"Tarragona",
    "wof:name":"Ingenieria Y Montajes Electroneumaticos",
    "wof:placetype":"venue"
},
  "geometry": {"coordinates":[1.2065999508,41.1918067932],"type":"Point"}
}