{
  "type": "Feature",
  "properties": {
    "iso:country":"ES",
    "sg:address":"Calle de Ortubia, 2",
    "sg:city":"Almunia De Do\u00e7a Godina",
    "sg:orig_category":"Electricidad: Instaladores",
    "sg:phone":"+34 976 60 10 54",
    "sg:postcode":"50100",
    "sg:province":"Zaragoza",
    "wof:name":"Inmela S. L.",
    "wof:placetype":"venue"
},
  "geometry": {"coordinates":[-1.3738820553,41.4783363342],"type":"Point"}
}