{
  "type": "Feature",
  "properties": {
    "iso:country":"ES",
    "sg:address":"Calle de Maestro Serrano, 36",
    "sg:city":"Tuejar",
    "sg:orig_category":"Agricultores, Agricultores",
    "sg:phone":"+34 961 63 53 14",
    "sg:postcode":"46177",
    "sg:province":"Valencia",
    "wof:name":"Oltra Martinez Maria Jesus",
    "wof:placetype":"venue"
},
  "geometry": {"coordinates":[-1.0406534672,39.7684249878],"type":"Point"}
}