{
  "type": "Feature",
  "properties": {
    "iso:country":"ES",
    "sg:address":"Eusko Gudarien Kalea, 5",
    "sg:city":"Orio",
    "sg:orig_category":"Contenedores (mercanc\u00cdas)",
    "sg:phone":"+34 943 83 21 55",
    "sg:postcode":"20810",
    "sg:province":"Guip\u00f9zcoa",
    "wof:name":"Elizalde Aldabaldetreku Maria Lourdes",
    "wof:placetype":"venue"
},
  "geometry": {"coordinates":[-2.1279230118,43.2769966125],"type":"Point"}
}