{
  "type": "Feature",
  "properties": {
    "addr:full":"Calle de Don Juan Manuel, 10 Torremolinos M\u00e1laga 29620",
    "addr:housenumber":"10",
    "addr:postcode":"29620",
    "addr:street":"Calle De Don Juan Manuel;Ma\u0301Laga",
    "iso:country":"ES",
    "sg:address":"Calle de Don Juan Manuel, 10",
    "sg:city":"Torremolinos",
    "sg:orig_category":"Plomeros",
    "sg:phone":"+34 952 37 56 23",
    "sg:postcode":"29620",
    "sg:province":"M\u00e1laga",
    "wof:name":"Gomez Sanchez Ignacio Manuel",
    "wof:placetype":"venue"
},
  "geometry": {"coordinates":[-4.5080857277,36.610118866],"type":"Point"}
}