{
  "type": "Feature",
  "properties": {
    "addr:full":"Calle de Doctor Aquilino Hurle, 42 Gijon Asturias 33203",
    "addr:housenumber":"42",
    "addr:postcode":"33203",
    "addr:street":"Calle De Doctor Aquilino Hurle",
    "iso:country":"ES",
    "sg:address":"Calle de Doctor Aquilino Hurle, 42",
    "sg:city":"Gijon",
    "sg:orig_category":"Panader\u00cdas, Panader\u00cdas",
    "sg:phone":"+34 985 36 63 37",
    "sg:postcode":"33203",
    "sg:province":"Asturias",
    "wof:name":"Pintueles Diaz Jose Luis",
    "wof:placetype":"venue"
},
  "geometry": {"coordinates":[-5.646985054,43.5399131775],"type":"Point"}
}