{
  "type": "Feature",
  "properties": {
    "iso:country":"ES",
    "sg:address":"Avda Arana Sabino, 8",
    "sg:city":"Bilbao",
    "sg:orig_category":"Asesor\u00cda Sobre Comunicaci\u00d3n De Empresas",
    "sg:phone":"+34 944 39 35 61",
    "sg:postcode":"48013",
    "sg:province":"Vizcaya",
    "wof:name":"Azpiegitura S.a.",
    "wof:placetype":"venue"
},
  "geometry": {"coordinates":[-2.9462828636,43.2631759644],"type":"Point"}
}