{
  "type": "Feature",
  "properties": {
    "addr:full":"Ctra. N. 432, Km. 4280,0 Atarfe Granada 18230",
    "addr:postcode":"18230",
    "addr:street":"Ctra. N. 432 Km. 4280,0",
    "iso:country":"ES",
    "sg:address":"Ctra. N. 432, Km. 4280,0",
    "sg:city":"Atarfe",
    "sg:orig_category":"Controles De Edificaci\u00d3n (construcci\u00d3n, Seguridad)",
    "sg:phone":"+34 958 43 47 16",
    "sg:postcode":"18230",
    "sg:province":"Granada",
    "wof:name":"Espartero Promotor De Viviendas",
    "wof:placetype":"venue"
},
  "geometry": {"coordinates":[-3.6903159618,37.2228775024],"type":"Point"}
}