{
  "type": "Feature",
  "properties": {
    "addr:full":"Rua Fari\u00d1a Ferre\u00d1o, 21 Vilagarcia Pontevedra 36600",
    "addr:housenumber":"21",
    "addr:postcode":"36600",
    "addr:street":"Rua Farin\u0303A Ferren\u0303O",
    "iso:country":"ES",
    "sg:address":"Rua Fari\u00d1a Ferre\u00d1o, 21",
    "sg:city":"Vilagarcia",
    "sg:orig_category":"Art\u00cdculos De Regalo (al Por Menor)",
    "sg:phone":"+34 986 50 22 56",
    "sg:postcode":"36600",
    "sg:province":"Pontevedra",
    "sg:website":"www.ideasenlata.com",
    "wof:name":"Lumeras Choren Julian",
    "wof:placetype":"venue"
},
  "geometry": {"coordinates":[-8.7636709213,42.592754364],"type":"Point"}
}