{
  "type": "Feature",
  "properties": {
    "iso:country":"ES",
    "sg:address":"Avda Rectores, S/n",
    "sg:city":"Conjunto Residencial",
    "sg:orig_category":"Diarios, Revistas Y Boletines (distribuidores)",
    "sg:phone":"+34 968 30 63 24",
    "sg:postcode":"30100",
    "sg:province":"Murcia",
    "wof:name":"Espin Martinez Teresa Maria",
    "wof:placetype":"venue"
},
  "geometry": {"coordinates":[-1.1629890203,38.0146064758],"type":"Point"}
}