{
  "type": "Feature",
  "properties": {
    "iso:country":"ES",
    "sg:address":"Calle de Mayor, 398",
    "sg:city":"Raal",
    "sg:orig_category":"Reposter\u00cdas",
    "sg:phone":"+34 968 60 09 02",
    "sg:postcode":"30139",
    "sg:province":"Murcia",
    "wof:name":"Soto Ayllon Antonia",
    "wof:placetype":"venue"
},
  "geometry": {"coordinates":[-1.0361876488,38.035610199],"type":"Point"}
}