{
  "type": "Feature",
  "properties": {
    "iso:country":"ES",
    "sg:address":"Carrer de Rector Farres I Poch, 11",
    "sg:city":"Prat Llobregat",
    "sg:orig_category":"Ense\u00d1anza: Idiomas",
    "sg:phone":"+34 933 70 09 05",
    "sg:postcode":"08820",
    "sg:province":"Barcelona",
    "wof:name":"My School English Centrex S.l",
    "wof:placetype":"venue"
},
  "geometry": {"coordinates":[2.091135025,41.3229064941],"type":"Point"}
}