{
  "type": "Feature",
  "properties": {
    "addr:full":"Av Goles De L'ebre, 13 Deltebre Tarragona 43580",
    "addr:housenumber":"13",
    "addr:postcode":"43580",
    "addr:street":"Av Goles De L'Ebre",
    "iso:country":"ES",
    "sg:address":"Av Goles De L'ebre, 13",
    "sg:city":"Deltebre",
    "sg:orig_category":"Congelados: Productos Alimentarios (al Por Menor)",
    "sg:phone":"+34 977 48 07 77",
    "sg:postcode":"43580",
    "sg:province":"Tarragona",
    "wof:name":"Pescabona S. A.",
    "wof:placetype":"venue"
},
  "geometry": {"coordinates":[0.7252910137,40.7227401733],"type":"Point"}
}