{
  "type": "Feature",
  "properties": {
    "iso:country":"ES",
    "sg:address":"Calle de Octavio Cuartero, 70",
    "sg:city":"Albacete",
    "sg:orig_category":"Promotores Constructores",
    "sg:phone":"+34 967 50 72 09",
    "sg:postcode":"02004",
    "sg:province":"Albacete",
    "sg:website":"www.promocioneseden.es",
    "wof:name":"Promociones Eden De Torrevieja S.l.",
    "wof:placetype":"venue"
},
  "geometry": {"coordinates":[-1.8621640205,38.9932556152],"type":"Point"}
}