{
  "type": "Feature",
  "properties": {
    "iso:country":"ES",
    "sg:address":"Avda Cidacos, 6",
    "sg:city":"Arnedo",
    "sg:orig_category":"Electricidad (montaje, Ensamblaje De Componentes)",
    "sg:phone":"+34 941 38 26 02",
    "sg:postcode":"26580",
    "sg:province":"La Rioja",
    "wof:name":"Ruiz Sanchez Angel",
    "wof:placetype":"venue"
},
  "geometry": {"coordinates":[-2.1055049896,42.2251472473],"type":"Point"}
}