{
  "type": "Feature",
  "properties": {
    "addr:full":"Ctra Villanueva-adamuz, 3 Adamuz C\u00f3rdoba 14430",
    "addr:housenumber":"3",
    "addr:postcode":"14430",
    "addr:street":"Ctra Villanueva-Adamuz",
    "iso:country":"ES",
    "sg:address":"Ctra Villanueva-adamuz, 3",
    "sg:city":"Adamuz",
    "sg:orig_category":"Refiner\u00cdas De Petr\u00d3leo",
    "sg:phone":"+34 957 16 61 10",
    "sg:postcode":"14430",
    "sg:province":"C\u00f3rdoba",
    "wof:name":"Compa\u00f1ia Logistica De Hidrocarburos Clh S.a.",
    "wof:placetype":"venue"
},
  "geometry": {"coordinates":[-4.5246610641,38.0278129578],"type":"Point"}
}