{
  "type": "Feature",
  "properties": {
    "iso:country":"ES",
    "sg:address":"Calle de Pico Balaitus, 22",
    "sg:city":"Madrid",
    "sg:orig_category":"Comerciantes Al Por Mayor De Vinos, Licores Y Alcoholes",
    "sg:phone":"+34 913 78 09 03",
    "sg:postcode":"28035",
    "sg:province":"Madrid",
    "wof:name":"Gomez Jimenez Jesus",
    "wof:placetype":"venue"
},
  "geometry": {"coordinates":[-3.7206940651,40.482963562],"type":"Point"}
}