{
  "type": "Feature",
  "properties": {
    "iso:country":"ES",
    "sg:address":"Avda Estacion, 12",
    "sg:city":"Torre-pacheco",
    "sg:orig_category":"M\u00c9dicos: An\u00c1lisis Cl\u00cdnicos",
    "sg:phone":"+34 968 58 53 60",
    "sg:postcode":"30700",
    "sg:province":"Murcia",
    "wof:name":"Nieto Villa Miriam",
    "wof:placetype":"venue"
},
  "geometry": {"coordinates":[-1.1370509863,37.9407463074],"type":"Point"}
}