{
  "type": "Feature",
  "properties": {
    "addr:full":"Carrer de Sant Isidre, 4 S. Celoni Barcelona 08470",
    "addr:housenumber":"4",
    "addr:postcode":"08470",
    "addr:street":"Carrer De Sant Isidre",
    "iso:country":"ES",
    "sg:address":"Carrer de Sant Isidre, 4",
    "sg:city":"S. Celoni",
    "sg:orig_category":"Alquiler De V\u00cddeo",
    "sg:phone":"+34 902 15 83 36",
    "sg:postcode":"08470",
    "sg:province":"Barcelona",
    "wof:name":"Vcx 24h S.l.",
    "wof:placetype":"venue"
},
  "geometry": {"coordinates":[2.4871070385,41.6805610657],"type":"Point"}
}