{
  "type": "Feature",
  "properties": {
    "iso:country":"ES",
    "sg:address":"O Caneiro, 26",
    "sg:city":"Baredo",
    "sg:orig_category":"Transportes Internacionales",
    "sg:phone":"+34 986 35 63 28",
    "sg:postcode":"36309",
    "sg:province":"Pontevedra",
    "wof:name":"Perez Martinez Camilo",
    "wof:placetype":"venue"
},
  "geometry": {"coordinates":[-8.8723278046,42.1140937805],"type":"Point"}
}