{
  "type": "Feature",
  "properties": {
    "addr:full":"Calle de Marques De Canillejas, 5 Llanes Asturias 33500",
    "addr:housenumber":"5",
    "addr:postcode":"33500",
    "addr:street":"Calle De Marques De Canillejas",
    "iso:country":"ES",
    "sg:address":"Calle de Marques De Canillejas, 5",
    "sg:city":"Llanes",
    "sg:orig_category":"Peluqueros: De Se\u00d1oras",
    "sg:phone":"+34 985 40 28 01",
    "sg:postcode":"33500",
    "sg:province":"Asturias",
    "wof:name":"Javier Peluqueros Cb.",
    "wof:placetype":"venue"
},
  "geometry": {"coordinates":[-4.7549939156,43.4207191467],"type":"Point"}
}