{
  "type": "Feature",
  "properties": {
    "iso:country":"ES",
    "sg:address":"Carrer de Annibal, 2",
    "sg:city":"Palma",
    "sg:orig_category":"Peluqueros: De Se\u00d1oras",
    "sg:phone":"+34 971 73 35 63",
    "sg:postcode":"07013",
    "sg:province":"Islas Baleares",
    "wof:name":"Adrover Ferrer Francisca",
    "wof:placetype":"venue"
},
  "geometry": {"coordinates":[2.6397213936,39.5711364746],"type":"Point"}
}