{
  "type": "Feature",
  "properties": {
    "iso:country":"ES",
    "sg:address":"Pase Dr Fernandez Iparraguirre, 15",
    "sg:city":"Guadalajara",
    "sg:orig_category":"Promotores Constructores",
    "sg:phone":"+34 949 22 39 42",
    "sg:postcode":"19001",
    "sg:province":"Guadalajara",
    "sg:website":"www.seop.es",
    "wof:name":"Seop Obras Y Proyectos S.l.",
    "wof:placetype":"venue"
},
  "geometry": {"coordinates":[-3.1678640842,40.6291160583],"type":"Point"}
}