{
  "type": "Feature",
  "properties": {
    "addr:full":"Avda Merelles (de), 40 Beariz Ourense 32520",
    "addr:housenumber":"40",
    "addr:postcode":"32520",
    "addr:street":"Avda Merelles De",
    "iso:country":"ES",
    "sg:address":"Avda Merelles (de), 40",
    "sg:city":"Beariz",
    "sg:orig_category":"Carnicer\u00cdas, Carnicer\u00cdas",
    "sg:phone":"+34 988 28 40 82",
    "sg:postcode":"32520",
    "sg:province":"Ourense",
    "wof:name":"Portas Eiroa Pilar",
    "wof:placetype":"venue"
},
  "geometry": {"coordinates":[-8.2681035995,42.475692749],"type":"Point"}
}