{
  "type": "Feature",
  "properties": {
    "iso:country":"ES",
    "sg:address":"Rua Roxelio Landeiro, 39",
    "sg:city":"Calle",
    "sg:orig_category":"Asociaciones Y Clubs Deportivos",
    "sg:phone":"+34 986 67 02 67",
    "sg:postcode":"36690",
    "sg:province":"Pontevedra",
    "wof:name":"Ra\u00f1a Reguera Elisa",
    "wof:placetype":"venue"
},
  "geometry": {"coordinates":[-8.6073646545,42.3431892395],"type":"Point"}
}