{
  "type": "Feature",
  "properties": {
    "addr:full":"Avgd Marina, 17 Alcudia Islas Baleares 07400",
    "addr:housenumber":"17",
    "addr:postcode":"07400",
    "iso:country":"ES",
    "sg:address":"Avgd Marina, 17",
    "sg:city":"Alcudia",
    "sg:orig_category":"Empresas De Carpinter\u00cda De Madera",
    "sg:phone":"+34 971 54 71 67",
    "sg:postcode":"07400",
    "sg:province":"Islas Baleares",
    "wof:name":"Romero Soler Manuel",
    "wof:placetype":"venue"
},
  "geometry": {"coordinates":[3.1137330532,39.8527183533],"type":"Point"}
}