{
  "type": "Feature",
  "properties": {
    "iso:country":"ES",
    "sg:address":"Carretera Toledo Navalpino, Km. 0065,0",
    "sg:city":"Navas De Estena",
    "sg:orig_category":"Inversiones",
    "sg:phone":"+34 925 40 90 16",
    "sg:postcode":"13194",
    "sg:province":"Ciudad Real",
    "wof:name":"Percacer S.a.",
    "wof:placetype":"venue"
},
  "geometry": {"coordinates":[-4.4072389603,39.4603309631],"type":"Point"}
}