{
  "type": "Feature",
  "properties": {
    "addr:full":"Calle de Mayor, 5 Goizueta Navarra 31754",
    "addr:housenumber":"5",
    "addr:postcode":"31754",
    "addr:street":"Calle De Mayor",
    "iso:country":"ES",
    "sg:address":"Calle de Mayor, 5",
    "sg:city":"Goizueta",
    "sg:orig_category":"Estancos",
    "sg:phone":"+34 948 51 40 03",
    "sg:postcode":"31754",
    "sg:province":"Navarra",
    "wof:name":"Miranda Berroeta Unai",
    "wof:placetype":"venue"
},
  "geometry": {"coordinates":[-1.8633290529,43.1704406738],"type":"Point"}
}