{
  "type": "Feature",
  "properties": {
    "iso:country":"ES",
    "sg:address":"Calle de Frontada, 3",
    "sg:city":"Aguilar Campoo",
    "sg:orig_category":"Tapicer\u00cdas",
    "sg:phone":"+34 979 12 24 03",
    "sg:postcode":"34800",
    "sg:province":"Palencia",
    "wof:name":"Sanz Rojo Sergio",
    "wof:placetype":"venue"
},
  "geometry": {"coordinates":[-4.2557640076,42.7922210693],"type":"Point"}
}