{
  "type": "Feature",
  "properties": {
    "iso:country":"ES",
    "sg:address":"Avda Simon Otxandategi Etorbidea, 112",
    "sg:city":"Berango",
    "sg:orig_category":"Peluqueros: De Se\u00d1oras",
    "sg:phone":"+34 946 68 08 57",
    "sg:postcode":"48640",
    "sg:province":"Vizcaya",
    "wof:name":"Escudero Olabarrieta Felix",
    "wof:placetype":"venue"
},
  "geometry": {"coordinates":[-2.9976699352,43.3599281311],"type":"Point"}
}