{
  "type": "Feature",
  "properties": {
    "iso:country":"ES",
    "sg:address":"Calle de Calderon De La Barca, 4",
    "sg:city":"San Bartolome",
    "sg:orig_category":"Loter\u00cda Y T\u00d3mbola",
    "sg:phone":"+34 968 21 67 56",
    "sg:postcode":"30001",
    "sg:province":"Murcia",
    "wof:name":"Castillejos Fernandez Francisca",
    "wof:placetype":"venue"
},
  "geometry": {"coordinates":[-0.4617904127,38.4436988831],"type":"Point"}
}