{
  "type": "Feature",
  "properties": {
    "iso:country":"ES",
    "sg:address":"Calle de Juan Bravo, 53",
    "sg:city":"Madrid",
    "sg:orig_category":"Asesor\u00cda Sobre Comunicaci\u00d3n De Empresas",
    "sg:phone":"+34 914 02 52 03",
    "sg:postcode":"28006",
    "sg:province":"Madrid",
    "wof:name":"Agrupacion De Gestiones Administrativas S.l.",
    "wof:placetype":"venue"
},
  "geometry": {"coordinates":[-3.6753489971,40.4325180054],"type":"Point"}
}