{
  "type": "Feature",
  "properties": {
    "iso:country":"ES",
    "sg:address":"Calle de Inglaterra, S/n",
    "sg:city":"Palencia",
    "sg:orig_category":"Chapister\u00cda",
    "sg:phone":"+34 979 73 00 88",
    "sg:postcode":"34004",
    "sg:province":"Palencia",
    "wof:name":"Pastor Garcia Francisco Javier",
    "wof:placetype":"venue"
},
  "geometry": {"coordinates":[-4.5116238594,42.001285553],"type":"Point"}
}