{
  "type": "Feature",
  "properties": {
    "iso:country":"ES",
    "sg:address":"Carrer de Rocabuquera, 66",
    "sg:city":"Garriga",
    "sg:orig_category":"Masajistas Kinesiterapeutas",
    "sg:phone":"+34 938 71 94 03",
    "sg:postcode":"08530",
    "sg:province":"Barcelona",
    "wof:name":"Guri Bigas Maria Josep",
    "wof:placetype":"venue"
},
  "geometry": {"coordinates":[2.2827999592,41.6907081604],"type":"Point"}
}