{
  "type": "Feature",
  "properties": {
    "addr:full":"Ctra. Madrid-barcelona, S/n Medinaceli Soria 42240",
    "addr:housenumber":"s",
    "addr:postcode":"42240",
    "addr:street":"Ctra. Madrid-Barcelona;/ N",
    "iso:country":"ES",
    "sg:address":"Ctra. Madrid-barcelona, S/n",
    "sg:city":"Medinaceli",
    "sg:orig_category":"Caf\u00c9s, Bares, Cervecer\u00cdas",
    "sg:phone":"+34 975 32 64 56",
    "sg:postcode":"42240",
    "sg:province":"Soria",
    "wof:name":"Santander Lazaro Maria Bernarda",
    "wof:placetype":"venue"
},
  "geometry": {"coordinates":[-2.4357540607,41.1723670959],"type":"Point"}
}