{
  "type": "Feature",
  "properties": {
    "iso:country":"ES",
    "sg:address":"Carrer de Rocafort, 109",
    "sg:city":"Barcelona",
    "sg:orig_category":"Decoraci\u00d3n: Instalaci\u00d3n Y Talleres",
    "sg:phone":"+34 934 23 79 60",
    "sg:postcode":"08015",
    "sg:province":"Barcelona",
    "wof:name":"Lahuerta Jarque Jose",
    "wof:placetype":"venue"
},
  "geometry": {"coordinates":[2.1522829533,41.3798751831],"type":"Point"}
}