{
  "type": "Feature",
  "properties": {
    "addr:full":"Avgd Alcalde Areny, 10 Lleida Lleida 25002",
    "addr:housenumber":"10",
    "addr:postcode":"25002",
    "addr:street":"Alcalde Areny",
    "iso:country":"ES",
    "sg:address":"Avgd Alcalde Areny, 10",
    "sg:city":"Lleida",
    "sg:orig_category":"Peluquer\u00cdas, Peluquer\u00cda Mixta",
    "sg:phone":"+34 973 26 45 21",
    "sg:postcode":"25002",
    "sg:province":"Lleida",
    "wof:name":"Top Hair Systems S.l.",
    "wof:placetype":"venue"
},
  "geometry": {"coordinates":[0.6219570041,41.6102752686],"type":"Point"}
}