{
  "type": "Feature",
  "properties": {
    "addr:full":"Calle de Enrique Benito Chavarri, 10 Guadalajara Guadalajara 19001",
    "addr:housenumber":"10",
    "addr:postcode":"19001",
    "addr:street":"Calle De Enrique Benito Chavarri",
    "iso:country":"ES",
    "sg:address":"Calle de Enrique Benito Chavarri, 10",
    "sg:city":"Guadalajara",
    "sg:orig_category":"Fabricaci\u00d3n De Sobres, Bolsas Y Fundas",
    "sg:phone":"+34 949 22 96 59",
    "sg:postcode":"19001",
    "sg:province":"Guadalajara",
    "wof:name":"Numancia Regalos S.a.",
    "wof:placetype":"venue"
},
  "geometry": {"coordinates":[-3.1650650501,40.632598877],"type":"Point"}
}