{
  "type": "Feature",
  "properties": {
    "addr:full":"Carr Jaume I, 16 Santa Maria Del Cami Islas Baleares 07320",
    "addr:housenumber":"16",
    "addr:postcode":"07320",
    "addr:street":"Carr Jaume I;Islas",
    "iso:country":"ES",
    "sg:address":"Carr Jaume I, 16",
    "sg:city":"Santa Maria Del Cami",
    "sg:orig_category":"Ense\u00d1anza, Formaci\u00d3n Profesional: Aprendizaje",
    "sg:phone":"+34 971 14 11 27",
    "sg:postcode":"07320",
    "sg:province":"Islas Baleares",
    "wof:name":"Ajuntament De Santa Maria Del Cami",
    "wof:placetype":"venue"
},
  "geometry": {"coordinates":[2.7748777866,39.6486625671],"type":"Point"}
}