{
  "type": "Feature",
  "properties": {
    "iso:country":"ES",
    "sg:address":"Calle de Jesus, 2",
    "sg:city":"Macotera",
    "sg:orig_category":"Droguer\u00cdas (al Por Menor)",
    "sg:phone":"+34 923 55 53 99",
    "sg:postcode":"37310",
    "sg:province":"Salamanca",
    "wof:name":"Blazquez Madrid Juan",
    "wof:placetype":"venue"
},
  "geometry": {"coordinates":[-5.28621912,40.829460144],"type":"Point"}
}