{
  "type": "Feature",
  "properties": {
    "iso:country":"ES",
    "sg:address":"Avda Desiderio Rodriguez, 23",
    "sg:city":"Torrevieja",
    "sg:orig_category":"Centros De Coordinaci\u00d3n",
    "sg:phone":"+34 965 70 54 00",
    "sg:postcode":"03180",
    "sg:province":"Alicante",
    "wof:name":"Verifica S.l.",
    "wof:placetype":"venue"
},
  "geometry": {"coordinates":[-0.6536790133,38.0173606873],"type":"Point"}
}