{
  "type": "Feature",
  "properties": {
    "addr:full":"Calle de Segre, S/n Algeciras C\u00e1diz 11206",
    "addr:housenumber":"s / n;ca\u0301diz",
    "addr:postcode":"11206",
    "addr:street":"Calle De Segre",
    "iso:country":"ES",
    "sg:address":"Calle de Segre, S/n",
    "sg:city":"Algeciras",
    "sg:orig_category":"Centros De Educaci\u00d3n Especial",
    "sg:phone":"+34 956 60 18 69",
    "sg:postcode":"11206",
    "sg:province":"C\u00e1diz",
    "wof:name":"Junta De Andalucia",
    "wof:placetype":"venue"
},
  "geometry": {"coordinates":[-5.4507842064,36.1230239868],"type":"Point"}
}