{
  "type": "Feature",
  "properties": {
    "addr:full":"Avda Andalucia, 77 Guaro M\u00e1laga 29108",
    "addr:housenumber":"77",
    "addr:postcode":"29108",
    "addr:street":"Avda Andalucia;Ma\u0301Laga",
    "iso:country":"ES",
    "sg:address":"Avda Andalucia, 77",
    "sg:city":"Guaro",
    "sg:classifiers":[
        {
            "category":"Autos & Motor Vehicles",
            "subcategory":"Automobile Sales",
            "type":"Retail Goods"
        }
    ],
    "sg:phone":"+34 952 45 78 98",
    "sg:postcode":"29108",
    "sg:province":"M\u00e1laga",
    "wof:name":"Autoescuela Buggy S.l.",
    "wof:placetype":"venue"
},
  "geometry": {"coordinates":[-4.8362970352,36.6586799622],"type":"Point"}
}