{
  "type": "Feature",
  "properties": {
    "iso:country":"ES",
    "sg:address":"Cost Deia, D'en, 9",
    "sg:city":"Mao",
    "sg:orig_category":"Inmobiliaria (agencias)",
    "sg:phone":"+34 971 35 32 71",
    "sg:postcode":"07702",
    "sg:province":"Islas Baleares",
    "wof:name":"Actividades Menorquinas S.l.",
    "wof:placetype":"venue"
},
  "geometry": {"coordinates":[4.2637548447,39.8880233765],"type":"Point"}
}