{
  "type": "Feature",
  "properties": {
    "iso:country":"ES",
    "sg:address":"Rua Republica Arxentina (da), 20",
    "sg:city":"Santiago De Compostela",
    "sg:orig_category":"Asesor\u00cdas Y Estudios Financieros",
    "sg:phone":"+34 981 59 45 79",
    "sg:postcode":"15701",
    "sg:province":"La Coru\u00f1a",
    "wof:name":"Fit For S.l.",
    "wof:placetype":"venue"
},
  "geometry": {"coordinates":[-8.54758358,42.8730773926],"type":"Point"}
}