{
  "type": "Feature",
  "properties": {
    "iso:country":"ES",
    "sg:address":"Ctra Montcada, 740",
    "sg:city":"Terrassa",
    "sg:orig_category":"Teatros Y Salas De Espect\u00c1culos",
    "sg:phone":"+34 937 86 23 66",
    "sg:postcode":"08227",
    "sg:province":"Barcelona",
    "wof:name":"Willicha S.l.",
    "wof:placetype":"venue"
},
  "geometry": {"coordinates":[2.0384759903,41.55727005],"type":"Point"}
}