{
  "type": "Feature",
  "properties": {
    "iso:country":"ES",
    "sg:address":"Senda Granada, 35",
    "sg:city":"Espinardo",
    "sg:orig_category":"Electricidad: Instaladores",
    "sg:phone":"+34 968 30 56 03",
    "sg:postcode":"30100",
    "sg:province":"Murcia",
    "wof:name":"Instalaciones Electricas Tortosa S.l.",
    "wof:placetype":"venue"
},
  "geometry": {"coordinates":[-1.1420589685,38.0059585571],"type":"Point"}
}