{
  "type": "Feature",
  "properties": {
    "addr:full":"Ca. Ba\u00f1os De Arteixo, 4 A Coru\u00f1a La Coru\u00f1a 15008",
    "addr:housenumber":"4 a",
    "addr:postcode":"15008",
    "addr:street":"Ban\u0303Os;Arteixo;Corun\u0303A La Corun\u0303A",
    "iso:country":"ES",
    "sg:address":"Ca. Ba\u00f1os De Arteixo, 4",
    "sg:city":"A Coru\u00f1a",
    "sg:orig_category":"Fabricaci\u00d3n, Distribuci\u00d3n De Material Para La Climatizaci\u00d3n, Aireaci\u00d3n Y Ventilaci\u00d3n",
    "sg:phone":"+34 981 17 51 22",
    "sg:postcode":"15008",
    "sg:province":"La Coru\u00f1a",
    "wof:name":"Incoga S.l.",
    "wof:placetype":"venue"
},
  "geometry": {"coordinates":[-8.4512443542,43.3434753418],"type":"Point"}
}