{
  "type": "Feature",
  "properties": {
    "addr:full":"Praj Real (el), S/n Almansa Albacete 02640",
    "addr:postcode":"02640",
    "addr:street":"S / N",
    "iso:country":"ES",
    "sg:address":"Praj Real (el), S/n",
    "sg:city":"Almansa",
    "sg:orig_category":"Arenas, Guijarros Y Granulados",
    "sg:phone":"+34 967 34 13 78",
    "sg:postcode":"02640",
    "sg:province":"Albacete",
    "wof:name":"Alguero Hermanos S.a.",
    "wof:placetype":"venue"
},
  "geometry": {"coordinates":[-1.0969400406,38.8572387695],"type":"Point"}
}