{
  "type": "Feature",
  "properties": {
    "iso:country":"ES",
    "sg:address":"Calle de Pablo Pocurull, 2",
    "sg:city":"Corral-rubio",
    "sg:orig_category":"Transportes Por V\u00cdas Navegables",
    "sg:phone":"+34 967 28 64 25",
    "sg:postcode":"02693",
    "sg:province":"Albacete",
    "wof:name":"Tramerca Zornosa S.l.",
    "wof:placetype":"venue"
},
  "geometry": {"coordinates":[-1.4241425991,38.7909812927],"type":"Point"}
}