{
  "type": "Feature",
  "properties": {
    "iso:country":"ES",
    "sg:address":"Calle de Guipuzcoa, 17",
    "sg:city":"Alsasua",
    "sg:orig_category":"Arquitectos",
    "sg:phone":"+34 948 56 26 04",
    "sg:postcode":"31800",
    "sg:province":"Navarra",
    "sg:website":"www.arquitecturayurbanismo.net",
    "wof:name":"Arquitectura Y Urbanismo Alsasua S.l.",
    "wof:placetype":"venue"
},
  "geometry": {"coordinates":[-2.1732857227,42.8924789429],"type":"Point"}
}