{
  "type": "Feature",
  "properties": {
    "addr:full":"Avda General Primo De Rivera, 3 Caceres C\u00e1ceres 10001",
    "addr:housenumber":"3",
    "addr:postcode":"10001",
    "addr:street":"Avda General Primo De Rivera;Ca\u0301Ceres",
    "iso:country":"ES",
    "sg:address":"Avda General Primo De Rivera, 3",
    "sg:city":"Caceres",
    "sg:orig_category":"Aud\u00cdfonos",
    "sg:phone":"+34 927 21 43 83",
    "sg:postcode":"10001",
    "sg:province":"C\u00e1ceres",
    "wof:name":"Audifon Toledo S.a.",
    "wof:placetype":"venue"
},
  "geometry": {"coordinates":[-6.3777890205,39.4719314575],"type":"Point"}
}