{
  "type": "Feature",
  "properties": {
    "addr:full":"Calle de Concejal Garcia Feo, 19 Palmas De Gran Canaria Las Palmas 35011",
    "addr:postcode":"35011",
    "addr:street":"Calle De Concejal Garcia Feo 19",
    "iso:country":"ES",
    "sg:address":"Calle de Concejal Garcia Feo, 19",
    "sg:city":"Palmas De Gran Canaria",
    "sg:orig_category":"Ingenier\u00cda, Centros De Estudios (diversos)",
    "sg:phone":"+34 928 25 35 50",
    "sg:postcode":"35011",
    "sg:province":"Las Palmas",
    "wof:name":"Mu\u00f1oz Rodrigo Manuel",
    "wof:placetype":"venue"
},
  "geometry": {"coordinates":[-15.4394817352,28.1209754944],"type":"Point"}
}