{
  "type": "Feature",
  "properties": {
    "iso:country":"ES",
    "sg:address":"Calle de Insula, 14",
    "sg:city":"Fuente Del Rey",
    "sg:orig_category":"Agricultura: Abastecimiento Y Cosechado (negocio)",
    "sg:phone":"+34 954 93 06 21",
    "sg:postcode":"41700",
    "sg:province":"Sevilla",
    "wof:name":"Conductores Hidraulicos Del Sur",
    "wof:placetype":"venue"
},
  "geometry": {"coordinates":[-5.9756040573,37.3112182617],"type":"Point"}
}