{
  "type": "Feature",
  "properties": {
    "iso:country":"ES",
    "sg:address":"Calle de Urarka, 3",
    "sg:city":"Elorrio",
    "sg:orig_category":"Herboristas (al Por Menor)",
    "sg:phone":"+34 946 58 25 34",
    "sg:postcode":"48230",
    "sg:province":"Vizcaya",
    "wof:name":"Mairena Perez Jose Maria",
    "wof:placetype":"venue"
},
  "geometry": {"coordinates":[-2.5451350212,43.1321640015],"type":"Point"}
}