{
  "type": "Feature",
  "properties": {
    "addr:full":"Avda Dos De Mayo (del), 27 Mostoles Madrid 28934",
    "addr:housenumber":"27",
    "addr:postcode":"28934",
    "addr:street":"Avda Dos De Mayo Del",
    "iso:country":"ES",
    "sg:address":"Avda Dos De Mayo (del), 27",
    "sg:city":"Mostoles",
    "sg:orig_category":"Radiocomunicaciones, Telefon\u00cda M\u00d3vil, Radiomensajer\u00cda: Servicios, Comercializaci\u00d3n",
    "sg:phone":"+34 916 14 73 76",
    "sg:postcode":"28934",
    "sg:province":"Madrid",
    "sg:website":"www.telyco.es",
    "wof:name":"Teleinformatica Y Comunicaciones S.a.",
    "wof:placetype":"venue"
},
  "geometry": {"coordinates":[-3.8699660301,40.3201293945],"type":"Point"}
}