{
  "type": "Feature",
  "properties": {
    "addr:full":"Carrer de Hereter, 25 S. Just Desvern Barcelona 08960",
    "addr:housenumber":"25",
    "addr:postcode":"08960",
    "addr:street":"Carrer De Hereter",
    "iso:country":"ES",
    "sg:address":"Carrer de Hereter, 25",
    "sg:city":"S. Just Desvern",
    "sg:orig_category":"Sales (al Por Mayor)",
    "sg:phone":"+34 934 73 24 53",
    "sg:postcode":"08960",
    "sg:province":"Barcelona",
    "sg:website":"www.molidepomeri.com",
    "wof:name":"Moli De Pomeri S.l.",
    "wof:placetype":"venue"
},
  "geometry": {"coordinates":[2.0719189644,41.3818435669],"type":"Point"}
}