{
  "type": "Feature",
  "properties": {
    "addr:full":"Calle de Emperador, 17 Laredo Cantabria 39770",
    "addr:housenumber":"17",
    "addr:postcode":"39770",
    "addr:street":"Calle De Emperador",
    "iso:country":"ES",
    "sg:address":"Calle de Emperador, 17",
    "sg:city":"Laredo",
    "sg:orig_category":"Peluquer\u00cdas",
    "sg:phone":"+34 942 61 11 62",
    "sg:postcode":"39770",
    "sg:province":"Cantabria",
    "wof:name":"Albo Garcia Adela",
    "wof:placetype":"venue"
},
  "geometry": {"coordinates":[-3.4091501236,43.4121398926],"type":"Point"}
}