{
  "type": "Feature",
  "properties": {
    "iso:country":"ES",
    "sg:address":"Calle de Los Isunza, 4",
    "sg:city":"Vitoria-gasteiz",
    "sg:orig_category":"Inform\u00c1tica (estudios, Servicios, Asesor\u00cda, Formaci\u00d3n)",
    "sg:phone":"+34 945 12 83 33",
    "sg:postcode":"01002",
    "sg:province":"\u00c1lava",
    "sg:website":"www.edsinformatica.com",
    "wof:name":"E.d.s.informatica S.a.l.",
    "wof:placetype":"venue"
},
  "geometry": {"coordinates":[-2.6640639305,42.8552207947],"type":"Point"}
}