{
  "type": "Feature",
  "properties": {
    "iso:country":"ES",
    "sg:address":"Carrer de Calvet, 25",
    "sg:city":"Barcelona",
    "sg:orig_category":"Asesor\u00cda Sobre Comunicaci\u00d3n De Empresas",
    "sg:phone":"+34 934 14 23 20",
    "sg:postcode":"08021",
    "sg:province":"Barcelona",
    "wof:name":"Nexum Cum Laude Xxi Sl",
    "wof:placetype":"venue"
},
  "geometry": {"coordinates":[2.1435620785,41.3945045471],"type":"Point"}
}