{
  "type": "Feature",
  "properties": {
    "addr:full":"Calle de Brasil, 48 Tablero Las Palmas 35100",
    "addr:housenumber":"48",
    "addr:postcode":"35100",
    "addr:street":"Calle De Brasil",
    "iso:country":"ES",
    "sg:address":"Calle de Brasil, 48",
    "sg:city":"Tablero",
    "sg:orig_category":"Congelados: Productos Alimentarios (al Por Menor)",
    "sg:phone":"+34 928 14 20 80",
    "sg:postcode":"35100",
    "sg:province":"Las Palmas",
    "wof:name":"Verguviz S.l.",
    "wof:placetype":"venue"
},
  "geometry": {"coordinates":[-15.6058216095,27.7729797363],"type":"Point"}
}