{
  "type": "Feature",
  "properties": {
    "iso:country":"ES",
    "sg:address":"Calle de Berta Perogordo, 6",
    "sg:city":"Torrelavega",
    "sg:orig_category":"Art\u00cdculos De Decoraci\u00d3n",
    "sg:phone":"+34 942 89 15 44",
    "sg:postcode":"39300",
    "sg:province":"Cantabria",
    "wof:name":"Mi\u00f1ambres Caballero Angelica",
    "wof:placetype":"venue"
},
  "geometry": {"coordinates":[-4.0457983017,43.3492164612],"type":"Point"}
}