{
  "type": "Feature",
  "properties": {
    "iso:country":"ES",
    "sg:address":"Avda Padre Carlos Ferris, 109",
    "sg:city":"Albal",
    "sg:orig_category":"Muebles",
    "sg:phone":"+34 961 26 03 48",
    "sg:postcode":"46470",
    "sg:province":"Valencia",
    "wof:name":"Tapizados Juanes S.a.",
    "wof:placetype":"venue"
},
  "geometry": {"coordinates":[-0.4069359899,39.3944664001],"type":"Point"}
}