{
  "type": "Feature",
  "properties": {
    "addr:full":"C/ Major, 16 Salt Girona 17190",
    "addr:housenumber":"16",
    "addr:postcode":"17190",
    "addr:street":"C / Major",
    "iso:country":"ES",
    "sg:address":"C/ Major, 16",
    "sg:city":"Salt",
    "sg:orig_category":"Panader\u00cdas, Panader\u00cdas",
    "sg:phone":"+34 972 23 35 33",
    "sg:postcode":"17190",
    "sg:province":"Girona",
    "wof:name":"Montoro Due\u00f1as Carmen",
    "wof:placetype":"venue"
},
  "geometry": {"coordinates":[2.7935979366,41.9754180908],"type":"Point"}
}