{
  "type": "Feature",
  "properties": {
    "addr:full":"Calle de Jose Cadalso, 17 Torrejon Ardoz Madrid 28850",
    "addr:housenumber":"17",
    "addr:postcode":"28850",
    "addr:street":"Calle De Jose Cadalso",
    "iso:country":"ES",
    "sg:address":"Calle de Jose Cadalso, 17",
    "sg:city":"Torrejon Ardoz",
    "sg:orig_category":"Abogados",
    "sg:phone":"+34 916 75 82 60",
    "sg:postcode":"28850",
    "sg:province":"Madrid",
    "wof:name":"Contreras Rodrigez Jose",
    "wof:placetype":"venue"
},
  "geometry": {"coordinates":[-3.461468935,40.442741394],"type":"Point"}
}