{
  "type": "Feature",
  "properties": {
    "iso:country":"ES",
    "sg:address":"Avda Rosalia De Castro, 8",
    "sg:city":"Santa Uxia De Ribeira",
    "sg:orig_category":"Laboratorios Y Trabajos De Fotograf\u00cda, V\u00cddeo Y Cine",
    "sg:phone":"+34 981 87 16 90",
    "sg:postcode":"15960",
    "sg:province":"La Coru\u00f1a",
    "wof:name":"Gonzalez Llanos Maria Remedios",
    "wof:placetype":"venue"
},
  "geometry": {"coordinates":[-8.9916477203,42.5553092957],"type":"Point"}
}