{
  "type": "Feature",
  "properties": {
    "iso:country":"ES",
    "sg:address":"Rua Vista Alegre (de), 48",
    "sg:city":"Santiago De Compostela",
    "sg:orig_category":"Asociaciones Y Clubs Deportivos",
    "sg:phone":"+34 981 56 67 56",
    "sg:postcode":"15705",
    "sg:province":"A Coru\u00f1a",
    "wof:name":"Santiago De Compostela C.f.",
    "wof:placetype":"venue"
},
  "geometry": {"coordinates":[-8.546749115,42.889289856],"type":"Point"}
}