{
  "type": "Feature",
  "properties": {
    "addr:full":"Matxiategi Kalea, 1 Bergara Guip\u00f9zcoa 20570",
    "addr:housenumber":"1",
    "addr:postcode":"20570",
    "addr:street":"Matxiategi Kalea;Guipu\u0300Zcoa",
    "iso:country":"ES",
    "sg:address":"Matxiategi Kalea, 1",
    "sg:city":"Bergara",
    "sg:orig_category":"Reposter\u00cdas",
    "sg:phone":"+34 943 76 72 73",
    "sg:postcode":"20570",
    "sg:province":"Guip\u00f9zcoa",
    "wof:name":"Mizpildi Okindegia Sl",
    "wof:placetype":"venue"
},
  "geometry": {"coordinates":[-2.4183559418,43.1209602356],"type":"Point"}
}