{
  "type": "Feature",
  "properties": {
    "addr:full":"Carr Miguel Hernandez, 67 Benetusser Valencia 46910",
    "addr:housenumber":"67",
    "addr:postcode":"46910",
    "addr:street":"Carr Miguel Hernandez",
    "iso:country":"ES",
    "sg:address":"Carr Miguel Hernandez, 67",
    "sg:city":"Benetusser",
    "sg:orig_category":"Alimentaci\u00d3n General (al Por Menor)",
    "sg:phone":"+34 963 75 17 47",
    "sg:postcode":"46910",
    "sg:province":"Valencia",
    "wof:name":"Autoservicio Polo",
    "wof:placetype":"venue"
},
  "geometry": {"coordinates":[-0.400690794,39.4241981506],"type":"Point"}
}