{
  "type": "Feature",
  "properties": {
    "iso:country":"ES",
    "sg:address":"Calle de Alcaiceria, 7",
    "sg:city":"Granada",
    "sg:orig_category":"Laboratorios Y Trabajos De Fotograf\u00cda, V\u00cddeo Y Cine",
    "sg:phone":"+34 958 22 19 99",
    "sg:postcode":"18001",
    "sg:province":"Granada",
    "wof:name":"Lopez Sanchez Maria Del Carmen",
    "wof:placetype":"venue"
},
  "geometry": {"coordinates":[-3.5989840031,37.1755027771],"type":"Point"}
}