{
  "type": "Feature",
  "properties": {
    "addr:full":"Calle de Fuente, 11 Bronchales Teruel 44367",
    "addr:housenumber":"11",
    "addr:postcode":"44367",
    "addr:street":"Calle De Fuente",
    "iso:country":"ES",
    "sg:address":"Calle de Fuente, 11",
    "sg:city":"Bronchales",
    "sg:orig_category":"Venta, Instalaci\u00d3n De Cocinas",
    "sg:phone":"+34 978 70 12 56",
    "sg:postcode":"44367",
    "sg:province":"Teruel",
    "wof:name":"P. Jumar S.l.",
    "wof:placetype":"venue"
},
  "geometry": {"coordinates":[-1.5876759291,40.5087356567],"type":"Point"}
}