{
  "type": "Feature",
  "properties": {
    "addr:full":"Carrer de Santa Margarida, 2 Barcelona Barcelona 08001",
    "addr:housenumber":"2",
    "addr:postcode":"08001",
    "addr:street":"Carrer De Santa Margarida",
    "iso:country":"ES",
    "sg:address":"Carrer de Santa Margarida, 2",
    "sg:city":"Barcelona",
    "sg:orig_category":"Servicios Gsm",
    "sg:phone":"+34 933 24 86 62",
    "sg:postcode":"08001",
    "sg:province":"Barcelona",
    "wof:name":"Ali Gula Mohammad  Maisam",
    "wof:placetype":"venue"
},
  "geometry": {"coordinates":[2.1722931862,41.379234314],"type":"Point"}
}