{
  "type": "Feature",
  "properties": {
    "iso:country":"ES",
    "sg:address":"Ctra Murcia-alicante, 47",
    "sg:city":"Crevillent",
    "sg:orig_category":"Centros Empresariales",
    "sg:phone":"+34 965 40 08 39",
    "sg:postcode":"03330",
    "sg:province":"Alicante",
    "wof:name":"Comercial Bagasse Sl",
    "wof:placetype":"venue"
},
  "geometry": {"coordinates":[-0.8139619827,38.2384681702],"type":"Point"}
}