{
  "type": "Feature",
  "properties": {
    "iso:country":"ES",
    "sg:address":"Calle de Espa\u00d1a, 38",
    "sg:city":"Campaspero",
    "sg:orig_category":"Talleres: Ropa A Medida",
    "sg:phone":"+34 983 69 80 70",
    "sg:postcode":"47310",
    "sg:province":"Valladolid",
    "wof:name":"Taller De Confeccion Campaspero C.b.",
    "wof:placetype":"venue"
},
  "geometry": {"coordinates":[-4.1974291801,41.4919891357],"type":"Point"}
}