{
  "type": "Feature",
  "properties": {
    "iso:country":"ES",
    "sg:address":"Carr Sant Josep, 22",
    "sg:city":"Picanya",
    "sg:orig_category":"Producci\u00d3n De Abonos Y De Fertilizantes",
    "sg:phone":"+34 961 59 25 23",
    "sg:postcode":"46210",
    "sg:province":"Valencia",
    "wof:name":"Ciscar Garces Cipriano",
    "wof:placetype":"venue"
},
  "geometry": {"coordinates":[-0.4360359907,39.4338722229],"type":"Point"}
}