{
  "type": "Feature",
  "properties": {
    "addr:full":"Calle de Allariz, 12 Madrid Madrid 28044",
    "addr:housenumber":"12",
    "addr:postcode":"madrid;28044",
    "addr:street":"Calle De Allariz",
    "iso:country":"ES",
    "sg:address":"Calle de Allariz, 12",
    "sg:city":"Madrid",
    "sg:orig_category":"Molduras, Junquillos, Listones Y Molduras Perforadas",
    "sg:phone":"+34 915 08 03 76",
    "sg:postcode":"28044",
    "sg:province":"Madrid",
    "wof:name":"Aguero Sierra Manuel",
    "wof:placetype":"venue"
},
  "geometry": {"coordinates":[-3.7554550171,40.3673591614],"type":"Point"}
}