{
  "type": "Feature",
  "properties": {
    "addr:full":"Rond Pilar, 8 Badajoz Badajoz 06002",
    "addr:housenumber":"8",
    "addr:postcode":"06002",
    "addr:street":"Pilar",
    "iso:country":"ES",
    "sg:address":"Rond Pilar, 8",
    "sg:city":"Badajoz",
    "sg:orig_category":"Edici\u00d3n De Diarios, Revistas, Boletines",
    "sg:phone":"+34 924 25 32 15",
    "sg:postcode":"06002",
    "sg:province":"Badajoz",
    "wof:name":"Garcia Marquez Luis",
    "wof:placetype":"venue"
},
  "geometry": {"coordinates":[-6.9699621201,38.875289917],"type":"Point"}
}