{
  "type": "Feature",
  "properties": {
    "addr:full":"Algazul, 89 Punta Umbria Huelva 21100",
    "addr:housenumber":"89",
    "addr:postcode":"21100",
    "addr:street":"Algazul",
    "iso:country":"ES",
    "sg:address":"Algazul, 89",
    "sg:city":"Punta Umbria",
    "sg:orig_category":"Inmobiliaria (agencias)",
    "sg:phone":"+34 959 52 85 91",
    "sg:postcode":"21100",
    "sg:province":"Huelva",
    "wof:name":"La Reunida Arrendamientos Inmobiliarios S.l.",
    "wof:placetype":"venue"
},
  "geometry": {"coordinates":[-7.0454139709,37.2087059021],"type":"Point"}
}