{
  "type": "Feature",
  "properties": {
    "iso:country":"ES",
    "sg:address":"Calle de Trajano, 29",
    "sg:city":"Sevilla",
    "sg:orig_category":"Agencias De Viajes",
    "sg:phone":"+34 954 91 59 01",
    "sg:postcode":"41002",
    "sg:province":"Sevilla",
    "wof:name":"Sevilla Ges Service S.l.",
    "wof:placetype":"venue"
},
  "geometry": {"coordinates":[-5.9952287674,37.3952331543],"type":"Point"}
}