{
  "type": "Feature",
  "properties": {
    "iso:country":"ES",
    "sg:address":"Avda Palencia, 24",
    "sg:city":"Valladolid",
    "sg:orig_category":"Centros Empresariales",
    "sg:phone":"+34 983 25 32 72",
    "sg:postcode":"47011",
    "sg:province":"Valladolid",
    "wof:name":"Hermanos Rios C.b.",
    "wof:placetype":"venue"
},
  "geometry": {"coordinates":[-4.7170782089,41.6609191895],"type":"Point"}
}