{
  "type": "Feature",
  "properties": {
    "addr:full":"Carrer de Rossello, 195 Barcelona Barcelona 08036",
    "addr:housenumber":"195",
    "addr:postcode":"08036",
    "addr:street":"Carrer De Rossello",
    "iso:country":"ES",
    "sg:address":"Carrer de Rossello, 195",
    "sg:city":"Barcelona",
    "sg:orig_category":"Compraventa De Antig\u00dcedades",
    "sg:phone":"+34 932 18 22 10",
    "sg:postcode":"08036",
    "sg:province":"Barcelona",
    "wof:name":"Rius Garrich Claudio",
    "wof:placetype":"venue"
},
  "geometry": {"coordinates":[2.1555221081,41.392124176],"type":"Point"}
}