{
  "type": "Feature",
  "properties": {
    "addr:full":"Rbla Vallromanes (de), 49 Casc Urba Barcelona 08188",
    "addr:postcode":"08188",
    "addr:street":"Rbla",
    "iso:country":"ES",
    "sg:address":"Rbla Vallromanes (de), 49",
    "sg:city":"Casc Urba",
    "sg:orig_category":"Panader\u00cdas, Pasteler\u00cdas, Boller\u00cda Industriale (fabricaci\u00d3n, Al Por Mayor)",
    "sg:phone":"+34 935 72 98 58",
    "sg:postcode":"08188",
    "sg:province":"Barcelona",
    "wof:name":"Alcoverro Lopez Enric",
    "wof:placetype":"venue"
},
  "geometry": {"coordinates":[2.1699187756,41.3879165649],"type":"Point"}
}