{
  "type": "Feature",
  "properties": {
    "addr:full":"Barrio Arroyo, S/n Quere\u00f1o Ourense 32320",
    "addr:postcode":"32320",
    "addr:street":"Barrio Arroyo S / N",
    "iso:country":"ES",
    "sg:address":"Barrio Arroyo, S/n",
    "sg:city":"Quere\u00f1o",
    "sg:orig_category":"Material Y Herramientas Agr\u00cdcolas",
    "sg:phone":"+34 987 46 02 91",
    "sg:postcode":"32320",
    "sg:province":"Ourense",
    "wof:name":"Talleres Dupont S.l.",
    "wof:placetype":"venue"
},
  "geometry": {"coordinates":[-6.8302202225,42.4216117859],"type":"Point"}
}