{
  "type": "Feature",
  "properties": {
    "addr:full":"Carr Doctor Fleming, S/n Picassent Valencia 46220",
    "addr:housenumber":"s / n",
    "addr:postcode":"46220",
    "addr:street":"Carr Doctor Fleming",
    "iso:country":"ES",
    "sg:address":"Carr Doctor Fleming, S/n",
    "sg:city":"Picassent",
    "sg:orig_category":"Fabricaci\u00d3n, Importaci\u00d3n De L\u00c1mparas Y Bombillas",
    "sg:phone":"+34 961 24 25 19",
    "sg:postcode":"46220",
    "sg:province":"Valencia",
    "wof:name":"European Lighting Team S.l.",
    "wof:placetype":"venue"
},
  "geometry": {"coordinates":[-0.4664410055,39.3645133972],"type":"Point"}
}