{
  "type": "Feature",
  "properties": {
    "iso:country":"ES",
    "sg:address":"Calle de Alfajor, 44",
    "sg:city":"Estepa",
    "sg:orig_category":"Empresas De Carpinter\u00cda De Madera",
    "sg:phone":"+34 955 91 43 68",
    "sg:postcode":"41560",
    "sg:province":"Sevilla",
    "wof:name":"Estepe\u00f1a De Carpinteria S.l.l.",
    "wof:placetype":"venue"
},
  "geometry": {"coordinates":[-4.8774828911,37.3001441956],"type":"Point"}
}