{
  "type": "Feature",
  "properties": {
    "addr:full":"Pol Ind Plazaola Mzana C, 8 Aizoain Navarra 31195",
    "addr:postcode":"31195",
    "addr:street":"C 8",
    "iso:country":"ES",
    "sg:address":"Pol Ind Plazaola Mzana C, 8",
    "sg:city":"Aizoain",
    "sg:orig_category":"Muebles",
    "sg:phone":"+34 948 30 35 55",
    "sg:postcode":"31195",
    "sg:province":"Navarra",
    "wof:name":"Palo Rosa Mobiliario S.l.",
    "wof:placetype":"venue"
},
  "geometry": {"coordinates":[-1.6867979765,42.8470611572],"type":"Point"}
}