{
  "type": "Feature",
  "properties": {
    "addr:full":"Carr Francesc De Sales Vidal, 7 Vilanova I La Geltru Barcelona 08800",
    "addr:housenumber":"7",
    "addr:postcode":"08800",
    "addr:street":"Carr Francesc De Sales Vidal",
    "iso:country":"ES",
    "sg:address":"Carr Francesc De Sales Vidal, 7",
    "sg:city":"Vilanova I La Geltru",
    "sg:orig_category":"Fabricaci\u00d3n De Juguetes Autom\u00c1ticos",
    "sg:phone":"+34 938 93 88 88",
    "sg:postcode":"08800",
    "sg:province":"Barcelona",
    "wof:name":"Dipmatic S.a.",
    "wof:placetype":"venue"
},
  "geometry": {"coordinates":[1.7302299738,41.2257652283],"type":"Point"}
}