{
  "type": "Feature",
  "properties": {
    "addr:full":"Plaz Mayor, 2 Caceres C\u00e1ceres 10003",
    "addr:housenumber":"2",
    "addr:postcode":"10003",
    "addr:street":"Plaz Mayor;Ca\u0301Ceres",
    "iso:country":"ES",
    "sg:address":"Plaz Mayor, 2",
    "sg:city":"Caceres",
    "sg:orig_category":"Asociaciones, Organismos Culturales Y Socioeducativos",
    "sg:phone":"+34 927 21 72 37",
    "sg:postcode":"10003",
    "sg:province":"C\u00e1ceres",
    "wof:name":"Asociacion Guias Turisticos De Caceres",
    "wof:placetype":"venue"
},
  "geometry": {"coordinates":[-6.2800865173,39.5237045288],"type":"Point"}
}