{
  "type": "Feature",
  "properties": {
    "iso:country":"ES",
    "sg:address":"Carr Menorca, 1",
    "sg:city":"Grau I Platja",
    "sg:orig_category":"Doctores En Medicina",
    "sg:phone":"+34 962 84 36 48",
    "sg:postcode":"46730",
    "sg:province":"Valencia",
    "wof:name":"Soria Duran Juan Ignacio",
    "wof:placetype":"venue"
},
  "geometry": {"coordinates":[-0.1678040028,39.0074005127],"type":"Point"}
}