{
  "type": "Feature",
  "properties": {
    "iso:country":"ES",
    "sg:address":"Calle de Conde De Torrefiel, 93",
    "sg:city":"Valencia",
    "sg:orig_category":"Promotores Constructores",
    "sg:phone":"+34 963 65 15 69",
    "sg:postcode":"46019",
    "sg:province":"Valencia",
    "wof:name":"Construcciones Lara Y Barbera S. L.",
    "wof:placetype":"venue"
},
  "geometry": {"coordinates":[-0.3776501119,39.4982261658],"type":"Point"}
}