{
  "type": "Feature",
  "properties": {
    "addr:full":"C/ Sant Lloren\u00c7, 32 Alcoi Alicante 03801",
    "addr:housenumber":"32",
    "addr:postcode":"03801",
    "addr:street":"C / Sant Llorenc\u0327",
    "iso:country":"ES",
    "sg:address":"C/ Sant Lloren\u00c7, 32",
    "sg:city":"Alcoi",
    "sg:orig_category":"Caf\u00c9s, Bares, Cervecer\u00cdas",
    "sg:phone":"+34 965 54 16 28",
    "sg:postcode":"03801",
    "sg:province":"Alicante",
    "wof:name":"Blaus C.b.",
    "wof:placetype":"venue"
},
  "geometry": {"coordinates":[-0.4747779965,38.6975364685],"type":"Point"}
}