{
  "type": "Feature",
  "properties": {
    "addr:full":"Cmno Carbonell (de), S/n Camino Carbonell C\u00f3rdoba 14010",
    "addr:housenumber":"/ n",
    "addr:postcode":"14010",
    "addr:street":"Cmno Carbonell De S;Camino Carbonell Co\u0301Rdoba",
    "iso:country":"ES",
    "sg:address":"Cmno Carbonell (de), S/n",
    "sg:city":"Camino Carbonell",
    "sg:orig_category":"Empresas De Carpinter\u00cda De Madera",
    "sg:phone":"+34 957 25 85 83",
    "sg:postcode":"14010",
    "sg:province":"C\u00f3rdoba",
    "wof:name":"Ramirez Aranda Silviano",
    "wof:placetype":"venue"
},
  "geometry": {"coordinates":[-4.7535738945,37.8832893372],"type":"Point"}
}