{
  "type": "Feature",
  "properties": {
    "addr:full":"Carrer de Domenech I Montaner, 10 Cornella Llobregat Barcelona 08940",
    "addr:housenumber":"10",
    "addr:postcode":"08940",
    "addr:street":"Carrer De Domenech I Montaner",
    "iso:country":"ES",
    "sg:address":"Carrer de Domenech I Montaner, 10",
    "sg:city":"Cornella Llobregat",
    "sg:orig_category":"Quincaller\u00cda (al Por Menor)",
    "sg:phone":"+34 933 76 49 96",
    "sg:postcode":"08940",
    "sg:province":"Barcelona",
    "wof:name":"Fertrans S.l.",
    "wof:placetype":"venue"
},
  "geometry": {"coordinates":[2.0757830143,41.3650131226],"type":"Point"}
}