{
  "type": "Feature",
  "properties": {
    "iso:country":"ES",
    "sg:address":"Calle de Virgen De Las Cruces, 1",
    "sg:city":"Daimiel",
    "sg:orig_category":"Promotores Constructores",
    "sg:phone":"+34 926 85 24 81",
    "sg:postcode":"13250",
    "sg:province":"Ciudad Real",
    "wof:name":"Construcciones Y Pavimentos Garsanchez S.l.",
    "wof:placetype":"venue"
},
  "geometry": {"coordinates":[-3.6130869389,39.069606781],"type":"Point"}
}