{
  "type": "Feature",
  "properties": {
    "addr:full":"Carrer de Corsega, 382 Barcelona Barcelona 08037",
    "addr:housenumber":"382",
    "addr:postcode":"08037",
    "addr:street":"Carrer De Corsega",
    "iso:country":"ES",
    "sg:address":"Carrer de Corsega, 382",
    "sg:city":"Barcelona",
    "sg:orig_category":"Comercio, Reparaci\u00d3n De Motocicletas, Bicicletas Y Piezas Sueltas",
    "sg:phone":"+34 934 58 64 96",
    "sg:postcode":"08037",
    "sg:province":"Barcelona",
    "wof:name":"Giner Torres Jose Ramon",
    "wof:placetype":"venue"
},
  "geometry": {"coordinates":[2.163367033,41.3993911743],"type":"Point"}
}