{
  "type": "Feature",
  "properties": {
    "addr:full":"Carrer de Cardener, 11 Barcelona Barcelona 08024",
    "addr:housenumber":"11",
    "addr:postcode":"08024",
    "addr:street":"Carrer De Cardener",
    "iso:country":"ES",
    "sg:address":"Carrer de Cardener, 11",
    "sg:city":"Barcelona",
    "sg:orig_category":"Agentes, Concesionarios Y Sucursales De Veh\u00cdculos",
    "sg:phone":"+34 932 84 26 94",
    "sg:postcode":"08024",
    "sg:province":"Barcelona",
    "wof:name":"Galofre Ferrerons Arturo",
    "wof:placetype":"venue"
},
  "geometry": {"coordinates":[2.1549041271,41.408946991],"type":"Point"}
}