{
  "type": "Feature",
  "properties": {
    "iso:country":"ES",
    "sg:address":"Carrer de Sant Gabriel, 7",
    "sg:city":"Esplugues Llobregat",
    "sg:orig_category":"Artes Gr\u00c1ficas, Artes Pl\u00c1sticas (curso)",
    "sg:phone":"+34 934 80 25 42",
    "sg:postcode":"08950",
    "sg:province":"Barcelona",
    "wof:name":"Cordomina Rivals S.l.",
    "wof:placetype":"venue"
},
  "geometry": {"coordinates":[2.0832490921,41.3712921143],"type":"Point"}
}