{
  "type": "Feature",
  "properties": {
    "iso:country":"ES",
    "sg:address":"Plaza Puente-zubia, 1 A",
    "sg:city":"Getxo",
    "sg:orig_category":"Asociaciones Y Clubs Deportivos",
    "sg:phone":"+34 944 31 68 47",
    "sg:postcode":"48930",
    "sg:province":"Vizcaya",
    "wof:name":"President Centro Deportivo, S.l.",
    "wof:placetype":"venue"
},
  "geometry": {"coordinates":[-3.0068490505,43.3258285522],"type":"Point"}
}