{
  "type": "Feature",
  "properties": {
    "iso:country":"ES",
    "sg:address":"C/ Alfons I, 11",
    "sg:city":"Puigcerda",
    "sg:orig_category":"Zapatos (al Por Menor)",
    "sg:phone":"+34 972 88 09 03",
    "sg:postcode":"17520",
    "sg:province":"Girona",
    "wof:name":"Costa Palau Venancio",
    "wof:placetype":"venue"
},
  "geometry": {"coordinates":[1.9279609919,42.4318161011],"type":"Point"}
}