{
  "type": "Feature",
  "properties": {
    "iso:country":"ES",
    "sg:address":"Av Francesc Macia, 75",
    "sg:city":"Vilanova I La Geltru",
    "sg:orig_category":"Servicios Gsm",
    "sg:phone":"+34 938 15 57 79",
    "sg:postcode":"08800",
    "sg:province":"Barcelona",
    "wof:name":"Navarro Diaz Dionisio",
    "wof:placetype":"venue"
},
  "geometry": {"coordinates":[1.720870018,41.2224807739],"type":"Point"}
}