{
  "type": "Feature",
  "properties": {
    "iso:country":"ES",
    "sg:address":"Ctra Irun (de), Km. 0014,5",
    "sg:city":"Alcobendas",
    "sg:orig_category":"Fabricaci\u00d3n De Peines Y De Accesorios De Peluquer\u00cda",
    "sg:phone":"+34 916 62 00 15",
    "sg:postcode":"28108",
    "sg:province":"Madrid",
    "wof:name":"Comercial Lobel S.l.",
    "wof:placetype":"venue"
},
  "geometry": {"coordinates":[-3.6225941181,40.5358009338],"type":"Point"}
}