{
  "type": "Feature",
  "properties": {
    "iso:country":"ES",
    "sg:address":"Av Gonzalez Robles, 19",
    "sg:city":"Orgiva",
    "sg:orig_category":"M\u00c9dicos: Estomatolog\u00cda",
    "sg:phone":"+34 958 78 42 27",
    "sg:postcode":"18400",
    "sg:province":"Granada",
    "wof:name":"Morales Garcia Patricia",
    "wof:placetype":"venue"
},
  "geometry": {"coordinates":[-3.4251298904,36.9007034302],"type":"Point"}
}