{
  "type": "Feature",
  "properties": {
    "addr:full":"Loidi Kalea-calle Loidi, 13 Lasarte-oria Guip\u00f9zcoa 20160",
    "addr:housenumber":"13",
    "addr:postcode":"20160",
    "addr:street":"Loidi;Guipu\u0300Zcoa",
    "iso:country":"ES",
    "sg:address":"Loidi Kalea-calle Loidi, 13",
    "sg:city":"Lasarte-oria",
    "sg:orig_category":"Maquinaria Para Industrias Diversas",
    "sg:phone":"+34 943 37 28 82",
    "sg:postcode":"20160",
    "sg:province":"Guip\u00f9zcoa",
    "wof:name":"Acove S.l.",
    "wof:placetype":"venue"
},
  "geometry": {"coordinates":[-2.020414114,43.2698173523],"type":"Point"}
}