{
  "type": "Feature",
  "properties": {
    "addr:full":"Bichican, S/n Bichican Lugo 27816",
    "addr:postcode":"27816",
    "addr:street":"Bichican S / N",
    "iso:country":"ES",
    "sg:address":"Bichican, S/n",
    "sg:city":"Bichican",
    "sg:orig_category":"Distribuci\u00d3n De Petr\u00d3leo Y Derivados",
    "sg:phone":"+34 982 51 24 43",
    "sg:postcode":"27816",
    "sg:province":"Lugo",
    "wof:name":"Otero Goez Manuel",
    "wof:placetype":"venue"
},
  "geometry": {"coordinates":[-7.7355051041,43.3212394714],"type":"Point"}
}