{
  "type": "Feature",
  "properties": {
    "addr:full":"Carrer de Isabel Julia, 4 Sitges Barcelona 08870",
    "addr:housenumber":"4",
    "addr:postcode":"08870",
    "addr:street":"Carrer De Isabel Julia",
    "iso:country":"ES",
    "sg:address":"Carrer de Isabel Julia, 4",
    "sg:city":"Sitges",
    "sg:orig_category":"Mec\u00c1nico Del Autom\u00d3vil",
    "sg:phone":"+34 938 94 42 31",
    "sg:postcode":"08870",
    "sg:province":"Barcelona",
    "wof:name":"Mir Rocamora Gaspar",
    "wof:placetype":"venue"
},
  "geometry": {"coordinates":[1.8129060268,41.2373199463],"type":"Point"}
}