{
  "type": "Feature",
  "properties": {
    "addr:full":"Plaz Santa Maria, 7 Merida Badajoz 06800",
    "addr:housenumber":"7",
    "addr:postcode":"06800",
    "addr:street":"Santa Maria",
    "iso:country":"ES",
    "sg:address":"Plaz Santa Maria, 7",
    "sg:city":"Merida",
    "sg:orig_category":"Abogados",
    "sg:phone":"+34 924 31 36 11",
    "sg:postcode":"06800",
    "sg:province":"Badajoz",
    "wof:name":"Juzgado De Primera Instancia E Instruccion N 2",
    "wof:placetype":"venue"
},
  "geometry": {"coordinates":[-6.3475708961,38.916431427],"type":"Point"}
}