{
  "type": "Feature",
  "properties": {
    "iso:country":"ES",
    "sg:address":"Calle de Mar (del), 5",
    "sg:city":"Torre Mar",
    "sg:orig_category":"Confecci\u00d3n (fabricaci\u00d3n, Al Por Mayor)",
    "sg:phone":"+34 952 54 02 43",
    "sg:postcode":"29740",
    "sg:province":"M\u00e1laga",
    "wof:name":"Confecciones Lupia\u00f1ez C.b.",
    "wof:placetype":"venue"
},
  "geometry": {"coordinates":[-4.3588581085,36.7207450867],"type":"Point"}
}