{
  "type": "Feature",
  "properties": {
    "addr:full":"Santa Ana Kalea, 7 Elgoibar Guip\u00f9zcoa 20870",
    "addr:housenumber":"7",
    "addr:postcode":"20870",
    "addr:street":"Santa Ana Kalea;Guipu\u0300Zcoa",
    "iso:country":"ES",
    "sg:address":"Santa Ana Kalea, 7",
    "sg:city":"Elgoibar",
    "sg:orig_category":"Carnicer\u00cdas, Carnicer\u00cdas",
    "sg:phone":"+34 943 74 30 42",
    "sg:postcode":"20870",
    "sg:province":"Guip\u00f9zcoa",
    "wof:name":"Iraola Zialzeta Manuel",
    "wof:placetype":"venue"
},
  "geometry": {"coordinates":[-2.4178268909,43.213104248],"type":"Point"}
}