{
  "type": "Feature",
  "properties": {
    "addr:full":"Rua Santiago De Chile (de), 13 Santiago De Compostela La Coru\u00f1a 15706",
    "addr:housenumber":"13",
    "addr:postcode":"15706",
    "addr:street":"Rua Santiago De Chile De;Corun\u0303A",
    "iso:country":"ES",
    "sg:address":"Rua Santiago De Chile (de), 13",
    "sg:city":"Santiago De Compostela",
    "sg:orig_category":"Frutas, Legumbres Frescas Y Tempranas (al Por Menor)",
    "sg:phone":"+34 981 59 52 60",
    "sg:postcode":"15706",
    "sg:province":"La Coru\u00f1a",
    "wof:name":"Merca-lozano S.l.",
    "wof:placetype":"venue"
},
  "geometry": {"coordinates":[-8.5506315231,42.8723564148],"type":"Point"}
}