{
  "type": "Feature",
  "properties": {
    "addr:full":"Calle de Alonso Del Castillo, 1 Salamanca Salamanca 37003",
    "addr:housenumber":"1",
    "addr:postcode":"37003",
    "addr:street":"Calle De Alonso Del Castillo",
    "iso:country":"ES",
    "sg:address":"Calle de Alonso Del Castillo, 1",
    "sg:city":"Salamanca",
    "sg:orig_category":"Asesor\u00cda, Estudio Y Control Medioambiental",
    "sg:phone":"+34 923 18 19 63",
    "sg:postcode":"37003",
    "sg:province":"Salamanca",
    "wof:name":"Lineatecnia.03 S.l",
    "wof:placetype":"venue"
},
  "geometry": {"coordinates":[-5.6492810249,40.9625701904],"type":"Point"}
}