{
  "type": "Feature",
  "properties": {
    "iso:country":"ES",
    "sg:address":"Barrio Espinamonte, S/n",
    "sg:city":"Arnuero",
    "sg:orig_category":"Distribuci\u00d3n De Petr\u00d3leo Y Derivados",
    "sg:phone":"+34 942 67 71 03",
    "sg:postcode":"39194",
    "sg:province":"Cantabria",
    "wof:name":"Fernandez Ruiz Moises",
    "wof:placetype":"venue"
},
  "geometry": {"coordinates":[-3.5678329468,43.4699211121],"type":"Point"}
}