{
  "type": "Feature",
  "properties": {
    "addr:full":"Carrer de Alzines, S/n Riviera Girona 17310",
    "addr:housenumber":"s / n",
    "addr:postcode":"17310",
    "addr:street":"Carrer De Alzines",
    "iso:country":"ES",
    "sg:address":"Carrer de Alzines, S/n",
    "sg:city":"Riviera",
    "sg:orig_category":"Promotores Constructores",
    "sg:phone":"+34 972 37 41 82",
    "sg:postcode":"17310",
    "sg:province":"Girona",
    "wof:name":"Ravelena Construccions S.a.",
    "wof:placetype":"venue"
},
  "geometry": {"coordinates":[2.846834898,41.6981697083],"type":"Point"}
}