{
  "type": "Feature",
  "properties": {
    "iso:country":"ES",
    "sg:address":"Ahumategi Bide, 3",
    "sg:city":"Bergara",
    "sg:orig_category":"Electrodom\u00c9sticos (fabricaci\u00d3n, Al Por Mayor)",
    "sg:phone":"+34 943 03 73 00",
    "sg:postcode":"20570",
    "sg:province":"Guip\u00f9zcoa",
    "wof:name":"Candy Hoover Electrodomesticos S.a.",
    "wof:placetype":"venue"
},
  "geometry": {"coordinates":[-2.4209918976,43.1079826355],"type":"Point"}
}