{
  "type": "Feature",
  "properties": {
    "iso:country":"ES",
    "sg:address":"Calle de Julian Toron, 6",
    "sg:city":"S.juan",
    "sg:orig_category":"Abogados",
    "sg:phone":"+34 928 69 10 75",
    "sg:postcode":"35200",
    "sg:province":"Las Palmas",
    "wof:name":"Abogadas Telde S.c.p.",
    "wof:placetype":"venue"
},
  "geometry": {"coordinates":[-15.430006,28.124823],"type":"Point"}
}