{
  "type": "Feature",
  "properties": {
    "addr:full":"Pol Ind Las Vaderas, S/n Pilas Sevilla 41840",
    "addr:housenumber":"s / n",
    "addr:postcode":"41840",
    "iso:country":"ES",
    "sg:address":"Pol Ind Las Vaderas, S/n",
    "sg:city":"Pilas",
    "sg:orig_category":"Fabricaci\u00d3n De Muebles",
    "sg:phone":"+34 955 75 22 64",
    "sg:postcode":"41840",
    "sg:province":"Sevilla",
    "wof:name":"Tapizados Do\u00d1ana S.l.",
    "wof:placetype":"venue"
},
  "geometry": {"coordinates":[-6.3043088913,37.3053894043],"type":"Point"}
}