{
  "type": "Feature",
  "properties": {
    "addr:full":"Ptda Beneito Moros, S/n Gandia Valencia 46700",
    "addr:housenumber":"s / n",
    "addr:postcode":"46700",
    "addr:street":"Ptda Beneito Moros;Valencia",
    "iso:country":"ES",
    "sg:address":"Ptda Beneito Moros, S/n",
    "sg:city":"Gandia",
    "sg:orig_category":"Fabricaci\u00d3n, Importaci\u00d3n De L\u00c1mparas Y Bombillas",
    "sg:phone":"+34 962 96 55 35",
    "sg:postcode":"46700",
    "sg:province":"Valencia",
    "wof:name":"Lamparas Llum Cristal S.l.",
    "wof:placetype":"venue"
},
  "geometry": {"coordinates":[-0.1913339943,38.960735321],"type":"Point"}
}