{
  "type": "Feature",
  "properties": {
    "addr:full":"Ctra Granada (de), S/n Venta Del Coronel Murcia 30817",
    "addr:postcode":"30817",
    "addr:street":"Ctra Granada De S / N Venta Del Coronel",
    "iso:country":"ES",
    "sg:address":"Ctra Granada (de), S/n",
    "sg:city":"Venta Del Coronel",
    "sg:orig_category":"Mec\u00c1nico Del Autom\u00d3vil",
    "sg:phone":"+34 968 46 34 59",
    "sg:postcode":"30817",
    "sg:province":"Murcia",
    "wof:name":"Ruiz Garcia Antonio",
    "wof:placetype":"venue"
},
  "geometry": {"coordinates":[-1.7245190144,37.6462936401],"type":"Point"}
}