{
  "type": "Feature",
  "properties": {
    "iso:country":"ES",
    "sg:address":"Calle de Oca, 31",
    "sg:city":"Madrid",
    "sg:orig_category":"Bazares, Art\u00cdculos De Limpieza Y De Cocina (al Por Menor)",
    "sg:phone":"+34 914 61 49 99",
    "sg:postcode":"28025",
    "sg:province":"Madrid",
    "wof:name":"Castellano Ciprian Venancio",
    "wof:placetype":"venue"
},
  "geometry": {"coordinates":[-3.735806942,40.389541626],"type":"Point"}
}