{
  "type": "Feature",
  "properties": {
    "iso:country":"ES",
    "sg:address":"Calle de Merkezabal, 20",
    "sg:city":"Donostia-san Sebastian",
    "sg:orig_category":"Inform\u00c1tica Equipo Y Programas (al Por Mayor)",
    "sg:phone":"+34 943 31 75 41",
    "sg:postcode":"20009",
    "sg:province":"Guip\u00f9zcoa",
    "wof:name":"Grupo Cim Sofinsa S.l.",
    "wof:placetype":"venue"
},
  "geometry": {"coordinates":[-1.9862890244,43.3022384644],"type":"Point"}
}