{
  "type": "Feature",
  "properties": {
    "iso:country":"ES",
    "sg:address":"Calle de Antonio Monedero, 6",
    "sg:city":"Due\u00f1as",
    "sg:orig_category":"Peluquer\u00cdas, Peluquer\u00cda Mixta",
    "sg:phone":"+34 979 78 08 09",
    "sg:postcode":"34210",
    "sg:province":"Palencia",
    "wof:name":"Garcia Moraleja Manuel",
    "wof:placetype":"venue"
},
  "geometry": {"coordinates":[-4.5453248024,41.8759002686],"type":"Point"}
}