{
  "type": "Feature",
  "properties": {
    "iso:country":"ES",
    "sg:address":"Calle de Juan Bautista Uriarte, 6",
    "sg:city":"Kurtzea",
    "sg:orig_category":"Traductores",
    "sg:phone":"+34 944 57 03 92",
    "sg:postcode":"48960",
    "sg:province":"Vizcaya",
    "wof:name":"Traduccion E Interpretacion Loghatk S.l.",
    "wof:placetype":"venue"
},
  "geometry": {"coordinates":[-2.8473105431,43.2297897339],"type":"Point"}
}