{
  "type": "Feature",
  "properties": {
    "addr:full":"Calle de Toro, 23 Salamanca Salamanca 37002",
    "addr:housenumber":"23",
    "addr:postcode":"37002",
    "addr:street":"Calle De Toro",
    "iso:country":"ES",
    "sg:address":"Calle de Toro, 23",
    "sg:city":"Salamanca",
    "sg:orig_category":"Detectives, Agentes Investigadores Privados",
    "sg:phone":"+34 923 26 67 53",
    "sg:postcode":"37002",
    "sg:province":"Salamanca",
    "wof:name":"Vargas Kadaveira Victor",
    "wof:placetype":"venue"
},
  "geometry": {"coordinates":[-5.6629281044,40.9663848877],"type":"Point"}
}