{
  "type": "Feature",
  "properties": {
    "addr:full":"Calle de Doctor Jose Zaldua, 31 Portugalete Vizcaya 48920",
    "addr:housenumber":"31",
    "addr:postcode":"48920",
    "addr:street":"Calle De Doctor Jose Zaldua",
    "iso:country":"ES",
    "sg:address":"Calle de Doctor Jose Zaldua, 31",
    "sg:city":"Portugalete",
    "sg:orig_category":"Caf\u00c9s, Bares, Cervecer\u00cdas",
    "sg:phone":"+34 944 62 01 08",
    "sg:postcode":"48920",
    "sg:province":"Vizcaya",
    "wof:name":"Maria De Las Mercedes Fernandez Ruiz-maria Milagros Ortiz Romero",
    "wof:placetype":"venue"
},
  "geometry": {"coordinates":[-3.0315086842,43.3202095032],"type":"Point"}
}