{
  "type": "Feature",
  "properties": {
    "addr:full":"Calle de Francisco Vitoria, 5 Zaragoza Zaragoza 50008",
    "addr:housenumber":"5",
    "addr:postcode":"50008",
    "addr:street":"Calle De Francisco Vitoria",
    "iso:country":"ES",
    "sg:address":"Calle de Francisco Vitoria, 5",
    "sg:city":"Zaragoza",
    "sg:orig_category":"Institutos De Belleza",
    "sg:phone":"+34 976 22 95 73",
    "sg:postcode":"50008",
    "sg:province":"Zaragoza",
    "wof:name":"Instituto De Belleza Marina Gil De Mora",
    "wof:placetype":"venue"
},
  "geometry": {"coordinates":[-0.8820959926,41.6472053528],"type":"Point"}
}