{
  "type": "Feature",
  "properties": {
    "iso:country":"ES",
    "sg:address":"Avda Almozara, 7",
    "sg:city":"Zaragoza",
    "sg:orig_category":"Carnicer\u00cdas, Carnicer\u00cdas",
    "sg:phone":"+34 976 43 20 71",
    "sg:postcode":"50003",
    "sg:province":"Zaragoza",
    "wof:name":"Superbien Punto De Venta S.l",
    "wof:placetype":"venue"
},
  "geometry": {"coordinates":[-0.8963879943,41.6613731384],"type":"Point"}
}