{
  "type": "Feature",
  "properties": {
    "iso:country":"ES",
    "sg:address":"Calle de Llano De Olmedo, 5",
    "sg:city":"Olmedo",
    "sg:orig_category":"Escayola Y Productos De Escayola (fabricaci\u00d3n, Al Por Mayor)",
    "sg:phone":"+34 983 60 08 51",
    "sg:postcode":"47410",
    "sg:province":"Valladolid",
    "wof:name":"Gordon De Celis Jose Luis",
    "wof:placetype":"venue"
},
  "geometry": {"coordinates":[-4.681789875,41.2848434448],"type":"Point"}
}