{
  "type": "Feature",
  "properties": {
    "addr:full":"Avgd Major, 66 Massamagrell Valencia 46130",
    "addr:housenumber":"66",
    "addr:postcode":"46130",
    "iso:country":"ES",
    "sg:address":"Avgd Major, 66",
    "sg:city":"Massamagrell",
    "sg:orig_category":"Arquitectos",
    "sg:phone":"+34 961 44 01 23",
    "sg:postcode":"46130",
    "sg:province":"Valencia",
    "wof:name":"Sancho Carbonell Jose",
    "wof:placetype":"venue"
},
  "geometry": {"coordinates":[-0.330467999,39.5715904236],"type":"Point"}
}