{
  "type": "Feature",
  "properties": {
    "addr:full":"Avda Ribera De Erandio, 9 Altzaga Vizcaya 48950",
    "addr:housenumber":"9",
    "addr:postcode":"48950",
    "addr:street":"Avda Ribera De Erandio",
    "iso:country":"ES",
    "sg:address":"Avda Ribera De Erandio, 9",
    "sg:city":"Altzaga",
    "sg:orig_category":"Agencias Y Asesores De Publicidad",
    "sg:phone":"+34 944 67 50 95",
    "sg:postcode":"48950",
    "sg:province":"Vizcaya",
    "wof:name":"Krea Comunicacion S.l.u",
    "wof:placetype":"venue"
},
  "geometry": {"coordinates":[-2.9753210545,43.2986030579],"type":"Point"}
}