{
  "type": "Feature",
  "properties": {
    "iso:country":"ES",
    "sg:address":"Avda Villamayor, 78",
    "sg:city":"Salamanca",
    "sg:orig_category":"Art\u00cdculos De Regalo (al Por Menor)",
    "sg:phone":"+34 923 25 17 53",
    "sg:postcode":"37007",
    "sg:province":"Salamanca",
    "wof:name":"Ahmad El Hallaj Said",
    "wof:placetype":"venue"
},
  "geometry": {"coordinates":[-5.6713204384,40.9724464417],"type":"Point"}
}