{
  "type": "Feature",
  "properties": {
    "addr:full":"Souton, S/n Vegadeo Asturias 33770",
    "addr:housenumber":"/ n",
    "addr:postcode":"33770",
    "addr:street":"Souton S",
    "iso:country":"ES",
    "sg:address":"Souton, S/n",
    "sg:city":"Vegadeo",
    "sg:orig_category":"Asociaciones Y Clubs Deportivos",
    "sg:phone":"+34 985 63 49 20",
    "sg:postcode":"33770",
    "sg:province":"Asturias",
    "wof:name":"Sociedad Deportiva Astur Vegadense",
    "wof:placetype":"venue"
},
  "geometry": {"coordinates":[-7.0507240295,43.464225769],"type":"Point"}
}