{
  "type": "Feature",
  "properties": {
    "addr:full":"Rua Real, 135 Ferrol La Coru\u00f1a 15402",
    "addr:housenumber":"135",
    "addr:postcode":"15402",
    "addr:street":"Rua Real;La Corun\u0303A",
    "iso:country":"ES",
    "sg:address":"Rua Real, 135",
    "sg:city":"Ferrol",
    "sg:orig_category":"Electrodom\u00c9sticos (al Por Menor)",
    "sg:phone":"+34 981 35 49 72",
    "sg:postcode":"15402",
    "sg:province":"La Coru\u00f1a",
    "wof:name":"Lopez Veloso Jose Luis",
    "wof:placetype":"venue"
},
  "geometry": {"coordinates":[-8.2345991135,43.4832839966],"type":"Point"}
}