{
  "type": "Feature",
  "properties": {
    "addr:full":"C/ Juan Espuche, 37 Elche Alicante 03202",
    "addr:housenumber":"37",
    "addr:postcode":"03202",
    "addr:street":"C / Juan Espuche",
    "iso:country":"ES",
    "sg:address":"C/ Juan Espuche, 37",
    "sg:city":"Elche",
    "sg:orig_category":"Maquinaria Para Industrias Diversas",
    "sg:phone":"+34 965 45 88 13",
    "sg:postcode":"03202",
    "sg:province":"Alicante",
    "wof:name":"Vending Elche S.l.",
    "wof:placetype":"venue"
},
  "geometry": {"coordinates":[-0.6840509772,38.2710952759],"type":"Point"}
}