{
  "type": "Feature",
  "properties": {
    "addr:full":"Bayuca, S/n Baiuca La Coru\u00f1a 15124",
    "addr:housenumber":"/ n",
    "addr:postcode":"15124",
    "addr:street":"Bayuca S;Baiuca La Corun\u0303A",
    "iso:country":"ES",
    "sg:address":"Bayuca, S/n",
    "sg:city":"Baiuca",
    "sg:orig_category":"Pescader\u00cdas (al Por Mayor)",
    "sg:phone":"+34 981 74 24 54",
    "sg:postcode":"15124",
    "sg:province":"La Coru\u00f1a",
    "wof:name":"Muxia Mar S.l.",
    "wof:placetype":"venue"
},
  "geometry": {"coordinates":[-9.2170591354,43.1062011719],"type":"Point"}
}