{
  "type": "Feature",
  "properties": {
    "iso:country":"ES",
    "sg:address":"Calle de Milicias, 4",
    "sg:city":"Logro\u00f1o",
    "sg:orig_category":"Restaurantes",
    "sg:phone":"+34 941 26 07 14",
    "sg:postcode":"26003",
    "sg:province":"La Rioja",
    "wof:name":"Iturbe Jimenez Florentino",
    "wof:placetype":"venue"
},
  "geometry": {"coordinates":[-2.4393839836,42.4628295898],"type":"Point"}
}