{
  "type": "Feature",
  "properties": {
    "addr:full":"Plaz Jesus, 3 Madrid Madrid 28014",
    "addr:housenumber":"3",
    "addr:postcode":"28014",
    "addr:street":"Jesus",
    "iso:country":"ES",
    "sg:address":"Plaz Jesus, 3",
    "sg:city":"Madrid",
    "sg:orig_category":"Reposter\u00cdas",
    "sg:phone":"+34 914 29 98 54",
    "sg:postcode":"28014",
    "sg:province":"Madrid",
    "wof:name":"Paz Trabazos Nieves",
    "wof:placetype":"venue"
},
  "geometry": {"coordinates":[-3.6955039501,40.4134178162],"type":"Point"}
}