{
  "type": "Feature",
  "properties": {
    "addr:full":"Calle de Vizcaya, 34 Coru\u00d1a La Coru\u00f1a 15007",
    "addr:housenumber":"34",
    "addr:postcode":"15007",
    "addr:street":"Calle De Vizcaya;Corun\u0303A",
    "iso:country":"ES",
    "sg:address":"Calle de Vizcaya, 34",
    "sg:city":"Coru\u00d1a",
    "sg:orig_category":"Almacenes Para Venta: Muebles Y Varios",
    "sg:phone":"+34 981 23 59 66",
    "sg:postcode":"15007",
    "sg:province":"La Coru\u00f1a",
    "wof:name":"Eiroa Maceiras Fernando",
    "wof:placetype":"venue"
},
  "geometry": {"coordinates":[-8.4094362259,43.3571586609],"type":"Point"}
}