{
  "type": "Feature",
  "properties": {
    "iso:country":"ES",
    "sg:address":"Calle de Vistahermosa, 34",
    "sg:city":"Almendralejo",
    "sg:classifiers":[
        {
            "category":"Communications",
            "type":"Services"
        }
    ],
    "sg:phone":"+34 924 67 04 68",
    "sg:postcode":"06200",
    "sg:province":"Badajoz",
    "sg:tags":[
        "televisiones",
        "y",
        "radio"
    ],
    "wof:name":"Radio Almendralejo S.l.",
    "wof:placetype":"venue"
},
  "geometry": {"coordinates":[-6.4023389816,38.6811294556],"type":"Point"}
}