{
  "type": "Feature",
  "properties": {
    "addr:full":"Carrer de Pons I Enrich, 26 Manresa Barcelona 08243",
    "addr:housenumber":"26",
    "addr:postcode":"08243",
    "addr:street":"Carrer De Pons;Enrich",
    "iso:country":"ES",
    "sg:address":"Carrer de Pons I Enrich, 26",
    "sg:city":"Manresa",
    "sg:orig_category":"Productos Qu\u00cdmicos (fabricaci\u00d3n, Al Por Mayor)",
    "sg:phone":"+34 938 78 40 32",
    "sg:postcode":"08243",
    "sg:province":"Barcelona",
    "wof:name":"Picassian S.l.",
    "wof:placetype":"venue"
},
  "geometry": {"coordinates":[1.8520640135,41.7102966309],"type":"Point"}
}