{
  "type": "Feature",
  "properties": {
    "addr:full":"Carrer de Mas Llui, 14 Sant Feliu Llobregat Barcelona 08980",
    "addr:housenumber":"14",
    "addr:postcode":"08980",
    "addr:street":"Carrer De Mas Llui",
    "iso:country":"ES",
    "sg:address":"Carrer de Mas Llui, 14",
    "sg:city":"Sant Feliu Llobregat",
    "sg:orig_category":"Inform\u00c1tica (estudios, Servicios, Asesor\u00cda, Formaci\u00d3n)",
    "sg:phone":"+34 936 85 36 56",
    "sg:postcode":"08980",
    "sg:province":"Barcelona",
    "wof:name":"Manteniment I Sistemes B. I G. S.l.",
    "wof:placetype":"venue"
},
  "geometry": {"coordinates":[2.0511341095,41.3864517212],"type":"Point"}
}