{
  "type": "Feature",
  "properties": {
    "iso:country":"ES",
    "sg:address":"Carrer de Riu De La Plata, 58",
    "sg:city":"Lloret Mar",
    "sg:orig_category":"Alquiler De Veh\u00cdculos: Turismos Y Utilitarios",
    "sg:phone":"+34 972 37 04 30",
    "sg:postcode":"17310",
    "sg:province":"Girona",
    "wof:name":"Mopets To Rengt S.l.",
    "wof:placetype":"venue"
},
  "geometry": {"coordinates":[2.8331999779,41.6983184814],"type":"Point"}
}