{
  "type": "Feature",
  "properties": {
    "addr:full":"Labeaga Kalea, 42 A Urretxu Guip\u00f9zcoa 20700",
    "addr:housenumber":"42 a",
    "addr:postcode":"20700",
    "addr:street":"Labeaga Kalea;Guipu\u0300Zcoa",
    "iso:country":"ES",
    "sg:address":"Labeaga Kalea, 42 A",
    "sg:city":"Urretxu",
    "sg:orig_category":"Talleres: Ropa A Medida",
    "sg:phone":"+34 943 53 24 96",
    "sg:postcode":"20700",
    "sg:province":"Guip\u00f9zcoa",
    "wof:name":"Olatz Crespo Cortabarria",
    "wof:placetype":"venue"
},
  "geometry": {"coordinates":[-2.3134770393,43.086730957],"type":"Point"}
}