{
  "type": "Feature",
  "properties": {
    "addr:full":"Carrer de Teodor Gonzalez (de), 11 Tortosa Tarragona 43500",
    "addr:housenumber":"11",
    "addr:postcode":"43500",
    "addr:street":"Carrer De Teodor Gonzalez De",
    "iso:country":"ES",
    "sg:address":"Carrer de Teodor Gonzalez (de), 11",
    "sg:city":"Tortosa",
    "sg:orig_category":"Herboristas (al Por Menor)",
    "sg:phone":"+34 977 51 08 37",
    "sg:postcode":"43500",
    "sg:province":"Tarragona",
    "wof:name":"Escurriola Curto Juan",
    "wof:placetype":"venue"
},
  "geometry": {"coordinates":[0.5201590061,40.8101501465],"type":"Point"}
}