{
  "type": "Feature",
  "properties": {
    "iso:country":"ES",
    "sg:address":"Carrer de Bailen, 28",
    "sg:city":"Barcelona",
    "sg:orig_category":"Doctores En Medicina",
    "sg:phone":"+34 932 65 18 01",
    "sg:postcode":"08010",
    "sg:province":"Barcelona",
    "wof:name":"Marti Mercadal Jose Antonio",
    "wof:placetype":"venue"
},
  "geometry": {"coordinates":[2.1761629581,41.3929252625],"type":"Point"}
}