{
  "type": "Feature",
  "properties": {
    "addr:full":"Carrer de Joaquim Costa, 181 Terrassa Barcelona 08222",
    "addr:housenumber":"181",
    "addr:postcode":"08222",
    "addr:street":"Carrer De Joaquim Costa",
    "iso:country":"ES",
    "sg:address":"Carrer de Joaquim Costa, 181",
    "sg:city":"Terrassa",
    "sg:orig_category":"Peluquer\u00cdas, Peluquer\u00cda Mixta",
    "sg:phone":"+34 937 86 34 61",
    "sg:postcode":"08222",
    "sg:province":"Barcelona",
    "wof:name":"Rodriguez Sanchez Maria Paz",
    "wof:placetype":"venue"
},
  "geometry": {"coordinates":[2.0262820721,41.5602912903],"type":"Point"}
}