{
  "type": "Feature",
  "properties": {
    "addr:full":"Puebla De Farnals, 7 Rafelbunyol Valencia 46138",
    "addr:postcode":"46138",
    "iso:country":"ES",
    "sg:address":"Puebla De Farnals, 7",
    "sg:city":"Rafelbunyol",
    "sg:orig_category":"Electricidad: Instaladores",
    "sg:phone":"+34 961 41 20 56",
    "sg:postcode":"46138",
    "sg:province":"Valencia",
    "wof:name":"Silva Caballero Angel",
    "wof:placetype":"venue"
},
  "geometry": {"coordinates":[-0.3324440122,39.5879592896],"type":"Point"}
}