{
  "type": "Feature",
  "properties": {
    "addr:full":"Ctra Alcora, 11 Castellon De La Plana Castell\u00f3n 12006",
    "addr:housenumber":"11",
    "addr:postcode":"12006",
    "addr:street":"Ctra Alcora",
    "iso:country":"ES",
    "sg:address":"Ctra Alcora, 11",
    "sg:city":"Castellon De La Plana",
    "sg:orig_category":"Molduras, Junquillos, Listones Y Molduras Perforadas",
    "sg:phone":"+34 964 21 32 14",
    "sg:postcode":"12006",
    "sg:province":"Castell\u00f3n",
    "wof:name":"Barreda Edo Aurelio",
    "wof:placetype":"venue"
},
  "geometry": {"coordinates":[-0.0538339987,39.9860458374],"type":"Point"}
}