{
  "type": "Feature",
  "properties": {
    "iso:country":"ES",
    "sg:address":"Carrer de Enric Morera, 58",
    "sg:city":"Prat Llobregat",
    "sg:orig_category":"Molduras, Junquillos, Listones Y Molduras Perforadas",
    "sg:phone":"+34 934 78 33 95",
    "sg:postcode":"08820",
    "sg:province":"Barcelona",
    "wof:name":"Cocteleria Prat S.l.",
    "wof:placetype":"venue"
},
  "geometry": {"coordinates":[2.0980141163,41.3266143799],"type":"Point"}
}