{
  "type": "Feature",
  "properties": {
    "iso:country":"ES",
    "sg:address":"Calle de Medina De Pomar, 14",
    "sg:city":"Madrid",
    "sg:orig_category":"Molduras, Junquillos, Listones Y Molduras Perforadas",
    "sg:phone":"+34 917 47 25 09",
    "sg:postcode":"28042",
    "sg:province":"Madrid",
    "wof:name":"Gil Garrido Basilio",
    "wof:placetype":"venue"
},
  "geometry": {"coordinates":[-3.5842819214,40.4512825012],"type":"Point"}
}