{
  "type": "Feature",
  "properties": {
    "addr:full":"Calle de Gran Canaria, 12 Pto. Rosario Las Palmas 35600",
    "addr:housenumber":"12",
    "addr:postcode":"35600",
    "addr:street":"Calle De Gran Canaria;Pto. Rosario Las",
    "iso:country":"ES",
    "sg:address":"Calle de Gran Canaria, 12",
    "sg:city":"Pto. Rosario",
    "sg:orig_category":"Transportes Por V\u00cdas Navegables",
    "sg:phone":"+34 928 85 21 47",
    "sg:postcode":"35600",
    "sg:province":"Las Palmas",
    "wof:name":"Barreto Hernandez Jose",
    "wof:placetype":"venue"
},
  "geometry": {"coordinates":[-13.864364624,28.5008029938],"type":"Point"}
}