{
  "type": "Feature",
  "properties": {
    "iso:country":"ES",
    "sg:address":"Plaz Mayor, 4",
    "sg:city":"Pozuelo De Alarcon",
    "sg:orig_category":"Ense\u00d1anza: Idiomas",
    "sg:phone":"+34 913 52 32 52",
    "sg:postcode":"28223",
    "sg:province":"Madrid",
    "wof:name":"Lefevre  Gary",
    "wof:placetype":"venue"
},
  "geometry": {"coordinates":[-3.8145849705,40.4339637756],"type":"Point"}
}