{
  "type": "Feature",
  "properties": {
    "addr:full":"Calle de Sierra Nevada, 10 Arganda Madrid 28500",
    "addr:housenumber":"10",
    "addr:postcode":"28500",
    "addr:street":"Calle De Sierra Nevada",
    "iso:country":"ES",
    "sg:address":"Calle de Sierra Nevada, 10",
    "sg:city":"Arganda",
    "sg:orig_category":"Artes Gr\u00c1ficas, Artes Pl\u00c1sticas (curso)",
    "sg:phone":"+34 918 71 93 12",
    "sg:postcode":"28500",
    "sg:province":"Madrid",
    "wof:name":"Feta S.a",
    "wof:placetype":"venue"
},
  "geometry": {"coordinates":[-3.47605896,40.3062515259],"type":"Point"}
}