{
  "type": "Feature",
  "properties": {
    "addr:full":"Calle de Ador, 59 Castellar-oliveral Valencia 46026",
    "addr:housenumber":"59",
    "addr:postcode":"46026",
    "addr:street":"Calle De Ador",
    "iso:country":"ES",
    "sg:address":"Calle de Ador, 59",
    "sg:city":"Castellar-oliveral",
    "sg:orig_category":"Reposter\u00cdas",
    "sg:phone":"+34 963 96 49 49",
    "sg:postcode":"46026",
    "sg:province":"Valencia",
    "wof:name":"Vila Pons Concepcion",
    "wof:placetype":"venue"
},
  "geometry": {"coordinates":[-0.3622280061,39.4288978577],"type":"Point"}
}