{
  "type": "Feature",
  "properties": {
    "addr:full":"Avda Almeria, 5 Benidorm Alicante 03500",
    "addr:housenumber":"5",
    "addr:postcode":"03500",
    "addr:street":"Avda Almeria",
    "iso:country":"ES",
    "sg:address":"Avda Almeria, 5",
    "sg:city":"Benidorm",
    "sg:orig_category":"Discotecas Y Salas De Baile",
    "sg:phone":"+34 965 86 35 23",
    "sg:postcode":"03500",
    "sg:province":"Alicante",
    "sg:website":"www.kmdisco.com",
    "wof:name":"Pamimaru S.a.",
    "wof:placetype":"venue"
},
  "geometry": {"coordinates":[-0.1126779988,38.5373573303],"type":"Point"}
}