{
  "type": "Feature",
  "properties": {
    "addr:full":"Calle de Rio Zujar, S/n Atalayuela Madrid 28906",
    "addr:housenumber":"s",
    "addr:postcode":"28906",
    "addr:street":"Calle De Rio Zujar;/ N Atalayuela",
    "iso:country":"ES",
    "sg:address":"Calle de Rio Zujar, S/n",
    "sg:city":"Atalayuela",
    "sg:orig_category":"Distribuci\u00d3n De Petr\u00d3leo Y Derivados",
    "sg:phone":"+34 916 91 82 19",
    "sg:postcode":"28906",
    "sg:province":"Madrid",
    "wof:name":"Repsol Ypf S.a.",
    "wof:placetype":"venue"
},
  "geometry": {"coordinates":[-3.7057700157,40.42029953],"type":"Point"}
}