{
  "type": "Feature",
  "properties": {
    "iso:country":"ES",
    "sg:address":"Av Perpinya, 26",
    "sg:city":"Figueres",
    "sg:orig_category":"Comercio, Reparaci\u00d3n De Motocicletas, Bicicletas Y Piezas Sueltas",
    "sg:phone":"+34 972 67 54 73",
    "sg:postcode":"17600",
    "sg:province":"Girona",
    "wof:name":"Casado Vallejos Josep Manuel",
    "wof:placetype":"venue"
},
  "geometry": {"coordinates":[2.9572610855,42.2728233337],"type":"Point"}
}