{
  "type": "Feature",
  "properties": {
    "iso:country":"ES",
    "sg:address":"Carrer de Governador Gonzalez, 11",
    "sg:city":"Tarragona",
    "sg:orig_category":"M\u00c9dicos: Estomatolog\u00cda",
    "sg:phone":"+34 977 23 09 59",
    "sg:postcode":"43001",
    "sg:province":"Tarragona",
    "wof:name":"Fan  Ke",
    "wof:placetype":"venue"
},
  "geometry": {"coordinates":[1.2515180111,41.1152153015],"type":"Point"}
}