{
  "type": "Feature",
  "properties": {
    "addr:full":"Carrer de Doctor Murillo, 14 S. Cugat Valles Barcelona 08172",
    "addr:housenumber":"14",
    "addr:postcode":"08172",
    "addr:street":"Carrer De Doctor Murillo;S. Cugat Valles Barcelona",
    "iso:country":"ES",
    "sg:address":"Carrer de Doctor Murillo, 14",
    "sg:city":"S. Cugat Valles",
    "sg:orig_category":"Inmobiliaria (agencias)",
    "sg:phone":"+34 936 75 11 12",
    "sg:postcode":"08172",
    "sg:province":"Barcelona",
    "wof:name":"San Jose Calvo Miguel Adolfo",
    "wof:placetype":"venue"
},
  "geometry": {"coordinates":[2.0806260109,41.4681587219],"type":"Point"}
}