{
  "type": "Feature",
  "properties": {
    "addr:full":"Calle de Miranda De Ebro, 1 Vitoria-gasteiz \u00c1lava 01003",
    "addr:housenumber":"1",
    "addr:postcode":"01003",
    "addr:street":"Calle De Miranda;Ebro",
    "iso:country":"ES",
    "sg:address":"Calle de Miranda De Ebro, 1",
    "sg:city":"Vitoria-gasteiz",
    "sg:orig_category":"Molduras, Junquillos, Listones Y Molduras Perforadas",
    "sg:phone":"+34 945 28 35 60",
    "sg:postcode":"01003",
    "sg:province":"\u00c1lava",
    "wof:name":"Union 84 S. A.",
    "wof:placetype":"venue"
},
  "geometry": {"coordinates":[-2.6623589993,42.8473129272],"type":"Point"}
}