{
  "type": "Feature",
  "properties": {
    "addr:full":"Avda Doctor Gadea, 8 Alacant Alicante 03001",
    "addr:housenumber":"8",
    "addr:postcode":"03001",
    "addr:street":"Avda Doctor Gadea",
    "iso:country":"ES",
    "sg:address":"Avda Doctor Gadea, 8",
    "sg:city":"Alacant",
    "sg:orig_category":"Cajas Para Embalar",
    "sg:phone":"+34 965 92 37 75",
    "sg:postcode":"03001",
    "sg:province":"Alicante",
    "wof:name":"Caja Rural Central De Orihuela",
    "wof:placetype":"venue"
},
  "geometry": {"coordinates":[-0.4873349965,38.3420295715],"type":"Point"}
}