{
  "type": "Feature",
  "properties": {
    "addr:full":"Calle de Isaac Peral, 36 Linares Ja\u00e9n 23700",
    "addr:housenumber":"36",
    "addr:postcode":"23700",
    "addr:street":"Calle De Isaac Peral;Jae\u0301N",
    "iso:country":"ES",
    "sg:address":"Calle de Isaac Peral, 36",
    "sg:city":"Linares",
    "sg:orig_category":"Inform\u00c1tica: Material Y Suministros",
    "sg:phone":"+34 953 60 10 65",
    "sg:postcode":"23700",
    "sg:province":"Ja\u00e9n",
    "wof:name":"Jump Ordenadores S.l.",
    "wof:placetype":"venue"
},
  "geometry": {"coordinates":[-3.6323099136,38.0948371887],"type":"Point"}
}