{
  "type": "Feature",
  "properties": {
    "addr:full":"Carr S Magi, 10 Igualada Barcelona 08700",
    "addr:housenumber":"10",
    "addr:postcode":"08700",
    "addr:street":"Carr S Magi",
    "iso:country":"ES",
    "sg:address":"Carr S Magi, 10",
    "sg:city":"Igualada",
    "sg:orig_category":"Papeler\u00cdas, Librer\u00cdas",
    "sg:phone":"+34 938 04 28 58",
    "sg:postcode":"08700",
    "sg:province":"Barcelona",
    "wof:name":"Llorachd Aribau Salvador",
    "wof:placetype":"venue"
},
  "geometry": {"coordinates":[1.6165800095,41.580368042],"type":"Point"}
}