{
  "type": "Feature",
  "properties": {
    "addr:full":"Av Ramon I Cajal, S/n Tarragona Tarragona 43005",
    "addr:housenumber":"s / n",
    "addr:postcode":"43005",
    "addr:street":"Av Ramon I Cajal",
    "iso:country":"ES",
    "sg:address":"Av Ramon I Cajal, S/n",
    "sg:city":"Tarragona",
    "sg:orig_category":"Ropa Para Ni\u00d1os (al Por Menor)",
    "sg:phone":"+34 977 25 27 11",
    "sg:postcode":"43005",
    "sg:province":"Tarragona",
    "sg:website":"www.neckandneck.com",
    "wof:name":"Neck Child S.a.",
    "wof:placetype":"venue"
},
  "geometry": {"coordinates":[1.2434350252,41.116065979],"type":"Point"}
}