{
  "type": "Feature",
  "properties": {
    "iso:country":"ES",
    "sg:address":"Calle de Carretas (de Las), 2",
    "sg:city":"Colmenar Viejo",
    "sg:orig_category":"Asociaciones Y Clubs Deportivos",
    "sg:phone":"+34 918 45 46 38",
    "sg:postcode":"28770",
    "sg:province":"Madrid",
    "wof:name":"Bartolome Jusdado Jose Nicasio",
    "wof:placetype":"venue"
},
  "geometry": {"coordinates":[-3.7681810856,40.6604614258],"type":"Point"}
}