{
  "type": "Feature",
  "properties": {
    "addr:full":"Plaz Garcia Lorca, 16 Durcal Granada 18650",
    "addr:housenumber":"16",
    "addr:postcode":"18650",
    "addr:street":"Lorca",
    "iso:country":"ES",
    "sg:address":"Plaz Garcia Lorca, 16",
    "sg:city":"Durcal",
    "sg:orig_category":"Asesor\u00cda Fiscal Y Jur\u00cddica",
    "sg:phone":"+34 958 78 03 97",
    "sg:postcode":"18650",
    "sg:province":"Granada",
    "wof:name":"Fernandez Melguizo S.l.",
    "wof:placetype":"venue"
},
  "geometry": {"coordinates":[-3.5704190731,36.9924316406],"type":"Point"}
}