{
  "type": "Feature",
  "properties": {
    "addr:full":"Carrer de Banys, 106 Garriga Barcelona 08530",
    "addr:housenumber":"106",
    "addr:postcode":"08530",
    "addr:street":"Carrer De Banys",
    "iso:country":"ES",
    "sg:address":"Carrer de Banys, 106",
    "sg:city":"Garriga",
    "sg:orig_category":"Colchones (fabricaci\u00d3n, Al Por Mayor, Al Por Menor)",
    "sg:phone":"+34 938 71 74 24",
    "sg:postcode":"08530",
    "sg:province":"Barcelona",
    "wof:name":"Adidos S.l.",
    "wof:placetype":"venue"
},
  "geometry": {"coordinates":[2.2863183022,41.6803092957],"type":"Point"}
}