{
  "type": "Feature",
  "properties": {
    "addr:full":"Po. Inmaculada, 76 Estella Navarra 31200",
    "addr:housenumber":"76",
    "addr:postcode":"31200",
    "iso:country":"ES",
    "sg:address":"Po. Inmaculada, 76",
    "sg:city":"Estella",
    "sg:orig_category":"Centros Empresariales",
    "sg:phone":"+34 948 55 03 63",
    "sg:postcode":"31200",
    "sg:province":"Navarra",
    "wof:name":"Labat Garcia Javier",
    "wof:placetype":"venue"
},
  "geometry": {"coordinates":[-2.0351579189,42.6721000671],"type":"Point"}
}