{
  "type": "Feature",
  "properties": {
    "addr:full":"Avda Jesus Garcia Naveira, 27 Betanzos La Coru\u00f1a 15300",
    "addr:housenumber":"27",
    "addr:postcode":"15300",
    "addr:street":"Avda Jesus Garcia Naveira;La",
    "iso:country":"ES",
    "sg:address":"Avda Jesus Garcia Naveira, 27",
    "sg:city":"Betanzos",
    "sg:orig_category":"Congelados: Productos Alimentarios (al Por Menor)",
    "sg:phone":"+34 981 77 41 42",
    "sg:postcode":"15300",
    "sg:province":"La Coru\u00f1a",
    "wof:name":"Pindusa S.l.",
    "wof:placetype":"venue"
},
  "geometry": {"coordinates":[-8.2119092941,43.279914856],"type":"Point"}
}