{
  "type": "Feature",
  "properties": {
    "addr:full":"Calle de Pilar, 6 Matas-pinar-monte Rozas Madrid 28290",
    "addr:housenumber":"6",
    "addr:postcode":"28290",
    "addr:street":"Calle De Pilar",
    "iso:country":"ES",
    "sg:address":"Calle de Pilar, 6",
    "sg:city":"Matas-pinar-monte Rozas",
    "sg:orig_category":"Electrodom\u00c9sticos (al Por Menor)",
    "sg:phone":"+34 916 30 40 66",
    "sg:postcode":"28290",
    "sg:province":"Madrid",
    "wof:name":"Rodao Matesanz Felisa",
    "wof:placetype":"venue"
},
  "geometry": {"coordinates":[-3.8968029022,40.554019928],"type":"Point"}
}