{
  "type": "Feature",
  "properties": {
    "addr:full":"C/ Vallespirans, 21 Banyoles Girona 17820",
    "addr:housenumber":"21",
    "addr:postcode":"17820",
    "addr:street":"C / Vallespirans",
    "iso:country":"ES",
    "sg:address":"C/ Vallespirans, 21",
    "sg:city":"Banyoles",
    "sg:orig_category":"Transporte En General",
    "sg:phone":"+34 972 57 54 57",
    "sg:postcode":"17820",
    "sg:province":"Girona",
    "wof:name":"A & M Look S.l.",
    "wof:placetype":"venue"
},
  "geometry": {"coordinates":[2.7610135078,42.1179389954],"type":"Point"}
}