{
  "type": "Feature",
  "properties": {
    "iso:country":"ES",
    "sg:address":"Calle de Barriada Del Santo, 10",
    "sg:city":"Bargas",
    "sg:orig_category":"Iglesia Cat\u00d3lica",
    "sg:phone":"+34 925 35 72 19",
    "sg:postcode":"45593",
    "sg:province":"Toledo",
    "wof:name":"Parroquia De San Esteban",
    "wof:placetype":"venue"
},
  "geometry": {"coordinates":[-4.0193328857,39.942817688],"type":"Point"}
}