{
  "type": "Feature",
  "properties": {
    "addr:full":"Calle de Fray Juan Regla, 17 Zaragoza Zaragoza 50017",
    "addr:housenumber":"17",
    "addr:postcode":"50017",
    "addr:street":"Calle De Fray Juan Regla",
    "iso:country":"ES",
    "sg:address":"Calle de Fray Juan Regla, 17",
    "sg:city":"Zaragoza",
    "sg:orig_category":"Tintes (fabricaci\u00d3n, Al Por Mayor)",
    "sg:phone":"+34 976 34 63 99",
    "sg:postcode":"50017",
    "sg:province":"Zaragoza",
    "wof:name":"Roy Perez Ismael",
    "wof:placetype":"venue"
},
  "geometry": {"coordinates":[-0.9138470292,41.6504020691],"type":"Point"}
}