{
  "type": "Feature",
  "properties": {
    "addr:full":"Calle de Askatasun Bidea, 28 Bermeo Vizcaya 48370",
    "addr:housenumber":"28",
    "addr:postcode":"48370",
    "addr:street":"Calle De Askatasun Bidea",
    "iso:country":"ES",
    "sg:address":"Calle de Askatasun Bidea, 28",
    "sg:city":"Bermeo",
    "sg:orig_category":"Electricidad: Instaladores",
    "sg:phone":"+34 946 88 19 55",
    "sg:postcode":"48370",
    "sg:province":"Vizcaya",
    "wof:name":"Electricidad Anasagasti, S.l.",
    "wof:placetype":"venue"
},
  "geometry": {"coordinates":[-2.726883173,43.4175605774],"type":"Point"}
}