{
  "type": "Feature",
  "properties": {
    "addr:full":"Calle de San Francisco, 13 Villanueva Serena Badajoz 06700",
    "addr:housenumber":"13",
    "addr:postcode":"06700",
    "addr:street":"Calle De San Francisco",
    "iso:country":"ES",
    "sg:address":"Calle de San Francisco, 13",
    "sg:city":"Villanueva Serena",
    "sg:orig_category":"M\u00c9dicos: Estomatolog\u00cda",
    "sg:phone":"+34 924 84 33 52",
    "sg:postcode":"06700",
    "sg:province":"Badajoz",
    "wof:name":"Canorea Carrasco Angeles",
    "wof:placetype":"venue"
},
  "geometry": {"coordinates":[-5.7964191437,38.9737014771],"type":"Point"}
}