{
  "type": "Feature",
  "properties": {
    "addr:full":"Calle de Oletxe, 33 Galdakao Vizcaya 48960",
    "addr:housenumber":"33",
    "addr:postcode":"48960",
    "addr:street":"Calle De Oletxe",
    "iso:country":"ES",
    "sg:address":"Calle de Oletxe, 33",
    "sg:city":"Galdakao",
    "sg:orig_category":"Alimentaci\u00d3n General (al Por Menor)",
    "sg:phone":"+34 944 56 06 18",
    "sg:postcode":"48960",
    "sg:province":"Vizcaya",
    "wof:name":"Supermercado San Pedro",
    "wof:placetype":"venue"
},
  "geometry": {"coordinates":[-2.8196399212,43.2178192139],"type":"Point"}
}