{
  "type": "Feature",
  "properties": {
    "iso:country":"ES",
    "sg:address":"Carrer de Sant Joan, 43",
    "sg:city":"Esparreguera",
    "sg:orig_category":"Electricidad: Instaladores",
    "sg:phone":"+34 937 77 11 36",
    "sg:postcode":"08292",
    "sg:province":"Barcelona",
    "wof:name":"S.e.f. Esparraguera S.l.",
    "wof:placetype":"venue"
},
  "geometry": {"coordinates":[1.8710449934,41.5367546082],"type":"Point"}
}