{
  "type": "Feature",
  "properties": {
    "iso:country":"ES",
    "sg:address":"Avda Miguel De Cervantes, 54",
    "sg:city":"Tarancon",
    "sg:orig_category":"Poller\u00cda Y Caza (al Por Menor)",
    "sg:phone":"+34 969 32 07 25",
    "sg:postcode":"16400",
    "sg:province":"Cuenca",
    "wof:name":"Yunta Alonso Victor",
    "wof:placetype":"venue"
},
  "geometry": {"coordinates":[-3.007386446,40.0106315613],"type":"Point"}
}