{
  "type": "Feature",
  "properties": {
    "iso:country":"ES",
    "sg:address":"Calle de Sierra Almagrera, 7",
    "sg:city":"Parador Hortichuelas",
    "sg:orig_category":"Textil",
    "sg:phone":"+34 950 34 12 50",
    "sg:postcode":"04720",
    "sg:province":"Almer\u00eda",
    "wof:name":"Medina Almagro Jose",
    "wof:placetype":"venue"
},
  "geometry": {"coordinates":[-2.5741510391,36.8138160706],"type":"Point"}
}