{
  "type": "Feature",
  "properties": {
    "addr:full":"Ptda Balafia, 7 Gualda Lleida 25191",
    "addr:housenumber":"7",
    "addr:postcode":"25191",
    "addr:street":"Ptda Balafia",
    "iso:country":"ES",
    "sg:address":"Ptda Balafia, 7",
    "sg:city":"Gualda",
    "sg:orig_category":"Asociaciones Humanitarias, De Cooperaci\u00d3n, De Acci\u00d3n Social",
    "sg:phone":"+34 973 23 10 96",
    "sg:postcode":"25191",
    "sg:province":"Lleida",
    "wof:name":"Reto A La Esperanza Asociacion",
    "wof:placetype":"venue"
},
  "geometry": {"coordinates":[0.6831650138,41.5832138062],"type":"Point"}
}