{
  "type": "Feature",
  "properties": {
    "iso:country":"ES",
    "sg:address":"Calle de Colador, 4",
    "sg:city":"Colador",
    "sg:orig_category":"Negocio De Enlosados, Soler\u00cdas",
    "sg:phone":"+34 964 77 12 88",
    "sg:postcode":"12200",
    "sg:province":"Castell\u00f3n",
    "wof:name":"Ceramicas Delarodia S.l.",
    "wof:placetype":"venue"
},
  "geometry": {"coordinates":[-0.2620640099,39.9651794434],"type":"Point"}
}