{
  "type": "Feature",
  "properties": {
    "addr:full":"Carrer de Colom, 50 Sabadell Barcelona 08201",
    "addr:housenumber":"50",
    "addr:postcode":"08201",
    "addr:street":"Carrer De Colom",
    "iso:country":"ES",
    "sg:address":"Carrer de Colom, 50",
    "sg:city":"Sabadell",
    "sg:orig_category":"Pod\u00d3logos: Pedicuros",
    "sg:phone":"+34 937 26 76 79",
    "sg:postcode":"08201",
    "sg:province":"Barcelona",
    "wof:name":"Bellver Paloma Roser",
    "wof:placetype":"venue"
},
  "geometry": {"coordinates":[2.1031908989,41.546245575],"type":"Point"}
}