{
  "type": "Feature",
  "properties": {
    "iso:country":"ES",
    "sg:address":"Avda Andalucia (de), 20",
    "sg:city":"Alcala Real",
    "sg:orig_category":"\u00d3ptica: Instrumentos (fabricaci\u00d3n)",
    "sg:phone":"+34 953 58 28 77",
    "sg:postcode":"23680",
    "sg:province":"Ja\u00e9n",
    "wof:name":"Navas Jurado S.l.",
    "wof:placetype":"venue"
},
  "geometry": {"coordinates":[-3.9227650166,37.4607429504],"type":"Point"}
}