{
  "type": "Feature",
  "properties": {
    "iso:country":"ES",
    "sg:address":"Nafarroa Etorbidea, S/n",
    "sg:city":"Arrasate",
    "sg:orig_category":"Fibras De Vidrio",
    "sg:phone":"+34 943 79 84 77",
    "sg:postcode":"20500",
    "sg:province":"Guip\u00f9zcoa",
    "wof:name":"Abeki Composites S.l.",
    "wof:placetype":"venue"
},
  "geometry": {"coordinates":[-2.477137,43.065445],"type":"Point"}
}