{
  "type": "Feature",
  "properties": {
    "iso:country":"ES",
    "sg:address":"Rua Real, 50",
    "sg:city":"Ferrol",
    "sg:orig_category":"Abogados",
    "sg:phone":"+34 981 35 93 72",
    "sg:postcode":"15402",
    "sg:province":"La Coru\u00f1a",
    "wof:name":"Deus Pallares Miguel",
    "wof:placetype":"venue"
},
  "geometry": {"coordinates":[-8.2309427261,43.4849662781],"type":"Point"}
}