{
  "type": "Feature",
  "properties": {
    "addr:full":"Calle de Diaz Emparanza Doctor, 1 Bilbao Vizcaya 48002",
    "addr:housenumber":"1",
    "addr:postcode":"48002",
    "addr:street":"Calle De Diaz;Doctor",
    "iso:country":"ES",
    "sg:address":"Calle de Diaz Emparanza Doctor, 1",
    "sg:city":"Bilbao",
    "sg:orig_category":"Agencias Y Agentes Comerciales, Representantes",
    "sg:phone":"+34 944 10 21 33",
    "sg:postcode":"48002",
    "sg:province":"Vizcaya",
    "wof:name":"Jose Martinez Capilla",
    "wof:placetype":"venue"
},
  "geometry": {"coordinates":[-2.9525632858,43.2480049133],"type":"Point"}
}