{
  "type": "Feature",
  "properties": {
    "addr:full":"Calle de Do\u00d1ana (de), 32 Humanes De Madrid Madrid 28970",
    "addr:housenumber":"32",
    "addr:postcode":"28970",
    "addr:street":"Calle De Don\u0303Ana De",
    "iso:country":"ES",
    "sg:address":"Calle de Do\u00d1ana (de), 32",
    "sg:city":"Humanes De Madrid",
    "sg:orig_category":"Extinci\u00d3n De Incendios: Material Y Suministros (fabricaci\u00d3n, Al Por Mayor)",
    "sg:phone":"+34 917 36 50 74",
    "sg:postcode":"28970",
    "sg:province":"Madrid",
    "wof:name":"Todoextintor S.l.",
    "wof:placetype":"venue"
},
  "geometry": {"coordinates":[-3.8184869289,40.2697677612],"type":"Point"}
}