{
  "type": "Feature",
  "properties": {
    "addr:full":"Cust Sal, 5 Toledo Toledo 45001",
    "addr:housenumber":"5",
    "addr:postcode":"45001",
    "iso:country":"ES",
    "sg:address":"Cust Sal, 5",
    "sg:city":"Toledo",
    "sg:orig_category":"Molduras, Junquillos, Listones Y Molduras Perforadas",
    "sg:phone":"+34 925 22 00 21",
    "sg:postcode":"45001",
    "sg:province":"Toledo",
    "wof:name":"Gomez Lancha Eladio",
    "wof:placetype":"venue"
},
  "geometry": {"coordinates":[-4.025138855,39.8618774414],"type":"Point"}
}