{
  "type": "Feature",
  "properties": {
    "addr:full":"Calle de Francisco Salinas, S/n Burgos Burgos 09003",
    "addr:housenumber":"s / n",
    "addr:postcode":"09003",
    "addr:street":"Calle De Francisco Salinas",
    "iso:country":"ES",
    "sg:address":"Calle de Francisco Salinas, S/n",
    "sg:city":"Burgos",
    "sg:orig_category":"Restaurantes",
    "sg:phone":"+34 947 25 02 58",
    "sg:postcode":"09003",
    "sg:province":"Burgos",
    "wof:name":"Aramark S.l.",
    "wof:placetype":"venue"
},
  "geometry": {"coordinates":[-3.7124016285,42.3470993042],"type":"Point"}
}