{
  "type": "Feature",
  "properties": {
    "addr:full":"Calle de Garcia Morato, 29 Valladolid Valladolid 47007",
    "addr:housenumber":"29",
    "addr:postcode":"47007",
    "addr:street":"Calle De Garcia Morato",
    "iso:country":"ES",
    "sg:address":"Calle de Garcia Morato, 29",
    "sg:city":"Valladolid",
    "sg:orig_category":"Sociedades, Compa\u00d1\u00cdas Aseguradoras",
    "sg:phone":"+34 983 47 60 66",
    "sg:postcode":"47007",
    "sg:province":"Valladolid",
    "sg:website":"www.fiatc.es",
    "wof:name":"Fiatc Mutua De Seguros Generales",
    "wof:placetype":"venue"
},
  "geometry": {"coordinates":[-4.734172821,41.6435623169],"type":"Point"}
}