{
  "type": "Feature",
  "properties": {
    "addr:full":"Calle de Constitucion, 3 Altea Alicante 03590",
    "addr:housenumber":"3",
    "addr:postcode":"03590",
    "addr:street":"Calle De Constitucion",
    "iso:country":"ES",
    "sg:address":"Calle de Constitucion, 3",
    "sg:city":"Altea",
    "sg:orig_category":"Molduras, Junquillos, Listones Y Molduras Perforadas",
    "sg:phone":"+34 966 88 06 76",
    "sg:postcode":"03590",
    "sg:province":"Alicante",
    "wof:name":"Sistelcom-telemensaje S.a.",
    "wof:placetype":"venue"
},
  "geometry": {"coordinates":[-0.047584001,38.6018333435],"type":"Point"}
}