{
  "type": "Feature",
  "properties": {
    "addr:full":"Pla\u00c7 Major, 9 Mollerussa Lleida 25230",
    "addr:housenumber":"9",
    "addr:postcode":"25230",
    "iso:country":"ES",
    "sg:address":"Pla\u00c7 Major, 9",
    "sg:city":"Mollerussa",
    "sg:orig_category":"Trajes Y Adornos De Boda (confecci\u00d3n, Al Por Menor)",
    "sg:phone":"+34 973 71 23 45",
    "sg:postcode":"25230",
    "sg:province":"Lleida",
    "wof:name":"Lluna De Drap S.l",
    "wof:placetype":"venue"
},
  "geometry": {"coordinates":[0.8913522959,41.6226844788],"type":"Point"}
}