{
  "type": "Feature",
  "properties": {
    "addr:full":"Calle de Barquillo, 15 Madrid Madrid 28004",
    "addr:housenumber":"15",
    "addr:postcode":"madrid;28004",
    "addr:street":"Calle De Barquillo",
    "iso:country":"ES",
    "sg:address":"Calle de Barquillo, 15",
    "sg:city":"Madrid",
    "sg:orig_category":"Importaci\u00d3n",
    "sg:phone":"+34 915 23 19 52",
    "sg:postcode":"28004",
    "sg:province":"Madrid",
    "sg:website":"www.venturaenter.com",
    "wof:name":"Ventura Enterprises S.l.",
    "wof:placetype":"venue"
},
  "geometry": {"coordinates":[-3.695841074,40.4215316772],"type":"Point"}
}