{
  "type": "Feature",
  "properties": {
    "addr:full":"Avda Condes De Soto Ameno, 26 Alacant Alicante 03005",
    "addr:housenumber":"26",
    "addr:postcode":"03005",
    "addr:street":"Avda Condes;Ameno",
    "iso:country":"ES",
    "sg:address":"Avda Condes De Soto Ameno, 26",
    "sg:city":"Alacant",
    "sg:orig_category":"C\u00c1maras De Comercio E Industria, Oficios, Agricultura",
    "sg:phone":"+34 965 13 33 30",
    "sg:postcode":"03005",
    "sg:province":"Alicante",
    "wof:name":"Aracil Crua\u00f1es Jose Juan",
    "wof:placetype":"venue"
},
  "geometry": {"coordinates":[-0.4954676032,38.3493804932],"type":"Point"}
}