{
  "type": "Feature",
  "properties": {
    "addr:full":"Carrer de Doctor Ferran, 6 Cornella Llobregat Barcelona 08940",
    "addr:housenumber":"6",
    "addr:postcode":"08940",
    "addr:street":"Carrer De Doctor Ferran",
    "iso:country":"ES",
    "sg:address":"Carrer de Doctor Ferran, 6",
    "sg:city":"Cornella Llobregat",
    "sg:orig_category":"Sociedades, Compa\u00d1\u00cdas Aseguradoras",
    "sg:phone":"+34 934 71 13 36",
    "sg:postcode":"08940",
    "sg:province":"Barcelona",
    "wof:name":"Ferrer Marcos Carmen",
    "wof:placetype":"venue"
},
  "geometry": {"coordinates":[2.0739700794,41.3619041443],"type":"Point"}
}