{
  "type": "Feature",
  "properties": {
    "addr:full":"Carr D'alcal, 1 Benicarlo Castell\u00f3n 12580",
    "addr:housenumber":"1",
    "addr:postcode":"12580",
    "addr:street":"Carr D'Alcal",
    "iso:country":"ES",
    "sg:address":"Carr D'alcal, 1",
    "sg:city":"Benicarlo",
    "sg:orig_category":"Muebles Y Accesorios Para Cocinas Y Cuartos De Ba\u00d1o (al Por Menor)",
    "sg:phone":"+34 964 47 48 93",
    "sg:postcode":"12580",
    "sg:province":"Castell\u00f3n",
    "wof:name":"Pitarch Llorach Jaime",
    "wof:placetype":"venue"
},
  "geometry": {"coordinates":[0.4042100012,40.4457893372],"type":"Point"}
}