{
  "type": "Feature",
  "properties": {
    "addr:full":"Calle-c P I Valdeferrin, 59 Ejea Caballeros Zaragoza 50600",
    "addr:housenumber":"59",
    "addr:postcode":"50600",
    "addr:street":"Calle-C;Valdeferrin",
    "iso:country":"ES",
    "sg:address":"Calle-c P I Valdeferrin, 59",
    "sg:city":"Ejea Caballeros",
    "sg:orig_category":"Construcciones Met\u00c1licas",
    "sg:phone":"+34 976 66 08 31",
    "sg:postcode":"50600",
    "sg:province":"Zaragoza",
    "wof:name":"Talleres Ramon S.c.",
    "wof:placetype":"venue"
},
  "geometry": {"coordinates":[-1.1382750273,42.1269798279],"type":"Point"}
}