{
  "type": "Feature",
  "properties": {
    "iso:country":"ES",
    "sg:address":"Descalzos, 63",
    "sg:city":"Iru\u00f1a",
    "sg:orig_category":"Asociaciones, Organismos Culturales Y Socioeducativos",
    "sg:phone":"+34 948 22 79 12",
    "sg:postcode":"31001",
    "sg:province":"Navarra",
    "wof:name":"Biltoki",
    "wof:placetype":"venue"
},
  "geometry": {"coordinates":[-1.6482930183,42.8187408447],"type":"Point"}
}