{
  "type": "Feature",
  "properties": {
    "addr:full":"Rua Garcia Abad, 49 Lugo Lugo 27004",
    "addr:housenumber":"49",
    "addr:postcode":"27004",
    "addr:street":"Rua Garcia Abad",
    "iso:country":"ES",
    "sg:address":"Rua Garcia Abad, 49",
    "sg:city":"Lugo",
    "sg:orig_category":"Centros De Adelgazamiento Y De Est\u00c9tica",
    "sg:phone":"+34 982 22 48 00",
    "sg:postcode":"27004",
    "sg:province":"Lugo",
    "wof:name":"Teldelugo Comunicacion S.l.",
    "wof:placetype":"venue"
},
  "geometry": {"coordinates":[-7.5616288185,43.0157318115],"type":"Point"}
}