{
  "type": "Feature",
  "properties": {
    "addr:full":"Rua Servando Ramilo, 1 Porri\u00f1o Pontevedra 36400",
    "addr:housenumber":"1",
    "addr:postcode":"36400",
    "addr:street":"Rua Servando Ramilo",
    "iso:country":"ES",
    "sg:address":"Rua Servando Ramilo, 1",
    "sg:city":"Porri\u00f1o",
    "sg:orig_category":"Farmacias",
    "sg:phone":"+34 986 33 13 73",
    "sg:postcode":"36400",
    "sg:province":"Pontevedra",
    "wof:name":"Peralba Cabaleiro Carmen",
    "wof:placetype":"venue"
},
  "geometry": {"coordinates":[-8.6209611893,42.1621055603],"type":"Point"}
}