{
  "type": "Feature",
  "properties": {
    "iso:country":"ES",
    "sg:address":"Calle de Rioja, 136",
    "sg:city":"Leganes",
    "sg:orig_category":"Arreglo, Reparaci\u00d3n, Piezas Sueltas De Televisi\u00d3n, V\u00cddeo, Hi",
    "sg:phone":"+34 916 86 43 20",
    "sg:postcode":"28915",
    "sg:province":"Madrid",
    "wof:name":"Fernandez Caballero Martin De Ruedas Roman",
    "wof:placetype":"venue"
},
  "geometry": {"coordinates":[-3.7484440804,40.334438324],"type":"Point"}
}