{
  "type": "Feature",
  "properties": {
    "addr:full":"Calle de San Juan, 4 Badajoz Badajoz 06002",
    "addr:housenumber":"4",
    "addr:postcode":"06002",
    "addr:street":"Calle De San Juan",
    "iso:country":"ES",
    "sg:address":"Calle de San Juan, 4",
    "sg:city":"Badajoz",
    "sg:orig_category":"Ropa Y Accesorios",
    "sg:phone":"+34 924 22 02 47",
    "sg:postcode":"06002",
    "sg:province":"Badajoz",
    "wof:name":"Montana",
    "wof:placetype":"venue"
},
  "geometry": {"coordinates":[-6.9698610306,38.8788108826],"type":"Point"}
}