{
  "type": "Feature",
  "properties": {
    "addr:full":"Calle de Calvario, 17 Petres Valencia 46500",
    "addr:housenumber":"17",
    "addr:postcode":"46500",
    "addr:street":"Calle De Calvario",
    "iso:country":"ES",
    "sg:address":"Calle de Calvario, 17",
    "sg:city":"Petres",
    "sg:orig_category":"Farmacias",
    "sg:phone":"+34 962 62 03 91",
    "sg:postcode":"46500",
    "sg:province":"Valencia",
    "wof:name":"Pe\u00f1a Mancho Eva Josefina",
    "wof:placetype":"venue"
},
  "geometry": {"coordinates":[-0.2732940018,39.6769218445],"type":"Point"}
}