{
  "type": "Feature",
  "properties": {
    "addr:full":"Calle de Andres Vicente, 4 Zaragoza Zaragoza 50017",
    "addr:housenumber":"4",
    "addr:postcode":"50017",
    "addr:street":"Calle De Andres Vicente",
    "iso:country":"ES",
    "sg:address":"Calle de Andres Vicente, 4",
    "sg:city":"Zaragoza",
    "sg:orig_category":"Fabricaci\u00d3n De Cortinas Y Visillos",
    "sg:phone":"+34 976 31 02 36",
    "sg:postcode":"50017",
    "sg:province":"Zaragoza",
    "wof:name":"Sarasa Piedrafita Maria Jose",
    "wof:placetype":"venue"
},
  "geometry": {"coordinates":[-0.9146230221,41.6506004333],"type":"Point"}
}