{
  "type": "Feature",
  "properties": {
    "iso:country":"ES",
    "sg:address":"Av Lluc, 130",
    "sg:city":"Inca",
    "sg:orig_category":"Inmobiliaria (agencias)",
    "sg:phone":"+34 971 50 60 84",
    "sg:postcode":"07300",
    "sg:province":"Islas Baleares",
    "wof:name":"Incahabitat S.l.",
    "wof:placetype":"venue"
},
  "geometry": {"coordinates":[2.9118299484,39.7250518799],"type":"Point"}
}