{
  "type": "Feature",
  "properties": {
    "iso:country":"ES",
    "sg:address":"Carrer de Llull, 145",
    "sg:city":"Barcelona",
    "sg:orig_category":"Farmacias (repartici\u00d3n Y Al Por Mayor)",
    "sg:phone":"+34 934 86 30 40",
    "sg:postcode":"08005",
    "sg:province":"Barcelona",
    "wof:name":"Prophyl Center S.a.",
    "wof:placetype":"venue"
},
  "geometry": {"coordinates":[2.1995379925,41.3992118835],"type":"Point"}
}