{
  "type": "Feature",
  "properties": {
    "addr:full":"Calle de Secretario Francisco Martinez Rodriguez, 4 Alcantarilla Murcia 30820",
    "addr:housenumber":"4",
    "addr:postcode":"30820",
    "addr:street":"Calle De Secretario Francisco Martinez Rodriguez",
    "iso:country":"ES",
    "sg:address":"Calle de Secretario Francisco Martinez Rodriguez, 4",
    "sg:city":"Alcantarilla",
    "sg:orig_category":"Institutos De Belleza",
    "sg:phone":"+34 968 89 13 42",
    "sg:postcode":"30820",
    "sg:province":"Murcia",
    "wof:name":"Sandoval Marin Juana",
    "wof:placetype":"venue"
},
  "geometry": {"coordinates":[-1.2211370468,37.963596344],"type":"Point"}
}