{
  "type": "Feature",
  "properties": {
    "addr:full":"Calle de Arechavaleta, 36 Madrid Madrid 28041",
    "addr:housenumber":"36",
    "addr:postcode":"madrid;28041",
    "addr:street":"Calle De Arechavaleta",
    "iso:country":"ES",
    "sg:address":"Calle de Arechavaleta, 36",
    "sg:city":"Madrid",
    "sg:orig_category":"Poller\u00cda Y Caza (al Por Menor)",
    "sg:phone":"+34 917 98 31 96",
    "sg:postcode":"28041",
    "sg:province":"Madrid",
    "wof:name":"Rojas Cristina Maria Piedad",
    "wof:placetype":"venue"
},
  "geometry": {"coordinates":[-3.6968507767,40.3525238037],"type":"Point"}
}