{
  "type": "Feature",
  "properties": {
    "addr:full":"Nocelo, 5 Ourense Ourense 32001",
    "addr:housenumber":"5",
    "addr:postcode":"32001",
    "addr:street":"Nocelo",
    "iso:country":"ES",
    "sg:address":"Nocelo, 5",
    "sg:city":"Ourense",
    "sg:orig_category":"Empresas De Carpinter\u00cda Met\u00c1lica",
    "sg:phone":"+34 988 21 77 26",
    "sg:postcode":"32001",
    "sg:province":"Ourense",
    "wof:name":"Quintillan Gonzalez Juan Carlos",
    "wof:placetype":"venue"
},
  "geometry": {"coordinates":[-7.8639168739,42.360332489],"type":"Point"}
}