{
  "type": "Feature",
  "properties": {
    "iso:country":"ES",
    "sg:address":"Carr Patricio Redondo, S/n",
    "sg:city":"Puigverd Lleida",
    "sg:orig_category":"Arboricultura Y Producci\u00d3n De Frutas",
    "sg:phone":"+34 973 16 77 14",
    "sg:postcode":"25153",
    "sg:province":"Lleida",
    "wof:name":"Fruits Queralt S.l.",
    "wof:placetype":"venue"
},
  "geometry": {"coordinates":[0.7358800173,41.5425415039],"type":"Point"}
}