{
  "type": "Feature",
  "properties": {
    "iso:country":"ES",
    "sg:address":"Avda. Margaritas, S/n",
    "sg:city":"Mijas Costa",
    "sg:orig_category":"Cristaler\u00cdas",
    "sg:phone":"+34 952 47 29 01",
    "sg:postcode":"29649",
    "sg:province":"M\u00e1laga",
    "wof:name":"Cortes Jaime Diego Jesus",
    "wof:placetype":"venue"
},
  "geometry": {"coordinates":[-4.713206768,36.491027832],"type":"Point"}
}