{
  "type": "Feature",
  "properties": {
    "addr:full":"Carr Ramon I Cajal, 29 Bellpuig Lleida 25250",
    "addr:housenumber":"29",
    "addr:postcode":"25250",
    "addr:street":"Carr Ramon I Cajal",
    "iso:country":"ES",
    "sg:address":"Carr Ramon I Cajal, 29",
    "sg:city":"Bellpuig",
    "sg:orig_category":"Negocio De Materiales De Construcci\u00d3n",
    "sg:phone":"+34 973 32 00 86",
    "sg:postcode":"25250",
    "sg:province":"Lleida",
    "wof:name":"Torrelles Pinent Jose",
    "wof:placetype":"venue"
},
  "geometry": {"coordinates":[1.0105400085,41.6245307922],"type":"Point"}
}