{
  "type": "Feature",
  "properties": {
    "addr:full":"La Acacia, 23 Carde\u00f1ajimeno Burgos 09193",
    "addr:housenumber":"23",
    "addr:postcode":"09193",
    "addr:street":"Acacia",
    "iso:country":"ES",
    "sg:address":"La Acacia, 23",
    "sg:city":"Carde\u00f1ajimeno",
    "sg:orig_category":"Empresas De Limpieza",
    "sg:phone":"+34 947 48 01 85",
    "sg:postcode":"09193",
    "sg:province":"Burgos",
    "wof:name":"Limpiezas Angel Y Marcos S.l.",
    "wof:placetype":"venue"
},
  "geometry": {"coordinates":[-3.6218464375,42.3310203552],"type":"Point"}
}