{
  "type": "Feature",
  "properties": {
    "iso:country":"ES",
    "sg:address":"Carr Santa Eugenia, 11",
    "sg:city":"Girona",
    "sg:orig_category":"Agencias De Viajes",
    "sg:phone":"+34 972 22 46 20",
    "sg:postcode":"17005",
    "sg:province":"Girona",
    "sg:website":"www.grupoeuropa.com",
    "wof:name":"Viatges Girones S.l.",
    "wof:placetype":"venue"
},
  "geometry": {"coordinates":[2.8156030178,41.980884552],"type":"Point"}
}