{
  "type": "Feature",
  "properties": {
    "iso:country":"ES",
    "sg:address":"Avda Sousas (de), 39",
    "sg:city":"Verin",
    "sg:orig_category":"Electricidad: Instaladores",
    "sg:phone":"+34 988 41 06 53",
    "sg:postcode":"32600",
    "sg:province":"Ourense",
    "wof:name":"Instelor S.l.",
    "wof:placetype":"venue"
},
  "geometry": {"coordinates":[-7.430521965,41.9407119751],"type":"Point"}
}