{
  "type": "Feature",
  "properties": {
    "iso:country":"ES",
    "sg:address":"Avda Finisterre, 1",
    "sg:city":"Coru\u00d1a",
    "sg:classifiers":[
        {
            "category":"Autos & Motor Vehicles",
            "subcategory":"Automobile Sales",
            "type":"Retail Goods"
        }
    ],
    "sg:phone":"+34 981 26 17 67",
    "sg:postcode":"15004",
    "sg:province":"La Coru\u00f1a",
    "wof:name":"Auto Escuela Sousa S.cv.",
    "wof:placetype":"venue"
},
  "geometry": {"coordinates":[-8.412314415,43.364402771],"type":"Point"}
}