{
  "type": "Feature",
  "properties": {
    "iso:country":"ES",
    "sg:address":"Calle de Mayor, 22",
    "sg:city":"Labastida",
    "sg:orig_category":"Pescader\u00cdas (al Por Menor)",
    "sg:phone":"+34 945 33 10 87",
    "sg:postcode":"01330",
    "sg:province":"\u00c1lava",
    "wof:name":"Amurrio Aguillo Maria Teresa",
    "wof:placetype":"venue"
},
  "geometry": {"coordinates":[-2.7941601276,42.5908203125],"type":"Point"}
}