{
  "type": "Feature",
  "properties": {
    "addr:full":"Pol Ind El Romeral, 1 Durcal Granada 18650",
    "addr:housenumber":"1",
    "addr:postcode":"18650",
    "addr:street":"Romeral",
    "iso:country":"ES",
    "sg:address":"Pol Ind El Romeral, 1",
    "sg:city":"Durcal",
    "sg:orig_category":"Frutas Y Legumbres Frescas (al Por Mayor)",
    "sg:phone":"+34 958 78 14 20",
    "sg:postcode":"18650",
    "sg:province":"Granada",
    "wof:name":"Frutas Hermanos Braojos S.l.",
    "wof:placetype":"venue"
},
  "geometry": {"coordinates":[-3.5704190731,36.9924316406],"type":"Point"}
}