{
  "type": "Feature",
  "properties": {
    "addr:full":"Calle de Pablo Mayayo, 36 Algeciras C\u00e1diz 11201",
    "addr:housenumber":"36;ca\u0301diz",
    "addr:postcode":"11201",
    "addr:street":"Calle De Pablo Mayayo",
    "iso:country":"ES",
    "sg:address":"Calle de Pablo Mayayo, 36",
    "sg:city":"Algeciras",
    "sg:orig_category":"M\u00c9dicos: Medicina Legal, Peritajes M\u00c9dicos",
    "sg:phone":"+34 956 66 23 13",
    "sg:postcode":"11201",
    "sg:province":"C\u00e1diz",
    "wof:name":"Gonzalez Sanchez Juan Jesus",
    "wof:placetype":"venue"
},
  "geometry": {"coordinates":[-5.4461770058,36.1317825317],"type":"Point"}
}