{
  "type": "Feature",
  "properties": {
    "iso:country":"ES",
    "sg:address":"Calle de Hermanos Pinzon, 68",
    "sg:city":"Almeria",
    "sg:orig_category":"Centros De Coordinaci\u00d3n",
    "sg:phone":"+34 950 26 22 55",
    "sg:postcode":"04005",
    "sg:province":"Almer\u00eda",
    "wof:name":"Tadeo Martinez Javier Enrique",
    "wof:placetype":"venue"
},
  "geometry": {"coordinates":[-2.4543089867,36.8418922424],"type":"Point"}
}