{
  "type": "Feature",
  "properties": {
    "addr:full":"Calle de Santa Lucia, 2 Miranda Ebro Burgos 09200",
    "addr:housenumber":"2",
    "addr:postcode":"09200",
    "addr:street":"Calle De Santa Lucia",
    "iso:country":"ES",
    "sg:address":"Calle de Santa Lucia, 2",
    "sg:city":"Miranda Ebro",
    "sg:orig_category":"Postigos, Persianas Y Celos\u00cdas",
    "sg:phone":"+34 947 33 23 48",
    "sg:postcode":"09200",
    "sg:province":"Burgos",
    "wof:name":"Urbiser S.l.",
    "wof:placetype":"venue"
},
  "geometry": {"coordinates":[-2.9490339756,42.6847305298],"type":"Point"}
}