{
  "type": "Feature",
  "properties": {
    "iso:country":"ES",
    "sg:address":"Carrer de America, 11",
    "sg:city":"Sabadell",
    "sg:orig_category":"Caf\u00c9s, Bares, Cervecer\u00cdas",
    "sg:phone":"+34 937 27 71 72",
    "sg:postcode":"08205",
    "sg:province":"Barcelona",
    "sg:website":"pendejo-online.com",
    "wof:name":"Picantino S.l",
    "wof:placetype":"venue"
},
  "geometry": {"coordinates":[2.0922279358,41.5454902649],"type":"Point"}
}