{
  "type": "Feature",
  "properties": {
    "addr:full":"Avda Arcadio Pardi\u00d1as, 97 Burela Lugo 27880",
    "addr:housenumber":"97",
    "addr:postcode":"27880",
    "addr:street":"Avda Arcadio Pardin\u0303As",
    "iso:country":"ES",
    "sg:address":"Avda Arcadio Pardi\u00d1as, 97",
    "sg:city":"Burela",
    "sg:orig_category":"Empresas De Limpieza",
    "sg:phone":"+34 982 58 14 12",
    "sg:postcode":"27880",
    "sg:province":"Lugo",
    "wof:name":"Bello Gonzalez Jose Antonio",
    "wof:placetype":"venue"
},
  "geometry": {"coordinates":[-7.3603467941,43.6587371826],"type":"Point"}
}