{
  "type": "Feature",
  "properties": {
    "addr:full":"Calle de Linneo, 14 Madrid Madrid 28005",
    "addr:housenumber":"14",
    "addr:postcode":"madrid;28005",
    "addr:street":"Calle De Linneo",
    "iso:country":"ES",
    "sg:address":"Calle de Linneo, 14",
    "sg:city":"Madrid",
    "sg:orig_category":"Laboratorios Farmac\u00c9uticos",
    "sg:phone":"+34 913 64 12 16",
    "sg:postcode":"28005",
    "sg:province":"Madrid",
    "wof:name":"Vitafarma S.l.",
    "wof:placetype":"venue"
},
  "geometry": {"coordinates":[-3.7205717564,40.4108886719],"type":"Point"}
}