{
  "type": "Feature",
  "properties": {
    "addr:full":"Av Catalunya, 4 Deltebre Tarragona 43580",
    "addr:housenumber":"4",
    "addr:postcode":"43580",
    "addr:street":"Av Catalunya",
    "iso:country":"ES",
    "sg:address":"Av Catalunya, 4",
    "sg:city":"Deltebre",
    "sg:orig_category":"Institutos De Belleza",
    "sg:phone":"+34 977 48 90 88",
    "sg:postcode":"43580",
    "sg:province":"Tarragona",
    "wof:name":"Guillen Turon Jessica",
    "wof:placetype":"venue"
},
  "geometry": {"coordinates":[0.7229449749,40.7188110352],"type":"Point"}
}