{
  "type": "Feature",
  "properties": {
    "addr:full":"Calle de Muro, 5 Algeciras C\u00e1diz 11201",
    "addr:housenumber":"5;ca\u0301diz",
    "addr:postcode":"11201",
    "addr:street":"Calle De Muro",
    "iso:country":"ES",
    "sg:address":"Calle de Muro, 5",
    "sg:city":"Algeciras",
    "sg:orig_category":"Agencias Y Asesores De Publicidad",
    "sg:phone":"+34 956 66 62 51",
    "sg:postcode":"11201",
    "sg:province":"C\u00e1diz",
    "wof:name":"Expresion Comunicacion Total S.l.",
    "wof:placetype":"venue"
},
  "geometry": {"coordinates":[-5.445857048,36.1306686401],"type":"Point"}
}