{
  "type": "Feature",
  "properties": {
    "addr:full":"Calle de Higueras, 45 Madrid Madrid 28011",
    "addr:housenumber":"45",
    "addr:postcode":"madrid;28011",
    "addr:street":"Calle De Higueras",
    "iso:country":"ES",
    "sg:address":"Calle de Higueras, 45",
    "sg:city":"Madrid",
    "sg:orig_category":"Frutas, Legumbres Frescas Y Tempranas (al Por Menor)",
    "sg:phone":"+34 914 64 85 63",
    "sg:postcode":"28011",
    "sg:province":"Madrid",
    "wof:name":"Cabezas Gonzalez Manuela",
    "wof:placetype":"venue"
},
  "geometry": {"coordinates":[-3.7450010777,40.4057579041],"type":"Point"}
}