{
  "type": "Feature",
  "properties": {
    "addr:full":"Avda Fernando Tarrago, D'en, 11 Cala D'or Islas Baleares 07660",
    "addr:housenumber":"11",
    "addr:postcode":"07660",
    "addr:street":"Avda Fernando Tarrago D'En",
    "iso:country":"ES",
    "sg:address":"Avda Fernando Tarrago, D'en, 11",
    "sg:city":"Cala D'or",
    "sg:orig_category":"Molduras, Junquillos, Listones Y Molduras Perforadas",
    "sg:phone":"+34 971 65 71 10",
    "sg:postcode":"07660",
    "sg:province":"Islas Baleares",
    "wof:name":"Bestard Mas Miguel",
    "wof:placetype":"venue"
},
  "geometry": {"coordinates":[2.9117100239,39.6136398315],"type":"Point"}
}