{
  "type": "Feature",
  "properties": {
    "iso:country":"ES",
    "sg:address":"Calle de Portugal, 20",
    "sg:city":"Alacant",
    "sg:orig_category":"Agencias De Viajes",
    "sg:phone":"+34 965 13 21 56",
    "sg:postcode":"03003",
    "sg:province":"Alicante",
    "sg:website":"www.marsans.es",
    "wof:name":"Viajes Marsans S.a.",
    "wof:placetype":"venue"
},
  "geometry": {"coordinates":[-0.4903410077,38.3419952393],"type":"Point"}
}