{
  "type": "Feature",
  "properties": {
    "addr:full":"Calle de Nueva, 27 Santaella C\u00f3rdoba 14546",
    "addr:housenumber":"27",
    "addr:postcode":"14546",
    "addr:street":"Calle De Nueva;Co\u0301Rdoba",
    "iso:country":"ES",
    "sg:address":"Calle de Nueva, 27",
    "sg:city":"Santaella",
    "sg:orig_category":"Transportes Por Carretera: Lotes Completos, Mercanc\u00cdas Diversas",
    "sg:phone":"+34 957 31 34 15",
    "sg:postcode":"14546",
    "sg:province":"C\u00f3rdoba",
    "wof:name":"Rodriguez Morales Manuel",
    "wof:placetype":"venue"
},
  "geometry": {"coordinates":[-4.8471927643,37.5679092407],"type":"Point"}
}