{
  "type": "Feature",
  "properties": {
    "iso:country":"ES",
    "sg:address":"Rua Curros Enriquez, 1",
    "sg:city":"Cambados",
    "sg:orig_category":"Panader\u00cdas, Panader\u00cdas",
    "sg:phone":"+34 986 52 10 70",
    "sg:postcode":"36630",
    "sg:province":"Pontevedra",
    "wof:name":"Ankarr Villagarcia S.l.u.",
    "wof:placetype":"venue"
},
  "geometry": {"coordinates":[-8.8151054382,42.5150108337],"type":"Point"}
}