{
  "type": "Feature",
  "properties": {
    "iso:country":"ES",
    "sg:address":"Poli Industrial Aeropuerto, 3",
    "sg:city":"Sevilla",
    "sg:orig_category":"Fabricaci\u00d3n De Telas Y Sedas",
    "sg:phone":"+34 954 25 78 90",
    "sg:postcode":"41020",
    "sg:province":"Sevilla",
    "wof:name":"Francisco Enriquez S.a.",
    "wof:placetype":"venue"
},
  "geometry": {"coordinates":[-5.9333291054,37.4165763855],"type":"Point"}
}