{
  "type": "Feature",
  "properties": {
    "iso:country":"ES",
    "sg:address":"Avda Septima, 10",
    "sg:city":"Colmenar Viejo",
    "sg:orig_category":"Traductores",
    "sg:phone":"+34 918 45 65 30",
    "sg:postcode":"28770",
    "sg:province":"Madrid",
    "wof:name":"Respaldo Informacion Y Comunicacion S.l",
    "wof:placetype":"venue"
},
  "geometry": {"coordinates":[-3.7679181099,40.6699066162],"type":"Point"}
}