{
  "type": "Feature",
  "properties": {
    "addr:full":"Calle de Logro\u00d1o, 17 San Juan De Aznalfarache Sevilla 41920",
    "addr:housenumber":"17",
    "addr:postcode":"41920",
    "addr:street":"Calle De Logron\u0303O",
    "iso:country":"ES",
    "sg:address":"Calle de Logro\u00d1o, 17",
    "sg:city":"San Juan De Aznalfarache",
    "sg:orig_category":"Agencias Y Agentes Comerciales, Representantes",
    "sg:phone":"+34 954 76 37 59",
    "sg:postcode":"41920",
    "sg:province":"Sevilla",
    "wof:name":"Gomez Andana Juan Luis",
    "wof:placetype":"venue"
},
  "geometry": {"coordinates":[-6.0277690887,37.359916687],"type":"Point"}
}