{
  "type": "Feature",
  "properties": {
    "iso:country":"ES",
    "sg:address":"Hoya Camino De La, S/n",
    "sg:city":"Laguardia-biasteri",
    "sg:orig_category":"Productores Recolectores, Venta Directa De Vinos",
    "sg:phone":"+34 945 60 05 28",
    "sg:postcode":"01300",
    "sg:province":"\u00c1lava",
    "wof:name":"Allied Domecq Wines Espa\u00d1a S.a.",
    "wof:placetype":"venue"
},
  "geometry": {"coordinates":[-2.5842370987,42.5542793274],"type":"Point"}
}