{
  "type": "Feature",
  "properties": {
    "iso:country":"ES",
    "sg:address":"Avda Independencia, 18",
    "sg:city":"Zaragoza",
    "sg:orig_category":"Notarios",
    "sg:phone":"+34 976 21 62 35",
    "sg:postcode":"50004",
    "sg:province":"Zaragoza",
    "wof:name":"Gimeno Lazaro Fernando",
    "wof:placetype":"venue"
},
  "geometry": {"coordinates":[-0.882660985,41.6504898071],"type":"Point"}
}