{
  "type": "Feature",
  "properties": {
    "addr:full":"Avda Mare Nostrum, 37 Almeria Almer\u00eda 04009",
    "addr:housenumber":"37",
    "addr:postcode":"04009",
    "addr:street":"Avda Mare Nostrum",
    "iso:country":"ES",
    "sg:address":"Avda Mare Nostrum, 37",
    "sg:city":"Almeria",
    "sg:orig_category":"Albergues",
    "sg:phone":"+34 950 22 59 28",
    "sg:postcode":"04009",
    "sg:province":"Almer\u00eda",
    "wof:name":"Bernal Lupia\u00f1ez Jose Maria",
    "wof:placetype":"venue"
},
  "geometry": {"coordinates":[-2.4321389198,36.8447990417],"type":"Point"}
}