{
  "type": "Feature",
  "properties": {
    "addr:full":"Calle de Jardin De San Federico, 9 Madrid Madrid 28009",
    "addr:housenumber":"9",
    "addr:postcode":"madrid;28009",
    "addr:street":"Calle De Jardin De San Federico",
    "iso:country":"ES",
    "sg:address":"Calle de Jardin De San Federico, 9",
    "sg:city":"Madrid",
    "sg:orig_category":"Fotograf\u00cda Y Cine: Aparatos, Pel\u00cdculas Y Accesorios (fabricaci\u00d3n, Al Por Mayor)",
    "sg:phone":"+34 913 09 18 81",
    "sg:postcode":"28009",
    "sg:province":"Madrid",
    "wof:name":"Joseph S.l.",
    "wof:placetype":"venue"
},
  "geometry": {"coordinates":[-3.6697871685,40.4249000549],"type":"Point"}
}