{
  "type": "Feature",
  "properties": {
    "addr:full":"Calle de Virgen Del Carmen, 19 Chiclana De La Frontera C\u00e1diz 11130",
    "addr:housenumber":"19",
    "addr:postcode":"11130",
    "addr:street":"Calle De Virgen Del Carmen",
    "iso:country":"ES",
    "sg:address":"Calle de Virgen Del Carmen, 19",
    "sg:city":"Chiclana De La Frontera",
    "sg:orig_category":"Ense\u00d1anza Variada",
    "sg:phone":"+34 956 53 09 41",
    "sg:postcode":"11130",
    "sg:province":"C\u00e1diz",
    "wof:name":"Alvarado Herrera Antonio",
    "wof:placetype":"venue"
},
  "geometry": {"coordinates":[-6.1457805634,36.4218940735],"type":"Point"}
}