{
  "type": "Feature",
  "properties": {
    "iso:country":"ES",
    "sg:address":"Carr Ferrer I Busquets, 3",
    "sg:city":"Mollerussa",
    "sg:orig_category":"Inmobiliaria (agencias)",
    "sg:phone":"+34 973 60 37 46",
    "sg:postcode":"25230",
    "sg:province":"Lleida",
    "wof:name":"Gabernet Rodriguez S.l.",
    "wof:placetype":"venue"
},
  "geometry": {"coordinates":[0.8924800158,41.6300086975],"type":"Point"}
}