{
  "type": "Feature",
  "properties": {
    "iso:country":"ES",
    "sg:address":"Calle de Cerrada, 2",
    "sg:city":"Valladolid",
    "sg:orig_category":"Reposter\u00cdas",
    "sg:phone":"+34 983 25 84 28",
    "sg:postcode":"47010",
    "sg:province":"Valladolid",
    "wof:name":"Real Perez Maria Asuncion",
    "wof:placetype":"venue"
},
  "geometry": {"coordinates":[-4.7195158005,41.6591796875],"type":"Point"}
}