{
  "type": "Feature",
  "properties": {
    "iso:country":"ES",
    "sg:address":"Carrer de Major, 4",
    "sg:city":"Alcover",
    "sg:orig_category":"Negocio De Metales No Ferrosos",
    "sg:phone":"+34 977 84 60 62",
    "sg:postcode":"43460",
    "sg:province":"Tarragona",
    "wof:name":"Martorell Torrens Jose",
    "wof:placetype":"venue"
},
  "geometry": {"coordinates":[1.1706800461,41.2619400024],"type":"Point"}
}