{
  "type": "Feature",
  "properties": {
    "iso:country":"ES",
    "sg:address":"Carrer de Jaume De Viver, 9",
    "sg:city":"Olesa Montserrat",
    "sg:orig_category":"Peluqueros: De Se\u00d1oras",
    "sg:phone":"+34 937 78 59 95",
    "sg:postcode":"08640",
    "sg:province":"Barcelona",
    "wof:name":"Agudo Bautista Margarita",
    "wof:placetype":"venue"
},
  "geometry": {"coordinates":[1.8971540928,41.5416374207],"type":"Point"}
}