{
  "type": "Feature",
  "properties": {
    "addr:full":"Carrer de Guerriller Alzina, 69 Sabadell Barcelona 08204",
    "addr:housenumber":"69",
    "addr:postcode":"08204",
    "addr:street":"Carrer De Guerriller Alzina",
    "iso:country":"ES",
    "sg:address":"Carrer de Guerriller Alzina, 69",
    "sg:city":"Sabadell",
    "sg:orig_category":"Cristaler\u00cdas",
    "sg:phone":"+34 937 10 27 27",
    "sg:postcode":"08204",
    "sg:province":"Barcelona",
    "wof:name":"Mora Monterde Mateo",
    "wof:placetype":"venue"
},
  "geometry": {"coordinates":[2.1152598858,41.5274353027],"type":"Point"}
}