{
  "type": "Feature",
  "properties": {
    "iso:country":"ES",
    "sg:address":"Calle de Alvaro Gil, 2",
    "sg:city":"Salamanca",
    "sg:orig_category":"Papeler\u00cdas, Librer\u00cdas",
    "sg:phone":"+34 923 25 53 84",
    "sg:postcode":"37007",
    "sg:province":"Salamanca",
    "sg:website":"wwwcopyexpres.com",
    "wof:name":"Vaquero Villa Alicia",
    "wof:placetype":"venue"
},
  "geometry": {"coordinates":[-5.6645350456,40.9699211121],"type":"Point"}
}