{
  "type": "Feature",
  "properties": {
    "iso:country":"ES",
    "sg:address":"Avda Gran Via Parque, 3",
    "sg:city":"Cordoba",
    "sg:orig_category":"Peluqueros: De Se\u00d1oras",
    "sg:phone":"+34 957 23 99 81",
    "sg:postcode":"14005",
    "sg:province":"C\u00f3rdoba",
    "wof:name":"Hernandez Mengibar Purificacion",
    "wof:placetype":"venue"
},
  "geometry": {"coordinates":[-4.7947368622,37.88438797],"type":"Point"}
}