{
  "type": "Feature",
  "properties": {
    "iso:country":"ES",
    "sg:address":"Alam Colon, 12",
    "sg:city":"Malaga",
    "sg:orig_category":"Cajas De Ahorro",
    "sg:phone":"+34 952 12 15 35",
    "sg:postcode":"29001",
    "sg:province":"M\u00e1laga",
    "wof:name":"Unicaja",
    "wof:placetype":"venue"
},
  "geometry": {"coordinates":[-4.4247279167,36.715221405],"type":"Point"}
}