{
  "type": "Feature",
  "properties": {
    "iso:country":"ES",
    "sg:address":"Rua G, 21",
    "sg:city":"Lalin",
    "sg:orig_category":"Electricidad: Instaladores",
    "sg:phone":"+34 986 78 04 42",
    "sg:postcode":"36500",
    "sg:province":"Pontevedra",
    "wof:name":"Bafer Lalin S.l.",
    "wof:placetype":"venue"
},
  "geometry": {"coordinates":[-8.110956192,42.658405304],"type":"Point"}
}