{
  "type": "Feature",
  "properties": {
    "addr:full":"Avda Canarias, 450 Vecindario Las Palmas 35110",
    "addr:housenumber":"450",
    "addr:postcode":"35110",
    "addr:street":"Avda Canarias;Las Palmas",
    "iso:country":"ES",
    "sg:address":"Avda Canarias, 450",
    "sg:city":"Vecindario",
    "sg:orig_category":"Servicios Gsm",
    "sg:phone":"+34 928 75 53 51",
    "sg:postcode":"35110",
    "sg:province":"Las Palmas",
    "wof:name":"Santana Deniz Pino Vanesa",
    "wof:placetype":"venue"
},
  "geometry": {"coordinates":[-15.4481868744,27.8400421143],"type":"Point"}
}