{
  "type": "Feature",
  "properties": {
    "iso:country":"ES",
    "sg:address":"Disseminat, S/n",
    "sg:city":"Terrassa",
    "sg:classifiers":[
        {
            "category":"Taxi",
            "type":"Transportation"
        }
    ],
    "sg:phone":"+34 937 80 57 47",
    "sg:postcode":"08224",
    "sg:province":"Barcelona",
    "wof:name":"Escobar Salvador Rosario",
    "wof:placetype":"venue"
},
  "geometry": {"coordinates":[2.0070500374,41.5507507324],"type":"Point"}
}