{
  "type": "Feature",
  "properties": {
    "addr:full":"Avda Corazon De Jesus, 6 Almunia De Do\u00e7a Godina Zaragoza 50100",
    "addr:housenumber":"6",
    "addr:postcode":"50100",
    "addr:street":"Avda Corazon De Jesus",
    "iso:country":"ES",
    "sg:address":"Avda Corazon De Jesus, 6",
    "sg:city":"Almunia De Do\u00e7a Godina",
    "sg:orig_category":"Semiller\u00cdas",
    "sg:phone":"+34 976 81 23 30",
    "sg:postcode":"50100",
    "sg:province":"Zaragoza",
    "wof:name":"Barra Raga Jose Javier",
    "wof:placetype":"venue"
},
  "geometry": {"coordinates":[-1.3693929911,41.4758262634],"type":"Point"}
}