{
  "type": "Feature",
  "properties": {
    "addr:full":"Carr Garriga, 10 Pollen\u00e7a Islas Baleares 07460",
    "addr:housenumber":"10",
    "addr:postcode":"07460",
    "addr:street":"Carr Garriga;Islas",
    "iso:country":"ES",
    "sg:address":"Carr Garriga, 10",
    "sg:city":"Pollen\u00e7a",
    "sg:orig_category":"Sonorizaci\u00d3n, Iluminaci\u00d3n Para Cine, Teatro Y Discotecas (al Por Mayor, Al Por Menor)",
    "sg:phone":"+34 971 53 44 50",
    "sg:postcode":"07460",
    "sg:province":"Islas Baleares",
    "wof:name":"Luz Y Arte C.b",
    "wof:placetype":"venue"
},
  "geometry": {"coordinates":[3.0136330128,39.8772773743],"type":"Point"}
}