{
  "type": "Feature",
  "properties": {
    "iso:country":"ES",
    "sg:address":"Calle de Leon, 3",
    "sg:city":"Fuenlabrada",
    "sg:orig_category":"Quincaller\u00cda (al Por Menor)",
    "sg:phone":"+34 916 42 01 04",
    "sg:postcode":"28947",
    "sg:province":"Madrid",
    "wof:name":"Suminfer S.l.",
    "wof:placetype":"venue"
},
  "geometry": {"coordinates":[-3.7439498901,40.2650794983],"type":"Point"}
}