{
  "type": "Feature",
  "properties": {
    "iso:country":"ES",
    "sg:address":"Calle de Burgos, 17",
    "sg:city":"Vitoria-gasteiz",
    "sg:orig_category":"Colocaci\u00d3n, Mantenimiento De Canalizaciones",
    "sg:phone":"+34 945 27 25 49",
    "sg:postcode":"01002",
    "sg:province":"\u00c1lava",
    "wof:name":"Tesa Vertical, S.l.",
    "wof:placetype":"venue"
},
  "geometry": {"coordinates":[-2.6602060795,42.8550224304],"type":"Point"}
}