{
  "type": "Feature",
  "properties": {
    "addr:full":"Calle de Donoso Cortes, 88 Madrid Madrid 28015",
    "addr:housenumber":"88",
    "addr:postcode":"madrid;28015",
    "addr:street":"Calle De Donoso Cortes",
    "iso:country":"ES",
    "sg:address":"Calle de Donoso Cortes, 88",
    "sg:city":"Madrid",
    "sg:orig_category":"Fabricaci\u00d3n, Venta De Cuadros, Accesorios Para Enmarcar",
    "sg:phone":"+34 915 49 16 62",
    "sg:postcode":"28015",
    "sg:province":"Madrid",
    "wof:name":"Baselga Llido Diego",
    "wof:placetype":"venue"
},
  "geometry": {"coordinates":[-3.7159740925,40.436668396],"type":"Point"}
}