{
  "type": "Feature",
  "properties": {
    "iso:country":"ES",
    "sg:address":"Calle de Pablo Gorosabel Kalea, 17",
    "sg:city":"Tolosa",
    "sg:orig_category":"Ropa Para Ni\u00d1os (al Por Menor)",
    "sg:phone":"+34 943 67 45 29",
    "sg:postcode":"20400",
    "sg:province":"Guip\u00f9zcoa",
    "wof:name":"Eizmendi Iraola Vicente",
    "wof:placetype":"venue"
},
  "geometry": {"coordinates":[-2.0735208988,43.138671875],"type":"Point"}
}