{
  "type": "Feature",
  "properties": {
    "addr:full":"Calle de Juan Carlos I, 6 Pe\u00e7arroya-pueblonuevo C\u00f3rdoba 14200",
    "addr:housenumber":"6",
    "addr:postcode":"14200",
    "addr:street":"Calle De Juan Carlos I;Co\u0301Rdoba",
    "iso:country":"ES",
    "sg:address":"Calle de Juan Carlos I, 6",
    "sg:city":"Pe\u00e7arroya-pueblonuevo",
    "sg:orig_category":"Zapater\u00cdas",
    "sg:phone":"+34 957 56 07 10",
    "sg:postcode":"14200",
    "sg:province":"C\u00f3rdoba",
    "sg:website":"www.moddo.com/lapalma",
    "wof:name":"Bretones-mora Hidalgo Flores",
    "wof:placetype":"venue"
},
  "geometry": {"coordinates":[-5.2651658058,38.2985153198],"type":"Point"}
}