{
  "type": "Feature",
  "properties": {
    "iso:country":"ES",
    "sg:address":"Calle de Guzman El Bueno, 5",
    "sg:city":"Malaga",
    "sg:orig_category":"Diplomas Diversos",
    "sg:phone":"+34 952 20 19 13",
    "sg:postcode":"29018",
    "sg:province":"M\u00e1laga",
    "wof:name":"Gabinete De Sociologia S.l.",
    "wof:placetype":"venue"
},
  "geometry": {"coordinates":[-4.3743391037,36.7271537781],"type":"Point"}
}