{
  "type": "Feature",
  "properties": {
    "iso:country":"ES",
    "sg:address":"Calle de Portales, 49",
    "sg:city":"Logro\u00f1o",
    "sg:orig_category":"Centros Empresariales",
    "sg:phone":"+34 941 23 99 96",
    "sg:postcode":"26001",
    "sg:province":"La Rioja",
    "wof:name":"Asociacion Club Financiero Portales",
    "wof:placetype":"venue"
},
  "geometry": {"coordinates":[-2.4467782974,42.4664535522],"type":"Point"}
}