{
  "type": "Feature",
  "properties": {
    "addr:full":"B. Infante, 20 Fuente Palmera C\u00f3rdoba 14120",
    "addr:housenumber":"20",
    "addr:postcode":"14120",
    "addr:street":"B. Infante",
    "iso:country":"ES",
    "sg:address":"B. Infante, 20",
    "sg:city":"Fuente Palmera",
    "sg:orig_category":"Fabricaci\u00d3n, Venta, Instalaci\u00d3n De R\u00d3tulos, De R\u00d3tulos Luminosos",
    "sg:phone":"+34 957 63 89 57",
    "sg:postcode":"14120",
    "sg:province":"C\u00f3rdoba",
    "wof:name":"Carmona Coheran Jose Antonio",
    "wof:placetype":"venue"
},
  "geometry": {"coordinates":[-5.104033947,37.7035446167],"type":"Point"}
}