{
  "type": "Feature",
  "properties": {
    "addr:full":"Calle de Reyes Catolicos, 34 Molina Segura Murcia 30500",
    "addr:housenumber":"34",
    "addr:postcode":"30500",
    "addr:street":"Calle De Reyes Catolicos",
    "iso:country":"ES",
    "sg:address":"Calle de Reyes Catolicos, 34",
    "sg:city":"Molina Segura",
    "sg:orig_category":"Carnicer\u00cdas, Carnicer\u00cdas",
    "sg:phone":"+34 968 61 10 67",
    "sg:postcode":"30500",
    "sg:province":"Murcia",
    "wof:name":"Garcia Abellan Jose Antonio",
    "wof:placetype":"venue"
},
  "geometry": {"coordinates":[-1.2052760124,38.0533485413],"type":"Point"}
}