{
  "type": "Feature",
  "properties": {
    "iso:country":"ES",
    "sg:address":"Calle de Butron, 29",
    "sg:city":"Madrid",
    "sg:orig_category":"Venta Al Preg\u00d3n",
    "sg:phone":"+34 913 06 68 27",
    "sg:postcode":"28022",
    "sg:province":"Madrid",
    "wof:name":"Vaquero Rodriguez Teodoro",
    "wof:placetype":"venue"
},
  "geometry": {"coordinates":[-3.6075880527,40.425868988],"type":"Point"}
}