{
  "type": "Feature",
  "properties": {
    "iso:country":"ES",
    "sg:address":"Carr Virtut, 52",
    "sg:city":"Igualada",
    "sg:orig_category":"Animales (al Por Menor)",
    "sg:phone":"+34 938 05 53 32",
    "sg:postcode":"08700",
    "sg:province":"Barcelona",
    "wof:name":"Freixa Farres Teresa Maria",
    "wof:placetype":"venue"
},
  "geometry": {"coordinates":[1.6247119904,41.5775985718],"type":"Point"}
}