{
  "type": "Feature",
  "properties": {
    "addr:full":"Calle de Murillo, 7 Le\u00f3n Le\u00f3n 24005",
    "addr:housenumber":"7",
    "addr:postcode":"24005",
    "addr:street":"Calle De Murillo;Leo\u0301N",
    "iso:country":"ES",
    "sg:address":"Calle de Murillo, 7",
    "sg:city":"Le\u00f3n",
    "sg:orig_category":"Granos Y Semillas (producci\u00d3n, Al Por Mayor)",
    "sg:phone":"+34 987 21 28 18",
    "sg:postcode":"24005",
    "sg:province":"Le\u00f3n",
    "wof:name":"Rojo Arienza Miguel Angel",
    "wof:placetype":"venue"
},
  "geometry": {"coordinates":[-5.5631761551,42.5889701843],"type":"Point"}
}