{
  "type": "Feature",
  "properties": {
    "addr:full":"Calle de Constitucion, 1 Villanueva Algaidas M\u00e1laga 29310",
    "addr:housenumber":"1",
    "addr:postcode":"29310",
    "addr:street":"Calle De Constitucion;Algaidas Ma\u0301Laga",
    "iso:country":"ES",
    "sg:address":"Calle de Constitucion, 1",
    "sg:city":"Villanueva Algaidas",
    "sg:orig_category":"Supermercados Y Hipermercados",
    "sg:phone":"+34 952 74 45 21",
    "sg:postcode":"29310",
    "sg:province":"M\u00e1laga",
    "wof:name":"Supermercado Algaidas S.l.l.",
    "wof:placetype":"venue"
},
  "geometry": {"coordinates":[-4.4505429268,37.1863746643],"type":"Point"}
}