{
  "type": "Feature",
  "properties": {
    "addr:full":"Avgd Beniopa (de), 34 Gandia Valencia 46700",
    "addr:postcode":"46700",
    "iso:country":"ES",
    "sg:address":"Avgd Beniopa (de), 34",
    "sg:city":"Gandia",
    "sg:orig_category":"Peluqueros: De Se\u00d1oras",
    "sg:phone":"+34 962 86 78 77",
    "sg:postcode":"46700",
    "sg:province":"Valencia",
    "wof:name":"Ordines Llopis Teresa",
    "wof:placetype":"venue"
},
  "geometry": {"coordinates":[-0.1913339943,38.960735321],"type":"Point"}
}