{
  "type": "Feature",
  "properties": {
    "iso:country":"ES",
    "sg:address":"Calle de Institutos, S/n",
    "sg:city":"Coria",
    "sg:orig_category":"Administraciones De Trabajo Y Empleo",
    "sg:phone":"+34 927 50 81 00",
    "sg:postcode":"10800",
    "sg:province":"C\u00e1ceres",
    "wof:name":"Servicio Publico De Empleo Estatal-dron. Prov. Caceres",
    "wof:placetype":"venue"
},
  "geometry": {"coordinates":[-6.5423288345,39.9924545288],"type":"Point"}
}