{
  "type": "Feature",
  "properties": {
    "addr:full":"Carr Bonifaci Viii, 4 Lleida Lleida 25005",
    "addr:housenumber":"4",
    "addr:postcode":"25005",
    "addr:street":"Carr Bonifaci Viii",
    "iso:country":"ES",
    "sg:address":"Carr Bonifaci Viii, 4",
    "sg:city":"Lleida",
    "sg:orig_category":"Promotores Constructores",
    "sg:phone":"+34 973 23 50 37",
    "sg:postcode":"25005",
    "sg:province":"Lleida",
    "wof:name":"Construcciones La Seu 2000 S.l.",
    "wof:placetype":"venue"
},
  "geometry": {"coordinates":[0.6272990108,41.6261787415],"type":"Point"}
}