{
  "type": "Feature",
  "properties": {
    "iso:country":"ES",
    "sg:address":"Pase Habana, 150",
    "sg:city":"Madrid",
    "sg:orig_category":"Venta, Alquiler De Toldos",
    "sg:phone":"+34 914 57 02 11",
    "sg:postcode":"28036",
    "sg:province":"Madrid",
    "wof:name":"Incofluid S.a.",
    "wof:placetype":"venue"
},
  "geometry": {"coordinates":[-3.6818249226,40.4583320618],"type":"Point"}
}