{
  "type": "Feature",
  "properties": {
    "addr:full":"Calle de Zabaleta, 55 Donostia-san Sebastian Guip\u00f9zcoa 20002",
    "addr:housenumber":"55",
    "addr:postcode":"20002",
    "addr:street":"Calle De Zabaleta",
    "iso:country":"ES",
    "sg:address":"Calle de Zabaleta, 55",
    "sg:city":"Donostia-san Sebastian",
    "sg:orig_category":"Agentes, Concesionarios Y Sucursales De Veh\u00cdculos",
    "sg:phone":"+34 943 29 32 92",
    "sg:postcode":"20002",
    "sg:province":"Guip\u00f9zcoa",
    "wof:name":"Gelsukar S.l.",
    "wof:placetype":"venue"
},
  "geometry": {"coordinates":[-1.972949028,43.3255195618],"type":"Point"}
}