{
  "type": "Feature",
  "properties": {
    "iso:country":"ES",
    "sg:address":"Carrer de Josep Anselm Clave, 36",
    "sg:city":"Hospitalet Llobregat",
    "sg:orig_category":"Ropa Para Ni\u00d1os (al Por Menor)",
    "sg:phone":"+34 933 31 52 43",
    "sg:postcode":"08902",
    "sg:province":"Barcelona",
    "wof:name":"Garrido Belles Maria Dolors",
    "wof:placetype":"venue"
},
  "geometry": {"coordinates":[2.1267700195,41.3654060364],"type":"Point"}
}