{
  "type": "Feature",
  "properties": {
    "addr:full":"Plaz Genaro Echeandia, 2 Irun Guip\u00f9zcoa 20302",
    "addr:housenumber":"2",
    "addr:postcode":"20302",
    "addr:street":"Genaro Echeandia;Guipu\u0300Zcoa",
    "iso:country":"ES",
    "sg:address":"Plaz Genaro Echeandia, 2",
    "sg:city":"Irun",
    "sg:orig_category":"Perfumer\u00cda Y Cosm\u00c9tica (fabricaci\u00d3n, Al Por Mayor)",
    "sg:phone":"+34 943 62 02 28",
    "sg:postcode":"20302",
    "sg:province":"Guip\u00f9zcoa",
    "wof:name":"Exclusivas Negredo S.l.",
    "wof:placetype":"venue"
},
  "geometry": {"coordinates":[-1.7902339697,43.3395233154],"type":"Point"}
}