{
  "type": "Feature",
  "properties": {
    "iso:country":"ES",
    "sg:address":"Avda Tres Cruces, 9",
    "sg:city":"Zamora",
    "sg:orig_category":"Ingenier\u00cda, Centros De Estudios (diversos)",
    "sg:phone":"+34 980 52 02 15",
    "sg:postcode":"49008",
    "sg:province":"Zamora",
    "wof:name":"Garrido Rodriguez Jesus",
    "wof:placetype":"venue"
},
  "geometry": {"coordinates":[-5.7418880463,41.5099372864],"type":"Point"}
}