{
  "type": "Feature",
  "properties": {
    "addr:full":"Ciudad Sueca, 7 Iru\u00f1a Navarra 31014",
    "addr:housenumber":"7",
    "addr:postcode":"31014",
    "addr:street":"Sueca",
    "iso:country":"ES",
    "sg:address":"Ciudad Sueca, 7",
    "sg:city":"Iru\u00f1a",
    "sg:orig_category":"Equipo De Refrigeraci\u00d3n Industrial",
    "sg:phone":"+34 948 12 66 33",
    "sg:postcode":"31014",
    "sg:province":"Navarra",
    "wof:name":"Fritecna S.l.",
    "wof:placetype":"venue"
},
  "geometry": {"coordinates":[-1.6525290012,42.8283462524],"type":"Point"}
}