{
  "type": "Feature",
  "properties": {
    "addr:full":"Calle de San Toribio, 7 Madrid Madrid 28031",
    "addr:housenumber":"7",
    "addr:postcode":"madrid;28031",
    "addr:street":"Calle De San Toribio",
    "iso:country":"ES",
    "sg:address":"Calle de San Toribio, 7",
    "sg:city":"Madrid",
    "sg:orig_category":"Cerrajer\u00cda, Ferrallista",
    "sg:phone":"+34 913 80 21 24",
    "sg:postcode":"28031",
    "sg:province":"Madrid",
    "wof:name":"Talleres Valdelafuente S.l.",
    "wof:placetype":"venue"
},
  "geometry": {"coordinates":[-3.6349270344,40.3802108765],"type":"Point"}
}