{
  "type": "Feature",
  "properties": {
    "iso:country":"ES",
    "sg:address":"Urb. Sotomar, S/n",
    "sg:city":"Sotogrande",
    "sg:orig_category":"Inmobiliaria (agencias)",
    "sg:phone":"+34 956 69 54 14",
    "sg:postcode":"11310",
    "sg:province":"C\u00e1diz",
    "wof:name":"Amiri Development S.l.",
    "wof:placetype":"venue"
},
  "geometry": {"coordinates":[-5.2761974335,36.2879981995],"type":"Point"}
}