{
  "type": "Feature",
  "properties": {
    "addr:full":"Calle de Velilla, 7 Madrid Madrid 28032",
    "addr:housenumber":"7",
    "addr:postcode":"madrid;28032",
    "addr:street":"Calle De Velilla",
    "iso:country":"ES",
    "sg:address":"Calle de Velilla, 7",
    "sg:city":"Madrid",
    "sg:orig_category":"Fabricaci\u00d3n De Peines Y De Accesorios De Peluquer\u00cda",
    "sg:phone":"+34 913 71 97 82",
    "sg:postcode":"28032",
    "sg:province":"Madrid",
    "wof:name":"Jordan Olivencia Julian",
    "wof:placetype":"venue"
},
  "geometry": {"coordinates":[-3.607749939,40.4034461975],"type":"Point"}
}