{
  "type": "Feature",
  "properties": {
    "iso:country":"ES",
    "sg:address":"Avda Pio Xii, S/n",
    "sg:city":"Valencia",
    "sg:orig_category":"Complementos De Vestir (al Por Menor)",
    "sg:phone":"+34 963 48 58 82",
    "sg:postcode":"46015",
    "sg:province":"Valencia",
    "wof:name":"Galerias Martin S.a.",
    "wof:placetype":"venue"
},
  "geometry": {"coordinates":[-0.3964424133,39.4857406616],"type":"Point"}
}