{
  "type": "Feature",
  "properties": {
    "iso:country":"ES",
    "sg:address":"Barr Lome\u00d1a, S/n",
    "sg:city":"Lome\u00d1a",
    "sg:orig_category":"T\u00c9cnicos Veterinarios",
    "sg:phone":"+34 942 73 51 07",
    "sg:postcode":"39574",
    "sg:province":"Cantabria",
    "wof:name":"Salceda Michelena Wladimiro",
    "wof:placetype":"venue"
},
  "geometry": {"coordinates":[-4.5950407982,43.1493797302],"type":"Point"}
}