{
  "type": "Feature",
  "properties": {
    "addr:full":"Calle de Cifuentes, 19 Guadalajara Guadalajara 19003",
    "addr:housenumber":"19",
    "addr:postcode":"19003",
    "addr:street":"Calle De Cifuentes",
    "iso:country":"ES",
    "sg:address":"Calle de Cifuentes, 19",
    "sg:city":"Guadalajara",
    "sg:orig_category":"Cl\u00cdnicas Dentales",
    "sg:phone":"+34 949 25 45 44",
    "sg:postcode":"19003",
    "sg:province":"Guadalajara",
    "wof:name":"Vivodent C.b.",
    "wof:placetype":"venue"
},
  "geometry": {"coordinates":[-3.1727573872,40.6302032471],"type":"Point"}
}