{
  "type": "Feature",
  "properties": {
    "iso:country":"ES",
    "sg:address":"Avda General Pereyra, 26",
    "sg:city":"Requena",
    "sg:orig_category":"Empresas De Limpieza",
    "sg:phone":"+34 962 30 50 90",
    "sg:postcode":"46340",
    "sg:province":"Valencia",
    "wof:name":"Limpiezas Y Servicios Secoman S.l.",
    "wof:placetype":"venue"
},
  "geometry": {"coordinates":[-1.1028599739,39.4896354675],"type":"Point"}
}