{
  "type": "Feature",
  "properties": {
    "addr:full":"Calle de Delfin Bericat, 5 Ejea De Los Caballeros Zaragoza 50600",
    "addr:housenumber":"5",
    "addr:postcode":"50600",
    "addr:street":"Calle De Delfin Bericat",
    "iso:country":"ES",
    "sg:address":"Calle de Delfin Bericat, 5",
    "sg:city":"Ejea De Los Caballeros",
    "sg:orig_category":"Promotores Constructores",
    "sg:phone":"+34 976 67 78 43",
    "sg:postcode":"50600",
    "sg:province":"Zaragoza",
    "wof:name":"Construcciones Larmiales S.l.",
    "wof:placetype":"venue"
},
  "geometry": {"coordinates":[-1.1399147511,42.1249198914],"type":"Point"}
}