{
  "type": "Feature",
  "properties": {
    "addr:full":"Calle de Alcalde Sainz De Baranda, 78 Madrid Madrid 28007",
    "addr:housenumber":"78",
    "addr:postcode":"madrid;28007",
    "addr:street":"Calle De Alcalde Sainz De Baranda",
    "iso:country":"ES",
    "sg:address":"Calle de Alcalde Sainz De Baranda, 78",
    "sg:city":"Madrid",
    "sg:orig_category":"Farmacias",
    "sg:phone":"+34 915 73 10 45",
    "sg:postcode":"28007",
    "sg:province":"Madrid",
    "wof:name":"Sanchez Brunete David Guillermo",
    "wof:placetype":"venue"
},
  "geometry": {"coordinates":[-3.6672687531,40.4173965454],"type":"Point"}
}