{
  "type": "Feature",
  "properties": {
    "addr:full":"Carr Hospital, 8 S. Pere Pescador Girona 17470",
    "addr:housenumber":"8",
    "addr:postcode":"17470",
    "addr:street":"Carr Hospital",
    "iso:country":"ES",
    "sg:address":"Carr Hospital, 8",
    "sg:city":"S. Pere Pescador",
    "sg:orig_category":"Arquitectos",
    "sg:phone":"+34 972 55 04 49",
    "sg:postcode":"17470",
    "sg:province":"Girona",
    "wof:name":"Tornafoch Boix Josep",
    "wof:placetype":"venue"
},
  "geometry": {"coordinates":[3.0805599689,42.1881332397],"type":"Point"}
}