{
  "type": "Feature",
  "properties": {
    "addr:full":"Calle de Jose Antonio (de), 20 Boadilla Del Monte Madrid 28660",
    "addr:housenumber":"20",
    "addr:postcode":"28660",
    "addr:street":"Calle De Jose Antonio De",
    "iso:country":"ES",
    "sg:address":"Calle de Jose Antonio (de), 20",
    "sg:city":"Boadilla Del Monte",
    "sg:orig_category":"Restaurantes",
    "sg:phone":"+34 916 32 15 59",
    "sg:postcode":"28660",
    "sg:province":"Madrid",
    "wof:name":"Perea Guisado Soraya",
    "wof:placetype":"venue"
},
  "geometry": {"coordinates":[-3.8771820068,40.4052696228],"type":"Point"}
}