{
  "type": "Feature",
  "properties": {
    "iso:country":"ES",
    "sg:address":"Calle de Alfonso I, 1",
    "sg:city":"Piedras Blancas",
    "sg:orig_category":"Cl\u00cdnicas Dentales",
    "sg:phone":"+34 985 53 29 77",
    "sg:postcode":"33450",
    "sg:province":"Asturias",
    "wof:name":"Maria Antonia Artime Fernandez Y Fernando Bendicho Cdad",
    "wof:placetype":"venue"
},
  "geometry": {"coordinates":[-5.9748153687,43.5593833923],"type":"Point"}
}