{
  "type": "Feature",
  "properties": {
    "addr:full":"Carretera De Acedera, S/n Orellana Vieja Badajoz 06740",
    "addr:housenumber":"s / n",
    "addr:postcode":"06740",
    "addr:street":"Carretera De Acedera",
    "iso:country":"ES",
    "sg:address":"Carretera De Acedera, S/n",
    "sg:city":"Orellana Vieja",
    "sg:orig_category":"Cooperativas Agr\u00cdcolas",
    "sg:phone":"+34 924 86 71 75",
    "sg:postcode":"06740",
    "sg:province":"Badajoz",
    "wof:name":"Cristo De Orellana La Vieja Soc.coop.",
    "wof:placetype":"venue"
},
  "geometry": {"coordinates":[-5.5316791534,39.0018997192],"type":"Point"}
}