{
  "type": "Feature",
  "properties": {
    "iso:country":"ES",
    "sg:address":"Ctra Burjasot-torres Torres, Km. 0008,0",
    "sg:city":"Betera",
    "sg:orig_category":"Semiller\u00cdas",
    "sg:phone":"+34 961 69 15 47",
    "sg:postcode":"46117",
    "sg:province":"Valencia",
    "wof:name":"S.a.t. Viveros Domenech 150 C.v.",
    "wof:placetype":"venue"
},
  "geometry": {"coordinates":[-0.4646939933,39.5906906128],"type":"Point"}
}