{
  "type": "Feature",
  "properties": {
    "iso:country":"ES",
    "sg:address":"Calle de Madrid, 4",
    "sg:city":"Torrejon Ardoz",
    "sg:orig_category":"Quincaller\u00cda (al Por Menor)",
    "sg:phone":"+34 916 56 38 48",
    "sg:postcode":"28850",
    "sg:province":"Madrid",
    "wof:name":"Herrajes Jardin S.a.",
    "wof:placetype":"venue"
},
  "geometry": {"coordinates":[-3.4808750153,40.4621429443],"type":"Point"}
}