{
  "type": "Feature",
  "properties": {
    "addr:full":"Las Balsillas, S/n Soria Soria 42004",
    "addr:housenumber":"s / n",
    "addr:postcode":"42004",
    "iso:country":"ES",
    "sg:address":"Las Balsillas, S/n",
    "sg:city":"Soria",
    "sg:orig_category":"Cristaler\u00cdas",
    "sg:phone":"+34 975 22 01 37",
    "sg:postcode":"42004",
    "sg:province":"Soria",
    "wof:name":"Acristalamientos Vinuesa S. A.",
    "wof:placetype":"venue"
},
  "geometry": {"coordinates":[-2.478962183,41.7601127625],"type":"Point"}
}