{
  "type": "Feature",
  "properties": {
    "iso:country":"ES",
    "sg:address":"Carrer de Enric Granados, 49",
    "sg:city":"Premia Mar",
    "sg:orig_category":"Juegos Y Juguetes (al Por Menor)",
    "sg:phone":"+34 937 52 37 36",
    "sg:postcode":"08330",
    "sg:province":"Barcelona",
    "wof:name":"Perguets S.l.",
    "wof:placetype":"venue"
},
  "geometry": {"coordinates":[2.3571310043,41.4936943054],"type":"Point"}
}