{
  "type": "Feature",
  "properties": {
    "iso:country":"ES",
    "sg:address":"Calle de Islas Columbretes, 182",
    "sg:city":"Alcazares",
    "sg:orig_category":"Inmobiliaria (agencias)",
    "sg:phone":"+34 968 17 00 61",
    "sg:postcode":"30710",
    "sg:province":"Murcia",
    "wof:name":"Halliday  Chinatsu",
    "wof:placetype":"venue"
},
  "geometry": {"coordinates":[-0.8518390059,37.7541885376],"type":"Point"}
}