{
  "type": "Feature",
  "properties": {
    "addr:full":"Calle de Rioja, 18 Sevilla Sevilla 41001",
    "addr:housenumber":"18",
    "addr:postcode":"41001",
    "addr:street":"Calle De Rioja",
    "iso:country":"ES",
    "sg:address":"Calle de Rioja, 18",
    "sg:city":"Sevilla",
    "sg:orig_category":"Estilistas Y Estudios De Estilo De Corte Y Confecci\u00d3n",
    "sg:phone":"+34 954 21 16 78",
    "sg:postcode":"41001",
    "sg:province":"Sevilla",
    "wof:name":"Cortesevi S. A.",
    "wof:placetype":"venue"
},
  "geometry": {"coordinates":[-5.9956741333,37.3911705017],"type":"Point"}
}