{
  "type": "Feature",
  "properties": {
    "iso:country":"ES",
    "sg:address":"Subida Al Faro, 49",
    "sg:city":"Cabo Palos",
    "sg:orig_category":"Notarios",
    "sg:phone":"+34 968 56 48 50",
    "sg:postcode":"30370",
    "sg:province":"Murcia",
    "wof:name":"Nieto Sanchez Jose",
    "wof:placetype":"venue"
},
  "geometry": {"coordinates":[-0.7274389863,37.6292953491],"type":"Point"}
}