{
  "type": "Feature",
  "properties": {
    "addr:full":"Calle de San Isidro, 23 Tauste Zaragoza 50660",
    "addr:housenumber":"23",
    "addr:postcode":"50660",
    "addr:street":"Calle De San Isidro",
    "iso:country":"ES",
    "sg:address":"Calle de San Isidro, 23",
    "sg:city":"Tauste",
    "sg:orig_category":"Alimentaci\u00d3n General (al Por Menor)",
    "sg:phone":"+34 976 85 92 18",
    "sg:postcode":"50660",
    "sg:province":"Zaragoza",
    "wof:name":"Garcia Abadillo Jose Maria",
    "wof:placetype":"venue"
},
  "geometry": {"coordinates":[-1.2538089752,41.9203987122],"type":"Point"}
}