{
  "type": "Feature",
  "properties": {
    "addr:full":"Cmno Suarez, 4 Malaga M\u00e1laga 29010",
    "addr:housenumber":"4",
    "addr:postcode":"29010",
    "addr:street":"Cmno Suarez;Ma\u0301Laga",
    "iso:country":"ES",
    "sg:address":"Cmno Suarez, 4",
    "sg:city":"Malaga",
    "sg:orig_category":"Cr\u00cda De Animales",
    "sg:phone":"+34 952 61 64 07",
    "sg:postcode":"29010",
    "sg:province":"M\u00e1laga",
    "wof:name":"Aranda Luque Sergio",
    "wof:placetype":"venue"
},
  "geometry": {"coordinates":[-4.4354496002,36.7270317078],"type":"Point"}
}