{
  "type": "Feature",
  "properties": {
    "iso:country":"ES",
    "sg:address":"Carrer de Industria, 135",
    "sg:city":"Barcelona",
    "sg:orig_category":"Institutos De Belleza",
    "sg:phone":"+34 934 36 87 66",
    "sg:postcode":"08025",
    "sg:province":"Barcelona",
    "wof:name":"Sanchez Vicente Agustina",
    "wof:placetype":"venue"
},
  "geometry": {"coordinates":[2.1729590893,41.4086532593],"type":"Point"}
}