{
  "type": "Feature",
  "properties": {
    "addr:full":"Calle de Sonsoles, 1 Leganes Madrid 28911",
    "addr:housenumber":"1",
    "addr:postcode":"28911",
    "addr:street":"Calle De Sonsoles",
    "iso:country":"ES",
    "sg:address":"Calle de Sonsoles, 1",
    "sg:city":"Leganes",
    "sg:orig_category":"Reposter\u00cdas",
    "sg:phone":"+34 916 93 50 07",
    "sg:postcode":"28911",
    "sg:province":"Madrid",
    "wof:name":"Gomez Cuadrado Francisco",
    "wof:placetype":"venue"
},
  "geometry": {"coordinates":[-3.7696459293,40.325843811],"type":"Point"}
}