{
  "type": "Feature",
  "properties": {
    "addr:full":"Calle de Campana (la), S/n Chorrillo Santa Cruz De Tenerife 38108",
    "addr:postcode":"38108",
    "addr:street":"Calle De Campana La S / N Chorrillo",
    "iso:country":"ES",
    "sg:address":"Calle de Campana (la), S/n",
    "sg:city":"Chorrillo",
    "sg:orig_category":"Transporte En General",
    "sg:phone":"+34 922 62 22 88",
    "sg:postcode":"38108",
    "sg:province":"Santa Cruz De Tenerife",
    "wof:name":"Anton Brito Maria Elena",
    "wof:placetype":"venue"
},
  "geometry": {"coordinates":[-16.3173675537,28.4172515869],"type":"Point"}
}