{
  "type": "Feature",
  "properties": {
    "iso:country":"ES",
    "sg:address":"Calle de Aguilar, 24",
    "sg:city":"Benameji",
    "sg:orig_category":"Arquitectos",
    "sg:phone":"+34 957 53 04 76",
    "sg:postcode":"14910",
    "sg:province":"C\u00f3rdoba",
    "wof:name":"Moran Moliz Juan",
    "wof:placetype":"venue"
},
  "geometry": {"coordinates":[-4.5412654877,37.2672157288],"type":"Point"}
}