{
  "type": "Feature",
  "properties": {
    "iso:country":"ES",
    "sg:address":"Calle de Manuel Lasala, 32",
    "sg:city":"Zaragoza",
    "sg:orig_category":"Agencias Y Agentes Comerciales, Representantes",
    "sg:phone":"+34 976 56 15 46",
    "sg:postcode":"50006",
    "sg:province":"Zaragoza",
    "wof:name":"Abou Khovdoud  Ahmad",
    "wof:placetype":"venue"
},
  "geometry": {"coordinates":[-0.894771,41.637894],"type":"Point"}
}