{
  "type": "Feature",
  "properties": {
    "iso:country":"ES",
    "sg:address":"Calle de Maestros Troveros, S/n",
    "sg:city":"Fuente Alamo",
    "sg:orig_category":"Molduras, Junquillos, Listones Y Molduras Perforadas",
    "sg:phone":"+34 968 59 66 57",
    "sg:postcode":"30320",
    "sg:province":"Murcia",
    "wof:name":"Surtel Comunicaciones S L",
    "wof:placetype":"venue"
},
  "geometry": {"coordinates":[-1.1709177494,37.7210044861],"type":"Point"}
}