{
  "type": "Feature",
  "properties": {
    "addr:full":"Carr Sant Pasqual, 1 Picanya Valencia 46210",
    "addr:housenumber":"1",
    "addr:postcode":"46210",
    "addr:street":"Carr Sant Pasqual",
    "iso:country":"ES",
    "sg:address":"Carr Sant Pasqual, 1",
    "sg:city":"Picanya",
    "sg:orig_category":"Producci\u00d3n De Abonos Y De Fertilizantes",
    "sg:phone":"+34 961 59 12 15",
    "sg:postcode":"46210",
    "sg:province":"Valencia",
    "wof:name":"Casaban Rubio Jose Alfredo",
    "wof:placetype":"venue"
},
  "geometry": {"coordinates":[-0.4383400083,39.437084198],"type":"Point"}
}