{
  "type": "Feature",
  "properties": {
    "addr:full":"Calle de Balbin, 11 Gijon Asturias 33209",
    "addr:housenumber":"11",
    "addr:postcode":"33209",
    "addr:street":"Calle De Balbin",
    "iso:country":"ES",
    "sg:address":"Calle de Balbin, 11",
    "sg:city":"Gijon",
    "sg:orig_category":"Molduras, Junquillos, Listones Y Molduras Perforadas",
    "sg:phone":"+34 985 14 96 45",
    "sg:postcode":"33209",
    "sg:province":"Asturias",
    "wof:name":"Sistelcom-telemensaje S.a.",
    "wof:placetype":"venue"
},
  "geometry": {"coordinates":[-5.6566648483,43.5301895142],"type":"Point"}
}