{
  "type": "Feature",
  "properties": {
    "addr:full":"Carrer de Alcudia, 58 Barcelona Barcelona 08016",
    "addr:housenumber":"58",
    "addr:postcode":"08016",
    "addr:street":"Carrer De Alcudia",
    "iso:country":"ES",
    "sg:address":"Carrer de Alcudia, 58",
    "sg:city":"Barcelona",
    "sg:orig_category":"Estancos",
    "sg:phone":"+34 933 54 84 18",
    "sg:postcode":"08016",
    "sg:province":"Barcelona",
    "wof:name":"Chueca Garcia Sergio",
    "wof:placetype":"venue"
},
  "geometry": {"coordinates":[2.1748580933,41.4363441467],"type":"Point"}
}