{
  "type": "Feature",
  "properties": {
    "iso:country":"ES",
    "sg:address":"Cant La Soledad, 5",
    "sg:city":"Vitoria-gasteiz",
    "sg:orig_category":"Arquitectos",
    "sg:phone":"+34 945 28 49 70",
    "sg:postcode":"01001",
    "sg:province":"\u00c1lava",
    "wof:name":"Lopez Martinez Mujika S.l.",
    "wof:placetype":"venue"
},
  "geometry": {"coordinates":[-2.6738600731,42.8484077454],"type":"Point"}
}