{
  "type": "Feature",
  "properties": {
    "iso:country":"ES",
    "sg:address":"Carrer de Rebato, S/n",
    "sg:city":"Abrera",
    "sg:orig_category":"Empresas De Hormig\u00d3n, Hormig\u00d3n Armado Y Pretensado",
    "sg:phone":"+34 937 70 02 59",
    "sg:postcode":"08630",
    "sg:province":"Barcelona",
    "wof:name":"Suberolita S. A.",
    "wof:placetype":"venue"
},
  "geometry": {"coordinates":[1.8946650028,41.5214347839],"type":"Point"}
}