{
  "type": "Feature",
  "properties": {
    "iso:country":"ES",
    "sg:address":"Av Jaume Recoder, 80",
    "sg:city":"Mataro",
    "sg:orig_category":"Abogados",
    "sg:phone":"+34 937 99 77 88",
    "sg:postcode":"08302",
    "sg:province":"Barcelona",
    "wof:name":"Bufet De Adelaida Molina S.l.",
    "wof:placetype":"venue"
},
  "geometry": {"coordinates":[2.4439139366,41.5332145691],"type":"Point"}
}