{
  "type": "Feature",
  "properties": {
    "iso:country":"ES",
    "sg:address":"C/ Cami (el), 86",
    "sg:city":"Alcoi",
    "sg:orig_category":"Comercio, Reparaci\u00d3n De Motocicletas, Bicicletas Y Piezas Sueltas",
    "sg:phone":"+34 965 54 81 41",
    "sg:postcode":"03801",
    "sg:province":"Alicante",
    "wof:name":"Compa\u00f1y Llopis Enrique",
    "wof:placetype":"venue"
},
  "geometry": {"coordinates":[-0.4770169854,38.6904220581],"type":"Point"}
}