{
  "type": "Feature",
  "properties": {
    "iso:country":"ES",
    "sg:address":"Calle de Santa Angela De La Cruz, S/n",
    "sg:city":"Villanueva Rio Y Minas",
    "sg:orig_category":"Partidos Pol\u00cdticos",
    "sg:phone":"+34 954 74 72 19",
    "sg:postcode":"41350",
    "sg:province":"Sevilla",
    "wof:name":"Partido Socialista Obrero Espa\u00f1ol",
    "wof:placetype":"venue"
},
  "geometry": {"coordinates":[-5.7130870819,37.6511688232],"type":"Point"}
}