{
  "type": "Feature",
  "properties": {
    "addr:full":"Plaz Mayor, S/n Santa Maria De Valverde Zamora 49333",
    "addr:housenumber":"s / n",
    "addr:postcode":"49333",
    "addr:street":"Plaz Mayor;Zamora",
    "iso:country":"ES",
    "sg:address":"Plaz Mayor, S/n",
    "sg:city":"Santa Maria De Valverde",
    "sg:orig_category":"Cr\u00cda De Bovinos",
    "sg:phone":"+34 980 65 82 11",
    "sg:postcode":"49333",
    "sg:province":"Zamora",
    "wof:name":"Hermanos Martin Junquera S.l.",
    "wof:placetype":"venue"
},
  "geometry": {"coordinates":[-5.9363341331,41.9346961975],"type":"Point"}
}