{
  "type": "Feature",
  "properties": {
    "iso:country":"ES",
    "sg:address":"Calle de Pintor Antonio Lopez, 7",
    "sg:city":"Navahermosa",
    "sg:orig_category":"Mec\u00c1nico Del Autom\u00d3vil",
    "sg:phone":"+34 925 42 86 00",
    "sg:postcode":"45150",
    "sg:province":"Toledo",
    "wof:name":"Gutierrez Sanchez Juan Manuel",
    "wof:placetype":"venue"
},
  "geometry": {"coordinates":[-4.4794588089,39.6354408264],"type":"Point"}
}