{
  "type": "Feature",
  "properties": {
    "iso:country":"ES",
    "sg:address":"Avda Viena (de), 6",
    "sg:city":"Coslada",
    "sg:orig_category":"Farmacias",
    "sg:phone":"+34 916 71 62 24",
    "sg:postcode":"28820",
    "sg:province":"Madrid",
    "wof:name":"Lobo Alonso Margarita",
    "wof:placetype":"venue"
},
  "geometry": {"coordinates":[-3.5426421165,40.4196662903],"type":"Point"}
}