{
  "type": "Feature",
  "properties": {
    "addr:full":"Calle de Mar (la), 10 Castro Urdiales Cantabria 39700",
    "addr:housenumber":"10",
    "addr:postcode":"39700",
    "addr:street":"Calle De Mar La",
    "iso:country":"ES",
    "sg:address":"Calle de Mar (la), 10",
    "sg:city":"Castro Urdiales",
    "sg:orig_category":"Cl\u00cdnicas Dentales",
    "sg:phone":"+34 942 86 47 45",
    "sg:postcode":"39700",
    "sg:province":"Cantabria",
    "wof:name":"Verdejo Ledesma Leyre",
    "wof:placetype":"venue"
},
  "geometry": {"coordinates":[-3.2183589935,43.3820724487],"type":"Point"}
}