{
  "type": "Feature",
  "properties": {
    "addr:full":"Avda Elizatxo, S/n Irun Guip\u00f9zcoa 20303",
    "addr:housenumber":"s / n",
    "addr:postcode":"20303",
    "addr:street":"Avda Elizatxo;Guipu\u0300Zcoa",
    "iso:country":"ES",
    "sg:address":"Avda Elizatxo, S/n",
    "sg:city":"Irun",
    "sg:orig_category":"Agentes, Concesionarios Y Sucursales De Veh\u00cdculos",
    "sg:phone":"+34 943 62 29 99",
    "sg:postcode":"20303",
    "sg:province":"Guip\u00f9zcoa",
    "wof:name":"Talleres Yarza S.a.",
    "wof:placetype":"venue"
},
  "geometry": {"coordinates":[-1.8043529987,43.3329353333],"type":"Point"}
}