{
  "type": "Feature",
  "properties": {
    "addr:full":"Calle de Pino Pi\u00d1onero, S/n Alcala Guadaira Sevilla 41500",
    "addr:housenumber":"s",
    "addr:postcode":"41500",
    "addr:street":"Calle De Pino Pin\u0303Onero;/ N",
    "iso:country":"ES",
    "sg:address":"Calle de Pino Pi\u00d1onero, S/n",
    "sg:city":"Alcala Guadaira",
    "sg:orig_category":"Frutas Y Legumbres Frescas (al Por Mayor)",
    "sg:phone":"+34 955 68 56 99",
    "sg:postcode":"41500",
    "sg:province":"Sevilla",
    "wof:name":"Aderezo De Aceitunas Del Aguila S.l.",
    "wof:placetype":"venue"
},
  "geometry": {"coordinates":[-5.851477623,37.3230857849],"type":"Point"}
}