{
  "type": "Feature",
  "properties": {
    "addr:full":"Avda Padre Mirabent, 4 Isla Cristina Huelva 21410",
    "addr:housenumber":"4",
    "addr:postcode":"21410",
    "addr:street":"Avda Padre Mirabent",
    "iso:country":"ES",
    "sg:address":"Avda Padre Mirabent, 4",
    "sg:city":"Isla Cristina",
    "sg:orig_category":"Molduras, Junquillos, Listones Y Molduras Perforadas",
    "sg:phone":"+34 959 34 35 08",
    "sg:postcode":"21410",
    "sg:province":"Huelva",
    "wof:name":"Grao Suarez Manuela",
    "wof:placetype":"venue"
},
  "geometry": {"coordinates":[-7.3286762238,37.2052841187],"type":"Point"}
}