{
  "type": "Feature",
  "properties": {
    "addr:full":"Calle de Rabal (el), 9 Hellin Albacete 02400",
    "addr:housenumber":"9",
    "addr:postcode":"02400",
    "addr:street":"Calle De Rabal El",
    "iso:country":"ES",
    "sg:address":"Calle de Rabal (el), 9",
    "sg:city":"Hellin",
    "sg:orig_category":"\u00d3ptica: Instrumentos (fabricaci\u00d3n)",
    "sg:phone":"+34 967 30 05 33",
    "sg:postcode":"02400",
    "sg:province":"Albacete",
    "wof:name":"Montajes Opticos De La Mancha S.l.",
    "wof:placetype":"venue"
},
  "geometry": {"coordinates":[-1.7010860443,38.5131835938],"type":"Point"}
}