{
  "type": "Feature",
  "properties": {
    "iso:country":"ES",
    "sg:address":"El Bergal, S/n",
    "sg:city":"S. Adrian",
    "sg:orig_category":"Ferreter\u00cda (diversos)",
    "sg:phone":"+34 948 67 28 34",
    "sg:postcode":"31570",
    "sg:province":"Navarra",
    "wof:name":"Recuperacion De Chatarras La Pinilla S.a.",
    "wof:placetype":"venue"
},
  "geometry": {"coordinates":[-1.9321240187,42.33335495],"type":"Point"}
}