{
  "type": "Feature",
  "properties": {
    "addr:full":"Perello, 112 Torrent Valencia 46900",
    "addr:housenumber":"112",
    "addr:postcode":"46900",
    "addr:street":"Perello;Valencia",
    "iso:country":"ES",
    "sg:address":"Perello, 112",
    "sg:city":"Torrent",
    "sg:orig_category":"Plomeros",
    "sg:phone":"+34 961 55 38 38",
    "sg:postcode":"46900",
    "sg:province":"Valencia",
    "wof:name":"Francisco Carrascosa S.l.",
    "wof:placetype":"venue"
},
  "geometry": {"coordinates":[-0.4949820042,39.4378852844],"type":"Point"}
}