{
  "type": "Feature",
  "properties": {
    "addr:full":"Pg Zona Franca, 230 Barcelona Barcelona 08038",
    "addr:housenumber":"230",
    "addr:postcode":"08038",
    "addr:street":"Pg Zona Franca",
    "iso:country":"ES",
    "sg:address":"Pg Zona Franca, 230",
    "sg:city":"Barcelona",
    "sg:orig_category":"Tintes (fabricaci\u00d3n, Al Por Mayor)",
    "sg:phone":"+34 933 32 03 48",
    "sg:postcode":"08038",
    "sg:province":"Barcelona",
    "wof:name":"Cortes Soto Victor",
    "wof:placetype":"venue"
},
  "geometry": {"coordinates":[2.137567997,41.3625984192],"type":"Point"}
}