{
  "type": "Feature",
  "properties": {
    "iso:country":"ES",
    "sg:address":"Calle de Etxezarra, 37",
    "sg:city":"Vitoria-gasteiz",
    "sg:orig_category":"Asilos De Ancianos. Centros Privados",
    "sg:phone":"+34 945 23 02 00",
    "sg:postcode":"01007",
    "sg:province":"\u00c1lava",
    "wof:name":"Religiosas Oblatas Del Santisimo Redentor",
    "wof:placetype":"venue"
},
  "geometry": {"coordinates":[-2.6932690144,42.8449516296],"type":"Point"}
}