{
  "type": "Feature",
  "properties": {
    "addr:full":"Avda Mediterraneo, 64 Benidorm Alicante 03500",
    "addr:housenumber":"64",
    "addr:postcode":"03500",
    "addr:street":"Avda Mediterraneo",
    "iso:country":"ES",
    "sg:address":"Avda Mediterraneo, 64",
    "sg:city":"Benidorm",
    "sg:orig_category":"Panader\u00cdas, Panader\u00cdas",
    "sg:phone":"+34 966 80 38 36",
    "sg:postcode":"03500",
    "sg:province":"Alicante",
    "wof:name":"Centeno Morillo Maria Angeles",
    "wof:placetype":"venue"
},
  "geometry": {"coordinates":[-0.1084320024,38.5349311829],"type":"Point"}
}