{
  "type": "Feature",
  "properties": {
    "addr:full":"Calle de Santa Ana Alta, 29 Madrid Madrid 28034",
    "addr:housenumber":"29",
    "addr:postcode":"madrid;28034",
    "addr:street":"Calle De Santa;Alta",
    "iso:country":"ES",
    "sg:address":"Calle de Santa Ana Alta, 29",
    "sg:city":"Madrid",
    "sg:orig_category":"Plomeros",
    "sg:phone":"+34 917 35 30 50",
    "sg:postcode":"28034",
    "sg:province":"Madrid",
    "wof:name":"Saneamientos Santana C.b.",
    "wof:placetype":"venue"
},
  "geometry": {"coordinates":[-3.6895990372,40.495929718],"type":"Point"}
}