{
  "type": "Feature",
  "properties": {
    "iso:country":"ES",
    "sg:address":"Calle de Jamaica, 18",
    "sg:city":"Tablero",
    "sg:orig_category":"Promotores Constructores",
    "sg:phone":"+34 928 14 51 56",
    "sg:postcode":"35100",
    "sg:province":"Las Palmas",
    "wof:name":"Lopesan Asfaltos Y Construcciones S.a.",
    "wof:placetype":"venue"
},
  "geometry": {"coordinates":[-15.6045703888,27.7714385986],"type":"Point"}
}