{
  "type": "Feature",
  "properties": {
    "addr:full":"Carrer de Tarragona, 108 Barcelona Barcelona 08015",
    "addr:housenumber":"108",
    "addr:postcode":"08015",
    "addr:street":"Carrer De Tarragona",
    "iso:country":"ES",
    "sg:address":"Carrer de Tarragona, 108",
    "sg:city":"Barcelona",
    "sg:orig_category":"Iglesias Cristianas Diversas",
    "sg:phone":"+34 932 26 88 48",
    "sg:postcode":"08015",
    "sg:province":"Barcelona",
    "wof:name":"Iglesia De Cristo",
    "wof:placetype":"venue"
},
  "geometry": {"coordinates":[2.1440150738,41.379650116],"type":"Point"}
}