{
  "type": "Feature",
  "properties": {
    "iso:country":"ES",
    "sg:address":"Calle de Estadio, 9",
    "sg:city":"Valladolid",
    "sg:orig_category":"Arquitectos",
    "sg:phone":"+34 983 47 33 35",
    "sg:postcode":"47006",
    "sg:province":"Valladolid",
    "wof:name":"Hernandez Rodriguez Francisco",
    "wof:placetype":"venue"
},
  "geometry": {"coordinates":[-4.7402682304,41.639465332],"type":"Point"}
}