{
  "type": "Feature",
  "properties": {
    "iso:country":"ES",
    "sg:address":"Calle de Antonio De Ulloa, 2",
    "sg:city":"Flota",
    "sg:orig_category":"Peluquer\u00cdas, Peluquer\u00cda Mixta",
    "sg:phone":"+34 968 23 98 47",
    "sg:postcode":"30008",
    "sg:province":"Murcia",
    "wof:name":"Gallego Ortega Francisco Javier",
    "wof:placetype":"venue"
},
  "geometry": {"coordinates":[-1.1298867464,37.9834747314],"type":"Point"}
}