{
  "type": "Feature",
  "properties": {
    "addr:full":"Carrer de Joan Guell, 165 Barcelona Barcelona 08028",
    "addr:housenumber":"165",
    "addr:postcode":"08028",
    "addr:street":"Carrer De Joan Guell",
    "iso:country":"ES",
    "sg:address":"Carrer de Joan Guell, 165",
    "sg:city":"Barcelona",
    "sg:orig_category":"Fabricaci\u00d3n, Comercio De Bol\u00cdgrafos Y L\u00c1pices",
    "sg:phone":"+34 934 09 05 80",
    "sg:postcode":"08028",
    "sg:province":"Barcelona",
    "wof:name":"Styb S. A.",
    "wof:placetype":"venue"
},
  "geometry": {"coordinates":[2.1310899258,41.3832702637],"type":"Point"}
}