{
  "type": "Feature",
  "properties": {
    "iso:country":"ES",
    "sg:address":"Calle de Palacio Valdes, 31",
    "sg:city":"Salamanca",
    "sg:orig_category":"Institutos De Belleza",
    "sg:phone":"+34 923 25 90 88",
    "sg:postcode":"37007",
    "sg:province":"Salamanca",
    "wof:name":"Felipe Casta\u00f1o Maria Jesus",
    "wof:placetype":"venue"
},
  "geometry": {"coordinates":[-5.6698999405,40.9712944031],"type":"Point"}
}