{
  "type": "Feature",
  "properties": {
    "iso:country":"ES",
    "sg:address":"Pla\u00e7a, S/n",
    "sg:city":"Orcau",
    "sg:orig_category":"Centros De Educaci\u00d3n Especial",
    "sg:phone":"+34 973 25 23 16",
    "sg:postcode":"25655",
    "sg:province":"Lleida",
    "wof:name":"Ayuntamiento De Isona Y Conca D'alla. Is",
    "wof:placetype":"venue"
},
  "geometry": {"coordinates":[0.9950960279,42.1314506531],"type":"Point"}
}