{
  "type": "Feature",
  "properties": {
    "iso:country":"ES",
    "sg:address":"Calle de Real, 75",
    "sg:city":"S. Fernando",
    "sg:orig_category":"Molduras, Junquillos, Listones Y Molduras Perforadas",
    "sg:phone":"+34 956 89 63 89",
    "sg:postcode":"11100",
    "sg:province":"C\u00e1diz",
    "wof:name":"Gonzalez Torre Manuel",
    "wof:placetype":"venue"
},
  "geometry": {"coordinates":[-6.1936240196,36.4668235779],"type":"Point"}
}