{
  "type": "Feature",
  "properties": {
    "iso:country":"ES",
    "sg:address":"Plaz Mayor, S/n",
    "sg:city":"Calvarrasa Arriba",
    "sg:orig_category":"Iglesia Cat\u00d3lica",
    "sg:phone":"+34 923 37 34 22",
    "sg:postcode":"37191",
    "sg:province":"Salamanca",
    "wof:name":"Obispado De Salamanca",
    "wof:placetype":"venue"
},
  "geometry": {"coordinates":[-5.6307687759,40.9287757874],"type":"Point"}
}