{
  "type": "Feature",
  "properties": {
    "addr:full":"Calle de Puentezuelas, 41 Granada Granada 18002",
    "addr:housenumber":"41",
    "addr:postcode":"18002",
    "addr:street":"Calle De Puentezuelas",
    "iso:country":"ES",
    "sg:address":"Calle de Puentezuelas, 41",
    "sg:city":"Granada",
    "sg:orig_category":"Bazares, Art\u00cdculos De Limpieza Y De Cocina (al Por Menor)",
    "sg:phone":"+34 958 52 29 79",
    "sg:postcode":"18002",
    "sg:province":"Granada",
    "wof:name":"Francisco Romero Ortega,s.l",
    "wof:placetype":"venue"
},
  "geometry": {"coordinates":[-3.6023590565,37.1742744446],"type":"Point"}
}