{
  "type": "Feature",
  "properties": {
    "iso:country":"ES",
    "sg:address":"Calle de San Cipriano, 30",
    "sg:city":"Madrid",
    "sg:orig_category":"Molduras, Junquillos, Listones Y Molduras Perforadas",
    "sg:phone":"+34 913 71 87 69",
    "sg:postcode":"28032",
    "sg:province":"Madrid",
    "wof:name":"Moreno Guillen Raquel",
    "wof:placetype":"venue"
},
  "geometry": {"coordinates":[-3.606085062,40.4039649963],"type":"Point"}
}