{
  "type": "Feature",
  "properties": {
    "addr:full":"Calle de Gran Via, 26 Zaragoza Zaragoza 50005",
    "addr:housenumber":"26",
    "addr:postcode":"50005",
    "addr:street":"Calle De Gran Via",
    "iso:country":"ES",
    "sg:address":"Calle de Gran Via, 26",
    "sg:city":"Zaragoza",
    "sg:orig_category":"Florister\u00cdas",
    "sg:phone":"+34 976 23 57 65",
    "sg:postcode":"50005",
    "sg:province":"Zaragoza",
    "sg:website":"www.selvalia.com",
    "wof:name":"La Selva Del Canal S.l.",
    "wof:placetype":"venue"
},
  "geometry": {"coordinates":[-0.8886418939,41.6460456848],"type":"Point"}
}