{
  "type": "Feature",
  "properties": {
    "addr:full":"Calle de Jacometrezo, 4 Madrid Madrid 28013",
    "addr:housenumber":"4",
    "addr:postcode":"28013",
    "addr:street":"Calle De Jacometrezo",
    "iso:country":"ES",
    "sg:address":"Calle de Jacometrezo, 4",
    "sg:city":"Madrid",
    "sg:orig_category":"Infograf\u00cda",
    "sg:phone":"+34 915 23 42 23",
    "sg:postcode":"28013",
    "sg:province":"Madrid",
    "wof:name":"Tirity Studio S L",
    "wof:placetype":"venue"
},
  "geometry": {"coordinates":[-3.7068200111,40.4203147888],"type":"Point"}
}