{
  "type": "Feature",
  "properties": {
    "addr:full":"Calle de Colon, 19 Palencia Palencia 34002",
    "addr:housenumber":"19",
    "addr:postcode":"34002",
    "addr:street":"Calle De Colon",
    "iso:country":"ES",
    "sg:address":"Calle de Colon, 19",
    "sg:city":"Palencia",
    "sg:orig_category":"Agencias De Trabajo Temporal",
    "sg:phone":"+34 979 70 65 16",
    "sg:postcode":"34002",
    "sg:province":"Palencia",
    "sg:website":"www.adecco.es",
    "wof:name":"Adecco E.t.t. S.a.",
    "wof:placetype":"venue"
},
  "geometry": {"coordinates":[-4.5311641693,42.0085144043],"type":"Point"}
}