{
  "type": "Feature",
  "properties": {
    "addr:full":"Calle de Virgen De Los Arcos, 8 Alca\u00f1iz Teruel 44600",
    "addr:housenumber":"8",
    "addr:postcode":"44600",
    "addr:street":"Calle De Virgen De Los Arcos",
    "iso:country":"ES",
    "sg:address":"Calle de Virgen De Los Arcos, 8",
    "sg:city":"Alca\u00f1iz",
    "sg:orig_category":"Empresas De Desmonte",
    "sg:phone":"+34 978 83 26 59",
    "sg:postcode":"44600",
    "sg:province":"Teruel",
    "wof:name":"Bernal Alquezar Juan Jose",
    "wof:placetype":"venue"
},
  "geometry": {"coordinates":[-0.1322589964,41.0473213196],"type":"Point"}
}