{
  "type": "Feature",
  "properties": {
    "iso:country":"ES",
    "sg:address":"Avda Juan Xxiii, S/n",
    "sg:city":"Sevilla",
    "sg:orig_category":"Iglesia Cat\u00d3lica",
    "sg:phone":"+34 954 63 74 96",
    "sg:postcode":"41006",
    "sg:province":"Sevilla",
    "wof:name":"Parroquia La Anunciacion De Nuestra Se\u00f1ora",
    "wof:placetype":"venue"
},
  "geometry": {"coordinates":[-5.9536290169,37.3796310425],"type":"Point"}
}