{
  "type": "Feature",
  "properties": {
    "iso:country":"ES",
    "sg:address":"Avda Garcia Doriga, 3",
    "sg:city":"Viveiro",
    "sg:orig_category":"Ropa Para Se\u00d1oras (al Por Menor)",
    "sg:phone":"+34 982 55 10 70",
    "sg:postcode":"27850",
    "sg:province":"Lugo",
    "wof:name":"Davosplus S.l.",
    "wof:placetype":"venue"
},
  "geometry": {"coordinates":[-7.5960731506,43.6601753235],"type":"Point"}
}