{
  "type": "Feature",
  "properties": {
    "addr:full":"Ptda Partida Azagador, S/n Barraca D'aigues Vives Valencia 46792",
    "addr:housenumber":"s / n",
    "addr:postcode":"46792",
    "addr:street":"Ptda Partida Azagador;Barraca D'Aigues",
    "iso:country":"ES",
    "sg:address":"Ptda Partida Azagador, S/n",
    "sg:city":"Barraca D'aigues Vives",
    "sg:orig_category":"Empresas De Hormig\u00d3n, Hormig\u00d3n Armado Y Pretensado",
    "sg:phone":"+34 962 58 91 04",
    "sg:postcode":"46792",
    "sg:province":"Valencia",
    "wof:name":"Perello Diez Alberto",
    "wof:placetype":"venue"
},
  "geometry": {"coordinates":[-0.33366099,39.4609527588],"type":"Point"}
}