{
  "type": "Feature",
  "properties": {
    "iso:country":"ES",
    "sg:address":"Avda Trece De Octubre, 9",
    "sg:city":"Alcazares",
    "sg:orig_category":"Electricidad: Instaladores",
    "sg:phone":"+34 968 17 13 72",
    "sg:postcode":"30710",
    "sg:province":"Murcia",
    "wof:name":"Mafeso Electricidad S.l.",
    "wof:placetype":"venue"
},
  "geometry": {"coordinates":[-0.851360023,37.7382545471],"type":"Point"}
}