{
  "type": "Feature",
  "properties": {
    "iso:country":"ES",
    "sg:address":"Avda America, 8",
    "sg:city":"Santa Fe",
    "sg:orig_category":"Productos Fitosanitarios (negocio, Aplicaci\u00d3n)",
    "sg:phone":"+34 958 51 04 35",
    "sg:postcode":"18320",
    "sg:province":"Granada",
    "wof:name":"Kenogard S. A.",
    "wof:placetype":"venue"
},
  "geometry": {"coordinates":[-3.7276439667,37.1891403198],"type":"Point"}
}