{
  "type": "Feature",
  "properties": {
    "addr:full":"Calle de Canovas Del Castillo, 62 Jumilla Murcia 30520",
    "addr:housenumber":"62",
    "addr:postcode":"30520",
    "addr:street":"Calle De Canovas Del Castillo",
    "iso:country":"ES",
    "sg:address":"Calle de Canovas Del Castillo, 62",
    "sg:city":"Jumilla",
    "sg:orig_category":"Mercer\u00cda, Lencer\u00cda (al Por Menor)",
    "sg:phone":"+34 968 78 01 53",
    "sg:postcode":"30520",
    "sg:province":"Murcia",
    "wof:name":"Rodriguez Marin Maria Dolores",
    "wof:placetype":"venue"
},
  "geometry": {"coordinates":[-1.3278179169,38.4745330811],"type":"Point"}
}