{
  "type": "Feature",
  "properties": {
    "iso:country":"ES",
    "sg:address":"Carrer de Riera Bonet, 12",
    "sg:city":"Molins Rei",
    "sg:orig_category":"Promotores Constructores",
    "sg:phone":"+34 936 80 09 62",
    "sg:postcode":"08750",
    "sg:province":"Barcelona",
    "wof:name":"Ucedas 2001 S.l.",
    "wof:placetype":"venue"
},
  "geometry": {"coordinates":[2.0164849758,41.414604187],"type":"Point"}
}