{
  "type": "Feature",
  "properties": {
    "addr:full":"Calle de General Mola, 12 Peraleda San Roman C\u00e1ceres 10334",
    "addr:housenumber":"12",
    "addr:postcode":"10334",
    "addr:street":"Calle De General Mola;San;Ca\u0301Ceres",
    "iso:country":"ES",
    "sg:address":"Calle de General Mola, 12",
    "sg:city":"Peraleda San Roman",
    "sg:orig_category":"Aceites Y Grasas Alimentarias (fabricaci\u00d3n, Al Por Mayor)",
    "sg:phone":"+34 927 55 30 18",
    "sg:postcode":"10334",
    "sg:province":"C\u00e1ceres",
    "wof:name":"Arroyo Rodriguez Lorenzo",
    "wof:placetype":"venue"
},
  "geometry": {"coordinates":[-5.3882703781,39.7416954041],"type":"Point"}
}