{
  "type": "Feature",
  "properties": {
    "iso:country":"ES",
    "sg:address":"V. Castillo, 12",
    "sg:city":"Iru\u00f1a",
    "sg:orig_category":"Agencias Y Agentes Comerciales, Representantes",
    "sg:phone":"+34 948 21 08 40",
    "sg:postcode":"31001",
    "sg:province":"Navarra",
    "wof:name":"Aroyo Rodriguez Monse",
    "wof:placetype":"venue"
},
  "geometry": {"coordinates":[-1.6422003508,42.8169975281],"type":"Point"}
}