{
  "type": "Feature",
  "properties": {
    "addr:full":"Carr Mercado, 6 Oliva Valencia 46780",
    "addr:housenumber":"6",
    "addr:postcode":"46780",
    "addr:street":"Carr Mercado",
    "iso:country":"ES",
    "sg:address":"Carr Mercado, 6",
    "sg:city":"Oliva",
    "sg:orig_category":"Guarder\u00cdas",
    "sg:phone":"+34 962 85 36 56",
    "sg:postcode":"46780",
    "sg:province":"Valencia",
    "wof:name":"Cardona Gasco Rosa Maria",
    "wof:placetype":"venue"
},
  "geometry": {"coordinates":[-0.1179220006,38.9189491272],"type":"Point"}
}