{
  "type": "Feature",
  "properties": {
    "addr:full":"Calle de Carretera Pantano, S/n Cuevas San Marcos M\u00e1laga 29210",
    "addr:housenumber":"s / n",
    "addr:postcode":"29210",
    "addr:street":"Calle De Carretera Pantano",
    "iso:country":"ES",
    "sg:address":"Calle de Carretera Pantano, S/n",
    "sg:city":"Cuevas San Marcos",
    "sg:orig_category":"Equipo De Refrigeraci\u00d3n Industrial",
    "sg:phone":"+34 952 71 90 11",
    "sg:postcode":"29210",
    "sg:province":"M\u00e1laga",
    "wof:name":"Refrigeracion Belda S.l",
    "wof:placetype":"venue"
},
  "geometry": {"coordinates":[-4.4142560959,37.2651977539],"type":"Point"}
}