{
  "type": "Feature",
  "properties": {
    "iso:country":"ES",
    "sg:address":"Calle de Parras, 16",
    "sg:city":"Fuente Palmera",
    "sg:orig_category":"Carnicer\u00cdas, Carnicer\u00cdas",
    "sg:phone":"+34 957 63 80 60",
    "sg:postcode":"14120",
    "sg:province":"C\u00f3rdoba",
    "wof:name":"Rossi Mengual Juan",
    "wof:placetype":"venue"
},
  "geometry": {"coordinates":[-5.1061577797,37.7031784058],"type":"Point"}
}