{
  "type": "Feature",
  "properties": {
    "iso:country":"ES",
    "sg:address":"Calle de Doctor Pasteur, 12",
    "sg:city":"San Cristobal De La Laguna",
    "sg:orig_category":"Congelados: Productos Alimentarios (al Por Menor)",
    "sg:phone":"+34 922 25 57 17",
    "sg:postcode":"38205",
    "sg:province":"Santa Cruz De Tenerife",
    "wof:name":"Gonzalez Perez Francisco",
    "wof:placetype":"venue"
},
  "geometry": {"coordinates":[-16.311006546,28.4801578522],"type":"Point"}
}