{
  "type": "Feature",
  "properties": {
    "iso:country":"ES",
    "sg:address":"Ctra Algete (de), Km. 0005,0",
    "sg:city":"Nogal",
    "sg:orig_category":"Material Y Suministros Para Imprenta E Industrias Gr\u00c1ficas",
    "sg:phone":"+34 916 28 03 60",
    "sg:postcode":"28110",
    "sg:province":"Madrid",
    "sg:website":"www.printerman.es",
    "wof:name":"Printerman Industrias Graficas S.a.",
    "wof:placetype":"venue"
},
  "geometry": {"coordinates":[-3.4999940395,40.5979003906],"type":"Point"}
}