{
  "type": "Feature",
  "properties": {
    "addr:full":"Calle de Nicolas Usera, 10 Madrid Madrid 28026",
    "addr:housenumber":"10",
    "addr:postcode":"madrid;28026",
    "addr:street":"Calle De Nicolas Usera",
    "iso:country":"ES",
    "sg:address":"Calle de Nicolas Usera, 10",
    "sg:city":"Madrid",
    "sg:orig_category":"Empresas De Electricidad En General",
    "sg:phone":"+34 915 00 60 51",
    "sg:postcode":"28026",
    "sg:province":"Madrid",
    "wof:name":"Gestra Electricidad Y Servicios S.l.",
    "wof:placetype":"venue"
},
  "geometry": {"coordinates":[-3.7060329914,40.3864860535],"type":"Point"}
}