{
  "type": "Feature",
  "properties": {
    "iso:country":"ES",
    "sg:address":"Calle de Butron, 8",
    "sg:city":"Madrid",
    "sg:orig_category":"Inform\u00c1tica Equipo Y Programas (al Por Mayor)",
    "sg:phone":"+34 917 60 07 88",
    "sg:postcode":"28022",
    "sg:province":"Madrid",
    "sg:website":"www.quvo.net",
    "wof:name":"Nieto Fernandez Alejandro Jesus",
    "wof:placetype":"venue"
},
  "geometry": {"coordinates":[-3.6097364426,40.4250793457],"type":"Point"}
}