{
  "type": "Feature",
  "properties": {
    "addr:full":"Calle de Chera, 46 Requena Valencia 46340",
    "addr:housenumber":"46",
    "addr:postcode":"46340",
    "addr:street":"Calle De Chera",
    "iso:country":"ES",
    "sg:address":"Calle de Chera, 46",
    "sg:city":"Requena",
    "sg:orig_category":"Chapister\u00cda",
    "sg:phone":"+34 962 30 16 05",
    "sg:postcode":"46340",
    "sg:province":"Valencia",
    "wof:name":"Gomez Martinez Francisco",
    "wof:placetype":"venue"
},
  "geometry": {"coordinates":[-1.0998133421,39.4916992188],"type":"Point"}
}