{
  "type": "Feature",
  "properties": {
    "iso:country":"ES",
    "sg:address":"Calle de San Miguel, 2",
    "sg:city":"Cortes",
    "sg:orig_category":"Artes Gr\u00c1ficas, Artes Pl\u00c1sticas (curso)",
    "sg:phone":"+34 948 84 41 00",
    "sg:postcode":"31530",
    "sg:province":"Navarra",
    "wof:name":"Urdaniz Preimpresion S.l.",
    "wof:placetype":"venue"
},
  "geometry": {"coordinates":[-1.4209090471,41.921421051],"type":"Point"}
}