{
  "type": "Feature",
  "properties": {
    "iso:country":"ES",
    "sg:address":"Calle de Actor Mora, 1",
    "sg:city":"Valencia",
    "sg:orig_category":"Inmobiliaria (agencias)",
    "sg:phone":"+34 963 17 33 33",
    "sg:postcode":"46009",
    "sg:province":"Valencia",
    "sg:website":"www.bienesraices.inmobiliarias",
    "wof:name":"Abil Event S.l.",
    "wof:placetype":"venue"
},
  "geometry": {"coordinates":[-0.374944,39.486454],"type":"Point"}
}