{
  "type": "Feature",
  "properties": {
    "addr:full":"B. Escobar, 25 Las Norias Almer\u00eda 04716",
    "addr:housenumber":"25",
    "addr:postcode":"04716",
    "addr:street":"Escobar;Norias Almeri\u0301A",
    "iso:country":"ES",
    "sg:address":"B. Escobar, 25",
    "sg:city":"Las Norias",
    "sg:orig_category":"Frutos Y Legumbres",
    "sg:phone":"+34 950 60 68 82",
    "sg:postcode":"04716",
    "sg:province":"Almer\u00eda",
    "wof:name":"Jose Maria Maleno Y Gracia Torres S.l.",
    "wof:placetype":"venue"
},
  "geometry": {"coordinates":[-2.7523419857,36.758895874],"type":"Point"}
}