{
  "type": "Feature",
  "properties": {
    "addr:full":"Calle de Cruz Del Rio, 67 Villanueva Serena Badajoz 06700",
    "addr:housenumber":"67",
    "addr:postcode":"06700",
    "addr:street":"Calle De Cruz Del Rio",
    "iso:country":"ES",
    "sg:address":"Calle de Cruz Del Rio, 67",
    "sg:city":"Villanueva Serena",
    "sg:orig_category":"Peluquer\u00cdas, Peluquer\u00cda Mixta",
    "sg:phone":"+34 924 84 77 87",
    "sg:postcode":"06700",
    "sg:province":"Badajoz",
    "wof:name":"Corraliza Romero Maria Isabel",
    "wof:placetype":"venue"
},
  "geometry": {"coordinates":[-5.7959570885,38.9796981812],"type":"Point"}
}