{
  "type": "Feature",
  "properties": {
    "iso:country":"ES",
    "sg:address":"Calle de Pino Canario, 5",
    "sg:city":"Tenoya",
    "sg:orig_category":"Electricidad: Instaladores",
    "sg:phone":"+34 928 67 24 65",
    "sg:postcode":"35018",
    "sg:province":"Las Palmas",
    "wof:name":"Macias Benitez Domingo",
    "wof:placetype":"venue"
},
  "geometry": {"coordinates":[-15.4940958023,28.1123714447],"type":"Point"}
}