{
  "type": "Feature",
  "properties": {
    "iso:country":"ES",
    "sg:address":"Calle de Navarro Villoslada, 1",
    "sg:city":"Vitoria-gasteiz",
    "sg:orig_category":"Estancos",
    "sg:phone":"+34 945 24 77 30",
    "sg:postcode":"01012",
    "sg:province":"\u00c1lava",
    "wof:name":"Atiega Sagredo, Lourdes",
    "wof:placetype":"venue"
},
  "geometry": {"coordinates":[-2.6794025898,42.8536109924],"type":"Point"}
}