{
  "type": "Feature",
  "properties": {
    "iso:country":"ES",
    "sg:address":"Pol. Ind. Congost, S/n",
    "sg:city":"La Garriga",
    "sg:orig_category":"Centros Empresariales",
    "sg:phone":"+34 938 71 84 04",
    "sg:postcode":"08530",
    "sg:province":"Barcelona",
    "wof:name":"1948 Associats S.l.",
    "wof:placetype":"venue"
},
  "geometry": {"coordinates":[2.277813,41.693348],"type":"Point"}
}