{
  "type": "Feature",
  "properties": {
    "iso:country":"ES",
    "sg:address":"Calle de Fernando Casariego, 28",
    "sg:city":"Langreo",
    "sg:orig_category":"Molduras, Junquillos, Listones Y Molduras Perforadas",
    "sg:phone":"+34 985 66 99 06",
    "sg:postcode":"33930",
    "sg:province":"Asturias",
    "wof:name":"Telefonos Publicos Y Privados S.l.",
    "wof:placetype":"venue"
},
  "geometry": {"coordinates":[-5.6966438293,43.3077964783],"type":"Point"}
}