{
  "type": "Feature",
  "properties": {
    "iso:country":"ES",
    "sg:address":"Calle de Santo Domingo, 12",
    "sg:city":"G\u00fcimar",
    "sg:orig_category":"Comercio De Piezas De Recambio Y De Accesorios De Veh\u00cdculos, Veh\u00cdculos Industriales",
    "sg:phone":"+34 922 51 11 65",
    "sg:postcode":"38500",
    "sg:province":"Santa Cruz De Tenerife",
    "wof:name":"Alejo Hernandez-castro Arcadio",
    "wof:placetype":"venue"
},
  "geometry": {"coordinates":[-16.4112682343,28.3149757385],"type":"Point"}
}