{
  "type": "Feature",
  "properties": {
    "iso:country":"ES",
    "sg:address":"Ctra Trassierra (extrarradio), Km. 0002,7",
    "sg:city":"Cordoba",
    "sg:orig_category":"Negocio De Materiales De Construcci\u00d3n",
    "sg:phone":"+34 957 27 95 01",
    "sg:postcode":"14011",
    "sg:province":"C\u00f3rdoba",
    "wof:name":"Azulejera Ceramica Cordobesa S.l.",
    "wof:placetype":"venue"
},
  "geometry": {"coordinates":[-4.9247074127,37.9286117554],"type":"Point"}
}