{
  "type": "Feature",
  "properties": {
    "iso:country":"ES",
    "sg:address":"Carr Esglesia, 6",
    "sg:city":"Mao",
    "sg:orig_category":"Asesor\u00cda Fiscal Y Jur\u00cddica",
    "sg:phone":"+34 971 35 06 04",
    "sg:postcode":"07701",
    "sg:province":"Islas Baleares",
    "wof:name":"Sintes Benejam Carlos",
    "wof:placetype":"venue"
},
  "geometry": {"coordinates":[4.2639331818,39.8893508911],"type":"Point"}
}