{
  "type": "Feature",
  "properties": {
    "addr:full":"Pl Sant Joan, 17 Berga-ciudad Barcelona 08600",
    "addr:housenumber":"17",
    "addr:postcode":"08600",
    "addr:street":"Pl Sant Joan;Barcelona",
    "iso:country":"ES",
    "sg:address":"Pl Sant Joan, 17",
    "sg:city":"Berga-ciudad",
    "sg:orig_category":"Lencer\u00cda Femenina, Corseter\u00cda, Trajes De Ba\u00d1o (al Por Menor)",
    "sg:phone":"+34 938 21 00 03",
    "sg:postcode":"08600",
    "sg:province":"Barcelona",
    "wof:name":"Hdi S.c.p",
    "wof:placetype":"venue"
},
  "geometry": {"coordinates":[1.8446999788,42.1021461487],"type":"Point"}
}