{
  "type": "Feature",
  "properties": {
    "addr:full":"Carrer de Sant Antoni, 13 Sitges Barcelona 08870",
    "addr:housenumber":"13",
    "addr:postcode":"08870",
    "addr:street":"Carrer De Sant Antoni",
    "iso:country":"ES",
    "sg:address":"Carrer de Sant Antoni, 13",
    "sg:city":"Sitges",
    "sg:orig_category":"Inform\u00c1tica (estudios, Servicios, Asesor\u00cda, Formaci\u00d3n)",
    "sg:phone":"+34 938 11 10 94",
    "sg:postcode":"08870",
    "sg:province":"Barcelona",
    "wof:name":"Siemens S.a.",
    "wof:placetype":"venue"
},
  "geometry": {"coordinates":[1.8053250313,41.2349357605],"type":"Point"}
}