{
  "type": "Feature",
  "properties": {
    "iso:country":"ES",
    "sg:address":"Av Diagonal, 566",
    "sg:city":"Barcelona",
    "sg:orig_category":"M\u00c9dicos: Medicina Manual",
    "sg:phone":"+34 932 41 12 02",
    "sg:postcode":"08021",
    "sg:province":"Barcelona",
    "wof:name":"Rosa Sempere Alberto",
    "wof:placetype":"venue"
},
  "geometry": {"coordinates":[2.1498799324,41.3944206238],"type":"Point"}
}