{
  "type": "Feature",
  "properties": {
    "iso:country":"ES",
    "sg:address":"S. Domingo, 7",
    "sg:city":"Gandesa",
    "sg:orig_category":"Panader\u00cdas, Panader\u00cdas",
    "sg:phone":"+34 977 42 00 83",
    "sg:postcode":"43780",
    "sg:province":"Tarragona",
    "wof:name":"Pujol Pastisseries S.l.",
    "wof:placetype":"venue"
},
  "geometry": {"coordinates":[0.4384000003,41.0540313721],"type":"Point"}
}