{
  "type": "Feature",
  "properties": {
    "iso:country":"ES",
    "sg:address":"Calle de Clara Del Rey, 31",
    "sg:city":"Madrid",
    "sg:orig_category":"M\u00c9dicos: An\u00c1lisis Cl\u00cdnicos",
    "sg:phone":"+34 915 62 41 96",
    "sg:postcode":"28002",
    "sg:province":"Madrid",
    "sg:website":"www.bial.com",
    "wof:name":"Bial-industrial Farmaceutica S.a.",
    "wof:placetype":"venue"
},
  "geometry": {"coordinates":[-3.6714100838,40.4418182373],"type":"Point"}
}