{
  "type": "Feature",
  "properties": {
    "iso:country":"ES",
    "sg:address":"Calle de Alfonso Xii, 91",
    "sg:city":"Mostoles",
    "sg:orig_category":"Artes Gr\u00c1ficas, Artes Pl\u00c1sticas (curso)",
    "sg:phone":"+34 916 46 72 57",
    "sg:postcode":"28938",
    "sg:province":"Madrid",
    "wof:name":"Arroyo Majano Jose Luis",
    "wof:placetype":"venue"
},
  "geometry": {"coordinates":[-3.8588120937,40.3165931702],"type":"Point"}
}