{
  "type": "Feature",
  "properties": {
    "addr:full":"Pol. Ind. El Mas, S/n Monistrol Montserrat Barcelona 08691",
    "addr:housenumber":"s / n",
    "addr:postcode":"08691",
    "iso:country":"ES",
    "sg:address":"Pol. Ind. El Mas, S/n",
    "sg:city":"Monistrol Montserrat",
    "sg:orig_category":"Suministros Para Carrocer\u00cdas",
    "sg:phone":"+34 938 35 02 06",
    "sg:postcode":"08691",
    "sg:province":"Barcelona",
    "wof:name":"Talleres Enda S.l.",
    "wof:placetype":"venue"
},
  "geometry": {"coordinates":[1.8437199593,41.6091804504],"type":"Point"}
}