{
  "type": "Feature",
  "properties": {
    "addr:full":"Calle de San Jose, 2 Villanueva Ariscal Sevilla 41808",
    "addr:housenumber":"2",
    "addr:postcode":"41808",
    "addr:street":"Calle De San Jose",
    "iso:country":"ES",
    "sg:address":"Calle de San Jose, 2",
    "sg:city":"Villanueva Ariscal",
    "sg:orig_category":"Cajas De Ahorro",
    "sg:phone":"+34 954 11 30 00",
    "sg:postcode":"41808",
    "sg:province":"Sevilla",
    "sg:website":"www.lacaixa.es",
    "wof:name":"Caixa D'estalvis I Pensions De Barcelona",
    "wof:placetype":"venue"
},
  "geometry": {"coordinates":[-6.1407489777,37.3958702087],"type":"Point"}
}