{
  "type": "Feature",
  "properties": {
    "iso:country":"ES",
    "sg:address":"Calle de Azuela, S/n",
    "sg:city":"Estacion",
    "sg:orig_category":"Inform\u00c1tica: Consultores",
    "sg:phone":"+34 918 40 60 71",
    "sg:postcode":"28400",
    "sg:province":"Madrid",
    "sg:website":"www.digitalfile.net",
    "wof:name":"Digital File S.l.",
    "wof:placetype":"venue"
},
  "geometry": {"coordinates":[-3.7003455162,40.4166908264],"type":"Point"}
}