{
  "type": "Feature",
  "properties": {
    "addr:full":"Plaz Calvo Sotelo, 22 Paredes Nava Palencia 34300",
    "addr:housenumber":"22",
    "addr:postcode":"34300",
    "addr:street":"Plaz Calvo Sotelo",
    "iso:country":"ES",
    "sg:address":"Plaz Calvo Sotelo, 22",
    "sg:city":"Paredes Nava",
    "sg:orig_category":"Cajas Para Embalar",
    "sg:phone":"+34 979 83 02 59",
    "sg:postcode":"34300",
    "sg:province":"Palencia",
    "wof:name":"Caja Rural Del Duero",
    "wof:placetype":"venue"
},
  "geometry": {"coordinates":[-4.6880588531,42.1550292969],"type":"Point"}
}