{
  "type": "Feature",
  "properties": {
    "addr:full":"Carrer de Bailen, 99 Barcelona Barcelona 08009",
    "addr:housenumber":"99",
    "addr:postcode":"08009",
    "addr:street":"Carrer De Bailen",
    "iso:country":"ES",
    "sg:address":"Carrer de Bailen, 99",
    "sg:city":"Barcelona",
    "sg:orig_category":"Ense\u00d1anza: Comercio, Gesti\u00d3n, Inform\u00c1tica",
    "sg:phone":"+34 902 14 14 41",
    "sg:postcode":"08009",
    "sg:province":"Barcelona",
    "sg:website":"www.gesem.es",
    "wof:name":"Gesem 9000 S.l.",
    "wof:placetype":"venue"
},
  "geometry": {"coordinates":[2.1704349518,41.3968925476],"type":"Point"}
}