{
  "type": "Feature",
  "properties": {
    "addr:full":"Avda Jose Maria Alcaraz Y Alenda, 47 Badajoz Badajoz 06011",
    "addr:housenumber":"47",
    "addr:postcode":"06011",
    "addr:street":"Avda Jose Maria Alcaraz Y Alenda",
    "iso:country":"ES",
    "sg:address":"Avda Jose Maria Alcaraz Y Alenda, 47",
    "sg:city":"Badajoz",
    "sg:orig_category":"Sociedades, Compa\u00d1\u00cdas Aseguradoras",
    "sg:phone":"+34 924 23 13 01",
    "sg:postcode":"06011",
    "sg:province":"Badajoz",
    "wof:name":"France Telecom Espa\u00d1a S.a.",
    "wof:placetype":"venue"
},
  "geometry": {"coordinates":[-6.9947738647,38.8652305603],"type":"Point"}
}