{
  "type": "Feature",
  "properties": {
    "addr:full":"Calle de Nicasio Gallego, 9 Madrid Madrid 28010",
    "addr:housenumber":"9",
    "addr:postcode":"madrid;28010",
    "addr:street":"Calle De Nicasio Gallego",
    "iso:country":"ES",
    "sg:address":"Calle de Nicasio Gallego, 9",
    "sg:city":"Madrid",
    "sg:orig_category":"Pintura Y Barniz (al Por Menor)",
    "sg:phone":"+34 914 47 55 34",
    "sg:postcode":"28010",
    "sg:province":"Madrid",
    "wof:name":"Roca Y Rozas Casa Laf S. L.",
    "wof:placetype":"venue"
},
  "geometry": {"coordinates":[-3.6990261078,40.4296302795],"type":"Point"}
}