{
  "type": "Feature",
  "properties": {
    "iso:country":"ES",
    "sg:address":"Calle de Sor Valentina Miron, 19",
    "sg:city":"Plasencia",
    "sg:orig_category":"Motocicletas (agentes, Concesionarios)",
    "sg:phone":"+34 927 42 61 33",
    "sg:postcode":"10600",
    "sg:province":"C\u00e1ceres",
    "wof:name":"Joaquimoto S.l.",
    "wof:placetype":"venue"
},
  "geometry": {"coordinates":[-6.0905590057,40.0325965881],"type":"Point"}
}