{
  "type": "Feature",
  "properties": {
    "iso:country":"ES",
    "sg:address":"Calle de Valle De Broto, 9",
    "sg:city":"Zaragoza",
    "sg:orig_category":"Importaci\u00d3n",
    "sg:phone":"+34 976 42 53 50",
    "sg:postcode":"50015",
    "sg:province":"Zaragoza",
    "wof:name":"Inso 2001 S. L.",
    "wof:placetype":"venue"
},
  "geometry": {"coordinates":[-0.8734089732,41.6665115356],"type":"Point"}
}