{
  "type": "Feature",
  "properties": {
    "addr:full":"Avda Region De Murcia, 58 Secano Murcia 30579",
    "addr:housenumber":"58",
    "addr:postcode":"30579",
    "addr:street":"Avda Region;Murcia",
    "iso:country":"ES",
    "sg:address":"Avda Region De Murcia, 58",
    "sg:city":"Secano",
    "sg:orig_category":"Promotores Constructores",
    "sg:phone":"+34 968 83 73 60",
    "sg:postcode":"30579",
    "sg:province":"Murcia",
    "wof:name":"Progimur S.l.",
    "wof:placetype":"venue"
},
  "geometry": {"coordinates":[-1.0529290438,37.9830245972],"type":"Point"}
}