{
  "type": "Feature",
  "properties": {
    "addr:full":"Calle de Palacio Valdes, 9 Oviedo Asturias 33002",
    "addr:housenumber":"9",
    "addr:postcode":"33002",
    "addr:street":"Calle De Palacio Valdes",
    "iso:country":"ES",
    "sg:address":"Calle de Palacio Valdes, 9",
    "sg:city":"Oviedo",
    "sg:orig_category":"Asesor\u00cda Sobre Comunicaci\u00d3n De Empresas",
    "sg:phone":"+34 985 22 17 62",
    "sg:postcode":"33002",
    "sg:province":"Asturias",
    "wof:name":"Nexo Asesores Consultores S.l.l",
    "wof:placetype":"venue"
},
  "geometry": {"coordinates":[-5.8496780396,43.3641357422],"type":"Point"}
}