{
  "type": "Feature",
  "properties": {
    "iso:country":"ES",
    "sg:address":"Urb Barrina Centro, 20",
    "sg:city":"Coblanca",
    "sg:orig_category":"Agentes Generales De Seguros",
    "sg:phone":"+34 965 86 61 03",
    "sg:postcode":"03500",
    "sg:province":"Alicante",
    "wof:name":"Gomez Arandiga Araceli",
    "wof:placetype":"venue"
},
  "geometry": {"coordinates":[-0.1739459932,38.5365180969],"type":"Point"}
}