{
  "type": "Feature",
  "properties": {
    "addr:full":"Calle de San Bartolome, 3 Zamora Zamora 49004",
    "addr:housenumber":"3",
    "addr:postcode":"49004",
    "addr:street":"Calle De San Bartolome",
    "iso:country":"ES",
    "sg:address":"Calle de San Bartolome, 3",
    "sg:city":"Zamora",
    "sg:orig_category":"Producci\u00d3n, Distribuci\u00d3n De Electricidad",
    "sg:phone":"+34 980 53 54 68",
    "sg:postcode":"49004",
    "sg:province":"Zamora",
    "wof:name":"Electricidad Mario C.b.",
    "wof:placetype":"venue"
},
  "geometry": {"coordinates":[-5.7489438057,41.5045661926],"type":"Point"}
}