{
  "type": "Feature",
  "properties": {
    "iso:country":"ES",
    "sg:address":"Calle de Mina, 15",
    "sg:city":"Guadalajara",
    "sg:orig_category":"Promotores Constructores",
    "sg:phone":"+34 949 24 84 80",
    "sg:postcode":"19001",
    "sg:province":"Guadalajara",
    "sg:website":"www.gestesa.com",
    "wof:name":"Gestesa Desarrollos Urbanos S.l.",
    "wof:placetype":"venue"
},
  "geometry": {"coordinates":[-3.1632699966,40.6311378479],"type":"Point"}
}