{
  "type": "Feature",
  "properties": {
    "iso:country":"ES",
    "sg:address":"Calle de Calvo Sotelo, 11",
    "sg:city":"Tui",
    "sg:orig_category":"Asesor\u00cda Sobre Comunicaci\u00d3n De Empresas",
    "sg:phone":"+34 986 60 71 46",
    "sg:postcode":"36700",
    "sg:province":"Pontevedra",
    "wof:name":"Gestil S.l.",
    "wof:placetype":"venue"
},
  "geometry": {"coordinates":[-8.6449480057,42.0472373962],"type":"Point"}
}