{
  "type": "Feature",
  "properties": {
    "addr:full":"Carrer de Pitagoras, 3 Rubi Barcelona 08191",
    "addr:housenumber":"3",
    "addr:postcode":"08191",
    "addr:street":"Carrer De Pitagoras",
    "iso:country":"ES",
    "sg:address":"Carrer de Pitagoras, 3",
    "sg:city":"Rubi",
    "sg:orig_category":"Carnicer\u00cdas, Carnicer\u00cdas",
    "sg:phone":"+34 935 88 10 10",
    "sg:postcode":"08191",
    "sg:province":"Barcelona",
    "wof:name":"Taribo Sole Jorge",
    "wof:placetype":"venue"
},
  "geometry": {"coordinates":[2.0360860825,41.4856872559],"type":"Point"}
}