{
  "type": "Feature",
  "properties": {
    "iso:country":"ES",
    "sg:address":"Calle de Deltebre, 4",
    "sg:city":"Reinosa",
    "sg:orig_category":"Laboratorios Y Cl\u00cdnicas Veterinarias",
    "sg:phone":"+34 942 75 51 86",
    "sg:postcode":"39200",
    "sg:province":"Cantabria",
    "wof:name":"Garcia Garcia Marcos",
    "wof:placetype":"venue"
},
  "geometry": {"coordinates":[-4.1358971596,43.0002059937],"type":"Point"}
}