{
  "type": "Feature",
  "properties": {
    "addr:full":"Calle de Alcorta Nicolas, S/n Bilbao Vizcaya 48003",
    "addr:housenumber":"s / n",
    "addr:postcode":"48003",
    "addr:street":"Calle De Alcorta Nicolas",
    "iso:country":"ES",
    "sg:address":"Calle de Alcorta Nicolas, S/n",
    "sg:city":"Bilbao",
    "sg:orig_category":"Peluquer\u00cdas, Peluquer\u00cda Mixta",
    "sg:phone":"+34 944 21 84 33",
    "sg:postcode":"48003",
    "sg:province":"Vizcaya",
    "wof:name":"Wicca Brida S.l",
    "wof:placetype":"venue"
},
  "geometry": {"coordinates":[-2.9342005253,43.2564506531],"type":"Point"}
}