{
  "type": "Feature",
  "properties": {
    "iso:country":"ES",
    "sg:address":"Avda Juan Carlos I, 52",
    "sg:city":"Torre-pacheco",
    "sg:orig_category":"Lencer\u00cda Femenina, Corseter\u00cda, Trajes De Ba\u00d1o (al Por Menor)",
    "sg:phone":"+34 968 57 84 66",
    "sg:postcode":"30700",
    "sg:province":"Murcia",
    "wof:name":"Sanmartin Sanmartin Josefa",
    "wof:placetype":"venue"
},
  "geometry": {"coordinates":[-1.0760020018,37.8179779053],"type":"Point"}
}