{
  "type": "Feature",
  "properties": {
    "addr:full":"Avda Ausias March, 40 Tavernes Blanques Valencia 46016",
    "addr:housenumber":"40",
    "addr:postcode":"46016",
    "addr:street":"Avda Ausias March",
    "iso:country":"ES",
    "sg:address":"Avda Ausias March, 40",
    "sg:city":"Tavernes Blanques",
    "sg:orig_category":"Droguer\u00cdas (al Por Menor)",
    "sg:phone":"+34 961 86 21 06",
    "sg:postcode":"46016",
    "sg:province":"Valencia",
    "sg:website":"www.schlecker.com",
    "wof:name":"Schlecker S.a.",
    "wof:placetype":"venue"
},
  "geometry": {"coordinates":[-0.3649390042,39.5054588318],"type":"Point"}
}