{
  "type": "Feature",
  "properties": {
    "iso:country":"ES",
    "sg:address":"Calle de Alcalde Garret Y Souto, 81",
    "sg:city":"Malaga",
    "sg:orig_category":"Chapister\u00cda",
    "sg:phone":"+34 952 31 20 93",
    "sg:postcode":"29006",
    "sg:province":"M\u00e1laga",
    "wof:name":"Taller Rodriguez Pinazo S.l.l.",
    "wof:placetype":"venue"
},
  "geometry": {"coordinates":[-4.4795589447,36.7094192505],"type":"Point"}
}