{
  "type": "Feature",
  "properties": {
    "addr:full":"Calle de Mariano Barbasan, 12 Zaragoza Zaragoza 50006",
    "addr:housenumber":"12",
    "addr:postcode":"50006",
    "addr:street":"Calle De Mariano Barbasan",
    "iso:country":"ES",
    "sg:address":"Calle de Mariano Barbasan, 12",
    "sg:city":"Zaragoza",
    "sg:orig_category":"Institutos De Belleza",
    "sg:phone":"+34 976 56 23 63",
    "sg:postcode":"50006",
    "sg:province":"Zaragoza",
    "wof:name":"Noan S.c.",
    "wof:placetype":"venue"
},
  "geometry": {"coordinates":[-0.89151299,41.6421012878],"type":"Point"}
}