{
  "type": "Feature",
  "properties": {
    "addr:full":"Calle de Aguila, 22 Algezares Murcia 30157",
    "addr:housenumber":"22",
    "addr:postcode":"30157",
    "addr:street":"Calle De Aguila",
    "iso:country":"ES",
    "sg:address":"Calle de Aguila, 22",
    "sg:city":"Algezares",
    "sg:orig_category":"Alimentaci\u00d3n General (al Por Menor)",
    "sg:phone":"+34 968 84 12 95",
    "sg:postcode":"30157",
    "sg:province":"Murcia",
    "wof:name":"Meseguer Vives Ascension",
    "wof:placetype":"venue"
},
  "geometry": {"coordinates":[-1.1136307716,37.9434127808],"type":"Point"}
}