{
  "type": "Feature",
  "properties": {
    "addr:full":"Calle de Guillem De Castro, 31 Valencia Valencia 46007",
    "addr:housenumber":"31",
    "addr:postcode":"46007",
    "addr:street":"Calle De Guillem De Castro",
    "iso:country":"ES",
    "sg:address":"Calle de Guillem De Castro, 31",
    "sg:city":"Valencia",
    "sg:orig_category":"Complementos De Vestir (al Por Menor)",
    "sg:phone":"+34 963 51 03 64",
    "sg:postcode":"46007",
    "sg:province":"Valencia",
    "wof:name":"Sanchez Cano Francisca",
    "wof:placetype":"venue"
},
  "geometry": {"coordinates":[-0.3805080056,39.4682617188],"type":"Point"}
}