{
  "type": "Feature",
  "properties": {
    "iso:country":"ES",
    "sg:address":"Av Diagonal, 340",
    "sg:city":"Barcelona",
    "sg:orig_category":"Molduras, Junquillos, Listones Y Molduras Perforadas",
    "sg:phone":"+34 934 58 25 62",
    "sg:postcode":"08013",
    "sg:province":"Barcelona",
    "wof:name":"Cortes Navarro Vidal",
    "wof:placetype":"venue"
},
  "geometry": {"coordinates":[2.1728971004,41.4002075195],"type":"Point"}
}