{
  "type": "Feature",
  "properties": {
    "iso:country":"ES",
    "sg:address":"Carrer de Saragossa, 89",
    "sg:city":"Amposta",
    "sg:orig_category":"Producci\u00d3n, Venta De Productos De Agricultura Biol\u00d3gica",
    "sg:phone":"+34 977 70 29 15",
    "sg:postcode":"43870",
    "sg:province":"Tarragona",
    "wof:name":"Castella Grau Juan",
    "wof:placetype":"venue"
},
  "geometry": {"coordinates":[0.575913012,40.7059402466],"type":"Point"}
}