{
  "type": "Feature",
  "properties": {
    "iso:country":"ES",
    "sg:address":"Calle de Larramendi, 9",
    "sg:city":"Donostia-san Sebastian",
    "sg:orig_category":"Agencias Y Agentes Comerciales, Representantes",
    "sg:phone":"+34 943 46 98 61",
    "sg:postcode":"20006",
    "sg:province":"Guip\u00f9zcoa",
    "wof:name":"Agrupacion Profesional De Representantes De Comercio",
    "wof:placetype":"venue"
},
  "geometry": {"coordinates":[-1.9810055494,43.3154792786],"type":"Point"}
}