{
  "type": "Feature",
  "properties": {
    "iso:country":"ES",
    "sg:address":"Calle de Empedrada, 35",
    "sg:city":"Noblejas",
    "sg:orig_category":"Ambulancias",
    "sg:phone":"+34 925 14 13 00",
    "sg:postcode":"45350",
    "sg:province":"Toledo",
    "wof:name":"Ballesteros Amores Felipe",
    "wof:placetype":"venue"
},
  "geometry": {"coordinates":[-3.4413909912,39.9797401428],"type":"Point"}
}