{
  "type": "Feature",
  "properties": {
    "iso:country":"ES",
    "sg:address":"Plaz Alonso Martinez, 8",
    "sg:city":"Burgos",
    "sg:orig_category":"Asesor\u00cda Sobre Comunicaci\u00d3n De Empresas",
    "sg:phone":"+34 947 26 67 52",
    "sg:postcode":"09003",
    "sg:province":"Burgos",
    "wof:name":"Salas Garcia Francisco",
    "wof:placetype":"venue"
},
  "geometry": {"coordinates":[-3.7001149654,42.3438224792],"type":"Point"}
}