{
  "type": "Feature",
  "properties": {
    "addr:full":"C/ 16, 9 Ca\u00d1ada Valencia 46182",
    "addr:housenumber":"9",
    "addr:postcode":"46182",
    "addr:street":"C / 16",
    "iso:country":"ES",
    "sg:address":"C/ 16, 9",
    "sg:city":"Ca\u00d1ada",
    "sg:orig_category":"Hornos Industriales",
    "sg:phone":"+34 961 32 23 13",
    "sg:postcode":"46182",
    "sg:province":"Valencia",
    "wof:name":"Horno Casa Pepet S.l.",
    "wof:placetype":"venue"
},
  "geometry": {"coordinates":[-0.4852339923,39.5221443176],"type":"Point"}
}