{
  "type": "Feature",
  "properties": {
    "addr:full":"Rua Conservatorio, 5 Burgo La Coru\u00f1a 15670",
    "addr:housenumber":"5",
    "addr:postcode":"15670",
    "addr:street":"Rua Conservatorio;Burgo La Corun\u0303A",
    "iso:country":"ES",
    "sg:address":"Rua Conservatorio, 5",
    "sg:city":"Burgo",
    "sg:orig_category":"Aguas (distribuci\u00d3n, Servicios)",
    "sg:phone":"+34 981 61 20 33",
    "sg:postcode":"15670",
    "sg:province":"La Coru\u00f1a",
    "wof:name":"Gestagua S.a.",
    "wof:placetype":"venue"
},
  "geometry": {"coordinates":[-8.3809137344,43.32447052],"type":"Point"}
}