{
  "type": "Feature",
  "properties": {
    "addr:full":"Ctra Bellver, 1 Alp Girona 17538",
    "addr:housenumber":"1",
    "addr:postcode":"17538",
    "addr:street":"Ctra Bellver",
    "iso:country":"ES",
    "sg:address":"Ctra Bellver, 1",
    "sg:city":"Alp",
    "sg:orig_category":"Centros De Reservas Hoteleras",
    "sg:phone":"+34 972 89 03 31",
    "sg:postcode":"17538",
    "sg:province":"Girona",
    "wof:name":"Puigbo-trevejo S.l.",
    "wof:placetype":"venue"
},
  "geometry": {"coordinates":[1.8819990158,42.3714752197],"type":"Point"}
}