{
  "type": "Feature",
  "properties": {
    "addr:full":"Calle de Molina Lario, 3 Malaga M\u00e1laga 29015",
    "addr:housenumber":"3",
    "addr:postcode":"29015",
    "addr:street":"Calle De Molina Lario;Ma\u0301Laga",
    "iso:country":"ES",
    "sg:address":"Calle de Molina Lario, 3",
    "sg:city":"Malaga",
    "sg:orig_category":"Fabricaci\u00d3n De Banderas Y De Banderines",
    "sg:phone":"+34 952 21 48 59",
    "sg:postcode":"29015",
    "sg:province":"M\u00e1laga",
    "wof:name":"Fernandez Y Frias S.c.",
    "wof:placetype":"venue"
},
  "geometry": {"coordinates":[-4.4199647903,36.7211761475],"type":"Point"}
}