{
  "type": "Feature",
  "properties": {
    "iso:country":"ES",
    "sg:address":"Calle de Bautista Diaz Iba\u00d1ez, 1",
    "sg:city":"Torrijos",
    "sg:orig_category":"Ropa Para Ni\u00d1os (al Por Menor)",
    "sg:phone":"+34 925 76 19 55",
    "sg:postcode":"45500",
    "sg:province":"Toledo",
    "wof:name":"Moreno Perez Jose",
    "wof:placetype":"venue"
},
  "geometry": {"coordinates":[-4.2824492455,39.9823608398],"type":"Point"}
}