{
  "type": "Feature",
  "properties": {
    "iso:country":"ES",
    "sg:address":"Urbanizacion Los Postes, S/n",
    "sg:city":"Antas",
    "sg:orig_category":"Muebles, Minoristas",
    "sg:phone":"+34 950 45 31 56",
    "sg:postcode":"04628",
    "sg:province":"Almer\u00eda",
    "wof:name":"Flores Rubio Bartolome",
    "wof:placetype":"venue"
},
  "geometry": {"coordinates":[-1.9216589928,37.2441215515],"type":"Point"}
}