{
  "type": "Feature",
  "properties": {
    "iso:country":"ES",
    "sg:address":"Avda Vilaboa, 151",
    "sg:city":"Vilaboa",
    "sg:orig_category":"Comerciantes Al Por Mayor De Vinos, Licores Y Alcoholes",
    "sg:phone":"+34 981 66 00 78",
    "sg:postcode":"15174",
    "sg:province":"La Coru\u00f1a",
    "wof:name":"Corral Quintela Jose",
    "wof:placetype":"venue"
},
  "geometry": {"coordinates":[-8.3828992844,43.3123588562],"type":"Point"}
}