{
  "type": "Feature",
  "properties": {
    "iso:country":"ES",
    "sg:address":"Calle de Union La, 80",
    "sg:city":"Fuengirola",
    "sg:orig_category":"Colchones (fabricaci\u00d3n, Al Por Mayor, Al Por Menor)",
    "sg:phone":"+34 952 58 20 90",
    "sg:postcode":"29640",
    "sg:province":"M\u00e1laga",
    "sg:website":"www.somycolchon.com",
    "wof:name":"Somycochon Descanso S.l.",
    "wof:placetype":"venue"
},
  "geometry": {"coordinates":[-4.629805088,36.5467147827],"type":"Point"}
}