{
  "type": "Feature",
  "properties": {
    "iso:country":"ES",
    "sg:address":"Calle de Marques De Celada, 100",
    "sg:city":"San Cristobal De La Laguna",
    "sg:classifiers":[
        {
            "category":"Personal",
            "subcategory":"Barber",
            "type":"Services"
        }
    ],
    "sg:phone":"+34 922 26 58 23",
    "sg:postcode":"38202",
    "sg:province":"Santa Cruz De Tenerife",
    "sg:tags":[
        "caballeros",
        "de",
        "peluqueros"
    ],
    "wof:name":"De La Paz Ramos Nicasio",
    "wof:placetype":"venue"
},
  "geometry": {"coordinates":[-16.325012207,28.4903793335],"type":"Point"}
}