{
  "type": "Feature",
  "properties": {
    "iso:country":"ES",
    "sg:address":"Calle de Obispo Pildain Zapiain, S/n",
    "sg:city":"Lomo Blanco",
    "sg:orig_category":"Iglesia Cat\u00d3lica",
    "sg:phone":"+34 928 35 07 97",
    "sg:postcode":"35015",
    "sg:province":"Las Palmas",
    "wof:name":"Parroquia San Jose Artesano",
    "wof:placetype":"venue"
},
  "geometry": {"coordinates":[-15.4231882095,28.0956287384],"type":"Point"}
}