{
  "type": "Feature",
  "properties": {
    "addr:full":"G.v. Corts Catalanes, 731 Barcelona Barcelona 08013",
    "addr:housenumber":"731",
    "addr:postcode":"08013",
    "addr:street":"Catalanes",
    "iso:country":"ES",
    "sg:address":"G.v. Corts Catalanes, 731",
    "sg:city":"Barcelona",
    "sg:orig_category":"Farmacias",
    "sg:phone":"+34 932 31 23 04",
    "sg:postcode":"08013",
    "sg:province":"Barcelona",
    "wof:name":"Farmacia Galcera Tarrago S.c.p.",
    "wof:placetype":"venue"
},
  "geometry": {"coordinates":[2.1799581051,41.3986282349],"type":"Point"}
}