{
  "type": "Feature",
  "properties": {
    "iso:country":"ES",
    "sg:address":"Calle de Pinilla, 2",
    "sg:city":"Madrid",
    "sg:orig_category":"Asesor\u00cdas Y Estudios Financieros",
    "sg:phone":"+34 913 57 36 59",
    "sg:postcode":"28023",
    "sg:province":"Madrid",
    "wof:name":"Egret Consusting S.l.",
    "wof:placetype":"venue"
},
  "geometry": {"coordinates":[-3.7799649239,40.4563827515],"type":"Point"}
}