{
  "type": "Feature",
  "properties": {
    "addr:full":"Dobladoras(finca Lacy), 5 Elda Alicante 03600",
    "addr:postcode":"03600",
    "iso:country":"ES",
    "sg:address":"Dobladoras(finca Lacy), 5",
    "sg:city":"Elda",
    "sg:orig_category":"Fabricaci\u00d3n De Revestimientos De Suelos Pl\u00c1sticos Y De Goma",
    "sg:phone":"+34 966 98 24 50",
    "sg:postcode":"03600",
    "sg:province":"Alicante",
    "wof:name":"Policarbonatos Levante S.l.",
    "wof:placetype":"venue"
},
  "geometry": {"coordinates":[-0.8072890043,38.4462203979],"type":"Point"}
}