{
  "type": "Feature",
  "properties": {
    "addr:full":"Calle de Heros, 7 Bilbao Vizcaya 48009",
    "addr:housenumber":"7",
    "addr:postcode":"48009",
    "addr:street":"Calle De Heros",
    "iso:country":"ES",
    "sg:address":"Calle de Heros, 7",
    "sg:city":"Bilbao",
    "sg:orig_category":"Sindicatos Y Colegios Profesionales",
    "sg:phone":"+34 944 23 43 86",
    "sg:postcode":"48009",
    "sg:province":"Vizcaya",
    "wof:name":"Kristau Eskola",
    "wof:placetype":"venue"
},
  "geometry": {"coordinates":[-2.9315168858,43.2669830322],"type":"Point"}
}