{
  "type": "Feature",
  "properties": {
    "iso:country":"ES",
    "sg:address":"Calle de Angel, 15",
    "sg:city":"Toledo",
    "sg:orig_category":"Librer\u00cdas",
    "sg:phone":"+34 925 21 64 54",
    "sg:postcode":"45002",
    "sg:province":"Toledo",
    "wof:name":"Llurba Huguet Maria Teresa",
    "wof:placetype":"venue"
},
  "geometry": {"coordinates":[-4.0303821564,39.8573760986],"type":"Point"}
}