{
  "type": "Feature",
  "properties": {
    "addr:full":"Av Miraflores, 44 Hospitalet Llobregat Barcelona 08905",
    "addr:housenumber":"44",
    "addr:postcode":"08905",
    "addr:street":"Av Miraflores",
    "iso:country":"ES",
    "sg:address":"Av Miraflores, 44",
    "sg:city":"Hospitalet Llobregat",
    "sg:orig_category":"Zapatos (al Por Menor)",
    "sg:phone":"+34 934 49 19 24",
    "sg:postcode":"08905",
    "sg:province":"Barcelona",
    "wof:name":"Padevi S.a.",
    "wof:placetype":"venue"
},
  "geometry": {"coordinates":[2.1093599796,41.3712387085],"type":"Point"}
}