{
  "type": "Feature",
  "properties": {
    "iso:country":"ES",
    "sg:address":"Calle de Fernando Iii El Santo, 15",
    "sg:city":"Linares",
    "sg:orig_category":"Procuradores",
    "sg:phone":"+34 953 69 88 57",
    "sg:postcode":"23700",
    "sg:province":"Ja\u00e9n",
    "wof:name":"Marin Pageo Salvador",
    "wof:placetype":"venue"
},
  "geometry": {"coordinates":[-3.6316299438,38.0964202881],"type":"Point"}
}