{
  "type": "Feature",
  "properties": {
    "addr:full":"Calle de Monsalupe, 18 Madrid Madrid 28047",
    "addr:housenumber":"18",
    "addr:postcode":"madrid;28047",
    "addr:street":"Calle De Monsalupe",
    "iso:country":"ES",
    "sg:address":"Calle de Monsalupe, 18",
    "sg:city":"Madrid",
    "sg:orig_category":"Arquitectos",
    "sg:phone":"+34 914 64 84 34",
    "sg:postcode":"28047",
    "sg:province":"Madrid",
    "wof:name":"Navas Hernandez Miguel",
    "wof:placetype":"venue"
},
  "geometry": {"coordinates":[-3.7534329891,40.4005088806],"type":"Point"}
}