{
  "type": "Feature",
  "properties": {
    "iso:country":"ES",
    "sg:address":"Avda Constitucion, 126",
    "sg:city":"Madridejos",
    "sg:orig_category":"Empresas De Carpinter\u00cda",
    "sg:phone":"+34 925 46 23 53",
    "sg:postcode":"45710",
    "sg:province":"Toledo",
    "wof:name":"Cristaleria Y Aluminio Gomez Carre\u00f1o S.l.",
    "wof:placetype":"venue"
},
  "geometry": {"coordinates":[-3.5335590839,39.4756584167],"type":"Point"}
}