{
  "type": "Feature",
  "properties": {
    "iso:country":"ES",
    "sg:address":"Calle de Eriabarrena, 2",
    "sg:city":"Gernika-lumo",
    "sg:orig_category":"Electrodom\u00c9sticos (al Por Menor)",
    "sg:phone":"+34 946 25 10 07",
    "sg:postcode":"48300",
    "sg:province":"Vizcaya",
    "wof:name":"Arrien Iturbe Jesus",
    "wof:placetype":"venue"
},
  "geometry": {"coordinates":[-2.6776502132,43.3138313293],"type":"Point"}
}