{
  "type": "Feature",
  "properties": {
    "iso:country":"ES",
    "sg:address":"Bjad Encina (la), 1",
    "sg:city":"Santander",
    "sg:orig_category":"Molduras, Junquillos, Listones Y Molduras Perforadas",
    "sg:phone":"+34 942 27 72 21",
    "sg:postcode":"39005",
    "sg:province":"Cantabria",
    "wof:name":"Guerrero Montes David",
    "wof:placetype":"venue"
},
  "geometry": {"coordinates":[-3.7918689251,43.4688911438],"type":"Point"}
}