{
  "type": "Feature",
  "properties": {
    "addr:full":"Av America, 25 Hospitalet Llobregat Barcelona 08907",
    "addr:housenumber":"25",
    "addr:postcode":"08907",
    "addr:street":"Av America",
    "iso:country":"ES",
    "sg:address":"Av America, 25",
    "sg:city":"Hospitalet Llobregat",
    "sg:orig_category":"Empresas De Carpinter\u00cda De Madera",
    "sg:phone":"+34 933 36 12 21",
    "sg:postcode":"08907",
    "sg:province":"Barcelona",
    "wof:name":"Abajo Lallama Rafael",
    "wof:placetype":"venue"
},
  "geometry": {"coordinates":[2.114081,41.352997],"type":"Point"}
}