{
  "type": "Feature",
  "properties": {
    "addr:full":"Calle de Virgen De La Esperanza, 12 Aspe Alicante 03680",
    "addr:housenumber":"12",
    "addr:postcode":"03680",
    "addr:street":"Calle De Virgen De La Esperanza",
    "iso:country":"ES",
    "sg:address":"Calle de Virgen De La Esperanza, 12",
    "sg:city":"Aspe",
    "sg:orig_category":"Farmacias",
    "sg:phone":"+34 965 49 09 11",
    "sg:postcode":"03680",
    "sg:province":"Alicante",
    "wof:name":"Coves Lopez Nieves",
    "wof:placetype":"venue"
},
  "geometry": {"coordinates":[-0.7659209967,38.3455314636],"type":"Point"}
}