{
  "type": "Feature",
  "properties": {
    "addr:full":"Plaz Espa\u00d1a, 15 Alange Badajoz 06840",
    "addr:housenumber":"15",
    "addr:postcode":"06840",
    "addr:street":"Plaz Espan\u0303A",
    "iso:country":"ES",
    "sg:address":"Plaz Espa\u00d1a, 15",
    "sg:city":"Alange",
    "sg:orig_category":"Cajas De Ahorro",
    "sg:phone":"+34 924 36 53 28",
    "sg:postcode":"06840",
    "sg:province":"Badajoz",
    "wof:name":"Caja De Badajoz",
    "wof:placetype":"venue"
},
  "geometry": {"coordinates":[-6.2525668144,38.7848701477],"type":"Point"}
}