{
  "type": "Feature",
  "properties": {
    "addr:full":"Santa Klara Kalea, 40 Elgoibar Guip\u00f9zcoa 20870",
    "addr:housenumber":"40",
    "addr:postcode":"20870",
    "addr:street":"Santa Klara Kalea;Guipu\u0300Zcoa",
    "iso:country":"ES",
    "sg:address":"Santa Klara Kalea, 40",
    "sg:city":"Elgoibar",
    "sg:orig_category":"Prot\u00c9sicos Dentales",
    "sg:phone":"+34 943 74 24 72",
    "sg:postcode":"20870",
    "sg:province":"Guip\u00f9zcoa",
    "wof:name":"Metalkua Laborategi Dentala",
    "wof:placetype":"venue"
},
  "geometry": {"coordinates":[-2.4201819897,43.2167167664],"type":"Point"}
}