{
  "type": "Feature",
  "properties": {
    "addr:full":"Rua Asdrubal Ferreiro, S/n Xunqueira Ambia Ourense 32670",
    "addr:housenumber":"s / n",
    "addr:postcode":"32670",
    "addr:street":"Rua Asdrubal Ferreiro;Xunqueira Ambia",
    "iso:country":"ES",
    "sg:address":"Rua Asdrubal Ferreiro, S/n",
    "sg:city":"Xunqueira Ambia",
    "sg:orig_category":"Hilaturas, Hilos Y Actividades Relacionadas",
    "sg:phone":"+34 988 43 60 03",
    "sg:postcode":"32670",
    "sg:province":"Ourense",
    "wof:name":"Xuncosmoda Galicia S.l.l.",
    "wof:placetype":"venue"
},
  "geometry": {"coordinates":[-7.8646407127,42.340007782],"type":"Point"}
}