{
  "type": "Feature",
  "properties": {
    "iso:country":"ES",
    "sg:address":"Avda Bondad (de La), 6",
    "sg:city":"Caceres",
    "sg:orig_category":"Asociaciones Humanitarias, De Cooperaci\u00d3n, De Acci\u00d3n Social",
    "sg:phone":"+34 927 22 50 95",
    "sg:postcode":"10002",
    "sg:province":"C\u00e1ceres",
    "wof:name":"Asociacion De Alcoholicos Nominativos Extreme\u00f1os Anex",
    "wof:placetype":"venue"
},
  "geometry": {"coordinates":[-6.3753404617,39.4625549316],"type":"Point"}
}