{
  "type": "Feature",
  "properties": {
    "addr:full":"Calle de Ramon Y Cajal, 5 Denia Alicante 03700",
    "addr:housenumber":"5",
    "addr:postcode":"03700",
    "addr:street":"Calle De Ramon Y Cajal",
    "iso:country":"ES",
    "sg:address":"Calle de Ramon Y Cajal, 5",
    "sg:city":"Denia",
    "sg:orig_category":"Venta, Alquiler De Instrumentos Y Accesorios De M\u00dasica",
    "sg:phone":"+34 965 78 79 22",
    "sg:postcode":"03700",
    "sg:province":"Alicante",
    "wof:name":"Piera Gil Francisco Javier",
    "wof:placetype":"venue"
},
  "geometry": {"coordinates":[0.1062360033,38.8399887085],"type":"Point"}
}