{
  "type": "Feature",
  "properties": {
    "iso:country":"ES",
    "sg:address":"Calle de Gabriel Y Galan, 7",
    "sg:city":"Valladolid",
    "sg:orig_category":"Peluqueros: De Se\u00d1oras",
    "sg:phone":"+34 983 29 52 02",
    "sg:postcode":"47005",
    "sg:province":"Valladolid",
    "wof:name":"Rodriguez Ya\u00f1ez Maria Del Pilar",
    "wof:placetype":"venue"
},
  "geometry": {"coordinates":[-4.7127718925,41.6524925232],"type":"Point"}
}