{
  "type": "Feature",
  "properties": {
    "addr:full":"Calle de Landabe, 14 Sopelana Vizcaya 48600",
    "addr:housenumber":"14",
    "addr:postcode":"48600",
    "addr:street":"Calle De Landabe",
    "iso:country":"ES",
    "sg:address":"Calle de Landabe, 14",
    "sg:city":"Sopelana",
    "sg:orig_category":"Retoques De Vestidos",
    "sg:phone":"+34 946 76 13 73",
    "sg:postcode":"48600",
    "sg:province":"Vizcaya",
    "wof:name":"Haria Eta Arratza C.b. Tintoreria Arreglos",
    "wof:placetype":"venue"
},
  "geometry": {"coordinates":[-2.9807760715,43.3799667358],"type":"Point"}
}