{
  "type": "Feature",
  "properties": {
    "iso:country":"ES",
    "sg:address":"Ctra Pardo (del), Km. 0012,5",
    "sg:city":"Pe\u00d1ascales",
    "sg:orig_category":"Agricultura: Abastecimiento Y Cosechado (negocio)",
    "sg:phone":"+34 918 59 93 05",
    "sg:postcode":"28250",
    "sg:province":"Madrid",
    "wof:name":"Selecciones Campo Ara\u00f1uelo Sa",
    "wof:placetype":"venue"
},
  "geometry": {"coordinates":[-3.9306790829,40.57654953],"type":"Point"}
}