{
  "type": "Feature",
  "properties": {
    "addr:full":"Calle de Partera, 6 Utrera Sevilla 41710",
    "addr:housenumber":"6",
    "addr:postcode":"41710",
    "addr:street":"Calle De Partera",
    "iso:country":"ES",
    "sg:address":"Calle de Partera, 6",
    "sg:city":"Utrera",
    "sg:orig_category":"Arquitectos",
    "sg:phone":"+34 954 86 03 26",
    "sg:postcode":"41710",
    "sg:province":"Sevilla",
    "wof:name":"Vidal Velazquez Miguel",
    "wof:placetype":"venue"
},
  "geometry": {"coordinates":[-5.7830700874,37.1836166382],"type":"Point"}
}