{
  "type": "Feature",
  "properties": {
    "iso:country":"ES",
    "sg:address":"Trva Silbial (la), S/n",
    "sg:city":"Folgoso De La Ribera",
    "sg:orig_category":"Explotaci\u00d3n De Minas",
    "sg:phone":"+34 987 69 32 15",
    "sg:postcode":"24311",
    "sg:province":"Le\u00f3n",
    "wof:name":"Minas De Valdeloso S. L.",
    "wof:placetype":"venue"
},
  "geometry": {"coordinates":[-6.3185791969,42.6428909302],"type":"Point"}
}