{
  "type": "Feature",
  "properties": {
    "iso:country":"ES",
    "sg:address":"Calle de Leitariegos, 7",
    "sg:city":"Villablino",
    "sg:orig_category":"T\u00c9cnicos Veterinarios",
    "sg:phone":"+34 987 48 01 37",
    "sg:postcode":"24100",
    "sg:province":"Le\u00f3n",
    "wof:name":"Aller Fernandez Mercedes",
    "wof:placetype":"venue"
},
  "geometry": {"coordinates":[-6.3200998306,42.9385223389],"type":"Point"}
}