{
  "type": "Feature",
  "properties": {
    "addr:full":"Barr Ventas, 80 Irun Guip\u00f9zcoa 20305",
    "addr:housenumber":"80",
    "addr:postcode":"20305",
    "addr:street":"Ventas;Guipu\u0300Zcoa",
    "iso:country":"ES",
    "sg:address":"Barr Ventas, 80",
    "sg:city":"Irun",
    "sg:orig_category":"Papeler\u00cdas, Librer\u00cdas",
    "sg:phone":"+34 943 62 49 96",
    "sg:postcode":"20305",
    "sg:province":"Guip\u00f9zcoa",
    "wof:name":"Urdaniz Ostiz Maria Angeles",
    "wof:placetype":"venue"
},
  "geometry": {"coordinates":[-1.7637690306,43.3425445557],"type":"Point"}
}