{
  "type": "Feature",
  "properties": {
    "iso:country":"ES",
    "sg:address":"Calle de Misericordia, 2",
    "sg:city":"Cartaya",
    "sg:orig_category":"Bisuter\u00cda, Joyer\u00cda, Relojer\u00cda (al Por Menor)",
    "sg:phone":"+34 959 39 13 29",
    "sg:postcode":"21450",
    "sg:province":"Huelva",
    "wof:name":"Joyeria Pedraza S.c.",
    "wof:placetype":"venue"
},
  "geometry": {"coordinates":[-7.1506900787,37.2824363708],"type":"Point"}
}