{
  "type": "Feature",
  "properties": {
    "addr:full":"Calle de Juan De La Cueva, 14 Malaga M\u00e1laga 29016",
    "addr:housenumber":"14",
    "addr:postcode":"29016",
    "addr:street":"Calle De Juan De La Cueva;Ma\u0301Laga",
    "iso:country":"ES",
    "sg:address":"Calle de Juan De La Cueva, 14",
    "sg:city":"Malaga",
    "sg:orig_category":"Artes Gr\u00c1ficas, Artes Pl\u00c1sticas: Material Y Suministros (al Por Menor)",
    "sg:phone":"+34 952 21 81 03",
    "sg:postcode":"29016",
    "sg:province":"M\u00e1laga",
    "wof:name":"Ca\u00f1a Ruz Antonio",
    "wof:placetype":"venue"
},
  "geometry": {"coordinates":[-4.3918881416,36.7252655029],"type":"Point"}
}