{
  "type": "Feature",
  "properties": {
    "iso:country":"ES",
    "sg:address":"Avda Iparralde, 7",
    "sg:city":"Irun",
    "sg:orig_category":"Ense\u00d1anza: Profesiones Art\u00cdsticas",
    "sg:phone":"+34 943 63 61 06",
    "sg:postcode":"20304",
    "sg:province":"Guip\u00f9zcoa",
    "wof:name":"Foto Llor S.l.",
    "wof:placetype":"venue"
},
  "geometry": {"coordinates":[-1.7885489464,43.3441581726],"type":"Point"}
}