{
  "type": "Feature",
  "properties": {
    "iso:country":"ES",
    "sg:address":"Calle de Corzo, 4",
    "sg:city":"Humera-somosaguas-prado Del Rey",
    "sg:orig_category":"Arquitectos",
    "sg:phone":"+34 917 15 27 02",
    "sg:postcode":"28223",
    "sg:province":"Madrid",
    "wof:name":"Vallejo Acevedo Antonio",
    "wof:placetype":"venue"
},
  "geometry": {"coordinates":[-3.7822630405,40.4207115173],"type":"Point"}
}