{
  "type": "Feature",
  "properties": {
    "addr:full":"Ctra Extremadura, Km. 0120,9 Talavera Reina Toledo 45600",
    "addr:postcode":"45600",
    "addr:street":"Ctra Extremadura Km. 0120,9",
    "iso:country":"ES",
    "sg:address":"Ctra Extremadura, Km. 0120,9",
    "sg:city":"Talavera Reina",
    "sg:orig_category":"Comercio De Piezas De Recambio Y De Accesorios De Veh\u00cdculos, Veh\u00cdculos Industriales",
    "sg:phone":"+34 925 81 12 01",
    "sg:postcode":"45600",
    "sg:province":"Toledo",
    "wof:name":"Desguace La Rueda Cdad",
    "wof:placetype":"venue"
},
  "geometry": {"coordinates":[-4.8326292038,39.9584884644],"type":"Point"}
}