{
  "type": "Feature",
  "properties": {
    "addr:full":"Avda Diputacion, S/n Calpe Alicante 03710",
    "addr:housenumber":"s / n",
    "addr:postcode":"03710",
    "addr:street":"Avda Diputacion",
    "iso:country":"ES",
    "sg:address":"Avda Diputacion, S/n",
    "sg:city":"Calpe",
    "sg:orig_category":"Supermercados Y Hipermercados",
    "sg:phone":"+34 965 83 78 18",
    "sg:postcode":"03710",
    "sg:province":"Alicante",
    "sg:website":"www.capraboacasa.com",
    "wof:name":"Erosmer Iberica S.a.",
    "wof:placetype":"venue"
},
  "geometry": {"coordinates":[0.0416899994,38.6459236145],"type":"Point"}
}