{
  "type": "Feature",
  "properties": {
    "iso:country":"ES",
    "sg:address":"Via Edison (de), 36",
    "sg:city":"Boisaca",
    "sg:orig_category":"Velas Y Cirios (fabricaci\u00d3n, Al Por Menor)",
    "sg:phone":"+34 981 55 71 73",
    "sg:postcode":"15890",
    "sg:province":"La Coru\u00f1a",
    "wof:name":"Chedas Souto Manuel",
    "wof:placetype":"venue"
},
  "geometry": {"coordinates":[-8.4769210815,42.8835983276],"type":"Point"}
}