{
  "type": "Feature",
  "properties": {
    "iso:country":"ES",
    "sg:address":"C/ Mas, 20",
    "sg:city":"Manacor",
    "sg:orig_category":"Peluqueros: De Se\u00d1oras",
    "sg:phone":"+34 971 55 17 07",
    "sg:postcode":"07500",
    "sg:province":"Islas Baleares",
    "wof:name":"Febrer Artigues Juan",
    "wof:placetype":"venue"
},
  "geometry": {"coordinates":[3.2135579586,39.5696334839],"type":"Point"}
}