{
  "type": "Feature",
  "properties": {
    "iso:country":"ES",
    "sg:address":"Calle de Gloria Fuertes, 61",
    "sg:city":"Gijon",
    "sg:orig_category":"Fabricaci\u00d3n De Tapices Y Moquetas Para Suelos Y Paredes",
    "sg:phone":"+34 985 13 34 81",
    "sg:postcode":"33204",
    "sg:province":"Asturias",
    "wof:name":"Puertas Hernandez Pedro Luis",
    "wof:placetype":"venue"
},
  "geometry": {"coordinates":[-5.7102918625,43.5197067261],"type":"Point"}
}