{
  "type": "Feature",
  "properties": {
    "iso:country":"ES",
    "sg:address":"Calle de Real, 6",
    "sg:city":"Roda Andalucia",
    "sg:orig_category":"Supermercados Y Hipermercados",
    "sg:phone":"+34 954 01 65 68",
    "sg:postcode":"41590",
    "sg:province":"Sevilla",
    "wof:name":"Maskomo S.l.",
    "wof:placetype":"venue"
},
  "geometry": {"coordinates":[-4.779779911,37.2003974915],"type":"Point"}
}