{
  "type": "Feature",
  "properties": {
    "iso:country":"ES",
    "sg:address":"Calle de Nuestra Se\u00d1ora Del Aguila, 21",
    "sg:city":"Alcala Guadaira",
    "sg:orig_category":"Peluquer\u00cdas, Peluquer\u00cda Mixta",
    "sg:phone":"+34 955 68 06 01",
    "sg:postcode":"41500",
    "sg:province":"Sevilla",
    "wof:name":"Anmar Peluqueria S.l.",
    "wof:placetype":"venue"
},
  "geometry": {"coordinates":[-5.8464598656,37.3360023499],"type":"Point"}
}