{
  "type": "Feature",
  "properties": {
    "addr:full":"Ctra Zaragoza, 28 Calahorra La Rioja 26500",
    "addr:housenumber":"28",
    "addr:postcode":"26500",
    "addr:street":"Ctra Zaragoza",
    "iso:country":"ES",
    "sg:address":"Ctra Zaragoza, 28",
    "sg:city":"Calahorra",
    "sg:orig_category":"Remolques, Carretillas De Mano Para Operaciones Portuarias",
    "sg:phone":"+34 941 14 66 48",
    "sg:postcode":"26500",
    "sg:province":"La Rioja",
    "wof:name":"Alvemaser S.l.",
    "wof:placetype":"venue"
},
  "geometry": {"coordinates":[-1.9538147449,42.2948112488],"type":"Point"}
}