{
  "type": "Feature",
  "properties": {
    "addr:full":"Calle de Carabanchel, 7 Getafe Madrid 28902",
    "addr:housenumber":"7",
    "addr:postcode":"28902",
    "addr:street":"Calle De Carabanchel",
    "iso:country":"ES",
    "sg:address":"Calle de Carabanchel, 7",
    "sg:city":"Getafe",
    "sg:orig_category":"Madera Para Construcci\u00d3n E Industria",
    "sg:phone":"+34 916 83 53 82",
    "sg:postcode":"28902",
    "sg:province":"Madrid",
    "sg:website":"www.parquetmensan.com",
    "wof:name":"Parquet Mensan S.l.",
    "wof:placetype":"venue"
},
  "geometry": {"coordinates":[-3.7283639908,40.3119506836],"type":"Point"}
}