{
  "type": "Feature",
  "properties": {
    "iso:country":"ES",
    "sg:address":"Trva Couto San Honorato 1, 3",
    "sg:city":"Vigo",
    "sg:orig_category":"Asociaciones Y Clubs Deportivos",
    "sg:phone":"+34 986 48 21 29",
    "sg:postcode":"36204",
    "sg:province":"Pontevedra",
    "wof:name":"Agrupacion Deportiva Primavera",
    "wof:placetype":"venue"
},
  "geometry": {"coordinates":[-8.7157278061,42.2284927368],"type":"Point"}
}