{
  "type": "Feature",
  "properties": {
    "addr:full":"Carrer de Sant Antoni, 27 Sabadell Barcelona 08201",
    "addr:housenumber":"27",
    "addr:postcode":"08201",
    "addr:street":"Carrer De Sant Antoni",
    "iso:country":"ES",
    "sg:address":"Carrer de Sant Antoni, 27",
    "sg:city":"Sabadell",
    "sg:orig_category":"M\u00c9dicos: Cirug\u00cda Pl\u00c1stica, Reconstructiva Y Est\u00c9tica",
    "sg:phone":"+34 937 25 31 32",
    "sg:postcode":"08201",
    "sg:province":"Barcelona",
    "wof:name":"Optim Laser S.l.",
    "wof:placetype":"venue"
},
  "geometry": {"coordinates":[2.1075460911,41.5479011536],"type":"Point"}
}