{
  "type": "Feature",
  "properties": {
    "iso:country":"ES",
    "sg:address":"Ctra Autopista A18, S/n",
    "sg:city":"Terrassa",
    "sg:orig_category":"Fabricaci\u00d3n, Importaci\u00d3n, Venta De Material De Telefon\u00cda, Peritelefon\u00cda",
    "sg:phone":"+34 937 36 10 73",
    "sg:postcode":"08228",
    "sg:province":"Barcelona",
    "wof:name":"Jecomtel Comunicaciones S.l.",
    "wof:placetype":"venue"
},
  "geometry": {"coordinates":[2.0389900208,41.536441803],"type":"Point"}
}