{
  "type": "Feature",
  "properties": {
    "addr:full":"Calle de Joaquin Costa, 57 Madrid Madrid 28002",
    "addr:housenumber":"57",
    "addr:postcode":"madrid;28002",
    "addr:street":"Calle De Joaquin Costa",
    "iso:country":"ES",
    "sg:address":"Calle de Joaquin Costa, 57",
    "sg:city":"Madrid",
    "sg:orig_category":"Creaci\u00d3n De Sitios, Hosting Internet",
    "sg:phone":"+34 915 63 28 07",
    "sg:postcode":"28002",
    "sg:province":"Madrid",
    "sg:website":"www.sismic.com",
    "wof:name":"Grupo 34 De Comunicacion S.l.",
    "wof:placetype":"venue"
},
  "geometry": {"coordinates":[-3.680907011,40.441192627],"type":"Point"}
}