{
  "type": "Feature",
  "properties": {
    "addr:full":"Finca De La Jabalina, S/n Carrasquilla Murcia 30439",
    "addr:housenumber":"/ n",
    "addr:postcode":"30439",
    "addr:street":"Jabalina S",
    "iso:country":"ES",
    "sg:address":"Finca De La Jabalina, S/n",
    "sg:city":"Carrasquilla",
    "sg:orig_category":"Agricultura: Abastecimiento Y Cosechado (negocio)",
    "sg:phone":"+34 968 74 91 10",
    "sg:postcode":"30439",
    "sg:province":"Murcia",
    "wof:name":"Monte Y Mar De Santa Pola S.l.",
    "wof:placetype":"venue"
},
  "geometry": {"coordinates":[-1.7682700157,38.1409721375],"type":"Point"}
}