{
  "type": "Feature",
  "properties": {
    "addr:full":"Calle de Balendin Berriotxoa, 18 Arizgoiti Vizcaya 48970",
    "addr:housenumber":"18",
    "addr:postcode":"48970",
    "addr:street":"Calle De Balendin Berriotxoa",
    "iso:country":"ES",
    "sg:address":"Calle de Balendin Berriotxoa, 18",
    "sg:city":"Arizgoiti",
    "sg:orig_category":"Complementos De Vestir (al Por Menor)",
    "sg:phone":"+34 944 49 84 06",
    "sg:postcode":"48970",
    "sg:province":"Vizcaya",
    "wof:name":"Gringos Crow S.l.",
    "wof:placetype":"venue"
},
  "geometry": {"coordinates":[-2.8840253353,43.2361450195],"type":"Point"}
}