{
  "type": "Feature",
  "properties": {
    "addr:full":"Carrer de Ivorra, 24 Barcelona Barcelona 08034",
    "addr:housenumber":"24",
    "addr:postcode":"08034",
    "addr:street":"Carrer De Ivorra",
    "iso:country":"ES",
    "sg:address":"Carrer de Ivorra, 24",
    "sg:city":"Barcelona",
    "sg:orig_category":"Molduras, Junquillos, Listones Y Molduras Perforadas",
    "sg:phone":"+34 932 03 49 88",
    "sg:postcode":"08034",
    "sg:province":"Barcelona",
    "wof:name":"Haro Alvarez Jose Ignacio",
    "wof:placetype":"venue"
},
  "geometry": {"coordinates":[2.1223590374,41.397228241],"type":"Point"}
}