{
  "type": "Feature",
  "properties": {
    "addr:full":"Ferroviarios, 16 Puente-genil C\u00f3rdoba 14500",
    "addr:housenumber":"16",
    "addr:postcode":"14500",
    "addr:street":"Ferroviarios;Co\u0301Rdoba",
    "iso:country":"ES",
    "sg:address":"Ferroviarios, 16",
    "sg:city":"Puente-genil",
    "sg:orig_category":"Centros Empresariales",
    "sg:phone":"+34 957 60 02 54",
    "sg:postcode":"14500",
    "sg:province":"C\u00f3rdoba",
    "wof:name":"Villafranca Hermanos S. A.",
    "wof:placetype":"venue"
},
  "geometry": {"coordinates":[-4.7779579163,37.3909187317],"type":"Point"}
}