{
  "type": "Feature",
  "properties": {
    "addr:full":"Ctra Fataga, S/n Fataga Las Palmas 35108",
    "addr:housenumber":"s / n",
    "addr:postcode":"35108",
    "addr:street":"Ctra Fataga",
    "iso:country":"ES",
    "sg:address":"Ctra Fataga, S/n",
    "sg:city":"Fataga",
    "sg:orig_category":"Parques De Atracciones Y Centros De Esparcimiento",
    "sg:phone":"+34 928 79 86 80",
    "sg:postcode":"35108",
    "sg:province":"Las Palmas",
    "wof:name":"Perez Dominguez Carmen",
    "wof:placetype":"venue"
},
  "geometry": {"coordinates":[-15.5638666153,27.8875045776],"type":"Point"}
}