{
  "type": "Feature",
  "properties": {
    "addr:full":"Calle de Nuestra Se\u00d1ora De La Luz, 24 Coru\u00d1a La Coru\u00f1a 15007",
    "addr:housenumber":"24",
    "addr:postcode":"15007",
    "addr:street":"Calle De Nuestra Sen\u0303Ora De La Luz;La Corun\u0303A",
    "iso:country":"ES",
    "sg:address":"Calle de Nuestra Se\u00d1ora De La Luz, 24",
    "sg:city":"Coru\u00d1a",
    "sg:orig_category":"Instalaci\u00d3n, Reparaci\u00d3n De Calefacci\u00d3n El\u00c9ctrica",
    "sg:phone":"+34 981 24 24 64",
    "sg:postcode":"15007",
    "sg:province":"La Coru\u00f1a",
    "wof:name":"Pollan Marcos David",
    "wof:placetype":"venue"
},
  "geometry": {"coordinates":[-8.7951183319,42.9959411621],"type":"Point"}
}