{
  "type": "Feature",
  "properties": {
    "iso:country":"ES",
    "sg:address":"Calle de Capitan Rojas, 10",
    "sg:city":"Pe\u00f1afiel",
    "sg:orig_category":"Imprenta",
    "sg:phone":"+34 983 88 00 35",
    "sg:postcode":"47300",
    "sg:province":"Valladolid",
    "wof:name":"Abalo Ramos Jose Antonio",
    "wof:placetype":"venue"
},
  "geometry": {"coordinates":[-4.119113,41.596897],"type":"Point"}
}