{
  "type": "Feature",
  "properties": {
    "addr:full":"Pase Recoletos, 27 Madrid Madrid 28004",
    "addr:housenumber":"27",
    "addr:postcode":"madrid;28004",
    "addr:street":"Recoletos",
    "iso:country":"ES",
    "sg:address":"Pase Recoletos, 27",
    "sg:city":"Madrid",
    "sg:orig_category":"Compraventa De Antig\u00dcedades",
    "sg:phone":"+34 913 19 59 12",
    "sg:postcode":"28004",
    "sg:province":"Madrid",
    "sg:website":"www.alvargonzalez.com",
    "wof:name":"Alvargonzalez S.a.",
    "wof:placetype":"venue"
},
  "geometry": {"coordinates":[-3.6917731762,40.4233779907],"type":"Point"}
}