{
  "type": "Feature",
  "properties": {
    "addr:full":"Ziku\u00d1aga Bailara, 33 Zikuinaga Guip\u00f9zcoa 20120",
    "addr:housenumber":"33",
    "addr:postcode":"20120",
    "addr:street":"Zikun\u0303Aga Bailara;Guipu\u0300Zcoa",
    "iso:country":"ES",
    "sg:address":"Ziku\u00d1aga Bailara, 33",
    "sg:city":"Zikuinaga",
    "sg:orig_category":"Molduras, Junquillos, Listones Y Molduras Perforadas",
    "sg:phone":"+34 943 55 61 24",
    "sg:postcode":"20120",
    "sg:province":"Guip\u00f9zcoa",
    "wof:name":"Zurutuza Goiburu Jose Martin",
    "wof:placetype":"venue"
},
  "geometry": {"coordinates":[-1.9798289537,43.2647514343],"type":"Point"}
}