{
  "type": "Feature",
  "properties": {
    "iso:country":"ES",
    "sg:address":"Carrer de Sant Joan B. De La Salle (de), 14",
    "sg:city":"Tortosa",
    "sg:orig_category":"Agencias Y Agentes Comerciales, Representantes",
    "sg:phone":"+34 977 51 11 80",
    "sg:postcode":"43500",
    "sg:province":"Tarragona",
    "wof:name":"Representaciones Marti S.l.",
    "wof:placetype":"venue"
},
  "geometry": {"coordinates":[0.5236219764,40.8091430664],"type":"Point"}
}