{
  "type": "Feature",
  "properties": {
    "addr:full":"Pase Ramon Y Cajal, 28 Huesca Huesca 22001",
    "addr:housenumber":"28",
    "addr:postcode":"22001",
    "addr:street":"Ramon Y Cajal",
    "iso:country":"ES",
    "sg:address":"Pase Ramon Y Cajal, 28",
    "sg:city":"Huesca",
    "sg:orig_category":"Reposter\u00cdas",
    "sg:phone":"+34 974 22 12 13",
    "sg:postcode":"22001",
    "sg:province":"Huesca",
    "wof:name":"Comercial Alto Aragonesa De Reposteria S.l.",
    "wof:placetype":"venue"
},
  "geometry": {"coordinates":[-0.4020420015,42.139289856],"type":"Point"}
}