{
  "type": "Feature",
  "properties": {
    "addr:full":"Carrer de Franc M Herreros, 5 Palma Islas Baleares 07005",
    "addr:housenumber":"5",
    "addr:postcode":"07005",
    "addr:street":"Carrer De Franc M Herreros",
    "iso:country":"ES",
    "sg:address":"Carrer de Franc M Herreros, 5",
    "sg:city":"Palma",
    "sg:orig_category":"T\u00c9cnicos Veterinarios",
    "sg:phone":"+34 971 46 08 50",
    "sg:postcode":"07005",
    "sg:province":"Islas Baleares",
    "wof:name":"Centro Veterinario De Baleares S.l.",
    "wof:placetype":"venue"
},
  "geometry": {"coordinates":[2.6615219116,39.5736274719],"type":"Point"}
}