{
  "type": "Feature",
  "properties": {
    "iso:country":"ES",
    "sg:address":"Calle de Ines Diego Del Noval, 62",
    "sg:city":"Cueto",
    "sg:orig_category":"Panader\u00cdas, Panader\u00cdas",
    "sg:phone":"+34 942 39 24 41",
    "sg:postcode":"39012",
    "sg:province":"Cantabria",
    "wof:name":"Pablo Sarraga Aurora Del Carmen De",
    "wof:placetype":"venue"
},
  "geometry": {"coordinates":[-3.8604888916,43.4665527344],"type":"Point"}
}