{
  "type": "Feature",
  "properties": {
    "addr:full":"Calle de General Ollero, 25 Porcuna Ja\u00e9n 23790",
    "addr:housenumber":"25",
    "addr:postcode":"23790",
    "addr:street":"Calle De General Ollero",
    "iso:country":"ES",
    "sg:address":"Calle de General Ollero, 25",
    "sg:city":"Porcuna",
    "sg:orig_category":"Abogados",
    "sg:phone":"+34 953 54 48 20",
    "sg:postcode":"23790",
    "sg:province":"Ja\u00e9n",
    "wof:name":"Perez Heredia Luis Felipe",
    "wof:placetype":"venue"
},
  "geometry": {"coordinates":[-4.1836152077,37.870136261],"type":"Point"}
}