{
  "type": "Feature",
  "properties": {
    "addr:full":"Avda Vilaboa, 82 Vilaboa La Coru\u00f1a 15174",
    "addr:housenumber":"82",
    "addr:postcode":"15174",
    "addr:street":"Avda Vilaboa;La Corun\u0303A",
    "iso:country":"ES",
    "sg:address":"Avda Vilaboa, 82",
    "sg:city":"Vilaboa",
    "sg:orig_category":"Frutas, Legumbres Frescas Y Tempranas (al Por Menor)",
    "sg:phone":"+34 981 65 03 12",
    "sg:postcode":"15174",
    "sg:province":"La Coru\u00f1a",
    "wof:name":"Clotilde Sanmartin Y Otra S.c.",
    "wof:placetype":"venue"
},
  "geometry": {"coordinates":[-8.3825883865,43.3121032715],"type":"Point"}
}