{
  "type": "Feature",
  "properties": {
    "addr:full":"Comer\u00e7(pol Ind Avenar), 13 Roda De Bara Tarragona 43883",
    "addr:housenumber":"13",
    "addr:postcode":"43883",
    "addr:street":"Avenar",
    "iso:country":"ES",
    "sg:address":"Comer\u00e7(pol Ind Avenar), 13",
    "sg:city":"Roda De Bara",
    "sg:orig_category":"Electricidad: Instaladores",
    "sg:phone":"+34 977 80 93 92",
    "sg:postcode":"43883",
    "sg:province":"Tarragona",
    "wof:name":"Ciuro S.a.",
    "wof:placetype":"venue"
},
  "geometry": {"coordinates":[1.4510300159,41.1821136475],"type":"Point"}
}