{
  "type": "Feature",
  "properties": {
    "iso:country":"ES",
    "sg:address":"Calle de Juan De La Cosa, 2",
    "sg:city":"Castro Urdiales",
    "sg:orig_category":"Asesor\u00cda Fiscal Y Jur\u00cddica",
    "sg:phone":"+34 942 86 27 91",
    "sg:postcode":"39700",
    "sg:province":"Cantabria",
    "wof:name":"Arcos Pascual Simeon De Los",
    "wof:placetype":"venue"
},
  "geometry": {"coordinates":[-3.2194201946,43.3813285828],"type":"Point"}
}