{
  "type": "Feature",
  "properties": {
    "addr:full":"A Igrexa, S/n Mos Pontevedra 36416",
    "addr:housenumber":"s / n",
    "addr:postcode":"36416",
    "addr:street":"A Igrexa",
    "iso:country":"ES",
    "sg:address":"A Igrexa, S/n",
    "sg:city":"Mos",
    "sg:orig_category":"Suministros Y Materiales Industriales",
    "sg:phone":"+34 986 33 04 87",
    "sg:postcode":"36416",
    "sg:province":"Pontevedra",
    "sg:website":"www.gcopo.com",
    "wof:name":"Copo Iberica S.a.",
    "wof:placetype":"venue"
},
  "geometry": {"coordinates":[-8.6126050949,42.1988525391],"type":"Point"}
}