{
  "type": "Feature",
  "properties": {
    "addr:full":"Pg Maritim, 26 Port D'alcudia Islas Baleares 07410",
    "addr:housenumber":"26",
    "addr:postcode":"07410",
    "addr:street":"Pg Maritim",
    "iso:country":"ES",
    "sg:address":"Pg Maritim, 26",
    "sg:city":"Port D'alcudia",
    "sg:orig_category":"Art\u00cdculos De Regalo (al Por Menor)",
    "sg:phone":"+34 971 54 72 64",
    "sg:postcode":"07410",
    "sg:province":"Islas Baleares",
    "wof:name":"Vives Cladera Mateo",
    "wof:placetype":"venue"
},
  "geometry": {"coordinates":[3.1349418163,39.8410453796],"type":"Point"}
}