{
  "type": "Feature",
  "properties": {
    "iso:country":"ES",
    "sg:address":"Calle de Matias Barrio Y Mier, 8",
    "sg:city":"Aguilar Campoo",
    "sg:orig_category":"Caf\u00c9s, Bares, Cervecer\u00cdas",
    "sg:phone":"+34 979 12 21 10",
    "sg:postcode":"34800",
    "sg:province":"Palencia",
    "wof:name":"Gutierrez Perez Luis",
    "wof:placetype":"venue"
},
  "geometry": {"coordinates":[-4.2579951286,42.7930374146],"type":"Point"}
}