{
  "type": "Feature",
  "properties": {
    "iso:country":"ES",
    "sg:address":"Avda Pais Valenciano, 101",
    "sg:city":"Albatera",
    "sg:orig_category":"Agentes Generales De Seguros",
    "sg:phone":"+34 965 48 76 74",
    "sg:postcode":"03340",
    "sg:province":"Alicante",
    "wof:name":"Berna Cerdan Manuel",
    "wof:placetype":"venue"
},
  "geometry": {"coordinates":[-0.8703939915,38.1803436279],"type":"Point"}
}