{
  "type": "Feature",
  "properties": {
    "iso:country":"ES",
    "sg:address":"Av Castellbisbal, 58",
    "sg:city":"Rubi",
    "sg:orig_category":"Empresas De Demolici\u00d3n",
    "sg:phone":"+34 936 97 40 18",
    "sg:postcode":"08191",
    "sg:province":"Barcelona",
    "wof:name":"Proyectos Y Excavaciones Rubi S.l.",
    "wof:placetype":"venue"
},
  "geometry": {"coordinates":[2.0242800713,41.4901695251],"type":"Point"}
}