{
  "type": "Feature",
  "properties": {
    "iso:country":"ES",
    "sg:address":"Calle de Manuel Ruiz Zorrilla, 23",
    "sg:city":"Malaga",
    "sg:orig_category":"Empresas De Carpinter\u00cda De Madera",
    "sg:phone":"+34 952 27 38 91",
    "sg:postcode":"29011",
    "sg:province":"M\u00e1laga",
    "wof:name":"Miro Luque Francisco",
    "wof:placetype":"venue"
},
  "geometry": {"coordinates":[-4.4360289574,36.7294845581],"type":"Point"}
}