{
  "type": "Feature",
  "properties": {
    "iso:country":"ES",
    "sg:address":"Avda Gran Via Rey Juan Carlos I, 56",
    "sg:city":"Logro\u00f1o",
    "sg:orig_category":"Mercer\u00cda, Lencer\u00cda (al Por Menor)",
    "sg:phone":"+34 941 20 94 16",
    "sg:postcode":"26005",
    "sg:province":"La Rioja",
    "wof:name":"Heredia Fernandez Josefa",
    "wof:placetype":"venue"
},
  "geometry": {"coordinates":[-2.453469038,42.4650764465],"type":"Point"}
}