{
  "type": "Feature",
  "properties": {
    "iso:country":"ES",
    "sg:address":"Av Diagonal, 400",
    "sg:city":"Barcelona",
    "sg:orig_category":"\u00d3ptica: Instrumentos (fabricaci\u00d3n)",
    "sg:phone":"+34 932 07 78 75",
    "sg:postcode":"08037",
    "sg:province":"Barcelona",
    "wof:name":"Novo Lent S.a.",
    "wof:placetype":"venue"
},
  "geometry": {"coordinates":[2.1660749912,41.3984718323],"type":"Point"}
}