{
  "type": "Feature",
  "properties": {
    "addr:full":"Calle de Neveria, 16 Quinto Zaragoza 50770",
    "addr:housenumber":"16",
    "addr:postcode":"50770",
    "addr:street":"Calle De Neveria",
    "iso:country":"ES",
    "sg:address":"Calle de Neveria, 16",
    "sg:city":"Quinto",
    "sg:orig_category":"Producci\u00d3n, Venta De Productos De Agricultura Biol\u00d3gica",
    "sg:phone":"+34 976 17 70 31",
    "sg:postcode":"50770",
    "sg:province":"Zaragoza",
    "wof:name":"Paseo 1001 S.l.",
    "wof:placetype":"venue"
},
  "geometry": {"coordinates":[-0.4993354976,41.4267997742],"type":"Point"}
}