{
  "type": "Feature",
  "properties": {
    "iso:country":"ES",
    "sg:address":"Avda Valencia, 27",
    "sg:city":"Zaragoza",
    "sg:orig_category":"Sociedades, Compa\u00d1\u00cdas Aseguradoras",
    "sg:phone":"+34 976 55 68 36",
    "sg:postcode":"50005",
    "sg:province":"Zaragoza",
    "wof:name":"Francisco Oliete Roche S.l.",
    "wof:placetype":"venue"
},
  "geometry": {"coordinates":[-0.8960639834,41.6465644836],"type":"Point"}
}