{
  "type": "Feature",
  "properties": {
    "addr:full":"Carrer de Lleida, 6 Caldes Montbui Barcelona 08140",
    "addr:housenumber":"6",
    "addr:postcode":"08140",
    "addr:street":"Carrer De Lleida;Montbui Barcelona",
    "iso:country":"ES",
    "sg:address":"Carrer de Lleida, 6",
    "sg:city":"Caldes Montbui",
    "sg:orig_category":"Fisioterapia",
    "sg:phone":"+34 938 65 51 79",
    "sg:postcode":"08140",
    "sg:province":"Barcelona",
    "wof:name":"Centre Medic I Rehabilitacio Caldes S.l.",
    "wof:placetype":"venue"
},
  "geometry": {"coordinates":[2.1678080559,41.6281471252],"type":"Point"}
}