{
  "type": "Feature",
  "properties": {
    "iso:country":"ES",
    "sg:address":"Av Barcelona, 165",
    "sg:city":"Cunit",
    "sg:orig_category":"Mec\u00c1nico Del Autom\u00d3vil",
    "sg:phone":"+34 977 67 42 22",
    "sg:postcode":"43881",
    "sg:province":"Tarragona",
    "wof:name":"Robles Galindo Antonio",
    "wof:placetype":"venue"
},
  "geometry": {"coordinates":[1.6348700523,41.1987609863],"type":"Point"}
}