{
  "type": "Feature",
  "properties": {
    "iso:country":"ES",
    "sg:address":"Avda Murcia, 80",
    "sg:city":"Balsicas",
    "sg:orig_category":"Alquiler De V\u00cddeo",
    "sg:phone":"+34 968 58 06 52",
    "sg:postcode":"30591",
    "sg:province":"Murcia",
    "wof:name":"Bernal Pacheco Francisco",
    "wof:placetype":"venue"
},
  "geometry": {"coordinates":[-0.9590690136,37.818977356],"type":"Point"}
}