{
  "type": "Feature",
  "properties": {
    "addr:full":"Calle de San Antonio, S/n Prado Del Rey C\u00e1diz 11660",
    "addr:housenumber":"s / n",
    "addr:postcode":"11660",
    "addr:street":"Calle De San Antonio",
    "iso:country":"ES",
    "sg:address":"Calle de San Antonio, S/n",
    "sg:city":"Prado Del Rey",
    "sg:orig_category":"Ense\u00d1anza Secundaria: Colegios Y Escuelas Privadas",
    "sg:phone":"+34 956 72 40 22",
    "sg:postcode":"11660",
    "sg:province":"C\u00e1diz",
    "wof:name":"Junta De Andalucia",
    "wof:placetype":"venue"
},
  "geometry": {"coordinates":[-5.556494236,36.7867202759],"type":"Point"}
}