{
  "type": "Feature",
  "properties": {
    "iso:country":"ES",
    "sg:address":"Calle de Bazan, 13",
    "sg:city":"Torrevieja",
    "sg:orig_category":"Promotores Constructores",
    "sg:phone":"+34 966 70 80 07",
    "sg:postcode":"03180",
    "sg:province":"Alicante",
    "wof:name":"J.s.promociones Urbanas De Levante S.l.",
    "wof:placetype":"venue"
},
  "geometry": {"coordinates":[-0.6826047897,37.9792137146],"type":"Point"}
}