{
  "type": "Feature",
  "properties": {
    "addr:full":"Bule Hernan Ruiz, 19 Cordoba C\u00f3rdoba 14005",
    "addr:postcode":"14005",
    "addr:street":"Co\u0301Rdoba",
    "iso:country":"ES",
    "sg:address":"Bule Hernan Ruiz, 19",
    "sg:city":"Cordoba",
    "sg:orig_category":"Asesor\u00cda Sobre Comunicaci\u00d3n De Empresas",
    "sg:phone":"+34 957 45 67 97",
    "sg:postcode":"14005",
    "sg:province":"C\u00f3rdoba",
    "wof:name":"Promociones Riojano Andaluzas S.a.",
    "wof:placetype":"venue"
},
  "geometry": {"coordinates":[-4.7898759842,37.8864364624],"type":"Point"}
}