{
  "type": "Feature",
  "properties": {
    "iso:country":"ES",
    "sg:address":"Carr Joaquin Navarro, 16",
    "sg:city":"Burjassot",
    "sg:orig_category":"Bisuter\u00cda, Joyer\u00cda, Relojer\u00cda (al Por Menor)",
    "sg:phone":"+34 963 63 99 00",
    "sg:postcode":"46100",
    "sg:province":"Valencia",
    "wof:name":"Linea Trevi S.l.",
    "wof:placetype":"venue"
},
  "geometry": {"coordinates":[-0.4101319909,39.5137252808],"type":"Point"}
}