{
  "type": "Feature",
  "properties": {
    "iso:country":"ES",
    "sg:address":"Calle de Jose Maria Pereda, 14",
    "sg:city":"Bu\u00f1ol",
    "sg:orig_category":"Centros Empresariales",
    "sg:phone":"+34 962 50 17 38",
    "sg:postcode":"46360",
    "sg:province":"Valencia",
    "wof:name":"Ospina Arebalo Juan",
    "wof:placetype":"venue"
},
  "geometry": {"coordinates":[-0.7911189795,39.4206085205],"type":"Point"}
}