{
  "type": "Feature",
  "properties": {
    "addr:full":"Calle de Luna, 2 Arroyo De La Miel-benalmadena Costa M\u00e1laga 29631",
    "addr:housenumber":"2",
    "addr:postcode":"29631",
    "addr:street":"Calle De Luna;Arroyo De La Miel-Benalmadena Costa Ma\u0301Laga",
    "iso:country":"ES",
    "sg:address":"Calle de Luna, 2",
    "sg:city":"Arroyo De La Miel-benalmadena Costa",
    "sg:orig_category":"Inmobiliaria (agencias)",
    "sg:phone":"+34 952 56 65 26",
    "sg:postcode":"29631",
    "sg:province":"M\u00e1laga",
    "wof:name":"Cim 95 S.l.",
    "wof:placetype":"venue"
},
  "geometry": {"coordinates":[-4.5344848633,36.5982818604],"type":"Point"}
}