{
  "type": "Feature",
  "properties": {
    "addr:full":"Calle de Tanausu, 43 Cornisa Del Suroeste Las Palmas 35120",
    "addr:housenumber":"43",
    "addr:postcode":"35120",
    "addr:street":"Calle De Tanausu",
    "iso:country":"ES",
    "sg:address":"Calle de Tanausu, 43",
    "sg:city":"Cornisa Del Suroeste",
    "sg:orig_category":"Promotores Constructores",
    "sg:phone":"+34 928 73 51 79",
    "sg:postcode":"35120",
    "sg:province":"Las Palmas",
    "wof:name":"Baez Valeron S.l.",
    "wof:placetype":"venue"
},
  "geometry": {"coordinates":[-15.4300060272,28.1248226166],"type":"Point"}
}