{
  "type": "Feature",
  "properties": {
    "addr:full":"Carrer de Cadi, 12 Poligono Barcelona 08213",
    "addr:housenumber":"12 poligono",
    "addr:postcode":"08213",
    "addr:street":"Carrer De Cadi;Barcelona",
    "iso:country":"ES",
    "sg:address":"Carrer de Cadi, 12",
    "sg:city":"Poligono",
    "sg:orig_category":"Promotores Constructores",
    "sg:phone":"+34 937 13 32 34",
    "sg:postcode":"08213",
    "sg:province":"Barcelona",
    "wof:name":"Alesan S.l.",
    "wof:placetype":"venue"
},
  "geometry": {"coordinates":[2.2989797592,41.6482887268],"type":"Point"}
}