{
  "type": "Feature",
  "properties": {
    "addr:full":"Pla Ramassar, 34 Granollers Barcelona 08402",
    "addr:housenumber":"34",
    "addr:postcode":"08402",
    "addr:street":"Ramassar",
    "iso:country":"ES",
    "sg:address":"Pla Ramassar, 34",
    "sg:city":"Granollers",
    "sg:orig_category":"Fabricaci\u00d3n De Telas Y Sedas",
    "sg:phone":"+34 938 46 65 63",
    "sg:postcode":"08402",
    "sg:province":"Barcelona",
    "sg:website":"www.somag.es",
    "wof:name":"Somag S.l.",
    "wof:placetype":"venue"
},
  "geometry": {"coordinates":[2.3036849499,41.6107139587],"type":"Point"}
}