{
  "type": "Feature",
  "properties": {
    "addr:full":"Calle de Nuestra Se\u00d1ora De Guadalupe, 12 Oliva Frontera Badajoz 06120",
    "addr:housenumber":"12",
    "addr:postcode":"06120",
    "addr:street":"Calle De Nuestra Sen\u0303Ora De Guadalupe",
    "iso:country":"ES",
    "sg:address":"Calle de Nuestra Se\u00d1ora De Guadalupe, 12",
    "sg:city":"Oliva Frontera",
    "sg:orig_category":"Mec\u00c1nico Del Autom\u00d3vil",
    "sg:phone":"+34 924 74 03 65",
    "sg:postcode":"06120",
    "sg:province":"Badajoz",
    "wof:name":"Pombero Pitel Francisco",
    "wof:placetype":"venue"
},
  "geometry": {"coordinates":[-6.9173288345,38.2742500305],"type":"Point"}
}