{
  "type": "Feature",
  "properties": {
    "iso:country":"ES",
    "sg:address":"Calle de Jose Azorin (de), 18",
    "sg:city":"S. Martin Vega",
    "sg:orig_category":"Fabricaci\u00d3n De Distribuidores Autom\u00c1ticos",
    "sg:phone":"+34 918 94 69 32",
    "sg:postcode":"28330",
    "sg:province":"Madrid",
    "wof:name":"Vega Vending S.l.",
    "wof:placetype":"venue"
},
  "geometry": {"coordinates":[-3.577352047,40.2097625732],"type":"Point"}
}