{
  "type": "Feature",
  "properties": {
    "addr:full":"Av Comarques Catalanes (de Les), 12 Torredembarra Tarragona 43830",
    "addr:housenumber":"12",
    "addr:postcode":"43830",
    "addr:street":"Av Comarques Catalanes De Les",
    "iso:country":"ES",
    "sg:address":"Av Comarques Catalanes (de Les), 12",
    "sg:city":"Torredembarra",
    "sg:orig_category":"Mec\u00c1nico Del Autom\u00d3vil",
    "sg:phone":"+34 977 64 27 99",
    "sg:postcode":"43830",
    "sg:province":"Tarragona",
    "wof:name":"Molina Cabezuelo Jose",
    "wof:placetype":"venue"
},
  "geometry": {"coordinates":[1.3980859518,41.1474990845],"type":"Point"}
}