{
  "type": "Feature",
  "properties": {
    "iso:country":"ES",
    "sg:address":"Rbla Josep Tomas Ventosa, 21",
    "sg:city":"Vilanova I La Geltru",
    "sg:orig_category":"Loter\u00cda Y T\u00d3mbola",
    "sg:phone":"+34 938 15 13 45",
    "sg:postcode":"08800",
    "sg:province":"Barcelona",
    "wof:name":"Pages Llambrich Amadeu",
    "wof:placetype":"venue"
},
  "geometry": {"coordinates":[1.7275600433,41.2211799622],"type":"Point"}
}