{
  "type": "Feature",
  "properties": {
    "iso:country":"ES",
    "sg:address":"Avda Suecia (de), 19",
    "sg:city":"Cristianos",
    "sg:orig_category":"Confecci\u00d3n (fabricaci\u00d3n, Al Por Mayor)",
    "sg:phone":"+34 922 75 02 90",
    "sg:postcode":"38650",
    "sg:province":"Santa Cruz De Tenerife",
    "wof:name":"Depositos Y Almacenes Numero-1 S.a.",
    "wof:placetype":"venue"
},
  "geometry": {"coordinates":[-16.7313289642,28.0631198883],"type":"Point"}
}