{
  "type": "Feature",
  "properties": {
    "addr:full":"Avda Adoratrices, 37 Huelva Huelva 21004",
    "addr:housenumber":"37",
    "addr:postcode":"21004",
    "addr:street":"Avda Adoratrices",
    "iso:country":"ES",
    "sg:address":"Avda Adoratrices, 37",
    "sg:city":"Huelva",
    "sg:orig_category":"Ropa Para Se\u00d1oras (al Por Menor)",
    "sg:phone":"+34 959 26 18 12",
    "sg:postcode":"21004",
    "sg:province":"Huelva",
    "wof:name":"Vega Gonzalez Antonia",
    "wof:placetype":"venue"
},
  "geometry": {"coordinates":[-6.9427990913,37.2648925781],"type":"Point"}
}