{
  "type": "Feature",
  "properties": {
    "addr:full":"Carrer de Gallifa, 20 Cubelles Barcelona 08880",
    "addr:housenumber":"20",
    "addr:postcode":"08880",
    "addr:street":"Carrer De Gallifa",
    "iso:country":"ES",
    "sg:address":"Carrer de Gallifa, 20",
    "sg:city":"Cubelles",
    "sg:orig_category":"Bancos",
    "sg:phone":"+34 938 95 79 78",
    "sg:postcode":"08880",
    "sg:province":"Barcelona",
    "wof:name":"Banco Bilbao Vizcaya Argentaria S.a.",
    "wof:placetype":"venue"
},
  "geometry": {"coordinates":[1.6742680073,41.2101325989],"type":"Point"}
}