{
  "type": "Feature",
  "properties": {
    "iso:country":"ES",
    "sg:address":"Carrer de Olesa, 53",
    "sg:city":"Barcelona",
    "sg:orig_category":"Reposter\u00cdas",
    "sg:phone":"+34 933 40 45 91",
    "sg:postcode":"08027",
    "sg:province":"Barcelona",
    "wof:name":"Mayopan S.l.",
    "wof:placetype":"venue"
},
  "geometry": {"coordinates":[2.1855659485,41.4237937927],"type":"Point"}
}