{
  "type": "Feature",
  "properties": {
    "iso:country":"ES",
    "sg:address":"Calle de Pontevedra, 23",
    "sg:city":"Albacete",
    "sg:orig_category":"Empresas De Carpinter\u00cda De Madera",
    "sg:phone":"+34 967 23 03 60",
    "sg:postcode":"02005",
    "sg:province":"Albacete",
    "wof:name":"Muebles Arquero S.l.",
    "wof:placetype":"venue"
},
  "geometry": {"coordinates":[-1.8692909479,39.0001754761],"type":"Point"}
}