{
  "type": "Feature",
  "properties": {
    "addr:full":"Avda Roma, 14 Le\u00f3n Le\u00f3n 24001",
    "addr:housenumber":"14",
    "addr:postcode":"24001",
    "addr:street":"Avda Roma;Leo\u0301N",
    "iso:country":"ES",
    "sg:address":"Avda Roma, 14",
    "sg:city":"Le\u00f3n",
    "sg:orig_category":"Alimentaci\u00d3n General (al Por Menor)",
    "sg:phone":"+34 987 27 07 64",
    "sg:postcode":"24001",
    "sg:province":"Le\u00f3n",
    "wof:name":"Montiel Rodriguez Virginia",
    "wof:placetype":"venue"
},
  "geometry": {"coordinates":[-5.5769329071,42.5978775024],"type":"Point"}
}