{
  "type": "Feature",
  "properties": {
    "addr:full":"Plaz Aragon, 11 Zaragoza Zaragoza 50004",
    "addr:housenumber":"11",
    "addr:postcode":"50004",
    "addr:street":"Aragon",
    "iso:country":"ES",
    "sg:address":"Plaz Aragon, 11",
    "sg:city":"Zaragoza",
    "sg:orig_category":"Bisuter\u00cda, Joyer\u00cda, Relojer\u00cda (al Por Menor)",
    "sg:phone":"+34 976 23 74 92",
    "sg:postcode":"50004",
    "sg:province":"Zaragoza",
    "wof:name":"Asiain Miguel Juan",
    "wof:placetype":"venue"
},
  "geometry": {"coordinates":[-0.8849027753,41.6487693787],"type":"Point"}
}