{
  "type": "Feature",
  "properties": {
    "addr:full":"Calle de Leonardo Rucabado, 23 Castro Urdiales Cantabria 39700",
    "addr:housenumber":"23",
    "addr:postcode":"39700",
    "addr:street":"Calle De Leonardo Rucabado",
    "iso:country":"ES",
    "sg:address":"Calle de Leonardo Rucabado, 23",
    "sg:city":"Castro Urdiales",
    "sg:orig_category":"Seguridad Social",
    "sg:phone":"+34 942 86 25 50",
    "sg:postcode":"39700",
    "sg:province":"Cantabria",
    "sg:website":"www.mutuamontanesa.es",
    "wof:name":"Mutua Monta\u00f1esa Mutua De Acc De Trab Y Enfer Prof De La S.s. Num 7",
    "wof:placetype":"venue"
},
  "geometry": {"coordinates":[-3.219769001,43.3795623779],"type":"Point"}
}