{
  "type": "Feature",
  "properties": {
    "iso:country":"ES",
    "sg:address":"Calle de Huerto, 19",
    "sg:city":"Pobla Vallbona",
    "sg:orig_category":"Laboratorios Y Trabajos De Fotograf\u00cda, V\u00cddeo Y Cine",
    "sg:phone":"+34 961 66 10 96",
    "sg:postcode":"46185",
    "sg:province":"Valencia",
    "wof:name":"Video Produccio Ximo S.l.",
    "wof:placetype":"venue"
},
  "geometry": {"coordinates":[-0.5534440279,39.5925750732],"type":"Point"}
}