{
  "type": "Feature",
  "properties": {
    "addr:full":"Carrer de Pau Sans, 38 Hospitalet Llobregat Barcelona 08901",
    "addr:housenumber":"38",
    "addr:postcode":"08901",
    "addr:street":"Carrer De Pau Sans",
    "iso:country":"ES",
    "sg:address":"Carrer de Pau Sans, 38",
    "sg:city":"Hospitalet Llobregat",
    "sg:orig_category":"Mec\u00c1nico Del Autom\u00d3vil",
    "sg:phone":"+34 933 38 36 21",
    "sg:postcode":"08901",
    "sg:province":"Barcelona",
    "wof:name":"Talleres J & J S.c.p.",
    "wof:placetype":"venue"
},
  "geometry": {"coordinates":[2.1120750904,41.3621139526],"type":"Point"}
}