{
  "type": "Feature",
  "properties": {
    "iso:country":"ES",
    "sg:address":"Pla\u00c7 Major - Suchs, 2",
    "sg:city":"Suchs",
    "sg:orig_category":"Aguas (distribuci\u00d3n, Servicios)",
    "sg:phone":"+34 973 74 81 94",
    "sg:postcode":"25113",
    "sg:province":"Lleida",
    "wof:name":"Sindicatos De Riegos",
    "wof:placetype":"venue"
},
  "geometry": {"coordinates":[0.4126850069,41.703289032],"type":"Point"}
}