{
  "type": "Feature",
  "properties": {
    "iso:country":"ES",
    "sg:address":"Calle de Seijas Lozano, 5",
    "sg:city":"Motril",
    "sg:orig_category":"\u00d3ptica: Instrumentos (fabricaci\u00d3n)",
    "sg:phone":"+34 958 60 78 22",
    "sg:postcode":"18600",
    "sg:province":"Granada",
    "wof:name":"Diezmar S.l.",
    "wof:placetype":"venue"
},
  "geometry": {"coordinates":[-3.5177130699,36.7464752197],"type":"Point"}
}