{
  "type": "Feature",
  "properties": {
    "iso:country":"ES",
    "sg:address":"Calle de Manigua, 4",
    "sg:city":"Alcala Henares",
    "sg:orig_category":"Electricidad: Instaladores",
    "sg:phone":"+34 918 88 13 13",
    "sg:postcode":"28802",
    "sg:province":"Madrid",
    "wof:name":"Alonso Regueiro Manuel",
    "wof:placetype":"venue"
},
  "geometry": {"coordinates":[-3.3737649918,40.4813690186],"type":"Point"}
}