{
  "type": "Feature",
  "properties": {
    "iso:country":"ES",
    "sg:address":"Pase Mostoles (de), 55",
    "sg:city":"Parque Coimbra",
    "sg:orig_category":"Mudanzas",
    "sg:phone":"+34 916 47 39 84",
    "sg:postcode":"28935",
    "sg:province":"Madrid",
    "wof:name":"Ruiz Lozano Agustin",
    "wof:placetype":"venue"
},
  "geometry": {"coordinates":[-3.9208850861,40.3111839294],"type":"Point"}
}