{
  "type": "Feature",
  "properties": {
    "iso:country":"ES",
    "sg:address":"Carr Tarragona, 74",
    "sg:city":"Mas Aliu",
    "sg:orig_category":"Alimentaci\u00d3n General (al Por Mayor)",
    "sg:phone":"+34 972 23 29 99",
    "sg:postcode":"17181",
    "sg:province":"Girona",
    "wof:name":"Quintana Feliu Narcis",
    "wof:placetype":"venue"
},
  "geometry": {"coordinates":[2.7786879539,41.9419059753],"type":"Point"}
}