{
  "type": "Feature",
  "properties": {
    "addr:full":"Pase Doctor Vallejo Nagera, 55 Madrid Madrid 28005",
    "addr:housenumber":"55",
    "addr:postcode":"madrid;28005",
    "addr:street":"Nagera",
    "iso:country":"ES",
    "sg:address":"Pase Doctor Vallejo Nagera, 55",
    "sg:city":"Madrid",
    "sg:orig_category":"Peluqueros: De Se\u00d1oras",
    "sg:phone":"+34 913 64 27 65",
    "sg:postcode":"28005",
    "sg:province":"Madrid",
    "wof:name":"Ramos Ramos Manuela",
    "wof:placetype":"venue"
},
  "geometry": {"coordinates":[-3.7110090256,40.4027404785],"type":"Point"}
}