{
  "type": "Feature",
  "properties": {
    "iso:country":"ES",
    "sg:address":"Calle de Salina (la), 5",
    "sg:city":"Zaragoza",
    "sg:orig_category":"Sindicatos De Trabajadores",
    "sg:phone":"+34 976 39 89 00",
    "sg:postcode":"50003",
    "sg:province":"Zaragoza",
    "wof:name":"Union Sindical De Comisiones Obreras De Aragon",
    "wof:placetype":"venue"
},
  "geometry": {"coordinates":[-0.8913869858,41.6581001282],"type":"Point"}
}