{
  "type": "Feature",
  "properties": {
    "addr:full":"Calle de Escuelas, 3 Malpartida Plasencia C\u00e1ceres 10680",
    "addr:housenumber":"3;plasencia",
    "addr:postcode":"10680",
    "addr:street":"Calle De Escuelas;Ca\u0301Ceres",
    "iso:country":"ES",
    "sg:address":"Calle de Escuelas, 3",
    "sg:city":"Malpartida Plasencia",
    "sg:orig_category":"Sanatorios M\u00c9dico",
    "sg:phone":"+34 927 40 48 03",
    "sg:postcode":"10680",
    "sg:province":"C\u00e1ceres",
    "wof:name":"Servicio Extreme\u00d1o De Salud",
    "wof:placetype":"venue"
},
  "geometry": {"coordinates":[-6.0448079109,39.9805183411],"type":"Point"}
}