{
  "type": "Feature",
  "properties": {
    "addr:full":"Fuentes, 11 Mota Cuervo Cuenca 16630",
    "addr:housenumber":"11",
    "addr:postcode":"16630",
    "addr:street":"Fuentes",
    "iso:country":"ES",
    "sg:address":"Fuentes, 11",
    "sg:city":"Mota Cuervo",
    "sg:orig_category":"Soportes L\u00d3gicos, Programas Integradores De Aplicaciones (progiciels)",
    "sg:phone":"+34 967 13 95 25",
    "sg:postcode":"16630",
    "sg:province":"Cuenca",
    "sg:website":"www.asposoft.net",
    "wof:name":"Analisis Sistemas Y Procesos Automaticos S.l.",
    "wof:placetype":"venue"
},
  "geometry": {"coordinates":[-2.873462677,39.5027198792],"type":"Point"}
}