{
  "type": "Feature",
  "properties": {
    "addr:full":"Calle de Miracruz, 24 Donostia-san Sebastian Guip\u00f9zcoa 20001",
    "addr:housenumber":"24",
    "addr:postcode":"20001",
    "addr:street":"Calle De Miracruz",
    "iso:country":"ES",
    "sg:address":"Calle de Miracruz, 24",
    "sg:city":"Donostia-san Sebastian",
    "sg:orig_category":"Molduras, Junquillos, Listones Y Molduras Perforadas",
    "sg:phone":"+34 943 27 16 08",
    "sg:postcode":"20001",
    "sg:province":"Guip\u00f9zcoa",
    "wof:name":"Merchan Verdasco Alonso",
    "wof:placetype":"venue"
},
  "geometry": {"coordinates":[-1.9738570452,43.3220825195],"type":"Point"}
}