{
  "type": "Feature",
  "properties": {
    "iso:country":"ES",
    "sg:address":"Calle de Mesones, 7",
    "sg:city":"Iscar",
    "sg:orig_category":"Empresas De Carpinter\u00cda De Madera",
    "sg:phone":"+34 983 61 12 16",
    "sg:postcode":"47420",
    "sg:province":"Valladolid",
    "sg:website":"www.coherga.com",
    "wof:name":"Coherga Instalaciones Sal",
    "wof:placetype":"venue"
},
  "geometry": {"coordinates":[-4.5340189934,41.3601264954],"type":"Point"}
}