{
  "type": "Feature",
  "properties": {
    "addr:full":"Calle de Puertas De Granada, 5 Velez-rubio Almer\u00eda 04820",
    "addr:housenumber":"5",
    "addr:postcode":"04820",
    "addr:street":"Calle De Puertas De Granada;Almeri\u0301A",
    "iso:country":"ES",
    "sg:address":"Calle de Puertas De Granada, 5",
    "sg:city":"Velez-rubio",
    "sg:orig_category":"Quincaller\u00cda (al Por Menor)",
    "sg:phone":"+34 950 41 01 49",
    "sg:postcode":"04820",
    "sg:province":"Almer\u00eda",
    "wof:name":"Valles Catala Vicente",
    "wof:placetype":"venue"
},
  "geometry": {"coordinates":[-2.0766251087,37.6500549316],"type":"Point"}
}