{
  "type": "Feature",
  "properties": {
    "iso:country":"ES",
    "sg:address":"Avda Menendez Pelayo, 61",
    "sg:city":"Linea De La Concepcion",
    "sg:orig_category":"Agentes, Concesionarios Y Sucursales De Veh\u00cdculos",
    "sg:phone":"+34 956 17 34 37",
    "sg:postcode":"11300",
    "sg:province":"C\u00e1diz",
    "wof:name":"Kalai Tunning Sca",
    "wof:placetype":"venue"
},
  "geometry": {"coordinates":[-5.3417239189,36.1673545837],"type":"Point"}
}