{
  "type": "Feature",
  "properties": {
    "addr:full":"Calle de Alameda, 5 Alfacar Granada 18170",
    "addr:housenumber":"5",
    "addr:postcode":"18170",
    "addr:street":"Calle De Alameda",
    "iso:country":"ES",
    "sg:address":"Calle de Alameda, 5",
    "sg:city":"Alfacar",
    "sg:orig_category":"Cursos Particulares, Asistencia Escolar",
    "sg:phone":"+34 958 54 39 58",
    "sg:postcode":"18170",
    "sg:province":"Granada",
    "wof:name":"Martinez De Medina Maria Teresa",
    "wof:placetype":"venue"
},
  "geometry": {"coordinates":[-3.5611166954,37.2365989685],"type":"Point"}
}