{
  "type": "Feature",
  "properties": {
    "addr:full":"Calle de Vereda Del Medio, 31 Campo De Golf Santa Cruz De Tenerife 38350",
    "addr:housenumber":"31",
    "addr:postcode":"38350",
    "addr:street":"Calle De Vereda Del Medio",
    "iso:country":"ES",
    "sg:address":"Calle de Vereda Del Medio, 31",
    "sg:city":"Campo De Golf",
    "sg:orig_category":"Informaci\u00d3n Financiera Y Comercial",
    "sg:phone":"+34 922 63 76 19",
    "sg:postcode":"38350",
    "sg:province":"Santa Cruz De Tenerife",
    "wof:name":"Airline Cargo System S.l.",
    "wof:placetype":"venue"
},
  "geometry": {"coordinates":[-16.3774909973,28.4823131561],"type":"Point"}
}