{
  "type": "Feature",
  "properties": {
    "iso:country":"ES",
    "sg:address":"Calle de Cami Cebolla, 48",
    "sg:city":"Rafelbunyol",
    "sg:orig_category":"Controles De Edificaci\u00d3n (construcci\u00d3n, Seguridad)",
    "sg:phone":"+34 961 41 41 30",
    "sg:postcode":"46138",
    "sg:province":"Valencia",
    "wof:name":"Carrion & Mena Promociones",
    "wof:placetype":"venue"
},
  "geometry": {"coordinates":[-0.3270308971,39.58826828],"type":"Point"}
}