{
  "type": "Feature",
  "properties": {
    "iso:country":"ES",
    "sg:address":"Avda Vaillo, 43",
    "sg:city":"Villaviciosa Odon",
    "sg:orig_category":"Centros Empresariales",
    "sg:phone":"+34 916 16 04 92",
    "sg:postcode":"28670",
    "sg:province":"Madrid",
    "wof:name":"Mora Gomez Jacinto",
    "wof:placetype":"venue"
},
  "geometry": {"coordinates":[-3.9124920368,40.3634872437],"type":"Point"}
}