{
  "type": "Feature",
  "properties": {
    "iso:country":"ES",
    "sg:address":"Fray Melchor Cano, 52",
    "sg:city":"Tarancon",
    "sg:orig_category":"Molduras, Junquillos, Listones Y Molduras Perforadas",
    "sg:phone":"+34 969 32 04 02",
    "sg:postcode":"16400",
    "sg:province":"Cuenca",
    "wof:name":"Sanchez Nu\u00f1ez Joaquin",
    "wof:placetype":"venue"
},
  "geometry": {"coordinates":[-3.0066480637,40.0112457275],"type":"Point"}
}