{
  "type": "Feature",
  "properties": {
    "addr:full":"Calle de Hispanoamerica, 36 Alcala Selva Teruel 44432",
    "addr:housenumber":"36",
    "addr:postcode":"44432",
    "addr:street":"Calle De Hispanoamerica",
    "iso:country":"ES",
    "sg:address":"Calle de Hispanoamerica, 36",
    "sg:city":"Alcala Selva",
    "sg:orig_category":"Promotores Constructores",
    "sg:phone":"+34 978 80 10 18",
    "sg:postcode":"44432",
    "sg:province":"Teruel",
    "wof:name":"Edo Tena Ramon",
    "wof:placetype":"venue"
},
  "geometry": {"coordinates":[-0.7180609703,40.3708839417],"type":"Point"}
}