{
  "type": "Feature",
  "properties": {
    "iso:country":"ES",
    "sg:address":"Calle de Santiago Franco, 2",
    "sg:city":"Santa Maria Del Paramo",
    "sg:orig_category":"Carnicer\u00cdas, Carnicer\u00cdas",
    "sg:phone":"+34 987 35 00 27",
    "sg:postcode":"24240",
    "sg:province":"Le\u00f3n",
    "wof:name":"Porrero Herrero Alberto",
    "wof:placetype":"venue"
},
  "geometry": {"coordinates":[-5.7469420433,42.354019165],"type":"Point"}
}