{
  "type": "Feature",
  "properties": {
    "iso:country":"ES",
    "sg:address":"Carr Cervantes, 14",
    "sg:city":"Algemesi",
    "sg:orig_category":"Molduras, Junquillos, Listones Y Molduras Perforadas",
    "sg:phone":"+34 962 42 36 51",
    "sg:postcode":"46680",
    "sg:province":"Valencia",
    "wof:name":"Nacher Ferris Juan",
    "wof:placetype":"venue"
},
  "geometry": {"coordinates":[-0.4359509945,39.1916503906],"type":"Point"}
}