{
  "type": "Feature",
  "properties": {
    "addr:full":"Calle de Solano, 22 Humera-somosaguas-prado Del Rey Madrid 28223",
    "addr:housenumber":"22",
    "addr:postcode":"28223",
    "addr:street":"Calle De Solano",
    "iso:country":"ES",
    "sg:address":"Calle de Solano, 22",
    "sg:city":"Humera-somosaguas-prado Del Rey",
    "sg:orig_category":"Agencias De Relaciones P\u00dablicas",
    "sg:phone":"+34 915 18 33 86",
    "sg:postcode":"28223",
    "sg:province":"Madrid",
    "wof:name":"Eurosearch-nts S.l.",
    "wof:placetype":"venue"
},
  "geometry": {"coordinates":[-3.7955040932,40.4115104675],"type":"Point"}
}