{
  "type": "Feature",
  "properties": {
    "iso:country":"ES",
    "sg:address":"Rua Cami\u00d1o Real (do), 55",
    "sg:city":"Lugo",
    "sg:orig_category":"Ingeniero",
    "sg:phone":"+34 982 24 63 04",
    "sg:postcode":"27004",
    "sg:province":"Lugo",
    "wof:name":"Yepes De Paz Eduardo",
    "wof:placetype":"venue"
},
  "geometry": {"coordinates":[-7.5622625351,43.0162124634],"type":"Point"}
}