{
  "type": "Feature",
  "properties": {
    "iso:country":"ES",
    "sg:address":"Zubiarte, 21",
    "sg:city":"Huarte",
    "sg:orig_category":"Molduras, Junquillos, Listones Y Molduras Perforadas",
    "sg:phone":"+34 948 33 06 72",
    "sg:postcode":"31620",
    "sg:province":"Navarra",
    "wof:name":"Oiezki Taberna S,i",
    "wof:placetype":"venue"
},
  "geometry": {"coordinates":[-1.5908089876,42.8317108154],"type":"Point"}
}