{
  "type": "Feature",
  "properties": {
    "addr:full":"Plaz Major, 10 Torrent Valencia 46900",
    "addr:housenumber":"10",
    "addr:postcode":"46900",
    "addr:street":"Plaz Major;Valencia",
    "iso:country":"ES",
    "sg:address":"Plaz Major, 10",
    "sg:city":"Torrent",
    "sg:orig_category":"Guarder\u00cdas",
    "sg:phone":"+34 961 56 56 00",
    "sg:postcode":"46900",
    "sg:province":"Valencia",
    "wof:name":"Simo Mu\u00f1oz Desamparados",
    "wof:placetype":"venue"
},
  "geometry": {"coordinates":[-0.4638060033,39.4368515015],"type":"Point"}
}