{
  "type": "Feature",
  "properties": {
    "addr:full":"Calle de Miguel De Cervantes, 30 Chipiona C\u00e1diz 11550",
    "addr:housenumber":"30",
    "addr:postcode":"11550",
    "addr:street":"Calle De Miguel De Cervantes",
    "iso:country":"ES",
    "sg:address":"Calle de Miguel De Cervantes, 30",
    "sg:city":"Chipiona",
    "sg:orig_category":"Ropa Para Se\u00d1oras (al Por Menor)",
    "sg:phone":"+34 956 37 34 30",
    "sg:postcode":"11550",
    "sg:province":"C\u00e1diz",
    "wof:name":"Harto Cordero Maria",
    "wof:placetype":"venue"
},
  "geometry": {"coordinates":[-6.4339828491,36.7359848022],"type":"Point"}
}