{
  "type": "Feature",
  "properties": {
    "addr:full":"Calle de La Del Manojo De Rosas, 12 Madrid Madrid 28041",
    "addr:housenumber":"12",
    "addr:postcode":"madrid;28041",
    "addr:street":"Calle De La Del Manojo De Rosas",
    "iso:country":"ES",
    "sg:address":"Calle de La Del Manojo De Rosas, 12",
    "sg:city":"Madrid",
    "sg:orig_category":"Abogados",
    "sg:phone":"+34 913 17 67 89",
    "sg:postcode":"28041",
    "sg:province":"Madrid",
    "wof:name":"Legis Abogados Cb.",
    "wof:placetype":"venue"
},
  "geometry": {"coordinates":[-3.6976835728,40.3600692749],"type":"Point"}
}