{
  "type": "Feature",
  "properties": {
    "addr:full":"Calle de Valdes, 43 Puerto De Santa Maria C\u00e1diz 11500",
    "addr:housenumber":"43",
    "addr:postcode":"11500",
    "addr:street":"Calle De Valdes;Ca\u0301Diz",
    "iso:country":"ES",
    "sg:address":"Calle de Valdes, 43",
    "sg:city":"Puerto De Santa Maria",
    "sg:orig_category":"Estancos",
    "sg:phone":"+34 956 85 26 56",
    "sg:postcode":"11500",
    "sg:province":"C\u00e1diz",
    "wof:name":"Castro Hernandez Margarita",
    "wof:placetype":"venue"
},
  "geometry": {"coordinates":[-6.2368588448,36.5982780457],"type":"Point"}
}