{
  "type": "Feature",
  "properties": {
    "iso:country":"ES",
    "sg:address":"Calle de Ruiz De Alarcon, 19",
    "sg:city":"Alacant",
    "sg:orig_category":"Reposter\u00cdas",
    "sg:phone":"+34 965 17 69 36",
    "sg:postcode":"03009",
    "sg:province":"Alicante",
    "wof:name":"Martinez Mendez Antonio",
    "wof:placetype":"venue"
},
  "geometry": {"coordinates":[-0.505892992,38.3685188293],"type":"Point"}
}