{
  "type": "Feature",
  "properties": {
    "addr:full":"Kale Nagusia, 7 Idiazabal Guip\u00f9zcoa 20213",
    "addr:housenumber":"7",
    "addr:postcode":"20213",
    "addr:street":"Kale Nagusia;Guipu\u0300Zcoa",
    "iso:country":"ES",
    "sg:address":"Kale Nagusia, 7",
    "sg:city":"Idiazabal",
    "sg:orig_category":"Pescader\u00cdas (al Por Menor)",
    "sg:phone":"+34 943 18 76 99",
    "sg:postcode":"20213",
    "sg:province":"Guip\u00f9zcoa",
    "wof:name":"Imaz Insausti Maria Aranzazu",
    "wof:placetype":"venue"
},
  "geometry": {"coordinates":[-2.2322790623,43.0144882202],"type":"Point"}
}