{
  "type": "Feature",
  "properties": {
    "iso:country":"ES",
    "sg:address":"Avda Generalitat, 20",
    "sg:city":"Palleja",
    "sg:orig_category":"Carnicer\u00cdas, Carnicer\u00cdas",
    "sg:phone":"+34 936 63 31 06",
    "sg:postcode":"08780",
    "sg:province":"Barcelona",
    "wof:name":"Corporacion Alimentaria Guissona S.a.",
    "wof:placetype":"venue"
},
  "geometry": {"coordinates":[1.9970829487,41.4226799011],"type":"Point"}
}