{
  "type": "Feature",
  "properties": {
    "iso:country":"ES",
    "sg:address":"Calle de Siete De Marzo, 11",
    "sg:city":"Union",
    "sg:orig_category":"Alquiler De V\u00cddeo",
    "sg:phone":"+34 968 54 09 22",
    "sg:postcode":"30360",
    "sg:province":"Murcia",
    "wof:name":"Pagan Sanchez Ramon",
    "wof:placetype":"venue"
},
  "geometry": {"coordinates":[-0.8807039857,37.6188964844],"type":"Point"}
}