{
  "type": "Feature",
  "properties": {
    "addr:full":"Calle de Barquillo, 29 Madrid Madrid 28004",
    "addr:housenumber":"29",
    "addr:postcode":"madrid;28004",
    "addr:street":"Calle De Barquillo",
    "iso:country":"ES",
    "sg:address":"Calle de Barquillo, 29",
    "sg:city":"Madrid",
    "sg:orig_category":"Empresarios Y Productoras De Espect\u00c1culos",
    "sg:phone":"+34 915 32 05 01",
    "sg:postcode":"28004",
    "sg:province":"Madrid",
    "wof:name":"Discovery 2 Localizaciones S.l",
    "wof:placetype":"venue"
},
  "geometry": {"coordinates":[-3.6956009865,40.4230079651],"type":"Point"}
}