{
  "type": "Feature",
  "properties": {
    "iso:country":"ES",
    "sg:address":"Pase Regino Sainz De La Maza, 6",
    "sg:city":"Burgos",
    "sg:orig_category":"Centros De Adelgazamiento Y De Est\u00c9tica",
    "sg:phone":"+34 947 20 54 14",
    "sg:postcode":"09004",
    "sg:province":"Burgos",
    "wof:name":"Centro Del Sol Burgos Sl",
    "wof:placetype":"venue"
},
  "geometry": {"coordinates":[-3.692291975,42.3433036804],"type":"Point"}
}