{
  "type": "Feature",
  "properties": {
    "iso:country":"ES",
    "sg:address":"Avda Malaga, 12",
    "sg:city":"Cala Moral",
    "sg:orig_category":"Ingenier\u00cda, Centros De Estudios (diversos)",
    "sg:phone":"+34 952 40 51 97",
    "sg:postcode":"29720",
    "sg:province":"M\u00e1laga",
    "wof:name":"Bituman Trabajos Asfalticos S.l.",
    "wof:placetype":"venue"
},
  "geometry": {"coordinates":[-4.3039898872,36.7159805298],"type":"Point"}
}