{
  "type": "Feature",
  "properties": {
    "iso:country":"ES",
    "sg:address":"Calle de Veintinueve De Abril, 64",
    "sg:city":"Palmas De Gran Canaria",
    "sg:orig_category":"Ropa Para Se\u00d1oras (al Por Menor)",
    "sg:phone":"+34 928 26 34 10",
    "sg:postcode":"35007",
    "sg:province":"Las Palmas",
    "wof:name":"Martinez Amor Miguel",
    "wof:placetype":"venue"
},
  "geometry": {"coordinates":[-15.4325065613,28.1406345367],"type":"Point"}
}