{
  "type": "Feature",
  "properties": {
    "addr:full":"Avgd Garrigues, 38 Lleida Lleida 25001",
    "addr:housenumber":"38",
    "addr:postcode":"25001",
    "iso:country":"ES",
    "sg:address":"Avgd Garrigues, 38",
    "sg:city":"Lleida",
    "sg:orig_category":"Frutas, Legumbres Frescas Y Tempranas (al Por Menor)",
    "sg:phone":"+34 973 21 19 15",
    "sg:postcode":"25001",
    "sg:province":"Lleida",
    "wof:name":"Vilodi S.a.",
    "wof:placetype":"venue"
},
  "geometry": {"coordinates":[0.631806016,41.611530304],"type":"Point"}
}