{
  "type": "Feature",
  "properties": {
    "addr:full":"Avda Andalucia (de), 123 Alcala Rio Sevilla 41200",
    "addr:housenumber":"123",
    "addr:postcode":"41200",
    "addr:street":"Avda Andalucia De",
    "iso:country":"ES",
    "sg:address":"Avda Andalucia (de), 123",
    "sg:city":"Alcala Rio",
    "sg:orig_category":"Molduras, Junquillos, Listones Y Molduras Perforadas",
    "sg:phone":"+34 955 65 07 97",
    "sg:postcode":"41200",
    "sg:province":"Sevilla",
    "wof:name":"Bares El Chaparral S.l.",
    "wof:placetype":"venue"
},
  "geometry": {"coordinates":[-5.978676796,37.5221405029],"type":"Point"}
}