{
  "type": "Feature",
  "properties": {
    "iso:country":"ES",
    "sg:address":"Rond Port, Del, 58",
    "sg:city":"Manacor",
    "sg:orig_category":"Mec\u00c1nico Del Autom\u00d3vil",
    "sg:phone":"+34 971 55 47 57",
    "sg:postcode":"07500",
    "sg:province":"Islas Baleares",
    "wof:name":"Masdeu Soler Jose",
    "wof:placetype":"venue"
},
  "geometry": {"coordinates":[3.2047450542,39.568649292],"type":"Point"}
}