{
  "type": "Feature",
  "properties": {
    "iso:country":"ES",
    "sg:address":"Toribio Etxebarria Kalea, 11",
    "sg:city":"Eibar",
    "sg:orig_category":"Estancos",
    "sg:phone":"+34 943 70 27 85",
    "sg:postcode":"20600",
    "sg:province":"Guip\u00f9zcoa",
    "wof:name":"Maria Dolores Zabala Beristain",
    "wof:placetype":"venue"
},
  "geometry": {"coordinates":[-2.4721136093,43.1852264404],"type":"Point"}
}