{
  "type": "Feature",
  "properties": {
    "iso:country":"ES",
    "sg:address":"Humilladero, 1",
    "sg:city":"Brozas",
    "sg:orig_category":"Alimentaci\u00d3n General (al Por Menor)",
    "sg:phone":"+34 927 39 52 15",
    "sg:postcode":"10950",
    "sg:province":"C\u00e1ceres",
    "wof:name":"Pino Santano Fabiana",
    "wof:placetype":"venue"
},
  "geometry": {"coordinates":[-6.7744731903,39.6103897095],"type":"Point"}
}