{
  "type": "Feature",
  "properties": {
    "addr:full":"Calle de Mayor, 2 Alcocer Guadalajara 19125",
    "addr:housenumber":"2",
    "addr:postcode":"19125",
    "addr:street":"Calle De Mayor",
    "iso:country":"ES",
    "sg:address":"Calle de Mayor, 2",
    "sg:city":"Alcocer",
    "sg:orig_category":"Cajas Para Embalar",
    "sg:phone":"+34 949 35 51 62",
    "sg:postcode":"19125",
    "sg:province":"Guadalajara",
    "wof:name":"Caja Rural Provincial De Toledo",
    "wof:placetype":"venue"
},
  "geometry": {"coordinates":[-2.6148729324,40.4712181091],"type":"Point"}
}