{
  "type": "Feature",
  "properties": {
    "iso:country":"ES",
    "sg:address":"Ctra. Razo, S/n",
    "sg:city":"Carballo",
    "sg:orig_category":"Centros Empresariales",
    "sg:phone":"+34 981 70 12 95",
    "sg:postcode":"15100",
    "sg:province":"A Coru\u00f1a",
    "wof:name":"Sociedad Porteiro Fernandez C.d",
    "wof:placetype":"venue"
},
  "geometry": {"coordinates":[-8.6918792725,43.2225761414],"type":"Point"}
}