{
  "type": "Feature",
  "properties": {
    "iso:country":"ES",
    "sg:address":"Hesperides, S/n",
    "sg:city":"Malaga",
    "sg:orig_category":"Promotores Constructores",
    "sg:phone":"+34 952 23 01 92",
    "sg:postcode":"29004",
    "sg:province":"M\u00e1laga",
    "wof:name":"Sociedad De Desarrollo Inmobiliario S.a.",
    "wof:placetype":"venue"
},
  "geometry": {"coordinates":[-4.4617562294,36.6640052795],"type":"Point"}
}