{
  "type": "Feature",
  "properties": {
    "iso:country":"ES",
    "sg:address":"Avda Carlos Iii, 118",
    "sg:city":"Campillo Del Moro",
    "sg:orig_category":"Negocio De Madera",
    "sg:phone":"+34 950 34 56 76",
    "sg:postcode":"04720",
    "sg:province":"Almer\u00eda",
    "wof:name":"Roblebaltico S.l.",
    "wof:placetype":"venue"
},
  "geometry": {"coordinates":[-2.5974500179,36.801410675],"type":"Point"}
}