{
  "type": "Feature",
  "properties": {
    "addr:full":"Calle de Tinamala, 10 Arrecife Las Palmas 35500",
    "addr:housenumber":"10",
    "addr:postcode":"35500",
    "addr:street":"Calle De Tinamala",
    "iso:country":"ES",
    "sg:address":"Calle de Tinamala, 10",
    "sg:city":"Arrecife",
    "sg:orig_category":"Pintura Y Barniz (al Por Menor)",
    "sg:phone":"+34 928 81 02 23",
    "sg:postcode":"35500",
    "sg:province":"Las Palmas",
    "wof:name":"Ojeda Ramos Jose Antonio",
    "wof:placetype":"venue"
},
  "geometry": {"coordinates":[-13.5569925308,28.9688987732],"type":"Point"}
}