{
  "type": "Feature",
  "properties": {
    "addr:full":"Calle de Piedra Redonda, 37 Olivos-la Postura Santa Cruz De Tenerife 38670",
    "addr:housenumber":"37",
    "addr:postcode":"38670",
    "addr:street":"Calle De Piedra Redonda",
    "iso:country":"ES",
    "sg:address":"Calle de Piedra Redonda, 37",
    "sg:city":"Olivos-la Postura",
    "sg:orig_category":"Carnicer\u00cdas, Carnicer\u00cdas",
    "sg:phone":"+34 922 78 06 57",
    "sg:postcode":"38670",
    "sg:province":"Santa Cruz De Tenerife",
    "wof:name":"Martin Delgado Leonardo Manuel",
    "wof:placetype":"venue"
},
  "geometry": {"coordinates":[-16.7311191559,28.121629715],"type":"Point"}
}