{
  "type": "Feature",
  "properties": {
    "iso:country":"ES",
    "sg:address":"Pg Pla\u00c7a Major, 51",
    "sg:city":"Sabadell",
    "sg:orig_category":"Sociedades, Compa\u00d1\u00cdas Aseguradoras",
    "sg:phone":"+34 937 27 73 50",
    "sg:postcode":"08201",
    "sg:province":"Barcelona",
    "wof:name":"A.c.i Associats 93 S.l.",
    "wof:placetype":"venue"
},
  "geometry": {"coordinates":[2.108782053,41.5480995178],"type":"Point"}
}