{
  "type": "Feature",
  "properties": {
    "addr:full":"Nevero Doce, S/n Badajoz Badajoz 06006",
    "addr:housenumber":"s / n",
    "addr:postcode":"06006",
    "iso:country":"ES",
    "sg:address":"Nevero Doce, S/n",
    "sg:city":"Badajoz",
    "sg:orig_category":"Fabrica De Cer\u00c1micas",
    "sg:phone":"+34 924 26 13 62",
    "sg:postcode":"06006",
    "sg:province":"Badajoz",
    "wof:name":"Ceramica Artistica Barcarrota S.l.",
    "wof:placetype":"venue"
},
  "geometry": {"coordinates":[-6.9920787811,38.8937950134],"type":"Point"}
}