{
  "type": "Feature",
  "properties": {
    "addr:full":"Maqueda, 41 Sevilla Sevilla 41006",
    "addr:postcode":"41006",
    "iso:country":"ES",
    "sg:address":"Maqueda, 41",
    "sg:city":"Sevilla",
    "sg:orig_category":"Comercio De Piezas De Recambio Y De Accesorios De Veh\u00cdculos, Veh\u00cdculos Industriales",
    "sg:phone":"+34 954 92 28 60",
    "sg:postcode":"41006",
    "sg:province":"Sevilla",
    "wof:name":"Autorecambios Hienipa S.l.",
    "wof:placetype":"venue"
},
  "geometry": {"coordinates":[-5.9523482323,37.3699035645],"type":"Point"}
}