{
  "type": "Feature",
  "properties": {
    "addr:full":"Calle de Matias Perello, 16 Valencia Valencia 46005",
    "addr:housenumber":"16",
    "addr:postcode":"46005",
    "addr:street":"Calle De Matias Perello",
    "iso:country":"ES",
    "sg:address":"Calle de Matias Perello, 16",
    "sg:city":"Valencia",
    "sg:orig_category":"Agentes Generales De Seguros",
    "sg:phone":"+34 963 95 28 12",
    "sg:postcode":"46005",
    "sg:province":"Valencia",
    "wof:name":"Vila Vidal Jose Vicente",
    "wof:placetype":"venue"
},
  "geometry": {"coordinates":[-0.3685052097,39.4611663818],"type":"Point"}
}