{
  "type": "Feature",
  "properties": {
    "iso:country":"ES",
    "sg:address":"Avda Andalucia, 1",
    "sg:city":"Atarfe",
    "sg:orig_category":"Molduras, Junquillos, Listones Y Molduras Perforadas",
    "sg:phone":"+34 958 43 80 23",
    "sg:postcode":"18230",
    "sg:province":"Granada",
    "wof:name":"Alanis Ortega Venancio",
    "wof:placetype":"venue"
},
  "geometry": {"coordinates":[-3.6897337437,37.2229194641],"type":"Point"}
}