{
  "type": "Feature",
  "properties": {
    "addr:full":"Calle de Alfredo Corrochano, 115 Malaga M\u00e1laga 29006",
    "addr:housenumber":"115",
    "addr:postcode":"29006",
    "addr:street":"Calle De Alfredo Corrochano;Ma\u0301Laga",
    "iso:country":"ES",
    "sg:address":"Calle de Alfredo Corrochano, 115",
    "sg:city":"Malaga",
    "sg:orig_category":"Fabricaci\u00d3n, Venta, Instalaci\u00d3n De R\u00d3tulos, De R\u00d3tulos Luminosos",
    "sg:phone":"+34 952 31 28 16",
    "sg:postcode":"29006",
    "sg:province":"M\u00e1laga",
    "wof:name":"Espejo Velasco Francisco Javier",
    "wof:placetype":"venue"
},
  "geometry": {"coordinates":[-4.4849081039,36.713760376],"type":"Point"}
}