{
  "type": "Feature",
  "properties": {
    "addr:full":"Calle de Mayor, 34 Albacete Albacete 02002",
    "addr:housenumber":"34",
    "addr:postcode":"02002",
    "addr:street":"Calle De Mayor",
    "iso:country":"ES",
    "sg:address":"Calle de Mayor, 34",
    "sg:city":"Albacete",
    "sg:orig_category":"Centros Comerciales Y Grandes Tiendas",
    "sg:phone":"+34 967 21 87 79",
    "sg:postcode":"02002",
    "sg:province":"Albacete",
    "sg:website":"www.bazarcanarias.com",
    "wof:name":"Gomez Rebenaque Carlos",
    "wof:placetype":"venue"
},
  "geometry": {"coordinates":[-1.8538589478,38.9929885864],"type":"Point"}
}