{
  "type": "Feature",
  "properties": {
    "addr:full":"Calle de Alfonso Vi, 43 Segovia Segovia 40004",
    "addr:housenumber":"43",
    "addr:postcode":"40004",
    "addr:street":"Calle De Alfonso Vi",
    "iso:country":"ES",
    "sg:address":"Calle de Alfonso Vi, 43",
    "sg:city":"Segovia",
    "sg:orig_category":"Mercer\u00cda, Lencer\u00cda (al Por Menor)",
    "sg:phone":"+34 921 42 50 59",
    "sg:postcode":"40004",
    "sg:province":"Segovia",
    "wof:name":"Ramos Matute Maximo",
    "wof:placetype":"venue"
},
  "geometry": {"coordinates":[-4.1057376862,40.9424285889],"type":"Point"}
}