{
  "type": "Feature",
  "properties": {
    "addr:full":"Calle de Valladolid, 10 Medina Campo Valladolid 47400",
    "addr:housenumber":"10",
    "addr:postcode":"47400",
    "addr:street":"Calle De Valladolid",
    "iso:country":"ES",
    "sg:address":"Calle de Valladolid, 10",
    "sg:city":"Medina Campo",
    "sg:orig_category":"Promotores Constructores",
    "sg:phone":"+34 983 80 36 68",
    "sg:postcode":"47400",
    "sg:province":"Valladolid",
    "wof:name":"Constructora Villa Escusa S.a.",
    "wof:placetype":"venue"
},
  "geometry": {"coordinates":[-4.9131989479,41.312210083],"type":"Point"}
}