{
  "type": "Feature",
  "properties": {
    "iso:country":"ES",
    "sg:address":"Avda Madrid (de), 2",
    "sg:city":"Xinzo De Limia",
    "sg:orig_category":"Farmacias",
    "sg:phone":"+34 988 46 23 68",
    "sg:postcode":"32630",
    "sg:province":"Ourense",
    "wof:name":"Gomez Penin Antonio",
    "wof:placetype":"venue"
},
  "geometry": {"coordinates":[-7.7158370018,42.0594749451],"type":"Point"}
}