{
  "type": "Feature",
  "properties": {
    "iso:country":"ES",
    "sg:address":"Carretera De Villasandino, S/n",
    "sg:city":"Grijalba",
    "sg:orig_category":"Producci\u00d3n, Venta De Productos De Agricultura Biol\u00d3gica",
    "sg:phone":"+34 947 37 51 03",
    "sg:postcode":"09128",
    "sg:province":"Burgos",
    "wof:name":"La Corrala Sociedad Cooperativa",
    "wof:placetype":"venue"
},
  "geometry": {"coordinates":[-4.117816925,42.4117126465],"type":"Point"}
}