{
  "type": "Feature",
  "properties": {
    "iso:country":"ES",
    "sg:address":"Calle de Soto (el), 10",
    "sg:city":"Etxauri",
    "sg:orig_category":"Institutos De Belleza",
    "sg:phone":"+34 948 32 93 92",
    "sg:postcode":"31174",
    "sg:province":"Navarra",
    "wof:name":"Jauregui Navarro Nerea",
    "wof:placetype":"venue"
},
  "geometry": {"coordinates":[-1.7900739908,42.7936630249],"type":"Point"}
}