{
  "type": "Feature",
  "properties": {
    "iso:country":"ES",
    "sg:address":"Avda Andalucia, 2",
    "sg:city":"Loja",
    "sg:orig_category":"Mec\u00c1nico Del Autom\u00d3vil",
    "sg:phone":"+34 958 32 00 07",
    "sg:postcode":"18300",
    "sg:province":"Granada",
    "wof:name":"El Genil Talleres Mecanicos S.l.",
    "wof:placetype":"venue"
},
  "geometry": {"coordinates":[-4.1640429497,37.1687545776],"type":"Point"}
}