{
  "type": "Feature",
  "properties": {
    "addr:full":"Concha, S/n S. Martin Lui\u00f1a Asturias 33155",
    "addr:housenumber":"s",
    "addr:postcode":"33155",
    "addr:street":"Concha;/ N S. Martin Luin\u0303A Asturias",
    "iso:country":"ES",
    "sg:address":"Concha, S/n",
    "sg:city":"S. Martin Lui\u00f1a",
    "sg:orig_category":"Inform\u00c1tica (estudios, Servicios, Asesor\u00cda, Formaci\u00d3n)",
    "sg:phone":"+34 985 59 61 60",
    "sg:postcode":"33155",
    "sg:province":"Asturias",
    "wof:name":"Sociedad Regional De Informatica S.a.",
    "wof:placetype":"venue"
},
  "geometry": {"coordinates":[-6.2274980545,43.5503578186],"type":"Point"}
}