{
  "type": "Feature",
  "properties": {
    "iso:country":"ES",
    "sg:address":"Calle de Santiago Diego Madrazo, S/n",
    "sg:city":"Salamanca",
    "sg:orig_category":"Alquiler De Casas Y Habitaciones Amuebladas",
    "sg:phone":"+34 923 16 07 00",
    "sg:postcode":"37006",
    "sg:province":"Salamanca",
    "wof:name":"Edimaro S.a.",
    "wof:placetype":"venue"
},
  "geometry": {"coordinates":[-5.6780438423,40.9727859497],"type":"Point"}
}