{
  "type": "Feature",
  "properties": {
    "addr:full":"Pasaje Espinel, 73 Ronda M\u00e1laga 29400",
    "addr:housenumber":"73",
    "addr:postcode":"29400",
    "addr:street":"Pasaje Espinel;Ronda Ma\u0301Laga",
    "iso:country":"ES",
    "sg:address":"Pasaje Espinel, 73",
    "sg:city":"Ronda",
    "sg:orig_category":"Art\u00cdculos De Regalo (al Por Menor)",
    "sg:phone":"+34 952 87 95 86",
    "sg:postcode":"29400",
    "sg:province":"M\u00e1laga",
    "wof:name":"Rey Martinez Juan Carlos",
    "wof:placetype":"venue"
},
  "geometry": {"coordinates":[-5.1662788391,36.7417945862],"type":"Point"}
}