{
  "type": "Feature",
  "properties": {
    "addr:full":"Pase Alcalde Rafael Ginel, Maritimo, 10 Melilla Melilla 52006",
    "addr:housenumber":"10",
    "addr:postcode":"52006",
    "addr:street":"Alcalde Rafael Ginel Maritimo",
    "iso:country":"ES",
    "sg:address":"Pase Alcalde Rafael Ginel, Maritimo, 10",
    "sg:city":"Melilla",
    "sg:orig_category":"Centros P\u00dablicos De Formaci\u00d3n Profesional Y T\u00c9cnica",
    "sg:phone":"+34 952 67 70 17",
    "sg:postcode":"52006",
    "sg:province":"Melilla",
    "wof:name":"Colegio Oficial De Medicos De Melilla",
    "wof:placetype":"venue"
},
  "geometry": {"coordinates":[-2.9383699894,35.2764587402],"type":"Point"}
}