{
  "type": "Feature",
  "properties": {
    "addr:full":"Avda Espa\u00d1a, S/n Chillon Ciudad Real 13412",
    "addr:housenumber":"s / n",
    "addr:postcode":"chillon;13412",
    "addr:street":"Avda Espan\u0303A",
    "iso:country":"ES",
    "sg:address":"Avda Espa\u00d1a, S/n",
    "sg:city":"Chillon",
    "sg:orig_category":"Promotores Constructores",
    "sg:phone":"+34 926 71 17 57",
    "sg:postcode":"13412",
    "sg:province":"Ciudad Real",
    "wof:name":"Construcciones Mena Cardenas S.l.",
    "wof:placetype":"venue"
},
  "geometry": {"coordinates":[-4.8690829277,38.7959251404],"type":"Point"}
}