{
  "type": "Feature",
  "properties": {
    "iso:country":"ES",
    "sg:address":"Avgd Pearson, 45",
    "sg:city":"Lleida",
    "sg:orig_category":"Molduras, Junquillos, Listones Y Molduras Perforadas",
    "sg:phone":"+34 973 23 25 80",
    "sg:postcode":"25005",
    "sg:province":"Lleida",
    "wof:name":"Camps Alvarez Francisco Jose",
    "wof:placetype":"venue"
},
  "geometry": {"coordinates":[0.641782999,41.62733078],"type":"Point"}
}