{
  "type": "Feature",
  "properties": {
    "addr:full":"Calle de Rosalia De Castro, 13 Coru\u00d1a A Coru\u00f1a 15004",
    "addr:housenumber":"13",
    "addr:postcode":"15004",
    "addr:street":"Calle De Rosalia De Castro;Corun\u0303A",
    "iso:country":"ES",
    "sg:address":"Calle de Rosalia De Castro, 13",
    "sg:city":"Coru\u00d1a",
    "sg:orig_category":"Asesor\u00cda Sobre Comunicaci\u00d3n De Empresas",
    "sg:phone":"+34 981 22 85 77",
    "sg:postcode":"15004",
    "sg:province":"A Coru\u00f1a",
    "wof:name":"Tecni Coru\u00f1a S.l.",
    "wof:placetype":"venue"
},
  "geometry": {"coordinates":[-8.4078588486,43.3659057617],"type":"Point"}
}