{
  "type": "Feature",
  "properties": {
    "iso:country":"ES",
    "sg:address":"Calle de Profesor Saez, 7",
    "sg:city":"Salamanca",
    "sg:orig_category":"Centros De Educaci\u00d3n Especial",
    "sg:phone":"+34 923 23 01 03",
    "sg:postcode":"37007",
    "sg:province":"Salamanca",
    "wof:name":"Colegio Nacional Masculino Juan Jaen",
    "wof:placetype":"venue"
},
  "geometry": {"coordinates":[-5.6659808159,40.9697761536],"type":"Point"}
}