{
  "type": "Feature",
  "properties": {
    "addr:full":"Ctra Carrion, S/n Ciudad Real Ciudad Real 13005",
    "addr:housenumber":"s / n",
    "addr:postcode":"13005",
    "addr:street":"Ctra Carrion",
    "iso:country":"ES",
    "sg:address":"Ctra Carrion, S/n",
    "sg:city":"Ciudad Real",
    "sg:orig_category":"Chapister\u00cda",
    "sg:phone":"+34 926 27 41 52",
    "sg:postcode":"13005",
    "sg:province":"Ciudad Real",
    "wof:name":"Hispanomocion S.a.",
    "wof:placetype":"venue"
},
  "geometry": {"coordinates":[-3.9127969742,38.988067627],"type":"Point"}
}