{
  "type": "Feature",
  "properties": {
    "addr:full":"Carrer de Aigues Del Llobregat, 62 Hospitalet Llobregat Barcelona 08905",
    "addr:housenumber":"62",
    "addr:postcode":"08905",
    "addr:street":"Carrer De Aigues Del Llobregat",
    "iso:country":"ES",
    "sg:address":"Carrer de Aigues Del Llobregat, 62",
    "sg:city":"Hospitalet Llobregat",
    "sg:orig_category":"Inmobiliaria (agencias)",
    "sg:phone":"+34 934 38 26 22",
    "sg:postcode":"08905",
    "sg:province":"Barcelona",
    "sg:website":"www.fincasblanco.com",
    "wof:name":"Fincas Blanco L'hospitalet S.l.",
    "wof:placetype":"venue"
},
  "geometry": {"coordinates":[2.1069400311,41.3725891113],"type":"Point"}
}