{
  "type": "Feature",
  "properties": {
    "iso:country":"ES",
    "sg:address":"Calle de Postas, 23",
    "sg:city":"Ciudad Real",
    "sg:orig_category":"Cajas De Ahorro",
    "sg:phone":"+34 926 21 43 48",
    "sg:postcode":"13001",
    "sg:province":"Ciudad Real",
    "wof:name":"Caja Espa\u00d1a De Inversiones Caja De Ahorros Y Monte De Piedad",
    "wof:placetype":"venue"
},
  "geometry": {"coordinates":[-3.9302830696,38.9843673706],"type":"Point"}
}