{
  "type": "Feature",
  "properties": {
    "iso:country":"ES",
    "sg:address":"Poligono Industrial, 33",
    "sg:city":"Caba\u00f1as Raras",
    "sg:orig_category":"Fabricaci\u00d3n De Moldes Y Modelos",
    "sg:phone":"+34 987 42 17 23",
    "sg:postcode":"24412",
    "sg:province":"Le\u00f3n",
    "sg:website":"www.ddmsl.com",
    "wof:name":"Dise\u00f1o Y Desarrollo De Matriceria S. L.",
    "wof:placetype":"venue"
},
  "geometry": {"coordinates":[-6.6369829178,42.6198806763],"type":"Point"}
}