{
  "type": "Feature",
  "properties": {
    "addr:full":"Carrer de Major, 6 S. Boi Llobregat Barcelona 08830",
    "addr:housenumber":"6",
    "addr:postcode":"08830",
    "addr:street":"Carrer De Major",
    "iso:country":"ES",
    "sg:address":"Carrer de Major, 6",
    "sg:city":"S. Boi Llobregat",
    "sg:orig_category":"Promotores Constructores",
    "sg:phone":"+34 936 30 18 41",
    "sg:postcode":"08830",
    "sg:province":"Barcelona",
    "wof:name":"Companyia Local D'actuacions Urbanistiques Santboianes S.a.",
    "wof:placetype":"venue"
},
  "geometry": {"coordinates":[2.043076992,41.3470916748],"type":"Point"}
}