{
  "type": "Feature",
  "properties": {
    "addr:full":"Carrer de Ignasi Iglesias, 79 Barcelona Barcelona 08030",
    "addr:housenumber":"79",
    "addr:postcode":"08030",
    "addr:street":"Carrer De Ignasi Iglesias",
    "iso:country":"ES",
    "sg:address":"Carrer de Ignasi Iglesias, 79",
    "sg:city":"Barcelona",
    "sg:orig_category":"Cajas De Ahorro",
    "sg:phone":"+34 933 46 35 11",
    "sg:postcode":"08030",
    "sg:province":"Barcelona",
    "wof:name":"Caixa D'estalvis I Pensions De Barcelona",
    "wof:placetype":"venue"
},
  "geometry": {"coordinates":[2.1864109039,41.4337730408],"type":"Point"}
}