{
  "type": "Feature",
  "properties": {
    "iso:country":"ES",
    "sg:address":"Calle de Delicias, 18",
    "sg:city":"Santaella",
    "sg:orig_category":"Autob\u00das (explotaci\u00d3n Y Servicios De)",
    "sg:phone":"+34 957 31 35 10",
    "sg:postcode":"14546",
    "sg:province":"C\u00f3rdoba",
    "wof:name":"Transportes Turisan S.l.",
    "wof:placetype":"venue"
},
  "geometry": {"coordinates":[-4.8460059166,37.5606040955],"type":"Point"}
}