{
  "type": "Feature",
  "properties": {
    "iso:country":"ES",
    "sg:address":"Carrer de Aribau, 65",
    "sg:city":"Barcelona",
    "sg:orig_category":"Arquitectos",
    "sg:phone":"+34 934 51 28 84",
    "sg:postcode":"08011",
    "sg:province":"Barcelona",
    "wof:name":"Saez Gimeno Jesus",
    "wof:placetype":"venue"
},
  "geometry": {"coordinates":[2.1586239338,41.3887786865],"type":"Point"}
}