{
  "type": "Feature",
  "properties": {
    "iso:country":"ES",
    "sg:address":"Plaz Chavarri Victor, 1",
    "sg:city":"Bilbao",
    "sg:orig_category":"Molduras, Junquillos, Listones Y Molduras Perforadas",
    "sg:phone":"+34 944 41 82 61",
    "sg:postcode":"48013",
    "sg:province":"Vizcaya",
    "wof:name":"Valerico Iglesias Lopez",
    "wof:placetype":"venue"
},
  "geometry": {"coordinates":[-2.9464790821,43.2623214722],"type":"Point"}
}