{
  "type": "Feature",
  "properties": {
    "addr:full":"Calle de Niebla, 33 Almonte Huelva 21730",
    "addr:housenumber":"33",
    "addr:postcode":"21730",
    "addr:street":"Calle De Niebla",
    "iso:country":"ES",
    "sg:address":"Calle de Niebla, 33",
    "sg:city":"Almonte",
    "sg:orig_category":"Molduras, Junquillos, Listones Y Molduras Perforadas",
    "sg:phone":"+34 959 40 74 87",
    "sg:postcode":"21730",
    "sg:province":"Huelva",
    "wof:name":"Moreno Montero Inmaculada",
    "wof:placetype":"venue"
},
  "geometry": {"coordinates":[-6.5199861526,37.2630081177],"type":"Point"}
}