{
  "type": "Feature",
  "properties": {
    "iso:country":"ES",
    "sg:address":"Rua Lavadeiro (do), 4",
    "sg:city":"Verin",
    "sg:orig_category":"Supermercados Y Hipermercados",
    "sg:phone":"+34 988 41 22 14",
    "sg:postcode":"32600",
    "sg:province":"Ourense",
    "sg:website":"www.mercadona.es",
    "wof:name":"Mercadona S.a.",
    "wof:placetype":"venue"
},
  "geometry": {"coordinates":[-7.4343090057,41.9418907166],"type":"Point"}
}