{
  "type": "Feature",
  "properties": {
    "addr:full":"Carrer de Martinez De La Rosa, 49 Barcelona Barcelona 08012",
    "addr:housenumber":"49",
    "addr:postcode":"08012",
    "addr:street":"Carrer De Martinez De La Rosa",
    "iso:country":"ES",
    "sg:address":"Carrer de Martinez De La Rosa, 49",
    "sg:city":"Barcelona",
    "sg:orig_category":"Dise\u00d1o Industrial",
    "sg:phone":"+34 932 37 46 44",
    "sg:postcode":"08012",
    "sg:province":"Barcelona",
    "wof:name":"Porta Homedes Antonio",
    "wof:placetype":"venue"
},
  "geometry": {"coordinates":[2.1586270332,41.4000244141],"type":"Point"}
}