{
  "type": "Feature",
  "properties": {
    "addr:full":"Plaz Media Legua, 2 Nonduermas Murcia 30166",
    "addr:housenumber":"2",
    "addr:postcode":"30166",
    "addr:street":"Media Legua",
    "iso:country":"ES",
    "sg:address":"Plaz Media Legua, 2",
    "sg:city":"Nonduermas",
    "sg:orig_category":"Cl\u00cdnicas Dentales",
    "sg:phone":"+34 968 34 21 47",
    "sg:postcode":"30166",
    "sg:province":"Murcia",
    "wof:name":"Rodriguez Cuello Jose Ignacio",
    "wof:placetype":"venue"
},
  "geometry": {"coordinates":[-1.1673840284,37.9729614258],"type":"Point"}
}