{
  "type": "Feature",
  "properties": {
    "iso:country":"ES",
    "sg:address":"Urb Jardines De Valverde, S/n",
    "sg:city":"Vaguadas",
    "sg:orig_category":"Arquitectos",
    "sg:phone":"+34 924 26 77 84",
    "sg:postcode":"06010",
    "sg:province":"Badajoz",
    "wof:name":"Ruiz Ortigosa Miguel",
    "wof:placetype":"venue"
},
  "geometry": {"coordinates":[-6.9663491249,38.8459205627],"type":"Point"}
}