{
  "type": "Feature",
  "properties": {
    "addr:full":"Calle de Huerta De Casta\u00d1eda, 10 Madrid Madrid 28011",
    "addr:housenumber":"10",
    "addr:postcode":"madrid;28011",
    "addr:street":"Calle De Huerta De Castan\u0303Eda",
    "iso:country":"ES",
    "sg:address":"Calle de Huerta De Casta\u00d1eda, 10",
    "sg:city":"Madrid",
    "sg:orig_category":"Alimentaci\u00d3n General (al Por Menor)",
    "sg:phone":"+34 914 64 48 91",
    "sg:postcode":"28011",
    "sg:province":"Madrid",
    "wof:name":"Miguel Vegas Emiliano De",
    "wof:placetype":"venue"
},
  "geometry": {"coordinates":[-3.741795063,40.4073028564],"type":"Point"}
}