{
  "type": "Feature",
  "properties": {
    "addr:full":"Carrer de Batista I Roca, 6 Barcelona Barcelona 08029",
    "addr:housenumber":"6",
    "addr:postcode":"08029",
    "addr:street":"Carrer De Batista I Roca",
    "iso:country":"ES",
    "sg:address":"Carrer de Batista I Roca, 6",
    "sg:city":"Barcelona",
    "sg:orig_category":"Agencias Y Agentes Comerciales, Representantes",
    "sg:phone":"+34 934 10 59 11",
    "sg:postcode":"08029",
    "sg:province":"Barcelona",
    "wof:name":"D.s.c Cote & Maria Barcelona S.l",
    "wof:placetype":"venue"
},
  "geometry": {"coordinates":[2.1366500854,41.3871498108],"type":"Point"}
}