{
  "type": "Feature",
  "properties": {
    "addr:full":"Barr Junyent, 2 Granollers Barcelona 08402",
    "addr:housenumber":"2",
    "addr:postcode":"08402",
    "addr:street":"Junyent",
    "iso:country":"ES",
    "sg:address":"Barr Junyent, 2",
    "sg:city":"Granollers",
    "sg:classifiers":[
        {
            "category":"Taxi",
            "type":"Transportation"
        }
    ],
    "sg:phone":"+34 938 70 10 38",
    "sg:postcode":"08402",
    "sg:province":"Barcelona",
    "wof:name":"Altimira Benedi Miguel",
    "wof:placetype":"venue"
},
  "geometry": {"coordinates":[2.2901277542,41.595916748],"type":"Point"}
}