{
  "type": "Feature",
  "properties": {
    "iso:country":"ES",
    "sg:address":"Ptda Riquer Baix, 1",
    "sg:city":"Alcoi",
    "sg:orig_category":"Asesor\u00cda De Comercio Exterior",
    "sg:phone":"+34 965 33 09 98",
    "sg:postcode":"03818",
    "sg:province":"Alicante",
    "wof:name":"Monllor Sanchez Francisco",
    "wof:placetype":"venue"
},
  "geometry": {"coordinates":[-0.456539005,38.7195396423],"type":"Point"}
}