{
  "type": "Feature",
  "properties": {
    "addr:full":"Calle de Maria Sanz Ramirez, 1 Riaza Segovia 40500",
    "addr:housenumber":"1",
    "addr:postcode":"40500",
    "addr:street":"Calle De Maria Sanz Ramirez",
    "iso:country":"ES",
    "sg:address":"Calle de Maria Sanz Ramirez, 1",
    "sg:city":"Riaza",
    "sg:orig_category":"Librer\u00cdas",
    "sg:phone":"+34 921 55 10 75",
    "sg:postcode":"40500",
    "sg:province":"Segovia",
    "wof:name":"Barahona Ramos Emilio",
    "wof:placetype":"venue"
},
  "geometry": {"coordinates":[-3.4774389267,41.2783088684],"type":"Point"}
}