{
  "type": "Feature",
  "properties": {
    "iso:country":"ES",
    "sg:address":"Calle de Obispo Rocamora, 13",
    "sg:city":"Orihuela",
    "sg:orig_category":"Promotores Constructores",
    "sg:phone":"+34 965 30 50 65",
    "sg:postcode":"03300",
    "sg:province":"Alicante",
    "wof:name":"Construcciones Pedrera S.l.",
    "wof:placetype":"venue"
},
  "geometry": {"coordinates":[-0.9439719915,38.0839080811],"type":"Point"}
}