{
  "type": "Feature",
  "properties": {
    "iso:country":"ES",
    "sg:address":"Calle de Bekoibarra, S/n",
    "sg:city":"Gernika-lumo",
    "sg:orig_category":"Aguas (distribuci\u00d3n, Servicios)",
    "sg:phone":"+34 946 25 35 75",
    "sg:postcode":"48300",
    "sg:province":"Vizcaya",
    "wof:name":"Consorcio De Aguas De Busturialdea",
    "wof:placetype":"venue"
},
  "geometry": {"coordinates":[-2.6745715141,43.3152122498],"type":"Point"}
}