{
  "type": "Feature",
  "properties": {
    "iso:country":"ES",
    "sg:address":"Carrer de Franc M Herreros, 16",
    "sg:city":"Palma",
    "sg:orig_category":"Agencias Y Agentes Comerciales, Representantes",
    "sg:phone":"+34 971 24 94 59",
    "sg:postcode":"07005",
    "sg:province":"Islas Baleares",
    "wof:name":"Gil Duarte Miguel Angel",
    "wof:placetype":"venue"
},
  "geometry": {"coordinates":[2.6626529694,39.5739173889],"type":"Point"}
}