{
  "type": "Feature",
  "properties": {
    "iso:country":"ES",
    "sg:address":"Carr Barcelona, 38",
    "sg:city":"Girona",
    "sg:orig_category":"Perfumer\u00cda Y Cosm\u00c9tica (fabricaci\u00d3n, Al Por Mayor)",
    "sg:phone":"+34 972 41 41 41",
    "sg:postcode":"17002",
    "sg:province":"Girona",
    "sg:website":"www.swanlabs.net",
    "wof:name":"Tradesma 2002 S.l.",
    "wof:placetype":"venue"
},
  "geometry": {"coordinates":[2.8173849583,41.9779663086],"type":"Point"}
}