{
  "type": "Feature",
  "properties": {
    "addr:full":"Carr Murcia, 29 Eivissa Islas Baleares 07800",
    "addr:housenumber":"29",
    "addr:postcode":"07800",
    "addr:street":"Carr Murcia",
    "iso:country":"ES",
    "sg:address":"Carr Murcia, 29",
    "sg:city":"Eivissa",
    "sg:orig_category":"Centros De Coordinaci\u00d3n",
    "sg:phone":"+34 971 19 00 52",
    "sg:postcode":"07800",
    "sg:province":"Islas Baleares",
    "wof:name":"Fernandez-ya\u00f1ez Perez Juan Manuel",
    "wof:placetype":"venue"
},
  "geometry": {"coordinates":[1.4188899994,38.9061164856],"type":"Point"}
}