{
  "type": "Feature",
  "properties": {
    "addr:full":"Avda Florez Estrada, 8 Nore\u00f1a Asturias 33180",
    "addr:housenumber":"8",
    "addr:postcode":"33180",
    "addr:street":"Avda Florez Estrada;Asturias",
    "iso:country":"ES",
    "sg:address":"Avda Florez Estrada, 8",
    "sg:city":"Nore\u00f1a",
    "sg:orig_category":"Abogados",
    "sg:phone":"+34 985 74 29 98",
    "sg:postcode":"33180",
    "sg:province":"Asturias",
    "wof:name":"Rato Cueto Jose Angel",
    "wof:placetype":"venue"
},
  "geometry": {"coordinates":[-5.7049617767,43.3936843872],"type":"Point"}
}