{
  "type": "Feature",
  "properties": {
    "iso:country":"ES",
    "sg:address":"Cmno Forestal, 56",
    "sg:city":"Adrada",
    "sg:orig_category":"Electricidad: Instaladores",
    "sg:phone":"+34 918 67 23 21",
    "sg:postcode":"05430",
    "sg:province":"\u00c1vila",
    "wof:name":"Saltos Del Tietar S.a.",
    "wof:placetype":"venue"
},
  "geometry": {"coordinates":[-4.638753891,40.3024139404],"type":"Point"}
}