{
  "type": "Feature",
  "properties": {
    "iso:country":"ES",
    "sg:address":"Av Principat D'andorra, 7",
    "sg:city":"Tarragona",
    "sg:orig_category":"Carnicer\u00cdas, Carnicer\u00cdas",
    "sg:phone":"+34 977 22 06 38",
    "sg:postcode":"43002",
    "sg:province":"Tarragona",
    "wof:name":"Reviriego Serrano Vicente",
    "wof:placetype":"venue"
},
  "geometry": {"coordinates":[1.2421449423,41.1258277893],"type":"Point"}
}