{
  "type": "Feature",
  "properties": {
    "iso:country":"ES",
    "sg:address":"Plaz Pueblo (del), 9",
    "sg:city":"Colmenar Viejo",
    "sg:orig_category":"Farmacias",
    "sg:phone":"+34 918 45 28 61",
    "sg:postcode":"28770",
    "sg:province":"Madrid",
    "wof:name":"Lopez Colmenarejo Maria Dolores",
    "wof:placetype":"venue"
},
  "geometry": {"coordinates":[-3.7654280663,40.6589202881],"type":"Point"}
}