{
  "type": "Feature",
  "properties": {
    "addr:full":"Calle de Zuares, S/n Pobladura Pelayo Garcia Le\u00f3n 24249",
    "addr:housenumber":"s / n",
    "addr:postcode":"24249",
    "addr:street":"Calle De Zuares;Leo\u0301N",
    "iso:country":"ES",
    "sg:address":"Calle de Zuares, S/n",
    "sg:city":"Pobladura Pelayo Garcia",
    "sg:orig_category":"Maquinaria Para Industrias Diversas",
    "sg:phone":"+34 987 38 40 64",
    "sg:postcode":"24249",
    "sg:province":"Le\u00f3n",
    "wof:name":"Diaz Casado Honorio",
    "wof:placetype":"venue"
},
  "geometry": {"coordinates":[-5.682694912,42.3079719543],"type":"Point"}
}