{
  "type": "Feature",
  "properties": {
    "addr:full":"Sierra Fuentes-medellin, Ctra., Km. 0000,8 Sierra Fuentes C\u00e1ceres 10181",
    "addr:postcode":"10181",
    "addr:street":"Ctra. Km. 0000,8 Sierra;Ca\u0301Ceres",
    "iso:country":"ES",
    "sg:address":"Sierra Fuentes-medellin, Ctra., Km. 0000,8",
    "sg:city":"Sierra Fuentes",
    "sg:orig_category":"Jardiner\u00cdas, Vegetales, Art\u00cdculos De Jardiner\u00cda (al Por Menor)",
    "sg:phone":"+34 927 20 11 30",
    "sg:postcode":"10181",
    "sg:province":"C\u00e1ceres",
    "wof:name":"Viveros Europa Koseu Rufu S.l.l.",
    "wof:placetype":"venue"
},
  "geometry": {"coordinates":[-6.3707604408,39.4761772156],"type":"Point"}
}