{
  "type": "Feature",
  "properties": {
    "addr:full":"Calle de Alarcos, 11 Ciudad Real Ciudad Real 13001",
    "addr:housenumber":"11",
    "addr:postcode":"13001",
    "addr:street":"Calle De Alarcos",
    "iso:country":"ES",
    "sg:address":"Calle de Alarcos, 11",
    "sg:city":"Ciudad Real",
    "sg:orig_category":"Empresarios",
    "sg:phone":"+34 926 21 26 46",
    "sg:postcode":"13001",
    "sg:province":"Ciudad Real",
    "wof:name":"Construcciones Garcia Del Castillo S. A.",
    "wof:placetype":"venue"
},
  "geometry": {"coordinates":[-3.9311056137,38.9832382202],"type":"Point"}
}