{
  "type": "Feature",
  "properties": {
    "addr:full":"Carrer de Casanova, 230 Barcelona Barcelona 08036",
    "addr:housenumber":"230",
    "addr:postcode":"08036",
    "addr:street":"Carrer De Casanova",
    "iso:country":"ES",
    "sg:address":"Carrer de Casanova, 230",
    "sg:city":"Barcelona",
    "sg:orig_category":"Confiter\u00cdas, Chocolater\u00cdas (al Por Menor)",
    "sg:phone":"+34 933 22 97 57",
    "sg:postcode":"08036",
    "sg:province":"Barcelona",
    "wof:name":"Verdu Colom Merce",
    "wof:placetype":"venue"
},
  "geometry": {"coordinates":[2.1493999958,41.3926353455],"type":"Point"}
}