{
  "type": "Feature",
  "properties": {
    "iso:country":"ES",
    "sg:address":"Calle de Pe\u00d1arrubia, 12",
    "sg:city":"Malaga",
    "sg:orig_category":"Cerrajer\u00cda, Ferrallista",
    "sg:phone":"+34 952 34 92 13",
    "sg:postcode":"29006",
    "sg:province":"M\u00e1laga",
    "wof:name":"Molina Rodriguez Juan",
    "wof:placetype":"venue"
},
  "geometry": {"coordinates":[-4.4536762238,36.7116470337],"type":"Point"}
}