{
  "type": "Feature",
  "properties": {
    "iso:country":"ES",
    "sg:address":"Pla\u00c7 Major, 1",
    "sg:city":"Figols",
    "sg:orig_category":"Telefon\u00cda: Instaladores Varios",
    "sg:phone":"+34 973 38 31 49",
    "sg:postcode":"25794",
    "sg:province":"Lleida",
    "wof:name":"Ajuntament De Figols I Alinya",
    "wof:placetype":"venue"
},
  "geometry": {"coordinates":[1.3400015831,42.2031593323],"type":"Point"}
}