{
  "type": "Feature",
  "properties": {
    "addr:full":"Plaz Barranco, 15 Alhendin Granada 18620",
    "addr:housenumber":"15",
    "addr:postcode":"18620",
    "addr:street":"Barranco",
    "iso:country":"ES",
    "sg:address":"Plaz Barranco, 15",
    "sg:city":"Alhendin",
    "sg:orig_category":"Contenedores Para Transporte De Mercanc\u00cdas",
    "sg:phone":"+34 958 57 65 19",
    "sg:postcode":"18620",
    "sg:province":"Granada",
    "wof:name":"Garcia Lopez Manuel",
    "wof:placetype":"venue"
},
  "geometry": {"coordinates":[-3.6415240765,37.1073913574],"type":"Point"}
}