{
  "type": "Feature",
  "properties": {
    "addr:full":"Calle de Vega La, 26 Nava Asturias 33520",
    "addr:housenumber":"26",
    "addr:postcode":"33520",
    "addr:street":"Calle De Vega La",
    "iso:country":"ES",
    "sg:address":"Calle de Vega La, 26",
    "sg:city":"Nava",
    "sg:orig_category":"Partidos Pol\u00cdticos",
    "sg:phone":"+34 985 71 81 04",
    "sg:postcode":"33520",
    "sg:province":"Asturias",
    "wof:name":"Partido Popular",
    "wof:placetype":"venue"
},
  "geometry": {"coordinates":[-5.5082039833,43.3590354919],"type":"Point"}
}