{
  "type": "Feature",
  "properties": {
    "iso:country":"ES",
    "sg:address":"Calle de Postas, 66",
    "sg:city":"Palacios Y Villafranca",
    "sg:orig_category":"Aguas (distribuci\u00d3n, Servicios)",
    "sg:phone":"+34 955 81 30 08",
    "sg:postcode":"41720",
    "sg:province":"Sevilla",
    "wof:name":"Aguas Del Huesna S.l.",
    "wof:placetype":"venue"
},
  "geometry": {"coordinates":[-5.9252309799,37.1581306458],"type":"Point"}
}