{
  "type": "Feature",
  "properties": {
    "addr:full":"Calle de General Arrando, 30 Madrid Madrid 28010",
    "addr:housenumber":"30",
    "addr:postcode":"madrid;28010",
    "addr:street":"Calle De General Arrando",
    "iso:country":"ES",
    "sg:address":"Calle de General Arrando, 30",
    "sg:city":"Madrid",
    "sg:orig_category":"Cl\u00cdnicas M\u00c9dicas",
    "sg:phone":"+34 913 10 09 08",
    "sg:postcode":"28010",
    "sg:province":"Madrid",
    "wof:name":"Promociones Tecnicas Medicas S. A.",
    "wof:placetype":"venue"
},
  "geometry": {"coordinates":[-3.6941030025,40.4316062927],"type":"Point"}
}