{
  "type": "Feature",
  "properties": {
    "addr:full":"Plaz Espa\u00d1a, 5 Coru\u00d1a La Coru\u00f1a 15001",
    "addr:housenumber":"5",
    "addr:postcode":"15001",
    "addr:street":"Plaz Espan\u0303A;La Corun\u0303A",
    "iso:country":"ES",
    "sg:address":"Plaz Espa\u00d1a, 5",
    "sg:city":"Coru\u00d1a",
    "sg:orig_category":"Peluquer\u00cdas, Peluquer\u00cda Mixta",
    "sg:phone":"+34 981 21 05 31",
    "sg:postcode":"15001",
    "sg:province":"La Coru\u00f1a",
    "wof:name":"Gonzalez Pesqueira Concepcion",
    "wof:placetype":"venue"
},
  "geometry": {"coordinates":[-8.3951234818,43.3712844849],"type":"Point"}
}