{
  "type": "Feature",
  "properties": {
    "addr:full":"Carrer de Mallorca, 338 Barcelona Barcelona 08037",
    "addr:housenumber":"338",
    "addr:postcode":"08037",
    "addr:street":"Carrer De Mallorca",
    "iso:country":"ES",
    "sg:address":"Carrer de Mallorca, 338",
    "sg:city":"Barcelona",
    "sg:orig_category":"Mec\u00c1nico Del Autom\u00d3vil",
    "sg:phone":"+34 934 58 36 73",
    "sg:postcode":"08037",
    "sg:province":"Barcelona",
    "wof:name":"Vila Cera Jorge",
    "wof:placetype":"venue"
},
  "geometry": {"coordinates":[2.1702830791,41.3994483948],"type":"Point"}
}