{
  "type": "Feature",
  "properties": {
    "iso:country":"ES",
    "sg:address":"Carrer de Riera De Tena, 14",
    "sg:city":"Barcelona",
    "sg:orig_category":"Postigos, Persianas Y Celos\u00cdas",
    "sg:phone":"+34 933 32 08 46",
    "sg:postcode":"08014",
    "sg:province":"Barcelona",
    "wof:name":"Gibert Pujol Juan",
    "wof:placetype":"venue"
},
  "geometry": {"coordinates":[2.1337943077,41.3706474304],"type":"Point"}
}