{
  "type": "Feature",
  "properties": {
    "iso:country":"ES",
    "sg:address":"Calle de Molino, 6",
    "sg:city":"Huelamo",
    "sg:orig_category":"Contenedores (mercanc\u00cdas)",
    "sg:phone":"+34 969 28 91 90",
    "sg:postcode":"16151",
    "sg:province":"Cuenca",
    "wof:name":"Marcelino Herranz S.l.",
    "wof:placetype":"venue"
},
  "geometry": {"coordinates":[-1.8100550175,40.2770767212],"type":"Point"}
}