{
  "type": "Feature",
  "properties": {
    "addr:full":"Calle de Historiador Manuel Cancela, 3 Jerez De La Frontera C\u00e1diz 11408",
    "addr:housenumber":"3",
    "addr:postcode":"11408",
    "addr:street":"Calle De Historiador Manuel Cancela",
    "iso:country":"ES",
    "sg:address":"Calle de Historiador Manuel Cancela, 3",
    "sg:city":"Jerez De La Frontera",
    "sg:classifiers":[
        {
            "category":"Autos & Motor Vehicles",
            "subcategory":"Automobile Sales",
            "type":"Retail Goods"
        }
    ],
    "sg:phone":"+34 956 14 58 22",
    "sg:postcode":"11408",
    "sg:province":"C\u00e1diz",
    "wof:name":"Autoescuela Nila S.l.",
    "wof:placetype":"venue"
},
  "geometry": {"coordinates":[-6.145837307,36.6743659973],"type":"Point"}
}