{
  "type": "Feature",
  "properties": {
    "iso:country":"ES",
    "sg:address":"Calle de Cendeja, 39",
    "sg:city":"San Juan De Muskiz",
    "sg:orig_category":"Cajas De Ahorro",
    "sg:phone":"+34 946 70 81 25",
    "sg:postcode":"48550",
    "sg:province":"Vizcaya",
    "wof:name":"Caixa D'estalvis I Pensions De Barcelona",
    "wof:placetype":"venue"
},
  "geometry": {"coordinates":[-3.1167533398,43.3219528198],"type":"Point"}
}