{
  "type": "Feature",
  "properties": {
    "iso:country":"ES",
    "sg:address":"Avda San Juan De La Canal, 37",
    "sg:city":"Soto Marina",
    "sg:orig_category":"Promotores Constructores",
    "sg:phone":"+34 942 58 79 50",
    "sg:postcode":"39110",
    "sg:province":"Cantabria",
    "wof:name":"Construcciones Eugenio Nava Viar S.a.",
    "wof:placetype":"venue"
},
  "geometry": {"coordinates":[-3.8951430321,43.4730644226],"type":"Point"}
}