{
  "type": "Feature",
  "properties": {
    "iso:country":"ES",
    "sg:address":"Calle de Conde Aranda, 94",
    "sg:city":"Zaragoza",
    "sg:orig_category":"Muebles Y Accesorios Para Cocinas Y Cuartos De Ba\u00d1o (al Por Menor)",
    "sg:phone":"+34 976 28 37 74",
    "sg:postcode":"50003",
    "sg:province":"Zaragoza",
    "wof:name":"Gordillo Guillen Antonio",
    "wof:placetype":"venue"
},
  "geometry": {"coordinates":[-0.8899099231,41.6555404663],"type":"Point"}
}