{
  "type": "Feature",
  "properties": {
    "addr:full":"Calle de Pozo, 7 Morales Toro Zamora 49810",
    "addr:housenumber":"7",
    "addr:postcode":"49810",
    "addr:street":"Calle De Pozo",
    "iso:country":"ES",
    "sg:address":"Calle de Pozo, 7",
    "sg:city":"Morales Toro",
    "sg:orig_category":"Plomeros",
    "sg:phone":"+34 980 69 67 04",
    "sg:postcode":"49810",
    "sg:province":"Zamora",
    "wof:name":"Montes Miguel Felix",
    "wof:placetype":"venue"
},
  "geometry": {"coordinates":[-5.3052210808,41.5364952087],"type":"Point"}
}