{
  "type": "Feature",
  "properties": {
    "iso:country":"ES",
    "sg:address":"Rua Ramon Y Cajal, 3",
    "sg:city":"Santa Uxia De Ribeira",
    "sg:orig_category":"\u00d3ptica: Instrumentos (fabricaci\u00d3n)",
    "sg:phone":"+34 981 87 38 07",
    "sg:postcode":"15960",
    "sg:province":"La Coru\u00f1a",
    "wof:name":"Miradoiro Opticos S.l.",
    "wof:placetype":"venue"
},
  "geometry": {"coordinates":[-8.9919548035,42.5549888611],"type":"Point"}
}