{
  "type": "Feature",
  "properties": {
    "addr:full":"Pol. Almanjayar, S/n Granada Granada 18013",
    "addr:housenumber":"s / n",
    "addr:postcode":"18013",
    "iso:country":"ES",
    "sg:address":"Pol. Almanjayar, S/n",
    "sg:city":"Granada",
    "sg:classifiers":[
        {
            "category":"Cinema",
            "subcategory":"Movie Theater",
            "type":"Entertainment"
        }
    ],
    "sg:phone":"+34 958 18 53 20",
    "sg:postcode":"18013",
    "sg:province":"Granada",
    "sg:tags":[
        "salas",
        "de",
        "cine"
    ],
    "wof:name":"Multicines El Arcangel S.l.",
    "wof:placetype":"venue"
},
  "geometry": {"coordinates":[-3.6054260731,37.1703987122],"type":"Point"}
}