{
  "type": "Feature",
  "properties": {
    "addr:full":"Av Jaume I, 188 Mollet Valles Barcelona 08100",
    "addr:housenumber":"188",
    "addr:postcode":"08100",
    "addr:street":"Av Jaume I",
    "iso:country":"ES",
    "sg:address":"Av Jaume I, 188",
    "sg:city":"Mollet Valles",
    "sg:orig_category":"Inmobiliaria (agencias)",
    "sg:phone":"+34 935 79 51 07",
    "sg:postcode":"08100",
    "sg:province":"Barcelona",
    "wof:name":"Fincas Gaudi I Advocats S.c.p.",
    "wof:placetype":"venue"
},
  "geometry": {"coordinates":[2.2166829109,41.5436935425],"type":"Point"}
}