{
  "type": "Feature",
  "properties": {
    "addr:full":"Calle de Acuario, 38 Madrid Madrid 28042",
    "addr:housenumber":"38",
    "addr:postcode":"madrid;28042",
    "addr:street":"Calle De Acuario",
    "iso:country":"ES",
    "sg:address":"Calle de Acuario, 38",
    "sg:city":"Madrid",
    "sg:orig_category":"Fisioterapia",
    "sg:phone":"+34 913 05 43 47",
    "sg:postcode":"28042",
    "sg:province":"Madrid",
    "wof:name":"Gonzalez Valiente Cristina",
    "wof:placetype":"venue"
},
  "geometry": {"coordinates":[-3.5802850723,40.4754371643],"type":"Point"}
}