{
  "type": "Feature",
  "properties": {
    "addr:full":"Avda Conde De Bugallal (do), 1 Pontevedra Pontevedra 36099",
    "addr:housenumber":"1",
    "addr:postcode":"36099",
    "addr:street":"Avda Conde De Bugallal Do",
    "iso:country":"ES",
    "sg:address":"Avda Conde De Bugallal (do), 1",
    "sg:city":"Pontevedra",
    "sg:orig_category":"Molduras, Junquillos, Listones Y Molduras Perforadas",
    "sg:phone":"+34 986 89 66 77",
    "sg:postcode":"36099",
    "sg:province":"Pontevedra",
    "wof:name":"Arosa Tieso Jaime",
    "wof:placetype":"venue"
},
  "geometry": {"coordinates":[-8.6327886581,42.421295166],"type":"Point"}
}