{
  "type": "Feature",
  "properties": {
    "iso:country":"ES",
    "sg:address":"Pol. Fabrica De Mieres, 1",
    "sg:city":"Rebollada",
    "sg:orig_category":"Reposter\u00cdas",
    "sg:phone":"+34 985 45 60 69",
    "sg:postcode":"33619",
    "sg:province":"Asturias",
    "wof:name":"Panaderia La Vienesa Compa\u00f1ia Laboral S. A.",
    "wof:placetype":"venue"
},
  "geometry": {"coordinates":[-5.8089671135,43.2838096619],"type":"Point"}
}