{
  "type": "Feature",
  "properties": {
    "iso:country":"ES",
    "sg:address":"Calle de Amargura, 16",
    "sg:city":"Zamora",
    "sg:orig_category":"M\u00c9dicos: Neumolog\u00cda",
    "sg:phone":"+34 980 52 46 27",
    "sg:postcode":"49008",
    "sg:province":"Zamora",
    "wof:name":"Gutierrez Maire-richard Eloy",
    "wof:placetype":"venue"
},
  "geometry": {"coordinates":[-5.7420887947,41.5096702576],"type":"Point"}
}