{
  "type": "Feature",
  "properties": {
    "addr:full":"Avda Constitucion (la), 24 Sevilla Sevilla 41001",
    "addr:housenumber":"24",
    "addr:postcode":"41001",
    "addr:street":"Avda Constitucion La",
    "iso:country":"ES",
    "sg:address":"Avda Constitucion (la), 24",
    "sg:city":"Sevilla",
    "sg:orig_category":"Centros De Coordinaci\u00d3n",
    "sg:phone":"+34 954 50 15 26",
    "sg:postcode":"41001",
    "sg:province":"Sevilla",
    "sg:website":"www.bmb.es",
    "wof:name":"B M B Gestion Documental S.l.",
    "wof:placetype":"venue"
},
  "geometry": {"coordinates":[-5.9941301346,37.3854179382],"type":"Point"}
}