{
  "type": "Feature",
  "properties": {
    "iso:country":"ES",
    "sg:address":"Carrer de Calabria, 282",
    "sg:city":"Barcelona",
    "sg:orig_category":"Loter\u00cda Y T\u00d3mbola",
    "sg:phone":"+34 934 39 33 64",
    "sg:postcode":"08029",
    "sg:province":"Barcelona",
    "wof:name":"Vidal Morera Josefina",
    "wof:placetype":"venue"
},
  "geometry": {"coordinates":[2.144315958,41.3879776001],"type":"Point"}
}