{
  "type": "Feature",
  "properties": {
    "iso:country":"ES",
    "sg:address":"Calle de Cullera, 12",
    "sg:city":"Madrid",
    "sg:orig_category":"Restaurantes",
    "sg:phone":"+34 914 62 97 41",
    "sg:postcode":"28047",
    "sg:province":"Madrid",
    "wof:name":"Recio Peinado Pedro Matias",
    "wof:placetype":"venue"
},
  "geometry": {"coordinates":[-3.7449631691,40.3968887329],"type":"Point"}
}