{
  "type": "Feature",
  "properties": {
    "addr:full":"Ctra. De Zarza La Mayor, S/n Ceclavin C\u00e1ceres 10870",
    "addr:housenumber":"s",
    "addr:postcode":"10870",
    "addr:street":"Ctra. De Zarza La Mayor;/ N Ceclavin Ca\u0301Ceres",
    "iso:country":"ES",
    "sg:address":"Ctra. De Zarza La Mayor, S/n",
    "sg:city":"Ceclavin",
    "sg:orig_category":"Distribuci\u00d3n De Petr\u00d3leo Y Derivados",
    "sg:phone":"+34 927 39 34 66",
    "sg:postcode":"10870",
    "sg:province":"C\u00e1ceres",
    "wof:name":"Perez Granados Francisca",
    "wof:placetype":"venue"
},
  "geometry": {"coordinates":[-6.7770857811,39.8258094788],"type":"Point"}
}