{
  "type": "Feature",
  "properties": {
    "addr:full":"Carretera De Iscar, S/n Cha\u00f1e Segovia 40216",
    "addr:housenumber":"s / n",
    "addr:postcode":"40216",
    "addr:street":"Carretera De Iscar",
    "iso:country":"ES",
    "sg:address":"Carretera De Iscar, S/n",
    "sg:city":"Cha\u00f1e",
    "sg:orig_category":"Distribuci\u00d3n De Petr\u00d3leo Y Derivados",
    "sg:phone":"+34 921 15 59 15",
    "sg:postcode":"40216",
    "sg:province":"Segovia",
    "wof:name":"Bernardos Moreno Jose",
    "wof:placetype":"venue"
},
  "geometry": {"coordinates":[-4.4277071953,41.3387870789],"type":"Point"}
}