{
  "type": "Feature",
  "properties": {
    "addr:full":"Cmno Dalias, S/n Alcaudique Almer\u00eda 04760",
    "addr:postcode":"04760",
    "addr:street":"Cmno Dalias S / N Alcaudique Almeri\u0301A",
    "iso:country":"ES",
    "sg:address":"Cmno Dalias, S/n",
    "sg:city":"Alcaudique",
    "sg:orig_category":"Arboricultura Y Producci\u00d3n De Frutas",
    "sg:phone":"+34 950 49 14 24",
    "sg:postcode":"04760",
    "sg:province":"Almer\u00eda",
    "wof:name":"Montivel S.a.t.",
    "wof:placetype":"venue"
},
  "geometry": {"coordinates":[-2.9501290321,36.8471107483],"type":"Point"}
}