{
  "type": "Feature",
  "properties": {
    "iso:country":"ES",
    "sg:address":"Calle de Barberan Y Collar, 2",
    "sg:city":"Alcala Henares",
    "sg:orig_category":"Peluqueros: De Se\u00d1oras",
    "sg:phone":"+34 918 83 37 32",
    "sg:postcode":"28805",
    "sg:province":"Madrid",
    "wof:name":"Ureta Abad Matilde",
    "wof:placetype":"venue"
},
  "geometry": {"coordinates":[-3.3489570618,40.5023345947],"type":"Point"}
}