{
  "type": "Feature",
  "properties": {
    "iso:country":"ES",
    "sg:address":"Avda Americas (de Las), S/n",
    "sg:city":"Alcantarilla",
    "sg:orig_category":"Asesor\u00cda Para La Organizaci\u00d3n Y Gesti\u00d3n Del Transporte",
    "sg:phone":"+34 968 80 82 66",
    "sg:postcode":"30820",
    "sg:province":"Murcia",
    "wof:name":"Transportes La Murciana Murcia S.l.",
    "wof:placetype":"venue"
},
  "geometry": {"coordinates":[-1.2070939541,37.9575767517],"type":"Point"}
}