{
  "type": "Feature",
  "properties": {
    "addr:full":"Aljezares, S/n Torres Albarracin Teruel 44111",
    "addr:housenumber":"/ n",
    "addr:postcode":"44111",
    "addr:street":"Aljezares S",
    "iso:country":"ES",
    "sg:address":"Aljezares, S/n",
    "sg:city":"Torres Albarracin",
    "sg:orig_category":"Cr\u00cda De Cerdos",
    "sg:phone":"+34 978 70 61 65",
    "sg:postcode":"44111",
    "sg:province":"Teruel",
    "wof:name":"Sociedad Agraria De Transformacion N\u00ba 3959",
    "wof:placetype":"venue"
},
  "geometry": {"coordinates":[-1.5317840576,40.4266471863],"type":"Point"}
}