{
  "type": "Feature",
  "properties": {
    "iso:country":"ES",
    "sg:address":"Av Castilla Mancha(p I Colador), S/n",
    "sg:city":"Onda",
    "sg:orig_category":"Suministros Y Materiales Industriales",
    "sg:phone":"+34 964 77 20 69",
    "sg:postcode":"12200",
    "sg:province":"Castell\u00f3n",
    "sg:website":"www.alvagargrupo.com",
    "wof:name":"Alvagar Y Peal S.l.",
    "wof:placetype":"venue"
},
  "geometry": {"coordinates":[-0.2432307005,39.9604454041],"type":"Point"}
}