{
  "type": "Feature",
  "properties": {
    "addr:full":"Carrer de Canyelles (de), 12 Tarragona Tarragona 43001",
    "addr:housenumber":"12",
    "addr:postcode":"43001",
    "addr:street":"Carrer De Canyelles De",
    "iso:country":"ES",
    "sg:address":"Carrer de Canyelles (de), 12",
    "sg:city":"Tarragona",
    "sg:orig_category":"Institutos De Belleza",
    "sg:phone":"+34 977 23 74 95",
    "sg:postcode":"43001",
    "sg:province":"Tarragona",
    "wof:name":"Sanchez Sanchez Mercedes",
    "wof:placetype":"venue"
},
  "geometry": {"coordinates":[1.2499370575,41.1159095764],"type":"Point"}
}