{
  "type": "Feature",
  "properties": {
    "addr:full":"Urba Pedrol, 15 Pedrol Tarragona 43007",
    "addr:housenumber":"15",
    "addr:postcode":"43007",
    "addr:street":"Pedrol",
    "iso:country":"ES",
    "sg:address":"Urba Pedrol, 15",
    "sg:city":"Pedrol",
    "sg:orig_category":"Guarder\u00cdas",
    "sg:phone":"+34 977 20 30 20",
    "sg:postcode":"43007",
    "sg:province":"Tarragona",
    "wof:name":"El Niuet S.coop.c.l.",
    "wof:placetype":"venue"
},
  "geometry": {"coordinates":[1.2959779501,41.1377334595],"type":"Point"}
}