{
  "type": "Feature",
  "properties": {
    "iso:country":"ES",
    "sg:address":"Las Fabricas, 4",
    "sg:city":"Ezcaray",
    "sg:orig_category":"Promotores Constructores",
    "sg:phone":"+34 941 35 43 42",
    "sg:postcode":"26280",
    "sg:province":"La Rioja",
    "wof:name":"Construcciones Bengoa Capeyan S.l.",
    "wof:placetype":"venue"
},
  "geometry": {"coordinates":[-3.0119850636,42.3285102844],"type":"Point"}
}