{
  "type": "Feature",
  "properties": {
    "addr:full":"Av Peru, 93 Mataro Barcelona 08304",
    "addr:housenumber":"93",
    "addr:postcode":"08304",
    "addr:street":"Av Peru",
    "iso:country":"ES",
    "sg:address":"Av Peru, 93",
    "sg:city":"Mataro",
    "sg:orig_category":"Fabricaci\u00d3n De Su\u00c9ters Y Chalecos De Punto",
    "sg:phone":"+34 937 90 40 02",
    "sg:postcode":"08304",
    "sg:province":"Barcelona",
    "wof:name":"Viuda De Santiago Valls S. A.",
    "wof:placetype":"venue"
},
  "geometry": {"coordinates":[2.4481899738,41.5515708923],"type":"Point"}
}