{
  "type": "Feature",
  "properties": {
    "addr:full":"Calle de Miguel Servet, 15 Almansa Albacete 02640",
    "addr:housenumber":"15",
    "addr:postcode":"02640",
    "addr:street":"Calle De Miguel Servet",
    "iso:country":"ES",
    "sg:address":"Calle de Miguel Servet, 15",
    "sg:city":"Almansa",
    "sg:orig_category":"Iglesias Evang\u00c9licas",
    "sg:phone":"+34 967 34 01 08",
    "sg:postcode":"02640",
    "sg:province":"Albacete",
    "wof:name":"Iglesia Evangelica Buenas Noticias",
    "wof:placetype":"venue"
},
  "geometry": {"coordinates":[-1.1047010422,38.8773956299],"type":"Point"}
}