{
  "type": "Feature",
  "properties": {
    "addr:full":"Av Barcelona, 110 Barri Colomer Barcelona 08690",
    "addr:housenumber":"110",
    "addr:postcode":"08690",
    "addr:street":"Av Barcelona;Barcelona",
    "iso:country":"ES",
    "sg:address":"Av Barcelona, 110",
    "sg:city":"Barri Colomer",
    "sg:orig_category":"Tubos Y Tuber\u00cdas De Goma Y Pl\u00c1stico (fabricaci\u00d3n, Al Por Mayor)",
    "sg:phone":"+34 936 45 03 60",
    "sg:postcode":"08690",
    "sg:province":"Barcelona",
    "wof:name":"Tec Neon S.l.",
    "wof:placetype":"venue"
},
  "geometry": {"coordinates":[2.0203399658,41.366519928],"type":"Point"}
}