{
  "type": "Feature",
  "properties": {
    "addr:full":"Avda Habana, 1 Melide La Coru\u00f1a 15800",
    "addr:housenumber":"1",
    "addr:postcode":"15800",
    "addr:street":"Avda Habana;La Corun\u0303A",
    "iso:country":"ES",
    "sg:address":"Avda Habana, 1",
    "sg:city":"Melide",
    "sg:orig_category":"Frutas Y Legumbres Frescas (al Por Mayor)",
    "sg:phone":"+34 981 50 76 97",
    "sg:postcode":"15800",
    "sg:province":"La Coru\u00f1a",
    "wof:name":"Frutas Gallego E Hijos S.l.",
    "wof:placetype":"venue"
},
  "geometry": {"coordinates":[-8.0131225586,42.9138221741],"type":"Point"}
}