{
  "type": "Feature",
  "properties": {
    "addr:full":"Csta De Valladolid, 7 Benavente Zamora 49600",
    "addr:housenumber":"7",
    "addr:postcode":"49600",
    "iso:country":"ES",
    "sg:address":"Csta De Valladolid, 7",
    "sg:city":"Benavente",
    "sg:orig_category":"Cl\u00cdnicas M\u00c9dicas",
    "sg:phone":"+34 980 63 52 44",
    "sg:postcode":"49600",
    "sg:province":"Zamora",
    "wof:name":"Policlinica De Benavente",
    "wof:placetype":"venue"
},
  "geometry": {"coordinates":[-5.677795887,42.0033531189],"type":"Point"}
}