{
  "type": "Feature",
  "properties": {
    "addr:full":"Calle de Juan Bautista, S/n Viso Del Alcor Sevilla 41520",
    "addr:housenumber":"s / n",
    "addr:postcode":"41520",
    "addr:street":"Calle De Juan Bautista",
    "iso:country":"ES",
    "sg:address":"Calle de Juan Bautista, S/n",
    "sg:city":"Viso Del Alcor",
    "sg:orig_category":"Ense\u00d1anza, Formaci\u00d3n Profesional: Aprendizaje",
    "sg:phone":"+34 955 74 09 72",
    "sg:postcode":"41520",
    "sg:province":"Sevilla",
    "wof:name":"Junta De Andalucia",
    "wof:placetype":"venue"
},
  "geometry": {"coordinates":[-5.7253842354,37.3858642578],"type":"Point"}
}