{
  "type": "Feature",
  "properties": {
    "iso:country":"ES",
    "sg:address":"Avda Madrid (de), 35",
    "sg:city":"Avila",
    "sg:orig_category":"Oficinas De Turismo, Asociaciones De Iniciativa",
    "sg:phone":"+34 920 22 59 69",
    "sg:postcode":"05001",
    "sg:province":"\u00c1vila",
    "wof:name":"Ayuntamiento De Avila",
    "wof:placetype":"venue"
},
  "geometry": {"coordinates":[-4.6945977211,40.658000946],"type":"Point"}
}