{
  "type": "Feature",
  "properties": {
    "iso:country":"ES",
    "sg:address":"Av Primavera, 11",
    "sg:city":"Cerdanyola Valles",
    "sg:orig_category":"Art\u00cdculos De Regalo (al Por Menor)",
    "sg:phone":"+34 935 86 55 55",
    "sg:postcode":"08290",
    "sg:province":"Barcelona",
    "wof:name":"Paris Cardona Olga",
    "wof:placetype":"venue"
},
  "geometry": {"coordinates":[2.1456310749,41.490776062],"type":"Point"}
}