{
  "type": "Feature",
  "properties": {
    "iso:country":"ES",
    "sg:address":"Los Riscos, 1",
    "sg:city":"Playa Blanca",
    "sg:orig_category":"Caf\u00c9s, Bares, Cervecer\u00cdas",
    "sg:phone":"+34 928 51 80 22",
    "sg:postcode":"35580",
    "sg:province":"Las Palmas",
    "wof:name":"Meier  Doris",
    "wof:placetype":"venue"
},
  "geometry": {"coordinates":[-13.8307790756,28.8657550812],"type":"Point"}
}