{
  "type": "Feature",
  "properties": {
    "addr:full":"Calle de Golfo De Salonica, 20 Madrid Madrid 28033",
    "addr:housenumber":"20",
    "addr:postcode":"madrid;28033",
    "addr:street":"Calle De Golfo De Salonica",
    "iso:country":"ES",
    "sg:address":"Calle de Golfo De Salonica, 20",
    "sg:city":"Madrid",
    "sg:orig_category":"Inmobiliaria (agencias)",
    "sg:phone":"+34 917 67 27 63",
    "sg:postcode":"28033",
    "sg:province":"Madrid",
    "wof:name":"Silpa Inversiones S.l.",
    "wof:placetype":"venue"
},
  "geometry": {"coordinates":[-3.6654849052,40.4759140015],"type":"Point"}
}