{
  "type": "Feature",
  "properties": {
    "iso:country":"ES",
    "sg:address":"Carr Petra, 87",
    "sg:city":"Sant Joan",
    "sg:orig_category":"Cooperativas Agr\u00cdcolas",
    "sg:phone":"+34 971 52 63 24",
    "sg:postcode":"07240",
    "sg:province":"Islas Baleares",
    "wof:name":"Cooperativa Agricola San Juan",
    "wof:placetype":"venue"
},
  "geometry": {"coordinates":[3.0475699902,39.5929298401],"type":"Point"}
}