{
  "type": "Feature",
  "properties": {
    "addr:full":"Avda Canteras (de Las), 27 Valmor-rompecubas Madrid 28340",
    "addr:housenumber":"27",
    "addr:postcode":"28340",
    "addr:street":"Avda Canteras De Las",
    "iso:country":"ES",
    "sg:address":"Avda Canteras (de Las), 27",
    "sg:city":"Valmor-rompecubas",
    "sg:orig_category":"Gr\u00daas, Montacargas Y Elevadores Para Astilleros",
    "sg:phone":"+34 918 95 50 25",
    "sg:postcode":"28340",
    "sg:province":"Madrid",
    "wof:name":"Carrocerias Peivan S.c.p.",
    "wof:placetype":"venue"
},
  "geometry": {"coordinates":[-3.6677899361,40.1646308899],"type":"Point"}
}