{
  "type": "Feature",
  "properties": {
    "addr:full":"Carr Sant Anastasi, 10 Badalona Barcelona 08911",
    "addr:housenumber":"10",
    "addr:postcode":"08911",
    "addr:street":"Carr Sant Anastasi",
    "iso:country":"ES",
    "sg:address":"Carr Sant Anastasi, 10",
    "sg:city":"Badalona",
    "sg:orig_category":"Ropa Para Se\u00d1oras (al Por Menor)",
    "sg:phone":"+34 934 64 48 39",
    "sg:postcode":"08911",
    "sg:province":"Barcelona",
    "wof:name":"Nogues Boqueras Moises",
    "wof:placetype":"venue"
},
  "geometry": {"coordinates":[2.2471408844,41.4505310059],"type":"Point"}
}