{
  "type": "Feature",
  "properties": {
    "iso:country":"ES",
    "sg:address":"Vali\u00f1o, S/n",
    "sg:city":"Mondo\u00f1edo",
    "sg:orig_category":"Contenedores (mercanc\u00cdas)",
    "sg:phone":"+34 982 52 12 09",
    "sg:postcode":"27740",
    "sg:province":"Lugo",
    "wof:name":"Transportes Zo\u00f1an S.l.",
    "wof:placetype":"venue"
},
  "geometry": {"coordinates":[-7.3697309494,43.4380378723],"type":"Point"}
}