{
  "type": "Feature",
  "properties": {
    "iso:country":"ES",
    "sg:address":"Barrio La Capellania, S/n",
    "sg:city":"Celis",
    "sg:orig_category":"Supermercados Y Hipermercados",
    "sg:phone":"+34 942 72 76 36",
    "sg:postcode":"39553",
    "sg:province":"Cantabria",
    "wof:name":"Alvarez Guerra Sara",
    "wof:placetype":"venue"
},
  "geometry": {"coordinates":[-4.434674263,43.2829017639],"type":"Point"}
}