{
  "type": "Feature",
  "properties": {
    "iso:country":"ES",
    "sg:address":"Carrer de Biscaia, 454",
    "sg:city":"Barcelona",
    "sg:orig_category":"Molduras, Junquillos, Listones Y Molduras Perforadas",
    "sg:phone":"+34 933 40 05 85",
    "sg:postcode":"08027",
    "sg:province":"Barcelona",
    "wof:name":"Fortea Pastor Clara",
    "wof:placetype":"venue"
},
  "geometry": {"coordinates":[2.1822309494,41.4206352234],"type":"Point"}
}