{
  "type": "Feature",
  "properties": {
    "addr:full":"Avenida Florentino Agustin Diez, 18 Canales-magdalena Le\u00f3n 24120",
    "addr:housenumber":"18",
    "addr:postcode":"24120",
    "addr:street":"Avenida Florentino Agustin Diez;Leo\u0301N",
    "iso:country":"ES",
    "sg:address":"Avenida Florentino Agustin Diez, 18",
    "sg:city":"Canales-magdalena",
    "sg:orig_category":"Comercio De Minerales, F\u00d3siles Y Conchas",
    "sg:phone":"+34 987 58 10 23",
    "sg:postcode":"24120",
    "sg:province":"Le\u00f3n",
    "wof:name":"Ordo\u00f1ez Balbuena Ricarda",
    "wof:placetype":"venue"
},
  "geometry": {"coordinates":[-5.8100237846,42.7811889648],"type":"Point"}
}