{
  "type": "Feature",
  "properties": {
    "iso:country":"ES",
    "sg:address":"Calle de Maestro Roca, 5",
    "sg:city":"Pe\u00f1iscola",
    "sg:orig_category":"Clases De M\u00dasica Y Canto",
    "sg:phone":"+34 964 48 98 01",
    "sg:postcode":"12598",
    "sg:province":"Castell\u00f3n",
    "wof:name":"Asociacion Cultural Escuela De Musica Ciudad De Pe\u00f1iscola",
    "wof:placetype":"venue"
},
  "geometry": {"coordinates":[-0.0360242017,39.9860687256],"type":"Point"}
}