{
  "type": "Feature",
  "properties": {
    "addr:full":"Calle de Doce De Octubre, 20 Madrid Madrid 28009",
    "addr:housenumber":"20",
    "addr:postcode":"madrid;28009",
    "addr:street":"Calle De Doce De Octubre",
    "iso:country":"ES",
    "sg:address":"Calle de Doce De Octubre, 20",
    "sg:city":"Madrid",
    "sg:orig_category":"Supermercados Y Hipermercados",
    "sg:phone":"+34 915 73 67 41",
    "sg:postcode":"28009",
    "sg:province":"Madrid",
    "sg:website":"www.capraboacasa.com",
    "wof:name":"Caprabo S.a.",
    "wof:placetype":"venue"
},
  "geometry": {"coordinates":[-3.6756742001,40.4158172607],"type":"Point"}
}