{
  "type": "Feature",
  "properties": {
    "addr:full":"Plaz Albert Einstein, 10 Granada Granada 18002",
    "addr:housenumber":"10",
    "addr:postcode":"18002",
    "addr:street":"Plaz Albert Einstein",
    "iso:country":"ES",
    "sg:address":"Plaz Albert Einstein, 10",
    "sg:city":"Granada",
    "sg:orig_category":"Organismos De Reclutamiento",
    "sg:phone":"+34 958 20 38 52",
    "sg:postcode":"18002",
    "sg:province":"Granada",
    "wof:name":"Talentic, S.l",
    "wof:placetype":"venue"
},
  "geometry": {"coordinates":[-3.6090700626,37.1778564453],"type":"Point"}
}