{
  "type": "Feature",
  "properties": {
    "iso:country":"ES",
    "sg:address":"Carretera Roquetes, 23",
    "sg:city":"Tortosa",
    "sg:orig_category":"Centros De Educaci\u00d3n Especial",
    "sg:phone":"+34 977 50 30 09",
    "sg:postcode":"43500",
    "sg:province":"Tarragona",
    "wof:name":"Escola Infantil Mare Natura S.c.c.l.",
    "wof:placetype":"venue"
},
  "geometry": {"coordinates":[0.5209109783,40.8127632141],"type":"Point"}
}