{
  "type": "Feature",
  "properties": {
    "addr:full":"Rond San Francisco (de), 1 Lucena C\u00f3rdoba 14900",
    "addr:postcode":"14900",
    "addr:street":"Francisco;Co\u0301Rdoba",
    "iso:country":"ES",
    "sg:address":"Rond San Francisco (de), 1",
    "sg:city":"Lucena",
    "sg:orig_category":"Transportes Por Carretera: Lotes Completos, Mercanc\u00cdas Diversas",
    "sg:phone":"+34 957 51 40 68",
    "sg:postcode":"14900",
    "sg:province":"C\u00f3rdoba",
    "wof:name":"Alimentacion Peninsular S.a.",
    "wof:placetype":"venue"
},
  "geometry": {"coordinates":[-4.5418143272,37.3598442078],"type":"Point"}
}