{
  "type": "Feature",
  "properties": {
    "addr:full":"Calle de Carrera, 10 Casares M\u00e1laga 29690",
    "addr:postcode":"29690",
    "addr:street":"Calle De Carrera 10 Casares Ma\u0301Laga",
    "iso:country":"ES",
    "sg:address":"Calle de Carrera, 10",
    "sg:city":"Casares",
    "sg:orig_category":"Cajas Para Embalar",
    "sg:phone":"+34 952 89 40 50",
    "sg:postcode":"29690",
    "sg:province":"M\u00e1laga",
    "sg:website":"www.cajamar.es",
    "wof:name":"Cajamar",
    "wof:placetype":"venue"
},
  "geometry": {"coordinates":[-5.2729291916,36.4444961548],"type":"Point"}
}