{
  "type": "Feature",
  "properties": {
    "iso:country":"ES",
    "sg:address":"Calle de Vara De Rey, 16",
    "sg:city":"Madrid",
    "sg:orig_category":"Marketing Directo",
    "sg:phone":"+34 914 68 23 90",
    "sg:postcode":"28045",
    "sg:province":"Madrid",
    "sg:website":"www.alfedonbuzon@telefonica.net",
    "wof:name":"Alfe Don Buzon S.l.",
    "wof:placetype":"venue"
},
  "geometry": {"coordinates":[-3.6894471645,40.4011497498],"type":"Point"}
}