{
  "type": "Feature",
  "properties": {
    "addr:full":"Aralar, 43 Iru\u00f1a Navarra 31004",
    "addr:housenumber":"43",
    "addr:postcode":"31004",
    "addr:street":"Aralar",
    "iso:country":"ES",
    "sg:address":"Aralar, 43",
    "sg:city":"Iru\u00f1a",
    "sg:orig_category":"Agencias Y Agentes Comerciales, Representantes",
    "sg:phone":"+34 948 15 08 89",
    "sg:postcode":"31004",
    "sg:province":"Navarra",
    "wof:name":"Otiz De Lazcano Piquer Jorge",
    "wof:placetype":"venue"
},
  "geometry": {"coordinates":[-1.632174015,42.8108558655],"type":"Point"}
}