{
  "type": "Feature",
  "properties": {
    "iso:country":"ES",
    "sg:address":"Calle de Extremadura (de), 3",
    "sg:city":"Jaen",
    "sg:orig_category":"Inmobiliaria (agencias)",
    "sg:phone":"+34 953 29 46 01",
    "sg:postcode":"23006",
    "sg:province":"Ja\u00e9n",
    "sg:website":"www.redde.iespana.es",
    "wof:name":"Garcia Garcia Salvador",
    "wof:placetype":"venue"
},
  "geometry": {"coordinates":[-3.7914559841,37.7809257507],"type":"Point"}
}