{
  "type": "Feature",
  "properties": {
    "addr:full":"Union, 17 Vecindario Las Palmas 35110",
    "addr:housenumber":"17",
    "addr:postcode":"35110",
    "addr:street":"Vecindario Las Palmas",
    "iso:country":"ES",
    "sg:address":"Union, 17",
    "sg:city":"Vecindario",
    "sg:orig_category":"Molduras, Junquillos, Listones Y Molduras Perforadas",
    "sg:phone":"+34 928 75 80 19",
    "sg:postcode":"35110",
    "sg:province":"Las Palmas",
    "wof:name":"Vega Sardi\u00f1a Luis",
    "wof:placetype":"venue"
},
  "geometry": {"coordinates":[-15.4450778961,27.8479499817],"type":"Point"}
}