{
  "type": "Feature",
  "properties": {
    "addr:full":"Avda Norte, S/n Huelva Huelva 21001",
    "addr:housenumber":"s / n",
    "addr:postcode":"21001",
    "addr:street":"Avda Norte",
    "iso:country":"ES",
    "sg:address":"Avda Norte, S/n",
    "sg:city":"Huelva",
    "sg:orig_category":"\u00d3ptica: Instrumentos (fabricaci\u00d3n)",
    "sg:phone":"+34 959 35 90 12",
    "sg:postcode":"21001",
    "sg:province":"Huelva",
    "wof:name":"Soloptical Berceo S.l.",
    "wof:placetype":"venue"
},
  "geometry": {"coordinates":[-6.9570188522,37.2560043335],"type":"Point"}
}