{
  "type": "Feature",
  "properties": {
    "iso:country":"ES",
    "sg:address":"Calle de Cura Iba\u00d1ez, 8",
    "sg:city":"Yecla",
    "sg:orig_category":"Sales (al Por Mayor)",
    "sg:phone":"+34 968 79 04 22",
    "sg:postcode":"30510",
    "sg:province":"Murcia",
    "wof:name":"Francisco Lopez Jose Ba\u00f1on Y Jose P.juan C.b.",
    "wof:placetype":"venue"
},
  "geometry": {"coordinates":[-1.1090933084,38.6121940613],"type":"Point"}
}