{
  "type": "Feature",
  "properties": {
    "addr:full":"Afores, S/n Viver Barcelona 08679",
    "addr:housenumber":"s / n",
    "addr:postcode":"08679",
    "addr:street":"Afores",
    "iso:country":"ES",
    "sg:address":"Afores, S/n",
    "sg:city":"Viver",
    "sg:orig_category":"Bosques (trabajos, Asesor\u00cda, Gesti\u00d3n)",
    "sg:phone":"+34 938 39 04 19",
    "sg:postcode":"08679",
    "sg:province":"Barcelona",
    "wof:name":"Agro-viver S.l.",
    "wof:placetype":"venue"
},
  "geometry": {"coordinates":[1.8130135536,41.9563598633],"type":"Point"}
}