{
  "type": "Feature",
  "properties": {
    "addr:full":"Calle de Here\u00d1a, S/n Here\u00d1a \u00c1lava 01429",
    "addr:housenumber":"s",
    "addr:postcode":"01429",
    "addr:street":"Calle De Heren\u0303A;/ N Heren\u0303A A\u0301Lava",
    "iso:country":"ES",
    "sg:address":"Calle de Here\u00d1a, S/n",
    "sg:city":"Here\u00d1a",
    "sg:orig_category":"Empresas De Hormig\u00d3n, Hormig\u00d3n Armado Y Pretensado",
    "sg:phone":"+34 945 36 21 02",
    "sg:postcode":"01429",
    "sg:province":"\u00c1lava",
    "sg:website":"www.weser.es",
    "wof:name":"Weser Iberica Prefabricados De Hormigones S.a.",
    "wof:placetype":"venue"
},
  "geometry": {"coordinates":[-2.9039449692,42.7776489258],"type":"Point"}
}