{
  "type": "Feature",
  "properties": {
    "iso:country":"ES",
    "sg:address":"Carr Generalitat De Catalunya, S/n",
    "sg:city":"Bell-lloc D'urgell",
    "sg:orig_category":"Empresarios",
    "sg:phone":"+34 973 56 02 56",
    "sg:postcode":"25220",
    "sg:province":"Lleida",
    "wof:name":"Bosch Tarda Vicente",
    "wof:placetype":"venue"
},
  "geometry": {"coordinates":[0.6457189918,41.6027946472],"type":"Point"}
}