{
  "type": "Feature",
  "properties": {
    "iso:country":"ES",
    "sg:address":"Calle de Ramon Perez De Ayala, 58",
    "sg:city":"Madrid",
    "sg:orig_category":"Ebanister\u00cda",
    "sg:phone":"+34 913 28 20 88",
    "sg:postcode":"28038",
    "sg:province":"Madrid",
    "wof:name":"Lamas Carpinteros C.b.",
    "wof:placetype":"venue"
},
  "geometry": {"coordinates":[-3.6522352695,40.4007110596],"type":"Point"}
}