{
  "type": "Feature",
  "properties": {
    "iso:country":"ES",
    "sg:address":"Calle de Mayor, 44",
    "sg:city":"Canteras",
    "sg:orig_category":"Venta, Instalaci\u00d3n De Cocinas",
    "sg:phone":"+34 968 55 31 29",
    "sg:postcode":"30394",
    "sg:province":"Murcia",
    "wof:name":"Moreno Garcia Antonio",
    "wof:placetype":"venue"
},
  "geometry": {"coordinates":[-1.0416369438,37.612071991],"type":"Point"}
}