{
  "type": "Feature",
  "properties": {
    "iso:country":"ES",
    "sg:address":"Calle de Paz (la), 165",
    "sg:city":"Torrevieja",
    "sg:orig_category":"Mec\u00c1nico Del Autom\u00d3vil",
    "sg:phone":"+34 965 71 05 59",
    "sg:postcode":"03180",
    "sg:province":"Alicante",
    "wof:name":"Andres Damian Francisco",
    "wof:placetype":"venue"
},
  "geometry": {"coordinates":[-0.6810371876,37.9794769287],"type":"Point"}
}