{
  "type": "Feature",
  "properties": {
    "addr:full":"Calle de Antonio Concha, 6 Navalmoral Mata C\u00e1ceres 10300",
    "addr:housenumber":"6",
    "addr:postcode":"10300",
    "addr:street":"Calle De Antonio Concha;Ca\u0301Ceres",
    "iso:country":"ES",
    "sg:address":"Calle de Antonio Concha, 6",
    "sg:city":"Navalmoral Mata",
    "sg:orig_category":"Aguas (distribuci\u00d3n, Servicios)",
    "sg:phone":"+34 927 53 21 84",
    "sg:postcode":"10300",
    "sg:province":"C\u00e1ceres",
    "sg:website":"www.personal.iddeo.es/edepuradorassa",
    "wof:name":"Estaciones Depuradoras S.a.",
    "wof:placetype":"venue"
},
  "geometry": {"coordinates":[-5.5346736908,39.8902397156],"type":"Point"}
}