{
  "type": "Feature",
  "properties": {
    "iso:country":"ES",
    "sg:address":"Calle de Aguila, 8",
    "sg:city":"Granada",
    "sg:orig_category":"Sindicatos De Trabajadores",
    "sg:phone":"+34 958 52 31 53",
    "sg:postcode":"18002",
    "sg:province":"Granada",
    "wof:name":"Sindicato Independiente De Ense\u00f1anza",
    "wof:placetype":"venue"
},
  "geometry": {"coordinates":[-3.6019420624,37.1733856201],"type":"Point"}
}