{
  "type": "Feature",
  "properties": {
    "iso:country":"ES",
    "sg:address":"Calle de Soledad (la), S/n",
    "sg:city":"Cabanillas Campo",
    "sg:orig_category":"Centros De Educaci\u00d3n Especial",
    "sg:phone":"+34 949 33 22 13",
    "sg:postcode":"19171",
    "sg:province":"Guadalajara",
    "wof:name":"Colegio Publico San Blas",
    "wof:placetype":"venue"
},
  "geometry": {"coordinates":[-3.238478899,40.63829422],"type":"Point"}
}