{
  "type": "Feature",
  "properties": {
    "addr:full":"Avda Concordia, 35 Talavera Real Badajoz 06140",
    "addr:housenumber":"35",
    "addr:postcode":"06140",
    "addr:street":"Avda Concordia",
    "iso:country":"ES",
    "sg:address":"Avda Concordia, 35",
    "sg:city":"Talavera Real",
    "sg:orig_category":"Bisuter\u00cda, Joyer\u00cda, Relojer\u00cda (al Por Menor)",
    "sg:phone":"+34 924 44 03 71",
    "sg:postcode":"06140",
    "sg:province":"Badajoz",
    "wof:name":"Roman Crespo Jose Maria",
    "wof:placetype":"venue"
},
  "geometry": {"coordinates":[-6.7671108246,38.8729438782],"type":"Point"}
}