{
  "type": "Feature",
  "properties": {
    "addr:full":"Praz Maior, 3 Xinzo De Limia Ourense 32630",
    "addr:housenumber":"3",
    "addr:postcode":"32630",
    "addr:street":"Praz Maior",
    "iso:country":"ES",
    "sg:address":"Praz Maior, 3",
    "sg:city":"Xinzo De Limia",
    "sg:orig_category":"Caf\u00c9s, Bares, Cervecer\u00cdas",
    "sg:phone":"+34 988 46 00 79",
    "sg:postcode":"32630",
    "sg:province":"Ourense",
    "wof:name":"Galtelcom",
    "wof:placetype":"venue"
},
  "geometry": {"coordinates":[-8.6335506439,42.6115875244],"type":"Point"}
}