{
  "type": "Feature",
  "properties": {
    "addr:full":"Calle de Peris Brell, 9 Valencia Valencia 46022",
    "addr:housenumber":"9",
    "addr:postcode":"46022",
    "addr:street":"Calle De Peris Brell",
    "iso:country":"ES",
    "sg:address":"Calle de Peris Brell, 9",
    "sg:city":"Valencia",
    "sg:orig_category":"Prot\u00c9sicos Dentales",
    "sg:phone":"+34 963 30 95 62",
    "sg:postcode":"46022",
    "sg:province":"Valencia",
    "wof:name":"Labodent C.b.",
    "wof:placetype":"venue"
},
  "geometry": {"coordinates":[-0.3476769924,39.4652709961],"type":"Point"}
}