{
  "type": "Feature",
  "properties": {
    "iso:country":"ES",
    "sg:address":"Carrer de Asturies, 23",
    "sg:city":"Barcelona",
    "sg:orig_category":"Textil",
    "sg:phone":"+34 932 37 06 39",
    "sg:postcode":"08012",
    "sg:province":"Barcelona",
    "wof:name":"Vouben S.l.",
    "wof:placetype":"venue"
},
  "geometry": {"coordinates":[2.1538414955,41.4030952454],"type":"Point"}
}