{
  "type": "Feature",
  "properties": {
    "iso:country":"ES",
    "sg:address":"Avda Aragon (de), 11",
    "sg:city":"Teruel",
    "sg:orig_category":"M\u00c9dicos: Estomatolog\u00cda",
    "sg:phone":"+34 978 61 74 60",
    "sg:postcode":"44002",
    "sg:province":"Teruel",
    "wof:name":"Cano Borao Manuel",
    "wof:placetype":"venue"
},
  "geometry": {"coordinates":[-1.1067689657,40.3304786682],"type":"Point"}
}