{
  "type": "Feature",
  "properties": {
    "iso:country":"ES",
    "sg:address":"Calle de Zuatzu, 2",
    "sg:city":"Donostia-san Sebastian",
    "sg:orig_category":"Trabajos De Topograf\u00cda",
    "sg:phone":"+34 943 31 64 96",
    "sg:postcode":"20018",
    "sg:province":"Guip\u00f9zcoa",
    "wof:name":"Neurri Ingenieros, S.a.",
    "wof:placetype":"venue"
},
  "geometry": {"coordinates":[-2.0090401173,43.2967758179],"type":"Point"}
}