{
  "type": "Feature",
  "properties": {
    "iso:country":"ES",
    "sg:address":"Calle de Toledo, 24",
    "sg:city":"Guadalajara",
    "sg:orig_category":"Internados & Ense\u00d1anza Privada",
    "sg:phone":"+34 949 24 71 11",
    "sg:postcode":"19002",
    "sg:province":"Guadalajara",
    "wof:name":"Colegio San Jose De Guadalajara Salesianos Inspectoria De San Juan",
    "wof:placetype":"venue"
},
  "geometry": {"coordinates":[-3.1612939835,40.62550354],"type":"Point"}
}