{
  "type": "Feature",
  "properties": {
    "iso:country":"ES",
    "sg:address":"Carr Anna Tugas, 8",
    "sg:city":"Badalona",
    "sg:orig_category":"Bancos",
    "sg:phone":"+34 933 95 55 36",
    "sg:postcode":"08917",
    "sg:province":"Barcelona",
    "wof:name":"Banco Espa\u00d1ol De Credito S.a.",
    "wof:placetype":"venue"
},
  "geometry": {"coordinates":[2.227545023,41.4550552368],"type":"Point"}
}