{
  "type": "Feature",
  "properties": {
    "iso:country":"ES",
    "sg:address":"Calle de Bruno Perez Medina, S/n",
    "sg:city":"Arucas",
    "sg:orig_category":"Electrodom\u00c9sticos (al Por Menor)",
    "sg:phone":"+34 928 60 51 02",
    "sg:postcode":"35400",
    "sg:province":"Las Palmas",
    "wof:name":"Rodriguez Gonzalez Andres",
    "wof:placetype":"venue"
},
  "geometry": {"coordinates":[-15.5269107819,28.1184864044],"type":"Point"}
}