{
  "type": "Feature",
  "properties": {
    "iso:country":"ES",
    "sg:address":"Calle de Purisima (la), 27",
    "sg:city":"Catral",
    "sg:orig_category":"Carnicer\u00cdas, Carnicer\u00cdas",
    "sg:phone":"+34 965 72 35 53",
    "sg:postcode":"03158",
    "sg:province":"Alicante",
    "wof:name":"Ballester Perez Antonio",
    "wof:placetype":"venue"
},
  "geometry": {"coordinates":[-0.8024889827,38.1641807556],"type":"Point"}
}