{
  "type": "Feature",
  "properties": {
    "addr:full":"Calle de Trujillo, 2 Alcorcon Madrid 28921",
    "addr:housenumber":"2",
    "addr:postcode":"28921",
    "addr:street":"Calle De Trujillo",
    "iso:country":"ES",
    "sg:address":"Calle de Trujillo, 2",
    "sg:city":"Alcorcon",
    "sg:orig_category":"Sexshops",
    "sg:phone":"+34 916 19 24 47",
    "sg:postcode":"28921",
    "sg:province":"Madrid",
    "sg:website":"www.tabualcorcon.com",
    "wof:name":"Ruiz Rodriguez Juan Manuel",
    "wof:placetype":"venue"
},
  "geometry": {"coordinates":[-3.8316040039,40.34815979],"type":"Point"}
}