{
  "type": "Feature",
  "properties": {
    "iso:country":"ES",
    "sg:address":"Calle de Progreso, 9",
    "sg:city":"Gabia Grande",
    "sg:orig_category":"Abogados",
    "sg:phone":"+34 958 58 59 12",
    "sg:postcode":"18110",
    "sg:province":"Granada",
    "wof:name":"Romero Blanco Fernando Miguel",
    "wof:placetype":"venue"
},
  "geometry": {"coordinates":[-3.6663548946,37.1366615295],"type":"Point"}
}