{
  "type": "Feature",
  "properties": {
    "iso:country":"ES",
    "sg:address":"Calle de Alberto Fernandez, 8",
    "sg:city":"Valladolid",
    "sg:orig_category":"Alimentaci\u00d3n General (al Por Menor)",
    "sg:phone":"+34 983 26 19 63",
    "sg:postcode":"47010",
    "sg:province":"Valladolid",
    "wof:name":"Valentin Gonzalez Antonio",
    "wof:placetype":"venue"
},
  "geometry": {"coordinates":[-4.7253680229,41.6637268066],"type":"Point"}
}