{
  "type": "Feature",
  "properties": {
    "addr:full":"Carr Vallcalent, 1 Lleida Lleida 25006",
    "addr:housenumber":"1",
    "addr:postcode":"25006",
    "addr:street":"Carr Vallcalent",
    "iso:country":"ES",
    "sg:address":"Carr Vallcalent, 1",
    "sg:city":"Lleida",
    "sg:orig_category":"Inform\u00c1tica (estudios, Servicios, Asesor\u00cda, Formaci\u00d3n)",
    "sg:phone":"+34 973 28 92 83",
    "sg:postcode":"25006",
    "sg:province":"Lleida",
    "wof:name":"France Telecom Espa\u00f1a S.a.",
    "wof:placetype":"venue"
},
  "geometry": {"coordinates":[0.6203600168,41.6168708801],"type":"Point"}
}