{
  "type": "Feature",
  "properties": {
    "addr:full":"Calle de Breton De Los Herreros, 26 Madrid Madrid 28003",
    "addr:housenumber":"26",
    "addr:postcode":"madrid;28003",
    "addr:street":"Calle De Breton De Los Herreros",
    "iso:country":"ES",
    "sg:address":"Calle de Breton De Los Herreros, 26",
    "sg:city":"Madrid",
    "sg:orig_category":"Institutos De Belleza",
    "sg:phone":"+34 913 99 39 76",
    "sg:postcode":"28003",
    "sg:province":"Madrid",
    "sg:website":"www.mimate.net",
    "wof:name":"Mimate C.b.",
    "wof:placetype":"venue"
},
  "geometry": {"coordinates":[-3.6980395317,40.4395256042],"type":"Point"}
}