{
  "type": "Feature",
  "properties": {
    "iso:country":"ES",
    "sg:address":"Calle de Do\u00d1a Juana Cordon, 11",
    "sg:city":"Pradejon",
    "sg:orig_category":"Asesor\u00cda Fiscal Y Jur\u00cddica",
    "sg:phone":"+34 941 14 11 19",
    "sg:postcode":"26510",
    "sg:province":"La Rioja",
    "wof:name":"Torrano Lopez Maria Del Alba",
    "wof:placetype":"venue"
},
  "geometry": {"coordinates":[-2.0681869984,42.3342781067],"type":"Point"}
}