{
  "type": "Feature",
  "properties": {
    "addr:full":"Calle de Marquesa De Canillejas, 25 Pola De Siero Asturias 33510",
    "addr:housenumber":"25",
    "addr:postcode":"33510",
    "addr:street":"Calle De Marquesa De Canillejas",
    "iso:country":"ES",
    "sg:address":"Calle de Marquesa De Canillejas, 25",
    "sg:city":"Pola De Siero",
    "sg:orig_category":"Cajas De Ahorro",
    "sg:phone":"+34 985 72 00 89",
    "sg:postcode":"33510",
    "sg:province":"Asturias",
    "wof:name":"Cajastur",
    "wof:placetype":"venue"
},
  "geometry": {"coordinates":[-5.6607718468,43.3928604126],"type":"Point"}
}