{
  "type": "Feature",
  "properties": {
    "addr:full":"Alfarero Salvador Hernandez, S/n Vera Almer\u00eda 04620",
    "addr:housenumber":"/ n;almeri\u0301a",
    "addr:postcode":"04620",
    "addr:street":"Hernandez S",
    "iso:country":"ES",
    "sg:address":"Alfarero Salvador Hernandez, S/n",
    "sg:city":"Vera",
    "sg:orig_category":"Material Y Suministros Para Dentistas, Cirujanos",
    "sg:phone":"+34 950 39 06 55",
    "sg:postcode":"04620",
    "sg:province":"Almer\u00eda",
    "wof:name":"Clinica Dental Vivadent S.l.",
    "wof:placetype":"venue"
},
  "geometry": {"coordinates":[-1.8647290468,37.2478790283],"type":"Point"}
}