{
  "type": "Feature",
  "properties": {
    "addr:full":"Pg Generalitat, 15 Banyoles Girona 17820",
    "addr:housenumber":"15",
    "addr:postcode":"17820",
    "addr:street":"Pg Generalitat",
    "iso:country":"ES",
    "sg:address":"Pg Generalitat, 15",
    "sg:city":"Banyoles",
    "sg:orig_category":"Laboratorios Y Cl\u00cdnicas Veterinarias",
    "sg:phone":"+34 972 58 32 88",
    "sg:postcode":"17820",
    "sg:province":"Girona",
    "wof:name":"Parals Granero Fausto",
    "wof:placetype":"venue"
},
  "geometry": {"coordinates":[2.7608349323,42.1233406067],"type":"Point"}
}