{
  "type": "Feature",
  "properties": {
    "addr:full":"Ctra Doctor Robert, 48 Vendrell Tarragona 43700",
    "addr:housenumber":"48",
    "addr:postcode":"43700",
    "addr:street":"Ctra Doctor Robert",
    "iso:country":"ES",
    "sg:address":"Ctra Doctor Robert, 48",
    "sg:city":"Vendrell",
    "sg:orig_category":"Comercio De Piezas De Recambio Y De Accesorios De Veh\u00cdculos, Veh\u00cdculos Industriales",
    "sg:phone":"+34 977 66 50 00",
    "sg:postcode":"43700",
    "sg:province":"Tarragona",
    "wof:name":"Ferret Carbonell Jose",
    "wof:placetype":"venue"
},
  "geometry": {"coordinates":[1.5380829573,41.2218475342],"type":"Point"}
}