{
  "type": "Feature",
  "properties": {
    "iso:country":"ES",
    "sg:address":"Calle de Escultor Roque Lopez, 2",
    "sg:city":"San Miguel",
    "sg:orig_category":"Agencias Y Agentes Comerciales, Representantes",
    "sg:phone":"+34 968 24 23 72",
    "sg:postcode":"30008",
    "sg:province":"Murcia",
    "wof:name":"Gallego Gimenez Francisco",
    "wof:placetype":"venue"
},
  "geometry": {"coordinates":[-1.1317230463,37.9906082153],"type":"Point"}
}