{
  "type": "Feature",
  "properties": {
    "addr:full":"Calle de Guadiana, 4 Villamartin C\u00e1diz 11650",
    "addr:housenumber":"4",
    "addr:postcode":"11650",
    "addr:street":"Calle De Guadiana;Ca\u0301Diz",
    "iso:country":"ES",
    "sg:address":"Calle de Guadiana, 4",
    "sg:city":"Villamartin",
    "sg:orig_category":"Peluqueros: De Se\u00d1oras",
    "sg:phone":"+34 956 73 02 63",
    "sg:postcode":"11650",
    "sg:province":"C\u00e1diz",
    "wof:name":"Jimenez Rodriguez Consuelo",
    "wof:placetype":"venue"
},
  "geometry": {"coordinates":[-5.6464891434,36.8602294922],"type":"Point"}
}