{
  "type": "Feature",
  "properties": {
    "iso:country":"ES",
    "sg:address":"Pase Extremadura, 209",
    "sg:city":"Monesterio",
    "sg:orig_category":"Alimentaci\u00d3n General (al Por Menor)",
    "sg:phone":"+34 924 51 73 17",
    "sg:postcode":"06260",
    "sg:province":"Badajoz",
    "wof:name":"Carrasco Mestre Jose",
    "wof:placetype":"venue"
},
  "geometry": {"coordinates":[-6.2733559608,38.0909118652],"type":"Point"}
}