{
  "type": "Feature",
  "properties": {
    "addr:full":"Ibargarai Hiribidea, 30 Bergara Guip\u00f9zcoa 20570",
    "addr:housenumber":"30",
    "addr:postcode":"20570",
    "addr:street":"Ibargarai Hiribidea;Guipu\u0300Zcoa",
    "iso:country":"ES",
    "sg:address":"Ibargarai Hiribidea, 30",
    "sg:city":"Bergara",
    "sg:orig_category":"Agentes Generales De Seguros",
    "sg:phone":"+34 943 76 08 71",
    "sg:postcode":"20570",
    "sg:province":"Guip\u00f9zcoa",
    "wof:name":"Juaristi Etxeberria I\u00f1igo",
    "wof:placetype":"venue"
},
  "geometry": {"coordinates":[-2.4157474041,43.1153450012],"type":"Point"}
}