{
  "type": "Feature",
  "properties": {
    "iso:country":"ES",
    "sg:address":"Pl. Marce%ina Monteys, 6",
    "sg:city":"El Masnou",
    "sg:orig_category":"Cajas De Ahorro",
    "sg:phone":"+34 935 40 51 38",
    "sg:postcode":"08320",
    "sg:province":"Barcelona",
    "wof:name":"Caixa Deestalvis De Manresa",
    "wof:placetype":"venue"
},
  "geometry": {"coordinates":[2.3165249825,41.480670929],"type":"Point"}
}