{
  "type": "Feature",
  "properties": {
    "iso:country":"ES",
    "sg:address":"Pg Germanies (de Les), 104",
    "sg:city":"Gandia",
    "sg:orig_category":"Panader\u00cdas, Panader\u00cdas",
    "sg:phone":"+34 962 86 22 49",
    "sg:postcode":"46700",
    "sg:province":"Valencia",
    "wof:name":"Toan S. L.",
    "wof:placetype":"venue"
},
  "geometry": {"coordinates":[-0.1923040003,38.9672088623],"type":"Point"}
}