{
  "type": "Feature",
  "properties": {
    "iso:country":"ES",
    "sg:address":"Meta%urgia (pol Ind Belianes), 24",
    "sg:city":"Cambrils",
    "sg:orig_category":"Ingenier\u00cda, Centros De Estudios (industria)",
    "sg:phone":"+34 977 36 33 65",
    "sg:postcode":"43850",
    "sg:province":"Tarragona",
    "wof:name":"Invercam Costa Daurada S.l.",
    "wof:placetype":"venue"
},
  "geometry": {"coordinates":[1.0380749702,41.0785217285],"type":"Point"}
}