{
  "type": "Feature",
  "properties": {
    "iso:country":"ES",
    "sg:address":"Calle de Ciruela, 10",
    "sg:city":"Ciudad Real",
    "sg:orig_category":"Ropa Y Accesorios",
    "sg:phone":"+34 926 22 29 69",
    "sg:postcode":"13001",
    "sg:province":"Ciudad Real",
    "wof:name":"Rivas Rojas Vicente",
    "wof:placetype":"venue"
},
  "geometry": {"coordinates":[-3.9278810024,38.9816741943],"type":"Point"}
}