{
  "type": "Feature",
  "properties": {
    "iso:country":"ES",
    "sg:address":"Carretera Nacional, Km. 0225,9",
    "sg:city":"S. Esteban Gormaz",
    "sg:orig_category":"Bater\u00cdas",
    "sg:phone":"+34 975 35 04 50",
    "sg:postcode":"42330",
    "sg:province":"Soria",
    "wof:name":"Sociedad Espa\u00d1ola Del Acumulador Tudor S.a.",
    "wof:placetype":"venue"
},
  "geometry": {"coordinates":[-3.1995689869,41.5723457336],"type":"Point"}
}