{
  "type": "Feature",
  "properties": {
    "iso:country":"ES",
    "sg:address":"Ctra. Soria Plasencia, Km. 0090,5",
    "sg:city":"La Colilla",
    "sg:orig_category":"Contenedores Para Transporte De Mercanc\u00cdas",
    "sg:phone":"+34 920 26 97 87",
    "sg:postcode":"05192",
    "sg:province":"\u00c1vila",
    "wof:name":"Martin Rodriguez Maximiliano",
    "wof:placetype":"venue"
},
  "geometry": {"coordinates":[-4.8183860779,40.6346130371],"type":"Point"}
}