{
  "type": "Feature",
  "properties": {
    "addr:full":"Calle de San Agustin, 13 Icod De Los Vinos Santa Cruz De Tenerife 38430",
    "addr:housenumber":"13",
    "addr:postcode":"38430",
    "addr:street":"Calle De San Agustin",
    "iso:country":"ES",
    "sg:address":"Calle de San Agustin, 13",
    "sg:city":"Icod De Los Vinos",
    "sg:orig_category":"Librer\u00cdas",
    "sg:phone":"+34 922 81 00 69",
    "sg:postcode":"38430",
    "sg:province":"Santa Cruz De Tenerife",
    "wof:name":"Perez Dorta Miguel Angel",
    "wof:placetype":"venue"
},
  "geometry": {"coordinates":[-16.7183532715,28.3671760559],"type":"Point"}
}