{
  "type": "Feature",
  "properties": {
    "addr:full":"Avda Jose Lopez, 17 Castellar Ja\u00e9n 23260",
    "addr:housenumber":"17",
    "addr:postcode":"23260",
    "addr:street":"Avda Jose Lopez",
    "iso:country":"ES",
    "sg:address":"Avda Jose Lopez, 17",
    "sg:city":"Castellar",
    "sg:orig_category":"Panader\u00cdas, Pasteler\u00cdas, Boller\u00cda Industriale (fabricaci\u00d3n, Al Por Mayor)",
    "sg:phone":"+34 953 40 02 15",
    "sg:postcode":"23260",
    "sg:province":"Ja\u00e9n",
    "wof:name":"Dulceria Macias S.l.u.",
    "wof:placetype":"venue"
},
  "geometry": {"coordinates":[-3.1323199272,38.2539482117],"type":"Point"}
}