{
  "type": "Feature",
  "properties": {
    "addr:full":"Calle de Asturias, 9 Oviedo Asturias 33004",
    "addr:housenumber":"9",
    "addr:postcode":"33004",
    "addr:street":"Calle De Asturias",
    "iso:country":"ES",
    "sg:address":"Calle de Asturias, 9",
    "sg:city":"Oviedo",
    "sg:orig_category":"Consultas M\u00c9dicas",
    "sg:phone":"+34 985 23 27 43",
    "sg:postcode":"33004",
    "sg:province":"Asturias",
    "wof:name":"Clinica Ginecologica Cecchini S.l.",
    "wof:placetype":"venue"
},
  "geometry": {"coordinates":[-5.8542733192,43.3624610901],"type":"Point"}
}