{
  "type": "Feature",
  "properties": {
    "addr:full":"Avenida San Jeronimo, 35 Bornos C\u00e1diz 11640",
    "addr:housenumber":"35",
    "addr:postcode":"11640",
    "addr:street":"Avenida San Jeronimo",
    "iso:country":"ES",
    "sg:address":"Avenida San Jeronimo, 35",
    "sg:city":"Bornos",
    "sg:classifiers":[
        {
            "category":"Communications",
            "type":"Services"
        }
    ],
    "sg:phone":"+34 956 71 22 13",
    "sg:postcode":"11640",
    "sg:province":"C\u00e1diz",
    "sg:tags":[
        "televisiones",
        "y",
        "radio"
    ],
    "wof:name":"Inmobiliarias Linea 19 S.l.",
    "wof:placetype":"venue"
},
  "geometry": {"coordinates":[-5.743311882,36.8173599243],"type":"Point"}
}