{
  "type": "Feature",
  "properties": {
    "addr:full":"Riera Del Pare Fita, 93 Arenys Mar Barcelona 08350",
    "addr:housenumber":"93",
    "addr:postcode":"08350",
    "addr:street":"Riera Del Pare Fita",
    "iso:country":"ES",
    "sg:address":"Riera Del Pare Fita, 93",
    "sg:city":"Arenys Mar",
    "sg:orig_category":"Cajas De Ahorro",
    "sg:phone":"+34 937 95 82 71",
    "sg:postcode":"08350",
    "sg:province":"Barcelona",
    "sg:website":"www.caixalaietana.es",
    "wof:name":"Caixa D'estalvis Laietana",
    "wof:placetype":"venue"
},
  "geometry": {"coordinates":[2.5450599194,41.5866394043],"type":"Point"}
}