{
  "type": "Feature",
  "properties": {
    "addr:full":"Calle de Islas, 41 Madrid Madrid 28021",
    "addr:housenumber":"41",
    "addr:postcode":"madrid;28021",
    "addr:street":"Calle De Islas",
    "iso:country":"ES",
    "sg:address":"Calle de Islas, 41",
    "sg:city":"Madrid",
    "sg:orig_category":"Poller\u00cda Y Caza (al Por Menor)",
    "sg:phone":"+34 917 98 33 86",
    "sg:postcode":"28021",
    "sg:province":"Madrid",
    "wof:name":"Aguilar Sanchez Antonia",
    "wof:placetype":"venue"
},
  "geometry": {"coordinates":[-3.7161493301,40.3499069214],"type":"Point"}
}