{
  "type": "Feature",
  "properties": {
    "addr:full":"Calle de Herreria, 34 Barrios C\u00e1diz 11370",
    "addr:housenumber":"34",
    "addr:postcode":"11370",
    "addr:street":"Calle De Herreria;Ca\u0301Diz",
    "iso:country":"ES",
    "sg:address":"Calle de Herreria, 34",
    "sg:city":"Barrios",
    "sg:orig_category":"Prot\u00c9sicos Dentales",
    "sg:phone":"+34 956 62 25 08",
    "sg:postcode":"11370",
    "sg:province":"C\u00e1diz",
    "wof:name":"Lembert Morales Luis Eugenio",
    "wof:placetype":"venue"
},
  "geometry": {"coordinates":[-5.4921951294,36.1837768555],"type":"Point"}
}