{
  "type": "Feature",
  "properties": {
    "iso:country":"ES",
    "sg:address":"Cm\u00d1o Laranxo, 10",
    "sg:city":"Igrexa",
    "sg:orig_category":"Adhesivos (fabricaci\u00d3n, Al Por Mayor)",
    "sg:phone":"+34 986 20 01 13",
    "sg:postcode":"36312",
    "sg:province":"Pontevedra",
    "wof:name":"Costas Fernandez Gabriel",
    "wof:placetype":"venue"
},
  "geometry": {"coordinates":[-8.7040929794,42.1925163269],"type":"Point"}
}