{
  "type": "Feature",
  "properties": {
    "iso:country":"ES",
    "sg:address":"Carrer de Unio, 13",
    "sg:city":"Palma",
    "sg:orig_category":"Peluqueros: De Se\u00d1oras",
    "sg:phone":"+34 971 71 51 53",
    "sg:postcode":"07001",
    "sg:province":"Islas Baleares",
    "wof:name":"Gracia Adrover Maria De Los Desamparados",
    "wof:placetype":"venue"
},
  "geometry": {"coordinates":[2.6484210491,39.5717086792],"type":"Point"}
}