{
  "type": "Feature",
  "properties": {
    "iso:country":"ES",
    "sg:address":"Joan Alcover(p I Ca S'hereu), S/n",
    "sg:city":"Son Servera",
    "sg:orig_category":"Ferreter\u00cda (diversos)",
    "sg:phone":"+34 971 81 72 51",
    "sg:postcode":"07550",
    "sg:province":"Islas Baleares",
    "wof:name":"Ferralla Serverina S.l",
    "wof:placetype":"venue"
},
  "geometry": {"coordinates":[3.3610699177,39.6125259399],"type":"Point"}
}