{
  "type": "Feature",
  "properties": {
    "addr:full":"Calle de Hilarion Eslava, 51 Madrid Madrid 28015",
    "addr:housenumber":"51",
    "addr:postcode":"madrid;28015",
    "addr:street":"Calle De Hilarion Eslava",
    "iso:country":"ES",
    "sg:address":"Calle de Hilarion Eslava, 51",
    "sg:city":"Madrid",
    "sg:orig_category":"Notarios",
    "sg:phone":"+34 915 44 60 11",
    "sg:postcode":"28015",
    "sg:province":"Madrid",
    "wof:name":"Baleriola Lucas Gabriel",
    "wof:placetype":"venue"
},
  "geometry": {"coordinates":[-3.7164494991,40.4384689331],"type":"Point"}
}