{
  "type": "Feature",
  "properties": {
    "addr:full":"M Pol Ind Ezkabarte, 16 Arre Navarra 31194",
    "addr:housenumber":"16",
    "addr:postcode":"31194",
    "addr:street":"Ezkabarte",
    "iso:country":"ES",
    "sg:address":"M Pol Ind Ezkabarte, 16",
    "sg:city":"Arre",
    "sg:orig_category":"Trabajos De Aislamiento T\u00c9rmico Y Ac\u00dastico",
    "sg:phone":"+34 948 33 30 68",
    "sg:postcode":"31194",
    "sg:province":"Navarra",
    "sg:website":"www.aislamientosirati.es",
    "wof:name":"Aislamientos Irati S.l.l.",
    "wof:placetype":"venue"
},
  "geometry": {"coordinates":[-1.6094944477,42.8416976929],"type":"Point"}
}