{
  "type": "Feature",
  "properties": {
    "iso:country":"ES",
    "sg:address":"Calle de Sirio, 8",
    "sg:city":"Madrid",
    "sg:classifiers":[
        {
            "category":"Personal",
            "subcategory":"Barber",
            "type":"Services"
        }
    ],
    "sg:phone":"+34 915 04 28 89",
    "sg:postcode":"28007",
    "sg:province":"Madrid",
    "sg:tags":[
        "caballeros",
        "de",
        "peluqueros"
    ],
    "wof:name":"Romero Cano Antonio",
    "wof:placetype":"venue"
},
  "geometry": {"coordinates":[-3.6669390202,40.4071273804],"type":"Point"}
}