{
  "type": "Feature",
  "properties": {
    "iso:country":"ES",
    "sg:address":"Calle de Isaac Albeniz, 36",
    "sg:city":"Gines",
    "sg:orig_category":"Empresas De Carpinter\u00cda Met\u00c1lica",
    "sg:phone":"+34 954 71 74 86",
    "sg:postcode":"41960",
    "sg:province":"Sevilla",
    "wof:name":"Talleres Majuelo S.l.",
    "wof:placetype":"venue"
},
  "geometry": {"coordinates":[-6.0734782219,37.3872528076],"type":"Point"}
}