{
  "type": "Feature",
  "properties": {
    "addr:full":"Plaz Constitucion, S/n Fuensanta Martos Ja\u00e9n 23610",
    "addr:housenumber":"/ n",
    "addr:postcode":"23610",
    "addr:street":"Constitucion S",
    "iso:country":"ES",
    "sg:address":"Plaz Constitucion, S/n",
    "sg:city":"Fuensanta Martos",
    "sg:orig_category":"Administraciones Regionales, Departamentales Y Locales",
    "sg:phone":"+34 953 56 50 00",
    "sg:postcode":"23610",
    "sg:province":"Ja\u00e9n",
    "wof:name":"Ayuntamiento De Fuensanta De Martos",
    "wof:placetype":"venue"
},
  "geometry": {"coordinates":[-3.9662585258,37.7227783203],"type":"Point"}
}