{
  "type": "Feature",
  "properties": {
    "addr:full":"Carr Sueca, S/n Cullera Valencia 46400",
    "addr:housenumber":"s / n",
    "addr:postcode":"46400",
    "addr:street":"Carr Sueca",
    "iso:country":"ES",
    "sg:address":"Carr Sueca, S/n",
    "sg:city":"Cullera",
    "sg:orig_category":"Quincaller\u00cda (al Por Menor)",
    "sg:phone":"+34 961 73 80 81",
    "sg:postcode":"46400",
    "sg:province":"Valencia",
    "wof:name":"Enrique Calabuig Monseny S.l.",
    "wof:placetype":"venue"
},
  "geometry": {"coordinates":[-0.2597639859,39.1683311462],"type":"Point"}
}