{
  "type": "Feature",
  "properties": {
    "iso:country":"ES",
    "sg:address":"Avda Castilla, 1",
    "sg:city":"Villarrobledo",
    "sg:orig_category":"Ropa De Trabajo Y Profesionales (al Por Menor)",
    "sg:phone":"+34 967 14 10 42",
    "sg:postcode":"02600",
    "sg:province":"Albacete",
    "wof:name":"Rotravi S.l.",
    "wof:placetype":"venue"
},
  "geometry": {"coordinates":[-2.5904541016,39.2748794556],"type":"Point"}
}