{
  "type": "Feature",
  "properties": {
    "addr:full":"Calle de Navio, S/n Playa Honda Las Palmas 35509",
    "addr:housenumber":"s / n",
    "addr:postcode":"35509",
    "addr:street":"Calle De Navio",
    "iso:country":"ES",
    "sg:address":"Calle de Navio, S/n",
    "sg:city":"Playa Honda",
    "sg:orig_category":"Farmacias",
    "sg:phone":"+34 928 82 00 83",
    "sg:postcode":"35509",
    "sg:province":"Las Palmas",
    "wof:name":"Parrilla Cabrera Maria Consolacion",
    "wof:placetype":"venue"
},
  "geometry": {"coordinates":[-13.5851287842,28.9573745728],"type":"Point"}
}