{
  "type": "Feature",
  "properties": {
    "iso:country":"ES",
    "sg:address":"Aveni Principal, 0",
    "sg:city":"Barriada San Gines",
    "sg:orig_category":"Grafistas",
    "sg:phone":"+34 968 88 33 18",
    "sg:postcode":"30169",
    "sg:province":"Murcia",
    "wof:name":"Marin Mas Ivan Eloy",
    "wof:placetype":"venue"
},
  "geometry": {"coordinates":[-1.177366972,37.9589958191],"type":"Point"}
}