{
  "type": "Feature",
  "properties": {
    "addr:full":"Casta\u00f1os, 34 Hoyo Ciudad Real 13594",
    "addr:housenumber":"34",
    "addr:postcode":"13594",
    "addr:street":"Castan\u0303Os;Real",
    "iso:country":"ES",
    "sg:address":"Casta\u00f1os, 34",
    "sg:city":"Hoyo",
    "sg:orig_category":"Panader\u00cdas, Panader\u00cdas",
    "sg:phone":"+34 926 46 30 94",
    "sg:postcode":"13594",
    "sg:province":"Ciudad Real",
    "wof:name":"Poyatos Redondo Ramon",
    "wof:placetype":"venue"
},
  "geometry": {"coordinates":[-3.9188330173,38.4098014832],"type":"Point"}
}