{
  "type": "Feature",
  "properties": {
    "addr:full":"B (p I Store), S/n Sevilla Sevilla 41008",
    "addr:housenumber":"s / n",
    "addr:postcode":"41008",
    "iso:country":"ES",
    "sg:address":"B (p I Store), S/n",
    "sg:city":"Sevilla",
    "sg:orig_category":"Pintura, Barniz, Productos Asimilables (fabricaci\u00d3n, Al Por Mayor)",
    "sg:phone":"+34 954 36 23 60",
    "sg:postcode":"41008",
    "sg:province":"Sevilla",
    "wof:name":"Color Y Pintura 2000 S.l.",
    "wof:placetype":"venue"
},
  "geometry": {"coordinates":[-5.955532074,37.3946418762],"type":"Point"}
}