{
  "type": "Feature",
  "properties": {
    "addr:full":"Hervillas, 1 Hervillas Pontevedra 36316",
    "addr:housenumber":"1",
    "addr:postcode":"36316",
    "addr:street":"Hervillas",
    "iso:country":"ES",
    "sg:address":"Hervillas, 1",
    "sg:city":"Hervillas",
    "sg:orig_category":"Caf\u00c9s, Bares, Cervecer\u00cdas",
    "sg:phone":"+34 986 46 92 68",
    "sg:postcode":"36316",
    "sg:province":"Pontevedra",
    "wof:name":"Figueroa Martinez Aroa",
    "wof:placetype":"venue"
},
  "geometry": {"coordinates":[-8.7297039032,42.1394195557],"type":"Point"}
}