{
  "type": "Feature",
  "properties": {
    "iso:country":"ES",
    "sg:address":"Calle de Marques De Monteagudo, 21",
    "sg:city":"Madrid",
    "sg:orig_category":"Panader\u00cdas, Panader\u00cdas",
    "sg:phone":"+34 913 55 74 01",
    "sg:postcode":"28028",
    "sg:province":"Madrid",
    "wof:name":"La Tahona De Albasanz S.l.",
    "wof:placetype":"venue"
},
  "geometry": {"coordinates":[-3.6685395241,40.4372291565],"type":"Point"}
}