{
  "type": "Feature",
  "properties": {
    "iso:country":"ES",
    "sg:address":"Calle de Fray Luis De Granada, 39",
    "sg:city":"Salamanca",
    "sg:orig_category":"Transportes De Animales Vivos",
    "sg:phone":"+34 923 22 24 58",
    "sg:postcode":"37007",
    "sg:province":"Salamanca",
    "wof:name":"Pe\u00f1a Diaz Joaquin",
    "wof:placetype":"venue"
},
  "geometry": {"coordinates":[-5.6677808762,40.9719467163],"type":"Point"}
}