{
  "type": "Feature",
  "properties": {
    "iso:country":"ES",
    "sg:address":"Estafeta, 7",
    "sg:city":"Iru\u00f1a",
    "sg:orig_category":"Cester\u00cda (fabricaci\u00d3n)",
    "sg:phone":"+34 948 21 25 13",
    "sg:postcode":"31001",
    "sg:province":"Navarra",
    "wof:name":"Latasa Unzue Maria Teresa Y Latasa Unzue Isabel S.i.",
    "wof:placetype":"venue"
},
  "geometry": {"coordinates":[-1.6426359415,42.8183021545],"type":"Point"}
}