{
  "type": "Feature",
  "properties": {
    "addr:full":"Rava Dins, 14 Sabadell Barcelona 08202",
    "addr:housenumber":"14",
    "addr:postcode":"08202",
    "addr:street":"Dins",
    "iso:country":"ES",
    "sg:address":"Rava Dins, 14",
    "sg:city":"Sabadell",
    "sg:orig_category":"Fabricaci\u00d3n, Importaci\u00d3n De L\u00c1mparas Y Bombillas",
    "sg:phone":"+34 937 25 27 11",
    "sg:postcode":"08202",
    "sg:province":"Barcelona",
    "wof:name":"Torras Duran Francesc",
    "wof:placetype":"venue"
},
  "geometry": {"coordinates":[2.125674963,41.5481300354],"type":"Point"}
}