{
  "type": "Feature",
  "properties": {
    "iso:country":"ES",
    "sg:address":"Rbla Llibertat, 5",
    "sg:city":"Girona",
    "sg:orig_category":"Confecci\u00d3n De Trajes Para Se\u00d1oras",
    "sg:phone":"+34 972 20 09 35",
    "sg:postcode":"17004",
    "sg:province":"Girona",
    "wof:name":"Maria Riera Scp",
    "wof:placetype":"venue"
},
  "geometry": {"coordinates":[2.8238689899,41.9836616516],"type":"Point"}
}