{
  "type": "Feature",
  "properties": {
    "iso:country":"ES",
    "sg:address":"Carrer de Creu Roja, 15",
    "sg:city":"Mataro",
    "sg:orig_category":"Electricidad (montaje, Ensamblaje De Componentes)",
    "sg:phone":"+34 937 57 81 24",
    "sg:postcode":"08304",
    "sg:province":"Barcelona",
    "wof:name":"Instal.lacions Els Molins S.c.p",
    "wof:placetype":"venue"
},
  "geometry": {"coordinates":[2.4418559074,41.5490455627],"type":"Point"}
}