{
  "type": "Feature",
  "properties": {
    "iso:country":"ES",
    "sg:address":"Calle de Sorbas, 34",
    "sg:city":"Carboneras",
    "sg:orig_category":"Ropa Para Caballeros (al Por Menor)",
    "sg:phone":"+34 950 45 41 08",
    "sg:postcode":"04140",
    "sg:province":"Almer\u00eda",
    "wof:name":"Fabricaman S.l.",
    "wof:placetype":"venue"
},
  "geometry": {"coordinates":[-1.8929220438,36.9981002808],"type":"Point"}
}