{
  "type": "Feature",
  "properties": {
    "iso:country":"ES",
    "sg:address":"Avda Lugo, S/n",
    "sg:city":"Friol",
    "sg:orig_category":"Mec\u00c1nico Del Autom\u00d3vil",
    "sg:phone":"+34 982 37 52 86",
    "sg:postcode":"27220",
    "sg:province":"Lugo",
    "wof:name":"Martinez Vi\u00f1a Manuel",
    "wof:placetype":"venue"
},
  "geometry": {"coordinates":[-7.7915987968,43.0296554565],"type":"Point"}
}