{
  "type": "Feature",
  "properties": {
    "iso:country":"ES",
    "sg:address":"Calle de San Juan Bosco, 1",
    "sg:city":"Paiporta",
    "sg:orig_category":"Puertas Y Portales",
    "sg:phone":"+34 963 97 48 54",
    "sg:postcode":"46200",
    "sg:province":"Valencia",
    "wof:name":"Puertas Metalicas Alton S.l.",
    "wof:placetype":"venue"
},
  "geometry": {"coordinates":[-0.4165320098,39.4315643311],"type":"Point"}
}