{
  "type": "Feature",
  "properties": {
    "addr:full":"Calle de Zagal, 6 Baza Granada 18800",
    "addr:housenumber":"6",
    "addr:postcode":"18800",
    "addr:street":"Calle De Zagal",
    "iso:country":"ES",
    "sg:address":"Calle de Zagal, 6",
    "sg:city":"Baza",
    "sg:orig_category":"Art\u00cdculos Funerarios (al Por Menor)",
    "sg:phone":"+34 958 70 33 33",
    "sg:postcode":"18800",
    "sg:province":"Granada",
    "wof:name":"Sociedad Cooperativa Andaluza De Trabajo Asociado De Ambulancias Sierra Nevada",
    "wof:placetype":"venue"
},
  "geometry": {"coordinates":[-2.7704091072,37.4930038452],"type":"Point"}
}