{
  "type": "Feature",
  "properties": {
    "iso:country":"ES",
    "sg:address":"Calle de Pedro Velasco, 6",
    "sg:city":"Vitigudino",
    "sg:orig_category":"Notarios",
    "sg:phone":"+34 923 50 01 49",
    "sg:postcode":"37210",
    "sg:province":"Salamanca",
    "wof:name":"Rodriguez Rios Maria Del Pilar",
    "wof:placetype":"venue"
},
  "geometry": {"coordinates":[-6.4347472191,41.0086936951],"type":"Point"}
}