{
  "type": "Feature",
  "properties": {
    "iso:country":"ES",
    "sg:address":"Calle de Jupiter, 115",
    "sg:city":"Valdemoro",
    "sg:orig_category":"Cervecer\u00cdas",
    "sg:phone":"+34 918 95 03 66",
    "sg:postcode":"28340",
    "sg:province":"Madrid",
    "wof:name":"Hernandez Portero Amelia",
    "wof:placetype":"venue"
},
  "geometry": {"coordinates":[-3.6824851036,40.1786804199],"type":"Point"}
}