{
  "type": "Feature",
  "properties": {
    "addr:full":"Pase Ruise\u00d1ores, 45 Zaragoza Zaragoza 50006",
    "addr:housenumber":"45",
    "addr:postcode":"50006",
    "addr:street":"Ruisen\u0303Ores",
    "iso:country":"ES",
    "sg:address":"Pase Ruise\u00d1ores, 45",
    "sg:city":"Zaragoza",
    "sg:orig_category":"Arquitectos",
    "sg:phone":"+34 976 27 40 73",
    "sg:postcode":"50006",
    "sg:province":"Zaragoza",
    "wof:name":"Urraca Pi\u00f1eiro Carlos",
    "wof:placetype":"venue"
},
  "geometry": {"coordinates":[-0.8897160292,41.6356697083],"type":"Point"}
}