{
  "type": "Feature",
  "properties": {
    "iso:country":"ES",
    "sg:address":"Calle de Camino Real, 27",
    "sg:city":"Cartes",
    "sg:orig_category":"Centros De Educaci\u00d3n Especial",
    "sg:phone":"+34 942 81 93 82",
    "sg:postcode":"39311",
    "sg:province":"Cantabria",
    "wof:name":"Colegio Publico Comarcal De Cartes",
    "wof:placetype":"venue"
},
  "geometry": {"coordinates":[-4.0684566498,43.3277931213],"type":"Point"}
}