{
  "type": "Feature",
  "properties": {
    "addr:full":"Ptge Masor, S/n Sant Feliu Llobregat Barcelona 08980",
    "addr:housenumber":"s",
    "addr:postcode":"08980",
    "addr:street":"Ptge Masor;/ N",
    "iso:country":"ES",
    "sg:address":"Ptge Masor, S/n",
    "sg:city":"Sant Feliu Llobregat",
    "sg:orig_category":"Instalaci\u00d3n, Preparaci\u00d3n De Exposiciones, Ferias, Salones",
    "sg:phone":"+34 936 85 44 89",
    "sg:postcode":"08980",
    "sg:province":"Barcelona",
    "wof:name":"Plastics Roser S.l.",
    "wof:placetype":"venue"
},
  "geometry": {"coordinates":[2.0486500263,41.3884811401],"type":"Point"}
}