{
  "type": "Feature",
  "properties": {
    "addr:full":"Pg Verdum, 24 Barcelona Barcelona 08016",
    "addr:housenumber":"24",
    "addr:postcode":"08016",
    "addr:street":"Pg Verdum",
    "iso:country":"ES",
    "sg:address":"Pg Verdum, 24",
    "sg:city":"Barcelona",
    "sg:orig_category":"Confiter\u00cdas, Chocolater\u00cdas (al Por Menor)",
    "sg:phone":"+34 933 54 67 83",
    "sg:postcode":"08016",
    "sg:province":"Barcelona",
    "wof:name":"Maza Ruiz Jose Maria",
    "wof:placetype":"venue"
},
  "geometry": {"coordinates":[2.1741080284,41.4374694824],"type":"Point"}
}