{
  "type": "Feature",
  "properties": {
    "iso:country":"ES",
    "sg:address":"Calle de Republica Dominicana, S/n",
    "sg:city":"Lastrilla",
    "sg:orig_category":"Empresas De Operaciones Portuarias Y Elevaci\u00d3n De Mercanc\u00cdas",
    "sg:phone":"+34 921 42 41 08",
    "sg:postcode":"40196",
    "sg:province":"Segovia",
    "wof:name":"Apadefim 2000 S.l.u.",
    "wof:placetype":"venue"
},
  "geometry": {"coordinates":[-4.0933494568,40.9643669128],"type":"Point"}
}