{
  "type": "Feature",
  "properties": {
    "addr:full":"Carrer de Galvani, 86 Terrassa Barcelona 08224",
    "addr:housenumber":"86",
    "addr:postcode":"08224",
    "addr:street":"Carrer De Galvani",
    "iso:country":"ES",
    "sg:address":"Carrer de Galvani, 86",
    "sg:city":"Terrassa",
    "sg:orig_category":"Asociaciones, Organismos Culturales Y Socioeducativos",
    "sg:phone":"+34 937 88 90 88",
    "sg:postcode":"08224",
    "sg:province":"Barcelona",
    "wof:name":"Sociedad Colombofila M. Egarense",
    "wof:placetype":"venue"
},
  "geometry": {"coordinates":[2.0026979446,41.5589637756],"type":"Point"}
}