{
  "type": "Feature",
  "properties": {
    "iso:country":"ES",
    "sg:address":"Avda Estacion, 63",
    "sg:city":"Torrijos",
    "sg:orig_category":"Alimentaci\u00d3n General (al Por Menor)",
    "sg:phone":"+34 925 77 14 99",
    "sg:postcode":"45500",
    "sg:province":"Toledo",
    "wof:name":"Jarillo Mu\u00f1oz Maria De Los Angeles",
    "wof:placetype":"venue"
},
  "geometry": {"coordinates":[-4.2824549675,39.9808998108],"type":"Point"}
}