{
  "type": "Feature",
  "properties": {
    "addr:full":"Grup Massarrojos (urbanizacion), 8 Masarrochos Valencia 46112",
    "addr:housenumber":"8",
    "addr:postcode":"46112",
    "addr:street":"Urbanizacion",
    "iso:country":"ES",
    "sg:address":"Grup Massarrojos (urbanizacion), 8",
    "sg:city":"Masarrochos",
    "sg:orig_category":"Producci\u00d3n De Cart\u00d3n",
    "sg:phone":"+34 961 31 15 39",
    "sg:postcode":"46112",
    "sg:province":"Valencia",
    "wof:name":"Reno De Medici Iberica S.l.",
    "wof:placetype":"venue"
},
  "geometry": {"coordinates":[-0.4119290113,39.5453643799],"type":"Point"}
}