{
  "type": "Feature",
  "properties": {
    "iso:country":"ES",
    "sg:address":"Calle de Escultor Rivera, 24",
    "sg:city":"Ba\u00d1eza",
    "sg:orig_category":"Ingeniero",
    "sg:phone":"+34 987 64 31 02",
    "sg:postcode":"24750",
    "sg:province":"Le\u00f3n",
    "wof:name":"Telecomunicaciones Los Ocho Ca\u00f1os S.l.",
    "wof:placetype":"venue"
},
  "geometry": {"coordinates":[-5.9242091179,42.3069114685],"type":"Point"}
}