{
  "type": "Feature",
  "properties": {
    "iso:country":"ES",
    "sg:address":"Carrer de Arc, 5",
    "sg:city":"S. Just Desvern",
    "sg:orig_category":"Ingenier\u00cda, Centros De Estudios (diversos)",
    "sg:phone":"+34 933 71 95 64",
    "sg:postcode":"08960",
    "sg:province":"Barcelona",
    "wof:name":"Quinto Bernal Rafael",
    "wof:placetype":"venue"
},
  "geometry": {"coordinates":[2.0782968998,41.3869590759],"type":"Point"}
}