{
  "type": "Feature",
  "properties": {
    "iso:country":"ES",
    "sg:address":"Calle de Florida, 26",
    "sg:city":"Ontur",
    "sg:orig_category":"Estancos",
    "sg:phone":"+34 967 32 42 82",
    "sg:postcode":"02652",
    "sg:province":"Albacete",
    "wof:name":"Miralles Mu\u00f1oz Carmen",
    "wof:placetype":"venue"
},
  "geometry": {"coordinates":[-1.4988180399,38.6157455444],"type":"Point"}
}