{
  "type": "Feature",
  "properties": {
    "addr:full":"M. Central, 277 Tarragona Tarragona 43001",
    "addr:housenumber":"277",
    "addr:postcode":"43001",
    "iso:country":"ES",
    "sg:address":"M. Central, 277",
    "sg:city":"Tarragona",
    "sg:orig_category":"Pescader\u00cdas (al Por Menor)",
    "sg:phone":"+34 977 23 66 54",
    "sg:postcode":"43001",
    "sg:province":"Tarragona",
    "wof:name":"Belchi Nolla Rosa",
    "wof:placetype":"venue"
},
  "geometry": {"coordinates":[1.2541049719,41.1169281006],"type":"Point"}
}