{
  "type": "Feature",
  "properties": {
    "addr:full":"Cno Vjo P Estrecho(barreros), 106 Cartagena Murcia 30310",
    "addr:housenumber":"106",
    "addr:postcode":"30310",
    "addr:street":"Cno Vjo P Estrecho Barreros",
    "iso:country":"ES",
    "sg:address":"Cno Vjo P Estrecho(barreros), 106",
    "sg:city":"Cartagena",
    "sg:orig_category":"Arquitectos",
    "sg:phone":"+34 968 51 59 13",
    "sg:postcode":"30310",
    "sg:province":"Murcia",
    "wof:name":"Chacon Gomez Juan Ignacio",
    "wof:placetype":"venue"
},
  "geometry": {"coordinates":[-1.0000170469,37.6280097961],"type":"Point"}
}