{
  "type": "Feature",
  "properties": {
    "addr:full":"Calle de Cipres, 2 Arganda Madrid 28500",
    "addr:housenumber":"2",
    "addr:postcode":"28500",
    "addr:street":"Calle De Cipres",
    "iso:country":"ES",
    "sg:address":"Calle de Cipres, 2",
    "sg:city":"Arganda",
    "sg:orig_category":"Tapicer\u00cdas",
    "sg:phone":"+34 918 70 19 95",
    "sg:postcode":"28500",
    "sg:province":"Madrid",
    "wof:name":"Martinez Gonzalez Jose",
    "wof:placetype":"venue"
},
  "geometry": {"coordinates":[-3.4628520012,40.313495636],"type":"Point"}
}