{
  "type": "Feature",
  "properties": {
    "addr:full":"Avda Coru\u00d1a (da), 54 Lugo Lugo 27003",
    "addr:housenumber":"54",
    "addr:postcode":"27003",
    "addr:street":"Avda Corun\u0303A Da",
    "iso:country":"ES",
    "sg:address":"Avda Coru\u00d1a (da), 54",
    "sg:city":"Lugo",
    "sg:orig_category":"Sociedades, Compa\u00d1\u00cdas Aseguradoras",
    "sg:phone":"+34 982 60 08 92",
    "sg:postcode":"27003",
    "sg:province":"Lugo",
    "wof:name":"Villamor Trashorras Y Asociados S.l.",
    "wof:placetype":"venue"
},
  "geometry": {"coordinates":[-7.5594549179,43.0161323547],"type":"Point"}
}