{
  "type": "Feature",
  "properties": {
    "addr:full":"Calle de San Juanillo, 1 Palencia Palencia 34003",
    "addr:housenumber":"1",
    "addr:postcode":"34003",
    "addr:street":"Calle De San Juanillo",
    "iso:country":"ES",
    "sg:address":"Calle de San Juanillo, 1",
    "sg:city":"Palencia",
    "sg:orig_category":"Empresas De Carpinter\u00cda De Madera",
    "sg:phone":"+34 979 70 18 37",
    "sg:postcode":"34003",
    "sg:province":"Palencia",
    "wof:name":"Pastor Zapatero Jose Luis",
    "wof:placetype":"venue"
},
  "geometry": {"coordinates":[-4.5273132324,42.0164146423],"type":"Point"}
}