{
  "type": "Feature",
  "properties": {
    "iso:country":"ES",
    "sg:address":"Calle de Carrera De La Virgen, 52",
    "sg:city":"Andujar",
    "sg:orig_category":"M\u00c1rmoles, Granitos Y Piedras Naturales",
    "sg:phone":"+34 953 50 24 56",
    "sg:postcode":"23740",
    "sg:province":"Ja\u00e9n",
    "wof:name":"Molina Delgado Florencio",
    "wof:placetype":"venue"
},
  "geometry": {"coordinates":[-4.0286779404,38.2897567749],"type":"Point"}
}