{
  "type": "Feature",
  "properties": {
    "addr:full":"Carr Vallcalent, 31 Lleida Lleida 25006",
    "addr:housenumber":"31",
    "addr:postcode":"25006",
    "addr:street":"Carr Vallcalent",
    "iso:country":"ES",
    "sg:address":"Carr Vallcalent, 31",
    "sg:city":"Lleida",
    "sg:orig_category":"Material Y Suministros Para Peluquer\u00cda",
    "sg:phone":"+34 973 26 97 71",
    "sg:postcode":"25006",
    "sg:province":"Lleida",
    "wof:name":"Magatzem Del Perruquer S.l.",
    "wof:placetype":"venue"
},
  "geometry": {"coordinates":[0.6184880137,41.6172294617],"type":"Point"}
}