{
  "type": "Feature",
  "properties": {
    "addr:full":"Calle de Catalu\u00d1a, 63 Pto. Rosario Las Palmas 35600",
    "addr:housenumber":"63",
    "addr:postcode":"35600",
    "addr:street":"Calle De Catalun\u0303A;Pto. Rosario Las",
    "iso:country":"ES",
    "sg:address":"Calle de Catalu\u00d1a, 63",
    "sg:city":"Pto. Rosario",
    "sg:orig_category":"Guarder\u00cdas",
    "sg:phone":"+34 928 53 23 76",
    "sg:postcode":"35600",
    "sg:province":"Las Palmas",
    "wof:name":"Rodriguez Umpierrez Soraya",
    "wof:placetype":"venue"
},
  "geometry": {"coordinates":[-13.8723011017,28.5051136017],"type":"Point"}
}