{
  "type": "Feature",
  "properties": {
    "addr:full":"Plaz Lauaxeta, 10 Bilbao Vizcaya 48004",
    "addr:housenumber":"10",
    "addr:postcode":"48004",
    "addr:street":"Lauaxeta",
    "iso:country":"ES",
    "sg:address":"Plaz Lauaxeta, 10",
    "sg:city":"Bilbao",
    "sg:orig_category":"Promotores Constructores",
    "sg:phone":"+34 944 73 43 44",
    "sg:postcode":"48004",
    "sg:province":"Vizcaya",
    "wof:name":"Txurdinaga Reformas S.l.",
    "wof:placetype":"venue"
},
  "geometry": {"coordinates":[-2.9095129967,43.2506980896],"type":"Point"}
}