{
  "type": "Feature",
  "properties": {
    "iso:country":"ES",
    "sg:address":"Calle de Castillo, 77",
    "sg:city":"Hornachuelos",
    "sg:orig_category":"Ropa Para Ni\u00d1os (al Por Menor)",
    "sg:phone":"+34 957 64 07 43",
    "sg:postcode":"14740",
    "sg:province":"C\u00f3rdoba",
    "wof:name":"Lopez Adames Maria Dolores",
    "wof:placetype":"venue"
},
  "geometry": {"coordinates":[-5.2455887794,37.8335037231],"type":"Point"}
}