{
  "type": "Feature",
  "properties": {
    "iso:country":"ES",
    "sg:address":"Avda Doctor Peset Aleixandre, 100",
    "sg:city":"Valencia",
    "sg:orig_category":"Ropa De Casa (fabricaci\u00d3n, Al Por Mayor)",
    "sg:phone":"+34 963 27 20 22",
    "sg:postcode":"46025",
    "sg:province":"Valencia",
    "wof:name":"Puertes Gomis Rosa",
    "wof:placetype":"venue"
},
  "geometry": {"coordinates":[-0.3835749924,39.4901161194],"type":"Point"}
}