{
  "type": "Feature",
  "properties": {
    "iso:country":"ES",
    "sg:address":"Pl Caserna, S/n",
    "sg:city":"Granollers",
    "sg:orig_category":"Sales (al Por Mayor)",
    "sg:phone":"+34 938 70 23 65",
    "sg:postcode":"08401",
    "sg:province":"Barcelona",
    "wof:name":"Maltas Ayma Angela",
    "wof:placetype":"venue"
},
  "geometry": {"coordinates":[2.2860100269,41.6089935303],"type":"Point"}
}