{
  "type": "Feature",
  "properties": {
    "addr:full":"Calle de Sipiri, 14 Moreaga Vizcaya 48600",
    "addr:housenumber":"14",
    "addr:postcode":"48600",
    "addr:street":"Calle De Sipiri",
    "iso:country":"ES",
    "sg:address":"Calle de Sipiri, 14",
    "sg:city":"Moreaga",
    "sg:orig_category":"Caf\u00c9s, Bares, Cervecer\u00cdas",
    "sg:phone":"+34 946 76 68 12",
    "sg:postcode":"48600",
    "sg:province":"Vizcaya",
    "wof:name":"Hijubamar S.l.",
    "wof:placetype":"venue"
},
  "geometry": {"coordinates":[-2.9829580784,43.3818130493],"type":"Point"}
}