{
  "type": "Feature",
  "properties": {
    "addr:full":"Calle de Teniente Infante, 4 Madridejos Toledo 45710",
    "addr:housenumber":"4",
    "addr:postcode":"45710",
    "addr:street":"Calle De Teniente Infante",
    "iso:country":"ES",
    "sg:address":"Calle de Teniente Infante, 4",
    "sg:city":"Madridejos",
    "sg:orig_category":"Sociedades, Compa\u00d1\u00cdas Aseguradoras",
    "sg:phone":"+34 925 46 23 48",
    "sg:postcode":"45710",
    "sg:province":"Toledo",
    "wof:name":"Ascuemp Asesores S.l",
    "wof:placetype":"venue"
},
  "geometry": {"coordinates":[-3.5349624157,39.4679794312],"type":"Point"}
}