{
  "type": "Feature",
  "properties": {
    "iso:country":"ES",
    "sg:address":"Calle de Barcelona, 2",
    "sg:city":"Ejido",
    "sg:orig_category":"Ropa Para Ni\u00d1os (al Por Menor)",
    "sg:phone":"+34 950 57 24 77",
    "sg:postcode":"04700",
    "sg:province":"Almer\u00eda",
    "wof:name":"Sanchez Reche Teresa",
    "wof:placetype":"venue"
},
  "geometry": {"coordinates":[-2.8127346039,36.775100708],"type":"Point"}
}