{
  "type": "Feature",
  "properties": {
    "addr:full":"Calle de Foncalada, 21 Oviedo Asturias 33002",
    "addr:housenumber":"21",
    "addr:postcode":"33002",
    "addr:street":"Calle De Foncalada",
    "iso:country":"ES",
    "sg:address":"Calle de Foncalada, 21",
    "sg:city":"Oviedo",
    "sg:orig_category":"Detectives, Agentes Investigadores Privados",
    "sg:phone":"+34 985 20 78 64",
    "sg:postcode":"33002",
    "sg:province":"Asturias",
    "wof:name":"Sys Norte S.l.",
    "wof:placetype":"venue"
},
  "geometry": {"coordinates":[-5.8462338448,43.366153717],"type":"Point"}
}