{
  "type": "Feature",
  "properties": {
    "iso:country":"ES",
    "sg:address":"Calle de Organista Plasencia, 20",
    "sg:city":"Valencia",
    "sg:orig_category":"Traductores",
    "sg:phone":"+34 963 34 05 21",
    "sg:postcode":"46006",
    "sg:province":"Valencia",
    "wof:name":"Cubel Aroca Mariano",
    "wof:placetype":"venue"
},
  "geometry": {"coordinates":[-0.3707979918,39.4584007263],"type":"Point"}
}