{
  "type": "Feature",
  "properties": {
    "addr:full":"Carrer de 31 De Desembre, 29 Palma Islas Baleares 07003",
    "addr:housenumber":"31;29",
    "addr:postcode":"07003",
    "addr:street":"Carrer De;Desembre",
    "iso:country":"ES",
    "sg:address":"Carrer de 31 De Desembre, 29",
    "sg:city":"Palma",
    "sg:orig_category":"Molduras, Junquillos, Listones Y Molduras Perforadas",
    "sg:phone":"+34 971 29 00 05",
    "sg:postcode":"07003",
    "sg:province":"Islas Baleares",
    "wof:name":"Bar Mavi S.l.",
    "wof:placetype":"venue"
},
  "geometry": {"coordinates":[2.6522068977,39.5804595947],"type":"Point"}
}