{
  "type": "Feature",
  "properties": {
    "addr:full":"Calle de Estrella, 5 Sevilla Sevilla 41004",
    "addr:housenumber":"5",
    "addr:postcode":"41004",
    "addr:street":"Calle De Estrella",
    "iso:country":"ES",
    "sg:address":"Calle de Estrella, 5",
    "sg:city":"Sevilla",
    "sg:orig_category":"Edici\u00d3n De Diarios, Revistas, Boletines",
    "sg:phone":"+34 954 22 79 64",
    "sg:postcode":"41004",
    "sg:province":"Sevilla",
    "wof:name":"Indice Sur S.l.",
    "wof:placetype":"venue"
},
  "geometry": {"coordinates":[-5.9914689064,37.3881874084],"type":"Point"}
}