{
  "type": "Feature",
  "properties": {
    "iso:country":"ES",
    "sg:address":"Carrer de Sant Bartomeu, 128",
    "sg:city":"Campello",
    "sg:orig_category":"Ense\u00d1anza: Idiomas",
    "sg:phone":"+34 965 63 55 16",
    "sg:postcode":"03560",
    "sg:province":"Alicante",
    "wof:name":"Lexis English Centre S.l.",
    "wof:placetype":"venue"
},
  "geometry": {"coordinates":[-0.3894889951,38.4294204712],"type":"Point"}
}