{
  "type": "Feature",
  "properties": {
    "addr:full":"Calle de San Vicente, 32 Sevilla Sevilla 41002",
    "addr:housenumber":"32",
    "addr:postcode":"41002",
    "addr:street":"Calle De San Vicente",
    "iso:country":"ES",
    "sg:address":"Calle de San Vicente, 32",
    "sg:city":"Sevilla",
    "sg:orig_category":"Abogados",
    "sg:phone":"+34 954 90 34 40",
    "sg:postcode":"41002",
    "sg:province":"Sevilla",
    "wof:name":"Garcia Gonzalez Mateo",
    "wof:placetype":"venue"
},
  "geometry": {"coordinates":[-5.9994368553,37.3940925598],"type":"Point"}
}