{
  "type": "Feature",
  "properties": {
    "iso:country":"ES",
    "sg:address":"Calle de Ferrerets, 16",
    "sg:city":"Alcora",
    "sg:orig_category":"Loter\u00cda Y T\u00d3mbola",
    "sg:phone":"+34 964 36 08 56",
    "sg:postcode":"12110",
    "sg:province":"Castell\u00f3n",
    "wof:name":"Sanz Albero Vicenta",
    "wof:placetype":"venue"
},
  "geometry": {"coordinates":[-0.2133419961,40.0771827698],"type":"Point"}
}