{
  "type": "Feature",
  "properties": {
    "addr:full":"C/ Lepant, 1 Manacor Islas Baleares 07500",
    "addr:housenumber":"1",
    "addr:postcode":"07500",
    "addr:street":"C / Lepant",
    "iso:country":"ES",
    "sg:address":"C/ Lepant, 1",
    "sg:city":"Manacor",
    "sg:orig_category":"Empresas De Carpinter\u00cda De Madera",
    "sg:phone":"+34 971 55 27 58",
    "sg:postcode":"07500",
    "sg:province":"Islas Baleares",
    "wof:name":"Ramis Galmes Juan",
    "wof:placetype":"venue"
},
  "geometry": {"coordinates":[3.2036089897,39.5684089661],"type":"Point"}
}