{
  "type": "Feature",
  "properties": {
    "iso:country":"ES",
    "sg:address":"R. Oliva, 98",
    "sg:city":"Malaga",
    "sg:orig_category":"\u00d3ptica: Instrumentos (fabricaci\u00d3n)",
    "sg:phone":"+34 952 23 14 75",
    "sg:postcode":"29004",
    "sg:province":"M\u00e1laga",
    "wof:name":"Fernandez Cano Daniel",
    "wof:placetype":"venue"
},
  "geometry": {"coordinates":[-4.4634490013,36.6657905579],"type":"Point"}
}