{
  "type": "Feature",
  "properties": {
    "addr:full":"Avda America, 54 Ingenio Las Palmas 35250",
    "addr:housenumber":"54",
    "addr:postcode":"35250",
    "addr:street":"Avda America",
    "iso:country":"ES",
    "sg:address":"Avda America, 54",
    "sg:city":"Ingenio",
    "sg:orig_category":"Ropa Para Caballeros (al Por Menor)",
    "sg:phone":"+34 928 78 30 23",
    "sg:postcode":"35250",
    "sg:province":"Las Palmas",
    "wof:name":"Espino Castro Maria Jose",
    "wof:placetype":"venue"
},
  "geometry": {"coordinates":[-15.4416055679,27.9178752899],"type":"Point"}
}