{
  "type": "Feature",
  "properties": {
    "addr:full":"C. Sta. Barbara, S/n Alacant Alicante 03013",
    "addr:housenumber":"/ n",
    "addr:postcode":"03013",
    "addr:street":"C. Sta. Barbara S",
    "iso:country":"ES",
    "sg:address":"C. Sta. Barbara, S/n",
    "sg:city":"Alacant",
    "sg:orig_category":"Arte, Cultura, Edici\u00d3n",
    "sg:phone":"+34 965 26 31 31",
    "sg:postcode":"03013",
    "sg:province":"Alicante",
    "sg:website":"www.fundacioncapa.net",
    "wof:name":"Patronato Municipal De La Cultura D'alacant",
    "wof:placetype":"venue"
},
  "geometry": {"coordinates":[-0.4854539931,38.3449783325],"type":"Point"}
}