{
  "type": "Feature",
  "properties": {
    "addr:full":"Calle de Norte-pinsoro, 1 Pinsoro Zaragoza 50694",
    "addr:housenumber":"1",
    "addr:postcode":"50694",
    "addr:street":"Calle De Norte-Pinsoro",
    "iso:country":"ES",
    "sg:address":"Calle de Norte-pinsoro, 1",
    "sg:city":"Pinsoro",
    "sg:orig_category":"Aparatos E Instalaci\u00d3n De Regad\u00cdos",
    "sg:phone":"+34 976 67 38 00",
    "sg:postcode":"50694",
    "sg:province":"Zaragoza",
    "wof:name":"Comunidad De Regantes Num-5",
    "wof:placetype":"venue"
},
  "geometry": {"coordinates":[-1.3374090195,42.1968612671],"type":"Point"}
}