{
  "type": "Feature",
  "properties": {
    "addr:full":"Av De El Romeral (p I Antequera), 13 Antequera M\u00e1laga 29200",
    "addr:housenumber":"13",
    "addr:postcode":"29200",
    "addr:street":"Av De El;Antequera",
    "iso:country":"ES",
    "sg:address":"Av De El Romeral (p I Antequera), 13",
    "sg:city":"Antequera",
    "sg:orig_category":"Agentes, Concesionarios Y Sucursales De Veh\u00cdculos",
    "sg:phone":"+34 952 70 36 33",
    "sg:postcode":"29200",
    "sg:province":"M\u00e1laga",
    "wof:name":"Automoviles Torcal S.l.",
    "wof:placetype":"venue"
},
  "geometry": {"coordinates":[-4.536049366,37.2492408752],"type":"Point"}
}