{
  "type": "Feature",
  "properties": {
    "iso:country":"ES",
    "sg:address":"Avda Zamora, 5",
    "sg:city":"Pego",
    "sg:orig_category":"Fabricaci\u00d3n Y Venta De Volquetes Y Remolques",
    "sg:phone":"+34 980 60 62 31",
    "sg:postcode":"49154",
    "sg:province":"Zamora",
    "wof:name":"Martin De San Jose Anibal",
    "wof:placetype":"venue"
},
  "geometry": {"coordinates":[-5.4682130814,41.3349914551],"type":"Point"}
}