{
  "type": "Feature",
  "properties": {
    "iso:country":"ES",
    "sg:address":"Calle de San Claudio, 5",
    "sg:city":"Le\u00f3n",
    "sg:classifiers":[
        {
            "category":"Cinema",
            "subcategory":"Movie Theater",
            "type":"Entertainment"
        }
    ],
    "sg:phone":"+34 987 21 40 22",
    "sg:postcode":"24004",
    "sg:province":"Le\u00f3n",
    "sg:tags":[
        "salas",
        "de",
        "cine"
    ],
    "wof:name":"Van Gogh Cines S. L.",
    "wof:placetype":"venue"
},
  "geometry": {"coordinates":[-5.5734820366,42.5916633606],"type":"Point"}
}