{
  "type": "Feature",
  "properties": {
    "addr:full":"Calle de Carretera De Gandia, 18 Villalonga Valencia 46720",
    "addr:housenumber":"18",
    "addr:postcode":"46720",
    "addr:street":"Calle De Carretera De Gandia",
    "iso:country":"ES",
    "sg:address":"Calle de Carretera De Gandia, 18",
    "sg:city":"Villalonga",
    "sg:orig_category":"Cooperativas Agr\u00cdcolas",
    "sg:phone":"+34 962 95 80 32",
    "sg:postcode":"46720",
    "sg:province":"Valencia",
    "wof:name":"Cooperativa Agricola Y Caja Rural Nuestra Se\u00d1ora De La Fuente",
    "wof:placetype":"venue"
},
  "geometry": {"coordinates":[-0.2090269029,38.8869934082],"type":"Point"}
}