{
  "type": "Feature",
  "properties": {
    "addr:full":"Calle de Trigo (del), 1 Leganes Madrid 28914",
    "addr:housenumber":"1",
    "addr:postcode":"28914",
    "addr:street":"Calle De Trigo Del",
    "iso:country":"ES",
    "sg:address":"Calle de Trigo (del), 1",
    "sg:city":"Leganes",
    "sg:orig_category":"Materias Pl\u00c1sticas: Productos De Consumo Masivo (fabricaci\u00d3n, Al Por Mayor)",
    "sg:phone":"+34 916 93 26 63",
    "sg:postcode":"28914",
    "sg:province":"Madrid",
    "wof:name":"Embalajes Plastivent S.l.",
    "wof:placetype":"venue"
},
  "geometry": {"coordinates":[-3.7788369656,40.3266792297],"type":"Point"}
}