{
  "type": "Feature",
  "properties": {
    "addr:full":"Calle de Hernani, 1 Donostia-san Sebastian Guip\u00f9zcoa 20004",
    "addr:housenumber":"1",
    "addr:postcode":"20004",
    "addr:street":"Calle De Hernani",
    "iso:country":"ES",
    "sg:address":"Calle de Hernani, 1",
    "sg:city":"Donostia-san Sebastian",
    "sg:orig_category":"Agencias De Viajes",
    "sg:phone":"+34 943 42 20 88",
    "sg:postcode":"20004",
    "sg:province":"Guip\u00f9zcoa",
    "sg:website":"www.marsans.es",
    "wof:name":"Viajes Marsans S.a.",
    "wof:placetype":"venue"
},
  "geometry": {"coordinates":[-1.9848719835,43.3214645386],"type":"Point"}
}