{
  "type": "Feature",
  "properties": {
    "iso:country":"ES",
    "sg:address":"Calle de Doctor Sumsi, 48",
    "sg:city":"Valencia",
    "sg:orig_category":"Ingeniero",
    "sg:phone":"+34 963 73 05 69",
    "sg:postcode":"46005",
    "sg:province":"Valencia",
    "wof:name":"Gilabert Selfa Vicente",
    "wof:placetype":"venue"
},
  "geometry": {"coordinates":[-0.3676980138,39.4608154297],"type":"Point"}
}