{
  "type": "Feature",
  "properties": {
    "iso:country":"ES",
    "sg:address":"Carr Nord, 5",
    "sg:city":"Selva",
    "sg:orig_category":"Construcci\u00d3n Mec\u00c1nica",
    "sg:phone":"+34 972 47 68 25",
    "sg:postcode":"17458",
    "sg:province":"Girona",
    "wof:name":"Construcciones Mecanicas Vela S.l.",
    "wof:placetype":"venue"
},
  "geometry": {"coordinates":[2.8099250793,41.9300727844],"type":"Point"}
}