{
  "type": "Feature",
  "properties": {
    "iso:country":"ES",
    "sg:address":"Calle de Rio Arlanza, 25",
    "sg:city":"Alcala Henares",
    "sg:orig_category":"Plomeros",
    "sg:phone":"+34 918 81 81 73",
    "sg:postcode":"28803",
    "sg:province":"Madrid",
    "wof:name":"Izquierdo Frias Maria Luisa",
    "wof:placetype":"venue"
},
  "geometry": {"coordinates":[-3.3707890511,40.4711112976],"type":"Point"}
}