{
  "type": "Feature",
  "properties": {
    "addr:full":"Carretera De Adanero-gijon, Km. 0111,0 Pola Gordon Le\u00f3n 24600",
    "addr:postcode":"24600",
    "addr:street":"Carretera De Adanero-Gijon Km. 0111,0 Pola;Leo\u0301N",
    "iso:country":"ES",
    "sg:address":"Carretera De Adanero-gijon, Km. 0111,0",
    "sg:city":"Pola Gordon",
    "sg:orig_category":"Piedra Natural",
    "sg:phone":"+34 987 69 81 31",
    "sg:postcode":"24600",
    "sg:province":"Le\u00f3n",
    "wof:name":"Rocalo S.l.",
    "wof:placetype":"venue"
},
  "geometry": {"coordinates":[-5.6685461998,42.8559532166],"type":"Point"}
}