{
  "type": "Feature",
  "properties": {
    "iso:country":"ES",
    "sg:address":"Menendez Pelayo, 25",
    "sg:city":"Malia\u00d1o",
    "sg:orig_category":"Reposter\u00cdas",
    "sg:phone":"+34 942 26 24 10",
    "sg:postcode":"39600",
    "sg:province":"Cantabria",
    "wof:name":"Hornopan S.l.",
    "wof:placetype":"venue"
},
  "geometry": {"coordinates":[-3.8434240818,43.4181861877],"type":"Point"}
}