{
  "type": "Feature",
  "properties": {
    "addr:full":"Avda Miguel De Cervantes, 49 Ecija Sevilla 41400",
    "addr:housenumber":"49",
    "addr:postcode":"41400",
    "addr:street":"Avda Miguel De Cervantes",
    "iso:country":"ES",
    "sg:address":"Avda Miguel De Cervantes, 49",
    "sg:city":"Ecija",
    "sg:orig_category":"Agentes Generales De Seguros",
    "sg:phone":"+34 954 83 40 11",
    "sg:postcode":"41400",
    "sg:province":"Sevilla",
    "wof:name":"Galvez Sotillo Maria De Los Angeles",
    "wof:placetype":"venue"
},
  "geometry": {"coordinates":[-5.0773658752,37.5380516052],"type":"Point"}
}