{
  "type": "Feature",
  "properties": {
    "addr:full":"Carrer de Riera Baste, S/n S. Boi Llobregat Barcelona 08830",
    "addr:housenumber":"s",
    "addr:postcode":"08830",
    "addr:street":"Carrer De Riera Baste;/ N",
    "iso:country":"ES",
    "sg:address":"Carrer de Riera Baste, S/n",
    "sg:city":"S. Boi Llobregat",
    "sg:orig_category":"Carnicer\u00cdas, Carnicer\u00cdas",
    "sg:phone":"+34 936 54 76 55",
    "sg:postcode":"08830",
    "sg:province":"Barcelona",
    "wof:name":"Xurit Carnicers S C P",
    "wof:placetype":"venue"
},
  "geometry": {"coordinates":[2.0339176655,41.345413208],"type":"Point"}
}