{
  "type": "Feature",
  "properties": {
    "iso:country":"ES",
    "sg:address":"Avda Portugal, 89",
    "sg:city":"Madrid",
    "sg:orig_category":"Pintores",
    "sg:phone":"+34 915 26 03 95",
    "sg:postcode":"28011",
    "sg:province":"Madrid",
    "wof:name":"Santamaria Juez Maria Del Carmen",
    "wof:placetype":"venue"
},
  "geometry": {"coordinates":[-3.7292230129,40.4143981934],"type":"Point"}
}