{
  "type": "Feature",
  "properties": {
    "addr:full":"Calle de Bellver, 18 Madrid Madrid 28039",
    "addr:housenumber":"18",
    "addr:postcode":"madrid;28039",
    "addr:street":"Calle De Bellver",
    "iso:country":"ES",
    "sg:address":"Calle de Bellver, 18",
    "sg:city":"Madrid",
    "sg:orig_category":"Inform\u00c1tica: Material Y Suministros",
    "sg:phone":"+34 913 11 44 20",
    "sg:postcode":"28039",
    "sg:province":"Madrid",
    "wof:name":"Villa Cid Jesus",
    "wof:placetype":"venue"
},
  "geometry": {"coordinates":[-3.7048654556,40.4627227783],"type":"Point"}
}