{
  "type": "Feature",
  "properties": {
    "addr:full":"Av. Fdez. Jardon, 39 Navia Asturias 33710",
    "addr:housenumber":"39",
    "addr:postcode":"33710",
    "addr:street":"Av. Fdez. Jardon",
    "iso:country":"ES",
    "sg:address":"Av. Fdez. Jardon, 39",
    "sg:city":"Navia",
    "sg:orig_category":"Contenedores (mercanc\u00cdas)",
    "sg:phone":"+34 985 47 34 18",
    "sg:postcode":"33710",
    "sg:province":"Asturias",
    "wof:name":"Gion Lombardero Antonio",
    "wof:placetype":"venue"
},
  "geometry": {"coordinates":[-6.6691579819,43.5343322754],"type":"Point"}
}