{
  "type": "Feature",
  "properties": {
    "iso:country":"ES",
    "sg:address":"Via Augusta, 149",
    "sg:city":"Barcelona",
    "sg:orig_category":"Colocaci\u00d3n, Mantenimiento, Vitrificaci\u00d3n De Parquets",
    "sg:phone":"+34 932 09 13 19",
    "sg:postcode":"08021",
    "sg:province":"Barcelona",
    "wof:name":"Serveis Per La Llar Pamosa S.l.",
    "wof:placetype":"venue"
},
  "geometry": {"coordinates":[2.143887043,41.3991737366],"type":"Point"}
}