{
  "type": "Feature",
  "properties": {
    "iso:country":"ES",
    "sg:address":"Calle de Don Llorente, 45",
    "sg:city":"Don Benito",
    "sg:orig_category":"Farmacias",
    "sg:phone":"+34 924 80 01 85",
    "sg:postcode":"06400",
    "sg:province":"Badajoz",
    "wof:name":"Farmacia Mayoral-godoy C.b.",
    "wof:placetype":"venue"
},
  "geometry": {"coordinates":[-5.8643422127,38.9590377808],"type":"Point"}
}