{
  "type": "Feature",
  "properties": {
    "addr:full":"Plaz Santa Barbara, 1 Pe\u00e7arroya-pueblonuevo C\u00f3rdoba 14200",
    "addr:housenumber":"1",
    "addr:postcode":"14200",
    "addr:street":"Santa Barbara;Co\u0301Rdoba",
    "iso:country":"ES",
    "sg:address":"Plaz Santa Barbara, 1",
    "sg:city":"Pe\u00e7arroya-pueblonuevo",
    "sg:orig_category":"Ropa Para Ni\u00d1os (al Por Menor)",
    "sg:phone":"+34 957 56 02 82",
    "sg:postcode":"14200",
    "sg:province":"C\u00f3rdoba",
    "wof:name":"Flores Guisado Maria Carmen",
    "wof:placetype":"venue"
},
  "geometry": {"coordinates":[-5.2682538033,38.3007049561],"type":"Point"}
}