{
  "type": "Feature",
  "properties": {
    "addr:full":"Pol Ind El Trocadero, S/n Pto Real C\u00e1diz 11519",
    "addr:housenumber":"s / n",
    "addr:postcode":"11519",
    "addr:street":"Pto;Ca\u0301Diz",
    "iso:country":"ES",
    "sg:address":"Pol Ind El Trocadero, S/n",
    "sg:city":"Pto Real",
    "sg:orig_category":"Comercio De Piezas De Recambio Y De Accesorios De Veh\u00cdculos, Veh\u00cdculos Industriales",
    "sg:phone":"+34 956 47 83 53",
    "sg:postcode":"11519",
    "sg:province":"C\u00e1diz",
    "wof:name":"Delphi Automotive Systems Espa\u00d1a S.l.",
    "wof:placetype":"venue"
},
  "geometry": {"coordinates":[-6.2170300484,36.5123291016],"type":"Point"}
}