{
  "type": "Feature",
  "properties": {
    "iso:country":"ES",
    "sg:address":"Calle de Pablo Picasso, 29",
    "sg:city":"Velez-malaga",
    "sg:orig_category":"Ingeniero",
    "sg:phone":"+34 952 50 40 62",
    "sg:postcode":"29700",
    "sg:province":"M\u00e1laga",
    "wof:name":"Ruiz Ortega Jose Miguel",
    "wof:placetype":"venue"
},
  "geometry": {"coordinates":[-4.102186203,36.7763252258],"type":"Point"}
}