{
  "type": "Feature",
  "properties": {
    "iso:country":"ES",
    "sg:address":"Calle de Cardenal Spinola, 22",
    "sg:city":"Estepa",
    "sg:orig_category":"Abogados",
    "sg:phone":"+34 955 91 42 22",
    "sg:postcode":"41560",
    "sg:province":"Sevilla",
    "wof:name":"Estudio Guridico Castellano Y Asociados S.l",
    "wof:placetype":"venue"
},
  "geometry": {"coordinates":[-4.8780741692,37.2938766479],"type":"Point"}
}