{
  "type": "Feature",
  "properties": {
    "iso:country":"ES",
    "sg:address":"Avda San Sebastian, 5",
    "sg:city":"Malaga",
    "sg:orig_category":"Servicios Gsm",
    "sg:phone":"+34 952 61 54 73",
    "sg:postcode":"29010",
    "sg:province":"M\u00e1laga",
    "wof:name":"Luichi Falcon Jose Carlos",
    "wof:placetype":"venue"
},
  "geometry": {"coordinates":[-4.4364027977,36.7229728699],"type":"Point"}
}