{
  "type": "Feature",
  "properties": {
    "addr:full":"Calle de Numancia, 1 Palmas De Gran Canaria Las Palmas 35010",
    "addr:housenumber":"1",
    "addr:postcode":"35010",
    "addr:street":"Calle De Numancia",
    "iso:country":"ES",
    "sg:address":"Calle de Numancia, 1",
    "sg:city":"Palmas De Gran Canaria",
    "sg:orig_category":"Delegados, Agentes De Tr\u00c1nsito, Auxiliares De Transporte Internacional",
    "sg:phone":"+34 928 27 10 00",
    "sg:postcode":"35010",
    "sg:province":"Las Palmas",
    "wof:name":"Transtecar Canarias S.l.",
    "wof:placetype":"venue"
},
  "geometry": {"coordinates":[-15.4433393478,28.1320705414],"type":"Point"}
}