{
  "type": "Feature",
  "properties": {
    "iso:country":"ES",
    "sg:address":"Carr Font (la), 16",
    "sg:city":"Juneda",
    "sg:orig_category":"Peluquer\u00cdas, Peluquer\u00cda Mixta",
    "sg:phone":"+34 973 15 13 68",
    "sg:postcode":"25430",
    "sg:province":"Lleida",
    "wof:name":"Niubo Cendre Merce",
    "wof:placetype":"venue"
},
  "geometry": {"coordinates":[0.8210999966,41.5490760803],"type":"Point"}
}