{
  "type": "Feature",
  "properties": {
    "addr:full":"Calle de Galaroza, S/n Huelva Huelva 21006",
    "addr:housenumber":"s / n",
    "addr:postcode":"21006",
    "addr:street":"Calle De Galaroza",
    "iso:country":"ES",
    "sg:address":"Calle de Galaroza, S/n",
    "sg:city":"Huelva",
    "sg:orig_category":"Panader\u00cdas, Panader\u00cdas",
    "sg:phone":"+34 959 23 04 36",
    "sg:postcode":"21006",
    "sg:province":"Huelva",
    "wof:name":"Rodriguez Morales Jose Antonio",
    "wof:placetype":"venue"
},
  "geometry": {"coordinates":[-6.9320540428,37.2610397339],"type":"Point"}
}