{
  "type": "Feature",
  "properties": {
    "addr:full":"Carrer de Alcoi, 1 Terrassa Barcelona 08225",
    "addr:housenumber":"1",
    "addr:postcode":"08225",
    "addr:street":"Carrer De Alcoi",
    "iso:country":"ES",
    "sg:address":"Carrer de Alcoi, 1",
    "sg:city":"Terrassa",
    "sg:orig_category":"Contenedores (mercanc\u00cdas)",
    "sg:phone":"+34 937 35 77 79",
    "sg:postcode":"08225",
    "sg:province":"Barcelona",
    "wof:name":"Julian Planas Jose",
    "wof:placetype":"venue"
},
  "geometry": {"coordinates":[2.0073060989,41.5789451599],"type":"Point"}
}