{
  "type": "Feature",
  "properties": {
    "addr:full":"Calle de Alonso El Sabio, 40 Cordoba C\u00f3rdoba 14001",
    "addr:housenumber":"40",
    "addr:postcode":"14001",
    "addr:street":"Calle De Alonso El Sabio;Co\u0301Rdoba",
    "iso:country":"ES",
    "sg:address":"Calle de Alonso El Sabio, 40",
    "sg:city":"Cordoba",
    "sg:orig_category":"Peluqueros: De Se\u00d1oras",
    "sg:phone":"+34 957 48 79 19",
    "sg:postcode":"14001",
    "sg:province":"C\u00f3rdoba",
    "wof:name":"Ca\u00f1ete Hierro Maria Antonia",
    "wof:placetype":"venue"
},
  "geometry": {"coordinates":[-4.7769255638,37.8897323608],"type":"Point"}
}