{
  "type": "Feature",
  "properties": {
    "addr:full":"Calle de Santa Cristina, 7 Malaga M\u00e1laga 29016",
    "addr:housenumber":"7",
    "addr:postcode":"29016",
    "addr:street":"Calle De Santa Cristina;Ma\u0301Laga",
    "iso:country":"ES",
    "sg:address":"Calle de Santa Cristina, 7",
    "sg:city":"Malaga",
    "sg:orig_category":"Peluqueros: De Se\u00d1oras",
    "sg:phone":"+34 952 21 79 23",
    "sg:postcode":"29016",
    "sg:province":"M\u00e1laga",
    "wof:name":"Montes Ruiz Miguel",
    "wof:placetype":"venue"
},
  "geometry": {"coordinates":[-4.4067320824,36.7200279236],"type":"Point"}
}