{
  "type": "Feature",
  "properties": {
    "iso:country":"ES",
    "sg:address":"Calle de Jazmines (los), 10",
    "sg:city":"Barrios",
    "sg:orig_category":"Sociedades, Compa\u00d1\u00cdas Aseguradoras",
    "sg:phone":"+34 956 62 32 89",
    "sg:postcode":"11370",
    "sg:province":"C\u00e1diz",
    "wof:name":"Multimarca Oliva Grande S.l.l.",
    "wof:placetype":"venue"
},
  "geometry": {"coordinates":[-5.4853820801,36.1825561523],"type":"Point"}
}