{
  "type": "Feature",
  "properties": {
    "iso:country":"ES",
    "sg:address":"Calle de Pages Del Corro, 98",
    "sg:city":"Sevilla",
    "sg:orig_category":"Molduras, Junquillos, Listones Y Molduras Perforadas",
    "sg:phone":"+34 954 33 30 67",
    "sg:postcode":"41010",
    "sg:province":"Sevilla",
    "wof:name":"Pulido Barba Cristobal",
    "wof:placetype":"venue"
},
  "geometry": {"coordinates":[-6.0041761398,37.3829879761],"type":"Point"}
}