{
  "type": "Feature",
  "properties": {
    "addr:full":"Calle de Francisco Lujan, 2 Badajoz Badajoz 06004",
    "addr:housenumber":"2",
    "addr:postcode":"06004",
    "addr:street":"Calle De Francisco Lujan",
    "iso:country":"ES",
    "sg:address":"Calle de Francisco Lujan, 2",
    "sg:city":"Badajoz",
    "sg:orig_category":"Psic\u00d3logos",
    "sg:phone":"+34 924 25 60 04",
    "sg:postcode":"06004",
    "sg:province":"Badajoz",
    "wof:name":"Cuenda Corrales Aquilino",
    "wof:placetype":"venue"
},
  "geometry": {"coordinates":[-6.9771780968,38.871673584],"type":"Point"}
}