{
  "type": "Feature",
  "properties": {
    "addr:full":"Calle de Barquillo, 2 Menasalbas Toledo 45128",
    "addr:housenumber":"2",
    "addr:postcode":"45128",
    "addr:street":"Calle De Barquillo",
    "iso:country":"ES",
    "sg:address":"Calle de Barquillo, 2",
    "sg:city":"Menasalbas",
    "sg:orig_category":"Art\u00cdculos De Regalo (al Por Menor)",
    "sg:phone":"+34 925 40 71 93",
    "sg:postcode":"45128",
    "sg:province":"Toledo",
    "wof:name":"Camino Ruiz Jose Luis",
    "wof:placetype":"venue"
},
  "geometry": {"coordinates":[-4.285282135,39.6403884888],"type":"Point"}
}