{
  "type": "Feature",
  "properties": {
    "addr:full":"Calle de Aguado, 15 Gijon Asturias 33202",
    "addr:housenumber":"15",
    "addr:postcode":"33202",
    "addr:street":"Calle De Aguado",
    "iso:country":"ES",
    "sg:address":"Calle de Aguado, 15",
    "sg:city":"Gijon",
    "sg:orig_category":"Loter\u00cda Y T\u00d3mbola",
    "sg:phone":"+34 985 13 30 94",
    "sg:postcode":"33202",
    "sg:province":"Asturias",
    "wof:name":"Garcia Puente Antonio",
    "wof:placetype":"venue"
},
  "geometry": {"coordinates":[-5.6496300697,43.5383262634],"type":"Point"}
}