{
  "type": "Feature",
  "properties": {
    "addr:full":"Calle de Valladolid, S/n Aranda Duero Burgos 09400",
    "addr:postcode":"09400",
    "addr:street":"Calle De Valladolid S / N Aranda Duero",
    "iso:country":"ES",
    "sg:address":"Calle de Valladolid, S/n",
    "sg:city":"Aranda Duero",
    "sg:orig_category":"Venta, Alquiler, Mantenimiento De Calderas",
    "sg:phone":"+34 947 50 78 92",
    "sg:postcode":"09400",
    "sg:province":"Burgos",
    "sg:website":"www.imesa.es",
    "wof:name":"Industrias Metalurgicas Esgueva S.a.",
    "wof:placetype":"venue"
},
  "geometry": {"coordinates":[-3.6945679188,41.6718597412],"type":"Point"}
}