{
  "type": "Feature",
  "properties": {
    "iso:country":"ES",
    "sg:address":"Calle de Federico Moreno Torroba, 1",
    "sg:city":"Madrid",
    "sg:orig_category":"Promotores Constructores",
    "sg:phone":"+34 915 02 13 93",
    "sg:postcode":"28007",
    "sg:province":"Madrid",
    "wof:name":"Promociones Y Alquileres Vadesol S.l.",
    "wof:placetype":"venue"
},
  "geometry": {"coordinates":[-3.6671578884,40.4050369263],"type":"Point"}
}