{
  "type": "Feature",
  "properties": {
    "iso:country":"ES",
    "sg:address":"Calle de Sargento Coriat, 4",
    "sg:city":"Ceuta",
    "sg:orig_category":"Papeler\u00cdas, Librer\u00cdas",
    "sg:phone":"+34 956 51 95 73",
    "sg:postcode":"51001",
    "sg:province":"Ceuta",
    "wof:name":"Benzauuen Beniflah Simy",
    "wof:placetype":"venue"
},
  "geometry": {"coordinates":[-5.3070321083,35.8872718811],"type":"Point"}
}