{
  "type": "Feature",
  "properties": {
    "addr:full":"Av Constitucio, 101 Castelldefels Barcelona 08860",
    "addr:housenumber":"101",
    "addr:postcode":"08860",
    "addr:street":"Av Constitucio",
    "iso:country":"ES",
    "sg:address":"Av Constitucio, 101",
    "sg:city":"Castelldefels",
    "sg:orig_category":"Inform\u00c1tica (estudios, Servicios, Asesor\u00cda, Formaci\u00d3n)",
    "sg:phone":"+34 936 36 22 99",
    "sg:postcode":"08860",
    "sg:province":"Barcelona",
    "sg:website":"www.microusa.es",
    "wof:name":"Microusa S.l.",
    "wof:placetype":"venue"
},
  "geometry": {"coordinates":[1.9797320366,41.2803153992],"type":"Point"}
}