{
  "type": "Feature",
  "properties": {
    "addr:full":"Calle de San Antonio, 104 Torreblanca Castell\u00f3n 12596",
    "addr:housenumber":"104",
    "addr:postcode":"12596",
    "addr:street":"Calle De San Antonio;Castello\u0301N",
    "iso:country":"ES",
    "sg:address":"Calle de San Antonio, 104",
    "sg:city":"Torreblanca",
    "sg:orig_category":"Frutas Y Legumbres Frescas (al Por Mayor)",
    "sg:phone":"+34 964 42 00 58",
    "sg:postcode":"12596",
    "sg:province":"Castell\u00f3n",
    "wof:name":"Fruites Y Verdures Betoret Roda S.l.",
    "wof:placetype":"venue"
},
  "geometry": {"coordinates":[0.1927320063,40.2193756104],"type":"Point"}
}