{
  "type": "Feature",
  "properties": {
    "addr:full":"Calle de Regimiento De Toledo, 31 Zamora Zamora 49011",
    "addr:housenumber":"31",
    "addr:postcode":"49011",
    "addr:street":"Calle De Regimiento De Toledo",
    "iso:country":"ES",
    "sg:address":"Calle de Regimiento De Toledo, 31",
    "sg:city":"Zamora",
    "sg:orig_category":"Papeler\u00cdas, Librer\u00cdas",
    "sg:phone":"+34 980 52 17 24",
    "sg:postcode":"49011",
    "sg:province":"Zamora",
    "wof:name":"Ya\u00f1ez Perez De Vargas Carlos",
    "wof:placetype":"venue"
},
  "geometry": {"coordinates":[-5.7382907867,41.5109786987],"type":"Point"}
}