{
  "type": "Feature",
  "properties": {
    "addr:full":"Calle de Procesiones, 1 Valencia De Don Juan Le\u00f3n 24200",
    "addr:housenumber":"1",
    "addr:postcode":"24200",
    "addr:street":"Calle De Procesiones",
    "iso:country":"ES",
    "sg:address":"Calle de Procesiones, 1",
    "sg:city":"Valencia De Don Juan",
    "sg:orig_category":"Panader\u00cdas, Panader\u00cdas",
    "sg:phone":"+34 987 75 05 64",
    "sg:postcode":"24200",
    "sg:province":"Le\u00f3n",
    "wof:name":"Blanco Cabal Manuel",
    "wof:placetype":"venue"
},
  "geometry": {"coordinates":[-5.5179138184,42.2936134338],"type":"Point"}
}