{
  "type": "Feature",
  "properties": {
    "iso:country":"ES",
    "sg:address":"Calle de Iparraguirre, 10",
    "sg:city":"Sestao",
    "sg:orig_category":"Quiropr\u00c1cticos",
    "sg:phone":"+34 944 01 33 30",
    "sg:postcode":"48910",
    "sg:province":"Vizcaya",
    "sg:website":"www.gastenet.com/masajelango",
    "wof:name":"Jose Ignacio Lambarri Ortiz",
    "wof:placetype":"venue"
},
  "geometry": {"coordinates":[-3.0072460175,43.3073959351],"type":"Point"}
}