{
  "type": "Feature",
  "properties": {
    "addr:full":"Calle de San Cayetano, 22 Churriana Vega Granada 18194",
    "addr:housenumber":"22",
    "addr:postcode":"18194",
    "addr:street":"Calle De San Cayetano",
    "iso:country":"ES",
    "sg:address":"Calle de San Cayetano, 22",
    "sg:city":"Churriana Vega",
    "sg:orig_category":"Panader\u00cdas, Panader\u00cdas",
    "sg:phone":"+34 958 55 38 35",
    "sg:postcode":"18194",
    "sg:province":"Granada",
    "wof:name":"Pulido Moyano Francisco Javier",
    "wof:placetype":"venue"
},
  "geometry": {"coordinates":[-3.6773679256,37.1503562927],"type":"Point"}
}