{
  "type": "Feature",
  "properties": {
    "iso:country":"ES",
    "sg:address":"Calle de Don Claudio, 5",
    "sg:city":"Sanlucar De Barrameda",
    "sg:classifiers":[
        {
            "category":"Autos & Motor Vehicles",
            "subcategory":"Automobile Sales",
            "type":"Retail Goods"
        }
    ],
    "sg:phone":"+34 956 36 33 02",
    "sg:postcode":"11540",
    "sg:province":"C\u00e1diz",
    "wof:name":"Harana Romero Antonio",
    "wof:placetype":"venue"
},
  "geometry": {"coordinates":[-6.3504972458,36.7799797058],"type":"Point"}
}