{
  "type": "Feature",
  "properties": {
    "iso:country":"ES",
    "sg:address":"Calle de Francisco De Quevedo, 7",
    "sg:city":"Santander",
    "sg:orig_category":"Institutos De Belleza",
    "sg:phone":"+34 942 36 21 20",
    "sg:postcode":"39001",
    "sg:province":"Cantabria",
    "wof:name":"Bujan De Berrazueta Maria Dolores",
    "wof:placetype":"venue"
},
  "geometry": {"coordinates":[-3.809276104,43.4622192383],"type":"Point"}
}