{
  "type": "Feature",
  "properties": {
    "addr:full":"Calle de Andalucia, 12 Mislata Valencia 46920",
    "addr:housenumber":"12",
    "addr:postcode":"46920",
    "addr:street":"Calle De Andalucia",
    "iso:country":"ES",
    "sg:address":"Calle de Andalucia, 12",
    "sg:city":"Mislata",
    "sg:orig_category":"Ropa Para Se\u00d1oras (al Por Menor)",
    "sg:phone":"+34 963 70 00 85",
    "sg:postcode":"46920",
    "sg:province":"Valencia",
    "wof:name":"Be\u00f1ago Rubio Maria Amparo",
    "wof:placetype":"venue"
},
  "geometry": {"coordinates":[-0.4189920127,39.4786262512],"type":"Point"}
}