{
  "type": "Feature",
  "properties": {
    "addr:full":"Plaz Espa\u00d1a, 7 Leganes Madrid 28911",
    "addr:housenumber":"7",
    "addr:postcode":"28911",
    "addr:street":"Plaz Espan\u0303A",
    "iso:country":"ES",
    "sg:address":"Plaz Espa\u00d1a, 7",
    "sg:city":"Leganes",
    "sg:orig_category":"Asesor\u00cda Fiscal Y Jur\u00cddica",
    "sg:phone":"+34 916 89 80 82",
    "sg:postcode":"28911",
    "sg:province":"Madrid",
    "wof:name":"Carrasco Vaquero Susana",
    "wof:placetype":"venue"
},
  "geometry": {"coordinates":[-3.7646379471,40.3278236389],"type":"Point"}
}