{
  "type": "Feature",
  "properties": {
    "iso:country":"ES",
    "sg:address":"Cllo Africano, 5",
    "sg:city":"Coru\u00d1a",
    "sg:orig_category":"Perfumer\u00cda (al Por Menor)",
    "sg:phone":"+34 981 22 41 18",
    "sg:postcode":"15003",
    "sg:province":"La Coru\u00f1a",
    "wof:name":"Lopez Sanchez Obdulia",
    "wof:placetype":"venue"
},
  "geometry": {"coordinates":[-8.4032936096,43.3700637817],"type":"Point"}
}