{
  "type": "Feature",
  "properties": {
    "addr:full":"Carrer de Empedrat, 18 Ibi Alicante 03440",
    "addr:housenumber":"18",
    "addr:postcode":"03440",
    "addr:street":"Carrer De Empedrat",
    "iso:country":"ES",
    "sg:address":"Carrer de Empedrat, 18",
    "sg:city":"Ibi",
    "sg:orig_category":"Art\u00cdculos De Regalo (al Por Menor)",
    "sg:phone":"+34 965 55 30 37",
    "sg:postcode":"03440",
    "sg:province":"Alicante",
    "wof:name":"Ferrandiz Berbegal Natalia",
    "wof:placetype":"venue"
},
  "geometry": {"coordinates":[-0.5754920244,38.6269035339],"type":"Point"}
}