{
  "type": "Feature",
  "properties": {
    "addr:full":"G.v. Lopez De Haro D. Diego, 28 Bilbao Vizcaya 48009",
    "addr:housenumber":"28",
    "addr:postcode":"48009",
    "addr:street":"Lopez De Haro D. Diego",
    "iso:country":"ES",
    "sg:address":"G.v. Lopez De Haro D. Diego, 28",
    "sg:city":"Bilbao",
    "sg:orig_category":"Deportes Y Ocio: Art\u00cdculos Y Ropas (al Por Menor Y Accesorios)",
    "sg:phone":"+34 944 24 12 65",
    "sg:postcode":"48009",
    "sg:province":"Vizcaya",
    "wof:name":"Fernandez De Pinedo Mieg Ines",
    "wof:placetype":"venue"
},
  "geometry": {"coordinates":[-2.9320569038,43.2625007629],"type":"Point"}
}