{
  "type": "Feature",
  "properties": {
    "addr:full":"Carr Figueres, 31 Torroella Montgri Girona 17257",
    "addr:housenumber":"31",
    "addr:postcode":"17257",
    "addr:street":"Carr Figueres",
    "iso:country":"ES",
    "sg:address":"Carr Figueres, 31",
    "sg:city":"Torroella Montgri",
    "sg:orig_category":"Molduras, Junquillos, Listones Y Molduras Perforadas",
    "sg:phone":"+34 972 75 72 14",
    "sg:postcode":"17257",
    "sg:province":"Girona",
    "wof:name":"Martin Guerrero Emilio",
    "wof:placetype":"venue"
},
  "geometry": {"coordinates":[3.1034500599,42.0303268433],"type":"Point"}
}