{
  "type": "Feature",
  "properties": {
    "addr:full":"Alberti, 3 Herrera Sevilla 41567",
    "addr:housenumber":"3",
    "addr:postcode":"41567",
    "addr:street":"Alberti",
    "iso:country":"ES",
    "sg:address":"Alberti, 3",
    "sg:city":"Herrera",
    "sg:orig_category":"Peleter\u00cdas",
    "sg:phone":"+34 954 01 26 22",
    "sg:postcode":"41567",
    "sg:province":"Sevilla",
    "wof:name":"Arteaga Jurado Remedios",
    "wof:placetype":"venue"
},
  "geometry": {"coordinates":[-4.8453474045,37.3595123291],"type":"Point"}
}