{
  "type": "Feature",
  "properties": {
    "addr:full":"Calle de Magdalena, 57 Daimiel Ciudad Real 13250",
    "addr:housenumber":"57",
    "addr:postcode":"13250",
    "addr:street":"Calle De Magdalena",
    "iso:country":"ES",
    "sg:address":"Calle de Magdalena, 57",
    "sg:city":"Daimiel",
    "sg:orig_category":"Estudios, Instalaci\u00d3n De Climatizaci\u00d3n",
    "sg:phone":"+34 926 26 00 26",
    "sg:postcode":"13250",
    "sg:province":"Ciudad Real",
    "wof:name":"Climatizaciones Vicar S.l.",
    "wof:placetype":"venue"
},
  "geometry": {"coordinates":[-3.6233990192,39.0682983398],"type":"Point"}
}