{
  "type": "Feature",
  "properties": {
    "addr:full":"Ctra. Arenal, 15 Les Meravelles Islas Baleares 07610",
    "addr:housenumber":"15",
    "addr:postcode":"07610",
    "addr:street":"Ctra. Arenal;Les Meravelles",
    "iso:country":"ES",
    "sg:address":"Ctra. Arenal, 15",
    "sg:city":"Les Meravelles",
    "sg:orig_category":"Ropa Para Se\u00d1oras (al Por Menor)",
    "sg:phone":"+34 971 26 52 09",
    "sg:postcode":"07610",
    "sg:province":"Islas Baleares",
    "wof:name":"Riera Salas Juan",
    "wof:placetype":"venue"
},
  "geometry": {"coordinates":[2.7243249416,39.5336914062],"type":"Point"}
}