{
  "type": "Feature",
  "properties": {
    "addr:full":"Pase Pechina, 30 Valencia Valencia 46008",
    "addr:housenumber":"30",
    "addr:postcode":"46008",
    "addr:street":"Pechina",
    "iso:country":"ES",
    "sg:address":"Pase Pechina, 30",
    "sg:city":"Valencia",
    "sg:classifiers":[
        {
            "category":"Arts & Performance",
            "subcategory":"Art Gallery",
            "type":"Entertainment"
        }
    ],
    "sg:phone":"+34 963 85 10 53",
    "sg:postcode":"46008",
    "sg:province":"Valencia",
    "sg:tags":[
        "obras",
        "de",
        "coleccionismo",
        "compraventa",
        "arte",
        "y"
    ],
    "sg:website":"www.artevecchio.com",
    "wof:name":"Arte Vecchio S.l.",
    "wof:placetype":"venue"
},
  "geometry": {"coordinates":[-0.3911904097,39.4770889282],"type":"Point"}
}