{
  "type": "Feature",
  "properties": {
    "iso:country":"ES",
    "sg:address":"Pla\u00c7 Abat Oliba, 1",
    "sg:city":"Centre Urba",
    "sg:orig_category":"Oficinas De Turismo, Asociaciones De Iniciativa",
    "sg:phone":"+34 972 70 23 51",
    "sg:postcode":"17500",
    "sg:province":"Girona",
    "wof:name":"Ajuntament De Ripoll-oficina De Turisme",
    "wof:placetype":"venue"
},
  "geometry": {"coordinates":[2.8236999512,41.9817962646],"type":"Point"}
}