{
  "type": "Feature",
  "properties": {
    "iso:country":"ES",
    "sg:address":"Calle de Pelayo, 9",
    "sg:city":"Madrid",
    "sg:classifiers":[
        {
            "category":"Autos & Motor Vehicles",
            "subcategory":"Automobile Sales",
            "type":"Retail Goods"
        }
    ],
    "sg:phone":"+34 915 23 20 25",
    "sg:postcode":"28004",
    "sg:province":"Madrid",
    "wof:name":"Futuro Conductor S.l.",
    "wof:placetype":"venue"
},
  "geometry": {"coordinates":[-3.6990680695,40.4222412109],"type":"Point"}
}