{
  "type": "Feature",
  "properties": {
    "addr:full":"Calle de Isidro Rueda, 1 Ponferrada Le\u00f3n 24400",
    "addr:housenumber":"1",
    "addr:postcode":"24400",
    "addr:street":"Calle De Isidro Rueda",
    "iso:country":"ES",
    "sg:address":"Calle de Isidro Rueda, 1",
    "sg:city":"Ponferrada",
    "sg:orig_category":"M\u00c9dicos: Dermatolog\u00cda Y Venereolog\u00cda",
    "sg:phone":"+34 987 42 55 38",
    "sg:postcode":"24400",
    "sg:province":"Le\u00f3n",
    "wof:name":"Gonzalez Montero Jose Manuel",
    "wof:placetype":"venue"
},
  "geometry": {"coordinates":[-6.5995807648,42.5460166931],"type":"Point"}
}