{
  "type": "Feature",
  "properties": {
    "addr:full":"Calle de Juan Alvargonzalez, 87 Gijon Asturias 33208",
    "addr:housenumber":"87",
    "addr:postcode":"33208",
    "addr:street":"Calle De Juan Alvargonzalez",
    "iso:country":"ES",
    "sg:address":"Calle de Juan Alvargonzalez, 87",
    "sg:city":"Gijon",
    "sg:orig_category":"Promotores Constructores",
    "sg:phone":"+34 985 38 89 10",
    "sg:postcode":"33208",
    "sg:province":"Asturias",
    "wof:name":"Estructuras Y Construcciones Palacios Urbies S.l.",
    "wof:placetype":"venue"
},
  "geometry": {"coordinates":[-5.6639990807,43.5296516418],"type":"Point"}
}