{
  "type": "Feature",
  "properties": {
    "addr:full":"Calle de Ca\u00d1uelo, 1 Benalup C\u00e1diz 11190",
    "addr:housenumber":"1",
    "addr:postcode":"11190",
    "addr:street":"Calle De Can\u0303Uelo;Ca\u0301Diz",
    "iso:country":"ES",
    "sg:address":"Calle de Ca\u00d1uelo, 1",
    "sg:city":"Benalup",
    "sg:orig_category":"Supermercados Y Hipermercados",
    "sg:phone":"+34 956 42 46 07",
    "sg:postcode":"11190",
    "sg:province":"C\u00e1diz",
    "wof:name":"Dinosol Supermercados S.l.",
    "wof:placetype":"venue"
},
  "geometry": {"coordinates":[-5.8122630119,36.3458633423],"type":"Point"}
}