{
  "type": "Feature",
  "properties": {
    "addr:full":"Calle de Sorni, 42 Valencia Valencia 46004",
    "addr:housenumber":"42",
    "addr:postcode":"46004",
    "addr:street":"Calle De Sorni",
    "iso:country":"ES",
    "sg:address":"Calle de Sorni, 42",
    "sg:city":"Valencia",
    "sg:orig_category":"Inmobiliaria (agencias)",
    "sg:phone":"+34 963 33 23 13",
    "sg:postcode":"46004",
    "sg:province":"Valencia",
    "wof:name":"Crespo Champion Alejandro",
    "wof:placetype":"venue"
},
  "geometry": {"coordinates":[-0.3658469915,39.4700889587],"type":"Point"}
}