{
  "type": "Feature",
  "properties": {
    "addr:full":"Calle de Guadalquivir, 1 Ronda M\u00e1laga 29400",
    "addr:housenumber":"1",
    "addr:postcode":"29400",
    "addr:street":"Calle De Guadalquivir;Ronda Ma\u0301Laga",
    "iso:country":"ES",
    "sg:address":"Calle de Guadalquivir, 1",
    "sg:city":"Ronda",
    "sg:orig_category":"Quincaller\u00cda (al Por Menor)",
    "sg:phone":"+34 952 87 37 14",
    "sg:postcode":"29400",
    "sg:province":"M\u00e1laga",
    "wof:name":"Suministros San Rafael S.l.",
    "wof:placetype":"venue"
},
  "geometry": {"coordinates":[-5.1651511192,36.7569694519],"type":"Point"}
}