{
  "type": "Feature",
  "properties": {
    "addr:full":"Carretera Trabanca, S/n Alora M\u00e1laga 29500",
    "addr:housenumber":"s / n",
    "addr:postcode":"29500",
    "addr:street":"Carretera Trabanca;Alora Ma\u0301Laga",
    "iso:country":"ES",
    "sg:address":"Carretera Trabanca, S/n",
    "sg:city":"Alora",
    "sg:orig_category":"Ense\u00d1anza Agr\u00cdcola",
    "sg:phone":"+34 952 49 83 93",
    "sg:postcode":"29500",
    "sg:province":"M\u00e1laga",
    "wof:name":"Elina Tuurna Maija",
    "wof:placetype":"venue"
},
  "geometry": {"coordinates":[-4.7050089836,36.8296661377],"type":"Point"}
}