{
  "type": "Feature",
  "properties": {
    "iso:country":"ES",
    "sg:address":"Avda Gran Via Rey Juan Carlos I, 38",
    "sg:city":"Logro\u00f1o",
    "sg:orig_category":"Herboristas (al Por Menor)",
    "sg:phone":"+34 941 22 61 49",
    "sg:postcode":"26002",
    "sg:province":"La Rioja",
    "wof:name":"Justo Torrecilla Jose Maria",
    "wof:placetype":"venue"
},
  "geometry": {"coordinates":[-2.4507210255,42.4644813538],"type":"Point"}
}