{
  "type": "Feature",
  "properties": {
    "iso:country":"ES",
    "sg:address":"Calle de General Margallo, 31",
    "sg:city":"Madrid",
    "sg:orig_category":"Papeler\u00cdas, Librer\u00cdas",
    "sg:phone":"+34 915 79 52 75",
    "sg:postcode":"28020",
    "sg:province":"Madrid",
    "wof:name":"Granado De Aza Donato",
    "wof:placetype":"venue"
},
  "geometry": {"coordinates":[-3.6947152615,40.4604034424],"type":"Point"}
}