{
  "type": "Feature",
  "properties": {
    "iso:country":"ES",
    "sg:address":"Calle de Antonio Machado (de), 21",
    "sg:city":"San Fernando De Henares",
    "sg:orig_category":"Carnicer\u00cdas, Carnicer\u00cdas",
    "sg:phone":"+34 916 71 11 23",
    "sg:postcode":"28830",
    "sg:province":"Madrid",
    "wof:name":"Ramiro Garcia Antonio",
    "wof:placetype":"venue"
},
  "geometry": {"coordinates":[-3.5339782238,40.4237327576],"type":"Point"}
}