{
  "type": "Feature",
  "properties": {
    "addr:full":"Calle de Burniola Kalea, 9 Irun Guip\u00f9zcoa 20303",
    "addr:housenumber":"9",
    "addr:postcode":"20303",
    "addr:street":"Calle De Burniola Kalea;Guipu\u0300Zcoa",
    "iso:country":"ES",
    "sg:address":"Calle de Burniola Kalea, 9",
    "sg:city":"Irun",
    "sg:orig_category":"Rectificaci\u00d3n, Mecanizado, Fresado",
    "sg:phone":"+34 943 63 39 88",
    "sg:postcode":"20303",
    "sg:province":"Guip\u00f9zcoa",
    "wof:name":"Mecanizados Josmil S.l.",
    "wof:placetype":"venue"
},
  "geometry": {"coordinates":[-1.7902339697,43.3395233154],"type":"Point"}
}