{
  "type": "Feature",
  "properties": {
    "addr:full":"Calle de Caleruega, 66 Madrid Madrid 28033",
    "addr:housenumber":"66",
    "addr:postcode":"madrid;28033",
    "addr:street":"Calle De Caleruega",
    "iso:country":"ES",
    "sg:address":"Calle de Caleruega, 66",
    "sg:city":"Madrid",
    "sg:orig_category":"Centros Empresariales",
    "sg:phone":"+34 913 02 11 08",
    "sg:postcode":"28033",
    "sg:province":"Madrid",
    "wof:name":"Inteldist Iberica 2006 S.l.",
    "wof:placetype":"venue"
},
  "geometry": {"coordinates":[-3.6705093384,40.4822616577],"type":"Point"}
}