{
  "type": "Feature",
  "properties": {
    "iso:country":"ES",
    "sg:address":"Calle de Cabrales, 69",
    "sg:city":"Gijon",
    "sg:orig_category":"Fabricaci\u00d3n De Juegos Y Juguetes",
    "sg:phone":"+34 984 39 44 98",
    "sg:postcode":"33201",
    "sg:province":"Asturias",
    "wof:name":"Almacenes Inocencio Garcia Sl",
    "wof:placetype":"venue"
},
  "geometry": {"coordinates":[-5.6586060524,43.5364723206],"type":"Point"}
}