{
  "type": "Feature",
  "properties": {
    "iso:country":"ES",
    "sg:address":"Calle de Maesso, 14",
    "sg:city":"Llerena",
    "sg:orig_category":"Asesor\u00cda De Formaci\u00d3n Y Gesti\u00d3n De Personal",
    "sg:phone":"+34 924 87 39 40",
    "sg:postcode":"06900",
    "sg:province":"Badajoz",
    "wof:name":"Tena Morales Maria Angeles",
    "wof:placetype":"venue"
},
  "geometry": {"coordinates":[-6.0136327744,38.2380485535],"type":"Point"}
}