{
  "type": "Feature",
  "properties": {
    "addr:full":"Part Particular De Asturias, 9 Arizgoiti Vizcaya 48970",
    "addr:housenumber":"9",
    "addr:postcode":"48970",
    "addr:street":"Arizgoiti Vizcaya",
    "iso:country":"ES",
    "sg:address":"Part Particular De Asturias, 9",
    "sg:city":"Arizgoiti",
    "sg:orig_category":"Juristas",
    "sg:phone":"+34 944 40 45 56",
    "sg:postcode":"48970",
    "sg:province":"Vizcaya",
    "wof:name":"Vallejo Morgada Encina",
    "wof:placetype":"venue"
},
  "geometry": {"coordinates":[-2.8870439529,43.2375488281],"type":"Point"}
}