{
  "type": "Feature",
  "properties": {
    "iso:country":"ES",
    "sg:address":"Calle de Amadeo Vives (de), 2",
    "sg:city":"Boadilla Del Monte",
    "sg:orig_category":"Artes Gr\u00c1ficas, Artes Pl\u00c1sticas: Material Y Suministros (al Por Menor)",
    "sg:phone":"+34 916 33 04 78",
    "sg:postcode":"28660",
    "sg:province":"Madrid",
    "wof:name":"Reprofot S.l.",
    "wof:placetype":"venue"
},
  "geometry": {"coordinates":[-3.8854365349,40.4024658203],"type":"Point"}
}