{
  "type": "Feature",
  "properties": {
    "iso:country":"ES",
    "sg:address":"Pg Sant Gervasi, 26",
    "sg:city":"Barcelona",
    "sg:orig_category":"Peluqueros: De Se\u00d1oras",
    "sg:phone":"+34 934 18 62 41",
    "sg:postcode":"08022",
    "sg:province":"Barcelona",
    "wof:name":"Bernado Bastida Carmen",
    "wof:placetype":"venue"
},
  "geometry": {"coordinates":[2.1351149082,41.4091873169],"type":"Point"}
}