{
  "type": "Feature",
  "properties": {
    "iso:country":"ES",
    "sg:address":"Calle de Cristobal Colon, 10",
    "sg:city":"Marbella",
    "sg:orig_category":"Muebles Y Accesorios Para Cocinas Y Cuartos De Ba\u00d1o (al Por Menor)",
    "sg:phone":"+34 952 82 95 67",
    "sg:postcode":"29600",
    "sg:province":"M\u00e1laga",
    "wof:name":"Martin Rodriguez Alejandro",
    "wof:placetype":"venue"
},
  "geometry": {"coordinates":[-4.8775701523,36.5100593567],"type":"Point"}
}