{
  "type": "Feature",
  "properties": {
    "addr:full":"Calle de Ca\u00d1ada, 2 Valdilecha Madrid 28511",
    "addr:housenumber":"2",
    "addr:postcode":"28511",
    "addr:street":"Calle De Can\u0303Ada",
    "iso:country":"ES",
    "sg:address":"Calle de Ca\u00d1ada, 2",
    "sg:city":"Valdilecha",
    "sg:orig_category":"Cooperativas Agr\u00cdcolas",
    "sg:phone":"+34 918 73 84 15",
    "sg:postcode":"28511",
    "sg:province":"Madrid",
    "wof:name":"Cooperativa Del Campo Nuestra Se\u00f1ora De La Oliva",
    "wof:placetype":"venue"
},
  "geometry": {"coordinates":[-3.3016679287,40.2973251343],"type":"Point"}
}