{
  "type": "Feature",
  "properties": {
    "addr:full":"Calle de Jose Luis Bugallal Marchesi, S/n Coru\u00d1a La Coru\u00f1a 15008",
    "addr:housenumber":"s / n",
    "addr:postcode":"15008",
    "addr:street":"Calle De Jose Luis Bugallal Marchesi;La Corun\u0303A",
    "iso:country":"ES",
    "sg:address":"Calle de Jose Luis Bugallal Marchesi, S/n",
    "sg:city":"Coru\u00d1a",
    "sg:orig_category":"Carnicer\u00cdas, Carnicer\u00cdas",
    "sg:phone":"+34 981 24 26 16",
    "sg:postcode":"15008",
    "sg:province":"La Coru\u00f1a",
    "wof:name":"Garcia Mari\u00f1o Eduardo",
    "wof:placetype":"venue"
},
  "geometry": {"coordinates":[-8.4094743729,43.3455734253],"type":"Point"}
}