{
  "type": "Feature",
  "properties": {
    "iso:country":"ES",
    "sg:address":"Carrer de Lluis Sagnier, 59",
    "sg:city":"Barcelona",
    "sg:orig_category":"Artes Gr\u00c1ficas, Artes Pl\u00c1sticas (curso)",
    "sg:phone":"+34 934 35 42 07",
    "sg:postcode":"08032",
    "sg:province":"Barcelona",
    "wof:name":"Serveis Editorials Track 20 S.l.l.",
    "wof:placetype":"venue"
},
  "geometry": {"coordinates":[2.1737399101,41.4252586365],"type":"Point"}
}