{
  "type": "Feature",
  "properties": {
    "iso:country":"ES",
    "sg:address":"Calle de Legion, La, 2",
    "sg:city":"Melilla",
    "sg:orig_category":"Comercio De Piezas De Recambio Y De Accesorios De Veh\u00cdculos, Veh\u00cdculos Industriales",
    "sg:phone":"+34 952 67 93 58",
    "sg:postcode":"52006",
    "sg:province":"Melilla",
    "wof:name":"Bouji S.l.",
    "wof:placetype":"venue"
},
  "geometry": {"coordinates":[-2.9361999035,35.2828216553],"type":"Point"}
}