{
  "type": "Feature",
  "properties": {
    "addr:full":"Calle de Iris, 1 Albacete Albacete 02005",
    "addr:housenumber":"1",
    "addr:postcode":"02005",
    "addr:street":"Calle De Iris",
    "iso:country":"ES",
    "sg:address":"Calle de Iris, 1",
    "sg:city":"Albacete",
    "sg:orig_category":"Caf\u00c9s, Bares, Cervecer\u00cdas",
    "sg:phone":"+34 967 52 02 99",
    "sg:postcode":"02005",
    "sg:province":"Albacete",
    "wof:name":"Ainsa Y Sotos S.l.",
    "wof:placetype":"venue"
},
  "geometry": {"coordinates":[-1.8558142185,38.9978713989],"type":"Point"}
}