{
  "type": "Feature",
  "properties": {
    "addr:full":"Cardalda, 104 Vilanova Arousa Pontevedra 36628",
    "addr:housenumber":"104",
    "addr:postcode":"36628",
    "addr:street":"Cardalda",
    "iso:country":"ES",
    "sg:address":"Cardalda, 104",
    "sg:city":"Vilanova Arousa",
    "sg:orig_category":"Laboratorios Y Cl\u00cdnicas Veterinarias",
    "sg:phone":"+34 986 55 56 78",
    "sg:postcode":"36628",
    "sg:province":"Pontevedra",
    "wof:name":"Arousa Veterinaria S.l.",
    "wof:placetype":"venue"
},
  "geometry": {"coordinates":[-8.8229598999,42.5492897034],"type":"Point"}
}