{
  "type": "Feature",
  "properties": {
    "iso:country":"ES",
    "sg:address":"Calle de Abadia, 2",
    "sg:city":"Cheste",
    "sg:orig_category":"Carnicer\u00cdas, Carnicer\u00cdas",
    "sg:phone":"+34 962 51 27 54",
    "sg:postcode":"46380",
    "sg:province":"Valencia",
    "wof:name":"Rodero Sanchez Jeronimo",
    "wof:placetype":"venue"
},
  "geometry": {"coordinates":[-0.6831020713,39.4941825867],"type":"Point"}
}