{
  "type": "Feature",
  "properties": {
    "addr:full":"Calle de Doctor Mu\u00d1oz, 21 Cazorla Ja\u00e9n 23470",
    "addr:housenumber":"21",
    "addr:postcode":"23470",
    "addr:street":"Calle De Doctor Mun\u0303Oz",
    "iso:country":"ES",
    "sg:address":"Calle de Doctor Mu\u00d1oz, 21",
    "sg:city":"Cazorla",
    "sg:orig_category":"Cajas De Ahorro",
    "sg:phone":"+34 953 72 09 84",
    "sg:postcode":"23470",
    "sg:province":"Ja\u00e9n",
    "sg:website":"www.caja-granada.es",
    "wof:name":"Cajagranada",
    "wof:placetype":"venue"
},
  "geometry": {"coordinates":[-3.002876997,37.9124603271],"type":"Point"}
}