{
  "type": "Feature",
  "properties": {
    "addr:full":"Carrer de Sant Viven\u00c7 Paul, 21 Palma Islas Baleares 07010",
    "addr:housenumber":"21",
    "addr:postcode":"07010",
    "addr:street":"Carrer De Sant Vivenc\u0327 Paul",
    "iso:country":"ES",
    "sg:address":"Carrer de Sant Viven\u00c7 Paul, 21",
    "sg:city":"Palma",
    "sg:orig_category":"Mec\u00c1nico Del Autom\u00d3vil",
    "sg:phone":"+34 971 75 63 11",
    "sg:postcode":"07010",
    "sg:province":"Islas Baleares",
    "wof:name":"Morro Capo Juan",
    "wof:placetype":"venue"
},
  "geometry": {"coordinates":[2.6215190887,39.6229019165],"type":"Point"}
}