{
  "type": "Feature",
  "properties": {
    "addr:full":"Psje San Benito, S/n Villena Alicante 03400",
    "addr:postcode":"03400",
    "addr:street":"Psje San Benito S / N",
    "iso:country":"ES",
    "sg:address":"Psje San Benito, S/n",
    "sg:city":"Villena",
    "sg:orig_category":"Carnicer\u00cdas, Carnicer\u00cdas",
    "sg:phone":"+34 965 80 13 74",
    "sg:postcode":"03400",
    "sg:province":"Alicante",
    "wof:name":"El Cuartelero Cdad",
    "wof:placetype":"venue"
},
  "geometry": {"coordinates":[-0.8609640002,38.6280593872],"type":"Point"}
}