{
  "type": "Feature",
  "properties": {
    "addr:full":"Ctra Reus-montblanc, Km. 0005,8 Paret-delgada Tarragona 43470",
    "addr:postcode":"43470",
    "addr:street":"Ctra Reus-Montblanc Km. 0005,8 Paret-Delgada",
    "iso:country":"ES",
    "sg:address":"Ctra Reus-montblanc, Km. 0005,8",
    "sg:city":"Paret-delgada",
    "sg:orig_category":"Distribuci\u00d3n De Petr\u00d3leo Y Derivados",
    "sg:phone":"+34 977 76 62 00",
    "sg:postcode":"43470",
    "sg:province":"Tarragona",
    "sg:website":"www.cepsa.es",
    "wof:name":"Ciurana Gasull S.l.",
    "wof:placetype":"venue"
},
  "geometry": {"coordinates":[1.1409749985,41.2144813538],"type":"Point"}
}