{
  "type": "Feature",
  "properties": {
    "addr:full":"Calle de Ramon Y Cajal, 31 Miguelturra Ciudad Real 13170",
    "addr:housenumber":"31",
    "addr:postcode":"13170",
    "addr:street":"Calle De Ramon Y Cajal",
    "iso:country":"ES",
    "sg:address":"Calle de Ramon Y Cajal, 31",
    "sg:city":"Miguelturra",
    "sg:orig_category":"Negocio De Materiales De Construcci\u00d3n",
    "sg:phone":"+34 926 24 02 63",
    "sg:postcode":"13170",
    "sg:province":"Ciudad Real",
    "wof:name":"Martin Garcia Sacramento",
    "wof:placetype":"venue"
},
  "geometry": {"coordinates":[-3.8893020153,38.9657096863],"type":"Point"}
}