{
  "type": "Feature",
  "properties": {
    "iso:country":"ES",
    "sg:address":"Rbla San Julian (de), 40",
    "sg:city":"Teruel",
    "sg:orig_category":"Droguer\u00cdas (al Por Menor)",
    "sg:phone":"+34 978 60 39 52",
    "sg:postcode":"44003",
    "sg:province":"Teruel",
    "wof:name":"Pinturas Godi S.a.",
    "wof:placetype":"venue"
},
  "geometry": {"coordinates":[-1.102560997,40.3414611816],"type":"Point"}
}