{
  "type": "Feature",
  "properties": {
    "addr:full":"Calle de San Francisco, 16 Monzon Huesca 22400",
    "addr:housenumber":"16",
    "addr:postcode":"22400",
    "addr:street":"Calle De San Francisco",
    "iso:country":"ES",
    "sg:address":"Calle de San Francisco, 16",
    "sg:city":"Monzon",
    "sg:orig_category":"T\u00c9cnicos Veterinarios",
    "sg:phone":"+34 974 40 06 45",
    "sg:postcode":"22400",
    "sg:province":"Huesca",
    "wof:name":"Nafria Burriel Maria Jose",
    "wof:placetype":"venue"
},
  "geometry": {"coordinates":[0.1936129928,41.9108123779],"type":"Point"}
}