{
  "type": "Feature",
  "properties": {
    "addr:full":"Avda De La Libertad, 53 Vinaros Castell\u00f3n 12500",
    "addr:housenumber":"53",
    "addr:postcode":"12500",
    "addr:street":"Avda De La Libertad",
    "iso:country":"ES",
    "sg:address":"Avda De La Libertad, 53",
    "sg:city":"Vinaros",
    "sg:orig_category":"Molduras, Junquillos, Listones Y Molduras Perforadas",
    "sg:phone":"+34 964 45 63 84",
    "sg:postcode":"12500",
    "sg:province":"Castell\u00f3n",
    "wof:name":"Hermanos Prados Cdad",
    "wof:placetype":"venue"
},
  "geometry": {"coordinates":[0.4749450088,40.4711990356],"type":"Point"}
}