{
  "type": "Feature",
  "properties": {
    "addr:full":"Av La Segarra, 20 Cervera Lleida 25200",
    "addr:housenumber":"20",
    "addr:postcode":"25200",
    "addr:street":"Av La Segarra",
    "iso:country":"ES",
    "sg:address":"Av La Segarra, 20",
    "sg:city":"Cervera",
    "sg:orig_category":"Zapatos (al Por Menor)",
    "sg:phone":"+34 973 53 08 18",
    "sg:postcode":"25200",
    "sg:province":"Lleida",
    "wof:name":"Esteve Teixe Zacarias",
    "wof:placetype":"venue"
},
  "geometry": {"coordinates":[1.2788909674,41.6759490967],"type":"Point"}
}