{
  "type": "Feature",
  "properties": {
    "addr:full":"Calle de San Patricio, 1 Madrid Madrid 28019",
    "addr:housenumber":"1",
    "addr:postcode":"28019",
    "addr:street":"Calle De San",
    "iso:country":"ES",
    "sg:address":"Calle de San Patricio, 1",
    "sg:city":"Madrid",
    "sg:orig_category":"Carnicer\u00cdas, Carnicer\u00cdas",
    "sg:phone":"+34 914 72 92 99",
    "sg:postcode":"28019",
    "sg:province":"Madrid",
    "wof:name":"Sanchez Sanchez Juan",
    "wof:placetype":"venue"
},
  "geometry": {"coordinates":[-3.7252020836,40.3918647766],"type":"Point"}
}