{
  "type": "Feature",
  "properties": {
    "iso:country":"ES",
    "sg:address":"Ctra Llacuna (de La), 9",
    "sg:city":"Santa Coloma De Queralt",
    "sg:orig_category":"Asilos De Ancianos. Centros Privados",
    "sg:phone":"+34 977 88 12 48",
    "sg:postcode":"43420",
    "sg:province":"Tarragona",
    "wof:name":"Carmelitas Misioneras Provincia Virgen Del Carmen Curia Provincial",
    "wof:placetype":"venue"
},
  "geometry": {"coordinates":[1.3844230175,41.5353088379],"type":"Point"}
}