{
  "type": "Feature",
  "properties": {
    "iso:country":"ES",
    "sg:address":"Calle de Rufino Sanchez, 21",
    "sg:city":"Matas-pinar-monte Rozas",
    "sg:orig_category":"Productos Qu\u00cdmicos (fabricaci\u00d3n, Al Por Mayor)",
    "sg:phone":"+34 916 30 49 92",
    "sg:postcode":"28290",
    "sg:province":"Madrid",
    "wof:name":"Clan Productos Quimicos S.l.",
    "wof:placetype":"venue"
},
  "geometry": {"coordinates":[-3.8961551189,40.5542259216],"type":"Point"}
}