{
  "type": "Feature",
  "properties": {
    "addr:full":"Calle de San Roque (de), 16 Colmenar Oreja Madrid 28380",
    "addr:postcode":"28380",
    "addr:street":"Calle De",
    "iso:country":"ES",
    "sg:address":"Calle de San Roque (de), 16",
    "sg:city":"Colmenar Oreja",
    "sg:orig_category":"Agricultores, Agricultores",
    "sg:phone":"+34 918 94 31 77",
    "sg:postcode":"28380",
    "sg:province":"Madrid",
    "wof:name":"Guerrero Castillo Angel",
    "wof:placetype":"venue"
},
  "geometry": {"coordinates":[-3.38519907,40.1097373962],"type":"Point"}
}