{
  "type": "Feature",
  "properties": {
    "addr:full":"Calle de Rio Jucar (del), 11 San Sebastian De Los Reyes Madrid 28700",
    "addr:housenumber":"11",
    "addr:postcode":"28700",
    "addr:street":"Calle De Rio Jucar Del",
    "iso:country":"ES",
    "sg:address":"Calle de Rio Jucar (del), 11",
    "sg:city":"San Sebastian De Los Reyes",
    "sg:orig_category":"Zapatos (al Por Menor)",
    "sg:phone":"+34 916 52 01 84",
    "sg:postcode":"28700",
    "sg:province":"Madrid",
    "wof:name":"Bravo Arias Flor Maria",
    "wof:placetype":"venue"
},
  "geometry": {"coordinates":[-3.6299219131,40.5464324951],"type":"Point"}
}