{
  "type": "Feature",
  "properties": {
    "iso:country":"ES",
    "sg:address":"Carrer de Francesc Layret, 7",
    "sg:city":"Cornella Llobregat",
    "sg:orig_category":"Empresas De Limpieza",
    "sg:phone":"+34 933 77 18 94",
    "sg:postcode":"08940",
    "sg:province":"Barcelona",
    "wof:name":"Rodriguez Suarez Enrique Domingo",
    "wof:placetype":"venue"
},
  "geometry": {"coordinates":[2.0708940029,41.3559417725],"type":"Point"}
}