{
  "type": "Feature",
  "properties": {
    "iso:country":"ES",
    "sg:address":"Avda Doctor Mara\u00d1on, 8",
    "sg:city":"Puerto De Santa Maria",
    "sg:orig_category":"Electrodom\u00c9sticos (al Por Menor)",
    "sg:phone":"+34 956 87 21 14",
    "sg:postcode":"11500",
    "sg:province":"C\u00e1diz",
    "wof:name":"Sherry Cocinas S.l.",
    "wof:placetype":"venue"
},
  "geometry": {"coordinates":[-6.2405200005,36.596698761],"type":"Point"}
}