{
  "type": "Feature",
  "properties": {
    "iso:country":"ES",
    "sg:address":"Calle de Movinda, 1",
    "sg:city":"Madrid",
    "sg:orig_category":"Molduras, Junquillos, Listones Y Molduras Perforadas",
    "sg:phone":"+34 913 93 04 39",
    "sg:postcode":"28037",
    "sg:province":"Madrid",
    "wof:name":"Lopez Barrero Felisa",
    "wof:placetype":"venue"
},
  "geometry": {"coordinates":[-3.6372170448,40.4373817444],"type":"Point"}
}