{
  "type": "Feature",
  "properties": {
    "addr:full":"Cmno Casta\u00d1os (somio), 172 Gijon Asturias 33203",
    "addr:housenumber":"172",
    "addr:postcode":"33203",
    "addr:street":"Cmno Castan\u0303Os Somio",
    "iso:country":"ES",
    "sg:address":"Cmno Casta\u00d1os (somio), 172",
    "sg:city":"Gijon",
    "sg:orig_category":"Asilos De Ancianos. Centros Privados",
    "sg:phone":"+34 985 33 06 07",
    "sg:postcode":"33203",
    "sg:province":"Asturias",
    "wof:name":"Ojedasmar S.l.",
    "wof:placetype":"venue"
},
  "geometry": {"coordinates":[-5.5962839127,43.5261116028],"type":"Point"}
}