{
  "type": "Feature",
  "properties": {
    "addr:full":"Canigo(mata), 25 Porqueres Girona 17834",
    "addr:housenumber":"25",
    "addr:postcode":"17834",
    "addr:street":"Mata",
    "iso:country":"ES",
    "sg:address":"Canigo(mata), 25",
    "sg:city":"Porqueres",
    "sg:orig_category":"Venta, Alquiler De Instrumentos Y Accesorios De M\u00dasica",
    "sg:phone":"+34 972 57 08 33",
    "sg:postcode":"17834",
    "sg:province":"Girona",
    "wof:name":"Guitarres Camps S.l.",
    "wof:placetype":"venue"
},
  "geometry": {"coordinates":[2.764480114,42.0982017517],"type":"Point"}
}