{
  "type": "Feature",
  "properties": {
    "addr:full":"Carr Joan Castello, 2 Eivissa Islas Baleares 07800",
    "addr:housenumber":"2",
    "addr:postcode":"07800",
    "addr:street":"Carr Joan Castello",
    "iso:country":"ES",
    "sg:address":"Carr Joan Castello, 2",
    "sg:city":"Eivissa",
    "sg:orig_category":"Pr\u00c1ctica De Vela, Navegaci\u00d3n Y Deportes N\u00c1uticos Y Acu\u00c1ticos",
    "sg:phone":"+34 971 19 06 80",
    "sg:postcode":"07800",
    "sg:province":"Islas Baleares",
    "wof:name":"Depritt Foncea Jose",
    "wof:placetype":"venue"
},
  "geometry": {"coordinates":[1.4347310066,38.9129104614],"type":"Point"}
}