{
  "type": "Feature",
  "properties": {
    "addr:full":"Calle de Hernan Cortes, 23 Valencia Valencia 46004",
    "addr:housenumber":"23",
    "addr:postcode":"46004",
    "addr:street":"Calle De Hernan Cortes",
    "iso:country":"ES",
    "sg:address":"Calle de Hernan Cortes, 23",
    "sg:city":"Valencia",
    "sg:orig_category":"Agencias De Viajes",
    "sg:phone":"+34 963 53 60 34",
    "sg:postcode":"46004",
    "sg:province":"Valencia",
    "wof:name":"Viajes Iberia S.a.",
    "wof:placetype":"venue"
},
  "geometry": {"coordinates":[-0.3709299862,39.4678268433],"type":"Point"}
}