{
  "type": "Feature",
  "properties": {
    "addr:full":"Calle de Alvaro Florez Estrada, 15 Oviedo Asturias 33006",
    "addr:housenumber":"15",
    "addr:postcode":"33006",
    "addr:street":"Calle De Alvaro Florez Estrada",
    "iso:country":"ES",
    "sg:address":"Calle de Alvaro Florez Estrada, 15",
    "sg:city":"Oviedo",
    "sg:orig_category":"Bazares, Art\u00cdculos De Limpieza Y De Cocina (al Por Menor)",
    "sg:phone":"+34 985 25 54 05",
    "sg:postcode":"33006",
    "sg:province":"Asturias",
    "wof:name":"Vega Alvarez Asuncion De La",
    "wof:placetype":"venue"
},
  "geometry": {"coordinates":[-5.8607897758,43.3561477661],"type":"Point"}
}