{
  "type": "Feature",
  "properties": {
    "addr:full":"Carr Barris I Buixo, 7 Palafrugell Girona 17200",
    "addr:housenumber":"7",
    "addr:postcode":"17200",
    "addr:street":"Carr Barris I Buixo",
    "iso:country":"ES",
    "sg:address":"Carr Barris I Buixo, 7",
    "sg:city":"Palafrugell",
    "sg:orig_category":"Agencias Y Agentes Comerciales, Representantes",
    "sg:phone":"+34 972 30 39 67",
    "sg:postcode":"17200",
    "sg:province":"Girona",
    "wof:name":"Gou Frigole Pere",
    "wof:placetype":"venue"
},
  "geometry": {"coordinates":[3.1680130959,41.9158172607],"type":"Point"}
}