{
  "type": "Feature",
  "properties": {
    "addr:full":"Calle de Sanchez Pacheco, 48 Madrid Madrid 28002",
    "addr:housenumber":"48",
    "addr:postcode":"madrid;28002",
    "addr:street":"Calle De Sanchez Pacheco",
    "iso:country":"ES",
    "sg:address":"Calle de Sanchez Pacheco, 48",
    "sg:city":"Madrid",
    "sg:orig_category":"Molduras, Junquillos, Listones Y Molduras Perforadas",
    "sg:phone":"+34 914 15 50 11",
    "sg:postcode":"28002",
    "sg:province":"Madrid",
    "wof:name":"Monterrubio Ramos Pedro",
    "wof:placetype":"venue"
},
  "geometry": {"coordinates":[-3.6742198467,40.4471626282],"type":"Point"}
}