{
  "type": "Feature",
  "properties": {
    "iso:country":"ES",
    "sg:address":"Calle de Don Cristian, S/n",
    "sg:city":"Malaga",
    "sg:orig_category":"M\u00c9dicos: Ginecolog\u00cda Y Obstetricia",
    "sg:phone":"+34 952 30 00 99",
    "sg:postcode":"29007",
    "sg:province":"M\u00e1laga",
    "wof:name":"Morales Alvari\u00f1o Hugo Daniel",
    "wof:placetype":"venue"
},
  "geometry": {"coordinates":[-4.4300723076,36.7193565369],"type":"Point"}
}