{
  "type": "Feature",
  "properties": {
    "addr:full":"Avda Santalla De Oscos, 38 Toral De Los Vados Le\u00f3n 24560",
    "addr:housenumber":"38",
    "addr:postcode":"24560",
    "addr:street":"Avda Santalla De Oscos",
    "iso:country":"ES",
    "sg:address":"Avda Santalla De Oscos, 38",
    "sg:city":"Toral De Los Vados",
    "sg:orig_category":"Peluquer\u00cdas, Peluquer\u00cda Mixta",
    "sg:phone":"+34 987 54 50 88",
    "sg:postcode":"24560",
    "sg:province":"Le\u00f3n",
    "wof:name":"Vidal Gonzalez Maria",
    "wof:placetype":"venue"
},
  "geometry": {"coordinates":[-6.7763490677,42.5442085266],"type":"Point"}
}