{
  "type": "Feature",
  "properties": {
    "iso:country":"ES",
    "sg:address":"Avda Pablo Iglesias, 15",
    "sg:city":"Madrid",
    "sg:orig_category":"Madera Para Construcci\u00d3n E Industria",
    "sg:phone":"+34 915 53 77 52",
    "sg:postcode":"28003",
    "sg:province":"Madrid",
    "wof:name":"Ser Gilsanz Jesus Del",
    "wof:placetype":"venue"
},
  "geometry": {"coordinates":[-3.7069249153,40.444934845],"type":"Point"}
}