{
  "type": "Feature",
  "properties": {
    "addr:full":"Calle de Principado, 11 Oviedo Asturias 33007",
    "addr:housenumber":"11",
    "addr:postcode":"33007",
    "addr:street":"Calle De Principado",
    "iso:country":"ES",
    "sg:address":"Calle de Principado, 11",
    "sg:city":"Oviedo",
    "sg:orig_category":"Agentes Generales De Seguros",
    "sg:phone":"+34 985 21 41 58",
    "sg:postcode":"33007",
    "sg:province":"Asturias",
    "wof:name":"Zamanillo Ortega Jose",
    "wof:placetype":"venue"
},
  "geometry": {"coordinates":[-5.8483452797,43.360496521],"type":"Point"}
}