{
  "type": "Feature",
  "properties": {
    "iso:country":"ES",
    "sg:address":"Avda Alfonso X, S/n",
    "sg:city":"Arcos Frontera",
    "sg:orig_category":"Charcuter\u00cdas (al Por Mayor)",
    "sg:phone":"+34 956 70 51 50",
    "sg:postcode":"11630",
    "sg:province":"C\u00e1diz",
    "wof:name":"Carnicas Y Embutidos Sierra Arcense S.l",
    "wof:placetype":"venue"
},
  "geometry": {"coordinates":[-5.7963938713,36.7413253784],"type":"Point"}
}