{
  "type": "Feature",
  "properties": {
    "iso:country":"ES",
    "sg:address":"Carrer de Pla De Balenya, 15",
    "sg:city":"Vic",
    "sg:orig_category":"Peluquer\u00cdas, Peluquer\u00cda Mixta",
    "sg:phone":"+34 938 89 10 06",
    "sg:postcode":"08500",
    "sg:province":"Barcelona",
    "wof:name":"Onoff S.c.p.",
    "wof:placetype":"venue"
},
  "geometry": {"coordinates":[2.2543020248,41.9321174622],"type":"Point"}
}