{
  "type": "Feature",
  "properties": {
    "addr:full":"Carrer de Balmes, 435 Barcelona Barcelona 08022",
    "addr:housenumber":"435",
    "addr:postcode":"08022",
    "addr:street":"Carrer De Balmes",
    "iso:country":"ES",
    "sg:address":"Carrer de Balmes, 435",
    "sg:city":"Barcelona",
    "sg:orig_category":"Inmobiliaria (agencias)",
    "sg:phone":"+34 934 18 51 07",
    "sg:postcode":"08022",
    "sg:province":"Barcelona",
    "wof:name":"De Anzizu Furest Asuncion",
    "wof:placetype":"venue"
},
  "geometry": {"coordinates":[2.1373419762,41.4089279175],"type":"Point"}
}