{
  "type": "Feature",
  "properties": {
    "iso:country":"ES",
    "sg:address":"Calle de Miguel Moreno Masson, 2",
    "sg:city":"Malaga",
    "sg:orig_category":"Estancos",
    "sg:phone":"+34 952 33 36 46",
    "sg:postcode":"29007",
    "sg:province":"M\u00e1laga",
    "wof:name":"Rodriguez Bernal Maria",
    "wof:placetype":"venue"
},
  "geometry": {"coordinates":[-4.442305088,36.7151565552],"type":"Point"}
}