{
  "type": "Feature",
  "properties": {
    "iso:country":"ES",
    "sg:address":"Carrer de Cantabria, 8",
    "sg:city":"Barcelona",
    "sg:orig_category":"Ropa Para Ni\u00d1os (al Por Menor)",
    "sg:phone":"+34 933 13 78 98",
    "sg:postcode":"08020",
    "sg:province":"Barcelona",
    "wof:name":"Martinez Martinez Francisca",
    "wof:placetype":"venue"
},
  "geometry": {"coordinates":[2.2040379047,41.4179420471],"type":"Point"}
}