{
  "type": "Feature",
  "properties": {
    "addr:full":"Calle de Urbieta, 34 Donostia-san Sebastian Guip\u00f9zcoa 20006",
    "addr:housenumber":"34",
    "addr:postcode":"20006",
    "addr:street":"Calle De Urbieta",
    "iso:country":"ES",
    "sg:address":"Calle de Urbieta, 34",
    "sg:city":"Donostia-san Sebastian",
    "sg:orig_category":"Carnicer\u00cdas, Carnicer\u00cdas",
    "sg:phone":"+34 943 45 26 65",
    "sg:postcode":"20006",
    "sg:province":"Guip\u00f9zcoa",
    "sg:website":"www.labarandilla.com",
    "wof:name":"Rotatxa S.l.",
    "wof:placetype":"venue"
},
  "geometry": {"coordinates":[-1.9824630022,43.3162536621],"type":"Point"}
}