{
  "type": "Feature",
  "properties": {
    "addr:full":"Carrer de Lepant, 380 Barcelona Barcelona 08025",
    "addr:housenumber":"380",
    "addr:postcode":"08025",
    "addr:street":"Carrer De Lepant",
    "iso:country":"ES",
    "sg:address":"Carrer de Lepant, 380",
    "sg:city":"Barcelona",
    "sg:orig_category":"Molduras, Junquillos, Listones Y Molduras Perforadas",
    "sg:phone":"+34 933 47 59 17",
    "sg:postcode":"08025",
    "sg:province":"Barcelona",
    "wof:name":"Perez Fernandez Juan",
    "wof:placetype":"venue"
},
  "geometry": {"coordinates":[2.170566082,41.4092216492],"type":"Point"}
}