{
  "type": "Feature",
  "properties": {
    "iso:country":"ES",
    "sg:address":"Carrer de Mercaders (dels), 2",
    "sg:city":"Tortosa",
    "sg:orig_category":"Abogados",
    "sg:phone":"+34 977 44 00 70",
    "sg:postcode":"43500",
    "sg:province":"Tarragona",
    "wof:name":"Ardit Blanch Luzdivina",
    "wof:placetype":"venue"
},
  "geometry": {"coordinates":[0.5217599273,40.8117866516],"type":"Point"}
}