{
  "type": "Feature",
  "properties": {
    "addr:full":"Calle de Quintana, 2 Oviedo Asturias 33009",
    "addr:housenumber":"2",
    "addr:postcode":"33009",
    "addr:street":"Calle De Quintana",
    "iso:country":"ES",
    "sg:address":"Calle de Quintana, 2",
    "sg:city":"Oviedo",
    "sg:orig_category":"Servidores Y Editores De Bases De Datos",
    "sg:phone":"+34 985 21 10 51",
    "sg:postcode":"33009",
    "sg:province":"Asturias",
    "sg:website":"www.cyberastur.com",
    "wof:name":"Cyberastur S.l.",
    "wof:placetype":"venue"
},
  "geometry": {"coordinates":[-5.8465409279,43.3596878052],"type":"Point"}
}