{
  "type": "Feature",
  "properties": {
    "addr:full":"Calle de Maximo Cayon Waldaliso, 16 Le\u00f3n Le\u00f3n 24005",
    "addr:housenumber":"16",
    "addr:postcode":"24005",
    "addr:street":"Calle De Maximo;Waldaliso;Leo\u0301N",
    "iso:country":"ES",
    "sg:address":"Calle de Maximo Cayon Waldaliso, 16",
    "sg:city":"Le\u00f3n",
    "sg:orig_category":"Farmacias",
    "sg:phone":"+34 987 26 33 97",
    "sg:postcode":"24005",
    "sg:province":"Le\u00f3n",
    "wof:name":"Carrasco Fernandez Joaquin",
    "wof:placetype":"venue"
},
  "geometry": {"coordinates":[-5.5685009956,42.5920600891],"type":"Point"}
}