{
  "type": "Feature",
  "properties": {
    "iso:country":"ES",
    "sg:address":"Calle de Carmen Conde, 4",
    "sg:city":"Alcazares",
    "sg:orig_category":"Muebles, Minoristas",
    "sg:phone":"+34 968 17 10 22",
    "sg:postcode":"30710",
    "sg:province":"Murcia",
    "wof:name":"Muebles Murcia C.b.",
    "wof:placetype":"venue"
},
  "geometry": {"coordinates":[-0.8595167994,37.7381515503],"type":"Point"}
}