{
  "type": "Feature",
  "properties": {
    "addr:full":"Carrer de Bonavista, 80 S. Just Desvern Barcelona 08960",
    "addr:housenumber":"80",
    "addr:postcode":"08960",
    "addr:street":"Carrer De Bonavista",
    "iso:country":"ES",
    "sg:address":"Carrer de Bonavista, 80",
    "sg:city":"S. Just Desvern",
    "sg:orig_category":"Fabricaci\u00d3n, Importaci\u00d3n De L\u00c1mparas Y Bombillas",
    "sg:phone":"+34 933 71 11 86",
    "sg:postcode":"08960",
    "sg:province":"Barcelona",
    "wof:name":"Asgalux S.l.",
    "wof:placetype":"venue"
},
  "geometry": {"coordinates":[2.077009201,41.3840179443],"type":"Point"}
}