{
  "type": "Feature",
  "properties": {
    "addr:full":"Ptda Inmediaciones, S/n S. Vicente Raspeig Alicante 03690",
    "addr:housenumber":"s",
    "addr:postcode":"03690",
    "addr:street":"Ptda Inmediaciones;/ N S. Vicente Raspeig",
    "iso:country":"ES",
    "sg:address":"Ptda Inmediaciones, S/n",
    "sg:city":"S. Vicente Raspeig",
    "sg:orig_category":"Cementerios",
    "sg:phone":"+34 965 66 03 45",
    "sg:postcode":"03690",
    "sg:province":"Alicante",
    "wof:name":"Ajuntament De San Vicent Del Raspeig",
    "wof:placetype":"venue"
},
  "geometry": {"coordinates":[-0.5111595988,38.4068145752],"type":"Point"}
}