{
  "type": "Feature",
  "properties": {
    "addr:full":"Avda Moratalaz, 123 Madrid Madrid 28030",
    "addr:housenumber":"123",
    "addr:postcode":"28030",
    "addr:street":"Avda Moratalaz",
    "iso:country":"ES",
    "sg:address":"Avda Moratalaz, 123",
    "sg:city":"Madrid",
    "sg:orig_category":"Electrodom\u00c9sticos (al Por Menor)",
    "sg:phone":"+34 914 30 98 11",
    "sg:postcode":"28030",
    "sg:province":"Madrid",
    "sg:website":"www.expert.es",
    "wof:name":"Sociedad Promotora Y Distribuidora De Electrodomesticos Ramon 2000 S.a.",
    "wof:placetype":"venue"
},
  "geometry": {"coordinates":[-3.6504929066,40.4061317444],"type":"Point"}
}