{
  "type": "Feature",
  "properties": {
    "iso:country":"ES",
    "sg:address":"Calle de Fernando Macias, 25",
    "sg:city":"Coru\u00d1a",
    "sg:orig_category":"Sociedades, Compa\u00d1\u00cdas Aseguradoras",
    "sg:phone":"+34 981 25 39 37",
    "sg:postcode":"15004",
    "sg:province":"La Coru\u00f1a",
    "wof:name":"Almudena Compa\u00d1ia De Seguros S.a.",
    "wof:placetype":"venue"
},
  "geometry": {"coordinates":[-8.4127159119,43.3662376404],"type":"Point"}
}