{
  "type": "Feature",
  "properties": {
    "addr:full":"Crucero De Valdomar, 11 Corcubion La Coru\u00f1a 15130",
    "addr:housenumber":"11",
    "addr:postcode":"15130",
    "addr:street":"Valdomar;La Corun\u0303A",
    "iso:country":"ES",
    "sg:address":"Crucero De Valdomar, 11",
    "sg:city":"Corcubion",
    "sg:orig_category":"Empresarios Y Productoras De Espect\u00c1culos",
    "sg:phone":"+34 981 74 50 46",
    "sg:postcode":"15130",
    "sg:province":"La Coru\u00f1a",
    "wof:name":"Abelleira Ronquete Miguel Angel",
    "wof:placetype":"venue"
},
  "geometry": {"coordinates":[-9.198213,42.928112],"type":"Point"}
}