{
  "type": "Feature",
  "properties": {
    "addr:full":"Calle de Balmes, 5 Onda Castell\u00f3n 12200",
    "addr:housenumber":"5",
    "addr:postcode":"12200",
    "addr:street":"Calle De Balmes;Castello\u0301N",
    "iso:country":"ES",
    "sg:address":"Calle de Balmes, 5",
    "sg:city":"Onda",
    "sg:orig_category":"Molduras, Junquillos, Listones Y Molduras Perforadas",
    "sg:phone":"+34 964 60 30 19",
    "sg:postcode":"12200",
    "sg:province":"Castell\u00f3n",
    "wof:name":"Rodriguez Garcia Francisco",
    "wof:placetype":"venue"
},
  "geometry": {"coordinates":[-0.2677161098,39.963092804],"type":"Point"}
}