{
  "type": "Feature",
  "properties": {
    "addr:full":"Pol Ind Nevero, 48 Badajoz Badajoz 06006",
    "addr:housenumber":"48",
    "addr:postcode":"06006",
    "addr:street":"Nevero",
    "iso:country":"ES",
    "sg:address":"Pol Ind Nevero, 48",
    "sg:city":"Badajoz",
    "sg:orig_category":"Bebidas",
    "sg:phone":"+34 924 27 23 24",
    "sg:postcode":"06006",
    "sg:province":"Badajoz",
    "wof:name":"Compa\u00d1ia De Bebidas Pepsico S.l.",
    "wof:placetype":"venue"
},
  "geometry": {"coordinates":[-7.0317192078,38.9165992737],"type":"Point"}
}