{
  "type": "Feature",
  "properties": {
    "addr:full":"Papabellotas (p I Antequera), 6 Antequera M\u00e1laga 29200",
    "addr:housenumber":"6",
    "addr:postcode":"29200",
    "addr:street":"Papabellotas;Antequera",
    "iso:country":"ES",
    "sg:address":"Papabellotas (p I Antequera), 6",
    "sg:city":"Antequera",
    "sg:orig_category":"Quincaller\u00cda (al Por Menor)",
    "sg:phone":"+34 952 84 64 15",
    "sg:postcode":"29200",
    "sg:province":"M\u00e1laga",
    "wof:name":"Ferreteria Linde S.l.",
    "wof:placetype":"venue"
},
  "geometry": {"coordinates":[-4.5316109657,37.0313224792],"type":"Point"}
}