{
  "type": "Feature",
  "properties": {
    "addr:full":"Zerkaosteta Kalea, 17 Arrasate Guip\u00f9zcoa 20500",
    "addr:housenumber":"17",
    "addr:postcode":"20500",
    "addr:street":"Zerkaosteta Kalea;Guipu\u0300Zcoa",
    "iso:country":"ES",
    "sg:address":"Zerkaosteta Kalea, 17",
    "sg:city":"Arrasate",
    "sg:orig_category":"Cl\u00cdnicas Dentales",
    "sg:phone":"+34 943 77 09 40",
    "sg:postcode":"20500",
    "sg:province":"Guip\u00f9zcoa",
    "wof:name":"Ardent, S.l.",
    "wof:placetype":"venue"
},
  "geometry": {"coordinates":[-2.4908812046,43.0648193359],"type":"Point"}
}