{
  "type": "Feature",
  "properties": {
    "addr:full":"Calle de Legion Espa\u00d1ola, 4 Burgos Burgos 09001",
    "addr:housenumber":"4",
    "addr:postcode":"09001",
    "addr:street":"Calle De Legion Espan\u0303Ola",
    "iso:country":"ES",
    "sg:address":"Calle de Legion Espa\u00d1ola, 4",
    "sg:city":"Burgos",
    "sg:orig_category":"Carnicer\u00cdas, Carnicer\u00cdas",
    "sg:phone":"+34 947 20 59 86",
    "sg:postcode":"09001",
    "sg:province":"Burgos",
    "wof:name":"Frias Lara Leoncio",
    "wof:placetype":"venue"
},
  "geometry": {"coordinates":[-3.6986670494,42.3331336975],"type":"Point"}
}