{
  "type": "Feature",
  "properties": {
    "iso:country":"ES",
    "sg:address":"Av Cami De Mao, 179",
    "sg:city":"Ciutadella Menorca",
    "sg:orig_category":"Agentes, Concesionarios Y Sucursales De Veh\u00cdculos",
    "sg:phone":"+34 971 48 40 38",
    "sg:postcode":"07760",
    "sg:province":"Islas Baleares",
    "wof:name":"Auto-freno Oliver S. A.",
    "wof:placetype":"venue"
},
  "geometry": {"coordinates":[3.8416149616,40.0027542114],"type":"Point"}
}