{
  "type": "Feature",
  "properties": {
    "iso:country":"ES",
    "sg:address":"Calle de Periodista Llorente, 10",
    "sg:city":"Valencia",
    "sg:orig_category":"Empresas De Carpinter\u00cda Met\u00c1lica",
    "sg:phone":"+34 963 49 86 44",
    "sg:postcode":"46009",
    "sg:province":"Valencia",
    "wof:name":"Olivares Lara Matias",
    "wof:placetype":"venue"
},
  "geometry": {"coordinates":[-0.3822189867,39.4849662781],"type":"Point"}
}