{
  "type": "Feature",
  "properties": {
    "iso:country":"ES",
    "sg:address":"Calle de Carniceria, 11",
    "sg:city":"Torredelcampo",
    "sg:orig_category":"Agencias De Viajes",
    "sg:phone":"+34 953 41 50 14",
    "sg:postcode":"23640",
    "sg:province":"Ja\u00e9n",
    "wof:name":"Jimenez Rico Manuel",
    "wof:placetype":"venue"
},
  "geometry": {"coordinates":[-3.8969526291,37.7713165283],"type":"Point"}
}