{
  "type": "Feature",
  "properties": {
    "addr:full":"Barr Molladar, S/n Cartes Cantabria 39311",
    "addr:housenumber":"s / n",
    "addr:postcode":"39311",
    "iso:country":"ES",
    "sg:address":"Barr Molladar, S/n",
    "sg:city":"Cartes",
    "sg:orig_category":"Supermercados Y Hipermercados",
    "sg:phone":"+34 942 81 92 16",
    "sg:postcode":"39311",
    "sg:province":"Cantabria",
    "wof:name":"Semark Group Sa",
    "wof:placetype":"venue"
},
  "geometry": {"coordinates":[-4.0697689056,43.3193817139],"type":"Point"}
}