{
  "type": "Feature",
  "properties": {
    "addr:full":"Calle de Sierra De Las Nieves, 3 Rincon Victoria M\u00e1laga 29730",
    "addr:housenumber":"3",
    "addr:postcode":"29730",
    "addr:street":"Calle De Sierra De Las Nieves;Ma\u0301Laga",
    "iso:country":"ES",
    "sg:address":"Calle de Sierra De Las Nieves, 3",
    "sg:city":"Rincon Victoria",
    "sg:orig_category":"Hielo Artificial (fabricaci\u00d3n, Distribuci\u00d3n)",
    "sg:phone":"+34 952 97 14 07",
    "sg:postcode":"29730",
    "sg:province":"M\u00e1laga",
    "wof:name":"Congelados Global S.c.",
    "wof:placetype":"venue"
},
  "geometry": {"coordinates":[-4.2807641029,36.714641571],"type":"Point"}
}