{
  "type": "Feature",
  "properties": {
    "iso:country":"ES",
    "sg:address":"Ctra Peguerinos (de), Km. 0002,0",
    "sg:city":"Navas Del Marques",
    "sg:orig_category":"Construcciones Met\u00c1licas",
    "sg:phone":"+34 918 97 01 85",
    "sg:postcode":"05230",
    "sg:province":"\u00c1vila",
    "wof:name":"Estructu-fer S&p Sl",
    "wof:placetype":"venue"
},
  "geometry": {"coordinates":[-4.3370528221,40.5976829529],"type":"Point"}
}