{
  "type": "Feature",
  "properties": {
    "addr:full":"Carr Silla, S/n Alcasser Valencia 46290",
    "addr:housenumber":"s / n",
    "addr:postcode":"46290",
    "addr:street":"Carr Silla",
    "iso:country":"ES",
    "sg:address":"Carr Silla, S/n",
    "sg:city":"Alcasser",
    "sg:orig_category":"Empresas De Pintura Y Revestimientos",
    "sg:phone":"+34 961 23 32 42",
    "sg:postcode":"46290",
    "sg:province":"Valencia",
    "wof:name":"Ondeco S. L.",
    "wof:placetype":"venue"
},
  "geometry": {"coordinates":[-0.443524003,39.3689994812],"type":"Point"}
}