{
  "type": "Feature",
  "properties": {
    "iso:country":"ES",
    "sg:address":"Calle de Castellvi, 8",
    "sg:city":"Zaragoza",
    "sg:orig_category":"Fabricaci\u00d3n De Su\u00c9ters Y Chalecos De Punto",
    "sg:phone":"+34 976 23 93 57",
    "sg:postcode":"50004",
    "sg:province":"Zaragoza",
    "wof:name":"Torralba Braulio Anunciacion",
    "wof:placetype":"venue"
},
  "geometry": {"coordinates":[-0.8891379833,41.6483345032],"type":"Point"}
}