{
  "type": "Feature",
  "properties": {
    "iso:country":"ES",
    "sg:address":"Carrer de Marti I Blasi, 79",
    "sg:city":"Hospitalet Llobregat",
    "sg:orig_category":"Molduras, Junquillos, Listones Y Molduras Perforadas",
    "sg:phone":"+34 934 47 17 51",
    "sg:postcode":"08905",
    "sg:province":"Barcelona",
    "wof:name":"Gonzalez Vargas Olga",
    "wof:placetype":"venue"
},
  "geometry": {"coordinates":[2.1123950481,41.3713874817],"type":"Point"}
}