{
  "type": "Feature",
  "properties": {
    "addr:full":"Pg Terraple, 40 Molins Rei Barcelona 08750",
    "addr:housenumber":"40",
    "addr:postcode":"08750",
    "addr:street":"Pg Terraple;Barcelona",
    "iso:country":"ES",
    "sg:address":"Pg Terraple, 40",
    "sg:city":"Molins Rei",
    "sg:orig_category":"Arquitectos",
    "sg:phone":"+34 936 80 25 72",
    "sg:postcode":"08750",
    "sg:province":"Barcelona",
    "wof:name":"Bermudez Garcia Juan Manuel",
    "wof:placetype":"venue"
},
  "geometry": {"coordinates":[2.0153079033,41.4120521545],"type":"Point"}
}