{
  "type": "Feature",
  "properties": {
    "iso:country":"ES",
    "sg:address":"Urb. Atalaya Alta, 6",
    "sg:city":"Estepona",
    "sg:orig_category":"Inversiones",
    "sg:phone":"+34 952 89 68 44",
    "sg:postcode":"29680",
    "sg:province":"M\u00e1laga",
    "wof:name":"Galta Inversiones S.l.",
    "wof:placetype":"venue"
},
  "geometry": {"coordinates":[-5.1452140808,36.4275817871],"type":"Point"}
}