{
  "type": "Feature",
  "properties": {
    "addr:full":"Avda Orense, 6 Marin Pontevedra 36900",
    "addr:housenumber":"6",
    "addr:postcode":"36900",
    "addr:street":"Avda Orense",
    "iso:country":"ES",
    "sg:address":"Avda Orense, 6",
    "sg:city":"Marin",
    "sg:orig_category":"Navegaci\u00d3n (equipos Fluviales)",
    "sg:phone":"+34 986 89 16 88",
    "sg:postcode":"36900",
    "sg:province":"Pontevedra",
    "wof:name":"Pesqueras Pardavila S.a.",
    "wof:placetype":"venue"
},
  "geometry": {"coordinates":[-8.6983156204,42.3930206299],"type":"Point"}
}