{
  "type": "Feature",
  "properties": {
    "addr:full":"Calle de Diaz Bravo, 22 Tudela Navarra 31500",
    "addr:housenumber":"22",
    "addr:postcode":"31500",
    "addr:street":"Calle De Diaz Bravo",
    "iso:country":"ES",
    "sg:address":"Calle de Diaz Bravo, 22",
    "sg:city":"Tudela",
    "sg:orig_category":"Muebles, Minoristas",
    "sg:phone":"+34 948 82 04 53",
    "sg:postcode":"31500",
    "sg:province":"Navarra",
    "wof:name":"Isidro Francisco Javier Madurga Perez Y Maria Jesus Vallejo Herreros S.cv.",
    "wof:placetype":"venue"
},
  "geometry": {"coordinates":[-1.6103576422,42.0604515076],"type":"Point"}
}