{
  "type": "Feature",
  "properties": {
    "addr:full":"Plg Cabanillas, 1 Guadalajara Guadalajara 19004",
    "addr:housenumber":"1",
    "addr:postcode":"19004",
    "addr:street":"Plg Cabanillas",
    "iso:country":"ES",
    "sg:address":"Plg Cabanillas, 1",
    "sg:city":"Guadalajara",
    "sg:orig_category":"Contenedores (mercanc\u00cdas)",
    "sg:phone":"+34 949 20 06 63",
    "sg:postcode":"19004",
    "sg:province":"Guadalajara",
    "wof:name":"J.l. Chicharro Transportes S.l.",
    "wof:placetype":"venue"
},
  "geometry": {"coordinates":[-3.1641490459,40.6297950745],"type":"Point"}
}