{
  "type": "Feature",
  "properties": {
    "addr:full":"O Cristal, 40 Vilanova Dos Infantes Ourense 32829",
    "addr:postcode":"32829",
    "iso:country":"ES",
    "sg:address":"O Cristal, 40",
    "sg:city":"Vilanova Dos Infantes",
    "sg:orig_category":"Empresas De Impermeabilizaci\u00d3n",
    "sg:phone":"+34 988 45 11 52",
    "sg:postcode":"32829",
    "sg:province":"Ourense",
    "wof:name":"Grupo Antolin Instalaciones S.l.",
    "wof:placetype":"venue"
},
  "geometry": {"coordinates":[-7.866109848,42.3389396667],"type":"Point"}
}