{
  "type": "Feature",
  "properties": {
    "addr:full":"Rond Poniente (de), 2 Tres Cantos Madrid 28760",
    "addr:housenumber":"2",
    "addr:postcode":"28760",
    "addr:street":"Rond Poniente De",
    "iso:country":"ES",
    "sg:address":"Rond Poniente (de), 2",
    "sg:city":"Tres Cantos",
    "sg:orig_category":"M\u00c9dicos: Estomatolog\u00cda",
    "sg:phone":"+34 918 04 30 14",
    "sg:postcode":"28760",
    "sg:province":"Madrid",
    "wof:name":"Cova Flores Mercedes",
    "wof:placetype":"venue"
},
  "geometry": {"coordinates":[-3.7157409191,40.6018371582],"type":"Point"}
}