{
  "type": "Feature",
  "properties": {
    "iso:country":"ES",
    "sg:address":"Cra. Peramola, S/n",
    "sg:city":"Oliana",
    "sg:orig_category":"Estudios Y Construcci\u00d3n De Acuarios Y Viveros",
    "sg:phone":"+34 973 46 30 17",
    "sg:postcode":"25790",
    "sg:province":"Lleida",
    "wof:name":"Truchas Del Segre S. A.",
    "wof:placetype":"venue"
},
  "geometry": {"coordinates":[1.3136800528,42.0673789978],"type":"Point"}
}