{
  "type": "Feature",
  "properties": {
    "addr:full":"Calle de Arevalo Lara, 60 Madrid Madrid 28027",
    "addr:housenumber":"60",
    "addr:postcode":"madrid;28027",
    "addr:street":"Calle De;Lara",
    "iso:country":"ES",
    "sg:address":"Calle de Arevalo Lara, 60",
    "sg:city":"Madrid",
    "sg:orig_category":"Asesor\u00cda Sobre Comunicaci\u00d3n De Empresas",
    "sg:phone":"+34 917 42 24 60",
    "sg:postcode":"28027",
    "sg:province":"Madrid",
    "wof:name":"Prediccion Y Coyuntura S.l.",
    "wof:placetype":"venue"
},
  "geometry": {"coordinates":[-3.6323213577,40.4424438477],"type":"Point"}
}