{
  "type": "Feature",
  "properties": {
    "iso:country":"ES",
    "sg:address":"Calle de Larragana, 12",
    "sg:city":"Vitoria-gasteiz",
    "sg:orig_category":"Inform\u00c1tica, Ofim\u00c1tica (estudios, Asesor\u00cda, Ingenier\u00cda, Formaci\u00d3n)",
    "sg:phone":"+34 945 12 33 80",
    "sg:postcode":"01013",
    "sg:province":"\u00c1lava",
    "sg:website":"www.datavi.com",
    "wof:name":"Datavi Sistemas S.l.",
    "wof:placetype":"venue"
},
  "geometry": {"coordinates":[-2.6502990723,42.867275238],"type":"Point"}
}