{
  "type": "Feature",
  "properties": {
    "addr:full":"Carrer de Roca Llarga, 27 Santa Margarida-salatar Girona 17480",
    "addr:housenumber":"27",
    "addr:postcode":"17480",
    "addr:street":"Carrer De Roca Llarga",
    "iso:country":"ES",
    "sg:address":"Carrer de Roca Llarga, 27",
    "sg:city":"Santa Margarida-salatar",
    "sg:orig_category":"Comercio, Reparaci\u00d3n De Bicicletas, De Motocicletas, De Accesorios",
    "sg:phone":"+34 972 25 39 26",
    "sg:postcode":"17480",
    "sg:province":"Girona",
    "wof:name":"Mu\u00f1oz Lopez Isabel",
    "wof:placetype":"venue"
},
  "geometry": {"coordinates":[3.1517300606,42.2628211975],"type":"Point"}
}