{
  "type": "Feature",
  "properties": {
    "iso:country":"ES",
    "sg:address":"Carrer de Bolos, 12",
    "sg:city":"Olot",
    "sg:orig_category":"Motocicletas (agentes, Concesionarios)",
    "sg:phone":"+34 972 26 04 49",
    "sg:postcode":"17800",
    "sg:province":"Girona",
    "wof:name":"Serra Moto S.l.",
    "wof:placetype":"venue"
},
  "geometry": {"coordinates":[2.4838199615,42.1825752258],"type":"Point"}
}