{
  "type": "Feature",
  "properties": {
    "iso:country":"ES",
    "sg:address":"Avda Constitucion (de La), 3",
    "sg:city":"Adrada",
    "sg:orig_category":"Peluquer\u00cdas, Peluquer\u00cda Mixta",
    "sg:phone":"+34 918 67 02 05",
    "sg:postcode":"05430",
    "sg:province":"\u00c1vila",
    "wof:name":"Garcia Ruiz Inmaculada",
    "wof:placetype":"venue"
},
  "geometry": {"coordinates":[-4.6346211433,40.3030357361],"type":"Point"}
}