{
  "type": "Feature",
  "properties": {
    "iso:country":"ES",
    "sg:address":"Pg Maritim, 211",
    "sg:city":"Castelldefels",
    "sg:orig_category":"Bazares, Art\u00cdculos De Limpieza Y De Cocina (al Por Menor)",
    "sg:phone":"+34 936 65 52 04",
    "sg:postcode":"08860",
    "sg:province":"Barcelona",
    "wof:name":"Fernandez Gomez Maria Ines",
    "wof:placetype":"venue"
},
  "geometry": {"coordinates":[1.9702860117,41.2658996582],"type":"Point"}
}