{
  "type": "Feature",
  "properties": {
    "addr:full":"Ctra Guipuzcoa, S/n Berrioplano Navarra 31195",
    "addr:housenumber":"s",
    "addr:postcode":"31195",
    "addr:street":"Ctra Guipuzcoa;/ N",
    "iso:country":"ES",
    "sg:address":"Ctra Guipuzcoa, S/n",
    "sg:city":"Berrioplano",
    "sg:orig_category":"Abrasivos Y Superabrasivos (fabricaci\u00d3n, Al Por Mayor)",
    "sg:phone":"+34 948 30 60 00",
    "sg:postcode":"31195",
    "sg:province":"Navarra",
    "wof:name":"Saint Gobain Abrasivos S.a.",
    "wof:placetype":"venue"
},
  "geometry": {"coordinates":[-1.6856540442,42.8458709717],"type":"Point"}
}