{
  "type": "Feature",
  "properties": {
    "iso:country":"ES",
    "sg:address":"Avda Algorta, 98",
    "sg:city":"Algorta",
    "sg:orig_category":"Ense\u00d1anza, Formaci\u00d3n Profesional: Aprendizaje",
    "sg:phone":"+34 944 60 79 47",
    "sg:postcode":"48991",
    "sg:province":"Vizcaya",
    "wof:name":"Ayuntamiento De Getxo",
    "wof:placetype":"venue"
},
  "geometry": {"coordinates":[-3.0117828846,43.3498840332],"type":"Point"}
}