{
  "type": "Feature",
  "properties": {
    "iso:country":"ES",
    "sg:address":"Calle de Cami Real, 113",
    "sg:city":"Sagunt",
    "sg:orig_category":"Asociaciones Ecologistas",
    "sg:phone":"+34 962 66 10 46",
    "sg:postcode":"46500",
    "sg:province":"Valencia",
    "wof:name":"Acequia Mayor De Sagunto",
    "wof:placetype":"venue"
},
  "geometry": {"coordinates":[-0.2730447948,39.6784057617],"type":"Point"}
}