{
  "type": "Feature",
  "properties": {
    "addr:full":"Calle de Rio Duerna, 2 Astorga Le\u00f3n 24700",
    "addr:housenumber":"2",
    "addr:postcode":"24700",
    "addr:street":"Calle De Rio Duerna;Leo\u0301N",
    "iso:country":"ES",
    "sg:address":"Calle de Rio Duerna, 2",
    "sg:city":"Astorga",
    "sg:orig_category":"Empresas De Carpinter\u00cda Met\u00c1lica",
    "sg:phone":"+34 987 61 83 10",
    "sg:postcode":"24700",
    "sg:province":"Le\u00f3n",
    "wof:name":"Calvo Garcia Francisco",
    "wof:placetype":"venue"
},
  "geometry": {"coordinates":[-6.061024189,42.4583015442],"type":"Point"}
}