{
  "type": "Feature",
  "properties": {
    "addr:full":"Carr Girona, Km. 0030,0 Besalu Girona 17850",
    "addr:postcode":"17850",
    "addr:street":"Carr Girona Km. 0030,0",
    "iso:country":"ES",
    "sg:address":"Carr Girona, Km. 0030,0",
    "sg:city":"Besalu",
    "sg:orig_category":"Chapister\u00cda",
    "sg:phone":"+34 972 59 02 67",
    "sg:postcode":"17850",
    "sg:province":"Girona",
    "wof:name":"Planas Masbernat Luis",
    "wof:placetype":"venue"
},
  "geometry": {"coordinates":[2.6976718903,42.2003211975],"type":"Point"}
}