{
  "type": "Feature",
  "properties": {
    "addr:full":"Carr Antoni Maura, 22 Pollen\u00e7a Islas Baleares 07460",
    "addr:housenumber":"22",
    "addr:postcode":"07460",
    "addr:street":"Carr Antoni Maura;Islas",
    "iso:country":"ES",
    "sg:address":"Carr Antoni Maura, 22",
    "sg:city":"Pollen\u00e7a",
    "sg:orig_category":"Bisuter\u00cda, Joyer\u00cda, Relojer\u00cda (al Por Menor)",
    "sg:phone":"+34 971 53 37 16",
    "sg:postcode":"07460",
    "sg:province":"Islas Baleares",
    "wof:name":"Bonnin Miralles Francisco Miguel",
    "wof:placetype":"venue"
},
  "geometry": {"coordinates":[3.015750885,39.877166748],"type":"Point"}
}