{
  "type": "Feature",
  "properties": {
    "iso:country":"ES",
    "sg:address":"Rua Antonio Palacios, 42",
    "sg:city":"Porri\u00f1o",
    "sg:orig_category":"Asociaciones Y Clubs Deportivos",
    "sg:phone":"+34 986 33 73 22",
    "sg:postcode":"36400",
    "sg:province":"Pontevedra",
    "wof:name":"Marcisport S.l.",
    "wof:placetype":"venue"
},
  "geometry": {"coordinates":[-8.6162900925,42.1607627869],"type":"Point"}
}