{
  "type": "Feature",
  "properties": {
    "addr:full":"Av Bejar, 41 Terrassa Barcelona 08225",
    "addr:housenumber":"41",
    "addr:postcode":"08225",
    "addr:street":"Av Bejar",
    "iso:country":"ES",
    "sg:address":"Av Bejar, 41",
    "sg:city":"Terrassa",
    "sg:orig_category":"Peluquer\u00cdas, Peluquer\u00cda Mixta",
    "sg:phone":"+34 937 34 29 68",
    "sg:postcode":"08225",
    "sg:province":"Barcelona",
    "wof:name":"Coma Sanchez Elisabeth",
    "wof:placetype":"venue"
},
  "geometry": {"coordinates":[2.0101799965,41.5800132751],"type":"Point"}
}