{
  "type": "Feature",
  "properties": {
    "iso:country":"ES",
    "sg:address":"Calle de Duque De La Torre, 38",
    "sg:city":"Arjona",
    "sg:orig_category":"Inform\u00c1tica, Ofim\u00c1tica (estudios, Asesor\u00cda, Ingenier\u00cda, Formaci\u00d3n)",
    "sg:phone":"+34 953 51 87 62",
    "sg:postcode":"23760",
    "sg:province":"Ja\u00e9n",
    "wof:name":"Foto Pc Arjona C.b.",
    "wof:placetype":"venue"
},
  "geometry": {"coordinates":[-4.0594129562,37.9378089905],"type":"Point"}
}