{
  "type": "Feature",
  "properties": {
    "iso:country":"ES",
    "sg:address":"Avda Mediterraneo, 119",
    "sg:city":"Urbanizacion Roquetas De Mar",
    "sg:orig_category":"Art\u00cdculos De Regalo (al Por Menor)",
    "sg:phone":"+34 950 33 42 72",
    "sg:postcode":"04740",
    "sg:province":"Almer\u00eda",
    "wof:name":"Tejada Rosales Francisco",
    "wof:placetype":"venue"
},
  "geometry": {"coordinates":[-2.6228320599,36.7348747253],"type":"Point"}
}