{
  "type": "Feature",
  "properties": {
    "addr:full":"Rua Praza (da), 34 Grove Pontevedra 36980",
    "addr:housenumber":"34",
    "addr:postcode":"36980",
    "addr:street":"Rua Praza Da;Grove Pontevedra",
    "iso:country":"ES",
    "sg:address":"Rua Praza (da), 34",
    "sg:city":"Grove",
    "sg:orig_category":"Centros De Coordinaci\u00d3n",
    "sg:phone":"+34 986 73 27 89",
    "sg:postcode":"36980",
    "sg:province":"Pontevedra",
    "wof:name":"Lamelas Dominguez Miguel",
    "wof:placetype":"venue"
},
  "geometry": {"coordinates":[-8.86282444,42.4956588745],"type":"Point"}
}