{
  "type": "Feature",
  "properties": {
    "addr:full":"Rbla Catalana, 38 Hospitalet Llobregat Barcelona 08903",
    "addr:housenumber":"38",
    "addr:postcode":"08903",
    "addr:street":"Rbla Catalana",
    "iso:country":"ES",
    "sg:address":"Rbla Catalana, 38",
    "sg:city":"Hospitalet Llobregat",
    "sg:orig_category":"Molduras, Junquillos, Listones Y Molduras Perforadas",
    "sg:phone":"+34 934 48 26 21",
    "sg:postcode":"08903",
    "sg:province":"Barcelona",
    "wof:name":"Salla Fortu\u00f1o Teresa",
    "wof:placetype":"venue"
},
  "geometry": {"coordinates":[2.1249210835,41.3711891174],"type":"Point"}
}