{
  "type": "Feature",
  "properties": {
    "addr:full":"Calle de Villalar (del), 2 Escorial Madrid 28280",
    "addr:housenumber":"2",
    "addr:postcode":"28280",
    "addr:street":"Calle De Villalar Del",
    "iso:country":"ES",
    "sg:address":"Calle de Villalar (del), 2",
    "sg:city":"Escorial",
    "sg:orig_category":"M\u00c9dicos: Pediatr\u00cda. Enfermedades De Los Ni\u00d1os",
    "sg:phone":"+34 918 96 17 30",
    "sg:postcode":"28280",
    "sg:province":"Madrid",
    "wof:name":"Salamanca Mucientes Felix",
    "wof:placetype":"venue"
},
  "geometry": {"coordinates":[-4.1339740753,40.5790748596],"type":"Point"}
}