{
  "type": "Feature",
  "properties": {
    "addr:full":"Calle de Iris, 6 Sobradillo Santa Cruz De Tenerife 38108",
    "addr:housenumber":"6",
    "addr:postcode":"38108",
    "addr:street":"Calle De Iris",
    "iso:country":"ES",
    "sg:address":"Calle de Iris, 6",
    "sg:city":"Sobradillo",
    "sg:orig_category":"Peluquer\u00cdas, Peluquer\u00cda Mixta",
    "sg:phone":"+34 922 61 67 06",
    "sg:postcode":"38108",
    "sg:province":"Santa Cruz De Tenerife",
    "wof:name":"Peluqueria Bucles S.l.",
    "wof:placetype":"venue"
},
  "geometry": {"coordinates":[-16.3147449493,28.4417724609],"type":"Point"}
}