{
  "type": "Feature",
  "properties": {
    "addr:full":"Tapissers, 26 Alaquas Valencia 46970",
    "addr:housenumber":"26",
    "addr:postcode":"46970",
    "addr:street":"Tapissers",
    "iso:country":"ES",
    "sg:address":"Tapissers, 26",
    "sg:city":"Alaquas",
    "sg:orig_category":"Fabricaci\u00d3n De Mobiliario Met\u00c1lico",
    "sg:phone":"+34 961 51 57 77",
    "sg:postcode":"46970",
    "sg:province":"Valencia",
    "wof:name":"Paco Folch S.l.",
    "wof:placetype":"venue"
},
  "geometry": {"coordinates":[-0.4756869972,39.4473114014],"type":"Point"}
}