{
  "type": "Feature",
  "properties": {
    "addr:full":"Atalaya La, 7 Atalaya Murcia 30878",
    "addr:postcode":"30878",
    "addr:street":"La 7",
    "iso:country":"ES",
    "sg:address":"Atalaya La, 7",
    "sg:city":"Atalaya",
    "sg:orig_category":"Int\u00c9rpretes",
    "sg:phone":"+34 968 59 90 03",
    "sg:postcode":"30878",
    "sg:province":"Murcia",
    "wof:name":"Gallagher  Hung",
    "wof:placetype":"venue"
},
  "geometry": {"coordinates":[-1.4224375486,37.6121864319],"type":"Point"}
}