{
  "type": "Feature",
  "properties": {
    "iso:country":"ES",
    "sg:address":"Calle de Melquiades Alvarez, 11",
    "sg:city":"Oviedo",
    "sg:orig_category":"Perfumer\u00cda (al Por Menor)",
    "sg:phone":"+34 985 21 48 53",
    "sg:postcode":"33003",
    "sg:province":"Asturias",
    "wof:name":"Castro Fernandez Maria Del Carmen De",
    "wof:placetype":"venue"
},
  "geometry": {"coordinates":[-5.8515911102,43.3647956848],"type":"Point"}
}