{
  "type": "Feature",
  "properties": {
    "iso:country":"ES",
    "sg:address":"Carrer de Jaume Balmes, 7",
    "sg:city":"Ametlla Mar",
    "sg:orig_category":"Promotores Constructores",
    "sg:phone":"+34 977 45 76 20",
    "sg:postcode":"43860",
    "sg:province":"Tarragona",
    "wof:name":"Construcciones Kam S.c.c.l",
    "wof:placetype":"venue"
},
  "geometry": {"coordinates":[0.8022680283,40.8833847046],"type":"Point"}
}