{
  "type": "Feature",
  "properties": {
    "iso:country":"ES",
    "sg:address":"Navarra-nafarroa Ebde, 1",
    "sg:city":"Iru\u00f1a",
    "sg:orig_category":"Deportes Diversos",
    "sg:phone":"+34 948 22 09 05",
    "sg:postcode":"31012",
    "sg:province":"Navarra",
    "wof:name":"Federacion Navarra De Natacion",
    "wof:placetype":"venue"
},
  "geometry": {"coordinates":[-1.6437540054,42.81275177],"type":"Point"}
}