{
  "type": "Feature",
  "properties": {
    "iso:country":"ES",
    "sg:address":"Rond Alcudia, 26",
    "sg:city":"Sueca",
    "sg:orig_category":"Electricidad: Instaladores",
    "sg:phone":"+34 961 71 06 04",
    "sg:postcode":"46410",
    "sg:province":"Valencia",
    "wof:name":"Instalaciones Hervas S.l.",
    "wof:placetype":"venue"
},
  "geometry": {"coordinates":[-0.3082979918,39.1977386475],"type":"Point"}
}