{
  "type": "Feature",
  "properties": {
    "addr:full":"Calle de Ruaya, 1 Valencia Valencia 46009",
    "addr:housenumber":"1",
    "addr:postcode":"46009",
    "addr:street":"Calle De Ruaya",
    "iso:country":"ES",
    "sg:address":"Calle de Ruaya, 1",
    "sg:city":"Valencia",
    "sg:orig_category":"Inmobiliaria (agencias)",
    "sg:phone":"+34 963 48 77 47",
    "sg:postcode":"46009",
    "sg:province":"Valencia",
    "wof:name":"Zona 9 S.l.",
    "wof:placetype":"venue"
},
  "geometry": {"coordinates":[-0.3747043908,39.4851760864],"type":"Point"}
}