{
  "type": "Feature",
  "properties": {
    "iso:country":"ES",
    "sg:address":"Av Diagonal, 506",
    "sg:city":"Barcelona",
    "sg:orig_category":"Energ\u00cda Solar Y Nuevas Energ\u00cdas (equipo, Estudios)",
    "sg:phone":"+34 932 37 25 09",
    "sg:postcode":"08006",
    "sg:province":"Barcelona",
    "wof:name":"Tarraco Eolica S.a.",
    "wof:placetype":"venue"
},
  "geometry": {"coordinates":[2.1539111137,41.3954429626],"type":"Point"}
}