{
  "type": "Feature",
  "properties": {
    "addr:full":"Carrer de Pasqual Ribot, 22 Palma Islas Baleares 07011",
    "addr:housenumber":"22",
    "addr:postcode":"07011",
    "addr:street":"Carrer De Pasqual Ribot",
    "iso:country":"ES",
    "sg:address":"Carrer de Pasqual Ribot, 22",
    "sg:city":"Palma",
    "sg:orig_category":"Florister\u00cdas",
    "sg:phone":"+34 971 73 91 83",
    "sg:postcode":"07011",
    "sg:province":"Islas Baleares",
    "wof:name":"Yerino Lafrocce Ester Lucia",
    "wof:placetype":"venue"
},
  "geometry": {"coordinates":[2.6362760067,39.5794525146],"type":"Point"}
}