{
  "type": "Feature",
  "properties": {
    "addr:full":"Ctra Madrid-cadiz, S/n Montoro C\u00f3rdoba 14600",
    "addr:housenumber":"/ n",
    "addr:postcode":"14600",
    "addr:street":"Ctra Madrid-Cadiz S;Co\u0301Rdoba",
    "iso:country":"ES",
    "sg:address":"Ctra Madrid-cadiz, S/n",
    "sg:city":"Montoro",
    "sg:orig_category":"Distribuci\u00d3n De Petr\u00d3leo Y Derivados",
    "sg:phone":"+34 957 16 26 40",
    "sg:postcode":"14600",
    "sg:province":"C\u00f3rdoba",
    "wof:name":"Dispesur S.l.",
    "wof:placetype":"venue"
},
  "geometry": {"coordinates":[-4.3815989494,38.0260391235],"type":"Point"}
}