{
  "type": "Feature",
  "properties": {
    "addr:full":"Calle de Rincona, 31 Lepe Huelva 21440",
    "addr:housenumber":"31",
    "addr:postcode":"21440",
    "addr:street":"Calle De Rincona",
    "iso:country":"ES",
    "sg:address":"Calle de Rincona, 31",
    "sg:city":"Lepe",
    "sg:orig_category":"Fisioterapia",
    "sg:phone":"+34 959 38 40 38",
    "sg:postcode":"21440",
    "sg:province":"Huelva",
    "wof:name":"Fisio Costa De Lepe",
    "wof:placetype":"venue"
},
  "geometry": {"coordinates":[-7.2049331665,37.254283905],"type":"Point"}
}