{
  "type": "Feature",
  "properties": {
    "iso:country":"ES",
    "sg:address":"Fdo Coca Pi\u00f1era, 1",
    "sg:city":"Constantina",
    "sg:orig_category":"Producci\u00d3n, Comercio De Cereales",
    "sg:phone":"+34 955 88 08 34",
    "sg:postcode":"41450",
    "sg:province":"Sevilla",
    "wof:name":"Hermanos Caballero Olivera S. L.",
    "wof:placetype":"venue"
},
  "geometry": {"coordinates":[-5.6197562218,37.8712120056],"type":"Point"}
}