{
  "type": "Feature",
  "properties": {
    "iso:country":"ES",
    "sg:address":"Carrer de Coromines, 13",
    "sg:city":"Sentmenat",
    "sg:orig_category":"Peluqueros: De Se\u00d1oras",
    "sg:phone":"+34 937 15 12 50",
    "sg:postcode":"08181",
    "sg:province":"Barcelona",
    "wof:name":"Fuentes Acu\u00f1a Maria Del Carmen",
    "wof:placetype":"venue"
},
  "geometry": {"coordinates":[2.1383609772,41.6083335876],"type":"Point"}
}