{
  "type": "Feature",
  "properties": {
    "iso:country":"ES",
    "sg:address":"Calle de Carmen Montoya, 12",
    "sg:city":"Madrid",
    "sg:orig_category":"Ense\u00d1anza: Profesiones Art\u00cdsticas",
    "sg:phone":"+34 917 33 80 78",
    "sg:postcode":"28029",
    "sg:province":"Madrid",
    "wof:name":"Yellow Dog C.b.",
    "wof:placetype":"venue"
},
  "geometry": {"coordinates":[-3.6983509064,40.4697685242],"type":"Point"}
}