{
  "type": "Feature",
  "properties": {
    "iso:country":"ES",
    "sg:address":"Carr Cellera, 16",
    "sg:city":"Vidreres",
    "sg:orig_category":"Inmobiliaria (agencias)",
    "sg:phone":"+34 972 85 14 39",
    "sg:postcode":"17411",
    "sg:province":"Girona",
    "wof:name":"Gestion Inmobiliaria Dominica Almaraz S.l.",
    "wof:placetype":"venue"
},
  "geometry": {"coordinates":[2.7773220539,41.789768219],"type":"Point"}
}