{
  "type": "Feature",
  "properties": {
    "addr:full":"Psaj Maza, 7 Jaen Ja\u00e9n 23001",
    "addr:housenumber":"7;jae\u0301n",
    "addr:postcode":"23001",
    "addr:street":"Maza",
    "iso:country":"ES",
    "sg:address":"Psaj Maza, 7",
    "sg:city":"Jaen",
    "sg:orig_category":"Inform\u00c1tica (estudios, Servicios, Asesor\u00cda, Formaci\u00d3n)",
    "sg:phone":"+34 953 25 82 10",
    "sg:postcode":"23001",
    "sg:province":"Ja\u00e9n",
    "wof:name":"Centro Mail Jaen S.l.",
    "wof:placetype":"venue"
},
  "geometry": {"coordinates":[-3.7882089615,37.7670555115],"type":"Point"}
}