{
  "type": "Feature",
  "properties": {
    "iso:country":"ES",
    "sg:address":"Avda San Diego, 3",
    "sg:city":"Madrid",
    "sg:orig_category":"Empresarios",
    "sg:phone":"+34 914 78 58 12",
    "sg:postcode":"28053",
    "sg:province":"Madrid",
    "wof:name":"Reformas Y Decoraciones Ayc",
    "wof:placetype":"venue"
},
  "geometry": {"coordinates":[-3.6711630821,40.3894424438],"type":"Point"}
}