{
  "type": "Feature",
  "properties": {
    "iso:country":"ES",
    "sg:address":"Calle de Gallo, 18",
    "sg:city":"Valladolid",
    "sg:orig_category":"Frutas, Legumbres Frescas Y Tempranas (al Por Menor)",
    "sg:phone":"+34 983 30 13 26",
    "sg:postcode":"47012",
    "sg:province":"Valladolid",
    "wof:name":"Dieguez Navarro Leticia",
    "wof:placetype":"venue"
},
  "geometry": {"coordinates":[-4.7080287933,41.6468467712],"type":"Point"}
}