{
  "type": "Feature",
  "properties": {
    "addr:full":"Calle de Reina Mora, 4 Granada Granada 18008",
    "addr:housenumber":"4",
    "addr:postcode":"18008",
    "addr:street":"Calle De Reina Mora",
    "iso:country":"ES",
    "sg:address":"Calle de Reina Mora, 4",
    "sg:city":"Granada",
    "sg:orig_category":"Confecci\u00d3n (fabricaci\u00d3n, Al Por Mayor)",
    "sg:phone":"+34 958 12 40 26",
    "sg:postcode":"18008",
    "sg:province":"Granada",
    "wof:name":"Blanca Herrera Julio",
    "wof:placetype":"venue"
},
  "geometry": {"coordinates":[-3.5939021111,37.1619110107],"type":"Point"}
}