{
  "type": "Feature",
  "properties": {
    "addr:full":"Calle de Federico Garcia Lorca (de), 4 Boadilla Del Monte Madrid 28660",
    "addr:housenumber":"4",
    "addr:postcode":"28660",
    "addr:street":"Calle De Federico Garcia Lorca De",
    "iso:country":"ES",
    "sg:address":"Calle de Federico Garcia Lorca (de), 4",
    "sg:city":"Boadilla Del Monte",
    "sg:orig_category":"Centros De Educaci\u00d3n Especial",
    "sg:phone":"+34 916 32 55 25",
    "sg:postcode":"28660",
    "sg:province":"Madrid",
    "wof:name":"Comunidad Autonoma De Madrid-centros De Educacion",
    "wof:placetype":"venue"
},
  "geometry": {"coordinates":[-3.9001030922,40.4081306458],"type":"Point"}
}