{
  "type": "Feature",
  "properties": {
    "iso:country":"ES",
    "sg:address":"Avda San Crispin, 68",
    "sg:city":"Fuensalida",
    "sg:orig_category":"Confecci\u00d3n De Zapatos",
    "sg:phone":"+34 925 78 42 77",
    "sg:postcode":"45510",
    "sg:province":"Toledo",
    "sg:website":"www.tolino.com",
    "wof:name":"Viucasar S. A.",
    "wof:placetype":"venue"
},
  "geometry": {"coordinates":[-4.203151226,40.0530471802],"type":"Point"}
}