{
  "type": "Feature",
  "properties": {
    "iso:country":"ES",
    "sg:address":"Avda Canillejas A Vicalvaro, 67",
    "sg:city":"Madrid",
    "sg:orig_category":"Fabricaci\u00d3n De Muebles",
    "sg:phone":"+34 913 13 13 49",
    "sg:postcode":"28022",
    "sg:province":"Madrid",
    "wof:name":"Enguidanos Romeral Juan Pablo",
    "wof:placetype":"venue"
},
  "geometry": {"coordinates":[-3.6120069027,40.4342384338],"type":"Point"}
}