{
  "type": "Feature",
  "properties": {
    "addr:full":"Carretera, S/n Adamuz C\u00f3rdoba 14430",
    "addr:housenumber":"s / n",
    "addr:postcode":"14430",
    "addr:street":"Carretera",
    "iso:country":"ES",
    "sg:address":"Carretera, S/n",
    "sg:city":"Adamuz",
    "sg:orig_category":"Producci\u00d3n, Venta De Productos De Agricultura Biol\u00d3gica",
    "sg:phone":"+34 957 16 61 35",
    "sg:postcode":"14430",
    "sg:province":"C\u00f3rdoba",
    "wof:name":"Leyva Perez Manuel",
    "wof:placetype":"venue"
},
  "geometry": {"coordinates":[-4.5246610641,38.0278129578],"type":"Point"}
}