{
  "type": "Feature",
  "properties": {
    "addr:full":"Calle de Valencia, 21 Madrid Madrid 28012",
    "addr:housenumber":"21",
    "addr:postcode":"madrid;28012",
    "addr:street":"Calle De Valencia",
    "iso:country":"ES",
    "sg:address":"Calle de Valencia, 21",
    "sg:city":"Madrid",
    "sg:orig_category":"Grafistas",
    "sg:phone":"+34 915 30 67 42",
    "sg:postcode":"28012",
    "sg:province":"Madrid",
    "sg:website":"www.teafortwo.com",
    "wof:name":"Teafor Two S.l",
    "wof:placetype":"venue"
},
  "geometry": {"coordinates":[-3.6995079517,40.4064445496],"type":"Point"}
}