{
  "type": "Feature",
  "properties": {
    "addr:full":"Calle de Lopez De Hoyos, 135 Madrid Madrid 28002",
    "addr:housenumber":"135",
    "addr:postcode":"28002",
    "addr:street":"Calle De Lopez De Hoyos",
    "iso:country":"ES",
    "sg:address":"Calle de Lopez De Hoyos, 135",
    "sg:city":"Madrid",
    "sg:orig_category":"Trabajos De Perforaciones, Sondeos, Construcci\u00d3n De Pozos",
    "sg:phone":"+34 915 61 08 07",
    "sg:postcode":"28002",
    "sg:province":"Madrid",
    "wof:name":"Iberica De Sondeos S. A.",
    "wof:placetype":"venue"
},
  "geometry": {"coordinates":[-3.6698479652,40.4471130371],"type":"Point"}
}