{
  "type": "Feature",
  "properties": {
    "iso:country":"ES",
    "sg:address":"Urb Virgen Del Pilar, 42",
    "sg:city":"Sig\u00fcenza",
    "sg:orig_category":"Procuradores",
    "sg:phone":"+34 949 39 31 28",
    "sg:postcode":"19250",
    "sg:province":"Guadalajara",
    "wof:name":"Lazaro Herranz Sonia",
    "wof:placetype":"venue"
},
  "geometry": {"coordinates":[-2.6316390038,41.0719718933],"type":"Point"}
}