{
  "type": "Feature",
  "properties": {
    "addr:full":"Vilanova, S/n Vilanova A Coru\u00f1a 15107",
    "addr:housenumber":"s / n",
    "addr:postcode":"15107",
    "addr:street":"Vilanova;Corun\u0303A",
    "iso:country":"ES",
    "sg:address":"Vilanova, S/n",
    "sg:city":"Vilanova",
    "sg:orig_category":"Mataderos Y Talleres De Despiezado",
    "sg:phone":"+34 981 75 67 05",
    "sg:postcode":"15107",
    "sg:province":"A Coru\u00f1a",
    "wof:name":"Xunta De Galicia",
    "wof:placetype":"venue"
},
  "geometry": {"coordinates":[-8.1568164825,43.4718284607],"type":"Point"}
}