{
  "type": "Feature",
  "properties": {
    "addr:full":"Carretera De Sinarcas, Km. 0013,0 La Torre Valencia 46321",
    "addr:postcode":"46321",
    "addr:street":"Carretera De Sinarcas Km. 0013,0",
    "iso:country":"ES",
    "sg:address":"Carretera De Sinarcas, Km. 0013,0",
    "sg:city":"La Torre",
    "sg:orig_category":"Agricultores, Agricultores",
    "sg:phone":"+34 962 31 53 26",
    "sg:postcode":"46321",
    "sg:province":"Valencia",
    "wof:name":"Sat Num 6810 Hermanos Verdu",
    "wof:placetype":"venue"
},
  "geometry": {"coordinates":[-1.2611759901,39.6686325073],"type":"Point"}
}