{
  "type": "Feature",
  "properties": {
    "iso:country":"ES",
    "sg:address":"Avda Euzkadi (de), 12",
    "sg:city":"San Sebastian De Los Reyes",
    "sg:orig_category":"Peluquer\u00cdas, Peluquer\u00cda Mixta",
    "sg:phone":"+34 916 52 29 59",
    "sg:postcode":"28700",
    "sg:province":"Madrid",
    "wof:name":"Grasa Aquilue Maria Teresa",
    "wof:placetype":"venue"
},
  "geometry": {"coordinates":[-3.6330769062,40.5556221008],"type":"Point"}
}