{
  "type": "Feature",
  "properties": {
    "addr:full":"Calle de Fray Pedro Payo Pi\u00d1eiro, 21 Casanova De Eiris La Coru\u00f1a 15009",
    "addr:housenumber":"21",
    "addr:postcode":"15009",
    "addr:street":"Calle De Fray Pedro Payo Pin\u0303Eiro;Corun\u0303A",
    "iso:country":"ES",
    "sg:address":"Calle de Fray Pedro Payo Pi\u00d1eiro, 21",
    "sg:city":"Casanova De Eiris",
    "sg:orig_category":"Ropa Para Beb\u00c9s Y Ni\u00d1os (confecci\u00d3n, Al Por Mayor)",
    "sg:phone":"+34 981 13 14 98",
    "sg:postcode":"15009",
    "sg:province":"La Coru\u00f1a",
    "wof:name":"Confecciones Eiris S.l.",
    "wof:placetype":"venue"
},
  "geometry": {"coordinates":[-8.3917312622,43.3449211121],"type":"Point"}
}