{
  "type": "Feature",
  "properties": {
    "addr:full":"Carr Ample, 5 Bisbal D'emporda Girona 17100",
    "addr:housenumber":"5",
    "addr:postcode":"17100",
    "addr:street":"Carr Ample",
    "iso:country":"ES",
    "sg:address":"Carr Ample, 5",
    "sg:city":"Bisbal D'emporda",
    "sg:orig_category":"Imprenta",
    "sg:phone":"+34 972 64 01 95",
    "sg:postcode":"17100",
    "sg:province":"Girona",
    "wof:name":"Jover Vall-llosera Joan",
    "wof:placetype":"venue"
},
  "geometry": {"coordinates":[2.813131094,41.9749221802],"type":"Point"}
}