{
  "type": "Feature",
  "properties": {
    "addr:full":"Calle de Palacio Valdes, 23 Aviles Asturias 33402",
    "addr:housenumber":"23",
    "addr:postcode":"33402",
    "addr:street":"Calle De Palacio Valdes",
    "iso:country":"ES",
    "sg:address":"Calle de Palacio Valdes, 23",
    "sg:city":"Aviles",
    "sg:orig_category":"Caf\u00c9s, Bares, Cervecer\u00cdas",
    "sg:phone":"+34 985 54 92 17",
    "sg:postcode":"33402",
    "sg:province":"Asturias",
    "wof:name":"Alba Cano Valentin",
    "wof:placetype":"venue"
},
  "geometry": {"coordinates":[-5.9192767143,43.553653717],"type":"Point"}
}