{
  "type": "Feature",
  "properties": {
    "iso:country":"ES",
    "sg:address":"Rep Saharawi (p I Univ. Cadiz), S/n",
    "sg:city":"Pto Real",
    "sg:orig_category":"Universidades",
    "sg:phone":"+34 956 47 33 32",
    "sg:postcode":"11519",
    "sg:province":"C\u00e1diz",
    "wof:name":"Universidad De Cadiz",
    "wof:placetype":"venue"
},
  "geometry": {"coordinates":[-6.2170300484,36.5123291016],"type":"Point"}
}