{
  "type": "Feature",
  "properties": {
    "iso:country":"ES",
    "sg:address":"Pl Portal D'anoia, 7",
    "sg:city":"Martorell",
    "sg:orig_category":"Cajas De Ahorro",
    "sg:phone":"+34 937 74 07 67",
    "sg:postcode":"08760",
    "sg:province":"Barcelona",
    "wof:name":"Caixa D'estalvis Sabadell",
    "wof:placetype":"venue"
},
  "geometry": {"coordinates":[1.9273990393,41.473526001],"type":"Point"}
}