{
  "type": "Feature",
  "properties": {
    "addr:full":"Calle de Juan Montes, 1 Coru\u00d1a La Coru\u00f1a 15006",
    "addr:housenumber":"1",
    "addr:postcode":"15006",
    "addr:street":"Calle De Juan Montes;La Corun\u0303A",
    "iso:country":"ES",
    "sg:address":"Calle de Juan Montes, 1",
    "sg:city":"Coru\u00d1a",
    "sg:orig_category":"Supermercados Y Hipermercados",
    "sg:phone":"+34 981 13 93 26",
    "sg:postcode":"15006",
    "sg:province":"La Coru\u00f1a",
    "wof:name":"Distribuciones Froiz S.a.",
    "wof:placetype":"venue"
},
  "geometry": {"coordinates":[-8.3939247131,43.3535194397],"type":"Point"}
}