{
  "type": "Feature",
  "properties": {
    "iso:country":"ES",
    "sg:address":"Carr Tarragona, 24",
    "sg:city":"Palafrugell",
    "sg:orig_category":"Chapister\u00cda",
    "sg:phone":"+34 972 30 59 13",
    "sg:postcode":"17200",
    "sg:province":"Girona",
    "wof:name":"Ortega Ponce Jose",
    "wof:placetype":"venue"
},
  "geometry": {"coordinates":[3.156085968,41.9133605957],"type":"Point"}
}