{
  "type": "Feature",
  "properties": {
    "iso:country":"ES",
    "sg:address":"Carrer de Suris, 44",
    "sg:city":"S. Feliu Guixols",
    "sg:orig_category":"Venta, Instalaci\u00d3n De Calefacci\u00d3n",
    "sg:phone":"+34 972 32 42 07",
    "sg:postcode":"17220",
    "sg:province":"Girona",
    "wof:name":"Niell Ezequiel Luis",
    "wof:placetype":"venue"
},
  "geometry": {"coordinates":[3.0256979465,41.7841796875],"type":"Point"}
}