{
  "type": "Feature",
  "properties": {
    "iso:country":"ES",
    "sg:address":"Rua San Miguel, 3",
    "sg:city":"Camari\u00f1as",
    "sg:orig_category":"Fabricaci\u00d3n De Bordados, Encajes Y Tules",
    "sg:phone":"+34 981 73 71 21",
    "sg:postcode":"15123",
    "sg:province":"La Coru\u00f1a",
    "wof:name":"Asociacion Profesional De Palilleras De Camari\u00f1as Rendas",
    "wof:placetype":"venue"
},
  "geometry": {"coordinates":[-9.182767868,43.1300430298],"type":"Point"}
}