{
  "type": "Feature",
  "properties": {
    "addr:full":"Calle de Jose Maria Peman, 23 Elda Alicante 03600",
    "addr:housenumber":"23",
    "addr:postcode":"03600",
    "addr:street":"Calle De Jose Maria Peman",
    "iso:country":"ES",
    "sg:address":"Calle de Jose Maria Peman, 23",
    "sg:city":"Elda",
    "sg:orig_category":"M\u00c9dicos: Oftalmolog\u00cda",
    "sg:phone":"+34 965 39 80 67",
    "sg:postcode":"03600",
    "sg:province":"Alicante",
    "wof:name":"Perez Garcia Reinaldo",
    "wof:placetype":"venue"
},
  "geometry": {"coordinates":[-0.7933670282,38.4766387939],"type":"Point"}
}