{
  "type": "Feature",
  "properties": {
    "addr:full":"Calle de Templarios, 5 Valladolid Valladolid 47011",
    "addr:housenumber":"5",
    "addr:postcode":"47011",
    "addr:street":"Calle De Templarios",
    "iso:country":"ES",
    "sg:address":"Calle de Templarios, 5",
    "sg:city":"Valladolid",
    "sg:orig_category":"Empresarios",
    "sg:phone":"+34 983 30 82 41",
    "sg:postcode":"47011",
    "sg:province":"Valladolid",
    "wof:name":"Obras Y Contratas Tacid S.l.",
    "wof:placetype":"venue"
},
  "geometry": {"coordinates":[-4.7071299553,41.6512374878],"type":"Point"}
}