{
  "type": "Feature",
  "properties": {
    "addr:full":"Carrer de Pujades, 191 Barcelona Barcelona 08005",
    "addr:housenumber":"191",
    "addr:postcode":"08005",
    "addr:street":"Carrer De Pujades",
    "iso:country":"ES",
    "sg:address":"Carrer de Pujades, 191",
    "sg:city":"Barcelona",
    "sg:orig_category":"Psic\u00d3logos",
    "sg:phone":"+34 932 66 33 25",
    "sg:postcode":"08005",
    "sg:province":"Barcelona",
    "wof:name":"Aula Equip Multidisciplinar De Psicopedagogia I Logopedia S.c.p.",
    "wof:placetype":"venue"
},
  "geometry": {"coordinates":[2.2016699314,41.402633667],"type":"Point"}
}