{
  "type": "Feature",
  "properties": {
    "addr:full":"Calle de Angustias, 24 Valladolid Valladolid 47003",
    "addr:housenumber":"24",
    "addr:postcode":"47003",
    "addr:street":"Calle De Angustias",
    "iso:country":"ES",
    "sg:address":"Calle de Angustias, 24",
    "sg:city":"Valladolid",
    "sg:orig_category":"Peluquer\u00cdas, Peluquer\u00cda Mixta",
    "sg:phone":"+34 983 21 19 01",
    "sg:postcode":"47003",
    "sg:province":"Valladolid",
    "wof:name":"Hair Stile Imagen S.l.",
    "wof:placetype":"venue"
},
  "geometry": {"coordinates":[-4.7236289978,41.6545448303],"type":"Point"}
}