{
  "type": "Feature",
  "properties": {
    "iso:country":"ES",
    "sg:address":"Calle de Melchor Fernandez Almagro, 12",
    "sg:city":"Madrid",
    "sg:orig_category":"Sociedades, Compa\u00d1\u00cdas Aseguradoras",
    "sg:phone":"+34 913 15 55 42",
    "sg:postcode":"28029",
    "sg:province":"Madrid",
    "wof:name":"Saymar S.a.",
    "wof:placetype":"venue"
},
  "geometry": {"coordinates":[-3.6960599422,40.4778022766],"type":"Point"}
}