{
  "type": "Feature",
  "properties": {
    "addr:full":"Plaz Constitucion (de La), 7 Carpio C\u00f3rdoba 14620",
    "addr:housenumber":"7",
    "addr:postcode":"14620",
    "addr:street":"Carpio Co\u0301Rdoba",
    "iso:country":"ES",
    "sg:address":"Plaz Constitucion (de La), 7",
    "sg:city":"Carpio",
    "sg:orig_category":"Bancos",
    "sg:phone":"+34 957 18 00 38",
    "sg:postcode":"14620",
    "sg:province":"C\u00f3rdoba",
    "sg:website":"www.banesto.es",
    "wof:name":"Banco Espa\u00f1ol De Credito S.a.",
    "wof:placetype":"venue"
},
  "geometry": {"coordinates":[-4.4988470078,37.9402809143],"type":"Point"}
}