{
  "type": "Feature",
  "properties": {
    "addr:full":"Avda Castrelos, 424 Vigo Pontevedra 36213",
    "addr:housenumber":"424",
    "addr:postcode":"36213",
    "addr:street":"Avda Castrelos",
    "iso:country":"ES",
    "sg:address":"Avda Castrelos, 424",
    "sg:city":"Vigo",
    "sg:orig_category":"Empresas De Carpinter\u00cda",
    "sg:phone":"+34 986 23 98 77",
    "sg:postcode":"36213",
    "sg:province":"Pontevedra",
    "wof:name":"Villar Sousa Jose",
    "wof:placetype":"venue"
},
  "geometry": {"coordinates":[-8.7217006683,42.1961593628],"type":"Point"}
}