{
  "type": "Feature",
  "properties": {
    "iso:country":"ES",
    "sg:address":"Partida Cabezo, S/n",
    "sg:city":"Ador",
    "sg:orig_category":"Zonas De Acampada, Aparcamiento Para Caravanas",
    "sg:phone":"+34 962 80 84 69",
    "sg:postcode":"46724",
    "sg:province":"Valencia",
    "wof:name":"Campamento Albergue Sierra De Ador S.l.",
    "wof:placetype":"venue"
},
  "geometry": {"coordinates":[-0.2228540033,38.922996521],"type":"Point"}
}