{
  "type": "Feature",
  "properties": {
    "addr:full":"Pase Palmeras (de Las), 12 Ceuta Ceuta 51001",
    "addr:housenumber":"12",
    "addr:postcode":"51001",
    "addr:street":"Las",
    "iso:country":"ES",
    "sg:address":"Pase Palmeras (de Las), 12",
    "sg:city":"Ceuta",
    "sg:orig_category":"Fabricaci\u00d3n De Bolsos Y Bolsos De Tela",
    "sg:phone":"+34 956 51 34 07",
    "sg:postcode":"51001",
    "sg:province":"Ceuta",
    "sg:website":"www.interlumar.com",
    "wof:name":"Interlumar S.a.",
    "wof:placetype":"venue"
},
  "geometry": {"coordinates":[-5.3302302361,35.8947601318],"type":"Point"}
}