{
  "type": "Feature",
  "properties": {
    "iso:country":"ES",
    "sg:address":"Rbla Egara, 390",
    "sg:city":"Terrassa",
    "sg:orig_category":"Ropa Para Se\u00d1oras Y Caballeros (al Por Menor)",
    "sg:phone":"+34 937 88 50 18",
    "sg:postcode":"08221",
    "sg:province":"Barcelona",
    "wof:name":"Miro Modas S.l.",
    "wof:placetype":"venue"
},
  "geometry": {"coordinates":[2.0048069954,41.5688819885],"type":"Point"}
}