{
  "type": "Feature",
  "properties": {
    "addr:full":"Poligono De El Raposal, S/n Arnedo La Rioja 26580",
    "addr:housenumber":"s / n",
    "addr:postcode":"26580",
    "addr:street":"Rioja",
    "iso:country":"ES",
    "sg:address":"Poligono De El Raposal, S/n",
    "sg:city":"Arnedo",
    "sg:orig_category":"Confecci\u00d3n De Zapatos",
    "sg:phone":"+34 941 38 21 00",
    "sg:postcode":"26580",
    "sg:province":"La Rioja",
    "wof:name":"Calzados Newjovi S.l.",
    "wof:placetype":"venue"
},
  "geometry": {"coordinates":[-2.0899488926,42.2300453186],"type":"Point"}
}