{
  "type": "Feature",
  "properties": {
    "iso:country":"ES",
    "sg:address":"Calle de Calvo Sotelo, 25",
    "sg:city":"Chantada",
    "sg:orig_category":"Confecci\u00d3n (fabricaci\u00d3n, Al Por Mayor)",
    "sg:phone":"+34 982 44 08 73",
    "sg:postcode":"27500",
    "sg:province":"Lugo",
    "wof:name":"Lopez Guerra Angel",
    "wof:placetype":"venue"
},
  "geometry": {"coordinates":[-7.7708263397,42.6086120605],"type":"Point"}
}