{
  "type": "Feature",
  "properties": {
    "addr:full":"Ctra Figueres, 2 Banyoles Girona 17820",
    "addr:housenumber":"2",
    "addr:postcode":"17820",
    "addr:street":"Ctra Figueres",
    "iso:country":"ES",
    "sg:address":"Ctra Figueres, 2",
    "sg:city":"Banyoles",
    "sg:orig_category":"Empresas De Pintura Y Revestimientos",
    "sg:phone":"+34 972 57 12 62",
    "sg:postcode":"17820",
    "sg:province":"Girona",
    "wof:name":"Rodriguez Padilla Fernando",
    "wof:placetype":"venue"
},
  "geometry": {"coordinates":[2.7630579472,42.125087738],"type":"Point"}
}