{
  "type": "Feature",
  "properties": {
    "addr:full":"Cno Tomares, S/n Castilleja Cuesta Sevilla 41950",
    "addr:housenumber":"s / n",
    "addr:postcode":"41950",
    "addr:street":"Cno Tomares;Castilleja Cuesta Sevilla",
    "iso:country":"ES",
    "sg:address":"Cno Tomares, S/n",
    "sg:city":"Castilleja Cuesta",
    "sg:orig_category":"Bazares, Art\u00cdculos De Limpieza Y De Cocina (al Por Menor)",
    "sg:phone":"+34 954 16 50 67",
    "sg:postcode":"41950",
    "sg:province":"Sevilla",
    "sg:website":"www.zarahome.com",
    "wof:name":"Zara Home Espa\u00d1a S.a.",
    "wof:placetype":"venue"
},
  "geometry": {"coordinates":[-6.0458288193,37.3869400024],"type":"Point"}
}