{
  "type": "Feature",
  "properties": {
    "iso:country":"ES",
    "sg:address":"Carretera De Guadadupe, S/n",
    "sg:city":"Casta\u00f1ar Ibor",
    "sg:orig_category":"Electrodom\u00c9sticos (al Por Menor)",
    "sg:phone":"+34 927 55 45 12",
    "sg:postcode":"10340",
    "sg:province":"C\u00e1ceres",
    "wof:name":"Muebles Curiel S.a.l.",
    "wof:placetype":"venue"
},
  "geometry": {"coordinates":[-5.4165887833,39.6288642883],"type":"Point"}
}