{
  "type": "Feature",
  "properties": {
    "iso:country":"ES",
    "sg:address":"Calle de Perez Porto, 3",
    "sg:city":"Coru\u00d1a",
    "sg:orig_category":"Abogados",
    "sg:phone":"+34 981 15 17 36",
    "sg:postcode":"15007",
    "sg:province":"La Coru\u00f1a",
    "sg:website":"www.armenteros-abogados.com",
    "wof:name":"Armenteros Montiel Jose Luis",
    "wof:placetype":"venue"
},
  "geometry": {"coordinates":[-8.4074735641,43.3549499512],"type":"Point"}
}