{
  "type": "Feature",
  "properties": {
    "iso:country":"ES",
    "sg:address":"Calle de Vallin El, S/n",
    "sg:city":"Piedras Blancas",
    "sg:orig_category":"Ense\u00d1anza Secundaria: Colegios Y Escuelas Privadas",
    "sg:phone":"+34 985 53 26 14",
    "sg:postcode":"33450",
    "sg:province":"Asturias",
    "wof:name":"Instituto De Educacion Secundaria Isla De La Deva",
    "wof:placetype":"venue"
},
  "geometry": {"coordinates":[-5.978290081,43.5613212585],"type":"Point"}
}