{
  "type": "Feature",
  "properties": {
    "iso:country":"ES",
    "sg:address":"Calle de Puerta De Granada, 2",
    "sg:city":"Almu\u00f1ecar",
    "sg:orig_category":"Imprenta",
    "sg:phone":"+34 958 88 07 83",
    "sg:postcode":"18690",
    "sg:province":"Granada",
    "wof:name":"Graficas Contreras S.l.",
    "wof:placetype":"venue"
},
  "geometry": {"coordinates":[-3.6905388832,36.7342720032],"type":"Point"}
}