{
  "type": "Feature",
  "properties": {
    "iso:country":"ES",
    "sg:address":"Calle de Padre Andivia, 4",
    "sg:city":"Huelva",
    "sg:orig_category":"Montaje (empresas De)",
    "sg:phone":"+34 959 25 09 73",
    "sg:postcode":"21003",
    "sg:province":"Huelva",
    "wof:name":"Moncobra S.a.",
    "wof:placetype":"venue"
},
  "geometry": {"coordinates":[-6.9500489235,37.2544746399],"type":"Point"}
}