{
  "type": "Feature",
  "properties": {
    "addr:full":"Calle de Anton Ruiz, 46 Sevilla Sevilla 41006",
    "addr:housenumber":"46",
    "addr:postcode":"41006",
    "addr:street":"Calle De Anton Ruiz",
    "iso:country":"ES",
    "sg:address":"Calle de Anton Ruiz, 46",
    "sg:city":"Sevilla",
    "sg:orig_category":"Partidos Pol\u00cdticos",
    "sg:phone":"+34 954 66 39 56",
    "sg:postcode":"41006",
    "sg:province":"Sevilla",
    "wof:name":"Izquierda Unida Convocatoria Por Andalucia",
    "wof:placetype":"venue"
},
  "geometry": {"coordinates":[-5.959174633,37.3798942566],"type":"Point"}
}