{
  "type": "Feature",
  "properties": {
    "addr:full":"Pg Tarongers, 44 Castelldefels Barcelona 08860",
    "addr:housenumber":"44",
    "addr:postcode":"08860",
    "addr:street":"Tarongers",
    "iso:country":"ES",
    "sg:address":"Pg Tarongers, 44",
    "sg:city":"Castelldefels",
    "sg:orig_category":"Pescader\u00cdas (al Por Menor)",
    "sg:phone":"+34 936 65 61 03",
    "sg:postcode":"08860",
    "sg:province":"Barcelona",
    "wof:name":"Galvez Aleman Jose",
    "wof:placetype":"venue"
},
  "geometry": {"coordinates":[1.9475339651,41.2672729492],"type":"Point"}
}