{
  "type": "Feature",
  "properties": {
    "iso:country":"ES",
    "sg:address":"Cmno Plano (del) (miralbueno), 60",
    "sg:city":"Zaragoza",
    "sg:orig_category":"Cr\u00cda De Animales",
    "sg:phone":"+34 976 32 93 57",
    "sg:postcode":"50011",
    "sg:province":"Zaragoza",
    "wof:name":"Fernandez Lau Jose",
    "wof:placetype":"venue"
},
  "geometry": {"coordinates":[-0.9913589954,41.662853241],"type":"Point"}
}