{
  "type": "Feature",
  "properties": {
    "addr:full":"Calle de Jose Antonio Primo De Rivera, 93 Arrecife Las Palmas 35500",
    "addr:housenumber":"93",
    "addr:postcode":"35500",
    "addr:street":"Calle De Jose Antonio Primo De Rivera",
    "iso:country":"ES",
    "sg:address":"Calle de Jose Antonio Primo De Rivera, 93",
    "sg:city":"Arrecife",
    "sg:orig_category":"Muebles Y Accesorios Para Cocinas Y Cuartos De Ba\u00d1o (al Por Menor)",
    "sg:phone":"+34 928 80 03 68",
    "sg:postcode":"35500",
    "sg:province":"Las Palmas",
    "wof:name":"Quesada Hernandez Francisco Javier",
    "wof:placetype":"venue"
},
  "geometry": {"coordinates":[-13.5552492142,28.9592723846],"type":"Point"}
}