{
  "type": "Feature",
  "properties": {
    "addr:full":"C/ General Weyler, 113 Inca Islas Baleares 07300",
    "addr:housenumber":"113",
    "addr:postcode":"07300",
    "addr:street":"C / General Weyler",
    "iso:country":"ES",
    "sg:address":"C/ General Weyler, 113",
    "sg:city":"Inca",
    "sg:orig_category":"Imprenta",
    "sg:phone":"+34 971 50 40 76",
    "sg:postcode":"07300",
    "sg:province":"Islas Baleares",
    "wof:name":"Graficas Amer S.l.",
    "wof:placetype":"venue"
},
  "geometry": {"coordinates":[2.9032189846,39.7165260315],"type":"Point"}
}