{
  "type": "Feature",
  "properties": {
    "addr:full":"Calle de Luis Bu\u00d1uel, 6 Zaragoza Zaragoza 50017",
    "addr:housenumber":"6",
    "addr:postcode":"50017",
    "addr:street":"Calle De Luis Bun\u0303Uel",
    "iso:country":"ES",
    "sg:address":"Calle de Luis Bu\u00d1uel, 6",
    "sg:city":"Zaragoza",
    "sg:orig_category":"Agencias Y Agentes Comerciales, Representantes",
    "sg:phone":"+34 976 34 36 63",
    "sg:postcode":"50017",
    "sg:province":"Zaragoza",
    "wof:name":"Villalba Ma\u00f1ez Guillermo",
    "wof:placetype":"venue"
},
  "geometry": {"coordinates":[-0.9195989966,41.6574363708],"type":"Point"}
}