{
  "type": "Feature",
  "properties": {
    "iso:country":"ES",
    "sg:address":"Calle de Maderuelos, 16",
    "sg:city":"Antequera",
    "sg:orig_category":"Cobro De Pr\u00c9stamos",
    "sg:phone":"+34 952 84 16 89",
    "sg:postcode":"29200",
    "sg:province":"M\u00e1laga",
    "wof:name":"Patronato De Recaudacion Provincial",
    "wof:placetype":"venue"
},
  "geometry": {"coordinates":[-4.5587210655,37.0186157227],"type":"Point"}
}