{
  "type": "Feature",
  "properties": {
    "addr:full":"Calle de Alejandro Collantes, 29 Sevilla Sevilla 41005",
    "addr:housenumber":"29",
    "addr:postcode":"41005",
    "addr:street":"Calle De Alejandro Collantes",
    "iso:country":"ES",
    "sg:address":"Calle de Alejandro Collantes, 29",
    "sg:city":"Sevilla",
    "sg:orig_category":"Internados & Ense\u00d1anza Privada",
    "sg:phone":"+34 954 57 97 19",
    "sg:postcode":"41005",
    "sg:province":"Sevilla",
    "wof:name":"Colegio Casa Del Ni\u00f1o Jesus",
    "wof:placetype":"venue"
},
  "geometry": {"coordinates":[-5.9645314217,37.3842849731],"type":"Point"}
}