{
  "type": "Feature",
  "properties": {
    "addr:full":"Carr Mas Enlaire, 7 Blanes Girona 17300",
    "addr:housenumber":"7",
    "addr:postcode":"17300",
    "addr:street":"Carr Mas Enlaire",
    "iso:country":"ES",
    "sg:address":"Carr Mas Enlaire, 7",
    "sg:city":"Blanes",
    "sg:orig_category":"Panader\u00cdas, Panader\u00cdas",
    "sg:phone":"+34 972 35 44 54",
    "sg:postcode":"17300",
    "sg:province":"Girona",
    "wof:name":"Mora 33 S.l.",
    "wof:placetype":"venue"
},
  "geometry": {"coordinates":[2.7874810696,41.6791877747],"type":"Point"}
}