{
  "type": "Feature",
  "properties": {
    "addr:full":"Calle de Luis Chamizo, 14 Siruela Badajoz 06650",
    "addr:housenumber":"14",
    "addr:postcode":"06650",
    "addr:street":"Calle De Luis Chamizo",
    "iso:country":"ES",
    "sg:address":"Calle de Luis Chamizo, 14",
    "sg:city":"Siruela",
    "sg:orig_category":"Empresas De Carpinter\u00cda De Madera",
    "sg:phone":"+34 924 63 40 35",
    "sg:postcode":"06650",
    "sg:province":"Badajoz",
    "wof:name":"Hermanos Morci S.l.",
    "wof:placetype":"venue"
},
  "geometry": {"coordinates":[-5.0440058708,38.9771156311],"type":"Point"}
}