{
  "type": "Feature",
  "properties": {
    "iso:country":"ES",
    "sg:address":"Calle de Cervantes, 25",
    "sg:city":"Villaviciosa",
    "sg:orig_category":"Molduras, Junquillos, Listones Y Molduras Perforadas",
    "sg:phone":"+34 985 89 11 84",
    "sg:postcode":"33300",
    "sg:province":"Asturias",
    "wof:name":"Arenas Martinez Maria Teresa",
    "wof:placetype":"venue"
},
  "geometry": {"coordinates":[-5.4321360588,43.4827156067],"type":"Point"}
}