{
  "type": "Feature",
  "properties": {
    "addr:full":"Carrer de Vallfogona, 6 Barcelona Barcelona 08012",
    "addr:housenumber":"6",
    "addr:postcode":"08012",
    "addr:street":"Carrer De Vallfogona",
    "iso:country":"ES",
    "sg:address":"Carrer de Vallfogona, 6",
    "sg:city":"Barcelona",
    "sg:orig_category":"Mec\u00c1nico Del Autom\u00d3vil",
    "sg:phone":"+34 932 13 63 20",
    "sg:postcode":"08012",
    "sg:province":"Barcelona",
    "wof:name":"Vi\u00f1as Vidal Javier",
    "wof:placetype":"venue"
},
  "geometry": {"coordinates":[2.1569581032,41.4026908875],"type":"Point"}
}