{
  "type": "Feature",
  "properties": {
    "iso:country":"ES",
    "sg:address":"Avda Mediterraneo, S/n",
    "sg:city":"Urbanizacion Roquetas De Mar",
    "sg:orig_category":"Pizzer\u00cdas",
    "sg:phone":"+34 950 33 36 03",
    "sg:postcode":"04740",
    "sg:province":"Almer\u00eda",
    "wof:name":"Lupi  Luciano Nicola",
    "wof:placetype":"venue"
},
  "geometry": {"coordinates":[-2.622729063,36.7349815369],"type":"Point"}
}