{
  "type": "Feature",
  "properties": {
    "addr:full":"Calle de Ramon Y Cajal, 31 Navas San Juan Ja\u00e9n 23240",
    "addr:housenumber":"31",
    "addr:postcode":"23240",
    "addr:street":"Calle De Ramon Y Cajal",
    "iso:country":"ES",
    "sg:address":"Calle de Ramon Y Cajal, 31",
    "sg:city":"Navas San Juan",
    "sg:orig_category":"Bancos",
    "sg:phone":"+34 953 68 90 20",
    "sg:postcode":"23240",
    "sg:province":"Ja\u00e9n",
    "wof:name":"Banco Espa\u00f1ol De Credito S.a.",
    "wof:placetype":"venue"
},
  "geometry": {"coordinates":[-3.3166379929,38.1833648682],"type":"Point"}
}