{
  "type": "Feature",
  "properties": {
    "iso:country":"ES",
    "sg:address":"Av Perpinya, 15",
    "sg:city":"Figueres",
    "sg:orig_category":"Empresarios",
    "sg:phone":"+34 972 50 47 52",
    "sg:postcode":"17600",
    "sg:province":"Girona",
    "wof:name":"Su\u00f1er Pages Jaime",
    "wof:placetype":"venue"
},
  "geometry": {"coordinates":[2.9563450813,42.2734069824],"type":"Point"}
}