{
  "type": "Feature",
  "properties": {
    "addr:full":"Plaz Poeta Miguel Hernandez, 4 Zaragoza Zaragoza 50007",
    "addr:housenumber":"4",
    "addr:postcode":"50007",
    "addr:street":"Plaz Poeta Miguel Hernandez",
    "iso:country":"ES",
    "sg:address":"Plaz Poeta Miguel Hernandez, 4",
    "sg:city":"Zaragoza",
    "sg:orig_category":"Zapatos (al Por Menor)",
    "sg:phone":"+34 976 37 21 02",
    "sg:postcode":"50007",
    "sg:province":"Zaragoza",
    "wof:name":"Almacenes Kaymo S. A.",
    "wof:placetype":"venue"
},
  "geometry": {"coordinates":[-0.8827803731,41.6389884949],"type":"Point"}
}