{
  "type": "Feature",
  "properties": {
    "iso:country":"ES",
    "sg:address":"Calle de Puerto Rico, 11",
    "sg:city":"Madrid",
    "sg:orig_category":"Peleter\u00cdas",
    "sg:phone":"+34 914 15 14 14",
    "sg:postcode":"28016",
    "sg:province":"Madrid",
    "wof:name":"Lopez Perez Santiago",
    "wof:placetype":"venue"
},
  "geometry": {"coordinates":[-3.6746571064,40.4533729553],"type":"Point"}
}