{
  "type": "Feature",
  "properties": {
    "addr:full":"Carrer de Doctor Carta\u00d1a (del), 3 S. Carles Rapita Tarragona 43540",
    "addr:postcode":"43540",
    "addr:street":"Carrer De Doctor Cartan\u0303A Del 3 S. Carles Rapita",
    "iso:country":"ES",
    "sg:address":"Carrer de Doctor Carta\u00d1a (del), 3",
    "sg:city":"S. Carles Rapita",
    "sg:orig_category":"Artes Gr\u00c1ficas, Artes Pl\u00c1sticas (curso)",
    "sg:phone":"+34 977 74 19 28",
    "sg:postcode":"43540",
    "sg:province":"Tarragona",
    "wof:name":"Imprenta I Papeleria Castella S.l.",
    "wof:placetype":"venue"
},
  "geometry": {"coordinates":[0.5931149721,40.6206436157],"type":"Point"}
}