{
  "type": "Feature",
  "properties": {
    "addr:full":"Calle de Andino, 3 Cartagena Murcia 30202",
    "addr:housenumber":"3",
    "addr:postcode":"30202",
    "addr:street":"Calle De Andino",
    "iso:country":"ES",
    "sg:address":"Calle de Andino, 3",
    "sg:city":"Cartagena",
    "sg:orig_category":"Sociedades, Compa\u00d1\u00cdas Aseguradoras",
    "sg:phone":"+34 968 52 91 81",
    "sg:postcode":"30202",
    "sg:province":"Murcia",
    "wof:name":"Martinez Diaz Damian",
    "wof:placetype":"venue"
},
  "geometry": {"coordinates":[-0.9859157205,37.5998954773],"type":"Point"}
}