{
  "type": "Feature",
  "properties": {
    "iso:country":"ES",
    "sg:address":"Calle de Real, 73",
    "sg:city":"Viso Marques",
    "sg:orig_category":"Telas Y Sedas (al Por Menor)",
    "sg:phone":"+34 926 33 60 16",
    "sg:postcode":"13770",
    "sg:province":"Ciudad Real",
    "wof:name":"Fernandez Monsalve Francisca",
    "wof:placetype":"venue"
},
  "geometry": {"coordinates":[-3.5626718998,38.5214424133],"type":"Point"}
}