{
  "type": "Feature",
  "properties": {
    "iso:country":"ES",
    "sg:address":"Pg Lepant, De, 51",
    "sg:city":"Casco Urbano",
    "sg:orig_category":"Quincaller\u00cda (al Por Menor)",
    "sg:phone":"+34 962 82 20 58",
    "sg:postcode":"46760",
    "sg:province":"Valencia",
    "wof:name":"Ferralux S.l.",
    "wof:placetype":"venue"
},
  "geometry": {"coordinates":[-0.2594090104,39.0749702454],"type":"Point"}
}