{
  "type": "Feature",
  "properties": {
    "addr:full":"La Quintana, S/n Trubia Asturias 33119",
    "addr:housenumber":"s",
    "addr:postcode":"33119",
    "addr:street":"/ N Trubia Asturias",
    "iso:country":"ES",
    "sg:address":"La Quintana, S/n",
    "sg:city":"Trubia",
    "sg:orig_category":"Carb\u00d3n, Carb\u00d3n De Madera (al Por Mayor)",
    "sg:phone":"+34 985 78 40 52",
    "sg:postcode":"33119",
    "sg:province":"Asturias",
    "wof:name":"Industrias Doy Manuel Morate S.l.",
    "wof:placetype":"venue"
},
  "geometry": {"coordinates":[-5.9873185158,43.3330345154],"type":"Point"}
}