{
  "type": "Feature",
  "properties": {
    "iso:country":"ES",
    "sg:address":"Calle de Fontanales, 34",
    "sg:city":"Palmas De Gran Canaria",
    "sg:orig_category":"Peluquer\u00cdas, Peluquer\u00cda Mixta",
    "sg:phone":"+34 928 46 25 01",
    "sg:postcode":"35009",
    "sg:province":"Las Palmas",
    "wof:name":"Martin Cabrera Yaiza",
    "wof:placetype":"venue"
},
  "geometry": {"coordinates":[-15.4256267548,28.1511631012],"type":"Point"}
}