{
  "type": "Feature",
  "properties": {
    "iso:country":"ES",
    "sg:address":"Plaz Iglesia, S/n",
    "sg:city":"Alberca De Las Torres",
    "sg:orig_category":"Iglesia Cat\u00d3lica",
    "sg:phone":"+34 968 84 01 56",
    "sg:postcode":"30150",
    "sg:province":"Murcia",
    "wof:name":"Obispado De Cartagena",
    "wof:placetype":"venue"
},
  "geometry": {"coordinates":[-1.1332499981,37.9421195984],"type":"Point"}
}