{
  "type": "Feature",
  "properties": {
    "addr:full":"Calle de Real, 3 Villanueva De La Ca\u00e7ada Madrid 28691",
    "addr:housenumber":"3",
    "addr:postcode":"28691",
    "addr:street":"Calle De Real",
    "iso:country":"ES",
    "sg:address":"Calle de Real, 3",
    "sg:city":"Villanueva De La Ca\u00e7ada",
    "sg:orig_category":"Servicios De Higiene Y Peluquer\u00cda Para Perros Y Gatos",
    "sg:phone":"+34 918 15 62 60",
    "sg:postcode":"28691",
    "sg:province":"Madrid",
    "wof:name":"Moreira Mayoral Manuela",
    "wof:placetype":"venue"
},
  "geometry": {"coordinates":[-4.0061058998,40.4502792358],"type":"Point"}
}