{
  "type": "Feature",
  "properties": {
    "addr:full":"Avda Castrelos, 190 Vigo Pontevedra 36210",
    "addr:housenumber":"190",
    "addr:postcode":"36210",
    "addr:street":"Avda Castrelos",
    "iso:country":"ES",
    "sg:address":"Avda Castrelos, 190",
    "sg:city":"Vigo",
    "sg:orig_category":"Transportes Por Carretera: Lotes Completos, Mercanc\u00cdas Diversas",
    "sg:phone":"+34 986 21 33 46",
    "sg:postcode":"36210",
    "sg:province":"Pontevedra",
    "wof:name":"Conxelados Castrelos S.l.",
    "wof:placetype":"venue"
},
  "geometry": {"coordinates":[-8.7324132919,42.2120475769],"type":"Point"}
}