{
  "type": "Feature",
  "properties": {
    "iso:country":"ES",
    "sg:address":"Carrer de Maravall, 17",
    "sg:city":"Benidorm",
    "sg:classifiers":[
        {
            "category":"Autos & Motor Vehicles",
            "subcategory":"Automobile Sales",
            "type":"Retail Goods"
        }
    ],
    "sg:phone":"+34 965 85 79 14",
    "sg:postcode":"03500",
    "sg:province":"Alicante",
    "wof:name":"Formacion Vial Parque S.l.",
    "wof:placetype":"venue"
},
  "geometry": {"coordinates":[-0.135018006,38.5391654968],"type":"Point"}
}