{
  "type": "Feature",
  "properties": {
    "iso:country":"ES",
    "sg:address":"Calle de Lila, 2",
    "sg:city":"Coria Rio",
    "sg:orig_category":"Ingeniero",
    "sg:phone":"+34 954 77 08 56",
    "sg:postcode":"41100",
    "sg:province":"Sevilla",
    "wof:name":"Garcia Tercero Manuel Alfonso",
    "wof:placetype":"venue"
},
  "geometry": {"coordinates":[-6.0563468933,37.2914276123],"type":"Point"}
}