{
  "type": "Feature",
  "properties": {
    "addr:full":"Conde De Cocentaina, 19 Cocentaina Alicante 03820",
    "addr:housenumber":"19",
    "addr:postcode":"03820",
    "addr:street":"Conde;Cocentaina",
    "iso:country":"ES",
    "sg:address":"Conde De Cocentaina, 19",
    "sg:city":"Cocentaina",
    "sg:orig_category":"Ropa Para Ni\u00d1os (al Por Menor)",
    "sg:phone":"+34 965 59 03 85",
    "sg:postcode":"03820",
    "sg:province":"Alicante",
    "wof:name":"Reig Girones Maria Jose",
    "wof:placetype":"venue"
},
  "geometry": {"coordinates":[-0.4402590096,38.7428245544],"type":"Point"}
}