{
  "type": "Feature",
  "properties": {
    "iso:country":"ES",
    "sg:address":"Barr Fondo Lugar, 52",
    "sg:city":"Veigadecabo",
    "sg:orig_category":"Agencias Y Agentes Comerciales, Representantes",
    "sg:phone":"+34 988 32 08 18",
    "sg:postcode":"32300",
    "sg:province":"Ourense",
    "wof:name":"Gonzalez Dato Elena",
    "wof:placetype":"venue"
},
  "geometry": {"coordinates":[-6.9837059975,42.4104614258],"type":"Point"}
}