{
  "type": "Feature",
  "properties": {
    "addr:full":"Calle de Espejo Blancas, 9 Cordoba C\u00f3rdoba 14006",
    "addr:housenumber":"9",
    "addr:postcode":"14006",
    "addr:street":"Calle De Espejo Blancas;Co\u0301Rdoba",
    "iso:country":"ES",
    "sg:address":"Calle de Espejo Blancas, 9",
    "sg:city":"Cordoba",
    "sg:orig_category":"Empresas De Limpieza",
    "sg:phone":"+34 957 28 08 17",
    "sg:postcode":"14006",
    "sg:province":"C\u00f3rdoba",
    "wof:name":"Saneamientos De Cordoba",
    "wof:placetype":"venue"
},
  "geometry": {"coordinates":[-4.7782559395,37.898601532],"type":"Point"}
}