{
  "type": "Feature",
  "properties": {
    "iso:country":"ES",
    "sg:address":"Fco Bergamin, 7",
    "sg:city":"Iru\u00f1a",
    "sg:orig_category":"Abogados",
    "sg:phone":"+34 948 24 93 50",
    "sg:postcode":"31003",
    "sg:province":"Navarra",
    "wof:name":"Jare\u00f1o Zuazu Rodolfo",
    "wof:placetype":"venue"
},
  "geometry": {"coordinates":[-1.6411759853,42.812664032],"type":"Point"}
}