{
  "type": "Feature",
  "properties": {
    "iso:country":"ES",
    "sg:address":"Calle de Atocha, 19",
    "sg:city":"Madrid",
    "sg:orig_category":"Artesan\u00cda De Mesa: Cristaler\u00cda, Vajilla, Orfebrer\u00cda (fabricaci\u00d3n, Al Por Mayor)",
    "sg:phone":"+34 914 20 09 28",
    "sg:postcode":"28012",
    "sg:province":"Madrid",
    "wof:name":"Don Galo S.a.",
    "wof:placetype":"venue"
},
  "geometry": {"coordinates":[-3.698489666,40.4120330811],"type":"Point"}
}