{
  "type": "Feature",
  "properties": {
    "iso:country":"ES",
    "sg:address":"Calle de Eduardo Dato, 54",
    "sg:city":"Utrera",
    "sg:orig_category":"Empresas De Pintura Y Revestimientos",
    "sg:phone":"+34 955 86 12 35",
    "sg:postcode":"41710",
    "sg:province":"Sevilla",
    "wof:name":"Pinturas Aguimar S.l.",
    "wof:placetype":"venue"
},
  "geometry": {"coordinates":[-5.7885189056,37.182144165],"type":"Point"}
}