{
  "type": "Feature",
  "properties": {
    "iso:country":"ES",
    "sg:address":"Calle de Pizarro, 14",
    "sg:city":"Moraleja",
    "sg:orig_category":"Ropa Para Se\u00d1oras Y Caballeros (al Por Menor)",
    "sg:phone":"+34 927 14 75 51",
    "sg:postcode":"10840",
    "sg:province":"C\u00e1ceres",
    "wof:name":"Martin Vazquez Esther",
    "wof:placetype":"venue"
},
  "geometry": {"coordinates":[-6.6612420082,40.0670967102],"type":"Point"}
}