{
  "type": "Feature",
  "properties": {
    "iso:country":"ES",
    "sg:address":"Pla\u00c7 Porta Murada, 7",
    "sg:city":"Santanyi",
    "sg:orig_category":"Inmobiliaria (agencias)",
    "sg:phone":"+34 971 64 20 70",
    "sg:postcode":"07650",
    "sg:province":"Islas Baleares",
    "sg:website":"www.piedra-nova.com",
    "wof:name":"Piedra Nova S.l.",
    "wof:placetype":"venue"
},
  "geometry": {"coordinates":[3.1282689571,39.354598999],"type":"Point"}
}