{
  "type": "Feature",
  "properties": {
    "addr:full":"Carr Tirant Lo Blanc, 17 Vilavella Castell\u00f3n 12526",
    "addr:housenumber":"17",
    "addr:postcode":"12526",
    "addr:street":"Carr Tirant Lo Blanc;Castello\u0301N",
    "iso:country":"ES",
    "sg:address":"Carr Tirant Lo Blanc, 17",
    "sg:city":"Vilavella",
    "sg:orig_category":"Mec\u00c1nico Del Autom\u00d3vil",
    "sg:phone":"+34 964 67 72 01",
    "sg:postcode":"12526",
    "sg:province":"Castell\u00f3n",
    "wof:name":"Cerezo Pitarch Jose Enrique",
    "wof:placetype":"venue"
},
  "geometry": {"coordinates":[-0.0456800014,39.9851417542],"type":"Point"}
}