{
  "type": "Feature",
  "properties": {
    "addr:full":"Av Meridiana, 34 Barcelona Barcelona 08018",
    "addr:housenumber":"34",
    "addr:postcode":"08018",
    "addr:street":"Meridiana",
    "iso:country":"ES",
    "sg:address":"Av Meridiana, 34",
    "sg:city":"Barcelona",
    "sg:orig_category":"Asesor\u00cda, Estudio Y Control Medioambiental",
    "sg:phone":"+34 934 85 62 48",
    "sg:postcode":"08018",
    "sg:province":"Barcelona",
    "wof:name":"Dasi Informatica S.l.",
    "wof:placetype":"venue"
},
  "geometry": {"coordinates":[2.1870310307,41.395198822],"type":"Point"}
}