{
  "type": "Feature",
  "properties": {
    "addr:full":"Calle de Gorbea, 16 Vitoria-gasteiz \u00c1lava 01012",
    "addr:housenumber":"16",
    "addr:postcode":"01012",
    "addr:street":"Calle De Gorbea",
    "iso:country":"ES",
    "sg:address":"Calle de Gorbea, 16",
    "sg:city":"Vitoria-gasteiz",
    "sg:orig_category":"Herboristas (al Por Menor)",
    "sg:phone":"+34 945 22 52 05",
    "sg:postcode":"01012",
    "sg:province":"\u00c1lava",
    "wof:name":"Vitalsana S.l.",
    "wof:placetype":"venue"
},
  "geometry": {"coordinates":[-2.6798839569,42.8498268127],"type":"Point"}
}