{
  "type": "Feature",
  "properties": {
    "iso:country":"ES",
    "sg:address":"Ctra. Gi. Banyoles, S/n",
    "sg:city":"Riudellots Creu",
    "sg:orig_category":"Centros De Educaci\u00d3n Especial",
    "sg:phone":"+34 972 17 14 42",
    "sg:postcode":"17842",
    "sg:province":"Girona",
    "wof:name":"Asociacion Educativa Valle Del Terri",
    "wof:placetype":"venue"
},
  "geometry": {"coordinates":[2.7933084965,42.102558136],"type":"Point"}
}