{
  "type": "Feature",
  "properties": {
    "iso:country":"ES",
    "sg:address":"Carrer de Granollers, 4",
    "sg:city":"Cardedeu",
    "sg:orig_category":"Bazares, Art\u00cdculos De Limpieza Y De Cocina (al Por Menor)",
    "sg:phone":"+34 938 71 26 20",
    "sg:postcode":"08440",
    "sg:province":"Barcelona",
    "wof:name":"Rosillo Norte Jose Antonio",
    "wof:placetype":"venue"
},
  "geometry": {"coordinates":[2.3616719246,41.6414451599],"type":"Point"}
}