{
  "type": "Feature",
  "properties": {
    "addr:full":"Cueva Sta(mascarell), 25 Mascarell Castell\u00f3n 12529",
    "addr:housenumber":"25",
    "addr:postcode":"12529",
    "addr:street":"Mascarell;Castello\u0301N",
    "iso:country":"ES",
    "sg:address":"Cueva Sta(mascarell), 25",
    "sg:city":"Mascarell",
    "sg:orig_category":"Institutos De Belleza",
    "sg:phone":"+34 964 67 35 52",
    "sg:postcode":"12529",
    "sg:province":"Castell\u00f3n",
    "wof:name":"Lozano Martinez Maria Isabel",
    "wof:placetype":"venue"
},
  "geometry": {"coordinates":[-0.1409360021,39.8597068787],"type":"Point"}
}