{
  "type": "Feature",
  "properties": {
    "addr:full":"Calle de Nueva, 2 Elda Alicante 03600",
    "addr:housenumber":"2",
    "addr:postcode":"03600",
    "addr:street":"Calle De Nueva",
    "iso:country":"ES",
    "sg:address":"Calle de Nueva, 2",
    "sg:city":"Elda",
    "sg:orig_category":"Farmacias",
    "sg:phone":"+34 965 38 01 72",
    "sg:postcode":"03600",
    "sg:province":"Alicante",
    "wof:name":"Rico Vidal Hortensia",
    "wof:placetype":"venue"
},
  "geometry": {"coordinates":[-0.7965499759,38.4778823853],"type":"Point"}
}