{
  "type": "Feature",
  "properties": {
    "addr:full":"Calle de Lourido, 16 Meira Lugo 27240",
    "addr:housenumber":"16",
    "addr:postcode":"27240",
    "addr:street":"Calle De Lourido",
    "iso:country":"ES",
    "sg:address":"Calle de Lourido, 16",
    "sg:city":"Meira",
    "sg:orig_category":"Fabricaci\u00d3n De Juguetes Autom\u00c1ticos",
    "sg:phone":"+34 982 33 04 03",
    "sg:postcode":"27240",
    "sg:province":"Lugo",
    "wof:name":"Recreativos Fiallega S. L.",
    "wof:placetype":"venue"
},
  "geometry": {"coordinates":[-7.2954688072,43.2133407593],"type":"Point"}
}