{
  "type": "Feature",
  "properties": {
    "iso:country":"ES",
    "sg:address":"Calle de Caravaca De La Cruz, 4",
    "sg:city":"Cordoba",
    "sg:orig_category":"Florister\u00cdas",
    "sg:phone":"+34 957 43 81 15",
    "sg:postcode":"14007",
    "sg:province":"C\u00f3rdoba",
    "sg:website":"www.floristeriarossan.com",
    "wof:name":"Morales Lopez Ana Rosa",
    "wof:placetype":"venue"
},
  "geometry": {"coordinates":[-4.7665138245,37.8934783936],"type":"Point"}
}