{
  "type": "Feature",
  "properties": {
    "iso:country":"ES",
    "sg:address":"Cmno Valderribas, 94",
    "sg:city":"Madrid",
    "sg:orig_category":"Mec\u00c1nico Del Autom\u00d3vil",
    "sg:phone":"+34 914 30 58 32",
    "sg:postcode":"28038",
    "sg:province":"Madrid",
    "wof:name":"Moratilla Sanchez Jose Maria",
    "wof:placetype":"venue"
},
  "geometry": {"coordinates":[-3.66071105,40.3989868164],"type":"Point"}
}