{
  "type": "Feature",
  "properties": {
    "addr:full":"Calle de Pascual Amat, 28 Yecla Murcia 30510",
    "addr:housenumber":"28",
    "addr:postcode":"30510",
    "addr:street":"Calle De Pascual Amat",
    "iso:country":"ES",
    "sg:address":"Calle de Pascual Amat, 28",
    "sg:city":"Yecla",
    "sg:orig_category":"Electricidad: Instaladores",
    "sg:phone":"+34 968 79 11 23",
    "sg:postcode":"30510",
    "sg:province":"Murcia",
    "wof:name":"Candela Palao Antonio",
    "wof:placetype":"venue"
},
  "geometry": {"coordinates":[-1.1168650389,38.6150665283],"type":"Point"}
}