{
  "type": "Feature",
  "properties": {
    "addr:full":"Avda Montes De Oca (de Los), 1 San Sebastian De Los Reyes Madrid 28700",
    "addr:housenumber":"1",
    "addr:postcode":"28700",
    "addr:street":"Avda Montes De Oca De Los",
    "iso:country":"ES",
    "sg:address":"Avda Montes De Oca (de Los), 1",
    "sg:city":"San Sebastian De Los Reyes",
    "sg:orig_category":"Agencias De Viajes",
    "sg:phone":"+34 916 63 87 34",
    "sg:postcode":"28700",
    "sg:province":"Madrid",
    "wof:name":"Viajes El Corte Ingles S.a.",
    "wof:placetype":"venue"
},
  "geometry": {"coordinates":[-3.616202116,40.5532722473],"type":"Point"}
}