{
  "type": "Feature",
  "properties": {
    "addr:full":"Calle de Montera, 8 Madrid Madrid 28013",
    "addr:housenumber":"8",
    "addr:postcode":"madrid;28013",
    "addr:street":"Calle De Montera",
    "iso:country":"ES",
    "sg:address":"Calle de Montera, 8",
    "sg:city":"Madrid",
    "sg:orig_category":"Perfumer\u00cda (al Por Menor)",
    "sg:phone":"+34 915 31 48 58",
    "sg:postcode":"28013",
    "sg:province":"Madrid",
    "sg:website":"www.ysusi-spring.com",
    "wof:name":"Ysusi Delgado Julio",
    "wof:placetype":"venue"
},
  "geometry": {"coordinates":[-3.7029495239,40.4174423218],"type":"Point"}
}