{
  "type": "Feature",
  "properties": {
    "addr:full":"Calle de San Antonio, 1 Arahal Sevilla 41600",
    "addr:housenumber":"1",
    "addr:postcode":"41600",
    "addr:street":"Calle De San Antonio",
    "iso:country":"ES",
    "sg:address":"Calle de San Antonio, 1",
    "sg:city":"Arahal",
    "sg:orig_category":"Pescader\u00cdas (al Por Menor)",
    "sg:phone":"+34 955 84 13 32",
    "sg:postcode":"41600",
    "sg:province":"Sevilla",
    "wof:name":"Jose Duque S.l.",
    "wof:placetype":"venue"
},
  "geometry": {"coordinates":[-5.542845726,37.2589950562],"type":"Point"}
}