{
  "type": "Feature",
  "properties": {
    "iso:country":"ES",
    "sg:address":"Carrer de Isaac Albeniz (d'), 10",
    "sg:city":"Pineda",
    "sg:orig_category":"Plomeros",
    "sg:phone":"+34 977 37 09 07",
    "sg:postcode":"43480",
    "sg:province":"Tarragona",
    "wof:name":"202020 Grupisman S.l.",
    "wof:placetype":"venue"
},
  "geometry": {"coordinates":[1.179724,41.076351],"type":"Point"}
}