{
  "type": "Feature",
  "properties": {
    "iso:country":"ES",
    "sg:address":"Calle de Lorca, 5",
    "sg:city":"Valencia",
    "sg:orig_category":"Asesor\u00cda Fiscal Y Jur\u00cddica",
    "sg:phone":"+34 963 84 36 43",
    "sg:postcode":"46018",
    "sg:province":"Valencia",
    "wof:name":"Cifre Garcia Luis Antonio",
    "wof:placetype":"venue"
},
  "geometry": {"coordinates":[-0.3917300105,39.4685058594],"type":"Point"}
}