{
  "type": "Feature",
  "properties": {
    "addr:full":"Ctra. Vilanna, S/n Vilanna Girona 17163",
    "addr:housenumber":"s",
    "addr:postcode":"17163",
    "addr:street":"Ctra. Vilanna;/ N Vilanna",
    "iso:country":"ES",
    "sg:address":"Ctra. Vilanna, S/n",
    "sg:city":"Vilanna",
    "sg:orig_category":"Empresas De Carpinter\u00cda De Madera",
    "sg:phone":"+34 972 42 33 69",
    "sg:postcode":"17163",
    "sg:province":"Girona",
    "wof:name":"Furtia Puig Albert",
    "wof:placetype":"venue"
},
  "geometry": {"coordinates":[2.703592062,41.971157074],"type":"Point"}
}