{
  "type": "Feature",
  "properties": {
    "addr:full":"Calle de Ciruela, 16 Majadahonda Madrid 28220",
    "addr:housenumber":"16",
    "addr:postcode":"28220",
    "addr:street":"Calle De Ciruela",
    "iso:country":"ES",
    "sg:address":"Calle de Ciruela, 16",
    "sg:city":"Majadahonda",
    "sg:orig_category":"Muebles, Minoristas",
    "sg:phone":"+34 916 02 79 02",
    "sg:postcode":"28220",
    "sg:province":"Madrid",
    "sg:website":"www.muebleslafabrica.com",
    "wof:name":"Okapi S.a.",
    "wof:placetype":"venue"
},
  "geometry": {"coordinates":[-3.8703999519,40.4537582397],"type":"Point"}
}