{
  "type": "Feature",
  "properties": {
    "iso:country":"ES",
    "sg:address":"Calle de Martires (de Los), 27",
    "sg:city":"Boadilla Del Monte",
    "sg:orig_category":"Bancos",
    "sg:phone":"+34 916 33 16 22",
    "sg:postcode":"28660",
    "sg:province":"Madrid",
    "wof:name":"Banco Popular Espa\u00f1ol S.a.",
    "wof:placetype":"venue"
},
  "geometry": {"coordinates":[-3.8803830147,40.4098739624],"type":"Point"}
}