{
  "type": "Feature",
  "properties": {
    "iso:country":"ES",
    "sg:address":"Calle de Ayala, 57",
    "sg:city":"Madrid",
    "sg:orig_category":"Inmobiliaria (agencias)",
    "sg:phone":"+34 914 02 38 23",
    "sg:postcode":"28001",
    "sg:province":"Madrid",
    "wof:name":"Valderrama Bonnet Mariano Jose",
    "wof:placetype":"venue"
},
  "geometry": {"coordinates":[-3.6778159142,40.4275512695],"type":"Point"}
}