{
  "type": "Feature",
  "properties": {
    "addr:full":"Avda Derechos Humanos, 15 Alhaurin El Grande M\u00e1laga 29120",
    "addr:housenumber":"15",
    "addr:postcode":"29120",
    "addr:street":"Avda Derechos Humanos",
    "iso:country":"ES",
    "sg:address":"Avda Derechos Humanos, 15",
    "sg:city":"Alhaurin El Grande",
    "sg:orig_category":"Plomeros",
    "sg:phone":"+34 952 49 12 33",
    "sg:postcode":"29120",
    "sg:province":"M\u00e1laga",
    "wof:name":"Fontaneria Alhagua S.l.",
    "wof:placetype":"venue"
},
  "geometry": {"coordinates":[-4.6793789864,36.6469116211],"type":"Point"}
}