{
  "type": "Feature",
  "properties": {
    "addr:full":"Pase San Segundo, 22 Abla Almer\u00eda 04510",
    "addr:housenumber":"22",
    "addr:postcode":"04510",
    "addr:street":"Segundo",
    "iso:country":"ES",
    "sg:address":"Pase San Segundo, 22",
    "sg:city":"Abla",
    "sg:orig_category":"Bebidas",
    "sg:phone":"+34 950 35 12 21",
    "sg:postcode":"04510",
    "sg:province":"Almer\u00eda",
    "wof:name":"Distribuciones Montagon Sc",
    "wof:placetype":"venue"
},
  "geometry": {"coordinates":[-2.7757019997,37.1436309814],"type":"Point"}
}