{
  "type": "Feature",
  "properties": {
    "addr:full":"Crt Avila-toledo, Km. 0054,8 Escalona Toledo 45910",
    "addr:postcode":"45910",
    "addr:street":"Avila-Toledo Km. 0054,8",
    "iso:country":"ES",
    "sg:address":"Crt Avila-toledo, Km. 0054,8",
    "sg:city":"Escalona",
    "sg:orig_category":"Mec\u00c1nico Del Autom\u00d3vil",
    "sg:phone":"+34 925 78 03 38",
    "sg:postcode":"45910",
    "sg:province":"Toledo",
    "wof:name":"Robledo Mayorga Angel",
    "wof:placetype":"venue"
},
  "geometry": {"coordinates":[-4.4054641724,40.1705665588],"type":"Point"}
}