{
  "type": "Feature",
  "properties": {
    "addr:full":"Carrer de Herrera, 58 Mataro Barcelona 08301",
    "addr:housenumber":"58",
    "addr:postcode":"08301",
    "addr:street":"Carrer De Herrera",
    "iso:country":"ES",
    "sg:address":"Carrer de Herrera, 58",
    "sg:city":"Mataro",
    "sg:orig_category":"Imprenta",
    "sg:phone":"+34 937 90 12 49",
    "sg:postcode":"08301",
    "sg:province":"Barcelona",
    "wof:name":"Graficas Rotativas S. A.",
    "wof:placetype":"venue"
},
  "geometry": {"coordinates":[2.4528799057,41.5433731079],"type":"Point"}
}