{
  "type": "Feature",
  "properties": {
    "iso:country":"ES",
    "sg:address":"Calle de Honsario, 6",
    "sg:city":"Jerez De La Frontera",
    "sg:orig_category":"Hoteles",
    "sg:phone":"+34 956 34 68 62",
    "sg:postcode":"11402",
    "sg:province":"C\u00e1diz",
    "wof:name":"Hotel La Albarizuela S.l",
    "wof:placetype":"venue"
},
  "geometry": {"coordinates":[-6.1322717667,36.684135437],"type":"Point"}
}