{
  "type": "Feature",
  "properties": {
    "addr:full":"Calle de Zubelzu, 2 Irun Guip\u00f9zcoa 20301",
    "addr:housenumber":"2",
    "addr:postcode":"20301",
    "addr:street":"Calle De Zubelzu;Guipu\u0300Zcoa",
    "iso:country":"ES",
    "sg:address":"Calle de Zubelzu, 2",
    "sg:city":"Irun",
    "sg:orig_category":"Carnicer\u00cdas, Carnicer\u00cdas",
    "sg:phone":"+34 943 61 89 23",
    "sg:postcode":"20301",
    "sg:province":"Guip\u00f9zcoa",
    "wof:name":"Comeron Miguel Pablo",
    "wof:placetype":"venue"
},
  "geometry": {"coordinates":[-1.8074760437,43.3420982361],"type":"Point"}
}