{
  "type": "Feature",
  "properties": {
    "addr:full":"Ctra Zaragoza, 41 Alfaro La Rioja 26540",
    "addr:housenumber":"41",
    "addr:postcode":"26540",
    "addr:street":"Ctra Zaragoza;Rioja",
    "iso:country":"ES",
    "sg:address":"Ctra Zaragoza, 41",
    "sg:city":"Alfaro",
    "sg:orig_category":"Productos Fitosanitarios (negocio, Aplicaci\u00d3n)",
    "sg:phone":"+34 941 18 21 05",
    "sg:postcode":"26540",
    "sg:province":"La Rioja",
    "wof:name":"Agrotecnica Del Norte S.l.",
    "wof:placetype":"venue"
},
  "geometry": {"coordinates":[-1.7542448044,42.1771812439],"type":"Point"}
}