{
  "type": "Feature",
  "properties": {
    "iso:country":"ES",
    "sg:address":"Calle de Donantes De Sangre, S/n",
    "sg:city":"Lahiguera",
    "sg:orig_category":"Venta, Instalaci\u00d3n De Calefacci\u00d3n",
    "sg:phone":"+34 953 53 01 17",
    "sg:postcode":"23146",
    "sg:province":"Ja\u00e9n",
    "wof:name":"Zafra Gavilan Sebastian",
    "wof:placetype":"venue"
},
  "geometry": {"coordinates":[-3.9850199223,37.9702148438],"type":"Point"}
}