{
  "type": "Feature",
  "properties": {
    "addr:full":"Avda Pero Mingo (de), S/n Sevilla Sevilla 41016",
    "addr:housenumber":"s / n",
    "addr:postcode":"41016",
    "addr:street":"Avda Pero",
    "iso:country":"ES",
    "sg:address":"Avda Pero Mingo (de), S/n",
    "sg:city":"Sevilla",
    "sg:orig_category":"Muebles, Minoristas",
    "sg:phone":"+34 954 40 82 47",
    "sg:postcode":"41016",
    "sg:province":"Sevilla",
    "wof:name":"Garcia Baquero S.a.",
    "wof:placetype":"venue"
},
  "geometry": {"coordinates":[-5.912853241,37.3857803345],"type":"Point"}
}