{
  "type": "Feature",
  "properties": {
    "iso:country":"ES",
    "sg:address":"Carrer de Pompeu Fabra, 36",
    "sg:city":"Lloren\u00e7 Penedes",
    "sg:orig_category":"Promotores Constructores",
    "sg:phone":"+34 977 67 74 08",
    "sg:postcode":"43712",
    "sg:province":"Tarragona",
    "wof:name":"Construcciones Raventos-inglada S.l.",
    "wof:placetype":"venue"
},
  "geometry": {"coordinates":[1.5531100035,41.2823829651],"type":"Point"}
}