{
  "type": "Feature",
  "properties": {
    "iso:country":"ES",
    "sg:address":"Calle de Cobre, 22",
    "sg:city":"Moraleja Enmedio",
    "sg:orig_category":"Perfumer\u00cda Y Cosm\u00c9tica (fabricaci\u00d3n, Al Por Mayor)",
    "sg:phone":"+34 913 67 84 56",
    "sg:postcode":"28950",
    "sg:province":"Madrid",
    "wof:name":"Laboratorios Ximart S. A.",
    "wof:placetype":"venue"
},
  "geometry": {"coordinates":[-3.8466246128,40.2644691467],"type":"Point"}
}