{
  "type": "Feature",
  "properties": {
    "iso:country":"ES",
    "sg:address":"Calle de Acebal Idigoras, 2",
    "sg:city":"Bilbao",
    "sg:orig_category":"Agencias De Aduana",
    "sg:phone":"+34 944 24 82 59",
    "sg:postcode":"48001",
    "sg:province":"Vizcaya",
    "wof:name":"Sugamon Bilbao S.l.",
    "wof:placetype":"venue"
},
  "geometry": {"coordinates":[-2.9250950813,43.2635231018],"type":"Point"}
}