{
  "type": "Feature",
  "properties": {
    "iso:country":"ES",
    "sg:address":"Ctra Loeches, 31",
    "sg:city":"Torrejon Ardoz",
    "sg:orig_category":"Asesor\u00cda Sobre Comunicaci\u00d3n De Empresas",
    "sg:phone":"+34 916 74 99 78",
    "sg:postcode":"28850",
    "sg:province":"Madrid",
    "wof:name":"World Service Hispania S.l. Unipersonal",
    "wof:placetype":"venue"
},
  "geometry": {"coordinates":[-3.4708285332,40.4506950378],"type":"Point"}
}