{
  "type": "Feature",
  "properties": {
    "iso:country":"ES",
    "sg:address":"Calle de Santo Domingo De La Calzada, 2",
    "sg:city":"Arnedo",
    "sg:orig_category":"Servicios De Telecomunicaciones",
    "sg:phone":"+34 941 38 50 55",
    "sg:postcode":"26580",
    "sg:province":"La Rioja",
    "wof:name":"Xtra Telecom S.a",
    "wof:placetype":"venue"
},
  "geometry": {"coordinates":[-2.1003940105,42.2264671326],"type":"Point"}
}