{
  "type": "Feature",
  "properties": {
    "addr:full":"Calle de San Francisco, 31 Teruel Teruel 44001",
    "addr:housenumber":"31",
    "addr:postcode":"44001",
    "addr:street":"Calle De San Francisco",
    "iso:country":"ES",
    "sg:address":"Calle de San Francisco, 31",
    "sg:city":"Teruel",
    "sg:orig_category":"Contables",
    "sg:phone":"+34 978 60 06 05",
    "sg:postcode":"44001",
    "sg:province":"Teruel",
    "wof:name":"Consultores Fiscales De Teruel S.l.",
    "wof:placetype":"venue"
},
  "geometry": {"coordinates":[-1.1106179953,40.3432235718],"type":"Point"}
}