{
  "type": "Feature",
  "properties": {
    "addr:full":"Calle de Magallanes, 13 Madrid Madrid 28015",
    "addr:housenumber":"13",
    "addr:postcode":"madrid;28015",
    "addr:street":"Calle De Magallanes",
    "iso:country":"ES",
    "sg:address":"Calle de Magallanes, 13",
    "sg:city":"Madrid",
    "sg:orig_category":"Reposter\u00cdas",
    "sg:phone":"+34 914 46 97 15",
    "sg:postcode":"28015",
    "sg:province":"Madrid",
    "wof:name":"Arias Pando David",
    "wof:placetype":"venue"
},
  "geometry": {"coordinates":[-3.7056956291,40.4342842102],"type":"Point"}
}