{
  "type": "Feature",
  "properties": {
    "iso:country":"ES",
    "sg:address":"Pase Larratxo De, 26",
    "sg:city":"Donostia-san Sebastian",
    "sg:orig_category":"Mec\u00c1nico Del Autom\u00d3vil",
    "sg:phone":"+34 943 39 22 39",
    "sg:postcode":"20017",
    "sg:province":"Guip\u00f9zcoa",
    "wof:name":"Jesus Lozano Garcia",
    "wof:placetype":"venue"
},
  "geometry": {"coordinates":[-1.9394210577,43.313117981],"type":"Point"}
}