{
  "type": "Feature",
  "properties": {
    "addr:full":"Carr Pare Marchena, Del, 2 Carcaixent Valencia 46740",
    "addr:housenumber":"2",
    "addr:postcode":"46740",
    "addr:street":"Carr Pare Marchena Del",
    "iso:country":"ES",
    "sg:address":"Carr Pare Marchena, Del, 2",
    "sg:city":"Carcaixent",
    "sg:orig_category":"Asociaciones Y Clubs Deportivos",
    "sg:phone":"+34 962 46 13 25",
    "sg:postcode":"46740",
    "sg:province":"Valencia",
    "wof:name":"Centresport Carcaixent S.l.",
    "wof:placetype":"venue"
},
  "geometry": {"coordinates":[-0.4491659999,39.1212882996],"type":"Point"}
}