{
  "type": "Feature",
  "properties": {
    "addr:full":"Carr Caragol, 22 Ciutadella Menorca Islas Baleares 07760",
    "addr:housenumber":"22",
    "addr:postcode":"07760",
    "addr:street":"Carr Caragol",
    "iso:country":"ES",
    "sg:address":"Carr Caragol, 22",
    "sg:city":"Ciutadella Menorca",
    "sg:orig_category":"Electricidad: Instaladores",
    "sg:phone":"+34 971 38 18 04",
    "sg:postcode":"07760",
    "sg:province":"Islas Baleares",
    "wof:name":"Sabatel Morla Rafael",
    "wof:placetype":"venue"
},
  "geometry": {"coordinates":[3.8446409702,40.00573349],"type":"Point"}
}