{
  "type": "Feature",
  "properties": {
    "addr:full":"Carr Concepcion Arenal, 12 Burjassot Valencia 46100",
    "addr:housenumber":"12",
    "addr:postcode":"46100",
    "addr:street":"Carr Concepcion Arenal",
    "iso:country":"ES",
    "sg:address":"Carr Concepcion Arenal, 12",
    "sg:city":"Burjassot",
    "sg:orig_category":"Cl\u00cdnicas Dentales",
    "sg:phone":"+34 963 64 02 02",
    "sg:postcode":"46100",
    "sg:province":"Valencia",
    "wof:name":"Mora Zinke Antonio Jose",
    "wof:placetype":"venue"
},
  "geometry": {"coordinates":[-0.4114550054,39.5097045898],"type":"Point"}
}