{
  "type": "Feature",
  "properties": {
    "iso:country":"ES",
    "sg:address":"Calle de Paulino Mendivil, 8",
    "sg:city":"Getxo",
    "sg:orig_category":"Abogados",
    "sg:phone":"+34 944 80 20 80",
    "sg:postcode":"48930",
    "sg:province":"Vizcaya",
    "wof:name":"Domingo Iglesias Vidaetxea",
    "wof:placetype":"venue"
},
  "geometry": {"coordinates":[-3.0151400566,43.3250694275],"type":"Point"}
}