{
  "type": "Feature",
  "properties": {
    "iso:country":"ES",
    "sg:address":"Calle de Circunvalacion, S/n",
    "sg:city":"Paredes Nava",
    "sg:orig_category":"Distribuci\u00d3n De Petr\u00d3leo Y Derivados",
    "sg:phone":"+34 979 83 10 05",
    "sg:postcode":"34300",
    "sg:province":"Palencia",
    "wof:name":"Fernandez Herrezuelo Mariano",
    "wof:placetype":"venue"
},
  "geometry": {"coordinates":[-4.6889352798,42.1511917114],"type":"Point"}
}