{
  "type": "Feature",
  "properties": {
    "addr:full":"Rua Espirito Santo, 9 Ferrol La Coru\u00f1a 15401",
    "addr:housenumber":"9",
    "addr:postcode":"15401",
    "addr:street":"Rua Espirito Santo;La Corun\u0303A",
    "iso:country":"ES",
    "sg:address":"Rua Espirito Santo, 9",
    "sg:city":"Ferrol",
    "sg:orig_category":"Organizaciones Profesionales",
    "sg:phone":"+34 981 35 73 12",
    "sg:postcode":"15401",
    "sg:province":"La Coru\u00f1a",
    "wof:name":"Martima Consiflet S.a.",
    "wof:placetype":"venue"
},
  "geometry": {"coordinates":[-8.2428836823,43.4780654907],"type":"Point"}
}