{
  "type": "Feature",
  "properties": {
    "iso:country":"ES",
    "sg:address":"Calle de Pintor Velazquez, S/n",
    "sg:city":"Peligros",
    "sg:classifiers":[
        {
            "category":"Taxi",
            "type":"Transportation"
        }
    ],
    "sg:phone":"+34 958 40 04 91",
    "sg:postcode":"18210",
    "sg:province":"Granada",
    "wof:name":"Marin Ortega Pedro",
    "wof:placetype":"venue"
},
  "geometry": {"coordinates":[-3.6261909008,37.2328987122],"type":"Point"}
}