{
  "type": "Feature",
  "properties": {
    "addr:full":"Calle de Correduria, 40 Sevilla Sevilla 41002",
    "addr:housenumber":"40",
    "addr:postcode":"41002",
    "addr:street":"Calle De Correduria",
    "iso:country":"ES",
    "sg:address":"Calle de Correduria, 40",
    "sg:city":"Sevilla",
    "sg:orig_category":"Costureras",
    "sg:phone":"+34 954 37 78 50",
    "sg:postcode":"41002",
    "sg:province":"Sevilla",
    "wof:name":"Campos Carmona Adela",
    "wof:placetype":"venue"
},
  "geometry": {"coordinates":[-5.9921660423,37.3978157043],"type":"Point"}
}