{
  "type": "Feature",
  "properties": {
    "addr:full":"Calle de Mayor, 18 Villafranca Campo Teruel 44394",
    "addr:housenumber":"18",
    "addr:postcode":"44394",
    "addr:street":"Calle De Mayor",
    "iso:country":"ES",
    "sg:address":"Calle de Mayor, 18",
    "sg:city":"Villafranca Campo",
    "sg:orig_category":"Reposter\u00cdas",
    "sg:phone":"+34 978 86 33 01",
    "sg:postcode":"44394",
    "sg:province":"Teruel",
    "wof:name":"Royo Yuste Manuel",
    "wof:placetype":"venue"
},
  "geometry": {"coordinates":[-1.3464870453,40.695274353],"type":"Point"}
}