{
  "type": "Feature",
  "properties": {
    "iso:country":"ES",
    "sg:address":"Rua Xasmins (dos), 1",
    "sg:city":"Santiago De Compostela",
    "sg:orig_category":"Ingeniero",
    "sg:phone":"+34 981 58 30 71",
    "sg:postcode":"15704",
    "sg:province":"La Coru\u00f1a",
    "wof:name":"Moreira Matos Luis",
    "wof:placetype":"venue"
},
  "geometry": {"coordinates":[-8.5431041718,42.8840293884],"type":"Point"}
}