{
  "type": "Feature",
  "properties": {
    "addr:full":"Calle de Infanta Mercedes, 68 Madrid Madrid 28020",
    "addr:housenumber":"68",
    "addr:postcode":"madrid;28020",
    "addr:street":"Calle De Infanta Mercedes",
    "iso:country":"ES",
    "sg:address":"Calle de Infanta Mercedes, 68",
    "sg:city":"Madrid",
    "sg:orig_category":"Inmobiliaria (agencias)",
    "sg:phone":"+34 915 67 22 50",
    "sg:postcode":"28020",
    "sg:province":"Madrid",
    "wof:name":"Habitat Serinmo S.l.",
    "wof:placetype":"venue"
},
  "geometry": {"coordinates":[-3.6958520412,40.4610176086],"type":"Point"}
}