{
  "type": "Feature",
  "properties": {
    "iso:country":"ES",
    "sg:address":"Avda. Madrid, 2",
    "sg:city":"Castellar",
    "sg:orig_category":"Cooperativas Agr\u00cdcolas",
    "sg:phone":"+34 953 46 01 13",
    "sg:postcode":"23260",
    "sg:province":"Ja\u00e9n",
    "wof:name":"Cooperativa Y Caja Rural San Benito",
    "wof:placetype":"venue"
},
  "geometry": {"coordinates":[-3.1249730587,38.2558021545],"type":"Point"}
}