{
  "type": "Feature",
  "properties": {
    "addr:full":"Calle de Badalona, 94 Madrid Madrid 28034",
    "addr:housenumber":"94",
    "addr:postcode":"madrid;28034",
    "addr:street":"Calle De Badalona",
    "iso:country":"ES",
    "sg:address":"Calle de Badalona, 94",
    "sg:city":"Madrid",
    "sg:orig_category":"Fisioterapia",
    "sg:phone":"+34 917 34 68 32",
    "sg:postcode":"28034",
    "sg:province":"Madrid",
    "wof:name":"Herrero Alvarez Carlos",
    "wof:placetype":"venue"
},
  "geometry": {"coordinates":[-3.694270134,40.4940757751],"type":"Point"}
}