{
  "type": "Feature",
  "properties": {
    "addr:full":"Plg. Industrial Xii, S/n Manzanares Ciudad Real 13200",
    "addr:housenumber":"s / n",
    "addr:postcode":"13200",
    "iso:country":"ES",
    "sg:address":"Plg. Industrial Xii, S/n",
    "sg:city":"Manzanares",
    "sg:orig_category":"Transportes Por Carretera: Lotes Completos, Mercanc\u00cdas Diversas",
    "sg:phone":"+34 926 62 01 90",
    "sg:postcode":"13200",
    "sg:province":"Ciudad Real",
    "wof:name":"Comercial Sebastian Gallego S.l.",
    "wof:placetype":"venue"
},
  "geometry": {"coordinates":[-3.3553938866,39.0116348267],"type":"Point"}
}