{
  "type": "Feature",
  "properties": {
    "addr:full":"Carrer de Cervantes, S/n Rubi Barcelona 08191",
    "addr:housenumber":"s",
    "addr:postcode":"08191",
    "addr:street":"Carrer De Cervantes;/ N",
    "iso:country":"ES",
    "sg:address":"Carrer de Cervantes, S/n",
    "sg:city":"Rubi",
    "sg:orig_category":"Internados & Ense\u00d1anza Privada",
    "sg:phone":"+34 936 99 12 18",
    "sg:postcode":"08191",
    "sg:province":"Barcelona",
    "wof:name":"Escuelas Del Patronato Ribas",
    "wof:placetype":"venue"
},
  "geometry": {"coordinates":[2.0399301052,41.4860153198],"type":"Point"}
}