{
  "type": "Feature",
  "properties": {
    "iso:country":"ES",
    "sg:address":"Carr Cendrassos, 6",
    "sg:city":"Figueres",
    "sg:orig_category":"Empresarios",
    "sg:phone":"+34 972 50 60 39",
    "sg:postcode":"17600",
    "sg:province":"Girona",
    "wof:name":"Lopez Vilches Francisco",
    "wof:placetype":"venue"
},
  "geometry": {"coordinates":[2.9649460316,42.2713928223],"type":"Point"}
}