{
  "type": "Feature",
  "properties": {
    "iso:country":"ES",
    "sg:address":"Calle de Manuel Uribe, 13",
    "sg:city":"Madrid",
    "sg:orig_category":"Centros Empresariales",
    "sg:phone":"+34 913 00 32 21",
    "sg:postcode":"28033",
    "sg:province":"Madrid",
    "wof:name":"Optimum Business",
    "wof:placetype":"venue"
},
  "geometry": {"coordinates":[-3.6610090733,40.4642295837],"type":"Point"}
}