{
  "type": "Feature",
  "properties": {
    "iso:country":"ES",
    "sg:address":"Avda Portugal, 29",
    "sg:city":"Monesterio",
    "sg:orig_category":"Asociaciones De Vecinos, Centros De Juventud",
    "sg:phone":"+34 924 51 71 93",
    "sg:postcode":"06260",
    "sg:province":"Badajoz",
    "sg:website":"www.tentudia.com",
    "wof:name":"Centro Desarrollo Comarcal De Tentudia",
    "wof:placetype":"venue"
},
  "geometry": {"coordinates":[-6.2769708633,38.0871429443],"type":"Point"}
}