{
  "type": "Feature",
  "properties": {
    "addr:full":"Calle de Rosa De Los Vientos, 66 Malaga M\u00e1laga 29006",
    "addr:housenumber":"66",
    "addr:postcode":"29006",
    "addr:street":"Calle De Rosa De Los Vientos;Ma\u0301Laga",
    "iso:country":"ES",
    "sg:address":"Calle de Rosa De Los Vientos, 66",
    "sg:city":"Malaga",
    "sg:orig_category":"Empresas De Limpieza",
    "sg:phone":"+34 952 33 28 95",
    "sg:postcode":"29006",
    "sg:province":"M\u00e1laga",
    "wof:name":"Limpieza Y Mantenimiento C. Costa S.l.",
    "wof:placetype":"venue"
},
  "geometry": {"coordinates":[-4.4869890213,36.7118415833],"type":"Point"}
}