{
  "type": "Feature",
  "properties": {
    "iso:country":"ES",
    "sg:address":"Carrer de Maresme, 149",
    "sg:city":"Barcelona",
    "sg:orig_category":"Reposter\u00cdas",
    "sg:phone":"+34 933 07 91 36",
    "sg:postcode":"08019",
    "sg:province":"Barcelona",
    "wof:name":"Forn I Pastisseries Vila S.l.",
    "wof:placetype":"venue"
},
  "geometry": {"coordinates":[2.2093019485,41.417049408],"type":"Point"}
}