{
  "type": "Feature",
  "properties": {
    "addr:full":"Avda Castelao, 3 Pontes Garcia Rodriguez La Coru\u00f1a 15320",
    "addr:housenumber":"3",
    "addr:postcode":"15320",
    "addr:street":"Avda Castelao;Corun\u0303A",
    "iso:country":"ES",
    "sg:address":"Avda Castelao, 3",
    "sg:city":"Pontes Garcia Rodriguez",
    "sg:orig_category":"Contenedores (mercanc\u00cdas)",
    "sg:phone":"+34 981 45 11 94",
    "sg:postcode":"15320",
    "sg:province":"La Coru\u00f1a",
    "wof:name":"Logistica Pontesa S. L.",
    "wof:placetype":"venue"
},
  "geometry": {"coordinates":[-7.8526339531,43.4499092102],"type":"Point"}
}