{
  "type": "Feature",
  "properties": {
    "iso:country":"ES",
    "sg:address":"Carrer de Salles, 16",
    "sg:city":"S. Cugat Valles",
    "sg:orig_category":"Asociaciones Y Clubs Deportivos",
    "sg:phone":"+34 935 83 05 39",
    "sg:postcode":"08172",
    "sg:province":"Barcelona",
    "wof:name":"Pericos De Sant Cugat",
    "wof:placetype":"venue"
},
  "geometry": {"coordinates":[2.0826311111,41.4740562439],"type":"Point"}
}