{
  "type": "Feature",
  "properties": {
    "addr:full":"Carrer de Pau Casals, 1 Puig-reig Barcelona 08692",
    "addr:housenumber":"1",
    "addr:postcode":"08692",
    "addr:street":"Carrer De Pau Casals",
    "iso:country":"ES",
    "sg:address":"Carrer de Pau Casals, 1",
    "sg:city":"Puig-reig",
    "sg:classifiers":[
        {
            "category":"Communications",
            "type":"Services"
        }
    ],
    "sg:phone":"+34 938 38 08 50",
    "sg:postcode":"08692",
    "sg:province":"Barcelona",
    "sg:tags":[
        "televisiones",
        "y",
        "radio"
    ],
    "wof:name":"Radio Puig-reig",
    "wof:placetype":"venue"
},
  "geometry": {"coordinates":[1.8793050051,41.9739151001],"type":"Point"}
}