{
  "type": "Feature",
  "properties": {
    "iso:country":"ES",
    "sg:address":"Carrer de Cultura, 33",
    "sg:city":"Santa Coloma De Gramenet",
    "sg:orig_category":"M\u00c9dicos: Medicina General Orientada A La Acupuntura",
    "sg:phone":"+34 933 85 34 34",
    "sg:postcode":"08922",
    "sg:province":"Barcelona",
    "wof:name":"Bermejo Gomez Jorge",
    "wof:placetype":"venue"
},
  "geometry": {"coordinates":[2.2086930275,41.4473571777],"type":"Point"}
}