{
  "type": "Feature",
  "properties": {
    "addr:full":"Trva San Mateo, 12 Madrid Madrid 28004",
    "addr:housenumber":"12",
    "addr:postcode":"madrid;28004",
    "addr:street":"Trva San Mateo",
    "iso:country":"ES",
    "sg:address":"Trva San Mateo, 12",
    "sg:city":"Madrid",
    "sg:orig_category":"Bisuter\u00cda, Joyer\u00cda, Relojer\u00cda (al Por Menor)",
    "sg:phone":"+34 913 08 56 11",
    "sg:postcode":"28004",
    "sg:province":"Madrid",
    "wof:name":"Salazar Caballero Francisco",
    "wof:placetype":"venue"
},
  "geometry": {"coordinates":[-3.6981871128,40.425163269],"type":"Point"}
}