{
  "type": "Feature",
  "properties": {
    "addr:full":"Carrer de Sallares I Pla, 140 Sabadell Barcelona 08202",
    "addr:housenumber":"140",
    "addr:postcode":"08202",
    "addr:street":"Carrer De Sallares I Pla",
    "iso:country":"ES",
    "sg:address":"Carrer de Sallares I Pla, 140",
    "sg:city":"Sabadell",
    "sg:orig_category":"Agencias Y Agentes Comerciales, Representantes",
    "sg:phone":"+34 937 27 03 31",
    "sg:postcode":"08202",
    "sg:province":"Barcelona",
    "wof:name":"Mateos Roig Jaime",
    "wof:placetype":"venue"
},
  "geometry": {"coordinates":[2.114000082,41.5424766541],"type":"Point"}
}