{
  "type": "Feature",
  "properties": {
    "iso:country":"ES",
    "sg:address":"Avda Bilbao, 109",
    "sg:city":"Sierrapando",
    "sg:orig_category":"Mec\u00c1nico Del Autom\u00d3vil",
    "sg:phone":"+34 942 88 16 30",
    "sg:postcode":"39317",
    "sg:province":"Cantabria",
    "wof:name":"Ramon Gonzalez Y Hermanos S. L.",
    "wof:placetype":"venue"
},
  "geometry": {"coordinates":[-4.0317258835,43.3432312012],"type":"Point"}
}