{
  "type": "Feature",
  "properties": {
    "addr:full":"Carrer de Mollet, S/n Granollers Barcelona 08401",
    "addr:housenumber":"s / n",
    "addr:postcode":"08401",
    "addr:street":"Carrer De Mollet",
    "iso:country":"ES",
    "sg:address":"Carrer de Mollet, S/n",
    "sg:city":"Granollers",
    "sg:orig_category":"Artes Gr\u00c1ficas, Artes Pl\u00c1sticas: Material Y Suministros (al Por Menor)",
    "sg:phone":"+34 938 70 33 67",
    "sg:postcode":"08401",
    "sg:province":"Barcelona",
    "wof:name":"A.m.s.-nexe Professional S.l.",
    "wof:placetype":"venue"
},
  "geometry": {"coordinates":[2.2809472084,41.5935516357],"type":"Point"}
}