{
  "type": "Feature",
  "properties": {
    "iso:country":"ES",
    "sg:address":"Calle de Sanchez Pacheco, 62",
    "sg:city":"Madrid",
    "sg:orig_category":"Cristaler\u00cdas",
    "sg:phone":"+34 914 13 78 98",
    "sg:postcode":"28002",
    "sg:province":"Madrid",
    "wof:name":"Camargo C.b.",
    "wof:placetype":"venue"
},
  "geometry": {"coordinates":[-3.6727209091,40.4473648071],"type":"Point"}
}