{
  "type": "Feature",
  "properties": {
    "iso:country":"ES",
    "sg:address":"Calle de Antonio Lopez, 6",
    "sg:city":"Santander",
    "sg:orig_category":"Ense\u00d1anza, Formaci\u00d3n Profesional: Aprendizaje",
    "sg:phone":"+34 942 20 06 91",
    "sg:postcode":"39...",
    "sg:province":"Cantabria",
    "sg:website":"www.ayto-santander.es",
    "wof:name":"Ayuntamiento De Santander",
    "wof:placetype":"venue"
},
  "geometry": {"coordinates":[-3.8093364239,43.4578323364],"type":"Point"}
}