{
  "type": "Feature",
  "properties": {
    "iso:country":"ES",
    "sg:address":"Calle de Chaparral, 4",
    "sg:city":"Malaga",
    "sg:orig_category":"Empresas De Carpinter\u00cda De Madera",
    "sg:phone":"+34 952 17 91 61",
    "sg:postcode":"29196",
    "sg:province":"M\u00e1laga",
    "wof:name":"Ruiz Carneros Francisco",
    "wof:placetype":"venue"
},
  "geometry": {"coordinates":[-4.5052938461,36.7056465149],"type":"Point"}
}