{
  "type": "Feature",
  "properties": {
    "addr:full":"Pl Catalunya, 7 Gava Barcelona 08850",
    "addr:housenumber":"7",
    "addr:postcode":"08850",
    "addr:street":"Pl Catalunya",
    "iso:country":"ES",
    "sg:address":"Pl Catalunya, 7",
    "sg:city":"Gava",
    "sg:orig_category":"Ropa Para Ni\u00d1os (al Por Menor)",
    "sg:phone":"+34 936 38 23 16",
    "sg:postcode":"08850",
    "sg:province":"Barcelona",
    "wof:name":"Hervas Lopez Josefa",
    "wof:placetype":"venue"
},
  "geometry": {"coordinates":[2.0022909641,41.3092689514],"type":"Point"}
}