{
  "type": "Feature",
  "properties": {
    "addr:full":"Ptda Santa Ana, 4 Oliva Valencia 46780",
    "addr:housenumber":"4",
    "addr:postcode":"46780",
    "addr:street":"Ptda Santa Ana",
    "iso:country":"ES",
    "sg:address":"Ptda Santa Ana, 4",
    "sg:city":"Oliva",
    "sg:orig_category":"Asilos De Ancianos. Centros Privados",
    "sg:phone":"+34 962 85 80 81",
    "sg:postcode":"46780",
    "sg:province":"Valencia",
    "wof:name":"Centro De La Tercera Edad Oliva S.l",
    "wof:placetype":"venue"
},
  "geometry": {"coordinates":[-0.1179220006,38.9189491272],"type":"Point"}
}