{
  "type": "Feature",
  "properties": {
    "iso:country":"ES",
    "sg:address":"Calle de Rebeca, S/n",
    "sg:city":"Malaga",
    "sg:orig_category":"Pescader\u00cdas (al Por Menor)",
    "sg:phone":"+34 952 33 46 95",
    "sg:postcode":"29006",
    "sg:province":"M\u00e1laga",
    "wof:name":"Alamilla Gonzalez Maria Teresa",
    "wof:placetype":"venue"
},
  "geometry": {"coordinates":[-4.4460597038,36.7109642029],"type":"Point"}
}