{
  "type": "Feature",
  "properties": {
    "addr:full":"Calle de Callao, 3 Sevilla Sevilla 41010",
    "addr:housenumber":"3",
    "addr:postcode":"41010",
    "addr:street":"Calle De Callao",
    "iso:country":"ES",
    "sg:address":"Calle de Callao, 3",
    "sg:city":"Sevilla",
    "sg:orig_category":"Telas Y Sedas (al Por Menor)",
    "sg:phone":"+34 954 33 38 92",
    "sg:postcode":"41010",
    "sg:province":"Sevilla",
    "wof:name":"Garces Del Bot Jose Antonio",
    "wof:placetype":"venue"
},
  "geometry": {"coordinates":[-6.0042452812,37.3860321045],"type":"Point"}
}