{
  "type": "Feature",
  "properties": {
    "iso:country":"ES",
    "sg:address":"Avda Tordesillas, Km. 0172,0",
    "sg:city":"Rueda",
    "sg:orig_category":"Vinos Y Licores (venta Al Por Menor)",
    "sg:phone":"+34 983 86 89 16",
    "sg:postcode":"47490",
    "sg:province":"Valladolid",
    "wof:name":"Productos Maxi S.c.",
    "wof:placetype":"venue"
},
  "geometry": {"coordinates":[-4.9597439766,41.4110107422],"type":"Point"}
}