{
  "type": "Feature",
  "properties": {
    "iso:country":"ES",
    "sg:address":"Calle de Sagasta, 1",
    "sg:city":"Madrid",
    "sg:orig_category":"M\u00c9dicos: Estomatolog\u00cda",
    "sg:phone":"+34 915 93 45 88",
    "sg:postcode":"28004",
    "sg:province":"Madrid",
    "wof:name":"Flores Legasa Luis",
    "wof:placetype":"venue"
},
  "geometry": {"coordinates":[-3.7014350891,40.4288330078],"type":"Point"}
}