{
  "type": "Feature",
  "properties": {
    "addr:full":"Calle de Dos Plazas, 12 S. Juan Puerto Huelva 21610",
    "addr:housenumber":"12",
    "addr:postcode":"21610",
    "addr:street":"Calle De Dos Plazas;S. Juan Puerto",
    "iso:country":"ES",
    "sg:address":"Calle de Dos Plazas, 12",
    "sg:city":"S. Juan Puerto",
    "sg:orig_category":"Cajas Para Embalar",
    "sg:phone":"+34 959 35 63 30",
    "sg:postcode":"21610",
    "sg:province":"Huelva",
    "sg:website":"www.cajadelsur.es",
    "wof:name":"Caja Rural Del Sur Sociedad Cooperativa",
    "wof:placetype":"venue"
},
  "geometry": {"coordinates":[-6.8410100937,37.3144645691],"type":"Point"}
}