{
  "type": "Feature",
  "properties": {
    "iso:country":"ES",
    "sg:address":"Carrer de Josep Fiter, 6",
    "sg:city":"Cornella Llobregat",
    "sg:orig_category":"Carnicer\u00cdas, Carnicer\u00cdas",
    "sg:phone":"+34 933 76 47 60",
    "sg:postcode":"08940",
    "sg:province":"Barcelona",
    "wof:name":"Cruz Salamanca Manuel",
    "wof:placetype":"venue"
},
  "geometry": {"coordinates":[2.0730559826,41.3628845215],"type":"Point"}
}