{
  "type": "Feature",
  "properties": {
    "addr:full":"Rua Suarez Vence (de), 1 Santa Comba La Coru\u00f1a 15840",
    "addr:postcode":"15840",
    "addr:street":"Rua Suarez;Corun\u0303A",
    "iso:country":"ES",
    "sg:address":"Rua Suarez Vence (de), 1",
    "sg:city":"Santa Comba",
    "sg:orig_category":"Carnicer\u00cdas, Carnicer\u00cdas",
    "sg:phone":"+34 981 88 00 80",
    "sg:postcode":"15840",
    "sg:province":"La Coru\u00f1a",
    "wof:name":"Gomez Gomez Jose",
    "wof:placetype":"venue"
},
  "geometry": {"coordinates":[-8.8163843155,43.0361595154],"type":"Point"}
}