{
  "type": "Feature",
  "properties": {
    "iso:country":"ES",
    "sg:address":"Cust Carmen, 1",
    "sg:city":"Salamanca",
    "sg:orig_category":"Bisuter\u00cda, Joyer\u00cda, Relojer\u00cda (al Por Menor)",
    "sg:phone":"+34 923 21 84 60",
    "sg:postcode":"37002",
    "sg:province":"Salamanca",
    "wof:name":"Garcia Velazquez Santiago",
    "wof:placetype":"venue"
},
  "geometry": {"coordinates":[-5.6652321815,40.9662780762],"type":"Point"}
}