{
  "type": "Feature",
  "properties": {
    "addr:full":"Pl 25 D'abril, 3 Pu\u00e7ol Valencia 46530",
    "addr:housenumber":"25;3",
    "addr:postcode":"46530",
    "addr:street":"Pl;D'Abril",
    "iso:country":"ES",
    "sg:address":"Pl 25 D'abril, 3",
    "sg:city":"Pu\u00e7ol",
    "sg:orig_category":"Cajas Para Embalar",
    "sg:phone":"+34 961 42 02 78",
    "sg:postcode":"46530",
    "sg:province":"Valencia",
    "sg:website":"www.ruralcaja.es",
    "wof:name":"Caja Rural Del Mediterraneo Ruralcaja S Coop De Credito",
    "wof:placetype":"venue"
},
  "geometry": {"coordinates":[-0.7019069791,38.2624092102],"type":"Point"}
}