{
  "type": "Feature",
  "properties": {
    "addr:full":"Carrer de Ram Berenguer Iii, 1 Palma Islas Baleares 07003",
    "addr:housenumber":"1",
    "addr:postcode":"07003",
    "addr:street":"Carrer De Ram Berenguer Iii",
    "iso:country":"ES",
    "sg:address":"Carrer de Ram Berenguer Iii, 1",
    "sg:city":"Palma",
    "sg:orig_category":"M\u00c9dicos: Estomatolog\u00cda",
    "sg:phone":"+34 971 29 89 58",
    "sg:postcode":"07003",
    "sg:province":"Islas Baleares",
    "wof:name":"Font Jaume Juan Miguel",
    "wof:placetype":"venue"
},
  "geometry": {"coordinates":[2.6521420479,39.5790786743],"type":"Point"}
}