{
  "type": "Feature",
  "properties": {
    "iso:country":"ES",
    "sg:address":"Rbla Llibertat, 17",
    "sg:city":"Girona",
    "sg:orig_category":"Relojer\u00cda (al Por Menor, Reparaci\u00d3n)",
    "sg:phone":"+34 972 41 42 33",
    "sg:postcode":"17004",
    "sg:province":"Girona",
    "sg:website":"www.swatch.com",
    "wof:name":"Clockwise S.l.",
    "wof:placetype":"venue"
},
  "geometry": {"coordinates":[2.8239719868,41.9839668274],"type":"Point"}
}