{
  "type": "Feature",
  "properties": {
    "iso:country":"ES",
    "sg:address":"Calle de Isabel La Catolica, 13",
    "sg:city":"Valencia",
    "sg:orig_category":"Iglesia Cat\u00d3lica",
    "sg:phone":"+34 963 51 25 95",
    "sg:postcode":"46004",
    "sg:province":"Valencia",
    "wof:name":"Parroquia De San Juan Y San Vicente",
    "wof:placetype":"venue"
},
  "geometry": {"coordinates":[-0.3703669906,39.4689254761],"type":"Point"}
}