{
  "type": "Feature",
  "properties": {
    "addr:full":"Barr Serna (la), S/n San Miguel De Meruelo Cantabria 39192",
    "addr:housenumber":"/ n",
    "addr:postcode":"39192",
    "addr:street":"La S",
    "iso:country":"ES",
    "sg:address":"Barr Serna (la), S/n",
    "sg:city":"San Miguel De Meruelo",
    "sg:orig_category":"Ense\u00d1anza, Formaci\u00d3n Profesional: Aprendizaje",
    "sg:phone":"+34 942 67 49 50",
    "sg:postcode":"39192",
    "sg:province":"Cantabria",
    "wof:name":"Dominguez Escallada Alfonso",
    "wof:placetype":"venue"
},
  "geometry": {"coordinates":[-3.5779850483,43.4566192627],"type":"Point"}
}