{
  "type": "Feature",
  "properties": {
    "iso:country":"ES",
    "sg:address":"Carrer de Diputacio, 274",
    "sg:city":"Barcelona",
    "sg:orig_category":"Abogados",
    "sg:phone":"+34 933 18 86 80",
    "sg:postcode":"08009",
    "sg:province":"Barcelona",
    "wof:name":"Sagrera Ribas Marc",
    "wof:placetype":"venue"
},
  "geometry": {"coordinates":[2.1690540314,41.3917274475],"type":"Point"}
}