{
  "type": "Feature",
  "properties": {
    "addr:full":"Carrer de Joaquim Monmany, 13 Sant Feliu Llobregat Barcelona 08980",
    "addr:housenumber":"13",
    "addr:postcode":"08980",
    "addr:street":"Carrer De Joaquim Monmany",
    "iso:country":"ES",
    "sg:address":"Carrer de Joaquim Monmany, 13",
    "sg:city":"Sant Feliu Llobregat",
    "sg:orig_category":"Deportes Diversos",
    "sg:phone":"+34 936 66 87 61",
    "sg:postcode":"08980",
    "sg:province":"Barcelona",
    "wof:name":"Federacion Catalana De Futbol",
    "wof:placetype":"venue"
},
  "geometry": {"coordinates":[2.0484559536,41.3869285583],"type":"Point"}
}