{
  "type": "Feature",
  "properties": {
    "addr:full":"Calle de Real, 18 Ceuta Ceuta 51001",
    "addr:housenumber":"18",
    "addr:postcode":"51001",
    "addr:street":"Calle De Real",
    "iso:country":"ES",
    "sg:address":"Calle de Real, 18",
    "sg:city":"Ceuta",
    "sg:orig_category":"Fabricaci\u00d3n De Telas Y Sedas",
    "sg:phone":"+34 956 51 48 44",
    "sg:postcode":"51001",
    "sg:province":"Ceuta",
    "wof:name":"Contex S. A.",
    "wof:placetype":"venue"
},
  "geometry": {"coordinates":[-5.3071269989,35.8873825073],"type":"Point"}
}