{
  "type": "Feature",
  "properties": {
    "addr:full":"Calle de Ezurriki Kalea, 4 Irun Guip\u00f9zcoa 20305",
    "addr:housenumber":"4",
    "addr:postcode":"20305",
    "addr:street":"Calle De Ezurriki Kalea;Guipu\u0300Zcoa",
    "iso:country":"ES",
    "sg:address":"Calle de Ezurriki Kalea, 4",
    "sg:city":"Irun",
    "sg:orig_category":"Materias Pl\u00c1sticas: Productos De Consumo Masivo (fabricaci\u00d3n, Al Por Mayor)",
    "sg:phone":"+34 943 63 34 00",
    "sg:postcode":"20305",
    "sg:province":"Guip\u00f9zcoa",
    "wof:name":"Poliester Gabiria S.a.l.",
    "wof:placetype":"venue"
},
  "geometry": {"coordinates":[-1.7637690306,43.3425445557],"type":"Point"}
}