{
  "type": "Feature",
  "properties": {
    "iso:country":"ES",
    "sg:address":"Avda Orense, 39",
    "sg:city":"Marin",
    "sg:orig_category":"Pescader\u00cdas (al Por Menor)",
    "sg:phone":"+34 986 89 11 91",
    "sg:postcode":"36900",
    "sg:province":"Pontevedra",
    "wof:name":"Pescados Miguel Navarro S.l.",
    "wof:placetype":"venue"
},
  "geometry": {"coordinates":[-8.6960296631,42.3932189941],"type":"Point"}
}