{
  "type": "Feature",
  "properties": {
    "addr:full":"Ctra Yegua Verde, 2 Congo-canal Almer\u00eda 04738",
    "addr:housenumber":"2",
    "addr:postcode":"04738",
    "addr:street":"Ctra Yegua Verde;Almeri\u0301A",
    "iso:country":"ES",
    "sg:address":"Ctra Yegua Verde, 2",
    "sg:city":"Congo-canal",
    "sg:orig_category":"Productos Fitosanitarios (negocio, Aplicaci\u00d3n)",
    "sg:phone":"+34 950 53 95 76",
    "sg:postcode":"04738",
    "sg:province":"Almer\u00eda",
    "wof:name":"Crisel Agroquimicos S.l",
    "wof:placetype":"venue"
},
  "geometry": {"coordinates":[-2.635559082,36.7998008728],"type":"Point"}
}