{
  "type": "Feature",
  "properties": {
    "addr:full":"Calle de Rodriguez De Cepeda, 42 Valencia Valencia 46021",
    "addr:housenumber":"42",
    "addr:postcode":"46021",
    "addr:street":"Calle De Rodriguez De Cepeda",
    "iso:country":"ES",
    "sg:address":"Calle de Rodriguez De Cepeda, 42",
    "sg:city":"Valencia",
    "sg:orig_category":"Arquitectos",
    "sg:phone":"+34 963 61 49 41",
    "sg:postcode":"46021",
    "sg:province":"Valencia",
    "wof:name":"Soria Giner Juan Luis",
    "wof:placetype":"venue"
},
  "geometry": {"coordinates":[-0.3516449928,39.4681816101],"type":"Point"}
}