{
  "type": "Feature",
  "properties": {
    "iso:country":"ES",
    "sg:address":"Carr Ciencia, 8",
    "sg:city":"Badalona",
    "sg:orig_category":"Caf\u00c9s, Bares, Cervecer\u00cdas",
    "sg:phone":"+34 934 65 28 52",
    "sg:postcode":"08917",
    "sg:province":"Barcelona",
    "wof:name":"Bar Restaurante El Capricho",
    "wof:placetype":"venue"
},
  "geometry": {"coordinates":[2.2354469299,41.4590187073],"type":"Point"}
}