{
  "type": "Feature",
  "properties": {
    "addr:full":"Carr Sant Pere, 8 Badalona Barcelona 08911",
    "addr:housenumber":"8",
    "addr:postcode":"08911",
    "addr:street":"Carr Sant Pere",
    "iso:country":"ES",
    "sg:address":"Carr Sant Pere, 8",
    "sg:city":"Badalona",
    "sg:orig_category":"Ropa Para Se\u00d1oras (al Por Menor)",
    "sg:phone":"+34 933 89 01 18",
    "sg:postcode":"08911",
    "sg:province":"Barcelona",
    "sg:website":"www.massimodutti.com",
    "wof:name":"Grupo Massimo Dutti S.a.",
    "wof:placetype":"venue"
},
  "geometry": {"coordinates":[2.2497711182,41.4482536316],"type":"Point"}
}