{
  "type": "Feature",
  "properties": {
    "addr:full":"Avda Manuel De Falla, S/n Olvera C\u00e1diz 11690",
    "addr:housenumber":"s / n",
    "addr:postcode":"11690",
    "addr:street":"Avda Manuel De Falla;Ca\u0301Diz",
    "iso:country":"ES",
    "sg:address":"Avda Manuel De Falla, S/n",
    "sg:city":"Olvera",
    "sg:orig_category":"Cooperativas Agr\u00cdcolas",
    "sg:phone":"+34 956 12 00 81",
    "sg:postcode":"11690",
    "sg:province":"C\u00e1diz",
    "wof:name":"Mi Super Albeyco S.a.",
    "wof:placetype":"venue"
},
  "geometry": {"coordinates":[-5.259414196,36.9338417053],"type":"Point"}
}