{
  "type": "Feature",
  "properties": {
    "addr:full":"Carr Juli Garreta, 16 Sils Girona 17410",
    "addr:housenumber":"16",
    "addr:postcode":"17410",
    "addr:street":"Carr Juli Garreta",
    "iso:country":"ES",
    "sg:address":"Carr Juli Garreta, 16",
    "sg:city":"Sils",
    "sg:orig_category":"Comerciantes Al Por Mayor De Vinos, Licores Y Alcoholes",
    "sg:phone":"+34 972 85 36 06",
    "sg:postcode":"17410",
    "sg:province":"Girona",
    "wof:name":"Guso Lloret Miquel",
    "wof:placetype":"venue"
},
  "geometry": {"coordinates":[2.7439854145,41.8102340698],"type":"Point"}
}