{
  "type": "Feature",
  "properties": {
    "addr:full":"Pg Estacio De L', 33 Valls Tarragona 43800",
    "addr:housenumber":"33",
    "addr:postcode":"43800",
    "addr:street":"Pg Estacio De L '",
    "iso:country":"ES",
    "sg:address":"Pg Estacio De L', 33",
    "sg:city":"Valls",
    "sg:orig_category":"Arquitectos",
    "sg:phone":"+34 977 60 17 34",
    "sg:postcode":"43800",
    "sg:province":"Tarragona",
    "wof:name":"Vilanova Puigbo Jose",
    "wof:placetype":"venue"
},
  "geometry": {"coordinates":[1.2525299788,41.2871513367],"type":"Point"}
}