{
  "type": "Feature",
  "properties": {
    "iso:country":"ES",
    "sg:address":"Calle de Roble, 12",
    "sg:city":"Moraleja Enmedio",
    "sg:orig_category":"Papel (al Por Mayor)",
    "sg:phone":"+34 916 09 42 14",
    "sg:postcode":"28950",
    "sg:province":"Madrid",
    "wof:name":"Akaba Manipulados S.l.",
    "wof:placetype":"venue"
},
  "geometry": {"coordinates":[-3.8498311043,40.2604980469],"type":"Point"}
}