{
  "type": "Feature",
  "properties": {
    "iso:country":"ES",
    "sg:address":"A Rocha, 90",
    "sg:city":"Rocha",
    "sg:orig_category":"Alimentaci\u00d3n General (al Por Menor)",
    "sg:phone":"+34 986 33 35 17",
    "sg:postcode":"36418",
    "sg:province":"Pontevedra",
    "wof:name":"Pereira Ramilo Manuel",
    "wof:placetype":"venue"
},
  "geometry": {"coordinates":[-8.6153745651,42.1443786621],"type":"Point"}
}