{
  "type": "Feature",
  "properties": {
    "addr:full":"Calle de Antolin Lopez Pelaez, 10 Ponferrada Le\u00f3n 24400",
    "addr:housenumber":"10",
    "addr:postcode":"24400",
    "addr:street":"Calle De Antolin Lopez Pelaez",
    "iso:country":"ES",
    "sg:address":"Calle de Antolin Lopez Pelaez, 10",
    "sg:city":"Ponferrada",
    "sg:orig_category":"M\u00c9dicos: Cirug\u00cda General",
    "sg:phone":"+34 987 42 81 38",
    "sg:postcode":"24400",
    "sg:province":"Le\u00f3n",
    "wof:name":"Quintela Ozores Adolfo",
    "wof:placetype":"venue"
},
  "geometry": {"coordinates":[-6.5993614197,42.5473403931],"type":"Point"}
}