{
  "type": "Feature",
  "properties": {
    "iso:country":"ES",
    "sg:address":"Avda Elvas, 6",
    "sg:city":"Badajoz",
    "sg:orig_category":"Bisuter\u00cda, Joyer\u00cda, Relojer\u00cda (al Por Menor)",
    "sg:phone":"+34 924 27 22 78",
    "sg:postcode":"06006",
    "sg:province":"Badajoz",
    "wof:name":"Jose M\u00aa Garcia E Hijos S.l.",
    "wof:placetype":"venue"
},
  "geometry": {"coordinates":[-7.0020041466,38.8824882507],"type":"Point"}
}