{
  "type": "Feature",
  "properties": {
    "iso:country":"ES",
    "sg:address":"Calle de Entrehuertas, 17",
    "sg:city":"Baiona",
    "sg:orig_category":"Peluquer\u00cdas, Peluquer\u00cda Mixta",
    "sg:phone":"+34 986 35 54 44",
    "sg:postcode":"36300",
    "sg:province":"Pontevedra",
    "wof:name":"Chamorro Rial Maria Dolores",
    "wof:placetype":"venue"
},
  "geometry": {"coordinates":[-97.78224945069999,45.7040786743],"type":"Point"}
}