{
  "type": "Feature",
  "properties": {
    "addr:full":"Carrer de Mare De Deu Dels Angels, 6 Santa Coloma De Gramenet Barcelona 08921",
    "addr:housenumber":"6",
    "addr:postcode":"08921",
    "addr:street":"Carrer De Mare De Deu",
    "iso:country":"ES",
    "sg:address":"Carrer de Mare De Deu Dels Angels, 6",
    "sg:city":"Santa Coloma De Gramenet",
    "sg:orig_category":"Fabricaci\u00d3n De Ropa De Deportes",
    "sg:phone":"+34 934 66 53 83",
    "sg:postcode":"08921",
    "sg:province":"Barcelona",
    "wof:name":"Robles Moya Juan",
    "wof:placetype":"venue"
},
  "geometry": {"coordinates":[2.2039079666,41.4527359009],"type":"Point"}
}