{
  "type": "Feature",
  "properties": {
    "iso:country":"ES",
    "sg:address":"Cmno Juncal (del), S/n",
    "sg:city":"San Sebastian De Los Reyes",
    "sg:orig_category":"Ropa Para Ni\u00d1os (al Por Menor)",
    "sg:phone":"+34 916 51 60 24",
    "sg:postcode":"28700",
    "sg:province":"Madrid",
    "wof:name":"Chicco Espa\u00d1a S.a.",
    "wof:placetype":"venue"
},
  "geometry": {"coordinates":[-3.6253190041,40.5473556519],"type":"Point"}
}