{
  "type": "Feature",
  "properties": {
    "iso:country":"ES",
    "sg:address":"Ctra Nacional Iv, 172",
    "sg:city":"Manzanares",
    "sg:orig_category":"Mec\u00c1nico Del Autom\u00d3vil",
    "sg:phone":"+34 926 61 03 78",
    "sg:postcode":"13200",
    "sg:province":"Ciudad Real",
    "wof:name":"Talleres Y Gruas Arroyo S.l.",
    "wof:placetype":"venue"
},
  "geometry": {"coordinates":[-3.373128891,38.994140625],"type":"Point"}
}