{
  "type": "Feature",
  "properties": {
    "addr:full":"Calle de Oliva (la), S/n Carcastillo Navarra 31310",
    "addr:postcode":"31310",
    "addr:street":"Calle De Oliva La S / N",
    "iso:country":"ES",
    "sg:address":"Calle de Oliva (la), S/n",
    "sg:city":"Carcastillo",
    "sg:orig_category":"Comunidades Religiosas",
    "sg:phone":"+34 948 72 52 88",
    "sg:postcode":"31310",
    "sg:province":"Navarra",
    "wof:name":"Conferencia Regional Espa\u00f1ola Cisterciense",
    "wof:placetype":"venue"
},
  "geometry": {"coordinates":[-1.4453669786,42.3794937134],"type":"Point"}
}