{
  "type": "Feature",
  "properties": {
    "addr:full":"Carrer de Zamora, 40 Rubi Barcelona 08191",
    "addr:housenumber":"40",
    "addr:postcode":"08191",
    "addr:street":"Carrer De Zamora",
    "iso:country":"ES",
    "sg:address":"Carrer de Zamora, 40",
    "sg:city":"Rubi",
    "sg:classifiers":[
        {
            "category":"Arts & Performance",
            "subcategory":"Art Gallery",
            "type":"Entertainment"
        }
    ],
    "sg:phone":"+34 936 99 05 47",
    "sg:postcode":"08191",
    "sg:province":"Barcelona",
    "sg:tags":[
        "arte",
        "de",
        "galer\u00cdas"
    ],
    "wof:name":"Arte Europeo 2000 S.l.",
    "wof:placetype":"venue"
},
  "geometry": {"coordinates":[2.0460963249,41.5016517639],"type":"Point"}
}