{
  "type": "Feature",
  "properties": {
    "addr:full":"Calle de Luis Salazar, 7 Campanillas M\u00e1laga 29590",
    "addr:housenumber":"7",
    "addr:postcode":"29590",
    "addr:street":"Calle De Luis Salazar;Ma\u0301Laga",
    "iso:country":"ES",
    "sg:address":"Calle de Luis Salazar, 7",
    "sg:city":"Campanillas",
    "sg:orig_category":"Carnicer\u00cdas, Carnicer\u00cdas",
    "sg:phone":"+34 952 43 32 78",
    "sg:postcode":"29590",
    "sg:province":"M\u00e1laga",
    "wof:name":"Martin Ramirez Rafael",
    "wof:placetype":"venue"
},
  "geometry": {"coordinates":[-4.5224900246,36.7190055847],"type":"Point"}
}