{
  "type": "Feature",
  "properties": {
    "addr:full":"C/ Fira, 3 Llucmajor Islas Baleares 07620",
    "addr:housenumber":"3",
    "addr:postcode":"07620",
    "addr:street":"C / Fira",
    "iso:country":"ES",
    "sg:address":"C/ Fira, 3",
    "sg:city":"Llucmajor",
    "sg:orig_category":"Electricidad: Instaladores",
    "sg:phone":"+34 971 66 19 01",
    "sg:postcode":"07620",
    "sg:province":"Islas Baleares",
    "wof:name":"Calafat Juan Cristobal",
    "wof:placetype":"venue"
},
  "geometry": {"coordinates":[2.8918659687,39.4909477234],"type":"Point"}
}