{
  "type": "Feature",
  "properties": {
    "iso:country":"ES",
    "sg:address":"Calle de Luis Adaro Magro, 4 000c",
    "sg:city":"S. Martin Rey Aurelio",
    "sg:orig_category":"Cajas De Ahorro",
    "sg:phone":"+34 985 65 48 03",
    "sg:postcode":"33940",
    "sg:province":"Asturias",
    "sg:website":"www.cajastur.es",
    "wof:name":"Caja De Ahorros De Asturias",
    "wof:placetype":"venue"
},
  "geometry": {"coordinates":[-5.6437277794,43.2868232727],"type":"Point"}
}