{
  "type": "Feature",
  "properties": {
    "iso:country":"ES",
    "sg:address":"Calle de Verbon, 7",
    "sg:city":"Malaga",
    "sg:orig_category":"Empresas De Carpinter\u00cda De Madera",
    "sg:phone":"+34 952 27 61 99",
    "sg:postcode":"29011",
    "sg:province":"M\u00e1laga",
    "wof:name":"Madrid Cabo Rafael",
    "wof:placetype":"venue"
},
  "geometry": {"coordinates":[-4.4372138977,36.7336730957],"type":"Point"}
}