{
  "type": "Feature",
  "properties": {
    "iso:country":"ES",
    "sg:address":"Concejo De Olaz, 10",
    "sg:city":"Iru\u00f1a",
    "sg:orig_category":"Carnicer\u00cdas, Carnicer\u00cdas",
    "sg:phone":"+34 948 16 10 78",
    "sg:postcode":"31016",
    "sg:province":"Navarra",
    "wof:name":"Pedroarena Etulain Eusebio",
    "wof:placetype":"venue"
},
  "geometry": {"coordinates":[-1.6123210192,42.8082084656],"type":"Point"}
}