{
  "type": "Feature",
  "properties": {
    "addr:full":"Calle de Mayor, 66 Almaden Ciudad Real 13400",
    "addr:housenumber":"66",
    "addr:postcode":"13400",
    "addr:street":"Calle De Mayor;Real",
    "iso:country":"ES",
    "sg:address":"Calle de Mayor, 66",
    "sg:city":"Almaden",
    "sg:orig_category":"Cajas Para Embalar",
    "sg:phone":"+34 926 71 05 29",
    "sg:postcode":"13400",
    "sg:province":"Ciudad Real",
    "wof:name":"Caja Rural De Ciudad Real",
    "wof:placetype":"venue"
},
  "geometry": {"coordinates":[-4.8338809013,38.7755775452],"type":"Point"}
}