{
  "type": "Feature",
  "properties": {
    "addr:full":"Calle de Esturion, S/n Urbanizacion Roquetas De Mar Almer\u00eda 04740",
    "addr:housenumber":"s / n",
    "addr:postcode":"04740",
    "addr:street":"Calle De Esturion;Roquetas",
    "iso:country":"ES",
    "sg:address":"Calle de Esturion, S/n",
    "sg:city":"Urbanizacion Roquetas De Mar",
    "sg:orig_category":"Arquitectos",
    "sg:phone":"+34 950 33 36 45",
    "sg:postcode":"04740",
    "sg:province":"Almer\u00eda",
    "wof:name":"Llorca Jimenez Pedro Jose",
    "wof:placetype":"venue"
},
  "geometry": {"coordinates":[-2.616549015,36.7374382019],"type":"Point"}
}