{
  "type": "Feature",
  "properties": {
    "iso:country":"ES",
    "sg:address":"Carr Ausias March, 5",
    "sg:city":"Benetusser",
    "sg:orig_category":"Art\u00cdculos De Madera (fabricaci\u00d3n Y Al Por Mayor)",
    "sg:phone":"+34 963 75 35 26",
    "sg:postcode":"46910",
    "sg:province":"Valencia",
    "wof:name":"Ba\u00f1on Lorenzo Fernando",
    "wof:placetype":"venue"
},
  "geometry": {"coordinates":[-0.3970130086,39.4215431213],"type":"Point"}
}