{
  "type": "Feature",
  "properties": {
    "addr:full":"Ctra Santa Fe, S/n Atarfe Granada 18230",
    "addr:housenumber":"s / n",
    "addr:postcode":"18230",
    "addr:street":"Ctra Santa Fe",
    "iso:country":"ES",
    "sg:address":"Ctra Santa Fe, S/n",
    "sg:city":"Atarfe",
    "sg:orig_category":"Empresas De Carpinter\u00cda Met\u00c1lica",
    "sg:phone":"+34 958 43 66 68",
    "sg:postcode":"18230",
    "sg:province":"Granada",
    "wof:name":"Guerrero Lezama Marco Antonio",
    "wof:placetype":"venue"
},
  "geometry": {"coordinates":[-3.6984341145,37.2160606384],"type":"Point"}
}