{
  "type": "Feature",
  "properties": {
    "iso:country":"ES",
    "sg:address":"Kalebarren, 1",
    "sg:city":"Antzuola",
    "sg:orig_category":"Librer\u00cdas",
    "sg:phone":"+34 943 76 60 62",
    "sg:postcode":"20577",
    "sg:province":"Guip\u00f9zcoa",
    "wof:name":"Laskurain Iturbe Maria Concepcion",
    "wof:placetype":"venue"
},
  "geometry": {"coordinates":[-2.3835036755,43.0996437073],"type":"Point"}
}