{
  "type": "Feature",
  "properties": {
    "addr:full":"Ctra. Militar, 28 S'aranjassa Islas Baleares 07199",
    "addr:housenumber":"28",
    "addr:postcode":"07199",
    "addr:street":"Ctra. Militar;Islas",
    "iso:country":"ES",
    "sg:address":"Ctra. Militar, 28",
    "sg:city":"S'aranjassa",
    "sg:orig_category":"Empresas De Carpinter\u00cda De Madera",
    "sg:phone":"+34 971 74 28 24",
    "sg:postcode":"07199",
    "sg:province":"Islas Baleares",
    "wof:name":"Fusteria Can Caseetes S.l.",
    "wof:placetype":"venue"
},
  "geometry": {"coordinates":[2.9117100239,39.6136398315],"type":"Point"}
}