{
  "type": "Feature",
  "properties": {
    "iso:country":"ES",
    "sg:address":"Carrer de Francesc Macia, S/n",
    "sg:city":"Vilafranca Penedes",
    "sg:orig_category":"Molduras, Junquillos, Listones Y Molduras Perforadas",
    "sg:phone":"+34 938 90 46 27",
    "sg:postcode":"08720",
    "sg:province":"Barcelona",
    "wof:name":"Dominguez Dominguez Arturo",
    "wof:placetype":"venue"
},
  "geometry": {"coordinates":[1.6925289631,41.3424186707],"type":"Point"}
}