{
  "type": "Feature",
  "properties": {
    "addr:full":"Carrer de Anselm Clave, 15 Pla Barcelona 08186",
    "addr:housenumber":"15",
    "addr:postcode":"08186",
    "addr:street":"Carrer De Anselm Clave;Barcelona",
    "iso:country":"ES",
    "sg:address":"Carrer de Anselm Clave, 15",
    "sg:city":"Pla",
    "sg:orig_category":"Alimentaci\u00d3n General (al Por Mayor)",
    "sg:phone":"+34 938 41 41 11",
    "sg:postcode":"08186",
    "sg:province":"Barcelona",
    "wof:name":"Bernat Maleno S.l.",
    "wof:placetype":"venue"
},
  "geometry": {"coordinates":[2.2382690907,41.612449646],"type":"Point"}
}