{
  "type": "Feature",
  "properties": {
    "addr:full":"Plaz Mayor, 12 Ahigal C\u00e1ceres 10650",
    "addr:housenumber":"12",
    "addr:postcode":"10650",
    "addr:street":"Plaz Mayor;Ca\u0301Ceres",
    "iso:country":"ES",
    "sg:address":"Plaz Mayor, 12",
    "sg:city":"Ahigal",
    "sg:orig_category":"Abogados",
    "sg:phone":"+34 927 43 91 42",
    "sg:postcode":"10650",
    "sg:province":"C\u00e1ceres",
    "wof:name":"Ayuntamiento",
    "wof:placetype":"venue"
},
  "geometry": {"coordinates":[-6.1845207214,40.1337623596],"type":"Point"}
}