{
  "type": "Feature",
  "properties": {
    "addr:full":"Calle de Santa Lucia, 1 Pozuelo De Alarcon Madrid 28223",
    "addr:housenumber":"1",
    "addr:postcode":"28223",
    "addr:street":"Calle De Santa Lucia",
    "iso:country":"ES",
    "sg:address":"Calle de Santa Lucia, 1",
    "sg:city":"Pozuelo De Alarcon",
    "sg:orig_category":"Peluquer\u00cdas, Peluquer\u00cda Mixta",
    "sg:phone":"+34 913 51 27 84",
    "sg:postcode":"28223",
    "sg:province":"Madrid",
    "wof:name":"Soltero Pinilla Maria Eulalia",
    "wof:placetype":"venue"
},
  "geometry": {"coordinates":[-3.8141527176,40.438659668],"type":"Point"}
}