{
  "type": "Feature",
  "properties": {
    "addr:full":"Avda Manuel Sirgo, S/n Gijon Asturias 33211",
    "addr:housenumber":"s",
    "addr:postcode":"33211",
    "addr:street":"Avda Manuel Sirgo;/ N",
    "iso:country":"ES",
    "sg:address":"Avda Manuel Sirgo, S/n",
    "sg:city":"Gijon",
    "sg:orig_category":"Goma: Productos De Uso Industrial (fabricaci\u00d3n, Al Por Mayor)",
    "sg:phone":"+34 985 32 00 55",
    "sg:postcode":"33211",
    "sg:province":"Asturias",
    "sg:website":"www.solis-sl.com",
    "wof:name":"Solis Industrias Del Caucho S. L.",
    "wof:placetype":"venue"
},
  "geometry": {"coordinates":[-5.7110738754,43.5243301392],"type":"Point"}
}