{
  "type": "Feature",
  "properties": {
    "iso:country":"ES",
    "sg:address":"Pase Habana, 41",
    "sg:city":"Madrid",
    "sg:orig_category":"Promotores Constructores",
    "sg:phone":"+34 915 64 16 63",
    "sg:postcode":"28036",
    "sg:province":"Madrid",
    "wof:name":"Consolidaciones Y Rehabilitaciones S.l.",
    "wof:placetype":"venue"
},
  "geometry": {"coordinates":[-3.6848409176,40.4533195496],"type":"Point"}
}