{
  "type": "Feature",
  "properties": {
    "iso:country":"ES",
    "sg:address":"H, S/n",
    "sg:city":"P. I. El Oliveral",
    "sg:orig_category":"Productos Qu\u00cdmicos (fabricaci\u00d3n, Al Por Mayor)",
    "sg:phone":"+34 961 66 62 00",
    "sg:postcode":"46190",
    "sg:province":"Valencia",
    "sg:website":"www.movaco.es",
    "wof:name":"Movaco S.a.",
    "wof:placetype":"venue"
},
  "geometry": {"coordinates":[-0.5698940158,39.5458450317],"type":"Point"}
}