{
  "type": "Feature",
  "properties": {
    "iso:country":"ES",
    "sg:address":"Ctra Palmar, S/n",
    "sg:city":"Barracas",
    "sg:orig_category":"Agentes, Concesionarios Y Sucursales De Veh\u00cdculos",
    "sg:phone":"+34 968 34 13 00",
    "sg:postcode":"30152",
    "sg:province":"Murcia",
    "sg:website":"www.motorsureste.es",
    "wof:name":"Marcos Motor S. A.",
    "wof:placetype":"venue"
},
  "geometry": {"coordinates":[-1.1390340328,37.9692993164],"type":"Point"}
}