{
  "type": "Feature",
  "properties": {
    "addr:full":"Carr Combat, 29 Cervera Lleida 25200",
    "addr:housenumber":"29",
    "addr:postcode":"25200",
    "addr:street":"Carr Combat",
    "iso:country":"ES",
    "sg:address":"Carr Combat, 29",
    "sg:city":"Cervera",
    "sg:orig_category":"Peluquer\u00cdas, Peluquer\u00cda Mixta",
    "sg:phone":"+34 973 53 31 36",
    "sg:postcode":"25200",
    "sg:province":"Lleida",
    "wof:name":"Peluqueria Eva Maria C.b",
    "wof:placetype":"venue"
},
  "geometry": {"coordinates":[1.272585988,41.6710357666],"type":"Point"}
}