{
  "type": "Feature",
  "properties": {
    "addr:full":"Calle de Paraguay, S/n Alcantarilla Murcia 30820",
    "addr:housenumber":"s",
    "addr:postcode":"30820",
    "addr:street":"Calle De Paraguay;/ N",
    "iso:country":"ES",
    "sg:address":"Calle de Paraguay, S/n",
    "sg:city":"Alcantarilla",
    "sg:orig_category":"Fabricaci\u00d3n De Mobiliario Met\u00c1lico",
    "sg:phone":"+34 968 89 59 98",
    "sg:postcode":"30820",
    "sg:province":"Murcia",
    "wof:name":"Tubo-murcia S.l.",
    "wof:placetype":"venue"
},
  "geometry": {"coordinates":[-1.197584033,37.9587364197],"type":"Point"}
}