{
  "type": "Feature",
  "properties": {
    "iso:country":"ES",
    "sg:address":"Avda Maisonnave, 15",
    "sg:city":"Alacant",
    "sg:orig_category":"Marroquiner\u00cda Y Art\u00cdculos De Viaje (al Por Menor)",
    "sg:phone":"+34 965 12 04 09",
    "sg:postcode":"03003",
    "sg:province":"Alicante",
    "wof:name":"Gonzalez Alarcon Primitivo",
    "wof:placetype":"venue"
},
  "geometry": {"coordinates":[-0.4901190102,38.3435401917],"type":"Point"}
}