{
  "type": "Feature",
  "properties": {
    "addr:full":"Avda Andurique, 28 Andurique Pontevedra 36005",
    "addr:housenumber":"28",
    "addr:postcode":"36005",
    "addr:street":"Avda Andurique",
    "iso:country":"ES",
    "sg:address":"Avda Andurique, 28",
    "sg:city":"Andurique",
    "sg:orig_category":"Ropa De Trabajo Y Profesionales (fabricaci\u00d3n, Al Por Mayor)",
    "sg:phone":"+34 986 87 16 52",
    "sg:postcode":"36005",
    "sg:province":"Pontevedra",
    "sg:website":"www.marblan.com",
    "wof:name":"Textil Poio S.l.",
    "wof:placetype":"venue"
},
  "geometry": {"coordinates":[-8.6331739426,42.4493751526],"type":"Point"}
}