{
  "type": "Feature",
  "properties": {
    "addr:full":"Calle de Lopez De Hoyos, 384 Madrid Madrid 28043",
    "addr:housenumber":"384",
    "addr:postcode":"28043",
    "addr:street":"Calle De Lopez De Hoyos",
    "iso:country":"ES",
    "sg:address":"Calle de Lopez De Hoyos, 384",
    "sg:city":"Madrid",
    "sg:orig_category":"Empresarios Y Productoras De Espect\u00c1culos",
    "sg:phone":"+34 915 24 11 68",
    "sg:postcode":"28043",
    "sg:province":"Madrid",
    "wof:name":"Mesala Films S.l.l.",
    "wof:placetype":"venue"
},
  "geometry": {"coordinates":[-3.6589169502,40.4609680176],"type":"Point"}
}