{
  "type": "Feature",
  "properties": {
    "iso:country":"ES",
    "sg:address":"Ctra Sequia Del Rei, S/n",
    "sg:city":"Grau I Platja",
    "sg:orig_category":"Centros De Coordinaci\u00d3n",
    "sg:phone":"+34 962 84 65 70",
    "sg:postcode":"46730",
    "sg:province":"Valencia",
    "wof:name":"Empori Gestion Y Administracion S.l.",
    "wof:placetype":"venue"
},
  "geometry": {"coordinates":[-0.1638440043,38.9950141907],"type":"Point"}
}