{
  "type": "Feature",
  "properties": {
    "addr:full":"Calle de Carretera, S/n Carcastillo Navarra 31310",
    "addr:postcode":"31310",
    "addr:street":"Calle De Carretera S / N",
    "iso:country":"ES",
    "sg:address":"Calle de Carretera, S/n",
    "sg:city":"Carcastillo",
    "sg:orig_category":"Conservas De Platos Cocinados (fabricaci\u00d3n, Al Por Mayor)",
    "sg:phone":"+34 948 72 50 00",
    "sg:postcode":"31310",
    "sg:province":"Navarra",
    "sg:website":"www.bajamar-mamia.com",
    "wof:name":"Bajamar S. A.",
    "wof:placetype":"venue"
},
  "geometry": {"coordinates":[-1.446408987,42.3809394836],"type":"Point"}
}