{
  "type": "Feature",
  "properties": {
    "addr:full":"S. Sebastia, 11 Palafrugell Girona 17200",
    "addr:housenumber":"11",
    "addr:postcode":"17200",
    "addr:street":"Sebastia",
    "iso:country":"ES",
    "sg:address":"S. Sebastia, 11",
    "sg:city":"Palafrugell",
    "sg:orig_category":"Ropa Para Ni\u00d1os (al Por Menor)",
    "sg:phone":"+34 972 30 08 19",
    "sg:postcode":"17200",
    "sg:province":"Girona",
    "wof:name":"Gerones Fontfreda Lluis",
    "wof:placetype":"venue"
},
  "geometry": {"coordinates":[3.1597599983,41.9181594849],"type":"Point"}
}