{
  "type": "Feature",
  "properties": {
    "iso:country":"ES",
    "sg:address":"Calle de Jose Garcia Selles, 2",
    "sg:city":"Alacant",
    "sg:orig_category":"Muebles, Minoristas",
    "sg:phone":"+34 965 24 42 57",
    "sg:postcode":"03012",
    "sg:province":"Alicante",
    "wof:name":"Mu\u00f1oz Mora Francisco",
    "wof:placetype":"venue"
},
  "geometry": {"coordinates":[-0.4696699977,38.3669319153],"type":"Point"}
}