{
  "type": "Feature",
  "properties": {
    "addr:full":"Fondo, S/n Quimaran Asturias 33438",
    "addr:housenumber":"s",
    "addr:postcode":"33438",
    "addr:street":"/ N Quimaran Asturias",
    "iso:country":"ES",
    "sg:address":"Fondo, S/n",
    "sg:city":"Quimaran",
    "sg:orig_category":"Cr\u00cda De Bovinos",
    "sg:phone":"+34 985 88 78 52",
    "sg:postcode":"33438",
    "sg:province":"Asturias",
    "wof:name":"Ganaderia Bernabe Sc",
    "wof:placetype":"venue"
},
  "geometry": {"coordinates":[-5.8532137871,43.552028656],"type":"Point"}
}