{
  "type": "Feature",
  "properties": {
    "addr:full":"Calle de Valdivieso, 7 Madrid Madrid 28023",
    "addr:housenumber":"7",
    "addr:postcode":"madrid;28023",
    "addr:street":"Calle De Valdivieso",
    "iso:country":"ES",
    "sg:address":"Calle de Valdivieso, 7",
    "sg:city":"Madrid",
    "sg:classifiers":[
        {
            "category":"Professional",
            "subcategory":"Management & Consulting",
            "type":"Services"
        }
    ],
    "sg:phone":"+34 917 40 25 01",
    "sg:postcode":"28023",
    "sg:province":"Madrid",
    "sg:tags":[
        "asesor\u00cda",
        "en",
        "marketing"
    ],
    "sg:website":"www.martin-and-sons.com",
    "wof:name":"Martin Sons S.l.u.",
    "wof:placetype":"venue"
},
  "geometry": {"coordinates":[-3.7803440094,40.4583969116],"type":"Point"}
}