{
  "type": "Feature",
  "properties": {
    "addr:full":"Calle de San Ignacio De Loyola, 8 Elda Alicante 03600",
    "addr:housenumber":"8",
    "addr:postcode":"03600",
    "addr:street":"Calle De San Ignacio De Loyola",
    "iso:country":"ES",
    "sg:address":"Calle de San Ignacio De Loyola, 8",
    "sg:city":"Elda",
    "sg:orig_category":"Mercer\u00cda, Lencer\u00cda (al Por Menor)",
    "sg:phone":"+34 965 38 02 17",
    "sg:postcode":"03600",
    "sg:province":"Alicante",
    "wof:name":"Sanz Amoros Jesus",
    "wof:placetype":"venue"
},
  "geometry": {"coordinates":[-0.79103899,38.4742698669],"type":"Point"}
}