{
  "type": "Feature",
  "properties": {
    "addr:full":"Calle de Santa Apolonia, 131 Aviles Asturias 33403",
    "addr:housenumber":"131",
    "addr:postcode":"33403",
    "addr:street":"Calle De Santa Apolonia",
    "iso:country":"ES",
    "sg:address":"Calle de Santa Apolonia, 131",
    "sg:city":"Aviles",
    "sg:orig_category":"Estancos",
    "sg:phone":"+34 985 57 60 00",
    "sg:postcode":"33403",
    "sg:province":"Asturias",
    "wof:name":"Jose Tresguerres Carrasco (estanco)",
    "wof:placetype":"venue"
},
  "geometry": {"coordinates":[-5.903717041,43.5392303467],"type":"Point"}
}