{
  "type": "Feature",
  "properties": {
    "iso:country":"ES",
    "sg:address":"Calle de Autonomia Aragon, 10",
    "sg:city":"Cartuja Baja",
    "sg:orig_category":"Encuadernaci\u00d3n E Impresi\u00d3n De Folletos",
    "sg:phone":"+34 976 50 12 43",
    "sg:postcode":"50720",
    "sg:province":"Zaragoza",
    "wof:name":"Garcia Irigoy Demetrio",
    "wof:placetype":"venue"
},
  "geometry": {"coordinates":[-0.8245267868,41.6059684753],"type":"Point"}
}