{
  "type": "Feature",
  "properties": {
    "iso:country":"ES",
    "sg:address":"Barr Murtatza, 5",
    "sg:city":"Murtatza",
    "sg:orig_category":"Aluminio Y Aleaciones (producci\u00d3n, Transformaci\u00d3n, Negocio)",
    "sg:phone":"+34 946 31 30 28",
    "sg:postcode":"48390",
    "sg:province":"Vizcaya",
    "wof:name":"Aluminios Padron S.a.",
    "wof:placetype":"venue"
},
  "geometry": {"coordinates":[-2.8106722832,43.2135391235],"type":"Point"}
}