{
  "type": "Feature",
  "properties": {
    "iso:country":"ES",
    "sg:address":"Av Pompeu Fabra, 13",
    "sg:city":"Barcelona",
    "sg:orig_category":"Asesor\u00cda Sobre Comunicaci\u00d3n De Empresas",
    "sg:phone":"+34 932 85 09 80",
    "sg:postcode":"08024",
    "sg:province":"Barcelona",
    "wof:name":"B C D Asesores S.a.",
    "wof:placetype":"venue"
},
  "geometry": {"coordinates":[2.1585059166,41.4142837524],"type":"Point"}
}