{
  "type": "Feature",
  "properties": {
    "iso:country":"ES",
    "sg:address":"Calle de Oca\u00d1a, 75",
    "sg:city":"Madrid",
    "sg:orig_category":"Farmacias",
    "sg:phone":"+34 914 65 11 12",
    "sg:postcode":"28047",
    "sg:province":"Madrid",
    "wof:name":"Valverde Jimenez Maria Lourdes",
    "wof:placetype":"venue"
},
  "geometry": {"coordinates":[-3.7559099197,40.3862724304],"type":"Point"}
}