{
  "type": "Feature",
  "properties": {
    "iso:country":"ES",
    "sg:address":"Carrer de Creu Dels Molers, 24",
    "sg:city":"Barcelona",
    "sg:orig_category":"Panader\u00cdas, Panader\u00cdas",
    "sg:phone":"+34 934 41 23 39",
    "sg:postcode":"08004",
    "sg:province":"Barcelona",
    "wof:name":"Garcia Duran Anastasio",
    "wof:placetype":"venue"
},
  "geometry": {"coordinates":[2.1614439487,41.3735961914],"type":"Point"}
}