{
  "type": "Feature",
  "properties": {
    "addr:full":"C/ Vila De Madrid, 1 Paterna Valencia 46988",
    "addr:housenumber":"1",
    "addr:postcode":"46988",
    "addr:street":"C / Vila De Madrid",
    "iso:country":"ES",
    "sg:address":"C/ Vila De Madrid, 1",
    "sg:city":"Paterna",
    "sg:orig_category":"Torrefactado De Caf\u00c9",
    "sg:phone":"+34 961 34 40 70",
    "sg:postcode":"46988",
    "sg:province":"Valencia",
    "sg:website":"www.cafesvaliente.es",
    "wof:name":"Cafes Valiente S.l.",
    "wof:placetype":"venue"
},
  "geometry": {"coordinates":[-0.4687919915,39.5216217041],"type":"Point"}
}