{
  "type": "Feature",
  "properties": {
    "addr:full":"Calle de Mazarron, Km. 2600,0 Ensanche-almarjal Murcia 30203",
    "addr:postcode":"30203",
    "addr:street":"Calle De Mazarron Km. 2600,0",
    "iso:country":"ES",
    "sg:address":"Calle de Mazarron, Km. 2600,0",
    "sg:city":"Ensanche-almarjal",
    "sg:orig_category":"Delegados, Agentes De Tr\u00c1nsito, Auxiliares De Transporte Internacional",
    "sg:phone":"+34 968 51 31 98",
    "sg:postcode":"30203",
    "sg:province":"Murcia",
    "wof:name":"Transportes Juan Saura S.l.",
    "wof:placetype":"venue"
},
  "geometry": {"coordinates":[-1.1298867464,37.9834747314],"type":"Point"}
}