{
  "type": "Feature",
  "properties": {
    "iso:country":"ES",
    "sg:address":"Maior, 3",
    "sg:city":"Pobra Trives",
    "sg:orig_category":"Cervecer\u00cdas",
    "sg:phone":"+34 988 33 00 72",
    "sg:postcode":"32780",
    "sg:province":"Ourense",
    "wof:name":"Rodriguez Mui\u00f1a Josefina",
    "wof:placetype":"venue"
},
  "geometry": {"coordinates":[-7.2561759949,42.3399772644],"type":"Point"}
}