{
  "type": "Feature",
  "properties": {
    "iso:country":"ES",
    "sg:address":"Carr Albeniz, 15",
    "sg:city":"Figueres",
    "sg:orig_category":"Arquitectos",
    "sg:phone":"+34 972 67 39 43",
    "sg:postcode":"17600",
    "sg:province":"Girona",
    "wof:name":"Falgueras Font Joan",
    "wof:placetype":"venue"
},
  "geometry": {"coordinates":[2.9581100941,42.2656898499],"type":"Point"}
}