{
  "type": "Feature",
  "properties": {
    "iso:country":"ES",
    "sg:address":"Plaz Zeroetxe Plaza, 2",
    "sg:city":"Elexalde Derio",
    "sg:orig_category":"Inmobiliaria (agencias)",
    "sg:phone":"+34 944 54 01 82",
    "sg:postcode":"48160",
    "sg:province":"Vizcaya",
    "wof:name":"Promociones Bei\u00f1 S.a.",
    "wof:placetype":"venue"
},
  "geometry": {"coordinates":[-2.8781220913,43.3008842468],"type":"Point"}
}