{
  "type": "Feature",
  "properties": {
    "addr:full":"Calle de Fermin Mosquera, 12 Caldas De Reis Pontevedra 36650",
    "addr:housenumber":"12",
    "addr:postcode":"36650",
    "addr:street":"Calle De Fermin Mosquera",
    "iso:country":"ES",
    "sg:address":"Calle de Fermin Mosquera, 12",
    "sg:city":"Caldas De Reis",
    "sg:orig_category":"Droguer\u00cdas (al Por Menor)",
    "sg:phone":"+34 986 54 04 26",
    "sg:postcode":"36650",
    "sg:province":"Pontevedra",
    "wof:name":"Perez Castro Hermanos S.l.",
    "wof:placetype":"venue"
},
  "geometry": {"coordinates":[-8.6462593079,42.6057815552],"type":"Point"}
}