{
  "type": "Feature",
  "properties": {
    "addr:full":"Kalezar Auzoa, 39 Kalezar Guip\u00f9zcoa 20170",
    "addr:housenumber":"39",
    "addr:postcode":"20170",
    "addr:street":"Kalezar Auzoa;Guipu\u0300Zcoa",
    "iso:country":"ES",
    "sg:address":"Kalezar Auzoa, 39",
    "sg:city":"Kalezar",
    "sg:orig_category":"Cervecer\u00cdas",
    "sg:phone":"+34 943 36 21 48",
    "sg:postcode":"20170",
    "sg:province":"Guip\u00f9zcoa",
    "wof:name":"Inversiones Etxekoak S.l.",
    "wof:placetype":"venue"
},
  "geometry": {"coordinates":[-2.0539140701,43.2733459473],"type":"Point"}
}