{
  "type": "Feature",
  "properties": {
    "iso:country":"ES",
    "sg:address":"Plgn Ind Sepes, S/n",
    "sg:city":"Puertollano",
    "sg:orig_category":"Montaje (empresas De)",
    "sg:phone":"+34 926 43 23 04",
    "sg:postcode":"13500",
    "sg:province":"Ciudad Real",
    "wof:name":"Talleres Mecanicos Del Sur S.a.",
    "wof:placetype":"venue"
},
  "geometry": {"coordinates":[-4.1123538017,38.6858253479],"type":"Point"}
}