{
  "type": "Feature",
  "properties": {
    "iso:country":"ES",
    "sg:address":"Trva Ezquerro, 40",
    "sg:city":"Autol",
    "sg:orig_category":"Farmacias",
    "sg:phone":"+34 941 39 03 77",
    "sg:postcode":"26560",
    "sg:province":"La Rioja",
    "wof:name":"Fernandez Hernandez Maria Angeles",
    "wof:placetype":"venue"
},
  "geometry": {"coordinates":[-2.0052258968,42.2163200378],"type":"Point"}
}