{
  "type": "Feature",
  "properties": {
    "addr:full":"Carrer de Varsovia, 82 Barcelona Barcelona 08041",
    "addr:housenumber":"82",
    "addr:postcode":"08041",
    "addr:street":"Carrer De Varsovia",
    "iso:country":"ES",
    "sg:address":"Carrer de Varsovia, 82",
    "sg:city":"Barcelona",
    "sg:orig_category":"Herradores, Herreros, Carreteros",
    "sg:phone":"+34 933 47 27 18",
    "sg:postcode":"08041",
    "sg:province":"Barcelona",
    "wof:name":"Doz Rey Jesus",
    "wof:placetype":"venue"
},
  "geometry": {"coordinates":[2.1745390892,41.4213867188],"type":"Point"}
}