{
  "type": "Feature",
  "properties": {
    "addr:full":"Pase Region Murciana, 3 Palmar  O Lugar De Don Juan Murcia 30120",
    "addr:housenumber":"3",
    "addr:postcode":"30120",
    "addr:street":"Murciana;Lugar",
    "iso:country":"ES",
    "sg:address":"Pase Region Murciana, 3",
    "sg:city":"Palmar  O Lugar De Don Juan",
    "sg:orig_category":"Comercio, Reparaci\u00d3n De Motocicletas, Bicicletas Y Piezas Sueltas",
    "sg:phone":"+34 968 88 53 33",
    "sg:postcode":"30120",
    "sg:province":"Murcia",
    "wof:name":"Frutos Galindo Jose",
    "wof:placetype":"venue"
},
  "geometry": {"coordinates":[-1.1302490234,37.9829597473],"type":"Point"}
}