{
  "type": "Feature",
  "properties": {
    "addr:full":"Calle de Procesiones, 46 Galapagar Madrid 28260",
    "addr:housenumber":"46",
    "addr:postcode":"28260",
    "addr:street":"Calle De Procesiones",
    "iso:country":"ES",
    "sg:address":"Calle de Procesiones, 46",
    "sg:city":"Galapagar",
    "sg:orig_category":"Asilos De Ancianos. Centros Privados",
    "sg:phone":"+34 918 58 42 40",
    "sg:postcode":"28260",
    "sg:province":"Madrid",
    "sg:website":"www.residencia-fatima.com",
    "wof:name":"Residencias Fatima S.l.",
    "wof:placetype":"venue"
},
  "geometry": {"coordinates":[-4.0036120415,40.5745162964],"type":"Point"}
}