{
  "type": "Feature",
  "properties": {
    "addr:full":"Calle de Victoriano Perez Vidal, 33 Esfarrapada Pontevedra 36470",
    "addr:housenumber":"33",
    "addr:postcode":"36470",
    "addr:street":"Calle De Victoriano Perez Vidal",
    "iso:country":"ES",
    "sg:address":"Calle de Victoriano Perez Vidal, 33",
    "sg:city":"Esfarrapada",
    "sg:orig_category":"M\u00c1rmoles, Granitos Y Piedras Naturales",
    "sg:phone":"+34 986 34 75 01",
    "sg:postcode":"36470",
    "sg:province":"Pontevedra",
    "wof:name":"Lemos Romero S.l.",
    "wof:placetype":"venue"
},
  "geometry": {"coordinates":[-8.5589160919,42.101108551],"type":"Point"}
}