{
  "type": "Feature",
  "properties": {
    "addr:full":"Trva Jose Antonio Ii, S/n Laredo Cantabria 39770",
    "addr:housenumber":"s / n",
    "addr:postcode":"39770",
    "addr:street":"Trva Jose Antonio Ii",
    "iso:country":"ES",
    "sg:address":"Trva Jose Antonio Ii, S/n",
    "sg:city":"Laredo",
    "sg:orig_category":"Ortopedia General",
    "sg:phone":"+34 942 61 11 77",
    "sg:postcode":"39770",
    "sg:province":"Cantabria",
    "wof:name":"Ortogan S.l.",
    "wof:placetype":"venue"
},
  "geometry": {"coordinates":[-3.4151239395,43.4095687866],"type":"Point"}
}