{
  "type": "Feature",
  "properties": {
    "iso:country":"ES",
    "sg:address":"Calle de Benavente, 48",
    "sg:city":"Albacete",
    "sg:orig_category":"Instalaci\u00d3n, Reparaci\u00d3n De Ascensores Y Montacargas",
    "sg:phone":"+34 967 22 05 16",
    "sg:postcode":"02006",
    "sg:province":"Albacete",
    "wof:name":"Devega S. A.",
    "wof:placetype":"venue"
},
  "geometry": {"coordinates":[-1.8717397451,38.9949111938],"type":"Point"}
}