{
  "type": "Feature",
  "properties": {
    "addr:full":"Calle de Guadiana, 15 Bosque Madrid 28670",
    "addr:housenumber":"15",
    "addr:postcode":"28670",
    "addr:street":"Calle De Guadiana",
    "iso:country":"ES",
    "sg:address":"Calle de Guadiana, 15",
    "sg:city":"Bosque",
    "sg:orig_category":"Maquinaria Para Industrias Diversas",
    "sg:phone":"+34 916 16 76 96",
    "sg:postcode":"28670",
    "sg:province":"Madrid",
    "wof:name":"Higuera Blanco Jose Luis",
    "wof:placetype":"venue"
},
  "geometry": {"coordinates":[-3.9257040024,40.3833999634],"type":"Point"}
}