{
  "type": "Feature",
  "properties": {
    "iso:country":"ES",
    "sg:address":"Ecuador, 1",
    "sg:city":"Elche",
    "sg:orig_category":"Agentes, Concesionarios Y Sucursales De Veh\u00cdculos",
    "sg:phone":"+34 965 43 62 62",
    "sg:postcode":"03205",
    "sg:province":"Alicante",
    "wof:name":"Automocion Anton S. L. (tata Motors",
    "wof:placetype":"venue"
},
  "geometry": {"coordinates":[-0.6995239854,38.2634811401],"type":"Point"}
}