{
  "type": "Feature",
  "properties": {
    "addr:full":"Don J. Fdez. Hurtado, 4 Cogollos Vega Granada 18197",
    "addr:housenumber":"4",
    "addr:postcode":"18197",
    "addr:street":"Hurtado",
    "iso:country":"ES",
    "sg:address":"Don J. Fdez. Hurtado, 4",
    "sg:city":"Cogollos Vega",
    "sg:orig_category":"Perfumer\u00cda Y Cosm\u00c9tica (fabricaci\u00d3n, Al Por Mayor)",
    "sg:phone":"+34 958 42 20 13",
    "sg:postcode":"18197",
    "sg:province":"Granada",
    "wof:name":"Morcillo Galvez Jose",
    "wof:placetype":"venue"
},
  "geometry": {"coordinates":[-3.6097240448,37.2210998535],"type":"Point"}
}