{
  "type": "Feature",
  "properties": {
    "addr:full":"Calle de Ramon Menendez Pidal, 3 Zaragoza Zaragoza 50009",
    "addr:housenumber":"3",
    "addr:postcode":"50009",
    "addr:street":"Calle De Ramon Menendez Pidal",
    "iso:country":"ES",
    "sg:address":"Calle de Ramon Menendez Pidal, 3",
    "sg:city":"Zaragoza",
    "sg:orig_category":"Asistencia Social",
    "sg:phone":"+34 976 56 71 04",
    "sg:postcode":"50009",
    "sg:province":"Zaragoza",
    "wof:name":"Asociacion De Padres De Ni\u00f1os Oncologicos De Aragon",
    "wof:placetype":"venue"
},
  "geometry": {"coordinates":[-0.9032769203,41.6400489807],"type":"Point"}
}