{
  "type": "Feature",
  "properties": {
    "addr:full":"Calle de Alcalde Juan Filter, 16 Ca\u00e7ada Rosal Sevilla 41439",
    "addr:housenumber":"16",
    "addr:postcode":"41439",
    "addr:street":"Calle De Alcalde Juan Filter;Rosal",
    "iso:country":"ES",
    "sg:address":"Calle de Alcalde Juan Filter, 16",
    "sg:city":"Ca\u00e7ada Rosal",
    "sg:orig_category":"Cajas Para Embalar",
    "sg:phone":"+34 954 83 91 53",
    "sg:postcode":"41439",
    "sg:province":"Sevilla",
    "sg:website":"www.ruralvia.com",
    "wof:name":"Caja Rural Del Sur Sociedad Cooperativa",
    "wof:placetype":"venue"
},
  "geometry": {"coordinates":[-5.9962949753,37.3826408386],"type":"Point"}
}