{
  "type": "Feature",
  "properties": {
    "iso:country":"ES",
    "sg:address":"Ctra. Romeral, S/n",
    "sg:city":"Lillo",
    "sg:orig_category":"Aer\u00d3grafo",
    "sg:phone":"+34 925 17 05 33",
    "sg:postcode":"45870",
    "sg:province":"Toledo",
    "wof:name":"Real Aeroclub De Toledo",
    "wof:placetype":"venue"
},
  "geometry": {"coordinates":[-3.3106338978,39.7220039368],"type":"Point"}
}