{
  "type": "Feature",
  "properties": {
    "addr:full":"Calle de Pedro Lopez, 7 Cordoba C\u00f3rdoba 14002",
    "addr:housenumber":"7",
    "addr:postcode":"14002",
    "addr:street":"Calle De Pedro Lopez;Co\u0301Rdoba",
    "iso:country":"ES",
    "sg:address":"Calle de Pedro Lopez, 7",
    "sg:city":"Cordoba",
    "sg:orig_category":"Bisuter\u00cda, Joyer\u00cda, Relojer\u00cda (al Por Menor)",
    "sg:phone":"+34 957 48 72 55",
    "sg:postcode":"14002",
    "sg:province":"C\u00f3rdoba",
    "wof:name":"Cruz Cano Manuel",
    "wof:placetype":"venue"
},
  "geometry": {"coordinates":[-4.7747850418,37.8844184875],"type":"Point"}
}