{
  "type": "Feature",
  "properties": {
    "iso:country":"ES",
    "sg:address":"Txonta Kalea, 1",
    "sg:city":"Eibar",
    "sg:orig_category":"Asociaciones, Organismos Culturales Y Socioeducativos",
    "sg:phone":"+34 943 12 05 53",
    "sg:postcode":"20600",
    "sg:province":"Guip\u00f9zcoa",
    "wof:name":"Sociedad Cultural Recreativa Edo-ser",
    "wof:placetype":"venue"
},
  "geometry": {"coordinates":[-2.4627740383,43.1865005493],"type":"Point"}
}