{
  "type": "Feature",
  "properties": {
    "iso:country":"ES",
    "sg:address":"F. Rguez Fuente, 20",
    "sg:city":"Montilla",
    "sg:classifiers":[
        {
            "category":"Taxi",
            "type":"Transportation"
        }
    ],
    "sg:phone":"+34 957 65 13 77",
    "sg:postcode":"14550",
    "sg:province":"C\u00f3rdoba",
    "wof:name":"Criado Duque Antonio",
    "wof:placetype":"venue"
},
  "geometry": {"coordinates":[-4.6404590607,37.58177948],"type":"Point"}
}