{
  "type": "Feature",
  "properties": {
    "addr:full":"Fco Bergamin, 7 Iru\u00f1a Navarra 31003",
    "addr:housenumber":"7",
    "addr:postcode":"31003",
    "addr:street":"Fco Bergamin",
    "iso:country":"ES",
    "sg:address":"Fco Bergamin, 7",
    "sg:city":"Iru\u00f1a",
    "sg:orig_category":"M\u00c9dicos: Estomatolog\u00cda",
    "sg:phone":"+34 948 24 81 94",
    "sg:postcode":"31003",
    "sg:province":"Navarra",
    "wof:name":"Larriu Castro Alvaro",
    "wof:placetype":"venue"
},
  "geometry": {"coordinates":[-1.6411759853,42.812664032],"type":"Point"}
}