{
  "type": "Feature",
  "properties": {
    "iso:country":"ES",
    "sg:address":"Calle de Potasa, 20",
    "sg:city":"Madrid",
    "sg:orig_category":"Molduras, Junquillos, Listones Y Molduras Perforadas",
    "sg:phone":"+34 917 95 02 21",
    "sg:postcode":"28021",
    "sg:province":"Madrid",
    "wof:name":"Jimenez Lopez Juan Antonio",
    "wof:placetype":"venue"
},
  "geometry": {"coordinates":[-3.6804471016,40.3517608643],"type":"Point"}
}