{
  "type": "Feature",
  "properties": {
    "addr:full":"Calle de Enrique Madrid, 22 Alacant Alicante 03013",
    "addr:housenumber":"22",
    "addr:postcode":"03013",
    "addr:street":"Calle De Enrique Madrid",
    "iso:country":"ES",
    "sg:address":"Calle de Enrique Madrid, 22",
    "sg:city":"Alacant",
    "sg:orig_category":"Cl\u00cdnicas Dentales",
    "sg:phone":"+34 965 21 52 16",
    "sg:postcode":"03013",
    "sg:province":"Alicante",
    "wof:name":"Puertas Plana Beatriz Maria",
    "wof:placetype":"venue"
},
  "geometry": {"coordinates":[-0.4750890136,38.3589668274],"type":"Point"}
}