{
  "type": "Feature",
  "properties": {
    "iso:country":"ES",
    "sg:address":"Calle de Duero, S/n",
    "sg:city":"Duruelo Sierra",
    "sg:orig_category":"Contenedores (mercanc\u00cdas)",
    "sg:phone":"+34 975 37 11 46",
    "sg:postcode":"42158",
    "sg:province":"Soria",
    "wof:name":"Francisco Rubio Rufo",
    "wof:placetype":"venue"
},
  "geometry": {"coordinates":[-2.9307010174,41.9523391724],"type":"Point"}
}