{
  "type": "Feature",
  "properties": {
    "addr:full":"Pla\u00c7 Pou (del), 4 Agramunt Lleida 25310",
    "addr:postcode":"25310",
    "iso:country":"ES",
    "sg:address":"Pla\u00c7 Pou (del), 4",
    "sg:city":"Agramunt",
    "sg:orig_category":"Venta, Instalaci\u00d3n De Cocinas",
    "sg:phone":"+34 973 39 01 09",
    "sg:postcode":"25310",
    "sg:province":"Lleida",
    "wof:name":"Ingles Sole Jorge",
    "wof:placetype":"venue"
},
  "geometry": {"coordinates":[1.0873551369,41.785369873],"type":"Point"}
}