{
  "type": "Feature",
  "properties": {
    "iso:country":"ES",
    "sg:address":"Calle de Rio Taju\u00d1a, 18",
    "sg:city":"Arganda",
    "sg:orig_category":"Empresas De Carpinter\u00cda De Madera",
    "sg:phone":"+34 918 70 28 97",
    "sg:postcode":"28500",
    "sg:province":"Madrid",
    "wof:name":"Carpinteria Gonmar Comunidad",
    "wof:placetype":"venue"
},
  "geometry": {"coordinates":[-3.4582710266,40.300907135],"type":"Point"}
}