{
  "type": "Feature",
  "properties": {
    "iso:country":"ES",
    "sg:address":"Paseo Colon De, 7",
    "sg:city":"Donostia-san Sebastian",
    "sg:orig_category":"Textil",
    "sg:phone":"+34 943 27 29 93",
    "sg:postcode":"20002",
    "sg:province":"Guip\u00f9zcoa",
    "wof:name":"Jose Ignacio Parra Gonzalez (condor)",
    "wof:placetype":"venue"
},
  "geometry": {"coordinates":[-1.9773459435,43.3223724365],"type":"Point"}
}