{
  "type": "Feature",
  "properties": {
    "iso:country":"ES",
    "sg:address":"Calle de Aldea Del Fresno, 1",
    "sg:city":"Madrid",
    "sg:orig_category":"Asociaciones Humanitarias, De Cooperaci\u00d3n, De Acci\u00d3n Social",
    "sg:phone":"+34 914 74 68 45",
    "sg:postcode":"28045",
    "sg:province":"Madrid",
    "wof:name":"Minka Centro De Promocion Y Solidaridad",
    "wof:placetype":"venue"
},
  "geometry": {"coordinates":[-3.6966080666,40.3962860107],"type":"Point"}
}