{
  "type": "Feature",
  "properties": {
    "iso:country":"ES",
    "sg:address":"Avda Almendros, 17",
    "sg:city":"Benidorm",
    "sg:orig_category":"Farmacias",
    "sg:phone":"+34 966 83 10 18",
    "sg:postcode":"03500",
    "sg:province":"Alicante",
    "wof:name":"Maria Elena Toledano Iborra Y Rosa Ruiz Galvez C.b.",
    "wof:placetype":"venue"
},
  "geometry": {"coordinates":[-0.1743289977,38.5408058167],"type":"Point"}
}