{
  "type": "Feature",
  "properties": {
    "addr:full":"Calle de Serrano Anguita, 12 Madrid Madrid 28004",
    "addr:housenumber":"12",
    "addr:postcode":"madrid;28004",
    "addr:street":"Calle De Serrano Anguita",
    "iso:country":"ES",
    "sg:address":"Calle de Serrano Anguita, 12",
    "sg:city":"Madrid",
    "sg:orig_category":"Fotocopias, Reprograf\u00cda",
    "sg:phone":"+34 914 48 42 57",
    "sg:postcode":"28004",
    "sg:province":"Madrid",
    "wof:name":"Copyprint S.l.",
    "wof:placetype":"venue"
},
  "geometry": {"coordinates":[-3.6983630657,40.4277420044],"type":"Point"}
}