{
  "type": "Feature",
  "properties": {
    "addr:full":"Calle de Molino, S/n Villafranca Navarra 31330",
    "addr:housenumber":"s",
    "addr:postcode":"31330",
    "addr:street":"Calle De Molino;/ N",
    "iso:country":"ES",
    "sg:address":"Calle de Molino, S/n",
    "sg:city":"Villafranca",
    "sg:orig_category":"Semiller\u00cdas",
    "sg:phone":"+34 948 84 50 50",
    "sg:postcode":"31330",
    "sg:province":"Navarra",
    "wof:name":"Viveros Zamarguilea",
    "wof:placetype":"venue"
},
  "geometry": {"coordinates":[-1.7501451969,42.279296875],"type":"Point"}
}