{
  "type": "Feature",
  "properties": {
    "addr:full":"Calle de Isla De Tavira, 12 Madrid Madrid 28035",
    "addr:housenumber":"12",
    "addr:postcode":"madrid;28035",
    "addr:street":"Calle De Isla De Tavira",
    "iso:country":"ES",
    "sg:address":"Calle de Isla De Tavira, 12",
    "sg:city":"Madrid",
    "sg:orig_category":"Centros Empresariales",
    "sg:phone":"+34 917 30 14 14",
    "sg:postcode":"28035",
    "sg:province":"Madrid",
    "wof:name":"Servicios De Internet Y Comunicaciones El Rubi S.l.",
    "wof:placetype":"venue"
},
  "geometry": {"coordinates":[-3.7178750038,40.4818725586],"type":"Point"}
}