{
  "type": "Feature",
  "properties": {
    "iso:country":"ES",
    "sg:address":"Calle de Alejandro Casona, 1",
    "sg:city":"Lugones",
    "sg:orig_category":"Decoradores",
    "sg:phone":"+34 985 26 67 00",
    "sg:postcode":"33420",
    "sg:province":"Asturias",
    "wof:name":"Fernandez Olay Natividad Josefa",
    "wof:placetype":"venue"
},
  "geometry": {"coordinates":[-5.8121337891,43.4023857117],"type":"Point"}
}