{
  "type": "Feature",
  "properties": {
    "iso:country":"ES",
    "sg:address":"Carr De Jose Iranzo, 63",
    "sg:city":"Ontinyent",
    "sg:orig_category":"Material Y Suministros Para Fotocopiadoras, Reprograf\u00cda",
    "sg:phone":"+34 962 38 04 67",
    "sg:postcode":"46870",
    "sg:province":"Valencia",
    "wof:name":"Ricotec S.l.",
    "wof:placetype":"venue"
},
  "geometry": {"coordinates":[-0.5992779732,38.8233375549],"type":"Point"}
}