{
  "type": "Feature",
  "properties": {
    "addr:full":"Calle de Historiador Claudio Sanchez Albornoz, 3 Valencia Valencia 46021",
    "addr:housenumber":"3",
    "addr:postcode":"46021",
    "addr:street":"Calle De Historiador Claudio Sanchez Albornoz",
    "iso:country":"ES",
    "sg:address":"Calle de Historiador Claudio Sanchez Albornoz, 3",
    "sg:city":"Valencia",
    "sg:orig_category":"Quincaller\u00cda (al Por Menor)",
    "sg:phone":"+34 963 93 35 38",
    "sg:postcode":"46021",
    "sg:province":"Valencia",
    "wof:name":"A\u00f1on Matamales Jose Luis",
    "wof:placetype":"venue"
},
  "geometry": {"coordinates":[-0.352376014,39.4768829346],"type":"Point"}
}