{
  "type": "Feature",
  "properties": {
    "addr:full":"Avda Venezuela, 20 Llanos De Aridane Santa Cruz De Tenerife 38760",
    "addr:housenumber":"20",
    "addr:postcode":"38760",
    "addr:street":"Avda Venezuela",
    "iso:country":"ES",
    "sg:address":"Avda Venezuela, 20",
    "sg:city":"Llanos De Aridane",
    "sg:orig_category":"Dietistas",
    "sg:phone":"+34 922 40 15 02",
    "sg:postcode":"38760",
    "sg:province":"Santa Cruz De Tenerife",
    "wof:name":"Sanchez Rodriguez Maria Mercedes",
    "wof:placetype":"venue"
},
  "geometry": {"coordinates":[-17.9085597992,28.6563796997],"type":"Point"}
}