{
  "type": "Feature",
  "properties": {
    "addr:full":"Calle de Padre Ferrer, 120 Granada Granada 18008",
    "addr:housenumber":"120",
    "addr:postcode":"18008",
    "addr:street":"Calle De Padre Ferrer",
    "iso:country":"ES",
    "sg:address":"Calle de Padre Ferrer, 120",
    "sg:city":"Granada",
    "sg:orig_category":"Centros Empresariales",
    "sg:phone":"+34 958 18 31 89",
    "sg:postcode":"18008",
    "sg:province":"Granada",
    "wof:name":"Arcon Patrimonial S.a.",
    "wof:placetype":"venue"
},
  "geometry": {"coordinates":[-3.5774064064,37.1567268372],"type":"Point"}
}