{
  "type": "Feature",
  "properties": {
    "iso:country":"ES",
    "sg:address":"Calle de Sornells, 30",
    "sg:city":"Valencia",
    "sg:orig_category":"Asesor\u00cda Sobre Comunicaci\u00d3n De Empresas",
    "sg:phone":"+34 963 33 09 54",
    "sg:postcode":"46006",
    "sg:province":"Valencia",
    "wof:name":"Abel Y Cain Asociados 2005 S.l.",
    "wof:placetype":"venue"
},
  "geometry": {"coordinates":[-0.371714,39.459881],"type":"Point"}
}