{
  "type": "Feature",
  "properties": {
    "iso:country":"ES",
    "sg:address":"Ctra Carretera De Plasencia, S/n",
    "sg:city":"Carcaboso",
    "sg:orig_category":"Cajas De Ahorro",
    "sg:phone":"+34 927 40 20 52",
    "sg:postcode":"10670",
    "sg:province":"C\u00e1ceres",
    "wof:name":"Caja De Ahorros Y Monte De Piedad De Extremadura",
    "wof:placetype":"venue"
},
  "geometry": {"coordinates":[-6.2152481079,40.0505523682],"type":"Point"}
}