{
  "type": "Feature",
  "properties": {
    "iso:country":"ES",
    "sg:address":"Calle de Capitan Pallares, 14",
    "sg:city":"Sagunt",
    "sg:orig_category":"Supermercados Y Hipermercados",
    "sg:phone":"+34 962 66 61 61",
    "sg:postcode":"46500",
    "sg:province":"Valencia",
    "wof:name":"Caprabo S.a.",
    "wof:placetype":"venue"
},
  "geometry": {"coordinates":[-0.2799566984,39.6805229187],"type":"Point"}
}