{
  "type": "Feature",
  "properties": {
    "iso:country":"ES",
    "sg:address":"Ctra Palma Del Rio (bda. Occidente), S/n",
    "sg:city":"Cordoba",
    "sg:orig_category":"Carnicer\u00cdas, Carnicer\u00cdas",
    "sg:phone":"+34 957 46 55 07",
    "sg:postcode":"14005",
    "sg:province":"C\u00f3rdoba",
    "wof:name":"Alimentacion Peninsular S.a.",
    "wof:placetype":"venue"
},
  "geometry": {"coordinates":[-4.8831849098,37.866859436],"type":"Point"}
}