{
  "type": "Feature",
  "properties": {
    "iso:country":"ES",
    "sg:address":"Avda Faro Pechiguera, S/n",
    "sg:city":"Monta\u00e7a Roja",
    "sg:orig_category":"Alquiler De Veh\u00cdculos: Turismos Y Utilitarios",
    "sg:phone":"+34 928 51 84 14",
    "sg:postcode":"35580",
    "sg:province":"Las Palmas",
    "wof:name":"A.cabrera S.l.",
    "wof:placetype":"venue"
},
  "geometry": {"coordinates":[-15.430006,28.124823],"type":"Point"}
}