{
  "type": "Feature",
  "properties": {
    "iso:country":"ES",
    "sg:address":"Ctra. Valencia-ademuz, Km. 0013,5",
    "sg:city":"S. Antonio Benageber",
    "sg:orig_category":"Muebles",
    "sg:phone":"+34 961 35 02 04",
    "sg:postcode":"46184",
    "sg:province":"Valencia",
    "wof:name":"Zry Productions S.l.",
    "wof:placetype":"venue"
},
  "geometry": {"coordinates":[-0.5399304032,39.5894050598],"type":"Point"}
}