{
  "type": "Feature",
  "properties": {
    "addr:full":"Calle de Oca, 49 Madrid Madrid 28025",
    "addr:housenumber":"49",
    "addr:postcode":"madrid;28025",
    "addr:street":"Calle De Oca",
    "iso:country":"ES",
    "sg:address":"Calle de Oca, 49",
    "sg:city":"Madrid",
    "sg:orig_category":"Fabricaci\u00d3n, Instalaci\u00d3n De Saunas",
    "sg:phone":"+34 914 61 82 92",
    "sg:postcode":"28025",
    "sg:province":"Madrid",
    "wof:name":"Gestion Integral Del Bronceado S.l.",
    "wof:placetype":"venue"
},
  "geometry": {"coordinates":[-3.737924099,40.3891181946],"type":"Point"}
}