{
  "type": "Feature",
  "properties": {
    "addr:full":"Plaz Conde De Barcelona, S/n Santa Marta De Tormes Salamanca 37900",
    "addr:housenumber":"/ n",
    "addr:postcode":"37900",
    "addr:street":"S",
    "iso:country":"ES",
    "sg:address":"Plaz Conde De Barcelona, S/n",
    "sg:city":"Santa Marta De Tormes",
    "sg:orig_category":"Restaurantes",
    "sg:phone":"+34 923 20 16 45",
    "sg:postcode":"37900",
    "sg:province":"Salamanca",
    "wof:name":"Arango  Salvador",
    "wof:placetype":"venue"
},
  "geometry": {"coordinates":[-5.6221389771,40.950466156],"type":"Point"}
}