{
  "type": "Feature",
  "properties": {
    "addr:full":"Carrer de Valencia (de), 58 Salou Tarragona 43840",
    "addr:housenumber":"58",
    "addr:postcode":"43840",
    "addr:street":"Carrer De Valencia De",
    "iso:country":"ES",
    "sg:address":"Carrer de Valencia (de), 58",
    "sg:city":"Salou",
    "sg:orig_category":"Alimentaci\u00d3n General (al Por Menor)",
    "sg:phone":"+34 977 38 59 09",
    "sg:postcode":"43840",
    "sg:province":"Tarragona",
    "wof:name":"Gesali Rius Magdalena",
    "wof:placetype":"venue"
},
  "geometry": {"coordinates":[1.1254709959,41.0759811401],"type":"Point"}
}