{
  "type": "Feature",
  "properties": {
    "addr:full":"Calle de Veinte De Noviembre, 25 Carrion Calatrava Ciudad Real 13150",
    "addr:housenumber":"25",
    "addr:postcode":"13150",
    "addr:street":"Calle De Veinte De Noviembre",
    "iso:country":"ES",
    "sg:address":"Calle de Veinte De Noviembre, 25",
    "sg:city":"Carrion Calatrava",
    "sg:orig_category":"Cooperativas Agr\u00cdcolas",
    "sg:phone":"+34 926 81 50 91",
    "sg:postcode":"13150",
    "sg:province":"Ciudad Real",
    "wof:name":"Tierra De Calatrava De Miguelturra S Coop De Clm",
    "wof:placetype":"venue"
},
  "geometry": {"coordinates":[-3.8151750565,39.0208435059],"type":"Point"}
}