{
  "type": "Feature",
  "properties": {
    "iso:country":"ES",
    "sg:address":"Calle de Artekale, 3",
    "sg:city":"Getxo",
    "sg:orig_category":"Mercer\u00cda, Lencer\u00cda (al Por Menor)",
    "sg:phone":"+34 944 80 28 22",
    "sg:postcode":"48930",
    "sg:province":"Vizcaya",
    "wof:name":"Ana Hormaechea Orbe (el  Boton)",
    "wof:placetype":"venue"
},
  "geometry": {"coordinates":[-3.0135154724,43.3246383667],"type":"Point"}
}