{
  "type": "Feature",
  "properties": {
    "iso:country":"ES",
    "sg:address":"Calle de San Eloy, 54",
    "sg:city":"Sevilla",
    "sg:orig_category":"Loter\u00cda Y T\u00d3mbola",
    "sg:phone":"+34 954 22 19 84",
    "sg:postcode":"41001",
    "sg:province":"Sevilla",
    "wof:name":"Mejias Ruiz Elisa",
    "wof:placetype":"venue"
},
  "geometry": {"coordinates":[-5.9982237816,37.391330719],"type":"Point"}
}