{
  "type": "Feature",
  "properties": {
    "addr:full":"Calle de Union, 32 Castellon Castell\u00f3n 12004",
    "addr:housenumber":"32",
    "addr:postcode":"12004",
    "addr:street":"Calle De;Castellon Castello\u0301N",
    "iso:country":"ES",
    "sg:address":"Calle de Union, 32",
    "sg:city":"Castellon",
    "sg:orig_category":"Caf\u00c9s, Bares, Cervecer\u00cdas",
    "sg:phone":"+34 964 21 56 15",
    "sg:postcode":"12004",
    "sg:province":"Castell\u00f3n",
    "wof:name":"Rabaza Conesa Jesus Narciso",
    "wof:placetype":"venue"
},
  "geometry": {"coordinates":[-0.0461479984,39.9905700684],"type":"Point"}
}