{
  "type": "Feature",
  "properties": {
    "iso:country":"ES",
    "sg:address":"Cra Santa Creu De Calafell, 41",
    "sg:city":"Gava",
    "sg:orig_category":"Notarios",
    "sg:phone":"+34 936 62 05 66",
    "sg:postcode":"08850",
    "sg:province":"Barcelona",
    "wof:name":"Del Rio Herrera Adolfo Carlos",
    "wof:placetype":"venue"
},
  "geometry": {"coordinates":[2.009155035,41.304107666],"type":"Point"}
}