{
  "type": "Feature",
  "properties": {
    "addr:full":"Calle de Lope Gisbert, S/n Santiago Murcia 30800",
    "addr:housenumber":"/ n",
    "addr:postcode":"30800",
    "addr:street":"Calle De Lope Gisbert S",
    "iso:country":"ES",
    "sg:address":"Calle de Lope Gisbert, S/n",
    "sg:city":"Santiago",
    "sg:orig_category":"Clubes, Asociaciones De Ocio",
    "sg:phone":"+34 968 47 02 69",
    "sg:postcode":"30800",
    "sg:province":"Murcia",
    "wof:name":"Amigos Del Flamenco",
    "wof:placetype":"venue"
},
  "geometry": {"coordinates":[-1.1298867464,37.9834747314],"type":"Point"}
}