{
  "type": "Feature",
  "properties": {
    "iso:country":"ES",
    "sg:address":"Carrer de Arago, 19",
    "sg:city":"Creus",
    "sg:orig_category":"Empresas De Carpinter\u00cda De Madera",
    "sg:phone":"+34 937 62 12 98",
    "sg:postcode":"08397",
    "sg:province":"Barcelona",
    "sg:website":"www.espais.biz",
    "wof:name":"Fusteria Pineda Mar Scp",
    "wof:placetype":"venue"
},
  "geometry": {"coordinates":[2.6812820435,41.6267356873],"type":"Point"}
}