{
  "type": "Feature",
  "properties": {
    "addr:full":"Calle de Arzobispo De Castro, 7 Burgos Burgos 09007",
    "addr:housenumber":"7",
    "addr:postcode":"09007",
    "addr:street":"Calle De Arzobispo De Castro",
    "iso:country":"ES",
    "sg:address":"Calle de Arzobispo De Castro, 7",
    "sg:city":"Burgos",
    "sg:orig_category":"Molduras, Junquillos, Listones Y Molduras Perforadas",
    "sg:phone":"+34 947 22 48 73",
    "sg:postcode":"09007",
    "sg:province":"Burgos",
    "wof:name":"Francisco Javier Diez Guemes Y Otro S.cv.",
    "wof:placetype":"venue"
},
  "geometry": {"coordinates":[-3.6693577766,42.3519592285],"type":"Point"}
}