{
  "type": "Feature",
  "properties": {
    "iso:country":"ES",
    "sg:address":"Avda Peris Y Valero, 81",
    "sg:city":"Valencia",
    "sg:orig_category":"Asesor\u00cda Sobre Comunicaci\u00d3n De Empresas",
    "sg:phone":"+34 963 33 33 58",
    "sg:postcode":"46006",
    "sg:province":"Valencia",
    "wof:name":"Yverdon Servicio De Asesoramiento Empresarial S.l.",
    "wof:placetype":"venue"
},
  "geometry": {"coordinates":[-0.3722938001,39.4584236145],"type":"Point"}
}