{
  "type": "Feature",
  "properties": {
    "iso:country":"ES",
    "sg:address":"Ptge L'hort Dels Velluters, 9",
    "sg:city":"Barcelona",
    "sg:orig_category":"Barnizadores",
    "sg:phone":"+34 932 68 25 27",
    "sg:postcode":"08003",
    "sg:province":"Barcelona",
    "wof:name":"Latorre Ari\u00f1o Jose",
    "wof:placetype":"venue"
},
  "geometry": {"coordinates":[2.1796889305,41.3897094727],"type":"Point"}
}