{
  "type": "Feature",
  "properties": {
    "iso:country":"ES",
    "sg:address":"Cra. Manresa A Abrera, Km. 0020,0",
    "sg:city":"S. Vicen\u00e7 Castellet",
    "sg:orig_category":"Fibras De Vidrio",
    "sg:phone":"+34 938 33 38 05",
    "sg:postcode":"08295",
    "sg:province":"Barcelona",
    "wof:name":"Owens Corning Fiberglass Espa\u00d1a S.a.",
    "wof:placetype":"venue"
},
  "geometry": {"coordinates":[1.8631989956,41.6670608521],"type":"Point"}
}