{
  "type": "Feature",
  "properties": {
    "iso:country":"ES",
    "sg:address":"Plaz Estacion De Autobuses (la), S/n",
    "sg:city":"Segovia",
    "sg:orig_category":"Autob\u00das (explotaci\u00d3n Y Servicios De)",
    "sg:phone":"+34 921 42 77 16",
    "sg:postcode":"40002",
    "sg:province":"Segovia",
    "sg:website":"www.paginasamarillas.es",
    "wof:name":"Autocares Bermejo S.l.",
    "wof:placetype":"venue"
},
  "geometry": {"coordinates":[-4.1215829849,40.9444732666],"type":"Point"}
}