{
  "type": "Feature",
  "properties": {
    "iso:country":"ES",
    "sg:address":"Calle de Consolacion, 28",
    "sg:city":"Torrelavega",
    "sg:orig_category":"Ropa Para Se\u00d1oras Y Caballeros (al Por Menor)",
    "sg:phone":"+34 942 80 27 13",
    "sg:postcode":"39300",
    "sg:province":"Cantabria",
    "wof:name":"Wilderson S.l.",
    "wof:placetype":"venue"
},
  "geometry": {"coordinates":[-4.0475120544,43.3508262634],"type":"Point"}
}