{
  "type": "Feature",
  "properties": {
    "iso:country":"ES",
    "sg:address":"Avda Doctor Mara\u00d1on, 17",
    "sg:city":"Majadahonda",
    "sg:orig_category":"Material Y Suministros Para Minas Y Canteras",
    "sg:phone":"+34 916 34 04 68",
    "sg:postcode":"28220",
    "sg:province":"Madrid",
    "sg:website":"www.jaguey.es",
    "wof:name":"Equipos Y Procesos Para Beneficio De Minerales S.l.",
    "wof:placetype":"venue"
},
  "geometry": {"coordinates":[-3.8770871162,40.473274231],"type":"Point"}
}