{
  "type": "Feature",
  "properties": {
    "addr:full":"Calle de Antonio Sequeros, 30 Almoradi Alicante 03160",
    "addr:housenumber":"30",
    "addr:postcode":"03160",
    "addr:street":"Calle De Antonio Sequeros",
    "iso:country":"ES",
    "sg:address":"Calle de Antonio Sequeros, 30",
    "sg:city":"Almoradi",
    "sg:orig_category":"Electrodom\u00c9sticos (al Por Menor)",
    "sg:phone":"+34 965 70 04 24",
    "sg:postcode":"03160",
    "sg:province":"Alicante",
    "wof:name":"Electro Escobedo,s.l.",
    "wof:placetype":"venue"
},
  "geometry": {"coordinates":[-0.7939031124,38.1084899902],"type":"Point"}
}