{
  "type": "Feature",
  "properties": {
    "iso:country":"ES",
    "sg:address":"Calle de General Vives, 77",
    "sg:city":"Palmas De Gran Canaria",
    "sg:orig_category":"Comit\u00c9s De Organizaci\u00d3n De Exposiciones, Ferias, Salones",
    "sg:phone":"+34 928 22 70 79",
    "sg:postcode":"35007",
    "sg:province":"Las Palmas",
    "sg:website":"www.elipse-eventos.com",
    "wof:name":"Samsara Tours S.l.",
    "wof:placetype":"venue"
},
  "geometry": {"coordinates":[-15.4312944412,28.1397132874],"type":"Point"}
}