{
  "type": "Feature",
  "properties": {
    "iso:country":"ES",
    "sg:address":"Avda Espa\u00d1a, 190",
    "sg:city":"Isla Cristina",
    "sg:orig_category":"Establecimientos De Cura, Prevenci\u00d3n Y Readaptaci\u00d3n",
    "sg:phone":"+34 959 34 36 34",
    "sg:postcode":"21410",
    "sg:province":"Huelva",
    "wof:name":"Ayuntamiento De Isla Cristina",
    "wof:placetype":"venue"
},
  "geometry": {"coordinates":[-7.3190674782,37.1992149353],"type":"Point"}
}