{
  "type": "Feature",
  "properties": {
    "iso:country":"ES",
    "sg:address":"Circunvalacion, 28",
    "sg:city":"Granada",
    "sg:orig_category":"Inmobiliaria (agencias)",
    "sg:phone":"+34 958 12 11 12",
    "sg:postcode":"18007",
    "sg:province":"Granada",
    "sg:website":"www.unicasa.es",
    "wof:name":"Union Intermediacion Financiera S.l.",
    "wof:placetype":"venue"
},
  "geometry": {"coordinates":[-3.5975089073,37.1594314575],"type":"Point"}
}