{
  "type": "Feature",
  "properties": {
    "addr:full":"Erdiko Kalea, 32 Arrasate Guip\u00f9zcoa 20500",
    "addr:housenumber":"32",
    "addr:postcode":"20500",
    "addr:street":"Erdiko Kalea;Guipu\u0300Zcoa",
    "iso:country":"ES",
    "sg:address":"Erdiko Kalea, 32",
    "sg:city":"Arrasate",
    "sg:orig_category":"Confecci\u00d3n (fabricaci\u00d3n, Al Por Mayor)",
    "sg:phone":"+34 943 79 16 12",
    "sg:postcode":"20500",
    "sg:province":"Guip\u00f9zcoa",
    "wof:name":"Raquel Alonso Casado Y Otro C.b.",
    "wof:placetype":"venue"
},
  "geometry": {"coordinates":[-2.4903790951,43.0656852722],"type":"Point"}
}