{
  "type": "Feature",
  "properties": {
    "iso:country":"ES",
    "sg:address":"Carr Conquista, 102",
    "sg:city":"Badalona",
    "sg:orig_category":"Asesor\u00cdas Y Estudios Financieros",
    "sg:phone":"+34 933 84 18 75",
    "sg:postcode":"08912",
    "sg:province":"Barcelona",
    "wof:name":"Viperfinance Sl.",
    "wof:placetype":"venue"
},
  "geometry": {"coordinates":[2.2420148849,41.4469146729],"type":"Point"}
}