{
  "type": "Feature",
  "properties": {
    "iso:country":"ES",
    "sg:address":"Calle de San Eloy, 45",
    "sg:city":"Zaragoza",
    "sg:orig_category":"Empresas De Limpieza",
    "sg:phone":"+34 976 32 69 64",
    "sg:postcode":"50011",
    "sg:province":"Zaragoza",
    "wof:name":"Limpiezas Barcino S.a.",
    "wof:placetype":"venue"
},
  "geometry": {"coordinates":[-0.9271590114,41.6535072327],"type":"Point"}
}