{
  "type": "Feature",
  "properties": {
    "iso:country":"ES",
    "sg:address":"Carrer de Arquitecte Sert, 12",
    "sg:city":"Barcelona",
    "sg:orig_category":"Caf\u00c9s, Bares, Cervecer\u00cdas",
    "sg:phone":"+34 932 25 12 19",
    "sg:postcode":"08005",
    "sg:province":"Barcelona",
    "wof:name":"Caffe Da Giotto S.r.l.",
    "wof:placetype":"venue"
},
  "geometry": {"coordinates":[2.1968269348,41.392829895],"type":"Point"}
}