{
  "type": "Feature",
  "properties": {
    "addr:full":"Pase Prado, 6 Madrid Madrid 28...",
    "addr:housenumber":"6;28 ...",
    "addr:street":"Prado;Madrid",
    "iso:country":"ES",
    "sg:address":"Pase Prado, 6",
    "sg:city":"Madrid",
    "sg:orig_category":"Ense\u00d1anza, Formaci\u00d3n Profesional: Aprendizaje",
    "sg:phone":"+34 912 09 95 00",
    "sg:postcode":"28...",
    "sg:province":"Madrid",
    "sg:website":"www.tesoro.es",
    "wof:name":"Ministerio De Economia Y Hacienda",
    "wof:placetype":"venue"
},
  "geometry": {"coordinates":[-3.7057740688,40.42029953],"type":"Point"}
}