{
  "type": "Feature",
  "properties": {
    "iso:country":"ES",
    "sg:address":"Icaria, 5",
    "sg:city":"Montornes Valles",
    "sg:orig_category":"Fabricaci\u00d3n, Venta, Instalaci\u00d3n De R\u00d3tulos, De R\u00d3tulos Luminosos",
    "sg:phone":"+34 935 72 00 25",
    "sg:postcode":"08170",
    "sg:province":"Barcelona",
    "wof:name":"Torcal Miguel Vicente",
    "wof:placetype":"venue"
},
  "geometry": {"coordinates":[2.2635331154,41.5431938171],"type":"Point"}
}