{
  "type": "Feature",
  "properties": {
    "iso:country":"ES",
    "sg:address":"Calle de Real Para Rioseco, 1",
    "sg:city":"Cuenca De Campos",
    "sg:orig_category":"Ingeniero",
    "sg:phone":"+34 983 74 00 79",
    "sg:postcode":"47650",
    "sg:province":"Valladolid",
    "wof:name":"Asensio De La Cuesta Moises",
    "wof:placetype":"venue"
},
  "geometry": {"coordinates":[-5.0552182198,42.0586967468],"type":"Point"}
}