{
  "type": "Feature",
  "properties": {
    "iso:country":"ES",
    "sg:address":"Calle de Nicolas Albornoz, 23",
    "sg:city":"Cabra",
    "sg:orig_category":"Cervecer\u00cdas",
    "sg:phone":"+34 957 52 23 60",
    "sg:postcode":"14940",
    "sg:province":"C\u00f3rdoba",
    "wof:name":"Aguilera Navarro Juan",
    "wof:placetype":"venue"
},
  "geometry": {"coordinates":[-4.4593791962,37.4908409119],"type":"Point"}
}