{
  "type": "Feature",
  "properties": {
    "iso:country":"ES",
    "sg:address":"Carrer de Espinach, 1",
    "sg:city":"Tarragona",
    "sg:orig_category":"Distribuci\u00d3n De Petr\u00d3leo Y Derivados",
    "sg:phone":"+34 977 21 23 69",
    "sg:postcode":"43004",
    "sg:province":"Tarragona",
    "wof:name":"Cooperativa Produccion Manipuladores Pescados Mariscos",
    "wof:placetype":"venue"
},
  "geometry": {"coordinates":[1.2406079769,41.1102256775],"type":"Point"}
}