{
  "type": "Feature",
  "properties": {
    "iso:country":"ES",
    "sg:address":"Pol Ind La Vaquera, S/n",
    "sg:city":"Hornachuelos",
    "sg:orig_category":"Carnicer\u00cdas, Carnicer\u00cdas",
    "sg:phone":"+34 957 64 12 75",
    "sg:postcode":"14740",
    "sg:province":"C\u00f3rdoba",
    "wof:name":"Carnicaza S L",
    "wof:placetype":"venue"
},
  "geometry": {"coordinates":[-5.2428050041,37.8309288025],"type":"Point"}
}