{
  "type": "Feature",
  "properties": {
    "addr:full":"Calle de Rejadorada, 1 Toro Zamora 49800",
    "addr:housenumber":"1",
    "addr:postcode":"49800",
    "addr:street":"Calle De Rejadorada",
    "iso:country":"ES",
    "sg:address":"Calle de Rejadorada, 1",
    "sg:city":"Toro",
    "sg:orig_category":"Droguer\u00cdas (al Por Menor)",
    "sg:phone":"+34 980 69 21 11",
    "sg:postcode":"49800",
    "sg:province":"Zamora",
    "wof:name":"Vergel Cebrian Isidro",
    "wof:placetype":"venue"
},
  "geometry": {"coordinates":[-5.3910269737,41.5214767456],"type":"Point"}
}