{
  "type": "Feature",
  "properties": {
    "addr:full":"Calle de Daza Valdes, 13 Leganes Madrid 28914",
    "addr:housenumber":"13",
    "addr:postcode":"28914",
    "addr:street":"Calle De Daza Valdes",
    "iso:country":"ES",
    "sg:address":"Calle de Daza Valdes, 13",
    "sg:city":"Leganes",
    "sg:orig_category":"Transportes Por Carretera: Lotes Completos, Mercanc\u00cdas Diversas",
    "sg:phone":"+34 917 95 55 61",
    "sg:postcode":"28914",
    "sg:province":"Madrid",
    "wof:name":"Brioche Pasquier Recondo S.l.",
    "wof:placetype":"venue"
},
  "geometry": {"coordinates":[-3.7439568043,40.3218574524],"type":"Point"}
}