{
  "type": "Feature",
  "properties": {
    "addr:full":"Calle de Barriguelo, 4 Logro\u00f1o La Rioja 26006",
    "addr:housenumber":"4",
    "addr:postcode":"26006",
    "addr:street":"Calle De Barriguelo;Rioja",
    "iso:country":"ES",
    "sg:address":"Calle de Barriguelo, 4",
    "sg:city":"Logro\u00f1o",
    "sg:orig_category":"Ropa De Casa (fabricaci\u00d3n, Al Por Mayor)",
    "sg:phone":"+34 941 25 74 77",
    "sg:postcode":"26006",
    "sg:province":"La Rioja",
    "wof:name":"Textiles Arigai S.l.",
    "wof:placetype":"venue"
},
  "geometry": {"coordinates":[-2.4036989212,42.46043396],"type":"Point"}
}