{
  "type": "Feature",
  "properties": {
    "iso:country":"ES",
    "sg:address":"Calle de Virgen De Gracia, S/n",
    "sg:city":"Mansilla Mulas",
    "sg:orig_category":"Molduras, Junquillos, Listones Y Molduras Perforadas",
    "sg:phone":"+34 987 31 00 26",
    "sg:postcode":"24210",
    "sg:province":"Le\u00f3n",
    "wof:name":"Sociedad Regional De Informatica S.a.",
    "wof:placetype":"venue"
},
  "geometry": {"coordinates":[-5.4153442383,42.4976081848],"type":"Point"}
}