{
  "type": "Feature",
  "properties": {
    "addr:full":"Calle de Doctor Ma\u00d1as Bernabeu, 9 Malaga M\u00e1laga 29006",
    "addr:housenumber":"9",
    "addr:postcode":"29006",
    "addr:street":"Calle De Doctor Man\u0303As Bernabeu;Ma\u0301Laga",
    "iso:country":"ES",
    "sg:address":"Calle de Doctor Ma\u00d1as Bernabeu, 9",
    "sg:city":"Malaga",
    "sg:orig_category":"Centros De Coordinaci\u00d3n",
    "sg:phone":"+34 952 35 70 62",
    "sg:postcode":"29006",
    "sg:province":"M\u00e1laga",
    "wof:name":"Cazorla Merida Maria Jesus",
    "wof:placetype":"venue"
},
  "geometry": {"coordinates":[-4.444299221,36.7105064392],"type":"Point"}
}