{
  "type": "Feature",
  "properties": {
    "iso:country":"ES",
    "sg:address":"Calle de Bolea, 36",
    "sg:city":"Elche Sierra",
    "sg:orig_category":"Distribuci\u00d3n De Petr\u00d3leo Y Derivados",
    "sg:phone":"+34 967 41 08 89",
    "sg:postcode":"02430",
    "sg:province":"Albacete",
    "wof:name":"La Sierra Estacion De Servicio S.l.",
    "wof:placetype":"venue"
},
  "geometry": {"coordinates":[-1.6613692045,38.5615997314],"type":"Point"}
}