{
  "type": "Feature",
  "properties": {
    "iso:country":"ES",
    "sg:address":"Ctra Osuna-el Saucejo, S/n",
    "sg:city":"Osuna",
    "sg:orig_category":"Producci\u00d3n, Venta De Productos De Agricultura Biol\u00d3gica",
    "sg:phone":"+34 955 95 80 57",
    "sg:postcode":"41640",
    "sg:province":"Sevilla",
    "wof:name":"Agropecuaria Bejarano S.l.",
    "wof:placetype":"venue"
},
  "geometry": {"coordinates":[-5.101522,37.230366],"type":"Point"}
}