{
  "type": "Feature",
  "properties": {
    "addr:full":"Plaz Mayor, 6 Riaza Segovia 40500",
    "addr:housenumber":"6",
    "addr:postcode":"40500",
    "addr:street":"Plaz Mayor",
    "iso:country":"ES",
    "sg:address":"Plaz Mayor, 6",
    "sg:city":"Riaza",
    "sg:orig_category":"Barbacoas Y Accesorios",
    "sg:phone":"+34 921 55 02 74",
    "sg:postcode":"40500",
    "sg:province":"Segovia",
    "wof:name":"Hernanz De Pablo Eugenio",
    "wof:placetype":"venue"
},
  "geometry": {"coordinates":[-3.4820048809,41.2783088684],"type":"Point"}
}