{
  "type": "Feature",
  "properties": {
    "iso:country":"ES",
    "sg:address":"Av Catalunya, 6",
    "sg:city":"Cervera",
    "sg:orig_category":"Quincaller\u00cda (al Por Menor)",
    "sg:phone":"+34 973 53 05 22",
    "sg:postcode":"25200",
    "sg:province":"Lleida",
    "wof:name":"Maja Anglarill Jaime",
    "wof:placetype":"venue"
},
  "geometry": {"coordinates":[1.2748149633,41.6723213196],"type":"Point"}
}