{
  "type": "Feature",
  "properties": {
    "addr:full":"Calle de Riego De Agua, 23 Coru\u00d1a La Coru\u00f1a 15001",
    "addr:housenumber":"23",
    "addr:postcode":"15001",
    "addr:street":"Calle De Riego De Agua;La Corun\u0303A",
    "iso:country":"ES",
    "sg:address":"Calle de Riego De Agua, 23",
    "sg:city":"Coru\u00d1a",
    "sg:orig_category":"Fabricaci\u00d3n De Telas Y Sedas",
    "sg:phone":"+34 981 22 91 14",
    "sg:postcode":"15001",
    "sg:province":"La Coru\u00f1a",
    "wof:name":"Primera Coru\u00f1esa S. A.",
    "wof:placetype":"venue"
},
  "geometry": {"coordinates":[-8.3978767395,43.3704414368],"type":"Point"}
}