{
  "type": "Feature",
  "properties": {
    "addr:full":"Cra. Ribes (sector Can Baldic), S/n Llerona Barcelona 08520",
    "addr:housenumber":"s",
    "addr:postcode":"08520",
    "addr:street":"/ N",
    "iso:country":"ES",
    "sg:address":"Cra. Ribes (sector Can Baldic), S/n",
    "sg:city":"Llerona",
    "sg:orig_category":"Agentes, Concesionarios Y Sucursales De Veh\u00cdculos",
    "sg:phone":"+34 938 49 55 98",
    "sg:postcode":"08520",
    "sg:province":"Barcelona",
    "wof:name":"Ankhar Motor S.l.",
    "wof:placetype":"venue"
},
  "geometry": {"coordinates":[2.2982094288,41.6478767395],"type":"Point"}
}