{
  "type": "Feature",
  "properties": {
    "iso:country":"ES",
    "sg:address":"Avda Daroca, 58",
    "sg:city":"Madrid",
    "sg:orig_category":"M\u00c1rmoles, Granitos Y Piedras Naturales",
    "sg:phone":"+34 914 04 48 65",
    "sg:postcode":"28017",
    "sg:province":"Madrid",
    "wof:name":"Gabriel Ramalleira Rafael",
    "wof:placetype":"venue"
},
  "geometry": {"coordinates":[-3.6535871029,40.429397583],"type":"Point"}
}