{
  "type": "Feature",
  "properties": {
    "addr:full":"Carrer de Fortuna, 7 Valls Tarragona 43800",
    "addr:housenumber":"7",
    "addr:postcode":"43800",
    "addr:street":"Carrer De Fortuna",
    "iso:country":"ES",
    "sg:address":"Carrer de Fortuna, 7",
    "sg:city":"Valls",
    "sg:orig_category":"Peluquer\u00cdas, Peluquer\u00cda Mixta",
    "sg:phone":"+34 977 60 67 43",
    "sg:postcode":"43800",
    "sg:province":"Tarragona",
    "wof:name":"Peris Goma Mireia",
    "wof:placetype":"venue"
},
  "geometry": {"coordinates":[1.2509750128,41.2872543335],"type":"Point"}
}