{
  "type": "Feature",
  "properties": {
    "iso:country":"ES",
    "sg:address":"Carrer de Paris, 38",
    "sg:city":"Barcelona",
    "sg:orig_category":"Inmobiliaria (agencias)",
    "sg:phone":"+34 934 30 35 37",
    "sg:postcode":"08029",
    "sg:province":"Barcelona",
    "wof:name":"Esta\u00f1ol Carrera Josep Anton",
    "wof:placetype":"venue"
},
  "geometry": {"coordinates":[2.1430039406,41.3858299255],"type":"Point"}
}