{
  "type": "Feature",
  "properties": {
    "iso:country":"ES",
    "sg:address":"Ctra Manlleu, 53",
    "sg:city":"Vic",
    "sg:orig_category":"Distribuci\u00d3n De Petr\u00d3leo Y Derivados",
    "sg:phone":"+34 938 86 11 62",
    "sg:postcode":"08500",
    "sg:province":"Barcelona",
    "wof:name":"Peixos Povedano S.l.",
    "wof:placetype":"venue"
},
  "geometry": {"coordinates":[2.2576379776,41.9441184998],"type":"Point"}
}