{
  "type": "Feature",
  "properties": {
    "iso:country":"ES",
    "sg:address":"Calle de Infanta Mercedes, 1",
    "sg:city":"Madrid",
    "sg:orig_category":"Frutas Y Legumbres Secas (al Por Mayor)",
    "sg:phone":"+34 915 72 27 51",
    "sg:postcode":"28020",
    "sg:province":"Madrid",
    "wof:name":"Fritos El Cisne S.l",
    "wof:placetype":"venue"
},
  "geometry": {"coordinates":[-3.699434042,40.4527053833],"type":"Point"}
}