{
  "type": "Feature",
  "properties": {
    "iso:country":"ES",
    "sg:address":"Calle de Carrachel, 2",
    "sg:city":"Algete",
    "sg:orig_category":"Molduras, Junquillos, Listones Y Molduras Perforadas",
    "sg:phone":"+34 916 28 30 54",
    "sg:postcode":"28110",
    "sg:province":"Madrid",
    "wof:name":"Telemensaje S.a.",
    "wof:placetype":"venue"
},
  "geometry": {"coordinates":[-3.5029370785,40.5980453491],"type":"Point"}
}