{
  "type": "Feature",
  "properties": {
    "iso:country":"ES",
    "sg:address":"Ctra. Cebreros, 1",
    "sg:city":"El Hoyo Pinares",
    "sg:orig_category":"Distribuci\u00d3n De Petr\u00d3leo Y Derivados",
    "sg:phone":"+34 918 63 91 47",
    "sg:postcode":"05250",
    "sg:province":"\u00c1vila",
    "wof:name":"Gestion De Servicios El Hoyo De Pinares S.l.",
    "wof:placetype":"venue"
},
  "geometry": {"coordinates":[-4.4256539345,40.4993934631],"type":"Point"}
}