{
  "type": "Feature",
  "properties": {
    "addr:full":"Calle de Juan Carlos I, 3 Pe\u00e7arroya-pueblonuevo C\u00f3rdoba 14200",
    "addr:housenumber":"3",
    "addr:postcode":"14200",
    "addr:street":"Calle De Juan Carlos I;Co\u0301Rdoba",
    "iso:country":"ES",
    "sg:address":"Calle de Juan Carlos I, 3",
    "sg:city":"Pe\u00e7arroya-pueblonuevo",
    "sg:orig_category":"Hielo Artificial (fabricaci\u00d3n, Distribuci\u00d3n)",
    "sg:phone":"+34 957 56 07 44",
    "sg:postcode":"14200",
    "sg:province":"C\u00f3rdoba",
    "wof:name":"Aumente Lavela Emilio",
    "wof:placetype":"venue"
},
  "geometry": {"coordinates":[-5.2651691437,38.2982635498],"type":"Point"}
}