{
  "type": "Feature",
  "properties": {
    "addr:full":"Calle de Europa, 12 Residencial Ontigola Toledo 45340",
    "addr:housenumber":"12",
    "addr:postcode":"45340",
    "addr:street":"Calle De Europa",
    "iso:country":"ES",
    "sg:address":"Calle de Europa, 12",
    "sg:city":"Residencial Ontigola",
    "sg:orig_category":"Carnicer\u00cdas, Carnicer\u00cdas",
    "sg:phone":"+34 925 14 21 20",
    "sg:postcode":"45340",
    "sg:province":"Toledo",
    "wof:name":"Burgos Garcia Maria Carolina",
    "wof:placetype":"venue"
},
  "geometry": {"coordinates":[-3.5730190277,40.0126495361],"type":"Point"}
}