{
  "type": "Feature",
  "properties": {
    "iso:country":"ES",
    "sg:address":"Calle de Amargura, 7",
    "sg:city":"Hiniesta",
    "sg:orig_category":"Empresas De Carpinter\u00cda Met\u00c1lica",
    "sg:phone":"+34 980 55 20 48",
    "sg:postcode":"49192",
    "sg:province":"Zamora",
    "wof:name":"Alvarez Carbajo Eloy",
    "wof:placetype":"venue"
},
  "geometry": {"coordinates":[-5.799967289,41.5513000488],"type":"Point"}
}