{
  "type": "Feature",
  "properties": {
    "addr:full":"Carr Trinitat, 21 Igualada Barcelona 08700",
    "addr:housenumber":"21",
    "addr:postcode":"08700",
    "addr:street":"Carr Trinitat",
    "iso:country":"ES",
    "sg:address":"Carr Trinitat, 21",
    "sg:city":"Igualada",
    "sg:orig_category":"Peluqueros: De Se\u00d1oras",
    "sg:phone":"+34 938 03 59 62",
    "sg:postcode":"08700",
    "sg:province":"Barcelona",
    "wof:name":"Massansalvado Brunet Elisabet",
    "wof:placetype":"venue"
},
  "geometry": {"coordinates":[1.6220630407,41.579082489],"type":"Point"}
}