{
  "type": "Feature",
  "properties": {
    "addr:full":"Carrer de Enten\u00c7a, 231 Barcelona Barcelona 08029",
    "addr:housenumber":"231",
    "addr:postcode":"08029",
    "addr:street":"Carrer De Entenc\u0327A",
    "iso:country":"ES",
    "sg:address":"Carrer de Enten\u00c7a, 231",
    "sg:city":"Barcelona",
    "sg:orig_category":"Inform\u00c1tica Equipo Y Programas (al Por Mayor)",
    "sg:phone":"+34 934 19 00 44",
    "sg:postcode":"08029",
    "sg:province":"Barcelona",
    "sg:website":"www.wavetek.net",
    "wof:name":"Mpg Abogados Barcelona Scp",
    "wof:placetype":"venue"
},
  "geometry": {"coordinates":[2.1409399509,41.3869171143],"type":"Point"}
}