{
  "type": "Feature",
  "properties": {
    "iso:country":"ES",
    "sg:address":"Av La Paz, 5",
    "sg:city":"Onil",
    "sg:orig_category":"Poller\u00cda Y Caza (al Por Menor)",
    "sg:phone":"+34 966 55 71 09",
    "sg:postcode":"03430",
    "sg:province":"Alicante",
    "wof:name":"Polleria Churreria Avenida C.b.",
    "wof:placetype":"venue"
},
  "geometry": {"coordinates":[-0.6773340106,38.6277160645],"type":"Point"}
}