{
  "type": "Feature",
  "properties": {
    "addr:full":"Calle de Doctor Melian, 60 Ejido Las Palmas 35200",
    "addr:housenumber":"60 ejido",
    "addr:postcode":"35200",
    "addr:street":"Calle De Doctor Melian;Las Palmas",
    "iso:country":"ES",
    "sg:address":"Calle de Doctor Melian, 60",
    "sg:city":"Ejido",
    "sg:orig_category":"Sociedades, Compa\u00d1\u00cdas Aseguradoras",
    "sg:phone":"+34 928 69 79 31",
    "sg:postcode":"35200",
    "sg:province":"Las Palmas",
    "sg:website":"www.mapfre.com",
    "wof:name":"Mapfre Guanarteme Compa\u00d1ia De Seguros Y Reaseguros De Canarias S.a.",
    "wof:placetype":"venue"
},
  "geometry": {"coordinates":[-15.4300060272,28.1248226166],"type":"Point"}
}