{
  "type": "Feature",
  "properties": {
    "iso:country":"ES",
    "sg:address":"Calle de Rocio (del), 7",
    "sg:city":"Arganda",
    "sg:orig_category":"Material Hidr\u00c1ulico",
    "sg:phone":"+34 918 75 70 52",
    "sg:postcode":"28500",
    "sg:province":"Madrid",
    "wof:name":"C.e.h.y.s. S.a.",
    "wof:placetype":"venue"
},
  "geometry": {"coordinates":[-3.4836239815,40.3096008301],"type":"Point"}
}