{
  "type": "Feature",
  "properties": {
    "addr:full":"Ctra Loeches (de), 3 Arganda Madrid 28500",
    "addr:housenumber":"3",
    "addr:postcode":"28500",
    "addr:street":"Ctra Loeches De",
    "iso:country":"ES",
    "sg:address":"Ctra Loeches (de), 3",
    "sg:city":"Arganda",
    "sg:orig_category":"Poller\u00cda Y Caza (al Por Menor)",
    "sg:phone":"+34 918 70 10 11",
    "sg:postcode":"28500",
    "sg:province":"Madrid",
    "wof:name":"Garcia-patron Galisteo Javier",
    "wof:placetype":"venue"
},
  "geometry": {"coordinates":[-3.4488940239,40.3117904663],"type":"Point"}
}