{
  "type": "Feature",
  "properties": {
    "iso:country":"ES",
    "sg:address":"Rond Outeiro, 274",
    "sg:city":"Coru\u00d1a",
    "sg:orig_category":"Molduras, Junquillos, Listones Y Molduras Perforadas",
    "sg:phone":"+34 981 26 02 22",
    "sg:postcode":"15010",
    "sg:province":"La Coru\u00f1a",
    "wof:name":"Bouzon Aran Jesus",
    "wof:placetype":"venue"
},
  "geometry": {"coordinates":[-8.4383602142,43.3564109802],"type":"Point"}
}