{
  "type": "Feature",
  "properties": {
    "addr:full":"Plaz Preciosa, 1 San Miguel Murcia 30008",
    "addr:housenumber":"1",
    "addr:postcode":"30008",
    "addr:street":"Plaz Preciosa",
    "iso:country":"ES",
    "sg:address":"Plaz Preciosa, 1",
    "sg:city":"San Miguel",
    "sg:orig_category":"Ortopedia General",
    "sg:phone":"+34 968 24 45 41",
    "sg:postcode":"30008",
    "sg:province":"Murcia",
    "wof:name":"Hernandez Moreno Jose Antonio",
    "wof:placetype":"venue"
},
  "geometry": {"coordinates":[-1.1311199665,37.989944458],"type":"Point"}
}