{
  "type": "Feature",
  "properties": {
    "iso:country":"ES",
    "sg:address":"Las Rosas, 18",
    "sg:city":"El Paso",
    "sg:orig_category":"Bazares, Art\u00cdculos De Limpieza Y De Cocina (al Por Menor)",
    "sg:phone":"+34 922 48 62 70",
    "sg:postcode":"38750",
    "sg:province":"Santa Cruz De Tenerife",
    "wof:name":"Gomez Muller S.l.",
    "wof:placetype":"venue"
},
  "geometry": {"coordinates":[-17.8813228607,28.6505889893],"type":"Point"}
}