{
  "type": "Feature",
  "properties": {
    "addr:full":"Avda Carlos Iii (de), 15 Cordoba C\u00f3rdoba 14014",
    "addr:housenumber":"15",
    "addr:postcode":"14014",
    "addr:street":"Avda Carlos Iii De;Co\u0301Rdoba",
    "iso:country":"ES",
    "sg:address":"Avda Carlos Iii (de), 15",
    "sg:city":"Cordoba",
    "sg:orig_category":"Art\u00cdculos De Aluminio",
    "sg:phone":"+34 957 26 19 01",
    "sg:postcode":"14014",
    "sg:province":"C\u00f3rdoba",
    "wof:name":"Cristaleria Levante S.l.",
    "wof:placetype":"venue"
},
  "geometry": {"coordinates":[-4.7618589401,37.8973312378],"type":"Point"}
}