{
  "type": "Feature",
  "properties": {
    "iso:country":"ES",
    "sg:address":"Avda Estacion, 9",
    "sg:city":"Torre-pacheco",
    "sg:classifiers":[
        {
            "category":"Taxi",
            "type":"Transportation"
        }
    ],
    "sg:phone":"+34 968 57 76 33",
    "sg:postcode":"30700",
    "sg:province":"Murcia",
    "wof:name":"Asociacion Radio Taxi Campo Cartagena",
    "wof:placetype":"venue"
},
  "geometry": {"coordinates":[-0.9549509883,37.7441711426],"type":"Point"}
}