{
  "type": "Feature",
  "properties": {
    "iso:country":"ES",
    "sg:address":"Carrer de Rubio I Ors, 141",
    "sg:city":"Cornella Llobregat",
    "sg:orig_category":"Empresarios",
    "sg:phone":"+34 933 77 36 93",
    "sg:postcode":"08940",
    "sg:province":"Barcelona",
    "wof:name":"Indelca Ingenieria De Proyectos S.l.",
    "wof:placetype":"venue"
},
  "geometry": {"coordinates":[2.0715970993,41.3527107239],"type":"Point"}
}