{
  "type": "Feature",
  "properties": {
    "iso:country":"ES",
    "sg:address":"Calle de Manuel Fernandez Y Gonzalez, 15",
    "sg:city":"Madrid",
    "sg:orig_category":"Molduras, Junquillos, Listones Y Molduras Perforadas",
    "sg:phone":"+34 914 29 62 64",
    "sg:postcode":"28014",
    "sg:province":"Madrid",
    "wof:name":"Del Tronco Alvarez Manuel",
    "wof:placetype":"venue"
},
  "geometry": {"coordinates":[-3.6992208958,40.4153137207],"type":"Point"}
}