{
  "type": "Feature",
  "properties": {
    "addr:full":"Carrer de Gran De Gracia, 67 Barcelona Barcelona 08012",
    "addr:housenumber":"67",
    "addr:postcode":"08012",
    "addr:street":"Carrer De Gran De Gracia",
    "iso:country":"ES",
    "sg:address":"Carrer de Gran De Gracia, 67",
    "sg:city":"Barcelona",
    "sg:orig_category":"Abogados",
    "sg:phone":"+34 932 38 66 11",
    "sg:postcode":"08012",
    "sg:province":"Barcelona",
    "wof:name":"Bufete Garcia Fajardo S.l.",
    "wof:placetype":"venue"
},
  "geometry": {"coordinates":[2.1552770138,41.3998756409],"type":"Point"}
}