{
  "type": "Feature",
  "properties": {
    "addr:full":"Cra San Jeronimo, 18 Madrid Madrid 28014",
    "addr:housenumber":"18",
    "addr:postcode":"madrid;28014",
    "addr:street":"Jeronimo",
    "iso:country":"ES",
    "sg:address":"Cra San Jeronimo, 18",
    "sg:city":"Madrid",
    "sg:orig_category":"Organismos De Reclutamiento",
    "sg:phone":"+34 915 22 61 01",
    "sg:postcode":"28014",
    "sg:province":"Madrid",
    "wof:name":"Zorita Jimenez Mercedes",
    "wof:placetype":"venue"
},
  "geometry": {"coordinates":[-3.7009136677,40.4166107178],"type":"Point"}
}