{
  "type": "Feature",
  "properties": {
    "addr:full":"Plaz San Gonzalo, S/n Sevilla Sevilla 41010",
    "addr:housenumber":"s / n",
    "addr:postcode":"41010",
    "addr:street":"Plaz San Gonzalo",
    "iso:country":"ES",
    "sg:address":"Plaz San Gonzalo, S/n",
    "sg:city":"Sevilla",
    "sg:orig_category":"Pescader\u00cdas (al Por Menor)",
    "sg:phone":"+34 954 34 45 34",
    "sg:postcode":"41010",
    "sg:province":"Sevilla",
    "wof:name":"Dominguez Morillo Juan Rafael",
    "wof:placetype":"venue"
},
  "geometry": {"coordinates":[-6.0104990005,37.3801956177],"type":"Point"}
}