{
  "type": "Feature",
  "properties": {
    "addr:full":"Calle de Vista Alegre, 5 Barakaldo Vizcaya 48903",
    "addr:housenumber":"5",
    "addr:postcode":"48903",
    "addr:street":"Calle De Vista Alegre",
    "iso:country":"ES",
    "sg:address":"Calle de Vista Alegre, 5",
    "sg:city":"Barakaldo",
    "sg:orig_category":"Molduras, Junquillos, Listones Y Molduras Perforadas",
    "sg:phone":"+34 944 90 05 54",
    "sg:postcode":"48903",
    "sg:province":"Vizcaya",
    "wof:name":"Maria Angeles Robles Gallego",
    "wof:placetype":"venue"
},
  "geometry": {"coordinates":[-2.9831769466,43.2807312012],"type":"Point"}
}