{
  "type": "Feature",
  "properties": {
    "addr:full":"Calle de Antonio Rodriguez Mo\u00d1ino, 35 Almendralejo Badajoz 06200",
    "addr:housenumber":"35",
    "addr:postcode":"06200",
    "addr:street":"Calle De Antonio;Mon\u0303Ino",
    "iso:country":"ES",
    "sg:address":"Calle de Antonio Rodriguez Mo\u00d1ino, 35",
    "sg:city":"Almendralejo",
    "sg:orig_category":"Transporte En General",
    "sg:phone":"+34 924 66 70 74",
    "sg:postcode":"06200",
    "sg:province":"Badajoz",
    "wof:name":"Mercado San Josse S.c.l.",
    "wof:placetype":"venue"
},
  "geometry": {"coordinates":[-6.3992986679,38.6796150208],"type":"Point"}
}