{
  "type": "Feature",
  "properties": {
    "iso:country":"ES",
    "sg:address":"Avda Jose Mesa Y Lopez, 50",
    "sg:city":"Palmas De Gran Canaria",
    "sg:orig_category":"Bisuter\u00cda, Joyer\u00cda, Relojer\u00cda (al Por Menor)",
    "sg:phone":"+34 928 22 79 68",
    "sg:postcode":"35007",
    "sg:province":"Las Palmas",
    "wof:name":"Ferreiro Garcia Jesus",
    "wof:placetype":"venue"
},
  "geometry": {"coordinates":[-15.4346532822,28.1347122192],"type":"Point"}
}