{
  "type": "Feature",
  "properties": {
    "iso:country":"ES",
    "sg:address":"Avda Betanzos, 10",
    "sg:city":"Madrid",
    "sg:orig_category":"Fisioterapia",
    "sg:phone":"+34 917 31 98 75",
    "sg:postcode":"28029",
    "sg:province":"Madrid",
    "sg:website":"www.sanaval.com",
    "wof:name":"Centro De Fisioterapia Sanaval S.l.",
    "wof:placetype":"venue"
},
  "geometry": {"coordinates":[-3.7115519047,40.4734725952],"type":"Point"}
}