{
  "type": "Feature",
  "properties": {
    "addr:full":"Rond Outeiro, 1 Coru\u00d1a La Coru\u00f1a 15006",
    "addr:housenumber":"1",
    "addr:postcode":"15006",
    "addr:street":"Outeiro;La Corun\u0303A",
    "iso:country":"ES",
    "sg:address":"Rond Outeiro, 1",
    "sg:city":"Coru\u00d1a",
    "sg:orig_category":"Inversiones",
    "sg:phone":"+34 981 29 79 01",
    "sg:postcode":"15006",
    "sg:province":"La Coru\u00f1a",
    "wof:name":"Promexin S.l.",
    "wof:placetype":"venue"
},
  "geometry": {"coordinates":[-8.3881797791,43.3491401672],"type":"Point"}
}