{
  "type": "Feature",
  "properties": {
    "iso:country":"ES",
    "sg:address":"El Conde, 8",
    "sg:city":"S. Esteban Valdueza",
    "sg:orig_category":"Alquiler De Gr\u00daas",
    "sg:phone":"+34 987 45 28 09",
    "sg:postcode":"24415",
    "sg:province":"Le\u00f3n",
    "wof:name":"Talleres Y Gruas Luna S. A.",
    "wof:placetype":"venue"
},
  "geometry": {"coordinates":[-6.5887460709,42.5373535156],"type":"Point"}
}