{
  "type": "Feature",
  "properties": {
    "addr:full":"Calle de Cavallers, 42 Alfara Patriarca Valencia 46115",
    "addr:housenumber":"42",
    "addr:postcode":"46115",
    "addr:street":"Calle De Cavallers",
    "iso:country":"ES",
    "sg:address":"Calle de Cavallers, 42",
    "sg:city":"Alfara Patriarca",
    "sg:orig_category":"Quincaller\u00cda (fabricaci\u00d3n)",
    "sg:phone":"+34 961 39 01 99",
    "sg:postcode":"46115",
    "sg:province":"Valencia",
    "sg:website":"www.hopama.com",
    "wof:name":"Hopama S. A.",
    "wof:placetype":"venue"
},
  "geometry": {"coordinates":[-0.3837338984,39.5467948914],"type":"Point"}
}