{
  "type": "Feature",
  "properties": {
    "addr:full":"Calle de Tierruca, 7 Madrid Madrid 28018",
    "addr:housenumber":"7",
    "addr:postcode":"madrid;28018",
    "addr:street":"Calle De Tierruca",
    "iso:country":"ES",
    "sg:address":"Calle de Tierruca, 7",
    "sg:city":"Madrid",
    "sg:orig_category":"Filtros Y Elementos Filtradores",
    "sg:phone":"+34 913 03 46 04",
    "sg:postcode":"28018",
    "sg:province":"Madrid",
    "sg:website":"www.mcleodrussel.com",
    "wof:name":"Vokes Air S.l.",
    "wof:placetype":"venue"
},
  "geometry": {"coordinates":[-3.649132967,40.3849372864],"type":"Point"}
}