{
  "type": "Feature",
  "properties": {
    "iso:country":"ES",
    "sg:address":"Calle de San Miguel, 3",
    "sg:city":"Najera",
    "sg:orig_category":"Quincaller\u00cda (al Por Mayor)",
    "sg:phone":"+34 941 36 33 81",
    "sg:postcode":"26300",
    "sg:province":"La Rioja",
    "wof:name":"Ferreteria Reinex S.l.",
    "wof:placetype":"venue"
},
  "geometry": {"coordinates":[-2.7348051071,42.4179573059],"type":"Point"}
}