{
  "type": "Feature",
  "properties": {
    "iso:country":"ES",
    "sg:address":"Calle de Bodegas, S/n",
    "sg:city":"Perdigon",
    "sg:orig_category":"Restaurantes",
    "sg:phone":"+34 980 57 62 17",
    "sg:postcode":"49720",
    "sg:province":"Zamora",
    "wof:name":"Torre Andres Jose Alberto De La",
    "wof:placetype":"venue"
},
  "geometry": {"coordinates":[-5.7549118996,41.4138031006],"type":"Point"}
}