{
  "type": "Feature",
  "properties": {
    "addr:full":"Calle de Guadiaro, 551 Ronda M\u00e1laga 29400",
    "addr:housenumber":"551",
    "addr:postcode":"29400",
    "addr:street":"Calle De Guadiaro;Ronda Ma\u0301Laga",
    "iso:country":"ES",
    "sg:address":"Calle de Guadiaro, 551",
    "sg:city":"Ronda",
    "sg:orig_category":"Alumbrados",
    "sg:phone":"+34 952 87 63 02",
    "sg:postcode":"29400",
    "sg:province":"M\u00e1laga",
    "wof:name":"Iluminaciones Flores E Hijos S.l.",
    "wof:placetype":"venue"
},
  "geometry": {"coordinates":[-5.1630091667,36.7521400452],"type":"Point"}
}