{
  "type": "Feature",
  "properties": {
    "iso:country":"ES",
    "sg:address":"Calle de Carretera De Gerindote, 2",
    "sg:city":"Torrijos",
    "sg:orig_category":"Inform\u00c1tica (estudios, Servicios, Asesor\u00cda, Formaci\u00d3n)",
    "sg:phone":"+34 925 77 50 22",
    "sg:postcode":"45500",
    "sg:province":"Toledo",
    "wof:name":"Intermatica Torrijos S.l.",
    "wof:placetype":"venue"
},
  "geometry": {"coordinates":[-4.2832546234,39.9792137146],"type":"Point"}
}