{
  "type": "Feature",
  "properties": {
    "addr:full":"Ayuntamiento, 11 Pedreguer Alicante 03750",
    "addr:housenumber":"11",
    "addr:postcode":"03750",
    "addr:street":"Ayuntamiento",
    "iso:country":"ES",
    "sg:address":"Ayuntamiento, 11",
    "sg:city":"Pedreguer",
    "sg:orig_category":"Estancos",
    "sg:phone":"+34 965 76 13 18",
    "sg:postcode":"03750",
    "sg:province":"Alicante",
    "wof:name":"Perez Fornes Rosa",
    "wof:placetype":"venue"
},
  "geometry": {"coordinates":[0.0341800004,38.7926559448],"type":"Point"}
}