{
  "type": "Feature",
  "properties": {
    "iso:country":"ES",
    "sg:address":"Plaza Del Fontan, 15",
    "sg:city":"Tineo",
    "sg:orig_category":"Panader\u00cdas, Panader\u00cdas",
    "sg:phone":"+34 985 80 00 74",
    "sg:postcode":"33870",
    "sg:province":"Asturias",
    "wof:name":"Anton Fernandez Cesar",
    "wof:placetype":"venue"
},
  "geometry": {"coordinates":[-6.4609999657,43.3495903015],"type":"Point"}
}