{
  "type": "Feature",
  "properties": {
    "iso:country":"ES",
    "sg:address":"Avda Aeropuerto (del), 5",
    "sg:city":"Cordoba",
    "sg:orig_category":"Frutas, Legumbres Frescas Y Tempranas (al Por Menor)",
    "sg:phone":"+34 957 23 20 54",
    "sg:postcode":"14004",
    "sg:province":"C\u00f3rdoba",
    "wof:name":"Valverde Montero Jose",
    "wof:placetype":"venue"
},
  "geometry": {"coordinates":[-4.7894282341,37.8784408569],"type":"Point"}
}