{
  "type": "Feature",
  "properties": {
    "iso:country":"ES",
    "sg:address":"Calle de Manuel Gonzalez Martin, 30",
    "sg:city":"Palmas De Gran Canaria",
    "sg:orig_category":"Loter\u00cda Y T\u00d3mbola",
    "sg:phone":"+34 928 24 16 42",
    "sg:postcode":"35005",
    "sg:province":"Las Palmas",
    "wof:name":"Nespereira Vidal Sara",
    "wof:placetype":"venue"
},
  "geometry": {"coordinates":[-15.4319791794,28.1293792725],"type":"Point"}
}