{
  "type": "Feature",
  "properties": {
    "iso:country":"ES",
    "sg:address":"Calle de Inocencio Fernandez, 26",
    "sg:city":"Madrid",
    "sg:orig_category":"Cine (producci\u00d3n, Realizaci\u00d3n)",
    "sg:phone":"+34 913 73 43 55",
    "sg:postcode":"28035",
    "sg:province":"Madrid",
    "wof:name":"Ara Producciones Cinematograficas S.l.",
    "wof:placetype":"venue"
},
  "geometry": {"coordinates":[-3.7313165665,40.4756889343],"type":"Point"}
}