{
  "type": "Feature",
  "properties": {
    "iso:country":"ES",
    "sg:address":"Avda Madariaga, 43",
    "sg:city":"Bilbao",
    "sg:orig_category":"Ropa Para Se\u00d1oras Y Caballeros (al Por Menor)",
    "sg:phone":"+34 944 47 31 37",
    "sg:postcode":"48014",
    "sg:province":"Vizcaya",
    "wof:name":"Sainz De La Maza Quintano Juan Ignacio",
    "wof:placetype":"venue"
},
  "geometry": {"coordinates":[-2.9504959583,43.2708435059],"type":"Point"}
}