{
  "type": "Feature",
  "properties": {
    "iso:country":"ES",
    "sg:address":"Calle de Hogar 68, S/n",
    "sg:city":"Alcorcon",
    "sg:orig_category":"Venta, Instalaci\u00d3n De Calefacci\u00d3n",
    "sg:phone":"+34 916 10 50 20",
    "sg:postcode":"28921",
    "sg:province":"Madrid",
    "wof:name":"Europea Del Gas S.a.",
    "wof:placetype":"venue"
},
  "geometry": {"coordinates":[-3.8257040977,40.3514099121],"type":"Point"}
}