{
  "type": "Feature",
  "properties": {
    "addr:full":"Plg Ind Base Dos Mil, S/n Lorqui Murcia 30564",
    "addr:housenumber":"s",
    "addr:postcode":"30564",
    "addr:street":"/ N",
    "iso:country":"ES",
    "sg:address":"Plg Ind Base Dos Mil, S/n",
    "sg:city":"Lorqui",
    "sg:orig_category":"Servicios Gsm",
    "sg:phone":"+34 968 69 45 25",
    "sg:postcode":"30564",
    "sg:province":"Murcia",
    "sg:website":"www.basetel2000.com",
    "wof:name":"Basetel 2000 S.l.",
    "wof:placetype":"venue"
},
  "geometry": {"coordinates":[-1.2517440319,38.0802001953],"type":"Point"}
}