{
  "type": "Feature",
  "properties": {
    "addr:full":"Carrer de Costa De Carbonell, 55 Lloret Mar Girona 17310",
    "addr:housenumber":"55",
    "addr:postcode":"17310",
    "addr:street":"Carrer De Costa De Carbonell",
    "iso:country":"ES",
    "sg:address":"Carrer de Costa De Carbonell, 55",
    "sg:city":"Lloret Mar",
    "sg:orig_category":"Inmobiliaria (agencias)",
    "sg:phone":"+34 972 36 02 58",
    "sg:postcode":"17310",
    "sg:province":"Girona",
    "wof:name":"Casa Nostra Lloret S.l.u.",
    "wof:placetype":"venue"
},
  "geometry": {"coordinates":[2.846834898,41.6981697083],"type":"Point"}
}