{
  "type": "Feature",
  "properties": {
    "addr:full":"Calle de Carrera, 7 Luque C\u00f3rdoba 14880",
    "addr:postcode":"14880",
    "addr:street":"Calle De Carrera 7;Co\u0301Rdoba",
    "iso:country":"ES",
    "sg:address":"Calle de Carrera, 7",
    "sg:city":"Luque",
    "sg:orig_category":"Cajas De Ahorro",
    "sg:phone":"+34 957 66 72 99",
    "sg:postcode":"14880",
    "sg:province":"C\u00f3rdoba",
    "sg:website":"www.cajasur.es",
    "wof:name":"Caja De Ahorros Y Monte De Piedad De Cordoba",
    "wof:placetype":"venue"
},
  "geometry": {"coordinates":[-4.2780838013,37.5589561462],"type":"Point"}
}