{
  "type": "Feature",
  "properties": {
    "addr:full":"Calle de Saavedra Fajardo, S/n Santa Eulalia Murcia 30001",
    "addr:housenumber":"s / n",
    "addr:postcode":"30001",
    "addr:street":"Calle De Saavedra Fajardo",
    "iso:country":"ES",
    "sg:address":"Calle de Saavedra Fajardo, S/n",
    "sg:city":"Santa Eulalia",
    "sg:orig_category":"Pescader\u00cdas (al Por Menor)",
    "sg:phone":"+34 968 20 21 66",
    "sg:postcode":"30001",
    "sg:province":"Murcia",
    "wof:name":"Blaya Hidalgo Mariano",
    "wof:placetype":"venue"
},
  "geometry": {"coordinates":[-1.1268559694,37.9856185913],"type":"Point"}
}