{
  "type": "Feature",
  "properties": {
    "addr:full":"Calle de Cortes De Aragon, 61 Zaragoza Zaragoza 50005",
    "addr:housenumber":"61",
    "addr:postcode":"50005",
    "addr:street":"Calle De Cortes De Aragon",
    "iso:country":"ES",
    "sg:address":"Calle de Cortes De Aragon, 61",
    "sg:city":"Zaragoza",
    "sg:orig_category":"Art\u00cdculos De Regalo (al Por Menor)",
    "sg:phone":"+34 976 55 15 81",
    "sg:postcode":"50005",
    "sg:province":"Zaragoza",
    "wof:name":"Abarco Reclamos Publicitarios S.l.",
    "wof:placetype":"venue"
},
  "geometry": {"coordinates":[-0.894955,41.64254],"type":"Point"}
}