{
  "type": "Feature",
  "properties": {
    "iso:country":"ES",
    "sg:address":"Carrer de Sicilia, 382",
    "sg:city":"Barcelona",
    "sg:orig_category":"Fotograf\u00cda Y Cine: Material (reparaci\u00d3n)",
    "sg:phone":"+34 932 07 38 83",
    "sg:postcode":"08025",
    "sg:province":"Barcelona",
    "wof:name":"Fotoservico S.l.",
    "wof:placetype":"venue"
},
  "geometry": {"coordinates":[2.1685409546,41.4055290222],"type":"Point"}
}