{
  "type": "Feature",
  "properties": {
    "iso:country":"ES",
    "sg:address":"Calle de Manuel Iradier, 7",
    "sg:city":"Vitoria-gasteiz",
    "sg:orig_category":"Asistencia Y Consejos",
    "sg:phone":"+34 945 23 22 75",
    "sg:postcode":"01005",
    "sg:province":"\u00c1lava",
    "wof:name":"Bazan Lex Asesoria Laboral S.l.",
    "wof:placetype":"venue"
},
  "geometry": {"coordinates":[-2.6750080585,42.8426551819],"type":"Point"}
}