{
  "type": "Feature",
  "properties": {
    "addr:full":"Calle de Ayala, 91 Madrid Madrid 28006",
    "addr:housenumber":"91",
    "addr:postcode":"madrid;28006",
    "addr:street":"Calle De Ayala",
    "iso:country":"ES",
    "sg:address":"Calle de Ayala, 91",
    "sg:city":"Madrid",
    "sg:orig_category":"Inmobiliaria (agencias)",
    "sg:phone":"+34 913 09 00 49",
    "sg:postcode":"28006",
    "sg:province":"Madrid",
    "wof:name":"Santano Negocios S.l.",
    "wof:placetype":"venue"
},
  "geometry": {"coordinates":[-3.6727330685,40.4272994995],"type":"Point"}
}