{
  "type": "Feature",
  "properties": {
    "iso:country":"ES",
    "sg:address":"Plaz Marques De Aracena, 20",
    "sg:city":"Aracena",
    "sg:orig_category":"Quincaller\u00cda (al Por Menor)",
    "sg:phone":"+34 959 12 84 80",
    "sg:postcode":"21200",
    "sg:province":"Huelva",
    "wof:name":"Ferreteria El Paseo S.l.",
    "wof:placetype":"venue"
},
  "geometry": {"coordinates":[-6.5615310669,37.8940620422],"type":"Point"}
}