{
  "type": "Feature",
  "properties": {
    "addr:full":"Carrer de Ramon I Cajal, 2 Eixample Barcelona 08...",
    "addr:housenumber":"2;08 ...",
    "addr:street":"Carrer De Ramon I Cajal;Barcelona",
    "iso:country":"ES",
    "sg:address":"Carrer de Ramon I Cajal, 2",
    "sg:city":"Eixample",
    "sg:orig_category":"Productos Qu\u00cdmicos (fabricaci\u00d3n, Al Por Mayor)",
    "sg:phone":"+34 934 62 98 00",
    "sg:postcode":"08...",
    "sg:province":"Barcelona",
    "wof:name":"Solvay Pharma S.a.",
    "wof:placetype":"venue"
},
  "geometry": {"coordinates":[1.917994976,41.5951461792],"type":"Point"}
}