{
  "type": "Feature",
  "properties": {
    "addr:full":"Oialume Bidea, 14 Astigarraga Guip\u00f9zcoa 20115",
    "addr:housenumber":"14",
    "addr:postcode":"20115",
    "addr:street":"Oialume Bidea;Guipu\u0300Zcoa",
    "iso:country":"ES",
    "sg:address":"Oialume Bidea, 14",
    "sg:city":"Astigarraga",
    "sg:orig_category":"Materias Pl\u00c1sticas: Productos De Consumo Masivo (fabricaci\u00d3n, Al Por Mayor)",
    "sg:phone":"+34 943 33 11 94",
    "sg:postcode":"20115",
    "sg:province":"Guip\u00f9zcoa",
    "wof:name":"Glaria Belasategui Jorge",
    "wof:placetype":"venue"
},
  "geometry": {"coordinates":[-1.9537400007,43.2747879028],"type":"Point"}
}