{
  "type": "Feature",
  "properties": {
    "iso:country":"ES",
    "sg:address":"Av Jacquard, 29",
    "sg:city":"Terrassa",
    "sg:orig_category":"Fabricaci\u00d3n, Venta De Cuadros, Accesorios Para Enmarcar",
    "sg:phone":"+34 937 85 48 16",
    "sg:postcode":"08222",
    "sg:province":"Barcelona",
    "wof:name":"Rusca Castellet Juan",
    "wof:placetype":"venue"
},
  "geometry": {"coordinates":[2.0196530819,41.563873291],"type":"Point"}
}