{
  "type": "Feature",
  "properties": {
    "iso:country":"ES",
    "sg:address":"Calle de San Sebastian, 75",
    "sg:city":"Alcala Guadaira",
    "sg:orig_category":"Ropa Para Caballeros (al Por Menor)",
    "sg:phone":"+34 955 68 38 91",
    "sg:postcode":"41500",
    "sg:province":"Sevilla",
    "wof:name":"Sanchez Garcia Maria Luisa",
    "wof:placetype":"venue"
},
  "geometry": {"coordinates":[-5.8394789696,37.3397445679],"type":"Point"}
}