{
  "type": "Feature",
  "properties": {
    "iso:country":"ES",
    "sg:address":"Calle de Paloma (de La), 7",
    "sg:city":"Algete",
    "sg:orig_category":"Empresarios",
    "sg:phone":"+34 916 28 30 31",
    "sg:postcode":"28110",
    "sg:province":"Madrid",
    "wof:name":"Construcciones Y Reformas Piedra Angular S.l.",
    "wof:placetype":"venue"
},
  "geometry": {"coordinates":[-3.4980149269,40.596736908],"type":"Point"}
}