{
  "type": "Feature",
  "properties": {
    "addr:full":"Calle de Cardenal Cisneros, 89 Santander Cantabria 39007",
    "addr:housenumber":"89",
    "addr:postcode":"39007",
    "addr:street":"Calle De Cardenal Cisneros",
    "iso:country":"ES",
    "sg:address":"Calle de Cardenal Cisneros, 89",
    "sg:city":"Santander",
    "sg:orig_category":"Supermercados Y Hipermercados",
    "sg:phone":"+34 942 23 69 73",
    "sg:postcode":"39007",
    "sg:province":"Cantabria",
    "wof:name":"Hipermercados Beta S. L.",
    "wof:placetype":"venue"
},
  "geometry": {"coordinates":[-3.8203988075,43.4618682861],"type":"Point"}
}