{
  "type": "Feature",
  "properties": {
    "iso:country":"ES",
    "sg:address":"Calle de Doctor Vallejo, 24",
    "sg:city":"Madrid",
    "sg:orig_category":"Caf\u00c9s, Bares, Cervecer\u00cdas",
    "sg:phone":"+34 914 08 30 46",
    "sg:postcode":"28027",
    "sg:province":"Madrid",
    "wof:name":"Minguez Valiente Miguel Angel",
    "wof:placetype":"venue"
},
  "geometry": {"coordinates":[-3.6447207928,40.4380302429],"type":"Point"}
}