{
  "type": "Feature",
  "properties": {
    "addr:full":"Ctra Cuatretondeta, 1 Gorga Alicante 03811",
    "addr:housenumber":"1",
    "addr:postcode":"03811",
    "addr:street":"Ctra Cuatretondeta",
    "iso:country":"ES",
    "sg:address":"Ctra Cuatretondeta, 1",
    "sg:city":"Gorga",
    "sg:orig_category":"Cooperativas Agr\u00cdcolas",
    "sg:phone":"+34 965 51 10 12",
    "sg:postcode":"03811",
    "sg:province":"Alicante",
    "wof:name":"Cooperativa De Labradores T Ganaderos Virgen De Gracia,coop.vp",
    "wof:placetype":"venue"
},
  "geometry": {"coordinates":[-0.3575679958,38.721118927],"type":"Point"}
}