{
  "type": "Feature",
  "properties": {
    "addr:full":"Avda Sevilla, 19 Palacios Y Villafranca Sevilla 41720",
    "addr:housenumber":"19",
    "addr:postcode":"41720",
    "addr:street":"Avda Sevilla",
    "iso:country":"ES",
    "sg:address":"Avda Sevilla, 19",
    "sg:city":"Palacios Y Villafranca",
    "sg:orig_category":"Distribuci\u00d3n De Petr\u00d3leo Y Derivados",
    "sg:phone":"+34 955 81 62 53",
    "sg:postcode":"41720",
    "sg:province":"Sevilla",
    "wof:name":"Ricardo Ruiz E Hijos S. A.",
    "wof:placetype":"venue"
},
  "geometry": {"coordinates":[-5.9239621162,37.1611785889],"type":"Point"}
}