{
  "type": "Feature",
  "properties": {
    "iso:country":"ES",
    "sg:address":"Plaz San Juan (de), S/n",
    "sg:city":"Hinojosa Del Duque",
    "sg:orig_category":"Ense\u00d1anza, Formaci\u00d3n Profesional: Aprendizaje",
    "sg:phone":"+34 957 14 16 04",
    "sg:postcode":"14270",
    "sg:province":"C\u00f3rdoba",
    "wof:name":"Junta De Andalucia-consejeria De Cultura",
    "wof:placetype":"venue"
},
  "geometry": {"coordinates":[-5.1485581398,38.5006484985],"type":"Point"}
}