{
  "type": "Feature",
  "properties": {
    "iso:country":"ES",
    "sg:address":"Calle de Pintor Rosales (del), 6",
    "sg:city":"Mostoles",
    "sg:orig_category":"Caf\u00c9s, Bares, Cervecer\u00cdas",
    "sg:phone":"+34 916 64 29 57",
    "sg:postcode":"28932",
    "sg:province":"Madrid",
    "wof:name":"Fernandez Lopez Baltasar Miguel Angel",
    "wof:placetype":"venue"
},
  "geometry": {"coordinates":[-3.8645188808,40.332359314],"type":"Point"}
}