{
  "type": "Feature",
  "properties": {
    "iso:country":"ES",
    "sg:address":"Calle de Ronda, S/n",
    "sg:city":"Fuensalda\u00d1a",
    "sg:orig_category":"Molduras, Junquillos, Listones Y Molduras Perforadas",
    "sg:phone":"+34 983 58 32 47",
    "sg:postcode":"47194",
    "sg:province":"Valladolid",
    "wof:name":"Principe Centeno Cesar Carlos",
    "wof:placetype":"venue"
},
  "geometry": {"coordinates":[-4.7630438805,41.7053871155],"type":"Point"}
}