{
  "type": "Feature",
  "properties": {
    "iso:country":"ES",
    "sg:address":"Avda Europa, 6",
    "sg:city":"Almu\u00f1ecar",
    "sg:orig_category":"Centros M\u00c9dicos Y Sociales, Dispensarios",
    "sg:phone":"+34 958 63 21 66",
    "sg:postcode":"18690",
    "sg:province":"Granada",
    "wof:name":"Garcia Perez Gracia",
    "wof:placetype":"venue"
},
  "geometry": {"coordinates":[-3.6953980923,36.7305297852],"type":"Point"}
}