{
  "type": "Feature",
  "properties": {
    "addr:full":"Calle de Angel, 39 Albacete Albacete 02002",
    "addr:housenumber":"39",
    "addr:postcode":"02002",
    "addr:street":"Calle De Angel",
    "iso:country":"ES",
    "sg:address":"Calle de Angel, 39",
    "sg:city":"Albacete",
    "sg:orig_category":"Supermercados Y Hipermercados",
    "sg:phone":"+34 967 51 22 69",
    "sg:postcode":"02002",
    "sg:province":"Albacete",
    "sg:website":"www.mercadona.es",
    "wof:name":"Mercadona S.a.",
    "wof:placetype":"venue"
},
  "geometry": {"coordinates":[-1.851346612,38.9861602783],"type":"Point"}
}