{
  "type": "Feature",
  "properties": {
    "addr:full":"Virgen Desamparados, 3 Puente-genil C\u00f3rdoba 14500",
    "addr:housenumber":"3",
    "addr:postcode":"14500",
    "addr:street":"Desamparados;Co\u0301Rdoba",
    "iso:country":"ES",
    "sg:address":"Virgen Desamparados, 3",
    "sg:city":"Puente-genil",
    "sg:orig_category":"Supermercados Y Hipermercados",
    "sg:phone":"+34 957 60 90 47",
    "sg:postcode":"14500",
    "sg:province":"C\u00f3rdoba",
    "wof:name":"Alvarez Aguilar Juana Maria",
    "wof:placetype":"venue"
},
  "geometry": {"coordinates":[-4.7658658028,37.3863182068],"type":"Point"}
}