{
  "type": "Feature",
  "properties": {
    "addr:full":"Carrer de Constitucio (de La), 24 Gata Gorgos Alicante 03740",
    "addr:housenumber":"24",
    "addr:postcode":"03740",
    "addr:street":"Carrer De Constitucio De La",
    "iso:country":"ES",
    "sg:address":"Carrer de Constitucio (de La), 24",
    "sg:city":"Gata Gorgos",
    "sg:orig_category":"Empresas De Carpinter\u00cda De Madera",
    "sg:phone":"+34 965 75 76 41",
    "sg:postcode":"03740",
    "sg:province":"Alicante",
    "wof:name":"Francisca Signes Y Hermanos S.l.",
    "wof:placetype":"venue"
},
  "geometry": {"coordinates":[0.0838349983,38.7745437622],"type":"Point"}
}