{
  "type": "Feature",
  "properties": {
    "addr:full":"Via Augusta, 59 Barcelona Barcelona 08006",
    "addr:housenumber":"59",
    "addr:postcode":"08006",
    "addr:street":"Via Augusta",
    "iso:country":"ES",
    "sg:address":"Via Augusta, 59",
    "sg:city":"Barcelona",
    "sg:orig_category":"Inform\u00c1tica Equipo Y Programas (al Por Mayor)",
    "sg:phone":"+34 932 38 48 70",
    "sg:postcode":"08006",
    "sg:province":"Barcelona",
    "wof:name":"Network Bcn Software S.l.",
    "wof:placetype":"venue"
},
  "geometry": {"coordinates":[2.1518421173,41.399772644],"type":"Point"}
}