{
  "type": "Feature",
  "properties": {
    "iso:country":"ES",
    "sg:address":"Calle de Ba\u00d1eza (de La), 42",
    "sg:city":"Fuenlabrada",
    "sg:orig_category":"Transporte En General",
    "sg:phone":"+34 916 42 11 37",
    "sg:postcode":"28947",
    "sg:province":"Madrid",
    "sg:website":"www.nuevalinea.es",
    "wof:name":"Azcue Y Compa\u00f1ia S. A.",
    "wof:placetype":"venue"
},
  "geometry": {"coordinates":[-3.7499330044,40.2639427185],"type":"Point"}
}