{
  "type": "Feature",
  "properties": {
    "iso:country":"ES",
    "sg:address":"Urb Santa Maria Del Pilar, 133",
    "sg:city":"Huelva",
    "sg:orig_category":"Vinos Y Licores (venta Al Por Menor)",
    "sg:phone":"+34 959 15 60 43",
    "sg:postcode":"21005",
    "sg:province":"Huelva",
    "wof:name":"Sanchez Betanzos Francisco",
    "wof:placetype":"venue"
},
  "geometry": {"coordinates":[-6.9352087975,37.2693214417],"type":"Point"}
}