{
  "type": "Feature",
  "properties": {
    "addr:full":"C/ Doctor Piguillem, 13 Puigcerda Girona 17520",
    "addr:housenumber":"13",
    "addr:postcode":"17520",
    "addr:street":"C / Doctor Piguillem",
    "iso:country":"ES",
    "sg:address":"C/ Doctor Piguillem, 13",
    "sg:city":"Puigcerda",
    "sg:orig_category":"Asesor\u00cda Sobre Comunicaci\u00d3n De Empresas",
    "sg:phone":"+34 972 88 03 70",
    "sg:postcode":"17520",
    "sg:province":"Girona",
    "wof:name":"Forinvest S.l.",
    "wof:placetype":"venue"
},
  "geometry": {"coordinates":[1.9263800383,42.4350395203],"type":"Point"}
}