{
  "type": "Feature",
  "properties": {
    "addr:full":"Calle de Hornija, 6 Valladolid Valladolid 47013",
    "addr:housenumber":"6",
    "addr:postcode":"47013",
    "addr:street":"Calle De Hornija",
    "iso:country":"ES",
    "sg:address":"Calle de Hornija, 6",
    "sg:city":"Valladolid",
    "sg:orig_category":"Molduras, Junquillos, Listones Y Molduras Perforadas",
    "sg:phone":"+34 983 47 32 98",
    "sg:postcode":"47013",
    "sg:province":"Valladolid",
    "wof:name":"Hernanz Gomez Juan",
    "wof:placetype":"venue"
},
  "geometry": {"coordinates":[-4.7231879234,41.6335411072],"type":"Point"}
}