{
  "type": "Feature",
  "properties": {
    "addr:full":"Calle de Joaquin Turina, 2 Pozuelo De Alarcon Madrid 28224",
    "addr:housenumber":"2",
    "addr:postcode":"28224",
    "addr:street":"Calle De Joaquin Turina",
    "iso:country":"ES",
    "sg:address":"Calle de Joaquin Turina, 2",
    "sg:city":"Pozuelo De Alarcon",
    "sg:orig_category":"Promotores Constructores",
    "sg:phone":"+34 915 63 61 30",
    "sg:postcode":"28224",
    "sg:province":"Madrid",
    "wof:name":"Alcuba S. A.",
    "wof:placetype":"venue"
},
  "geometry": {"coordinates":[-3.8131253719,40.4562187195],"type":"Point"}
}