{
  "type": "Feature",
  "properties": {
    "iso:country":"ES",
    "sg:address":"Calle de Ocho De Enero Kalea, 8",
    "sg:city":"Gernika-lumo",
    "sg:orig_category":"Marroquiner\u00cda (confecci\u00d3n)",
    "sg:phone":"+34 946 25 63 81",
    "sg:postcode":"48300",
    "sg:province":"Vizcaya",
    "wof:name":"Rodriguez Garmendia Mikel",
    "wof:placetype":"venue"
},
  "geometry": {"coordinates":[-2.6773450375,43.3149757385],"type":"Point"}
}