{
  "type": "Feature",
  "properties": {
    "iso:country":"ES",
    "sg:address":"Ptda Segunda Rio, S/n",
    "sg:city":"Morella",
    "sg:orig_category":"Cr\u00cda De Cerdos",
    "sg:phone":"+34 964 16 08 52",
    "sg:postcode":"12300",
    "sg:province":"Castell\u00f3n",
    "wof:name":"Ganados Selectos Morella S.l.",
    "wof:placetype":"venue"
},
  "geometry": {"coordinates":[-0.0373200998,40.5940513611],"type":"Point"}
}