{
  "type": "Feature",
  "properties": {
    "iso:country":"ES",
    "sg:address":"Lamas De Castelo, S/n",
    "sg:city":"Carnota",
    "sg:orig_category":"Ense\u00d1anza Secundaria: Colegios Y Escuelas Privadas",
    "sg:phone":"+34 981 85 70 04",
    "sg:postcode":"15293",
    "sg:province":"La Coru\u00f1a",
    "wof:name":"Instituto De Educacion Secundaria De Carnota",
    "wof:placetype":"venue"
},
  "geometry": {"coordinates":[-9.0902872086,42.8618965149],"type":"Point"}
}