{
  "type": "Feature",
  "properties": {
    "addr:full":"Calle de Almendro, 2 Getafe Madrid 28901",
    "addr:housenumber":"2",
    "addr:postcode":"28901",
    "addr:street":"Calle De Almendro",
    "iso:country":"ES",
    "sg:address":"Calle de Almendro, 2",
    "sg:city":"Getafe",
    "sg:orig_category":"Asesor\u00cda Sobre Comunicaci\u00d3n De Empresas",
    "sg:phone":"+34 916 81 98 97",
    "sg:postcode":"28901",
    "sg:province":"Madrid",
    "wof:name":"Sanchez Vermejo Manuel",
    "wof:placetype":"venue"
},
  "geometry": {"coordinates":[-3.7315201759,40.3030204773],"type":"Point"}
}