{
  "type": "Feature",
  "properties": {
    "addr:full":"Calle de Labradores, 5 Almansa Albacete 02640",
    "addr:housenumber":"5",
    "addr:postcode":"02640",
    "addr:street":"Calle De Labradores",
    "iso:country":"ES",
    "sg:address":"Calle de Labradores, 5",
    "sg:city":"Almansa",
    "sg:orig_category":"Modistas",
    "sg:phone":"+34 967 31 06 74",
    "sg:postcode":"02640",
    "sg:province":"Albacete",
    "wof:name":"Triese Designers C.b.",
    "wof:placetype":"venue"
},
  "geometry": {"coordinates":[-1.1070940495,38.8765830994],"type":"Point"}
}