{
  "type": "Feature",
  "properties": {
    "iso:country":"ES",
    "sg:address":"Calle de Seminario De Nobles, 4",
    "sg:city":"Madrid",
    "sg:orig_category":"Ingenier\u00cda, Centros De Estudios (diversos)",
    "sg:phone":"+34 915 59 43 93",
    "sg:postcode":"28015",
    "sg:province":"Madrid",
    "wof:name":"M M Baukost S.l.",
    "wof:placetype":"venue"
},
  "geometry": {"coordinates":[-3.7133579254,40.4282341003],"type":"Point"}
}