{
  "type": "Feature",
  "properties": {
    "addr:full":"Bodega Monge, S/n Villada Palencia 34340",
    "addr:housenumber":"s / n",
    "addr:postcode":"34340",
    "iso:country":"ES",
    "sg:address":"Bodega Monge, S/n",
    "sg:city":"Villada",
    "sg:orig_category":"Aperitivos (fabricaci\u00d3n Y Al Por Mayor)",
    "sg:phone":"+34 979 84 45 13",
    "sg:postcode":"34340",
    "sg:province":"Palencia",
    "wof:name":"Facundo Blanco S. A.",
    "wof:placetype":"venue"
},
  "geometry": {"coordinates":[-4.9712848663,42.2468833923],"type":"Point"}
}