{
  "type": "Feature",
  "properties": {
    "iso:country":"ES",
    "sg:address":"Carrer de Residencia, 7",
    "sg:city":"Barcelona",
    "sg:orig_category":"Abogados",
    "sg:phone":"+34 932 74 12 44",
    "sg:postcode":"08030",
    "sg:province":"Barcelona",
    "wof:name":"Rojo Estebanez Juan Luis",
    "wof:placetype":"venue"
},
  "geometry": {"coordinates":[2.1912009716,41.4397621155],"type":"Point"}
}