{
  "type": "Feature",
  "properties": {
    "iso:country":"ES",
    "sg:address":"Calle de Maestro Castillo, 33",
    "sg:city":"Dos Hermanas",
    "sg:orig_category":"Farmacias",
    "sg:phone":"+34 955 66 90 72",
    "sg:postcode":"41700",
    "sg:province":"Sevilla",
    "wof:name":"Laborde Mu\u00f1oz De Bustillo Trinidad",
    "wof:placetype":"venue"
},
  "geometry": {"coordinates":[-5.9027647972,37.2911987305],"type":"Point"}
}