{
  "type": "Feature",
  "properties": {
    "addr:full":"Calle de Manuel Morales, 36 Elda Alicante 03600",
    "addr:housenumber":"36",
    "addr:postcode":"03600",
    "addr:street":"Calle De Manuel Morales",
    "iso:country":"ES",
    "sg:address":"Calle de Manuel Morales, 36",
    "sg:city":"Elda",
    "sg:orig_category":"Supermercados Y Hipermercados",
    "sg:phone":"+34 965 39 79 35",
    "sg:postcode":"03600",
    "sg:province":"Alicante",
    "wof:name":"Franco Maruenda Juan Antonio",
    "wof:placetype":"venue"
},
  "geometry": {"coordinates":[-0.7922019958,38.4788665771],"type":"Point"}
}