{
  "type": "Feature",
  "properties": {
    "addr:full":"Bjad Mercado, 1 Zamora Zamora 49005",
    "addr:postcode":"49005",
    "addr:street":"Mercado",
    "iso:country":"ES",
    "sg:address":"Bjad Mercado, 1",
    "sg:city":"Zamora",
    "sg:orig_category":"Cr\u00cda De Animales",
    "sg:phone":"+34 980 55 73 00",
    "sg:postcode":"49005",
    "sg:province":"Zamora",
    "wof:name":"Sociedad Cooperativa De Ovino Sayaguesa S.c.l. Covisa",
    "wof:placetype":"venue"
},
  "geometry": {"coordinates":[-5.7465867996,41.5081825256],"type":"Point"}
}