{
  "type": "Feature",
  "properties": {
    "iso:country":"ES",
    "sg:address":"Calle de Rio Garona, 5",
    "sg:city":"Mostoles",
    "sg:orig_category":"Caf\u00c9s, Bares, Cervecer\u00cdas",
    "sg:phone":"+34 916 13 12 43",
    "sg:postcode":"28934",
    "sg:province":"Madrid",
    "wof:name":"Fernandez Gallego Juan Bautista",
    "wof:placetype":"venue"
},
  "geometry": {"coordinates":[-3.8730430603,40.3190879822],"type":"Point"}
}