{
  "type": "Feature",
  "properties": {
    "addr:full":"Calle de Antonio Machado, 7 Espinar Segovia 40400",
    "addr:housenumber":"7",
    "addr:postcode":"40400",
    "addr:street":"Calle De Antonio Machado",
    "iso:country":"ES",
    "sg:address":"Calle de Antonio Machado, 7",
    "sg:city":"Espinar",
    "sg:orig_category":"Asesor\u00cda Fiscal Y Jur\u00cddica",
    "sg:phone":"+34 921 18 21 16",
    "sg:postcode":"40400",
    "sg:province":"Segovia",
    "wof:name":"Bartolome Rodriguez Andres",
    "wof:placetype":"venue"
},
  "geometry": {"coordinates":[-4.2481160164,40.7182731628],"type":"Point"}
}