{
  "type": "Feature",
  "properties": {
    "addr:full":"Calle de Federico Garcia Lorca, 19 Benejuzar Alicante 03390",
    "addr:housenumber":"19",
    "addr:postcode":"03390",
    "addr:street":"Calle De Federico Garcia Lorca",
    "iso:country":"ES",
    "sg:address":"Calle de Federico Garcia Lorca, 19",
    "sg:city":"Benejuzar",
    "sg:orig_category":"Ingenier\u00cda, Centros De Estudios (diversos)",
    "sg:phone":"+34 965 35 63 13",
    "sg:postcode":"03390",
    "sg:province":"Alicante",
    "wof:name":"Obras Proyectos E Infraestructuras S.l.",
    "wof:placetype":"venue"
},
  "geometry": {"coordinates":[-0.8365719914,38.0790939331],"type":"Point"}
}