{
  "type": "Feature",
  "properties": {
    "iso:country":"ES",
    "sg:address":"Calle de Azafranal, 4",
    "sg:city":"Salamanca",
    "sg:orig_category":"Promotores Constructores",
    "sg:phone":"+34 923 26 36 00",
    "sg:postcode":"37001",
    "sg:province":"Salamanca",
    "wof:name":"Salamanca Consulting S.l.",
    "wof:placetype":"venue"
},
  "geometry": {"coordinates":[-5.6623549461,40.9664382935],"type":"Point"}
}