{
  "type": "Feature",
  "properties": {
    "iso:country":"ES",
    "sg:address":"Avda. Constitucion, 23",
    "sg:city":"Caba\u00d1aquinta",
    "sg:orig_category":"Quincaller\u00cda (al Por Menor)",
    "sg:phone":"+34 985 49 40 92",
    "sg:postcode":"33686",
    "sg:province":"Asturias",
    "wof:name":"Fernandez Lobo Vicente",
    "wof:placetype":"venue"
},
  "geometry": {"coordinates":[-5.6233692169,43.1617012024],"type":"Point"}
}