{
  "type": "Feature",
  "properties": {
    "addr:full":"Carr Manel Quer, 7 Girona Girona 17002",
    "addr:housenumber":"7",
    "addr:postcode":"17002",
    "addr:street":"Carr Manel Quer",
    "iso:country":"ES",
    "sg:address":"Carr Manel Quer, 7",
    "sg:city":"Girona",
    "sg:orig_category":"Arquitectos",
    "sg:phone":"+34 972 21 03 47",
    "sg:postcode":"17002",
    "sg:province":"Girona",
    "wof:name":"Roca Casademont Jordi",
    "wof:placetype":"venue"
},
  "geometry": {"coordinates":[2.8178300858,41.9757614136],"type":"Point"}
}