{
  "type": "Feature",
  "properties": {
    "addr:full":"Carrer de Orquidies, 39 Viladecans Barcelona 08840",
    "addr:housenumber":"39",
    "addr:postcode":"08840",
    "addr:street":"Carrer De Orquidies",
    "iso:country":"ES",
    "sg:address":"Carrer de Orquidies, 39",
    "sg:city":"Viladecans",
    "sg:orig_category":"Molduras, Junquillos, Listones Y Molduras Perforadas",
    "sg:phone":"+34 936 58 77 00",
    "sg:postcode":"08840",
    "sg:province":"Barcelona",
    "wof:name":"Urban Uson Clemente",
    "wof:placetype":"venue"
},
  "geometry": {"coordinates":[2.0023570061,41.3150672913],"type":"Point"}
}