{
  "type": "Feature",
  "properties": {
    "iso:country":"ES",
    "sg:address":"Calle de De Sancti Spiritus, 18",
    "sg:city":"Benavente",
    "sg:orig_category":"Ropa Para Se\u00d1oras Y Caballeros (al Por Menor)",
    "sg:phone":"+34 980 63 71 40",
    "sg:postcode":"49600",
    "sg:province":"Zamora",
    "wof:name":"Garcia Garcia Milagros",
    "wof:placetype":"venue"
},
  "geometry": {"coordinates":[-5.6815829277,42.0019683838],"type":"Point"}
}