{
  "type": "Feature",
  "properties": {
    "addr:full":"Calle de Cerca (la), S/n Villalobon Palencia 34191",
    "addr:postcode":"34191",
    "addr:street":"Calle De Cerca La S / N",
    "iso:country":"ES",
    "sg:address":"Calle de Cerca (la), S/n",
    "sg:city":"Villalobon",
    "sg:orig_category":"Molduras, Junquillos, Listones Y Molduras Perforadas",
    "sg:phone":"+34 979 76 52 14",
    "sg:postcode":"34191",
    "sg:province":"Palencia",
    "wof:name":"Norella Chavarriaga Maria Elena",
    "wof:placetype":"venue"
},
  "geometry": {"coordinates":[-4.5028982162,42.02866745],"type":"Point"}
}