{
  "type": "Feature",
  "properties": {
    "addr:full":"Cra. Martorell A Capellades, 19 S. Esteve Sesrovires Barcelona 08635",
    "addr:housenumber":"19",
    "addr:postcode":"08635",
    "addr:street":"S. Esteve Sesrovires Barcelona",
    "iso:country":"ES",
    "sg:address":"Cra. Martorell A Capellades, 19",
    "sg:city":"S. Esteve Sesrovires",
    "sg:classifiers":[
        {
            "category":"Sports & Exercise",
            "subcategory":"Golf",
            "type":"Entertainment"
        }
    ],
    "sg:phone":"+34 937 72 88 00",
    "sg:postcode":"08635",
    "sg:province":"Barcelona",
    "sg:tags":[
        "y",
        "de",
        "campos",
        "clases"
    ],
    "wof:name":"Club De Golf Masia Bach",
    "wof:placetype":"venue"
},
  "geometry": {"coordinates":[1.8731199503,41.4965515137],"type":"Point"}
}