{
  "type": "Feature",
  "properties": {
    "iso:country":"ES",
    "sg:address":"Avda Tres Cruces, 2",
    "sg:city":"Zamora",
    "sg:orig_category":"Molduras, Junquillos, Listones Y Molduras Perforadas",
    "sg:phone":"+34 980 51 10 90",
    "sg:postcode":"49008",
    "sg:province":"Zamora",
    "wof:name":"Campo Rodrigo Francisco Javier",
    "wof:placetype":"venue"
},
  "geometry": {"coordinates":[-5.7422289848,41.5088272095],"type":"Point"}
}