{
  "type": "Feature",
  "properties": {
    "iso:country":"ES",
    "sg:address":"Av Fra Juniper Serra, 20",
    "sg:city":"Manacor",
    "sg:orig_category":"Molduras, Junquillos, Listones Y Molduras Perforadas",
    "sg:phone":"+34 971 55 10 47",
    "sg:postcode":"07500",
    "sg:province":"Islas Baleares",
    "wof:name":"Grimalt Montserrat Montserrat",
    "wof:placetype":"venue"
},
  "geometry": {"coordinates":[3.2024149895,39.5728912354],"type":"Point"}
}