{
  "type": "Feature",
  "properties": {
    "iso:country":"ES",
    "sg:address":"Calle de Hermano Juan Fernandez, 13",
    "sg:city":"Cordoba",
    "sg:orig_category":"Ense\u00d1anza: Profesiones Art\u00cdsticas",
    "sg:phone":"+34 957 26 35 49",
    "sg:postcode":"14014",
    "sg:province":"C\u00f3rdoba",
    "wof:name":"Zurita Castro Jose",
    "wof:placetype":"venue"
},
  "geometry": {"coordinates":[-4.7561359406,37.8938941956],"type":"Point"}
}