{
  "type": "Feature",
  "properties": {
    "addr:full":"Alambique, S/n Salobre\u00f1a Granada 18680",
    "addr:postcode":"18680",
    "addr:street":"Alambique S / N Salobren\u0303A",
    "iso:country":"ES",
    "sg:address":"Alambique, S/n",
    "sg:city":"Salobre\u00f1a",
    "sg:orig_category":"Maquinaria Para Industrias Diversas",
    "sg:phone":"+34 958 61 27 45",
    "sg:postcode":"18680",
    "sg:province":"Granada",
    "wof:name":"Villacreces E Hijos S.l.",
    "wof:placetype":"venue"
},
  "geometry": {"coordinates":[-3.5900440216,36.7471542358],"type":"Point"}
}