{
  "type": "Feature",
  "properties": {
    "addr:full":"Carrer de Casanova, 63 Barcelona Barcelona 08011",
    "addr:housenumber":"63",
    "addr:postcode":"08011",
    "addr:street":"Carrer De Casanova",
    "iso:country":"ES",
    "sg:address":"Carrer de Casanova, 63",
    "sg:city":"Barcelona",
    "sg:orig_category":"Abogados",
    "sg:phone":"+34 933 23 43 43",
    "sg:postcode":"08011",
    "sg:province":"Barcelona",
    "wof:name":"Pi\u00f1ol And Lindin Abogados S.l.l.",
    "wof:placetype":"venue"
},
  "geometry": {"coordinates":[2.1588289738,41.385181427],"type":"Point"}
}