{
  "type": "Feature",
  "properties": {
    "addr:full":"Francisco Aleson, 4 Iru\u00f1a Navarra 31008",
    "addr:housenumber":"4",
    "addr:postcode":"31008",
    "addr:street":"Francisco Aleson",
    "iso:country":"ES",
    "sg:address":"Francisco Aleson, 4",
    "sg:city":"Iru\u00f1a",
    "sg:orig_category":"M\u00c9dicos: Anestesiolog\u00cda Y Reanimaci\u00d3n Quir\u00dargica",
    "sg:phone":"+34 948 19 67 80",
    "sg:postcode":"31008",
    "sg:province":"Navarra",
    "wof:name":"Achury Bello German",
    "wof:placetype":"venue"
},
  "geometry": {"coordinates":[-1.6658875942,42.8099594116],"type":"Point"}
}