{
  "type": "Feature",
  "properties": {
    "addr:full":"Carrer de Gavina (de La), 1 Salou Tarragona 43840",
    "addr:housenumber":"1",
    "addr:postcode":"43840",
    "addr:street":"Carrer De Gavina De La",
    "iso:country":"ES",
    "sg:address":"Carrer de Gavina (de La), 1",
    "sg:city":"Salou",
    "sg:orig_category":"Telefon\u00cda: Instaladores Varios",
    "sg:phone":"+34 977 35 11 03",
    "sg:postcode":"43840",
    "sg:province":"Tarragona",
    "wof:name":"Polipero S.l.",
    "wof:placetype":"venue"
},
  "geometry": {"coordinates":[1.1496599913,41.0682182312],"type":"Point"}
}