{
  "type": "Feature",
  "properties": {
    "addr:full":"Calle de Madrid, 7 Caspe Zaragoza 50700",
    "addr:housenumber":"7",
    "addr:postcode":"50700",
    "addr:street":"Calle De Madrid",
    "iso:country":"ES",
    "sg:address":"Calle de Madrid, 7",
    "sg:city":"Caspe",
    "sg:orig_category":"Agentes, Concesionarios Y Sucursales De Veh\u00cdculos",
    "sg:phone":"+34 976 63 01 74",
    "sg:postcode":"50700",
    "sg:province":"Zaragoza",
    "wof:name":"Auto F.r.n. S.l.",
    "wof:placetype":"venue"
},
  "geometry": {"coordinates":[-0.0459359996,41.2385787964],"type":"Point"}
}