{
  "type": "Feature",
  "properties": {
    "iso:country":"ES",
    "sg:address":"Ctra Pedrera-gilena, Km. 0009,5",
    "sg:city":"Pedrera",
    "sg:orig_category":"Aceites Y Grasas Alimentarias (fabricaci\u00d3n, Al Por Mayor)",
    "sg:phone":"+34 954 81 95 04",
    "sg:postcode":"41566",
    "sg:province":"Sevilla",
    "wof:name":"Comercial Alimenticia Antequerana S.l.u.",
    "wof:placetype":"venue"
},
  "geometry": {"coordinates":[-4.8989639282,37.2236633301],"type":"Point"}
}