{
  "type": "Feature",
  "properties": {
    "addr:full":"Calle de Serrana, S/n Dos Hermanas Sevilla 41700",
    "addr:housenumber":"s / n",
    "addr:postcode":"41700",
    "addr:street":"Calle De Serrana",
    "iso:country":"ES",
    "sg:address":"Calle de Serrana, S/n",
    "sg:city":"Dos Hermanas",
    "sg:orig_category":"Asociaciones Y Clubs Deportivos",
    "sg:phone":"+34 954 72 20 15",
    "sg:postcode":"41700",
    "sg:province":"Sevilla",
    "wof:name":"Pe\u00f1a Ciclista",
    "wof:placetype":"venue"
},
  "geometry": {"coordinates":[-5.9138636589,37.2722091675],"type":"Point"}
}