{
  "type": "Feature",
  "properties": {
    "addr:full":"Avda Carlos Iii, 294 Campillo Del Moro Almer\u00eda 04720",
    "addr:housenumber":"294",
    "addr:postcode":"04720",
    "addr:street":"Avda Carlos Iii",
    "iso:country":"ES",
    "sg:address":"Avda Carlos Iii, 294",
    "sg:city":"Campillo Del Moro",
    "sg:orig_category":"Institutos De Belleza",
    "sg:phone":"+34 950 34 21 26",
    "sg:postcode":"04720",
    "sg:province":"Almer\u00eda",
    "wof:name":"Jimenez Rosal Purificacion",
    "wof:placetype":"venue"
},
  "geometry": {"coordinates":[-2.5974500179,36.801410675],"type":"Point"}
}