{
  "type": "Feature",
  "properties": {
    "addr:full":"Av Doctor Fleming, 1 Ondara Alicante 03760",
    "addr:housenumber":"1",
    "addr:postcode":"03760",
    "addr:street":"Av Doctor Fleming",
    "iso:country":"ES",
    "sg:address":"Av Doctor Fleming, 1",
    "sg:city":"Ondara",
    "sg:orig_category":"Alimentaci\u00d3n General (al Por Menor)",
    "sg:phone":"+34 965 76 71 25",
    "sg:postcode":"03760",
    "sg:province":"Alicante",
    "wof:name":"Fernandez Mero\u00f1o Francisco",
    "wof:placetype":"venue"
},
  "geometry": {"coordinates":[0.0153599996,38.8265266418],"type":"Point"}
}