{
  "type": "Feature",
  "properties": {
    "addr:full":"Pase Marques De Corvera, 94 Carmen Murcia 30002",
    "addr:housenumber":"94",
    "addr:postcode":"30002",
    "addr:street":"Marques;Corvera",
    "iso:country":"ES",
    "sg:address":"Pase Marques De Corvera, 94",
    "sg:city":"Carmen",
    "sg:orig_category":"M\u00c1quinas De Coser Y De Hacer Punto (al Por Mayor)",
    "sg:phone":"+34 968 25 23 91",
    "sg:postcode":"30002",
    "sg:province":"Murcia",
    "sg:website":"www.reymasur.com",
    "wof:name":"Reymasur Lorca S.l.",
    "wof:placetype":"venue"
},
  "geometry": {"coordinates":[-1.1302499771,37.9829597473],"type":"Point"}
}