{
  "type": "Feature",
  "properties": {
    "addr:full":"Avda Democracia (de La), 1 Aguilas Murcia 30880",
    "addr:housenumber":"1",
    "addr:postcode":"30880",
    "addr:street":"Avda Democracia De La",
    "iso:country":"ES",
    "sg:address":"Avda Democracia (de La), 1",
    "sg:city":"Aguilas",
    "sg:orig_category":"Caf\u00c9s, Bares, Cervecer\u00cdas",
    "sg:phone":"+34 968 44 89 68",
    "sg:postcode":"30880",
    "sg:province":"Murcia",
    "wof:name":"Fernandez Saez Jose",
    "wof:placetype":"venue"
},
  "geometry": {"coordinates":[-1.5769850016,37.4141769409],"type":"Point"}
}