{
  "type": "Feature",
  "properties": {
    "iso:country":"ES",
    "sg:address":"Cmno Finca El Chaparral, S/n",
    "sg:city":"Galapagar",
    "sg:orig_category":"Cr\u00cda De Animales",
    "sg:phone":"+34 918 56 30 96",
    "sg:postcode":"28260",
    "sg:province":"Madrid",
    "wof:name":"Perez-seoane Fernandez-villaverde Carmen",
    "wof:placetype":"venue"
},
  "geometry": {"coordinates":[-4.0020170212,40.5765609741],"type":"Point"}
}