{
  "type": "Feature",
  "properties": {
    "iso:country":"ES",
    "sg:address":"Calle de Jose Antonio, 7",
    "sg:city":"Huecas",
    "sg:orig_category":"Cerrajer\u00cda, Ferrallista",
    "sg:phone":"+34 925 73 07 30",
    "sg:postcode":"45511",
    "sg:province":"Toledo",
    "wof:name":"Bravo Herrera Melecio",
    "wof:placetype":"venue"
},
  "geometry": {"coordinates":[-4.1962199211,40.0120849609],"type":"Point"}
}