{
  "type": "Feature",
  "properties": {
    "addr:full":"Ctra Ossa De Montiel, 8 Villarrobledo Albacete 02600",
    "addr:housenumber":"8",
    "addr:postcode":"02600",
    "addr:street":"Ctra Ossa De Montiel",
    "iso:country":"ES",
    "sg:address":"Ctra Ossa De Montiel, 8",
    "sg:city":"Villarrobledo",
    "sg:orig_category":"Electricidad: Equipos Industriales, Componentes (fabricaci\u00d3n)",
    "sg:phone":"+34 967 14 67 13",
    "sg:postcode":"02600",
    "sg:province":"Albacete",
    "wof:name":"Joman Electric S.l.",
    "wof:placetype":"venue"
},
  "geometry": {"coordinates":[-2.6160368919,39.2551994324],"type":"Point"}
}