{
  "type": "Feature",
  "properties": {
    "addr:full":"Calle de Castillo, 6 Rojales Alicante 03170",
    "addr:housenumber":"6",
    "addr:postcode":"03170",
    "addr:street":"Calle De Castillo",
    "iso:country":"ES",
    "sg:address":"Calle de Castillo, 6",
    "sg:city":"Rojales",
    "sg:orig_category":"Alimentaci\u00d3n General (al Por Menor)",
    "sg:phone":"+34 966 71 53 35",
    "sg:postcode":"03170",
    "sg:province":"Alicante",
    "wof:name":"Roca Costa Manuel",
    "wof:placetype":"venue"
},
  "geometry": {"coordinates":[-0.7237159014,38.0868492126],"type":"Point"}
}