{
  "type": "Feature",
  "properties": {
    "addr:full":"Calle de Sagasta, 22 San Pedro Murcia 30005",
    "addr:housenumber":"22",
    "addr:postcode":"30005",
    "addr:street":"Calle De Sagasta",
    "iso:country":"ES",
    "sg:address":"Calle de Sagasta, 22",
    "sg:city":"San Pedro",
    "sg:orig_category":"C\u00c1maras De Comercio E Industria, Oficios, Agricultura",
    "sg:phone":"+34 968 22 14 78",
    "sg:postcode":"30005",
    "sg:province":"Murcia",
    "wof:name":"Gil Imaz Catalina",
    "wof:placetype":"venue"
},
  "geometry": {"coordinates":[-1.1362220049,37.9851608276],"type":"Point"}
}