{
  "type": "Feature",
  "properties": {
    "iso:country":"ES",
    "sg:address":"Calle de Alberca (de La), 5",
    "sg:city":"Boadilla Del Monte",
    "sg:orig_category":"Cl\u00cdnicas Dentales",
    "sg:phone":"+34 916 32 69 09",
    "sg:postcode":"28660",
    "sg:province":"Madrid",
    "wof:name":"Vazquez Perera Maria Aranzazu",
    "wof:placetype":"venue"
},
  "geometry": {"coordinates":[-3.8840770721,40.4057655334],"type":"Point"}
}