{
  "type": "Feature",
  "properties": {
    "iso:country":"ES",
    "sg:address":"Calle de F. Toribio De Motolinia, 16",
    "sg:city":"Zamora",
    "sg:orig_category":"Venta, Montaje De Neum\u00c1ticos",
    "sg:phone":"+34 980 52 29 60",
    "sg:postcode":"49007",
    "sg:province":"Zamora",
    "wof:name":"Silva Berrocal Fernando Jose",
    "wof:placetype":"venue"
},
  "geometry": {"coordinates":[-5.7435288429,41.5102577209],"type":"Point"}
}