{
  "type": "Feature",
  "properties": {
    "iso:country":"ES",
    "sg:address":"Av Jaume I, 198",
    "sg:city":"Terrassa",
    "sg:orig_category":"Agentes, Concesionarios Y Sucursales De Veh\u00cdculos",
    "sg:phone":"+34 937 86 30 13",
    "sg:postcode":"08226",
    "sg:province":"Barcelona",
    "wof:name":"Egara Motor S. A.",
    "wof:placetype":"venue"
},
  "geometry": {"coordinates":[2.0236260891,41.5708274841],"type":"Point"}
}