{
  "type": "Feature",
  "properties": {
    "iso:country":"ES",
    "sg:address":"Carrer de Flors, 1",
    "sg:city":"Vic",
    "sg:orig_category":"Ropa Para Se\u00d1oras Y Caballeros (al Por Menor)",
    "sg:phone":"+34 938 85 03 41",
    "sg:postcode":"08500",
    "sg:province":"Barcelona",
    "wof:name":"Luna Pino Francisco",
    "wof:placetype":"venue"
},
  "geometry": {"coordinates":[2.2493460178,41.9274711609],"type":"Point"}
}