{
  "type": "Feature",
  "properties": {
    "addr:full":"Calle de Muralla Del Mar, 5 Cartagena Murcia 30202",
    "addr:housenumber":"5",
    "addr:postcode":"30202",
    "addr:street":"Calle De Muralla Del Mar",
    "iso:country":"ES",
    "sg:address":"Calle de Muralla Del Mar, 5",
    "sg:city":"Cartagena",
    "sg:orig_category":"Producci\u00d3n, Venta De Productos De Agricultura Biol\u00d3gica",
    "sg:phone":"+34 968 50 29 41",
    "sg:postcode":"30202",
    "sg:province":"Murcia",
    "wof:name":"Duerma S.l.",
    "wof:placetype":"venue"
},
  "geometry": {"coordinates":[-0.981678009,37.5988464355],"type":"Point"}
}