{
  "type": "Feature",
  "properties": {
    "iso:country":"ES",
    "sg:address":"Plaz San Lazaro, 2",
    "sg:city":"Palencia",
    "sg:orig_category":"Cl\u00cdnicas Dentales",
    "sg:phone":"+34 979 74 03 03",
    "sg:postcode":"34001",
    "sg:province":"Palencia",
    "wof:name":"Alvarez Redondo Maria Luisa",
    "wof:placetype":"venue"
},
  "geometry": {"coordinates":[-4.5297031403,42.0096855164],"type":"Point"}
}