{
  "type": "Feature",
  "properties": {
    "iso:country":"ES",
    "sg:address":"Calle de Baena, 4",
    "sg:city":"Sevilla",
    "sg:orig_category":"Electricidad: Instaladores",
    "sg:phone":"+34 954 25 87 85",
    "sg:postcode":"41006",
    "sg:province":"Sevilla",
    "wof:name":"Telvent Outsourcing S.a.",
    "wof:placetype":"venue"
},
  "geometry": {"coordinates":[-5.9408288002,37.3776359558],"type":"Point"}
}