{
  "type": "Feature",
  "properties": {
    "iso:country":"ES",
    "sg:address":"Avda Miguel Hernandez, 94",
    "sg:city":"Madrid",
    "sg:orig_category":"Caf\u00c9s, Bares, Cervecer\u00cdas",
    "sg:phone":"+34 917 65 03 01",
    "sg:postcode":"28018",
    "sg:province":"Madrid",
    "wof:name":"Galvez Navarro Raul Antonio",
    "wof:placetype":"venue"
},
  "geometry": {"coordinates":[-3.6437740326,40.3810501099],"type":"Point"}
}