{
  "type": "Feature",
  "properties": {
    "addr:full":"Carrer de Viladecans, 9 S. Boi Llobregat Barcelona 08830",
    "addr:housenumber":"9",
    "addr:postcode":"08830",
    "addr:street":"Carrer De Viladecans",
    "iso:country":"ES",
    "sg:address":"Carrer de Viladecans, 9",
    "sg:city":"S. Boi Llobregat",
    "sg:orig_category":"Maquinaria Para Industrias Diversas",
    "sg:phone":"+34 936 52 11 92",
    "sg:postcode":"08830",
    "sg:province":"Barcelona",
    "wof:name":"Nu\u00d1ez Nu\u00d1ez Vicente",
    "wof:placetype":"venue"
},
  "geometry": {"coordinates":[2.0417470932,41.3327331543],"type":"Point"}
}