{
  "type": "Feature",
  "properties": {
    "iso:country":"ES",
    "sg:address":"Calle de Mayor, 45",
    "sg:city":"Cartagena",
    "sg:orig_category":"Mercer\u00cda, Lencer\u00cda (al Por Menor)",
    "sg:phone":"+34 968 51 15 31",
    "sg:postcode":"30300",
    "sg:province":"Murcia",
    "wof:name":"Gonzalez Caselles Joaquin",
    "wof:placetype":"venue"
},
  "geometry": {"coordinates":[-0.9148190022,37.6042823792],"type":"Point"}
}