{
  "type": "Feature",
  "properties": {
    "iso:country":"ES",
    "sg:address":"Calle de Santander, 13",
    "sg:city":"San Juan De Aznalfarache",
    "sg:orig_category":"Mercer\u00cda, Lencer\u00cda (al Por Menor)",
    "sg:phone":"+34 954 76 53 01",
    "sg:postcode":"41920",
    "sg:province":"Sevilla",
    "wof:name":"Diaz Herrera Luis",
    "wof:placetype":"venue"
},
  "geometry": {"coordinates":[-6.0353050232,37.3571205139],"type":"Point"}
}