{
  "type": "Feature",
  "properties": {
    "addr:full":"Calle de San Cipriano, 66 Madrid Madrid 28032",
    "addr:housenumber":"66",
    "addr:postcode":"madrid;28032",
    "addr:street":"Calle De San",
    "iso:country":"ES",
    "sg:address":"Calle de San Cipriano, 66",
    "sg:city":"Madrid",
    "sg:orig_category":"Delegados, Agentes De Tr\u00c1nsito, Auxiliares De Transporte Internacional",
    "sg:phone":"+34 917 75 30 96",
    "sg:postcode":"28032",
    "sg:province":"Madrid",
    "wof:name":"Barrold Dos Iberica, S.l.",
    "wof:placetype":"venue"
},
  "geometry": {"coordinates":[-3.6025509834,40.4038047791],"type":"Point"}
}