{
  "type": "Feature",
  "properties": {
    "iso:country":"ES",
    "sg:address":"Rua Areal, 18",
    "sg:city":"Vigo",
    "sg:orig_category":"Inmobiliaria (agencias)",
    "sg:phone":"+34 986 44 17 66",
    "sg:postcode":"36201",
    "sg:province":"Pontevedra",
    "wof:name":"Couso, Alvarez Y Giraldez S.l.",
    "wof:placetype":"venue"
},
  "geometry": {"coordinates":[-8.718911171,42.2392120361],"type":"Point"}
}