{
  "type": "Feature",
  "properties": {
    "iso:country":"ES",
    "sg:address":"Calle de Beaterio, 15",
    "sg:city":"Villamalea",
    "sg:orig_category":"Grafistas",
    "sg:phone":"+34 967 48 32 78",
    "sg:postcode":"02270",
    "sg:province":"Albacete",
    "wof:name":"Mercenariosde La Imagen S.l.",
    "wof:placetype":"venue"
},
  "geometry": {"coordinates":[-1.6002844572,39.3634147644],"type":"Point"}
}