{
  "type": "Feature",
  "properties": {
    "iso:country":"ES",
    "sg:address":"Barr Campo De Futbol, S/n",
    "sg:city":"Villaseca Laciana",
    "sg:orig_category":"Centros De Educaci\u00d3n Especial",
    "sg:phone":"+34 987 48 38 05",
    "sg:postcode":"24140",
    "sg:province":"Le\u00f3n",
    "wof:name":"Colegio Publico Manuel Barrio Msp",
    "wof:placetype":"venue"
},
  "geometry": {"coordinates":[-6.2514429092,42.9444885254],"type":"Point"}
}