{
  "type": "Feature",
  "properties": {
    "addr:full":"Calle de Huelva, 33 Arrecife Las Palmas 35500",
    "addr:housenumber":"33",
    "addr:postcode":"35500",
    "addr:street":"Calle De Huelva",
    "iso:country":"ES",
    "sg:address":"Calle de Huelva, 33",
    "sg:city":"Arrecife",
    "sg:orig_category":"Promotores Constructores",
    "sg:phone":"+34 928 80 33 29",
    "sg:postcode":"35500",
    "sg:province":"Las Palmas",
    "wof:name":"Leonardo David S.l.",
    "wof:placetype":"venue"
},
  "geometry": {"coordinates":[-13.5504894257,28.9684753418],"type":"Point"}
}