{
  "type": "Feature",
  "properties": {
    "addr:full":"Calle de San Miguel, 105 Villanueva Serena Badajoz 06700",
    "addr:housenumber":"105",
    "addr:postcode":"06700",
    "addr:street":"Calle De San Miguel",
    "iso:country":"ES",
    "sg:address":"Calle de San Miguel, 105",
    "sg:city":"Villanueva Serena",
    "sg:orig_category":"Cristaler\u00cdas",
    "sg:phone":"+34 924 84 32 56",
    "sg:postcode":"06700",
    "sg:province":"Badajoz",
    "wof:name":"Cristaleria Carmona Mu\u00f1oz S.l.",
    "wof:placetype":"venue"
},
  "geometry": {"coordinates":[-5.7911338806,38.9786949158],"type":"Point"}
}