{
  "type": "Feature",
  "properties": {
    "iso:country":"ES",
    "sg:address":"Carr Wagner, 63",
    "sg:city":"Badalona",
    "sg:orig_category":"Molduras, Junquillos, Listones Y Molduras Perforadas",
    "sg:phone":"+34 933 99 25 03",
    "sg:postcode":"08917",
    "sg:province":"Barcelona",
    "wof:name":"Cano Ruiz Ursula",
    "wof:placetype":"venue"
},
  "geometry": {"coordinates":[2.2215809822,41.4520187378],"type":"Point"}
}