{
  "type": "Feature",
  "properties": {
    "iso:country":"ES",
    "sg:address":"Calle de Zaragoza, 12",
    "sg:city":"Palmas De Gran Canaria",
    "sg:orig_category":"\u00d3ptica: Instrumentos (fabricaci\u00d3n)",
    "sg:phone":"+34 928 25 77 16",
    "sg:postcode":"35012",
    "sg:province":"Las Palmas",
    "wof:name":"Torres Dominguez Hermenegildo",
    "wof:placetype":"venue"
},
  "geometry": {"coordinates":[-15.4322881699,28.1099948883],"type":"Point"}
}