{
  "type": "Feature",
  "properties": {
    "addr:full":"Calle de Bilbao, 24 Albacete Albacete 02005",
    "addr:housenumber":"24",
    "addr:postcode":"02005",
    "addr:street":"Calle De Bilbao",
    "iso:country":"ES",
    "sg:address":"Calle de Bilbao, 24",
    "sg:city":"Albacete",
    "sg:orig_category":"M\u00c9dicos: An\u00c1lisis Cl\u00cdnicos",
    "sg:phone":"+34 967 22 90 73",
    "sg:postcode":"02005",
    "sg:province":"Albacete",
    "wof:name":"Aleman Y Gonzalez C.b.",
    "wof:placetype":"venue"
},
  "geometry": {"coordinates":[-1.8675744534,39.0008125305],"type":"Point"}
}