{
  "type": "Feature",
  "properties": {
    "addr:full":"Calle de Castilla, 3 Jaen Ja\u00e9n 23007",
    "addr:housenumber":"3;jae\u0301n",
    "addr:postcode":"23007",
    "addr:street":"Calle De Castilla",
    "iso:country":"ES",
    "sg:address":"Calle de Castilla, 3",
    "sg:city":"Jaen",
    "sg:orig_category":"Complementos De Vestir (al Por Menor)",
    "sg:phone":"+34 953 26 62 45",
    "sg:postcode":"23007",
    "sg:province":"Ja\u00e9n",
    "wof:name":"Parraga Montilla Maria Jesus",
    "wof:placetype":"venue"
},
  "geometry": {"coordinates":[-3.7894868851,37.7705917358],"type":"Point"}
}