{
  "type": "Feature",
  "properties": {
    "addr:full":"Carrer de Sant Pau, 16 Riudoms Tarragona 43330",
    "addr:housenumber":"16",
    "addr:postcode":"43330",
    "addr:street":"Carrer De Sant Pau",
    "iso:country":"ES",
    "sg:address":"Carrer de Sant Pau, 16",
    "sg:city":"Riudoms",
    "sg:orig_category":"Sociedades, Compa\u00d1\u00cdas Aseguradoras",
    "sg:phone":"+34 977 85 07 50",
    "sg:postcode":"43330",
    "sg:province":"Tarragona",
    "wof:name":"Gestio D'assegurances Jofran S.l.",
    "wof:placetype":"venue"
},
  "geometry": {"coordinates":[1.049849987,41.1397018433],"type":"Point"}
}