{
  "type": "Feature",
  "properties": {
    "addr:full":"Calle de Puerto De Alazores, 30 Madrid Madrid 28031",
    "addr:housenumber":"30",
    "addr:postcode":"madrid;28031",
    "addr:street":"Calle De Puerto De Alazores",
    "iso:country":"ES",
    "sg:address":"Calle de Puerto De Alazores, 30",
    "sg:city":"Madrid",
    "sg:orig_category":"Prot\u00c9sicos Dentales",
    "sg:phone":"+34 913 03 67 90",
    "sg:postcode":"28031",
    "sg:province":"Madrid",
    "wof:name":"Dica Dental Laboratorio De Protesis S.l.l.",
    "wof:placetype":"venue"
},
  "geometry": {"coordinates":[-3.6267640591,40.3785438538],"type":"Point"}
}