{
  "type": "Feature",
  "properties": {
    "addr:full":"Calle de Doctor Borrull, 1 Javea Alicante 03730",
    "addr:housenumber":"1",
    "addr:postcode":"03730",
    "addr:street":"Calle De Doctor Borrull",
    "iso:country":"ES",
    "sg:address":"Calle de Doctor Borrull, 1",
    "sg:city":"Javea",
    "sg:orig_category":"Supermercados Y Hipermercados",
    "sg:phone":"+34 965 79 28 60",
    "sg:postcode":"03730",
    "sg:province":"Alicante",
    "wof:name":"Juan Fornes Fornes S.a.",
    "wof:placetype":"venue"
},
  "geometry": {"coordinates":[0.1604788005,38.787940979],"type":"Point"}
}