{
  "type": "Feature",
  "properties": {
    "addr:full":"Avda Galicia, 34 Fonsagrada Lugo 27100",
    "addr:housenumber":"34",
    "addr:postcode":"27100",
    "addr:street":"Avda Galicia",
    "iso:country":"ES",
    "sg:address":"Avda Galicia, 34",
    "sg:city":"Fonsagrada",
    "sg:orig_category":"Ense\u00d1anza: Profesiones Art\u00cdsticas",
    "sg:phone":"+34 982 34 02 08",
    "sg:postcode":"27100",
    "sg:province":"Lugo",
    "wof:name":"Fernandez Gomez Manuel",
    "wof:placetype":"venue"
},
  "geometry": {"coordinates":[-7.0700750351,43.1256599426],"type":"Point"}
}