{
  "type": "Feature",
  "properties": {
    "addr:full":"Calle de Dulcinea, 1 Alcorcon Madrid 28921",
    "addr:housenumber":"1",
    "addr:postcode":"28921",
    "addr:street":"Calle De Dulcinea",
    "iso:country":"ES",
    "sg:address":"Calle de Dulcinea, 1",
    "sg:city":"Alcorcon",
    "sg:orig_category":"Peluquer\u00cdas, Peluquer\u00cda Mixta",
    "sg:phone":"+34 916 44 20 04",
    "sg:postcode":"28921",
    "sg:province":"Madrid",
    "wof:name":"Kokett Peluqueros C.b.",
    "wof:placetype":"venue"
},
  "geometry": {"coordinates":[-3.8282492161,40.3408279419],"type":"Point"}
}