{
  "type": "Feature",
  "properties": {
    "addr:full":"Cxon Fontevieita, 40 Quintela Pontevedra 36950",
    "addr:housenumber":"40",
    "addr:postcode":"36950",
    "addr:street":"Fontevieita",
    "iso:country":"ES",
    "sg:address":"Cxon Fontevieita, 40",
    "sg:city":"Quintela",
    "sg:orig_category":"Centros Empresariales",
    "sg:phone":"+34 986 31 13 35",
    "sg:postcode":"36950",
    "sg:province":"Pontevedra",
    "wof:name":"Jesus Portela Hijos S.l.",
    "wof:placetype":"venue"
},
  "geometry": {"coordinates":[-8.738442421,42.2772254944],"type":"Point"}
}