{
  "type": "Feature",
  "properties": {
    "iso:country":"ES",
    "sg:address":"Avda Madrid (de), 57",
    "sg:city":"Alcobendas",
    "sg:orig_category":"Quincaller\u00cda (al Por Menor)",
    "sg:phone":"+34 916 51 80 20",
    "sg:postcode":"28100",
    "sg:province":"Madrid",
    "wof:name":"Pe\u00f1a Fresnillo Marcial",
    "wof:placetype":"venue"
},
  "geometry": {"coordinates":[-3.6395850182,40.5515060425],"type":"Point"}
}