{
  "type": "Feature",
  "properties": {
    "addr:full":"Carrer de Cavallers, 76 Barcelona Barcelona 08034",
    "addr:housenumber":"76",
    "addr:postcode":"08034",
    "addr:street":"Carrer De Cavallers",
    "iso:country":"ES",
    "sg:address":"Carrer de Cavallers, 76",
    "sg:city":"Barcelona",
    "sg:orig_category":"Ingenier\u00cda, Centros De Estudios (diversos)",
    "sg:phone":"+34 932 06 01 69",
    "sg:postcode":"08034",
    "sg:province":"Barcelona",
    "wof:name":"Rubiralta Vilaseca Francisco",
    "wof:placetype":"venue"
},
  "geometry": {"coordinates":[2.1163570881,41.3940544128],"type":"Point"}
}