{
  "type": "Feature",
  "properties": {
    "addr:full":"Calle de Casas De Campos, 18 Malaga M\u00e1laga 29001",
    "addr:housenumber":"18",
    "addr:postcode":"29001",
    "addr:street":"Calle De Casas;Campos;Ma\u0301Laga",
    "iso:country":"ES",
    "sg:address":"Calle de Casas De Campos, 18",
    "sg:city":"Malaga",
    "sg:orig_category":"Asociaciones, Organismos Culturales Y Socioeducativos",
    "sg:phone":"+34 952 60 38 30",
    "sg:postcode":"29001",
    "sg:province":"M\u00e1laga",
    "wof:name":"Hermandad Antiguos Caballeros Legionarios",
    "wof:placetype":"venue"
},
  "geometry": {"coordinates":[-4.4234185219,36.7160797119],"type":"Point"}
}