{
  "type": "Feature",
  "properties": {
    "iso:country":"ES",
    "sg:address":"Luga Carrus Poligono Industrial, S/n",
    "sg:city":"Elche",
    "sg:orig_category":"Carnicer\u00cdas, Carnicer\u00cdas",
    "sg:phone":"+34 965 43 84 33",
    "sg:postcode":"03291",
    "sg:province":"Alicante",
    "wof:name":"Profesionales De La Carne Coop. V.",
    "wof:placetype":"venue"
},
  "geometry": {"coordinates":[-0.6765189767,38.2994346619],"type":"Point"}
}