{
  "type": "Feature",
  "properties": {
    "addr:full":"Kale Nagusia, 36 Zarautz Guip\u00f9zcoa 20800",
    "addr:housenumber":"36",
    "addr:postcode":"20800",
    "addr:street":"Kale Nagusia;Guipu\u0300Zcoa",
    "iso:country":"ES",
    "sg:address":"Kale Nagusia, 36",
    "sg:city":"Zarautz",
    "sg:orig_category":"Herboristas (al Por Menor)",
    "sg:phone":"+34 943 83 22 98",
    "sg:postcode":"20800",
    "sg:province":"Guip\u00f9zcoa",
    "wof:name":"Aguirrezabala Esnal Bego\u00f1a",
    "wof:placetype":"venue"
},
  "geometry": {"coordinates":[-2.1742637157,43.2856826782],"type":"Point"}
}