{
  "type": "Feature",
  "properties": {
    "iso:country":"ES",
    "sg:address":"Terracina, 12",
    "sg:city":"Garrapinillos",
    "sg:orig_category":"Asociaciones Y Clubs Deportivos",
    "sg:phone":"+34 976 46 09 09",
    "sg:postcode":"50197",
    "sg:province":"Zaragoza",
    "wof:name":"Bm Sportech S.a.",
    "wof:placetype":"venue"
},
  "geometry": {"coordinates":[-1.0269140005,41.6842803955],"type":"Point"}
}