{
  "type": "Feature",
  "properties": {
    "iso:country":"ES",
    "sg:address":"Av Pau Casals, 11",
    "sg:city":"Riudoms",
    "sg:orig_category":"Empresas De Carpinter\u00cda De Madera",
    "sg:phone":"+34 977 85 03 57",
    "sg:postcode":"43330",
    "sg:province":"Tarragona",
    "wof:name":"Pujol Panades Francesc Lluis",
    "wof:placetype":"venue"
},
  "geometry": {"coordinates":[1.054224968,41.1384391785],"type":"Point"}
}