{
  "type": "Feature",
  "properties": {
    "iso:country":"ES",
    "sg:address":"Ptge Salvador Espriu, 1",
    "sg:city":"Hospitalet Llobregat",
    "sg:orig_category":"Afiladoras, Pulidoras Y Bru\u00d1idoras",
    "sg:phone":"+34 932 23 56 92",
    "sg:postcode":"08908",
    "sg:province":"Barcelona",
    "wof:name":"Servicroma S.a.",
    "wof:placetype":"venue"
},
  "geometry": {"coordinates":[2.1280310154,41.3481826782],"type":"Point"}
}