{
  "type": "Feature",
  "properties": {
    "iso:country":"ES",
    "sg:address":"Carrer de Esperan\u00c7a (l'), 5",
    "sg:city":"Vic",
    "sg:orig_category":"Automatizaci\u00d3n De Procesos Industriales Y De Edificaci\u00d3n (estudios, Instalaci\u00d3n)",
    "sg:phone":"+34 938 86 60 92",
    "sg:postcode":"08500",
    "sg:province":"Barcelona",
    "wof:name":"E3a Technologies S. A.",
    "wof:placetype":"venue"
},
  "geometry": {"coordinates":[2.2550199032,41.9312210083],"type":"Point"}
}