{
  "type": "Feature",
  "properties": {
    "addr:full":"Av. San Ignacio, 4 Iru\u00f1a Navarra 31002",
    "addr:housenumber":"4",
    "addr:postcode":"31002",
    "addr:street":"Av. San Ignacio",
    "iso:country":"ES",
    "sg:address":"Av. San Ignacio, 4",
    "sg:city":"Iru\u00f1a",
    "sg:orig_category":"Marroquiner\u00cda (confecci\u00d3n)",
    "sg:phone":"+34 948 22 13 83",
    "sg:postcode":"31002",
    "sg:province":"Navarra",
    "wof:name":"Arrizabalaga Santos Felix",
    "wof:placetype":"venue"
},
  "geometry": {"coordinates":[-1.643301487,42.8153419495],"type":"Point"}
}