{
  "type": "Feature",
  "properties": {
    "iso:country":"ES",
    "sg:address":"Carrer de Jaume Huguet, 5",
    "sg:city":"Valls",
    "sg:orig_category":"Marroquiner\u00cda (confecci\u00d3n)",
    "sg:phone":"+34 977 60 07 26",
    "sg:postcode":"43800",
    "sg:province":"Tarragona",
    "wof:name":"Marti Gine Jose",
    "wof:placetype":"venue"
},
  "geometry": {"coordinates":[1.2505899668,41.2862319946],"type":"Point"}
}