{
  "type": "Feature",
  "properties": {
    "addr:full":"Avda Europa, 5 Fuenlabrada Madrid 28943",
    "addr:housenumber":"5",
    "addr:postcode":"28943",
    "addr:street":"Avda Europa",
    "iso:country":"ES",
    "sg:address":"Avda Europa, 5",
    "sg:city":"Fuenlabrada",
    "sg:orig_category":"Peluquer\u00cdas",
    "sg:phone":"+34 916 97 42 33",
    "sg:postcode":"28943",
    "sg:province":"Madrid",
    "wof:name":"Jimenez Gonzalez Iluminada",
    "wof:placetype":"venue"
},
  "geometry": {"coordinates":[-3.8048779964,40.2890853882],"type":"Point"}
}