{
  "type": "Feature",
  "properties": {
    "addr:full":"Pist Armada (da), S/n Xinzo De Limia Ourense 32630",
    "addr:postcode":"32630",
    "addr:street":"S / N",
    "iso:country":"ES",
    "sg:address":"Pist Armada (da), S/n",
    "sg:city":"Xinzo De Limia",
    "sg:orig_category":"Piedra Natural",
    "sg:phone":"+34 988 46 23 32",
    "sg:postcode":"32630",
    "sg:province":"Ourense",
    "wof:name":"Construcciones Milucho S.l.",
    "wof:placetype":"venue"
},
  "geometry": {"coordinates":[-7.7259440422,42.0631408691],"type":"Point"}
}