{
  "type": "Feature",
  "properties": {
    "addr:full":"Carr Darrera Sant Marti, 15 Lleida Lleida 25004",
    "addr:housenumber":"15",
    "addr:postcode":"25004",
    "addr:street":"Carr Darrera;Marti",
    "iso:country":"ES",
    "sg:address":"Carr Darrera Sant Marti, 15",
    "sg:city":"Lleida",
    "sg:orig_category":"Ingenier\u00cda, Centros De Estudios (diversos)",
    "sg:phone":"+34 973 24 86 31",
    "sg:postcode":"25004",
    "sg:province":"Lleida",
    "wof:name":"Imogep S.a.",
    "wof:placetype":"venue"
},
  "geometry": {"coordinates":[0.6236119866,41.6168861389],"type":"Point"}
}