{
  "type": "Feature",
  "properties": {
    "addr:full":"Avda Arces, 7 Madrid Madrid 28042",
    "addr:housenumber":"7",
    "addr:postcode":"madrid;28042",
    "addr:street":"Avda Arces",
    "iso:country":"ES",
    "sg:address":"Avda Arces, 7",
    "sg:city":"Madrid",
    "sg:orig_category":"Inversiones",
    "sg:phone":"+34 913 20 47 46",
    "sg:postcode":"28042",
    "sg:province":"Madrid",
    "wof:name":"Rosado Hernandez David Emilio",
    "wof:placetype":"venue"
},
  "geometry": {"coordinates":[-3.6173489094,40.4561386108],"type":"Point"}
}