{
  "type": "Feature",
  "properties": {
    "addr:full":"Calle de Zurbaran, S/n Cadrete Zaragoza 50420",
    "addr:housenumber":"s",
    "addr:postcode":"50420",
    "addr:street":"Calle De Zurbaran;/ N Cadrete",
    "iso:country":"ES",
    "sg:address":"Calle de Zurbaran, S/n",
    "sg:city":"Cadrete",
    "sg:orig_category":"Lacadores",
    "sg:phone":"+34 976 12 53 32",
    "sg:postcode":"50420",
    "sg:province":"Zaragoza",
    "wof:name":"Clemente Plou S.l",
    "wof:placetype":"venue"
},
  "geometry": {"coordinates":[-0.9675089717,41.5582389832],"type":"Point"}
}