{
  "type": "Feature",
  "properties": {
    "addr:full":"Calle de Juntas Generales, 18 Vitoria-gasteiz \u00c1lava 01010",
    "addr:housenumber":"18",
    "addr:postcode":"01010",
    "addr:street":"Calle De Juntas Generales",
    "iso:country":"ES",
    "sg:address":"Calle de Juntas Generales, 18",
    "sg:city":"Vitoria-gasteiz",
    "sg:orig_category":"Frutas, Legumbres Frescas Y Tempranas (al Por Menor)",
    "sg:phone":"+34 945 17 36 04",
    "sg:postcode":"01010",
    "sg:province":"\u00c1lava",
    "wof:name":"Frutas Zaranton S.l.",
    "wof:placetype":"venue"
},
  "geometry": {"coordinates":[-2.6998240948,42.8534507751],"type":"Point"}
}