{
  "type": "Feature",
  "properties": {
    "addr:full":"Pl Camprecios, 2 S. Just Desvern Barcelona 08960",
    "addr:housenumber":"2",
    "addr:postcode":"08960",
    "addr:street":"Pl Camprecios",
    "iso:country":"ES",
    "sg:address":"Pl Camprecios, 2",
    "sg:city":"S. Just Desvern",
    "sg:orig_category":"Asociaciones Y Clubs Deportivos",
    "sg:phone":"+34 933 72 82 53",
    "sg:postcode":"08960",
    "sg:province":"Barcelona",
    "wof:name":"Edson Esport S.l.",
    "wof:placetype":"venue"
},
  "geometry": {"coordinates":[2.0757000446,41.3850746155],"type":"Point"}
}