{
  "type": "Feature",
  "properties": {
    "addr:full":"Calle de General Serrano, 59 Santa Cruz De Tenerife Santa Cruz De Tenerife 38004",
    "addr:housenumber":"59",
    "addr:postcode":"38004",
    "addr:street":"Calle De General Serrano",
    "iso:country":"ES",
    "sg:address":"Calle de General Serrano, 59",
    "sg:city":"Santa Cruz De Tenerife",
    "sg:orig_category":"Asesor\u00cda De Formaci\u00d3n Y Gesti\u00d3n De Personal",
    "sg:phone":"+34 922 27 48 02",
    "sg:postcode":"38004",
    "sg:province":"Santa Cruz De Tenerife",
    "wof:name":"Perez Alvarez Hipolito",
    "wof:placetype":"venue"
},
  "geometry": {"coordinates":[-16.2598552704,28.4673309326],"type":"Point"}
}