{
  "type": "Feature",
  "properties": {
    "addr:full":"Calle de Rey Don Pelayo, 26 Roda Albacete 02630",
    "addr:housenumber":"26",
    "addr:postcode":"02630",
    "addr:street":"Calle De Rey Don Pelayo",
    "iso:country":"ES",
    "sg:address":"Calle de Rey Don Pelayo, 26",
    "sg:city":"Roda",
    "sg:orig_category":"Producci\u00d3n, Distribuci\u00d3n De Gas Butano Y Propano",
    "sg:phone":"+34 967 44 05 01",
    "sg:postcode":"02630",
    "sg:province":"Albacete",
    "wof:name":"Lopez Hortelano Jose",
    "wof:placetype":"venue"
},
  "geometry": {"coordinates":[-2.1608989239,39.2054786682],"type":"Point"}
}