{
  "type": "Feature",
  "properties": {
    "addr:full":"Calle de Luna (la), 6 Alcorcon Madrid 28922",
    "addr:postcode":"28922",
    "addr:street":"Calle De Luna La 6 Alcorcon",
    "iso:country":"ES",
    "sg:address":"Calle de Luna (la), 6",
    "sg:city":"Alcorcon",
    "sg:orig_category":"Peluqueros: De Se\u00d1oras",
    "sg:phone":"+34 916 41 36 88",
    "sg:postcode":"28922",
    "sg:province":"Madrid",
    "wof:name":"Perez Perez Juana",
    "wof:placetype":"venue"
},
  "geometry": {"coordinates":[-3.8254287243,40.3425865173],"type":"Point"}
}