{
  "type": "Feature",
  "properties": {
    "iso:country":"ES",
    "sg:address":"Calle de Antonia Ruiz, S/n",
    "sg:city":"Viso Marques",
    "sg:orig_category":"Ense\u00d1anza Secundaria: Colegios Y Escuelas Privadas",
    "sg:phone":"+34 926 33 72 10",
    "sg:postcode":"13770",
    "sg:province":"Ciudad Real",
    "wof:name":"Instituto De Ense\u00f1anza Secundaria Los Batanes",
    "wof:placetype":"venue"
},
  "geometry": {"coordinates":[-3.5642576218,38.5247917175],"type":"Point"}
}