{
  "type": "Feature",
  "properties": {
    "iso:country":"ES",
    "sg:address":"Calle de Irlanda, 112",
    "sg:city":"Monta\u00e7a Roja",
    "sg:orig_category":"Promotores Constructores",
    "sg:phone":"+34 928 51 85 69",
    "sg:postcode":"35580",
    "sg:province":"Las Palmas",
    "wof:name":"Atlantida Creaciones S.l",
    "wof:placetype":"venue"
},
  "geometry": {"coordinates":[-15.4300060272,28.1248226166],"type":"Point"}
}