{
  "type": "Feature",
  "properties": {
    "addr:full":"Calle de Alondra, 33 Madrid Madrid 28025",
    "addr:housenumber":"33",
    "addr:postcode":"madrid;28025",
    "addr:street":"Calle De Alondra",
    "iso:country":"ES",
    "sg:address":"Calle de Alondra, 33",
    "sg:city":"Madrid",
    "sg:orig_category":"Bisuter\u00cda, Joyer\u00cda, Relojer\u00cda (al Por Menor)",
    "sg:phone":"+34 914 62 18 11",
    "sg:postcode":"28025",
    "sg:province":"Madrid",
    "wof:name":"Ausin Del Moral German",
    "wof:placetype":"venue"
},
  "geometry": {"coordinates":[-3.7380669117,40.3879394531],"type":"Point"}
}