{
  "type": "Feature",
  "properties": {
    "iso:country":"ES",
    "sg:address":"Pg Eres De Santa Llucia, 3",
    "sg:city":"Elche",
    "sg:orig_category":"M\u00c9dicos: Cirug\u00cda General",
    "sg:phone":"+34 965 45 43 65",
    "sg:postcode":"03202",
    "sg:province":"Alicante",
    "wof:name":"Garcia Mi\u00f1ana Jose",
    "wof:placetype":"venue"
},
  "geometry": {"coordinates":[-0.6965721846,38.2676239014],"type":"Point"}
}