{
  "type": "Feature",
  "properties": {
    "iso:country":"ES",
    "sg:address":"Stmo. Cristo Salud, 55",
    "sg:city":"Vilamarxant",
    "sg:orig_category":"Asociaciones Y Clubs Deportivos",
    "sg:phone":"+34 962 71 23 89",
    "sg:postcode":"46191",
    "sg:province":"Valencia",
    "wof:name":"Palones Faus Salvador",
    "wof:placetype":"venue"
},
  "geometry": {"coordinates":[-0.6272540092,39.5677604675],"type":"Point"}
}