{
  "type": "Feature",
  "properties": {
    "addr:full":"Calle de Jose Maria Millares Sall, S/n Goro Las Palmas 35215",
    "addr:housenumber":"s / n",
    "addr:postcode":"35215",
    "addr:street":"Calle De Jose Maria Millares Sall",
    "iso:country":"ES",
    "sg:address":"Calle de Jose Maria Millares Sall, S/n",
    "sg:city":"Goro",
    "sg:orig_category":"Fabricaci\u00d3n, Importaci\u00d3n, Venta De Material De Telefon\u00cda, Peritelefon\u00cda",
    "sg:phone":"+34 928 70 03 56",
    "sg:postcode":"35215",
    "sg:province":"Las Palmas",
    "wof:name":"Vodafone Espa\u00d1a S.a.",
    "wof:placetype":"venue"
},
  "geometry": {"coordinates":[-15.394241333,27.9673309326],"type":"Point"}
}