{
  "type": "Feature",
  "properties": {
    "addr:full":"Carrer de Esglesia, 108 Calella Barcelona 08370",
    "addr:housenumber":"108",
    "addr:postcode":"08370",
    "addr:street":"Carrer De Esglesia",
    "iso:country":"ES",
    "sg:address":"Carrer de Esglesia, 108",
    "sg:city":"Calella",
    "sg:orig_category":"Hielo Artificial (fabricaci\u00d3n, Distribuci\u00d3n)",
    "sg:phone":"+34 937 69 28 95",
    "sg:postcode":"08370",
    "sg:province":"Barcelona",
    "wof:name":"Ferretti Dimension S.l.",
    "wof:placetype":"venue"
},
  "geometry": {"coordinates":[2.6611800194,41.6142807007],"type":"Point"}
}