{
  "type": "Feature",
  "properties": {
    "iso:country":"ES",
    "sg:address":"Avda Abaro, 1",
    "sg:city":"Portugalete",
    "sg:orig_category":"\u00d3ptica: Instrumentos (fabricaci\u00d3n)",
    "sg:phone":"+34 944 62 90 03",
    "sg:postcode":"48920",
    "sg:province":"Vizcaya",
    "wof:name":"Mutiozabal Martin Maria Del Carmen",
    "wof:placetype":"venue"
},
  "geometry": {"coordinates":[-3.0205230713,43.3209037781],"type":"Point"}
}