{
  "type": "Feature",
  "properties": {
    "iso:country":"ES",
    "sg:address":"Avda Faro De Mesa Roldan, 33",
    "sg:city":"Carboneras",
    "sg:orig_category":"Estudios Y Construcci\u00d3n De Acuarios Y Viveros",
    "sg:phone":"+34 950 13 06 91",
    "sg:postcode":"04140",
    "sg:province":"Almer\u00eda",
    "wof:name":"Framar S.l.",
    "wof:placetype":"venue"
},
  "geometry": {"coordinates":[-1.8956240416,36.9959602356],"type":"Point"}
}