{
  "type": "Feature",
  "properties": {
    "iso:country":"ES",
    "sg:address":"Calle de Ribadesella, 15",
    "sg:city":"Berzosa",
    "sg:orig_category":"Controles De Edificaci\u00d3n (construcci\u00d3n, Seguridad)",
    "sg:phone":"+34 918 56 97 20",
    "sg:postcode":"28248",
    "sg:province":"Madrid",
    "wof:name":"Heinpa S.l.",
    "wof:placetype":"venue"
},
  "geometry": {"coordinates":[-3.9413340092,40.6030082703],"type":"Point"}
}