{
  "type": "Feature",
  "properties": {
    "addr:full":"Calle de Jose Serrano, 11 Madrid Madrid 28053",
    "addr:housenumber":"11",
    "addr:postcode":"madrid;28053",
    "addr:street":"Calle De Jose Serrano",
    "iso:country":"ES",
    "sg:address":"Calle de Jose Serrano, 11",
    "sg:city":"Madrid",
    "sg:orig_category":"Farmacias",
    "sg:phone":"+34 914 77 60 48",
    "sg:postcode":"28053",
    "sg:province":"Madrid",
    "wof:name":"Lopez Gonzalez Jose Maria",
    "wof:placetype":"venue"
},
  "geometry": {"coordinates":[-3.6699459553,40.386844635],"type":"Point"}
}