{
  "type": "Feature",
  "properties": {
    "iso:country":"ES",
    "sg:address":"Carrer de Francesc Layret, 75",
    "sg:city":"Mollet Valles",
    "sg:orig_category":"Jardiner\u00cdas, Vegetales, Art\u00cdculos De Jardiner\u00cda (al Por Menor)",
    "sg:phone":"+34 935 79 03 77",
    "sg:postcode":"08100",
    "sg:province":"Barcelona",
    "sg:website":"jardinesporto.com",
    "wof:name":"Jardines P Porto S.l.",
    "wof:placetype":"venue"
},
  "geometry": {"coordinates":[2.203015089,41.5482139587],"type":"Point"}
}