{
  "type": "Feature",
  "properties": {
    "iso:country":"ES",
    "sg:address":"Calle de Ramon Perello, 3",
    "sg:city":"Union",
    "sg:orig_category":"Ense\u00d1anza Secundaria: Colegios Y Escuelas Privadas",
    "sg:phone":"+34 968 56 04 10",
    "sg:postcode":"30360",
    "sg:province":"Murcia",
    "wof:name":"Instituto De Bachillerato Maria Salcedo",
    "wof:placetype":"venue"
},
  "geometry": {"coordinates":[-0.879956007,37.6162109375],"type":"Point"}
}