{
  "type": "Feature",
  "properties": {
    "iso:country":"ES",
    "sg:address":"Rua Oliveira (da), 4",
    "sg:city":"Santiago De Compostela",
    "sg:orig_category":"Art\u00cdculos De Decoraci\u00d3n",
    "sg:phone":"+34 981 56 24 79",
    "sg:postcode":"15704",
    "sg:province":"A Coru\u00f1a",
    "wof:name":"Valois Calvo Jose Antonio",
    "wof:placetype":"venue"
},
  "geometry": {"coordinates":[-8.5406751633,42.881565094],"type":"Point"}
}