{
  "type": "Feature",
  "properties": {
    "addr:full":"Avda Nava, 2 Montijo Badajoz 06480",
    "addr:housenumber":"2",
    "addr:postcode":"06480",
    "addr:street":"Avda Nava",
    "iso:country":"ES",
    "sg:address":"Avda Nava, 2",
    "sg:city":"Montijo",
    "sg:orig_category":"Agencias Y Agentes Comerciales, Representantes",
    "sg:phone":"+34 924 45 08 62",
    "sg:postcode":"06480",
    "sg:province":"Badajoz",
    "wof:name":"Sierra Gomez Isabel",
    "wof:placetype":"venue"
},
  "geometry": {"coordinates":[-6.6064047813,38.9115333557],"type":"Point"}
}