{
  "type": "Feature",
  "properties": {
    "iso:country":"ES",
    "sg:address":"Calle de Concilio (del), 5",
    "sg:city":"Alcobendas",
    "sg:orig_category":"Farmacias",
    "sg:phone":"+34 916 51 71 12",
    "sg:postcode":"28100",
    "sg:province":"Madrid",
    "wof:name":"Torroja Bendito Maria Del Pilar",
    "wof:placetype":"venue"
},
  "geometry": {"coordinates":[-3.6361529827,40.5437164307],"type":"Point"}
}