{
  "type": "Feature",
  "properties": {
    "addr:full":"Praj Jotatell, S/n Macael Almer\u00eda 04867",
    "addr:housenumber":"s / n",
    "addr:postcode":"04867",
    "iso:country":"ES",
    "sg:address":"Praj Jotatell, S/n",
    "sg:city":"Macael",
    "sg:orig_category":"M\u00c1rmoles, Granitos Y Piedras Naturales",
    "sg:phone":"+34 950 12 80 64",
    "sg:postcode":"04867",
    "sg:province":"Almer\u00eda",
    "wof:name":"Marmoles Y Plaquetas S.l.",
    "wof:placetype":"venue"
},
  "geometry": {"coordinates":[-2.3024399281,37.3340568542],"type":"Point"}
}