{
  "type": "Feature",
  "properties": {
    "addr:full":"Calle de Santa Margarita, 20 Aranda Duero Burgos 09400",
    "addr:housenumber":"20",
    "addr:postcode":"09400",
    "addr:street":"Calle De Santa Margarita",
    "iso:country":"ES",
    "sg:address":"Calle de Santa Margarita, 20",
    "sg:city":"Aranda Duero",
    "sg:orig_category":"Enfermeras: Consultas, Atenci\u00d3n A Domicilio",
    "sg:phone":"+34 947 50 11 39",
    "sg:postcode":"09400",
    "sg:province":"Burgos",
    "wof:name":"Lopez Sanz Maximo",
    "wof:placetype":"venue"
},
  "geometry": {"coordinates":[-3.6889948845,41.6699256897],"type":"Point"}
}