{
  "type": "Feature",
  "properties": {
    "iso:country":"ES",
    "sg:address":"Avda Mirat, 36",
    "sg:city":"Salamanca",
    "sg:orig_category":"Art\u00cdculos De Regalo (al Por Menor)",
    "sg:phone":"+34 923 22 92 75",
    "sg:postcode":"37005",
    "sg:province":"Salamanca",
    "wof:name":"Martin Salgado Angela",
    "wof:placetype":"venue"
},
  "geometry": {"coordinates":[-5.6625571251,40.9699630737],"type":"Point"}
}