{
  "type": "Feature",
  "properties": {
    "iso:country":"ES",
    "sg:address":"Pase Virgen De Linarejos, 4",
    "sg:city":"Linares",
    "sg:orig_category":"Carnicer\u00cdas, Carnicer\u00cdas",
    "sg:phone":"+34 953 60 09 95",
    "sg:postcode":"23700",
    "sg:province":"Ja\u00e9n",
    "wof:name":"Salchicheria Extreme\u00d1a Garcia Hermanos S.l.",
    "wof:placetype":"venue"
},
  "geometry": {"coordinates":[-3.6323540211,38.0981941223],"type":"Point"}
}