{
  "type": "Feature",
  "properties": {
    "addr:full":"Av Antoni Maura, 146 Inca Islas Baleares 07300",
    "addr:housenumber":"146",
    "addr:postcode":"07300",
    "addr:street":"Av Antoni Maura",
    "iso:country":"ES",
    "sg:address":"Av Antoni Maura, 146",
    "sg:city":"Inca",
    "sg:orig_category":"Material Y Suministros Para Fotocopiadoras, Reprograf\u00cda",
    "sg:phone":"+34 971 50 23 61",
    "sg:postcode":"07300",
    "sg:province":"Islas Baleares",
    "wof:name":"Sistemas De Oficina Des Pla S. A.",
    "wof:placetype":"venue"
},
  "geometry": {"coordinates":[2.9023499489,39.7214889526],"type":"Point"}
}