{
  "type": "Feature",
  "properties": {
    "addr:full":"Carr Pizarro, 11 Vila Joiosa Alicante 03570",
    "addr:housenumber":"11",
    "addr:postcode":"03570",
    "addr:street":"Carr Pizarro",
    "iso:country":"ES",
    "sg:address":"Carr Pizarro, 11",
    "sg:city":"Vila Joiosa",
    "sg:orig_category":"Fotocopias, Reprograf\u00cda",
    "sg:phone":"+34 966 85 16 79",
    "sg:postcode":"03570",
    "sg:province":"Alicante",
    "wof:name":"Copylab La Vila C.b.",
    "wof:placetype":"venue"
},
  "geometry": {"coordinates":[-0.2327190042,38.505821228],"type":"Point"}
}