{
  "type": "Feature",
  "properties": {
    "iso:country":"ES",
    "sg:address":"Calle de Francisco Carrion Mejias, 4",
    "sg:city":"Sevilla",
    "sg:orig_category":"Peluquer\u00cdas, Peluquer\u00cda Mixta",
    "sg:phone":"+34 954 21 76 16",
    "sg:postcode":"41003",
    "sg:province":"Sevilla",
    "wof:name":"Romero Pizarro Josefa",
    "wof:placetype":"venue"
},
  "geometry": {"coordinates":[-5.9881248474,37.3924293518],"type":"Point"}
}