{
  "type": "Feature",
  "properties": {
    "iso:country":"ES",
    "sg:address":"Calle de Martinez Izquierdo, 82",
    "sg:city":"Madrid",
    "sg:orig_category":"Obras Y Organismos Sociales",
    "sg:phone":"+34 917 25 50 22",
    "sg:postcode":"28028",
    "sg:province":"Madrid",
    "wof:name":"Asociacion De Tecnicos Para El Desarrollo De Programas Sociales A.r.e.s.",
    "wof:placetype":"venue"
},
  "geometry": {"coordinates":[-3.6626195908,40.4352111816],"type":"Point"}
}