{
  "type": "Feature",
  "properties": {
    "addr:full":"Ctra. Yunclillos, 19 Recas Toledo 45211",
    "addr:housenumber":"19",
    "addr:postcode":"45211",
    "addr:street":"Ctra. Yunclillos",
    "iso:country":"ES",
    "sg:address":"Ctra. Yunclillos, 19",
    "sg:city":"Recas",
    "sg:orig_category":"Mec\u00c1nico Del Autom\u00d3vil",
    "sg:phone":"+34 925 52 26 57",
    "sg:postcode":"45211",
    "sg:province":"Toledo",
    "wof:name":"Talleres Diperauto S.l.",
    "wof:placetype":"venue"
},
  "geometry": {"coordinates":[-3.9833369255,40.0520896912],"type":"Point"}
}