{
  "type": "Feature",
  "properties": {
    "iso:country":"ES",
    "sg:address":"Calle de Cervantes, 16",
    "sg:city":"Zafra",
    "sg:orig_category":"Ense\u00d1anza: Profesiones Art\u00cdsticas",
    "sg:phone":"+34 924 55 21 22",
    "sg:postcode":"06300",
    "sg:province":"Badajoz",
    "wof:name":"Baena Encarnado Luis Fernando",
    "wof:placetype":"venue"
},
  "geometry": {"coordinates":[-6.4142837524,38.4230194092],"type":"Point"}
}