{
  "type": "Feature",
  "properties": {
    "iso:country":"ES",
    "sg:address":"Carr Valls D'andorra, 75",
    "sg:city":"Lleida",
    "sg:orig_category":"Contenedores (mercanc\u00cdas)",
    "sg:phone":"+34 973 22 86 14",
    "sg:postcode":"25005",
    "sg:province":"Lleida",
    "wof:name":"Endopack S.l.",
    "wof:placetype":"venue"
},
  "geometry": {"coordinates":[0.6204169989,41.6335983276],"type":"Point"}
}