{
  "type": "Feature",
  "properties": {
    "iso:country":"ES",
    "sg:address":"Calle de Piedra De Molino, 7",
    "sg:city":"Hoya Del Pedregal",
    "sg:orig_category":"Art\u00cdculos De Regalo (al Por Menor)",
    "sg:phone":"+34 928 55 80 92",
    "sg:postcode":"35457",
    "sg:province":"Las Palmas",
    "wof:name":"Rodriguez Melian Jose",
    "wof:placetype":"venue"
},
  "geometry": {"coordinates":[-15.6223421097,28.0842895508],"type":"Point"}
}