{
  "type": "Feature",
  "properties": {
    "iso:country":"ES",
    "sg:address":"Calle de Ledesma, 4",
    "sg:city":"Bilbao",
    "sg:orig_category":"Promotores Constructores",
    "sg:phone":"+34 944 24 66 46",
    "sg:postcode":"48001",
    "sg:province":"Vizcaya",
    "wof:name":"Promociones Inblam, S.l.",
    "wof:placetype":"venue"
},
  "geometry": {"coordinates":[-2.9269258976,43.2619667053],"type":"Point"}
}