{
  "type": "Feature",
  "properties": {
    "addr:full":"Carretera De Ponferrada-la Espina, 93 Ponferrada Le\u00f3n 24400",
    "addr:housenumber":"93",
    "addr:postcode":"24400",
    "addr:street":"Carretera De Ponferrada-La Espina",
    "iso:country":"ES",
    "sg:address":"Carretera De Ponferrada-la Espina, 93",
    "sg:city":"Ponferrada",
    "sg:orig_category":"Producci\u00d3n, Comercio De Cereales",
    "sg:phone":"+34 987 41 15 68",
    "sg:postcode":"24400",
    "sg:province":"Le\u00f3n",
    "wof:name":"Pedro Nu\u00d1ez Cabezas S.a.",
    "wof:placetype":"venue"
},
  "geometry": {"coordinates":[-6.5983390808,42.5483360291],"type":"Point"}
}