{
  "type": "Feature",
  "properties": {
    "addr:full":"Calle de Principe De Vergara, 282 Madrid Madrid 28016",
    "addr:housenumber":"282",
    "addr:postcode":"28016",
    "addr:street":"Calle De Principe De Vergara",
    "iso:country":"ES",
    "sg:address":"Calle de Principe De Vergara, 282",
    "sg:city":"Madrid",
    "sg:classifiers":[
        {
            "category":"Arts & Performance",
            "subcategory":"Art Gallery",
            "type":"Entertainment"
        }
    ],
    "sg:phone":"+34 913 59 94 15",
    "sg:postcode":"28016",
    "sg:province":"Madrid",
    "sg:tags":[
        "arte",
        "de",
        "galer\u00cdas"
    ],
    "wof:name":"Guerra Cauqui Isabel",
    "wof:placetype":"venue"
},
  "geometry": {"coordinates":[-3.6766190529,40.4602088928],"type":"Point"}
}