{
  "type": "Feature",
  "properties": {
    "addr:full":"Avda Condes De San Isidro, 45 Fuengirola M\u00e1laga 29640",
    "addr:housenumber":"45",
    "addr:postcode":"29640",
    "addr:street":"Avda Condes De San Isidro;Ma\u0301Laga",
    "iso:country":"ES",
    "sg:address":"Avda Condes De San Isidro, 45",
    "sg:city":"Fuengirola",
    "sg:orig_category":"Bancos",
    "sg:phone":"+34 952 58 45 85",
    "sg:postcode":"29640",
    "sg:province":"M\u00e1laga",
    "wof:name":"Deutsche Bank S.a.e.",
    "wof:placetype":"venue"
},
  "geometry": {"coordinates":[-4.6263790131,36.5349006653],"type":"Point"}
}