{
  "type": "Feature",
  "properties": {
    "addr:full":"Plaz Landabaso, 8 Bilbao Vizcaya 48015",
    "addr:housenumber":"8",
    "addr:postcode":"48015",
    "addr:street":"Plaz Landabaso",
    "iso:country":"ES",
    "sg:address":"Plaz Landabaso, 8",
    "sg:city":"Bilbao",
    "sg:orig_category":"Administradores De Bienes Y Delegados De Comunidades De Propietarios",
    "sg:phone":"+34 944 75 43 31",
    "sg:postcode":"48015",
    "sg:province":"Vizcaya",
    "wof:name":"Gloria De Jesus Garaizar Y Otros Cdad",
    "wof:placetype":"venue"
},
  "geometry": {"coordinates":[-2.9603993893,43.2744903564],"type":"Point"}
}