{
  "type": "Feature",
  "properties": {
    "addr:full":"Calle de Alcalde Lopez Casero, 2 Madrid Madrid 28027",
    "addr:housenumber":"2",
    "addr:postcode":"28027",
    "addr:street":"Calle De Alcalde Lopez Casero",
    "iso:country":"ES",
    "sg:address":"Calle de Alcalde Lopez Casero, 2",
    "sg:city":"Madrid",
    "sg:orig_category":"Zapatos (al Por Menor)",
    "sg:phone":"+34 914 04 03 75",
    "sg:postcode":"28027",
    "sg:province":"Madrid",
    "wof:name":"Chen Y Matteo 2003 S.l.",
    "wof:placetype":"venue"
},
  "geometry": {"coordinates":[-3.6553792953,40.4322013855],"type":"Point"}
}