{
  "type": "Feature",
  "properties": {
    "iso:country":"ES",
    "sg:address":"Calle de Pascual Arbos, 13",
    "sg:city":"Xirivella",
    "sg:orig_category":"Bisuter\u00cda, Joyer\u00cda, Relojer\u00cda (al Por Menor)",
    "sg:phone":"+34 963 70 90 27",
    "sg:postcode":"46950",
    "sg:province":"Valencia",
    "wof:name":"Perez Iniesta Jesus",
    "wof:placetype":"venue"
},
  "geometry": {"coordinates":[-0.4279569983,39.4656677246],"type":"Point"}
}