{
  "type": "Feature",
  "properties": {
    "addr:full":"Calle de Ines (la), 31 Arrecife Las Palmas 35500",
    "addr:housenumber":"31",
    "addr:postcode":"35500",
    "addr:street":"Calle De Ines La",
    "iso:country":"ES",
    "sg:address":"Calle de Ines (la), 31",
    "sg:city":"Arrecife",
    "sg:orig_category":"Alquiler De Veh\u00cdculos: Turismos Y Utilitarios",
    "sg:phone":"+34 928 81 03 52",
    "sg:postcode":"35500",
    "sg:province":"Las Palmas",
    "wof:name":"Juan Rocio Renta Car S.l.",
    "wof:placetype":"venue"
},
  "geometry": {"coordinates":[-13.5539646149,28.9606952667],"type":"Point"}
}