{
  "type": "Feature",
  "properties": {
    "iso:country":"ES",
    "sg:address":"Urb Alondra, S/n",
    "sg:city":"Salteras",
    "sg:orig_category":"Asociaciones, Organismos Culturales Y Socioeducativos",
    "sg:phone":"+34 955 71 91 86",
    "sg:postcode":"41909",
    "sg:province":"Sevilla",
    "wof:name":"Villarreal Cabrera Carmen",
    "wof:placetype":"venue"
},
  "geometry": {"coordinates":[-6.1336321831,37.4484596252],"type":"Point"}
}