{
  "type": "Feature",
  "properties": {
    "addr:full":"Carrer de Varsovia, 148 Barcelona Barcelona 08041",
    "addr:housenumber":"148",
    "addr:postcode":"08041",
    "addr:street":"Carrer De Varsovia",
    "iso:country":"ES",
    "sg:address":"Carrer de Varsovia, 148",
    "sg:city":"Barcelona",
    "sg:orig_category":"Carnicer\u00cdas, Carnicer\u00cdas",
    "sg:phone":"+34 934 36 09 19",
    "sg:postcode":"08041",
    "sg:province":"Barcelona",
    "wof:name":"Santafe Gasco Maria Teresa",
    "wof:placetype":"venue"
},
  "geometry": {"coordinates":[2.1726028919,41.4185829163],"type":"Point"}
}