{
  "type": "Feature",
  "properties": {
    "addr:full":"Calle de Iturrigorri, 1 Getxo Vizcaya 48930",
    "addr:housenumber":"1",
    "addr:postcode":"48930",
    "addr:street":"Calle De Iturrigorri",
    "iso:country":"ES",
    "sg:address":"Calle de Iturrigorri, 1",
    "sg:city":"Getxo",
    "sg:orig_category":"Forjas Y Altos Hornos",
    "sg:phone":"+34 944 63 08 49",
    "sg:postcode":"48930",
    "sg:province":"Vizcaya",
    "wof:name":"Alfonso Jimenez Gonzalez",
    "wof:placetype":"venue"
},
  "geometry": {"coordinates":[-3.0137987137,43.3272819519],"type":"Point"}
}