{
  "type": "Feature",
  "properties": {
    "addr:full":"Calle de Gervasio Artigas, 1 Zaragoza Zaragoza 50017",
    "addr:housenumber":"1",
    "addr:postcode":"50017",
    "addr:street":"Calle De Gervasio Artigas",
    "iso:country":"ES",
    "sg:address":"Calle de Gervasio Artigas, 1",
    "sg:city":"Zaragoza",
    "sg:classifiers":[
        {
            "category":"Personal",
            "subcategory":"Barber",
            "type":"Services"
        }
    ],
    "sg:phone":"+34 976 53 77 34",
    "sg:postcode":"50017",
    "sg:province":"Zaragoza",
    "sg:tags":[
        "caballeros",
        "de",
        "peluqueros"
    ],
    "wof:name":"Casta\u00f1o Palomo Javier",
    "wof:placetype":"venue"
},
  "geometry": {"coordinates":[-0.9171950221,41.6478691101],"type":"Point"}
}