{
  "type": "Feature",
  "properties": {
    "iso:country":"ES",
    "sg:address":"Calle de Poeta Llorente, 14",
    "sg:city":"Pobla Vallbona",
    "sg:orig_category":"Frutas Y Legumbres Frescas (al Por Mayor)",
    "sg:phone":"+34 962 76 00 11",
    "sg:postcode":"46185",
    "sg:province":"Valencia",
    "wof:name":"Cebollas Consuay S.l.",
    "wof:placetype":"venue"
},
  "geometry": {"coordinates":[-0.5533660054,39.5927009583],"type":"Point"}
}