{
  "type": "Feature",
  "properties": {
    "iso:country":"ES",
    "sg:address":"Carr De Sant Francesc, 130",
    "sg:city":"Benicarlo",
    "sg:orig_category":"Mec\u00c1nico Del Autom\u00d3vil",
    "sg:phone":"+34 964 46 14 71",
    "sg:postcode":"12580",
    "sg:province":"Castell\u00f3n",
    "wof:name":"Auto Sajusa S.l.",
    "wof:placetype":"venue"
},
  "geometry": {"coordinates":[0.4186243117,40.422000885],"type":"Point"}
}