{
  "type": "Feature",
  "properties": {
    "iso:country":"ES",
    "sg:address":"Carr Carretera De Lliria, 102",
    "sg:city":"Burjassot",
    "sg:orig_category":"Loter\u00cda Y T\u00d3mbola",
    "sg:phone":"+34 963 63 30 77",
    "sg:postcode":"46100",
    "sg:province":"Valencia",
    "wof:name":"Lazaro Miro Aurelio",
    "wof:placetype":"venue"
},
  "geometry": {"coordinates":[-0.4105490148,39.5093688965],"type":"Point"}
}