{
  "type": "Feature",
  "properties": {
    "iso:country":"ES",
    "sg:address":"Carrer de Ruiz De Padron, 97",
    "sg:city":"Barcelona",
    "sg:orig_category":"Supermercados Y Hipermercados",
    "sg:phone":"+34 933 52 33 29",
    "sg:postcode":"08026",
    "sg:province":"Barcelona",
    "wof:name":"Garciz S. A.",
    "wof:placetype":"venue"
},
  "geometry": {"coordinates":[2.1848011017,41.4164085388],"type":"Point"}
}