{
  "type": "Feature",
  "properties": {
    "addr:full":"Avda Castilla, 1 Antilla Huelva 21449",
    "addr:housenumber":"1",
    "addr:postcode":"21449",
    "addr:street":"Avda Castilla",
    "iso:country":"ES",
    "sg:address":"Avda Castilla, 1",
    "sg:city":"Antilla",
    "sg:orig_category":"Papeler\u00cdas, Librer\u00cdas",
    "sg:phone":"+34 959 48 13 80",
    "sg:postcode":"21449",
    "sg:province":"Huelva",
    "wof:name":"Bello Sanchez Angel",
    "wof:placetype":"venue"
},
  "geometry": {"coordinates":[-7.2176141739,37.2065467834],"type":"Point"}
}