{
  "type": "Feature",
  "properties": {
    "addr:full":"Avda Doctor Gregorio Mara\u00d1on, 79 Torrevieja Alicante 03180",
    "addr:housenumber":"79",
    "addr:postcode":"03180",
    "addr:street":"Avda Doctor Gregorio Maran\u0303On",
    "iso:country":"ES",
    "sg:address":"Avda Doctor Gregorio Mara\u00d1on, 79",
    "sg:city":"Torrevieja",
    "sg:orig_category":"Promotores Constructores",
    "sg:phone":"+34 965 71 77 71",
    "sg:postcode":"03180",
    "sg:province":"Alicante",
    "wof:name":"Promociones Y Construcciones Prisma S.a.",
    "wof:placetype":"venue"
},
  "geometry": {"coordinates":[-0.684607029,37.9756202698],"type":"Point"}
}