{
  "type": "Feature",
  "properties": {
    "iso:country":"ES",
    "sg:address":"Calle de Serrano Alcazar, 3",
    "sg:city":"San Miguel",
    "sg:orig_category":"Transportes Internacionales",
    "sg:phone":"+34 968 22 23 22",
    "sg:postcode":"30001",
    "sg:province":"Murcia",
    "wof:name":"Transalliance S.l.",
    "wof:placetype":"venue"
},
  "geometry": {"coordinates":[-1.1300630569,37.9868545532],"type":"Point"}
}