{
  "type": "Feature",
  "properties": {
    "addr:full":"Calle de Matilde Hernandez, 66 Madrid Madrid 28025",
    "addr:housenumber":"66",
    "addr:postcode":"madrid;28025",
    "addr:street":"Calle De Matilde Hernandez",
    "iso:country":"ES",
    "sg:address":"Calle de Matilde Hernandez, 66",
    "sg:city":"Madrid",
    "sg:orig_category":"Molduras, Junquillos, Listones Y Molduras Perforadas",
    "sg:phone":"+34 914 61 05 91",
    "sg:postcode":"28025",
    "sg:province":"Madrid",
    "wof:name":"Diaz Garcia Ventura",
    "wof:placetype":"venue"
},
  "geometry": {"coordinates":[-3.7350680828,40.3892784119],"type":"Point"}
}