{
  "type": "Feature",
  "properties": {
    "addr:full":"Pase Direccion, 11 Madrid Madrid 28039",
    "addr:housenumber":"11",
    "addr:postcode":"madrid;28039",
    "iso:country":"ES",
    "sg:address":"Pase Direccion, 11",
    "sg:city":"Madrid",
    "sg:orig_category":"Aparatos, Sistemas De Tele",
    "sg:phone":"+34 914 50 27 60",
    "sg:postcode":"28039",
    "sg:province":"Madrid",
    "wof:name":"Sistemas De Seguridad Deteccion Y Extinc",
    "wof:placetype":"venue"
},
  "geometry": {"coordinates":[-3.7094600201,40.4579391479],"type":"Point"}
}