{
  "type": "Feature",
  "properties": {
    "addr:full":"Calle de Calvo Sotelo, 13 Figueruelas Zaragoza 50639",
    "addr:housenumber":"13",
    "addr:postcode":"50639",
    "addr:street":"Calle De Calvo Sotelo",
    "iso:country":"ES",
    "sg:address":"Calle de Calvo Sotelo, 13",
    "sg:city":"Figueruelas",
    "sg:orig_category":"Cajas Para Embalar",
    "sg:phone":"+34 976 65 55 80",
    "sg:postcode":"50639",
    "sg:province":"Zaragoza",
    "wof:name":"Caja Rural De Aragon S.coop Credito",
    "wof:placetype":"venue"
},
  "geometry": {"coordinates":[-1.1749663353,41.7662811279],"type":"Point"}
}