{
  "type": "Feature",
  "properties": {
    "iso:country":"ES",
    "sg:address":"Calle de Gil De Santiva\u00d1es, 5",
    "sg:city":"Madrid",
    "sg:orig_category":"Art\u00cdculos De Decoraci\u00d3n",
    "sg:phone":"+34 915 76 83 02",
    "sg:postcode":"28001",
    "sg:province":"Madrid",
    "sg:website":"www.kawayan-budgi.com.es",
    "wof:name":"Kawayan 99 S.l.",
    "wof:placetype":"venue"
},
  "geometry": {"coordinates":[-3.689043045,40.4224662781],"type":"Point"}
}