{
  "type": "Feature",
  "properties": {
    "addr:full":"Calle de Milagrosa, 30 Valencia Valencia 46009",
    "addr:housenumber":"30",
    "addr:postcode":"46009",
    "addr:street":"Calle De Milagrosa",
    "iso:country":"ES",
    "sg:address":"Calle de Milagrosa, 30",
    "sg:city":"Valencia",
    "sg:orig_category":"Bordado, Marcado A Medida",
    "sg:phone":"+34 963 65 62 66",
    "sg:postcode":"46009",
    "sg:province":"Valencia",
    "wof:name":"Moreno Ruiz Teresa",
    "wof:placetype":"venue"
},
  "geometry": {"coordinates":[-0.3731890023,39.4848594666],"type":"Point"}
}