{
  "type": "Feature",
  "properties": {
    "addr:full":"Avda Valentin Andres, 11 Grado Asturias 33820",
    "addr:housenumber":"11",
    "addr:postcode":"33820",
    "addr:street":"Avda Valentin Andres",
    "iso:country":"ES",
    "sg:address":"Avda Valentin Andres, 11",
    "sg:city":"Grado",
    "sg:orig_category":"Empresas De Limpieza",
    "sg:phone":"+34 985 75 31 13",
    "sg:postcode":"33820",
    "sg:province":"Asturias",
    "wof:name":"La Moscona S.coop.",
    "wof:placetype":"venue"
},
  "geometry": {"coordinates":[-6.0673890114,43.3921089172],"type":"Point"}
}