{
  "type": "Feature",
  "properties": {
    "addr:full":"Avda Martin Palomino, S/n Plasencia C\u00e1ceres 10600",
    "addr:housenumber":"s / n",
    "addr:postcode":"10600",
    "addr:street":"Avda Martin Palomino;Ca\u0301Ceres",
    "iso:country":"ES",
    "sg:address":"Avda Martin Palomino, S/n",
    "sg:city":"Plasencia",
    "sg:orig_category":"Supermercados Y Hipermercados",
    "sg:phone":"+34 927 42 25 40",
    "sg:postcode":"10600",
    "sg:province":"C\u00e1ceres",
    "sg:website":"www.aldi.com",
    "wof:name":"Aldi Pinto Supermercados S.l.",
    "wof:placetype":"venue"
},
  "geometry": {"coordinates":[-6.1079235077,40.0117225647],"type":"Point"}
}