{
  "type": "Feature",
  "properties": {
    "iso:country":"ES",
    "sg:address":"Cmno Cabaldos, 37",
    "sg:city":"Zaragoza",
    "sg:orig_category":"Molduras, Junquillos, Listones Y Molduras Perforadas",
    "sg:phone":"+34 976 42 23 21",
    "sg:postcode":"50013",
    "sg:province":"Zaragoza",
    "wof:name":"Garcia Calvo Ernesto",
    "wof:placetype":"venue"
},
  "geometry": {"coordinates":[-0.8687160015,41.6392707825],"type":"Point"}
}