{
  "type": "Feature",
  "properties": {
    "iso:country":"ES",
    "sg:address":"Avgd Doctor Fleming, 45",
    "sg:city":"Lleida",
    "sg:orig_category":"Lavado, Limpieza De Veh\u00cdculos",
    "sg:phone":"+34 973 26 83 04",
    "sg:postcode":"25006",
    "sg:province":"Lleida",
    "wof:name":"Super Tren De Lavado Lleida S.l.",
    "wof:placetype":"venue"
},
  "geometry": {"coordinates":[0.6132339835,41.6205406189],"type":"Point"}
}