{
  "type": "Feature",
  "properties": {
    "iso:country":"ES",
    "sg:address":"Avda Constitucion (de La), 39",
    "sg:city":"Mostoles",
    "sg:orig_category":"Inmobiliaria (agencias)",
    "sg:phone":"+34 916 13 96 62",
    "sg:postcode":"28931",
    "sg:province":"Madrid",
    "wof:name":"Jupiter 2000",
    "wof:placetype":"venue"
},
  "geometry": {"coordinates":[-3.8618481159,40.3260154724],"type":"Point"}
}