{
  "type": "Feature",
  "properties": {
    "addr:full":"Plz S Nevada, S/n Guadix Granada 18500",
    "addr:postcode":"18500",
    "addr:street":"Plz S Nevada S / N",
    "iso:country":"ES",
    "sg:address":"Plz S Nevada, S/n",
    "sg:city":"Guadix",
    "sg:orig_category":"Guarder\u00cdas",
    "sg:phone":"+34 958 66 61 06",
    "sg:postcode":"18500",
    "sg:province":"Granada",
    "wof:name":"Martinez Balinot Pedro",
    "wof:placetype":"venue"
},
  "geometry": {"coordinates":[-3.1343688965,37.303894043],"type":"Point"}
}