{
  "type": "Feature",
  "properties": {
    "iso:country":"ES",
    "sg:address":"Calle de Pilar (el), 20",
    "sg:city":"Santa Cruz De Tenerife",
    "sg:orig_category":"Ropa Para Se\u00d1oras (al Por Menor)",
    "sg:phone":"+34 922 29 66 63",
    "sg:postcode":"38002",
    "sg:province":"Santa Cruz De Tenerife",
    "sg:website":"www.etxartpanno.com",
    "wof:name":"Pequpe C.b.",
    "wof:placetype":"venue"
},
  "geometry": {"coordinates":[-16.2519226074,28.4692516327],"type":"Point"}
}