{
  "type": "Feature",
  "properties": {
    "addr:full":"Calle de Algatocin, 11 Jubrique M\u00e1laga 29492",
    "addr:housenumber":"11",
    "addr:postcode":"29492",
    "addr:street":"Calle De Algatocin",
    "iso:country":"ES",
    "sg:address":"Calle de Algatocin, 11",
    "sg:city":"Jubrique",
    "sg:orig_category":"Negocio De Madera",
    "sg:phone":"+34 952 15 22 51",
    "sg:postcode":"29492",
    "sg:province":"M\u00e1laga",
    "wof:name":"Mateo Del Rio Juan",
    "wof:placetype":"venue"
},
  "geometry": {"coordinates":[-5.2175173759,36.5640335083],"type":"Point"}
}