{
  "type": "Feature",
  "properties": {
    "addr:full":"Calle de Cardenal Xavierre, 22 Zaragoza Zaragoza 50011",
    "addr:housenumber":"22",
    "addr:postcode":"50011",
    "addr:street":"Calle De Cardenal Xavierre",
    "iso:country":"ES",
    "sg:address":"Calle de Cardenal Xavierre, 22",
    "sg:city":"Zaragoza",
    "sg:orig_category":"Artesan\u00cda",
    "sg:phone":"+34 976 32 77 35",
    "sg:postcode":"50011",
    "sg:province":"Zaragoza",
    "wof:name":"Laporta Samitier Juan Carlos",
    "wof:placetype":"venue"
},
  "geometry": {"coordinates":[-0.9277907014,41.6536827087],"type":"Point"}
}