{
  "type": "Feature",
  "properties": {
    "addr:full":"Pol Ind Torrubero, S/n Museros Valencia 46136",
    "addr:housenumber":"s / n",
    "addr:postcode":"46136",
    "iso:country":"ES",
    "sg:address":"Pol Ind Torrubero, S/n",
    "sg:city":"Museros",
    "sg:orig_category":"Metales (labores, Pulido)",
    "sg:phone":"+34 961 44 36 61",
    "sg:postcode":"46136",
    "sg:province":"Valencia",
    "wof:name":"Metama S.l.",
    "wof:placetype":"venue"
},
  "geometry": {"coordinates":[-0.3349789977,39.5633239746],"type":"Point"}
}