{
  "type": "Feature",
  "properties": {
    "iso:country":"ES",
    "sg:address":"Calle de Don Jaime Sanz, 20",
    "sg:city":"Pe\u00f1iscola",
    "sg:orig_category":"Comercio De Cuadros, L\u00c1minas Y Reproducciones De Obras De Arte",
    "sg:phone":"+34 964 48 00 47",
    "sg:postcode":"12598",
    "sg:province":"Castell\u00f3n",
    "wof:name":"Sanchez Perez Maria Victoria",
    "wof:placetype":"venue"
},
  "geometry": {"coordinates":[0.4078533947,40.3578796387],"type":"Point"}
}