{
  "type": "Feature",
  "properties": {
    "iso:country":"ES",
    "sg:address":"Avda Leon, 1",
    "sg:city":"Santovenia Valdoncina",
    "sg:orig_category":"Molduras, Junquillos, Listones Y Molduras Perforadas",
    "sg:phone":"+34 987 28 04 21",
    "sg:postcode":"24391",
    "sg:province":"Le\u00f3n",
    "wof:name":"Peixeiro Costa Demetrio",
    "wof:placetype":"venue"
},
  "geometry": {"coordinates":[-5.624478817,42.5425567627],"type":"Point"}
}