{
  "type": "Feature",
  "properties": {
    "iso:country":"ES",
    "sg:address":"Carr Raval Del Castell, S/n",
    "sg:city":"Corbins",
    "sg:orig_category":"Aguas (distribuci\u00d3n, Servicios)",
    "sg:phone":"+34 973 19 10 95",
    "sg:postcode":"25137",
    "sg:province":"Lleida",
    "wof:name":"Companyia D'aigues De Sabadell S.a.",
    "wof:placetype":"venue"
},
  "geometry": {"coordinates":[0.6906549931,41.6874809265],"type":"Point"}
}