{
  "type": "Feature",
  "properties": {
    "addr:full":"Calle de Fenelon, 16 Madrid Madrid 28022",
    "addr:housenumber":"16",
    "addr:postcode":"madrid;28022",
    "addr:street":"Calle De Fenelon",
    "iso:country":"ES",
    "sg:address":"Calle de Fenelon, 16",
    "sg:city":"Madrid",
    "sg:orig_category":"Peluqueros: De Se\u00d1oras",
    "sg:phone":"+34 917 42 32 55",
    "sg:postcode":"28022",
    "sg:province":"Madrid",
    "wof:name":"Saez Lopez Sonsoles",
    "wof:placetype":"venue"
},
  "geometry": {"coordinates":[-3.6096138954,40.4378700256],"type":"Point"}
}