{
  "type": "Feature",
  "properties": {
    "addr:full":"Carrer de Montseny, 23 Santa Perpetua De Mogoda Barcelona 08130",
    "addr:housenumber":"23",
    "addr:postcode":"08130",
    "addr:street":"Carrer De Montseny",
    "iso:country":"ES",
    "sg:address":"Carrer de Montseny, 23",
    "sg:city":"Santa Perpetua De Mogoda",
    "sg:orig_category":"Cajas De Ahorro",
    "sg:phone":"+34 935 60 19 63",
    "sg:postcode":"08130",
    "sg:province":"Barcelona",
    "wof:name":"Caixa De Estalvis De Manresa",
    "wof:placetype":"venue"
},
  "geometry": {"coordinates":[2.1819601059,41.5345993042],"type":"Point"}
}