{
  "type": "Feature",
  "properties": {
    "addr:full":"Carrer de Girona, 65 Barcelona Barcelona 08009",
    "addr:housenumber":"65",
    "addr:postcode":"08009",
    "addr:street":"Carrer De Girona",
    "iso:country":"ES",
    "sg:address":"Carrer de Girona, 65",
    "sg:city":"Barcelona",
    "sg:orig_category":"Abogados",
    "sg:phone":"+34 934 87 42 14",
    "sg:postcode":"08009",
    "sg:province":"Barcelona",
    "wof:name":"Martin Martin Antonio",
    "wof:placetype":"venue"
},
  "geometry": {"coordinates":[2.1713819504,41.3944396973],"type":"Point"}
}