{
  "type": "Feature",
  "properties": {
    "iso:country":"ES",
    "sg:address":"Carrer de Alfons Xii, 17",
    "sg:city":"Barcelona",
    "sg:orig_category":"Promotores Constructores",
    "sg:phone":"+34 932 09 05 20",
    "sg:postcode":"08006",
    "sg:province":"Barcelona",
    "wof:name":"Promocion Construccion Y Venta De Edificios S.a.",
    "wof:placetype":"venue"
},
  "geometry": {"coordinates":[2.1499381065,41.3980293274],"type":"Point"}
}