{
  "type": "Feature",
  "properties": {
    "iso:country":"ES",
    "sg:address":"Ptge Pere Serra, 6",
    "sg:city":"Sabadell",
    "sg:orig_category":"Empresas De Portes Y Mensajer\u00cda",
    "sg:phone":"+34 937 15 53 61",
    "sg:postcode":"08205",
    "sg:province":"Barcelona",
    "sg:website":"www.topvalles.com",
    "wof:name":"Top Valles Express S.l.",
    "wof:placetype":"venue"
},
  "geometry": {"coordinates":[2.0952379704,41.540725708],"type":"Point"}
}