{
  "type": "Feature",
  "properties": {
    "iso:country":"ES",
    "sg:address":"Pl Ramon Llull, D'en, 12",
    "sg:city":"Manacor",
    "sg:orig_category":"M\u00c9dicos: Estomatolog\u00cda",
    "sg:phone":"+34 971 55 43 85",
    "sg:postcode":"07500",
    "sg:province":"Islas Baleares",
    "wof:name":"Diego Gomila Juan Francisco",
    "wof:placetype":"venue"
},
  "geometry": {"coordinates":[3.2118420601,39.5671157837],"type":"Point"}
}