{
  "type": "Feature",
  "properties": {
    "iso:country":"ES",
    "sg:address":"Calle de Buenos Aires, 14",
    "sg:city":"Linea De La Concepcion",
    "sg:orig_category":"Asociaciones Y Clubs Deportivos",
    "sg:phone":"+34 956 17 61 22",
    "sg:postcode":"11300",
    "sg:province":"C\u00e1diz",
    "wof:name":"Duarte Perez Francisco",
    "wof:placetype":"venue"
},
  "geometry": {"coordinates":[-5.3537898064,36.1641159058],"type":"Point"}
}