{
  "type": "Feature",
  "properties": {
    "iso:country":"ES",
    "sg:address":"Via Augusta, 188",
    "sg:city":"Barcelona",
    "sg:orig_category":"Agentes, Concesionarios Y Sucursales De Veh\u00cdculos",
    "sg:phone":"+34 932 00 90 00",
    "sg:postcode":"08021",
    "sg:province":"Barcelona",
    "sg:website":"www.autosaenz.es",
    "wof:name":"Auto Saenz S. A.",
    "wof:placetype":"venue"
},
  "geometry": {"coordinates":[2.1417360306,41.398399353],"type":"Point"}
}