{
  "type": "Feature",
  "properties": {
    "iso:country":"ES",
    "sg:address":"Can Vilanrosa, S/n",
    "sg:city":"Clariana Cardener",
    "sg:orig_category":"Cr\u00cda De Animales",
    "sg:phone":"+34 973 29 91 95",
    "sg:postcode":"25290",
    "sg:province":"Lleida",
    "wof:name":"Nova Genetica S.a.",
    "wof:placetype":"venue"
},
  "geometry": {"coordinates":[1.5639150143,41.9418334961],"type":"Point"}
}