{
  "type": "Feature",
  "properties": {
    "iso:country":"ES",
    "sg:address":"Conde Superunda, 1",
    "sg:city":"Priego Cordoba",
    "sg:orig_category":"Organismos De Turismo",
    "sg:phone":"+34 957 54 38 05",
    "sg:postcode":"14800",
    "sg:province":"C\u00f3rdoba",
    "wof:name":"Sural S.l.",
    "wof:placetype":"venue"
},
  "geometry": {"coordinates":[-4.196243763,37.4395446777],"type":"Point"}
}