{
  "type": "Feature",
  "properties": {
    "addr:full":"Carr Sant Gregori, 128 Girona Girona 17007",
    "addr:housenumber":"128",
    "addr:postcode":"17007",
    "addr:street":"Carr Sant Gregori",
    "iso:country":"ES",
    "sg:address":"Carr Sant Gregori, 128",
    "sg:city":"Girona",
    "sg:orig_category":"Artes Gr\u00c1ficas, Artes Pl\u00c1sticas (curso)",
    "sg:phone":"+34 972 21 79 74",
    "sg:postcode":"17007",
    "sg:province":"Girona",
    "wof:name":"Alquicam S.l.",
    "wof:placetype":"venue"
},
  "geometry": {"coordinates":[2.8063154221,41.9923286438],"type":"Point"}
}