{
  "type": "Feature",
  "properties": {
    "iso:country":"ES",
    "sg:address":"Calle de Conchas, 1",
    "sg:city":"Madrid",
    "sg:orig_category":"Librer\u00cdas",
    "sg:phone":"+34 915 48 26 30",
    "sg:postcode":"28013",
    "sg:province":"Madrid",
    "wof:name":"Alcantarilla Gil Pedro",
    "wof:placetype":"venue"
},
  "geometry": {"coordinates":[-3.7074654102,40.4190711975],"type":"Point"}
}