{
  "type": "Feature",
  "properties": {
    "addr:full":"Calle de Frailes, 23 Cortegana Huelva 21230",
    "addr:housenumber":"23",
    "addr:postcode":"21230",
    "addr:street":"Calle De Frailes",
    "iso:country":"ES",
    "sg:address":"Calle de Frailes, 23",
    "sg:city":"Cortegana",
    "sg:orig_category":"Doctores En Medicina",
    "sg:phone":"+34 959 13 12 24",
    "sg:postcode":"21230",
    "sg:province":"Huelva",
    "wof:name":"Bermejo Perez Antonio",
    "wof:placetype":"venue"
},
  "geometry": {"coordinates":[-6.8191318512,37.9098701477],"type":"Point"}
}