{
  "type": "Feature",
  "properties": {
    "addr:full":"Calle de Fuentelviejo, 46 Madrid Madrid 28022",
    "addr:housenumber":"46",
    "addr:postcode":"madrid;28022",
    "addr:street":"Calle De Fuentelviejo",
    "iso:country":"ES",
    "sg:address":"Calle de Fuentelviejo, 46",
    "sg:city":"Madrid",
    "sg:orig_category":"Fabricaci\u00d3n De Sobres, Bolsas Y Fundas",
    "sg:phone":"+34 917 47 24 22",
    "sg:postcode":"28022",
    "sg:province":"Madrid",
    "wof:name":"Lafuente Giner Francisco",
    "wof:placetype":"venue"
},
  "geometry": {"coordinates":[-3.5674834251,40.4483528137],"type":"Point"}
}