{
  "type": "Feature",
  "properties": {
    "addr:full":"Aeropuerto Tenerife Sur, S/n San Isidro Santa Cruz De Tenerife 38611",
    "addr:housenumber":"s / n",
    "addr:postcode":"38611",
    "iso:country":"ES",
    "sg:address":"Aeropuerto Tenerife Sur, S/n",
    "sg:city":"San Isidro",
    "sg:orig_category":"Transportes A\u00c9reos",
    "sg:phone":"+34 922 39 22 96",
    "sg:postcode":"38611",
    "sg:province":"Santa Cruz De Tenerife",
    "wof:name":"Deuxmilles Zoll I Transport S.l.",
    "wof:placetype":"venue"
},
  "geometry": {"coordinates":[-16.5577411652,28.0779342651],"type":"Point"}
}