{
  "type": "Feature",
  "properties": {
    "iso:country":"ES",
    "sg:address":"Calle de San Sebastian, 48",
    "sg:city":"Caniles",
    "sg:orig_category":"Supermercados Y Hipermercados",
    "sg:phone":"+34 958 71 01 75",
    "sg:postcode":"18810",
    "sg:province":"Granada",
    "wof:name":"Carrillo Fernandez Francisco",
    "wof:placetype":"venue"
},
  "geometry": {"coordinates":[-2.7236020565,37.4346008301],"type":"Point"}
}