{
  "type": "Feature",
  "properties": {
    "iso:country":"ES",
    "sg:address":"Estafeta, 15",
    "sg:city":"Iru\u00f1a",
    "sg:orig_category":"Cuchiller\u00cda (al Por Menor)",
    "sg:phone":"+34 948 22 34 32",
    "sg:postcode":"31001",
    "sg:province":"Navarra",
    "wof:name":"Gomez Gomez Valentin",
    "wof:placetype":"venue"
},
  "geometry": {"coordinates":[-1.6424939632,42.8181381226],"type":"Point"}
}