{
  "type": "Feature",
  "properties": {
    "addr:full":"Hortichuelas Altas, S/n Hortichuelas Almer\u00eda 04116",
    "addr:postcode":"04116",
    "addr:street":"S / N Hortichuelas Almeri\u0301A",
    "iso:country":"ES",
    "sg:address":"Hortichuelas Altas, S/n",
    "sg:city":"Hortichuelas",
    "sg:orig_category":"Alquiler De Apartamentos",
    "sg:phone":"+34 950 38 81 07",
    "sg:postcode":"04116",
    "sg:province":"Almer\u00eda",
    "wof:name":"Fernandez Fernandez Francisco",
    "wof:placetype":"venue"
},
  "geometry": {"coordinates":[-2.0093569756,36.8781661987],"type":"Point"}
}