{
  "type": "Feature",
  "properties": {
    "addr:full":"Avda Quinto Centenario, 77 Sanlucar De Barrameda C\u00e1diz 11540",
    "addr:housenumber":"77",
    "addr:postcode":"11540",
    "addr:street":"Avda Quinto Centenario;Ca\u0301Diz",
    "iso:country":"ES",
    "sg:address":"Avda Quinto Centenario, 77",
    "sg:city":"Sanlucar De Barrameda",
    "sg:orig_category":"Inmobiliaria (agencias)",
    "sg:phone":"+34 956 38 13 79",
    "sg:postcode":"11540",
    "sg:province":"C\u00e1diz",
    "wof:name":"Gralfer S.l.",
    "wof:placetype":"venue"
},
  "geometry": {"coordinates":[-6.3595747948,36.7783050537],"type":"Point"}
}