{
  "type": "Feature",
  "properties": {
    "iso:country":"ES",
    "sg:address":"Calle de Ronda, 34",
    "sg:city":"Saucejo",
    "sg:orig_category":"Equitaci\u00d3n: Guarnicioner\u00cda, Equipo (al Por Menor)",
    "sg:phone":"+34 955 82 44 33",
    "sg:postcode":"41650",
    "sg:province":"Sevilla",
    "wof:name":"Sanchez Rueda Alonso",
    "wof:placetype":"venue"
},
  "geometry": {"coordinates":[-5.0975728035,37.069316864],"type":"Point"}
}