{
  "type": "Feature",
  "properties": {
    "iso:country":"ES",
    "sg:address":"Avda Denia, 102",
    "sg:city":"Alacant",
    "sg:orig_category":"Decapado, Desengrasado (preparaci\u00d3n De Superficies)",
    "sg:phone":"+34 965 15 31 57",
    "sg:postcode":"03016",
    "sg:province":"Alicante",
    "wof:name":"Hyprocosta S.l.",
    "wof:placetype":"venue"
},
  "geometry": {"coordinates":[-0.4657019973,38.3606491089],"type":"Point"}
}