{
  "type": "Feature",
  "properties": {
    "addr:full":"Calle de Luis Morote, 6 Palmas De Gran Canaria Las Palmas 35007",
    "addr:housenumber":"6",
    "addr:postcode":"35007",
    "addr:street":"Calle De Luis Morote",
    "iso:country":"ES",
    "sg:address":"Calle de Luis Morote, 6",
    "sg:city":"Palmas De Gran Canaria",
    "sg:orig_category":"Abogados",
    "sg:phone":"+34 928 27 02 09",
    "sg:postcode":"35007",
    "sg:province":"Las Palmas",
    "wof:name":"Lopez Noriega Esteban",
    "wof:placetype":"venue"
},
  "geometry": {"coordinates":[-15.4303817749,28.141456604],"type":"Point"}
}