{
  "type": "Feature",
  "properties": {
    "iso:country":"ES",
    "sg:address":"Jauregi Kalea, 2",
    "sg:city":"Urretxu",
    "sg:orig_category":"Alumbrados",
    "sg:phone":"+34 943 72 01 54",
    "sg:postcode":"20700",
    "sg:province":"Guip\u00f9zcoa",
    "wof:name":"Ezpeleta Argidenda Deunor Ezpeleta Apaolaza Y Otros Dos Cb",
    "wof:placetype":"venue"
},
  "geometry": {"coordinates":[-2.3146309853,43.0930175781],"type":"Point"}
}