{
  "type": "Feature",
  "properties": {
    "iso:country":"ES",
    "sg:address":"Carrer de Rellotge, 51",
    "sg:city":"Santa Coloma De Gramenet",
    "sg:orig_category":"Fabricaci\u00d3n, Instalaci\u00d3n Y Reparaci\u00d3n De Bombas",
    "sg:phone":"+34 933 92 34 51",
    "sg:postcode":"08923",
    "sg:province":"Barcelona",
    "wof:name":"Ventaja Delgado Jose",
    "wof:placetype":"venue"
},
  "geometry": {"coordinates":[2.2211589813,41.448425293],"type":"Point"}
}