{
  "type": "Feature",
  "properties": {
    "iso:country":"ES",
    "sg:address":"Carr Sant Antoni, 51",
    "sg:city":"Figueres",
    "sg:classifiers":[
        {
            "category":"Building & Trades",
            "subcategory":"Construction",
            "type":"Services"
        }
    ],
    "sg:phone":"+34 972 50 74 93",
    "sg:postcode":"17600",
    "sg:province":"Girona",
    "sg:tags":[
        "calefacci\u00d3n",
        "central",
        "para",
        "de",
        "fabricaci\u00d3n",
        "caldera"
    ],
    "sg:website":"www.enalter.com",
    "wof:name":"Jordi Capel S.c.",
    "wof:placetype":"venue"
},
  "geometry": {"coordinates":[2.9653689861,42.2635383606],"type":"Point"}
}