{
  "type": "Feature",
  "properties": {
    "iso:country":"ES",
    "sg:address":"Calle de Porto Cristo, 9",
    "sg:city":"Alcorcon",
    "sg:orig_category":"Peluquer\u00cdas",
    "sg:phone":"+34 916 12 07 13",
    "sg:postcode":"28924",
    "sg:province":"Madrid",
    "wof:name":"Casnie C.b.",
    "wof:placetype":"venue"
},
  "geometry": {"coordinates":[-3.8173799515,40.3513870239],"type":"Point"}
}