{
  "type": "Feature",
  "properties": {
    "addr:full":"Calle de Benelux, S/n Elda Alicante 03600",
    "addr:housenumber":"s",
    "addr:postcode":"03600",
    "addr:street":"Calle De Benelux;/ N",
    "iso:country":"ES",
    "sg:address":"Calle de Benelux, S/n",
    "sg:city":"Elda",
    "sg:orig_category":"Contenedores (mercanc\u00cdas)",
    "sg:phone":"+34 965 38 24 23",
    "sg:postcode":"03600",
    "sg:province":"Alicante",
    "wof:name":"Faz Hispania S.l.",
    "wof:placetype":"venue"
},
  "geometry": {"coordinates":[-0.8158627748,38.4646492004],"type":"Point"}
}