{
  "type": "Feature",
  "properties": {
    "iso:country":"ES",
    "sg:address":"Calle de Joaquin Costa, 40",
    "sg:city":"Ejea De Los Caballeros",
    "sg:orig_category":"Mec\u00c1nico Del Autom\u00d3vil",
    "sg:phone":"+34 976 66 10 35",
    "sg:postcode":"50600",
    "sg:province":"Zaragoza",
    "wof:name":"Tasancris S.l.",
    "wof:placetype":"venue"
},
  "geometry": {"coordinates":[-1.1426290274,42.1220474243],"type":"Point"}
}