{
  "type": "Feature",
  "properties": {
    "iso:country":"ES",
    "sg:address":"Calle de Moratin, 14",
    "sg:city":"Valencia",
    "sg:orig_category":"Inversiones",
    "sg:phone":"+34 963 94 40 20",
    "sg:postcode":"46002",
    "sg:province":"Valencia",
    "sg:website":"www.gesfinversion.com",
    "wof:name":"Gesfinversion Compania Espanola S.l.",
    "wof:placetype":"venue"
},
  "geometry": {"coordinates":[-0.3757539988,39.4704627991],"type":"Point"}
}