{
  "type": "Feature",
  "properties": {
    "iso:country":"ES",
    "sg:address":"Calle de Reyes Catolicos, 16",
    "sg:city":"Cordoba",
    "sg:orig_category":"Estancos",
    "sg:phone":"+34 957 49 11 38",
    "sg:postcode":"14001",
    "sg:province":"C\u00f3rdoba",
    "wof:name":"Cabezas Carrasquilla Juan Carlos",
    "wof:placetype":"venue"
},
  "geometry": {"coordinates":[-4.78083992,37.8892250061],"type":"Point"}
}