{
  "type": "Feature",
  "properties": {
    "iso:country":"ES",
    "sg:address":"Avda Alcalde Jose Ramirez Bethencourt, 5",
    "sg:city":"Palmas De Gran Canaria",
    "sg:orig_category":"Doctores En Medicina",
    "sg:phone":"+34 928 36 15 52",
    "sg:postcode":"35003",
    "sg:province":"Las Palmas",
    "wof:name":"Toro Y Del Toro Margarita Del",
    "wof:placetype":"venue"
},
  "geometry": {"coordinates":[-15.4161691666,28.1096057892],"type":"Point"}
}