{
  "type": "Feature",
  "properties": {
    "addr:full":"Avgd Francesc Tarrega, 43 Villarreal Castell\u00f3n 12540",
    "addr:housenumber":"43",
    "addr:postcode":"12540",
    "addr:street":"Tarrega",
    "iso:country":"ES",
    "sg:address":"Avgd Francesc Tarrega, 43",
    "sg:city":"Villarreal",
    "sg:orig_category":"Agencias Y Agentes Comerciales, Representantes",
    "sg:phone":"+34 964 52 21 48",
    "sg:postcode":"12540",
    "sg:province":"Castell\u00f3n",
    "wof:name":"Garcia Petit Simon",
    "wof:placetype":"venue"
},
  "geometry": {"coordinates":[-0.1214234978,39.9298171997],"type":"Point"}
}