{
  "type": "Feature",
  "properties": {
    "iso:country":"ES",
    "sg:address":"Trasouto, 23",
    "sg:city":"Trasouto",
    "sg:orig_category":"Mec\u00c1nico Del Autom\u00d3vil",
    "sg:phone":"+34 986 32 26 26",
    "sg:postcode":"36939",
    "sg:province":"Pontevedra",
    "wof:name":"Motor Bueu S.l.",
    "wof:placetype":"venue"
},
  "geometry": {"coordinates":[-8.7823858261,42.3033218384],"type":"Point"}
}