{
  "type": "Feature",
  "properties": {
    "addr:full":"Calle de Juan Illescas Pavon, 19 San Pedro Alcantara M\u00e1laga 29670",
    "addr:housenumber":"19",
    "addr:postcode":"29670",
    "addr:street":"Calle De Juan Illescas Pavon",
    "iso:country":"ES",
    "sg:address":"Calle de Juan Illescas Pavon, 19",
    "sg:city":"San Pedro Alcantara",
    "sg:orig_category":"M\u00c9dicos: Foniatr\u00cda Y Logopedia",
    "sg:phone":"+34 952 92 74 83",
    "sg:postcode":"29670",
    "sg:province":"M\u00e1laga",
    "wof:name":"Corrales Dominguez Laura",
    "wof:placetype":"venue"
},
  "geometry": {"coordinates":[-4.9864649773,36.4903297424],"type":"Point"}
}