{
  "type": "Feature",
  "properties": {
    "addr:full":"Trva Alejandro Cerecedo, 5 Vilagarcia Pontevedra 36600",
    "addr:housenumber":"5",
    "addr:postcode":"36600",
    "addr:street":"Trva Alejandro Cerecedo",
    "iso:country":"ES",
    "sg:address":"Trva Alejandro Cerecedo, 5",
    "sg:city":"Vilagarcia",
    "sg:orig_category":"T\u00c9cnicos Veterinarios",
    "sg:phone":"+34 986 50 05 15",
    "sg:postcode":"36600",
    "sg:province":"Pontevedra",
    "wof:name":"Reiriz Mera Josefa",
    "wof:placetype":"venue"
},
  "geometry": {"coordinates":[-8.7665138245,42.5931396484],"type":"Point"}
}