{
  "type": "Feature",
  "properties": {
    "iso:country":"ES",
    "sg:address":"Carr Alzina Surera, 22",
    "sg:city":"Urbanitzacio Can Carbonell",
    "sg:orig_category":"Ense\u00d1anza: Idiomas",
    "sg:phone":"+34 972 47 16 99",
    "sg:postcode":"17455",
    "sg:province":"Girona",
    "wof:name":"Catalonia Languages Services S.l.",
    "wof:placetype":"venue"
},
  "geometry": {"coordinates":[2.8018240929,41.8385505676],"type":"Point"}
}