{
  "type": "Feature",
  "properties": {
    "iso:country":"ES",
    "sg:address":"Calle de Zapateria, 66",
    "sg:city":"Vitoria-gasteiz",
    "sg:orig_category":"Librer\u00cdas",
    "sg:phone":"+34 945 27 54 23",
    "sg:postcode":"01001",
    "sg:province":"\u00c1lava",
    "wof:name":"Lebrancon Alonso Francisco Julian",
    "wof:placetype":"venue"
},
  "geometry": {"coordinates":[-2.6739559174,42.8488845825],"type":"Point"}
}