{
  "type": "Feature",
  "properties": {
    "iso:country":"ES",
    "sg:address":"Calle de Feria, 42",
    "sg:city":"Sevilla",
    "sg:orig_category":"Quincaller\u00cda (al Por Menor)",
    "sg:phone":"+34 954 38 75 04",
    "sg:postcode":"41003",
    "sg:province":"Sevilla",
    "wof:name":"Caceres Reina Luis",
    "wof:placetype":"venue"
},
  "geometry": {"coordinates":[-5.9912462234,37.3973960876],"type":"Point"}
}