{
  "type": "Feature",
  "properties": {
    "addr:full":"Calle de Badajoz, 2 Alcorcon Madrid 28921",
    "addr:housenumber":"2",
    "addr:postcode":"28921",
    "addr:street":"Calle De Badajoz",
    "iso:country":"ES",
    "sg:address":"Calle de Badajoz, 2",
    "sg:city":"Alcorcon",
    "sg:orig_category":"Confecci\u00d3n De Trajes Para Se\u00d1oras",
    "sg:phone":"+34 916 11 44 05",
    "sg:postcode":"28921",
    "sg:province":"Madrid",
    "wof:name":"Martin Rodriguez Jesus",
    "wof:placetype":"venue"
},
  "geometry": {"coordinates":[-3.8307132721,40.3483047485],"type":"Point"}
}