{
  "type": "Feature",
  "properties": {
    "iso:country":"ES",
    "sg:address":"Calle de San Rafael, S/n",
    "sg:city":"S. Adrian",
    "sg:orig_category":"Escayola Y Productos De Escayola (fabricaci\u00d3n, Al Por Mayor)",
    "sg:phone":"+34 948 69 65 12",
    "sg:postcode":"31570",
    "sg:province":"Navarra",
    "wof:name":"Prefabricados Valerio S.a.",
    "wof:placetype":"venue"
},
  "geometry": {"coordinates":[-1.9384839535,42.3355331421],"type":"Point"}
}