{
  "type": "Feature",
  "properties": {
    "addr:full":"Carr Matematic Marzal, 2 Sueca Valencia 46410",
    "addr:housenumber":"2",
    "addr:postcode":"46410",
    "addr:street":"Carr Matematic Marzal",
    "iso:country":"ES",
    "sg:address":"Carr Matematic Marzal, 2",
    "sg:city":"Sueca",
    "sg:orig_category":"Limpieza Industrial",
    "sg:phone":"+34 961 70 05 78",
    "sg:postcode":"46410",
    "sg:province":"Valencia",
    "wof:name":"Lavanderia Miele S.l.",
    "wof:placetype":"venue"
},
  "geometry": {"coordinates":[-0.3037779927,39.2058792114],"type":"Point"}
}