{
  "type": "Feature",
  "properties": {
    "iso:country":"ES",
    "sg:address":"Ctra Cobre (al), 57",
    "sg:city":"Algeciras",
    "sg:orig_category":"Contenedores (mercanc\u00cdas)",
    "sg:phone":"+34 956 57 15 33",
    "sg:postcode":"11206",
    "sg:province":"C\u00e1diz",
    "wof:name":"Gil Silva Jose",
    "wof:placetype":"venue"
},
  "geometry": {"coordinates":[-5.4579749107,36.1132850647],"type":"Point"}
}