{
  "type": "Feature",
  "properties": {
    "iso:country":"ES",
    "sg:address":"Relva, S/n",
    "sg:city":"Relba",
    "sg:classifiers":[
        {
            "category":"Personal",
            "subcategory":"Barber",
            "type":"Services"
        }
    ],
    "sg:phone":"+34 986 33 59 04",
    "sg:postcode":"36410",
    "sg:province":"Pontevedra",
    "sg:tags":[
        "caballeros",
        "de",
        "peluqueros"
    ],
    "wof:name":"Portas Alvarez Fernando",
    "wof:placetype":"venue"
},
  "geometry": {"coordinates":[-8.6314487457,42.1545600891],"type":"Point"}
}