{
  "type": "Feature",
  "properties": {
    "iso:country":"ES",
    "sg:address":"Calle de Secretario Artiles, 50",
    "sg:city":"Palmas De Gran Canaria",
    "sg:orig_category":"Construcciones Met\u00c1licas",
    "sg:phone":"+34 928 26 44 41",
    "sg:postcode":"35007",
    "sg:province":"Las Palmas",
    "wof:name":"A\u00f1uri S. A.",
    "wof:placetype":"venue"
},
  "geometry": {"coordinates":[-15.4321146011,28.1396999359],"type":"Point"}
}