{
  "type": "Feature",
  "properties": {
    "iso:country":"ES",
    "sg:address":"Rua Rocio, 44",
    "sg:city":"Vigo",
    "sg:orig_category":"Carnicer\u00cdas, Carnicer\u00cdas",
    "sg:phone":"+34 986 23 52 40",
    "sg:postcode":"36208",
    "sg:province":"Pontevedra",
    "wof:name":"Sexto Alvarez Valentina",
    "wof:placetype":"venue"
},
  "geometry": {"coordinates":[-8.751042366,42.220916748],"type":"Point"}
}