{
  "type": "Feature",
  "properties": {
    "iso:country":"ES",
    "sg:address":"Ctra Pego (de), 1",
    "sg:city":"Oliva",
    "sg:orig_category":"Muebles Y Accesorios Para Cocinas Y Cuartos De Ba\u00d1o (al Por Menor)",
    "sg:phone":"+34 962 83 84 49",
    "sg:postcode":"46780",
    "sg:province":"Valencia",
    "wof:name":"Parra Molla Vicente Sebastian",
    "wof:placetype":"venue"
},
  "geometry": {"coordinates":[-0.1152710021,38.9154014587],"type":"Point"}
}