{
  "type": "Feature",
  "properties": {
    "iso:country":"ES",
    "sg:address":"Carrer de Mare De Deu De Port, 337",
    "sg:city":"Barcelona",
    "sg:orig_category":"Ropa Para Se\u00d1oras Y Caballeros (al Por Menor)",
    "sg:phone":"+34 932 96 88 92",
    "sg:postcode":"08038",
    "sg:province":"Barcelona",
    "wof:name":"Sarmiento Gomez Isaac",
    "wof:placetype":"venue"
},
  "geometry": {"coordinates":[2.1394970417,41.361579895],"type":"Point"}
}