{
  "type": "Feature",
  "properties": {
    "addr:full":"Cuatrocientos Veintiuno, 27 Sa Vileta Islas Baleares 07011",
    "addr:housenumber":"27",
    "addr:postcode":"07011",
    "addr:street":"Veintiuno;Vileta",
    "iso:country":"ES",
    "sg:address":"Cuatrocientos Veintiuno, 27",
    "sg:city":"Sa Vileta",
    "sg:orig_category":"Molduras, Junquillos, Listones Y Molduras Perforadas",
    "sg:phone":"+34 971 79 27 45",
    "sg:postcode":"07011",
    "sg:province":"Islas Baleares",
    "wof:name":"Camacho Chica Ventura",
    "wof:placetype":"venue"
},
  "geometry": {"coordinates":[2.6205170155,39.5930747986],"type":"Point"}
}