{
  "type": "Feature",
  "properties": {
    "iso:country":"ES",
    "sg:address":"Carrer de Peixateria (de La), 10",
    "sg:city":"Valls",
    "sg:orig_category":"Bisuter\u00cda, Joyer\u00cda, Relojer\u00cda (al Por Menor)",
    "sg:phone":"+34 977 60 59 53",
    "sg:postcode":"43800",
    "sg:province":"Tarragona",
    "wof:name":"Aida Joies C.b.",
    "wof:placetype":"venue"
},
  "geometry": {"coordinates":[1.2490235567,41.2840080261],"type":"Point"}
}