{
  "type": "Feature",
  "properties": {
    "addr:full":"Cra Laurea Miro, 204 Sant Feliu Llobregat Barcelona 08980",
    "addr:housenumber":"204",
    "addr:postcode":"08980",
    "iso:country":"ES",
    "sg:address":"Cra Laurea Miro, 204",
    "sg:city":"Sant Feliu Llobregat",
    "sg:orig_category":"Sociedades, Compa\u00d1\u00cdas Aseguradoras",
    "sg:phone":"+34 936 85 71 71",
    "sg:postcode":"08980",
    "sg:province":"Barcelona",
    "wof:name":"Massague Associats S. C. A. S. L.",
    "wof:placetype":"venue"
},
  "geometry": {"coordinates":[2.0440590382,41.3810386658],"type":"Point"}
}