{
  "type": "Feature",
  "properties": {
    "iso:country":"ES",
    "sg:address":"Carrer de Antoni Roig (d'), 36",
    "sg:city":"Torredembarra",
    "sg:orig_category":"Carnicer\u00cdas, Carnicer\u00cdas",
    "sg:phone":"+34 977 64 12 28",
    "sg:postcode":"43830",
    "sg:province":"Tarragona",
    "wof:name":"Sole Godall Daniel",
    "wof:placetype":"venue"
},
  "geometry": {"coordinates":[1.3990340233,41.1444587708],"type":"Point"}
}