{
  "type": "Feature",
  "properties": {
    "iso:country":"ES",
    "sg:address":"Calle de Segovia, 31",
    "sg:city":"Madrid",
    "sg:orig_category":"Venta, Localizaci\u00d3n, Reparaci\u00d3n De Material E Instrumental M\u00c9dico",
    "sg:phone":"+34 913 66 81 20",
    "sg:postcode":"28005",
    "sg:province":"Madrid",
    "sg:website":"www.deposito2000.com",
    "wof:name":"Den S.l.",
    "wof:placetype":"venue"
},
  "geometry": {"coordinates":[-3.7117059231,40.4138221741],"type":"Point"}
}