{
  "type": "Feature",
  "properties": {
    "iso:country":"ES",
    "sg:address":"Calle de Lepanto, 7",
    "sg:city":"Barco De Avila",
    "sg:orig_category":"Sociedades, Compa\u00d1\u00cdas Aseguradoras",
    "sg:phone":"+34 920 34 07 71",
    "sg:postcode":"05600",
    "sg:province":"\u00c1vila",
    "wof:name":"Garcia De La Calle Basilio",
    "wof:placetype":"venue"
},
  "geometry": {"coordinates":[-5.5214748383,40.3571548462],"type":"Point"}
}