{
  "type": "Feature",
  "properties": {
    "iso:country":"ES",
    "sg:address":"Calle de Santa Rita, 3",
    "sg:city":"Majadahonda",
    "sg:orig_category":"Mec\u00c1nico Del Autom\u00d3vil",
    "sg:phone":"+34 916 38 27 19",
    "sg:postcode":"28220",
    "sg:province":"Madrid",
    "wof:name":"Martin Gallego Juan",
    "wof:placetype":"venue"
},
  "geometry": {"coordinates":[-3.8770959377,40.4726715088],"type":"Point"}
}