{
  "type": "Feature",
  "properties": {
    "addr:full":"Calle de Goya, 123 Madrid Madrid 28009",
    "addr:housenumber":"123",
    "addr:postcode":"28009",
    "addr:street":"Calle De Goya",
    "iso:country":"ES",
    "sg:address":"Calle de Goya, 123",
    "sg:city":"Madrid",
    "sg:orig_category":"Muebles, Minoristas",
    "sg:phone":"+34 914 01 45 91",
    "sg:postcode":"28009",
    "sg:province":"Madrid",
    "wof:name":"Monseco Martin Domingo",
    "wof:placetype":"venue"
},
  "geometry": {"coordinates":[-3.6712989807,40.424747467],"type":"Point"}
}