{
  "type": "Feature",
  "properties": {
    "iso:country":"ES",
    "sg:address":"C/ Porta De La Morera, 41",
    "sg:city":"Elche",
    "sg:orig_category":"Restaurantes",
    "sg:phone":"+34 965 45 34 18",
    "sg:postcode":"03203",
    "sg:province":"Alicante",
    "wof:name":"Robledillo Leiva Julia",
    "wof:placetype":"venue"
},
  "geometry": {"coordinates":[-0.6918879747,38.2641830444],"type":"Point"}
}