{
  "type": "Feature",
  "properties": {
    "iso:country":"ES",
    "sg:address":"Calle de Avenida Pamplona, 5",
    "sg:city":"Mutiloabeiti",
    "sg:orig_category":"Cl\u00cdnicas Dentales",
    "sg:phone":"+34 948 23 60 70",
    "sg:postcode":"31192",
    "sg:province":"Navarra",
    "wof:name":"Planes  Christophe",
    "wof:placetype":"venue"
},
  "geometry": {"coordinates":[-1.6760691404,42.6953926086],"type":"Point"}
}