{
  "type": "Feature",
  "properties": {
    "iso:country":"ES",
    "sg:address":"Pase Cuellar, 15",
    "sg:city":"Zaragoza",
    "sg:orig_category":"Ropa Para Se\u00d1oras (al Por Menor)",
    "sg:phone":"+34 976 38 03 46",
    "sg:postcode":"50007",
    "sg:province":"Zaragoza",
    "wof:name":"Aranda Diaz De Villegas Mercedes",
    "wof:placetype":"venue"
},
  "geometry": {"coordinates":[-0.8848066926,41.6384277344],"type":"Point"}
}