{
  "type": "Feature",
  "properties": {
    "addr:full":"Plaz Jesus, S/n Valencia Valencia 46007",
    "addr:housenumber":"s / n",
    "addr:postcode":"46007",
    "iso:country":"ES",
    "sg:address":"Plaz Jesus, S/n",
    "sg:city":"Valencia",
    "sg:orig_category":"Mercados De Productos Alimenticios",
    "sg:phone":"+34 963 42 25 06",
    "sg:postcode":"46007",
    "sg:province":"Valencia",
    "wof:name":"Fuster Morant Maria Luisa",
    "wof:placetype":"venue"
},
  "geometry": {"coordinates":[-0.3835990131,39.4659805298],"type":"Point"}
}