{
  "type": "Feature",
  "properties": {
    "addr:full":"Ctra Alicante, 163 Flota Murcia 30007",
    "addr:housenumber":"163",
    "addr:postcode":"30007",
    "addr:street":"Ctra Alicante",
    "iso:country":"ES",
    "sg:address":"Ctra Alicante, 163",
    "sg:city":"Flota",
    "sg:orig_category":"Droguer\u00cdas (al Por Menor)",
    "sg:phone":"+34 968 24 65 52",
    "sg:postcode":"30007",
    "sg:province":"Murcia",
    "wof:name":"C.m.todo En Pintura S.l.",
    "wof:placetype":"venue"
},
  "geometry": {"coordinates":[-1.1142389774,37.9970092773],"type":"Point"}
}