{
  "type": "Feature",
  "properties": {
    "iso:country":"ES",
    "sg:address":"Calle de Marques De La Valdavia (del), 59",
    "sg:city":"Alcobendas",
    "sg:orig_category":"Promotores Constructores",
    "sg:phone":"+34 916 62 03 41",
    "sg:postcode":"28100",
    "sg:province":"Madrid",
    "wof:name":"Obras Saype S.l.",
    "wof:placetype":"venue"
},
  "geometry": {"coordinates":[-3.6418449879,40.544052124],"type":"Point"}
}