{
  "type": "Feature",
  "properties": {
    "iso:country":"ES",
    "sg:address":"Carrer de Proven\u00c7a, 199",
    "sg:city":"Barcelona",
    "sg:orig_category":"Librer\u00cdas",
    "sg:phone":"+34 934 54 79 01",
    "sg:postcode":"08008",
    "sg:province":"Barcelona",
    "wof:name":"Freixanet Llibres S.a.",
    "wof:placetype":"venue"
},
  "geometry": {"coordinates":[2.1575651169,41.3919677734],"type":"Point"}
}