{
  "type": "Feature",
  "properties": {
    "addr:full":"Calle de Isaac Peral, 3 Zaragoza Zaragoza 50001",
    "addr:housenumber":"3",
    "addr:postcode":"50001",
    "addr:street":"Calle De Isaac Peral",
    "iso:country":"ES",
    "sg:address":"Calle de Isaac Peral, 3",
    "sg:city":"Zaragoza",
    "sg:orig_category":"Bisuter\u00cda, Joyer\u00cda, Relojer\u00cda (al Por Menor)",
    "sg:phone":"+34 976 23 39 93",
    "sg:postcode":"50001",
    "sg:province":"Zaragoza",
    "wof:name":"Arbiol Garcia Natalia",
    "wof:placetype":"venue"
},
  "geometry": {"coordinates":[-0.8807935715,41.6503410339],"type":"Point"}
}