{
  "type": "Feature",
  "properties": {
    "addr:full":"Ctra. Bilbao, Km. 0009,0 Mi\u00f1ano Goien \u00c1lava 01510",
    "addr:postcode":"01510",
    "addr:street":"Ctra. Bilbao Km. 0009,0 Min\u0303Ano;A\u0301Lava",
    "iso:country":"ES",
    "sg:address":"Ctra. Bilbao, Km. 0009,0",
    "sg:city":"Mi\u00f1ano Goien",
    "sg:orig_category":"Muebles, Minoristas",
    "sg:phone":"+34 945 29 80 68",
    "sg:postcode":"01510",
    "sg:province":"\u00c1lava",
    "wof:name":"Almum S. L.",
    "wof:placetype":"venue"
},
  "geometry": {"coordinates":[-2.6502892971,42.8999252319],"type":"Point"}
}