{
  "type": "Feature",
  "properties": {
    "iso:country":"ES",
    "sg:address":"Carrer de Rossello, 340",
    "sg:city":"Barcelona",
    "sg:orig_category":"Agencias De Viajes",
    "sg:phone":"+34 932 07 38 11",
    "sg:postcode":"08025",
    "sg:province":"Barcelona",
    "wof:name":"Eureka Tours S. A.",
    "wof:placetype":"venue"
},
  "geometry": {"coordinates":[2.1699841022,41.4027137756],"type":"Point"}
}