{
  "type": "Feature",
  "properties": {
    "iso:country":"ES",
    "sg:address":"Carrer de Sevilla, 137",
    "sg:city":"Terrassa",
    "sg:orig_category":"Veh\u00cdculos De Ocasi\u00d3n",
    "sg:phone":"+34 937 83 58 55",
    "sg:postcode":"08226",
    "sg:province":"Barcelona",
    "wof:name":"Automoviles Egara S.a.",
    "wof:placetype":"venue"
},
  "geometry": {"coordinates":[2.0319869518,41.5731201172],"type":"Point"}
}