{
  "type": "Feature",
  "properties": {
    "addr:full":"Carrer de Major, 342 Centre Barcelona 08759",
    "addr:housenumber":"342",
    "addr:postcode":"08759",
    "addr:street":"Carrer De Major;Centre Barcelona",
    "iso:country":"ES",
    "sg:address":"Carrer de Major, 342",
    "sg:city":"Centre",
    "sg:orig_category":"Bibliotecas, Mediatecas",
    "sg:phone":"+34 936 83 13 65",
    "sg:postcode":"08759",
    "sg:province":"Barcelona",
    "wof:name":"Ajuntament De Vallirana",
    "wof:placetype":"venue"
},
  "geometry": {"coordinates":[1.8108078241,41.2359657288],"type":"Point"}
}