{
  "type": "Feature",
  "properties": {
    "addr:full":"Calle de Compa\u00d1ia, 12 Salamanca Salamanca 37002",
    "addr:housenumber":"12",
    "addr:postcode":"37002",
    "addr:street":"Calle De Compan\u0303Ia",
    "iso:country":"ES",
    "sg:address":"Calle de Compa\u00d1ia, 12",
    "sg:city":"Salamanca",
    "sg:orig_category":"Molduras, Junquillos, Listones Y Molduras Perforadas",
    "sg:phone":"+34 923 26 57 39",
    "sg:postcode":"37002",
    "sg:province":"Salamanca",
    "wof:name":"Laboranka Sociedad Cooperativa",
    "wof:placetype":"venue"
},
  "geometry": {"coordinates":[-5.6661310196,40.9629974365],"type":"Point"}
}