{
  "type": "Feature",
  "properties": {
    "addr:full":"Calle de Santa Rosa, 22 Atarfe Granada 18230",
    "addr:housenumber":"22",
    "addr:postcode":"18230",
    "addr:street":"Calle De Santa Rosa",
    "iso:country":"ES",
    "sg:address":"Calle de Santa Rosa, 22",
    "sg:city":"Atarfe",
    "sg:orig_category":"Fabricaci\u00d3n De Distribuidores Autom\u00c1ticos",
    "sg:phone":"+34 958 43 87 23",
    "sg:postcode":"18230",
    "sg:province":"Granada",
    "wof:name":"Francisco Javier Morillas Hernandez Y Otro Cdad",
    "wof:placetype":"venue"
},
  "geometry": {"coordinates":[-3.682929039,37.2276916504],"type":"Point"}
}