{
  "type": "Feature",
  "properties": {
    "addr:full":"Calle de Sagrado Corazon De Jesus, S/n Jaen Ja\u00e9n 23005",
    "addr:housenumber":"s / n;jae\u0301n",
    "addr:postcode":"23005",
    "addr:street":"Calle De Sagrado Corazon",
    "iso:country":"ES",
    "sg:address":"Calle de Sagrado Corazon De Jesus, S/n",
    "sg:city":"Jaen",
    "sg:orig_category":"Iglesia Cat\u00d3lica",
    "sg:phone":"+34 953 26 20 21",
    "sg:postcode":"23005",
    "sg:province":"Ja\u00e9n",
    "wof:name":"Obispado De Jaen",
    "wof:placetype":"venue"
},
  "geometry": {"coordinates":[-3.7951359749,37.7748908997],"type":"Point"}
}