{
  "type": "Feature",
  "properties": {
    "addr:full":"Carrer de Major, 54 Hospitalet Llobregat Barcelona 08901",
    "addr:housenumber":"54",
    "addr:postcode":"08901",
    "addr:street":"Carrer De Major",
    "iso:country":"ES",
    "sg:address":"Carrer de Major, 54",
    "sg:city":"Hospitalet Llobregat",
    "sg:orig_category":"Asociaciones, Organismos Culturales Y Socioeducativos",
    "sg:phone":"+34 933 38 60 91",
    "sg:postcode":"08901",
    "sg:province":"Barcelona",
    "wof:name":"Centre D'estudis De L'hospitalet",
    "wof:placetype":"venue"
},
  "geometry": {"coordinates":[2.0978150368,41.3595848083],"type":"Point"}
}