{
  "type": "Feature",
  "properties": {
    "addr:full":"Calle de Torrejon De Ardoz (de), 8 Leganes Madrid 28914",
    "addr:postcode":"28914",
    "addr:street":"Calle De Torrejon",
    "iso:country":"ES",
    "sg:address":"Calle de Torrejon De Ardoz (de), 8",
    "sg:city":"Leganes",
    "sg:orig_category":"Empresarios",
    "sg:phone":"+34 916 48 43 52",
    "sg:postcode":"28914",
    "sg:province":"Madrid",
    "wof:name":"Limpiezas Garco S.l.",
    "wof:placetype":"venue"
},
  "geometry": {"coordinates":[-3.754668951,40.322303772],"type":"Point"}
}