{
  "type": "Feature",
  "properties": {
    "iso:country":"ES",
    "sg:address":"Carrer de Rampi, 3",
    "sg:city":"Olot",
    "sg:orig_category":"M\u00c9dicos: Neumolog\u00cda",
    "sg:phone":"+34 972 26 72 37",
    "sg:postcode":"17800",
    "sg:province":"Girona",
    "wof:name":"Obrador Lagares Antonio",
    "wof:placetype":"venue"
},
  "geometry": {"coordinates":[2.4764769077,42.1842498779],"type":"Point"}
}