{
  "type": "Feature",
  "properties": {
    "iso:country":"ES",
    "sg:address":"Av. Carlos Iii El Noble, 51",
    "sg:city":"Iru\u00f1a",
    "sg:orig_category":"M\u00c9dicos: Estomatolog\u00cda",
    "sg:phone":"+34 948 24 68 72",
    "sg:postcode":"31004",
    "sg:province":"Navarra",
    "wof:name":"Ager Iciz Lourdes",
    "wof:placetype":"venue"
},
  "geometry": {"coordinates":[-1.6376458406,42.8118515015],"type":"Point"}
}