{
  "type": "Feature",
  "properties": {
    "addr:full":"Avda Juan Carlos I, 45 Avila \u00c1vila 05004",
    "addr:housenumber":"45",
    "addr:postcode":"05004",
    "addr:street":"Avda Juan Carlos I;A\u0301Vila",
    "iso:country":"ES",
    "sg:address":"Avda Juan Carlos I, 45",
    "sg:city":"Avila",
    "sg:orig_category":"Zapater\u00cdas",
    "sg:phone":"+34 920 21 90 27",
    "sg:postcode":"05004",
    "sg:province":"\u00c1vila",
    "wof:name":"Lopez Blazquez Julio Cesar",
    "wof:placetype":"venue"
},
  "geometry": {"coordinates":[-4.6581425667,40.668132782],"type":"Point"}
}