{
  "type": "Feature",
  "properties": {
    "addr:full":"Cubillo, 61 Cuenca Cuenca 16004",
    "addr:housenumber":"61",
    "addr:postcode":"16004",
    "addr:street":"Cubillo",
    "iso:country":"ES",
    "sg:address":"Cubillo, 61",
    "sg:city":"Cuenca",
    "sg:orig_category":"Mec\u00c1nico Del Autom\u00d3vil",
    "sg:phone":"+34 969 21 00 24",
    "sg:postcode":"16004",
    "sg:province":"Cuenca",
    "wof:name":"Talleres Villa Lain S.l.",
    "wof:placetype":"venue"
},
  "geometry": {"coordinates":[-2.1162490845,40.0256004333],"type":"Point"}
}