{
  "type": "Feature",
  "properties": {
    "iso:country":"ES",
    "sg:address":"Prje Mos Del Bou, S/n",
    "sg:city":"Albatera",
    "sg:orig_category":"Fabricaci\u00d3n, Instalaci\u00d3n Y Reparaci\u00d3n De Bombas",
    "sg:phone":"+34 965 48 57 83",
    "sg:postcode":"03340",
    "sg:province":"Alicante",
    "wof:name":"General De Bombeo De Hormigon S.l.",
    "wof:placetype":"venue"
},
  "geometry": {"coordinates":[-0.8711339831,38.1797294617],"type":"Point"}
}