{
  "type": "Feature",
  "properties": {
    "iso:country":"ES",
    "sg:address":"Calle de Mamariga, 3",
    "sg:city":"Santurtzi",
    "sg:orig_category":"Electricidad: Instaladores",
    "sg:phone":"+34 944 61 35 71",
    "sg:postcode":"48980",
    "sg:province":"Vizcaya",
    "wof:name":"Electricidad Idoiaga 2001, S.l.",
    "wof:placetype":"venue"
},
  "geometry": {"coordinates":[-3.0358159542,43.3303642273],"type":"Point"}
}