{
  "type": "Feature",
  "properties": {
    "iso:country":"ES",
    "sg:address":"Calle de Boticas, 3",
    "sg:city":"Zafra",
    "sg:orig_category":"Molduras, Junquillos, Listones Y Molduras Perforadas",
    "sg:phone":"+34 924 55 39 05",
    "sg:postcode":"06300",
    "sg:province":"Badajoz",
    "wof:name":"Eurotel-sur S.l.",
    "wof:placetype":"venue"
},
  "geometry": {"coordinates":[-6.4202342033,38.4256591797],"type":"Point"}
}