{
  "type": "Feature",
  "properties": {
    "iso:country":"ES",
    "sg:address":"Gr. Pat. N. S. Piedad, S/n",
    "sg:city":"Almendralejo",
    "sg:orig_category":"Peluquer\u00cdas, Peluquer\u00cda Mixta",
    "sg:phone":"+34 924 67 15 04",
    "sg:postcode":"06200",
    "sg:province":"Badajoz",
    "wof:name":"Collados Lazaro Antonia",
    "wof:placetype":"venue"
},
  "geometry": {"coordinates":[-6.4068241119,38.6845092773],"type":"Point"}
}