{
  "type": "Feature",
  "properties": {
    "iso:country":"ES",
    "sg:address":"Avda Constitucion, 76",
    "sg:city":"Gijon",
    "sg:orig_category":"Muebles, Minoristas",
    "sg:phone":"+34 984 39 32 52",
    "sg:postcode":"33207",
    "sg:province":"Asturias",
    "wof:name":"Comercial Del Mueble Flay S.l.",
    "wof:placetype":"venue"
},
  "geometry": {"coordinates":[-5.6675891876,43.5352592468],"type":"Point"}
}