{
  "type": "Feature",
  "properties": {
    "addr:full":"Carrer de Mestre Carbo, 5 Hospitalet Llobregat Barcelona 08902",
    "addr:housenumber":"5",
    "addr:postcode":"08902",
    "addr:street":"Carrer De Mestre Carbo",
    "iso:country":"ES",
    "sg:address":"Carrer de Mestre Carbo, 5",
    "sg:city":"Hospitalet Llobregat",
    "sg:orig_category":"Radiocomunicaciones, Telefon\u00cda M\u00d3vil, Radiomensajer\u00cda: Servicios, Comercializaci\u00d3n",
    "sg:phone":"+34 932 98 01 35",
    "sg:postcode":"08902",
    "sg:province":"Barcelona",
    "wof:name":"Hussain  Abid",
    "wof:placetype":"venue"
},
  "geometry": {"coordinates":[2.1264929771,41.3639945984],"type":"Point"}
}