{
  "type": "Feature",
  "properties": {
    "addr:full":"Ctra Castellon Rugat, S/n Salem Valencia 46843",
    "addr:housenumber":"s / n",
    "addr:postcode":"46843",
    "addr:street":"Ctra Castellon Rugat",
    "iso:country":"ES",
    "sg:address":"Ctra Castellon Rugat, S/n",
    "sg:city":"Salem",
    "sg:orig_category":"Fabricaci\u00d3n De Su\u00c9ters Y Chalecos De Punto",
    "sg:phone":"+34 962 81 43 46",
    "sg:postcode":"46843",
    "sg:province":"Valencia",
    "sg:website":"www.valdepunt.com",
    "wof:name":"Valdepunt Sl",
    "wof:placetype":"venue"
},
  "geometry": {"coordinates":[-0.3809689879,38.8554191589],"type":"Point"}
}