{
  "type": "Feature",
  "properties": {
    "iso:country":"ES",
    "sg:address":"Calle de Valle De Anso, 4",
    "sg:city":"Lomas Del Gallego",
    "sg:orig_category":"Agencias Y Agentes Comerciales, Representantes",
    "sg:phone":"+34 976 18 50 65",
    "sg:postcode":"50830",
    "sg:province":"Zaragoza",
    "wof:name":"Lopez Sanchez Bernardo",
    "wof:placetype":"venue"
},
  "geometry": {"coordinates":[-0.8173449039,41.7987136841],"type":"Point"}
}