{
  "type": "Feature",
  "properties": {
    "addr:full":"Av Caldes De Montbui, 17 Mollet Valles Barcelona 08100",
    "addr:housenumber":"17",
    "addr:postcode":"08100",
    "addr:street":"Av Caldes De Montbui",
    "iso:country":"ES",
    "sg:address":"Av Caldes De Montbui, 17",
    "sg:city":"Mollet Valles",
    "sg:orig_category":"Alquiler De V\u00cddeo",
    "sg:phone":"+34 935 70 67 51",
    "sg:postcode":"08100",
    "sg:province":"Barcelona",
    "wof:name":"Cyber Plhiseas S.c.p.",
    "wof:placetype":"venue"
},
  "geometry": {"coordinates":[2.2056109905,41.5450172424],"type":"Point"}
}