{
  "type": "Feature",
  "properties": {
    "iso:country":"ES",
    "sg:address":"C/ Capita Alfons Vives, 74",
    "sg:city":"Elche",
    "sg:orig_category":"Electrodom\u00c9sticos (al Por Menor)",
    "sg:phone":"+34 966 64 14 06",
    "sg:postcode":"03204",
    "sg:province":"Alicante",
    "wof:name":"Rodenas Lopez Juan Antonio",
    "wof:placetype":"venue"
},
  "geometry": {"coordinates":[-0.7103350163,38.2616386414],"type":"Point"}
}