{
  "type": "Feature",
  "properties": {
    "addr:full":"Plaz Principes De Espa\u00d1a, 2 Alcorcon Madrid 28924",
    "addr:housenumber":"2",
    "addr:postcode":"28924",
    "addr:street":"Espan\u0303A",
    "iso:country":"ES",
    "sg:address":"Plaz Principes De Espa\u00d1a, 2",
    "sg:city":"Alcorcon",
    "sg:orig_category":"Panader\u00cdas, Panader\u00cdas",
    "sg:phone":"+34 916 12 44 70",
    "sg:postcode":"28924",
    "sg:province":"Madrid",
    "wof:name":"Herrero Navas Olga",
    "wof:placetype":"venue"
},
  "geometry": {"coordinates":[-3.8242239952,40.3513946533],"type":"Point"}
}