{
  "type": "Feature",
  "properties": {
    "iso:country":"ES",
    "sg:address":"Calle de Beethoven, 1",
    "sg:city":"Valencia",
    "sg:orig_category":"Molduras, Junquillos, Listones Y Molduras Perforadas",
    "sg:phone":"+34 963 57 11 58",
    "sg:postcode":"46017",
    "sg:province":"Valencia",
    "wof:name":"Torres Gonzalez Alonso Jesus",
    "wof:placetype":"venue"
},
  "geometry": {"coordinates":[-0.3896251023,39.4503440857],"type":"Point"}
}