{
  "type": "Feature",
  "properties": {
    "addr:full":"Valdemora, 111 Fenolleda Asturias 33828",
    "addr:housenumber":"111",
    "addr:postcode":"33828",
    "addr:street":"Valdemora",
    "iso:country":"ES",
    "sg:address":"Valdemora, 111",
    "sg:city":"Fenolleda",
    "sg:orig_category":"Material Y Herramientas Agr\u00cdcolas",
    "sg:phone":"+34 985 82 83 62",
    "sg:postcode":"33828",
    "sg:province":"Asturias",
    "wof:name":"Baudilio Granda Lopez Y Pedro Granda Lopez Cdad.",
    "wof:placetype":"venue"
},
  "geometry": {"coordinates":[-6.0615839958,43.4731445312],"type":"Point"}
}