{
  "type": "Feature",
  "properties": {
    "iso:country":"ES",
    "sg:address":"Txonta Kalea, 25",
    "sg:city":"Eibar",
    "sg:orig_category":"Rectificaci\u00d3n, Mecanizado, Fresado",
    "sg:phone":"+34 943 12 03 63",
    "sg:postcode":"20600",
    "sg:province":"Guip\u00f9zcoa",
    "wof:name":"Aguirre Unamuno Clara",
    "wof:placetype":"venue"
},
  "geometry": {"coordinates":[-2.461956501,43.1834411621],"type":"Point"}
}