{
  "type": "Feature",
  "properties": {
    "addr:full":"Praz Maior, S/n Neves Pontevedra 36440",
    "addr:housenumber":"s / n",
    "addr:postcode":"36440",
    "addr:street":"Praz Maior",
    "iso:country":"ES",
    "sg:address":"Praz Maior, S/n",
    "sg:city":"Neves",
    "sg:classifiers":[
        {
            "category":"Taxi",
            "type":"Transportation"
        }
    ],
    "sg:phone":"+34 986 64 81 40",
    "sg:postcode":"36440",
    "sg:province":"Pontevedra",
    "wof:name":"Agrupacion Local De Autonomos Del Taxi",
    "wof:placetype":"venue"
},
  "geometry": {"coordinates":[-8.6480531693,42.4336204529],"type":"Point"}
}