{
  "type": "Feature",
  "properties": {
    "addr:full":"Avda Diputacion, S/n Oyon-oion \u00c1lava 01320",
    "addr:housenumber":"s",
    "addr:postcode":"01320",
    "addr:street":"Avda Diputacion;/ N Oyon-Oion A\u0301Lava",
    "iso:country":"ES",
    "sg:address":"Avda Diputacion, S/n",
    "sg:city":"Oyon-oion",
    "sg:orig_category":"Agricultores, Agricultores",
    "sg:phone":"+34 945 60 19 52",
    "sg:postcode":"01320",
    "sg:province":"\u00c1lava",
    "wof:name":"Pablo Ezquerro Siguenza Y Tres Cdad",
    "wof:placetype":"venue"
},
  "geometry": {"coordinates":[-2.4395740032,42.508014679],"type":"Point"}
}