{
  "type": "Feature",
  "properties": {
    "iso:country":"ES",
    "sg:address":"Calle de Yuncos, 1",
    "sg:city":"Madrid",
    "sg:orig_category":"Peluqueros: De Se\u00d1oras",
    "sg:phone":"+34 913 04 09 22",
    "sg:postcode":"28037",
    "sg:province":"Madrid",
    "wof:name":"Ocampos Perello Antonia",
    "wof:placetype":"venue"
},
  "geometry": {"coordinates":[-3.6236488819,40.4299507141],"type":"Point"}
}