{
  "type": "Feature",
  "properties": {
    "iso:country":"ES",
    "sg:address":"Calle de Canarias, 20",
    "sg:city":"Barrio De La Vega",
    "sg:orig_category":"Caf\u00c9s, Bares, Cervecer\u00cdas",
    "sg:phone":"+34 958 30 23 92",
    "sg:postcode":"18193",
    "sg:province":"Granada",
    "wof:name":"Balderas Morilla Francisco",
    "wof:placetype":"venue"
},
  "geometry": {"coordinates":[-3.5577690601,37.1343917847],"type":"Point"}
}