{
  "type": "Feature",
  "properties": {
    "addr:full":"Carrer de Diputacio, 391 Barcelona Barcelona 08013",
    "addr:housenumber":"391",
    "addr:postcode":"08013",
    "addr:street":"Carrer De Diputacio",
    "iso:country":"ES",
    "sg:address":"Carrer de Diputacio, 391",
    "sg:city":"Barcelona",
    "sg:orig_category":"Farmacias",
    "sg:phone":"+34 932 45 43 91",
    "sg:postcode":"08013",
    "sg:province":"Barcelona",
    "wof:name":"Sales Boleda Emilio",
    "wof:placetype":"venue"
},
  "geometry": {"coordinates":[2.1761369705,41.3974075317],"type":"Point"}
}