{
  "type": "Feature",
  "properties": {
    "iso:country":"ES",
    "sg:address":"Pg Gracia, 27",
    "sg:city":"Barcelona",
    "sg:orig_category":"Jardiner\u00cdas, Vegetales, Art\u00cdculos De Jardiner\u00cda (al Por Menor)",
    "sg:phone":"+34 934 87 12 82",
    "sg:postcode":"08007",
    "sg:province":"Barcelona",
    "wof:name":"Miguelez Domingo Olga",
    "wof:placetype":"venue"
},
  "geometry": {"coordinates":[2.1662418842,41.3906707764],"type":"Point"}
}