{
  "type": "Feature",
  "properties": {
    "iso:country":"ES",
    "sg:address":"Calle de Doce De Octubre, 14",
    "sg:city":"Mieres",
    "sg:orig_category":"Ropa Para Se\u00d1oras Y Caballeros (al Por Menor)",
    "sg:phone":"+34 985 46 73 97",
    "sg:postcode":"33600",
    "sg:province":"Asturias",
    "wof:name":"Textil Suarez S.l.",
    "wof:placetype":"venue"
},
  "geometry": {"coordinates":[-5.7735939026,43.250793457],"type":"Point"}
}