{
  "type": "Feature",
  "properties": {
    "iso:country":"ES",
    "sg:address":"Plaz Poeta Vicente Gaos, 4",
    "sg:city":"Valencia",
    "sg:orig_category":"Productos Qu\u00cdmicos (fabricaci\u00d3n, Al Por Mayor)",
    "sg:phone":"+34 963 89 06 34",
    "sg:postcode":"46021",
    "sg:province":"Valencia",
    "wof:name":"Ensayos Y Asesoramiento Agricola S.l.l.",
    "wof:placetype":"venue"
},
  "geometry": {"coordinates":[-0.3495619893,39.4775695801],"type":"Point"}
}