{
  "type": "Feature",
  "properties": {
    "addr:full":"Calle de Andra Mari Kalea, 18 Durango Vizcaya 48200",
    "addr:housenumber":"18",
    "addr:postcode":"48200",
    "addr:street":"Calle De Andra Mari Kalea",
    "iso:country":"ES",
    "sg:address":"Calle de Andra Mari Kalea, 18",
    "sg:city":"Durango",
    "sg:orig_category":"Complementos De Vestir (al Por Menor)",
    "sg:phone":"+34 946 20 35 25",
    "sg:postcode":"48200",
    "sg:province":"Vizcaya",
    "wof:name":"Maria Nieves Hernandez Ramos",
    "wof:placetype":"venue"
},
  "geometry": {"coordinates":[-2.6308920383,43.167678833],"type":"Point"}
}