{
  "type": "Feature",
  "properties": {
    "addr:full":"Calle de Camino De Murcia, S/n Cieza Murcia 30530",
    "addr:housenumber":"s / n",
    "addr:postcode":"30530",
    "addr:street":"Calle De Camino De Murcia",
    "iso:country":"ES",
    "sg:address":"Calle de Camino De Murcia, S/n",
    "sg:city":"Cieza",
    "sg:orig_category":"Distribuci\u00d3n De Petr\u00d3leo Y Derivados",
    "sg:phone":"+34 968 45 40 52",
    "sg:postcode":"30530",
    "sg:province":"Murcia",
    "wof:name":"Osdaframa S.l.",
    "wof:placetype":"venue"
},
  "geometry": {"coordinates":[-1.413844347,38.2368812561],"type":"Point"}
}