{
  "type": "Feature",
  "properties": {
    "addr:full":"Calle de Juan Pantoja, 28 Madrid Madrid 28039",
    "addr:housenumber":"28",
    "addr:postcode":"madrid;28039",
    "addr:street":"Calle De Juan Pantoja",
    "iso:country":"ES",
    "sg:address":"Calle de Juan Pantoja, 28",
    "sg:city":"Madrid",
    "sg:orig_category":"Administradores De Bienes Y Delegados De Comunidades De Propietarios",
    "sg:phone":"+34 915 53 63 96",
    "sg:postcode":"28039",
    "sg:province":"Madrid",
    "wof:name":"G.m. Fincas S.l.",
    "wof:placetype":"venue"
},
  "geometry": {"coordinates":[-3.7056570053,40.4502868652],"type":"Point"}
}