{
  "type": "Feature",
  "properties": {
    "addr:full":"Ctra Barcelona, 75 Cerdanyola Valles Barcelona 08290",
    "addr:housenumber":"75",
    "addr:postcode":"08290",
    "addr:street":"Ctra Barcelona;Valles Barcelona",
    "iso:country":"ES",
    "sg:address":"Ctra Barcelona, 75",
    "sg:city":"Cerdanyola Valles",
    "sg:orig_category":"Comadronas",
    "sg:phone":"+34 936 92 20 10",
    "sg:postcode":"08290",
    "sg:province":"Barcelona",
    "wof:name":"Ricart Gil Margarita",
    "wof:placetype":"venue"
},
  "geometry": {"coordinates":[2.149461031,41.4922561646],"type":"Point"}
}