{
  "type": "Feature",
  "properties": {
    "iso:country":"ES",
    "sg:address":"Ptge Joan Puig, 4",
    "sg:city":"Vic",
    "sg:orig_category":"Plomeros",
    "sg:phone":"+34 938 86 12 13",
    "sg:postcode":"08500",
    "sg:province":"Barcelona",
    "wof:name":"Parareda Pujols Jaume",
    "wof:placetype":"venue"
},
  "geometry": {"coordinates":[2.2543070316,41.9332695007],"type":"Point"}
}