{
  "type": "Feature",
  "properties": {
    "addr:full":"Calle de Constitucion, 26 Brozas C\u00e1ceres 10950",
    "addr:housenumber":"26",
    "addr:postcode":"10950",
    "addr:street":"Calle De Constitucion;Ca\u0301Ceres",
    "iso:country":"ES",
    "sg:address":"Calle de Constitucion, 26",
    "sg:city":"Brozas",
    "sg:orig_category":"Molduras, Junquillos, Listones Y Molduras Perforadas",
    "sg:phone":"+34 927 39 50 09",
    "sg:postcode":"10950",
    "sg:province":"C\u00e1ceres",
    "wof:name":"Barriga Alvarez Tomas",
    "wof:placetype":"venue"
},
  "geometry": {"coordinates":[-6.7784719467,39.6120872498],"type":"Point"}
}