{
  "type": "Feature",
  "properties": {
    "addr:full":"Calle de Zalmedina, 4 Zaragoza Zaragoza 50015",
    "addr:housenumber":"4",
    "addr:postcode":"50015",
    "addr:street":"Calle De Zalmedina",
    "iso:country":"ES",
    "sg:address":"Calle de Zalmedina, 4",
    "sg:city":"Zaragoza",
    "sg:orig_category":"Naipes, Carteles, Artilugios",
    "sg:phone":"+34 976 46 64 02",
    "sg:postcode":"50015",
    "sg:province":"Zaragoza",
    "wof:name":"Pablo Cabrero Jose Manuel De",
    "wof:placetype":"venue"
},
  "geometry": {"coordinates":[-0.878493011,41.6604652405],"type":"Point"}
}