{
  "type": "Feature",
  "properties": {
    "iso:country":"ES",
    "sg:address":"Calle de Rosas, 6",
    "sg:city":"Horche",
    "sg:orig_category":"Ingeniero",
    "sg:phone":"+34 949 29 11 19",
    "sg:postcode":"19140",
    "sg:province":"Guadalajara",
    "wof:name":"Julian Domarco S.l.",
    "wof:placetype":"venue"
},
  "geometry": {"coordinates":[-3.0682189465,40.5641479492],"type":"Point"}
}