{
  "type": "Feature",
  "properties": {
    "iso:country":"ES",
    "sg:address":"Calle de Metales (de Los), 21",
    "sg:city":"Humanes De Madrid",
    "sg:orig_category":"Quincaller\u00cda (al Por Menor)",
    "sg:phone":"+34 916 90 16 45",
    "sg:postcode":"28970",
    "sg:province":"Madrid",
    "wof:name":"Ferreteria Cuadrado Hijos S.l",
    "wof:placetype":"venue"
},
  "geometry": {"coordinates":[-3.8232860565,40.2677764893],"type":"Point"}
}