{
  "type": "Feature",
  "properties": {
    "addr:full":"Carrer de Doctor Trueta, 1 Manresa Barcelona 08243",
    "addr:housenumber":"1",
    "addr:postcode":"08243",
    "addr:street":"Carrer De Doctor Trueta",
    "iso:country":"ES",
    "sg:address":"Carrer de Doctor Trueta, 1",
    "sg:city":"Manresa",
    "sg:orig_category":"Florister\u00cdas",
    "sg:phone":"+34 938 74 28 77",
    "sg:postcode":"08243",
    "sg:province":"Barcelona",
    "wof:name":"Clotet Sala Angela",
    "wof:placetype":"venue"
},
  "geometry": {"coordinates":[1.8322759867,41.7352218628],"type":"Point"}
}