{
  "type": "Feature",
  "properties": {
    "iso:country":"ES",
    "sg:address":"Calle de Tia Javiera, 19",
    "sg:city":"Loranca",
    "sg:orig_category":"Cristaler\u00cdas",
    "sg:phone":"+34 916 85 51 81",
    "sg:postcode":"28942",
    "sg:province":"Madrid",
    "wof:name":"Mtc One World Shop S.l.",
    "wof:placetype":"venue"
},
  "geometry": {"coordinates":[-3.8407940865,40.3041992188],"type":"Point"}
}