{
  "type": "Feature",
  "properties": {
    "iso:country":"ES",
    "sg:address":"Rua Garcia Lorca (de), 7",
    "sg:city":"Santiago De Compostela",
    "sg:orig_category":"Venta, Instalaci\u00d3n, Reparaci\u00d3n De Antenas Para Televisi\u00d3n",
    "sg:phone":"+34 981 56 32 59",
    "sg:postcode":"15704",
    "sg:province":"La Coru\u00f1a",
    "wof:name":"Becerra Telecom S.l.",
    "wof:placetype":"venue"
},
  "geometry": {"coordinates":[-8.5371761322,42.8902931213],"type":"Point"}
}