{
  "type": "Feature",
  "properties": {
    "addr:full":"Psaj Azahares (los), S/n Sevilla Sevilla 41003",
    "addr:postcode":"41003",
    "addr:street":"Los S / N",
    "iso:country":"ES",
    "sg:address":"Psaj Azahares (los), S/n",
    "sg:city":"Sevilla",
    "sg:orig_category":"Centros Empresariales",
    "sg:phone":"+34 954 50 24 24",
    "sg:postcode":"41003",
    "sg:province":"Sevilla",
    "wof:name":"Pepa & Adela S.c.",
    "wof:placetype":"venue"
},
  "geometry": {"coordinates":[-5.9933772087,37.3938102722],"type":"Point"}
}