{
  "type": "Feature",
  "properties": {
    "addr:full":"Caldereria, 1 Iru\u00f1a Navarra 31001",
    "addr:housenumber":"1",
    "addr:postcode":"31001",
    "addr:street":"Caldereria",
    "iso:country":"ES",
    "sg:address":"Caldereria, 1",
    "sg:city":"Iru\u00f1a",
    "sg:orig_category":"Promotores Constructores",
    "sg:phone":"+34 948 22 41 31",
    "sg:postcode":"31001",
    "sg:province":"Navarra",
    "wof:name":"San Martin Boade Jesus",
    "wof:placetype":"venue"
},
  "geometry": {"coordinates":[-1.6423490047,42.8187866211],"type":"Point"}
}