{
  "type": "Feature",
  "properties": {
    "iso:country":"ES",
    "sg:address":"Calle de Nueva, S/n",
    "sg:city":"Villanueva Del Rio",
    "sg:orig_category":"Institutos M\u00c9dicos",
    "sg:phone":"+34 954 74 89 05",
    "sg:postcode":"41359",
    "sg:province":"Sevilla",
    "wof:name":"Servicio Andaluz De Salud",
    "wof:placetype":"venue"
},
  "geometry": {"coordinates":[-5.6900391579,37.6246414185],"type":"Point"}
}