{
  "type": "Feature",
  "properties": {
    "iso:country":"ES",
    "sg:address":"Pase Santa Maria De La Cabeza, 135",
    "sg:city":"Madrid",
    "sg:orig_category":"Molduras, Junquillos, Listones Y Molduras Perforadas",
    "sg:phone":"+34 914 69 03 15",
    "sg:postcode":"28026",
    "sg:province":"Madrid",
    "wof:name":"Barbeito Reino Jose",
    "wof:placetype":"venue"
},
  "geometry": {"coordinates":[-3.7128129005,40.3890113831],"type":"Point"}
}