{
  "type": "Feature",
  "properties": {
    "addr:full":"Calle de Concepcion, 46 Campo Criptana Ciudad Real 13610",
    "addr:housenumber":"46",
    "addr:postcode":"13610",
    "addr:street":"Calle De Concepcion;Criptana",
    "iso:country":"ES",
    "sg:address":"Calle de Concepcion, 46",
    "sg:city":"Campo Criptana",
    "sg:orig_category":"Tintes (fabricaci\u00d3n, Al Por Mayor)",
    "sg:phone":"+34 926 56 35 92",
    "sg:postcode":"13610",
    "sg:province":"Ciudad Real",
    "wof:name":"Tinte Valencia Campo De Criptana",
    "wof:placetype":"venue"
},
  "geometry": {"coordinates":[-3.1224145889,39.4031791687],"type":"Point"}
}