{
  "type": "Feature",
  "properties": {
    "addr:full":"Carrer de Gran De Sant Andreu, 62 Barcelona Barcelona 08030",
    "addr:housenumber":"62",
    "addr:postcode":"08030",
    "addr:street":"Carrer De Gran De Sant Andreu",
    "iso:country":"ES",
    "sg:address":"Carrer de Gran De Sant Andreu, 62",
    "sg:city":"Barcelona",
    "sg:orig_category":"Peluqueros: De Se\u00d1oras",
    "sg:phone":"+34 933 11 21 51",
    "sg:postcode":"08030",
    "sg:province":"Barcelona",
    "wof:name":"Angli Jane Juan",
    "wof:placetype":"venue"
},
  "geometry": {"coordinates":[2.1901350021,41.4293289185],"type":"Point"}
}