{
  "type": "Feature",
  "properties": {
    "iso:country":"ES",
    "sg:address":"Carrer de Alaba, 45",
    "sg:city":"Barcelona",
    "sg:orig_category":"Muebles, Minoristas",
    "sg:phone":"+34 933 00 61 04",
    "sg:postcode":"08005",
    "sg:province":"Barcelona",
    "wof:name":"Garcia Carbellido Santiago",
    "wof:placetype":"venue"
},
  "geometry": {"coordinates":[2.1957070827,41.3950462341],"type":"Point"}
}