{
  "type": "Feature",
  "properties": {
    "iso:country":"ES",
    "sg:address":"Calle de Santa Natalia, S/n",
    "sg:city":"Nules",
    "sg:orig_category":"Asilos De Ancianos. Centros Privados",
    "sg:phone":"+34 964 67 15 57",
    "sg:postcode":"12520",
    "sg:province":"Castell\u00f3n",
    "wof:name":"Residencia De Ancianos Virgen De La Soledad",
    "wof:placetype":"venue"
},
  "geometry": {"coordinates":[-0.1605740041,39.8558692932],"type":"Point"}
}