{
  "type": "Feature",
  "properties": {
    "iso:country":"ES",
    "sg:address":"Calle de Africa, S/n",
    "sg:city":"Polan",
    "sg:orig_category":"Lacadores",
    "sg:phone":"+34 925 37 06 63",
    "sg:postcode":"45161",
    "sg:province":"Toledo",
    "wof:name":"Torija Navas Javier",
    "wof:placetype":"venue"
},
  "geometry": {"coordinates":[-4.1755552292,39.7862892151],"type":"Point"}
}