{
  "type": "Feature",
  "properties": {
    "iso:country":"ES",
    "sg:address":"Luga Finca Vega Del Moral, 17",
    "sg:city":"Lobon",
    "sg:orig_category":"Iglesia Cat\u00d3lica",
    "sg:phone":"+34 924 44 74 17",
    "sg:postcode":"06498",
    "sg:province":"Badajoz",
    "wof:name":"Parroquia Nuestra Se\u00f1ora De La Asuncion",
    "wof:placetype":"venue"
},
  "geometry": {"coordinates":[-6.6271691322,38.8500518799],"type":"Point"}
}