{
  "type": "Feature",
  "properties": {
    "iso:country":"ES",
    "sg:address":"Carrer de Lepant, 290",
    "sg:city":"Barcelona",
    "sg:orig_category":"Ropa Y Art\u00cdculos Pre",
    "sg:phone":"+34 934 46 09 47",
    "sg:postcode":"08013",
    "sg:province":"Barcelona",
    "wof:name":"Hannisyan  Karine",
    "wof:placetype":"venue"
},
  "geometry": {"coordinates":[2.1758730412,41.4052658081],"type":"Point"}
}