{
  "type": "Feature",
  "properties": {
    "addr:full":"Calle de Artilleria, 2 Valladolid Valladolid 47013",
    "addr:housenumber":"2",
    "addr:postcode":"47013",
    "addr:street":"Calle De Artilleria",
    "iso:country":"ES",
    "sg:address":"Calle de Artilleria, 2",
    "sg:city":"Valladolid",
    "sg:orig_category":"Empresas De Carpinter\u00cda",
    "sg:phone":"+34 983 23 04 84",
    "sg:postcode":"47013",
    "sg:province":"Valladolid",
    "wof:name":"Manuel Gutierrez Vicente",
    "wof:placetype":"venue"
},
  "geometry": {"coordinates":[-4.7242751122,41.6362609863],"type":"Point"}
}