{
  "type": "Feature",
  "properties": {
    "addr:full":"Calle de Juan Padron, 35 Orotava Santa Cruz De Tenerife 38300",
    "addr:housenumber":"35",
    "addr:postcode":"38300",
    "addr:street":"Calle De Juan Padron",
    "iso:country":"ES",
    "sg:address":"Calle de Juan Padron, 35",
    "sg:city":"Orotava",
    "sg:orig_category":"Mec\u00c1nico Del Autom\u00d3vil",
    "sg:phone":"+34 922 32 62 52",
    "sg:postcode":"38300",
    "sg:province":"Santa Cruz De Tenerife",
    "wof:name":"Jimenez Gonzalez Juan Antonio",
    "wof:placetype":"venue"
},
  "geometry": {"coordinates":[-16.5225028992,28.392950058],"type":"Point"}
}