{
  "type": "Feature",
  "properties": {
    "iso:country":"ES",
    "sg:address":"Rbla Pompeu Fabra, 32",
    "sg:city":"Mollet Valles",
    "sg:orig_category":"Publicidad (soportes Y Gesti\u00d3n)",
    "sg:phone":"+34 935 70 52 59",
    "sg:postcode":"08100",
    "sg:province":"Barcelona",
    "sg:website":"www.contrapunt.tk",
    "wof:name":"Contrapunt S.c.c.l.",
    "wof:placetype":"venue"
},
  "geometry": {"coordinates":[2.2188720703,41.540271759],"type":"Point"}
}