{
  "type": "Feature",
  "properties": {
    "iso:country":"ES",
    "sg:address":"Pl Catalunya, 5",
    "sg:city":"Manresa",
    "sg:orig_category":"Inmobiliaria (agencias)",
    "sg:phone":"+34 938 72 63 16",
    "sg:postcode":"08242",
    "sg:province":"Barcelona",
    "wof:name":"Fincas Born S.l.",
    "wof:placetype":"venue"
},
  "geometry": {"coordinates":[1.8194489479,41.7287216187],"type":"Point"}
}