{
  "type": "Feature",
  "properties": {
    "addr:full":"Calle de Calvo Sotelo, 21 Logro\u00f1o La Rioja 26003",
    "addr:housenumber":"21",
    "addr:postcode":"26003",
    "addr:street":"Calle De Calvo Sotelo;Rioja",
    "iso:country":"ES",
    "sg:address":"Calle de Calvo Sotelo, 21",
    "sg:city":"Logro\u00f1o",
    "sg:orig_category":"Aparatos E Instalaci\u00d3n De Regad\u00cdos",
    "sg:phone":"+34 941 23 10 55",
    "sg:postcode":"26003",
    "sg:province":"La Rioja",
    "wof:name":"Ferreteria Y Regalos Lopez Suberviola S.l.",
    "wof:placetype":"venue"
},
  "geometry": {"coordinates":[-2.4413940907,42.464050293],"type":"Point"}
}