{
  "type": "Feature",
  "properties": {
    "addr:full":"Carr Gardisso, 3 Vila Girona 17490",
    "addr:housenumber":"3",
    "addr:postcode":"17490",
    "addr:street":"Carr Gardisso",
    "iso:country":"ES",
    "sg:address":"Carr Gardisso, 3",
    "sg:city":"Vila",
    "sg:orig_category":"Droguer\u00cdas (al Por Menor)",
    "sg:phone":"+34 972 12 08 23",
    "sg:postcode":"17490",
    "sg:province":"Girona",
    "wof:name":"Zaragoza Vilanova Laura",
    "wof:placetype":"venue"
},
  "geometry": {"coordinates":[2.8236999512,41.9817962646],"type":"Point"}
}