{
  "type": "Feature",
  "properties": {
    "addr:full":"Calle de Libertad, 37 Alcazar S. Juan Ciudad Real 13600",
    "addr:housenumber":"37",
    "addr:postcode":"13600",
    "addr:street":"Calle De Libertad;Alcazar S. Juan Ciudad Real",
    "iso:country":"ES",
    "sg:address":"Calle de Libertad, 37",
    "sg:city":"Alcazar S. Juan",
    "sg:orig_category":"Inmobiliaria (agencias)",
    "sg:phone":"+34 926 54 22 55",
    "sg:postcode":"13600",
    "sg:province":"Ciudad Real",
    "wof:name":"Indeco S.l.",
    "wof:placetype":"venue"
},
  "geometry": {"coordinates":[-3.2179589272,39.3963317871],"type":"Point"}
}