{
  "type": "Feature",
  "properties": {
    "iso:country":"ES",
    "sg:address":"Calle de Peladoras (las), 10",
    "sg:city":"Milla Del Rio",
    "sg:orig_category":"Hilaturas, Hilos Y Actividades Relacionadas",
    "sg:phone":"+34 987 35 82 28",
    "sg:postcode":"24283",
    "sg:province":"Le\u00f3n",
    "wof:name":"Textil Orbiga S L L",
    "wof:placetype":"venue"
},
  "geometry": {"coordinates":[-5.8473238945,42.571975708],"type":"Point"}
}