{
  "type": "Feature",
  "properties": {
    "addr:full":"Cruceiro, 11 Cenlle Ourense 32454",
    "addr:housenumber":"11",
    "addr:postcode":"32454",
    "addr:street":"Cruceiro",
    "iso:country":"ES",
    "sg:address":"Cruceiro, 11",
    "sg:city":"Cenlle",
    "sg:orig_category":"Farmacias",
    "sg:phone":"+34 988 40 40 55",
    "sg:postcode":"32454",
    "sg:province":"Ourense",
    "wof:name":"Elena Rodriguez Lamela Y Maria Jose Rodriguez Lamela S.c.",
    "wof:placetype":"venue"
},
  "geometry": {"coordinates":[-8.0893125534,42.3414154053],"type":"Point"}
}