{
  "type": "Feature",
  "properties": {
    "iso:country":"ES",
    "sg:address":"Carr Sevilla, (de), 6",
    "sg:city":"Carlet",
    "sg:orig_category":"Mec\u00c1nico Del Autom\u00d3vil",
    "sg:phone":"+34 962 53 07 74",
    "sg:postcode":"46240",
    "sg:province":"Valencia",
    "wof:name":"Hermanos Sebastian Hervas S. L.",
    "wof:placetype":"venue"
},
  "geometry": {"coordinates":[-0.519957006,39.2225456238],"type":"Point"}
}