{
  "type": "Feature",
  "properties": {
    "addr:full":"Barr Sorriba, 7 Liencres Cantabria 39120",
    "addr:housenumber":"7",
    "addr:postcode":"39120",
    "addr:street":"Sorriba",
    "iso:country":"ES",
    "sg:address":"Barr Sorriba, 7",
    "sg:city":"Liencres",
    "sg:orig_category":"Centros Empresariales",
    "sg:phone":"+34 942 57 82 36",
    "sg:postcode":"39120",
    "sg:province":"Cantabria",
    "wof:name":"Barriuso Abad Alberto",
    "wof:placetype":"venue"
},
  "geometry": {"coordinates":[-3.9269039631,43.4604797363],"type":"Point"}
}