{
  "type": "Feature",
  "properties": {
    "iso:country":"ES",
    "sg:address":"Avda Juan Xxiii, 2",
    "sg:city":"Logro\u00f1o",
    "sg:orig_category":"Doctores En Medicina",
    "sg:phone":"+34 941 23 70 87",
    "sg:postcode":"26003",
    "sg:province":"La Rioja",
    "wof:name":"Gonzalez Murga Jesus",
    "wof:placetype":"venue"
},
  "geometry": {"coordinates":[-2.4417934418,42.4649429321],"type":"Point"}
}