{
  "type": "Feature",
  "properties": {
    "iso:country":"ES",
    "sg:address":"Carrer de Sant Francesc Xavier, 42",
    "sg:city":"Pego",
    "sg:orig_category":"Reposter\u00cdas",
    "sg:phone":"+34 965 57 11 31",
    "sg:postcode":"03780",
    "sg:province":"Alicante",
    "wof:name":"Pastor Cardona Luis",
    "wof:placetype":"venue"
},
  "geometry": {"coordinates":[-0.1186570004,38.8395195007],"type":"Point"}
}