{
  "type": "Feature",
  "properties": {
    "iso:country":"ES",
    "sg:address":"Calle de Capitan Eliseo Lopez Ordu\u00d1a, 5",
    "sg:city":"Palmas De Gran Canaria",
    "sg:orig_category":"Asesor\u00cda Fiscal Y Jur\u00cddica",
    "sg:phone":"+34 928 25 34 60",
    "sg:postcode":"35014",
    "sg:province":"Las Palmas",
    "wof:name":"Luna Manzanares Miguel De",
    "wof:placetype":"venue"
},
  "geometry": {"coordinates":[-15.4283103943,28.1160621643],"type":"Point"}
}