{
  "type": "Feature",
  "properties": {
    "iso:country":"ES",
    "sg:address":"Calle de Plata, 47",
    "sg:city":"Moraleja Enmedio",
    "sg:orig_category":"Panader\u00cdas, Pasteler\u00cdas, Boller\u00cda Industriale (fabricaci\u00d3n, Al Por Mayor)",
    "sg:phone":"+34 916 09 48 63",
    "sg:postcode":"28950",
    "sg:province":"Madrid",
    "wof:name":"Productos Quintana S.l.",
    "wof:placetype":"venue"
},
  "geometry": {"coordinates":[-3.8480761051,40.2649307251],"type":"Point"}
}