{
  "type": "Feature",
  "properties": {
    "iso:country":"ES",
    "sg:address":"Rua Ourense, 84",
    "sg:city":"Lugo",
    "sg:orig_category":"Doctores En Medicina",
    "sg:phone":"+34 982 20 08 55",
    "sg:postcode":"27004",
    "sg:province":"Lugo",
    "wof:name":"Sanchez Fernandez De La Vega Carlos",
    "wof:placetype":"venue"
},
  "geometry": {"coordinates":[-7.5655531883,43.0157356262],"type":"Point"}
}