{
  "type": "Feature",
  "properties": {
    "addr:full":"Rond General Mitre, 172 Barcelona Barcelona 08006",
    "addr:housenumber":"172",
    "addr:postcode":"08006",
    "addr:street":"Mitre",
    "iso:country":"ES",
    "sg:address":"Rond General Mitre, 172",
    "sg:city":"Barcelona",
    "sg:orig_category":"Motocicletas (agentes, Concesionarios)",
    "sg:phone":"+34 932 12 57 98",
    "sg:postcode":"08006",
    "sg:province":"Barcelona",
    "wof:name":"Saito Yusani Kalishi S.l.",
    "wof:placetype":"venue"
},
  "geometry": {"coordinates":[2.1413929462,41.4045333862],"type":"Point"}
}