{
  "type": "Feature",
  "properties": {
    "iso:country":"ES",
    "sg:address":"Calle de Genova, 2",
    "sg:city":"Madrid",
    "sg:orig_category":"Parques De Atracciones Y Centros De Esparcimiento",
    "sg:phone":"+34 913 19 61 39",
    "sg:postcode":"28004",
    "sg:province":"Madrid",
    "wof:name":"Uniplay S.a.",
    "wof:placetype":"venue"
},
  "geometry": {"coordinates":[-3.6952419281,40.4273071289],"type":"Point"}
}