{
  "type": "Feature",
  "properties": {
    "iso:country":"ES",
    "sg:address":"Calle de Ruiz Bona, 2",
    "sg:city":"Higuera Vargas",
    "sg:orig_category":"Cr\u00cda De Animales",
    "sg:phone":"+34 924 42 40 20",
    "sg:postcode":"06132",
    "sg:province":"Badajoz",
    "wof:name":"Terron Diaz Julio",
    "wof:placetype":"venue"
},
  "geometry": {"coordinates":[-6.9750490189,38.4452590942],"type":"Point"}
}