{
  "type": "Feature",
  "properties": {
    "addr:full":"Carrer de Marinada, 18 S. Celoni Barcelona 08470",
    "addr:housenumber":"18",
    "addr:postcode":"08470",
    "addr:street":"Carrer De Marinada;S. Celoni Barcelona",
    "iso:country":"ES",
    "sg:address":"Carrer de Marinada, 18",
    "sg:city":"S. Celoni",
    "sg:orig_category":"Transportes Por V\u00cdas Navegables",
    "sg:phone":"+34 938 67 29 54",
    "sg:postcode":"08470",
    "sg:province":"Barcelona",
    "wof:name":"Nicolau Antolinez Jose",
    "wof:placetype":"venue"
},
  "geometry": {"coordinates":[2.4807589054,41.6841621399],"type":"Point"}
}