{
  "type": "Feature",
  "properties": {
    "iso:country":"ES",
    "sg:address":"Avda Lopez Blanco, 18",
    "sg:city":"Celanova",
    "sg:orig_category":"Arquitectos",
    "sg:phone":"+34 988 45 16 27",
    "sg:postcode":"32800",
    "sg:province":"Ourense",
    "wof:name":"Basalo Arquictectos S.l.",
    "wof:placetype":"venue"
},
  "geometry": {"coordinates":[-7.9557709694,42.154800415],"type":"Point"}
}