{
  "type": "Feature",
  "properties": {
    "iso:country":"ES",
    "sg:address":"Av Mare Deu De Montserrat, 245",
    "sg:city":"Barcelona",
    "sg:orig_category":"Muebles Y Accesorios Para Cocinas Y Cuartos De Ba\u00d1o (al Por Menor)",
    "sg:phone":"+34 934 46 02 01",
    "sg:postcode":"08041",
    "sg:province":"Barcelona",
    "wof:name":"Oromi Llado Concepcion",
    "wof:placetype":"venue"
},
  "geometry": {"coordinates":[2.1752090454,41.4234161377],"type":"Point"}
}