{
  "type": "Feature",
  "properties": {
    "addr:full":"Calle de Celleruelo, S/n Pola De Siero Asturias 33510",
    "addr:housenumber":"s",
    "addr:postcode":"33510",
    "addr:street":"Calle De Celleruelo;/ N",
    "iso:country":"ES",
    "sg:address":"Calle de Celleruelo, S/n",
    "sg:city":"Pola De Siero",
    "sg:orig_category":"Ropa Para Ni\u00d1os (al Por Menor)",
    "sg:phone":"+34 985 72 11 72",
    "sg:postcode":"33510",
    "sg:province":"Asturias",
    "wof:name":"Perez Quintana Pilar",
    "wof:placetype":"venue"
},
  "geometry": {"coordinates":[-5.6654143333,43.3934211731],"type":"Point"}
}