{
  "type": "Feature",
  "properties": {
    "iso:country":"ES",
    "sg:address":"Afores Ponent, S/n",
    "sg:city":"Arenys Mar",
    "sg:orig_category":"Locales Deportivos",
    "sg:phone":"+34 937 95 81 98",
    "sg:postcode":"08350",
    "sg:province":"Barcelona",
    "wof:name":"Mestres March Jordi",
    "wof:placetype":"venue"
},
  "geometry": {"coordinates":[2.5485088825,41.5823173523],"type":"Point"}
}