{
  "type": "Feature",
  "properties": {
    "addr:full":"Ctra Caravaca (de), Km. 0059,0 Corazon De Maria Murcia 30817",
    "addr:postcode":"30817",
    "addr:street":"Ctra Caravaca De Km. 0059,0 Corazon",
    "iso:country":"ES",
    "sg:address":"Ctra Caravaca (de), Km. 0059,0",
    "sg:city":"Corazon De Maria",
    "sg:orig_category":"Contenedores (mercanc\u00cdas)",
    "sg:phone":"+34 968 47 73 07",
    "sg:postcode":"30817",
    "sg:province":"Murcia",
    "wof:name":"Holcim Espa\u00f1a S.a.",
    "wof:placetype":"venue"
},
  "geometry": {"coordinates":[-1.7245190144,37.6462936401],"type":"Point"}
}