{
  "type": "Feature",
  "properties": {
    "iso:country":"ES",
    "sg:address":"C/ Fila Navarros, 18",
    "sg:city":"Alcoi",
    "sg:orig_category":"Ropa De Casa (fabricaci\u00d3n, Al Por Mayor)",
    "sg:phone":"+34 965 54 70 02",
    "sg:postcode":"03801",
    "sg:province":"Alicante",
    "sg:website":"www.lencera.com",
    "wof:name":"Sociedad Textil Lencera S.l.",
    "wof:placetype":"venue"
},
  "geometry": {"coordinates":[-0.4761449993,38.6836662292],"type":"Point"}
}