{
  "type": "Feature",
  "properties": {
    "iso:country":"ES",
    "sg:address":"Plaz Constitucion, S/n",
    "sg:city":"Alcaudete",
    "sg:orig_category":"Molduras, Junquillos, Listones Y Molduras Perforadas",
    "sg:phone":"+34 953 70 82 60",
    "sg:postcode":"23660",
    "sg:province":"Ja\u00e9n",
    "wof:name":"Cebayos Jimenez Manuel Luis",
    "wof:placetype":"venue"
},
  "geometry": {"coordinates":[-4.0797557831,37.5926971436],"type":"Point"}
}