{
  "type": "Feature",
  "properties": {
    "addr:full":"Calle de Luis Galdos, 10 Portugalete Vizcaya 48920",
    "addr:housenumber":"10",
    "addr:postcode":"48920",
    "addr:street":"Calle De Luis Galdos",
    "iso:country":"ES",
    "sg:address":"Calle de Luis Galdos, 10",
    "sg:city":"Portugalete",
    "sg:orig_category":"Molduras, Junquillos, Listones Y Molduras Perforadas",
    "sg:phone":"+34 944 62 11 48",
    "sg:postcode":"48920",
    "sg:province":"Vizcaya",
    "wof:name":"Teciruna S.l.",
    "wof:placetype":"venue"
},
  "geometry": {"coordinates":[-3.0248329639,43.3172683716],"type":"Point"}
}