{
  "type": "Feature",
  "properties": {
    "iso:country":"ES",
    "sg:address":"C/ Joan Lliteras, 42",
    "sg:city":"Manacor",
    "sg:orig_category":"Molduras, Junquillos, Listones Y Molduras Perforadas",
    "sg:phone":"+34 971 55 01 07",
    "sg:postcode":"07500",
    "sg:province":"Islas Baleares",
    "wof:name":"Canovas Jaume Gabriel",
    "wof:placetype":"venue"
},
  "geometry": {"coordinates":[3.207983017,39.5709915161],"type":"Point"}
}