{
  "type": "Feature",
  "properties": {
    "addr:full":"Calle de Rodolfo Gil, 77 Puente-genil C\u00f3rdoba 14500",
    "addr:housenumber":"77",
    "addr:postcode":"14500",
    "addr:street":"Calle De Rodolfo Gil;Co\u0301Rdoba",
    "iso:country":"ES",
    "sg:address":"Calle de Rodolfo Gil, 77",
    "sg:city":"Puente-genil",
    "sg:orig_category":"Electrodom\u00c9sticos (al Por Menor)",
    "sg:phone":"+34 957 60 63 00",
    "sg:postcode":"14500",
    "sg:province":"C\u00f3rdoba",
    "wof:name":"Martin Palos Miguel Angel",
    "wof:placetype":"venue"
},
  "geometry": {"coordinates":[-4.7659029961,37.3879356384],"type":"Point"}
}