{
  "type": "Feature",
  "properties": {
    "addr:full":"Calle de Pozas (de Las), S/n San Lorenzo De El Escorial Madrid 28200",
    "addr:housenumber":"/ n",
    "addr:postcode":"28200",
    "addr:street":"Calle De Pozas De Las S",
    "iso:country":"ES",
    "sg:address":"Calle de Pozas (de Las), S/n",
    "sg:city":"San Lorenzo De El Escorial",
    "sg:orig_category":"Inmobiliaria (agencias)",
    "sg:phone":"+34 918 98 20 15",
    "sg:postcode":"28200",
    "sg:province":"Madrid",
    "sg:website":"www.pinareal.com",
    "wof:name":"Morco S.a.",
    "wof:placetype":"venue"
},
  "geometry": {"coordinates":[-4.1296210289,40.602432251],"type":"Point"}
}