{
  "type": "Feature",
  "properties": {
    "addr:full":"Calle de Santa Pola, 14 Madrid Madrid 28008",
    "addr:housenumber":"14",
    "addr:postcode":"madrid;28008",
    "addr:street":"Calle De Santa Pola",
    "iso:country":"ES",
    "sg:address":"Calle de Santa Pola, 14",
    "sg:city":"Madrid",
    "sg:orig_category":"Administradores De Bienes Y Delegados De Comunidades De Propietarios",
    "sg:phone":"+34 915 59 60 04",
    "sg:postcode":"28008",
    "sg:province":"Madrid",
    "wof:name":"Gomez Morante Juan",
    "wof:placetype":"venue"
},
  "geometry": {"coordinates":[-3.7364220619,40.4317512512],"type":"Point"}
}