{
  "type": "Feature",
  "properties": {
    "iso:country":"ES",
    "sg:address":"Pg Bonanova, 56",
    "sg:city":"Barcelona",
    "sg:orig_category":"M\u00c9dicos: Cancerolog\u00cda, Oncolog\u00cda M\u00c9dica",
    "sg:phone":"+34 934 18 20 89",
    "sg:postcode":"08017",
    "sg:province":"Barcelona",
    "wof:name":"Bellmunt Molins Joaquim",
    "wof:placetype":"venue"
},
  "geometry": {"coordinates":[2.1274020672,41.4034309387],"type":"Point"}
}