{
  "type": "Feature",
  "properties": {
    "addr:full":"Avda Pintor Xavier Soler, 9 Alacant Alicante 03015",
    "addr:housenumber":"9",
    "addr:postcode":"03015",
    "addr:street":"Avda Pintor Xavier Soler",
    "iso:country":"ES",
    "sg:address":"Avda Pintor Xavier Soler, 9",
    "sg:city":"Alacant",
    "sg:orig_category":"Muebles Y Accesorios Para Cocinas Y Cuartos De Ba\u00d1o (al Por Menor)",
    "sg:phone":"+34 965 24 19 71",
    "sg:postcode":"03015",
    "sg:province":"Alicante",
    "wof:name":"Mobilco Dise\u00f1o S.l.",
    "wof:placetype":"venue"
},
  "geometry": {"coordinates":[-0.4676580131,38.3638839722],"type":"Point"}
}