{
  "type": "Feature",
  "properties": {
    "iso:country":"ES",
    "sg:address":"Poligono Ind. Vincios, 42",
    "sg:city":"Vincios",
    "sg:orig_category":"Charcuter\u00cdas (al Por Mayor)",
    "sg:phone":"+34 986 46 80 34",
    "sg:postcode":"36316",
    "sg:province":"Pontevedra",
    "wof:name":"Pondisa S.l.",
    "wof:placetype":"venue"
},
  "geometry": {"coordinates":[-8.7297039032,42.1394195557],"type":"Point"}
}