{
  "type": "Feature",
  "properties": {
    "addr:full":"Rbla Roma Barnes, 7 Lloret Mar Girona 17310",
    "addr:housenumber":"7",
    "addr:postcode":"17310",
    "addr:street":"Rbla Roma Barnes",
    "iso:country":"ES",
    "sg:address":"Rbla Roma Barnes, 7",
    "sg:city":"Lloret Mar",
    "sg:orig_category":"Ingeniero",
    "sg:phone":"+34 972 37 18 99",
    "sg:postcode":"17310",
    "sg:province":"Girona",
    "wof:name":"Parull Inginyeria S.l.",
    "wof:placetype":"venue"
},
  "geometry": {"coordinates":[2.8458909988,41.6982727051],"type":"Point"}
}