{
  "type": "Feature",
  "properties": {
    "iso:country":"ES",
    "sg:address":"Calle de Autogiro, 7",
    "sg:city":"Madrid",
    "sg:orig_category":"Abrasivos Y Superabrasivos (fabricaci\u00d3n, Al Por Mayor)",
    "sg:phone":"+34 913 29 63 13",
    "sg:postcode":"28042",
    "sg:province":"Madrid",
    "sg:website":"www.abrasivosymaquinaria.com",
    "wof:name":"Abrasivos Y Maquinaria S. A.",
    "wof:placetype":"venue"
},
  "geometry": {"coordinates":[-3.58407,40.471474],"type":"Point"}
}