{
  "type": "Feature",
  "properties": {
    "iso:country":"ES",
    "sg:address":"Rua Ramon Gonzalez, 32",
    "sg:city":"Porri\u00f1o",
    "sg:orig_category":"Producci\u00d3n, Distribuci\u00d3n De Electricidad",
    "sg:phone":"+34 986 33 62 81",
    "sg:postcode":"36400",
    "sg:province":"Pontevedra",
    "wof:name":"Electricidad Remeseiro S. L.",
    "wof:placetype":"venue"
},
  "geometry": {"coordinates":[-8.6179990768,42.1610298157],"type":"Point"}
}