{
  "type": "Feature",
  "properties": {
    "addr:full":"Calle de Bizenta Mogel, 6 Vitoria-gasteiz \u00c1lava 01008",
    "addr:housenumber":"6",
    "addr:postcode":"01008",
    "addr:street":"Calle De Bizenta Mogel",
    "iso:country":"ES",
    "sg:address":"Calle de Bizenta Mogel, 6",
    "sg:city":"Vitoria-gasteiz",
    "sg:orig_category":"Edici\u00d3n De Diarios, Revistas, Boletines",
    "sg:phone":"+34 945 14 83 07",
    "sg:postcode":"01008",
    "sg:province":"\u00c1lava",
    "wof:name":"Euskal Editorea S.l.",
    "wof:placetype":"venue"
},
  "geometry": {"coordinates":[-2.6809151173,42.8442955017],"type":"Point"}
}