{
  "type": "Feature",
  "properties": {
    "iso:country":"ES",
    "sg:address":"Ctra Mata De, 97",
    "sg:city":"Palmas De Gran Canaria",
    "sg:orig_category":"Asistencia Social",
    "sg:phone":"+34 928 36 00 66",
    "sg:postcode":"35014",
    "sg:province":"Las Palmas",
    "wof:name":"El Camino De Emaus",
    "wof:placetype":"venue"
},
  "geometry": {"coordinates":[-15.425620079,28.1060180664],"type":"Point"}
}