{
  "type": "Feature",
  "properties": {
    "iso:country":"ES",
    "sg:address":"Carrer de Can Serra Marina, 4",
    "sg:city":"Palma",
    "sg:classifiers":[
        {
            "category":"Arts & Performance",
            "subcategory":"Art Gallery",
            "type":"Entertainment"
        }
    ],
    "sg:phone":"+34 971 22 94 18",
    "sg:postcode":"07012",
    "sg:province":"Islas Baleares",
    "sg:tags":[
        "arte",
        "de",
        "galer\u00cdas"
    ],
    "wof:name":"Artistas E Intelectuales(galeria Blitz",
    "wof:placetype":"venue"
},
  "geometry": {"coordinates":[2.6449849606,39.5714836121],"type":"Point"}
}