{
  "type": "Feature",
  "properties": {
    "iso:country":"ES",
    "sg:address":"Calle de Ciruelo, 25",
    "sg:city":"Herrera Duque",
    "sg:orig_category":"Ense\u00d1anza: Profesiones Art\u00cdsticas",
    "sg:phone":"+34 924 65 01 84",
    "sg:postcode":"06670",
    "sg:province":"Badajoz",
    "wof:name":"Fotos Rafael C.b",
    "wof:placetype":"venue"
},
  "geometry": {"coordinates":[-5.0496797562,39.1676559448],"type":"Point"}
}