{
  "type": "Feature",
  "properties": {
    "addr:full":"Carrer de L'escultor Ordo\u00d1ez, 18 Barcelona Barcelona 08016",
    "addr:housenumber":"18",
    "addr:postcode":"08016",
    "addr:street":"Carrer De L'Escultor Ordon\u0303Ez",
    "iso:country":"ES",
    "sg:address":"Carrer de L'escultor Ordo\u00d1ez, 18",
    "sg:city":"Barcelona",
    "sg:orig_category":"Ropa Para Caballeros (al Por Menor)",
    "sg:phone":"+34 933 49 95 56",
    "sg:postcode":"08016",
    "sg:province":"Barcelona",
    "wof:name":"Monje Yag\u00fce Bonifacia",
    "wof:placetype":"venue"
},
  "geometry": {"coordinates":[2.1743612289,41.4327697754],"type":"Point"}
}