{
  "type": "Feature",
  "properties": {
    "addr:full":"Carrer de Santiago Rusi\u00d1ol, 43 S. Cugat Valles Barcelona 08172",
    "addr:housenumber":"43",
    "addr:postcode":"08172",
    "addr:street":"Carrer De Santiago Rusin\u0303Ol;S. Cugat Valles Barcelona",
    "iso:country":"ES",
    "sg:address":"Carrer de Santiago Rusi\u00d1ol, 43",
    "sg:city":"S. Cugat Valles",
    "sg:orig_category":"Molduras, Junquillos, Listones Y Molduras Perforadas",
    "sg:phone":"+34 936 75 56 77",
    "sg:postcode":"08172",
    "sg:province":"Barcelona",
    "wof:name":"Cardona Castillo Ramon",
    "wof:placetype":"venue"
},
  "geometry": {"coordinates":[2.0836560726,41.4728355408],"type":"Point"}
}