{
  "type": "Feature",
  "properties": {
    "addr:full":"Carrer de Esglesia, 3 Sant Feliu Llobregat Barcelona 08980",
    "addr:housenumber":"3",
    "addr:postcode":"08980",
    "addr:street":"Carrer De Esglesia",
    "iso:country":"ES",
    "sg:address":"Carrer de Esglesia, 3",
    "sg:city":"Sant Feliu Llobregat",
    "sg:orig_category":"Ingeniero",
    "sg:phone":"+34 936 85 22 50",
    "sg:postcode":"08980",
    "sg:province":"Barcelona",
    "wof:name":"Remola Sans Luis",
    "wof:placetype":"venue"
},
  "geometry": {"coordinates":[2.0451419353,41.3805618286],"type":"Point"}
}