{
  "type": "Feature",
  "properties": {
    "addr:full":"Calle de Alejandro Sanchez, 95 Madrid Madrid 28019",
    "addr:housenumber":"95",
    "addr:postcode":"madrid;28019",
    "addr:street":"Calle De Alejandro Sanchez",
    "iso:country":"ES",
    "sg:address":"Calle de Alejandro Sanchez, 95",
    "sg:city":"Madrid",
    "sg:orig_category":"Confecci\u00d3n De Zapatos",
    "sg:phone":"+34 915 60 47 97",
    "sg:postcode":"28019",
    "sg:province":"Madrid",
    "sg:website":"www.maboluda.com",
    "wof:name":"Boluda Geva Miguel Angel",
    "wof:placetype":"venue"
},
  "geometry": {"coordinates":[-3.7184085846,40.389377594],"type":"Point"}
}