{
  "type": "Feature",
  "properties": {
    "iso:country":"ES",
    "sg:address":"Plaza Sakona, 4",
    "sg:city":"Barakaldo",
    "sg:orig_category":"Venta, Instalaci\u00d3n De Sistemas De Alarmas Y Vigilancia",
    "sg:phone":"+34 944 38 93 55",
    "sg:postcode":"48902",
    "sg:province":"Vizcaya",
    "sg:website":"www.apelseguridad.com",
    "wof:name":"Jose Ramon Alcubilla Lopez",
    "wof:placetype":"venue"
},
  "geometry": {"coordinates":[-2.9871730804,43.2919845581],"type":"Point"}
}