{
  "type": "Feature",
  "properties": {
    "addr:full":"Ptda La Pe\u00f1a, 64 Elche Alicante 03296",
    "addr:housenumber":"64",
    "addr:postcode":"03296",
    "addr:street":"Ptda La Pen\u0303A",
    "iso:country":"ES",
    "sg:address":"Ptda La Pe\u00f1a, 64",
    "sg:city":"Elche",
    "sg:orig_category":"Confecci\u00d3n De Zapatos",
    "sg:phone":"+34 965 43 19 19",
    "sg:postcode":"03296",
    "sg:province":"Alicante",
    "wof:name":"Hurtado Gil Carlos",
    "wof:placetype":"venue"
},
  "geometry": {"coordinates":[-0.7447530031,38.227268219],"type":"Point"}
}