{
  "type": "Feature",
  "properties": {
    "iso:country":"ES",
    "sg:address":"Carrer de Gran De Sant Andreu, 99",
    "sg:city":"Barcelona",
    "sg:orig_category":"Electrodom\u00c9sticos (al Por Menor)",
    "sg:phone":"+34 933 46 33 69",
    "sg:postcode":"08030",
    "sg:province":"Barcelona",
    "sg:website":"www.bazarelregalo.com",
    "wof:name":"Tefaur S.l.",
    "wof:placetype":"venue"
},
  "geometry": {"coordinates":[2.1894218922,41.4305038452],"type":"Point"}
}