{
  "type": "Feature",
  "properties": {
    "addr:full":"Conj. S. Luis, 3 Manilva M\u00e1laga 29692",
    "addr:housenumber":"3",
    "addr:postcode":"29692",
    "addr:street":"Conj. S. Luis",
    "iso:country":"ES",
    "sg:address":"Conj. S. Luis, 3",
    "sg:city":"Manilva",
    "sg:orig_category":"Decoraci\u00d3n: Instalaci\u00d3n Y Talleres",
    "sg:phone":"+34 952 89 03 82",
    "sg:postcode":"29692",
    "sg:province":"M\u00e1laga",
    "wof:name":"Pinturas Industriales Ramirez",
    "wof:placetype":"venue"
},
  "geometry": {"coordinates":[-5.2260499001,36.3661231995],"type":"Point"}
}