{
  "type": "Feature",
  "properties": {
    "iso:country":"ES",
    "sg:address":"Muelle Bateria, 1",
    "sg:city":"A Coru\u00f1a",
    "sg:classifiers":[
        {
            "category":"Manufacturing",
            "subcategory":"Building Materials",
            "type":"Manufacturing & Wholesale Goods"
        }
    ],
    "sg:phone":"+34 981 12 25 56",
    "sg:postcode":"15006",
    "sg:province":"A Coru\u00f1a",
    "sg:tags":[
        "cemento",
        "y",
        "de",
        "fabricaci\u00d3n",
        "cal"
    ],
    "wof:name":"Tudela Veguin S.a.",
    "wof:placetype":"venue"
},
  "geometry": {"coordinates":[-8.4013938904,43.3671531677],"type":"Point"}
}