{
  "type": "Feature",
  "properties": {
    "iso:country":"ES",
    "sg:address":"Carrer de Sant Bertomeu, 8",
    "sg:city":"Barcelona",
    "sg:orig_category":"Asociaciones Humanitarias, De Cooperaci\u00d3n, De Acci\u00d3n Social",
    "sg:phone":"+34 934 41 92 87",
    "sg:postcode":"08001",
    "sg:province":"Barcelona",
    "wof:name":"Asociacion Azad Catalu\u00d1a",
    "wof:placetype":"venue"
},
  "geometry": {"coordinates":[2.1688861847,41.3778953552],"type":"Point"}
}