{
  "type": "Feature",
  "properties": {
    "iso:country":"ES",
    "sg:address":"Plaz Cardenal Siliceo, S/n",
    "sg:city":"Toledo",
    "sg:orig_category":"Internados & Ense\u00d1anza Privada",
    "sg:phone":"+34 925 25 37 67",
    "sg:postcode":"45002",
    "sg:province":"Toledo",
    "wof:name":"Instituto Secular Cruzadas De Santa Maria",
    "wof:placetype":"venue"
},
  "geometry": {"coordinates":[-4.0291638374,39.8587989807],"type":"Point"}
}