{
  "type": "Feature",
  "properties": {
    "addr:full":"Calle de Candasnos De, 10 Fraga Huesca 22520",
    "addr:housenumber":"10",
    "addr:postcode":"22520",
    "addr:street":"Calle De Candasnos De",
    "iso:country":"ES",
    "sg:address":"Calle de Candasnos De, 10",
    "sg:city":"Fraga",
    "sg:orig_category":"Panader\u00cdas, Panader\u00cdas",
    "sg:phone":"+34 974 47 02 31",
    "sg:postcode":"22520",
    "sg:province":"Huesca",
    "wof:name":"Dueso Corbalan Pedro",
    "wof:placetype":"venue"
},
  "geometry": {"coordinates":[0.3405410945,41.5224266052],"type":"Point"}
}