{
  "type": "Feature",
  "properties": {
    "iso:country":"ES",
    "sg:address":"Calle de Diego Betancor Suarez, S/n",
    "sg:city":"Palmas De Gran Canaria",
    "sg:orig_category":"Peluquer\u00cdas, Peluquer\u00cda Mixta",
    "sg:phone":"+34 928 41 96 49",
    "sg:postcode":"35012",
    "sg:province":"Las Palmas",
    "wof:name":"Rodriguez Perez Sabina",
    "wof:placetype":"venue"
},
  "geometry": {"coordinates":[-15.4458322525,28.1073112488],"type":"Point"}
}