{
  "type": "Feature",
  "properties": {
    "addr:full":"Avda Inventor Pedro Cawley, 21 Poligono Industrial Salinas De San Jose C\u00e1diz 11500",
    "addr:housenumber":"21",
    "addr:postcode":"11500",
    "addr:street":"Avda Inventor Pedro Cawley;Industrial;Ca\u0301Diz",
    "iso:country":"ES",
    "sg:address":"Avda Inventor Pedro Cawley, 21",
    "sg:city":"Poligono Industrial Salinas De San Jose",
    "sg:orig_category":"Confecci\u00d3n De Zapatos",
    "sg:phone":"+34 956 85 76 49",
    "sg:postcode":"11500",
    "sg:province":"C\u00e1diz",
    "wof:name":"Almacenes Peyco S.l.",
    "wof:placetype":"venue"
},
  "geometry": {"coordinates":[-6.1996545792,36.6145629883],"type":"Point"}
}