{
  "type": "Feature",
  "properties": {
    "addr:full":"Calle de Embajadores, 96 Madrid Madrid 28012",
    "addr:housenumber":"96",
    "addr:postcode":"madrid;28012",
    "addr:street":"Calle De Embajadores",
    "iso:country":"ES",
    "sg:address":"Calle de Embajadores, 96",
    "sg:city":"Madrid",
    "sg:orig_category":"Cl\u00cdnicas Dentales",
    "sg:phone":"+34 915 17 07 10",
    "sg:postcode":"28012",
    "sg:province":"Madrid",
    "wof:name":"Poyato Ariza Serafina",
    "wof:placetype":"venue"
},
  "geometry": {"coordinates":[-3.7009301186,40.4027023315],"type":"Point"}
}