{
  "type": "Feature",
  "properties": {
    "addr:full":"Calle de General Vives, 52 Palmas De Gran Canaria Las Palmas 35007",
    "addr:postcode":"35007",
    "addr:street":"Calle De General Vives 52",
    "iso:country":"ES",
    "sg:address":"Calle de General Vives, 52",
    "sg:city":"Palmas De Gran Canaria",
    "sg:orig_category":"Fabricaci\u00d3n, Importaci\u00d3n, Venta De Material De Telefon\u00cda, Peritelefon\u00cda",
    "sg:phone":"+34 928 27 07 67",
    "sg:postcode":"35007",
    "sg:province":"Las Palmas",
    "wof:name":"Diape Tecnology S.l.",
    "wof:placetype":"venue"
},
  "geometry": {"coordinates":[-15.4312381744,28.1382217407],"type":"Point"}
}