{
  "type": "Feature",
  "properties": {
    "addr:full":"Calle de Sal (de La), 1 Parla Madrid 28980",
    "addr:postcode":"28980",
    "addr:street":"Calle De",
    "iso:country":"ES",
    "sg:address":"Calle de Sal (de La), 1",
    "sg:city":"Parla",
    "sg:orig_category":"Farmacias",
    "sg:phone":"+34 916 05 45 41",
    "sg:postcode":"28980",
    "sg:province":"Madrid",
    "wof:name":"Sanchez Hernandez Maria Del Carmen",
    "wof:placetype":"venue"
},
  "geometry": {"coordinates":[-3.7734029293,40.239025116],"type":"Point"}
}