{
  "type": "Feature",
  "properties": {
    "iso:country":"ES",
    "sg:address":"Calle de Alferez Provisional, 26",
    "sg:city":"Talavera Reina",
    "sg:orig_category":"Contenedores (mercanc\u00cdas)",
    "sg:phone":"+34 925 80 64 80",
    "sg:postcode":"45600",
    "sg:province":"Toledo",
    "wof:name":"Herron Rodrigo Jose",
    "wof:placetype":"venue"
},
  "geometry": {"coordinates":[-4.8295307159,39.965927124],"type":"Point"}
}