{
  "type": "Feature",
  "properties": {
    "iso:country":"ES",
    "sg:address":"Avda General Peron, 26",
    "sg:city":"Madrid",
    "sg:orig_category":"Zapatos (al Por Menor)",
    "sg:phone":"+34 915 55 13 91",
    "sg:postcode":"28020",
    "sg:province":"Madrid",
    "sg:website":"www.gbbravo.com",
    "wof:name":"Comercios Peninsulares De Calzado S.a.",
    "wof:placetype":"venue"
},
  "geometry": {"coordinates":[-3.6952259541,40.452255249],"type":"Point"}
}