{
  "type": "Feature",
  "properties": {
    "iso:country":"ES",
    "sg:address":"Calle de Pintor Cabrera, 19",
    "sg:city":"Alacant",
    "sg:orig_category":"Colchones (fabricaci\u00d3n, Al Por Mayor, Al Por Menor)",
    "sg:phone":"+34 965 13 30 06",
    "sg:postcode":"03003",
    "sg:province":"Alicante",
    "wof:name":"Mobeltodo S.a.",
    "wof:placetype":"venue"
},
  "geometry": {"coordinates":[-0.4921689928,38.3441886902],"type":"Point"}
}