{
  "type": "Feature",
  "properties": {
    "iso:country":"ES",
    "sg:address":"Carrer de Diputacio, 237",
    "sg:city":"Barcelona",
    "sg:orig_category":"Perfumer\u00cda: Materias Primas Y Esencias",
    "sg:phone":"+34 934 87 44 08",
    "sg:postcode":"08007",
    "sg:province":"Barcelona",
    "wof:name":"Masip Jover Pedro Ramon",
    "wof:placetype":"venue"
},
  "geometry": {"coordinates":[2.1644170284,41.3886108398],"type":"Point"}
}