{
  "type": "Feature",
  "properties": {
    "iso:country":"ES",
    "sg:address":"Calle de Afuera, 93",
    "sg:city":"Torquemada",
    "sg:orig_category":"Autob\u00das (explotaci\u00d3n Y Servicios De)",
    "sg:phone":"+34 979 80 00 84",
    "sg:postcode":"34230",
    "sg:province":"Palencia",
    "wof:name":"Marino Y Lerma S.l.",
    "wof:placetype":"venue"
},
  "geometry": {"coordinates":[-4.3193378448,42.034614563],"type":"Point"}
}