{
  "type": "Feature",
  "properties": {
    "addr:full":"Rosario, S/n Albox Almer\u00eda 04800",
    "addr:housenumber":"/ n",
    "addr:postcode":"04800",
    "addr:street":"Rosario S",
    "iso:country":"ES",
    "sg:address":"Rosario, S/n",
    "sg:city":"Albox",
    "sg:orig_category":"Panader\u00cdas, Panader\u00cdas",
    "sg:phone":"+34 950 12 19 75",
    "sg:postcode":"04800",
    "sg:province":"Almer\u00eda",
    "wof:name":"Pasteleria La Peque\u00d1ica S.l.",
    "wof:placetype":"venue"
},
  "geometry": {"coordinates":[-2.1481239796,37.3885307312],"type":"Point"}
}