{
  "type": "Feature",
  "properties": {
    "addr:full":"Carrer de Sant Cristofol, 20 Denia Alicante 03700",
    "addr:housenumber":"20",
    "addr:postcode":"03700",
    "addr:street":"Carrer De Sant Cristofol",
    "iso:country":"ES",
    "sg:address":"Carrer de Sant Cristofol, 20",
    "sg:city":"Denia",
    "sg:orig_category":"Ense\u00d1anza: Peluquer\u00cda Est\u00c9tica",
    "sg:phone":"+34 966 43 51 87",
    "sg:postcode":"03700",
    "sg:province":"Alicante",
    "wof:name":"Grupo 8 Peluqueros Denia S.l.",
    "wof:placetype":"venue"
},
  "geometry": {"coordinates":[0.1045949981,38.8411598206],"type":"Point"}
}