{
  "type": "Feature",
  "properties": {
    "iso:country":"ES",
    "sg:address":"Rond Caballero De La Mancha, 75",
    "sg:city":"Madrid",
    "sg:orig_category":"Centros M\u00c9dicos Y Sociales, Dispensarios",
    "sg:phone":"+34 913 72 16 62",
    "sg:postcode":"28034",
    "sg:province":"Madrid",
    "wof:name":"Sanimed S.l.",
    "wof:placetype":"venue"
},
  "geometry": {"coordinates":[-3.6919250488,40.501789093],"type":"Point"}
}