{
  "type": "Feature",
  "properties": {
    "iso:country":"ES",
    "sg:address":"Calle de Paraiso, 1",
    "sg:city":"Valladolid",
    "sg:orig_category":"Molduras, Junquillos, Listones Y Molduras Perforadas",
    "sg:phone":"+34 983 25 87 50",
    "sg:postcode":"47003",
    "sg:province":"Valladolid",
    "wof:name":"La Espumosa S.l.",
    "wof:placetype":"venue"
},
  "geometry": {"coordinates":[-4.7216758728,41.6546783447],"type":"Point"}
}