{
  "type": "Feature",
  "properties": {
    "addr:full":"Calle de Guatemala, 14 Madrid Madrid 28016",
    "addr:housenumber":"14",
    "addr:postcode":"madrid;28016",
    "addr:street":"Calle De Guatemala",
    "iso:country":"ES",
    "sg:address":"Calle de Guatemala, 14",
    "sg:city":"Madrid",
    "sg:orig_category":"Centros Empresariales",
    "sg:phone":"+34 913 45 40 18",
    "sg:postcode":"28016",
    "sg:province":"Madrid",
    "wof:name":"Sistemas De Gestion Sanitaria S.a.",
    "wof:placetype":"venue"
},
  "geometry": {"coordinates":[-3.6706418991,40.4591522217],"type":"Point"}
}