{
  "type": "Feature",
  "properties": {
    "addr:full":"Avda Madrid, 28 Puebla Montalban Toledo 45516",
    "addr:housenumber":"28",
    "addr:postcode":"45516",
    "addr:street":"Avda Madrid",
    "iso:country":"ES",
    "sg:address":"Avda Madrid, 28",
    "sg:city":"Puebla Montalban",
    "sg:orig_category":"Pompas F\u00danebres, Inhumaciones Y Cremaciones",
    "sg:phone":"+34 925 77 66 91",
    "sg:postcode":"45516",
    "sg:province":"Toledo",
    "wof:name":"Robles Palomo Jose",
    "wof:placetype":"venue"
},
  "geometry": {"coordinates":[-4.3586359024,39.8730583191],"type":"Point"}
}