{
  "type": "Feature",
  "properties": {
    "addr:full":"Calle de Recogidas, 24 Granada Granada 18002",
    "addr:housenumber":"24",
    "addr:postcode":"18002",
    "addr:street":"Calle De Recogidas",
    "iso:country":"ES",
    "sg:address":"Calle de Recogidas, 24",
    "sg:city":"Granada",
    "sg:orig_category":"Asociaciones Humanitarias, De Cooperaci\u00d3n, De Acci\u00d3n Social",
    "sg:phone":"+34 958 25 52 03",
    "sg:postcode":"18002",
    "sg:province":"Granada",
    "sg:website":"www.aldaima.org",
    "wof:name":"Aldaima Asociacion Andaluza De Apoyo A La Infancia",
    "wof:placetype":"venue"
},
  "geometry": {"coordinates":[-3.602355957,37.1720695496],"type":"Point"}
}