{
  "type": "Feature",
  "properties": {
    "iso:country":"ES",
    "sg:address":"Carrer de Joan Prim, 102",
    "sg:city":"Granollers",
    "sg:orig_category":"Florister\u00cdas",
    "sg:phone":"+34 938 49 01 06",
    "sg:postcode":"08402",
    "sg:province":"Barcelona",
    "wof:name":"Brihuega I Jener Teresa",
    "wof:placetype":"venue"
},
  "geometry": {"coordinates":[2.2902479172,41.6124572754],"type":"Point"}
}