{
  "type": "Feature",
  "properties": {
    "iso:country":"ES",
    "sg:address":"Calle de Tenerife (de), 42",
    "sg:city":"Humanes De Madrid",
    "sg:orig_category":"Serigraf\u00cda (material Y Suministros)",
    "sg:phone":"+34 916 90 54 06",
    "sg:postcode":"28970",
    "sg:province":"Madrid",
    "wof:name":"Pre-car 2000 S.l.",
    "wof:placetype":"venue"
},
  "geometry": {"coordinates":[-3.8166790009,40.2700500488],"type":"Point"}
}