{
  "type": "Feature",
  "properties": {
    "addr:full":"Calle de Emilio Valle, 2 Reinosa Cantabria 39200",
    "addr:housenumber":"2",
    "addr:postcode":"39200",
    "addr:street":"Calle De Emilio Valle",
    "iso:country":"ES",
    "sg:address":"Calle de Emilio Valle, 2",
    "sg:city":"Reinosa",
    "sg:orig_category":"Internados & Ense\u00d1anza Privada",
    "sg:phone":"+34 942 75 02 96",
    "sg:postcode":"39200",
    "sg:province":"Cantabria",
    "wof:name":"Colegio Antares",
    "wof:placetype":"venue"
},
  "geometry": {"coordinates":[-4.1443219185,42.997756958],"type":"Point"}
}