{
  "type": "Feature",
  "properties": {
    "addr:full":"Carrer de Lepant, 295 Barcelona Barcelona 08025",
    "addr:housenumber":"295",
    "addr:postcode":"08025",
    "addr:street":"Carrer De Lepant",
    "iso:country":"ES",
    "sg:address":"Carrer de Lepant, 295",
    "sg:city":"Barcelona",
    "sg:orig_category":"Institutos De Belleza",
    "sg:phone":"+34 934 50 25 40",
    "sg:postcode":"08025",
    "sg:province":"Barcelona",
    "wof:name":"Dios Prieto Maria Anunciacion De",
    "wof:placetype":"venue"
},
  "geometry": {"coordinates":[2.1747789383,41.405708313],"type":"Point"}
}