{
  "type": "Feature",
  "properties": {
    "addr:full":"Urb Balco (el), S/n Balco Castell\u00f3n 12594",
    "addr:postcode":"12594",
    "addr:street":"Urb;El S / N Balco Castello\u0301N",
    "iso:country":"ES",
    "sg:address":"Urb Balco (el), S/n",
    "sg:city":"Balco",
    "sg:orig_category":"Reposter\u00cdas",
    "sg:phone":"+34 964 31 07 03",
    "sg:postcode":"12594",
    "sg:province":"Castell\u00f3n",
    "wof:name":"Velazquez Garcia Alberto",
    "wof:placetype":"venue"
},
  "geometry": {"coordinates":[0.135344997,40.0945358276],"type":"Point"}
}