{
  "type": "Feature",
  "properties": {
    "addr:full":"Monasterio Irache, 22 Iru\u00f1a Navarra 31011",
    "addr:housenumber":"22",
    "addr:postcode":"31011",
    "addr:street":"Irache",
    "iso:country":"ES",
    "sg:address":"Monasterio Irache, 22",
    "sg:city":"Iru\u00f1a",
    "sg:orig_category":"Arquitectos",
    "sg:phone":"+34 948 25 56 15",
    "sg:postcode":"31011",
    "sg:province":"Navarra",
    "wof:name":"Bru Roig Belen Y Villarreoel Casado Francisco Javier S.c.",
    "wof:placetype":"venue"
},
  "geometry": {"coordinates":[-1.6596570015,42.817691803],"type":"Point"}
}