{
  "type": "Feature",
  "properties": {
    "iso:country":"ES",
    "sg:address":"Calle de Artemi Semidan, 10",
    "sg:city":"Galdar",
    "sg:orig_category":"\u00d3ptica: Instrumentos (fabricaci\u00d3n)",
    "sg:phone":"+34 928 88 20 61",
    "sg:postcode":"35460",
    "sg:province":"Las Palmas",
    "wof:name":"Dominguez Romero Jose Luis",
    "wof:placetype":"venue"
},
  "geometry": {"coordinates":[-15.6537036896,28.1447601318],"type":"Point"}
}