{
  "type": "Feature",
  "properties": {
    "iso:country":"ES",
    "sg:address":"Avda Jose Antonio, 16",
    "sg:city":"Pe\u00f1iscola",
    "sg:orig_category":"Lencer\u00cda Femenina, Corseter\u00cda, Trajes De Ba\u00d1o (al Por Menor)",
    "sg:phone":"+34 964 48 94 86",
    "sg:postcode":"12598",
    "sg:province":"Castell\u00f3n",
    "wof:name":"Promociones Inmar, Pe\u00d1iscola S.l.",
    "wof:placetype":"venue"
},
  "geometry": {"coordinates":[0.4020929933,40.360042572],"type":"Point"}
}