{
  "type": "Feature",
  "properties": {
    "addr:full":"Avda Jose Antonio, 19 Polan Toledo 45161",
    "addr:housenumber":"19",
    "addr:postcode":"45161",
    "addr:street":"Avda Jose Antonio",
    "iso:country":"ES",
    "sg:address":"Avda Jose Antonio, 19",
    "sg:city":"Polan",
    "sg:orig_category":"Bazares, Art\u00cdculos De Limpieza Y De Cocina (al Por Menor)",
    "sg:phone":"+34 925 37 07 08",
    "sg:postcode":"45161",
    "sg:province":"Toledo",
    "wof:name":"Alce Import S.l",
    "wof:placetype":"venue"
},
  "geometry": {"coordinates":[-4.1634731293,39.790222168],"type":"Point"}
}