{
  "type": "Feature",
  "properties": {
    "iso:country":"ES",
    "sg:address":"Plaz San Jeronimo Hermosilla, 30",
    "sg:city":"Santo Domingo De La Calzada",
    "sg:orig_category":"Ingenier\u00cda, Centros De Estudios (diversos)",
    "sg:phone":"+34 941 34 09 93",
    "sg:postcode":"26250",
    "sg:province":"La Rioja",
    "wof:name":"Ingenieria Agroindustrial Y Servicios De Arquitectura Rioja S.l.",
    "wof:placetype":"venue"
},
  "geometry": {"coordinates":[-2.9541389942,42.4373588562],"type":"Point"}
}