{
  "type": "Feature",
  "properties": {
    "addr:full":"Calle de Roya, 17 Estepa Sevilla 41560",
    "addr:housenumber":"17",
    "addr:postcode":"41560",
    "addr:street":"Calle De Roya;Sevilla",
    "iso:country":"ES",
    "sg:address":"Calle de Roya, 17",
    "sg:city":"Estepa",
    "sg:orig_category":"Molduras, Junquillos, Listones Y Molduras Perforadas",
    "sg:phone":"+34 955 91 40 40",
    "sg:postcode":"41560",
    "sg:province":"Sevilla",
    "wof:name":"Borrego Ruiz Francisco",
    "wof:placetype":"venue"
},
  "geometry": {"coordinates":[-4.8849830627,37.2884101868],"type":"Point"}
}