{
  "type": "Feature",
  "properties": {
    "iso:country":"ES",
    "sg:address":"Calle de Honda, 20",
    "sg:city":"Turleque",
    "sg:orig_category":"Plomeros",
    "sg:phone":"+34 925 32 70 39",
    "sg:postcode":"45789",
    "sg:province":"Toledo",
    "wof:name":"Garrido Fernandez Gregorio",
    "wof:placetype":"venue"
},
  "geometry": {"coordinates":[-3.6111030579,39.6028671265],"type":"Point"}
}