{
  "type": "Feature",
  "properties": {
    "iso:country":"ES",
    "sg:address":"Carrer de Mallorca, 246",
    "sg:city":"Barcelona",
    "sg:orig_category":"Ropa Para Se\u00d1oras (al Por Menor)",
    "sg:phone":"+34 932 15 20 25",
    "sg:postcode":"08008",
    "sg:province":"Barcelona",
    "wof:name":"Balmes Blanch Maria Teresa",
    "wof:placetype":"venue"
},
  "geometry": {"coordinates":[2.1620531082,41.3933067322],"type":"Point"}
}