{
  "type": "Feature",
  "properties": {
    "addr:full":"Pase Zorrilla, 89 Valladolid Valladolid 47008",
    "addr:housenumber":"89",
    "addr:postcode":"47008",
    "addr:street":"Zorrilla",
    "iso:country":"ES",
    "sg:address":"Pase Zorrilla, 89",
    "sg:city":"Valladolid",
    "sg:orig_category":"Cajas De Ahorro",
    "sg:phone":"+34 983 45 77 03",
    "sg:postcode":"47008",
    "sg:province":"Valladolid",
    "sg:website":"www.cajalaboral.es",
    "wof:name":"Caja Laboral Popular",
    "wof:placetype":"venue"
},
  "geometry": {"coordinates":[-4.7927489281,41.6193618774],"type":"Point"}
}