{
  "type": "Feature",
  "properties": {
    "iso:country":"ES",
    "sg:address":"Carrer de Maurici Vilomara, 33",
    "sg:city":"Prat Llobregat",
    "sg:orig_category":"Promotores Constructores",
    "sg:phone":"+34 933 79 03 60",
    "sg:postcode":"08820",
    "sg:province":"Barcelona",
    "wof:name":"Jaime Mones S.a.",
    "wof:placetype":"venue"
},
  "geometry": {"coordinates":[2.0957949162,41.3293495178],"type":"Point"}
}