{
  "type": "Feature",
  "properties": {
    "addr:full":"Calle de Pradollano, 4 Granada Granada 18008",
    "addr:housenumber":"4",
    "addr:postcode":"18008",
    "addr:street":"Calle De Pradollano",
    "iso:country":"ES",
    "sg:address":"Calle de Pradollano, 4",
    "sg:city":"Granada",
    "sg:orig_category":"Venta, Instalaci\u00d3n, Reparaci\u00d3n De Antenas Para Televisi\u00d3n",
    "sg:phone":"+34 958 13 99 46",
    "sg:postcode":"18008",
    "sg:province":"Granada",
    "wof:name":"Ruiz Romero Roberto Javier",
    "wof:placetype":"venue"
},
  "geometry": {"coordinates":[-3.5841300488,37.1630821228],"type":"Point"}
}