{
  "type": "Feature",
  "properties": {
    "iso:country":"ES",
    "sg:address":"Carrer de Muralla Del Carme, 14",
    "sg:city":"Manresa",
    "sg:orig_category":"Art\u00cdculos De Decoraci\u00d3n",
    "sg:phone":"+34 938 72 13 32",
    "sg:postcode":"08241",
    "sg:province":"Barcelona",
    "sg:website":"www.isadecoracio.com",
    "wof:name":"Alvaro Garcia Julio Francisco",
    "wof:placetype":"venue"
},
  "geometry": {"coordinates":[1.8251080513,41.7253570557],"type":"Point"}
}