{
  "type": "Feature",
  "properties": {
    "addr:full":"Calle de Almirante Bonifaz, 6 Burgos Burgos 09003",
    "addr:housenumber":"6",
    "addr:postcode":"09003",
    "addr:street":"Calle De Almirante Bonifaz",
    "iso:country":"ES",
    "sg:address":"Calle de Almirante Bonifaz, 6",
    "sg:city":"Burgos",
    "sg:orig_category":"Mercer\u00cda, Lencer\u00cda (al Por Menor)",
    "sg:phone":"+34 947 20 28 20",
    "sg:postcode":"09003",
    "sg:province":"Burgos",
    "wof:name":"Mu\u00f1oz Izquierdo Pablo",
    "wof:placetype":"venue"
},
  "geometry": {"coordinates":[-3.7009894848,42.3416824341],"type":"Point"}
}