{
  "type": "Feature",
  "properties": {
    "addr:full":"Calle de Claudio Coello, 72 Madrid Madrid 28001",
    "addr:housenumber":"72",
    "addr:postcode":"madrid;28001",
    "addr:street":"Calle De Claudio Coello",
    "iso:country":"ES",
    "sg:address":"Calle de Claudio Coello, 72",
    "sg:city":"Madrid",
    "sg:orig_category":"Ropa Y Art\u00cdculos Pre",
    "sg:phone":"+34 915 77 23 19",
    "sg:postcode":"28001",
    "sg:province":"Madrid",
    "sg:website":"www.mothercare.es",
    "wof:name":"Mothercare Iberica S.a.",
    "wof:placetype":"venue"
},
  "geometry": {"coordinates":[-3.6859617233,40.4293556213],"type":"Point"}
}