{
  "type": "Feature",
  "properties": {
    "iso:country":"ES",
    "sg:address":"Carrer de Sant Francesc D'assis, 16",
    "sg:city":"Mataro",
    "sg:orig_category":"Ense\u00d1anza Variada",
    "sg:phone":"+34 937 96 45 05",
    "sg:postcode":"08301",
    "sg:province":"Barcelona",
    "wof:name":"Varea Aparicio Manuel",
    "wof:placetype":"venue"
},
  "geometry": {"coordinates":[2.4479339123,41.5373954773],"type":"Point"}
}