{
  "type": "Feature",
  "properties": {
    "iso:country":"ES",
    "sg:address":"Calle de Labayru, 36",
    "sg:city":"Bilbao",
    "sg:orig_category":"Molduras, Junquillos, Listones Y Molduras Perforadas",
    "sg:phone":"+34 944 44 08 35",
    "sg:postcode":"48012",
    "sg:province":"Vizcaya",
    "wof:name":"Gonzalez Garcia Julian",
    "wof:placetype":"venue"
},
  "geometry": {"coordinates":[-2.9410820007,43.2568511963],"type":"Point"}
}