{
  "type": "Feature",
  "properties": {
    "addr:full":"Cra Fuente De San Luis, 32 Valencia Valencia 46006",
    "addr:housenumber":"32",
    "addr:postcode":"46006",
    "addr:street":"Fuente;San Luis",
    "iso:country":"ES",
    "sg:address":"Cra Fuente De San Luis, 32",
    "sg:city":"Valencia",
    "sg:orig_category":"Bisuter\u00cda, Joyer\u00cda, Relojer\u00cda (al Por Menor)",
    "sg:phone":"+34 963 73 97 34",
    "sg:postcode":"46006",
    "sg:province":"Valencia",
    "wof:name":"Garcia Garrido Maria Belen",
    "wof:placetype":"venue"
},
  "geometry": {"coordinates":[-0.3717939854,39.4564704895],"type":"Point"}
}