{
  "type": "Feature",
  "properties": {
    "iso:country":"ES",
    "sg:address":"Avda Rafael Cabrera, 19",
    "sg:city":"Palmas De Gran Canaria",
    "sg:orig_category":"Abogados",
    "sg:phone":"+34 928 37 04 36",
    "sg:postcode":"35002",
    "sg:province":"Las Palmas",
    "wof:name":"Rua-figueroa Rodriguez Alberto",
    "wof:placetype":"venue"
},
  "geometry": {"coordinates":[-15.415678978,28.1079807281],"type":"Point"}
}