{
  "type": "Feature",
  "properties": {
    "addr:full":"Carr Rei San\u00c7, 3 Santa Maria Del Cami Islas Baleares 07320",
    "addr:housenumber":"3",
    "addr:postcode":"07320",
    "addr:street":"Carr Rei Sanc\u0327;Islas",
    "iso:country":"ES",
    "sg:address":"Carr Rei San\u00c7, 3",
    "sg:city":"Santa Maria Del Cami",
    "sg:orig_category":"Alcoholes Y Aguardientes (fabricaci\u00d3n, Al Por Mayor)",
    "sg:phone":"+34 971 14 03 50",
    "sg:postcode":"07320",
    "sg:province":"Islas Baleares",
    "wof:name":"Bartolome Ca\u00f1ellas S.l.",
    "wof:placetype":"venue"
},
  "geometry": {"coordinates":[2.7729899883,39.6510467529],"type":"Point"}
}