{
  "type": "Feature",
  "properties": {
    "iso:country":"ES",
    "sg:address":"Av Generalitat, 184",
    "sg:city":"Viladecans",
    "sg:orig_category":"Importaci\u00d3n",
    "sg:phone":"+34 936 58 69 95",
    "sg:postcode":"08840",
    "sg:province":"Barcelona",
    "wof:name":"Caral Advising, S.l.u.",
    "wof:placetype":"venue"
},
  "geometry": {"coordinates":[2.0155899525,41.3110084534],"type":"Point"}
}