{
  "type": "Feature",
  "properties": {
    "addr:full":"Avgd Marina, De La, 55 Playa Valencia 46760",
    "addr:postcode":"46760",
    "addr:street":"Playa Valencia",
    "iso:country":"ES",
    "sg:address":"Avgd Marina, De La, 55",
    "sg:city":"Playa",
    "sg:orig_category":"Supermercados Y Hipermercados",
    "sg:phone":"+34 962 88 45 55",
    "sg:postcode":"46760",
    "sg:province":"Valencia",
    "wof:name":"Talora Bono Consuelo",
    "wof:placetype":"venue"
},
  "geometry": {"coordinates":[-0.2594090104,39.0749702454],"type":"Point"}
}