{
  "type": "Feature",
  "properties": {
    "iso:country":"ES",
    "sg:address":"Rua Caldeireria (da), 4",
    "sg:city":"Santiago De Compostela",
    "sg:orig_category":"Bisuter\u00cda, Joyer\u00cda, Relojer\u00cda (al Por Menor)",
    "sg:phone":"+34 981 57 82 56",
    "sg:postcode":"15702",
    "sg:province":"La Coru\u00f1a",
    "wof:name":"Joyeria Jose Antonio Rodriguez Francisco S.l.",
    "wof:placetype":"venue"
},
  "geometry": {"coordinates":[-8.5424699783,42.8796081543],"type":"Point"}
}