{
  "type": "Feature",
  "properties": {
    "iso:country":"ES",
    "sg:address":"Pase Comandante Fortea, 28",
    "sg:city":"Madrid",
    "sg:orig_category":"Alimentaci\u00d3n General (al Por Menor)",
    "sg:phone":"+34 915 47 30 04",
    "sg:postcode":"28008",
    "sg:province":"Madrid",
    "wof:name":"Sanchez Garci Angel",
    "wof:placetype":"venue"
},
  "geometry": {"coordinates":[-3.7308740616,40.426361084],"type":"Point"}
}