{
  "type": "Feature",
  "properties": {
    "addr:full":"Calle de Capataz Santiago, 3 Montealegre Castillo Albacete 02650",
    "addr:housenumber":"3",
    "addr:postcode":"02650",
    "addr:street":"Calle De Capataz Santiago",
    "iso:country":"ES",
    "sg:address":"Calle de Capataz Santiago, 3",
    "sg:city":"Montealegre Castillo",
    "sg:orig_category":"Empresas De Carpinter\u00cda Met\u00c1lica",
    "sg:phone":"+34 967 33 61 13",
    "sg:postcode":"02650",
    "sg:province":"Albacete",
    "wof:name":"Carpinteria Torralba S.l.",
    "wof:placetype":"venue"
},
  "geometry": {"coordinates":[-1.3281860352,38.7889289856],"type":"Point"}
}