{
  "type": "Feature",
  "properties": {
    "iso:country":"ES",
    "sg:address":"Av Rio De Janeiro, 123",
    "sg:city":"Barcelona",
    "sg:orig_category":"Tapicer\u00cdas",
    "sg:phone":"+34 933 59 75 68",
    "sg:postcode":"08016",
    "sg:province":"Barcelona",
    "wof:name":"Morales Zambrano Antonio",
    "wof:placetype":"venue"
},
  "geometry": {"coordinates":[2.184896946,41.4422454834],"type":"Point"}
}