{
  "type": "Feature",
  "properties": {
    "iso:country":"ES",
    "sg:address":"Calle de Viaducto Marquina, 5",
    "sg:city":"Oviedo",
    "sg:orig_category":"Asesor\u00cda De Formaci\u00d3n Y Gesti\u00d3n De Personal",
    "sg:phone":"+34 985 24 09 33",
    "sg:postcode":"33004",
    "sg:province":"Asturias",
    "wof:name":"Villanueva Areces Victoriano",
    "wof:placetype":"venue"
},
  "geometry": {"coordinates":[-5.8550071716,43.3656730652],"type":"Point"}
}