{
  "type": "Feature",
  "properties": {
    "addr:full":"Ctra. Zurbano, 3 Vitoria-gasteiz \u00c1lava 01013",
    "addr:housenumber":"3",
    "addr:postcode":"01013",
    "addr:street":"Ctra. Zurbano",
    "iso:country":"ES",
    "sg:address":"Ctra. Zurbano, 3",
    "sg:city":"Vitoria-gasteiz",
    "sg:orig_category":"Promotores Constructores",
    "sg:phone":"+34 945 12 32 36",
    "sg:postcode":"01013",
    "sg:province":"\u00c1lava",
    "wof:name":"Gesypro",
    "wof:placetype":"venue"
},
  "geometry": {"coordinates":[-2.6840889454,42.8761367798],"type":"Point"}
}