{
  "type": "Feature",
  "properties": {
    "addr:full":"Calle de La Florida, 10 Vitoria-gasteiz \u00c1lava 01005",
    "addr:housenumber":"10",
    "addr:postcode":"01005",
    "addr:street":"Calle De La Florida",
    "iso:country":"ES",
    "sg:address":"Calle de La Florida, 10",
    "sg:city":"Vitoria-gasteiz",
    "sg:orig_category":"Agencias De Viajes",
    "sg:phone":"+34 945 14 27 84",
    "sg:postcode":"01005",
    "sg:province":"\u00c1lava",
    "sg:website":"www.viajeseroski.com",
    "wof:name":"Viajes Eroski S.a.",
    "wof:placetype":"venue"
},
  "geometry": {"coordinates":[-2.6740059853,42.8432273865],"type":"Point"}
}