{
  "type": "Feature",
  "properties": {
    "addr:full":"Calle de Asuncion, 40 Sevilla Sevilla 41011",
    "addr:housenumber":"40",
    "addr:postcode":"41011",
    "addr:street":"Calle De Asuncion",
    "iso:country":"ES",
    "sg:address":"Calle de Asuncion, 40",
    "sg:city":"Sevilla",
    "sg:orig_category":"Zapatos (al Por Menor)",
    "sg:phone":"+34 954 27 66 78",
    "sg:postcode":"41011",
    "sg:province":"Sevilla",
    "wof:name":"Yorga S. A.",
    "wof:placetype":"venue"
},
  "geometry": {"coordinates":[-5.9976329803,37.3764610291],"type":"Point"}
}