{
  "type": "Feature",
  "properties": {
    "addr:full":"B. Piedad, S/n Palamos Girona 17230",
    "addr:housenumber":"s / n",
    "addr:postcode":"17230",
    "iso:country":"ES",
    "sg:address":"B. Piedad, S/n",
    "sg:city":"Palamos",
    "sg:orig_category":"Goma: Productos De Uso Industrial (fabricaci\u00d3n, Al Por Mayor)",
    "sg:phone":"+34 972 31 20 55",
    "sg:postcode":"17230",
    "sg:province":"Girona",
    "wof:name":"Hutchinson Palamos S.a.",
    "wof:placetype":"venue"
},
  "geometry": {"coordinates":[3.1279499531,41.8473548889],"type":"Point"}
}