{
  "type": "Feature",
  "properties": {
    "addr:full":"A Atalaia, 2 San Cibrao Lugo 27890",
    "addr:housenumber":"2",
    "addr:postcode":"27890",
    "addr:street":"San Cibrao",
    "iso:country":"ES",
    "sg:address":"A Atalaia, 2",
    "sg:city":"San Cibrao",
    "sg:orig_category":"Molduras, Junquillos, Listones Y Molduras Perforadas",
    "sg:phone":"+34 982 59 41 27",
    "sg:postcode":"27890",
    "sg:province":"Lugo",
    "wof:name":"Garcia Vazquez Benedicto",
    "wof:placetype":"venue"
},
  "geometry": {"coordinates":[-7.4429941177,43.6938285828],"type":"Point"}
}