{
  "type": "Feature",
  "properties": {
    "addr:full":"Sect Oficios, 23 Tres Cantos Madrid 28760",
    "addr:housenumber":"23",
    "addr:postcode":"28760",
    "addr:street":"Sect Oficios",
    "iso:country":"ES",
    "sg:address":"Sect Oficios, 23",
    "sg:city":"Tres Cantos",
    "sg:orig_category":"Arquitectos",
    "sg:phone":"+34 918 04 53 24",
    "sg:postcode":"28760",
    "sg:province":"Madrid",
    "wof:name":"Chacon Martinez Miguel",
    "wof:placetype":"venue"
},
  "geometry": {"coordinates":[-3.7144949436,40.6039199829],"type":"Point"}
}