{
  "type": "Feature",
  "properties": {
    "iso:country":"ES",
    "sg:address":"Poligono De Piadela, S/n",
    "sg:city":"Piadela",
    "sg:orig_category":"Bobinado, Reparaci\u00d3n De Material El\u00c9ctrico Profesional",
    "sg:phone":"+34 981 77 32 90",
    "sg:postcode":"15319",
    "sg:province":"La Coru\u00f1a",
    "wof:name":"Megom Betanzos S.l.",
    "wof:placetype":"venue"
},
  "geometry": {"coordinates":[-8.0784473419,43.3035011292],"type":"Point"}
}