{
  "type": "Feature",
  "properties": {
    "iso:country":"ES",
    "sg:address":"Calle de Graciliano Afonso, 9",
    "sg:city":"Palmas De Gran Canaria",
    "sg:orig_category":"M\u00c9dicos: Estomatolog\u00cda",
    "sg:phone":"+34 928 24 19 01",
    "sg:postcode":"35005",
    "sg:province":"Las Palmas",
    "wof:name":"Megias Rosales Jose Juan",
    "wof:placetype":"venue"
},
  "geometry": {"coordinates":[-15.4295167923,28.1267166138],"type":"Point"}
}