{
  "type": "Feature",
  "properties": {
    "iso:country":"ES",
    "sg:address":"Calle de Ancha, 16",
    "sg:city":"Motril",
    "sg:orig_category":"Artes Gr\u00c1ficas, Artes Pl\u00c1sticas (curso)",
    "sg:phone":"+34 958 82 57 79",
    "sg:postcode":"18600",
    "sg:province":"Granada",
    "wof:name":"Grafimar Sdad. Coop. Andaluza",
    "wof:placetype":"venue"
},
  "geometry": {"coordinates":[-3.5161213875,36.7522010803],"type":"Point"}
}