{
  "type": "Feature",
  "properties": {
    "iso:country":"ES",
    "sg:address":"Carrer de Fran\u00c7a, 29",
    "sg:city":"Barcelona",
    "sg:orig_category":"Inform\u00c1tica: Consultores",
    "sg:phone":"+34 932 84 18 79",
    "sg:postcode":"08024",
    "sg:province":"Barcelona",
    "wof:name":"Rigel Consulting S.l.",
    "wof:placetype":"venue"
},
  "geometry": {"coordinates":[2.1631240845,41.4155807495],"type":"Point"}
}