{
  "type": "Feature",
  "properties": {
    "addr:full":"Calle de Velazquez Bosco, 3 Cordoba C\u00f3rdoba 14003",
    "addr:housenumber":"3",
    "addr:postcode":"14003",
    "addr:street":"Calle De Velazquez Bosco;Co\u0301Rdoba",
    "iso:country":"ES",
    "sg:address":"Calle de Velazquez Bosco, 3",
    "sg:city":"Cordoba",
    "sg:orig_category":"Centros P\u00dablicos De Formaci\u00d3n Profesional Y T\u00c9cnica",
    "sg:phone":"+34 957 47 35 87",
    "sg:postcode":"14003",
    "sg:province":"C\u00f3rdoba",
    "wof:name":"Colegio Oficial De A. T. S. Y Diplomado En Enfermeria",
    "wof:placetype":"venue"
},
  "geometry": {"coordinates":[-4.779815197,37.880607605],"type":"Point"}
}