{
  "type": "Feature",
  "properties": {
    "addr:full":"Calle de Jose Maria Roquero, 5 Madrid Madrid 28045",
    "addr:housenumber":"5",
    "addr:postcode":"28045",
    "addr:street":"Calle De Jose Maria Roquero",
    "iso:country":"ES",
    "sg:address":"Calle de Jose Maria Roquero, 5",
    "sg:city":"Madrid",
    "sg:orig_category":"Mudanzas",
    "sg:phone":"+34 914 67 86 95",
    "sg:postcode":"28045",
    "sg:province":"Madrid",
    "wof:name":"Moreno De Juanas Juan",
    "wof:placetype":"venue"
},
  "geometry": {"coordinates":[-3.692923069,40.4012985229],"type":"Point"}
}