{
  "type": "Feature",
  "properties": {
    "iso:country":"ES",
    "sg:address":"Calle de Mayor, 22",
    "sg:city":"Esparragal",
    "sg:orig_category":"Higiene, Belleza: Art\u00cdculos (al Por Menor)",
    "sg:phone":"+34 968 85 01 43",
    "sg:postcode":"30163",
    "sg:province":"Murcia",
    "wof:name":"Sanchez Garcia Enrique",
    "wof:placetype":"venue"
},
  "geometry": {"coordinates":[-1.0809340477,38.038520813],"type":"Point"}
}