{
  "type": "Feature",
  "properties": {
    "addr:full":"Avda Federico G Lorca, 56 Huelma Ja\u00e9n 23560",
    "addr:housenumber":"56",
    "addr:postcode":"23560",
    "addr:street":"Avda Federico G Lorca",
    "iso:country":"ES",
    "sg:address":"Avda Federico G Lorca, 56",
    "sg:city":"Huelma",
    "sg:orig_category":"Farmacias",
    "sg:phone":"+34 953 39 00 87",
    "sg:postcode":"23560",
    "sg:province":"Ja\u00e9n",
    "wof:name":"Cardenas Moreno Ildefonso",
    "wof:placetype":"venue"
},
  "geometry": {"coordinates":[-3.4611830711,37.6509132385],"type":"Point"}
}