{
  "type": "Feature",
  "properties": {
    "addr:full":"Ctra Sadaba, 2 Ejea De Los Caballeros Zaragoza 50600",
    "addr:housenumber":"2",
    "addr:postcode":"50600",
    "addr:street":"Ctra Sadaba",
    "iso:country":"ES",
    "sg:address":"Ctra Sadaba, 2",
    "sg:city":"Ejea De Los Caballeros",
    "sg:orig_category":"Distribuci\u00d3n De Petr\u00d3leo Y Derivados",
    "sg:phone":"+34 976 66 08 91",
    "sg:postcode":"50600",
    "sg:province":"Zaragoza",
    "sg:website":"www.cepsa.es",
    "wof:name":"Cedipsa Compa\u00d1ia Espa\u00d1ola Distribuidora De Petroleos S.a.",
    "wof:placetype":"venue"
},
  "geometry": {"coordinates":[-1.1521539688,42.1332817078],"type":"Point"}
}