{
  "type": "Feature",
  "properties": {
    "addr:full":"Carrer de Mare De Deu Del Socors, 10 Terrassa Barcelona 08222",
    "addr:housenumber":"10",
    "addr:postcode":"08222",
    "addr:street":"Carrer De Mare De Deu Del Socors",
    "iso:country":"ES",
    "sg:address":"Carrer de Mare De Deu Del Socors, 10",
    "sg:city":"Terrassa",
    "sg:orig_category":"Ropa Para Se\u00d1oras Y Caballeros (al Por Menor)",
    "sg:phone":"+34 937 85 91 87",
    "sg:postcode":"08222",
    "sg:province":"Barcelona",
    "wof:name":"Zafra Luque Manuel",
    "wof:placetype":"venue"
},
  "geometry": {"coordinates":[2.0283946991,41.5626220703],"type":"Point"}
}