{
  "type": "Feature",
  "properties": {
    "iso:country":"ES",
    "sg:address":"Avda Alcazar De San Juan, 55",
    "sg:city":"Consuegra",
    "sg:orig_category":"Agricultores, Agricultores",
    "sg:phone":"+34 925 48 17 65",
    "sg:postcode":"45700",
    "sg:province":"Toledo",
    "wof:name":"Distribuciones Maria Rosa De La Cruz S.l.",
    "wof:placetype":"venue"
},
  "geometry": {"coordinates":[-3.5958490372,39.4581794739],"type":"Point"}
}