{
  "type": "Feature",
  "properties": {
    "iso:country":"ES",
    "sg:address":"Carrer de Retama, 89",
    "sg:city":"Viladecans",
    "sg:orig_category":"Cables Y Hilos El\u00c9ctricos (fabricaci\u00d3n, Al Por Mayor)",
    "sg:phone":"+34 936 37 79 64",
    "sg:postcode":"08840",
    "sg:province":"Barcelona",
    "wof:name":"Rosines Cortadellas Ramon",
    "wof:placetype":"venue"
},
  "geometry": {"coordinates":[2.0071771145,41.3201637268],"type":"Point"}
}