{
  "type": "Feature",
  "properties": {
    "iso:country":"ES",
    "sg:address":"Calle de Traviesa, 6",
    "sg:city":"Zamora",
    "sg:orig_category":"Ense\u00d1anza Secundaria: Colegios Y Escuelas Privadas",
    "sg:phone":"+34 980 51 47 77",
    "sg:postcode":"49003",
    "sg:province":"Zamora",
    "wof:name":"Sampedro Fradejas Licinio",
    "wof:placetype":"venue"
},
  "geometry": {"coordinates":[-5.7418642044,41.5047645569],"type":"Point"}
}