{
  "type": "Feature",
  "properties": {
    "addr:full":"Avda Boliches De Los, 2 Fuengirola M\u00e1laga 29640",
    "addr:postcode":"29640",
    "addr:street":"Avda Boliches De Los;Ma\u0301Laga",
    "iso:country":"ES",
    "sg:address":"Avda Boliches De Los, 2",
    "sg:city":"Fuengirola",
    "sg:orig_category":"Servicios De Telecomunicaciones",
    "sg:phone":"+34 952 47 95 24",
    "sg:postcode":"29640",
    "sg:province":"M\u00e1laga",
    "wof:name":"Tampa Fe S.l.",
    "wof:placetype":"venue"
},
  "geometry": {"coordinates":[-4.611907959,36.5568618774],"type":"Point"}
}