{
  "type": "Feature",
  "properties": {
    "iso:country":"ES",
    "sg:address":"Avda Ronda De Los Tejares, 13",
    "sg:city":"Cordoba",
    "sg:orig_category":"M\u00c9dicos: Estomatolog\u00cda",
    "sg:phone":"+34 957 48 12 32",
    "sg:postcode":"14001",
    "sg:province":"C\u00f3rdoba",
    "wof:name":"Ventosa Fragua Natividad",
    "wof:placetype":"venue"
},
  "geometry": {"coordinates":[-4.7807631493,37.8883666992],"type":"Point"}
}