{
  "type": "Feature",
  "properties": {
    "iso:country":"ES",
    "sg:address":"Calle de Real, 39",
    "sg:city":"Utiel",
    "sg:orig_category":"Relojer\u00cda (al Por Menor, Reparaci\u00d3n)",
    "sg:phone":"+34 962 17 05 33",
    "sg:postcode":"46300",
    "sg:province":"Valencia",
    "wof:name":"Aguado Ubeda Jose Vicente",
    "wof:placetype":"venue"
},
  "geometry": {"coordinates":[-1.2044299841,39.5663833618],"type":"Point"}
}