{
  "type": "Feature",
  "properties": {
    "iso:country":"ES",
    "sg:address":"Calle de Moraleja, 1",
    "sg:city":"Alcorcon",
    "sg:orig_category":"Asesor\u00cda Sobre Comunicaci\u00d3n De Empresas",
    "sg:phone":"+34 916 43 83 88",
    "sg:postcode":"28921",
    "sg:province":"Madrid",
    "wof:name":"Aseconta S.l.",
    "wof:placetype":"venue"
},
  "geometry": {"coordinates":[-3.8271021843,40.3464889526],"type":"Point"}
}