{
  "type": "Feature",
  "properties": {
    "iso:country":"ES",
    "sg:address":"Pasada Del Cristo, S/n",
    "sg:city":"Lardero",
    "sg:orig_category":"Conservas De Legumbres (fabricaci\u00d3n, Al Por Mayor)",
    "sg:phone":"+34 941 44 93 50",
    "sg:postcode":"26140",
    "sg:province":"La Rioja",
    "sg:website":"www.conservas-ortema.com",
    "wof:name":"Ortega Mu\u00f1oz Jesus",
    "wof:placetype":"venue"
},
  "geometry": {"coordinates":[-2.4645929337,42.426776886],"type":"Point"}
}