{
  "type": "Feature",
  "properties": {
    "iso:country":"ES",
    "sg:address":"Calle de Bolivia, 6",
    "sg:city":"Madrid",
    "sg:orig_category":"Panader\u00cdas, Panader\u00cdas",
    "sg:phone":"+34 914 58 67 55",
    "sg:postcode":"28016",
    "sg:province":"Madrid",
    "wof:name":"Heras Coloma Julio",
    "wof:placetype":"venue"
},
  "geometry": {"coordinates":[-3.6780519485,40.4562110901],"type":"Point"}
}