{
  "type": "Feature",
  "properties": {
    "iso:country":"ES",
    "sg:address":"Avgd Ricard Hernandez, 75",
    "sg:city":"Alcasser",
    "sg:orig_category":"Molduras, Junquillos, Listones Y Molduras Perforadas",
    "sg:phone":"+34 961 23 31 21",
    "sg:postcode":"46290",
    "sg:province":"Valencia",
    "wof:name":"Lopez Alferez Antonio",
    "wof:placetype":"venue"
},
  "geometry": {"coordinates":[-0.4455200136,39.3768234253],"type":"Point"}
}