{
  "type": "Feature",
  "properties": {
    "addr:full":"Calle de Francisco De Medina Y Mendoza, S/n Cabanillas Campo Guadalajara 19171",
    "addr:housenumber":"s",
    "addr:postcode":"19171",
    "addr:street":"Calle De Francisco De Medina Y Mendoza;/ N",
    "iso:country":"ES",
    "sg:address":"Calle de Francisco De Medina Y Mendoza, S/n",
    "sg:city":"Cabanillas Campo",
    "sg:orig_category":"Muebles Y Accesorios Para Cocinas Y Cuartos De Ba\u00d1o (al Por Menor)",
    "sg:phone":"+34 949 20 01 61",
    "sg:postcode":"19171",
    "sg:province":"Guadalajara",
    "wof:name":"Leticia Dise\u00d1o S.l.",
    "wof:placetype":"venue"
},
  "geometry": {"coordinates":[-3.2051389217,40.6177062988],"type":"Point"}
}