{
  "type": "Feature",
  "properties": {
    "addr:full":"Calle de Goienkale, 18 Plentzia Vizcaya 48620",
    "addr:housenumber":"18",
    "addr:postcode":"48620",
    "addr:street":"Calle De Goienkale",
    "iso:country":"ES",
    "sg:address":"Calle de Goienkale, 18",
    "sg:city":"Plentzia",
    "sg:orig_category":"Ropa Para Se\u00d1oras (al Por Menor)",
    "sg:phone":"+34 946 77 26 36",
    "sg:postcode":"48620",
    "sg:province":"Vizcaya",
    "wof:name":"Ellakuria Delgado Regina",
    "wof:placetype":"venue"
},
  "geometry": {"coordinates":[-2.9485099316,43.4047813416],"type":"Point"}
}