{
  "type": "Feature",
  "properties": {
    "iso:country":"ES",
    "sg:address":"Calle de Tavira, 3",
    "sg:city":"Salamanca",
    "sg:orig_category":"M\u00c9dicos: Pediatr\u00cda. Enfermedades De Los Ni\u00d1os",
    "sg:phone":"+34 923 21 47 80",
    "sg:postcode":"37008",
    "sg:province":"Salamanca",
    "wof:name":"Lopez-berges Nu\u00f1o Carlos",
    "wof:placetype":"venue"
},
  "geometry": {"coordinates":[-5.6673550606,40.9604568481],"type":"Point"}
}