{
  "type": "Feature",
  "properties": {
    "addr:full":"Calle de Estio (del), 8 Arganda Madrid 28500",
    "addr:housenumber":"8",
    "addr:postcode":"28500",
    "addr:street":"Calle De Estio Del",
    "iso:country":"ES",
    "sg:address":"Calle de Estio (del), 8",
    "sg:city":"Arganda",
    "sg:orig_category":"Muebles Y Accesorios Para Cocinas Y Cuartos De Ba\u00d1o (al Por Menor)",
    "sg:phone":"+34 918 71 91 89",
    "sg:postcode":"28500",
    "sg:province":"Madrid",
    "wof:name":"Muebles De Cocina Hico S.l.",
    "wof:placetype":"venue"
},
  "geometry": {"coordinates":[-3.4406979084,40.2999954224],"type":"Point"}
}