{
  "type": "Feature",
  "properties": {
    "addr:full":"Plaz Mondariz, 15 Madrid Madrid 28029",
    "addr:housenumber":"15",
    "addr:postcode":"madrid;28029",
    "addr:street":"Mondariz",
    "iso:country":"ES",
    "sg:address":"Plaz Mondariz, 15",
    "sg:city":"Madrid",
    "sg:orig_category":"Asociaciones Y Clubs Deportivos",
    "sg:phone":"+34 917 30 52 89",
    "sg:postcode":"28029",
    "sg:province":"Madrid",
    "wof:name":"Vega Dominguez Francisco",
    "wof:placetype":"venue"
},
  "geometry": {"coordinates":[-3.7052989006,40.4783592224],"type":"Point"}
}