{
  "type": "Feature",
  "properties": {
    "addr:full":"Calle de Luis Menendez Pidal, 42 Pola De Lena Asturias 33630",
    "addr:housenumber":"42",
    "addr:postcode":"33630",
    "addr:street":"Calle De Luis Menendez Pidal",
    "iso:country":"ES",
    "sg:address":"Calle de Luis Menendez Pidal, 42",
    "sg:city":"Pola De Lena",
    "sg:classifiers":[
        {
            "category":"Taxi",
            "type":"Transportation"
        }
    ],
    "sg:phone":"+34 985 49 30 41",
    "sg:postcode":"33630",
    "sg:province":"Asturias",
    "wof:name":"Mateo Rubin Jose Luis",
    "wof:placetype":"venue"
},
  "geometry": {"coordinates":[-5.8273568153,43.1562271118],"type":"Point"}
}