{
  "type": "Feature",
  "properties": {
    "iso:country":"ES",
    "sg:address":"Carrer de Portalada, 7",
    "sg:city":"Altafulla",
    "sg:orig_category":"Centros De Educaci\u00d3n Especial",
    "sg:phone":"+34 977 65 03 23",
    "sg:postcode":"43893",
    "sg:province":"Tarragona",
    "wof:name":"Ajuntament De Altafulla",
    "wof:placetype":"venue"
},
  "geometry": {"coordinates":[1.3719129562,41.1418647766],"type":"Point"}
}