{
  "type": "Feature",
  "properties": {
    "iso:country":"ES",
    "sg:address":"Avda Andalucia, 73",
    "sg:city":"Cadiz",
    "sg:orig_category":"Distribuci\u00d3n De Petr\u00d3leo Y Derivados",
    "sg:phone":"+34 956 27 05 05",
    "sg:postcode":"11007",
    "sg:province":"C\u00e1diz",
    "wof:name":"Santiago Perez Luis",
    "wof:placetype":"venue"
},
  "geometry": {"coordinates":[-6.2822737694,36.5158119202],"type":"Point"}
}