{
  "type": "Feature",
  "properties": {
    "iso:country":"ES",
    "sg:address":"Carrer de Lepant, 293",
    "sg:city":"Barcelona",
    "sg:orig_category":"Molduras, Junquillos, Listones Y Molduras Perforadas",
    "sg:phone":"+34 934 55 71 10",
    "sg:postcode":"08025",
    "sg:province":"Barcelona",
    "wof:name":"Sanchez Rodriguez Juan Manuel",
    "wof:placetype":"venue"
},
  "geometry": {"coordinates":[2.1749019623,41.4056167603],"type":"Point"}
}