{
  "type": "Feature",
  "properties": {
    "iso:country":"ES",
    "sg:address":"Calle de Sanchez Vera, 3",
    "sg:city":"Cuenca",
    "sg:orig_category":"Impuestos, Tesoro P\u00dablico",
    "sg:phone":"+34 969 23 03 21",
    "sg:postcode":"16002",
    "sg:province":"Cuenca",
    "wof:name":"Club Todo Terreno Montes De Cuenca",
    "wof:placetype":"venue"
},
  "geometry": {"coordinates":[-2.1370670795,40.0729866028],"type":"Point"}
}