{
  "type": "Feature",
  "properties": {
    "iso:country":"ES",
    "sg:address":"Carrer de Montflorit, 64",
    "sg:city":"Gava",
    "sg:orig_category":"Molduras, Junquillos, Listones Y Molduras Perforadas",
    "sg:phone":"+34 936 38 27 96",
    "sg:postcode":"08850",
    "sg:province":"Barcelona",
    "wof:name":"Angas S.c.p",
    "wof:placetype":"venue"
},
  "geometry": {"coordinates":[2.0009098053,41.3020515442],"type":"Point"}
}