{
  "type": "Feature",
  "properties": {
    "iso:country":"ES",
    "sg:address":"Calle de Pedro Rico, 27",
    "sg:city":"Madrid",
    "sg:orig_category":"Edici\u00d3n De Diarios, Revistas, Boletines",
    "sg:phone":"+34 917 33 88 11",
    "sg:postcode":"28029",
    "sg:province":"Madrid",
    "wof:name":"Alpe Editores Sociedad Anonima",
    "wof:placetype":"venue"
},
  "geometry": {"coordinates":[-3.6956279278,40.4840583801],"type":"Point"}
}