{
  "type": "Feature",
  "properties": {
    "addr:full":"Pla\u00c7 De Sant Domingo, 1 Ontinyent Valencia 46870",
    "addr:housenumber":"1",
    "addr:postcode":"46870",
    "addr:street":"Domingo",
    "iso:country":"ES",
    "sg:address":"Pla\u00c7 De Sant Domingo, 1",
    "sg:city":"Ontinyent",
    "sg:orig_category":"Alimentaci\u00d3n General (al Por Menor)",
    "sg:phone":"+34 962 38 04 87",
    "sg:postcode":"46870",
    "sg:province":"Valencia",
    "wof:name":"Gramage Terol Gonzalo",
    "wof:placetype":"venue"
},
  "geometry": {"coordinates":[-0.6072440147,38.8219413757],"type":"Point"}
}