{
  "type": "Feature",
  "properties": {
    "addr:full":"C/ Princep, 23 Manacor Islas Baleares 07500",
    "addr:housenumber":"23",
    "addr:postcode":"07500",
    "addr:street":"C / Princep",
    "iso:country":"ES",
    "sg:address":"C/ Princep, 23",
    "sg:city":"Manacor",
    "sg:orig_category":"Inversiones",
    "sg:phone":"+34 971 55 97 87",
    "sg:postcode":"07500",
    "sg:province":"Islas Baleares",
    "wof:name":"Associacio 3 Edad Verge De Lluc",
    "wof:placetype":"venue"
},
  "geometry": {"coordinates":[3.210334301,39.5666809082],"type":"Point"}
}