{
  "type": "Feature",
  "properties": {
    "addr:full":"Calle de Benedicto Xiii, 6 Alagon Zaragoza 50630",
    "addr:housenumber":"6",
    "addr:postcode":"50630",
    "addr:street":"Calle De Benedicto Xiii",
    "iso:country":"ES",
    "sg:address":"Calle de Benedicto Xiii, 6",
    "sg:city":"Alagon",
    "sg:orig_category":"Ingeniero",
    "sg:phone":"+34 976 61 19 80",
    "sg:postcode":"50630",
    "sg:province":"Zaragoza",
    "wof:name":"Garcia Gracia Francisco",
    "wof:placetype":"venue"
},
  "geometry": {"coordinates":[-1.1149177551,41.766910553],"type":"Point"}
}