{
  "type": "Feature",
  "properties": {
    "iso:country":"ES",
    "sg:address":"Calle de Flores (las), 12",
    "sg:city":"Linea De La Concepcion",
    "sg:orig_category":"Frutas, Legumbres Frescas Y Tempranas (al Por Menor)",
    "sg:phone":"+34 956 76 59 65",
    "sg:postcode":"11300",
    "sg:province":"C\u00e1diz",
    "wof:name":"Eurotel Sur S.l.",
    "wof:placetype":"venue"
},
  "geometry": {"coordinates":[-5.3500285149,36.1630439758],"type":"Point"}
}