{
  "type": "Feature",
  "properties": {
    "iso:country":"ES",
    "sg:address":"Avda Cardenal Herrera Oria, 247",
    "sg:city":"Madrid",
    "sg:orig_category":"Pintura Y Barniz (al Por Menor)",
    "sg:phone":"+34 917 39 89 96",
    "sg:postcode":"28035",
    "sg:province":"Madrid",
    "sg:website":"www.imcasa.com",
    "wof:name":"Imcasa S.l.",
    "wof:placetype":"venue"
},
  "geometry": {"coordinates":[-3.7165238857,40.4824790955],"type":"Point"}
}