{
  "type": "Feature",
  "properties": {
    "addr:full":"Carrer de Barcelona, 25 Prat Llobregat Barcelona 08820",
    "addr:housenumber":"25",
    "addr:postcode":"08820",
    "addr:street":"Carrer De Barcelona;Llobregat",
    "iso:country":"ES",
    "sg:address":"Carrer de Barcelona, 25",
    "sg:city":"Prat Llobregat",
    "sg:orig_category":"Art\u00cdculos De Decoraci\u00d3n",
    "sg:phone":"+34 933 79 22 91",
    "sg:postcode":"08820",
    "sg:province":"Barcelona",
    "wof:name":"Materiales De Construccion Y Decoracion Alonso S.l",
    "wof:placetype":"venue"
},
  "geometry": {"coordinates":[2.0943670273,41.3239936829],"type":"Point"}
}