{
  "type": "Feature",
  "properties": {
    "addr:full":"Carr Garrigas, 9 Figueres Girona 17600",
    "addr:housenumber":"9",
    "addr:postcode":"17600",
    "addr:street":"Carr Garrigas",
    "iso:country":"ES",
    "sg:address":"Carr Garrigas, 9",
    "sg:city":"Figueres",
    "sg:orig_category":"Cortadoras, Tronzadoras, Cosechadoras (al Por Menor)",
    "sg:phone":"+34 972 67 23 18",
    "sg:postcode":"17600",
    "sg:province":"Girona",
    "wof:name":"Oxiter Girona S.l.",
    "wof:placetype":"venue"
},
  "geometry": {"coordinates":[2.9581100941,42.2656898499],"type":"Point"}
}