{
  "type": "Feature",
  "properties": {
    "iso:country":"ES",
    "sg:address":"Ctra. H-ayamonte, S/n",
    "sg:city":"Cartaya",
    "sg:orig_category":"\u00c1rboles Frutales",
    "sg:phone":"+34 959 39 38 20",
    "sg:postcode":"21450",
    "sg:province":"Huelva",
    "wof:name":"Viveros Sevilla S. A.",
    "wof:placetype":"venue"
},
  "geometry": {"coordinates":[-7.1453080177,37.2888221741],"type":"Point"}
}