{
  "type": "Feature",
  "properties": {
    "iso:country":"ES",
    "sg:address":"Castelo(nandin), 28",
    "sg:city":"A Ramallosa",
    "sg:orig_category":"Promotores Constructores",
    "sg:phone":"+34 986 36 91 08",
    "sg:postcode":"36379",
    "sg:province":"Pontevedra",
    "wof:name":"Construcciones Valverde Mendez S.l",
    "wof:placetype":"venue"
},
  "geometry": {"coordinates":[-8.8134374619,42.1331443787],"type":"Point"}
}