{
  "type": "Feature",
  "properties": {
    "addr:full":"Plaza Patxi Bengoa, 2 Etxebarri Vizcaya 48450",
    "addr:housenumber":"2",
    "addr:postcode":"48450",
    "addr:street":"Patxi Bengoa",
    "iso:country":"ES",
    "sg:address":"Plaza Patxi Bengoa, 2",
    "sg:city":"Etxebarri",
    "sg:orig_category":"Peluquer\u00cdas, Peluquer\u00cda Mixta",
    "sg:phone":"+34 944 26 04 07",
    "sg:postcode":"48450",
    "sg:province":"Vizcaya",
    "wof:name":"Itziar Iragorri Arranz",
    "wof:placetype":"venue"
},
  "geometry": {"coordinates":[-2.8931515217,43.246799469],"type":"Point"}
}