{
  "type": "Feature",
  "properties": {
    "addr:full":"Avda Mediterraneo, Km. 0014,0 Madrid Madrid 28031",
    "addr:postcode":"28031",
    "addr:street":"Avda Mediterraneo Km. 0014,0",
    "iso:country":"ES",
    "sg:address":"Avda Mediterraneo, Km. 0014,0",
    "sg:city":"Madrid",
    "sg:orig_category":"Delegados, Agentes De Tr\u00c1nsito, Auxiliares De Transporte Internacional",
    "sg:phone":"+34 913 31 39 53",
    "sg:postcode":"28031",
    "sg:province":"Madrid",
    "wof:name":"Rodriguez Martin Ambrosio",
    "wof:placetype":"venue"
},
  "geometry": {"coordinates":[-3.6271688938,40.3911514282],"type":"Point"}
}