{
  "type": "Feature",
  "properties": {
    "addr:full":"Kale Nagusia, 20 Hernani Guip\u00f9zcoa 20120",
    "addr:housenumber":"20",
    "addr:postcode":"20120",
    "addr:street":"Kale Nagusia;Guipu\u0300Zcoa",
    "iso:country":"ES",
    "sg:address":"Kale Nagusia, 20",
    "sg:city":"Hernani",
    "sg:orig_category":"Pescader\u00cdas (al Por Menor)",
    "sg:phone":"+34 943 55 51 56",
    "sg:postcode":"20120",
    "sg:province":"Guip\u00f9zcoa",
    "wof:name":"Barral Fernandez Juan Jose",
    "wof:placetype":"venue"
},
  "geometry": {"coordinates":[-1.9798289537,43.2647514343],"type":"Point"}
}