{
  "type": "Feature",
  "properties": {
    "iso:country":"ES",
    "sg:address":"Ctra Arta, 8",
    "sg:city":"Port D'alcudia",
    "sg:orig_category":"Confecci\u00d3n (fabricaci\u00d3n, Al Por Mayor)",
    "sg:phone":"+34 971 54 64 06",
    "sg:postcode":"07410",
    "sg:province":"Islas Baleares",
    "wof:name":"Mir Munar Rafael",
    "wof:placetype":"venue"
},
  "geometry": {"coordinates":[3.120937109,39.8396034241],"type":"Point"}
}