{
  "type": "Feature",
  "properties": {
    "addr:full":"C/ Antonio Machado, 94 Elche Alicante 03201",
    "addr:housenumber":"94",
    "addr:postcode":"03201",
    "addr:street":"C / Antonio Machado",
    "iso:country":"ES",
    "sg:address":"C/ Antonio Machado, 94",
    "sg:city":"Elche",
    "sg:orig_category":"Electricidad: Instaladores",
    "sg:phone":"+34 965 46 48 51",
    "sg:postcode":"03201",
    "sg:province":"Alicante",
    "wof:name":"Jodar Jimenez Maria Jose",
    "wof:placetype":"venue"
},
  "geometry": {"coordinates":[-0.7151790261,38.2611312866],"type":"Point"}
}