{
  "type": "Feature",
  "properties": {
    "addr:full":"Calle de Gibraltar, 2 Estepona M\u00e1laga 29680",
    "addr:housenumber":"2",
    "addr:postcode":"29680",
    "addr:street":"Calle De Gibraltar",
    "iso:country":"ES",
    "sg:address":"Calle de Gibraltar, 2",
    "sg:city":"Estepona",
    "sg:orig_category":"Cl\u00cdnicas Dentales",
    "sg:phone":"+34 952 79 47 39",
    "sg:postcode":"29680",
    "sg:province":"M\u00e1laga",
    "wof:name":"Alpima Cabi S.l.",
    "wof:placetype":"venue"
},
  "geometry": {"coordinates":[-5.1457624435,36.4291229248],"type":"Point"}
}