{
  "type": "Feature",
  "properties": {
    "addr:full":"Pase Estacion, 19 Veguellina Orbigo Le\u00f3n 24350",
    "addr:housenumber":"19",
    "addr:postcode":"24350",
    "addr:street":"Estacion;Leo\u0301N",
    "iso:country":"ES",
    "sg:address":"Pase Estacion, 19",
    "sg:city":"Veguellina Orbigo",
    "sg:orig_category":"Alimentaci\u00d3n General (al Por Menor)",
    "sg:phone":"+34 987 37 64 15",
    "sg:postcode":"24350",
    "sg:province":"Le\u00f3n",
    "wof:name":"Promotora Dominguez Castrillo S.l.",
    "wof:placetype":"venue"
},
  "geometry": {"coordinates":[-5.8852372169,42.4383964539],"type":"Point"}
}