{
  "type": "Feature",
  "properties": {
    "iso:country":"ES",
    "sg:address":"Calle de Pedro Cabanes, 81",
    "sg:city":"Valencia",
    "sg:orig_category":"Laboratorios Y Trabajos De Fotograf\u00cda, V\u00cddeo Y Cine",
    "sg:phone":"+34 963 66 83 32",
    "sg:postcode":"46019",
    "sg:province":"Valencia",
    "wof:name":"Foto Star S.l.",
    "wof:placetype":"venue"
},
  "geometry": {"coordinates":[-0.37876001,39.4940452576],"type":"Point"}
}