{
  "type": "Feature",
  "properties": {
    "addr:full":"Calle de Virgen, 16 Linares Ja\u00e9n 23700",
    "addr:housenumber":"16",
    "addr:postcode":"23700",
    "addr:street":"Calle De Virgen;Jae\u0301N",
    "iso:country":"ES",
    "sg:address":"Calle de Virgen, 16",
    "sg:city":"Linares",
    "sg:orig_category":"Molduras, Junquillos, Listones Y Molduras Perforadas",
    "sg:phone":"+34 953 69 10 07",
    "sg:postcode":"23700",
    "sg:province":"Ja\u00e9n",
    "wof:name":"Ruiz Gonzalez Antonio",
    "wof:placetype":"venue"
},
  "geometry": {"coordinates":[-3.6354739666,38.0963287354],"type":"Point"}
}