{
  "type": "Feature",
  "properties": {
    "iso:country":"ES",
    "sg:address":"De La Constitucion, S/n",
    "sg:city":"Palomares",
    "sg:orig_category":"Cooperativas Agr\u00cdcolas",
    "sg:phone":"+34 950 46 75 67",
    "sg:postcode":"04618",
    "sg:province":"Almer\u00eda",
    "wof:name":"Asociacion Agraria De Jovenes Agricultores De Almeria",
    "wof:placetype":"venue"
},
  "geometry": {"coordinates":[-1.7983723879,37.2491760254],"type":"Point"}
}