{
  "type": "Feature",
  "properties": {
    "iso:country":"ES",
    "sg:address":"Carretera De Holguera, 22",
    "sg:city":"Torrejoncillo",
    "sg:orig_category":"Promotores Constructores",
    "sg:phone":"+34 927 30 43 61",
    "sg:postcode":"10830",
    "sg:province":"C\u00e1ceres",
    "wof:name":"Arcajo Construcciones Obras Publicas Sl",
    "wof:placetype":"venue"
},
  "geometry": {"coordinates":[-6.433962822,39.9056892395],"type":"Point"}
}