{
  "type": "Feature",
  "properties": {
    "addr:full":"Calle de Larga, 53 Jerez De La Frontera C\u00e1diz 11403",
    "addr:housenumber":"53",
    "addr:postcode":"11403",
    "addr:street":"Calle De Larga",
    "iso:country":"ES",
    "sg:address":"Calle de Larga, 53",
    "sg:city":"Jerez De La Frontera",
    "sg:orig_category":"Fotograf\u00cda Y Cine: Aparatos, Pel\u00cdculas Y Accesorios (fabricaci\u00d3n, Al Por Mayor)",
    "sg:phone":"+34 956 34 25 84",
    "sg:postcode":"11403",
    "sg:province":"C\u00e1diz",
    "wof:name":"Fotosherry S.l.",
    "wof:placetype":"venue"
},
  "geometry": {"coordinates":[-6.1364159584,36.6847686768],"type":"Point"}
}