{
  "type": "Feature",
  "properties": {
    "addr:full":"Plaz San Fermin, 1 Malaga M\u00e1laga 29003",
    "addr:housenumber":"1",
    "addr:postcode":"29003",
    "addr:street":"Plaz San Fermin;Ma\u0301Laga",
    "iso:country":"ES",
    "sg:address":"Plaz San Fermin, 1",
    "sg:city":"Malaga",
    "sg:orig_category":"Bricolaje, Herramientas (al Por Menor)",
    "sg:phone":"+34 952 34 99 47",
    "sg:postcode":"29003",
    "sg:province":"M\u00e1laga",
    "wof:name":"Maderas Garcia-mi\u00d1a S.l.",
    "wof:placetype":"venue"
},
  "geometry": {"coordinates":[-4.4477968216,36.7004547119],"type":"Point"}
}