{
  "type": "Feature",
  "properties": {
    "iso:country":"ES",
    "sg:address":"Calle de Lasierra Purroy, 1",
    "sg:city":"Zaragoza",
    "sg:orig_category":"Producci\u00d3n, Distribuci\u00d3n De Electricidad",
    "sg:phone":"+34 976 37 79 25",
    "sg:postcode":"50007",
    "sg:province":"Zaragoza",
    "wof:name":"Iglesia Riveres Marai Pilar",
    "wof:placetype":"venue"
},
  "geometry": {"coordinates":[-0.8845610023,41.6321907043],"type":"Point"}
}