{
  "type": "Feature",
  "properties": {
    "iso:country":"ES",
    "sg:address":"Calle de Eibar, 11",
    "sg:city":"Logro\u00f1o",
    "sg:orig_category":"Ense\u00d1anza: Idiomas",
    "sg:phone":"+34 941 51 14 24",
    "sg:postcode":"26006",
    "sg:province":"La Rioja",
    "wof:name":"Bosse  Anita Sylvie",
    "wof:placetype":"venue"
},
  "geometry": {"coordinates":[-2.4036989212,42.46043396],"type":"Point"}
}