{
  "type": "Feature",
  "properties": {
    "iso:country":"ES",
    "sg:address":"Ctra. Nacional T. Cuarenta, Km. 0175,0",
    "sg:city":"Marbella",
    "sg:orig_category":"Art\u00cdculos De Decoraci\u00d3n",
    "sg:phone":"+34 952 90 81 13",
    "sg:postcode":"29600",
    "sg:province":"M\u00e1laga",
    "wof:name":"Reformy Tsredicemnoe S.l.",
    "wof:placetype":"venue"
},
  "geometry": {"coordinates":[-4.8833007812,36.5079956055],"type":"Point"}
}