{
  "type": "Feature",
  "properties": {
    "iso:country":"ES",
    "sg:address":"Calle de Poeta Salvador Rueda, 87",
    "sg:city":"Fuengirola",
    "sg:orig_category":"Abogados",
    "sg:phone":"+34 952 58 63 91",
    "sg:postcode":"29640",
    "sg:province":"M\u00e1laga",
    "wof:name":"Navarrete Azon Susana",
    "wof:placetype":"venue"
},
  "geometry": {"coordinates":[-4.6132287979,36.5538787842],"type":"Point"}
}