{
  "type": "Feature",
  "properties": {
    "iso:country":"ES",
    "sg:address":"Calle de Belchite, 19",
    "sg:city":"Muel",
    "sg:orig_category":"Ingeniero",
    "sg:phone":"+34 976 14 05 31",
    "sg:postcode":"50450",
    "sg:province":"Zaragoza",
    "wof:name":"Tecnica Y Proyectos S.a.",
    "wof:placetype":"venue"
},
  "geometry": {"coordinates":[-1.0865695477,41.4647827148],"type":"Point"}
}