{
  "type": "Feature",
  "properties": {
    "addr:full":"Muelle Comercial (p I Guadalete), S/n Pto Sta Maria C\u00e1diz 11500",
    "addr:housenumber":"s / n",
    "addr:postcode":"11500",
    "addr:street":"Guadalete;Pto Sta;Ca\u0301Diz",
    "iso:country":"ES",
    "sg:address":"Muelle Comercial (p I Guadalete), S/n",
    "sg:city":"Pto Sta Maria",
    "sg:orig_category":"Almacenes Frigor\u00cdficos",
    "sg:phone":"+34 956 56 03 09",
    "sg:postcode":"11500",
    "sg:province":"C\u00e1diz",
    "wof:name":"Insurpol S.l.",
    "wof:placetype":"venue"
},
  "geometry": {"coordinates":[-6.222949028,36.5945358276],"type":"Point"}
}