{
  "type": "Feature",
  "properties": {
    "iso:country":"ES",
    "sg:address":"Calle de Don Juan Talero, 6",
    "sg:city":"Cabezas Rubias",
    "sg:orig_category":"Estancos",
    "sg:phone":"+34 959 57 10 03",
    "sg:postcode":"21580",
    "sg:province":"Huelva",
    "wof:name":"Ponce Haldon Josefa",
    "wof:placetype":"venue"
},
  "geometry": {"coordinates":[-7.087667942,37.7264862061],"type":"Point"}
}