{
  "type": "Feature",
  "properties": {
    "iso:country":"ES",
    "sg:address":"Rbla Rambla, 32",
    "sg:city":"Figueres",
    "sg:orig_category":"Quincaller\u00cda (al Por Menor)",
    "sg:phone":"+34 972 50 45 29",
    "sg:postcode":"17600",
    "sg:province":"Girona",
    "wof:name":"Ymbert Dunjo S.a.",
    "wof:placetype":"venue"
},
  "geometry": {"coordinates":[2.9616653919,42.2662811279],"type":"Point"}
}