{
  "type": "Feature",
  "properties": {
    "addr:full":"Barr Concepcion (la), 39 San Mateo Cantabria 39408",
    "addr:postcode":"39408",
    "iso:country":"ES",
    "sg:address":"Barr Concepcion (la), 39",
    "sg:city":"San Mateo",
    "sg:orig_category":"Molduras, Junquillos, Listones Y Molduras Perforadas",
    "sg:phone":"+34 942 83 09 89",
    "sg:postcode":"39408",
    "sg:province":"Cantabria",
    "wof:name":"Sociedad Regional De Informatica S.a.",
    "wof:placetype":"venue"
},
  "geometry": {"coordinates":[-4.0770049095,43.279712677],"type":"Point"}
}