{
  "type": "Feature",
  "properties": {
    "addr:full":"Avda Polideportivo, S/n Santa Marina Del Rey Le\u00f3n 24393",
    "addr:housenumber":"s / n",
    "addr:postcode":"24393",
    "addr:street":"Avda Polideportivo;Leo\u0301N",
    "iso:country":"ES",
    "sg:address":"Avda Polideportivo, S/n",
    "sg:city":"Santa Marina Del Rey",
    "sg:orig_category":"Asesor\u00cda Para La Organizaci\u00d3n Y Gesti\u00d3n Del Transporte",
    "sg:phone":"+34 987 37 75 06",
    "sg:postcode":"24393",
    "sg:province":"Le\u00f3n",
    "wof:name":"Otraes S.l.",
    "wof:placetype":"venue"
},
  "geometry": {"coordinates":[-5.8702487946,42.5114021301],"type":"Point"}
}