{
  "type": "Feature",
  "properties": {
    "iso:country":"ES",
    "sg:address":"Calle de Manuela Espinosa, S/n",
    "sg:city":"Caravaca Cruz",
    "sg:orig_category":"Confecci\u00d3n De Zapatos",
    "sg:phone":"+34 968 70 24 45",
    "sg:postcode":"30400",
    "sg:province":"Murcia",
    "wof:name":"Creaciones Torres Comodos S.l.",
    "wof:placetype":"venue"
},
  "geometry": {"coordinates":[-1.8561489582,38.1074943542],"type":"Point"}
}