{
  "type": "Feature",
  "properties": {
    "addr:full":"Avda Fuente (de La), 21 Peligros Granada 18210",
    "addr:housenumber":"21",
    "addr:postcode":"18210",
    "addr:street":"Avda Fuente De La",
    "iso:country":"ES",
    "sg:address":"Avda Fuente (de La), 21",
    "sg:city":"Peligros",
    "sg:orig_category":"Venta, Instalaci\u00d3n De Calefacci\u00d3n",
    "sg:phone":"+34 958 40 56 58",
    "sg:postcode":"18210",
    "sg:province":"Granada",
    "wof:name":"Instalaciones Tecnicas Bayma,sl",
    "wof:placetype":"venue"
},
  "geometry": {"coordinates":[-3.6301970482,37.2327156067],"type":"Point"}
}