{
  "type": "Feature",
  "properties": {
    "iso:country":"ES",
    "sg:address":"Avda Rosalia De Castro (de), 102",
    "sg:city":"Santiago De Compostela",
    "sg:orig_category":"Quincaller\u00cda (al Por Menor)",
    "sg:phone":"+34 981 59 21 79",
    "sg:postcode":"15706",
    "sg:province":"La Coru\u00f1a",
    "wof:name":"Garabal Pais Jose Ramon",
    "wof:placetype":"venue"
},
  "geometry": {"coordinates":[-8.5530891418,42.8733978271],"type":"Point"}
}