{
  "type": "Feature",
  "properties": {
    "iso:country":"ES",
    "sg:address":"Calle de Consistorio, 13",
    "sg:city":"Jerez De La Frontera",
    "sg:orig_category":"Asociaciones, Organismos Culturales Y Socioeducativos",
    "sg:phone":"+34 956 34 80 03",
    "sg:postcode":"11403",
    "sg:province":"C\u00e1diz",
    "wof:name":"Real Academia De San Dionisio De Ciencias Artes Y Letras",
    "wof:placetype":"venue"
},
  "geometry": {"coordinates":[-6.1380028725,36.6825370789],"type":"Point"}
}