{
  "type": "Feature",
  "properties": {
    "addr:full":"Ctra Almaden A Posadas (de), S/n Villaviciosa Cordoba C\u00f3rdoba 14300",
    "addr:housenumber":"s",
    "addr:postcode":"14300",
    "addr:street":"Ctra Almaden A;/ N",
    "iso:country":"ES",
    "sg:address":"Ctra Almaden A Posadas (de), S/n",
    "sg:city":"Villaviciosa Cordoba",
    "sg:orig_category":"Distribuci\u00d3n De Petr\u00d3leo Y Derivados",
    "sg:phone":"+34 957 36 10 20",
    "sg:postcode":"14300",
    "sg:province":"C\u00f3rdoba",
    "wof:name":"Estacion De Servicio Arribas De La Torre S.l.",
    "wof:placetype":"venue"
},
  "geometry": {"coordinates":[-5.0143089294,38.0761260986],"type":"Point"}
}