{
  "type": "Feature",
  "properties": {
    "addr:full":"Calle de Bekoetxe, 2 Zaldibar Vizcaya 48250",
    "addr:housenumber":"2",
    "addr:postcode":"48250",
    "addr:street":"Calle De Bekoetxe",
    "iso:country":"ES",
    "sg:address":"Calle de Bekoetxe, 2",
    "sg:city":"Zaldibar",
    "sg:orig_category":"Estancos",
    "sg:phone":"+34 946 82 72 60",
    "sg:postcode":"48250",
    "sg:province":"Vizcaya",
    "wof:name":"Gonzalo Simon Angel",
    "wof:placetype":"venue"
},
  "geometry": {"coordinates":[-2.5461800098,43.1702919006],"type":"Point"}
}