{
  "type": "Feature",
  "properties": {
    "addr:full":"Calle de Lope De Vega, 8 Elda Alicante 03600",
    "addr:housenumber":"8",
    "addr:postcode":"03600",
    "addr:street":"Calle De Lope De Vega",
    "iso:country":"ES",
    "sg:address":"Calle de Lope De Vega, 8",
    "sg:city":"Elda",
    "sg:orig_category":"Textil",
    "sg:phone":"+34 965 39 83 90",
    "sg:postcode":"03600",
    "sg:province":"Alicante",
    "wof:name":"Sunso Y Loles C.b.",
    "wof:placetype":"venue"
},
  "geometry": {"coordinates":[-0.7950804234,38.4766845703],"type":"Point"}
}