{
  "type": "Feature",
  "properties": {
    "iso:country":"ES",
    "sg:address":"Avda Benito Perez Armas, 31",
    "sg:city":"Santa Cruz De Tenerife",
    "sg:orig_category":"Mec\u00c1nico Del Autom\u00d3vil",
    "sg:phone":"+34 922 21 90 66",
    "sg:postcode":"38007",
    "sg:province":"Santa Cruz De Tenerife",
    "wof:name":"Tur Torres Miguel",
    "wof:placetype":"venue"
},
  "geometry": {"coordinates":[-16.2680549622,28.4628925323],"type":"Point"}
}