{
  "type": "Feature",
  "properties": {
    "addr:full":"Calle de Progreso, 19 Puerto Valencia 46520",
    "addr:housenumber":"19",
    "addr:postcode":"46520",
    "addr:street":"Calle De Progreso",
    "iso:country":"ES",
    "sg:address":"Calle de Progreso, 19",
    "sg:city":"Puerto",
    "sg:orig_category":"Carnicer\u00cdas, Carnicer\u00cdas",
    "sg:phone":"+34 962 67 09 25",
    "sg:postcode":"46520",
    "sg:province":"Valencia",
    "wof:name":"Julian Navarrete Pascual",
    "wof:placetype":"venue"
},
  "geometry": {"coordinates":[-0.218836993,39.6592674255],"type":"Point"}
}