{
  "type": "Feature",
  "properties": {
    "addr:full":"Pase Ronda, 49 Coru\u00d1a A Coru\u00f1a 15011",
    "addr:housenumber":"49",
    "addr:postcode":"15011",
    "addr:street":"Ronda;Corun\u0303A",
    "iso:country":"ES",
    "sg:address":"Pase Ronda, 49",
    "sg:city":"Coru\u00d1a",
    "sg:orig_category":"Ense\u00d1anza Secundaria: Colegios Y Escuelas Privadas",
    "sg:phone":"+34 981 27 86 55",
    "sg:postcode":"15011",
    "sg:province":"A Coru\u00f1a",
    "wof:name":"Xunta De Galicia Red Privada",
    "wof:placetype":"venue"
},
  "geometry": {"coordinates":[-8.4485845566,43.3661346436],"type":"Point"}
}