{
  "type": "Feature",
  "properties": {
    "iso:country":"ES",
    "sg:address":"Calle de Berruguete, 2",
    "sg:city":"Madrid",
    "sg:orig_category":"Restaurantes",
    "sg:phone":"+34 914 50 17 59",
    "sg:postcode":"28039",
    "sg:province":"Madrid",
    "wof:name":"Abril Rodriguez Juan Manuel",
    "wof:placetype":"venue"
},
  "geometry": {"coordinates":[-3.703395,40.455391],"type":"Point"}
}