{
  "type": "Feature",
  "properties": {
    "iso:country":"ES",
    "sg:address":"Carrer de Emili Badiella, 53",
    "sg:city":"Terrassa",
    "sg:orig_category":"Peluquer\u00cdas, Peluquer\u00cda Mixta",
    "sg:phone":"+34 937 35 46 91",
    "sg:postcode":"08225",
    "sg:province":"Barcelona",
    "wof:name":"Rosique Poveda Isabel",
    "wof:placetype":"venue"
},
  "geometry": {"coordinates":[2.0150299072,41.5744934082],"type":"Point"}
}