{
  "type": "Feature",
  "properties": {
    "iso:country":"ES",
    "sg:address":"Calle de Aldaya, 45",
    "sg:city":"Madrid",
    "sg:orig_category":"Arreglo, Reparaci\u00d3n, Piezas Sueltas De Televisi\u00d3n, V\u00cddeo, Hi",
    "sg:phone":"+34 913 81 72 99",
    "sg:postcode":"28033",
    "sg:province":"Madrid",
    "wof:name":"Rodriguez Albarran Tirso",
    "wof:placetype":"venue"
},
  "geometry": {"coordinates":[-3.6480534077,40.4782066345],"type":"Point"}
}