{
  "type": "Feature",
  "properties": {
    "addr:full":"Calle de Feria, 34 Sotogrande C\u00e1diz 11310",
    "addr:housenumber":"34",
    "addr:postcode":"11310",
    "addr:street":"Calle De Feria;Ca\u0301Diz",
    "iso:country":"ES",
    "sg:address":"Calle de Feria, 34",
    "sg:city":"Sotogrande",
    "sg:orig_category":"Inmobiliaria (agencias)",
    "sg:phone":"+34 956 79 69 09",
    "sg:postcode":"11310",
    "sg:province":"C\u00e1diz",
    "wof:name":"Dirlanda Sl",
    "wof:placetype":"venue"
},
  "geometry": {"coordinates":[-5.3322811127,36.2752723694],"type":"Point"}
}