{
  "type": "Feature",
  "properties": {
    "iso:country":"ES",
    "sg:address":"Calle de Rio Manzanares, 23",
    "sg:city":"Valdemoro",
    "sg:orig_category":"M\u00c9dicos: Estomatolog\u00cda",
    "sg:phone":"+34 918 95 69 12",
    "sg:postcode":"28340",
    "sg:province":"Madrid",
    "wof:name":"Reed Godoy Celeste Andrea",
    "wof:placetype":"venue"
},
  "geometry": {"coordinates":[-3.6851379871,40.193901062],"type":"Point"}
}