{
  "type": "Feature",
  "properties": {
    "addr:full":"Calle de Xi, 10 Matas-pinar-monte Rozas Madrid 28290",
    "addr:housenumber":"10",
    "addr:postcode":"28290",
    "addr:street":"Calle De Xi",
    "iso:country":"ES",
    "sg:address":"Calle de Xi, 10",
    "sg:city":"Matas-pinar-monte Rozas",
    "sg:orig_category":"Mercer\u00cda, Lencer\u00cda (al Por Menor)",
    "sg:phone":"+34 916 30 01 73",
    "sg:postcode":"28290",
    "sg:province":"Madrid",
    "wof:name":"Jimenez Diaz Amparo",
    "wof:placetype":"venue"
},
  "geometry": {"coordinates":[-3.9152576923,40.5226135254],"type":"Point"}
}