{
  "type": "Feature",
  "properties": {
    "addr:full":"Calle de Periodista Federico Joly, S/n Cadiz C\u00e1diz 11012",
    "addr:housenumber":"s / n",
    "addr:postcode":"11012",
    "addr:street":"Calle De Periodista Federico Joly",
    "iso:country":"ES",
    "sg:address":"Calle de Periodista Federico Joly, S/n",
    "sg:city":"Cadiz",
    "sg:orig_category":"Alimentaci\u00d3n General (al Por Menor)",
    "sg:phone":"+34 956 26 26 14",
    "sg:postcode":"11012",
    "sg:province":"C\u00e1diz",
    "wof:name":"Asociacion Alendoy Colegio Eduardo Benot",
    "wof:placetype":"venue"
},
  "geometry": {"coordinates":[-6.2735948563,36.5148010254],"type":"Point"}
}