{
  "type": "Feature",
  "properties": {
    "addr:full":"Calle de Villadiego, 5 Lora Rio Sevilla 41440",
    "addr:housenumber":"5",
    "addr:postcode":"41440",
    "addr:street":"Calle De Villadiego;Rio Sevilla",
    "iso:country":"ES",
    "sg:address":"Calle de Villadiego, 5",
    "sg:city":"Lora Rio",
    "sg:orig_category":"Venta, Colocaci\u00d3n, Reparaci\u00d3n De Radiadores Para Veh\u00cdculos",
    "sg:phone":"+34 955 80 08 27",
    "sg:postcode":"41440",
    "sg:province":"Sevilla",
    "wof:name":"Millan Blanco Jose Antonio",
    "wof:placetype":"venue"
},
  "geometry": {"coordinates":[-5.5276651382,37.6598777771],"type":"Point"}
}