{
  "type": "Feature",
  "properties": {
    "iso:country":"ES",
    "sg:address":"Calle de Pedro Garavito, 4",
    "sg:city":"Arenas San Pedro",
    "sg:orig_category":"Peluquer\u00cdas, Peluquer\u00cda Mixta",
    "sg:phone":"+34 920 37 10 00",
    "sg:postcode":"05400",
    "sg:province":"\u00c1vila",
    "wof:name":"Suarez Perez Adoracion",
    "wof:placetype":"venue"
},
  "geometry": {"coordinates":[-5.0866141319,40.210231781],"type":"Point"}
}