{
  "type": "Feature",
  "properties": {
    "iso:country":"ES",
    "sg:address":"Ctra Cartagena, S/n",
    "sg:city":"Palmar  O Lugar De Don Juan",
    "sg:orig_category":"Florister\u00cdas",
    "sg:phone":"+34 968 88 59 91",
    "sg:postcode":"30120",
    "sg:province":"Murcia",
    "wof:name":"Diaz Ramos Antonio",
    "wof:placetype":"venue"
},
  "geometry": {"coordinates":[-1.1635539532,37.9342384338],"type":"Point"}
}