{
  "type": "Feature",
  "properties": {
    "iso:country":"ES",
    "sg:address":"Calle de Huelva, 133",
    "sg:city":"Ayamonte",
    "sg:orig_category":"Promotores Constructores",
    "sg:phone":"+34 959 32 12 20",
    "sg:postcode":"21400",
    "sg:province":"Huelva",
    "wof:name":"Construcciones Juan Margallo S.l.",
    "wof:placetype":"venue"
},
  "geometry": {"coordinates":[-7.4016208649,37.2146034241],"type":"Point"}
}