{
  "type": "Feature",
  "properties": {
    "iso:country":"ES",
    "sg:address":"Isaac Peral, 24",
    "sg:city":"Rubio",
    "sg:orig_category":"Transportes Por V\u00cdas Navegables",
    "sg:phone":"+34 955 82 84 67",
    "sg:postcode":"41568",
    "sg:province":"Sevilla",
    "wof:name":"Perez Moreno Manuel",
    "wof:placetype":"venue"
},
  "geometry": {"coordinates":[-4.9903421402,37.3552055359],"type":"Point"}
}