{
  "type": "Feature",
  "properties": {
    "iso:country":"ES",
    "sg:address":"Calle de Suarez Somonte, 19",
    "sg:city":"Merida",
    "sg:orig_category":"Panader\u00cdas, Panader\u00cdas",
    "sg:phone":"+34 924 31 12 10",
    "sg:postcode":"06800",
    "sg:province":"Badajoz",
    "wof:name":"Sanchez Benitez Isidra",
    "wof:placetype":"venue"
},
  "geometry": {"coordinates":[-6.3430957794,38.9146766663],"type":"Point"}
}