{
  "type": "Feature",
  "properties": {
    "iso:country":"ES",
    "sg:address":"Calle de Anselmo Perez De Brito, 58",
    "sg:city":"Santa Cruz Palma",
    "sg:orig_category":"Abogados",
    "sg:phone":"+34 922 41 61 53",
    "sg:postcode":"38700",
    "sg:province":"Santa Cruz De Tenerife",
    "wof:name":"Rodriguez Camino Luis Miguel",
    "wof:placetype":"venue"
},
  "geometry": {"coordinates":[-17.7624740601,28.6856517792],"type":"Point"}
}