{
  "type": "Feature",
  "properties": {
    "addr:full":"Avda Principe De Asturias, 13 Navalmorales Toledo 45140",
    "addr:housenumber":"13",
    "addr:postcode":"45140",
    "addr:street":"Avda Principe De Asturias",
    "iso:country":"ES",
    "sg:address":"Avda Principe De Asturias, 13",
    "sg:city":"Navalmorales",
    "sg:orig_category":"Supermercados Y Hipermercados",
    "sg:phone":"+34 925 40 49 25",
    "sg:postcode":"45140",
    "sg:province":"Toledo",
    "wof:name":"Del Puerto Martin Ramon",
    "wof:placetype":"venue"
},
  "geometry": {"coordinates":[-4.645318985,39.7231063843],"type":"Point"}
}