{
  "type": "Feature",
  "properties": {
    "addr:full":"Pla\u00c7 Paeria, 13 Lleida Lleida 25007",
    "addr:housenumber":"13",
    "addr:postcode":"25007",
    "addr:street":"Plac\u0327 Paeria",
    "iso:country":"ES",
    "sg:address":"Pla\u00c7 Paeria, 13",
    "sg:city":"Lleida",
    "sg:orig_category":"Zapater\u00cdas",
    "sg:phone":"+34 973 24 22 42",
    "sg:postcode":"25007",
    "sg:province":"Lleida",
    "wof:name":"Farreres Arroyo Maria Dolores",
    "wof:placetype":"venue"
},
  "geometry": {"coordinates":[0.627129972,41.6145210266],"type":"Point"}
}