{
  "type": "Feature",
  "properties": {
    "addr:full":"Calle de Camarena, 233 Madrid Madrid 28047",
    "addr:housenumber":"233",
    "addr:postcode":"28047",
    "addr:street":"Calle De Camarena",
    "iso:country":"ES",
    "sg:address":"Calle de Camarena, 233",
    "sg:city":"Madrid",
    "sg:orig_category":"Mudanzas",
    "sg:phone":"+34 917 17 95 86",
    "sg:postcode":"28047",
    "sg:province":"Madrid",
    "wof:name":"Gonzalez Garcia Pedro Antonio",
    "wof:placetype":"venue"
},
  "geometry": {"coordinates":[-3.7568058968,40.3864555359],"type":"Point"}
}