{
  "type": "Feature",
  "properties": {
    "iso:country":"ES",
    "sg:address":"Plaz Miramar, 57",
    "sg:city":"Luanco",
    "sg:orig_category":"Molduras, Junquillos, Listones Y Molduras Perforadas",
    "sg:phone":"+34 985 88 07 68",
    "sg:postcode":"33440",
    "sg:province":"Asturias",
    "wof:name":"Alvarez Alonso Bernardo",
    "wof:placetype":"venue"
},
  "geometry": {"coordinates":[-5.9600286484,43.5770683289],"type":"Point"}
}