{
  "type": "Feature",
  "properties": {
    "addr:full":"Calle de Emeterio Cuadrado, 10 Mula Murcia 30170",
    "addr:housenumber":"10",
    "addr:postcode":"30170",
    "addr:street":"Calle De Emeterio Cuadrado",
    "iso:country":"ES",
    "sg:address":"Calle de Emeterio Cuadrado, 10",
    "sg:city":"Mula",
    "sg:orig_category":"Hielo Artificial (fabricaci\u00d3n, Distribuci\u00d3n)",
    "sg:phone":"+34 968 66 16 11",
    "sg:postcode":"30170",
    "sg:province":"Murcia",
    "wof:name":"Helados Picolo S.l.",
    "wof:placetype":"venue"
},
  "geometry": {"coordinates":[-1.493376255,38.0402755737],"type":"Point"}
}