{
  "type": "Feature",
  "properties": {
    "addr:full":"Calle de Arjona, 45 Arjonilla Ja\u00e9n 23750",
    "addr:housenumber":"45",
    "addr:postcode":"23750",
    "addr:street":"Calle De Arjona",
    "iso:country":"ES",
    "sg:address":"Calle de Arjona, 45",
    "sg:city":"Arjonilla",
    "sg:orig_category":"Cer\u00c1mica Art\u00cdstica Y Decorativa",
    "sg:phone":"+34 953 52 12 74",
    "sg:postcode":"23750",
    "sg:province":"Ja\u00e9n",
    "wof:name":"Ceramica Artistica Rualbin C.b.",
    "wof:placetype":"venue"
},
  "geometry": {"coordinates":[-4.098300457,37.9734725952],"type":"Point"}
}