{
  "type": "Feature",
  "properties": {
    "iso:country":"ES",
    "sg:address":"Afueras, S/n",
    "sg:city":"S. Josep Talaia",
    "sg:orig_category":"Hoteles",
    "sg:phone":"+34 971 80 03 18",
    "sg:postcode":"07830",
    "sg:province":"Islas Baleares",
    "wof:name":"Agua C.b.",
    "wof:placetype":"venue"
},
  "geometry": {"coordinates":[2.8577105999,39.5341796875],"type":"Point"}
}