{
  "type": "Feature",
  "properties": {
    "iso:country":"ES",
    "sg:address":"Calle de Concepcion Arenal, 12",
    "sg:city":"Gijon",
    "sg:orig_category":"Tintorer\u00cdas, Limpieza En Seco",
    "sg:phone":"+34 985 35 55 64",
    "sg:postcode":"33202",
    "sg:province":"Asturias",
    "wof:name":"Bustas Cuartas Raquel",
    "wof:placetype":"venue"
},
  "geometry": {"coordinates":[-5.6586198807,43.5392608643],"type":"Point"}
}