{
  "type": "Feature",
  "properties": {
    "iso:country":"ES",
    "sg:address":"Av Aixernador (l'), 9",
    "sg:city":"Argentona",
    "sg:orig_category":"Mec\u00c1nico Del Autom\u00d3vil",
    "sg:phone":"+34 937 97 05 54",
    "sg:postcode":"08310",
    "sg:province":"Barcelona",
    "wof:name":"Pruna Dangla Jose",
    "wof:placetype":"venue"
},
  "geometry": {"coordinates":[2.4047369957,41.5570907593],"type":"Point"}
}