{
  "type": "Feature",
  "properties": {
    "iso:country":"ES",
    "sg:address":"La Barganiza, S/n",
    "sg:city":"Anes",
    "sg:orig_category":"Maquinaria Para Industrias Diversas",
    "sg:phone":"+34 985 74 18 53",
    "sg:postcode":"33192",
    "sg:province":"Asturias",
    "wof:name":"Lopez Mosquera Julio",
    "wof:placetype":"venue"
},
  "geometry": {"coordinates":[-5.7745718956,43.4596939087],"type":"Point"}
}