{
  "type": "Feature",
  "properties": {
    "iso:country":"ES",
    "sg:address":"Calle de Luis Moraleda, S/n",
    "sg:city":"Malaga",
    "sg:orig_category":"Sociedades, Compa\u00d1\u00cdas Aseguradoras",
    "sg:phone":"+34 952 33 25 74",
    "sg:postcode":"29003",
    "sg:province":"M\u00e1laga",
    "wof:name":"Gestion Pericial Bermudez S.l.",
    "wof:placetype":"venue"
},
  "geometry": {"coordinates":[-4.4493727684,36.6979598999],"type":"Point"}
}