{
  "type": "Feature",
  "properties": {
    "iso:country":"ES",
    "sg:address":"Rua Cabeza De Manzaneda, 12",
    "sg:city":"Ourense",
    "sg:orig_category":"Muebles Y Accesorios Para Cocinas Y Cuartos De Ba\u00d1o (al Por Menor)",
    "sg:phone":"+34 988 25 30 85",
    "sg:postcode":"32005",
    "sg:province":"Ourense",
    "wof:name":"Cervi\u00f1o Rodriguez Maria Teresa Clara",
    "wof:placetype":"venue"
},
  "geometry": {"coordinates":[-7.8619499207,42.335067749],"type":"Point"}
}