{
  "type": "Feature",
  "properties": {
    "iso:country":"ES",
    "sg:address":"Carr Doctor Camps, 1",
    "sg:city":"Mao",
    "sg:orig_category":"Laboratorios Y Trabajos De Fotograf\u00cda, V\u00cddeo Y Cine",
    "sg:phone":"+34 971 35 31 81",
    "sg:postcode":"07703",
    "sg:province":"Islas Baleares",
    "wof:name":"Illa Color S.l.",
    "wof:placetype":"venue"
},
  "geometry": {"coordinates":[4.2592000961,39.8858604431],"type":"Point"}
}