{
  "type": "Feature",
  "properties": {
    "iso:country":"ES",
    "sg:address":"Calle de Camino De Las Acacias, 20",
    "sg:city":"Urbanizacion La Fresneda",
    "sg:orig_category":"Urbanistas",
    "sg:phone":"+34 985 26 75 85",
    "sg:postcode":"33429",
    "sg:province":"Asturias",
    "wof:name":"Gsgs Consultores Asociados S.l.",
    "wof:placetype":"venue"
},
  "geometry": {"coordinates":[-5.7888607979,43.4130096436],"type":"Point"}
}