{
  "type": "Feature",
  "properties": {
    "addr:full":"Carrer de Calderon, 169 Sabadell Barcelona 08201",
    "addr:housenumber":"169",
    "addr:postcode":"08201",
    "addr:street":"Carrer De Calderon",
    "iso:country":"ES",
    "sg:address":"Carrer de Calderon, 169",
    "sg:city":"Sabadell",
    "sg:orig_category":"Molduras, Junquillos, Listones Y Molduras Perforadas",
    "sg:phone":"+34 937 27 05 41",
    "sg:postcode":"08201",
    "sg:province":"Barcelona",
    "wof:name":"Moya Mendoza Antonio",
    "wof:placetype":"venue"
},
  "geometry": {"coordinates":[2.0999419689,41.5461769104],"type":"Point"}
}