{
  "type": "Feature",
  "properties": {
    "addr:full":"Calle de Puerto Principe, 2 Madrid Madrid 28043",
    "addr:housenumber":"2",
    "addr:postcode":"28043",
    "addr:street":"Calle De Puerto Principe",
    "iso:country":"ES",
    "sg:address":"Calle de Puerto Principe, 2",
    "sg:city":"Madrid",
    "sg:orig_category":"Trabajos De Perforaciones, Sondeos, Construcci\u00d3n De Pozos",
    "sg:phone":"+34 913 81 88 11",
    "sg:postcode":"28043",
    "sg:province":"Madrid",
    "wof:name":"Rela\u00f1o Medina Jose",
    "wof:placetype":"venue"
},
  "geometry": {"coordinates":[-3.6447439194,40.4692306519],"type":"Point"}
}