{
  "type": "Feature",
  "properties": {
    "iso:country":"ES",
    "sg:address":"Calle de Carlota Navarrete, 23",
    "sg:city":"San Pedro Alcantara",
    "sg:orig_category":"Tapicer\u00cdas",
    "sg:phone":"+34 952 78 86 28",
    "sg:postcode":"29670",
    "sg:province":"M\u00e1laga",
    "wof:name":"Garcia Etayo Emilio",
    "wof:placetype":"venue"
},
  "geometry": {"coordinates":[-4.9877281189,36.4848709106],"type":"Point"}
}