{
  "type": "Feature",
  "properties": {
    "addr:full":"Avda Estacion (de La), 14 Almeria Almer\u00eda 04005",
    "addr:housenumber":"14",
    "addr:postcode":"04005",
    "addr:street":"Avda Estacion De La",
    "iso:country":"ES",
    "sg:address":"Avda Estacion (de La), 14",
    "sg:city":"Almeria",
    "sg:orig_category":"M\u00c1rmoles, Granitos Y Piedras Naturales",
    "sg:phone":"+34 950 23 33 16",
    "sg:postcode":"04005",
    "sg:province":"Almer\u00eda",
    "wof:name":"Uran Sola Serafin",
    "wof:placetype":"venue"
},
  "geometry": {"coordinates":[-2.4588000774,36.8374404907],"type":"Point"}
}