{
  "type": "Feature",
  "properties": {
    "iso:country":"ES",
    "sg:address":"Calle de Palacio, 1",
    "sg:city":"Alfafar",
    "sg:orig_category":"Desinfecci\u00d3n, Desinsectaci\u00d3n, Desratizaci\u00d3n",
    "sg:phone":"+34 963 75 63 45",
    "sg:postcode":"46910",
    "sg:province":"Valencia",
    "wof:name":"Garfer Control Y Servicios Comerciales S.l.",
    "wof:placetype":"venue"
},
  "geometry": {"coordinates":[-0.3912189901,39.4217987061],"type":"Point"}
}