{
  "type": "Feature",
  "properties": {
    "iso:country":"ES",
    "sg:address":"Calle de Antonio Concha, 33",
    "sg:city":"Navalmoral Mata",
    "sg:orig_category":"Droguer\u00cdas (al Por Menor)",
    "sg:phone":"+34 927 53 02 81",
    "sg:postcode":"10300",
    "sg:province":"C\u00e1ceres",
    "wof:name":"Ramos Gutierrez Jesus",
    "wof:placetype":"venue"
},
  "geometry": {"coordinates":[-5.539085865,39.8909492493],"type":"Point"}
}