{
  "type": "Feature",
  "properties": {
    "addr:full":"Carrer de Major, 9 Amposta Tarragona 43870",
    "addr:housenumber":"9",
    "addr:postcode":"43870",
    "addr:street":"Carrer De Major",
    "iso:country":"ES",
    "sg:address":"Carrer de Major, 9",
    "sg:city":"Amposta",
    "sg:orig_category":"Cl\u00cdnicas Dentales",
    "sg:phone":"+34 977 70 37 23",
    "sg:postcode":"43870",
    "sg:province":"Tarragona",
    "wof:name":"Clide S.l.",
    "wof:placetype":"venue"
},
  "geometry": {"coordinates":[0.5803819895,40.7129478455],"type":"Point"}
}