{
  "type": "Feature",
  "properties": {
    "iso:country":"ES",
    "sg:address":"Carrer de Albert Llanas, 24",
    "sg:city":"Barcelona",
    "sg:orig_category":"Empresas De Carpinter\u00cda De Madera",
    "sg:phone":"+34 932 19 94 08",
    "sg:postcode":"08024",
    "sg:province":"Barcelona",
    "wof:name":"Carballo Gonzalez Jose",
    "wof:placetype":"venue"
},
  "geometry": {"coordinates":[2.1583240032,41.4166564941],"type":"Point"}
}