{
  "type": "Feature",
  "properties": {
    "addr:full":"Calle de Vega Nueva, S/n Sestao Vizcaya 48910",
    "addr:housenumber":"s / n",
    "addr:postcode":"48910",
    "addr:street":"Calle De Vega Nueva",
    "iso:country":"ES",
    "sg:address":"Calle de Vega Nueva, S/n",
    "sg:city":"Sestao",
    "sg:orig_category":"Agentes, Concesionarios Y Sucursales De Veh\u00cdculos",
    "sg:phone":"+34 944 72 23 38",
    "sg:postcode":"48910",
    "sg:province":"Vizcaya",
    "wof:name":"Auvol S.a.",
    "wof:placetype":"venue"
},
  "geometry": {"coordinates":[-2.9913184643,43.3058319092],"type":"Point"}
}