{
  "type": "Feature",
  "properties": {
    "addr:full":"Carr Cosmografo Ramirez, 15 Xativa Valencia 46800",
    "addr:housenumber":"15",
    "addr:postcode":"46800",
    "addr:street":"Carr Cosmografo Ramirez",
    "iso:country":"ES",
    "sg:address":"Carr Cosmografo Ramirez, 15",
    "sg:city":"Xativa",
    "sg:orig_category":"Venta, Alquiler Y Mantenimiento De Juegos De Sal\u00d3n O Casinos",
    "sg:phone":"+34 962 27 74 15",
    "sg:postcode":"46800",
    "sg:province":"Valencia",
    "wof:name":"Recreativos Xativa S. A.",
    "wof:placetype":"venue"
},
  "geometry": {"coordinates":[-0.5134630203,38.990852356],"type":"Point"}
}