{
  "type": "Feature",
  "properties": {
    "addr:full":"Calle de Cerrada Santa Cruz, 15 Benavente Zamora 49600",
    "addr:housenumber":"15",
    "addr:postcode":"49600",
    "addr:street":"Calle De Cerrada Santa Cruz",
    "iso:country":"ES",
    "sg:address":"Calle de Cerrada Santa Cruz, 15",
    "sg:city":"Benavente",
    "sg:orig_category":"Droguer\u00cdas (al Por Menor)",
    "sg:phone":"+34 980 63 17 45",
    "sg:postcode":"49600",
    "sg:province":"Zamora",
    "wof:name":"Drogas Hermanos Zamora S.l.",
    "wof:placetype":"venue"
},
  "geometry": {"coordinates":[-5.6741995811,42.0031280518],"type":"Point"}
}