{
  "type": "Feature",
  "properties": {
    "iso:country":"ES",
    "sg:address":"Emb. Inocencio Arias, S/n",
    "sg:city":"Albox",
    "sg:orig_category":"Molduras, Junquillos, Listones Y Molduras Perforadas",
    "sg:phone":"+34 950 12 08 75",
    "sg:postcode":"04800",
    "sg:province":"Almer\u00eda",
    "wof:name":"Martinez Guillen Francisco",
    "wof:placetype":"venue"
},
  "geometry": {"coordinates":[-2.1463840008,37.3870315552],"type":"Point"}
}