{
  "type": "Feature",
  "properties": {
    "addr:full":"Calle de Paseo De Navegantes, 33 Adra Almer\u00eda 04770",
    "addr:housenumber":"33",
    "addr:postcode":"04770",
    "addr:street":"Calle De Paseo De Navegantes;Almeri\u0301A",
    "iso:country":"ES",
    "sg:address":"Calle de Paseo De Navegantes, 33",
    "sg:city":"Adra",
    "sg:orig_category":"Agencias Y Agentes Comerciales, Representantes",
    "sg:phone":"+34 950 60 43 73",
    "sg:postcode":"04770",
    "sg:province":"Almer\u00eda",
    "wof:name":"Parrilla Sanchez Antonio",
    "wof:placetype":"venue"
},
  "geometry": {"coordinates":[-3.0056390762,36.7545166016],"type":"Point"}
}