{
  "type": "Feature",
  "properties": {
    "iso:country":"ES",
    "sg:address":"Calle de Ruzafa, 24",
    "sg:city":"Valencia",
    "sg:orig_category":"Parques De Atracciones Y Centros De Esparcimiento",
    "sg:phone":"+34 963 52 51 74",
    "sg:postcode":"46004",
    "sg:province":"Valencia",
    "wof:name":"Rubio Martinez Filiberto",
    "wof:placetype":"venue"
},
  "geometry": {"coordinates":[-0.3743239939,39.4655303955],"type":"Point"}
}