{
  "type": "Feature",
  "properties": {
    "iso:country":"ES",
    "sg:address":"Estda. De Vigo, 26",
    "sg:city":"Ourense",
    "sg:orig_category":"Agentes, Concesionarios Y Sucursales De Veh\u00cdculos",
    "sg:phone":"+34 988 36 50 76",
    "sg:postcode":"32001",
    "sg:province":"Ourense",
    "wof:name":"Balpersa S.a.",
    "wof:placetype":"venue"
},
  "geometry": {"coordinates":[-7.8814702034,42.3738327026],"type":"Point"}
}