{
  "type": "Feature",
  "properties": {
    "addr:full":"Calle de Marcelo Usera, 63 Madrid Madrid 28026",
    "addr:housenumber":"63",
    "addr:postcode":"madrid;28026",
    "addr:street":"Calle De Marcelo Usera",
    "iso:country":"ES",
    "sg:address":"Calle de Marcelo Usera, 63",
    "sg:city":"Madrid",
    "sg:orig_category":"Camiser\u00cda Y Ropa Interior Masculina (al Por Menor)",
    "sg:phone":"+34 915 00 22 93",
    "sg:postcode":"28026",
    "sg:province":"Madrid",
    "sg:website":"www.tonycollections.com",
    "wof:name":"Mingo Saez Antonio",
    "wof:placetype":"venue"
},
  "geometry": {"coordinates":[-3.704877615,40.3858566284],"type":"Point"}
}