{
  "type": "Feature",
  "properties": {
    "iso:country":"ES",
    "sg:address":"Avda Esteiro, 70",
    "sg:city":"Ferrol",
    "sg:orig_category":"Asociaciones, Organismos Culturales Y Socioeducativos",
    "sg:phone":"+34 981 36 90 09",
    "sg:postcode":"15403",
    "sg:province":"La Coru\u00f1a",
    "sg:website":"www.circulo.es",
    "wof:name":"Circulo De Lectores S.a.",
    "wof:placetype":"venue"
},
  "geometry": {"coordinates":[-8.2238388062,43.4838790894],"type":"Point"}
}