{
  "type": "Feature",
  "properties": {
    "addr:full":"C/ Poeta Miguel Hernandez, 94 Elche Alicante 03201",
    "addr:housenumber":"94",
    "addr:postcode":"03201",
    "addr:street":"C / Poeta Miguel Hernandez",
    "iso:country":"ES",
    "sg:address":"C/ Poeta Miguel Hernandez, 94",
    "sg:city":"Elche",
    "sg:orig_category":"Empresas De Pintura Y Revestimientos",
    "sg:phone":"+34 965 46 20 83",
    "sg:postcode":"03201",
    "sg:province":"Alicante",
    "wof:name":"Alcaraz Martinez Jose",
    "wof:placetype":"venue"
},
  "geometry": {"coordinates":[-0.556838274,38.1914367676],"type":"Point"}
}