{
  "type": "Feature",
  "properties": {
    "iso:country":"ES",
    "sg:address":"Calle de Timanfaya, S/n",
    "sg:city":"Santa Cruz De Tenerife",
    "sg:orig_category":"Quincaller\u00cda (al Por Menor)",
    "sg:phone":"+34 922 20 11 83",
    "sg:postcode":"38009",
    "sg:province":"Santa Cruz De Tenerife",
    "wof:name":"Fijaciones Canarias S.l.",
    "wof:placetype":"venue"
},
  "geometry": {"coordinates":[-16.2747745514,28.461894989],"type":"Point"}
}