{
  "type": "Feature",
  "properties": {
    "iso:country":"ES",
    "sg:address":"Carrer de Roger De Lluria, 25",
    "sg:city":"Barcelona",
    "sg:orig_category":"Disfraces",
    "sg:phone":"+34 933 01 00 89",
    "sg:postcode":"08010",
    "sg:province":"Barcelona",
    "sg:website":"www.atuendoforfun.com",
    "wof:name":"Atuendo For Fun S.l.",
    "wof:placetype":"venue"
},
  "geometry": {"coordinates":[2.1705510616,41.3916511536],"type":"Point"}
}