{
  "type": "Feature",
  "properties": {
    "addr:full":"Rua Sagasta, 16 Pontevedra Pontevedra 36001",
    "addr:housenumber":"16",
    "addr:postcode":"36001",
    "addr:street":"Rua Sagasta",
    "iso:country":"ES",
    "sg:address":"Rua Sagasta, 16",
    "sg:city":"Pontevedra",
    "sg:orig_category":"Bancos",
    "sg:phone":"+34 986 86 64 52",
    "sg:postcode":"36001",
    "sg:province":"Pontevedra",
    "wof:name":"Banco Etcheverria",
    "wof:placetype":"venue"
},
  "geometry": {"coordinates":[-8.6416788101,42.4292678833],"type":"Point"}
}