{
  "type": "Feature",
  "properties": {
    "addr:full":"Pol Ind Cantalgallo, 4 Aracena Huelva 21200",
    "addr:housenumber":"4",
    "addr:postcode":"21200",
    "addr:street":"Cantalgallo",
    "iso:country":"ES",
    "sg:address":"Pol Ind Cantalgallo, 4",
    "sg:city":"Aracena",
    "sg:orig_category":"Empresas De Carpinter\u00cda Met\u00c1lica",
    "sg:phone":"+34 959 12 73 71",
    "sg:postcode":"21200",
    "sg:province":"Huelva",
    "wof:name":"Hierros Mercan Cdad",
    "wof:placetype":"venue"
},
  "geometry": {"coordinates":[-6.5612440109,37.8929443359],"type":"Point"}
}