{
  "type": "Feature",
  "properties": {
    "iso:country":"ES",
    "sg:address":"Calle de Matias Garcia, S/n",
    "sg:city":"Coin",
    "sg:orig_category":"Inform\u00c1tica, Ofim\u00c1tica (estudios, Asesor\u00cda, Ingenier\u00cda, Formaci\u00d3n)",
    "sg:phone":"+34 952 45 57 56",
    "sg:postcode":"29100",
    "sg:province":"M\u00e1laga",
    "wof:name":"Pc Studio Sistemas Informatico",
    "wof:placetype":"venue"
},
  "geometry": {"coordinates":[-4.7535591125,36.659450531],"type":"Point"}
}