{
  "type": "Feature",
  "properties": {
    "iso:country":"ES",
    "sg:address":"Avda Portus Illicitanus, 10",
    "sg:city":"Santa Pola",
    "sg:orig_category":"Peluquer\u00cdas, Peluquer\u00cda Mixta",
    "sg:phone":"+34 965 41 71 05",
    "sg:postcode":"03130",
    "sg:province":"Alicante",
    "wof:name":"Murillo Nogales Manoli",
    "wof:placetype":"venue"
},
  "geometry": {"coordinates":[-0.5610460043,38.1943702698],"type":"Point"}
}