{
  "type": "Feature",
  "properties": {
    "iso:country":"ES",
    "sg:address":"Calle de General Franco, 4",
    "sg:city":"Ahigal",
    "sg:orig_category":"Carnicer\u00cdas, Carnicer\u00cdas",
    "sg:phone":"+34 927 43 93 12",
    "sg:postcode":"10650",
    "sg:province":"C\u00e1ceres",
    "wof:name":"Barroso Jimenez Alejandro",
    "wof:placetype":"venue"
},
  "geometry": {"coordinates":[-6.1865739822,40.189781189],"type":"Point"}
}