{
  "type": "Feature",
  "properties": {
    "iso:country":"ES",
    "sg:address":"Par. Mas Patxot, S/n",
    "sg:city":"Llagostera",
    "sg:orig_category":"Maquinaria Para Industrias Diversas",
    "sg:phone":"+34 972 83 12 33",
    "sg:postcode":"17240",
    "sg:province":"Girona",
    "wof:name":"Alberich Abello S.l.",
    "wof:placetype":"venue"
},
  "geometry": {"coordinates":[2.8939113617,41.8292808533],"type":"Point"}
}