{
  "type": "Feature",
  "properties": {
    "iso:country":"ES",
    "sg:address":"Carrer de Girona, 92",
    "sg:city":"Barcelona",
    "sg:orig_category":"Peluquer\u00cdas, Peluquer\u00cda Mixta",
    "sg:phone":"+34 934 59 00 58",
    "sg:postcode":"08009",
    "sg:province":"Barcelona",
    "wof:name":"Andreu Puig Abel",
    "wof:placetype":"venue"
},
  "geometry": {"coordinates":[2.1696960926,41.3959236145],"type":"Point"}
}