{
  "type": "Feature",
  "properties": {
    "addr:full":"Avda Madrid (de), 73 Chipiona C\u00e1diz 11550",
    "addr:housenumber":"73",
    "addr:postcode":"11550",
    "addr:street":"Avda Madrid De",
    "iso:country":"ES",
    "sg:address":"Avda Madrid (de), 73",
    "sg:city":"Chipiona",
    "sg:orig_category":"Electrodom\u00c9sticos (al Por Menor)",
    "sg:phone":"+34 956 37 25 15",
    "sg:postcode":"11550",
    "sg:province":"C\u00e1diz",
    "wof:name":"Franco Del Valle Juan",
    "wof:placetype":"venue"
},
  "geometry": {"coordinates":[-6.4310669899,36.7336807251],"type":"Point"}
}