{
  "type": "Feature",
  "properties": {
    "iso:country":"ES",
    "sg:address":"Calle de Caveda Y Nava, 3",
    "sg:city":"Villaviciosa",
    "sg:classifiers":[
        {
            "category":"Personal",
            "subcategory":"Barber",
            "type":"Services"
        }
    ],
    "sg:phone":"+34 985 89 14 26",
    "sg:postcode":"33300",
    "sg:province":"Asturias",
    "sg:tags":[
        "caballeros",
        "de",
        "peluqueros"
    ],
    "wof:name":"Candas Granda Fulgencio",
    "wof:placetype":"venue"
},
  "geometry": {"coordinates":[-5.4350242615,43.4802398682],"type":"Point"}
}