{
  "type": "Feature",
  "properties": {
    "iso:country":"ES",
    "sg:address":"Avda Barber, 2",
    "sg:city":"Toledo",
    "sg:orig_category":"Arquitectos",
    "sg:phone":"+34 925 25 39 34",
    "sg:postcode":"45004",
    "sg:province":"Toledo",
    "wof:name":"Cobos Gil Arquitectos S.l.",
    "wof:placetype":"venue"
},
  "geometry": {"coordinates":[-4.0301408768,39.8688278198],"type":"Point"}
}