{
  "type": "Feature",
  "properties": {
    "iso:country":"ES",
    "sg:address":"Calle de Santander, 32",
    "sg:city":"Zaragoza",
    "sg:orig_category":"Estudios, Instalaci\u00d3n De Climatizaci\u00d3n",
    "sg:phone":"+34 976 53 38 95",
    "sg:postcode":"50010",
    "sg:province":"Zaragoza",
    "wof:name":"Ansatra S.a.",
    "wof:placetype":"venue"
},
  "geometry": {"coordinates":[-0.8967366815,41.649055481],"type":"Point"}
}