{
  "type": "Feature",
  "properties": {
    "addr:full":"Calle de Huertas (las), 7 Aguilar Campoo Palencia 34800",
    "addr:housenumber":"7",
    "addr:postcode":"34800",
    "addr:street":"Calle De Huertas Las",
    "iso:country":"ES",
    "sg:address":"Calle de Huertas (las), 7",
    "sg:city":"Aguilar Campoo",
    "sg:orig_category":"Agencias De Viajes",
    "sg:phone":"+34 979 12 51 36",
    "sg:postcode":"34800",
    "sg:province":"Palencia",
    "wof:name":"Garfercar S.l.",
    "wof:placetype":"venue"
},
  "geometry": {"coordinates":[-4.2870588303,42.7445793152],"type":"Point"}
}