{
  "type": "Feature",
  "properties": {
    "addr:full":"Carrer de Torcuato Luca Tena, 43 Palma Islas Baleares 07005",
    "addr:housenumber":"43",
    "addr:postcode":"07005",
    "addr:street":"Carrer De Torcuato Luca Tena",
    "iso:country":"ES",
    "sg:address":"Carrer de Torcuato Luca Tena, 43",
    "sg:city":"Palma",
    "sg:orig_category":"\u00d3ptica: Instrumentos (fabricaci\u00d3n)",
    "sg:phone":"+34 971 27 39 55",
    "sg:postcode":"07005",
    "sg:province":"Islas Baleares",
    "wof:name":"Jaime Guasp Perello S. A.",
    "wof:placetype":"venue"
},
  "geometry": {"coordinates":[2.662956953,39.5781860352],"type":"Point"}
}