{
  "type": "Feature",
  "properties": {
    "iso:country":"ES",
    "sg:address":"Calle de Feijoo, 36",
    "sg:city":"Gijon",
    "sg:orig_category":"Porcelanas, Azulejos (fabricaci\u00d3n, Al Por Mayor)",
    "sg:phone":"+34 985 33 64 13",
    "sg:postcode":"33204",
    "sg:province":"Asturias",
    "wof:name":"Suministros Ceramicos Errasti S.l.",
    "wof:placetype":"venue"
},
  "geometry": {"coordinates":[-5.6502919197,43.5320777893],"type":"Point"}
}