{
  "type": "Feature",
  "properties": {
    "addr:full":"Pg Vint-i-dos De Juliol, 408 Terrassa Barcelona 08221",
    "addr:housenumber":"408",
    "addr:postcode":"08221",
    "addr:street":"Pg Vint-I-Dos",
    "iso:country":"ES",
    "sg:address":"Pg Vint-i-dos De Juliol, 408",
    "sg:city":"Terrassa",
    "sg:orig_category":"Centros Empresariales",
    "sg:phone":"+34 937 84 40 08",
    "sg:postcode":"08221",
    "sg:province":"Barcelona",
    "wof:name":"Ingest Egara S. L.",
    "wof:placetype":"venue"
},
  "geometry": {"coordinates":[2.0148661137,41.5696487427],"type":"Point"}
}