{
  "type": "Feature",
  "properties": {
    "iso:country":"ES",
    "sg:address":"Calle de Infanta Maria Teresa, 12",
    "sg:city":"Madrid",
    "sg:orig_category":"Mec\u00c1nico Del Autom\u00d3vil",
    "sg:phone":"+34 914 57 76 37",
    "sg:postcode":"28016",
    "sg:province":"Madrid",
    "wof:name":"Talleres Jurado Y Lopez",
    "wof:placetype":"venue"
},
  "geometry": {"coordinates":[-3.6806778908,40.4539527893],"type":"Point"}
}