{
  "type": "Feature",
  "properties": {
    "addr:full":"Plaz San Juan De Covas, 9 Alcorcon Madrid 28925",
    "addr:housenumber":"9",
    "addr:postcode":"28925",
    "addr:street":"Plaz;Covas",
    "iso:country":"ES",
    "sg:address":"Plaz San Juan De Covas, 9",
    "sg:city":"Alcorcon",
    "sg:orig_category":"Tintorer\u00cdas, Limpieza En Seco",
    "sg:phone":"+34 916 10 23 59",
    "sg:postcode":"28925",
    "sg:province":"Madrid",
    "wof:name":"Gonzalez Raposo Salvador",
    "wof:placetype":"venue"
},
  "geometry": {"coordinates":[-3.8150169849,40.3545684814],"type":"Point"}
}