{
  "type": "Feature",
  "properties": {
    "addr:full":"Avda San Crispin, 104 Fuensalida Toledo 45510",
    "addr:housenumber":"104",
    "addr:postcode":"45510",
    "addr:street":"Avda San Crispin",
    "iso:country":"ES",
    "sg:address":"Avda San Crispin, 104",
    "sg:city":"Fuensalida",
    "sg:orig_category":"Muebles Y Accesorios Para Cocinas Y Cuartos De Ba\u00d1o (al Por Menor)",
    "sg:phone":"+34 925 78 43 70",
    "sg:postcode":"45510",
    "sg:province":"Toledo",
    "wof:name":"Rodriguez Bautista Fernando",
    "wof:placetype":"venue"
},
  "geometry": {"coordinates":[-4.1983242035,40.0570297241],"type":"Point"}
}