{
  "type": "Feature",
  "properties": {
    "iso:country":"ES",
    "sg:address":"Carr Liria, 20",
    "sg:city":"Moncada",
    "sg:orig_category":"Reciclaje Y Tratamiento De Desechos Varios",
    "sg:phone":"+34 961 39 25 90",
    "sg:postcode":"46113",
    "sg:province":"Valencia",
    "wof:name":"Recuperaciones Manuel Marti S A",
    "wof:placetype":"venue"
},
  "geometry": {"coordinates":[-0.4008809924,39.543586731],"type":"Point"}
}