{
  "type": "Feature",
  "properties": {
    "addr:full":"Calle de Ubeda, 24 Pozo Alcon Ja\u00e9n 23485",
    "addr:housenumber":"24",
    "addr:postcode":"23485",
    "addr:street":"Calle De Ubeda;Alcon Jae\u0301N",
    "iso:country":"ES",
    "sg:address":"Calle de Ubeda, 24",
    "sg:city":"Pozo Alcon",
    "sg:orig_category":"Molduras, Junquillos, Listones Y Molduras Perforadas",
    "sg:phone":"+34 953 73 87 07",
    "sg:postcode":"23485",
    "sg:province":"Ja\u00e9n",
    "wof:name":"Marin Castillejo Ramon",
    "wof:placetype":"venue"
},
  "geometry": {"coordinates":[-2.9365749359,37.7010192871],"type":"Point"}
}