{
  "type": "Feature",
  "properties": {
    "iso:country":"ES",
    "sg:address":"Calle de Nuestra Se\u00d1ora Del Aguila, 65",
    "sg:city":"Alcala Guadaira",
    "sg:orig_category":"Arquitectos",
    "sg:phone":"+34 955 68 76 75",
    "sg:postcode":"41500",
    "sg:province":"Sevilla",
    "wof:name":"Sanchez Ca\u00f1ete Bego\u00f1a",
    "wof:placetype":"venue"
},
  "geometry": {"coordinates":[-5.848637104,37.3343086243],"type":"Point"}
}