{
  "type": "Feature",
  "properties": {
    "addr:full":"Carrer de Narcisa Freixas, 25 Sabadell Barcelona 08202",
    "addr:housenumber":"25",
    "addr:postcode":"08202",
    "addr:street":"Carrer De Narcisa Freixas",
    "iso:country":"ES",
    "sg:address":"Carrer de Narcisa Freixas, 25",
    "sg:city":"Sabadell",
    "sg:orig_category":"Fabricaci\u00d3n De Telas Y Sedas",
    "sg:phone":"+34 937 27 30 00",
    "sg:postcode":"08202",
    "sg:province":"Barcelona",
    "wof:name":"Samtex S. A.",
    "wof:placetype":"venue"
},
  "geometry": {"coordinates":[2.1129829884,41.5491676331],"type":"Point"}
}