{
  "type": "Feature",
  "properties": {
    "iso:country":"ES",
    "sg:address":"Calle de Alcalde Sainz De Baranda, 62",
    "sg:city":"Madrid",
    "sg:orig_category":"Carnicer\u00cdas, Carnicer\u00cdas",
    "sg:phone":"+34 915 73 82 15",
    "sg:postcode":"28009",
    "sg:province":"Madrid",
    "wof:name":"Simon Lopez Andres",
    "wof:placetype":"venue"
},
  "geometry": {"coordinates":[-3.6698310375,40.4163513184],"type":"Point"}
}