{
  "type": "Feature",
  "properties": {
    "addr:full":"Nafarroa Kalea, 1 Zarautz Guip\u00f9zcoa 20800",
    "addr:housenumber":"1",
    "addr:postcode":"20800",
    "addr:street":"Nafarroa Kalea;Guipu\u0300Zcoa",
    "iso:country":"ES",
    "sg:address":"Nafarroa Kalea, 1",
    "sg:city":"Zarautz",
    "sg:orig_category":"M\u00c9dicos: Medicina General Orientada A La Homeopat\u00cda",
    "sg:phone":"+34 943 13 42 61",
    "sg:postcode":"20800",
    "sg:province":"Guip\u00f9zcoa",
    "wof:name":"Altuna Etxeberria I\u00f1igo",
    "wof:placetype":"venue"
},
  "geometry": {"coordinates":[-2.1765038967,43.2867546082],"type":"Point"}
}