{
  "type": "Feature",
  "properties": {
    "iso:country":"ES",
    "sg:address":"Cmno Arges, S/n",
    "sg:city":"Cobisa",
    "sg:orig_category":"Contenedores (mercanc\u00cdas)",
    "sg:phone":"+34 925 37 66 57",
    "sg:postcode":"45111",
    "sg:province":"Toledo",
    "wof:name":"Transportes Roberto S.l.",
    "wof:placetype":"venue"
},
  "geometry": {"coordinates":[-4.0295591354,39.8032188416],"type":"Point"}
}