{
  "type": "Feature",
  "properties": {
    "addr:full":"Plaz Doctor San Martin, 1 Cenicero La Rioja 26350",
    "addr:housenumber":"1",
    "addr:postcode":"26350",
    "addr:street":"San Martin;Rioja",
    "iso:country":"ES",
    "sg:address":"Plaz Doctor San Martin, 1",
    "sg:city":"Cenicero",
    "sg:orig_category":"Cajas De Ahorro",
    "sg:phone":"+34 941 45 47 62",
    "sg:postcode":"26350",
    "sg:province":"La Rioja",
    "sg:website":"www.",
    "wof:name":"Caja De Ahorros De La Rioja",
    "wof:placetype":"venue"
},
  "geometry": {"coordinates":[-2.6444430351,42.4821395874],"type":"Point"}
}