{
  "type": "Feature",
  "properties": {
    "addr:full":"Carr Nord, 9 Pu\u00e7ol Valencia 46530",
    "addr:housenumber":"9",
    "addr:postcode":"46530",
    "addr:street":"Carr Nord",
    "iso:country":"ES",
    "sg:address":"Carr Nord, 9",
    "sg:city":"Pu\u00e7ol",
    "sg:orig_category":"Peluquer\u00cdas, Peluquer\u00cda Mixta",
    "sg:phone":"+34 961 46 45 16",
    "sg:postcode":"46530",
    "sg:province":"Valencia",
    "wof:name":"Sielva Gomez Ana Maria",
    "wof:placetype":"venue"
},
  "geometry": {"coordinates":[-0.3008790016,39.6156044006],"type":"Point"}
}