{
  "type": "Feature",
  "properties": {
    "addr:full":"C/ Elda, 6 Elche Alicante 03203",
    "addr:housenumber":"6",
    "addr:postcode":"03203",
    "addr:street":"C / Elda",
    "iso:country":"ES",
    "sg:address":"C/ Elda, 6",
    "sg:city":"Elche",
    "sg:orig_category":"Confecci\u00d3n De Zapatos",
    "sg:phone":"+34 966 61 31 27",
    "sg:postcode":"03203",
    "sg:province":"Alicante",
    "wof:name":"Dyla's Shoes S.%.",
    "wof:placetype":"venue"
},
  "geometry": {"coordinates":[-0.6715959907,38.2707290649],"type":"Point"}
}