{
  "type": "Feature",
  "properties": {
    "addr:full":"Avgd Jaume I, 23 Olleria Valencia 46850",
    "addr:housenumber":"23",
    "addr:postcode":"46850",
    "addr:street":"Olleria",
    "iso:country":"ES",
    "sg:address":"Avgd Jaume I, 23",
    "sg:city":"Olleria",
    "sg:orig_category":"Hospitales",
    "sg:phone":"+34 962 20 01 27",
    "sg:postcode":"46850",
    "sg:province":"Valencia",
    "wof:name":"Hospital San Juan Bautista",
    "wof:placetype":"venue"
},
  "geometry": {"coordinates":[-0.5478360057,38.9096603394],"type":"Point"}
}