{
  "type": "Feature",
  "properties": {
    "addr:full":"Grup Union Bloques (la), 4 Vall D'uixo Castell\u00f3n 12600",
    "addr:housenumber":"4",
    "addr:postcode":"12600",
    "iso:country":"ES",
    "sg:address":"Grup Union Bloques (la), 4",
    "sg:city":"Vall D'uixo",
    "sg:orig_category":"Electricidad (montaje, Ensamblaje De Componentes)",
    "sg:phone":"+34 964 66 10 46",
    "sg:postcode":"12600",
    "sg:province":"Castell\u00f3n",
    "wof:name":"Maroto Almoguera Candido",
    "wof:placetype":"venue"
},
  "geometry": {"coordinates":[-0.0482099988,39.992477417],"type":"Point"}
}