{
  "type": "Feature",
  "properties": {
    "addr:full":"Calle de Alenza, 13 Madrid Madrid 28003",
    "addr:housenumber":"13",
    "addr:postcode":"madrid;28003",
    "addr:street":"Calle De Alenza",
    "iso:country":"ES",
    "sg:address":"Calle de Alenza, 13",
    "sg:city":"Madrid",
    "sg:orig_category":"Cooperativas Agr\u00cdcolas",
    "sg:phone":"+34 915 53 57 58",
    "sg:postcode":"28003",
    "sg:province":"Madrid",
    "wof:name":"A.s.d.h.a.c. Gestion Y Servicios S.l.",
    "wof:placetype":"venue"
},
  "geometry": {"coordinates":[-3.7005887032,40.4441146851],"type":"Point"}
}