{
  "type": "Feature",
  "properties": {
    "iso:country":"ES",
    "sg:address":"Ctra Rosario (del), 102",
    "sg:city":"Santa Cruz De Tenerife",
    "sg:orig_category":"Centros Empresariales",
    "sg:phone":"+34 922 64 33 52",
    "sg:postcode":"38009",
    "sg:province":"Santa Cruz De Tenerife",
    "wof:name":"Entidad De Conservacion Del Poligono Industrial San Isidro El Chorrillo",
    "wof:placetype":"venue"
},
  "geometry": {"coordinates":[-17.7755756378,28.6416091919],"type":"Point"}
}