{
  "type": "Feature",
  "properties": {
    "iso:country":"ES",
    "sg:address":"Calle de Maestro Arrieta, 44",
    "sg:city":"Castellon",
    "sg:orig_category":"Cajas Para Embalar",
    "sg:phone":"+34 964 25 70 61",
    "sg:postcode":"12006",
    "sg:province":"Castell\u00f3n",
    "wof:name":"Caja Rural San Isidro De Castellon Coop.de Credito V.",
    "wof:placetype":"venue"
},
  "geometry": {"coordinates":[-0.1292939931,40.0168533325],"type":"Point"}
}