{
  "type": "Feature",
  "properties": {
    "addr:full":"Calle de Santo Domingo, 11 Santiago Murcia 30800",
    "addr:housenumber":"11",
    "addr:postcode":"30800",
    "addr:street":"Calle De Santo Domingo",
    "iso:country":"ES",
    "sg:address":"Calle de Santo Domingo, 11",
    "sg:city":"Santiago",
    "sg:orig_category":"Cooperativas Agr\u00cdcolas",
    "sg:phone":"+34 968 47 70 18",
    "sg:postcode":"30800",
    "sg:province":"Murcia",
    "wof:name":"Agencia Estatal De Administracion Tributaria",
    "wof:placetype":"venue"
},
  "geometry": {"coordinates":[-0.8110970259,37.7981262207],"type":"Point"}
}