{
  "type": "Feature",
  "properties": {
    "addr:full":"Carrer de Ramon Turro, 336 Barcelona Barcelona 08019",
    "addr:housenumber":"336",
    "addr:postcode":"08019",
    "addr:street":"Carrer De Ramon Turro",
    "iso:country":"ES",
    "sg:address":"Carrer de Ramon Turro, 336",
    "sg:city":"Barcelona",
    "sg:orig_category":"Inform\u00c1tica: Soportes De Informaci\u00d3n, Suministros & Accesorios",
    "sg:phone":"+34 932 66 52 54",
    "sg:postcode":"08019",
    "sg:province":"Barcelona",
    "wof:name":"Blanco Montero Ana Isabel",
    "wof:placetype":"venue"
},
  "geometry": {"coordinates":[2.2112770081,41.4060516357],"type":"Point"}
}