{
  "type": "Feature",
  "properties": {
    "iso:country":"ES",
    "sg:address":"Avgd Barcelona, 21",
    "sg:city":"Lleida",
    "sg:orig_category":"Promotores Constructores",
    "sg:phone":"+34 973 21 32 11",
    "sg:postcode":"25001",
    "sg:province":"Lleida",
    "wof:name":"Trebor 2010 S.l.",
    "wof:placetype":"venue"
},
  "geometry": {"coordinates":[0.6248319745,41.6055259705],"type":"Point"}
}