{
  "type": "Feature",
  "properties": {
    "addr:full":"Pl Clave, 13 Terrassa Barcelona 08...",
    "addr:housenumber":"13",
    "addr:street":"Pl Clave",
    "iso:country":"ES",
    "sg:address":"Pl Clave, 13",
    "sg:city":"Terrassa",
    "sg:orig_category":"Asesor\u00cda Fiscal Y Jur\u00cddica",
    "sg:phone":"+34 937 33 74 00",
    "sg:postcode":"08...",
    "sg:province":"Barcelona",
    "wof:name":"Oficina Administrativa S.a.",
    "wof:placetype":"venue"
},
  "geometry": {"coordinates":[2.0080239773,41.5606918335],"type":"Point"}
}