{
  "type": "Feature",
  "properties": {
    "iso:country":"ES",
    "sg:address":"Calle de Juan De La Cierva, 29",
    "sg:city":"Merida",
    "sg:orig_category":"Promotores Constructores",
    "sg:phone":"+34 924 37 12 57",
    "sg:postcode":"06800",
    "sg:province":"Badajoz",
    "sg:website":"www.cyopsa.es",
    "wof:name":"Cyopsa Sisocia S.a.",
    "wof:placetype":"venue"
},
  "geometry": {"coordinates":[-6.3333659172,38.9039726257],"type":"Point"}
}