{
  "type": "Feature",
  "properties": {
    "iso:country":"ES",
    "sg:address":"Calle de Florencia, 14",
    "sg:city":"Torrejon Ardoz",
    "sg:orig_category":"Molduras, Junquillos, Listones Y Molduras Perforadas",
    "sg:phone":"+34 916 76 39 50",
    "sg:postcode":"28850",
    "sg:province":"Madrid",
    "wof:name":"Jimenez Jimenez M.carmen",
    "wof:placetype":"venue"
},
  "geometry": {"coordinates":[-3.4675009251,40.4647293091],"type":"Point"}
}