{
  "type": "Feature",
  "properties": {
    "addr:full":"Plaz Virgen Del Pilar, 24 Vilamarxant Valencia 46191",
    "addr:housenumber":"24",
    "addr:postcode":"46191",
    "addr:street":"Plaz Virgen Del Pilar",
    "iso:country":"ES",
    "sg:address":"Plaz Virgen Del Pilar, 24",
    "sg:city":"Vilamarxant",
    "sg:orig_category":"Promotores Constructores",
    "sg:phone":"+34 962 71 22 63",
    "sg:postcode":"46191",
    "sg:province":"Valencia",
    "wof:name":"Sanchis Caurin S.l.",
    "wof:placetype":"venue"
},
  "geometry": {"coordinates":[-0.6269490123,39.5700187683],"type":"Point"}
}