{
  "type": "Feature",
  "properties": {
    "iso:country":"ES",
    "sg:address":"Carrer de Torrent De L'olla, 171",
    "sg:city":"Barcelona",
    "sg:orig_category":"Molduras, Junquillos, Listones Y Molduras Perforadas",
    "sg:phone":"+34 934 15 51 68",
    "sg:postcode":"08012",
    "sg:province":"Barcelona",
    "wof:name":"Perez Anglada Jorge",
    "wof:placetype":"venue"
},
  "geometry": {"coordinates":[2.1540939808,41.4049224854],"type":"Point"}
}