{
  "type": "Feature",
  "properties": {
    "addr:full":"Avda Barcelona (de), 3 Cordoba C\u00f3rdoba 14010",
    "addr:housenumber":"3",
    "addr:postcode":"14010",
    "addr:street":"Avda Barcelona De;Co\u0301Rdoba",
    "iso:country":"ES",
    "sg:address":"Avda Barcelona (de), 3",
    "sg:city":"Cordoba",
    "sg:orig_category":"Tintes (fabricaci\u00d3n, Al Por Mayor)",
    "sg:phone":"+34 957 25 91 99",
    "sg:postcode":"14010",
    "sg:province":"C\u00f3rdoba",
    "wof:name":"Verdejo Granados Jose Luis",
    "wof:placetype":"venue"
},
  "geometry": {"coordinates":[-4.7643737793,37.8900871277],"type":"Point"}
}