{
  "type": "Feature",
  "properties": {
    "iso:country":"ES",
    "sg:address":"Errosario Kalea, 30",
    "sg:city":"Elgoibar",
    "sg:classifiers":[
        {
            "category":"Personal",
            "subcategory":"Barber",
            "type":"Services"
        }
    ],
    "sg:phone":"+34 943 74 14 92",
    "sg:postcode":"20870",
    "sg:province":"Guip\u00f9zcoa",
    "sg:tags":[
        "caballeros",
        "de",
        "peluqueros"
    ],
    "wof:name":"Jose Antonio Gonzalez Gimenez",
    "wof:placetype":"venue"
},
  "geometry": {"coordinates":[-2.4167859554,43.2149772644],"type":"Point"}
}