{
  "type": "Feature",
  "properties": {
    "iso:country":"ES",
    "sg:address":"Calle de Domingo De Orueta, 13",
    "sg:city":"Malaga",
    "sg:orig_category":"Negocio De Materiales De Construcci\u00d3n",
    "sg:phone":"+34 952 32 63 41",
    "sg:postcode":"29002",
    "sg:province":"M\u00e1laga",
    "wof:name":"Rene Boxstal Gerard",
    "wof:placetype":"venue"
},
  "geometry": {"coordinates":[-4.4381818771,36.706653595],"type":"Point"}
}