{
  "type": "Feature",
  "properties": {
    "addr:full":"Calle de Antonio Concha, 106 Navalmoral Mata C\u00e1ceres 10300",
    "addr:housenumber":"106",
    "addr:postcode":"10300",
    "addr:street":"Calle De Antonio Concha;Ca\u0301Ceres",
    "iso:country":"ES",
    "sg:address":"Calle de Antonio Concha, 106",
    "sg:city":"Navalmoral Mata",
    "sg:orig_category":"Material Y Herramientas Agr\u00cdcolas",
    "sg:phone":"+34 927 53 53 31",
    "sg:postcode":"10300",
    "sg:province":"C\u00e1ceres",
    "wof:name":"Maquinaria Agricola Fraile S.l.",
    "wof:placetype":"venue"
},
  "geometry": {"coordinates":[-5.5345048904,39.8902320862],"type":"Point"}
}