{
  "type": "Feature",
  "properties": {
    "iso:country":"ES",
    "sg:address":"Calle de Doctor Fleming, 15",
    "sg:city":"Bailen",
    "sg:orig_category":"Asesor\u00cda Fiscal Y Jur\u00cddica",
    "sg:phone":"+34 953 67 40 13",
    "sg:postcode":"23710",
    "sg:province":"Ja\u00e9n",
    "wof:name":"Merino Torres Marco Antonio",
    "wof:placetype":"venue"
},
  "geometry": {"coordinates":[-3.7736496925,38.097114563],"type":"Point"}
}