{
  "type": "Feature",
  "properties": {
    "addr:full":"Calle de Lopez De Hoyos, 383 Madrid Madrid 28043",
    "addr:housenumber":"383",
    "addr:postcode":"28043",
    "addr:street":"Calle De Lopez De Hoyos",
    "iso:country":"ES",
    "sg:address":"Calle de Lopez De Hoyos, 383",
    "sg:city":"Madrid",
    "sg:orig_category":"Muebles Y Accesorios Para Cocinas Y Cuartos De Ba\u00d1o (al Por Menor)",
    "sg:phone":"+34 917 63 09 62",
    "sg:postcode":"28043",
    "sg:province":"Madrid",
    "wof:name":"Garcia Due\u00f1as Francisco",
    "wof:placetype":"venue"
},
  "geometry": {"coordinates":[-3.65020895,40.471408844],"type":"Point"}
}