{
  "type": "Feature",
  "properties": {
    "iso:country":"ES",
    "sg:address":"Carrer de Cop, 19",
    "sg:city":"Denia",
    "sg:orig_category":"M\u00c9dicos: Estomatolog\u00cda",
    "sg:phone":"+34 966 43 03 77",
    "sg:postcode":"03700",
    "sg:province":"Alicante",
    "wof:name":"Esteve Vives Juan Carlos",
    "wof:placetype":"venue"
},
  "geometry": {"coordinates":[0.1068259999,38.8401107788],"type":"Point"}
}