{
  "type": "Feature",
  "properties": {
    "iso:country":"ES",
    "sg:address":"Trva Marques Alcedo, 7",
    "sg:city":"Vigo",
    "sg:orig_category":"Electrodom\u00c9sticos (al Por Menor)",
    "sg:phone":"+34 986 41 17 29",
    "sg:postcode":"36203",
    "sg:province":"Pontevedra",
    "wof:name":"Diaz Y Mandado S.l.",
    "wof:placetype":"venue"
},
  "geometry": {"coordinates":[-8.7224836349,42.2317733765],"type":"Point"}
}