{
  "type": "Feature",
  "properties": {
    "iso:country":"ES",
    "sg:address":"Calle de Uruguay, S/n",
    "sg:city":"Alcantarilla",
    "sg:orig_category":"Material Y Suministros Para Fotocopiadoras, Reprograf\u00cda",
    "sg:phone":"+34 968 89 06 72",
    "sg:postcode":"30820",
    "sg:province":"Murcia",
    "wof:name":"Tortosa Sanchez Jose",
    "wof:placetype":"venue"
},
  "geometry": {"coordinates":[-1.1980240345,37.9597854614],"type":"Point"}
}