{
  "type": "Feature",
  "properties": {
    "addr:full":"Carrer de Eusebi Guell, 101 S. Boi Llobregat Barcelona 08830",
    "addr:housenumber":"101",
    "addr:postcode":"08830",
    "addr:street":"Carrer De Eusebi Guell;S.",
    "iso:country":"ES",
    "sg:address":"Carrer de Eusebi Guell, 101",
    "sg:city":"S. Boi Llobregat",
    "sg:orig_category":"Ropa Para Ni\u00d1os (al Por Menor)",
    "sg:phone":"+34 936 61 53 87",
    "sg:postcode":"08830",
    "sg:province":"Barcelona",
    "wof:name":"Vivaracho Leon Juana",
    "wof:placetype":"venue"
},
  "geometry": {"coordinates":[2.0271565914,41.3466720581],"type":"Point"}
}