{
  "type": "Feature",
  "properties": {
    "addr:full":"Calle de General Valcarcel, 3 Mula Murcia 30170",
    "addr:housenumber":"3",
    "addr:postcode":"30170",
    "addr:street":"Calle De General Valcarcel",
    "iso:country":"ES",
    "sg:address":"Calle de General Valcarcel, 3",
    "sg:city":"Mula",
    "sg:orig_category":"Cajas Para Embalar",
    "sg:phone":"+34 968 63 70 31",
    "sg:postcode":"30170",
    "sg:province":"Murcia",
    "sg:website":"www.cajamar.es",
    "wof:name":"Cajamar",
    "wof:placetype":"venue"
},
  "geometry": {"coordinates":[-1.4936590195,38.0395393372],"type":"Point"}
}