{
  "type": "Feature",
  "properties": {
    "iso:country":"ES",
    "sg:address":"Calle de Ramon Y Cajal, 4",
    "sg:city":"Valle Trapaga",
    "sg:orig_category":"Alimentaci\u00d3n General (al Por Menor)",
    "sg:phone":"+34 944 92 10 88",
    "sg:postcode":"48510",
    "sg:province":"Vizcaya",
    "wof:name":"Bueno Carranza Pedro",
    "wof:placetype":"venue"
},
  "geometry": {"coordinates":[-3.0338521004,43.3021736145],"type":"Point"}
}