{
  "type": "Feature",
  "properties": {
    "addr:full":"Pase San Juan Bosco (de), 1 Arevalo \u00c1vila 05200",
    "addr:postcode":"05200",
    "iso:country":"ES",
    "sg:address":"Pase San Juan Bosco (de), 1",
    "sg:city":"Arevalo",
    "sg:orig_category":"Internados & Ense\u00d1anza Privada",
    "sg:phone":"+34 920 30 00 87",
    "sg:postcode":"05200",
    "sg:province":"\u00c1vila",
    "wof:name":"Salesianos San Juan Bosco",
    "wof:placetype":"venue"
},
  "geometry": {"coordinates":[-4.7201008797,41.0528526306],"type":"Point"}
}