{
  "type": "Feature",
  "properties": {
    "iso:country":"ES",
    "sg:address":"Pase Alameda (de La), 24",
    "sg:city":"Alcala Henares",
    "sg:orig_category":"Caf\u00c9s, Bares, Cervecer\u00cdas",
    "sg:phone":"+34 918 80 43 97",
    "sg:postcode":"28804",
    "sg:province":"Madrid",
    "wof:name":"Cafeteria Mayca S.c.",
    "wof:placetype":"venue"
},
  "geometry": {"coordinates":[-3.3549950123,40.4826011658],"type":"Point"}
}