{
  "type": "Feature",
  "properties": {
    "addr:full":"Calle de Pico Del Naranco, 8 Salamanca Salamanca 37008",
    "addr:housenumber":"8",
    "addr:postcode":"37008",
    "addr:street":"Calle De Pico Del Naranco",
    "iso:country":"ES",
    "sg:address":"Calle de Pico Del Naranco, 8",
    "sg:city":"Salamanca",
    "sg:orig_category":"Cerrajer\u00cda, Ferrallista",
    "sg:phone":"+34 923 19 21 65",
    "sg:postcode":"37008",
    "sg:province":"Salamanca",
    "wof:name":"Sanchez Sanchez Jesus",
    "wof:placetype":"venue"
},
  "geometry": {"coordinates":[-5.672533989,40.9516563416],"type":"Point"}
}