{
  "type": "Feature",
  "properties": {
    "addr:full":"Calle de Cruces, 49 Valdepe\u00f1as Ciudad Real 13300",
    "addr:housenumber":"49",
    "addr:postcode":"13300",
    "addr:street":"Calle De Cruces",
    "iso:country":"ES",
    "sg:address":"Calle de Cruces, 49",
    "sg:city":"Valdepe\u00f1as",
    "sg:orig_category":"Bazares, Art\u00cdculos De Limpieza Y De Cocina (al Por Menor)",
    "sg:phone":"+34 926 32 10 08",
    "sg:postcode":"13300",
    "sg:province":"Ciudad Real",
    "wof:name":"Consuegra Blanco Jose Luis",
    "wof:placetype":"venue"
},
  "geometry": {"coordinates":[-3.378524065,38.7632484436],"type":"Point"}
}