{
  "type": "Feature",
  "properties": {
    "addr:full":"Carrer de Sol, 1 Palleja Barcelona 08780",
    "addr:housenumber":"1",
    "addr:postcode":"08780",
    "addr:street":"Carrer De Sol",
    "iso:country":"ES",
    "sg:address":"Carrer de Sol, 1",
    "sg:city":"Palleja",
    "sg:orig_category":"Administraciones Regionales, Departamentales Y Locales",
    "sg:phone":"+34 936 63 00 00",
    "sg:postcode":"08780",
    "sg:province":"Barcelona",
    "sg:website":"www.palleja.net",
    "wof:name":"Ajuntament De Palleja",
    "wof:placetype":"venue"
},
  "geometry": {"coordinates":[1.9961637259,41.4228363037],"type":"Point"}
}