{
  "type": "Feature",
  "properties": {
    "addr:full":"Rua Reconco (o), 17 Maceda Ourense 32700",
    "addr:housenumber":"17",
    "addr:postcode":"32700",
    "addr:street":"Rua Reconco O",
    "iso:country":"ES",
    "sg:address":"Rua Reconco (o), 17",
    "sg:city":"Maceda",
    "sg:orig_category":"Asesor\u00cda Sobre Comunicaci\u00d3n De Empresas",
    "sg:phone":"+34 988 46 34 49",
    "sg:postcode":"32700",
    "sg:province":"Ourense",
    "wof:name":"Xiama Maceda S.l.",
    "wof:placetype":"venue"
},
  "geometry": {"coordinates":[-7.6515350342,42.2662963867],"type":"Point"}
}