{
  "type": "Feature",
  "properties": {
    "addr:full":"Calle de Virgen Del Casta\u00d1ar, 1 Madrid Madrid 28027",
    "addr:housenumber":"1",
    "addr:postcode":"28027",
    "addr:street":"Calle De Virgen Del Castan\u0303Ar",
    "iso:country":"ES",
    "sg:address":"Calle de Virgen Del Casta\u00d1ar, 1",
    "sg:city":"Madrid",
    "sg:orig_category":"Afiladoras, Pulidoras Y Bru\u00d1idoras",
    "sg:phone":"+34 914 04 75 48",
    "sg:postcode":"28027",
    "sg:province":"Madrid",
    "wof:name":"Bermejo Ballesteros Pedro Luis",
    "wof:placetype":"venue"
},
  "geometry": {"coordinates":[-3.6535899639,40.437210083],"type":"Point"}
}