{
  "type": "Feature",
  "properties": {
    "addr:full":"Calle de Granada, 1 Alameda M\u00e1laga 29530",
    "addr:housenumber":"1",
    "addr:postcode":"29530",
    "addr:street":"Calle De Granada;Alameda Ma\u0301Laga",
    "iso:country":"ES",
    "sg:address":"Calle de Granada, 1",
    "sg:city":"Alameda",
    "sg:classifiers":[
        {
            "category":"Autos & Motor Vehicles",
            "subcategory":"Automobile Sales",
            "type":"Retail Goods"
        }
    ],
    "sg:phone":"+34 952 71 03 04",
    "sg:postcode":"29530",
    "sg:province":"M\u00e1laga",
    "wof:name":"Soriano Garcia Juan",
    "wof:placetype":"venue"
},
  "geometry": {"coordinates":[-4.6576209068,37.2077903748],"type":"Point"}
}