{
  "type": "Feature",
  "properties": {
    "addr:full":"Calle de Alba\u00d1iles, S/n Cabezas S. Juan Sevilla 41730",
    "addr:housenumber":"s",
    "addr:postcode":"41730",
    "addr:street":"Calle De Alban\u0303Iles;/ N Cabezas S. Juan Sevilla",
    "iso:country":"ES",
    "sg:address":"Calle de Alba\u00d1iles, S/n",
    "sg:city":"Cabezas S. Juan",
    "sg:orig_category":"Ense\u00d1anza, Formaci\u00d3n Profesional: Aprendizaje",
    "sg:phone":"+34 955 87 38 21",
    "sg:postcode":"41730",
    "sg:province":"Sevilla",
    "wof:name":"Organismo Provincial De Asistencia Economica Y Fiscal",
    "wof:placetype":"venue"
},
  "geometry": {"coordinates":[-5.9394993782,36.983379364],"type":"Point"}
}