{
  "type": "Feature",
  "properties": {
    "iso:country":"ES",
    "sg:address":"Av Francesc Marimon, 124",
    "sg:city":"Esparreguera",
    "sg:orig_category":"T\u00c9cnicos Veterinarios",
    "sg:phone":"+34 937 77 40 53",
    "sg:postcode":"08292",
    "sg:province":"Barcelona",
    "wof:name":"Vila Verdes Daniel",
    "wof:placetype":"venue"
},
  "geometry": {"coordinates":[1.8712719679,41.5343856812],"type":"Point"}
}