{
  "type": "Feature",
  "properties": {
    "iso:country":"ES",
    "sg:address":"Calle de Obispo Cobos, 37",
    "sg:city":"Ubeda",
    "sg:orig_category":"Ropa Para Beb\u00c9s Y Ni\u00d1os (confecci\u00d3n, Al Por Mayor)",
    "sg:phone":"+34 953 75 23 66",
    "sg:postcode":"23400",
    "sg:province":"Ja\u00e9n",
    "wof:name":"Maeso Martinez Maria Dolores",
    "wof:placetype":"venue"
},
  "geometry": {"coordinates":[-3.3760390282,38.011390686],"type":"Point"}
}