{
  "type": "Feature",
  "properties": {
    "iso:country":"ES",
    "sg:address":"Calle de Manuel Badia, 22",
    "sg:city":"Madrid",
    "sg:orig_category":"Comercio De Piezas De Recambio Y De Accesorios De Veh\u00cdculos, Veh\u00cdculos Industriales",
    "sg:phone":"+34 917 78 04 12",
    "sg:postcode":"28018",
    "sg:province":"Madrid",
    "wof:name":"Accesorios Palomeras S.l.",
    "wof:placetype":"venue"
},
  "geometry": {"coordinates":[-3.6513872147,40.3856124878],"type":"Point"}
}