{
  "type": "Feature",
  "properties": {
    "iso:country":"ES",
    "sg:address":"Ctra. B-motril, Km. 0370,0",
    "sg:city":"La Yuca",
    "sg:orig_category":"Charcuter\u00cdas (al Por Mayor)",
    "sg:phone":"+34 953 32 20 68",
    "sg:postcode":"23001",
    "sg:province":"Ja\u00e9n",
    "wof:name":"Juber Y Dos Mas S.l",
    "wof:placetype":"venue"
},
  "geometry": {"coordinates":[-3.7906799316,37.7650909424],"type":"Point"}
}