{
  "type": "Feature",
  "properties": {
    "iso:country":"ES",
    "sg:address":"Pl Sant Jaume, 11",
    "sg:city":"Manacor",
    "sg:orig_category":"Caf\u00c9s, Bares, Cervecer\u00cdas",
    "sg:phone":"+34 971 84 51 37",
    "sg:postcode":"07500",
    "sg:province":"Islas Baleares",
    "wof:name":"Afif  Said",
    "wof:placetype":"venue"
},
  "geometry": {"coordinates":[3.205878973,39.5714912415],"type":"Point"}
}