{
  "type": "Feature",
  "properties": {
    "addr:full":"Calle de Alpotreques, 4 Badajoz Badajoz 06003",
    "addr:housenumber":"4",
    "addr:postcode":"06003",
    "addr:street":"Calle De Alpotreques",
    "iso:country":"ES",
    "sg:address":"Calle de Alpotreques, 4",
    "sg:city":"Badajoz",
    "sg:orig_category":"Molduras, Junquillos, Listones Y Molduras Perforadas",
    "sg:phone":"+34 924 26 04 73",
    "sg:postcode":"06003",
    "sg:province":"Badajoz",
    "wof:name":"Alcantara Cuello Jose Diosdado",
    "wof:placetype":"venue"
},
  "geometry": {"coordinates":[-6.9696907997,38.8701858521],"type":"Point"}
}