{
  "type": "Feature",
  "properties": {
    "iso:country":"ES",
    "sg:address":"Calle de Mayor, 14",
    "sg:city":"Mislata",
    "sg:orig_category":"\u00d3ptica: Instrumentos (fabricaci\u00d3n)",
    "sg:phone":"+34 963 83 68 65",
    "sg:postcode":"46920",
    "sg:province":"Valencia",
    "wof:name":"Geropcle S.l",
    "wof:placetype":"venue"
},
  "geometry": {"coordinates":[-0.4160430133,39.4745864868],"type":"Point"}
}