{
  "type": "Feature",
  "properties": {
    "addr:full":"Calle de Sanchez Barcaiztegui, 35 Madrid Madrid 28007",
    "addr:housenumber":"35",
    "addr:postcode":"madrid;28007",
    "addr:street":"Calle De Sanchez Barcaiztegui",
    "iso:country":"ES",
    "sg:address":"Calle de Sanchez Barcaiztegui, 35",
    "sg:city":"Madrid",
    "sg:orig_category":"Arquitectos",
    "sg:phone":"+34 915 51 46 10",
    "sg:postcode":"28007",
    "sg:province":"Madrid",
    "wof:name":"Garcia Sanchez Isidoro",
    "wof:placetype":"venue"
},
  "geometry": {"coordinates":[-3.673167944,40.4060287476],"type":"Point"}
}