{
  "type": "Feature",
  "properties": {
    "addr:full":"Rua Cami\u00d1o Real, 99 Burela Lugo 27880",
    "addr:housenumber":"99",
    "addr:postcode":"27880",
    "addr:street":"Rua Camin\u0303O Real",
    "iso:country":"ES",
    "sg:address":"Rua Cami\u00d1o Real, 99",
    "sg:city":"Burela",
    "sg:orig_category":"Promotores Constructores",
    "sg:phone":"+34 982 58 61 73",
    "sg:postcode":"27880",
    "sg:province":"Lugo",
    "sg:website":"www.ocatalan.com",
    "wof:name":"Goldkey S.l.",
    "wof:placetype":"venue"
},
  "geometry": {"coordinates":[-7.3604969978,43.658657074],"type":"Point"}
}