{
  "type": "Feature",
  "properties": {
    "iso:country":"ES",
    "sg:address":"Calle de Jardin, S/n",
    "sg:city":"Guadix",
    "sg:orig_category":"Inform\u00c1tica, Ofim\u00c1tica (estudios, Asesor\u00cda, Ingenier\u00cda, Formaci\u00d3n)",
    "sg:phone":"+34 958 66 00 58",
    "sg:postcode":"18500",
    "sg:province":"Granada",
    "sg:website":"www.pccoste.com",
    "wof:name":"Informatica Guillen Global Sl",
    "wof:placetype":"venue"
},
  "geometry": {"coordinates":[-3.1330690384,37.3016014099],"type":"Point"}
}