{
  "type": "Feature",
  "properties": {
    "addr:full":"Calle de Jose Cueto, 4 Aviles Asturias 33401",
    "addr:housenumber":"4",
    "addr:postcode":"33401",
    "addr:street":"Calle De Jose Cueto",
    "iso:country":"ES",
    "sg:address":"Calle de Jose Cueto, 4",
    "sg:city":"Aviles",
    "sg:orig_category":"Asesor\u00cda Fiscal Y Jur\u00cddica",
    "sg:phone":"+34 984 83 21 97",
    "sg:postcode":"33401",
    "sg:province":"Asturias",
    "wof:name":"Romero S.c.",
    "wof:placetype":"venue"
},
  "geometry": {"coordinates":[-5.9253029823,43.5581016541],"type":"Point"}
}