{
  "type": "Feature",
  "properties": {
    "iso:country":"ES",
    "sg:address":"Estda. Xeral(o Eixo), S/n",
    "sg:city":"Fazouro",
    "sg:orig_category":"Empresas De Carpinter\u00cda Met\u00c1lica",
    "sg:phone":"+34 982 13 66 26",
    "sg:postcode":"27789",
    "sg:province":"Lugo",
    "wof:name":"Construcciones Metalicas Fazouro S.l.",
    "wof:placetype":"venue"
},
  "geometry": {"coordinates":[-7.3789391518,43.5581245422],"type":"Point"}
}