{
  "type": "Feature",
  "properties": {
    "iso:country":"ES",
    "sg:address":"Calle de Floranes, 23",
    "sg:city":"Santander",
    "sg:orig_category":"Muebles Y Accesorios Para Cocinas Y Cuartos De Ba\u00d1o (al Por Menor)",
    "sg:phone":"+34 942 37 65 12",
    "sg:postcode":"39010",
    "sg:province":"Cantabria",
    "sg:website":"www.geocities.com/ceamobiliario",
    "wof:name":"Cea Mobiliario S.l.",
    "wof:placetype":"venue"
},
  "geometry": {"coordinates":[-3.8197131157,43.4610748291],"type":"Point"}
}