{
  "type": "Feature",
  "properties": {
    "iso:country":"ES",
    "sg:address":"Carr Estepar, De S', 1",
    "sg:city":"Cala Millor",
    "sg:orig_category":"Aguas (distribuci\u00d3n, Servicios)",
    "sg:phone":"+34 971 58 68 99",
    "sg:postcode":"07560",
    "sg:province":"Islas Baleares",
    "wof:name":"Aguas De Son Sard S.a.",
    "wof:placetype":"venue"
},
  "geometry": {"coordinates":[3.3858470917,39.6062545776],"type":"Point"}
}