{
  "type": "Feature",
  "properties": {
    "addr:full":"Carr Salmeron, 8 Lleida Lleida 25004",
    "addr:housenumber":"8",
    "addr:postcode":"25004",
    "addr:street":"Carr Salmeron",
    "iso:country":"ES",
    "sg:address":"Carr Salmeron, 8",
    "sg:city":"Lleida",
    "sg:orig_category":"Herboristas (al Por Menor)",
    "sg:phone":"+34 973 23 32 24",
    "sg:postcode":"25004",
    "sg:province":"Lleida",
    "wof:name":"Cayuela Jordan Maria Carmen",
    "wof:placetype":"venue"
},
  "geometry": {"coordinates":[0.6271449924,41.6208572388],"type":"Point"}
}