{
  "type": "Feature",
  "properties": {
    "iso:country":"ES",
    "sg:address":"Katea Kalea, 5",
    "sg:city":"Beasain",
    "sg:orig_category":"Mec\u00c1nico Del Autom\u00d3vil",
    "sg:phone":"+34 943 88 92 50",
    "sg:postcode":"20200",
    "sg:province":"Guip\u00f9zcoa",
    "wof:name":"San Cristobal C.b.",
    "wof:placetype":"venue"
},
  "geometry": {"coordinates":[-2.2163898945,43.0428314209],"type":"Point"}
}