{
  "type": "Feature",
  "properties": {
    "addr:full":"Ctra Vieja, 92 Bajos Y Tagoro Santa Cruz De Tenerife 38380",
    "addr:housenumber":"92",
    "addr:postcode":"38380",
    "addr:street":"Ctra Vieja",
    "iso:country":"ES",
    "sg:address":"Ctra Vieja, 92",
    "sg:city":"Bajos Y Tagoro",
    "sg:orig_category":"Mec\u00c1nico Del Autom\u00d3vil",
    "sg:phone":"+34 922 58 04 77",
    "sg:postcode":"38380",
    "sg:province":"Santa Cruz De Tenerife",
    "wof:name":"Yanes Cruz Jose Guillermo",
    "wof:placetype":"venue"
},
  "geometry": {"coordinates":[-16.4805450439,28.4302616119],"type":"Point"}
}