{
  "type": "Feature",
  "properties": {
    "iso:country":"ES",
    "sg:address":"Carrer de Pere Iv, 176",
    "sg:city":"Barcelona",
    "sg:orig_category":"Perfumer\u00cda (al Por Menor)",
    "sg:phone":"+34 933 09 36 61",
    "sg:postcode":"08005",
    "sg:province":"Barcelona",
    "wof:name":"Navarro Perales Jose Maria",
    "wof:placetype":"venue"
},
  "geometry": {"coordinates":[2.1976339817,41.4024925232],"type":"Point"}
}