{
  "type": "Feature",
  "properties": {
    "iso:country":"ES",
    "sg:address":"Carrer de Anselm Clave, 13",
    "sg:city":"Lloret Mar",
    "sg:orig_category":"Pod\u00d3logos: Pedicuros",
    "sg:phone":"+34 972 37 27 91",
    "sg:postcode":"17310",
    "sg:province":"Girona",
    "wof:name":"Saavedra Martinez Rosalia",
    "wof:placetype":"venue"
},
  "geometry": {"coordinates":[2.8491020203,41.7032203674],"type":"Point"}
}