{
  "type": "Feature",
  "properties": {
    "addr:full":"Carrer de Balmes, 57 Barcelona Barcelona 08007",
    "addr:housenumber":"57",
    "addr:postcode":"08007",
    "addr:street":"Carrer De Balmes",
    "iso:country":"ES",
    "sg:address":"Carrer de Balmes, 57",
    "sg:city":"Barcelona",
    "sg:orig_category":"M\u00c9dicos: Ginecolog\u00cda Y Obstetricia",
    "sg:phone":"+34 934 53 83 73",
    "sg:postcode":"08007",
    "sg:province":"Barcelona",
    "wof:name":"Buxo Massaguer Javier Maria",
    "wof:placetype":"venue"
},
  "geometry": {"coordinates":[2.1620059013,41.389591217],"type":"Point"}
}