{
  "type": "Feature",
  "properties": {
    "addr:full":"Calle de Algorta, 10 Medina Pomar Burgos 09500",
    "addr:housenumber":"10",
    "addr:postcode":"09500",
    "addr:street":"Calle De Algorta",
    "iso:country":"ES",
    "sg:address":"Calle de Algorta, 10",
    "sg:city":"Medina Pomar",
    "sg:orig_category":"Producci\u00d3n, Distribuci\u00d3n De Electricidad",
    "sg:phone":"+34 947 19 15 67",
    "sg:postcode":"09500",
    "sg:province":"Burgos",
    "sg:website":"www.aduriz.com",
    "wof:name":"Electra Aduriz S.a.",
    "wof:placetype":"venue"
},
  "geometry": {"coordinates":[-3.4875178337,42.9330368042],"type":"Point"}
}