{
  "type": "Feature",
  "properties": {
    "addr:full":"Calle de Carta Puebla, S/n Urbanizacion La Fresneda Asturias 33429",
    "addr:postcode":"33429",
    "addr:street":"Calle De Carta Puebla S / N Urbanizacion La;Asturias",
    "iso:country":"ES",
    "sg:address":"Calle de Carta Puebla, S/n",
    "sg:city":"Urbanizacion La Fresneda",
    "sg:orig_category":"Iglesia Cat\u00d3lica",
    "sg:phone":"+34 985 26 44 24",
    "sg:postcode":"33429",
    "sg:province":"Asturias",
    "wof:name":"Diocesis De Oviedo",
    "wof:placetype":"venue"
},
  "geometry": {"coordinates":[-5.7704091072,43.3952407837],"type":"Point"}
}