{
  "type": "Feature",
  "properties": {
    "iso:country":"ES",
    "sg:address":"Avda Juan Carlos I, 81",
    "sg:city":"Peal Becerro",
    "sg:orig_category":"Negocio De Materiales De Construcci\u00d3n",
    "sg:phone":"+34 953 73 02 80",
    "sg:postcode":"23460",
    "sg:province":"Ja\u00e9n",
    "wof:name":"Suministros Torres Martinez S.l",
    "wof:placetype":"venue"
},
  "geometry": {"coordinates":[-3.1209990978,37.9165916443],"type":"Point"}
}