{
  "type": "Feature",
  "properties": {
    "addr:full":"Calle de Real, S/n Villabrazaro Zamora 49770",
    "addr:housenumber":"s / n",
    "addr:postcode":"49770",
    "addr:street":"Calle De Real",
    "iso:country":"ES",
    "sg:address":"Calle de Real, S/n",
    "sg:city":"Villabrazaro",
    "sg:orig_category":"Transportes Por Carretera: Lotes Completos, Mercanc\u00cdas Diversas",
    "sg:phone":"+34 980 64 25 70",
    "sg:postcode":"49770",
    "sg:province":"Zamora",
    "wof:name":"Mayo Geras Maria Del Amparo",
    "wof:placetype":"venue"
},
  "geometry": {"coordinates":[-5.729557991,42.0539894104],"type":"Point"}
}