{
  "type": "Feature",
  "properties": {
    "addr:full":"Calle de Ibaiondo, 9 Madrid Madrid 28023",
    "addr:housenumber":"9",
    "addr:postcode":"madrid;28023",
    "addr:street":"Calle De Ibaiondo",
    "iso:country":"ES",
    "sg:address":"Calle de Ibaiondo, 9",
    "sg:city":"Madrid",
    "sg:orig_category":"Inmobiliaria (agencias)",
    "sg:phone":"+34 913 07 73 43",
    "sg:postcode":"28023",
    "sg:province":"Madrid",
    "wof:name":"Herpil S.l.",
    "wof:placetype":"venue"
},
  "geometry": {"coordinates":[-3.8170740604,40.4721565247],"type":"Point"}
}