{
  "type": "Feature",
  "properties": {
    "addr:full":"Avda Extremadura, 78 Santiponce Sevilla 41970",
    "addr:housenumber":"78",
    "addr:postcode":"41970",
    "addr:street":"Avda Extremadura",
    "iso:country":"ES",
    "sg:address":"Avda Extremadura, 78",
    "sg:city":"Santiponce",
    "sg:orig_category":"Cr\u00cda De Animales",
    "sg:phone":"+34 955 99 78 09",
    "sg:postcode":"41970",
    "sg:province":"Sevilla",
    "wof:name":"Garcia Vega Pedro",
    "wof:placetype":"venue"
},
  "geometry": {"coordinates":[-6.0401558876,37.4376678467],"type":"Point"}
}