{
  "type": "Feature",
  "properties": {
    "iso:country":"ES",
    "sg:address":"Av Notari Alemany, 10",
    "sg:city":"Magaluf",
    "sg:orig_category":"Cl\u00cdnicas M\u00c9dicas",
    "sg:phone":"+34 971 13 27 71",
    "sg:postcode":"07181",
    "sg:province":"Islas Baleares",
    "wof:name":"The British Surgery Magaluf S.l.",
    "wof:placetype":"venue"
},
  "geometry": {"coordinates":[2.5310549736,39.5035438538],"type":"Point"}
}