{
  "type": "Feature",
  "properties": {
    "addr:full":"Calle de Juan Bautista Zabala, 12 Getxo Vizcaya 48991",
    "addr:housenumber":"12",
    "addr:postcode":"48991",
    "addr:street":"Calle De Juan Bautista Zabala",
    "iso:country":"ES",
    "sg:address":"Calle de Juan Bautista Zabala, 12",
    "sg:city":"Getxo",
    "sg:orig_category":"Agencias Y Asesores De Publicidad",
    "sg:phone":"+34 946 02 67 86",
    "sg:postcode":"48991",
    "sg:province":"Vizcaya",
    "wof:name":"Laluca Comunicacion",
    "wof:placetype":"venue"
},
  "geometry": {"coordinates":[-3.0100948811,43.3507347107],"type":"Point"}
}