{
  "type": "Feature",
  "properties": {
    "iso:country":"ES",
    "sg:address":"Avda Pumarin De, 11",
    "sg:city":"Oviedo",
    "sg:orig_category":"Librer\u00cdas",
    "sg:phone":"+34 985 28 16 52",
    "sg:postcode":"33001",
    "sg:province":"Asturias",
    "wof:name":"Izquierdo Iglesias Jose Maria",
    "wof:placetype":"venue"
},
  "geometry": {"coordinates":[-5.8456315994,43.3670959473],"type":"Point"}
}