{
  "type": "Feature",
  "properties": {
    "addr:full":"Calle de Santa Rosa, 14 Santiago El Mayor Murcia 30012",
    "addr:housenumber":"14",
    "addr:postcode":"30012",
    "addr:street":"Calle De Santa Rosa",
    "iso:country":"ES",
    "sg:address":"Calle de Santa Rosa, 14",
    "sg:city":"Santiago El Mayor",
    "sg:orig_category":"Venta, Alquiler De Instrumentos Y Accesorios De M\u00dasica",
    "sg:phone":"+34 968 25 58 21",
    "sg:postcode":"30012",
    "sg:province":"Murcia",
    "wof:name":"Igualada Jimenez Angel",
    "wof:placetype":"venue"
},
  "geometry": {"coordinates":[-1.1230629683,37.971206665],"type":"Point"}
}