{
  "type": "Feature",
  "properties": {
    "iso:country":"ES",
    "sg:address":"Pla\u00c7 Vila, 28",
    "sg:city":"Amer",
    "sg:orig_category":"Molduras, Junquillos, Listones Y Molduras Perforadas",
    "sg:phone":"+34 972 43 01 69",
    "sg:postcode":"17170",
    "sg:province":"Girona",
    "wof:name":"Font Comajoan Anna",
    "wof:placetype":"venue"
},
  "geometry": {"coordinates":[2.5891647339,42.0193862915],"type":"Point"}
}