{
  "type": "Feature",
  "properties": {
    "iso:country":"ES",
    "sg:address":"Calle de Paris, 18",
    "sg:city":"Valdemoro",
    "sg:orig_category":"Autob\u00das (explotaci\u00d3n Y Servicios De)",
    "sg:phone":"+34 918 95 20 46",
    "sg:postcode":"28340",
    "sg:province":"Madrid",
    "wof:name":"Autocares Fernanbus S.l.",
    "wof:placetype":"venue"
},
  "geometry": {"coordinates":[-3.6855428219,40.2108268738],"type":"Point"}
}