{
  "type": "Feature",
  "properties": {
    "addr:full":"Av Llibertat, 36 Mollet Valles Barcelona 08100",
    "addr:housenumber":"36",
    "addr:postcode":"08100",
    "addr:street":"Av Llibertat",
    "iso:country":"ES",
    "sg:address":"Av Llibertat, 36",
    "sg:city":"Mollet Valles",
    "sg:orig_category":"Farmacias",
    "sg:phone":"+34 935 70 25 18",
    "sg:postcode":"08100",
    "sg:province":"Barcelona",
    "wof:name":"Satorres Lape\u00f1a Manuel",
    "wof:placetype":"venue"
},
  "geometry": {"coordinates":[2.2099070549,41.5334777832],"type":"Point"}
}