{
  "type": "Feature",
  "properties": {
    "iso:country":"ES",
    "sg:address":"Calle de Galicia, 29",
    "sg:city":"Palmas De Gran Canaria",
    "sg:orig_category":"Agencias De Viajes",
    "sg:phone":"+34 928 22 53 83",
    "sg:postcode":"35007",
    "sg:province":"Las Palmas",
    "sg:website":"www.solisonviajes.com",
    "wof:name":"Sol Y Son Viajes S.a.",
    "wof:placetype":"venue"
},
  "geometry": {"coordinates":[-15.4332952499,28.1353664398],"type":"Point"}
}