{
  "type": "Feature",
  "properties": {
    "addr:full":"Avgd Comunitat Europea, 2 Badalona Barcelona 08917",
    "addr:housenumber":"2",
    "addr:postcode":"08917",
    "addr:street":"Europea",
    "iso:country":"ES",
    "sg:address":"Avgd Comunitat Europea, 2",
    "sg:city":"Badalona",
    "sg:orig_category":"Ropa Para Caballeros Y Se\u00d1oras (al Por Mayor)",
    "sg:phone":"+34 934 65 78 30",
    "sg:postcode":"08917",
    "sg:province":"Barcelona",
    "wof:name":"Eva S.c.p.",
    "wof:placetype":"venue"
},
  "geometry": {"coordinates":[2.2235150337,41.4558296204],"type":"Point"}
}