{
  "type": "Feature",
  "properties": {
    "addr:full":"Calle de General Vara De Rey, 9 Logro\u00f1o La Rioja 26002",
    "addr:housenumber":"9",
    "addr:postcode":"26002",
    "addr:street":"Calle De General Vara De Rey;Rioja",
    "iso:country":"ES",
    "sg:address":"Calle de General Vara De Rey, 9",
    "sg:city":"Logro\u00f1o",
    "sg:orig_category":"Mec\u00c1nica Y Herramientas De Precisi\u00d3n",
    "sg:phone":"+34 941 23 65 13",
    "sg:postcode":"26002",
    "sg:province":"La Rioja",
    "sg:website":"www.maxonmotor.es",
    "wof:name":"Maxon Motor Iberica S.a.",
    "wof:placetype":"venue"
},
  "geometry": {"coordinates":[-2.4466691017,42.4585189819],"type":"Point"}
}