{
  "type": "Feature",
  "properties": {
    "addr:full":"Plaz Conde De Priego, 2 Cordoba C\u00f3rdoba 14001",
    "addr:housenumber":"2",
    "addr:postcode":"14001",
    "addr:street":"Priego;Co\u0301Rdoba",
    "iso:country":"ES",
    "sg:address":"Plaz Conde De Priego, 2",
    "sg:city":"Cordoba",
    "sg:orig_category":"Bisuter\u00cda, Joyer\u00cda, Relojer\u00cda (al Por Menor)",
    "sg:phone":"+34 957 48 05 83",
    "sg:postcode":"14001",
    "sg:province":"C\u00f3rdoba",
    "wof:name":"Maria Auxiliadora Joyas S.l.",
    "wof:placetype":"venue"
},
  "geometry": {"coordinates":[-4.7759251595,37.8893508911],"type":"Point"}
}