{
  "type": "Feature",
  "properties": {
    "addr:full":"Calle de Bejar, 7 Madrid Madrid 28028",
    "addr:housenumber":"7",
    "addr:postcode":"madrid;28028",
    "addr:street":"Calle De Bejar",
    "iso:country":"ES",
    "sg:address":"Calle de Bejar, 7",
    "sg:city":"Madrid",
    "sg:orig_category":"Alquiler De Material De Oficina E Inform\u00c1tica",
    "sg:phone":"+34 913 61 07 00",
    "sg:postcode":"28028",
    "sg:province":"Madrid",
    "wof:name":"Jot Prosystems S.c.",
    "wof:placetype":"venue"
},
  "geometry": {"coordinates":[-3.6742229462,40.4353256226],"type":"Point"}
}