{
  "type": "Feature",
  "properties": {
    "addr:full":"Cmno Sotet (del), 2 Fraga Huesca 22520",
    "addr:housenumber":"2",
    "addr:postcode":"22520",
    "addr:street":"Cmno Sotet Del",
    "iso:country":"ES",
    "sg:address":"Cmno Sotet (del), 2",
    "sg:city":"Fraga",
    "sg:orig_category":"Asesor\u00cda Fiscal Y Jur\u00cddica",
    "sg:phone":"+34 974 47 04 06",
    "sg:postcode":"22520",
    "sg:province":"Huesca",
    "wof:name":"Margallo Asesores S.l.",
    "wof:placetype":"venue"
},
  "geometry": {"coordinates":[0.3484250009,41.5196495056],"type":"Point"}
}