{
  "type": "Feature",
  "properties": {
    "addr:full":"Pase Molino De Viento, 7 Carolina Ja\u00e9n 23200",
    "addr:housenumber":"7",
    "addr:postcode":"23200",
    "addr:street":"Viento;Carolina Jae\u0301N",
    "iso:country":"ES",
    "sg:address":"Pase Molino De Viento, 7",
    "sg:city":"Carolina",
    "sg:orig_category":"M\u00c9dicos: Estomatolog\u00cda",
    "sg:phone":"+34 953 68 00 61",
    "sg:postcode":"23200",
    "sg:province":"Ja\u00e9n",
    "wof:name":"Balaguer Recena Luis Carlos",
    "wof:placetype":"venue"
},
  "geometry": {"coordinates":[-3.7895176411,37.7657394409],"type":"Point"}
}