{
  "type": "Feature",
  "properties": {
    "addr:full":"Av President Companys, 10 Reus Tarragona 43201",
    "addr:housenumber":"10",
    "addr:postcode":"43201",
    "addr:street":"Av President Companys",
    "iso:country":"ES",
    "sg:address":"Av President Companys, 10",
    "sg:city":"Reus",
    "sg:orig_category":"Restaurantes",
    "sg:phone":"+34 977 32 37 05",
    "sg:postcode":"43201",
    "sg:province":"Tarragona",
    "wof:name":"Vallverdu Vallverdu Luis",
    "wof:placetype":"venue"
},
  "geometry": {"coordinates":[1.1026320457,41.1551971436],"type":"Point"}
}