{
  "type": "Feature",
  "properties": {
    "iso:country":"ES",
    "sg:address":"Calle de Pobla De Farnals, 33",
    "sg:city":"Valencia",
    "sg:orig_category":"Ense\u00d1anza P\u00dablica Primaria",
    "sg:phone":"+34 963 62 38 30",
    "sg:postcode":"46021",
    "sg:province":"Valencia",
    "wof:name":"Creciendo Juntos C.b",
    "wof:placetype":"venue"
},
  "geometry": {"coordinates":[-0.3518129885,39.4697723389],"type":"Point"}
}