{
  "type": "Feature",
  "properties": {
    "iso:country":"ES",
    "sg:address":"Calle de Espinar, 23",
    "sg:city":"Madrid",
    "sg:orig_category":"Papeler\u00cdas, Librer\u00cdas",
    "sg:phone":"+34 915 25 86 51",
    "sg:postcode":"28025",
    "sg:province":"Madrid",
    "wof:name":"Garcia Segovia Luis",
    "wof:placetype":"venue"
},
  "geometry": {"coordinates":[-3.7442970276,40.3861656189],"type":"Point"}
}