{
  "type": "Feature",
  "properties": {
    "iso:country":"ES",
    "sg:address":"Calle de Madre Petra, 8",
    "sg:city":"Martos",
    "sg:orig_category":"Institutos De Belleza (productos Y Aparatos)",
    "sg:phone":"+34 953 70 46 13",
    "sg:postcode":"23600",
    "sg:province":"Ja\u00e9n",
    "wof:name":"Doybel Esteticista S.l.",
    "wof:placetype":"venue"
},
  "geometry": {"coordinates":[-3.9735488892,37.7180099487],"type":"Point"}
}