{
  "type": "Feature",
  "properties": {
    "iso:country":"ES",
    "sg:address":"Carr Ballesteries, 38",
    "sg:city":"Girona",
    "sg:orig_category":"Ropa Para Ni\u00d1os (al Por Menor)",
    "sg:phone":"+34 972 48 50 41",
    "sg:postcode":"17003",
    "sg:province":"Girona",
    "wof:name":"Abadia Abella Montse",
    "wof:placetype":"venue"
},
  "geometry": {"coordinates":[2.824719,41.986385],"type":"Point"}
}