{
  "type": "Feature",
  "properties": {
    "addr:full":"Calle de Sor Valentina Miron, 35 Plasencia C\u00e1ceres 10600",
    "addr:housenumber":"35",
    "addr:postcode":"10600",
    "addr:street":"Calle De Sor Valentina Miron;Ca\u0301Ceres",
    "iso:country":"ES",
    "sg:address":"Calle de Sor Valentina Miron, 35",
    "sg:city":"Plasencia",
    "sg:orig_category":"Supermercados Y Hipermercados",
    "sg:phone":"+34 927 42 12 78",
    "sg:postcode":"10600",
    "sg:province":"C\u00e1ceres",
    "wof:name":"Supermercado Sor Valentina S.l.",
    "wof:placetype":"venue"
},
  "geometry": {"coordinates":[-6.0890088081,40.0336532593],"type":"Point"}
}