{
  "type": "Feature",
  "properties": {
    "iso:country":"ES",
    "sg:address":"Cartagena, 3",
    "sg:city":"Cabo Palos",
    "sg:orig_category":"Centros Empresariales",
    "sg:phone":"+34 968 14 60 59",
    "sg:postcode":"30370",
    "sg:province":"Murcia",
    "sg:website":"www.asistenciatecnicaregional.com",
    "wof:name":"Asistencia Tecnica Regional S.l.",
    "wof:placetype":"venue"
},
  "geometry": {"coordinates":[-0.7754248977,37.6226921082],"type":"Point"}
}