{
  "type": "Feature",
  "properties": {
    "addr:full":"Calle de Corazon De Maria, 70 Madrid Madrid 28002",
    "addr:housenumber":"70",
    "addr:postcode":"madrid;28002",
    "addr:street":"Calle De Corazon;Maria",
    "iso:country":"ES",
    "sg:address":"Calle de Corazon De Maria, 70",
    "sg:city":"Madrid",
    "sg:orig_category":"Cajas De Ahorro",
    "sg:phone":"+34 915 15 36 40",
    "sg:postcode":"28002",
    "sg:province":"Madrid",
    "sg:website":"www.cam.es",
    "wof:name":"Caja De Ahorros Del Mediterraneo",
    "wof:placetype":"venue"
},
  "geometry": {"coordinates":[-3.6661820412,40.4465904236],"type":"Point"}
}