{
  "type": "Feature",
  "properties": {
    "addr:full":"Carrer de Joan Maragall, 8 Prat Llobregat Barcelona 08820",
    "addr:housenumber":"8",
    "addr:postcode":"08820",
    "addr:street":"Carrer De Joan Maragall;Llobregat",
    "iso:country":"ES",
    "sg:address":"Carrer de Joan Maragall, 8",
    "sg:city":"Prat Llobregat",
    "sg:orig_category":"Soldadura, Equipo Y Herramental",
    "sg:phone":"+34 933 78 92 80",
    "sg:postcode":"08820",
    "sg:province":"Barcelona",
    "wof:name":"Castolin Espa\u00d1a S.a.",
    "wof:placetype":"venue"
},
  "geometry": {"coordinates":[2.0957489014,41.332233429],"type":"Point"}
}