{
  "type": "Feature",
  "properties": {
    "iso:country":"ES",
    "sg:address":"Calle de Medio, 11",
    "sg:city":"Santander",
    "sg:orig_category":"Bisuter\u00cda, Joyer\u00cda, Relojer\u00cda (al Por Menor)",
    "sg:phone":"+34 942 21 29 88",
    "sg:postcode":"39003",
    "sg:province":"Cantabria",
    "wof:name":"Hijos De Pablo Galan C. De B.",
    "wof:placetype":"venue"
},
  "geometry": {"coordinates":[-3.8044219017,43.4628753662],"type":"Point"}
}