{
  "type": "Feature",
  "properties": {
    "addr:full":"Calle de Carreterilla, 3 Castrojeriz Burgos 09110",
    "addr:housenumber":"3",
    "addr:postcode":"09110",
    "addr:street":"Calle De Carreterilla",
    "iso:country":"ES",
    "sg:address":"Calle de Carreterilla, 3",
    "sg:city":"Castrojeriz",
    "sg:orig_category":"Asociaciones, Organismos Culturales Y Socioeducativos",
    "sg:phone":"+34 947 37 70 06",
    "sg:postcode":"09110",
    "sg:province":"Burgos",
    "wof:name":"Caja De Ahorros Municipal De Burgos",
    "wof:placetype":"venue"
},
  "geometry": {"coordinates":[-4.1414990425,42.2864265442],"type":"Point"}
}