{
  "type": "Feature",
  "properties": {
    "addr:full":"Ctra. Gamarra, S/n Gamarra Mayor \u00c1lava 01510",
    "addr:housenumber":"s / n",
    "addr:postcode":"01510",
    "addr:street":"Ctra. Gamarra",
    "iso:country":"ES",
    "sg:address":"Ctra. Gamarra, S/n",
    "sg:city":"Gamarra Mayor",
    "sg:orig_category":"Electricidad: Equipos Industriales, Componentes (fabricaci\u00d3n)",
    "sg:phone":"+34 945 12 03 24",
    "sg:postcode":"01510",
    "sg:province":"\u00c1lava",
    "wof:name":"Rohde & Schwarz Espana S.a.",
    "wof:placetype":"venue"
},
  "geometry": {"coordinates":[-2.6584849358,42.8780326843],"type":"Point"}
}