{
  "type": "Feature",
  "properties": {
    "addr:full":"Carr Pla Del Rei, Des, 14 S. Francesc Formentera Islas Baleares 07860",
    "addr:postcode":"07860",
    "addr:street":"Carr Pla Del Rei Des 14 S. Francesc",
    "iso:country":"ES",
    "sg:address":"Carr Pla Del Rei, Des, 14",
    "sg:city":"S. Francesc Formentera",
    "sg:orig_category":"Peluquer\u00cdas, Peluquer\u00cda Mixta",
    "sg:phone":"+34 971 32 23 00",
    "sg:postcode":"07860",
    "sg:province":"Islas Baleares",
    "wof:name":"Tur Tur Claudia",
    "wof:placetype":"venue"
},
  "geometry": {"coordinates":[1.4309200048,38.7072410583],"type":"Point"}
}