{
  "type": "Feature",
  "properties": {
    "addr:full":"Urb. Nueva Andalucia, S/n Nueva Andalucia M\u00e1laga 29660",
    "addr:postcode":"29660",
    "addr:street":"Andalucia S / N;Ma\u0301Laga",
    "iso:country":"ES",
    "sg:address":"Urb. Nueva Andalucia, S/n",
    "sg:city":"Nueva Andalucia",
    "sg:orig_category":"Muebles, Minoristas",
    "sg:phone":"+34 952 90 83 00",
    "sg:postcode":"29660",
    "sg:province":"M\u00e1laga",
    "wof:name":"Imperio Fornitures Muebles S.l.",
    "wof:placetype":"venue"
},
  "geometry": {"coordinates":[-4.9541988373,36.5097084045],"type":"Point"}
}