{
  "type": "Feature",
  "properties": {
    "iso:country":"ES",
    "sg:address":"Calle de Carcastillo, 1",
    "sg:city":"Tudela",
    "sg:orig_category":"Promotores Constructores",
    "sg:phone":"+34 948 40 31 25",
    "sg:postcode":"31500",
    "sg:province":"Navarra",
    "wof:name":"Comunidad Propietarios Ubiercas 9 Y Carc",
    "wof:placetype":"venue"
},
  "geometry": {"coordinates":[-1.5951094627,42.0525245667],"type":"Point"}
}