{
  "type": "Feature",
  "properties": {
    "addr:full":"Ctra Alcala-sevilla(p I Bansur), 8 Alcala Guadaira Sevilla 41500",
    "addr:housenumber":"8",
    "addr:postcode":"41500",
    "addr:street":"Ctra Alcala-Sevilla P;Bansur",
    "iso:country":"ES",
    "sg:address":"Ctra Alcala-sevilla(p I Bansur), 8",
    "sg:city":"Alcala Guadaira",
    "sg:orig_category":"Construcciones Met\u00c1licas",
    "sg:phone":"+34 955 63 14 10",
    "sg:postcode":"41500",
    "sg:province":"Sevilla",
    "wof:name":"Sociedad Anonima De Construcciones Metalicas",
    "wof:placetype":"venue"
},
  "geometry": {"coordinates":[-5.8537950516,37.3369216919],"type":"Point"}
}