{
  "type": "Feature",
  "properties": {
    "addr:full":"L. H. Pilcher, 17 Carrizal Las Palmas 35240",
    "addr:housenumber":"17",
    "addr:postcode":"35240",
    "addr:street":"Pilcher",
    "iso:country":"ES",
    "sg:address":"L. H. Pilcher, 17",
    "sg:city":"Carrizal",
    "sg:orig_category":"Alimentaci\u00d3n General (al Por Menor)",
    "sg:phone":"+34 928 78 15 79",
    "sg:postcode":"35240",
    "sg:province":"Las Palmas",
    "wof:name":"Trejo Hernandez Maria",
    "wof:placetype":"venue"
},
  "geometry": {"coordinates":[-15.4145336151,27.9132900238],"type":"Point"}
}