{
  "type": "Feature",
  "properties": {
    "iso:country":"ES",
    "sg:address":"Carrer de Cami Bellavista, S/n",
    "sg:city":"Puigdalber",
    "sg:orig_category":"Panader\u00cdas, Pasteler\u00cdas, Boller\u00cda Industriale (fabricaci\u00d3n, Al Por Mayor)",
    "sg:phone":"+34 938 98 81 42",
    "sg:postcode":"08797",
    "sg:province":"Barcelona",
    "wof:name":"Especialitats M. Masdeu S.l.",
    "wof:placetype":"venue"
},
  "geometry": {"coordinates":[1.7004400492,41.4052963257],"type":"Point"}
}