{
  "type": "Feature",
  "properties": {
    "iso:country":"ES",
    "sg:address":"Pg Gracia, 111",
    "sg:city":"Barcelona",
    "sg:orig_category":"Sociedades, Compa\u00d1\u00cdas Aseguradoras",
    "sg:phone":"+34 934 15 62 67",
    "sg:postcode":"08008",
    "sg:province":"Barcelona",
    "wof:name":"Willis Syc Correduria De Seguros Y Reaseguros S.a.",
    "wof:placetype":"venue"
},
  "geometry": {"coordinates":[2.1589186192,41.3967285156],"type":"Point"}
}