{
  "type": "Feature",
  "properties": {
    "addr:full":"Rosalia De Castro, S/n Nogais Lugo 27677",
    "addr:housenumber":"s / n",
    "addr:postcode":"27677",
    "addr:street":"Rosalia De Castro",
    "iso:country":"ES",
    "sg:address":"Rosalia De Castro, S/n",
    "sg:city":"Nogais",
    "sg:orig_category":"Hoteles",
    "sg:phone":"+34 982 36 40 50",
    "sg:postcode":"27677",
    "sg:province":"Lugo",
    "wof:name":"Alvarez Ferreiro Bego\u00f1a",
    "wof:placetype":"venue"
},
  "geometry": {"coordinates":[-7.1090431213,42.8091430664],"type":"Point"}
}