{
  "type": "Feature",
  "properties": {
    "addr:full":"Calle de Portuetxe, 63 Donostia-san Sebastian Guip\u00f9zcoa 20018",
    "addr:housenumber":"63",
    "addr:postcode":"20018",
    "addr:street":"Calle De Portuetxe",
    "iso:country":"ES",
    "sg:address":"Calle de Portuetxe, 63",
    "sg:city":"Donostia-san Sebastian",
    "sg:orig_category":"Empresas De Vigilancia, Guardia Y Protecci\u00d3n",
    "sg:phone":"+34 943 21 01 70",
    "sg:postcode":"20018",
    "sg:province":"Guip\u00f9zcoa",
    "wof:name":"Adostu Sl",
    "wof:placetype":"venue"
},
  "geometry": {"coordinates":[-2.0177106857,43.3012619019],"type":"Point"}
}