{
  "type": "Feature",
  "properties": {
    "iso:country":"ES",
    "sg:address":"Rica Posada, S/n",
    "sg:city":"Villanueva De Gumiel",
    "sg:orig_category":"Agricultores, Agricultores",
    "sg:phone":"+34 947 52 57 44",
    "sg:postcode":"09450",
    "sg:province":"Burgos",
    "wof:name":"Cooperativa Del Campo De San Mames",
    "wof:placetype":"venue"
},
  "geometry": {"coordinates":[-3.5581541061,41.7713050842],"type":"Point"}
}