{
  "type": "Feature",
  "properties": {
    "iso:country":"ES",
    "sg:address":"Calle de Zaragoza, 15",
    "sg:city":"Fuentes Ebro",
    "sg:orig_category":"Electricidad: Instaladores",
    "sg:phone":"+34 976 16 12 43",
    "sg:postcode":"50740",
    "sg:province":"Zaragoza",
    "wof:name":"Instalaciones, Mantenimientos Y Automatismos Electricos S.l.l.",
    "wof:placetype":"venue"
},
  "geometry": {"coordinates":[-0.6327329874,41.514629364],"type":"Point"}
}