{
  "type": "Feature",
  "properties": {
    "iso:country":"ES",
    "sg:address":"Calle de Miguel Servet, 7",
    "sg:city":"Villaviciosa Odon",
    "sg:orig_category":"Empresarios",
    "sg:phone":"+34 916 16 48 73",
    "sg:postcode":"28670",
    "sg:province":"Madrid",
    "wof:name":"Velazquez Bermejo Damian",
    "wof:placetype":"venue"
},
  "geometry": {"coordinates":[-3.9152479172,40.3631362915],"type":"Point"}
}