{
  "type": "Feature",
  "properties": {
    "iso:country":"ES",
    "sg:address":"Avda San Jose, 64",
    "sg:city":"Zaragoza",
    "sg:orig_category":"Mec\u00c1nico Del Autom\u00d3vil",
    "sg:phone":"+34 976 41 56 35",
    "sg:postcode":"50008",
    "sg:province":"Zaragoza",
    "wof:name":"Talleres Julian S.l.",
    "wof:placetype":"venue"
},
  "geometry": {"coordinates":[-0.8734930158,41.6412773132],"type":"Point"}
}