{
  "type": "Feature",
  "properties": {
    "iso:country":"ES",
    "sg:address":"Barr Fervedoira, 15",
    "sg:city":"Lugo",
    "sg:orig_category":"Comerciantes Al Por Mayor De Vinos, Licores Y Alcoholes",
    "sg:phone":"+34 982 24 03 09",
    "sg:postcode":"27003",
    "sg:province":"Lugo",
    "sg:website":"www.augadomino.com",
    "wof:name":"Auga Do Mi\u00f1o S.l.",
    "wof:placetype":"venue"
},
  "geometry": {"coordinates":[-7.5763959885,43.0335426331],"type":"Point"}
}