{
  "type": "Feature",
  "properties": {
    "iso:country":"ES",
    "sg:address":"Calle de Alangobarri, 1",
    "sg:city":"Getxo",
    "sg:orig_category":"Electricidad: Material Y Suministros De Instalaci\u00d3n (fabricaci\u00d3n)",
    "sg:phone":"+34 944 60 42 80",
    "sg:postcode":"48990",
    "sg:province":"Vizcaya",
    "wof:name":"Cositronics Sl",
    "wof:placetype":"venue"
},
  "geometry": {"coordinates":[-3.0096838474,43.3477935791],"type":"Point"}
}