{
  "type": "Feature",
  "properties": {
    "iso:country":"ES",
    "sg:address":"F. El Chivero, S/n",
    "sg:city":"Bargas",
    "sg:orig_category":"Producci\u00d3n, Venta De Productos De Agricultura Biol\u00d3gica",
    "sg:phone":"+34 925 59 01 17",
    "sg:postcode":"45593",
    "sg:province":"Toledo",
    "wof:name":"Escobar Gomez Pablo",
    "wof:placetype":"venue"
},
  "geometry": {"coordinates":[-4.0285930634,39.9432487488],"type":"Point"}
}