{
  "type": "Feature",
  "properties": {
    "iso:country":"ES",
    "sg:address":"Calle de Saavedra Fajardo, 73",
    "sg:city":"Torre-pacheco",
    "sg:orig_category":"Peluquer\u00cdas, Peluquer\u00cda Mixta",
    "sg:phone":"+34 968 57 82 85",
    "sg:postcode":"30700",
    "sg:province":"Murcia",
    "wof:name":"Navarro Ros Carmen",
    "wof:placetype":"venue"
},
  "geometry": {"coordinates":[-1.1271020174,37.9869995117],"type":"Point"}
}