{
  "type": "Feature",
  "properties": {
    "addr:full":"Calle de Torriente, 5 Benacazon Sevilla 41805",
    "addr:housenumber":"5",
    "addr:postcode":"41805",
    "addr:street":"Calle De Torriente",
    "iso:country":"ES",
    "sg:address":"Calle de Torriente, 5",
    "sg:city":"Benacazon",
    "sg:orig_category":"Librer\u00cdas",
    "sg:phone":"+34 955 70 61 20",
    "sg:postcode":"41805",
    "sg:province":"Sevilla",
    "wof:name":"Valencia Cuenca Antonio",
    "wof:placetype":"venue"
},
  "geometry": {"coordinates":[-6.199324131,37.3563652039],"type":"Point"}
}