{
  "type": "Feature",
  "properties": {
    "addr:full":"Calle de Roger De Lauria, 16 Valencia Valencia 46002",
    "addr:housenumber":"16",
    "addr:postcode":"46002",
    "addr:street":"Calle De Roger De Lauria",
    "iso:country":"ES",
    "sg:address":"Calle de Roger De Lauria, 16",
    "sg:city":"Valencia",
    "sg:orig_category":"Estilistas Y Estudios De Estilo De Corte Y Confecci\u00d3n",
    "sg:phone":"+34 963 51 17 92",
    "sg:postcode":"46002",
    "sg:province":"Valencia",
    "wof:name":"Valencia Passion And Fashion Sl",
    "wof:placetype":"venue"
},
  "geometry": {"coordinates":[-0.3740420043,39.4690284729],"type":"Point"}
}