{
  "type": "Feature",
  "properties": {
    "iso:country":"ES",
    "sg:address":"Salto Del Pollo, 18",
    "sg:city":"Villamartin",
    "sg:orig_category":"Promotores Constructores",
    "sg:phone":"+34 956 73 11 34",
    "sg:postcode":"11650",
    "sg:province":"C\u00e1diz",
    "wof:name":"Construcciones Ruano Castillo S.l.",
    "wof:placetype":"venue"
},
  "geometry": {"coordinates":[-5.6406030655,36.8608970642],"type":"Point"}
}