{
  "type": "Feature",
  "properties": {
    "addr:full":"Carrer de Pedrissos, 9 Castellar Valles Barcelona 08211",
    "addr:housenumber":"9",
    "addr:postcode":"08211",
    "addr:street":"Carrer De Pedrissos",
    "iso:country":"ES",
    "sg:address":"Carrer de Pedrissos, 9",
    "sg:city":"Castellar Valles",
    "sg:orig_category":"Sindicatos De Trabajadores",
    "sg:phone":"+34 937 14 21 21",
    "sg:postcode":"08211",
    "sg:province":"Barcelona",
    "wof:name":"Confederacio General Del Treball De Catalunya",
    "wof:placetype":"venue"
},
  "geometry": {"coordinates":[2.0857300758,41.6151885986],"type":"Point"}
}