{
  "type": "Feature",
  "properties": {
    "iso:country":"ES",
    "sg:address":"Calle de Royel, 1",
    "sg:city":"Epila",
    "sg:orig_category":"Bazares, Art\u00cdculos De Limpieza Y De Cocina (al Por Menor)",
    "sg:phone":"+34 976 60 40 34",
    "sg:postcode":"50290",
    "sg:province":"Zaragoza",
    "wof:name":"Aguirre Rojas Diana Maria",
    "wof:placetype":"venue"
},
  "geometry": {"coordinates":[-1.2804260254,41.6004676819],"type":"Point"}
}