{
  "type": "Feature",
  "properties": {
    "iso:country":"ES",
    "sg:address":"Calle de Carmen De Icaza, 1",
    "sg:city":"Granada",
    "sg:orig_category":"Ropa Para Se\u00d1oras Y Caballeros (al Por Menor)",
    "sg:phone":"+34 958 81 11 58",
    "sg:postcode":"18007",
    "sg:province":"Granada",
    "wof:name":"Caliz Bricio Alfredo",
    "wof:placetype":"venue"
},
  "geometry": {"coordinates":[-3.6012845039,37.155582428],"type":"Point"}
}