{
  "type": "Feature",
  "properties": {
    "iso:country":"ES",
    "sg:address":"Los Peregrinos, 11",
    "sg:city":"Bembibre",
    "sg:orig_category":"Empresas De Pintura Y Revestimientos",
    "sg:phone":"+34 987 51 17 66",
    "sg:postcode":"24300",
    "sg:province":"Le\u00f3n",
    "wof:name":"Rodriguez Perez Agustin",
    "wof:placetype":"venue"
},
  "geometry": {"coordinates":[-6.4149289131,42.6145935059],"type":"Point"}
}