{
  "type": "Feature",
  "properties": {
    "iso:country":"ES",
    "sg:address":"La Luz, 6",
    "sg:city":"Oion",
    "sg:orig_category":"Colchones (fabricaci\u00d3n, Al Por Mayor, Al Por Menor)",
    "sg:phone":"+34 945 60 15 73",
    "sg:postcode":"01320",
    "sg:province":"\u00c1lava",
    "wof:name":"Iberlax S.c.",
    "wof:placetype":"venue"
},
  "geometry": {"coordinates":[-2.4377920628,42.4945297241],"type":"Point"}
}