{
  "type": "Feature",
  "properties": {
    "addr:full":"Bda. Sta. Marta, 2 Algaba Sevilla 41980",
    "addr:housenumber":"2",
    "addr:postcode":"41980",
    "addr:street":"Marta",
    "iso:country":"ES",
    "sg:address":"Bda. Sta. Marta, 2",
    "sg:city":"Algaba",
    "sg:orig_category":"Bisuter\u00cda, Joyer\u00cda, Relojer\u00cda (al Por Menor)",
    "sg:phone":"+34 955 78 79 82",
    "sg:postcode":"41980",
    "sg:province":"Sevilla",
    "wof:name":"Serrano Carbonell Diego",
    "wof:placetype":"venue"
},
  "geometry": {"coordinates":[-6.0125188828,37.4622116089],"type":"Point"}
}