{
  "type": "Feature",
  "properties": {
    "iso:country":"ES",
    "sg:address":"Calle de Postas, 16",
    "sg:city":"Aranda Duero",
    "sg:orig_category":"Ropa Para Caballeros (al Por Menor)",
    "sg:phone":"+34 947 50 91 16",
    "sg:postcode":"09400",
    "sg:province":"Burgos",
    "wof:name":"El-ouahabi  Bouchra",
    "wof:placetype":"venue"
},
  "geometry": {"coordinates":[-3.6861379147,41.670211792],"type":"Point"}
}