{
  "type": "Feature",
  "properties": {
    "addr:full":"Rbla Just Oliveras, 34 Hospitalet Llobregat Barcelona 08901",
    "addr:housenumber":"34",
    "addr:postcode":"08901",
    "addr:street":"Rbla Just Oliveras",
    "iso:country":"ES",
    "sg:address":"Rbla Just Oliveras, 34",
    "sg:city":"Hospitalet Llobregat",
    "sg:orig_category":"Molduras, Junquillos, Listones Y Molduras Perforadas",
    "sg:phone":"+34 932 61 07 61",
    "sg:postcode":"08901",
    "sg:province":"Barcelona",
    "wof:name":"Centro Catolico",
    "wof:placetype":"venue"
},
  "geometry": {"coordinates":[2.1013720036,41.3616027832],"type":"Point"}
}