{
  "type": "Feature",
  "properties": {
    "iso:country":"ES",
    "sg:address":"Calle de Azor, 13",
    "sg:city":"Fuenlabrada",
    "sg:orig_category":"Acero: Productos Sider\u00dargicos Y Transformados (fabricaci\u00d3n, Negocio)",
    "sg:phone":"+34 916 42 23 14",
    "sg:postcode":"28946",
    "sg:province":"Madrid",
    "wof:name":"Arran Industrias Metalurgicas Del Centro S.l.",
    "wof:placetype":"venue"
},
  "geometry": {"coordinates":[-3.7678678036,40.2602500916],"type":"Point"}
}