{
  "type": "Feature",
  "properties": {
    "iso:country":"ES",
    "sg:address":"Calle de Marbella, 32",
    "sg:city":"Fuengirola",
    "sg:orig_category":"Molduras, Junquillos, Listones Y Molduras Perforadas",
    "sg:phone":"+34 952 59 24 02",
    "sg:postcode":"29640",
    "sg:province":"M\u00e1laga",
    "wof:name":"Ferrero Velez Jose Daniel",
    "wof:placetype":"venue"
},
  "geometry": {"coordinates":[-4.6252841949,36.5371322632],"type":"Point"}
}