{
  "type": "Feature",
  "properties": {
    "iso:country":"ES",
    "sg:address":"Calle de Medina Y Galnares, 125",
    "sg:city":"Sevilla",
    "sg:orig_category":"Molduras, Junquillos, Listones Y Molduras Perforadas",
    "sg:phone":"+34 954 37 10 07",
    "sg:postcode":"41015",
    "sg:province":"Sevilla",
    "wof:name":"Garcia Gutierrez Rafael",
    "wof:placetype":"venue"
},
  "geometry": {"coordinates":[-5.9808101654,37.4300842285],"type":"Point"}
}