{
  "type": "Feature",
  "properties": {
    "iso:country":"ES",
    "sg:address":"Ctra Malaga, S/n",
    "sg:city":"Algeciras",
    "sg:orig_category":"Extinci\u00d3n De Incendios: Material Y Suministros (fabricaci\u00d3n, Al Por Mayor)",
    "sg:phone":"+34 956 65 03 45",
    "sg:postcode":"11203",
    "sg:province":"C\u00e1diz",
    "wof:name":"Ruiz Sistemas S.l.",
    "wof:placetype":"venue"
},
  "geometry": {"coordinates":[-5.4526491165,36.1276016235],"type":"Point"}
}