{
  "type": "Feature",
  "properties": {
    "iso:country":"ES",
    "sg:address":"Calle de Real De Abajo, 49",
    "sg:city":"Tornavacas",
    "sg:orig_category":"Carnicer\u00cdas, Carnicer\u00cdas",
    "sg:phone":"+34 927 17 73 24",
    "sg:postcode":"10611",
    "sg:province":"C\u00e1ceres",
    "wof:name":"Martin Bermejo Paloma",
    "wof:placetype":"venue"
},
  "geometry": {"coordinates":[-5.6897301674,40.2536849976],"type":"Point"}
}