{
  "type": "Feature",
  "properties": {
    "addr:full":"Rbla Francesc Macia, 25 Terrassa Barcelona 08226",
    "addr:housenumber":"25",
    "addr:postcode":"08226",
    "addr:street":"Rbla Francesc Macia",
    "iso:country":"ES",
    "sg:address":"Rbla Francesc Macia, 25",
    "sg:city":"Terrassa",
    "sg:orig_category":"Cajas De Ahorro",
    "sg:phone":"+34 937 34 94 68",
    "sg:postcode":"08226",
    "sg:province":"Barcelona",
    "wof:name":"Caixa D'estalvis Laietana",
    "wof:placetype":"venue"
},
  "geometry": {"coordinates":[2.0183970928,41.5761032104],"type":"Point"}
}