{
  "type": "Feature",
  "properties": {
    "addr:full":"Carrer de Bilbao, 51 Barcelona Barcelona 08005",
    "addr:housenumber":"51",
    "addr:postcode":"08005",
    "addr:street":"Carrer De Bilbao",
    "iso:country":"ES",
    "sg:address":"Carrer de Bilbao, 51",
    "sg:city":"Barcelona",
    "sg:orig_category":"Panader\u00cdas, Pasteler\u00cdas, Boller\u00cda Industriale (fabricaci\u00d3n, Al Por Mayor)",
    "sg:phone":"+34 934 85 19 40",
    "sg:postcode":"08005",
    "sg:province":"Barcelona",
    "wof:name":"Garrido Carrasco Isabel",
    "wof:placetype":"venue"
},
  "geometry": {"coordinates":[2.20342803,41.4029312134],"type":"Point"}
}