{
  "type": "Feature",
  "properties": {
    "addr:full":"Calle de Santiago Dulong, 4 Zaragoza Zaragoza 50003",
    "addr:housenumber":"4",
    "addr:postcode":"50003",
    "addr:street":"Calle De Santiago Dulong",
    "iso:country":"ES",
    "sg:address":"Calle de Santiago Dulong, 4",
    "sg:city":"Zaragoza",
    "sg:orig_category":"Procuradores",
    "sg:phone":"+34 976 43 79 16",
    "sg:postcode":"50003",
    "sg:province":"Zaragoza",
    "wof:name":"Borobia Lorente Elisa Maria",
    "wof:placetype":"venue"
},
  "geometry": {"coordinates":[-0.9016789794,41.6590881348],"type":"Point"}
}