{
  "type": "Feature",
  "properties": {
    "iso:country":"ES",
    "sg:address":"Calle de Bilbao, S/n",
    "sg:city":"Placa",
    "sg:orig_category":"Transportes Por V\u00cdas Navegables",
    "sg:phone":"+34 987 42 84 24",
    "sg:postcode":"24400",
    "sg:province":"Le\u00f3n",
    "wof:name":"Vazquez Rivas S.l.",
    "wof:placetype":"venue"
},
  "geometry": {"coordinates":[-6.6317191124,42.5488433838],"type":"Point"}
}