{
  "type": "Feature",
  "properties": {
    "addr:full":"Calle de Rioja, 26 Zaragoza Zaragoza 50017",
    "addr:housenumber":"26",
    "addr:postcode":"50017",
    "addr:street":"Calle De Rioja",
    "iso:country":"ES",
    "sg:address":"Calle de Rioja, 26",
    "sg:city":"Zaragoza",
    "sg:orig_category":"Dibujos Animados",
    "sg:phone":"+34 976 33 55 24",
    "sg:postcode":"50017",
    "sg:province":"Zaragoza",
    "wof:name":"Snikt S.l",
    "wof:placetype":"venue"
},
  "geometry": {"coordinates":[-0.9091529846,41.6550674438],"type":"Point"}
}