{
  "type": "Feature",
  "properties": {
    "iso:country":"ES",
    "sg:address":"Calle de San Cristobal, 1",
    "sg:city":"Mesas",
    "sg:orig_category":"Ambulancias",
    "sg:phone":"+34 967 15 55 87",
    "sg:postcode":"16650",
    "sg:province":"Cuenca",
    "wof:name":"Sevilla Jimenez Victoriano",
    "wof:placetype":"venue"
},
  "geometry": {"coordinates":[-2.7674269676,39.3904571533],"type":"Point"}
}