{
  "type": "Feature",
  "properties": {
    "addr:full":"Cno. Pescadores, S/n Marbella M\u00e1laga 29600",
    "addr:housenumber":"s / n",
    "addr:postcode":"29600",
    "addr:street":"Pescadores;Ma\u0301Laga",
    "iso:country":"ES",
    "sg:address":"Cno. Pescadores, S/n",
    "sg:city":"Marbella",
    "sg:orig_category":"Pintura Y Barniz (al Por Menor)",
    "sg:phone":"+34 952 89 81 00",
    "sg:postcode":"29600",
    "sg:province":"M\u00e1laga",
    "wof:name":"Pinturas Mata E Hijos S.l.",
    "wof:placetype":"venue"
},
  "geometry": {"coordinates":[-4.8833007812,36.5079956055],"type":"Point"}
}