{
  "type": "Feature",
  "properties": {
    "iso:country":"ES",
    "sg:address":"Zapateria, 27",
    "sg:city":"Iru\u00f1a",
    "sg:orig_category":"Ingenier\u00cda, Centros De Estudios (diversos)",
    "sg:phone":"+34 948 20 31 20",
    "sg:postcode":"31001",
    "sg:province":"Navarra",
    "wof:name":"Iryma Ingenieros S.l",
    "wof:placetype":"venue"
},
  "geometry": {"coordinates":[-1.6445604563,42.8171081543],"type":"Point"}
}