{
  "type": "Feature",
  "properties": {
    "addr:full":"Calle de Castilla, 172 Sevilla Sevilla 41010",
    "addr:housenumber":"172",
    "addr:postcode":"41010",
    "addr:street":"Calle De Castilla",
    "iso:country":"ES",
    "sg:address":"Calle de Castilla, 172",
    "sg:city":"Sevilla",
    "sg:orig_category":"Molduras, Junquillos, Listones Y Molduras Perforadas",
    "sg:phone":"+34 954 33 30 68",
    "sg:postcode":"41010",
    "sg:province":"Sevilla",
    "wof:name":"Gonzalez Martin Primitivo",
    "wof:placetype":"venue"
},
  "geometry": {"coordinates":[-6.010342598,37.3893051147],"type":"Point"}
}