{
  "type": "Feature",
  "properties": {
    "iso:country":"ES",
    "sg:address":"Calle de Galeon, 34",
    "sg:city":"Palmones",
    "sg:orig_category":"Cr\u00cda De Animales",
    "sg:phone":"+34 956 67 51 91",
    "sg:postcode":"11379",
    "sg:province":"C\u00e1diz",
    "wof:name":"Naturalia El Baraka S.l.",
    "wof:placetype":"venue"
},
  "geometry": {"coordinates":[-5.4428992271,36.1843261719],"type":"Point"}
}