{
  "type": "Feature",
  "properties": {
    "addr:full":"Av Catalunya, 125 Palau-solita I Plegamans Barcelona 08184",
    "addr:housenumber":"125",
    "addr:postcode":"08184",
    "addr:street":"Av Catalunya",
    "iso:country":"ES",
    "sg:address":"Av Catalunya, 125",
    "sg:city":"Palau-solita I Plegamans",
    "sg:orig_category":"Cajas De Ahorro",
    "sg:phone":"+34 938 64 30 64",
    "sg:postcode":"08184",
    "sg:province":"Barcelona",
    "wof:name":"Caixa D'estalvis I Pensions De Barcelona",
    "wof:placetype":"venue"
},
  "geometry": {"coordinates":[2.1807661057,41.5804328918],"type":"Point"}
}