{
  "type": "Feature",
  "properties": {
    "addr:full":"Calle de Valentin Calderon, 11 Palencia Palencia 34001",
    "addr:housenumber":"11",
    "addr:postcode":"34001",
    "addr:street":"Calle De Valentin Calderon",
    "iso:country":"ES",
    "sg:address":"Calle de Valentin Calderon, 11",
    "sg:city":"Palencia",
    "sg:orig_category":"M\u00c9dicos: Pediatr\u00cda. Enfermedades De Los Ni\u00d1os",
    "sg:phone":"+34 979 75 15 62",
    "sg:postcode":"34001",
    "sg:province":"Palencia",
    "wof:name":"Gonzalez Menendez Angel Enrique",
    "wof:placetype":"venue"
},
  "geometry": {"coordinates":[-4.5327129364,42.0122566223],"type":"Point"}
}