{
  "type": "Feature",
  "properties": {
    "iso:country":"ES",
    "sg:address":"Calle de Cronista Agustin Sandoval, 2",
    "sg:city":"Villarrobledo",
    "sg:orig_category":"Peluqueros: De Se\u00d1oras",
    "sg:phone":"+34 967 14 62 65",
    "sg:postcode":"02600",
    "sg:province":"Albacete",
    "wof:name":"Martinez Jerez Maria Concepcion",
    "wof:placetype":"venue"
},
  "geometry": {"coordinates":[-2.6050341129,39.264705658],"type":"Point"}
}