{
  "type": "Feature",
  "properties": {
    "iso:country":"ES",
    "sg:address":"Carrer de Saragossa, 11",
    "sg:city":"Terrassa",
    "sg:orig_category":"Cerrajer\u00cda, Ferrallista",
    "sg:phone":"+34 937 31 46 22",
    "sg:postcode":"08227",
    "sg:province":"Barcelona",
    "wof:name":"Blustex General S.l.",
    "wof:placetype":"venue"
},
  "geometry": {"coordinates":[2.0404469967,41.5617980957],"type":"Point"}
}