{
  "type": "Feature",
  "properties": {
    "addr:full":"Carrer de Sant Marc, 7 Manresa Barcelona 08241",
    "addr:housenumber":"7",
    "addr:postcode":"08241",
    "addr:street":"Carrer De Sant Marc",
    "iso:country":"ES",
    "sg:address":"Carrer de Sant Marc, 7",
    "sg:city":"Manresa",
    "sg:orig_category":"Construcciones Met\u00c1licas",
    "sg:phone":"+34 938 72 21 25",
    "sg:postcode":"08241",
    "sg:province":"Barcelona",
    "wof:name":"Serralleria I Forjats Manresa S.l.",
    "wof:placetype":"venue"
},
  "geometry": {"coordinates":[1.8235629797,41.7227210999],"type":"Point"}
}