{
  "type": "Feature",
  "properties": {
    "iso:country":"ES",
    "sg:address":"Avda Jota (la), 48",
    "sg:city":"Zaragoza",
    "sg:orig_category":"Tiendas De Grano, Frutas Y Legumbres Secas (al Por Menor)",
    "sg:phone":"+34 976 47 24 42",
    "sg:postcode":"50014",
    "sg:province":"Zaragoza",
    "wof:name":"Doma S.c.",
    "wof:placetype":"venue"
},
  "geometry": {"coordinates":[-0.8577299714,41.6615409851],"type":"Point"}
}