{
  "type": "Feature",
  "properties": {
    "addr:full":"Carrer de Italia, 17 Castellar Valles Barcelona 08211",
    "addr:housenumber":"17",
    "addr:postcode":"08211",
    "addr:street":"Carrer De Italia",
    "iso:country":"ES",
    "sg:address":"Carrer de Italia, 17",
    "sg:city":"Castellar Valles",
    "sg:orig_category":"Supermercados Y Hipermercados",
    "sg:phone":"+34 937 15 89 51",
    "sg:postcode":"08211",
    "sg:province":"Barcelona",
    "sg:website":"www.mercadona.es",
    "wof:name":"Mercadona S.a.",
    "wof:placetype":"venue"
},
  "geometry": {"coordinates":[2.0857300758,41.6151885986],"type":"Point"}
}