{
  "type": "Feature",
  "properties": {
    "addr:full":"Calle de Real, 18 Bollullos Par Condado Huelva 21710",
    "addr:housenumber":"18",
    "addr:postcode":"21710",
    "addr:street":"Calle De Real",
    "iso:country":"ES",
    "sg:address":"Calle de Real, 18",
    "sg:city":"Bollullos Par Condado",
    "sg:orig_category":"Papeler\u00cdas, Librer\u00cdas",
    "sg:phone":"+34 959 41 22 71",
    "sg:postcode":"21710",
    "sg:province":"Huelva",
    "wof:name":"Graficolor S.c.a.",
    "wof:placetype":"venue"
},
  "geometry": {"coordinates":[-6.5367231369,37.3370933533],"type":"Point"}
}