{
  "type": "Feature",
  "properties": {
    "addr:full":"Ctra Andalucia (de), Km. 0043,0 Aranjuez Madrid 28300",
    "addr:postcode":"28300",
    "addr:street":"Ctra Andalucia De Km. 0043,0",
    "iso:country":"ES",
    "sg:address":"Ctra Andalucia (de), Km. 0043,0",
    "sg:city":"Aranjuez",
    "sg:orig_category":"Bebidas",
    "sg:phone":"+34 918 91 61 44",
    "sg:postcode":"28300",
    "sg:province":"Madrid",
    "wof:name":"Compa\u00f1ia Castellana De Bebidas S.a.",
    "wof:placetype":"venue"
},
  "geometry": {"coordinates":[-3.6283650398,40.01171875],"type":"Point"}
}