{
  "type": "Feature",
  "properties": {
    "addr:full":"Carr Bisbe Desbach, 20 Pollen\u00e7a Islas Baleares 07460",
    "addr:housenumber":"20",
    "addr:postcode":"07460",
    "addr:street":"Carr Bisbe Desbach;Islas",
    "iso:country":"ES",
    "sg:address":"Carr Bisbe Desbach, 20",
    "sg:city":"Pollen\u00e7a",
    "sg:orig_category":"Inform\u00c1tica, Ofim\u00c1tica (estudios, Asesor\u00cda, Ingenier\u00cda, Formaci\u00d3n)",
    "sg:phone":"+34 971 53 52 08",
    "sg:postcode":"07460",
    "sg:province":"Islas Baleares",
    "wof:name":"Equip Informatics Pollen\u00e7a S.l.",
    "wof:placetype":"venue"
},
  "geometry": {"coordinates":[3.0166199207,39.8740386963],"type":"Point"}
}