{
  "type": "Feature",
  "properties": {
    "addr:full":"Calle de Doctor Arguelles, 1 Pravia Asturias 33120",
    "addr:housenumber":"1",
    "addr:postcode":"33120",
    "addr:street":"Calle De Doctor Arguelles",
    "iso:country":"ES",
    "sg:address":"Calle de Doctor Arguelles, 1",
    "sg:city":"Pravia",
    "sg:orig_category":"Sociedades, Compa\u00d1\u00cdas Aseguradoras",
    "sg:phone":"+34 985 82 23 37",
    "sg:postcode":"33120",
    "sg:province":"Asturias",
    "wof:name":"Ramon Fernandez Lopez Correduria De Seguros S. A.",
    "wof:placetype":"venue"
},
  "geometry": {"coordinates":[-6.115128994,43.4901008606],"type":"Point"}
}