{
  "type": "Feature",
  "properties": {
    "iso:country":"ES",
    "sg:address":"Calle de San Miguel, 25",
    "sg:city":"Zaragoza",
    "sg:orig_category":"Abogados",
    "sg:phone":"+34 976 30 11 80",
    "sg:postcode":"50001",
    "sg:province":"Zaragoza",
    "wof:name":"Sancho Arroyo Abogados Asociados S.l.",
    "wof:placetype":"venue"
},
  "geometry": {"coordinates":[-0.8788210154,41.6504745483],"type":"Point"}
}