{
  "type": "Feature",
  "properties": {
    "iso:country":"ES",
    "sg:address":"Carrer de Consell De Cent, 35",
    "sg:city":"Barcelona",
    "sg:orig_category":"Puertas Y Portales",
    "sg:phone":"+34 934 26 98 90",
    "sg:postcode":"08014",
    "sg:province":"Barcelona",
    "wof:name":"Donaire Ramirez Dolores",
    "wof:placetype":"venue"
},
  "geometry": {"coordinates":[2.1451179981,41.3763923645],"type":"Point"}
}