{
  "type": "Feature",
  "properties": {
    "addr:full":"Calle de Longuera (la), 27 Longuera Santa Cruz De Tenerife 38418",
    "addr:housenumber":"27",
    "addr:postcode":"38418",
    "addr:street":"Calle De Longuera La",
    "iso:country":"ES",
    "sg:address":"Calle de Longuera (la), 27",
    "sg:city":"Longuera",
    "sg:orig_category":"Ropa Para Se\u00d1oras (al Por Menor)",
    "sg:phone":"+34 922 36 35 27",
    "sg:postcode":"38418",
    "sg:province":"Santa Cruz De Tenerife",
    "wof:name":"Hernandez Gonzalez Amparo Iraida",
    "wof:placetype":"venue"
},
  "geometry": {"coordinates":[-16.5776081085,28.3974990845],"type":"Point"}
}