{
  "type": "Feature",
  "properties": {
    "addr:full":"Av Europa, 55 Hospitalet Llobregat Barcelona 08907",
    "addr:housenumber":"55",
    "addr:postcode":"08907",
    "addr:street":"Av Europa",
    "iso:country":"ES",
    "sg:address":"Av Europa, 55",
    "sg:city":"Hospitalet Llobregat",
    "sg:orig_category":"Confecci\u00d3n De Trajes Para Se\u00d1oras",
    "sg:phone":"+34 933 35 49 09",
    "sg:postcode":"08907",
    "sg:province":"Barcelona",
    "wof:name":"Ayllon De Las Heras Agripina",
    "wof:placetype":"venue"
},
  "geometry": {"coordinates":[2.1138665676,41.3538398743],"type":"Point"}
}