{
  "type": "Feature",
  "properties": {
    "addr:full":"Carr Andoval (d'), 2 Lliria Valencia 46160",
    "addr:housenumber":"2",
    "addr:postcode":"46160",
    "addr:street":"Carr Andoval D '",
    "iso:country":"ES",
    "sg:address":"Carr Andoval (d'), 2",
    "sg:city":"Lliria",
    "sg:orig_category":"Asociaciones De Vecinos, Centros De Juventud",
    "sg:phone":"+34 962 71 71 34",
    "sg:postcode":"46160",
    "sg:province":"Valencia",
    "wof:name":"Promocion Y Desarrollo Camp De Turia",
    "wof:placetype":"venue"
},
  "geometry": {"coordinates":[-0.5919319987,39.6255531311],"type":"Point"}
}