{
  "type": "Feature",
  "properties": {
    "iso:country":"ES",
    "sg:address":"Calle de Doctor Cerda Marti, 8",
    "sg:city":"Hellin",
    "sg:orig_category":"Empresarios",
    "sg:phone":"+34 967 30 37 67",
    "sg:postcode":"02400",
    "sg:province":"Albacete",
    "wof:name":"Infraestructuras Rincon Del Moro S.l.",
    "wof:placetype":"venue"
},
  "geometry": {"coordinates":[-1.6971890926,38.5092697144],"type":"Point"}
}