{
  "type": "Feature",
  "properties": {
    "addr:full":"Cabezuelos, S/n Autol La Rioja 26560",
    "addr:postcode":"26560",
    "addr:street":"Cabezuelos S / N Autol;Rioja",
    "iso:country":"ES",
    "sg:address":"Cabezuelos, S/n",
    "sg:city":"Autol",
    "sg:orig_category":"Confecci\u00d3n De Zapatos",
    "sg:phone":"+34 941 39 05 38",
    "sg:postcode":"26560",
    "sg:province":"La Rioja",
    "wof:name":"Calzados Dami S.l.",
    "wof:placetype":"venue"
},
  "geometry": {"coordinates":[-2.004224062,42.2131233215],"type":"Point"}
}