{
  "type": "Feature",
  "properties": {
    "iso:country":"ES",
    "sg:address":"Avgd De Daniel Gil, 11",
    "sg:city":"Ontinyent",
    "sg:orig_category":"M\u00c9dicos: Estomatolog\u00cda",
    "sg:phone":"+34 962 38 77 58",
    "sg:postcode":"46870",
    "sg:province":"Valencia",
    "wof:name":"Burgoa Palacios Gorka",
    "wof:placetype":"venue"
},
  "geometry": {"coordinates":[-0.6027579904,38.8252334595],"type":"Point"}
}