{
  "type": "Feature",
  "properties": {
    "addr:full":"Calle de Nueva, 2 Lapuebla Labarca \u00c1lava 01306",
    "addr:housenumber":"2",
    "addr:postcode":"01306",
    "addr:street":"Calle De Nueva;Lapuebla Labarca A\u0301Lava",
    "iso:country":"ES",
    "sg:address":"Calle de Nueva, 2",
    "sg:city":"Lapuebla Labarca",
    "sg:orig_category":"Maquinaria Para Industrias Diversas",
    "sg:phone":"+34 945 62 72 48",
    "sg:postcode":"01306",
    "sg:province":"\u00c1lava",
    "wof:name":"Rodriguez Novoa Juan Ignacio",
    "wof:placetype":"venue"
},
  "geometry": {"coordinates":[-2.5733599663,42.4942436218],"type":"Point"}
}