{
  "type": "Feature",
  "properties": {
    "addr:full":"Avda Tenor Fleta, 82 Zaragoza Zaragoza 50007",
    "addr:housenumber":"82",
    "addr:postcode":"50007",
    "addr:street":"Avda Tenor Fleta",
    "iso:country":"ES",
    "sg:address":"Avda Tenor Fleta, 82",
    "sg:city":"Zaragoza",
    "sg:orig_category":"Bisuter\u00cda, Joyer\u00cda, Relojer\u00cda (al Por Menor)",
    "sg:phone":"+34 976 37 20 85",
    "sg:postcode":"50007",
    "sg:province":"Zaragoza",
    "wof:name":"Ferrer Gascon Maria Paz",
    "wof:placetype":"venue"
},
  "geometry": {"coordinates":[-0.8778820038,41.6379203796],"type":"Point"}
}