{
  "type": "Feature",
  "properties": {
    "addr:full":"Calle de Inmaculada Concepcion, S/n Linea De La Concepcion C\u00e1diz 11300",
    "addr:housenumber":"s / n",
    "addr:postcode":"11300",
    "addr:street":"Calle De Inmaculada Concepcion;Ca\u0301Diz",
    "iso:country":"ES",
    "sg:address":"Calle de Inmaculada Concepcion, S/n",
    "sg:city":"Linea De La Concepcion",
    "sg:orig_category":"Carnicer\u00cdas, Carnicer\u00cdas",
    "sg:phone":"+34 956 17 19 40",
    "sg:postcode":"11300",
    "sg:province":"C\u00e1diz",
    "wof:name":"Escobar Miranda Manuel",
    "wof:placetype":"venue"
},
  "geometry": {"coordinates":[-5.353623867,36.1608772278],"type":"Point"}
}