{
  "type": "Feature",
  "properties": {
    "iso:country":"ES",
    "sg:address":"Avda Colmenar Viejo (de), 13",
    "sg:city":"San Sebastian De Los Reyes",
    "sg:orig_category":"Quincaller\u00cda (al Por Menor)",
    "sg:phone":"+34 916 52 70 66",
    "sg:postcode":"28700",
    "sg:province":"Madrid",
    "wof:name":"Ferreteria J.campillo C.b.",
    "wof:placetype":"venue"
},
  "geometry": {"coordinates":[-3.6297330856,40.5456161499],"type":"Point"}
}