{
  "type": "Feature",
  "properties": {
    "addr:full":"Rua Escola, S/n Cee La Coru\u00f1a 15270",
    "addr:housenumber":"s / n",
    "addr:postcode":"15270",
    "addr:street":"Rua Escola;La",
    "iso:country":"ES",
    "sg:address":"Rua Escola, S/n",
    "sg:city":"Cee",
    "sg:orig_category":"Bricolaje, Herramientas (al Por Menor)",
    "sg:phone":"+34 981 74 75 07",
    "sg:postcode":"15270",
    "sg:province":"La Coru\u00f1a",
    "wof:name":"Aspadex",
    "wof:placetype":"venue"
},
  "geometry": {"coordinates":[-9.1917848587,42.9587516785],"type":"Point"}
}