{
  "type": "Feature",
  "properties": {
    "addr:full":"Avda Tolerancia (de La), 5 Villares Madrid 28500",
    "addr:housenumber":"5",
    "addr:postcode":"28500",
    "addr:street":"Avda Tolerancia De La",
    "iso:country":"ES",
    "sg:address":"Avda Tolerancia (de La), 5",
    "sg:city":"Villares",
    "sg:orig_category":"Inmobiliaria (agencias)",
    "sg:phone":"+34 902 36 39 72",
    "sg:postcode":"28500",
    "sg:province":"Madrid",
    "wof:name":"Welcome House S.l.",
    "wof:placetype":"venue"
},
  "geometry": {"coordinates":[-3.4470658302,40.3096122742],"type":"Point"}
}