{
  "type": "Feature",
  "properties": {
    "iso:country":"ES",
    "sg:address":"Las Barreras, 80",
    "sg:city":"Orgiva",
    "sg:orig_category":"Carnicer\u00cdas, Carnicer\u00cdas",
    "sg:phone":"+34 958 78 44 88",
    "sg:postcode":"18400",
    "sg:province":"Granada",
    "wof:name":"Jamones Rosillo S.l.",
    "wof:placetype":"venue"
},
  "geometry": {"coordinates":[-3.4366209507,36.9042015076],"type":"Point"}
}