{
  "type": "Feature",
  "properties": {
    "iso:country":"ES",
    "sg:address":"Calle de Rio, S/n",
    "sg:city":"Langa Duero",
    "sg:orig_category":"Forjas Y Altos Hornos",
    "sg:phone":"+34 975 35 30 39",
    "sg:postcode":"42320",
    "sg:province":"Soria",
    "wof:name":"Almazan Lafuente Vicenta",
    "wof:placetype":"venue"
},
  "geometry": {"coordinates":[-3.4010696411,41.6074714661],"type":"Point"}
}