{
  "type": "Feature",
  "properties": {
    "addr:full":"Avenida De Silvia Mu\u00f1oz, 49 Cuellar Segovia 40200",
    "addr:housenumber":"49",
    "addr:postcode":"40200",
    "addr:street":"Avenida De Silvia Mun\u0303Oz",
    "iso:country":"ES",
    "sg:address":"Avenida De Silvia Mu\u00f1oz, 49",
    "sg:city":"Cuellar",
    "sg:orig_category":"Asociaciones Humanitarias, De Cooperaci\u00d3n, De Acci\u00d3n Social",
    "sg:phone":"+34 921 14 22 18",
    "sg:postcode":"40200",
    "sg:province":"Segovia",
    "wof:name":"Asoc. Padres Defic. Fisicos Intel. Y Men",
    "wof:placetype":"venue"
},
  "geometry": {"coordinates":[-4.335963726,41.3797950745],"type":"Point"}
}