{
  "type": "Feature",
  "properties": {
    "iso:country":"ES",
    "sg:address":"Psaj Puntida, 2",
    "sg:city":"Santander",
    "sg:orig_category":"Centros De Coordinaci\u00d3n",
    "sg:phone":"+34 942 21 15 38",
    "sg:postcode":"39001",
    "sg:province":"Cantabria",
    "wof:name":"Bringas Rodriguez-arango Maria Isabel",
    "wof:placetype":"venue"
},
  "geometry": {"coordinates":[-3.8100090027,43.4614982605],"type":"Point"}
}