{
  "type": "Feature",
  "properties": {
    "iso:country":"ES",
    "sg:address":"Calle de Viena, 2",
    "sg:city":"Toledo",
    "sg:orig_category":"Cerrajer\u00cda, Ferrallista",
    "sg:phone":"+34 925 22 82 27",
    "sg:postcode":"45005",
    "sg:province":"Toledo",
    "wof:name":"Morales Perez Vicente",
    "wof:placetype":"venue"
},
  "geometry": {"coordinates":[-4.05473423,39.8932037354],"type":"Point"}
}