{
  "type": "Feature",
  "properties": {
    "addr:full":"Carrer de Pau Claris, 174 Barcelona Barcelona 08037",
    "addr:housenumber":"174",
    "addr:postcode":"08037",
    "addr:street":"Carrer De Pau Claris",
    "iso:country":"ES",
    "sg:address":"Carrer de Pau Claris, 174",
    "sg:city":"Barcelona",
    "sg:orig_category":"Aparcamientos (infraestructuras, Accesorios)",
    "sg:phone":"+34 932 16 09 42",
    "sg:postcode":"08037",
    "sg:province":"Barcelona",
    "wof:name":"Saba Aparcamientos S.a.",
    "wof:placetype":"venue"
},
  "geometry": {"coordinates":[2.1635429859,41.3956451416],"type":"Point"}
}