{
  "type": "Feature",
  "properties": {
    "addr:full":"Calle de Hernan Cortes, 7 Tauste Zaragoza 50660",
    "addr:housenumber":"7",
    "addr:postcode":"50660",
    "addr:street":"Calle De Hernan Cortes",
    "iso:country":"ES",
    "sg:address":"Calle de Hernan Cortes, 7",
    "sg:city":"Tauste",
    "sg:orig_category":"Importaci\u00d3n",
    "sg:phone":"+34 976 85 49 56",
    "sg:postcode":"50660",
    "sg:province":"Zaragoza",
    "wof:name":"Exportaciones Tauste S.l.",
    "wof:placetype":"venue"
},
  "geometry": {"coordinates":[-1.256270051,41.9164886475],"type":"Point"}
}