{
  "type": "Feature",
  "properties": {
    "addr:full":"Praj Malaguilla, S/n Alhama De Almeria Almer\u00eda 04400",
    "addr:housenumber":"/ n",
    "addr:postcode":"04400",
    "addr:street":"Malaguilla S;Almeri\u0301A",
    "iso:country":"ES",
    "sg:address":"Praj Malaguilla, S/n",
    "sg:city":"Alhama De Almeria",
    "sg:orig_category":"Laboratorios Farmac\u00c9uticos",
    "sg:phone":"+34 950 64 00 38",
    "sg:postcode":"04400",
    "sg:province":"Almer\u00eda",
    "wof:name":"Fernandez Vargas Antonio",
    "wof:placetype":"venue"
},
  "geometry": {"coordinates":[-2.5619790554,36.9550018311],"type":"Point"}
}