{
  "type": "Feature",
  "properties": {
    "addr:full":"C/ Mare De Deu De Les Feixes, 27 Cerdanyola Valles Barcelona 08290",
    "addr:housenumber":"27",
    "addr:postcode":"08290",
    "addr:street":"C / Mare De Deu De Les Feixes;Valles Barcelona",
    "iso:country":"ES",
    "sg:address":"C/ Mare De Deu De Les Feixes, 27",
    "sg:city":"Cerdanyola Valles",
    "sg:orig_category":"Electricidad: Instaladores",
    "sg:phone":"+34 935 80 28 98",
    "sg:postcode":"08290",
    "sg:province":"Barcelona",
    "wof:name":"Inserty Instalacions S.l",
    "wof:placetype":"venue"
},
  "geometry": {"coordinates":[2.1470150948,41.4924812317],"type":"Point"}
}