{
  "type": "Feature",
  "properties": {
    "addr:full":"Prje Chacon, S/n Jimenado Murcia 30708",
    "addr:postcode":"30708",
    "addr:street":"Chacon S / N",
    "iso:country":"ES",
    "sg:address":"Prje Chacon, S/n",
    "sg:city":"Jimenado",
    "sg:orig_category":"Aparatos E Instalaci\u00d3n De Regad\u00cdos",
    "sg:phone":"+34 968 16 04 93",
    "sg:postcode":"30708",
    "sg:province":"Murcia",
    "sg:website":"www.cajamurcia.es",
    "wof:name":"Comunidad Regantes Campo De Cartagena",
    "wof:placetype":"venue"
},
  "geometry": {"coordinates":[-1.0358489752,37.7589912415],"type":"Point"}
}