{
  "type": "Feature",
  "properties": {
    "addr:full":"Avda Gran Via, 8 Vigo Pontevedra 36203",
    "addr:housenumber":"8",
    "addr:postcode":"36203",
    "addr:street":"Avda Gran Via",
    "iso:country":"ES",
    "sg:address":"Avda Gran Via, 8",
    "sg:city":"Vigo",
    "sg:orig_category":"Bisuter\u00cda, Joyer\u00cda, Relojer\u00cda (al Por Menor)",
    "sg:phone":"+34 986 43 26 77",
    "sg:postcode":"36203",
    "sg:province":"Pontevedra",
    "sg:website":"www.tous.es",
    "wof:name":"Tous Joyeros Vigo S.l.",
    "wof:placetype":"venue"
},
  "geometry": {"coordinates":[-8.7169084549,42.2341079712],"type":"Point"}
}