{
  "type": "Feature",
  "properties": {
    "iso:country":"ES",
    "sg:address":"Cmno Sanatorio Maritimo Del, 13",
    "sg:city":"Torremolinos",
    "sg:orig_category":"Inmobiliaria (agencias)",
    "sg:phone":"+34 952 37 80 31",
    "sg:postcode":"29620",
    "sg:province":"M\u00e1laga",
    "wof:name":"Inversiones De Mercado Inmobiliario S.l.",
    "wof:placetype":"venue"
},
  "geometry": {"coordinates":[-4.491174221,36.6394615173],"type":"Point"}
}