{
  "type": "Feature",
  "properties": {
    "addr:full":"Avda Parque (del) (bloques), 1 Manzanares Ciudad Real 13200",
    "addr:housenumber":"1",
    "addr:postcode":"13200",
    "addr:street":"Avda Parque Del Bloques",
    "iso:country":"ES",
    "sg:address":"Avda Parque (del) (bloques), 1",
    "sg:city":"Manzanares",
    "sg:orig_category":"Fabricaci\u00d3n De Distribuidores Autom\u00c1ticos",
    "sg:phone":"+34 926 61 46 26",
    "sg:postcode":"13200",
    "sg:province":"Ciudad Real",
    "wof:name":"Vilches Delgado Rafael",
    "wof:placetype":"venue"
},
  "geometry": {"coordinates":[-3.3605530262,39.0008506775],"type":"Point"}
}