{
  "type": "Feature",
  "properties": {
    "iso:country":"ES",
    "sg:address":"Calle de Alfonso Vi, 78",
    "sg:city":"Miranda Ebro",
    "sg:orig_category":"Molduras, Junquillos, Listones Y Molduras Perforadas",
    "sg:phone":"+34 947 31 20 54",
    "sg:postcode":"09200",
    "sg:province":"Burgos",
    "wof:name":"Ortiz Gomez Antonio",
    "wof:placetype":"venue"
},
  "geometry": {"coordinates":[-2.9402532578,42.6875457764],"type":"Point"}
}