{
  "type": "Feature",
  "properties": {
    "iso:country":"ES",
    "sg:address":"Avenida De Zaragoza, S/n",
    "sg:city":"Vinaros",
    "sg:orig_category":"Agentes, Concesionarios Y Sucursales De Veh\u00cdculos",
    "sg:phone":"+34 964 40 15 15",
    "sg:postcode":"12500",
    "sg:province":"Castell\u00f3n",
    "wof:name":"Castejon Gomez Angel",
    "wof:placetype":"venue"
},
  "geometry": {"coordinates":[0.4749450088,40.4711990356],"type":"Point"}
}