{
  "type": "Feature",
  "properties": {
    "iso:country":"ES",
    "sg:address":"Calle de Mayor, 3",
    "sg:city":"Pioz",
    "sg:orig_category":"Molduras, Junquillos, Listones Y Molduras Perforadas",
    "sg:phone":"+34 949 27 21 62",
    "sg:postcode":"19162",
    "sg:province":"Guadalajara",
    "wof:name":"Paez Espartosa Juan Luis",
    "wof:placetype":"venue"
},
  "geometry": {"coordinates":[-3.1759250164,40.4646873474],"type":"Point"}
}