{
  "type": "Feature",
  "properties": {
    "addr:full":"Avda Espa\u00d1a, 151 Segorbe Castell\u00f3n 12400",
    "addr:housenumber":"151",
    "addr:postcode":"12400",
    "addr:street":"Avda Espan\u0303A",
    "iso:country":"ES",
    "sg:address":"Avda Espa\u00d1a, 151",
    "sg:city":"Segorbe",
    "sg:orig_category":"Herradores, Herreros, Carreteros",
    "sg:phone":"+34 964 13 20 10",
    "sg:postcode":"12400",
    "sg:province":"Castell\u00f3n",
    "wof:name":"Montalban Gil Rosario",
    "wof:placetype":"venue"
},
  "geometry": {"coordinates":[-0.4934689999,39.8479385376],"type":"Point"}
}