{
  "type": "Feature",
  "properties": {
    "iso:country":"ES",
    "sg:address":"Calle de Tinajas, 12",
    "sg:city":"Coru\u00d1a",
    "sg:orig_category":"Asociaciones Y Clubs Deportivos",
    "sg:phone":"+34 981 21 23 02",
    "sg:postcode":"15001",
    "sg:province":"La Coru\u00f1a",
    "wof:name":"Club Deportivo Ciudad",
    "wof:placetype":"venue"
},
  "geometry": {"coordinates":[-8.3915405273,43.3695526123],"type":"Point"}
}