{
  "type": "Feature",
  "properties": {
    "iso:country":"ES",
    "sg:address":"Avda Andalucia, 36",
    "sg:city":"Jaen",
    "sg:orig_category":"Loter\u00cda Y T\u00d3mbola",
    "sg:phone":"+34 953 22 08 48",
    "sg:postcode":"23006",
    "sg:province":"Ja\u00e9n",
    "wof:name":"Pardo Roa Teresa Eufemia",
    "wof:placetype":"venue"
},
  "geometry": {"coordinates":[-3.7964890003,37.7777786255],"type":"Point"}
}