{
  "type": "Feature",
  "properties": {
    "addr:full":"Carr Humbert Torres, 2 Lleida Lleida 25008",
    "addr:housenumber":"2",
    "addr:postcode":"25008",
    "addr:street":"Carr Humbert Torres",
    "iso:country":"ES",
    "sg:address":"Carr Humbert Torres, 2",
    "sg:city":"Lleida",
    "sg:orig_category":"Cajas De Ahorro",
    "sg:phone":"+34 973 22 56 81",
    "sg:postcode":"25008",
    "sg:province":"Lleida",
    "sg:website":"www.bancaja.es",
    "wof:name":"Caja De Ahorros De Valencia Castellon Y Alicante",
    "wof:placetype":"venue"
},
  "geometry": {"coordinates":[0.621769011,41.6213188171],"type":"Point"}
}