{
  "type": "Feature",
  "properties": {
    "addr:full":"Carrer de Bruc, 46 Hospitalet Llobregat Barcelona 08901",
    "addr:housenumber":"46",
    "addr:postcode":"08901",
    "addr:street":"Carrer De Bruc",
    "iso:country":"ES",
    "sg:address":"Carrer de Bruc, 46",
    "sg:city":"Hospitalet Llobregat",
    "sg:orig_category":"Molduras, Junquillos, Listones Y Molduras Perforadas",
    "sg:phone":"+34 933 38 67 51",
    "sg:postcode":"08901",
    "sg:province":"Barcelona",
    "wof:name":"J.d. Dos S.c.p.",
    "wof:placetype":"venue"
},
  "geometry": {"coordinates":[2.0992670059,41.362651825],"type":"Point"}
}