{
  "type": "Feature",
  "properties": {
    "addr:full":"Calle de Zugastinobia, 10 Bilbao Vizcaya 48012",
    "addr:housenumber":"10",
    "addr:postcode":"48012",
    "addr:street":"Calle De Zugastinobia",
    "iso:country":"ES",
    "sg:address":"Calle de Zugastinobia, 10",
    "sg:city":"Bilbao",
    "sg:orig_category":"Molduras, Junquillos, Listones Y Molduras Perforadas",
    "sg:phone":"+34 944 21 66 45",
    "sg:postcode":"48012",
    "sg:province":"Vizcaya",
    "wof:name":"Phone Euskadi S. L.",
    "wof:placetype":"venue"
},
  "geometry": {"coordinates":[-2.941947937,43.2571220398],"type":"Point"}
}