{
  "type": "Feature",
  "properties": {
    "addr:full":"Crt. G. Sevilla, 47 Almendralejo Badajoz 06200",
    "addr:housenumber":"47",
    "addr:postcode":"06200",
    "addr:street":"Crt. G. Sevilla",
    "iso:country":"ES",
    "sg:address":"Crt. G. Sevilla, 47",
    "sg:city":"Almendralejo",
    "sg:orig_category":"Comercio De Piezas De Recambio Y De Accesorios De Veh\u00cdculos, Veh\u00cdculos Industriales",
    "sg:phone":"+34 924 66 59 54",
    "sg:postcode":"06200",
    "sg:province":"Badajoz",
    "wof:name":"Recambios Marquez Hermanos C.b.",
    "wof:placetype":"venue"
},
  "geometry": {"coordinates":[-6.3891019821,38.6721000671],"type":"Point"}
}