{
  "type": "Feature",
  "properties": {
    "iso:country":"ES",
    "sg:address":"Calle de Barco, 46",
    "sg:city":"San Bartolome Pinares",
    "sg:orig_category":"Cerrajer\u00cda, Ferrallista",
    "sg:phone":"+34 920 27 02 74",
    "sg:postcode":"05267",
    "sg:province":"\u00c1vila",
    "wof:name":"Parro Martin Antonio",
    "wof:placetype":"venue"
},
  "geometry": {"coordinates":[-4.537375927,40.544708252],"type":"Point"}
}