{
  "type": "Feature",
  "properties": {
    "iso:country":"ES",
    "sg:address":"Calle de D(campollano), 13",
    "sg:city":"Albacete",
    "sg:orig_category":"Calefacci\u00d3n Central: Material (fabricaci\u00d3n, Al Por Mayor)",
    "sg:phone":"+34 967 19 21 79",
    "sg:postcode":"02006",
    "sg:province":"Albacete",
    "sg:website":"www.salvadorescoda.com",
    "wof:name":"Salvador Escoda S.a.",
    "wof:placetype":"venue"
},
  "geometry": {"coordinates":[-1.9363039732,39.0603866577],"type":"Point"}
}