{
  "type": "Feature",
  "properties": {
    "addr:full":"Rua Xavier Prado Lameiro, 13 Ourense Ourense 32002",
    "addr:housenumber":"13",
    "addr:postcode":"32002",
    "addr:street":"Rua Xavier Prado Lameiro",
    "iso:country":"ES",
    "sg:address":"Rua Xavier Prado Lameiro, 13",
    "sg:city":"Ourense",
    "sg:orig_category":"Molduras, Junquillos, Listones Y Molduras Perforadas",
    "sg:phone":"+34 988 22 10 39",
    "sg:postcode":"32002",
    "sg:province":"Ourense",
    "wof:name":"Pacios Miguel Antonio",
    "wof:placetype":"venue"
},
  "geometry": {"coordinates":[-7.8742241859,42.3407249451],"type":"Point"}
}