{
  "type": "Feature",
  "properties": {
    "addr:full":"Avda Doutor Touron, 40 Vilagarcia Pontevedra 36600",
    "addr:housenumber":"40",
    "addr:postcode":"36600",
    "addr:street":"Avda Doutor Touron",
    "iso:country":"ES",
    "sg:address":"Avda Doutor Touron, 40",
    "sg:city":"Vilagarcia",
    "sg:orig_category":"Alimentaci\u00d3n Animal (fabricaci\u00d3n, Al Por Mayor)",
    "sg:phone":"+34 986 50 80 05",
    "sg:postcode":"36600",
    "sg:province":"Pontevedra",
    "wof:name":"Reiriz Oubi\u00f1a Jose Benito",
    "wof:placetype":"venue"
},
  "geometry": {"coordinates":[-8.7652978897,42.5917396545],"type":"Point"}
}