{
  "type": "Feature",
  "properties": {
    "iso:country":"ES",
    "sg:address":"Calle de Santander, 1",
    "sg:city":"Colindres",
    "sg:orig_category":"Reparaciones Y Remolcado De Veh\u00cdculos",
    "sg:phone":"+34 942 65 02 40",
    "sg:postcode":"39750",
    "sg:province":"Cantabria",
    "wof:name":"Pacheco Ahedo Manuel",
    "wof:placetype":"venue"
},
  "geometry": {"coordinates":[-3.4486660957,43.396194458],"type":"Point"}
}