{
  "type": "Feature",
  "properties": {
    "addr:full":"Pla\u00c7 Pais Valencia, 30 Picanya Valencia 46210",
    "addr:housenumber":"30",
    "addr:postcode":"46210",
    "addr:street":"Valencia",
    "iso:country":"ES",
    "sg:address":"Pla\u00c7 Pais Valencia, 30",
    "sg:city":"Picanya",
    "sg:orig_category":"Cajas De Ahorro",
    "sg:phone":"+34 961 59 12 75",
    "sg:postcode":"46210",
    "sg:province":"Valencia",
    "sg:website":"www.bancaja.es",
    "wof:name":"Caja De Ahorros De Valencia Castellon Y Alicante",
    "wof:placetype":"venue"
},
  "geometry": {"coordinates":[-0.4355089962,39.4355392456],"type":"Point"}
}