{
  "type": "Feature",
  "properties": {
    "iso:country":"ES",
    "sg:address":"Carrer de Enten\u00c7a, 35",
    "sg:city":"Barcelona",
    "sg:orig_category":"Perfumer\u00cda (al Por Menor)",
    "sg:phone":"+34 934 24 61 92",
    "sg:postcode":"08015",
    "sg:province":"Barcelona",
    "wof:name":"Correa Sanchez Salvador",
    "wof:placetype":"venue"
},
  "geometry": {"coordinates":[2.1538639069,41.3769836426],"type":"Point"}
}