{
  "type": "Feature",
  "properties": {
    "addr:full":"Rua Areal (do), 59 Lalin Pontevedra 36500",
    "addr:housenumber":"59",
    "addr:postcode":"36500",
    "addr:street":"Rua Areal Do",
    "iso:country":"ES",
    "sg:address":"Rua Areal (do), 59",
    "sg:city":"Lalin",
    "sg:orig_category":"M\u00c9dicos: Geriatr\u00cda, Gerontolog\u00cda (enfermedades De La Tercera Edad)",
    "sg:phone":"+34 986 78 06 54",
    "sg:postcode":"36500",
    "sg:province":"Pontevedra",
    "wof:name":"Senra Gamallo Maria Jesus",
    "wof:placetype":"venue"
},
  "geometry": {"coordinates":[-8.1106138229,42.6577606201],"type":"Point"}
}