{
  "type": "Feature",
  "properties": {
    "addr:full":"Calle de Infantas, 4 Alcorcon Madrid 28922",
    "addr:housenumber":"4",
    "addr:postcode":"28922",
    "addr:street":"Calle De Infantas",
    "iso:country":"ES",
    "sg:address":"Calle de Infantas, 4",
    "sg:city":"Alcorcon",
    "sg:orig_category":"\u00d3ptica: Instrumentos (fabricaci\u00d3n)",
    "sg:phone":"+34 916 44 29 68",
    "sg:postcode":"28922",
    "sg:province":"Madrid",
    "wof:name":"Resaraq S.l.",
    "wof:placetype":"venue"
},
  "geometry": {"coordinates":[-3.8319723606,40.346912384],"type":"Point"}
}