{
  "type": "Feature",
  "properties": {
    "addr:full":"Atvia De Logro\u00f1o, Km. 0245,0 Zaragoza Zaragoza 50011",
    "addr:postcode":"50011",
    "addr:street":"Logron\u0303O Km. 0245,0",
    "iso:country":"ES",
    "sg:address":"Atvia De Logro\u00f1o, Km. 0245,0",
    "sg:city":"Zaragoza",
    "sg:orig_category":"Colchones (fabricaci\u00d3n, Al Por Mayor, Al Por Menor)",
    "sg:phone":"+34 976 32 17 00",
    "sg:postcode":"50011",
    "sg:province":"Zaragoza",
    "sg:website":"www.beds.es",
    "wof:name":"Espa\u00f1ola Del Descanso S.a.",
    "wof:placetype":"venue"
},
  "geometry": {"coordinates":[-0.9913589954,41.662853241],"type":"Point"}
}