{
  "type": "Feature",
  "properties": {
    "addr:full":"Urb San Jeronimo, S/n San Jeronimo Santa Cruz De Tenerife 38312",
    "addr:housenumber":"s / n",
    "addr:postcode":"38312",
    "addr:street":"San Jeronimo;Jeronimo",
    "iso:country":"ES",
    "sg:address":"Urb San Jeronimo, S/n",
    "sg:city":"San Jeronimo",
    "sg:orig_category":"Agentes, Concesionarios Y Sucursales De Veh\u00cdculos",
    "sg:phone":"+34 902 19 34 86",
    "sg:postcode":"38312",
    "sg:province":"Santa Cruz De Tenerife",
    "wof:name":"Palma Canaria S.a.",
    "wof:placetype":"venue"
},
  "geometry": {"coordinates":[-16.5448322296,28.3948001862],"type":"Point"}
}