{
  "type": "Feature",
  "properties": {
    "iso:country":"ES",
    "sg:address":"Calle de Ignacio Herrero Garralda, 5",
    "sg:city":"Corredoria",
    "sg:orig_category":"Muebles Y Accesorios Para Cocinas Y Cuartos De Ba\u00d1o (al Por Menor)",
    "sg:phone":"+34 985 11 94 27",
    "sg:postcode":"33011",
    "sg:province":"Asturias",
    "wof:name":"Sanchez Garcia Enrique Florentino",
    "wof:placetype":"venue"
},
  "geometry": {"coordinates":[-5.8210020065,43.3860702515],"type":"Point"}
}