{
  "type": "Feature",
  "properties": {
    "iso:country":"ES",
    "sg:address":"Avda Cedros, 30",
    "sg:city":"Salamanca",
    "sg:orig_category":"Caf\u00c9s (al Por Menor)",
    "sg:phone":"+34 923 24 92 73",
    "sg:postcode":"37004",
    "sg:province":"Salamanca",
    "wof:name":"Gomez Hernandez Jose",
    "wof:placetype":"venue"
},
  "geometry": {"coordinates":[-5.6509070396,40.9753112793],"type":"Point"}
}