{
  "type": "Feature",
  "properties": {
    "addr:full":"Raval Del Castell, 46 Valls Tarragona 43800",
    "addr:housenumber":"46",
    "addr:postcode":"43800",
    "addr:street":"Raval Del Castell",
    "iso:country":"ES",
    "sg:address":"Raval Del Castell, 46",
    "sg:city":"Valls",
    "sg:orig_category":"Transportes Internacionales",
    "sg:phone":"+34 977 60 12 32",
    "sg:postcode":"43800",
    "sg:province":"Tarragona",
    "wof:name":"Ramos Peral Alfonso",
    "wof:placetype":"venue"
},
  "geometry": {"coordinates":[1.2592509985,41.2979469299],"type":"Point"}
}