{
  "type": "Feature",
  "properties": {
    "iso:country":"ES",
    "sg:address":"Pintor Maeztu, 4",
    "sg:city":"Iru\u00f1a",
    "sg:orig_category":"M\u00c9dicos: Estomatolog\u00cda",
    "sg:phone":"+34 948 17 26 17",
    "sg:postcode":"31008",
    "sg:province":"Navarra",
    "wof:name":"Sada Garralda Maria Del Pilar",
    "wof:placetype":"venue"
},
  "geometry": {"coordinates":[-1.6588959694,42.8073005676],"type":"Point"}
}