{
  "type": "Feature",
  "properties": {
    "addr:full":"Calle de Emperador, 42 Burgos Burgos 09003",
    "addr:housenumber":"42",
    "addr:postcode":"09003",
    "addr:street":"Calle De Emperador",
    "iso:country":"ES",
    "sg:address":"Calle de Emperador, 42",
    "sg:city":"Burgos",
    "sg:orig_category":"Iglesia Cat\u00d3lica",
    "sg:phone":"+34 947 20 54 72",
    "sg:postcode":"09003",
    "sg:province":"Burgos",
    "wof:name":"Parroquia De San Pedro De La Fuente",
    "wof:placetype":"venue"
},
  "geometry": {"coordinates":[-3.7135989666,42.3420715332],"type":"Point"}
}