{
  "type": "Feature",
  "properties": {
    "addr:full":"Cllo Mellizo, 4 Madrid Madrid 28005",
    "addr:housenumber":"4",
    "addr:postcode":"28005",
    "addr:street":"Mellizo",
    "iso:country":"ES",
    "sg:address":"Cllo Mellizo, 4",
    "sg:city":"Madrid",
    "sg:orig_category":"Comisarios",
    "sg:phone":"+34 915 28 14 32",
    "sg:postcode":"28005",
    "sg:province":"Madrid",
    "wof:name":"Gutierrez Aguado Maria Cruz",
    "wof:placetype":"venue"
},
  "geometry": {"coordinates":[-3.709233284,40.4077301025],"type":"Point"}
}