{
  "type": "Feature",
  "properties": {
    "iso:country":"ES",
    "sg:address":"Avda Pais Valencia (del), 45",
    "sg:city":"Onda",
    "sg:orig_category":"Abogados",
    "sg:phone":"+34 964 77 00 89",
    "sg:postcode":"12200",
    "sg:province":"Castell\u00f3n",
    "wof:name":"Palasi Gimeno Salvador",
    "wof:placetype":"venue"
},
  "geometry": {"coordinates":[-0.2624199986,39.9650535583],"type":"Point"}
}