{
  "type": "Feature",
  "properties": {
    "addr:full":"Calle de Almeria, S/n Turre Almer\u00eda 04639",
    "addr:housenumber":"s",
    "addr:postcode":"04639",
    "addr:street":"Calle De Almeria;/ N Turre Almeri\u0301A",
    "iso:country":"ES",
    "sg:address":"Calle de Almeria, S/n",
    "sg:city":"Turre",
    "sg:orig_category":"Papeler\u00cdas, Librer\u00cdas",
    "sg:phone":"+34 950 47 94 18",
    "sg:postcode":"04639",
    "sg:province":"Almer\u00eda",
    "wof:name":"Alias Sanchez Maria Del Carmen",
    "wof:placetype":"venue"
},
  "geometry": {"coordinates":[-1.9004081488,37.1504898071],"type":"Point"}
}