{
  "type": "Feature",
  "properties": {
    "addr:full":"Barr Serra (la), S/n Pacs Del Penedes Barcelona 08796",
    "addr:housenumber":"s",
    "addr:postcode":"08796",
    "addr:street":"/ N;Barcelona",
    "iso:country":"ES",
    "sg:address":"Barr Serra (la), S/n",
    "sg:city":"Pacs Del Penedes",
    "sg:orig_category":"Locales Y Clases De Danza",
    "sg:phone":"+34 938 17 06 36",
    "sg:postcode":"08796",
    "sg:province":"Barcelona",
    "wof:name":"Escola De Ball De Salo  Josep I Rosa Maria",
    "wof:placetype":"venue"
},
  "geometry": {"coordinates":[1.6594820023,41.3621406555],"type":"Point"}
}