{
  "type": "Feature",
  "properties": {
    "iso:country":"ES",
    "sg:address":"Calle de Juan Ramon Jimenez, 24",
    "sg:city":"Valencia",
    "sg:orig_category":"Iglesia Cat\u00d3lica",
    "sg:phone":"+34 963 74 25 62",
    "sg:postcode":"46006",
    "sg:province":"Valencia",
    "wof:name":"Parroquia Santa Cecilia",
    "wof:placetype":"venue"
},
  "geometry": {"coordinates":[-0.3757809997,39.4543190002],"type":"Point"}
}