{
  "type": "Feature",
  "properties": {
    "addr:full":"P. Esparto, S/n Cuevas Almanzora Almer\u00eda 04610",
    "addr:housenumber":"s / n",
    "addr:postcode":"04610",
    "addr:street":"P. Esparto;Almeri\u0301A",
    "iso:country":"ES",
    "sg:address":"P. Esparto, S/n",
    "sg:city":"Cuevas Almanzora",
    "sg:orig_category":"Inmobiliaria (agencias)",
    "sg:phone":"+34 950 16 82 67",
    "sg:postcode":"04610",
    "sg:province":"Almer\u00eda",
    "wof:name":"Almer-invest S.l.",
    "wof:placetype":"venue"
},
  "geometry": {"coordinates":[-1.6951677799,37.3309898376],"type":"Point"}
}