{
  "type": "Feature",
  "properties": {
    "iso:country":"ES",
    "sg:address":"Calle de Mar (del), 28",
    "sg:city":"Torre Mar",
    "sg:orig_category":"Electrodom\u00c9sticos (al Por Menor)",
    "sg:phone":"+34 952 54 13 42",
    "sg:postcode":"29740",
    "sg:province":"M\u00e1laga",
    "wof:name":"Cafe-bar Centro S.c.",
    "wof:placetype":"venue"
},
  "geometry": {"coordinates":[-4.3591890335,36.7190475464],"type":"Point"}
}