{
  "type": "Feature",
  "properties": {
    "addr:full":"Calle de Antonio Maria Manrique, S/n Palmas De Gran Canaria Las Palmas 35011",
    "addr:housenumber":"s",
    "addr:postcode":"35011",
    "addr:street":"Calle De Antonio Maria Manrique;/ N",
    "iso:country":"ES",
    "sg:address":"Calle de Antonio Maria Manrique, S/n",
    "sg:city":"Palmas De Gran Canaria",
    "sg:orig_category":"Ense\u00d1anza Secundaria: Colegios Y Escuelas Privadas",
    "sg:phone":"+34 928 26 33 93",
    "sg:postcode":"35011",
    "sg:province":"Las Palmas",
    "wof:name":"Gobierno De Canarias",
    "wof:placetype":"venue"
},
  "geometry": {"coordinates":[-15.4372320175,28.1257038116],"type":"Point"}
}