{
  "type": "Feature",
  "properties": {
    "addr:full":"Reis-padri\u00f1an, 26 Reis Pontevedra 36966",
    "addr:housenumber":"26",
    "addr:postcode":"36966",
    "addr:street":"Reis-Padrin\u0303An",
    "iso:country":"ES",
    "sg:address":"Reis-padri\u00f1an, 26",
    "sg:city":"Reis",
    "sg:orig_category":"Promotores Constructores",
    "sg:phone":"+34 986 72 31 11",
    "sg:postcode":"36966",
    "sg:province":"Pontevedra",
    "wof:name":"Promotora Atures S.l.",
    "wof:placetype":"venue"
},
  "geometry": {"coordinates":[-8.7881994247,42.3987045288],"type":"Point"}
}