{
  "type": "Feature",
  "properties": {
    "iso:country":"ES",
    "sg:address":"Avda Cantabrico, 21",
    "sg:city":"Badia Del Valles",
    "sg:orig_category":"Peluquer\u00cdas, Peluquer\u00cda Mixta",
    "sg:phone":"+34 937 18 99 03",
    "sg:postcode":"08214",
    "sg:province":"Barcelona",
    "wof:name":"Campillo Soria Arancha",
    "wof:placetype":"venue"
},
  "geometry": {"coordinates":[2.116617918,41.5098190308],"type":"Point"}
}