{
  "type": "Feature",
  "properties": {
    "addr:full":"Carrer de Aiguamarina, 10 Arenal Islas Baleares 07600",
    "addr:housenumber":"10",
    "addr:postcode":"07600",
    "addr:street":"Carrer De Aiguamarina",
    "iso:country":"ES",
    "sg:address":"Carrer de Aiguamarina, 10",
    "sg:city":"Arenal",
    "sg:orig_category":"Art\u00cdculos De Regalo (al Por Menor)",
    "sg:phone":"+34 971 49 15 14",
    "sg:postcode":"07600",
    "sg:province":"Islas Baleares",
    "wof:name":"Molina Lorenzo Antonio",
    "wof:placetype":"venue"
},
  "geometry": {"coordinates":[2.7505679131,39.5100631714],"type":"Point"}
}