{
  "type": "Feature",
  "properties": {
    "iso:country":"ES",
    "sg:address":"Psaj Gonzalez Del Campo, 2",
    "sg:city":"Cordoba",
    "sg:orig_category":"Carnicer\u00cdas, Carnicer\u00cdas",
    "sg:phone":"+34 957 25 48 99",
    "sg:postcode":"14014",
    "sg:province":"C\u00f3rdoba",
    "wof:name":"Martinez Rios Miguel",
    "wof:placetype":"venue"
},
  "geometry": {"coordinates":[-4.7544341087,37.8938522339],"type":"Point"}
}