{
  "type": "Feature",
  "properties": {
    "iso:country":"ES",
    "sg:address":"Avda Algorta, 16",
    "sg:city":"Algorta",
    "sg:orig_category":"Inform\u00c1tica: Mantenimiento Y Reparaci\u00d3n De Ordenadores",
    "sg:phone":"+34 944 89 32 00",
    "sg:postcode":"48...",
    "sg:province":"Vizcaya",
    "wof:name":"International Business Machines S.a.e.",
    "wof:placetype":"venue"
},
  "geometry": {"coordinates":[-3.0088560581,43.3407745361],"type":"Point"}
}