{
  "type": "Feature",
  "properties": {
    "addr:full":"Carrer de Doctor Manuel Riera, 5 Esplugues Llobregat Barcelona 08950",
    "addr:housenumber":"5",
    "addr:postcode":"08950",
    "addr:street":"Carrer De Doctor Manuel Riera",
    "iso:country":"ES",
    "sg:address":"Carrer de Doctor Manuel Riera, 5",
    "sg:city":"Esplugues Llobregat",
    "sg:orig_category":"Doctores En Medicina",
    "sg:phone":"+34 933 72 66 07",
    "sg:postcode":"08950",
    "sg:province":"Barcelona",
    "wof:name":"Cervera Manuel Teresa",
    "wof:placetype":"venue"
},
  "geometry": {"coordinates":[2.0856280327,41.3744812012],"type":"Point"}
}