{
  "type": "Feature",
  "properties": {
    "addr:full":"Avda Blasco Iba\u00d1ez, 104 Valencia Valencia 46021",
    "addr:housenumber":"104",
    "addr:postcode":"46021",
    "addr:street":"Avda Blasco Iban\u0303Ez",
    "iso:country":"ES",
    "sg:address":"Avda Blasco Iba\u00d1ez, 104",
    "sg:city":"Valencia",
    "sg:orig_category":"M\u00c9dicos: Cirug\u00cda Ortop\u00c9dica Y Traumatolog\u00cda",
    "sg:phone":"+34 963 93 19 62",
    "sg:postcode":"46021",
    "sg:province":"Valencia",
    "wof:name":"Risent Martinez Francisco",
    "wof:placetype":"venue"
},
  "geometry": {"coordinates":[-0.3492490053,39.4738426208],"type":"Point"}
}