{
  "type": "Feature",
  "properties": {
    "addr:full":"Calle de Colon, 41 Castellar Ja\u00e9n 23260",
    "addr:housenumber":"41",
    "addr:postcode":"23260",
    "addr:street":"Calle De Colon",
    "iso:country":"ES",
    "sg:address":"Calle de Colon, 41",
    "sg:city":"Castellar",
    "sg:orig_category":"Agentes Generales De Seguros",
    "sg:phone":"+34 953 40 03 21",
    "sg:postcode":"23260",
    "sg:province":"Ja\u00e9n",
    "wof:name":"Gonzalez Ramos Dolores",
    "wof:placetype":"venue"
},
  "geometry": {"coordinates":[-3.132424593,38.253162384],"type":"Point"}
}