{
  "type": "Feature",
  "properties": {
    "addr:full":"Carr Mossen Alcover, 16 Esporles Islas Baleares 07190",
    "addr:housenumber":"16",
    "addr:postcode":"07190",
    "addr:street":"Carr Mossen Alcover",
    "iso:country":"ES",
    "sg:address":"Carr Mossen Alcover, 16",
    "sg:city":"Esporles",
    "sg:orig_category":"Promotores Constructores",
    "sg:phone":"+34 971 61 12 17",
    "sg:postcode":"07190",
    "sg:province":"Islas Baleares",
    "wof:name":"Promoteix S.l.",
    "wof:placetype":"venue"
},
  "geometry": {"coordinates":[2.579253912,39.665977478],"type":"Point"}
}