{
  "type": "Feature",
  "properties": {
    "iso:country":"ES",
    "sg:address":"Ctra. Vitoria-boveda, S/n",
    "sg:city":"Pobes",
    "sg:orig_category":"Sanatorios M\u00c9dico",
    "sg:phone":"+34 945 36 21 12",
    "sg:postcode":"01420",
    "sg:province":"\u00c1lava",
    "wof:name":"Ayuntamiento De Ribera Alta",
    "wof:placetype":"venue"
},
  "geometry": {"coordinates":[-2.9096889496,42.8032951355],"type":"Point"}
}