{
  "type": "Feature",
  "properties": {
    "iso:country":"ES",
    "sg:address":"Calle de Gabriel Y Galan, 4",
    "sg:city":"Tamames",
    "sg:orig_category":"Sociedades, Compa\u00d1\u00cdas Aseguradoras",
    "sg:phone":"+34 923 44 90 75",
    "sg:postcode":"37600",
    "sg:province":"Salamanca",
    "sg:website":"www.mapfre.com",
    "wof:name":"Mapfre Servicios De Informatica S.a.",
    "wof:placetype":"venue"
},
  "geometry": {"coordinates":[-6.1067547798,40.6566238403],"type":"Point"}
}