{
  "type": "Feature",
  "properties": {
    "iso:country":"ES",
    "sg:address":"Calle de Principe De Vergara, 55",
    "sg:city":"Madrid",
    "sg:orig_category":"Arquitectos",
    "sg:phone":"+34 914 11 59 61",
    "sg:postcode":"28006",
    "sg:province":"Madrid",
    "wof:name":"Gutierrez-ambrossi Robles Miguel Hernan",
    "wof:placetype":"venue"
},
  "geometry": {"coordinates":[-3.679680109,40.4328956604],"type":"Point"}
}