{
  "type": "Feature",
  "properties": {
    "addr:full":"Calle de Santa Marina, 9 Cuellar Segovia 40200",
    "addr:housenumber":"9",
    "addr:postcode":"40200",
    "addr:street":"Calle De Santa Marina",
    "iso:country":"ES",
    "sg:address":"Calle de Santa Marina, 9",
    "sg:city":"Cuellar",
    "sg:orig_category":"Iglesia Cat\u00d3lica",
    "sg:phone":"+34 921 14 01 74",
    "sg:postcode":"40200",
    "sg:province":"Segovia",
    "wof:name":"Obispado Segovia",
    "wof:placetype":"venue"
},
  "geometry": {"coordinates":[-4.3138360977,41.4001312256],"type":"Point"}
}