{
  "type": "Feature",
  "properties": {
    "iso:country":"ES",
    "sg:address":"Avda Mungialde Etorbidea, 1",
    "sg:city":"San Esteban Derio",
    "sg:orig_category":"Bancos",
    "sg:phone":"+34 944 54 00 39",
    "sg:postcode":"48160",
    "sg:province":"Vizcaya",
    "wof:name":"Banco Espa\u00d1ol De Credito S.a.",
    "wof:placetype":"venue"
},
  "geometry": {"coordinates":[-2.8869299889,43.2909088135],"type":"Point"}
}