{
  "type": "Feature",
  "properties": {
    "addr:full":"J. Violon, S/n Granada Granada 18006",
    "addr:housenumber":"s / n",
    "addr:postcode":"18006",
    "addr:street":"J. Violon",
    "iso:country":"ES",
    "sg:address":"J. Violon, S/n",
    "sg:city":"Granada",
    "sg:orig_category":"Cl\u00cdnicas M\u00c9dicas",
    "sg:phone":"+34 958 12 88 63",
    "sg:postcode":"18006",
    "sg:province":"Granada",
    "wof:name":"Infante Trescastro Maria Jose",
    "wof:placetype":"venue"
},
  "geometry": {"coordinates":[-3.5977239609,37.1667900085],"type":"Point"}
}