{
  "type": "Feature",
  "properties": {
    "iso:country":"ES",
    "sg:address":"Pase San Gregorio, 1",
    "sg:city":"Puertollano",
    "sg:orig_category":"Ropa Para Caballeros (al Por Menor)",
    "sg:phone":"+34 926 43 08 77",
    "sg:postcode":"13500",
    "sg:province":"Ciudad Real",
    "wof:name":"Textil Daimiele\u00f1a S.a.",
    "wof:placetype":"venue"
},
  "geometry": {"coordinates":[-4.1066908836,38.6885604858],"type":"Point"}
}