{
  "type": "Feature",
  "properties": {
    "iso:country":"ES",
    "sg:address":"Pase Cientifico Gabriel Ciscar, 22",
    "sg:city":"Flota",
    "sg:orig_category":"Escuelas De Maternidad P\u00dablicas",
    "sg:phone":"+34 968 20 22 62",
    "sg:postcode":"30007",
    "sg:province":"Murcia",
    "wof:name":"Garcia Ruiz Maria Jose",
    "wof:placetype":"venue"
},
  "geometry": {"coordinates":[-1.1142389774,37.9970092773],"type":"Point"}
}