{
  "type": "Feature",
  "properties": {
    "addr:full":"Cmno Viejo, 61 Tegueste Casco Santa Cruz De Tenerife 38280",
    "addr:housenumber":"61",
    "addr:postcode":"38280",
    "addr:street":"Cmno Viejo",
    "iso:country":"ES",
    "sg:address":"Cmno Viejo, 61",
    "sg:city":"Tegueste Casco",
    "sg:orig_category":"Fisioterapia",
    "sg:phone":"+34 922 54 36 99",
    "sg:postcode":"38280",
    "sg:province":"Santa Cruz De Tenerife",
    "wof:name":"Centro De Fisioterapia Y Rehabilitacion Magec C.b.",
    "wof:placetype":"venue"
},
  "geometry": {"coordinates":[-16.3423995972,28.5218334198],"type":"Point"}
}