{
  "type": "Feature",
  "properties": {
    "iso:country":"ES",
    "sg:address":"Calle de Fray Ceferino, 20",
    "sg:city":"Oviedo",
    "sg:orig_category":"Asesor\u00cda Sobre Comunicaci\u00d3n De Empresas",
    "sg:phone":"+34 985 21 01 80",
    "sg:postcode":"33001",
    "sg:province":"Asturias",
    "wof:name":"Martinez Bra\u00f1a Carlos",
    "wof:placetype":"venue"
},
  "geometry": {"coordinates":[-5.8507628441,43.3665733337],"type":"Point"}
}