{
  "type": "Feature",
  "properties": {
    "iso:country":"ES",
    "sg:address":"Pase Delfin (el), 3",
    "sg:city":"Puerto Naos",
    "sg:orig_category":"Supermercados Y Hipermercados",
    "sg:phone":"+34 922 40 83 87",
    "sg:postcode":"38769",
    "sg:province":"Santa Cruz De Tenerife",
    "wof:name":"Centros De Ahorro San Martin S.l.",
    "wof:placetype":"venue"
},
  "geometry": {"coordinates":[-17.9101696014,28.5873203278],"type":"Point"}
}