{
  "type": "Feature",
  "properties": {
    "addr:full":"Cust Paz De La, 5 Antequera M\u00e1laga 29200",
    "addr:postcode":"29200",
    "addr:street":"Ma\u0301Laga",
    "iso:country":"ES",
    "sg:address":"Cust Paz De La, 5",
    "sg:city":"Antequera",
    "sg:orig_category":"Arquitectos",
    "sg:phone":"+34 952 84 18 89",
    "sg:postcode":"29200",
    "sg:province":"M\u00e1laga",
    "wof:name":"Estudio De Arquitectura Y Urbanismo E.a Pacheco Y Asociadsos S.l..",
    "wof:placetype":"venue"
},
  "geometry": {"coordinates":[-4.5636138916,37.0203018188],"type":"Point"}
}