{
  "type": "Feature",
  "properties": {
    "iso:country":"ES",
    "sg:address":"C/ Fernanda Santamaria, 74",
    "sg:city":"Elche",
    "sg:orig_category":"Farmacias",
    "sg:phone":"+34 966 63 67 35",
    "sg:postcode":"03204",
    "sg:province":"Alicante",
    "wof:name":"Rabadan Cachero Maria Socorro",
    "wof:placetype":"venue"
},
  "geometry": {"coordinates":[-0.7068009973,38.2602615356],"type":"Point"}
}