{
  "type": "Feature",
  "properties": {
    "addr:full":"Carrer de Can Dusai, 6 Palma Islas Baleares 07001",
    "addr:housenumber":"6",
    "addr:postcode":"07001",
    "addr:street":"Carrer De Can Dusai",
    "iso:country":"ES",
    "sg:address":"Carrer de Can Dusai, 6",
    "sg:city":"Palma",
    "sg:orig_category":"Arquitectos",
    "sg:phone":"+34 971 72 03 61",
    "sg:postcode":"07001",
    "sg:province":"Islas Baleares",
    "wof:name":"Arzubialde Saenz-badillos Ignacio",
    "wof:placetype":"venue"
},
  "geometry": {"coordinates":[2.6517066956,39.5675849915],"type":"Point"}
}