{
  "type": "Feature",
  "properties": {
    "addr:full":"Urb Capricho (el), S/n Marbella M\u00e1laga 29600",
    "addr:postcode":"29600",
    "addr:street":"Urb;El S / N;Ma\u0301Laga",
    "iso:country":"ES",
    "sg:address":"Urb Capricho (el), S/n",
    "sg:city":"Marbella",
    "sg:orig_category":"Empresas De Vigilancia, Guardia Y Protecci\u00d3n",
    "sg:phone":"+34 952 77 18 29",
    "sg:postcode":"29600",
    "sg:province":"M\u00e1laga",
    "wof:name":"Catalana De Proteccion Y Vigilancia De Bienes S.a.",
    "wof:placetype":"venue"
},
  "geometry": {"coordinates":[-4.8833007812,36.5079956055],"type":"Point"}
}