{
  "type": "Feature",
  "properties": {
    "addr:full":"Carrer de Sant Joan, 19 Viladecans Barcelona 08840",
    "addr:housenumber":"19",
    "addr:postcode":"08840",
    "addr:street":"Carrer De Sant Joan",
    "iso:country":"ES",
    "sg:address":"Carrer de Sant Joan, 19",
    "sg:city":"Viladecans",
    "sg:orig_category":"Animales (al Por Menor)",
    "sg:phone":"+34 936 58 70 50",
    "sg:postcode":"08840",
    "sg:province":"Barcelona",
    "wof:name":"Maria Del Carmen Gonzalez Y Rosa Maria Sancho S.c.",
    "wof:placetype":"venue"
},
  "geometry": {"coordinates":[2.0184690952,41.3168945312],"type":"Point"}
}