{
  "type": "Feature",
  "properties": {
    "iso:country":"ES",
    "sg:address":"Calle de Soto Del Barco, 9",
    "sg:city":"Oviedo",
    "sg:orig_category":"Agencias Y Agentes Comerciales, Representantes",
    "sg:phone":"+34 985 20 70 08",
    "sg:postcode":"33012",
    "sg:province":"Asturias",
    "sg:website":"www.domoresidencial.com",
    "wof:name":"Domo Residencial S.a.",
    "wof:placetype":"venue"
},
  "geometry": {"coordinates":[-5.8765439987,43.3672142029],"type":"Point"}
}