{
  "type": "Feature",
  "properties": {
    "iso:country":"ES",
    "sg:address":"Avda Diputacion (de La), S/n",
    "sg:city":"Castro Rio",
    "sg:orig_category":"Suministros Para Hoteles",
    "sg:phone":"+34 957 37 27 90",
    "sg:postcode":"14840",
    "sg:province":"C\u00f3rdoba",
    "wof:name":"Cruz Urbano Jesus",
    "wof:placetype":"venue"
},
  "geometry": {"coordinates":[-4.4868540764,37.6937904358],"type":"Point"}
}