{
  "type": "Feature",
  "properties": {
    "iso:country":"ES",
    "sg:address":"Carr Barcelona, 2",
    "sg:city":"Badalona",
    "sg:orig_category":"Importaci\u00d3n, Exportaci\u00d3n Y Comercios De Productos Textiles",
    "sg:phone":"+34 933 89 22 11",
    "sg:postcode":"08911",
    "sg:province":"Barcelona",
    "wof:name":"Alier Prat Antonio",
    "wof:placetype":"venue"
},
  "geometry": {"coordinates":[2.2455089092,41.4519996643],"type":"Point"}
}