{
  "type": "Feature",
  "properties": {
    "addr:full":"Calle de Granada, 22 Linea De La Concepcion C\u00e1diz 11300",
    "addr:housenumber":"22",
    "addr:postcode":"11300",
    "addr:street":"Calle De Granada;Ca\u0301Diz",
    "iso:country":"ES",
    "sg:address":"Calle de Granada, 22",
    "sg:city":"Linea De La Concepcion",
    "sg:orig_category":"Equipo De Refrigeraci\u00d3n Industrial",
    "sg:phone":"+34 956 17 11 64",
    "sg:postcode":"11300",
    "sg:province":"C\u00e1diz",
    "wof:name":"Orrillo Vazquez Fernando",
    "wof:placetype":"venue"
},
  "geometry": {"coordinates":[-5.3491339684,36.164642334],"type":"Point"}
}