{
  "type": "Feature",
  "properties": {
    "addr:full":"Calle de San Roque, 45 Piedralaves \u00c1vila 05440",
    "addr:housenumber":"45",
    "addr:postcode":"05440",
    "addr:street":"Calle De San Roque",
    "iso:country":"ES",
    "sg:address":"Calle de San Roque, 45",
    "sg:city":"Piedralaves",
    "sg:orig_category":"Supermercados Y Hipermercados",
    "sg:phone":"+34 918 60 60 04",
    "sg:postcode":"05440",
    "sg:province":"\u00c1vila",
    "wof:name":"Jigara S.l.",
    "wof:placetype":"venue"
},
  "geometry": {"coordinates":[-4.6985287666,40.3194503784],"type":"Point"}
}