{
  "type": "Feature",
  "properties": {
    "addr:full":"Pl Vila (de La), 13 Torredembarra Tarragona 43830",
    "addr:housenumber":"13",
    "addr:postcode":"43830",
    "addr:street":"Pl Vila De La",
    "iso:country":"ES",
    "sg:address":"Pl Vila (de La), 13",
    "sg:city":"Torredembarra",
    "sg:orig_category":"Pelucas Y Postizos",
    "sg:phone":"+34 977 64 02 27",
    "sg:postcode":"43830",
    "sg:province":"Tarragona",
    "wof:name":"Antonieta Agusti-peluquerias S. A.",
    "wof:placetype":"venue"
},
  "geometry": {"coordinates":[1.3966712952,41.1447029114],"type":"Point"}
}