{
  "type": "Feature",
  "properties": {
    "iso:country":"ES",
    "sg:address":"Santo Domingo, 37",
    "sg:city":"Iru\u00f1a",
    "sg:orig_category":"Inform\u00c1tica (estudios, Servicios, Asesor\u00cda, Formaci\u00d3n)",
    "sg:phone":"+34 948 20 75 97",
    "sg:postcode":"31001",
    "sg:province":"Navarra",
    "wof:name":"Informatica San Fermin S.c.i.",
    "wof:placetype":"venue"
},
  "geometry": {"coordinates":[-1.6456234455,42.8190765381],"type":"Point"}
}