{
  "type": "Feature",
  "properties": {
    "iso:country":"ES",
    "sg:address":"Carrer de Ceravalls, 10",
    "sg:city":"Hospitalet Llobregat",
    "sg:orig_category":"Peluquer\u00cdas, Peluquer\u00cda Mixta",
    "sg:phone":"+34 933 33 27 17",
    "sg:postcode":"08905",
    "sg:province":"Barcelona",
    "wof:name":"Calero Gaspar Maria Pilar",
    "wof:placetype":"venue"
},
  "geometry": {"coordinates":[2.1084640026,41.3689155579],"type":"Point"}
}