{
  "type": "Feature",
  "properties": {
    "iso:country":"ES",
    "sg:address":"Rbla Catalunya, 58",
    "sg:city":"Barcelona",
    "sg:orig_category":"Panader\u00cdas, Panader\u00cdas",
    "sg:phone":"+34 932 16 02 69",
    "sg:postcode":"08007",
    "sg:province":"Barcelona",
    "wof:name":"Casa Vives S.l.",
    "wof:placetype":"venue"
},
  "geometry": {"coordinates":[2.1638178825,41.3911361694],"type":"Point"}
}