{
  "type": "Feature",
  "properties": {
    "iso:country":"ES",
    "sg:address":"Calle de Beato Berrio Ochoa, 5",
    "sg:city":"Logro\u00f1o",
    "sg:orig_category":"Fabricaci\u00d3n, Instalaci\u00d3n Y Reparaci\u00d3n De Bombas",
    "sg:phone":"+34 941 24 80 25",
    "sg:postcode":"26004",
    "sg:province":"La Rioja",
    "wof:name":"Velasco Gonzalez Jose Maria",
    "wof:placetype":"venue"
},
  "geometry": {"coordinates":[-2.4293580055,42.4661064148],"type":"Point"}
}