{
  "type": "Feature",
  "properties": {
    "iso:country":"ES",
    "sg:address":"Calle de Cid, 12",
    "sg:city":"Cabezo Torres",
    "sg:orig_category":"Planchado",
    "sg:phone":"+34 968 30 62 74",
    "sg:postcode":"30110",
    "sg:province":"Murcia",
    "wof:name":"Ekipa Vestuario Profesional S.l.",
    "wof:placetype":"venue"
},
  "geometry": {"coordinates":[-1.1193368435,38.0247154236],"type":"Point"}
}