{
  "type": "Feature",
  "properties": {
    "iso:country":"ES",
    "sg:address":"Carrer de Corsega, 234",
    "sg:city":"Barcelona",
    "sg:orig_category":"Molduras, Junquillos, Listones Y Molduras Perforadas",
    "sg:phone":"+34 932 37 23 72",
    "sg:postcode":"08036",
    "sg:province":"Barcelona",
    "wof:name":"Jacome Gomez Pedro",
    "wof:placetype":"venue"
},
  "geometry": {"coordinates":[2.1544649601,41.3926696777],"type":"Point"}
}