{
  "type": "Feature",
  "properties": {
    "iso:country":"ES",
    "sg:address":"Pl. Mayor, S/n",
    "sg:city":"Monasterio De Rodilla",
    "sg:orig_category":"Iglesia Cat\u00d3lica",
    "sg:phone":"+34 947 59 43 88",
    "sg:postcode":"09292",
    "sg:province":"Burgos",
    "wof:name":"Parroquia Monasterio De Rodilla",
    "wof:placetype":"venue"
},
  "geometry": {"coordinates":[-3.4694740772,42.4579162598],"type":"Point"}
}