{
  "type": "Feature",
  "properties": {
    "iso:country":"ES",
    "sg:address":"Carrer de Blavets De Lluc, 23",
    "sg:city":"Secar De La Real",
    "sg:orig_category":"Bisuteros (fabricaci\u00d3n, Al Por Mayor)",
    "sg:phone":"+34 971 76 92 92",
    "sg:postcode":"07010",
    "sg:province":"Islas Baleares",
    "sg:website":"www.scorpalma1@hotmail.com",
    "wof:name":"Scorpalma S.l.",
    "wof:placetype":"venue"
},
  "geometry": {"coordinates":[2.6215190887,39.6229019165],"type":"Point"}
}