{
  "type": "Feature",
  "properties": {
    "iso:country":"ES",
    "sg:address":"Carrer de Mallorca, 486",
    "sg:city":"Barcelona",
    "sg:orig_category":"Instalaci\u00d3n, Reparaci\u00d3n De Calefacci\u00d3n El\u00c9ctrica",
    "sg:phone":"+34 932 44 08 10",
    "sg:postcode":"08013",
    "sg:province":"Barcelona",
    "wof:name":"Atermycal S.a.",
    "wof:placetype":"venue"
},
  "geometry": {"coordinates":[2.1794848442,41.4065132141],"type":"Point"}
}