{
  "type": "Feature",
  "properties": {
    "iso:country":"ES",
    "sg:address":"Calle de Mosen Pedro Rubio, 22",
    "sg:city":"Cuarte Huerva",
    "sg:orig_category":"Escayola Y Productos De Escayola (fabricaci\u00d3n, Al Por Mayor)",
    "sg:phone":"+34 976 50 33 20",
    "sg:postcode":"50410",
    "sg:province":"Zaragoza",
    "wof:name":"Diez Carnicer Feliciano",
    "wof:placetype":"venue"
},
  "geometry": {"coordinates":[-0.930539012,41.589630127],"type":"Point"}
}