{
  "type": "Feature",
  "properties": {
    "iso:country":"ES",
    "sg:address":"Carrer de Torres (gracia), 29",
    "sg:city":"Barcelona",
    "sg:orig_category":"Peluqueros: De Se\u00d1oras",
    "sg:phone":"+34 932 76 39 63",
    "sg:postcode":"08042",
    "sg:province":"Barcelona",
    "wof:name":"Peluqueria Babiliss S.cv.",
    "wof:placetype":"venue"
},
  "geometry": {"coordinates":[2.1770679951,41.4468612671],"type":"Point"}
}