{
  "type": "Feature",
  "properties": {
    "iso:country":"ES",
    "sg:address":"Avda Ramon Y Cajal, 2",
    "sg:city":"Fraga",
    "sg:classifiers":[
        {
            "category":"Taxi",
            "type":"Transportation"
        }
    ],
    "sg:phone":"+34 974 47 16 73",
    "sg:postcode":"22520",
    "sg:province":"Huesca",
    "wof:name":"Taxis Romera S.c.",
    "wof:placetype":"venue"
},
  "geometry": {"coordinates":[0.3420790136,41.5212783813],"type":"Point"}
}