{
  "type": "Feature",
  "properties": {
    "addr:full":"Calle de Esperanza, 7 Biescas Huesca 22630",
    "addr:housenumber":"7",
    "addr:postcode":"22630",
    "addr:street":"Calle De Esperanza",
    "iso:country":"ES",
    "sg:address":"Calle de Esperanza, 7",
    "sg:city":"Biescas",
    "sg:orig_category":"Reposter\u00cdas",
    "sg:phone":"+34 974 48 53 41",
    "sg:postcode":"22630",
    "sg:province":"Huesca",
    "wof:name":"La Artesa De Biescas S.c.",
    "wof:placetype":"venue"
},
  "geometry": {"coordinates":[-0.3206745088,42.6283721924],"type":"Point"}
}