{
  "type": "Feature",
  "properties": {
    "iso:country":"ES",
    "sg:address":"Calle de Alta Del Mar, 12",
    "sg:city":"Almu\u00f1ecar",
    "sg:orig_category":"Tapicer\u00cdas",
    "sg:phone":"+34 958 63 21 56",
    "sg:postcode":"18690",
    "sg:province":"Granada",
    "wof:name":"Ruiz Lopez Antonio",
    "wof:placetype":"venue"
},
  "geometry": {"coordinates":[-3.6900959015,36.7321205139],"type":"Point"}
}