{
  "type": "Feature",
  "properties": {
    "addr:full":"Urb Benfis-park, S/n Urbanizacion Benfis-park Alicante 03315",
    "addr:housenumber":"s",
    "addr:postcode":"03315",
    "addr:street":"Urb Benfis-Park;/ N Urbanizacion",
    "iso:country":"ES",
    "sg:address":"Urb Benfis-park, S/n",
    "sg:city":"Urbanizacion Benfis-park",
    "sg:orig_category":"Marketing Telef\u00d3nico",
    "sg:phone":"+34 965 36 97 22",
    "sg:postcode":"03315",
    "sg:province":"Alicante",
    "wof:name":"Perry  Roy Stewart",
    "wof:placetype":"venue"
},
  "geometry": {"coordinates":[-0.9639940262,38.1715431213],"type":"Point"}
}