{
  "type": "Feature",
  "properties": {
    "addr:full":"Calle de San Isidro, 16 Vinaros Castell\u00f3n 12500",
    "addr:housenumber":"16",
    "addr:postcode":"12500",
    "addr:street":"Calle De San Isidro",
    "iso:country":"ES",
    "sg:address":"Calle de San Isidro, 16",
    "sg:city":"Vinaros",
    "sg:orig_category":"Prendas Y Chalecos De Punto (al Por Menor)",
    "sg:phone":"+34 964 45 28 56",
    "sg:postcode":"12500",
    "sg:province":"Castell\u00f3n",
    "wof:name":"Cotano Castellar S.l.",
    "wof:placetype":"venue"
},
  "geometry": {"coordinates":[0.4749450088,40.4711990356],"type":"Point"}
}