{
  "type": "Feature",
  "properties": {
    "iso:country":"ES",
    "sg:address":"Calle de Greco, 2",
    "sg:city":"Talavera Reina",
    "sg:orig_category":"Ense\u00d1anza Variada",
    "sg:phone":"+34 925 82 16 09",
    "sg:postcode":"45600",
    "sg:province":"Toledo",
    "wof:name":"Gonzalez Perez Carlos",
    "wof:placetype":"venue"
},
  "geometry": {"coordinates":[-4.8277249336,39.9624252319],"type":"Point"}
}