{
  "type": "Feature",
  "properties": {
    "addr:full":"Calle de Era (la), S/n Benagalbon M\u00e1laga 29738",
    "addr:postcode":"29738",
    "addr:street":"Calle De Era La S / N Benagalbon Ma\u0301Laga",
    "iso:country":"ES",
    "sg:address":"Calle de Era (la), S/n",
    "sg:city":"Benagalbon",
    "sg:orig_category":"M\u00c1quinas De Jardiner\u00cda",
    "sg:phone":"+34 952 40 09 73",
    "sg:postcode":"29738",
    "sg:province":"M\u00e1laga",
    "wof:name":"Viveros F.serrano S.l.",
    "wof:placetype":"venue"
},
  "geometry": {"coordinates":[-4.2452349663,36.7380599976],"type":"Point"}
}