{
  "type": "Feature",
  "properties": {
    "iso:country":"ES",
    "sg:address":"Calle de Arroyo De Tejada (del), 14",
    "sg:city":"Colmenar Viejo",
    "sg:orig_category":"Electricidad, Electr\u00d3nica: Material Y Suministros (al Por Mayor)",
    "sg:phone":"+34 918 46 25 98",
    "sg:postcode":"28770",
    "sg:province":"Madrid",
    "sg:website":"www.cavacins.com",
    "wof:name":"Cavac Instruments S.r.l.",
    "wof:placetype":"venue"
},
  "geometry": {"coordinates":[-3.762373209,40.6643371582],"type":"Point"}
}