{
  "type": "Feature",
  "properties": {
    "iso:country":"ES",
    "sg:address":"Av Joan Xxiii, 46",
    "sg:city":"Masnou",
    "sg:orig_category":"Alquiler De Apartamentos",
    "sg:phone":"+34 935 55 23 33",
    "sg:postcode":"08320",
    "sg:province":"Barcelona",
    "wof:name":"Duran Vila Josefina",
    "wof:placetype":"venue"
},
  "geometry": {"coordinates":[2.3157000542,41.4831085205],"type":"Point"}
}