{
  "type": "Feature",
  "properties": {
    "addr:full":"Pla\u00c7 Maestro Palau, 2 Moncada Valencia 46113",
    "addr:housenumber":"2",
    "addr:postcode":"46113",
    "addr:street":"Maestro Palau",
    "iso:country":"ES",
    "sg:address":"Pla\u00c7 Maestro Palau, 2",
    "sg:city":"Moncada",
    "sg:orig_category":"Medicamentos",
    "sg:phone":"+34 961 39 19 22",
    "sg:postcode":"46113",
    "sg:province":"Valencia",
    "wof:name":"Vicent Lopez Julia Maria",
    "wof:placetype":"venue"
},
  "geometry": {"coordinates":[-0.391858995,39.5454292297],"type":"Point"}
}