{
  "type": "Feature",
  "properties": {
    "iso:country":"ES",
    "sg:address":"Carr Rentadors, 28",
    "sg:city":"Sant Joan De Palamos",
    "sg:orig_category":"Mec\u00c1nico Del Autom\u00d3vil",
    "sg:phone":"+34 972 31 62 86",
    "sg:postcode":"17230",
    "sg:province":"Girona",
    "wof:name":"Payet Corominas Enric",
    "wof:placetype":"venue"
},
  "geometry": {"coordinates":[3.128029108,41.8527641296],"type":"Point"}
}