{
  "type": "Feature",
  "properties": {
    "addr:full":"Avda Generalisimo, 110 Barbate C\u00e1diz 11160",
    "addr:housenumber":"110",
    "addr:postcode":"11160",
    "addr:street":"Avda Generalisimo",
    "iso:country":"ES",
    "sg:address":"Avda Generalisimo, 110",
    "sg:city":"Barbate",
    "sg:classifiers":[
        {
            "category":"Taxi",
            "type":"Transportation"
        }
    ],
    "sg:phone":"+34 956 43 10 84",
    "sg:postcode":"11160",
    "sg:province":"C\u00e1diz",
    "wof:name":"Asociacion Profesional De Taxi Barbate Y Zahara",
    "wof:placetype":"venue"
},
  "geometry": {"coordinates":[-5.9238195419,36.187374115],"type":"Point"}
}