{
  "type": "Feature",
  "properties": {
    "addr:full":"Carr Mendez Nu\u00d1ez, S/n Puerto De Pollen\u00c7a Islas Baleares 07470",
    "addr:housenumber":"s / n",
    "addr:postcode":"07470",
    "addr:street":"Carr Mendez Nun\u0303Ez",
    "iso:country":"ES",
    "sg:address":"Carr Mendez Nu\u00d1ez, S/n",
    "sg:city":"Puerto De Pollen\u00c7a",
    "sg:orig_category":"Molduras, Junquillos, Listones Y Molduras Perforadas",
    "sg:phone":"+34 971 86 68 31",
    "sg:postcode":"07470",
    "sg:province":"Islas Baleares",
    "wof:name":"Vives Martinez Francisco",
    "wof:placetype":"venue"
},
  "geometry": {"coordinates":[3.0836985111,39.9096946716],"type":"Point"}
}