{
  "type": "Feature",
  "properties": {
    "addr:full":"Avgd Balmes, 22 Lleida Lleida 25006",
    "addr:housenumber":"22",
    "addr:postcode":"25006",
    "addr:street":"Avgd Balmes",
    "iso:country":"ES",
    "sg:address":"Avgd Balmes, 22",
    "sg:city":"Lleida",
    "sg:orig_category":"Fabricaci\u00d3n De Bebidas No Alcoh\u00d3licas",
    "sg:phone":"+34 973 23 10 74",
    "sg:postcode":"25006",
    "sg:province":"Lleida",
    "wof:name":"Cortes Sirvent Francisco",
    "wof:placetype":"venue"
},
  "geometry": {"coordinates":[0.6201019883,41.6179695129],"type":"Point"}
}