{
  "type": "Feature",
  "properties": {
    "iso:country":"ES",
    "sg:address":"Calle de Antonio Rubio Torres, 1",
    "sg:city":"Fuengirola",
    "sg:orig_category":"Desinfecci\u00d3n, Desinsectaci\u00d3n, Desratizaci\u00d3n",
    "sg:phone":"+34 952 46 83 64",
    "sg:postcode":"29640",
    "sg:province":"M\u00e1laga",
    "wof:name":"Garpi Andalucia S.l.",
    "wof:placetype":"venue"
},
  "geometry": {"coordinates":[-4.6222267151,36.5429382324],"type":"Point"}
}