{
  "type": "Feature",
  "properties": {
    "iso:country":"ES",
    "sg:address":"Calle de Carmen, 3",
    "sg:city":"Le\u00f3n",
    "sg:orig_category":"Asesor\u00cda Sobre Comunicaci\u00d3n De Empresas",
    "sg:phone":"+34 987 23 53 23",
    "sg:postcode":"24001",
    "sg:province":"Le\u00f3n",
    "wof:name":"Asesoria Alonso Bellido S.l.",
    "wof:placetype":"venue"
},
  "geometry": {"coordinates":[-5.5761723518,42.5974960327],"type":"Point"}
}