{
  "type": "Feature",
  "properties": {
    "addr:full":"Carr Alcalde Don Laureano Su\u00d1er Carbonell, 2 Carcer Valencia 46294",
    "addr:housenumber":"2",
    "addr:postcode":"46294",
    "addr:street":"Carr Alcalde Don Laureano Sun\u0303Er Carbonell",
    "iso:country":"ES",
    "sg:address":"Carr Alcalde Don Laureano Su\u00d1er Carbonell, 2",
    "sg:city":"Carcer",
    "sg:orig_category":"M\u00c9dicos: An\u00c1lisis Cl\u00cdnicos",
    "sg:phone":"+34 962 58 00 61",
    "sg:postcode":"46294",
    "sg:province":"Valencia",
    "wof:name":"Peydro Soucase Antonio Francisco",
    "wof:placetype":"venue"
},
  "geometry": {"coordinates":[-0.5658329725,39.0699462891],"type":"Point"}
}