{
  "type": "Feature",
  "properties": {
    "iso:country":"ES",
    "sg:address":"Ctra Lliria-villamarxant, Km. 0000,0",
    "sg:city":"Lliria",
    "sg:orig_category":"Electromec\u00c1nica",
    "sg:phone":"+34 962 79 01 97",
    "sg:postcode":"46160",
    "sg:province":"Valencia",
    "wof:name":"Talleres De Automocion X-34 S.l.",
    "wof:placetype":"venue"
},
  "geometry": {"coordinates":[-0.5952839851,39.6247406006],"type":"Point"}
}