{
  "type": "Feature",
  "properties": {
    "addr:full":"Cno Font Rocha, S/n Montortal Valencia 46250",
    "addr:housenumber":"s",
    "addr:postcode":"46250",
    "addr:street":"Cno Font Rocha;/ N",
    "iso:country":"ES",
    "sg:address":"Cno Font Rocha, S/n",
    "sg:city":"Montortal",
    "sg:orig_category":"Muebles Y Accesorios Para Cocinas Y Cuartos De Ba\u00d1o (al Por Menor)",
    "sg:phone":"+34 962 44 20 00",
    "sg:postcode":"46250",
    "sg:province":"Valencia",
    "wof:name":"Briar Banys S.l.",
    "wof:placetype":"venue"
},
  "geometry": {"coordinates":[-0.5070289969,39.1940689087],"type":"Point"}
}