{
  "type": "Feature",
  "properties": {
    "addr:full":"Carr Miquel De Cortiada, 27 Lleida Lleida 25005",
    "addr:housenumber":"27",
    "addr:postcode":"25005",
    "addr:street":"Carr Miquel De Cortiada",
    "iso:country":"ES",
    "sg:address":"Carr Miquel De Cortiada, 27",
    "sg:city":"Lleida",
    "sg:orig_category":"Agencias Y Agentes Comerciales, Representantes",
    "sg:phone":"+34 973 24 37 11",
    "sg:postcode":"25005",
    "sg:province":"Lleida",
    "wof:name":"Morancho Puy Jose Maria",
    "wof:placetype":"venue"
},
  "geometry": {"coordinates":[0.6395589709,41.6257743835],"type":"Point"}
}