{
  "type": "Feature",
  "properties": {
    "iso:country":"ES",
    "sg:address":"Calle de Doctor, 4",
    "sg:city":"Linares",
    "sg:orig_category":"Papeler\u00cdas, Librer\u00cdas",
    "sg:phone":"+34 953 60 02 27",
    "sg:postcode":"23700",
    "sg:province":"Ja\u00e9n",
    "wof:name":"Hidalgo Valverde Margarita",
    "wof:placetype":"venue"
},
  "geometry": {"coordinates":[-3.6272335052,38.0907707214],"type":"Point"}
}