{
  "type": "Feature",
  "properties": {
    "iso:country":"ES",
    "sg:address":"Carr Antoni Maura, 17",
    "sg:city":"Lloseta",
    "sg:orig_category":"Cueros Y Pieles (al Por Mayor)",
    "sg:phone":"+34 971 51 48 39",
    "sg:postcode":"07360",
    "sg:province":"Islas Baleares",
    "wof:name":"Hidalgo Torreblanco Mariano",
    "wof:placetype":"venue"
},
  "geometry": {"coordinates":[2.8670749664,39.7177009583],"type":"Point"}
}