{
  "type": "Feature",
  "properties": {
    "iso:country":"ES",
    "sg:address":"Rua Fernandez Areal, 4",
    "sg:city":"Porri\u00f1o",
    "sg:orig_category":"M\u00c9dicos: Foniatr\u00cda Y Logopedia",
    "sg:phone":"+34 986 33 89 72",
    "sg:postcode":"36400",
    "sg:province":"Pontevedra",
    "wof:name":"Cabaleiro Rodriguez Maria",
    "wof:placetype":"venue"
},
  "geometry": {"coordinates":[-8.6173009872,42.1576118469],"type":"Point"}
}