{
  "type": "Feature",
  "properties": {
    "addr:full":"Lopene Plaza, 3 Lezo Guip\u00f9zcoa 20100",
    "addr:housenumber":"3",
    "addr:postcode":"20100",
    "addr:street":"Lopene Plaza;Guipu\u0300Zcoa",
    "iso:country":"ES",
    "sg:address":"Lopene Plaza, 3",
    "sg:city":"Lezo",
    "sg:orig_category":"Peluqueros: De Se\u00d1oras",
    "sg:phone":"+34 943 34 13 38",
    "sg:postcode":"20100",
    "sg:province":"Guip\u00f9zcoa",
    "wof:name":"Mari Carmen Alonso Del Rio (peluqueria Olatz)",
    "wof:placetype":"venue"
},
  "geometry": {"coordinates":[-1.8929729462,43.3218955994],"type":"Point"}
}