{
  "type": "Feature",
  "properties": {
    "addr:full":"Rua Rosas, 4 Carballo La Coru\u00f1a 15100",
    "addr:housenumber":"4",
    "addr:postcode":"15100",
    "addr:street":"Rua Rosas;La Corun\u0303A",
    "iso:country":"ES",
    "sg:address":"Rua Rosas, 4",
    "sg:city":"Carballo",
    "sg:orig_category":"Fabricaci\u00d3n De Juguetes Autom\u00c1ticos",
    "sg:phone":"+34 981 75 61 77",
    "sg:postcode":"15100",
    "sg:province":"La Coru\u00f1a",
    "wof:name":"Recreativos Xolda S.l.",
    "wof:placetype":"venue"
},
  "geometry": {"coordinates":[-8.6997442245,43.2135391235],"type":"Point"}
}