{
  "type": "Feature",
  "properties": {
    "iso:country":"ES",
    "sg:address":"Trva Carcel (la), 2",
    "sg:city":"Orihuela",
    "sg:orig_category":"Comercio, Reparaci\u00d3n De Motocicletas, Bicicletas Y Piezas Sueltas",
    "sg:phone":"+34 965 30 24 60",
    "sg:postcode":"03300",
    "sg:province":"Alicante",
    "wof:name":"Olit Alvarez Jesus",
    "wof:placetype":"venue"
},
  "geometry": {"coordinates":[-0.9512820244,38.0837898254],"type":"Point"}
}