{
  "type": "Feature",
  "properties": {
    "iso:country":"ES",
    "sg:address":"Calle de Camino De La Minguilla, 8",
    "sg:city":"Castro Rio",
    "sg:orig_category":"Producci\u00d3n De Abonos Y De Fertilizantes",
    "sg:phone":"+34 957 37 05 06",
    "sg:postcode":"14840",
    "sg:province":"C\u00f3rdoba",
    "wof:name":"Sanchez Pe\u00f1a Francisco",
    "wof:placetype":"venue"
},
  "geometry": {"coordinates":[-4.7791519165,37.884727478],"type":"Point"}
}