{
  "type": "Feature",
  "properties": {
    "iso:country":"ES",
    "sg:address":"Av Mossen Cinto Verdaguer, 7",
    "sg:city":"Arbo\u00e7",
    "sg:orig_category":"Minerales (al Por Mayor)",
    "sg:phone":"+34 977 67 01 25",
    "sg:postcode":"43720",
    "sg:province":"Tarragona",
    "sg:website":"www.mdelibach.com",
    "wof:name":"Minerals I Derivats S.a.",
    "wof:placetype":"venue"
},
  "geometry": {"coordinates":[1.6021629572,41.2704849243],"type":"Point"}
}