{
  "type": "Feature",
  "properties": {
    "addr:full":"Mare De Deu De Nuria S. Boi Llobregat Barcelona 08830",
    "addr:postcode":"08830",
    "iso:country":"ES",
    "sg:address":"Mare De Deu De Nuria",
    "sg:city":"S. Boi Llobregat",
    "sg:orig_category":"Contenedores (mercanc\u00cdas)",
    "sg:phone":"+34 936 35 41 77",
    "sg:postcode":"08830",
    "sg:province":"Barcelona",
    "wof:name":"Gt Transp S.a.",
    "wof:placetype":"venue"
},
  "geometry": {"coordinates":[2.0283110142,41.3283004761],"type":"Point"}
}