{
  "type": "Feature",
  "properties": {
    "iso:country":"ES",
    "sg:address":"Carrer de Catorze D'abril, 1",
    "sg:city":"Terrassa",
    "sg:orig_category":"Multimedia: Servicios En L\u00cdnea, Acceso En L\u00cdnea, Cd",
    "sg:phone":"+34 937 80 47 88",
    "sg:postcode":"08224",
    "sg:province":"Barcelona",
    "wof:name":"Recerca Grafica S.l.",
    "wof:placetype":"venue"
},
  "geometry": {"coordinates":[2.0006248951,41.5664863586],"type":"Point"}
}