{
  "type": "Feature",
  "properties": {
    "addr:full":"Ptda Alberca (l'), 1 Nucia Alicante 03530",
    "addr:housenumber":"1",
    "addr:postcode":"03530",
    "addr:street":"Ptda Alberca L '",
    "iso:country":"ES",
    "sg:address":"Ptda Alberca (l'), 1",
    "sg:city":"Nucia",
    "sg:orig_category":"Perfumer\u00cda, Art\u00cdculos De Ba\u00d1o (fabricaci\u00d3n, Al Por Mayor)",
    "sg:phone":"+34 966 89 65 94",
    "sg:postcode":"03530",
    "sg:province":"Alicante",
    "sg:website":"www.juliomartin.com",
    "wof:name":"Creation Julio Martin S.l.",
    "wof:placetype":"venue"
},
  "geometry": {"coordinates":[-0.1213990003,38.594619751],"type":"Point"}
}