{
  "type": "Feature",
  "properties": {
    "addr:full":"Dip Tercia, S/n Lorca Murcia 30815",
    "addr:housenumber":"s / n",
    "addr:postcode":"30815",
    "addr:street":"Dip Tercia",
    "iso:country":"ES",
    "sg:address":"Dip Tercia, S/n",
    "sg:city":"Lorca",
    "sg:orig_category":"Frutas, Legumbres Frescas Y Tempranas (al Por Menor)",
    "sg:phone":"+34 968 46 00 64",
    "sg:postcode":"30815",
    "sg:province":"Murcia",
    "wof:name":"Agrotercia S.l.",
    "wof:placetype":"venue"
},
  "geometry": {"coordinates":[-1.575363636,37.6082267761],"type":"Point"}
}