{
  "type": "Feature",
  "properties": {
    "iso:country":"ES",
    "sg:address":"Calle de Eretza Monte, 7",
    "sg:city":"Bilbao",
    "sg:orig_category":"Inform\u00c1tica (estudios, Servicios, Asesor\u00cda, Formaci\u00d3n)",
    "sg:phone":"+34 944 44 31 34",
    "sg:postcode":"48003",
    "sg:province":"Vizcaya",
    "sg:website":"www.argisoft.com",
    "wof:name":"Sergio Blanco Alvarez",
    "wof:placetype":"venue"
},
  "geometry": {"coordinates":[-2.930973053,43.2480621338],"type":"Point"}
}