{
  "type": "Feature",
  "properties": {
    "iso:country":"ES",
    "sg:address":"Ctra Molins De Rei, Km. 0013,0",
    "sg:city":"Rubi",
    "sg:orig_category":"Fabricaci\u00d3n De Mobiliario De Oficina",
    "sg:phone":"+34 935 88 56 07",
    "sg:postcode":"08191",
    "sg:province":"Barcelona",
    "wof:name":"Kroper Mobiliario S.l.",
    "wof:placetype":"venue"
},
  "geometry": {"coordinates":[2.0307109356,41.4825019836],"type":"Point"}
}