{
  "type": "Feature",
  "properties": {
    "addr:full":"Calle de Puerto Pajares, 15 Pola De Laviana Asturias 33980",
    "addr:housenumber":"15",
    "addr:postcode":"33980",
    "addr:street":"Calle De Puerto Pajares;Pola",
    "iso:country":"ES",
    "sg:address":"Calle de Puerto Pajares, 15",
    "sg:city":"Pola De Laviana",
    "sg:orig_category":"Peluqueros: De Se\u00d1oras",
    "sg:phone":"+34 985 61 02 48",
    "sg:postcode":"33980",
    "sg:province":"Asturias",
    "wof:name":"Alvarez Vazquez Maria Elena",
    "wof:placetype":"venue"
},
  "geometry": {"coordinates":[-5.5607619286,43.240398407],"type":"Point"}
}