{
  "type": "Feature",
  "properties": {
    "addr:full":"Carrer de Vistalegre, 62 Cornella Llobregat Barcelona 08940",
    "addr:housenumber":"62",
    "addr:postcode":"08940",
    "addr:street":"Carrer De Vistalegre",
    "iso:country":"ES",
    "sg:address":"Carrer de Vistalegre, 62",
    "sg:city":"Cornella Llobregat",
    "sg:orig_category":"Empresas De Carpinter\u00cda De Madera",
    "sg:phone":"+34 933 75 37 57",
    "sg:postcode":"08940",
    "sg:province":"Barcelona",
    "wof:name":"Cantarero Alcaraz Francisco",
    "wof:placetype":"venue"
},
  "geometry": {"coordinates":[2.0769848824,41.3637313843],"type":"Point"}
}