{
  "type": "Feature",
  "properties": {
    "iso:country":"ES",
    "sg:address":"Pase Cerrado De Calderon, 1",
    "sg:city":"Malaga",
    "sg:orig_category":"Agentes Generales De Seguros",
    "sg:phone":"+34 952 29 90 48",
    "sg:postcode":"29018",
    "sg:province":"M\u00e1laga",
    "sg:website":"www.confiamalaga.com",
    "wof:name":"Aifnoc Malaga S.l.",
    "wof:placetype":"venue"
},
  "geometry": {"coordinates":[-4.3462371826,36.756652832],"type":"Point"}
}