{
  "type": "Feature",
  "properties": {
    "addr:full":"Avda Tomas Dominguez, S/n Huelva Huelva 21001",
    "addr:postcode":"21001",
    "addr:street":"Avda Tomas Dominguez S / N",
    "iso:country":"ES",
    "sg:address":"Avda Tomas Dominguez, S/n",
    "sg:city":"Huelva",
    "sg:orig_category":"Centros Empresariales",
    "sg:phone":"+34 959 25 17 86",
    "sg:postcode":"21001",
    "sg:province":"Huelva",
    "wof:name":"Union Provincial De Empresarios De La Construccion De Huelva",
    "wof:placetype":"venue"
},
  "geometry": {"coordinates":[-6.9550690651,37.2546195984],"type":"Point"}
}