{
  "type": "Feature",
  "properties": {
    "iso:country":"ES",
    "sg:address":"Toledo, 8",
    "sg:city":"Piedrabuena",
    "sg:orig_category":"Empresas De Carpinter\u00cda",
    "sg:phone":"+34 926 76 07 95",
    "sg:postcode":"13100",
    "sg:province":"Ciudad Real",
    "wof:name":"Albalate Cabezas Antonio",
    "wof:placetype":"venue"
},
  "geometry": {"coordinates":[-4.1710424423,39.0346107483],"type":"Point"}
}