{
  "type": "Feature",
  "properties": {
    "iso:country":"ES",
    "sg:address":"Ctra La Campana, S/n",
    "sg:city":"Carmona",
    "sg:orig_category":"Producci\u00d3n, Venta De Productos De Agricultura Biol\u00d3gica",
    "sg:phone":"+34 955 95 37 58",
    "sg:postcode":"41410",
    "sg:province":"Sevilla",
    "wof:name":"Agricola La Baldia S. A.",
    "wof:placetype":"venue"
},
  "geometry": {"coordinates":[-5.5129299164,37.5121421814],"type":"Point"}
}