{
  "type": "Feature",
  "properties": {
    "iso:country":"ES",
    "sg:address":"Calle de Dr Fleming (del), 5",
    "sg:city":"Coslada",
    "sg:orig_category":"Arreglo, Reparaci\u00d3n, Piezas Sueltas De Televisi\u00d3n, V\u00cddeo, Hi",
    "sg:phone":"+34 916 72 25 49",
    "sg:postcode":"28820",
    "sg:province":"Madrid",
    "wof:name":"Melero Samaniego Jesus",
    "wof:placetype":"venue"
},
  "geometry": {"coordinates":[-3.5691726208,40.4235191345],"type":"Point"}
}