{
  "type": "Feature",
  "properties": {
    "iso:country":"ES",
    "sg:address":"Calle de Esperanto, Km. 0005,0",
    "sg:city":"Benidorm",
    "sg:orig_category":"Agentes, Concesionarios Y Sucursales De Veh\u00cdculos",
    "sg:phone":"+34 965 86 60 60",
    "sg:postcode":"03500",
    "sg:province":"Alicante",
    "sg:website":"www.marinamovil.com",
    "wof:name":"Marina Movil S.l.",
    "wof:placetype":"venue"
},
  "geometry": {"coordinates":[-0.1739459932,38.5365180969],"type":"Point"}
}