{
  "type": "Feature",
  "properties": {
    "addr:full":"Calle de Hernani, 33 Madrid Madrid 28020",
    "addr:housenumber":"33",
    "addr:postcode":"madrid;28020",
    "addr:street":"Calle De Hernani",
    "iso:country":"ES",
    "sg:address":"Calle de Hernani, 33",
    "sg:city":"Madrid",
    "sg:orig_category":"Restaurantes",
    "sg:phone":"+34 915 53 01 84",
    "sg:postcode":"28020",
    "sg:province":"Madrid",
    "wof:name":"Gurmesa Restauracion Y Animacion S.a.",
    "wof:placetype":"venue"
},
  "geometry": {"coordinates":[-3.7003960609,40.4483909607],"type":"Point"}
}