{
  "type": "Feature",
  "properties": {
    "iso:country":"ES",
    "sg:address":"Ctra General Del Norte, 33",
    "sg:city":"Cantillo",
    "sg:orig_category":"Abogados",
    "sg:phone":"+34 922 56 28 55",
    "sg:postcode":"38350",
    "sg:province":"Santa Cruz De Tenerife",
    "wof:name":"Rivero Rivero Emeterio Antonio",
    "wof:placetype":"venue"
},
  "geometry": {"coordinates":[-16.4174289703,28.4756546021],"type":"Point"}
}