{
  "type": "Feature",
  "properties": {
    "iso:country":"ES",
    "sg:address":"Calle de Reyes Catolicos, 16",
    "sg:city":"Almeria",
    "sg:orig_category":"M\u00c9dicos: Cirug\u00cda Ortop\u00c9dica Y Traumatolog\u00cda",
    "sg:phone":"+34 950 23 52 24",
    "sg:postcode":"04001",
    "sg:province":"Almer\u00eda",
    "wof:name":"Bueso Iglesias Jose Armando",
    "wof:placetype":"venue"
},
  "geometry": {"coordinates":[-2.4625029564,36.839050293],"type":"Point"}
}