{
  "type": "Feature",
  "properties": {
    "iso:country":"ES",
    "sg:address":"Barr Barcena, S/n",
    "sg:city":"Barcena De Pie De Concha",
    "sg:orig_category":"Administraciones Regionales, Departamentales Y Locales",
    "sg:phone":"+34 942 84 10 36",
    "sg:postcode":"39420",
    "sg:province":"Cantabria",
    "wof:name":"Ayuntamiento De Pie De Concha",
    "wof:placetype":"venue"
},
  "geometry": {"coordinates":[-4.0562381744,43.1292648315],"type":"Point"}
}