{
  "type": "Feature",
  "properties": {
    "iso:country":"ES",
    "sg:address":"Calle de Amazonas, 8",
    "sg:city":"Petrer",
    "sg:orig_category":"Zapatos (al Por Menor)",
    "sg:phone":"+34 966 95 54 68",
    "sg:postcode":"03610",
    "sg:province":"Alicante",
    "wof:name":"Industria Zapatera Del Vinalopo S.l.",
    "wof:placetype":"venue"
},
  "geometry": {"coordinates":[-0.766997695,38.4810371399],"type":"Point"}
}