{
  "type": "Feature",
  "properties": {
    "addr:full":"Calle de Valeriano Miranda, 3 Mieres Asturias 33600",
    "addr:housenumber":"3",
    "addr:postcode":"33600",
    "addr:street":"Calle De Valeriano Miranda",
    "iso:country":"ES",
    "sg:address":"Calle de Valeriano Miranda, 3",
    "sg:city":"Mieres",
    "sg:orig_category":"Universidades",
    "sg:phone":"+34 985 46 17 64",
    "sg:postcode":"33600",
    "sg:province":"Asturias",
    "wof:name":"Centro De Estudios Universitarios Mieres",
    "wof:placetype":"venue"
},
  "geometry": {"coordinates":[-5.7758669853,43.2499198914],"type":"Point"}
}