{
  "type": "Feature",
  "properties": {
    "iso:country":"ES",
    "sg:address":"Rond Sant Pere, 19",
    "sg:city":"Barcelona",
    "sg:orig_category":"Mutuas De Seguros",
    "sg:phone":"+34 933 01 20 32",
    "sg:postcode":"08010",
    "sg:province":"Barcelona",
    "wof:name":"Mutualidad De Futbolistas Espa\u00d1oles Dele",
    "wof:placetype":"venue"
},
  "geometry": {"coordinates":[2.1738159657,41.3894882202],"type":"Point"}
}