{
  "type": "Feature",
  "properties": {
    "addr:full":"Carrer de Joan Coromines, 9 Terrassa Barcelona 08221",
    "addr:housenumber":"9",
    "addr:postcode":"08221",
    "addr:street":"Carrer De Joan Coromines",
    "iso:country":"ES",
    "sg:address":"Carrer de Joan Coromines, 9",
    "sg:city":"Terrassa",
    "sg:orig_category":"Fabricaci\u00d3n, Importaci\u00d3n De Material Y Sistemas De Telecomunicaciones",
    "sg:phone":"+34 937 33 62 50",
    "sg:postcode":"08221",
    "sg:province":"Barcelona",
    "wof:name":"Comunica Con Elitel S.l.",
    "wof:placetype":"venue"
},
  "geometry": {"coordinates":[2.0097010136,41.5623207092],"type":"Point"}
}