{
  "type": "Feature",
  "properties": {
    "iso:country":"ES",
    "sg:address":"Calle de Pe\u00d1a Nueva, 28",
    "sg:city":"Madrid",
    "sg:orig_category":"Peluqueros: De Se\u00d1oras",
    "sg:phone":"+34 913 32 80 55",
    "sg:postcode":"28031",
    "sg:province":"Madrid",
    "wof:name":"Jimenez Arroyo Josefa",
    "wof:placetype":"venue"
},
  "geometry": {"coordinates":[-3.6208600998,40.3731155396],"type":"Point"}
}