{
  "type": "Feature",
  "properties": {
    "iso:country":"ES",
    "sg:address":"Calle de Andres Mellado, 61",
    "sg:city":"Madrid",
    "sg:orig_category":"Inmobiliaria (agencias)",
    "sg:phone":"+34 915 44 02 93",
    "sg:postcode":"28015",
    "sg:province":"Madrid",
    "wof:name":"A & A Investiments S.a.",
    "wof:placetype":"venue"
},
  "geometry": {"coordinates":[-3.714262,40.436825],"type":"Point"}
}