{
  "type": "Feature",
  "properties": {
    "iso:country":"ES",
    "sg:address":"Avda Alemania (de), S/n",
    "sg:city":"Playa Del Ingles",
    "sg:orig_category":"Restaurantes",
    "sg:phone":"+34 928 76 24 89",
    "sg:postcode":"35100",
    "sg:province":"Las Palmas",
    "wof:name":"Martin Martin Jacinto",
    "wof:placetype":"venue"
},
  "geometry": {"coordinates":[-15.5737190247,27.7490711212],"type":"Point"}
}