{
  "type": "Feature",
  "properties": {
    "iso:country":"ES",
    "sg:address":"Avda San Carlos, 9",
    "sg:city":"Arroyo De La Miel-benalmadena Costa",
    "sg:orig_category":"Prot\u00c9sicos Dentales",
    "sg:phone":"+34 952 56 22 22",
    "sg:postcode":"29630",
    "sg:province":"M\u00e1laga",
    "wof:name":"Melgar Gonzalez Jose Luis",
    "wof:placetype":"venue"
},
  "geometry": {"coordinates":[-4.5249090195,36.597328186],"type":"Point"}
}