{
  "type": "Feature",
  "properties": {
    "iso:country":"ES",
    "sg:address":"Calle de Amelia De Vilallonga, 10",
    "sg:city":"Pilas",
    "sg:orig_category":"Servicios De Telecomunicaciones",
    "sg:phone":"+34 955 75 48 00",
    "sg:postcode":"41840",
    "sg:province":"Sevilla",
    "wof:name":"Zurita  Byron Nelson",
    "wof:placetype":"venue"
},
  "geometry": {"coordinates":[-6.3021354675,37.3012161255],"type":"Point"}
}