{
  "type": "Feature",
  "properties": {
    "iso:country":"ES",
    "sg:address":"Carrer de Maria Maspons, 4",
    "sg:city":"Granollers",
    "sg:orig_category":"\u00d3pticos Optometristas (al Por Menor)",
    "sg:phone":"+34 938 60 60 64",
    "sg:postcode":"08402",
    "sg:province":"Barcelona",
    "wof:name":"Codina Fossas Marta",
    "wof:placetype":"venue"
},
  "geometry": {"coordinates":[2.2889239788,41.6074676514],"type":"Point"}
}