{
  "type": "Feature",
  "properties": {
    "iso:country":"ES",
    "sg:address":"Zna Indust Pont-xemma, 7",
    "sg:city":"Cornella Terri",
    "sg:orig_category":"Limpieza Con Chorro De Arena Y Con Granalla, Pulido",
    "sg:phone":"+34 972 59 50 96",
    "sg:postcode":"17844",
    "sg:province":"Girona",
    "wof:name":"Verges Bretcha Albert",
    "wof:placetype":"venue"
},
  "geometry": {"coordinates":[2.8163619041,42.0891227722],"type":"Point"}
}