{
  "type": "Feature",
  "properties": {
    "addr:full":"Calle de Hermanos Maristas, 9 Tui Pontevedra 36700",
    "addr:housenumber":"9",
    "addr:postcode":"36700",
    "addr:street":"Calle De Hermanos Maristas",
    "iso:country":"ES",
    "sg:address":"Calle de Hermanos Maristas, 9",
    "sg:city":"Tui",
    "sg:orig_category":"Asesor\u00cda Sobre Comunicaci\u00d3n De Empresas",
    "sg:phone":"+34 986 60 70 74",
    "sg:postcode":"36700",
    "sg:province":"Pontevedra",
    "wof:name":"Xestion Tui S.l.",
    "wof:placetype":"venue"
},
  "geometry": {"coordinates":[-8.6440658569,42.0519180298],"type":"Point"}
}