{
  "type": "Feature",
  "properties": {
    "addr:full":"Avda Salamanca, 2 Alacant Alicante 03003",
    "addr:housenumber":"2",
    "addr:postcode":"03003",
    "addr:street":"Avda Salamanca",
    "iso:country":"ES",
    "sg:address":"Avda Salamanca, 2",
    "sg:city":"Alacant",
    "sg:orig_category":"Ropa Para Ni\u00d1os (al Por Menor)",
    "sg:phone":"+34 965 92 07 45",
    "sg:postcode":"03003",
    "sg:province":"Alicante",
    "sg:website":"www.bershka.com",
    "wof:name":"Bershka Bsr Espa\u00f1a S.a.",
    "wof:placetype":"venue"
},
  "geometry": {"coordinates":[-0.4943889976,38.34349823],"type":"Point"}
}