{
  "type": "Feature",
  "properties": {
    "addr:full":"Calle de Pico Almanzor (del), 22 Humanes De Madrid Madrid 28970",
    "addr:housenumber":"22",
    "addr:postcode":"28970",
    "addr:street":"Calle De Pico Almanzor Del",
    "iso:country":"ES",
    "sg:address":"Calle de Pico Almanzor (del), 22",
    "sg:city":"Humanes De Madrid",
    "sg:orig_category":"Fabricaci\u00d3n De Muebles",
    "sg:phone":"+34 916 04 12 38",
    "sg:postcode":"28970",
    "sg:province":"Madrid",
    "wof:name":"Proyecto Xxi Arte Y Oficio S.l.",
    "wof:placetype":"venue"
},
  "geometry": {"coordinates":[-3.8149409294,40.262928009],"type":"Point"}
}