{
  "type": "Feature",
  "properties": {
    "addr:full":"Calle de Claudio Sanchez Albornoz, 1 Raso \u00c1vila 05489",
    "addr:housenumber":"1",
    "addr:postcode":"05489",
    "addr:street":"Calle De Claudio Sanchez Albornoz;A\u0301Vila",
    "iso:country":"ES",
    "sg:address":"Calle de Claudio Sanchez Albornoz, 1",
    "sg:city":"Raso",
    "sg:orig_category":"Hosteler\u00cda, Empleados",
    "sg:phone":"+34 920 38 97 80",
    "sg:postcode":"05489",
    "sg:province":"\u00c1vila",
    "wof:name":"Sanchez Lancho Teodoro",
    "wof:placetype":"venue"
},
  "geometry": {"coordinates":[-5.3392577171,40.1707420349],"type":"Point"}
}