{
  "type": "Feature",
  "properties": {
    "iso:country":"ES",
    "sg:address":"Carrer de Carme, 43",
    "sg:city":"Papiol",
    "sg:orig_category":"Artes Gr\u00c1ficas, Artes Pl\u00c1sticas (curso)",
    "sg:phone":"+34 936 73 03 86",
    "sg:postcode":"08754",
    "sg:province":"Barcelona",
    "wof:name":"Industrias Faeser S.a.l.",
    "wof:placetype":"venue"
},
  "geometry": {"coordinates":[2.0148301125,41.4390792847],"type":"Point"}
}