{
  "type": "Feature",
  "properties": {
    "addr:full":"Calle de San Anton, 13 Caceres C\u00e1ceres 10004",
    "addr:housenumber":"13",
    "addr:postcode":"10004",
    "addr:street":"Calle De San Anton;Ca\u0301Ceres",
    "iso:country":"ES",
    "sg:address":"Calle de San Anton, 13",
    "sg:city":"Caceres",
    "sg:orig_category":"Administradores De Bienes Y Delegados De Comunidades De Propietarios",
    "sg:phone":"+34 927 21 70 00",
    "sg:postcode":"10004",
    "sg:province":"C\u00e1ceres",
    "wof:name":"Progesefa S.l.",
    "wof:placetype":"venue"
},
  "geometry": {"coordinates":[-6.3753128052,39.4728660583],"type":"Point"}
}