{
  "type": "Feature",
  "properties": {
    "addr:full":"Calle de Paez De Ribera, 8 Sevilla Sevilla 41012",
    "addr:housenumber":"8",
    "addr:postcode":"41012",
    "addr:street":"Calle De Paez De Ribera",
    "iso:country":"ES",
    "sg:address":"Calle de Paez De Ribera, 8",
    "sg:city":"Sevilla",
    "sg:orig_category":"Agencias Y Agentes Comerciales, Representantes",
    "sg:phone":"+34 954 61 51 95",
    "sg:postcode":"41012",
    "sg:province":"Sevilla",
    "wof:name":"Alzueta Mu\u00f1oz Francisco",
    "wof:placetype":"venue"
},
  "geometry": {"coordinates":[-5.9877386093,37.3635482788],"type":"Point"}
}