{
  "type": "Feature",
  "properties": {
    "iso:country":"ES",
    "sg:address":"Carrer de Llobregat, 159",
    "sg:city":"Hospitalet Llobregat",
    "sg:orig_category":"Empresarios",
    "sg:phone":"+34 933 34 16 00",
    "sg:postcode":"08904",
    "sg:province":"Barcelona",
    "wof:name":"Fundacio Viure I Conviure",
    "wof:placetype":"venue"
},
  "geometry": {"coordinates":[2.121696949,41.3699951172],"type":"Point"}
}