{
  "type": "Feature",
  "properties": {
    "iso:country":"ES",
    "sg:address":"Calle de Telletxe, 1",
    "sg:city":"Algorta",
    "sg:orig_category":"Panader\u00cdas, Panader\u00cdas",
    "sg:phone":"+34 944 91 38 80",
    "sg:postcode":"48991",
    "sg:province":"Vizcaya",
    "wof:name":"Pazu 2004 S.l.",
    "wof:placetype":"venue"
},
  "geometry": {"coordinates":[-3.0099329948,43.3507347107],"type":"Point"}
}