{
  "type": "Feature",
  "properties": {
    "addr:full":"Cm\u00d1o Meixueiro, 21 Fonti\u00d1as Pontevedra 36214",
    "addr:housenumber":"21",
    "addr:postcode":"36214",
    "addr:street":"Meixueiro",
    "iso:country":"ES",
    "sg:address":"Cm\u00d1o Meixueiro, 21",
    "sg:city":"Fonti\u00d1as",
    "sg:orig_category":"Molduras, Junquillos, Listones Y Molduras Perforadas",
    "sg:phone":"+34 986 27 61 20",
    "sg:postcode":"36214",
    "sg:province":"Pontevedra",
    "wof:name":"Caride Vila Julia",
    "wof:placetype":"venue"
},
  "geometry": {"coordinates":[-8.7059106827,42.2124443054],"type":"Point"}
}