{
  "type": "Feature",
  "properties": {
    "addr:full":"Calle de Mercedes (las), 19 Arenas -areeta Vizcaya 48930",
    "addr:housenumber":"19;areeta",
    "addr:postcode":"48930",
    "addr:street":"Calle De Mercedes Las",
    "iso:country":"ES",
    "sg:address":"Calle de Mercedes (las), 19",
    "sg:city":"Arenas -areeta",
    "sg:orig_category":"Ropa Para Ni\u00d1os (al Por Menor)",
    "sg:phone":"+34 944 80 27 01",
    "sg:postcode":"48930",
    "sg:province":"Vizcaya",
    "wof:name":"Barayazarra Rodriguez Teresa",
    "wof:placetype":"venue"
},
  "geometry": {"coordinates":[-3.0139029026,43.3266563416],"type":"Point"}
}