{
  "type": "Feature",
  "properties": {
    "addr:full":"Calle de Loteria, 2 Bilbao Vizcaya 48005",
    "addr:housenumber":"2",
    "addr:postcode":"48005",
    "addr:street":"Calle De Loteria",
    "iso:country":"ES",
    "sg:address":"Calle de Loteria, 2",
    "sg:city":"Bilbao",
    "sg:orig_category":"M\u00c9dicos: Foniatr\u00cda Y Logopedia",
    "sg:phone":"+34 944 15 07 78",
    "sg:postcode":"48005",
    "sg:province":"Vizcaya",
    "wof:name":"Qui\u00f1ones Echevarria Carmen",
    "wof:placetype":"venue"
},
  "geometry": {"coordinates":[-2.9240310192,43.2577056885],"type":"Point"}
}