{
  "type": "Feature",
  "properties": {
    "addr:full":"Calle de Bajo Vinalopo, 1 Mislata Valencia 46920",
    "addr:housenumber":"1",
    "addr:postcode":"46920",
    "addr:street":"Calle De Bajo Vinalopo",
    "iso:country":"ES",
    "sg:address":"Calle de Bajo Vinalopo, 1",
    "sg:city":"Mislata",
    "sg:orig_category":"Alumbrados",
    "sg:phone":"+34 963 79 29 19",
    "sg:postcode":"46920",
    "sg:province":"Valencia",
    "wof:name":"Pianoteca S.a",
    "wof:placetype":"venue"
},
  "geometry": {"coordinates":[-0.4268431962,39.4721374512],"type":"Point"}
}