{
  "type": "Feature",
  "properties": {
    "iso:country":"ES",
    "sg:address":"Carrer de Junceda, 12",
    "sg:city":"Rubi",
    "sg:orig_category":"Molduras, Junquillos, Listones Y Molduras Perforadas",
    "sg:phone":"+34 936 97 34 19",
    "sg:postcode":"08191",
    "sg:province":"Barcelona",
    "wof:name":"Fabre Sanchez Juan",
    "wof:placetype":"venue"
},
  "geometry": {"coordinates":[2.0380399227,41.4940986633],"type":"Point"}
}