{
  "type": "Feature",
  "properties": {
    "iso:country":"ES",
    "sg:address":"Trva Timanfaya, 8",
    "sg:city":"Alcorcon",
    "sg:orig_category":"Molduras, Junquillos, Listones Y Molduras Perforadas",
    "sg:phone":"+34 916 42 71 61",
    "sg:postcode":"28924",
    "sg:province":"Madrid",
    "wof:name":"Ya\u00f1ez Lopez Julio",
    "wof:placetype":"venue"
},
  "geometry": {"coordinates":[-3.813308239,40.3464317322],"type":"Point"}
}