{
  "type": "Feature",
  "properties": {
    "addr:full":"La Muela, 45 El Viso Alcor Sevilla 41520",
    "addr:housenumber":"45",
    "addr:postcode":"41520",
    "addr:street":"La Muela",
    "iso:country":"ES",
    "sg:address":"La Muela, 45",
    "sg:city":"El Viso Alcor",
    "sg:orig_category":"Agentes, Concesionarios Y Sucursales De Camiones Y Veh\u00cdculos Industriales",
    "sg:phone":"+34 955 94 56 16",
    "sg:postcode":"41520",
    "sg:province":"Sevilla",
    "wof:name":"Moreno Marquez Manuel",
    "wof:placetype":"venue"
},
  "geometry": {"coordinates":[-5.7220811844,37.3838844299],"type":"Point"}
}