{
  "type": "Feature",
  "properties": {
    "iso:country":"ES",
    "sg:address":"Calle de Huerta Del Gato, 20",
    "sg:city":"Piedrahita",
    "sg:classifiers":[
        {
            "category":"Taxi",
            "type":"Transportation"
        }
    ],
    "sg:phone":"+34 920 36 10 71",
    "sg:postcode":"05500",
    "sg:province":"\u00c1vila",
    "wof:name":"Gonzalez Sanchez Pedro Tomas",
    "wof:placetype":"venue"
},
  "geometry": {"coordinates":[-5.3284578323,40.466796875],"type":"Point"}
}