{
  "type": "Feature",
  "properties": {
    "addr:full":"Plaz Cruz Del Ca\u00d1amelar, 2 Valencia Valencia 46011",
    "addr:housenumber":"2",
    "addr:postcode":"46011",
    "addr:street":"Plaz Cruz Del Can\u0303Amelar",
    "iso:country":"ES",
    "sg:address":"Plaz Cruz Del Ca\u00d1amelar, 2",
    "sg:city":"Valencia",
    "sg:orig_category":"Caf\u00c9s, Bares, Cervecer\u00cdas",
    "sg:phone":"+34 963 55 77 20",
    "sg:postcode":"46011",
    "sg:province":"Valencia",
    "wof:name":"Eurotel Sur S.l.",
    "wof:placetype":"venue"
},
  "geometry": {"coordinates":[-0.3315449953,39.4679946899],"type":"Point"}
}