{
  "type": "Feature",
  "properties": {
    "addr:full":"Calle de Encomienda, 8 Alange Badajoz 06840",
    "addr:housenumber":"8",
    "addr:postcode":"06840",
    "addr:street":"Calle De Encomienda",
    "iso:country":"ES",
    "sg:address":"Calle de Encomienda, 8",
    "sg:city":"Alange",
    "sg:orig_category":"Peluqueros: De Se\u00d1oras",
    "sg:phone":"+34 924 36 55 30",
    "sg:postcode":"06840",
    "sg:province":"Badajoz",
    "wof:name":"Gordillo Gomez Manuela",
    "wof:placetype":"venue"
},
  "geometry": {"coordinates":[-6.2472138405,38.7849388123],"type":"Point"}
}