{
  "type": "Feature",
  "properties": {
    "addr:full":"Rua Figueira (da), 2 Ourense Ourense 32001",
    "addr:postcode":"32001",
    "addr:street":"Rua Figueira Da",
    "iso:country":"ES",
    "sg:address":"Rua Figueira (da), 2",
    "sg:city":"Ourense",
    "sg:orig_category":"Maquinaria Y Herramientas Para Madera, Pvc, Aluminio Y Aperos (fabricaci\u00d3n, Comercio)",
    "sg:phone":"+34 988 21 99 29",
    "sg:postcode":"32001",
    "sg:province":"Ourense",
    "wof:name":"Comercial David Perez S.l.",
    "wof:placetype":"venue"
},
  "geometry": {"coordinates":[-7.8685097694,42.3581962585],"type":"Point"}
}