{
  "type": "Feature",
  "properties": {
    "iso:country":"ES",
    "sg:address":"Rua Naturista Lopez Seoane, 21",
    "sg:city":"Ferrol",
    "sg:orig_category":"Locales Y Clases De Danza",
    "sg:phone":"+34 981 35 10 49",
    "sg:postcode":"15403",
    "sg:province":"La Coru\u00f1a",
    "wof:name":"Rico Sobrino Paloma",
    "wof:placetype":"venue"
},
  "geometry": {"coordinates":[-8.2249994278,43.4831733704],"type":"Point"}
}