{
  "type": "Feature",
  "properties": {
    "addr:full":"Ptge Forn, 5 Igualada Barcelona 08700",
    "addr:housenumber":"5",
    "addr:postcode":"08700",
    "addr:street":"Ptge Forn",
    "iso:country":"ES",
    "sg:address":"Ptge Forn, 5",
    "sg:city":"Igualada",
    "sg:orig_category":"Platos Preparados Refrigerados (fabricaci\u00d3n, Al Por Mayor)",
    "sg:phone":"+34 938 03 19 11",
    "sg:postcode":"08700",
    "sg:province":"Barcelona",
    "wof:name":"Llorachd Aribau Salvador",
    "wof:placetype":"venue"
},
  "geometry": {"coordinates":[1.6170699596,41.5795402527],"type":"Point"}
}