{
  "type": "Feature",
  "properties": {
    "iso:country":"ES",
    "sg:address":"Calle de Albeniz, 1",
    "sg:city":"Marbella",
    "sg:orig_category":"Ense\u00d1anza Variada",
    "sg:phone":"+34 952 82 18 00",
    "sg:postcode":"29600",
    "sg:province":"M\u00e1laga",
    "wof:name":"Tutor Gabinete De Estudios S.l.",
    "wof:placetype":"venue"
},
  "geometry": {"coordinates":[-4.8782281876,36.5131454468],"type":"Point"}
}