{
  "type": "Feature",
  "properties": {
    "iso:country":"ES",
    "sg:address":"Carrer de Jaume Casanovas, 105",
    "sg:city":"Prat Llobregat",
    "sg:orig_category":"Ropa De Hogar (al Por Menor)",
    "sg:phone":"+34 933 79 15 26",
    "sg:postcode":"08820",
    "sg:province":"Barcelona",
    "wof:name":"Ceron Quiles Alfonso",
    "wof:placetype":"venue"
},
  "geometry": {"coordinates":[2.0864720345,41.3289909363],"type":"Point"}
}