{
  "type": "Feature",
  "properties": {
    "addr:full":"Calle de San Isidro, 4 Valladolid Valladolid 47004",
    "addr:housenumber":"4",
    "addr:postcode":"47004",
    "addr:street":"Calle De San Isidro",
    "iso:country":"ES",
    "sg:address":"Calle de San Isidro, 4",
    "sg:city":"Valladolid",
    "sg:orig_category":"Centros Empresariales",
    "sg:phone":"+34 983 20 41 02",
    "sg:postcode":"47004",
    "sg:province":"Valladolid",
    "wof:name":"Disart 21 S.l.",
    "wof:placetype":"venue"
},
  "geometry": {"coordinates":[-4.7167158127,41.6464538574],"type":"Point"}
}