{
  "type": "Feature",
  "properties": {
    "addr:full":"Avda Rafael Alberti, 32 Madrid Madrid 28038",
    "addr:housenumber":"32",
    "addr:postcode":"madrid;28038",
    "addr:street":"Avda Rafael Alberti",
    "iso:country":"ES",
    "sg:address":"Avda Rafael Alberti, 32",
    "sg:city":"Madrid",
    "sg:orig_category":"M\u00c9dicos: Salud P\u00dablica",
    "sg:phone":"+34 913 03 89 28",
    "sg:postcode":"28038",
    "sg:province":"Madrid",
    "wof:name":"Alvarez Suarez Alfredo",
    "wof:placetype":"venue"
},
  "geometry": {"coordinates":[-3.6424098015,40.3849220276],"type":"Point"}
}