{
  "type": "Feature",
  "properties": {
    "iso:country":"ES",
    "sg:address":"Carrer de Francesc Macia, 25",
    "sg:city":"Lloren\u00e7 Penedes",
    "sg:orig_category":"Quincaller\u00cda (al Por Menor)",
    "sg:phone":"+34 977 67 71 23",
    "sg:postcode":"43712",
    "sg:province":"Tarragona",
    "wof:name":"Electro-llar I Ferreteria Cal Jep S.l.",
    "wof:placetype":"venue"
},
  "geometry": {"coordinates":[1.5507370234,41.2840118408],"type":"Point"}
}