{
  "type": "Feature",
  "properties": {
    "addr:full":"Carrer de Francesc Macia, 25 Lloren\u00e7 Penedes Tarragona 43712",
    "addr:housenumber":"25",
    "addr:postcode":"43712",
    "addr:street":"Carrer De Francesc Macia",
    "iso:country":"ES",
    "sg:address":"Carrer de Francesc Macia, 25",
    "sg:city":"Lloren\u00e7 Penedes",
    "sg:orig_category":"Quincaller\u00cda (al Por Menor)",
    "sg:phone":"+34 977 67 71 23",
    "sg:postcode":"43712",
    "sg:province":"Tarragona",
    "wof:name":"Electro-llar I Ferreteria Cal Jep S.l.",
    "wof:placetype":"venue"
},
  "geometry": {"coordinates":[1.5507370234,41.2840118408],"type":"Point"}
}