{
  "type": "Feature",
  "properties": {
    "iso:country":"ES",
    "sg:address":"Urtatza Auzoa, S/n",
    "sg:city":"Legazpi",
    "sg:orig_category":"Maquinaria Para Industrias Diversas",
    "sg:phone":"+34 943 73 06 92",
    "sg:postcode":"20230",
    "sg:province":"Guip\u00f9zcoa",
    "wof:name":"Talleres Protegidos Gureak S. A.",
    "wof:placetype":"venue"
},
  "geometry": {"coordinates":[-2.3409628868,43.0594902039],"type":"Point"}
}