{
  "type": "Feature",
  "properties": {
    "addr:full":"Carr Diana, 4 Veinat De Diana Girona 17464",
    "addr:housenumber":"4",
    "addr:postcode":"17464",
    "addr:street":"Carr Diana",
    "iso:country":"ES",
    "sg:address":"Carr Diana, 4",
    "sg:city":"Veinat De Diana",
    "sg:orig_category":"Agricultura: Abastecimiento Y Cosechado (negocio)",
    "sg:phone":"+34 972 79 81 47",
    "sg:postcode":"17464",
    "sg:province":"Girona",
    "wof:name":"Agricula Gines S.c.p.",
    "wof:placetype":"venue"
},
  "geometry": {"coordinates":[2.9580829144,42.0746917725],"type":"Point"}
}