{
  "type": "Feature",
  "properties": {
    "addr:full":"Urkizu Pasealekua, 19 Eibar Guip\u00f9zcoa 20600",
    "addr:housenumber":"19",
    "addr:postcode":"20600",
    "addr:street":"Urkizu Pasealekua;Guipu\u0300Zcoa",
    "iso:country":"ES",
    "sg:address":"Urkizu Pasealekua, 19",
    "sg:city":"Eibar",
    "sg:orig_category":"Suministros Y Materiales Industriales",
    "sg:phone":"+34 943 12 12 71",
    "sg:postcode":"20600",
    "sg:province":"Guip\u00f9zcoa",
    "wof:name":"Exclusivas Olalsa S.l.",
    "wof:placetype":"venue"
},
  "geometry": {"coordinates":[-2.4621250629,43.1871833801],"type":"Point"}
}