{
  "type": "Feature",
  "properties": {
    "iso:country":"ES",
    "sg:address":"Avda Zaragoza, 5",
    "sg:city":"Calatayud",
    "sg:orig_category":"Alimentaci\u00d3n General (al Por Menor)",
    "sg:phone":"+34 976 88 54 28",
    "sg:postcode":"50300",
    "sg:province":"Zaragoza",
    "wof:name":"La Charluca S.l.",
    "wof:placetype":"venue"
},
  "geometry": {"coordinates":[-1.6215440035,41.3547401428],"type":"Point"}
}