{
  "type": "Feature",
  "properties": {
    "addr:full":"Carr Miguel Servet, S/n Almacelles Lleida 25100",
    "addr:housenumber":"s / n",
    "addr:postcode":"25100",
    "addr:street":"Carr Miguel Servet",
    "iso:country":"ES",
    "sg:address":"Carr Miguel Servet, S/n",
    "sg:city":"Almacelles",
    "sg:orig_category":"Empresas De Carpinter\u00cda Met\u00c1lica",
    "sg:phone":"+34 973 74 02 76",
    "sg:postcode":"25100",
    "sg:province":"Lleida",
    "wof:name":"Metalicas Sanz S.a.",
    "wof:placetype":"venue"
},
  "geometry": {"coordinates":[0.4403150082,41.7284088135],"type":"Point"}
}