{
  "type": "Feature",
  "properties": {
    "addr:full":"Calle de Juan Bravo, 54 Segovia Segovia 40001",
    "addr:housenumber":"54",
    "addr:postcode":"40001",
    "addr:street":"Calle De Juan Bravo",
    "iso:country":"ES",
    "sg:address":"Calle de Juan Bravo, 54",
    "sg:city":"Segovia",
    "sg:orig_category":"Ingenier\u00cda, Centros De Estudios (industria)",
    "sg:phone":"+34 921 46 27 44",
    "sg:postcode":"40001",
    "sg:province":"Segovia",
    "wof:name":"Genique Martin Carlos Alfonso",
    "wof:placetype":"venue"
},
  "geometry": {"coordinates":[-4.1203927994,40.9480857849],"type":"Point"}
}