{
  "type": "Feature",
  "properties": {
    "addr:full":"Calle de Rosas De Aravaca, 1 Madrid Madrid 28023",
    "addr:housenumber":"1",
    "addr:postcode":"28023",
    "addr:street":"Calle De Rosas De Aravaca",
    "iso:country":"ES",
    "sg:address":"Calle de Rosas De Aravaca, 1",
    "sg:city":"Madrid",
    "sg:orig_category":"Asesor\u00cda De Formaci\u00d3n Y Gesti\u00d3n De Personal",
    "sg:phone":"+34 917 40 00 31",
    "sg:postcode":"28023",
    "sg:province":"Madrid",
    "wof:name":"Wakonigg Figueras Clara",
    "wof:placetype":"venue"
},
  "geometry": {"coordinates":[-3.782119751,40.4509620667],"type":"Point"}
}