{
  "type": "Feature",
  "properties": {
    "addr:full":"Carrer de Doctor Reig, 36 Viladecans Barcelona 08840",
    "addr:housenumber":"36",
    "addr:postcode":"08840",
    "addr:street":"Carrer De Doctor Reig",
    "iso:country":"ES",
    "sg:address":"Carrer de Doctor Reig, 36",
    "sg:city":"Viladecans",
    "sg:orig_category":"Ropa Para Ni\u00d1os (al Por Menor)",
    "sg:phone":"+34 936 58 29 52",
    "sg:postcode":"08840",
    "sg:province":"Barcelona",
    "wof:name":"Martinez Gomez Gloria",
    "wof:placetype":"venue"
},
  "geometry": {"coordinates":[2.0145459175,41.3182525635],"type":"Point"}
}