{
  "type": "Feature",
  "properties": {
    "iso:country":"ES",
    "sg:address":"Avda Alcalde Alvaro Domecq, 6",
    "sg:city":"Jerez De La Frontera",
    "sg:orig_category":"Centros Empresariales",
    "sg:phone":"+34 956 34 60 81",
    "sg:postcode":"11405",
    "sg:province":"C\u00e1diz",
    "sg:website":"www.fedejerez.com",
    "wof:name":"Federacion De Bodegas Del Marco De Jerez",
    "wof:placetype":"venue"
},
  "geometry": {"coordinates":[-6.1229290962,36.6982116699],"type":"Point"}
}