{
  "type": "Feature",
  "properties": {
    "iso:country":"ES",
    "sg:address":"Avda Valencia, 128",
    "sg:city":"Villanueva Arzobispo",
    "sg:orig_category":"Producci\u00d3n De Abonos Y De Fertilizantes",
    "sg:phone":"+34 953 45 02 89",
    "sg:postcode":"23330",
    "sg:province":"Ja\u00e9n",
    "wof:name":"Fuentes Pinel Francisco",
    "wof:placetype":"venue"
},
  "geometry": {"coordinates":[-3.0007519722,38.1737174988],"type":"Point"}
}