{
  "type": "Feature",
  "properties": {
    "addr:full":"Avda Casalduch, 60 Castellon Castell\u00f3n 12005",
    "addr:housenumber":"60",
    "addr:postcode":"12005",
    "addr:street":"Avda Casalduch",
    "iso:country":"ES",
    "sg:address":"Avda Casalduch, 60",
    "sg:city":"Castellon",
    "sg:orig_category":"Laboratorios Y Trabajos De Fotograf\u00cda, V\u00cddeo Y Cine",
    "sg:phone":"+34 964 25 46 57",
    "sg:postcode":"12005",
    "sg:province":"Castell\u00f3n",
    "wof:name":"Labomator S.l.",
    "wof:placetype":"venue"
},
  "geometry": {"coordinates":[-0.041788999,39.9770507812],"type":"Point"}
}