{
  "type": "Feature",
  "properties": {
    "iso:country":"ES",
    "sg:address":"Calle de Jose Santos Gonzalez, 33",
    "sg:city":"San Fernando",
    "sg:classifiers":[
        {
            "category":"Communications",
            "type":"Services"
        }
    ],
    "sg:phone":"+34 928 76 85 00",
    "sg:postcode":"35100",
    "sg:province":"Las Palmas",
    "sg:tags":[
        "televisiones",
        "y",
        "radio"
    ],
    "wof:name":"Onda Latina Radio S.l.",
    "wof:placetype":"venue"
},
  "geometry": {"coordinates":[-15.5842504501,28.0904903412],"type":"Point"}
}