{
  "type": "Feature",
  "properties": {
    "addr:full":"Avda Catalu\u00d1a (de), 11 San Sebastian De Los Reyes Madrid 28700",
    "addr:housenumber":"11",
    "addr:postcode":"28700",
    "addr:street":"Avda Catalun\u0303A De",
    "iso:country":"ES",
    "sg:address":"Avda Catalu\u00d1a (de), 11",
    "sg:city":"San Sebastian De Los Reyes",
    "sg:orig_category":"Complementos De Vestir (al Por Menor)",
    "sg:phone":"+34 916 53 48 67",
    "sg:postcode":"28700",
    "sg:province":"Madrid",
    "wof:name":"Grupo Michad S.l.",
    "wof:placetype":"venue"
},
  "geometry": {"coordinates":[-3.5000019073,40.6055603027],"type":"Point"}
}