{
  "type": "Feature",
  "properties": {
    "addr:full":"Pg Sant Joan, 138 Barcelona Barcelona 08037",
    "addr:housenumber":"138",
    "addr:postcode":"08037",
    "addr:street":"Pg Sant Joan",
    "iso:country":"ES",
    "sg:address":"Pg Sant Joan, 138",
    "sg:city":"Barcelona",
    "sg:orig_category":"Supermercados Y Hipermercados",
    "sg:phone":"+34 932 08 07 40",
    "sg:postcode":"08037",
    "sg:province":"Barcelona",
    "wof:name":"Tiendas De Conveniencia S.a.",
    "wof:placetype":"venue"
},
  "geometry": {"coordinates":[2.1675770283,41.4013557434],"type":"Point"}
}