{
  "type": "Feature",
  "properties": {
    "addr:full":"Calle de Turbintos, S/n Alberca De Las Torres Murcia 30150",
    "addr:housenumber":"s / n",
    "addr:postcode":"30150",
    "addr:street":"Calle De Turbintos",
    "iso:country":"ES",
    "sg:address":"Calle de Turbintos, S/n",
    "sg:city":"Alberca De Las Torres",
    "sg:orig_category":"Importaci\u00d3n, Exportaci\u00d3n Y Comercios De Productos Textiles",
    "sg:phone":"+34 968 84 08 04",
    "sg:postcode":"30150",
    "sg:province":"Murcia",
    "wof:name":"Patronato De La Seda De La Region De Murcia",
    "wof:placetype":"venue"
},
  "geometry": {"coordinates":[-1.135668993,37.9414215088],"type":"Point"}
}