{
  "type": "Feature",
  "properties": {
    "iso:country":"ES",
    "sg:address":"Calle de Raul Guerra Garrido, 2",
    "sg:city":"Cacabelos",
    "sg:orig_category":"Ropa Para Se\u00d1oras Y Caballeros (al Por Menor)",
    "sg:phone":"+34 987 54 63 39",
    "sg:postcode":"24540",
    "sg:province":"Le\u00f3n",
    "wof:name":"Los Salmantinos C.b.",
    "wof:placetype":"venue"
},
  "geometry": {"coordinates":[-6.7232689857,42.5972709656],"type":"Point"}
}