{
  "type": "Feature",
  "properties": {
    "iso:country":"ES",
    "sg:address":"Calle de Laguneta, 8",
    "sg:city":"Grazalema",
    "sg:orig_category":"Formaci\u00d3n Continuada (variada)",
    "sg:phone":"+34 956 13 23 61",
    "sg:postcode":"11610",
    "sg:province":"C\u00e1diz",
    "wof:name":"Rios Perez Cristobal",
    "wof:placetype":"venue"
},
  "geometry": {"coordinates":[-5.3646388054,36.7581596375],"type":"Point"}
}