{
  "type": "Feature",
  "properties": {
    "iso:country":"ES",
    "sg:address":"Pase Zarategi De, 70",
    "sg:city":"Donostia-san Sebastian",
    "sg:orig_category":"Distribuci\u00d3n De Petr\u00d3leo Y Derivados",
    "sg:phone":"+34 943 29 11 70",
    "sg:postcode":"20015",
    "sg:province":"Guip\u00f9zcoa",
    "wof:name":"Europea De Mariscos Y Pescados S.l.",
    "wof:placetype":"venue"
},
  "geometry": {"coordinates":[-1.9538509846,43.3168334961],"type":"Point"}
}