{
  "type": "Feature",
  "properties": {
    "iso:country":"ES",
    "sg:address":"Carretera Caniles, S/n",
    "sg:city":"Baza",
    "sg:orig_category":"Confecci\u00d3n De Zapatos",
    "sg:phone":"+34 958 70 01 84",
    "sg:postcode":"18800",
    "sg:province":"Granada",
    "wof:name":"Hermanos Soriano C.b.",
    "wof:placetype":"venue"
},
  "geometry": {"coordinates":[-2.7678890228,37.4831848145],"type":"Point"}
}