{
  "type": "Feature",
  "properties": {
    "addr:full":"Calle de Garcia De Paredes, 25 Badajoz Badajoz 06006",
    "addr:housenumber":"25",
    "addr:postcode":"06006",
    "addr:street":"Calle De Garcia De Paredes",
    "iso:country":"ES",
    "sg:address":"Calle de Garcia De Paredes, 25",
    "sg:city":"Badajoz",
    "sg:orig_category":"Servicios Gsm",
    "sg:phone":"+34 924 27 33 49",
    "sg:postcode":"06006",
    "sg:province":"Badajoz",
    "wof:name":"Europa Excom S.l.",
    "wof:placetype":"venue"
},
  "geometry": {"coordinates":[-6.9827528,38.8862266541],"type":"Point"}
}