{
  "type": "Feature",
  "properties": {
    "addr:full":"B. Paloma, S/n Almu\u00f1ecar Granada 18690",
    "addr:housenumber":"s",
    "addr:postcode":"18690",
    "addr:street":"B. Paloma;/ N Almun\u0303Ecar",
    "iso:country":"ES",
    "sg:address":"B. Paloma, S/n",
    "sg:city":"Almu\u00f1ecar",
    "sg:orig_category":"Alquiler De Veh\u00cdculos: Turismos Y Utilitarios",
    "sg:phone":"+34 958 63 07 08",
    "sg:postcode":"18690",
    "sg:province":"Granada",
    "wof:name":"Sidinsiel S.l.",
    "wof:placetype":"venue"
},
  "geometry": {"coordinates":[-3.7554039955,36.7381591797],"type":"Point"}
}