{
  "type": "Feature",
  "properties": {
    "iso:country":"ES",
    "sg:address":"Calle de Barrameda, 34",
    "sg:city":"Sanlucar De Barrameda",
    "sg:orig_category":"Ropa De Hogar (al Por Menor)",
    "sg:phone":"+34 956 38 04 26",
    "sg:postcode":"11540",
    "sg:province":"C\u00e1diz",
    "wof:name":"Capdevila De Los Reyes Antonio Jose",
    "wof:placetype":"venue"
},
  "geometry": {"coordinates":[-6.361125946,36.7788124084],"type":"Point"}
}