{
  "type": "Feature",
  "properties": {
    "addr:full":"Calle de Pozoblanco, S/n Villanueva Cordoba C\u00f3rdoba 14440",
    "addr:housenumber":"s",
    "addr:postcode":"14440",
    "addr:street":"Calle De Pozoblanco;/ N;Cordoba Co\u0301Rdoba",
    "iso:country":"ES",
    "sg:address":"Calle de Pozoblanco, S/n",
    "sg:city":"Villanueva Cordoba",
    "sg:orig_category":"Producci\u00d3n, Venta De Productos De Agricultura Biol\u00d3gica",
    "sg:phone":"+34 957 12 09 69",
    "sg:postcode":"14440",
    "sg:province":"C\u00f3rdoba",
    "wof:name":"Ortega Mu\u00f1oz Juana",
    "wof:placetype":"venue"
},
  "geometry": {"coordinates":[-4.6345191002,38.3240814209],"type":"Point"}
}