{
  "type": "Feature",
  "properties": {
    "addr:full":"Carrer de Pare Claret, 63 Roses Girona 17480",
    "addr:housenumber":"63",
    "addr:postcode":"17480",
    "addr:street":"Carrer De Pare Claret",
    "iso:country":"ES",
    "sg:address":"Carrer de Pare Claret, 63",
    "sg:city":"Roses",
    "sg:orig_category":"Promotores Constructores",
    "sg:phone":"+34 972 25 51 18",
    "sg:postcode":"17480",
    "sg:province":"Girona",
    "wof:name":"Construcciones Horizon S.a.",
    "wof:placetype":"venue"
},
  "geometry": {"coordinates":[3.182708025,42.2622184753],"type":"Point"}
}