{
  "type": "Feature",
  "properties": {
    "addr:full":"Avda Galicia De, 11 Luarca Asturias 33700",
    "addr:housenumber":"11",
    "addr:postcode":"33700",
    "addr:street":"Avda Galicia De",
    "iso:country":"ES",
    "sg:address":"Avda Galicia De, 11",
    "sg:city":"Luarca",
    "sg:orig_category":"Estudios Y Construcci\u00d3n De Acuarios Y Viveros",
    "sg:phone":"+34 985 47 04 66",
    "sg:postcode":"33700",
    "sg:province":"Asturias",
    "wof:name":"Mendez Menendez Maria Elisa",
    "wof:placetype":"venue"
},
  "geometry": {"coordinates":[-6.5396680832,43.5403404236],"type":"Point"}
}