{
  "type": "Feature",
  "properties": {
    "iso:country":"ES",
    "sg:address":"Calle de Don Bosco, 25",
    "sg:city":"Ubeda",
    "sg:orig_category":"Fabricaci\u00d3n De Enlosados, Soler\u00cdas",
    "sg:phone":"+34 953 75 50 08",
    "sg:postcode":"23400",
    "sg:province":"Ja\u00e9n",
    "sg:website":"www.porcelanosagrupo.com",
    "wof:name":"Porceral S.a.",
    "wof:placetype":"venue"
},
  "geometry": {"coordinates":[-3.3792934418,38.017288208],"type":"Point"}
}