{
  "type": "Feature",
  "properties": {
    "iso:country":"ES",
    "sg:address":"Calle de San Pedro De Carde\u00d1a, 130",
    "sg:city":"Burgos",
    "sg:orig_category":"Frutas Y Legumbres Frescas (al Por Mayor)",
    "sg:phone":"+34 947 27 69 34",
    "sg:postcode":"09002",
    "sg:province":"Burgos",
    "wof:name":"Hermanos Miguel Garcia S.l.",
    "wof:placetype":"venue"
},
  "geometry": {"coordinates":[-3.6807599068,42.3412132263],"type":"Point"}
}