{
  "type": "Feature",
  "properties": {
    "iso:country":"ES",
    "sg:address":"Calle de Miguel Fluiters, 20",
    "sg:city":"Guadalajara",
    "sg:orig_category":"Estancos",
    "sg:phone":"+34 949 21 21 98",
    "sg:postcode":"19001",
    "sg:province":"Guadalajara",
    "wof:name":"Garcia Herrera Belen",
    "wof:placetype":"venue"
},
  "geometry": {"coordinates":[-3.1673378944,40.6348876953],"type":"Point"}
}