{
  "type": "Feature",
  "properties": {
    "addr:full":"Las Cuevas, 4 Ribaseca Le\u00f3n 24391",
    "addr:housenumber":"4",
    "addr:postcode":"24391",
    "addr:street":"Cuevas;Leo\u0301N",
    "iso:country":"ES",
    "sg:address":"Las Cuevas, 4",
    "sg:city":"Ribaseca",
    "sg:orig_category":"Muebles, Minoristas",
    "sg:phone":"+34 987 28 03 69",
    "sg:postcode":"24391",
    "sg:province":"Le\u00f3n",
    "sg:website":"www.paginasamarillas.es",
    "wof:name":"Blanco Del Pozo Eva Maria",
    "wof:placetype":"venue"
},
  "geometry": {"coordinates":[-5.6244401932,42.5436477661],"type":"Point"}
}