{
  "type": "Feature",
  "properties": {
    "iso:country":"ES",
    "sg:address":"Calle de Nu\u00d1ez De Balboa, 10",
    "sg:city":"Villafranca De Los Barros",
    "sg:orig_category":"Empresas De Carpinter\u00cda Met\u00c1lica",
    "sg:phone":"+34 924 52 42 90",
    "sg:postcode":"06220",
    "sg:province":"Badajoz",
    "wof:name":"Blanco Bogallo Vicente",
    "wof:placetype":"venue"
},
  "geometry": {"coordinates":[-6.344189167,38.5589942932],"type":"Point"}
}