{
  "type": "Feature",
  "properties": {
    "iso:country":"ES",
    "sg:address":"Calle de Real De Burgos, 12",
    "sg:city":"Valladolid",
    "sg:orig_category":"Venta, Instalaci\u00d3n, Reparaci\u00d3n De Antenas Para Televisi\u00d3n",
    "sg:phone":"+34 983 26 74 00",
    "sg:postcode":"47011",
    "sg:province":"Valladolid",
    "wof:name":"Hernaez Barriocanal Jose Luis",
    "wof:placetype":"venue"
},
  "geometry": {"coordinates":[-4.7184100151,41.6581268311],"type":"Point"}
}