{
  "type": "Feature",
  "properties": {
    "addr:full":"Calle de Ramiro De Maeztu, 31 Valencia Valencia 46022",
    "addr:housenumber":"31",
    "addr:postcode":"46022",
    "addr:street":"Calle De Ramiro De Maeztu",
    "iso:country":"ES",
    "sg:address":"Calle de Ramiro De Maeztu, 31",
    "sg:city":"Valencia",
    "sg:orig_category":"Cl\u00cdnicas Dentales",
    "sg:phone":"+34 963 55 17 95",
    "sg:postcode":"46022",
    "sg:province":"Valencia",
    "wof:name":"Chinesta Sanchis Vicenta",
    "wof:placetype":"venue"
},
  "geometry": {"coordinates":[-0.3472769856,39.4674415588],"type":"Point"}
}