{
  "type": "Feature",
  "properties": {
    "addr:full":"Avda Gonzalez Mayo, 32 Tineo Asturias 33870",
    "addr:housenumber":"32",
    "addr:postcode":"33870",
    "addr:street":"Avda Gonzalez Mayo",
    "iso:country":"ES",
    "sg:address":"Avda Gonzalez Mayo, 32",
    "sg:city":"Tineo",
    "sg:orig_category":"Administraciones De Trabajo Y Empleo",
    "sg:phone":"+34 985 90 07 50",
    "sg:postcode":"33870",
    "sg:province":"Asturias",
    "wof:name":"Servicio Publico De Empleo Estatal-dron. Prov. Asturias",
    "wof:placetype":"venue"
},
  "geometry": {"coordinates":[-6.416618824,43.3339385986],"type":"Point"}
}