{
  "type": "Feature",
  "properties": {
    "addr:full":"Cmno Lomo Espino, 37 Lomo Espino Las Palmas 35300",
    "addr:housenumber":"37",
    "addr:postcode":"35300",
    "addr:street":"Cmno Lomo Espino;Espino",
    "iso:country":"ES",
    "sg:address":"Cmno Lomo Espino, 37",
    "sg:city":"Lomo Espino",
    "sg:orig_category":"Arquitectos",
    "sg:phone":"+34 928 64 19 50",
    "sg:postcode":"35300",
    "sg:province":"Las Palmas",
    "wof:name":"Sosa Perez Jose Manuel",
    "wof:placetype":"venue"
},
  "geometry": {"coordinates":[-15.4988956451,28.0369472504],"type":"Point"}
}