{
  "type": "Feature",
  "properties": {
    "iso:country":"ES",
    "sg:address":"Calle de Nafarroa, 20",
    "sg:city":"San Vicente De Barakaldo",
    "sg:orig_category":"Fisioterapia",
    "sg:phone":"+34 944 38 50 22",
    "sg:postcode":"48901",
    "sg:province":"Vizcaya",
    "wof:name":"Badillos Garcia Javier Miguel",
    "wof:placetype":"venue"
},
  "geometry": {"coordinates":[-2.9866449833,43.2952537537],"type":"Point"}
}