{
  "type": "Feature",
  "properties": {
    "addr:full":"Calle de Diamante, 37 Humanes De Madrid Madrid 28970",
    "addr:housenumber":"37",
    "addr:postcode":"28970",
    "addr:street":"Calle De Diamante",
    "iso:country":"ES",
    "sg:address":"Calle de Diamante, 37",
    "sg:city":"Humanes De Madrid",
    "sg:orig_category":"Alumbrados",
    "sg:phone":"+34 916 97 40 17",
    "sg:postcode":"28970",
    "sg:province":"Madrid",
    "sg:website":"www.lamparasmcordoba.com",
    "wof:name":"Cordoba Ochoa Miguel Angel",
    "wof:placetype":"venue"
},
  "geometry": {"coordinates":[-3.8273570538,40.2690429688],"type":"Point"}
}