{
  "type": "Feature",
  "properties": {
    "iso:country":"ES",
    "sg:address":"Calle de Ercavica, 4",
    "sg:city":"Cuenca",
    "sg:orig_category":"Venta, Instalaci\u00d3n De Calefacci\u00d3n",
    "sg:phone":"+34 969 22 93 82",
    "sg:postcode":"16001",
    "sg:province":"Cuenca",
    "wof:name":"Martinez Lucas Francisco Javier",
    "wof:placetype":"venue"
},
  "geometry": {"coordinates":[-2.1326439381,40.0717010498],"type":"Point"}
}