{
  "type": "Feature",
  "properties": {
    "iso:country":"ES",
    "sg:address":"Calle de Principe, 4",
    "sg:city":"Granada",
    "sg:orig_category":"Agencias De Viajes",
    "sg:phone":"+34 958 22 67 00",
    "sg:postcode":"18001",
    "sg:province":"Granada",
    "wof:name":"Viajes Principe S.a",
    "wof:placetype":"venue"
},
  "geometry": {"coordinates":[-3.5993089676,37.1745605469],"type":"Point"}
}