{
  "type": "Feature",
  "properties": {
    "iso:country":"ES",
    "sg:address":"Carrer de Carrasco I Formiguera, 16",
    "sg:city":"Manresa",
    "sg:orig_category":"Librer\u00cdas",
    "sg:phone":"+34 938 73 74 34",
    "sg:postcode":"08242",
    "sg:province":"Barcelona",
    "sg:website":"www.petitparcir.com",
    "wof:name":"Petitparcir S.l.",
    "wof:placetype":"venue"
},
  "geometry": {"coordinates":[1.823439002,41.7301483154],"type":"Point"}
}