{
  "type": "Feature",
  "properties": {
    "iso:country":"ES",
    "sg:address":"Calle de San Justo, 2",
    "sg:city":"Salamanca",
    "sg:orig_category":"Institutos De Belleza",
    "sg:phone":"+34 923 21 04 98",
    "sg:postcode":"37001",
    "sg:province":"Salamanca",
    "wof:name":"Villalon Juanes Maria Del Mar",
    "wof:placetype":"venue"
},
  "geometry": {"coordinates":[-5.6634168625,40.9636268616],"type":"Point"}
}