{
  "type": "Feature",
  "properties": {
    "iso:country":"ES",
    "sg:address":"Carrer de Sant Isidre, 12",
    "sg:city":"Cambrils",
    "sg:orig_category":"Artes Gr\u00c1ficas, Artes Pl\u00c1sticas (curso)",
    "sg:phone":"+34 977 79 24 93",
    "sg:postcode":"43850",
    "sg:province":"Tarragona",
    "wof:name":"Cartonatges Cambrils S.l.",
    "wof:placetype":"venue"
},
  "geometry": {"coordinates":[1.0547870398,41.0706825256],"type":"Point"}
}