{
  "type": "Feature",
  "properties": {
    "addr:full":"Calle de Ba\u00d1uetaibar Kalea, 14 Amurrio \u00c1lava 01470",
    "addr:housenumber":"14",
    "addr:postcode":"01470",
    "addr:street":"Calle De Ban\u0303Uetaibar Kalea",
    "iso:country":"ES",
    "sg:address":"Calle de Ba\u00d1uetaibar Kalea, 14",
    "sg:city":"Amurrio",
    "sg:orig_category":"Muebles, Minoristas",
    "sg:phone":"+34 945 89 23 45",
    "sg:postcode":"01470",
    "sg:province":"\u00c1lava",
    "wof:name":"Sanchez Maudes Maria Del Carmen",
    "wof:placetype":"venue"
},
  "geometry": {"coordinates":[-2.9957337379,43.0528755188],"type":"Point"}
}