{
  "type": "Feature",
  "properties": {
    "addr:full":"Extramuros, S/n Villaverde Rio Sevilla 41318",
    "addr:postcode":"41318",
    "addr:street":"Extramuros S / N Villaverde Rio Sevilla",
    "iso:country":"ES",
    "sg:address":"Extramuros, S/n",
    "sg:city":"Villaverde Rio",
    "sg:orig_category":"Agricultura: Abastecimiento Y Cosechado (negocio)",
    "sg:phone":"+34 955 73 66 67",
    "sg:postcode":"41318",
    "sg:province":"Sevilla",
    "wof:name":"Sociedad Agraria De Transformacion El Pe\u00f1on",
    "wof:placetype":"venue"
},
  "geometry": {"coordinates":[-5.8795042038,37.5939064026],"type":"Point"}
}