{
  "type": "Feature",
  "properties": {
    "iso:country":"ES",
    "sg:address":"Calle de Amistad, 10",
    "sg:city":"Getxo",
    "sg:orig_category":"Quincaller\u00cda (al Por Menor)",
    "sg:phone":"+34 944 63 78 26",
    "sg:postcode":"48930",
    "sg:province":"Vizcaya",
    "wof:name":"Maria Carmen Ruiz Palacio E Ignacio Salazar, C.b.",
    "wof:placetype":"venue"
},
  "geometry": {"coordinates":[-3.0150449276,43.3252182007],"type":"Point"}
}