{
  "type": "Feature",
  "properties": {
    "iso:country":"ES",
    "sg:address":"Avda Canteras (de Las), 60",
    "sg:city":"Valmor-rompecubas",
    "sg:orig_category":"Artes Gr\u00c1ficas, Artes Pl\u00c1sticas: Material Y Suministros (al Por Menor)",
    "sg:phone":"+34 918 95 19 12",
    "sg:postcode":"28340",
    "sg:province":"Madrid",
    "wof:name":"Cerrajeria Metalica Sese\u00f1a 2006 S.l.",
    "wof:placetype":"venue"
},
  "geometry": {"coordinates":[-3.6677899361,40.1646308899],"type":"Point"}
}