{
  "type": "Feature",
  "properties": {
    "iso:country":"ES",
    "sg:address":"Avda Artesanos (de Los), 60",
    "sg:city":"Tres Cantos",
    "sg:orig_category":"Inmobiliaria (agencias)",
    "sg:phone":"+34 918 04 40 15",
    "sg:postcode":"28760",
    "sg:province":"Madrid",
    "wof:name":"Ch Infor S.l.",
    "wof:placetype":"venue"
},
  "geometry": {"coordinates":[-3.7083060741,40.6141548157],"type":"Point"}
}