{
  "type": "Feature",
  "properties": {
    "iso:country":"ES",
    "sg:address":"Toki-eder Plaza, 5",
    "sg:city":"Bergara",
    "sg:orig_category":"Pescader\u00cdas (al Por Menor)",
    "sg:phone":"+34 943 76 47 41",
    "sg:postcode":"20570",
    "sg:province":"Guip\u00f9zcoa",
    "wof:name":"Gauna Moreno Jose",
    "wof:placetype":"venue"
},
  "geometry": {"coordinates":[-2.4142439365,43.1125221252],"type":"Point"}
}