{
  "type": "Feature",
  "properties": {
    "iso:country":"ES",
    "sg:address":"Calle de Enrique De Eguren, 11",
    "sg:city":"Vitoria-gasteiz",
    "sg:orig_category":"Reposter\u00cdas",
    "sg:phone":"+34 945 22 06 02",
    "sg:postcode":"01009",
    "sg:province":"\u00c1lava",
    "wof:name":"La Vitoriana De La Alimentacion S.l.",
    "wof:placetype":"venue"
},
  "geometry": {"coordinates":[-2.6841659546,42.851348877],"type":"Point"}
}