{
  "type": "Feature",
  "properties": {
    "iso:country":"ES",
    "sg:address":"Rua Carmen Santiso (de), S/n",
    "sg:city":"Santa Comba",
    "sg:orig_category":"Asociaciones Y Clubs Deportivos",
    "sg:phone":"+34 981 88 11 60",
    "sg:postcode":"15840",
    "sg:province":"La Coru\u00f1a",
    "wof:name":"Facal Capelo Minia",
    "wof:placetype":"venue"
},
  "geometry": {"coordinates":[-8.813038826,43.0326385498],"type":"Point"}
}