{
  "type": "Feature",
  "properties": {
    "addr:full":"Carrer de Rossello (de), 3 Tortosa Tarragona 43500",
    "addr:postcode":"43500",
    "addr:street":"Carrer De Rossello De",
    "iso:country":"ES",
    "sg:address":"Carrer de Rossello (de), 3",
    "sg:city":"Tortosa",
    "sg:orig_category":"Asesor\u00cda Fiscal Y Jur\u00cddica",
    "sg:phone":"+34 977 51 03 95",
    "sg:postcode":"43500",
    "sg:province":"Tarragona",
    "sg:website":"www.adecassesors.com",
    "wof:name":"Adec Assessors S.l.",
    "wof:placetype":"venue"
},
  "geometry": {"coordinates":[0.4995729923,40.7147521973],"type":"Point"}
}