{
  "type": "Feature",
  "properties": {
    "addr:full":"Carrer de Girona, 161 Sabadell Barcelona 08202",
    "addr:housenumber":"161",
    "addr:postcode":"08202",
    "addr:street":"Carrer De Girona",
    "iso:country":"ES",
    "sg:address":"Carrer de Girona, 161",
    "sg:city":"Sabadell",
    "sg:orig_category":"Molduras, Junquillos, Listones Y Molduras Perforadas",
    "sg:phone":"+34 937 12 06 22",
    "sg:postcode":"08202",
    "sg:province":"Barcelona",
    "wof:name":"Pedreny Lozano Jordi",
    "wof:placetype":"venue"
},
  "geometry": {"coordinates":[2.1226100922,41.551158905],"type":"Point"}
}