{
  "type": "Feature",
  "properties": {
    "addr:full":"Calle de Elisa Cendrero, 7 Ciudad Real Ciudad Real 13004",
    "addr:housenumber":"7",
    "addr:postcode":"13004",
    "addr:street":"Calle De Elisa Cendrero",
    "iso:country":"ES",
    "sg:address":"Calle de Elisa Cendrero, 7",
    "sg:city":"Ciudad Real",
    "sg:orig_category":"M\u00c9dicos: Estomatolog\u00cda",
    "sg:phone":"+34 926 22 29 15",
    "sg:postcode":"13004",
    "sg:province":"Ciudad Real",
    "wof:name":"Iglesias Alvarez Alejandra Monica",
    "wof:placetype":"venue"
},
  "geometry": {"coordinates":[-3.9301741123,38.9844093323],"type":"Point"}
}