{
  "type": "Feature",
  "properties": {
    "addr:full":"Calle de Numancia, 10 Santa Cruz De Tenerife Santa Cruz De Tenerife 38004",
    "addr:housenumber":"10",
    "addr:postcode":"38004",
    "addr:street":"Calle De Numancia",
    "iso:country":"ES",
    "sg:address":"Calle de Numancia, 10",
    "sg:city":"Santa Cruz De Tenerife",
    "sg:orig_category":"Abogados",
    "sg:phone":"+34 922 24 09 55",
    "sg:postcode":"38004",
    "sg:province":"Santa Cruz De Tenerife",
    "wof:name":"Llorens Diaz De Aguilar Bufetes Asociados S.l.",
    "wof:placetype":"venue"
},
  "geometry": {"coordinates":[-16.2558994293,28.4724597931],"type":"Point"}
}