{
  "type": "Feature",
  "properties": {
    "addr:full":"Calle de Alonso Cano, 57 Madrid Madrid 28003",
    "addr:housenumber":"57",
    "addr:postcode":"madrid;28003",
    "addr:street":"Calle De Alonso Cano",
    "iso:country":"ES",
    "sg:address":"Calle de Alonso Cano, 57",
    "sg:city":"Madrid",
    "sg:orig_category":"Molduras, Junquillos, Listones Y Molduras Perforadas",
    "sg:phone":"+34 913 99 07 36",
    "sg:postcode":"28003",
    "sg:province":"Madrid",
    "wof:name":"Endre Inmuebles S.l.",
    "wof:placetype":"venue"
},
  "geometry": {"coordinates":[-3.69764781,40.4403991699],"type":"Point"}
}