{
  "type": "Feature",
  "properties": {
    "addr:full":"Av Verge De Montserrat, 48 Barbera Valles Barcelona 08210",
    "addr:housenumber":"48",
    "addr:postcode":"08210",
    "addr:street":"Av Verge De Montserrat",
    "iso:country":"ES",
    "sg:address":"Av Verge De Montserrat, 48",
    "sg:city":"Barbera Valles",
    "sg:orig_category":"Pintura Y Barniz (al Por Menor)",
    "sg:phone":"+34 937 19 14 96",
    "sg:postcode":"08210",
    "sg:province":"Barcelona",
    "wof:name":"Villamana Casas Jose Maria",
    "wof:placetype":"venue"
},
  "geometry": {"coordinates":[2.1238570213,41.5139503479],"type":"Point"}
}