{
  "type": "Feature",
  "properties": {
    "iso:country":"ES",
    "sg:address":"Plaz Villa (la), S/n",
    "sg:city":"Villamuriel De Cerrato",
    "sg:orig_category":"Pescader\u00cdas (al Por Menor)",
    "sg:phone":"+34 979 77 61 20",
    "sg:postcode":"34190",
    "sg:province":"Palencia",
    "wof:name":"Puertas Sanz Juan Antonio",
    "wof:placetype":"venue"
},
  "geometry": {"coordinates":[-4.5154891014,41.9498138428],"type":"Point"}
}