{
  "type": "Feature",
  "properties": {
    "iso:country":"ES",
    "sg:address":"Calle de Granada, 41",
    "sg:city":"Ogijares",
    "sg:orig_category":"Inform\u00c1tica: Material Y Suministros",
    "sg:phone":"+34 958 59 79 34",
    "sg:postcode":"18151",
    "sg:province":"Granada",
    "wof:name":"Lozano Ocon S.l.",
    "wof:placetype":"venue"
},
  "geometry": {"coordinates":[-3.6050109863,37.1229400635],"type":"Point"}
}