{
  "type": "Feature",
  "properties": {
    "iso:country":"ES",
    "sg:address":"Avgd D'albaida, 20",
    "sg:city":"Ontinyent",
    "sg:orig_category":"Comercio De Piezas De Recambio Y De Accesorios De Veh\u00cdculos, Veh\u00cdculos Industriales",
    "sg:phone":"+34 962 91 13 84",
    "sg:postcode":"46870",
    "sg:province":"Valencia",
    "wof:name":"Auto Centers Ontinyent S.l.",
    "wof:placetype":"venue"
},
  "geometry": {"coordinates":[-0.5987122059,38.8226699829],"type":"Point"}
}