{
  "type": "Feature",
  "properties": {
    "iso:country":"ES",
    "sg:address":"Avda Constitucion De La, 22",
    "sg:city":"S.gregorio",
    "sg:orig_category":"Telas Para Tapizar, Cortinas, Pasamaner\u00cda (fabricaci\u00d3n, Al Por Mayor)",
    "sg:phone":"+34 928 68 03 68",
    "sg:postcode":"35200",
    "sg:province":"Las Palmas",
    "wof:name":"Pulido Hernandez Juan Diego",
    "wof:placetype":"venue"
},
  "geometry": {"coordinates":[-15.4144220352,28.0029888153],"type":"Point"}
}