{
  "type": "Feature",
  "properties": {
    "addr:full":"Matoses, 11 Pedreguer Alicante 03750",
    "addr:housenumber":"11",
    "addr:postcode":"03750",
    "addr:street":"Matoses",
    "iso:country":"ES",
    "sg:address":"Matoses, 11",
    "sg:city":"Pedreguer",
    "sg:orig_category":"Maquinaria Para Industrias Diversas",
    "sg:phone":"+34 966 45 64 71",
    "sg:postcode":"03750",
    "sg:province":"Alicante",
    "wof:name":"Friofred S.l.",
    "wof:placetype":"venue"
},
  "geometry": {"coordinates":[0.0347849987,38.7958145142],"type":"Point"}
}