{
  "type": "Feature",
  "properties": {
    "iso:country":"ES",
    "sg:address":"Carr Calvari, S/n",
    "sg:city":"Castellnou Seana",
    "sg:orig_category":"Fabricaci\u00d3n De Instrumentos Y Accesorios Musicales",
    "sg:phone":"+34 973 32 08 30",
    "sg:postcode":"25265",
    "sg:province":"Lleida",
    "wof:name":"Capdevila Andres Manuel",
    "wof:placetype":"venue"
},
  "geometry": {"coordinates":[0.9706739783,41.6483421326],"type":"Point"}
}