{
  "type": "Feature",
  "properties": {
    "addr:full":"Pase Alameda, 51 Valencia Valencia 46023",
    "addr:housenumber":"51",
    "addr:postcode":"46023",
    "addr:street":"Alameda",
    "iso:country":"ES",
    "sg:address":"Pase Alameda, 51",
    "sg:city":"Valencia",
    "sg:orig_category":"Agencias Y Agentes Comerciales, Representantes",
    "sg:phone":"+34 963 30 36 15",
    "sg:postcode":"46023",
    "sg:province":"Valencia",
    "wof:name":"Santiago Hornos Jose Antonio",
    "wof:placetype":"venue"
},
  "geometry": {"coordinates":[-0.3602719903,39.4677505493],"type":"Point"}
}