{
  "type": "Feature",
  "properties": {
    "addr:full":"Carrer de Fontanella, 14 Barcelona Barcelona 08010",
    "addr:housenumber":"14",
    "addr:postcode":"08010",
    "addr:street":"Carrer De Fontanella",
    "iso:country":"ES",
    "sg:address":"Carrer de Fontanella, 14",
    "sg:city":"Barcelona",
    "sg:orig_category":"Organizaciones Internacionales",
    "sg:phone":"+34 933 01 84 93",
    "sg:postcode":"08010",
    "sg:province":"Barcelona",
    "wof:name":"Associacio Per A Les Nacions Unides A Espanya",
    "wof:placetype":"venue"
},
  "geometry": {"coordinates":[2.172337532,41.387966156],"type":"Point"}
}