{
  "type": "Feature",
  "properties": {
    "iso:country":"ES",
    "sg:address":"Partida Cap-blanch, 37",
    "sg:city":"Cap-blanch",
    "sg:orig_category":"Molduras, Junquillos, Listones Y Molduras Perforadas",
    "sg:phone":"+34 966 88 07 32",
    "sg:postcode":"03590",
    "sg:province":"Alicante",
    "wof:name":"Castillo Olivar Ana Maria",
    "wof:placetype":"venue"
},
  "geometry": {"coordinates":[-0.0522690006,38.601108551],"type":"Point"}
}