{
  "type": "Feature",
  "properties": {
    "addr:full":"Calle de Pintor Luis Alvarez, S/n Cangas Narcea Asturias 33800",
    "addr:postcode":"33800",
    "addr:street":"Calle De Pintor Luis Alvarez S / N",
    "iso:country":"ES",
    "sg:address":"Calle de Pintor Luis Alvarez, S/n",
    "sg:city":"Cangas Narcea",
    "sg:orig_category":"Librer\u00cdas",
    "sg:phone":"+34 985 81 34 20",
    "sg:postcode":"33800",
    "sg:province":"Asturias",
    "wof:name":"Garcia Fernandez Clara",
    "wof:placetype":"venue"
},
  "geometry": {"coordinates":[-6.5505580902,43.1801147461],"type":"Point"}
}