{
  "type": "Feature",
  "properties": {
    "addr:full":"Av Ntra Sra Montserrat, 38 Alio Tarragona 43813",
    "addr:housenumber":"38",
    "addr:postcode":"43813",
    "addr:street":"Av Ntra Sra Montserrat",
    "iso:country":"ES",
    "sg:address":"Av Ntra Sra Montserrat, 38",
    "sg:city":"Alio",
    "sg:orig_category":"Frutas Y Legumbres Secas (al Por Mayor)",
    "sg:phone":"+34 977 60 19 29",
    "sg:postcode":"43813",
    "sg:province":"Tarragona",
    "wof:name":"Frutos Secos Cabre S.a.",
    "wof:placetype":"venue"
},
  "geometry": {"coordinates":[1.3077210188,41.2955360413],"type":"Point"}
}