{
  "type": "Feature",
  "properties": {
    "addr:full":"Carrer de Sardenya, 96 Barcelona Barcelona 08018",
    "addr:housenumber":"96",
    "addr:postcode":"08018",
    "addr:street":"Carrer De Sardenya",
    "iso:country":"ES",
    "sg:address":"Carrer de Sardenya, 96",
    "sg:city":"Barcelona",
    "sg:orig_category":"Molduras, Junquillos, Listones Y Molduras Perforadas",
    "sg:phone":"+34 933 09 18 68",
    "sg:postcode":"08018",
    "sg:province":"Barcelona",
    "wof:name":"El Rincon De La Tentacion S.l.",
    "wof:placetype":"venue"
},
  "geometry": {"coordinates":[2.1876211166,41.3927993774],"type":"Point"}
}