{
  "type": "Feature",
  "properties": {
    "addr:full":"Calle de Anglo-vasco, 1 Vitoria-gasteiz \u00c1lava 01002",
    "addr:housenumber":"1",
    "addr:postcode":"01002",
    "addr:street":"Calle De Anglo-Vasco",
    "iso:country":"ES",
    "sg:address":"Calle de Anglo-vasco, 1",
    "sg:city":"Vitoria-gasteiz",
    "sg:orig_category":"Molduras, Junquillos, Listones Y Molduras Perforadas",
    "sg:phone":"+34 945 27 29 17",
    "sg:postcode":"01002",
    "sg:province":"\u00c1lava",
    "wof:name":"Galdos Zabalo Irune",
    "wof:placetype":"venue"
},
  "geometry": {"coordinates":[-2.6656579971,42.8521308899],"type":"Point"}
}