{
  "type": "Feature",
  "properties": {
    "iso:country":"ES",
    "sg:address":"Avda Alfaguara (de La), 55",
    "sg:city":"Alfacar",
    "sg:orig_category":"Quincaller\u00cda (al Por Menor)",
    "sg:phone":"+34 958 54 31 23",
    "sg:postcode":"18170",
    "sg:province":"Granada",
    "wof:name":"Garcia Cabello Manuel",
    "wof:placetype":"venue"
},
  "geometry": {"coordinates":[-3.5601119995,37.2423744202],"type":"Point"}
}