{
  "type": "Feature",
  "properties": {
    "iso:country":"ES",
    "sg:address":"Calle de Garcia Sanchez, 25",
    "sg:city":"Zaragoza",
    "sg:orig_category":"Cajas Para Embalar",
    "sg:phone":"+34 976 30 63 68",
    "sg:postcode":"50005",
    "sg:province":"Zaragoza",
    "wof:name":"Caja Rural De Aragon S.coop Credito",
    "wof:placetype":"venue"
},
  "geometry": {"coordinates":[-0.8996700048,41.6475334167],"type":"Point"}
}