{
  "type": "Feature",
  "properties": {
    "iso:country":"ES",
    "sg:address":"Calle de Huertas, 36",
    "sg:city":"Paradas",
    "sg:orig_category":"Bares, Piano",
    "sg:phone":"+34 955 84 43 79",
    "sg:postcode":"41610",
    "sg:province":"Sevilla",
    "wof:name":"Hermanos Carrion Vargas C.b.",
    "wof:placetype":"venue"
},
  "geometry": {"coordinates":[-5.4943208694,37.2899055481],"type":"Point"}
}