{
  "type": "Feature",
  "properties": {
    "addr:full":"Calle de Rincon Rambla, 3 Vall D'uixo Castell\u00f3n 12600",
    "addr:housenumber":"3",
    "addr:postcode":"12600",
    "addr:street":"Calle De Rincon Rambla",
    "iso:country":"ES",
    "sg:address":"Calle de Rincon Rambla, 3",
    "sg:city":"Vall D'uixo",
    "sg:orig_category":"Ropa Para Ni\u00d1os (al Por Menor)",
    "sg:phone":"+34 964 66 10 67",
    "sg:postcode":"12600",
    "sg:province":"Castell\u00f3n",
    "wof:name":"Solets Dorats S.l.",
    "wof:placetype":"venue"
},
  "geometry": {"coordinates":[-0.0482099988,39.992477417],"type":"Point"}
}