{
  "type": "Feature",
  "properties": {
    "iso:country":"ES",
    "sg:address":"Carrer de Sardenya, 308",
    "sg:city":"Barcelona",
    "sg:orig_category":"Calzados Ortop\u00c9dicos",
    "sg:phone":"+34 932 46 13 65",
    "sg:postcode":"08013",
    "sg:province":"Barcelona",
    "wof:name":"Charles Poch Enrique",
    "wof:placetype":"venue"
},
  "geometry": {"coordinates":[2.1747779846,41.4024963379],"type":"Point"}
}