{
  "type": "Feature",
  "properties": {
    "iso:country":"ES",
    "sg:address":"Calle de Covachuelas, 12",
    "sg:city":"Madrid",
    "sg:orig_category":"Marketing Telef\u00d3nico",
    "sg:phone":"+34 917 10 05 10",
    "sg:postcode":"28021",
    "sg:province":"Madrid",
    "wof:name":"Red Universal De Formacion S.l.",
    "wof:placetype":"venue"
},
  "geometry": {"coordinates":[-3.7084584236,40.3483543396],"type":"Point"}
}