{
  "type": "Feature",
  "properties": {
    "addr:full":"Calle de Santo Cristo De La Paz, 31 Badajoz Badajoz 06009",
    "addr:housenumber":"31",
    "addr:postcode":"06009",
    "addr:street":"Calle De Santo Cristo De La Paz",
    "iso:country":"ES",
    "sg:address":"Calle de Santo Cristo De La Paz, 31",
    "sg:city":"Badajoz",
    "sg:orig_category":"Motocicletas (agentes, Concesionarios)",
    "sg:phone":"+34 924 25 56 26",
    "sg:postcode":"06009",
    "sg:province":"Badajoz",
    "wof:name":"Motos Campini S.l.",
    "wof:placetype":"venue"
},
  "geometry": {"coordinates":[-6.9611968994,38.8765029907],"type":"Point"}
}