{
  "type": "Feature",
  "properties": {
    "iso:country":"ES",
    "sg:address":"Av Francesc Macia, 70",
    "sg:city":"Sabadell",
    "sg:orig_category":"Peluqueros: De Se\u00d1oras",
    "sg:phone":"+34 937 16 85 33",
    "sg:postcode":"08206",
    "sg:province":"Barcelona",
    "wof:name":"Peluqueria Jairo S.l.",
    "wof:placetype":"venue"
},
  "geometry": {"coordinates":[2.0971000195,41.5580215454],"type":"Point"}
}