{
  "type": "Feature",
  "properties": {
    "iso:country":"ES",
    "sg:address":"C/ Sebastia Garriga, 1",
    "sg:city":"Cerdanyola Valles",
    "sg:orig_category":"Estudios, Instalaci\u00d3n De Climatizaci\u00d3n",
    "sg:phone":"+34 935 92 02 42",
    "sg:postcode":"08290",
    "sg:province":"Barcelona",
    "wof:name":"Absorsistem S.l.",
    "wof:placetype":"venue"
},
  "geometry": {"coordinates":[2.131667,41.489559],"type":"Point"}
}