{
  "type": "Feature",
  "properties": {
    "iso:country":"ES",
    "sg:address":"Ctra. Logro\u00f1o, Km. 0016,0",
    "sg:city":"Sobradiel",
    "sg:orig_category":"Construcciones Met\u00c1licas",
    "sg:phone":"+34 976 46 27 80",
    "sg:postcode":"50629",
    "sg:province":"Zaragoza",
    "wof:name":"Estructuras Metalicas Lazaro S. A.",
    "wof:placetype":"venue"
},
  "geometry": {"coordinates":[-1.0388139486,41.7388267517],"type":"Point"}
}