{
  "type": "Feature",
  "properties": {
    "iso:country":"ES",
    "sg:address":"Rua Compostela, 9",
    "sg:city":"Ordes",
    "sg:orig_category":"Cl\u00cdnicas M\u00c9dicas",
    "sg:phone":"+34 981 68 22 55",
    "sg:postcode":"15680",
    "sg:province":"La Coru\u00f1a",
    "wof:name":"Carrasco Lopez Maria Luisa",
    "wof:placetype":"venue"
},
  "geometry": {"coordinates":[-8.4081344604,43.0776443481],"type":"Point"}
}