{
  "type": "Feature",
  "properties": {
    "iso:country":"ES",
    "sg:address":"Monasterio Fitero, 29",
    "sg:city":"Iru\u00f1a",
    "sg:orig_category":"Sonorizaci\u00d3n, Iluminaci\u00d3n Para Cine, Teatro Y Discotecas (al Por Mayor, Al Por Menor)",
    "sg:phone":"+34 948 19 87 05",
    "sg:postcode":"31011",
    "sg:province":"Navarra",
    "sg:website":"www.zetaaudiovisuales.com",
    "wof:name":"Zeta Soluciones Audiovisuales S. L.",
    "wof:placetype":"venue"
},
  "geometry": {"coordinates":[-1.6629401445,42.8169784546],"type":"Point"}
}