{
  "type": "Feature",
  "properties": {
    "addr:full":"Burgos (poligonos Industriales), Km. 0117,4 Valladolid Valladolid 47009",
    "addr:postcode":"47009",
    "addr:street":"Industriales Km. 0117,4",
    "iso:country":"ES",
    "sg:address":"Burgos (poligonos Industriales), Km. 0117,4",
    "sg:city":"Valladolid",
    "sg:orig_category":"Producci\u00d3n, Venta De Productos De Agricultura Biol\u00d3gica",
    "sg:phone":"+34 983 37 11 15",
    "sg:postcode":"47009",
    "sg:province":"Valladolid",
    "sg:website":"www.ecosem.es",
    "wof:name":"Ecosem S.l.",
    "wof:placetype":"venue"
},
  "geometry": {"coordinates":[-4.7070288658,41.6909103394],"type":"Point"}
}