{
  "type": "Feature",
  "properties": {
    "iso:country":"ES",
    "sg:address":"Calle de Maestro Pascual Baca, 12",
    "sg:city":"Alcala Real",
    "sg:orig_category":"Agentes, Concesionarios Y Sucursales De Veh\u00cdculos",
    "sg:phone":"+34 953 58 50 47",
    "sg:postcode":"23680",
    "sg:province":"Ja\u00e9n",
    "wof:name":"Bretones Serrano Rafael",
    "wof:placetype":"venue"
},
  "geometry": {"coordinates":[-3.9191040993,37.4566116333],"type":"Point"}
}