{
  "type": "Feature",
  "properties": {
    "iso:country":"ES",
    "sg:address":"Calle de Santa Maria De Gracia, 13",
    "sg:city":"Camas",
    "sg:orig_category":"Asociaciones, Organismos Culturales Y Socioeducativos",
    "sg:phone":"+34 954 39 59 53",
    "sg:postcode":"41900",
    "sg:province":"Sevilla",
    "wof:name":"Pe\u00f1a Taurina Curro Romero",
    "wof:placetype":"venue"
},
  "geometry": {"coordinates":[-6.0349731445,37.4019775391],"type":"Point"}
}