{
  "type": "Feature",
  "properties": {
    "addr:full":"Calle de Unceta, 83 Zaragoza Zaragoza 50010",
    "addr:housenumber":"83",
    "addr:postcode":"50010",
    "addr:street":"Calle De Unceta",
    "iso:country":"ES",
    "sg:address":"Calle de Unceta, 83",
    "sg:city":"Zaragoza",
    "sg:orig_category":"Fabricaci\u00d3n De Peines Y De Accesorios De Peluquer\u00cda",
    "sg:phone":"+34 976 33 10 02",
    "sg:postcode":"50010",
    "sg:province":"Zaragoza",
    "wof:name":"Antonio Fariza S.l.",
    "wof:placetype":"venue"
},
  "geometry": {"coordinates":[-0.900983572,41.6500473022],"type":"Point"}
}