{
  "type": "Feature",
  "properties": {
    "iso:country":"ES",
    "sg:address":"Plaz Constitucion (de La), 1",
    "sg:city":"Conil De La Frontera",
    "sg:orig_category":"Administraciones Regionales, Departamentales Y Locales",
    "sg:phone":"+34 956 44 03 06",
    "sg:postcode":"11140",
    "sg:province":"C\u00e1diz",
    "wof:name":"Ayuntamiento De Conil De La Frontera",
    "wof:placetype":"venue"
},
  "geometry": {"coordinates":[-6.0881857872,36.2774810791],"type":"Point"}
}