{
  "type": "Feature",
  "properties": {
    "addr:full":"Calle de Felipe Ii, 15 Valladolid Valladolid 47003",
    "addr:housenumber":"15",
    "addr:postcode":"47003",
    "addr:street":"Calle De Felipe Ii",
    "iso:country":"ES",
    "sg:address":"Calle de Felipe Ii, 15",
    "sg:city":"Valladolid",
    "sg:orig_category":"Papeler\u00cdas, Librer\u00cdas",
    "sg:phone":"+34 983 35 94 13",
    "sg:postcode":"47003",
    "sg:province":"Valladolid",
    "wof:name":"Gaite Pando Fernando",
    "wof:placetype":"venue"
},
  "geometry": {"coordinates":[-4.7250609398,41.656288147],"type":"Point"}
}