{
  "type": "Feature",
  "properties": {
    "iso:country":"ES",
    "sg:address":"Calle de Llano Ponte, 26",
    "sg:city":"Aviles",
    "sg:orig_category":"\u00d3ptica: Instrumentos (fabricaci\u00d3n)",
    "sg:phone":"+34 985 54 56 33",
    "sg:postcode":"33402",
    "sg:province":"Asturias",
    "wof:name":"Optica Albastur S.a.",
    "wof:placetype":"venue"
},
  "geometry": {"coordinates":[-5.9183168411,43.5543403625],"type":"Point"}
}