{
  "type": "Feature",
  "properties": {
    "iso:country":"ES",
    "sg:address":"Carrer de L'alfambra, 18",
    "sg:city":"Barcelona",
    "sg:orig_category":"Reposter\u00cdas",
    "sg:phone":"+34 932 05 54 69",
    "sg:postcode":"08034",
    "sg:province":"Barcelona",
    "wof:name":"Menilo S.c.p.",
    "wof:placetype":"venue"
},
  "geometry": {"coordinates":[2.1123964787,41.3868408203],"type":"Point"}
}