{
  "type": "Feature",
  "properties": {
    "iso:country":"ES",
    "sg:address":"Calle de Alta, 82",
    "sg:city":"Santander",
    "sg:orig_category":"Centros De Educaci\u00d3n Especial",
    "sg:phone":"+34 942 23 17 92",
    "sg:postcode":"39008",
    "sg:province":"Cantabria",
    "wof:name":"Colegio Publico Ramon Pelayo",
    "wof:placetype":"venue"
},
  "geometry": {"coordinates":[-3.8231561184,43.4582710266],"type":"Point"}
}