{
  "type": "Feature",
  "properties": {
    "iso:country":"ES",
    "sg:address":"Calle de Concepcion Arenal, 29",
    "sg:city":"Malaga",
    "sg:orig_category":"Bebidas",
    "sg:phone":"+34 902 36 32 95",
    "sg:postcode":"29004",
    "sg:province":"M\u00e1laga",
    "wof:name":"Costasur Distribucion Y Logistica S.l.",
    "wof:placetype":"venue"
},
  "geometry": {"coordinates":[-4.4787597656,36.6934356689],"type":"Point"}
}