{
  "type": "Feature",
  "properties": {
    "addr:full":"Carrer de Sepulveda, 121 Barcelona Barcelona 08015",
    "addr:housenumber":"121",
    "addr:postcode":"08015",
    "addr:street":"Carrer De Sepulveda",
    "iso:country":"ES",
    "sg:address":"Carrer de Sepulveda, 121",
    "sg:city":"Barcelona",
    "sg:classifiers":[
        {
            "category":"Autos & Motor Vehicles",
            "subcategory":"Automobile Sales",
            "type":"Retail Goods"
        }
    ],
    "sg:phone":"+34 933 23 94 30",
    "sg:postcode":"08015",
    "sg:province":"Barcelona",
    "wof:name":"Sociedad Cooperativa Limitada De Trabaja",
    "wof:placetype":"venue"
},
  "geometry": {"coordinates":[2.1592640877,41.3809509277],"type":"Point"}
}