{
  "type": "Feature",
  "properties": {
    "iso:country":"ES",
    "sg:address":"Carr Rei En Jaume (del), 75",
    "sg:city":"Lliria",
    "sg:orig_category":"Peluqueros: De Se\u00d1oras",
    "sg:phone":"+34 962 78 08 77",
    "sg:postcode":"46160",
    "sg:province":"Valencia",
    "wof:name":"Alcocer Enguidanos Vicente",
    "wof:placetype":"venue"
},
  "geometry": {"coordinates":[-0.6001030803,39.6261520386],"type":"Point"}
}