{
  "type": "Feature",
  "properties": {
    "addr:full":"Calle de Dulcinea, 35 Madrid Madrid 28020",
    "addr:housenumber":"35",
    "addr:postcode":"madrid;28020",
    "addr:street":"Calle De Dulcinea",
    "iso:country":"ES",
    "sg:address":"Calle de Dulcinea, 35",
    "sg:city":"Madrid",
    "sg:orig_category":"Restaurantes",
    "sg:phone":"+34 915 53 12 22",
    "sg:postcode":"28020",
    "sg:province":"Madrid",
    "wof:name":"Meson Restaurante Ospi\u00f1eiros S.l.",
    "wof:placetype":"venue"
},
  "geometry": {"coordinates":[-3.6998980045,40.4494247437],"type":"Point"}
}