{
  "type": "Feature",
  "properties": {
    "addr:full":"Calle de Emilio Baro, 57 Valencia Valencia 46020",
    "addr:housenumber":"57",
    "addr:postcode":"46020",
    "addr:street":"Calle De Emilio Baro",
    "iso:country":"ES",
    "sg:address":"Calle de Emilio Baro, 57",
    "sg:city":"Valencia",
    "sg:orig_category":"Loter\u00cda Y T\u00d3mbola",
    "sg:phone":"+34 963 93 14 85",
    "sg:postcode":"46020",
    "sg:province":"Valencia",
    "wof:name":"Truman Peidro Monserrat",
    "wof:placetype":"venue"
},
  "geometry": {"coordinates":[-0.3609440029,39.4876823425],"type":"Point"}
}