{
  "type": "Feature",
  "properties": {
    "addr:full":"Calle de Colon, 84 Valencia Valencia 46004",
    "addr:housenumber":"84",
    "addr:postcode":"46004",
    "addr:street":"Calle De Colon",
    "iso:country":"ES",
    "sg:address":"Calle de Colon, 84",
    "sg:city":"Valencia",
    "sg:orig_category":"Radiocomunicaciones, Telefon\u00cda M\u00d3vil, Radiomensajer\u00cda: Servicios, Comercializaci\u00d3n",
    "sg:phone":"+34 963 94 07 25",
    "sg:postcode":"46004",
    "sg:province":"Valencia",
    "sg:website":"www.telyco.es",
    "wof:name":"Teleinformatica Y Comunicaciones S.a.",
    "wof:placetype":"venue"
},
  "geometry": {"coordinates":[-0.3688989878,39.4714622498],"type":"Point"}
}