{
  "type": "Feature",
  "properties": {
    "iso:country":"ES",
    "sg:address":"Calle de Colon, 6",
    "sg:city":"Ugarte",
    "sg:orig_category":"Afiladoras, Pulidoras Y Bru\u00d1idoras",
    "sg:phone":"+34 944 92 19 37",
    "sg:postcode":"48510",
    "sg:province":"Vizcaya",
    "wof:name":"Campos Pino Aitor",
    "wof:placetype":"venue"
},
  "geometry": {"coordinates":[-3.0161859989,43.2913322449],"type":"Point"}
}