{
  "type": "Feature",
  "properties": {
    "iso:country":"ES",
    "sg:address":"Avda Yecla (de), Km. 0042,2",
    "sg:city":"Jumilla",
    "sg:orig_category":"Cer\u00c1micas: Material Y Suministros",
    "sg:phone":"+34 968 78 24 16",
    "sg:postcode":"30520",
    "sg:province":"Murcia",
    "wof:name":"Terrazos Jumilla S. C. L.",
    "wof:placetype":"venue"
},
  "geometry": {"coordinates":[-1.3222140074,38.4765434265],"type":"Point"}
}