{
  "type": "Feature",
  "properties": {
    "addr:full":"Calle de Zabaleta, 5 Carolina Ja\u00e9n 23200",
    "addr:housenumber":"5",
    "addr:postcode":"23200",
    "addr:street":"Calle De Zabaleta;Carolina Jae\u0301N",
    "iso:country":"ES",
    "sg:address":"Calle de Zabaleta, 5",
    "sg:city":"Carolina",
    "sg:orig_category":"Guarder\u00cdas",
    "sg:phone":"+34 953 66 12 63",
    "sg:postcode":"23200",
    "sg:province":"Ja\u00e9n",
    "wof:name":"Martinez Pastor Maria Del Carmen",
    "wof:placetype":"venue"
},
  "geometry": {"coordinates":[-3.6149539948,38.2775917053],"type":"Point"}
}