{
  "type": "Feature",
  "properties": {
    "iso:country":"ES",
    "sg:address":"Calle de Ancha, 20",
    "sg:city":"Castro Rio",
    "sg:orig_category":"M\u00c9dicos: Estomatolog\u00cda",
    "sg:phone":"+34 957 37 26 51",
    "sg:postcode":"14840",
    "sg:province":"C\u00f3rdoba",
    "wof:name":"Villar Luque Jose Maria",
    "wof:placetype":"venue"
},
  "geometry": {"coordinates":[-4.4805951118,37.6917610168],"type":"Point"}
}