{
  "type": "Feature",
  "properties": {
    "iso:country":"ES",
    "sg:address":"Ptda Condomina, 109",
    "sg:city":"Alacant",
    "sg:orig_category":"Art\u00cdculos M\u00c9dicos",
    "sg:phone":"+34 965 26 29 45",
    "sg:postcode":"03016",
    "sg:province":"Alicante",
    "wof:name":"Traunmansilla S.l",
    "wof:placetype":"venue"
},
  "geometry": {"coordinates":[-0.4365290105,38.3630905151],"type":"Point"}
}