{
  "type": "Feature",
  "properties": {
    "addr:full":"Calle de Torres Quevedo, 6 Merida Badajoz 06800",
    "addr:housenumber":"6",
    "addr:postcode":"06800",
    "addr:street":"Calle De Torres Quevedo",
    "iso:country":"ES",
    "sg:address":"Calle de Torres Quevedo, 6",
    "sg:city":"Merida",
    "sg:orig_category":"T\u00c9cnicos Veterinarios",
    "sg:phone":"+34 924 37 01 41",
    "sg:postcode":"06800",
    "sg:province":"Badajoz",
    "wof:name":"Regalado Fernandez Manuel",
    "wof:placetype":"venue"
},
  "geometry": {"coordinates":[-6.3639740944,38.9106674194],"type":"Point"}
}