{
  "type": "Feature",
  "properties": {
    "iso:country":"ES",
    "sg:address":"Calle de Castillo, 4",
    "sg:city":"Montanchez",
    "sg:orig_category":"Electricidad: Instaladores",
    "sg:phone":"+34 927 38 04 30",
    "sg:postcode":"10170",
    "sg:province":"C\u00e1ceres",
    "wof:name":"Pavon Solis Felicisimo",
    "wof:placetype":"venue"
},
  "geometry": {"coordinates":[-6.1547160149,39.2260055542],"type":"Point"}
}