{
  "type": "Feature",
  "properties": {
    "iso:country":"ES",
    "sg:address":"Plaz Aragon, S/n",
    "sg:city":"Binaced",
    "sg:orig_category":"Centros M\u00c9dicos Y Sociales, Dispensarios",
    "sg:phone":"+34 974 42 74 68",
    "sg:postcode":"22510",
    "sg:province":"Huesca",
    "wof:name":"Ayuntamiento De Binaced",
    "wof:placetype":"venue"
},
  "geometry": {"coordinates":[0.2023870051,41.8255233765],"type":"Point"}
}