{
  "type": "Feature",
  "properties": {
    "iso:country":"ES",
    "sg:address":"Cmn Calzadilla, S/n",
    "sg:city":"Casarrubios Monte",
    "sg:orig_category":"Arenas, Guijarros Y Granulados",
    "sg:phone":"+34 918 14 50 18",
    "sg:postcode":"45950",
    "sg:province":"Toledo",
    "wof:name":"Aridos La Cabeza S.l.",
    "wof:placetype":"venue"
},
  "geometry": {"coordinates":[-3.9688551426,40.1674423218],"type":"Point"}
}