{
  "type": "Feature",
  "properties": {
    "addr:full":"Avda Caldas (das), S/n Ourense Ourense 32001",
    "addr:postcode":"32001",
    "addr:street":"Avda Caldas Das S / N",
    "iso:country":"ES",
    "sg:address":"Avda Caldas (das), S/n",
    "sg:city":"Ourense",
    "sg:orig_category":"Carnicer\u00cdas, Carnicer\u00cdas",
    "sg:phone":"+34 988 21 87 49",
    "sg:postcode":"32001",
    "sg:province":"Ourense",
    "wof:name":"Manuel Crespo Laura",
    "wof:placetype":"venue"
},
  "geometry": {"coordinates":[-7.869284153,42.3474655151],"type":"Point"}
}