{
  "type": "Feature",
  "properties": {
    "iso:country":"ES",
    "sg:address":"Calle de San Blas, 59",
    "sg:city":"Pina De Ebro",
    "sg:orig_category":"Empresas De Desmonte",
    "sg:phone":"+34 976 16 55 82",
    "sg:postcode":"50750",
    "sg:province":"Zaragoza",
    "wof:name":"Construcciones Y Excavaciones Portoles S.l.",
    "wof:placetype":"venue"
},
  "geometry": {"coordinates":[-0.5262389779,41.4924087524],"type":"Point"}
}