{
  "type": "Feature",
  "properties": {
    "iso:country":"ES",
    "sg:address":"Carrer de Orient, 72",
    "sg:city":"S. Cugat Valles",
    "sg:orig_category":"Inmobiliaria (agencias)",
    "sg:phone":"+34 935 89 74 72",
    "sg:postcode":"08172",
    "sg:province":"Barcelona",
    "wof:name":"4river S.l.",
    "wof:placetype":"venue"
},
  "geometry": {"coordinates":[2.091516,41.474773],"type":"Point"}
}