{
  "type": "Feature",
  "properties": {
    "iso:country":"ES",
    "sg:address":"Calle de Titanio, 26",
    "sg:city":"Valladolid",
    "sg:orig_category":"Electricidad, Electr\u00d3nica: Material Y Suministros (al Por Mayor)",
    "sg:phone":"+34 983 21 81 35",
    "sg:postcode":"47012",
    "sg:province":"Valladolid",
    "sg:website":"www.arme.es",
    "wof:name":"Arme S. L.",
    "wof:placetype":"venue"
},
  "geometry": {"coordinates":[-4.7036619186,41.6270141602],"type":"Point"}
}