{
  "type": "Feature",
  "properties": {
    "iso:country":"ES",
    "sg:address":"Carrer de Verge De La Salut, 1",
    "sg:city":"Rieral",
    "sg:orig_category":"Cajas De Ahorro",
    "sg:phone":"+34 938 44 63 58",
    "sg:postcode":"08187",
    "sg:province":"Barcelona",
    "sg:website":"www.lacaixa.es",
    "wof:name":"Caixa D'estalvis I Pensions De Barcelona",
    "wof:placetype":"venue"
},
  "geometry": {"coordinates":[2.2322869301,41.6420211792],"type":"Point"}
}