{
  "type": "Feature",
  "properties": {
    "addr:full":"Calle de Tafetana, 29 Chafiras Santa Cruz De Tenerife 38639",
    "addr:housenumber":"29",
    "addr:postcode":"38639",
    "addr:street":"Calle De Tafetana",
    "iso:country":"ES",
    "sg:address":"Calle de Tafetana, 29",
    "sg:city":"Chafiras",
    "sg:orig_category":"Producci\u00d3n De Abonos Y De Fertilizantes",
    "sg:phone":"+34 922 73 52 76",
    "sg:postcode":"38639",
    "sg:province":"Santa Cruz De Tenerife",
    "wof:name":"Canarias Explosivos S. A.",
    "wof:placetype":"venue"
},
  "geometry": {"coordinates":[-16.6115474701,28.0350246429],"type":"Point"}
}