{
  "type": "Feature",
  "properties": {
    "iso:country":"ES",
    "sg:address":"Calle de Rosales, 18",
    "sg:city":"Valencia",
    "sg:orig_category":"Metales (labores, Pulido)",
    "sg:phone":"+34 963 49 78 00",
    "sg:postcode":"46025",
    "sg:province":"Valencia",
    "wof:name":"Martinez Cruz Alfonso",
    "wof:placetype":"venue"
},
  "geometry": {"coordinates":[-0.3877480924,39.490562439],"type":"Point"}
}