{
  "type": "Feature",
  "properties": {
    "addr:full":"Avda Niza, 5 Alacant Alicante 03540",
    "addr:housenumber":"5",
    "addr:postcode":"03540",
    "addr:street":"Avda Niza",
    "iso:country":"ES",
    "sg:address":"Avda Niza, 5",
    "sg:city":"Alacant",
    "sg:orig_category":"Inmobiliaria (agencias)",
    "sg:phone":"+34 965 16 05 94",
    "sg:postcode":"03540",
    "sg:province":"Alicante",
    "wof:name":"Casanova Blanco Manuel Ramon",
    "wof:placetype":"venue"
},
  "geometry": {"coordinates":[-0.4103989899,38.367149353],"type":"Point"}
}