{
  "type": "Feature",
  "properties": {
    "addr:full":"Calle de Divina Aurora, 29 Yatova Valencia 46367",
    "addr:housenumber":"29",
    "addr:postcode":"46367",
    "addr:street":"Calle De Divina Aurora",
    "iso:country":"ES",
    "sg:address":"Calle de Divina Aurora, 29",
    "sg:city":"Yatova",
    "sg:orig_category":"Cl\u00cdnicas Dentales",
    "sg:phone":"+34 962 50 81 22",
    "sg:postcode":"46367",
    "sg:province":"Valencia",
    "wof:name":"Cervera Sanchez Carlos",
    "wof:placetype":"venue"
},
  "geometry": {"coordinates":[-0.8104041219,39.3839263916],"type":"Point"}
}