{
  "type": "Feature",
  "properties": {
    "addr:full":"Calle de Nuncio, 30 Leganes Madrid 28911",
    "addr:housenumber":"30",
    "addr:postcode":"28911",
    "addr:street":"Calle De Nuncio",
    "iso:country":"ES",
    "sg:address":"Calle de Nuncio, 30",
    "sg:city":"Leganes",
    "sg:orig_category":"Ropa Para Se\u00d1oras Y Caballeros (al Por Menor)",
    "sg:phone":"+34 916 80 03 79",
    "sg:postcode":"28911",
    "sg:province":"Madrid",
    "wof:name":"Cadena Q Comercial S.l.",
    "wof:placetype":"venue"
},
  "geometry": {"coordinates":[-3.7659730911,40.3308868408],"type":"Point"}
}