{
  "type": "Feature",
  "properties": {
    "iso:country":"ES",
    "sg:address":"Calle de Fernando Guanarteme, 44",
    "sg:city":"Palmas De Gran Canaria",
    "sg:orig_category":"Expertos Contables, Revisores De Cuentas",
    "sg:phone":"+34 928 26 62 23",
    "sg:postcode":"35010",
    "sg:province":"Las Palmas",
    "wof:name":"Conesa Duarte Antonio",
    "wof:placetype":"venue"
},
  "geometry": {"coordinates":[-15.4370288849,28.1354389191],"type":"Point"}
}