{
  "type": "Feature",
  "properties": {
    "iso:country":"ES",
    "sg:address":"Doctor Juaristi, 2",
    "sg:city":"Iru\u00f1a",
    "sg:orig_category":"Arquitectos",
    "sg:phone":"+34 948 38 28 80",
    "sg:postcode":"31012",
    "sg:province":"Navarra",
    "wof:name":"Echeverria Echeverria Silvia",
    "wof:placetype":"venue"
},
  "geometry": {"coordinates":[-1.6664969921,42.8212623596],"type":"Point"}
}