{
  "type": "Feature",
  "properties": {
    "iso:country":"ES",
    "sg:address":"Calle de Virgen De Lourdes, 18",
    "sg:city":"Madrid",
    "sg:orig_category":"Carnes De Carnicer\u00cda (al Por Mayor)",
    "sg:phone":"+34 914 03 88 16",
    "sg:postcode":"28027",
    "sg:province":"Madrid",
    "wof:name":"Bajolomo S.l.",
    "wof:placetype":"venue"
},
  "geometry": {"coordinates":[-3.6578614712,40.4360771179],"type":"Point"}
}