{
  "type": "Feature",
  "properties": {
    "addr:full":"Calle de Ferrocarril, 1 Torre-pacheco Murcia 30700",
    "addr:housenumber":"1",
    "addr:postcode":"30700",
    "addr:street":"Calle De Ferrocarril",
    "iso:country":"ES",
    "sg:address":"Calle de Ferrocarril, 1",
    "sg:city":"Torre-pacheco",
    "sg:orig_category":"Electricidad (montaje, Ensamblaje De Componentes)",
    "sg:phone":"+34 968 33 61 39",
    "sg:postcode":"30700",
    "sg:province":"Murcia",
    "wof:name":"Auto Electricidad Rosique Y Martinez S.l.",
    "wof:placetype":"venue"
},
  "geometry": {"coordinates":[-0.9662715793,37.7455368042],"type":"Point"}
}