{
  "type": "Feature",
  "properties": {
    "iso:country":"ES",
    "sg:address":"Avda Albufera, 48",
    "sg:city":"Madrid",
    "sg:orig_category":"Abogados",
    "sg:phone":"+34 914 78 91 35",
    "sg:postcode":"28038",
    "sg:province":"Madrid",
    "wof:name":"Forum General De Servicios S.c.",
    "wof:placetype":"venue"
},
  "geometry": {"coordinates":[-3.6657850742,40.3963241577],"type":"Point"}
}