{
  "type": "Feature",
  "properties": {
    "addr:full":"Calle de Luis Bu\u00d1uel, 48 Almoradi Alicante 03160",
    "addr:housenumber":"48",
    "addr:postcode":"03160",
    "addr:street":"Calle De Luis Bun\u0303Uel",
    "iso:country":"ES",
    "sg:address":"Calle de Luis Bu\u00d1uel, 48",
    "sg:city":"Almoradi",
    "sg:orig_category":"M\u00c9dicos: Ginecolog\u00cda Y Obstetricia",
    "sg:phone":"+34 966 78 07 76",
    "sg:postcode":"03160",
    "sg:province":"Alicante",
    "wof:name":"Campos Liarte Jose",
    "wof:placetype":"venue"
},
  "geometry": {"coordinates":[-0.7898079753,38.112159729],"type":"Point"}
}