{
  "type": "Feature",
  "properties": {
    "iso:country":"ES",
    "sg:address":"Pla\u00c7 Del Mestre Ferrero, 2",
    "sg:city":"Ontinyent",
    "sg:orig_category":"Heladeros",
    "sg:phone":"+34 962 38 18 97",
    "sg:postcode":"46870",
    "sg:province":"Valencia",
    "wof:name":"Vicedo Molto Jose Vicente",
    "wof:placetype":"venue"
},
  "geometry": {"coordinates":[-0.6030989885,38.8258895874],"type":"Point"}
}