{
  "type": "Feature",
  "properties": {
    "addr:full":"Carrer de Maria Fortuny, 57 S. Boi Llobregat Barcelona 08830",
    "addr:housenumber":"57",
    "addr:postcode":"08830",
    "addr:street":"Carrer De Maria Fortuny",
    "iso:country":"ES",
    "sg:address":"Carrer de Maria Fortuny, 57",
    "sg:city":"S. Boi Llobregat",
    "sg:orig_category":"Peluquer\u00cdas, Peluquer\u00cda Mixta",
    "sg:phone":"+34 936 40 16 24",
    "sg:postcode":"08830",
    "sg:province":"Barcelona",
    "wof:name":"Centro De Peluqueria Y Estetica Euro Estil",
    "wof:placetype":"venue"
},
  "geometry": {"coordinates":[2.0398170948,41.3418693542],"type":"Point"}
}