{
  "type": "Feature",
  "properties": {
    "iso:country":"ES",
    "sg:address":"Rua Castelao, 68",
    "sg:city":"Grove",
    "sg:orig_category":"Edici\u00d3n De Diarios, Revistas, Boletines",
    "sg:phone":"+34 986 73 50 45",
    "sg:postcode":"36980",
    "sg:province":"Pontevedra",
    "wof:name":"Editorial Prensa Iberica S.a.",
    "wof:placetype":"venue"
},
  "geometry": {"coordinates":[-8.858259201,42.4904518127],"type":"Point"}
}