{
  "type": "Feature",
  "properties": {
    "addr:full":"Calle de San Agustin, 7 Medina-sidonia C\u00e1diz 11170",
    "addr:housenumber":"7",
    "addr:postcode":"11170",
    "addr:street":"Calle De San Agustin;Ca\u0301Diz",
    "iso:country":"ES",
    "sg:address":"Calle de San Agustin, 7",
    "sg:city":"Medina-sidonia",
    "sg:orig_category":"Internados & Ense\u00d1anza Privada",
    "sg:phone":"+34 956 41 00 60",
    "sg:postcode":"11170",
    "sg:province":"C\u00e1diz",
    "wof:name":"Hijas De La Caridad",
    "wof:placetype":"venue"
},
  "geometry": {"coordinates":[-5.9274568558,36.4603309631],"type":"Point"}
}