{
  "type": "Feature",
  "properties": {
    "iso:country":"ES",
    "sg:address":"Calle de Calvo Sotelo, 15",
    "sg:city":"Logro\u00f1o",
    "sg:orig_category":"Promotores Constructores",
    "sg:phone":"+34 941 25 70 40",
    "sg:postcode":"26003",
    "sg:province":"La Rioja",
    "sg:website":"www.aragonizquierdo.com",
    "wof:name":"Construcciones Aragon Izquierdo S.l.",
    "wof:placetype":"venue"
},
  "geometry": {"coordinates":[-2.4417068958,42.4641075134],"type":"Point"}
}