{
  "type": "Feature",
  "properties": {
    "addr:full":"Carrer de Sol I Padris, 96 Sabadell Barcelona 08203",
    "addr:housenumber":"96",
    "addr:postcode":"08203",
    "addr:street":"Carrer De Sol I Padris",
    "iso:country":"ES",
    "sg:address":"Carrer de Sol I Padris, 96",
    "sg:city":"Sabadell",
    "sg:orig_category":"Panader\u00cdas, Panader\u00cdas",
    "sg:phone":"+34 937 11 38 14",
    "sg:postcode":"08203",
    "sg:province":"Barcelona",
    "wof:name":"Fet A Ma 2003 S.l.",
    "wof:placetype":"venue"
},
  "geometry": {"coordinates":[2.1189630032,41.5363273621],"type":"Point"}
}