{
  "type": "Feature",
  "properties": {
    "addr:full":"Pl Doctor Letamendi, 35 Barcelona Barcelona 08007",
    "addr:housenumber":"35",
    "addr:postcode":"08007",
    "addr:street":"Pl Doctor Letamendi",
    "iso:country":"ES",
    "sg:address":"Pl Doctor Letamendi, 35",
    "sg:city":"Barcelona",
    "sg:orig_category":"Delegados, Agentes De Tr\u00c1nsito, Auxiliares De Transporte Internacional",
    "sg:phone":"+34 934 54 15 59",
    "sg:postcode":"08007",
    "sg:province":"Barcelona",
    "wof:name":"Barcino Pack S.a.",
    "wof:placetype":"venue"
},
  "geometry": {"coordinates":[2.1614329815,41.3889427185],"type":"Point"}
}