{
  "type": "Feature",
  "properties": {
    "iso:country":"ES",
    "sg:address":"Calle de Valdemorillo, 80",
    "sg:city":"Ventorro Del Cano",
    "sg:orig_category":"Empresas De Carpinter\u00cda De Madera",
    "sg:phone":"+34 916 32 17 07",
    "sg:postcode":"28925",
    "sg:province":"Madrid",
    "wof:name":"Bricoma S.l.",
    "wof:placetype":"venue"
},
  "geometry": {"coordinates":[-3.8446400166,40.3900756836],"type":"Point"}
}