{
  "type": "Feature",
  "properties": {
    "addr:full":"Calle de Leon Y Castillo, 62 Palmas De Gran Canaria Las Palmas 35003",
    "addr:postcode":"35003",
    "addr:street":"Calle De Leon Y Castillo 62",
    "iso:country":"ES",
    "sg:address":"Calle de Leon Y Castillo, 62",
    "sg:city":"Palmas De Gran Canaria",
    "sg:orig_category":"Arquitectos",
    "sg:phone":"+34 928 38 10 84",
    "sg:postcode":"35003",
    "sg:province":"Las Palmas",
    "wof:name":"Manchado Boza Enrique",
    "wof:placetype":"venue"
},
  "geometry": {"coordinates":[-15.4192962646,28.1122436523],"type":"Point"}
}