{
  "type": "Feature",
  "properties": {
    "iso:country":"ES",
    "sg:address":"Calle de Letra O, 4",
    "sg:city":"Puebla Alfinden",
    "sg:orig_category":"Construcciones Met\u00c1licas",
    "sg:phone":"+34 976 10 72 16",
    "sg:postcode":"50171",
    "sg:province":"Zaragoza",
    "wof:name":"German Castiella Roberto",
    "wof:placetype":"venue"
},
  "geometry": {"coordinates":[-0.752523005,41.6355133057],"type":"Point"}
}