{
  "type": "Feature",
  "properties": {
    "iso:country":"ES",
    "sg:address":"Ctra Sant Feliu De Guixols, 24",
    "sg:city":"Font De La Polvora",
    "sg:orig_category":"Venta, Colocaci\u00d3n, Tratamiento De Enlosados, Soler\u00cdas",
    "sg:phone":"+34 972 21 09 22",
    "sg:postcode":"17004",
    "sg:province":"Girona",
    "wof:name":"Set Ceramiques S.a.",
    "wof:placetype":"venue"
},
  "geometry": {"coordinates":[2.8422400951,41.9735031128],"type":"Point"}
}