{
  "type": "Feature",
  "properties": {
    "iso:country":"ES",
    "sg:address":"Fca. Mozarvitos, S/n",
    "sg:city":"Aldehuela Boveda",
    "sg:orig_category":"Cr\u00cda De Animales",
    "sg:phone":"+34 923 16 42 78",
    "sg:postcode":"37460",
    "sg:province":"Salamanca",
    "wof:name":"Perez De Herrasti Narvaez Matilde",
    "wof:placetype":"venue"
},
  "geometry": {"coordinates":[-6.1305918694,40.9009666443],"type":"Point"}
}