{
  "type": "Feature",
  "properties": {
    "addr:full":"Avda Andalucia (de), 121 Alcala Rio Sevilla 41200",
    "addr:housenumber":"121",
    "addr:postcode":"41200",
    "addr:street":"Avda Andalucia De",
    "iso:country":"ES",
    "sg:address":"Avda Andalucia (de), 121",
    "sg:city":"Alcala Rio",
    "sg:orig_category":"Congelados: Productos Alimentarios (fabricaci\u00d3n, Al Por Mayor)",
    "sg:phone":"+34 955 65 15 99",
    "sg:postcode":"41200",
    "sg:province":"Sevilla",
    "wof:name":"Congelados Delve S.l.",
    "wof:placetype":"venue"
},
  "geometry": {"coordinates":[-5.9786968231,37.5220832825],"type":"Point"}
}