{
  "type": "Feature",
  "properties": {
    "addr:full":"Avda Florida, 9 Vigo Pontevedra 36210",
    "addr:housenumber":"9",
    "addr:postcode":"36210",
    "addr:street":"Avda Florida",
    "iso:country":"ES",
    "sg:address":"Avda Florida, 9",
    "sg:city":"Vigo",
    "sg:orig_category":"Deportes Diversos",
    "sg:phone":"+34 986 21 18 75",
    "sg:postcode":"36210",
    "sg:province":"Pontevedra",
    "wof:name":"Federacion Gallega De Patinaje",
    "wof:placetype":"venue"
},
  "geometry": {"coordinates":[-8.7486486435,42.2094497681],"type":"Point"}
}