{
  "type": "Feature",
  "properties": {
    "addr:full":"Avda Urtiaga, 1 Mallabia Vizcaya 48269",
    "addr:housenumber":"1",
    "addr:postcode":"48269",
    "addr:street":"Avda Urtiaga",
    "iso:country":"ES",
    "sg:address":"Avda Urtiaga, 1",
    "sg:city":"Mallabia",
    "sg:orig_category":"Agentes, Concesionarios Y Sucursales De Veh\u00cdculos",
    "sg:phone":"+34 943 17 11 00",
    "sg:postcode":"48269",
    "sg:province":"Vizcaya",
    "wof:name":"Perez Prieto Alberto",
    "wof:placetype":"venue"
},
  "geometry": {"coordinates":[-2.5248250961,43.1882171631],"type":"Point"}
}