{
  "type": "Feature",
  "properties": {
    "iso:country":"ES",
    "sg:address":"Carrer de L'abadessa Olzet, 1",
    "sg:city":"Barcelona",
    "sg:orig_category":"Electrodom\u00c9sticos (al Por Menor)",
    "sg:phone":"+34 932 06 03 80",
    "sg:postcode":"08034",
    "sg:province":"Barcelona",
    "wof:name":"Aa Edesa Asistencia Tecnica Averias Servicio Tecnico Reparacion 001 Soh Cb.",
    "wof:placetype":"venue"
},
  "geometry": {"coordinates":[2.114371,41.390663],"type":"Point"}
}