{
  "type": "Feature",
  "properties": {
    "addr:full":"Calle de Jose Zorrilla, 113 Segovia Segovia 40002",
    "addr:housenumber":"113",
    "addr:postcode":"40002",
    "addr:street":"Calle De Jose Zorrilla",
    "iso:country":"ES",
    "sg:address":"Calle de Jose Zorrilla, 113",
    "sg:city":"Segovia",
    "sg:orig_category":"Psic\u00d3logos",
    "sg:phone":"+34 921 42 07 25",
    "sg:postcode":"40002",
    "sg:province":"Segovia",
    "wof:name":"Marazuela Llorente Antonio",
    "wof:placetype":"venue"
},
  "geometry": {"coordinates":[-4.113670826,40.9380950928],"type":"Point"}
}