{
  "type": "Feature",
  "properties": {
    "addr:full":"Avda Vi\u00d1uelas (de), 1 Tres Cantos Madrid 28760",
    "addr:housenumber":"1",
    "addr:postcode":"28760",
    "addr:street":"Avda Vin\u0303Uelas De",
    "iso:country":"ES",
    "sg:address":"Avda Vi\u00d1uelas (de), 1",
    "sg:city":"Tres Cantos",
    "sg:orig_category":"Inmobiliaria (agencias)",
    "sg:phone":"+34 918 03 91 72",
    "sg:postcode":"28760",
    "sg:province":"Madrid",
    "wof:name":"Igs S.a.",
    "wof:placetype":"venue"
},
  "geometry": {"coordinates":[-3.7081251144,40.5955619812],"type":"Point"}
}