{
  "type": "Feature",
  "properties": {
    "iso:country":"ES",
    "sg:address":"Calle de Manuel Aza\u00d1a, S/n",
    "sg:city":"Alcala Guadaira",
    "sg:orig_category":"Metalurgia",
    "sg:phone":"+34 955 61 02 66",
    "sg:postcode":"41500",
    "sg:province":"Sevilla",
    "wof:name":"Herramientas De Corte Tornay S.l.",
    "wof:placetype":"venue"
},
  "geometry": {"coordinates":[-5.8267989159,37.3442764282],"type":"Point"}
}