{
  "type": "Feature",
  "properties": {
    "addr:full":"Calle de Martin Cansado, 59 Badajoz Badajoz 06002",
    "addr:housenumber":"59",
    "addr:postcode":"06002",
    "addr:street":"Calle De Martin Cansado",
    "iso:country":"ES",
    "sg:address":"Calle de Martin Cansado, 59",
    "sg:city":"Badajoz",
    "sg:orig_category":"Arreglo, Reparaci\u00d3n, Piezas Sueltas De Televisi\u00d3n, V\u00cddeo, Hi",
    "sg:phone":"+34 924 22 45 25",
    "sg:postcode":"06002",
    "sg:province":"Badajoz",
    "wof:name":"Jimenez Berrocal Quintin",
    "wof:placetype":"venue"
},
  "geometry": {"coordinates":[-6.9662809372,38.8768997192],"type":"Point"}
}