{
  "type": "Feature",
  "properties": {
    "addr:full":"Calle de Santiago, 22 Valladolid Valladolid 47001",
    "addr:housenumber":"22",
    "addr:postcode":"47001",
    "addr:street":"Calle De Santiago",
    "iso:country":"ES",
    "sg:address":"Calle de Santiago, 22",
    "sg:city":"Valladolid",
    "sg:orig_category":"M\u00c9dicos: Ginecolog\u00cda Y Obstetricia",
    "sg:phone":"+34 983 35 05 41",
    "sg:postcode":"47001",
    "sg:province":"Valladolid",
    "wof:name":"Garcia Hervas Jose Maria",
    "wof:placetype":"venue"
},
  "geometry": {"coordinates":[-4.7292718887,41.6494064331],"type":"Point"}
}