{
  "type": "Feature",
  "properties": {
    "iso:country":"ES",
    "sg:address":"Plaz Rafael Rodriguez, S/n",
    "sg:city":"Cangas Narcea",
    "sg:orig_category":"Lencer\u00cda Femenina, Corseter\u00cda, Trajes De Ba\u00d1o (al Por Menor)",
    "sg:phone":"+34 985 81 08 59",
    "sg:postcode":"33800",
    "sg:province":"Asturias",
    "wof:name":"Rodriguez Menendez Isabel",
    "wof:placetype":"venue"
},
  "geometry": {"coordinates":[-6.5502290726,43.1801643372],"type":"Point"}
}