{
  "type": "Feature",
  "properties": {
    "addr:full":"Calle de Real, 57 Javali Nuevo Murcia 30832",
    "addr:housenumber":"57",
    "addr:postcode":"30832",
    "addr:street":"Calle De Real",
    "iso:country":"ES",
    "sg:address":"Calle de Real, 57",
    "sg:city":"Javali Nuevo",
    "sg:orig_category":"Lencer\u00cda Femenina, Corseter\u00cda, Trajes De Ba\u00d1o (al Por Menor)",
    "sg:phone":"+34 968 89 23 67",
    "sg:postcode":"30832",
    "sg:province":"Murcia",
    "wof:name":"Ruiz Torrecillas C.b.",
    "wof:placetype":"venue"
},
  "geometry": {"coordinates":[-1.2172750235,37.9861335754],"type":"Point"}
}