{
  "type": "Feature",
  "properties": {
    "addr:full":"Av Bisaroques, 13 Sant Cristofol Les Fonts Girona 17800",
    "addr:housenumber":"13",
    "addr:postcode":"17800",
    "addr:street":"Av Bisaroques;Cristofol",
    "iso:country":"ES",
    "sg:address":"Av Bisaroques, 13",
    "sg:city":"Sant Cristofol Les Fonts",
    "sg:orig_category":"Empresas De Carpinter\u00cda De Madera",
    "sg:phone":"+34 972 26 46 38",
    "sg:postcode":"17800",
    "sg:province":"Girona",
    "wof:name":"Aulinas Espu\u00f1a Francisco",
    "wof:placetype":"venue"
},
  "geometry": {"coordinates":[2.4961194992,42.1826782227],"type":"Point"}
}