{
  "type": "Feature",
  "properties": {
    "iso:country":"ES",
    "sg:address":"Calle de Nu\u00d1ez De Balboa, 6",
    "sg:city":"Palmas De Gran Canaria",
    "sg:orig_category":"Peluqueros: De Se\u00d1oras",
    "sg:phone":"+34 928 39 81 17",
    "sg:postcode":"35012",
    "sg:province":"Las Palmas",
    "wof:name":"Salon Los 4 Soles S.l.l.",
    "wof:placetype":"venue"
},
  "geometry": {"coordinates":[-15.430970192,28.1136188507],"type":"Point"}
}