{
  "type": "Feature",
  "properties": {
    "addr:full":"G.v. Corts Catalanes, 333 Barcelona Barcelona 08014",
    "addr:housenumber":"333",
    "addr:postcode":"08014",
    "addr:street":"Catalanes",
    "iso:country":"ES",
    "sg:address":"G.v. Corts Catalanes, 333",
    "sg:city":"Barcelona",
    "sg:orig_category":"M\u00c9dicos: Estomatolog\u00cda",
    "sg:phone":"+34 934 25 02 86",
    "sg:postcode":"08014",
    "sg:province":"Barcelona",
    "wof:name":"Arfelis Zaragoza Carles",
    "wof:placetype":"venue"
},
  "geometry": {"coordinates":[2.1462693214,41.3730773926],"type":"Point"}
}