{
  "type": "Feature",
  "properties": {
    "addr:full":"Portua, 1 Getaria Guip\u00f9zcoa 20808",
    "addr:housenumber":"1",
    "addr:postcode":"20808",
    "addr:street":"Portua;Guipu\u0300Zcoa",
    "iso:country":"ES",
    "sg:address":"Portua, 1",
    "sg:city":"Getaria",
    "sg:orig_category":"Sanatorios M\u00c9dico",
    "sg:phone":"+34 943 14 06 53",
    "sg:postcode":"20808",
    "sg:province":"Guip\u00f9zcoa",
    "wof:name":"Servicio Vasco De Salud",
    "wof:placetype":"venue"
},
  "geometry": {"coordinates":[-2.2049660683,43.3031158447],"type":"Point"}
}