{
  "type": "Feature",
  "properties": {
    "addr:full":"Calle de Santa Teresa De Jesus, 2 Navahermosa Toledo 45150",
    "addr:housenumber":"2",
    "addr:postcode":"45150",
    "addr:street":"Calle De Santa Teresa De Jesus",
    "iso:country":"ES",
    "sg:address":"Calle de Santa Teresa De Jesus, 2",
    "sg:city":"Navahermosa",
    "sg:orig_category":"Ense\u00d1anza, Formaci\u00d3n Profesional: Aprendizaje",
    "sg:phone":"+34 925 41 05 32",
    "sg:postcode":"45150",
    "sg:province":"Toledo",
    "wof:name":"Ayuntamiento De Navahermosa",
    "wof:placetype":"venue"
},
  "geometry": {"coordinates":[-4.4767260551,39.6335220337],"type":"Point"}
}