{
  "type": "Feature",
  "properties": {
    "addr:full":"C/ Santiago Ramon Y Cajal, 22 Salt Girona 17190",
    "addr:housenumber":"22",
    "addr:postcode":"17190",
    "addr:street":"C / Santiago Ramon Y Cajal",
    "iso:country":"ES",
    "sg:address":"C/ Santiago Ramon Y Cajal, 22",
    "sg:city":"Salt",
    "sg:orig_category":"Peluqueros: De Se\u00d1oras",
    "sg:phone":"+34 972 23 51 23",
    "sg:postcode":"17190",
    "sg:province":"Girona",
    "wof:name":"Martinez Magdaleno Soledad",
    "wof:placetype":"venue"
},
  "geometry": {"coordinates":[2.7939629555,41.9731369019],"type":"Point"}
}