{
  "type": "Feature",
  "properties": {
    "iso:country":"ES",
    "sg:address":"Calle de Estret, 13",
    "sg:city":"Javea",
    "sg:orig_category":"Formaci\u00d3n Continuada (variada)",
    "sg:phone":"+34 965 79 02 45",
    "sg:postcode":"03730",
    "sg:province":"Alicante",
    "wof:name":"Castilla Moncho Yolanda",
    "wof:placetype":"venue"
},
  "geometry": {"coordinates":[0.1640650034,38.7888832092],"type":"Point"}
}