{
  "type": "Feature",
  "properties": {
    "iso:country":"ES",
    "sg:address":"Carrer de Doctor Pi I Sunyer, 10",
    "sg:city":"Roses",
    "sg:orig_category":"Marroquiner\u00cda (confecci\u00d3n)",
    "sg:phone":"+34 972 25 63 22",
    "sg:postcode":"17480",
    "sg:province":"Girona",
    "wof:name":"Turro Abad Sebastia",
    "wof:placetype":"venue"
},
  "geometry": {"coordinates":[3.1755900383,42.2626533508],"type":"Point"}
}