{
  "type": "Feature",
  "properties": {
    "iso:country":"ES",
    "sg:address":"Calle de San Telmo, 61",
    "sg:city":"Madrid",
    "sg:orig_category":"Asilos De Ancianos. Centros Privados",
    "sg:phone":"+34 913 50 09 58",
    "sg:postcode":"28016",
    "sg:province":"Madrid",
    "wof:name":"Pe\u00f1a Jaime S.l.",
    "wof:placetype":"venue"
},
  "geometry": {"coordinates":[-3.6777689457,40.4634437561],"type":"Point"}
}