{
  "type": "Feature",
  "properties": {
    "iso:country":"ES",
    "sg:address":"Prag Bujonis, S/n",
    "sg:city":"S. Feliu Guixols",
    "sg:orig_category":"Fabricaci\u00d3n De Peines Y De Accesorios De Peluquer\u00cda",
    "sg:phone":"+34 972 32 57 08",
    "sg:postcode":"17220",
    "sg:province":"Girona",
    "sg:website":"www.kincosmetics.com",
    "wof:name":"Kin Cosmetics S.a.u.",
    "wof:placetype":"venue"
},
  "geometry": {"coordinates":[3.0378599167,41.7843742371],"type":"Point"}
}