{
  "type": "Feature",
  "properties": {
    "iso:country":"ES",
    "sg:address":"Pase Conde De Los Gaitanes (del), 41",
    "sg:city":"Alcobendas",
    "sg:orig_category":"Muebles, Minoristas",
    "sg:phone":"+34 916 50 68 34",
    "sg:postcode":"28109",
    "sg:province":"Madrid",
    "wof:name":"Oriente Mobiliario S.a.",
    "wof:placetype":"venue"
},
  "geometry": {"coordinates":[-3.6321029663,40.5227508545],"type":"Point"}
}