{
  "type": "Feature",
  "properties": {
    "addr:full":"Calle de Armengual De La Mota, 30 Malaga M\u00e1laga 29007",
    "addr:housenumber":"30",
    "addr:postcode":"29007",
    "addr:street":"Calle De Armengual De La Mota;Ma\u0301Laga",
    "iso:country":"ES",
    "sg:address":"Calle de Armengual De La Mota, 30",
    "sg:city":"Malaga",
    "sg:orig_category":"Ropa Para Se\u00d1oras (al Por Menor)",
    "sg:phone":"+34 952 61 35 68",
    "sg:postcode":"29007",
    "sg:province":"M\u00e1laga",
    "wof:name":"Solo Dise\u00f1o S.l.",
    "wof:placetype":"venue"
},
  "geometry": {"coordinates":[-4.4289898872,36.720741272],"type":"Point"}
}