{
  "type": "Feature",
  "properties": {
    "addr:full":"Avda Constitucion, 13 Brihuega Guadalajara 19400",
    "addr:housenumber":"13",
    "addr:postcode":"19400",
    "addr:street":"Avda Constitucion",
    "iso:country":"ES",
    "sg:address":"Avda Constitucion, 13",
    "sg:city":"Brihuega",
    "sg:orig_category":"Peluquer\u00cdas, Peluquer\u00cda Mixta",
    "sg:phone":"+34 949 28 02 25",
    "sg:postcode":"19400",
    "sg:province":"Guadalajara",
    "wof:name":"Barroso Pastor Maria Elena",
    "wof:placetype":"venue"
},
  "geometry": {"coordinates":[-2.8703289032,40.7592315674],"type":"Point"}
}