{
  "type": "Feature",
  "properties": {
    "addr:full":"Carr Menendez Y Pelayo, 5 Burjassot Valencia 46100",
    "addr:housenumber":"5",
    "addr:postcode":"46100",
    "addr:street":"Carr Menendez Y Pelayo",
    "iso:country":"ES",
    "sg:address":"Carr Menendez Y Pelayo, 5",
    "sg:city":"Burjassot",
    "sg:orig_category":"Empresas De Carpinter\u00cda De Madera",
    "sg:phone":"+34 963 64 30 60",
    "sg:postcode":"46100",
    "sg:province":"Valencia",
    "wof:name":"Tomas Tomas Pedro",
    "wof:placetype":"venue"
},
  "geometry": {"coordinates":[-0.4093889892,39.5153160095],"type":"Point"}
}