{
  "type": "Feature",
  "properties": {
    "addr:full":"Calle de Alhelies, 7 Ranero Murcia 30009",
    "addr:housenumber":"7",
    "addr:postcode":"30009",
    "addr:street":"Calle De Alhelies",
    "iso:country":"ES",
    "sg:address":"Calle de Alhelies, 7",
    "sg:city":"Ranero",
    "sg:orig_category":"Negocio De Materiales De Construcci\u00d3n",
    "sg:phone":"+34 968 29 48 63",
    "sg:postcode":"30009",
    "sg:province":"Murcia",
    "wof:name":"Hernandez Fernandez Pedro Jesus",
    "wof:placetype":"venue"
},
  "geometry": {"coordinates":[-1.1464250088,37.9990577698],"type":"Point"}
}