{
  "type": "Feature",
  "properties": {
    "iso:country":"ES",
    "sg:address":"Calle de San Quintin, 5",
    "sg:city":"Salamanca",
    "sg:orig_category":"Administraciones De Trabajo Y Empleo",
    "sg:phone":"+34 923 28 08 74",
    "sg:postcode":"37001",
    "sg:province":"Salamanca",
    "wof:name":"Servicio Publico De Empleo Estatal-dron. Prov. Salamanca",
    "wof:placetype":"venue"
},
  "geometry": {"coordinates":[-5.6587338448,40.9616851807],"type":"Point"}
}