{
  "type": "Feature",
  "properties": {
    "addr:full":"Rua Coru\u00d1a, 8 Ourense Ourense 32005",
    "addr:housenumber":"8",
    "addr:postcode":"32005",
    "addr:street":"Rua Corun\u0303A",
    "iso:country":"ES",
    "sg:address":"Rua Coru\u00d1a, 8",
    "sg:city":"Ourense",
    "sg:orig_category":"Peluqueros: De Se\u00d1oras",
    "sg:phone":"+34 988 23 18 19",
    "sg:postcode":"32005",
    "sg:province":"Ourense",
    "wof:name":"Gonzalez Romero Aurora",
    "wof:placetype":"venue"
},
  "geometry": {"coordinates":[-7.8639187813,42.3304138184],"type":"Point"}
}