{
  "type": "Feature",
  "properties": {
    "addr:full":"Calle de Poniente, 10 Madrid Madrid 28036",
    "addr:housenumber":"10",
    "addr:postcode":"madrid;28036",
    "addr:street":"Calle De Poniente",
    "iso:country":"ES",
    "sg:address":"Calle de Poniente, 10",
    "sg:city":"Madrid",
    "sg:orig_category":"Formaci\u00d3n Continuada (variada)",
    "sg:phone":"+34 913 02 06 13",
    "sg:postcode":"28036",
    "sg:province":"Madrid",
    "wof:name":"Congregacion Hijas Santa Maria De La Providencia",
    "wof:placetype":"venue"
},
  "geometry": {"coordinates":[-3.6817901134,40.4680900574],"type":"Point"}
}