{
  "type": "Feature",
  "properties": {
    "addr:full":"Carrer de Bassegoda, 56 Barcelona Barcelona 08028",
    "addr:housenumber":"56",
    "addr:postcode":"08028",
    "addr:street":"Carrer De Bassegoda",
    "iso:country":"ES",
    "sg:address":"Carrer de Bassegoda, 56",
    "sg:city":"Barcelona",
    "sg:orig_category":"Panader\u00cdas, Panader\u00cdas",
    "sg:phone":"+34 933 33 06 85",
    "sg:postcode":"08028",
    "sg:province":"Barcelona",
    "wof:name":"Artesa Del Dol\u00e7 S.l.",
    "wof:placetype":"venue"
},
  "geometry": {"coordinates":[2.1239962578,41.3742713928],"type":"Point"}
}