{
  "type": "Feature",
  "properties": {
    "addr:full":"C/ Tarragona, 3 Llucmajor Islas Baleares 07620",
    "addr:housenumber":"3",
    "addr:postcode":"07620",
    "addr:street":"C / Tarragona",
    "iso:country":"ES",
    "sg:address":"C/ Tarragona, 3",
    "sg:city":"Llucmajor",
    "sg:orig_category":"Material Y Herramientas Agr\u00cdcolas",
    "sg:phone":"+34 971 66 01 62",
    "sg:postcode":"07620",
    "sg:province":"Islas Baleares",
    "wof:name":"Manresa Rigo Jose",
    "wof:placetype":"venue"
},
  "geometry": {"coordinates":[2.8943190575,39.4851264954],"type":"Point"}
}