{
  "type": "Feature",
  "properties": {
    "iso:country":"ES",
    "sg:address":"Calle de Jose Cremades, 5",
    "sg:city":"Molina Segura",
    "sg:orig_category":"Postigos, Persianas Y Celos\u00cdas",
    "sg:phone":"+34 968 61 14 64",
    "sg:postcode":"30500",
    "sg:province":"Murcia",
    "wof:name":"Persianas Mimar S.l.",
    "wof:placetype":"venue"
},
  "geometry": {"coordinates":[-1.2132594585,38.0652046204],"type":"Point"}
}