{
  "type": "Feature",
  "properties": {
    "iso:country":"ES",
    "sg:address":"Calle de Hornos Caleros (de Los), 2",
    "sg:city":"Avila",
    "sg:orig_category":"Cr\u00cda De Animales",
    "sg:phone":"+34 920 25 55 62",
    "sg:postcode":"05001",
    "sg:province":"\u00c1vila",
    "wof:name":"Ganavila S.l.",
    "wof:placetype":"venue"
},
  "geometry": {"coordinates":[-4.6871891022,40.6558609009],"type":"Point"}
}