{
  "type": "Feature",
  "properties": {
    "iso:country":"ES",
    "sg:address":"As Vendas Da Barreira, S/n",
    "sg:city":"Rios",
    "sg:orig_category":"Distribuci\u00d3n De Petr\u00d3leo Y Derivados",
    "sg:phone":"+34 988 42 30 09",
    "sg:postcode":"32610",
    "sg:province":"Ourense",
    "wof:name":"Valcarce Tarjeta De Transporte S.a.",
    "wof:placetype":"venue"
},
  "geometry": {"coordinates":[-7.2783889771,41.986076355],"type":"Point"}
}