{
  "type": "Feature",
  "properties": {
    "addr:full":"Calle de Virgen De Africa, 20 Sevilla Sevilla 41011",
    "addr:housenumber":"20",
    "addr:postcode":"41011",
    "addr:street":"Calle De Virgen De Africa",
    "iso:country":"ES",
    "sg:address":"Calle de Virgen De Africa, 20",
    "sg:city":"Sevilla",
    "sg:orig_category":"Papeler\u00cdas, Librer\u00cdas",
    "sg:phone":"+34 954 28 13 75",
    "sg:postcode":"41011",
    "sg:province":"Sevilla",
    "wof:name":"Exposito Moreno Francisco Cesar",
    "wof:placetype":"venue"
},
  "geometry": {"coordinates":[-6.0030698776,37.3762397766],"type":"Point"}
}