{
  "type": "Feature",
  "properties": {
    "iso:country":"ES",
    "sg:address":"Zona Industrial, S/n",
    "sg:city":"Punta Umbria",
    "sg:orig_category":"Reposter\u00cdas",
    "sg:phone":"+34 959 31 29 39",
    "sg:postcode":"21100",
    "sg:province":"Huelva",
    "wof:name":"Bueno Muriel Manuel",
    "wof:placetype":"venue"
},
  "geometry": {"coordinates":[-6.9698939323,37.1816444397],"type":"Point"}
}