{
  "type": "Feature",
  "properties": {
    "addr:full":"Calle de Altube, 4 Bilbao Vizcaya 48002",
    "addr:housenumber":"4",
    "addr:postcode":"48002",
    "addr:street":"Calle De Altube",
    "iso:country":"ES",
    "sg:address":"Calle de Altube, 4",
    "sg:city":"Bilbao",
    "sg:orig_category":"Venta, Instalaci\u00d3n De Calefacci\u00d3n",
    "sg:phone":"+34 944 21 76 20",
    "sg:postcode":"48002",
    "sg:province":"Vizcaya",
    "wof:name":"Alberto Alonso Calefaccion S. A.",
    "wof:placetype":"venue"
},
  "geometry": {"coordinates":[-2.9473602772,43.2514915466],"type":"Point"}
}