{
  "type": "Feature",
  "properties": {
    "iso:country":"ES",
    "sg:address":"Carrer de Ciutat, 40",
    "sg:city":"Berga-ciudad",
    "sg:orig_category":"Alimentaci\u00d3n General (al Por Menor)",
    "sg:phone":"+34 938 21 13 85",
    "sg:postcode":"08600",
    "sg:province":"Barcelona",
    "wof:name":"Canals Llado Domingo",
    "wof:placetype":"venue"
},
  "geometry": {"coordinates":[1.8447619677,42.1023330688],"type":"Point"}
}