{
  "type": "Feature",
  "properties": {
    "iso:country":"ES",
    "sg:address":"Plaz Pontevedra, 12",
    "sg:city":"Coru\u00d1a",
    "sg:orig_category":"Abogados",
    "sg:phone":"+34 981 22 70 32",
    "sg:postcode":"15003",
    "sg:province":"La Coru\u00f1a",
    "wof:name":"Corredoira Conde Jose",
    "wof:placetype":"venue"
},
  "geometry": {"coordinates":[-8.4063863754,43.3679389954],"type":"Point"}
}