{
  "type": "Feature",
  "properties": {
    "iso:country":"ES",
    "sg:address":"Calle de Lepanto, 10",
    "sg:city":"Guadalajara",
    "sg:orig_category":"Material Y Herramientas Agr\u00cdcolas",
    "sg:phone":"+34 949 20 82 10",
    "sg:postcode":"19004",
    "sg:province":"Guadalajara",
    "wof:name":"Com. Mec. Agricola S.a.",
    "wof:placetype":"venue"
},
  "geometry": {"coordinates":[-3.193999052,40.6276054382],"type":"Point"}
}