{
  "type": "Feature",
  "properties": {
    "iso:country":"ES",
    "sg:address":"Ctra. Petra, Km. 0005,5",
    "sg:city":"Sineu",
    "sg:orig_category":"Arenas, Guijarros Y Granulados",
    "sg:phone":"+34 971 52 03 41",
    "sg:postcode":"07510",
    "sg:province":"Islas Baleares",
    "wof:name":"Cantera Can Sabane",
    "wof:placetype":"venue"
},
  "geometry": {"coordinates":[3.0094261169,39.6433181763],"type":"Point"}
}