{
  "type": "Feature",
  "properties": {
    "addr:full":"Ctra. Cadiz-malaga, Km. 0144,5 Manilva M\u00e1laga 29692",
    "addr:postcode":"29692",
    "addr:street":"Ctra. Cadiz-Malaga Km. 0144,5;Ma\u0301Laga",
    "iso:country":"ES",
    "sg:address":"Ctra. Cadiz-malaga, Km. 0144,5",
    "sg:city":"Manilva",
    "sg:orig_category":"Inmobiliaria (agencias)",
    "sg:phone":"+34 952 93 68 38",
    "sg:postcode":"29692",
    "sg:province":"M\u00e1laga",
    "sg:website":"www.adhspain.com",
    "wof:name":"Andalucian Dream Homes S.l.",
    "wof:placetype":"venue"
},
  "geometry": {"coordinates":[-5.2657518387,36.3019676208],"type":"Point"}
}