{
  "type": "Feature",
  "properties": {
    "addr:full":"Avda Pontevedra (de), 2 Monterroso Lugo 27560",
    "addr:housenumber":"2",
    "addr:postcode":"27560",
    "addr:street":"Avda Pontevedra De",
    "iso:country":"ES",
    "sg:address":"Avda Pontevedra (de), 2",
    "sg:city":"Monterroso",
    "sg:orig_category":"Molduras, Junquillos, Listones Y Molduras Perforadas",
    "sg:phone":"+34 982 37 75 11",
    "sg:postcode":"27560",
    "sg:province":"Lugo",
    "wof:name":"Doytela S.l.",
    "wof:placetype":"venue"
},
  "geometry": {"coordinates":[-7.8396630287,42.793132782],"type":"Point"}
}