{
  "type": "Feature",
  "properties": {
    "addr:full":"Calle de San Clemente, 5 Jaen Ja\u00e9n 23001",
    "addr:housenumber":"5;jae\u0301n",
    "addr:postcode":"23001",
    "addr:street":"Calle De San Clemente",
    "iso:country":"ES",
    "sg:address":"Calle de San Clemente, 5",
    "sg:city":"Jaen",
    "sg:orig_category":"M\u00c9dicos: An\u00c1lisis Cl\u00cdnicos",
    "sg:phone":"+34 953 24 26 06",
    "sg:postcode":"23001",
    "sg:province":"Ja\u00e9n",
    "wof:name":"Francisco Vera Valiente C.b.",
    "wof:placetype":"venue"
},
  "geometry": {"coordinates":[-3.788695097,37.7678184509],"type":"Point"}
}