{
  "type": "Feature",
  "properties": {
    "addr:full":"Calle de Fuente, 8 Santa Croya De Tera Zamora 49626",
    "addr:housenumber":"8",
    "addr:postcode":"49626",
    "addr:street":"Calle De Fuente",
    "iso:country":"ES",
    "sg:address":"Calle de Fuente, 8",
    "sg:city":"Santa Croya De Tera",
    "sg:orig_category":"Molduras, Junquillos, Listones Y Molduras Perforadas",
    "sg:phone":"+34 980 64 52 71",
    "sg:postcode":"49626",
    "sg:province":"Zamora",
    "wof:name":"Vara Mateos Julia",
    "wof:placetype":"venue"
},
  "geometry": {"coordinates":[-5.9787688255,41.983001709],"type":"Point"}
}