{
  "type": "Feature",
  "properties": {
    "iso:country":"ES",
    "sg:address":"Pase Salut, 47",
    "sg:city":"Badalona",
    "sg:orig_category":"Fabricaci\u00d3n, Importaci\u00d3n, Venta De Material De Telefon\u00cda, Peritelefon\u00cda",
    "sg:phone":"+34 934 60 37 45",
    "sg:postcode":"08914",
    "sg:province":"Barcelona",
    "wof:name":"Catphone Net S.l.",
    "wof:placetype":"venue"
},
  "geometry": {"coordinates":[2.2270600796,41.4407501221],"type":"Point"}
}