{
  "type": "Feature",
  "properties": {
    "addr:full":"Carrer de Montsant, 33 Barcelona Barcelona 08031",
    "addr:housenumber":"33",
    "addr:postcode":"08031",
    "addr:street":"Carrer De Montsant",
    "iso:country":"ES",
    "sg:address":"Carrer de Montsant, 33",
    "sg:city":"Barcelona",
    "sg:orig_category":"Farmacias",
    "sg:phone":"+34 934 29 41 13",
    "sg:postcode":"08031",
    "sg:province":"Barcelona",
    "wof:name":"Trillo Tejedor Yolanda",
    "wof:placetype":"venue"
},
  "geometry": {"coordinates":[2.1699171066,41.4335708618],"type":"Point"}
}