{
  "type": "Feature",
  "properties": {
    "addr:full":"Zona Diseminado Barrio Carrasconte, Km. 0000,8 Piedrafita Babia Le\u00f3n 24141",
    "addr:postcode":"24141",
    "addr:street":"Diseminado Barrio Carrasconte Km. 0000,8 Piedrafita;Leo\u0301N",
    "iso:country":"ES",
    "sg:address":"Zona Diseminado Barrio Carrasconte, Km. 0000,8",
    "sg:city":"Piedrafita Babia",
    "sg:orig_category":"Explotaci\u00d3n De Minas",
    "sg:phone":"+34 987 68 80 76",
    "sg:postcode":"24141",
    "sg:province":"Le\u00f3n",
    "wof:name":"Union Minera Del Norte S.a.",
    "wof:placetype":"venue"
},
  "geometry": {"coordinates":[-6.1893839836,42.9525604248],"type":"Point"}
}