{
  "type": "Feature",
  "properties": {
    "addr:full":"Psaj Jose Flores 'camara', 3 Cordoba C\u00f3rdoba 14005",
    "addr:housenumber":"3",
    "addr:postcode":"14005",
    "addr:street":"Jose Flores ' Camara ';Co\u0301Rdoba",
    "iso:country":"ES",
    "sg:address":"Psaj Jose Flores 'camara', 3",
    "sg:city":"Cordoba",
    "sg:orig_category":"Arquitectos",
    "sg:phone":"+34 957 45 60 29",
    "sg:postcode":"14005",
    "sg:province":"C\u00f3rdoba",
    "wof:name":"Boyero Gallego Jose Luis",
    "wof:placetype":"venue"
},
  "geometry": {"coordinates":[-4.7988119125,37.8795814514],"type":"Point"}
}