{
  "type": "Feature",
  "properties": {
    "iso:country":"ES",
    "sg:address":"Mirabo, 5",
    "sg:city":"Pedreguer",
    "sg:orig_category":"Plomeros",
    "sg:phone":"+34 966 45 67 11",
    "sg:postcode":"03750",
    "sg:province":"Alicante",
    "wof:name":"Van Elst  Antonio",
    "wof:placetype":"venue"
},
  "geometry": {"coordinates":[0.0347849987,38.7958145142],"type":"Point"}
}