{
  "type": "Feature",
  "properties": {
    "addr:full":"Bidasoa Karrika, 76 Bera Navarra 31780",
    "addr:housenumber":"76",
    "addr:postcode":"31780",
    "addr:street":"Karrika",
    "iso:country":"ES",
    "sg:address":"Bidasoa Karrika, 76",
    "sg:city":"Bera",
    "sg:orig_category":"Fabricaci\u00d3n De Moldes Y Modelos",
    "sg:phone":"+34 948 62 51 66",
    "sg:postcode":"31780",
    "sg:province":"Navarra",
    "wof:name":"Azpiroz Nazabal Unai",
    "wof:placetype":"venue"
},
  "geometry": {"coordinates":[-1.6882283688,43.2741355896],"type":"Point"}
}