{
  "type": "Feature",
  "properties": {
    "addr:full":"Avda Madrid (de), 6 San Fernando De Henares Madrid 28830",
    "addr:postcode":"28830",
    "addr:street":"Avda Madrid De 6",
    "iso:country":"ES",
    "sg:address":"Avda Madrid (de), 6",
    "sg:city":"San Fernando De Henares",
    "sg:orig_category":"Estancos",
    "sg:phone":"+34 916 69 35 17",
    "sg:postcode":"28830",
    "sg:province":"Madrid",
    "wof:name":"Soler Garcia Maria Antonia",
    "wof:placetype":"venue"
},
  "geometry": {"coordinates":[-3.535089016,40.4280471802],"type":"Point"}
}