{
  "type": "Feature",
  "properties": {
    "addr:full":"Ctra. Fortuna, Km. 0001,7 Molina Segura Murcia 30500",
    "addr:postcode":"30500",
    "addr:street":"Ctra. Fortuna Km. 0001,7 Molina",
    "iso:country":"ES",
    "sg:address":"Ctra. Fortuna, Km. 0001,7",
    "sg:city":"Molina Segura",
    "sg:orig_category":"Insecticidas, Fumigaci\u00d3n",
    "sg:phone":"+34 968 64 31 00",
    "sg:postcode":"30500",
    "sg:province":"Murcia",
    "wof:name":"Arom S.a.",
    "wof:placetype":"venue"
},
  "geometry": {"coordinates":[-1.1568307877,38.1172027588],"type":"Point"}
}