{
  "type": "Feature",
  "properties": {
    "iso:country":"ES",
    "sg:address":"Calle de Colon, 33",
    "sg:city":"Valencia",
    "sg:orig_category":"Confecci\u00d3n De Trajes Para Se\u00d1oras",
    "sg:phone":"+34 963 51 07 79",
    "sg:postcode":"46004",
    "sg:province":"Valencia",
    "wof:name":"Douglas Spain S.a.",
    "wof:placetype":"venue"
},
  "geometry": {"coordinates":[-0.3995935023,39.4247245789],"type":"Point"}
}