{
  "type": "Feature",
  "properties": {
    "addr:full":"Pg Josep Carner, 51 Barcelona Barcelona 08038",
    "addr:housenumber":"51",
    "addr:postcode":"08038",
    "addr:street":"Pg Josep Carner",
    "iso:country":"ES",
    "sg:address":"Pg Josep Carner, 51",
    "sg:city":"Barcelona",
    "sg:orig_category":"Obras Y Organismos Sociales",
    "sg:phone":"+34 934 42 09 62",
    "sg:postcode":"08038",
    "sg:province":"Barcelona",
    "wof:name":"Delegacio Diocesana Del Apostolat Del Mar Arquebisbat De Barcelona",
    "wof:placetype":"venue"
},
  "geometry": {"coordinates":[2.1737320423,41.3695869446],"type":"Point"}
}