{
  "type": "Feature",
  "properties": {
    "iso:country":"ES",
    "sg:address":"Calle de Barcelona, 5",
    "sg:city":"Cox",
    "sg:orig_category":"Inmobiliaria (agencias)",
    "sg:phone":"+34 966 75 05 35",
    "sg:postcode":"03350",
    "sg:province":"Alicante",
    "wof:name":"Marin Inmobiliaria C.b.",
    "wof:placetype":"venue"
},
  "geometry": {"coordinates":[-0.8900207877,38.1456260681],"type":"Point"}
}