{
  "type": "Feature",
  "properties": {
    "iso:country":"ES",
    "sg:address":"Freans, S/n",
    "sg:city":"Freans",
    "sg:orig_category":"Empresas De Carpinter\u00cda De Madera",
    "sg:phone":"+34 988 49 48 45",
    "sg:postcode":"32226",
    "sg:province":"Ourense",
    "wof:name":"Miguez Fernandez Elias",
    "wof:placetype":"venue"
},
  "geometry": {"coordinates":[-8.151304245,42.1236190796],"type":"Point"}
}