{
  "type": "Feature",
  "properties": {
    "addr:full":"Carr Migdia, 1 Girona Girona 17002",
    "addr:housenumber":"1",
    "addr:postcode":"17002",
    "addr:street":"Carr Migdia",
    "iso:country":"ES",
    "sg:address":"Carr Migdia, 1",
    "sg:city":"Girona",
    "sg:orig_category":"Marroquiner\u00cda (confecci\u00d3n)",
    "sg:phone":"+34 972 22 05 57",
    "sg:postcode":"17002",
    "sg:province":"Girona",
    "wof:name":"Big Bag Shop S.l.",
    "wof:placetype":"venue"
},
  "geometry": {"coordinates":[2.8216729164,41.9779586792],"type":"Point"}
}