{
  "type": "Feature",
  "properties": {
    "iso:country":"ES",
    "sg:address":"Calle de Malaga, 1",
    "sg:city":"Cordoba",
    "sg:orig_category":"\u00d3ptica: Instrumentos (fabricaci\u00d3n)",
    "sg:phone":"+34 957 47 65 61",
    "sg:postcode":"14003",
    "sg:province":"C\u00f3rdoba",
    "wof:name":"Hortelano Rodriguez Juan Miguel",
    "wof:placetype":"venue"
},
  "geometry": {"coordinates":[-4.7801270485,37.8840866089],"type":"Point"}
}