{
  "type": "Feature",
  "properties": {
    "addr:full":"Pol. Ind. La Central, S/n Central Asturias 33940",
    "addr:housenumber":"s / n",
    "addr:postcode":"33940",
    "addr:street":"Central Asturias",
    "iso:country":"ES",
    "sg:address":"Pol. Ind. La Central, S/n",
    "sg:city":"Central",
    "sg:orig_category":"Peluquer\u00cdas, Peluquer\u00cda Mixta",
    "sg:phone":"+34 985 65 48 84",
    "sg:postcode":"33940",
    "sg:province":"Asturias",
    "wof:name":"F & R Imagen Peluqueria Y Belleza S.l.",
    "wof:placetype":"venue"
},
  "geometry": {"coordinates":[-5.6435742378,43.2864112854],"type":"Point"}
}