{
  "type": "Feature",
  "properties": {
    "addr:full":"Pg Illetes, 32 Cas Catala-illetes Islas Baleares 07181",
    "addr:housenumber":"32",
    "addr:postcode":"07181",
    "addr:street":"Illetes;Islas",
    "iso:country":"ES",
    "sg:address":"Pg Illetes, 32",
    "sg:city":"Cas Catala-illetes",
    "sg:orig_category":"Alquiler De Veh\u00cdculos: Turismos Y Utilitarios",
    "sg:phone":"+34 971 70 30 62",
    "sg:postcode":"07181",
    "sg:province":"Islas Baleares",
    "wof:name":"Massanet Barcelo Juan Bautista",
    "wof:placetype":"venue"
},
  "geometry": {"coordinates":[2.5917849541,39.5399398804],"type":"Point"}
}