{
  "type": "Feature",
  "properties": {
    "iso:country":"ES",
    "sg:address":"Calle de Doctor Mu\u00d1oz, 21",
    "sg:city":"Cazorla",
    "sg:orig_category":"Ense\u00d1anza: Profesiones Art\u00cdsticas",
    "sg:phone":"+34 953 72 05 02",
    "sg:postcode":"23470",
    "sg:province":"Ja\u00e9n",
    "wof:name":"Gomez Mu\u00f1oz Pedro",
    "wof:placetype":"venue"
},
  "geometry": {"coordinates":[-3.0027885437,37.9123306274],"type":"Point"}
}