{
  "type": "Feature",
  "properties": {
    "iso:country":"ES",
    "sg:address":"Carrer de Fra Francesc Palou, 10",
    "sg:city":"Palma",
    "sg:orig_category":"Zapatos (al Por Mayor)",
    "sg:phone":"+34 971 20 81 09",
    "sg:postcode":"07010",
    "sg:province":"Islas Baleares",
    "wof:name":"Calzados Soler S.l.",
    "wof:placetype":"venue"
},
  "geometry": {"coordinates":[2.6525828838,39.5871658325],"type":"Point"}
}