{
  "type": "Feature",
  "properties": {
    "addr:full":"Ctra Pego, S/n Muro Alcoy Alicante 03830",
    "addr:housenumber":"s / n",
    "addr:postcode":"03830",
    "addr:street":"Ctra Pego",
    "iso:country":"ES",
    "sg:address":"Ctra Pego, S/n",
    "sg:city":"Muro Alcoy",
    "sg:orig_category":"Fabricaci\u00d3n De Su\u00c9ters Y Chalecos De Punto",
    "sg:phone":"+34 965 53 09 43",
    "sg:postcode":"03830",
    "sg:province":"Alicante",
    "wof:name":"Diana Punt S.l.",
    "wof:placetype":"venue"
},
  "geometry": {"coordinates":[-0.4414289892,38.7812538147],"type":"Point"}
}