{
  "type": "Feature",
  "properties": {
    "iso:country":"ES",
    "sg:address":"Calle de Gravina, 12",
    "sg:city":"Huelva",
    "sg:orig_category":"Art\u00cdculos De Decoraci\u00d3n",
    "sg:phone":"+34 959 54 21 93",
    "sg:postcode":"21001",
    "sg:province":"Huelva",
    "wof:name":"Herrera Tirador Margarita",
    "wof:placetype":"venue"
},
  "geometry": {"coordinates":[-6.9557938576,37.2577133179],"type":"Point"}
}