{
  "type": "Feature",
  "properties": {
    "iso:country":"ES",
    "sg:address":"Carrer de Antoni Rovira I Virgili (d'), 5",
    "sg:city":"Tarragona",
    "sg:orig_category":"Doctores En Medicina",
    "sg:phone":"+34 977 23 58 54",
    "sg:postcode":"43002",
    "sg:province":"Tarragona",
    "wof:name":"Araujo Lastra Fernando",
    "wof:placetype":"venue"
},
  "geometry": {"coordinates":[1.2496037483,41.1176338196],"type":"Point"}
}