{
  "type": "Feature",
  "properties": {
    "iso:country":"ES",
    "sg:address":"Carrer de Roger De Flor, 276",
    "sg:city":"Barcelona",
    "sg:orig_category":"Arquitectos",
    "sg:phone":"+34 932 07 32 09",
    "sg:postcode":"08025",
    "sg:province":"Barcelona",
    "wof:name":"Bantula Pi Antoni",
    "wof:placetype":"venue"
},
  "geometry": {"coordinates":[2.1671791077,41.4031448364],"type":"Point"}
}