{
  "type": "Feature",
  "properties": {
    "addr:full":"Carrer de L'arc Del Mercat, 10 Barcelona Barcelona 08030",
    "addr:housenumber":"10",
    "addr:postcode":"08030",
    "addr:street":"Carrer De L'Arc Del Mercat",
    "iso:country":"ES",
    "sg:address":"Carrer de L'arc Del Mercat, 10",
    "sg:city":"Barcelona",
    "sg:orig_category":"Poller\u00cda Y Caza (al Por Menor)",
    "sg:phone":"+34 933 45 05 02",
    "sg:postcode":"08030",
    "sg:province":"Barcelona",
    "wof:name":"Prats Lopez Ascension",
    "wof:placetype":"venue"
},
  "geometry": {"coordinates":[2.1889588833,41.434928894],"type":"Point"}
}