{
  "type": "Feature",
  "properties": {
    "addr:full":"Carrer de Call, 19 Barcelona Barcelona 08002",
    "addr:housenumber":"19",
    "addr:postcode":"08002",
    "addr:street":"Carrer De Call",
    "iso:country":"ES",
    "sg:address":"Carrer de Call, 19",
    "sg:city":"Barcelona",
    "sg:orig_category":"Fabricaci\u00d3n De Sobres, Bolsas Y Fundas",
    "sg:phone":"+34 933 18 30 33",
    "sg:postcode":"08002",
    "sg:province":"Barcelona",
    "wof:name":"Bustiche Y Poidomane S.l.",
    "wof:placetype":"venue"
},
  "geometry": {"coordinates":[2.1763329506,41.3825492859],"type":"Point"}
}