{
  "type": "Feature",
  "properties": {
    "addr:full":"Carrer de Ferran Puig, 24 Prat Llobregat Barcelona 08820",
    "addr:housenumber":"24",
    "addr:postcode":"08820",
    "addr:street":"Carrer De Ferran Puig;Llobregat",
    "iso:country":"ES",
    "sg:address":"Carrer de Ferran Puig, 24",
    "sg:city":"Prat Llobregat",
    "sg:orig_category":"Ropa Para Ni\u00d1os (al Por Menor)",
    "sg:phone":"+34 933 79 58 41",
    "sg:postcode":"08820",
    "sg:province":"Barcelona",
    "wof:name":"Vila Bertran Ana Maria",
    "wof:placetype":"venue"
},
  "geometry": {"coordinates":[2.0932409763,41.3294944763],"type":"Point"}
}