{
  "type": "Feature",
  "properties": {
    "iso:country":"ES",
    "sg:address":"Plaz Espa\u00d1a, 13",
    "sg:city":"Cantavieja",
    "sg:classifiers":[
        {
            "category":"Tea Room",
            "subcategory":"None",
            "type":"Food & Drink"
        }
    ],
    "sg:phone":"+34 964 18 50 36",
    "sg:postcode":"44140",
    "sg:province":"Teruel",
    "sg:tags":[
        "snack"
    ],
    "wof:name":"Castillo Buj Maria Angeles",
    "wof:placetype":"venue"
},
  "geometry": {"coordinates":[-0.405054003,40.5264396667],"type":"Point"}
}