{
  "type": "Feature",
  "properties": {
    "iso:country":"ES",
    "sg:address":"Pase General Davila, 42",
    "sg:city":"Santander",
    "sg:orig_category":"Carpinteros",
    "sg:phone":"+34 942 28 17 76",
    "sg:postcode":"39005",
    "sg:province":"Cantabria",
    "wof:name":"Borrego Manzano Andres",
    "wof:placetype":"venue"
},
  "geometry": {"coordinates":[-3.7946250439,43.4685211182],"type":"Point"}
}