{
  "type": "Feature",
  "properties": {
    "iso:country":"ES",
    "sg:address":"Carr Ernest Ehrenfeld, 2",
    "sg:city":"Eivissa",
    "sg:orig_category":"Conservatorios",
    "sg:phone":"+34 971 39 22 53",
    "sg:postcode":"07800",
    "sg:province":"Islas Baleares",
    "wof:name":"Conservatori Professional De Musica Y Dansa Deivissa I Formentera",
    "wof:placetype":"venue"
},
  "geometry": {"coordinates":[1.4106199741,38.9010391235],"type":"Point"}
}