{
  "type": "Feature",
  "properties": {
    "addr:full":"Carrer de L'escorial, 112 Barcelona Barcelona 08024",
    "addr:housenumber":"112",
    "addr:postcode":"08024",
    "addr:street":"Carrer De L'Escorial",
    "iso:country":"ES",
    "sg:address":"Carrer de L'escorial, 112",
    "sg:city":"Barcelona",
    "sg:orig_category":"Agencias De Viajes",
    "sg:phone":"+34 932 19 04 54",
    "sg:postcode":"08024",
    "sg:province":"Barcelona",
    "wof:name":"Viatges Madras S. A.",
    "wof:placetype":"venue"
},
  "geometry": {"coordinates":[2.1600329876,41.4086952209],"type":"Point"}
}