{
  "type": "Feature",
  "properties": {
    "iso:country":"ES",
    "sg:address":"Pol. Ind. Os Capelos, S/n",
    "sg:city":"Carral",
    "sg:orig_category":"Maquinaria Para Industrias Diversas",
    "sg:phone":"+34 981 67 66 52",
    "sg:postcode":"15175",
    "sg:province":"La Coru\u00f1a",
    "wof:name":"Blanco Mayer S.l.",
    "wof:placetype":"venue"
},
  "geometry": {"coordinates":[-8.3558893204,43.2278442383],"type":"Point"}
}