{
  "type": "Feature",
  "properties": {
    "iso:country":"ES",
    "sg:address":"Av Josep M. Bosch Aymerich, 16",
    "sg:city":"Masella",
    "sg:orig_category":"Deportes Y Ocio: Art\u00cdculos Y Ropas (al Por Menor Y Accesorios)",
    "sg:phone":"+34 972 14 44 71",
    "sg:postcode":"17538",
    "sg:province":"Girona",
    "wof:name":"Puigbo Trevejo S.l.",
    "wof:placetype":"venue"
},
  "geometry": {"coordinates":[1.8867280483,42.3738555908],"type":"Point"}
}