{
  "type": "Feature",
  "properties": {
    "iso:country":"ES",
    "sg:address":"Calle de Cocherito De Bilbao, 2",
    "sg:city":"Bilbao",
    "sg:orig_category":"Empresas De Carpinter\u00cda Met\u00c1lica",
    "sg:phone":"+34 944 11 84 67",
    "sg:postcode":"48004",
    "sg:province":"Vizcaya",
    "wof:name":"Uniamy S.l.",
    "wof:placetype":"venue"
},
  "geometry": {"coordinates":[-2.9091312885,43.2501983643],"type":"Point"}
}