{
  "type": "Feature",
  "properties": {
    "iso:country":"ES",
    "sg:address":"Carrer de Ca N'alzina, 136",
    "sg:city":"Torre-romeu",
    "sg:orig_category":"Contenedores (mercanc\u00cdas)",
    "sg:phone":"+34 937 26 07 05",
    "sg:postcode":"08202",
    "sg:province":"Barcelona",
    "wof:name":"Gruas Calhitrans S.l.",
    "wof:placetype":"venue"
},
  "geometry": {"coordinates":[2.1323900223,41.5427436829],"type":"Point"}
}