{
  "type": "Feature",
  "properties": {
    "addr:full":"Calle de Alquenencia, 14 Alzira Valencia 46600",
    "addr:housenumber":"14",
    "addr:postcode":"46600",
    "addr:street":"Calle De Alquenencia",
    "iso:country":"ES",
    "sg:address":"Calle de Alquenencia, 14",
    "sg:city":"Alzira",
    "sg:classifiers":[
        {
            "category":"Casinos & Gambling",
            "type":"Entertainment"
        }
    ],
    "sg:phone":"+34 962 40 41 28",
    "sg:postcode":"46600",
    "sg:province":"Valencia",
    "sg:tags":[
        "locale",
        "de",
        "juego"
    ],
    "wof:name":"Bombolletes Park S.l",
    "wof:placetype":"venue"
},
  "geometry": {"coordinates":[-0.4306190908,39.150592804],"type":"Point"}
}