{
  "type": "Feature",
  "properties": {
    "iso:country":"ES",
    "sg:address":"Avda Cristobal Colon, 26",
    "sg:city":"Puerto Cruz",
    "sg:orig_category":"M\u00c9dicos: Oftalmolog\u00cda",
    "sg:phone":"+34 922 37 63 72",
    "sg:postcode":"38400",
    "sg:province":"Santa Cruz De Tenerife",
    "wof:name":"Gonzalez Gimenez Antonio",
    "wof:placetype":"venue"
},
  "geometry": {"coordinates":[-16.5423679352,28.4187755585],"type":"Point"}
}