{
  "type": "Feature",
  "properties": {
    "iso:country":"ES",
    "sg:address":"Carrer de Portalet, 10",
    "sg:city":"Granollers",
    "sg:orig_category":"Peluquer\u00cdas, Peluquer\u00cda Mixta",
    "sg:phone":"+34 938 70 20 75",
    "sg:postcode":"08401",
    "sg:province":"Barcelona",
    "wof:name":"Miras Sanchez Esther",
    "wof:placetype":"venue"
},
  "geometry": {"coordinates":[2.287375927,41.6076011658],"type":"Point"}
}