{
  "type": "Feature",
  "properties": {
    "iso:country":"ES",
    "sg:address":"Calle de Torrellana, 3",
    "sg:city":"Sevilla",
    "sg:orig_category":"Abogados",
    "sg:phone":"+34 954 40 66 78",
    "sg:postcode":"41016",
    "sg:province":"Sevilla",
    "wof:name":"Parrilla Calvente Jose",
    "wof:placetype":"venue"
},
  "geometry": {"coordinates":[-5.9072828293,37.3833465576],"type":"Point"}
}