{
  "type": "Feature",
  "properties": {
    "iso:country":"ES",
    "sg:address":"Calle de Compositor Lehmberg Ruiz, 9",
    "sg:city":"Malaga",
    "sg:orig_category":"Peluqueros: De Se\u00d1oras",
    "sg:phone":"+34 952 39 27 41",
    "sg:postcode":"29007",
    "sg:province":"M\u00e1laga",
    "wof:name":"Guadamuro Bravo Asuncion",
    "wof:placetype":"venue"
},
  "geometry": {"coordinates":[-4.4326896667,36.7177963257],"type":"Point"}
}