{
  "type": "Feature",
  "properties": {
    "iso:country":"ES",
    "sg:address":"Avda Buenos Aires, 4",
    "sg:city":"Utebo",
    "sg:orig_category":"Ropa Para Ni\u00d1os (al Por Menor)",
    "sg:phone":"+34 976 77 32 30",
    "sg:postcode":"50180",
    "sg:province":"Zaragoza",
    "wof:name":"Euromodas,s.c.",
    "wof:placetype":"venue"
},
  "geometry": {"coordinates":[-0.9999449849,41.7045936584],"type":"Point"}
}