{
  "type": "Feature",
  "properties": {
    "iso:country":"ES",
    "sg:address":"Plaz Mondariz, 10",
    "sg:city":"Madrid",
    "sg:orig_category":"Ebanister\u00cda",
    "sg:phone":"+34 917 38 37 10",
    "sg:postcode":"28029",
    "sg:province":"Madrid",
    "wof:name":"Barroso Casado Antonio",
    "wof:placetype":"venue"
},
  "geometry": {"coordinates":[-3.7051401138,40.4780006409],"type":"Point"}
}