{
  "type": "Feature",
  "properties": {
    "iso:country":"ES",
    "sg:address":"Urb. Mi\u00f1or, 46",
    "sg:city":"Mi\u00d1or",
    "sg:orig_category":"Inversiones",
    "sg:phone":"+34 986 38 90 51",
    "sg:postcode":"36380",
    "sg:province":"Pontevedra",
    "wof:name":"Lusiana Inversiones S.l",
    "wof:placetype":"venue"
},
  "geometry": {"coordinates":[-8.7611093521,42.1116867065],"type":"Point"}
}