{
  "type": "Feature",
  "properties": {
    "addr:full":"Calle de Fray Leopoldo, 79 Moraleda Zafayona Granada 18370",
    "addr:housenumber":"79;zafayona",
    "addr:postcode":"18370",
    "addr:street":"Calle De Fray Leopoldo",
    "iso:country":"ES",
    "sg:address":"Calle de Fray Leopoldo, 79",
    "sg:city":"Moraleda Zafayona",
    "sg:orig_category":"Empresas De Carpinter\u00cda Met\u00c1lica",
    "sg:phone":"+34 958 44 30 48",
    "sg:postcode":"18370",
    "sg:province":"Granada",
    "wof:name":"Castillo Gonzalez Francisco Jorge",
    "wof:placetype":"venue"
},
  "geometry": {"coordinates":[-3.9627950191,37.1669273376],"type":"Point"}
}