{
  "type": "Feature",
  "properties": {
    "iso:country":"ES",
    "sg:address":"Cust San Bartolome, 4",
    "sg:city":"Zamora",
    "sg:orig_category":"Empresarios Y Productoras De Espect\u00c1culos",
    "sg:phone":"+34 980 53 30 77",
    "sg:postcode":"49004",
    "sg:province":"Zamora",
    "wof:name":"Chicote Folgado Maria Teresa",
    "wof:placetype":"venue"
},
  "geometry": {"coordinates":[-5.7485351562,41.5047988892],"type":"Point"}
}