{
  "type": "Feature",
  "properties": {
    "addr:full":"Carrer de Jesus, 32 Sitges Barcelona 08870",
    "addr:housenumber":"32",
    "addr:postcode":"08870",
    "addr:street":"Carrer De Jesus",
    "iso:country":"ES",
    "sg:address":"Carrer de Jesus, 32",
    "sg:city":"Sitges",
    "sg:orig_category":"Inmobiliaria (agencias)",
    "sg:phone":"+34 938 94 68 02",
    "sg:postcode":"08870",
    "sg:province":"Barcelona",
    "wof:name":"Fincas El Baluard S.c.p.",
    "wof:placetype":"venue"
},
  "geometry": {"coordinates":[1.8106379509,41.2372245789],"type":"Point"}
}