{
  "type": "Feature",
  "properties": {
    "addr:full":"Ctra Villacastin, Km. 0002,7 Valcabado Zamora 49192",
    "addr:postcode":"49192",
    "addr:street":"Ctra Villacastin Km. 0002,7",
    "iso:country":"ES",
    "sg:address":"Ctra Villacastin, Km. 0002,7",
    "sg:city":"Valcabado",
    "sg:orig_category":"Agentes, Concesionarios Y Sucursales De Veh\u00cdculos",
    "sg:phone":"+34 980 53 89 99",
    "sg:postcode":"49192",
    "sg:province":"Zamora",
    "wof:name":"Royal Motors Salamanca S.l.",
    "wof:placetype":"venue"
},
  "geometry": {"coordinates":[-5.8029990196,41.550819397],"type":"Point"}
}