{
  "type": "Feature",
  "properties": {
    "iso:country":"ES",
    "sg:address":"Calle de Corrida, 13",
    "sg:city":"Gijon",
    "sg:orig_category":"Notarios",
    "sg:phone":"+34 985 34 04 40",
    "sg:postcode":"33206",
    "sg:province":"Asturias",
    "wof:name":"Boulet Alonso Pilar",
    "wof:placetype":"venue"
},
  "geometry": {"coordinates":[-5.6642231941,43.5430450439],"type":"Point"}
}