{
  "type": "Feature",
  "properties": {
    "addr:full":"Avda Valladolid, 42 Tudela Duero Valladolid 47320",
    "addr:housenumber":"42;duero",
    "addr:postcode":"47320",
    "addr:street":"Avda Valladolid",
    "iso:country":"ES",
    "sg:address":"Avda Valladolid, 42",
    "sg:city":"Tudela Duero",
    "sg:orig_category":"Electrodom\u00c9sticos (fabricaci\u00d3n, Al Por Mayor)",
    "sg:phone":"+34 983 52 22 04",
    "sg:postcode":"47320",
    "sg:province":"Valladolid",
    "wof:name":"Herguedas Pascual Pedro Luis",
    "wof:placetype":"venue"
},
  "geometry": {"coordinates":[-4.5839958191,41.5874481201],"type":"Point"}
}