{
  "type": "Feature",
  "properties": {
    "addr:full":"Calle de Mokarte, 3 Burlada Navarra 31600",
    "addr:housenumber":"3",
    "addr:postcode":"31600",
    "addr:street":"Calle De Mokarte",
    "iso:country":"ES",
    "sg:address":"Calle de Mokarte, 3",
    "sg:city":"Burlada",
    "sg:orig_category":"Dise\u00d1o Industrial",
    "sg:phone":"+34 948 23 15 77",
    "sg:postcode":"31600",
    "sg:province":"Navarra",
    "wof:name":"Dp 10 Delineacion",
    "wof:placetype":"venue"
},
  "geometry": {"coordinates":[-1.6127729416,42.8233222961],"type":"Point"}
}