{
  "type": "Feature",
  "properties": {
    "addr:full":"Calle de Ramon Y Cajal, 23 Teruel Teruel 44001",
    "addr:housenumber":"23",
    "addr:postcode":"44001",
    "addr:street":"Calle De Ramon Y Cajal",
    "iso:country":"ES",
    "sg:address":"Calle de Ramon Y Cajal, 23",
    "sg:city":"Teruel",
    "sg:orig_category":"Ropa Para Se\u00d1oras (al Por Menor)",
    "sg:phone":"+34 978 61 22 54",
    "sg:postcode":"44001",
    "sg:province":"Teruel",
    "wof:name":"Spanditex S.a.",
    "wof:placetype":"venue"
},
  "geometry": {"coordinates":[-1.107303977,40.3417358398],"type":"Point"}
}