{
  "type": "Feature",
  "properties": {
    "iso:country":"ES",
    "sg:address":"Carrer de Bosc, 12",
    "sg:city":"Mollet Valles",
    "sg:orig_category":"Telefon\u00cda: Instaladores Varios",
    "sg:phone":"+34 935 93 05 27",
    "sg:postcode":"08100",
    "sg:province":"Barcelona",
    "wof:name":"Instelfa 2001 S.l.",
    "wof:placetype":"venue"
},
  "geometry": {"coordinates":[2.2216830254,41.5481681824],"type":"Point"}
}