{
  "type": "Feature",
  "properties": {
    "iso:country":"ES",
    "sg:address":"Ctra Torrejon (de), Km. 0003,3",
    "sg:city":"Ajalvir",
    "sg:orig_category":"Colchones (fabricaci\u00d3n, Al Por Mayor, Al Por Menor)",
    "sg:phone":"+34 918 84 42 68",
    "sg:postcode":"28864",
    "sg:province":"Madrid",
    "wof:name":"Colchonerias Alcala S.l.",
    "wof:placetype":"venue"
},
  "geometry": {"coordinates":[-3.4812059402,40.5271034241],"type":"Point"}
}