{
  "type": "Feature",
  "properties": {
    "addr:full":"Calle de Granada, 41 Malaga M\u00e1laga 29015",
    "addr:housenumber":"41",
    "addr:postcode":"29015",
    "addr:street":"Calle De Granada;Ma\u0301Laga",
    "iso:country":"ES",
    "sg:address":"Calle de Granada, 41",
    "sg:city":"Malaga",
    "sg:orig_category":"Centros P\u00dablicos De Formaci\u00d3n Profesional Y T\u00c9cnica",
    "sg:phone":"+34 952 21 40 29",
    "sg:postcode":"29015",
    "sg:province":"M\u00e1laga",
    "wof:name":"Colegio Oficial De Economistas",
    "wof:placetype":"venue"
},
  "geometry": {"coordinates":[-4.4189891815,36.7221298218],"type":"Point"}
}