{
  "type": "Feature",
  "properties": {
    "iso:country":"ES",
    "sg:address":"Poli Poligono Industrial De Bakiola, 1",
    "sg:city":"Arene",
    "sg:orig_category":"Papeler\u00cdas: Art\u00cdculos (al Por Mayor)",
    "sg:phone":"+34 946 71 30 00",
    "sg:postcode":"48498",
    "sg:province":"Vizcaya",
    "wof:name":"The Paper Office Equipment Spain Ass S.a.",
    "wof:placetype":"venue"
},
  "geometry": {"coordinates":[-2.9183759689,43.1738014221],"type":"Point"}
}