{
  "type": "Feature",
  "properties": {
    "iso:country":"ES",
    "sg:address":"Csta San Andres, 12",
    "sg:city":"Madrid",
    "sg:orig_category":"Audiovisuales (producci\u00d3n, Edici\u00d3n, Realizaci\u00d3n)",
    "sg:phone":"+34 913 64 34 47",
    "sg:postcode":"28005",
    "sg:province":"Madrid",
    "wof:name":"Perello Santandreu Elisabeth",
    "wof:placetype":"venue"
},
  "geometry": {"coordinates":[-3.7119801044,40.4127807617],"type":"Point"}
}