{
  "type": "Feature",
  "properties": {
    "addr:full":"Carrer de Gran Via De Lluis Companys, 107 Premia Mar Barcelona 08330",
    "addr:housenumber":"107",
    "addr:postcode":"08330",
    "addr:street":"Carrer De Gran Via De Lluis Companys",
    "iso:country":"ES",
    "sg:address":"Carrer de Gran Via De Lluis Companys, 107",
    "sg:city":"Premia Mar",
    "sg:orig_category":"Frutas, Legumbres Frescas Y Tempranas (al Por Menor)",
    "sg:phone":"+34 937 51 24 30",
    "sg:postcode":"08330",
    "sg:province":"Barcelona",
    "wof:name":"Montull Lopez Manuel",
    "wof:placetype":"venue"
},
  "geometry": {"coordinates":[2.353110075,41.4906196594],"type":"Point"}
}