{
  "type": "Feature",
  "properties": {
    "iso:country":"ES",
    "sg:address":"Calle de Nu\u00d1ez De Balboa, 46",
    "sg:city":"Zamora",
    "sg:orig_category":"Farmacias",
    "sg:phone":"+34 980 52 06 80",
    "sg:postcode":"49021",
    "sg:province":"Zamora",
    "wof:name":"Santamaria Moro Carmen",
    "wof:placetype":"venue"
},
  "geometry": {"coordinates":[-5.730132103,41.5130844116],"type":"Point"}
}