{
  "type": "Feature",
  "properties": {
    "iso:country":"ES",
    "sg:address":"Calle de Hilarion Eslava, 69",
    "sg:city":"Madrid",
    "sg:orig_category":"M\u00c9dicos: Estomatolog\u00cda",
    "sg:phone":"+34 915 49 09 67",
    "sg:postcode":"28015",
    "sg:province":"Madrid",
    "wof:name":"Sanchez Vicente Antonio",
    "wof:placetype":"venue"
},
  "geometry": {"coordinates":[-3.7163789272,40.4391098022],"type":"Point"}
}