{
  "type": "Feature",
  "properties": {
    "addr:full":"Carrer de Gonzalez Tablas, 5 Barcelona Barcelona 08034",
    "addr:housenumber":"5",
    "addr:postcode":"08034",
    "addr:street":"Carrer De Gonzalez Tablas",
    "iso:country":"ES",
    "sg:address":"Carrer de Gonzalez Tablas, 5",
    "sg:city":"Barcelona",
    "sg:orig_category":"M\u00c9dicos: Enfermedades De La Sangre (hematolog\u00cda)",
    "sg:phone":"+34 932 04 35 14",
    "sg:postcode":"08034",
    "sg:province":"Barcelona",
    "wof:name":"Vives Corrons Juan Luis",
    "wof:placetype":"venue"
},
  "geometry": {"coordinates":[2.1097557545,41.3851928711],"type":"Point"}
}