{
  "type": "Feature",
  "properties": {
    "iso:country":"ES",
    "sg:address":"Ctra Sevilla-lisboa, S/n",
    "sg:city":"Galaroza",
    "sg:orig_category":"Maquinaria Neum\u00c1tica",
    "sg:phone":"+34 959 12 32 78",
    "sg:postcode":"21291",
    "sg:province":"Huelva",
    "wof:name":"Sociedad De Gestion Del Ciclo Integral Del Agua S.l.",
    "wof:placetype":"venue"
},
  "geometry": {"coordinates":[-6.7124300003,37.9250144958],"type":"Point"}
}