{
  "type": "Feature",
  "properties": {
    "addr:full":"Carr Balanguera ,de La, 8 Santa Eugenia Islas Baleares 07142",
    "addr:housenumber":"8",
    "addr:postcode":"07142",
    "addr:street":"Carr Balanguera De La",
    "iso:country":"ES",
    "sg:address":"Carr Balanguera ,de La, 8",
    "sg:city":"Santa Eugenia",
    "sg:orig_category":"Desinfecci\u00d3n, Desinsectaci\u00d3n, Desratizaci\u00d3n",
    "sg:phone":"+34 971 14 42 77",
    "sg:postcode":"07142",
    "sg:province":"Islas Baleares",
    "wof:name":"Emdema S.l.",
    "wof:placetype":"venue"
},
  "geometry": {"coordinates":[2.8382821083,39.6247177124],"type":"Point"}
}