{
  "type": "Feature",
  "properties": {
    "addr:full":"Calle de San Jorge, 13 Sanlucar De Barrameda C\u00e1diz 11540",
    "addr:housenumber":"13",
    "addr:postcode":"11540",
    "addr:street":"Calle De San Jorge;Ca\u0301Diz",
    "iso:country":"ES",
    "sg:address":"Calle de San Jorge, 13",
    "sg:city":"Sanlucar De Barrameda",
    "sg:orig_category":"Textil",
    "sg:phone":"+34 956 36 80 34",
    "sg:postcode":"11540",
    "sg:province":"C\u00e1diz",
    "wof:name":"Sanchez Falcon Gregorio",
    "wof:placetype":"venue"
},
  "geometry": {"coordinates":[-6.3520212173,36.7786102295],"type":"Point"}
}