{
  "type": "Feature",
  "properties": {
    "addr:full":"Barrio Quintana, S/n Cue Asturias 33509",
    "addr:housenumber":"s / n",
    "addr:postcode":"33509",
    "addr:street":"Barrio Quintana",
    "iso:country":"ES",
    "sg:address":"Barrio Quintana, S/n",
    "sg:city":"Cue",
    "sg:orig_category":"Conservas De Pescados Y Salazones Mar\u00cdtimos (fabricaci\u00d3n, Al Por Mayor)",
    "sg:phone":"+34 985 40 24 54",
    "sg:postcode":"33509",
    "sg:province":"Asturias",
    "wof:name":"Anchoas Ballota S.coop.",
    "wof:placetype":"venue"
},
  "geometry": {"coordinates":[-4.7342357635,43.4117622375],"type":"Point"}
}