{
  "type": "Feature",
  "properties": {
    "iso:country":"ES",
    "sg:address":"Avda Principe De Espa\u00d1a, 14",
    "sg:city":"Almoradi",
    "sg:orig_category":"Muebles, Minoristas",
    "sg:phone":"+34 965 70 11 26",
    "sg:postcode":"03160",
    "sg:province":"Alicante",
    "wof:name":"Franuno S.l.",
    "wof:placetype":"venue"
},
  "geometry": {"coordinates":[-0.7882660031,38.1155776978],"type":"Point"}
}