{
  "type": "Feature",
  "properties": {
    "iso:country":"ES",
    "sg:address":"Carrer de Jerico, 10",
    "sg:city":"Barcelona",
    "sg:orig_category":"Fabricaci\u00d3n De Aparatos De Electricidad, Electromedicina Y Radiolog\u00cda",
    "sg:phone":"+34 932 54 15 40",
    "sg:postcode":"08035",
    "sg:province":"Barcelona",
    "wof:name":"A. B. Medica S. A.",
    "wof:placetype":"venue"
},
  "geometry": {"coordinates":[2.138839,41.421013],"type":"Point"}
}