{
  "type": "Feature",
  "properties": {
    "iso:country":"ES",
    "sg:address":"Calle de Carrera (la), 1",
    "sg:city":"Sax",
    "sg:orig_category":"Arquitectos",
    "sg:phone":"+34 966 96 81 87",
    "sg:postcode":"03630",
    "sg:province":"Alicante",
    "wof:name":"Carbonell Serrano Jose Luis",
    "wof:placetype":"venue"
},
  "geometry": {"coordinates":[-0.8196582794,38.5372962952],"type":"Point"}
}