{
  "type": "Feature",
  "properties": {
    "addr:full":"Calle de Amador De Los Rios, 1 Baena C\u00f3rdoba 14850",
    "addr:housenumber":"1",
    "addr:postcode":"14850",
    "addr:street":"Calle De Amador De Los Rios",
    "iso:country":"ES",
    "sg:address":"Calle de Amador De Los Rios, 1",
    "sg:city":"Baena",
    "sg:orig_category":"Loter\u00cda Y T\u00d3mbola",
    "sg:phone":"+34 957 67 09 68",
    "sg:postcode":"14850",
    "sg:province":"C\u00f3rdoba",
    "wof:name":"Leon-salas Moreno Asuncion",
    "wof:placetype":"venue"
},
  "geometry": {"coordinates":[-4.324640274,37.6153831482],"type":"Point"}
}