{
  "type": "Feature",
  "properties": {
    "iso:country":"ES",
    "sg:address":"Calle de Vazquez De Leca, 12",
    "sg:city":"Sevilla",
    "sg:orig_category":"Iglesia Cat\u00d3lica",
    "sg:phone":"+34 954 27 41 87",
    "sg:postcode":"41010",
    "sg:province":"Sevilla",
    "wof:name":"Real Parroquia De Se\u00f1ora Santa Ana-escuela Taller",
    "wof:placetype":"venue"
},
  "geometry": {"coordinates":[-6.0007238388,37.3829345703],"type":"Point"}
}