{
  "type": "Feature",
  "properties": {
    "addr:full":"Calle de Atocha, 107 Madrid Madrid 28012",
    "addr:housenumber":"107",
    "addr:postcode":"28012",
    "addr:street":"Calle De Atocha",
    "iso:country":"ES",
    "sg:address":"Calle de Atocha, 107",
    "sg:city":"Madrid",
    "sg:orig_category":"Asesor\u00cda Fiscal Y Jur\u00cddica",
    "sg:phone":"+34 913 69 12 12",
    "sg:postcode":"28012",
    "sg:province":"Madrid",
    "wof:name":"Acta Tributaria S.l.",
    "wof:placetype":"venue"
},
  "geometry": {"coordinates":[-3.6952662468,40.4104232788],"type":"Point"}
}