{
  "type": "Feature",
  "properties": {
    "iso:country":"ES",
    "sg:address":"Calle de San Juan, 13",
    "sg:city":"Briones",
    "sg:orig_category":"Restaurantes",
    "sg:phone":"+34 941 32 21 31",
    "sg:postcode":"26330",
    "sg:province":"La Rioja",
    "wof:name":"Los Calaos De Briones S.c.",
    "wof:placetype":"venue"
},
  "geometry": {"coordinates":[-2.7849171162,42.5429534912],"type":"Point"}
}