{
  "type": "Feature",
  "properties": {
    "addr:full":"Avda Italia, 3 Sevilla Sevilla 41012",
    "addr:housenumber":"3",
    "addr:postcode":"41012",
    "addr:street":"Avda Italia",
    "iso:country":"ES",
    "sg:address":"Avda Italia, 3",
    "sg:city":"Sevilla",
    "sg:orig_category":"Granos Y Semillas (producci\u00d3n, Al Por Mayor)",
    "sg:phone":"+34 954 62 50 01",
    "sg:postcode":"41012",
    "sg:province":"Sevilla",
    "wof:name":"Syngenta Seeds S.a.",
    "wof:placetype":"venue"
},
  "geometry": {"coordinates":[-5.9792737961,37.3513145447],"type":"Point"}
}