{
  "type": "Feature",
  "properties": {
    "addr:full":"Carr Son Corco, De, 1 Consell Islas Baleares 07330",
    "addr:housenumber":"1",
    "addr:postcode":"07330",
    "addr:street":"Carr Son Corco De",
    "iso:country":"ES",
    "sg:address":"Carr Son Corco, De, 1",
    "sg:city":"Consell",
    "sg:orig_category":"Inmobiliaria (agencias)",
    "sg:phone":"+34 971 14 22 45",
    "sg:postcode":"07330",
    "sg:province":"Islas Baleares",
    "wof:name":"Feranjosa Tot Vents S.l.",
    "wof:placetype":"venue"
},
  "geometry": {"coordinates":[2.8105449677,39.6676445007],"type":"Point"}
}