{
  "type": "Feature",
  "properties": {
    "iso:country":"ES",
    "sg:address":"Calle de Arzobispo Guerrero, 4",
    "sg:city":"Granada",
    "sg:orig_category":"Institutos De Belleza",
    "sg:phone":"+34 958 20 32 22",
    "sg:postcode":"18015",
    "sg:province":"Granada",
    "wof:name":"Martin Jimenez Maria Del Mar",
    "wof:placetype":"venue"
},
  "geometry": {"coordinates":[-3.6232187748,37.1916809082],"type":"Point"}
}