{
  "type": "Feature",
  "properties": {
    "iso:country":"ES",
    "sg:address":"Moll Adossat, S/n",
    "sg:city":"Barcelona",
    "sg:orig_category":"Informaci\u00d3n Financiera Y Comercial",
    "sg:phone":"+34 932 24 07 10",
    "sg:postcode":"08039",
    "sg:province":"Barcelona",
    "sg:website":"www.cathelicopters.com",
    "wof:name":"Cat Helicopters",
    "wof:placetype":"venue"
},
  "geometry": {"coordinates":[2.1822900772,41.3628540039],"type":"Point"}
}