{
  "type": "Feature",
  "properties": {
    "addr:full":"Calle de Cincel (del), 4 Fuenlabrada Madrid 28947",
    "addr:housenumber":"4",
    "addr:postcode":"28947",
    "addr:street":"Calle De Cincel Del",
    "iso:country":"ES",
    "sg:address":"Calle de Cincel (del), 4",
    "sg:city":"Fuenlabrada",
    "sg:orig_category":"Ingenier\u00cda, Centros De Estudios (diversos)",
    "sg:phone":"+34 916 42 21 50",
    "sg:postcode":"28947",
    "sg:province":"Madrid",
    "sg:website":"www.proakis.es",
    "wof:name":"Proakis S.a.",
    "wof:placetype":"venue"
},
  "geometry": {"coordinates":[-3.7591648102,40.2716217041],"type":"Point"}
}