{
  "type": "Feature",
  "properties": {
    "addr:full":"Carrer de Passeig, 10 S. Andreu Barca Barcelona 08740",
    "addr:housenumber":"10",
    "addr:postcode":"08740",
    "addr:street":"Carrer De Passeig;Andreu;Barcelona",
    "iso:country":"ES",
    "sg:address":"Carrer de Passeig, 10",
    "sg:city":"S. Andreu Barca",
    "sg:orig_category":"Alimentaci\u00d3n: Aditivos, Esencias Alimentarias, Levaduras (fabricaci\u00d3n, Al Por Mayor)",
    "sg:phone":"+34 936 82 02 33",
    "sg:postcode":"08740",
    "sg:province":"Barcelona",
    "sg:website":"www.ictnet.es/+hausmann",
    "wof:name":"Hausmann S.a.",
    "wof:placetype":"venue"
},
  "geometry": {"coordinates":[1.9715509415,41.4475440979],"type":"Point"}
}