{
  "type": "Feature",
  "properties": {
    "iso:country":"ES",
    "sg:address":"Calle de Candido Albarran, 46",
    "sg:city":"Salamanca",
    "sg:orig_category":"Reposter\u00cdas",
    "sg:phone":"+34 923 22 51 43",
    "sg:postcode":"37006",
    "sg:province":"Salamanca",
    "wof:name":"Rogarca Sociedad Laboral",
    "wof:placetype":"venue"
},
  "geometry": {"coordinates":[-5.6771655083,40.9781494141],"type":"Point"}
}