{
  "type": "Feature",
  "properties": {
    "iso:country":"ES",
    "sg:address":"Calle de Marquesa Paterna Del Campo, 10",
    "sg:city":"Valencia",
    "sg:orig_category":"Empresas De Pintura Y Revestimientos",
    "sg:phone":"+34 963 49 95 53",
    "sg:postcode":"46025",
    "sg:province":"Valencia",
    "wof:name":"Garcia Atienzar Isabel",
    "wof:placetype":"venue"
},
  "geometry": {"coordinates":[-0.390545994,39.4994773865],"type":"Point"}
}