{
  "type": "Feature",
  "properties": {
    "iso:country":"ES",
    "sg:address":"Calle de Uruguay, S/n",
    "sg:city":"Toledo",
    "sg:orig_category":"Inmobiliaria (agencias)",
    "sg:phone":"+34 925 22 77 70",
    "sg:postcode":"45004",
    "sg:province":"Toledo",
    "sg:website":"www paginasamarillas.es",
    "wof:name":"Tardio Ledesma Sonia",
    "wof:placetype":"venue"
},
  "geometry": {"coordinates":[-4.0323691368,39.8679466248],"type":"Point"}
}