{
  "type": "Feature",
  "properties": {
    "addr:full":"Calle de Darro, S/n Dos Hermanas Sevilla 41700",
    "addr:housenumber":"s / n",
    "addr:postcode":"41700",
    "addr:street":"Calle De Darro",
    "iso:country":"ES",
    "sg:address":"Calle de Darro, S/n",
    "sg:city":"Dos Hermanas",
    "sg:classifiers":[
        {
            "category":"Tea Room",
            "subcategory":"None",
            "type":"Food & Drink"
        }
    ],
    "sg:phone":"+34 955 66 22 56",
    "sg:postcode":"41700",
    "sg:province":"Sevilla",
    "sg:tags":[
        "snack"
    ],
    "wof:name":"Martin Bermudez Jose Manuel",
    "wof:placetype":"venue"
},
  "geometry": {"coordinates":[-5.9129309654,37.2826766968],"type":"Point"}
}