{
  "type": "Feature",
  "properties": {
    "iso:country":"ES",
    "sg:address":"Calle de Miguel Servet, 59",
    "sg:city":"Zaragoza",
    "sg:orig_category":"Sindicatos Y Colegios Profesionales",
    "sg:phone":"+34 976 48 62 41",
    "sg:postcode":"50013",
    "sg:province":"Zaragoza",
    "wof:name":"Asociacion Profesional De Artesanos De Aragon",
    "wof:placetype":"venue"
},
  "geometry": {"coordinates":[-0.8694561124,41.6435279846],"type":"Point"}
}