{
  "type": "Feature",
  "properties": {
    "addr:full":"Afores, S/n S. Miquel Campmajor Girona 17831",
    "addr:housenumber":"s",
    "addr:postcode":"17831",
    "addr:street":"Afores;/ N S. Miquel Campmajor",
    "iso:country":"ES",
    "sg:address":"Afores, S/n",
    "sg:city":"S. Miquel Campmajor",
    "sg:orig_category":"Iglesia Cat\u00d3lica",
    "sg:phone":"+34 972 58 08 34",
    "sg:postcode":"17831",
    "sg:province":"Girona",
    "wof:name":"Bisbat De Girona",
    "wof:placetype":"venue"
},
  "geometry": {"coordinates":[2.6801700592,42.1358909607],"type":"Point"}
}