{
  "type": "Feature",
  "properties": {
    "iso:country":"ES",
    "sg:address":"Av Pau Claris, 14",
    "sg:city":"Seu D'urgell",
    "sg:orig_category":"Peluquer\u00cdas, Peluquer\u00cda Mixta",
    "sg:phone":"+34 973 35 41 96",
    "sg:postcode":"25700",
    "sg:province":"Lleida",
    "wof:name":"Armengol Tosas Montse",
    "wof:placetype":"venue"
},
  "geometry": {"coordinates":[1.4593274593,42.3576927185],"type":"Point"}
}