{
  "type": "Feature",
  "properties": {
    "addr:full":"Calle de Calatrava, 21 Valencia Valencia 46001",
    "addr:housenumber":"21",
    "addr:postcode":"46001",
    "addr:street":"Calle De Calatrava",
    "iso:country":"ES",
    "sg:address":"Calle de Calatrava, 21",
    "sg:city":"Valencia",
    "sg:orig_category":"Arquitectos",
    "sg:phone":"+34 963 92 57 75",
    "sg:postcode":"46001",
    "sg:province":"Valencia",
    "wof:name":"Herrero Polo Jose Maria",
    "wof:placetype":"venue"
},
  "geometry": {"coordinates":[-0.3773537874,39.4765090942],"type":"Point"}
}