{
  "type": "Feature",
  "properties": {
    "iso:country":"ES",
    "sg:address":"Carr Ferran Rambla, 30",
    "sg:city":"Lleida",
    "sg:orig_category":"Ingenier\u00cda, Centros De Estudios (diversos)",
    "sg:phone":"+34 973 24 37 72",
    "sg:postcode":"25007",
    "sg:province":"Lleida",
    "wof:name":"Proyectec S.a.",
    "wof:placetype":"venue"
},
  "geometry": {"coordinates":[0.627129972,41.6145210266],"type":"Point"}
}