{
  "type": "Feature",
  "properties": {
    "addr:full":"Calle de San Vicente, S/n Villamediana Iregua La Rioja 26142",
    "addr:housenumber":"s / n",
    "addr:postcode":"26142",
    "addr:street":"Calle De San Vicente;Villamediana Iregua;Rioja",
    "iso:country":"ES",
    "sg:address":"Calle de San Vicente, S/n",
    "sg:city":"Villamediana Iregua",
    "sg:orig_category":"Empresas De Carpinter\u00cda",
    "sg:phone":"+34 941 43 56 07",
    "sg:postcode":"26142",
    "sg:province":"La Rioja",
    "wof:name":"Marzoal Carpinteria Metalica Del Aluminio, S.l.",
    "wof:placetype":"venue"
},
  "geometry": {"coordinates":[-2.4213039875,42.4237709045],"type":"Point"}
}