{
  "type": "Feature",
  "properties": {
    "iso:country":"ES",
    "sg:address":"Arkiskil Auzoa, Km. 0001,9",
    "sg:city":"Leitza",
    "sg:orig_category":"Distribuci\u00d3n De Petr\u00d3leo Y Derivados",
    "sg:phone":"+34 948 51 00 57",
    "sg:postcode":"31880",
    "sg:province":"Navarra",
    "wof:name":"Alsua Tellechea Maria Angeles",
    "wof:placetype":"venue"
},
  "geometry": {"coordinates":[-1.8903882504,43.1010017395],"type":"Point"}
}