{
  "type": "Feature",
  "properties": {
    "iso:country":"ES",
    "sg:address":"Calle de Pintores, 5",
    "sg:city":"Caceres",
    "sg:orig_category":"Asociaciones Y Clubs Deportivos",
    "sg:phone":"+34 927 24 47 77",
    "sg:postcode":"10003",
    "sg:province":"C\u00e1ceres",
    "wof:name":"Olimpiada S.a.",
    "wof:placetype":"venue"
},
  "geometry": {"coordinates":[-6.3723640442,39.4747467041],"type":"Point"}
}