{
  "type": "Feature",
  "properties": {
    "iso:country":"ES",
    "sg:address":"Av Jaume I, 46",
    "sg:city":"Mollet Valles",
    "sg:orig_category":"Cajas De Ahorro",
    "sg:phone":"+34 935 70 53 12",
    "sg:postcode":"08100",
    "sg:province":"Barcelona",
    "wof:name":"Caixa D'estalvis I Pensions De Barcelona",
    "wof:placetype":"venue"
},
  "geometry": {"coordinates":[2.2130820751,41.5398368835],"type":"Point"}
}