{
  "type": "Feature",
  "properties": {
    "addr:full":"Avda Legion De (la), 9 Antequera M\u00e1laga 29200",
    "addr:housenumber":"9",
    "addr:postcode":"29200",
    "addr:street":"Avda Legion De La",
    "iso:country":"ES",
    "sg:address":"Avda Legion De (la), 9",
    "sg:city":"Antequera",
    "sg:orig_category":"Producci\u00d3n, Distribuci\u00d3n De Gas Butano Y Propano",
    "sg:phone":"+34 952 84 09 58",
    "sg:postcode":"29200",
    "sg:province":"M\u00e1laga",
    "wof:name":"Butano Gallardo S. L.",
    "wof:placetype":"venue"
},
  "geometry": {"coordinates":[-4.5654740334,37.0200614929],"type":"Point"}
}