{
  "type": "Feature",
  "properties": {
    "addr:full":"Julian Etxeberria Kalea, 6 Eibar Guip\u00f9zcoa 20600",
    "addr:housenumber":"6",
    "addr:postcode":"20600",
    "addr:street":"Julian Etxeberria Kalea;Guipu\u0300Zcoa",
    "iso:country":"ES",
    "sg:address":"Julian Etxeberria Kalea, 6",
    "sg:city":"Eibar",
    "sg:orig_category":"Caf\u00c9s, Bares, Cervecer\u00cdas",
    "sg:phone":"+34 943 20 71 85",
    "sg:postcode":"20600",
    "sg:province":"Guip\u00f9zcoa",
    "wof:name":"Gabiola Garechana Maria Victoria",
    "wof:placetype":"venue"
},
  "geometry": {"coordinates":[-2.4702150822,43.1859741211],"type":"Point"}
}