{
  "type": "Feature",
  "properties": {
    "addr:full":"Calle de Conde Aranda, 91 Zaragoza Zaragoza 50004",
    "addr:housenumber":"91",
    "addr:postcode":"50004",
    "addr:street":"Calle De Conde Aranda",
    "iso:country":"ES",
    "sg:address":"Calle de Conde Aranda, 91",
    "sg:city":"Zaragoza",
    "sg:orig_category":"Camiser\u00cda Y Ropa Interior Masculina (al Por Menor)",
    "sg:phone":"+34 976 43 29 79",
    "sg:postcode":"50004",
    "sg:province":"Zaragoza",
    "wof:name":"Zhou  Yijin",
    "wof:placetype":"venue"
},
  "geometry": {"coordinates":[-0.8914920092,41.6556854248],"type":"Point"}
}