{
  "type": "Feature",
  "properties": {
    "addr:full":"Carr Valdivia, 5 Ca'n Picafort Islas Baleares 07458",
    "addr:housenumber":"5",
    "addr:postcode":"07458",
    "addr:street":"Carr Valdivia",
    "iso:country":"ES",
    "sg:address":"Carr Valdivia, 5",
    "sg:city":"Ca'n Picafort",
    "sg:orig_category":"Agencias De Viajes",
    "sg:phone":"+34 971 85 22 30",
    "sg:postcode":"07458",
    "sg:province":"Islas Baleares",
    "wof:name":"Viajes Canals S.a.",
    "wof:placetype":"venue"
},
  "geometry": {"coordinates":[2.9117100239,39.6136398315],"type":"Point"}
}