{
  "type": "Feature",
  "properties": {
    "addr:full":"Carrer de Esteve Terradas, S/n Manresa Barcelona 08243",
    "addr:housenumber":"s / n",
    "addr:postcode":"08243",
    "addr:street":"Carrer De Esteve Terradas",
    "iso:country":"ES",
    "sg:address":"Carrer de Esteve Terradas, S/n",
    "sg:city":"Manresa",
    "sg:orig_category":"Promotores Constructores",
    "sg:phone":"+34 938 73 63 55",
    "sg:postcode":"08243",
    "sg:province":"Barcelona",
    "wof:name":"Ind.agrop.percar S.l.",
    "wof:placetype":"venue"
},
  "geometry": {"coordinates":[1.8502459526,41.7129402161],"type":"Point"}
}