{
  "type": "Feature",
  "properties": {
    "addr:full":"Ctra Sevilla-merida, Km. 0630,0 Valencina Concepcion Sevilla 41907",
    "addr:postcode":"41907",
    "addr:street":"Ctra Sevilla-Merida Km. 0630,0",
    "iso:country":"ES",
    "sg:address":"Ctra Sevilla-merida, Km. 0630,0",
    "sg:city":"Valencina Concepcion",
    "sg:orig_category":"Frutas Y Legumbres Frescas (al Por Mayor)",
    "sg:phone":"+34 955 95 02 66",
    "sg:postcode":"41907",
    "sg:province":"Sevilla",
    "wof:name":"Snorescombe S.a.",
    "wof:placetype":"venue"
},
  "geometry": {"coordinates":[-6.0776147842,37.4170455933],"type":"Point"}
}