{
  "type": "Feature",
  "properties": {
    "iso:country":"ES",
    "sg:address":"Av Verge Montserrat, 51",
    "sg:city":"Prat Llobregat",
    "sg:orig_category":"Reposter\u00cdas",
    "sg:phone":"+34 934 78 74 23",
    "sg:postcode":"08820",
    "sg:province":"Barcelona",
    "wof:name":"Forn De Pa Valero S.l.",
    "wof:placetype":"venue"
},
  "geometry": {"coordinates":[2.0984559059,41.3269538879],"type":"Point"}
}