{
  "type": "Feature",
  "properties": {
    "iso:country":"ES",
    "sg:address":"Poo, S/n",
    "sg:city":"Poo",
    "sg:orig_category":"Asilos De Ancianos. Centros Privados",
    "sg:phone":"+34 985 40 09 05",
    "sg:postcode":"33509",
    "sg:province":"Asturias",
    "wof:name":"Hospitalarias Del Sagrado Corazon De Jesus",
    "wof:placetype":"venue"
},
  "geometry": {"coordinates":[-4.7796788216,43.4244918823],"type":"Point"}
}