{
  "type": "Feature",
  "properties": {
    "iso:country":"ES",
    "sg:address":"Calle de Guezala Antonio Pintor, 13",
    "sg:city":"Bilbao",
    "sg:orig_category":"Inform\u00c1tica, Ofim\u00c1tica (estudios, Asesor\u00cda, Ingenier\u00cda, Formaci\u00d3n)",
    "sg:phone":"+34 944 47 54 77",
    "sg:postcode":"48015",
    "sg:province":"Vizcaya",
    "wof:name":"Javier Martinez Gonzalez",
    "wof:placetype":"venue"
},
  "geometry": {"coordinates":[-2.9589509964,43.278793335],"type":"Point"}
}