{
  "type": "Feature",
  "properties": {
    "addr:full":"Calle de Errebitarte, 7 Arenas -areeta Vizcaya 48930",
    "addr:housenumber":"7;areeta",
    "addr:postcode":"48930",
    "addr:street":"Calle De Errebitarte",
    "iso:country":"ES",
    "sg:address":"Calle de Errebitarte, 7",
    "sg:city":"Arenas -areeta",
    "sg:orig_category":"Agencias Y Agentes Comerciales, Representantes",
    "sg:phone":"+34 944 64 08 11",
    "sg:postcode":"48930",
    "sg:province":"Vizcaya",
    "wof:name":"Omarrementeria Peiro Ciriaco",
    "wof:placetype":"venue"
},
  "geometry": {"coordinates":[-3.0101668835,43.3217430115],"type":"Point"}
}