{
  "type": "Feature",
  "properties": {
    "iso:country":"ES",
    "sg:address":"Calle de Nereidas, 8",
    "sg:city":"Adra",
    "sg:classifiers":[
        {
            "category":"Autos & Motor Vehicles",
            "subcategory":"Automobile Sales",
            "type":"Retail Goods"
        }
    ],
    "sg:phone":"+34 950 40 04 81",
    "sg:postcode":"04770",
    "sg:province":"Almer\u00eda",
    "wof:name":"Autoescuela Oliver Adra S.l.",
    "wof:placetype":"venue"
},
  "geometry": {"coordinates":[-3.0167577267,36.7478942871],"type":"Point"}
}