{
  "type": "Feature",
  "properties": {
    "addr:full":"German Bernacer(pol Ind), 85 Torrellano Alicante 03320",
    "addr:housenumber":"85",
    "addr:postcode":"03320",
    "addr:street":"Ind",
    "iso:country":"ES",
    "sg:address":"German Bernacer(pol Ind), 85",
    "sg:city":"Torrellano",
    "sg:orig_category":"Ropa Y Accesorios",
    "sg:phone":"+34 965 43 14 10",
    "sg:postcode":"03320",
    "sg:province":"Alicante",
    "wof:name":"King Belt Accesorios Sl",
    "wof:placetype":"venue"
},
  "geometry": {"coordinates":[-0.586401701,38.2937545776],"type":"Point"}
}