{
  "type": "Feature",
  "properties": {
    "addr:full":"Calle de Amparo, 12 Madrid Madrid 28012",
    "addr:housenumber":"12",
    "addr:postcode":"madrid;28012",
    "addr:street":"Calle De Amparo",
    "iso:country":"ES",
    "sg:address":"Calle de Amparo, 12",
    "sg:city":"Madrid",
    "sg:orig_category":"Bisuter\u00cda, Joyer\u00cda, Relojer\u00cda (al Por Menor)",
    "sg:phone":"+34 914 67 53 66",
    "sg:postcode":"28012",
    "sg:province":"Madrid",
    "wof:name":"Gutierrez Gomez Soledad",
    "wof:placetype":"venue"
},
  "geometry": {"coordinates":[-3.7038602829,40.4106407166],"type":"Point"}
}