{
  "type": "Feature",
  "properties": {
    "iso:country":"ES",
    "sg:address":"Calle de Santa Teresita, 33",
    "sg:city":"Zaragoza",
    "sg:orig_category":"Peluqueros: De Se\u00d1oras",
    "sg:phone":"+34 976 32 95 82",
    "sg:postcode":"50017",
    "sg:province":"Zaragoza",
    "wof:name":"Fando Ezquerra Maria Olga",
    "wof:placetype":"venue"
},
  "geometry": {"coordinates":[-0.9114750028,41.6503295898],"type":"Point"}
}