{
  "type": "Feature",
  "properties": {
    "addr:full":"Psaj Sandalo (del), 3 Cuenca Cuenca 16004",
    "addr:postcode":"16004",
    "iso:country":"ES",
    "sg:address":"Psaj Sandalo (del), 3",
    "sg:city":"Cuenca",
    "sg:orig_category":"Ingeniero",
    "sg:phone":"+34 969 22 42 00",
    "sg:postcode":"16004",
    "sg:province":"Cuenca",
    "wof:name":"Tecnologias Y Servicios Agrarios S A",
    "wof:placetype":"venue"
},
  "geometry": {"coordinates":[-2.1316189766,40.0633430481],"type":"Point"}
}