{
  "type": "Feature",
  "properties": {
    "iso:country":"ES",
    "sg:address":"Calle de Perez Galdos, 2",
    "sg:city":"Bilbao",
    "sg:orig_category":"Ingeniero",
    "sg:phone":"+34 944 22 04 99",
    "sg:postcode":"48010",
    "sg:province":"Vizcaya",
    "wof:name":"Eguileor Zulueta Josune",
    "wof:placetype":"venue"
},
  "geometry": {"coordinates":[-2.9407749176,43.2588386536],"type":"Point"}
}