{
  "type": "Feature",
  "properties": {
    "addr:full":"Calle de Sendilla, 7 Estepa Sevilla 41560",
    "addr:housenumber":"7",
    "addr:postcode":"41560",
    "addr:street":"Calle De Sendilla;Sevilla",
    "iso:country":"ES",
    "sg:address":"Calle de Sendilla, 7",
    "sg:city":"Estepa",
    "sg:orig_category":"M\u00c1quinas Y Material Para La Industria De La Alimentaci\u00d3n",
    "sg:phone":"+34 954 82 06 64",
    "sg:postcode":"41560",
    "sg:province":"Sevilla",
    "wof:name":"Mu\u00f1oz Y Mu\u00f1oz Sdad.cv",
    "wof:placetype":"venue"
},
  "geometry": {"coordinates":[-4.8820910454,37.2904968262],"type":"Point"}
}