{
  "type": "Feature",
  "properties": {
    "addr:full":"Calle de Referendum De Vi\u00d1a Grande, 2 Alcorcon Madrid 28925",
    "addr:housenumber":"2",
    "addr:postcode":"28925",
    "addr:street":"Calle De Referendum;Grande",
    "iso:country":"ES",
    "sg:address":"Calle de Referendum De Vi\u00d1a Grande, 2",
    "sg:city":"Alcorcon",
    "sg:orig_category":"Guarder\u00cdas",
    "sg:phone":"+34 916 11 68 61",
    "sg:postcode":"28925",
    "sg:province":"Madrid",
    "wof:name":"Guarderia Nuria S.l.",
    "wof:placetype":"venue"
},
  "geometry": {"coordinates":[-3.8033330441,40.3503456116],"type":"Point"}
}