{
  "type": "Feature",
  "properties": {
    "addr:full":"Av Catalunya, 10 Vilafranca Penedes Barcelona 08720",
    "addr:housenumber":"10",
    "addr:postcode":"08720",
    "addr:street":"Av Catalunya;Penedes Barcelona",
    "iso:country":"ES",
    "sg:address":"Av Catalunya, 10",
    "sg:city":"Vilafranca Penedes",
    "sg:orig_category":"Fisioterapia",
    "sg:phone":"+34 938 17 08 46",
    "sg:postcode":"08720",
    "sg:province":"Barcelona",
    "wof:name":"Fyt Natural Fisioterapia",
    "wof:placetype":"venue"
},
  "geometry": {"coordinates":[1.6915049553,41.3472595215],"type":"Point"}
}