{
  "type": "Feature",
  "properties": {
    "iso:country":"ES",
    "sg:address":"Carretera De Baeza, S/n",
    "sg:city":"Ibros",
    "sg:orig_category":"Mec\u00c1nico Del Autom\u00d3vil",
    "sg:phone":"+34 953 76 62 88",
    "sg:postcode":"23450",
    "sg:province":"Ja\u00e9n",
    "wof:name":"Maeso Granada Jose",
    "wof:placetype":"venue"
},
  "geometry": {"coordinates":[-3.5054740906,38.020980835],"type":"Point"}
}