{
  "type": "Feature",
  "properties": {
    "addr:full":"Rua Ramon Otero Pedrayo, 31 Monforte De Lemos Lugo 27400",
    "addr:housenumber":"31",
    "addr:postcode":"27400",
    "addr:street":"Rua Ramon Otero Pedrayo",
    "iso:country":"ES",
    "sg:address":"Rua Ramon Otero Pedrayo, 31",
    "sg:city":"Monforte De Lemos",
    "sg:classifiers":[
        {
            "category":"Cinema",
            "subcategory":"Movie Theater",
            "type":"Entertainment"
        }
    ],
    "sg:phone":"+34 982 40 53 14",
    "sg:postcode":"27400",
    "sg:province":"Lugo",
    "sg:tags":[
        "salas",
        "de",
        "cine"
    ],
    "wof:name":"Coru\u00f1a Films S.l.",
    "wof:placetype":"venue"
},
  "geometry": {"coordinates":[-7.5114750862,42.5193595886],"type":"Point"}
}