{
  "type": "Feature",
  "properties": {
    "addr:full":"Ctra. S. Clemente, S/n Villanueva Jara Cuenca 16230",
    "addr:housenumber":"s",
    "addr:postcode":"16230",
    "addr:street":"Ctra. S. Clemente;/ N;Jara",
    "iso:country":"ES",
    "sg:address":"Ctra. S. Clemente, S/n",
    "sg:city":"Villanueva Jara",
    "sg:orig_category":"Producci\u00d3n De Abonos Y De Fertilizantes",
    "sg:phone":"+34 967 54 44 03",
    "sg:postcode":"16230",
    "sg:province":"Cuenca",
    "wof:name":"La Jara Compost Scl",
    "wof:placetype":"venue"
},
  "geometry": {"coordinates":[-1.9584540129,39.4430656433],"type":"Point"}
}