{
  "type": "Feature",
  "properties": {
    "iso:country":"ES",
    "sg:address":"Calle de Cardenal Cisneros, 74",
    "sg:city":"Santander",
    "sg:orig_category":"Caf\u00c9s, Bares, Cervecer\u00cdas",
    "sg:phone":"+34 942 37 04 02",
    "sg:postcode":"39007",
    "sg:province":"Cantabria",
    "wof:name":"Perez Sanz Carlos",
    "wof:placetype":"venue"
},
  "geometry": {"coordinates":[-3.8178722858,43.4624862671],"type":"Point"}
}