{
  "type": "Feature",
  "properties": {
    "addr:full":"Barranquet, 10 Aldaia Valencia 46960",
    "addr:housenumber":"10",
    "addr:postcode":"46960",
    "addr:street":"Barranquet",
    "iso:country":"ES",
    "sg:address":"Barranquet, 10",
    "sg:city":"Aldaia",
    "sg:orig_category":"Materias Pl\u00c1sticas: Art\u00cdculos Para La Industria",
    "sg:phone":"+34 961 51 83 80",
    "sg:postcode":"46960",
    "sg:province":"Valencia",
    "wof:name":"Andreu Chenoll Angel Vicente",
    "wof:placetype":"venue"
},
  "geometry": {"coordinates":[-0.4710812867,39.4678382874],"type":"Point"}
}