{
  "type": "Feature",
  "properties": {
    "iso:country":"ES",
    "sg:address":"Mont Kobeta, 45",
    "sg:city":"Bilbao",
    "sg:orig_category":"Cervecer\u00cdas",
    "sg:phone":"+34 944 27 10 02",
    "sg:postcode":"48002",
    "sg:province":"Vizcaya",
    "wof:name":"Maria Bego\u00f1a Gutierrez Leguina Y Ana Isabel Gutierrez Leguina Cdad",
    "wof:placetype":"venue"
},
  "geometry": {"coordinates":[-2.9595239162,43.2590179443],"type":"Point"}
}