{
  "type": "Feature",
  "properties": {
    "addr:full":"Carrer de Fran\u00c7a, 62 Hospitalet Llobregat Barcelona 08907",
    "addr:housenumber":"62",
    "addr:postcode":"08907",
    "addr:street":"Carrer De Franc\u0327A",
    "iso:country":"ES",
    "sg:address":"Carrer de Fran\u00c7a, 62",
    "sg:city":"Hospitalet Llobregat",
    "sg:orig_category":"Frutas, Legumbres Frescas Y Tempranas (al Por Menor)",
    "sg:phone":"+34 933 36 56 01",
    "sg:postcode":"08907",
    "sg:province":"Barcelona",
    "wof:name":"Del Estal Morillo Marcos",
    "wof:placetype":"venue"
},
  "geometry": {"coordinates":[2.1117639542,41.3550987244],"type":"Point"}
}