{
  "type": "Feature",
  "properties": {
    "addr:full":"Carr Pizarro, 3 Algemesi Valencia 46680",
    "addr:housenumber":"3",
    "addr:postcode":"46680",
    "addr:street":"Carr Pizarro",
    "iso:country":"ES",
    "sg:address":"Carr Pizarro, 3",
    "sg:city":"Algemesi",
    "sg:orig_category":"Cerrajer\u00cda, Ferrallista",
    "sg:phone":"+34 962 42 14 78",
    "sg:postcode":"46680",
    "sg:province":"Valencia",
    "wof:name":"Ivars Ferrer Antonio",
    "wof:placetype":"venue"
},
  "geometry": {"coordinates":[-0.4383490086,39.1962852478],"type":"Point"}
}