{
  "type": "Feature",
  "properties": {
    "iso:country":"ES",
    "sg:address":"Calle de Velilla, S/n",
    "sg:city":"Entrena",
    "sg:orig_category":"Bosques (trabajos, Asesor\u00cda, Gesti\u00d3n)",
    "sg:phone":"+34 941 44 60 25",
    "sg:postcode":"26375",
    "sg:province":"La Rioja",
    "wof:name":"Agroiregua S.l",
    "wof:placetype":"venue"
},
  "geometry": {"coordinates":[-2.533415556,42.3901634216],"type":"Point"}
}