{
  "type": "Feature",
  "properties": {
    "iso:country":"ES",
    "sg:address":"Calle de Serrano, 76",
    "sg:city":"Madrid",
    "sg:orig_category":"Centros Empresariales",
    "sg:phone":"+34 915 75 82 26",
    "sg:postcode":"28006",
    "sg:province":"Madrid",
    "sg:website":"www.aneabe.com",
    "wof:name":"Asociacion Nacional De Embotelladores De Aguas De Bebidas Envasadas",
    "wof:placetype":"venue"
},
  "geometry": {"coordinates":[-3.686861515,40.4307098389],"type":"Point"}
}