{
  "type": "Feature",
  "properties": {
    "addr:full":"Port, S/n Ametlla Mar Tarragona 43860",
    "addr:housenumber":"s / n",
    "addr:postcode":"43860",
    "addr:street":"Port",
    "iso:country":"ES",
    "sg:address":"Port, S/n",
    "sg:city":"Ametlla Mar",
    "sg:orig_category":"Sindicatos De Trabajadores",
    "sg:phone":"+34 977 45 67 12",
    "sg:postcode":"43860",
    "sg:province":"Tarragona",
    "wof:name":"Cofradia De Pescadores De San Pedro",
    "wof:placetype":"venue"
},
  "geometry": {"coordinates":[0.846759975,40.9282798767],"type":"Point"}
}