{
  "type": "Feature",
  "properties": {
    "iso:country":"ES",
    "sg:address":"Ctra. A Hevia, S/n",
    "sg:city":"Hevia",
    "sg:orig_category":"Muebles, Minoristas",
    "sg:phone":"+34 985 74 10 23",
    "sg:postcode":"33186",
    "sg:province":"Asturias",
    "sg:website":"www.mueblesjoca.com",
    "wof:name":"Montero Automatismos Y Cierres S.l.",
    "wof:placetype":"venue"
},
  "geometry": {"coordinates":[-5.7012858391,43.3833732605],"type":"Point"}
}