{
  "type": "Feature",
  "properties": {
    "iso:country":"ES",
    "sg:address":"Calle de San Cristobal, 1",
    "sg:city":"Velez-malaga",
    "sg:orig_category":"Comerciantes Al Por Mayor De Vinos, Licores Y Alcoholes",
    "sg:phone":"+34 952 50 17 46",
    "sg:postcode":"29700",
    "sg:province":"M\u00e1laga",
    "wof:name":"Ramos Jurado Jose Luis",
    "wof:placetype":"venue"
},
  "geometry": {"coordinates":[-4.105948925,36.78125],"type":"Point"}
}