{
  "type": "Feature",
  "properties": {
    "addr:full":"Avda Navarra, 54 Zaragoza Zaragoza 50010",
    "addr:housenumber":"54",
    "addr:postcode":"50010",
    "addr:street":"Avda Navarra",
    "iso:country":"ES",
    "sg:address":"Avda Navarra, 54",
    "sg:city":"Zaragoza",
    "sg:orig_category":"Asociaciones, Organismos Culturales Y Socioeducativos",
    "sg:phone":"+34 976 33 32 82",
    "sg:postcode":"50010",
    "sg:province":"Zaragoza",
    "wof:name":"Ayuntamiento De Zaragoza",
    "wof:placetype":"venue"
},
  "geometry": {"coordinates":[-0.906596601,41.6554832458],"type":"Point"}
}