{
  "type": "Feature",
  "properties": {
    "addr:full":"Calle de Fernando Iii, 4 Bola\u00e7os De Calatrava Ciudad Real 13260",
    "addr:housenumber":"4",
    "addr:postcode":"13260",
    "addr:street":"Calle De Fernando Iii",
    "iso:country":"ES",
    "sg:address":"Calle de Fernando Iii, 4",
    "sg:city":"Bola\u00e7os De Calatrava",
    "sg:orig_category":"Arreglo, Reparaci\u00d3n, Piezas Sueltas De Televisi\u00d3n, V\u00cddeo, Hi",
    "sg:phone":"+34 926 87 04 10",
    "sg:postcode":"13260",
    "sg:province":"Ciudad Real",
    "wof:name":"Electro Plata Del Valle S.l.",
    "wof:placetype":"venue"
},
  "geometry": {"coordinates":[-3.6704940796,38.9051551819],"type":"Point"}
}