{
  "type": "Feature",
  "properties": {
    "addr:full":"Calle de Valle Inclan, 20 Gibraleon Huelva 21500",
    "addr:housenumber":"20",
    "addr:postcode":"21500",
    "addr:street":"Calle De Valle Inclan",
    "iso:country":"ES",
    "sg:address":"Calle de Valle Inclan, 20",
    "sg:city":"Gibraleon",
    "sg:orig_category":"Delegados, Agentes De Tr\u00c1nsito, Auxiliares De Transporte Internacional",
    "sg:phone":"+34 959 30 11 43",
    "sg:postcode":"21500",
    "sg:province":"Huelva",
    "wof:name":"Perera Solano Antonio",
    "wof:placetype":"venue"
},
  "geometry": {"coordinates":[-6.966053009,37.3784103394],"type":"Point"}
}