{
  "type": "Feature",
  "properties": {
    "addr:full":"Calle de Fronton, 5 Cantalejo Segovia 40320",
    "addr:housenumber":"5",
    "addr:postcode":"40320",
    "addr:street":"Calle De Fronton",
    "iso:country":"ES",
    "sg:address":"Calle de Fronton, 5",
    "sg:city":"Cantalejo",
    "sg:orig_category":"Frutas, Legumbres Frescas Y Tempranas (al Por Menor)",
    "sg:phone":"+34 921 52 14 38",
    "sg:postcode":"40320",
    "sg:province":"Segovia",
    "wof:name":"Sanz Pastor Angel",
    "wof:placetype":"venue"
},
  "geometry": {"coordinates":[-3.9267139435,41.2570610046],"type":"Point"}
}