{
  "type": "Feature",
  "properties": {
    "iso:country":"ES",
    "sg:address":"Av Castell D'aro, 101",
    "sg:city":"Platja D'aro",
    "sg:orig_category":"Trabajos De Perforaciones, Sondeos, Construcci\u00d3n De Pozos",
    "sg:phone":"+34 972 81 73 73",
    "sg:postcode":"17250",
    "sg:province":"Girona",
    "wof:name":"Navarro Rojas Josefa",
    "wof:placetype":"venue"
},
  "geometry": {"coordinates":[2.8271551132,41.988822937],"type":"Point"}
}