{
  "type": "Feature",
  "properties": {
    "addr:full":"Av Europa, 2 S. Feliu Guixols Girona 17220",
    "addr:housenumber":"2",
    "addr:postcode":"17220",
    "addr:street":"Av Europa;Feliu",
    "iso:country":"ES",
    "sg:address":"Av Europa, 2",
    "sg:city":"S. Feliu Guixols",
    "sg:orig_category":"Cristaler\u00cdas",
    "sg:phone":"+34 972 32 13 37",
    "sg:postcode":"17220",
    "sg:province":"Girona",
    "wof:name":"Ca\u00f1averas Triguero Manuel",
    "wof:placetype":"venue"
},
  "geometry": {"coordinates":[3.0325849056,41.790348053],"type":"Point"}
}