{
  "type": "Feature",
  "properties": {
    "iso:country":"ES",
    "sg:address":"Calle de Triana, 50",
    "sg:city":"Madrid",
    "sg:orig_category":"Arquitectos",
    "sg:phone":"+34 913 50 34 23",
    "sg:postcode":"28016",
    "sg:province":"Madrid",
    "wof:name":"C.o.a. S.l",
    "wof:placetype":"venue"
},
  "geometry": {"coordinates":[-3.6761140823,40.4651222229],"type":"Point"}
}