{
  "type": "Feature",
  "properties": {
    "addr:full":"Calle de Sagastia, 24 Ezcaray La Rioja 26280",
    "addr:housenumber":"24",
    "addr:postcode":"26280",
    "addr:street":"Calle De Sagastia;Rioja",
    "iso:country":"ES",
    "sg:address":"Calle de Sagastia, 24",
    "sg:city":"Ezcaray",
    "sg:orig_category":"Pescader\u00cdas (al Por Menor)",
    "sg:phone":"+34 941 42 71 19",
    "sg:postcode":"26280",
    "sg:province":"La Rioja",
    "wof:name":"Silvestre Saiz Maria Del Carmen",
    "wof:placetype":"venue"
},
  "geometry": {"coordinates":[-3.0145890713,42.3238182068],"type":"Point"}
}