{
  "type": "Feature",
  "properties": {
    "addr:full":"Avda Constitucion (de La), 35 Candelaria Santa Cruz De Tenerife 38530",
    "addr:housenumber":"35",
    "addr:postcode":"38530",
    "addr:street":"Avda Constitucion De La",
    "iso:country":"ES",
    "sg:address":"Avda Constitucion (de La), 35",
    "sg:city":"Candelaria",
    "sg:orig_category":"Asociaciones Y Clubs Deportivos",
    "sg:phone":"+34 922 50 50 12",
    "sg:postcode":"38530",
    "sg:province":"Santa Cruz De Tenerife",
    "wof:name":"Grupo De Compras Canario De Articulos Deportivos S.a.",
    "wof:placetype":"venue"
},
  "geometry": {"coordinates":[-16.3691825867,28.3574733734],"type":"Point"}
}