{
  "type": "Feature",
  "properties": {
    "addr:full":"Carrer de Sant Baltasar, 1 Barcelona Barcelona 08014",
    "addr:housenumber":"1",
    "addr:postcode":"08014",
    "addr:street":"Carrer De Sant Baltasar",
    "iso:country":"ES",
    "sg:address":"Carrer de Sant Baltasar, 1",
    "sg:city":"Barcelona",
    "sg:orig_category":"Promotores Constructores",
    "sg:phone":"+34 932 23 21 70",
    "sg:postcode":"08014",
    "sg:province":"Barcelona",
    "wof:name":"Cayco 1998 S.l.",
    "wof:placetype":"venue"
},
  "geometry": {"coordinates":[2.1339359283,41.3713188171],"type":"Point"}
}