{
  "type": "Feature",
  "properties": {
    "addr:full":"Barr Callejas (las) (pontejos), 23 Pontejos Cantabria 39618",
    "addr:housenumber":"23",
    "addr:postcode":"39618",
    "addr:street":"Pontejos",
    "iso:country":"ES",
    "sg:address":"Barr Callejas (las) (pontejos), 23",
    "sg:city":"Pontejos",
    "sg:orig_category":"Molduras, Junquillos, Listones Y Molduras Perforadas",
    "sg:phone":"+34 942 50 20 22",
    "sg:postcode":"39618",
    "sg:province":"Cantabria",
    "wof:name":"Arnejo Vierna Gerardo",
    "wof:placetype":"venue"
},
  "geometry": {"coordinates":[-3.8051187992,43.4055633545],"type":"Point"}
}