{
  "type": "Feature",
  "properties": {
    "iso:country":"ES",
    "sg:address":"Carrer de Marques De Mulhacen, 11",
    "sg:city":"Barcelona",
    "sg:orig_category":"Doctores En Medicina",
    "sg:phone":"+34 932 04 63 61",
    "sg:postcode":"08034",
    "sg:province":"Barcelona",
    "wof:name":"Murtra Ferre Marcos",
    "wof:placetype":"venue"
},
  "geometry": {"coordinates":[2.1196401119,41.3913269043],"type":"Point"}
}