{
  "type": "Feature",
  "properties": {
    "iso:country":"ES",
    "sg:address":"Carretera De Gallur-sanguesa, S/n",
    "sg:city":"Castiliscar",
    "sg:orig_category":"Cooperativas Agr\u00cdcolas",
    "sg:phone":"+34 976 67 11 57",
    "sg:postcode":"50696",
    "sg:province":"Zaragoza",
    "wof:name":"Cooperativa Del Campo Cristo Del Castillo",
    "wof:placetype":"venue"
},
  "geometry": {"coordinates":[-1.3134829998,42.4308738708],"type":"Point"}
}