{
  "type": "Feature",
  "properties": {
    "addr:full":"Calle de Santa Cruz, 22 Burgos Burgos 09002",
    "addr:housenumber":"22",
    "addr:postcode":"09002",
    "addr:street":"Calle De Santa Cruz",
    "iso:country":"ES",
    "sg:address":"Calle de Santa Cruz, 22",
    "sg:city":"Burgos",
    "sg:orig_category":"Artes Gr\u00c1ficas, Artes Pl\u00c1sticas (curso)",
    "sg:phone":"+34 947 27 60 61",
    "sg:postcode":"09002",
    "sg:province":"Burgos",
    "wof:name":"Menendez Martinez Angel Jesus",
    "wof:placetype":"venue"
},
  "geometry": {"coordinates":[-3.6973979473,42.3366470337],"type":"Point"}
}