{
  "type": "Feature",
  "properties": {
    "addr:full":"Avda Francisco Sobrin, 21 Camponaraya Le\u00f3n 24410",
    "addr:housenumber":"21",
    "addr:postcode":"24410",
    "addr:street":"Avda Francisco Sobrin",
    "iso:country":"ES",
    "sg:address":"Avda Francisco Sobrin, 21",
    "sg:city":"Camponaraya",
    "sg:orig_category":"Comerciantes Al Por Mayor De Vinos, Licores Y Alcoholes",
    "sg:phone":"+34 987 46 31 83",
    "sg:postcode":"24410",
    "sg:province":"Le\u00f3n",
    "wof:name":"Ovalle Rodriguez Jose Luis",
    "wof:placetype":"venue"
},
  "geometry": {"coordinates":[-6.6785559654,42.6148796082],"type":"Point"}
}