{
  "type": "Feature",
  "properties": {
    "addr:full":"Calle de Jesus De La Vera-cruz, 18 Sevilla Sevilla 41002",
    "addr:housenumber":"18",
    "addr:postcode":"41002",
    "addr:street":"Calle De Jesus De La Vera-Cruz",
    "iso:country":"ES",
    "sg:address":"Calle de Jesus De La Vera-cruz, 18",
    "sg:city":"Sevilla",
    "sg:orig_category":"Internados & Ense\u00d1anza Privada",
    "sg:phone":"+34 954 56 16 29",
    "sg:postcode":"41002",
    "sg:province":"Sevilla",
    "wof:name":"Colegio Sagrado Corazon En Sevilla Esclavas Del Divino Corazon Provincia Sur",
    "wof:placetype":"venue"
},
  "geometry": {"coordinates":[-5.9983887672,37.3941116333],"type":"Point"}
}