{
  "type": "Feature",
  "properties": {
    "iso:country":"ES",
    "sg:address":"Plaz Cebada, S/n",
    "sg:city":"Madrid",
    "sg:orig_category":"Frutas, Legumbres Frescas Y Tempranas (al Por Menor)",
    "sg:phone":"+34 913 64 50 79",
    "sg:postcode":"28005",
    "sg:province":"Madrid",
    "wof:name":"Amador Collado Alfredo",
    "wof:placetype":"venue"
},
  "geometry": {"coordinates":[-3.7096903324,40.4107780457],"type":"Point"}
}