{
  "type": "Feature",
  "properties": {
    "addr:full":"Avda Larrondo Beheko Etorbidea, S/n Elotxelerri Vizcaya 48180",
    "addr:housenumber":"s",
    "addr:postcode":"48180",
    "addr:street":"Avda Larrondo Beheko Etorbidea;/ N",
    "iso:country":"ES",
    "sg:address":"Avda Larrondo Beheko Etorbidea, S/n",
    "sg:city":"Elotxelerri",
    "sg:orig_category":"Fabricaci\u00d3n Y Comercio De M\u00c1quinas",
    "sg:phone":"+34 944 53 82 00",
    "sg:postcode":"48180",
    "sg:province":"Vizcaya",
    "sg:website":"www.hilti.es",
    "wof:name":"Hilti Espa\u00d1ola S.a.",
    "wof:placetype":"venue"
},
  "geometry": {"coordinates":[-2.932158947,43.3143386841],"type":"Point"}
}