{
  "type": "Feature",
  "properties": {
    "addr:full":"Rua Luis Seoane (pintor), 5 Lugo Lugo 27003",
    "addr:housenumber":"5",
    "addr:postcode":"27003",
    "addr:street":"Rua Luis Seoane Pintor",
    "iso:country":"ES",
    "sg:address":"Rua Luis Seoane (pintor), 5",
    "sg:city":"Lugo",
    "sg:orig_category":"Tintes (fabricaci\u00d3n, Al Por Mayor)",
    "sg:phone":"+34 982 24 42 77",
    "sg:postcode":"27003",
    "sg:province":"Lugo",
    "wof:name":"Lopez Leiras Maria Eulalia",
    "wof:placetype":"venue"
},
  "geometry": {"coordinates":[-7.5603508949,43.016872406],"type":"Point"}
}