{
  "type": "Feature",
  "properties": {
    "iso:country":"ES",
    "sg:address":"C/ Monserrate Guilabert Valero, 29",
    "sg:city":"Elche",
    "sg:orig_category":"Caf\u00c9s, Bares, Cervecer\u00cdas",
    "sg:phone":"+34 965 44 83 90",
    "sg:postcode":"03205",
    "sg:province":"Alicante",
    "wof:name":"Rada Business S.l.",
    "wof:placetype":"venue"
},
  "geometry": {"coordinates":[-0.7114419937,38.2682304382],"type":"Point"}
}