{
  "type": "Feature",
  "properties": {
    "iso:country":"ES",
    "sg:address":"Carrer de Enric Prat De La Riba, 44",
    "sg:city":"Premia Mar",
    "sg:orig_category":"Audiovisuales (producci\u00d3n, Edici\u00d3n, Realizaci\u00d3n)",
    "sg:phone":"+34 937 52 26 41",
    "sg:postcode":"08330",
    "sg:province":"Barcelona",
    "wof:name":"Jimenez Duran Jose",
    "wof:placetype":"venue"
},
  "geometry": {"coordinates":[2.3571839333,41.4891090393],"type":"Point"}
}