{
  "type": "Feature",
  "properties": {
    "iso:country":"ES",
    "sg:address":"Carrer de Pere Iv, 108",
    "sg:city":"Barcelona",
    "sg:orig_category":"Asesor\u00cda Sobre Comunicaci\u00d3n De Empresas",
    "sg:phone":"+34 933 09 45 14",
    "sg:postcode":"08005",
    "sg:province":"Barcelona",
    "wof:name":"Bamemi S.l.",
    "wof:placetype":"venue"
},
  "geometry": {"coordinates":[2.1952250004,41.3994865417],"type":"Point"}
}