{
  "type": "Feature",
  "properties": {
    "addr:full":"Calle de Concepcion De La Oliva, 24 Madrid Madrid 28021",
    "addr:housenumber":"24",
    "addr:postcode":"madrid;28021",
    "addr:street":"Calle De Concepcion De La Oliva",
    "iso:country":"ES",
    "sg:address":"Calle de Concepcion De La Oliva, 24",
    "sg:city":"Madrid",
    "sg:orig_category":"Peluqueros: De Se\u00d1oras",
    "sg:phone":"+34 917 95 20 27",
    "sg:postcode":"28021",
    "sg:province":"Madrid",
    "wof:name":"Alonso Fraile Maria Cruz",
    "wof:placetype":"venue"
},
  "geometry": {"coordinates":[-3.6813602448,40.3540458679],"type":"Point"}
}