{
  "type": "Feature",
  "properties": {
    "addr:full":"Cami Era (de L'), 37 Torredembarra Tarragona 43830",
    "addr:housenumber":"37",
    "addr:postcode":"43830",
    "addr:street":"Era;L '",
    "iso:country":"ES",
    "sg:address":"Cami Era (de L'), 37",
    "sg:city":"Torredembarra",
    "sg:orig_category":"Reposter\u00cdas",
    "sg:phone":"+34 977 64 27 43",
    "sg:postcode":"43830",
    "sg:province":"Tarragona",
    "wof:name":"Cubells Vi\u00f1es Maria Dolors",
    "wof:placetype":"venue"
},
  "geometry": {"coordinates":[1.3986439705,41.1463356018],"type":"Point"}
}