{
  "type": "Feature",
  "properties": {
    "iso:country":"ES",
    "sg:address":"Hondartza Kalea, 6",
    "sg:city":"Deba",
    "sg:orig_category":"Agencias Y Asesores De Publicidad",
    "sg:phone":"+34 943 60 80 06",
    "sg:postcode":"20820",
    "sg:province":"Guip\u00f9zcoa",
    "wof:name":"Kaioa Asp S.l.",
    "wof:placetype":"venue"
},
  "geometry": {"coordinates":[-2.3508679867,43.2976074219],"type":"Point"}
}