{
  "type": "Feature",
  "properties": {
    "iso:country":"ES",
    "sg:address":"Cra. Panadella, Km. 0004,7",
    "sg:city":"S. Guim Freixenet",
    "sg:orig_category":"Art\u00cdculos De Madera (fabricaci\u00d3n Y Al Por Mayor)",
    "sg:phone":"+34 973 55 63 84",
    "sg:postcode":"25270",
    "sg:province":"Lleida",
    "wof:name":"Xule Mobiliario 2004 S.l.",
    "wof:placetype":"venue"
},
  "geometry": {"coordinates":[1.5704418421,41.9208488464],"type":"Point"}
}