{
  "type": "Feature",
  "properties": {
    "iso:country":"ES",
    "sg:address":"Calle de Ambrosio Ballesteros, 1",
    "sg:city":"Torrijos",
    "sg:orig_category":"Publicidad (soportes Y Gesti\u00d3n)",
    "sg:phone":"+34 925 77 10 01",
    "sg:postcode":"45500",
    "sg:province":"Toledo",
    "wof:name":"Kapa Publicidad S.l.",
    "wof:placetype":"venue"
},
  "geometry": {"coordinates":[-4.2827296257,39.9826812744],"type":"Point"}
}