{
  "type": "Feature",
  "properties": {
    "addr:full":"Calle de Montpellier, 1 Madrid Madrid 28030",
    "addr:housenumber":"1",
    "addr:postcode":"28030",
    "addr:street":"Calle De Montpellier",
    "iso:country":"ES",
    "sg:address":"Calle de Montpellier, 1",
    "sg:city":"Madrid",
    "sg:orig_category":"Grafistas",
    "sg:phone":"+34 913 05 16 09",
    "sg:postcode":"28030",
    "sg:province":"Madrid",
    "wof:name":"Lucas Mateos David",
    "wof:placetype":"venue"
},
  "geometry": {"coordinates":[-3.6305520535,40.404964447],"type":"Point"}
}