{
  "type": "Feature",
  "properties": {
    "iso:country":"ES",
    "sg:address":"Rbla Juan Mateo Garcia, 16",
    "sg:city":"Torrevieja",
    "sg:orig_category":"Asesor\u00cda Fiscal Y Jur\u00cddica",
    "sg:phone":"+34 965 70 80 43",
    "sg:postcode":"03180",
    "sg:province":"Alicante",
    "wof:name":"Real Tax Bureau",
    "wof:placetype":"venue"
},
  "geometry": {"coordinates":[-0.6793090105,37.9769859314],"type":"Point"}
}