{
  "type": "Feature",
  "properties": {
    "iso:country":"ES",
    "sg:address":"Calle de Ganekogorta Kalea, 2",
    "sg:city":"Zamudio",
    "sg:orig_category":"Suministros Para Carrocer\u00cdas",
    "sg:phone":"+34 944 06 08 10",
    "sg:postcode":"48170",
    "sg:province":"Vizcaya",
    "wof:name":"Severiano Luis Tielve Elorriaga",
    "wof:placetype":"venue"
},
  "geometry": {"coordinates":[-2.8634541035,43.2821044922],"type":"Point"}
}