{
  "type": "Feature",
  "properties": {
    "iso:country":"ES",
    "sg:address":"Avda Pasaje, 67",
    "sg:city":"Coru\u00d1a",
    "sg:orig_category":"Pescader\u00cdas (al Por Mayor)",
    "sg:phone":"+34 981 28 70 27",
    "sg:postcode":"15006",
    "sg:province":"La Coru\u00f1a",
    "wof:name":"Garcia Losada Gervasio",
    "wof:placetype":"venue"
},
  "geometry": {"coordinates":[-8.3873319626,43.3426742554],"type":"Point"}
}