{
  "type": "Feature",
  "properties": {
    "addr:full":"Calle de Quevedo, 6 Santa Cruz De Tenerife Santa Cruz De Tenerife 38005",
    "addr:housenumber":"6",
    "addr:postcode":"38005",
    "addr:street":"Calle De Quevedo",
    "iso:country":"ES",
    "sg:address":"Calle de Quevedo, 6",
    "sg:city":"Santa Cruz De Tenerife",
    "sg:orig_category":"Torrefactado De Caf\u00c9",
    "sg:phone":"+34 922 22 01 24",
    "sg:postcode":"38005",
    "sg:province":"Santa Cruz De Tenerife",
    "wof:name":"Carmelo Villa S.a.",
    "wof:placetype":"venue"
},
  "geometry": {"coordinates":[-16.2571601868,28.4573993683],"type":"Point"}
}