{
  "type": "Feature",
  "properties": {
    "addr:full":"Calle de Niebla, 16 Sevilla Sevilla 41011",
    "addr:housenumber":"16",
    "addr:postcode":"41011",
    "addr:street":"Calle De Niebla",
    "iso:country":"ES",
    "sg:address":"Calle de Niebla, 16",
    "sg:city":"Sevilla",
    "sg:orig_category":"Abogados",
    "sg:phone":"+34 954 27 77 70",
    "sg:postcode":"41011",
    "sg:province":"Sevilla",
    "wof:name":"Garcia Palomo Venancio",
    "wof:placetype":"venue"
},
  "geometry": {"coordinates":[-6.0005521774,37.3778381348],"type":"Point"}
}