{
  "type": "Feature",
  "properties": {
    "iso:country":"ES",
    "sg:address":"Calle de Don Ramon De La Cruz, 2",
    "sg:city":"Madrid",
    "sg:orig_category":"Ropa Para Se\u00d1oras (al Por Menor)",
    "sg:phone":"+34 915 75 55 76",
    "sg:postcode":"28001",
    "sg:province":"Madrid",
    "sg:website":"www.angelschlesser.com",
    "wof:name":"Angel Schlesser Madrid S.l.u.",
    "wof:placetype":"venue"
},
  "geometry": {"coordinates":[-3.6869940758,40.4292526245],"type":"Point"}
}