{
  "type": "Feature",
  "properties": {
    "addr:full":"Avda Veintiocho De Febrero, 15 Chipiona C\u00e1diz 11550",
    "addr:housenumber":"15",
    "addr:postcode":"11550",
    "addr:street":"Avda Veintiocho De Febrero",
    "iso:country":"ES",
    "sg:address":"Avda Veintiocho De Febrero, 15",
    "sg:city":"Chipiona",
    "sg:orig_category":"Peluqueros: De Se\u00d1oras",
    "sg:phone":"+34 956 37 26 75",
    "sg:postcode":"11550",
    "sg:province":"C\u00e1diz",
    "wof:name":"Del Moral Gonzalez Maria Jose",
    "wof:placetype":"venue"
},
  "geometry": {"coordinates":[-6.4297127724,36.7379188538],"type":"Point"}
}