{
  "type": "Feature",
  "properties": {
    "iso:country":"ES",
    "sg:address":"C/ Mariano Perez Vives, 53",
    "sg:city":"Elche",
    "sg:orig_category":"Confecci\u00d3n De Zapatos",
    "sg:phone":"+34 965 43 03 02",
    "sg:postcode":"03205",
    "sg:province":"Alicante",
    "wof:name":"Ortega Toledo Magdalena",
    "wof:placetype":"venue"
},
  "geometry": {"coordinates":[-0.7128829956,38.2683792114],"type":"Point"}
}