{
  "type": "Feature",
  "properties": {
    "iso:country":"ES",
    "sg:address":"Calle de Montesinos (de), 3",
    "sg:city":"Aranjuez",
    "sg:orig_category":"Suministros Para Hoteles",
    "sg:phone":"+34 918 91 85 96",
    "sg:postcode":"28300",
    "sg:province":"Madrid",
    "sg:website":"www.yostin.com",
    "wof:name":"Comercial Yostin S.l",
    "wof:placetype":"venue"
},
  "geometry": {"coordinates":[-3.5985689163,40.0364761353],"type":"Point"}
}