{
  "type": "Feature",
  "properties": {
    "iso:country":"ES",
    "sg:address":"Calle de Gazteluondo, 5",
    "sg:city":"Bilbao",
    "sg:orig_category":"Ense\u00d1anza: Profesiones Art\u00cdsticas",
    "sg:phone":"+34 944 10 36 46",
    "sg:postcode":"48002",
    "sg:province":"Vizcaya",
    "wof:name":"Marta Teran S.l",
    "wof:placetype":"venue"
},
  "geometry": {"coordinates":[-2.9446909428,43.2479133606],"type":"Point"}
}