{
  "type": "Feature",
  "properties": {
    "iso:country":"ES",
    "sg:address":"Plaz Espa\u00d1a, 6",
    "sg:city":"Zaragoza",
    "sg:orig_category":"Abogados",
    "sg:phone":"+34 976 23 80 62",
    "sg:postcode":"50001",
    "sg:province":"Zaragoza",
    "sg:website":"www.fincasegea.com",
    "wof:name":"Cortina Gomez Francisco Javier",
    "wof:placetype":"venue"
},
  "geometry": {"coordinates":[-0.8808969855,41.6518516541],"type":"Point"}
}