{
  "type": "Feature",
  "properties": {
    "addr:full":"J. Maria Planas, 11 Manresa Barcelona 08242",
    "addr:housenumber":"11",
    "addr:postcode":"08242",
    "addr:street":"Planas",
    "iso:country":"ES",
    "sg:address":"J. Maria Planas, 11",
    "sg:city":"Manresa",
    "sg:orig_category":"Abogados",
    "sg:phone":"+34 938 36 20 36",
    "sg:postcode":"08242",
    "sg:province":"Barcelona",
    "wof:name":"Domenech Bartra Francisco",
    "wof:placetype":"venue"
},
  "geometry": {"coordinates":[1.8238949776,41.7253952026],"type":"Point"}
}