{
  "type": "Feature",
  "properties": {
    "iso:country":"ES",
    "sg:address":"Carrer de Vista Alegre, 1",
    "sg:city":"Casc Urba",
    "sg:orig_category":"Controles De Edificaci\u00d3n (construcci\u00d3n, Seguridad)",
    "sg:phone":"+34 935 72 90 81",
    "sg:postcode":"08188",
    "sg:province":"Barcelona",
    "wof:name":"Arcs-91 Construcciones I Serveis S.l.",
    "wof:placetype":"venue"
},
  "geometry": {"coordinates":[2.2977027893,41.5306129456],"type":"Point"}
}