{
  "type": "Feature",
  "properties": {
    "addr:full":"Carrer de Ample, 314 Terrassa Barcelona 08226",
    "addr:housenumber":"314",
    "addr:postcode":"08226",
    "addr:street":"Carrer De Ample",
    "iso:country":"ES",
    "sg:address":"Carrer de Ample, 314",
    "sg:city":"Terrassa",
    "sg:orig_category":"Ropa Para Se\u00d1oras (al Por Menor)",
    "sg:phone":"+34 937 84 04 43",
    "sg:postcode":"08226",
    "sg:province":"Barcelona",
    "wof:name":"Cabello Diaz Francisca",
    "wof:placetype":"venue"
},
  "geometry": {"coordinates":[2.0268039703,41.5742645264],"type":"Point"}
}