{
  "type": "Feature",
  "properties": {
    "addr:full":"Cmno Palomares, Km. 0002,0 Valladolid Valladolid 47011",
    "addr:postcode":"47011",
    "addr:street":"Cmno Palomares Km. 0002,0",
    "iso:country":"ES",
    "sg:address":"Cmno Palomares, Km. 0002,0",
    "sg:city":"Valladolid",
    "sg:orig_category":"Producci\u00d3n, Venta De Productos De Agricultura Biol\u00d3gica",
    "sg:phone":"+34 983 48 00 25",
    "sg:postcode":"47011",
    "sg:province":"Valladolid",
    "wof:name":"Garrido Fraile Jose",
    "wof:placetype":"venue"
},
  "geometry": {"coordinates":[-4.6942858696,41.6653938293],"type":"Point"}
}