{
  "type": "Feature",
  "properties": {
    "iso:country":"ES",
    "sg:address":"Calle de Libertad (de La), 63",
    "sg:city":"Alcobendas",
    "sg:orig_category":"Fabricaci\u00d3n, Instalaci\u00d3n De Armarios",
    "sg:phone":"+34 916 61 79 54",
    "sg:postcode":"28100",
    "sg:province":"Madrid",
    "wof:name":"Calvo Sanchez Francisco Javier",
    "wof:placetype":"venue"
},
  "geometry": {"coordinates":[-3.6361489296,40.5380973816],"type":"Point"}
}