{
  "type": "Feature",
  "properties": {
    "iso:country":"ES",
    "sg:address":"Ruel Peso (do), 2",
    "sg:city":"Santiago De Compostela",
    "sg:orig_category":"Molduras, Junquillos, Listones Y Molduras Perforadas",
    "sg:phone":"+34 981 58 59 76",
    "sg:postcode":"15702",
    "sg:province":"A Coru\u00f1a",
    "wof:name":"Tu\u00f1as Lourido Argimiro",
    "wof:placetype":"venue"
},
  "geometry": {"coordinates":[-8.5453681946,42.8771362305],"type":"Point"}
}