{
  "type": "Feature",
  "properties": {
    "addr:full":"Crtra. Cordoba-sevilla, S/n Estacion Palma Rio C\u00f3rdoba 14700",
    "addr:housenumber":"s",
    "addr:postcode":"14700",
    "addr:street":"Crtra. Cordoba-Sevilla;/ N Estacion Palma Rio Co\u0301Rdoba",
    "iso:country":"ES",
    "sg:address":"Crtra. Cordoba-sevilla, S/n",
    "sg:city":"Estacion Palma Rio",
    "sg:orig_category":"Producci\u00d3n, Distribuci\u00d3n De Gas Butano Y Propano",
    "sg:phone":"+34 957 71 60 04",
    "sg:postcode":"14700",
    "sg:province":"C\u00f3rdoba",
    "wof:name":"Repsol Ypf S.a.",
    "wof:placetype":"venue"
},
  "geometry": {"coordinates":[-5.2795991898,37.7004241943],"type":"Point"}
}