{
  "type": "Feature",
  "properties": {
    "iso:country":"ES",
    "sg:address":"Calle de Barrio Nuevo, 63",
    "sg:city":"Alcala Guadaira",
    "sg:orig_category":"Ropa De Trabajo Y Profesionales (al Por Menor)",
    "sg:phone":"+34 955 68 33 44",
    "sg:postcode":"41500",
    "sg:province":"Sevilla",
    "wof:name":"Vallejo Diaz Antonio",
    "wof:placetype":"venue"
},
  "geometry": {"coordinates":[-5.8462843895,37.3417472839],"type":"Point"}
}