{
  "type": "Feature",
  "properties": {
    "addr:full":"Calle de Cardenal Cisneros, 33 Lomo De La Herradura Las Palmas 35200",
    "addr:housenumber":"33",
    "addr:postcode":"35200",
    "addr:street":"Calle De Cardenal Cisneros;Herradura Las",
    "iso:country":"ES",
    "sg:address":"Calle de Cardenal Cisneros, 33",
    "sg:city":"Lomo De La Herradura",
    "sg:orig_category":"Asesor\u00cda Fiscal Y Jur\u00cddica",
    "sg:phone":"+34 928 68 15 75",
    "sg:postcode":"35200",
    "sg:province":"Las Palmas",
    "wof:name":"Mayor Guerra Manuel Damaso",
    "wof:placetype":"venue"
},
  "geometry": {"coordinates":[-15.4291820526,27.9960250854],"type":"Point"}
}