{
  "type": "Feature",
  "properties": {
    "iso:country":"ES",
    "sg:address":"Calle de Real, 10",
    "sg:city":"Pozoblanco",
    "sg:orig_category":"Fabricaci\u00d3n De Productos Textiles Sin Tejer",
    "sg:phone":"+34 957 13 02 17",
    "sg:postcode":"14400",
    "sg:province":"C\u00f3rdoba",
    "wof:name":"Tejidos Ulises S.l.",
    "wof:placetype":"venue"
},
  "geometry": {"coordinates":[-4.8480291367,38.3777503967],"type":"Point"}
}