{
  "type": "Feature",
  "properties": {
    "iso:country":"ES",
    "sg:address":"Calle de Nueva, 16",
    "sg:city":"Rozas De Madrid",
    "sg:orig_category":"Electricidad: Equipos Industriales, Componentes (fabricaci\u00d3n)",
    "sg:phone":"+34 916 37 12 94",
    "sg:postcode":"28231",
    "sg:province":"Madrid",
    "wof:name":"Alameda Sanchez Santiago",
    "wof:placetype":"venue"
},
  "geometry": {"coordinates":[-3.8711619377,40.493434906],"type":"Point"}
}