{
  "type": "Feature",
  "properties": {
    "addr:full":"Calle de Navas Las, 18 Malaga M\u00e1laga 29002",
    "addr:housenumber":"18",
    "addr:postcode":"29002",
    "addr:street":"Calle De Navas Las;Ma\u0301Laga",
    "iso:country":"ES",
    "sg:address":"Calle de Navas Las, 18",
    "sg:city":"Malaga",
    "sg:orig_category":"Muebles Y Accesorios Para Cocinas Y Cuartos De Ba\u00d1o (al Por Menor)",
    "sg:phone":"+34 952 36 24 53",
    "sg:postcode":"29002",
    "sg:province":"M\u00e1laga",
    "wof:name":"Mi Cocina Dise\u00f1o Y Seleccion S.l.",
    "wof:placetype":"venue"
},
  "geometry": {"coordinates":[-4.4363570213,36.7024536133],"type":"Point"}
}