{
  "type": "Feature",
  "properties": {
    "iso:country":"ES",
    "sg:address":"Rua Pizarro, 67",
    "sg:city":"Vigo",
    "sg:orig_category":"Venta, Colocaci\u00d3n De Frenos",
    "sg:phone":"+34 986 41 77 19",
    "sg:postcode":"36204",
    "sg:province":"Pontevedra",
    "wof:name":"Angel Araujo Fernandez S.l.",
    "wof:placetype":"venue"
},
  "geometry": {"coordinates":[-8.7125787735,42.231300354],"type":"Point"}
}