{
  "type": "Feature",
  "properties": {
    "iso:country":"ES",
    "sg:address":"Calle de Lutxana, 6",
    "sg:city":"Bilbao",
    "sg:orig_category":"Ense\u00d1anza, Formaci\u00d3n Profesional: Aprendizaje",
    "sg:phone":"+34 944 15 46 37",
    "sg:postcode":"48008",
    "sg:province":"Vizcaya",
    "wof:name":"Egailan S.a.",
    "wof:placetype":"venue"
},
  "geometry": {"coordinates":[-2.9307029247,43.2599983215],"type":"Point"}
}