{
  "type": "Feature",
  "properties": {
    "iso:country":"ES",
    "sg:address":"Calle de Rio Jucar, 1",
    "sg:city":"Alacant",
    "sg:classifiers":[
        {
            "category":"Personal",
            "subcategory":"Massage",
            "type":"Services"
        }
    ],
    "sg:phone":"+34 965 10 02 86",
    "sg:postcode":"03006",
    "sg:province":"Alicante",
    "sg:tags":[
        "corporal",
        "material",
        "de",
        "cuidado",
        "y",
        "est\u00c9tica"
    ],
    "wof:name":"Distribuidora Gelma Sl",
    "wof:placetype":"venue"
},
  "geometry": {"coordinates":[-0.5214390159,38.3440093994],"type":"Point"}
}