{
  "type": "Feature",
  "properties": {
    "addr:full":"Carrer de Enric Prat De La Riba, 15 Premia Mar Barcelona 08330",
    "addr:housenumber":"15",
    "addr:postcode":"08330",
    "addr:street":"Carrer De Enric Prat De La Riba",
    "iso:country":"ES",
    "sg:address":"Carrer de Enric Prat De La Riba, 15",
    "sg:city":"Premia Mar",
    "sg:orig_category":"Organismos De Reclutamiento",
    "sg:phone":"+34 937 52 52 72",
    "sg:postcode":"08330",
    "sg:province":"Barcelona",
    "wof:name":"Centre D'orientacio Professional",
    "wof:placetype":"venue"
},
  "geometry": {"coordinates":[2.3563210964,41.489151001],"type":"Point"}
}