{
  "type": "Feature",
  "properties": {
    "addr:full":"Pl Marques De Caldes De Montbui, 16 Caldes Montbui Barcelona 08140",
    "addr:housenumber":"16",
    "addr:postcode":"08140",
    "addr:street":"Pl Marques De Caldes De Montbui;Montbui Barcelona",
    "iso:country":"ES",
    "sg:address":"Pl Marques De Caldes De Montbui, 16",
    "sg:city":"Caldes Montbui",
    "sg:orig_category":"Agencias De Viajes",
    "sg:phone":"+34 938 62 62 02",
    "sg:postcode":"08140",
    "sg:province":"Barcelona",
    "wof:name":"Viajes Lord Travel S.a.",
    "wof:placetype":"venue"
},
  "geometry": {"coordinates":[2.1686599255,41.631111145],"type":"Point"}
}