{
  "type": "Feature",
  "properties": {
    "addr:full":"Plaz Maria Auxiliadora, 1 Villena Alicante 03400",
    "addr:housenumber":"1",
    "addr:postcode":"03400",
    "iso:country":"ES",
    "sg:address":"Plaz Maria Auxiliadora, 1",
    "sg:city":"Villena",
    "sg:orig_category":"Expertos Contables, Revisores De Cuentas",
    "sg:phone":"+34 965 81 72 33",
    "sg:postcode":"03400",
    "sg:province":"Alicante",
    "wof:name":"Audifiel S.l.",
    "wof:placetype":"venue"
},
  "geometry": {"coordinates":[-0.8664720058,38.6363945007],"type":"Point"}
}