{
  "type": "Feature",
  "properties": {
    "addr:full":"Avda. De Manilva, 1 Manilva M\u00e1laga 29692",
    "addr:housenumber":"1",
    "addr:postcode":"29692",
    "addr:street":"Avda. De Manilva",
    "iso:country":"ES",
    "sg:address":"Avda. De Manilva, 1",
    "sg:city":"Manilva",
    "sg:orig_category":"Ingeniero",
    "sg:phone":"+34 952 89 30 16",
    "sg:postcode":"29692",
    "sg:province":"M\u00e1laga",
    "wof:name":"Fastech S.l.",
    "wof:placetype":"venue"
},
  "geometry": {"coordinates":[-5.2275772095,36.3670539856],"type":"Point"}
}