{
  "type": "Feature",
  "properties": {
    "addr:full":"Calle de Capitan Luna, 1 Aldea Obispo C\u00e1ceres 10291",
    "addr:housenumber":"1",
    "addr:postcode":"10291",
    "addr:street":"Calle De Capitan Luna;Obispo Ca\u0301Ceres",
    "iso:country":"ES",
    "sg:address":"Calle de Capitan Luna, 1",
    "sg:city":"Aldea Obispo",
    "sg:orig_category":"Electrodom\u00c9sticos (al Por Menor)",
    "sg:phone":"+34 927 31 16 33",
    "sg:postcode":"10291",
    "sg:province":"C\u00e1ceres",
    "wof:name":"Vaquero Solis Mari Flor",
    "wof:placetype":"venue"
},
  "geometry": {"coordinates":[-5.9125809669,39.5621871948],"type":"Point"}
}