{
  "type": "Feature",
  "properties": {
    "iso:country":"ES",
    "sg:address":"Poli Casa Grande, 27",
    "sg:city":"Torrevieja",
    "sg:orig_category":"Electricidad, Electr\u00d3nica: Material Y Suministros (al Por Mayor)",
    "sg:phone":"+34 965 70 56 56",
    "sg:postcode":"03180",
    "sg:province":"Alicante",
    "wof:name":"Rentostrum S.l.",
    "wof:placetype":"venue"
},
  "geometry": {"coordinates":[-0.6536790133,38.0173606873],"type":"Point"}
}