{
  "type": "Feature",
  "properties": {
    "iso:country":"ES",
    "sg:address":"Carrer de Folgueroles, 2",
    "sg:city":"Barcelona",
    "sg:orig_category":"Doctores En Medicina",
    "sg:phone":"+34 932 12 36 08",
    "sg:postcode":"08022",
    "sg:province":"Barcelona",
    "wof:name":"Rodenas Cerda Juan",
    "wof:placetype":"venue"
},
  "geometry": {"coordinates":[2.1347808838,41.4087295532],"type":"Point"}
}