{
  "type": "Feature",
  "properties": {
    "iso:country":"ES",
    "sg:address":"Carrer de Francisco De Vitoria, 12",
    "sg:city":"Terrassa",
    "sg:orig_category":"Molduras, Junquillos, Listones Y Molduras Perforadas",
    "sg:phone":"+34 937 89 19 46",
    "sg:postcode":"08225",
    "sg:province":"Barcelona",
    "wof:name":"Bayo Castilla Purificacion",
    "wof:placetype":"venue"
},
  "geometry": {"coordinates":[2.003082037,41.569858551],"type":"Point"}
}