{
  "type": "Feature",
  "properties": {
    "addr:full":"Calle de Pardo Jimeno, 28 Alacant Alicante 03007",
    "addr:housenumber":"28",
    "addr:postcode":"03007",
    "addr:street":"Calle De Pardo Jimeno",
    "iso:country":"ES",
    "sg:address":"Calle de Pardo Jimeno, 28",
    "sg:city":"Alacant",
    "sg:orig_category":"Promotores Constructores",
    "sg:phone":"+34 965 28 64 04",
    "sg:postcode":"03007",
    "sg:province":"Alicante",
    "wof:name":"Arquitectura Y Obras Yeltes S.l.",
    "wof:placetype":"venue"
},
  "geometry": {"coordinates":[-0.4992940128,38.34167099],"type":"Point"}
}