{
  "type": "Feature",
  "properties": {
    "iso:country":"ES",
    "sg:address":"Calle de Granada, 40",
    "sg:city":"Almeria",
    "sg:orig_category":"Inmobiliaria (agencias)",
    "sg:phone":"+34 950 26 44 47",
    "sg:postcode":"04003",
    "sg:province":"Almer\u00eda",
    "wof:name":"Fernandez Fernandez Vicente",
    "wof:placetype":"venue"
},
  "geometry": {"coordinates":[-2.4618918896,36.8432922363],"type":"Point"}
}