{
  "type": "Feature",
  "properties": {
    "iso:country":"ES",
    "sg:address":"Plaz Espa\u00d1a, 25",
    "sg:city":"Herrera Duque",
    "sg:orig_category":"Farmacias",
    "sg:phone":"+34 924 65 01 83",
    "sg:postcode":"06670",
    "sg:province":"Badajoz",
    "wof:name":"Lopez Gonzalez Maria",
    "wof:placetype":"venue"
},
  "geometry": {"coordinates":[-5.049038887,39.1718788147],"type":"Point"}
}