{
  "type": "Feature",
  "properties": {
    "iso:country":"ES",
    "sg:address":"Carrer de Mila I Fontanals, 41",
    "sg:city":"S. Pere Molanta",
    "sg:classifiers":[
        {
            "category":"Professional",
            "subcategory":"Business Services",
            "type":"Services"
        }
    ],
    "sg:phone":"+34 938 92 38 59",
    "sg:postcode":"08799",
    "sg:province":"Barcelona",
    "sg:tags":[
        "control",
        "asesor\u00cda",
        "organizaci\u00d3n",
        "la",
        "de",
        "gesti\u00d3n",
        "y"
    ],
    "wof:name":"Padial Silva Maria Jose",
    "wof:placetype":"venue"
},
  "geometry": {"coordinates":[1.7406760454,41.3488311768],"type":"Point"}
}