{
  "type": "Feature",
  "properties": {
    "iso:country":"ES",
    "sg:address":"Calle de Tortola, 16",
    "sg:city":"Valladolid",
    "sg:orig_category":"Carnicer\u00cdas, Carnicer\u00cdas",
    "sg:phone":"+34 983 39 23 45",
    "sg:postcode":"47012",
    "sg:province":"Valladolid",
    "wof:name":"De La Fuente Rodriguez Raul",
    "wof:placetype":"venue"
},
  "geometry": {"coordinates":[-4.7113118172,41.6459960938],"type":"Point"}
}