{
  "type": "Feature",
  "properties": {
    "iso:country":"ES",
    "sg:address":"Carr Dalias, 4",
    "sg:city":"Campo Olivar",
    "sg:orig_category":"Psic\u00d3logos",
    "sg:phone":"+34 963 63 01 40",
    "sg:postcode":"46110",
    "sg:province":"Valencia",
    "wof:name":"Macias Berrocal Martina",
    "wof:placetype":"venue"
},
  "geometry": {"coordinates":[-0.4154840112,39.5255889893],"type":"Point"}
}