{
  "type": "Feature",
  "properties": {
    "addr:full":"Rua Axesta, 10 Muros La Coru\u00f1a 15250",
    "addr:housenumber":"10",
    "addr:postcode":"15250",
    "addr:street":"Rua Axesta;La Corun\u0303A",
    "iso:country":"ES",
    "sg:address":"Rua Axesta, 10",
    "sg:city":"Muros",
    "sg:orig_category":"Procuradores",
    "sg:phone":"+34 981 82 72 51",
    "sg:postcode":"15250",
    "sg:province":"La Coru\u00f1a",
    "wof:name":"Otero Ramos Ignacio",
    "wof:placetype":"venue"
},
  "geometry": {"coordinates":[-9.0576505661,42.7748222351],"type":"Point"}
}