{
  "type": "Feature",
  "properties": {
    "addr:full":"Calle de Rafael Lucenqui, 13 Badajoz Badajoz 06004",
    "addr:housenumber":"13",
    "addr:postcode":"06004",
    "addr:street":"Calle De Rafael Lucenqui",
    "iso:country":"ES",
    "sg:address":"Calle de Rafael Lucenqui, 13",
    "sg:city":"Badajoz",
    "sg:orig_category":"Fabricaci\u00d3n De Muebles",
    "sg:phone":"+34 924 23 83 19",
    "sg:postcode":"06004",
    "sg:province":"Badajoz",
    "wof:name":"Refolio Venera Luis",
    "wof:placetype":"venue"
},
  "geometry": {"coordinates":[-6.975320816,38.8701705933],"type":"Point"}
}