{
  "type": "Feature",
  "properties": {
    "addr:full":"San Isidro, S/n Realejos, Los Santa Cruz De Tenerife 38410",
    "addr:housenumber":"s / n",
    "addr:postcode":"38410",
    "addr:street":"San Isidro",
    "iso:country":"ES",
    "sg:address":"San Isidro, S/n",
    "sg:city":"Realejos, Los",
    "sg:orig_category":"Carnicer\u00cdas, Carnicer\u00cdas",
    "sg:phone":"+34 922 35 41 63",
    "sg:postcode":"38410",
    "sg:province":"Santa Cruz De Tenerife",
    "wof:name":"Carniceria Tomas Mesa S.l.",
    "wof:placetype":"venue"
},
  "geometry": {"coordinates":[-16.5806484222,28.3678607941],"type":"Point"}
}