{
  "type": "Feature",
  "properties": {
    "addr:full":"Av Rei Jaume I, 107 Santa Pon\u00c7a Islas Baleares 07180",
    "addr:housenumber":"107",
    "addr:postcode":"07180",
    "addr:street":"Av Rei Jaume I",
    "iso:country":"ES",
    "sg:address":"Av Rei Jaume I, 107",
    "sg:city":"Santa Pon\u00c7a",
    "sg:orig_category":"Inmobiliaria (agencias)",
    "sg:phone":"+34 971 69 48 24",
    "sg:postcode":"07180",
    "sg:province":"Islas Baleares",
    "sg:website":"www.dsi-mallorca.com",
    "wof:name":"Interdom Mallorcas.l.",
    "wof:placetype":"venue"
},
  "geometry": {"coordinates":[2.4712362289,39.5095443726],"type":"Point"}
}