{
  "type": "Feature",
  "properties": {
    "iso:country":"ES",
    "sg:address":"Avda Constitucion, 107",
    "sg:city":"Torredelcampo",
    "sg:orig_category":"Inmobiliaria (agencias)",
    "sg:phone":"+34 953 56 88 15",
    "sg:postcode":"23640",
    "sg:province":"Ja\u00e9n",
    "wof:name":"Padilla Lopez Josefa",
    "wof:placetype":"venue"
},
  "geometry": {"coordinates":[-3.897028923,37.7717285156],"type":"Point"}
}