{
  "type": "Feature",
  "properties": {
    "addr:full":"S. Duran, 2 Sta. Cristina Aro Girona 17246",
    "addr:postcode":"17246",
    "iso:country":"ES",
    "sg:address":"S. Duran, 2",
    "sg:city":"Sta. Cristina Aro",
    "sg:orig_category":"Iglesia Cat\u00d3lica",
    "sg:phone":"+34 972 83 70 38",
    "sg:postcode":"17246",
    "sg:province":"Girona",
    "wof:name":"Bisbat De Girona",
    "wof:placetype":"venue"
},
  "geometry": {"coordinates":[2.9987950325,41.8115959167],"type":"Point"}
}