{
  "type": "Feature",
  "properties": {
    "addr:full":"C/ Doctor Caro, 87 Elche Alicante 03201",
    "addr:housenumber":"87",
    "addr:postcode":"03201",
    "addr:street":"C / Doctor Caro",
    "iso:country":"ES",
    "sg:address":"C/ Doctor Caro, 87",
    "sg:city":"Elche",
    "sg:orig_category":"Electricidad Veh\u00cdculo",
    "sg:phone":"+34 965 44 11 97",
    "sg:postcode":"03201",
    "sg:province":"Alicante",
    "wof:name":"Jarque Mor Amado",
    "wof:placetype":"venue"
},
  "geometry": {"coordinates":[-0.7010009885,38.269657135],"type":"Point"}
}