{
  "type": "Feature",
  "properties": {
    "iso:country":"ES",
    "sg:address":"Calle de Trafalgar, 7",
    "sg:city":"Malaga",
    "sg:orig_category":"Estancos",
    "sg:phone":"+34 952 32 14 09",
    "sg:postcode":"29003",
    "sg:province":"M\u00e1laga",
    "wof:name":"Andreu Nu\u00f1ez Amalia",
    "wof:placetype":"venue"
},
  "geometry": {"coordinates":[-4.4435973167,36.6971321106],"type":"Point"}
}