{
  "type": "Feature",
  "properties": {
    "addr:full":"Plaz Carmen (del), 2 Fuente El Fresno Ciudad Real 13680",
    "addr:postcode":"13680",
    "iso:country":"ES",
    "sg:address":"Plaz Carmen (del), 2",
    "sg:city":"Fuente El Fresno",
    "sg:orig_category":"Pescader\u00cdas (al Por Menor)",
    "sg:phone":"+34 926 80 60 56",
    "sg:postcode":"13680",
    "sg:province":"Ciudad Real",
    "wof:name":"Arroyo Santos Modesto",
    "wof:placetype":"venue"
},
  "geometry": {"coordinates":[-3.794315815,39.2278785706],"type":"Point"}
}