{
  "type": "Feature",
  "properties": {
    "iso:country":"ES",
    "sg:address":"Avda Gran Capitan (del), 35",
    "sg:city":"Cordoba",
    "sg:orig_category":"Prot\u00c9sicos Dentales",
    "sg:phone":"+34 957 48 06 31",
    "sg:postcode":"14008",
    "sg:province":"C\u00f3rdoba",
    "wof:name":"Estudios Y Desarrollos De Protesis S.l.",
    "wof:placetype":"venue"
},
  "geometry": {"coordinates":[-4.7830491066,37.8899459839],"type":"Point"}
}