{
  "type": "Feature",
  "properties": {
    "iso:country":"ES",
    "sg:address":"Calle de Magallanes, 36",
    "sg:city":"Santander",
    "sg:orig_category":"Asociaciones Humanitarias, De Cooperaci\u00d3n, De Acci\u00d3n Social",
    "sg:phone":"+34 942 23 55 00",
    "sg:postcode":"39007",
    "sg:province":"Cantabria",
    "wof:name":"Asociacion Espa\u00f1ola Contra Cancer",
    "wof:placetype":"venue"
},
  "geometry": {"coordinates":[-3.8159482479,43.4622993469],"type":"Point"}
}