{
  "type": "Feature",
  "properties": {
    "addr:full":"Bran Cruz (la), S/n Ca\u00e7ada De Don Rodrigo Almer\u00eda 04140",
    "addr:postcode":"04140",
    "addr:street":"La S / N;Almeri\u0301A",
    "iso:country":"ES",
    "sg:address":"Bran Cruz (la), S/n",
    "sg:city":"Ca\u00e7ada De Don Rodrigo",
    "sg:orig_category":"Empresas De Electricidad En General",
    "sg:phone":"+34 950 13 04 77",
    "sg:postcode":"04140",
    "sg:province":"Almer\u00eda",
    "wof:name":"Jose Ferre Segura E Hijos S.l.",
    "wof:placetype":"venue"
},
  "geometry": {"coordinates":[-1.90099895,36.9979705811],"type":"Point"}
}