{
  "type": "Feature",
  "properties": {
    "addr:full":"Calle de I\u00d1aki Deuna, 10 Ondarroa Vizcaya 48700",
    "addr:housenumber":"10",
    "addr:postcode":"48700",
    "addr:street":"Calle De In\u0303Aki Deuna",
    "iso:country":"ES",
    "sg:address":"Calle de I\u00d1aki Deuna, 10",
    "sg:city":"Ondarroa",
    "sg:orig_category":"Molduras, Junquillos, Listones Y Molduras Perforadas",
    "sg:phone":"+34 946 83 17 29",
    "sg:postcode":"48700",
    "sg:province":"Vizcaya",
    "wof:name":"Badiola Badiola Pablo Maria",
    "wof:placetype":"venue"
},
  "geometry": {"coordinates":[-2.4240305424,43.320438385],"type":"Point"}
}