{
  "type": "Feature",
  "properties": {
    "addr:full":"Carrer de Illa De Xipre, 37 Coll De'n Rabassa Islas Baleares 07007",
    "addr:housenumber":"37",
    "addr:postcode":"07007",
    "addr:street":"Carrer De Illa De Xipre;De'N;Islas",
    "iso:country":"ES",
    "sg:address":"Carrer de Illa De Xipre, 37",
    "sg:city":"Coll De'n Rabassa",
    "sg:orig_category":"Caf\u00c9s, Bares, Cervecer\u00cdas",
    "sg:phone":"+34 971 26 74 87",
    "sg:postcode":"07007",
    "sg:province":"Islas Baleares",
    "wof:name":"Mesa Pareja Juan Antonio",
    "wof:placetype":"venue"
},
  "geometry": {"coordinates":[2.9117100239,39.6136398315],"type":"Point"}
}