{
  "type": "Feature",
  "properties": {
    "addr:full":"Calle de Padre Matias, 1 Granatula De Calatrava Ciudad Real 13360",
    "addr:housenumber":"1",
    "addr:postcode":"13360",
    "addr:street":"Calle De Padre Matias",
    "iso:country":"ES",
    "sg:address":"Calle de Padre Matias, 1",
    "sg:city":"Granatula De Calatrava",
    "sg:orig_category":"Cajas De Ahorro",
    "sg:phone":"+34 926 86 81 91",
    "sg:postcode":"13360",
    "sg:province":"Ciudad Real",
    "wof:name":"Unicaja",
    "wof:placetype":"venue"
},
  "geometry": {"coordinates":[-3.7451736927,38.7966995239],"type":"Point"}
}