{
  "type": "Feature",
  "properties": {
    "addr:full":"Carr Major, 2 Moncada Valencia 46113",
    "addr:housenumber":"2",
    "addr:postcode":"46113",
    "addr:street":"Carr Major",
    "iso:country":"ES",
    "sg:address":"Carr Major, 2",
    "sg:city":"Moncada",
    "sg:orig_category":"Cajas Para Embalar",
    "sg:phone":"+34 961 39 28 61",
    "sg:postcode":"46113",
    "sg:province":"Valencia",
    "wof:name":"Caja Campo",
    "wof:placetype":"venue"
},
  "geometry": {"coordinates":[-0.393404007,39.5454902649],"type":"Point"}
}