{
  "type": "Feature",
  "properties": {
    "addr:full":"Calle de Santo Cristo Del Consuelo (del), 8 Estacion Madrid 28250",
    "addr:housenumber":"8 estacion",
    "addr:postcode":"28250",
    "addr:street":"Calle De Santo Cristo Del Consuelo Del",
    "iso:country":"ES",
    "sg:address":"Calle de Santo Cristo Del Consuelo (del), 8",
    "sg:city":"Estacion",
    "sg:orig_category":"Abogados",
    "sg:phone":"+34 918 59 68 67",
    "sg:postcode":"28250",
    "sg:province":"Madrid",
    "wof:name":"Salcedo Espinosa Gabriel",
    "wof:placetype":"venue"
},
  "geometry": {"coordinates":[-3.9443900585,40.5741882324],"type":"Point"}
}