{
  "type": "Feature",
  "properties": {
    "iso:country":"ES",
    "sg:address":"Rua Mar Cantabrico, 94",
    "sg:city":"Lugo",
    "sg:orig_category":"Organizaciones Profesionales",
    "sg:phone":"+34 982 21 85 68",
    "sg:postcode":"27296",
    "sg:province":"Lugo",
    "wof:name":"Fernandez Penas Jose",
    "wof:placetype":"venue"
},
  "geometry": {"coordinates":[-7.6102118492,43.0405654907],"type":"Point"}
}