{
  "type": "Feature",
  "properties": {
    "iso:country":"ES",
    "sg:address":"Calle de Tonel (del), S/n",
    "sg:city":"Valdepe\u00f1as",
    "sg:orig_category":"Asociaciones Humanitarias, De Cooperaci\u00d3n, De Acci\u00d3n Social",
    "sg:phone":"+34 926 32 39 52",
    "sg:postcode":"13300",
    "sg:province":"Ciudad Real",
    "wof:name":"A.f.a Valdepe\u00d1as",
    "wof:placetype":"venue"
},
  "geometry": {"coordinates":[-3.3926455975,38.7725524902],"type":"Point"}
}