{
  "type": "Feature",
  "properties": {
    "iso:country":"ES",
    "sg:address":"Calle de Martires, 6",
    "sg:city":"Zafra",
    "sg:orig_category":"Ingeniero",
    "sg:phone":"+34 924 55 18 63",
    "sg:postcode":"06300",
    "sg:province":"Badajoz",
    "wof:name":"Guillen Rodriguez Manuel",
    "wof:placetype":"venue"
},
  "geometry": {"coordinates":[-6.4184188843,38.4186935425],"type":"Point"}
}