{
  "type": "Feature",
  "properties": {
    "addr:full":"Calle de Salvador (el), 30 Roda Albacete 02630",
    "addr:postcode":"02630",
    "addr:street":"Calle De Salvador El;Roda",
    "iso:country":"ES",
    "sg:address":"Calle de Salvador (el), 30",
    "sg:city":"Roda",
    "sg:orig_category":"Pintores",
    "sg:phone":"+34 967 44 27 56",
    "sg:postcode":"02630",
    "sg:province":"Albacete",
    "wof:name":"Luis Palacios Jose Antonio",
    "wof:placetype":"venue"
},
  "geometry": {"coordinates":[-2.1613490582,39.2045402527],"type":"Point"}
}