{
  "type": "Feature",
  "properties": {
    "addr:full":"Ctra Mig, 261 Hospitalet Llobregat Barcelona 08907",
    "addr:housenumber":"261",
    "addr:postcode":"08907",
    "addr:street":"Ctra Mig",
    "iso:country":"ES",
    "sg:address":"Ctra Mig, 261",
    "sg:city":"Hospitalet Llobregat",
    "sg:orig_category":"Importaci\u00d3n",
    "sg:phone":"+34 933 35 07 34",
    "sg:postcode":"08907",
    "sg:province":"Barcelona",
    "wof:name":"M. Camacho Internacional S.l.",
    "wof:placetype":"venue"
},
  "geometry": {"coordinates":[2.0960640907,41.350025177],"type":"Point"}
}