{
  "type": "Feature",
  "properties": {
    "iso:country":"ES",
    "sg:address":"Calle de Estacion, S/n",
    "sg:city":"Haro",
    "sg:orig_category":"Productores Recolectores, Venta Directa De Vinos",
    "sg:phone":"+34 941 30 32 33",
    "sg:postcode":"26200",
    "sg:province":"La Rioja",
    "wof:name":"Compa\u00d1ia Vinicola Del Norte De Espa\u00d1a Cune",
    "wof:placetype":"venue"
},
  "geometry": {"coordinates":[-2.8489089012,42.5831947327],"type":"Point"}
}