{
  "type": "Feature",
  "properties": {
    "addr:full":"Av Tarragona, 10 Vilafranca Penedes Barcelona 08720",
    "addr:housenumber":"10",
    "addr:postcode":"08720",
    "addr:street":"Av Tarragona;Penedes Barcelona",
    "iso:country":"ES",
    "sg:address":"Av Tarragona, 10",
    "sg:city":"Vilafranca Penedes",
    "sg:orig_category":"Abogados",
    "sg:phone":"+34 938 17 14 70",
    "sg:postcode":"08720",
    "sg:province":"Barcelona",
    "wof:name":"Ramon Sogas Jose",
    "wof:placetype":"venue"
},
  "geometry": {"coordinates":[1.6977829933,41.3440666199],"type":"Point"}
}