{
  "type": "Feature",
  "properties": {
    "addr:full":"Carretera, Km. 0001,2 Pueyo Fa\u00f1anas Huesca 22135",
    "addr:postcode":"22135",
    "addr:street":"Carretera Km. 0001,2 Pueyo Fan\u0303Anas",
    "iso:country":"ES",
    "sg:address":"Carretera, Km. 0001,2",
    "sg:city":"Pueyo Fa\u00f1anas",
    "sg:orig_category":"Agricultores, Agricultores",
    "sg:phone":"+34 974 34 01 66",
    "sg:postcode":"22135",
    "sg:province":"Huesca",
    "wof:name":"Materfra S.l.",
    "wof:placetype":"venue"
},
  "geometry": {"coordinates":[-0.2887189984,42.0775413513],"type":"Point"}
}