{
  "type": "Feature",
  "properties": {
    "addr:full":"C/ Raval Del Carme, 31 Tarrega Lleida 25300",
    "addr:housenumber":"31",
    "addr:postcode":"25300",
    "addr:street":"C / Raval Del Carme",
    "iso:country":"ES",
    "sg:address":"C/ Raval Del Carme, 31",
    "sg:city":"Tarrega",
    "sg:orig_category":"Agencias De Trabajo Temporal",
    "sg:phone":"+34 973 50 15 36",
    "sg:postcode":"25300",
    "sg:province":"Lleida",
    "sg:website":"www.adecco.es",
    "wof:name":"Adecco E.t.t. S.a.",
    "wof:placetype":"venue"
},
  "geometry": {"coordinates":[1.141317606,41.6487159729],"type":"Point"}
}