{
  "type": "Feature",
  "properties": {
    "addr:full":"Pol Ind La Barrena, S/n Tudela Navarra 31500",
    "addr:housenumber":"s",
    "addr:postcode":"31500",
    "addr:street":"Barrena;/ N",
    "iso:country":"ES",
    "sg:address":"Pol Ind La Barrena, S/n",
    "sg:city":"Tudela",
    "sg:orig_category":"Bricolaje, Herramientas (al Por Menor)",
    "sg:phone":"+34 948 40 33 90",
    "sg:postcode":"31500",
    "sg:province":"Navarra",
    "wof:name":"Bricoking S.l.",
    "wof:placetype":"venue"
},
  "geometry": {"coordinates":[-1.60295403,42.0619239807],"type":"Point"}
}