{
  "type": "Feature",
  "properties": {
    "addr:full":"Carrer de President Lluis Companys, 19 Ametlla Mar Tarragona 43860",
    "addr:housenumber":"19",
    "addr:postcode":"43860",
    "addr:street":"Carrer De President Lluis Companys",
    "iso:country":"ES",
    "sg:address":"Carrer de President Lluis Companys, 19",
    "sg:city":"Ametlla Mar",
    "sg:orig_category":"Cl\u00cdnicas Dentales",
    "sg:phone":"+34 977 49 32 85",
    "sg:postcode":"43860",
    "sg:province":"Tarragona",
    "wof:name":"Blasco Quilez Manuel",
    "wof:placetype":"venue"
},
  "geometry": {"coordinates":[0.8036779761,40.885181427],"type":"Point"}
}