{
  "type": "Feature",
  "properties": {
    "iso:country":"ES",
    "sg:address":"C/ Vicent Andres Estelles, 20",
    "sg:city":"Elche",
    "sg:orig_category":"Agencias De Viajes",
    "sg:phone":"+34 966 61 34 77",
    "sg:postcode":"03202",
    "sg:province":"Alicante",
    "wof:name":"Sevilla Carbonell Maria Asuncion",
    "wof:placetype":"venue"
},
  "geometry": {"coordinates":[-0.6800789833,38.2720565796],"type":"Point"}
}