{
  "type": "Feature",
  "properties": {
    "addr:full":"Calle de Abogado Palop Guillem, 8 Alaquas Valencia 46970",
    "addr:housenumber":"8",
    "addr:postcode":"46970",
    "addr:street":"Calle De Abogado Palop Guillem",
    "iso:country":"ES",
    "sg:address":"Calle de Abogado Palop Guillem, 8",
    "sg:city":"Alaquas",
    "sg:orig_category":"Reposter\u00cdas",
    "sg:phone":"+34 961 50 33 39",
    "sg:postcode":"46970",
    "sg:province":"Valencia",
    "wof:name":"Montesinos Valero Pascual",
    "wof:placetype":"venue"
},
  "geometry": {"coordinates":[-0.4714694023,39.4518432617],"type":"Point"}
}