{
  "type": "Feature",
  "properties": {
    "iso:country":"ES",
    "sg:address":"Carr Cendrassos, 41",
    "sg:city":"Figueres",
    "sg:orig_category":"Ense\u00d1anza: Idiomas",
    "sg:phone":"+34 972 67 61 84",
    "sg:postcode":"17600",
    "sg:province":"Girona",
    "wof:name":"Laboria  Geraldine",
    "wof:placetype":"venue"
},
  "geometry": {"coordinates":[2.9639649391,42.2719573975],"type":"Point"}
}