{
  "type": "Feature",
  "properties": {
    "iso:country":"ES",
    "sg:address":"Carrer de Riu Segre, 1",
    "sg:city":"Campclar",
    "sg:orig_category":"Electricidad: Instaladores",
    "sg:phone":"+34 977 54 09 30",
    "sg:postcode":"43006",
    "sg:province":"Tarragona",
    "wof:name":"Punt De Servei Installum S.l.",
    "wof:placetype":"venue"
},
  "geometry": {"coordinates":[1.2209249735,41.1154441833],"type":"Point"}
}