{
  "type": "Feature",
  "properties": {
    "iso:country":"ES",
    "sg:address":"Carrer de Sant Sebastia, 29",
    "sg:city":"Roses",
    "sg:orig_category":"Art\u00cdculos De Regalo (al Por Menor)",
    "sg:phone":"+34 972 15 33 49",
    "sg:postcode":"17480",
    "sg:province":"Girona",
    "wof:name":"Suarez Ruffino Rafael",
    "wof:placetype":"venue"
},
  "geometry": {"coordinates":[3.1776759624,42.2617454529],"type":"Point"}
}