{
  "type": "Feature",
  "properties": {
    "iso:country":"ES",
    "sg:address":"Calle de Ramon Y Cajal, 25",
    "sg:city":"Torre Juan Abad",
    "sg:orig_category":"Empresas De Carpinter\u00cda De Madera",
    "sg:phone":"+34 926 38 35 81",
    "sg:postcode":"13344",
    "sg:province":"Ciudad Real",
    "wof:name":"Sanchez Ruiz Jesus",
    "wof:placetype":"venue"
},
  "geometry": {"coordinates":[-3.9284191132,38.9837493896],"type":"Point"}
}