{
  "type": "Feature",
  "properties": {
    "addr:full":"Calle de Capitan Haya, 58 Madrid Madrid 28020",
    "addr:housenumber":"58",
    "addr:postcode":"madrid;28020",
    "addr:street":"Calle De Capitan Haya",
    "iso:country":"ES",
    "sg:address":"Calle de Capitan Haya, 58",
    "sg:city":"Madrid",
    "sg:orig_category":"Transportes Internacionales",
    "sg:phone":"+34 915 71 58 95",
    "sg:postcode":"28020",
    "sg:province":"Madrid",
    "wof:name":"Soluciones Logisticas Alltrans, S.a.",
    "wof:placetype":"venue"
},
  "geometry": {"coordinates":[-3.6916334629,40.4630241394],"type":"Point"}
}