{
  "type": "Feature",
  "properties": {
    "iso:country":"ES",
    "sg:address":"Avda Reyes Catolicos, 12",
    "sg:city":"Burgos",
    "sg:orig_category":"Procuradores",
    "sg:phone":"+34 947 27 43 12",
    "sg:postcode":"09004",
    "sg:province":"Burgos",
    "wof:name":"Manero De Pereda Jose Maria",
    "wof:placetype":"venue"
},
  "geometry": {"coordinates":[-3.6951990128,42.3451385498],"type":"Point"}
}