{
  "type": "Feature",
  "properties": {
    "addr:full":"Calle de Buenos Aires, 29 Palmas De Gran Canaria Las Palmas 35002",
    "addr:housenumber":"29",
    "addr:postcode":"35002",
    "addr:street":"Calle De Buenos Aires",
    "iso:country":"ES",
    "sg:address":"Calle de Buenos Aires, 29",
    "sg:city":"Palmas De Gran Canaria",
    "sg:orig_category":"Centros Empresariales",
    "sg:phone":"+34 928 43 24 50",
    "sg:postcode":"35002",
    "sg:province":"Las Palmas",
    "wof:name":"Asociacion De Empresarios De Construccion Provincial De Las Palmas Delegacion De Lanzarote",
    "wof:placetype":"venue"
},
  "geometry": {"coordinates":[-15.4192085266,28.1074180603],"type":"Point"}
}