{
  "type": "Feature",
  "properties": {
    "addr:full":"Calle de Antonio De Leyva, 82 Madrid Madrid 28019",
    "addr:housenumber":"82",
    "addr:postcode":"madrid;28019",
    "addr:street":"Calle De Antonio De Leyva",
    "iso:country":"ES",
    "sg:address":"Calle de Antonio De Leyva, 82",
    "sg:city":"Madrid",
    "sg:orig_category":"Bares, Piano",
    "sg:phone":"+34 915 69 55 06",
    "sg:postcode":"28019",
    "sg:province":"Madrid",
    "wof:name":"Bombon 97 S.l.",
    "wof:placetype":"venue"
},
  "geometry": {"coordinates":[-3.7164850235,40.3889465332],"type":"Point"}
}