{
  "type": "Feature",
  "properties": {
    "iso:country":"ES",
    "sg:address":"Calle de Alfonso Xii, 46",
    "sg:city":"Madrid",
    "sg:orig_category":"Inversiones",
    "sg:phone":"+34 914 20 27 61",
    "sg:postcode":"28014",
    "sg:province":"Madrid",
    "wof:name":"Industrias Y Finanzas S. A.",
    "wof:placetype":"venue"
},
  "geometry": {"coordinates":[-3.6889262199,40.4126052856],"type":"Point"}
}