{
  "type": "Feature",
  "properties": {
    "addr:full":"Calle de Concilio (del), 15 Alcobendas Madrid 28100",
    "addr:postcode":"28100",
    "addr:street":"Calle De Concilio Del;Alcobendas",
    "iso:country":"ES",
    "sg:address":"Calle de Concilio (del), 15",
    "sg:city":"Alcobendas",
    "sg:orig_category":"Supermercados Y Hipermercados",
    "sg:phone":"+34 916 54 31 71",
    "sg:postcode":"28100",
    "sg:province":"Madrid",
    "wof:name":"Panmin  Qi",
    "wof:placetype":"venue"
},
  "geometry": {"coordinates":[-3.6374249458,40.5436477661],"type":"Point"}
}