{
  "type": "Feature",
  "properties": {
    "addr:full":"Carrer de Bellavista, 9 Argentona Barcelona 08310",
    "addr:housenumber":"9",
    "addr:postcode":"08310",
    "addr:street":"Carrer De Bellavista",
    "iso:country":"ES",
    "sg:address":"Carrer de Bellavista, 9",
    "sg:city":"Argentona",
    "sg:orig_category":"Asilos De Ancianos. Centros Privados",
    "sg:phone":"+34 937 56 05 89",
    "sg:postcode":"08310",
    "sg:province":"Barcelona",
    "wof:name":"Laia Arquera S.l. Residencial Bonavista",
    "wof:placetype":"venue"
},
  "geometry": {"coordinates":[2.3989500999,41.5511436462],"type":"Point"}
}