{
  "type": "Feature",
  "properties": {
    "iso:country":"ES",
    "sg:address":"Calle de General Lacy, 58",
    "sg:city":"Madrid",
    "sg:orig_category":"Pintura Y Barniz (al Por Menor)",
    "sg:phone":"+34 915 27 50 04",
    "sg:postcode":"28045",
    "sg:province":"Madrid",
    "wof:name":"Borreguero Martinez Felix",
    "wof:placetype":"venue"
},
  "geometry": {"coordinates":[-3.6912200451,40.4000320435],"type":"Point"}
}