{
  "type": "Feature",
  "properties": {
    "addr:full":"Avda Marconi, 9 Cadiz C\u00e1diz 11010",
    "addr:housenumber":"9",
    "addr:postcode":"11010",
    "addr:street":"Avda Marconi",
    "iso:country":"ES",
    "sg:address":"Avda Marconi, 9",
    "sg:city":"Cadiz",
    "sg:orig_category":"Internados & Ense\u00d1anza Privada",
    "sg:phone":"+34 956 27 73 00",
    "sg:postcode":"11010",
    "sg:province":"C\u00e1diz",
    "wof:name":"Colegio Amor De Dios Congregacion H H Del Amor De Dios Provincia Del Oeste De Espa\u00d1a",
    "wof:placetype":"venue"
},
  "geometry": {"coordinates":[-6.2743139267,36.5081062317],"type":"Point"}
}