{
  "type": "Feature",
  "properties": {
    "addr:full":"Calle de Amor De Dios, 4 Madrid Madrid 28014",
    "addr:housenumber":"4",
    "addr:postcode":"28014",
    "addr:street":"Calle De Amor De Dios",
    "iso:country":"ES",
    "sg:address":"Calle de Amor De Dios, 4",
    "sg:city":"Madrid",
    "sg:orig_category":"Pe\u00d1as Y Asociaciones Varias",
    "sg:phone":"+34 913 60 17 80",
    "sg:postcode":"28014",
    "sg:province":"Madrid",
    "wof:name":"Asociacion De Cocineros Y Reposteros De Madrid",
    "wof:placetype":"venue"
},
  "geometry": {"coordinates":[-3.6983232498,40.4130821228],"type":"Point"}
}