{
  "type": "Feature",
  "properties": {
    "iso:country":"ES",
    "sg:address":"La Carolina-p I Ca\u00f1ada Fuente, 6",
    "sg:city":"Martos",
    "sg:orig_category":"Maquinaria Para Industrias Diversas",
    "sg:phone":"+34 953 70 25 01",
    "sg:postcode":"23600",
    "sg:province":"Ja\u00e9n",
    "wof:name":"Interclima Tucitana S.l.l.",
    "wof:placetype":"venue"
},
  "geometry": {"coordinates":[-3.971973896,37.7217330933],"type":"Point"}
}