{
  "type": "Feature",
  "properties": {
    "addr:full":"Calle de Ronda Del Salvador, 51 Plasencia C\u00e1ceres 10600",
    "addr:housenumber":"51",
    "addr:postcode":"10600",
    "addr:street":"Calle De Ronda Del Salvador;Ca\u0301Ceres",
    "iso:country":"ES",
    "sg:address":"Calle de Ronda Del Salvador, 51",
    "sg:city":"Plasencia",
    "sg:orig_category":"Farmacias",
    "sg:phone":"+34 927 41 11 97",
    "sg:postcode":"10600",
    "sg:province":"C\u00e1ceres",
    "wof:name":"Manzano Sanchez-oca\u00f1a Maria Asuncion",
    "wof:placetype":"venue"
},
  "geometry": {"coordinates":[-6.0897188187,40.0317382812],"type":"Point"}
}