{
  "type": "Feature",
  "properties": {
    "iso:country":"ES",
    "sg:address":"Pg Joan Carles I, 19",
    "sg:city":"Eivissa",
    "sg:orig_category":"Promotores Constructores",
    "sg:phone":"+34 971 19 97 73",
    "sg:postcode":"07800",
    "sg:province":"Islas Baleares",
    "sg:website":"www.conceptibiza.com",
    "wof:name":"Ibiza Magic Compis S.l.",
    "wof:placetype":"venue"
},
  "geometry": {"coordinates":[1.447726965,38.9138946533],"type":"Point"}
}