{
  "type": "Feature",
  "properties": {
    "addr:full":"Ptda Coves, 13 Benidorm Alicante 03500",
    "addr:housenumber":"13",
    "addr:postcode":"03500",
    "addr:street":"Ptda Coves",
    "iso:country":"ES",
    "sg:address":"Ptda Coves, 13",
    "sg:city":"Benidorm",
    "sg:orig_category":"Agencias De Viajes",
    "sg:phone":"+34 966 80 74 73",
    "sg:postcode":"03500",
    "sg:province":"Alicante",
    "wof:name":"Jumbo Tours Espa\u00f1a S.a.u.",
    "wof:placetype":"venue"
},
  "geometry": {"coordinates":[-0.1739459932,38.5365180969],"type":"Point"}
}