{
  "type": "Feature",
  "properties": {
    "iso:country":"ES",
    "sg:address":"Carrer de Fran\u00c7a Xica, 18",
    "sg:city":"Barcelona",
    "sg:orig_category":"Suministros Para Exposiciones, Ferias, Salones",
    "sg:phone":"+34 934 41 57 86",
    "sg:postcode":"08004",
    "sg:province":"Barcelona",
    "sg:website":"www.fecomon.com",
    "wof:name":"Gonzalez Rodriguez Josefa",
    "wof:placetype":"venue"
},
  "geometry": {"coordinates":[2.1593439579,41.3723907471],"type":"Point"}
}