{
  "type": "Feature",
  "properties": {
    "addr:full":"Plaz Navarro Rodrigo, 21 Alacant Alicante 03007",
    "addr:housenumber":"21",
    "addr:postcode":"03007",
    "addr:street":"Plaz;Rodrigo",
    "iso:country":"ES",
    "sg:address":"Plaz Navarro Rodrigo, 21",
    "sg:city":"Alacant",
    "sg:orig_category":"Cajas Para Embalar",
    "sg:phone":"+34 965 12 32 90",
    "sg:postcode":"03007",
    "sg:province":"Alicante",
    "sg:website":"www.ruralcaja.es",
    "wof:name":"Caja Rural Del Mediterraneo Ruralcaja S Coop De Credito",
    "wof:placetype":"venue"
},
  "geometry": {"coordinates":[-0.4804739952,38.3440856934],"type":"Point"}
}