{
  "type": "Feature",
  "properties": {
    "iso:country":"ES",
    "sg:address":"Calle de Gerona, 6",
    "sg:city":"Gijon",
    "sg:orig_category":"Suministros Para Carrocer\u00cdas",
    "sg:phone":"+34 985 32 59 06",
    "sg:postcode":"33212",
    "sg:province":"Asturias",
    "wof:name":"Pi\u00f1era Rodriguez Luis Domingo",
    "wof:placetype":"venue"
},
  "geometry": {"coordinates":[-5.6850662231,43.5411071777],"type":"Point"}
}