{
  "type": "Feature",
  "properties": {
    "iso:country":"ES",
    "sg:address":"Calle de Juan De Austria, 31",
    "sg:city":"Madrid",
    "sg:orig_category":"Compraventa De Antig\u00dcedades",
    "sg:phone":"+34 915 94 20 17",
    "sg:postcode":"28010",
    "sg:province":"Madrid",
    "wof:name":"Alonso Fernandez Maria Victoria",
    "wof:placetype":"venue"
},
  "geometry": {"coordinates":[-3.7001011372,40.4342041016],"type":"Point"}
}