{
  "type": "Feature",
  "properties": {
    "addr:full":"Avda Cardenal Herrera Oria, 49 Santander Cantabria 39011",
    "addr:housenumber":"49",
    "addr:postcode":"39011",
    "addr:street":"Avda Cardenal Herrera Oria",
    "iso:country":"ES",
    "sg:address":"Avda Cardenal Herrera Oria, 49",
    "sg:city":"Santander",
    "sg:orig_category":"Fabrica De Cer\u00c1micas",
    "sg:phone":"+34 942 34 30 70",
    "sg:postcode":"39011",
    "sg:province":"Cantabria",
    "wof:name":"Martinez Cabrero Jose Antonio",
    "wof:placetype":"venue"
},
  "geometry": {"coordinates":[-3.862869978,43.4475975037],"type":"Point"}
}