{
  "type": "Feature",
  "properties": {
    "iso:country":"ES",
    "sg:address":"Calle de Higuera (la), 34",
    "sg:city":"Higuera",
    "sg:orig_category":"Asistencia Social",
    "sg:phone":"+34 928 66 00 65",
    "sg:postcode":"35328",
    "sg:province":"Las Palmas",
    "wof:name":"Fundacion Canaria Sociosanitaria",
    "wof:placetype":"venue"
},
  "geometry": {"coordinates":[-15.5824928284,28.0158691406],"type":"Point"}
}