{
  "type": "Feature",
  "properties": {
    "addr:full":"Calle de Postas, 17 Ciudad Real Ciudad Real 13001",
    "addr:housenumber":"17",
    "addr:postcode":"13001",
    "addr:street":"Calle De Postas",
    "iso:country":"ES",
    "sg:address":"Calle de Postas, 17",
    "sg:city":"Ciudad Real",
    "sg:orig_category":"Mercer\u00cda, Lencer\u00cda (al Por Menor)",
    "sg:phone":"+34 926 21 57 56",
    "sg:postcode":"13001",
    "sg:province":"Ciudad Real",
    "wof:name":"Murillo Sanz Matilde",
    "wof:placetype":"venue"
},
  "geometry": {"coordinates":[-3.9301447868,38.9849205017],"type":"Point"}
}