{
  "type": "Feature",
  "properties": {
    "iso:country":"ES",
    "sg:address":"Carrer de Nou, 133",
    "sg:city":"Vic",
    "sg:orig_category":"Sellos De Goma Y Met\u00c1licos",
    "sg:phone":"+34 938 86 34 42",
    "sg:postcode":"08500",
    "sg:province":"Barcelona",
    "wof:name":"Ballosada Canals Jose",
    "wof:placetype":"venue"
},
  "geometry": {"coordinates":[2.2599139214,41.9314956665],"type":"Point"}
}