{
  "type": "Feature",
  "properties": {
    "iso:country":"ES",
    "sg:address":"Calle de Cantarranas, 2",
    "sg:city":"Moron Frontera",
    "sg:orig_category":"Sociedades, Compa\u00d1\u00cdas Aseguradoras",
    "sg:phone":"+34 955 85 16 72",
    "sg:postcode":"41530",
    "sg:province":"Sevilla",
    "wof:name":"Macho Armellones Maria Jesus",
    "wof:placetype":"venue"
},
  "geometry": {"coordinates":[-5.4525117874,37.1215782166],"type":"Point"}
}