{
  "type": "Feature",
  "properties": {
    "iso:country":"ES",
    "sg:address":"Calle de Mirabel, 11",
    "sg:city":"Valladolid",
    "sg:orig_category":"Librer\u00cdas",
    "sg:phone":"+34 983 26 19 26",
    "sg:postcode":"47010",
    "sg:province":"Valladolid",
    "wof:name":"Alvarez Casado Ana Isabel",
    "wof:placetype":"venue"
},
  "geometry": {"coordinates":[-4.7242326736,41.6631889343],"type":"Point"}
}