{
  "type": "Feature",
  "properties": {
    "addr:full":"Calle de Patricios, S/n Casillas  O Ermita De Buendia Murcia 30007",
    "addr:housenumber":"s / n",
    "addr:postcode":"30007",
    "addr:street":"Calle De Patricios",
    "iso:country":"ES",
    "sg:address":"Calle de Patricios, S/n",
    "sg:city":"Casillas  O Ermita De Buendia",
    "sg:orig_category":"Ferreter\u00cda (diversos)",
    "sg:phone":"+34 968 30 29 36",
    "sg:postcode":"30007",
    "sg:province":"Murcia",
    "wof:name":"Guillen Martinez Cayetano",
    "wof:placetype":"venue"
},
  "geometry": {"coordinates":[-1.1053819656,38.0032577515],"type":"Point"}
}