{
  "type": "Feature",
  "properties": {
    "addr:full":"Calle de Gumersindo Azcarate, 2 Linares Ja\u00e9n 23700",
    "addr:housenumber":"2",
    "addr:postcode":"23700",
    "addr:street":"Calle De Gumersindo Azcarate;Jae\u0301N",
    "iso:country":"ES",
    "sg:address":"Calle de Gumersindo Azcarate, 2",
    "sg:city":"Linares",
    "sg:orig_category":"Electricidad: Instaladores",
    "sg:phone":"+34 953 69 14 11",
    "sg:postcode":"23700",
    "sg:province":"Ja\u00e9n",
    "wof:name":"Quilez Garcia Mariano",
    "wof:placetype":"venue"
},
  "geometry": {"coordinates":[-3.634360075,38.0966682434],"type":"Point"}
}