{
  "type": "Feature",
  "properties": {
    "iso:country":"ES",
    "sg:address":"Av Nord, 29",
    "sg:city":"Hospitalet Llobregat",
    "sg:orig_category":"Molduras, Junquillos, Listones Y Molduras Perforadas",
    "sg:phone":"+34 933 34 86 00",
    "sg:postcode":"08905",
    "sg:province":"Barcelona",
    "wof:name":"Rodriguez Ramirez Andres",
    "wof:placetype":"venue"
},
  "geometry": {"coordinates":[2.1125190258,41.3686904907],"type":"Point"}
}