{
  "type": "Feature",
  "properties": {
    "iso:country":"ES",
    "sg:address":"Avda Veintiocho De Febrero, 113",
    "sg:city":"Bollullos Par Condado",
    "sg:orig_category":"Quincaller\u00cda (al Por Menor)",
    "sg:phone":"+34 959 41 01 66",
    "sg:postcode":"21710",
    "sg:province":"Huelva",
    "wof:name":"Mauro Ojeda Jose Maria",
    "wof:placetype":"venue"
},
  "geometry": {"coordinates":[-6.5396051407,37.3446235657],"type":"Point"}
}