{
  "type": "Feature",
  "properties": {
    "addr:full":"Calle de Santander, 33 Zaragoza Zaragoza 50010",
    "addr:housenumber":"33",
    "addr:postcode":"50010",
    "addr:street":"Calle De Santander",
    "iso:country":"ES",
    "sg:address":"Calle de Santander, 33",
    "sg:city":"Zaragoza",
    "sg:orig_category":"Cajas De Ahorro",
    "sg:phone":"+34 976 30 64 71",
    "sg:postcode":"50010",
    "sg:province":"Zaragoza",
    "wof:name":"Caja Laboral Popular",
    "wof:placetype":"venue"
},
  "geometry": {"coordinates":[-0.8975989819,41.6491584778],"type":"Point"}
}