{
  "type": "Feature",
  "properties": {
    "iso:country":"ES",
    "sg:address":"Avda. Gral. Franco, 37",
    "sg:city":"Ortigueira",
    "sg:orig_category":"Electrodom\u00c9sticos (al Por Menor)",
    "sg:phone":"+34 981 42 21 45",
    "sg:postcode":"15330",
    "sg:province":"La Coru\u00f1a",
    "wof:name":"Pereira Lage Luis",
    "wof:placetype":"venue"
},
  "geometry": {"coordinates":[-7.8514261246,43.6837654114],"type":"Point"}
}