{
  "type": "Feature",
  "properties": {
    "addr:full":"Avda Primero De Mayo, 20 Palmas De Gran Canaria Las Palmas 35002",
    "addr:postcode":"35002",
    "addr:street":"Avda Primero De Mayo 20",
    "iso:country":"ES",
    "sg:address":"Avda Primero De Mayo, 20",
    "sg:city":"Palmas De Gran Canaria",
    "sg:orig_category":"Agencias Y Agentes Comerciales, Representantes",
    "sg:phone":"+34 928 36 13 76",
    "sg:postcode":"35002",
    "sg:province":"Las Palmas",
    "wof:name":"Garcia Morales Antonio",
    "wof:placetype":"venue"
},
  "geometry": {"coordinates":[-15.4186620712,28.1041793823],"type":"Point"}
}