{
  "type": "Feature",
  "properties": {
    "addr:full":"Carrer de Eduard Fontsere, 20 Rubi Barcelona 08191",
    "addr:housenumber":"20",
    "addr:postcode":"08191",
    "addr:street":"Carrer De Eduard Fontsere",
    "iso:country":"ES",
    "sg:address":"Carrer de Eduard Fontsere, 20",
    "sg:city":"Rubi",
    "sg:orig_category":"Embalajes",
    "sg:phone":"+34 936 97 95 02",
    "sg:postcode":"08191",
    "sg:province":"Barcelona",
    "wof:name":"Embilco 2000 S.l.",
    "wof:placetype":"venue"
},
  "geometry": {"coordinates":[2.0413119793,41.4896507263],"type":"Point"}
}