{
  "type": "Feature",
  "properties": {
    "iso:country":"ES",
    "sg:address":"Calle de Antonio Maura, 5",
    "sg:city":"Robles",
    "sg:orig_category":"Asesor\u00cda Sobre Comunicaci\u00d3n De Empresas",
    "sg:phone":"+34 918 59 36 13",
    "sg:postcode":"28250",
    "sg:province":"Madrid",
    "wof:name":"Satgep S.l.",
    "wof:placetype":"venue"
},
  "geometry": {"coordinates":[-3.9225859642,40.5864906311],"type":"Point"}
}