{
  "type": "Feature",
  "properties": {
    "addr:full":"Avda Jesus Morante Borras, 133 Valencia Valencia 46012",
    "addr:housenumber":"133",
    "addr:postcode":"46012",
    "addr:street":"Avda Jesus Morante Borras",
    "iso:country":"ES",
    "sg:address":"Avda Jesus Morante Borras, 133",
    "sg:city":"Valencia",
    "sg:orig_category":"Muebles Y Accesorios Para Cocinas Y Cuartos De Ba\u00d1o (al Por Menor)",
    "sg:phone":"+34 963 67 95 45",
    "sg:postcode":"46012",
    "sg:province":"Valencia",
    "wof:name":"Ferrer Gracia Victor",
    "wof:placetype":"venue"
},
  "geometry": {"coordinates":[-0.3436749876,39.4448509216],"type":"Point"}
}