{
  "type": "Feature",
  "properties": {
    "iso:country":"ES",
    "sg:address":"Calle de Angosto, 80",
    "sg:city":"Beas Segura",
    "sg:orig_category":"Muebles, Minoristas",
    "sg:phone":"+34 953 42 52 35",
    "sg:postcode":"23280",
    "sg:province":"Ja\u00e9n",
    "wof:name":"Martinez Gomez Manuel",
    "wof:placetype":"venue"
},
  "geometry": {"coordinates":[-2.8937513828,38.2532272339],"type":"Point"}
}