{
  "type": "Feature",
  "properties": {
    "iso:country":"ES",
    "sg:address":"Calle de Camino De Morata, 1",
    "sg:city":"Albacete",
    "sg:orig_category":"Centros Empresariales",
    "sg:phone":"+34 967 51 10 83",
    "sg:postcode":"02006",
    "sg:province":"Albacete",
    "wof:name":"Presentacionistas Parroquiales Adoradoras",
    "wof:placetype":"venue"
},
  "geometry": {"coordinates":[-1.8724024296,38.9884719849],"type":"Point"}
}