{
  "type": "Feature",
  "properties": {
    "addr:full":"Plaz Egido, 6 Trabanca Salamanca 37173",
    "addr:housenumber":"6",
    "addr:postcode":"37173",
    "addr:street":"Plaz Egido",
    "iso:country":"ES",
    "sg:address":"Plaz Egido, 6",
    "sg:city":"Trabanca",
    "sg:orig_category":"Oficinas De Turismo, Asociaciones De Iniciativa",
    "sg:phone":"+34 923 14 14 95",
    "sg:postcode":"37173",
    "sg:province":"Salamanca",
    "sg:website":"www.trabanca.com",
    "wof:name":"Ayuntamiento De Trabanca",
    "wof:placetype":"venue"
},
  "geometry": {"coordinates":[-6.3846840858,41.2329216003],"type":"Point"}
}