{
  "type": "Feature",
  "properties": {
    "iso:country":"ES",
    "sg:address":"Calle de Arana, 16",
    "sg:city":"Vitoria-gasteiz",
    "sg:orig_category":"Bazares, Art\u00cdculos De Limpieza Y De Cocina (al Por Menor)",
    "sg:phone":"+34 945 27 61 45",
    "sg:postcode":"01002",
    "sg:province":"\u00c1lava",
    "wof:name":"Ye  Jianrong",
    "wof:placetype":"venue"
},
  "geometry": {"coordinates":[-2.667388916,42.8503494263],"type":"Point"}
}