{
  "type": "Feature",
  "properties": {
    "addr:full":"Calle de General Lacy, 1 S. Roque C\u00e1diz 11360",
    "addr:housenumber":"1",
    "addr:postcode":"11360",
    "addr:street":"Calle De General Lacy;S. Roque Ca\u0301Diz",
    "iso:country":"ES",
    "sg:address":"Calle de General Lacy, 1",
    "sg:city":"S. Roque",
    "sg:orig_category":"Bancos",
    "sg:phone":"+34 956 78 00 57",
    "sg:postcode":"11360",
    "sg:province":"C\u00e1diz",
    "wof:name":"Banco Espa\u00f1ol De Credito S.a.",
    "wof:placetype":"venue"
},
  "geometry": {"coordinates":[-5.3869290352,36.2101783752],"type":"Point"}
}