{
  "type": "Feature",
  "properties": {
    "addr:full":"Av. Carlos Iii El Noble, 19 Iru\u00f1a Navarra 31002",
    "addr:housenumber":"19",
    "addr:postcode":"31002",
    "addr:street":"Av. Carlos Iii El Noble",
    "iso:country":"ES",
    "sg:address":"Av. Carlos Iii El Noble, 19",
    "sg:city":"Iru\u00f1a",
    "sg:orig_category":"Cajas De Ahorro",
    "sg:phone":"+34 948 22 88 11",
    "sg:postcode":"31002",
    "sg:province":"Navarra",
    "sg:website":"www.cajalaboral.es",
    "wof:name":"Caja Laboral Popular",
    "wof:placetype":"venue"
},
  "geometry": {"coordinates":[-1.6401599646,42.8142814636],"type":"Point"}
}