{
  "type": "Feature",
  "properties": {
    "iso:country":"ES",
    "sg:address":"Calle de Agapito Marazuela, 32",
    "sg:city":"Segovia",
    "sg:orig_category":"Promotores Constructores",
    "sg:phone":"+34 921 42 34 65",
    "sg:postcode":"40005",
    "sg:province":"Segovia",
    "wof:name":"Ramirez De Andres Martin",
    "wof:placetype":"venue"
},
  "geometry": {"coordinates":[-4.1121783257,40.937461853],"type":"Point"}
}