{
  "type": "Feature",
  "properties": {
    "iso:country":"ES",
    "sg:address":"C/ Carmelo Serrano Garcia, 4",
    "sg:city":"Elche",
    "sg:orig_category":"Plomeros",
    "sg:phone":"+34 966 67 22 60",
    "sg:postcode":"03206",
    "sg:province":"Alicante",
    "wof:name":"Plaza Moreno Angel",
    "wof:placetype":"venue"
},
  "geometry": {"coordinates":[-0.7125210166,38.2772674561],"type":"Point"}
}