{
  "type": "Feature",
  "properties": {
    "addr:full":"C/ Ponent, 45 Banyoles Girona 17820",
    "addr:housenumber":"45",
    "addr:postcode":"17820",
    "addr:street":"C / Ponent",
    "iso:country":"ES",
    "sg:address":"C/ Ponent, 45",
    "sg:city":"Banyoles",
    "sg:orig_category":"Guarder\u00cdas",
    "sg:phone":"+34 972 57 36 03",
    "sg:postcode":"17820",
    "sg:province":"Girona",
    "wof:name":"Patufets S.l. Llar De Infants",
    "wof:placetype":"venue"
},
  "geometry": {"coordinates":[2.7605319023,42.1201934814],"type":"Point"}
}