{
  "type": "Feature",
  "properties": {
    "iso:country":"ES",
    "sg:address":"Avda America, 11",
    "sg:city":"Zaragoza",
    "sg:orig_category":"Bisuteros (fabricaci\u00d3n, Al Por Mayor)",
    "sg:phone":"+34 976 27 17 91",
    "sg:postcode":"50007",
    "sg:province":"Zaragoza",
    "wof:name":"Mallor Guiu Fernando",
    "wof:placetype":"venue"
},
  "geometry": {"coordinates":[-0.8849880099,41.6332855225],"type":"Point"}
}