{
  "type": "Feature",
  "properties": {
    "addr:full":"Carrer de Santa Creu, 21 Sant Feliu Llobregat Barcelona 08980",
    "addr:housenumber":"21",
    "addr:postcode":"08980",
    "addr:street":"Carrer De Santa Creu",
    "iso:country":"ES",
    "sg:address":"Carrer de Santa Creu, 21",
    "sg:city":"Sant Feliu Llobregat",
    "sg:orig_category":"Perfumer\u00cda (al Por Menor)",
    "sg:phone":"+34 936 85 54 53",
    "sg:postcode":"08980",
    "sg:province":"Barcelona",
    "wof:name":"Garcia Lopez Purificacion",
    "wof:placetype":"venue"
},
  "geometry": {"coordinates":[2.0465068817,41.3859672546],"type":"Point"}
}