{
  "type": "Feature",
  "properties": {
    "addr:full":"San Ignacio, 10 Ola Navarra 31809",
    "addr:housenumber":"10",
    "addr:postcode":"31809",
    "addr:street":"San Ignacio;Navarra",
    "iso:country":"ES",
    "sg:address":"San Ignacio, 10",
    "sg:city":"Ola",
    "sg:orig_category":"Farmacias",
    "sg:phone":"+34 948 56 24 47",
    "sg:postcode":"31809",
    "sg:province":"Navarra",
    "wof:name":"Marquiegui Rodriguez Bego\u00f1a",
    "wof:placetype":"venue"
},
  "geometry": {"coordinates":[-2.1980309486,42.8752555847],"type":"Point"}
}