{
  "type": "Feature",
  "properties": {
    "addr:full":"Calle de Carlos Iii, 17 Villaviciosa Odon Madrid 28670",
    "addr:housenumber":"17",
    "addr:postcode":"28670",
    "addr:street":"Calle De Carlos Iii;Odon",
    "iso:country":"ES",
    "sg:address":"Calle de Carlos Iii, 17",
    "sg:city":"Villaviciosa Odon",
    "sg:orig_category":"Electrodom\u00c9sticos (fabricaci\u00d3n, Al Por Mayor)",
    "sg:phone":"+34 916 16 34 58",
    "sg:postcode":"28670",
    "sg:province":"Madrid",
    "wof:name":"Serrano Calle Mari Paz",
    "wof:placetype":"venue"
},
  "geometry": {"coordinates":[-3.9122300148,40.3575515747],"type":"Point"}
}