{
  "type": "Feature",
  "properties": {
    "addr:full":"Calle de Juan Deniz Marrero, 25 Santidad Baja Las Palmas 35400",
    "addr:housenumber":"25",
    "addr:postcode":"35400",
    "addr:street":"Calle De Juan Deniz Marrero",
    "iso:country":"ES",
    "sg:address":"Calle de Juan Deniz Marrero, 25",
    "sg:city":"Santidad Baja",
    "sg:orig_category":"Carnicer\u00cdas, Carnicer\u00cdas",
    "sg:phone":"+34 928 63 32 06",
    "sg:postcode":"35400",
    "sg:province":"Las Palmas",
    "wof:name":"Martin Rosario Lucia Del",
    "wof:placetype":"venue"
},
  "geometry": {"coordinates":[-15.4300060272,28.1248226166],"type":"Point"}
}