{
  "type": "Feature",
  "properties": {
    "iso:country":"ES",
    "sg:address":"Carr Besalu, 13",
    "sg:city":"Figueres",
    "sg:orig_category":"Ropa Para Ni\u00d1os (al Por Menor)",
    "sg:phone":"+34 972 50 21 19",
    "sg:postcode":"17600",
    "sg:province":"Girona",
    "wof:name":"Fajol Soler Maria Antonia",
    "wof:placetype":"venue"
},
  "geometry": {"coordinates":[2.9601080418,42.2669944763],"type":"Point"}
}