{
  "type": "Feature",
  "properties": {
    "addr:full":"Pase Cuellar, 11 Zaragoza Zaragoza 50007",
    "addr:housenumber":"11",
    "addr:postcode":"50007",
    "iso:country":"ES",
    "sg:address":"Pase Cuellar, 11",
    "sg:city":"Zaragoza",
    "sg:orig_category":"Inmobiliaria (agencias)",
    "sg:phone":"+34 976 25 16 28",
    "sg:postcode":"50007",
    "sg:province":"Zaragoza",
    "wof:name":"Financiera Grupo Dali S. L.",
    "wof:placetype":"venue"
},
  "geometry": {"coordinates":[-0.8848289847,41.6385536194],"type":"Point"}
}