{
  "type": "Feature",
  "properties": {
    "addr:full":"Carrer de Buscarons, 18 Barcelona Barcelona 08022",
    "addr:housenumber":"18",
    "addr:postcode":"08022",
    "addr:street":"Carrer De Buscarons",
    "iso:country":"ES",
    "sg:address":"Carrer de Buscarons, 18",
    "sg:city":"Barcelona",
    "sg:orig_category":"Asociaciones Y Clubs Deportivos",
    "sg:phone":"+34 932 11 22 66",
    "sg:postcode":"08022",
    "sg:province":"Barcelona",
    "wof:name":"Escalona Lloret Luis",
    "wof:placetype":"venue"
},
  "geometry": {"coordinates":[2.1382091045,41.4062576294],"type":"Point"}
}