{
  "type": "Feature",
  "properties": {
    "addr:full":"Calle de San Torcuato, 22 Zamora Zamora 49014",
    "addr:housenumber":"22",
    "addr:postcode":"49014",
    "addr:street":"Calle De San Torcuato",
    "iso:country":"ES",
    "sg:address":"Calle de San Torcuato, 22",
    "sg:city":"Zamora",
    "sg:orig_category":"Juguetes Y Juegos (al Por Mayor)",
    "sg:phone":"+34 980 53 57 22",
    "sg:postcode":"49014",
    "sg:province":"Zamora",
    "wof:name":"Garcia Gonzalez Maria Isabel",
    "wof:placetype":"venue"
},
  "geometry": {"coordinates":[-5.7442979813,41.5058135986],"type":"Point"}
}