{
  "type": "Feature",
  "properties": {
    "iso:country":"ES",
    "sg:address":"Avda Americas, 25",
    "sg:city":"Perillo",
    "sg:orig_category":"Asesor\u00cdas Y Estudios Financieros",
    "sg:phone":"+34 981 63 88 44",
    "sg:postcode":"15172",
    "sg:province":"La Coru\u00f1a",
    "wof:name":"J. V. Economist S.l.",
    "wof:placetype":"venue"
},
  "geometry": {"coordinates":[-8.3784446716,43.3389701843],"type":"Point"}
}