{
  "type": "Feature",
  "properties": {
    "iso:country":"ES",
    "sg:address":"Calle de Santa Lucia, 21",
    "sg:city":"Miranda Ebro",
    "sg:orig_category":"Pescader\u00cdas (al Por Menor)",
    "sg:phone":"+34 947 32 28 17",
    "sg:postcode":"09200",
    "sg:province":"Burgos",
    "wof:name":"Nieto Castro Jose",
    "wof:placetype":"venue"
},
  "geometry": {"coordinates":[-2.9502849579,42.6853866577],"type":"Point"}
}