{
  "type": "Feature",
  "properties": {
    "iso:country":"ES",
    "sg:address":"Calle de Procesiones, 7",
    "sg:city":"Gerindote",
    "sg:orig_category":"Contenedores (mercanc\u00cdas)",
    "sg:phone":"+34 925 76 12 79",
    "sg:postcode":"45518",
    "sg:province":"Toledo",
    "wof:name":"Cabrera De La Pe\u00f1a Jose",
    "wof:placetype":"venue"
},
  "geometry": {"coordinates":[-4.302022934,39.965877533],"type":"Point"}
}