{
  "type": "Feature",
  "properties": {
    "iso:country":"ES",
    "sg:address":"Calle de General Sanjurjo, 15",
    "sg:city":"Moraleja",
    "sg:orig_category":"Agencias Y Agentes Comerciales, Representantes",
    "sg:phone":"+34 927 51 56 30",
    "sg:postcode":"10840",
    "sg:province":"C\u00e1ceres",
    "wof:name":"Gutierrez Cordero Consuelo Maria",
    "wof:placetype":"venue"
},
  "geometry": {"coordinates":[-6.6614928246,40.0693016052],"type":"Point"}
}