{
  "type": "Feature",
  "properties": {
    "iso:country":"ES",
    "sg:address":"Calle de Soldados (los), 9",
    "sg:city":"Palencia",
    "sg:classifiers":[
        {
            "category":"Autos & Motor Vehicles",
            "subcategory":"Automobile Sales",
            "type":"Retail Goods"
        }
    ],
    "sg:phone":"+34 979 74 23 24",
    "sg:postcode":"34001",
    "sg:province":"Palencia",
    "sg:website":"www.aecantera.com",
    "wof:name":"Cantera Avila Angel",
    "wof:placetype":"venue"
},
  "geometry": {"coordinates":[-4.532913208,42.0128364563],"type":"Point"}
}