{
  "type": "Feature",
  "properties": {
    "addr:full":"Calle de Padron, 13 Luque C\u00f3rdoba 14880",
    "addr:housenumber":"13",
    "addr:postcode":"14880",
    "addr:street":"Calle De Padron;Co\u0301Rdoba",
    "iso:country":"ES",
    "sg:address":"Calle de Padron, 13",
    "sg:city":"Luque",
    "sg:classifiers":[
        {
            "category":"Taxi",
            "type":"Transportation"
        }
    ],
    "sg:phone":"+34 957 66 70 38",
    "sg:postcode":"14880",
    "sg:province":"C\u00f3rdoba",
    "wof:name":"Leon Castro Rafael",
    "wof:placetype":"venue"
},
  "geometry": {"coordinates":[-4.2830271721,37.5566635132],"type":"Point"}
}