{
  "type": "Feature",
  "properties": {
    "iso:country":"ES",
    "sg:address":"Carrer de Gran, 84",
    "sg:city":"Esparreguera",
    "sg:orig_category":"Droguer\u00cdas (al Por Menor)",
    "sg:phone":"+34 937 77 14 86",
    "sg:postcode":"08292",
    "sg:province":"Barcelona",
    "wof:name":"Udina Marfa Joan",
    "wof:placetype":"venue"
},
  "geometry": {"coordinates":[1.8687239885,41.5407066345],"type":"Point"}
}