{
  "type": "Feature",
  "properties": {
    "addr:full":"Ctra Niebla-bonares, Km. 0001,8 Niebla Huelva 21840",
    "addr:postcode":"21840",
    "addr:street":"Ctra Niebla-Bonares Km. 0001,8",
    "iso:country":"ES",
    "sg:address":"Ctra Niebla-bonares, Km. 0001,8",
    "sg:city":"Niebla",
    "sg:orig_category":"Producci\u00d3n De Abonos Y De Fertilizantes",
    "sg:phone":"+34 959 36 21 42",
    "sg:postcode":"21840",
    "sg:province":"Huelva",
    "sg:website":"www.gatfertiliquidos.com",
    "wof:name":"Gat Fertiliquidos S.a.",
    "wof:placetype":"venue"
},
  "geometry": {"coordinates":[-6.680627346,37.3607711792],"type":"Point"}
}