{
  "type": "Feature",
  "properties": {
    "addr:full":"Avda. Ejercito, 18 Plasencia C\u00e1ceres 10600",
    "addr:housenumber":"18",
    "addr:postcode":"10600",
    "addr:street":"Avda. Ejercito;Ca\u0301Ceres",
    "iso:country":"ES",
    "sg:address":"Avda. Ejercito, 18",
    "sg:city":"Plasencia",
    "sg:orig_category":"Ense\u00d1anza Variada",
    "sg:phone":"+34 900 50 71 13",
    "sg:postcode":"10600",
    "sg:province":"C\u00e1ceres",
    "sg:website":"www.audiolisextremadura.com",
    "wof:name":"Centro Multimedia Placentino",
    "wof:placetype":"venue"
},
  "geometry": {"coordinates":[-6.0898518562,40.0299453735],"type":"Point"}
}