{
  "type": "Feature",
  "properties": {
    "addr:full":"Calle de Herrerias, 17 Coru\u00d1a La Coru\u00f1a 15001",
    "addr:housenumber":"17",
    "addr:postcode":"15001",
    "addr:street":"Calle De Herrerias;La Corun\u0303A",
    "iso:country":"ES",
    "sg:address":"Calle de Herrerias, 17",
    "sg:city":"Coru\u00d1a",
    "sg:orig_category":"Guarder\u00cdas",
    "sg:phone":"+34 981 21 10 09",
    "sg:postcode":"15001",
    "sg:province":"La Coru\u00f1a",
    "wof:name":"Escuelas Populares Gratuitas",
    "wof:placetype":"venue"
},
  "geometry": {"coordinates":[-8.3922605515,43.3711891174],"type":"Point"}
}