{
  "type": "Feature",
  "properties": {
    "addr:full":"Calle de Vaquerias, 8 Madrid Madrid 28007",
    "addr:housenumber":"8",
    "addr:postcode":"madrid;28007",
    "addr:street":"Calle De Vaquerias",
    "iso:country":"ES",
    "sg:address":"Calle de Vaquerias, 8",
    "sg:city":"Madrid",
    "sg:orig_category":"Periodistas Profesionales",
    "sg:phone":"+34 915 04 64 72",
    "sg:postcode":"28007",
    "sg:province":"Madrid",
    "wof:name":"Ya\u00f1ez Alfageme Isabel",
    "wof:placetype":"venue"
},
  "geometry": {"coordinates":[-3.6683249474,40.4189491272],"type":"Point"}
}