{
  "type": "Feature",
  "properties": {
    "iso:country":"ES",
    "sg:address":"Calle de Barrera, 15",
    "sg:city":"Coru\u00d1a",
    "sg:orig_category":"Molduras, Junquillos, Listones Y Molduras Perforadas",
    "sg:phone":"+34 981 22 10 78",
    "sg:postcode":"15001",
    "sg:province":"La Coru\u00f1a",
    "wof:name":"Lopez Lopez Jesus",
    "wof:placetype":"venue"
},
  "geometry": {"coordinates":[-8.3995399475,43.3712921143],"type":"Point"}
}