{
  "type": "Feature",
  "properties": {
    "addr:full":"Avda Espa\u00d1a, 142 Estepona M\u00e1laga 29680",
    "addr:housenumber":"142",
    "addr:postcode":"29680",
    "addr:street":"Avda Espan\u0303A",
    "iso:country":"ES",
    "sg:address":"Avda Espa\u00d1a, 142",
    "sg:city":"Estepona",
    "sg:orig_category":"Inmobiliaria (agencias)",
    "sg:phone":"+34 952 80 08 12",
    "sg:postcode":"29680",
    "sg:province":"M\u00e1laga",
    "wof:name":"Lopez Lopez Diego Roberto",
    "wof:placetype":"venue"
},
  "geometry": {"coordinates":[-5.145483017,36.4241905212],"type":"Point"}
}