{
  "type": "Feature",
  "properties": {
    "addr:full":"Calle de Serrano, 88 Madrid Madrid 28006",
    "addr:housenumber":"88",
    "addr:postcode":"madrid;28006",
    "addr:street":"Calle De Serrano",
    "iso:country":"ES",
    "sg:address":"Calle de Serrano, 88",
    "sg:city":"Madrid",
    "sg:orig_category":"Inversiones",
    "sg:phone":"+34 914 31 25 14",
    "sg:postcode":"28006",
    "sg:province":"Madrid",
    "wof:name":"Espirito Santo Gestion S.a. S.g.i.i.c.",
    "wof:placetype":"venue"
},
  "geometry": {"coordinates":[-3.6865808964,40.4320869446],"type":"Point"}
}