{
  "type": "Feature",
  "properties": {
    "addr:full":"Calle de Doctor Martin Arevalo, 26 Madrid Madrid 28021",
    "addr:housenumber":"26",
    "addr:postcode":"madrid;28021",
    "addr:street":"Calle De Doctor Martin Arevalo",
    "iso:country":"ES",
    "sg:address":"Calle de Doctor Martin Arevalo, 26",
    "sg:city":"Madrid",
    "sg:orig_category":"Caf\u00c9s, Bares, Cervecer\u00cdas",
    "sg:phone":"+34 917 95 02 77",
    "sg:postcode":"28021",
    "sg:province":"Madrid",
    "wof:name":"Mu\u00f1oz Bodas Pilar",
    "wof:placetype":"venue"
},
  "geometry": {"coordinates":[-3.7066142559,40.3460922241],"type":"Point"}
}