{
  "type": "Feature",
  "properties": {
    "iso:country":"ES",
    "sg:address":"Calle de Sorni, 12",
    "sg:city":"Valencia",
    "sg:orig_category":"Deportes Y Ocio: Art\u00cdculos Y Ropas (al Por Menor Y Accesorios)",
    "sg:phone":"+34 963 52 18 44",
    "sg:postcode":"46004",
    "sg:province":"Valencia",
    "wof:name":"Staatsmann Legleiter Fernando",
    "wof:placetype":"venue"
},
  "geometry": {"coordinates":[-0.3691191077,39.4702453613],"type":"Point"}
}