{
  "type": "Feature",
  "properties": {
    "addr:full":"Avda Vicente Aleixandre, S/n Segovia Segovia 40006",
    "addr:housenumber":"s / n",
    "addr:postcode":"40006",
    "addr:street":"Avda Vicente Aleixandre",
    "iso:country":"ES",
    "sg:address":"Avda Vicente Aleixandre, S/n",
    "sg:city":"Segovia",
    "sg:orig_category":"Panader\u00cdas, Panader\u00cdas",
    "sg:phone":"+34 921 44 14 68",
    "sg:postcode":"40006",
    "sg:province":"Segovia",
    "wof:name":"Blanco Martinez Emilio",
    "wof:placetype":"venue"
},
  "geometry": {"coordinates":[-4.0993609428,40.9286422729],"type":"Point"}
}