{
  "type": "Feature",
  "properties": {
    "iso:country":"ES",
    "sg:address":"Calle de Villa De Marin, 47",
    "sg:city":"Madrid",
    "sg:orig_category":"Electrodom\u00c9sticos (al Por Menor)",
    "sg:phone":"+34 913 14 79 83",
    "sg:postcode":"28029",
    "sg:province":"Madrid",
    "wof:name":"Cafeteria Felgar S. A.",
    "wof:placetype":"venue"
},
  "geometry": {"coordinates":[-3.697357893,40.4787788391],"type":"Point"}
}