{
  "type": "Feature",
  "properties": {
    "addr:full":"Calle de San Bartolome, 39 Almarcha Cuenca 16740",
    "addr:housenumber":"39",
    "addr:postcode":"16740",
    "addr:street":"Calle De San Bartolome",
    "iso:country":"ES",
    "sg:address":"Calle de San Bartolome, 39",
    "sg:city":"Almarcha",
    "sg:classifiers":[
        {
            "category":"Taxi",
            "type":"Transportation"
        }
    ],
    "sg:phone":"+34 969 29 10 67",
    "sg:postcode":"16740",
    "sg:province":"Cuenca",
    "wof:name":"Martinez Olmedilla Jose Antonio",
    "wof:placetype":"venue"
},
  "geometry": {"coordinates":[-2.381500721,39.6858291626],"type":"Point"}
}