{
  "type": "Feature",
  "properties": {
    "iso:country":"ES",
    "sg:address":"Calle de Mercedes, 1",
    "sg:city":"Valladolid",
    "sg:orig_category":"Limpieza Industrial",
    "sg:phone":"+34 983 23 32 31",
    "sg:postcode":"47006",
    "sg:province":"Valladolid",
    "wof:name":"Ledo S.l.",
    "wof:placetype":"venue"
},
  "geometry": {"coordinates":[-4.7394995689,41.6406402588],"type":"Point"}
}