{
  "type": "Feature",
  "properties": {
    "addr:full":"Calle de Villanueva, 8 Herrera Duque Badajoz 06670",
    "addr:housenumber":"8",
    "addr:postcode":"06670",
    "addr:street":"Calle De Villanueva",
    "iso:country":"ES",
    "sg:address":"Calle de Villanueva, 8",
    "sg:city":"Herrera Duque",
    "sg:orig_category":"Imprenta",
    "sg:phone":"+34 924 65 08 29",
    "sg:postcode":"06670",
    "sg:province":"Badajoz",
    "wof:name":"Calero Carrasco Moises",
    "wof:placetype":"venue"
},
  "geometry": {"coordinates":[-5.0512881279,39.1685638428],"type":"Point"}
}