{
  "type": "Feature",
  "properties": {
    "iso:country":"ES",
    "sg:address":"Avda Covadonga, 7",
    "sg:city":"Cangas Onis",
    "sg:orig_category":"Frutas, Legumbres Frescas Y Tempranas (al Por Menor)",
    "sg:phone":"+34 985 94 75 54",
    "sg:postcode":"33550",
    "sg:province":"Asturias",
    "wof:name":"Palomares Cuquejo Gerardo",
    "wof:placetype":"venue"
},
  "geometry": {"coordinates":[-5.1315689087,43.3506202698],"type":"Point"}
}