{
  "type": "Feature",
  "properties": {
    "iso:country":"ES",
    "sg:address":"Carrer de Casteras, 23",
    "sg:city":"Barcelona",
    "sg:orig_category":"Molduras, Junquillos, Listones Y Molduras Perforadas",
    "sg:phone":"+34 932 96 45 14",
    "sg:postcode":"08028",
    "sg:province":"Barcelona",
    "wof:name":"Ortonobes Aran Carles",
    "wof:placetype":"venue"
},
  "geometry": {"coordinates":[2.1298110485,41.3740196228],"type":"Point"}
}