{
  "type": "Feature",
  "properties": {
    "iso:country":"ES",
    "sg:address":"Carrer de Alcalde Aris, 18",
    "sg:city":"S. Just Desvern",
    "sg:orig_category":"Centros Empresariales",
    "sg:phone":"+34 934 70 02 25",
    "sg:postcode":"08960",
    "sg:province":"Barcelona",
    "wof:name":"Araico Y Asociados S.l.",
    "wof:placetype":"venue"
},
  "geometry": {"coordinates":[2.0768227577,41.3782424927],"type":"Point"}
}