{
  "type": "Feature",
  "properties": {
    "iso:country":"ES",
    "sg:address":"Calle de Edison, 16",
    "sg:city":"Getafe",
    "sg:orig_category":"Fabricaci\u00d3n De Moldes Y Modelos",
    "sg:phone":"+34 916 82 55 64",
    "sg:postcode":"28906",
    "sg:province":"Madrid",
    "wof:name":"Fabricacion De Moldes Y Accesorios S.l.",
    "wof:placetype":"venue"
},
  "geometry": {"coordinates":[-3.7005364895,40.3026390076],"type":"Point"}
}