{
  "type": "Feature",
  "properties": {
    "iso:country":"ES",
    "sg:address":"Ctra Murcia, S/n",
    "sg:city":"Baza",
    "sg:orig_category":"Albergues",
    "sg:phone":"+34 958 70 03 00",
    "sg:postcode":"18800",
    "sg:province":"Granada",
    "wof:name":"Maria Del Carmen Polaino Jimenez Y Otra C.b.",
    "wof:placetype":"venue"
},
  "geometry": {"coordinates":[-2.7643990517,37.4935264587],"type":"Point"}
}