{
  "type": "Feature",
  "properties": {
    "iso:country":"ES",
    "sg:address":"Carrer de Mallorca, 615",
    "sg:city":"Barcelona",
    "sg:orig_category":"Zonas De Acampada, Aparcamiento Para Caravanas",
    "sg:phone":"+34 933 40 17 18",
    "sg:postcode":"08026",
    "sg:province":"Barcelona",
    "sg:website":"www.agenapisos.com",
    "wof:name":"Fincas A. G. Nu\u00f1ez S. L.",
    "wof:placetype":"venue"
},
  "geometry": {"coordinates":[2.1874759197,41.4127616882],"type":"Point"}
}