{
  "type": "Feature",
  "properties": {
    "addr:full":"Avda Salamanca, 15 Santa Marta De Tormes Salamanca 37900",
    "addr:housenumber":"15",
    "addr:postcode":"37900",
    "addr:street":"Avda Salamanca",
    "iso:country":"ES",
    "sg:address":"Avda Salamanca, 15",
    "sg:city":"Santa Marta De Tormes",
    "sg:orig_category":"Peluquer\u00cdas, Peluquer\u00cda Mixta",
    "sg:phone":"+34 923 13 31 13",
    "sg:postcode":"37900",
    "sg:province":"Salamanca",
    "wof:name":"Jevamer Peluqueros S.l.",
    "wof:placetype":"venue"
},
  "geometry": {"coordinates":[-5.6482391357,40.9512214661],"type":"Point"}
}