{
  "type": "Feature",
  "properties": {
    "addr:full":"Ctra. Valencia, Km. 0011,9 Cadrete Zaragoza 50420",
    "addr:postcode":"50420",
    "addr:street":"Ctra. Valencia Km. 0011,9",
    "iso:country":"ES",
    "sg:address":"Ctra. Valencia, Km. 0011,9",
    "sg:city":"Cadrete",
    "sg:orig_category":"Negocio De Madera",
    "sg:phone":"+34 976 12 67 65",
    "sg:postcode":"50420",
    "sg:province":"Zaragoza",
    "sg:website":"www.maderasunidas.com",
    "wof:name":"Maderas Unidas S.a.",
    "wof:placetype":"venue"
},
  "geometry": {"coordinates":[-0.9601830244,41.5556411743],"type":"Point"}
}