{
  "type": "Feature",
  "properties": {
    "addr:full":"Avda Independencia, 24 Zaragoza Zaragoza 50004",
    "addr:housenumber":"24",
    "addr:postcode":"50004",
    "addr:street":"Avda Independencia",
    "iso:country":"ES",
    "sg:address":"Avda Independencia, 24",
    "sg:city":"Zaragoza",
    "sg:orig_category":"Promotores Constructores",
    "sg:phone":"+34 976 23 13 19",
    "sg:postcode":"50004",
    "sg:province":"Zaragoza",
    "wof:name":"Viii Milla Promociones Inmobiliarias S.l.",
    "wof:placetype":"venue"
},
  "geometry": {"coordinates":[-0.8832430243,41.649974823],"type":"Point"}
}