{
  "type": "Feature",
  "properties": {
    "addr:full":"Calle de Volcan Irazu, 1 Vereda Murcia 30300",
    "addr:housenumber":"1",
    "addr:postcode":"30300",
    "addr:street":"Calle De Volcan Irazu",
    "iso:country":"ES",
    "sg:address":"Calle de Volcan Irazu, 1",
    "sg:city":"Vereda",
    "sg:orig_category":"Materias Pl\u00c1sticas: Art\u00cdculos Para La Industria",
    "sg:phone":"+34 968 31 16 72",
    "sg:postcode":"30300",
    "sg:province":"Murcia",
    "wof:name":"Sanchez Pilar Perez",
    "wof:placetype":"venue"
},
  "geometry": {"coordinates":[-1.1302499771,37.9829597473],"type":"Point"}
}