{
  "type": "Feature",
  "properties": {
    "addr:full":"Av Peguera, 28 Peguera Islas Baleares 07160",
    "addr:housenumber":"28",
    "addr:postcode":"07160",
    "addr:street":"Av Peguera",
    "iso:country":"ES",
    "sg:address":"Av Peguera, 28",
    "sg:city":"Peguera",
    "sg:orig_category":"Art\u00cdculos De Regalo (al Por Menor)",
    "sg:phone":"+34 971 68 76 50",
    "sg:postcode":"07160",
    "sg:province":"Islas Baleares",
    "wof:name":"Kellermann Hoffer Roberto",
    "wof:placetype":"venue"
},
  "geometry": {"coordinates":[2.4456350803,39.5372123718],"type":"Point"}
}