{
  "type": "Feature",
  "properties": {
    "addr:full":"Pol. Ind. Erratzu, 172 Urnieta Guip\u00f9zcoa 20130",
    "addr:housenumber":"172",
    "addr:postcode":"20130",
    "addr:street":"Erratzu;Guipu\u0300Zcoa",
    "iso:country":"ES",
    "sg:address":"Pol. Ind. Erratzu, 172",
    "sg:city":"Urnieta",
    "sg:orig_category":"Jardiner\u00cdas, Vegetales, Art\u00cdculos De Jardiner\u00cda (al Por Menor)",
    "sg:phone":"+34 943 33 07 41",
    "sg:postcode":"20130",
    "sg:province":"Guip\u00f9zcoa",
    "wof:name":"Rafael Gonzalez Caso S.l.",
    "wof:placetype":"venue"
},
  "geometry": {"coordinates":[-1.992429018,43.248588562],"type":"Point"}
}