{
  "type": "Feature",
  "properties": {
    "iso:country":"ES",
    "sg:address":"Calle de Reyes Catolicos (de Los), 8",
    "sg:city":"Alcobendas",
    "sg:orig_category":"Conservas De Platos Cocinados (fabricaci\u00d3n, Al Por Mayor)",
    "sg:phone":"+34 916 61 82 10",
    "sg:postcode":"28108",
    "sg:province":"Madrid",
    "wof:name":"Varma S.a.",
    "wof:placetype":"venue"
},
  "geometry": {"coordinates":[-3.6534199715,40.5369987488],"type":"Point"}
}