{
  "type": "Feature",
  "properties": {
    "addr:full":"Carrer de Mendez Nu\u00d1ez, 25 Alcanar Tarragona 43530",
    "addr:housenumber":"25",
    "addr:postcode":"43530",
    "addr:street":"Carrer De Mendez Nun\u0303Ez",
    "iso:country":"ES",
    "sg:address":"Carrer de Mendez Nu\u00d1ez, 25",
    "sg:city":"Alcanar",
    "sg:orig_category":"Ropa De Trabajo Y Profesionales (fabricaci\u00d3n, Al Por Mayor)",
    "sg:phone":"+34 977 73 23 70",
    "sg:postcode":"43530",
    "sg:province":"Tarragona",
    "wof:name":"Confeccions Laborals Marza S.l.",
    "wof:placetype":"venue"
},
  "geometry": {"coordinates":[0.4789769948,40.5426445007],"type":"Point"}
}