{
  "type": "Feature",
  "properties": {
    "iso:country":"ES",
    "sg:address":"Calle de Jose Tomas Borrego, 16",
    "sg:city":"Conil De La Frontera",
    "sg:orig_category":"Estancos",
    "sg:phone":"+34 956 44 00 81",
    "sg:postcode":"11140",
    "sg:province":"C\u00e1diz",
    "wof:name":"Brenes Ureba Antonio",
    "wof:placetype":"venue"
},
  "geometry": {"coordinates":[-6.0895371437,36.2757148743],"type":"Point"}
}