{
  "type": "Feature",
  "properties": {
    "addr:full":"Calle de Talero, 1 Jabugo Huelva 21290",
    "addr:housenumber":"1",
    "addr:postcode":"21290",
    "addr:street":"Calle De Talero",
    "iso:country":"ES",
    "sg:address":"Calle de Talero, 1",
    "sg:city":"Jabugo",
    "sg:orig_category":"Instalaci\u00d3n De Aspiraci\u00d3n De Gases Y Humos",
    "sg:phone":"+34 959 12 14 03",
    "sg:postcode":"21290",
    "sg:province":"Huelva",
    "wof:name":"Vazquez Pulido Jose Reyes",
    "wof:placetype":"venue"
},
  "geometry": {"coordinates":[-6.738576889,37.8851966858],"type":"Point"}
}