{
  "type": "Feature",
  "properties": {
    "iso:country":"ES",
    "sg:address":"Calle de Nardiz Tar Jon, 22",
    "sg:city":"Bermeo",
    "sg:orig_category":"Pintura Y Barniz (al Por Menor)",
    "sg:phone":"+34 946 88 31 02",
    "sg:postcode":"48370",
    "sg:province":"Vizcaya",
    "wof:name":"Bilbao Bilbao Maria Teresa",
    "wof:placetype":"venue"
},
  "geometry": {"coordinates":[-2.7233490944,43.4199905396],"type":"Point"}
}