{
  "type": "Feature",
  "properties": {
    "addr:full":"Cmno Baden, 118 Purisima -barriomar Murcia 30010",
    "addr:housenumber":"118",
    "addr:postcode":"30010",
    "addr:street":"Cmno Baden",
    "iso:country":"ES",
    "sg:address":"Cmno Baden, 118",
    "sg:city":"Purisima -barriomar",
    "sg:orig_category":"Reposter\u00cdas",
    "sg:phone":"+34 968 26 38 10",
    "sg:postcode":"30010",
    "sg:province":"Murcia",
    "wof:name":"Balsalobre Rodriguez Jose",
    "wof:placetype":"venue"
},
  "geometry": {"coordinates":[-1.1507740021,37.9745788574],"type":"Point"}
}