{
  "type": "Feature",
  "properties": {
    "iso:country":"ES",
    "sg:address":"Cno Borriquillo, S/n",
    "sg:city":"Meliana",
    "sg:orig_category":"Frutas Y Legumbres Frescas (al Por Mayor)",
    "sg:phone":"+34 961 49 26 74",
    "sg:postcode":"46133",
    "sg:province":"Valencia",
    "wof:name":"Sociedad Agraria De Transformacion Frutas Pellicer R.l",
    "wof:placetype":"venue"
},
  "geometry": {"coordinates":[-0.3391410112,39.527305603],"type":"Point"}
}