{
  "type": "Feature",
  "properties": {
    "addr:full":"Carrer de Progres, 77 Hospitalet Llobregat Barcelona 08903",
    "addr:housenumber":"77",
    "addr:postcode":"08903",
    "addr:street":"Carrer De Progres",
    "iso:country":"ES",
    "sg:address":"Carrer de Progres, 77",
    "sg:city":"Hospitalet Llobregat",
    "sg:orig_category":"Art\u00cdculos De Regalo (al Por Menor)",
    "sg:phone":"+34 934 40 45 46",
    "sg:postcode":"08903",
    "sg:province":"Barcelona",
    "wof:name":"Haimin  Lin",
    "wof:placetype":"venue"
},
  "geometry": {"coordinates":[2.120882988,41.3725852966],"type":"Point"}
}