{
  "type": "Feature",
  "properties": {
    "addr:full":"Calle de Conde Aranda, 2 Zaragoza Zaragoza 50003",
    "addr:housenumber":"2",
    "addr:postcode":"50003",
    "addr:street":"Calle De Conde Aranda",
    "iso:country":"ES",
    "sg:address":"Calle de Conde Aranda, 2",
    "sg:city":"Zaragoza",
    "sg:orig_category":"Florister\u00cdas",
    "sg:phone":"+34 976 43 97 04",
    "sg:postcode":"50003",
    "sg:province":"Zaragoza",
    "wof:name":"Ferrer Lasmarias Agustin",
    "wof:placetype":"venue"
},
  "geometry": {"coordinates":[-0.8846492171,41.6542472839],"type":"Point"}
}