{
  "type": "Feature",
  "properties": {
    "iso:country":"ES",
    "sg:address":"Calle de Melilla, S/n",
    "sg:city":"Estepona",
    "sg:orig_category":"Pizzer\u00cdas",
    "sg:phone":"+34 952 80 34 91",
    "sg:postcode":"29680",
    "sg:province":"M\u00e1laga",
    "wof:name":"Martin Gavira S.l.",
    "wof:placetype":"venue"
},
  "geometry": {"coordinates":[-5.1496591568,36.4227867126],"type":"Point"}
}