{
  "type": "Feature",
  "properties": {
    "addr:full":"Avda Virgen De Fatima (de), 9 Cordoba C\u00f3rdoba 14014",
    "addr:postcode":"14014",
    "addr:street":"Avda Virgen;Co\u0301Rdoba",
    "iso:country":"ES",
    "sg:address":"Avda Virgen De Fatima (de), 9",
    "sg:city":"Cordoba",
    "sg:orig_category":"Estancos",
    "sg:phone":"+34 957 43 26 63",
    "sg:postcode":"14014",
    "sg:province":"C\u00f3rdoba",
    "wof:name":"Cisnal Del Mazo Carmen",
    "wof:placetype":"venue"
},
  "geometry": {"coordinates":[-4.7592310905,37.8983612061],"type":"Point"}
}