{
  "type": "Feature",
  "properties": {
    "iso:country":"ES",
    "sg:address":"Calle de Sevilla, 26",
    "sg:city":"Utiel",
    "sg:orig_category":"Transportes Por V\u00cdas Navegables",
    "sg:phone":"+34 962 17 18 02",
    "sg:postcode":"46300",
    "sg:province":"Valencia",
    "wof:name":"Terradez Perez Carmen",
    "wof:placetype":"venue"
},
  "geometry": {"coordinates":[-1.2034549713,39.5705947876],"type":"Point"}
}