{
  "type": "Feature",
  "properties": {
    "addr:full":"Ctra Manresa, S/n Pi S. Just Lleida 25280",
    "addr:housenumber":"s / n",
    "addr:postcode":"25280",
    "addr:street":"Ctra Manresa",
    "iso:country":"ES",
    "sg:address":"Ctra Manresa, S/n",
    "sg:city":"Pi S. Just",
    "sg:orig_category":"Restaurantes",
    "sg:phone":"+34 973 48 07 00",
    "sg:postcode":"25280",
    "sg:province":"Lleida",
    "wof:name":"Vilaseca Sole Juan",
    "wof:placetype":"venue"
},
  "geometry": {"coordinates":[1.5570679903,41.9775466919],"type":"Point"}
}