{
  "type": "Feature",
  "properties": {
    "iso:country":"ES",
    "sg:address":"Cjto. R. Pueblo Quinta, S/n",
    "sg:city":"Benalmadena-costa",
    "sg:orig_category":"Asesor\u00cda Fiscal Y Jur\u00cddica",
    "sg:phone":"+34 952 56 07 57",
    "sg:postcode":"29630",
    "sg:province":"M\u00e1laga",
    "wof:name":"Vacaciones Torrequebrada S.l.",
    "wof:placetype":"venue"
},
  "geometry": {"coordinates":[-4.521381855,36.5971374512],"type":"Point"}
}