{
  "type": "Feature",
  "properties": {
    "iso:country":"ES",
    "sg:address":"Ctra Salda\u00f1a, S/n",
    "sg:city":"Quintanadiez Vega",
    "sg:orig_category":"Venta, Instalaci\u00d3n De Quemadores",
    "sg:phone":"+34 979 89 13 99",
    "sg:postcode":"34113",
    "sg:province":"Palencia",
    "wof:name":"Hermanos Monje Mediavilla S.l.",
    "wof:placetype":"venue"
},
  "geometry": {"coordinates":[-4.7458691597,42.4825515747],"type":"Point"}
}