{
  "type": "Feature",
  "properties": {
    "addr:full":"Ctra Hospitalet, 310 Almeda Mercader Barcelona 08940",
    "addr:housenumber":"310",
    "addr:postcode":"08940",
    "addr:street":"Ctra Hospitalet;Mercader Barcelona",
    "iso:country":"ES",
    "sg:address":"Ctra Hospitalet, 310",
    "sg:city":"Almeda Mercader",
    "sg:orig_category":"Cer\u00c1micas: Material Y Suministros",
    "sg:phone":"+34 934 80 07 07",
    "sg:postcode":"08940",
    "sg:province":"Barcelona",
    "wof:name":"Vizcaino S.a.",
    "wof:placetype":"venue"
},
  "geometry": {"coordinates":[2.085726738,41.3562507629],"type":"Point"}
}