{
  "type": "Feature",
  "properties": {
    "addr:full":"Carrer de Joan Antoni Samaranch, 23 Sant Feliu Llobregat Barcelona 08980",
    "addr:housenumber":"23",
    "addr:postcode":"08980",
    "addr:street":"Carrer De Joan Antoni Samaranch",
    "iso:country":"ES",
    "sg:address":"Carrer de Joan Antoni Samaranch, 23",
    "sg:city":"Sant Feliu Llobregat",
    "sg:orig_category":"Ense\u00d1anza, Formaci\u00d3n Profesional: Aprendizaje",
    "sg:phone":"+34 936 85 35 91",
    "sg:postcode":"08980",
    "sg:province":"Barcelona",
    "wof:name":"Ajuntament De Sant Feliu De Llobregat Codi 654",
    "wof:placetype":"venue"
},
  "geometry": {"coordinates":[2.0408596992,41.3815879822],"type":"Point"}
}