{
  "type": "Feature",
  "properties": {
    "addr:full":"Carrer de Muralla (de La), 16 Torredembarra Tarragona 43830",
    "addr:housenumber":"16",
    "addr:postcode":"43830",
    "addr:street":"Carrer De Muralla De La",
    "iso:country":"ES",
    "sg:address":"Carrer de Muralla (de La), 16",
    "sg:city":"Torredembarra",
    "sg:orig_category":"Bibliotecas, Mediatecas",
    "sg:phone":"+34 977 64 31 75",
    "sg:postcode":"43830",
    "sg:province":"Tarragona",
    "wof:name":"Ajuntament De Torredembarra",
    "wof:placetype":"venue"
},
  "geometry": {"coordinates":[1.3961879015,41.144405365],"type":"Point"}
}