{
  "type": "Feature",
  "properties": {
    "addr:full":"Avda Salamanca, 5 Ciudad Rodrigo Salamanca 37500",
    "addr:housenumber":"5",
    "addr:postcode":"37500",
    "addr:street":"Avda Salamanca",
    "iso:country":"ES",
    "sg:address":"Avda Salamanca, 5",
    "sg:city":"Ciudad Rodrigo",
    "sg:orig_category":"Mensajer\u00cda Express, Portes Internacionales",
    "sg:phone":"+34 923 48 19 94",
    "sg:postcode":"37500",
    "sg:province":"Salamanca",
    "wof:name":"Ramaje Courrier S.l.",
    "wof:placetype":"venue"
},
  "geometry": {"coordinates":[-6.5285887718,40.604511261],"type":"Point"}
}