{
  "type": "Feature",
  "properties": {
    "iso:country":"ES",
    "sg:address":"Calle de Arca Real, 8",
    "sg:city":"Valladolid",
    "sg:orig_category":"Discapacitados",
    "sg:phone":"+34 983 27 82 71",
    "sg:postcode":"47013",
    "sg:province":"Valladolid",
    "wof:name":"Cfie Valladolid 1",
    "wof:placetype":"venue"
},
  "geometry": {"coordinates":[-4.7227892876,41.6390914917],"type":"Point"}
}