{
  "type": "Feature",
  "properties": {
    "iso:country":"ES",
    "sg:address":"Calle de Alfred Nobel, S/n",
    "sg:city":"Palmas De Gran Canaria",
    "sg:orig_category":"Venta, Instalaci\u00d3n De Sistemas De Alarmas Y Vigilancia",
    "sg:phone":"+34 928 42 40 48",
    "sg:postcode":"35...",
    "sg:province":"Las Palmas",
    "wof:name":"Seguridad Integral Canaria S.a.",
    "wof:placetype":"venue"
},
  "geometry": {"coordinates":[-15.452129364,28.0919303894],"type":"Point"}
}