{
  "type": "Feature",
  "properties": {
    "addr:full":"Calle de Mendez Nu\u00d1ez, 102 Santa Cruz De Tenerife Santa Cruz De Tenerife 38001",
    "addr:housenumber":"102",
    "addr:postcode":"38001",
    "addr:street":"Calle De Mendez Nun\u0303Ez",
    "iso:country":"ES",
    "sg:address":"Calle de Mendez Nu\u00d1ez, 102",
    "sg:city":"Santa Cruz De Tenerife",
    "sg:orig_category":"M\u00c9dicos: Cirug\u00cda Ortop\u00c9dica Y Traumatolog\u00cda",
    "sg:phone":"+34 922 24 91 91",
    "sg:postcode":"38001",
    "sg:province":"Santa Cruz De Tenerife",
    "wof:name":"Cozar Y Adelantado S.l.",
    "wof:placetype":"venue"
},
  "geometry": {"coordinates":[-16.2502536774,28.4741535187],"type":"Point"}
}