{
  "type": "Feature",
  "properties": {
    "iso:country":"ES",
    "sg:address":"Calle de Claudio Coello, 114",
    "sg:city":"Madrid",
    "sg:orig_category":"Promotores Constructores",
    "sg:phone":"+34 915 61 11 62",
    "sg:postcode":"28006",
    "sg:province":"Madrid",
    "wof:name":"Ica Obras Y Construcciones S.a.",
    "wof:placetype":"venue"
},
  "geometry": {"coordinates":[-3.6853473186,40.4360046387],"type":"Point"}
}