{
  "type": "Feature",
  "properties": {
    "addr:full":"Av Granvia, 8 Hospitalet Llobregat Barcelona 08902",
    "addr:housenumber":"8",
    "addr:postcode":"08902",
    "addr:street":"Av Granvia",
    "iso:country":"ES",
    "sg:address":"Av Granvia, 8",
    "sg:city":"Hospitalet Llobregat",
    "sg:orig_category":"Confecci\u00d3n De Zapatos",
    "sg:phone":"+34 933 32 54 16",
    "sg:postcode":"08902",
    "sg:province":"Barcelona",
    "sg:website":"www.dc-co.com",
    "wof:name":"The D.c. Company Spain S.a.",
    "wof:placetype":"venue"
},
  "geometry": {"coordinates":[2.1321129799,41.3626327515],"type":"Point"}
}