{
  "type": "Feature",
  "properties": {
    "addr:full":"Calle de Doctor Cornago, 24 Pozuelo De Alarcon Madrid 28223",
    "addr:housenumber":"24",
    "addr:postcode":"28223",
    "addr:street":"Calle De Doctor Cornago",
    "iso:country":"ES",
    "sg:address":"Calle de Doctor Cornago, 24",
    "sg:city":"Pozuelo De Alarcon",
    "sg:orig_category":"Estancos",
    "sg:phone":"+34 917 15 40 44",
    "sg:postcode":"28223",
    "sg:province":"Madrid",
    "wof:name":"Fernandez Rodriguez Angel",
    "wof:placetype":"venue"
},
  "geometry": {"coordinates":[-3.814009428,40.4371147156],"type":"Point"}
}