{
  "type": "Feature",
  "properties": {
    "iso:country":"ES",
    "sg:address":"Calle de Eras Del Cerrillo, 1",
    "sg:city":"Ciudad Real",
    "sg:orig_category":"Bares, Piano",
    "sg:phone":"+34 926 21 27 91",
    "sg:postcode":"13004",
    "sg:province":"Ciudad Real",
    "wof:name":"Laru Restauracion S.l.",
    "wof:placetype":"venue"
},
  "geometry": {"coordinates":[-3.9305050373,38.9779396057],"type":"Point"}
}