{
  "type": "Feature",
  "properties": {
    "addr:full":"Calle de Virgen (la), 3 Conil De La Frontera C\u00e1diz 11140",
    "addr:housenumber":"3",
    "addr:postcode":"11140",
    "addr:street":"Calle De Virgen La",
    "iso:country":"ES",
    "sg:address":"Calle de Virgen (la), 3",
    "sg:city":"Conil De La Frontera",
    "sg:orig_category":"Inmobiliaria (agencias)",
    "sg:phone":"+34 956 44 12 01",
    "sg:postcode":"11140",
    "sg:province":"C\u00e1diz",
    "wof:name":"Navarro Fernandez Jose Maria Francisco De",
    "wof:placetype":"venue"
},
  "geometry": {"coordinates":[-6.0878138542,36.2767028809],"type":"Point"}
}