{
  "type": "Feature",
  "properties": {
    "iso:country":"ES",
    "sg:address":"Calle de Santa Teresa De Jesus, 4",
    "sg:city":"Caceres",
    "sg:orig_category":"Prot\u00c9sicos Dentales",
    "sg:phone":"+34 927 22 57 95",
    "sg:postcode":"10001",
    "sg:province":"C\u00e1ceres",
    "wof:name":"Collado Protesis Dental S.l.",
    "wof:placetype":"venue"
},
  "geometry": {"coordinates":[-6.3806071281,39.4738426208],"type":"Point"}
}