{
  "type": "Feature",
  "properties": {
    "addr:full":"Calle de Marques De Montealegre, S/n Le\u00f3n Le\u00f3n 24007",
    "addr:housenumber":"s",
    "addr:postcode":"24007",
    "addr:street":"Calle De Marques De Montealegre;/ N Leo\u0301N Leo\u0301N",
    "iso:country":"ES",
    "sg:address":"Calle de Marques De Montealegre, S/n",
    "sg:city":"Le\u00f3n",
    "sg:orig_category":"Molduras, Junquillos, Listones Y Molduras Perforadas",
    "sg:phone":"+34 987 22 15 20",
    "sg:postcode":"24007",
    "sg:province":"Le\u00f3n",
    "wof:name":"Marques Garcia Maria Del Carmen",
    "wof:placetype":"venue"
},
  "geometry": {"coordinates":[-5.5640292168,42.601398468],"type":"Point"}
}