{
  "type": "Feature",
  "properties": {
    "addr:full":"Carrer de Antoni Gaudi, 4 Esplugues Llobregat Barcelona 08950",
    "addr:housenumber":"4",
    "addr:postcode":"08950",
    "addr:street":"Carrer De Antoni Gaudi",
    "iso:country":"ES",
    "sg:address":"Carrer de Antoni Gaudi, 4",
    "sg:city":"Esplugues Llobregat",
    "sg:orig_category":"Electricidad: Instaladores",
    "sg:phone":"+34 934 73 54 38",
    "sg:postcode":"08950",
    "sg:province":"Barcelona",
    "wof:name":"Cableados Y Electromontajes Catel S.a.",
    "wof:placetype":"venue"
},
  "geometry": {"coordinates":[2.0974149704,41.3708114624],"type":"Point"}
}