{
  "type": "Feature",
  "properties": {
    "iso:country":"ES",
    "sg:address":"Calle de Escuelas, 9",
    "sg:city":"Bo\u00f1ar",
    "sg:orig_category":"Cervecer\u00cdas",
    "sg:phone":"+34 987 73 52 27",
    "sg:postcode":"24850",
    "sg:province":"Le\u00f3n",
    "wof:name":"Sierra Diez Andres",
    "wof:placetype":"venue"
},
  "geometry": {"coordinates":[-5.3133702278,42.8650665283],"type":"Point"}
}