{
  "type": "Feature",
  "properties": {
    "iso:country":"ES",
    "sg:address":"Calle de Burdeos, 3",
    "sg:city":"Bahia De Javea",
    "sg:orig_category":"Contenedores (mercanc\u00cdas)",
    "sg:phone":"+34 966 46 36 57",
    "sg:postcode":"03730",
    "sg:province":"Alicante",
    "wof:name":"Hergotrans 97 S.l.",
    "wof:placetype":"venue"
},
  "geometry": {"coordinates":[0.1663361043,38.7888031006],"type":"Point"}
}