{
  "type": "Feature",
  "properties": {
    "addr:full":"Carrer de Calabria, 39 Barcelona Barcelona 08015",
    "addr:housenumber":"39",
    "addr:postcode":"08015",
    "addr:street":"Carrer De Calabria",
    "iso:country":"ES",
    "sg:address":"Carrer de Calabria, 39",
    "sg:city":"Barcelona",
    "sg:classifiers":[
        {
            "category":"Personal",
            "subcategory":"Barber",
            "type":"Services"
        }
    ],
    "sg:phone":"+34 934 23 28 79",
    "sg:postcode":"08015",
    "sg:province":"Barcelona",
    "sg:tags":[
        "caballeros",
        "de",
        "peluqueros"
    ],
    "wof:name":"Ruiz Delgado Alberto",
    "wof:placetype":"venue"
},
  "geometry": {"coordinates":[2.1584889889,41.3769645691],"type":"Point"}
}