{
  "type": "Feature",
  "properties": {
    "addr:full":"Ctra Nal Trescientos Treinta Y Dos, Km. 0189,0 Oliva Valencia 46780",
    "addr:postcode":"46780",
    "addr:street":"Ctra Nal Trescientos Treinta Y Dos Km. 0189,0",
    "iso:country":"ES",
    "sg:address":"Ctra Nal Trescientos Treinta Y Dos, Km. 0189,0",
    "sg:city":"Oliva",
    "sg:orig_category":"Almacenes Frigor\u00cdficos",
    "sg:phone":"+34 962 85 07 74",
    "sg:postcode":"46780",
    "sg:province":"Valencia",
    "wof:name":"Frigotel S. A.",
    "wof:placetype":"venue"
},
  "geometry": {"coordinates":[-0.1179220006,38.9189491272],"type":"Point"}
}