{
  "type": "Feature",
  "properties": {
    "addr:full":"Pg Vall D'hebron, 135 Barcelona Barcelona 08035",
    "addr:housenumber":"135",
    "addr:postcode":"08035",
    "addr:street":"Pg Vall D'Hebron",
    "iso:country":"ES",
    "sg:address":"Pg Vall D'hebron, 135",
    "sg:city":"Barcelona",
    "sg:orig_category":"Empresarios",
    "sg:phone":"+34 934 28 00 00",
    "sg:postcode":"08035",
    "sg:province":"Barcelona",
    "wof:name":"Chc Personalia Fundacio Privada",
    "wof:placetype":"venue"
},
  "geometry": {"coordinates":[2.1446368694,41.4302902222],"type":"Point"}
}