{
  "type": "Feature",
  "properties": {
    "addr:full":"Carr Sant Pere Claver, 39 Lleida Lleida 25005",
    "addr:housenumber":"39",
    "addr:postcode":"25005",
    "addr:street":"Carr Sant Pere Claver",
    "iso:country":"ES",
    "sg:address":"Carr Sant Pere Claver, 39",
    "sg:city":"Lleida",
    "sg:orig_category":"Carnicer\u00cdas, Carnicer\u00cdas",
    "sg:phone":"+34 973 22 26 74",
    "sg:postcode":"25005",
    "sg:province":"Lleida",
    "wof:name":"Distribucions Ramon Productes Exclusius Sl",
    "wof:placetype":"venue"
},
  "geometry": {"coordinates":[0.6403660178,41.6244468689],"type":"Point"}
}