{
  "type": "Feature",
  "properties": {
    "addr:full":"Avda Jose Antonio, 15 Pe\u00f1iscola Castell\u00f3n 12598",
    "addr:housenumber":"15",
    "addr:postcode":"12598",
    "addr:street":"Avda Jose Antonio;Castello\u0301N",
    "iso:country":"ES",
    "sg:address":"Avda Jose Antonio, 15",
    "sg:city":"Pe\u00f1iscola",
    "sg:orig_category":"Caf\u00c9s, Bares, Cervecer\u00cdas",
    "sg:phone":"+34 964 48 12 44",
    "sg:postcode":"12598",
    "sg:province":"Castell\u00f3n",
    "wof:name":"Gonzalez Roig C.b.",
    "wof:placetype":"venue"
},
  "geometry": {"coordinates":[0.4021809995,40.3597640991],"type":"Point"}
}