{
  "type": "Feature",
  "properties": {
    "addr:full":"Calle de Oceano Pacifico, 3 Alhaurin Torre M\u00e1laga 29130",
    "addr:housenumber":"3",
    "addr:postcode":"29130",
    "addr:street":"Calle De Oceano Pacifico",
    "iso:country":"ES",
    "sg:address":"Calle de Oceano Pacifico, 3",
    "sg:city":"Alhaurin Torre",
    "sg:orig_category":"Venta, Alquiler De Instrumentos Y Accesorios De M\u00dasica",
    "sg:phone":"+34 952 96 00 10",
    "sg:postcode":"29130",
    "sg:province":"M\u00e1laga",
    "sg:website":"www.chikidelectronica.com/armonia",
    "wof:name":"Luque Lopez Matilde",
    "wof:placetype":"venue"
},
  "geometry": {"coordinates":[-4.5619688034,36.6582107544],"type":"Point"}
}