{
  "type": "Feature",
  "properties": {
    "iso:country":"ES",
    "sg:address":"Calle de San Agustin, 84",
    "sg:city":"Icod De Los Vinos",
    "sg:orig_category":"Asociaciones Y Clubs Deportivos",
    "sg:phone":"+34 922 12 16 72",
    "sg:postcode":"38430",
    "sg:province":"Santa Cruz De Tenerife",
    "wof:name":"Herrera Leon Carmen Rosa",
    "wof:placetype":"venue"
},
  "geometry": {"coordinates":[-16.7151546478,28.3690872192],"type":"Point"}
}