{
  "type": "Feature",
  "properties": {
    "addr:full":"Calle de Zaforteza, S/n Vinyola Barcelona 08850",
    "addr:housenumber":"s",
    "addr:postcode":"08850",
    "addr:street":"Calle De Zaforteza;/ N Vinyola",
    "iso:country":"ES",
    "sg:address":"Calle de Zaforteza, S/n",
    "sg:city":"Vinyola",
    "sg:orig_category":"Inmobiliaria (agencias)",
    "sg:phone":"+34 936 45 17 26",
    "sg:postcode":"08850",
    "sg:province":"Barcelona",
    "wof:name":"Habit-eudo S.l.",
    "wof:placetype":"venue"
},
  "geometry": {"coordinates":[2.0012850761,41.3040237427],"type":"Point"}
}