{
  "type": "Feature",
  "properties": {
    "addr:full":"Pol Ind Olivares, S/n Jaen Ja\u00e9n 23009",
    "addr:postcode":"23009",
    "addr:street":"Olivares S / N Jaen Jae\u0301N",
    "iso:country":"ES",
    "sg:address":"Pol Ind Olivares, S/n",
    "sg:city":"Jaen",
    "sg:orig_category":"Frutas, Legumbres Frescas Y Tempranas (al Por Menor)",
    "sg:phone":"+34 953 28 02 39",
    "sg:postcode":"23009",
    "sg:province":"Ja\u00e9n",
    "wof:name":"Cruz Godino Vicente",
    "wof:placetype":"venue"
},
  "geometry": {"coordinates":[-3.7824859619,37.8041343689],"type":"Point"}
}