{
  "type": "Feature",
  "properties": {
    "iso:country":"ES",
    "sg:address":"Calle de Exposicion, S/n",
    "sg:city":"Mairena Aljarafe",
    "sg:orig_category":"Promotores Constructores",
    "sg:phone":"+34 954 18 43 66",
    "sg:postcode":"41927",
    "sg:province":"Sevilla",
    "wof:name":"Somadisa Activos Inmobiliarios S.l.",
    "wof:placetype":"venue"
},
  "geometry": {"coordinates":[-6.055685997,37.3528175354],"type":"Point"}
}