{
  "type": "Feature",
  "properties": {
    "iso:country":"ES",
    "sg:address":"Calle de Hermanas Manrique, 49",
    "sg:city":"Cardones",
    "sg:orig_category":"Asociaciones Y Clubs Deportivos",
    "sg:phone":"+34 928 62 31 18",
    "sg:postcode":"35400",
    "sg:province":"Las Palmas",
    "wof:name":"Arencibia Saavedra Bienvenido",
    "wof:placetype":"venue"
},
  "geometry": {"coordinates":[-15.511092186,28.1340141296],"type":"Point"}
}