{
  "type": "Feature",
  "properties": {
    "addr:full":"Calle de Tabla, 13 Madrigalejo C\u00e1ceres 10110",
    "addr:housenumber":"13",
    "addr:postcode":"10110",
    "addr:street":"Calle De Tabla;Ca\u0301Ceres",
    "iso:country":"ES",
    "sg:address":"Calle de Tabla, 13",
    "sg:city":"Madrigalejo",
    "sg:orig_category":"Iglesia Cat\u00d3lica",
    "sg:phone":"+34 927 35 40 58",
    "sg:postcode":"10110",
    "sg:province":"C\u00e1ceres",
    "wof:name":"Obispado De Plasencia",
    "wof:placetype":"venue"
},
  "geometry": {"coordinates":[-5.627781868,39.140422821],"type":"Point"}
}