{
  "type": "Feature",
  "properties": {
    "addr:full":"Carrer de Foneria, 36 Mataro Barcelona 08304",
    "addr:housenumber":"36",
    "addr:postcode":"08304",
    "addr:street":"Carrer De Foneria",
    "iso:country":"ES",
    "sg:address":"Carrer de Foneria, 36",
    "sg:city":"Mataro",
    "sg:orig_category":"Comercio De Piezas De Recambio Y De Accesorios De Veh\u00cdculos, Veh\u00cdculos Industriales",
    "sg:phone":"+34 937 90 70 21",
    "sg:postcode":"08304",
    "sg:province":"Barcelona",
    "wof:name":"Autocenter Racing S.l.",
    "wof:placetype":"venue"
},
  "geometry": {"coordinates":[2.4529800415,41.5538711548],"type":"Point"}
}