{
  "type": "Feature",
  "properties": {
    "iso:country":"ES",
    "sg:address":"Carr Santa Margarida, S/n",
    "sg:city":"Quart",
    "sg:orig_category":"Electricidad: Instaladores",
    "sg:phone":"+34 972 46 95 46",
    "sg:postcode":"17242",
    "sg:province":"Girona",
    "wof:name":"Domingo Boadas Josep",
    "wof:placetype":"venue"
},
  "geometry": {"coordinates":[2.8405001163,41.9427337646],"type":"Point"}
}