{
  "type": "Feature",
  "properties": {
    "addr:full":"Avda Sor Soledad Cobian, 44 Orotava Santa Cruz De Tenerife 38300",
    "addr:housenumber":"44",
    "addr:postcode":"38300",
    "addr:street":"Avda Sor Soledad Cobian",
    "iso:country":"ES",
    "sg:address":"Avda Sor Soledad Cobian, 44",
    "sg:city":"Orotava",
    "sg:orig_category":"Chapister\u00cda",
    "sg:phone":"+34 922 33 13 67",
    "sg:postcode":"38300",
    "sg:province":"Santa Cruz De Tenerife",
    "wof:name":"Cabrera Oramas Vicente",
    "wof:placetype":"venue"
},
  "geometry": {"coordinates":[-16.5185146332,28.3915233612],"type":"Point"}
}