{
  "type": "Feature",
  "properties": {
    "iso:country":"ES",
    "sg:address":"Pol. Indust. Emporda, S/n",
    "sg:city":"Vilamalla",
    "sg:orig_category":"Calefacci\u00d3n Central: Material (fabricaci\u00d3n, Al Por Mayor)",
    "sg:phone":"+34 972 52 51 50",
    "sg:postcode":"17469",
    "sg:province":"Girona",
    "sg:website":"wwwpaginasamarillas.es",
    "wof:name":"Cal Y Gas S. L.",
    "wof:placetype":"venue"
},
  "geometry": {"coordinates":[2.9704549313,42.2177505493],"type":"Point"}
}