{
  "type": "Feature",
  "properties": {
    "iso:country":"ES",
    "sg:address":"Ctra. Buzanada-aldea, 43",
    "sg:city":"Buzanada",
    "sg:orig_category":"Electricidad: Instaladores",
    "sg:phone":"+34 922 76 53 36",
    "sg:postcode":"38626",
    "sg:province":"Santa Cruz De Tenerife",
    "wof:name":"Amaro Tacoronte Ramon",
    "wof:placetype":"venue"
},
  "geometry": {"coordinates":[-16.6569862366,28.0686664581],"type":"Point"}
}