{
  "type": "Feature",
  "properties": {
    "addr:full":"Calle de Santiago Ascanio Montemayor, 2 S.gregorio Las Palmas 35200",
    "addr:housenumber":"2",
    "addr:postcode":"35200",
    "addr:street":"Calle De Santiago Ascanio Montemayor;Las Palmas",
    "iso:country":"ES",
    "sg:address":"Calle de Santiago Ascanio Montemayor, 2",
    "sg:city":"S.gregorio",
    "sg:orig_category":"Transportes Por Carretera: Lotes Completos, Mercanc\u00cdas Diversas",
    "sg:phone":"+34 928 68 53 82",
    "sg:postcode":"35200",
    "sg:province":"Las Palmas",
    "wof:name":"Dinosol Supermercados S.l.",
    "wof:placetype":"venue"
},
  "geometry": {"coordinates":[-15.4144220352,28.0029888153],"type":"Point"}
}