{
  "type": "Feature",
  "properties": {
    "iso:country":"ES",
    "sg:address":"Pg Industria, S/n",
    "sg:city":"Banyoles",
    "sg:orig_category":"Inmobiliaria (agencias)",
    "sg:phone":"+34 972 57 20 16",
    "sg:postcode":"17820",
    "sg:province":"Girona",
    "wof:name":"Inmoban 2000 S. L.",
    "wof:placetype":"venue"
},
  "geometry": {"coordinates":[2.7640099525,42.1167984009],"type":"Point"}
}