{
  "type": "Feature",
  "properties": {
    "iso:country":"ES",
    "sg:address":"Urb Nuevo Versalles, 205",
    "sg:city":"Loranca",
    "sg:orig_category":"Poller\u00cda Y Caza (al Por Menor)",
    "sg:phone":"+34 916 89 27 18",
    "sg:postcode":"28942",
    "sg:province":"Madrid",
    "wof:name":"Gomez Castellanos Antonio",
    "wof:placetype":"venue"
},
  "geometry": {"coordinates":[-3.8329060078,40.2946128845],"type":"Point"}
}