{
  "type": "Feature",
  "properties": {
    "iso:country":"ES",
    "sg:address":"Calle de Olmo, 4",
    "sg:city":"Puebla Alfinden",
    "sg:orig_category":"M\u00c1rmoles, Granitos Y Piedras Naturales",
    "sg:phone":"+34 976 10 85 13",
    "sg:postcode":"50171",
    "sg:province":"Zaragoza",
    "wof:name":"Cosentino S.a.",
    "wof:placetype":"venue"
},
  "geometry": {"coordinates":[-0.7660539746,41.6409492493],"type":"Point"}
}