{
  "type": "Feature",
  "properties": {
    "addr:full":"Calle de Jardines, 71 Menasalbas Toledo 45128",
    "addr:housenumber":"71",
    "addr:postcode":"45128",
    "addr:street":"Calle De Jardines",
    "iso:country":"ES",
    "sg:address":"Calle de Jardines, 71",
    "sg:city":"Menasalbas",
    "sg:orig_category":"Mec\u00c1nico Del Autom\u00d3vil",
    "sg:phone":"+34 925 40 70 41",
    "sg:postcode":"45128",
    "sg:province":"Toledo",
    "wof:name":"Garcia Ruiz Fernando",
    "wof:placetype":"venue"
},
  "geometry": {"coordinates":[-4.2851791382,39.6462898254],"type":"Point"}
}