{
  "type": "Feature",
  "properties": {
    "iso:country":"ES",
    "sg:address":"Ctra. Villafranqueza, Km. 0001,5",
    "sg:city":"Alacant",
    "sg:orig_category":"Muebles, Minoristas",
    "sg:phone":"+34 965 17 53 15",
    "sg:postcode":"03012",
    "sg:province":"Alicante",
    "wof:name":"Zarco Pareja S.l.",
    "wof:placetype":"venue"
},
  "geometry": {"coordinates":[-0.489151597,38.3822402954],"type":"Point"}
}