{
  "type": "Feature",
  "properties": {
    "addr:full":"Carrer de Doctor Fleming, S/n Riudoms Tarragona 43330",
    "addr:housenumber":"s / n",
    "addr:postcode":"43330",
    "addr:street":"Carrer De Doctor Fleming",
    "iso:country":"ES",
    "sg:address":"Carrer de Doctor Fleming, S/n",
    "sg:city":"Riudoms",
    "sg:orig_category":"Cooperativas Agr\u00cdcolas",
    "sg:phone":"+34 977 85 00 42",
    "sg:postcode":"43330",
    "sg:province":"Tarragona",
    "wof:name":"Cooperativa Agricola",
    "wof:placetype":"venue"
},
  "geometry": {"coordinates":[1.051224947,41.1398849487],"type":"Point"}
}