{
  "type": "Feature",
  "properties": {
    "addr:full":"Avda Ollerias (de Las), 4 Cordoba C\u00f3rdoba 14001",
    "addr:housenumber":"4",
    "addr:postcode":"14001",
    "addr:street":"Avda Ollerias De Las;Co\u0301Rdoba",
    "iso:country":"ES",
    "sg:address":"Avda Ollerias (de Las), 4",
    "sg:city":"Cordoba",
    "sg:orig_category":"Cl\u00cdnicas Dentales",
    "sg:phone":"+34 957 48 08 41",
    "sg:postcode":"14001",
    "sg:province":"C\u00f3rdoba",
    "wof:name":"Berlanga Cortes Jose Antonio",
    "wof:placetype":"venue"
},
  "geometry": {"coordinates":[-4.7761769295,37.8918151855],"type":"Point"}
}