{
  "type": "Feature",
  "properties": {
    "addr:full":"Ctra. De Motril, 111 Armilla Granada 18100",
    "addr:housenumber":"111",
    "addr:postcode":"18100",
    "addr:street":"Ctra. De Motril",
    "iso:country":"ES",
    "sg:address":"Ctra. De Motril, 111",
    "sg:city":"Armilla",
    "sg:orig_category":"Fabricaci\u00d3n De Productos Textiles Sin Tejer",
    "sg:phone":"+34 958 55 12 72",
    "sg:postcode":"18100",
    "sg:province":"Granada",
    "wof:name":"Hidalgo Cordon Julio",
    "wof:placetype":"venue"
},
  "geometry": {"coordinates":[-3.6233580112,37.1459732056],"type":"Point"}
}