{
  "type": "Feature",
  "properties": {
    "addr:full":"Calle de Hermanos Ruiz, 7 Madrid Madrid 28007",
    "addr:housenumber":"7",
    "addr:postcode":"madrid;28007",
    "addr:street":"Calle De Hermanos Ruiz",
    "iso:country":"ES",
    "sg:address":"Calle de Hermanos Ruiz, 7",
    "sg:city":"Madrid",
    "sg:orig_category":"Enfermeras: Consultas, Atenci\u00d3n A Domicilio",
    "sg:phone":"+34 915 52 42 29",
    "sg:postcode":"28007",
    "sg:province":"Madrid",
    "wof:name":"Cristobal Nogueira Jose Maria",
    "wof:placetype":"venue"
},
  "geometry": {"coordinates":[-3.673774004,40.4000968933],"type":"Point"}
}