{
  "type": "Feature",
  "properties": {
    "iso:country":"ES",
    "sg:address":"Pase Colorado Del, 16",
    "sg:city":"Torremolinos",
    "sg:orig_category":"Caf\u00c9s, Bares, Cervecer\u00cdas",
    "sg:phone":"+34 952 37 47 00",
    "sg:postcode":"29620",
    "sg:province":"M\u00e1laga",
    "wof:name":"Ure\u00f1a Martinez Manuel Antonio",
    "wof:placetype":"venue"
},
  "geometry": {"coordinates":[-4.4927330017,36.6315765381],"type":"Point"}
}