{
  "type": "Feature",
  "properties": {
    "addr:full":"Carr Poligon Industrial Puigtio, 35 Poligon Industrial Puigtio Girona 17412",
    "addr:housenumber":"35",
    "addr:postcode":"17412",
    "addr:street":"Carr Poligon Industrial Puigtio;Industrial",
    "iso:country":"ES",
    "sg:address":"Carr Poligon Industrial Puigtio, 35",
    "sg:city":"Poligon Industrial Puigtio",
    "sg:orig_category":"Carnicer\u00cdas, Carnicer\u00cdas",
    "sg:phone":"+34 972 85 91 53",
    "sg:postcode":"17412",
    "sg:province":"Girona",
    "wof:name":"Frecarn S. A.",
    "wof:placetype":"venue"
},
  "geometry": {"coordinates":[2.7342700958,41.7778396606],"type":"Point"}
}