{
  "type": "Feature",
  "properties": {
    "iso:country":"ES",
    "sg:address":"Calle de Soto Galo, 55",
    "sg:city":"Logro\u00f1o",
    "sg:orig_category":"Higiene, Belleza: Art\u00cdculos (al Por Menor)",
    "sg:phone":"+34 941 26 03 37",
    "sg:postcode":"26006",
    "sg:province":"La Rioja",
    "wof:name":"Europea De Cepillos Higden S.l. U",
    "wof:placetype":"venue"
},
  "geometry": {"coordinates":[-2.4036989212,42.46043396],"type":"Point"}
}