{
  "type": "Feature",
  "properties": {
    "addr:full":"Calle de Carton, 12 San Vicente Del Raspeig-sant Vicent Del Raspeig Alicante 03690",
    "addr:housenumber":"12",
    "addr:postcode":"03690",
    "addr:street":"Calle De Carton",
    "iso:country":"ES",
    "sg:address":"Calle de Carton, 12",
    "sg:city":"San Vicente Del Raspeig-sant Vicent Del Raspeig",
    "sg:orig_category":"Fabricaci\u00d3n, Venta De Cuadros, Accesorios Para Enmarcar",
    "sg:phone":"+34 902 99 80 38",
    "sg:postcode":"03690",
    "sg:province":"Alicante",
    "sg:website":"www.revestem.es",
    "wof:name":"Revestem S.a.",
    "wof:placetype":"venue"
},
  "geometry": {"coordinates":[-0.5410813093,38.4004325867],"type":"Point"}
}