{
  "type": "Feature",
  "properties": {
    "iso:country":"ES",
    "sg:address":"Calle de Alto Santa Colomba, 219",
    "sg:city":"Fermoselle",
    "sg:orig_category":"Empresas De Carpinter\u00cda De Madera",
    "sg:phone":"+34 980 61 31 79",
    "sg:postcode":"49220",
    "sg:province":"Zamora",
    "wof:name":"Fernandez Vaquero Angel",
    "wof:placetype":"venue"
},
  "geometry": {"coordinates":[-6.3910274506,41.3157615662],"type":"Point"}
}