{
  "type": "Feature",
  "properties": {
    "iso:country":"ES",
    "sg:address":"Plaz Fraga Iribarne, S/n",
    "sg:city":"Pacios",
    "sg:orig_category":"Centros De Educaci\u00d3n Especial",
    "sg:phone":"+34 982 54 11 80",
    "sg:postcode":"27611",
    "sg:province":"Lugo",
    "wof:name":"Colegio De Educacion Infantil Y Primaria San Miguel",
    "wof:placetype":"venue"
},
  "geometry": {"coordinates":[-7.5675940514,42.7657356262],"type":"Point"}
}