{
  "type": "Feature",
  "properties": {
    "addr:full":"Calle de Cuenca Tramoyeres, 2 Valencia Valencia 46020",
    "addr:housenumber":"2",
    "addr:postcode":"46020",
    "addr:street":"Calle De Cuenca Tramoyeres",
    "iso:country":"ES",
    "sg:address":"Calle de Cuenca Tramoyeres, 2",
    "sg:city":"Valencia",
    "sg:orig_category":"Librer\u00cdas",
    "sg:phone":"+34 963 62 55 14",
    "sg:postcode":"46020",
    "sg:province":"Valencia",
    "wof:name":"Valera Garcia Eusebio",
    "wof:placetype":"venue"
},
  "geometry": {"coordinates":[-0.3607879877,39.4826965332],"type":"Point"}
}