{
  "type": "Feature",
  "properties": {
    "addr:full":"Tragove, S/n Tragove Pontevedra 36639",
    "addr:postcode":"36639",
    "addr:street":"Tragove S / N",
    "iso:country":"ES",
    "sg:address":"Tragove, S/n",
    "sg:city":"Tragove",
    "sg:orig_category":"Pescader\u00cdas (al Por Menor)",
    "sg:phone":"+34 986 52 11 82",
    "sg:postcode":"36639",
    "sg:province":"Pontevedra",
    "sg:website":"www.grupolinamar.com",
    "wof:name":"Mariscos Linamar S.l.",
    "wof:placetype":"venue"
},
  "geometry": {"coordinates":[-8.8220100403,42.4838981628],"type":"Point"}
}