{
  "type": "Feature",
  "properties": {
    "addr:full":"Paiendes, 7 Paiendes Pontevedra 36637",
    "addr:housenumber":"7",
    "addr:postcode":"36637",
    "addr:street":"Paiendes",
    "iso:country":"ES",
    "sg:address":"Paiendes, 7",
    "sg:city":"Paiendes",
    "sg:orig_category":"Telas Para Tapizar, Cortinas, Pasamaner\u00cda (fabricaci\u00d3n, Al Por Mayor)",
    "sg:phone":"+34 986 71 54 09",
    "sg:postcode":"36637",
    "sg:province":"Pontevedra",
    "wof:name":"Padin Mouri\u00f1o Maria Del Carmen",
    "wof:placetype":"venue"
},
  "geometry": {"coordinates":[-8.7034988403,42.5184783936],"type":"Point"}
}