{
  "type": "Feature",
  "properties": {
    "addr:full":"Calle de Iturribarri, 5 Ondarroa Vizcaya 48700",
    "addr:housenumber":"5",
    "addr:postcode":"48700",
    "addr:street":"Calle De Iturribarri",
    "iso:country":"ES",
    "sg:address":"Calle de Iturribarri, 5",
    "sg:city":"Ondarroa",
    "sg:classifiers":[
        {
            "category":"Taxi",
            "type":"Transportation"
        }
    ],
    "sg:phone":"+34 946 83 15 96",
    "sg:postcode":"48700",
    "sg:province":"Vizcaya",
    "wof:name":"Arriaga Olave Manuel Maria",
    "wof:placetype":"venue"
},
  "geometry": {"coordinates":[-2.4314050674,43.3215484619],"type":"Point"}
}