{
  "type": "Feature",
  "properties": {
    "addr:full":"Calle de Meson Del Duque, 24 Sanlucar De Barrameda C\u00e1diz 11540",
    "addr:housenumber":"24",
    "addr:postcode":"11540",
    "addr:street":"Calle De Meson Del Duque;Ca\u0301Diz",
    "iso:country":"ES",
    "sg:address":"Calle de Meson Del Duque, 24",
    "sg:city":"Sanlucar De Barrameda",
    "sg:orig_category":"Reposter\u00cdas",
    "sg:phone":"+34 956 36 16 00",
    "sg:postcode":"11540",
    "sg:province":"C\u00e1diz",
    "wof:name":"Jimenez Mora Juan",
    "wof:placetype":"venue"
},
  "geometry": {"coordinates":[-6.3510022163,36.7728500366],"type":"Point"}
}