{
  "type": "Feature",
  "properties": {
    "iso:country":"ES",
    "sg:address":"Tv. Arroyos, S/n",
    "sg:city":"Vallelado",
    "sg:orig_category":"Cajas De Ahorro",
    "sg:phone":"+34 921 15 05 88",
    "sg:postcode":"40213",
    "sg:province":"Segovia",
    "sg:website":"www.cajasegovia.es",
    "wof:name":"Caja De Ahorros Y Monte De Piedad De Segovia",
    "wof:placetype":"venue"
},
  "geometry": {"coordinates":[-4.4318938255,41.4040145874],"type":"Point"}
}