{
  "type": "Feature",
  "properties": {
    "iso:country":"ES",
    "sg:address":"Calle de Ingeniero De La Torre Acosta, 23",
    "sg:city":"Malaga",
    "sg:orig_category":"Cajas Para Embalar",
    "sg:phone":"+34 952 07 06 85",
    "sg:postcode":"29007",
    "sg:province":"M\u00e1laga",
    "wof:name":"Cajamar",
    "wof:placetype":"venue"
},
  "geometry": {"coordinates":[-4.4540362358,36.6977653503],"type":"Point"}
}