{
  "type": "Feature",
  "properties": {
    "addr:full":"Calle de Ingeniero De La Torre Acosta, 23 Malaga M\u00e1laga 29007",
    "addr:housenumber":"23",
    "addr:postcode":"29007",
    "addr:street":"Calle De Ingeniero;Torre Acosta;Ma\u0301Laga",
    "iso:country":"ES",
    "sg:address":"Calle de Ingeniero De La Torre Acosta, 23",
    "sg:city":"Malaga",
    "sg:orig_category":"Cajas Para Embalar",
    "sg:phone":"+34 952 07 06 85",
    "sg:postcode":"29007",
    "sg:province":"M\u00e1laga",
    "wof:name":"Cajamar",
    "wof:placetype":"venue"
},
  "geometry": {"coordinates":[-4.4540362358,36.6977653503],"type":"Point"}
}