{
  "type": "Feature",
  "properties": {
    "addr:full":"Avda Libertad, 79 Ubeda Ja\u00e9n 23400",
    "addr:housenumber":"79",
    "addr:postcode":"23400",
    "addr:street":"Avda Libertad;Jae\u0301N",
    "iso:country":"ES",
    "sg:address":"Avda Libertad, 79",
    "sg:city":"Ubeda",
    "sg:orig_category":"Alumbrados",
    "sg:phone":"+34 953 75 08 22",
    "sg:postcode":"23400",
    "sg:province":"Ja\u00e9n",
    "wof:name":"Lamparas C.molina S.l.",
    "wof:placetype":"venue"
},
  "geometry": {"coordinates":[-3.3687369823,38.0162086487],"type":"Point"}
}