{
  "type": "Feature",
  "properties": {
    "addr:full":"Calle de Raimundo Fernandez Villaverde, 35 Madrid Madrid 28003",
    "addr:housenumber":"35",
    "addr:postcode":"madrid;28003",
    "addr:street":"Calle De Raimundo Fernandez Villaverde",
    "iso:country":"ES",
    "sg:address":"Calle de Raimundo Fernandez Villaverde, 35",
    "sg:city":"Madrid",
    "sg:orig_category":"Venta, Instalaci\u00d3n De Calefacci\u00d3n",
    "sg:phone":"+34 915 53 09 63",
    "sg:postcode":"28003",
    "sg:province":"Madrid",
    "wof:name":"Fausto Mora E Hijos S. L.",
    "wof:placetype":"venue"
},
  "geometry": {"coordinates":[-3.698319912,40.4464378357],"type":"Point"}
}