{
  "type": "Feature",
  "properties": {
    "addr:full":"Polig. Industrial-bertoa, S/n Miron La Coru\u00f1a 15105",
    "addr:housenumber":"s / n",
    "addr:postcode":"15105",
    "addr:street":"Polig. Industrial-Bertoa;Miron La Corun\u0303A",
    "iso:country":"ES",
    "sg:address":"Polig. Industrial-bertoa, S/n",
    "sg:city":"Miron",
    "sg:orig_category":"Alimentaci\u00d3n General (al Por Mayor)",
    "sg:phone":"+34 981 70 40 27",
    "sg:postcode":"15105",
    "sg:province":"La Coru\u00f1a",
    "wof:name":"Comercial Martinez Sanchez S.a.",
    "wof:placetype":"venue"
},
  "geometry": {"coordinates":[-8.605348587,43.3203735352],"type":"Point"}
}