{
  "type": "Feature",
  "properties": {
    "iso:country":"ES",
    "sg:address":"Calle de Bidebarrieta, 16",
    "sg:city":"Bilbao",
    "sg:orig_category":"Peleter\u00cdas",
    "sg:phone":"+34 944 16 76 75",
    "sg:postcode":"48005",
    "sg:province":"Vizcaya",
    "wof:name":"Taller Mundo Piel S.l.",
    "wof:placetype":"venue"
},
  "geometry": {"coordinates":[-2.924366951,43.2576560974],"type":"Point"}
}