{
  "type": "Feature",
  "properties": {
    "iso:country":"ES",
    "sg:address":"Calle de Lorenzo Silva, 33",
    "sg:city":"Malaga",
    "sg:orig_category":"Agencias Y Agentes Comerciales, Representantes",
    "sg:phone":"+34 952 30 36 48",
    "sg:postcode":"29010",
    "sg:province":"M\u00e1laga",
    "wof:name":"Promociones Novo Coin S.a.",
    "wof:placetype":"venue"
},
  "geometry": {"coordinates":[-4.4425501823,36.726940155],"type":"Point"}
}