{
  "type": "Feature",
  "properties": {
    "addr:full":"Calle de General Ricardos, 4 Barbastro Huesca 22300",
    "addr:housenumber":"4",
    "addr:postcode":"22300",
    "addr:street":"Calle De General Ricardos",
    "iso:country":"ES",
    "sg:address":"Calle de General Ricardos, 4",
    "sg:city":"Barbastro",
    "sg:orig_category":"Servicio De Salud",
    "sg:phone":"+34 974 31 15 85",
    "sg:postcode":"22300",
    "sg:province":"Huesca",
    "wof:name":"Villanueva Doz Reinaldo Emilio",
    "wof:placetype":"venue"
},
  "geometry": {"coordinates":[0.1273380071,42.0365257263],"type":"Point"}
}