{
  "type": "Feature",
  "properties": {
    "iso:country":"ES",
    "sg:address":"Calle de San Damaso, 12",
    "sg:city":"Madrid",
    "sg:orig_category":"Reposter\u00cdas",
    "sg:phone":"+34 915 60 32 05",
    "sg:postcode":"28019",
    "sg:province":"Madrid",
    "wof:name":"Moran Reina Manuel Jesus",
    "wof:placetype":"venue"
},
  "geometry": {"coordinates":[-3.7239382267,40.4016342163],"type":"Point"}
}