{
  "type": "Feature",
  "properties": {
    "iso:country":"ES",
    "sg:address":"Carrer de Pare Gallissa, 25",
    "sg:city":"Vic",
    "sg:orig_category":"Ropa De Hogar (al Por Menor)",
    "sg:phone":"+34 938 89 43 64",
    "sg:postcode":"08500",
    "sg:province":"Barcelona",
    "wof:name":"Confeccio I Decoracio De La Casa S.l.",
    "wof:placetype":"venue"
},
  "geometry": {"coordinates":[2.249243021,41.9317855835],"type":"Point"}
}