{
  "type": "Feature",
  "properties": {
    "addr:full":"Ctra Adanero-gijon, Km. 0194,2 Zaratan Valladolid 47610",
    "addr:postcode":"47610",
    "addr:street":"Ctra Adanero-Gijon Km. 0194,2 Zaratan",
    "iso:country":"ES",
    "sg:address":"Ctra Adanero-gijon, Km. 0194,2",
    "sg:city":"Zaratan",
    "sg:orig_category":"Colocaci\u00d3n, Mantenimiento De Canalizaciones",
    "sg:phone":"+34 983 35 45 08",
    "sg:postcode":"47610",
    "sg:province":"Valladolid",
    "wof:name":"Rica Guerrero S. C. L.",
    "wof:placetype":"venue"
},
  "geometry": {"coordinates":[-4.7845540047,41.6637001038],"type":"Point"}
}