{
  "type": "Feature",
  "properties": {
    "iso:country":"ES",
    "sg:address":"Avda Ciudad De Almeria, 23",
    "sg:city":"Purisima -barriomar",
    "sg:orig_category":"Servicios De Telecomunicaciones",
    "sg:phone":"+34 968 25 93 81",
    "sg:postcode":"30010",
    "sg:province":"Murcia",
    "wof:name":"Unimundo Telecom S.l.",
    "wof:placetype":"venue"
},
  "geometry": {"coordinates":[-1.1492689848,37.9747200012],"type":"Point"}
}