{
  "type": "Feature",
  "properties": {
    "addr:full":"Av Sant Narcis, 18 Girona Girona 17005",
    "addr:housenumber":"18",
    "addr:postcode":"17005",
    "addr:street":"Av Sant Narcis",
    "iso:country":"ES",
    "sg:address":"Av Sant Narcis, 18",
    "sg:city":"Girona",
    "sg:orig_category":"Molduras, Junquillos, Listones Y Molduras Perforadas",
    "sg:phone":"+34 972 23 65 17",
    "sg:postcode":"17005",
    "sg:province":"Girona",
    "wof:name":"Hosteleria Gironina S.c.p.",
    "wof:placetype":"venue"
},
  "geometry": {"coordinates":[2.8139219284,41.9787139893],"type":"Point"}
}