{
  "type": "Feature",
  "properties": {
    "iso:country":"ES",
    "sg:address":"Avda Cervantes, 51",
    "sg:city":"Arizgoiti",
    "sg:orig_category":"Empresas De Limpieza",
    "sg:phone":"+34 944 40 11 27",
    "sg:postcode":"48970",
    "sg:province":"Vizcaya",
    "wof:name":"Euskadi De Limpiezas Y Mantenimiento S.l.",
    "wof:placetype":"venue"
},
  "geometry": {"coordinates":[-2.8774580956,43.2388687134],"type":"Point"}
}