{
  "type": "Feature",
  "properties": {
    "iso:country":"ES",
    "sg:address":"Pase Federico Garcia Lorca, 9",
    "sg:city":"Madrid",
    "sg:orig_category":"Electrodom\u00c9sticos (al Por Menor)",
    "sg:phone":"+34 913 32 07 37",
    "sg:postcode":"28031",
    "sg:province":"Madrid",
    "wof:name":"Peygo S.l.",
    "wof:placetype":"venue"
},
  "geometry": {"coordinates":[-3.6210420132,40.3785095215],"type":"Point"}
}