{
  "type": "Feature",
  "properties": {
    "addr:full":"Calle de San Julian, 10 Ca\u00d1ete Cuenca 16300",
    "addr:housenumber":"10",
    "addr:postcode":"16300",
    "addr:street":"Calle De San Julian",
    "iso:country":"ES",
    "sg:address":"Calle de San Julian, 10",
    "sg:city":"Ca\u00d1ete",
    "sg:orig_category":"Reposter\u00cdas",
    "sg:phone":"+34 969 34 60 54",
    "sg:postcode":"16300",
    "sg:province":"Cuenca",
    "wof:name":"Ruiz Castelblanque Francisco",
    "wof:placetype":"venue"
},
  "geometry": {"coordinates":[-1.6490689516,40.0415802002],"type":"Point"}
}