{
  "type": "Feature",
  "properties": {
    "iso:country":"ES",
    "sg:address":"Calle de Angel Del Cerro Sornichero, 1",
    "sg:city":"Alcantarilla",
    "sg:orig_category":"Arquitectos",
    "sg:phone":"+34 968 89 09 93",
    "sg:postcode":"30820",
    "sg:province":"Murcia",
    "wof:name":"Arquipolis Estudio De Arquitectura S.l.",
    "wof:placetype":"venue"
},
  "geometry": {"coordinates":[-1.2145353556,37.974861145],"type":"Point"}
}