{
  "type": "Feature",
  "properties": {
    "addr:full":"Ctra. Adanero-gijon, Km. 0268,0 Mayorga Valladolid 47680",
    "addr:postcode":"47680",
    "addr:street":"Ctra. Adanero-Gijon Km. 0268,0",
    "iso:country":"ES",
    "sg:address":"Ctra. Adanero-gijon, Km. 0268,0",
    "sg:city":"Mayorga",
    "sg:orig_category":"Hormigonados",
    "sg:phone":"+34 983 75 15 15",
    "sg:postcode":"47680",
    "sg:province":"Valladolid",
    "wof:name":"Hormigones Bartolome S.a.",
    "wof:placetype":"venue"
},
  "geometry": {"coordinates":[-5.2690138817,42.1637191772],"type":"Point"}
}