{
  "type": "Feature",
  "properties": {
    "addr:full":"Avgd Primer De Maig, 16 Paterna Valencia 46980",
    "addr:housenumber":"16",
    "addr:postcode":"46980",
    "addr:street":"Maig",
    "iso:country":"ES",
    "sg:address":"Avgd Primer De Maig, 16",
    "sg:city":"Paterna",
    "sg:orig_category":"M\u00c1rmoles, Granitos Y Piedras Naturales",
    "sg:phone":"+34 961 38 26 48",
    "sg:postcode":"46980",
    "sg:province":"Valencia",
    "wof:name":"Alonso Fernandez Juan Manuel",
    "wof:placetype":"venue"
},
  "geometry": {"coordinates":[-0.4446952939,39.5056686401],"type":"Point"}
}