{
  "type": "Feature",
  "properties": {
    "iso:country":"ES",
    "sg:address":"Rua Mercado (do), 4",
    "sg:city":"Carballi\u00f1o",
    "sg:orig_category":"Carnicer\u00cdas, Carnicer\u00cdas",
    "sg:phone":"+34 988 27 42 34",
    "sg:postcode":"32500",
    "sg:province":"Ourense",
    "wof:name":"Puga Novoa Jose Andres",
    "wof:placetype":"venue"
},
  "geometry": {"coordinates":[-8.0793838501,42.4299049377],"type":"Point"}
}