{
  "type": "Feature",
  "properties": {
    "addr:full":"Calle de Ni\u00d1o Practicante, 1 Salteras Sevilla 41909",
    "addr:housenumber":"1",
    "addr:postcode":"41909",
    "addr:street":"Calle De Nin\u0303O Practicante",
    "iso:country":"ES",
    "sg:address":"Calle de Ni\u00d1o Practicante, 1",
    "sg:city":"Salteras",
    "sg:orig_category":"Asociaciones, Organismos Culturales Y Socioeducativos",
    "sg:phone":"+34 955 70 76 99",
    "sg:postcode":"41909",
    "sg:province":"Sevilla",
    "wof:name":"Hermandad De La Oliva",
    "wof:placetype":"venue"
},
  "geometry": {"coordinates":[-6.1109662056,37.4182319641],"type":"Point"}
}