{
  "type": "Feature",
  "properties": {
    "addr:full":"Calle de Republica Argentina, 13 Campo Criptana Ciudad Real 13610",
    "addr:housenumber":"13",
    "addr:postcode":"13610",
    "addr:street":"Calle De Republica Argentina;Criptana",
    "iso:country":"ES",
    "sg:address":"Calle de Republica Argentina, 13",
    "sg:city":"Campo Criptana",
    "sg:orig_category":"Molduras, Junquillos, Listones Y Molduras Perforadas",
    "sg:phone":"+34 926 56 01 91",
    "sg:postcode":"13610",
    "sg:province":"Ciudad Real",
    "wof:name":"Ioana Luchian Daniela Maria",
    "wof:placetype":"venue"
},
  "geometry": {"coordinates":[-3.1270129681,39.3983726501],"type":"Point"}
}