{
  "type": "Feature",
  "properties": {
    "addr:full":"Calle de Doctor Encinas, 3 Potes Cantabria 39570",
    "addr:housenumber":"3",
    "addr:postcode":"39570",
    "addr:street":"Calle De Doctor Encinas",
    "iso:country":"ES",
    "sg:address":"Calle de Doctor Encinas, 3",
    "sg:city":"Potes",
    "sg:orig_category":"Quincaller\u00cda (al Por Menor)",
    "sg:phone":"+34 942 73 04 20",
    "sg:postcode":"39570",
    "sg:province":"Cantabria",
    "wof:name":"Ferreteria La Llave Gomez-celis S. Cv",
    "wof:placetype":"venue"
},
  "geometry": {"coordinates":[-4.6225504875,43.1537590027],"type":"Point"}
}