{
  "type": "Feature",
  "properties": {
    "addr:full":"Avgd Pi Y Margall, 15 Burjassot Valencia 46100",
    "addr:housenumber":"15",
    "addr:postcode":"46100",
    "addr:street":"Pi Y Margall",
    "iso:country":"ES",
    "sg:address":"Avgd Pi Y Margall, 15",
    "sg:city":"Burjassot",
    "sg:orig_category":"Internados & Ense\u00d1anza Privada",
    "sg:phone":"+34 963 63 90 74",
    "sg:postcode":"46100",
    "sg:province":"Valencia",
    "wof:name":"Cucarella Roda Amparo",
    "wof:placetype":"venue"
},
  "geometry": {"coordinates":[-0.415989995,39.5149230957],"type":"Point"}
}