{
  "type": "Feature",
  "properties": {
    "addr:full":"Calle de Virgen De La Vega, S/n Piedrahita \u00c1vila 05500",
    "addr:housenumber":"s / n",
    "addr:postcode":"05500",
    "addr:street":"Calle De Virgen De La Vega",
    "iso:country":"ES",
    "sg:address":"Calle de Virgen De La Vega, S/n",
    "sg:city":"Piedrahita",
    "sg:orig_category":"Asistencia Domiciliaria",
    "sg:phone":"+34 920 36 10 11",
    "sg:postcode":"05500",
    "sg:province":"\u00c1vila",
    "wof:name":"Sergesa Hogar S.a.",
    "wof:placetype":"venue"
},
  "geometry": {"coordinates":[-5.3254041672,40.465511322],"type":"Point"}
}