{
  "type": "Feature",
  "properties": {
    "iso:country":"ES",
    "sg:address":"Carretera De Alcolea, S/n",
    "sg:city":"Laujar Andarax",
    "sg:orig_category":"Productores Recolectores, Venta Directa De Vinos",
    "sg:phone":"+34 950 51 42 00",
    "sg:postcode":"04470",
    "sg:province":"Almer\u00eda",
    "wof:name":"Bodegas Valle De Laujar Sociedad Cooperativa Andaluza",
    "wof:placetype":"venue"
},
  "geometry": {"coordinates":[-2.8938889503,36.9929962158],"type":"Point"}
}