{
  "type": "Feature",
  "properties": {
    "addr:full":"Pl. Vila, 4 Lli\u00e7a Vall Barcelona 08185",
    "addr:housenumber":"4",
    "addr:postcode":"08185",
    "addr:street":"Vila;Vall Barcelona",
    "iso:country":"ES",
    "sg:address":"Pl. Vila, 4",
    "sg:city":"Lli\u00e7a Vall",
    "sg:orig_category":"Pintura, Barniz, Productos Asimilables (fabricaci\u00d3n, Al Por Mayor)",
    "sg:phone":"+34 938 43 90 34",
    "sg:postcode":"08185",
    "sg:province":"Barcelona",
    "wof:name":"Rio Empresa De Limpiezas S.a.",
    "wof:placetype":"venue"
},
  "geometry": {"coordinates":[2.2325119972,41.5866622925],"type":"Point"}
}