{
  "type": "Feature",
  "properties": {
    "iso:country":"ES",
    "sg:address":"Pase Castellana, 10",
    "sg:city":"Madrid",
    "sg:orig_category":"Promotores Constructores",
    "sg:phone":"+34 915 75 12 64",
    "sg:postcode":"28046",
    "sg:province":"Madrid",
    "sg:website":"www.nozar.es",
    "wof:name":"Lena Construcciones S.a.",
    "wof:placetype":"venue"
},
  "geometry": {"coordinates":[-3.6892030239,40.4274864197],"type":"Point"}
}