{
  "type": "Feature",
  "properties": {
    "addr:full":"Calle de Villamartin, 4 Arahal Sevilla 41600",
    "addr:housenumber":"4",
    "addr:postcode":"41600",
    "addr:street":"Calle De Villamartin",
    "iso:country":"ES",
    "sg:address":"Calle de Villamartin, 4",
    "sg:city":"Arahal",
    "sg:orig_category":"Ingeniero",
    "sg:phone":"+34 955 84 22 16",
    "sg:postcode":"41600",
    "sg:province":"Sevilla",
    "wof:name":"Sevitel Servicios Integrales De Telecomunicaciones S.l.",
    "wof:placetype":"venue"
},
  "geometry": {"coordinates":[-5.5492801666,37.2562866211],"type":"Point"}
}