{
  "type": "Feature",
  "properties": {
    "addr:full":"Calle de Barroso, 10 Malaga M\u00e1laga 29001",
    "addr:housenumber":"10",
    "addr:postcode":"29001",
    "addr:street":"Calle De Barroso;Ma\u0301Laga",
    "iso:country":"ES",
    "sg:address":"Calle de Barroso, 10",
    "sg:city":"Malaga",
    "sg:orig_category":"Agencias Y Asesores De Publicidad",
    "sg:phone":"+34 952 06 13 46",
    "sg:postcode":"29001",
    "sg:province":"M\u00e1laga",
    "wof:name":"The Bottle Company S.c.a.",
    "wof:placetype":"venue"
},
  "geometry": {"coordinates":[-4.4233670235,36.7157592773],"type":"Point"}
}