{
  "type": "Feature",
  "properties": {
    "iso:country":"ES",
    "sg:address":"Avda Cervantes, 43",
    "sg:city":"Basauri",
    "sg:orig_category":"Electromec\u00c1nica",
    "sg:phone":"+34 944 26 26 09",
    "sg:postcode":"48970",
    "sg:province":"Vizcaya",
    "wof:name":"Cervantes Motor",
    "wof:placetype":"venue"
},
  "geometry": {"coordinates":[-2.8794870377,43.2417945862],"type":"Point"}
}