{
  "type": "Feature",
  "properties": {
    "iso:country":"ES",
    "sg:address":"Ctra. General (vilacha), 13",
    "sg:city":"Cangas",
    "sg:orig_category":"Pintura Y Barniz (al Por Menor)",
    "sg:phone":"+34 982 15 60 72",
    "sg:postcode":"27892",
    "sg:province":"Lugo",
    "wof:name":"Cuba Pernas Miguel",
    "wof:placetype":"venue"
},
  "geometry": {"coordinates":[-7.3413281441,43.628818512],"type":"Point"}
}