{
  "type": "Feature",
  "properties": {
    "iso:country":"ES",
    "sg:address":"Calle de Cisne, 52",
    "sg:city":"Punta Umbria",
    "sg:orig_category":"Promotores Constructores",
    "sg:phone":"+34 959 31 15 80",
    "sg:postcode":"21100",
    "sg:province":"Huelva",
    "wof:name":"Mormedina Xxi S.l.",
    "wof:placetype":"venue"
},
  "geometry": {"coordinates":[-6.9633350372,37.1796226501],"type":"Point"}
}