{
  "type": "Feature",
  "properties": {
    "iso:country":"ES",
    "sg:address":"Avda Sevilla, S/n",
    "sg:city":"Salteras",
    "sg:orig_category":"Comit\u00c9s De Organizaci\u00d3n De Exposiciones, Ferias, Salones",
    "sg:phone":"+34 955 70 70 70",
    "sg:postcode":"41909",
    "sg:province":"Sevilla",
    "wof:name":"Muebles Salteras S.l.",
    "wof:placetype":"venue"
},
  "geometry": {"coordinates":[-6.1071691513,37.4179992676],"type":"Point"}
}