{
  "type": "Feature",
  "properties": {
    "iso:country":"ES",
    "sg:address":"Calle de Argimiro Torrecilla, 2",
    "sg:city":"Jarandilla Vera",
    "sg:orig_category":"Complementos De Vestir (al Por Menor)",
    "sg:phone":"+34 927 56 10 60",
    "sg:postcode":"10450",
    "sg:province":"C\u00e1ceres",
    "wof:name":"Rodriguez Tores Virginia",
    "wof:placetype":"venue"
},
  "geometry": {"coordinates":[-5.6573152542,40.1293411255],"type":"Point"}
}