{
  "type": "Feature",
  "properties": {
    "addr:full":"Avda Madrid (de), 101 Petrer Alicante 03610",
    "addr:housenumber":"101",
    "addr:postcode":"03610",
    "addr:street":"Avda Madrid De",
    "iso:country":"ES",
    "sg:address":"Avda Madrid (de), 101",
    "sg:city":"Petrer",
    "sg:orig_category":"Empresarios",
    "sg:phone":"+34 966 95 50 41",
    "sg:postcode":"03610",
    "sg:province":"Alicante",
    "wof:name":"Proydeco S.l",
    "wof:placetype":"venue"
},
  "geometry": {"coordinates":[-0.7877069712,38.4845275879],"type":"Point"}
}