{
  "type": "Feature",
  "properties": {
    "iso:country":"ES",
    "sg:address":"Calle de Bidasoa, 13",
    "sg:city":"Errenteria",
    "sg:orig_category":"Fabrica, Negocio De Vidrieras, Productos Vidriados Y Espejos",
    "sg:phone":"+34 943 01 21 74",
    "sg:postcode":"20100",
    "sg:province":"Guip\u00f9zcoa",
    "wof:name":"Cristaleria Xenpelar",
    "wof:placetype":"venue"
},
  "geometry": {"coordinates":[-1.9021060467,43.3131141663],"type":"Point"}
}