{
  "type": "Feature",
  "properties": {
    "iso:country":"ES",
    "sg:address":"Avda Isla Mayor, 75",
    "sg:city":"Puebla Del Rio",
    "sg:orig_category":"Aparatos E Instalaci\u00d3n De Regad\u00cdos",
    "sg:phone":"+34 955 77 07 34",
    "sg:postcode":"41130",
    "sg:province":"Sevilla",
    "wof:name":"Comunidad De Regantes De La Puebla Del Rio",
    "wof:placetype":"venue"
},
  "geometry": {"coordinates":[-6.0661091805,37.2644195557],"type":"Point"}
}