{
  "type": "Feature",
  "properties": {
    "addr:full":"Carrer de Guimros, 3 Montblanc Tarragona 43400",
    "addr:housenumber":"3",
    "addr:postcode":"43400",
    "addr:street":"Carrer De Guimros",
    "iso:country":"ES",
    "sg:address":"Carrer de Guimros, 3",
    "sg:city":"Montblanc",
    "sg:orig_category":"Molduras, Junquillos, Listones Y Molduras Perforadas",
    "sg:phone":"+34 977 86 22 17",
    "sg:postcode":"43400",
    "sg:province":"Tarragona",
    "wof:name":"Bonet Munt Carlos",
    "wof:placetype":"venue"
},
  "geometry": {"coordinates":[1.1610770226,41.3762397766],"type":"Point"}
}