{
  "type": "Feature",
  "properties": {
    "addr:full":"Carrer de Napols, 160 Barcelona Barcelona 08013",
    "addr:housenumber":"160",
    "addr:postcode":"08013",
    "addr:street":"Carrer De Napols",
    "iso:country":"ES",
    "sg:address":"Carrer de Napols, 160",
    "sg:city":"Barcelona",
    "sg:orig_category":"Periodistas Profesionales",
    "sg:phone":"+34 932 46 21 30",
    "sg:postcode":"08013",
    "sg:province":"Barcelona",
    "wof:name":"Munso Cabus Juan",
    "wof:placetype":"venue"
},
  "geometry": {"coordinates":[2.1764650345,41.3978042603],"type":"Point"}
}