{
  "type": "Feature",
  "properties": {
    "iso:country":"ES",
    "sg:address":"Pase San Frantzisko Ibiltokia, 41",
    "sg:city":"Tolosa",
    "sg:orig_category":"Arquitectos",
    "sg:phone":"+34 943 65 22 36",
    "sg:postcode":"20400",
    "sg:province":"Guip\u00f9zcoa",
    "wof:name":"Armando Roca Garcia",
    "wof:placetype":"venue"
},
  "geometry": {"coordinates":[-2.0782530308,43.1339263916],"type":"Point"}
}