{
  "type": "Feature",
  "properties": {
    "addr:full":"Calle de Julian Fuentecilla, 3 Ramales Victoria Cantabria 39800",
    "addr:housenumber":"3",
    "addr:postcode":"39800",
    "addr:street":"Calle De Julian Fuentecilla",
    "iso:country":"ES",
    "sg:address":"Calle de Julian Fuentecilla, 3",
    "sg:city":"Ramales Victoria",
    "sg:orig_category":"Quincaller\u00cda (al Por Menor)",
    "sg:phone":"+34 942 64 60 84",
    "sg:postcode":"39800",
    "sg:province":"Cantabria",
    "wof:name":"Sainz Pereda Miguel",
    "wof:placetype":"venue"
},
  "geometry": {"coordinates":[-3.442991972,43.2613754272],"type":"Point"}
}