{
  "type": "Feature",
  "properties": {
    "iso:country":"ES",
    "sg:address":"Plaz Montecompatri, 6",
    "sg:city":"Calahorra",
    "sg:orig_category":"Psic\u00d3logos",
    "sg:phone":"+34 941 14 69 03",
    "sg:postcode":"26500",
    "sg:province":"La Rioja",
    "wof:name":"Calvo Merino Cristina",
    "wof:placetype":"venue"
},
  "geometry": {"coordinates":[-1.9620640278,42.3058395386],"type":"Point"}
}