{
  "type": "Feature",
  "properties": {
    "addr:full":"Calle de Mayor, 5 Donostia-san Sebastian Guip\u00f9zcoa 20003",
    "addr:housenumber":"5",
    "addr:postcode":"20003",
    "addr:street":"Calle De Mayor",
    "iso:country":"ES",
    "sg:address":"Calle de Mayor, 5",
    "sg:city":"Donostia-san Sebastian",
    "sg:orig_category":"Fisioterapia",
    "sg:phone":"+34 943 43 10 36",
    "sg:postcode":"20003",
    "sg:province":"Guip\u00f9zcoa",
    "wof:name":"Arribas Del Campo Pedro Maria",
    "wof:placetype":"venue"
},
  "geometry": {"coordinates":[-1.9858715534,43.3227386475],"type":"Point"}
}