{
  "type": "Feature",
  "properties": {
    "iso:country":"ES",
    "sg:address":"Pl Castilla Mancha, S/n",
    "sg:city":"Villanueva Infantes",
    "sg:orig_category":"Empresas De Pintura Y Revestimientos",
    "sg:phone":"+34 926 36 05 39",
    "sg:postcode":"13320",
    "sg:province":"Ciudad Real",
    "wof:name":"Arroyo Rubio Pedro",
    "wof:placetype":"venue"
},
  "geometry": {"coordinates":[-3.0068602562,38.7373046875],"type":"Point"}
}