{
  "type": "Feature",
  "properties": {
    "addr:full":"Pase San Roque (de), 25 Avila \u00c1vila 05003",
    "addr:postcode":"05003",
    "addr:street":"A\u0301Vila",
    "iso:country":"ES",
    "sg:address":"Pase San Roque (de), 25",
    "sg:city":"Avila",
    "sg:orig_category":"Agencias De Viajes",
    "sg:phone":"+34 920 25 64 76",
    "sg:postcode":"05003",
    "sg:province":"\u00c1vila",
    "wof:name":"Moreno Echanove Maria Luisa",
    "wof:placetype":"venue"
},
  "geometry": {"coordinates":[-4.7072339058,40.6581344604],"type":"Point"}
}