{
  "type": "Feature",
  "properties": {
    "iso:country":"ES",
    "sg:address":"Calle de Isabel La Catolica, 9",
    "sg:city":"Cadiz",
    "sg:orig_category":"Bisuter\u00cda, Joyer\u00cda, Relojer\u00cda (al Por Menor)",
    "sg:phone":"+34 956 22 34 07",
    "sg:postcode":"11004",
    "sg:province":"C\u00e1diz",
    "wof:name":"Collantes Ariza Antonio",
    "wof:placetype":"venue"
},
  "geometry": {"coordinates":[-6.2948169708,36.5353775024],"type":"Point"}
}