{
  "type": "Feature",
  "properties": {
    "addr:full":"Carrer de Bisbe Sastre, 13 Palma Islas Baleares 07011",
    "addr:housenumber":"13",
    "addr:postcode":"07011",
    "addr:street":"Carrer De Bisbe Sastre",
    "iso:country":"ES",
    "sg:address":"Carrer de Bisbe Sastre, 13",
    "sg:city":"Palma",
    "sg:orig_category":"Plomeros",
    "sg:phone":"+34 971 45 32 40",
    "sg:postcode":"07011",
    "sg:province":"Islas Baleares",
    "wof:name":"Instalaciones Y Mantenimientos Balcor S.l.",
    "wof:placetype":"venue"
},
  "geometry": {"coordinates":[2.6376080513,39.5804672241],"type":"Point"}
}