{
  "type": "Feature",
  "properties": {
    "iso:country":"ES",
    "sg:address":"Calle de Sierra De Guadarrama, 30",
    "sg:city":"Arganda",
    "sg:orig_category":"Electricidad: Equipos Industriales, Componentes (fabricaci\u00d3n)",
    "sg:phone":"+34 918 72 90 04",
    "sg:postcode":"28500",
    "sg:province":"Madrid",
    "wof:name":"D.s. Componentes S.l.",
    "wof:placetype":"venue"
},
  "geometry": {"coordinates":[-3.4753201008,40.3064575195],"type":"Point"}
}