{
  "type": "Feature",
  "properties": {
    "iso:country":"ES",
    "sg:address":"Bidekurutzeta Kalea, 13",
    "sg:city":"Bergara",
    "sg:orig_category":"Relojer\u00cda (al Por Menor, Reparaci\u00d3n)",
    "sg:phone":"+34 943 76 13 73",
    "sg:postcode":"20570",
    "sg:province":"Guip\u00f9zcoa",
    "wof:name":"Garagorri Arin Miguel",
    "wof:placetype":"venue"
},
  "geometry": {"coordinates":[-2.4135138988,43.1164588928],"type":"Point"}
}