{
  "type": "Feature",
  "properties": {
    "iso:country":"ES",
    "sg:address":"Cno. Cruz, 1",
    "sg:city":"Marbella",
    "sg:orig_category":"Centros Empresariales",
    "sg:phone":"+34 952 85 80 33",
    "sg:postcode":"29600",
    "sg:province":"M\u00e1laga",
    "wof:name":"N.m. Servicios Hipotecarios S.l.",
    "wof:placetype":"venue"
},
  "geometry": {"coordinates":[-4.8833007812,36.5079956055],"type":"Point"}
}