{
  "type": "Feature",
  "properties": {
    "iso:country":"ES",
    "sg:address":"Calle de Trinidad, 16",
    "sg:city":"Villena",
    "sg:orig_category":"Asesor\u00cda Fiscal Y Jur\u00cddica",
    "sg:phone":"+34 965 80 36 12",
    "sg:postcode":"03400",
    "sg:province":"Alicante",
    "wof:name":"Montero Navarro Jose Maria",
    "wof:placetype":"venue"
},
  "geometry": {"coordinates":[-0.865481019,38.6301879883],"type":"Point"}
}