{
  "type": "Feature",
  "properties": {
    "iso:country":"ES",
    "sg:address":"Calle de Jose Salvetti, 12",
    "sg:city":"Alacant",
    "sg:orig_category":"Asesor\u00cda Fiscal Y Jur\u00cddica",
    "sg:phone":"+34 965 10 28 06",
    "sg:postcode":"03007",
    "sg:province":"Alicante",
    "wof:name":"Valero Garcia Paulino",
    "wof:placetype":"venue"
},
  "geometry": {"coordinates":[-0.5101550221,38.341293335],"type":"Point"}
}