{
  "type": "Feature",
  "properties": {
    "addr:full":"Real, 100 Aldea Rey Ciudad Real 13380",
    "addr:housenumber":"100",
    "addr:postcode":"13380",
    "addr:street":"Real;Real",
    "iso:country":"ES",
    "sg:address":"Real, 100",
    "sg:city":"Aldea Rey",
    "sg:orig_category":"Cajas De Ahorro",
    "sg:phone":"+34 926 86 50 33",
    "sg:postcode":"13380",
    "sg:province":"Ciudad Real",
    "sg:website":"www.unicaja.es",
    "wof:name":"Unicaja",
    "wof:placetype":"venue"
},
  "geometry": {"coordinates":[-3.8391160965,38.7372283936],"type":"Point"}
}