{
  "type": "Feature",
  "properties": {
    "iso:country":"ES",
    "sg:address":"San Joaquin, 28",
    "sg:city":"Catral",
    "sg:orig_category":"Promotores Constructores",
    "sg:phone":"+34 965 72 31 21",
    "sg:postcode":"03158",
    "sg:province":"Alicante",
    "wof:name":"Garcia Gomez Jose",
    "wof:placetype":"venue"
},
  "geometry": {"coordinates":[-0.8515859246,38.1044998169],"type":"Point"}
}