{
  "type": "Feature",
  "properties": {
    "addr:full":"Calle de Centelles, Los, 57 Valencia Valencia 46006",
    "addr:housenumber":"57",
    "addr:postcode":"46006",
    "addr:street":"Calle De Centelles Los",
    "iso:country":"ES",
    "sg:address":"Calle de Centelles, Los, 57",
    "sg:city":"Valencia",
    "sg:orig_category":"Ense\u00d1anza Variada",
    "sg:phone":"+34 963 34 31 90",
    "sg:postcode":"46006",
    "sg:province":"Valencia",
    "wof:name":"Porcel Lopez Carles",
    "wof:placetype":"venue"
},
  "geometry": {"coordinates":[-0.3756527901,39.4581413269],"type":"Point"}
}