{
  "type": "Feature",
  "properties": {
    "addr:full":"Calle de Nuestra Se\u00d1ora Del Pilar, 14 Leganes Madrid 28911",
    "addr:housenumber":"14",
    "addr:postcode":"28911",
    "addr:street":"Calle De Nuestra Sen\u0303Ora Del Pilar",
    "iso:country":"ES",
    "sg:address":"Calle de Nuestra Se\u00d1ora Del Pilar, 14",
    "sg:city":"Leganes",
    "sg:orig_category":"Farmacias",
    "sg:phone":"+34 916 93 53 50",
    "sg:postcode":"28911",
    "sg:province":"Madrid",
    "wof:name":"Yerro Callejo Vicenta Del",
    "wof:placetype":"venue"
},
  "geometry": {"coordinates":[-3.7694067955,40.3259048462],"type":"Point"}
}