{
  "type": "Feature",
  "properties": {
    "iso:country":"ES",
    "sg:address":"Calle de Reina Victoria, 4",
    "sg:city":"Pe\u00e7arroya-pueblonuevo",
    "sg:orig_category":"Doctores En Medicina",
    "sg:phone":"+34 957 57 10 40",
    "sg:postcode":"14200",
    "sg:province":"C\u00f3rdoba",
    "wof:name":"Barquero Fernandez Juan Miguel",
    "wof:placetype":"venue"
},
  "geometry": {"coordinates":[-5.2730660439,38.3016166687],"type":"Point"}
}