{
  "type": "Feature",
  "properties": {
    "addr:full":"Calle de Lectoral Feo Ramos, 11 Palmas De Gran Canaria Las Palmas 35001",
    "addr:postcode":"35001",
    "addr:street":"Calle De Lectoral Feo Ramos 11",
    "iso:country":"ES",
    "sg:address":"Calle de Lectoral Feo Ramos, 11",
    "sg:city":"Palmas De Gran Canaria",
    "sg:orig_category":"Obras Y Organismos Sociales",
    "sg:phone":"+34 928 31 28 03",
    "sg:postcode":"35001",
    "sg:province":"Las Palmas",
    "wof:name":"Asociacion De Hogares Para Ni\u00d1os Privados De Ambiente Familiar Nuevo Futuro De Las Palmas",
    "wof:placetype":"venue"
},
  "geometry": {"coordinates":[-15.4140338898,28.0966262817],"type":"Point"}
}