{
  "type": "Feature",
  "properties": {
    "iso:country":"ES",
    "sg:address":"Avda Tres De Mayo, 85",
    "sg:city":"Santa Cruz De Tenerife",
    "sg:orig_category":"Distribuci\u00d3n De Petr\u00d3leo Y Derivados",
    "sg:phone":"+34 922 22 19 56",
    "sg:postcode":"38005",
    "sg:province":"Santa Cruz De Tenerife",
    "wof:name":"Gonzalez Diaz Miguel Angel",
    "wof:placetype":"venue"
},
  "geometry": {"coordinates":[-16.2620849609,28.4577312469],"type":"Point"}
}