{
  "type": "Feature",
  "properties": {
    "addr:full":"Calle de Alejandro Casona, 7 Entrego Asturias 33940",
    "addr:housenumber":"7",
    "addr:postcode":"33940",
    "addr:street":"Calle De Alejandro Casona",
    "iso:country":"ES",
    "sg:address":"Calle de Alejandro Casona, 7",
    "sg:city":"Entrego",
    "sg:orig_category":"Droguer\u00cdas (al Por Menor)",
    "sg:phone":"+34 985 66 08 81",
    "sg:postcode":"33940",
    "sg:province":"Asturias",
    "wof:name":"Deconalon S.l.",
    "wof:placetype":"venue"
},
  "geometry": {"coordinates":[-5.6365795135,43.2883682251],"type":"Point"}
}