{
  "type": "Feature",
  "properties": {
    "addr:full":"Avenida Los Cristianos, S/n Los Cristianos Santa Cruz De Tenerife 38650",
    "addr:housenumber":"s / n",
    "addr:postcode":"38650",
    "addr:street":"Avenida Los Cristianos",
    "iso:country":"ES",
    "sg:address":"Avenida Los Cristianos, S/n",
    "sg:city":"Los Cristianos",
    "sg:orig_category":"Bisuteros (fabricaci\u00d3n, Al Por Mayor)",
    "sg:phone":"+34 922 79 46 74",
    "sg:postcode":"38650",
    "sg:province":"Santa Cruz De Tenerife",
    "wof:name":"Ayelen 99 Distribuciones S.l.",
    "wof:placetype":"venue"
},
  "geometry": {"coordinates":[-16.7313289642,28.0631198883],"type":"Point"}
}