{
  "type": "Feature",
  "properties": {
    "addr:full":"Calle de Mayor, 2 Ecija Sevilla 41400",
    "addr:housenumber":"2",
    "addr:postcode":"41400",
    "addr:street":"Calle De Mayor",
    "iso:country":"ES",
    "sg:address":"Calle de Mayor, 2",
    "sg:city":"Ecija",
    "sg:orig_category":"Ense\u00d1anza, Formaci\u00d3n Profesional: Aprendizaje",
    "sg:phone":"+34 954 83 13 77",
    "sg:postcode":"41400",
    "sg:province":"Sevilla",
    "wof:name":"Servicio Andaluz De Empleo",
    "wof:placetype":"venue"
},
  "geometry": {"coordinates":[-5.0813088417,37.5457687378],"type":"Point"}
}