{
  "type": "Feature",
  "properties": {
    "addr:full":"Calle de Cardenal Siliceo, 19 Madrid Madrid 28002",
    "addr:housenumber":"19",
    "addr:postcode":"madrid;28002",
    "addr:street":"Calle De Cardenal Siliceo",
    "iso:country":"ES",
    "sg:address":"Calle de Cardenal Siliceo, 19",
    "sg:city":"Madrid",
    "sg:orig_category":"Servicios Gsm",
    "sg:phone":"+34 914 16 92 66",
    "sg:postcode":"28002",
    "sg:province":"Madrid",
    "wof:name":"Cometa Instalaciones S.l",
    "wof:placetype":"venue"
},
  "geometry": {"coordinates":[-3.6704866886,40.4444694519],"type":"Point"}
}