{
  "type": "Feature",
  "properties": {
    "iso:country":"ES",
    "sg:address":"Avda Paz De (la), 68",
    "sg:city":"Logro\u00f1o",
    "sg:orig_category":"Zapatos (al Por Menor)",
    "sg:phone":"+34 941 24 53 83",
    "sg:postcode":"26004",
    "sg:province":"La Rioja",
    "wof:name":"Calzados Ebro S.a.",
    "wof:placetype":"venue"
},
  "geometry": {"coordinates":[-2.434664011,42.464138031],"type":"Point"}
}