{
  "type": "Feature",
  "properties": {
    "iso:country":"ES",
    "sg:address":"Calle de Alejandro Casona, 7",
    "sg:city":"Zaragoza",
    "sg:orig_category":"M\u00c9dicos: Estomatolog\u00cda",
    "sg:phone":"+34 976 73 68 01",
    "sg:postcode":"50015",
    "sg:province":"Zaragoza",
    "wof:name":"Cobo Plana Monica Trinidad",
    "wof:placetype":"venue"
},
  "geometry": {"coordinates":[-0.8914272189,41.6771392822],"type":"Point"}
}