{
  "type": "Feature",
  "properties": {
    "iso:country":"ES",
    "sg:address":"Calle de Leon Xiii, 75",
    "sg:city":"Sevilla",
    "sg:orig_category":"Partidos Pol\u00cdticos",
    "sg:phone":"+34 954 90 88 48",
    "sg:postcode":"41009",
    "sg:province":"Sevilla",
    "wof:name":"Partido Andalucista",
    "wof:placetype":"venue"
},
  "geometry": {"coordinates":[-5.9828357697,37.4058494568],"type":"Point"}
}