{
  "type": "Feature",
  "properties": {
    "addr:full":"Carr Bisbe Irurita, 6 Lleida Lleida 25006",
    "addr:housenumber":"6",
    "addr:postcode":"25006",
    "addr:street":"Carr Bisbe Irurita",
    "iso:country":"ES",
    "sg:address":"Carr Bisbe Irurita, 6",
    "sg:city":"Lleida",
    "sg:orig_category":"Transportes En Cisternas",
    "sg:phone":"+34 973 26 86 68",
    "sg:postcode":"25006",
    "sg:province":"Lleida",
    "wof:name":"Nieto Navas Jose",
    "wof:placetype":"venue"
},
  "geometry": {"coordinates":[0.6143280268,41.616443634],"type":"Point"}
}