{
  "type": "Feature",
  "properties": {
    "addr:full":"Carr Poblat Tipic-avgda.fages De Climent, 9 Empuriabrava Girona 17487",
    "addr:housenumber":"9",
    "addr:postcode":"17487",
    "addr:street":"Carr Poblat Tipic-Avgda.Fages De Climent",
    "iso:country":"ES",
    "sg:address":"Carr Poblat Tipic-avgda.fages De Climent, 9",
    "sg:city":"Empuriabrava",
    "sg:orig_category":"Servicios De Telecomunicaciones",
    "sg:phone":"+34 972 45 44 16",
    "sg:postcode":"17487",
    "sg:province":"Girona",
    "wof:name":"Kaddouri  Mohamed",
    "wof:placetype":"venue"
},
  "geometry": {"coordinates":[3.1070549488,42.2568092346],"type":"Point"}
}