{
  "type": "Feature",
  "properties": {
    "iso:country":"ES",
    "sg:address":"Calle de Tomas Maria Ari\u00d1o, 112",
    "sg:city":"Manzanera",
    "sg:orig_category":"Albergues",
    "sg:phone":"+34 978 78 18 08",
    "sg:postcode":"44420",
    "sg:province":"Teruel",
    "wof:name":"Garpey Javalambre S.l.",
    "wof:placetype":"venue"
},
  "geometry": {"coordinates":[-0.8299390078,40.0588531494],"type":"Point"}
}