{
  "type": "Feature",
  "properties": {
    "iso:country":"ES",
    "sg:address":"Calle de San Jose, 46",
    "sg:city":"Santa Pola",
    "sg:orig_category":"Institutos De Belleza",
    "sg:phone":"+34 965 41 68 49",
    "sg:postcode":"03130",
    "sg:province":"Alicante",
    "wof:name":"Molina Ortiz Antonia",
    "wof:placetype":"venue"
},
  "geometry": {"coordinates":[-0.5585557818,38.193687439],"type":"Point"}
}