{
  "type": "Feature",
  "properties": {
    "addr:full":"Avda Virgen De Los Dolores, 5 Cordoba C\u00f3rdoba 14004",
    "addr:housenumber":"5",
    "addr:postcode":"14004",
    "addr:street":"Avda Virgen De Los Dolores;Co\u0301Rdoba",
    "iso:country":"ES",
    "sg:address":"Avda Virgen De Los Dolores, 5",
    "sg:city":"Cordoba",
    "sg:orig_category":"Carnicer\u00cdas, Carnicer\u00cdas",
    "sg:phone":"+34 957 23 26 70",
    "sg:postcode":"14004",
    "sg:province":"C\u00f3rdoba",
    "wof:name":"Lara Sanchez Francisco Manuel",
    "wof:placetype":"venue"
},
  "geometry": {"coordinates":[-4.7962040901,37.8748435974],"type":"Point"}
}