{
  "type": "Feature",
  "properties": {
    "addr:full":"Calle de Gorbea, 36 Vitoria-gasteiz \u00c1lava 01012",
    "addr:housenumber":"36",
    "addr:postcode":"01012",
    "addr:street":"Calle De Gorbea",
    "iso:country":"ES",
    "sg:address":"Calle de Gorbea, 36",
    "sg:city":"Vitoria-gasteiz",
    "sg:orig_category":"Papel Pintado (al Por Menor)",
    "sg:phone":"+34 945 24 02 95",
    "sg:postcode":"01012",
    "sg:province":"\u00c1lava",
    "wof:name":"Papeles Y Pinturas Mendizabal",
    "wof:placetype":"venue"
},
  "geometry": {"coordinates":[-2.6795392036,42.8516998291],"type":"Point"}
}