{
  "type": "Feature",
  "properties": {
    "iso:country":"ES",
    "sg:address":"Avda Reconquista, S/n",
    "sg:city":"Hervas",
    "sg:orig_category":"Electricidad: Instaladores",
    "sg:phone":"+34 927 47 32 00",
    "sg:postcode":"10700",
    "sg:province":"C\u00e1ceres",
    "wof:name":"Instalaciones Electricas Egosa S.l.",
    "wof:placetype":"venue"
},
  "geometry": {"coordinates":[-5.8648138046,40.2719688416],"type":"Point"}
}