{
  "type": "Feature",
  "properties": {
    "addr:full":"Plaz Portal, 22 Sobrado La Coru\u00f1a 15813",
    "addr:postcode":"15813",
    "addr:street":"Sobrado;Corun\u0303A",
    "iso:country":"ES",
    "sg:address":"Plaz Portal, 22",
    "sg:city":"Sobrado",
    "sg:orig_category":"Marmolistas Funerarios",
    "sg:phone":"+34 981 78 76 54",
    "sg:postcode":"15813",
    "sg:province":"La Coru\u00f1a",
    "wof:name":"Funeraria Vali\u00f1o Mosteiro S.l.",
    "wof:placetype":"venue"
},
  "geometry": {"coordinates":[-8.0220422745,43.0429534912],"type":"Point"}
}