{
  "type": "Feature",
  "properties": {
    "addr:full":"Carrer de Palamos, S/n Mas Rampinyo Barcelona 08110",
    "addr:housenumber":"s / n",
    "addr:postcode":"08110",
    "addr:street":"Carrer De Palamos",
    "iso:country":"ES",
    "sg:address":"Carrer de Palamos, S/n",
    "sg:city":"Mas Rampinyo",
    "sg:orig_category":"Molduras, Junquillos, Listones Y Molduras Perforadas",
    "sg:phone":"+34 935 64 08 83",
    "sg:postcode":"08110",
    "sg:province":"Barcelona",
    "wof:name":"Ca L'estany",
    "wof:placetype":"venue"
},
  "geometry": {"coordinates":[2.1843190193,41.4985542297],"type":"Point"}
}