{
  "type": "Feature",
  "properties": {
    "addr:full":"Calle de Luis Muriel, 9 Madrid Madrid 28002",
    "addr:housenumber":"9",
    "addr:postcode":"madrid;28002",
    "addr:street":"Calle De Luis Muriel",
    "iso:country":"ES",
    "sg:address":"Calle de Luis Muriel, 9",
    "sg:city":"Madrid",
    "sg:orig_category":"Cultos Diversos",
    "sg:phone":"+34 915 62 45 63",
    "sg:postcode":"28002",
    "sg:province":"Madrid",
    "wof:name":"Verdadero Budismo De Nichiren Shoshu Espa\u00f1a",
    "wof:placetype":"venue"
},
  "geometry": {"coordinates":[-3.687335968,40.4487991333],"type":"Point"}
}