{
  "type": "Feature",
  "properties": {
    "addr:full":"Rua Doctor Loureiro Crespo, 19 Pontevedra Pontevedra 36001",
    "addr:housenumber":"19",
    "addr:postcode":"36001",
    "addr:street":"Rua Doctor Loureiro Crespo",
    "iso:country":"ES",
    "sg:address":"Rua Doctor Loureiro Crespo, 19",
    "sg:city":"Pontevedra",
    "sg:orig_category":"Molduras, Junquillos, Listones Y Molduras Perforadas",
    "sg:phone":"+34 986 85 51 65",
    "sg:postcode":"36001",
    "sg:province":"Pontevedra",
    "wof:name":"Sistelcom-telemensaje S.a.",
    "wof:placetype":"venue"
},
  "geometry": {"coordinates":[-8.6358213425,42.4289665222],"type":"Point"}
}