{
  "type": "Feature",
  "properties": {
    "iso:country":"ES",
    "sg:address":"Plaz Arenal Celestino M. Del, 8",
    "sg:city":"Bilbao",
    "sg:orig_category":"Instalaci\u00d3n De Aspiraci\u00d3n De Gases Y Humos",
    "sg:phone":"+34 944 75 27 89",
    "sg:postcode":"48015",
    "sg:province":"Vizcaya",
    "wof:name":"Arturo Manteca Lopez",
    "wof:placetype":"venue"
},
  "geometry": {"coordinates":[-2.956264019,43.2761459351],"type":"Point"}
}