{
  "type": "Feature",
  "properties": {
    "addr:full":"Avda Madrid, 56 Zaragoza Zaragoza 50010",
    "addr:housenumber":"56",
    "addr:postcode":"50010",
    "addr:street":"Avda Madrid",
    "iso:country":"ES",
    "sg:address":"Avda Madrid, 56",
    "sg:city":"Zaragoza",
    "sg:orig_category":"Puertas Y Portales",
    "sg:phone":"+34 976 34 36 72",
    "sg:postcode":"50010",
    "sg:province":"Zaragoza",
    "wof:name":"Puertas Iris S.l.",
    "wof:placetype":"venue"
},
  "geometry": {"coordinates":[-0.9036359787,41.6538238525],"type":"Point"}
}