{
  "type": "Feature",
  "properties": {
    "addr:full":"Calle de Estrella Sirio, 4 Cordoba C\u00f3rdoba 14007",
    "addr:housenumber":"4",
    "addr:postcode":"14007",
    "addr:street":"Calle De Estrella Sirio;Co\u0301Rdoba",
    "iso:country":"ES",
    "sg:address":"Calle de Estrella Sirio, 4",
    "sg:city":"Cordoba",
    "sg:orig_category":"Mobiliario Para Hoteles",
    "sg:phone":"+34 957 43 19 21",
    "sg:postcode":"14007",
    "sg:province":"C\u00f3rdoba",
    "wof:name":"Estevez Valiente Juan",
    "wof:placetype":"venue"
},
  "geometry": {"coordinates":[-4.7685341835,37.8935661316],"type":"Point"}
}