{
  "type": "Feature",
  "properties": {
    "iso:country":"ES",
    "sg:address":"Calle de Dolores Ibarruri 'pasionaria', 11",
    "sg:city":"Sevilla",
    "sg:orig_category":"Asociaciones, Organismos Culturales Y Socioeducativos",
    "sg:phone":"+34 954 62 85 68",
    "sg:postcode":"41013",
    "sg:province":"Sevilla",
    "wof:name":"Asociacion De Mujeres Gitanas Akherdi-tromipen",
    "wof:placetype":"venue"
},
  "geometry": {"coordinates":[-5.9628596306,37.3628425598],"type":"Point"}
}