{
  "type": "Feature",
  "properties": {
    "iso:country":"ES",
    "sg:address":"Calle de San Juan, 8",
    "sg:city":"Gernika-lumo",
    "sg:orig_category":"Muebles Y Accesorios Para Cocinas Y Cuartos De Ba\u00d1o (al Por Menor)",
    "sg:phone":"+34 946 25 21 68",
    "sg:postcode":"48300",
    "sg:province":"Vizcaya",
    "wof:name":"Goyeneche Bilbao Jose Ramon",
    "wof:placetype":"venue"
},
  "geometry": {"coordinates":[-2.6771979332,43.3163566589],"type":"Point"}
}