{
  "type": "Feature",
  "properties": {
    "iso:country":"ES",
    "sg:address":"Calle de Menendez Pidal, 7",
    "sg:city":"Palencia",
    "sg:orig_category":"Mercer\u00cda, Lencer\u00cda (al Por Menor)",
    "sg:phone":"+34 979 73 06 55",
    "sg:postcode":"34004",
    "sg:province":"Palencia",
    "wof:name":"Capdevila Fernandez Margarita",
    "wof:placetype":"venue"
},
  "geometry": {"coordinates":[-4.5215940475,41.9962463379],"type":"Point"}
}