{
  "type": "Feature",
  "properties": {
    "addr:full":"Avda Fuente Vieja, 2 San Juan De Muskiz Vizcaya 48550",
    "addr:housenumber":"2",
    "addr:postcode":"48550",
    "addr:street":"Avda Fuente Vieja",
    "iso:country":"ES",
    "sg:address":"Avda Fuente Vieja, 2",
    "sg:city":"San Juan De Muskiz",
    "sg:orig_category":"Farmacias",
    "sg:phone":"+34 946 70 68 64",
    "sg:postcode":"48550",
    "sg:province":"Vizcaya",
    "wof:name":"Presa Pascual I\u00f1igo",
    "wof:placetype":"venue"
},
  "geometry": {"coordinates":[-3.1237380505,43.3243370056],"type":"Point"}
}