{
  "type": "Feature",
  "properties": {
    "addr:full":"Calle de Iglesia (de La), 2 Alustante Guadalajara 19320",
    "addr:postcode":"19320",
    "addr:street":"Calle De Iglesia;La 2 Alustante",
    "iso:country":"ES",
    "sg:address":"Calle de Iglesia (de La), 2",
    "sg:city":"Alustante",
    "sg:orig_category":"Ense\u00d1anza, Formaci\u00d3n Profesional: Aprendizaje",
    "sg:phone":"+34 978 71 41 44",
    "sg:postcode":"19320",
    "sg:province":"Guadalajara",
    "wof:name":"Ayuntamiento De Alustante",
    "wof:placetype":"venue"
},
  "geometry": {"coordinates":[-1.6587135792,40.6159172058],"type":"Point"}
}