{
  "type": "Feature",
  "properties": {
    "iso:country":"ES",
    "sg:address":"Calle de Alcala, 429",
    "sg:city":"Madrid",
    "sg:orig_category":"Asociaciones Y Clubs Deportivos",
    "sg:phone":"+34 917 42 11 30",
    "sg:postcode":"28027",
    "sg:province":"Madrid",
    "wof:name":"Cebollero Jimenez Manuel",
    "wof:placetype":"venue"
},
  "geometry": {"coordinates":[-3.6366333961,40.4382705688],"type":"Point"}
}