{
  "type": "Feature",
  "properties": {
    "iso:country":"ES",
    "sg:address":"Rbla Joaquim Vayreda, 65",
    "sg:city":"Gava",
    "sg:orig_category":"Art\u00cdculos De Regalo (al Por Menor)",
    "sg:phone":"+34 936 62 11 94",
    "sg:postcode":"08850",
    "sg:province":"Barcelona",
    "wof:name":"Masvidal Torrents Maria Carmen",
    "wof:placetype":"venue"
},
  "geometry": {"coordinates":[2.0069949627,41.3056335449],"type":"Point"}
}