{
  "type": "Feature",
  "properties": {
    "iso:country":"ES",
    "sg:address":"Avda Euskadi, 40",
    "sg:city":"San Vicente De Barakaldo",
    "sg:orig_category":"Fabricaci\u00d3n, Distribuci\u00d3n De Discos, V\u00cddeodiscos Y Musicassettes",
    "sg:phone":"+34 944 99 29 35",
    "sg:postcode":"48902",
    "sg:province":"Vizcaya",
    "wof:name":"Diez Zorrilla Carlos",
    "wof:placetype":"venue"
},
  "geometry": {"coordinates":[-2.9919860363,43.2910041809],"type":"Point"}
}