{
  "type": "Feature",
  "properties": {
    "addr:full":"Rua Eduardo Iglesias, 5 Vigo Pontevedra 36202",
    "addr:housenumber":"5",
    "addr:postcode":"36202",
    "addr:street":"Rua Eduardo Iglesias",
    "iso:country":"ES",
    "sg:address":"Rua Eduardo Iglesias, 5",
    "sg:city":"Vigo",
    "sg:orig_category":"Arquitectos",
    "sg:phone":"+34 986 44 32 23",
    "sg:postcode":"36202",
    "sg:province":"Pontevedra",
    "wof:name":"Vazquez Perez Jose Luis",
    "wof:placetype":"venue"
},
  "geometry": {"coordinates":[-8.7222824097,42.2362861633],"type":"Point"}
}