{
  "type": "Feature",
  "properties": {
    "addr:full":"Carrer de Montseny, 82 Hospitalet Llobregat Barcelona 08904",
    "addr:housenumber":"82",
    "addr:postcode":"08904",
    "addr:street":"Carrer De Montseny",
    "iso:country":"ES",
    "sg:address":"Carrer de Montseny, 82",
    "sg:city":"Hospitalet Llobregat",
    "sg:orig_category":"Art\u00cdculos De Regalo (al Por Menor)",
    "sg:phone":"+34 934 47 04 34",
    "sg:postcode":"08904",
    "sg:province":"Barcelona",
    "wof:name":"Espejo Agilar Maria Dolores",
    "wof:placetype":"venue"
},
  "geometry": {"coordinates":[2.1213929653,41.3711853027],"type":"Point"}
}