{
  "type": "Feature",
  "properties": {
    "iso:country":"ES",
    "sg:address":"Avda San Juan De La Salle, 4",
    "sg:city":"Sevilla",
    "sg:orig_category":"Centros Comerciales Y Grandes Tiendas",
    "sg:phone":"+34 954 35 47 62",
    "sg:postcode":"41008",
    "sg:province":"Sevilla",
    "wof:name":"Multiprecio Los Dalmatas S.l.",
    "wof:placetype":"venue"
},
  "geometry": {"coordinates":[-5.9731030464,37.4063529968],"type":"Point"}
}