{
  "type": "Feature",
  "properties": {
    "iso:country":"ES",
    "sg:address":"Carrer de Aribau, 37",
    "sg:city":"Barcelona",
    "sg:orig_category":"Abogados",
    "sg:phone":"+34 934 53 17 80",
    "sg:postcode":"08011",
    "sg:province":"Barcelona",
    "wof:name":"Puig Enrich Jordi",
    "wof:placetype":"venue"
},
  "geometry": {"coordinates":[2.1602480412,41.3875427246],"type":"Point"}
}