{
  "type": "Feature",
  "properties": {
    "iso:country":"ES",
    "sg:address":"Calle de Hornillo De Cartuja, 18",
    "sg:city":"Granada",
    "sg:orig_category":"Lencer\u00cda Femenina, Corseter\u00cda, Trajes De Ba\u00d1o (al Por Menor)",
    "sg:phone":"+34 958 29 38 09",
    "sg:postcode":"18012",
    "sg:province":"Granada",
    "wof:name":"Califaquin S.l.",
    "wof:placetype":"venue"
},
  "geometry": {"coordinates":[-3.601336956,37.1856117249],"type":"Point"}
}