{
  "type": "Feature",
  "properties": {
    "iso:country":"ES",
    "sg:address":"Calle de Gil De Andrade, 11",
    "sg:city":"Alcala Henares",
    "sg:orig_category":"Ropa Para Se\u00d1oras Y Caballeros (al Por Menor)",
    "sg:phone":"+34 918 82 26 32",
    "sg:postcode":"28804",
    "sg:province":"Madrid",
    "wof:name":"Zapata Aguilera Manuel",
    "wof:placetype":"venue"
},
  "geometry": {"coordinates":[-3.3548109531,40.4879455566],"type":"Point"}
}