{
  "type": "Feature",
  "properties": {
    "iso:country":"ES",
    "sg:address":"Carrer de Cinca, 38",
    "sg:city":"Terrassa",
    "sg:orig_category":"Limpieza Industrial",
    "sg:phone":"+34 937 36 04 11",
    "sg:postcode":"08223",
    "sg:province":"Barcelona",
    "wof:name":"Tints And Washed S.l.",
    "wof:placetype":"venue"
},
  "geometry": {"coordinates":[2.0369050503,41.5479698181],"type":"Point"}
}