{
  "type": "Feature",
  "properties": {
    "addr:full":"Calle de Fanego Rojo, S/n Abadin Lugo 27730",
    "addr:postcode":"27730",
    "addr:street":"Calle De Fanego Rojo S / N",
    "iso:country":"ES",
    "sg:address":"Calle de Fanego Rojo, S/n",
    "sg:city":"Abadin",
    "sg:orig_category":"Farmacias",
    "sg:phone":"+34 982 50 80 58",
    "sg:postcode":"27730",
    "sg:province":"Lugo",
    "wof:name":"Diez Roura Enrique",
    "wof:placetype":"venue"
},
  "geometry": {"coordinates":[-7.4971280098,43.2962989807],"type":"Point"}
}