{
  "type": "Feature",
  "properties": {
    "iso:country":"ES",
    "sg:address":"C/ Doctor Sapena, 65",
    "sg:city":"Elche",
    "sg:orig_category":"Asistencia Social",
    "sg:phone":"+34 966 63 63 34",
    "sg:postcode":"03204",
    "sg:province":"Alicante",
    "wof:name":"Asociacion A.s.f.e.m.e. De Elche",
    "wof:placetype":"venue"
},
  "geometry": {"coordinates":[-0.707421124,38.2620429993],"type":"Point"}
}