{
  "type": "Feature",
  "properties": {
    "addr:full":"Barr Larrea, 9 Villabona Guip\u00f9zcoa 20150",
    "addr:housenumber":"9",
    "addr:postcode":"20150",
    "addr:street":"Larrea;Guipu\u0300Zcoa",
    "iso:country":"ES",
    "sg:address":"Barr Larrea, 9",
    "sg:city":"Villabona",
    "sg:orig_category":"Molduras, Junquillos, Listones Y Molduras Perforadas",
    "sg:phone":"+34 943 69 19 33",
    "sg:postcode":"20150",
    "sg:province":"Guip\u00f9zcoa",
    "wof:name":"Felisa Urkola Y Otra C.b.",
    "wof:placetype":"venue"
},
  "geometry": {"coordinates":[-2.0533599854,43.183380127],"type":"Point"}
}