{
  "type": "Feature",
  "properties": {
    "iso:country":"ES",
    "sg:address":"Avda El Ferrol, 7",
    "sg:city":"Madrid",
    "sg:orig_category":"Cl\u00cdnicas Dentales",
    "sg:phone":"+34 913 14 12 95",
    "sg:postcode":"28029",
    "sg:province":"Madrid",
    "wof:name":"Aneiros Lopez Fernando",
    "wof:placetype":"venue"
},
  "geometry": {"coordinates":[-3.7035989761,40.474067688],"type":"Point"}
}