{
  "type": "Feature",
  "properties": {
    "addr:full":"Telleria Kalea, 9 Bergara Guip\u00f9zcoa 20570",
    "addr:housenumber":"9",
    "addr:postcode":"20570",
    "addr:street":"Telleria Kalea;Guipu\u0300Zcoa",
    "iso:country":"ES",
    "sg:address":"Telleria Kalea, 9",
    "sg:city":"Bergara",
    "sg:orig_category":"Fabricaci\u00d3n De Pernos, Tornillos Y Clavos",
    "sg:phone":"+34 943 76 98 23",
    "sg:postcode":"20570",
    "sg:province":"Guip\u00f9zcoa",
    "wof:name":"Industrias Ugatu S.l.",
    "wof:placetype":"venue"
},
  "geometry": {"coordinates":[-2.4233329296,43.1255264282],"type":"Point"}
}