{
  "type": "Feature",
  "properties": {
    "iso:country":"ES",
    "sg:address":"Calle de Mistral, 10",
    "sg:city":"Chiclana De La Frontera",
    "sg:orig_category":"Organizaciones Internacionales",
    "sg:phone":"+34 956 40 71 55",
    "sg:postcode":"11130",
    "sg:province":"C\u00e1diz",
    "wof:name":"Asociacion De Solidaridad Con Los Pueblos Balcanicos Caravana Por La Paz",
    "wof:placetype":"venue"
},
  "geometry": {"coordinates":[-6.1620101929,36.4168357849],"type":"Point"}
}