{
  "type": "Feature",
  "properties": {
    "addr:full":"Av Ildefons Cerda, 12 Centelles Barcelona 08540",
    "addr:housenumber":"12",
    "addr:postcode":"08540",
    "addr:street":"Av Ildefons Cerda",
    "iso:country":"ES",
    "sg:address":"Av Ildefons Cerda, 12",
    "sg:city":"Centelles",
    "sg:orig_category":"Metales (labores, Pulido)",
    "sg:phone":"+34 938 81 07 33",
    "sg:postcode":"08540",
    "sg:province":"Barcelona",
    "wof:name":"Molas Lluis Filomena",
    "wof:placetype":"venue"
},
  "geometry": {"coordinates":[2.2233269215,41.798122406],"type":"Point"}
}