{
  "type": "Feature",
  "properties": {
    "addr:full":"Calle de Marques De La Valdavia (del), 10 Alcobendas Madrid 28100",
    "addr:postcode":"28100",
    "addr:street":"Calle De Marques De La Valdavia Del;Alcobendas",
    "iso:country":"ES",
    "sg:address":"Calle de Marques De La Valdavia (del), 10",
    "sg:city":"Alcobendas",
    "sg:orig_category":"Fabricaci\u00d3n De Sobres, Bolsas Y Fundas",
    "sg:phone":"+34 916 53 96 39",
    "sg:postcode":"28100",
    "sg:province":"Madrid",
    "wof:name":"Diez Antolin Jose Maria",
    "wof:placetype":"venue"
},
  "geometry": {"coordinates":[-3.6362650394,40.5404701233],"type":"Point"}
}