{
  "type": "Feature",
  "properties": {
    "addr:full":"Ma\u00f1ueta, 16 Iru\u00f1a Navarra 31001",
    "addr:housenumber":"16",
    "addr:postcode":"31001",
    "addr:street":"Man\u0303Ueta",
    "iso:country":"ES",
    "sg:address":"Ma\u00f1ueta, 16",
    "sg:city":"Iru\u00f1a",
    "sg:orig_category":"Pescader\u00cdas (al Por Menor)",
    "sg:phone":"+34 948 22 77 15",
    "sg:postcode":"31001",
    "sg:province":"Navarra",
    "wof:name":"Urzainqui Martinez Antonio",
    "wof:placetype":"venue"
},
  "geometry": {"coordinates":[-1.6439590454,42.8192558289],"type":"Point"}
}