{
  "type": "Feature",
  "properties": {
    "addr:full":"Avda Juan Carlos I, 16 Haro La Rioja 26200",
    "addr:housenumber":"16",
    "addr:postcode":"26200",
    "addr:street":"Avda Juan Carlos I",
    "iso:country":"ES",
    "sg:address":"Avda Juan Carlos I, 16",
    "sg:city":"Haro",
    "sg:orig_category":"Electricidad: Instaladores",
    "sg:phone":"+34 941 30 41 86",
    "sg:postcode":"26200",
    "sg:province":"La Rioja",
    "wof:name":"Cueva Ria\u00f1o Santos",
    "wof:placetype":"venue"
},
  "geometry": {"coordinates":[-2.8490519524,42.5727462769],"type":"Point"}
}