{
  "type": "Feature",
  "properties": {
    "addr:full":"Calle de Luis De Hoyos Sainz, 162 Madrid Madrid 28030",
    "addr:housenumber":"162",
    "addr:postcode":"28030",
    "addr:street":"Calle De Luis De Hoyos Sainz",
    "iso:country":"ES",
    "sg:address":"Calle de Luis De Hoyos Sainz, 162",
    "sg:city":"Madrid",
    "sg:orig_category":"Centros Empresariales",
    "sg:phone":"+34 913 71 41 38",
    "sg:postcode":"28030",
    "sg:province":"Madrid",
    "wof:name":"O.s.l-punto Y Numero Cero S.l.",
    "wof:placetype":"venue"
},
  "geometry": {"coordinates":[-3.6302909851,40.4037704468],"type":"Point"}
}