{
  "type": "Feature",
  "properties": {
    "addr:full":"Plaz Salvador, 8 Sagunt Valencia 46500",
    "addr:housenumber":"8",
    "addr:postcode":"46500",
    "addr:street":"Salvador",
    "iso:country":"ES",
    "sg:address":"Plaz Salvador, 8",
    "sg:city":"Sagunt",
    "sg:orig_category":"Reposter\u00cdas",
    "sg:phone":"+34 962 66 23 65",
    "sg:postcode":"46500",
    "sg:province":"Valencia",
    "wof:name":"Alandi Perez Manuel",
    "wof:placetype":"venue"
},
  "geometry": {"coordinates":[-0.268643707,39.6750869751],"type":"Point"}
}