{
  "type": "Feature",
  "properties": {
    "iso:country":"ES",
    "sg:address":"Cra. Sant Jaume Domenys, S/n",
    "sg:city":"Banyeres Penedes",
    "sg:orig_category":"Asesor\u00cda Fiscal Y Jur\u00cddica",
    "sg:phone":"+34 977 67 79 10",
    "sg:postcode":"43711",
    "sg:province":"Tarragona",
    "wof:name":"Vandellos I Associats S.c.c.l.",
    "wof:placetype":"venue"
},
  "geometry": {"coordinates":[1.582654953,41.280216217],"type":"Point"}
}