{
  "type": "Feature",
  "properties": {
    "iso:country":"ES",
    "sg:address":"Calle de Valderribas, 21",
    "sg:city":"Madrid",
    "sg:orig_category":"Ropa Para Se\u00d1oras (al Por Menor)",
    "sg:phone":"+34 915 02 05 15",
    "sg:postcode":"28007",
    "sg:province":"Madrid",
    "wof:name":"Rios Gutierrez Maria Del Carmen De Los",
    "wof:placetype":"venue"
},
  "geometry": {"coordinates":[-3.6777150631,40.4056053162],"type":"Point"}
}