{
  "type": "Feature",
  "properties": {
    "iso:country":"ES",
    "sg:address":"Calle de Urbano Larruzea, 4",
    "sg:city":"Amorebieta",
    "sg:orig_category":"Tintes (fabricaci\u00d3n, Al Por Mayor)",
    "sg:phone":"+34 946 30 93 16",
    "sg:postcode":"48340",
    "sg:province":"Vizcaya",
    "wof:name":"Goiria Barroetabe\u00f1a Ana",
    "wof:placetype":"venue"
},
  "geometry": {"coordinates":[-2.7334759235,43.2191734314],"type":"Point"}
}