{
  "type": "Feature",
  "properties": {
    "addr:full":"Calle de Palacio Valdes, 2 Valladolid Valladolid 47005",
    "addr:housenumber":"2",
    "addr:postcode":"47005",
    "addr:street":"Calle De Palacio Valdes",
    "iso:country":"ES",
    "sg:address":"Calle de Palacio Valdes, 2",
    "sg:city":"Valladolid",
    "sg:orig_category":"Carnicer\u00cdas, Carnicer\u00cdas",
    "sg:phone":"+34 983 29 22 18",
    "sg:postcode":"47005",
    "sg:province":"Valladolid",
    "wof:name":"Bergara Merino Carlos",
    "wof:placetype":"venue"
},
  "geometry": {"coordinates":[-4.7124619484,41.6512374878],"type":"Point"}
}