{
  "type": "Feature",
  "properties": {
    "iso:country":"ES",
    "sg:address":"Calle de Mayor, 23",
    "sg:city":"Burgo Osma",
    "sg:orig_category":"Flores Y Plantas Naturales (al Por Mayor)",
    "sg:phone":"+34 975 34 04 02",
    "sg:postcode":"42300",
    "sg:province":"Soria",
    "wof:name":"Leon Gomez Maria Eugenia Del Carmen",
    "wof:placetype":"venue"
},
  "geometry": {"coordinates":[-3.0683391094,41.5867500305],"type":"Point"}
}