{
  "type": "Feature",
  "properties": {
    "addr:full":"Pg Lluis Companys, 25 S. Pere Ribes Barcelona 08810",
    "addr:housenumber":"25",
    "addr:postcode":"08810",
    "addr:street":"Pg Lluis Companys;S. Pere Ribes Barcelona",
    "iso:country":"ES",
    "sg:address":"Pg Lluis Companys, 25",
    "sg:city":"S. Pere Ribes",
    "sg:orig_category":"Reposter\u00cdas",
    "sg:phone":"+34 938 96 26 81",
    "sg:postcode":"08810",
    "sg:province":"Barcelona",
    "wof:name":"Forn De Pa Bonet S.cp.",
    "wof:placetype":"venue"
},
  "geometry": {"coordinates":[1.7684149742,41.2592544556],"type":"Point"}
}