{
  "type": "Feature",
  "properties": {
    "iso:country":"ES",
    "sg:address":"Av Generalitat, 51",
    "sg:city":"Barri Maritim De Comarruga",
    "sg:orig_category":"Quincaller\u00cda (al Por Menor)",
    "sg:phone":"+34 977 68 05 24",
    "sg:postcode":"43880",
    "sg:province":"Tarragona",
    "wof:name":"Tevonai S.l.",
    "wof:placetype":"venue"
},
  "geometry": {"coordinates":[1.5386699438,41.1833496094],"type":"Point"}
}