{
  "type": "Feature",
  "properties": {
    "iso:country":"ES",
    "sg:address":"Calle de Domingo Hergueta, 2",
    "sg:city":"Haro",
    "sg:orig_category":"Molduras, Junquillos, Listones Y Molduras Perforadas",
    "sg:phone":"+34 941 31 05 77",
    "sg:postcode":"26200",
    "sg:province":"La Rioja",
    "wof:name":"Labarga Gordo Jose",
    "wof:placetype":"venue"
},
  "geometry": {"coordinates":[-2.8473556042,42.5727996826],"type":"Point"}
}