{
  "type": "Feature",
  "properties": {
    "addr:full":"Calle de Puerto Rico, 7 Majadahonda Madrid 28220",
    "addr:housenumber":"7",
    "addr:postcode":"28220",
    "addr:street":"Calle De Puerto Rico",
    "iso:country":"ES",
    "sg:address":"Calle de Puerto Rico, 7",
    "sg:city":"Majadahonda",
    "sg:orig_category":"M\u00c9dicos: Estomatolog\u00cda",
    "sg:phone":"+34 916 38 67 38",
    "sg:postcode":"28220",
    "sg:province":"Madrid",
    "wof:name":"Spezzi  Isabel Cristina",
    "wof:placetype":"venue"
},
  "geometry": {"coordinates":[-3.871514082,40.4758987427],"type":"Point"}
}