{
  "type": "Feature",
  "properties": {
    "iso:country":"ES",
    "sg:address":"Carrer de Xaloc, 10",
    "sg:city":"Buvisa",
    "sg:orig_category":"Impresiones Sobre Tela",
    "sg:phone":"+34 937 52 42 12",
    "sg:postcode":"08338",
    "sg:province":"Barcelona",
    "wof:name":"Mundo Dise\u00f1o 2000 S.l.",
    "wof:placetype":"venue"
},
  "geometry": {"coordinates":[2.3502030373,41.5012817383],"type":"Point"}
}