{
  "type": "Feature",
  "properties": {
    "addr:full":"Carrer de Maria Escalfet, 2 Castellar Valles Barcelona 08211",
    "addr:housenumber":"2",
    "addr:postcode":"08211",
    "addr:street":"Carrer De Maria Escalfet",
    "iso:country":"ES",
    "sg:address":"Carrer de Maria Escalfet, 2",
    "sg:city":"Castellar Valles",
    "sg:orig_category":"Herboristas (al Por Menor)",
    "sg:phone":"+34 937 47 20 59",
    "sg:postcode":"08211",
    "sg:province":"Barcelona",
    "wof:name":"Guillamat Segura Daniel",
    "wof:placetype":"venue"
},
  "geometry": {"coordinates":[2.0889589787,41.6193466187],"type":"Point"}
}