{
  "type": "Feature",
  "properties": {
    "addr:full":"Calle de Guitarrista Tarrega, 28 Alcora Castell\u00f3n 12110",
    "addr:housenumber":"28",
    "addr:postcode":"12110",
    "addr:street":"Calle De Guitarrista Tarrega;Castello\u0301N",
    "iso:country":"ES",
    "sg:address":"Calle de Guitarrista Tarrega, 28",
    "sg:city":"Alcora",
    "sg:orig_category":"Contenedores (mercanc\u00cdas)",
    "sg:phone":"+34 964 36 00 61",
    "sg:postcode":"12110",
    "sg:province":"Castell\u00f3n",
    "wof:name":"Eugenio Pallares Vicente",
    "wof:placetype":"venue"
},
  "geometry": {"coordinates":[-0.2152179927,40.0702476501],"type":"Point"}
}