{
  "type": "Feature",
  "properties": {
    "iso:country":"ES",
    "sg:address":"Calle de Poeta Ramon De Garciasol, 37",
    "sg:city":"Guadalajara",
    "sg:orig_category":"Periodistas Profesionales",
    "sg:phone":"+34 949 20 30 09",
    "sg:postcode":"19004",
    "sg:province":"Guadalajara",
    "wof:name":"Barra Toquero Santiago",
    "wof:placetype":"venue"
},
  "geometry": {"coordinates":[-3.1802930832,40.6347732544],"type":"Point"}
}