{
  "type": "Feature",
  "properties": {
    "iso:country":"ES",
    "sg:address":"Cmno Venta, 1",
    "sg:city":"Columbrianos",
    "sg:orig_category":"Centros De Educaci\u00d3n Especial",
    "sg:phone":"+34 987 42 37 10",
    "sg:postcode":"24490",
    "sg:province":"Le\u00f3n",
    "wof:name":"Colegio Rural Agrupado De Columbrianos",
    "wof:placetype":"venue"
},
  "geometry": {"coordinates":[-6.6118087769,42.5740661621],"type":"Point"}
}