{
  "type": "Feature",
  "properties": {
    "iso:country":"ES",
    "sg:address":"Calle de Arinaga, 15",
    "sg:city":"Palmas De Gran Canaria",
    "sg:orig_category":"Fabricaci\u00d3n De Harinas, S\u00c9molas, Productos De Elaboraci\u00d3n Del Grano",
    "sg:phone":"+34 928 48 05 68",
    "sg:postcode":"35010",
    "sg:province":"Las Palmas",
    "wof:name":"Molinera De Schamann S. A.",
    "wof:placetype":"venue"
},
  "geometry": {"coordinates":[-15.4585647583,28.1058063507],"type":"Point"}
}