{
  "type": "Feature",
  "properties": {
    "addr:full":"Plaz Nueva, 13 Ribesalbes Castell\u00f3n 12210",
    "addr:housenumber":"13",
    "addr:postcode":"12210",
    "addr:street":"Plaz Nueva;Castello\u0301N",
    "iso:country":"ES",
    "sg:address":"Plaz Nueva, 13",
    "sg:city":"Ribesalbes",
    "sg:orig_category":"Mataderos De Poller\u00cda",
    "sg:phone":"+34 964 62 50 37",
    "sg:postcode":"12210",
    "sg:province":"Castell\u00f3n",
    "wof:name":"Sociedad De Fomento Agricola Castellonense S.a.",
    "wof:placetype":"venue"
},
  "geometry": {"coordinates":[-0.2735399902,40.0291213989],"type":"Point"}
}