{
  "type": "Feature",
  "properties": {
    "iso:country":"ES",
    "sg:address":"Calle de Darsena, S/n",
    "sg:city":"Santo\u00f1a",
    "sg:classifiers":[
        {
            "category":"Recreation",
            "type":"Entertainment"
        }
    ],
    "sg:phone":"+34 942 66 02 12",
    "sg:postcode":"39740",
    "sg:province":"Cantabria",
    "sg:tags":[
        "caza",
        "pr\u00c1ctica",
        "la",
        "de",
        "pesca",
        "y"
    ],
    "wof:name":"Cofradia De Pescadores De Santo\u00d1a",
    "wof:placetype":"venue"
},
  "geometry": {"coordinates":[-3.4613239765,43.441734314],"type":"Point"}
}