{
  "type": "Feature",
  "properties": {
    "addr:full":"Calle de Tulipan, 3 Loma Cabrera Almer\u00eda 04120",
    "addr:housenumber":"3",
    "addr:postcode":"04120",
    "addr:street":"Calle De Tulipan;Cabrera Almeri\u0301A",
    "iso:country":"ES",
    "sg:address":"Calle de Tulipan, 3",
    "sg:city":"Loma Cabrera",
    "sg:orig_category":"Laboratorios Y Trabajos De Fotograf\u00cda, V\u00cddeo Y Cine",
    "sg:phone":"+34 950 29 11 34",
    "sg:postcode":"04120",
    "sg:province":"Almer\u00eda",
    "wof:name":"Carre\u00f1o Calvo Francisca",
    "wof:placetype":"venue"
},
  "geometry": {"coordinates":[-2.3839790821,36.858039856],"type":"Point"}
}