{
  "type": "Feature",
  "properties": {
    "addr:full":"Poli Poligon 27, S/n Manacor Islas Baleares 07500",
    "addr:housenumber":"27 s / n",
    "addr:postcode":"07500",
    "addr:street":"Poligon",
    "iso:country":"ES",
    "sg:address":"Poli Poligon 27, S/n",
    "sg:city":"Manacor",
    "sg:orig_category":"Caf\u00c9s, Bares, Cervecer\u00cdas",
    "sg:phone":"+34 971 18 23 24",
    "sg:postcode":"07500",
    "sg:province":"Islas Baleares",
    "wof:name":"Crepereria Colon 2003 Sl",
    "wof:placetype":"venue"
},
  "geometry": {"coordinates":[3.2279529572,39.564037323],"type":"Point"}
}