{
  "type": "Feature",
  "properties": {
    "iso:country":"ES",
    "sg:address":"Carrer de Major, 11",
    "sg:city":"Reus",
    "sg:orig_category":"Fabricaci\u00d3n De Sobres, Bolsas Y Fundas",
    "sg:phone":"+34 977 12 87 98",
    "sg:postcode":"43201",
    "sg:province":"Tarragona",
    "wof:name":"Chivite 1947 S.l.",
    "wof:placetype":"venue"
},
  "geometry": {"coordinates":[1.1090170145,41.1544532776],"type":"Point"}
}