{
  "type": "Feature",
  "properties": {
    "addr:full":"Pg Gracia, 120 Barcelona Barcelona 08008",
    "addr:housenumber":"120",
    "addr:postcode":"08008",
    "addr:street":"Pg Gracia",
    "iso:country":"ES",
    "sg:address":"Pg Gracia, 120",
    "sg:city":"Barcelona",
    "sg:orig_category":"Papeler\u00cdas, Librer\u00cdas",
    "sg:phone":"+34 932 37 92 22",
    "sg:postcode":"08008",
    "sg:province":"Barcelona",
    "wof:name":"Nouprint Servei Grafic Integral S.l.",
    "wof:placetype":"venue"
},
  "geometry": {"coordinates":[2.1588509083,41.3974571228],"type":"Point"}
}