{
  "type": "Feature",
  "properties": {
    "addr:full":"Carrer de Joan Guell, 107 Barcelona Barcelona 08028",
    "addr:housenumber":"107",
    "addr:postcode":"08028",
    "addr:street":"Carrer De Joan Guell",
    "iso:country":"ES",
    "sg:address":"Carrer de Joan Guell, 107",
    "sg:city":"Barcelona",
    "sg:orig_category":"Molduras, Junquillos, Listones Y Molduras Perforadas",
    "sg:phone":"+34 933 39 10 26",
    "sg:postcode":"08028",
    "sg:province":"Barcelona",
    "wof:name":"Prada Florez Magaly",
    "wof:placetype":"venue"
},
  "geometry": {"coordinates":[2.1323580742,41.380695343],"type":"Point"}
}