{
  "type": "Feature",
  "properties": {
    "iso:country":"ES",
    "sg:address":"Calle de Cobalto, 50",
    "sg:city":"Valladolid",
    "sg:orig_category":"Calderer\u00cda",
    "sg:phone":"+34 983 29 51 14",
    "sg:postcode":"47012",
    "sg:province":"Valladolid",
    "wof:name":"Talleres Pisuerga S.a.",
    "wof:placetype":"venue"
},
  "geometry": {"coordinates":[-4.7118730545,41.6178741455],"type":"Point"}
}