{
  "type": "Feature",
  "properties": {
    "iso:country":"ES",
    "sg:address":"Calle de Princesa, 31",
    "sg:city":"Madrid",
    "sg:orig_category":"Transportes Urbanos Y Regionales Para Personas",
    "sg:phone":"+34 915 41 13 14",
    "sg:postcode":"28008",
    "sg:province":"Madrid",
    "wof:name":"Asociacion Empresas Gestoras De Transportes Urbanos Colectivos",
    "wof:placetype":"venue"
},
  "geometry": {"coordinates":[-3.71443367,40.4280128479],"type":"Point"}
}