{
  "type": "Feature",
  "properties": {
    "addr:full":"Vial Industrial, 6 Ihurre Guip\u00f9zcoa 20212",
    "addr:postcode":"20212",
    "addr:street":"Guipu\u0300Zcoa",
    "iso:country":"ES",
    "sg:address":"Vial Industrial, 6",
    "sg:city":"Ihurre",
    "sg:orig_category":"Alquiler De Gr\u00daas",
    "sg:phone":"+34 943 88 13 44",
    "sg:postcode":"20212",
    "sg:province":"Guip\u00f9zcoa",
    "wof:name":"Gruas De Obras S.a.",
    "wof:placetype":"venue"
},
  "geometry": {"coordinates":[-2.2013700008,43.0282554626],"type":"Point"}
}