{
  "type": "Feature",
  "properties": {
    "iso:country":"ES",
    "sg:address":"Calle de Artemi Semidan, 17",
    "sg:city":"Palmas De Gran Canaria",
    "sg:orig_category":"Molduras, Junquillos, Listones Y Molduras Perforadas",
    "sg:phone":"+34 928 46 02 47",
    "sg:postcode":"35009",
    "sg:province":"Las Palmas",
    "wof:name":"Millares Montimui\u00f1o Juan",
    "wof:placetype":"venue"
},
  "geometry": {"coordinates":[-15.4256067276,28.1500988007],"type":"Point"}
}