{
  "type": "Feature",
  "properties": {
    "iso:country":"ES",
    "sg:address":"Plaz Pla, El, 25",
    "sg:city":"Burriana",
    "sg:orig_category":"Cajas De Ahorro",
    "sg:phone":"+34 964 59 11 34",
    "sg:postcode":"12530",
    "sg:province":"Castell\u00f3n",
    "sg:website":"www.ibercaja.es",
    "wof:name":"Caja De Ahorros Y Monte De Piedad De Zaragoza Aragon Y Rioja",
    "wof:placetype":"venue"
},
  "geometry": {"coordinates":[-0.0852660015,39.8894195557],"type":"Point"}
}