{
  "type": "Feature",
  "properties": {
    "iso:country":"ES",
    "sg:address":"Calle de Zamora, S/n",
    "sg:city":"San Esteban Del Molar",
    "sg:orig_category":"Material Y Herramientas Agr\u00cdcolas",
    "sg:phone":"+34 980 66 53 30",
    "sg:postcode":"49650",
    "sg:province":"Zamora",
    "wof:name":"Martinez Vega Jacinto",
    "wof:placetype":"venue"
},
  "geometry": {"coordinates":[-5.5522861481,41.93775177],"type":"Point"}
}