{
  "type": "Feature",
  "properties": {
    "iso:country":"ES",
    "sg:address":"Calle de Agintari Kalea, 17",
    "sg:city":"Tolosa",
    "sg:orig_category":"Molduras, Junquillos, Listones Y Molduras Perforadas",
    "sg:phone":"+34 943 67 07 20",
    "sg:postcode":"20400",
    "sg:province":"Guip\u00f9zcoa",
    "wof:name":"Ameztoi Olasagasti,maria De Las Mercedes",
    "wof:placetype":"venue"
},
  "geometry": {"coordinates":[-2.0716910362,43.1389961243],"type":"Point"}
}