{
  "type": "Feature",
  "properties": {
    "addr:full":"A Juan Hernandez, 2 Baza Granada 18800",
    "addr:postcode":"18800",
    "addr:street":"Hernandez",
    "iso:country":"ES",
    "sg:address":"A Juan Hernandez, 2",
    "sg:city":"Baza",
    "sg:orig_category":"Cajas De Ahorro",
    "sg:phone":"+34 958 71 28 69",
    "sg:postcode":"18800",
    "sg:province":"Granada",
    "wof:name":"Caixa D'estalvis I Pensions De Barcelona",
    "wof:placetype":"venue"
},
  "geometry": {"coordinates":[-2.7732279301,37.4888114929],"type":"Point"}
}