{
  "type": "Feature",
  "properties": {
    "addr:full":"Carr Llibertat, 1 Linyola Lleida 25240",
    "addr:housenumber":"1",
    "addr:postcode":"25240",
    "addr:street":"Carr Llibertat",
    "iso:country":"ES",
    "sg:address":"Carr Llibertat, 1",
    "sg:city":"Linyola",
    "sg:orig_category":"Reposter\u00cdas",
    "sg:phone":"+34 973 57 53 33",
    "sg:postcode":"25240",
    "sg:province":"Lleida",
    "wof:name":"Fleca Pastisseria Castella S.l.",
    "wof:placetype":"venue"
},
  "geometry": {"coordinates":[0.9043409824,41.7109413147],"type":"Point"}
}