{
  "type": "Feature",
  "properties": {
    "iso:country":"ES",
    "sg:address":"Calle de Golondrina - Aldea Moret, 10",
    "sg:city":"Caceres",
    "sg:orig_category":"Panader\u00cdas, Panader\u00cdas",
    "sg:phone":"+34 927 23 48 80",
    "sg:postcode":"10195",
    "sg:province":"C\u00e1ceres",
    "wof:name":"Jimenez Rodriguez Manuel",
    "wof:placetype":"venue"
},
  "geometry": {"coordinates":[-6.3927369118,39.4524269104],"type":"Point"}
}