{
  "type": "Feature",
  "properties": {
    "addr:full":"Calle de Villa (la), 4 Espinar Segovia 40400",
    "addr:housenumber":"4",
    "addr:postcode":"40400",
    "addr:street":"Calle De Villa La",
    "iso:country":"ES",
    "sg:address":"Calle de Villa (la), 4",
    "sg:city":"Espinar",
    "sg:orig_category":"Molduras, Junquillos, Listones Y Molduras Perforadas",
    "sg:phone":"+34 921 18 13 39",
    "sg:postcode":"40400",
    "sg:province":"Segovia",
    "wof:name":"Matute Manso C.b.",
    "wof:placetype":"venue"
},
  "geometry": {"coordinates":[-4.2479891777,40.7184829712],"type":"Point"}
}