{
  "type": "Feature",
  "properties": {
    "iso:country":"ES",
    "sg:address":"Trav Dalt, 93",
    "sg:city":"Barcelona",
    "sg:orig_category":"Servicios De Higiene Y Peluquer\u00cda Para Perros Y Gatos",
    "sg:phone":"+34 932 10 57 02",
    "sg:postcode":"08024",
    "sg:province":"Barcelona",
    "wof:name":"Mu\u00f1oz Segu Carlos",
    "wof:placetype":"venue"
},
  "geometry": {"coordinates":[2.1572370529,41.4112548828],"type":"Point"}
}