{
  "type": "Feature",
  "properties": {
    "iso:country":"ES",
    "sg:address":"Calle de Ordesa, 2",
    "sg:city":"Sabi\u00f1anigo",
    "sg:orig_category":"Arquitectos",
    "sg:phone":"+34 974 48 06 19",
    "sg:postcode":"22600",
    "sg:province":"Huesca",
    "wof:name":"Orientacion Y Clima S.l.",
    "wof:placetype":"venue"
},
  "geometry": {"coordinates":[-0.3649390042,42.5191993713],"type":"Point"}
}