{
  "type": "Feature",
  "properties": {
    "iso:country":"ES",
    "sg:address":"Calle de Federico Garcia Lorca, 8",
    "sg:city":"Zaragoza",
    "sg:orig_category":"Perfumer\u00cda Y Cosm\u00c9tica (fabricaci\u00d3n, Al Por Mayor)",
    "sg:phone":"+34 976 38 94 97",
    "sg:postcode":"50007",
    "sg:province":"Zaragoza",
    "wof:name":"Dispalban S.l.",
    "wof:placetype":"venue"
},
  "geometry": {"coordinates":[-0.878847003,41.6347160339],"type":"Point"}
}