{
  "type": "Feature",
  "properties": {
    "addr:full":"Estd Catabois, 122 Ferrol A Coru\u00f1a 15405",
    "addr:housenumber":"122",
    "addr:postcode":"15405",
    "addr:street":"Catabois;A Corun\u0303A",
    "iso:country":"ES",
    "sg:address":"Estd Catabois, 122",
    "sg:city":"Ferrol",
    "sg:orig_category":"Peluqueros: De Se\u00d1oras",
    "sg:phone":"+34 981 31 48 05",
    "sg:postcode":"15405",
    "sg:province":"A Coru\u00f1a",
    "wof:name":"Souto Dopico Remedios",
    "wof:placetype":"venue"
},
  "geometry": {"coordinates":[-8.2315092087,43.4922981262],"type":"Point"}
}