{
  "type": "Feature",
  "properties": {
    "addr:full":"Calle de Panama, 18 Vitoria-gasteiz \u00c1lava 01012",
    "addr:housenumber":"18",
    "addr:postcode":"01012",
    "addr:street":"Calle De Panama",
    "iso:country":"ES",
    "sg:address":"Calle de Panama, 18",
    "sg:city":"Vitoria-gasteiz",
    "sg:orig_category":"Molduras, Junquillos, Listones Y Molduras Perforadas",
    "sg:phone":"+34 945 28 31 95",
    "sg:postcode":"01012",
    "sg:province":"\u00c1lava",
    "wof:name":"Union 84 S.a.",
    "wof:placetype":"venue"
},
  "geometry": {"coordinates":[-2.6763041019,42.8582687378],"type":"Point"}
}