{
  "type": "Feature",
  "properties": {
    "iso:country":"ES",
    "sg:address":"Luga Rabales, S/n",
    "sg:city":"Balsapintada",
    "sg:orig_category":"Discotecas Y Salas De Baile",
    "sg:phone":"+34 968 15 97 19",
    "sg:postcode":"30332",
    "sg:province":"Murcia",
    "wof:name":"Garcia Hernandez Pedro",
    "wof:placetype":"venue"
},
  "geometry": {"coordinates":[-1.1106909513,37.732383728],"type":"Point"}
}