{
  "type": "Feature",
  "properties": {
    "addr:full":"Avda Buenos Aires, 18 Porri\u00f1o Pontevedra 36400",
    "addr:housenumber":"18",
    "addr:postcode":"36400",
    "addr:street":"Avda Buenos Aires",
    "iso:country":"ES",
    "sg:address":"Avda Buenos Aires, 18",
    "sg:city":"Porri\u00f1o",
    "sg:orig_category":"Accesorios Para Tintorer\u00cdas, Limpieza En Seco",
    "sg:phone":"+34 986 33 98 03",
    "sg:postcode":"36400",
    "sg:province":"Pontevedra",
    "wof:name":"Distribuciones Alonso Lusqui\u00f1os S.l.",
    "wof:placetype":"venue"
},
  "geometry": {"coordinates":[-8.6290750504,42.1607933044],"type":"Point"}
}