{
  "type": "Feature",
  "properties": {
    "iso:country":"ES",
    "sg:address":"Calle de Gerona, 2",
    "sg:city":"Mostoles",
    "sg:orig_category":"Zapatos (al Por Menor)",
    "sg:phone":"+34 916 64 25 10",
    "sg:postcode":"28938",
    "sg:province":"Madrid",
    "wof:name":"Calzados Andrea Ruiz S.l.",
    "wof:placetype":"venue"
},
  "geometry": {"coordinates":[-3.8626680374,40.3196144104],"type":"Point"}
}