{
  "type": "Feature",
  "properties": {
    "iso:country":"ES",
    "sg:address":"Plaz Mayor, 24",
    "sg:city":"Salamanca",
    "sg:orig_category":"Zapatos (al Por Menor)",
    "sg:phone":"+34 923 26 89 39",
    "sg:postcode":"37002",
    "sg:province":"Salamanca",
    "wof:name":"Areces Y Perez S. L.",
    "wof:placetype":"venue"
},
  "geometry": {"coordinates":[-5.6640949249,40.9649963379],"type":"Point"}
}