{
  "type": "Feature",
  "properties": {
    "iso:country":"ES",
    "sg:address":"Calle de San Juan Bautista, 1",
    "sg:city":"Arroyo De La Miel-benalmadena Costa",
    "sg:orig_category":"Panader\u00cdas, Panader\u00cdas",
    "sg:phone":"+34 952 44 01 30",
    "sg:postcode":"29631",
    "sg:province":"M\u00e1laga",
    "wof:name":"Segado Garcia Juan",
    "wof:placetype":"venue"
},
  "geometry": {"coordinates":[-4.5482521057,36.6017608643],"type":"Point"}
}