{
  "type": "Feature",
  "properties": {
    "iso:country":"ES",
    "sg:address":"Calle de Duquesa De Parcent, 34",
    "sg:city":"Madrid",
    "sg:orig_category":"Fabricaci\u00d3n, Instalaci\u00d3n De Armarios",
    "sg:phone":"+34 914 62 89 02",
    "sg:postcode":"28047",
    "sg:province":"Madrid",
    "wof:name":"Gonzalez Barranco Yolanda",
    "wof:placetype":"venue"
},
  "geometry": {"coordinates":[-3.7463850975,40.3951950073],"type":"Point"}
}