{
  "type": "Feature",
  "properties": {
    "iso:country":"ES",
    "sg:address":"Calle de Uria, 40",
    "sg:city":"Oviedo",
    "sg:orig_category":"M\u00c9dicos: Estomatolog\u00cda",
    "sg:phone":"+34 985 21 58 07",
    "sg:postcode":"33003",
    "sg:province":"Asturias",
    "wof:name":"Picatto Hernandez Luis Bartolome",
    "wof:placetype":"venue"
},
  "geometry": {"coordinates":[-5.8509697914,43.3640136719],"type":"Point"}
}