{
  "type": "Feature",
  "properties": {
    "addr:full":"Poli Cortijo Real - Plg.indust., 22 Algeciras C\u00e1diz 11206",
    "addr:housenumber":"22;ca\u0301diz",
    "addr:postcode":"11206",
    "addr:street":"Plg.Indust.",
    "iso:country":"ES",
    "sg:address":"Poli Cortijo Real - Plg.indust., 22",
    "sg:city":"Algeciras",
    "sg:orig_category":"Rectificaci\u00d3n, Mecanizado, Fresado",
    "sg:phone":"+34 956 57 45 68",
    "sg:postcode":"11206",
    "sg:province":"C\u00e1diz",
    "wof:name":"Merend S.l.",
    "wof:placetype":"venue"
},
  "geometry": {"coordinates":[-5.5359191895,36.1193008423],"type":"Point"}
}