{
  "type": "Feature",
  "properties": {
    "addr:full":"Soterra\u00f1a, S/n Soterra\u00d1a Asturias 33639",
    "addr:postcode":"33639",
    "addr:street":"Soterran\u0303A S / N Soterran\u0303A Asturias",
    "iso:country":"ES",
    "sg:address":"Soterra\u00f1a, S/n",
    "sg:city":"Soterra\u00d1a",
    "sg:orig_category":"Minerales (al Por Mayor)",
    "sg:phone":"+34 985 92 61 45",
    "sg:postcode":"33639",
    "sg:province":"Asturias",
    "wof:name":"Siderfluor S.a.",
    "wof:placetype":"venue"
},
  "geometry": {"coordinates":[-5.8464779854,43.1959037781],"type":"Point"}
}