{
  "type": "Feature",
  "properties": {
    "iso:country":"ES",
    "sg:address":"Calle de San Sebastian, 16",
    "sg:city":"Mota Cuervo",
    "sg:orig_category":"Telas Y Sedas (al Por Menor)",
    "sg:phone":"+34 967 18 00 30",
    "sg:postcode":"16630",
    "sg:province":"Cuenca",
    "wof:name":"Alcolado Carriazo Felix",
    "wof:placetype":"venue"
},
  "geometry": {"coordinates":[-2.8687036037,39.5022087097],"type":"Point"}
}