{
  "type": "Feature",
  "properties": {
    "iso:country":"ES",
    "sg:address":"Calle de Puebla De Valverde, 5",
    "sg:city":"Valencia",
    "sg:orig_category":"Delineantes",
    "sg:phone":"+34 963 57 10 97",
    "sg:postcode":"46014",
    "sg:province":"Valencia",
    "wof:name":"Implantacion De Tratamientos Y Dise\u00f1os Industriales S.l.",
    "wof:placetype":"venue"
},
  "geometry": {"coordinates":[-0.4017019868,39.4596824646],"type":"Point"}
}