{
  "type": "Feature",
  "properties": {
    "addr:full":"Carr Sargento Provisional, 16 Pai I Capellans Valencia 46930",
    "addr:housenumber":"16",
    "addr:postcode":"46930",
    "addr:street":"Carr Sargento Provisional",
    "iso:country":"ES",
    "sg:address":"Carr Sargento Provisional, 16",
    "sg:city":"Pai I Capellans",
    "sg:orig_category":"Fabricaci\u00d3n De Moldes Y Modelos",
    "sg:phone":"+34 961 59 70 82",
    "sg:postcode":"46930",
    "sg:province":"Valencia",
    "wof:name":"Matriceria De Inyeccion S. L.",
    "wof:placetype":"venue"
},
  "geometry": {"coordinates":[-0.4419890046,39.482711792],"type":"Point"}
}