{
  "type": "Feature",
  "properties": {
    "iso:country":"ES",
    "sg:address":"Poli Los Ca\u00d1os, S/n",
    "sg:city":"Zafra",
    "sg:orig_category":"Ropa De Casa (fabricaci\u00d3n, Al Por Mayor)",
    "sg:phone":"+34 924 55 32 62",
    "sg:postcode":"06300",
    "sg:province":"Badajoz",
    "wof:name":"Comercial Extreme\u00f1a Gomez Martinez S.l.",
    "wof:placetype":"venue"
},
  "geometry": {"coordinates":[-6.4134092331,38.4236793518],"type":"Point"}
}