{
  "type": "Feature",
  "properties": {
    "iso:country":"ES",
    "sg:address":"Calle de Vitoria, 258",
    "sg:city":"Burgos",
    "sg:orig_category":"Fabricaci\u00d3n, Importaci\u00d3n De L\u00c1mparas Y Bombillas",
    "sg:phone":"+34 947 47 18 47",
    "sg:postcode":"09007",
    "sg:province":"Burgos",
    "wof:name":"Ilumina Burgos S.l.",
    "wof:placetype":"venue"
},
  "geometry": {"coordinates":[-3.6629719734,42.3550643921],"type":"Point"}
}