{
  "type": "Feature",
  "properties": {
    "iso:country":"ES",
    "sg:address":"Luga Poligono Industrial, 38",
    "sg:city":"Cabanillas Campo",
    "sg:orig_category":"Agentes, Concesionarios Y Sucursales De Veh\u00cdculos",
    "sg:phone":"+34 949 20 71 93",
    "sg:postcode":"19171",
    "sg:province":"Guadalajara",
    "wof:name":"Autocarpe Concesionarios S.l.",
    "wof:placetype":"venue"
},
  "geometry": {"coordinates":[-3.2374420166,40.6377639771],"type":"Point"}
}