{
  "type": "Feature",
  "properties": {
    "addr:full":"Carr Sant Ramon, 22 Palafrugell Girona 17200",
    "addr:housenumber":"22",
    "addr:postcode":"17200",
    "addr:street":"Carr Sant Ramon",
    "iso:country":"ES",
    "sg:address":"Carr Sant Ramon, 22",
    "sg:city":"Palafrugell",
    "sg:orig_category":"Fabricaci\u00d3n, Importaci\u00d3n De L\u00c1mparas Y Bombillas",
    "sg:phone":"+34 972 30 26 46",
    "sg:postcode":"17200",
    "sg:province":"Girona",
    "wof:name":"Instalacions Fabrega S.c.",
    "wof:placetype":"venue"
},
  "geometry": {"coordinates":[3.1650640965,41.9139442444],"type":"Point"}
}