{
  "type": "Feature",
  "properties": {
    "addr:full":"Calle de Blas Y Ubide, 4 Calatayud Zaragoza 50300",
    "addr:housenumber":"4",
    "addr:postcode":"50300",
    "addr:street":"Calle De Blas Y Ubide",
    "iso:country":"ES",
    "sg:address":"Calle de Blas Y Ubide, 4",
    "sg:city":"Calatayud",
    "sg:orig_category":"Venta, Instalaci\u00d3n, Reparaci\u00d3n De Antenas Para Televisi\u00d3n",
    "sg:phone":"+34 976 88 41 53",
    "sg:postcode":"50300",
    "sg:province":"Zaragoza",
    "wof:name":"Alcaire Garcia Valentin Daniel",
    "wof:placetype":"venue"
},
  "geometry": {"coordinates":[-1.6402150393,41.3491172791],"type":"Point"}
}