{
  "type": "Feature",
  "properties": {
    "iso:country":"ES",
    "sg:address":"Calle de Joaquin Costa, 52",
    "sg:city":"Palmas De Gran Canaria",
    "sg:orig_category":"Agencias Y Agentes Comerciales, Representantes",
    "sg:phone":"+34 928 22 27 53",
    "sg:postcode":"35007",
    "sg:province":"Las Palmas",
    "wof:name":"Cerro Del Sol S. A.",
    "wof:placetype":"venue"
},
  "geometry": {"coordinates":[-15.4343166351,28.139503479],"type":"Point"}
}