{
  "type": "Feature",
  "properties": {
    "addr:full":"Calle de Flor De Pascua, 1 Acantilados De Los Gigantes Santa Cruz De Tenerife 38683",
    "addr:housenumber":"1",
    "addr:postcode":"38683",
    "addr:street":"Calle De Flor De Pascua",
    "iso:country":"ES",
    "sg:address":"Calle de Flor De Pascua, 1",
    "sg:city":"Acantilados De Los Gigantes",
    "sg:orig_category":"Supermercados Y Hipermercados",
    "sg:phone":"+34 922 86 17 09",
    "sg:postcode":"38683",
    "sg:province":"Santa Cruz De Tenerife",
    "wof:name":"Armando Flores S.l.",
    "wof:placetype":"venue"
},
  "geometry": {"coordinates":[-16.2548561096,28.4698104858],"type":"Point"}
}