{
  "type": "Feature",
  "properties": {
    "addr:full":"Barr Aretxalde, 43 Aretxalde Vizcaya 48196",
    "addr:housenumber":"43",
    "addr:postcode":"48196",
    "addr:street":"Aretxalde",
    "iso:country":"ES",
    "sg:address":"Barr Aretxalde, 43",
    "sg:city":"Aretxalde",
    "sg:orig_category":"Productores Recolectores, Venta Directa De Vinos",
    "sg:phone":"+34 944 55 64 20",
    "sg:postcode":"48196",
    "sg:province":"Vizcaya",
    "wof:name":"Ayarza Da\u00f1obeitia Domingo",
    "wof:placetype":"venue"
},
  "geometry": {"coordinates":[-2.8261504173,43.266708374],"type":"Point"}
}