{
  "type": "Feature",
  "properties": {
    "addr:full":"Carrer de Gran Canaria, S/n Granja Tarragona 43006",
    "addr:housenumber":"s / n",
    "addr:postcode":"43006",
    "addr:street":"Carrer De Gran Canaria",
    "iso:country":"ES",
    "sg:address":"Carrer de Gran Canaria, S/n",
    "sg:city":"Granja",
    "sg:orig_category":"Cajas De Ahorro",
    "sg:phone":"+34 977 55 12 08",
    "sg:postcode":"43006",
    "sg:province":"Tarragona",
    "sg:website":"www.caixapenedes.es",
    "wof:name":"Caixa D'estalvis Del Penedes",
    "wof:placetype":"venue"
},
  "geometry": {"coordinates":[1.2209249735,41.1154441833],"type":"Point"}
}