{
  "type": "Feature",
  "properties": {
    "addr:full":"Calle de Cuesta De San Antonio, 101 Aduanas Alicante 03730",
    "addr:housenumber":"101",
    "addr:postcode":"03730",
    "addr:street":"Calle De Cuesta;San Antonio",
    "iso:country":"ES",
    "sg:address":"Calle de Cuesta De San Antonio, 101",
    "sg:city":"Aduanas",
    "sg:orig_category":"Maquinaria Para Industrias Diversas",
    "sg:phone":"+34 966 46 05 92",
    "sg:postcode":"03730",
    "sg:province":"Alicante",
    "wof:name":"Mena-tracon Spain S.l.",
    "wof:placetype":"venue"
},
  "geometry": {"coordinates":[0.1812382936,38.8013839722],"type":"Point"}
}