{
  "type": "Feature",
  "properties": {
    "addr:full":"Cllo Gato, 2 Majadahonda Madrid 28220",
    "addr:postcode":"28220",
    "iso:country":"ES",
    "sg:address":"Cllo Gato, 2",
    "sg:city":"Majadahonda",
    "sg:orig_category":"Alquiler De Veh\u00cdculos: Turismos Y Utilitarios",
    "sg:phone":"+34 916 34 30 04",
    "sg:postcode":"28220",
    "sg:province":"Madrid",
    "wof:name":"Gutierrez Martinez Felipe",
    "wof:placetype":"venue"
},
  "geometry": {"coordinates":[-3.8737080097,40.4735069275],"type":"Point"}
}