{
  "type": "Feature",
  "properties": {
    "addr:full":"Calle de Rodriguez Arias, 30 Bilbao Vizcaya 48011",
    "addr:housenumber":"30",
    "addr:postcode":"48011",
    "addr:street":"Calle De Rodriguez Arias",
    "iso:country":"ES",
    "sg:address":"Calle de Rodriguez Arias, 30",
    "sg:city":"Bilbao",
    "sg:orig_category":"Ropa Para Ni\u00d1os (al Por Menor)",
    "sg:phone":"+34 944 42 11 98",
    "sg:postcode":"48011",
    "sg:province":"Vizcaya",
    "wof:name":"Moda Mu\u00f1ecas, S.l.",
    "wof:placetype":"venue"
},
  "geometry": {"coordinates":[-2.9401278496,43.2629852295],"type":"Point"}
}