{
  "type": "Feature",
  "properties": {
    "addr:full":"Avda Tomas Roca Bosch, 6 Puerto Rico Las Palmas 35130",
    "addr:housenumber":"6",
    "addr:postcode":"35130",
    "addr:street":"Avda Tomas Roca Bosch;Rico",
    "iso:country":"ES",
    "sg:address":"Avda Tomas Roca Bosch, 6",
    "sg:city":"Puerto Rico",
    "sg:orig_category":"Asesor\u00cda De Formaci\u00d3n Y Gesti\u00d3n De Personal",
    "sg:phone":"+34 928 56 21 76",
    "sg:postcode":"35130",
    "sg:province":"Las Palmas",
    "wof:name":"Hassan Abrante Jose Juan",
    "wof:placetype":"venue"
},
  "geometry": {"coordinates":[-15.7080802917,27.7902240753],"type":"Point"}
}