{
  "type": "Feature",
  "properties": {
    "addr:full":"Pg Vilanova, 25 Sitges Barcelona 08870",
    "addr:housenumber":"25",
    "addr:postcode":"08870",
    "addr:street":"Vilanova",
    "iso:country":"ES",
    "sg:address":"Pg Vilanova, 25",
    "sg:city":"Sitges",
    "sg:orig_category":"Molduras, Junquillos, Listones Y Molduras Perforadas",
    "sg:phone":"+34 938 94 50 26",
    "sg:postcode":"08870",
    "sg:province":"Barcelona",
    "wof:name":"Ortega Perea Carmen",
    "wof:placetype":"venue"
},
  "geometry": {"coordinates":[1.8060480356,41.237865448],"type":"Point"}
}