{
  "type": "Feature",
  "properties": {
    "iso:country":"ES",
    "sg:address":"Calle de Adelardo Covarsi, 1",
    "sg:city":"Zafra",
    "sg:orig_category":"Centros Empresariales",
    "sg:phone":"+34 924 55 02 92",
    "sg:postcode":"06300",
    "sg:province":"Badajoz",
    "wof:name":"Rodriguez Jimenez Felix",
    "wof:placetype":"venue"
},
  "geometry": {"coordinates":[-6.4133672714,38.4234313965],"type":"Point"}
}