{
  "type": "Feature",
  "properties": {
    "addr:full":"Calvo Sotelo, 31 Alicun De Ortega Granada 18538",
    "addr:housenumber":"31",
    "addr:postcode":"18538",
    "addr:street":"Calvo Sotelo",
    "iso:country":"ES",
    "sg:address":"Calvo Sotelo, 31",
    "sg:city":"Alicun De Ortega",
    "sg:classifiers":[
        {
            "category":"Taxi",
            "type":"Transportation"
        }
    ],
    "sg:phone":"+34 958 67 76 75",
    "sg:postcode":"18538",
    "sg:province":"Granada",
    "wof:name":"Medina Vi\u00f1eglas Juan",
    "wof:placetype":"venue"
},
  "geometry": {"coordinates":[-3.1049690247,37.5899238586],"type":"Point"}
}