{
  "type": "Feature",
  "properties": {
    "addr:full":"Calle de Carlos Cia\u00d1o Canto, 3 Villaviciosa Asturias 33300",
    "addr:housenumber":"3",
    "addr:postcode":"33300",
    "addr:street":"Calle De Carlos Cian\u0303O Canto",
    "iso:country":"ES",
    "sg:address":"Calle de Carlos Cia\u00d1o Canto, 3",
    "sg:city":"Villaviciosa",
    "sg:orig_category":"Distribuci\u00d3n De Petr\u00d3leo Y Derivados",
    "sg:phone":"+34 985 89 00 32",
    "sg:postcode":"33300",
    "sg:province":"Asturias",
    "wof:name":"Mayfal S.l.",
    "wof:placetype":"venue"
},
  "geometry": {"coordinates":[-5.4308180809,43.4838905334],"type":"Point"}
}