{
  "type": "Feature",
  "properties": {
    "addr:full":"Carr Castella-leo (de), 15 Grau I Platja Valencia 46730",
    "addr:housenumber":"15",
    "addr:postcode":"46730",
    "addr:street":"Carr Castella-Leo De",
    "iso:country":"ES",
    "sg:address":"Carr Castella-leo (de), 15",
    "sg:city":"Grau I Platja",
    "sg:orig_category":"Carnicer\u00cdas, Carnicer\u00cdas",
    "sg:phone":"+34 962 84 27 37",
    "sg:postcode":"46730",
    "sg:province":"Valencia",
    "wof:name":"Berto Chova Maria",
    "wof:placetype":"venue"
},
  "geometry": {"coordinates":[-0.1747509986,39.0130081177],"type":"Point"}
}