{
  "type": "Feature",
  "properties": {
    "addr:full":"Calle de Salabert, 39 Valencia Valencia 46018",
    "addr:housenumber":"39",
    "addr:postcode":"46018",
    "addr:street":"Calle De Salabert",
    "iso:country":"ES",
    "sg:address":"Calle de Salabert, 39",
    "sg:city":"Valencia",
    "sg:orig_category":"Agencias Y Agentes Comerciales, Representantes",
    "sg:phone":"+34 963 57 88 13",
    "sg:postcode":"46018",
    "sg:province":"Valencia",
    "wof:name":"Abril Garcia Jose",
    "wof:placetype":"venue"
},
  "geometry": {"coordinates":[-0.395567,39.463406],"type":"Point"}
}