{
  "type": "Feature",
  "properties": {
    "iso:country":"ES",
    "sg:address":"Calle de Duero, S/n",
    "sg:city":"Bosque",
    "sg:orig_category":"Locales Y Clases De Danza",
    "sg:phone":"+34 916 16 86 79",
    "sg:postcode":"28670",
    "sg:province":"Madrid",
    "wof:name":"Pv Dance Chasse",
    "wof:placetype":"venue"
},
  "geometry": {"coordinates":[-3.9285619259,40.3885040283],"type":"Point"}
}