{
  "type": "Feature",
  "properties": {
    "iso:country":"ES",
    "sg:address":"Calle de Carlos Gangoiti, 38",
    "sg:city":"Gernika-lumo",
    "sg:orig_category":"Transportes Por Carretera: Lotes Completos, Mercanc\u00cdas Diversas",
    "sg:phone":"+34 946 25 09 55",
    "sg:postcode":"48300",
    "sg:province":"Vizcaya",
    "wof:name":"Daniel Y Xabier Tamayo Perez C.b.",
    "wof:placetype":"venue"
},
  "geometry": {"coordinates":[-2.678442955,43.3196640015],"type":"Point"}
}