{
  "type": "Feature",
  "properties": {
    "iso:country":"ES",
    "sg:address":"Av. J. Pere Jacas, 38",
    "sg:city":"S. Pere Ribes",
    "sg:orig_category":"Postigos, Persianas Y Celos\u00cdas",
    "sg:phone":"+34 938 96 06 69",
    "sg:postcode":"08810",
    "sg:province":"Barcelona",
    "wof:name":"Grup 7 Persianes I Tancaments S.l.",
    "wof:placetype":"venue"
},
  "geometry": {"coordinates":[1.768658042,41.2592658997],"type":"Point"}
}