{
  "type": "Feature",
  "properties": {
    "addr:full":"G.v. Pau Casals, S/n Suredes D'en Mairo-grecs-muntanyeta Girona 17480",
    "addr:housenumber":"s",
    "addr:postcode":"17480",
    "addr:street":"/ N Suredes D'En Mairo-Grecs-Muntanyeta",
    "iso:country":"ES",
    "sg:address":"G.v. Pau Casals, S/n",
    "sg:city":"Suredes D'en Mairo-grecs-muntanyeta",
    "sg:orig_category":"Supermercados Y Hipermercados",
    "sg:phone":"+34 972 15 43 35",
    "sg:postcode":"17480",
    "sg:province":"Girona",
    "wof:name":"Caprabo S.a.",
    "wof:placetype":"venue"
},
  "geometry": {"coordinates":[2.8156359196,41.9840202332],"type":"Point"}
}