{
  "type": "Feature",
  "properties": {
    "addr:full":"Calle de Veintinueve De Abril, 58 Palmas De Gran Canaria Las Palmas 35007",
    "addr:postcode":"35007",
    "addr:street":"Calle De Veintinueve De Abril 58",
    "iso:country":"ES",
    "sg:address":"Calle de Veintinueve De Abril, 58",
    "sg:city":"Palmas De Gran Canaria",
    "sg:orig_category":"Importaci\u00d3n",
    "sg:phone":"+34 928 22 16 11",
    "sg:postcode":"35007",
    "sg:province":"Las Palmas",
    "wof:name":"Visanta S. L.",
    "wof:placetype":"venue"
},
  "geometry": {"coordinates":[-15.4324026108,28.1402988434],"type":"Point"}
}