{
  "type": "Feature",
  "properties": {
    "addr:full":"A Igrexa, S/n Breto\u00f1a Lugo 27286",
    "addr:housenumber":"s / n",
    "addr:postcode":"27286",
    "addr:street":"A Igrexa",
    "iso:country":"ES",
    "sg:address":"A Igrexa, S/n",
    "sg:city":"Breto\u00f1a",
    "sg:orig_category":"Fabricaci\u00d3n De Productos L\u00c1cteos Y Derivados",
    "sg:phone":"+34 982 34 93 51",
    "sg:postcode":"27286",
    "sg:province":"Lugo",
    "wof:name":"Gancobre S. Coop. Ltda",
    "wof:placetype":"venue"
},
  "geometry": {"coordinates":[-7.5558514595,43.0120849609],"type":"Point"}
}