{
  "type": "Feature",
  "properties": {
    "iso:country":"ES",
    "sg:address":"Calle de Calatrava, 27",
    "sg:city":"Ciudad Real",
    "sg:orig_category":"Bisuter\u00cda, Joyer\u00cda, Relojer\u00cda (al Por Menor)",
    "sg:phone":"+34 926 22 86 08",
    "sg:postcode":"13003",
    "sg:province":"Ciudad Real",
    "wof:name":"Clerico Canalejo Francisco Javier",
    "wof:placetype":"venue"
},
  "geometry": {"coordinates":[-3.9254255295,38.9891204834],"type":"Point"}
}