{
  "type": "Feature",
  "properties": {
    "addr:full":"Calle de Alonso De Palencia, 20 Malaga M\u00e1laga 29007",
    "addr:housenumber":"20",
    "addr:postcode":"29007",
    "addr:street":"Calle De Alonso De Palencia;Ma\u0301Laga",
    "iso:country":"ES",
    "sg:address":"Calle de Alonso De Palencia, 20",
    "sg:city":"Malaga",
    "sg:orig_category":"Ense\u00d1anza: Peluquer\u00cda Est\u00c9tica",
    "sg:phone":"+34 952 07 04 64",
    "sg:postcode":"29007",
    "sg:province":"M\u00e1laga",
    "wof:name":"Carmen Nebro S.l.",
    "wof:placetype":"venue"
},
  "geometry": {"coordinates":[-4.4326844215,36.7208099365],"type":"Point"}
}