{
  "type": "Feature",
  "properties": {
    "iso:country":"ES",
    "sg:address":"Calle de Canalejas, 50",
    "sg:city":"Palmas De Gran Canaria",
    "sg:orig_category":"Bricolaje, Herramientas (al Por Menor)",
    "sg:phone":"+34 928 38 15 12",
    "sg:postcode":"35003",
    "sg:province":"Las Palmas",
    "wof:name":"Geschaft S.l.",
    "wof:placetype":"venue"
},
  "geometry": {"coordinates":[-15.4205656052,28.110918045],"type":"Point"}
}