{
  "type": "Feature",
  "properties": {
    "iso:country":"ES",
    "sg:address":"C/ Sant Francesc, 1",
    "sg:city":"Alcoi",
    "sg:orig_category":"Arquitectos",
    "sg:phone":"+34 965 54 24 43",
    "sg:postcode":"03801",
    "sg:province":"Alicante",
    "wof:name":"Monllor Marti Roque",
    "wof:placetype":"venue"
},
  "geometry": {"coordinates":[-0.4741260111,38.6974067688],"type":"Point"}
}