{
  "type": "Feature",
  "properties": {
    "addr:full":"Monasterio Fitero, 7 Iru\u00f1a Navarra 31011",
    "addr:housenumber":"7",
    "addr:postcode":"31011",
    "addr:street":"Fitero",
    "iso:country":"ES",
    "sg:address":"Monasterio Fitero, 7",
    "sg:city":"Iru\u00f1a",
    "sg:orig_category":"Procuradores",
    "sg:phone":"+34 948 27 18 12",
    "sg:postcode":"31011",
    "sg:province":"Navarra",
    "wof:name":"Ubillos Minondo Jaime",
    "wof:placetype":"venue"
},
  "geometry": {"coordinates":[-1.6618609428,42.8171577454],"type":"Point"}
}