{
  "type": "Feature",
  "properties": {
    "addr:full":"C/ Puigcerda (de), 23 Llivia Girona 17527",
    "addr:housenumber":"23",
    "addr:postcode":"17527",
    "addr:street":"C / Puigcerda De",
    "iso:country":"ES",
    "sg:address":"C/ Puigcerda (de), 23",
    "sg:city":"Llivia",
    "sg:orig_category":"Doctores En Medicina",
    "sg:phone":"+34 972 89 61 34",
    "sg:postcode":"17527",
    "sg:province":"Girona",
    "wof:name":"Se\u00f1or Izquierdo Juan Carlos",
    "wof:placetype":"venue"
},
  "geometry": {"coordinates":[1.976590991,42.462688446],"type":"Point"}
}