{
  "type": "Feature",
  "properties": {
    "addr:full":"C/ Luis Llorente, 3 Elche Alicante 03201",
    "addr:housenumber":"3",
    "addr:postcode":"03201",
    "addr:street":"C / Luis Llorente",
    "iso:country":"ES",
    "sg:address":"C/ Luis Llorente, 3",
    "sg:city":"Elche",
    "sg:orig_category":"Discotecas Y Salas De Baile",
    "sg:phone":"+34 965 46 38 24",
    "sg:postcode":"03201",
    "sg:province":"Alicante",
    "wof:name":"Torre De Carrus S.l.",
    "wof:placetype":"venue"
},
  "geometry": {"coordinates":[-0.7057340145,38.2675628662],"type":"Point"}
}