{
  "type": "Feature",
  "properties": {
    "addr:full":"Calle de Santa Elena, 12 Madrid Madrid 28017",
    "addr:housenumber":"12",
    "addr:postcode":"madrid;28017",
    "addr:street":"Calle De Santa Elena",
    "iso:country":"ES",
    "sg:address":"Calle de Santa Elena, 12",
    "sg:city":"Madrid",
    "sg:orig_category":"Comercio De Piezas De Recambio Y De Accesorios De Veh\u00cdculos, Veh\u00cdculos Industriales",
    "sg:phone":"+34 913 26 59 50",
    "sg:postcode":"28017",
    "sg:province":"Madrid",
    "wof:name":"Talleres Loreto S.l.",
    "wof:placetype":"venue"
},
  "geometry": {"coordinates":[-3.6515440941,40.4319496155],"type":"Point"}
}