{
  "type": "Feature",
  "properties": {
    "addr:full":"Avda Ramon Y Cajal, 10 Marbella M\u00e1laga 29600",
    "addr:housenumber":"10",
    "addr:postcode":"29600",
    "addr:street":"Avda Ramon Y Cajal;Ma\u0301Laga",
    "iso:country":"ES",
    "sg:address":"Avda Ramon Y Cajal, 10",
    "sg:city":"Marbella",
    "sg:orig_category":"Asesor\u00cda Sobre Comunicaci\u00d3n De Empresas",
    "sg:phone":"+34 952 77 43 84",
    "sg:postcode":"29600",
    "sg:province":"M\u00e1laga",
    "wof:name":"Torres Barquero Juan",
    "wof:placetype":"venue"
},
  "geometry": {"coordinates":[-4.8836898804,36.5079689026],"type":"Point"}
}