{
  "type": "Feature",
  "properties": {
    "addr:full":"Pl Ajuntament (de L'), 5 Botarell Tarragona 43772",
    "addr:housenumber":"5",
    "addr:postcode":"43772",
    "addr:street":"Pl;'",
    "iso:country":"ES",
    "sg:address":"Pl Ajuntament (de L'), 5",
    "sg:city":"Botarell",
    "sg:orig_category":"Administraciones Regionales, Departamentales Y Locales",
    "sg:phone":"+34 977 82 61 30",
    "sg:postcode":"43772",
    "sg:province":"Tarragona",
    "wof:name":"Ajuntament De Botarell",
    "wof:placetype":"venue"
},
  "geometry": {"coordinates":[0.9889503121,41.1360664368],"type":"Point"}
}