{
  "type": "Feature",
  "properties": {
    "addr:full":"Calle de Yebenes, 116 Madrid Madrid 28047",
    "addr:housenumber":"116",
    "addr:postcode":"28047",
    "addr:street":"Calle De Yebenes",
    "iso:country":"ES",
    "sg:address":"Calle de Yebenes, 116",
    "sg:city":"Madrid",
    "sg:orig_category":"Asociaciones Y Clubs Deportivos",
    "sg:phone":"+34 917 19 02 05",
    "sg:postcode":"28047",
    "sg:province":"Madrid",
    "wof:name":"Club Deportivo Los Yebenes",
    "wof:placetype":"venue"
},
  "geometry": {"coordinates":[-3.752024889,40.3914909363],"type":"Point"}
}