{
  "type": "Feature",
  "properties": {
    "addr:full":"Calle de Caceres, 33 Linares Ja\u00e9n 23700",
    "addr:housenumber":"33",
    "addr:postcode":"23700",
    "addr:street":"Calle De Caceres;Jae\u0301N",
    "iso:country":"ES",
    "sg:address":"Calle de Caceres, 33",
    "sg:city":"Linares",
    "sg:orig_category":"Negocio De Materiales De Construcci\u00d3n",
    "sg:phone":"+34 953 69 86 02",
    "sg:postcode":"23700",
    "sg:province":"Ja\u00e9n",
    "wof:name":"Soto Cintas Francisco",
    "wof:placetype":"venue"
},
  "geometry": {"coordinates":[-3.6448810101,38.0996856689],"type":"Point"}
}