{
  "type": "Feature",
  "properties": {
    "iso:country":"ES",
    "sg:address":"Sol, 3",
    "sg:city":"Azcona",
    "sg:orig_category":"Cervezas (negociantes Y Depositarios)",
    "sg:phone":"+34 948 54 22 65",
    "sg:postcode":"31177",
    "sg:province":"Navarra",
    "sg:website":"www.servebel.es",
    "wof:name":"Cervebel S.l.",
    "wof:placetype":"venue"
},
  "geometry": {"coordinates":[-1.994912982,42.7404670715],"type":"Point"}
}