{
  "type": "Feature",
  "properties": {
    "iso:country":"ES",
    "sg:address":"Carr Felip De Silva, 5",
    "sg:city":"Lleida",
    "sg:orig_category":"Comit\u00c9s De Organizaci\u00d3n De Exposiciones, Ferias, Salones",
    "sg:phone":"+34 973 24 14 07",
    "sg:postcode":"25005",
    "sg:province":"Lleida",
    "wof:name":"Gonzalez Gonzalez Miguel Angel",
    "wof:placetype":"venue"
},
  "geometry": {"coordinates":[0.6308150291,41.6251144409],"type":"Point"}
}