{
  "type": "Feature",
  "properties": {
    "addr:full":"Av Puigcerda, Km. 0024,0 Pla Barcelona 08185",
    "addr:postcode":"08185",
    "addr:street":"Av Puigcerda Km. 0024,0 Pla Barcelona",
    "iso:country":"ES",
    "sg:address":"Av Puigcerda, Km. 0024,0",
    "sg:city":"Pla",
    "sg:orig_category":"Electricidad: Equipos Industriales, Componentes (fabricaci\u00d3n)",
    "sg:phone":"+34 938 40 53 96",
    "sg:postcode":"08185",
    "sg:province":"Barcelona",
    "wof:name":"Aparellaje Electrotecnico S.a.",
    "wof:placetype":"venue"
},
  "geometry": {"coordinates":[2.2147409916,41.411403656],"type":"Point"}
}