{
  "type": "Feature",
  "properties": {
    "iso:country":"ES",
    "sg:address":"Calle de Escultor Jose Capuz, 15",
    "sg:city":"Valencia",
    "sg:orig_category":"Venta Al Preg\u00d3n",
    "sg:phone":"+34 963 34 91 62",
    "sg:postcode":"46006",
    "sg:province":"Valencia",
    "wof:name":"Blasco Blasco Enrique",
    "wof:placetype":"venue"
},
  "geometry": {"coordinates":[-0.361988008,39.4610061646],"type":"Point"}
}