{
  "type": "Feature",
  "properties": {
    "iso:country":"ES",
    "sg:address":"Zabalotegi Kalea, 6",
    "sg:city":"Bergara",
    "sg:orig_category":"Centros De Educaci\u00d3n Especial",
    "sg:phone":"+34 943 76 08 17",
    "sg:postcode":"20570",
    "sg:province":"Guip\u00f9zcoa",
    "wof:name":"Gobierno Vasco-eusko Jaurlaritza",
    "wof:placetype":"venue"
},
  "geometry": {"coordinates":[-2.4126288891,43.1156806946],"type":"Point"}
}