{
  "type": "Feature",
  "properties": {
    "iso:country":"ES",
    "sg:address":"Blasco Iba\u00f1ez, 28",
    "sg:city":"Benissa",
    "sg:orig_category":"Chapister\u00cda",
    "sg:phone":"+34 965 73 31 93",
    "sg:postcode":"03720",
    "sg:province":"Alicante",
    "wof:name":"Juan Y Tayeb S.l.",
    "wof:placetype":"venue"
},
  "geometry": {"coordinates":[0.0610349998,38.7181587219],"type":"Point"}
}