{
  "type": "Feature",
  "properties": {
    "iso:country":"ES",
    "sg:address":"Poligono Industrial, S/n",
    "sg:city":"Astorga",
    "sg:orig_category":"Mec\u00c1nico Del Autom\u00d3vil",
    "sg:phone":"+34 987 61 74 01",
    "sg:postcode":"24700",
    "sg:province":"Le\u00f3n",
    "wof:name":"Taller Mecanico Vela S.l.",
    "wof:placetype":"venue"
},
  "geometry": {"coordinates":[-6.0532841682,42.4577598572],"type":"Point"}
}