{
  "type": "Feature",
  "properties": {
    "iso:country":"ES",
    "sg:address":"Luga Siesta, S/n",
    "sg:city":"Siesta",
    "sg:orig_category":"Art\u00cdculos De Regalo (al Por Menor)",
    "sg:phone":"+34 971 33 05 72",
    "sg:postcode":"07840",
    "sg:province":"Islas Baleares",
    "wof:name":"Torres Juan Catalina",
    "wof:placetype":"venue"
},
  "geometry": {"coordinates":[1.5341850519,38.9850311279],"type":"Point"}
}