{
  "type": "Feature",
  "properties": {
    "addr:full":"Carr Pompeu Fabra, 26 Linyola Lleida 25240",
    "addr:housenumber":"26",
    "addr:postcode":"25240",
    "addr:street":"Carr Pompeu Fabra",
    "iso:country":"ES",
    "sg:address":"Carr Pompeu Fabra, 26",
    "sg:city":"Linyola",
    "sg:orig_category":"Doctores En Medicina",
    "sg:phone":"+34 973 57 52 38",
    "sg:postcode":"25240",
    "sg:province":"Lleida",
    "wof:name":"Lezcano Luesma Eduardo",
    "wof:placetype":"venue"
},
  "geometry": {"coordinates":[0.89872998,41.710231781],"type":"Point"}
}