{
  "type": "Feature",
  "properties": {
    "addr:full":"Calle de General Vara De Rey, 38 Logro\u00f1o La Rioja 26002",
    "addr:housenumber":"38",
    "addr:postcode":"26002",
    "addr:street":"Calle De General Vara De Rey;Rioja",
    "iso:country":"ES",
    "sg:address":"Calle de General Vara De Rey, 38",
    "sg:city":"Logro\u00f1o",
    "sg:orig_category":"Asesor\u00cda Sobre Comunicaci\u00d3n De Empresas",
    "sg:phone":"+34 941 25 86 25",
    "sg:postcode":"26002",
    "sg:province":"La Rioja",
    "wof:name":"Aliaga Asesores Y Consultores S.l.",
    "wof:placetype":"venue"
},
  "geometry": {"coordinates":[-2.4458870888,42.4606971741],"type":"Point"}
}