{
  "type": "Feature",
  "properties": {
    "addr:full":"Carrer de Sant Marian, 145 Terrassa Barcelona 08221",
    "addr:housenumber":"145",
    "addr:postcode":"08221",
    "addr:street":"Carrer De Sant Marian",
    "iso:country":"ES",
    "sg:address":"Carrer de Sant Marian, 145",
    "sg:city":"Terrassa",
    "sg:orig_category":"Inmobiliaria (agencias)",
    "sg:phone":"+34 937 33 19 20",
    "sg:postcode":"08221",
    "sg:province":"Barcelona",
    "wof:name":"Comunidad De Propietarios De La Calles Sant Marian 145",
    "wof:placetype":"venue"
},
  "geometry": {"coordinates":[2.0125319958,41.5578536987],"type":"Point"}
}