{
  "type": "Feature",
  "properties": {
    "addr:full":"Calle de Santiago De Compostela, 24 Madrid Madrid 28034",
    "addr:housenumber":"24",
    "addr:postcode":"madrid;28034",
    "addr:street":"Calle De Santiago De Compostela",
    "iso:country":"ES",
    "sg:address":"Calle de Santiago De Compostela, 24",
    "sg:city":"Madrid",
    "sg:orig_category":"Art\u00cdculos De Regalo (al Por Menor)",
    "sg:phone":"+34 913 78 20 90",
    "sg:postcode":"28034",
    "sg:province":"Madrid",
    "wof:name":"Ojeda Villarroya Cecilia",
    "wof:placetype":"venue"
},
  "geometry": {"coordinates":[-3.7107961178,40.4812049866],"type":"Point"}
}