{
  "type": "Feature",
  "properties": {
    "addr:full":"Calle de Rio Jandula, 1 Martos Ja\u00e9n 23600",
    "addr:housenumber":"1",
    "addr:postcode":"23600",
    "addr:street":"Calle De Rio Jandula;Jae\u0301N",
    "iso:country":"ES",
    "sg:address":"Calle de Rio Jandula, 1",
    "sg:city":"Martos",
    "sg:orig_category":"Ense\u00d1anza Secundaria: Colegios Y Escuelas Privadas",
    "sg:phone":"+34 953 55 01 51",
    "sg:postcode":"23600",
    "sg:province":"Ja\u00e9n",
    "wof:name":"Junta De Andalucia",
    "wof:placetype":"venue"
},
  "geometry": {"coordinates":[-3.9712491035,37.7089195251],"type":"Point"}
}