{
  "type": "Feature",
  "properties": {
    "iso:country":"ES",
    "sg:address":"Avda Portugal, 58",
    "sg:city":"Gijon",
    "sg:orig_category":"Quincaller\u00cda (al Por Menor)",
    "sg:phone":"+34 985 34 23 93",
    "sg:postcode":"33207",
    "sg:province":"Asturias",
    "wof:name":"Valdavida Roberto S.l.",
    "wof:placetype":"venue"
},
  "geometry": {"coordinates":[-5.6714739799,43.5374412537],"type":"Point"}
}