{
  "type": "Feature",
  "properties": {
    "iso:country":"ES",
    "sg:address":"Calle de Pintor Zabaleta, 11",
    "sg:city":"Puerta De Segura",
    "sg:orig_category":"Zapatos (al Por Menor)",
    "sg:phone":"+34 953 48 70 19",
    "sg:postcode":"23360",
    "sg:province":"Ja\u00e9n",
    "wof:name":"Guillen Lopez Daniel",
    "wof:placetype":"venue"
},
  "geometry": {"coordinates":[-2.7370131016,38.3486099243],"type":"Point"}
}