{
  "type": "Feature",
  "properties": {
    "addr:full":"Poblado De Puerto Pe\u00f1a, S/n Pto Pe\u00f1a Badajoz 06640",
    "addr:housenumber":"/ n",
    "addr:postcode":"06640",
    "addr:street":"Pen\u0303A S;Pto Pen\u0303A",
    "iso:country":"ES",
    "sg:address":"Poblado De Puerto Pe\u00f1a, S/n",
    "sg:city":"Pto Pe\u00f1a",
    "sg:orig_category":"Promotores Constructores",
    "sg:phone":"+34 924 63 14 65",
    "sg:postcode":"06640",
    "sg:province":"Badajoz",
    "wof:name":"Molina Domenech Angela",
    "wof:placetype":"venue"
},
  "geometry": {"coordinates":[-5.2343840599,39.0305633545],"type":"Point"}
}