{
  "type": "Feature",
  "properties": {
    "addr:full":"Avda Valle El, 14 Hinojos Huelva 21740",
    "addr:housenumber":"14",
    "addr:postcode":"21740",
    "addr:street":"Avda Valle El",
    "iso:country":"ES",
    "sg:address":"Avda Valle El, 14",
    "sg:city":"Hinojos",
    "sg:orig_category":"Carb\u00d3n, Carb\u00d3n De Madera (al Por Mayor)",
    "sg:phone":"+34 959 45 94 18",
    "sg:postcode":"21740",
    "sg:province":"Huelva",
    "wof:name":"Rubio Naranjo Socorro",
    "wof:placetype":"venue"
},
  "geometry": {"coordinates":[-6.3790822029,37.2923469543],"type":"Point"}
}