{
  "type": "Feature",
  "properties": {
    "addr:full":"Vinqui\u00f1o-padri\u00f1an, S/n Vinqui\u00d1o Pontevedra 36969",
    "addr:postcode":"36969",
    "addr:street":"Vinquin\u0303O-Padrin\u0303An S / N",
    "iso:country":"ES",
    "sg:address":"Vinqui\u00f1o-padri\u00f1an, S/n",
    "sg:city":"Vinqui\u00d1o",
    "sg:orig_category":"Art\u00cdculos Funerarios (al Por Menor)",
    "sg:phone":"+34 986 72 37 24",
    "sg:postcode":"36969",
    "sg:province":"Pontevedra",
    "wof:name":"Alfonso Iglesias Srlu",
    "wof:placetype":"venue"
},
  "geometry": {"coordinates":[-8.8149108887,42.4153060913],"type":"Point"}
}