{
  "type": "Feature",
  "properties": {
    "iso:country":"ES",
    "sg:address":"Calle de Beriso, 1",
    "sg:city":"Barrio De Peral",
    "sg:orig_category":"Animales (al Por Menor)",
    "sg:phone":"+34 968 53 47 61",
    "sg:postcode":"30300",
    "sg:province":"Murcia",
    "wof:name":"Ruiz Sanchez Beatriz",
    "wof:placetype":"venue"
},
  "geometry": {"coordinates":[-1.1298867464,37.9834747314],"type":"Point"}
}