{
  "type": "Feature",
  "properties": {
    "addr:full":"Calle de Uria, 20 Oviedo Asturias 33003",
    "addr:housenumber":"20",
    "addr:postcode":"33003",
    "addr:street":"Calle De Uria",
    "iso:country":"ES",
    "sg:address":"Calle de Uria, 20",
    "sg:city":"Oviedo",
    "sg:orig_category":"Abogados",
    "sg:phone":"+34 985 27 27 28",
    "sg:postcode":"33003",
    "sg:province":"Asturias",
    "wof:name":"Gutierrez De La Roza Abogados S.l.",
    "wof:placetype":"venue"
},
  "geometry": {"coordinates":[-5.8501291275,43.3633956909],"type":"Point"}
}