{
  "type": "Feature",
  "properties": {
    "iso:country":"ES",
    "sg:address":"Carr Anselm Clave, 85",
    "sg:city":"Blanes",
    "sg:orig_category":"Asesor\u00cda Sobre Comunicaci\u00d3n De Empresas",
    "sg:phone":"+34 972 33 44 04",
    "sg:postcode":"17300",
    "sg:province":"Girona",
    "wof:name":"Gabinet Tecnic D'administracio Empresarial Camero Castiblanque S.l.",
    "wof:placetype":"venue"
},
  "geometry": {"coordinates":[2.789192915,41.6761054993],"type":"Point"}
}