{
  "type": "Feature",
  "properties": {
    "addr:full":"Avda. Finisterre, 259 A Coru\u00f1a La Coru\u00f1a 15010",
    "addr:housenumber":"259 a",
    "addr:postcode":"15010",
    "addr:street":"Avda. Finisterre;Corun\u0303A La Corun\u0303A",
    "iso:country":"ES",
    "sg:address":"Avda. Finisterre, 259",
    "sg:city":"A Coru\u00f1a",
    "sg:orig_category":"Inversiones",
    "sg:phone":"+34 981 14 12 72",
    "sg:postcode":"15010",
    "sg:province":"La Coru\u00f1a",
    "wof:name":"Coruna Norte De Inversiones S.l.",
    "wof:placetype":"venue"
},
  "geometry": {"coordinates":[-8.4377470016,43.3511428833],"type":"Point"}
}