{
  "type": "Feature",
  "properties": {
    "addr:full":"Rua Paseo (do), 22 Ourense Ourense 32003",
    "addr:housenumber":"22",
    "addr:postcode":"32003",
    "addr:street":"Rua Paseo Do",
    "iso:country":"ES",
    "sg:address":"Rua Paseo (do), 22",
    "sg:city":"Ourense",
    "sg:orig_category":"Asesor\u00cda Fiscal Y Jur\u00cddica",
    "sg:phone":"+34 988 25 35 88",
    "sg:postcode":"32003",
    "sg:province":"Ourense",
    "wof:name":"Asesoria Bieito S.l.",
    "wof:placetype":"venue"
},
  "geometry": {"coordinates":[-7.8645915985,42.3405914307],"type":"Point"}
}