{
  "type": "Feature",
  "properties": {
    "iso:country":"ES",
    "sg:address":"Cllo Monardes, 4",
    "sg:city":"Sevilla",
    "sg:orig_category":"Dorados, Plater\u00cda (orfebrer\u00cda)",
    "sg:phone":"+34 954 21 68 28",
    "sg:postcode":"41004",
    "sg:province":"Sevilla",
    "wof:name":"Barragan Ca\u00f1al Juan Carlos",
    "wof:placetype":"venue"
},
  "geometry": {"coordinates":[-5.993888855,37.3902282715],"type":"Point"}
}