{
  "type": "Feature",
  "properties": {
    "iso:country":"ES",
    "sg:address":"Calle de Puerto Rico, 6",
    "sg:city":"Majadahonda",
    "sg:orig_category":"Administradores De Bienes Y Delegados De Comunidades De Propietarios",
    "sg:phone":"+34 916 39 41 32",
    "sg:postcode":"28220",
    "sg:province":"Madrid",
    "wof:name":"Laesa 5 S.l.",
    "wof:placetype":"venue"
},
  "geometry": {"coordinates":[-3.8710770607,40.4753837585],"type":"Point"}
}