{
  "type": "Feature",
  "properties": {
    "addr:full":"Carrer de Margarida Xirgu, S/n Sitges Barcelona 08870",
    "addr:housenumber":"s / n",
    "addr:postcode":"08870",
    "addr:street":"Carrer De Margarida Xirgu",
    "iso:country":"ES",
    "sg:address":"Carrer de Margarida Xirgu, S/n",
    "sg:city":"Sitges",
    "sg:orig_category":"Asesor\u00cda Sobre Comunicaci\u00d3n De Empresas",
    "sg:phone":"+34 938 94 46 71",
    "sg:postcode":"08870",
    "sg:province":"Barcelona",
    "wof:name":"Farmaprojects S. A.",
    "wof:placetype":"venue"
},
  "geometry": {"coordinates":[1.78837502,41.2370834351],"type":"Point"}
}