{
  "type": "Feature",
  "properties": {
    "iso:country":"ES",
    "sg:address":"Calle de Lepanto, 1",
    "sg:city":"Talavera Reina",
    "sg:orig_category":"Cer\u00c1mica Art\u00cdstica Y Decorativa",
    "sg:phone":"+34 925 81 54 78",
    "sg:postcode":"45600",
    "sg:province":"Toledo",
    "wof:name":"Ramos Oliva Jose Carlos",
    "wof:placetype":"venue"
},
  "geometry": {"coordinates":[-4.8184890747,39.962677002],"type":"Point"}
}