{
  "type": "Feature",
  "properties": {
    "addr:full":"Calle de Alvarez Quintero, 16 Sevilla Sevilla 41004",
    "addr:housenumber":"16",
    "addr:postcode":"41004",
    "addr:street":"Calle De Alvarez Quintero",
    "iso:country":"ES",
    "sg:address":"Calle de Alvarez Quintero, 16",
    "sg:city":"Sevilla",
    "sg:orig_category":"Ropa Para Ni\u00d1os (al Por Menor)",
    "sg:phone":"+34 954 22 54 94",
    "sg:postcode":"41004",
    "sg:province":"Sevilla",
    "wof:name":"Aurora Gavi\u00f1o S.l.",
    "wof:placetype":"venue"
},
  "geometry": {"coordinates":[-5.9932556152,37.3882255554],"type":"Point"}
}