{
  "type": "Feature",
  "properties": {
    "iso:country":"ES",
    "sg:address":"Calle de Camino De La Huerta (del), 31",
    "sg:city":"Alcobendas",
    "sg:orig_category":"Ingeniero",
    "sg:phone":"+34 916 50 36 63",
    "sg:postcode":"28109",
    "sg:province":"Madrid",
    "wof:name":"Beamonte De Cominges Carlos",
    "wof:placetype":"venue"
},
  "geometry": {"coordinates":[-3.6271491051,40.5124168396],"type":"Point"}
}