{
  "type": "Feature",
  "properties": {
    "iso:country":"ES",
    "sg:address":"Calle de Martires De Oca\u00d1a, 5",
    "sg:city":"Oca\u00f1a",
    "sg:orig_category":"Cl\u00cdnicas Dentales",
    "sg:phone":"+34 925 13 14 47",
    "sg:postcode":"45300",
    "sg:province":"Toledo",
    "wof:name":"Clinica Medico Dental Oca\u00f1a S.l.",
    "wof:placetype":"venue"
},
  "geometry": {"coordinates":[-3.4978909492,39.9539833069],"type":"Point"}
}