{
  "type": "Feature",
  "properties": {
    "iso:country":"ES",
    "sg:address":"Calle de Real, 24",
    "sg:city":"Albolote",
    "sg:orig_category":"Material Y Herramientas Agr\u00cdcolas",
    "sg:phone":"+34 958 43 09 08",
    "sg:postcode":"18220",
    "sg:province":"Granada",
    "wof:name":"Granada Maquinaria 03 S.l.",
    "wof:placetype":"venue"
},
  "geometry": {"coordinates":[-3.6575219631,37.2319908142],"type":"Point"}
}