{
  "type": "Feature",
  "properties": {
    "addr:full":"Calle de Concejo, 3 Galapagar Madrid 28260",
    "addr:housenumber":"3",
    "addr:postcode":"28260",
    "addr:street":"Calle De Concejo",
    "iso:country":"ES",
    "sg:address":"Calle de Concejo, 3",
    "sg:city":"Galapagar",
    "sg:orig_category":"Art\u00cdculos De Regalo (al Por Menor)",
    "sg:phone":"+34 918 58 00 86",
    "sg:postcode":"28260",
    "sg:province":"Madrid",
    "wof:name":"Alberquilla Rubio Mario",
    "wof:placetype":"venue"
},
  "geometry": {"coordinates":[-4.0040335655,40.5771179199],"type":"Point"}
}