{
  "type": "Feature",
  "properties": {
    "addr:full":"Calle de Irurzun, 29 Peralta Navarra 31350",
    "addr:housenumber":"29",
    "addr:postcode":"31350",
    "addr:street":"Calle De Irurzun",
    "iso:country":"ES",
    "sg:address":"Calle de Irurzun, 29",
    "sg:city":"Peralta",
    "sg:orig_category":"Carnicer\u00cdas, Carnicer\u00cdas",
    "sg:phone":"+34 948 75 00 83",
    "sg:postcode":"31350",
    "sg:province":"Navarra",
    "wof:name":"Oses Gil Jose",
    "wof:placetype":"venue"
},
  "geometry": {"coordinates":[-1.7946790457,42.3372612],"type":"Point"}
}