{
  "type": "Feature",
  "properties": {
    "iso:country":"ES",
    "sg:address":"Calle de Padre Claret, 6",
    "sg:city":"San Ildefonso O La Granja",
    "sg:orig_category":"Asociaciones Y Clubs Deportivos",
    "sg:phone":"+34 921 47 15 86",
    "sg:postcode":"40100",
    "sg:province":"Segovia",
    "wof:name":"Revillo Romero Gustavo Adolfo",
    "wof:placetype":"venue"
},
  "geometry": {"coordinates":[-4.0059480667,40.901889801],"type":"Point"}
}