{
  "type": "Feature",
  "properties": {
    "addr:full":"Calle de Matilla (la), 6 Santa Maria Del Paramo Le\u00f3n 24240",
    "addr:housenumber":"6",
    "addr:postcode":"24240",
    "addr:street":"Calle De Matilla La",
    "iso:country":"ES",
    "sg:address":"Calle de Matilla (la), 6",
    "sg:city":"Santa Maria Del Paramo",
    "sg:orig_category":"Empresas De Carpinter\u00cda De Madera",
    "sg:phone":"+34 987 35 07 73",
    "sg:postcode":"24240",
    "sg:province":"Le\u00f3n",
    "wof:name":"Carre\u00f1o Mata German",
    "wof:placetype":"venue"
},
  "geometry": {"coordinates":[-5.7518568039,42.3581848145],"type":"Point"}
}