{
  "type": "Feature",
  "properties": {
    "iso:country":"ES",
    "sg:address":"Carrer de Benicarlo (de), 40",
    "sg:city":"Campredo",
    "sg:orig_category":"Reposter\u00cdas",
    "sg:phone":"+34 977 59 71 87",
    "sg:postcode":"43897",
    "sg:province":"Tarragona",
    "wof:name":"Gisbert Pe\u00f1alba Juan",
    "wof:placetype":"venue"
},
  "geometry": {"coordinates":[0.5542290211,40.7594909668],"type":"Point"}
}