{
  "type": "Feature",
  "properties": {
    "addr:full":"Crta. La Rambla, S/n Puente-genil C\u00f3rdoba 14500",
    "addr:postcode":"14500",
    "addr:street":"Crta. La Rambla S / N Puente-Genil Co\u0301Rdoba",
    "iso:country":"ES",
    "sg:address":"Crta. La Rambla, S/n",
    "sg:city":"Puente-genil",
    "sg:orig_category":"Negocio De Materiales De Construcci\u00d3n",
    "sg:phone":"+34 957 60 32 95",
    "sg:postcode":"14500",
    "sg:province":"C\u00f3rdoba",
    "wof:name":"Hijos De Pedro Carmona S.l.",
    "wof:placetype":"venue"
},
  "geometry": {"coordinates":[-4.7648339272,37.3961639404],"type":"Point"}
}