{
  "type": "Feature",
  "properties": {
    "iso:country":"ES",
    "sg:address":"Po. Sobradiel, S/n",
    "sg:city":"El Monte",
    "sg:orig_category":"Materias Pl\u00c1sticas: Productos Para Industria Y Agricultura (fabricaci\u00d3n, Al Por Mayor)",
    "sg:phone":"+34 976 77 25 78",
    "sg:postcode":"50629",
    "sg:province":"Zaragoza",
    "sg:website":"www.josmal.com",
    "wof:name":"Josmal S.l.",
    "wof:placetype":"venue"
},
  "geometry": {"coordinates":[-0.8765661716,41.6563491821],"type":"Point"}
}