{
  "type": "Feature",
  "properties": {
    "iso:country":"ES",
    "sg:address":"Plzl Don Pedro, 1",
    "sg:city":"Guadalajara",
    "sg:orig_category":"Fabricaci\u00d3n, Venta De Cuadros, Accesorios Para Enmarcar",
    "sg:phone":"+34 949 21 30 63",
    "sg:postcode":"19001",
    "sg:province":"Guadalajara",
    "wof:name":"Gonzalez Mora Francisca",
    "wof:placetype":"venue"
},
  "geometry": {"coordinates":[-3.1671071053,40.6329231262],"type":"Point"}
}