{
  "type": "Feature",
  "properties": {
    "iso:country":"ES",
    "sg:address":"Carr Anastasi Pinos, 33",
    "sg:city":"Lleida",
    "sg:orig_category":"Centros De Educaci\u00d3n Especial",
    "sg:phone":"+34 973 23 68 63",
    "sg:postcode":"25005",
    "sg:province":"Lleida",
    "wof:name":"Colegio Nacional Pardi\u00f1as",
    "wof:placetype":"venue"
},
  "geometry": {"coordinates":[0.6389070153,41.6247215271],"type":"Point"}
}