{
  "type": "Feature",
  "properties": {
    "iso:country":"ES",
    "sg:address":"Calle de Sagunto, 13",
    "sg:city":"Madrid",
    "sg:orig_category":"Marketing Directo",
    "sg:phone":"+34 915 94 22 48",
    "sg:postcode":"28010",
    "sg:province":"Madrid",
    "wof:name":"El Paso Galeria De Comunicacion S.l.",
    "wof:placetype":"venue"
},
  "geometry": {"coordinates":[-3.6994729042,40.4339103699],"type":"Point"}
}