{
  "type": "Feature",
  "properties": {
    "iso:country":"ES",
    "sg:address":"Calle de Toledo, 172",
    "sg:city":"Madrid",
    "sg:orig_category":"M\u00c9dicos: Estomatolog\u00cda",
    "sg:phone":"+34 913 64 01 05",
    "sg:postcode":"28005",
    "sg:province":"Madrid",
    "wof:name":"Andres Golvano Carmen Eugenia",
    "wof:placetype":"venue"
},
  "geometry": {"coordinates":[-3.7137784958,40.4024772644],"type":"Point"}
}