{
  "type": "Feature",
  "properties": {
    "iso:country":"ES",
    "sg:address":"Carrer de Calaf, 46",
    "sg:city":"Barcelona",
    "sg:orig_category":"Bordado, Marcado A Medida",
    "sg:phone":"+34 932 00 66 02",
    "sg:postcode":"08021",
    "sg:province":"Barcelona",
    "wof:name":"Sacando Hilos S.l.",
    "wof:placetype":"venue"
},
  "geometry": {"coordinates":[2.1425180435,41.3964500427],"type":"Point"}
}