{
  "type": "Feature",
  "properties": {
    "iso:country":"ES",
    "sg:address":"Calle de Caballeros, 26",
    "sg:city":"Villa Rio",
    "sg:orig_category":"Centros De Coordinaci\u00d3n",
    "sg:phone":"+34 957 17 64 06",
    "sg:postcode":"14640",
    "sg:province":"C\u00f3rdoba",
    "wof:name":"Horcas Garcia Aurora",
    "wof:placetype":"venue"
},
  "geometry": {"coordinates":[-4.2963232994,37.9815864563],"type":"Point"}
}