{
  "type": "Feature",
  "properties": {
    "addr:full":"Pl. Obpo Irurita, 1 Iru\u00f1a Navarra 31011",
    "addr:housenumber":"1",
    "addr:postcode":"31011",
    "addr:street":"Pl. Obpo Irurita",
    "iso:country":"ES",
    "sg:address":"Pl. Obpo Irurita, 1",
    "sg:city":"Iru\u00f1a",
    "sg:orig_category":"Farmacias",
    "sg:phone":"+34 948 25 04 93",
    "sg:postcode":"31011",
    "sg:province":"Navarra",
    "wof:name":"Aramburu Cruza Maria Dolores",
    "wof:placetype":"venue"
},
  "geometry": {"coordinates":[-1.6578519344,42.8164863586],"type":"Point"}
}