{
  "type": "Feature",
  "properties": {
    "addr:full":"Calle de Cuchareras Bajas, S/n Matanza De Acentejo Santa Cruz De Tenerife 38370",
    "addr:housenumber":"s / n",
    "addr:postcode":"38370",
    "addr:street":"Calle De Cuchareras Bajas",
    "iso:country":"ES",
    "sg:address":"Calle de Cuchareras Bajas, S/n",
    "sg:city":"Matanza De Acentejo",
    "sg:orig_category":"Centros Empresariales",
    "sg:phone":"+34 922 57 85 07",
    "sg:postcode":"38370",
    "sg:province":"Santa Cruz De Tenerife",
    "wof:name":"Suarez Perez Jesus Manuel",
    "wof:placetype":"venue"
},
  "geometry": {"coordinates":[-16.450334549,28.4526233673],"type":"Point"}
}