{
  "type": "Feature",
  "properties": {
    "iso:country":"ES",
    "sg:address":"Calle de Cuesta De La Virgen, 2",
    "sg:city":"Jaen",
    "sg:orig_category":"M\u00c9dicos: Salud P\u00dablica",
    "sg:phone":"+34 953 22 26 46",
    "sg:postcode":"23001",
    "sg:province":"Ja\u00e9n",
    "wof:name":"Fernandez Espa\u00f1a Eliseo",
    "wof:placetype":"venue"
},
  "geometry": {"coordinates":[-3.7862799168,37.7710189819],"type":"Point"}
}