{
  "type": "Feature",
  "properties": {
    "iso:country":"ES",
    "sg:address":"Av Emeterio Escudero, 68",
    "sg:city":"Floresta",
    "sg:orig_category":"Formaci\u00d3n Continuada (variada)",
    "sg:phone":"+34 935 89 21 75",
    "sg:postcode":"08198",
    "sg:province":"Barcelona",
    "wof:name":"Serra Salomon David",
    "wof:placetype":"venue"
},
  "geometry": {"coordinates":[2.0828230381,41.4475250244],"type":"Point"}
}