{
  "type": "Feature",
  "properties": {
    "iso:country":"ES",
    "sg:address":"Calle de Carravaldemazo, S/n",
    "sg:city":"Cabezuela",
    "sg:orig_category":"Cr\u00cda De Animales",
    "sg:phone":"+34 921 12 14 59",
    "sg:postcode":"40396",
    "sg:province":"Segovia",
    "wof:name":"Demidesa S.l.",
    "wof:placetype":"venue"
},
  "geometry": {"coordinates":[-3.9291949272,41.2353439331],"type":"Point"}
}