{
  "type": "Feature",
  "properties": {
    "iso:country":"ES",
    "sg:address":"Veintinueve De Marzo, S/n",
    "sg:city":"Nijar",
    "sg:orig_category":"Iglesia Cat\u00d3lica",
    "sg:phone":"+34 950 36 01 34",
    "sg:postcode":"04100",
    "sg:province":"Almer\u00eda",
    "wof:name":"Parroquia Santa Maria",
    "wof:placetype":"venue"
},
  "geometry": {"coordinates":[-2.139029026,36.9047737122],"type":"Point"}
}