{
  "type": "Feature",
  "properties": {
    "iso:country":"ES",
    "sg:address":"Calle de Marques De Santillana (del), 10",
    "sg:city":"Colmenar Viejo",
    "sg:orig_category":"Ropa Para Caballeros (al Por Menor)",
    "sg:phone":"+34 918 45 12 51",
    "sg:postcode":"28770",
    "sg:province":"Madrid",
    "wof:name":"Martinez Vega Ruben",
    "wof:placetype":"venue"
},
  "geometry": {"coordinates":[-3.7675960064,40.6593093872],"type":"Point"}
}