{
  "type": "Feature",
  "properties": {
    "iso:country":"ES",
    "sg:address":"Calle de Gran Via, 38",
    "sg:city":"Hellin",
    "sg:orig_category":"Delegados, Agentes De Tr\u00c1nsito, Auxiliares De Transporte Internacional",
    "sg:phone":"+34 967 30 06 33",
    "sg:postcode":"02400",
    "sg:province":"Albacete",
    "wof:name":"Garcia Garcia Jose",
    "wof:placetype":"venue"
},
  "geometry": {"coordinates":[-1.6960840225,38.5083618164],"type":"Point"}
}