{
  "type": "Feature",
  "properties": {
    "addr:full":"C/ Sant Lluis, 116 Sant Lluis Islas Baleares 07710",
    "addr:housenumber":"116",
    "addr:postcode":"07710",
    "addr:street":"C / Sant Lluis",
    "iso:country":"ES",
    "sg:address":"C/ Sant Lluis, 116",
    "sg:city":"Sant Lluis",
    "sg:orig_category":"Mec\u00c1nico Del Autom\u00d3vil",
    "sg:phone":"+34 971 15 17 83",
    "sg:postcode":"07710",
    "sg:province":"Islas Baleares",
    "wof:name":"Parra Garcia Eduardo",
    "wof:placetype":"venue"
},
  "geometry": {"coordinates":[4.2580599785,39.8476142883],"type":"Point"}
}