{
  "type": "Feature",
  "properties": {
    "iso:country":"ES",
    "sg:address":"Calle de Zubieta, 32",
    "sg:city":"Donostia-san Sebastian",
    "sg:orig_category":"M\u00c9dicos: Estomatolog\u00cda",
    "sg:phone":"+34 943 42 44 44",
    "sg:postcode":"20007",
    "sg:province":"Guip\u00f9zcoa",
    "wof:name":"Lasarte Garcia Guillermo",
    "wof:placetype":"venue"
},
  "geometry": {"coordinates":[-1.9863469601,43.3165168762],"type":"Point"}
}