{
  "type": "Feature",
  "properties": {
    "iso:country":"ES",
    "sg:address":"Calle de Padre Maresme, 23",
    "sg:city":"Sagunt",
    "sg:orig_category":"Inmobiliaria (agencias)",
    "sg:phone":"+34 962 66 33 19",
    "sg:postcode":"46500",
    "sg:province":"Valencia",
    "wof:name":"Casas Sinisterra Juan Jesus",
    "wof:placetype":"venue"
},
  "geometry": {"coordinates":[-0.2826589942,39.6788902283],"type":"Point"}
}