{
  "type": "Feature",
  "properties": {
    "addr:full":"Carrer de Barcelona, 22 Llagosta Barcelona 08120",
    "addr:housenumber":"22",
    "addr:postcode":"08120",
    "addr:street":"Carrer De Barcelona",
    "iso:country":"ES",
    "sg:address":"Carrer de Barcelona, 22",
    "sg:city":"Llagosta",
    "sg:orig_category":"Mec\u00c1nica General",
    "sg:phone":"+34 935 60 68 00",
    "sg:postcode":"08120",
    "sg:province":"Barcelona",
    "sg:website":"www.vimax-sa.com",
    "wof:name":"Vimax S.a.",
    "wof:placetype":"venue"
},
  "geometry": {"coordinates":[2.1987569332,41.5141105652],"type":"Point"}
}