{
  "type": "Feature",
  "properties": {
    "iso:country":"ES",
    "sg:address":"Carr Ermita, 58",
    "sg:city":"Villarreal",
    "sg:orig_category":"Bordado, Marcado A Medida",
    "sg:phone":"+34 964 52 39 99",
    "sg:postcode":"12540",
    "sg:province":"Castell\u00f3n",
    "wof:name":"Bariel Llorens Ana Maria Del Carmen",
    "wof:placetype":"venue"
},
  "geometry": {"coordinates":[-0.0952939987,39.9453048706],"type":"Point"}
}