{
  "type": "Feature",
  "properties": {
    "iso:country":"ES",
    "sg:address":"Calle de Eras De Maria, 11",
    "sg:city":"Requena",
    "sg:orig_category":"Empresas De Pintura Y Revestimientos",
    "sg:phone":"+34 962 30 05 50",
    "sg:postcode":"46340",
    "sg:province":"Valencia",
    "wof:name":"Carrascosa Perez Bernardino",
    "wof:placetype":"venue"
},
  "geometry": {"coordinates":[-1.106662035,39.4862518311],"type":"Point"}
}