{
  "type": "Feature",
  "properties": {
    "addr:full":"Carrer de Cometa, 6 Pallaresos Tarragona 43151",
    "addr:housenumber":"6",
    "addr:postcode":"43151",
    "addr:street":"Carrer De Cometa",
    "iso:country":"ES",
    "sg:address":"Carrer de Cometa, 6",
    "sg:city":"Pallaresos",
    "sg:orig_category":"M\u00c9dicos: Estomatolog\u00cda",
    "sg:phone":"+34 977 61 05 61",
    "sg:postcode":"43151",
    "sg:province":"Tarragona",
    "wof:name":"Scoppettuolo Cherchi Maria Susana",
    "wof:placetype":"venue"
},
  "geometry": {"coordinates":[1.2740199566,41.1734161377],"type":"Point"}
}