{
  "type": "Feature",
  "properties": {
    "addr:full":"Calle de Fuenterrabia, 3 Irun Guip\u00f9zcoa 20301",
    "addr:housenumber":"3",
    "addr:postcode":"20301",
    "addr:street":"Calle De Fuenterrabia;Guipu\u0300Zcoa",
    "iso:country":"ES",
    "sg:address":"Calle de Fuenterrabia, 3",
    "sg:city":"Irun",
    "sg:orig_category":"Bazares, Art\u00cdculos De Limpieza Y De Cocina (al Por Menor)",
    "sg:phone":"+34 943 01 66 42",
    "sg:postcode":"20301",
    "sg:province":"Guip\u00f9zcoa",
    "wof:name":"Pedro Michelena Garcia",
    "wof:placetype":"venue"
},
  "geometry": {"coordinates":[-1.7896629572,43.3636741638],"type":"Point"}
}