{
  "type": "Feature",
  "properties": {
    "addr:full":"Calle de Pilar (el), 16 Pina De Ebro Zaragoza 50750",
    "addr:housenumber":"16",
    "addr:postcode":"50750",
    "addr:street":"Calle De Pilar El",
    "iso:country":"ES",
    "sg:address":"Calle de Pilar (el), 16",
    "sg:city":"Pina De Ebro",
    "sg:orig_category":"Bares, Piano",
    "sg:phone":"+34 976 16 51 34",
    "sg:postcode":"50750",
    "sg:province":"Zaragoza",
    "wof:name":"Carblas Destribuciones S.l.",
    "wof:placetype":"venue"
},
  "geometry": {"coordinates":[-0.5298889875,41.4902000427],"type":"Point"}
}