{
  "type": "Feature",
  "properties": {
    "addr:full":"Calle de Mayor, 45 Albacete Albacete 02002",
    "addr:housenumber":"45",
    "addr:postcode":"02002",
    "addr:street":"Calle De Mayor",
    "iso:country":"ES",
    "sg:address":"Calle de Mayor, 45",
    "sg:city":"Albacete",
    "sg:orig_category":"Ense\u00d1anza Variada",
    "sg:phone":"+34 967 24 68 90",
    "sg:postcode":"02002",
    "sg:province":"Albacete",
    "wof:name":"Martinez Gimenez Ana",
    "wof:placetype":"venue"
},
  "geometry": {"coordinates":[-1.8544956446,38.9931640625],"type":"Point"}
}