{
  "type": "Feature",
  "properties": {
    "iso:country":"ES",
    "sg:address":"Rond Cabanyal, 34",
    "sg:city":"Sueca",
    "sg:orig_category":"Pintura, Barniz, Productos Asimilables (fabricaci\u00d3n, Al Por Mayor)",
    "sg:phone":"+34 961 71 05 17",
    "sg:postcode":"46410",
    "sg:province":"Valencia",
    "wof:name":"Pinturas Fraycar S.l.",
    "wof:placetype":"venue"
},
  "geometry": {"coordinates":[-0.3095499873,39.1978912354],"type":"Point"}
}