{
  "type": "Feature",
  "properties": {
    "addr:full":"Ptge Llavallol, 2 Barcelona Barcelona 08025",
    "addr:housenumber":"2",
    "addr:postcode":"08025",
    "addr:street":"Ptge Llavallol",
    "iso:country":"ES",
    "sg:address":"Ptge Llavallol, 2",
    "sg:city":"Barcelona",
    "sg:orig_category":"Centros De Educaci\u00d3n Especial",
    "sg:phone":"+34 932 07 24 43",
    "sg:postcode":"08025",
    "sg:province":"Barcelona",
    "wof:name":"Ajuntament De Barcelona",
    "wof:placetype":"venue"
},
  "geometry": {"coordinates":[2.1680128574,41.4048728943],"type":"Point"}
}