{
  "type": "Feature",
  "properties": {
    "addr:full":"Carrer de Via (la), 13 Denia Alicante 03700",
    "addr:housenumber":"13",
    "addr:postcode":"03700",
    "addr:street":"Carrer De Via La",
    "iso:country":"ES",
    "sg:address":"Carrer de Via (la), 13",
    "sg:city":"Denia",
    "sg:orig_category":"Promotores Constructores",
    "sg:phone":"+34 966 43 51 95",
    "sg:postcode":"03700",
    "sg:province":"Alicante",
    "wof:name":"Construcciones Conca S.l.",
    "wof:placetype":"venue"
},
  "geometry": {"coordinates":[0.1076499969,38.8389015198],"type":"Point"}
}