{
  "type": "Feature",
  "properties": {
    "addr:full":"Carrer de Nord, S/n Buvisa Barcelona 08329",
    "addr:housenumber":"s",
    "addr:postcode":"08329",
    "addr:street":"Carrer De Nord;/ N Buvisa",
    "iso:country":"ES",
    "sg:address":"Carrer de Nord, S/n",
    "sg:city":"Buvisa",
    "sg:orig_category":"Institutos De Belleza (productos Y Aparatos)",
    "sg:phone":"+34 935 55 54 59",
    "sg:postcode":"08329",
    "sg:province":"Barcelona",
    "sg:website":"www.movisan.es",
    "wof:name":"Movisan S.a.",
    "wof:placetype":"venue"
},
  "geometry": {"coordinates":[2.3220500946,41.498260498],"type":"Point"}
}