{
  "type": "Feature",
  "properties": {
    "iso:country":"ES",
    "sg:address":"Calle de Jose Canalejas, 2",
    "sg:city":"Aljaraque",
    "sg:orig_category":"Mec\u00c1nico Del Autom\u00d3vil",
    "sg:phone":"+34 959 31 84 60",
    "sg:postcode":"21110",
    "sg:province":"Huelva",
    "wof:name":"Gomez Perez Diego",
    "wof:placetype":"venue"
},
  "geometry": {"coordinates":[-7.0236349106,37.2706604004],"type":"Point"}
}