{
  "type": "Feature",
  "properties": {
    "addr:full":"Carr Jacint Verdaguer, 3 Badalona Barcelona 08915",
    "addr:housenumber":"3",
    "addr:postcode":"08915",
    "addr:street":"Carr Jacint Verdaguer",
    "iso:country":"ES",
    "sg:address":"Carr Jacint Verdaguer, 3",
    "sg:city":"Badalona",
    "sg:orig_category":"Electricidad: Instaladores",
    "sg:phone":"+34 933 97 09 57",
    "sg:postcode":"08915",
    "sg:province":"Barcelona",
    "wof:name":"Coisa S. Coop. Ltda.",
    "wof:placetype":"venue"
},
  "geometry": {"coordinates":[2.2435750961,41.4559783936],"type":"Point"}
}