{
  "type": "Feature",
  "properties": {
    "addr:full":"Julian Gayarre, 10 Iru\u00f1a Navarra 31005",
    "addr:housenumber":"10",
    "addr:postcode":"31005",
    "addr:street":"Julian Gayarre",
    "iso:country":"ES",
    "sg:address":"Julian Gayarre, 10",
    "sg:city":"Iru\u00f1a",
    "sg:orig_category":"Agentes, Concesionarios Y Sucursales De Camiones Y Veh\u00cdculos Industriales",
    "sg:phone":"+34 948 24 46 62",
    "sg:postcode":"31005",
    "sg:province":"Navarra",
    "wof:name":"Alfaro Miqueleiz Mikel",
    "wof:placetype":"venue"
},
  "geometry": {"coordinates":[-1.6429970264,42.8077392578],"type":"Point"}
}