{
  "type": "Feature",
  "properties": {
    "iso:country":"ES",
    "sg:address":"Plaz Pozo Del Tio Raimundo, 7",
    "sg:city":"Madrid",
    "sg:orig_category":"Peluqueros: De Se\u00d1oras",
    "sg:phone":"+34 917 85 70 38",
    "sg:postcode":"28053",
    "sg:province":"Madrid",
    "wof:name":"Gonzalez Jimenez Julia",
    "wof:placetype":"venue"
},
  "geometry": {"coordinates":[-3.6590299606,40.3723487854],"type":"Point"}
}