{
  "type": "Feature",
  "properties": {
    "iso:country":"ES",
    "sg:address":"Calle de Rafael Alberti, 24",
    "sg:city":"Vitoria-gasteiz",
    "sg:orig_category":"Relojer\u00cda (al Por Menor, Reparaci\u00d3n)",
    "sg:phone":"+34 945 13 22 38",
    "sg:postcode":"01010",
    "sg:province":"\u00c1lava",
    "wof:name":"Relojeria Miriam Hermanos Suescun S.c.",
    "wof:placetype":"venue"
},
  "geometry": {"coordinates":[-2.6998240948,42.8534507751],"type":"Point"}
}