{
  "type": "Feature",
  "properties": {
    "addr:full":"Rbla Menceyes (los), S/n Candelaria Santa Cruz De Tenerife 38530",
    "addr:postcode":"38530",
    "addr:street":"Rbla Menceyes Los S / N",
    "iso:country":"ES",
    "sg:address":"Rbla Menceyes (los), S/n",
    "sg:city":"Candelaria",
    "sg:orig_category":"Bazares, Art\u00cdculos De Limpieza Y De Cocina (al Por Menor)",
    "sg:phone":"+34 922 58 30 41",
    "sg:postcode":"38530",
    "sg:province":"Santa Cruz De Tenerife",
    "wof:name":"Indico Trade Candelaria S.l.",
    "wof:placetype":"venue"
},
  "geometry": {"coordinates":[-16.3678607941,28.3607463837],"type":"Point"}
}