{
  "type": "Feature",
  "properties": {
    "iso:country":"ES",
    "sg:address":"Calle de Principe Felipe, S/n",
    "sg:city":"Albolote",
    "sg:orig_category":"Equipo De Refrigeraci\u00d3n Industrial",
    "sg:phone":"+34 958 46 84 99",
    "sg:postcode":"18220",
    "sg:province":"Granada",
    "wof:name":"Refrigeracion Albolote S.l.",
    "wof:placetype":"venue"
},
  "geometry": {"coordinates":[-3.6517939568,37.2268981934],"type":"Point"}
}