{
  "type": "Feature",
  "properties": {
    "addr:full":"Crtra. As 18, S/n Gijon Asturias 33211",
    "addr:housenumber":"18 s / n",
    "addr:postcode":"33211",
    "iso:country":"ES",
    "sg:address":"Crtra. As 18, S/n",
    "sg:city":"Gijon",
    "sg:orig_category":"Aeropuertos Y Servicios Aeroportuarios",
    "sg:phone":"+34 985 30 70 64",
    "sg:postcode":"33211",
    "sg:province":"Asturias",
    "wof:name":"Savia Amadeus S.a.",
    "wof:placetype":"venue"
},
  "geometry": {"coordinates":[-5.6863942146,43.5233383179],"type":"Point"}
}