{
  "type": "Feature",
  "properties": {
    "iso:country":"ES",
    "sg:address":"Calle de Pani (la), 1",
    "sg:city":"Posadas",
    "sg:orig_category":"Doctores En Medicina",
    "sg:phone":"+34 957 63 08 02",
    "sg:postcode":"14730",
    "sg:province":"C\u00f3rdoba",
    "wof:name":"Carmona Segura Francisco De Asis",
    "wof:placetype":"venue"
},
  "geometry": {"coordinates":[-97.78224945069999,45.7040786743],"type":"Point"}
}