{
  "type": "Feature",
  "properties": {
    "iso:country":"ES",
    "sg:address":"Rua Jesus Espinosa, 6",
    "sg:city":"Gaifar",
    "sg:orig_category":"Carnicer\u00cdas, Carnicer\u00cdas",
    "sg:phone":"+34 986 36 81 14",
    "sg:postcode":"36340",
    "sg:province":"Pontevedra",
    "wof:name":"Carniceria Sol Y Mar Mi\u00f1or S.l.",
    "wof:placetype":"venue"
},
  "geometry": {"coordinates":[-8.8266677856,42.1491203308],"type":"Point"}
}