{
  "type": "Feature",
  "properties": {
    "iso:country":"ES",
    "sg:address":"Avda Peru (del), 18",
    "sg:city":"Cadiz",
    "sg:orig_category":"Congelados: Productos Alimentarios (al Por Menor)",
    "sg:phone":"+34 956 26 29 29",
    "sg:postcode":"11007",
    "sg:province":"C\u00e1diz",
    "sg:website":"www.procosur.com",
    "wof:name":"Procosur S.a.",
    "wof:placetype":"venue"
},
  "geometry": {"coordinates":[-6.2765278816,36.5178108215],"type":"Point"}
}