{
  "type": "Feature",
  "properties": {
    "iso:country":"ES",
    "sg:address":"Avda Burjasot, 38",
    "sg:city":"Valencia",
    "sg:orig_category":"Asesor\u00cda Sobre Comunicaci\u00d3n De Empresas",
    "sg:phone":"+34 963 47 33 05",
    "sg:postcode":"46009",
    "sg:province":"Valencia",
    "wof:name":"Tecnica Administrativa Financiera S.l.",
    "wof:placetype":"venue"
},
  "geometry": {"coordinates":[-0.3840610087,39.4844398499],"type":"Point"}
}