{
  "type": "Feature",
  "properties": {
    "iso:country":"ES",
    "sg:address":"Av Llibertat, 112",
    "sg:city":"Elche",
    "sg:orig_category":"Pod\u00d3logos: Pedicuros",
    "sg:phone":"+34 965 43 96 82",
    "sg:postcode":"03205",
    "sg:province":"Alicante",
    "wof:name":"Rico Alfosea Vicente",
    "wof:placetype":"venue"
},
  "geometry": {"coordinates":[-0.709634006,38.2674369812],"type":"Point"}
}