{
  "type": "Feature",
  "properties": {
    "addr:full":"Rond Nuestra Se\u00d1ora De La Oliva, 1 Sevilla Sevilla 41013",
    "addr:housenumber":"1",
    "addr:postcode":"41013",
    "addr:street":"Oliva",
    "iso:country":"ES",
    "sg:address":"Rond Nuestra Se\u00d1ora De La Oliva, 1",
    "sg:city":"Sevilla",
    "sg:orig_category":"Supermercados Y Hipermercados",
    "sg:phone":"+34 954 62 34 53",
    "sg:postcode":"41013",
    "sg:province":"Sevilla",
    "wof:name":"Peral Villa Dionisio",
    "wof:placetype":"venue"
},
  "geometry": {"coordinates":[-5.9828929901,37.373298645],"type":"Point"}
}