{
  "type": "Feature",
  "properties": {
    "addr:full":"Prado Llano, 3 Sierra Nevada Granada 18196",
    "addr:housenumber":"3",
    "addr:postcode":"18196",
    "addr:street":"Llano;Sierra Nevada Granada",
    "iso:country":"ES",
    "sg:address":"Prado Llano, 3",
    "sg:city":"Sierra Nevada",
    "sg:orig_category":"Fabricaci\u00d3n De Art\u00cdculos Y Equipos Deportivos Y De Ocio",
    "sg:phone":"+34 958 48 01 25",
    "sg:postcode":"18196",
    "sg:province":"Granada",
    "wof:name":"Midama S.l.",
    "wof:placetype":"venue"
},
  "geometry": {"coordinates":[-3.0351140499,37.0072669983],"type":"Point"}
}