{
  "type": "Feature",
  "properties": {
    "addr:full":"Calle de Rambla (la), 12 Cella Teruel 44370",
    "addr:housenumber":"12",
    "addr:postcode":"44370",
    "addr:street":"Calle De Rambla La",
    "iso:country":"ES",
    "sg:address":"Calle de Rambla (la), 12",
    "sg:city":"Cella",
    "sg:orig_category":"Escayola Y Productos De Escayola (fabricaci\u00d3n, Al Por Mayor)",
    "sg:phone":"+34 978 65 32 15",
    "sg:postcode":"44370",
    "sg:province":"Teruel",
    "wof:name":"Hernandez Iritia Angel",
    "wof:placetype":"venue"
},
  "geometry": {"coordinates":[-1.2887200117,40.4524879456],"type":"Point"}
}