{
  "type": "Feature",
  "properties": {
    "iso:country":"ES",
    "sg:address":"Tecina, S/n",
    "sg:city":"Laguna Santiago",
    "sg:orig_category":"Alquiler De Veh\u00cdculos: Turismos Y Utilitarios",
    "sg:phone":"+34 922 89 59 09",
    "sg:postcode":"38811",
    "sg:province":"Santa Cruz De Tenerife",
    "wof:name":"Pi\u00f1ero Darias Carmelo",
    "wof:placetype":"venue"
},
  "geometry": {"coordinates":[-17.1741352081,28.0645580292],"type":"Point"}
}