{
  "type": "Feature",
  "properties": {
    "addr:full":"Calle de Canalejas, 14 Granja Torrehermosa Badajoz 06910",
    "addr:housenumber":"14",
    "addr:postcode":"06910",
    "addr:street":"Calle De Canalejas",
    "iso:country":"ES",
    "sg:address":"Calle de Canalejas, 14",
    "sg:city":"Granja Torrehermosa",
    "sg:orig_category":"Cajas Para Embalar",
    "sg:phone":"+34 924 89 55 48",
    "sg:postcode":"06910",
    "sg:province":"Badajoz",
    "wof:name":"Caja Rural De Extremadura",
    "wof:placetype":"venue"
},
  "geometry": {"coordinates":[-5.5955781937,38.3097610474],"type":"Point"}
}