{
  "type": "Feature",
  "properties": {
    "addr:full":"Calle de Cordoba, 10 Pulianas Granada 18197",
    "addr:housenumber":"10",
    "addr:postcode":"18197",
    "addr:street":"Calle De Cordoba",
    "iso:country":"ES",
    "sg:address":"Calle de Cordoba, 10",
    "sg:city":"Pulianas",
    "sg:orig_category":"Artesan\u00cda",
    "sg:phone":"+34 958 42 43 17",
    "sg:postcode":"18197",
    "sg:province":"Granada",
    "wof:name":"Fernandez Jimenez Rafael",
    "wof:placetype":"venue"
},
  "geometry": {"coordinates":[-3.6108760834,37.2196807861],"type":"Point"}
}