{
  "type": "Feature",
  "properties": {
    "iso:country":"ES",
    "sg:address":"Avda Alt Rei En Jaume I (l'), 21",
    "sg:city":"Altea",
    "sg:orig_category":"Bancos",
    "sg:phone":"+34 965 84 13 26",
    "sg:postcode":"03590",
    "sg:province":"Alicante",
    "wof:name":"Banco De Valencia S.a.",
    "wof:placetype":"venue"
},
  "geometry": {"coordinates":[-0.0471620001,38.6018943787],"type":"Point"}
}