{
  "type": "Feature",
  "properties": {
    "iso:country":"ES",
    "sg:address":"Pla\u00c7 Born, Des, 15",
    "sg:city":"Ciutadella Menorca",
    "sg:orig_category":"Aguas (distribuci\u00d3n, Servicios)",
    "sg:phone":"+34 971 48 40 30",
    "sg:postcode":"07760",
    "sg:province":"Islas Baleares",
    "wof:name":"Ajuntament De Ciutadella De Menorca",
    "wof:placetype":"venue"
},
  "geometry": {"coordinates":[3.8858954906,39.9778633118],"type":"Point"}
}