{
  "type": "Feature",
  "properties": {
    "iso:country":"ES",
    "sg:address":"Calle de Rey Pelayo, 1",
    "sg:city":"Nava",
    "sg:classifiers":[
        {
            "category":"Autos & Motor Vehicles",
            "subcategory":"Automobile Sales",
            "type":"Retail Goods"
        }
    ],
    "sg:phone":"+34 985 71 63 73",
    "sg:postcode":"33529",
    "sg:province":"Asturias",
    "sg:website":"www.elcarmin.com",
    "wof:name":"El Carmin Siero S.l.",
    "wof:placetype":"venue"
},
  "geometry": {"coordinates":[-5.5089230537,43.3601493835],"type":"Point"}
}