{
  "type": "Feature",
  "properties": {
    "iso:country":"ES",
    "sg:address":"Hortichuelas, 10",
    "sg:city":"Parador Hortichuelas",
    "sg:orig_category":"Alimentaci\u00d3n General (al Por Menor)",
    "sg:phone":"+34 950 34 17 02",
    "sg:postcode":"04720",
    "sg:province":"Almer\u00eda",
    "wof:name":"Ruiz Mu\u00f1oz Antonio",
    "wof:placetype":"venue"
},
  "geometry": {"coordinates":[-2.5962700844,36.8076896667],"type":"Point"}
}