{
  "type": "Feature",
  "properties": {
    "addr:full":"Plaz Manuel Andujar, 1 Santo\u00f1a Cantabria 39740",
    "addr:housenumber":"1",
    "addr:postcode":"39740",
    "addr:street":"Manuel Andujar",
    "iso:country":"ES",
    "sg:address":"Plaz Manuel Andujar, 1",
    "sg:city":"Santo\u00f1a",
    "sg:orig_category":"Molduras, Junquillos, Listones Y Molduras Perforadas",
    "sg:phone":"+34 942 67 19 39",
    "sg:postcode":"39740",
    "sg:province":"Cantabria",
    "wof:name":"Phone Euskadi S. L.",
    "wof:placetype":"venue"
},
  "geometry": {"coordinates":[-3.4538080692,43.4452705383],"type":"Point"}
}