{
  "type": "Feature",
  "properties": {
    "addr:full":"Rua Real, 109 Ferrol La Coru\u00f1a 15402",
    "addr:housenumber":"109",
    "addr:postcode":"15402",
    "addr:street":"Rua Real;La Corun\u0303A",
    "iso:country":"ES",
    "sg:address":"Rua Real, 109",
    "sg:city":"Ferrol",
    "sg:orig_category":"Panader\u00cdas, Panader\u00cdas",
    "sg:phone":"+34 981 35 16 93",
    "sg:postcode":"15402",
    "sg:province":"La Coru\u00f1a",
    "wof:name":"Rubio Pita Elena",
    "wof:placetype":"venue"
},
  "geometry": {"coordinates":[-8.2333364487,43.4836730957],"type":"Point"}
}