{
  "type": "Feature",
  "properties": {
    "addr:full":"Carrer de Arenal (de L'), S/n S. Carles Rapita Tarragona 43540",
    "addr:postcode":"43540",
    "addr:street":"Carrer De Arenal De L ' S / N S. Carles Rapita",
    "iso:country":"ES",
    "sg:address":"Carrer de Arenal (de L'), S/n",
    "sg:city":"S. Carles Rapita",
    "sg:orig_category":"Asilos De Ancianos. Centros Privados",
    "sg:phone":"+34 977 74 42 04",
    "sg:postcode":"43540",
    "sg:province":"Tarragona",
    "wof:name":"Club De Pensionistas De La Casa Del Mar",
    "wof:placetype":"venue"
},
  "geometry": {"coordinates":[0.5961850286,40.6194648743],"type":"Point"}
}