{
  "type": "Feature",
  "properties": {
    "iso:country":"ES",
    "sg:address":"Calle de Italia, 51",
    "sg:city":"Palencia",
    "sg:orig_category":"Puertas Y Portales",
    "sg:phone":"+34 979 71 12 08",
    "sg:postcode":"34004",
    "sg:province":"Palencia",
    "wof:name":"Puertas Y Armarios El Salon S.l.",
    "wof:placetype":"venue"
},
  "geometry": {"coordinates":[-4.5112690926,42.0020561218],"type":"Point"}
}