{
  "type": "Feature",
  "properties": {
    "iso:country":"ES",
    "sg:address":"Ctra De Domingo Perez, S/n",
    "sg:city":"Montejicar",
    "sg:orig_category":"Distribuci\u00d3n De Petr\u00d3leo Y Derivados",
    "sg:phone":"+34 958 34 61 35",
    "sg:postcode":"18561",
    "sg:province":"Granada",
    "wof:name":"Estacion De Servicio Domingo Y Linde S.l.",
    "wof:placetype":"venue"
},
  "geometry": {"coordinates":[-3.4996790886,37.5729637146],"type":"Point"}
}