{
  "type": "Feature",
  "properties": {
    "addr:full":"Barr Sagar-erreka, 25 Soraluze-placencia Armas Guip\u00f9zcoa 20590",
    "addr:housenumber":"25",
    "addr:postcode":"20590",
    "addr:street":"Sagar-Erreka;Armas Guipu\u0300Zcoa",
    "iso:country":"ES",
    "sg:address":"Barr Sagar-erreka, 25",
    "sg:city":"Soraluze-placencia Armas",
    "sg:orig_category":"Fabricaci\u00d3n De Pernos, Tornillos Y Clavos",
    "sg:phone":"+34 943 75 16 94",
    "sg:postcode":"20590",
    "sg:province":"Guip\u00f9zcoa",
    "sg:website":"oruesagasti.com",
    "wof:name":"Tornilleria Oruesagasti S.a.",
    "wof:placetype":"venue"
},
  "geometry": {"coordinates":[-2.4274671078,43.1713790894],"type":"Point"}
}