{
  "type": "Feature",
  "properties": {
    "addr:full":"Cami Les Simetes, S/n Manises Valencia 46940",
    "addr:postcode":"46940",
    "addr:street":"Les;S / N",
    "iso:country":"ES",
    "sg:address":"Cami Les Simetes, S/n",
    "sg:city":"Manises",
    "sg:orig_category":"Ferreter\u00cda (diversos)",
    "sg:phone":"+34 961 53 39 19",
    "sg:postcode":"46940",
    "sg:province":"Valencia",
    "wof:name":"Gruas Y Desguaces Manises S.l.",
    "wof:placetype":"venue"
},
  "geometry": {"coordinates":[-0.4762890041,39.4994659424],"type":"Point"}
}