{
  "type": "Feature",
  "properties": {
    "iso:country":"ES",
    "sg:address":"Ctra. General, S/n",
    "sg:city":"Navelgas",
    "sg:orig_category":"Maquinaria Para Industrias Diversas",
    "sg:phone":"+34 985 80 60 25",
    "sg:postcode":"33873",
    "sg:province":"Asturias",
    "wof:name":"Agricola Adolfo S.l.",
    "wof:placetype":"venue"
},
  "geometry": {"coordinates":[-6.5406727791,43.4034004211],"type":"Point"}
}