{
  "type": "Feature",
  "properties": {
    "addr:full":"Avgd Madrid, 19 Lleida Lleida 25002",
    "addr:housenumber":"19",
    "addr:postcode":"25002",
    "addr:street":"Madrid",
    "iso:country":"ES",
    "sg:address":"Avgd Madrid, 19",
    "sg:city":"Lleida",
    "sg:orig_category":"Ense\u00d1anza: Profesiones Art\u00cdsticas",
    "sg:phone":"+34 973 28 20 99",
    "sg:postcode":"25002",
    "sg:province":"Lleida",
    "wof:name":"Alins Centre S.l",
    "wof:placetype":"venue"
},
  "geometry": {"coordinates":[0.6188759208,41.6089859009],"type":"Point"}
}