{
  "type": "Feature",
  "properties": {
    "iso:country":"ES",
    "sg:address":"Calle de Zaragoza, 1",
    "sg:city":"San Fernando De Henares",
    "sg:orig_category":"Sociedades, Compa\u00d1\u00cdas Aseguradoras",
    "sg:phone":"+34 916 60 10 63",
    "sg:postcode":"28830",
    "sg:province":"Madrid",
    "sg:website":"www.mmtseguros.es",
    "wof:name":"Mutua Mmt Seguros",
    "wof:placetype":"venue"
},
  "geometry": {"coordinates":[-3.5336709023,40.4290466309],"type":"Point"}
}