{
  "type": "Feature",
  "properties": {
    "iso:country":"ES",
    "sg:address":"Carrer de Enric Borras, 31",
    "sg:city":"Prat Llobregat",
    "sg:orig_category":"Confecci\u00d3n De Trajes Para Se\u00d1oras",
    "sg:phone":"+34 933 79 83 81",
    "sg:postcode":"08820",
    "sg:province":"Barcelona",
    "wof:name":"Cerrato Sanchez Jose",
    "wof:placetype":"venue"
},
  "geometry": {"coordinates":[2.0979421139,41.3316230774],"type":"Point"}
}