{
  "type": "Feature",
  "properties": {
    "iso:country":"ES",
    "sg:address":"Calle de Arguelles, 13",
    "sg:city":"Arriondas",
    "sg:orig_category":"Alimentaci\u00d3n General (al Por Menor)",
    "sg:phone":"+34 985 84 02 51",
    "sg:postcode":"33540",
    "sg:province":"Asturias",
    "wof:name":"Pandiello Perez Maria Teresa",
    "wof:placetype":"venue"
},
  "geometry": {"coordinates":[-5.1876268387,43.3882408142],"type":"Point"}
}