{
  "type": "Feature",
  "properties": {
    "addr:full":"Carrer de Petrarca, 50 Sabadell Barcelona 08206",
    "addr:housenumber":"50",
    "addr:postcode":"08206",
    "addr:street":"Carrer De Petrarca",
    "iso:country":"ES",
    "sg:address":"Carrer de Petrarca, 50",
    "sg:city":"Sabadell",
    "sg:orig_category":"Molduras, Junquillos, Listones Y Molduras Perforadas",
    "sg:phone":"+34 937 17 03 59",
    "sg:postcode":"08206",
    "sg:province":"Barcelona",
    "wof:name":"Pelayo Jimenez Petra",
    "wof:placetype":"venue"
},
  "geometry": {"coordinates":[2.0859360695,41.5575027466],"type":"Point"}
}