{
  "type": "Feature",
  "properties": {
    "iso:country":"ES",
    "sg:address":"Avda Cervantes, 23",
    "sg:city":"Alora",
    "sg:orig_category":"Droguer\u00cdas (al Por Menor)",
    "sg:phone":"+34 952 49 95 27",
    "sg:postcode":"29500",
    "sg:province":"M\u00e1laga",
    "wof:name":"Drosolu S.l.",
    "wof:placetype":"venue"
},
  "geometry": {"coordinates":[-4.7047781944,36.8276786804],"type":"Point"}
}