{
  "type": "Feature",
  "properties": {
    "iso:country":"ES",
    "sg:address":"Avda Garrucha, 25",
    "sg:city":"Carboneras",
    "sg:orig_category":"Electrodom\u00c9sticos (al Por Menor)",
    "sg:phone":"+34 950 13 05 89",
    "sg:postcode":"04140",
    "sg:province":"Almer\u00eda",
    "wof:name":"Electrodomesticos Carboneras S.l.",
    "wof:placetype":"venue"
},
  "geometry": {"coordinates":[-1.8911249638,37.0025444031],"type":"Point"}
}