{
  "type": "Feature",
  "properties": {
    "addr:full":"Carrer de Sant Francesc, 21 Sitges Barcelona 08870",
    "addr:housenumber":"21",
    "addr:postcode":"08870",
    "addr:street":"Carrer De Sant Francesc",
    "iso:country":"ES",
    "sg:address":"Carrer de Sant Francesc, 21",
    "sg:city":"Sitges",
    "sg:orig_category":"Peluquer\u00cdas, Peluquer\u00cda Mixta",
    "sg:phone":"+34 938 94 84 17",
    "sg:postcode":"08870",
    "sg:province":"Barcelona",
    "sg:website":"www.cebado.es",
    "wof:name":"Sant Francesc Cabell S.l.",
    "wof:placetype":"venue"
},
  "geometry": {"coordinates":[1.8082319498,41.2373809814],"type":"Point"}
}