{
  "type": "Feature",
  "properties": {
    "iso:country":"ES",
    "sg:address":"Calle de Barrio Gimeno, 25",
    "sg:city":"Burgos",
    "sg:orig_category":"Asociaciones, Organismos Culturales Y Socioeducativos",
    "sg:phone":"+34 947 20 63 57",
    "sg:postcode":"09001",
    "sg:province":"Burgos",
    "wof:name":"Caja De Ahorros Municipal De Burgos",
    "wof:placetype":"venue"
},
  "geometry": {"coordinates":[-3.7040150166,42.3356552124],"type":"Point"}
}