{
  "type": "Feature",
  "properties": {
    "addr:full":"Ctra. El Boqueron, 3 Tacoronte Santa Cruz De Tenerife 38350",
    "addr:housenumber":"3",
    "addr:postcode":"38350",
    "addr:street":"Ctra. El Boqueron",
    "iso:country":"ES",
    "sg:address":"Ctra. El Boqueron, 3",
    "sg:city":"Tacoronte",
    "sg:orig_category":"Congelados: Productos Alimentarios (al Por Menor)",
    "sg:phone":"+34 922 63 64 45",
    "sg:postcode":"38350",
    "sg:province":"Santa Cruz De Tenerife",
    "wof:name":"Frigorificos Frant S. L.",
    "wof:placetype":"venue"
},
  "geometry": {"coordinates":[-16.4174289703,28.4756546021],"type":"Point"}
}