{
  "type": "Feature",
  "properties": {
    "addr:full":"Conj Res Plaza Mayor, S/n Benalmadena-costa M\u00e1laga 29630",
    "addr:housenumber":"s",
    "addr:postcode":"29630",
    "addr:street":"Mayor;/ N Benalmadena-Costa Ma\u0301Laga",
    "iso:country":"ES",
    "sg:address":"Conj Res Plaza Mayor, S/n",
    "sg:city":"Benalmadena-costa",
    "sg:orig_category":"Panader\u00cdas, Panader\u00cdas",
    "sg:phone":"+34 952 57 41 32",
    "sg:postcode":"29630",
    "sg:province":"M\u00e1laga",
    "wof:name":"Panificadora El Bambi",
    "wof:placetype":"venue"
},
  "geometry": {"coordinates":[-4.521381855,36.5971374512],"type":"Point"}
}