{
  "type": "Feature",
  "properties": {
    "addr:full":"Calle de Rio Guadalquivir, 14 Parla Madrid 28980",
    "addr:housenumber":"14",
    "addr:postcode":"28980",
    "addr:street":"Calle De Rio Guadalquivir",
    "iso:country":"ES",
    "sg:address":"Calle de Rio Guadalquivir, 14",
    "sg:city":"Parla",
    "sg:orig_category":"Centros Empresariales",
    "sg:phone":"+34 916 98 16 56",
    "sg:postcode":"28980",
    "sg:province":"Madrid",
    "wof:name":"Pe\u00f1a Villasante Mariano",
    "wof:placetype":"venue"
},
  "geometry": {"coordinates":[-3.7712268829,40.2412757874],"type":"Point"}
}