{
  "type": "Feature",
  "properties": {
    "addr:full":"Calle de Virgen Del Monte, 56 Cazalla Sierra Sevilla 41370",
    "addr:housenumber":"56",
    "addr:postcode":"41370",
    "addr:street":"Calle De Virgen Del Monte",
    "iso:country":"ES",
    "sg:address":"Calle de Virgen Del Monte, 56",
    "sg:city":"Cazalla Sierra",
    "sg:orig_category":"Molduras, Junquillos, Listones Y Molduras Perforadas",
    "sg:phone":"+34 954 88 48 63",
    "sg:postcode":"41370",
    "sg:province":"Sevilla",
    "wof:name":"Garcia Acosta Joaquin",
    "wof:placetype":"venue"
},
  "geometry": {"coordinates":[-5.7591600418,37.9326515198],"type":"Point"}
}