{
  "type": "Feature",
  "properties": {
    "addr:full":"Calle de Soledad (la), 6 Humanes Guadalajara 19220",
    "addr:housenumber":"6",
    "addr:postcode":"19220",
    "addr:street":"Calle De Soledad La",
    "iso:country":"ES",
    "sg:address":"Calle de Soledad (la), 6",
    "sg:city":"Humanes",
    "sg:orig_category":"Caf\u00c9s, Bares, Cervecer\u00cdas",
    "sg:phone":"+34 949 85 12 01",
    "sg:postcode":"19220",
    "sg:province":"Guadalajara",
    "wof:name":"Dominguez Concha Pedro",
    "wof:placetype":"venue"
},
  "geometry": {"coordinates":[-3.1567049026,40.8264541626],"type":"Point"}
}