{
  "type": "Feature",
  "properties": {
    "addr:full":"C/ Jorge Juan, 19 Elche Alicante 03201",
    "addr:housenumber":"19",
    "addr:postcode":"03201",
    "addr:street":"C / Jorge Juan",
    "iso:country":"ES",
    "sg:address":"C/ Jorge Juan, 19",
    "sg:city":"Elche",
    "sg:orig_category":"Asesor\u00cda Sobre Comunicaci\u00d3n De Empresas",
    "sg:phone":"+34 966 67 43 02",
    "sg:postcode":"03201",
    "sg:province":"Alicante",
    "wof:name":"Jose Rodriguez Ramis Y Evaristo Mendiola Valero Cdad",
    "wof:placetype":"venue"
},
  "geometry": {"coordinates":[-0.7046380043,38.2666740417],"type":"Point"}
}