{
  "type": "Feature",
  "properties": {
    "iso:country":"ES",
    "sg:address":"Calle de Doctor Zamenhof, 23",
    "sg:city":"Valencia",
    "sg:orig_category":"Suministros Y Materiales Industriales",
    "sg:phone":"+34 963 82 06 00",
    "sg:postcode":"46008",
    "sg:province":"Valencia",
    "wof:name":"Suministros Industriales Alagarda S. L.",
    "wof:placetype":"venue"
},
  "geometry": {"coordinates":[-0.3925090134,39.4755058289],"type":"Point"}
}