{
  "type": "Feature",
  "properties": {
    "iso:country":"ES",
    "sg:address":"Av Diagonal, 598",
    "sg:city":"Barcelona",
    "sg:orig_category":"Administradores De Bienes Y Delegados De Comunidades De Propietarios",
    "sg:phone":"+34 932 17 22 74",
    "sg:postcode":"08021",
    "sg:province":"Barcelona",
    "wof:name":"Bernat Juanos Francesc Xavier",
    "wof:placetype":"venue"
},
  "geometry": {"coordinates":[2.1457500458,41.3933792114],"type":"Point"}
}