{
  "type": "Feature",
  "properties": {
    "addr:full":"Chan Da Ponte, S/n Chan Da Ponte Pontevedra 36459",
    "addr:housenumber":"s / n",
    "addr:postcode":"36459",
    "iso:country":"ES",
    "sg:address":"Chan Da Ponte, S/n",
    "sg:city":"Chan Da Ponte",
    "sg:orig_category":"Cintas Transportadoras",
    "sg:phone":"+34 986 65 84 52",
    "sg:postcode":"36459",
    "sg:province":"Pontevedra",
    "wof:name":"Vulcanizados Perez S.l.",
    "wof:placetype":"venue"
},
  "geometry": {"coordinates":[-8.587729454,42.4085502625],"type":"Point"}
}