{
  "type": "Feature",
  "properties": {
    "addr:full":"Calle de Asturias, 14 Gijon Asturias 33206",
    "addr:housenumber":"14",
    "addr:postcode":"33206",
    "addr:street":"Calle De Asturias",
    "iso:country":"ES",
    "sg:address":"Calle de Asturias, 14",
    "sg:city":"Gijon",
    "sg:orig_category":"Panader\u00cdas, Panader\u00cdas",
    "sg:phone":"+34 985 34 17 68",
    "sg:postcode":"33206",
    "sg:province":"Asturias",
    "wof:name":"Alvarez Ba\u00f1os Salvador",
    "wof:placetype":"venue"
},
  "geometry": {"coordinates":[-5.6652312279,43.5400009155],"type":"Point"}
}