{
  "type": "Feature",
  "properties": {
    "addr:full":"C/ Cami La Vall, 44 Moncofa Castell\u00f3n 12593",
    "addr:housenumber":"44",
    "addr:postcode":"12593",
    "addr:street":"C / Cami La Vall;Castello\u0301N",
    "iso:country":"ES",
    "sg:address":"C/ Cami La Vall, 44",
    "sg:city":"Moncofa",
    "sg:orig_category":"Fotocopias, Reprograf\u00cda",
    "sg:phone":"+34 964 57 90 01",
    "sg:postcode":"12593",
    "sg:province":"Castell\u00f3n",
    "wof:name":"Perez Obiol Maria Jose",
    "wof:placetype":"venue"
},
  "geometry": {"coordinates":[-0.1429889947,39.8067741394],"type":"Point"}
}