{
  "type": "Feature",
  "properties": {
    "addr:full":"Calle de Santa Maria De Gracia, 43 Camas Sevilla 41900",
    "addr:housenumber":"43",
    "addr:postcode":"41900",
    "addr:street":"Calle De Santa",
    "iso:country":"ES",
    "sg:address":"Calle de Santa Maria De Gracia, 43",
    "sg:city":"Camas",
    "sg:orig_category":"Motocicletas (agentes, Concesionarios)",
    "sg:phone":"+34 954 39 23 51",
    "sg:postcode":"41900",
    "sg:province":"Sevilla",
    "wof:name":"Pi\u00f1ol Mu\u00f1oz Manuel Angel",
    "wof:placetype":"venue"
},
  "geometry": {"coordinates":[-6.0353059769,37.4042663574],"type":"Point"}
}