{
  "type": "Feature",
  "properties": {
    "iso:country":"ES",
    "sg:address":"Carrer de Sabina Sureda, 6",
    "sg:city":"Olot",
    "sg:orig_category":"Agentes Generales De Seguros",
    "sg:phone":"+34 972 26 22 84",
    "sg:postcode":"17800",
    "sg:province":"Girona",
    "wof:name":"Sacrest Ayats Jose Maria",
    "wof:placetype":"venue"
},
  "geometry": {"coordinates":[2.4879000187,42.1796798706],"type":"Point"}
}