{
  "type": "Feature",
  "properties": {
    "iso:country":"ES",
    "sg:address":"Calle de Lago Van, 3",
    "sg:city":"Madrid",
    "sg:orig_category":"Bisuter\u00cda, Joyer\u00cda, Relojer\u00cda (al Por Menor)",
    "sg:phone":"+34 917 76 82 14",
    "sg:postcode":"28032",
    "sg:province":"Madrid",
    "wof:name":"Esteban Blas Alfonso",
    "wof:placetype":"venue"
},
  "geometry": {"coordinates":[-3.6067330837,40.4035987854],"type":"Point"}
}