{
  "type": "Feature",
  "properties": {
    "addr:full":"Avda Real De Pinto, 87 Madrid Madrid 28021",
    "addr:housenumber":"87",
    "addr:postcode":"madrid;28021",
    "addr:street":"Avda Real De Pinto",
    "iso:country":"ES",
    "sg:address":"Avda Real De Pinto, 87",
    "sg:city":"Madrid",
    "sg:orig_category":"Transporte En General",
    "sg:phone":"+34 917 98 19 80",
    "sg:postcode":"28021",
    "sg:province":"Madrid",
    "wof:name":"Madrid Sistemas Comfort S.l.",
    "wof:placetype":"venue"
},
  "geometry": {"coordinates":[-3.7119820118,40.3347091675],"type":"Point"}
}