{
  "type": "Feature",
  "properties": {
    "iso:country":"ES",
    "sg:address":"Calle de Zaragoza, 21",
    "sg:city":"Guadalajara",
    "sg:orig_category":"\u00d3ptica: Instrumentos (fabricaci\u00d3n)",
    "sg:phone":"+34 949 21 99 26",
    "sg:postcode":"19005",
    "sg:province":"Guadalajara",
    "wof:name":"Sanchez Nervion Maria Isabel",
    "wof:placetype":"venue"
},
  "geometry": {"coordinates":[-3.156883955,40.633846283],"type":"Point"}
}