{
  "type": "Feature",
  "properties": {
    "iso:country":"ES",
    "sg:address":"Calle de Martinez De La Rosa, 77",
    "sg:city":"Malaga",
    "sg:orig_category":"Mec\u00c1nico Del Autom\u00d3vil",
    "sg:phone":"+34 952 27 10 54",
    "sg:postcode":"29010",
    "sg:province":"M\u00e1laga",
    "wof:name":"Jimenez Moreno Juan",
    "wof:placetype":"venue"
},
  "geometry": {"coordinates":[-4.4372258186,36.726184845],"type":"Point"}
}