{
  "type": "Feature",
  "properties": {
    "iso:country":"ES",
    "sg:address":"Pol Ind Condor, 10",
    "sg:city":"Amorebieta",
    "sg:orig_category":"Construcciones Met\u00c1licas",
    "sg:phone":"+34 946 73 14 38",
    "sg:postcode":"48340",
    "sg:province":"Vizcaya",
    "wof:name":"Mecanizados Elga S.l.",
    "wof:placetype":"venue"
},
  "geometry": {"coordinates":[-2.7321588993,43.2210960388],"type":"Point"}
}