{
  "type": "Feature",
  "properties": {
    "iso:country":"ES",
    "sg:address":"Calle de Monasterio De Montes, 8",
    "sg:city":"Ponferrada",
    "sg:orig_category":"Caf\u00c9s, Bares, Cervecer\u00cdas",
    "sg:phone":"+34 987 40 54 97",
    "sg:postcode":"24400",
    "sg:province":"Le\u00f3n",
    "wof:name":"Teldespa\u00d1a S.l.",
    "wof:placetype":"venue"
},
  "geometry": {"coordinates":[-6.5871901512,42.547039032],"type":"Point"}
}