{
  "type": "Feature",
  "properties": {
    "addr:full":"Calle de Nemesio Sobrino, S/n Llanes Asturias 33500",
    "addr:housenumber":"s / n",
    "addr:postcode":"33500",
    "addr:street":"Calle De Nemesio Sobrino",
    "iso:country":"ES",
    "sg:address":"Calle de Nemesio Sobrino, S/n",
    "sg:city":"Llanes",
    "sg:orig_category":"Panader\u00cdas, Panader\u00cdas",
    "sg:phone":"+34 985 40 08 60",
    "sg:postcode":"33500",
    "sg:province":"Asturias",
    "wof:name":"Ortegal Fito S.l.",
    "wof:placetype":"venue"
},
  "geometry": {"coordinates":[-4.7560639381,43.4210548401],"type":"Point"}
}