{
  "type": "Feature",
  "properties": {
    "addr:full":"Avda Rafael Alberti, 2 Madrid Madrid 28038",
    "addr:housenumber":"2",
    "addr:postcode":"28038",
    "addr:street":"Avda Rafael Alberti",
    "iso:country":"ES",
    "sg:address":"Avda Rafael Alberti, 2",
    "sg:city":"Madrid",
    "sg:orig_category":"Empresarios",
    "sg:phone":"+34 913 80 56 90",
    "sg:postcode":"28038",
    "sg:province":"Madrid",
    "wof:name":"Fundacion Tomillo",
    "wof:placetype":"venue"
},
  "geometry": {"coordinates":[-3.6399619579,40.3884315491],"type":"Point"}
}