{
  "type": "Feature",
  "properties": {
    "iso:country":"ES",
    "sg:address":"Calle de Santa Rosa, 2",
    "sg:city":"Cordoba",
    "sg:orig_category":"Alimentaci\u00d3n General (al Por Menor)",
    "sg:phone":"+34 957 27 40 76",
    "sg:postcode":"14006",
    "sg:province":"C\u00f3rdoba",
    "wof:name":"Ayala Romero Juan Jose",
    "wof:placetype":"venue"
},
  "geometry": {"coordinates":[-4.7804179192,37.8967018127],"type":"Point"}
}