{
  "type": "Feature",
  "properties": {
    "iso:country":"ES",
    "sg:address":"Ctra Farhana, 98",
    "sg:city":"Melilla",
    "sg:orig_category":"Internados & Ense\u00d1anza Privada",
    "sg:phone":"+34 952 67 71 19",
    "sg:postcode":"52005",
    "sg:province":"Melilla",
    "wof:name":"Hermanas Terciarias Franciscanas De Los Sagrados Corazones",
    "wof:placetype":"venue"
},
  "geometry": {"coordinates":[-2.9577190876,35.2935905457],"type":"Point"}
}