{
  "type": "Feature",
  "properties": {
    "addr:full":"Avda Guatemala, 24 Huelva Huelva 21003",
    "addr:housenumber":"24",
    "addr:postcode":"21003",
    "addr:street":"Avda Guatemala",
    "iso:country":"ES",
    "sg:address":"Avda Guatemala, 24",
    "sg:city":"Huelva",
    "sg:orig_category":"Fabrica De Charcuter\u00cda",
    "sg:phone":"+34 959 27 18 05",
    "sg:postcode":"21003",
    "sg:province":"Huelva",
    "wof:name":"La Serrania De Jabugo S.l.",
    "wof:placetype":"venue"
},
  "geometry": {"coordinates":[-6.9374489784,37.2536354065],"type":"Point"}
}