{
  "type": "Feature",
  "properties": {
    "addr:full":"Euskadi Etorbidea, 1 Pasai S. Pedro Guip\u00f9zcoa 20110",
    "addr:housenumber":"1",
    "addr:postcode":"20110",
    "addr:street":"Euskadi Etorbidea;Guipu\u0300Zcoa",
    "iso:country":"ES",
    "sg:address":"Euskadi Etorbidea, 1",
    "sg:city":"Pasai S. Pedro",
    "sg:orig_category":"Caf\u00c9s, Bares, Cervecer\u00cdas",
    "sg:phone":"+34 943 39 97 61",
    "sg:postcode":"20110",
    "sg:province":"Guip\u00f9zcoa",
    "wof:name":"Sistelcom-telemensaje S.a.",
    "wof:placetype":"venue"
},
  "geometry": {"coordinates":[-1.9300839901,43.3229217529],"type":"Point"}
}