{
  "type": "Feature",
  "properties": {
    "iso:country":"ES",
    "sg:address":"Rua Terra, 41",
    "sg:city":"Ferrol",
    "sg:orig_category":"M\u00c9dicos: An\u00c1lisis Cl\u00cdnicos",
    "sg:phone":"+34 981 35 17 09",
    "sg:postcode":"15402",
    "sg:province":"La Coru\u00f1a",
    "wof:name":"Laboratio Punin",
    "wof:placetype":"venue"
},
  "geometry": {"coordinates":[-8.2342653275,43.4852981567],"type":"Point"}
}