{
  "type": "Feature",
  "properties": {
    "addr:full":"Carrer de Comte De Barcelona, 19 Palma Islas Baleares 07013",
    "addr:housenumber":"19",
    "addr:postcode":"07013",
    "addr:street":"Carrer De Comte De Barcelona",
    "iso:country":"ES",
    "sg:address":"Carrer de Comte De Barcelona, 19",
    "sg:city":"Palma",
    "sg:orig_category":"Electrodom\u00c9sticos (al Por Menor)",
    "sg:phone":"+34 971 73 08 91",
    "sg:postcode":"07013",
    "sg:province":"Islas Baleares",
    "wof:name":"Gomez Moreno Sebastian",
    "wof:placetype":"venue"
},
  "geometry": {"coordinates":[2.638094902,39.5730361938],"type":"Point"}
}