{
  "type": "Feature",
  "properties": {
    "iso:country":"ES",
    "sg:address":"Calle de Hernan Cortes, 8",
    "sg:city":"Navalmorales",
    "sg:orig_category":"Carnicer\u00cdas, Carnicer\u00cdas",
    "sg:phone":"+34 925 40 50 75",
    "sg:postcode":"45140",
    "sg:province":"Toledo",
    "wof:name":"Pineda Estrella Julian",
    "wof:placetype":"venue"
},
  "geometry": {"coordinates":[-4.6447439194,39.729221344],"type":"Point"}
}