{
  "type": "Feature",
  "properties": {
    "addr:full":"Carrer de Guadiana, 32 Barcelona Barcelona 08014",
    "addr:housenumber":"32",
    "addr:postcode":"08014",
    "addr:street":"Carrer De Guadiana",
    "iso:country":"ES",
    "sg:address":"Carrer de Guadiana, 32",
    "sg:city":"Barcelona",
    "sg:orig_category":"Papeler\u00cdas, Librer\u00cdas",
    "sg:phone":"+34 934 22 98 16",
    "sg:postcode":"08014",
    "sg:province":"Barcelona",
    "wof:name":"Cerdan Vega Victor",
    "wof:placetype":"venue"
},
  "geometry": {"coordinates":[2.1392381191,41.3737220764],"type":"Point"}
}