{
  "type": "Feature",
  "properties": {
    "addr:full":"Calle de Corazon De Maria, 54 Madrid Madrid 28002",
    "addr:housenumber":"54",
    "addr:postcode":"madrid;28002",
    "addr:street":"Calle De Corazon;Maria",
    "iso:country":"ES",
    "sg:address":"Calle de Corazon De Maria, 54",
    "sg:city":"Madrid",
    "sg:orig_category":"Arquitectos",
    "sg:phone":"+34 915 19 58 30",
    "sg:postcode":"28002",
    "sg:province":"Madrid",
    "wof:name":"Gonzalez Jimenez Arquitectos S.l.",
    "wof:placetype":"venue"
},
  "geometry": {"coordinates":[-3.6666870117,40.4455947876],"type":"Point"}
}