{
  "type": "Feature",
  "properties": {
    "addr:full":"Calle de Igorreko Industrialdea, S/n Sabino Arana Vizcaya 48140",
    "addr:housenumber":"s / n",
    "addr:postcode":"48140",
    "addr:street":"Calle De Igorreko Industrialdea;Sabino Arana Vizcaya",
    "iso:country":"ES",
    "sg:address":"Calle de Igorreko Industrialdea, S/n",
    "sg:city":"Sabino Arana",
    "sg:orig_category":"L\u00c1ser (fabricaci\u00d3n Y Aplicaciones)",
    "sg:phone":"+34 946 31 56 79",
    "sg:postcode":"48140",
    "sg:province":"Vizcaya",
    "wof:name":"Laskort S.l.",
    "wof:placetype":"venue"
},
  "geometry": {"coordinates":[-2.7739768028,43.156829834],"type":"Point"}
}