{
  "type": "Feature",
  "properties": {
    "addr:full":"Calle de Ciscar, 26 Valencia Valencia 46005",
    "addr:housenumber":"26",
    "addr:postcode":"46005",
    "addr:street":"Calle De Ciscar",
    "iso:country":"ES",
    "sg:address":"Calle de Ciscar, 26",
    "sg:city":"Valencia",
    "sg:orig_category":"Abogados",
    "sg:phone":"+34 963 73 29 83",
    "sg:postcode":"46005",
    "sg:province":"Valencia",
    "wof:name":"Pe\u00f1a Parre\u00f1o Manuel",
    "wof:placetype":"venue"
},
  "geometry": {"coordinates":[-0.3656263947,39.4659729004],"type":"Point"}
}