{
  "type": "Feature",
  "properties": {
    "iso:country":"ES",
    "sg:address":"Calle de Conejo, 5",
    "sg:city":"Hernansancho",
    "sg:orig_category":"Alimentaci\u00d3n General (al Por Menor)",
    "sg:phone":"+34 920 26 10 30",
    "sg:postcode":"05164",
    "sg:province":"\u00c1vila",
    "wof:name":"Aldudo Saez Ernesto",
    "wof:placetype":"venue"
},
  "geometry": {"coordinates":[-4.7281990051,40.8593711853],"type":"Point"}
}