{
  "type": "Feature",
  "properties": {
    "iso:country":"ES",
    "sg:address":"Carr Ramon Llull, 42",
    "sg:city":"Pollen\u00e7a",
    "sg:orig_category":"Promotores Constructores",
    "sg:phone":"+34 971 53 08 31",
    "sg:postcode":"07460",
    "sg:province":"Islas Baleares",
    "wof:name":"Llobera Bota Jose",
    "wof:placetype":"venue"
},
  "geometry": {"coordinates":[3.0190110207,39.8783912659],"type":"Point"}
}