{
  "type": "Feature",
  "properties": {
    "iso:country":"ES",
    "sg:address":"Calle de Racimo, S/n",
    "sg:city":"Jerez De La Frontera",
    "sg:orig_category":"Internados & Ense\u00d1anza Privada",
    "sg:phone":"+34 956 30 45 89",
    "sg:postcode":"11407",
    "sg:province":"C\u00e1diz",
    "wof:name":"Escuelas Profesionales Sagrada Familia",
    "wof:placetype":"venue"
},
  "geometry": {"coordinates":[-6.1402339935,36.698890686],"type":"Point"}
}