{
  "type": "Feature",
  "properties": {
    "addr:full":"Avda Marques De Sotelo, 9 Valencia Valencia 46002",
    "addr:housenumber":"9",
    "addr:postcode":"46002",
    "addr:street":"Avda Marques De Sotelo",
    "iso:country":"ES",
    "sg:address":"Avda Marques De Sotelo, 9",
    "sg:city":"Valencia",
    "sg:orig_category":"Abogados",
    "sg:phone":"+34 963 51 53 71",
    "sg:postcode":"46002",
    "sg:province":"Valencia",
    "wof:name":"Verdu Sancho Carlos",
    "wof:placetype":"venue"
},
  "geometry": {"coordinates":[-0.3768979907,39.4682197571],"type":"Point"}
}