{
  "type": "Feature",
  "properties": {
    "addr:full":"Ctra Bolulla (de), 110 Callosa D'en Sarria Alicante 03510",
    "addr:housenumber":"110",
    "addr:postcode":"03510",
    "addr:street":"Ctra Bolulla De",
    "iso:country":"ES",
    "sg:address":"Ctra Bolulla (de), 110",
    "sg:city":"Callosa D'en Sarria",
    "sg:orig_category":"Quincaller\u00cda (al Por Menor)",
    "sg:phone":"+34 965 88 03 55",
    "sg:postcode":"03510",
    "sg:province":"Alicante",
    "wof:name":"Ferreteria Palacio 2003 S.l.",
    "wof:placetype":"venue"
},
  "geometry": {"coordinates":[-0.1186437011,38.6509284973],"type":"Point"}
}