{
  "type": "Feature",
  "properties": {
    "addr:full":"Coop Vvdas San Rafael, 52 Santaella C\u00f3rdoba 14546",
    "addr:housenumber":"52",
    "addr:postcode":"14546",
    "addr:street":"San Rafael;Co\u0301Rdoba",
    "iso:country":"ES",
    "sg:address":"Coop Vvdas San Rafael, 52",
    "sg:city":"Santaella",
    "sg:orig_category":"Reposter\u00cdas",
    "sg:phone":"+34 957 31 37 98",
    "sg:postcode":"14546",
    "sg:province":"C\u00f3rdoba",
    "wof:name":"Perez Cruz Feliciano",
    "wof:placetype":"venue"
},
  "geometry": {"coordinates":[-4.8407640457,37.5633239746],"type":"Point"}
}