{
  "type": "Feature",
  "properties": {
    "iso:country":"ES",
    "sg:address":"Calle de Francos Rodriguez, 28",
    "sg:city":"Madrid",
    "sg:orig_category":"Cajas De Ahorro",
    "sg:phone":"+34 914 50 53 03",
    "sg:postcode":"28039",
    "sg:province":"Madrid",
    "wof:name":"Caixa D'estalvis I Pensions De Barcelona",
    "wof:placetype":"venue"
},
  "geometry": {"coordinates":[-3.7042770386,40.4558372498],"type":"Point"}
}