{
  "type": "Feature",
  "properties": {
    "iso:country":"ES",
    "sg:address":"Calle de San Marcos, 15",
    "sg:city":"Don Benito",
    "sg:orig_category":"Administradores De Bienes Y Delegados De Comunidades De Propietarios",
    "sg:phone":"+34 924 81 03 42",
    "sg:postcode":"06400",
    "sg:province":"Badajoz",
    "wof:name":"Administracion De Fincas Vegas Altas S.l.",
    "wof:placetype":"venue"
},
  "geometry": {"coordinates":[-5.8606739044,38.9590606689],"type":"Point"}
}