{
  "type": "Feature",
  "properties": {
    "addr:full":"Calle de Virgen De Los Desamparados, 4 Novelda Alicante 03660",
    "addr:housenumber":"4",
    "addr:postcode":"03660",
    "addr:street":"Calle De Virgen De Los Desamparados",
    "iso:country":"ES",
    "sg:address":"Calle de Virgen De Los Desamparados, 4",
    "sg:city":"Novelda",
    "sg:orig_category":"M\u00c1rmoles, Granitos Y Piedras Naturales",
    "sg:phone":"+34 965 60 12 74",
    "sg:postcode":"03660",
    "sg:province":"Alicante",
    "wof:name":"Piedraparket S.l.",
    "wof:placetype":"venue"
},
  "geometry": {"coordinates":[-0.7634660006,38.3845825195],"type":"Point"}
}