{
  "type": "Feature",
  "properties": {
    "iso:country":"ES",
    "sg:address":"Avda Constitucion, S/n",
    "sg:city":"Boiro",
    "sg:orig_category":"Abogados",
    "sg:phone":"+34 981 84 63 53",
    "sg:postcode":"15930",
    "sg:province":"La Coru\u00f1a",
    "wof:name":"Fajardo Otero Luis",
    "wof:placetype":"venue"
},
  "geometry": {"coordinates":[-8.8791770935,42.6474685669],"type":"Point"}
}