{
  "type": "Feature",
  "properties": {
    "iso:country":"ES",
    "sg:address":"Carrer de Nicaragua, S/n",
    "sg:city":"Mollet Valles",
    "sg:orig_category":"Transportes Por Carretera: Lotes Completos, Mercanc\u00cdas Diversas",
    "sg:phone":"+34 935 79 31 78",
    "sg:postcode":"08100",
    "sg:province":"Barcelona",
    "wof:name":"Valles Preu S.a.",
    "wof:placetype":"venue"
},
  "geometry": {"coordinates":[2.2051110268,41.5489883423],"type":"Point"}
}