{
  "type": "Feature",
  "properties": {
    "iso:country":"ES",
    "sg:address":"Avda Eladio Perlado, 30",
    "sg:city":"Burgos",
    "sg:orig_category":"Perfumer\u00cda (al Por Menor)",
    "sg:phone":"+34 947 23 75 61",
    "sg:postcode":"09007",
    "sg:province":"Burgos",
    "wof:name":"Perez Garcia Maria Azucena",
    "wof:placetype":"venue"
},
  "geometry": {"coordinates":[-3.6673629284,42.3508987427],"type":"Point"}
}