{
  "type": "Feature",
  "properties": {
    "addr:full":"Calle de Uno De Mayo, 85 Pedrera Sevilla 41566",
    "addr:housenumber":"85",
    "addr:postcode":"41566",
    "addr:street":"Calle De Uno De Mayo",
    "iso:country":"ES",
    "sg:address":"Calle de Uno De Mayo, 85",
    "sg:city":"Pedrera",
    "sg:orig_category":"Cajas Para Embalar",
    "sg:phone":"+34 954 81 90 30",
    "sg:postcode":"41566",
    "sg:province":"Sevilla",
    "sg:website":"www.cajarural.es",
    "wof:name":"Caja Rural Del Sur Sociedad Cooperativa",
    "wof:placetype":"venue"
},
  "geometry": {"coordinates":[-4.8958492279,37.2228164673],"type":"Point"}
}