{
  "type": "Feature",
  "properties": {
    "iso:country":"ES",
    "sg:address":"Calle de Santa Rosa De Lima, 1",
    "sg:city":"Santa Cruz De Tenerife",
    "sg:orig_category":"Abogados",
    "sg:phone":"+34 922 27 81 82",
    "sg:postcode":"38002",
    "sg:province":"Santa Cruz De Tenerife",
    "wof:name":"Oramas Reyes Maria Gloria",
    "wof:placetype":"venue"
},
  "geometry": {"coordinates":[-16.2502288818,28.4692764282],"type":"Point"}
}