{
  "type": "Feature",
  "properties": {
    "addr:full":"Rua Do Castro, 23 Donramiro Pontevedra 36500",
    "addr:housenumber":"23",
    "addr:postcode":"36500",
    "addr:street":"Rua Do Castro",
    "iso:country":"ES",
    "sg:address":"Rua Do Castro, 23",
    "sg:city":"Donramiro",
    "sg:orig_category":"Electrodom\u00c9sticos (al Por Menor)",
    "sg:phone":"+34 986 78 11 04",
    "sg:postcode":"36500",
    "sg:province":"Pontevedra",
    "wof:name":"Te Se Deza S.l.",
    "wof:placetype":"venue"
},
  "geometry": {"coordinates":[-8.1106138229,42.6577606201],"type":"Point"}
}