{
  "type": "Feature",
  "properties": {
    "iso:country":"ES",
    "sg:address":"Carrer de Sant Antoni Maria Claret, 514",
    "sg:city":"Barcelona",
    "sg:orig_category":"Lencer\u00cda Femenina, Corseter\u00cda, Trajes De Ba\u00d1o (al Por Menor)",
    "sg:phone":"+34 933 49 48 04",
    "sg:postcode":"08027",
    "sg:province":"Barcelona",
    "wof:name":"Covede S.l.",
    "wof:placetype":"venue"
},
  "geometry": {"coordinates":[2.1887769699,41.421710968],"type":"Point"}
}