{
  "type": "Feature",
  "properties": {
    "iso:country":"ES",
    "sg:address":"Pso Fernandez Caballero, 8",
    "sg:city":"Murcia",
    "sg:orig_category":"Asesor\u00cda Sobre Comunicaci\u00d3n De Empresas",
    "sg:phone":"+34 968 20 30 00",
    "sg:postcode":"30007",
    "sg:province":"Murcia",
    "wof:name":"Gabinete Asesor De Murcia S.l.",
    "wof:placetype":"venue"
},
  "geometry": {"coordinates":[-1.1294690371,38.0024986267],"type":"Point"}
}