{
  "type": "Feature",
  "properties": {
    "iso:country":"ES",
    "sg:address":"Calle de Marquesa De Pinares, 39",
    "sg:city":"Merida",
    "sg:orig_category":"Venta, Instalaci\u00d3n De Calefacci\u00d3n",
    "sg:phone":"+34 924 31 25 11",
    "sg:postcode":"06800",
    "sg:province":"Badajoz",
    "wof:name":"Mena Moreno Vicente",
    "wof:placetype":"venue"
},
  "geometry": {"coordinates":[-6.3475961685,38.9215202332],"type":"Point"}
}