{
  "type": "Feature",
  "properties": {
    "iso:country":"ES",
    "sg:address":"Pl. Los Fueros, 16",
    "sg:city":"Estella",
    "sg:orig_category":"Relojer\u00cda (al Por Menor, Reparaci\u00d3n)",
    "sg:phone":"+34 948 55 09 90",
    "sg:postcode":"31200",
    "sg:province":"Navarra",
    "wof:name":"Campos Clerigue Beatriz",
    "wof:placetype":"venue"
},
  "geometry": {"coordinates":[-2.0320260525,42.6720733643],"type":"Point"}
}