{
  "type": "Feature",
  "properties": {
    "addr:full":"Nafarroa Etorbidea, 53 Beasain Guip\u00f9zcoa 20200",
    "addr:housenumber":"53",
    "addr:postcode":"20200",
    "addr:street":"Nafarroa Etorbidea;Guipu\u0300Zcoa",
    "iso:country":"ES",
    "sg:address":"Nafarroa Etorbidea, 53",
    "sg:city":"Beasain",
    "sg:orig_category":"Peluquer\u00cdas, Peluquer\u00cda Mixta",
    "sg:phone":"+34 943 88 23 40",
    "sg:postcode":"20200",
    "sg:province":"Guip\u00f9zcoa",
    "wof:name":"Garmendia Sukia Mari Paz",
    "wof:placetype":"venue"
},
  "geometry": {"coordinates":[-2.2064027786,43.0471191406],"type":"Point"}
}