{
  "type": "Feature",
  "properties": {
    "iso:country":"ES",
    "sg:address":"Calle de Virgen De La Vega, 21",
    "sg:city":"Haro",
    "sg:orig_category":"Panader\u00cdas, Panader\u00cdas",
    "sg:phone":"+34 941 31 05 97",
    "sg:postcode":"26200",
    "sg:province":"La Rioja",
    "wof:name":"Pozo Martinez Angel",
    "wof:placetype":"venue"
},
  "geometry": {"coordinates":[-2.8490080833,42.5769271851],"type":"Point"}
}