{
  "type": "Feature",
  "properties": {
    "iso:country":"ES",
    "sg:address":"Carrer de Escudellers, 6",
    "sg:city":"Barcelona",
    "sg:orig_category":"Zapatos (al Por Menor)",
    "sg:phone":"+34 933 02 41 59",
    "sg:postcode":"08002",
    "sg:province":"Barcelona",
    "wof:name":"Valdeperas Su\u00f1er Jose Maria",
    "wof:placetype":"venue"
},
  "geometry": {"coordinates":[2.1760599613,41.3790473938],"type":"Point"}
}