{
  "type": "Feature",
  "properties": {
    "iso:country":"ES",
    "sg:address":"Pl Nova, 1",
    "sg:city":"Vendrell",
    "sg:orig_category":"Ropa Para Se\u00d1oras (al Por Menor)",
    "sg:phone":"+34 977 66 55 82",
    "sg:postcode":"43700",
    "sg:province":"Tarragona",
    "wof:name":"Mascaro Soler Maria Dolores",
    "wof:placetype":"venue"
},
  "geometry": {"coordinates":[1.5349040031,41.2213821411],"type":"Point"}
}