{
  "type": "Feature",
  "properties": {
    "iso:country":"ES",
    "sg:address":"Av. Pio Xii, 45",
    "sg:city":"Iru\u00f1a",
    "sg:orig_category":"Deporte (estadios Y Complejos Deportivos)",
    "sg:phone":"+34 948 36 60 11",
    "sg:postcode":"31008",
    "sg:province":"Navarra",
    "wof:name":"Claretianos Misioneros Corazon Maria Casa Pamplona",
    "wof:placetype":"venue"
},
  "geometry": {"coordinates":[-1.6614309549,42.8061828613],"type":"Point"}
}