{
  "type": "Feature",
  "properties": {
    "addr:full":"Calle de Bernabe Soriano, 22 Jaen Ja\u00e9n 23001",
    "addr:housenumber":"22;jae\u0301n",
    "addr:postcode":"23001",
    "addr:street":"Calle De Bernabe Soriano",
    "iso:country":"ES",
    "sg:address":"Calle de Bernabe Soriano, 22",
    "sg:city":"Jaen",
    "sg:orig_category":"Telas Y Sedas (al Por Menor)",
    "sg:phone":"+34 953 24 05 94",
    "sg:postcode":"23001",
    "sg:province":"Ja\u00e9n",
    "wof:name":"Espinosa Garcia-olalla Francisco",
    "wof:placetype":"venue"
},
  "geometry": {"coordinates":[-3.7878088951,37.7665481567],"type":"Point"}
}