{
  "type": "Feature",
  "properties": {
    "iso:country":"ES",
    "sg:address":"Ctra Perales (m-220), Km. 0002,6",
    "sg:city":"Campo Real",
    "sg:orig_category":"Construcciones Met\u00c1licas",
    "sg:phone":"+34 918 73 35 62",
    "sg:postcode":"28510",
    "sg:province":"Madrid",
    "wof:name":"Gona S.a.",
    "wof:placetype":"venue"
},
  "geometry": {"coordinates":[-3.3764793873,40.3396720886],"type":"Point"}
}