{
  "type": "Feature",
  "properties": {
    "iso:country":"ES",
    "sg:address":"Bard Blas Infante, S/n",
    "sg:city":"Manzanilla",
    "sg:orig_category":"Sanatorios M\u00c9dico",
    "sg:phone":"+34 959 41 51 84",
    "sg:postcode":"21890",
    "sg:province":"Huelva",
    "wof:name":"Instituto Nacional De Gestion Sanitaria",
    "wof:placetype":"venue"
},
  "geometry": {"coordinates":[-6.4378800392,37.3890533447],"type":"Point"}
}