{
  "type": "Feature",
  "properties": {
    "iso:country":"ES",
    "sg:address":"Calle de Torrene, 13",
    "sg:city":"Algorta",
    "sg:orig_category":"M\u00c9dicos: Oftalmolog\u00cda",
    "sg:phone":"+34 944 60 87 65",
    "sg:postcode":"48991",
    "sg:province":"Vizcaya",
    "wof:name":"Martinez Compadre Jesus Alberto",
    "wof:placetype":"venue"
},
  "geometry": {"coordinates":[-3.0105876923,43.3506469727],"type":"Point"}
}