{
  "type": "Feature",
  "properties": {
    "addr:full":"Carrer de Major, 12 Amposta Tarragona 43870",
    "addr:housenumber":"12",
    "addr:postcode":"43870",
    "addr:street":"Carrer De Major",
    "iso:country":"ES",
    "sg:address":"Carrer de Major, 12",
    "sg:city":"Amposta",
    "sg:classifiers":[
        {
            "category":"Personal",
            "subcategory":"Barber",
            "type":"Services"
        }
    ],
    "sg:phone":"+34 977 70 46 27",
    "sg:postcode":"43870",
    "sg:province":"Tarragona",
    "sg:tags":[
        "caballeros",
        "de",
        "peluqueros"
    ],
    "wof:name":"Llobat Miro Jesus",
    "wof:placetype":"venue"
},
  "geometry": {"coordinates":[0.580689013,40.7130126953],"type":"Point"}
}