{
  "type": "Feature",
  "properties": {
    "addr:full":"Calle de San Pedro Alcantara, 4 Torrent Valencia 46900",
    "addr:housenumber":"4",
    "addr:postcode":"46900",
    "addr:street":"Calle De San;Alcantara;Valencia",
    "iso:country":"ES",
    "sg:address":"Calle de San Pedro Alcantara, 4",
    "sg:city":"Torrent",
    "sg:orig_category":"Poller\u00cda Y Caza (al Por Menor)",
    "sg:phone":"+34 961 55 24 93",
    "sg:postcode":"46900",
    "sg:province":"Valencia",
    "wof:name":"Benavent Chulia Abelardo",
    "wof:placetype":"venue"
},
  "geometry": {"coordinates":[-0.4662469923,39.4340858459],"type":"Point"}
}