{
  "type": "Feature",
  "properties": {
    "iso:country":"ES",
    "sg:address":"Carrer de Creu Coberta, 93",
    "sg:city":"Barcelona",
    "sg:orig_category":"Papeler\u00cdas: Art\u00cdculos (al Por Mayor)",
    "sg:phone":"+34 934 22 20 84",
    "sg:postcode":"08014",
    "sg:province":"Barcelona",
    "sg:website":"www.abacus.es",
    "wof:name":"Abacus Sdad. Coop. Catalana Limitada",
    "wof:placetype":"venue"
},
  "geometry": {"coordinates":[2.143657,41.375225],"type":"Point"}
}