{
  "type": "Feature",
  "properties": {
    "addr:full":"Carrer de Sant Pere, 14 Cambrils Tarragona 43850",
    "addr:housenumber":"14",
    "addr:postcode":"43850",
    "addr:street":"Carrer De Sant Pere",
    "iso:country":"ES",
    "sg:address":"Carrer de Sant Pere, 14",
    "sg:city":"Cambrils",
    "sg:orig_category":"Ropa Para Se\u00d1oras (al Por Menor)",
    "sg:phone":"+34 977 36 36 09",
    "sg:postcode":"43850",
    "sg:province":"Tarragona",
    "wof:name":"Sarsal Solichero Jose Maria",
    "wof:placetype":"venue"
},
  "geometry": {"coordinates":[1.0622099638,41.0661506653],"type":"Point"}
}