{
  "type": "Feature",
  "properties": {
    "iso:country":"ES",
    "sg:address":"Ctra San Vicente, Km. 0010,2",
    "sg:city":"Agost",
    "sg:orig_category":"Mec\u00c1nico Del Autom\u00d3vil",
    "sg:phone":"+34 965 69 12 70",
    "sg:postcode":"03698",
    "sg:province":"Alicante",
    "wof:name":"Catony Motor S.l.",
    "wof:placetype":"venue"
},
  "geometry": {"coordinates":[-0.6349989772,38.4366798401],"type":"Point"}
}