{
  "type": "Feature",
  "properties": {
    "addr:full":"Calle de Marina (la), 15 Abrigos Santa Cruz De Tenerife 38639",
    "addr:housenumber":"15",
    "addr:postcode":"38639",
    "addr:street":"Calle De Marina La",
    "iso:country":"ES",
    "sg:address":"Calle de Marina (la), 15",
    "sg:city":"Abrigos",
    "sg:orig_category":"Panader\u00cdas, Panader\u00cdas",
    "sg:phone":"+34 922 17 01 56",
    "sg:postcode":"38639",
    "sg:province":"Santa Cruz De Tenerife",
    "wof:name":"Pasteleria Floype S.l.l.",
    "wof:placetype":"venue"
},
  "geometry": {"coordinates":[-16.6115474701,28.0350246429],"type":"Point"}
}