{
  "type": "Feature",
  "properties": {
    "iso:country":"ES",
    "sg:address":"Av Pavos (els), 30",
    "sg:city":"Blanes",
    "sg:orig_category":"Farmacias",
    "sg:phone":"+34 972 33 83 34",
    "sg:postcode":"17300",
    "sg:province":"Girona",
    "wof:name":"Cots Clariana Ana Maria",
    "wof:placetype":"venue"
},
  "geometry": {"coordinates":[2.7844350338,41.6744613647],"type":"Point"}
}