{
  "type": "Feature",
  "properties": {
    "addr:full":"Calle de Miguel Sanchez, 44 Pruna Sevilla 41670",
    "addr:housenumber":"44",
    "addr:postcode":"41670",
    "addr:street":"Calle De Miguel Sanchez",
    "iso:country":"ES",
    "sg:address":"Calle de Miguel Sanchez, 44",
    "sg:city":"Pruna",
    "sg:classifiers":[
        {
            "category":"Taxi",
            "type":"Transportation"
        }
    ],
    "sg:phone":"+34 954 85 83 40",
    "sg:postcode":"41670",
    "sg:province":"Sevilla",
    "wof:name":"Fernandez Jimenez Roque",
    "wof:placetype":"venue"
},
  "geometry": {"coordinates":[-5.2198719978,36.9737854004],"type":"Point"}
}