{
  "type": "Feature",
  "properties": {
    "addr:full":"Carr Pla, S/n Algerri Lleida 25130",
    "addr:housenumber":"/ n",
    "addr:postcode":"25130",
    "addr:street":"Carr Pla S",
    "iso:country":"ES",
    "sg:address":"Carr Pla, S/n",
    "sg:city":"Algerri",
    "sg:orig_category":"Empresarios",
    "sg:phone":"+34 973 42 61 20",
    "sg:postcode":"25130",
    "sg:province":"Lleida",
    "wof:name":"Lopez Garcia Alfonso",
    "wof:placetype":"venue"
},
  "geometry": {"coordinates":[0.6381819844,41.8139686584],"type":"Point"}
}