{
  "type": "Feature",
  "properties": {
    "addr:full":"Carrer de Ricardo Caro, 73 Terrassa Barcelona 08222",
    "addr:housenumber":"73",
    "addr:postcode":"08222",
    "addr:street":"Carrer De Ricardo Caro",
    "iso:country":"ES",
    "sg:address":"Carrer de Ricardo Caro, 73",
    "sg:city":"Terrassa",
    "sg:orig_category":"Agencias Y Agentes Comerciales, Representantes",
    "sg:phone":"+34 937 31 46 07",
    "sg:postcode":"08222",
    "sg:province":"Barcelona",
    "wof:name":"Vilaro Pueyo Francisco Javier",
    "wof:placetype":"venue"
},
  "geometry": {"coordinates":[2.0260820389,41.5655021667],"type":"Point"}
}