{
  "type": "Feature",
  "properties": {
    "addr:full":"Calle de Paredes De Nava, 3 Madrid Madrid 28017",
    "addr:housenumber":"3",
    "addr:postcode":"28017",
    "addr:street":"Calle De Paredes De Nava",
    "iso:country":"ES",
    "sg:address":"Calle de Paredes De Nava, 3",
    "sg:city":"Madrid",
    "sg:orig_category":"Peluqueros: De Se\u00d1oras",
    "sg:phone":"+34 913 04 50 82",
    "sg:postcode":"28017",
    "sg:province":"Madrid",
    "wof:name":"Palmero Ruiz Ana",
    "wof:placetype":"venue"
},
  "geometry": {"coordinates":[-3.6268599033,40.4210090637],"type":"Point"}
}