{
  "type": "Feature",
  "properties": {
    "iso:country":"ES",
    "sg:address":"Part. Burga, S/n",
    "sg:city":"Reus",
    "sg:orig_category":"Producci\u00d3n, Venta De Productos De Agricultura Biol\u00d3gica",
    "sg:phone":"+34 977 34 04 92",
    "sg:postcode":"43206",
    "sg:province":"Tarragona",
    "wof:name":"Agricola Alcover S. A.",
    "wof:placetype":"venue"
},
  "geometry": {"coordinates":[1.1400997639,41.1496086121],"type":"Point"}
}