{
  "type": "Feature",
  "properties": {
    "iso:country":"ES",
    "sg:address":"Calle de Guadalix, 4",
    "sg:city":"Madrid",
    "sg:orig_category":"Cojinetes De Bolas, Agujas Y Rodillos (fabricaci\u00d3n, Al Por Mayor)",
    "sg:phone":"+34 914 59 49 29",
    "sg:postcode":"28039",
    "sg:province":"Madrid",
    "wof:name":"Talleres Gutierrez Alvarez S.l.",
    "wof:placetype":"venue"
},
  "geometry": {"coordinates":[-3.7094419003,40.4576339722],"type":"Point"}
}