{
  "type": "Feature",
  "properties": {
    "iso:country":"ES",
    "sg:address":"Carrer de Roig I Jalpi, 14",
    "sg:city":"Pineda Mar",
    "sg:orig_category":"Psic\u00d3logos",
    "sg:phone":"+34 937 62 59 56",
    "sg:postcode":"08397",
    "sg:province":"Barcelona",
    "wof:name":"Iscla Aragones Artur",
    "wof:placetype":"venue"
},
  "geometry": {"coordinates":[2.6887381077,41.6270294189],"type":"Point"}
}