{
  "type": "Feature",
  "properties": {
    "iso:country":"ES",
    "sg:address":"C/ Mossen Baldiri Reixach, 188",
    "sg:city":"Banyoles",
    "sg:orig_category":"Ropa Para Se\u00d1oras (al Por Menor)",
    "sg:phone":"+34 972 58 01 82",
    "sg:postcode":"17820",
    "sg:province":"Girona",
    "wof:name":"Diaz Gonzalez Concepcion",
    "wof:placetype":"venue"
},
  "geometry": {"coordinates":[2.7668149471,42.113571167],"type":"Point"}
}