{
  "type": "Feature",
  "properties": {
    "iso:country":"ES",
    "sg:address":"Calle de Isabel La Catolica, 23",
    "sg:city":"Mislata",
    "sg:orig_category":"Peluqueros: De Se\u00d1oras",
    "sg:phone":"+34 963 79 78 98",
    "sg:postcode":"46920",
    "sg:province":"Valencia",
    "wof:name":"Mazcu\u00f1an Villarreal Maria Teresa",
    "wof:placetype":"venue"
},
  "geometry": {"coordinates":[-0.415948987,39.4716682434],"type":"Point"}
}