{
  "type": "Feature",
  "properties": {
    "addr:full":"Del Medio, 20 S. Sebastian Gomera Santa Cruz De Tenerife 38800",
    "addr:housenumber":"20",
    "addr:postcode":"38800",
    "addr:street":"Del Medio;S. Sebastian Gomera",
    "iso:country":"ES",
    "sg:address":"Del Medio, 20",
    "sg:city":"S. Sebastian Gomera",
    "sg:orig_category":"Bazares, Art\u00cdculos De Limpieza Y De Cocina (al Por Menor)",
    "sg:phone":"+34 922 87 14 85",
    "sg:postcode":"38800",
    "sg:province":"Santa Cruz De Tenerife",
    "wof:name":"Teleropa S.l.",
    "wof:placetype":"venue"
},
  "geometry": {"coordinates":[-17.1105136871,28.0907344818],"type":"Point"}
}