{
  "type": "Feature",
  "properties": {
    "iso:country":"ES",
    "sg:address":"Carrer de Font (la), 9",
    "sg:city":"Novelda",
    "sg:orig_category":"Peluqueros: De Se\u00d1oras",
    "sg:phone":"+34 965 60 12 91",
    "sg:postcode":"03660",
    "sg:province":"Alicante",
    "wof:name":"Rodriguez De La Paz Juana",
    "wof:placetype":"venue"
},
  "geometry": {"coordinates":[-0.7673730254,38.3852996826],"type":"Point"}
}