{
  "type": "Feature",
  "properties": {
    "addr:full":"Carrer de Santa Elvira (de), 25 Vilassar De Mar Barcelona 08340",
    "addr:housenumber":"25",
    "addr:postcode":"08340",
    "addr:street":"Carrer De Santa Elvira De",
    "iso:country":"ES",
    "sg:address":"Carrer de Santa Elvira (de), 25",
    "sg:city":"Vilassar De Mar",
    "sg:orig_category":"Prot\u00c9sicos Dentales",
    "sg:phone":"+34 937 50 61 12",
    "sg:postcode":"08340",
    "sg:province":"Barcelona",
    "wof:name":"Rosas Pujol Jose",
    "wof:placetype":"venue"
},
  "geometry": {"coordinates":[2.3859100342,41.5022201538],"type":"Point"}
}