{
  "type": "Feature",
  "properties": {
    "addr:full":"Calle de Mayor, 1 Casas-iba\u00e7ez Albacete 02200",
    "addr:housenumber":"1",
    "addr:postcode":"02200",
    "addr:street":"Calle De Mayor",
    "iso:country":"ES",
    "sg:address":"Calle de Mayor, 1",
    "sg:city":"Casas-iba\u00e7ez",
    "sg:orig_category":"Alimentaci\u00d3n General (al Por Menor)",
    "sg:phone":"+34 967 46 00 11",
    "sg:postcode":"02200",
    "sg:province":"Albacete",
    "wof:name":"Soriano Cebrian Milagros",
    "wof:placetype":"venue"
},
  "geometry": {"coordinates":[-1.4711450338,39.287311554],"type":"Point"}
}