{
  "type": "Feature",
  "properties": {
    "iso:country":"ES",
    "sg:address":"Avgd Pius Xii, 21",
    "sg:city":"Lleida",
    "sg:orig_category":"Mec\u00c1nico Del Autom\u00d3vil",
    "sg:phone":"+34 973 26 72 55",
    "sg:postcode":"25003",
    "sg:province":"Lleida",
    "wof:name":"Mimbrera Cuenca Jose",
    "wof:placetype":"venue"
},
  "geometry": {"coordinates":[0.6138240099,41.6140213013],"type":"Point"}
}