{
  "type": "Feature",
  "properties": {
    "iso:country":"ES",
    "sg:address":"Closa, 27",
    "sg:city":"San Isidro De Benageber",
    "sg:orig_category":"Doctores En Medicina",
    "sg:phone":"+34 961 39 46 28",
    "sg:postcode":"46116",
    "sg:province":"Valencia",
    "wof:name":"Clinica Laboral Moncada Sl",
    "wof:placetype":"venue"
},
  "geometry": {"coordinates":[-0.4134680033,39.5645027161],"type":"Point"}
}