{
  "type": "Feature",
  "properties": {
    "addr:full":"Calle de Pe\u00d1alara, 32 Segovia Segovia 40006",
    "addr:housenumber":"32",
    "addr:postcode":"40006",
    "addr:street":"Calle De Pen\u0303Alara",
    "iso:country":"ES",
    "sg:address":"Calle de Pe\u00d1alara, 32",
    "sg:city":"Segovia",
    "sg:orig_category":"Limpieza Industrial",
    "sg:phone":"+34 921 44 36 16",
    "sg:postcode":"40006",
    "sg:province":"Segovia",
    "wof:name":"Fomento De Construcciones Y Contratas S.a.",
    "wof:placetype":"venue"
},
  "geometry": {"coordinates":[-4.110604763,40.9290504456],"type":"Point"}
}