{
  "type": "Feature",
  "properties": {
    "addr:full":"Calle de Cimadevilla, 11 Oviedo Asturias 33003",
    "addr:housenumber":"11",
    "addr:postcode":"33003",
    "addr:street":"Calle De Cimadevilla",
    "iso:country":"ES",
    "sg:address":"Calle de Cimadevilla, 11",
    "sg:city":"Oviedo",
    "sg:orig_category":"Agencias Y Agentes Comerciales, Representantes",
    "sg:phone":"+34 985 22 36 34",
    "sg:postcode":"33003",
    "sg:province":"Asturias",
    "wof:name":"Secades Arguelles Maria Luisa",
    "wof:placetype":"venue"
},
  "geometry": {"coordinates":[-5.8446741104,43.3607902527],"type":"Point"}
}