{
  "type": "Feature",
  "properties": {
    "addr:full":"Carr Sant Salvador, 18 Alfes Lleida 25161",
    "addr:housenumber":"18",
    "addr:postcode":"25161",
    "addr:street":"Carr Sant Salvador",
    "iso:country":"ES",
    "sg:address":"Carr Sant Salvador, 18",
    "sg:city":"Alfes",
    "sg:orig_category":"Inform\u00c1tica: Mini Y Grandes Sistemas (venta, Instalaci\u00d3n, Mantenimiento)",
    "sg:phone":"+34 973 13 61 02",
    "sg:postcode":"25161",
    "sg:province":"Lleida",
    "wof:name":"Soft El Moli",
    "wof:placetype":"venue"
},
  "geometry": {"coordinates":[0.6218240261,41.5214195251],"type":"Point"}
}