{
  "type": "Feature",
  "properties": {
    "addr:full":"Calle de Juan Ii, 14 Zamora Zamora 49011",
    "addr:housenumber":"14",
    "addr:postcode":"49011",
    "addr:street":"Calle De Juan Ii",
    "iso:country":"ES",
    "sg:address":"Calle de Juan Ii, 14",
    "sg:city":"Zamora",
    "sg:orig_category":"Dise\u00d1o Industrial",
    "sg:phone":"+34 980 52 34 72",
    "sg:postcode":"49011",
    "sg:province":"Zamora",
    "wof:name":"Rodriguez Casado Miguel",
    "wof:placetype":"venue"
},
  "geometry": {"coordinates":[-5.7402658463,41.511138916],"type":"Point"}
}