{
  "type": "Feature",
  "properties": {
    "addr:full":"Av Pavos (els), 13 Blanes Girona 17300",
    "addr:housenumber":"13",
    "addr:postcode":"17300",
    "addr:street":"Av Pavos Els",
    "iso:country":"ES",
    "sg:address":"Av Pavos (els), 13",
    "sg:city":"Blanes",
    "sg:orig_category":"Comercio De Minerales, F\u00d3siles Y Conchas",
    "sg:phone":"+34 972 33 70 80",
    "sg:postcode":"17300",
    "sg:province":"Girona",
    "wof:name":"Lopez Alvarez Alfredo",
    "wof:placetype":"venue"
},
  "geometry": {"coordinates":[2.7846128941,41.6731719971],"type":"Point"}
}