{
  "type": "Feature",
  "properties": {
    "addr:full":"Calle de Tomas Higuera, 23 Zaragoza Zaragoza 50013",
    "addr:housenumber":"23",
    "addr:postcode":"50013",
    "addr:street":"Calle De Tomas Higuera",
    "iso:country":"ES",
    "sg:address":"Calle de Tomas Higuera, 23",
    "sg:city":"Zaragoza",
    "sg:orig_category":"Fabricaci\u00d3n De Muebles",
    "sg:phone":"+34 976 49 39 25",
    "sg:postcode":"50013",
    "sg:province":"Zaragoza",
    "wof:name":"Caltesa S. L.",
    "wof:placetype":"venue"
},
  "geometry": {"coordinates":[-0.8664569855,41.6429786682],"type":"Point"}
}