{
  "type": "Feature",
  "properties": {
    "iso:country":"ES",
    "sg:address":"Calle de Doctor Fleming, 2",
    "sg:city":"Andujar",
    "sg:orig_category":"\u00d3ptica: Instrumentos (fabricaci\u00d3n)",
    "sg:phone":"+34 953 50 27 28",
    "sg:postcode":"23740",
    "sg:province":"Ja\u00e9n",
    "wof:name":"Ca\u00f1o Calderat Ana Paula",
    "wof:placetype":"venue"
},
  "geometry": {"coordinates":[-4.0573339462,38.0388183594],"type":"Point"}
}