{
  "type": "Feature",
  "properties": {
    "iso:country":"ES",
    "sg:address":"Telers, 28",
    "sg:city":"Ontinyent",
    "sg:orig_category":"Electricidad: Instaladores",
    "sg:phone":"+34 962 91 50 39",
    "sg:postcode":"46870",
    "sg:province":"Valencia",
    "wof:name":"Soelec S.l.",
    "wof:placetype":"venue"
},
  "geometry": {"coordinates":[-0.5788289905,38.8316307068],"type":"Point"}
}