{
  "type": "Feature",
  "properties": {
    "iso:country":"ES",
    "sg:address":"Carr Mimosa, 12",
    "sg:city":"Font De La Polvora",
    "sg:orig_category":"Molduras, Junquillos, Listones Y Molduras Perforadas",
    "sg:phone":"+34 972 20 96 20",
    "sg:postcode":"17004",
    "sg:province":"Girona",
    "wof:name":"Amador Heredia Jose",
    "wof:placetype":"venue"
},
  "geometry": {"coordinates":[2.843791008,41.9750404358],"type":"Point"}
}