{
  "type": "Feature",
  "properties": {
    "addr:full":"Crt. Valenzuela, Km. 0001,1 Pozuelo Calatrava Ciudad Real 13179",
    "addr:postcode":"13179",
    "addr:street":"Valenzuela Km. 0001,1 Pozuelo",
    "iso:country":"ES",
    "sg:address":"Crt. Valenzuela, Km. 0001,1",
    "sg:city":"Pozuelo Calatrava",
    "sg:orig_category":"Centros Empresariales",
    "sg:phone":"+34 926 69 00 63",
    "sg:postcode":"13179",
    "sg:province":"Ciudad Real",
    "wof:name":"Metalicas La Granja Sl",
    "wof:placetype":"venue"
},
  "geometry": {"coordinates":[-3.8354260921,38.9131889343],"type":"Point"}
}