{
  "type": "Feature",
  "properties": {
    "addr:full":"Calle de Manuel Machado, 14 Vejer De La Frontera C\u00e1diz 11150",
    "addr:housenumber":"14",
    "addr:postcode":"11150",
    "addr:street":"Calle De Manuel Machado",
    "iso:country":"ES",
    "sg:address":"Calle de Manuel Machado, 14",
    "sg:city":"Vejer De La Frontera",
    "sg:orig_category":"Bisuter\u00cda, Joyer\u00cda, Relojer\u00cda (al Por Menor)",
    "sg:phone":"+34 956 44 72 58",
    "sg:postcode":"11150",
    "sg:province":"C\u00e1diz",
    "wof:name":"Perez Caravaca Francisco",
    "wof:placetype":"venue"
},
  "geometry": {"coordinates":[-5.9452719688,36.2187042236],"type":"Point"}
}