{
  "type": "Feature",
  "properties": {
    "addr:full":"Calle de Astros, 9 Valladolid Valladolid 47009",
    "addr:housenumber":"9",
    "addr:postcode":"47009",
    "addr:street":"Calle De Astros",
    "iso:country":"ES",
    "sg:address":"Calle de Astros, 9",
    "sg:city":"Valladolid",
    "sg:orig_category":"Empresas De Carpinter\u00cda De Madera",
    "sg:phone":"+34 983 33 55 13",
    "sg:postcode":"47009",
    "sg:province":"Valladolid",
    "wof:name":"Zazo Lopez Francisco",
    "wof:placetype":"venue"
},
  "geometry": {"coordinates":[-4.7267827988,41.6674003601],"type":"Point"}
}