{
  "type": "Feature",
  "properties": {
    "iso:country":"ES",
    "sg:address":"Pl Carme (del), 9",
    "sg:city":"Valls",
    "sg:orig_category":"Cooperativas Agr\u00cdcolas",
    "sg:phone":"+34 977 60 05 21",
    "sg:postcode":"43800",
    "sg:province":"Tarragona",
    "wof:name":"Societat Agricola I Seccio De Credit De Valls Sccl",
    "wof:placetype":"venue"
},
  "geometry": {"coordinates":[1.2489459515,41.2828636169],"type":"Point"}
}