{
  "type": "Feature",
  "properties": {
    "iso:country":"ES",
    "sg:address":"Avda Mediterraneo (del), 182",
    "sg:city":"Rincon Victoria",
    "sg:orig_category":"Inmobiliaria (agencias)",
    "sg:phone":"+34 952 97 81 68",
    "sg:postcode":"29730",
    "sg:province":"M\u00e1laga",
    "wof:name":"Malaga Costa Asesoria Inmobiliria S.l.",
    "wof:placetype":"venue"
},
  "geometry": {"coordinates":[-4.2807641029,36.714641571],"type":"Point"}
}