{
  "type": "Feature",
  "properties": {
    "addr:full":"Calle de Jose Zorrilla, 11 Candeleda \u00c1vila 05480",
    "addr:housenumber":"11",
    "addr:postcode":"05480",
    "addr:street":"Calle De Jose Zorrilla",
    "iso:country":"ES",
    "sg:address":"Calle de Jose Zorrilla, 11",
    "sg:city":"Candeleda",
    "sg:orig_category":"Abogados",
    "sg:phone":"+34 920 38 20 88",
    "sg:postcode":"05480",
    "sg:province":"\u00c1vila",
    "wof:name":"Almeida Martin Antonio",
    "wof:placetype":"venue"
},
  "geometry": {"coordinates":[-5.2424244881,40.1564788818],"type":"Point"}
}