{
  "type": "Feature",
  "properties": {
    "iso:country":"ES",
    "sg:address":"Calle de Turia, 5",
    "sg:city":"Camas",
    "sg:orig_category":"Reposter\u00cdas",
    "sg:phone":"+34 954 39 51 04",
    "sg:postcode":"41900",
    "sg:province":"Sevilla",
    "wof:name":"Martinez Illescas Carlos",
    "wof:placetype":"venue"
},
  "geometry": {"coordinates":[-6.0326590538,37.3990135193],"type":"Point"}
}