{
  "type": "Feature",
  "properties": {
    "iso:country":"ES",
    "sg:address":"Via Europa, 181",
    "sg:city":"Mataro",
    "sg:orig_category":"Fabricaci\u00d3n, Importaci\u00d3n, Venta De Material De Telefon\u00cda, Peritelefon\u00cda",
    "sg:phone":"+34 937 58 69 48",
    "sg:postcode":"08303",
    "sg:province":"Barcelona",
    "sg:website":"www.cadenamovitel.com",
    "wof:name":"Movitel Comunicaciones S.l.",
    "wof:placetype":"venue"
},
  "geometry": {"coordinates":[2.4325299263,41.5437507629],"type":"Point"}
}