{
  "type": "Feature",
  "properties": {
    "iso:country":"ES",
    "sg:address":"Puerto La Duquesa-chanquete, S/n",
    "sg:city":"Manilva",
    "sg:orig_category":"Abogados",
    "sg:phone":"+34 952 89 36 18",
    "sg:postcode":"29692",
    "sg:province":"M\u00e1laga",
    "wof:name":"Astolfi Perez De Guzman Joaquin",
    "wof:placetype":"venue"
},
  "geometry": {"coordinates":[-5.2384138107,36.3421859741],"type":"Point"}
}