{
  "type": "Feature",
  "properties": {
    "iso:country":"ES",
    "sg:address":"Carr Concordia, 9",
    "sg:city":"Figueres",
    "sg:orig_category":"Asesor\u00cda Fiscal Y Jur\u00cddica",
    "sg:phone":"+34 972 50 29 93",
    "sg:postcode":"17600",
    "sg:province":"Girona",
    "wof:name":"Asesoria Triadu S. A.",
    "wof:placetype":"venue"
},
  "geometry": {"coordinates":[2.9590218067,42.2626075745],"type":"Point"}
}