{
  "type": "Feature",
  "properties": {
    "iso:country":"ES",
    "sg:address":"Avda Condes De San Isidro, 2",
    "sg:city":"Fuengirola",
    "sg:orig_category":"Mensajer\u00cda Express, Portes Internacionales",
    "sg:phone":"+34 952 47 27 81",
    "sg:postcode":"29640",
    "sg:province":"M\u00e1laga",
    "wof:name":"Gomez Iglesias Alonso Jose",
    "wof:placetype":"venue"
},
  "geometry": {"coordinates":[-4.6269459724,36.5331535339],"type":"Point"}
}