{
  "type": "Feature",
  "properties": {
    "iso:country":"ES",
    "sg:address":"Calle de San Juan, 5",
    "sg:city":"Badajoz",
    "sg:orig_category":"Prot\u00c9sicos Dentales",
    "sg:phone":"+34 924 22 08 12",
    "sg:postcode":"06002",
    "sg:province":"Badajoz",
    "wof:name":"Navarro Fernandez Francisco",
    "wof:placetype":"venue"
},
  "geometry": {"coordinates":[-6.9697546959,38.8792648315],"type":"Point"}
}