{
  "type": "Feature",
  "properties": {
    "iso:country":"ES",
    "sg:address":"Calle de Gerardo Linares, 4",
    "sg:city":"Villablino",
    "sg:orig_category":"Ense\u00d1anza: Comercio, Gesti\u00d3n, Inform\u00c1tica",
    "sg:phone":"+34 987 48 10 03",
    "sg:postcode":"24100",
    "sg:province":"Le\u00f3n",
    "wof:name":"Suarez Reguero Maria Lourdes",
    "wof:placetype":"venue"
},
  "geometry": {"coordinates":[-6.3171839714,42.939201355],"type":"Point"}
}