{
  "type": "Feature",
  "properties": {
    "iso:country":"ES",
    "sg:address":"Rond Del Cabildo, 14",
    "sg:city":"Benavente",
    "sg:orig_category":"Electrodom\u00c9sticos (al Por Menor)",
    "sg:phone":"+34 980 63 64 01",
    "sg:postcode":"49600",
    "sg:province":"Zamora",
    "wof:name":"Pintado Hermanos S.l.",
    "wof:placetype":"venue"
},
  "geometry": {"coordinates":[-5.677795887,42.0033531189],"type":"Point"}
}