{
  "type": "Feature",
  "properties": {
    "addr:full":"Calle de Carmona, S/n Arahal Sevilla 41600",
    "addr:postcode":"41600",
    "addr:street":"Calle De Carmona S / N",
    "iso:country":"ES",
    "sg:address":"Calle de Carmona, S/n",
    "sg:city":"Arahal",
    "sg:orig_category":"Estancos",
    "sg:phone":"+34 954 84 05 57",
    "sg:postcode":"41600",
    "sg:province":"Sevilla",
    "wof:name":"Barrera Garcia Carmen",
    "wof:placetype":"venue"
},
  "geometry": {"coordinates":[-5.5413990021,37.2647438049],"type":"Point"}
}