{
  "type": "Feature",
  "properties": {
    "addr:full":"Calle de Santander, 48 Ciudad Quesada Alicante 03170",
    "addr:housenumber":"48",
    "addr:postcode":"03170",
    "addr:street":"Calle De Santander",
    "iso:country":"ES",
    "sg:address":"Calle de Santander, 48",
    "sg:city":"Ciudad Quesada",
    "sg:orig_category":"Centros Empresariales",
    "sg:phone":"+34 966 71 60 71",
    "sg:postcode":"03170",
    "sg:province":"Alicante",
    "wof:name":"Ngs Servicios S.l.",
    "wof:placetype":"venue"
},
  "geometry": {"coordinates":[-0.7096850276,38.0642433167],"type":"Point"}
}