{
  "type": "Feature",
  "properties": {
    "iso:country":"ES",
    "sg:address":"Carrer de Bartrina, 31",
    "sg:city":"Barcelona",
    "sg:orig_category":"Reposter\u00cdas",
    "sg:phone":"+34 933 45 36 39",
    "sg:postcode":"08030",
    "sg:province":"Barcelona",
    "wof:name":"Ramos Bardi Carlos",
    "wof:placetype":"venue"
},
  "geometry": {"coordinates":[2.1872429848,41.4414558411],"type":"Point"}
}