{
  "type": "Feature",
  "properties": {
    "iso:country":"ES",
    "sg:address":"Calle de Orense, 23",
    "sg:city":"Madrid",
    "sg:orig_category":"Inform\u00c1tica (estudios, Servicios, Asesor\u00cda, Formaci\u00d3n)",
    "sg:phone":"+34 915 56 18 58",
    "sg:postcode":"28020",
    "sg:province":"Madrid",
    "wof:name":"Hispano Belga De Informatica Y Servicio S. A.",
    "wof:placetype":"venue"
},
  "geometry": {"coordinates":[-3.695305109,40.4510002136],"type":"Point"}
}