{
  "type": "Feature",
  "properties": {
    "iso:country":"ES",
    "sg:address":"Calle de La Iglesia, S/n",
    "sg:city":"Alquezar",
    "sg:orig_category":"Centros De Educaci\u00d3n Especial",
    "sg:phone":"+34 974 31 89 61",
    "sg:postcode":"22145",
    "sg:province":"Huesca",
    "wof:name":"Ayuntamiento De Alquezar-radiquero",
    "wof:placetype":"venue"
},
  "geometry": {"coordinates":[0.0269898996,42.1722068787],"type":"Point"}
}