{
  "type": "Feature",
  "properties": {
    "iso:country":"ES",
    "sg:address":"Cra. Nal. Tres-cents Quaranta, Km. 0280,7",
    "sg:city":"Bellvei",
    "sg:orig_category":"Fibras De Vidrio",
    "sg:phone":"+34 977 66 60 80",
    "sg:postcode":"43719",
    "sg:province":"Tarragona",
    "wof:name":"Fibrester S. A.",
    "wof:placetype":"venue"
},
  "geometry": {"coordinates":[1.5798250437,41.2386817932],"type":"Point"}
}