{
  "type": "Feature",
  "properties": {
    "addr:full":"Carr Teatre, 27 Cabanes Castell\u00f3n 12180",
    "addr:housenumber":"27",
    "addr:postcode":"12180",
    "addr:street":"Carr Teatre",
    "iso:country":"ES",
    "sg:address":"Carr Teatre, 27",
    "sg:city":"Cabanes",
    "sg:orig_category":"Electricidad: Instaladores",
    "sg:phone":"+34 964 33 12 34",
    "sg:postcode":"12180",
    "sg:province":"Castell\u00f3n",
    "wof:name":"Llorens Sidro Jose",
    "wof:placetype":"venue"
},
  "geometry": {"coordinates":[0.0448350012,40.1544303894],"type":"Point"}
}