{
  "type": "Feature",
  "properties": {
    "addr:full":"Calle de Manuel De Falla, 6 Puerto Serrano C\u00e1diz 11659",
    "addr:housenumber":"6",
    "addr:postcode":"11659",
    "addr:street":"Calle De Manuel De Falla;Ca\u0301Diz",
    "iso:country":"ES",
    "sg:address":"Calle de Manuel De Falla, 6",
    "sg:city":"Puerto Serrano",
    "sg:orig_category":"Mataderos De Poller\u00cda",
    "sg:phone":"+34 956 12 71 68",
    "sg:postcode":"11659",
    "sg:province":"C\u00e1diz",
    "wof:name":"Aves Barrera S.l.",
    "wof:placetype":"venue"
},
  "geometry": {"coordinates":[-5.546585083,36.9207992554],"type":"Point"}
}