{
  "type": "Feature",
  "properties": {
    "addr:full":"Monasterio Fitero, 12 Iru\u00f1a Navarra 31011",
    "addr:housenumber":"12",
    "addr:postcode":"31011",
    "addr:street":"Fitero",
    "iso:country":"ES",
    "sg:address":"Monasterio Fitero, 12",
    "sg:city":"Iru\u00f1a",
    "sg:orig_category":"Farmacias",
    "sg:phone":"+34 948 25 51 85",
    "sg:postcode":"31011",
    "sg:province":"Navarra",
    "wof:name":"Santamaria Martinez Caridad",
    "wof:placetype":"venue"
},
  "geometry": {"coordinates":[-1.6626089811,42.8171844482],"type":"Point"}
}