{
  "type": "Feature",
  "properties": {
    "iso:country":"ES",
    "sg:address":"Calle de Covadonga, 14",
    "sg:city":"Le\u00f3n",
    "sg:orig_category":"Peluquer\u00cdas, Peluquer\u00cda Mixta",
    "sg:phone":"+34 987 25 13 60",
    "sg:postcode":"24004",
    "sg:province":"Le\u00f3n",
    "wof:name":"Lobo Ribera Ana Maria",
    "wof:placetype":"venue"
},
  "geometry": {"coordinates":[-5.5740847588,42.5931510925],"type":"Point"}
}