{
  "type": "Feature",
  "properties": {
    "addr:full":"Calle de Herreria, 9 Bordon Teruel 44563",
    "addr:housenumber":"9",
    "addr:postcode":"44563",
    "addr:street":"Calle De Herreria",
    "iso:country":"ES",
    "sg:address":"Calle de Herreria, 9",
    "sg:city":"Bordon",
    "sg:orig_category":"Cr\u00cda De Cerdos",
    "sg:phone":"+34 964 17 84 21",
    "sg:postcode":"44563",
    "sg:province":"Teruel",
    "wof:name":"Porcino Bordon S.l.",
    "wof:placetype":"venue"
},
  "geometry": {"coordinates":[-0.321743995,40.6868858337],"type":"Point"}
}