{
  "type": "Feature",
  "properties": {
    "addr:full":"Calle de Uria, 43 Oviedo Asturias 33003",
    "addr:housenumber":"43",
    "addr:postcode":"33003",
    "addr:street":"Calle De Uria",
    "iso:country":"ES",
    "sg:address":"Calle de Uria, 43",
    "sg:city":"Oviedo",
    "sg:orig_category":"Abogados",
    "sg:phone":"+34 985 96 39 85",
    "sg:postcode":"33003",
    "sg:province":"Asturias",
    "wof:name":"Gonzalez Rodriguez Alfredo",
    "wof:placetype":"venue"
},
  "geometry": {"coordinates":[-5.8497238159,43.3631706238],"type":"Point"}
}