{
  "type": "Feature",
  "properties": {
    "addr:full":"Calle de Jose Miranda Guerra, 4 Teror Las Palmas 35330",
    "addr:housenumber":"4",
    "addr:postcode":"35330",
    "addr:street":"Calle De Jose Miranda Guerra",
    "iso:country":"ES",
    "sg:address":"Calle de Jose Miranda Guerra, 4",
    "sg:city":"Teror",
    "sg:orig_category":"Farmacias",
    "sg:phone":"+34 928 63 00 16",
    "sg:postcode":"35330",
    "sg:province":"Las Palmas",
    "wof:name":"Rodriguez Medina Maria Elba",
    "wof:placetype":"venue"
},
  "geometry": {"coordinates":[-15.5454912186,28.0591545105],"type":"Point"}
}