{
  "type": "Feature",
  "properties": {
    "addr:full":"Calle de Verge De La Mar, 25 Pinedo Valencia 46012",
    "addr:housenumber":"25",
    "addr:postcode":"46012",
    "addr:street":"Calle De Verge De La Mar",
    "iso:country":"ES",
    "sg:address":"Calle de Verge De La Mar, 25",
    "sg:city":"Pinedo",
    "sg:orig_category":"Parques De Atracciones Y Centros De Esparcimiento",
    "sg:phone":"+34 963 24 86 62",
    "sg:postcode":"46012",
    "sg:province":"Valencia",
    "wof:name":"Comercial Igove 94 S.l.",
    "wof:placetype":"venue"
},
  "geometry": {"coordinates":[-0.2913190126,39.3012657166],"type":"Point"}
}