{
  "type": "Feature",
  "properties": {
    "iso:country":"ES",
    "sg:address":"Calle de Teresa Gil, 22",
    "sg:city":"Valladolid",
    "sg:orig_category":"Art\u00cdculos De Regalo (al Por Menor)",
    "sg:phone":"+34 983 39 84 70",
    "sg:postcode":"47002",
    "sg:province":"Valladolid",
    "wof:name":"Sipecusa S.l.",
    "wof:placetype":"venue"
},
  "geometry": {"coordinates":[-4.7255840302,41.6501846313],"type":"Point"}
}