{
  "type": "Feature",
  "properties": {
    "addr:full":"Ctra Murcia (de), Km. 0063,0 Caravaca Cruz Murcia 30400",
    "addr:postcode":"30400",
    "addr:street":"Ctra Murcia De Km. 0063,0",
    "iso:country":"ES",
    "sg:address":"Ctra Murcia (de), Km. 0063,0",
    "sg:city":"Caravaca Cruz",
    "sg:orig_category":"Fabricaci\u00d3n De Muebles",
    "sg:phone":"+34 968 70 03 03",
    "sg:postcode":"30400",
    "sg:province":"Murcia",
    "wof:name":"Muebles Alvarez S.l.",
    "wof:placetype":"venue"
},
  "geometry": {"coordinates":[-1.8645700216,38.104763031],"type":"Point"}
}