{
  "type": "Feature",
  "properties": {
    "addr:full":"Calle de Calvario (el), 5 Esperanza Santa Cruz De Tenerife 38290",
    "addr:housenumber":"5",
    "addr:postcode":"38290",
    "addr:street":"Calle De Calvario El",
    "iso:country":"ES",
    "sg:address":"Calle de Calvario (el), 5",
    "sg:city":"Esperanza",
    "sg:orig_category":"Abogados",
    "sg:phone":"+34 922 29 74 84",
    "sg:postcode":"38290",
    "sg:province":"Santa Cruz De Tenerife",
    "wof:name":"Perez Cruz Alicia",
    "wof:placetype":"venue"
},
  "geometry": {"coordinates":[-16.3665466309,28.452123642],"type":"Point"}
}