{
  "type": "Feature",
  "properties": {
    "addr:full":"Calle de Mendaro, 9 Chiclana De La Frontera C\u00e1diz 11130",
    "addr:housenumber":"9",
    "addr:postcode":"11130",
    "addr:street":"Calle De Mendaro",
    "iso:country":"ES",
    "sg:address":"Calle de Mendaro, 9",
    "sg:city":"Chiclana De La Frontera",
    "sg:orig_category":"Pintura Y Barniz (al Por Menor)",
    "sg:phone":"+34 956 53 54 12",
    "sg:postcode":"11130",
    "sg:province":"C\u00e1diz",
    "wof:name":"Pinturas Brico S.l.",
    "wof:placetype":"venue"
},
  "geometry": {"coordinates":[-6.1515908241,36.4192390442],"type":"Point"}
}