{
  "type": "Feature",
  "properties": {
    "addr:full":"Avda Cid Campeador, 45 Burgos Burgos 09005",
    "addr:housenumber":"45",
    "addr:postcode":"09005",
    "addr:street":"Avda Cid Campeador",
    "iso:country":"ES",
    "sg:address":"Avda Cid Campeador, 45",
    "sg:city":"Burgos",
    "sg:orig_category":"Pensiones Familiares",
    "sg:phone":"+34 947 22 10 76",
    "sg:postcode":"09005",
    "sg:province":"Burgos",
    "wof:name":"Lopez Espinosa Jose Manuel",
    "wof:placetype":"venue"
},
  "geometry": {"coordinates":[-3.6967899799,42.3484611511],"type":"Point"}
}