{
  "type": "Feature",
  "properties": {
    "iso:country":"ES",
    "sg:address":"Calle de Covadonga, 82",
    "sg:city":"Palmas De Gran Canaria",
    "sg:orig_category":"Alimentaci\u00d3n General (al Por Menor)",
    "sg:phone":"+34 928 27 87 02",
    "sg:postcode":"35010",
    "sg:province":"Las Palmas",
    "wof:name":"Rivero Quintana Benedicta",
    "wof:placetype":"venue"
},
  "geometry": {"coordinates":[-15.4446353912,28.1276435852],"type":"Point"}
}