{
  "type": "Feature",
  "properties": {
    "iso:country":"ES",
    "sg:address":"Carrer de Manlleu, 10",
    "sg:city":"Vic",
    "sg:orig_category":"Casquer\u00cda (al Por Menor)",
    "sg:phone":"+34 938 89 12 19",
    "sg:postcode":"08500",
    "sg:province":"Barcelona",
    "wof:name":"Curos Fred S.l.",
    "wof:placetype":"venue"
},
  "geometry": {"coordinates":[2.2554829121,41.9315032959],"type":"Point"}
}