{
  "type": "Feature",
  "properties": {
    "iso:country":"ES",
    "sg:address":"C/ Pintor Marsa, S/n",
    "sg:city":"Tarrega",
    "sg:orig_category":"Inmobiliaria (agencias)",
    "sg:phone":"+34 973 31 33 80",
    "sg:postcode":"25300",
    "sg:province":"Lleida",
    "wof:name":"Plans 508 S.a.",
    "wof:placetype":"venue"
},
  "geometry": {"coordinates":[1.1451920271,41.6424789429],"type":"Point"}
}