{
  "type": "Feature",
  "properties": {
    "addr:full":"Calle de Iglesia, 8 Roda Eresma Segovia 40290",
    "addr:housenumber":"8",
    "addr:postcode":"40290",
    "addr:street":"Calle De Iglesia",
    "iso:country":"ES",
    "sg:address":"Calle de Iglesia, 8",
    "sg:city":"Roda Eresma",
    "sg:orig_category":"Fabricaci\u00d3n De Juguetes Autom\u00c1ticos",
    "sg:phone":"+34 921 49 30 73",
    "sg:postcode":"40290",
    "sg:province":"Segovia",
    "wof:name":"Hermadur S.l.",
    "wof:placetype":"venue"
},
  "geometry": {"coordinates":[-4.1811561584,41.0292625427],"type":"Point"}
}