{
  "type": "Feature",
  "properties": {
    "iso:country":"ES",
    "sg:address":"Plaz Circular, 8",
    "sg:city":"Vista Alegre",
    "sg:orig_category":"M\u00c9dicos: Cirug\u00cda Ortop\u00c9dica Y Traumatolog\u00cda",
    "sg:phone":"+34 968 23 44 28",
    "sg:postcode":"30008",
    "sg:province":"Murcia",
    "wof:name":"Guirao Baenas Juan",
    "wof:placetype":"venue"
},
  "geometry": {"coordinates":[-1.1310509443,37.9916038513],"type":"Point"}
}