{
  "type": "Feature",
  "properties": {
    "addr:full":"Parroco Pablo Diez, 29 Trobajo Camino Le\u00f3n 24010",
    "addr:housenumber":"29",
    "addr:postcode":"24010",
    "addr:street":"Camino Leo\u0301N",
    "iso:country":"ES",
    "sg:address":"Parroco Pablo Diez, 29",
    "sg:city":"Trobajo Camino",
    "sg:orig_category":"Mec\u00c1nico Del Autom\u00d3vil",
    "sg:phone":"+34 987 80 11 32",
    "sg:postcode":"24010",
    "sg:province":"Le\u00f3n",
    "wof:name":"Talleres Jualfe S.l.",
    "wof:placetype":"venue"
},
  "geometry": {"coordinates":[-5.5716600418,42.5981292725],"type":"Point"}
}