{
  "type": "Feature",
  "properties": {
    "iso:country":"ES",
    "sg:address":"Av Peguera, 13",
    "sg:city":"Peguera",
    "sg:orig_category":"\u00d3ptica: Instrumentos (fabricaci\u00d3n)",
    "sg:phone":"+34 971 68 57 92",
    "sg:postcode":"07160",
    "sg:province":"Islas Baleares",
    "wof:name":"Optica Paguera Gafco S.l.",
    "wof:placetype":"venue"
},
  "geometry": {"coordinates":[2.4466249943,39.5372695923],"type":"Point"}
}