{
  "type": "Feature",
  "properties": {
    "addr:full":"La Plata, S/n Jerez C\u00e1diz 11404",
    "addr:postcode":"11404",
    "addr:street":"La Plata S / N",
    "iso:country":"ES",
    "sg:address":"La Plata, S/n",
    "sg:city":"Jerez",
    "sg:orig_category":"Distribuci\u00d3n De Petr\u00d3leo Y Derivados",
    "sg:phone":"+34 956 31 96 31",
    "sg:postcode":"11404",
    "sg:province":"C\u00e1diz",
    "wof:name":"Morillo Zamorano S.l.",
    "wof:placetype":"venue"
},
  "geometry": {"coordinates":[-6.1417860985,36.6949157715],"type":"Point"}
}