{
  "type": "Feature",
  "properties": {
    "addr:full":"Avda Estacion De La, 14 Arroyo De La Miel-benalmadena Costa M\u00e1laga 29631",
    "addr:housenumber":"14",
    "addr:postcode":"29631",
    "addr:street":"Avda Estacion De La;Ma\u0301Laga",
    "iso:country":"ES",
    "sg:address":"Avda Estacion De La, 14",
    "sg:city":"Arroyo De La Miel-benalmadena Costa",
    "sg:orig_category":"Ense\u00d1anza: Profesiones Art\u00cdsticas",
    "sg:phone":"+34 952 56 63 88",
    "sg:postcode":"29631",
    "sg:province":"M\u00e1laga",
    "wof:name":"Estudios Fotograficos Amparo S.l.",
    "wof:placetype":"venue"
},
  "geometry": {"coordinates":[-4.5482521057,36.6017608643],"type":"Point"}
}