{
  "type": "Feature",
  "properties": {
    "addr:full":"Calle de Encinas (de Las), 33 Parque Coimbra Madrid 28935",
    "addr:housenumber":"33",
    "addr:postcode":"28935",
    "addr:street":"Calle De Encinas De Las",
    "iso:country":"ES",
    "sg:address":"Calle de Encinas (de Las), 33",
    "sg:city":"Parque Coimbra",
    "sg:classifiers":[
        {
            "category":"Professional",
            "subcategory":"Management & Consulting",
            "type":"Services"
        }
    ],
    "sg:phone":"+34 916 45 77 12",
    "sg:postcode":"28935",
    "sg:province":"Madrid",
    "sg:tags":[
        "asesor\u00cda",
        "en",
        "marketing"
    ],
    "wof:name":"Monak Impex S.l.",
    "wof:placetype":"venue"
},
  "geometry": {"coordinates":[-3.9371483326,40.3045082092],"type":"Point"}
}