{
  "type": "Feature",
  "properties": {
    "addr:full":"Cmno Zorrozgoiti, 66 Bilbao Vizcaya 48013",
    "addr:housenumber":"66",
    "addr:postcode":"48013",
    "addr:street":"Cmno Zorrozgoiti",
    "iso:country":"ES",
    "sg:address":"Cmno Zorrozgoiti, 66",
    "sg:city":"Bilbao",
    "sg:orig_category":"Ingeniero",
    "sg:phone":"+34 944 39 87 07",
    "sg:postcode":"48013",
    "sg:province":"Vizcaya",
    "sg:website":"www.zaitel.com",
    "wof:name":"Zaitel 500 S.l.",
    "wof:placetype":"venue"
},
  "geometry": {"coordinates":[-2.9754662514,43.2743225098],"type":"Point"}
}