{
  "type": "Feature",
  "properties": {
    "iso:country":"ES",
    "sg:address":"Psaj Palmeras (las), 29",
    "sg:city":"San Pedro Alcantara",
    "sg:orig_category":"Ropa Para Se\u00d1oras (al Por Menor)",
    "sg:phone":"+34 952 78 64 55",
    "sg:postcode":"29670",
    "sg:province":"M\u00e1laga",
    "wof:name":"Alonso Ortega Angel",
    "wof:placetype":"venue"
},
  "geometry": {"coordinates":[-4.9894766808,36.4856033325],"type":"Point"}
}