{
  "type": "Feature",
  "properties": {
    "addr:full":"Calle de Cabildo (el), 32 Astorga Le\u00f3n 24700",
    "addr:postcode":"24700",
    "addr:street":"Calle De Cabildo El;Astorga Leo\u0301N",
    "iso:country":"ES",
    "sg:address":"Calle de Cabildo (el), 32",
    "sg:city":"Astorga",
    "sg:orig_category":"Arreglo, Reparaci\u00d3n, Piezas Sueltas De Televisi\u00d3n, V\u00cddeo, Hi",
    "sg:phone":"+34 987 61 88 52",
    "sg:postcode":"24700",
    "sg:province":"Le\u00f3n",
    "wof:name":"Alonso Canseco Jose Elias",
    "wof:placetype":"venue"
},
  "geometry": {"coordinates":[-6.0504798889,42.4573249817],"type":"Point"}
}