{
  "type": "Feature",
  "properties": {
    "iso:country":"ES",
    "sg:address":"Carr Camp De La Vila (del), 19",
    "sg:city":"Pont Suert",
    "sg:orig_category":"Molduras, Junquillos, Listones Y Molduras Perforadas",
    "sg:phone":"+34 973 69 00 87",
    "sg:postcode":"25520",
    "sg:province":"Lleida",
    "wof:name":"Ribagor\u00e7a Vigo Doste S.l.",
    "wof:placetype":"venue"
},
  "geometry": {"coordinates":[0.741320014,42.408416748],"type":"Point"}
}