{
  "type": "Feature",
  "properties": {
    "iso:country":"ES",
    "sg:address":"Avda Albufera, 119",
    "sg:city":"Madrid",
    "sg:orig_category":"Cervecer\u00cdas",
    "sg:phone":"+34 914 77 50 70",
    "sg:postcode":"28038",
    "sg:province":"Madrid",
    "wof:name":"Hija Mu\u00f1ico Pedro De La",
    "wof:placetype":"venue"
},
  "geometry": {"coordinates":[-3.6595470905,40.3933906555],"type":"Point"}
}