{
  "type": "Feature",
  "properties": {
    "addr:full":"Calle de Butron, 1 Madrid Madrid 28022",
    "addr:housenumber":"1",
    "addr:postcode":"28022",
    "addr:street":"Calle De Butron",
    "iso:country":"ES",
    "sg:address":"Calle de Butron, 1",
    "sg:city":"Madrid",
    "sg:orig_category":"Empresas De Carpinter\u00cda",
    "sg:phone":"+34 913 24 11 12",
    "sg:postcode":"28022",
    "sg:province":"Madrid",
    "wof:name":"Aluminios Andres De Frutos S.l.",
    "wof:placetype":"venue"
},
  "geometry": {"coordinates":[-3.6112511158,40.4251976013],"type":"Point"}
}