{
  "type": "Feature",
  "properties": {
    "iso:country":"ES",
    "sg:address":"Desamparados, 6",
    "sg:city":"Elche",
    "sg:classifiers":[
        {
            "category":"Banks & Credit Unions",
            "subcategory":"Bank",
            "type":"Services"
        }
    ],
    "sg:phone":"+34 965 42 61 41",
    "sg:postcode":"03203",
    "sg:province":"Alicante",
    "sg:tags":[
        "interior",
        "arquitectos",
        "de"
    ],
    "wof:name":"Campello Selva Liberto",
    "wof:placetype":"venue"
},
  "geometry": {"coordinates":[-0.6698989868,38.2703514099],"type":"Point"}
}