{
  "type": "Feature",
  "properties": {
    "addr:full":"Pl Verge Del Miracle, 2 Palma Islas Baleares 07013",
    "addr:housenumber":"2",
    "addr:postcode":"07013",
    "addr:street":"Verge;Miracle",
    "iso:country":"ES",
    "sg:address":"Pl Verge Del Miracle, 2",
    "sg:city":"Palma",
    "sg:orig_category":"Iluminaci\u00d3n Industrial, Alumbrado P\u00dablico: Material (fabricaci\u00d3n, Importaci\u00d3n)",
    "sg:phone":"+34 971 73 43 43",
    "sg:postcode":"07013",
    "sg:province":"Islas Baleares",
    "sg:website":"www.carandini.com",
    "wof:name":"C. & G. Carandini S. A.",
    "wof:placetype":"venue"
},
  "geometry": {"coordinates":[2.635559082,39.5711593628],"type":"Point"}
}