{
  "type": "Feature",
  "properties": {
    "addr:full":"Calle de Caceres, S/n Malaga M\u00e1laga 29018",
    "addr:housenumber":"s",
    "addr:postcode":"29018",
    "addr:street":"Calle De Caceres;/ N;Ma\u0301Laga",
    "iso:country":"ES",
    "sg:address":"Calle de Caceres, S/n",
    "sg:city":"Malaga",
    "sg:orig_category":"Inmobiliaria (agencias)",
    "sg:phone":"+34 952 20 46 22",
    "sg:postcode":"29018",
    "sg:province":"M\u00e1laga",
    "wof:name":"Garcia Avila Jose Francisco",
    "wof:placetype":"venue"
},
  "geometry": {"coordinates":[-4.3778986931,36.7341842651],"type":"Point"}
}