{
  "type": "Feature",
  "properties": {
    "addr:full":"Calle de Primero De Mayo, 37 Huelma Ja\u00e9n 23560",
    "addr:housenumber":"37",
    "addr:postcode":"23560",
    "addr:street":"Calle De Primero De Mayo",
    "iso:country":"ES",
    "sg:address":"Calle de Primero De Mayo, 37",
    "sg:city":"Huelma",
    "sg:orig_category":"Molduras, Junquillos, Listones Y Molduras Perforadas",
    "sg:phone":"+34 953 39 12 00",
    "sg:postcode":"23560",
    "sg:province":"Ja\u00e9n",
    "wof:name":"Martinez Garcia Jacinto",
    "wof:placetype":"venue"
},
  "geometry": {"coordinates":[-3.454075098,37.6482887268],"type":"Point"}
}