{
  "type": "Feature",
  "properties": {
    "iso:country":"ES",
    "sg:address":"Avda Corredera, 41",
    "sg:city":"Hinojosa Del Duque",
    "sg:classifiers":[
        {
            "category":"Taxi",
            "type":"Transportation"
        }
    ],
    "sg:phone":"+34 957 14 04 94",
    "sg:postcode":"14270",
    "sg:province":"C\u00f3rdoba",
    "wof:name":"Monje Aranda Luis",
    "wof:placetype":"venue"
},
  "geometry": {"coordinates":[-5.1455011368,38.4989700317],"type":"Point"}
}