{
  "type": "Feature",
  "properties": {
    "addr:full":"Rua Alfonso Xiii, 8 Vigo Pontevedra 36201",
    "addr:housenumber":"8",
    "addr:postcode":"36201",
    "addr:street":"Rua Alfonso Xiii",
    "iso:country":"ES",
    "sg:address":"Rua Alfonso Xiii, 8",
    "sg:city":"Vigo",
    "sg:orig_category":"Fabricaci\u00d3n, Venta De Cuadros, Accesorios Para Enmarcar",
    "sg:phone":"+34 986 22 11 08",
    "sg:postcode":"36201",
    "sg:province":"Pontevedra",
    "wof:name":"Gonzalez Estevez Consejo",
    "wof:placetype":"venue"
},
  "geometry": {"coordinates":[-8.717297554,42.2365951538],"type":"Point"}
}