{
  "type": "Feature",
  "properties": {
    "addr:full":"Calle de Calderon De La Barca, 21 Alacant Alicante 03004",
    "addr:housenumber":"21",
    "addr:postcode":"03004",
    "addr:street":"Calle De Calderon De La Barca",
    "iso:country":"ES",
    "sg:address":"Calle de Calderon De La Barca, 21",
    "sg:city":"Alacant",
    "sg:orig_category":"Ropa Para Caballeros (al Por Menor)",
    "sg:phone":"+34 965 21 36 63",
    "sg:postcode":"03004",
    "sg:province":"Alicante",
    "wof:name":"Pastor Masip Jose",
    "wof:placetype":"venue"
},
  "geometry": {"coordinates":[-0.4856869876,38.3498573303],"type":"Point"}
}