{
  "type": "Feature",
  "properties": {
    "addr:full":"A Ruibal, 60 Pontevedra Pontevedra 36143",
    "addr:housenumber":"60",
    "addr:postcode":"36143",
    "addr:street":"Ruibal",
    "iso:country":"ES",
    "sg:address":"A Ruibal, 60",
    "sg:city":"Pontevedra",
    "sg:orig_category":"Bazares, Art\u00cdculos De Limpieza Y De Cocina (al Por Menor)",
    "sg:phone":"+34 986 86 07 38",
    "sg:postcode":"36143",
    "sg:province":"Pontevedra",
    "wof:name":"Pazos Estonllo Carmen",
    "wof:placetype":"venue"
},
  "geometry": {"coordinates":[-8.6421194077,42.4087219238],"type":"Point"}
}