{
  "type": "Feature",
  "properties": {
    "iso:country":"ES",
    "sg:address":"Calle de Escombreras (de Las), 14",
    "sg:city":"El Cruce",
    "sg:orig_category":"Art\u00cdculos De Decoraci\u00d3n (fabricaci\u00d3n Y Al Por Mayor)",
    "sg:phone":"+34 916 58 20 01",
    "sg:postcode":"28860",
    "sg:province":"Madrid",
    "wof:name":"Lecodor S.a.",
    "wof:placetype":"venue"
},
  "geometry": {"coordinates":[-3.5504379272,40.5101203918],"type":"Point"}
}