{
  "type": "Feature",
  "properties": {
    "iso:country":"ES",
    "sg:address":"Calle de San Juan De La Cruz, 28",
    "sg:city":"Ingenio",
    "sg:orig_category":"Cine (producci\u00d3n, Realizaci\u00d3n)",
    "sg:phone":"+34 928 78 08 36",
    "sg:postcode":"35250",
    "sg:province":"Las Palmas",
    "sg:website":"www.produccioneslarepublica.com",
    "wof:name":"Producciones La Republica S.l",
    "wof:placetype":"venue"
},
  "geometry": {"coordinates":[-15.4339389801,27.9221305847],"type":"Point"}
}