{
  "type": "Feature",
  "properties": {
    "iso:country":"ES",
    "sg:address":"Rua Celso Emilio Ferreiro, 18",
    "sg:city":"Ourense",
    "sg:orig_category":"Florister\u00cdas",
    "sg:phone":"+34 988 23 29 13",
    "sg:postcode":"32004",
    "sg:province":"Ourense",
    "wof:name":"Vazquez Losada Servando",
    "wof:placetype":"venue"
},
  "geometry": {"coordinates":[-7.8613982201,42.3434677124],"type":"Point"}
}