{
  "type": "Feature",
  "properties": {
    "addr:full":"Pino, S/n Pino Asturias 33411",
    "addr:housenumber":"s / n",
    "addr:postcode":"33411",
    "addr:street":"Pino",
    "iso:country":"ES",
    "sg:address":"Pino, S/n",
    "sg:city":"Pino",
    "sg:orig_category":"Asociaciones Humanitarias, De Cooperaci\u00d3n, De Acci\u00d3n Social",
    "sg:phone":"+34 985 57 65 59",
    "sg:postcode":"33411",
    "sg:province":"Asturias",
    "wof:name":"Reto A La Esperanza Asociacion",
    "wof:placetype":"venue"
},
  "geometry": {"coordinates":[-5.9681491852,43.4958076477],"type":"Point"}
}