{
  "type": "Feature",
  "properties": {
    "iso:country":"ES",
    "sg:address":"Calle de Escultor Benlliure, 1",
    "sg:city":"Zaragoza",
    "sg:orig_category":"Asilos De Ancianos. Centros Privados",
    "sg:phone":"+34 976 29 44 05",
    "sg:postcode":"50002",
    "sg:province":"Zaragoza",
    "wof:name":"Abadia Vera Maria Pilar",
    "wof:placetype":"venue"
},
  "geometry": {"coordinates":[-0.861326,41.649738],"type":"Point"}
}