{
  "type": "Feature",
  "properties": {
    "addr:full":"Trva Meicende, 173 Meicende La Coru\u00f1a 15140",
    "addr:housenumber":"173",
    "addr:postcode":"15140",
    "addr:street":"Trva Meicende;La Corun\u0303A",
    "iso:country":"ES",
    "sg:address":"Trva Meicende, 173",
    "sg:city":"Meicende",
    "sg:orig_category":"Pescader\u00cdas (al Por Menor)",
    "sg:phone":"+34 981 26 49 50",
    "sg:postcode":"15140",
    "sg:province":"La Coru\u00f1a",
    "wof:name":"Rodriguez Mourelle Jose",
    "wof:placetype":"venue"
},
  "geometry": {"coordinates":[-8.4471940994,43.346408844],"type":"Point"}
}