{
  "type": "Feature",
  "properties": {
    "iso:country":"ES",
    "sg:address":"Calle de Carretera De Peralta, S/n",
    "sg:city":"Marcilla",
    "sg:orig_category":"Conservas De Legumbres (fabricaci\u00d3n, Al Por Mayor)",
    "sg:phone":"+34 948 71 39 10",
    "sg:postcode":"31340",
    "sg:province":"Navarra",
    "wof:name":"Precomar S.l.",
    "wof:placetype":"venue"
},
  "geometry": {"coordinates":[-1.7198214531,42.3268661499],"type":"Point"}
}