{
  "type": "Feature",
  "properties": {
    "iso:country":"ES",
    "sg:address":"Carrer de Roger De Lluria, 9",
    "sg:city":"Barcelona",
    "sg:orig_category":"Reciclaje, Tratamiento De Tejidos",
    "sg:phone":"+34 933 18 94 61",
    "sg:postcode":"08010",
    "sg:province":"Barcelona",
    "wof:name":"Santos Villafa\u00f1e Juan Manuel",
    "wof:placetype":"venue"
},
  "geometry": {"coordinates":[2.1724839211,41.3901824951],"type":"Point"}
}