{
  "type": "Feature",
  "properties": {
    "addr:full":"Calle de Portal Del Rey, 8 Vitoria-gasteiz \u00c1lava 01001",
    "addr:housenumber":"8",
    "addr:postcode":"01001",
    "addr:street":"Calle De Portal Del Rey",
    "iso:country":"ES",
    "sg:address":"Calle de Portal Del Rey, 8",
    "sg:city":"Vitoria-gasteiz",
    "sg:orig_category":"Asociaciones Humanitarias, De Cooperaci\u00d3n, De Acci\u00d3n Social",
    "sg:phone":"+34 945 25 20 69",
    "sg:postcode":"01001",
    "sg:province":"\u00c1lava",
    "wof:name":"Asociacion De Amigos De La Rasd",
    "wof:placetype":"venue"
},
  "geometry": {"coordinates":[-2.6688277721,42.8470344543],"type":"Point"}
}