{
  "type": "Feature",
  "properties": {
    "iso:country":"ES",
    "sg:address":"Calle de Comisario, 16",
    "sg:city":"Iniesta",
    "sg:orig_category":"Plomeros",
    "sg:phone":"+34 967 49 00 92",
    "sg:postcode":"16235",
    "sg:province":"Cuenca",
    "wof:name":"Tarin Roldan Eugenio Jose",
    "wof:placetype":"venue"
},
  "geometry": {"coordinates":[-1.7477796078,39.4466781616],"type":"Point"}
}