{
  "type": "Feature",
  "properties": {
    "addr:full":"Polig. San Paio De Navia, S/n Vigo Pontevedra 36213",
    "addr:housenumber":"s / n",
    "addr:postcode":"36213",
    "addr:street":"Polig. San Paio De Navia",
    "iso:country":"ES",
    "sg:address":"Polig. San Paio De Navia, S/n",
    "sg:city":"Vigo",
    "sg:orig_category":"Promotores Constructores",
    "sg:phone":"+34 986 24 41 37",
    "sg:postcode":"36213",
    "sg:province":"Pontevedra",
    "wof:name":"Uicesa Obras Y Construcciones S.a.",
    "wof:placetype":"venue"
},
  "geometry": {"coordinates":[-8.7210121155,42.1948318481],"type":"Point"}
}