{
  "type": "Feature",
  "properties": {
    "addr:full":"Calle de Eduardo Marquina, 24 Avila \u00c1vila 05001",
    "addr:housenumber":"24",
    "addr:postcode":"05001",
    "addr:street":"Calle De Eduardo Marquina;A\u0301Vila",
    "iso:country":"ES",
    "sg:address":"Calle de Eduardo Marquina, 24",
    "sg:city":"Avila",
    "sg:orig_category":"Venta, Instalaci\u00d3n, Reparaci\u00d3n De Antenas Para Televisi\u00d3n",
    "sg:phone":"+34 920 22 48 39",
    "sg:postcode":"05001",
    "sg:province":"\u00c1vila",
    "wof:name":"Fernandez-amaro Sarmiento Eugenio",
    "wof:placetype":"venue"
},
  "geometry": {"coordinates":[-4.6918215752,40.6563301086],"type":"Point"}
}