{
  "type": "Feature",
  "properties": {
    "addr:full":"Carrer de Florida (la), 39 Cornella Llobregat Barcelona 08940",
    "addr:housenumber":"39",
    "addr:postcode":"08940",
    "addr:street":"Carrer De Florida La",
    "iso:country":"ES",
    "sg:address":"Carrer de Florida (la), 39",
    "sg:city":"Cornella Llobregat",
    "sg:orig_category":"Inform\u00c1tica (estudios, Servicios, Asesor\u00cda, Formaci\u00d3n)",
    "sg:phone":"+34 934 71 21 55",
    "sg:postcode":"08940",
    "sg:province":"Barcelona",
    "wof:name":"Vargas Torres Josefina",
    "wof:placetype":"venue"
},
  "geometry": {"coordinates":[2.0756099224,41.357131958],"type":"Point"}
}