{
  "type": "Feature",
  "properties": {
    "addr:full":"Migjorn, 8 Betera Valencia 46117",
    "addr:housenumber":"8",
    "addr:postcode":"46117",
    "addr:street":"Migjorn",
    "iso:country":"ES",
    "sg:address":"Migjorn, 8",
    "sg:city":"Betera",
    "sg:orig_category":"Semiller\u00cdas",
    "sg:phone":"+34 961 60 27 08",
    "sg:postcode":"46117",
    "sg:province":"Valencia",
    "wof:name":"Recuperaciones Agricolas Moreno S.l",
    "wof:placetype":"venue"
},
  "geometry": {"coordinates":[-0.4622890055,39.6092605591],"type":"Point"}
}