{
  "type": "Feature",
  "properties": {
    "iso:country":"ES",
    "sg:address":"Calle de Alonso De Cespedes, 16",
    "sg:city":"Horcajo Santiago",
    "sg:orig_category":"Molduras, Junquillos, Listones Y Molduras Perforadas",
    "sg:phone":"+34 969 12 72 74",
    "sg:postcode":"16410",
    "sg:province":"Cuenca",
    "wof:name":"Hosteleria Marjelus S.l.",
    "wof:placetype":"venue"
},
  "geometry": {"coordinates":[-2.9996933937,39.8410415649],"type":"Point"}
}