{
  "type": "Feature",
  "properties": {
    "addr:full":"Carr Nou, 49 Figueres Girona 17600",
    "addr:housenumber":"49",
    "addr:postcode":"17600",
    "addr:street":"Carr Nou",
    "iso:country":"ES",
    "sg:address":"Carr Nou, 49",
    "sg:city":"Figueres",
    "sg:orig_category":"Colchones (fabricaci\u00d3n, Al Por Mayor, Al Por Menor)",
    "sg:phone":"+34 972 50 29 97",
    "sg:postcode":"17600",
    "sg:province":"Girona",
    "wof:name":"Font Massias Lluis",
    "wof:placetype":"venue"
},
  "geometry": {"coordinates":[2.9581100941,42.2656898499],"type":"Point"}
}