{
  "type": "Feature",
  "properties": {
    "iso:country":"ES",
    "sg:address":"Ctra Higueron (p I Zabal Bajo), 57",
    "sg:city":"La Linea",
    "sg:orig_category":"Vinos Y Licores (venta Al Por Menor)",
    "sg:phone":"+34 956 64 41 99",
    "sg:postcode":"11300",
    "sg:province":"C\u00e1diz",
    "wof:name":"Distribuciones Y Exclusivas Manuel Mena S.l.",
    "wof:placetype":"venue"
},
  "geometry": {"coordinates":[-5.340939045,36.1683044434],"type":"Point"}
}