{
  "type": "Feature",
  "properties": {
    "addr:full":"Calle de Doctor Ferran, 5 Alacant Alicante 03012",
    "addr:housenumber":"5",
    "addr:postcode":"03012",
    "addr:street":"Calle De Doctor Ferran",
    "iso:country":"ES",
    "sg:address":"Calle de Doctor Ferran, 5",
    "sg:city":"Alacant",
    "sg:orig_category":"Inform\u00c1tica: Soportes De Informaci\u00d3n, Suministros & Accesorios",
    "sg:phone":"+34 965 21 02 74",
    "sg:postcode":"03012",
    "sg:province":"Alicante",
    "wof:name":"Comercial Sinal S.l.",
    "wof:placetype":"venue"
},
  "geometry": {"coordinates":[-0.4809907079,38.3547554016],"type":"Point"}
}