{
  "type": "Feature",
  "properties": {
    "iso:country":"ES",
    "sg:address":"Calle de Viso, 45",
    "sg:city":"Gumiel Mercado",
    "sg:orig_category":"Venta, Instalaci\u00d3n De Cocinas",
    "sg:phone":"+34 947 54 51 03",
    "sg:postcode":"09440",
    "sg:province":"Burgos",
    "wof:name":"Izquierdo Lopez Eusebio",
    "wof:placetype":"venue"
},
  "geometry": {"coordinates":[-3.8008270264,41.7564735413],"type":"Point"}
}