{
  "type": "Feature",
  "properties": {
    "iso:country":"ES",
    "sg:address":"Luga Poligono El Chaparral, 13",
    "sg:city":"Ermita De Las Monta\u00e7as",
    "sg:orig_category":"Escayola Y Productos De Escayola (fabricaci\u00d3n, Al Por Mayor)",
    "sg:phone":"+34 956 73 10 86",
    "sg:postcode":"11650",
    "sg:province":"C\u00e1diz",
    "wof:name":"Escayolas Villamartin S.l.",
    "wof:placetype":"venue"
},
  "geometry": {"coordinates":[-5.6441640854,36.8604202271],"type":"Point"}
}