{
  "type": "Feature",
  "properties": {
    "iso:country":"ES",
    "sg:address":"Calle de Olvido, 17",
    "sg:city":"Madrid",
    "sg:orig_category":"Asistencia Social",
    "sg:phone":"+34 913 92 02 80",
    "sg:postcode":"28026",
    "sg:province":"Madrid",
    "wof:name":"Opcion 3 S.coop",
    "wof:placetype":"venue"
},
  "geometry": {"coordinates":[-3.7027099133,40.3866653442],"type":"Point"}
}