{
  "type": "Feature",
  "properties": {
    "iso:country":"ES",
    "sg:address":"Calle de Ahorro, 19",
    "sg:city":"Sevilla",
    "sg:orig_category":"Cables Y Hilos El\u00c9ctricos (fabricaci\u00d3n, Al Por Mayor)",
    "sg:phone":"+34 954 67 35 52",
    "sg:postcode":"41007",
    "sg:province":"Sevilla",
    "wof:name":"Cables Y Telecomunicaciones Andalucia S.l.",
    "wof:placetype":"venue"
},
  "geometry": {"coordinates":[-5.9518675804,37.3904037476],"type":"Point"}
}