{
  "type": "Feature",
  "properties": {
    "iso:country":"ES",
    "sg:address":"Ptda Cantereria, S/n",
    "sg:city":"Finestrat",
    "sg:orig_category":"Fabricaci\u00d3n De Bolsos Y Bolsos De Tela",
    "sg:phone":"+34 965 87 82 58",
    "sg:postcode":"03509",
    "sg:province":"Alicante",
    "sg:website":"www.dreacha.com",
    "wof:name":"Dreacha S.l.",
    "wof:placetype":"venue"
},
  "geometry": {"coordinates":[-0.216564998,38.5663986206],"type":"Point"}
}