{
  "type": "Feature",
  "properties": {
    "addr:full":"Calle de Bortandia, 4 Oteiza Navarra 31250",
    "addr:housenumber":"4",
    "addr:postcode":"31250",
    "addr:street":"Calle De Bortandia",
    "iso:country":"ES",
    "sg:address":"Calle de Bortandia, 4",
    "sg:city":"Oteiza",
    "sg:orig_category":"Cooperativas Agr\u00cdcolas",
    "sg:phone":"+34 948 54 31 25",
    "sg:postcode":"31250",
    "sg:province":"Navarra",
    "wof:name":"Cooperativa Agricola Santa Barbara",
    "wof:placetype":"venue"
},
  "geometry": {"coordinates":[-1.9537365437,42.6176528931],"type":"Point"}
}