{
  "type": "Feature",
  "properties": {
    "addr:full":"Ctra. Portocristo, Km. 0006,5 Manacor Islas Baleares 07500",
    "addr:postcode":"07500",
    "addr:street":"Ctra. Portocristo Km. 0006,5",
    "iso:country":"ES",
    "sg:address":"Ctra. Portocristo, Km. 0006,5",
    "sg:city":"Manacor",
    "sg:orig_category":"Equitaci\u00d3n Y Centros De H\u00cdpica",
    "sg:phone":"+34 971 55 72 66",
    "sg:postcode":"07500",
    "sg:province":"Islas Baleares",
    "wof:name":"Cabrer Games Esperanza",
    "wof:placetype":"venue"
},
  "geometry": {"coordinates":[3.3240180016,39.5378570557],"type":"Point"}
}