{
  "type": "Feature",
  "properties": {
    "addr:full":"Rua Pai Crespo, 24 Redondela Pontevedra 36800",
    "addr:housenumber":"24",
    "addr:postcode":"36800",
    "addr:street":"Rua Pai Crespo",
    "iso:country":"ES",
    "sg:address":"Rua Pai Crespo, 24",
    "sg:city":"Redondela",
    "sg:orig_category":"Ense\u00d1anza Variada",
    "sg:phone":"+34 986 40 45 36",
    "sg:postcode":"36800",
    "sg:province":"Pontevedra",
    "wof:name":"Perez Rodriguez Lilian",
    "wof:placetype":"venue"
},
  "geometry": {"coordinates":[-8.6090650558,42.2815933228],"type":"Point"}
}