{
  "type": "Feature",
  "properties": {
    "iso:country":"ES",
    "sg:address":"Carrer de Doctor Fleming, 17",
    "sg:city":"Esparreguera",
    "sg:orig_category":"Peluquer\u00cdas, Peluquer\u00cda Mixta",
    "sg:phone":"+34 937 77 34 53",
    "sg:postcode":"08292",
    "sg:province":"Barcelona",
    "wof:name":"Cardenas Gomez Josefina",
    "wof:placetype":"venue"
},
  "geometry": {"coordinates":[1.8715699911,41.533744812],"type":"Point"}
}