{
  "type": "Feature",
  "properties": {
    "iso:country":"ES",
    "sg:address":"Obanca, S/n",
    "sg:city":"Obanca",
    "sg:orig_category":"Muebles Y Accesorios Para Cocinas Y Cuartos De Ba\u00d1o (al Por Menor)",
    "sg:phone":"+34 985 81 05 90",
    "sg:postcode":"33819",
    "sg:province":"Asturias",
    "wof:name":"Martinez Fernandez Jose Antonio",
    "wof:placetype":"venue"
},
  "geometry": {"coordinates":[-6.4327960014,43.2157478333],"type":"Point"}
}