{
  "type": "Feature",
  "properties": {
    "iso:country":"ES",
    "sg:address":"Calle de Juan Jimenez, 4",
    "sg:city":"Carlota",
    "sg:orig_category":"Empresas De Electricidad En General",
    "sg:phone":"+34 957 30 00 31",
    "sg:postcode":"14100",
    "sg:province":"C\u00f3rdoba",
    "wof:name":"Endesa Servicios S.l.",
    "wof:placetype":"venue"
},
  "geometry": {"coordinates":[-4.9311947823,37.6740760803],"type":"Point"}
}