{
  "type": "Feature",
  "properties": {
    "iso:country":"ES",
    "sg:address":"Avda Reina Mercedes, 27",
    "sg:city":"Sevilla",
    "sg:orig_category":"Inform\u00c1tica, Ofim\u00c1tica (estudios, Asesor\u00cda, Ingenier\u00cda, Formaci\u00d3n)",
    "sg:phone":"+34 954 23 28 15",
    "sg:postcode":"41012",
    "sg:province":"Sevilla",
    "wof:name":"Electrodomesticos Guerrero S.l.",
    "wof:placetype":"venue"
},
  "geometry": {"coordinates":[-5.9859848022,37.3600387573],"type":"Point"}
}