{
  "type": "Feature",
  "properties": {
    "addr:full":"Calle de Bizkaia, 9 Portugalete Vizcaya 48920",
    "addr:housenumber":"9",
    "addr:postcode":"48920",
    "addr:street":"Calle De Bizkaia",
    "iso:country":"ES",
    "sg:address":"Calle de Bizkaia, 9",
    "sg:city":"Portugalete",
    "sg:orig_category":"Promotores Constructores",
    "sg:phone":"+34 944 83 36 64",
    "sg:postcode":"48920",
    "sg:province":"Vizcaya",
    "wof:name":"Antxeta S.l.",
    "wof:placetype":"venue"
},
  "geometry": {"coordinates":[-3.0204586983,43.323009491],"type":"Point"}
}