{
  "type": "Feature",
  "properties": {
    "addr:full":"Ctro Cial Calahonda, 17 Calahonda M\u00e1laga 29647",
    "addr:housenumber":"17",
    "addr:postcode":"29647",
    "addr:street":"Calahonda;Ma\u0301Laga",
    "iso:country":"ES",
    "sg:address":"Ctro Cial Calahonda, 17",
    "sg:city":"Calahonda",
    "sg:orig_category":"Art\u00cdculos De Decoraci\u00d3n",
    "sg:phone":"+34 952 93 55 39",
    "sg:postcode":"29647",
    "sg:province":"M\u00e1laga",
    "wof:name":"Montys Furnitures",
    "wof:placetype":"venue"
},
  "geometry": {"coordinates":[-4.7157039642,36.4931945801],"type":"Point"}
}