{
  "type": "Feature",
  "properties": {
    "addr:full":"Plaz Progreso, Del, S/n Valencia Alcantara C\u00e1ceres 10500",
    "addr:housenumber":"/ n",
    "addr:postcode":"10500",
    "addr:street":"Del S;Alcantara Ca\u0301Ceres",
    "iso:country":"ES",
    "sg:address":"Plaz Progreso, Del, S/n",
    "sg:city":"Valencia Alcantara",
    "sg:orig_category":"Asilos De Ancianos. Centros Privados",
    "sg:phone":"+34 927 58 24 22",
    "sg:postcode":"10500",
    "sg:province":"C\u00e1ceres",
    "wof:name":"Ayuntamiento De Valencia De Alcantara",
    "wof:placetype":"venue"
},
  "geometry": {"coordinates":[-7.2451472282,39.4101142883],"type":"Point"}
}