{
  "type": "Feature",
  "properties": {
    "iso:country":"ES",
    "sg:address":"Calle de Colombia, 14",
    "sg:city":"Tablero",
    "sg:orig_category":"Electrodom\u00c9sticos (al Por Menor)",
    "sg:phone":"+34 928 14 09 00",
    "sg:postcode":"35100",
    "sg:province":"Las Palmas",
    "wof:name":"Matas Perez Gabriel",
    "wof:placetype":"venue"
},
  "geometry": {"coordinates":[-15.6051921844,27.7724819183],"type":"Point"}
}