{
  "type": "Feature",
  "properties": {
    "iso:country":"ES",
    "sg:address":"Calle de Blas Infante, 3",
    "sg:city":"Velez-malaga",
    "sg:orig_category":"M\u00c9dicos: Estomatolog\u00cda",
    "sg:phone":"+34 952 50 56 96",
    "sg:postcode":"29700",
    "sg:province":"M\u00e1laga",
    "wof:name":"Ruiz Martin Jose Joaquin",
    "wof:placetype":"venue"
},
  "geometry": {"coordinates":[-4.1090364456,36.7823486328],"type":"Point"}
}