{
  "type": "Feature",
  "properties": {
    "addr:full":"Calle de Andres Benito (santa Isabel), 3 Zaragoza Zaragoza 50016",
    "addr:housenumber":"3",
    "addr:postcode":"50016",
    "addr:street":"Calle De Andres Benito Santa Isabel",
    "iso:country":"ES",
    "sg:address":"Calle de Andres Benito (santa Isabel), 3",
    "sg:city":"Zaragoza",
    "sg:orig_category":"Empresas De Portes Y Mensajer\u00cda",
    "sg:phone":"+34 976 57 75 18",
    "sg:postcode":"50016",
    "sg:province":"Zaragoza",
    "wof:name":"Carrillo Portal Armando",
    "wof:placetype":"venue"
},
  "geometry": {"coordinates":[-0.8285425901,41.666934967],"type":"Point"}
}