{
  "type": "Feature",
  "properties": {
    "iso:country":"ES",
    "sg:address":"Avda Eladio Perlado, 28",
    "sg:city":"Burgos",
    "sg:orig_category":"Centros Pms (psico",
    "sg:phone":"+34 947 21 21 02",
    "sg:postcode":"09007",
    "sg:province":"Burgos",
    "wof:name":"Bravo De La Hera Amalia",
    "wof:placetype":"venue"
},
  "geometry": {"coordinates":[-3.6673939228,42.35105896],"type":"Point"}
}