{
  "type": "Feature",
  "properties": {
    "iso:country":"ES",
    "sg:address":"Ctra Rota (de), 137",
    "sg:city":"Chipiona",
    "sg:orig_category":"Comercio De Piezas De Recambio Y De Accesorios De Veh\u00cdculos, Veh\u00cdculos Industriales",
    "sg:phone":"+34 956 37 06 33",
    "sg:postcode":"11550",
    "sg:province":"C\u00e1diz",
    "wof:name":"Automotos Ramar S.l.",
    "wof:placetype":"venue"
},
  "geometry": {"coordinates":[-6.4295816422,36.7326202393],"type":"Point"}
}