{
  "type": "Feature",
  "properties": {
    "addr:full":"Calle de Granada, 97 Almeria Almer\u00eda 04008",
    "addr:housenumber":"97",
    "addr:postcode":"04008",
    "addr:street":"Calle De Granada",
    "iso:country":"ES",
    "sg:address":"Calle de Granada, 97",
    "sg:city":"Almeria",
    "sg:orig_category":"Ropa Para Caballeros Y Se\u00d1oras (al Por Mayor)",
    "sg:phone":"+34 950 25 03 49",
    "sg:postcode":"04008",
    "sg:province":"Almer\u00eda",
    "wof:name":"Molina Villaescusa Maria Del Carmen",
    "wof:placetype":"venue"
},
  "geometry": {"coordinates":[-2.4602987766,36.8449859619],"type":"Point"}
}