{
  "type": "Feature",
  "properties": {
    "iso:country":"ES",
    "sg:address":"Calle de Santa Ana, S/n",
    "sg:city":"Molares",
    "sg:orig_category":"Producci\u00d3n, Comercio De Cereales",
    "sg:phone":"+34 955 83 38 95",
    "sg:postcode":"41750",
    "sg:province":"Sevilla",
    "wof:name":"Cereales Moreno Y Gonzalez S.l.",
    "wof:placetype":"venue"
},
  "geometry": {"coordinates":[-5.7218170166,37.1534080505],"type":"Point"}
}