{
  "type": "Feature",
  "properties": {
    "iso:country":"ES",
    "sg:address":"Rua Principe, 22",
    "sg:city":"Vigo",
    "sg:orig_category":"Productos Qu\u00cdmicos (fabricaci\u00d3n, Al Por Mayor)",
    "sg:phone":"+34 986 22 21 91",
    "sg:postcode":"36202",
    "sg:province":"Pontevedra",
    "wof:name":"H2o Galicia S.l.",
    "wof:placetype":"venue"
},
  "geometry": {"coordinates":[-8.7233476639,42.236946106],"type":"Point"}
}