{
  "type": "Feature",
  "properties": {
    "addr:full":"Pl Enric Morera, 13 Sabadell Barcelona 08203",
    "addr:housenumber":"13",
    "addr:postcode":"08203",
    "addr:street":"Pl Enric Morera",
    "iso:country":"ES",
    "sg:address":"Pl Enric Morera, 13",
    "sg:city":"Sabadell",
    "sg:orig_category":"Molduras, Junquillos, Listones Y Molduras Perforadas",
    "sg:phone":"+34 937 12 24 16",
    "sg:postcode":"08203",
    "sg:province":"Barcelona",
    "wof:name":"Telefonia De Pago T.d.p. S.l.",
    "wof:placetype":"venue"
},
  "geometry": {"coordinates":[2.105768919,41.5290641785],"type":"Point"}
}