{
  "type": "Feature",
  "properties": {
    "iso:country":"ES",
    "sg:address":"Playa Jardin, S/n",
    "sg:city":"Boiro",
    "sg:orig_category":"Ense\u00d1anza, Formaci\u00d3n Profesional: Aprendizaje",
    "sg:phone":"+34 981 84 76 46",
    "sg:postcode":"15930",
    "sg:province":"La Coru\u00f1a",
    "wof:name":"Ayuntamiento De Boiro-casa De Oficios.",
    "wof:placetype":"venue"
},
  "geometry": {"coordinates":[-8.9355735779,42.6803779602],"type":"Point"}
}