{
  "type": "Feature",
  "properties": {
    "iso:country":"ES",
    "sg:address":"Calle de Granada, 11",
    "sg:city":"Aspe",
    "sg:orig_category":"Carnicer\u00cdas, Carnicer\u00cdas",
    "sg:phone":"+34 965 49 14 86",
    "sg:postcode":"03680",
    "sg:province":"Alicante",
    "wof:name":"Berenguer Botella Jose Luis",
    "wof:placetype":"venue"
},
  "geometry": {"coordinates":[-0.7653170228,38.3432502747],"type":"Point"}
}