{
  "type": "Feature",
  "properties": {
    "iso:country":"ES",
    "sg:address":"Cno. Regalfari, S/n",
    "sg:city":"Alcala Chivert",
    "sg:orig_category":"Poller\u00cda Y Caza (al Por Menor)",
    "sg:phone":"+34 964 76 11 17",
    "sg:postcode":"12570",
    "sg:province":"Castell\u00f3n",
    "wof:name":"Espallergues Vi\u00f1olo S.c.p.",
    "wof:placetype":"venue"
},
  "geometry": {"coordinates":[0.2261050045,40.3059234619],"type":"Point"}
}