{
  "type": "Feature",
  "properties": {
    "addr:full":"Calle de Alicun, 16 Madrid Madrid 28033",
    "addr:housenumber":"16",
    "addr:postcode":"madrid;28033",
    "addr:street":"Calle De Alicun",
    "iso:country":"ES",
    "sg:address":"Calle de Alicun, 16",
    "sg:city":"Madrid",
    "sg:orig_category":"Centros Empresariales",
    "sg:phone":"+34 913 83 45 51",
    "sg:postcode":"28033",
    "sg:province":"Madrid",
    "wof:name":"Dbm New Line S L",
    "wof:placetype":"venue"
},
  "geometry": {"coordinates":[-3.6596519947,40.4791526794],"type":"Point"}
}