{
  "type": "Feature",
  "properties": {
    "iso:country":"ES",
    "sg:address":"Calle de Santa Barbara, 47",
    "sg:city":"Monzon",
    "sg:orig_category":"Alquiler De V\u00cddeo",
    "sg:phone":"+34 974 40 32 62",
    "sg:postcode":"22400",
    "sg:province":"Huesca",
    "wof:name":"Fernandez Bello Francisco",
    "wof:placetype":"venue"
},
  "geometry": {"coordinates":[0.1953019947,41.9108467102],"type":"Point"}
}