{
  "type": "Feature",
  "properties": {
    "iso:country":"ES",
    "sg:address":"Calle de General Alava, 10",
    "sg:city":"Vitoria-gasteiz",
    "sg:orig_category":"Bancos",
    "sg:phone":"+34 945 13 11 41",
    "sg:postcode":"01005",
    "sg:province":"\u00c1lava",
    "wof:name":"Banco Espa\u00d1ol De Credito S.a.",
    "wof:placetype":"venue"
},
  "geometry": {"coordinates":[-2.6731100082,42.8449440002],"type":"Point"}
}