{
  "type": "Feature",
  "properties": {
    "iso:country":"ES",
    "sg:address":"Calle de Tetuan, 22",
    "sg:city":"Madrid",
    "sg:orig_category":"Cuidado Del Cabello",
    "sg:phone":"+34 915 32 78 10",
    "sg:postcode":"28013",
    "sg:province":"Madrid",
    "wof:name":"Bellido S. A.",
    "wof:placetype":"venue"
},
  "geometry": {"coordinates":[-3.7032709122,40.4177207947],"type":"Point"}
}