{
  "type": "Feature",
  "properties": {
    "addr:full":"Carretera De Campillos, S/n Ronda M\u00e1laga 29400",
    "addr:housenumber":"s / n",
    "addr:postcode":"29400",
    "addr:street":"Carretera De Campillos;Ronda Ma\u0301Laga",
    "iso:country":"ES",
    "sg:address":"Carretera De Campillos, S/n",
    "sg:city":"Ronda",
    "sg:orig_category":"Agencias De Viajes",
    "sg:phone":"+34 952 87 41 09",
    "sg:postcode":"29400",
    "sg:province":"M\u00e1laga",
    "wof:name":"Don Pedro Travel S.a.",
    "wof:placetype":"venue"
},
  "geometry": {"coordinates":[-5.1662788391,36.7417945862],"type":"Point"}
}