{
  "type": "Feature",
  "properties": {
    "addr:full":"Calle de San Diego, 12 S.gregorio Las Palmas 35200",
    "addr:housenumber":"12",
    "addr:postcode":"35200",
    "addr:street":"Calle De San Diego;Las Palmas",
    "iso:country":"ES",
    "sg:address":"Calle de San Diego, 12",
    "sg:city":"S.gregorio",
    "sg:orig_category":"Parafarmacias",
    "sg:phone":"+34 928 68 40 53",
    "sg:postcode":"35200",
    "sg:province":"Las Palmas",
    "wof:name":"Nutadi S.l.",
    "wof:placetype":"venue"
},
  "geometry": {"coordinates":[-15.4300060272,28.1248226166],"type":"Point"}
}