{
  "type": "Feature",
  "properties": {
    "addr:full":"Avda Rey Don Jaime, 2 Castellon Castell\u00f3n 12001",
    "addr:housenumber":"2",
    "addr:postcode":"12001",
    "addr:street":"Avda Rey Don Jaime;Castello\u0301N",
    "iso:country":"ES",
    "sg:address":"Avda Rey Don Jaime, 2",
    "sg:city":"Castellon",
    "sg:orig_category":"Abogados",
    "sg:phone":"+34 964 24 49 85",
    "sg:postcode":"12001",
    "sg:province":"Castell\u00f3n",
    "wof:name":"Rodriguez Andres C.b.",
    "wof:placetype":"venue"
},
  "geometry": {"coordinates":[-0.0390900001,39.9866714478],"type":"Point"}
}