{
  "type": "Feature",
  "properties": {
    "addr:full":"Calle de Fuenlabrada, 33 Alcorcon Madrid 28922",
    "addr:housenumber":"33",
    "addr:postcode":"28922",
    "addr:street":"Calle De Fuenlabrada",
    "iso:country":"ES",
    "sg:address":"Calle de Fuenlabrada, 33",
    "sg:city":"Alcorcon",
    "sg:orig_category":"Inform\u00c1tica, Ofim\u00c1tica (estudios, Asesor\u00cda, Ingenier\u00cda, Formaci\u00d3n)",
    "sg:phone":"+34 916 43 04 15",
    "sg:postcode":"28922",
    "sg:province":"Madrid",
    "wof:name":"Fernandez Martin Federico",
    "wof:placetype":"venue"
},
  "geometry": {"coordinates":[-3.8257539272,40.3440551758],"type":"Point"}
}