{
  "type": "Feature",
  "properties": {
    "addr:full":"Plaz Andalucia (de), 3 Cordoba C\u00f3rdoba 14009",
    "addr:housenumber":"3",
    "addr:postcode":"14009",
    "addr:street":"Plaz Andalucia De;Co\u0301Rdoba",
    "iso:country":"ES",
    "sg:address":"Plaz Andalucia (de), 3",
    "sg:city":"Cordoba",
    "sg:orig_category":"M\u00c9dicos: Estomatolog\u00cda",
    "sg:phone":"+34 957 29 29 69",
    "sg:postcode":"14009",
    "sg:province":"C\u00f3rdoba",
    "wof:name":"Godoy Pizarro Rafael",
    "wof:placetype":"venue"
},
  "geometry": {"coordinates":[-4.7780418396,37.8699111938],"type":"Point"}
}