{
  "type": "Feature",
  "properties": {
    "addr:full":"Pl Major, 40 Vic Barcelona 08500",
    "addr:housenumber":"40",
    "addr:postcode":"08500",
    "addr:street":"Pl Major",
    "iso:country":"ES",
    "sg:address":"Pl Major, 40",
    "sg:city":"Vic",
    "sg:orig_category":"\u00d3ptica: Instrumentos (fabricaci\u00d3n)",
    "sg:phone":"+34 938 89 09 15",
    "sg:postcode":"08500",
    "sg:province":"Barcelona",
    "wof:name":"Maestre Contreras S.a.",
    "wof:placetype":"venue"
},
  "geometry": {"coordinates":[2.2549040318,41.9302558899],"type":"Point"}
}