{
  "type": "Feature",
  "properties": {
    "iso:country":"ES",
    "sg:address":"Calle de Liebre, 25",
    "sg:city":"Valdezorras",
    "sg:orig_category":"Carnicer\u00cdas, Carnicer\u00cdas",
    "sg:phone":"+34 954 51 09 97",
    "sg:postcode":"41020",
    "sg:province":"Sevilla",
    "wof:name":"Jamones Y Embutidos Ibericos Guzman De Cala S.l.l.",
    "wof:placetype":"venue"
},
  "geometry": {"coordinates":[-5.9251542091,37.4299316406],"type":"Point"}
}