{
  "type": "Feature",
  "properties": {
    "iso:country":"ES",
    "sg:address":"Ferrerias Kalea, 27",
    "sg:city":"Arrasate",
    "sg:orig_category":"Molduras, Junquillos, Listones Y Molduras Perforadas",
    "sg:phone":"+34 943 79 20 04",
    "sg:postcode":"20500",
    "sg:province":"Guip\u00f9zcoa",
    "wof:name":"Lopez Losada Maria Del Sagrario",
    "wof:placetype":"venue"
},
  "geometry": {"coordinates":[-2.491754055,43.0656051636],"type":"Point"}
}