{
  "type": "Feature",
  "properties": {
    "iso:country":"ES",
    "sg:address":"Carrer de Pedraforca, 50",
    "sg:city":"Hospitalet Llobregat",
    "sg:orig_category":"M\u00c1quinas De Coser Y De Hacer Punto (al Por Mayor)",
    "sg:phone":"+34 934 48 05 69",
    "sg:postcode":"08905",
    "sg:province":"Barcelona",
    "wof:name":"Macoalpi S.l.",
    "wof:placetype":"venue"
},
  "geometry": {"coordinates":[2.1093859673,41.3723106384],"type":"Point"}
}