{
  "type": "Feature",
  "properties": {
    "addr:full":"Calle de Humera, 46 Madrid Madrid 28023",
    "addr:housenumber":"46",
    "addr:postcode":"madrid;28023",
    "addr:street":"Calle De Humera",
    "iso:country":"ES",
    "sg:address":"Calle de Humera, 46",
    "sg:city":"Madrid",
    "sg:orig_category":"Inmobiliaria (agencias)",
    "sg:phone":"+34 913 07 80 89",
    "sg:postcode":"28023",
    "sg:province":"Madrid",
    "wof:name":"Balboa Inmuebles S.l.",
    "wof:placetype":"venue"
},
  "geometry": {"coordinates":[-3.78215909,40.4489097595],"type":"Point"}
}