{
  "type": "Feature",
  "properties": {
    "addr:full":"Carrer de Comte D'urgell, 202 Barcelona Barcelona 08036",
    "addr:housenumber":"202",
    "addr:postcode":"08036",
    "addr:street":"Carrer De Comte D'Urgell",
    "iso:country":"ES",
    "sg:address":"Carrer de Comte D'urgell, 202",
    "sg:city":"Barcelona",
    "sg:orig_category":"Venta, Localizaci\u00d3n, Reparaci\u00d3n De Material E Instrumental M\u00c9dico",
    "sg:phone":"+34 934 54 49 26",
    "sg:postcode":"08036",
    "sg:province":"Barcelona",
    "wof:name":"Marpe Suministros Medicos Hospitalarios S.a.",
    "wof:placetype":"venue"
},
  "geometry": {"coordinates":[2.1506137848,41.3881645203],"type":"Point"}
}