{
  "type": "Feature",
  "properties": {
    "iso:country":"ES",
    "sg:address":"Cmno Valdenu\u00d1o (de), 4",
    "sg:city":"Casar",
    "sg:orig_category":"Chapister\u00cda",
    "sg:phone":"+34 949 33 53 32",
    "sg:postcode":"19170",
    "sg:province":"Guadalajara",
    "wof:name":"Autorefurb Europe S L L",
    "wof:placetype":"venue"
},
  "geometry": {"coordinates":[-3.4244785309,40.7036781311],"type":"Point"}
}