{
  "type": "Feature",
  "properties": {
    "iso:country":"ES",
    "sg:address":"Av Jaume I, 14",
    "sg:city":"Roses",
    "sg:orig_category":"Inmobiliaria (agencias)",
    "sg:phone":"+34 972 15 38 00",
    "sg:postcode":"17480",
    "sg:province":"Girona",
    "wof:name":"Fincas Corral Occitania S.l.",
    "wof:placetype":"venue"
},
  "geometry": {"coordinates":[3.1809530258,42.2595062256],"type":"Point"}
}