{
  "type": "Feature",
  "properties": {
    "addr:full":"Calle de Jose Manuel Pedregal, 7 Aviles Asturias 33401",
    "addr:housenumber":"7",
    "addr:postcode":"33401",
    "addr:street":"Calle De Jose Manuel Pedregal",
    "iso:country":"ES",
    "sg:address":"Calle de Jose Manuel Pedregal, 7",
    "sg:city":"Aviles",
    "sg:orig_category":"Art\u00cdculos De Decoraci\u00d3n",
    "sg:phone":"+34 985 56 41 96",
    "sg:postcode":"33401",
    "sg:province":"Asturias",
    "sg:website":"www.ka-international.com",
    "wof:name":"Bogas Y Tocino S.l.l.",
    "wof:placetype":"venue"
},
  "geometry": {"coordinates":[-5.9259309769,43.5594558716],"type":"Point"}
}