{
  "type": "Feature",
  "properties": {
    "iso:country":"ES",
    "sg:address":"Ctra Carrion, 16",
    "sg:city":"Ciudad Real",
    "sg:orig_category":"Material Y Suministros Para Imprenta E Industrias Gr\u00c1ficas",
    "sg:phone":"+34 926 23 25 07",
    "sg:postcode":"13004",
    "sg:province":"Ciudad Real",
    "wof:name":"Imprenta Delmo Sociedad Cooperativa",
    "wof:placetype":"venue"
},
  "geometry": {"coordinates":[-3.9190950394,38.9863014221],"type":"Point"}
}