{
  "type": "Feature",
  "properties": {
    "addr:full":"Calle de Uranio, 23 Fuenlabrada Madrid 28946",
    "addr:housenumber":"23",
    "addr:postcode":"28946",
    "addr:street":"Calle De Uranio",
    "iso:country":"ES",
    "sg:address":"Calle de Uranio, 23",
    "sg:city":"Fuenlabrada",
    "sg:orig_category":"Grabados Y Decoraci\u00d3n De Metales",
    "sg:phone":"+34 916 42 16 31",
    "sg:postcode":"28946",
    "sg:province":"Madrid",
    "sg:website":"www.entalladosmetalicos.com",
    "wof:name":"Enmeta S.a.",
    "wof:placetype":"venue"
},
  "geometry": {"coordinates":[-3.760445118,40.2662239075],"type":"Point"}
}