{
  "type": "Feature",
  "properties": {
    "iso:country":"ES",
    "sg:address":"Calle de Dan, 10",
    "sg:city":"Malaga",
    "sg:orig_category":"Electricidad: Instaladores",
    "sg:phone":"+34 952 36 17 12",
    "sg:postcode":"29006",
    "sg:province":"M\u00e1laga",
    "wof:name":"Tritec 2002 S.l.",
    "wof:placetype":"venue"
},
  "geometry": {"coordinates":[-4.456952095,36.7040977478],"type":"Point"}
}