{
  "type": "Feature",
  "properties": {
    "addr:full":"Rua Nova, 10 Cambados Pontevedra 36630",
    "addr:housenumber":"10",
    "addr:postcode":"36630",
    "addr:street":"Rua Nova",
    "iso:country":"ES",
    "sg:address":"Rua Nova, 10",
    "sg:city":"Cambados",
    "sg:orig_category":"Bisuter\u00cda, Joyer\u00cda, Relojer\u00cda (al Por Menor)",
    "sg:phone":"+34 986 52 40 20",
    "sg:postcode":"36630",
    "sg:province":"Pontevedra",
    "wof:name":"Padin Montans Maria Del Carmen",
    "wof:placetype":"venue"
},
  "geometry": {"coordinates":[-8.8138113022,42.5130958557],"type":"Point"}
}