{
  "type": "Feature",
  "properties": {
    "addr:full":"Calle de Audiencia, 32 Galdar Las Palmas 35460",
    "addr:housenumber":"32",
    "addr:postcode":"35460",
    "addr:street":"Calle De Audiencia",
    "iso:country":"ES",
    "sg:address":"Calle de Audiencia, 32",
    "sg:city":"Galdar",
    "sg:orig_category":"Alimentaci\u00d3n General (al Por Menor)",
    "sg:phone":"+34 928 88 05 93",
    "sg:postcode":"35460",
    "sg:province":"Las Palmas",
    "wof:name":"Reyes Afonso Jose Luis",
    "wof:placetype":"venue"
},
  "geometry": {"coordinates":[-15.6538286209,28.1433048248],"type":"Point"}
}