{
  "type": "Feature",
  "properties": {
    "iso:country":"ES",
    "sg:address":"Calle de Delgado Serrano, 1",
    "sg:city":"Ceuta",
    "sg:classifiers":[
        {
            "category":"Communications",
            "type":"Services"
        }
    ],
    "sg:phone":"+34 956 52 46 37",
    "sg:postcode":"51001",
    "sg:province":"Ceuta",
    "sg:tags":[
        "televisiones",
        "y",
        "radio"
    ],
    "wof:name":"Uniprex-onda Cero",
    "wof:placetype":"venue"
},
  "geometry": {"coordinates":[-5.3095431328,35.8874359131],"type":"Point"}
}