{
  "type": "Feature",
  "properties": {
    "addr:full":"Carrer de Portbou, 11 Barcelona Barcelona 08028",
    "addr:housenumber":"11",
    "addr:postcode":"08028",
    "addr:street":"Carrer De Portbou",
    "iso:country":"ES",
    "sg:address":"Carrer de Portbou, 11",
    "sg:city":"Barcelona",
    "sg:orig_category":"Asesor\u00cda Fiscal Y Jur\u00cddica",
    "sg:phone":"+34 934 48 31 99",
    "sg:postcode":"08028",
    "sg:province":"Barcelona",
    "wof:name":"Romero Castro Maria Victoria",
    "wof:placetype":"venue"
},
  "geometry": {"coordinates":[2.1268379688,41.376033783],"type":"Point"}
}