{
  "type": "Feature",
  "properties": {
    "iso:country":"ES",
    "sg:address":"Calle de Cristobal Colon-rivas, S/n",
    "sg:city":"Rivas",
    "sg:orig_category":"Agricultores, Agricultores",
    "sg:phone":"+34 976 66 18 36",
    "sg:postcode":"50619",
    "sg:province":"Zaragoza",
    "wof:name":"Sat 942 Herpeza",
    "wof:placetype":"venue"
},
  "geometry": {"coordinates":[-0.9369559884,42.3860816956],"type":"Point"}
}