{
  "type": "Feature",
  "properties": {
    "addr:full":"Carretera Leon, S/n Huergas Babia Le\u00f3n 24143",
    "addr:postcode":"24143",
    "addr:street":"Carretera Leon S / N Huergas Babia Leo\u0301N",
    "iso:country":"ES",
    "sg:address":"Carretera Leon, S/n",
    "sg:city":"Huergas Babia",
    "sg:orig_category":"Alimentaci\u00d3n General (al Por Mayor)",
    "sg:phone":"+34 987 48 87 48",
    "sg:postcode":"24143",
    "sg:province":"Le\u00f3n",
    "wof:name":"Martinez Alvarez Cesareo",
    "wof:placetype":"venue"
},
  "geometry": {"coordinates":[-6.0747351646,42.9727630615],"type":"Point"}
}