{
  "type": "Feature",
  "properties": {
    "iso:country":"ES",
    "sg:address":"Avda Fernandez Ladreda, 3",
    "sg:city":"Le\u00f3n",
    "sg:orig_category":"Fabricaci\u00d3n Y Comercio De M\u00c1quinas",
    "sg:phone":"+34 987 20 28 54",
    "sg:postcode":"24005",
    "sg:province":"Le\u00f3n",
    "wof:name":"Ortiz Feijoo Angel",
    "wof:placetype":"venue"
},
  "geometry": {"coordinates":[-5.5614771843,42.5871315002],"type":"Point"}
}