{
  "type": "Feature",
  "properties": {
    "addr:full":"Calle de Sierra De Alcaraz, 41 Madrid Madrid 28053",
    "addr:housenumber":"41",
    "addr:postcode":"madrid;28053",
    "addr:street":"Calle De Sierra De Alcaraz",
    "iso:country":"ES",
    "sg:address":"Calle de Sierra De Alcaraz, 41",
    "sg:city":"Madrid",
    "sg:orig_category":"Guarder\u00cdas",
    "sg:phone":"+34 914 77 35 08",
    "sg:postcode":"28053",
    "sg:province":"Madrid",
    "wof:name":"Escuela Infantil Vickie S.l.",
    "wof:placetype":"venue"
},
  "geometry": {"coordinates":[-3.669303894,40.3904037476],"type":"Point"}
}