{
  "type": "Feature",
  "properties": {
    "iso:country":"ES",
    "sg:address":"Carrer de Alcala De Guadaira, 8",
    "sg:city":"Barcelona",
    "sg:orig_category":"Empresas De Limpieza",
    "sg:phone":"+34 932 66 37 27",
    "sg:postcode":"08020",
    "sg:province":"Barcelona",
    "wof:name":"Jpj Limpex S.l.",
    "wof:placetype":"venue"
},
  "geometry": {"coordinates":[2.1972210407,41.4173164368],"type":"Point"}
}