{
  "type": "Feature",
  "properties": {
    "iso:country":"ES",
    "sg:address":"Pl Esglesia, 7",
    "sg:city":"Castellbisbal",
    "sg:orig_category":"Perfumer\u00cda (al Por Menor)",
    "sg:phone":"+34 937 72 09 74",
    "sg:postcode":"08755",
    "sg:province":"Barcelona",
    "wof:name":"Saura Velasco Encarnacion",
    "wof:placetype":"venue"
},
  "geometry": {"coordinates":[1.9808939695,41.4747505188],"type":"Point"}
}