{
  "type": "Feature",
  "properties": {
    "iso:country":"ES",
    "sg:address":"Calle de San Gerardo, 5",
    "sg:city":"Madrid",
    "sg:orig_category":"Papeler\u00cdas, Librer\u00cdas",
    "sg:phone":"+34 913 73 61 12",
    "sg:postcode":"28035",
    "sg:province":"Madrid",
    "wof:name":"Calle De Mercado Maria Jesus De La",
    "wof:placetype":"venue"
},
  "geometry": {"coordinates":[-3.721517086,40.4664611816],"type":"Point"}
}