{
  "type": "Feature",
  "properties": {
    "iso:country":"ES",
    "sg:address":"Avda Andalucia (de), 3",
    "sg:city":"Granada",
    "sg:orig_category":"Inform\u00c1tica: Material Y Suministros",
    "sg:phone":"+34 958 20 67 70",
    "sg:postcode":"18014",
    "sg:province":"Granada",
    "wof:name":"Rm Informatica C.b.",
    "wof:placetype":"venue"
},
  "geometry": {"coordinates":[-3.6126980782,37.1883506775],"type":"Point"}
}