{
  "type": "Feature",
  "properties": {
    "addr:full":"Calle de San Perfecto, 19 Cordoba C\u00f3rdoba 14007",
    "addr:housenumber":"19",
    "addr:postcode":"14007",
    "addr:street":"Calle De San Perfecto;Co\u0301Rdoba",
    "iso:country":"ES",
    "sg:address":"Calle de San Perfecto, 19",
    "sg:city":"Cordoba",
    "sg:orig_category":"Bisuter\u00cda, Joyer\u00cda, Relojer\u00cda (al Por Menor)",
    "sg:phone":"+34 957 43 47 94",
    "sg:postcode":"14007",
    "sg:province":"C\u00f3rdoba",
    "wof:name":"Chapasur S.l.",
    "wof:placetype":"venue"
},
  "geometry": {"coordinates":[-4.7592282295,37.8944854736],"type":"Point"}
}