{
  "type": "Feature",
  "properties": {
    "addr:full":"Avda Portugal, 122 Salamanca Salamanca 37006",
    "addr:housenumber":"122",
    "addr:postcode":"37006",
    "addr:street":"Avda Portugal",
    "iso:country":"ES",
    "sg:address":"Avda Portugal, 122",
    "sg:city":"Salamanca",
    "sg:orig_category":"Molduras, Junquillos, Listones Y Molduras Perforadas",
    "sg:phone":"+34 923 25 05 36",
    "sg:postcode":"37006",
    "sg:province":"Salamanca",
    "wof:name":"Mangas Aparicio Gabriel",
    "wof:placetype":"venue"
},
  "geometry": {"coordinates":[-5.6635627747,40.9726448059],"type":"Point"}
}