{
  "type": "Feature",
  "properties": {
    "iso:country":"ES",
    "sg:address":"Calle de General Ricardos, 39",
    "sg:city":"Madrid",
    "sg:orig_category":"Electrodom\u00c9sticos (fabricaci\u00d3n, Al Por Mayor)",
    "sg:phone":"+34 914 72 00 89",
    "sg:postcode":"28019",
    "sg:province":"Madrid",
    "wof:name":"Proselco S.a.",
    "wof:placetype":"venue"
},
  "geometry": {"coordinates":[-3.7196276188,40.3955917358],"type":"Point"}
}