{
  "type": "Feature",
  "properties": {
    "addr:full":"Ctra Madrid-irun, Km. 0234,3 Burgos Burgos 09001",
    "addr:postcode":"09001",
    "addr:street":"Ctra Madrid-Irun Km. 0234,3",
    "iso:country":"ES",
    "sg:address":"Ctra Madrid-irun, Km. 0234,3",
    "sg:city":"Burgos",
    "sg:orig_category":"Ingenier\u00cda, Centros De Estudios (diversos)",
    "sg:phone":"+34 947 25 77 60",
    "sg:postcode":"09001",
    "sg:province":"Burgos",
    "wof:name":"Eptisa Servicios De Ingenieria S.a.",
    "wof:placetype":"venue"
},
  "geometry": {"coordinates":[-3.7021090984,42.3170166016],"type":"Point"}
}