{
  "type": "Feature",
  "properties": {
    "addr:full":"Calle de Urbieta, 62 Donostia-san Sebastian Guip\u00f9zcoa 20006",
    "addr:housenumber":"62",
    "addr:postcode":"20006",
    "addr:street":"Calle De Urbieta",
    "iso:country":"ES",
    "sg:address":"Calle de Urbieta, 62",
    "sg:city":"Donostia-san Sebastian",
    "sg:orig_category":"Centros De Coordinaci\u00d3n",
    "sg:phone":"+34 943 45 35 41",
    "sg:postcode":"20006",
    "sg:province":"Guip\u00f9zcoa",
    "wof:name":"Insausti Gestion S.l.",
    "wof:placetype":"venue"
},
  "geometry": {"coordinates":[-1.9807690382,43.3138542175],"type":"Point"}
}