{
  "type": "Feature",
  "properties": {
    "iso:country":"ES",
    "sg:address":"Calle de Acacias, 16",
    "sg:city":"Salamanca",
    "sg:orig_category":"Delegados, Agentes De Tr\u00c1nsito, Auxiliares De Transporte Internacional",
    "sg:phone":"+34 923 23 71 25",
    "sg:postcode":"37004",
    "sg:province":"Salamanca",
    "wof:name":"Transportes Tisamar S.l.",
    "wof:placetype":"venue"
},
  "geometry": {"coordinates":[-5.6525959969,40.9759941101],"type":"Point"}
}