{
  "type": "Feature",
  "properties": {
    "addr:full":"Av Mestre Josep Bonay, 23 Palafrugell Girona 17200",
    "addr:housenumber":"23",
    "addr:postcode":"17200",
    "addr:street":"Av Mestre Josep Bonay",
    "iso:country":"ES",
    "sg:address":"Av Mestre Josep Bonay, 23",
    "sg:city":"Palafrugell",
    "sg:orig_category":"Alquiler De Veh\u00cdculos: Turismos Y Utilitarios",
    "sg:phone":"+34 972 30 31 47",
    "sg:postcode":"17200",
    "sg:province":"Girona",
    "wof:name":"Autocares Celymar Sl",
    "wof:placetype":"venue"
},
  "geometry": {"coordinates":[3.1705186367,41.9221076965],"type":"Point"}
}