{
  "type": "Feature",
  "properties": {
    "addr:full":"Calle de Atocha, 26 Madrid Madrid 28012",
    "addr:housenumber":"26",
    "addr:postcode":"madrid;28012",
    "addr:street":"Calle De Atocha",
    "iso:country":"ES",
    "sg:address":"Calle de Atocha, 26",
    "sg:city":"Madrid",
    "sg:orig_category":"Telas Y Sedas (al Por Menor)",
    "sg:phone":"+34 913 69 45 00",
    "sg:postcode":"28012",
    "sg:province":"Madrid",
    "sg:website":"www.ribescasals.com",
    "wof:name":"Ribes Y Casals S.a.",
    "wof:placetype":"venue"
},
  "geometry": {"coordinates":[-3.701972723,40.4136123657],"type":"Point"}
}