{
  "type": "Feature",
  "properties": {
    "addr:full":"Pla\u00c7 Diputacio, 1 Girona Girona 17001",
    "addr:housenumber":"1",
    "addr:postcode":"17001",
    "addr:street":"Diputacio",
    "iso:country":"ES",
    "sg:address":"Pla\u00c7 Diputacio, 1",
    "sg:city":"Girona",
    "sg:orig_category":"Doctores En Medicina",
    "sg:phone":"+34 972 20 80 36",
    "sg:postcode":"17001",
    "sg:province":"Girona",
    "wof:name":"Negre Frigola Narcis",
    "wof:placetype":"venue"
},
  "geometry": {"coordinates":[2.8210680485,41.9823036194],"type":"Point"}
}