{
  "type": "Feature",
  "properties": {
    "addr:full":"Calle de San Sebastian, 53 Santa Cruz Palma Santa Cruz De Tenerife 38700",
    "addr:housenumber":"53",
    "addr:postcode":"38700",
    "addr:street":"Calle De San Sebastian",
    "iso:country":"ES",
    "sg:address":"Calle de San Sebastian, 53",
    "sg:city":"Santa Cruz Palma",
    "sg:orig_category":"Panader\u00cdas, Panader\u00cdas",
    "sg:phone":"+34 922 41 53 28",
    "sg:postcode":"38700",
    "sg:province":"Santa Cruz De Tenerife",
    "wof:name":"Hernandez Guerra Jesus Manuel",
    "wof:placetype":"venue"
},
  "geometry": {"coordinates":[-17.7671298981,28.6836719513],"type":"Point"}
}