{
  "type": "Feature",
  "properties": {
    "iso:country":"ES",
    "sg:address":"L'ordim, 10",
    "sg:city":"Ontinyent",
    "sg:orig_category":"Fabricaci\u00d3n De Telas Y Sedas",
    "sg:phone":"+34 962 91 08 88",
    "sg:postcode":"46870",
    "sg:province":"Valencia",
    "sg:website":"www.ribetesmora.com",
    "wof:name":"Ribetes Mora S.l.",
    "wof:placetype":"venue"
},
  "geometry": {"coordinates":[-0.6489199996,38.8086509705],"type":"Point"}
}