{
  "type": "Feature",
  "properties": {
    "iso:country":"ES",
    "sg:address":"Crri Viveros Municipales, 10",
    "sg:city":"Belchi",
    "sg:orig_category":"Venta Al Preg\u00d3n",
    "sg:phone":"+34 968 28 47 32",
    "sg:postcode":"30009",
    "sg:province":"Murcia",
    "wof:name":"Martinez Espinosa Manuel",
    "wof:placetype":"venue"
},
  "geometry": {"coordinates":[-1.1528439522,37.9883460999],"type":"Point"}
}