{
  "type": "Feature",
  "properties": {
    "addr:full":"Calle de Cantos Gordos (de Los), 9 Cercedilla Madrid 28470",
    "addr:postcode":"28470",
    "addr:street":"Calle De Cantos",
    "iso:country":"ES",
    "sg:address":"Calle de Cantos Gordos (de Los), 9",
    "sg:city":"Cercedilla",
    "sg:orig_category":"Centros De Reservas Hoteleras",
    "sg:phone":"+34 918 52 07 31",
    "sg:postcode":"28470",
    "sg:province":"Madrid",
    "wof:name":"Iberia Consulting Gundi S.l.",
    "wof:placetype":"venue"
},
  "geometry": {"coordinates":[-4.0489535332,40.743598938],"type":"Point"}
}