{
  "type": "Feature",
  "properties": {
    "iso:country":"ES",
    "sg:address":"Avda Europa, S/n",
    "sg:city":"Arcos Frontera",
    "sg:orig_category":"Farmacias",
    "sg:phone":"+34 956 70 02 52",
    "sg:postcode":"11630",
    "sg:province":"C\u00e1diz",
    "wof:name":"Reina Gonzalez Pilar",
    "wof:placetype":"venue"
},
  "geometry": {"coordinates":[-5.7962021828,36.7435951233],"type":"Point"}
}