{
  "type": "Feature",
  "properties": {
    "addr:full":"Calle de Polo Y Peyrolon, 28 Valencia Valencia 46021",
    "addr:housenumber":"28",
    "addr:postcode":"46021",
    "addr:street":"Calle De Polo Y Peyrolon",
    "iso:country":"ES",
    "sg:address":"Calle de Polo Y Peyrolon, 28",
    "sg:city":"Valencia",
    "sg:orig_category":"Supermercados Y Hipermercados",
    "sg:phone":"+34 963 61 29 15",
    "sg:postcode":"46021",
    "sg:province":"Valencia",
    "sg:website":"www.mercadona.es",
    "wof:name":"Mercadona S.a.",
    "wof:placetype":"venue"
},
  "geometry": {"coordinates":[-0.3546459973,39.4736671448],"type":"Point"}
}