{
  "type": "Feature",
  "properties": {
    "iso:country":"ES",
    "sg:address":"Plaz Pedagogo Pestalozzi, 2",
    "sg:city":"Valencia",
    "sg:orig_category":"Edici\u00d3n De Diarios, Revistas, Boletines",
    "sg:phone":"+34 963 73 43 54",
    "sg:postcode":"46006",
    "sg:province":"Valencia",
    "wof:name":"Baguena Reig Amado",
    "wof:placetype":"venue"
},
  "geometry": {"coordinates":[-0.3656939864,39.4577407837],"type":"Point"}
}