{
  "type": "Feature",
  "properties": {
    "iso:country":"ES",
    "sg:address":"Carr Lorenzo Borja, 6",
    "sg:city":"Cullera",
    "sg:orig_category":"Inmobiliaria (agencias)",
    "sg:phone":"+34 961 72 16 27",
    "sg:postcode":"46400",
    "sg:province":"Valencia",
    "wof:name":"Sapnish Agents Investment, S.l.",
    "wof:placetype":"venue"
},
  "geometry": {"coordinates":[-0.2438610047,39.1661643982],"type":"Point"}
}