{
  "type": "Feature",
  "properties": {
    "iso:country":"ES",
    "sg:address":"Rua Lopez De Neira, 22",
    "sg:city":"Vigo",
    "sg:orig_category":"Sociedades, Compa\u00d1\u00cdas Aseguradoras",
    "sg:phone":"+34 986 22 12 07",
    "sg:postcode":"36202",
    "sg:province":"Pontevedra",
    "wof:name":"D.a.s. Defensa Del Automovilista Y De Siniestros Internacional S.a.",
    "wof:placetype":"venue"
},
  "geometry": {"coordinates":[-8.7244968414,42.2363395691],"type":"Point"}
}