{
  "type": "Feature",
  "properties": {
    "addr:full":"Cmno Eras (las), S/n Herrera Sevilla 41567",
    "addr:postcode":"41567",
    "addr:street":"Cmno Eras Las S / N Herrera",
    "iso:country":"ES",
    "sg:address":"Cmno Eras (las), S/n",
    "sg:city":"Herrera",
    "sg:orig_category":"Hormig\u00d3n (m\u00c1quinas E Instalaci\u00d3n)",
    "sg:phone":"+34 954 01 29 10",
    "sg:postcode":"41567",
    "sg:province":"Sevilla",
    "wof:name":"Hormigones Jurado S.c.",
    "wof:placetype":"venue"
},
  "geometry": {"coordinates":[-4.8506789207,37.3627128601],"type":"Point"}
}