{
  "type": "Feature",
  "properties": {
    "iso:country":"ES",
    "sg:address":"Plaz Santo Domingo, 12",
    "sg:city":"Madrid",
    "sg:orig_category":"Producci\u00d3n, Distribuci\u00d3n De Electricidad",
    "sg:phone":"+34 915 47 36 19",
    "sg:postcode":"28013",
    "sg:province":"Madrid",
    "wof:name":"Alonso Lista Luis Miguel",
    "wof:placetype":"venue"
},
  "geometry": {"coordinates":[-3.7089457512,40.4205856323],"type":"Point"}
}