{
  "type": "Feature",
  "properties": {
    "addr:full":"Carrer de Ruben Dario, 40 Barcelona Barcelona 08030",
    "addr:housenumber":"40",
    "addr:postcode":"08030",
    "addr:street":"Carrer De Ruben Dario",
    "iso:country":"ES",
    "sg:address":"Carrer de Ruben Dario, 40",
    "sg:city":"Barcelona",
    "sg:orig_category":"Arquitectos",
    "sg:phone":"+34 933 45 48 81",
    "sg:postcode":"08030",
    "sg:province":"Barcelona",
    "wof:name":"Copons Balius Jose",
    "wof:placetype":"venue"
},
  "geometry": {"coordinates":[2.187789917,41.4343948364],"type":"Point"}
}