{
  "type": "Feature",
  "properties": {
    "iso:country":"ES",
    "sg:address":"Calle de Barrenkale, 23",
    "sg:city":"Plentzia",
    "sg:orig_category":"Deportes Diversos",
    "sg:phone":"+34 946 77 34 97",
    "sg:postcode":"48620",
    "sg:province":"Vizcaya",
    "wof:name":"Estratos Publicidad Aerostatica S.l.",
    "wof:placetype":"venue"
},
  "geometry": {"coordinates":[-2.9479832649,43.4041252136],"type":"Point"}
}