{
  "type": "Feature",
  "properties": {
    "iso:country":"ES",
    "sg:address":"Carrer de Pujol, 8",
    "sg:city":"Mataro",
    "sg:orig_category":"Ingenier\u00cda, Centros De Estudios (diversos)",
    "sg:phone":"+34 937 41 04 49",
    "sg:postcode":"08301",
    "sg:province":"Barcelona",
    "sg:website":"www.dracnet.com",
    "wof:name":"Dracnet Project S.l.",
    "wof:placetype":"venue"
},
  "geometry": {"coordinates":[2.445250988,41.5390930176],"type":"Point"}
}