{
  "type": "Feature",
  "properties": {
    "iso:country":"ES",
    "sg:address":"Carrer de Arago, 93",
    "sg:city":"Barcelona",
    "sg:orig_category":"Abogados",
    "sg:phone":"+34 932 26 63 21",
    "sg:postcode":"08015",
    "sg:province":"Barcelona",
    "wof:name":"Hiniesta Torres Eduardo",
    "wof:placetype":"venue"
},
  "geometry": {"coordinates":[2.1511418819,41.3820228577],"type":"Point"}
}