{
  "type": "Feature",
  "properties": {
    "iso:country":"ES",
    "sg:address":"Calle de San Rodrigo, 6",
    "sg:city":"Cabra",
    "sg:orig_category":"Panader\u00cdas, Panader\u00cdas",
    "sg:phone":"+34 957 52 42 78",
    "sg:postcode":"14940",
    "sg:province":"C\u00f3rdoba",
    "wof:name":"Blancas Ordo\u00f1ez Manuel",
    "wof:placetype":"venue"
},
  "geometry": {"coordinates":[-4.4293060303,37.4741630554],"type":"Point"}
}