{
  "type": "Feature",
  "properties": {
    "addr:full":"Carrer de Joaquin Costa, 57 Barcelona Barcelona 08001",
    "addr:housenumber":"57",
    "addr:postcode":"08001",
    "addr:street":"Carrer De Joaquin Costa",
    "iso:country":"ES",
    "sg:address":"Carrer de Joaquin Costa, 57",
    "sg:city":"Barcelona",
    "sg:orig_category":"Zapatos (al Por Menor)",
    "sg:phone":"+34 933 01 22 30",
    "sg:postcode":"08001",
    "sg:province":"Barcelona",
    "wof:name":"Valldeperas Ribe Francisco",
    "wof:placetype":"venue"
},
  "geometry": {"coordinates":[2.1645169258,41.3835296631],"type":"Point"}
}