{
  "type": "Feature",
  "properties": {
    "iso:country":"ES",
    "sg:address":"Carrer de Sol, 7",
    "sg:city":"Nucli Urba",
    "sg:orig_category":"Fabrica De Charcuter\u00cda",
    "sg:phone":"+34 938 45 98 27",
    "sg:postcode":"08410",
    "sg:province":"Barcelona",
    "wof:name":"Costa Angelet S.a.",
    "wof:placetype":"venue"
},
  "geometry": {"coordinates":[2.2929201126,41.5559082031],"type":"Point"}
}