{
  "type": "Feature",
  "properties": {
    "iso:country":"ES",
    "sg:address":"Carrer de Corro, 185",
    "sg:city":"Granollers",
    "sg:orig_category":"Veh\u00cdculos De Ocasi\u00d3n",
    "sg:phone":"+34 938 49 58 49",
    "sg:postcode":"08401",
    "sg:province":"Barcelona",
    "wof:name":"Reyes Reyes Jose Manuel",
    "wof:placetype":"venue"
},
  "geometry": {"coordinates":[2.2900691032,41.613861084],"type":"Point"}
}