{
  "type": "Feature",
  "properties": {
    "addr:full":"G.v. Lopez De Haro D. Diego, 64 Bilbao Vizcaya 48011",
    "addr:housenumber":"64",
    "addr:postcode":"48011",
    "addr:street":"Lopez De Haro D. Diego",
    "iso:country":"ES",
    "sg:address":"G.v. Lopez De Haro D. Diego, 64",
    "sg:city":"Bilbao",
    "sg:orig_category":"M\u00c9dicos: Estomatolog\u00cda",
    "sg:phone":"+34 944 42 47 47",
    "sg:postcode":"48011",
    "sg:province":"Vizcaya",
    "wof:name":"Casta\u00f1os Madariaga Florentino Javier",
    "wof:placetype":"venue"
},
  "geometry": {"coordinates":[-2.9414570332,43.2645797729],"type":"Point"}
}