{
  "type": "Feature",
  "properties": {
    "iso:country":"ES",
    "sg:address":"Avda Ancha De Castelar, 93",
    "sg:city":"San Vicente Del Raspeig-sant Vicent Del Raspeig",
    "sg:orig_category":"Mec\u00c1nico Del Autom\u00d3vil",
    "sg:phone":"+34 965 67 07 76",
    "sg:postcode":"03690",
    "sg:province":"Alicante",
    "wof:name":"Mecanica Rapida San Vicente S.l",
    "wof:placetype":"venue"
},
  "geometry": {"coordinates":[-0.5238710046,38.3988189697],"type":"Point"}
}