{
  "type": "Feature",
  "properties": {
    "addr:full":"Av Urgell, 6 Bellpuig Lleida 25250",
    "addr:housenumber":"6",
    "addr:postcode":"25250",
    "addr:street":"Av Urgell",
    "iso:country":"ES",
    "sg:address":"Av Urgell, 6",
    "sg:city":"Bellpuig",
    "sg:orig_category":"Serrer\u00cdas De Madera",
    "sg:phone":"+34 973 32 03 47",
    "sg:postcode":"25250",
    "sg:province":"Lleida",
    "wof:name":"Cordoba Mur Jose Francisco",
    "wof:placetype":"venue"
},
  "geometry": {"coordinates":[1.0085630417,41.6279029846],"type":"Point"}
}