{
  "type": "Feature",
  "properties": {
    "iso:country":"ES",
    "sg:address":"Calle de Cardenal Fonseca, S/n",
    "sg:city":"Alcala Henares",
    "sg:orig_category":"Empresas De Limpieza",
    "sg:phone":"+34 918 82 32 65",
    "sg:postcode":"28805",
    "sg:province":"Madrid",
    "wof:name":"Limieza Hemanos Deverjo S.l.",
    "wof:placetype":"venue"
},
  "geometry": {"coordinates":[-3.3562664986,40.4868354797],"type":"Point"}
}