{
  "type": "Feature",
  "properties": {
    "iso:country":"ES",
    "sg:address":"Pl. Duque, 12",
    "sg:city":"Osuna",
    "sg:orig_category":"Peluquer\u00cdas, Peluquer\u00cda Mixta",
    "sg:phone":"+34 955 82 06 36",
    "sg:postcode":"41640",
    "sg:province":"Sevilla",
    "wof:name":"C.rivera Peluqueros S.c.",
    "wof:placetype":"venue"
},
  "geometry": {"coordinates":[-5.1050539017,37.2361679077],"type":"Point"}
}