{
  "type": "Feature",
  "properties": {
    "iso:country":"ES",
    "sg:address":"Calle de Borujas, S/n",
    "sg:city":"Moron Frontera",
    "sg:orig_category":"Muebles, Minoristas",
    "sg:phone":"+34 955 85 23 82",
    "sg:postcode":"41530",
    "sg:province":"Sevilla",
    "wof:name":"Hispavidrio S.l.",
    "wof:placetype":"venue"
},
  "geometry": {"coordinates":[-5.444873333,37.1313018799],"type":"Point"}
}