{
  "type": "Feature",
  "properties": {
    "iso:country":"ES",
    "sg:address":"Cala Finestrat, S/n",
    "sg:city":"Finestrat",
    "sg:orig_category":"Mec\u00c1nico Del Autom\u00d3vil",
    "sg:phone":"+34 965 85 37 53",
    "sg:postcode":"03509",
    "sg:province":"Alicante",
    "wof:name":"Talleres La Cala S.a.l.",
    "wof:placetype":"venue"
},
  "geometry": {"coordinates":[-0.1988539994,38.5523109436],"type":"Point"}
}