{
  "type": "Feature",
  "properties": {
    "iso:country":"ES",
    "sg:address":"Rua Ronda Don Bosco, S/n",
    "sg:city":"Vigo",
    "sg:orig_category":"Carnicer\u00cdas, Carnicer\u00cdas",
    "sg:phone":"+34 986 43 64 87",
    "sg:postcode":"36202",
    "sg:province":"Pontevedra",
    "wof:name":"Gil Rocha Manuel",
    "wof:placetype":"venue"
},
  "geometry": {"coordinates":[-8.7211723328,42.2350540161],"type":"Point"}
}