{
  "type": "Feature",
  "properties": {
    "addr:full":"Ctra Nacional Ii, 66 Jonquera Girona 17700",
    "addr:housenumber":"66",
    "addr:postcode":"17700",
    "addr:street":"Ctra Nacional Ii",
    "iso:country":"ES",
    "sg:address":"Ctra Nacional Ii, 66",
    "sg:city":"Jonquera",
    "sg:orig_category":"Perfumer\u00cda (al Por Menor)",
    "sg:phone":"+34 972 55 41 55",
    "sg:postcode":"17700",
    "sg:province":"Girona",
    "wof:name":"Garcia Cadarso C.b.",
    "wof:placetype":"venue"
},
  "geometry": {"coordinates":[2.8876435757,42.4460220337],"type":"Point"}
}