{
  "type": "Feature",
  "properties": {
    "addr:full":"Calle de San Andres (de), 7 Fuenlabrada Madrid 28945",
    "addr:housenumber":"7",
    "addr:postcode":"28945",
    "addr:street":"Calle De San Andres De",
    "iso:country":"ES",
    "sg:address":"Calle de San Andres (de), 7",
    "sg:city":"Fuenlabrada",
    "sg:orig_category":"Maquinaria Para Industrias Diversas",
    "sg:phone":"+34 916 06 59 60",
    "sg:postcode":"28945",
    "sg:province":"Madrid",
    "wof:name":"Supralux S.l.",
    "wof:placetype":"venue"
},
  "geometry": {"coordinates":[-3.7957932949,40.2855911255],"type":"Point"}
}