{
  "type": "Feature",
  "properties": {
    "iso:country":"ES",
    "sg:address":"Zapateros(p I Tres Hermanas), 20",
    "sg:city":"Aspe",
    "sg:orig_category":"Confecci\u00d3n De Zapatos",
    "sg:phone":"+34 965 49 26 34",
    "sg:postcode":"03680",
    "sg:province":"Alicante",
    "wof:name":"Exclusivas Yessey S.l.",
    "wof:placetype":"venue"
},
  "geometry": {"coordinates":[-0.757043004,38.3229293823],"type":"Point"}
}