{
  "type": "Feature",
  "properties": {
    "addr:full":"Carrer de Diana, 12 Denia Alicante 03700",
    "addr:housenumber":"12",
    "addr:postcode":"03700",
    "addr:street":"Carrer De Diana",
    "iso:country":"ES",
    "sg:address":"Carrer de Diana, 12",
    "sg:city":"Denia",
    "sg:orig_category":"Estilistas Y Estudios De Estilo De Corte Y Confecci\u00d3n",
    "sg:phone":"+34 965 78 92 61",
    "sg:postcode":"03700",
    "sg:province":"Alicante",
    "wof:name":"Ortega Claros Jose",
    "wof:placetype":"venue"
},
  "geometry": {"coordinates":[0.1069130003,38.8402900696],"type":"Point"}
}