{
  "type": "Feature",
  "properties": {
    "addr:full":"Avda Juan De La Cierva, 33 Getafe Madrid 28902",
    "addr:housenumber":"33",
    "addr:postcode":"28902",
    "addr:street":"Avda Juan De La Cierva",
    "iso:country":"ES",
    "sg:address":"Avda Juan De La Cierva, 33",
    "sg:city":"Getafe",
    "sg:orig_category":"Loter\u00cda Y T\u00d3mbola",
    "sg:phone":"+34 916 65 22 58",
    "sg:postcode":"28902",
    "sg:province":"Madrid",
    "wof:name":"Benavente Doniga Jesus",
    "wof:placetype":"venue"
},
  "geometry": {"coordinates":[-3.7252709866,40.3094329834],"type":"Point"}
}