{
  "type": "Feature",
  "properties": {
    "addr:full":"Z. Sinia, S/n Ripollet Barcelona 08291",
    "addr:housenumber":"s / n",
    "addr:postcode":"08291",
    "addr:street":"Z. Sinia",
    "iso:country":"ES",
    "sg:address":"Z. Sinia, S/n",
    "sg:city":"Ripollet",
    "sg:orig_category":"Transporte En General",
    "sg:phone":"+34 935 80 58 44",
    "sg:postcode":"08291",
    "sg:province":"Barcelona",
    "sg:website":"www.sorea.es",
    "wof:name":"Sorea S.a.",
    "wof:placetype":"venue"
},
  "geometry": {"coordinates":[2.1581029892,41.4984054565],"type":"Point"}
}