{
  "type": "Feature",
  "properties": {
    "iso:country":"ES",
    "sg:address":"Pla\u00c7 Soler I Gustems, 5",
    "sg:city":"Vilanova I La Geltru",
    "sg:orig_category":"Asociaciones Y Clubs Deportivos",
    "sg:phone":"+34 938 14 14 36",
    "sg:postcode":"08800",
    "sg:province":"Barcelona",
    "wof:name":"Olaria Esports S.l.",
    "wof:placetype":"venue"
},
  "geometry": {"coordinates":[1.7270840406,41.2234153748],"type":"Point"}
}