{
  "type": "Feature",
  "properties": {
    "addr:full":"Ctra Lorca, 340 Totana Murcia 30850",
    "addr:housenumber":"340",
    "addr:postcode":"30850",
    "addr:street":"Ctra Lorca",
    "iso:country":"ES",
    "sg:address":"Ctra Lorca, 340",
    "sg:city":"Totana",
    "sg:orig_category":"Mec\u00c1nico Del Autom\u00d3vil",
    "sg:phone":"+34 968 42 28 65",
    "sg:postcode":"30850",
    "sg:province":"Murcia",
    "wof:name":"Garcia Cayuela Pedro",
    "wof:placetype":"venue"
},
  "geometry": {"coordinates":[-1.5030390024,37.7726860046],"type":"Point"}
}