{
  "type": "Feature",
  "properties": {
    "iso:country":"ES",
    "sg:address":"Calle de Agua, 6",
    "sg:city":"Berja",
    "sg:orig_category":"Molduras, Junquillos, Listones Y Molduras Perforadas",
    "sg:phone":"+34 950 49 16 63",
    "sg:postcode":"04760",
    "sg:province":"Almer\u00eda",
    "wof:name":"Ortega Barrionuevo Francico",
    "wof:placetype":"venue"
},
  "geometry": {"coordinates":[-2.9495396614,36.8459510803],"type":"Point"}
}