{
  "type": "Feature",
  "properties": {
    "iso:country":"ES",
    "sg:address":"Calle de Lope De Vega, 4",
    "sg:city":"Gijon",
    "sg:orig_category":"Fabricaci\u00d3n De Art\u00cdculos Y Equipos Deportivos Y De Ocio",
    "sg:phone":"+34 985 33 77 07",
    "sg:postcode":"33204",
    "sg:province":"Asturias",
    "wof:name":"Freezed Bee Sociedad Anonima Laboral",
    "wof:placetype":"venue"
},
  "geometry": {"coordinates":[-5.6529808044,43.5334472656],"type":"Point"}
}