{
  "type": "Feature",
  "properties": {
    "addr:full":"Calle de Virgen De Loreto, 35 Sevilla Sevilla 41011",
    "addr:housenumber":"35",
    "addr:postcode":"41011",
    "addr:street":"Calle De Virgen De Loreto",
    "iso:country":"ES",
    "sg:address":"Calle de Virgen De Loreto, 35",
    "sg:city":"Sevilla",
    "sg:orig_category":"Ropa Para Se\u00d1oras (al Por Menor)",
    "sg:phone":"+34 954 27 74 54",
    "sg:postcode":"41011",
    "sg:province":"Sevilla",
    "wof:name":"Moda 2 R Loreto 35s.l.",
    "wof:placetype":"venue"
},
  "geometry": {"coordinates":[-5.9993929863,37.3755378723],"type":"Point"}
}