{
  "type": "Feature",
  "properties": {
    "addr:full":"Diseminados, 44 Urretxu Guip\u00f9zcoa 20700",
    "addr:housenumber":"44",
    "addr:postcode":"20700",
    "addr:street":"Diseminados;Guipu\u0300Zcoa",
    "iso:country":"ES",
    "sg:address":"Diseminados, 44",
    "sg:city":"Urretxu",
    "sg:orig_category":"Negocio De Materiales De Construcci\u00d3n",
    "sg:phone":"+34 943 72 63 29",
    "sg:postcode":"20700",
    "sg:province":"Guip\u00f9zcoa",
    "wof:name":"Almacenes De Materiales De Construcciones Ramon Maiztegui S.l.",
    "wof:placetype":"venue"
},
  "geometry": {"coordinates":[-2.3314831257,43.091178894],"type":"Point"}
}