{
  "type": "Feature",
  "properties": {
    "iso:country":"ES",
    "sg:address":"Calle de Cabo Noval, 12",
    "sg:city":"Oviedo",
    "sg:orig_category":"Ropa Para Se\u00d1oras (al Por Menor)",
    "sg:phone":"+34 985 22 28 96",
    "sg:postcode":"33007",
    "sg:province":"Asturias",
    "wof:name":"Fernandez Posada Eufemia",
    "wof:placetype":"venue"
},
  "geometry": {"coordinates":[-5.848628521,43.3604812622],"type":"Point"}
}