{
  "type": "Feature",
  "properties": {
    "iso:country":"ES",
    "sg:address":"Calle de Santa Virgilia, 3",
    "sg:city":"Madrid",
    "sg:orig_category":"M\u00c9dicos: Estomatolog\u00cda",
    "sg:phone":"+34 917 64 66 85",
    "sg:postcode":"28033",
    "sg:province":"Madrid",
    "wof:name":"Aguado Galvez Felipe",
    "wof:placetype":"venue"
},
  "geometry": {"coordinates":[-3.6442525387,40.4772071838],"type":"Point"}
}