{
  "type": "Feature",
  "properties": {
    "iso:country":"ES",
    "sg:address":"Cno De Colmenar, 5",
    "sg:city":"Casabermeja",
    "sg:orig_category":"Sociedades, Compa\u00d1\u00cdas Aseguradoras",
    "sg:phone":"+34 952 75 82 06",
    "sg:postcode":"29160",
    "sg:province":"M\u00e1laga",
    "wof:name":"Pedro Molina Mu\u00f1oz S.l.",
    "wof:placetype":"venue"
},
  "geometry": {"coordinates":[-4.4291119576,36.8940238953],"type":"Point"}
}