{
  "type": "Feature",
  "properties": {
    "iso:country":"ES",
    "sg:address":"Calle de Comedias, 11",
    "sg:city":"Malaga",
    "sg:orig_category":"M\u00c9dicos: Foniatr\u00cda Y Logopedia",
    "sg:phone":"+34 952 21 90 10",
    "sg:postcode":"29008",
    "sg:province":"M\u00e1laga",
    "wof:name":"Gabinete De Psicologia Y Logopedia Almaraz S.c.",
    "wof:placetype":"venue"
},
  "geometry": {"coordinates":[-4.421482563,36.7228813171],"type":"Point"}
}