{
  "type": "Feature",
  "properties": {
    "iso:country":"ES",
    "sg:address":"Carrer de Berenguer Iii, 45",
    "sg:city":"Mollet Valles",
    "sg:orig_category":"Bisuter\u00cda, Joyer\u00cda, Relojer\u00cda (al Por Menor)",
    "sg:phone":"+34 935 79 43 43",
    "sg:postcode":"08100",
    "sg:province":"Barcelona",
    "wof:name":"Rodriguez Rodriguez Anna",
    "wof:placetype":"venue"
},
  "geometry": {"coordinates":[2.2153708935,41.5365257263],"type":"Point"}
}