{
  "type": "Feature",
  "properties": {
    "iso:country":"ES",
    "sg:address":"Carr Don Juan De Austria, 18",
    "sg:city":"Burjassot",
    "sg:orig_category":"Alimentaci\u00d3n General (al Por Menor)",
    "sg:phone":"+34 963 63 37 89",
    "sg:postcode":"46100",
    "sg:province":"Valencia",
    "wof:name":"Albarracin Tarazon Vicente",
    "wof:placetype":"venue"
},
  "geometry": {"coordinates":[-0.4193406105,39.51720047],"type":"Point"}
}