{
  "type": "Feature",
  "properties": {
    "addr:full":"Calle de San Pascual, 79 Yecla Murcia 30510",
    "addr:housenumber":"79",
    "addr:postcode":"30510",
    "addr:street":"Calle De San Pascual",
    "iso:country":"ES",
    "sg:address":"Calle de San Pascual, 79",
    "sg:city":"Yecla",
    "sg:orig_category":"Peluqueros: De Se\u00d1oras",
    "sg:phone":"+34 968 79 58 45",
    "sg:postcode":"30510",
    "sg:province":"Murcia",
    "wof:name":"Concha Martinez Peluqueros S.l.",
    "wof:placetype":"venue"
},
  "geometry": {"coordinates":[-1.110532999,38.6130256653],"type":"Point"}
}