{
  "type": "Feature",
  "properties": {
    "addr:full":"Calle de Santa Maria, S/n Palos Frontera Huelva 21810",
    "addr:housenumber":"/ n",
    "addr:postcode":"21810",
    "addr:street":"Calle De Santa;S;Palos Frontera",
    "iso:country":"ES",
    "sg:address":"Calle de Santa Maria, S/n",
    "sg:city":"Palos Frontera",
    "sg:orig_category":"Farmacias",
    "sg:phone":"+34 959 35 04 61",
    "sg:postcode":"21810",
    "sg:province":"Huelva",
    "wof:name":"Fragoso Rovira David",
    "wof:placetype":"venue"
},
  "geometry": {"coordinates":[-6.8948187828,37.2291717529],"type":"Point"}
}