{
  "type": "Feature",
  "properties": {
    "iso:country":"ES",
    "sg:address":"Av Marina Alta, S/n",
    "sg:city":"Ondara",
    "sg:orig_category":"Hormigonados",
    "sg:phone":"+34 965 76 73 44",
    "sg:postcode":"03760",
    "sg:province":"Alicante",
    "wof:name":"Vibroaspre S. A.",
    "wof:placetype":"venue"
},
  "geometry": {"coordinates":[0.0201750007,38.8261413574],"type":"Point"}
}