{
  "type": "Feature",
  "properties": {
    "addr:full":"Calle de Adan Y Eva, 6 Lebrija Sevilla 41740",
    "addr:housenumber":"6",
    "addr:postcode":"41740",
    "addr:street":"Calle De Adan Y Eva",
    "iso:country":"ES",
    "sg:address":"Calle de Adan Y Eva, 6",
    "sg:city":"Lebrija",
    "sg:orig_category":"Asociaciones, Organismos Culturales Y Socioeducativos",
    "sg:phone":"+34 955 97 15 02",
    "sg:postcode":"41740",
    "sg:province":"Sevilla",
    "wof:name":"Hermandad De Maria Santisima De Los Dolores E.t. Los Frailes",
    "wof:placetype":"venue"
},
  "geometry": {"coordinates":[-6.0805106163,36.9200744629],"type":"Point"}
}