{
  "type": "Feature",
  "properties": {
    "iso:country":"ES",
    "sg:address":"Avda Teodomiro, 3",
    "sg:city":"Orihuela",
    "sg:orig_category":"M\u00c9dicos: Neurolog\u00cda",
    "sg:phone":"+34 965 30 55 79",
    "sg:postcode":"03300",
    "sg:province":"Alicante",
    "wof:name":"Flores Ruiz Jose Jesus",
    "wof:placetype":"venue"
},
  "geometry": {"coordinates":[-0.944896996,38.0810928345],"type":"Point"}
}