{
  "type": "Feature",
  "properties": {
    "addr:full":"Urb Atalaya Park, S/n Atalaya-isdabe M\u00e1laga 29680",
    "addr:housenumber":"s / n",
    "addr:postcode":"29680",
    "addr:street":"Urb;Ma\u0301Laga",
    "iso:country":"ES",
    "sg:address":"Urb Atalaya Park, S/n",
    "sg:city":"Atalaya-isdabe",
    "sg:orig_category":"Ense\u00d1anza Variada",
    "sg:phone":"+34 952 88 62 34",
    "sg:postcode":"29680",
    "sg:province":"M\u00e1laga",
    "wof:name":"Paraula Asistencia Educativa S.l.",
    "wof:placetype":"venue"
},
  "geometry": {"coordinates":[-5.0172138214,36.4688491821],"type":"Point"}
}