{
  "type": "Feature",
  "properties": {
    "iso:country":"ES",
    "sg:address":"Calle de Alcala, 125",
    "sg:city":"Madrid",
    "sg:orig_category":"Empresarios",
    "sg:phone":"+34 914 35 87 72",
    "sg:postcode":"28009",
    "sg:province":"Madrid",
    "wof:name":"Tecteo Construcciones S. L.",
    "wof:placetype":"venue"
},
  "geometry": {"coordinates":[-3.6798620224,40.4231071472],"type":"Point"}
}