{
  "type": "Feature",
  "properties": {
    "addr:full":"Carrer de Querol, 9 S. Climent Llobregat Barcelona 08849",
    "addr:housenumber":"9",
    "addr:postcode":"08849",
    "addr:street":"Carrer De Querol",
    "iso:country":"ES",
    "sg:address":"Carrer de Querol, 9",
    "sg:city":"S. Climent Llobregat",
    "sg:orig_category":"Carnicer\u00cdas, Carnicer\u00cdas",
    "sg:phone":"+34 936 37 66 55",
    "sg:postcode":"08849",
    "sg:province":"Barcelona",
    "wof:name":"Saavedra Y Telesforo S.l.",
    "wof:placetype":"venue"
},
  "geometry": {"coordinates":[1.9951289892,41.3393325806],"type":"Point"}
}