{
  "type": "Feature",
  "properties": {
    "addr:full":"Carrer de Proven\u00c7a, 2 Montcada Centre Barcelona 08110",
    "addr:housenumber":"2",
    "addr:postcode":"08110",
    "addr:street":"Carrer De Provenc\u0327A",
    "iso:country":"ES",
    "sg:address":"Carrer de Proven\u00c7a, 2",
    "sg:city":"Montcada Centre",
    "sg:orig_category":"Artes Gr\u00c1ficas, Artes Pl\u00c1sticas (curso)",
    "sg:phone":"+34 935 64 27 24",
    "sg:postcode":"08110",
    "sg:province":"Barcelona",
    "sg:website":"www.lahoz-es.com",
    "wof:name":"Lahoz Int. Machinery Network S.l.",
    "wof:placetype":"venue"
},
  "geometry": {"coordinates":[2.1881089211,41.4801597595],"type":"Point"}
}