{
  "type": "Feature",
  "properties": {
    "iso:country":"ES",
    "sg:address":"Calle de Teresa De Aragon, 5",
    "sg:city":"Sotogrande",
    "sg:orig_category":"Inversiones",
    "sg:phone":"+34 956 79 53 06",
    "sg:postcode":"11310",
    "sg:province":"C\u00e1diz",
    "wof:name":"Any Inversiones S.l.",
    "wof:placetype":"venue"
},
  "geometry": {"coordinates":[-5.2997264862,36.285194397],"type":"Point"}
}