{
  "type": "Feature",
  "properties": {
    "iso:country":"ES",
    "sg:address":"Rua Pi Y Margall, 9",
    "sg:city":"Vigo",
    "sg:orig_category":"Asociaciones Y Clubs Deportivos",
    "sg:phone":"+34 986 22 10 27",
    "sg:postcode":"36202",
    "sg:province":"Pontevedra",
    "wof:name":"Carriloa-tutu C.b.",
    "wof:placetype":"venue"
},
  "geometry": {"coordinates":[-8.7287111282,42.235408783],"type":"Point"}
}