{
  "type": "Feature",
  "properties": {
    "iso:country":"ES",
    "sg:address":"Mercovasa, S/n",
    "sg:city":"Mercovasa",
    "sg:orig_category":"Frutas, Legumbres Frescas Y Tempranas (al Por Menor)",
    "sg:phone":"+34 961 47 24 68",
    "sg:postcode":"46540",
    "sg:province":"Valencia",
    "wof:name":"Jose Guerrero S. A.",
    "wof:placetype":"venue"
},
  "geometry": {"coordinates":[-0.3003390133,39.5875854492],"type":"Point"}
}