{
  "type": "Feature",
  "properties": {
    "addr:full":"Plaz Conde De Colombi, S/n Alcala Guadaira Sevilla 41500",
    "addr:housenumber":"s",
    "addr:postcode":"41500",
    "addr:street":"/ N",
    "iso:country":"ES",
    "sg:address":"Plaz Conde De Colombi, S/n",
    "sg:city":"Alcala Guadaira",
    "sg:orig_category":"M\u00c9dicos: An\u00c1lisis Cl\u00cdnicos",
    "sg:phone":"+34 955 62 17 77",
    "sg:postcode":"41500",
    "sg:province":"Sevilla",
    "wof:name":"Troncoso Lopez Pablo",
    "wof:placetype":"venue"
},
  "geometry": {"coordinates":[-5.8443441391,37.344871521],"type":"Point"}
}