{
  "type": "Feature",
  "properties": {
    "addr:full":"Calle de Torrene, 4 Algorta Vizcaya 48991",
    "addr:housenumber":"4",
    "addr:postcode":"48991",
    "addr:street":"Calle De Torrene",
    "iso:country":"ES",
    "sg:address":"Calle de Torrene, 4",
    "sg:city":"Algorta",
    "sg:orig_category":"Carnicer\u00cdas, Carnicer\u00cdas",
    "sg:phone":"+34 944 91 18 22",
    "sg:postcode":"48991",
    "sg:province":"Vizcaya",
    "wof:name":"Aguirre Zarate Javier",
    "wof:placetype":"venue"
},
  "geometry": {"coordinates":[-3.0110616684,43.3500862122],"type":"Point"}
}