{
  "type": "Feature",
  "properties": {
    "iso:country":"ES",
    "sg:address":"Calle de Higueras, 67",
    "sg:city":"Madrid",
    "sg:orig_category":"Molduras, Junquillos, Listones Y Molduras Perforadas",
    "sg:phone":"+34 914 64 33 43",
    "sg:postcode":"28047",
    "sg:province":"Madrid",
    "wof:name":"Sanchez Guijarro Pedro",
    "wof:placetype":"venue"
},
  "geometry": {"coordinates":[-3.7453289032,40.4024467468],"type":"Point"}
}