{
  "type": "Feature",
  "properties": {
    "addr:full":"Calle de Damaso Alonso, S/n Segovia Segovia 40006",
    "addr:housenumber":"s / n",
    "addr:postcode":"40006",
    "addr:street":"Calle De Damaso Alonso",
    "iso:country":"ES",
    "sg:address":"Calle de Damaso Alonso, S/n",
    "sg:city":"Segovia",
    "sg:orig_category":"Polideportivos",
    "sg:phone":"+34 921 44 34 10",
    "sg:postcode":"40006",
    "sg:province":"Segovia",
    "wof:name":"Ayuntamiento De Segovia",
    "wof:placetype":"venue"
},
  "geometry": {"coordinates":[-4.0969629288,40.9325523376],"type":"Point"}
}