{
  "type": "Feature",
  "properties": {
    "addr:full":"Carrer de Carreras I Candi, 49 Barcelona Barcelona 08028",
    "addr:housenumber":"49",
    "addr:postcode":"08028",
    "addr:street":"Carrer De Carreras I Candi",
    "iso:country":"ES",
    "sg:address":"Carrer de Carreras I Candi, 49",
    "sg:city":"Barcelona",
    "sg:orig_category":"Farmacias",
    "sg:phone":"+34 934 22 43 92",
    "sg:postcode":"08028",
    "sg:province":"Barcelona",
    "wof:name":"Guasch Badell Silvia",
    "wof:placetype":"venue"
},
  "geometry": {"coordinates":[2.1277348995,41.3733024597],"type":"Point"}
}