{
  "type": "Feature",
  "properties": {
    "iso:country":"ES",
    "sg:address":"Calle de Juan Loaisa, 4",
    "sg:city":"Plasencia",
    "sg:orig_category":"Compresores",
    "sg:phone":"+34 927 42 37 77",
    "sg:postcode":"10600",
    "sg:province":"C\u00e1ceres",
    "wof:name":"Excavaciones Y Desmontes Placentinos S.a.l.",
    "wof:placetype":"venue"
},
  "geometry": {"coordinates":[-6.0810689926,40.0378913879],"type":"Point"}
}