{
  "type": "Feature",
  "properties": {
    "addr:full":"Calle de Medinaceli, 2 Soria Soria 42003",
    "addr:housenumber":"2",
    "addr:postcode":"42003",
    "addr:street":"Calle De Medinaceli",
    "iso:country":"ES",
    "sg:address":"Calle de Medinaceli, 2",
    "sg:city":"Soria",
    "sg:orig_category":"Caf\u00c9s, Bares, Cervecer\u00cdas",
    "sg:phone":"+34 975 22 50 52",
    "sg:postcode":"42003",
    "sg:province":"Soria",
    "wof:name":"Gil Rodrigo Javier",
    "wof:placetype":"venue"
},
  "geometry": {"coordinates":[-2.4691479206,41.7636032104],"type":"Point"}
}