{
  "type": "Feature",
  "properties": {
    "iso:country":"ES",
    "sg:address":"Carrer de Periodista Grane, 216",
    "sg:city":"Terrassa",
    "sg:orig_category":"Molduras, Junquillos, Listones Y Molduras Perforadas",
    "sg:phone":"+34 937 86 25 60",
    "sg:postcode":"08226",
    "sg:province":"Barcelona",
    "wof:name":"Buj Robles Emilio Dario",
    "wof:placetype":"venue"
},
  "geometry": {"coordinates":[2.0287098885,41.5751533508],"type":"Point"}
}