{
  "type": "Feature",
  "properties": {
    "addr:full":"Eras De Zaratan, S/n Zaratan Valladolid 47610",
    "addr:housenumber":"s",
    "addr:postcode":"47610",
    "addr:street":"/ N",
    "iso:country":"ES",
    "sg:address":"Eras De Zaratan, S/n",
    "sg:city":"Zaratan",
    "sg:orig_category":"Fabricaci\u00d3n Y Comercio De M\u00c1quinas",
    "sg:phone":"+34 983 33 77 79",
    "sg:postcode":"47610",
    "sg:province":"Valladolid",
    "wof:name":"Gutierrez Del Rio Julio",
    "wof:placetype":"venue"
},
  "geometry": {"coordinates":[-4.7876491547,41.6588859558],"type":"Point"}
}