{
  "type": "Feature",
  "properties": {
    "iso:country":"ES",
    "sg:address":"Pase Ibaialde, 1",
    "sg:city":"Mutiloabeiti",
    "sg:orig_category":"Guarder\u00cdas",
    "sg:phone":"+34 948 23 15 93",
    "sg:postcode":"31192",
    "sg:province":"Navarra",
    "wof:name":"Ayuntamiento De Valle De Aranguren",
    "wof:placetype":"venue"
},
  "geometry": {"coordinates":[-1.6760691404,42.6953926086],"type":"Point"}
}