{
  "type": "Feature",
  "properties": {
    "addr:full":"Calle de Barraca (la), Km. 0002,2 Sesamo Le\u00f3n 24434",
    "addr:postcode":"24434",
    "addr:street":"Calle De Barraca La Km. 0002,2;Leo\u0301N",
    "iso:country":"ES",
    "sg:address":"Calle de Barraca (la), Km. 0002,2",
    "sg:city":"Sesamo",
    "sg:orig_category":"M\u00c1rmoles, Granitos Y Piedras Naturales",
    "sg:phone":"+34 987 56 89 35",
    "sg:postcode":"24434",
    "sg:province":"Le\u00f3n",
    "wof:name":"Granitos Del Cua Sl",
    "wof:placetype":"venue"
},
  "geometry": {"coordinates":[-6.6544532776,42.7409477234],"type":"Point"}
}