{
  "type": "Feature",
  "properties": {
    "iso:country":"ES",
    "sg:address":"Plaz Andalucia, S/n",
    "sg:city":"Sierra Nevada",
    "sg:orig_category":"Deportes Diversos",
    "sg:phone":"+34 958 48 11 06",
    "sg:postcode":"18196",
    "sg:province":"Granada",
    "wof:name":"Escuela De Esqui Solynieve S.l.",
    "wof:placetype":"venue"
},
  "geometry": {"coordinates":[-3.4015190601,37.0969848633],"type":"Point"}
}