{
  "type": "Feature",
  "properties": {
    "addr:full":"Calle de Gurutzegi, 12 Donostia-san Sebastian Guip\u00f9zcoa 20018",
    "addr:housenumber":"12",
    "addr:postcode":"20018",
    "addr:street":"Calle De Gurutzegi",
    "iso:country":"ES",
    "sg:address":"Calle de Gurutzegi, 12",
    "sg:city":"Donostia-san Sebastian",
    "sg:orig_category":"Arquitectos",
    "sg:phone":"+34 943 37 78 49",
    "sg:postcode":"20018",
    "sg:province":"Guip\u00f9zcoa",
    "wof:name":"Briones Alcalde Jose Luis",
    "wof:placetype":"venue"
},
  "geometry": {"coordinates":[-2.0029520988,43.2836837769],"type":"Point"}
}