{
  "type": "Feature",
  "properties": {
    "iso:country":"ES",
    "sg:address":"Carr Alemanya, 28",
    "sg:city":"Badalona",
    "sg:orig_category":"Hilaturas, Hilos Y Actividades Relacionadas",
    "sg:phone":"+34 934 65 16 16",
    "sg:postcode":"08917",
    "sg:province":"Barcelona",
    "wof:name":"Women Change S.l",
    "wof:placetype":"venue"
},
  "geometry": {"coordinates":[2.2217679024,41.4588241577],"type":"Point"}
}