{
  "type": "Feature",
  "properties": {
    "addr:full":"Calle de Antonio Trueba, 1 Basauri Vizcaya 48970",
    "addr:housenumber":"1",
    "addr:postcode":"48970",
    "addr:street":"Calle De Antonio Trueba",
    "iso:country":"ES",
    "sg:address":"Calle de Antonio Trueba, 1",
    "sg:city":"Basauri",
    "sg:orig_category":"Ropa Para Ni\u00d1os (al Por Menor)",
    "sg:phone":"+34 944 26 37 78",
    "sg:postcode":"48970",
    "sg:province":"Vizcaya",
    "wof:name":"Natalia Barrero Pascual",
    "wof:placetype":"venue"
},
  "geometry": {"coordinates":[-2.8836586475,43.2365646362],"type":"Point"}
}