{
  "type": "Feature",
  "properties": {
    "addr:full":"Alam Areilza Doctor, 60 Bilbao Vizcaya 48010",
    "addr:housenumber":"60",
    "addr:postcode":"48010",
    "addr:street":"Alam;Doctor",
    "iso:country":"ES",
    "sg:address":"Alam Areilza Doctor, 60",
    "sg:city":"Bilbao",
    "sg:orig_category":"Agencias De Viajes",
    "sg:phone":"+34 944 21 23 13",
    "sg:postcode":"48010",
    "sg:province":"Vizcaya",
    "sg:website":"www.viajesiberia.com",
    "wof:name":"Viajes Iberia S.a.",
    "wof:placetype":"venue"
},
  "geometry": {"coordinates":[-2.9438929558,43.258014679],"type":"Point"}
}