{
  "type": "Feature",
  "properties": {
    "addr:full":"Carrer de Minerva, 44 S. Andreu Llavaneres Barcelona 08392",
    "addr:housenumber":"44",
    "addr:postcode":"08392",
    "addr:street":"Carrer De Minerva;S. Andreu Llavaneres Barcelona",
    "iso:country":"ES",
    "sg:address":"Carrer de Minerva, 44",
    "sg:city":"S. Andreu Llavaneres",
    "sg:orig_category":"Sales (al Por Mayor)",
    "sg:phone":"+34 937 92 85 24",
    "sg:postcode":"08392",
    "sg:province":"Barcelona",
    "wof:name":"Eco Aliment S.l.",
    "wof:placetype":"venue"
},
  "geometry": {"coordinates":[2.4817700386,41.5696601868],"type":"Point"}
}