{
  "type": "Feature",
  "properties": {
    "iso:country":"ES",
    "sg:address":"Carrer de Avinyonet, S/n",
    "sg:city":"Vilafranca Penedes",
    "sg:orig_category":"Electricidad: Instaladores",
    "sg:phone":"+34 938 92 23 31",
    "sg:postcode":"08720",
    "sg:province":"Barcelona",
    "wof:name":"Lectro-90 S.a.",
    "wof:placetype":"venue"
},
  "geometry": {"coordinates":[1.7099200487,41.3498687744],"type":"Point"}
}