{
  "type": "Feature",
  "properties": {
    "addr:full":"Calle de Arias, 10 Zaragoza Zaragoza 50010",
    "addr:housenumber":"10",
    "addr:postcode":"50010",
    "addr:street":"Calle De Arias",
    "iso:country":"ES",
    "sg:address":"Calle de Arias, 10",
    "sg:city":"Zaragoza",
    "sg:orig_category":"Muebles Y Accesorios Para Cocinas Y Cuartos De Ba\u00d1o (al Por Menor)",
    "sg:phone":"+34 976 31 37 54",
    "sg:postcode":"50010",
    "sg:province":"Zaragoza",
    "wof:name":"Oroseta S.l.",
    "wof:placetype":"venue"
},
  "geometry": {"coordinates":[-0.9085780978,41.653049469],"type":"Point"}
}