{
  "type": "Feature",
  "properties": {
    "iso:country":"ES",
    "sg:address":"Calle de Hemingway, 13",
    "sg:city":"Malaga",
    "sg:orig_category":"Fabricaci\u00d3n De Capiteles",
    "sg:phone":"+34 952 24 03 29",
    "sg:postcode":"29004",
    "sg:province":"M\u00e1laga",
    "wof:name":"Carpas Integrales S.l.",
    "wof:placetype":"venue"
},
  "geometry": {"coordinates":[-4.4749679565,36.6880073547],"type":"Point"}
}