{
  "type": "Feature",
  "properties": {
    "addr:full":"Calle de Dunas (las), 1 Corralejo Playa Las Palmas 35660",
    "addr:housenumber":"1",
    "addr:postcode":"35660",
    "addr:street":"Calle De Dunas Las;Playa Las Palmas",
    "iso:country":"ES",
    "sg:address":"Calle de Dunas (las), 1",
    "sg:city":"Corralejo Playa",
    "sg:orig_category":"Imprenta",
    "sg:phone":"+34 928 53 53 62",
    "sg:postcode":"35660",
    "sg:province":"Las Palmas",
    "wof:name":"Imprenta Factory S.c.p.",
    "wof:placetype":"venue"
},
  "geometry": {"coordinates":[-15.4300060272,28.1248226166],"type":"Point"}
}