{
  "type": "Feature",
  "properties": {
    "iso:country":"ES",
    "sg:address":"Calle de Cervantes, 29",
    "sg:city":"Villaviciosa",
    "sg:orig_category":"Comercio De Piezas De Recambio Y De Accesorios De Veh\u00cdculos, Veh\u00cdculos Industriales",
    "sg:phone":"+34 985 89 12 08",
    "sg:postcode":"33300",
    "sg:province":"Asturias",
    "wof:name":"Villa Sanchez Jose Manuel",
    "wof:placetype":"venue"
},
  "geometry": {"coordinates":[-5.4331240654,43.481628418],"type":"Point"}
}