{
  "type": "Feature",
  "properties": {
    "addr:full":"Calle de Felipe Ii, S/n Talayuela C\u00e1ceres 10310",
    "addr:housenumber":"s / n",
    "addr:postcode":"10310",
    "addr:street":"Calle De Felipe Ii;Ca\u0301Ceres",
    "iso:country":"ES",
    "sg:address":"Calle de Felipe Ii, S/n",
    "sg:city":"Talayuela",
    "sg:orig_category":"Molduras, Junquillos, Listones Y Molduras Perforadas",
    "sg:phone":"+34 927 57 80 80",
    "sg:postcode":"10310",
    "sg:province":"C\u00e1ceres",
    "wof:name":"Salas Moreno Matias",
    "wof:placetype":"venue"
},
  "geometry": {"coordinates":[-5.6089839935,39.9857749939],"type":"Point"}
}