{
  "type": "Feature",
  "properties": {
    "addr:full":"Pla\u00c7 Mercat Vell, 1 Silla Valencia 46460",
    "addr:housenumber":"1",
    "addr:postcode":"46460",
    "addr:street":"Silla",
    "iso:country":"ES",
    "sg:address":"Pla\u00c7 Mercat Vell, 1",
    "sg:city":"Silla",
    "sg:orig_category":"Promotores Constructores",
    "sg:phone":"+34 961 21 34 04",
    "sg:postcode":"46460",
    "sg:province":"Valencia",
    "wof:name":"Toyen's Sociedad Cooperativa Valenciana",
    "wof:placetype":"venue"
},
  "geometry": {"coordinates":[-0.417858988,39.3685531616],"type":"Point"}
}