{
  "type": "Feature",
  "properties": {
    "addr:full":"Avda Manuel Colomer Marco, 14 Valencia Valencia 46017",
    "addr:housenumber":"14",
    "addr:postcode":"46017",
    "addr:street":"Avda Manuel Colomer Marco",
    "iso:country":"ES",
    "sg:address":"Avda Manuel Colomer Marco, 14",
    "sg:city":"Valencia",
    "sg:orig_category":"Comercio De Piezas De Recambio Y De Accesorios De Veh\u00cdculos, Veh\u00cdculos Industriales",
    "sg:phone":"+34 963 78 16 07",
    "sg:postcode":"46017",
    "sg:province":"Valencia",
    "wof:name":"Dava S.a.",
    "wof:placetype":"venue"
},
  "geometry": {"coordinates":[-0.3897329867,39.4390563965],"type":"Point"}
}