{
  "type": "Feature",
  "properties": {
    "addr:full":"Avda Europa, 14 Arriondas Asturias 33540",
    "addr:housenumber":"14",
    "addr:postcode":"33540",
    "addr:street":"Avda Europa",
    "iso:country":"ES",
    "sg:address":"Avda Europa, 14",
    "sg:city":"Arriondas",
    "sg:orig_category":"Restaurantes",
    "sg:phone":"+34 985 84 10 72",
    "sg:postcode":"33540",
    "sg:province":"Asturias",
    "wof:name":"Campo Viejo Jose Antonio",
    "wof:placetype":"venue"
},
  "geometry": {"coordinates":[-5.1821389198,43.3912849426],"type":"Point"}
}