{
  "type": "Feature",
  "properties": {
    "addr:full":"Carrer de Poetessa Remei Pico, 4 Monovar Alicante 03640",
    "addr:housenumber":"4",
    "addr:postcode":"03640",
    "addr:street":"Carrer De Poetessa Remei Pico;Alicante",
    "iso:country":"ES",
    "sg:address":"Carrer de Poetessa Remei Pico, 4",
    "sg:city":"Monovar",
    "sg:orig_category":"Confecci\u00d3n De Zapatos",
    "sg:phone":"+34 966 96 02 98",
    "sg:postcode":"03640",
    "sg:province":"Alicante",
    "wof:name":"Promociones Deltell S.l.",
    "wof:placetype":"venue"
},
  "geometry": {"coordinates":[-0.8421599865,38.4374656677],"type":"Point"}
}