{
  "type": "Feature",
  "properties": {
    "iso:country":"ES",
    "sg:address":"Calle de Sao Paulo, 2",
    "sg:city":"Palmas De Gran Canaria",
    "sg:orig_category":"Agencias De Aduana",
    "sg:phone":"+34 928 46 80 41",
    "sg:postcode":"35008",
    "sg:province":"Las Palmas",
    "wof:name":"Pedro Guerra Sanchez Agencia Guerra S.l.",
    "wof:placetype":"venue"
},
  "geometry": {"coordinates":[-15.4154691696,28.1576805115],"type":"Point"}
}