{
  "type": "Feature",
  "properties": {
    "addr:full":"Avda Val Mi\u00d1or, 14 Vilamean Pontevedra 36350",
    "addr:housenumber":"14",
    "addr:postcode":"36350",
    "addr:street":"Avda Val Min\u0303Or",
    "iso:country":"ES",
    "sg:address":"Avda Val Mi\u00d1or, 14",
    "sg:city":"Vilamean",
    "sg:orig_category":"Inmobiliaria (agencias)",
    "sg:phone":"+34 986 36 63 74",
    "sg:postcode":"36350",
    "sg:province":"Pontevedra",
    "wof:name":"As Estelas S.a.",
    "wof:placetype":"venue"
},
  "geometry": {"coordinates":[-8.8065166473,42.142791748],"type":"Point"}
}