{
  "type": "Feature",
  "properties": {
    "addr:full":"Calle de Roma, S/n Torrejon Ardoz Madrid 28850",
    "addr:housenumber":"/ n",
    "addr:postcode":"28850",
    "addr:street":"Calle De Roma S",
    "iso:country":"ES",
    "sg:address":"Calle de Roma, S/n",
    "sg:city":"Torrejon Ardoz",
    "sg:orig_category":"Molduras, Junquillos, Listones Y Molduras Perforadas",
    "sg:phone":"+34 916 56 16 02",
    "sg:postcode":"28850",
    "sg:province":"Madrid",
    "wof:name":"Lopez Barragan Julian",
    "wof:placetype":"venue"
},
  "geometry": {"coordinates":[-3.471419096,40.4587478638],"type":"Point"}
}