{
  "type": "Feature",
  "properties": {
    "iso:country":"ES",
    "sg:address":"Calle de Halcon, 49",
    "sg:city":"San Marcos",
    "sg:orig_category":"Ingeniero",
    "sg:phone":"+34 924 66 68 39",
    "sg:postcode":"06200",
    "sg:province":"Badajoz",
    "wof:name":"Mu\u00f1oz-reja Pizarro Blas",
    "wof:placetype":"venue"
},
  "geometry": {"coordinates":[-6.4495081902,38.7006645203],"type":"Point"}
}