{
  "type": "Feature",
  "properties": {
    "addr:full":"C/ Sant Daniel, 8 Cerdanyola Valles Barcelona 08290",
    "addr:housenumber":"8",
    "addr:postcode":"08290",
    "addr:street":"C / Sant Daniel;Valles Barcelona",
    "iso:country":"ES",
    "sg:address":"C/ Sant Daniel, 8",
    "sg:city":"Cerdanyola Valles",
    "sg:orig_category":"Peluquer\u00cdas, Peluquer\u00cda Mixta",
    "sg:phone":"+34 936 91 41 54",
    "sg:postcode":"08290",
    "sg:province":"Barcelona",
    "wof:name":"Teruel Carrillo Juan",
    "wof:placetype":"venue"
},
  "geometry": {"coordinates":[2.1363530159,41.4915924072],"type":"Point"}
}