{
  "type": "Feature",
  "properties": {
    "addr:full":"Ctra Sevilla, 267 Almendralejo Badajoz 06200",
    "addr:housenumber":"267",
    "addr:postcode":"06200",
    "addr:street":"Ctra Sevilla",
    "iso:country":"ES",
    "sg:address":"Ctra Sevilla, 267",
    "sg:city":"Almendralejo",
    "sg:orig_category":"Agentes, Concesionarios Y Sucursales De Veh\u00cdculos",
    "sg:phone":"+34 924 67 18 53",
    "sg:postcode":"06200",
    "sg:province":"Badajoz",
    "wof:name":"Nieto Torres Diego",
    "wof:placetype":"venue"
},
  "geometry": {"coordinates":[-6.3891019821,38.6721000671],"type":"Point"}
}