{
  "type": "Feature",
  "properties": {
    "iso:country":"ES",
    "sg:address":"Avda Rioja (la), 6",
    "sg:city":"Entrena",
    "sg:orig_category":"Iglesia Cat\u00d3lica",
    "sg:phone":"+34 941 44 61 77",
    "sg:postcode":"26375",
    "sg:province":"La Rioja",
    "wof:name":"Parroquia De San Martin",
    "wof:placetype":"venue"
},
  "geometry": {"coordinates":[-2.5298080444,42.3869056702],"type":"Point"}
}