{
  "type": "Feature",
  "properties": {
    "addr:full":"Ctra Segovia, Km. 0188,8 Cisterniga Valladolid 47193",
    "addr:postcode":"47193",
    "addr:street":"Ctra Segovia Km. 0188,8 Cisterniga",
    "iso:country":"ES",
    "sg:address":"Ctra Segovia, Km. 0188,8",
    "sg:city":"Cisterniga",
    "sg:orig_category":"Arenas, Guijarros Y Granulados",
    "sg:phone":"+34 983 40 10 68",
    "sg:postcode":"47193",
    "sg:province":"Valladolid",
    "wof:name":"Aridos Sanz S.l.",
    "wof:placetype":"venue"
},
  "geometry": {"coordinates":[-4.6660885811,41.5648117065],"type":"Point"}
}