{
  "type": "Feature",
  "properties": {
    "addr:full":"Ctra Antigua De Cebreros, Km. 0004,0 Avila \u00c1vila 05005",
    "addr:postcode":"05005",
    "addr:street":"Ctra Antigua De Cebreros Km. 0004,0;A\u0301Vila",
    "iso:country":"ES",
    "sg:address":"Ctra Antigua De Cebreros, Km. 0004,0",
    "sg:city":"Avila",
    "sg:orig_category":"Arenas, Guijarros Y Granulados",
    "sg:phone":"+34 920 35 21 13",
    "sg:postcode":"05005",
    "sg:province":"\u00c1vila",
    "sg:website":"www",
    "wof:name":"Canteras Cuadrado S.l.",
    "wof:placetype":"venue"
},
  "geometry": {"coordinates":[-4.7116389275,40.6626739502],"type":"Point"}
}