{
  "type": "Feature",
  "properties": {
    "iso:country":"ES",
    "sg:address":"Playa Del Saler, S/n",
    "sg:city":"El Saler",
    "sg:orig_category":"Polideportivos",
    "sg:phone":"+34 961 83 02 03",
    "sg:postcode":"46012",
    "sg:province":"Valencia",
    "wof:name":"Fundacion Deportiva Municipal De Valencia",
    "wof:placetype":"venue"
},
  "geometry": {"coordinates":[-0.3325085938,39.3827018738],"type":"Point"}
}