{
  "type": "Feature",
  "properties": {
    "iso:country":"ES",
    "sg:address":"Ctra Fonfria, 23",
    "sg:city":"Moralina",
    "sg:orig_category":"Telas Y Sedas (al Por Menor)",
    "sg:phone":"+34 980 61 60 55",
    "sg:postcode":"49253",
    "sg:province":"Zamora",
    "wof:name":"Bernabe Berrocal Manuel",
    "wof:placetype":"venue"
},
  "geometry": {"coordinates":[-6.1388988495,41.4915084839],"type":"Point"}
}