{
  "type": "Feature",
  "properties": {
    "addr:full":"Calle de Ferraz, 88 Madrid Madrid 28008",
    "addr:housenumber":"88",
    "addr:postcode":"madrid;28008",
    "addr:street":"Calle De Ferraz",
    "iso:country":"ES",
    "sg:address":"Calle de Ferraz, 88",
    "sg:city":"Madrid",
    "sg:orig_category":"M\u00c9dicos: Psiquiatr\u00cda",
    "sg:phone":"+34 915 43 64 86",
    "sg:postcode":"28008",
    "sg:province":"Madrid",
    "wof:name":"Diez Rubio Maria Concepcion",
    "wof:placetype":"venue"
},
  "geometry": {"coordinates":[-3.7211329937,40.4303245544],"type":"Point"}
}