{
  "type": "Feature",
  "properties": {
    "addr:full":"Calle de Maestro Joaquin Rodrigo, 16 Quartell Valencia 46510",
    "addr:housenumber":"16",
    "addr:postcode":"46510",
    "addr:street":"Calle De Maestro Joaquin Rodrigo",
    "iso:country":"ES",
    "sg:address":"Calle de Maestro Joaquin Rodrigo, 16",
    "sg:city":"Quartell",
    "sg:orig_category":"Servicios De Telecomunicaciones",
    "sg:phone":"+34 962 63 61 02",
    "sg:postcode":"46510",
    "sg:province":"Valencia",
    "wof:name":"Roca Daniel Vicente",
    "wof:placetype":"venue"
},
  "geometry": {"coordinates":[-0.2627829909,39.7385101318],"type":"Point"}
}