{
  "type": "Feature",
  "properties": {
    "addr:full":"Carrer de Sicilia, 298 Barcelona Barcelona 08013",
    "addr:housenumber":"298",
    "addr:postcode":"08013",
    "addr:street":"Carrer De Sicilia",
    "iso:country":"ES",
    "sg:address":"Carrer de Sicilia, 298",
    "sg:city":"Barcelona",
    "sg:orig_category":"Tatuajes",
    "sg:phone":"+34 932 07 07 67",
    "sg:postcode":"08013",
    "sg:province":"Barcelona",
    "wof:name":"De Gregorio Garcia Susana",
    "wof:placetype":"venue"
},
  "geometry": {"coordinates":[2.1734440327,41.4017677307],"type":"Point"}
}