{
  "type": "Feature",
  "properties": {
    "iso:country":"ES",
    "sg:address":"Valdelamaestra, 5",
    "sg:city":"Villares Reina",
    "sg:orig_category":"Aceites Y Grasas Industriales (fabricaci\u00d3n, Al Por Mayor)",
    "sg:phone":"+34 923 25 41 02",
    "sg:postcode":"37184",
    "sg:province":"Salamanca",
    "wof:name":"Eurocastilla De Recambios S.l.l.",
    "wof:placetype":"venue"
},
  "geometry": {"coordinates":[-5.6462268829,40.9935874939],"type":"Point"}
}