{
  "type": "Feature",
  "properties": {
    "addr:full":"Ctra Puerto, 22 Coru\u00d1a La Coru\u00f1a 15006",
    "addr:housenumber":"22",
    "addr:postcode":"15006",
    "addr:street":"Ctra Puerto;La Corun\u0303A",
    "iso:country":"ES",
    "sg:address":"Ctra Puerto, 22",
    "sg:city":"Coru\u00d1a",
    "sg:orig_category":"Distribuci\u00d3n De Petr\u00d3leo Y Derivados",
    "sg:phone":"+34 981 28 89 29",
    "sg:postcode":"15006",
    "sg:province":"La Coru\u00f1a",
    "wof:name":"Meirama-pati\u00f1o S.a.",
    "wof:placetype":"venue"
},
  "geometry": {"coordinates":[-8.3939676285,43.3573684692],"type":"Point"}
}