{
  "type": "Feature",
  "properties": {
    "iso:country":"ES",
    "sg:address":"Calle de Avellanas, 14",
    "sg:city":"Valencia",
    "sg:orig_category":"Abogados",
    "sg:phone":"+34 963 15 37 45",
    "sg:postcode":"46003",
    "sg:province":"Valencia",
    "sg:website":"www.bc-abogados.com",
    "wof:name":"Blanes Y Carrion Abogados C.b.",
    "wof:placetype":"venue"
},
  "geometry": {"coordinates":[-0.3741140068,39.4745903015],"type":"Point"}
}