{
  "type": "Feature",
  "properties": {
    "iso:country":"ES",
    "sg:address":"Calle de Bailen, 35",
    "sg:city":"Sevilla",
    "sg:orig_category":"Agencias Y Asesores De Publicidad",
    "sg:phone":"+34 954 22 29 57",
    "sg:postcode":"41001",
    "sg:province":"Sevilla",
    "wof:name":"Publicidad Subeybaja",
    "wof:placetype":"venue"
},
  "geometry": {"coordinates":[-5.9999446869,37.3919410706],"type":"Point"}
}