{
  "type": "Feature",
  "properties": {
    "addr:full":"Carr Barcelona, 93 Girona Girona 17003",
    "addr:housenumber":"93",
    "addr:postcode":"17003",
    "addr:street":"Carr Barcelona",
    "iso:country":"ES",
    "sg:address":"Carr Barcelona, 93",
    "sg:city":"Girona",
    "sg:orig_category":"Agencias De Modelos",
    "sg:phone":"+34 972 41 06 52",
    "sg:postcode":"17003",
    "sg:province":"Girona",
    "wof:name":"D.m.models S.c.",
    "wof:placetype":"venue"
},
  "geometry": {"coordinates":[2.8150770664,41.9715118408],"type":"Point"}
}