{
  "type": "Feature",
  "properties": {
    "addr:full":"Avda Andalucia (de), 2 Motril Granada 18600",
    "addr:postcode":"18600",
    "addr:street":"Avda Andalucia De",
    "iso:country":"ES",
    "sg:address":"Avda Andalucia (de), 2",
    "sg:city":"Motril",
    "sg:orig_category":"\u00d3ptica: Instrumentos (fabricaci\u00d3n)",
    "sg:phone":"+34 958 60 59 20",
    "sg:postcode":"18600",
    "sg:province":"Granada",
    "wof:name":"Milan Corral Jose",
    "wof:placetype":"venue"
},
  "geometry": {"coordinates":[-3.516865015,36.7447052002],"type":"Point"}
}