{
  "type": "Feature",
  "properties": {
    "addr:full":"Ctra Nazaret-oliva, S/n Piles Valencia 46712",
    "addr:housenumber":"s",
    "addr:postcode":"46712",
    "addr:street":"Ctra Nazaret-Oliva;/ N",
    "iso:country":"ES",
    "sg:address":"Ctra Nazaret-oliva, S/n",
    "sg:city":"Piles",
    "sg:orig_category":"Discotecas Y Salas De Baile",
    "sg:phone":"+34 962 83 11 40",
    "sg:postcode":"46712",
    "sg:province":"Valencia",
    "wof:name":"Disc Pampol's S.l.",
    "wof:placetype":"venue"
},
  "geometry": {"coordinates":[-0.1360210031,38.9410552979],"type":"Point"}
}