{
  "type": "Feature",
  "properties": {
    "iso:country":"ES",
    "sg:address":"Poli Escopar, S/n",
    "sg:city":"Peralta",
    "sg:orig_category":"Almacenes Frigor\u00cdficos",
    "sg:phone":"+34 948 71 33 16",
    "sg:postcode":"31350",
    "sg:province":"Navarra",
    "sg:website":"www.grupohaimi.com",
    "wof:name":"Haimi S.l.",
    "wof:placetype":"venue"
},
  "geometry": {"coordinates":[-1.8131040335,42.33385849],"type":"Point"}
}