{
  "type": "Feature",
  "properties": {
    "addr:full":"Ctra Arta, S/n Port D'alcudia Islas Baleares 07410",
    "addr:housenumber":"s / n",
    "addr:postcode":"07410",
    "addr:street":"Ctra Arta",
    "iso:country":"ES",
    "sg:address":"Ctra Arta, S/n",
    "sg:city":"Port D'alcudia",
    "sg:orig_category":"Oficinas De Cambio",
    "sg:phone":"+34 971 54 91 58",
    "sg:postcode":"07410",
    "sg:province":"Islas Baleares",
    "wof:name":"Company Campins Jaime",
    "wof:placetype":"venue"
},
  "geometry": {"coordinates":[3.120937109,39.8396034241],"type":"Point"}
}