{
  "type": "Feature",
  "properties": {
    "iso:country":"ES",
    "sg:address":"Isla, S/n",
    "sg:city":"Lorca",
    "sg:orig_category":"Frutas, Legumbres Frescas Y Tempranas (al Por Menor)",
    "sg:phone":"+34 968 46 15 08",
    "sg:postcode":"30800",
    "sg:province":"Murcia",
    "wof:name":"Vera Martinez Jesus",
    "wof:placetype":"venue"
},
  "geometry": {"coordinates":[-1.6905640364,37.680557251],"type":"Point"}
}