{
  "type": "Feature",
  "properties": {
    "addr:full":"Prje. Valdevalero, S/n S. Leonardo Yag\u00fce Soria 42140",
    "addr:housenumber":"s",
    "addr:postcode":"42140",
    "addr:street":"/ N S. Leonardo Yaguee",
    "iso:country":"ES",
    "sg:address":"Prje. Valdevalero, S/n",
    "sg:city":"S. Leonardo Yag\u00fce",
    "sg:orig_category":"Ebanister\u00cda",
    "sg:phone":"+34 975 37 60 48",
    "sg:postcode":"42140",
    "sg:province":"Soria",
    "wof:name":"Francisco G.perez Perez E Hijos C.b.",
    "wof:placetype":"venue"
},
  "geometry": {"coordinates":[-3.0625391006,41.8294868469],"type":"Point"}
}