{
  "type": "Feature",
  "properties": {
    "iso:country":"ES",
    "sg:address":"Gazanda Bidea, 4",
    "sg:city":"Mungia",
    "sg:orig_category":"Maquinaria Para Industrias Diversas",
    "sg:phone":"+34 946 15 63 09",
    "sg:postcode":"48100",
    "sg:province":"Vizcaya",
    "wof:name":"Arlan Enkofratuak S.l.",
    "wof:placetype":"venue"
},
  "geometry": {"coordinates":[-2.8251338005,43.3509635925],"type":"Point"}
}