{
  "type": "Feature",
  "properties": {
    "iso:country":"ES",
    "sg:address":"Calle de Alcalde Gines Belda, 7",
    "sg:city":"Fortuna",
    "sg:orig_category":"Empresas De Carpinter\u00cda De Madera",
    "sg:phone":"+34 968 68 52 34",
    "sg:postcode":"30620",
    "sg:province":"Murcia",
    "wof:name":"Alacid Perez Jose Luis",
    "wof:placetype":"venue"
},
  "geometry": {"coordinates":[-1.1544963121,38.2054405212],"type":"Point"}
}