{
  "type": "Feature",
  "properties": {
    "iso:country":"ES",
    "sg:address":"Calle de Idiakez, 13",
    "sg:city":"Donostia-san Sebastian",
    "sg:orig_category":"Procuradores",
    "sg:phone":"+34 943 42 70 12",
    "sg:postcode":"20004",
    "sg:province":"Guip\u00f9zcoa",
    "wof:name":"Juan Jose Gonzalez Belmonte (procurador)",
    "wof:placetype":"venue"
},
  "geometry": {"coordinates":[-1.9808709621,43.3201713562],"type":"Point"}
}