{
  "type": "Feature",
  "properties": {
    "addr:full":"Calle de Conde Pestagua, 3 Castellon Castell\u00f3n 12004",
    "addr:housenumber":"3",
    "addr:postcode":"12004",
    "addr:street":"Calle De Conde Pestagua;Castello\u0301N",
    "iso:country":"ES",
    "sg:address":"Calle de Conde Pestagua, 3",
    "sg:city":"Castellon",
    "sg:orig_category":"Deportes Y Ocio: Art\u00cdculos Y Ropas (al Por Menor Y Accesorios)",
    "sg:phone":"+34 964 22 01 24",
    "sg:postcode":"12004",
    "sg:province":"Castell\u00f3n",
    "wof:name":"Cicles A.b.castello S.l.l.",
    "wof:placetype":"venue"
},
  "geometry": {"coordinates":[-0.0257600006,40.0253791809],"type":"Point"}
}