{
  "type": "Feature",
  "properties": {
    "addr:full":"Carr Isaac Peral, 2 Badalona Barcelona 08912",
    "addr:housenumber":"2",
    "addr:postcode":"08912",
    "addr:street":"Carr Isaac Peral",
    "iso:country":"ES",
    "sg:address":"Carr Isaac Peral, 2",
    "sg:city":"Badalona",
    "sg:orig_category":"Mec\u00c1nico Del Autom\u00d3vil",
    "sg:phone":"+34 933 87 18 25",
    "sg:postcode":"08912",
    "sg:province":"Barcelona",
    "wof:name":"Ballestero Automecanica",
    "wof:placetype":"venue"
},
  "geometry": {"coordinates":[2.2352828979,41.442779541],"type":"Point"}
}