{
  "type": "Feature",
  "properties": {
    "addr:full":"Calle de Alcala, 388 Madrid Madrid 28027",
    "addr:housenumber":"388",
    "addr:postcode":"28027",
    "addr:street":"Calle De Alcala",
    "iso:country":"ES",
    "sg:address":"Calle de Alcala, 388",
    "sg:city":"Madrid",
    "sg:orig_category":"\u00d3ptica: Instrumentos (fabricaci\u00d3n)",
    "sg:phone":"+34 914 06 15 25",
    "sg:postcode":"28027",
    "sg:province":"Madrid",
    "wof:name":"Optica Roma S.l.",
    "wof:placetype":"venue"
},
  "geometry": {"coordinates":[-3.6411590576,40.4364471436],"type":"Point"}
}