{
  "type": "Feature",
  "properties": {
    "addr:full":"Pase Justicia (del), 14 Fuentes Ebro Zaragoza 50740",
    "addr:housenumber":"14",
    "addr:postcode":"50740",
    "addr:street":"Justicia Del",
    "iso:country":"ES",
    "sg:address":"Pase Justicia (del), 14",
    "sg:city":"Fuentes Ebro",
    "sg:orig_category":"Frutas Y Legumbres Frescas (al Por Mayor)",
    "sg:phone":"+34 976 16 13 28",
    "sg:postcode":"50740",
    "sg:province":"Zaragoza",
    "wof:name":"Sat 45 Ara Prodebro",
    "wof:placetype":"venue"
},
  "geometry": {"coordinates":[-0.6268740296,41.5112380981],"type":"Point"}
}