{
  "type": "Feature",
  "properties": {
    "iso:country":"ES",
    "sg:address":"Calle de Galicia, 39",
    "sg:city":"Corralejo",
    "sg:orig_category":"Ebanister\u00cda",
    "sg:phone":"+34 928 86 75 95",
    "sg:postcode":"35660",
    "sg:province":"Las Palmas",
    "wof:name":"Alonso Perdomo Deogracias",
    "wof:placetype":"venue"
},
  "geometry": {"coordinates":[-13.8694543839,28.7310504913],"type":"Point"}
}