{
  "type": "Feature",
  "properties": {
    "addr:full":"Calle de Fernandez De Isla, 7 Santander Cantabria 39008",
    "addr:housenumber":"7",
    "addr:postcode":"39008",
    "addr:street":"Calle De Fernandez De Isla",
    "iso:country":"ES",
    "sg:address":"Calle de Fernandez De Isla, 7",
    "sg:city":"Santander",
    "sg:orig_category":"Arquitectos",
    "sg:phone":"+34 942 21 14 55",
    "sg:postcode":"39008",
    "sg:province":"Cantabria",
    "wof:name":"Cfl Arquitectos S.c.",
    "wof:placetype":"venue"
},
  "geometry": {"coordinates":[-3.8126370907,43.4611167908],"type":"Point"}
}