{
  "type": "Feature",
  "properties": {
    "addr:full":"Ptda Almarra-alfas, 191 Castalla Alicante 03420",
    "addr:housenumber":"191",
    "addr:postcode":"03420",
    "addr:street":"Ptda Almarra-Alfas",
    "iso:country":"ES",
    "sg:address":"Ptda Almarra-alfas, 191",
    "sg:city":"Castalla",
    "sg:orig_category":"Flores Y Plantas Naturales (al Por Mayor)",
    "sg:phone":"+34 965 52 95 01",
    "sg:postcode":"03420",
    "sg:province":"Alicante",
    "wof:name":"Elig-flor Castalla S.l.",
    "wof:placetype":"venue"
},
  "geometry": {"coordinates":[-0.6697350144,38.5959472656],"type":"Point"}
}