{
  "type": "Feature",
  "properties": {
    "iso:country":"ES",
    "sg:address":"Plaz Espa\u00d1a, S/n",
    "sg:city":"Malpartida De La Serena",
    "sg:orig_category":"Administraciones Regionales, Departamentales Y Locales",
    "sg:phone":"+34 924 77 67 51",
    "sg:postcode":"06440",
    "sg:province":"Badajoz",
    "wof:name":"Ayuntamiento De Malpartida De La Serena",
    "wof:placetype":"venue"
},
  "geometry": {"coordinates":[-5.6352801323,38.6745948792],"type":"Point"}
}