{
  "type": "Feature",
  "properties": {
    "iso:country":"ES",
    "sg:address":"Calle de Juan De Labrit, 1",
    "sg:city":"Peralta",
    "sg:orig_category":"Molduras, Junquillos, Listones Y Molduras Perforadas",
    "sg:phone":"+34 948 75 30 08",
    "sg:postcode":"31350",
    "sg:province":"Navarra",
    "wof:name":"Ezpeleta Tapiz Jose Maria",
    "wof:placetype":"venue"
},
  "geometry": {"coordinates":[-1.7989230156,42.338180542],"type":"Point"}
}