{
  "type": "Feature",
  "properties": {
    "addr:full":"Calle de Cobre, 16 Hueros Madrid 28810",
    "addr:housenumber":"16",
    "addr:postcode":"28810",
    "addr:street":"Calle De Cobre",
    "iso:country":"ES",
    "sg:address":"Calle de Cobre, 16",
    "sg:city":"Hueros",
    "sg:orig_category":"Trabajos De Soldaduras",
    "sg:phone":"+34 918 79 36 88",
    "sg:postcode":"28810",
    "sg:province":"Madrid",
    "wof:name":"Soldaduras Solis S.l.l.",
    "wof:placetype":"venue"
},
  "geometry": {"coordinates":[-3.3547339439,40.4387893677],"type":"Point"}
}