{
  "type": "Feature",
  "properties": {
    "addr:full":"Carrer de Bassegoda, 19 Barcelona Barcelona 08028",
    "addr:housenumber":"19",
    "addr:postcode":"08028",
    "addr:street":"Carrer De Bassegoda",
    "iso:country":"ES",
    "sg:address":"Carrer de Bassegoda, 19",
    "sg:city":"Barcelona",
    "sg:orig_category":"Aceites Y Grasas Alimentarias (fabricaci\u00d3n, Al Por Mayor)",
    "sg:phone":"+34 934 40 09 29",
    "sg:postcode":"08028",
    "sg:province":"Barcelona",
    "wof:name":"Vilalta Comaposada Luisa",
    "wof:placetype":"venue"
},
  "geometry": {"coordinates":[2.1258490086,41.3750305176],"type":"Point"}
}