{
  "type": "Feature",
  "properties": {
    "addr:full":"Carrer de Magdalena, 1 Galatzo Islas Baleares 07180",
    "addr:housenumber":"1",
    "addr:postcode":"07180",
    "addr:street":"Carrer De Magdalena;Islas",
    "iso:country":"ES",
    "sg:address":"Carrer de Magdalena, 1",
    "sg:city":"Galatzo",
    "sg:orig_category":"Promotores Constructores",
    "sg:phone":"+34 971 69 95 71",
    "sg:postcode":"07180",
    "sg:province":"Islas Baleares",
    "wof:name":"Baltyc Obras Y Servivcios S.a.",
    "wof:placetype":"venue"
},
  "geometry": {"coordinates":[2.5077250004,39.5292053223],"type":"Point"}
}