{
  "type": "Feature",
  "properties": {
    "iso:country":"ES",
    "sg:address":"Calle de Puerto De Los Leones, 1",
    "sg:city":"Majadahonda",
    "sg:orig_category":"Centros Empresariales",
    "sg:phone":"+34 916 34 12 45",
    "sg:postcode":"28220",
    "sg:province":"Madrid",
    "wof:name":"Amsen Advisors S.l.",
    "wof:placetype":"venue"
},
  "geometry": {"coordinates":[-3.8776838779,40.4764480591],"type":"Point"}
}