{
  "type": "Feature",
  "properties": {
    "iso:country":"ES",
    "sg:address":"Carrer de L'avenir, 67",
    "sg:city":"Barcelona",
    "sg:orig_category":"Inmobiliaria (agencias)",
    "sg:phone":"+34 932 00 68 28",
    "sg:postcode":"08021",
    "sg:province":"Barcelona",
    "wof:name":"Avenir 71 S.l.",
    "wof:placetype":"venue"
},
  "geometry": {"coordinates":[2.1443123817,41.3943405151],"type":"Point"}
}