{
  "type": "Feature",
  "properties": {
    "addr:full":"Calle de Ubeda, 21 Mairena Alcor Sevilla 41510",
    "addr:housenumber":"21",
    "addr:postcode":"41510",
    "addr:street":"Calle De Ubeda",
    "iso:country":"ES",
    "sg:address":"Calle de Ubeda, 21",
    "sg:city":"Mairena Alcor",
    "sg:orig_category":"Transportes Por V\u00cdas Navegables",
    "sg:phone":"+34 955 74 42 81",
    "sg:postcode":"41510",
    "sg:province":"Sevilla",
    "wof:name":"Brito Macias Gumersindo",
    "wof:placetype":"venue"
},
  "geometry": {"coordinates":[-5.7441082001,37.3790359497],"type":"Point"}
}