{
  "type": "Feature",
  "properties": {
    "addr:full":"Calle de Lope De Rueda, 3 Madrid Madrid 28009",
    "addr:housenumber":"3",
    "addr:postcode":"28009",
    "addr:street":"Calle De Lope De Rueda",
    "iso:country":"ES",
    "sg:address":"Calle de Lope De Rueda, 3",
    "sg:city":"Madrid",
    "sg:orig_category":"Farmacias",
    "sg:phone":"+34 914 35 24 07",
    "sg:postcode":"28009",
    "sg:province":"Madrid",
    "wof:name":"Montero Sanchez Maria Del Carmen",
    "wof:placetype":"venue"
},
  "geometry": {"coordinates":[-3.6771581173,40.4236297607],"type":"Point"}
}