{
  "type": "Feature",
  "properties": {
    "iso:country":"ES",
    "sg:address":"Calle de Pozo, 7",
    "sg:city":"Le\u00f3n",
    "sg:orig_category":"Empresarios",
    "sg:phone":"+34 987 26 03 25",
    "sg:postcode":"24003",
    "sg:province":"Le\u00f3n",
    "sg:website":"www.paginasamarillas.es",
    "wof:name":"Instalaciones Reparaciones Y Conservacion Grupo Decolux S.l.",
    "wof:placetype":"venue"
},
  "geometry": {"coordinates":[-5.5679402351,42.5974731445],"type":"Point"}
}