{
  "type": "Feature",
  "properties": {
    "addr:full":"Calle de Vega La, 26 Mieres Asturias 33600",
    "addr:housenumber":"26",
    "addr:postcode":"33600",
    "addr:street":"Calle De Vega La",
    "iso:country":"ES",
    "sg:address":"Calle de Vega La, 26",
    "sg:city":"Mieres",
    "sg:orig_category":"Farmacias",
    "sg:phone":"+34 985 46 63 89",
    "sg:postcode":"33600",
    "sg:province":"Asturias",
    "wof:name":"Dosil Caama\u00f1o Juana",
    "wof:placetype":"venue"
},
  "geometry": {"coordinates":[-5.7735638618,43.2481613159],"type":"Point"}
}