{
  "type": "Feature",
  "properties": {
    "iso:country":"ES",
    "sg:address":"Calle de Viera Y Clavijo, 48",
    "sg:city":"Palmas De Gran Canaria",
    "sg:orig_category":"Funcionario",
    "sg:phone":"+34 928 37 03 68",
    "sg:postcode":"35002",
    "sg:province":"Las Palmas",
    "wof:name":"Colegio Territorial De Administradores De Fincas De Las Palmas",
    "wof:placetype":"venue"
},
  "geometry": {"coordinates":[-15.4187555313,28.1081047058],"type":"Point"}
}