{
  "type": "Feature",
  "properties": {
    "addr:full":"Bda. Las Paredillas, 17 Alhaurin Torre M\u00e1laga 29130",
    "addr:housenumber":"17",
    "addr:postcode":"29130",
    "addr:street":"Paredillas",
    "iso:country":"ES",
    "sg:address":"Bda. Las Paredillas, 17",
    "sg:city":"Alhaurin Torre",
    "sg:orig_category":"Fabricaci\u00d3n, Reparaci\u00d3n Y Mantenimiento De Construcciones Navales Y Fluviales",
    "sg:phone":"+34 952 17 30 76",
    "sg:postcode":"29130",
    "sg:province":"M\u00e1laga",
    "wof:name":"Marina Benalnautic S.l.",
    "wof:placetype":"venue"
},
  "geometry": {"coordinates":[-4.5667190552,36.6618614197],"type":"Point"}
}