{
  "type": "Feature",
  "properties": {
    "addr:full":"Barr Trebuesto, 3 Trebuesto Cantabria 39788",
    "addr:housenumber":"3",
    "addr:postcode":"39788",
    "addr:street":"Trebuesto",
    "iso:country":"ES",
    "sg:address":"Barr Trebuesto, 3",
    "sg:city":"Trebuesto",
    "sg:orig_category":"Molduras, Junquillos, Listones Y Molduras Perforadas",
    "sg:phone":"+34 942 85 03 45",
    "sg:postcode":"39788",
    "sg:province":"Cantabria",
    "wof:name":"Ruiz Llama Jose",
    "wof:placetype":"venue"
},
  "geometry": {"coordinates":[-3.3257288933,43.3466300964],"type":"Point"}
}