{
  "type": "Feature",
  "properties": {
    "addr:full":"Av Diagonal, 644 Barcelona Barcelona 08017",
    "addr:housenumber":"644",
    "addr:postcode":"08017",
    "addr:street":"Av Diagonal",
    "iso:country":"ES",
    "sg:address":"Av Diagonal, 644",
    "sg:city":"Barcelona",
    "sg:orig_category":"Promotores Constructores",
    "sg:phone":"+34 932 89 09 67",
    "sg:postcode":"08017",
    "sg:province":"Barcelona",
    "wof:name":"Armacentro S.a.",
    "wof:placetype":"venue"
},
  "geometry": {"coordinates":[2.1347792149,41.3906173706],"type":"Point"}
}