{
  "type": "Feature",
  "properties": {
    "iso:country":"ES",
    "sg:address":"Calle de Julio Valdelomar, 11",
    "sg:city":"Cordoba",
    "sg:orig_category":"Bisuteros (fabricaci\u00d3n, Al Por Mayor)",
    "sg:phone":"+34 957 43 53 55",
    "sg:postcode":"14002",
    "sg:province":"C\u00f3rdoba",
    "wof:name":"Manuel Alvarez Damian Y Otros Cdad",
    "wof:placetype":"venue"
},
  "geometry": {"coordinates":[-4.7671308517,37.886264801],"type":"Point"}
}