{
  "type": "Feature",
  "properties": {
    "iso:country":"ES",
    "sg:address":"Avda Cayetano Roldan, S/n",
    "sg:city":"S. Fernando",
    "sg:orig_category":"Ense\u00d1anza Secundaria: Colegios Y Escuelas Privadas",
    "sg:phone":"+34 956 80 06 73",
    "sg:postcode":"11100",
    "sg:province":"C\u00e1diz",
    "wof:name":"Junta De Andalucia",
    "wof:placetype":"venue"
},
  "geometry": {"coordinates":[-6.2009887695,36.4710388184],"type":"Point"}
}