{
  "type": "Feature",
  "properties": {
    "addr:full":"Carrer de Francisco Tomas Y Valiente, 11 Viladecans Barcelona 08840",
    "addr:housenumber":"11",
    "addr:postcode":"08840",
    "addr:street":"Carrer De Francisco Tomas Y Valiente",
    "iso:country":"ES",
    "sg:address":"Carrer de Francisco Tomas Y Valiente, 11",
    "sg:city":"Viladecans",
    "sg:orig_category":"Autob\u00das (explotaci\u00d3n Y Servicios De)",
    "sg:phone":"+34 936 37 12 08",
    "sg:postcode":"08840",
    "sg:province":"Barcelona",
    "wof:name":"Capitan Leiva Joaquin",
    "wof:placetype":"venue"
},
  "geometry": {"coordinates":[2.0004620552,41.3136634827],"type":"Point"}
}