{
  "type": "Feature",
  "properties": {
    "iso:country":"ES",
    "sg:address":"Carrer de Varsovia, 152",
    "sg:city":"Barcelona",
    "sg:orig_category":"Muebles Y Accesorios Para Cocinas Y Cuartos De Ba\u00d1o (al Por Menor)",
    "sg:phone":"+34 933 47 05 15",
    "sg:postcode":"08041",
    "sg:province":"Barcelona",
    "wof:name":"Ruiz Gonzalez Raquel",
    "wof:placetype":"venue"
},
  "geometry": {"coordinates":[2.1723361015,41.4181175232],"type":"Point"}
}