{
  "type": "Feature",
  "properties": {
    "iso:country":"ES",
    "sg:address":"Psaj Ventura Feliu, 11",
    "sg:city":"Valencia",
    "sg:orig_category":"M\u00c9dicos: Cirug\u00cda Urol\u00d3gica",
    "sg:phone":"+34 963 41 96 90",
    "sg:postcode":"46007",
    "sg:province":"Valencia",
    "wof:name":"Chuan Nuez Pascual",
    "wof:placetype":"venue"
},
  "geometry": {"coordinates":[-0.3835540116,39.4622268677],"type":"Point"}
}