{
  "type": "Feature",
  "properties": {
    "iso:country":"ES",
    "sg:address":"Nueva, 35",
    "sg:city":"Valentin",
    "sg:classifiers":[
        {
            "category":"Taxi",
            "type":"Transportation"
        }
    ],
    "sg:phone":"+34 968 72 07 58",
    "sg:postcode":"30420",
    "sg:province":"Murcia",
    "wof:name":"Marin Marin Jose",
    "wof:placetype":"venue"
},
  "geometry": {"coordinates":[-1.6999490261,38.2315101624],"type":"Point"}
}