{
  "type": "Feature",
  "properties": {
    "addr:full":"Avda Blasco Iba\u00d1ez, 62 Hondon De Los Frailes Alicante 03689",
    "addr:housenumber":"62",
    "addr:postcode":"03689",
    "addr:street":"Avda Blasco Iban\u0303Ez",
    "iso:country":"ES",
    "sg:address":"Avda Blasco Iba\u00d1ez, 62",
    "sg:city":"Hondon De Los Frailes",
    "sg:orig_category":"Bazares, Art\u00cdculos De Limpieza Y De Cocina (al Por Menor)",
    "sg:phone":"+34 965 48 20 19",
    "sg:postcode":"03689",
    "sg:province":"Alicante",
    "wof:name":"Prieto Navarro Ezequiel",
    "wof:placetype":"venue"
},
  "geometry": {"coordinates":[-0.9297829866,38.2735862732],"type":"Point"}
}