{
  "type": "Feature",
  "properties": {
    "addr:full":"Pl. Palomas, S/n Guadix Granada 18500",
    "addr:postcode":"18500",
    "addr:street":"Palomas S / N",
    "iso:country":"ES",
    "sg:address":"Pl. Palomas, S/n",
    "sg:city":"Guadix",
    "sg:orig_category":"Loter\u00cda Y T\u00d3mbola",
    "sg:phone":"+34 958 66 49 35",
    "sg:postcode":"18500",
    "sg:province":"Granada",
    "wof:name":"Regalado Ubeda Javier Vicente",
    "wof:placetype":"venue"
},
  "geometry": {"coordinates":[-3.1343688965,37.303894043],"type":"Point"}
}