{
  "type": "Feature",
  "properties": {
    "iso:country":"ES",
    "sg:address":"Carrer de Nou Pins, 62",
    "sg:city":"Barcelona",
    "sg:orig_category":"Reposter\u00cdas",
    "sg:phone":"+34 932 76 40 66",
    "sg:postcode":"08016",
    "sg:province":"Barcelona",
    "wof:name":"Barna Pa",
    "wof:placetype":"venue"
},
  "geometry": {"coordinates":[2.1827769279,41.4436264038],"type":"Point"}
}