{
  "type": "Feature",
  "properties": {
    "iso:country":"ES",
    "sg:address":"Calle de Cronista Sepulveda, 26",
    "sg:city":"Pozoblanco",
    "sg:orig_category":"Barbacoas Y Accesorios",
    "sg:phone":"+34 957 13 15 63",
    "sg:postcode":"14400",
    "sg:province":"C\u00f3rdoba",
    "wof:name":"Serrano Moreno Isidoro",
    "wof:placetype":"venue"
},
  "geometry": {"coordinates":[-4.847014904,38.377040863],"type":"Point"}
}