{
  "type": "Feature",
  "properties": {
    "addr:full":"Calle de Escritor Secundino Delgado, 48 Mesas Las Palmas 35018",
    "addr:housenumber":"48",
    "addr:postcode":"35018",
    "addr:street":"Calle De Escritor Secundino Delgado",
    "iso:country":"ES",
    "sg:address":"Calle de Escritor Secundino Delgado, 48",
    "sg:city":"Mesas",
    "sg:orig_category":"Farmacias",
    "sg:phone":"+34 928 67 48 18",
    "sg:postcode":"35018",
    "sg:province":"Las Palmas",
    "wof:name":"Guerra Rivero Manuel",
    "wof:placetype":"venue"
},
  "geometry": {"coordinates":[-15.495798111,28.1026935577],"type":"Point"}
}