{
  "type": "Feature",
  "properties": {
    "addr:full":"Calle de Andra Mari Kalea, 3 Durango Vizcaya 48200",
    "addr:housenumber":"3",
    "addr:postcode":"48200",
    "addr:street":"Calle De Andra Mari Kalea",
    "iso:country":"ES",
    "sg:address":"Calle de Andra Mari Kalea, 3",
    "sg:city":"Durango",
    "sg:orig_category":"M\u00c9dicos: Oftalmolog\u00cda",
    "sg:phone":"+34 946 81 53 04",
    "sg:postcode":"48200",
    "sg:province":"Vizcaya",
    "wof:name":"Mercedes Lasso Manzano",
    "wof:placetype":"venue"
},
  "geometry": {"coordinates":[-2.6317131519,43.1681556702],"type":"Point"}
}