{
  "type": "Feature",
  "properties": {
    "iso:country":"ES",
    "sg:address":"Pla\u00c7 Firal, 17",
    "sg:city":"Santa Coloma De Farners",
    "sg:orig_category":"Sociedades, Compa\u00d1\u00cdas Aseguradoras",
    "sg:phone":"+34 972 84 17 15",
    "sg:postcode":"17430",
    "sg:province":"Girona",
    "wof:name":"Mapfre Servicios De Informatica",
    "wof:placetype":"venue"
},
  "geometry": {"coordinates":[2.6665511131,41.8617858887],"type":"Point"}
}