{
  "type": "Feature",
  "properties": {
    "addr:full":"Calle de Ortiz Ota\u00d1ez, 19 Santo\u00f1a Cantabria 39740",
    "addr:housenumber":"19",
    "addr:postcode":"39740",
    "addr:street":"Calle De Ortiz Otan\u0303Ez",
    "iso:country":"ES",
    "sg:address":"Calle de Ortiz Ota\u00d1ez, 19",
    "sg:city":"Santo\u00f1a",
    "sg:orig_category":"Laboratorios Y Trabajos De Fotograf\u00cda, V\u00cddeo Y Cine",
    "sg:phone":"+34 942 67 12 94",
    "sg:postcode":"39740",
    "sg:province":"Cantabria",
    "wof:name":"Fonfria Lavin Jose Maria",
    "wof:placetype":"venue"
},
  "geometry": {"coordinates":[-3.4589340687,43.4439659119],"type":"Point"}
}