{
  "type": "Feature",
  "properties": {
    "iso:country":"ES",
    "sg:address":"Calle de Lomo (el), 2",
    "sg:city":"Moraleja Enmedio",
    "sg:orig_category":"Goma: Productos De Uso Industrial (fabricaci\u00d3n, Al Por Mayor)",
    "sg:phone":"+34 916 09 40 72",
    "sg:postcode":"28950",
    "sg:province":"Madrid",
    "wof:name":"Juntiberia Elastomeros",
    "wof:placetype":"venue"
},
  "geometry": {"coordinates":[-3.850769043,40.2618942261],"type":"Point"}
}