{
  "type": "Feature",
  "properties": {
    "iso:country":"ES",
    "sg:address":"Casa, 18",
    "sg:city":"Ve\u00efnat Hortsavinya",
    "sg:orig_category":"Cerrajer\u00cda, Ferrallista",
    "sg:phone":"+34 937 64 17 73",
    "sg:postcode":"08490",
    "sg:province":"Barcelona",
    "wof:name":"Casellas Pla Jaime",
    "wof:placetype":"venue"
},
  "geometry": {"coordinates":[2.7045679092,41.705078125],"type":"Point"}
}