{
  "type": "Feature",
  "properties": {
    "addr:full":"Calle de Apuron, 1 Santa Cruz Palma Santa Cruz De Tenerife 38700",
    "addr:housenumber":"1",
    "addr:postcode":"38700",
    "addr:street":"Calle De Apuron",
    "iso:country":"ES",
    "sg:address":"Calle de Apuron, 1",
    "sg:city":"Santa Cruz Palma",
    "sg:orig_category":"Ropa Para Se\u00d1oras Y Caballeros (al Por Menor)",
    "sg:phone":"+34 922 41 11 34",
    "sg:postcode":"38700",
    "sg:province":"Santa Cruz De Tenerife",
    "wof:name":"Gonzalez Leal Oscar",
    "wof:placetype":"venue"
},
  "geometry": {"coordinates":[-17.7649784088,28.6820869446],"type":"Point"}
}