{
  "type": "Feature",
  "properties": {
    "addr:full":"C/ Major, 91 Argelaguer Girona 17853",
    "addr:housenumber":"91",
    "addr:postcode":"17853",
    "addr:street":"C / Major",
    "iso:country":"ES",
    "sg:address":"C/ Major, 91",
    "sg:city":"Argelaguer",
    "sg:orig_category":"Administraciones Regionales, Departamentales Y Locales",
    "sg:phone":"+34 972 68 71 37",
    "sg:postcode":"17853",
    "sg:province":"Girona",
    "wof:name":"Ajuntament Argelaguer",
    "wof:placetype":"venue"
},
  "geometry": {"coordinates":[2.6419081688,42.2156066895],"type":"Point"}
}