{
  "type": "Feature",
  "properties": {
    "iso:country":"ES",
    "sg:address":"Urb El Trigal, 71",
    "sg:city":"Urbanizacion El Trigal",
    "sg:orig_category":"Agencias Y Agentes Comerciales, Representantes",
    "sg:phone":"+34 967 60 52 59",
    "sg:postcode":"02006",
    "sg:province":"Albacete",
    "wof:name":"R.m.p.roberto Mu\u00f1oz Perez S.l.",
    "wof:placetype":"venue"
},
  "geometry": {"coordinates":[-1.7381440401,38.6840438843],"type":"Point"}
}