{
  "type": "Feature",
  "properties": {
    "addr:full":"Calle de Zurbaran, 1 Ventanicas-el Cantal Almer\u00eda 04638",
    "addr:housenumber":"1",
    "addr:postcode":"04638",
    "addr:street":"Calle De Zurbaran",
    "iso:country":"ES",
    "sg:address":"Calle de Zurbaran, 1",
    "sg:city":"Ventanicas-el Cantal",
    "sg:orig_category":"Agencias De Viajes",
    "sg:phone":"+34 950 61 53 00",
    "sg:postcode":"04638",
    "sg:province":"Almer\u00eda",
    "wof:name":"Linares Ortiz Noemi",
    "wof:placetype":"venue"
},
  "geometry": {"coordinates":[-1.8406590223,37.122089386],"type":"Point"}
}