{
  "type": "Feature",
  "properties": {
    "addr:full":"Pase Extremadura, 111 Madrid Madrid 28011",
    "addr:housenumber":"111",
    "addr:postcode":"28011",
    "addr:street":"Extremadura",
    "iso:country":"ES",
    "sg:address":"Pase Extremadura, 111",
    "sg:city":"Madrid",
    "sg:orig_category":"Frutas, Legumbres Frescas Y Tempranas (al Por Menor)",
    "sg:phone":"+34 914 63 19 25",
    "sg:postcode":"28011",
    "sg:province":"Madrid",
    "wof:name":"Frutas Eloy Ruano S.l.",
    "wof:placetype":"venue"
},
  "geometry": {"coordinates":[-3.7346138954,40.4112434387],"type":"Point"}
}