{
  "type": "Feature",
  "properties": {
    "addr:full":"Calle de Roque Morera, 1 Palmas De Gran Canaria Las Palmas 35001",
    "addr:housenumber":"1",
    "addr:postcode":"35001",
    "addr:street":"Calle De Roque Morera",
    "iso:country":"ES",
    "sg:address":"Calle de Roque Morera, 1",
    "sg:city":"Palmas De Gran Canaria",
    "sg:orig_category":"Asociaciones, Organismos Culturales Y Socioeducativos",
    "sg:phone":"+34 928 33 43 41",
    "sg:postcode":"35001",
    "sg:province":"Las Palmas",
    "wof:name":"Real Sociedad Economica Amigos Del Pais G.c.",
    "wof:placetype":"venue"
},
  "geometry": {"coordinates":[-15.4122409821,28.1011543274],"type":"Point"}
}