{
  "type": "Feature",
  "properties": {
    "iso:country":"ES",
    "sg:address":"Carrer de Enamorats, 74",
    "sg:city":"Barcelona",
    "sg:orig_category":"Compraventa De Antig\u00dcedades",
    "sg:phone":"+34 932 31 28 73",
    "sg:postcode":"08013",
    "sg:province":"Barcelona",
    "wof:name":"Izquierdo Ibarra Juan Carlos",
    "wof:placetype":"venue"
},
  "geometry": {"coordinates":[2.181926012,41.404510498],"type":"Point"}
}