{
  "type": "Feature",
  "properties": {
    "addr:full":"Avda Argentina, 1 Maracena Granada 18200",
    "addr:housenumber":"1",
    "addr:postcode":"18200",
    "addr:street":"Avda Argentina",
    "iso:country":"ES",
    "sg:address":"Avda Argentina, 1",
    "sg:city":"Maracena",
    "sg:orig_category":"Fabricaci\u00d3n De Art\u00cdculos Y Ornamentos Religiosos",
    "sg:phone":"+34 958 41 58 65",
    "sg:postcode":"18200",
    "sg:province":"Granada",
    "sg:website":"www.pablopeinado.com",
    "wof:name":"Peinado Molina Pablo",
    "wof:placetype":"venue"
},
  "geometry": {"coordinates":[-3.6394169331,37.2090835571],"type":"Point"}
}