{
  "type": "Feature",
  "properties": {
    "iso:country":"ES",
    "sg:address":"Carrer de Lluis Labarta, 7",
    "sg:city":"Esplugues Llobregat",
    "sg:orig_category":"Publicidad (soportes Y Gesti\u00d3n)",
    "sg:phone":"+34 934 70 31 40",
    "sg:postcode":"08950",
    "sg:province":"Barcelona",
    "wof:name":"Pevemar S.l.",
    "wof:placetype":"venue"
},
  "geometry": {"coordinates":[2.0930240154,41.3835029602],"type":"Point"}
}