{
  "type": "Feature",
  "properties": {
    "addr:full":"Calle de San Agustin, 18 Mota Cuervo Cuenca 16630",
    "addr:housenumber":"18",
    "addr:postcode":"16630",
    "addr:street":"Calle De San Agustin",
    "iso:country":"ES",
    "sg:address":"Calle de San Agustin, 18",
    "sg:city":"Mota Cuervo",
    "sg:orig_category":"Fabricaci\u00d3n De Acumuladores Y De Pilas El\u00c9ctricas",
    "sg:phone":"+34 967 18 00 40",
    "sg:postcode":"16630",
    "sg:province":"Cuenca",
    "wof:name":"Electro Union Manchega S.l.",
    "wof:placetype":"venue"
},
  "geometry": {"coordinates":[-2.8707590103,39.5057983398],"type":"Point"}
}