{
  "type": "Feature",
  "properties": {
    "iso:country":"ES",
    "sg:address":"Cmno Leganes, 45",
    "sg:city":"Madrid",
    "sg:orig_category":"Inform\u00c1tica: Soportes De Informaci\u00d3n, Suministros & Accesorios",
    "sg:phone":"+34 917 95 67 47",
    "sg:postcode":"28021",
    "sg:province":"Madrid",
    "wof:name":"Iberica De Productos Cad S.l",
    "wof:placetype":"venue"
},
  "geometry": {"coordinates":[-3.7126998901,40.3435287476],"type":"Point"}
}