{
  "type": "Feature",
  "properties": {
    "addr:full":"Calle de Catamaran, 11 Madrid Madrid 28042",
    "addr:housenumber":"11",
    "addr:postcode":"madrid;28042",
    "addr:street":"Calle De Catamaran",
    "iso:country":"ES",
    "sg:address":"Calle de Catamaran, 11",
    "sg:city":"Madrid",
    "sg:orig_category":"Artes Gr\u00c1ficas, Artes Pl\u00c1sticas (curso)",
    "sg:phone":"+34 913 20 04 81",
    "sg:postcode":"28042",
    "sg:province":"Madrid",
    "wof:name":"Vitresla S.l.",
    "wof:placetype":"venue"
},
  "geometry": {"coordinates":[-3.5943818092,40.452545166],"type":"Point"}
}