{
  "type": "Feature",
  "properties": {
    "addr:full":"Luga Belonga, S/n Belonga Asturias 33193",
    "addr:housenumber":"s",
    "addr:postcode":"33193",
    "addr:street":"/ N Belonga Asturias",
    "iso:country":"ES",
    "sg:address":"Luga Belonga, S/n",
    "sg:city":"Belonga",
    "sg:orig_category":"Autob\u00das (explotaci\u00d3n Y Servicios De)",
    "sg:phone":"+34 985 79 65 14",
    "sg:postcode":"33193",
    "sg:province":"Asturias",
    "wof:name":"Curin Bus Sl",
    "wof:placetype":"venue"
},
  "geometry": {"coordinates":[-5.894742012,43.3435211182],"type":"Point"}
}