{
  "type": "Feature",
  "properties": {
    "addr:full":"Calle de Alfonso Xiii, 63 San Vicente Del Raspeig-sant Vicent Del Raspeig Alicante 03690",
    "addr:housenumber":"63",
    "addr:postcode":"03690",
    "addr:street":"Calle De Alfonso Xiii",
    "iso:country":"ES",
    "sg:address":"Calle de Alfonso Xiii, 63",
    "sg:city":"San Vicente Del Raspeig-sant Vicent Del Raspeig",
    "sg:orig_category":"Doctores En Medicina",
    "sg:phone":"+34 965 66 81 65",
    "sg:postcode":"03690",
    "sg:province":"Alicante",
    "wof:name":"Ferrandiz Marin Francisca Luisa",
    "wof:placetype":"venue"
},
  "geometry": {"coordinates":[-0.5243268013,38.3935089111],"type":"Point"}
}