{
  "type": "Feature",
  "properties": {
    "iso:country":"ES",
    "sg:address":"Calle de Maestro Gozalbo, 14",
    "sg:city":"Valencia",
    "sg:orig_category":"Ropa Y Accesorios",
    "sg:phone":"+34 963 95 56 50",
    "sg:postcode":"46005",
    "sg:province":"Valencia",
    "wof:name":"Fabra Portillo Amparo",
    "wof:placetype":"venue"
},
  "geometry": {"coordinates":[-0.3694519997,39.465171814],"type":"Point"}
}