{
  "type": "Feature",
  "properties": {
    "addr:full":"Cant Toural (do), 1 Santiago De Compostela A Coru\u00f1a 15705",
    "addr:postcode":"15705",
    "addr:street":"Corun\u0303A",
    "iso:country":"ES",
    "sg:address":"Cant Toural (do), 1",
    "sg:city":"Santiago De Compostela",
    "sg:orig_category":"Farmacias",
    "sg:phone":"+34 981 58 58 95",
    "sg:postcode":"15705",
    "sg:province":"A Coru\u00f1a",
    "wof:name":"Valdes Cabo Maria Jesus",
    "wof:placetype":"venue"
},
  "geometry": {"coordinates":[-8.5442848206,42.8774223328],"type":"Point"}
}