{
  "type": "Feature",
  "properties": {
    "iso:country":"ES",
    "sg:address":"Ctra. Valverde, S/n",
    "sg:city":"Merida",
    "sg:orig_category":"Goma: Productos De Consumo, De Hogar, Higi\u00c9nicos (fabricaci\u00d3n)",
    "sg:phone":"+34 924 31 10 12",
    "sg:postcode":"06800",
    "sg:province":"Badajoz",
    "wof:name":"Juan Quintana S.l.",
    "wof:placetype":"venue"
},
  "geometry": {"coordinates":[-6.3242912292,38.9209442139],"type":"Point"}
}