{
  "type": "Feature",
  "properties": {
    "addr:full":"Calle de Picos Europa, 1 Torrelavega Cantabria 39300",
    "addr:housenumber":"1",
    "addr:postcode":"39300",
    "addr:street":"Calle De Picos Europa",
    "iso:country":"ES",
    "sg:address":"Calle de Picos Europa, 1",
    "sg:city":"Torrelavega",
    "sg:orig_category":"Mec\u00c1nico Del Autom\u00d3vil",
    "sg:phone":"+34 942 80 50 88",
    "sg:postcode":"39300",
    "sg:province":"Cantabria",
    "wof:name":"Alonso Gutierrez Javier",
    "wof:placetype":"venue"
},
  "geometry": {"coordinates":[-4.0548825264,43.347782135],"type":"Point"}
}