{
  "type": "Feature",
  "properties": {
    "iso:country":"ES",
    "sg:address":"Calle de Emperatriz Eugenia, 17",
    "sg:city":"Granada",
    "sg:orig_category":"Ropa Y Accesorios",
    "sg:phone":"+34 958 80 41 18",
    "sg:postcode":"18002",
    "sg:province":"Granada",
    "wof:name":"Garcia Torrico Manuel",
    "wof:placetype":"venue"
},
  "geometry": {"coordinates":[-3.6077010632,37.1755638123],"type":"Point"}
}