{
  "type": "Feature",
  "properties": {
    "addr:full":"Avda Flores (las), 71 Alcorcon Madrid 28925",
    "addr:housenumber":"71",
    "addr:postcode":"28925",
    "addr:street":"Avda Flores Las",
    "iso:country":"ES",
    "sg:address":"Avda Flores (las), 71",
    "sg:city":"Alcorcon",
    "sg:orig_category":"Asesor\u00cda Fiscal Y Jur\u00cddica",
    "sg:phone":"+34 916 19 85 57",
    "sg:postcode":"28925",
    "sg:province":"Madrid",
    "wof:name":"Ropero Lopez Fermina",
    "wof:placetype":"venue"
},
  "geometry": {"coordinates":[-3.8033840656,40.3557281494],"type":"Point"}
}