{
  "type": "Feature",
  "properties": {
    "iso:country":"ES",
    "sg:address":"Calle de Axular, 7",
    "sg:city":"Portugalete",
    "sg:orig_category":"Montaje (empresas De)",
    "sg:phone":"+34 944 72 34 87",
    "sg:postcode":"48920",
    "sg:province":"Vizcaya",
    "wof:name":"Montajes Y Mantenimientos Industriales Sella S.l.",
    "wof:placetype":"venue"
},
  "geometry": {"coordinates":[-3.0189201832,43.3175086975],"type":"Point"}
}