{
  "type": "Feature",
  "properties": {
    "addr:full":"Calle de Fragua (la), 11 San Jose Rinconada Sevilla 41300",
    "addr:housenumber":"11",
    "addr:postcode":"41300",
    "addr:street":"Calle De Fragua La",
    "iso:country":"ES",
    "sg:address":"Calle de Fragua (la), 11",
    "sg:city":"San Jose Rinconada",
    "sg:orig_category":"Fisioterapia",
    "sg:phone":"+34 954 79 00 21",
    "sg:postcode":"41300",
    "sg:province":"Sevilla",
    "wof:name":"Jimenez Ortiz Maria Del Pilar",
    "wof:placetype":"venue"
},
  "geometry": {"coordinates":[-5.9413142204,37.4882774353],"type":"Point"}
}