{
  "type": "Feature",
  "properties": {
    "addr:full":"Calle de General Moscardo Guzman, 18 Guadalajara Guadalajara 19004",
    "addr:housenumber":"18",
    "addr:postcode":"19004",
    "addr:street":"Calle De General Moscardo Guzman",
    "iso:country":"ES",
    "sg:address":"Calle de General Moscardo Guzman, 18",
    "sg:city":"Guadalajara",
    "sg:orig_category":"Reposter\u00cdas",
    "sg:phone":"+34 949 23 22 55",
    "sg:postcode":"19004",
    "sg:province":"Guadalajara",
    "wof:name":"Industrias Panaderas Alcarre\u00f1as S. A.",
    "wof:placetype":"venue"
},
  "geometry": {"coordinates":[-3.171536684,40.63306427],"type":"Point"}
}