{
  "type": "Feature",
  "properties": {
    "iso:country":"ES",
    "sg:address":"Ptda Ramonet, S/n",
    "sg:city":"Almassora Pol. Ind.",
    "sg:orig_category":"Cer\u00c1mica Art\u00cdstica Y Decorativa",
    "sg:phone":"+34 964 53 09 54",
    "sg:postcode":"12550",
    "sg:province":"Castell\u00f3n",
    "wof:name":"Tecnofoc S.a.",
    "wof:placetype":"venue"
},
  "geometry": {"coordinates":[-0.0631740019,39.9439582825],"type":"Point"}
}