{
  "type": "Feature",
  "properties": {
    "addr:full":"Calle de Santa Trinidad, 28 Torrevieja Alicante 03180",
    "addr:housenumber":"28",
    "addr:postcode":"03180",
    "addr:street":"Calle De Santa Trinidad",
    "iso:country":"ES",
    "sg:address":"Calle de Santa Trinidad, 28",
    "sg:city":"Torrevieja",
    "sg:orig_category":"Promotores Constructores",
    "sg:phone":"+34 965 71 44 80",
    "sg:postcode":"03180",
    "sg:province":"Alicante",
    "wof:name":"Promocion Rosemarpe S.l.",
    "wof:placetype":"venue"
},
  "geometry": {"coordinates":[-0.6848090291,37.9815444946],"type":"Point"}
}