{
  "type": "Feature",
  "properties": {
    "addr:full":"Urb Jard Monsalvez, S/n Churriana M\u00e1laga 29140",
    "addr:housenumber":"s",
    "addr:postcode":"29140",
    "addr:street":"Urb;/ N",
    "iso:country":"ES",
    "sg:address":"Urb Jard Monsalvez, S/n",
    "sg:city":"Churriana",
    "sg:orig_category":"Bazares, Art\u00cdculos De Limpieza Y De Cocina (al Por Menor)",
    "sg:phone":"+34 952 43 72 30",
    "sg:postcode":"29140",
    "sg:province":"M\u00e1laga",
    "wof:name":"Prados Carmona Josefa",
    "wof:placetype":"venue"
},
  "geometry": {"coordinates":[-4.5008687973,36.6678237915],"type":"Point"}
}