{
  "type": "Feature",
  "properties": {
    "iso:country":"ES",
    "sg:address":"Calle de Brahms, 2",
    "sg:city":"Malaga",
    "sg:orig_category":"Fabricaci\u00d3n De Muebles",
    "sg:phone":"+34 952 23 16 17",
    "sg:postcode":"29004",
    "sg:province":"M\u00e1laga",
    "wof:name":"Gonzalez Garcia Leonardo",
    "wof:placetype":"venue"
},
  "geometry": {"coordinates":[-4.4515733719,36.6947174072],"type":"Point"}
}