{
  "type": "Feature",
  "properties": {
    "addr:full":"Calle de Gaztambide, 45 Madrid Madrid 28015",
    "addr:housenumber":"45",
    "addr:postcode":"madrid;28015",
    "addr:street":"Calle De Gaztambide",
    "iso:country":"ES",
    "sg:address":"Calle de Gaztambide, 45",
    "sg:city":"Madrid",
    "sg:orig_category":"Comercio De Piezas De Recambio Y De Accesorios De Veh\u00cdculos, Veh\u00cdculos Industriales",
    "sg:phone":"+34 915 43 42 06",
    "sg:postcode":"28015",
    "sg:province":"Madrid",
    "wof:name":"Gonzalez Estrada Antonio",
    "wof:placetype":"venue"
},
  "geometry": {"coordinates":[-3.7155618668,40.4349212646],"type":"Point"}
}