{
  "type": "Feature",
  "properties": {
    "addr:full":"Avda Arquitecto Julio Carrilero, S/n Albacete Albacete 02005",
    "addr:housenumber":"s / n",
    "addr:postcode":"02005",
    "addr:street":"Avda Arquitecto Julio Carrilero",
    "iso:country":"ES",
    "sg:address":"Avda Arquitecto Julio Carrilero, S/n",
    "sg:city":"Albacete",
    "sg:orig_category":"Centros De Educaci\u00d3n Especial",
    "sg:phone":"+34 967 22 53 30",
    "sg:postcode":"02005",
    "sg:province":"Albacete",
    "wof:name":"Colegio Nacional Diego Velazquez",
    "wof:placetype":"venue"
},
  "geometry": {"coordinates":[-1.8660889864,38.9979705811],"type":"Point"}
}