{
  "type": "Feature",
  "properties": {
    "iso:country":"ES",
    "sg:address":"Calle de Eugenio Hermoso, 7",
    "sg:city":"Calera Leon",
    "sg:orig_category":"Supermercados Y Hipermercados",
    "sg:phone":"+34 924 58 40 66",
    "sg:postcode":"06292",
    "sg:province":"Badajoz",
    "wof:name":"Coronado Gata Josefa",
    "wof:placetype":"venue"
},
  "geometry": {"coordinates":[-6.3388037682,38.1062011719],"type":"Point"}
}