{
  "type": "Feature",
  "properties": {
    "iso:country":"ES",
    "sg:address":"Calle de Caracas, S/n",
    "sg:city":"Vitoria-gasteiz",
    "sg:orig_category":"Farmacias",
    "sg:phone":"+34 945 22 25 46",
    "sg:postcode":"01012",
    "sg:province":"\u00c1lava",
    "wof:name":"Lopez De Ocariz Saez De Adana Maria Jesus",
    "wof:placetype":"venue"
},
  "geometry": {"coordinates":[-2.6776576042,42.8574180603],"type":"Point"}
}