{
  "type": "Feature",
  "properties": {
    "iso:country":"ES",
    "sg:address":"Calle de Animas, 7",
    "sg:city":"Valverde Camino",
    "sg:orig_category":"Clubes Y Asociaciones Deportivas Y De Actividades Invernales Y De Monta\u00d1a",
    "sg:phone":"+34 959 55 50 68",
    "sg:postcode":"21600",
    "sg:province":"Huelva",
    "wof:name":"Motoclub Valverde\u00d1o",
    "wof:placetype":"venue"
},
  "geometry": {"coordinates":[-6.7480993271,37.5754890442],"type":"Point"}
}