{
  "type": "Feature",
  "properties": {
    "addr:full":"Calle de Real, 25 Talveila Soria 42148",
    "addr:housenumber":"25",
    "addr:postcode":"42148",
    "addr:street":"Calle De Real",
    "iso:country":"ES",
    "sg:address":"Calle de Real, 25",
    "sg:city":"Talveila",
    "sg:orig_category":"Artes Gr\u00c1ficas, Artes Pl\u00c1sticas: Material Y Suministros (al Por Menor)",
    "sg:phone":"+34 975 37 53 55",
    "sg:postcode":"42148",
    "sg:province":"Soria",
    "wof:name":"Jose Maria Uriel S.l.",
    "wof:placetype":"venue"
},
  "geometry": {"coordinates":[-2.9658174515,41.7844047546],"type":"Point"}
}