{
  "type": "Feature",
  "properties": {
    "addr:full":"Cullerers, 14 Alaquas Valencia 46970",
    "addr:housenumber":"14",
    "addr:postcode":"46970",
    "addr:street":"Cullerers",
    "iso:country":"ES",
    "sg:address":"Cullerers, 14",
    "sg:city":"Alaquas",
    "sg:orig_category":"Paneles De Madera: Contrachapados, Fibras, Particulados, Estratificados (fabricaci\u00d3n, Venta)",
    "sg:phone":"+34 961 50 75 98",
    "sg:postcode":"46970",
    "sg:province":"Valencia",
    "wof:name":"Tableros Y Rechapados Sueca S.a.",
    "wof:placetype":"venue"
},
  "geometry": {"coordinates":[-0.4785439968,39.4476203918],"type":"Point"}
}