{
  "type": "Feature",
  "properties": {
    "iso:country":"ES",
    "sg:address":"Av Ave Maria, 2",
    "sg:city":"Escala",
    "sg:orig_category":"Inmobiliaria (agencias)",
    "sg:phone":"+34 972 77 02 72",
    "sg:postcode":"17130",
    "sg:province":"Girona",
    "sg:website":"www.guanter.com",
    "wof:name":"Guanter Ballesta Carlos",
    "wof:placetype":"venue"
},
  "geometry": {"coordinates":[3.1364684105,42.1238441467],"type":"Point"}
}