{
  "type": "Feature",
  "properties": {
    "iso:country":"ES",
    "sg:address":"Avda Regiones, 2",
    "sg:city":"Fuenlabrada",
    "sg:orig_category":"Empresas De Vigilancia, Guardia Y Protecci\u00d3n",
    "sg:phone":"+34 916 06 79 02",
    "sg:postcode":"28941",
    "sg:province":"Madrid",
    "wof:name":"Mvb Quality S.l.",
    "wof:placetype":"venue"
},
  "geometry": {"coordinates":[-3.7969989777,40.2882003784],"type":"Point"}
}