{
  "type": "Feature",
  "properties": {
    "iso:country":"ES",
    "sg:address":"Calle de Gil De Andrade, 5",
    "sg:city":"Alcala Henares",
    "sg:orig_category":"Asociaciones Humanitarias, De Cooperaci\u00d3n, De Acci\u00d3n Social",
    "sg:phone":"+34 918 80 69 75",
    "sg:postcode":"28804",
    "sg:province":"Madrid",
    "wof:name":"Asociacion Para La Defensa De La Atencion A La Anorexia Nerviosa",
    "wof:placetype":"venue"
},
  "geometry": {"coordinates":[-3.3542785645,40.4873733521],"type":"Point"}
}