{
  "type": "Feature",
  "properties": {
    "addr:full":"Calle de Do\u00d1a Blanca, 23 Jerez De La Frontera C\u00e1diz 11402",
    "addr:housenumber":"23",
    "addr:postcode":"11402",
    "addr:street":"Calle De Don\u0303A Blanca",
    "iso:country":"ES",
    "sg:address":"Calle de Do\u00d1a Blanca, 23",
    "sg:city":"Jerez De La Frontera",
    "sg:orig_category":"Mercer\u00cda, Lencer\u00cda (al Por Menor)",
    "sg:phone":"+34 956 34 09 21",
    "sg:postcode":"11402",
    "sg:province":"C\u00e1diz",
    "wof:name":"Serna Enriquez Ana Pilar",
    "wof:placetype":"venue"
},
  "geometry": {"coordinates":[-6.134305954,36.6817436218],"type":"Point"}
}