{
  "type": "Feature",
  "properties": {
    "iso:country":"ES",
    "sg:address":"Pla\u00c7 Major, 3",
    "sg:city":"Mollo",
    "sg:orig_category":"Transportes Por Carretera: Lotes Completos, Mercanc\u00cdas Diversas",
    "sg:phone":"+34 972 74 03 83",
    "sg:postcode":"17868",
    "sg:province":"Girona",
    "wof:name":"Llongarriu Vila Juan",
    "wof:placetype":"venue"
},
  "geometry": {"coordinates":[2.4044399261,42.3481636047],"type":"Point"}
}