{
  "type": "Feature",
  "properties": {
    "iso:country":"ES",
    "sg:address":"Calle de Ortega Y Gasset, 29",
    "sg:city":"Carrizal",
    "sg:orig_category":"Frutas, Legumbres Frescas Y Tempranas (al Por Menor)",
    "sg:phone":"+34 928 78 20 98",
    "sg:postcode":"35240",
    "sg:province":"Las Palmas",
    "wof:name":"Ortega Ortega Antonio",
    "wof:placetype":"venue"
},
  "geometry": {"coordinates":[-15.4024209976,27.911359787],"type":"Point"}
}