{
  "type": "Feature",
  "properties": {
    "addr:full":"A Casalonga, S/n Casalonga La Coru\u00f1a 15866",
    "addr:housenumber":"s",
    "addr:postcode":"15866",
    "addr:street":"/ N Casalonga La Corun\u0303A",
    "iso:country":"ES",
    "sg:address":"A Casalonga, S/n",
    "sg:city":"Casalonga",
    "sg:orig_category":"Tapicer\u00cdas",
    "sg:phone":"+34 981 53 80 08",
    "sg:postcode":"15866",
    "sg:province":"La Coru\u00f1a",
    "wof:name":"Ares Garcia Jesus",
    "wof:placetype":"venue"
},
  "geometry": {"coordinates":[-8.3959693909,43.3714904785],"type":"Point"}
}