{
  "type": "Feature",
  "properties": {
    "iso:country":"ES",
    "sg:address":"Calle de Alcazar, 11",
    "sg:city":"Ceclavin",
    "sg:orig_category":"Mercer\u00cda, Lencer\u00cda (al Por Menor)",
    "sg:phone":"+34 927 39 30 66",
    "sg:postcode":"10870",
    "sg:province":"C\u00e1ceres",
    "wof:name":"Antunez Rubio Cipriano",
    "wof:placetype":"venue"
},
  "geometry": {"coordinates":[-6.7740573883,39.8222503662],"type":"Point"}
}