{
  "type": "Feature",
  "properties": {
    "addr:full":"Calle de General, 9 Medulas Le\u00f3n 24442",
    "addr:housenumber":"9",
    "addr:postcode":"24442",
    "addr:street":"Calle De General;Leo\u0301N",
    "iso:country":"ES",
    "sg:address":"Calle de General, 9",
    "sg:city":"Medulas",
    "sg:orig_category":"Venta, Instalaci\u00d3n De Cocinas",
    "sg:phone":"+34 987 42 28 72",
    "sg:postcode":"24442",
    "sg:province":"Le\u00f3n",
    "wof:name":"Vega Yebra Maria Fe",
    "wof:placetype":"venue"
},
  "geometry": {"coordinates":[-6.7656288147,42.4908943176],"type":"Point"}
}