{
  "type": "Feature",
  "properties": {
    "iso:country":"ES",
    "sg:address":"Calle de Ondara, Km. 0001,0",
    "sg:city":"Denia",
    "sg:orig_category":"Agentes, Concesionarios Y Sucursales De Veh\u00cdculos",
    "sg:phone":"+34 965 78 28 26",
    "sg:postcode":"03700",
    "sg:province":"Alicante",
    "wof:name":"Auto Perbo S.l.",
    "wof:placetype":"venue"
},
  "geometry": {"coordinates":[0.1039630026,38.8354949951],"type":"Point"}
}