{
  "type": "Feature",
  "properties": {
    "iso:country":"ES",
    "sg:address":"Carrer de Floridablanca, 119",
    "sg:city":"Barcelona",
    "sg:orig_category":"Ropa Para Se\u00d1oras (al Por Menor)",
    "sg:phone":"+34 934 26 76 16",
    "sg:postcode":"08011",
    "sg:province":"Barcelona",
    "wof:name":"Tuldra Oliveras Francisca",
    "wof:placetype":"venue"
},
  "geometry": {"coordinates":[2.1612279415,41.38073349],"type":"Point"}
}