{
  "type": "Feature",
  "properties": {
    "addr:full":"Cno Relonge, S/n S. Vicente Raspeig Alicante 03690",
    "addr:housenumber":"s",
    "addr:postcode":"03690",
    "addr:street":"Cno Relonge;/ N S. Vicente Raspeig",
    "iso:country":"ES",
    "sg:address":"Cno Relonge, S/n",
    "sg:city":"S. Vicente Raspeig",
    "sg:orig_category":"Transportes A\u00c9reos",
    "sg:phone":"+34 965 66 59 67",
    "sg:postcode":"03690",
    "sg:province":"Alicante",
    "wof:name":"Helicopteros Del Sureste S.a.",
    "wof:placetype":"venue"
},
  "geometry": {"coordinates":[-0.5231339931,38.3981590271],"type":"Point"}
}