{
  "type": "Feature",
  "properties": {
    "iso:country":"ES",
    "sg:address":"Calle de Cervantes, 9",
    "sg:city":"Cuenca",
    "sg:orig_category":"Sociedades, Compa\u00d1\u00cdas Aseguradoras",
    "sg:phone":"+34 969 24 13 00",
    "sg:postcode":"16004",
    "sg:province":"Cuenca",
    "sg:website":"www.vitalicio.es",
    "wof:name":"Banco Vitalicio De Espa\u00f1a",
    "wof:placetype":"venue"
},
  "geometry": {"coordinates":[-2.1361079216,40.0705757141],"type":"Point"}
}