{
  "type": "Feature",
  "properties": {
    "iso:country":"ES",
    "sg:address":"Avda Estacion (la), 5",
    "sg:city":"Alacant",
    "sg:orig_category":"Creaci\u00d3n De Sitios, Hosting Internet",
    "sg:phone":"+34 965 92 60 54",
    "sg:postcode":"03003",
    "sg:province":"Alicante",
    "wof:name":"Virtual Affairs S.l.",
    "wof:placetype":"venue"
},
  "geometry": {"coordinates":[-0.4920380116,38.3453826904],"type":"Point"}
}