{
  "type": "Feature",
  "properties": {
    "addr:full":"Calle de Eras Yermas, 31 Cosuenda Zaragoza 50409",
    "addr:housenumber":"31",
    "addr:postcode":"50409",
    "addr:street":"Calle De Eras Yermas",
    "iso:country":"ES",
    "sg:address":"Calle de Eras Yermas, 31",
    "sg:city":"Cosuenda",
    "sg:orig_category":"Limpieza Con Chorro De Arena Y Con Granalla, Pulido",
    "sg:phone":"+34 976 62 70 21",
    "sg:postcode":"50409",
    "sg:province":"Zaragoza",
    "wof:name":"Universal De Pulidos S.c.",
    "wof:placetype":"venue"
},
  "geometry": {"coordinates":[-1.3002580404,41.3659858704],"type":"Point"}
}