{
  "type": "Feature",
  "properties": {
    "iso:country":"ES",
    "sg:address":"Calle de Don Cristian, 10",
    "sg:city":"Malaga",
    "sg:orig_category":"Agencias De Viajes",
    "sg:phone":"+34 952 07 06 93",
    "sg:postcode":"29007",
    "sg:province":"M\u00e1laga",
    "sg:website":"www.zafirotours.es",
    "wof:name":"Sun Moon Travel S.l.",
    "wof:placetype":"venue"
},
  "geometry": {"coordinates":[-4.4293580055,36.7188606262],"type":"Point"}
}