{
  "type": "Feature",
  "properties": {
    "addr:full":"Calle de Deportes, 9 Aguilas Murcia 30880",
    "addr:housenumber":"9",
    "addr:postcode":"30880",
    "addr:street":"Calle De Deportes",
    "iso:country":"ES",
    "sg:address":"Calle de Deportes, 9",
    "sg:city":"Aguilas",
    "sg:orig_category":"Asesor\u00cda Para La Organizaci\u00d3n Y Gesti\u00d3n Del Transporte",
    "sg:phone":"+34 968 44 94 14",
    "sg:postcode":"30880",
    "sg:province":"Murcia",
    "wof:name":"Rodriguez Guijarro Isabel Maria",
    "wof:placetype":"venue"
},
  "geometry": {"coordinates":[-1.5863790512,37.4075012207],"type":"Point"}
}