{
  "type": "Feature",
  "properties": {
    "iso:country":"ES",
    "sg:address":"Rava Robuster, 29",
    "sg:city":"Reus",
    "sg:orig_category":"Administradores De Bienes Y Delegados De Comunidades De Propietarios",
    "sg:phone":"+34 977 34 01 28",
    "sg:postcode":"43204",
    "sg:province":"Tarragona",
    "wof:name":"Pascual Faixes Jose",
    "wof:placetype":"venue"
},
  "geometry": {"coordinates":[1.1095000505,41.1532402039],"type":"Point"}
}