{
  "type": "Feature",
  "properties": {
    "iso:country":"ES",
    "sg:address":"Calle de Marcenado, 46",
    "sg:city":"Madrid",
    "sg:orig_category":"Abogados",
    "sg:phone":"+34 914 16 04 24",
    "sg:postcode":"28002",
    "sg:province":"Madrid",
    "wof:name":"Rafael Cano Antonio De",
    "wof:placetype":"venue"
},
  "geometry": {"coordinates":[-3.6736030579,40.448513031],"type":"Point"}
}