{
  "type": "Feature",
  "properties": {
    "iso:country":"ES",
    "sg:address":"Carr Joaquim Ruyra, S/n",
    "sg:city":"Badalona",
    "sg:orig_category":"Molduras, Junquillos, Listones Y Molduras Perforadas",
    "sg:phone":"+34 933 99 92 04",
    "sg:postcode":"08918",
    "sg:province":"Barcelona",
    "wof:name":"Moldes Cirera Jose Luis",
    "wof:placetype":"venue"
},
  "geometry": {"coordinates":[2.2316219807,41.4403800964],"type":"Point"}
}