{
  "type": "Feature",
  "properties": {
    "addr:full":"Calle de Gregorio Fernandez, 32 Zafra Badajoz 06300",
    "addr:housenumber":"32",
    "addr:postcode":"06300",
    "addr:street":"Calle De Gregorio Fernandez",
    "iso:country":"ES",
    "sg:address":"Calle de Gregorio Fernandez, 32",
    "sg:city":"Zafra",
    "sg:orig_category":"Guarder\u00cdas",
    "sg:phone":"+34 924 55 23 42",
    "sg:postcode":"06300",
    "sg:province":"Badajoz",
    "wof:name":"Escudero Jane Encarnacion",
    "wof:placetype":"venue"
},
  "geometry": {"coordinates":[-6.4183287621,38.4188804626],"type":"Point"}
}