{
  "type": "Feature",
  "properties": {
    "addr:full":"Ctra Mediodia, 16 Madrid Madrid 28050",
    "addr:housenumber":"16",
    "addr:postcode":"madrid;28050",
    "addr:street":"Ctra Mediodia",
    "iso:country":"ES",
    "sg:address":"Ctra Mediodia, 16",
    "sg:city":"Madrid",
    "sg:orig_category":"Financiaci\u00d3n Y Cr\u00c9ditos",
    "sg:phone":"+34 916 50 19 50",
    "sg:postcode":"28050",
    "sg:province":"Madrid",
    "wof:name":"Goizutlan S.l.",
    "wof:placetype":"venue"
},
  "geometry": {"coordinates":[-3.6388890743,40.5049438477],"type":"Point"}
}