{
  "type": "Feature",
  "properties": {
    "addr:full":"Calle de Merced, 19 Burgos Burgos 09002",
    "addr:housenumber":"19",
    "addr:postcode":"09002",
    "addr:street":"Calle De Merced",
    "iso:country":"ES",
    "sg:address":"Calle de Merced, 19",
    "sg:city":"Burgos",
    "sg:orig_category":"Ropa Y Art\u00cdculos Pre",
    "sg:phone":"+34 947 27 70 04",
    "sg:postcode":"09002",
    "sg:province":"Burgos",
    "wof:name":"Garrido Buj Miguel",
    "wof:placetype":"venue"
},
  "geometry": {"coordinates":[-3.704433918,42.3379974365],"type":"Point"}
}