{
  "type": "Feature",
  "properties": {
    "addr:full":"Avda Constitucion (de La), 2 S. Fernando C\u00e1diz 11100",
    "addr:postcode":"11100",
    "addr:street":"Avda Constitucion De La 2 S. Fernando Ca\u0301Diz",
    "iso:country":"ES",
    "sg:address":"Avda Constitucion (de La), 2",
    "sg:city":"S. Fernando",
    "sg:orig_category":"Carnicer\u00cdas, Carnicer\u00cdas",
    "sg:phone":"+34 956 48 71 88",
    "sg:postcode":"11100",
    "sg:province":"C\u00e1diz",
    "wof:name":"Jamones Fernandez Revuelta S.l.",
    "wof:placetype":"venue"
},
  "geometry": {"coordinates":[-6.2067799568,36.4519042969],"type":"Point"}
}