{
  "type": "Feature",
  "properties": {
    "iso:country":"ES",
    "sg:address":"Sta. Eulalia, 8",
    "sg:city":"Las Torres",
    "sg:orig_category":"Delineantes",
    "sg:phone":"+34 923 28 88 82",
    "sg:postcode":"37796",
    "sg:province":"Salamanca",
    "wof:name":"Garcia Nu\u00f1ez Ricardo",
    "wof:placetype":"venue"
},
  "geometry": {"coordinates":[-5.6527791023,40.9079856873],"type":"Point"}
}