{
  "type": "Feature",
  "properties": {
    "addr:full":"Barr Altzusta, 122 Altzusta Vizcaya 48144",
    "addr:housenumber":"122",
    "addr:postcode":"48144",
    "addr:street":"Altzusta Vizcaya",
    "iso:country":"ES",
    "sg:address":"Barr Altzusta, 122",
    "sg:city":"Altzusta",
    "sg:orig_category":"Venta, Instalaci\u00d3n De Cocinas",
    "sg:phone":"+34 946 73 95 64",
    "sg:postcode":"48144",
    "sg:province":"Vizcaya",
    "wof:name":"Bar Restaurante Barazar S.l.",
    "wof:placetype":"venue"
},
  "geometry": {"coordinates":[-2.7497589588,43.0989303589],"type":"Point"}
}