{
  "type": "Feature",
  "properties": {
    "addr:full":"Carrer de Zurbano, 1 Sabadell Barcelona 08201",
    "addr:housenumber":"1",
    "addr:postcode":"08201",
    "addr:street":"Carrer De Zurbano",
    "iso:country":"ES",
    "sg:address":"Carrer de Zurbano, 1",
    "sg:city":"Sabadell",
    "sg:orig_category":"Asesor\u00cdas Y Estudios Financieros",
    "sg:phone":"+34 937 45 03 34",
    "sg:postcode":"08201",
    "sg:province":"Barcelona",
    "wof:name":"Quer Peramiquel Agusti",
    "wof:placetype":"venue"
},
  "geometry": {"coordinates":[2.1115980148,41.5409927368],"type":"Point"}
}