{
  "type": "Feature",
  "properties": {
    "iso:country":"ES",
    "sg:address":"Calle de Trabuco, 2",
    "sg:city":"Sevilla",
    "sg:orig_category":"Molduras, Junquillos, Listones Y Molduras Perforadas",
    "sg:phone":"+34 954 90 15 96",
    "sg:postcode":"41015",
    "sg:province":"Sevilla",
    "wof:name":"Monge Moreno Joaquin",
    "wof:placetype":"venue"
},
  "geometry": {"coordinates":[-5.9763221741,37.4303436279],"type":"Point"}
}