{
  "type": "Feature",
  "properties": {
    "addr:full":"Calle de Paraguay, S/n Alcantarilla Murcia 30820",
    "addr:housenumber":"s",
    "addr:postcode":"30820",
    "addr:street":"Calle De Paraguay;/ N",
    "iso:country":"ES",
    "sg:address":"Calle de Paraguay, S/n",
    "sg:city":"Alcantarilla",
    "sg:classifiers":[
        {
            "category":"Banks & Credit Unions",
            "subcategory":"Bank",
            "type":"Services"
        }
    ],
    "sg:phone":"+34 968 89 44 47",
    "sg:postcode":"30820",
    "sg:province":"Murcia",
    "sg:tags":[
        "interior",
        "arquitectos",
        "de"
    ],
    "wof:name":"Pladinter S.l.",
    "wof:placetype":"venue"
},
  "geometry": {"coordinates":[-1.197584033,37.9587364197],"type":"Point"}
}