{
  "type": "Feature",
  "properties": {
    "iso:country":"ES",
    "sg:address":"Carr Agudes, 4",
    "sg:city":"Breda",
    "sg:orig_category":"Electricidad: Instalaciones Industriales",
    "sg:phone":"+34 972 87 12 29",
    "sg:postcode":"17400",
    "sg:province":"Girona",
    "wof:name":"Instalacions I Mantenients Electrics Breda S.l",
    "wof:placetype":"venue"
},
  "geometry": {"coordinates":[2.5594749451,41.7517814636],"type":"Point"}
}