{
  "type": "Feature",
  "properties": {
    "addr:full":"Avda Libertad (la), S/n Alameda M\u00e1laga 29530",
    "addr:housenumber":"/ n",
    "addr:postcode":"29530",
    "addr:street":"Avda Libertad La S;Alameda Ma\u0301Laga",
    "iso:country":"ES",
    "sg:address":"Avda Libertad (la), S/n",
    "sg:city":"Alameda",
    "sg:orig_category":"Muebles, Minoristas",
    "sg:phone":"+34 952 71 02 59",
    "sg:postcode":"29530",
    "sg:province":"M\u00e1laga",
    "wof:name":"Muebles Soriano Gomez S.l.",
    "wof:placetype":"venue"
},
  "geometry": {"coordinates":[-4.6511387825,37.2043685913],"type":"Point"}
}