{
  "type": "Feature",
  "properties": {
    "iso:country":"ES",
    "sg:address":"Calle de Hermanos Gomez, 24",
    "sg:city":"Madrid",
    "sg:orig_category":"Transporte En General",
    "sg:phone":"+34 913 77 45 73",
    "sg:postcode":"28017",
    "sg:province":"Madrid",
    "wof:name":"Hermanos Diaz Galan C.b.",
    "wof:placetype":"venue"
},
  "geometry": {"coordinates":[-3.650001049,40.4308929443],"type":"Point"}
}