{
  "type": "Feature",
  "properties": {
    "iso:country":"ES",
    "sg:address":"Ur Peq. Chaparral, 18",
    "sg:city":"Pepino",
    "sg:orig_category":"Limpieza Con Chorro De Arena Y Con Granalla, Pulido",
    "sg:phone":"+34 925 82 31 23",
    "sg:postcode":"45638",
    "sg:province":"Toledo",
    "wof:name":"Mu\u00f1oz Delgado Aurelio",
    "wof:placetype":"venue"
},
  "geometry": {"coordinates":[-4.803000927,40.0316200256],"type":"Point"}
}