{
  "type": "Feature",
  "properties": {
    "addr:full":"Rond Industria (de La), 80 Huesca Huesca 22006",
    "addr:postcode":"22006",
    "addr:street":"Rond",
    "iso:country":"ES",
    "sg:address":"Rond Industria (de La), 80",
    "sg:city":"Huesca",
    "sg:orig_category":"Suministros Y Materiales Industriales",
    "sg:phone":"+34 974 24 36 81",
    "sg:postcode":"22006",
    "sg:province":"Huesca",
    "wof:name":"Navasola Huesca S.l.-fax",
    "wof:placetype":"venue"
},
  "geometry": {"coordinates":[-0.3940289915,42.1475105286],"type":"Point"}
}