{
  "type": "Feature",
  "properties": {
    "iso:country":"ES",
    "sg:address":"Carr Vidreres, 4",
    "sg:city":"Ma\u00e7anet Selva",
    "sg:orig_category":"Empresas De Carpinter\u00cda",
    "sg:phone":"+34 972 85 93 32",
    "sg:postcode":"17412",
    "sg:province":"Girona",
    "wof:name":"Aguilera Aliments Naturals S.l.",
    "wof:placetype":"venue"
},
  "geometry": {"coordinates":[2.732227087,41.7722969055],"type":"Point"}
}