{
  "type": "Feature",
  "properties": {
    "iso:country":"ES",
    "sg:address":"Calle de Pintor Barjola, 2",
    "sg:city":"Badajoz",
    "sg:orig_category":"Peluquer\u00cdas, Peluquer\u00cda Mixta",
    "sg:phone":"+34 924 27 21 61",
    "sg:postcode":"06007",
    "sg:province":"Badajoz",
    "wof:name":"Franco Liberal Lucio",
    "wof:placetype":"venue"
},
  "geometry": {"coordinates":[-6.9754528999,38.8975868225],"type":"Point"}
}