{
  "type": "Feature",
  "properties": {
    "iso:country":"ES",
    "sg:address":"Calle de Pilar (del), 2",
    "sg:city":"Alustante",
    "sg:orig_category":"Cajas De Ahorro",
    "sg:phone":"+34 978 71 41 10",
    "sg:postcode":"19320",
    "sg:province":"Guadalajara",
    "wof:name":"Caja De Ahorros Y Monte De Piedad De Zaragoza Aragon Y Rioja",
    "wof:placetype":"venue"
},
  "geometry": {"coordinates":[-1.6572010517,40.614402771],"type":"Point"}
}