{
  "type": "Feature",
  "properties": {
    "iso:country":"ES",
    "sg:address":"Avda General Lopez Dominguez, S/n",
    "sg:city":"Marbella",
    "sg:orig_category":"Financiaci\u00d3n Y Cr\u00c9ditos",
    "sg:phone":"+34 952 86 58 96",
    "sg:postcode":"29600",
    "sg:province":"M\u00e1laga",
    "wof:name":"Finanjona S.l.",
    "wof:placetype":"venue"
},
  "geometry": {"coordinates":[-4.8758540154,36.5112113953],"type":"Point"}
}