{
  "type": "Feature",
  "properties": {
    "iso:country":"ES",
    "sg:address":"Calle de Sierra Nevada (de La), 1",
    "sg:city":"Humanes De Madrid",
    "sg:orig_category":"Muebles, Minoristas",
    "sg:phone":"+34 916 90 41 81",
    "sg:postcode":"28970",
    "sg:province":"Madrid",
    "wof:name":"Ofimar De La Fuente S.l.",
    "wof:placetype":"venue"
},
  "geometry": {"coordinates":[-3.8166875839,40.272857666],"type":"Point"}
}