{
  "type": "Feature",
  "properties": {
    "addr:full":"Pg Bonanova, 39 Barcelona Barcelona 08022",
    "addr:housenumber":"39",
    "addr:postcode":"08022",
    "addr:street":"Pg Bonanova",
    "iso:country":"ES",
    "sg:address":"Pg Bonanova, 39",
    "sg:city":"Barcelona",
    "sg:orig_category":"Cajas De Ahorro",
    "sg:phone":"+34 932 11 74 48",
    "sg:postcode":"08022",
    "sg:province":"Barcelona",
    "sg:website":"www.lacaixa.es",
    "wof:name":"Caixa D'estalvis I Pensions De Barcelona",
    "wof:placetype":"venue"
},
  "geometry": {"coordinates":[2.1304318905,41.4047851562],"type":"Point"}
}