{
  "type": "Feature",
  "properties": {
    "addr:full":"Calle de Mariano Benlliure, 10 Alacant Alicante 03009",
    "addr:housenumber":"10",
    "addr:postcode":"03009",
    "addr:street":"Calle De Mariano Benlliure",
    "iso:country":"ES",
    "sg:address":"Calle de Mariano Benlliure, 10",
    "sg:city":"Alacant",
    "sg:orig_category":"Aluminio Y Aleaciones (producci\u00d3n, Transformaci\u00d3n, Negocio)",
    "sg:phone":"+34 965 18 16 92",
    "sg:postcode":"03009",
    "sg:province":"Alicante",
    "wof:name":"Alugom Alicante S.l.",
    "wof:placetype":"venue"
},
  "geometry": {"coordinates":[-0.5016450286,38.3767700195],"type":"Point"}
}