{
  "type": "Feature",
  "properties": {
    "addr:full":"Pl. B. Vista, 6 Cordoba C\u00f3rdoba 14012",
    "addr:housenumber":"6",
    "addr:postcode":"14012",
    "addr:street":"B. Vista;Co\u0301Rdoba",
    "iso:country":"ES",
    "sg:address":"Pl. B. Vista, 6",
    "sg:city":"Cordoba",
    "sg:orig_category":"\u00d3ptica: Instrumentos (fabricaci\u00d3n)",
    "sg:phone":"+34 957 27 00 50",
    "sg:postcode":"14012",
    "sg:province":"C\u00f3rdoba",
    "wof:name":"Avila Carames Pedro Fernando",
    "wof:placetype":"venue"
},
  "geometry": {"coordinates":[-4.790435791,37.8763313293],"type":"Point"}
}