{
  "type": "Feature",
  "properties": {
    "addr:full":"Plaz San Juan, 5 Xirivella Valencia 46950",
    "addr:housenumber":"5",
    "addr:postcode":"46950",
    "addr:street":"Plaz San Juan",
    "iso:country":"ES",
    "sg:address":"Plaz San Juan, 5",
    "sg:city":"Xirivella",
    "sg:orig_category":"Molduras, Junquillos, Listones Y Molduras Perforadas",
    "sg:phone":"+34 963 79 99 84",
    "sg:postcode":"46950",
    "sg:province":"Valencia",
    "wof:name":"Martinez Soriano Fidel",
    "wof:placetype":"venue"
},
  "geometry": {"coordinates":[-0.4282700121,39.4641456604],"type":"Point"}
}