{
  "type": "Feature",
  "properties": {
    "addr:full":"Ptda Pla Museros, S/n Almassora Castell\u00f3n 12550",
    "addr:housenumber":"s / n",
    "addr:postcode":"12550",
    "addr:street":"Ptda Pla Museros;Almassora Castello\u0301N",
    "iso:country":"ES",
    "sg:address":"Ptda Pla Museros, S/n",
    "sg:city":"Almassora",
    "sg:orig_category":"Fabricaci\u00d3n De Enlosados, Soler\u00cdas",
    "sg:phone":"+34 964 56 50 21",
    "sg:postcode":"12550",
    "sg:province":"Castell\u00f3n",
    "wof:name":"Cima Ceramica S.l.",
    "wof:placetype":"venue"
},
  "geometry": {"coordinates":[-0.0631700009,39.9439582825],"type":"Point"}
}