{
  "type": "Feature",
  "properties": {
    "addr:full":"Avda Canarias, 235 Vecindario Las Palmas 35110",
    "addr:housenumber":"235",
    "addr:postcode":"35110",
    "addr:street":"Avda Canarias;Las Palmas",
    "iso:country":"ES",
    "sg:address":"Avda Canarias, 235",
    "sg:city":"Vecindario",
    "sg:orig_category":"Cl\u00cdnicas Dentales",
    "sg:phone":"+34 928 75 40 83",
    "sg:postcode":"35110",
    "sg:province":"Las Palmas",
    "wof:name":"Sociedad Civil Particular Navarro Suarez",
    "wof:placetype":"venue"
},
  "geometry": {"coordinates":[-15.4416589737,27.8498458862],"type":"Point"}
}