{
  "type": "Feature",
  "properties": {
    "iso:country":"ES",
    "sg:address":"Calle de Remedio, 29",
    "sg:city":"Sagunt",
    "sg:orig_category":"Electricidad: Instaladores",
    "sg:phone":"+34 962 66 05 79",
    "sg:postcode":"46500",
    "sg:province":"Valencia",
    "wof:name":"Botella Iba\u00f1ez Manuel",
    "wof:placetype":"venue"
},
  "geometry": {"coordinates":[-0.2753109932,39.68151474],"type":"Point"}
}