{
  "type": "Feature",
  "properties": {
    "addr:full":"Calle de Ajuriaguerra Juan, 4 Bilbao Vizcaya 48009",
    "addr:housenumber":"4",
    "addr:postcode":"48009",
    "addr:street":"Calle De Ajuriaguerra Juan",
    "iso:country":"ES",
    "sg:address":"Calle de Ajuriaguerra Juan, 4",
    "sg:city":"Bilbao",
    "sg:orig_category":"M\u00c9dicos: Estomatolog\u00cda",
    "sg:phone":"+34 944 23 38 59",
    "sg:postcode":"48009",
    "sg:province":"Vizcaya",
    "wof:name":"Solis Polo Ignacio",
    "wof:placetype":"venue"
},
  "geometry": {"coordinates":[-2.9309287071,43.2652397156],"type":"Point"}
}