{
  "type": "Feature",
  "properties": {
    "addr:full":"Calle de San Francisco Javier, S/n Carcastillo Navarra 31310",
    "addr:postcode":"31310",
    "addr:street":"Calle De San Francisco Javier S / N",
    "iso:country":"ES",
    "sg:address":"Calle de San Francisco Javier, S/n",
    "sg:city":"Carcastillo",
    "sg:classifiers":[
        {
            "category":"Autos & Motor Vehicles",
            "subcategory":"Automobile Sales",
            "type":"Retail Goods"
        }
    ],
    "sg:phone":"+34 948 72 50 62",
    "sg:postcode":"31310",
    "sg:province":"Navarra",
    "wof:name":"Auria Echegoyen Miguel",
    "wof:placetype":"venue"
},
  "geometry": {"coordinates":[-1.4425849915,42.3793792725],"type":"Point"}
}