{
  "type": "Feature",
  "properties": {
    "iso:country":"ES",
    "sg:address":"Rua Alfredo Nan, 8",
    "sg:city":"Allariz",
    "sg:orig_category":"Arquitectos",
    "sg:phone":"+34 988 44 14 14",
    "sg:postcode":"32660",
    "sg:province":"Ourense",
    "wof:name":"Vazquez Martin Jose Antonio",
    "wof:placetype":"venue"
},
  "geometry": {"coordinates":[-7.8045091629,42.1868553162],"type":"Point"}
}