{
  "type": "Feature",
  "properties": {
    "iso:country":"ES",
    "sg:address":"Calle de Embajadores, 23",
    "sg:city":"S. Martin Pusa",
    "sg:orig_category":"Plomeros",
    "sg:phone":"+34 925 42 02 45",
    "sg:postcode":"45170",
    "sg:province":"Toledo",
    "wof:name":"Instalaciones Marquez S.l.",
    "wof:placetype":"venue"
},
  "geometry": {"coordinates":[-4.6307420731,39.7847709656],"type":"Point"}
}