{
  "type": "Feature",
  "properties": {
    "addr:full":"Carrer de Valencia, 545 Barcelona Barcelona 08026",
    "addr:housenumber":"545",
    "addr:postcode":"08026",
    "addr:street":"Carrer De Valencia",
    "iso:country":"ES",
    "sg:address":"Carrer de Valencia, 545",
    "sg:city":"Barcelona",
    "sg:orig_category":"Cajas De Ahorro",
    "sg:phone":"+34 932 32 72 10",
    "sg:postcode":"08026",
    "sg:province":"Barcelona",
    "wof:name":"Caixa D'estalvis I Pensions De Barcelona",
    "wof:placetype":"venue"
},
  "geometry": {"coordinates":[2.1822800636,41.4071388245],"type":"Point"}
}