{
  "type": "Feature",
  "properties": {
    "iso:country":"ES",
    "sg:address":"Calle de Union (la), 1",
    "sg:city":"Alacant",
    "sg:orig_category":"Ropa Para Se\u00d1oras (al Por Menor)",
    "sg:phone":"+34 965 92 36 63",
    "sg:postcode":"03005",
    "sg:province":"Alicante",
    "wof:name":"Lloret Gonzalez Silvia",
    "wof:placetype":"venue"
},
  "geometry": {"coordinates":[-0.4948874116,38.3475227356],"type":"Point"}
}