{
  "type": "Feature",
  "properties": {
    "iso:country":"ES",
    "sg:address":"Unic, S/n",
    "sg:city":"Pont Bar",
    "sg:orig_category":"Suministros Para Hoteles",
    "sg:phone":"+34 973 38 41 07",
    "sg:postcode":"25723",
    "sg:province":"Lleida",
    "wof:name":"Porta Grau Agustin",
    "wof:placetype":"venue"
},
  "geometry": {"coordinates":[1.6034990549,42.3264198303],"type":"Point"}
}