{
  "type": "Feature",
  "properties": {
    "addr:full":"Carr Lluis Companys, 5 Palafrugell Girona 17200",
    "addr:housenumber":"5",
    "addr:postcode":"17200",
    "addr:street":"Carr Lluis Companys",
    "iso:country":"ES",
    "sg:address":"Carr Lluis Companys, 5",
    "sg:city":"Palafrugell",
    "sg:orig_category":"Electricidad: Equipos Industriales, Componentes (fabricaci\u00d3n)",
    "sg:phone":"+34 972 30 39 80",
    "sg:postcode":"17200",
    "sg:province":"Girona",
    "wof:name":"Sermat Emporda S.c.",
    "wof:placetype":"venue"
},
  "geometry": {"coordinates":[3.1579051018,41.9161949158],"type":"Point"}
}