{
  "type": "Feature",
  "properties": {
    "iso:country":"ES",
    "sg:address":"Calle de Concepcion Arenal, 44",
    "sg:city":"Guarda",
    "sg:orig_category":"Ense\u00d1anza: Idiomas",
    "sg:phone":"+34 986 61 20 08",
    "sg:postcode":"36780",
    "sg:province":"Pontevedra",
    "wof:name":"Award C.b.",
    "wof:placetype":"venue"
},
  "geometry": {"coordinates":[-8.8712062836,41.9012413025],"type":"Point"}
}