{
  "type": "Feature",
  "properties": {
    "iso:country":"ES",
    "sg:address":"Carr Jaime Santaolalla, 6",
    "sg:city":"Vila Joiosa",
    "sg:orig_category":"Congelados: Productos Alimentarios (fabricaci\u00d3n, Al Por Mayor)",
    "sg:phone":"+34 965 89 48 53",
    "sg:postcode":"03570",
    "sg:province":"Alicante",
    "wof:name":"Fuentes Sanchez Eleuterio",
    "wof:placetype":"venue"
},
  "geometry": {"coordinates":[-0.7466139793,38.3102035522],"type":"Point"}
}