{
  "type": "Feature",
  "properties": {
    "iso:country":"ES",
    "sg:address":"Calle de Mejico, 36",
    "sg:city":"Coslada",
    "sg:orig_category":"Guarder\u00cdas",
    "sg:phone":"+34 916 73 04 42",
    "sg:postcode":"28820",
    "sg:province":"Madrid",
    "wof:name":"Romero Crenes Y Asociados S.l.",
    "wof:placetype":"venue"
},
  "geometry": {"coordinates":[-3.5401299,40.4281959534],"type":"Point"}
}