{
  "type": "Feature",
  "properties": {
    "addr:full":"Praz Cervantes (de), 13 Santiago De Compostela La Coru\u00f1a 15704",
    "addr:housenumber":"13",
    "addr:postcode":"15704",
    "addr:street":"Praz;De;Corun\u0303A",
    "iso:country":"ES",
    "sg:address":"Praz Cervantes (de), 13",
    "sg:city":"Santiago De Compostela",
    "sg:orig_category":"Asociaciones, Organismos Culturales Y Socioeducativos",
    "sg:phone":"+34 981 57 58 48",
    "sg:postcode":"15704",
    "sg:province":"La Coru\u00f1a",
    "wof:name":"Alfa Xestion Cultural S.l.",
    "wof:placetype":"venue"
},
  "geometry": {"coordinates":[-8.537771225,42.8864784241],"type":"Point"}
}