{
  "type": "Feature",
  "properties": {
    "addr:full":"Avda De La Mojarra, S/n Isla Moral Huelva 21409",
    "addr:housenumber":"s / n",
    "addr:postcode":"21409",
    "addr:street":"Avda De La Mojarra",
    "iso:country":"ES",
    "sg:address":"Avda De La Mojarra, S/n",
    "sg:city":"Isla Moral",
    "sg:orig_category":"M\u00c9dicos: An\u00c1lisis Cl\u00cdnicos",
    "sg:phone":"+34 959 47 90 55",
    "sg:postcode":"21409",
    "sg:province":"Huelva",
    "wof:name":"Martin Ruiz Manuel",
    "wof:placetype":"venue"
},
  "geometry": {"coordinates":[-7.3418722153,37.1882247925],"type":"Point"}
}