{
  "type": "Feature",
  "properties": {
    "iso:country":"ES",
    "sg:address":"Av Castilla Mancha, S/n",
    "sg:city":"Villel Mesa",
    "sg:orig_category":"Abogados",
    "sg:phone":"+34 949 83 47 12",
    "sg:postcode":"19332",
    "sg:province":"Guadalajara",
    "wof:name":"Hernandez Espeja Armando",
    "wof:placetype":"venue"
},
  "geometry": {"coordinates":[-1.9879770279,41.1258468628],"type":"Point"}
}