{
  "type": "Feature",
  "properties": {
    "addr:full":"Calle de Ave Maria, 33 Torredonjimeno Ja\u00e9n 23650",
    "addr:housenumber":"33",
    "addr:postcode":"23650",
    "addr:street":"Calle De Ave Maria",
    "iso:country":"ES",
    "sg:address":"Calle de Ave Maria, 33",
    "sg:city":"Torredonjimeno",
    "sg:orig_category":"Comercio, Reparaci\u00d3n De Motocicletas, Bicicletas Y Piezas Sueltas",
    "sg:phone":"+34 953 34 21 32",
    "sg:postcode":"23650",
    "sg:province":"Ja\u00e9n",
    "wof:name":"Trigo Arjona Francisco Jose",
    "wof:placetype":"venue"
},
  "geometry": {"coordinates":[-3.9535009861,37.7618179321],"type":"Point"}
}