{
  "type": "Feature",
  "properties": {
    "iso:country":"ES",
    "sg:address":"Plaz Gonzalo Nardiz, 1",
    "sg:city":"Bermeo",
    "sg:orig_category":"Notarios",
    "sg:phone":"+34 946 18 70 40",
    "sg:postcode":"48370",
    "sg:province":"Vizcaya",
    "wof:name":"Valentin Canaval Manso Y Otros C.b.",
    "wof:placetype":"venue"
},
  "geometry": {"coordinates":[-2.7251009941,43.41929245],"type":"Point"}
}