{
  "type": "Feature",
  "properties": {
    "addr:full":"Carrer de Sant Josep, 49 Martorell Barcelona 08760",
    "addr:housenumber":"49",
    "addr:postcode":"08760",
    "addr:street":"Carrer De Sant Josep",
    "iso:country":"ES",
    "sg:address":"Carrer de Sant Josep, 49",
    "sg:city":"Martorell",
    "sg:orig_category":"Imprenta",
    "sg:phone":"+34 937 75 24 31",
    "sg:postcode":"08760",
    "sg:province":"Barcelona",
    "wof:name":"Pitarch Sancho Antonia",
    "wof:placetype":"venue"
},
  "geometry": {"coordinates":[1.9263930321,41.4715538025],"type":"Point"}
}