{
  "type": "Feature",
  "properties": {
    "addr:full":"Avda Fernando Conde, 12 Estrada Pontevedra 36680",
    "addr:housenumber":"12",
    "addr:postcode":"36680",
    "addr:street":"Avda Fernando Conde;Estrada Pontevedra",
    "iso:country":"ES",
    "sg:address":"Avda Fernando Conde, 12",
    "sg:city":"Estrada",
    "sg:orig_category":"T\u00c9cnicos Veterinarios",
    "sg:phone":"+34 986 57 13 39",
    "sg:postcode":"36680",
    "sg:province":"Pontevedra",
    "wof:name":"Fontevoa 2003 S.l.",
    "wof:placetype":"venue"
},
  "geometry": {"coordinates":[-8.4845371246,42.6897964478],"type":"Point"}
}