{
  "type": "Feature",
  "properties": {
    "addr:full":"Calle de Puerto De Maspalomas, 15 Madrid Madrid 28029",
    "addr:housenumber":"15",
    "addr:postcode":"madrid;28029",
    "addr:street":"Calle De Puerto De Maspalomas",
    "iso:country":"ES",
    "sg:address":"Calle de Puerto De Maspalomas, 15",
    "sg:city":"Madrid",
    "sg:orig_category":"Colocaci\u00d3n, Mantenimiento, Vitrificaci\u00d3n De Parquets",
    "sg:phone":"+34 913 86 14 12",
    "sg:postcode":"28029",
    "sg:province":"Madrid",
    "wof:name":"Promotora Inmobiliaria Dorana S.l.",
    "wof:placetype":"venue"
},
  "geometry": {"coordinates":[-3.7141609192,40.4783782959],"type":"Point"}
}