{
  "type": "Feature",
  "properties": {
    "iso:country":"ES",
    "sg:address":"Pg Generalitat, 4",
    "sg:city":"Vic",
    "sg:orig_category":"Promotores Constructores",
    "sg:phone":"+34 938 85 03 01",
    "sg:postcode":"08500",
    "sg:province":"Barcelona",
    "wof:name":"Habitatges D'osona S. A.",
    "wof:placetype":"venue"
},
  "geometry": {"coordinates":[2.2535328865,41.9248809814],"type":"Point"}
}