{
  "type": "Feature",
  "properties": {
    "addr:full":"Teofilo Hernandez, 10 Ronda M\u00e1laga 29400",
    "addr:housenumber":"10",
    "addr:postcode":"29400",
    "addr:street":"Teofilo Hernandez;Ronda Ma\u0301Laga",
    "iso:country":"ES",
    "sg:address":"Teofilo Hernandez, 10",
    "sg:city":"Ronda",
    "sg:orig_category":"Agencias Y Asesores De Publicidad",
    "sg:phone":"+34 952 18 75 26",
    "sg:postcode":"29400",
    "sg:province":"M\u00e1laga",
    "wof:name":"Cortijo Villazambra S.l.",
    "wof:placetype":"venue"
},
  "geometry": {"coordinates":[-5.1709141731,36.7520675659],"type":"Point"}
}