{
  "type": "Feature",
  "properties": {
    "iso:country":"ES",
    "sg:address":"Prj Del Pilar, S/n",
    "sg:city":"Elche Sierra",
    "sg:orig_category":"Empresas De Carpinter\u00cda De Madera",
    "sg:phone":"+34 967 41 03 94",
    "sg:postcode":"02430",
    "sg:province":"Albacete",
    "wof:name":"Garcia Galafada Jose Enrique De La Cruz",
    "wof:placetype":"venue"
},
  "geometry": {"coordinates":[-2.0470540524,38.4507904053],"type":"Point"}
}