{
  "type": "Feature",
  "properties": {
    "iso:country":"ES",
    "sg:address":"Calle de Perales, 40",
    "sg:city":"Yuncos",
    "sg:orig_category":"Negocio De Materiales De Construcci\u00d3n",
    "sg:phone":"+34 925 53 60 30",
    "sg:postcode":"45210",
    "sg:province":"Toledo",
    "wof:name":"Transportes Y Materiales Benco S.l.",
    "wof:placetype":"venue"
},
  "geometry": {"coordinates":[-3.8768789768,40.0890808105],"type":"Point"}
}