{
  "type": "Feature",
  "properties": {
    "addr:full":"Calle de Garcia Galdeano, 8 Zaragoza Zaragoza 50004",
    "addr:housenumber":"8",
    "addr:postcode":"50004",
    "addr:street":"Calle De Garcia Galdeano",
    "iso:country":"ES",
    "sg:address":"Calle de Garcia Galdeano, 8",
    "sg:city":"Zaragoza",
    "sg:orig_category":"Molduras, Junquillos, Listones Y Molduras Perforadas",
    "sg:phone":"+34 976 22 11 39",
    "sg:postcode":"50004",
    "sg:province":"Zaragoza",
    "wof:name":"Ragtime S. C.",
    "wof:placetype":"venue"
},
  "geometry": {"coordinates":[-0.8909260035,41.6503562927],"type":"Point"}
}