{
  "type": "Feature",
  "properties": {
    "addr:full":"Brocense, 10 Brozas C\u00e1ceres 10950",
    "addr:housenumber":"10",
    "addr:postcode":"10950",
    "addr:street":"Brocense;Ca\u0301Ceres",
    "iso:country":"ES",
    "sg:address":"Brocense, 10",
    "sg:city":"Brozas",
    "sg:orig_category":"Carnicer\u00cdas, Carnicer\u00cdas",
    "sg:phone":"+34 927 39 51 39",
    "sg:postcode":"10950",
    "sg:province":"C\u00e1ceres",
    "wof:name":"Alonso Sanchez Florentino",
    "wof:placetype":"venue"
},
  "geometry": {"coordinates":[-6.7786779404,39.6116447449],"type":"Point"}
}