{
  "type": "Feature",
  "properties": {
    "iso:country":"ES",
    "sg:address":"Calle de Solana Kalea, 7",
    "sg:city":"Tolosa",
    "sg:orig_category":"Lanas (al Por Mayor)",
    "sg:phone":"+34 943 67 01 46",
    "sg:postcode":"20400",
    "sg:province":"Guip\u00f9zcoa",
    "wof:name":"Phildar",
    "wof:placetype":"venue"
},
  "geometry": {"coordinates":[-2.0722548962,43.1373634338],"type":"Point"}
}