{
  "type": "Feature",
  "properties": {
    "iso:country":"ES",
    "sg:address":"Calle de Martin Ferrador, 1",
    "sg:city":"Jerez De La Frontera",
    "sg:orig_category":"Carnicer\u00cdas, Carnicer\u00cdas",
    "sg:phone":"+34 956 31 48 18",
    "sg:postcode":"11405",
    "sg:province":"C\u00e1diz",
    "wof:name":"Hermanos Castronieves S. A.",
    "wof:placetype":"venue"
},
  "geometry": {"coordinates":[-6.127644062,36.6903419495],"type":"Point"}
}