{
  "type": "Feature",
  "properties": {
    "iso:country":"ES",
    "sg:address":"Rua Concepcion Arenal, 18",
    "sg:city":"Vilagarcia",
    "sg:orig_category":"Albergues",
    "sg:phone":"+34 986 50 27 00",
    "sg:postcode":"36600",
    "sg:province":"Pontevedra",
    "wof:name":"Alvarez Losada Ramon",
    "wof:placetype":"venue"
},
  "geometry": {"coordinates":[-8.7647848129,42.6046218872],"type":"Point"}
}