{
  "type": "Feature",
  "properties": {
    "addr:full":"Ctra Sevilla-huelva, Km. 0567,1 Sanlucar Mayor Sevilla 41800",
    "addr:postcode":"41800",
    "addr:street":"Ctra Sevilla-Huelva Km. 0567,1",
    "iso:country":"ES",
    "sg:address":"Ctra Sevilla-huelva, Km. 0567,1",
    "sg:city":"Sanlucar Mayor",
    "sg:orig_category":"Maquinaria Para Industrias Diversas",
    "sg:phone":"+34 955 70 31 53",
    "sg:postcode":"41800",
    "sg:province":"Sevilla",
    "wof:name":"Alquileres Luna S.l.",
    "wof:placetype":"venue"
},
  "geometry": {"coordinates":[-6.2064390182,37.3923377991],"type":"Point"}
}