{
  "type": "Feature",
  "properties": {
    "addr:full":"Carrer de Arizala, 22 Barcelona Barcelona 08028",
    "addr:housenumber":"22",
    "addr:postcode":"08028",
    "addr:street":"Carrer De Arizala",
    "iso:country":"ES",
    "sg:address":"Carrer de Arizala, 22",
    "sg:city":"Barcelona",
    "sg:orig_category":"Librer\u00cdas",
    "sg:phone":"+34 933 34 89 00",
    "sg:postcode":"08028",
    "sg:province":"Barcelona",
    "wof:name":"Caro Moncayo Antonio",
    "wof:placetype":"venue"
},
  "geometry": {"coordinates":[2.1247808933,41.3770446777],"type":"Point"}
}