{
  "type": "Feature",
  "properties": {
    "addr:full":"Calle de Veracruz, 39 Tomelloso Ciudad Real 13700",
    "addr:housenumber":"39",
    "addr:postcode":"13700",
    "addr:street":"Calle De Veracruz",
    "iso:country":"ES",
    "sg:address":"Calle de Veracruz, 39",
    "sg:city":"Tomelloso",
    "sg:orig_category":"Organizaciones Internacionales",
    "sg:phone":"+34 926 51 12 24",
    "sg:postcode":"13700",
    "sg:province":"Ciudad Real",
    "wof:name":"Asamblea Local Cruz Roja",
    "wof:placetype":"venue"
},
  "geometry": {"coordinates":[-3.0201423168,39.1583137512],"type":"Point"}
}