{
  "type": "Feature",
  "properties": {
    "addr:full":"Calle de Castilla, 49 Santander Cantabria 39009",
    "addr:housenumber":"49",
    "addr:postcode":"39009",
    "addr:street":"Calle De Castilla",
    "iso:country":"ES",
    "sg:address":"Calle de Castilla, 49",
    "sg:city":"Santander",
    "sg:orig_category":"Carnicer\u00cdas, Carnicer\u00cdas",
    "sg:phone":"+34 942 36 01 14",
    "sg:postcode":"39009",
    "sg:province":"Cantabria",
    "wof:name":"Hernandez Perez Angel",
    "wof:placetype":"venue"
},
  "geometry": {"coordinates":[-3.8171525002,43.4559020996],"type":"Point"}
}