{
  "type": "Feature",
  "properties": {
    "iso:country":"ES",
    "sg:address":"Calle de Vallehermoso, 90",
    "sg:city":"Madrid",
    "sg:orig_category":"Arquitectos",
    "sg:phone":"+34 915 33 99 19",
    "sg:postcode":"28015",
    "sg:province":"Madrid",
    "wof:name":"Pita Macias Fernando",
    "wof:placetype":"venue"
},
  "geometry": {"coordinates":[-3.708108902,40.4386024475],"type":"Point"}
}