{
  "type": "Feature",
  "properties": {
    "addr:full":"Calle de Silveria Fa\u00d1anas, 5 Zaragoza Zaragoza 50011",
    "addr:housenumber":"5",
    "addr:postcode":"50011",
    "addr:street":"Calle De Silveria Fan\u0303Anas",
    "iso:country":"ES",
    "sg:address":"Calle de Silveria Fa\u00d1anas, 5",
    "sg:city":"Zaragoza",
    "sg:orig_category":"Agencias Y Agentes Comerciales, Representantes",
    "sg:phone":"+34 976 53 50 57",
    "sg:postcode":"50011",
    "sg:province":"Zaragoza",
    "wof:name":"Mu\u00f1oz Ardanuy Fernando",
    "wof:placetype":"venue"
},
  "geometry": {"coordinates":[-0.9913589954,41.662853241],"type":"Point"}
}