{
  "type": "Feature",
  "properties": {
    "addr:full":"Carrer de Retama, 28 Viladecans Barcelona 08840",
    "addr:housenumber":"28",
    "addr:postcode":"08840",
    "addr:street":"Carrer De Retama",
    "iso:country":"ES",
    "sg:address":"Carrer de Retama, 28",
    "sg:city":"Viladecans",
    "sg:orig_category":"Promotores Constructores",
    "sg:phone":"+34 936 37 14 44",
    "sg:postcode":"08840",
    "sg:province":"Barcelona",
    "wof:name":"Construccions Nou Sales 2000 S.l.",
    "wof:placetype":"venue"
},
  "geometry": {"coordinates":[2.009016037,41.3219833374],"type":"Point"}
}