{
  "type": "Feature",
  "properties": {
    "iso:country":"ES",
    "sg:address":"Cai\u00f1os, S/n",
    "sg:city":"Cai\u00d1os",
    "sg:orig_category":"Empresas De Carpinter\u00cda",
    "sg:phone":"+34 981 83 29 50",
    "sg:postcode":"15940",
    "sg:province":"La Coru\u00f1a",
    "wof:name":"Gigirey Miguez Ismael",
    "wof:placetype":"venue"
},
  "geometry": {"coordinates":[-8.9388437271,42.6042404175],"type":"Point"}
}