{
  "type": "Feature",
  "properties": {
    "addr:full":"Av Ugarrandia, 8 Huarte Navarra 31620",
    "addr:housenumber":"8",
    "addr:postcode":"31620",
    "addr:street":"Av Ugarrandia;Navarra",
    "iso:country":"ES",
    "sg:address":"Av Ugarrandia, 8",
    "sg:city":"Huarte",
    "sg:orig_category":"Obras Y Organismos Sociales",
    "sg:phone":"+34 948 19 85 03",
    "sg:postcode":"31620",
    "sg:province":"Navarra",
    "wof:name":"Asociacion Navarra Nuevo Futuro",
    "wof:placetype":"venue"
},
  "geometry": {"coordinates":[-1.5933148861,42.8285980225],"type":"Point"}
}