{
  "type": "Feature",
  "properties": {
    "addr:full":"Calle de Rosas De Aravaca, 5 Madrid Madrid 28023",
    "addr:housenumber":"5",
    "addr:postcode":"28023",
    "addr:street":"Calle De Rosas De Aravaca",
    "iso:country":"ES",
    "sg:address":"Calle de Rosas De Aravaca, 5",
    "sg:city":"Madrid",
    "sg:orig_category":"Agencias Y Agentes Comerciales, Representantes",
    "sg:phone":"+34 913 07 92 79",
    "sg:postcode":"28023",
    "sg:province":"Madrid",
    "wof:name":"Ingenieros De Ventas S.l.",
    "wof:placetype":"venue"
},
  "geometry": {"coordinates":[-3.781056881,40.4509429932],"type":"Point"}
}