{
  "type": "Feature",
  "properties": {
    "addr:full":"Carrer de Castillejos (dels), 19 Reus Tarragona 43206",
    "addr:housenumber":"19",
    "addr:postcode":"43206",
    "addr:street":"Carrer De Castillejos Dels",
    "iso:country":"ES",
    "sg:address":"Carrer de Castillejos (dels), 19",
    "sg:city":"Reus",
    "sg:orig_category":"Panader\u00cdas, Pasteler\u00cdas, Boller\u00cda Industriale (fabricaci\u00d3n, Al Por Mayor)",
    "sg:phone":"+34 977 31 84 54",
    "sg:postcode":"43206",
    "sg:province":"Tarragona",
    "wof:name":"Centre De Distribucio Morcu S.a.",
    "wof:placetype":"venue"
},
  "geometry": {"coordinates":[1.076374054,41.1605606079],"type":"Point"}
}