{
  "type": "Feature",
  "properties": {
    "addr:full":"Plaz Principal, 13 Peralta Navarra 31350",
    "addr:housenumber":"13",
    "addr:postcode":"31350",
    "iso:country":"ES",
    "sg:address":"Plaz Principal, 13",
    "sg:city":"Peralta",
    "sg:orig_category":"Molduras, Junquillos, Listones Y Molduras Perforadas",
    "sg:phone":"+34 948 75 00 77",
    "sg:postcode":"31350",
    "sg:province":"Navarra",
    "wof:name":"Jimenez Sanz Jose Javier",
    "wof:placetype":"venue"
},
  "geometry": {"coordinates":[-1.8050489426,42.3389167786],"type":"Point"}
}