{
  "type": "Feature",
  "properties": {
    "addr:full":"Carrer de Arago, 112 Barcelona Barcelona 08015",
    "addr:housenumber":"112",
    "addr:postcode":"08015",
    "addr:street":"Carrer De Arago",
    "iso:country":"ES",
    "sg:address":"Carrer de Arago, 112",
    "sg:city":"Barcelona",
    "sg:orig_category":"Partidos Pol\u00cdticos",
    "sg:phone":"+34 934 51 43 37",
    "sg:postcode":"08015",
    "sg:province":"Barcelona",
    "wof:name":"Alianza Popular",
    "wof:placetype":"venue"
},
  "geometry": {"coordinates":[2.1543557644,41.3842391968],"type":"Point"}
}