{
  "type": "Feature",
  "properties": {
    "iso:country":"ES",
    "sg:address":"Avda Libertad, 81",
    "sg:city":"Casillas",
    "sg:orig_category":"Supermercados Y Hipermercados",
    "sg:phone":"+34 968 24 00 10",
    "sg:postcode":"30007",
    "sg:province":"Murcia",
    "wof:name":"Centro De Alimentacion Frajavi S.l.",
    "wof:placetype":"venue"
},
  "geometry": {"coordinates":[-1.0976289511,38.0081596375],"type":"Point"}
}