{
  "type": "Feature",
  "properties": {
    "iso:country":"ES",
    "sg:address":"Retuerto Carrer de Carrer de Max Center, 60",
    "sg:city":"San Vicente De Barakaldo",
    "sg:orig_category":"Estilistas Y Estudios De Estilo De Corte Y Confecci\u00d3n",
    "sg:phone":"+34 944 90 22 68",
    "sg:postcode":"48903",
    "sg:province":"Vizcaya",
    "wof:name":"Bandera Verde Iberica S.a.",
    "wof:placetype":"venue"
},
  "geometry": {"coordinates":[-3.0188579559,43.2634010315],"type":"Point"}
}