{
  "type": "Feature",
  "properties": {
    "iso:country":"ES",
    "sg:address":"Pl Esglesia, S/n",
    "sg:city":"Montcada Centre",
    "sg:orig_category":"Iglesia Cat\u00d3lica",
    "sg:phone":"+34 935 64 14 84",
    "sg:postcode":"08110",
    "sg:province":"Barcelona",
    "wof:name":"Parroquia De Santa Engracia",
    "wof:placetype":"venue"
},
  "geometry": {"coordinates":[2.1879301071,41.4865341187],"type":"Point"}
}