{
  "type": "Feature",
  "properties": {
    "addr:full":"Calle de Arfe, 20 Sevilla Sevilla 41001",
    "addr:housenumber":"20",
    "addr:postcode":"41001",
    "addr:street":"Calle De Arfe",
    "iso:country":"ES",
    "sg:address":"Calle de Arfe, 20",
    "sg:city":"Sevilla",
    "sg:orig_category":"Alimentaci\u00d3n General (al Por Menor)",
    "sg:phone":"+34 954 22 13 14",
    "sg:postcode":"41001",
    "sg:province":"Sevilla",
    "wof:name":"El Bacalao S. A.",
    "wof:placetype":"venue"
},
  "geometry": {"coordinates":[-5.9959559441,37.3860244751],"type":"Point"}
}