{
  "type": "Feature",
  "properties": {
    "addr:full":"Calle de Ginzo De Limia, 54 Madrid Madrid 28029",
    "addr:housenumber":"54",
    "addr:postcode":"madrid;28029",
    "addr:street":"Calle De Ginzo De Limia",
    "iso:country":"ES",
    "sg:address":"Calle de Ginzo De Limia, 54",
    "sg:city":"Madrid",
    "sg:orig_category":"Farmacias",
    "sg:phone":"+34 917 39 53 49",
    "sg:postcode":"28029",
    "sg:province":"Madrid",
    "wof:name":"Salgueiro Portillo Gloria",
    "wof:placetype":"venue"
},
  "geometry": {"coordinates":[-3.7045450211,40.4810676575],"type":"Point"}
}