{
  "type": "Feature",
  "properties": {
    "iso:country":"ES",
    "sg:address":"Calle de Barrio Busquet, 1",
    "sg:city":"Caceres",
    "sg:orig_category":"Ense\u00d1anza Variada",
    "sg:phone":"+34 927 21 67 27",
    "sg:postcode":"10004",
    "sg:province":"C\u00e1ceres",
    "wof:name":"Nevado Gonzalez Alfonso Carlos",
    "wof:placetype":"venue"
},
  "geometry": {"coordinates":[-6.3757991791,39.5287971497],"type":"Point"}
}