{
  "type": "Feature",
  "properties": {
    "iso:country":"ES",
    "sg:address":"Calle de Cuesta Del Matadero, 3",
    "sg:city":"Chiclana De La Frontera",
    "sg:orig_category":"Peluquer\u00cdas, Peluquer\u00cda Mixta",
    "sg:phone":"+34 956 40 39 02",
    "sg:postcode":"11130",
    "sg:province":"C\u00e1diz",
    "wof:name":"Feerchak  Dress",
    "wof:placetype":"venue"
},
  "geometry": {"coordinates":[-6.1455698013,36.4163322449],"type":"Point"}
}