{
  "type": "Feature",
  "properties": {
    "addr:full":"Calle de Aguila (el), 46 Hellin Albacete 02400",
    "addr:housenumber":"46",
    "addr:postcode":"02400",
    "addr:street":"Calle De Aguila El",
    "iso:country":"ES",
    "sg:address":"Calle de Aguila (el), 46",
    "sg:city":"Hellin",
    "sg:orig_category":"Telas Y Sedas (al Por Menor)",
    "sg:phone":"+34 967 30 10 04",
    "sg:postcode":"02400",
    "sg:province":"Albacete",
    "wof:name":"Perona Lopez Valeriano",
    "wof:placetype":"venue"
},
  "geometry": {"coordinates":[-1.699644208,38.5132141113],"type":"Point"}
}