{
  "type": "Feature",
  "properties": {
    "addr:full":"Calle de Murcia, 23 Catral Alicante 03158",
    "addr:housenumber":"23",
    "addr:postcode":"03158",
    "addr:street":"Calle De Murcia",
    "iso:country":"ES",
    "sg:address":"Calle de Murcia, 23",
    "sg:city":"Catral",
    "sg:orig_category":"Empresas De Carpinter\u00cda De Madera",
    "sg:phone":"+34 965 72 30 32",
    "sg:postcode":"03158",
    "sg:province":"Alicante",
    "sg:website":"www.catmader.es",
    "wof:name":"Cat Mader S.l.",
    "wof:placetype":"venue"
},
  "geometry": {"coordinates":[-0.8015390038,38.1696281433],"type":"Point"}
}