{
  "type": "Feature",
  "properties": {
    "iso:country":"ES",
    "sg:address":"Avda Primero De Mayo, 16",
    "sg:city":"Palmas De Gran Canaria",
    "sg:orig_category":"Abogados",
    "sg:phone":"+34 928 38 55 06",
    "sg:postcode":"35002",
    "sg:province":"Las Palmas",
    "wof:name":"Espinosa Juez Sonia",
    "wof:placetype":"venue"
},
  "geometry": {"coordinates":[-15.4184989929,28.1039485931],"type":"Point"}
}