{
  "type": "Feature",
  "properties": {
    "iso:country":"ES",
    "sg:address":"Calle de Ciruelo, 22",
    "sg:city":"Herrera Duque",
    "sg:orig_category":"Procuradores",
    "sg:phone":"+34 924 65 08 89",
    "sg:postcode":"06670",
    "sg:province":"Badajoz",
    "wof:name":"Gil Mu\u00f1oz Consolacion",
    "wof:placetype":"venue"
},
  "geometry": {"coordinates":[-5.0494260788,39.167514801],"type":"Point"}
}