{
  "type": "Feature",
  "properties": {
    "iso:country":"ES",
    "sg:address":"Calle de San Braulio, 2",
    "sg:city":"Zaragoza",
    "sg:orig_category":"Bisuter\u00cda, Joyer\u00cda, Relojer\u00cda (al Por Menor)",
    "sg:phone":"+34 976 39 05 27",
    "sg:postcode":"50003",
    "sg:province":"Zaragoza",
    "wof:name":"Sancho Martin Maria Del Carmen",
    "wof:placetype":"venue"
},
  "geometry": {"coordinates":[-0.8791400194,41.6547584534],"type":"Point"}
}