{
  "type": "Feature",
  "properties": {
    "addr:full":"Avda Marina Espa\u00d1ola, 2 Aduanas Alicante 03730",
    "addr:housenumber":"2",
    "addr:postcode":"03730",
    "addr:street":"Avda Marina Espan\u0303Ola",
    "iso:country":"ES",
    "sg:address":"Avda Marina Espa\u00d1ola, 2",
    "sg:city":"Aduanas",
    "sg:orig_category":"Ropa Para Se\u00d1oras (al Por Menor)",
    "sg:phone":"+34 966 46 01 90",
    "sg:postcode":"03730",
    "sg:province":"Alicante",
    "wof:name":"Clive Bellmann John",
    "wof:placetype":"venue"
},
  "geometry": {"coordinates":[0.1817349941,38.7940139771],"type":"Point"}
}