{
  "type": "Feature",
  "properties": {
    "iso:country":"ES",
    "sg:address":"Calle de San Jose, 9",
    "sg:city":"Valle Trapaga",
    "sg:orig_category":"Muebles, Minoristas",
    "sg:phone":"+34 944 92 22 78",
    "sg:postcode":"48510",
    "sg:province":"Vizcaya",
    "wof:name":"Pablo Alonso Esturo (nuevo Hogar)",
    "wof:placetype":"venue"
},
  "geometry": {"coordinates":[-3.0347440243,43.3032455444],"type":"Point"}
}