{
  "type": "Feature",
  "properties": {
    "iso:country":"ES",
    "sg:address":"Calle de Madrid, S/n",
    "sg:city":"Torrejon Ardoz",
    "sg:orig_category":"Electrodom\u00c9sticos (al Por Menor)",
    "sg:phone":"+34 916 56 21 89",
    "sg:postcode":"28850",
    "sg:province":"Madrid",
    "wof:name":"Perez Rodriguez Jose",
    "wof:placetype":"venue"
},
  "geometry": {"coordinates":[-3.4769740105,40.4629249573],"type":"Point"}
}