{
  "type": "Feature",
  "properties": {
    "iso:country":"ES",
    "sg:address":"Calle de Urbieta, 50",
    "sg:city":"Donostia-san Sebastian",
    "sg:orig_category":"Plomeros",
    "sg:phone":"+34 943 45 21 94",
    "sg:postcode":"20006",
    "sg:province":"Guip\u00f9zcoa",
    "wof:name":"Irizar Argui\u00f1ano Miguel",
    "wof:placetype":"venue"
},
  "geometry": {"coordinates":[-1.9813020229,43.3146057129],"type":"Point"}
}