{
  "type": "Feature",
  "properties": {
    "iso:country":"ES",
    "sg:address":"La Ribera, S/n",
    "sg:city":"Burgos",
    "sg:orig_category":"Rectificaci\u00d3n, Mecanizado, Fresado",
    "sg:phone":"+34 947 47 07 47",
    "sg:postcode":"09007",
    "sg:province":"Burgos",
    "wof:name":"Tmp Construccion De Maquinaria S.a.",
    "wof:placetype":"venue"
},
  "geometry": {"coordinates":[-3.6524159908,42.3495597839],"type":"Point"}
}