{
  "type": "Feature",
  "properties": {
    "iso:country":"ES",
    "sg:address":"Calle de Castelar, 40",
    "sg:city":"Zaragoza",
    "sg:orig_category":"Contenedores (mercanc\u00cdas)",
    "sg:phone":"+34 976 41 53 02",
    "sg:postcode":"50013",
    "sg:province":"Zaragoza",
    "wof:name":"Transportes Tezar S.l.",
    "wof:placetype":"venue"
},
  "geometry": {"coordinates":[-0.871006012,41.6397514343],"type":"Point"}
}