{
  "type": "Feature",
  "properties": {
    "addr:full":"Disseminat, 2 Corro D'avall Barcelona 08520",
    "addr:housenumber":"2",
    "addr:postcode":"08520",
    "addr:street":"Disseminat;D'Avall Barcelona",
    "iso:country":"ES",
    "sg:address":"Disseminat, 2",
    "sg:city":"Corro D'avall",
    "sg:orig_category":"Artes Gr\u00c1ficas, Artes Pl\u00c1sticas (curso)",
    "sg:phone":"+34 938 49 21 79",
    "sg:postcode":"08520",
    "sg:province":"Barcelona",
    "wof:name":"Nu\u00f1ez Y Nebot S.l.",
    "wof:placetype":"venue"
},
  "geometry": {"coordinates":[2.2962567806,41.6326560974],"type":"Point"}
}