{
  "type": "Feature",
  "properties": {
    "iso:country":"ES",
    "sg:address":"Calle de Ontiveros, S/n",
    "sg:city":"Ampudia",
    "sg:orig_category":"Alimentaci\u00d3n General (al Por Menor)",
    "sg:phone":"+34 979 76 80 94",
    "sg:postcode":"34160",
    "sg:province":"Palencia",
    "wof:name":"Aguado Torres Amado",
    "wof:placetype":"venue"
},
  "geometry": {"coordinates":[-4.7792935371,41.9145507812],"type":"Point"}
}