{
  "type": "Feature",
  "properties": {
    "addr:full":"Plaz Catedral, 6 Avila \u00c1vila 05001",
    "addr:housenumber":"6",
    "addr:postcode":"05001",
    "addr:street":"Catedral;A\u0301Vila",
    "iso:country":"ES",
    "sg:address":"Plaz Catedral, 6",
    "sg:city":"Avila",
    "sg:orig_category":"Restaurantes",
    "sg:phone":"+34 920 25 28 85",
    "sg:postcode":"05001",
    "sg:province":"\u00c1vila",
    "wof:name":"Gutierrez Sanchidrian Antonio",
    "wof:placetype":"venue"
},
  "geometry": {"coordinates":[-4.6975421906,40.6562385559],"type":"Point"}
}