{
  "type": "Feature",
  "properties": {
    "iso:country":"ES",
    "sg:address":"Carr Molins, Dels, 21",
    "sg:city":"Cala Millor",
    "sg:orig_category":"Promotores Constructores",
    "sg:phone":"+34 971 58 60 65",
    "sg:postcode":"07560",
    "sg:province":"Islas Baleares",
    "wof:name":"Promociones E Intervenciones Calzado S.l.",
    "wof:placetype":"venue"
},
  "geometry": {"coordinates":[3.3733510971,39.5831985474],"type":"Point"}
}