{
  "type": "Feature",
  "properties": {
    "iso:country":"ES",
    "sg:address":"Carrer de Antonia Canet, 17",
    "sg:city":"Mollet Valles",
    "sg:orig_category":"Carnicer\u00cdas, Carnicer\u00cdas",
    "sg:phone":"+34 935 93 68 44",
    "sg:postcode":"08100",
    "sg:province":"Barcelona",
    "wof:name":"Collado Romero Encarnacion",
    "wof:placetype":"venue"
},
  "geometry": {"coordinates":[2.2113850117,41.5392913818],"type":"Point"}
}