{
  "type": "Feature",
  "properties": {
    "addr:full":"Ctra Sant Cugat, Km. 0003,0 Cerdanyola Valles Barcelona 08290",
    "addr:postcode":"08290",
    "addr:street":"Ctra Sant Cugat Km. 0003,0;Valles Barcelona",
    "iso:country":"ES",
    "sg:address":"Ctra Sant Cugat, Km. 0003,0",
    "sg:city":"Cerdanyola Valles",
    "sg:orig_category":"Porcelanas, Azulejos (fabricaci\u00d3n, Al Por Mayor)",
    "sg:phone":"+34 936 92 48 49",
    "sg:postcode":"08290",
    "sg:province":"Barcelona",
    "wof:name":"Sociedad Anonima Ceramica De Sardanyola",
    "wof:placetype":"venue"
},
  "geometry": {"coordinates":[2.1470150948,41.4924812317],"type":"Point"}
}