{
  "type": "Feature",
  "properties": {
    "iso:country":"ES",
    "sg:address":"C/ Born, 28",
    "sg:city":"Llucmajor",
    "sg:orig_category":"Cristaler\u00cdas",
    "sg:phone":"+34 971 66 29 31",
    "sg:postcode":"07620",
    "sg:province":"Islas Baleares",
    "wof:name":"Cristaleria Ca N'alegria C.b.",
    "wof:placetype":"venue"
},
  "geometry": {"coordinates":[2.8891708851,39.4911613464],"type":"Point"}
}