{
  "type": "Feature",
  "properties": {
    "iso:country":"ES",
    "sg:address":"Avda Jeronimos, S/n",
    "sg:city":"Guadalupe De Maciascoque",
    "sg:orig_category":"Contables",
    "sg:phone":"+34 968 30 55 45",
    "sg:postcode":"30107",
    "sg:province":"Murcia",
    "wof:name":"Ruiz Martinez Juan Manuel",
    "wof:placetype":"venue"
},
  "geometry": {"coordinates":[-1.1736390591,37.9982147217],"type":"Point"}
}