{
  "type": "Feature",
  "properties": {
    "addr:full":"Urb. La Rad, S/n R.a.d. Salamanca 37449",
    "addr:housenumber":"s / n",
    "addr:postcode":"37449",
    "iso:country":"ES",
    "sg:address":"Urb. La Rad, S/n",
    "sg:city":"R.a.d.",
    "sg:orig_category":"Asociaciones Y Clubs Deportivos",
    "sg:phone":"+34 923 17 03 44",
    "sg:postcode":"37449",
    "sg:province":"Salamanca",
    "wof:name":"Suministros Evia S.l.",
    "wof:placetype":"venue"
},
  "geometry": {"coordinates":[-5.8711547852,40.9429244995],"type":"Point"}
}