{
  "type": "Feature",
  "properties": {
    "addr:full":"Calle de Orzan, 47 Coru\u00d1a La Coru\u00f1a 15003",
    "addr:housenumber":"47",
    "addr:postcode":"15003",
    "addr:street":"Calle De Orzan;Corun\u0303A",
    "iso:country":"ES",
    "sg:address":"Calle de Orzan, 47",
    "sg:city":"Coru\u00d1a",
    "sg:orig_category":"Transporte En General",
    "sg:phone":"+34 981 22 21 58",
    "sg:postcode":"15003",
    "sg:province":"La Coru\u00f1a",
    "wof:name":"Anidos Lopez Jose",
    "wof:placetype":"venue"
},
  "geometry": {"coordinates":[-8.4019260406,43.3711967468],"type":"Point"}
}