{
  "type": "Feature",
  "properties": {
    "iso:country":"ES",
    "sg:address":"Calle de Topacio, 15",
    "sg:city":"Valladolid",
    "sg:orig_category":"Agencias Y Agentes Comerciales, Representantes",
    "sg:phone":"+34 983 29 76 09",
    "sg:postcode":"47012",
    "sg:province":"Valladolid",
    "wof:name":"Faustino Gonzalez E Hijos S.l.",
    "wof:placetype":"venue"
},
  "geometry": {"coordinates":[-4.7127599716,41.6157035828],"type":"Point"}
}