{
  "type": "Feature",
  "properties": {
    "addr:full":"Pol Ind San Cayetano, S/n Churriana Vega Granada 18194",
    "addr:housenumber":"s",
    "addr:postcode":"18194",
    "addr:street":"Cayetano;/ N",
    "iso:country":"ES",
    "sg:address":"Pol Ind San Cayetano, S/n",
    "sg:city":"Churriana Vega",
    "sg:orig_category":"Productos Qu\u00cdmicos (fabricaci\u00d3n, Al Por Mayor)",
    "sg:phone":"+34 958 55 09 00",
    "sg:postcode":"18194",
    "sg:province":"Granada",
    "wof:name":"Productos Quimicos Hifersa S. A.",
    "wof:placetype":"venue"
},
  "geometry": {"coordinates":[-3.6773679256,37.1503562927],"type":"Point"}
}