{
  "type": "Feature",
  "properties": {
    "addr:full":"Calle de Ca\u00d1o, 8 Mula Murcia 30170",
    "addr:housenumber":"8",
    "addr:postcode":"30170",
    "addr:street":"Calle De Can\u0303O",
    "iso:country":"ES",
    "sg:address":"Calle de Ca\u00d1o, 8",
    "sg:city":"Mula",
    "sg:orig_category":"Art\u00cdculos De Regalo (al Por Menor)",
    "sg:phone":"+34 968 66 04 45",
    "sg:postcode":"30170",
    "sg:province":"Murcia",
    "wof:name":"Copero De Mula S.l.",
    "wof:placetype":"venue"
},
  "geometry": {"coordinates":[-1.4897110462,38.0405578613],"type":"Point"}
}