{
  "type": "Feature",
  "properties": {
    "addr:full":"Cmno Moncada, 79 Valencia Valencia 46025",
    "addr:housenumber":"79",
    "addr:postcode":"46025",
    "addr:street":"Cmno Moncada",
    "iso:country":"ES",
    "sg:address":"Cmno Moncada, 79",
    "sg:city":"Valencia",
    "sg:orig_category":"Tintes (fabricaci\u00d3n, Al Por Mayor)",
    "sg:phone":"+34 963 47 92 78",
    "sg:postcode":"46025",
    "sg:province":"Valencia",
    "wof:name":"Grupo De Tintorerias 2001 S.l.",
    "wof:placetype":"venue"
},
  "geometry": {"coordinates":[-0.3796339929,39.4927558899],"type":"Point"}
}