{
  "type": "Feature",
  "properties": {
    "addr:full":"Carrer de Bertran I Musitu, 53 Viladecans Barcelona 08840",
    "addr:housenumber":"53",
    "addr:postcode":"08840",
    "addr:street":"Carrer De Bertran I Musitu",
    "iso:country":"ES",
    "sg:address":"Carrer de Bertran I Musitu, 53",
    "sg:city":"Viladecans",
    "sg:orig_category":"Cristaler\u00cdas",
    "sg:phone":"+34 936 58 15 99",
    "sg:postcode":"08840",
    "sg:province":"Barcelona",
    "wof:name":"Gracia Hernandez Manuel",
    "wof:placetype":"venue"
},
  "geometry": {"coordinates":[2.0260510445,41.3159484863],"type":"Point"}
}