{
  "type": "Feature",
  "properties": {
    "iso:country":"ES",
    "sg:address":"Goierri Kalea, 12",
    "sg:city":"Ordizia",
    "sg:orig_category":"Agentes Generales De Seguros",
    "sg:phone":"+34 943 16 14 15",
    "sg:postcode":"20240",
    "sg:province":"Guip\u00f9zcoa",
    "wof:name":"Rodriguez Cardesin Carlos",
    "wof:placetype":"venue"
},
  "geometry": {"coordinates":[-2.1802461147,43.0527687073],"type":"Point"}
}