{
  "type": "Feature",
  "properties": {
    "iso:country":"ES",
    "sg:address":"Calle de Serreta, 19",
    "sg:city":"Cartagena",
    "sg:orig_category":"Condimentos, Especias, Vinagres, Salsas Preparadas (fabricaci\u00d3n, Al Por Mayor)",
    "sg:phone":"+34 968 50 27 86",
    "sg:postcode":"30201",
    "sg:province":"Murcia",
    "wof:name":"Boj Cami\u00f1a Joaquin",
    "wof:placetype":"venue"
},
  "geometry": {"coordinates":[-0.9842969775,37.6043434143],"type":"Point"}
}