{
  "type": "Feature",
  "properties": {
    "iso:country":"ES",
    "sg:address":"Carrer de Roger De Lluria, 42",
    "sg:city":"Barcelona",
    "sg:orig_category":"Seguridad Social",
    "sg:phone":"+34 933 17 72 12",
    "sg:postcode":"08009",
    "sg:province":"Barcelona",
    "wof:name":"Mutua De Accidentes De Trabajo Y Enfermedades Profesionales De La Seguridad Social Num 25",
    "wof:placetype":"venue"
},
  "geometry": {"coordinates":[2.1703529358,41.3921813965],"type":"Point"}
}