{
  "type": "Feature",
  "properties": {
    "addr:full":"Calle de Curtidores (los), 5 Segovia Segovia 40004",
    "addr:housenumber":"5",
    "addr:postcode":"40004",
    "addr:street":"Calle De Curtidores Los",
    "iso:country":"ES",
    "sg:address":"Calle de Curtidores (los), 5",
    "sg:city":"Segovia",
    "sg:orig_category":"Asilos De Ancianos. Centros Privados",
    "sg:phone":"+34 921 43 15 47",
    "sg:postcode":"40004",
    "sg:province":"Segovia",
    "sg:website":"www.clece.es",
    "wof:name":"Clecer S.a.",
    "wof:placetype":"venue"
},
  "geometry": {"coordinates":[-4.1178050041,40.9438018799],"type":"Point"}
}