{
  "type": "Feature",
  "properties": {
    "addr:full":"Calle de General Asensio Cabanillas, 15 Madrid Madrid 28003",
    "addr:housenumber":"15",
    "addr:postcode":"madrid;28003",
    "addr:street":"Calle De General Asensio Cabanillas",
    "iso:country":"ES",
    "sg:address":"Calle de General Asensio Cabanillas, 15",
    "sg:city":"Madrid",
    "sg:orig_category":"Comit\u00c9s De Organizaci\u00d3n De Exposiciones, Ferias, Salones",
    "sg:phone":"+34 915 33 76 45",
    "sg:postcode":"28003",
    "sg:province":"Madrid",
    "wof:name":"Delegacion Mf S.l.",
    "wof:placetype":"venue"
},
  "geometry": {"coordinates":[-3.7153530121,40.444770813],"type":"Point"}
}