{
  "type": "Feature",
  "properties": {
    "iso:country":"ES",
    "sg:address":"C/ Rafael Javaloyes Alema\u00d1, 5",
    "sg:city":"Elche",
    "sg:orig_category":"Art\u00cdculos De Madera (fabricaci\u00d3n Y Al Por Mayor)",
    "sg:phone":"+34 965 45 21 08",
    "sg:postcode":"03203",
    "sg:province":"Alicante",
    "wof:name":"Pi\u00f1ol Guillo Ramon",
    "wof:placetype":"venue"
},
  "geometry": {"coordinates":[-0.6837049723,38.268371582],"type":"Point"}
}