{
  "type": "Feature",
  "properties": {
    "iso:country":"ES",
    "sg:address":"Calle de Padilla, 6",
    "sg:city":"Madrid",
    "sg:orig_category":"Obras Y Organismos Sociales",
    "sg:phone":"+34 915 77 32 03",
    "sg:postcode":"28006",
    "sg:province":"Madrid",
    "wof:name":"Fundacion Luca De Tena Patronato Casa De Nazareth",
    "wof:placetype":"venue"
},
  "geometry": {"coordinates":[-3.6861400604,40.4315567017],"type":"Point"}
}