{
  "type": "Feature",
  "properties": {
    "iso:country":"ES",
    "sg:address":"Toribio Etxebarria Kalea, 13",
    "sg:city":"Eibar",
    "sg:orig_category":"Confiter\u00cdas, Chocolater\u00cdas (al Por Menor)",
    "sg:phone":"+34 943 20 63 22",
    "sg:postcode":"20600",
    "sg:province":"Guip\u00f9zcoa",
    "wof:name":"Santas Fernandez Isabel",
    "wof:placetype":"venue"
},
  "geometry": {"coordinates":[-2.4723229408,43.1851119995],"type":"Point"}
}