{
  "type": "Feature",
  "properties": {
    "addr:full":"Calle de Agustina De Aragon, 12 Valencia Valencia 46017",
    "addr:housenumber":"12",
    "addr:postcode":"46017",
    "addr:street":"Calle De Agustina De Aragon",
    "iso:country":"ES",
    "sg:address":"Calle de Agustina De Aragon, 12",
    "sg:city":"Valencia",
    "sg:orig_category":"Asesor\u00cda Sobre Comunicaci\u00d3n De Empresas",
    "sg:phone":"+34 963 77 82 29",
    "sg:postcode":"46017",
    "sg:province":"Valencia",
    "sg:website":"www.jegabi.com",
    "wof:name":"Servicios Y Gestion Empresarial S.l.",
    "wof:placetype":"venue"
},
  "geometry": {"coordinates":[-0.3901880085,39.4556541443],"type":"Point"}
}