{
  "type": "Feature",
  "properties": {
    "iso:country":"ES",
    "sg:address":"Rua Emilia Pardo Bazan, 48",
    "sg:city":"Allariz",
    "sg:orig_category":"Masajistas Kinesiterapeutas",
    "sg:phone":"+34 988 44 10 65",
    "sg:postcode":"32660",
    "sg:province":"Ourense",
    "wof:name":"Devesa Quintaidos Maria Rosa",
    "wof:placetype":"venue"
},
  "geometry": {"coordinates":[-7.7991919518,42.1877555847],"type":"Point"}
}