{
  "type": "Feature",
  "properties": {
    "iso:country":"ES",
    "sg:address":"Calle de Sancho Panza, 15",
    "sg:city":"Miguel Esteban",
    "sg:orig_category":"Confecci\u00d3n De Trajes Para Se\u00d1oras",
    "sg:phone":"+34 925 56 73 11",
    "sg:postcode":"45830",
    "sg:province":"Toledo",
    "wof:name":"Gallego Tebas Maria Del Pilar",
    "wof:placetype":"venue"
},
  "geometry": {"coordinates":[-3.0717689991,39.5283546448],"type":"Point"}
}