{
  "type": "Feature",
  "properties": {
    "iso:country":"ES",
    "sg:address":"Carrer de Feliu I Codina, 12",
    "sg:city":"Barcelona",
    "sg:orig_category":"Servicio De Salud",
    "sg:phone":"+34 934 29 97 97",
    "sg:postcode":"08031",
    "sg:province":"Barcelona",
    "wof:name":"Garcia Garcia Santiago",
    "wof:placetype":"venue"
},
  "geometry": {"coordinates":[2.1605548859,41.4324035645],"type":"Point"}
}