{
  "type": "Feature",
  "properties": {
    "addr:full":"Calle de Castello, 23 Madrid Madrid 28001",
    "addr:housenumber":"23",
    "addr:postcode":"madrid;28001",
    "addr:street":"Calle De Castello",
    "iso:country":"ES",
    "sg:address":"Calle de Castello, 23",
    "sg:city":"Madrid",
    "sg:orig_category":"Agencias Y Asesores De Publicidad",
    "sg:phone":"+34 914 35 53 55",
    "sg:postcode":"28001",
    "sg:province":"Madrid",
    "wof:name":"Diana Promocion S.a.",
    "wof:placetype":"venue"
},
  "geometry": {"coordinates":[-3.6817469597,40.4244728088],"type":"Point"}
}