{
  "type": "Feature",
  "properties": {
    "addr:full":"Carrer de Guillem De Montcada (de), 26 Salou Tarragona 43840",
    "addr:housenumber":"26",
    "addr:postcode":"43840",
    "addr:street":"Carrer De Guillem De Montcada De",
    "iso:country":"ES",
    "sg:address":"Carrer de Guillem De Montcada (de), 26",
    "sg:city":"Salou",
    "sg:orig_category":"Alimentaci\u00d3n General (al Por Menor)",
    "sg:phone":"+34 977 38 36 26",
    "sg:postcode":"43840",
    "sg:province":"Tarragona",
    "wof:name":"Marine Ferre Jorge",
    "wof:placetype":"venue"
},
  "geometry": {"coordinates":[1.1252119541,41.0770263672],"type":"Point"}
}