{
  "type": "Feature",
  "properties": {
    "addr:full":"Calle de Cerro De Los Machos, 16 Granada Granada 18008",
    "addr:housenumber":"16",
    "addr:postcode":"18008",
    "addr:street":"Calle De Cerro De Los Machos",
    "iso:country":"ES",
    "sg:address":"Calle de Cerro De Los Machos, 16",
    "sg:city":"Granada",
    "sg:orig_category":"Agencias Y Agentes Comerciales, Representantes",
    "sg:phone":"+34 958 12 55 87",
    "sg:postcode":"18008",
    "sg:province":"Granada",
    "wof:name":"Colinet Casta\u00f1o Rafael",
    "wof:placetype":"venue"
},
  "geometry": {"coordinates":[-3.5846555233,37.1594467163],"type":"Point"}
}