{
  "type": "Feature",
  "properties": {
    "addr:full":"Av. Marques Villanueva Del Prado, S/n Puerto Cruz Santa Cruz De Tenerife 38400",
    "addr:housenumber":"s / n",
    "addr:postcode":"38400",
    "addr:street":"Av. Marques;Del Prado;Cruz",
    "iso:country":"ES",
    "sg:address":"Av. Marques Villanueva Del Prado, S/n",
    "sg:city":"Puerto Cruz",
    "sg:orig_category":"Alquiler De Veh\u00cdculos: Turismos Y Utilitarios",
    "sg:phone":"+34 922 38 82 74",
    "sg:postcode":"38400",
    "sg:province":"Santa Cruz De Tenerife",
    "wof:name":"Viajes Arco S.l.",
    "wof:placetype":"venue"
},
  "geometry": {"coordinates":[-16.5422172546,28.4132347107],"type":"Point"}
}