{
  "type": "Feature",
  "properties": {
    "addr:full":"Av Josep Fontcuberta, 155 Caldes Montbui Barcelona 08140",
    "addr:housenumber":"155",
    "addr:postcode":"08140",
    "addr:street":"Av Josep Fontcuberta;Montbui Barcelona",
    "iso:country":"ES",
    "sg:address":"Av Josep Fontcuberta, 155",
    "sg:city":"Caldes Montbui",
    "sg:orig_category":"Inform\u00c1tica: Consultores",
    "sg:phone":"+34 938 62 66 81",
    "sg:postcode":"08140",
    "sg:province":"Barcelona",
    "wof:name":"Variant Soft S.l.",
    "wof:placetype":"venue"
},
  "geometry": {"coordinates":[2.1705598831,41.6338806152],"type":"Point"}
}