{
  "type": "Feature",
  "properties": {
    "addr:full":"Avda General Fanjul, 90 Madrid Madrid 28044",
    "addr:housenumber":"90",
    "addr:postcode":"madrid;28044",
    "addr:street":"Avda General Fanjul",
    "iso:country":"ES",
    "sg:address":"Avda General Fanjul, 90",
    "sg:city":"Madrid",
    "sg:orig_category":"Encuadernaci\u00d3n E Impresi\u00d3n De Folletos",
    "sg:phone":"+34 917 06 85 50",
    "sg:postcode":"28044",
    "sg:province":"Madrid",
    "wof:name":"Lozano Blanco Maria Del Carmen",
    "wof:placetype":"venue"
},
  "geometry": {"coordinates":[-3.7791199684,40.3812866211],"type":"Point"}
}