{
  "type": "Feature",
  "properties": {
    "addr:full":"Poli Poligono Industrial El Paramo, 7 Pe\u00d1ueco Vizcaya 48800",
    "addr:housenumber":"7",
    "addr:postcode":"48800",
    "addr:street":"Poligono Industrial El Paramo",
    "iso:country":"ES",
    "sg:address":"Poli Poligono Industrial El Paramo, 7",
    "sg:city":"Pe\u00d1ueco",
    "sg:orig_category":"Centros Empresariales",
    "sg:phone":"+34 946 80 19 34",
    "sg:postcode":"48800",
    "sg:province":"Vizcaya",
    "sg:website":"www.urbegi.com",
    "wof:name":"Urbegi Iniciativas Sociales Sll",
    "wof:placetype":"venue"
},
  "geometry": {"coordinates":[-3.196199894,43.1932907104],"type":"Point"}
}