{
  "type": "Feature",
  "properties": {
    "addr:full":"Pl Zurbaran, 1 Barcelona Barcelona 08035",
    "addr:housenumber":"1",
    "addr:postcode":"08035",
    "addr:street":"Pl Zurbaran",
    "iso:country":"ES",
    "sg:address":"Pl Zurbaran, 1",
    "sg:city":"Barcelona",
    "sg:orig_category":"Estancos",
    "sg:phone":"+34 934 28 10 95",
    "sg:postcode":"08035",
    "sg:province":"Barcelona",
    "wof:name":"Hernandez Pau Ana Maria",
    "wof:placetype":"venue"
},
  "geometry": {"coordinates":[2.1434080601,41.4296646118],"type":"Point"}
}