{
  "type": "Feature",
  "properties": {
    "addr:full":"Carrer de Morell, 20 Reus Tarragona 43203",
    "addr:housenumber":"20",
    "addr:postcode":"43203",
    "addr:street":"Carrer De Morell",
    "iso:country":"ES",
    "sg:address":"Carrer de Morell, 20",
    "sg:city":"Reus",
    "sg:orig_category":"Imprenta",
    "sg:phone":"+34 977 34 13 34",
    "sg:postcode":"43203",
    "sg:province":"Tarragona",
    "wof:name":"Grafiques Gama Reus Scp",
    "wof:placetype":"venue"
},
  "geometry": {"coordinates":[1.1133539677,41.160949707],"type":"Point"}
}