{
  "type": "Feature",
  "properties": {
    "addr:full":"Calle de Navamonjas, 15 Galapagar Madrid 28260",
    "addr:housenumber":"15",
    "addr:postcode":"28260",
    "addr:street":"Calle De Navamonjas",
    "iso:country":"ES",
    "sg:address":"Calle de Navamonjas, 15",
    "sg:city":"Galapagar",
    "sg:orig_category":"Hospitales",
    "sg:phone":"+34 918 56 93 96",
    "sg:postcode":"28260",
    "sg:province":"Madrid",
    "wof:name":"Coloplast Productos Medicos S.a.",
    "wof:placetype":"venue"
},
  "geometry": {"coordinates":[-3.9853770733,40.5851211548],"type":"Point"}
}