{
  "type": "Feature",
  "properties": {
    "iso:country":"ES",
    "sg:address":"Cmno Cabaldos, 60",
    "sg:city":"Zaragoza",
    "sg:orig_category":"Mec\u00c1nico Del Autom\u00d3vil",
    "sg:phone":"+34 976 49 52 99",
    "sg:postcode":"50013",
    "sg:province":"Zaragoza",
    "wof:name":"Serviauto S. Coop. Ltda.",
    "wof:placetype":"venue"
},
  "geometry": {"coordinates":[-0.8690969944,41.6403694153],"type":"Point"}
}