{
  "type": "Feature",
  "properties": {
    "addr:full":"Pda Merce, 8 Girona Girona 17004",
    "addr:housenumber":"8",
    "addr:postcode":"17004",
    "iso:country":"ES",
    "sg:address":"Pda Merce, 8",
    "sg:city":"Girona",
    "sg:orig_category":"Organizaciones Internacionales",
    "sg:phone":"+34 972 20 49 80",
    "sg:postcode":"17004",
    "sg:province":"Girona",
    "wof:name":"Caritas Diocesana De Gerona",
    "wof:placetype":"venue"
},
  "geometry": {"coordinates":[2.824739933,41.981880188],"type":"Point"}
}