{
  "type": "Feature",
  "properties": {
    "addr:full":"Calle de Villanueva, 1 Alcala De Xivert Castell\u00f3n 12570",
    "addr:housenumber":"1",
    "addr:postcode":"12570",
    "addr:street":"Calle De Villanueva",
    "iso:country":"ES",
    "sg:address":"Calle de Villanueva, 1",
    "sg:city":"Alcala De Xivert",
    "sg:orig_category":"Ense\u00d1anza, Formaci\u00d3n Profesional: Aprendizaje",
    "sg:phone":"+34 964 41 11 36",
    "sg:postcode":"12570",
    "sg:province":"Castell\u00f3n",
    "wof:name":"Generalitat Valenciana",
    "wof:placetype":"venue"
},
  "geometry": {"coordinates":[0.2378000021,40.2983894348],"type":"Point"}
}