{
  "type": "Feature",
  "properties": {
    "addr:full":"Calle de Real, S/n Ba\u00e7os De Rio Tobia La Rioja 26320",
    "addr:housenumber":"s / n",
    "addr:postcode":"26320",
    "addr:street":"Calle De Real;Tobia;Rioja",
    "iso:country":"ES",
    "sg:address":"Calle de Real, S/n",
    "sg:city":"Ba\u00e7os De Rio Tobia",
    "sg:orig_category":"Charcuter\u00cdas (al Por Menor)",
    "sg:phone":"+34 941 37 41 05",
    "sg:postcode":"26320",
    "sg:province":"La Rioja",
    "wof:name":"Villoslada Uru\u00f1uuela Miguel Angel",
    "wof:placetype":"venue"
},
  "geometry": {"coordinates":[-2.7588710785,42.3386688232],"type":"Point"}
}