{
  "type": "Feature",
  "properties": {
    "addr:full":"Calle de Concepcion Arenal, 18 Guarda Pontevedra 36780",
    "addr:housenumber":"18",
    "addr:postcode":"36780",
    "addr:street":"Calle De Concepcion Arenal",
    "iso:country":"ES",
    "sg:address":"Calle de Concepcion Arenal, 18",
    "sg:city":"Guarda",
    "sg:orig_category":"Bazares, Art\u00cdculos De Limpieza Y De Cocina (al Por Menor)",
    "sg:phone":"+34 986 61 44 53",
    "sg:postcode":"36780",
    "sg:province":"Pontevedra",
    "wof:name":"Bazar Arenal C.b.",
    "wof:placetype":"venue"
},
  "geometry": {"coordinates":[-8.8721590042,41.9003410339],"type":"Point"}
}