{
  "type": "Feature",
  "properties": {
    "iso:country":"ES",
    "sg:address":"Calle de Palustre El, 16",
    "sg:city":"Malaga",
    "sg:orig_category":"Asociaciones, Organismos Culturales Y Socioeducativos",
    "sg:phone":"+34 952 29 00 35",
    "sg:postcode":"29017",
    "sg:province":"M\u00e1laga",
    "wof:name":"Pe\u00f1a Recreativa El Palustre",
    "wof:placetype":"venue"
},
  "geometry": {"coordinates":[-4.3598031998,36.7236022949],"type":"Point"}
}