{
  "type": "Feature",
  "properties": {
    "addr:full":"Avda Padre Isla, 2 Le\u00f3n Le\u00f3n 24002",
    "addr:housenumber":"2",
    "addr:postcode":"24002",
    "addr:street":"Avda Padre Isla;Leo\u0301N",
    "iso:country":"ES",
    "sg:address":"Avda Padre Isla, 2",
    "sg:city":"Le\u00f3n",
    "sg:orig_category":"Zapatos (al Por Menor)",
    "sg:phone":"+34 987 27 01 21",
    "sg:postcode":"24002",
    "sg:province":"Le\u00f3n",
    "sg:website":"www.calzadoslopezsl.com",
    "wof:name":"Lopez Vizan Hermanos S.l.",
    "wof:placetype":"venue"
},
  "geometry": {"coordinates":[-5.5718097687,42.5985374451],"type":"Point"}
}