{
  "type": "Feature",
  "properties": {
    "iso:country":"ES",
    "sg:address":"Rua Alfonso Senra, 30",
    "sg:city":"Ordes",
    "sg:orig_category":"Institutos De Belleza",
    "sg:phone":"+34 981 68 12 54",
    "sg:postcode":"15680",
    "sg:province":"La Coru\u00f1a",
    "wof:name":"Boquete Remui\u00d1a Jose Antonio",
    "wof:placetype":"venue"
},
  "geometry": {"coordinates":[-8.4057979584,43.0798416138],"type":"Point"}
}