{
  "type": "Feature",
  "properties": {
    "iso:country":"ES",
    "sg:address":"Trav De Gracia, 115",
    "sg:city":"Barcelona",
    "sg:orig_category":"Pod\u00d3logos: Pedicuros",
    "sg:phone":"+34 932 37 83 13",
    "sg:postcode":"08012",
    "sg:province":"Barcelona",
    "wof:name":"Infante Antich Jordi",
    "wof:placetype":"venue"
},
  "geometry": {"coordinates":[2.1543240547,41.3993148804],"type":"Point"}
}