{
  "type": "Feature",
  "properties": {
    "addr:full":"Calle de Nuria, 10 Madrid Madrid 28034",
    "addr:housenumber":"10",
    "addr:postcode":"madrid;28034",
    "addr:street":"Calle De Nuria",
    "iso:country":"ES",
    "sg:address":"Calle de Nuria, 10",
    "sg:city":"Madrid",
    "sg:orig_category":"Pescader\u00cdas (al Por Menor)",
    "sg:phone":"+34 917 34 07 98",
    "sg:postcode":"28034",
    "sg:province":"Madrid",
    "wof:name":"Garcia Heredero Francisco",
    "wof:placetype":"venue"
},
  "geometry": {"coordinates":[-3.7055170536,40.4920425415],"type":"Point"}
}