{
  "type": "Feature",
  "properties": {
    "iso:country":"ES",
    "sg:address":"C/ Lluna, 96",
    "sg:city":"Cerdanyola Valles",
    "sg:orig_category":"Inmobiliaria (agencias)",
    "sg:phone":"+34 935 80 42 74",
    "sg:postcode":"08290",
    "sg:province":"Barcelona",
    "wof:name":"Inmobles La Tevesa S.l",
    "wof:placetype":"venue"
},
  "geometry": {"coordinates":[2.1240227222,41.4975166321],"type":"Point"}
}