{
  "type": "Feature",
  "properties": {
    "addr:full":"Po Constitucion, 76 Pinoso Alicante 03650",
    "addr:housenumber":"76",
    "addr:postcode":"03650",
    "addr:street":"Constitucion",
    "iso:country":"ES",
    "sg:address":"Po Constitucion, 76",
    "sg:city":"Pinoso",
    "sg:orig_category":"Promotores Constructores",
    "sg:phone":"+34 965 47 80 27",
    "sg:postcode":"03650",
    "sg:province":"Alicante",
    "wof:name":"Montpedra Desarrollo Inmobiliario S.l.u.",
    "wof:placetype":"venue"
},
  "geometry": {"coordinates":[-1.0416959524,38.3983192444],"type":"Point"}
}