{
  "type": "Feature",
  "properties": {
    "addr:full":"Ptda Partida San Bernabe, S/n Alzira Valencia 46600",
    "addr:housenumber":"s / n",
    "addr:postcode":"46600",
    "addr:street":"Ptda Partida San Bernabe",
    "iso:country":"ES",
    "sg:address":"Ptda Partida San Bernabe, S/n",
    "sg:city":"Alzira",
    "sg:orig_category":"Productos Alimentarios",
    "sg:phone":"+34 962 40 38 67",
    "sg:postcode":"46600",
    "sg:province":"Valencia",
    "wof:name":"Vidal Mas Antonio",
    "wof:placetype":"venue"
},
  "geometry": {"coordinates":[-0.4241290092,39.1648368835],"type":"Point"}
}