{
  "type": "Feature",
  "properties": {
    "iso:country":"ES",
    "sg:address":"Calle de Feria Jerez, 3",
    "sg:city":"Fuengirola",
    "sg:orig_category":"Fabricaci\u00d3n De Clavijas Y De Pistones",
    "sg:phone":"+34 952 46 46 54",
    "sg:postcode":"29640",
    "sg:province":"M\u00e1laga",
    "sg:website":"www.tuttoparquet.com",
    "wof:name":"Anzani  Walter",
    "wof:placetype":"venue"
},
  "geometry": {"coordinates":[-4.6211557388,36.547542572],"type":"Point"}
}