{
  "type": "Feature",
  "properties": {
    "iso:country":"ES",
    "sg:address":"Plaz Mayor, 9",
    "sg:city":"Le\u00f3n",
    "sg:orig_category":"Molduras, Junquillos, Listones Y Molduras Perforadas",
    "sg:phone":"+34 987 20 90 15",
    "sg:postcode":"24003",
    "sg:province":"Le\u00f3n",
    "wof:name":"Ahmet Akinci Seyit",
    "wof:placetype":"venue"
},
  "geometry": {"coordinates":[-5.5682911873,42.5982131958],"type":"Point"}
}