{
  "type": "Feature",
  "properties": {
    "addr:full":"Calle de Tomillar El (urb El Mirador), 93 Marbella M\u00e1laga 29600",
    "addr:housenumber":"93",
    "addr:postcode":"29600",
    "addr:street":"Calle De Tomillar El Urb El Mirador;Ma\u0301Laga",
    "iso:country":"ES",
    "sg:address":"Calle de Tomillar El (urb El Mirador), 93",
    "sg:city":"Marbella",
    "sg:orig_category":"Doctores En Medicina",
    "sg:phone":"+34 952 86 22 87",
    "sg:postcode":"29600",
    "sg:province":"M\u00e1laga",
    "wof:name":"Madue\u00f1o Garcia Maria Antonia",
    "wof:placetype":"venue"
},
  "geometry": {"coordinates":[-4.8833007812,36.5079956055],"type":"Point"}
}