{
  "type": "Feature",
  "properties": {
    "addr:full":"Calle de Nueva, 13 Carboneras Almer\u00eda 04140",
    "addr:housenumber":"13",
    "addr:postcode":"04140",
    "addr:street":"Calle De Nueva",
    "iso:country":"ES",
    "sg:address":"Calle de Nueva, 13",
    "sg:city":"Carboneras",
    "sg:orig_category":"Supermercados Y Hipermercados",
    "sg:phone":"+34 950 45 45 32",
    "sg:postcode":"04140",
    "sg:province":"Almer\u00eda",
    "wof:name":"Soto Belmonte Francico",
    "wof:placetype":"venue"
},
  "geometry": {"coordinates":[-1.8946540356,36.9971847534],"type":"Point"}
}