{
  "type": "Feature",
  "properties": {
    "addr:full":"Ctra Sant Climent, 94 Viladecans Barcelona 08840",
    "addr:housenumber":"94",
    "addr:postcode":"08840",
    "addr:street":"Ctra Sant Climent",
    "iso:country":"ES",
    "sg:address":"Ctra Sant Climent, 94",
    "sg:city":"Viladecans",
    "sg:orig_category":"Suministros Para Hoteles",
    "sg:phone":"+34 936 58 77 03",
    "sg:postcode":"08840",
    "sg:province":"Barcelona",
    "wof:name":"Comercial Hostelera Fred Pino S.l.",
    "wof:placetype":"venue"
},
  "geometry": {"coordinates":[2.0135800838,41.3247489929],"type":"Point"}
}