{
  "type": "Feature",
  "properties": {
    "iso:country":"ES",
    "sg:address":"Calle de Ruise\u00d1or, 11",
    "sg:city":"Granada",
    "sg:orig_category":"Peluqueros: De Se\u00d1oras",
    "sg:phone":"+34 958 20 30 15",
    "sg:postcode":"18014",
    "sg:province":"Granada",
    "wof:name":"Perez Cui\u00f1as Carina",
    "wof:placetype":"venue"
},
  "geometry": {"coordinates":[-3.6099369526,37.1856155396],"type":"Point"}
}