{
  "type": "Feature",
  "properties": {
    "iso:country":"ES",
    "sg:address":"Carrer de Col.legi, 21",
    "sg:city":"Terrassa",
    "sg:orig_category":"Ense\u00d1anza: Turismo, Cocina, Hosteler\u00cda",
    "sg:phone":"+34 937 33 32 37",
    "sg:postcode":"08221",
    "sg:province":"Barcelona",
    "sg:website":"www.xup-xup.com",
    "wof:name":"Xup-xup Falacassola S.l.",
    "wof:placetype":"venue"
},
  "geometry": {"coordinates":[2.0112149715,41.5595283508],"type":"Point"}
}