{
  "type": "Feature",
  "properties": {
    "addr:full":"Plaz Espa\u00d1a, 5 Castellote Teruel 44560",
    "addr:housenumber":"5",
    "addr:postcode":"44560",
    "addr:street":"Plaz Espan\u0303A",
    "iso:country":"ES",
    "sg:address":"Plaz Espa\u00d1a, 5",
    "sg:city":"Castellote",
    "sg:orig_category":"Reposter\u00cdas",
    "sg:phone":"+34 978 88 76 36",
    "sg:postcode":"44560",
    "sg:province":"Teruel",
    "wof:name":"Figueras Garin Alicia Maria Teresa",
    "wof:placetype":"venue"
},
  "geometry": {"coordinates":[-0.3181439936,40.7997589111],"type":"Point"}
}