{
  "type": "Feature",
  "properties": {
    "addr:full":"Cno. R. Caya, S/n Badajoz Badajoz 06006",
    "addr:housenumber":"s",
    "addr:postcode":"06006",
    "addr:street":"R. Caya;/ N",
    "iso:country":"ES",
    "sg:address":"Cno. R. Caya, S/n",
    "sg:city":"Badajoz",
    "sg:orig_category":"Poller\u00cda Y Caza (al Por Menor)",
    "sg:phone":"+34 924 14 01 99",
    "sg:postcode":"06006",
    "sg:province":"Badajoz",
    "wof:name":"Huevos Marma S.l.",
    "wof:placetype":"venue"
},
  "geometry": {"coordinates":[-7.0317192078,38.9165992737],"type":"Point"}
}