{
  "type": "Feature",
  "properties": {
    "addr:full":"Calle de Santa Barbara, 39 Monzon Huesca 22400",
    "addr:housenumber":"39",
    "addr:postcode":"22400",
    "addr:street":"Calle De Santa Barbara",
    "iso:country":"ES",
    "sg:address":"Calle de Santa Barbara, 39",
    "sg:city":"Monzon",
    "sg:orig_category":"Molduras, Junquillos, Listones Y Molduras Perforadas",
    "sg:phone":"+34 974 40 49 68",
    "sg:postcode":"22400",
    "sg:province":"Huesca",
    "wof:name":"Ferriz Ari\u00f1o Pablo",
    "wof:placetype":"venue"
},
  "geometry": {"coordinates":[0.195896998,41.9107933044],"type":"Point"}
}