{
  "type": "Feature",
  "properties": {
    "addr:full":"Avda Martinez De Velasco, 51 Huesca Huesca 22004",
    "addr:housenumber":"51",
    "addr:postcode":"22004",
    "addr:street":"Avda Martinez De Velasco",
    "iso:country":"ES",
    "sg:address":"Avda Martinez De Velasco, 51",
    "sg:city":"Huesca",
    "sg:orig_category":"Iglesia Cat\u00d3lica",
    "sg:phone":"+34 974 21 03 59",
    "sg:postcode":"22004",
    "sg:province":"Huesca",
    "wof:name":"Compania Hijas De La Caridad De San Vicente De Paul Provincia De Barcelona Curia Provincial",
    "wof:placetype":"venue"
},
  "geometry": {"coordinates":[-0.416918993,42.1317100525],"type":"Point"}
}