{
  "type": "Feature",
  "properties": {
    "iso:country":"ES",
    "sg:address":"Calle de Mayor, 88",
    "sg:city":"Alberca De Las Torres",
    "sg:orig_category":"Asociaciones Y Clubs Deportivos",
    "sg:phone":"+34 968 84 70 01",
    "sg:postcode":"30150",
    "sg:province":"Murcia",
    "wof:name":"Ramirez Martinez Jeronima",
    "wof:placetype":"venue"
},
  "geometry": {"coordinates":[-1.1428819895,37.9413833618],"type":"Point"}
}