{
  "type": "Feature",
  "properties": {
    "addr:full":"Pol. Palancares, S/n Cuenca Cuenca 16003",
    "addr:housenumber":"/ n",
    "addr:postcode":"16003",
    "addr:street":"Palancares S",
    "iso:country":"ES",
    "sg:address":"Pol. Palancares, S/n",
    "sg:city":"Cuenca",
    "sg:orig_category":"Empresas De Carpinter\u00cda",
    "sg:phone":"+34 969 23 24 75",
    "sg:postcode":"16003",
    "sg:province":"Cuenca",
    "wof:name":"Bascu\u00f1an De La Fuente Jose Angel",
    "wof:placetype":"venue"
},
  "geometry": {"coordinates":[-2.1361989975,40.0586967468],"type":"Point"}
}