{
  "type": "Feature",
  "properties": {
    "addr:full":"Avda Generalisimo, 28 Proba Lugo 27650",
    "addr:housenumber":"28",
    "addr:postcode":"27650",
    "addr:street":"Avda Generalisimo",
    "iso:country":"ES",
    "sg:address":"Avda Generalisimo, 28",
    "sg:city":"Proba",
    "sg:orig_category":"Restaurantes",
    "sg:phone":"+34 982 36 50 84",
    "sg:postcode":"27650",
    "sg:province":"Lugo",
    "wof:name":"Fernandez Castrillon Manuela",
    "wof:placetype":"venue"
},
  "geometry": {"coordinates":[-7.0043501854,42.964931488],"type":"Point"}
}