{
  "type": "Feature",
  "properties": {
    "iso:country":"ES",
    "sg:address":"Carr Vila Antonia, 2",
    "sg:city":"Lleida",
    "sg:orig_category":"M\u00c9dicos: Neurolog\u00cda",
    "sg:phone":"+34 973 23 67 90",
    "sg:postcode":"25007",
    "sg:province":"Lleida",
    "wof:name":"Rabasa Arevalo Jorge",
    "wof:placetype":"venue"
},
  "geometry": {"coordinates":[0.6308190227,41.6179924011],"type":"Point"}
}