{
  "type": "Feature",
  "properties": {
    "addr:full":"Calle de Ramon Y Cajal, 3 Teruel Teruel 44001",
    "addr:housenumber":"3",
    "addr:postcode":"44001",
    "addr:street":"Calle De Ramon Y Cajal",
    "iso:country":"ES",
    "sg:address":"Calle de Ramon Y Cajal, 3",
    "sg:city":"Teruel",
    "sg:orig_category":"M\u00c1quinas De Coser Y De Hacer Punto (al Por Mayor)",
    "sg:phone":"+34 978 60 29 86",
    "sg:postcode":"44001",
    "sg:province":"Teruel",
    "wof:name":"Gonzalez Bellanco Maria Carmen",
    "wof:placetype":"venue"
},
  "geometry": {"coordinates":[-1.1067429781,40.3424911499],"type":"Point"}
}