{
  "type": "Feature",
  "properties": {
    "addr:full":"Sect P, 39 Torre De La Higuera O Matalasca\u00e7as Huelva 21760",
    "addr:housenumber":"39",
    "addr:postcode":"21760",
    "addr:street":"Sect P",
    "iso:country":"ES",
    "sg:address":"Sect P, 39",
    "sg:city":"Torre De La Higuera O Matalasca\u00e7as",
    "sg:orig_category":"Electrodom\u00c9sticos (al Por Menor)",
    "sg:phone":"+34 959 44 01 11",
    "sg:postcode":"21760",
    "sg:province":"Huelva",
    "wof:name":"Sanchez Ducoy Manuel",
    "wof:placetype":"venue"
},
  "geometry": {"coordinates":[-6.9495940208,37.256313324],"type":"Point"}
}