{
  "type": "Feature",
  "properties": {
    "iso:country":"ES",
    "sg:address":"Calle de Albeniz, 29",
    "sg:city":"Malaga",
    "sg:orig_category":"Muebles Y Accesorios Para Cocinas Y Cuartos De Ba\u00d1o (al Por Menor)",
    "sg:phone":"+34 952 26 34 08",
    "sg:postcode":"29014",
    "sg:province":"M\u00e1laga",
    "wof:name":"Supercocinas Malaga S.l.",
    "wof:placetype":"venue"
},
  "geometry": {"coordinates":[-4.4220690727,36.7348632812],"type":"Point"}
}