{
  "type": "Feature",
  "properties": {
    "iso:country":"ES",
    "sg:address":"Partida Senyora, S/n",
    "sg:city":"Amposta",
    "sg:orig_category":"Poller\u00cda Y Caza (al Por Menor)",
    "sg:phone":"+34 977 70 60 63",
    "sg:postcode":"43870",
    "sg:province":"Tarragona",
    "wof:name":"Gorcar Aves S.l.",
    "wof:placetype":"venue"
},
  "geometry": {"coordinates":[0.5797849894,40.7130432129],"type":"Point"}
}