{
  "type": "Feature",
  "properties": {
    "addr:full":"Cmno Huerta De Abajo, 20 Huerta De Abajo Murcia 30565",
    "addr:housenumber":"20",
    "addr:postcode":"30565",
    "addr:street":"Cmno Huerta De Abajo",
    "iso:country":"ES",
    "sg:address":"Cmno Huerta De Abajo, 20",
    "sg:city":"Huerta De Abajo",
    "sg:orig_category":"Maquinaria Para Industrias Diversas",
    "sg:phone":"+34 968 62 41 38",
    "sg:postcode":"30565",
    "sg:province":"Murcia",
    "wof:name":"Vicente Martinez Antonia",
    "wof:placetype":"venue"
},
  "geometry": {"coordinates":[-1.2395490408,38.0263290405],"type":"Point"}
}