{
  "type": "Feature",
  "properties": {
    "addr:full":"Calle de Poeta Altet, 12 Valencia Valencia 46020",
    "addr:housenumber":"12",
    "addr:postcode":"46020",
    "addr:street":"Calle De Poeta Altet",
    "iso:country":"ES",
    "sg:address":"Calle de Poeta Altet, 12",
    "sg:city":"Valencia",
    "sg:orig_category":"Molduras, Junquillos, Listones Y Molduras Perforadas",
    "sg:phone":"+34 963 60 62 92",
    "sg:postcode":"46020",
    "sg:province":"Valencia",
    "wof:name":"Bar Lyvi C.b.",
    "wof:placetype":"venue"
},
  "geometry": {"coordinates":[-0.364143014,39.4865074158],"type":"Point"}
}