{
  "type": "Feature",
  "properties": {
    "iso:country":"ES",
    "sg:address":"Carr Colon, 6",
    "sg:city":"Burjassot",
    "sg:orig_category":"Ingenier\u00cda, Centros De Estudios (diversos)",
    "sg:phone":"+34 963 90 66 99",
    "sg:postcode":"46100",
    "sg:province":"Valencia",
    "wof:name":"Insegma S.l.",
    "wof:placetype":"venue"
},
  "geometry": {"coordinates":[-0.4113889933,39.5102272034],"type":"Point"}
}