{
  "type": "Feature",
  "properties": {
    "addr:full":"Calle de Guadarrama, 2 Madrid Madrid 28011",
    "addr:housenumber":"2",
    "addr:postcode":"28011",
    "addr:street":"Calle De Guadarrama",
    "iso:country":"ES",
    "sg:address":"Calle de Guadarrama, 2",
    "sg:city":"Madrid",
    "sg:orig_category":"Alimentaci\u00d3n General (al Por Menor)",
    "sg:phone":"+34 914 63 56 83",
    "sg:postcode":"28011",
    "sg:province":"Madrid",
    "wof:name":"Zhan  Airong",
    "wof:placetype":"venue"
},
  "geometry": {"coordinates":[-3.7319180965,40.4121856689],"type":"Point"}
}