{
  "type": "Feature",
  "properties": {
    "addr:full":"Carrer de Sagunt, 7 Rubi Barcelona 08191",
    "addr:housenumber":"7",
    "addr:postcode":"08191",
    "addr:street":"Carrer De Sagunt",
    "iso:country":"ES",
    "sg:address":"Carrer de Sagunt, 7",
    "sg:city":"Rubi",
    "sg:orig_category":"Peluqueros: De Se\u00d1oras",
    "sg:phone":"+34 936 97 23 42",
    "sg:postcode":"08191",
    "sg:province":"Barcelona",
    "wof:name":"Martinez Lopez Antonio",
    "wof:placetype":"venue"
},
  "geometry": {"coordinates":[2.0357749462,41.5006599426],"type":"Point"}
}