{
  "type": "Feature",
  "properties": {
    "addr:full":"Crta Circunvalacion, 35 Esparragosa Serena Badajoz 06439",
    "addr:housenumber":"35",
    "addr:postcode":"06439",
    "addr:street":"Crta Circunvalacion",
    "iso:country":"ES",
    "sg:address":"Crta Circunvalacion, 35",
    "sg:city":"Esparragosa Serena",
    "sg:orig_category":"Panader\u00cdas, Panader\u00cdas",
    "sg:phone":"+34 924 77 60 03",
    "sg:postcode":"06439",
    "sg:province":"Badajoz",
    "wof:name":"Leon Rodriguez Adelaida",
    "wof:placetype":"venue"
},
  "geometry": {"coordinates":[-5.606523037,38.6518478394],"type":"Point"}
}