{
  "type": "Feature",
  "properties": {
    "iso:country":"ES",
    "sg:address":"Calle de Hnos. De La Instruccion Cristiana, 9",
    "sg:city":"Portugalete",
    "sg:orig_category":"Inform\u00c1tica, Ofim\u00c1tica (estudios, Asesor\u00cda, Ingenier\u00cda, Formaci\u00d3n)",
    "sg:phone":"+34 944 61 82 18",
    "sg:postcode":"48920",
    "sg:province":"Vizcaya",
    "wof:name":"Billelambide S.l.",
    "wof:placetype":"venue"
},
  "geometry": {"coordinates":[-3.0229930878,43.3226737976],"type":"Point"}
}