{
  "type": "Feature",
  "properties": {
    "addr:full":"Calle de Garcia Goyena, 9 Tafalla Navarra 31300",
    "addr:housenumber":"9",
    "addr:postcode":"31300",
    "addr:street":"Calle De Garcia Goyena",
    "iso:country":"ES",
    "sg:address":"Calle de Garcia Goyena, 9",
    "sg:city":"Tafalla",
    "sg:orig_category":"Perfumer\u00cda (al Por Menor)",
    "sg:phone":"+34 948 70 27 09",
    "sg:postcode":"31300",
    "sg:province":"Navarra",
    "wof:name":"Julieta Perfumeria S.l.",
    "wof:placetype":"venue"
},
  "geometry": {"coordinates":[-1.6759649515,42.5266113281],"type":"Point"}
}