{
  "type": "Feature",
  "properties": {
    "addr:full":"Calle de Dos De Mayo, 38 Ba\u00d1eza Le\u00f3n 24750",
    "addr:housenumber":"38",
    "addr:postcode":"24750",
    "addr:street":"Calle De Dos;Mayo;Leo\u0301N",
    "iso:country":"ES",
    "sg:address":"Calle de Dos De Mayo, 38",
    "sg:city":"Ba\u00d1eza",
    "sg:orig_category":"Herboristas (al Por Menor)",
    "sg:phone":"+34 987 65 59 73",
    "sg:postcode":"24750",
    "sg:province":"Le\u00f3n",
    "wof:name":"Pozuelo Lorenzana Cecilia",
    "wof:placetype":"venue"
},
  "geometry": {"coordinates":[-5.9001092911,42.2978515625],"type":"Point"}
}