{
  "type": "Feature",
  "properties": {
    "addr:full":"Avda Reyes Catolicos, 40 Burgos Burgos 09005",
    "addr:housenumber":"40",
    "addr:postcode":"09005",
    "addr:street":"Avda Reyes Catolicos",
    "iso:country":"ES",
    "sg:address":"Avda Reyes Catolicos, 40",
    "sg:city":"Burgos",
    "sg:orig_category":"Frutas, Legumbres Frescas Y Tempranas (al Por Menor)",
    "sg:phone":"+34 947 22 60 96",
    "sg:postcode":"09005",
    "sg:province":"Burgos",
    "wof:name":"Anton Gonzalez Maximiliano",
    "wof:placetype":"venue"
},
  "geometry": {"coordinates":[-3.6907453537,42.348903656],"type":"Point"}
}