{
  "type": "Feature",
  "properties": {
    "iso:country":"ES",
    "sg:address":"Calle de Ronda, 8",
    "sg:city":"Algodonales",
    "sg:orig_category":"Bisuter\u00cda, Joyer\u00cda, Relojer\u00cda (al Por Menor)",
    "sg:phone":"+34 956 13 72 82",
    "sg:postcode":"11680",
    "sg:province":"C\u00e1diz",
    "wof:name":"Menacho Hidalgo Maria Remedios",
    "wof:placetype":"venue"
},
  "geometry": {"coordinates":[-5.405506134,36.880531311],"type":"Point"}
}