{
  "type": "Feature",
  "properties": {
    "addr:full":"Carrer de Castellnou, 21 Barcelona Barcelona 08017",
    "addr:housenumber":"21",
    "addr:postcode":"08017",
    "addr:street":"Carrer De Castellnou",
    "iso:country":"ES",
    "sg:address":"Carrer de Castellnou, 21",
    "sg:city":"Barcelona",
    "sg:orig_category":"Quincaller\u00cda (al Por Menor)",
    "sg:phone":"+34 932 80 32 12",
    "sg:postcode":"08017",
    "sg:province":"Barcelona",
    "wof:name":"Herrajes Y Perfiles S.l.",
    "wof:placetype":"venue"
},
  "geometry": {"coordinates":[2.1305201054,41.3948936462],"type":"Point"}
}