{
  "type": "Feature",
  "properties": {
    "addr:full":"Calle de Amargura, S/n Yebra Guadalajara 19111",
    "addr:postcode":"19111",
    "addr:street":"Calle De Amargura S / N Yebra",
    "iso:country":"ES",
    "sg:address":"Calle de Amargura, S/n",
    "sg:city":"Yebra",
    "sg:orig_category":"Farmacias",
    "sg:phone":"+34 949 38 82 66",
    "sg:postcode":"19111",
    "sg:province":"Guadalajara",
    "wof:name":"Moreno Gomez Jesus Maria",
    "wof:placetype":"venue"
},
  "geometry": {"coordinates":[-2.9673128128,40.3571014404],"type":"Point"}
}