{
  "type": "Feature",
  "properties": {
    "iso:country":"ES",
    "sg:address":"Avda Arlanzon, 34",
    "sg:city":"Burgos",
    "sg:orig_category":"Sociedades, Compa\u00d1\u00cdas Aseguradoras",
    "sg:phone":"+34 947 27 30 37",
    "sg:postcode":"09004",
    "sg:province":"Burgos",
    "wof:name":"Maria Araceli Fernandez Manzanedo Y Otro Cb",
    "wof:placetype":"venue"
},
  "geometry": {"coordinates":[-3.6896591187,42.3424873352],"type":"Point"}
}