{
  "type": "Feature",
  "properties": {
    "addr:full":"Cmno San Sebastian (de), 4 Boadilla Del Monte Madrid 28660",
    "addr:housenumber":"4",
    "addr:postcode":"28660",
    "addr:street":"Cmno San Sebastian De",
    "iso:country":"ES",
    "sg:address":"Cmno San Sebastian (de), 4",
    "sg:city":"Boadilla Del Monte",
    "sg:orig_category":"Arreglo, Reparaci\u00d3n, Piezas Sueltas De Televisi\u00d3n, V\u00cddeo, Hi",
    "sg:phone":"+34 916 32 30 68",
    "sg:postcode":"28660",
    "sg:province":"Madrid",
    "wof:name":"Benito Martin Olga",
    "wof:placetype":"venue"
},
  "geometry": {"coordinates":[-3.8769309521,40.4069213867],"type":"Point"}
}