{
  "type": "Feature",
  "properties": {
    "addr:full":"Muel Poniente, S/n Ceuta Ceuta 51001",
    "addr:housenumber":"s / n",
    "addr:postcode":"51001",
    "addr:street":"Poniente",
    "iso:country":"ES",
    "sg:address":"Muel Poniente, S/n",
    "sg:city":"Ceuta",
    "sg:orig_category":"Comercio De Piezas De Recambio Y De Accesorios De Veh\u00cdculos, Veh\u00cdculos Industriales",
    "sg:phone":"+34 956 52 20 63",
    "sg:postcode":"51001",
    "sg:province":"Ceuta",
    "wof:name":"Rodaco Motor S.a.",
    "wof:placetype":"venue"
},
  "geometry": {"coordinates":[-5.3302302361,35.8947601318],"type":"Point"}
}