{
  "type": "Feature",
  "properties": {
    "iso:country":"ES",
    "sg:address":"Carrer de Aribau, 36",
    "sg:city":"Barcelona",
    "sg:orig_category":"Farmacias",
    "sg:phone":"+34 934 54 09 05",
    "sg:postcode":"08011",
    "sg:province":"Barcelona",
    "wof:name":"Urgelles Esquerra Patricia",
    "wof:placetype":"venue"
},
  "geometry": {"coordinates":[2.1610310078,41.3873329163],"type":"Point"}
}