{
  "type": "Feature",
  "properties": {
    "addr:full":"Torraxa, 3 Valls Tarragona 43800",
    "addr:housenumber":"3",
    "addr:postcode":"43800",
    "addr:street":"Torraxa",
    "iso:country":"ES",
    "sg:address":"Torraxa, 3",
    "sg:city":"Valls",
    "sg:orig_category":"Peluquer\u00cdas, Peluquer\u00cda Mixta",
    "sg:phone":"+34 977 61 40 15",
    "sg:postcode":"43800",
    "sg:province":"Tarragona",
    "wof:name":"Martinez Lopez Ricardo",
    "wof:placetype":"venue"
},
  "geometry": {"coordinates":[1.2551749945,41.2873344421],"type":"Point"}
}