{
  "type": "Feature",
  "properties": {
    "iso:country":"ES",
    "sg:address":"Calle de Leon Gil De Palacio, 2",
    "sg:city":"Madrid",
    "sg:orig_category":"M\u00c9dicos: Medicina Y Biolog\u00cda Del Deporte",
    "sg:phone":"+34 914 34 84 15",
    "sg:postcode":"28007",
    "sg:province":"Madrid",
    "sg:website":"www.smpmedinadeportiva.com",
    "wof:name":"Esports Medicine Products S.l.",
    "wof:placetype":"venue"
},
  "geometry": {"coordinates":[-3.6791470051,40.4028434753],"type":"Point"}
}