{
  "type": "Feature",
  "properties": {
    "iso:country":"ES",
    "sg:address":"Calle de Ortu\u00d1o De Alango, 10",
    "sg:city":"Portugalete",
    "sg:classifiers":[
        {
            "category":"Personal",
            "subcategory":"Barber",
            "type":"Services"
        }
    ],
    "sg:phone":"+34 944 83 79 44",
    "sg:postcode":"48920",
    "sg:province":"Vizcaya",
    "sg:tags":[
        "caballeros",
        "de",
        "peluqueros"
    ],
    "wof:name":"I\u00f1aki Ranedo Garcia",
    "wof:placetype":"venue"
},
  "geometry": {"coordinates":[-3.0227560997,43.3223304749],"type":"Point"}
}