{
  "type": "Feature",
  "properties": {
    "addr:full":"Cust Reina, Km. 0004,0 Toledo Toledo 45002",
    "addr:postcode":"45002",
    "addr:street":"Reina Km. 0004,0",
    "iso:country":"ES",
    "sg:address":"Cust Reina, Km. 0004,0",
    "sg:city":"Toledo",
    "sg:orig_category":"Distribuci\u00d3n De Petr\u00d3leo Y Derivados",
    "sg:phone":"+34 925 25 53 90",
    "sg:postcode":"45002",
    "sg:province":"Toledo",
    "wof:name":"Suministros Y Carburantes Martinez Gomez S.l.",
    "wof:placetype":"venue"
},
  "geometry": {"coordinates":[-4.025138855,39.8618774414],"type":"Point"}
}