{
  "type": "Feature",
  "properties": {
    "addr:full":"Calle de Espalter, 2 Madrid Madrid 28014",
    "addr:housenumber":"2",
    "addr:postcode":"28014",
    "addr:street":"Calle De Espalter",
    "iso:country":"ES",
    "sg:address":"Calle de Espalter, 2",
    "sg:city":"Madrid",
    "sg:orig_category":"Abogados",
    "sg:phone":"+34 914 20 34 72",
    "sg:postcode":"28014",
    "sg:province":"Madrid",
    "wof:name":"Palao Menor Juan Eugenio",
    "wof:placetype":"venue"
},
  "geometry": {"coordinates":[-3.6900620461,40.412612915],"type":"Point"}
}