{
  "type": "Feature",
  "properties": {
    "addr:full":"Vilarchao(coles), 4 Vilarchao Ourense 32152",
    "addr:housenumber":"4",
    "addr:postcode":"32152",
    "addr:street":"Coles",
    "iso:country":"ES",
    "sg:address":"Vilarchao(coles), 4",
    "sg:city":"Vilarchao",
    "sg:orig_category":"Veh\u00cdculos De Ocasi\u00d3n",
    "sg:phone":"+34 988 20 41 39",
    "sg:postcode":"32152",
    "sg:province":"Ourense",
    "wof:name":"Dereimport S.l.",
    "wof:placetype":"venue"
},
  "geometry": {"coordinates":[-7.8468360901,42.4271011353],"type":"Point"}
}