{
  "type": "Feature",
  "properties": {
    "addr:full":"Rua Nova, 6 Cambados Pontevedra 36630",
    "addr:housenumber":"6",
    "addr:postcode":"36630",
    "addr:street":"Rua Nova",
    "iso:country":"ES",
    "sg:address":"Rua Nova, 6",
    "sg:city":"Cambados",
    "sg:orig_category":"Cl\u00cdnicas Dentales",
    "sg:phone":"+34 986 54 36 58",
    "sg:postcode":"36630",
    "sg:province":"Pontevedra",
    "wof:name":"Datorre Arca Paula",
    "wof:placetype":"venue"
},
  "geometry": {"coordinates":[-8.8138113022,42.5130958557],"type":"Point"}
}