{
  "type": "Feature",
  "properties": {
    "iso:country":"ES",
    "sg:address":"Calle de Ibiza, 15",
    "sg:city":"Benidorm",
    "sg:orig_category":"Alquiler De Apartamentos",
    "sg:phone":"+34 965 85 32 83",
    "sg:postcode":"03500",
    "sg:province":"Alicante",
    "wof:name":"Proyecto Diez S.a.",
    "wof:placetype":"venue"
},
  "geometry": {"coordinates":[-0.1158960015,38.5397377014],"type":"Point"}
}