{
  "type": "Feature",
  "properties": {
    "addr:full":"Calle de Pernet Esteban Padre, 14 Bilbao Vizcaya 48004",
    "addr:housenumber":"14",
    "addr:postcode":"48004",
    "addr:street":"Calle De Pernet Esteban Padre",
    "iso:country":"ES",
    "sg:address":"Calle de Pernet Esteban Padre, 14",
    "sg:city":"Bilbao",
    "sg:orig_category":"Colchones (fabricaci\u00d3n, Al Por Mayor, Al Por Menor)",
    "sg:phone":"+34 944 11 58 43",
    "sg:postcode":"48004",
    "sg:province":"Vizcaya",
    "wof:name":"Cama Nueva S.l.",
    "wof:placetype":"venue"
},
  "geometry": {"coordinates":[-2.9134368896,43.2547187805],"type":"Point"}
}