{
  "type": "Feature",
  "properties": {
    "addr:full":"Avda Constitucion De La, 1 Arroyo De La Miel-benalmadena Costa M\u00e1laga 29631",
    "addr:housenumber":"1",
    "addr:postcode":"29631",
    "addr:street":"Avda Constitucion De La;Arroyo De La Miel-Benalmadena Costa Ma\u0301Laga",
    "iso:country":"ES",
    "sg:address":"Avda Constitucion De La, 1",
    "sg:city":"Arroyo De La Miel-benalmadena Costa",
    "sg:orig_category":"Fotograf\u00cda Y Cine: Aparatos, Pel\u00cdculas Y Accesorios (fabricaci\u00d3n, Al Por Mayor)",
    "sg:phone":"+34 952 44 03 65",
    "sg:postcode":"29631",
    "sg:province":"M\u00e1laga",
    "wof:name":"O.k. Foto Shop S.l.",
    "wof:placetype":"venue"
},
  "geometry": {"coordinates":[-4.5482521057,36.6017608643],"type":"Point"}
}