{
  "type": "Feature",
  "properties": {
    "iso:country":"ES",
    "sg:address":"Calle de Roda (la), 11",
    "sg:city":"Albacete",
    "sg:orig_category":"Comercio De Piezas De Recambio Y De Accesorios De Veh\u00cdculos, Veh\u00cdculos Industriales",
    "sg:phone":"+34 967 50 10 89",
    "sg:postcode":"02006",
    "sg:province":"Albacete",
    "wof:name":"Albarecambios S.l.",
    "wof:placetype":"venue"
},
  "geometry": {"coordinates":[-1.8702992201,39.0000686646],"type":"Point"}
}