{
  "type": "Feature",
  "properties": {
    "iso:country":"ES",
    "sg:address":"Avda Paz (la), 33",
    "sg:city":"Tarazona",
    "sg:orig_category":"Ense\u00d1anza, Formaci\u00d3n Profesional: Aprendizaje",
    "sg:phone":"+34 976 64 45 13",
    "sg:postcode":"50500",
    "sg:province":"Zaragoza",
    "wof:name":"Cruz Roja",
    "wof:placetype":"venue"
},
  "geometry": {"coordinates":[-1.7208869457,41.9073448181],"type":"Point"}
}