{
  "type": "Feature",
  "properties": {
    "iso:country":"ES",
    "sg:address":"Calle de Santisimo Cristo, 30",
    "sg:city":"Rueda",
    "sg:orig_category":"Molduras, Junquillos, Listones Y Molduras Perforadas",
    "sg:phone":"+34 983 86 81 20",
    "sg:postcode":"47490",
    "sg:province":"Valladolid",
    "wof:name":"Perez Marcos Jose",
    "wof:placetype":"venue"
},
  "geometry": {"coordinates":[-4.9599189758,41.4102478027],"type":"Point"}
}