{
  "type": "Feature",
  "properties": {
    "iso:country":"ES",
    "sg:address":"Calle de Bartolome De Castro, 5",
    "sg:city":"Alcala Henares",
    "sg:orig_category":"Estancos",
    "sg:phone":"+34 918 80 30 53",
    "sg:postcode":"28802",
    "sg:province":"Madrid",
    "wof:name":"Perez Garcia Guillermo",
    "wof:placetype":"venue"
},
  "geometry": {"coordinates":[-3.3800733089,40.4783973694],"type":"Point"}
}