{
  "type": "Feature",
  "properties": {
    "addr:full":"Carr Puig, 3 Prullans Lleida 25727",
    "addr:housenumber":"3",
    "addr:postcode":"25727",
    "addr:street":"Carr Puig",
    "iso:country":"ES",
    "sg:address":"Carr Puig, 3",
    "sg:city":"Prullans",
    "sg:orig_category":"Hoteles",
    "sg:phone":"+34 973 51 02 60",
    "sg:postcode":"25727",
    "sg:province":"Lleida",
    "wof:name":"Hotel Muntanya Prullans S.l.",
    "wof:placetype":"venue"
},
  "geometry": {"coordinates":[1.7381739616,42.3789787292],"type":"Point"}
}