{
  "type": "Feature",
  "properties": {
    "addr:full":"Calle de Mocan El, 7 Ag\u00fcimes Las Palmas 35260",
    "addr:housenumber":"7",
    "addr:postcode":"35260",
    "addr:street":"Calle De Mocan El",
    "iso:country":"ES",
    "sg:address":"Calle de Mocan El, 7",
    "sg:city":"Ag\u00fcimes",
    "sg:orig_category":"Bancos",
    "sg:phone":"+34 928 78 65 77",
    "sg:postcode":"35260",
    "sg:province":"Las Palmas",
    "wof:name":"Banco Espa\u00f1ol De Credito S.a.",
    "wof:placetype":"venue"
},
  "geometry": {"coordinates":[-15.4447793961,27.9041996002],"type":"Point"}
}