{
  "type": "Feature",
  "properties": {
    "addr:full":"Carrer de Major, 59 Cervello Barcelona 08758",
    "addr:housenumber":"59",
    "addr:postcode":"08758",
    "addr:street":"Carrer De Major;Barcelona",
    "iso:country":"ES",
    "sg:address":"Carrer de Major, 59",
    "sg:city":"Cervello",
    "sg:orig_category":"Ropa Para Se\u00d1oras (al Por Menor)",
    "sg:phone":"+34 936 84 01 38",
    "sg:postcode":"08758",
    "sg:province":"Barcelona",
    "wof:name":"Bautista Font Marta",
    "wof:placetype":"venue"
},
  "geometry": {"coordinates":[1.955335021,41.3958435059],"type":"Point"}
}