{
  "type": "Feature",
  "properties": {
    "iso:country":"ES",
    "sg:address":"Carrer de Muntaner, 271",
    "sg:city":"Barcelona",
    "sg:orig_category":"M\u00c9dicos: Cardiolog\u00cda Y Afecciones Cardiovasculares",
    "sg:phone":"+34 932 00 55 26",
    "sg:postcode":"08021",
    "sg:province":"Barcelona",
    "wof:name":"Simon Lamuela Joaquin",
    "wof:placetype":"venue"
},
  "geometry": {"coordinates":[2.1472120285,41.3956718445],"type":"Point"}
}