{
  "type": "Feature",
  "properties": {
    "iso:country":"ES",
    "sg:address":"Carr Ausias March (d'), 10",
    "sg:city":"Betxi",
    "sg:orig_category":"Peluquer\u00cdas, Peluquer\u00cda Mixta",
    "sg:phone":"+34 964 62 24 22",
    "sg:postcode":"12549",
    "sg:province":"Castell\u00f3n",
    "wof:name":"Aibar Santillana Maria Dolores",
    "wof:placetype":"venue"
},
  "geometry": {"coordinates":[-0.1955852062,39.9277000427],"type":"Point"}
}