{
  "type": "Feature",
  "properties": {
    "iso:country":"ES",
    "sg:address":"Plaz Sede\u00d1o, 3",
    "sg:city":"Nava Asuncion",
    "sg:orig_category":"Electrodom\u00c9sticos (al Por Menor)",
    "sg:phone":"+34 921 58 00 58",
    "sg:postcode":"40450",
    "sg:province":"Segovia",
    "sg:website":"www.eleccebrian.es",
    "wof:name":"Cebrian Casado Roberto",
    "wof:placetype":"venue"
},
  "geometry": {"coordinates":[-4.4882631302,41.1547355652],"type":"Point"}
}