{
  "type": "Feature",
  "properties": {
    "iso:country":"ES",
    "sg:address":"Calle de Gran Avenida, 29",
    "sg:city":"Madrid",
    "sg:orig_category":"\u00d3ptica: Instrumentos (fabricaci\u00d3n)",
    "sg:phone":"+34 913 41 78 26",
    "sg:postcode":"28041",
    "sg:province":"Madrid",
    "wof:name":"A.b.c. Vision S.l.",
    "wof:placetype":"venue"
},
  "geometry": {"coordinates":[-3.707019,40.369915],"type":"Point"}
}