{
  "type": "Feature",
  "properties": {
    "addr:full":"Calle de San Juan, 34 Navas Del Marques \u00c1vila 05230",
    "addr:housenumber":"34",
    "addr:postcode":"05230",
    "addr:street":"Calle De San Juan",
    "iso:country":"ES",
    "sg:address":"Calle de San Juan, 34",
    "sg:city":"Navas Del Marques",
    "sg:orig_category":"Mec\u00c1nico Del Autom\u00d3vil",
    "sg:phone":"+34 918 97 04 17",
    "sg:postcode":"05230",
    "sg:province":"\u00c1vila",
    "wof:name":"Comunidad De Propietarios San Juan 34",
    "wof:placetype":"venue"
},
  "geometry": {"coordinates":[-4.3308792114,40.6029815674],"type":"Point"}
}