{
  "type": "Feature",
  "properties": {
    "iso:country":"ES",
    "sg:address":"Calle de Pintor Sorolla (del), S/n",
    "sg:city":"Cercedilla",
    "sg:orig_category":"Alquiler De Casas Y Habitaciones Amuebladas",
    "sg:phone":"+34 918 52 09 49",
    "sg:postcode":"28470",
    "sg:province":"Madrid",
    "wof:name":"Maria Inmaculada S Domestico Prov Iberica Septentrional Residencia Maria Inmaculada",
    "wof:placetype":"venue"
},
  "geometry": {"coordinates":[-4.0601172447,40.7409515381],"type":"Point"}
}