{
  "type": "Feature",
  "properties": {
    "addr:full":"Plaz Espa\u00d1a (de), 15 Valdepe\u00f1as Ciudad Real 13300",
    "addr:postcode":"13300",
    "addr:street":"Plaz",
    "iso:country":"ES",
    "sg:address":"Plaz Espa\u00d1a (de), 15",
    "sg:city":"Valdepe\u00f1as",
    "sg:orig_category":"Ropa Para Ni\u00d1os (al Por Menor)",
    "sg:phone":"+34 926 31 14 74",
    "sg:postcode":"13300",
    "sg:province":"Ciudad Real",
    "sg:website":"www.benetton.com",
    "wof:name":"Martin Del Fresno Maria Consuelo",
    "wof:placetype":"venue"
},
  "geometry": {"coordinates":[-3.3877990246,38.7597694397],"type":"Point"}
}