{
  "type": "Feature",
  "properties": {
    "addr:full":"Cra. Vilanova, Km. 0004,0 S. Pere Ribes Barcelona 08810",
    "addr:postcode":"08810",
    "addr:street":"Vilanova Km. 0004,0 S. Pere Ribes Barcelona",
    "iso:country":"ES",
    "sg:address":"Cra. Vilanova, Km. 0004,0",
    "sg:city":"S. Pere Ribes",
    "sg:orig_category":"Alimentaci\u00d3n General (al Por Menor)",
    "sg:phone":"+34 938 96 54 34",
    "sg:postcode":"08810",
    "sg:province":"Barcelona",
    "wof:name":"Utillajes Montgros S. L.",
    "wof:placetype":"venue"
},
  "geometry": {"coordinates":[1.7786979675,41.2564849854],"type":"Point"}
}