{
  "type": "Feature",
  "properties": {
    "addr:full":"Estd Santiago (estrada Vella De), 164 Lugo Lugo 27004",
    "addr:housenumber":"164",
    "addr:postcode":"27004",
    "addr:street":"Estrada Vella De",
    "iso:country":"ES",
    "sg:address":"Estd Santiago (estrada Vella De), 164",
    "sg:city":"Lugo",
    "sg:orig_category":"Molduras, Junquillos, Listones Y Molduras Perforadas",
    "sg:phone":"+34 982 25 10 84",
    "sg:postcode":"27004",
    "sg:province":"Lugo",
    "wof:name":"Nu\u00f1ez Parada Maria Pilar",
    "wof:placetype":"venue"
},
  "geometry": {"coordinates":[-7.569381237,43.0095176697],"type":"Point"}
}