{
  "type": "Feature",
  "properties": {
    "addr:full":"Sect S, S/n Torre De La Higuera O Matalasca\u00e7as Huelva 21760",
    "addr:housenumber":"/ n",
    "addr:postcode":"21760",
    "addr:street":"Sect S S",
    "iso:country":"ES",
    "sg:address":"Sect S, S/n",
    "sg:city":"Torre De La Higuera O Matalasca\u00e7as",
    "sg:orig_category":"Bares, Piano",
    "sg:phone":"+34 959 44 04 60",
    "sg:postcode":"21760",
    "sg:province":"Huelva",
    "wof:name":"Ba\u00f1ez Martinez Jose",
    "wof:placetype":"venue"
},
  "geometry": {"coordinates":[-6.9495940208,37.256313324],"type":"Point"}
}