{
  "type": "Feature",
  "properties": {
    "iso:country":"ES",
    "sg:address":"Calle de Balagar (el), S/n",
    "sg:city":"Torrecaballeros",
    "sg:orig_category":"M\u00c9dicos: Oftalmolog\u00cda",
    "sg:phone":"+34 921 40 12 54",
    "sg:postcode":"40160",
    "sg:province":"Segovia",
    "wof:name":"Montejos Iglesias Fernando",
    "wof:placetype":"venue"
},
  "geometry": {"coordinates":[-4.0226836205,40.9971542358],"type":"Point"}
}