{
  "type": "Feature",
  "properties": {
    "addr:full":"Playa De La Torrecilla, 4 Nerja M\u00e1laga 29780",
    "addr:housenumber":"4",
    "addr:postcode":"29780",
    "addr:street":"Playa De La Torrecilla",
    "iso:country":"ES",
    "sg:address":"Playa De La Torrecilla, 4",
    "sg:city":"Nerja",
    "sg:orig_category":"Inmobiliaria (agencias)",
    "sg:phone":"+34 952 52 07 31",
    "sg:postcode":"29780",
    "sg:province":"M\u00e1laga",
    "wof:name":"Kopcke Winkel S.a.",
    "wof:placetype":"venue"
},
  "geometry": {"coordinates":[-3.8762149811,36.751914978],"type":"Point"}
}