{
  "type": "Feature",
  "properties": {
    "iso:country":"ES",
    "sg:address":"Calle de Mayor Antigua, 18",
    "sg:city":"Palencia",
    "sg:orig_category":"Producci\u00d3n, Distribuci\u00d3n De Gas Butano Y Propano",
    "sg:phone":"+34 979 70 65 19",
    "sg:postcode":"34005",
    "sg:province":"Palencia",
    "wof:name":"Arnaiz Ojeda Leopoldo",
    "wof:placetype":"venue"
},
  "geometry": {"coordinates":[-4.5398831367,42.0136985779],"type":"Point"}
}