{
  "type": "Feature",
  "properties": {
    "iso:country":"ES",
    "sg:address":"Calle de Ponce De Leon, 8",
    "sg:city":"Madrid",
    "sg:orig_category":"Agencias De Viajes",
    "sg:phone":"+34 914 45 50 72",
    "sg:postcode":"28010",
    "sg:province":"Madrid",
    "sg:website":"www.puertaeuropaviajes.com",
    "wof:name":"Amunsen Incentivos, S.l.",
    "wof:placetype":"venue"
},
  "geometry": {"coordinates":[-3.6983742714,40.4361190796],"type":"Point"}
}