{
  "type": "Feature",
  "properties": {
    "iso:country":"ES",
    "sg:address":"Carr Espados, 2",
    "sg:city":"Almenar",
    "sg:orig_category":"Sindicatos De Trabajadores",
    "sg:phone":"+34 973 77 14 16",
    "sg:postcode":"25126",
    "sg:province":"Lleida",
    "wof:name":"Unio De Pagesos De Catalunya",
    "wof:placetype":"venue"
},
  "geometry": {"coordinates":[0.5701000094,41.7965431213],"type":"Point"}
}