{
  "type": "Feature",
  "properties": {
    "addr:full":"Avda Andalucia, 25 Malaga M\u00e1laga 29006",
    "addr:housenumber":"25",
    "addr:postcode":"29006",
    "addr:street":"Avda Andalucia;Ma\u0301Laga",
    "iso:country":"ES",
    "sg:address":"Avda Andalucia, 25",
    "sg:city":"Malaga",
    "sg:orig_category":"T\u00c9cnicos Veterinarios",
    "sg:phone":"+34 952 31 57 82",
    "sg:postcode":"29006",
    "sg:province":"M\u00e1laga",
    "wof:name":"Requena Calvo Felix",
    "wof:placetype":"venue"
},
  "geometry": {"coordinates":[-4.4398159981,36.7164306641],"type":"Point"}
}