{
  "type": "Feature",
  "properties": {
    "addr:full":"Avda Diez De Enero, 75 Sabero Le\u00f3n 24810",
    "addr:housenumber":"75",
    "addr:postcode":"24810",
    "addr:street":"Avda Diez De Enero;Leo\u0301N",
    "iso:country":"ES",
    "sg:address":"Avda Diez De Enero, 75",
    "sg:city":"Sabero",
    "sg:orig_category":"Pescader\u00cdas (al Por Menor)",
    "sg:phone":"+34 987 71 84 62",
    "sg:postcode":"24810",
    "sg:province":"Le\u00f3n",
    "wof:name":"Alvarez Fernandez Maximo",
    "wof:placetype":"venue"
},
  "geometry": {"coordinates":[-5.1488060951,42.8356361389],"type":"Point"}
}