{
  "type": "Feature",
  "properties": {
    "iso:country":"ES",
    "sg:address":"Ctra Cortijo, 80",
    "sg:city":"Logro\u00f1o",
    "sg:orig_category":"Cr\u00cda De Animales",
    "sg:phone":"+34 941 22 94 96",
    "sg:postcode":"26006",
    "sg:province":"La Rioja",
    "wof:name":"Ganaderia Francisco De Torre S.l.",
    "wof:placetype":"venue"
},
  "geometry": {"coordinates":[-2.4845588207,42.4849243164],"type":"Point"}
}