{
  "type": "Feature",
  "properties": {
    "addr:full":"Carr Col.legi, 17 Vilanova I La Geltru Barcelona 08800",
    "addr:housenumber":"17",
    "addr:postcode":"08800",
    "addr:street":"Carr Col.Legi",
    "iso:country":"ES",
    "sg:address":"Carr Col.legi, 17",
    "sg:city":"Vilanova I La Geltru",
    "sg:orig_category":"Inmobiliaria (agencias)",
    "sg:phone":"+34 938 14 21 50",
    "sg:postcode":"08800",
    "sg:province":"Barcelona",
    "wof:name":"Immogestio S.t.p.",
    "wof:placetype":"venue"
},
  "geometry": {"coordinates":[1.7269920111,41.2240982056],"type":"Point"}
}