{
  "type": "Feature",
  "properties": {
    "iso:country":"ES",
    "sg:address":"Calle de Marroquina, 51",
    "sg:city":"Madrid",
    "sg:orig_category":"Persianas Interiores, Exteriores",
    "sg:phone":"+34 913 28 44 38",
    "sg:postcode":"28030",
    "sg:province":"Madrid",
    "wof:name":"Montero Montes Teodoro",
    "wof:placetype":"venue"
},
  "geometry": {"coordinates":[-3.6470050812,40.4098510742],"type":"Point"}
}