{
  "type": "Feature",
  "properties": {
    "iso:country":"ES",
    "sg:address":"Carr Rector, 97",
    "sg:city":"Badalona",
    "sg:orig_category":"Sales (al Por Mayor)",
    "sg:phone":"+34 934 64 06 12",
    "sg:postcode":"08912",
    "sg:province":"Barcelona",
    "wof:name":"Moreno Gutierrez Victorino",
    "wof:placetype":"venue"
},
  "geometry": {"coordinates":[2.2449560165,41.4458999634],"type":"Point"}
}