{
  "type": "Feature",
  "properties": {
    "addr:full":"Calle de Cervantes, 11 Massamagrell Valencia 46130",
    "addr:housenumber":"11",
    "addr:postcode":"46130",
    "addr:street":"Calle De Cervantes",
    "iso:country":"ES",
    "sg:address":"Calle de Cervantes, 11",
    "sg:city":"Massamagrell",
    "sg:orig_category":"Ingeniero",
    "sg:phone":"+34 961 44 20 83",
    "sg:postcode":"46130",
    "sg:province":"Valencia",
    "wof:name":"Albert Sales Juan",
    "wof:placetype":"venue"
},
  "geometry": {"coordinates":[-0.3349733055,39.5691642761],"type":"Point"}
}