{
  "type": "Feature",
  "properties": {
    "iso:country":"ES",
    "sg:address":"Ptge Ferran Sor, 6",
    "sg:city":"Rubi",
    "sg:orig_category":"Material Did\u00c1ctico",
    "sg:phone":"+34 935 88 19 70",
    "sg:postcode":"08191",
    "sg:province":"Barcelona",
    "wof:name":"Oclu-plast S.a.",
    "wof:placetype":"venue"
},
  "geometry": {"coordinates":[2.0188200474,41.4717063904],"type":"Point"}
}