{
  "type": "Feature",
  "properties": {
    "iso:country":"ES",
    "sg:address":"Carrer de Molar (del), 10",
    "sg:city":"Reus",
    "sg:orig_category":"Cer\u00c1micas: Material Y Suministros",
    "sg:phone":"+34 977 32 84 44",
    "sg:postcode":"43206",
    "sg:province":"Tarragona",
    "wof:name":"Enrique Castells Fargas S.l",
    "wof:placetype":"venue"
},
  "geometry": {"coordinates":[1.0791419744,41.1560783386],"type":"Point"}
}