{
  "type": "Feature",
  "properties": {
    "iso:country":"ES",
    "sg:address":"Av Mistral, 77",
    "sg:city":"Barcelona",
    "sg:orig_category":"Agricultura: Abastecimiento Y Cosechado (negocio)",
    "sg:phone":"+34 934 25 41 43",
    "sg:postcode":"08015",
    "sg:province":"Barcelona",
    "wof:name":"Gallego Jurado Remedios",
    "wof:placetype":"venue"
},
  "geometry": {"coordinates":[2.1534340382,41.3754348755],"type":"Point"}
}