{
  "type": "Feature",
  "properties": {
    "iso:country":"ES",
    "sg:address":"Ctra Miguel Esteban, S/n",
    "sg:city":"Quintanar Orden",
    "sg:orig_category":"Comercio De Hierro",
    "sg:phone":"+34 925 18 16 26",
    "sg:postcode":"45800",
    "sg:province":"Toledo",
    "wof:name":"Hierros Villarejo S.a.",
    "wof:placetype":"venue"
},
  "geometry": {"coordinates":[-3.0395541191,39.5857849121],"type":"Point"}
}