{
  "type": "Feature",
  "properties": {
    "addr:full":"Calle de Corbones, 12 Mairena Alcor Sevilla 41510",
    "addr:housenumber":"12",
    "addr:postcode":"41510",
    "addr:street":"Calle De Corbones",
    "iso:country":"ES",
    "sg:address":"Calle de Corbones, 12",
    "sg:city":"Mairena Alcor",
    "sg:orig_category":"Ahumados Y Salazones",
    "sg:phone":"+34 955 74 63 26",
    "sg:postcode":"41510",
    "sg:province":"Sevilla",
    "wof:name":"Salazones Gonzalez E Hijos S.cv.",
    "wof:placetype":"venue"
},
  "geometry": {"coordinates":[-5.7353916168,37.3756446838],"type":"Point"}
}