{
  "type": "Feature",
  "properties": {
    "addr:full":"Pl. Reial, 2 Les Pallargues Lleida 25212",
    "addr:housenumber":"2",
    "addr:postcode":"25212",
    "addr:street":"Pl. Reial;Les Pallargues",
    "iso:country":"ES",
    "sg:address":"Pl. Reial, 2",
    "sg:city":"Les Pallargues",
    "sg:orig_category":"Centros De Educaci\u00d3n Especial",
    "sg:phone":"+34 973 52 00 30",
    "sg:postcode":"25212",
    "sg:province":"Lleida",
    "wof:name":"Ajuntament Dels Plans De Sio",
    "wof:placetype":"venue"
},
  "geometry": {"coordinates":[1.1975543499,41.7617607117],"type":"Point"}
}