{
  "type": "Feature",
  "properties": {
    "addr:full":"Ptge Milans, 4 Hospitalet Llobregat Barcelona 08907",
    "addr:housenumber":"4",
    "addr:postcode":"08907",
    "addr:street":"Ptge Milans",
    "iso:country":"ES",
    "sg:address":"Ptge Milans, 4",
    "sg:city":"Hospitalet Llobregat",
    "sg:orig_category":"Empresas De Limpieza",
    "sg:phone":"+34 932 60 25 02",
    "sg:postcode":"08907",
    "sg:province":"Barcelona",
    "wof:name":"Matis.net S.c.p.",
    "wof:placetype":"venue"
},
  "geometry": {"coordinates":[2.1019001007,41.3574790955],"type":"Point"}
}