{
  "type": "Feature",
  "properties": {
    "addr:full":"Calle de Division Azul, 4 Oviedo Asturias 33013",
    "addr:housenumber":"4",
    "addr:postcode":"33013",
    "addr:street":"Calle De Division Azul",
    "iso:country":"ES",
    "sg:address":"Calle de Division Azul, 4",
    "sg:city":"Oviedo",
    "sg:orig_category":"Peluqueros: De Se\u00d1oras",
    "sg:phone":"+34 985 24 44 50",
    "sg:postcode":"33013",
    "sg:province":"Asturias",
    "wof:name":"Secades Roca Maria Del Carmen",
    "wof:placetype":"venue"
},
  "geometry": {"coordinates":[-5.8590908051,43.3618850708],"type":"Point"}
}