{
  "type": "Feature",
  "properties": {
    "iso:country":"ES",
    "sg:address":"Rua Anton Losada Dieguez, 23",
    "sg:city":"Estrada",
    "sg:orig_category":"Procuradores",
    "sg:phone":"+34 986 58 48 98",
    "sg:postcode":"36680",
    "sg:province":"Pontevedra",
    "wof:name":"Villaverde Guldris Cristina",
    "wof:placetype":"venue"
},
  "geometry": {"coordinates":[-8.4931631088,42.6905937195],"type":"Point"}
}