{
  "type": "Feature",
  "properties": {
    "addr:full":"Ctra Orihuela, 12 Pilar Horadada Alicante 03190",
    "addr:housenumber":"12",
    "addr:postcode":"03190",
    "addr:street":"Ctra Orihuela",
    "iso:country":"ES",
    "sg:address":"Ctra Orihuela, 12",
    "sg:city":"Pilar Horadada",
    "sg:orig_category":"Plomeros",
    "sg:phone":"+34 965 35 25 54",
    "sg:postcode":"03190",
    "sg:province":"Alicante",
    "wof:name":"Pagan Belmonte Juan Antonio",
    "wof:placetype":"venue"
},
  "geometry": {"coordinates":[-0.7914999723,37.863986969],"type":"Point"}
}