{
  "type": "Feature",
  "properties": {
    "iso:country":"ES",
    "sg:address":"Avda Diagonal, 9",
    "sg:city":"Jesus Pobre",
    "sg:orig_category":"Fabricaci\u00d3n De Muebles",
    "sg:phone":"+34 965 75 67 90",
    "sg:postcode":"03749",
    "sg:province":"Alicante",
    "wof:name":"Tarraula S.l.",
    "wof:placetype":"venue"
},
  "geometry": {"coordinates":[0.0856920034,38.7985115051],"type":"Point"}
}