{
  "type": "Feature",
  "properties": {
    "iso:country":"ES",
    "sg:address":"Ctra Valladolid, Km. 0002,1",
    "sg:city":"Poligono Industrial Los Villares",
    "sg:orig_category":"Venta, Colocaci\u00d3n, Reparaci\u00d3n De Parabrisas, Techos Descapotables",
    "sg:phone":"+34 923 22 60 30",
    "sg:postcode":"37184",
    "sg:province":"Salamanca",
    "wof:name":"Cristal Parabrisas S.l.",
    "wof:placetype":"venue"
},
  "geometry": {"coordinates":[-5.6469841003,41.0071716309],"type":"Point"}
}