{
  "type": "Feature",
  "properties": {
    "iso:country":"ES",
    "sg:address":"Calle de Calahorra, 11",
    "sg:city":"Madrid",
    "sg:orig_category":"Caf\u00c9s, Bares, Cervecer\u00cdas",
    "sg:phone":"+34 917 76 00 03",
    "sg:postcode":"28032",
    "sg:province":"Madrid",
    "wof:name":"Hosteleria Covajovi S.l.",
    "wof:placetype":"venue"
},
  "geometry": {"coordinates":[-3.6126656532,40.4074630737],"type":"Point"}
}