{
  "type": "Feature",
  "properties": {
    "addr:full":"Ctra. Albal-torrente, Km. 0004,5 Catarroja Valencia 46470",
    "addr:postcode":"46470",
    "addr:street":"Ctra. Albal-Torrente Km. 0004,5",
    "iso:country":"ES",
    "sg:address":"Ctra. Albal-torrente, Km. 0004,5",
    "sg:city":"Catarroja",
    "sg:orig_category":"Semiller\u00cdas",
    "sg:phone":"+34 961 26 69 04",
    "sg:postcode":"46470",
    "sg:province":"Valencia",
    "wof:name":"Viveros Vicente Dalmau E Hijos S.a.",
    "wof:placetype":"venue"
},
  "geometry": {"coordinates":[-0.4653016925,39.4341278076],"type":"Point"}
}