{
  "type": "Feature",
  "properties": {
    "addr:full":"Carrer de Pau Vila, 7 Cambrils Badia Tarragona 43850",
    "addr:housenumber":"7",
    "addr:postcode":"43850",
    "addr:street":"Carrer De Pau Vila",
    "iso:country":"ES",
    "sg:address":"Carrer de Pau Vila, 7",
    "sg:city":"Cambrils Badia",
    "sg:orig_category":"Agencias Y Agentes Comerciales, Representantes",
    "sg:phone":"+34 977 36 55 51",
    "sg:postcode":"43850",
    "sg:province":"Tarragona",
    "wof:name":"P & B Hunters S.c.p.",
    "wof:placetype":"venue"
},
  "geometry": {"coordinates":[1.0723949671,41.0718803406],"type":"Point"}
}