{
  "type": "Feature",
  "properties": {
    "iso:country":"ES",
    "sg:address":"Calle de Sandalio Lopez, 20",
    "sg:city":"Madrid",
    "sg:orig_category":"Maquinaria Para Industrias Diversas",
    "sg:phone":"+34 902 44 04 40",
    "sg:postcode":"28034",
    "sg:province":"Madrid",
    "sg:website":"www.alkitodo.es",
    "wof:name":"Alkitodo 2000 S.l.",
    "wof:placetype":"venue"
},
  "geometry": {"coordinates":[-3.6903297901,40.4933395386],"type":"Point"}
}