{
  "type": "Feature",
  "properties": {
    "iso:country":"ES",
    "sg:address":"Calle de Recreo (del), 6",
    "sg:city":"Aranzueque",
    "sg:orig_category":"Centros De Educaci\u00d3n Especial",
    "sg:phone":"+34 949 29 23 72",
    "sg:postcode":"19141",
    "sg:province":"Guadalajara",
    "wof:name":"Colegio Rural Agrupado De Tendilla",
    "wof:placetype":"venue"
},
  "geometry": {"coordinates":[-3.078797102,40.4921607971],"type":"Point"}
}