{
  "type": "Feature",
  "properties": {
    "iso:country":"ES",
    "sg:address":"Calle de Carpinteros, 12",
    "sg:city":"Ecija",
    "sg:orig_category":"Material Y Herramientas Agr\u00cdcolas",
    "sg:phone":"+34 955 90 37 11",
    "sg:postcode":"41400",
    "sg:province":"Sevilla",
    "wof:name":"Rivera Agricola S.l.",
    "wof:placetype":"venue"
},
  "geometry": {"coordinates":[-5.1015224457,37.4861946106],"type":"Point"}
}