{
  "type": "Feature",
  "properties": {
    "iso:country":"ES",
    "sg:address":"Calle de Reloj (el), 4",
    "sg:city":"Ba\u00d1eza",
    "sg:orig_category":"Zapatos (al Por Menor)",
    "sg:phone":"+34 987 65 58 63",
    "sg:postcode":"24750",
    "sg:province":"Le\u00f3n",
    "wof:name":"Toral Amigo Jose",
    "wof:placetype":"venue"
},
  "geometry": {"coordinates":[-5.9242091179,42.3069114685],"type":"Point"}
}