{
  "type": "Feature",
  "properties": {
    "addr:full":"Calle de Anton Dvorak, 5 Palmas De Gran Canaria Las Palmas 35016",
    "addr:housenumber":"5",
    "addr:postcode":"35016",
    "addr:street":"Calle De Anton Dvorak",
    "iso:country":"ES",
    "sg:address":"Calle de Anton Dvorak, 5",
    "sg:city":"Palmas De Gran Canaria",
    "sg:orig_category":"Farmacias",
    "sg:phone":"+34 928 31 51 14",
    "sg:postcode":"35016",
    "sg:province":"Las Palmas",
    "wof:name":"Zumbado Pe\u00f1a Maria Dolores",
    "wof:placetype":"venue"
},
  "geometry": {"coordinates":[-15.4185247421,28.0744514465],"type":"Point"}
}