{
  "type": "Feature",
  "properties": {
    "addr:full":"Calle de Virgen Del Carmen, 12 Llodio \u00c1lava 01400",
    "addr:housenumber":"12",
    "addr:postcode":"01400",
    "addr:street":"Calle De Virgen Del Carmen",
    "iso:country":"ES",
    "sg:address":"Calle de Virgen Del Carmen, 12",
    "sg:city":"Llodio",
    "sg:orig_category":"Electricidad: Instaladores",
    "sg:phone":"+34 946 72 24 98",
    "sg:postcode":"01400",
    "sg:province":"\u00c1lava",
    "wof:name":"Vahle Espa\u00f1a S. A.",
    "wof:placetype":"venue"
},
  "geometry": {"coordinates":[-2.9603669643,43.143371582],"type":"Point"}
}