{
  "type": "Feature",
  "properties": {
    "iso:country":"ES",
    "sg:address":"Cmno Cristo, 7",
    "sg:city":"Aldeanueva Ebro",
    "sg:orig_category":"Cajas Y Embalajes Met\u00c1licos",
    "sg:phone":"+34 941 14 40 40",
    "sg:postcode":"26559",
    "sg:province":"La Rioja",
    "sg:website":"www.mivisa.com",
    "wof:name":"Mivisa Envases S.a.",
    "wof:placetype":"venue"
},
  "geometry": {"coordinates":[-1.8801590204,42.2278594971],"type":"Point"}
}