{
  "type": "Feature",
  "properties": {
    "addr:full":"Avda Fuentesauco, S/n Poligono Industrial Los Villares Salamanca 37184",
    "addr:housenumber":"s / n",
    "addr:postcode":"37184",
    "addr:street":"Avda Fuentesauco;Industrial",
    "iso:country":"ES",
    "sg:address":"Avda Fuentesauco, S/n",
    "sg:city":"Poligono Industrial Los Villares",
    "sg:orig_category":"Reciclaje, Desguace De Veh\u00cdculos",
    "sg:phone":"+34 923 16 02 89",
    "sg:postcode":"37184",
    "sg:province":"Salamanca",
    "wof:name":"Villanueva De Dios Francisco",
    "wof:placetype":"venue"
},
  "geometry": {"coordinates":[-5.646173954,40.9929161072],"type":"Point"}
}