{
  "type": "Feature",
  "properties": {
    "iso:country":"ES",
    "sg:address":"Patxiku Kalea, 5",
    "sg:city":"Zarautz",
    "sg:orig_category":"Electrodom\u00c9sticos (al Por Menor)",
    "sg:phone":"+34 943 13 06 33",
    "sg:postcode":"20800",
    "sg:province":"Guip\u00f9zcoa",
    "wof:name":"Visson Bi, S.l.",
    "wof:placetype":"venue"
},
  "geometry": {"coordinates":[-2.1760299206,43.2851486206],"type":"Point"}
}