{
  "type": "Feature",
  "properties": {
    "addr:full":"Ctra. La Ventilla, S/n Fuente Palmera C\u00f3rdoba 14120",
    "addr:housenumber":"s / n",
    "addr:postcode":"14120",
    "addr:street":"Ctra. La Ventilla",
    "iso:country":"ES",
    "sg:address":"Ctra. La Ventilla, S/n",
    "sg:city":"Fuente Palmera",
    "sg:orig_category":"Frutas, Legumbres Frescas Y Tempranas (al Por Menor)",
    "sg:phone":"+34 957 63 82 12",
    "sg:postcode":"14120",
    "sg:province":"C\u00f3rdoba",
    "wof:name":"Frutas Nieto S.l.",
    "wof:placetype":"venue"
},
  "geometry": {"coordinates":[-5.0916819572,37.7111854553],"type":"Point"}
}