{
  "type": "Feature",
  "properties": {
    "addr:full":"Calle de Sol, 20 Sevilla Sevilla 41003",
    "addr:housenumber":"20",
    "addr:postcode":"41003",
    "addr:street":"Calle De Sol",
    "iso:country":"ES",
    "sg:address":"Calle de Sol, 20",
    "sg:city":"Sevilla",
    "sg:orig_category":"Ense\u00d1anza: Comercio, Gesti\u00d3n, Inform\u00c1tica",
    "sg:phone":"+34 954 21 12 83",
    "sg:postcode":"41003",
    "sg:province":"Sevilla",
    "sg:website":"www.formacionstudium.com",
    "wof:name":"Instituto Tecnico Superior De Informatica Studium S.l.",
    "wof:placetype":"venue"
},
  "geometry": {"coordinates":[-5.9874091148,37.3941307068],"type":"Point"}
}