{
  "type": "Feature",
  "properties": {
    "iso:country":"ES",
    "sg:address":"Calle de Duque, 15",
    "sg:city":"Bejar",
    "sg:orig_category":"Carnicer\u00cdas, Carnicer\u00cdas",
    "sg:phone":"+34 923 40 20 04",
    "sg:postcode":"37700",
    "sg:province":"Salamanca",
    "wof:name":"Ganados Y Carnes Sorihuela S.l.",
    "wof:placetype":"venue"
},
  "geometry": {"coordinates":[-5.776892662,40.3880271912],"type":"Point"}
}