{
  "type": "Feature",
  "properties": {
    "iso:country":"ES",
    "sg:address":"Calle de San Miguel, 56",
    "sg:city":"Torremolinos",
    "sg:orig_category":"Bisuter\u00cda, Joyer\u00cda, Relojer\u00cda (al Por Menor)",
    "sg:phone":"+34 952 38 04 47",
    "sg:postcode":"29620",
    "sg:province":"M\u00e1laga",
    "wof:name":"Kishinchand Kirpalani Prakash",
    "wof:placetype":"venue"
},
  "geometry": {"coordinates":[-4.4978561401,36.6226158142],"type":"Point"}
}