{
  "type": "Feature",
  "properties": {
    "iso:country":"ES",
    "sg:address":"Ctra Vitoria, Km. 0053,0",
    "sg:city":"Samaniego",
    "sg:orig_category":"Productores Recolectores, Venta Directa De Vinos",
    "sg:phone":"+34 945 60 94 20",
    "sg:postcode":"01307",
    "sg:province":"\u00c1lava",
    "sg:website":"www.bodegasbaigorri.com",
    "wof:name":"Bodegas Baigorri S.l.",
    "wof:placetype":"venue"
},
  "geometry": {"coordinates":[-2.6686489582,42.5500984192],"type":"Point"}
}