{
  "type": "Feature",
  "properties": {
    "iso:country":"ES",
    "sg:address":"Villarigan, 35",
    "sg:city":"Escoredo",
    "sg:orig_category":"Producci\u00d3n, Venta De Productos De Agricultura Biol\u00d3gica",
    "sg:phone":"+34 985 82 25 45",
    "sg:postcode":"33129",
    "sg:province":"Asturias",
    "wof:name":"Rialdi S.a.",
    "wof:placetype":"venue"
},
  "geometry": {"coordinates":[-6.1370148659,43.4517707825],"type":"Point"}
}