{
  "type": "Feature",
  "properties": {
    "addr:full":"Calle de Murcia, 53 Almeria Almer\u00eda 04004",
    "addr:housenumber":"53",
    "addr:postcode":"04004",
    "addr:street":"Calle De Murcia",
    "iso:country":"ES",
    "sg:address":"Calle de Murcia, 53",
    "sg:city":"Almeria",
    "sg:orig_category":"Peluqueros: De Se\u00d1oras",
    "sg:phone":"+34 950 26 18 12",
    "sg:postcode":"04004",
    "sg:province":"Almer\u00eda",
    "wof:name":"Mullor Rodriguez Carmen",
    "wof:placetype":"venue"
},
  "geometry": {"coordinates":[-2.4603099823,36.843460083],"type":"Point"}
}