{
  "type": "Feature",
  "properties": {
    "iso:country":"ES",
    "sg:address":"Calle de Acera Del Darro, 96",
    "sg:city":"Granada",
    "sg:orig_category":"Farmacias",
    "sg:phone":"+34 958 26 37 20",
    "sg:postcode":"18005",
    "sg:province":"Granada",
    "wof:name":"Perales Lopez Celia",
    "wof:placetype":"venue"
},
  "geometry": {"coordinates":[-3.5967955589,37.1688308716],"type":"Point"}
}