{
  "type": "Feature",
  "properties": {
    "addr:full":"Calle de Montesa, 51 Madrid Madrid 28006",
    "addr:housenumber":"51",
    "addr:postcode":"madrid;28006",
    "addr:street":"Calle De Montesa",
    "iso:country":"ES",
    "sg:address":"Calle de Montesa, 51",
    "sg:city":"Madrid",
    "sg:orig_category":"Inmobiliaria (agencias)",
    "sg:phone":"+34 914 02 23 39",
    "sg:postcode":"28006",
    "sg:province":"Madrid",
    "sg:website":"www.grpo-atico.net",
    "wof:name":"Atico Servicios Inmobiliarios S.l.",
    "wof:placetype":"venue"
},
  "geometry": {"coordinates":[-3.6722741127,40.4290122986],"type":"Point"}
}