{
  "type": "Feature",
  "properties": {
    "addr:full":"Cami Ral, S/n Cantonigros Barcelona 08569",
    "addr:housenumber":"s",
    "addr:postcode":"08569",
    "addr:street":"Ral;/ N Cantonigros",
    "iso:country":"ES",
    "sg:address":"Cami Ral, S/n",
    "sg:city":"Cantonigros",
    "sg:orig_category":"Controles De Edificaci\u00d3n (construcci\u00d3n, Seguridad)",
    "sg:phone":"+34 938 56 51 00",
    "sg:postcode":"08569",
    "sg:province":"Barcelona",
    "wof:name":"Finques Cantoni S.l.",
    "wof:placetype":"venue"
},
  "geometry": {"coordinates":[2.4056448936,42.042339325],"type":"Point"}
}