{
  "type": "Feature",
  "properties": {
    "addr:full":"Calle de Berdigon, 24 Huelva Huelva 21003",
    "addr:housenumber":"24",
    "addr:postcode":"21003",
    "addr:street":"Calle De Berdigon",
    "iso:country":"ES",
    "sg:address":"Calle de Berdigon, 24",
    "sg:city":"Huelva",
    "sg:orig_category":"\u00d3ptica: Instrumentos (fabricaci\u00d3n)",
    "sg:phone":"+34 959 25 46 46",
    "sg:postcode":"21003",
    "sg:province":"Huelva",
    "wof:name":"Garquinvision S.l.",
    "wof:placetype":"venue"
},
  "geometry": {"coordinates":[-6.9487733841,37.2551307678],"type":"Point"}
}