{
  "type": "Feature",
  "properties": {
    "iso:country":"ES",
    "sg:address":"Ptge Fraser Lawton, 17",
    "sg:city":"Sabadell",
    "sg:orig_category":"Transportes Por Carretera: Lotes Completos, Mercanc\u00cdas Diversas",
    "sg:phone":"+34 937 27 24 90",
    "sg:postcode":"08205",
    "sg:province":"Barcelona",
    "wof:name":"Mega-valles S.c.c.l.",
    "wof:placetype":"venue"
},
  "geometry": {"coordinates":[2.1006600857,41.542301178],"type":"Point"}
}