{
  "type": "Feature",
  "properties": {
    "addr:full":"Calle de Tanca (la), S/n Vilafames Castell\u00f3n 12192",
    "addr:postcode":"12192",
    "addr:street":"Calle De Tanca La S / N;Castello\u0301N",
    "iso:country":"ES",
    "sg:address":"Calle de Tanca (la), S/n",
    "sg:city":"Vilafames",
    "sg:orig_category":"Poller\u00cda Y Caza (al Por Menor)",
    "sg:phone":"+34 964 76 06 49",
    "sg:postcode":"12192",
    "sg:province":"Castell\u00f3n",
    "wof:name":"Belles Julian Elisa",
    "wof:placetype":"venue"
},
  "geometry": {"coordinates":[-0.0640499964,40.1220092773],"type":"Point"}
}