{
  "type": "Feature",
  "properties": {
    "addr:full":"Plaz Cristo (el), 1 Ponferrada Le\u00f3n 24400",
    "addr:postcode":"24400",
    "iso:country":"ES",
    "sg:address":"Plaz Cristo (el), 1",
    "sg:city":"Ponferrada",
    "sg:orig_category":"Panader\u00cdas, Panader\u00cdas",
    "sg:phone":"+34 987 40 29 61",
    "sg:postcode":"24400",
    "sg:province":"Le\u00f3n",
    "wof:name":"Confiteria Pili S.a.",
    "wof:placetype":"venue"
},
  "geometry": {"coordinates":[-6.5970311165,42.5471763611],"type":"Point"}
}