{
  "type": "Feature",
  "properties": {
    "iso:country":"ES",
    "sg:address":"Calle de San Melchor Garcia Sampedro, 11",
    "sg:city":"Oviedo",
    "sg:orig_category":"Aparatos, Sistemas De Tele",
    "sg:phone":"+34 985 22 27 42",
    "sg:postcode":"33009",
    "sg:province":"Asturias",
    "wof:name":"Tapia Electroacustica S.l.",
    "wof:placetype":"venue"
},
  "geometry": {"coordinates":[-5.8405017853,43.3577003479],"type":"Point"}
}