{
  "type": "Feature",
  "properties": {
    "addr:full":"Calle de Mochuelo, 5 Madrid Madrid 28019",
    "addr:housenumber":"5",
    "addr:postcode":"28019",
    "addr:street":"Calle De Mochuelo",
    "iso:country":"ES",
    "sg:address":"Calle de Mochuelo, 5",
    "sg:city":"Madrid",
    "sg:orig_category":"Carnicer\u00cdas, Carnicer\u00cdas",
    "sg:phone":"+34 914 61 84 71",
    "sg:postcode":"28019",
    "sg:province":"Madrid",
    "wof:name":"Abril Benitez Rafael",
    "wof:placetype":"venue"
},
  "geometry": {"coordinates":[-3.737339,40.396137],"type":"Point"}
}