{
  "type": "Feature",
  "properties": {
    "iso:country":"ES",
    "sg:address":"Carrer de Calvet, 48",
    "sg:city":"Barcelona",
    "sg:orig_category":"Florister\u00cdas",
    "sg:phone":"+34 932 02 11 90",
    "sg:postcode":"08021",
    "sg:province":"Barcelona",
    "wof:name":"Rochelsberg  Klaus Friedrich",
    "wof:placetype":"venue"
},
  "geometry": {"coordinates":[2.1431939602,41.3950614929],"type":"Point"}
}