{
  "type": "Feature",
  "properties": {
    "addr:full":"Calle de Escuelas, 1 Ribera Fresno Badajoz 06225",
    "addr:housenumber":"1",
    "addr:postcode":"06225",
    "addr:street":"Calle De Escuelas",
    "iso:country":"ES",
    "sg:address":"Calle de Escuelas, 1",
    "sg:city":"Ribera Fresno",
    "sg:orig_category":"Centros De Coordinaci\u00d3n",
    "sg:phone":"+34 924 53 73 12",
    "sg:postcode":"06225",
    "sg:province":"Badajoz",
    "wof:name":"Fernandez Gonzalez Isabel",
    "wof:placetype":"venue"
},
  "geometry": {"coordinates":[-6.236137867,38.5537185669],"type":"Point"}
}