{
  "type": "Feature",
  "properties": {
    "addr:full":"Cami Vell De Miralcamp, S/n Mollerussa Lleida 25230",
    "addr:housenumber":"s / n",
    "addr:postcode":"25230",
    "addr:street":"Cami Vell De Miralcamp",
    "iso:country":"ES",
    "sg:address":"Cami Vell De Miralcamp, S/n",
    "sg:city":"Mollerussa",
    "sg:orig_category":"Postigos, Persianas Y Celos\u00cdas",
    "sg:phone":"+34 973 60 07 90",
    "sg:postcode":"25230",
    "sg:province":"Lleida",
    "wof:name":"Aceituno Freixes Antonio",
    "wof:placetype":"venue"
},
  "geometry": {"coordinates":[0.8912426233,41.6200370789],"type":"Point"}
}