{
  "type": "Feature",
  "properties": {
    "addr:full":"Carrer de Barca, 18 Canyelles-almadrava-puig-rom Girona 17480",
    "addr:housenumber":"18",
    "addr:postcode":"17480",
    "addr:street":"Carrer De Barca",
    "iso:country":"ES",
    "sg:address":"Carrer de Barca, 18",
    "sg:city":"Canyelles-almadrava-puig-rom",
    "sg:orig_category":"Centros De Educaci\u00d3n Especial",
    "sg:phone":"+34 972 25 57 57",
    "sg:postcode":"17480",
    "sg:province":"Girona",
    "wof:name":"Mora Marba Pere",
    "wof:placetype":"venue"
},
  "geometry": {"coordinates":[3.1663351059,42.2661399841],"type":"Point"}
}