{
  "type": "Feature",
  "properties": {
    "iso:country":"ES",
    "sg:address":"Plaz Brisas, S/n",
    "sg:city":"Santander",
    "sg:orig_category":"Sociedades, Compa\u00d1\u00cdas Aseguradoras",
    "sg:phone":"+34 942 36 01 80",
    "sg:postcode":"39005",
    "sg:province":"Cantabria",
    "wof:name":"France Telecom Espa\u00d1a S.a.",
    "wof:placetype":"venue"
},
  "geometry": {"coordinates":[-3.7857089043,43.4739151001],"type":"Point"}
}