{
  "type": "Feature",
  "properties": {
    "iso:country":"ES",
    "sg:address":"Plaz General Primo De Rivera, 1",
    "sg:city":"Oviedo",
    "sg:orig_category":"Estancos",
    "sg:phone":"+34 985 29 32 45",
    "sg:postcode":"33001",
    "sg:province":"Asturias",
    "wof:name":"Pati\u00f1o Esteban Maria Teresa",
    "wof:placetype":"venue"
},
  "geometry": {"coordinates":[-5.8500437737,43.3675575256],"type":"Point"}
}