{
  "type": "Feature",
  "properties": {
    "addr:full":"Calle de Jorge Cocci, 1 Zaragoza Zaragoza 50002",
    "addr:housenumber":"1",
    "addr:postcode":"50002",
    "addr:street":"Calle De Jorge Cocci",
    "iso:country":"ES",
    "sg:address":"Calle de Jorge Cocci, 1",
    "sg:city":"Zaragoza",
    "sg:orig_category":"Frutas Y Legumbres Frescas (al Por Mayor)",
    "sg:phone":"+34 976 29 90 01",
    "sg:postcode":"50002",
    "sg:province":"Zaragoza",
    "wof:name":"Frutas Mimadas S.l.",
    "wof:placetype":"venue"
},
  "geometry": {"coordinates":[-0.8705940247,41.6488952637],"type":"Point"}
}