{
  "type": "Feature",
  "properties": {
    "addr:full":"Rond Valencia, 16 Madrid Madrid 28012",
    "addr:housenumber":"16",
    "addr:postcode":"madrid;28012",
    "addr:street":"Valencia",
    "iso:country":"ES",
    "sg:address":"Rond Valencia, 16",
    "sg:city":"Madrid",
    "sg:orig_category":"Reposter\u00cdas",
    "sg:phone":"+34 915 39 00 49",
    "sg:postcode":"28012",
    "sg:province":"Madrid",
    "wof:name":"Rodriguez Mendieta Maria Angeles",
    "wof:placetype":"venue"
},
  "geometry": {"coordinates":[-3.7003099918,40.4072608948],"type":"Point"}
}