{
  "type": "Feature",
  "properties": {
    "iso:country":"ES",
    "sg:address":"Carrer de Cigne, 12",
    "sg:city":"Barcelona",
    "sg:orig_category":"Ropa Para Ni\u00d1os (al Por Menor)",
    "sg:phone":"+34 932 37 89 12",
    "sg:postcode":"08012",
    "sg:province":"Barcelona",
    "wof:name":"Martin Prat Maria Montserrat",
    "wof:placetype":"venue"
},
  "geometry": {"coordinates":[2.1536870003,41.400592804],"type":"Point"}
}