{
  "type": "Feature",
  "properties": {
    "iso:country":"ES",
    "sg:address":"Plaz Nuestra Se\u00d1ora Del Carmen, 25",
    "sg:city":"Palenciana",
    "sg:orig_category":"Telas Y Sedas (al Por Menor)",
    "sg:phone":"+34 957 53 50 15",
    "sg:postcode":"14914",
    "sg:province":"C\u00f3rdoba",
    "wof:name":"Garcia Hurtado Francisco",
    "wof:placetype":"venue"
},
  "geometry": {"coordinates":[-4.5832791328,37.248840332],"type":"Point"}
}