{
  "type": "Feature",
  "properties": {
    "iso:country":"ES",
    "sg:address":"Calle de Rafael De Muro, S/n",
    "sg:city":"Algeciras",
    "sg:orig_category":"Centros De Coordinaci\u00d3n",
    "sg:phone":"+34 956 66 42 28",
    "sg:postcode":"11201",
    "sg:province":"C\u00e1diz",
    "wof:name":"Bellver-candela S. A.",
    "wof:placetype":"venue"
},
  "geometry": {"coordinates":[-5.4459338188,36.1292190552],"type":"Point"}
}