{
  "type": "Feature",
  "properties": {
    "addr:full":"Calle de Hacienda De Pavones, 10 Madrid Madrid 28030",
    "addr:housenumber":"10",
    "addr:postcode":"madrid;28030",
    "addr:street":"Calle De Hacienda De Pavones",
    "iso:country":"ES",
    "sg:address":"Calle de Hacienda De Pavones, 10",
    "sg:city":"Madrid",
    "sg:orig_category":"Farmacias",
    "sg:phone":"+34 914 39 38 77",
    "sg:postcode":"28030",
    "sg:province":"Madrid",
    "wof:name":"Canales Aguirre Ana",
    "wof:placetype":"venue"
},
  "geometry": {"coordinates":[-3.6481149197,40.4039649963],"type":"Point"}
}