{
  "type": "Feature",
  "properties": {
    "addr:full":"Carrer de Martinez De La Rosa, 66 Barcelona Barcelona 08012",
    "addr:housenumber":"66",
    "addr:postcode":"08012",
    "addr:street":"Carrer De Martinez De La Rosa",
    "iso:country":"ES",
    "sg:address":"Carrer de Martinez De La Rosa, 66",
    "sg:city":"Barcelona",
    "sg:orig_category":"Traductores",
    "sg:phone":"+34 932 18 97 58",
    "sg:postcode":"08012",
    "sg:province":"Barcelona",
    "sg:website":"www.volaverun.com",
    "wof:name":"Zander Vilaclara Cristina",
    "wof:placetype":"venue"
},
  "geometry": {"coordinates":[2.157720089,41.4010353088],"type":"Point"}
}