{
  "type": "Feature",
  "properties": {
    "addr:full":"Carrer de Antoni De Campmany, 7 Barcelona Barcelona 08028",
    "addr:housenumber":"7",
    "addr:postcode":"08028",
    "addr:street":"Carrer De Antoni De Campmany",
    "iso:country":"ES",
    "sg:address":"Carrer de Antoni De Campmany, 7",
    "sg:city":"Barcelona",
    "sg:orig_category":"Maquinaria Y Herramientas Para Madera, Pvc, Aluminio Y Aperos (fabricaci\u00d3n, Comercio)",
    "sg:phone":"+34 934 22 37 32",
    "sg:postcode":"08028",
    "sg:province":"Barcelona",
    "wof:name":"Virutex S. A.",
    "wof:placetype":"venue"
},
  "geometry": {"coordinates":[2.1302490234,41.3703994751],"type":"Point"}
}