{
  "type": "Feature",
  "properties": {
    "addr:full":"Calle de Ledesma, 46 Madrid Madrid 28017",
    "addr:housenumber":"46",
    "addr:postcode":"madrid;28017",
    "addr:street":"Calle De Ledesma",
    "iso:country":"ES",
    "sg:address":"Calle de Ledesma, 46",
    "sg:city":"Madrid",
    "sg:orig_category":"Farmacias",
    "sg:phone":"+34 914 07 89 12",
    "sg:postcode":"28017",
    "sg:province":"Madrid",
    "wof:name":"Martinez Villanueva Angeles",
    "wof:placetype":"venue"
},
  "geometry": {"coordinates":[-3.646780014,40.4284973145],"type":"Point"}
}