{
  "type": "Feature",
  "properties": {
    "iso:country":"ES",
    "sg:address":"Calle de Afueras, S/n",
    "sg:city":"Berbegal",
    "sg:orig_category":"Maquinaria Para Industrias Diversas",
    "sg:phone":"+34 974 30 14 61",
    "sg:postcode":"22131",
    "sg:province":"Huesca",
    "wof:name":"Navarro Bometon Francisco Javier",
    "wof:placetype":"venue"
},
  "geometry": {"coordinates":[-0.0093265995,41.9692382812],"type":"Point"}
}