{
  "type": "Feature",
  "properties": {
    "addr:full":"Calle de Joaquin Costa, 27 Santander Cantabria 39005",
    "addr:housenumber":"27",
    "addr:postcode":"39005",
    "addr:street":"Calle De Joaquin Costa",
    "iso:country":"ES",
    "sg:address":"Calle de Joaquin Costa, 27",
    "sg:city":"Santander",
    "sg:orig_category":"Arquitectos",
    "sg:phone":"+34 942 27 20 18",
    "sg:postcode":"39005",
    "sg:province":"Cantabria",
    "wof:name":"Oryges Ingenieros S.l.",
    "wof:placetype":"venue"
},
  "geometry": {"coordinates":[-3.7843799591,43.4695510864],"type":"Point"}
}