{
  "type": "Feature",
  "properties": {
    "iso:country":"ES",
    "sg:address":"Avda Gutierrez Mellado, 74",
    "sg:city":"Molina Segura",
    "sg:orig_category":"Electricidad Veh\u00cdculo",
    "sg:phone":"+34 968 64 19 96",
    "sg:postcode":"30500",
    "sg:province":"Murcia",
    "wof:name":"Talleres Ros Abellan S.l.",
    "wof:placetype":"venue"
},
  "geometry": {"coordinates":[-1.2083740234,38.0611572266],"type":"Point"}
}