{
  "type": "Feature",
  "properties": {
    "iso:country":"ES",
    "sg:address":"Ctra. Ncnal. Seiscientos Treinta, Km. 0474,4",
    "sg:city":"Plasencia",
    "sg:orig_category":"Reposter\u00cdas",
    "sg:phone":"+34 927 42 53 30",
    "sg:postcode":"10600",
    "sg:province":"C\u00e1ceres",
    "wof:name":"Panificadora Extreme\u00d1a S.l.",
    "wof:placetype":"venue"
},
  "geometry": {"coordinates":[-6.0898518562,40.0299453735],"type":"Point"}
}