{
  "type": "Feature",
  "properties": {
    "addr:full":"Calle de Pablo Neruda, 36 Santiponce Sevilla 41970",
    "addr:housenumber":"36",
    "addr:postcode":"41970",
    "addr:street":"Calle De Pablo Neruda",
    "iso:country":"ES",
    "sg:address":"Calle de Pablo Neruda, 36",
    "sg:city":"Santiponce",
    "sg:classifiers":[
        {
            "category":"Autos & Motor Vehicles",
            "subcategory":"Automobile Sales",
            "type":"Retail Goods"
        }
    ],
    "sg:phone":"+34 955 99 66 84",
    "sg:postcode":"41970",
    "sg:province":"Sevilla",
    "wof:name":"Fuentes Cervantes Jose Maria",
    "wof:placetype":"venue"
},
  "geometry": {"coordinates":[-6.0414662361,37.4356269836],"type":"Point"}
}