{
  "type": "Feature",
  "properties": {
    "addr:full":"Montenegro, 2 El Barco Avila \u00c1vila 05600",
    "addr:housenumber":"2",
    "addr:postcode":"05600",
    "addr:street":"Montenegro;A\u0301Vila",
    "iso:country":"ES",
    "sg:address":"Montenegro, 2",
    "sg:city":"El Barco Avila",
    "sg:orig_category":"Agencias Y Agentes Comerciales, Representantes",
    "sg:phone":"+34 920 34 13 26",
    "sg:postcode":"05600",
    "sg:province":"\u00c1vila",
    "wof:name":"Blesa Saiz Juan Jose",
    "wof:placetype":"venue"
},
  "geometry": {"coordinates":[-5.5217738152,40.3557319641],"type":"Point"}
}