{
  "type": "Feature",
  "properties": {
    "iso:country":"ES",
    "sg:address":"Ctra. Soria, S/n",
    "sg:city":"S. Esteban Gormaz",
    "sg:orig_category":"Cr\u00cda De Animales",
    "sg:phone":"+34 975 35 04 53",
    "sg:postcode":"42330",
    "sg:province":"Soria",
    "wof:name":"Molinero Rubio Emilio",
    "wof:placetype":"venue"
},
  "geometry": {"coordinates":[-3.1995689869,41.5723457336],"type":"Point"}
}