{
  "type": "Feature",
  "properties": {
    "iso:country":"ES",
    "sg:address":"Plaz Dr Mara\u00d1on (del), 4",
    "sg:city":"Coslada",
    "sg:orig_category":"Juegos Y Juguetes (al Por Menor)",
    "sg:phone":"+34 916 71 35 38",
    "sg:postcode":"28820",
    "sg:province":"Madrid",
    "wof:name":"Gandul Sanz Maria Teresa",
    "wof:placetype":"venue"
},
  "geometry": {"coordinates":[-3.562046051,40.4261131287],"type":"Point"}
}