{
  "type": "Feature",
  "properties": {
    "iso:country":"ES",
    "sg:address":"Calle de Jose Maria Pereda, 5",
    "sg:city":"Reinosa",
    "sg:orig_category":"Ense\u00d1anza: Idiomas",
    "sg:phone":"+34 942 75 51 23",
    "sg:postcode":"39200",
    "sg:province":"Cantabria",
    "wof:name":"Villanueva Ayestaran Maria Aranzazu",
    "wof:placetype":"venue"
},
  "geometry": {"coordinates":[-4.1390070915,43.0027809143],"type":"Point"}
}