{
  "type": "Feature",
  "properties": {
    "iso:country":"ES",
    "sg:address":"Av Comte De Llobregat, 36",
    "sg:city":"Martorell",
    "sg:orig_category":"Agentes, Concesionarios Y Sucursales De Veh\u00cdculos",
    "sg:phone":"+34 937 75 48 60",
    "sg:postcode":"08760",
    "sg:province":"Barcelona",
    "wof:name":"Fortuny Mulet David",
    "wof:placetype":"venue"
},
  "geometry": {"coordinates":[1.9194589853,41.4827537537],"type":"Point"}
}