{
  "type": "Feature",
  "properties": {
    "iso:country":"ES",
    "sg:address":"Carrer de Rius I Taulet, 1",
    "sg:city":"Poblenou",
    "sg:orig_category":"Notarios",
    "sg:phone":"+34 937 62 65 43",
    "sg:postcode":"08397",
    "sg:province":"Barcelona",
    "wof:name":"Lopez Leis Gonzalez Santiago",
    "wof:placetype":"venue"
},
  "geometry": {"coordinates":[2.6730279922,41.6171875],"type":"Point"}
}