{
  "type": "Feature",
  "properties": {
    "iso:country":"ES",
    "sg:address":"Avda Osa Mayor, 76",
    "sg:city":"Madrid",
    "sg:orig_category":"Cajas De Ahorro",
    "sg:phone":"+34 913 07 94 43",
    "sg:postcode":"28023",
    "sg:province":"Madrid",
    "wof:name":"Caja Espa\u00f1a De Inversiones Caja De Ahorros Y Monte De Piedad",
    "wof:placetype":"venue"
},
  "geometry": {"coordinates":[-3.7835400105,40.4592094421],"type":"Point"}
}