{
  "type": "Feature",
  "properties": {
    "iso:country":"ES",
    "sg:address":"Calle de Campo De La Cruz, 11",
    "sg:city":"Ponferrada",
    "sg:orig_category":"Agentes, Concesionarios Y Sucursales De Veh\u00cdculos",
    "sg:phone":"+34 987 40 96 52",
    "sg:postcode":"24400",
    "sg:province":"Le\u00f3n",
    "wof:name":"Macoca S.a.",
    "wof:placetype":"venue"
},
  "geometry": {"coordinates":[-6.588391304,42.5481109619],"type":"Point"}
}