{
  "type": "Feature",
  "properties": {
    "addr:full":"Ronda Norte, S/n El Altet Alicante 03195",
    "addr:housenumber":"s / n",
    "addr:postcode":"03195",
    "addr:street":"Ronda Norte",
    "iso:country":"ES",
    "sg:address":"Ronda Norte, S/n",
    "sg:city":"El Altet",
    "sg:orig_category":"Frutas Y Legumbres Frescas (al Por Mayor)",
    "sg:phone":"+34 965 68 70 75",
    "sg:postcode":"03195",
    "sg:province":"Alicante",
    "wof:name":"Guillo Fuentes Manuel",
    "wof:placetype":"venue"
},
  "geometry": {"coordinates":[-0.5177140236,38.2559547424],"type":"Point"}
}