{
  "type": "Feature",
  "properties": {
    "addr:full":"Pol Ind Ciudadl Transporte Del Poniente, S/n Mojonera Almer\u00eda 04745",
    "addr:housenumber":"s / n",
    "addr:postcode":"04745",
    "iso:country":"ES",
    "sg:address":"Pol Ind Ciudadl Transporte Del Poniente, S/n",
    "sg:city":"Mojonera",
    "sg:orig_category":"Negocio De Materiales De Construcci\u00d3n",
    "sg:phone":"+34 950 62 20 45",
    "sg:postcode":"04745",
    "sg:province":"Almer\u00eda",
    "wof:name":"Sala Corbi S.l.",
    "wof:placetype":"venue"
},
  "geometry": {"coordinates":[-2.6811990738,36.7550849915],"type":"Point"}
}