{
  "type": "Feature",
  "properties": {
    "iso:country":"ES",
    "sg:address":"Carrer de Providencia, 7",
    "sg:city":"Barcelona",
    "sg:orig_category":"Peluqueros: De Se\u00d1oras",
    "sg:phone":"+34 932 17 75 75",
    "sg:postcode":"08024",
    "sg:province":"Barcelona",
    "wof:name":"Prous Torrelles Maria Rosa",
    "wof:placetype":"venue"
},
  "geometry": {"coordinates":[2.1553649902,41.405796051],"type":"Point"}
}