{
  "type": "Feature",
  "properties": {
    "addr:full":"Poli Elegarcu, S/n Cacicedo Cantabria 39608",
    "addr:housenumber":"s / n",
    "addr:postcode":"39608",
    "addr:street":"Poli Elegarcu",
    "iso:country":"ES",
    "sg:address":"Poli Elegarcu, S/n",
    "sg:city":"Cacicedo",
    "sg:orig_category":"Negocio De Materiales De Construcci\u00d3n",
    "sg:phone":"+34 942 25 34 63",
    "sg:postcode":"39608",
    "sg:province":"Cantabria",
    "wof:name":"Almacenes Lavin S. A.",
    "wof:placetype":"venue"
},
  "geometry": {"coordinates":[-3.8863019943,43.4352455139],"type":"Point"}
}