{
  "type": "Feature",
  "properties": {
    "iso:country":"ES",
    "sg:address":"Carrer de Pau (la), 58",
    "sg:city":"Muro Alcoy",
    "sg:orig_category":"Fotograf\u00cda Art\u00cdstica Y Retratos",
    "sg:phone":"+34 965 53 00 66",
    "sg:postcode":"03830",
    "sg:province":"Alicante",
    "wof:name":"Jorda Bonell Vicente",
    "wof:placetype":"venue"
},
  "geometry": {"coordinates":[-0.4345270097,38.7821731567],"type":"Point"}
}