{
  "type": "Feature",
  "properties": {
    "addr:full":"Calle de Valcarcel, 34 Santiago Ribera Murcia 30720",
    "addr:housenumber":"34",
    "addr:postcode":"30720",
    "addr:street":"Calle De Valcarcel",
    "iso:country":"ES",
    "sg:address":"Calle de Valcarcel, 34",
    "sg:city":"Santiago Ribera",
    "sg:orig_category":"Tintorer\u00cdas, Limpieza En Seco",
    "sg:phone":"+34 968 57 30 13",
    "sg:postcode":"30720",
    "sg:province":"Murcia",
    "wof:name":"Tintoreria Lavanderia Loli S.l.",
    "wof:placetype":"venue"
},
  "geometry": {"coordinates":[-0.8048210144,37.7965393066],"type":"Point"}
}