{
  "type": "Feature",
  "properties": {
    "addr:full":"Ctra Estacion, Km. 0002,0 Abaran Murcia 30550",
    "addr:postcode":"30550",
    "addr:street":"Ctra Estacion;0002,0",
    "iso:country":"ES",
    "sg:address":"Ctra Estacion, Km. 0002,0",
    "sg:city":"Abaran",
    "sg:orig_category":"Electricidad: Instaladores",
    "sg:phone":"+34 968 77 01 08",
    "sg:postcode":"30550",
    "sg:province":"Murcia",
    "wof:name":"Electrydesa",
    "wof:placetype":"venue"
},
  "geometry": {"coordinates":[-1.3346090317,38.2355575562],"type":"Point"}
}