{
  "type": "Feature",
  "properties": {
    "addr:full":"Calle de Baron De Patraix, 1 Valencia Valencia 46018",
    "addr:housenumber":"1",
    "addr:postcode":"46018",
    "addr:street":"Calle De Baron De Patraix",
    "iso:country":"ES",
    "sg:address":"Calle de Baron De Patraix, 1",
    "sg:city":"Valencia",
    "sg:orig_category":"Cajas Para Embalar",
    "sg:phone":"+34 963 17 40 49",
    "sg:postcode":"46018",
    "sg:province":"Valencia",
    "wof:name":"Caja Rural Del Mediterraneo Ruralcaja S Coop De Credito",
    "wof:placetype":"venue"
},
  "geometry": {"coordinates":[-0.3901821077,39.4621658325],"type":"Point"}
}