{
  "type": "Feature",
  "properties": {
    "addr:full":"Lasao Hiribidea, 1 Lasao Guip\u00f9zcoa 20740",
    "addr:housenumber":"1",
    "addr:postcode":"20740",
    "addr:street":"Lasao Hiribidea;Guipu\u0300Zcoa",
    "iso:country":"ES",
    "sg:address":"Lasao Hiribidea, 1",
    "sg:city":"Lasao",
    "sg:orig_category":"Establecimientos De Cura, Prevenci\u00d3n Y Readaptaci\u00d3n",
    "sg:phone":"+34 943 14 80 69",
    "sg:postcode":"20740",
    "sg:province":"Guip\u00f9zcoa",
    "wof:name":"Fundacion Izan-proyecto Hombre",
    "wof:placetype":"venue"
},
  "geometry": {"coordinates":[-2.2549140453,43.2378883362],"type":"Point"}
}