{
  "type": "Feature",
  "properties": {
    "addr:full":"Calle de Nu\u00d1ez De Balboa, 102 Madrid Madrid 28006",
    "addr:housenumber":"102",
    "addr:postcode":"28006",
    "addr:street":"Calle De Nun\u0303Ez De Balboa",
    "iso:country":"ES",
    "sg:address":"Calle de Nu\u00d1ez De Balboa, 102",
    "sg:city":"Madrid",
    "sg:orig_category":"Empresas De Limpieza",
    "sg:phone":"+34 915 62 48 97",
    "sg:postcode":"28006",
    "sg:province":"Madrid",
    "wof:name":"Majid Rezaeian",
    "wof:placetype":"venue"
},
  "geometry": {"coordinates":[-3.6817760468,40.4350700378],"type":"Point"}
}