{
  "type": "Feature",
  "properties": {
    "addr:full":"Carrer de Sant Genis De Rocafort, 4 Martorell Barcelona 08760",
    "addr:housenumber":"4",
    "addr:postcode":"08760",
    "addr:street":"Carrer De Sant Genis De Rocafort",
    "iso:country":"ES",
    "sg:address":"Carrer de Sant Genis De Rocafort, 4",
    "sg:city":"Martorell",
    "sg:orig_category":"Rectificaci\u00d3n, Mecanizado, Fresado",
    "sg:phone":"+34 937 75 04 56",
    "sg:postcode":"08760",
    "sg:province":"Barcelona",
    "wof:name":"Canals Piera Miguel",
    "wof:placetype":"venue"
},
  "geometry": {"coordinates":[1.9271190166,41.4726829529],"type":"Point"}
}