{
  "type": "Feature",
  "properties": {
    "iso:country":"ES",
    "sg:address":"Mercat Sant Antoni, 53",
    "sg:city":"Barcelona",
    "sg:orig_category":"Frutas, Legumbres Frescas Y Tempranas (al Por Menor)",
    "sg:phone":"+34 934 24 03 65",
    "sg:postcode":"08015",
    "sg:province":"Barcelona",
    "wof:name":"Polo Pages Teresa",
    "wof:placetype":"venue"
},
  "geometry": {"coordinates":[2.1635420322,41.3832588196],"type":"Point"}
}