{
  "type": "Feature",
  "properties": {
    "iso:country":"ES",
    "sg:address":"Calle de Marva, 17",
    "sg:city":"Valencia",
    "sg:orig_category":"Importaci\u00d3n",
    "sg:phone":"+34 963 41 12 80",
    "sg:postcode":"46007",
    "sg:province":"Valencia",
    "wof:name":"Top Quantum S.l.",
    "wof:placetype":"venue"
},
  "geometry": {"coordinates":[-0.3833619952,39.4634132385],"type":"Point"}
}