{
  "type": "Feature",
  "properties": {
    "addr:full":"Calle de Castellon, 20 Valencia Valencia 46004",
    "addr:housenumber":"20",
    "addr:postcode":"46004",
    "addr:street":"Calle De Castellon",
    "iso:country":"ES",
    "sg:address":"Calle de Castellon, 20",
    "sg:city":"Valencia",
    "sg:orig_category":"Importaci\u00d3n",
    "sg:phone":"+34 963 41 50 57",
    "sg:postcode":"46004",
    "sg:province":"Valencia",
    "wof:name":"I.s.v.group S.a.",
    "wof:placetype":"venue"
},
  "geometry": {"coordinates":[-0.3756256998,39.4647064209],"type":"Point"}
}