{
  "type": "Feature",
  "properties": {
    "addr:full":"Avda Federico Garcia Lorca, 8 Almeria Almer\u00eda 04004",
    "addr:housenumber":"8",
    "addr:postcode":"04004",
    "addr:street":"Avda Federico Garcia Lorca",
    "iso:country":"ES",
    "sg:address":"Avda Federico Garcia Lorca, 8",
    "sg:city":"Almeria",
    "sg:orig_category":"Ingenier\u00cda, Centros De Estudios (diversos)",
    "sg:phone":"+34 950 25 21 24",
    "sg:postcode":"04004",
    "sg:province":"Almer\u00eda",
    "wof:name":"Serra Lorenzo Ana Fe",
    "wof:placetype":"venue"
},
  "geometry": {"coordinates":[-2.462282896,36.8361053467],"type":"Point"}
}