{
  "type": "Feature",
  "properties": {
    "addr:full":"Avda Cristobal De Murrieta, 21 Santurtzi Vizcaya 48980",
    "addr:housenumber":"21",
    "addr:postcode":"48980",
    "addr:street":"Avda Cristobal De Murrieta",
    "iso:country":"ES",
    "sg:address":"Avda Cristobal De Murrieta, 21",
    "sg:city":"Santurtzi",
    "sg:orig_category":"Restaurantes",
    "sg:phone":"+34 944 93 73 08",
    "sg:postcode":"48980",
    "sg:province":"Vizcaya",
    "wof:name":"Restaurante Currito S. L.",
    "wof:placetype":"venue"
},
  "geometry": {"coordinates":[-3.0402638912,43.3327636719],"type":"Point"}
}