{
  "type": "Feature",
  "properties": {
    "addr:full":"Calle de Oriente, 14 Valencia Valencia 46006",
    "addr:housenumber":"14",
    "addr:postcode":"46006",
    "addr:street":"Calle De Oriente",
    "iso:country":"ES",
    "sg:address":"Calle de Oriente, 14",
    "sg:city":"Valencia",
    "sg:orig_category":"Pintores",
    "sg:phone":"+34 963 33 99 33",
    "sg:postcode":"46006",
    "sg:province":"Valencia",
    "wof:name":"Segrelles Del Pilar Eustaquio",
    "wof:placetype":"venue"
},
  "geometry": {"coordinates":[-0.3622399867,39.4587211609],"type":"Point"}
}