{
  "type": "Feature",
  "properties": {
    "addr:full":"Carrer de Proven\u00c7a, 386 Barcelona Barcelona 08025",
    "addr:housenumber":"386",
    "addr:postcode":"08025",
    "addr:street":"Carrer De Provenc\u0327A",
    "iso:country":"ES",
    "sg:address":"Carrer de Proven\u00c7a, 386",
    "sg:city":"Barcelona",
    "sg:orig_category":"Laboratorios Farmac\u00c9uticos",
    "sg:phone":"+34 932 08 03 34",
    "sg:postcode":"08025",
    "sg:province":"Barcelona",
    "wof:name":"Laboratorios Vi\u00f1as S.a.",
    "wof:placetype":"venue"
},
  "geometry": {"coordinates":[2.1697969437,41.4007835388],"type":"Point"}
}