{
  "type": "Feature",
  "properties": {
    "addr:full":"Calle de Pilar, 7 Sevilla Sevilla 41018",
    "addr:housenumber":"7",
    "addr:postcode":"41018",
    "addr:street":"Calle De Pilar",
    "iso:country":"ES",
    "sg:address":"Calle de Pilar, 7",
    "sg:city":"Sevilla",
    "sg:orig_category":"Abogados",
    "sg:phone":"+34 954 57 08 43",
    "sg:postcode":"41018",
    "sg:province":"Sevilla",
    "sg:website":"www.bufetegonzalez-dominguez.com",
    "wof:name":"Bufete Gonzalez Y Dominguez & Asociados S.c.",
    "wof:placetype":"venue"
},
  "geometry": {"coordinates":[-5.9764771461,37.3876037598],"type":"Point"}
}