{
  "type": "Feature",
  "properties": {
    "addr:full":"Helena, S/n Torrelamata Alicante 03188",
    "addr:housenumber":"s",
    "addr:postcode":"03188",
    "addr:street":"Helena;/ N Torrelamata",
    "iso:country":"ES",
    "sg:address":"Helena, S/n",
    "sg:city":"Torrelamata",
    "sg:orig_category":"Inmobiliaria (agencias)",
    "sg:phone":"+34 966 92 62 64",
    "sg:postcode":"03188",
    "sg:province":"Alicante",
    "wof:name":"Van Roosendael  Annie",
    "wof:placetype":"venue"
},
  "geometry": {"coordinates":[-0.6579220295,38.0312385559],"type":"Point"}
}