{
  "type": "Feature",
  "properties": {
    "addr:full":"Plaz Constitucion (de La), 7 Linea De La Concepcion C\u00e1diz 11300",
    "addr:housenumber":"7",
    "addr:postcode":"11300",
    "addr:street":"Ca\u0301Diz",
    "iso:country":"ES",
    "sg:address":"Plaz Constitucion (de La), 7",
    "sg:city":"Linea De La Concepcion",
    "sg:orig_category":"Parques De Atracciones Y Centros De Esparcimiento",
    "sg:phone":"+34 956 17 66 53",
    "sg:postcode":"11300",
    "sg:province":"C\u00e1diz",
    "wof:name":"Pemaca S.l.",
    "wof:placetype":"venue"
},
  "geometry": {"coordinates":[-5.3484587669,36.1610450745],"type":"Point"}
}