{
  "type": "Feature",
  "properties": {
    "addr:full":"Calle de Abajo, S/n Villarejo \u00c1vila 05120",
    "addr:housenumber":"s",
    "addr:postcode":"05120",
    "addr:street":"Calle De Abajo;/ N Villarejo A\u0301Vila",
    "iso:country":"ES",
    "sg:address":"Calle de Abajo, S/n",
    "sg:city":"Villarejo",
    "sg:orig_category":"Molduras, Junquillos, Listones Y Molduras Perforadas",
    "sg:phone":"+34 920 29 77 64",
    "sg:postcode":"05120",
    "sg:province":"\u00c1vila",
    "wof:name":"Gonzalez Martin Francisca",
    "wof:placetype":"venue"
},
  "geometry": {"coordinates":[-4.8206601143,40.4654006958],"type":"Point"}
}