{
  "type": "Feature",
  "properties": {
    "iso:country":"ES",
    "sg:address":"Calle de Estrella, 9",
    "sg:city":"Cangas",
    "sg:orig_category":"Administradores De Bienes Y Delegados De Comunidades De Propietarios",
    "sg:phone":"+34 986 30 58 38",
    "sg:postcode":"36940",
    "sg:province":"Pontevedra",
    "wof:name":"Pereiras Malvido Francisco",
    "wof:placetype":"venue"
},
  "geometry": {"coordinates":[-8.8184690475,42.2741928101],"type":"Point"}
}