{
  "type": "Feature",
  "properties": {
    "addr:full":"Carr Palleters, 3 Sueca Valencia 46410",
    "addr:housenumber":"3",
    "addr:postcode":"46410",
    "addr:street":"Carr Palleters",
    "iso:country":"ES",
    "sg:address":"Carr Palleters, 3",
    "sg:city":"Sueca",
    "sg:orig_category":"Peluqueros: De Se\u00d1oras",
    "sg:phone":"+34 961 70 18 58",
    "sg:postcode":"46410",
    "sg:province":"Valencia",
    "wof:name":"Baldovi Martinez Josefa",
    "wof:placetype":"venue"
},
  "geometry": {"coordinates":[-0.3124380112,39.2071647644],"type":"Point"}
}