{
  "type": "Feature",
  "properties": {
    "iso:country":"ES",
    "sg:address":"Alam Recalde, 54",
    "sg:city":"Bilbao",
    "sg:orig_category":"Agentes De Seguros",
    "sg:phone":"+34 944 10 22 56",
    "sg:postcode":"48008",
    "sg:province":"Vizcaya",
    "wof:name":"Risk & Insurances Services S. L.",
    "wof:placetype":"venue"
},
  "geometry": {"coordinates":[-2.9362139702,43.2604370117],"type":"Point"}
}