{
  "type": "Feature",
  "properties": {
    "addr:full":"Grup Parque Miraflores, 2 Sevilla Sevilla 41008",
    "addr:housenumber":"2",
    "addr:postcode":"41008",
    "iso:country":"ES",
    "sg:address":"Grup Parque Miraflores, 2",
    "sg:city":"Sevilla",
    "sg:orig_category":"Papeler\u00cdas, Librer\u00cdas",
    "sg:phone":"+34 954 95 84 15",
    "sg:postcode":"41008",
    "sg:province":"Sevilla",
    "wof:name":"Rojas Calderon Ana Maria",
    "wof:placetype":"venue"
},
  "geometry": {"coordinates":[-5.972949028,37.4099807739],"type":"Point"}
}