{
  "type": "Feature",
  "properties": {
    "iso:country":"ES",
    "sg:address":"Carrer de Ignasi Iglesias, 30",
    "sg:city":"Molins Rei",
    "sg:orig_category":"Masajes",
    "sg:phone":"+34 936 68 85 38",
    "sg:postcode":"08750",
    "sg:province":"Barcelona",
    "wof:name":"Holistic's 3 S.c.p.",
    "wof:placetype":"venue"
},
  "geometry": {"coordinates":[2.0178658962,41.4131393433],"type":"Point"}
}