{
  "type": "Feature",
  "properties": {
    "iso:country":"ES",
    "sg:address":"Calle de Arco, 10",
    "sg:city":"S. Clemente",
    "sg:orig_category":"Asesor\u00cda Fiscal Y Jur\u00cddica",
    "sg:phone":"+34 969 30 24 67",
    "sg:postcode":"16600",
    "sg:province":"Cuenca",
    "wof:name":"Martinez Moragon Maria Carmen",
    "wof:placetype":"venue"
},
  "geometry": {"coordinates":[-2.4296925068,39.4045524597],"type":"Point"}
}