{
  "type": "Feature",
  "properties": {
    "addr:full":"San Juan Kalea, 1 Eibar Guip\u00f9zcoa 20600",
    "addr:housenumber":"1",
    "addr:postcode":"20600",
    "addr:street":"San Juan Kalea;Guipu\u0300Zcoa",
    "iso:country":"ES",
    "sg:address":"San Juan Kalea, 1",
    "sg:city":"Eibar",
    "sg:orig_category":"Importaci\u00d3n",
    "sg:phone":"+34 943 20 33 29",
    "sg:postcode":"20600",
    "sg:province":"Guip\u00f9zcoa",
    "wof:name":"Garbi\u00f1e Ajuria Arrese (izadi)",
    "wof:placetype":"venue"
},
  "geometry": {"coordinates":[-2.473077774,43.1849517822],"type":"Point"}
}