{
  "type": "Feature",
  "properties": {
    "addr:full":"Calle de Quevedo, 24 Hellin Albacete 02400",
    "addr:housenumber":"24",
    "addr:postcode":"02400",
    "addr:street":"Calle De Quevedo",
    "iso:country":"ES",
    "sg:address":"Calle de Quevedo, 24",
    "sg:city":"Hellin",
    "sg:orig_category":"Contenedores (mercanc\u00cdas)",
    "sg:phone":"+34 967 30 13 52",
    "sg:postcode":"02400",
    "sg:province":"Albacete",
    "wof:name":"Lopez Diaz Jose",
    "wof:placetype":"venue"
},
  "geometry": {"coordinates":[-1.6905907393,38.507183075],"type":"Point"}
}