{
  "type": "Feature",
  "properties": {
    "iso:country":"ES",
    "sg:address":"Calle de Jeronima Llorente, 39",
    "sg:city":"Madrid",
    "sg:classifiers":[
        {
            "category":"Taxi",
            "type":"Transportation"
        }
    ],
    "sg:phone":"+34 914 59 68 05",
    "sg:postcode":"28039",
    "sg:province":"Madrid",
    "wof:name":"Sanchez Lopez Damian",
    "wof:placetype":"venue"
},
  "geometry": {"coordinates":[-3.707020998,40.4543418884],"type":"Point"}
}