{
  "type": "Feature",
  "properties": {
    "iso:country":"ES",
    "sg:address":"Carr Gardisso, S/n",
    "sg:city":"Vila",
    "sg:orig_category":"Restaurantes",
    "sg:phone":"+34 972 38 07 60",
    "sg:postcode":"17490",
    "sg:province":"Girona",
    "wof:name":"Castilla Valle Antonio",
    "wof:placetype":"venue"
},
  "geometry": {"coordinates":[3.1481759548,42.3640785217],"type":"Point"}
}