{
  "type": "Feature",
  "properties": {
    "addr:full":"Yumbo, S/n S. Agustin-playa Ingles Las Palmas 35100",
    "addr:housenumber":"s",
    "addr:postcode":"35100",
    "addr:street":"/ N S. Agustin-Playa",
    "iso:country":"ES",
    "sg:address":"Yumbo, S/n",
    "sg:city":"S. Agustin-playa Ingles",
    "sg:orig_category":"Asociaciones Y Clubs Deportivos",
    "sg:phone":"+34 928 77 07 27",
    "sg:postcode":"35100",
    "sg:province":"Las Palmas",
    "wof:name":"Comercial Macy's Canarias S.l.",
    "wof:placetype":"venue"
},
  "geometry": {"coordinates":[-15.4397096634,28.1302204132],"type":"Point"}
}