{
  "type": "Feature",
  "properties": {
    "iso:country":"ES",
    "sg:address":"Avda Perez Galdos, 25",
    "sg:city":"Valencia",
    "sg:orig_category":"Deportes Diversos",
    "sg:phone":"+34 963 85 95 08",
    "sg:postcode":"46018",
    "sg:province":"Valencia",
    "sg:website":"www.facv.es",
    "wof:name":"Federacion Valenciana De Atletismo",
    "wof:placetype":"venue"
},
  "geometry": {"coordinates":[-0.3882659972,39.4643745422],"type":"Point"}
}