{
  "type": "Feature",
  "properties": {
    "addr:full":"Calle de Santa Adela, 17 Madrid Madrid 28033",
    "addr:housenumber":"17",
    "addr:postcode":"madrid;28033",
    "addr:street":"Calle De Santa Adela",
    "iso:country":"ES",
    "sg:address":"Calle de Santa Adela, 17",
    "sg:city":"Madrid",
    "sg:orig_category":"Telas Y Sedas (al Por Menor)",
    "sg:phone":"+34 917 63 66 13",
    "sg:postcode":"28033",
    "sg:province":"Madrid",
    "wof:name":"Martin Guio Miguel Angel",
    "wof:placetype":"venue"
},
  "geometry": {"coordinates":[-3.6496551037,40.4782600403],"type":"Point"}
}