{
  "type": "Feature",
  "properties": {
    "addr:full":"Ctra. Camposines, Km. 0812,2 La Fatarella Tarragona 43781",
    "addr:postcode":"43781",
    "addr:street":"Ctra. Camposines Km. 0812,2",
    "iso:country":"ES",
    "sg:address":"Ctra. Camposines, Km. 0812,2",
    "sg:city":"La Fatarella",
    "sg:orig_category":"Distribuci\u00d3n De Petr\u00d3leo Y Derivados",
    "sg:phone":"+34 977 40 07 29",
    "sg:postcode":"43781",
    "sg:province":"Tarragona",
    "wof:name":"Vidal Abas Juan Bautista",
    "wof:placetype":"venue"
},
  "geometry": {"coordinates":[0.4747149944,41.1594734192],"type":"Point"}
}