{
  "type": "Feature",
  "properties": {
    "addr:full":"Pol La Residencia, 11 Castello Plana Castell\u00f3n 12004",
    "addr:housenumber":"11",
    "addr:postcode":"12004",
    "addr:street":"Pol La Residencia;Castello\u0301N",
    "iso:country":"ES",
    "sg:address":"Pol La Residencia, 11",
    "sg:city":"Castello Plana",
    "sg:orig_category":"Mec\u00c1nico Del Autom\u00d3vil",
    "sg:phone":"+34 964 25 42 95",
    "sg:postcode":"12004",
    "sg:province":"Castell\u00f3n",
    "wof:name":"Reparauto Castellon S.l.",
    "wof:placetype":"venue"
},
  "geometry": {"coordinates":[-0.0441690013,40.0043563843],"type":"Point"}
}