{
  "type": "Feature",
  "properties": {
    "addr:full":"Alto Infanzon, 5871 Gijon Asturias 33203",
    "addr:postcode":"5871;33203",
    "iso:country":"ES",
    "sg:address":"Alto Infanzon, 5871",
    "sg:city":"Gijon",
    "sg:orig_category":"Cr\u00cda De Animales",
    "sg:phone":"+34 985 36 87 20",
    "sg:postcode":"33203",
    "sg:province":"Asturias",
    "wof:name":"Suarez Meana Amancio",
    "wof:placetype":"venue"
},
  "geometry": {"coordinates":[-5.5962839127,43.5261116028],"type":"Point"}
}