{
  "type": "Feature",
  "properties": {
    "addr:full":"Calle de Cupido, 12 Puerto Cruz Santa Cruz De Tenerife 38400",
    "addr:housenumber":"12",
    "addr:postcode":"38400",
    "addr:street":"Calle De Cupido;Puerto Cruz",
    "iso:country":"ES",
    "sg:address":"Calle de Cupido, 12",
    "sg:city":"Puerto Cruz",
    "sg:orig_category":"Alquiler De Veh\u00cdculos: Turismos Y Utilitarios",
    "sg:phone":"+34 922 38 44 65",
    "sg:postcode":"38400",
    "sg:province":"Santa Cruz De Tenerife",
    "wof:name":"Rent A Car Durazno S.l.",
    "wof:placetype":"venue"
},
  "geometry": {"coordinates":[-16.5519886017,28.4145870209],"type":"Point"}
}