{
  "type": "Feature",
  "properties": {
    "addr:full":"Calle de Bravo Murillo, 36 Madrid Madrid 28015",
    "addr:housenumber":"36",
    "addr:postcode":"madrid;28015",
    "addr:street":"Calle De Bravo Murillo",
    "iso:country":"ES",
    "sg:address":"Calle de Bravo Murillo, 36",
    "sg:city":"Madrid",
    "sg:orig_category":"Agencias De Viajes",
    "sg:phone":"+34 914 46 06 80",
    "sg:postcode":"28015",
    "sg:province":"Madrid",
    "sg:website":"www.conchi_tormon.com",
    "wof:name":"Tormon Viajes",
    "wof:placetype":"venue"
},
  "geometry": {"coordinates":[-3.7040610313,40.4378204346],"type":"Point"}
}