{
  "type": "Feature",
  "properties": {
    "addr:full":"Via Aurelia, 1 Sabadell Barcelona 08206",
    "addr:housenumber":"1",
    "addr:postcode":"08206",
    "addr:street":"Via Aurelia",
    "iso:country":"ES",
    "sg:address":"Via Aurelia, 1",
    "sg:city":"Sabadell",
    "sg:orig_category":"Abogados",
    "sg:phone":"+34 937 16 59 21",
    "sg:postcode":"08206",
    "sg:province":"Barcelona",
    "wof:name":"Sanchez Lopez Miguel",
    "wof:placetype":"venue"
},
  "geometry": {"coordinates":[2.0949161053,41.555316925],"type":"Point"}
}