{
  "type": "Feature",
  "properties": {
    "addr:full":"Pesqueiras, 198 Boiro A Coru\u00f1a 15930",
    "addr:housenumber":"198",
    "addr:postcode":"15930",
    "addr:street":"Pesqueiras;Corun\u0303A",
    "iso:country":"ES",
    "sg:address":"Pesqueiras, 198",
    "sg:city":"Boiro",
    "sg:orig_category":"Administradores De Bienes Y Delegados De Comunidades De Propietarios",
    "sg:phone":"+34 981 84 86 99",
    "sg:postcode":"15930",
    "sg:province":"A Coru\u00f1a",
    "wof:name":"Vidal Mari\u00f1o Juan Pablo",
    "wof:placetype":"venue"
},
  "geometry": {"coordinates":[-8.8847093582,42.6471214294],"type":"Point"}
}