{
  "type": "Feature",
  "properties": {
    "addr:full":"Carr Metge Miguel Perez (del), 4 Lliria Valencia 46160",
    "addr:housenumber":"4",
    "addr:postcode":"46160",
    "addr:street":"Carr Metge Miguel Perez Del",
    "iso:country":"ES",
    "sg:address":"Carr Metge Miguel Perez (del), 4",
    "sg:city":"Lliria",
    "sg:orig_category":"Ense\u00d1anza: Profesiones Art\u00cdsticas",
    "sg:phone":"+34 962 78 08 47",
    "sg:postcode":"46160",
    "sg:province":"Valencia",
    "wof:name":"Ateneo Musical Y De Ense\u00d1anza Banda Primitiva",
    "wof:placetype":"venue"
},
  "geometry": {"coordinates":[-0.5974252224,39.6273117065],"type":"Point"}
}