{
  "type": "Feature",
  "properties": {
    "iso:country":"ES",
    "sg:address":"Carrer de Sant Salvador, 43",
    "sg:city":"Roda De Bara",
    "sg:orig_category":"Peluquer\u00cdas, Peluquer\u00cda Mixta",
    "sg:phone":"+34 977 65 71 06",
    "sg:postcode":"43883",
    "sg:province":"Tarragona",
    "wof:name":"Montagut G\u00fcell Maria Magdalena",
    "wof:placetype":"venue"
},
  "geometry": {"coordinates":[1.4699560404,41.1792793274],"type":"Point"}
}