{
  "type": "Feature",
  "properties": {
    "addr:full":"Calle de Jose Payan Garrido, 5 San Juan De Aznalfarache Sevilla 41920",
    "addr:housenumber":"5",
    "addr:postcode":"41920",
    "addr:street":"Calle De Jose Payan Garrido",
    "iso:country":"ES",
    "sg:address":"Calle de Jose Payan Garrido, 5",
    "sg:city":"San Juan De Aznalfarache",
    "sg:orig_category":"Paisajistas Asesor\u00cda",
    "sg:phone":"+34 954 76 01 56",
    "sg:postcode":"41920",
    "sg:province":"Sevilla",
    "wof:name":"Delicado Estevez Maria Luisa",
    "wof:placetype":"venue"
},
  "geometry": {"coordinates":[-6.0354700089,37.3591575623],"type":"Point"}
}