{
  "type": "Feature",
  "properties": {
    "iso:country":"ES",
    "sg:address":"Calle de Circunde, 12",
    "sg:city":"Logro\u00f1o",
    "sg:orig_category":"Metalurgia",
    "sg:phone":"+34 941 25 46 05",
    "sg:postcode":"26006",
    "sg:province":"La Rioja",
    "wof:name":"Impermeabilizaciones Hermanos Anguiano S.l.",
    "wof:placetype":"venue"
},
  "geometry": {"coordinates":[-2.399772644,42.4572982788],"type":"Point"}
}