{
  "type": "Feature",
  "properties": {
    "iso:country":"ES",
    "sg:address":"Calle de Juan Palo, 2",
    "sg:city":"Cordoba",
    "sg:orig_category":"Bisuter\u00cda, Joyer\u00cda, Relojer\u00cda (al Por Menor)",
    "sg:phone":"+34 957 49 05 57",
    "sg:postcode":"14002",
    "sg:province":"C\u00f3rdoba",
    "wof:name":"Crisolar S.a.",
    "wof:placetype":"venue"
},
  "geometry": {"coordinates":[-4.7678899765,37.8891487122],"type":"Point"}
}