{
  "type": "Feature",
  "properties": {
    "iso:country":"ES",
    "sg:address":"Calle de Galicia, 13",
    "sg:city":"Fuenlabrada",
    "sg:orig_category":"Centros Empresariales",
    "sg:phone":"+34 916 08 31 36",
    "sg:postcode":"28942",
    "sg:province":"Madrid",
    "wof:name":"Cheng  Zhengxu",
    "wof:placetype":"venue"
},
  "geometry": {"coordinates":[-3.8100879192,40.2955322266],"type":"Point"}
}