{
  "type": "Feature",
  "properties": {
    "iso:country":"ES",
    "sg:address":"Rua Ribeiro (do), 1",
    "sg:city":"Ribadavia",
    "sg:orig_category":"M\u00c9dicos: Estomatolog\u00cda",
    "sg:phone":"+34 988 47 04 56",
    "sg:postcode":"32400",
    "sg:province":"Ourense",
    "wof:name":"Charr Milano Ana Maria",
    "wof:placetype":"venue"
},
  "geometry": {"coordinates":[-8.1432886124,42.2903938293],"type":"Point"}
}