{
  "type": "Feature",
  "properties": {
    "addr:full":"Les Llargues, 2 Albal Valencia 46470",
    "addr:housenumber":"2",
    "addr:postcode":"46470",
    "iso:country":"ES",
    "sg:address":"Les Llargues, 2",
    "sg:city":"Albal",
    "sg:classifiers":[
        {
            "category":"Personal",
            "subcategory":"Barber",
            "type":"Services"
        }
    ],
    "sg:phone":"+34 961 26 54 60",
    "sg:postcode":"46470",
    "sg:province":"Valencia",
    "sg:tags":[
        "caballeros",
        "de",
        "peluqueros"
    ],
    "wof:name":"Garcia Soriano Agustin",
    "wof:placetype":"venue"
},
  "geometry": {"coordinates":[-0.4129010141,39.397480011],"type":"Point"}
}