{
  "type": "Feature",
  "properties": {
    "addr:full":"Carrer de Sant Josep, 1 Manresa Barcelona 08242",
    "addr:housenumber":"1",
    "addr:postcode":"08242",
    "addr:street":"Carrer De Sant Josep",
    "iso:country":"ES",
    "sg:address":"Carrer de Sant Josep, 1",
    "sg:city":"Manresa",
    "sg:orig_category":"Abogados",
    "sg:phone":"+34 938 74 61 25",
    "sg:postcode":"08242",
    "sg:province":"Barcelona",
    "wof:name":"Pinos Font Assessors S.l.",
    "wof:placetype":"venue"
},
  "geometry": {"coordinates":[1.8271689415,41.7317390442],"type":"Point"}
}