{
  "type": "Feature",
  "properties": {
    "iso:country":"ES",
    "sg:address":"Carr Joan Maragall, 44",
    "sg:city":"Girona",
    "sg:orig_category":"Agencias Y Agentes Comerciales, Representantes",
    "sg:phone":"+34 972 20 24 71",
    "sg:postcode":"17002",
    "sg:province":"Girona",
    "wof:name":"Comas Borrell Miquel",
    "wof:placetype":"venue"
},
  "geometry": {"coordinates":[2.81960392,41.9772949219],"type":"Point"}
}