{
  "type": "Feature",
  "properties": {
    "addr:full":"Calle de Maravillas, 10 Sevilla Sevilla 41003",
    "addr:housenumber":"10",
    "addr:postcode":"41003",
    "addr:street":"Calle De Maravillas",
    "iso:country":"ES",
    "sg:address":"Calle de Maravillas, 10",
    "sg:city":"Sevilla",
    "sg:orig_category":"Arquitectos",
    "sg:phone":"+34 954 37 26 36",
    "sg:postcode":"41003",
    "sg:province":"Sevilla",
    "wof:name":"Sanchez-monta\u00f1es Macias Benito",
    "wof:placetype":"venue"
},
  "geometry": {"coordinates":[-5.9882202148,37.3970184326],"type":"Point"}
}