{
  "type": "Feature",
  "properties": {
    "addr:full":"Rua Isidro Parga Pondal (de), 7 Santiago De Compostela A Coru\u00f1a 15702",
    "addr:housenumber":"7",
    "addr:postcode":"15702",
    "addr:street":"Rua Isidro Parga Pondal De;Corun\u0303A",
    "iso:country":"ES",
    "sg:address":"Rua Isidro Parga Pondal (de), 7",
    "sg:city":"Santiago De Compostela",
    "sg:orig_category":"Aguas (distribuci\u00d3n, Servicios)",
    "sg:phone":"+34 981 52 02 66",
    "sg:postcode":"15702",
    "sg:province":"A Coru\u00f1a",
    "wof:name":"Shang Filtracion De Fluidos S.l.",
    "wof:placetype":"venue"
},
  "geometry": {"coordinates":[-8.5435037613,42.864151001],"type":"Point"}
}