{
  "type": "Feature",
  "properties": {
    "iso:country":"ES",
    "sg:address":"Avda Jose Ortega Y Gasset, 121",
    "sg:city":"Malaga",
    "sg:orig_category":"Maquinaria Para Industrias Diversas",
    "sg:phone":"+34 952 34 89 80",
    "sg:postcode":"29006",
    "sg:province":"M\u00e1laga",
    "sg:website":"www.hnosperalhenares.com",
    "wof:name":"Hermanos Peral Henares Transportes Y Excavaciones S.l.",
    "wof:placetype":"venue"
},
  "geometry": {"coordinates":[-4.4522309303,36.7100334167],"type":"Point"}
}