{
  "type": "Feature",
  "properties": {
    "iso:country":"ES",
    "sg:address":"Avda Valencia, 47",
    "sg:city":"Ademuz",
    "sg:orig_category":"Asistencia Domiciliaria",
    "sg:phone":"+34 978 78 51 09",
    "sg:postcode":"46140",
    "sg:province":"Valencia",
    "wof:name":"Servira De Servicios Sociales S.l.",
    "wof:placetype":"venue"
},
  "geometry": {"coordinates":[-1.2864409685,40.0590705872],"type":"Point"}
}