{
  "type": "Feature",
  "properties": {
    "iso:country":"ES",
    "sg:address":"Carrer de Colom, 402",
    "sg:city":"Terrassa",
    "sg:orig_category":"Hilaturas, Hilos Y Actividades Relacionadas",
    "sg:phone":"+34 937 85 43 45",
    "sg:postcode":"08223",
    "sg:province":"Barcelona",
    "wof:name":"Encoladora Boher S.a.",
    "wof:placetype":"venue"
},
  "geometry": {"coordinates":[2.0267291069,41.5498733521],"type":"Point"}
}