{
  "type": "Feature",
  "properties": {
    "iso:country":"ES",
    "sg:address":"Avda Santiago Ramon Y Cajal, 15",
    "sg:city":"Badajoz",
    "sg:orig_category":"M\u00c9dicos: Medicina General",
    "sg:phone":"+34 924 22 99 33",
    "sg:postcode":"06001",
    "sg:province":"Badajoz",
    "wof:name":"Asuar Jurado Elena",
    "wof:placetype":"venue"
},
  "geometry": {"coordinates":[-6.9732613564,38.8799781799],"type":"Point"}
}