{
  "type": "Feature",
  "properties": {
    "addr:full":"Ctr. Saelices, Km. 0000,3 Villamayor Santiago Cuenca 16415",
    "addr:postcode":"16415",
    "addr:street":"Saelices Km. 0000,3 Villamayor;Cuenca",
    "iso:country":"ES",
    "sg:address":"Ctr. Saelices, Km. 0000,3",
    "sg:city":"Villamayor Santiago",
    "sg:orig_category":"Empresas De Carpinter\u00cda Met\u00c1lica",
    "sg:phone":"+34 969 13 91 26",
    "sg:postcode":"16415",
    "sg:province":"Cuenca",
    "wof:name":"Hermanos Lopez Calleja S.l.",
    "wof:placetype":"venue"
},
  "geometry": {"coordinates":[-2.9234220982,39.7301254272],"type":"Point"}
}