{
  "type": "Feature",
  "properties": {
    "iso:country":"ES",
    "sg:address":"Calle de Santa Clara, 2",
    "sg:city":"Granada",
    "sg:orig_category":"Empresas De Carpinter\u00cda Met\u00c1lica",
    "sg:phone":"+34 958 81 59 01",
    "sg:postcode":"18007",
    "sg:province":"Granada",
    "wof:name":"Crisalman S.l.",
    "wof:placetype":"venue"
},
  "geometry": {"coordinates":[-3.6003820896,37.1584243774],"type":"Point"}
}