{
  "type": "Feature",
  "properties": {
    "addr:full":"Calle de Lope De Vega, 9 Le\u00f3n Le\u00f3n 24002",
    "addr:housenumber":"9",
    "addr:postcode":"24002",
    "addr:street":"Calle De Lope De Vega;Leo\u0301N",
    "iso:country":"ES",
    "sg:address":"Calle de Lope De Vega, 9",
    "sg:city":"Le\u00f3n",
    "sg:orig_category":"M\u00c9dicos: Otorrinolaringolog\u00cda",
    "sg:phone":"+34 987 27 14 12",
    "sg:postcode":"24002",
    "sg:province":"Le\u00f3n",
    "wof:name":"Clinica Orl Dr. Alonso Alonso C.b.",
    "wof:placetype":"venue"
},
  "geometry": {"coordinates":[-5.5726089478,42.5996665955],"type":"Point"}
}