{
  "type": "Feature",
  "properties": {
    "iso:country":"ES",
    "sg:address":"Plaz Federico Wattenberg, S/n",
    "sg:city":"Valladolid",
    "sg:orig_category":"Guarder\u00cdas",
    "sg:phone":"+34 983 26 40 47",
    "sg:postcode":"47011",
    "sg:province":"Valladolid",
    "wof:name":"De La Red Mantilla Miguel Angel",
    "wof:placetype":"venue"
},
  "geometry": {"coordinates":[-4.7229890823,41.6566009521],"type":"Point"}
}