{
  "type": "Feature",
  "properties": {
    "iso:country":"ES",
    "sg:address":"Calle de Casimiro Sainz, 1",
    "sg:city":"Reinosa",
    "sg:orig_category":"Procuradores",
    "sg:phone":"+34 942 75 12 94",
    "sg:postcode":"39200",
    "sg:province":"Cantabria",
    "wof:name":"Fernandez Ruiz Martina",
    "wof:placetype":"venue"
},
  "geometry": {"coordinates":[-4.1394162178,42.9960594177],"type":"Point"}
}