{
  "type": "Feature",
  "properties": {
    "iso:country":"ES",
    "sg:address":"Calle de San Vicente De Paul, 39",
    "sg:city":"Zaragoza",
    "sg:orig_category":"Conservatorios",
    "sg:phone":"+34 976 20 22 05",
    "sg:postcode":"50001",
    "sg:province":"Zaragoza",
    "sg:website":"www.centros6.pntic.mec.es/conser.prof.de.musica.de.zaragoza/index.htm",
    "wof:name":"Conservatorio Profesional Estatal De Musica De Zaragoza",
    "wof:placetype":"venue"
},
  "geometry": {"coordinates":[-0.8741490245,41.654258728],"type":"Point"}
}