{
  "type": "Feature",
  "properties": {
    "iso:country":"ES",
    "sg:address":"Hornos(peal De Becerro), S/n",
    "sg:city":"Hornos",
    "sg:orig_category":"\u00c1rboles Frutales",
    "sg:phone":"+34 953 12 41 54",
    "sg:postcode":"23468",
    "sg:province":"Ja\u00e9n",
    "wof:name":"Encebras S.l.",
    "wof:placetype":"venue"
},
  "geometry": {"coordinates":[-2.7172999382,38.216091156],"type":"Point"}
}