{
  "type": "Feature",
  "properties": {
    "addr:full":"Avda Madrid (de), 44 Avila \u00c1vila 05001",
    "addr:housenumber":"44",
    "addr:postcode":"05001",
    "addr:street":"Avda Madrid De;A\u0301Vila",
    "iso:country":"ES",
    "sg:address":"Avda Madrid (de), 44",
    "sg:city":"Avila",
    "sg:orig_category":"Venta, Instalaci\u00d3n, Mantenimiento De Chimeneas De Interior Y Accesorios",
    "sg:phone":"+34 920 21 28 17",
    "sg:postcode":"05001",
    "sg:province":"\u00c1vila",
    "wof:name":"Jotul Y Moronta S. A.",
    "wof:placetype":"venue"
},
  "geometry": {"coordinates":[-4.6980261803,40.6588172913],"type":"Point"}
}