{
  "type": "Feature",
  "properties": {
    "iso:country":"ES",
    "sg:address":"Calle de Ramon Y Cajal, 81",
    "sg:city":"Alberic",
    "sg:orig_category":"Alimentaci\u00d3n Animal (fabricaci\u00d3n, Al Por Mayor)",
    "sg:phone":"+34 962 44 29 30",
    "sg:postcode":"46260",
    "sg:province":"Valencia",
    "wof:name":"Pons Aparisi Maria Amparo",
    "wof:placetype":"venue"
},
  "geometry": {"coordinates":[-0.5196430087,39.1203117371],"type":"Point"}
}