{
  "type": "Feature",
  "properties": {
    "addr:full":"Av Francesc Macia, 20 Riudoms Tarragona 43330",
    "addr:housenumber":"20",
    "addr:postcode":"43330",
    "addr:street":"Av Francesc Macia",
    "iso:country":"ES",
    "sg:address":"Av Francesc Macia, 20",
    "sg:city":"Riudoms",
    "sg:orig_category":"Reposter\u00cdas",
    "sg:phone":"+34 977 85 15 20",
    "sg:postcode":"43330",
    "sg:province":"Tarragona",
    "wof:name":"Domingo Guinjoan Juan Maria",
    "wof:placetype":"venue"
},
  "geometry": {"coordinates":[1.0504519939,41.1358451843],"type":"Point"}
}