{
  "type": "Feature",
  "properties": {
    "iso:country":"ES",
    "sg:address":"Calle de Joselito, 16",
    "sg:city":"Madrid",
    "sg:orig_category":"Ingenier\u00cda, Centros De Estudios (diversos)",
    "sg:phone":"+34 913 88 31 37",
    "sg:postcode":"28043",
    "sg:province":"Madrid",
    "wof:name":"Imj S.l.",
    "wof:placetype":"venue"
},
  "geometry": {"coordinates":[-3.6418709755,40.4537353516],"type":"Point"}
}