{
  "type": "Feature",
  "properties": {
    "iso:country":"ES",
    "sg:address":"Calle de Azorin, 9",
    "sg:city":"Torrent",
    "sg:orig_category":"Librer\u00cdas",
    "sg:phone":"+34 961 58 02 28",
    "sg:postcode":"46900",
    "sg:province":"Valencia",
    "wof:name":"Fuertes Herranz Maria Dolores",
    "wof:placetype":"venue"
},
  "geometry": {"coordinates":[-0.4770228863,39.4317741394],"type":"Point"}
}