{
  "type": "Feature",
  "properties": {
    "iso:country":"ES",
    "sg:address":"Gta Tamarindo (del), 12",
    "sg:city":"Aranjuez",
    "sg:orig_category":"Platos Preparados Refrigerados (fabricaci\u00d3n, Al Por Mayor)",
    "sg:phone":"+34 918 91 55 79",
    "sg:postcode":"28300",
    "sg:province":"Madrid",
    "wof:name":"Barrejon Madrigal S.l.",
    "wof:placetype":"venue"
},
  "geometry": {"coordinates":[-3.6168088913,40.0265007019],"type":"Point"}
}