{
  "type": "Feature",
  "properties": {
    "iso:country":"ES",
    "sg:address":"Calle de Puerto Serrano, 1",
    "sg:city":"Conil De La Frontera",
    "sg:orig_category":"Discapacitados",
    "sg:phone":"+34 956 44 17 10",
    "sg:postcode":"11140",
    "sg:province":"C\u00e1diz",
    "wof:name":"Ahinco",
    "wof:placetype":"venue"
},
  "geometry": {"coordinates":[-6.0830106735,36.2798461914],"type":"Point"}
}