{
  "type": "Feature",
  "properties": {
    "addr:full":"Calle de Fernan Gonzalez, 74 Madrid Madrid 28009",
    "addr:housenumber":"74",
    "addr:postcode":"madrid;28009",
    "addr:street":"Calle De Fernan Gonzalez",
    "iso:country":"ES",
    "sg:address":"Calle de Fernan Gonzalez, 74",
    "sg:city":"Madrid",
    "sg:orig_category":"Herboristas (al Por Menor)",
    "sg:phone":"+34 915 74 39 07",
    "sg:postcode":"28009",
    "sg:province":"Madrid",
    "wof:name":"Ynsadiet S.a.",
    "wof:placetype":"venue"
},
  "geometry": {"coordinates":[-3.6749389172,40.4162788391],"type":"Point"}
}