{
  "type": "Feature",
  "properties": {
    "addr:full":"Pol Ind Arza, 1 Llodio \u00c1lava 01400",
    "addr:housenumber":"1",
    "addr:postcode":"01400",
    "addr:street":"Arza",
    "iso:country":"ES",
    "sg:address":"Pol Ind Arza, 1",
    "sg:city":"Llodio",
    "sg:orig_category":"Promotores Constructores",
    "sg:phone":"+34 946 72 47 44",
    "sg:postcode":"01400",
    "sg:province":"\u00c1lava",
    "wof:name":"Construcciones Catuja Ibarra S.l.",
    "wof:placetype":"venue"
},
  "geometry": {"coordinates":[-2.9624290466,43.1436882019],"type":"Point"}
}