{
  "type": "Feature",
  "properties": {
    "iso:country":"ES",
    "sg:address":"Aben Aljatib, 25",
    "sg:city":"Cullar-vega",
    "sg:orig_category":"Inmobiliaria (agencias)",
    "sg:phone":"+34 958 58 57 10",
    "sg:postcode":"18195",
    "sg:province":"Granada",
    "wof:name":"Armicuve S.l",
    "wof:placetype":"venue"
},
  "geometry": {"coordinates":[-3.6665050983,37.1523284912],"type":"Point"}
}