{
  "type": "Feature",
  "properties": {
    "iso:country":"ES",
    "sg:address":"Carrer de Mestre Nicolau, 11",
    "sg:city":"Palmanova",
    "sg:orig_category":"Estudios, Instalaci\u00d3n De Climatizaci\u00d3n",
    "sg:phone":"+34 971 68 01 40",
    "sg:postcode":"07181",
    "sg:province":"Islas Baleares",
    "wof:name":"Valsamis  Veatriki",
    "wof:placetype":"venue"
},
  "geometry": {"coordinates":[2.538574934,39.5247383118],"type":"Point"}
}