{
  "type": "Feature",
  "properties": {
    "iso:country":"ES",
    "sg:address":"Carrer de Pedreres, 11",
    "sg:city":"Corbera Llobregat",
    "sg:orig_category":"Int\u00c9rpretes",
    "sg:phone":"+34 936 88 07 70",
    "sg:postcode":"08757",
    "sg:province":"Barcelona",
    "wof:name":"Hendrick  Mike",
    "wof:placetype":"venue"
},
  "geometry": {"coordinates":[1.9248100519,41.4131889343],"type":"Point"}
}