{
  "type": "Feature",
  "properties": {
    "addr:full":"Pg Pare Manyanet, 49 Tremp Lleida 25620",
    "addr:housenumber":"49",
    "addr:postcode":"25620",
    "addr:street":"Pg Pare Manyanet",
    "iso:country":"ES",
    "sg:address":"Pg Pare Manyanet, 49",
    "sg:city":"Tremp",
    "sg:orig_category":"Barbacoas Y Accesorios",
    "sg:phone":"+34 973 65 02 26",
    "sg:postcode":"25620",
    "sg:province":"Lleida",
    "wof:name":"Piedra Llop Joaquin",
    "wof:placetype":"venue"
},
  "geometry": {"coordinates":[0.8941130042,42.1677742004],"type":"Point"}
}