{
  "type": "Feature",
  "properties": {
    "iso:country":"ES",
    "sg:address":"G.v. Lopez De Haro D. Diego, 64",
    "sg:city":"Bilbao",
    "sg:orig_category":"Asesor\u00cda Fiscal Y Jur\u00cddica",
    "sg:phone":"+34 944 27 40 86",
    "sg:postcode":"48011",
    "sg:province":"Vizcaya",
    "wof:name":"A.b. Asesoria Fiscal S.l.",
    "wof:placetype":"venue"
},
  "geometry": {"coordinates":[-2.935019,43.263039],"type":"Point"}
}