{
  "type": "Feature",
  "properties": {
    "iso:country":"ES",
    "sg:address":"Calle de Melilla, 25",
    "sg:city":"Madrid",
    "sg:orig_category":"Arquitectos",
    "sg:phone":"+34 915 17 09 48",
    "sg:postcode":"28005",
    "sg:province":"Madrid",
    "wof:name":"Iba\u00f1ez Genis Maria Rosario",
    "wof:placetype":"venue"
},
  "geometry": {"coordinates":[-3.7094490528,40.4016418457],"type":"Point"}
}