{
  "type": "Feature",
  "properties": {
    "iso:country":"ES",
    "sg:address":"Rua Tomas Maria Mosquera, 13",
    "sg:city":"Carballi\u00f1o",
    "sg:orig_category":"Molduras, Junquillos, Listones Y Molduras Perforadas",
    "sg:phone":"+34 988 27 00 46",
    "sg:postcode":"32500",
    "sg:province":"Ourense",
    "wof:name":"Madelon Zurita Fari\u00f1a Yolanda",
    "wof:placetype":"venue"
},
  "geometry": {"coordinates":[-8.0786457062,42.4295654297],"type":"Point"}
}