{
  "type": "Feature",
  "properties": {
    "iso:country":"ES",
    "sg:address":"Calle de Marsella, 1",
    "sg:city":"Madrid",
    "sg:orig_category":"Abogados",
    "sg:phone":"+34 917 75 73 75",
    "sg:postcode":"28022",
    "sg:province":"Madrid",
    "wof:name":"Granda Moreno Nuria",
    "wof:placetype":"venue"
},
  "geometry": {"coordinates":[-3.6108179092,40.4227104187],"type":"Point"}
}