{
  "type": "Feature",
  "properties": {
    "iso:country":"ES",
    "sg:address":"Calle de Montserrat Caballe, 1",
    "sg:city":"Getafe",
    "sg:orig_category":"Librer\u00cdas",
    "sg:phone":"+34 916 83 23 67",
    "sg:postcode":"28903",
    "sg:province":"Madrid",
    "wof:name":"Libreria Siglo Xxi S.l.",
    "wof:placetype":"venue"
},
  "geometry": {"coordinates":[-3.7235519886,40.318523407],"type":"Point"}
}