{
  "type": "Feature",
  "properties": {
    "addr:full":"Pintor Joaquim Sunyer, 13 Sitges Barcelona 08870",
    "addr:housenumber":"13",
    "addr:postcode":"08870",
    "addr:street":"Pintor;Sunyer",
    "iso:country":"ES",
    "sg:address":"Pintor Joaquim Sunyer, 13",
    "sg:city":"Sitges",
    "sg:orig_category":"Agencias Y Agentes Comerciales, Representantes",
    "sg:phone":"+34 938 94 20 99",
    "sg:postcode":"08870",
    "sg:province":"Barcelona",
    "wof:name":"Lecornu  Olivier",
    "wof:placetype":"venue"
},
  "geometry": {"coordinates":[1.8002539873,41.2348861694],"type":"Point"}
}