{
  "type": "Feature",
  "properties": {
    "addr:full":"Don Quijote, S/n Las Palmas Las Palmas 35009",
    "addr:housenumber":"s / n",
    "addr:postcode":"35009",
    "iso:country":"ES",
    "sg:address":"Don Quijote, S/n",
    "sg:city":"Las Palmas",
    "sg:orig_category":"Art\u00cdculos De Limpieza Y De Cocina (fabricaci\u00d3n, Al Por Mayor)",
    "sg:phone":"+34 928 46 41 62",
    "sg:postcode":"35009",
    "sg:province":"Las Palmas",
    "wof:name":"Santiago Vega Bartolome",
    "wof:placetype":"venue"
},
  "geometry": {"coordinates":[-15.429980278,28.1644802094],"type":"Point"}
}