{
  "type": "Feature",
  "properties": {
    "iso:country":"ES",
    "sg:address":"Ctra Mendavia, Km. 0004,0",
    "sg:city":"Viana",
    "sg:orig_category":"Fabricaci\u00d3n De Su\u00c9ters Y Chalecos De Punto",
    "sg:phone":"+34 948 64 60 34",
    "sg:postcode":"31230",
    "sg:province":"Navarra",
    "wof:name":"Miniprecio Murciano S.l.",
    "wof:placetype":"venue"
},
  "geometry": {"coordinates":[-2.3724679947,42.5140380859],"type":"Point"}
}