{
  "type": "Feature",
  "properties": {
    "addr:full":"Rua Real, 22 Muros A Coru\u00f1a 15250",
    "addr:housenumber":"22",
    "addr:postcode":"15250",
    "addr:street":"Rua Real;A Corun\u0303A",
    "iso:country":"ES",
    "sg:address":"Rua Real, 22",
    "sg:city":"Muros",
    "sg:orig_category":"Ingeniero",
    "sg:phone":"+34 981 82 60 42",
    "sg:postcode":"15250",
    "sg:province":"A Coru\u00f1a",
    "wof:name":"Vazquez Sanchez Antonio",
    "wof:placetype":"venue"
},
  "geometry": {"coordinates":[-9.0588932037,42.7754478455],"type":"Point"}
}