{
  "type": "Feature",
  "properties": {
    "iso:country":"ES",
    "sg:address":"Calle de Castello, 108",
    "sg:city":"Madrid",
    "sg:orig_category":"Aparcamientos (infraestructuras, Accesorios)",
    "sg:phone":"+34 915 62 08 10",
    "sg:postcode":"28006",
    "sg:province":"Madrid",
    "wof:name":"Gonzalez Chimeno Jose",
    "wof:placetype":"venue"
},
  "geometry": {"coordinates":[-3.6806733608,40.43542099],"type":"Point"}
}