{
  "type": "Feature",
  "properties": {
    "iso:country":"ES",
    "sg:address":"Plaz Angustias (las), 6",
    "sg:city":"Jerez De La Frontera",
    "sg:orig_category":"Florister\u00cdas",
    "sg:phone":"+34 956 32 00 05",
    "sg:postcode":"11402",
    "sg:province":"C\u00e1diz",
    "wof:name":"Lopez Garcia Mateo",
    "wof:placetype":"venue"
},
  "geometry": {"coordinates":[-6.1348838806,36.6909637451],"type":"Point"}
}