{
  "type": "Feature",
  "properties": {
    "addr:full":"C/ Ventarich, 11 Elche Alicante 03201",
    "addr:housenumber":"11",
    "addr:postcode":"03201",
    "addr:street":"C / Ventarich",
    "iso:country":"ES",
    "sg:address":"C/ Ventarich, 11",
    "sg:city":"Elche",
    "sg:orig_category":"Mec\u00c1nico Del Autom\u00d3vil",
    "sg:phone":"+34 965 46 35 56",
    "sg:postcode":"03201",
    "sg:province":"Alicante",
    "wof:name":"Chacon Salas Francisco",
    "wof:placetype":"venue"
},
  "geometry": {"coordinates":[-0.7028220296,38.2604866028],"type":"Point"}
}