{
  "type": "Feature",
  "properties": {
    "iso:country":"ES",
    "sg:address":"Carr Marques De Caldes De Montbui, 28",
    "sg:city":"Girona",
    "sg:orig_category":"Institutos De Belleza",
    "sg:phone":"+34 972 20 83 02",
    "sg:postcode":"17003",
    "sg:province":"Girona",
    "sg:website":"www.galdana.net",
    "wof:name":"De Eusebio Ventola Marta",
    "wof:placetype":"venue"
},
  "geometry": {"coordinates":[2.8157680035,41.9696311951],"type":"Point"}
}