{
  "type": "Feature",
  "properties": {
    "iso:country":"ES",
    "sg:address":"Kale Nagusia-calle Mayor, 4",
    "sg:city":"Lasarte",
    "sg:orig_category":"Centros Empresariales",
    "sg:phone":"+34 943 37 33 79",
    "sg:postcode":"20160",
    "sg:province":"Guip\u00f9zcoa",
    "wof:name":"Arquitempo Servicios S.l.",
    "wof:placetype":"venue"
},
  "geometry": {"coordinates":[-2.020414114,43.2698173523],"type":"Point"}
}