{
  "type": "Feature",
  "properties": {
    "iso:country":"ES",
    "sg:address":"Calle de Huertos, 46",
    "sg:city":"Castuera",
    "sg:orig_category":"Poller\u00cda Y Caza (al Por Menor)",
    "sg:phone":"+34 924 76 08 95",
    "sg:postcode":"06420",
    "sg:province":"Badajoz",
    "wof:name":"Gragera Trevi\u00f1o C.b.",
    "wof:placetype":"venue"
},
  "geometry": {"coordinates":[-5.5463089943,38.7176818848],"type":"Point"}
}