{
  "type": "Feature",
  "properties": {
    "addr:full":"Calle de Cuesta De Picasso, 4 Casta\u00e7ar De Ibor C\u00e1ceres 10340",
    "addr:housenumber":"4",
    "addr:postcode":"10340",
    "addr:street":"Calle De Cuesta De Picasso;Ca\u0301Ceres",
    "iso:country":"ES",
    "sg:address":"Calle de Cuesta De Picasso, 4",
    "sg:city":"Casta\u00e7ar De Ibor",
    "sg:orig_category":"Cajas De Ahorro",
    "sg:phone":"+34 927 55 40 59",
    "sg:postcode":"10340",
    "sg:province":"C\u00e1ceres",
    "wof:name":"Caja De Ahorros Y Monte De Piedad De Extremadura",
    "wof:placetype":"venue"
},
  "geometry": {"coordinates":[-5.4156088829,39.627620697],"type":"Point"}
}