{
  "type": "Feature",
  "properties": {
    "iso:country":"ES",
    "sg:address":"Calle de Operarias Parroquiales, 14",
    "sg:city":"S. Adrian",
    "sg:orig_category":"Internados & Ense\u00d1anza Privada",
    "sg:phone":"+34 948 67 28 28",
    "sg:postcode":"31570",
    "sg:province":"Navarra",
    "wof:name":"Asociacion Arreso",
    "wof:placetype":"venue"
},
  "geometry": {"coordinates":[-1.9351241589,42.3365783691],"type":"Point"}
}