{
  "type": "Feature",
  "properties": {
    "addr:full":"Aldeasouto, 11 Aldea Souto Ourense 32229",
    "addr:housenumber":"11",
    "addr:postcode":"32229",
    "addr:street":"Aldeasouto",
    "iso:country":"ES",
    "sg:address":"Aldeasouto, 11",
    "sg:city":"Aldea Souto",
    "sg:orig_category":"Ense\u00d1anza, Formaci\u00d3n Profesional: Aprendizaje",
    "sg:phone":"+34 988 49 44 45",
    "sg:postcode":"32229",
    "sg:province":"Ourense",
    "wof:name":"Ayuntamiento De Padrenda",
    "wof:placetype":"venue"
},
  "geometry": {"coordinates":[-7.6929821968,42.3755989075],"type":"Point"}
}