{
  "type": "Feature",
  "properties": {
    "addr:full":"Carr Lluna, 50 Pobla Islas Baleares 07420",
    "addr:housenumber":"50",
    "addr:postcode":"07420",
    "addr:street":"Carr Lluna;Baleares",
    "iso:country":"ES",
    "sg:address":"Carr Lluna, 50",
    "sg:city":"Pobla",
    "sg:orig_category":"Ropa Para Se\u00d1oras Y Caballeros (al Por Menor)",
    "sg:phone":"+34 971 54 04 05",
    "sg:postcode":"07420",
    "sg:province":"Islas Baleares",
    "wof:name":"Soler Pons Maria",
    "wof:placetype":"venue"
},
  "geometry": {"coordinates":[3.025769949,39.7738304138],"type":"Point"}
}