{
  "type": "Feature",
  "properties": {
    "addr:full":"Carrer de Miquel Marques, 28 Palma Islas Baleares 07005",
    "addr:housenumber":"28",
    "addr:postcode":"07005",
    "addr:street":"Carrer De Miquel Marques",
    "iso:country":"ES",
    "sg:address":"Carrer de Miquel Marques, 28",
    "sg:city":"Palma",
    "sg:orig_category":"Peluquer\u00cdas, Peluquer\u00cda Mixta",
    "sg:phone":"+34 971 77 15 16",
    "sg:postcode":"07005",
    "sg:province":"Islas Baleares",
    "wof:name":"Torrens Gelabert Maria",
    "wof:placetype":"venue"
},
  "geometry": {"coordinates":[2.6569600105,39.5769882202],"type":"Point"}
}