{
  "type": "Feature",
  "properties": {
    "iso:country":"ES",
    "sg:address":"Gta Bilbao, 7",
    "sg:city":"Madrid",
    "sg:orig_category":"\u00d3ptica: Instrumentos (fabricaci\u00d3n)",
    "sg:phone":"+34 915 22 17 48",
    "sg:postcode":"28004",
    "sg:province":"Madrid",
    "wof:name":"Internacional Optica Rivoli S. A.",
    "wof:placetype":"venue"
},
  "geometry": {"coordinates":[-3.7020039558,40.4286384583],"type":"Point"}
}