{
  "type": "Feature",
  "properties": {
    "addr:full":"Calle de Mayor, 46 Beniajan Murcia 30570",
    "addr:housenumber":"46",
    "addr:postcode":"30570",
    "addr:street":"Calle De Mayor",
    "iso:country":"ES",
    "sg:address":"Calle de Mayor, 46",
    "sg:city":"Beniajan",
    "sg:orig_category":"Bazares, Art\u00cdculos De Limpieza Y De Cocina (al Por Menor)",
    "sg:phone":"+34 968 87 57 63",
    "sg:postcode":"30570",
    "sg:province":"Murcia",
    "wof:name":"Jaime Martinez Irene",
    "wof:placetype":"venue"
},
  "geometry": {"coordinates":[-1.0733770132,37.9753417969],"type":"Point"}
}