{
  "type": "Feature",
  "properties": {
    "iso:country":"ES",
    "sg:address":"Pla\u00c7 Coma (de La), 18",
    "sg:city":"Cassa Selva",
    "sg:orig_category":"Agentes De Seguros",
    "sg:phone":"+34 972 46 07 26",
    "sg:postcode":"17244",
    "sg:province":"Girona",
    "wof:name":"A.s. Cassa Roqueta S.l.",
    "wof:placetype":"venue"
},
  "geometry": {"coordinates":[2.8236999512,41.9817962646],"type":"Point"}
}