{
  "type": "Feature",
  "properties": {
    "addr:full":"Aviacion (p I Calonge), Km. 0537,0 Sevilla Sevilla 41007",
    "addr:postcode":"41007",
    "addr:street":"Calonge Km. 0537,0",
    "iso:country":"ES",
    "sg:address":"Aviacion (p I Calonge), Km. 0537,0",
    "sg:city":"Sevilla",
    "sg:orig_category":"Agentes, Concesionarios Y Sucursales De Veh\u00cdculos",
    "sg:phone":"+34 954 35 04 50",
    "sg:postcode":"41007",
    "sg:province":"Sevilla",
    "wof:name":"Hispanomocion S.a.",
    "wof:placetype":"venue"
},
  "geometry": {"coordinates":[-5.9537520409,37.4072494507],"type":"Point"}
}