{
  "type": "Feature",
  "properties": {
    "addr:full":"Carrer de Torrent Del Remei, 2 Barcelona Barcelona 08023",
    "addr:housenumber":"2",
    "addr:postcode":"08023",
    "addr:street":"Carrer De Torrent Del Remei",
    "iso:country":"ES",
    "sg:address":"Carrer de Torrent Del Remei, 2",
    "sg:city":"Barcelona",
    "sg:orig_category":"Centros De Educaci\u00d3n Especial",
    "sg:phone":"+34 932 13 98 45",
    "sg:postcode":"08023",
    "sg:province":"Barcelona",
    "wof:name":"Ajuntament De Barcelona",
    "wof:placetype":"venue"
},
  "geometry": {"coordinates":[2.1481509209,41.4155540466],"type":"Point"}
}