{
  "type": "Feature",
  "properties": {
    "iso:country":"ES",
    "sg:address":"Avda Santa Icia, 7",
    "sg:city":"Roibo",
    "sg:orig_category":"Fabricaci\u00d3n, Venta De Cuadros, Accesorios Para Enmarcar",
    "sg:phone":"+34 981 38 33 03",
    "sg:postcode":"15407",
    "sg:province":"La Coru\u00f1a",
    "wof:name":"Mui\u00f1o Couce Marcial",
    "wof:placetype":"venue"
},
  "geometry": {"coordinates":[-8.1969175339,43.5052642822],"type":"Point"}
}