{
  "type": "Feature",
  "properties": {
    "addr:full":"Ctra Sueca, Km. 0003,1 Alzira Valencia 46600",
    "addr:postcode":"46600",
    "addr:street":"Ctra Sueca Km. 0003,1;Valencia",
    "iso:country":"ES",
    "sg:address":"Ctra Sueca, Km. 0003,1",
    "sg:city":"Alzira",
    "sg:orig_category":"Explotaci\u00d3n De Canteras",
    "sg:phone":"+34 962 40 37 81",
    "sg:postcode":"46600",
    "sg:province":"Valencia",
    "wof:name":"Cementval Hormigones S.l.u.",
    "wof:placetype":"venue"
},
  "geometry": {"coordinates":[-0.4378489852,39.1517295837],"type":"Point"}
}