{
  "type": "Feature",
  "properties": {
    "addr:full":"Carrer de Pi I Margall, 28 Barcelona Barcelona 08025",
    "addr:housenumber":"28",
    "addr:postcode":"08025",
    "addr:street":"Carrer De Pi I Margall",
    "iso:country":"ES",
    "sg:address":"Carrer de Pi I Margall, 28",
    "sg:city":"Barcelona",
    "sg:orig_category":"Muebles, Minoristas",
    "sg:phone":"+34 932 19 85 20",
    "sg:postcode":"08025",
    "sg:province":"Barcelona",
    "wof:name":"Sirius Mobiliari S. L.",
    "wof:placetype":"venue"
},
  "geometry": {"coordinates":[2.1635138988,41.4069099426],"type":"Point"}
}