{
  "type": "Feature",
  "properties": {
    "iso:country":"ES",
    "sg:address":"Ctra Tries, Les, 73",
    "sg:city":"Olot",
    "sg:orig_category":"Colorantes, Colores Y Pigmentos (fabricaci\u00d3n, Al Por Mayor)",
    "sg:phone":"+34 972 26 91 02",
    "sg:postcode":"17800",
    "sg:province":"Girona",
    "wof:name":"Blanqueo Y Tintes J.pares Uge S.a.",
    "wof:placetype":"venue"
},
  "geometry": {"coordinates":[2.5038928986,42.1899108887],"type":"Point"}
}