{
  "type": "Feature",
  "properties": {
    "iso:country":"ES",
    "sg:address":"Calle de Virgen De Los Milagros, 84",
    "sg:city":"Puerto De Santa Maria",
    "sg:orig_category":"Confecci\u00d3n (fabricaci\u00d3n, Al Por Mayor)",
    "sg:phone":"+34 956 54 21 11",
    "sg:postcode":"11500",
    "sg:province":"C\u00e1diz",
    "wof:name":"Rianal S.a.",
    "wof:placetype":"venue"
},
  "geometry": {"coordinates":[-6.2251749039,36.5996131897],"type":"Point"}
}