{
  "type": "Feature",
  "properties": {
    "addr:full":"Carrer de Guinea (la), 12 Terrassa Barcelona 08228",
    "addr:housenumber":"12",
    "addr:postcode":"08228",
    "addr:street":"Carrer De Guinea La",
    "iso:country":"ES",
    "sg:address":"Carrer de Guinea (la), 12",
    "sg:city":"Terrassa",
    "sg:orig_category":"Empresas De Desmonte",
    "sg:phone":"+34 937 84 26 65",
    "sg:postcode":"08228",
    "sg:province":"Barcelona",
    "wof:name":"Excavaciones Antonio Domenech S.l.",
    "wof:placetype":"venue"
},
  "geometry": {"coordinates":[2.0465900898,41.5322647095],"type":"Point"}
}