{
  "type": "Feature",
  "properties": {
    "addr:full":"Ctra Tres Mil Trescientos Veintidos, S/n Chiva Valencia 46370",
    "addr:housenumber":"s / n",
    "addr:postcode":"46370",
    "addr:street":"Ctra Tres;Veintidos",
    "iso:country":"ES",
    "sg:address":"Ctra Tres Mil Trescientos Veintidos, S/n",
    "sg:city":"Chiva",
    "sg:orig_category":"Agentes, Concesionarios Y Sucursales De Veh\u00cdculos",
    "sg:phone":"+34 962 52 05 36",
    "sg:postcode":"46370",
    "sg:province":"Valencia",
    "wof:name":"Chivauto S.l.",
    "wof:placetype":"venue"
},
  "geometry": {"coordinates":[-0.7179690003,39.4728012085],"type":"Point"}
}