{
  "type": "Feature",
  "properties": {
    "addr:full":"Carrer de Consell De Cent, 463 Barcelona Barcelona 08013",
    "addr:housenumber":"463",
    "addr:postcode":"08013",
    "addr:street":"Carrer De Consell De Cent",
    "iso:country":"ES",
    "sg:address":"Carrer de Consell De Cent, 463",
    "sg:city":"Barcelona",
    "sg:orig_category":"Carnicer\u00cdas, Carnicer\u00cdas",
    "sg:phone":"+34 932 32 92 75",
    "sg:postcode":"08013",
    "sg:province":"Barcelona",
    "wof:name":"Costa Bru S.c.c.l",
    "wof:placetype":"venue"
},
  "geometry": {"coordinates":[2.17572999,41.3988037109],"type":"Point"}
}