{
  "type": "Feature",
  "properties": {
    "iso:country":"ES",
    "sg:address":"Ctr. Valencia, Km. 0002,0",
    "sg:city":"Cuenca",
    "sg:orig_category":"Distribuci\u00d3n De Petr\u00d3leo Y Derivados",
    "sg:phone":"+34 969 21 00 00",
    "sg:postcode":"16004",
    "sg:province":"Cuenca",
    "wof:name":"Logioil S.a.",
    "wof:placetype":"venue"
},
  "geometry": {"coordinates":[-2.1237630844,40.0522689819],"type":"Point"}
}