{
  "type": "Feature",
  "properties": {
    "iso:country":"ES",
    "sg:address":"Calle de Brunete, 2",
    "sg:city":"Cadiz",
    "sg:orig_category":"Promotores Constructores",
    "sg:phone":"+34 956 27 04 50",
    "sg:postcode":"11007",
    "sg:province":"C\u00e1diz",
    "wof:name":"Alcaraz Romero Hogar S.l.",
    "wof:placetype":"venue"
},
  "geometry": {"coordinates":[-6.2838439941,36.5216369629],"type":"Point"}
}