{
  "type": "Feature",
  "properties": {
    "addr:full":"Calle de San Buenaventura, 1 Madrid Madrid 28005",
    "addr:housenumber":"1",
    "addr:postcode":"28005",
    "addr:street":"Calle De San Buenaventura",
    "iso:country":"ES",
    "sg:address":"Calle de San Buenaventura, 1",
    "sg:city":"Madrid",
    "sg:orig_category":"Hospitales",
    "sg:phone":"+34 913 65 76 57",
    "sg:postcode":"28005",
    "sg:province":"Madrid",
    "wof:name":"Hospital De La Venerable Orden Tercera",
    "wof:placetype":"venue"
},
  "geometry": {"coordinates":[-3.7149209976,40.4112854004],"type":"Point"}
}