{
  "type": "Feature",
  "properties": {
    "addr:full":"Maquianes, 35 Ribadavia Ourense 32400",
    "addr:housenumber":"35",
    "addr:postcode":"32400",
    "addr:street":"Maquianes",
    "iso:country":"ES",
    "sg:address":"Maquianes, 35",
    "sg:city":"Ribadavia",
    "sg:orig_category":"Agencias Y Agentes Comerciales, Representantes",
    "sg:phone":"+34 988 47 00 55",
    "sg:postcode":"32400",
    "sg:province":"Ourense",
    "wof:name":"Moreira Martinez Virginia",
    "wof:placetype":"venue"
},
  "geometry": {"coordinates":[-8.1431999207,42.2956809998],"type":"Point"}
}