{
  "type": "Feature",
  "properties": {
    "iso:country":"ES",
    "sg:address":"Calle de Flaubert, 1",
    "sg:city":"Malaga",
    "sg:orig_category":"Ense\u00d1ante, Direcci\u00d3n",
    "sg:phone":"+34 952 61 69 85",
    "sg:postcode":"29010",
    "sg:province":"M\u00e1laga",
    "wof:name":"Carrasco Cassini Fernando",
    "wof:placetype":"venue"
},
  "geometry": {"coordinates":[-4.4612560272,36.7239112854],"type":"Point"}
}