{
  "type": "Feature",
  "properties": {
    "iso:country":"ES",
    "sg:address":"Calle de Vicente Cantos Figuerola, 21",
    "sg:city":"Burriana",
    "sg:orig_category":"Fabricaci\u00d3n De Jabones, Detergentes Y Lej\u00cdas",
    "sg:phone":"+34 964 51 06 96",
    "sg:postcode":"12530",
    "sg:province":"Castell\u00f3n",
    "wof:name":"Covectronic Int S.l.",
    "wof:placetype":"venue"
},
  "geometry": {"coordinates":[-0.088349998,39.8901634216],"type":"Point"}
}