{
  "type": "Feature",
  "properties": {
    "addr:full":"Calle de Canal, 2 Aguadulce Almer\u00eda 04720",
    "addr:housenumber":"2",
    "addr:postcode":"04720",
    "addr:street":"Calle De Canal;Almeri\u0301A",
    "iso:country":"ES",
    "sg:address":"Calle de Canal, 2",
    "sg:city":"Aguadulce",
    "sg:orig_category":"Electricidad: Instaladores",
    "sg:phone":"+34 950 34 97 00",
    "sg:postcode":"04720",
    "sg:province":"Almer\u00eda",
    "wof:name":"Instalaciones Friluz S.l",
    "wof:placetype":"venue"
},
  "geometry": {"coordinates":[-2.5817272663,36.8105659485],"type":"Point"}
}