{
  "type": "Feature",
  "properties": {
    "iso:country":"ES",
    "sg:address":"Av Pere El Cerimonios, 83",
    "sg:city":"Reus",
    "sg:orig_category":"Fabricaci\u00d3n De Ropa De Deportes",
    "sg:phone":"+34 977 75 75 68",
    "sg:postcode":"43205",
    "sg:province":"Tarragona",
    "wof:name":"Conreus S.coop.c.ltda",
    "wof:placetype":"venue"
},
  "geometry": {"coordinates":[1.1064089537,41.1467933655],"type":"Point"}
}