{
  "type": "Feature",
  "properties": {
    "iso:country":"ES",
    "sg:address":"Av Catalunya, 349",
    "sg:city":"Aldea",
    "sg:orig_category":"Carnicer\u00cdas, Carnicer\u00cdas",
    "sg:phone":"+34 977 45 04 45",
    "sg:postcode":"43896",
    "sg:province":"Tarragona",
    "wof:name":"Estorach Paez Clara",
    "wof:placetype":"venue"
},
  "geometry": {"coordinates":[0.6261289716,40.7497138977],"type":"Point"}
}