{
  "type": "Feature",
  "properties": {
    "iso:country":"ES",
    "sg:address":"Calle de Kolitza Kalea, 1",
    "sg:city":"Zamudio",
    "sg:orig_category":"Lateros",
    "sg:phone":"+34 944 52 04 67",
    "sg:postcode":"48170",
    "sg:province":"Vizcaya",
    "wof:name":"Ur Konpon Iturgi\u00f1ak, S.l.",
    "wof:placetype":"venue"
},
  "geometry": {"coordinates":[-2.8656949997,43.2839279175],"type":"Point"}
}