{
  "type": "Feature",
  "properties": {
    "addr:full":"Calle de Encomienda, 18 Madrid Madrid 28012",
    "addr:housenumber":"18",
    "addr:postcode":"madrid;28012",
    "addr:street":"Calle De Encomienda",
    "iso:country":"ES",
    "sg:address":"Calle de Encomienda, 18",
    "sg:city":"Madrid",
    "sg:orig_category":"Alimentaci\u00d3n General (al Por Menor)",
    "sg:phone":"+34 915 28 65 12",
    "sg:postcode":"28012",
    "sg:province":"Madrid",
    "wof:name":"Wanshi Shunda",
    "wof:placetype":"venue"
},
  "geometry": {"coordinates":[-3.706120491,40.4106216431],"type":"Point"}
}