{
  "type": "Feature",
  "properties": {
    "iso:country":"ES",
    "sg:address":"Calle de Purisima, 27",
    "sg:city":"Fortuna",
    "sg:orig_category":"Bisuter\u00cda, Joyer\u00cda, Relojer\u00cda (al Por Menor)",
    "sg:phone":"+34 968 68 62 36",
    "sg:postcode":"30620",
    "sg:province":"Murcia",
    "wof:name":"Gonbel Joyeros S.l.",
    "wof:placetype":"venue"
},
  "geometry": {"coordinates":[-1.123388052,38.1810302734],"type":"Point"}
}