{
  "type": "Feature",
  "properties": {
    "iso:country":"ES",
    "sg:address":"Calle de Carteros, 9",
    "sg:city":"Valencia",
    "sg:orig_category":"Molduras, Junquillos, Listones Y Molduras Perforadas",
    "sg:phone":"+34 963 77 30 80",
    "sg:postcode":"46017",
    "sg:province":"Valencia",
    "wof:name":"Mora Mora Amable",
    "wof:placetype":"venue"
},
  "geometry": {"coordinates":[-0.3888998926,39.4514389038],"type":"Point"}
}