{
  "type": "Feature",
  "properties": {
    "addr:full":"Calle de Ramon Y Cajal, 21 Tamarite Litera Huesca 22550",
    "addr:housenumber":"21",
    "addr:postcode":"22550",
    "addr:street":"Calle De Ramon Y Cajal",
    "iso:country":"ES",
    "sg:address":"Calle de Ramon Y Cajal, 21",
    "sg:city":"Tamarite Litera",
    "sg:orig_category":"Mec\u00c1nico Del Autom\u00d3vil",
    "sg:phone":"+34 974 42 01 81",
    "sg:postcode":"22550",
    "sg:province":"Huesca",
    "wof:name":"Cartocars Automocion S.l.",
    "wof:placetype":"venue"
},
  "geometry": {"coordinates":[0.4172790051,41.8648071289],"type":"Point"}
}