{
  "type": "Feature",
  "properties": {
    "iso:country":"ES",
    "sg:address":"Calle de Trinidad, 20",
    "sg:city":"Toledo",
    "sg:orig_category":"Sociedades, Compa\u00d1\u00cdas Aseguradoras",
    "sg:phone":"+34 925 22 64 70",
    "sg:postcode":"45002",
    "sg:province":"Toledo",
    "wof:name":"Ocaso S.a. Compa\u00f1ia De Seguros Y Reaseguros",
    "wof:placetype":"venue"
},
  "geometry": {"coordinates":[-4.0263209343,39.8571014404],"type":"Point"}
}