{
  "type": "Feature",
  "properties": {
    "addr:full":"Avda Pintor Felo Monzon, S/n Palmas De Gran Canaria Las Palmas 35019",
    "addr:housenumber":"s",
    "addr:postcode":"35019",
    "addr:street":"Avda Pintor Felo Monzon;/ N",
    "iso:country":"ES",
    "sg:address":"Avda Pintor Felo Monzon, S/n",
    "sg:city":"Palmas De Gran Canaria",
    "sg:orig_category":"Medias Y Calcetines (al Por Menor)",
    "sg:phone":"+34 928 42 20 89",
    "sg:postcode":"35019",
    "sg:province":"Las Palmas",
    "sg:website":"www.calzedonia.com",
    "wof:name":"Alena Isa Jose Maria Sl",
    "wof:placetype":"venue"
},
  "geometry": {"coordinates":[-15.4540748596,28.0999279022],"type":"Point"}
}