{
  "type": "Feature",
  "properties": {
    "addr:full":"Avda Diputacion, 81 Lepe Huelva 21440",
    "addr:housenumber":"81",
    "addr:postcode":"21440",
    "addr:street":"Avda Diputacion",
    "iso:country":"ES",
    "sg:address":"Avda Diputacion, 81",
    "sg:city":"Lepe",
    "sg:orig_category":"Restaurantes",
    "sg:phone":"+34 959 38 34 11",
    "sg:postcode":"21440",
    "sg:province":"Huelva",
    "wof:name":"Cui  Minglu",
    "wof:placetype":"venue"
},
  "geometry": {"coordinates":[-7.2023940086,37.2496376038],"type":"Point"}
}