{
  "type": "Feature",
  "properties": {
    "iso:country":"ES",
    "sg:address":"Calle de Panaderos, 39",
    "sg:city":"Valladolid",
    "sg:orig_category":"Pescader\u00cdas (al Por Menor)",
    "sg:phone":"+34 983 20 00 91",
    "sg:postcode":"47004",
    "sg:province":"Valladolid",
    "wof:name":"Pescaderia Eugenia S.l.",
    "wof:placetype":"venue"
},
  "geometry": {"coordinates":[-4.722659111,41.6464729309],"type":"Point"}
}