{
  "type": "Feature",
  "properties": {
    "addr:full":"Calle de San Julian, 1 Burgos Burgos 09002",
    "addr:housenumber":"1",
    "addr:postcode":"09002",
    "addr:street":"Calle De San Julian",
    "iso:country":"ES",
    "sg:address":"Calle de San Julian, 1",
    "sg:city":"Burgos",
    "sg:orig_category":"Asociaciones Humanitarias, De Cooperaci\u00d3n, De Acci\u00d3n Social",
    "sg:phone":"+34 947 20 71 42",
    "sg:postcode":"09002",
    "sg:province":"Burgos",
    "wof:name":"Organizacion Impulsora De Discapacitados O.i.d.",
    "wof:placetype":"venue"
},
  "geometry": {"coordinates":[-3.6991169453,42.336807251],"type":"Point"}
}