{
  "type": "Feature",
  "properties": {
    "iso:country":"ES",
    "sg:address":"Calle de Condado De Trevi\u00d1o, 81",
    "sg:city":"Miranda Ebro",
    "sg:orig_category":"Peluquer\u00cdas, Peluquer\u00cda Mixta",
    "sg:phone":"+34 947 32 38 22",
    "sg:postcode":"09200",
    "sg:province":"Burgos",
    "wof:name":"Juez Garrido Isabel",
    "wof:placetype":"venue"
},
  "geometry": {"coordinates":[-2.9430911541,42.6850852966],"type":"Point"}
}