{
  "type": "Feature",
  "properties": {
    "iso:country":"ES",
    "sg:address":"Carr Sant Jaume, 120",
    "sg:city":"Almacelles",
    "sg:orig_category":"Electricidad: Instaladores",
    "sg:phone":"+34 973 74 17 21",
    "sg:postcode":"25100",
    "sg:province":"Lleida",
    "wof:name":"Justribo Arfelis Jaime",
    "wof:placetype":"venue"
},
  "geometry": {"coordinates":[0.4411489964,41.727519989],"type":"Point"}
}