{
  "type": "Feature",
  "properties": {
    "addr:full":"Av Germans Marti, 25 Martorell Barcelona 08760",
    "addr:housenumber":"25",
    "addr:postcode":"08760",
    "addr:street":"Av Germans Marti",
    "iso:country":"ES",
    "sg:address":"Av Germans Marti, 25",
    "sg:city":"Martorell",
    "sg:orig_category":"Farmacias",
    "sg:phone":"+34 937 74 15 19",
    "sg:postcode":"08760",
    "sg:province":"Barcelona",
    "wof:name":"Miralles Via Montserrat",
    "wof:placetype":"venue"
},
  "geometry": {"coordinates":[1.9180450439,41.4771118164],"type":"Point"}
}