{
  "type": "Feature",
  "properties": {
    "addr:full":"Calle de Pajares, 17 Santurtzi Vizcaya 48980",
    "addr:housenumber":"17",
    "addr:postcode":"48980",
    "addr:street":"Calle De Pajares",
    "iso:country":"ES",
    "sg:address":"Calle de Pajares, 17",
    "sg:city":"Santurtzi",
    "sg:orig_category":"Delegados, Agentes De Tr\u00c1nsito, Auxiliares De Transporte Internacional",
    "sg:phone":"+34 944 62 35 20",
    "sg:postcode":"48980",
    "sg:province":"Vizcaya",
    "wof:name":"Echaniz Gutierrez Josu",
    "wof:placetype":"venue"
},
  "geometry": {"coordinates":[-3.0391619205,43.3237342834],"type":"Point"}
}