{
  "type": "Feature",
  "properties": {
    "iso:country":"ES",
    "sg:address":"Avda Juan Pablo Ii, S/n",
    "sg:city":"Alba Tormes",
    "sg:orig_category":"Caf\u00c9s, Bares, Cervecer\u00cdas",
    "sg:phone":"+34 923 30 10 30",
    "sg:postcode":"37800",
    "sg:province":"Salamanca",
    "wof:name":"Cosme Duran Isabel",
    "wof:placetype":"venue"
},
  "geometry": {"coordinates":[-5.5159339905,40.8246231079],"type":"Point"}
}