{
  "type": "Feature",
  "properties": {
    "iso:country":"ES",
    "sg:address":"Calle de Arango, 13",
    "sg:city":"Malaga",
    "sg:orig_category":"Asociaciones Humanitarias, De Cooperaci\u00d3n, De Acci\u00d3n Social",
    "sg:phone":"+34 952 61 87 78",
    "sg:postcode":"29007",
    "sg:province":"M\u00e1laga",
    "wof:name":"Asociacion De Pacientes Anticoagulados De Malaga",
    "wof:placetype":"venue"
},
  "geometry": {"coordinates":[-4.4341096878,36.7208213806],"type":"Point"}
}