{
  "type": "Feature",
  "properties": {
    "iso:country":"ES",
    "sg:address":"Avda Paz De (la), 80",
    "sg:city":"Logro\u00f1o",
    "sg:orig_category":"Molduras, Junquillos, Listones Y Molduras Perforadas",
    "sg:phone":"+34 941 23 03 77",
    "sg:postcode":"26004",
    "sg:province":"La Rioja",
    "wof:name":"Garrido Bellido Santiago Isidro",
    "wof:placetype":"venue"
},
  "geometry": {"coordinates":[-2.4331820011,42.4638786316],"type":"Point"}
}