{
  "type": "Feature",
  "properties": {
    "iso:country":"ES",
    "sg:address":"Calle de Sagrada Familia, 5",
    "sg:city":"Donostia-san Sebastian",
    "sg:orig_category":"Peritos Diversos",
    "sg:phone":"+34 943 45 74 12",
    "sg:postcode":"20010",
    "sg:province":"Guip\u00f9zcoa",
    "wof:name":"Asociacion De Pericia Caligrafica De La C.a.v. Shermi",
    "wof:placetype":"venue"
},
  "geometry": {"coordinates":[-1.9805810452,43.308380127],"type":"Point"}
}