{
  "type": "Feature",
  "properties": {
    "iso:country":"ES",
    "sg:address":"Generalisimo Franco, 18",
    "sg:city":"Padron",
    "sg:orig_category":"Bisuter\u00cda, Joyer\u00cda, Relojer\u00cda (al Por Menor)",
    "sg:phone":"+34 981 81 13 57",
    "sg:postcode":"15900",
    "sg:province":"La Coru\u00f1a",
    "wof:name":"Bragado Calleja Luis",
    "wof:placetype":"venue"
},
  "geometry": {"coordinates":[-8.660492897,42.7385063171],"type":"Point"}
}