{
  "type": "Feature",
  "properties": {
    "addr:full":"Luga Mesa De Los Angeles, S/n Angeles C\u00e1diz 11330",
    "addr:housenumber":"s / n",
    "addr:postcode":"11330",
    "iso:country":"ES",
    "sg:address":"Luga Mesa De Los Angeles, S/n",
    "sg:city":"Angeles",
    "sg:orig_category":"Contenedores (mercanc\u00cdas)",
    "sg:phone":"+34 956 64 04 61",
    "sg:postcode":"11330",
    "sg:province":"C\u00e1diz",
    "wof:name":"Rodriguez Rodriguez Francisco Javier",
    "wof:placetype":"venue"
},
  "geometry": {"coordinates":[-5.4481987953,36.4326057434],"type":"Point"}
}