{
  "type": "Feature",
  "properties": {
    "iso:country":"ES",
    "sg:address":"Carrer de Font, 9",
    "sg:city":"Gunyoles",
    "sg:orig_category":"Fabrica De Cer\u00c1micas",
    "sg:phone":"+34 977 63 75 00",
    "sg:postcode":"43154",
    "sg:province":"Tarragona",
    "wof:name":"Casas Roig Maria Dolors",
    "wof:placetype":"venue"
},
  "geometry": {"coordinates":[1.2659300566,41.2104301453],"type":"Point"}
}