{
  "type": "Feature",
  "properties": {
    "addr:full":"Calle de Gerona, 2 Fuenlabrada Madrid 28945",
    "addr:housenumber":"2",
    "addr:postcode":"28945",
    "addr:street":"Calle De Gerona",
    "iso:country":"ES",
    "sg:address":"Calle de Gerona, 2",
    "sg:city":"Fuenlabrada",
    "sg:orig_category":"Empresas De Pintura Y Revestimientos",
    "sg:phone":"+34 916 09 70 68",
    "sg:postcode":"28945",
    "sg:province":"Madrid",
    "wof:name":"Ramirez Espinosa Pascual",
    "wof:placetype":"venue"
},
  "geometry": {"coordinates":[-3.7914059162,40.294090271],"type":"Point"}
}