{
  "type": "Feature",
  "properties": {
    "iso:country":"ES",
    "sg:address":"Carrer de Major, 76",
    "sg:city":"S. Joan Despi",
    "sg:orig_category":"Venta, Instalaci\u00d3n, Reparaci\u00d3n De Antenas Para Televisi\u00d3n",
    "sg:phone":"+34 933 73 88 72",
    "sg:postcode":"08970",
    "sg:province":"Barcelona",
    "wof:name":"Stam Telecomunicacions S.l.",
    "wof:placetype":"venue"
},
  "geometry": {"coordinates":[2.0547280312,41.367225647],"type":"Point"}
}