{
  "type": "Feature",
  "properties": {
    "iso:country":"ES",
    "sg:address":"Tajonar, 6",
    "sg:city":"Iru\u00f1a",
    "sg:orig_category":"Inmobiliaria (agencias)",
    "sg:phone":"+34 948 23 23 76",
    "sg:postcode":"31006",
    "sg:province":"Navarra",
    "wof:name":"Promociones Inmobiliarias Y Edificaciones Urtesa S.l.",
    "wof:placetype":"venue"
},
  "geometry": {"coordinates":[-1.6354459524,42.8060073853],"type":"Point"}
}