{
  "type": "Feature",
  "properties": {
    "iso:country":"ES",
    "sg:address":"Calle de Agata, 48",
    "sg:city":"Pozuelo De Alarcon",
    "sg:orig_category":"Fabricaci\u00d3n De Su\u00c9ters Y Chalecos De Punto",
    "sg:phone":"+34 913 52 66 29",
    "sg:postcode":"28224",
    "sg:province":"Madrid",
    "wof:name":"Jaenestextim S.l.",
    "wof:placetype":"venue"
},
  "geometry": {"coordinates":[-3.795648098,40.4394264221],"type":"Point"}
}