{
  "type": "Feature",
  "properties": {
    "iso:country":"ES",
    "sg:address":"Calle de Manuel De Vera, S/n",
    "sg:city":"Valle De Guerra",
    "sg:orig_category":"Empresas De Carpinter\u00cda De Madera",
    "sg:phone":"+34 922 54 43 52",
    "sg:postcode":"38270",
    "sg:province":"Santa Cruz De Tenerife",
    "wof:name":"Fernandez Diaz Jose Manuel",
    "wof:placetype":"venue"
},
  "geometry": {"coordinates":[-16.3963832855,28.5111694336],"type":"Point"}
}