{
  "type": "Feature",
  "properties": {
    "addr:full":"Calle de Alcala, 27 Madrid Madrid 28014",
    "addr:housenumber":"27",
    "addr:postcode":"madrid;28014",
    "addr:street":"Calle De Alcala",
    "iso:country":"ES",
    "sg:address":"Calle de Alcala, 27",
    "sg:city":"Madrid",
    "sg:orig_category":"Cajas De Ahorro",
    "sg:phone":"+34 915 32 09 89",
    "sg:postcode":"28014",
    "sg:province":"Madrid",
    "sg:website":"www.cajacantabria.com",
    "wof:name":"Cableuropa",
    "wof:placetype":"venue"
},
  "geometry": {"coordinates":[-3.698725462,40.4181098938],"type":"Point"}
}