{
  "type": "Feature",
  "properties": {
    "iso:country":"ES",
    "sg:address":"Calle de Major Sant Agusti, 5",
    "sg:city":"Alzira",
    "sg:orig_category":"Venta, Alquiler De Instrumentos Y Accesorios De M\u00dasica",
    "sg:phone":"+34 962 40 29 82",
    "sg:postcode":"46600",
    "sg:province":"Valencia",
    "wof:name":"Alzira Musical S.l.",
    "wof:placetype":"venue"
},
  "geometry": {"coordinates":[-0.4364452958,39.1501083374],"type":"Point"}
}