{
  "type": "Feature",
  "properties": {
    "iso:country":"ES",
    "sg:address":"Calle de General Mas De Gaminde, 22",
    "sg:city":"Palmas De Gran Canaria",
    "sg:orig_category":"Farmacias",
    "sg:phone":"+34 928 24 17 37",
    "sg:postcode":"35006",
    "sg:province":"Las Palmas",
    "wof:name":"Lantigua Usar Sandra",
    "wof:placetype":"venue"
},
  "geometry": {"coordinates":[-15.4337320328,28.1317596436],"type":"Point"}
}