{
  "type": "Feature",
  "properties": {
    "addr:full":"Carrer de Lleida, 59 S. Feliu Guixols Girona 17220",
    "addr:housenumber":"59",
    "addr:postcode":"17220",
    "addr:street":"Carrer De Lleida;S. Feliu Guixols",
    "iso:country":"ES",
    "sg:address":"Carrer de Lleida, 59",
    "sg:city":"S. Feliu Guixols",
    "sg:orig_category":"Panader\u00cdas, Panader\u00cdas",
    "sg:phone":"+34 972 32 24 00",
    "sg:postcode":"17220",
    "sg:province":"Girona",
    "wof:name":"Ruiz Garcia Sixto",
    "wof:placetype":"venue"
},
  "geometry": {"coordinates":[3.0246620178,41.7916641235],"type":"Point"}
}