{
  "type": "Feature",
  "properties": {
    "addr:full":"Uzbina Kalea, 24 Jundiz \u00c1lava 01015",
    "addr:housenumber":"24",
    "addr:postcode":"01015",
    "addr:street":"Uzbina Kalea;A\u0301Lava",
    "iso:country":"ES",
    "sg:address":"Uzbina Kalea, 24",
    "sg:city":"Jundiz",
    "sg:orig_category":"Venta, Alquiler De Plataformas Y Barquillas Elevadoras",
    "sg:phone":"+34 945 21 51 76",
    "sg:postcode":"01015",
    "sg:province":"\u00c1lava",
    "wof:name":"Redimauto S.l.",
    "wof:placetype":"venue"
},
  "geometry": {"coordinates":[-6.1999697685,43.3617782593],"type":"Point"}
}