{
  "type": "Feature",
  "properties": {
    "addr:full":"Calle de Leon Y Castillo, 12 Arrecife Las Palmas 35500",
    "addr:housenumber":"12",
    "addr:postcode":"35500",
    "addr:street":"Calle De Leon Y Castillo",
    "iso:country":"ES",
    "sg:address":"Calle de Leon Y Castillo, 12",
    "sg:city":"Arrecife",
    "sg:orig_category":"Bazares, Art\u00cdculos De Limpieza Y De Cocina (al Por Menor)",
    "sg:phone":"+34 928 81 59 96",
    "sg:postcode":"35500",
    "sg:province":"Las Palmas",
    "wof:name":"Rahoo Jethani Anita",
    "wof:placetype":"venue"
},
  "geometry": {"coordinates":[-13.5485334396,28.9592971802],"type":"Point"}
}