{
  "type": "Feature",
  "properties": {
    "iso:country":"ES",
    "sg:address":"Carr Infanta, 5",
    "sg:city":"Mao",
    "sg:orig_category":"Estancos",
    "sg:phone":"+34 971 36 33 55",
    "sg:postcode":"07702",
    "sg:province":"Islas Baleares",
    "wof:name":"Perches Escandell Catalina",
    "wof:placetype":"venue"
},
  "geometry": {"coordinates":[4.2684569359,39.8832893372],"type":"Point"}
}