{
  "type": "Feature",
  "properties": {
    "addr:full":"Calle de Juan De Austria, 2 Algar Murcia 30366",
    "addr:housenumber":"2",
    "addr:postcode":"30366",
    "addr:street":"Calle De Juan De Austria",
    "iso:country":"ES",
    "sg:address":"Calle de Juan De Austria, 2",
    "sg:city":"Algar",
    "sg:orig_category":"Centros De Educaci\u00d3n Especial",
    "sg:phone":"+34 968 13 56 20",
    "sg:postcode":"30366",
    "sg:province":"Murcia",
    "wof:name":"Colegio Nacional San Isidoro",
    "wof:placetype":"venue"
},
  "geometry": {"coordinates":[-0.8678010106,37.6480293274],"type":"Point"}
}