{
  "type": "Feature",
  "properties": {
    "iso:country":"ES",
    "sg:address":"Avda Gran Capitan (del), 48",
    "sg:city":"Cordoba",
    "sg:orig_category":"Ense\u00d1ante, Direcci\u00d3n",
    "sg:phone":"+34 957 40 21 16",
    "sg:postcode":"14006",
    "sg:province":"C\u00f3rdoba",
    "wof:name":"Vizuete Gonzalez Manuel",
    "wof:placetype":"venue"
},
  "geometry": {"coordinates":[-4.7829523087,37.8904876709],"type":"Point"}
}