{
  "type": "Feature",
  "properties": {
    "addr:full":"Colom, 485 Can Parellada Barcelona 08228",
    "addr:housenumber":"485",
    "addr:postcode":"08228",
    "addr:street":"Colom",
    "iso:country":"ES",
    "sg:address":"Colom, 485",
    "sg:city":"Can Parellada",
    "sg:orig_category":"Puertas Y Portales",
    "sg:phone":"+34 937 36 14 23",
    "sg:postcode":"08228",
    "sg:province":"Barcelona",
    "sg:website":"www.macpauesa.es",
    "wof:name":"Macpuar S.a.",
    "wof:placetype":"venue"
},
  "geometry": {"coordinates":[2.0362648964,41.5310096741],"type":"Point"}
}