{
  "type": "Feature",
  "properties": {
    "iso:country":"ES",
    "sg:address":"Calle de Feira Nova, S/n",
    "sg:city":"Ferreira",
    "sg:orig_category":"Distribuci\u00d3n De Petr\u00d3leo Y Derivados",
    "sg:phone":"+34 982 57 40 51",
    "sg:postcode":"27770",
    "sg:province":"Lugo",
    "wof:name":"Estacion De Servicio Valle De Oro",
    "wof:placetype":"venue"
},
  "geometry": {"coordinates":[-7.4409542084,43.5518302917],"type":"Point"}
}