{
  "type": "Feature",
  "properties": {
    "iso:country":"ES",
    "sg:address":"Calle de Lopez De Ayala, 11",
    "sg:city":"Montijo",
    "sg:orig_category":"Arquitectos",
    "sg:phone":"+34 924 45 58 49",
    "sg:postcode":"06480",
    "sg:province":"Badajoz",
    "wof:name":"Alvarez Rodriguez Filomena",
    "wof:placetype":"venue"
},
  "geometry": {"coordinates":[-6.6129550934,38.9102134705],"type":"Point"}
}