{
  "type": "Feature",
  "properties": {
    "iso:country":"ES",
    "sg:address":"Plaz Colon, 3",
    "sg:city":"Salamanca",
    "sg:orig_category":"Obras Y Organismos Sociales",
    "sg:phone":"+34 923 21 27 67",
    "sg:postcode":"37001",
    "sg:province":"Salamanca",
    "wof:name":"Patronato Institucion Particular Caritativo-benefica Esteban Sant",
    "wof:placetype":"venue"
},
  "geometry": {"coordinates":[-5.6636171341,40.9628257751],"type":"Point"}
}