{
  "type": "Feature",
  "properties": {
    "addr:full":"Av Pi I Margall, 43 Caldes Montbui Barcelona 08140",
    "addr:housenumber":"43",
    "addr:postcode":"08140",
    "addr:street":"Av Pi I Margall;Montbui Barcelona",
    "iso:country":"ES",
    "sg:address":"Av Pi I Margall, 43",
    "sg:city":"Caldes Montbui",
    "sg:orig_category":"Agentes Generales De Seguros",
    "sg:phone":"+34 938 65 09 36",
    "sg:postcode":"08140",
    "sg:province":"Barcelona",
    "wof:name":"Plantada Poch Maria Merce",
    "wof:placetype":"venue"
},
  "geometry": {"coordinates":[2.1644949913,41.6312026978],"type":"Point"}
}