{
  "type": "Feature",
  "properties": {
    "iso:country":"ES",
    "sg:address":"Calle de Canoa, 26",
    "sg:city":"Madrid",
    "sg:orig_category":"Florister\u00cdas",
    "sg:phone":"+34 913 93 06 61",
    "sg:postcode":"28042",
    "sg:province":"Madrid",
    "wof:name":"Gutierrez Delgado Alberto",
    "wof:placetype":"venue"
},
  "geometry": {"coordinates":[-3.5911841393,40.4547309875],"type":"Point"}
}