{
  "type": "Feature",
  "properties": {
    "iso:country":"ES",
    "sg:address":"Carr Vallier, 19",
    "sg:city":"Gandia",
    "sg:orig_category":"Ropa Y Accesorios",
    "sg:phone":"+34 962 86 05 82",
    "sg:postcode":"46700",
    "sg:province":"Valencia",
    "wof:name":"Oltra Martinez Eduardo",
    "wof:placetype":"venue"
},
  "geometry": {"coordinates":[-0.1913339943,38.960735321],"type":"Point"}
}