{
  "type": "Feature",
  "properties": {
    "iso:country":"ES",
    "sg:address":"Avda Antonio Machado, 11",
    "sg:city":"Arroyo De La Miel-benalmadena Costa",
    "sg:orig_category":"Molduras, Junquillos, Listones Y Molduras Perforadas",
    "sg:phone":"+34 952 44 98 34",
    "sg:postcode":"29630",
    "sg:province":"M\u00e1laga",
    "wof:name":"Suleyman Pascha S.l",
    "wof:placetype":"venue"
},
  "geometry": {"coordinates":[-4.5154829025,36.6006851196],"type":"Point"}
}