{
  "type": "Feature",
  "properties": {
    "addr:full":"Carr Ermita, 165 Villarreal Castell\u00f3n 12540",
    "addr:housenumber":"165",
    "addr:postcode":"12540",
    "addr:street":"Carr Ermita",
    "iso:country":"ES",
    "sg:address":"Carr Ermita, 165",
    "sg:city":"Villarreal",
    "sg:orig_category":"Fabricaci\u00d3n De Bebidas No Alcoh\u00d3licas",
    "sg:phone":"+34 964 52 73 67",
    "sg:postcode":"12540",
    "sg:province":"Castell\u00f3n",
    "wof:name":"Felix Meneu Jaime",
    "wof:placetype":"venue"
},
  "geometry": {"coordinates":[-0.0952939987,39.9453048706],"type":"Point"}
}