{
  "type": "Feature",
  "properties": {
    "addr:full":"Calle de Doctor Fleming, 56 Dos Hermanas Sevilla 41700",
    "addr:housenumber":"56",
    "addr:postcode":"41700",
    "addr:street":"Calle De Doctor Fleming",
    "iso:country":"ES",
    "sg:address":"Calle de Doctor Fleming, 56",
    "sg:city":"Dos Hermanas",
    "sg:orig_category":"Mec\u00c1nico Del Autom\u00d3vil",
    "sg:phone":"+34 954 72 02 29",
    "sg:postcode":"41700",
    "sg:province":"Sevilla",
    "wof:name":"Auto Valdelvira E Hijos S.l.",
    "wof:placetype":"venue"
},
  "geometry": {"coordinates":[-5.934387207,37.283290863],"type":"Point"}
}