{
  "type": "Feature",
  "properties": {
    "addr:full":"Calle de Poeta Carlos Mellado, 1 San Mateo Murcia 30800",
    "addr:housenumber":"1",
    "addr:postcode":"30800",
    "addr:street":"Calle De Poeta Carlos Mellado",
    "iso:country":"ES",
    "sg:address":"Calle de Poeta Carlos Mellado, 1",
    "sg:city":"San Mateo",
    "sg:orig_category":"Ingenier\u00cda, Centros De Estudios (diversos)",
    "sg:phone":"+34 968 44 29 44",
    "sg:postcode":"30800",
    "sg:province":"Murcia",
    "wof:name":"Meca Alcazar Jesus",
    "wof:placetype":"venue"
},
  "geometry": {"coordinates":[-1.6905640364,37.680557251],"type":"Point"}
}