{
  "type": "Feature",
  "properties": {
    "addr:full":"Carrer de Sant Pau, 30 Riudoms Tarragona 43330",
    "addr:housenumber":"30",
    "addr:postcode":"43330",
    "addr:street":"Carrer De Sant Pau",
    "iso:country":"ES",
    "sg:address":"Carrer de Sant Pau, 30",
    "sg:city":"Riudoms",
    "sg:orig_category":"Triper\u00cdas",
    "sg:phone":"+34 977 85 02 32",
    "sg:postcode":"43330",
    "sg:province":"Tarragona",
    "wof:name":"Olle Font Pedro",
    "wof:placetype":"venue"
},
  "geometry": {"coordinates":[1.049849987,41.1397018433],"type":"Point"}
}