{
  "type": "Feature",
  "properties": {
    "iso:country":"ES",
    "sg:address":"Calle de Martin Machio, 13",
    "sg:city":"Madrid",
    "sg:orig_category":"Alumbrados",
    "sg:phone":"+34 914 15 86 04",
    "sg:postcode":"28002",
    "sg:province":"Madrid",
    "sg:website":"www.grauluminotecnia.com",
    "wof:name":"Grau Luminotecnia S. A.",
    "wof:placetype":"venue"
},
  "geometry": {"coordinates":[-3.6633059978,40.4479141235],"type":"Point"}
}