{
  "type": "Feature",
  "properties": {
    "iso:country":"ES",
    "sg:address":"Avda Blas Infante, 22",
    "sg:city":"Arroyo De La Miel-benalmadena Costa",
    "sg:orig_category":"Agencias De Viajes",
    "sg:phone":"+34 952 56 27 50",
    "sg:postcode":"29631",
    "sg:province":"M\u00e1laga",
    "wof:name":"Viajes Univercom S.l.",
    "wof:placetype":"venue"
},
  "geometry": {"coordinates":[-4.5355639458,36.5975456238],"type":"Point"}
}