{
  "type": "Feature",
  "properties": {
    "iso:country":"ES",
    "sg:address":"Calle de Tiendas (las), 42",
    "sg:city":"Cuevas Almanzora",
    "sg:orig_category":"Heladeros",
    "sg:phone":"+34 950 45 61 62",
    "sg:postcode":"04610",
    "sg:province":"Almer\u00eda",
    "wof:name":"Azor Benitez Pedro",
    "wof:placetype":"venue"
},
  "geometry": {"coordinates":[-1.8810195923,37.2964668274],"type":"Point"}
}