{
  "type": "Feature",
  "properties": {
    "iso:country":"ES",
    "sg:address":"Calle de Colon, 42",
    "sg:city":"Castellon",
    "sg:orig_category":"Alimentaci\u00d3n General (al Por Menor)",
    "sg:phone":"+34 964 21 48 64",
    "sg:postcode":"12001",
    "sg:province":"Castell\u00f3n",
    "wof:name":"Arcusa Breva Joaquin",
    "wof:placetype":"venue"
},
  "geometry": {"coordinates":[-0.0388494991,39.9868545532],"type":"Point"}
}