{
  "type": "Feature",
  "properties": {
    "addr:full":"Rua Manuel Murguia, 14 Ourense Ourense 32...",
    "addr:housenumber":"14;32 ...",
    "addr:street":"Rua Manuel Murguia;Ourense",
    "iso:country":"ES",
    "sg:address":"Rua Manuel Murguia, 14",
    "sg:city":"Ourense",
    "sg:orig_category":"Cables Y Hilos El\u00c9ctricos (fabricaci\u00d3n, Al Por Mayor)",
    "sg:phone":"+34 988 39 86 00",
    "sg:postcode":"32...",
    "sg:province":"Ourense",
    "wof:name":"R Cable Y Telecomunicaciones Galicia S.a.",
    "wof:placetype":"venue"
},
  "geometry": {"coordinates":[-7.864795208,42.3284606934],"type":"Point"}
}