{
  "type": "Feature",
  "properties": {
    "iso:country":"ES",
    "sg:address":"Calle de Camelia, 15",
    "sg:city":"Zaragoza",
    "sg:orig_category":"Electricidad: Instalaciones Industriales",
    "sg:phone":"+34 976 53 64 86",
    "sg:postcode":"50012",
    "sg:province":"Zaragoza",
    "wof:name":"Montajes Electricos Numen S.l",
    "wof:placetype":"venue"
},
  "geometry": {"coordinates":[-0.9278767109,41.6413002014],"type":"Point"}
}