{
  "type": "Feature",
  "properties": {
    "addr:full":"Carrer de Pescadors, 4 Cambrils Tarragona 43850",
    "addr:housenumber":"4",
    "addr:postcode":"43850",
    "addr:street":"Carrer De Pescadors",
    "iso:country":"ES",
    "sg:address":"Carrer de Pescadors, 4",
    "sg:city":"Cambrils",
    "sg:orig_category":"Relojer\u00cda (al Por Menor, Reparaci\u00d3n)",
    "sg:phone":"+34 977 36 05 51",
    "sg:postcode":"43850",
    "sg:province":"Tarragona",
    "wof:name":"Serrano Ma\u00f1e S.c.p.",
    "wof:placetype":"venue"
},
  "geometry": {"coordinates":[1.0613050461,41.0655555725],"type":"Point"}
}