{
  "type": "Feature",
  "properties": {
    "addr:full":"Avda Eugenio Sequeiros, S/n Cangas Pontevedra 36940",
    "addr:housenumber":"s / n",
    "addr:postcode":"36940",
    "addr:street":"Avda Eugenio Sequeiros",
    "iso:country":"ES",
    "sg:address":"Avda Eugenio Sequeiros, S/n",
    "sg:city":"Cangas",
    "sg:orig_category":"Quincaller\u00cda (al Por Menor)",
    "sg:phone":"+34 986 30 01 64",
    "sg:postcode":"36940",
    "sg:province":"Pontevedra",
    "wof:name":"Fernandez Chapela Antonio",
    "wof:placetype":"venue"
},
  "geometry": {"coordinates":[-8.8184690475,42.2742500305],"type":"Point"}
}