{
  "type": "Feature",
  "properties": {
    "addr:full":"Pl Nova, 7 Fonts Barcelona 08194",
    "addr:housenumber":"7",
    "addr:postcode":"08194",
    "addr:street":"Pl Nova;Barcelona",
    "iso:country":"ES",
    "sg:address":"Pl Nova, 7",
    "sg:city":"Fonts",
    "sg:orig_category":"Extinci\u00d3n De Incendios: Material Y Suministros (fabricaci\u00d3n, Al Por Mayor)",
    "sg:phone":"+34 937 31 51 17",
    "sg:postcode":"08194",
    "sg:province":"Barcelona",
    "wof:name":"Doya Perez Jose Luis",
    "wof:placetype":"venue"
},
  "geometry": {"coordinates":[2.035597086,41.5243530273],"type":"Point"}
}