{
  "type": "Feature",
  "properties": {
    "addr:full":"Villaprimera, 3 Pobra Trives Ourense 32780",
    "addr:housenumber":"3",
    "addr:postcode":"32780",
    "addr:street":"Villaprimera",
    "iso:country":"ES",
    "sg:address":"Villaprimera, 3",
    "sg:city":"Pobra Trives",
    "sg:orig_category":"Mec\u00c1nico Del Autom\u00d3vil",
    "sg:phone":"+34 988 33 00 79",
    "sg:postcode":"32780",
    "sg:province":"Ourense",
    "wof:name":"Talleres Garcia Sociedad Civil",
    "wof:placetype":"venue"
},
  "geometry": {"coordinates":[-7.2545762062,42.3393707275],"type":"Point"}
}