{
  "type": "Feature",
  "properties": {
    "addr:full":"Rua Cami\u00d1o De Carracedo, S/n Fonsagrada Lugo 27100",
    "addr:housenumber":"s / n",
    "addr:postcode":"27100",
    "addr:street":"Rua Camin\u0303O",
    "iso:country":"ES",
    "sg:address":"Rua Cami\u00d1o De Carracedo, S/n",
    "sg:city":"Fonsagrada",
    "sg:orig_category":"Electricidad Veh\u00cdculo",
    "sg:phone":"+34 982 34 01 78",
    "sg:postcode":"27100",
    "sg:province":"Lugo",
    "wof:name":"Rey Vila Jose Ramon",
    "wof:placetype":"venue"
},
  "geometry": {"coordinates":[-7.0673189163,43.125995636],"type":"Point"}
}