{
  "type": "Feature",
  "properties": {
    "addr:full":"Calle de Madrid, 10 Santo Domingo De La Calzada La Rioja 26250",
    "addr:housenumber":"10",
    "addr:postcode":"26250",
    "addr:street":"Calle De Madrid;Rioja",
    "iso:country":"ES",
    "sg:address":"Calle de Madrid, 10",
    "sg:city":"Santo Domingo De La Calzada",
    "sg:orig_category":"M\u00c9dicos: Estomatolog\u00cda",
    "sg:phone":"+34 941 34 21 42",
    "sg:postcode":"26250",
    "sg:province":"La Rioja",
    "wof:name":"Arce Diaz Maria Angeles",
    "wof:placetype":"venue"
},
  "geometry": {"coordinates":[-2.9546134472,42.4385795593],"type":"Point"}
}