{
  "type": "Feature",
  "properties": {
    "iso:country":"ES",
    "sg:address":"Ctra Monforte, 25",
    "sg:city":"Aspe",
    "sg:orig_category":"Muebles Y Accesorios Para Cocinas Y Cuartos De Ba\u00d1o (al Por Menor)",
    "sg:phone":"+34 965 49 15 13",
    "sg:postcode":"03680",
    "sg:province":"Alicante",
    "wof:name":"Auximobel S.l.",
    "wof:placetype":"venue"
},
  "geometry": {"coordinates":[-0.7650079131,38.3524742126],"type":"Point"}
}