{
  "type": "Feature",
  "properties": {
    "addr:full":"Carrer de Puig Rom, 20 Roses Girona 17480",
    "addr:housenumber":"20",
    "addr:postcode":"17480",
    "addr:street":"Carrer De Puig Rom",
    "iso:country":"ES",
    "sg:address":"Carrer de Puig Rom, 20",
    "sg:city":"Roses",
    "sg:orig_category":"Florister\u00cdas",
    "sg:phone":"+34 972 25 53 08",
    "sg:postcode":"17480",
    "sg:province":"Girona",
    "wof:name":"Barcelo Baro Jose",
    "wof:placetype":"venue"
},
  "geometry": {"coordinates":[3.1837520599,42.2570762634],"type":"Point"}
}