{
  "type": "Feature",
  "properties": {
    "addr:full":"Calle de Cardenal Lorenzana, 5 Le\u00f3n Le\u00f3n 24001",
    "addr:housenumber":"5",
    "addr:postcode":"24001",
    "addr:street":"Calle De Cardenal Lorenzana;Leo\u0301N",
    "iso:country":"ES",
    "sg:address":"Calle de Cardenal Lorenzana, 5",
    "sg:city":"Le\u00f3n",
    "sg:orig_category":"Abogados",
    "sg:phone":"+34 987 27 25 22",
    "sg:postcode":"24001",
    "sg:province":"Le\u00f3n",
    "wof:name":"Martinez Martinez Santiago Santos",
    "wof:placetype":"venue"
},
  "geometry": {"coordinates":[-5.5781140327,42.5977859497],"type":"Point"}
}