{
  "type": "Feature",
  "properties": {
    "addr:full":"Los Batanes, S/n Alcaraz Albacete 02300",
    "addr:housenumber":"s / n",
    "addr:postcode":"02300",
    "addr:street":"Alcaraz",
    "iso:country":"ES",
    "sg:address":"Los Batanes, S/n",
    "sg:city":"Alcaraz",
    "sg:orig_category":"Empresas De Electricidad En General",
    "sg:phone":"+34 967 58 10 47",
    "sg:postcode":"02300",
    "sg:province":"Albacete",
    "wof:name":"Hidroelectrica Los Batanes S.a.",
    "wof:placetype":"venue"
},
  "geometry": {"coordinates":[-2.4667539597,38.6473884583],"type":"Point"}
}