{
  "type": "Feature",
  "properties": {
    "addr:full":"Calle de Aracataca, S/n Madrid Madrid 28033",
    "addr:housenumber":"s / n",
    "addr:postcode":"28033",
    "addr:street":"Calle De Aracataca",
    "iso:country":"ES",
    "sg:address":"Calle de Aracataca, S/n",
    "sg:city":"Madrid",
    "sg:orig_category":"Cerrajer\u00cda, Ferrallista",
    "sg:phone":"+34 917 63 73 58",
    "sg:postcode":"28033",
    "sg:province":"Madrid",
    "wof:name":"Nu\u00f1ez Fernandez Tomas",
    "wof:placetype":"venue"
},
  "geometry": {"coordinates":[-3.6384096146,40.4736480713],"type":"Point"}
}