{
  "type": "Feature",
  "properties": {
    "iso:country":"ES",
    "sg:address":"Rua Conde Torrecedeira, 29",
    "sg:city":"Vigo",
    "sg:orig_category":"Droguer\u00cdas (al Por Menor)",
    "sg:phone":"+34 986 24 03 95",
    "sg:postcode":"36202",
    "sg:province":"Pontevedra",
    "wof:name":"Dropu S.l.",
    "wof:placetype":"venue"
},
  "geometry": {"coordinates":[-8.7312898636,42.2332992554],"type":"Point"}
}