{
  "type": "Feature",
  "properties": {
    "iso:country":"ES",
    "sg:address":"Psaj Maria Auxiliadora, 3",
    "sg:city":"Valdepe\u00f1as",
    "sg:orig_category":"Loter\u00cda Y T\u00d3mbola",
    "sg:phone":"+34 926 31 18 85",
    "sg:postcode":"13300",
    "sg:province":"Ciudad Real",
    "wof:name":"Pe\u00f1alver Cornejo Maria Del Carmen",
    "wof:placetype":"venue"
},
  "geometry": {"coordinates":[-3.3835420609,38.7606887817],"type":"Point"}
}