{
  "type": "Feature",
  "properties": {
    "addr:full":"Calle de Pilar, 5 Casinos Valencia 46171",
    "addr:housenumber":"5",
    "addr:postcode":"46171",
    "addr:street":"Calle De Pilar",
    "iso:country":"ES",
    "sg:address":"Calle de Pilar, 5",
    "sg:city":"Casinos",
    "sg:orig_category":"Ahumados Y Salazones",
    "sg:phone":"+34 962 70 04 97",
    "sg:postcode":"46171",
    "sg:province":"Valencia",
    "wof:name":"Vicente Alvir Herrero Y Rafael Albir Herrero Comunidad De Bienes",
    "wof:placetype":"venue"
},
  "geometry": {"coordinates":[-0.709641993,39.6986274719],"type":"Point"}
}