{
  "type": "Feature",
  "properties": {
    "addr:full":"Calle de Baluarte, 2 Algeciras C\u00e1diz 11201",
    "addr:housenumber":"2;ca\u0301diz",
    "addr:postcode":"11201",
    "addr:street":"Calle De Baluarte",
    "iso:country":"ES",
    "sg:address":"Calle de Baluarte, 2",
    "sg:city":"Algeciras",
    "sg:orig_category":"Abogados",
    "sg:phone":"+34 956 66 20 64",
    "sg:postcode":"11201",
    "sg:province":"C\u00e1diz",
    "wof:name":"Campmany Y Diez De Revenga Juan",
    "wof:placetype":"venue"
},
  "geometry": {"coordinates":[-5.4459738731,36.1337394714],"type":"Point"}
}