{
  "type": "Feature",
  "properties": {
    "addr:full":"Genilla, Km. 0009,5 Genilla C\u00f3rdoba 14816",
    "addr:postcode":"14816",
    "addr:street":"Genilla Km. 0009,5 Genilla Co\u0301Rdoba",
    "iso:country":"ES",
    "sg:address":"Genilla, Km. 0009,5",
    "sg:city":"Genilla",
    "sg:orig_category":"Asociaciones Y Clubs Deportivos",
    "sg:phone":"+34 957 72 01 19",
    "sg:postcode":"14816",
    "sg:province":"C\u00f3rdoba",
    "wof:name":"Onieba Merino Aurora",
    "wof:placetype":"venue"
},
  "geometry": {"coordinates":[-4.1533799171,37.4520111084],"type":"Point"}
}