{
  "type": "Feature",
  "properties": {
    "addr:full":"Calle de San Vicente Martir, 25 Madrid Madrid 28043",
    "addr:housenumber":"25",
    "addr:postcode":"madrid;28043",
    "addr:street":"Calle De San Vicente Martir",
    "iso:country":"ES",
    "sg:address":"Calle de San Vicente Martir, 25",
    "sg:city":"Madrid",
    "sg:orig_category":"Creaci\u00d3n De Sitios, Hosting Internet",
    "sg:phone":"+34 915 41 59 97",
    "sg:postcode":"28043",
    "sg:province":"Madrid",
    "sg:website":"www.lemonade.es",
    "wof:name":"Lemonade S.l.",
    "wof:placetype":"venue"
},
  "geometry": {"coordinates":[-3.6624441147,40.4559364319],"type":"Point"}
}