{
  "type": "Feature",
  "properties": {
    "iso:country":"ES",
    "sg:address":"Carrer de Can Cortes, 45",
    "sg:city":"Palau-solita I Plegamans",
    "sg:orig_category":"Mec\u00c1nico Del Autom\u00d3vil",
    "sg:phone":"+34 938 64 54 59",
    "sg:postcode":"08184",
    "sg:province":"Barcelona",
    "wof:name":"Autoservei Pujalt S.l.",
    "wof:placetype":"venue"
},
  "geometry": {"coordinates":[2.1749289036,41.5829811096],"type":"Point"}
}