{
  "type": "Feature",
  "properties": {
    "addr:full":"Rbla Marquesa De Castellbell, 84 Sant Feliu Llobregat Barcelona 08980",
    "addr:housenumber":"84",
    "addr:postcode":"08980",
    "addr:street":"Rbla Marquesa De Castellbell",
    "iso:country":"ES",
    "sg:address":"Rbla Marquesa De Castellbell, 84",
    "sg:city":"Sant Feliu Llobregat",
    "sg:orig_category":"Cajas De Ahorro",
    "sg:phone":"+34 936 66 02 25",
    "sg:postcode":"08980",
    "sg:province":"Barcelona",
    "wof:name":"Caixa D'estalvis Del Penedes",
    "wof:placetype":"venue"
},
  "geometry": {"coordinates":[2.0488529205,41.3856811523],"type":"Point"}
}