{
  "type": "Feature",
  "properties": {
    "iso:country":"ES",
    "sg:address":"Calle de Veleta, 16",
    "sg:city":"Zubia",
    "sg:orig_category":"Promotores Constructores",
    "sg:phone":"+34 958 89 20 05",
    "sg:postcode":"18140",
    "sg:province":"Granada",
    "wof:name":"Construcciones Los Abetos De La Zubia S.l.",
    "wof:placetype":"venue"
},
  "geometry": {"coordinates":[-3.5925040245,37.1117591858],"type":"Point"}
}