{
  "type": "Feature",
  "properties": {
    "iso:country":"ES",
    "sg:address":"Avgd Concordia, 8",
    "sg:city":"Aldaia",
    "sg:orig_category":"M\u00c1rmoles, Granitos Y Piedras Naturales",
    "sg:phone":"+34 961 50 15 24",
    "sg:postcode":"46960",
    "sg:province":"Valencia",
    "wof:name":"Valenciana Del Granito Escribano S.l.",
    "wof:placetype":"venue"
},
  "geometry": {"coordinates":[-0.4691349864,39.4625205994],"type":"Point"}
}