{
  "type": "Feature",
  "properties": {
    "iso:country":"ES",
    "sg:address":"Calle de Luis Gonzalez Valdesuso, S/n",
    "sg:city":"Vilalba",
    "sg:orig_category":"Telas Para Tapizar, Cortinas, Pasamaner\u00cda (fabricaci\u00d3n, Al Por Mayor)",
    "sg:phone":"+34 982 51 00 69",
    "sg:postcode":"27800",
    "sg:province":"Lugo",
    "wof:name":"Valle Cascudo Severino Del",
    "wof:placetype":"venue"
},
  "geometry": {"coordinates":[-7.6331129074,43.2868766785],"type":"Point"}
}