{
  "type": "Feature",
  "properties": {
    "iso:country":"ES",
    "sg:address":"Av Grecia, 45",
    "sg:city":"Estartit",
    "sg:orig_category":"Fabricaci\u00d3n, Importaci\u00d3n De L\u00c1mparas Y Bombillas",
    "sg:phone":"+34 972 75 14 83",
    "sg:postcode":"17258",
    "sg:province":"Girona",
    "wof:name":"Artalejo Sanchez Martin",
    "wof:placetype":"venue"
},
  "geometry": {"coordinates":[3.1946592331,42.0509262085],"type":"Point"}
}