{
  "type": "Feature",
  "properties": {
    "addr:full":"Carrer de L'alzina, 35 Barcelona Barcelona 08024",
    "addr:housenumber":"35",
    "addr:postcode":"08024",
    "addr:street":"Carrer De L'Alzina",
    "iso:country":"ES",
    "sg:address":"Carrer de L'alzina, 35",
    "sg:city":"Barcelona",
    "sg:orig_category":"Planchado",
    "sg:phone":"+34 932 37 57 34",
    "sg:postcode":"08024",
    "sg:province":"Barcelona",
    "wof:name":"Soriano Molina Francisco",
    "wof:placetype":"venue"
},
  "geometry": {"coordinates":[2.1551821232,41.4077453613],"type":"Point"}
}