{
  "type": "Feature",
  "properties": {
    "addr:full":"Avgd Ros I Guell, 21 Badalona Barcelona 08915",
    "addr:housenumber":"21",
    "addr:postcode":"08915",
    "addr:street":"Guell",
    "iso:country":"ES",
    "sg:address":"Avgd Ros I Guell, 21",
    "sg:city":"Badalona",
    "sg:orig_category":"Dibujantes (diversos)",
    "sg:phone":"+34 933 95 03 57",
    "sg:postcode":"08915",
    "sg:province":"Barcelona",
    "wof:name":"Monta\u00f1a Alsina Luis",
    "wof:placetype":"venue"
},
  "geometry": {"coordinates":[2.2372829914,41.4665679932],"type":"Point"}
}