{
  "type": "Feature",
  "properties": {
    "iso:country":"ES",
    "sg:address":"Urb Lagomar, 13",
    "sg:city":"Nueva Andalucia",
    "sg:orig_category":"Ropa Para Se\u00d1oras (al Por Menor)",
    "sg:phone":"+34 952 81 90 88",
    "sg:postcode":"29660",
    "sg:province":"M\u00e1laga",
    "wof:name":"Wissenberg  Benedicte Elisabeth",
    "wof:placetype":"venue"
},
  "geometry": {"coordinates":[-4.963350296,36.498714447],"type":"Point"}
}