{
  "type": "Feature",
  "properties": {
    "iso:country":"ES",
    "sg:address":"Plaz Fueros, 10",
    "sg:city":"Ablitas",
    "sg:orig_category":"Farmacias",
    "sg:phone":"+34 948 81 38 11",
    "sg:postcode":"31523",
    "sg:province":"Navarra",
    "wof:name":"Escalada Abrahan Maria Monserrat",
    "wof:placetype":"venue"
},
  "geometry": {"coordinates":[-1.6395529509,41.9735603333],"type":"Point"}
}