{
  "type": "Feature",
  "properties": {
    "iso:country":"ES",
    "sg:address":"C/ Santa Rosa, 28",
    "sg:city":"Alcoi",
    "sg:orig_category":"Inmobiliaria (agencias)",
    "sg:phone":"+34 965 33 32 30",
    "sg:postcode":"03802",
    "sg:province":"Alicante",
    "wof:name":"Motilla Canto Paulino",
    "wof:placetype":"venue"
},
  "geometry": {"coordinates":[-0.4842689931,38.6963195801],"type":"Point"}
}