{
  "type": "Feature",
  "properties": {
    "iso:country":"ES",
    "sg:address":"Carrer de Balmes, 89",
    "sg:city":"Barcelona",
    "sg:orig_category":"Institutos De Belleza",
    "sg:phone":"+34 933 23 25 20",
    "sg:postcode":"08008",
    "sg:province":"Barcelona",
    "wof:name":"Body Balmes S.l.",
    "wof:placetype":"venue"
},
  "geometry": {"coordinates":[2.1599829197,41.3911132812],"type":"Point"}
}