{
  "type": "Feature",
  "properties": {
    "addr:full":"Calle de E(campollano), 18 Albacete Albacete 02006",
    "addr:housenumber":"18",
    "addr:postcode":"02006",
    "addr:street":"Calle De E Campollano",
    "iso:country":"ES",
    "sg:address":"Calle de E(campollano), 18",
    "sg:city":"Albacete",
    "sg:orig_category":"Cerrajer\u00cda, Ferrallista",
    "sg:phone":"+34 967 21 04 28",
    "sg:postcode":"02006",
    "sg:province":"Albacete",
    "wof:name":"Sanchez Corcoles Hermanos S.l.",
    "wof:placetype":"venue"
},
  "geometry": {"coordinates":[-1.937054038,39.0609474182],"type":"Point"}
}