{
  "type": "Feature",
  "properties": {
    "iso:country":"ES",
    "sg:address":"Carr Canonge Moll, S/n",
    "sg:city":"Ciutadella Menorca",
    "sg:orig_category":"M\u00c9dicos: An\u00c1lisis Cl\u00cdnicos",
    "sg:phone":"+34 971 48 05 05",
    "sg:postcode":"07760",
    "sg:province":"Islas Baleares",
    "wof:name":"Clinica Salus Menorca S.l.",
    "wof:placetype":"venue"
},
  "geometry": {"coordinates":[3.8412148952,40.0055351257],"type":"Point"}
}