{
  "type": "Feature",
  "properties": {
    "addr:full":"Calle de Leon Merino, 15 Carolina Ja\u00e9n 23200",
    "addr:housenumber":"15",
    "addr:postcode":"23200",
    "addr:street":"Calle De Leon Merino;Jae\u0301N",
    "iso:country":"ES",
    "sg:address":"Calle de Leon Merino, 15",
    "sg:city":"Carolina",
    "sg:orig_category":"Frutas Y Legumbres Frescas (al Por Mayor)",
    "sg:phone":"+34 953 66 04 47",
    "sg:postcode":"23200",
    "sg:province":"Ja\u00e9n",
    "wof:name":"Frutas Y Verduras La Carolina S.l.",
    "wof:placetype":"venue"
},
  "geometry": {"coordinates":[-3.6146440506,38.2782936096],"type":"Point"}
}