{
  "type": "Feature",
  "properties": {
    "iso:country":"ES",
    "sg:address":"Plaz Mayor, 1",
    "sg:city":"Encina S. Silvestre",
    "sg:orig_category":"Centros De Educaci\u00d3n Especial",
    "sg:phone":"+34 923 14 05 27",
    "sg:postcode":"37114",
    "sg:province":"Salamanca",
    "wof:name":"Cra El Tomillar",
    "wof:placetype":"venue"
},
  "geometry": {"coordinates":[-6.1118588448,41.0353660583],"type":"Point"}
}