{
  "type": "Feature",
  "properties": {
    "iso:country":"ES",
    "sg:address":"Calle de Salcillo, 5",
    "sg:city":"Mostoles",
    "sg:orig_category":"Confecci\u00d3n (fabricaci\u00d3n, Al Por Mayor)",
    "sg:phone":"+34 916 17 59 62",
    "sg:postcode":"28932",
    "sg:province":"Madrid",
    "wof:name":"Suarez Santamaria Carlos",
    "wof:placetype":"venue"
},
  "geometry": {"coordinates":[-3.8644287586,40.3341331482],"type":"Point"}
}