{
  "type": "Feature",
  "properties": {
    "iso:country":"ES",
    "sg:address":"Calle de Victor Pe\u00d1asco (don), 50",
    "sg:city":"Tomelloso",
    "sg:orig_category":"Ropa De Trabajo Y Profesionales (al Por Menor)",
    "sg:phone":"+34 926 51 40 76",
    "sg:postcode":"13700",
    "sg:province":"Ciudad Real",
    "wof:name":"Sevilla Andujar Fe",
    "wof:placetype":"venue"
},
  "geometry": {"coordinates":[-3.0227329731,39.1559333801],"type":"Point"}
}