{
  "type": "Feature",
  "properties": {
    "addr:full":"Calle de Cruz Blanca, 9 Vitoria-gasteiz \u00c1lava 01012",
    "addr:housenumber":"9",
    "addr:postcode":"01012",
    "addr:street":"Calle De Cruz Blanca",
    "iso:country":"ES",
    "sg:address":"Calle de Cruz Blanca, 9",
    "sg:city":"Vitoria-gasteiz",
    "sg:orig_category":"Venta, Montaje De Neum\u00c1ticos",
    "sg:phone":"+34 945 22 57 15",
    "sg:postcode":"01012",
    "sg:province":"\u00c1lava",
    "wof:name":"Rubio Ortigosa Luis Maria",
    "wof:placetype":"venue"
},
  "geometry": {"coordinates":[-2.6788079739,42.8524627686],"type":"Point"}
}