{
  "type": "Feature",
  "properties": {
    "iso:country":"ES",
    "sg:address":"Carrer de Poeta Boscan, 2",
    "sg:city":"Barbera Valles",
    "sg:orig_category":"Empresas De Pintura Y Revestimientos",
    "sg:phone":"+34 937 18 34 04",
    "sg:postcode":"08210",
    "sg:province":"Barcelona",
    "wof:name":"Fabregat Casoliva Lluis",
    "wof:placetype":"venue"
},
  "geometry": {"coordinates":[2.1228530407,41.5128936768],"type":"Point"}
}