{
  "type": "Feature",
  "properties": {
    "addr:full":"Calle de Paseo De La Ribera, 106 Valtierra Navarra 31514",
    "addr:housenumber":"106",
    "addr:postcode":"31514",
    "addr:street":"Calle De Paseo De La Ribera",
    "iso:country":"ES",
    "sg:address":"Calle de Paseo De La Ribera, 106",
    "sg:city":"Valtierra",
    "sg:orig_category":"Molduras, Junquillos, Listones Y Molduras Perforadas",
    "sg:phone":"+34 948 86 71 53",
    "sg:postcode":"31514",
    "sg:province":"Navarra",
    "wof:name":"Mena Martinez Jose Luis",
    "wof:placetype":"venue"
},
  "geometry": {"coordinates":[-1.6343460083,42.1953735352],"type":"Point"}
}