{
  "type": "Feature",
  "properties": {
    "iso:country":"ES",
    "sg:address":"Avda Mariano Andres, 228",
    "sg:city":"Le\u00f3n",
    "sg:orig_category":"Guarder\u00cdas",
    "sg:phone":"+34 987 24 50 62",
    "sg:postcode":"24008",
    "sg:province":"Le\u00f3n",
    "wof:name":"Ayuntamiento De Leon",
    "wof:placetype":"venue"
},
  "geometry": {"coordinates":[-5.5705704689,42.6120300293],"type":"Point"}
}