{
  "type": "Feature",
  "properties": {
    "addr:full":"Calle de Constitucion (de La), 108 Alcobendas Madrid 28100",
    "addr:housenumber":"108",
    "addr:postcode":"28100",
    "addr:street":"Calle De Constitucion De La",
    "iso:country":"ES",
    "sg:address":"Calle de Constitucion (de La), 108",
    "sg:city":"Alcobendas",
    "sg:orig_category":"Cajas De Ahorro",
    "sg:phone":"+34 916 23 94 17",
    "sg:postcode":"28100",
    "sg:province":"Madrid",
    "wof:name":"Caja De Ahorros Y Monte De Piedad De Zaragoza Aragon Y Rioja",
    "wof:placetype":"venue"
},
  "geometry": {"coordinates":[-3.6456542015,40.5475997925],"type":"Point"}
}