{
  "type": "Feature",
  "properties": {
    "iso:country":"ES",
    "sg:address":"Carrer de Masia, 51",
    "sg:city":"Can Sant Joan",
    "sg:orig_category":"Fabricaci\u00d3n De Su\u00c9ters Y Chalecos De Punto",
    "sg:phone":"+34 935 64 16 26",
    "sg:postcode":"08110",
    "sg:province":"Barcelona",
    "wof:name":"Aragones Mata Teresa",
    "wof:placetype":"venue"
},
  "geometry": {"coordinates":[2.1839511395,41.4714584351],"type":"Point"}
}