{
  "type": "Feature",
  "properties": {
    "addr:full":"Calle de Amargura, 56 Malaga M\u00e1laga 29012",
    "addr:housenumber":"56",
    "addr:postcode":"29012",
    "addr:street":"Calle De Amargura;Ma\u0301Laga",
    "iso:country":"ES",
    "sg:address":"Calle de Amargura, 56",
    "sg:city":"Malaga",
    "sg:orig_category":"Formaci\u00d3n Continuada (variada)",
    "sg:phone":"+34 952 25 97 45",
    "sg:postcode":"29012",
    "sg:province":"M\u00e1laga",
    "wof:name":"Leria Alix Comercializacion S.l.",
    "wof:placetype":"venue"
},
  "geometry": {"coordinates":[-4.4119076729,36.7292938232],"type":"Point"}
}