{
  "type": "Feature",
  "properties": {
    "iso:country":"ES",
    "sg:address":"Avda Cinco Villas, 23",
    "sg:city":"Tauste",
    "sg:orig_category":"Producci\u00d3n, Venta De Productos De Agricultura Biol\u00d3gica",
    "sg:phone":"+34 976 85 93 70",
    "sg:postcode":"50660",
    "sg:province":"Zaragoza",
    "wof:name":"Montolar Julian C.b.",
    "wof:placetype":"venue"
},
  "geometry": {"coordinates":[-1.324805975,41.940952301],"type":"Point"}
}