{
  "type": "Feature",
  "properties": {
    "addr:full":"Carrer de Cavallers, 15 Esparreguera Barcelona 08292",
    "addr:housenumber":"15",
    "addr:postcode":"08292",
    "addr:street":"Carrer De Cavallers",
    "iso:country":"ES",
    "sg:address":"Carrer de Cavallers, 15",
    "sg:city":"Esparreguera",
    "sg:orig_category":"Muebles Y Accesorios Para Cocinas Y Cuartos De Ba\u00d1o (al Por Menor)",
    "sg:phone":"+34 937 77 11 66",
    "sg:postcode":"08292",
    "sg:province":"Barcelona",
    "wof:name":"Reynes Garcia Josep Maria",
    "wof:placetype":"venue"
},
  "geometry": {"coordinates":[1.8127340078,41.5431747437],"type":"Point"}
}