{
  "type": "Feature",
  "properties": {
    "addr:full":"Calle de Carlos Arniches, 5 Elda Alicante 03600",
    "addr:housenumber":"5",
    "addr:postcode":"03600",
    "addr:street":"Calle De Carlos Arniches",
    "iso:country":"ES",
    "sg:address":"Calle de Carlos Arniches, 5",
    "sg:city":"Elda",
    "sg:orig_category":"Carnicer\u00cdas, Carnicer\u00cdas",
    "sg:phone":"+34 965 39 12 62",
    "sg:postcode":"03600",
    "sg:province":"Alicante",
    "wof:name":"Sanchez Maestre Marcelo",
    "wof:placetype":"venue"
},
  "geometry": {"coordinates":[-0.7930654883,38.4721603394],"type":"Point"}
}