{
  "type": "Feature",
  "properties": {
    "addr:full":"Avda Yecla (de), 82 Jumilla Murcia 30520",
    "addr:housenumber":"82",
    "addr:postcode":"30520",
    "addr:street":"Avda Yecla De",
    "iso:country":"ES",
    "sg:address":"Avda Yecla (de), 82",
    "sg:city":"Jumilla",
    "sg:orig_category":"Comercio De Muebles De Estilo Y Contempor\u00c1neos",
    "sg:phone":"+34 968 78 18 30",
    "sg:postcode":"30520",
    "sg:province":"Murcia",
    "wof:name":"Jimenez Garcia Gines",
    "wof:placetype":"venue"
},
  "geometry": {"coordinates":[-1.3215309381,38.4825325012],"type":"Point"}
}