{
  "type": "Feature",
  "properties": {
    "addr:full":"Calle de Gil Berges, 10 Jaca Huesca 22700",
    "addr:housenumber":"10",
    "addr:postcode":"22700",
    "addr:street":"Calle De Gil Berges",
    "iso:country":"ES",
    "sg:address":"Calle de Gil Berges, 10",
    "sg:city":"Jaca",
    "sg:orig_category":"Loter\u00cda Y T\u00d3mbola",
    "sg:phone":"+34 974 36 11 89",
    "sg:postcode":"22700",
    "sg:province":"Huesca",
    "wof:name":"Caballero Trapero Isidro",
    "wof:placetype":"venue"
},
  "geometry": {"coordinates":[-0.5479249954,42.5691986084],"type":"Point"}
}