{
  "type": "Feature",
  "properties": {
    "addr:full":"Pase Moreras, 13 Madrid Madrid 28021",
    "addr:housenumber":"13",
    "addr:postcode":"madrid;28021",
    "addr:street":"Moreras",
    "iso:country":"ES",
    "sg:address":"Pase Moreras, 13",
    "sg:city":"Madrid",
    "sg:orig_category":"Cajas Para Embalar",
    "sg:phone":"+34 917 10 96 34",
    "sg:postcode":"28021",
    "sg:province":"Madrid",
    "wof:name":"Cajamar",
    "wof:placetype":"venue"
},
  "geometry": {"coordinates":[-3.7103099823,40.3460044861],"type":"Point"}
}