{
  "type": "Feature",
  "properties": {
    "addr:full":"Calle de Estocolmo, 43 Madrid Madrid 28022",
    "addr:housenumber":"43",
    "addr:postcode":"madrid;28022",
    "addr:street":"Calle De Estocolmo",
    "iso:country":"ES",
    "sg:address":"Calle de Estocolmo, 43",
    "sg:city":"Madrid",
    "sg:orig_category":"Peluqueros: De Se\u00d1oras",
    "sg:phone":"+34 917 75 52 23",
    "sg:postcode":"28022",
    "sg:province":"Madrid",
    "wof:name":"Gomez Villoria Maria Isabel",
    "wof:placetype":"venue"
},
  "geometry": {"coordinates":[-3.600127697,40.4281997681],"type":"Point"}
}