{
  "type": "Feature",
  "properties": {
    "iso:country":"ES",
    "sg:address":"Avda Pedro Diez, 23",
    "sg:city":"Madrid",
    "sg:orig_category":"Empresas De Carpinter\u00cda Met\u00c1lica",
    "sg:phone":"+34 914 72 50 86",
    "sg:postcode":"28019",
    "sg:province":"Madrid",
    "wof:name":"Sanchez Valtierra Angel",
    "wof:placetype":"venue"
},
  "geometry": {"coordinates":[-3.7314960957,40.3914146423],"type":"Point"}
}