{
  "type": "Feature",
  "properties": {
    "iso:country":"ES",
    "sg:address":"Rua Do Mui\u00f1o, 8",
    "sg:city":"Ordes",
    "sg:orig_category":"Molduras, Junquillos, Listones Y Molduras Perforadas",
    "sg:phone":"+34 981 68 12 45",
    "sg:postcode":"15680",
    "sg:province":"A Coru\u00f1a",
    "wof:name":"Suarez Garabato Paloma",
    "wof:placetype":"venue"
},
  "geometry": {"coordinates":[-8.4100437164,43.0783004761],"type":"Point"}
}