{
  "type": "Feature",
  "properties": {
    "iso:country":"ES",
    "sg:address":"Calle de Guadalquivir, S/n",
    "sg:city":"Tarifa",
    "sg:orig_category":"Comercio De Piezas De Recambio Y De Accesorios De Veh\u00cdculos, Veh\u00cdculos Industriales",
    "sg:phone":"+34 956 68 51 45",
    "sg:postcode":"11380",
    "sg:province":"C\u00e1diz",
    "wof:name":"Campos Hidalgo Francisco",
    "wof:placetype":"venue"
},
  "geometry": {"coordinates":[-5.6087841988,36.0170059204],"type":"Point"}
}