{
  "type": "Feature",
  "properties": {
    "addr:full":"Carr Santa Barbara, 11 Cabaneta Islas Baleares 07141",
    "addr:housenumber":"11",
    "addr:postcode":"07141",
    "addr:street":"Carr Santa Barbara;Islas",
    "iso:country":"ES",
    "sg:address":"Carr Santa Barbara, 11",
    "sg:city":"Cabaneta",
    "sg:orig_category":"Ense\u00d1anza, Formaci\u00d3n Profesional: Aprendizaje",
    "sg:phone":"+34 971 79 76 24",
    "sg:postcode":"07141",
    "sg:province":"Islas Baleares",
    "sg:website":"www.ajuntmarratxi.com",
    "wof:name":"Ajuntament De Marratxi",
    "wof:placetype":"venue"
},
  "geometry": {"coordinates":[2.7502477169,39.6226234436],"type":"Point"}
}