{
  "type": "Feature",
  "properties": {
    "addr:full":"Calle de Comercio, 7 Mairena Aljarafe Sevilla 41927",
    "addr:housenumber":"7",
    "addr:postcode":"41927",
    "addr:street":"Calle De Comercio",
    "iso:country":"ES",
    "sg:address":"Calle de Comercio, 7",
    "sg:city":"Mairena Aljarafe",
    "sg:orig_category":"Vinos Y Licores (venta Al Por Menor)",
    "sg:phone":"+34 954 18 57 89",
    "sg:postcode":"41927",
    "sg:province":"Sevilla",
    "wof:name":"Compa\u00d1ia Becerra Olmedo S.a.",
    "wof:placetype":"venue"
},
  "geometry": {"coordinates":[-6.0611138344,37.3530807495],"type":"Point"}
}