{
  "type": "Feature",
  "properties": {
    "addr:full":"Avgd Castello, 58 Benicasim Castell\u00f3n 12560",
    "addr:housenumber":"58",
    "addr:postcode":"12560",
    "addr:street":"Castello",
    "iso:country":"ES",
    "sg:address":"Avgd Castello, 58",
    "sg:city":"Benicasim",
    "sg:orig_category":"Arreglo, Reparaci\u00d3n, Piezas Sueltas De Televisi\u00d3n, V\u00cddeo, Hi",
    "sg:phone":"+34 964 30 35 94",
    "sg:postcode":"12560",
    "sg:province":"Castell\u00f3n",
    "wof:name":"Fuentes Gil Juan Enrique",
    "wof:placetype":"venue"
},
  "geometry": {"coordinates":[0.0457400009,40.0510292053],"type":"Point"}
}