{
  "type": "Feature",
  "properties": {
    "addr:full":"Calle de Nu\u00d1ez De Balboa, 13 Madrid Madrid 28001",
    "addr:housenumber":"13",
    "addr:postcode":"madrid;28001",
    "addr:street":"Calle De Nun\u0303Ez De Balboa",
    "iso:country":"ES",
    "sg:address":"Calle de Nu\u00d1ez De Balboa, 13",
    "sg:city":"Madrid",
    "sg:orig_category":"Artes Gr\u00c1ficas, Artes Pl\u00c1sticas: Material Y Suministros (al Por Menor)",
    "sg:phone":"+34 914 31 67 30",
    "sg:postcode":"28001",
    "sg:province":"Madrid",
    "wof:name":"Inversiones Nuevo Horizonte S.l.",
    "wof:placetype":"venue"
},
  "geometry": {"coordinates":[-3.6831409931,40.4229240417],"type":"Point"}
}