{
  "type": "Feature",
  "properties": {
    "addr:full":"Plaz Puerto, 11 Tarazona Zaragoza 50500",
    "addr:housenumber":"11",
    "addr:postcode":"50500",
    "addr:street":"Plaz Puerto",
    "iso:country":"ES",
    "sg:address":"Plaz Puerto, 11",
    "sg:city":"Tarazona",
    "sg:orig_category":"Carnicer\u00cdas, Carnicer\u00cdas",
    "sg:phone":"+34 976 64 13 80",
    "sg:postcode":"50500",
    "sg:province":"Zaragoza",
    "wof:name":"Izquierdo Ejea Adolfo",
    "wof:placetype":"venue"
},
  "geometry": {"coordinates":[-1.7313120365,41.904296875],"type":"Point"}
}