{
  "type": "Feature",
  "properties": {
    "iso:country":"ES",
    "sg:address":"Mercado Central Abastos, S/n",
    "sg:city":"Jerez",
    "sg:orig_category":"Poller\u00cda Y Caza (al Por Menor)",
    "sg:phone":"+34 956 34 78 13",
    "sg:postcode":"11403",
    "sg:province":"C\u00e1diz",
    "wof:name":"Sanchez Ramirez Magdalena",
    "wof:placetype":"venue"
},
  "geometry": {"coordinates":[-6.1406798363,36.6853103638],"type":"Point"}
}