{
  "type": "Feature",
  "properties": {
    "iso:country":"ES",
    "sg:address":"Via Cabrera, 16",
    "sg:city":"Santa Pon\u00c7a",
    "sg:orig_category":"M\u00c9dicos: Ginecolog\u00cda Y Obstetricia",
    "sg:phone":"+34 971 69 16 10",
    "sg:postcode":"07180",
    "sg:province":"Islas Baleares",
    "wof:name":"Policlinica Alemana S.a.",
    "wof:placetype":"venue"
},
  "geometry": {"coordinates":[2.4837698936,39.5131607056],"type":"Point"}
}