{
  "type": "Feature",
  "properties": {
    "iso:country":"ES",
    "sg:address":"Carr Major, 21",
    "sg:city":"Sort",
    "sg:orig_category":"Carnicer\u00cdas, Carnicer\u00cdas",
    "sg:phone":"+34 973 62 07 78",
    "sg:postcode":"25560",
    "sg:province":"Lleida",
    "wof:name":"Pujol Masa Alfonso",
    "wof:placetype":"venue"
},
  "geometry": {"coordinates":[1.1304709911,42.4118995667],"type":"Point"}
}