{
  "type": "Feature",
  "properties": {
    "iso:country":"ES",
    "sg:address":"Carrer de Doctor Gimbernat, 56",
    "sg:city":"Sabadell",
    "sg:orig_category":"Maquinaria Para Industrias Diversas",
    "sg:phone":"+34 937 11 59 69",
    "sg:postcode":"08203",
    "sg:province":"Barcelona",
    "wof:name":"Balada Garcia Luis Miguel",
    "wof:placetype":"venue"
},
  "geometry": {"coordinates":[2.117534399,41.532951355],"type":"Point"}
}