{
  "type": "Feature",
  "properties": {
    "addr:full":"Avda Andalucia, 4 Ecija Sevilla 41400",
    "addr:housenumber":"4",
    "addr:postcode":"41400",
    "addr:street":"Avda Andalucia",
    "iso:country":"ES",
    "sg:address":"Avda Andalucia, 4",
    "sg:city":"Ecija",
    "sg:orig_category":"Asesor\u00cda Sobre Comunicaci\u00d3n De Empresas",
    "sg:phone":"+34 955 90 03 00",
    "sg:postcode":"41400",
    "sg:province":"Sevilla",
    "wof:name":"Gestion Empresarial De Ecija S.l.",
    "wof:placetype":"venue"
},
  "geometry": {"coordinates":[-5.0771188736,37.5378608704],"type":"Point"}
}