{
  "type": "Feature",
  "properties": {
    "addr:full":"Avda Santiago (de), S/n Viso Marques Ciudad Real 13770",
    "addr:postcode":"marques;13770",
    "addr:street":"Avda Santiago De S / N",
    "iso:country":"ES",
    "sg:address":"Avda Santiago (de), S/n",
    "sg:city":"Viso Marques",
    "sg:orig_category":"Confecci\u00d3n De Trajes Para Se\u00d1oras",
    "sg:phone":"+34 926 33 65 97",
    "sg:postcode":"13770",
    "sg:province":"Ciudad Real",
    "wof:name":"Avitex Sll",
    "wof:placetype":"venue"
},
  "geometry": {"coordinates":[-3.5667779446,38.5230789185],"type":"Point"}
}