{
  "type": "Feature",
  "properties": {
    "iso:country":"ES",
    "sg:address":"Calle de Cincel, 15",
    "sg:city":"San Vicente Del Raspeig-sant Vicent Del Raspeig",
    "sg:orig_category":"Zapatos: Material, Suministros, Accesorios (fabricaci\u00d3n, Al Por Mayor)",
    "sg:phone":"+34 965 67 41 76",
    "sg:postcode":"03690",
    "sg:province":"Alicante",
    "wof:name":"For Shoes S.l.",
    "wof:placetype":"venue"
},
  "geometry": {"coordinates":[-0.5360983014,38.4037399292],"type":"Point"}
}