{
  "type": "Feature",
  "properties": {
    "addr:full":"Avda Islantilla, 5 Antilla Huelva 21449",
    "addr:housenumber":"5",
    "addr:postcode":"21449",
    "addr:street":"Avda Islantilla",
    "iso:country":"ES",
    "sg:address":"Avda Islantilla, 5",
    "sg:city":"Antilla",
    "sg:orig_category":"Inmobiliaria (agencias)",
    "sg:phone":"+34 959 48 61 48",
    "sg:postcode":"21449",
    "sg:province":"Huelva",
    "sg:website":"www.inmobiliariatenorio.com",
    "wof:name":"Inmobiliaria Tenorio Martin S.l.",
    "wof:placetype":"venue"
},
  "geometry": {"coordinates":[-7.2178740501,37.2062454224],"type":"Point"}
}