{
  "type": "Feature",
  "properties": {
    "iso:country":"ES",
    "sg:address":"Calle de San Martin, 5",
    "sg:city":"Donostia-san Sebastian",
    "sg:orig_category":"Muebles, Minoristas",
    "sg:phone":"+34 943 42 17 14",
    "sg:postcode":"20005",
    "sg:province":"Guip\u00f9zcoa",
    "wof:name":"Espiral S.l.",
    "wof:placetype":"venue"
},
  "geometry": {"coordinates":[-1.9800150394,43.3180007935],"type":"Point"}
}