{
  "type": "Feature",
  "properties": {
    "addr:full":"Calle de Leon Felipe, 19 Zaragoza Zaragoza 50015",
    "addr:housenumber":"19",
    "addr:postcode":"50015",
    "addr:street":"Calle De Leon Felipe",
    "iso:country":"ES",
    "sg:address":"Calle de Leon Felipe, 19",
    "sg:city":"Zaragoza",
    "sg:orig_category":"Peluquer\u00cdas, Peluquer\u00cda Mixta",
    "sg:phone":"+34 976 52 68 98",
    "sg:postcode":"50015",
    "sg:province":"Zaragoza",
    "wof:name":"Cano Laplaza Jose Carlos",
    "wof:placetype":"venue"
},
  "geometry": {"coordinates":[-0.8844439983,41.6678581238],"type":"Point"}
}