{
  "type": "Feature",
  "properties": {
    "iso:country":"ES",
    "sg:address":"Carrer de Sepulveda, 171",
    "sg:city":"Barcelona",
    "sg:orig_category":"Reposter\u00cdas",
    "sg:phone":"+34 934 54 69 73",
    "sg:postcode":"08011",
    "sg:province":"Barcelona",
    "wof:name":"Forn Sepulveda S.l.",
    "wof:placetype":"venue"
},
  "geometry": {"coordinates":[2.1623990536,41.3833427429],"type":"Point"}
}