{
  "type": "Feature",
  "properties": {
    "addr:full":"Plaz Constitucion (de La), 4 Adamuz C\u00f3rdoba 14430",
    "addr:postcode":"14430",
    "iso:country":"ES",
    "sg:address":"Plaz Constitucion (de La), 4",
    "sg:city":"Adamuz",
    "sg:orig_category":"Molduras, Junquillos, Listones Y Molduras Perforadas",
    "sg:phone":"+34 957 16 60 12",
    "sg:postcode":"14430",
    "sg:province":"C\u00f3rdoba",
    "wof:name":"Gavilan Diaz Manuel",
    "wof:placetype":"venue"
},
  "geometry": {"coordinates":[-4.5247850418,38.0279655457],"type":"Point"}
}