{
  "type": "Feature",
  "properties": {
    "iso:country":"ES",
    "sg:address":"Carr Bellprat, 6",
    "sg:city":"Igualada",
    "sg:classifiers":[
        {
            "category":"Taxi",
            "type":"Transportation"
        }
    ],
    "sg:phone":"+34 938 03 68 99",
    "sg:postcode":"08700",
    "sg:province":"Barcelona",
    "wof:name":"Pe\u00f1a Pe\u00f1a Lorenzo",
    "wof:placetype":"venue"
},
  "geometry": {"coordinates":[1.6170270443,41.587387085],"type":"Point"}
}