{
  "type": "Feature",
  "properties": {
    "addr:full":"Carr Sagunto, 2 Moncada Valencia 46113",
    "addr:housenumber":"2",
    "addr:postcode":"46113",
    "addr:street":"Carr Sagunto",
    "iso:country":"ES",
    "sg:address":"Carr Sagunto, 2",
    "sg:city":"Moncada",
    "sg:orig_category":"Ropa Para Se\u00d1oras (al Por Menor)",
    "sg:phone":"+34 961 30 12 47",
    "sg:postcode":"46113",
    "sg:province":"Valencia",
    "wof:name":"Papallona C.b.",
    "wof:placetype":"venue"
},
  "geometry": {"coordinates":[-0.3914209902,39.5466537476],"type":"Point"}
}