{
  "type": "Feature",
  "properties": {
    "iso:country":"ES",
    "sg:address":"Cno Ti\u00f1osa(s J De La Vega), 58",
    "sg:city":"Beniajan",
    "sg:orig_category":"Mec\u00c1nico Del Autom\u00d3vil",
    "sg:phone":"+34 968 82 03 31",
    "sg:postcode":"30570",
    "sg:province":"Murcia",
    "wof:name":"Romero Alarcon Tomas",
    "wof:placetype":"venue"
},
  "geometry": {"coordinates":[-1.0805039406,37.9669761658],"type":"Point"}
}