{
  "type": "Feature",
  "properties": {
    "addr:full":"Calle de Corzo, 109 Cabanillas Campo Guadalajara 19171",
    "addr:housenumber":"109",
    "addr:postcode":"19171",
    "addr:street":"Calle De Corzo",
    "iso:country":"ES",
    "sg:address":"Calle de Corzo, 109",
    "sg:city":"Cabanillas Campo",
    "sg:orig_category":"Administraci\u00d3n En Agricultura",
    "sg:phone":"+34 949 32 41 11",
    "sg:postcode":"19171",
    "sg:province":"Guadalajara",
    "wof:name":"Eusebio Centenera E Hijos S.l.",
    "wof:placetype":"venue"
},
  "geometry": {"coordinates":[-3.2268996239,40.635723114],"type":"Point"}
}