{
  "type": "Feature",
  "properties": {
    "iso:country":"ES",
    "sg:address":"Plaz Castilla, S/n",
    "sg:city":"San Anton",
    "sg:orig_category":"Edici\u00d3n De Diarios, Revistas, Boletines",
    "sg:phone":"+34 968 28 65 68",
    "sg:postcode":"30009",
    "sg:province":"Murcia",
    "wof:name":"La Opinion De Murcia S.a.",
    "wof:placetype":"venue"
},
  "geometry": {"coordinates":[-1.1528439522,37.9883460999],"type":"Point"}
}