{
  "type": "Feature",
  "properties": {
    "iso:country":"ES",
    "sg:address":"Avda Arroyomolinos (de), 3",
    "sg:city":"Moraleja Enmedio",
    "sg:orig_category":"Centros De Salud",
    "sg:phone":"+34 916 09 40 12",
    "sg:postcode":"28950",
    "sg:province":"Madrid",
    "wof:name":"Residencia Nuestra Se\u00f1ora Del Sagrario S.l.",
    "wof:placetype":"venue"
},
  "geometry": {"coordinates":[-3.8640730381,40.2599983215],"type":"Point"}
}