{
  "type": "Feature",
  "properties": {
    "iso:country":"ES",
    "sg:address":"Carrer de Marques De Campo, 27",
    "sg:city":"Denia",
    "sg:orig_category":"Ingenier\u00cda, Centros De Estudios (diversos)",
    "sg:phone":"+34 966 42 74 76",
    "sg:postcode":"03700",
    "sg:province":"Alicante",
    "wof:name":"Graydon & Associates Costa Blanca, S.l.",
    "wof:placetype":"venue"
},
  "geometry": {"coordinates":[0.108837001,38.8406105042],"type":"Point"}
}