{
  "type": "Feature",
  "properties": {
    "addr:full":"Plaz Cristo Del Rescate, 1 San Juan Murcia 30003",
    "addr:postcode":"30003",
    "iso:country":"ES",
    "sg:address":"Plaz Cristo Del Rescate, 1",
    "sg:city":"San Juan",
    "sg:orig_category":"Restaurantes",
    "sg:phone":"+34 968 22 00 96",
    "sg:postcode":"30003",
    "sg:province":"Murcia",
    "wof:name":"Comercio Y Bebercio S.l.",
    "wof:placetype":"venue"
},
  "geometry": {"coordinates":[-1.1255090237,37.9836807251],"type":"Point"}
}