{
  "type": "Feature",
  "properties": {
    "iso:country":"ES",
    "sg:address":"C/ Born, 24",
    "sg:city":"Inca",
    "sg:orig_category":"Molduras, Junquillos, Listones Y Molduras Perforadas",
    "sg:phone":"+34 971 88 03 54",
    "sg:postcode":"07300",
    "sg:province":"Islas Baleares",
    "wof:name":"Es Born S.l.",
    "wof:placetype":"venue"
},
  "geometry": {"coordinates":[2.9111959934,39.7205429077],"type":"Point"}
}