{
  "type": "Feature",
  "properties": {
    "addr:full":"Calle de Santiago, 17 Valladolid Valladolid 47001",
    "addr:housenumber":"17",
    "addr:postcode":"47001",
    "addr:street":"Calle De Santiago",
    "iso:country":"ES",
    "sg:address":"Calle de Santiago, 17",
    "sg:city":"Valladolid",
    "sg:orig_category":"Bancos",
    "sg:phone":"+34 983 36 32 00",
    "sg:postcode":"47001",
    "sg:province":"Valladolid",
    "wof:name":"Banco De Castilla",
    "wof:placetype":"venue"
},
  "geometry": {"coordinates":[-4.7287240028,41.6498336792],"type":"Point"}
}