{
  "type": "Feature",
  "properties": {
    "iso:country":"ES",
    "sg:address":"Plaz Doctor Lozano, 4",
    "sg:city":"Madrid",
    "sg:orig_category":"Tapicer\u00cdas",
    "sg:phone":"+34 915 52 20 25",
    "sg:postcode":"28038",
    "sg:province":"Madrid",
    "wof:name":"Tapicerias Gandhi S.l.",
    "wof:placetype":"venue"
},
  "geometry": {"coordinates":[-3.6625230312,40.4033050537],"type":"Point"}
}