{
  "type": "Feature",
  "properties": {
    "addr:full":"Carrer de Aritjols, 83 Barcelona Barcelona 08016",
    "addr:housenumber":"83",
    "addr:postcode":"08016",
    "addr:street":"Carrer De Aritjols",
    "iso:country":"ES",
    "sg:address":"Carrer de Aritjols, 83",
    "sg:city":"Barcelona",
    "sg:orig_category":"Mec\u00c1nico Del Autom\u00d3vil",
    "sg:phone":"+34 932 76 42 81",
    "sg:postcode":"08016",
    "sg:province":"Barcelona",
    "wof:name":"Carqueijeda Garcia Manuel",
    "wof:placetype":"venue"
},
  "geometry": {"coordinates":[2.1834828854,41.444152832],"type":"Point"}
}