{
  "type": "Feature",
  "properties": {
    "iso:country":"ES",
    "sg:address":"Carrer de Camelies, 1",
    "sg:city":"Can Cuias",
    "sg:orig_category":"Abogados",
    "sg:phone":"+34 935 75 86 37",
    "sg:postcode":"08110",
    "sg:province":"Barcelona",
    "wof:name":"Gutierrez Palomares Sonia",
    "wof:placetype":"venue"
},
  "geometry": {"coordinates":[2.1698989868,41.4641456604],"type":"Point"}
}