{
  "type": "Feature",
  "properties": {
    "iso:country":"ES",
    "sg:address":"Carrer de Primavera, 105",
    "sg:city":"Hospitalet Llobregat",
    "sg:orig_category":"Piedras Artificiales",
    "sg:phone":"+34 934 37 32 46",
    "sg:postcode":"08905",
    "sg:province":"Barcelona",
    "wof:name":"Serret Pitarch Juan Pedro",
    "wof:placetype":"venue"
},
  "geometry": {"coordinates":[2.1068329811,41.3715248108],"type":"Point"}
}