{
  "type": "Feature",
  "properties": {
    "iso:country":"ES",
    "sg:address":"Calle de Mayor De Santa Marina, 4",
    "sg:city":"Cordoba",
    "sg:orig_category":"Comerciantes Al Por Mayor De Vinos, Licores Y Alcoholes",
    "sg:phone":"+34 957 48 09 34",
    "sg:postcode":"14001",
    "sg:province":"C\u00f3rdoba",
    "wof:name":"Calvillo Soriano Maria Del Carmen",
    "wof:placetype":"venue"
},
  "geometry": {"coordinates":[-4.7750930786,37.8903007507],"type":"Point"}
}