{
  "type": "Feature",
  "properties": {
    "addr:full":"Calle de Bancos, 18 Alanis Sevilla 41380",
    "addr:housenumber":"18",
    "addr:postcode":"41380",
    "addr:street":"Calle De Bancos",
    "iso:country":"ES",
    "sg:address":"Calle de Bancos, 18",
    "sg:city":"Alanis",
    "sg:orig_category":"Supermercados Y Hipermercados",
    "sg:phone":"+34 954 88 52 32",
    "sg:postcode":"41380",
    "sg:province":"Sevilla",
    "wof:name":"Romero Lora Ramiro",
    "wof:placetype":"venue"
},
  "geometry": {"coordinates":[-5.713745594,38.0377616882],"type":"Point"}
}