{
  "type": "Feature",
  "properties": {
    "addr:full":"Avda Palencia, 6 Valladolid Valladolid 47011",
    "addr:housenumber":"6",
    "addr:postcode":"47011",
    "addr:street":"Avda Palencia",
    "iso:country":"ES",
    "sg:address":"Avda Palencia, 6",
    "sg:city":"Valladolid",
    "sg:orig_category":"Cajas De Ahorro",
    "sg:phone":"+34 983 26 37 61",
    "sg:postcode":"47011",
    "sg:province":"Valladolid",
    "sg:website":"www.cajacirculo.es",
    "wof:name":"Caja De Ahorros Del Circulo Catolico Obrero De Burgos",
    "wof:placetype":"venue"
},
  "geometry": {"coordinates":[-4.7188768387,41.6594161987],"type":"Point"}
}