{
  "type": "Feature",
  "properties": {
    "addr:full":"G.v. Corts Catalanes, 736 Barcelona Barcelona 08013",
    "addr:housenumber":"736",
    "addr:postcode":"08013",
    "addr:street":"Catalanes",
    "iso:country":"ES",
    "sg:address":"G.v. Corts Catalanes, 736",
    "sg:city":"Barcelona",
    "sg:orig_category":"Abogados",
    "sg:phone":"+34 932 31 67 56",
    "sg:postcode":"08013",
    "sg:province":"Barcelona",
    "wof:name":"Tubau Puigoriol Juan",
    "wof:placetype":"venue"
},
  "geometry": {"coordinates":[2.1788740158,41.3969497681],"type":"Point"}
}