{
  "type": "Feature",
  "properties": {
    "addr:full":"Calle de Amistad, 12 Arenas -areeta Vizcaya 48930",
    "addr:housenumber":"12;areeta",
    "addr:postcode":"48930",
    "addr:street":"Calle De Amistad",
    "iso:country":"ES",
    "sg:address":"Calle de Amistad, 12",
    "sg:city":"Arenas -areeta",
    "sg:orig_category":"Organismos Y Centros De Vacaciones Y Esparcimiento Para Ni\u00d1os Y Adolescentes",
    "sg:phone":"+34 944 63 85 15",
    "sg:postcode":"48930",
    "sg:province":"Vizcaya",
    "wof:name":"Piccola S.l.",
    "wof:placetype":"venue"
},
  "geometry": {"coordinates":[-2.6983869076,43.2204284668],"type":"Point"}
}