{
  "type": "Feature",
  "properties": {
    "iso:country":"ES",
    "sg:address":"Calle de Carlos Arniches, 8",
    "sg:city":"San Lorenzo De El Escorial",
    "sg:orig_category":"Abogados",
    "sg:phone":"+34 918 90 14 79",
    "sg:postcode":"28200",
    "sg:province":"Madrid",
    "wof:name":"Echeverria Echaniz Jose Ignacio",
    "wof:placetype":"venue"
},
  "geometry": {"coordinates":[-4.1544718742,40.5920295715],"type":"Point"}
}