{
  "type": "Feature",
  "properties": {
    "iso:country":"ES",
    "sg:address":"Avda Andalucia (de), 72",
    "sg:city":"Estepa",
    "sg:orig_category":"Confiter\u00cdas, Chocolater\u00cdas (al Por Menor)",
    "sg:phone":"+34 955 91 21 20",
    "sg:postcode":"41560",
    "sg:province":"Sevilla",
    "wof:name":"Dulcestepa Sociedad Anonima",
    "wof:placetype":"venue"
},
  "geometry": {"coordinates":[-4.87271595,37.2969093323],"type":"Point"}
}