{
  "type": "Feature",
  "properties": {
    "addr:full":"Calle de Aldapa, 21 Ondiz Vizcaya 48940",
    "addr:housenumber":"21",
    "addr:postcode":"48940",
    "addr:street":"Calle De Aldapa",
    "iso:country":"ES",
    "sg:address":"Calle de Aldapa, 21",
    "sg:city":"Ondiz",
    "sg:orig_category":"Inform\u00c1tica (estudios, Servicios, Asesor\u00cda, Formaci\u00d3n)",
    "sg:phone":"+34 944 80 14 70",
    "sg:postcode":"48940",
    "sg:province":"Vizcaya",
    "wof:name":"Bitbat S.l.",
    "wof:placetype":"venue"
},
  "geometry": {"coordinates":[-2.6983869076,43.2204284668],"type":"Point"}
}