{
  "type": "Feature",
  "properties": {
    "addr:full":"Calle de Antonio Abellan Abellan, 6 Paz Murcia 30006",
    "addr:housenumber":"6",
    "addr:postcode":"30006",
    "addr:street":"Calle De Antonio Abellan Abellan",
    "iso:country":"ES",
    "sg:address":"Calle de Antonio Abellan Abellan, 6",
    "sg:city":"Paz",
    "sg:orig_category":"Mec\u00c1nico Del Autom\u00d3vil",
    "sg:phone":"+34 968 23 87 49",
    "sg:postcode":"30006",
    "sg:province":"Murcia",
    "wof:name":"Bernal Soto Francisco",
    "wof:placetype":"venue"
},
  "geometry": {"coordinates":[-1.1008939743,37.9940185547],"type":"Point"}
}