{
  "type": "Feature",
  "properties": {
    "iso:country":"ES",
    "sg:address":"Cro Sant Pere, 8",
    "sg:city":"S. Feliu Guixols",
    "sg:orig_category":"Laboratorios Y Cl\u00cdnicas Veterinarias",
    "sg:phone":"+34 972 82 20 25",
    "sg:postcode":"17220",
    "sg:province":"Girona",
    "wof:name":"Plandiura Celma Maria Luisa",
    "wof:placetype":"venue"
},
  "geometry": {"coordinates":[3.029861927,41.7808685303],"type":"Point"}
}