{
  "type": "Feature",
  "properties": {
    "addr:full":"Pol. Ind. Erletxes, S/n Gumuzio Vizcaya 48960",
    "addr:housenumber":"s",
    "addr:postcode":"48960",
    "addr:street":"/ N",
    "iso:country":"ES",
    "sg:address":"Pol. Ind. Erletxes, S/n",
    "sg:city":"Gumuzio",
    "sg:orig_category":"Fabricaci\u00d3n De Productos L\u00c1cteos Y Derivados",
    "sg:phone":"+34 944 56 54 62",
    "sg:postcode":"48960",
    "sg:province":"Vizcaya",
    "wof:name":"Garmesan S.a.",
    "wof:placetype":"venue"
},
  "geometry": {"coordinates":[-2.8470389843,43.2298049927],"type":"Point"}
}