{
  "type": "Feature",
  "properties": {
    "iso:country":"ES",
    "sg:address":"Calle de Tiziano, 52",
    "sg:city":"Tafira Alta",
    "sg:orig_category":"Ense\u00d1ante, Direcci\u00d3n",
    "sg:phone":"+34 928 35 05 80",
    "sg:postcode":"35017",
    "sg:province":"Las Palmas",
    "wof:name":"Calleja Garcia Elisa",
    "wof:placetype":"venue"
},
  "geometry": {"coordinates":[-15.4688825607,28.0524635315],"type":"Point"}
}