{
  "type": "Feature",
  "properties": {
    "iso:country":"ES",
    "sg:address":"Avda Estacion (de La), Km. 0002,0",
    "sg:city":"Abaran",
    "sg:orig_category":"Venta, Montaje De Neum\u00c1ticos",
    "sg:phone":"+34 968 77 45 59",
    "sg:postcode":"30550",
    "sg:province":"Murcia",
    "wof:name":"Neumaticos Las Colinas S.l.",
    "wof:placetype":"venue"
},
  "geometry": {"coordinates":[-1.3870439529,38.2075386047],"type":"Point"}
}