{
  "type": "Feature",
  "properties": {
    "addr:full":"Calle de Zaragoza, 8 Almeria Almer\u00eda 04001",
    "addr:housenumber":"8",
    "addr:postcode":"04001",
    "addr:street":"Calle De Zaragoza",
    "iso:country":"ES",
    "sg:address":"Calle de Zaragoza, 8",
    "sg:city":"Almeria",
    "sg:orig_category":"M\u00c9dicos: Cardiolog\u00cda Y Afecciones Cardiovasculares",
    "sg:phone":"+34 950 23 79 38",
    "sg:postcode":"04001",
    "sg:province":"Almer\u00eda",
    "wof:name":"Palanca Vidal Carlos",
    "wof:placetype":"venue"
},
  "geometry": {"coordinates":[-2.4616758823,36.8392601013],"type":"Point"}
}