{
  "type": "Feature",
  "properties": {
    "iso:country":"ES",
    "sg:address":"Ctra. Toledo, S/n",
    "sg:city":"Galvez",
    "sg:orig_category":"Cerrajer\u00cda, Ferrallista",
    "sg:phone":"+34 925 40 07 16",
    "sg:postcode":"45164",
    "sg:province":"Toledo",
    "wof:name":"Cerrajeria Ortiz Cb.",
    "wof:placetype":"venue"
},
  "geometry": {"coordinates":[-4.2757091522,39.7027244568],"type":"Point"}
}