{
  "type": "Feature",
  "properties": {
    "addr:full":"Carrer de Parlament, 31 Amposta Tarragona 43870",
    "addr:housenumber":"31",
    "addr:postcode":"43870",
    "addr:street":"Carrer De Parlament",
    "iso:country":"ES",
    "sg:address":"Carrer de Parlament, 31",
    "sg:city":"Amposta",
    "sg:orig_category":"Material Y Herramientas Agr\u00cdcolas",
    "sg:phone":"+34 977 70 18 98",
    "sg:postcode":"43870",
    "sg:province":"Tarragona",
    "wof:name":"Huguet Mauri Manuel",
    "wof:placetype":"venue"
},
  "geometry": {"coordinates":[0.5786560178,40.7114753723],"type":"Point"}
}