{
  "type": "Feature",
  "properties": {
    "iso:country":"ES",
    "sg:address":"Pont Espados, S/n",
    "sg:city":"Almenar",
    "sg:orig_category":"Producci\u00d3n, Comercio De Cereales",
    "sg:phone":"+34 973 77 05 20",
    "sg:postcode":"25126",
    "sg:province":"Lleida",
    "wof:name":"Cereales Torremorell S.a.",
    "wof:placetype":"venue"
},
  "geometry": {"coordinates":[0.5774130225,41.8009109497],"type":"Point"}
}