{
  "type": "Feature",
  "properties": {
    "addr:full":"Proyecto Uno, 20 Mahora Albacete 02240",
    "addr:housenumber":"20",
    "addr:postcode":"02240",
    "addr:street":"Mahora",
    "iso:country":"ES",
    "sg:address":"Proyecto Uno, 20",
    "sg:city":"Mahora",
    "sg:orig_category":"Negocio De Materiales De Construcci\u00d3n",
    "sg:phone":"+34 967 49 42 25",
    "sg:postcode":"02240",
    "sg:province":"Albacete",
    "wof:name":"Tebar Gomez Felix",
    "wof:placetype":"venue"
},
  "geometry": {"coordinates":[-1.7249890566,39.2094345093],"type":"Point"}
}