{
  "type": "Feature",
  "properties": {
    "addr:full":"Pza. Inmaculada, 2 Establiments Islas Baleares 07010",
    "addr:housenumber":"2",
    "addr:postcode":"07010",
    "addr:street":"Inmaculada;Islas",
    "iso:country":"ES",
    "sg:address":"Pza. Inmaculada, 2",
    "sg:city":"Establiments",
    "sg:orig_category":"Iglesia Cat\u00d3lica",
    "sg:phone":"+34 971 76 81 77",
    "sg:postcode":"07010",
    "sg:province":"Islas Baleares",
    "wof:name":"Obispado De Mallorca",
    "wof:placetype":"venue"
},
  "geometry": {"coordinates":[2.6215190887,39.6229019165],"type":"Point"}
}