{
  "type": "Feature",
  "properties": {
    "iso:country":"ES",
    "sg:address":"Cmno Real, 2",
    "sg:city":"Ugena",
    "sg:orig_category":"Tapicer\u00cdas",
    "sg:phone":"+34 925 54 48 08",
    "sg:postcode":"45217",
    "sg:province":"Toledo",
    "wof:name":"Tapizados La Sagra,s.l.",
    "wof:placetype":"venue"
},
  "geometry": {"coordinates":[-3.877669096,40.1581344604],"type":"Point"}
}