{
  "type": "Feature",
  "properties": {
    "addr:full":"Carr Santissim, 3 Ciutadella Menorca Islas Baleares 07760",
    "addr:housenumber":"3",
    "addr:postcode":"07760",
    "addr:street":"Carr Santissim",
    "iso:country":"ES",
    "sg:address":"Carr Santissim, 3",
    "sg:city":"Ciutadella Menorca",
    "sg:orig_category":"Marroquiner\u00cda (confecci\u00d3n)",
    "sg:phone":"+34 971 38 47 07",
    "sg:postcode":"07760",
    "sg:province":"Islas Baleares",
    "wof:name":"Reyero Alonso Maria Amparo",
    "wof:placetype":"venue"
},
  "geometry": {"coordinates":[3.8416149616,40.0027542114],"type":"Point"}
}