{
  "type": "Feature",
  "properties": {
    "iso:country":"ES",
    "sg:address":"Calle de Sabino Arana Kalea, 8",
    "sg:city":"Berango",
    "sg:orig_category":"Molduras, Junquillos, Listones Y Molduras Perforadas",
    "sg:phone":"+34 946 68 05 64",
    "sg:postcode":"48640",
    "sg:province":"Vizcaya",
    "wof:name":"Miguel Grijalvo Ana Maria De",
    "wof:placetype":"venue"
},
  "geometry": {"coordinates":[-3.0000801086,43.3651351929],"type":"Point"}
}