{
  "type": "Feature",
  "properties": {
    "iso:country":"ES",
    "sg:address":"Calle de Palencia, 5",
    "sg:city":"Granada",
    "sg:orig_category":"Alimentaci\u00d3n General (al Por Menor)",
    "sg:phone":"+34 958 81 10 51",
    "sg:postcode":"18007",
    "sg:province":"Granada",
    "wof:name":"Molina Esturillo Juan",
    "wof:placetype":"venue"
},
  "geometry": {"coordinates":[-3.5988507271,37.1602058411],"type":"Point"}
}