{
  "type": "Feature",
  "properties": {
    "iso:country":"ES",
    "sg:address":"Calle de Luisa Fernanda, 12",
    "sg:city":"Madrid",
    "sg:orig_category":"Ense\u00d1anza Variada",
    "sg:phone":"+34 915 47 47 67",
    "sg:postcode":"28008",
    "sg:province":"Madrid",
    "wof:name":"Instituto De Estudios Superiores De Gobiernos De Personas S.l.",
    "wof:placetype":"venue"
},
  "geometry": {"coordinates":[-3.7152869701,40.4257278442],"type":"Point"}
}