{
  "type": "Feature",
  "properties": {
    "addr:full":"Rua Santo Domingo, 23 Ourense Ourense 32003",
    "addr:housenumber":"23",
    "addr:postcode":"32003",
    "addr:street":"Rua Santo Domingo",
    "iso:country":"ES",
    "sg:address":"Rua Santo Domingo, 23",
    "sg:city":"Ourense",
    "sg:orig_category":"Iglesia Cat\u00d3lica",
    "sg:phone":"+34 988 23 13 02",
    "sg:postcode":"32003",
    "sg:province":"Ourense",
    "wof:name":"Obispado De Orense",
    "wof:placetype":"venue"
},
  "geometry": {"coordinates":[-7.8631839752,42.3388252258],"type":"Point"}
}