{
  "type": "Feature",
  "properties": {
    "addr:full":"Calle de Teide, 5 Molinos Madrid 28460",
    "addr:housenumber":"5",
    "addr:postcode":"28460",
    "addr:street":"Calle De Teide",
    "iso:country":"ES",
    "sg:address":"Calle de Teide, 5",
    "sg:city":"Molinos",
    "sg:orig_category":"Flores Y Plantas Naturales (al Por Mayor)",
    "sg:phone":"+34 918 55 06 55",
    "sg:postcode":"28460",
    "sg:province":"Madrid",
    "wof:name":"Angel Ballesteros Plantas De Galicia S.l.u.",
    "wof:placetype":"venue"
},
  "geometry": {"coordinates":[-4.0729737282,40.7052993774],"type":"Point"}
}