{
  "type": "Feature",
  "properties": {
    "iso:country":"ES",
    "sg:address":"Bda Gloria, 14",
    "sg:city":"Barcelona",
    "sg:orig_category":"Agencias Y Agentes Comerciales, Representantes",
    "sg:phone":"+34 932 84 59 38",
    "sg:postcode":"08023",
    "sg:province":"Barcelona",
    "wof:name":"Mac Plat 99 S.l.",
    "wof:placetype":"venue"
},
  "geometry": {"coordinates":[2.1486709118,41.4107894897],"type":"Point"}
}