{
  "type": "Feature",
  "properties": {
    "iso:country":"ES",
    "sg:address":"Paulino Caballero, 52",
    "sg:city":"Iru\u00f1a",
    "sg:orig_category":"Ense\u00d1anza Variada",
    "sg:phone":"+34 948 29 01 61",
    "sg:postcode":"31003",
    "sg:province":"Navarra",
    "wof:name":"Jamar Turrillas Angel",
    "wof:placetype":"venue"
},
  "geometry": {"coordinates":[-1.6360459328,42.8089866638],"type":"Point"}
}