{
  "type": "Feature",
  "properties": {
    "addr:full":"Calle de Sabio, 10 Higuera Real Badajoz 06350",
    "addr:housenumber":"10",
    "addr:postcode":"06350",
    "addr:street":"Calle De Sabio",
    "iso:country":"ES",
    "sg:address":"Calle de Sabio, 10",
    "sg:city":"Higuera Real",
    "sg:orig_category":"Alimentaci\u00d3n General (al Por Menor)",
    "sg:phone":"+34 924 72 33 16",
    "sg:postcode":"06350",
    "sg:province":"Badajoz",
    "wof:name":"Serrano Luna Candido",
    "wof:placetype":"venue"
},
  "geometry": {"coordinates":[-6.6874089241,38.1418495178],"type":"Point"}
}