{
  "type": "Feature",
  "properties": {
    "addr:full":"Pl Baltasar Aragon, 1 Terrassa Barcelona 08224",
    "addr:housenumber":"1",
    "addr:postcode":"08224",
    "addr:street":"Pl Baltasar Aragon",
    "iso:country":"ES",
    "sg:address":"Pl Baltasar Aragon, 1",
    "sg:city":"Terrassa",
    "sg:orig_category":"Semiller\u00cdas",
    "sg:phone":"+34 937 80 39 66",
    "sg:postcode":"08224",
    "sg:province":"Barcelona",
    "wof:name":"Rodriguez Cirera Juanita",
    "wof:placetype":"venue"
},
  "geometry": {"coordinates":[2.0037651062,41.5564231873],"type":"Point"}
}