{
  "type": "Feature",
  "properties": {
    "iso:country":"ES",
    "sg:address":"Gipuzkoa Kalea, 40",
    "sg:city":"Zarautz",
    "sg:orig_category":"Internados & Ense\u00d1anza Privada",
    "sg:phone":"+34 943 83 27 08",
    "sg:postcode":"20800",
    "sg:province":"Guip\u00f9zcoa",
    "wof:name":"Colegio Maria Inmaculada",
    "wof:placetype":"venue"
},
  "geometry": {"coordinates":[-2.1695239544,43.2851371765],"type":"Point"}
}