{
  "type": "Feature",
  "properties": {
    "addr:full":"Carrer de Major, 57 Montornes Centre Barcelona 08170",
    "addr:housenumber":"57",
    "addr:postcode":"08170",
    "addr:street":"Carrer De Major;Centre Barcelona",
    "iso:country":"ES",
    "sg:address":"Carrer de Major, 57",
    "sg:city":"Montornes Centre",
    "sg:orig_category":"Inform\u00c1tica (estudios, Servicios, Asesor\u00cda, Formaci\u00d3n)",
    "sg:phone":"+34 935 72 03 89",
    "sg:postcode":"08170",
    "sg:province":"Barcelona",
    "wof:name":"Indiworks S.l",
    "wof:placetype":"venue"
},
  "geometry": {"coordinates":[2.2692990303,41.5411109924],"type":"Point"}
}