{
  "type": "Feature",
  "properties": {
    "iso:country":"ES",
    "sg:address":"Virxe Das Mareas, 56",
    "sg:city":"Virxe Das Mareas",
    "sg:orig_category":"Negocio De Madera",
    "sg:phone":"+34 986 73 14 01",
    "sg:postcode":"36980",
    "sg:province":"Pontevedra",
    "wof:name":"Mari\u00f1o Mascato Amador",
    "wof:placetype":"venue"
},
  "geometry": {"coordinates":[-8.86282444,42.4956588745],"type":"Point"}
}