{
  "type": "Feature",
  "properties": {
    "addr:full":"Carrer de Viladomat, 259 Barcelona Barcelona 08029",
    "addr:housenumber":"259",
    "addr:postcode":"08029",
    "addr:street":"Carrer De Viladomat",
    "iso:country":"ES",
    "sg:address":"Carrer de Viladomat, 259",
    "sg:city":"Barcelona",
    "sg:orig_category":"Artes Gr\u00c1ficas, Artes Pl\u00c1sticas (curso)",
    "sg:phone":"+34 933 63 10 11",
    "sg:postcode":"08029",
    "sg:province":"Barcelona",
    "sg:website":"www.gourmetdor.com",
    "wof:name":"Gourmet D'or S.l.",
    "wof:placetype":"venue"
},
  "geometry": {"coordinates":[2.147744894,41.3866958618],"type":"Point"}
}