{
  "type": "Feature",
  "properties": {
    "addr:full":"Carrer de Blas Infante (de), 5 Montornes Centre Barcelona 08170",
    "addr:postcode":"08170",
    "addr:street":"Carrer De Blas Infante De 5 Montornes Centre Barcelona",
    "iso:country":"ES",
    "sg:address":"Carrer de Blas Infante (de), 5",
    "sg:city":"Montornes Centre",
    "sg:orig_category":"Peluquer\u00cdas, Peluquer\u00cda Mixta",
    "sg:phone":"+34 935 68 25 13",
    "sg:postcode":"08170",
    "sg:province":"Barcelona",
    "wof:name":"Tarrago Valero Nuria",
    "wof:placetype":"venue"
},
  "geometry": {"coordinates":[2.2636899948,41.5415153503],"type":"Point"}
}