{
  "type": "Feature",
  "properties": {
    "addr:full":"Calle de Miguel De Cervantes, 10 Teruel Teruel 44002",
    "addr:housenumber":"10",
    "addr:postcode":"44002",
    "addr:street":"Calle De Miguel De Cervantes",
    "iso:country":"ES",
    "sg:address":"Calle de Miguel De Cervantes, 10",
    "sg:city":"Teruel",
    "sg:orig_category":"Delegados, Agentes De Tr\u00c1nsito, Auxiliares De Transporte Internacional",
    "sg:phone":"+34 978 60 28 52",
    "sg:postcode":"44002",
    "sg:province":"Teruel",
    "wof:name":"Guillen Hoyo Jose",
    "wof:placetype":"venue"
},
  "geometry": {"coordinates":[-1.1034719944,40.3324012756],"type":"Point"}
}