{
  "type": "Feature",
  "properties": {
    "iso:country":"ES",
    "sg:address":"Cmno Barco (del), 8",
    "sg:city":"San Sebastian De Los Reyes",
    "sg:orig_category":"Promotores Constructores",
    "sg:phone":"+34 916 51 14 44",
    "sg:postcode":"28700",
    "sg:province":"Madrid",
    "wof:name":"Zail S.l.",
    "wof:placetype":"venue"
},
  "geometry": {"coordinates":[-3.6032409668,40.5610618591],"type":"Point"}
}