{
  "type": "Feature",
  "properties": {
    "addr:full":"Calle de Obispo Climent, 9 Castellon Castell\u00f3n 12001",
    "addr:housenumber":"9",
    "addr:postcode":"12001",
    "addr:street":"Calle De Obispo Climent;Castello\u0301N",
    "iso:country":"ES",
    "sg:address":"Calle de Obispo Climent, 9",
    "sg:city":"Castellon",
    "sg:orig_category":"Laboratorios Y Trabajos De Fotograf\u00cda, V\u00cddeo Y Cine",
    "sg:phone":"+34 964 23 61 25",
    "sg:postcode":"12001",
    "sg:province":"Castell\u00f3n",
    "wof:name":"Foto Cine Esgrig S.l.",
    "wof:placetype":"venue"
},
  "geometry": {"coordinates":[-0.0363840014,39.9851036072],"type":"Point"}
}