{
  "type": "Feature",
  "properties": {
    "addr:full":"Calle de Pando, 26 Torrelavega Cantabria 39300",
    "addr:housenumber":"26",
    "addr:postcode":"39300",
    "addr:street":"Calle De Pando",
    "iso:country":"ES",
    "sg:address":"Calle de Pando, 26",
    "sg:city":"Torrelavega",
    "sg:orig_category":"Internados & Ense\u00d1anza Privada",
    "sg:phone":"+34 942 80 73 13",
    "sg:postcode":"39300",
    "sg:province":"Cantabria",
    "wof:name":"Congregacion De Los Sagrados Corazones",
    "wof:placetype":"venue"
},
  "geometry": {"coordinates":[-4.0447869301,43.3464927673],"type":"Point"}
}