{
  "type": "Feature",
  "properties": {
    "iso:country":"ES",
    "sg:address":"Ctra Rubi, Km. 0001,0",
    "sg:city":"Mira-sol",
    "sg:orig_category":"Fabricaci\u00d3n De Telas Y Sedas",
    "sg:phone":"+34 935 83 05 50",
    "sg:postcode":"08173",
    "sg:province":"Barcelona",
    "sg:website":"www.fibertex.com",
    "wof:name":"Fibertex Elephant Espa\u00f1a S.l. Sociedad Unipersonal",
    "wof:placetype":"venue"
},
  "geometry": {"coordinates":[2.0622999668,41.4687690735],"type":"Point"}
}