{
  "type": "Feature",
  "properties": {
    "iso:country":"ES",
    "sg:address":"Calle de Santa Clara, 50",
    "sg:city":"Burgos",
    "sg:orig_category":"Maquinaria Para Industrias Diversas",
    "sg:phone":"+34 947 20 38 45",
    "sg:postcode":"09002",
    "sg:province":"Burgos",
    "wof:name":"Castrillo Perez Aurelio",
    "wof:placetype":"venue"
},
  "geometry": {"coordinates":[-3.6931400299,42.3371391296],"type":"Point"}
}