{
  "type": "Feature",
  "properties": {
    "addr:full":"Avda Denia, 82 Alacant Alicante 03016",
    "addr:housenumber":"82",
    "addr:postcode":"03016",
    "addr:street":"Avda Denia",
    "iso:country":"ES",
    "sg:address":"Avda Denia, 82",
    "sg:city":"Alacant",
    "sg:orig_category":"Inform\u00c1tica (estudios, Servicios, Asesor\u00cda, Formaci\u00d3n)",
    "sg:phone":"+34 965 26 54 53",
    "sg:postcode":"03016",
    "sg:province":"Alicante",
    "wof:name":"Mecanizacion De Empresas S. A.",
    "wof:placetype":"venue"
},
  "geometry": {"coordinates":[-0.4689919949,38.3579483032],"type":"Point"}
}