{
  "type": "Feature",
  "properties": {
    "iso:country":"ES",
    "sg:address":"Calle de Ramal Rodeo, 2",
    "sg:city":"Malaga",
    "sg:orig_category":"Estudios, Instalaci\u00d3n De Climatizaci\u00d3n",
    "sg:phone":"+34 952 20 72 28",
    "sg:postcode":"29018",
    "sg:province":"M\u00e1laga",
    "wof:name":"Construcciones Olia S.l.",
    "wof:placetype":"venue"
},
  "geometry": {"coordinates":[-4.3855361938,36.7265167236],"type":"Point"}
}