{
  "type": "Feature",
  "properties": {
    "addr:full":"Calle de Acosta, 48 Burgo Osma Soria 42300",
    "addr:housenumber":"48",
    "addr:postcode":"42300",
    "addr:street":"Calle De Acosta",
    "iso:country":"ES",
    "sg:address":"Calle de Acosta, 48",
    "sg:city":"Burgo Osma",
    "sg:orig_category":"Mec\u00c1nico Del Autom\u00d3vil",
    "sg:phone":"+34 975 34 02 01",
    "sg:postcode":"42300",
    "sg:province":"Soria",
    "wof:name":"Chamarro Llorente Juan",
    "wof:placetype":"venue"
},
  "geometry": {"coordinates":[-3.0632641315,41.5901908875],"type":"Point"}
}