{
  "type": "Feature",
  "properties": {
    "addr:full":"Calle de Miguel De Cervantes, 8 Alcala Real Ja\u00e9n 23680",
    "addr:housenumber":"8",
    "addr:postcode":"23680",
    "addr:street":"Calle De Miguel De Cervantes;Jae\u0301N",
    "iso:country":"ES",
    "sg:address":"Calle de Miguel De Cervantes, 8",
    "sg:city":"Alcala Real",
    "sg:orig_category":"Bancos",
    "sg:phone":"+34 953 58 05 84",
    "sg:postcode":"23680",
    "sg:province":"Ja\u00e9n",
    "wof:name":"Banco De Andalucia",
    "wof:placetype":"venue"
},
  "geometry": {"coordinates":[-3.9232890606,37.4620018005],"type":"Point"}
}