{
  "type": "Feature",
  "properties": {
    "iso:country":"ES",
    "sg:address":"Cmno Zamora, S/n",
    "sg:city":"Morales Vino",
    "sg:orig_category":"Negocio De Materiales De Construcci\u00d3n",
    "sg:phone":"+34 980 57 02 14",
    "sg:postcode":"49190",
    "sg:province":"Zamora",
    "wof:name":"San Damian Hernandez Felix",
    "wof:placetype":"venue"
},
  "geometry": {"coordinates":[-5.7349591255,41.445602417],"type":"Point"}
}