{
  "type": "Feature",
  "properties": {
    "addr:full":"Carr Marius Verdaguer, 20 Ciutadella Menorca Islas Baleares 07760",
    "addr:housenumber":"20",
    "addr:postcode":"07760",
    "addr:street":"Carr Marius Verdaguer",
    "iso:country":"ES",
    "sg:address":"Carr Marius Verdaguer, 20",
    "sg:city":"Ciutadella Menorca",
    "sg:orig_category":"Cr\u00cda De Animales",
    "sg:phone":"+34 971 38 19 41",
    "sg:postcode":"07760",
    "sg:province":"Islas Baleares",
    "wof:name":"Pons Pons Juana Maria",
    "wof:placetype":"venue"
},
  "geometry": {"coordinates":[3.8421800137,40.0057907104],"type":"Point"}
}