{
  "type": "Feature",
  "properties": {
    "iso:country":"ES",
    "sg:address":"Calle de Uruguay, 13",
    "sg:city":"Valencia",
    "sg:orig_category":"Inform\u00c1tica (estudios, Servicios, Asesor\u00cda, Formaci\u00d3n)",
    "sg:phone":"+34 963 10 70 53",
    "sg:postcode":"46007",
    "sg:province":"Valencia",
    "wof:name":"Berisa Diaz Jesus Maria",
    "wof:placetype":"venue"
},
  "geometry": {"coordinates":[-0.3868489861,39.4588813782],"type":"Point"}
}