{
  "type": "Feature",
  "properties": {
    "addr:full":"Avda Finisterre, 23 Carballo La Coru\u00f1a 15100",
    "addr:housenumber":"23",
    "addr:postcode":"15100",
    "addr:street":"Avda Finisterre;La Corun\u0303A",
    "iso:country":"ES",
    "sg:address":"Avda Finisterre, 23",
    "sg:city":"Carballo",
    "sg:orig_category":"Electrodom\u00c9sticos (al Por Menor)",
    "sg:phone":"+34 981 70 17 63",
    "sg:postcode":"15100",
    "sg:province":"La Coru\u00f1a",
    "wof:name":"Brions Barral Justo Amador",
    "wof:placetype":"venue"
},
  "geometry": {"coordinates":[-8.6915636063,43.2116165161],"type":"Point"}
}