{
  "type": "Feature",
  "properties": {
    "addr:full":"Avda Rosalia Castro, 65 Milladoiro La Coru\u00f1a 15895",
    "addr:housenumber":"65",
    "addr:postcode":"15895",
    "addr:street":"Avda Rosalia Castro;La Corun\u0303A",
    "iso:country":"ES",
    "sg:address":"Avda Rosalia Castro, 65",
    "sg:city":"Milladoiro",
    "sg:orig_category":"Maquinaria Para Industrias Diversas",
    "sg:phone":"+34 981 53 43 34",
    "sg:postcode":"15895",
    "sg:province":"La Coru\u00f1a",
    "wof:name":"Maquinaria Industrial Galaico Lusa S.l.",
    "wof:placetype":"venue"
},
  "geometry": {"coordinates":[-8.551943779,42.8742828369],"type":"Point"}
}