{
  "type": "Feature",
  "properties": {
    "addr:full":"Pase Coca (de), 28 Barrios C\u00e1diz 11370",
    "addr:postcode":"11370",
    "addr:street":"Ca\u0301Diz",
    "iso:country":"ES",
    "sg:address":"Pase Coca (de), 28",
    "sg:city":"Barrios",
    "sg:orig_category":"Empresarios",
    "sg:phone":"+34 956 62 13 17",
    "sg:postcode":"11370",
    "sg:province":"C\u00e1diz",
    "sg:website":"www.delgasur.es.mn",
    "wof:name":"Construcciones Delgasur S.l.",
    "wof:placetype":"venue"
},
  "geometry": {"coordinates":[-5.4946498871,36.1863174438],"type":"Point"}
}