{
  "type": "Feature",
  "properties": {
    "addr:full":"Carr Samaria, 55 Pals Girona 17256",
    "addr:housenumber":"55",
    "addr:postcode":"17256",
    "addr:street":"Carr Samaria",
    "iso:country":"ES",
    "sg:address":"Carr Samaria, 55",
    "sg:city":"Pals",
    "sg:orig_category":"Restaurantes",
    "sg:phone":"+34 972 63 69 67",
    "sg:postcode":"17256",
    "sg:province":"Girona",
    "wof:name":"Bonet Tauler Maria",
    "wof:placetype":"venue"
},
  "geometry": {"coordinates":[3.1503200531,41.9683685303],"type":"Point"}
}