{
  "type": "Feature",
  "properties": {
    "addr:full":"San Inazio Kalea, 14 Beasain Guip\u00f9zcoa 20200",
    "addr:housenumber":"14",
    "addr:postcode":"20200",
    "addr:street":"San Inazio Kalea;Guipu\u0300Zcoa",
    "iso:country":"ES",
    "sg:address":"San Inazio Kalea, 14",
    "sg:city":"Beasain",
    "sg:orig_category":"Zapatos (al Por Menor)",
    "sg:phone":"+34 943 16 04 34",
    "sg:postcode":"20200",
    "sg:province":"Guip\u00f9zcoa",
    "wof:name":"Garicano Uranga Lourdes",
    "wof:placetype":"venue"
},
  "geometry": {"coordinates":[-2.196862936,43.0473213196],"type":"Point"}
}