{
  "type": "Feature",
  "properties": {
    "addr:full":"Calle de Granjilla, S/n Garcihernandez Salamanca 37810",
    "addr:housenumber":"s",
    "addr:postcode":"37810",
    "addr:street":"Calle De Granjilla;/ N",
    "iso:country":"ES",
    "sg:address":"Calle de Granjilla, S/n",
    "sg:city":"Garcihernandez",
    "sg:orig_category":"Aguas (distribuci\u00d3n, Servicios)",
    "sg:phone":"+34 923 37 15 85",
    "sg:postcode":"37810",
    "sg:province":"Salamanca",
    "wof:name":"Confederacion Hidrografica Del Duero",
    "wof:placetype":"venue"
},
  "geometry": {"coordinates":[-5.437710762,40.8861045837],"type":"Point"}
}