{
  "type": "Feature",
  "properties": {
    "addr:full":"Carrer de Narcis Monturiol (de), 59 Vilassar De Mar Barcelona 08340",
    "addr:housenumber":"59",
    "addr:postcode":"08340",
    "addr:street":"Carrer De Narcis Monturiol De",
    "iso:country":"ES",
    "sg:address":"Carrer de Narcis Monturiol (de), 59",
    "sg:city":"Vilassar De Mar",
    "sg:orig_category":"M\u00c9dicos: Estomatolog\u00cda",
    "sg:phone":"+34 937 50 04 04",
    "sg:postcode":"08340",
    "sg:province":"Barcelona",
    "wof:name":"Ferrer Bosca Modest",
    "wof:placetype":"venue"
},
  "geometry": {"coordinates":[2.390034914,41.5060958862],"type":"Point"}
}