{
  "type": "Feature",
  "properties": {
    "iso:country":"ES",
    "sg:address":"Pg Republica Argentina, 5",
    "sg:city":"Felanitx",
    "sg:orig_category":"Muebles Y Accesorios Para Cocinas Y Cuartos De Ba\u00d1o (al Por Menor)",
    "sg:phone":"+34 971 82 73 67",
    "sg:postcode":"07200",
    "sg:province":"Islas Baleares",
    "wof:name":"Barcelo Tuduri Sebastian",
    "wof:placetype":"venue"
},
  "geometry": {"coordinates":[3.1508910656,39.4739303589],"type":"Point"}
}