{
  "type": "Feature",
  "properties": {
    "addr:full":"Avda Garcia Barbon, 58 Vigo Pontevedra 36201",
    "addr:housenumber":"58",
    "addr:postcode":"36201",
    "addr:street":"Avda Garcia Barbon",
    "iso:country":"ES",
    "sg:address":"Avda Garcia Barbon, 58",
    "sg:city":"Vigo",
    "sg:orig_category":"Abogados",
    "sg:phone":"+34 986 43 43 71",
    "sg:postcode":"36201",
    "sg:province":"Pontevedra",
    "wof:name":"Ega\u00f1a Dominguez Adolfo",
    "wof:placetype":"venue"
},
  "geometry": {"coordinates":[-8.7129230499,42.2368049622],"type":"Point"}
}