{
  "type": "Feature",
  "properties": {
    "addr:full":"Carrer de Joan Maragall, 7 Sant Feliu Llobregat Barcelona 08980",
    "addr:housenumber":"7",
    "addr:postcode":"08980",
    "addr:street":"Carrer De Joan Maragall;Sant Feliu",
    "iso:country":"ES",
    "sg:address":"Carrer de Joan Maragall, 7",
    "sg:city":"Sant Feliu Llobregat",
    "sg:orig_category":"Servicios De Higiene Y Peluquer\u00cda Para Perros Y Gatos",
    "sg:phone":"+34 936 85 49 23",
    "sg:postcode":"08980",
    "sg:province":"Barcelona",
    "wof:name":"Ricart Viladiu Alberto",
    "wof:placetype":"venue"
},
  "geometry": {"coordinates":[2.0454759598,41.3803062439],"type":"Point"}
}