{
  "type": "Feature",
  "properties": {
    "iso:country":"ES",
    "sg:address":"Calle de Virgen Del Sagrario, 22",
    "sg:city":"Madrid",
    "sg:orig_category":"Asociaciones Humanitarias, De Cooperaci\u00d3n, De Acci\u00d3n Social",
    "sg:phone":"+34 913 77 59 32",
    "sg:postcode":"28027",
    "sg:province":"Madrid",
    "wof:name":"Asociacion Para La Atencion Terapeutica Del Juego Aatj",
    "wof:placetype":"venue"
},
  "geometry": {"coordinates":[-3.6492350101,40.4359970093],"type":"Point"}
}