{
  "type": "Feature",
  "properties": {
    "addr:full":"Av Rei Jaume I, 109 Santa Pon\u00c7a Islas Baleares 07180",
    "addr:housenumber":"109",
    "addr:postcode":"07180",
    "addr:street":"Av Rei Jaume I",
    "iso:country":"ES",
    "sg:address":"Av Rei Jaume I, 109",
    "sg:city":"Santa Pon\u00c7a",
    "sg:orig_category":"Ropa Para Se\u00d1oras (al Por Menor)",
    "sg:phone":"+34 971 69 02 62",
    "sg:postcode":"07180",
    "sg:province":"Islas Baleares",
    "wof:name":"Gutierrez Garcia Victoria",
    "wof:placetype":"venue"
},
  "geometry": {"coordinates":[2.4848630428,39.5164108276],"type":"Point"}
}