{
  "type": "Feature",
  "properties": {
    "addr:full":"Calle de Joaquin Blake, 17 Torremolinos M\u00e1laga 29620",
    "addr:housenumber":"17",
    "addr:postcode":"29620",
    "addr:street":"Calle De Joaquin Blake;Ma\u0301Laga",
    "iso:country":"ES",
    "sg:address":"Calle de Joaquin Blake, 17",
    "sg:city":"Torremolinos",
    "sg:orig_category":"Guarder\u00cdas",
    "sg:phone":"+34 952 05 61 41",
    "sg:postcode":"29620",
    "sg:province":"M\u00e1laga",
    "wof:name":"La Liga Malague\u00d1a De La Educacion Y La C",
    "wof:placetype":"venue"
},
  "geometry": {"coordinates":[-4.5053100586,36.6238746643],"type":"Point"}
}