{
  "type": "Feature",
  "properties": {
    "addr:full":"Carrer de Cobalt, 175 Hospitalet Llobregat Barcelona 08907",
    "addr:housenumber":"175",
    "addr:postcode":"08907",
    "addr:street":"Carrer De Cobalt",
    "iso:country":"ES",
    "sg:address":"Carrer de Cobalt, 175",
    "sg:city":"Hospitalet Llobregat",
    "sg:orig_category":"Suministros Y Materiales Industriales",
    "sg:phone":"+34 933 38 11 55",
    "sg:postcode":"08907",
    "sg:province":"Barcelona",
    "wof:name":"Trebede S.l",
    "wof:placetype":"venue"
},
  "geometry": {"coordinates":[2.1002240181,41.3547515869],"type":"Point"}
}