{
  "type": "Feature",
  "properties": {
    "iso:country":"ES",
    "sg:address":"Carr Riu Guadalaviar, 10",
    "sg:city":"Pai I Capellans",
    "sg:orig_category":"Importaci\u00d3n",
    "sg:phone":"+34 961 92 10 28",
    "sg:postcode":"46930",
    "sg:province":"Valencia",
    "sg:website":"www.ateval.com/dolz",
    "wof:name":"Dolz S.a.",
    "wof:placetype":"venue"
},
  "geometry": {"coordinates":[-0.4419890046,39.482711792],"type":"Point"}
}