{
  "type": "Feature",
  "properties": {
    "addr:full":"Ferreiros, 22 Pontedeume La Coru\u00f1a 15600",
    "addr:housenumber":"22",
    "addr:postcode":"15600",
    "addr:street":"Ferreiros;La Corun\u0303A",
    "iso:country":"ES",
    "sg:address":"Ferreiros, 22",
    "sg:city":"Pontedeume",
    "sg:orig_category":"Molduras, Junquillos, Listones Y Molduras Perforadas",
    "sg:phone":"+34 981 43 37 57",
    "sg:postcode":"15600",
    "sg:province":"La Coru\u00f1a",
    "wof:name":"Lopez Rico Santiago",
    "wof:placetype":"venue"
},
  "geometry": {"coordinates":[-8.1699476242,43.4069976807],"type":"Point"}
}