{
  "type": "Feature",
  "properties": {
    "addr:full":"Carr Manuel De Falla, 25 Palafrugell Girona 17200",
    "addr:housenumber":"25",
    "addr:postcode":"17200",
    "addr:street":"Carr Manuel De Falla",
    "iso:country":"ES",
    "sg:address":"Carr Manuel De Falla, 25",
    "sg:city":"Palafrugell",
    "sg:orig_category":"Promotores Constructores",
    "sg:phone":"+34 972 30 82 71",
    "sg:postcode":"17200",
    "sg:province":"Girona",
    "wof:name":"Ar-gam Pavimentos Autonivelantes S.l.",
    "wof:placetype":"venue"
},
  "geometry": {"coordinates":[3.1572179794,41.9216880798],"type":"Point"}
}