{
  "type": "Feature",
  "properties": {
    "iso:country":"ES",
    "sg:address":"Calle de Almirante Benitez Inglott, 22",
    "sg:city":"Palmas De Gran Canaria",
    "sg:orig_category":"Alimentaci\u00d3n General (al Por Menor)",
    "sg:phone":"+34 928 25 08 72",
    "sg:postcode":"35011",
    "sg:province":"Las Palmas",
    "wof:name":"Santiago Almeida Francisco",
    "wof:placetype":"venue"
},
  "geometry": {"coordinates":[-15.4367799759,28.1131916046],"type":"Point"}
}