{
  "type": "Feature",
  "properties": {
    "addr:full":"Calle de Cruz, 76 Aznalcollar Sevilla 41870",
    "addr:housenumber":"76",
    "addr:postcode":"41870",
    "addr:street":"Calle De Cruz",
    "iso:country":"ES",
    "sg:address":"Calle de Cruz, 76",
    "sg:city":"Aznalcollar",
    "sg:orig_category":"Cr\u00cda De Animales",
    "sg:phone":"+34 954 13 30 59",
    "sg:postcode":"41870",
    "sg:province":"Sevilla",
    "wof:name":"Ramirez Escoresca Juan",
    "wof:placetype":"venue"
},
  "geometry": {"coordinates":[-6.2742595673,37.5203323364],"type":"Point"}
}