{
  "type": "Feature",
  "properties": {
    "addr:full":"Carrer de Cardaire, 11 Terrassa Barcelona 08221",
    "addr:housenumber":"11",
    "addr:postcode":"08221",
    "addr:street":"Carrer De Cardaire",
    "iso:country":"ES",
    "sg:address":"Carrer de Cardaire, 11",
    "sg:city":"Terrassa",
    "sg:orig_category":"Florister\u00cdas",
    "sg:phone":"+34 937 86 16 75",
    "sg:postcode":"08221",
    "sg:province":"Barcelona",
    "sg:website":"www.artverd.com",
    "wof:name":"Marti Escayol Rosa Maria",
    "wof:placetype":"venue"
},
  "geometry": {"coordinates":[2.0130159855,41.5633659363],"type":"Point"}
}