{
  "type": "Feature",
  "properties": {
    "addr:full":"Calle de Vargas (los), 16 Segovia Segovia 40003",
    "addr:housenumber":"16",
    "addr:postcode":"40003",
    "addr:street":"Calle De Vargas Los",
    "iso:country":"ES",
    "sg:address":"Calle de Vargas (los), 16",
    "sg:city":"Segovia",
    "sg:orig_category":"Arquitectos",
    "sg:phone":"+34 921 43 18 98",
    "sg:postcode":"40003",
    "sg:province":"Segovia",
    "wof:name":"Gil-vargas Sanchez De Toledo Marcos",
    "wof:placetype":"venue"
},
  "geometry": {"coordinates":[-4.1119999886,40.9524421692],"type":"Point"}
}