{
  "type": "Feature",
  "properties": {
    "addr:full":"Parque Empresarial La Esprilla, 31 Igollo Cantabria 39608",
    "addr:housenumber":"31",
    "addr:postcode":"39608",
    "addr:street":"Igollo",
    "iso:country":"ES",
    "sg:address":"Parque Empresarial La Esprilla, 31",
    "sg:city":"Igollo",
    "sg:orig_category":"Muebles, Minoristas",
    "sg:phone":"+34 942 58 19 75",
    "sg:postcode":"39608",
    "sg:province":"Cantabria",
    "wof:name":"Muebles La Mies",
    "wof:placetype":"venue"
},
  "geometry": {"coordinates":[-3.8830139637,43.4323272705],"type":"Point"}
}