{
  "type": "Feature",
  "properties": {
    "addr:full":"Calle de Rio Jiloca, 49 Zaragoza Zaragoza 50007",
    "addr:housenumber":"49",
    "addr:postcode":"50007",
    "addr:street":"Calle De Rio Jiloca",
    "iso:country":"ES",
    "sg:address":"Calle de Rio Jiloca, 49",
    "sg:city":"Zaragoza",
    "sg:orig_category":"Servicios Diversos",
    "sg:phone":"+34 976 27 90 82",
    "sg:postcode":"50007",
    "sg:province":"Zaragoza",
    "wof:name":"Rigu Conductos De Aire Acondicionado S.coop.",
    "wof:placetype":"venue"
},
  "geometry": {"coordinates":[-0.8833990097,41.6289215088],"type":"Point"}
}