{
  "type": "Feature",
  "properties": {
    "iso:country":"ES",
    "sg:address":"Calle de Pedro Duro, 6",
    "sg:city":"Gijon",
    "sg:orig_category":"Transportes Por Carretera: Lotes Completos, Mercanc\u00cdas Diversas",
    "sg:phone":"+34 985 34 53 21",
    "sg:postcode":"33206",
    "sg:province":"Asturias",
    "wof:name":"Tetrafer S.l.",
    "wof:placetype":"venue"
},
  "geometry": {"coordinates":[-5.6671347618,43.5417327881],"type":"Point"}
}