{
  "type": "Feature",
  "properties": {
    "iso:country":"ES",
    "sg:address":"La Iglesia, 28",
    "sg:city":"Carbajal Legua",
    "sg:orig_category":"Caf\u00c9s, Bares, Cervecer\u00cdas",
    "sg:phone":"+34 987 28 82 50",
    "sg:postcode":"24196",
    "sg:province":"Le\u00f3n",
    "wof:name":"Taller Mecanico La Solana",
    "wof:placetype":"venue"
},
  "geometry": {"coordinates":[-5.6045589447,42.6573486328],"type":"Point"}
}