{
  "type": "Feature",
  "properties": {
    "addr:full":"Carrer de Almaden, 3 Hospitalet Llobregat Barcelona 08901",
    "addr:housenumber":"3",
    "addr:postcode":"08901",
    "addr:street":"Carrer De Almaden",
    "iso:country":"ES",
    "sg:address":"Carrer de Almaden, 3",
    "sg:city":"Hospitalet Llobregat",
    "sg:orig_category":"Artes Gr\u00c1ficas, Artes Pl\u00c1sticas (curso)",
    "sg:phone":"+34 933 37 41 65",
    "sg:postcode":"08901",
    "sg:province":"Barcelona",
    "wof:name":"Flexo Rem S.l.",
    "wof:placetype":"venue"
},
  "geometry": {"coordinates":[2.1060760021,41.3645248413],"type":"Point"}
}