{
  "type": "Feature",
  "properties": {
    "iso:country":"ES",
    "sg:address":"Avda Doctor Fleming, 43",
    "sg:city":"Le\u00f3n",
    "sg:orig_category":"Molduras, Junquillos, Listones Y Molduras Perforadas",
    "sg:phone":"+34 987 21 66 96",
    "sg:postcode":"24009",
    "sg:province":"Le\u00f3n",
    "wof:name":"Gonzalez Del Riego Agustin",
    "wof:placetype":"venue"
},
  "geometry": {"coordinates":[-5.5852298737,42.5967712402],"type":"Point"}
}