{
  "type": "Feature",
  "properties": {
    "addr:full":"Avda Padre Isla, 48 Le\u00f3n Le\u00f3n 24002",
    "addr:housenumber":"48",
    "addr:postcode":"24002",
    "addr:street":"Avda Padre Isla;Leo\u0301N",
    "iso:country":"ES",
    "sg:address":"Avda Padre Isla, 48",
    "sg:city":"Le\u00f3n",
    "sg:orig_category":"Aparcamientos (infraestructuras, Accesorios)",
    "sg:phone":"+34 987 22 25 84",
    "sg:postcode":"24002",
    "sg:province":"Le\u00f3n",
    "wof:name":"Proleon S.a.",
    "wof:placetype":"venue"
},
  "geometry": {"coordinates":[-5.5758671761,42.6028862],"type":"Point"}
}