{
  "type": "Feature",
  "properties": {
    "addr:full":"Calle de Antonio Machado, 5 Miguelturra Ciudad Real 13170",
    "addr:housenumber":"5",
    "addr:postcode":"13170",
    "addr:street":"Calle De Antonio Machado",
    "iso:country":"ES",
    "sg:address":"Calle de Antonio Machado, 5",
    "sg:city":"Miguelturra",
    "sg:orig_category":"Persianas Interiores, Exteriores",
    "sg:phone":"+34 926 24 09 64",
    "sg:postcode":"13170",
    "sg:province":"Ciudad Real",
    "wof:name":"Garcia Sanchez Manuel",
    "wof:placetype":"venue"
},
  "geometry": {"coordinates":[-3.8933866024,38.9620246887],"type":"Point"}
}