{
  "type": "Feature",
  "properties": {
    "iso:country":"ES",
    "sg:address":"Calle de Ganivet, 39",
    "sg:city":"Iznalloz",
    "sg:orig_category":"Reposter\u00cdas",
    "sg:phone":"+34 958 38 40 83",
    "sg:postcode":"18550",
    "sg:province":"Granada",
    "wof:name":"Productos La Campana Panaderia Y Bolleria S.l.",
    "wof:placetype":"venue"
},
  "geometry": {"coordinates":[-3.5257229805,37.3925361633],"type":"Point"}
}