{
  "type": "Feature",
  "properties": {
    "iso:country":"ES",
    "sg:address":"Calle de Innovacion, S/n",
    "sg:city":"Sevilla",
    "sg:orig_category":"Promotores Constructores",
    "sg:phone":"+34 954 51 25 55",
    "sg:postcode":"41020",
    "sg:province":"Sevilla",
    "wof:name":"Inmo-galaxy S.a.",
    "wof:placetype":"venue"
},
  "geometry": {"coordinates":[-5.9279742241,37.4058189392],"type":"Point"}
}