{
  "type": "Feature",
  "properties": {
    "iso:country":"ES",
    "sg:address":"Calle de Virgen De La Soledad, 52",
    "sg:city":"Manzanares",
    "sg:orig_category":"Garajes De Veh\u00cdculos",
    "sg:phone":"+34 926 61 11 36",
    "sg:postcode":"13200",
    "sg:province":"Ciudad Real",
    "wof:name":"Ruiz-peinado Alvaro Bartolome",
    "wof:placetype":"venue"
},
  "geometry": {"coordinates":[-3.3765590191,38.9976615906],"type":"Point"}
}