{
  "type": "Feature",
  "properties": {
    "iso:country":"ES",
    "sg:address":"Avda General Sanjurjo, 26",
    "sg:city":"Coru\u00d1a",
    "sg:orig_category":"Florister\u00cdas",
    "sg:phone":"+34 981 28 94 19",
    "sg:postcode":"15006",
    "sg:province":"A Coru\u00f1a",
    "wof:name":"Ya\u00f1ez Gonzalez Gloria",
    "wof:placetype":"venue"
},
  "geometry": {"coordinates":[-8.4026231766,43.3561019897],"type":"Point"}
}