{
  "type": "Feature",
  "properties": {
    "iso:country":"ES",
    "sg:address":"Calle de San Zacarias, 18",
    "sg:city":"Villacedre",
    "sg:orig_category":"Mec\u00c1nico Del Autom\u00d3vil",
    "sg:phone":"+34 987 25 49 52",
    "sg:postcode":"24194",
    "sg:province":"Le\u00f3n",
    "sg:website":"www.paginasamarillas.es",
    "wof:name":"Autocooperativa Leonesa De Reparaciones",
    "wof:placetype":"venue"
},
  "geometry": {"coordinates":[-5.5753798485,42.6218910217],"type":"Point"}
}