{
  "type": "Feature",
  "properties": {
    "addr:full":"Praj Carretera De Berja, S/n Dalias Almer\u00eda 04750",
    "addr:housenumber":"s",
    "addr:postcode":"04750",
    "addr:street":"Carretera De Berja;/ N Dalias Almeri\u0301A",
    "iso:country":"ES",
    "sg:address":"Praj Carretera De Berja, S/n",
    "sg:city":"Dalias",
    "sg:orig_category":"Granos Y Semillas (producci\u00d3n, Al Por Mayor)",
    "sg:phone":"+34 950 49 46 46",
    "sg:postcode":"04750",
    "sg:province":"Almer\u00eda",
    "wof:name":"Ba\u00f1os Fernandez Antonio",
    "wof:placetype":"venue"
},
  "geometry": {"coordinates":[-2.8728890419,36.8234138489],"type":"Point"}
}