{
  "type": "Feature",
  "properties": {
    "addr:full":"Calle de Chile, 20 Logro\u00f1o La Rioja 26005",
    "addr:housenumber":"20",
    "addr:postcode":"26005",
    "addr:street":"Calle De Chile;Rioja",
    "iso:country":"ES",
    "sg:address":"Calle de Chile, 20",
    "sg:city":"Logro\u00f1o",
    "sg:orig_category":"Ropa Para Ni\u00d1os (al Por Menor)",
    "sg:phone":"+34 941 20 09 53",
    "sg:postcode":"26005",
    "sg:province":"La Rioja",
    "wof:name":"Ordo\u00f1ez Alvarez Bego\u00f1a",
    "wof:placetype":"venue"
},
  "geometry": {"coordinates":[-2.4542396069,42.4619750977],"type":"Point"}
}