{
  "type": "Feature",
  "properties": {
    "iso:country":"ES",
    "sg:address":"Ctra Constantina, Km. 0006,0",
    "sg:city":"Villanueva Rio Y Minas",
    "sg:orig_category":"Aguas (distribuci\u00d3n, Servicios)",
    "sg:phone":"+34 954 74 70 41",
    "sg:postcode":"41350",
    "sg:province":"Sevilla",
    "wof:name":"Aguas Del Huesna S.l.",
    "wof:placetype":"venue"
},
  "geometry": {"coordinates":[-5.627269268,37.6822280884],"type":"Point"}
}