{
  "type": "Feature",
  "properties": {
    "iso:country":"ES",
    "sg:address":"Calle de Goleta, 15",
    "sg:city":"Tomillares",
    "sg:orig_category":"Creaci\u00d3n De Sitios, Hosting Internet",
    "sg:phone":"+34 952 41 06 58",
    "sg:postcode":"29130",
    "sg:province":"M\u00e1laga",
    "sg:website":"www.alhaurin.com",
    "wof:name":"Andalucia Comunidad Cultural S.l.",
    "wof:placetype":"venue"
},
  "geometry": {"coordinates":[-4.5393328667,36.6618423462],"type":"Point"}
}