{
  "type": "Feature",
  "properties": {
    "iso:country":"ES",
    "sg:address":"Calle de Simon Carpintero, S/n",
    "sg:city":"Cordoba",
    "sg:orig_category":"Cristaler\u00cdas",
    "sg:phone":"+34 957 32 50 17",
    "sg:postcode":"14014",
    "sg:province":"C\u00f3rdoba",
    "wof:name":"Acristalamientos Profesionales Sll",
    "wof:placetype":"venue"
},
  "geometry": {"coordinates":[-4.721370697,37.9048919678],"type":"Point"}
}