{
  "type": "Feature",
  "properties": {
    "addr:full":"Vena Sant Jaume, 16 Sant Jaume De Treia Barcelona 08310",
    "addr:housenumber":"16",
    "addr:postcode":"08310",
    "addr:street":"Jaume",
    "iso:country":"ES",
    "sg:address":"Vena Sant Jaume, 16",
    "sg:city":"Sant Jaume De Treia",
    "sg:orig_category":"Semiller\u00cdas",
    "sg:phone":"+34 937 97 17 00",
    "sg:postcode":"08310",
    "sg:province":"Barcelona",
    "wof:name":"Riera Vilagrasa S.l.",
    "wof:placetype":"venue"
},
  "geometry": {"coordinates":[2.4036650658,41.5564155579],"type":"Point"}
}