{
  "type": "Feature",
  "properties": {
    "iso:country":"ES",
    "sg:address":"Calle de Centelles, Los, 17",
    "sg:city":"Valencia",
    "sg:orig_category":"Alquiler De V\u00cddeo",
    "sg:phone":"+34 963 95 69 80",
    "sg:postcode":"46006",
    "sg:province":"Valencia",
    "wof:name":"Dvd Cine Digital Stromboli C.b.",
    "wof:placetype":"venue"
},
  "geometry": {"coordinates":[-0.3716070056,39.4598350525],"type":"Point"}
}