{
  "type": "Feature",
  "properties": {
    "addr:full":"Viella, 34 Viella Asturias 33429",
    "addr:housenumber":"34",
    "addr:postcode":"33429",
    "addr:street":"Viella",
    "iso:country":"ES",
    "sg:address":"Viella, 34",
    "sg:city":"Viella",
    "sg:orig_category":"Vinos Y Licores (venta Al Por Menor)",
    "sg:phone":"+34 985 79 27 75",
    "sg:postcode":"33429",
    "sg:province":"Asturias",
    "wof:name":"Allied Domecq Wines Espa\u00d1a S.a.",
    "wof:placetype":"venue"
},
  "geometry": {"coordinates":[-5.7827033997,43.3959465027],"type":"Point"}
}