{
  "type": "Feature",
  "properties": {
    "addr:full":"Calle de Fuertes Acevedo, 1 Oviedo Asturias 33006",
    "addr:housenumber":"1",
    "addr:postcode":"33006",
    "addr:street":"Calle De Fuertes Acevedo",
    "iso:country":"ES",
    "sg:address":"Calle de Fuertes Acevedo, 1",
    "sg:city":"Oviedo",
    "sg:orig_category":"Cajas De Ahorro",
    "sg:phone":"+34 985 23 72 39",
    "sg:postcode":"33006",
    "sg:province":"Asturias",
    "sg:website":"www.cajastur.es",
    "wof:name":"Caja De Ahorros De Asturias",
    "wof:placetype":"venue"
},
  "geometry": {"coordinates":[-5.8627839088,43.3600845337],"type":"Point"}
}