{
  "type": "Feature",
  "properties": {
    "iso:country":"ES",
    "sg:address":"Carrer de Travessera, 26",
    "sg:city":"Cornella Llobregat",
    "sg:orig_category":"Inform\u00c1tica: Material Y Suministros",
    "sg:phone":"+34 933 76 74 18",
    "sg:postcode":"08940",
    "sg:province":"Barcelona",
    "wof:name":"Blatpa S.a.",
    "wof:placetype":"venue"
},
  "geometry": {"coordinates":[2.0791399479,41.36536026],"type":"Point"}
}