{
  "type": "Feature",
  "properties": {
    "iso:country":"ES",
    "sg:address":"Calle de Eguzki, 1",
    "sg:city":"Mutiloagoiti",
    "sg:orig_category":"Asociaciones, Organismos Culturales Y Socioeducativos",
    "sg:phone":"+34 948 29 14 89",
    "sg:postcode":"31192",
    "sg:province":"Navarra",
    "wof:name":"Ayuntamiento De Valle De Aranguren",
    "wof:placetype":"venue"
},
  "geometry": {"coordinates":[-1.6184910536,42.7996330261],"type":"Point"}
}