{
  "type": "Feature",
  "properties": {
    "addr:full":"Avgd Ausias March, 21 Alboraya Valencia 46120",
    "addr:housenumber":"21",
    "addr:postcode":"46120",
    "addr:street":"March",
    "iso:country":"ES",
    "sg:address":"Avgd Ausias March, 21",
    "sg:city":"Alboraya",
    "sg:orig_category":"Art\u00cdculos De Regalo (al Por Menor)",
    "sg:phone":"+34 961 86 04 78",
    "sg:postcode":"46120",
    "sg:province":"Valencia",
    "wof:name":"Marvencien S.l.",
    "wof:placetype":"venue"
},
  "geometry": {"coordinates":[-0.3512699902,39.4959335327],"type":"Point"}
}