{
  "type": "Feature",
  "properties": {
    "addr:full":"Calle de Profesor Motos Guirao, 5 Granada Granada 18002",
    "addr:housenumber":"5",
    "addr:postcode":"18002",
    "addr:street":"Calle De;Guirao",
    "iso:country":"ES",
    "sg:address":"Calle de Profesor Motos Guirao, 5",
    "sg:city":"Granada",
    "sg:orig_category":"Ense\u00d1anza, Formaci\u00d3n Profesional: Aprendizaje",
    "sg:phone":"+34 958 28 51 53",
    "sg:postcode":"18002",
    "sg:province":"Granada",
    "wof:name":"Ruiz Garrido Ceferino",
    "wof:placetype":"venue"
},
  "geometry": {"coordinates":[-3.606249094,37.1791610718],"type":"Point"}
}