{
  "type": "Feature",
  "properties": {
    "addr:full":"Calle de Huescar, S/n Malaga M\u00e1laga 29007",
    "addr:housenumber":"s",
    "addr:postcode":"29007",
    "addr:street":"Calle De Huescar;/ N;Ma\u0301Laga",
    "iso:country":"ES",
    "sg:address":"Calle de Huescar, S/n",
    "sg:city":"Malaga",
    "sg:orig_category":"Farmacias",
    "sg:phone":"+34 952 39 98 58",
    "sg:postcode":"29007",
    "sg:province":"M\u00e1laga",
    "wof:name":"Merino Palomo, Hnos C.b.",
    "wof:placetype":"venue"
},
  "geometry": {"coordinates":[-4.4354162216,36.7183036804],"type":"Point"}
}