{
  "type": "Feature",
  "properties": {
    "addr:full":"Carrer de Numero 60 De La Zona Franca, S/n Barcelona Barcelona 08040",
    "addr:postcode":"08040",
    "addr:street":"Carrer De Numero 60 De La;Franca S / N",
    "iso:country":"ES",
    "sg:address":"Carrer de Numero 60 De La Zona Franca, S/n",
    "sg:city":"Barcelona",
    "sg:orig_category":"Aceros Inoxidables",
    "sg:phone":"+34 932 23 44 87",
    "sg:postcode":"08040",
    "sg:province":"Barcelona",
    "wof:name":"Acerinox S.a.",
    "wof:placetype":"venue"
},
  "geometry": {"coordinates":[2.130294323,41.3364562988],"type":"Point"}
}