{
  "type": "Feature",
  "properties": {
    "addr:full":"Calle de Correos, 7 Jaca Huesca 22700",
    "addr:housenumber":"7",
    "addr:postcode":"22700",
    "addr:street":"Calle De Correos",
    "iso:country":"ES",
    "sg:address":"Calle de Correos, 7",
    "sg:city":"Jaca",
    "sg:orig_category":"Cueros Y Pieles (al Por Mayor)",
    "sg:phone":"+34 974 35 61 93",
    "sg:postcode":"22700",
    "sg:province":"Huesca",
    "wof:name":"Morlans Palacio Jose Maria",
    "wof:placetype":"venue"
},
  "geometry": {"coordinates":[-0.5519142151,42.5684013367],"type":"Point"}
}