{
  "type": "Feature",
  "properties": {
    "addr:full":"Carrer de Alcoi, 34 Xixona Alicante 03100",
    "addr:housenumber":"34",
    "addr:postcode":"03100",
    "addr:street":"Carrer De Alcoi",
    "iso:country":"ES",
    "sg:address":"Carrer de Alcoi, 34",
    "sg:city":"Xixona",
    "sg:orig_category":"Abogados",
    "sg:phone":"+34 965 61 12 16",
    "sg:postcode":"03100",
    "sg:province":"Alicante",
    "wof:name":"Miralles Sirvent Gracia",
    "wof:placetype":"venue"
},
  "geometry": {"coordinates":[-0.5061399937,38.5404968262],"type":"Point"}
}