{
  "type": "Feature",
  "properties": {
    "iso:country":"ES",
    "sg:address":"Calle de Pinosol, 10",
    "sg:city":"Malaga",
    "sg:orig_category":"Mercer\u00cda, Lencer\u00cda (al Por Menor)",
    "sg:phone":"+34 952 26 08 96",
    "sg:postcode":"29012",
    "sg:province":"M\u00e1laga",
    "wof:name":"Serrano Do\u00f1a Salvador",
    "wof:placetype":"venue"
},
  "geometry": {"coordinates":[-4.4112710953,36.7265396118],"type":"Point"}
}