{
  "type": "Feature",
  "properties": {
    "addr:full":"Calle de Gaztambide, 6 Madrid Madrid 28015",
    "addr:housenumber":"6",
    "addr:postcode":"28015",
    "addr:street":"Calle De Gaztambide",
    "iso:country":"ES",
    "sg:address":"Calle de Gaztambide, 6",
    "sg:city":"Madrid",
    "sg:orig_category":"Librer\u00cdas",
    "sg:phone":"+34 915 49 88 21",
    "sg:postcode":"28015",
    "sg:province":"Madrid",
    "sg:website":"www.libreriaagaztambide.com",
    "wof:name":"Libreria Gaztambide S.l.",
    "wof:placetype":"venue"
},
  "geometry": {"coordinates":[-3.7157287598,40.4312477112],"type":"Point"}
}