{
  "type": "Feature",
  "properties": {
    "addr:full":"Poli Poligono Louzaneta, S/n Lugo Lugo 27297",
    "addr:housenumber":"s / n",
    "addr:postcode":"27297",
    "addr:street":"Poligono Louzaneta",
    "iso:country":"ES",
    "sg:address":"Poli Poligono Louzaneta, S/n",
    "sg:city":"Lugo",
    "sg:orig_category":"Alimentaci\u00d3n General (al Por Mayor)",
    "sg:phone":"+34 982 25 54 32",
    "sg:postcode":"27297",
    "sg:province":"Lugo",
    "wof:name":"Agris Sociedad Cooperativa Galega",
    "wof:placetype":"venue"
},
  "geometry": {"coordinates":[-7.5951576233,43.0050773621],"type":"Point"}
}