{
  "type": "Feature",
  "properties": {
    "iso:country":"ES",
    "sg:address":"Carr Alemanya, 35",
    "sg:city":"Igualada",
    "sg:orig_category":"Fabricaci\u00d3n De Su\u00c9ters Y Chalecos De Punto",
    "sg:phone":"+34 938 04 21 43",
    "sg:postcode":"08700",
    "sg:province":"Barcelona",
    "wof:name":"Piernas Feliu Carlos",
    "wof:placetype":"venue"
},
  "geometry": {"coordinates":[1.6307140589,41.5862731934],"type":"Point"}
}