{
  "type": "Feature",
  "properties": {
    "addr:full":"Calle de Jacinto Benavente, 5 Hellin Albacete 02400",
    "addr:housenumber":"5",
    "addr:postcode":"02400",
    "addr:street":"Calle De Jacinto Benavente",
    "iso:country":"ES",
    "sg:address":"Calle de Jacinto Benavente, 5",
    "sg:city":"Hellin",
    "sg:orig_category":"Transporte En General",
    "sg:phone":"+34 967 54 32 45",
    "sg:postcode":"02400",
    "sg:province":"Albacete",
    "wof:name":"Supermercado Hijos De Charo S.l.l.",
    "wof:placetype":"venue"
},
  "geometry": {"coordinates":[-1.6900105476,38.5070724487],"type":"Point"}
}