{
  "type": "Feature",
  "properties": {
    "iso:country":"ES",
    "sg:address":"Carrer de Llibertat, 27",
    "sg:city":"Castelldefels",
    "sg:orig_category":"Peluquer\u00cdas, Peluquer\u00cda Mixta",
    "sg:phone":"+34 936 36 68 98",
    "sg:postcode":"08860",
    "sg:province":"Barcelona",
    "wof:name":"Blanco Membrive Eva",
    "wof:placetype":"venue"
},
  "geometry": {"coordinates":[1.9761389494,41.2779693604],"type":"Point"}
}