{
  "type": "Feature",
  "properties": {
    "iso:country":"ES",
    "sg:address":"Calle de Canovas, 16",
    "sg:city":"Zaragoza",
    "sg:orig_category":"Instalaci\u00d3n, Reparaci\u00d3n De Ascensores Y Montacargas",
    "sg:phone":"+34 976 22 87 22",
    "sg:postcode":"50004",
    "sg:province":"Zaragoza",
    "sg:website":"www.otis.com",
    "wof:name":"Zardoya Otis S. A.",
    "wof:placetype":"venue"
},
  "geometry": {"coordinates":[-0.8917300105,41.6478805542],"type":"Point"}
}