{
  "type": "Feature",
  "properties": {
    "iso:country":"ES",
    "sg:address":"Calle de Lepanto, S/n",
    "sg:city":"Caniles",
    "sg:orig_category":"Empresas De Demolici\u00d3n",
    "sg:phone":"+34 958 86 82 54",
    "sg:postcode":"18810",
    "sg:province":"Granada",
    "wof:name":"Martinez Ramirez Fernando",
    "wof:placetype":"venue"
},
  "geometry": {"coordinates":[-2.7265241146,37.4370536804],"type":"Point"}
}