{
  "type": "Feature",
  "properties": {
    "iso:country":"ES",
    "sg:address":"Calle de Santiago, 21",
    "sg:city":"Granada",
    "sg:orig_category":"Ingenier\u00cda, Centros De Estudios (diversos)",
    "sg:phone":"+34 958 22 45 57",
    "sg:postcode":"18009",
    "sg:province":"Granada",
    "wof:name":"Crocus Tecnicos Consultores S.l.",
    "wof:placetype":"venue"
},
  "geometry": {"coordinates":[-3.5931260586,37.1725082397],"type":"Point"}
}