{
  "type": "Feature",
  "properties": {
    "addr:full":"Calle de Hilarion Eslava, 17 Elda Alicante 03600",
    "addr:housenumber":"17",
    "addr:postcode":"03600",
    "addr:street":"Calle De Hilarion Eslava",
    "iso:country":"ES",
    "sg:address":"Calle de Hilarion Eslava, 17",
    "sg:city":"Elda",
    "sg:orig_category":"M\u00c9dicos: Cirug\u00cda Ortop\u00c9dica Y Traumatolog\u00cda",
    "sg:phone":"+34 965 39 17 64",
    "sg:postcode":"03600",
    "sg:province":"Alicante",
    "wof:name":"Jorda Gisbert Fernando",
    "wof:placetype":"venue"
},
  "geometry": {"coordinates":[-0.7921550274,38.4765968323],"type":"Point"}
}