{
  "type": "Feature",
  "properties": {
    "addr:full":"Calle de Alarcon Lujan, 4 Malaga M\u00e1laga 29005",
    "addr:housenumber":"4",
    "addr:postcode":"29005",
    "addr:street":"Calle De;Lujan;Ma\u0301Laga",
    "iso:country":"ES",
    "sg:address":"Calle de Alarcon Lujan, 4",
    "sg:city":"Malaga",
    "sg:orig_category":"Bazares, Art\u00cdculos De Limpieza Y De Cocina (al Por Menor)",
    "sg:phone":"+34 952 22 02 63",
    "sg:postcode":"29005",
    "sg:province":"M\u00e1laga",
    "wof:name":"Jaime Martin Juan",
    "wof:placetype":"venue"
},
  "geometry": {"coordinates":[-4.4227252007,36.7188949585],"type":"Point"}
}