{
  "type": "Feature",
  "properties": {
    "iso:country":"ES",
    "sg:address":"Calle de Pantoja, 5",
    "sg:city":"Madrid",
    "sg:orig_category":"Venta, Colocaci\u00d3n De Moquetas, Revestimiento De Suelos Y De Paredes",
    "sg:phone":"+34 914 16 88 95",
    "sg:postcode":"28002",
    "sg:province":"Madrid",
    "wof:name":"Grupo Ever S.a.",
    "wof:placetype":"venue"
},
  "geometry": {"coordinates":[-3.6706180573,40.4473495483],"type":"Point"}
}