{
  "type": "Feature",
  "properties": {
    "iso:country":"ES",
    "sg:address":"Carrer de Turonet, 7",
    "sg:city":"Fonts",
    "sg:orig_category":"Agencias Y Agentes Comerciales, Representantes",
    "sg:phone":"+34 937 85 70 62",
    "sg:postcode":"08228",
    "sg:province":"Barcelona",
    "wof:name":"Lopez Botella Alejandro",
    "wof:placetype":"venue"
},
  "geometry": {"coordinates":[2.0367279053,41.533531189],"type":"Point"}
}