{
  "type": "Feature",
  "properties": {
    "iso:country":"ES",
    "sg:address":"San Leonardo, 4",
    "sg:city":"Albox",
    "sg:orig_category":"Asociaciones Y Clubs Deportivos",
    "sg:phone":"+34 950 12 10 75",
    "sg:postcode":"04800",
    "sg:province":"Almer\u00eda",
    "wof:name":"Juan Bautista Naverrete S.l.",
    "wof:placetype":"venue"
},
  "geometry": {"coordinates":[-2.1402580738,37.3875198364],"type":"Point"}
}