{
  "type": "Feature",
  "properties": {
    "addr:full":"Carrer de Malgrat, 97 Barcelona Barcelona 08016",
    "addr:housenumber":"97",
    "addr:postcode":"08016",
    "addr:street":"Carrer De Malgrat",
    "iso:country":"ES",
    "sg:address":"Carrer de Malgrat, 97",
    "sg:city":"Barcelona",
    "sg:orig_category":"Electricidad, Electr\u00d3nica: Suministros (al Por Menor)",
    "sg:phone":"+34 934 08 00 96",
    "sg:postcode":"08016",
    "sg:province":"Barcelona",
    "wof:name":"Componentes Y Logistica Electronica S.l.",
    "wof:placetype":"venue"
},
  "geometry": {"coordinates":[2.1797549725,41.43201828],"type":"Point"}
}