{
  "type": "Feature",
  "properties": {
    "iso:country":"ES",
    "sg:address":"Calle de Hilario Marco, 85",
    "sg:city":"Cazorla",
    "sg:orig_category":"Agentes Generales De Seguros",
    "sg:phone":"+34 953 72 17 55",
    "sg:postcode":"23470",
    "sg:province":"Ja\u00e9n",
    "wof:name":"Mallenco Diaz Francisco",
    "wof:placetype":"venue"
},
  "geometry": {"coordinates":[-3.0047590733,37.9159011841],"type":"Point"}
}