{
  "type": "Feature",
  "properties": {
    "iso:country":"ES",
    "sg:address":"Calle de Jose Murphy, 2",
    "sg:city":"Santa Cruz De Tenerife",
    "sg:orig_category":"Instalaci\u00d3n De Sanitarios",
    "sg:phone":"+34 922 24 50 51",
    "sg:postcode":"38002",
    "sg:province":"Santa Cruz De Tenerife",
    "wof:name":"Trujillo Bencomo Ibrahim",
    "wof:placetype":"venue"
},
  "geometry": {"coordinates":[-16.2500324249,28.4672050476],"type":"Point"}
}