{
  "type": "Feature",
  "properties": {
    "iso:country":"ES",
    "sg:address":"La Fana(roces), S/n",
    "sg:city":"Gijon",
    "sg:orig_category":"Agentes, Concesionarios Y Sucursales De Veh\u00cdculos",
    "sg:phone":"+34 985 16 88 01",
    "sg:postcode":"33...",
    "sg:province":"Asturias",
    "wof:name":"Astur Wagen S.a.",
    "wof:placetype":"venue"
},
  "geometry": {"coordinates":[-5.6619262695,43.5452613831],"type":"Point"}
}