{
  "type": "Feature",
  "properties": {
    "iso:country":"ES",
    "sg:address":"Av Reina Maria Cristina, 22",
    "sg:city":"Tarragona",
    "sg:orig_category":"Centros M\u00c9dicos Y Sociales, Dispensarios",
    "sg:phone":"+34 977 21 72 93",
    "sg:postcode":"43002",
    "sg:province":"Tarragona",
    "wof:name":"Institut Pere Mata S.a.",
    "wof:placetype":"venue"
},
  "geometry": {"coordinates":[1.2522070408,41.1187324524],"type":"Point"}
}