{
  "type": "Feature",
  "properties": {
    "addr:full":"Calle de Beatriz De Bobadilla, 1 Madrid Madrid 28040",
    "addr:housenumber":"1",
    "addr:postcode":"28040",
    "addr:street":"Calle De Beatriz De Bobadilla",
    "iso:country":"ES",
    "sg:address":"Calle de Beatriz De Bobadilla, 1",
    "sg:city":"Madrid",
    "sg:orig_category":"Promotores Constructores",
    "sg:phone":"+34 915 33 00 25",
    "sg:postcode":"28040",
    "sg:province":"Madrid",
    "wof:name":"Puldain S. A.",
    "wof:placetype":"venue"
},
  "geometry": {"coordinates":[-3.7140803337,40.4469413757],"type":"Point"}
}