{
  "type": "Feature",
  "properties": {
    "addr:full":"Calle de Diputacion, 1 Olvera C\u00e1diz 11690",
    "addr:housenumber":"1",
    "addr:postcode":"11690",
    "addr:street":"Calle De Diputacion;Ca\u0301Diz",
    "iso:country":"ES",
    "sg:address":"Calle de Diputacion, 1",
    "sg:city":"Olvera",
    "sg:orig_category":"\u00d3ptica: Instrumentos (fabricaci\u00d3n)",
    "sg:phone":"+34 956 13 01 27",
    "sg:postcode":"11690",
    "sg:province":"C\u00e1diz",
    "wof:name":"Diaz Mu\u00f1oz Juan Antonio",
    "wof:placetype":"venue"
},
  "geometry": {"coordinates":[-5.2579441071,36.9353866577],"type":"Point"}
}