{
  "type": "Feature",
  "properties": {
    "addr:full":"Carr Del Dos De Maig, 54 Ontinyent Valencia 46870",
    "addr:housenumber":"54",
    "addr:postcode":"46870",
    "addr:street":"Carr Del Dos De Maig",
    "iso:country":"ES",
    "sg:address":"Carr Del Dos De Maig, 54",
    "sg:city":"Ontinyent",
    "sg:orig_category":"Textil",
    "sg:phone":"+34 962 38 42 55",
    "sg:postcode":"46870",
    "sg:province":"Valencia",
    "wof:name":"Noel Moda Joven Sll",
    "wof:placetype":"venue"
},
  "geometry": {"coordinates":[-0.6030989885,38.8258895874],"type":"Point"}
}