{
  "type": "Feature",
  "properties": {
    "iso:country":"ES",
    "sg:address":"Urbanizacion Los Olivos, S/n",
    "sg:city":"Rincon Victoria",
    "sg:orig_category":"Colchones (fabricaci\u00d3n, Al Por Mayor, Al Por Menor)",
    "sg:phone":"+34 952 97 26 70",
    "sg:postcode":"29730",
    "sg:province":"M\u00e1laga",
    "wof:name":"Comercial Rujami S.l.",
    "wof:placetype":"venue"
},
  "geometry": {"coordinates":[-4.2807641029,36.714641571],"type":"Point"}
}