{
  "type": "Feature",
  "properties": {
    "addr:full":"Tarragona, 2 Cabrera Mar Barcelona 08349",
    "addr:housenumber":"2",
    "addr:postcode":"08349",
    "addr:street":"Tarragona",
    "iso:country":"ES",
    "sg:address":"Tarragona, 2",
    "sg:city":"Cabrera Mar",
    "sg:orig_category":"Grafistas",
    "sg:phone":"+34 937 59 41 63",
    "sg:postcode":"08349",
    "sg:province":"Barcelona",
    "wof:name":"Peidro Ferraro Carles",
    "wof:placetype":"venue"
},
  "geometry": {"coordinates":[2.3933050632,41.5273513794],"type":"Point"}
}