{
  "type": "Feature",
  "properties": {
    "addr:full":"Avda Fernandez Ladreda, 33 Segovia Segovia 40002",
    "addr:housenumber":"33",
    "addr:postcode":"40002",
    "addr:street":"Avda Fernandez Ladreda",
    "iso:country":"ES",
    "sg:address":"Avda Fernandez Ladreda, 33",
    "sg:city":"Segovia",
    "sg:orig_category":"Quincaller\u00cda (al Por Menor)",
    "sg:phone":"+34 921 42 57 02",
    "sg:postcode":"40002",
    "sg:province":"Segovia",
    "sg:website":"www.paginasamarillas.es",
    "wof:name":"Suministros Industriales Y Agricola",
    "wof:placetype":"venue"
},
  "geometry": {"coordinates":[-4.1198019981,40.9454154968],"type":"Point"}
}