{
  "type": "Feature",
  "properties": {
    "addr:full":"Finca Olmillo, S/n Fuente-alamo Albacete 02651",
    "addr:housenumber":"s / n",
    "addr:postcode":"02651",
    "iso:country":"ES",
    "sg:address":"Finca Olmillo, S/n",
    "sg:city":"Fuente-alamo",
    "sg:orig_category":"Agricultura: Abastecimiento Y Cosechado (negocio)",
    "sg:phone":"+34 967 58 80 41",
    "sg:postcode":"02651",
    "sg:province":"Albacete",
    "wof:name":"Francisco Bernat Izquierdo Y Otros Cdad",
    "wof:placetype":"venue"
},
  "geometry": {"coordinates":[-1.4333479404,38.6902923584],"type":"Point"}
}