{
  "type": "Feature",
  "properties": {
    "addr:full":"Calle de Fuente (la), 7 Torrejon Rey Guadalajara 19174",
    "addr:housenumber":"7",
    "addr:postcode":"19174",
    "addr:street":"Calle De Fuente La;Rey",
    "iso:country":"ES",
    "sg:address":"Calle de Fuente (la), 7",
    "sg:city":"Torrejon Rey",
    "sg:orig_category":"Frutas, Legumbres Frescas Y Tempranas (al Por Menor)",
    "sg:phone":"+34 949 33 95 45",
    "sg:postcode":"19174",
    "sg:province":"Guadalajara",
    "wof:name":"Barbacid Martin Antonio",
    "wof:placetype":"venue"
},
  "geometry": {"coordinates":[-3.336879015,40.6445465088],"type":"Point"}
}