{
  "type": "Feature",
  "properties": {
    "addr:full":"Calle de San Francisco, 21 Talavera Reina Toledo 45600",
    "addr:housenumber":"21",
    "addr:postcode":"45600",
    "addr:street":"Calle De San Francisco",
    "iso:country":"ES",
    "sg:address":"Calle de San Francisco, 21",
    "sg:city":"Talavera Reina",
    "sg:orig_category":"Panader\u00cdas, Panader\u00cdas",
    "sg:phone":"+34 925 80 55 16",
    "sg:postcode":"45600",
    "sg:province":"Toledo",
    "wof:name":"Ramon Alcaide Alfredo",
    "wof:placetype":"venue"
},
  "geometry": {"coordinates":[-4.8299269676,39.9612197876],"type":"Point"}
}