{
  "type": "Feature",
  "properties": {
    "iso:country":"ES",
    "sg:address":"Calle de Camino Real, 111",
    "sg:city":"Vilches",
    "sg:classifiers":[
        {
            "category":"Taxi",
            "type":"Transportation"
        }
    ],
    "sg:phone":"+34 953 63 07 55",
    "sg:postcode":"23220",
    "sg:province":"Ja\u00e9n",
    "wof:name":"Lopez Gonzalez Juan Carlos",
    "wof:placetype":"venue"
},
  "geometry": {"coordinates":[-3.51461339,38.2123794556],"type":"Point"}
}