{
  "type": "Feature",
  "properties": {
    "iso:country":"ES",
    "sg:address":"Calle de Lorenzo Solano Tendero, 7",
    "sg:city":"Madrid",
    "sg:orig_category":"Cine: Pel\u00cdculas Educativas, Industriales Y Publicitarias (producci\u00d3n)",
    "sg:phone":"+34 917 13 11 41",
    "sg:postcode":"28043",
    "sg:province":"Madrid",
    "wof:name":"Group Films Latino S.l.",
    "wof:placetype":"venue"
},
  "geometry": {"coordinates":[-3.6528859138,40.4531974792],"type":"Point"}
}