{
  "type": "Feature",
  "properties": {
    "addr:full":"Pase Pinar, 5 Rozas De Madrid Madrid 28230",
    "addr:housenumber":"5",
    "addr:postcode":"28230",
    "addr:street":"Pinar",
    "iso:country":"ES",
    "sg:address":"Pase Pinar, 5",
    "sg:city":"Rozas De Madrid",
    "sg:orig_category":"Arquitectos",
    "sg:phone":"+34 913 07 65 98",
    "sg:postcode":"28230",
    "sg:province":"Madrid",
    "wof:name":"Agrupacion Cardiel Arquitectos S.l.",
    "wof:placetype":"venue"
},
  "geometry": {"coordinates":[-3.8719038963,40.4961738586],"type":"Point"}
}