{
  "type": "Feature",
  "properties": {
    "addr:full":"Calle de Ametzaga\u00d1a, 55 Donostia-san Sebastian Guip\u00f9zcoa 20012",
    "addr:housenumber":"55",
    "addr:postcode":"20012",
    "addr:street":"Calle De Ametzagan\u0303A",
    "iso:country":"ES",
    "sg:address":"Calle de Ametzaga\u00d1a, 55",
    "sg:city":"Donostia-san Sebastian",
    "sg:orig_category":"Molduras, Junquillos, Listones Y Molduras Perforadas",
    "sg:phone":"+34 943 27 18 18",
    "sg:postcode":"20012",
    "sg:province":"Guip\u00f9zcoa",
    "wof:name":"Litago Montori Rita",
    "wof:placetype":"venue"
},
  "geometry": {"coordinates":[-1.9669295549,43.3182487488],"type":"Point"}
}