{
  "type": "Feature",
  "properties": {
    "addr:full":"Calle de Gipuzkoa, 11 San Vicente De Barakaldo Vizcaya 48901",
    "addr:housenumber":"11",
    "addr:postcode":"48901",
    "addr:street":"Calle De Gipuzkoa",
    "iso:country":"ES",
    "sg:address":"Calle de Gipuzkoa, 11",
    "sg:city":"San Vicente De Barakaldo",
    "sg:orig_category":"Inmobiliaria (agencias)",
    "sg:phone":"+34 944 38 00 52",
    "sg:postcode":"48901",
    "sg:province":"Vizcaya",
    "wof:name":"Estate Borde S.l.",
    "wof:placetype":"venue"
},
  "geometry": {"coordinates":[-2.9869499207,43.2949752808],"type":"Point"}
}