{
  "type": "Feature",
  "properties": {
    "addr:full":"C. Morcillo, 43 Gojar Granada 18150",
    "addr:housenumber":"43",
    "addr:postcode":"18150",
    "addr:street":"Morcillo",
    "iso:country":"ES",
    "sg:address":"C. Morcillo, 43",
    "sg:city":"Gojar",
    "sg:orig_category":"Doctores En Medicina",
    "sg:phone":"+34 958 59 79 03",
    "sg:postcode":"18150",
    "sg:province":"Granada",
    "wof:name":"Molina Moreno Manuel",
    "wof:placetype":"venue"
},
  "geometry": {"coordinates":[-3.6036090851,37.1015357971],"type":"Point"}
}