{
  "type": "Feature",
  "properties": {
    "iso:country":"ES",
    "sg:address":"Calle de Prado Tuerto, 7",
    "sg:city":"Zamora",
    "sg:orig_category":"Elementos Para Suelos Prefabricados",
    "sg:phone":"+34 980 52 48 54",
    "sg:postcode":"49019",
    "sg:province":"Zamora",
    "wof:name":"Juanes Casta\u00f1o Angel",
    "wof:placetype":"venue"
},
  "geometry": {"coordinates":[-5.7346029282,41.5075531006],"type":"Point"}
}