{
  "type": "Feature",
  "properties": {
    "iso:country":"ES",
    "sg:address":"Calle de Orense, 12",
    "sg:city":"Madrid",
    "sg:orig_category":"Trabajos De Aislamiento T\u00c9rmico Y Ac\u00dastico",
    "sg:phone":"+34 915 56 57 24",
    "sg:postcode":"28020",
    "sg:province":"Madrid",
    "wof:name":"Aislamientos Termicos Y Frigorificos S.a.",
    "wof:placetype":"venue"
},
  "geometry": {"coordinates":[-3.6952986717,40.4490852356],"type":"Point"}
}