{
  "type": "Feature",
  "properties": {
    "iso:country":"ES",
    "sg:address":"Calle de Corredera, 3",
    "sg:city":"Fuente Obejuna",
    "sg:orig_category":"Florister\u00cdas",
    "sg:phone":"+34 957 58 52 50",
    "sg:postcode":"14290",
    "sg:province":"C\u00f3rdoba",
    "wof:name":"Perez Gonzalez Carmen",
    "wof:placetype":"venue"
},
  "geometry": {"coordinates":[-5.41877985,38.2665100098],"type":"Point"}
}