{
  "type": "Feature",
  "properties": {
    "iso:country":"ES",
    "sg:address":"Pol. 4, S/n",
    "sg:city":"Maria De La Salut",
    "sg:orig_category":"Charcuter\u00cdas (al Por Mayor)",
    "sg:phone":"+34 971 52 57 17",
    "sg:postcode":"07519",
    "sg:province":"Islas Baleares",
    "wof:name":"Embotits Matas S.l.",
    "wof:placetype":"venue"
},
  "geometry": {"coordinates":[3.0761051178,39.6650886536],"type":"Point"}
}