{
  "type": "Feature",
  "properties": {
    "addr:full":"Carr Riu Vinalopo, 3 Pai I Capellans Valencia 46930",
    "addr:housenumber":"3",
    "addr:postcode":"46930",
    "addr:street":"Carr Riu Vinalopo",
    "iso:country":"ES",
    "sg:address":"Carr Riu Vinalopo, 3",
    "sg:city":"Pai I Capellans",
    "sg:orig_category":"Pintura, Barniz, Productos Asimilables (fabricaci\u00d3n, Al Por Mayor)",
    "sg:phone":"+34 961 59 72 90",
    "sg:postcode":"46930",
    "sg:province":"Valencia",
    "wof:name":"Ppg Iberica S.a.",
    "wof:placetype":"venue"
},
  "geometry": {"coordinates":[-0.4419890046,39.482711792],"type":"Point"}
}