{
  "type": "Feature",
  "properties": {
    "iso:country":"ES",
    "sg:address":"Carrer de Maestrat, 15",
    "sg:city":"Sabadell",
    "sg:orig_category":"Fabricaci\u00d3n, Distribuci\u00d3n De Material Para La Climatizaci\u00d3n, Aireaci\u00d3n Y Ventilaci\u00d3n",
    "sg:phone":"+34 937 17 27 12",
    "sg:postcode":"08208",
    "sg:province":"Barcelona",
    "wof:name":"Clicon S.c.c.l.",
    "wof:placetype":"venue"
},
  "geometry": {"coordinates":[2.1023900509,41.5621414185],"type":"Point"}
}