{
  "type": "Feature",
  "properties": {
    "addr:full":"Santamaria-andre Mari Kalea, 22 Ordizia Guip\u00f9zcoa 20240",
    "addr:housenumber":"22",
    "addr:postcode":"20240",
    "addr:street":"Mari Kalea;Guipu\u0300Zcoa",
    "iso:country":"ES",
    "sg:address":"Santamaria-andre Mari Kalea, 22",
    "sg:city":"Ordizia",
    "sg:orig_category":"Laboratorios Y Trabajos De Fotograf\u00cda, V\u00cddeo Y Cine",
    "sg:phone":"+34 943 80 54 43",
    "sg:postcode":"20240",
    "sg:province":"Guip\u00f9zcoa",
    "wof:name":"Carrizo Alcoba Francisco Javier",
    "wof:placetype":"venue"
},
  "geometry": {"coordinates":[-2.1773040295,43.0538711548],"type":"Point"}
}