{
  "type": "Feature",
  "properties": {
    "addr:full":"Fuengirola, Km. 0000,8 Mijas M\u00e1laga 29650",
    "addr:postcode":"29650",
    "addr:street":"Fuengirola Km. 0000,8;Ma\u0301Laga",
    "iso:country":"ES",
    "sg:address":"Fuengirola, Km. 0000,8",
    "sg:city":"Mijas",
    "sg:orig_category":"Centros M\u00c9dicos Y Sociales, Dispensarios",
    "sg:phone":"+34 952 48 60 10",
    "sg:postcode":"29650",
    "sg:province":"M\u00e1laga",
    "wof:name":"Amarant Consult S. A.",
    "wof:placetype":"venue"
},
  "geometry": {"coordinates":[-4.684296608,36.5013046265],"type":"Point"}
}