{
  "type": "Feature",
  "properties": {
    "addr:full":"Calle de Manuel Castellanos, 12 Valencia Valencia 46020",
    "addr:housenumber":"12",
    "addr:postcode":"46020",
    "addr:street":"Calle De Manuel Castellanos",
    "iso:country":"ES",
    "sg:address":"Calle de Manuel Castellanos, 12",
    "sg:city":"Valencia",
    "sg:orig_category":"Cooperativas Agr\u00cdcolas",
    "sg:phone":"+34 963 69 56 71",
    "sg:postcode":"46020",
    "sg:province":"Valencia",
    "wof:name":"Cooperativa Obrera De Consumo La Prosperidad",
    "wof:placetype":"venue"
},
  "geometry": {"coordinates":[-0.3610869944,39.4869384766],"type":"Point"}
}