{
  "type": "Feature",
  "properties": {
    "iso:country":"ES",
    "sg:address":"Carrer de Gurb, 1",
    "sg:city":"Vic",
    "sg:orig_category":"Ropa Y Accesorios",
    "sg:phone":"+34 938 83 35 29",
    "sg:postcode":"08500",
    "sg:province":"Barcelona",
    "wof:name":"Urlex Distribuciones S.l.",
    "wof:placetype":"venue"
},
  "geometry": {"coordinates":[2.2533791065,41.9312667847],"type":"Point"}
}