{
  "type": "Feature",
  "properties": {
    "addr:full":"Carrer de Josep Umbert, 43 Granollers Barcelona 08402",
    "addr:housenumber":"43",
    "addr:postcode":"08402",
    "addr:street":"Carrer De Josep Umbert",
    "iso:country":"ES",
    "sg:address":"Carrer de Josep Umbert, 43",
    "sg:city":"Granollers",
    "sg:orig_category":"Centros Empresariales",
    "sg:phone":"+34 938 70 50 25",
    "sg:postcode":"08402",
    "sg:province":"Barcelona",
    "wof:name":"Eurofirms Ett S.l.",
    "wof:placetype":"venue"
},
  "geometry": {"coordinates":[2.2920980453,41.6050643921],"type":"Point"}
}