{
  "type": "Feature",
  "properties": {
    "addr:full":"Trva Sorolla, 28 Castalla Alicante 03420",
    "addr:housenumber":"28",
    "addr:postcode":"03420",
    "addr:street":"Trva Sorolla",
    "iso:country":"ES",
    "sg:address":"Trva Sorolla, 28",
    "sg:city":"Castalla",
    "sg:orig_category":"Comercio De Mobiliario De Oficina",
    "sg:phone":"+34 965 56 15 04",
    "sg:postcode":"03420",
    "sg:province":"Alicante",
    "wof:name":"Merlos Bautista Rosa",
    "wof:placetype":"venue"
},
  "geometry": {"coordinates":[-0.6749590039,38.5923881531],"type":"Point"}
}