{
  "type": "Feature",
  "properties": {
    "iso:country":"ES",
    "sg:address":"Calle de Pelayo, 30",
    "sg:city":"Madrid",
    "sg:orig_category":"Restaurantes",
    "sg:phone":"+34 915 21 78 62",
    "sg:postcode":"28004",
    "sg:province":"Madrid",
    "wof:name":"Barnola Cifuentes Mariana",
    "wof:placetype":"venue"
},
  "geometry": {"coordinates":[-3.6981799603,40.4229125977],"type":"Point"}
}