{
  "type": "Feature",
  "properties": {
    "addr:full":"Carrer de Arc De Sant Marti, 53 Palma Islas Baleares 07011",
    "addr:housenumber":"53",
    "addr:postcode":"07011",
    "addr:street":"Carrer De Arc De Sant Marti",
    "iso:country":"ES",
    "sg:address":"Carrer de Arc De Sant Marti, 53",
    "sg:city":"Palma",
    "sg:orig_category":"Electricidad: Instalaciones Industriales",
    "sg:phone":"+34 971 73 55 32",
    "sg:postcode":"07011",
    "sg:province":"Islas Baleares",
    "wof:name":"Electrificaciones Y Montajes De Baleares S.a.",
    "wof:placetype":"venue"
},
  "geometry": {"coordinates":[2.6347060204,39.5836105347],"type":"Point"}
}