{
  "type": "Feature",
  "properties": {
    "iso:country":"ES",
    "sg:address":"Calle de Capitan Pe\u00d1as, 30",
    "sg:city":"Avila",
    "sg:orig_category":"Arquitectos",
    "sg:phone":"+34 920 22 51 70",
    "sg:postcode":"05003",
    "sg:province":"\u00c1vila",
    "wof:name":"Garcia Garcia Angel",
    "wof:placetype":"venue"
},
  "geometry": {"coordinates":[-4.6893854141,40.6529083252],"type":"Point"}
}