{
  "type": "Feature",
  "properties": {
    "iso:country":"ES",
    "sg:address":"Calle de Lopez Gomez, 9",
    "sg:city":"Valladolid",
    "sg:orig_category":"Ense\u00d1anza Variada",
    "sg:phone":"+34 983 39 72 08",
    "sg:postcode":"47002",
    "sg:province":"Valladolid",
    "wof:name":"Iet-instituto De Ense\u00f1anzas Tecnicas C.b",
    "wof:placetype":"venue"
},
  "geometry": {"coordinates":[-4.7235989571,41.650554657],"type":"Point"}
}