{
  "type": "Feature",
  "properties": {
    "addr:full":"Calle de Linea, 3 Pozuelo De Alarcon Madrid 28224",
    "addr:housenumber":"3",
    "addr:postcode":"28224",
    "addr:street":"Calle De Linea",
    "iso:country":"ES",
    "sg:address":"Calle de Linea, 3",
    "sg:city":"Pozuelo De Alarcon",
    "sg:orig_category":"Promotores Constructores",
    "sg:phone":"+34 917 14 01 90",
    "sg:postcode":"28224",
    "sg:province":"Madrid",
    "wof:name":"Barocha S.l.",
    "wof:placetype":"venue"
},
  "geometry": {"coordinates":[-3.8169360161,40.4481468201],"type":"Point"}
}