{
  "type": "Feature",
  "properties": {
    "iso:country":"ES",
    "sg:address":"Av Valles, 484",
    "sg:city":"Terrassa",
    "sg:orig_category":"Zapatos (al Por Menor)",
    "sg:phone":"+34 937 83 18 47",
    "sg:postcode":"08227",
    "sg:province":"Barcelona",
    "wof:name":"Yorga S. A.",
    "wof:placetype":"venue"
},
  "geometry": {"coordinates":[2.0339388847,41.5629882812],"type":"Point"}
}