{
  "type": "Feature",
  "properties": {
    "addr:full":"Calle de Mercedes (las), 18 Arenas -areeta Vizcaya 48930",
    "addr:housenumber":"18;areeta",
    "addr:postcode":"48930",
    "addr:street":"Calle De Mercedes Las",
    "iso:country":"ES",
    "sg:address":"Calle de Mercedes (las), 18",
    "sg:city":"Arenas -areeta",
    "sg:orig_category":"Zapatos (al Por Menor)",
    "sg:phone":"+34 944 80 20 65",
    "sg:postcode":"48930",
    "sg:province":"Vizcaya",
    "wof:name":"Gandarias Zuazagoitia Maria",
    "wof:placetype":"venue"
},
  "geometry": {"coordinates":[-3.0143148899,43.3261146545],"type":"Point"}
}