{
  "type": "Feature",
  "properties": {
    "iso:country":"ES",
    "sg:address":"Av. Mar, S/n",
    "sg:city":"Garrucha",
    "sg:orig_category":"Inmobiliaria (agencias)",
    "sg:phone":"+34 950 39 70 60",
    "sg:postcode":"04630",
    "sg:province":"Almer\u00eda",
    "wof:name":"Alfoque S.l.",
    "wof:placetype":"venue"
},
  "geometry": {"coordinates":[-1.820828557,37.1851921082],"type":"Point"}
}