{
  "type": "Feature",
  "properties": {
    "iso:country":"ES",
    "sg:address":"Luga Puerto De Morro Jable, 1",
    "sg:city":"Morro Jable",
    "sg:orig_category":"Fabricaci\u00d3n De Muebles",
    "sg:phone":"+34 928 16 62 67",
    "sg:postcode":"35625",
    "sg:province":"Las Palmas",
    "wof:name":"Pe\u00f1a Rodriguez Fernando",
    "wof:placetype":"venue"
},
  "geometry": {"coordinates":[-14.3222913742,28.0607738495],"type":"Point"}
}