{
  "type": "Feature",
  "properties": {
    "iso:country":"ES",
    "sg:address":"Carrer de Sarda, 53",
    "sg:city":"Reus",
    "sg:orig_category":"Chapister\u00cda",
    "sg:phone":"+34 977 34 57 96",
    "sg:postcode":"43201",
    "sg:province":"Tarragona",
    "wof:name":"Pintura Y Decoracion De Automoviles Gomez Hnos S.l.",
    "wof:placetype":"venue"
},
  "geometry": {"coordinates":[1.1097849607,41.159488678],"type":"Point"}
}