{
  "type": "Feature",
  "properties": {
    "addr:full":"Avda Novelda, 101 Alacant Alicante 03009",
    "addr:housenumber":"101",
    "addr:postcode":"03009",
    "addr:street":"Avda Novelda",
    "iso:country":"ES",
    "sg:address":"Avda Novelda, 101",
    "sg:city":"Alacant",
    "sg:orig_category":"Motocicletas (agentes, Concesionarios)",
    "sg:phone":"+34 965 17 28 05",
    "sg:postcode":"03009",
    "sg:province":"Alicante",
    "wof:name":"Isidro Ruiz E Hijos S.l.",
    "wof:placetype":"venue"
},
  "geometry": {"coordinates":[-0.4952540994,38.3651847839],"type":"Point"}
}