{
  "type": "Feature",
  "properties": {
    "iso:country":"ES",
    "sg:address":"Calle de Lealtad, 12",
    "sg:city":"Santander",
    "sg:orig_category":"Promotores Constructores",
    "sg:phone":"+34 942 31 97 37",
    "sg:postcode":"39002",
    "sg:province":"Cantabria",
    "wof:name":"Anjuca S.l.",
    "wof:placetype":"venue"
},
  "geometry": {"coordinates":[-3.8083689213,43.4612388611],"type":"Point"}
}