{
  "type": "Feature",
  "properties": {
    "iso:country":"ES",
    "sg:address":"Calle de Plateria, 13",
    "sg:city":"Ecija",
    "sg:orig_category":"Estancos",
    "sg:phone":"+34 954 83 10 06",
    "sg:postcode":"41400",
    "sg:province":"Sevilla",
    "wof:name":"Borjas Mu\u00f1oz Jose",
    "wof:placetype":"venue"
},
  "geometry": {"coordinates":[-5.0786042213,37.5415534973],"type":"Point"}
}