{
  "type": "Feature",
  "properties": {
    "addr:full":"B. El Morralin-berron, 15 La Carrera Asturias 33186",
    "addr:housenumber":"15",
    "addr:postcode":"33186",
    "addr:street":"Morralin-Berron",
    "iso:country":"ES",
    "sg:address":"B. El Morralin-berron, 15",
    "sg:city":"La Carrera",
    "sg:orig_category":"Vinos Y Licores (venta Al Por Menor)",
    "sg:phone":"+34 985 74 03 14",
    "sg:postcode":"33186",
    "sg:province":"Asturias",
    "wof:name":"Montequin Laiz S.a.",
    "wof:placetype":"venue"
},
  "geometry": {"coordinates":[-5.7012858391,43.3833732605],"type":"Point"}
}