{
  "type": "Feature",
  "properties": {
    "iso:country":"ES",
    "sg:address":"Plaz Coso (el), 6",
    "sg:city":"Navarrete",
    "sg:orig_category":"Restaurantes",
    "sg:phone":"+34 941 44 05 64",
    "sg:postcode":"26370",
    "sg:province":"La Rioja",
    "wof:name":"El Molino S.c.",
    "wof:placetype":"venue"
},
  "geometry": {"coordinates":[-2.5627059937,42.4329109192],"type":"Point"}
}