{
  "type": "Feature",
  "properties": {
    "addr:full":"Carrer de Rambla, 17 Santa Perpetua De Mogoda Barcelona 08130",
    "addr:housenumber":"17",
    "addr:postcode":"08130",
    "addr:street":"Carrer De Rambla",
    "iso:country":"ES",
    "sg:address":"Carrer de Rambla, 17",
    "sg:city":"Santa Perpetua De Mogoda",
    "sg:orig_category":"Cajas De Ahorro",
    "sg:phone":"+34 935 60 01 04",
    "sg:postcode":"08130",
    "sg:province":"Barcelona",
    "sg:website":"www.lacaixa.es",
    "wof:name":"Caixa D'estalvis I Pensions De Barcelona",
    "wof:placetype":"venue"
},
  "geometry": {"coordinates":[2.1808729172,41.5349502563],"type":"Point"}
}