{
  "type": "Feature",
  "properties": {
    "iso:country":"ES",
    "sg:address":"Ctra Crevillente, S/n",
    "sg:city":"Aspe",
    "sg:classifiers":[
        {
            "category":"Professional",
            "subcategory":"Management & Consulting",
            "type":"Services"
        }
    ],
    "sg:phone":"+34 965 49 27 11",
    "sg:postcode":"03680",
    "sg:province":"Alicante",
    "sg:tags":[
        "asesor\u00cda",
        "en",
        "marketing"
    ],
    "wof:name":"Caldesu S.l.",
    "wof:placetype":"venue"
},
  "geometry": {"coordinates":[-0.7689840198,38.3471984863],"type":"Point"}
}