{
  "type": "Feature",
  "properties": {
    "iso:country":"ES",
    "sg:address":"Calle de Minimas, 27",
    "sg:city":"Daimiel",
    "sg:orig_category":"Promotores Constructores",
    "sg:phone":"+34 926 85 51 68",
    "sg:postcode":"13250",
    "sg:province":"Ciudad Real",
    "wof:name":"Construcciones Ivelsa Daimiel S.a.",
    "wof:placetype":"venue"
},
  "geometry": {"coordinates":[-3.610599041,39.0696411133],"type":"Point"}
}