{
  "type": "Feature",
  "properties": {
    "addr:full":"Calle de Honda, 4 Aspe Alicante 03680",
    "addr:housenumber":"4",
    "addr:postcode":"03680",
    "addr:street":"Calle De Honda",
    "iso:country":"ES",
    "sg:address":"Calle de Honda, 4",
    "sg:city":"Aspe",
    "sg:orig_category":"Notarios",
    "sg:phone":"+34 965 49 59 93",
    "sg:postcode":"03680",
    "sg:province":"Alicante",
    "wof:name":"Barnes Romero Luis",
    "wof:placetype":"venue"
},
  "geometry": {"coordinates":[-0.7697380185,38.3465385437],"type":"Point"}
}