{
  "type": "Feature",
  "properties": {
    "iso:country":"ES",
    "sg:address":"Calle de Elcano, 40",
    "sg:city":"Bilbao",
    "sg:orig_category":"M\u00c9dicos: Foniatr\u00cda Y Logopedia",
    "sg:phone":"+34 944 10 45 47",
    "sg:postcode":"48008",
    "sg:province":"Vizcaya",
    "sg:website":"www.bilboguia.com/medicofoniatra",
    "wof:name":"Ana Apellaniz Gonzalez",
    "wof:placetype":"venue"
},
  "geometry": {"coordinates":[-2.9324710369,43.2585220337],"type":"Point"}
}