{
  "type": "Feature",
  "properties": {
    "addr:full":"Calle de General Franco, S/n Cristianos Santa Cruz De Tenerife 38650",
    "addr:housenumber":"s / n",
    "addr:postcode":"38650",
    "addr:street":"Calle De General Franco",
    "iso:country":"ES",
    "sg:address":"Calle de General Franco, S/n",
    "sg:city":"Cristianos",
    "sg:orig_category":"Talleres De Corte Y Confecci\u00d3n",
    "sg:phone":"+34 922 75 04 87",
    "sg:postcode":"38650",
    "sg:province":"Santa Cruz De Tenerife",
    "wof:name":"Perez Amador Diego Manuel",
    "wof:placetype":"venue"
},
  "geometry": {"coordinates":[-16.7186546326,28.0511054993],"type":"Point"}
}