{
  "type": "Feature",
  "properties": {
    "addr:full":"Roca Verdura, 5 Tivissa Tarragona 43746",
    "addr:housenumber":"5",
    "addr:postcode":"43746",
    "iso:country":"ES",
    "sg:address":"Roca Verdura, 5",
    "sg:city":"Tivissa",
    "sg:orig_category":"Fabricaci\u00d3n, Venta De Cuadros, Accesorios Para Enmarcar",
    "sg:phone":"+34 977 41 80 10",
    "sg:postcode":"43746",
    "sg:province":"Tarragona",
    "wof:name":"Marcs Rojals S.c.p.",
    "wof:placetype":"venue"
},
  "geometry": {"coordinates":[0.7349410057,41.0436477661],"type":"Point"}
}