{
  "type": "Feature",
  "properties": {
    "addr:full":"Ctjo Arriba, 7 Navares Murcia 30410",
    "addr:housenumber":"7",
    "addr:postcode":"30410",
    "addr:street":"Arriba",
    "iso:country":"ES",
    "sg:address":"Ctjo Arriba, 7",
    "sg:city":"Navares",
    "sg:orig_category":"Mataderos Y Talleres De Despiezado",
    "sg:phone":"+34 968 70 43 66",
    "sg:postcode":"30410",
    "sg:province":"Murcia",
    "wof:name":"Perez Marin Jesus",
    "wof:placetype":"venue"
},
  "geometry": {"coordinates":[-1.9453239441,38.0200157166],"type":"Point"}
}