{
  "type": "Feature",
  "properties": {
    "iso:country":"ES",
    "sg:address":"Chantrea-txantreako, 6",
    "sg:city":"Iru\u00f1a",
    "sg:orig_category":"Farmacias",
    "sg:phone":"+34 948 12 65 70",
    "sg:postcode":"31015",
    "sg:province":"Navarra",
    "wof:name":"Urtasun Sanz Rosario",
    "wof:placetype":"venue"
},
  "geometry": {"coordinates":[-1.6305010319,42.829158783],"type":"Point"}
}