{
  "type": "Feature",
  "properties": {
    "iso:country":"ES",
    "sg:address":"Ctra. C. Ext. Ciento Cuatro, Km. 0007,5",
    "sg:city":"Villanueva Serena",
    "sg:orig_category":"Empresas De Limpieza",
    "sg:phone":"+34 924 14 70 44",
    "sg:postcode":"06700",
    "sg:province":"Badajoz",
    "wof:name":"Urbaser S.a.",
    "wof:placetype":"venue"
},
  "geometry": {"coordinates":[-5.7927408218,38.9731750488],"type":"Point"}
}