{
  "type": "Feature",
  "properties": {
    "iso:country":"ES",
    "sg:address":"Calle de Jaime Tercero, 17",
    "sg:city":"Madrid",
    "sg:orig_category":"Alumbrados",
    "sg:phone":"+34 914 79 54 57",
    "sg:postcode":"28011",
    "sg:province":"Madrid",
    "sg:website":"www.torresiluminacin.com",
    "wof:name":"Torres Junco Alberto",
    "wof:placetype":"venue"
},
  "geometry": {"coordinates":[-3.7310979366,40.4083938599],"type":"Point"}
}