{
  "type": "Feature",
  "properties": {
    "iso:country":"ES",
    "sg:address":"Avenida San Andres, 53",
    "sg:city":"Trobajo Camino",
    "sg:orig_category":"Escayola Y Productos De Escayola (fabricaci\u00d3n, Al Por Mayor)",
    "sg:phone":"+34 987 23 21 76",
    "sg:postcode":"24010",
    "sg:province":"Le\u00f3n",
    "wof:name":"Cuevas Villalo Jose Luis De Las",
    "wof:placetype":"venue"
},
  "geometry": {"coordinates":[-5.5905189514,42.6018981934],"type":"Point"}
}