{
  "type": "Feature",
  "properties": {
    "addr:full":"Calle de Romero De Torres, 29 Priego Cordoba C\u00f3rdoba 14800",
    "addr:housenumber":"29",
    "addr:postcode":"14800",
    "addr:street":"Calle De Romero De Torres;Cordoba Co\u0301Rdoba",
    "iso:country":"ES",
    "sg:address":"Calle de Romero De Torres, 29",
    "sg:city":"Priego Cordoba",
    "sg:orig_category":"Empresas De Carpinter\u00cda De Madera",
    "sg:phone":"+34 957 54 37 00",
    "sg:postcode":"14800",
    "sg:province":"C\u00f3rdoba",
    "wof:name":"Rodriguez Jurado Amador",
    "wof:placetype":"venue"
},
  "geometry": {"coordinates":[-4.2045288086,37.4413375854],"type":"Point"}
}