{
  "type": "Feature",
  "properties": {
    "addr:full":"Avgd Del Cami Nou, S/n Xirivella Valencia 46950",
    "addr:housenumber":"s / n",
    "addr:postcode":"46950",
    "addr:street":"Nou",
    "iso:country":"ES",
    "sg:address":"Avgd Del Cami Nou, S/n",
    "sg:city":"Xirivella",
    "sg:orig_category":"Lavado, Limpieza De Veh\u00cdculos",
    "sg:phone":"+34 963 83 41 25",
    "sg:postcode":"46950",
    "sg:province":"Valencia",
    "wof:name":"Rentat Xirivella",
    "wof:placetype":"venue"
},
  "geometry": {"coordinates":[-0.4368239939,39.4632453918],"type":"Point"}
}