{
  "type": "Feature",
  "properties": {
    "addr:full":"Calle de Cervantes, 15 Santander Cantabria 39001",
    "addr:housenumber":"15",
    "addr:postcode":"39001",
    "addr:street":"Calle De Cervantes",
    "iso:country":"ES",
    "sg:address":"Calle de Cervantes, 15",
    "sg:city":"Santander",
    "sg:orig_category":"Agencias De Viajes",
    "sg:phone":"+34 942 23 84 74",
    "sg:postcode":"39001",
    "sg:province":"Cantabria",
    "sg:website":"www.halconviajes.com",
    "wof:name":"Viajes Halcon S.a.",
    "wof:placetype":"venue"
},
  "geometry": {"coordinates":[-3.8111290932,43.4636993408],"type":"Point"}
}