{
  "type": "Feature",
  "properties": {
    "iso:country":"ES",
    "sg:address":"Calle de Tomas Conde, 8",
    "sg:city":"Cordoba",
    "sg:orig_category":"M\u00c9dicos: Cirug\u00cda Cardiovascular Y Tor\u00c1cica",
    "sg:phone":"+34 957 29 61 48",
    "sg:postcode":"14004",
    "sg:province":"C\u00f3rdoba",
    "wof:name":"Concha Ruiz Manuel",
    "wof:placetype":"venue"
},
  "geometry": {"coordinates":[-4.7823290825,37.8786315918],"type":"Point"}
}