{
  "type": "Feature",
  "properties": {
    "addr:full":"Av Paral.lel, 97 Barcelona Barcelona 08004",
    "addr:housenumber":"97",
    "addr:postcode":"08004",
    "addr:street":"Av Paral.Lel",
    "iso:country":"ES",
    "sg:address":"Av Paral.lel, 97",
    "sg:city":"Barcelona",
    "sg:orig_category":"Cajas De Ahorro",
    "sg:phone":"+34 934 41 25 18",
    "sg:postcode":"08004",
    "sg:province":"Barcelona",
    "wof:name":"Caixa D'estalvis Del Penedes",
    "wof:placetype":"venue"
},
  "geometry": {"coordinates":[2.1640200615,41.3749694824],"type":"Point"}
}