{
  "type": "Feature",
  "properties": {
    "iso:country":"ES",
    "sg:address":"Pl Pep Ventura, 2",
    "sg:city":"Badalona",
    "sg:orig_category":"Alimentaci\u00d3n General (al Por Menor)",
    "sg:phone":"+34 933 87 18 26",
    "sg:postcode":"08912",
    "sg:province":"Barcelona",
    "wof:name":"Yang  Maoli",
    "wof:placetype":"venue"
},
  "geometry": {"coordinates":[2.2398087978,41.4455718994],"type":"Point"}
}