{
  "type": "Feature",
  "properties": {
    "iso:country":"ES",
    "sg:address":"Calle de Malagon, 15",
    "sg:city":"Ciudad Real",
    "sg:orig_category":"Venta, Montaje De Neum\u00c1ticos",
    "sg:phone":"+34 926 21 67 74",
    "sg:postcode":"13005",
    "sg:province":"Ciudad Real",
    "wof:name":"Antonio Parre\u00f1o Leon Y Candido Heredia Marchan Cdad",
    "wof:placetype":"venue"
},
  "geometry": {"coordinates":[-3.9349737167,38.9746208191],"type":"Point"}
}