{
  "type": "Feature",
  "properties": {
    "addr:full":"Calle de Regidor Juan De Isla, 2 Segura Sierra Ja\u00e9n 23391",
    "addr:housenumber":"2",
    "addr:postcode":"23391",
    "addr:street":"Calle De Regidor Juan De Isla",
    "iso:country":"ES",
    "sg:address":"Calle de Regidor Juan De Isla, 2",
    "sg:city":"Segura Sierra",
    "sg:orig_category":"Cajas De Ahorro",
    "sg:phone":"+34 953 48 01 00",
    "sg:postcode":"23391",
    "sg:province":"Ja\u00e9n",
    "wof:name":"Unicaja",
    "wof:placetype":"venue"
},
  "geometry": {"coordinates":[-2.6828589439,38.4163322449],"type":"Point"}
}