{
  "type": "Feature",
  "properties": {
    "iso:country":"ES",
    "sg:address":"Pl Major, 19",
    "sg:city":"Vic",
    "sg:orig_category":"Lencer\u00cda Femenina, Corseter\u00cda, Trajes De Ba\u00d1o (al Por Menor)",
    "sg:phone":"+34 938 89 02 79",
    "sg:postcode":"08500",
    "sg:province":"Barcelona",
    "wof:name":"Domingo Alcazar Lidia",
    "wof:placetype":"venue"
},
  "geometry": {"coordinates":[2.2542159557,41.9309043884],"type":"Point"}
}