{
  "type": "Feature",
  "properties": {
    "addr:full":"Carrer de Escoles Pies, 70 Barcelona Barcelona 08017",
    "addr:housenumber":"70",
    "addr:postcode":"08017",
    "addr:street":"Carrer De Escoles Pies",
    "iso:country":"ES",
    "sg:address":"Carrer de Escoles Pies, 70",
    "sg:city":"Barcelona",
    "sg:orig_category":"Peluqueros: De Se\u00d1oras",
    "sg:phone":"+34 932 11 07 68",
    "sg:postcode":"08017",
    "sg:province":"Barcelona",
    "wof:name":"Suau Gil Maria Teresa",
    "wof:placetype":"venue"
},
  "geometry": {"coordinates":[2.131141901,41.4005088806],"type":"Point"}
}