{
  "type": "Feature",
  "properties": {
    "iso:country":"ES",
    "sg:address":"Avda Martin Alonso Pinzon, 10",
    "sg:city":"Huelva",
    "sg:orig_category":"Abogados",
    "sg:phone":"+34 959 24 77 05",
    "sg:postcode":"21003",
    "sg:province":"Huelva",
    "wof:name":"Martin Rodriguez Carmen",
    "wof:placetype":"venue"
},
  "geometry": {"coordinates":[-6.9490199089,37.2558746338],"type":"Point"}
}