{
  "type": "Feature",
  "properties": {
    "addr:full":"Calle de Estame\u00d1as, 1 Benavente Zamora 49600",
    "addr:housenumber":"1",
    "addr:postcode":"49600",
    "addr:street":"Calle De Estamen\u0303As",
    "iso:country":"ES",
    "sg:address":"Calle de Estame\u00d1as, 1",
    "sg:city":"Benavente",
    "sg:orig_category":"Fabricaci\u00d3n De Capiteles",
    "sg:phone":"+34 980 63 74 99",
    "sg:postcode":"49600",
    "sg:province":"Zamora",
    "wof:name":"Proteccion Solar Ladis Sl",
    "wof:placetype":"venue"
},
  "geometry": {"coordinates":[-5.6838340759,42.0034065247],"type":"Point"}
}