{
  "type": "Feature",
  "properties": {
    "addr:full":"San Francisco, 34 Iru\u00f1a Navarra 31001",
    "addr:housenumber":"34",
    "addr:postcode":"31001",
    "addr:street":"San Francisco",
    "iso:country":"ES",
    "sg:address":"San Francisco, 34",
    "sg:city":"Iru\u00f1a",
    "sg:orig_category":"Librer\u00cdas",
    "sg:phone":"+34 948 22 33 48",
    "sg:postcode":"31001",
    "sg:province":"Navarra",
    "wof:name":"Libreria Luquin S.l.",
    "wof:placetype":"venue"
},
  "geometry": {"coordinates":[-1.6488089561,42.8171615601],"type":"Point"}
}