{
  "type": "Feature",
  "properties": {
    "addr:full":"Pg Ramon Berenguer Iii, 63 Mataro Barcelona 08303",
    "addr:housenumber":"63",
    "addr:postcode":"08303",
    "addr:street":"Mataro Barcelona",
    "iso:country":"ES",
    "sg:address":"Pg Ramon Berenguer Iii, 63",
    "sg:city":"Mataro",
    "sg:orig_category":"Complementos De Vestir (al Por Menor)",
    "sg:phone":"+34 937 99 70 40",
    "sg:postcode":"08303",
    "sg:province":"Barcelona",
    "wof:name":"Flores Mendez E Hijos S.l.",
    "wof:placetype":"venue"
},
  "geometry": {"coordinates":[2.424216032,41.5368843079],"type":"Point"}
}