{
  "type": "Feature",
  "properties": {
    "addr:full":"Calle de Nazaries, 2 Andujar Ja\u00e9n 23740",
    "addr:housenumber":"2",
    "addr:postcode":"23740",
    "addr:street":"Calle De Nazaries",
    "iso:country":"ES",
    "sg:address":"Calle de Nazaries, 2",
    "sg:city":"Andujar",
    "sg:orig_category":"Molduras, Junquillos, Listones Y Molduras Perforadas",
    "sg:phone":"+34 953 51 06 80",
    "sg:postcode":"23740",
    "sg:province":"Ja\u00e9n",
    "wof:name":"Castro Elvira Carmen",
    "wof:placetype":"venue"
},
  "geometry": {"coordinates":[-4.0454230309,38.036605835],"type":"Point"}
}