{
  "type": "Feature",
  "properties": {
    "addr:full":"Calle de Hospital, 2 Puerto De Bejar Salamanca 37720",
    "addr:housenumber":"2",
    "addr:postcode":"37720",
    "addr:street":"Calle De Hospital",
    "iso:country":"ES",
    "sg:address":"Calle de Hospital, 2",
    "sg:city":"Puerto De Bejar",
    "sg:orig_category":"Asilos De Ancianos. Centros Privados",
    "sg:phone":"+34 923 41 42 77",
    "sg:postcode":"37720",
    "sg:province":"Salamanca",
    "wof:name":"Fundacion Nuestra Se\u00f1ora De La Asuncion/residencia Nuestra Se\u00f1ora De La Asuncion",
    "wof:placetype":"venue"
},
  "geometry": {"coordinates":[-97.78224945069999,45.7040786743],"type":"Point"}
}