{
  "type": "Feature",
  "properties": {
    "iso:country":"ES",
    "sg:address":"Av Cami Dels Capellans, 16",
    "sg:city":"Sitges",
    "sg:orig_category":"Motocicletas (agentes, Concesionarios)",
    "sg:phone":"+34 938 11 12 22",
    "sg:postcode":"08870",
    "sg:province":"Barcelona",
    "wof:name":"Zona Roja S.l.",
    "wof:placetype":"venue"
},
  "geometry": {"coordinates":[1.8019959927,41.2416801453],"type":"Point"}
}