{
  "type": "Feature",
  "properties": {
    "iso:country":"ES",
    "sg:address":"Avda Fernandez Ladreda, 12",
    "sg:city":"Segovia",
    "sg:classifiers":[
        {
            "category":"Personal",
            "subcategory":"Barber",
            "type":"Services"
        }
    ],
    "sg:phone":"+34 921 46 16 79",
    "sg:postcode":"40001",
    "sg:province":"Segovia",
    "sg:tags":[
        "caballeros",
        "de",
        "peluqueros"
    ],
    "wof:name":"Gutierrez Garrido Gregorio Luis",
    "wof:placetype":"venue"
},
  "geometry": {"coordinates":[-4.1188850403,40.9473686218],"type":"Point"}
}