{
  "type": "Feature",
  "properties": {
    "addr:full":"Plaz Pablo Iglesias, 1 Guadalajara Guadalajara 19001",
    "addr:housenumber":"1",
    "addr:postcode":"19001",
    "addr:street":"Pablo Iglesias",
    "iso:country":"ES",
    "sg:address":"Plaz Pablo Iglesias, 1",
    "sg:city":"Guadalajara",
    "sg:orig_category":"Asesor\u00cda Sobre Comunicaci\u00d3n De Empresas",
    "sg:phone":"+34 949 21 71 85",
    "sg:postcode":"19001",
    "sg:province":"Guadalajara",
    "wof:name":"Gestion Integral Pyme S.l.",
    "wof:placetype":"venue"
},
  "geometry": {"coordinates":[-3.1655859947,40.6305084229],"type":"Point"}
}