{
  "type": "Feature",
  "properties": {
    "addr:full":"Ctra Ezcaray, Km. 0002,0 Santo Domingo De La Calzada La Rioja 26250",
    "addr:postcode":"26250",
    "addr:street":"Ctra Ezcaray Km. 0002,0;Calzada;Rioja",
    "iso:country":"ES",
    "sg:address":"Ctra Ezcaray, Km. 0002,0",
    "sg:city":"Santo Domingo De La Calzada",
    "sg:orig_category":"Internados & Ense\u00d1anza Privada",
    "sg:phone":"+34 941 34 10 06",
    "sg:postcode":"26250",
    "sg:province":"La Rioja",
    "wof:name":"Hermanos De La Instruccion Cristiana",
    "wof:placetype":"venue"
},
  "geometry": {"coordinates":[-2.9541339874,42.4394760132],"type":"Point"}
}