{
  "type": "Feature",
  "properties": {
    "iso:country":"ES",
    "sg:address":"Calle de Canovas Del Castillo, 7",
    "sg:city":"Santa Eulalia",
    "sg:orig_category":"Molduras, Junquillos, Listones Y Molduras Perforadas",
    "sg:phone":"+34 968 21 02 05",
    "sg:postcode":"30003",
    "sg:province":"Murcia",
    "wof:name":"Navarro Vidal Maria Jose",
    "wof:placetype":"venue"
},
  "geometry": {"coordinates":[-1.1260024309,37.9841194153],"type":"Point"}
}