{
  "type": "Feature",
  "properties": {
    "iso:country":"ES",
    "sg:address":"Calle de San Vicente, 6",
    "sg:city":"Majadahonda",
    "sg:orig_category":"Centros Empresariales",
    "sg:phone":"+34 916 34 66 20",
    "sg:postcode":"28220",
    "sg:province":"Madrid",
    "wof:name":"Sebastian Garcia-sicilia Francisco",
    "wof:placetype":"venue"
},
  "geometry": {"coordinates":[-3.8788979053,40.4717178345],"type":"Point"}
}