{
  "type": "Feature",
  "properties": {
    "iso:country":"ES",
    "sg:address":"Diagonal 579, 7\u00aa",
    "sg:city":"Barcelona",
    "sg:classifiers":[
        {
            "category":"Professional",
            "subcategory":"Computer Services",
            "type":"Services"
        }
    ],
    "sg:postcode":"08014",
    "sg:tags":[
        "trovit",
        "classifieds",
        "search",
        "vertical-search",
        "homes",
        "cars",
        "jobs"
    ],
    "sg:website":"http://www.trovit.com",
    "wof:name":"Trovit",
    "wof:placetype":"venue"
},
  "geometry": {"coordinates":[2.1486797,41.3939974],"type":"Point"}
}