{
  "type": "Feature",
  "properties": {
    "addr:full":"Cmno Venta (de La), 60 Santomera Murcia 30140",
    "addr:housenumber":"60",
    "addr:postcode":"30140",
    "addr:street":"Cmno Venta De La",
    "iso:country":"ES",
    "sg:address":"Cmno Venta (de La), 60",
    "sg:city":"Santomera",
    "sg:orig_category":"Art\u00cdculos De Regalo (al Por Menor)",
    "sg:phone":"+34 968 86 54 70",
    "sg:postcode":"30140",
    "sg:province":"Murcia",
    "wof:name":"Jamonera Rubio S.l.",
    "wof:placetype":"venue"
},
  "geometry": {"coordinates":[-1.0484639406,38.0597610474],"type":"Point"}
}