{
  "type": "Feature",
  "properties": {
    "iso:country":"ES",
    "sg:address":"Carrer de Radas, 9",
    "sg:city":"Barcelona",
    "sg:orig_category":"Telas Y Sedas (al Por Menor)",
    "sg:phone":"+34 934 41 98 38",
    "sg:postcode":"08004",
    "sg:province":"Barcelona",
    "wof:name":"Mauri Lape\u00f1a Luis",
    "wof:placetype":"venue"
},
  "geometry": {"coordinates":[2.1613960266,41.3743896484],"type":"Point"}
}