{
  "type": "Feature",
  "properties": {
    "iso:country":"ES",
    "sg:address":"Calle de Autonomia, 7",
    "sg:city":"Donostia-san Sebastian",
    "sg:orig_category":"Peluquer\u00cdas, Peluquer\u00cda Mixta",
    "sg:phone":"+34 943 46 47 17",
    "sg:postcode":"20006",
    "sg:province":"Guip\u00f9zcoa",
    "wof:name":"Alberdi Bicandi Bego\u00f1a",
    "wof:placetype":"venue"
},
  "geometry": {"coordinates":[-1.9822696447,43.3133125305],"type":"Point"}
}