{
  "type": "Feature",
  "properties": {
    "addr:full":"Calle de Fortunato Arias, 29 Hellin Albacete 02400",
    "addr:housenumber":"29",
    "addr:postcode":"02400",
    "addr:street":"Calle De Fortunato Arias",
    "iso:country":"ES",
    "sg:address":"Calle de Fortunato Arias, 29",
    "sg:city":"Hellin",
    "sg:orig_category":"Electricidad, Electr\u00d3nica: Suministros (al Por Menor)",
    "sg:phone":"+34 967 30 43 54",
    "sg:postcode":"02400",
    "sg:province":"Albacete",
    "wof:name":"Altapo S.l.",
    "wof:placetype":"venue"
},
  "geometry": {"coordinates":[-1.6934640408,38.5074958801],"type":"Point"}
}