{
  "type": "Feature",
  "properties": {
    "iso:country":"ES",
    "sg:address":"Carrer de Petrarca, 32",
    "sg:city":"Barcelona",
    "sg:orig_category":"Empresas De Carpinter\u00cda Met\u00c1lica",
    "sg:phone":"+34 933 57 76 04",
    "sg:postcode":"08031",
    "sg:province":"Barcelona",
    "wof:name":"Martinez Garcia Jose Ramon",
    "wof:placetype":"venue"
},
  "geometry": {"coordinates":[2.1652140617,41.4292755127],"type":"Point"}
}