{
  "type": "Feature",
  "properties": {
    "addr:full":"Calle de Castilla, 24 Sevilla Sevilla 41010",
    "addr:housenumber":"24",
    "addr:postcode":"41010",
    "addr:street":"Calle De Castilla",
    "iso:country":"ES",
    "sg:address":"Calle de Castilla, 24",
    "sg:city":"Sevilla",
    "sg:orig_category":"Promotores Constructores",
    "sg:phone":"+34 954 34 20 11",
    "sg:postcode":"41010",
    "sg:province":"Sevilla",
    "wof:name":"Urbanismo Y Nuevas Obras Uno S.l.",
    "wof:placetype":"venue"
},
  "geometry": {"coordinates":[-6.0048551559,37.386806488],"type":"Point"}
}