{
  "type": "Feature",
  "properties": {
    "addr:full":"Calle de San Juan Bosco, 11 Rota C\u00e1diz 11520",
    "addr:housenumber":"11",
    "addr:postcode":"11520",
    "addr:street":"Calle De San Juan Bosco;Ca\u0301Diz",
    "iso:country":"ES",
    "sg:address":"Calle de San Juan Bosco, 11",
    "sg:city":"Rota",
    "sg:orig_category":"Fisioterapia",
    "sg:phone":"+34 956 81 19 64",
    "sg:postcode":"11520",
    "sg:province":"C\u00e1diz",
    "wof:name":"Ulriz Angelit Concepcion",
    "wof:placetype":"venue"
},
  "geometry": {"coordinates":[-6.372906208,36.6270484924],"type":"Point"}
}