{
  "type": "Feature",
  "properties": {
    "iso:country":"ES",
    "sg:address":"Calle de Valle Inclan, 1",
    "sg:city":"Cehegin",
    "sg:orig_category":"Asesor\u00cda Fiscal Y Jur\u00cddica",
    "sg:phone":"+34 968 74 28 76",
    "sg:postcode":"30430",
    "sg:province":"Murcia",
    "wof:name":"Asesores Cehemur S.l..",
    "wof:placetype":"venue"
},
  "geometry": {"coordinates":[-1.7971558571,38.0922698975],"type":"Point"}
}