{
  "type": "Feature",
  "properties": {
    "iso:country":"ES",
    "sg:address":"Calle de Valencia, 7",
    "sg:city":"Salamanca",
    "sg:orig_category":"Muebles Y Accesorios Para Cocinas Y Cuartos De Ba\u00d1o (al Por Menor)",
    "sg:phone":"+34 923 22 36 85",
    "sg:postcode":"37005",
    "sg:province":"Salamanca",
    "wof:name":"Inspiracion Del Ba\u00f1o Hgr S.l.l.",
    "wof:placetype":"venue"
},
  "geometry": {"coordinates":[-5.659430027,40.9706001282],"type":"Point"}
}