{
  "type": "Feature",
  "properties": {
    "addr:full":"Calle de Paca Diaz, 1 Madrid Madrid 28023",
    "addr:housenumber":"1",
    "addr:postcode":"28023",
    "addr:street":"Calle De Paca Diaz",
    "iso:country":"ES",
    "sg:address":"Calle de Paca Diaz, 1",
    "sg:city":"Madrid",
    "sg:orig_category":"Fabricaci\u00d3n De Art\u00cdculos Y Equipos Deportivos Y De Ocio",
    "sg:phone":"+34 915 51 54 47",
    "sg:postcode":"28023",
    "sg:province":"Madrid",
    "wof:name":"Barbero Romero Juan Luis",
    "wof:placetype":"venue"
},
  "geometry": {"coordinates":[-3.7795090675,40.458278656],"type":"Point"}
}