{
  "type": "Feature",
  "properties": {
    "iso:country":"ES",
    "sg:address":"Av Paisos Catalans, 96",
    "sg:city":"Vic",
    "sg:orig_category":"Mec\u00c1nico Del Autom\u00d3vil",
    "sg:phone":"+34 938 89 56 99",
    "sg:postcode":"08500",
    "sg:province":"Barcelona",
    "wof:name":"Balda Coll Joan",
    "wof:placetype":"venue"
},
  "geometry": {"coordinates":[2.260119915,41.9206466675],"type":"Point"}
}