{
  "type": "Feature",
  "properties": {
    "addr:full":"Calle de Tirso De Molina, 20 S. Fernando C\u00e1diz 11100",
    "addr:housenumber":"20",
    "addr:postcode":"11100",
    "addr:street":"Calle De Tirso De Molina;S. Fernando Ca\u0301Diz",
    "iso:country":"ES",
    "sg:address":"Calle de Tirso De Molina, 20",
    "sg:city":"S. Fernando",
    "sg:orig_category":"Procuradores",
    "sg:phone":"+34 956 89 68 22",
    "sg:postcode":"11100",
    "sg:province":"C\u00e1diz",
    "wof:name":"Pedrero Ariza Maria Dolores",
    "wof:placetype":"venue"
},
  "geometry": {"coordinates":[-6.1974458694,36.4603271484],"type":"Point"}
}