{
  "type": "Feature",
  "properties": {
    "addr:full":"Calle de Alejandro Casona, 12 Malaga M\u00e1laga 29004",
    "addr:housenumber":"12",
    "addr:postcode":"29004",
    "addr:street":"Calle De Alejandro Casona;Ma\u0301Laga",
    "iso:country":"ES",
    "sg:address":"Calle de Alejandro Casona, 12",
    "sg:city":"Malaga",
    "sg:orig_category":"Fabricaci\u00d3n, Venta, Instalaci\u00d3n De R\u00d3tulos, De R\u00d3tulos Luminosos",
    "sg:phone":"+34 952 17 14 20",
    "sg:postcode":"29004",
    "sg:province":"M\u00e1laga",
    "wof:name":"Comercial Malague\u00f1a Del Rotulo S.l.",
    "wof:placetype":"venue"
},
  "geometry": {"coordinates":[-4.4781551361,36.6903800964],"type":"Point"}
}