{
  "type": "Feature",
  "properties": {
    "addr:full":"Plaz Marques, 2 Gijon Asturias 33201",
    "addr:housenumber":"2",
    "addr:postcode":"33201",
    "addr:street":"Marques",
    "iso:country":"ES",
    "sg:address":"Plaz Marques, 2",
    "sg:city":"Gijon",
    "sg:orig_category":"Cajas De Ahorro",
    "sg:phone":"+34 985 17 40 13",
    "sg:postcode":"33201",
    "sg:province":"Asturias",
    "wof:name":"Cajastur",
    "wof:placetype":"venue"
},
  "geometry": {"coordinates":[-5.66370821,43.5451469421],"type":"Point"}
}