{
  "type": "Feature",
  "properties": {
    "iso:country":"ES",
    "sg:address":"Cami Garreta, S/n",
    "sg:city":"S. Bartomeu Valldan",
    "sg:orig_category":"Agentes, Concesionarios Y Sucursales De Veh\u00cdculos",
    "sg:phone":"+34 938 21 16 88",
    "sg:postcode":"08600",
    "sg:province":"Barcelona",
    "wof:name":"Nissan Motor Espa\u00d1a S.a.",
    "wof:placetype":"venue"
},
  "geometry": {"coordinates":[1.8476580381,42.1001281738],"type":"Point"}
}