{
  "type": "Feature",
  "properties": {
    "iso:country":"ES",
    "sg:address":"C/ Marededeu De L'assumpcio, 23",
    "sg:city":"Elche",
    "sg:orig_category":"Promotores Constructores",
    "sg:phone":"+34 966 61 52 46",
    "sg:postcode":"03203",
    "sg:province":"Alicante",
    "wof:name":"Botella Y Quirant S.l.",
    "wof:placetype":"venue"
},
  "geometry": {"coordinates":[-0.6970999837,38.2596282959],"type":"Point"}
}