{
  "type": "Feature",
  "properties": {
    "addr:full":"Ameiro, S/n Ameiro Pontevedra 36967",
    "addr:postcode":"36967",
    "addr:street":"Ameiro S / N",
    "iso:country":"ES",
    "sg:address":"Ameiro, S/n",
    "sg:city":"Ameiro",
    "sg:orig_category":"Empresas De Carpinter\u00cda De Madera",
    "sg:phone":"+34 986 74 32 40",
    "sg:postcode":"36967",
    "sg:province":"Pontevedra",
    "wof:name":"Fontan Otero Jose Antonio",
    "wof:placetype":"venue"
},
  "geometry": {"coordinates":[-8.8113698959,42.4530296326],"type":"Point"}
}