{
  "type": "Feature",
  "properties": {
    "iso:country":"ES",
    "sg:address":"Calle de Juan De Lanuza, 6",
    "sg:city":"Barbastro",
    "sg:orig_category":"Ense\u00d1anza, Formaci\u00d3n Profesional: Aprendizaje",
    "sg:phone":"+34 974 31 06 97",
    "sg:postcode":"22300",
    "sg:province":"Huesca",
    "wof:name":"Obispado De Barbastro",
    "wof:placetype":"venue"
},
  "geometry": {"coordinates":[0.1319150031,42.0351371765],"type":"Point"}
}