{
  "type": "Feature",
  "properties": {
    "iso:country":"ES",
    "sg:address":"Calle de Maitena, 10",
    "sg:city":"Ogijares",
    "sg:orig_category":"Reparaciones Y Remolcado De Veh\u00cdculos",
    "sg:phone":"+34 958 50 68 31",
    "sg:postcode":"18151",
    "sg:province":"Granada",
    "wof:name":"Gruas Cecilio E Hijos S.l.",
    "wof:placetype":"venue"
},
  "geometry": {"coordinates":[-3.6195709705,37.1115455627],"type":"Point"}
}