{
  "type": "Feature",
  "properties": {
    "addr:full":"Ctra Abrigos (a Los), Km. 0005,0 Zocas Santa Cruz De Tenerife 38628",
    "addr:postcode":"38628",
    "addr:street":"Ctra Abrigos;Los Km. 0005,0 Zocas",
    "iso:country":"ES",
    "sg:address":"Ctra Abrigos (a Los), Km. 0005,0",
    "sg:city":"Zocas",
    "sg:orig_category":"Muebles, Minoristas",
    "sg:phone":"+34 922 73 50 10",
    "sg:postcode":"38628",
    "sg:province":"Santa Cruz De Tenerife",
    "wof:name":"Z.l. Muebles San Miguel S.l.",
    "wof:placetype":"venue"
},
  "geometry": {"coordinates":[-16.6135387421,28.0789070129],"type":"Point"}
}