{
  "type": "Feature",
  "properties": {
    "addr:full":"Calle de Hermano Pedro Bethencourt, S/n Orotava Santa Cruz De Tenerife 38300",
    "addr:housenumber":"s",
    "addr:postcode":"38300",
    "addr:street":"Calle De Hermano Pedro Bethencourt;/ N Orotava",
    "iso:country":"ES",
    "sg:address":"Calle de Hermano Pedro Bethencourt, S/n",
    "sg:city":"Orotava",
    "sg:orig_category":"Empresas De Carpinter\u00cda De Madera",
    "sg:phone":"+34 922 33 11 25",
    "sg:postcode":"38300",
    "sg:province":"Santa Cruz De Tenerife",
    "wof:name":"Trujillo Baez Julian",
    "wof:placetype":"venue"
},
  "geometry": {"coordinates":[-16.5238189697,28.3809223175],"type":"Point"}
}