{
  "type": "Feature",
  "properties": {
    "addr:full":"Calle de Cartero German, 14 Santurtzi Vizcaya 48980",
    "addr:housenumber":"14",
    "addr:postcode":"48980",
    "addr:street":"Calle De Cartero German",
    "iso:country":"ES",
    "sg:address":"Calle de Cartero German, 14",
    "sg:city":"Santurtzi",
    "sg:orig_category":"Caf\u00c9s, Bares, Cervecer\u00cdas",
    "sg:phone":"+34 944 62 73 82",
    "sg:postcode":"48980",
    "sg:province":"Vizcaya",
    "wof:name":"Maria Concepcion Soto Y Maria Luisa",
    "wof:placetype":"venue"
},
  "geometry": {"coordinates":[-3.0354351997,43.3276519775],"type":"Point"}
}