{
  "type": "Feature",
  "properties": {
    "iso:country":"ES",
    "sg:address":"Calle de Juan De Dios Diaz, 1",
    "sg:city":"Real S. Vicente",
    "sg:orig_category":"Delegados, Agentes De Tr\u00c1nsito, Auxiliares De Transporte Internacional",
    "sg:phone":"+34 925 87 92 23",
    "sg:postcode":"45640",
    "sg:province":"Toledo",
    "wof:name":"Rey Moreno Adolfo Antonio",
    "wof:placetype":"venue"
},
  "geometry": {"coordinates":[-4.6931438446,40.1323509216],"type":"Point"}
}