{
  "type": "Feature",
  "properties": {
    "iso:country":"ES",
    "sg:address":"Calle de Santaren, 2",
    "sg:city":"Badajoz",
    "sg:classifiers":[
        {
            "category":"Cinema",
            "subcategory":"Movie Theater",
            "type":"Entertainment"
        }
    ],
    "sg:phone":"+34 924 26 25 62",
    "sg:postcode":"06011",
    "sg:province":"Badajoz",
    "sg:tags":[
        "salas",
        "de",
        "cine"
    ],
    "wof:name":"Zojadab S.l.",
    "wof:placetype":"venue"
},
  "geometry": {"coordinates":[-6.9837808609,38.8760871887],"type":"Point"}
}