{
  "type": "Feature",
  "properties": {
    "addr:full":"Calle de Iglesia, 12 Almodovar Del Rio C\u00f3rdoba 14720",
    "addr:housenumber":"12",
    "addr:postcode":"14720",
    "addr:street":"Calle De Iglesia;Co\u0301Rdoba",
    "iso:country":"ES",
    "sg:address":"Calle de Iglesia, 12",
    "sg:city":"Almodovar Del Rio",
    "sg:orig_category":"Enfermeras: Consultas, Atenci\u00d3n A Domicilio",
    "sg:phone":"+34 957 71 33 12",
    "sg:postcode":"14720",
    "sg:province":"C\u00f3rdoba",
    "wof:name":"Ruiz Mangas Transito",
    "wof:placetype":"venue"
},
  "geometry": {"coordinates":[-5.0209360123,37.8089332581],"type":"Point"}
}