{
  "type": "Feature",
  "properties": {
    "addr:full":"Avda Blasco Iba\u00d1ez, 105 Bu\u00f1ol Valencia 46360",
    "addr:housenumber":"105",
    "addr:postcode":"46360",
    "addr:street":"Avda Blasco Iban\u0303Ez",
    "iso:country":"ES",
    "sg:address":"Avda Blasco Iba\u00d1ez, 105",
    "sg:city":"Bu\u00f1ol",
    "sg:orig_category":"Material Y Suministros Para Fabricar Y Transformar El Papel Y El Cart\u00d3n",
    "sg:phone":"+34 962 50 10 28",
    "sg:postcode":"46360",
    "sg:province":"Valencia",
    "wof:name":"D.g.internacional S.a.",
    "wof:placetype":"venue"
},
  "geometry": {"coordinates":[-0.7838190198,39.4277496338],"type":"Point"}
}