{
  "type": "Feature",
  "properties": {
    "iso:country":"ES",
    "sg:address":"Av. Blasco Iba\u00f1ez, 47",
    "sg:city":"Corbera",
    "sg:orig_category":"Arboricultura Y Producci\u00d3n De Frutas",
    "sg:phone":"+34 962 56 01 12",
    "sg:postcode":"46612",
    "sg:province":"Valencia",
    "wof:name":"Frutas Ber S. L.",
    "wof:placetype":"venue"
},
  "geometry": {"coordinates":[-0.3522090018,39.1583786011],"type":"Point"}
}