{
  "type": "Feature",
  "properties": {
    "addr:full":"Calle de Somosierra, 2 Segovia Segovia 40006",
    "addr:housenumber":"2",
    "addr:postcode":"40006",
    "addr:street":"Calle De Somosierra",
    "iso:country":"ES",
    "sg:address":"Calle de Somosierra, 2",
    "sg:city":"Segovia",
    "sg:orig_category":"Carpinteros",
    "sg:phone":"+34 921 44 07 39",
    "sg:postcode":"40006",
    "sg:province":"Segovia",
    "wof:name":"Pvc Cesyplas S.l.",
    "wof:placetype":"venue"
},
  "geometry": {"coordinates":[-4.1122698784,40.9269332886],"type":"Point"}
}