{
  "type": "Feature",
  "properties": {
    "iso:country":"ES",
    "sg:address":"Calle de Nuria, 40",
    "sg:city":"Madrid",
    "sg:orig_category":"Promotores Constructores",
    "sg:phone":"+34 917 65 16 59",
    "sg:postcode":"28034",
    "sg:province":"Madrid",
    "wof:name":"Tilmon Espa\u00d1a S.a.",
    "wof:placetype":"venue"
},
  "geometry": {"coordinates":[-3.7072706223,40.4930343628],"type":"Point"}
}