{
  "type": "Feature",
  "properties": {
    "iso:country":"ES",
    "sg:address":"Calle de Pare Presentat, 3",
    "sg:city":"Valencia",
    "sg:orig_category":"Agencias Y Agentes Comerciales, Representantes",
    "sg:phone":"+34 963 33 22 89",
    "sg:postcode":"46013",
    "sg:province":"Valencia",
    "wof:name":"Navarro Fuerte Enrique",
    "wof:placetype":"venue"
},
  "geometry": {"coordinates":[-0.3669390082,39.4419174194],"type":"Point"}
}