{
  "type": "Feature",
  "properties": {
    "addr:full":"Calle de Miel, 15 Aranda Duero Burgos 09400",
    "addr:housenumber":"15",
    "addr:postcode":"09400",
    "addr:street":"Calle De Miel",
    "iso:country":"ES",
    "sg:address":"Calle de Miel, 15",
    "sg:city":"Aranda Duero",
    "sg:orig_category":"Carnicer\u00cdas, Carnicer\u00cdas",
    "sg:phone":"+34 947 50 49 52",
    "sg:postcode":"09400",
    "sg:province":"Burgos",
    "wof:name":"Martin Martin Antonio",
    "wof:placetype":"venue"
},
  "geometry": {"coordinates":[-3.6894199848,41.671546936],"type":"Point"}
}