{
  "type": "Feature",
  "properties": {
    "iso:country":"ES",
    "sg:address":"Calle de Manuel Iradier, 24",
    "sg:city":"Vitoria-gasteiz",
    "sg:orig_category":"Psic\u00d3logos",
    "sg:phone":"+34 945 14 80 53",
    "sg:postcode":"01005",
    "sg:province":"\u00c1lava",
    "wof:name":"Larrieta Pascual Ana",
    "wof:placetype":"venue"
},
  "geometry": {"coordinates":[-2.6722779274,42.8420829773],"type":"Point"}
}