{
  "type": "Feature",
  "properties": {
    "addr:full":"Poli Arenal (el), S/n Illueca Zaragoza 50250",
    "addr:postcode":"50250",
    "addr:street":"S / N Illueca",
    "iso:country":"ES",
    "sg:address":"Poli Arenal (el), S/n",
    "sg:city":"Illueca",
    "sg:orig_category":"Montaje (empresas De)",
    "sg:phone":"+34 976 82 22 63",
    "sg:postcode":"50250",
    "sg:province":"Zaragoza",
    "wof:name":"Distribuciones Y Montajes Electricos Illueca S.l.",
    "wof:placetype":"venue"
},
  "geometry": {"coordinates":[-1.6206890345,41.5430183411],"type":"Point"}
}