{
  "type": "Feature",
  "properties": {
    "iso:country":"ES",
    "sg:address":"Calle de Arapiles, 22",
    "sg:city":"Almeria",
    "sg:orig_category":"Abogados",
    "sg:phone":"+34 950 26 63 98",
    "sg:postcode":"04001",
    "sg:province":"Almer\u00eda",
    "wof:name":"Castro Ariza Maria Concepcion",
    "wof:placetype":"venue"
},
  "geometry": {"coordinates":[-2.4641084671,36.8352622986],"type":"Point"}
}