{
  "type": "Feature",
  "properties": {
    "iso:country":"ES",
    "sg:address":"Calle de Marcelo Usera, 69",
    "sg:city":"Madrid",
    "sg:orig_category":"Ense\u00d1anza Variada",
    "sg:phone":"+34 915 00 36 54",
    "sg:postcode":"28026",
    "sg:province":"Madrid",
    "sg:website":"www.teacher-formacion.com",
    "wof:name":"Ingles Teachers S.l.",
    "wof:placetype":"venue"
},
  "geometry": {"coordinates":[-3.7053630352,40.3857574463],"type":"Point"}
}