{
  "type": "Feature",
  "properties": {
    "addr:full":"Calle de Menacho, 3 Sanlucar De Barrameda C\u00e1diz 11540",
    "addr:housenumber":"3",
    "addr:postcode":"11540",
    "addr:street":"Calle De Menacho;Ca\u0301Diz",
    "iso:country":"ES",
    "sg:address":"Calle de Menacho, 3",
    "sg:city":"Sanlucar De Barrameda",
    "sg:orig_category":"Promotores Constructores",
    "sg:phone":"+34 956 36 78 27",
    "sg:postcode":"11540",
    "sg:province":"C\u00e1diz",
    "wof:name":"Segoan S.l.",
    "wof:placetype":"venue"
},
  "geometry": {"coordinates":[-6.3514060974,36.7736549377],"type":"Point"}
}