{
  "type": "Feature",
  "properties": {
    "iso:country":"ES",
    "sg:address":"Osona (parc Negocis Mas Blau I), 2",
    "sg:city":"Prat Llobregat",
    "sg:orig_category":"Material Y Suministros Para Fotocopiadoras, Reprograf\u00cda",
    "sg:phone":"+34 934 84 48 00",
    "sg:postcode":"08820",
    "sg:province":"Barcelona",
    "wof:name":"Oce Espa\u00d1a S.a.",
    "wof:placetype":"venue"
},
  "geometry": {"coordinates":[2.0721271038,41.3170890808],"type":"Point"}
}