{
  "type": "Feature",
  "properties": {
    "addr:full":"Rbla Guipuscoa, 178 Barcelona Barcelona 08020",
    "addr:housenumber":"178",
    "addr:postcode":"08020",
    "addr:street":"Rbla Guipuscoa",
    "iso:country":"ES",
    "sg:address":"Rbla Guipuscoa, 178",
    "sg:city":"Barcelona",
    "sg:orig_category":"Artes Gr\u00c1ficas, Artes Pl\u00c1sticas (curso)",
    "sg:phone":"+34 933 13 17 81",
    "sg:postcode":"08020",
    "sg:province":"Barcelona",
    "wof:name":"Sars Simon",
    "wof:placetype":"venue"
},
  "geometry": {"coordinates":[2.2090370655,41.4249649048],"type":"Point"}
}