{
  "type": "Feature",
  "properties": {
    "addr:full":"Calle de Daoiz, 9 Segovia Segovia 40003",
    "addr:housenumber":"9",
    "addr:postcode":"40003",
    "addr:street":"Calle De Daoiz",
    "iso:country":"ES",
    "sg:address":"Calle de Daoiz, 9",
    "sg:city":"Segovia",
    "sg:orig_category":"M\u00c9dicos: Psiquiatr\u00cda",
    "sg:phone":"+34 921 46 07 78",
    "sg:postcode":"40003",
    "sg:province":"Segovia",
    "wof:name":"Redero San Roman Jose Maria",
    "wof:placetype":"venue"
},
  "geometry": {"coordinates":[-4.1286315918,40.9519348145],"type":"Point"}
}