{
  "type": "Feature",
  "properties": {
    "iso:country":"ES",
    "sg:address":"Calle de Cirilo Amoros, 13",
    "sg:city":"Valencia",
    "sg:orig_category":"Asesor\u00cda Sobre Comunicaci\u00d3n De Empresas",
    "sg:phone":"+34 963 51 67 87",
    "sg:postcode":"46004",
    "sg:province":"Valencia",
    "wof:name":"Beltran Alandete Maria Teresa",
    "wof:placetype":"venue"
},
  "geometry": {"coordinates":[-0.3733249903,39.4667053223],"type":"Point"}
}