{
  "type": "Feature",
  "properties": {
    "addr:full":"Plaz Espa\u00d1a, 4 Palencia Palencia 34002",
    "addr:housenumber":"4",
    "addr:postcode":"34002",
    "addr:street":"Plaz Espan\u0303A",
    "iso:country":"ES",
    "sg:address":"Plaz Espa\u00d1a, 4",
    "sg:city":"Palencia",
    "sg:orig_category":"Cl\u00cdnicas Dentales",
    "sg:phone":"+34 979 71 31 85",
    "sg:postcode":"34002",
    "sg:province":"Palencia",
    "wof:name":"Gonzalez Rico Francisco Javier",
    "wof:placetype":"venue"
},
  "geometry": {"coordinates":[-4.527636528,42.0076599121],"type":"Point"}
}