{
  "type": "Feature",
  "properties": {
    "iso:country":"ES",
    "sg:address":"Barr Peruri, 33",
    "sg:city":"Peruri",
    "sg:orig_category":"Camiser\u00cda Y Ropa Interior Masculina (al Por Menor)",
    "sg:phone":"+34 944 60 09 63",
    "sg:postcode":"48940",
    "sg:province":"Vizcaya",
    "sg:website":"www.q-ellos.com",
    "wof:name":"Teiking Gestion S.l.",
    "wof:placetype":"venue"
},
  "geometry": {"coordinates":[-2.9860789776,43.3275489807],"type":"Point"}
}