{
  "type": "Feature",
  "properties": {
    "iso:country":"ES",
    "sg:address":"Calle de Daute, 33",
    "sg:city":"San Cristobal De La Laguna",
    "sg:orig_category":"Organizaciones Internacionales",
    "sg:phone":"+34 922 25 54 67",
    "sg:postcode":"38203",
    "sg:province":"Santa Cruz De Tenerife",
    "wof:name":"Asociacion Tinerfe\u00f1a Lucha Salud Mental",
    "wof:placetype":"venue"
},
  "geometry": {"coordinates":[-16.3231067657,28.4872131348],"type":"Point"}
}