{
  "type": "Feature",
  "properties": {
    "addr:full":"Calle de Margarita, 3 Valladolid Valladolid 47012",
    "addr:housenumber":"3",
    "addr:postcode":"47012",
    "addr:street":"Calle De Margarita",
    "iso:country":"ES",
    "sg:address":"Calle de Margarita, 3",
    "sg:city":"Valladolid",
    "sg:orig_category":"Artesan\u00cda",
    "sg:phone":"+34 983 21 23 80",
    "sg:postcode":"47012",
    "sg:province":"Valladolid",
    "wof:name":"Cascanueces Red S.l.",
    "wof:placetype":"venue"
},
  "geometry": {"coordinates":[-4.6923780441,41.6425170898],"type":"Point"}
}