{
  "type": "Feature",
  "properties": {
    "addr:full":"Rcda San Francisco, 11 Ribadeo Lugo 27700",
    "addr:housenumber":"11",
    "addr:postcode":"27700",
    "addr:street":"Rcda San Francisco",
    "iso:country":"ES",
    "sg:address":"Rcda San Francisco, 11",
    "sg:city":"Ribadeo",
    "sg:orig_category":"Albergues",
    "sg:phone":"+34 982 12 87 42",
    "sg:postcode":"27700",
    "sg:province":"Lugo",
    "wof:name":"Orol Carragal C.b.",
    "wof:placetype":"venue"
},
  "geometry": {"coordinates":[-7.0404257774,43.5352363586],"type":"Point"}
}