{
  "type": "Feature",
  "properties": {
    "iso:country":"ES",
    "sg:address":"Calle de Gaviota, 55",
    "sg:city":"Madrid",
    "sg:orig_category":"Empresas De Carpinter\u00cda De Madera",
    "sg:phone":"+34 914 66 75 67",
    "sg:postcode":"28025",
    "sg:province":"Madrid",
    "wof:name":"Puerta Gaviota S.l.",
    "wof:placetype":"venue"
},
  "geometry": {"coordinates":[-3.7386550903,40.3884239197],"type":"Point"}
}