{
  "type": "Feature",
  "properties": {
    "iso:country":"ES",
    "sg:address":"Calle de Diputacion, 8",
    "sg:city":"Caspe",
    "sg:orig_category":"Venta, Instalaci\u00d3n De Calefacci\u00d3n",
    "sg:phone":"+34 976 63 03 65",
    "sg:postcode":"50700",
    "sg:province":"Zaragoza",
    "wof:name":"Industrias Bial Sl",
    "wof:placetype":"venue"
},
  "geometry": {"coordinates":[-0.0455689989,41.2353363037],"type":"Point"}
}