{
  "type": "Feature",
  "properties": {
    "addr:full":"Avda Vino (del), 62 Valdepe\u00f1as Ciudad Real 13300",
    "addr:housenumber":"62",
    "addr:postcode":"13300",
    "addr:street":"Avda Vino Del",
    "iso:country":"ES",
    "sg:address":"Avda Vino (del), 62",
    "sg:city":"Valdepe\u00f1as",
    "sg:orig_category":"Frutas Y Legumbres Frescas (al Por Mayor)",
    "sg:phone":"+34 926 31 00 57",
    "sg:postcode":"13300",
    "sg:province":"Ciudad Real",
    "wof:name":"Central Hortofruticola Micafrut S.l.",
    "wof:placetype":"venue"
},
  "geometry": {"coordinates":[-3.3884789944,38.7696609497],"type":"Point"}
}