{
  "type": "Feature",
  "properties": {
    "iso:country":"ES",
    "sg:address":"Calle de Doctor J.j. Domine, 18",
    "sg:city":"Valencia",
    "sg:orig_category":"Agencias De Aduana",
    "sg:phone":"+34 902 15 01 20",
    "sg:postcode":"46011",
    "sg:province":"Valencia",
    "wof:name":"Arabandinternationalservices.l.",
    "wof:placetype":"venue"
},
  "geometry": {"coordinates":[-0.3306570053,39.4625740051],"type":"Point"}
}