{
  "type": "Feature",
  "properties": {
    "addr:full":"Carr Olerdola, 30 Vilanova I La Geltru Barcelona 08800",
    "addr:housenumber":"30",
    "addr:postcode":"08800",
    "addr:street":"Carr Olerdola",
    "iso:country":"ES",
    "sg:address":"Carr Olerdola, 30",
    "sg:city":"Vilanova I La Geltru",
    "sg:orig_category":"Inmobiliaria (agencias)",
    "sg:phone":"+34 938 15 41 71",
    "sg:postcode":"08800",
    "sg:province":"Barcelona",
    "sg:website":"www.libertypropertysl.com",
    "wof:name":"Liberty Property S.l",
    "wof:placetype":"venue"
},
  "geometry": {"coordinates":[1.7112460136,41.2186355591],"type":"Point"}
}