{
  "type": "Feature",
  "properties": {
    "addr:full":"Calle de Calvario, S/n Marbella M\u00e1laga 29600",
    "addr:housenumber":"s / n",
    "addr:postcode":"29600",
    "addr:street":"Calle De Calvario;Ma\u0301Laga",
    "iso:country":"ES",
    "sg:address":"Calle de Calvario, S/n",
    "sg:city":"Marbella",
    "sg:orig_category":"Arquitectos",
    "sg:phone":"+34 952 77 92 82",
    "sg:postcode":"29600",
    "sg:province":"M\u00e1laga",
    "wof:name":"Aranda Sanchez Jose Manuel",
    "wof:placetype":"venue"
},
  "geometry": {"coordinates":[-4.8910388947,36.5136909485],"type":"Point"}
}