{
  "type": "Feature",
  "properties": {
    "addr:full":"Monasterio De Irache, 3 Estella Navarra 31200",
    "addr:housenumber":"3",
    "addr:postcode":"31200",
    "iso:country":"ES",
    "sg:address":"Monasterio De Irache, 3",
    "sg:city":"Estella",
    "sg:orig_category":"Fabricaci\u00d3n De Su\u00c9ters Y Chalecos De Punto",
    "sg:phone":"+34 948 55 00 47",
    "sg:postcode":"31200",
    "sg:province":"Navarra",
    "wof:name":"Comercial Lizarra S. L.",
    "wof:placetype":"venue"
},
  "geometry": {"coordinates":[-2.0323441029,42.666595459],"type":"Point"}
}