{
  "type": "Feature",
  "properties": {
    "addr:full":"Calle de Miguel Servet, 60 Zaragoza Zaragoza 50013",
    "addr:housenumber":"60",
    "addr:postcode":"50013",
    "addr:street":"Calle De Miguel Servet",
    "iso:country":"ES",
    "sg:address":"Calle de Miguel Servet, 60",
    "sg:city":"Zaragoza",
    "sg:orig_category":"Psic\u00d3logos",
    "sg:phone":"+34 976 42 07 56",
    "sg:postcode":"50013",
    "sg:province":"Zaragoza",
    "wof:name":"Gimeno Marco Fernando",
    "wof:placetype":"venue"
},
  "geometry": {"coordinates":[-0.8718739748,41.6456375122],"type":"Point"}
}