{
  "type": "Feature",
  "properties": {
    "iso:country":"ES",
    "sg:address":"Calle de Lucios, 32",
    "sg:city":"Puente Tocinos",
    "sg:orig_category":"Plomeros",
    "sg:phone":"+34 968 23 34 14",
    "sg:postcode":"30006",
    "sg:province":"Murcia",
    "wof:name":"Jem Hidraulicas Del Sureste S.l.",
    "wof:placetype":"venue"
},
  "geometry": {"coordinates":[-1.1047290564,37.9914512634],"type":"Point"}
}