{
  "type": "Feature",
  "properties": {
    "iso:country":"ES",
    "sg:address":"Calle de Palma, 1",
    "sg:city":"Madridejos",
    "sg:orig_category":"Loter\u00cda Y T\u00d3mbola",
    "sg:phone":"+34 925 46 03 32",
    "sg:postcode":"45710",
    "sg:province":"Toledo",
    "wof:name":"Pe\u00f1a Nieves Angel",
    "wof:placetype":"venue"
},
  "geometry": {"coordinates":[-3.534318924,39.4695205688],"type":"Point"}
}