{
  "type": "Feature",
  "properties": {
    "addr:full":"Calle de Mayor, 42 Villaca\u00f1as Toledo 45860",
    "addr:housenumber":"42",
    "addr:postcode":"45860",
    "addr:street":"Calle De Mayor",
    "iso:country":"ES",
    "sg:address":"Calle de Mayor, 42",
    "sg:city":"Villaca\u00f1as",
    "sg:orig_category":"Venta, Alquiler De Instrumentos Y Accesorios De M\u00dasica",
    "sg:phone":"+34 925 16 01 55",
    "sg:postcode":"45860",
    "sg:province":"Toledo",
    "sg:website":"www.reticulo.com/garcia-cid",
    "wof:name":"Instrumentos Musicales Garcia-cid S.l.",
    "wof:placetype":"venue"
},
  "geometry": {"coordinates":[-3.3415510654,39.6231002808],"type":"Point"}
}