{
  "type": "Feature",
  "properties": {
    "addr:full":"Calle de Toledo, 82 Madrid Madrid 28005",
    "addr:housenumber":"82",
    "addr:postcode":"madrid;28005",
    "addr:street":"Calle De Toledo",
    "iso:country":"ES",
    "sg:address":"Calle de Toledo, 82",
    "sg:city":"Madrid",
    "sg:orig_category":"Importaci\u00d3n",
    "sg:phone":"+34 913 66 34 05",
    "sg:postcode":"28005",
    "sg:province":"Madrid",
    "wof:name":"Hiperimport S.l.",
    "wof:placetype":"venue"
},
  "geometry": {"coordinates":[-3.7102329731,40.4090690613],"type":"Point"}
}