{
  "type": "Feature",
  "properties": {
    "iso:country":"ES",
    "sg:address":"Calle de San Sebastian, 43",
    "sg:city":"Campillos",
    "sg:orig_category":"Florister\u00cdas",
    "sg:phone":"+34 952 72 28 19",
    "sg:postcode":"29320",
    "sg:province":"M\u00e1laga",
    "wof:name":"Funeflor Anoria S.l.",
    "wof:placetype":"venue"
},
  "geometry": {"coordinates":[-4.8653120995,37.0480537415],"type":"Point"}
}