{
  "type": "Feature",
  "properties": {
    "addr:full":"J. Antonio, 40 Alcantara C\u00e1ceres 10980",
    "addr:housenumber":"40",
    "addr:postcode":"10980",
    "addr:street":"Antonio;Ca\u0301Ceres",
    "iso:country":"ES",
    "sg:address":"J. Antonio, 40",
    "sg:city":"Alcantara",
    "sg:orig_category":"Bancos",
    "sg:phone":"+34 927 39 00 21",
    "sg:postcode":"10980",
    "sg:province":"C\u00e1ceres",
    "wof:name":"Banco Caixa Geral S.a.",
    "wof:placetype":"venue"
},
  "geometry": {"coordinates":[-6.8813929558,39.7164115906],"type":"Point"}
}