{
  "type": "Feature",
  "properties": {
    "addr:full":"Calle de Malateria La, S/n Oviedo Asturias 33008",
    "addr:postcode":"33008",
    "addr:street":"Calle De Malateria La S / N",
    "iso:country":"ES",
    "sg:address":"Calle de Malateria La, S/n",
    "sg:city":"Oviedo",
    "sg:orig_category":"Ense\u00d1anza, Formaci\u00d3n Profesional: Aprendizaje",
    "sg:phone":"+34 985 20 31 02",
    "sg:postcode":"33008",
    "sg:province":"Asturias",
    "wof:name":"Principado De Asturias",
    "wof:placetype":"venue"
},
  "geometry": {"coordinates":[-5.8443288803,43.352432251],"type":"Point"}
}