{
  "type": "Feature",
  "properties": {
    "iso:country":"ES",
    "sg:address":"Calle de Puerta Nueva, S/n",
    "sg:city":"Malaga",
    "sg:orig_category":"Loter\u00cda Y T\u00d3mbola",
    "sg:phone":"+34 952 21 36 22",
    "sg:postcode":"29008",
    "sg:province":"M\u00e1laga",
    "wof:name":"Sanchez Vega Francisca",
    "wof:placetype":"venue"
},
  "geometry": {"coordinates":[-4.4247641563,36.7213897705],"type":"Point"}
}