{
  "type": "Feature",
  "properties": {
    "addr:full":"Calle de Doctor Fleming, S/n Jerez De La Frontera C\u00e1diz 11407",
    "addr:housenumber":"s",
    "addr:postcode":"11407",
    "addr:street":"Calle De Doctor Fleming;/ N",
    "iso:country":"ES",
    "sg:address":"Calle de Doctor Fleming, S/n",
    "sg:city":"Jerez De La Frontera",
    "sg:orig_category":"Institutos M\u00c9dicos",
    "sg:phone":"+34 956 30 52 04",
    "sg:postcode":"11407",
    "sg:province":"C\u00e1diz",
    "wof:name":"Servicio Andaluz De Salud",
    "wof:placetype":"venue"
},
  "geometry": {"coordinates":[-6.1399440765,36.6999282837],"type":"Point"}
}