{
  "type": "Feature",
  "properties": {
    "iso:country":"ES",
    "sg:address":"Calle de Fuenterrabia, 2",
    "sg:city":"Donostia-san Sebastian",
    "sg:orig_category":"Agentes Generales De Seguros",
    "sg:phone":"+34 943 42 81 31",
    "sg:postcode":"20005",
    "sg:province":"Guip\u00f9zcoa",
    "wof:name":"Otaegui Bianchi I\u00f1igo",
    "wof:placetype":"venue"
},
  "geometry": {"coordinates":[-1.9825919867,43.3191833496],"type":"Point"}
}