{
  "type": "Feature",
  "properties": {
    "addr:full":"Calle de Colegios, 9 Alcala Henares Madrid 28801",
    "addr:housenumber":"9",
    "addr:postcode":"28801",
    "addr:street":"Calle De Colegios",
    "iso:country":"ES",
    "sg:address":"Calle de Colegios, 9",
    "sg:city":"Alcala Henares",
    "sg:orig_category":"Comunidades Religiosas",
    "sg:phone":"+34 918 83 00 65",
    "sg:postcode":"28801",
    "sg:province":"Madrid",
    "wof:name":"Cofradia De Cristo Universitario",
    "wof:placetype":"venue"
},
  "geometry": {"coordinates":[-3.3243501186,40.5536193848],"type":"Point"}
}