{
  "type": "Feature",
  "properties": {
    "iso:country":"ES",
    "sg:address":"Camino Beljafel, S/n",
    "sg:city":"Fontanar",
    "sg:orig_category":"Poller\u00cda Y Caza (al Por Menor)",
    "sg:phone":"+34 949 82 07 88",
    "sg:postcode":"19290",
    "sg:province":"Guadalajara",
    "wof:name":"Juan Luis Castillo Martinez Y Javier Castillo Martinez Cdad",
    "wof:placetype":"venue"
},
  "geometry": {"coordinates":[-3.1767890453,40.7265930176],"type":"Point"}
}