{
  "type": "Feature",
  "properties": {
    "iso:country":"ES",
    "sg:address":"Calle de Pedro Laborde, 8",
    "sg:city":"Madrid",
    "sg:orig_category":"Lencer\u00cda Femenina, Corseter\u00cda, Trajes De Ba\u00d1o (al Por Menor)",
    "sg:phone":"+34 913 03 07 80",
    "sg:postcode":"28038",
    "sg:province":"Madrid",
    "wof:name":"Arroyo Linares Maria Dolores",
    "wof:placetype":"venue"
},
  "geometry": {"coordinates":[-3.6473333836,40.389465332],"type":"Point"}
}