{
  "type": "Feature",
  "properties": {
    "addr:full":"Calle de Quejigo, 15 Toledo Toledo 45005",
    "addr:housenumber":"15",
    "addr:postcode":"45005",
    "addr:street":"Calle De Quejigo",
    "iso:country":"ES",
    "sg:address":"Calle de Quejigo, 15",
    "sg:city":"Toledo",
    "sg:orig_category":"Promotores Constructores",
    "sg:phone":"+34 925 25 67 23",
    "sg:postcode":"45005",
    "sg:province":"Toledo",
    "wof:name":"Estopcar S.l.",
    "wof:placetype":"venue"
},
  "geometry": {"coordinates":[-4.0572361946,39.89220047],"type":"Point"}
}