{
  "type": "Feature",
  "properties": {
    "iso:country":"ES",
    "sg:address":"Ctra Montcada, Km. 0750,0",
    "sg:city":"Terrassa",
    "sg:orig_category":"Limpieza Industrial",
    "sg:phone":"+34 937 36 33 28",
    "sg:postcode":"08227",
    "sg:province":"Barcelona",
    "wof:name":"Itram 2000 S.l.",
    "wof:placetype":"venue"
},
  "geometry": {"coordinates":[2.0383529663,41.5572013855],"type":"Point"}
}