{
  "type": "Feature",
  "properties": {
    "iso:country":"ES",
    "sg:address":"Carr Arravaleta, 5",
    "sg:city":"Mao",
    "sg:orig_category":"Farmacias",
    "sg:phone":"+34 971 36 29 61",
    "sg:postcode":"07702",
    "sg:province":"Islas Baleares",
    "wof:name":"Felix Nicolas Juan Ernesto",
    "wof:placetype":"venue"
},
  "geometry": {"coordinates":[4.265625,39.8903694153],"type":"Point"}
}