{
  "type": "Feature",
  "properties": {
    "iso:country":"ES",
    "sg:address":"Barr Palacio, 38",
    "sg:city":"Arnuero",
    "sg:orig_category":"Supermercados Y Hipermercados",
    "sg:phone":"+34 942 67 71 14",
    "sg:postcode":"39194",
    "sg:province":"Cantabria",
    "wof:name":"El Arenal De Noja S.l.",
    "wof:placetype":"venue"
},
  "geometry": {"coordinates":[-3.5678329468,43.4699211121],"type":"Point"}
}