{
  "type": "Feature",
  "properties": {
    "addr:full":"Carrer de Sant Pere Mes Alt, 25 Barcelona Barcelona 08003",
    "addr:housenumber":"25",
    "addr:postcode":"08003",
    "addr:street":"Carrer De Sant",
    "iso:country":"ES",
    "sg:address":"Carrer de Sant Pere Mes Alt, 25",
    "sg:city":"Barcelona",
    "sg:orig_category":"Confecci\u00d3n De Trajes Para Se\u00d1oras",
    "sg:phone":"+34 932 68 02 27",
    "sg:postcode":"08003",
    "sg:province":"Barcelona",
    "wof:name":"Gatibu S.l",
    "wof:placetype":"venue"
},
  "geometry": {"coordinates":[2.1762120724,41.3881721497],"type":"Point"}
}