{
  "type": "Feature",
  "properties": {
    "iso:country":"ES",
    "sg:address":"Carrer de Fedanci, 1",
    "sg:city":"Manlleu",
    "sg:orig_category":"Marroquiner\u00cda (confecci\u00d3n)",
    "sg:phone":"+34 938 51 12 28",
    "sg:postcode":"08560",
    "sg:province":"Barcelona",
    "wof:name":"El Lagarto S. A.",
    "wof:placetype":"venue"
},
  "geometry": {"coordinates":[2.2831161022,41.9995574951],"type":"Point"}
}