{
  "type": "Feature",
  "properties": {
    "addr:full":"Carrer de Torrent Llibre, 16 Cardedeu Barcelona 08440",
    "addr:housenumber":"16",
    "addr:postcode":"08440",
    "addr:street":"Carrer De Torrent Llibre",
    "iso:country":"ES",
    "sg:address":"Carrer de Torrent Llibre, 16",
    "sg:city":"Cardedeu",
    "sg:orig_category":"Dietistas",
    "sg:phone":"+34 938 71 35 16",
    "sg:postcode":"08440",
    "sg:province":"Barcelona",
    "sg:website":"www.bionets.net",
    "wof:name":"Bionets S L",
    "wof:placetype":"venue"
},
  "geometry": {"coordinates":[2.3543720245,41.6396064758],"type":"Point"}
}