{
  "type": "Feature",
  "properties": {
    "iso:country":"ES",
    "sg:address":"Calle de Antonio Gonzalez Vizcaino, 8",
    "sg:city":"Almeria",
    "sg:orig_category":"Muebles Y Accesorios Para Cocinas Y Cuartos De Ba\u00d1o (al Por Menor)",
    "sg:phone":"+34 950 26 77 63",
    "sg:postcode":"04006",
    "sg:province":"Almer\u00eda",
    "wof:name":"Muebles Amate S.l.",
    "wof:placetype":"venue"
},
  "geometry": {"coordinates":[-2.4502859116,36.8384513855],"type":"Point"}
}