{
  "type": "Feature",
  "properties": {
    "addr:full":"Avda Lugo (de), 55 Taboada Lugo 27550",
    "addr:housenumber":"55",
    "addr:postcode":"27550",
    "addr:street":"Avda Lugo De",
    "iso:country":"ES",
    "sg:address":"Avda Lugo (de), 55",
    "sg:city":"Taboada",
    "sg:orig_category":"Farmacias",
    "sg:phone":"+34 982 46 54 35",
    "sg:postcode":"27550",
    "sg:province":"Lugo",
    "wof:name":"Fernandez Valeiras Rosa Maria",
    "wof:placetype":"venue"
},
  "geometry": {"coordinates":[-7.7629489899,42.7171897888],"type":"Point"}
}