{
  "type": "Feature",
  "properties": {
    "iso:country":"ES",
    "sg:address":"Avda Portugal, 6",
    "sg:city":"Talavera Reina",
    "sg:orig_category":"Cer\u00c1mica Art\u00cdstica Y Decorativa",
    "sg:phone":"+34 925 82 84 52",
    "sg:postcode":"45600",
    "sg:province":"Toledo",
    "wof:name":"Froilan Oviedo Juan Antonio",
    "wof:placetype":"venue"
},
  "geometry": {"coordinates":[-4.8403000832,39.9586105347],"type":"Point"}
}