{
  "type": "Feature",
  "properties": {
    "iso:country":"ES",
    "sg:address":"Calle de Calvario, 69",
    "sg:city":"Benavente",
    "sg:orig_category":"Calefacci\u00d3n Central: Material (fabricaci\u00d3n, Al Por Mayor)",
    "sg:phone":"+34 980 63 09 94",
    "sg:postcode":"49600",
    "sg:province":"Zamora",
    "wof:name":"Troia Espa\u00f1a S.l.",
    "wof:placetype":"venue"
},
  "geometry": {"coordinates":[-5.6657037735,42.0032501221],"type":"Point"}
}