{
  "type": "Feature",
  "properties": {
    "addr:full":"Calle de Eduardo Marquina, 6 Avila \u00c1vila 05001",
    "addr:housenumber":"6",
    "addr:postcode":"05001",
    "addr:street":"Calle De Eduardo Marquina;A\u0301Vila",
    "iso:country":"ES",
    "sg:address":"Calle de Eduardo Marquina, 6",
    "sg:city":"Avila",
    "sg:orig_category":"Ense\u00d1anza, Formaci\u00d3n Profesional: Aprendizaje",
    "sg:phone":"+34 920 35 35 80",
    "sg:postcode":"05001",
    "sg:province":"\u00c1vila",
    "sg:website":"www.ventanillaempresarial.org",
    "wof:name":"Camara Oficial De Comercio E Industria De Avila",
    "wof:placetype":"venue"
},
  "geometry": {"coordinates":[-4.6943478584,40.6565513611],"type":"Point"}
}