{
  "type": "Feature",
  "properties": {
    "addr:full":"Barr Abajo De, 76 Pelugano Asturias 33686",
    "addr:postcode":"33686",
    "addr:street":"Pelugano Asturias",
    "iso:country":"ES",
    "sg:address":"Barr Abajo De, 76",
    "sg:city":"Pelugano",
    "sg:orig_category":"Vinos (agentes)",
    "sg:phone":"+34 985 48 63 31",
    "sg:postcode":"33686",
    "sg:province":"Asturias",
    "wof:name":"Embotelladora De Pelugano S.l.",
    "wof:placetype":"venue"
},
  "geometry": {"coordinates":[-5.6228342056,43.1615257263],"type":"Point"}
}