{
  "type": "Feature",
  "properties": {
    "iso:country":"ES",
    "sg:address":"Carrer de Sant Iscle, 23",
    "sg:city":"Barcelona",
    "sg:orig_category":"Animales (al Por Menor)",
    "sg:phone":"+34 933 58 32 01",
    "sg:postcode":"08031",
    "sg:province":"Barcelona",
    "wof:name":"Jimenez Roldan Antonio Miguel",
    "wof:placetype":"venue"
},
  "geometry": {"coordinates":[2.1734290123,41.4315299988],"type":"Point"}
}