{
  "type": "Feature",
  "properties": {
    "addr:full":"Avda Baron De Carcer, 41 Valencia Valencia 46001",
    "addr:housenumber":"41",
    "addr:postcode":"46001",
    "addr:street":"Avda Baron De Carcer",
    "iso:country":"ES",
    "sg:address":"Avda Baron De Carcer, 41",
    "sg:city":"Valencia",
    "sg:orig_category":"Zapatos (al Por Menor)",
    "sg:phone":"+34 963 52 28 81",
    "sg:postcode":"46001",
    "sg:province":"Valencia",
    "wof:name":"Alcahut Legidos Casimiro",
    "wof:placetype":"venue"
},
  "geometry": {"coordinates":[-0.3796432912,39.4700927734],"type":"Point"}
}