{
  "type": "Feature",
  "properties": {
    "iso:country":"ES",
    "sg:address":"Calle de Echegaray, 7",
    "sg:city":"Salamanca",
    "sg:orig_category":"Abogados",
    "sg:phone":"+34 923 22 27 77",
    "sg:postcode":"37005",
    "sg:province":"Salamanca",
    "wof:name":"Roman Hernandez Jose Antonio",
    "wof:placetype":"venue"
},
  "geometry": {"coordinates":[-5.6611838341,40.9706993103],"type":"Point"}
}