{
  "type": "Feature",
  "properties": {
    "addr:full":"Ptge Mas Sant Jordi, 24 Mataro Barcelona 08303",
    "addr:housenumber":"24",
    "addr:postcode":"08303",
    "addr:street":"Ptge Mas Sant Jordi",
    "iso:country":"ES",
    "sg:address":"Ptge Mas Sant Jordi, 24",
    "sg:city":"Mataro",
    "sg:orig_category":"Arreglo, Reparaci\u00d3n, Piezas Sueltas De Televisi\u00d3n, V\u00cddeo, Hi",
    "sg:phone":"+34 937 98 02 48",
    "sg:postcode":"08303",
    "sg:province":"Barcelona",
    "wof:name":"Villaret Polo Ramon",
    "wof:placetype":"venue"
},
  "geometry": {"coordinates":[2.4256160259,41.5471076965],"type":"Point"}
}