{
  "type": "Feature",
  "properties": {
    "iso:country":"ES",
    "sg:address":"Pg Pere Iii, 89",
    "sg:city":"Manresa",
    "sg:orig_category":"M\u00c9dicos: Ginecolog\u00cda Y Obstetricia",
    "sg:phone":"+34 938 73 53 04",
    "sg:postcode":"08242",
    "sg:province":"Barcelona",
    "wof:name":"Carreras Almirall Pere",
    "wof:placetype":"venue"
},
  "geometry": {"coordinates":[1.8303450346,41.7300987244],"type":"Point"}
}