{
  "type": "Feature",
  "properties": {
    "addr:full":"Calle de Calderon De La Barca, 37 Cuenca Cuenca 16001",
    "addr:housenumber":"37",
    "addr:postcode":"16001",
    "addr:street":"Calle De Calderon De La Barca",
    "iso:country":"ES",
    "sg:address":"Calle de Calderon De La Barca, 37",
    "sg:city":"Cuenca",
    "sg:orig_category":"Arquitectos",
    "sg:phone":"+34 969 23 61 98",
    "sg:postcode":"16001",
    "sg:province":"Cuenca",
    "wof:name":"Qubo Dos S.l.",
    "wof:placetype":"venue"
},
  "geometry": {"coordinates":[-2.1368610859,40.0751838684],"type":"Point"}
}