{
  "type": "Feature",
  "properties": {
    "addr:full":"Pase Mu\u00d1oz Grandes, 9 Madrid Madrid 28025",
    "addr:housenumber":"9",
    "addr:postcode":"madrid;28025",
    "addr:street":"Grandes",
    "iso:country":"ES",
    "sg:address":"Pase Mu\u00d1oz Grandes, 9",
    "sg:city":"Madrid",
    "sg:orig_category":"Equipo De Refrigeraci\u00d3n Industrial",
    "sg:phone":"+34 914 61 72 22",
    "sg:postcode":"28025",
    "sg:province":"Madrid",
    "wof:name":"P.rincon Y M.perurena S.l.",
    "wof:placetype":"venue"
},
  "geometry": {"coordinates":[-3.740240097,40.3851165771],"type":"Point"}
}