{
  "type": "Feature",
  "properties": {
    "iso:country":"ES",
    "sg:address":"Calle de Saavedra, 38",
    "sg:city":"Gijon",
    "sg:orig_category":"Aparcamientos (infraestructuras, Accesorios)",
    "sg:phone":"+34 985 39 70 23",
    "sg:postcode":"33208",
    "sg:province":"Asturias",
    "wof:name":"Alvarez Uria Francisco Javier",
    "wof:placetype":"venue"
},
  "geometry": {"coordinates":[-5.6641640663,43.5333251953],"type":"Point"}
}