{
  "type": "Feature",
  "properties": {
    "addr:full":"Ptda Rambla Alta, 24 Alcoi Alicante 03818",
    "addr:housenumber":"24",
    "addr:postcode":"03818",
    "addr:street":"Rambla Alta",
    "iso:country":"ES",
    "sg:address":"Ptda Rambla Alta, 24",
    "sg:city":"Alcoi",
    "sg:orig_category":"Equitaci\u00d3n Y Centros De H\u00cdpica",
    "sg:phone":"+34 965 54 48 35",
    "sg:postcode":"03818",
    "sg:province":"Alicante",
    "sg:website":"www.escueladeequitacionpeluca.com",
    "wof:name":"Llorens Montava Jose Rafael",
    "wof:placetype":"venue"
},
  "geometry": {"coordinates":[-0.456539005,38.7195396423],"type":"Point"}
}