{
  "type": "Feature",
  "properties": {
    "addr:full":"Calle de Campoamor, 21 Oviedo Asturias 33001",
    "addr:housenumber":"21",
    "addr:postcode":"33001",
    "addr:street":"Calle De Campoamor",
    "iso:country":"ES",
    "sg:address":"Calle de Campoamor, 21",
    "sg:city":"Oviedo",
    "sg:orig_category":"Asesor\u00cda Fiscal Y Jur\u00cddica",
    "sg:phone":"+34 985 22 93 17",
    "sg:postcode":"33001",
    "sg:province":"Asturias",
    "wof:name":"Fanjul Bertrand Julio",
    "wof:placetype":"venue"
},
  "geometry": {"coordinates":[-5.8526973724,43.3659439087],"type":"Point"}
}