{
  "type": "Feature",
  "properties": {
    "iso:country":"ES",
    "sg:address":"Central Termica, S/n",
    "sg:city":"Pontes Garcia Rodriguez",
    "sg:orig_category":"Montaje (empresas De)",
    "sg:phone":"+34 981 45 15 05",
    "sg:postcode":"15320",
    "sg:province":"La Coru\u00f1a",
    "wof:name":"Masa Galicia S.a.",
    "wof:placetype":"venue"
},
  "geometry": {"coordinates":[-7.8519802094,43.4437828064],"type":"Point"}
}