{
  "type": "Feature",
  "properties": {
    "iso:country":"ES",
    "sg:address":"Avda Leon, 36",
    "sg:city":"Villanueva Carrizo",
    "sg:orig_category":"Mec\u00c1nico Del Autom\u00d3vil",
    "sg:phone":"+34 987 35 76 94",
    "sg:postcode":"24270",
    "sg:province":"Le\u00f3n",
    "wof:name":"Alvarez Martinez Ramon",
    "wof:placetype":"venue"
},
  "geometry": {"coordinates":[-5.8157382011,42.5802154541],"type":"Point"}
}