{
  "type": "Feature",
  "properties": {
    "addr:full":"Calle de Gran Avenida, 31 Madrid Madrid 28041",
    "addr:housenumber":"31",
    "addr:postcode":"madrid;28041",
    "addr:street":"Calle De Gran Avenida",
    "iso:country":"ES",
    "sg:address":"Calle de Gran Avenida, 31",
    "sg:city":"Madrid",
    "sg:orig_category":"Zapatos (al Por Menor)",
    "sg:phone":"+34 913 41 78 48",
    "sg:postcode":"28041",
    "sg:province":"Madrid",
    "wof:name":"Oro Gudiel Elena",
    "wof:placetype":"venue"
},
  "geometry": {"coordinates":[-3.7056999207,40.3697090149],"type":"Point"}
}