{
  "type": "Feature",
  "properties": {
    "addr:full":"Plaz Cabildo (del), 12 Pilas Sevilla 41840",
    "addr:postcode":"41840",
    "addr:street":"Del",
    "iso:country":"ES",
    "sg:address":"Plaz Cabildo (del), 12",
    "sg:city":"Pilas",
    "sg:orig_category":"Confecci\u00d3n (fabricaci\u00d3n, Al Por Mayor)",
    "sg:phone":"+34 954 75 13 05",
    "sg:postcode":"41840",
    "sg:province":"Sevilla",
    "wof:name":"Diez Gancedo Manuel",
    "wof:placetype":"venue"
},
  "geometry": {"coordinates":[-6.3025197983,37.3019065857],"type":"Point"}
}