{
  "type": "Feature",
  "properties": {
    "addr:full":"Calle de Doctor Civera, 1 Jaen Ja\u00e9n 23003",
    "addr:housenumber":"1;jae\u0301n",
    "addr:postcode":"23003",
    "addr:street":"Calle De Doctor Civera",
    "iso:country":"ES",
    "sg:address":"Calle de Doctor Civera, 1",
    "sg:city":"Jaen",
    "sg:orig_category":"Ropa Para Caballeros (al Por Menor)",
    "sg:phone":"+34 953 29 12 58",
    "sg:postcode":"23003",
    "sg:province":"Ja\u00e9n",
    "wof:name":"Martinez Cortes Juan Carlos",
    "wof:placetype":"venue"
},
  "geometry": {"coordinates":[-3.790610075,37.7673988342],"type":"Point"}
}