{
  "type": "Feature",
  "properties": {
    "iso:country":"ES",
    "sg:address":"Carrer de Manlleu, 6",
    "sg:city":"Vic",
    "sg:orig_category":"Peluqueros: De Se\u00d1oras",
    "sg:phone":"+34 938 86 09 84",
    "sg:postcode":"08500",
    "sg:province":"Barcelona",
    "wof:name":"Campdelacreu Allue Maria Assumpta",
    "wof:placetype":"venue"
},
  "geometry": {"coordinates":[2.2554690838,41.9313926697],"type":"Point"}
}