{
  "type": "Feature",
  "properties": {
    "iso:country":"ES",
    "sg:address":"Carrer de Agricultura, 29",
    "sg:city":"Viladecans",
    "sg:orig_category":"Tratamiento De Metales",
    "sg:phone":"+34 936 35 76 52",
    "sg:postcode":"08840",
    "sg:province":"Barcelona",
    "wof:name":"Moiatext Manipulats S.l.",
    "wof:placetype":"venue"
},
  "geometry": {"coordinates":[2.0192699432,41.3090896606],"type":"Point"}
}