{
  "type": "Feature",
  "properties": {
    "addr:full":"Ctra Villacastin, Km. 0277,0 Zamora Zamora 49002",
    "addr:postcode":"49002",
    "addr:street":"Ctra Villacastin Km. 0277,0",
    "iso:country":"ES",
    "sg:address":"Ctra Villacastin, Km. 0277,0",
    "sg:city":"Zamora",
    "sg:orig_category":"Maquinaria Para Industrias Diversas",
    "sg:phone":"+34 980 51 75 12",
    "sg:postcode":"49002",
    "sg:province":"Zamora",
    "sg:website":"www.alcaser.com",
    "wof:name":"Alcalser 2000 S.l.",
    "wof:placetype":"venue"
},
  "geometry": {"coordinates":[-5.7562398911,41.5224838257],"type":"Point"}
}