{
  "type": "Feature",
  "properties": {
    "addr:full":"Ctra. Ubeda, S/n Donadio Ja\u00e9n 23509",
    "addr:housenumber":"s",
    "addr:postcode":"23509",
    "addr:street":"Ctra. Ubeda;/ N Donadio Jae\u0301N",
    "iso:country":"ES",
    "sg:address":"Ctra. Ubeda, S/n",
    "sg:city":"Donadio",
    "sg:orig_category":"Producci\u00d3n, Venta De Productos De Agricultura Biol\u00d3gica",
    "sg:phone":"+34 953 12 70 74",
    "sg:postcode":"23509",
    "sg:province":"Ja\u00e9n",
    "wof:name":"Cortijo La Catolica S.a.",
    "wof:placetype":"venue"
},
  "geometry": {"coordinates":[-3.367027998,37.9277954102],"type":"Point"}
}