{
  "type": "Feature",
  "properties": {
    "iso:country":"ES",
    "sg:address":"Avda Pais Valenciano, 115",
    "sg:city":"Albatera",
    "sg:orig_category":"Promotores Constructores",
    "sg:phone":"+34 965 48 68 08",
    "sg:postcode":"03340",
    "sg:province":"Alicante",
    "wof:name":"Oleza Urbana S.l.",
    "wof:placetype":"venue"
},
  "geometry": {"coordinates":[-0.8697929978,38.1806755066],"type":"Point"}
}