{
  "type": "Feature",
  "properties": {
    "iso:country":"ES",
    "sg:address":"Cortijo Los Martos, S/n",
    "sg:city":"Gallardos",
    "sg:orig_category":"Inmobiliaria (agencias)",
    "sg:phone":"+34 950 52 80 58",
    "sg:postcode":"04280",
    "sg:province":"Almer\u00eda",
    "wof:name":"Obrascampo S.l.",
    "wof:placetype":"venue"
},
  "geometry": {"coordinates":[-1.9397890568,37.1677284241],"type":"Point"}
}