{
  "type": "Feature",
  "properties": {
    "addr:full":"Comarca De L'horta, 9 Aldaia Valencia 46960",
    "addr:housenumber":"9",
    "addr:postcode":"46960",
    "iso:country":"ES",
    "sg:address":"Comarca De L'horta, 9",
    "sg:city":"Aldaia",
    "sg:orig_category":"Cerrajer\u00cda, Ferrallista",
    "sg:phone":"+34 961 51 77 24",
    "sg:postcode":"46960",
    "sg:province":"Valencia",
    "wof:name":"Cemalu Cerrajeros S.l.",
    "wof:placetype":"venue"
},
  "geometry": {"coordinates":[-0.4861220121,39.4594192505],"type":"Point"}
}