{
  "type": "Feature",
  "properties": {
    "addr:full":"Calle de Nueva, 6 S. Lorenzo Parrilla Cuenca 16770",
    "addr:postcode":"16770",
    "addr:street":"Calle De Nueva 6 S. Lorenzo",
    "iso:country":"ES",
    "sg:address":"Calle de Nueva, 6",
    "sg:city":"S. Lorenzo Parrilla",
    "sg:orig_category":"Asociaciones, Organismos Culturales Y Socioeducativos",
    "sg:phone":"+34 969 19 50 54",
    "sg:postcode":"16770",
    "sg:province":"Cuenca",
    "wof:name":"Club De Jubilados De San Lorenzo De La Parrilla",
    "wof:placetype":"venue"
},
  "geometry": {"coordinates":[-2.3609490395,39.8521347046],"type":"Point"}
}