{
  "type": "Feature",
  "properties": {
    "addr:full":"Av Gatassa, 16 Mataro Barcelona 08303",
    "addr:housenumber":"16",
    "addr:postcode":"08303",
    "addr:street":"Av Gatassa",
    "iso:country":"ES",
    "sg:address":"Av Gatassa, 16",
    "sg:city":"Mataro",
    "sg:orig_category":"Ropa Para Se\u00d1oras (al Por Menor)",
    "sg:phone":"+34 937 57 00 26",
    "sg:postcode":"08303",
    "sg:province":"Barcelona",
    "wof:name":"Mora Bartres Maria Dolors",
    "wof:placetype":"venue"
},
  "geometry": {"coordinates":[2.4300820827,41.5372619629],"type":"Point"}
}