{
  "type": "Feature",
  "properties": {
    "addr:full":"Carr Industria, S/n Palafrugell Girona 17200",
    "addr:housenumber":"/ n",
    "addr:postcode":"17200",
    "addr:street":"Carr Industria S",
    "iso:country":"ES",
    "sg:address":"Carr Industria, S/n",
    "sg:city":"Palafrugell",
    "sg:orig_category":"Delegados, Agentes De Tr\u00c1nsito, Auxiliares De Transporte Internacional",
    "sg:phone":"+34 972 30 07 23",
    "sg:postcode":"17200",
    "sg:province":"Girona",
    "wof:name":"Oliver Carreras Enrique",
    "wof:placetype":"venue"
},
  "geometry": {"coordinates":[3.1558849812,41.9255981445],"type":"Point"}
}