{
  "type": "Feature",
  "properties": {
    "addr:full":"Calle de Arrorro, 9 Palmas De Gran Canaria Las Palmas 35015",
    "addr:housenumber":"9",
    "addr:postcode":"35015",
    "addr:street":"Calle De Arrorro",
    "iso:country":"ES",
    "sg:address":"Calle de Arrorro, 9",
    "sg:city":"Palmas De Gran Canaria",
    "sg:orig_category":"Molduras, Junquillos, Listones Y Molduras Perforadas",
    "sg:phone":"+34 928 32 20 20",
    "sg:postcode":"35015",
    "sg:province":"Las Palmas",
    "wof:name":"Medina Baez Jose Manuel",
    "wof:placetype":"venue"
},
  "geometry": {"coordinates":[-15.4286766052,28.0971660614],"type":"Point"}
}