{
  "type": "Feature",
  "properties": {
    "addr:full":"Pla\u00c7 Espa\u00d1a, 3 Xativa Valencia 46800",
    "addr:housenumber":"3",
    "addr:postcode":"46800",
    "addr:street":"Espan\u0303A",
    "iso:country":"ES",
    "sg:address":"Pla\u00c7 Espa\u00d1a, 3",
    "sg:city":"Xativa",
    "sg:orig_category":"Transportes De Material De Construcci\u00d3n",
    "sg:phone":"+34 962 27 50 34",
    "sg:postcode":"46800",
    "sg:province":"Valencia",
    "wof:name":"Jose Torregrosa Soler S.l",
    "wof:placetype":"venue"
},
  "geometry": {"coordinates":[-0.5163311958,38.9969673157],"type":"Point"}
}