{
  "type": "Feature",
  "properties": {
    "addr:full":"Plaz Camachos, 2 Carmen Murcia 30002",
    "addr:housenumber":"2",
    "addr:postcode":"30002",
    "addr:street":"Plaz Camachos",
    "iso:country":"ES",
    "sg:address":"Plaz Camachos, 2",
    "sg:city":"Carmen",
    "sg:orig_category":"Asociaciones Y Clubs Deportivos",
    "sg:phone":"+34 968 21 75 51",
    "sg:postcode":"30002",
    "sg:province":"Murcia",
    "wof:name":"Won  Duk Hong",
    "wof:placetype":"venue"
},
  "geometry": {"coordinates":[-1.1298867464,37.9834747314],"type":"Point"}
}