{
  "type": "Feature",
  "properties": {
    "iso:country":"ES",
    "sg:address":"Plaz Padre Vallet, 6",
    "sg:city":"Pozuelo De Alarcon",
    "sg:orig_category":"Pescader\u00cdas (al Por Menor)",
    "sg:phone":"+34 913 52 04 66",
    "sg:postcode":"28223",
    "sg:province":"Madrid",
    "wof:name":"Aparicio Clemente Luis",
    "wof:placetype":"venue"
},
  "geometry": {"coordinates":[-3.8144154549,40.4354133606],"type":"Point"}
}