{
  "type": "Feature",
  "properties": {
    "iso:country":"ES",
    "sg:address":"Calle de Martinez Oviol, 62",
    "sg:city":"Madrid",
    "sg:orig_category":"Promotores Constructores",
    "sg:phone":"+34 917 98 83 91",
    "sg:postcode":"28021",
    "sg:province":"Madrid",
    "wof:name":"Insijos S.l.",
    "wof:placetype":"venue"
},
  "geometry": {"coordinates":[-3.6882829666,40.3492774963],"type":"Point"}
}