{
  "type": "Feature",
  "properties": {
    "addr:full":"Calle de Capitan Angosto Gomez Castrillon (del), 146 Aranjuez Madrid 28300",
    "addr:housenumber":"146",
    "addr:postcode":"28300",
    "addr:street":"Calle De Capitan Angosto Gomez Castrillon Del",
    "iso:country":"ES",
    "sg:address":"Calle de Capitan Angosto Gomez Castrillon (del), 146",
    "sg:city":"Aranjuez",
    "sg:orig_category":"Postigos, Persianas Y Celos\u00cdas",
    "sg:phone":"+34 918 91 17 30",
    "sg:postcode":"28300",
    "sg:province":"Madrid",
    "wof:name":"Persianas Minisol S.l.",
    "wof:placetype":"venue"
},
  "geometry": {"coordinates":[-3.6024632454,40.0296707153],"type":"Point"}
}