{
  "type": "Feature",
  "properties": {
    "addr:full":"Carr Raval De Sant Roc, 42 Raval Valencia 46680",
    "addr:housenumber":"42",
    "addr:postcode":"46680",
    "addr:street":"Carr Raval De Sant Roc",
    "iso:country":"ES",
    "sg:address":"Carr Raval De Sant Roc, 42",
    "sg:city":"Raval",
    "sg:orig_category":"Ferreter\u00cda (diversos)",
    "sg:phone":"+34 902 11 75 42",
    "sg:postcode":"46680",
    "sg:province":"Valencia",
    "wof:name":"Don Ocasion Vehiculos De Ocasion S.l.",
    "wof:placetype":"venue"
},
  "geometry": {"coordinates":[-0.4383490086,39.1962852478],"type":"Point"}
}