{
  "type": "Feature",
  "properties": {
    "iso:country":"ES",
    "sg:address":"Ctra Badajoz, S/n",
    "sg:city":"San Vicente Alcantara",
    "sg:orig_category":"Maquinaria Para Industrias Diversas",
    "sg:phone":"+34 924 41 20 75",
    "sg:postcode":"06500",
    "sg:province":"Badajoz",
    "wof:name":"Hormigo Piriz S.l.",
    "wof:placetype":"venue"
},
  "geometry": {"coordinates":[-7.1398491859,39.3628463745],"type":"Point"}
}