{
  "type": "Feature",
  "properties": {
    "iso:country":"ES",
    "sg:address":"Carrer de Consell De Cent, 301",
    "sg:city":"Barcelona",
    "sg:orig_category":"M\u00c9dicos: Estomatolog\u00cda",
    "sg:phone":"+34 934 54 09 50",
    "sg:postcode":"08007",
    "sg:province":"Barcelona",
    "wof:name":"Pou Cortadellas Enrique",
    "wof:placetype":"venue"
},
  "geometry": {"coordinates":[2.1623430252,41.3887634277],"type":"Point"}
}