{
  "type": "Feature",
  "properties": {
    "iso:country":"ES",
    "sg:address":"Calle de Pinto, 79",
    "sg:city":"Parla",
    "sg:orig_category":"Peluquer\u00cdas, Peluquer\u00cda Mixta",
    "sg:phone":"+34 916 05 62 28",
    "sg:postcode":"28980",
    "sg:province":"Madrid",
    "wof:name":"Eurostyle",
    "wof:placetype":"venue"
},
  "geometry": {"coordinates":[-3.7602300644,40.2399139404],"type":"Point"}
}