{
  "type": "Feature",
  "properties": {
    "addr:full":"Carrer de Banys, 51 Garriga Barcelona 08530",
    "addr:housenumber":"51",
    "addr:postcode":"08530",
    "addr:street":"Carrer De Banys",
    "iso:country":"ES",
    "sg:address":"Carrer de Banys, 51",
    "sg:city":"Garriga",
    "sg:orig_category":"Imprenta",
    "sg:phone":"+34 938 71 85 06",
    "sg:postcode":"08530",
    "sg:province":"Barcelona",
    "wof:name":"Digi Print Grafic S.l.",
    "wof:placetype":"venue"
},
  "geometry": {"coordinates":[2.2862439156,41.6825675964],"type":"Point"}
}