{
  "type": "Feature",
  "properties": {
    "iso:country":"ES",
    "sg:address":"Asomada, 35",
    "sg:city":"Abaran",
    "sg:orig_category":"Asesor\u00cda De Comercio Exterior",
    "sg:phone":"+34 968 45 14 63",
    "sg:postcode":"30550",
    "sg:province":"Murcia",
    "sg:website":"www.fernandezychiclano.com",
    "wof:name":"Fernandez Y Chiclano C.b.",
    "wof:placetype":"venue"
},
  "geometry": {"coordinates":[-1.3944859505,38.2074737549],"type":"Point"}
}