{
  "type": "Feature",
  "properties": {
    "addr:full":"Ptge Espiell, 2 Barcelona Barcelona 08032",
    "addr:housenumber":"2",
    "addr:postcode":"08032",
    "addr:street":"Ptge Espiell",
    "iso:country":"ES",
    "sg:address":"Ptge Espiell, 2",
    "sg:city":"Barcelona",
    "sg:orig_category":"Administradores De Bienes Y Delegados De Comunidades De Propietarios",
    "sg:phone":"+34 934 29 86 95",
    "sg:postcode":"08032",
    "sg:province":"Barcelona",
    "wof:name":"Enrique Perez Aleza Y Cia C.b.",
    "wof:placetype":"venue"
},
  "geometry": {"coordinates":[2.1595590115,41.4250297546],"type":"Point"}
}