{
  "type": "Feature",
  "properties": {
    "iso:country":"ES",
    "sg:address":"Calle de Camino Viejo De Leganes, 177",
    "sg:city":"Madrid",
    "sg:orig_category":"Congelados: Productos Alimentarios (al Por Menor)",
    "sg:phone":"+34 914 65 64 16",
    "sg:postcode":"28025",
    "sg:province":"Madrid",
    "wof:name":"Prados Gil Miguel Angel",
    "wof:placetype":"venue"
},
  "geometry": {"coordinates":[-3.7311840057,40.3810997009],"type":"Point"}
}