{
  "type": "Feature",
  "properties": {
    "iso:country":"ES",
    "sg:address":"Ctra M-506 (san Martin De La Vega), Km. 0001,0",
    "sg:city":"Pinto",
    "sg:orig_category":"Bares, Piano",
    "sg:phone":"+34 916 92 18 29",
    "sg:postcode":"28320",
    "sg:province":"Madrid",
    "wof:name":"Gutierrez Molina Jose Luis",
    "wof:placetype":"venue"
},
  "geometry": {"coordinates":[-3.6993589401,40.2411193848],"type":"Point"}
}