{
  "type": "Feature",
  "properties": {
    "iso:country":"ES",
    "sg:address":"Cint Ronda, S/n",
    "sg:city":"Mave",
    "sg:orig_category":"Ense\u00d1anza, Formaci\u00d3n Profesional: Aprendizaje",
    "sg:phone":"+34 979 12 23 23",
    "sg:postcode":"34492",
    "sg:province":"Palencia",
    "wof:name":"Junta Vecinal De Mave",
    "wof:placetype":"venue"
},
  "geometry": {"coordinates":[-4.2729921341,42.7362632751],"type":"Point"}
}