{
  "type": "Feature",
  "properties": {
    "addr:full":"Pase Maritimo, 91 Torremolinos M\u00e1laga 29620",
    "addr:housenumber":"91",
    "addr:postcode":"29620",
    "addr:street":"Maritimo;Ma\u0301Laga",
    "iso:country":"ES",
    "sg:address":"Pase Maritimo, 91",
    "sg:city":"Torremolinos",
    "sg:orig_category":"Confecci\u00d3n (fabricaci\u00d3n, Al Por Mayor)",
    "sg:phone":"+34 952 37 35 69",
    "sg:postcode":"29620",
    "sg:province":"M\u00e1laga",
    "wof:name":"Mohamed Gladak Y Otros S.l.",
    "wof:placetype":"venue"
},
  "geometry": {"coordinates":[-4.4998540878,36.6244087219],"type":"Point"}
}