{
  "type": "Feature",
  "properties": {
    "addr:full":"Calle de Andalucia, 14 Ajalvir Madrid 28864",
    "addr:housenumber":"14",
    "addr:postcode":"28864",
    "addr:street":"Calle De Andalucia",
    "iso:country":"ES",
    "sg:address":"Calle de Andalucia, 14",
    "sg:city":"Ajalvir",
    "sg:orig_category":"Empresas De Carpinter\u00cda De Madera",
    "sg:phone":"+34 918 84 40 54",
    "sg:postcode":"28864",
    "sg:province":"Madrid",
    "wof:name":"Trabajos Enmadera 2 S.l.",
    "wof:placetype":"venue"
},
  "geometry": {"coordinates":[-3.4910759926,40.5315093994],"type":"Point"}
}