{
  "type": "Feature",
  "properties": {
    "addr:full":"Polig. San Benito, S/n Jerez C\u00e1diz 11407",
    "addr:postcode":"11407",
    "addr:street":"Polig. San Benito S / N",
    "iso:country":"ES",
    "sg:address":"Polig. San Benito, S/n",
    "sg:city":"Jerez",
    "sg:orig_category":"Centros De Educaci\u00d3n Especial",
    "sg:phone":"+34 956 30 52 24",
    "sg:postcode":"11407",
    "sg:province":"C\u00e1diz",
    "wof:name":"Junta De Andalucia",
    "wof:placetype":"venue"
},
  "geometry": {"coordinates":[-6.0982751846,36.7228431702],"type":"Point"}
}