{
  "type": "Feature",
  "properties": {
    "addr:full":"Calle de Rio Guajaraz, 1 Poligono Sta M. De Benquerencia Toledo 45007",
    "addr:housenumber":"1 poligono",
    "addr:postcode":"45007",
    "addr:street":"Calle De Rio Guajaraz;Sta M. De Benquerencia",
    "iso:country":"ES",
    "sg:address":"Calle de Rio Guajaraz, 1",
    "sg:city":"Poligono Sta M. De Benquerencia",
    "sg:orig_category":"Polideportivos",
    "sg:phone":"+34 925 23 26 46",
    "sg:postcode":"45007",
    "sg:province":"Toledo",
    "wof:name":"Patronato Deportivo Municipal De Toledo",
    "wof:placetype":"venue"
},
  "geometry": {"coordinates":[-3.9420120716,39.8697967529],"type":"Point"}
}