{
  "type": "Feature",
  "properties": {
    "addr:full":"Carr Pare Coll, 2 Girona Girona 17005",
    "addr:housenumber":"2",
    "addr:postcode":"17005",
    "addr:street":"Carr Pare Coll",
    "iso:country":"ES",
    "sg:address":"Carr Pare Coll, 2",
    "sg:city":"Girona",
    "sg:orig_category":"Cajas De Ahorro",
    "sg:phone":"+34 972 40 69 58",
    "sg:postcode":"17005",
    "sg:province":"Girona",
    "sg:website":"www.caixadegirona.es",
    "wof:name":"Caixa De Girona",
    "wof:placetype":"venue"
},
  "geometry": {"coordinates":[2.8133919239,41.9770774841],"type":"Point"}
}