{
  "type": "Feature",
  "properties": {
    "iso:country":"ES",
    "sg:address":"Calle de Periodista Azzati, 3",
    "sg:city":"Valencia",
    "sg:orig_category":"Abogados",
    "sg:phone":"+34 963 51 45 91",
    "sg:postcode":"46002",
    "sg:province":"Valencia",
    "wof:name":"Monzon Jose Bego\u00f1a",
    "wof:placetype":"venue"
},
  "geometry": {"coordinates":[-0.3773230016,39.4692649841],"type":"Point"}
}