{
  "type": "Feature",
  "properties": {
    "iso:country":"ES",
    "sg:address":"Avda Olimpica, S/n",
    "sg:city":"Alcobendas",
    "sg:orig_category":"Fisioterapia",
    "sg:phone":"+34 916 61 39 34",
    "sg:postcode":"28108",
    "sg:province":"Madrid",
    "wof:name":"Delgado Ca\u00f1averas Montserrat",
    "wof:placetype":"venue"
},
  "geometry": {"coordinates":[-3.6311841011,40.5369415283],"type":"Point"}
}