{
  "type": "Feature",
  "properties": {
    "addr:full":"Calle de Jaen, 36 Maracena Granada 18200",
    "addr:housenumber":"36",
    "addr:postcode":"18200",
    "addr:street":"Calle De Jaen",
    "iso:country":"ES",
    "sg:address":"Calle de Jaen, 36",
    "sg:city":"Maracena",
    "sg:orig_category":"Ingeniero",
    "sg:phone":"+34 958 42 06 70",
    "sg:postcode":"18200",
    "sg:province":"Granada",
    "wof:name":"Tallon Garcia Luis",
    "wof:placetype":"venue"
},
  "geometry": {"coordinates":[-3.6383368969,37.2091064453],"type":"Point"}
}