{
  "type": "Feature",
  "properties": {
    "iso:country":"ES",
    "sg:address":"Avda Ribados, 14",
    "sg:city":"Burgo",
    "sg:orig_category":"Barquillos De Miel (fabricaci\u00d3n)",
    "sg:phone":"+34 981 66 18 17",
    "sg:postcode":"15670",
    "sg:province":"La Coru\u00f1a",
    "wof:name":"Garcia Bosca Santiago",
    "wof:placetype":"venue"
},
  "geometry": {"coordinates":[-8.4444141388,42.8421287537],"type":"Point"}
}