{
  "type": "Feature",
  "properties": {
    "addr:full":"Plaz Brecha De La, 1 Donostia-san Sebastian Guip\u00f9zcoa 20003",
    "addr:housenumber":"1",
    "addr:postcode":"20003",
    "iso:country":"ES",
    "sg:address":"Plaz Brecha De La, 1",
    "sg:city":"Donostia-san Sebastian",
    "sg:orig_category":"Bisuter\u00cda, Joyer\u00cda, Relojer\u00cda (al Por Menor)",
    "sg:phone":"+34 943 43 10 34",
    "sg:postcode":"20003",
    "sg:province":"Guip\u00f9zcoa",
    "wof:name":"Bediru\u00f1a S.l.",
    "wof:placetype":"venue"
},
  "geometry": {"coordinates":[-1.9794000387,43.3173789978],"type":"Point"}
}