{
  "type": "Feature",
  "properties": {
    "addr:full":"Calle de Palmas (de Las), 51 Mostoles Madrid 28938",
    "addr:housenumber":"51",
    "addr:postcode":"28938",
    "addr:street":"Calle De Palmas De Las",
    "iso:country":"ES",
    "sg:address":"Calle de Palmas (de Las), 51",
    "sg:city":"Mostoles",
    "sg:classifiers":[
        {
            "category":"Autos & Motor Vehicles",
            "subcategory":"Automobile Sales",
            "type":"Retail Goods"
        }
    ],
    "sg:phone":"+34 916 47 65 63",
    "sg:postcode":"28938",
    "sg:province":"Madrid",
    "wof:name":"Cridomar S.l.",
    "wof:placetype":"venue"
},
  "geometry": {"coordinates":[-3.8662590981,40.3169364929],"type":"Point"}
}