{
  "type": "Feature",
  "properties": {
    "iso:country":"ES",
    "sg:address":"Carrer de General Prim (del), 4",
    "sg:city":"Montornes Centre",
    "sg:orig_category":"Traductores",
    "sg:phone":"+34 935 72 02 98",
    "sg:postcode":"08170",
    "sg:province":"Barcelona",
    "wof:name":"Masters Restell Heathers",
    "wof:placetype":"venue"
},
  "geometry": {"coordinates":[2.265805006,41.5413093567],"type":"Point"}
}