{
  "type": "Feature",
  "properties": {
    "addr:full":"Carr Santa Maria, 3 Seu D'urgell Lleida 25700",
    "addr:housenumber":"3",
    "addr:postcode":"25700",
    "addr:street":"Carr Santa Maria",
    "iso:country":"ES",
    "sg:address":"Carr Santa Maria, 3",
    "sg:city":"Seu D'urgell",
    "sg:orig_category":"Reposter\u00cdas",
    "sg:phone":"+34 973 35 03 06",
    "sg:postcode":"25700",
    "sg:province":"Lleida",
    "wof:name":"Lebron Segovia Montserrat",
    "wof:placetype":"venue"
},
  "geometry": {"coordinates":[1.4609062672,42.3577194214],"type":"Point"}
}