{
  "type": "Feature",
  "properties": {
    "addr:full":"Avda Iparraguirre, 3 Zumarraga Guip\u00f9zcoa 20700",
    "addr:housenumber":"3",
    "addr:postcode":"20700",
    "addr:street":"Avda Iparraguirre;Guipu\u0300Zcoa",
    "iso:country":"ES",
    "sg:address":"Avda Iparraguirre, 3",
    "sg:city":"Zumarraga",
    "sg:orig_category":"Promotores Constructores",
    "sg:phone":"+34 943 72 16 61",
    "sg:postcode":"20700",
    "sg:province":"Guip\u00f9zcoa",
    "wof:name":"Construcciones Francisco Mugica S. L.",
    "wof:placetype":"venue"
},
  "geometry": {"coordinates":[-2.3138520718,43.0892410278],"type":"Point"}
}