{
  "type": "Feature",
  "properties": {
    "iso:country":"ES",
    "sg:address":"Cra Esporles, 63",
    "sg:city":"Establiments Nou",
    "sg:orig_category":"Peluqueros: De Se\u00d1oras",
    "sg:phone":"+34 971 76 80 19",
    "sg:postcode":"07010",
    "sg:province":"Islas Baleares",
    "wof:name":"Cifuentes Mu\u00f1oz Maria",
    "wof:placetype":"venue"
},
  "geometry": {"coordinates":[2.6354699135,39.6081161499],"type":"Point"}
}