{
  "type": "Feature",
  "properties": {
    "addr:full":"Calle de Jabonerias, 12 Cartagena Murcia 30201",
    "addr:housenumber":"12",
    "addr:postcode":"30201",
    "addr:street":"Calle De Jabonerias",
    "iso:country":"ES",
    "sg:address":"Calle de Jabonerias, 12",
    "sg:city":"Cartagena",
    "sg:orig_category":"Inmobiliaria (agencias)",
    "sg:phone":"+34 968 12 26 66",
    "sg:postcode":"30201",
    "sg:province":"Murcia",
    "wof:name":"Promotora Urbana De Cartagena S. A.",
    "wof:placetype":"venue"
},
  "geometry": {"coordinates":[-0.9896280169,37.6036338806],"type":"Point"}
}