{
  "type": "Feature",
  "properties": {
    "iso:country":"ES",
    "sg:address":"Rua Caravel, 12",
    "sg:city":"Lugo",
    "sg:orig_category":"Sociedades, Compa\u00d1\u00cdas Aseguradoras",
    "sg:phone":"+34 982 21 84 66",
    "sg:postcode":"27003",
    "sg:province":"Lugo",
    "wof:name":"Granda Barreiro Rocio",
    "wof:placetype":"venue"
},
  "geometry": {"coordinates":[-7.5712900162,43.0296134949],"type":"Point"}
}