{
  "type": "Feature",
  "properties": {
    "addr:full":"Plaz Puente Malaga, 2 Marbella M\u00e1laga 29600",
    "addr:housenumber":"2",
    "addr:postcode":"29600",
    "addr:street":"Plaz;Malaga;Ma\u0301Laga",
    "iso:country":"ES",
    "sg:address":"Plaz Puente Malaga, 2",
    "sg:city":"Marbella",
    "sg:orig_category":"Carnicer\u00cdas, Carnicer\u00cdas",
    "sg:phone":"+34 952 86 37 82",
    "sg:postcode":"29600",
    "sg:province":"M\u00e1laga",
    "wof:name":"Gonzalez Lopez Maria Del Pilar",
    "wof:placetype":"venue"
},
  "geometry": {"coordinates":[-4.8823289871,36.5100898743],"type":"Point"}
}