{
  "type": "Feature",
  "properties": {
    "addr:full":"Ctra Alhama, Km. 0021,0 Fuente Alamo Murcia 30320",
    "addr:postcode":"30320",
    "addr:street":"Ctra Alhama Km. 0021,0",
    "iso:country":"ES",
    "sg:address":"Ctra Alhama, Km. 0021,0",
    "sg:city":"Fuente Alamo",
    "sg:orig_category":"Mec\u00c1nico Del Autom\u00d3vil",
    "sg:phone":"+34 968 59 75 12",
    "sg:postcode":"30320",
    "sg:province":"Murcia",
    "wof:name":"Fernando Miras Molino C.b.",
    "wof:placetype":"venue"
},
  "geometry": {"coordinates":[-1.1687190533,37.7235946655],"type":"Point"}
}