{
  "type": "Feature",
  "properties": {
    "addr:full":"Avgd Pius Xii, 5 Lleida Lleida 25003",
    "addr:housenumber":"5",
    "addr:postcode":"25003",
    "addr:street":"Xii",
    "iso:country":"ES",
    "sg:address":"Avgd Pius Xii, 5",
    "sg:city":"Lleida",
    "sg:orig_category":"Mec\u00c1nico Del Autom\u00d3vil",
    "sg:phone":"+34 973 26 10 47",
    "sg:postcode":"25003",
    "sg:province":"Lleida",
    "wof:name":"Gonzalez Navarro Manuel",
    "wof:placetype":"venue"
},
  "geometry": {"coordinates":[0.6162077188,41.6156196594],"type":"Point"}
}