{
  "type": "Feature",
  "properties": {
    "addr:full":"Avda Estacion (de La), 6 Abaran Murcia 30550",
    "addr:housenumber":"6",
    "addr:postcode":"30550",
    "addr:street":"Avda Estacion De La",
    "iso:country":"ES",
    "sg:address":"Avda Estacion (de La), 6",
    "sg:city":"Abaran",
    "sg:orig_category":"Librer\u00cdas",
    "sg:phone":"+34 968 77 03 13",
    "sg:postcode":"30550",
    "sg:province":"Murcia",
    "wof:name":"Yelo Bermejo Antonio",
    "wof:placetype":"venue"
},
  "geometry": {"coordinates":[-1.384909749,38.2072257996],"type":"Point"}
}