{
  "type": "Feature",
  "properties": {
    "iso:country":"ES",
    "sg:address":"Carrer de Concili De Trento, 106",
    "sg:city":"Barcelona",
    "sg:orig_category":"Asociaciones, Organismos Culturales Y Socioeducativos",
    "sg:phone":"+34 933 03 29 93",
    "sg:postcode":"08020",
    "sg:province":"Barcelona",
    "wof:name":"Centro Social Y Cultural Santo Angel",
    "wof:placetype":"venue"
},
  "geometry": {"coordinates":[2.1964950562,41.4139709473],"type":"Point"}
}