{
  "type": "Feature",
  "properties": {
    "iso:country":"ES",
    "sg:address":"Carrer de Sant Miquel Dels Sants, 5",
    "sg:city":"Vic",
    "sg:orig_category":"Empresarios",
    "sg:phone":"+34 938 89 13 67",
    "sg:postcode":"08500",
    "sg:province":"Barcelona",
    "wof:name":"Fundacion Privada Casa De Caridad De Vic",
    "wof:placetype":"venue"
},
  "geometry": {"coordinates":[2.2546920776,41.9296798706],"type":"Point"}
}