{
  "type": "Feature",
  "properties": {
    "iso:country":"ES",
    "sg:address":"Avda Oltra Molto, 28",
    "sg:city":"Torres Cotillas",
    "sg:orig_category":"Maquinaria Para Industrias Diversas",
    "sg:phone":"+34 968 62 81 50",
    "sg:postcode":"30565",
    "sg:province":"Murcia",
    "wof:name":"Excavaciones Galmar S.l.",
    "wof:placetype":"venue"
},
  "geometry": {"coordinates":[-1.2438290119,38.0287628174],"type":"Point"}
}