{
  "type": "Feature",
  "properties": {
    "addr:full":"Calle de Porcelana (fta), 1 Madrid Madrid 28013",
    "addr:housenumber":"1",
    "addr:postcode":"28013",
    "addr:street":"Calle De Porcelana Fta",
    "iso:country":"ES",
    "sg:address":"Calle de Porcelana (fta), 1",
    "sg:city":"Madrid",
    "sg:orig_category":"Restaurantes",
    "sg:phone":"+34 915 59 11 72",
    "sg:postcode":"28013",
    "sg:province":"Madrid",
    "wof:name":"Hermanos Lopez Tarrio S.l.",
    "wof:placetype":"venue"
},
  "geometry": {"coordinates":[-3.6153690815,40.4261894226],"type":"Point"}
}