{
  "type": "Feature",
  "properties": {
    "addr:full":"Pol Indust Malpica F, 48 Pol. Malpica Zaragoza 50057",
    "addr:housenumber":"48",
    "addr:postcode":"50057",
    "addr:street":"Indust Malpica F;Pol. Malpica",
    "iso:country":"ES",
    "sg:address":"Pol Indust Malpica F, 48",
    "sg:city":"Pol. Malpica",
    "sg:orig_category":"Molduras, Junquillos, Listones Y Molduras Perforadas",
    "sg:phone":"+34 976 57 76 57",
    "sg:postcode":"50057",
    "sg:province":"Zaragoza",
    "wof:name":"Aznar Armengol Fernando",
    "wof:placetype":"venue"
},
  "geometry": {"coordinates":[-0.8765661716,41.6563491821],"type":"Point"}
}