{
  "type": "Feature",
  "properties": {
    "iso:country":"ES",
    "sg:address":"Mecanica (pol Ind La Drecera), 5",
    "sg:city":"Selva Del Camp",
    "sg:orig_category":"Quincaller\u00cda (al Por Menor)",
    "sg:phone":"+34 977 76 61 27",
    "sg:postcode":"43470",
    "sg:province":"Tarragona",
    "wof:name":"Ferreteria Industrial Servimakina S.l",
    "wof:placetype":"venue"
},
  "geometry": {"coordinates":[1.1487350464,41.2154541016],"type":"Point"}
}