{
  "type": "Feature",
  "properties": {
    "addr:full":"Plaz Monjas Las, 10 Huelva Huelva 21001",
    "addr:housenumber":"10",
    "addr:postcode":"21001",
    "addr:street":"Plaz Monjas Las",
    "iso:country":"ES",
    "sg:address":"Plaz Monjas Las, 10",
    "sg:city":"Huelva",
    "sg:orig_category":"Talleres: Ropa A Medida",
    "sg:phone":"+34 959 28 59 66",
    "sg:postcode":"21001",
    "sg:province":"Huelva",
    "wof:name":"Rodes Suero Antonio Manuel",
    "wof:placetype":"venue"
},
  "geometry": {"coordinates":[-6.9495940208,37.256313324],"type":"Point"}
}