{
  "type": "Feature",
  "properties": {
    "addr:full":"Ctra Rafelguaraf, Km. 0000,2 Pobla Llarga Valencia 46670",
    "addr:postcode":"46670",
    "addr:street":"Ctra Rafelguaraf Km. 0000,2",
    "iso:country":"ES",
    "sg:address":"Ctra Rafelguaraf, Km. 0000,2",
    "sg:city":"Pobla Llarga",
    "sg:orig_category":"Muebles Y Accesorios Para Cocinas Y Cuartos De Ba\u00d1o (al Por Menor)",
    "sg:phone":"+34 962 97 07 72",
    "sg:postcode":"46670",
    "sg:province":"Valencia",
    "wof:name":"L.t Aqua Plus Iberica S.l.u.",
    "wof:placetype":"venue"
},
  "geometry": {"coordinates":[-0.4746389985,39.0884284973],"type":"Point"}
}