{
  "type": "Feature",
  "properties": {
    "iso:country":"ES",
    "sg:address":"Ctra Segovia, Km. 0063,0",
    "sg:city":"San Rafael",
    "sg:orig_category":"Empresas De Carpinter\u00cda De Madera",
    "sg:phone":"+34 921 17 18 62",
    "sg:postcode":"40410",
    "sg:province":"Segovia",
    "wof:name":"Martin Moral Gonzalo",
    "wof:placetype":"venue"
},
  "geometry": {"coordinates":[-4.1855669022,40.7127342224],"type":"Point"}
}