{
  "type": "Feature",
  "properties": {
    "addr:full":"Calle de Flores Las, S/n Arroyo De La Miel-benalmadena Costa M\u00e1laga 29631",
    "addr:postcode":"29631",
    "addr:street":"Calle De Flores Las S / N Arroyo De La Miel-Benalmadena Costa Ma\u0301Laga",
    "iso:country":"ES",
    "sg:address":"Calle de Flores Las, S/n",
    "sg:city":"Arroyo De La Miel-benalmadena Costa",
    "sg:orig_category":"Sociedades, Compa\u00d1\u00cdas Aseguradoras",
    "sg:phone":"+34 952 56 42 86",
    "sg:postcode":"29631",
    "sg:province":"M\u00e1laga",
    "sg:website":"www.santalucia.es",
    "wof:name":"Santa Lucia S.a.",
    "wof:placetype":"venue"
},
  "geometry": {"coordinates":[-4.5482521057,36.6017608643],"type":"Point"}
}