{
  "type": "Feature",
  "properties": {
    "addr:full":"Ctra De La Fuente, Km. 0002,6 Estepa Sevilla 41560",
    "addr:postcode":"41560",
    "addr:street":"Ctra De La Fuente Km. 0002,6;Sevilla",
    "iso:country":"ES",
    "sg:address":"Ctra De La Fuente, Km. 0002,6",
    "sg:city":"Estepa",
    "sg:orig_category":"Contenedores (mercanc\u00cdas)",
    "sg:phone":"+34 955 91 38 24",
    "sg:postcode":"41560",
    "sg:province":"Sevilla",
    "wof:name":"Estepatrans S.cooperativa Andaluza",
    "wof:placetype":"venue"
},
  "geometry": {"coordinates":[-4.871740818,37.2891731262],"type":"Point"}
}