{
  "type": "Feature",
  "properties": {
    "addr:full":"Calle de O'donnell, 41 Madrid Madrid 28009",
    "addr:housenumber":"41",
    "addr:postcode":"madrid;28009",
    "addr:street":"Calle De O'Donnell",
    "iso:country":"ES",
    "sg:address":"Calle de O'donnell, 41",
    "sg:city":"Madrid",
    "sg:orig_category":"M\u00c9dicos: Cirug\u00cda Pl\u00c1stica, Reconstructiva Y Est\u00c9tica",
    "sg:phone":"+34 914 31 78 61",
    "sg:postcode":"28009",
    "sg:province":"Madrid",
    "wof:name":"Jaen Olasolo Pedro",
    "wof:placetype":"venue"
},
  "geometry": {"coordinates":[-3.675194025,40.4215507507],"type":"Point"}
}