{
  "type": "Feature",
  "properties": {
    "addr:full":"Carrer de Santa Eulalia, 151 Hospitalet Llobregat Barcelona 08902",
    "addr:housenumber":"151",
    "addr:postcode":"08902",
    "addr:street":"Carrer De Santa Eulalia",
    "iso:country":"ES",
    "sg:address":"Carrer de Santa Eulalia, 151",
    "sg:city":"Hospitalet Llobregat",
    "sg:orig_category":"Alquiler De V\u00cddeo",
    "sg:phone":"+34 933 32 72 32",
    "sg:postcode":"08902",
    "sg:province":"Barcelona",
    "wof:name":"85 Video Club S.l.",
    "wof:placetype":"venue"
},
  "geometry": {"coordinates":[2.123037,41.366405],"type":"Point"}
}