{
  "type": "Feature",
  "properties": {
    "iso:country":"ES",
    "sg:address":"Calle de San Cristobal, 37",
    "sg:city":"Puente-genil",
    "sg:orig_category":"Ense\u00d1ante, Direcci\u00d3n",
    "sg:phone":"+34 957 60 03 02",
    "sg:postcode":"14500",
    "sg:province":"C\u00f3rdoba",
    "wof:name":"Cruz Jurado Alfonso",
    "wof:placetype":"venue"
},
  "geometry": {"coordinates":[-4.7713608742,37.389175415],"type":"Point"}
}