{
  "type": "Feature",
  "properties": {
    "iso:country":"ES",
    "sg:address":"Poligono Segarra, S/n",
    "sg:city":"Vall Uixo",
    "sg:orig_category":"Zapatos: Material, Suministros, Accesorios (fabricaci\u00d3n, Al Por Mayor)",
    "sg:phone":"+34 964 69 15 90",
    "sg:postcode":"12600",
    "sg:province":"Castell\u00f3n",
    "wof:name":"Lopez Marti Joaquin",
    "wof:placetype":"venue"
},
  "geometry": {"coordinates":[-0.2325990051,39.8129615784],"type":"Point"}
}