{
  "type": "Feature",
  "properties": {
    "iso:country":"ES",
    "sg:address":"Argentina(bda H America), 1",
    "sg:city":"Los Dolores",
    "sg:orig_category":"Confiter\u00cdas, Chocolater\u00cdas (al Por Menor)",
    "sg:phone":"+34 968 51 20 23",
    "sg:postcode":"30310",
    "sg:province":"Murcia",
    "wof:name":"Pan Flori S. A.",
    "wof:placetype":"venue"
},
  "geometry": {"coordinates":[-1.010964036,37.6348953247],"type":"Point"}
}