{
  "type": "Feature",
  "properties": {
    "iso:country":"ES",
    "sg:address":"Rua Toural, 17",
    "sg:city":"Cambre",
    "sg:orig_category":"Electricidad: Instaladores",
    "sg:phone":"+34 981 67 57 92",
    "sg:postcode":"15660",
    "sg:province":"A Coru\u00f1a",
    "wof:name":"Souto Varela Jose Antonio",
    "wof:placetype":"venue"
},
  "geometry": {"coordinates":[-8.3438081741,43.2973251343],"type":"Point"}
}