{
  "type": "Feature",
  "properties": {
    "iso:country":"ES",
    "sg:address":"Av Joan Miro, 5",
    "sg:city":"Palma",
    "sg:orig_category":"Tintorer\u00cdas, Limpieza En Seco",
    "sg:phone":"+34 971 45 46 14",
    "sg:postcode":"07014",
    "sg:province":"Islas Baleares",
    "wof:name":"Bugaderia Fast S.l.",
    "wof:placetype":"venue"
},
  "geometry": {"coordinates":[2.6271309853,39.5665473938],"type":"Point"}
}