{
  "type": "Feature",
  "properties": {
    "iso:country":"ES",
    "sg:address":"Carrer de Mossen Antoni Solanas, 84",
    "sg:city":"S. Boi Llobregat",
    "sg:orig_category":"Empresas De Limpieza",
    "sg:phone":"+34 936 35 41 35",
    "sg:postcode":"08830",
    "sg:province":"Barcelona",
    "wof:name":"Limpiezas El Teide S.l.",
    "wof:placetype":"venue"
},
  "geometry": {"coordinates":[2.0422959328,41.3368377686],"type":"Point"}
}