{
  "type": "Feature",
  "properties": {
    "addr:full":"Carrer de Costa Rica, 10 Palma Islas Baleares 07014",
    "addr:housenumber":"10",
    "addr:postcode":"07014",
    "addr:street":"Carrer De Costa Rica",
    "iso:country":"ES",
    "sg:address":"Carrer de Costa Rica, 10",
    "sg:city":"Palma",
    "sg:classifiers":[
        {
            "category":"Home & Garden",
            "subcategory":"Household Appliances",
            "type":"Retail Goods"
        }
    ],
    "sg:phone":"+34 971 28 62 92",
    "sg:postcode":"07014",
    "sg:province":"Islas Baleares",
    "sg:tags":[
        "bodega",
        "de",
        "vino",
        "acondicionamiento"
    ],
    "sg:website":"www.freixenet.com",
    "wof:name":"Comercial Grupo Freixenet S.a.",
    "wof:placetype":"venue"
},
  "geometry": {"coordinates":[2.6287391186,39.5734291077],"type":"Point"}
}