{
  "type": "Feature",
  "properties": {
    "addr:full":"Carrer de Bogatell, 62 S. Adria Besos Barcelona 08930",
    "addr:housenumber":"62",
    "addr:postcode":"08930",
    "addr:street":"Carrer De Bogatell;S. Adria Besos Barcelona",
    "iso:country":"ES",
    "sg:address":"Carrer de Bogatell, 62",
    "sg:city":"S. Adria Besos",
    "sg:orig_category":"Mec\u00c1nico Del Autom\u00d3vil",
    "sg:phone":"+34 933 81 10 58",
    "sg:postcode":"08930",
    "sg:province":"Barcelona",
    "wof:name":"Alcantud Roman Francisco",
    "wof:placetype":"venue"
},
  "geometry": {"coordinates":[2.2193841934,41.4289779663],"type":"Point"}
}