{
  "type": "Feature",
  "properties": {
    "iso:country":"ES",
    "sg:address":"Calle de Leganes, S/n",
    "sg:city":"Getafe",
    "sg:orig_category":"Distribuci\u00d3n De Petr\u00d3leo Y Derivados",
    "sg:phone":"+34 916 83 77 22",
    "sg:postcode":"28904",
    "sg:province":"Madrid",
    "wof:name":"Oiland Europea S.l.",
    "wof:placetype":"venue"
},
  "geometry": {"coordinates":[-3.7385139465,40.3119697571],"type":"Point"}
}