{
  "type": "Feature",
  "properties": {
    "iso:country":"ES",
    "sg:address":"Calle de Caudal, 70",
    "sg:city":"Malaga",
    "sg:classifiers":[
        {
            "category":"Taxi",
            "type":"Transportation"
        }
    ],
    "sg:phone":"+34 952 04 08 04",
    "sg:postcode":"29006",
    "sg:province":"M\u00e1laga",
    "wof:name":"Taxi Union Sociedad Cooperativa Andaluza",
    "wof:placetype":"venue"
},
  "geometry": {"coordinates":[-4.486468792,36.7125778198],"type":"Point"}
}