{
  "type": "Feature",
  "properties": {
    "addr:full":"Avda. Constitucion, 94 Moreda Asturias 33670",
    "addr:housenumber":"94",
    "addr:postcode":"33670",
    "addr:street":"Avda. Constitucion",
    "iso:country":"ES",
    "sg:address":"Avda. Constitucion, 94",
    "sg:city":"Moreda",
    "sg:orig_category":"Imprenta",
    "sg:phone":"+34 985 48 05 39",
    "sg:postcode":"33670",
    "sg:province":"Asturias",
    "wof:name":"Gonzalez Tejon Raquel",
    "wof:placetype":"venue"
},
  "geometry": {"coordinates":[-5.7416834831,43.1710586548],"type":"Point"}
}