{
  "type": "Feature",
  "properties": {
    "addr:full":"Calle de Capitan Angosto Gomez Castrillon (del), 110 Aranjuez Madrid 28300",
    "addr:housenumber":"110",
    "addr:postcode":"28300",
    "addr:street":"Calle De Capitan Angosto Gomez Castrillon Del",
    "iso:country":"ES",
    "sg:address":"Calle de Capitan Angosto Gomez Castrillon (del), 110",
    "sg:city":"Aranjuez",
    "sg:orig_category":"Herboristas (al Por Menor)",
    "sg:phone":"+34 918 92 31 84",
    "sg:postcode":"28300",
    "sg:province":"Madrid",
    "wof:name":"Albar Lucas Pedro",
    "wof:placetype":"venue"
},
  "geometry": {"coordinates":[-3.602247715,40.031211853],"type":"Point"}
}