{
  "type": "Feature",
  "properties": {
    "iso:country":"ES",
    "sg:address":"Calle de F(campollano), 26",
    "sg:city":"Albacete",
    "sg:orig_category":"Triper\u00cdas",
    "sg:phone":"+34 967 21 08 26",
    "sg:postcode":"02006",
    "sg:province":"Albacete",
    "wof:name":"Garcia Pardo Jose",
    "wof:placetype":"venue"
},
  "geometry": {"coordinates":[-1.9490209818,39.013168335],"type":"Point"}
}