{
  "type": "Feature",
  "properties": {
    "addr:full":"Pl Esglesia, 3 Tordera Barcelona 08490",
    "addr:housenumber":"3",
    "addr:postcode":"08490",
    "addr:street":"Pl Esglesia",
    "iso:country":"ES",
    "sg:address":"Pl Esglesia, 3",
    "sg:city":"Tordera",
    "sg:orig_category":"Cajas De Ahorro",
    "sg:phone":"+34 937 64 05 99",
    "sg:postcode":"08490",
    "sg:province":"Barcelona",
    "wof:name":"Caixa D'estalvis Laietana",
    "wof:placetype":"venue"
},
  "geometry": {"coordinates":[2.7190649509,41.7016639709],"type":"Point"}
}