{
  "type": "Feature",
  "properties": {
    "addr:full":"Calle de Jose Maria Osborne, 1 Sevilla Sevilla 41004",
    "addr:housenumber":"1",
    "addr:postcode":"41004",
    "addr:street":"Calle De Jose Maria Osborne",
    "iso:country":"ES",
    "sg:address":"Calle de Jose Maria Osborne, 1",
    "sg:city":"Sevilla",
    "sg:orig_category":"Formaci\u00d3n Continuada (variada)",
    "sg:phone":"+34 954 53 08 03",
    "sg:postcode":"41004",
    "sg:province":"Sevilla",
    "wof:name":"Cruzado Ramon Ignacio",
    "wof:placetype":"venue"
},
  "geometry": {"coordinates":[-5.9864320755,37.3812408447],"type":"Point"}
}