{
  "type": "Feature",
  "properties": {
    "iso:country":"ES",
    "sg:address":"Calle de Canalejas, 14",
    "sg:city":"Palmas De Gran Canaria",
    "sg:orig_category":"Inform\u00c1tica (estudios, Servicios, Asesor\u00cda, Formaci\u00d3n)",
    "sg:phone":"+34 928 38 56 12",
    "sg:postcode":"35003",
    "sg:province":"Las Palmas",
    "wof:name":"Alba Asesores Integrales Sl",
    "wof:placetype":"venue"
},
  "geometry": {"coordinates":[-15.4197263718,28.1090927124],"type":"Point"}
}