{
  "type": "Feature",
  "properties": {
    "iso:country":"ES",
    "sg:address":"Chapitela-txapitela Kalea, 20",
    "sg:city":"Iru\u00f1a",
    "sg:orig_category":"Ropa Para Se\u00d1oras (al Por Menor)",
    "sg:phone":"+34 948 22 05 30",
    "sg:postcode":"31001",
    "sg:province":"Navarra",
    "wof:name":"Unzu S.a.",
    "wof:placetype":"venue"
},
  "geometry": {"coordinates":[-1.6430380344,42.8176231384],"type":"Point"}
}