{
  "type": "Feature",
  "properties": {
    "addr:full":"Calle de Juan Ramon Jimenez, S/n Burgos Burgos 09007",
    "addr:postcode":"09007",
    "addr:street":"Calle De Juan Ramon Jimenez S / N",
    "iso:country":"ES",
    "sg:address":"Calle de Juan Ramon Jimenez, S/n",
    "sg:city":"Burgos",
    "sg:orig_category":"Venta De Caravanas, Casas M\u00d3viles, Camping",
    "sg:phone":"+34 947 48 49 48",
    "sg:postcode":"09007",
    "sg:province":"Burgos",
    "sg:website":"www.mnorte.com",
    "wof:name":"Metalurgicas Norte Burgos S.l.",
    "wof:placetype":"venue"
},
  "geometry": {"coordinates":[-3.6618552208,42.352848053],"type":"Point"}
}