{
  "type": "Feature",
  "properties": {
    "addr:full":"Ctra Ceuti (de), 3 Alguazas Murcia 30560",
    "addr:housenumber":"3",
    "addr:postcode":"30560",
    "addr:street":"Ctra Ceuti De",
    "iso:country":"ES",
    "sg:address":"Ctra Ceuti (de), 3",
    "sg:city":"Alguazas",
    "sg:orig_category":"Centros Empresariales",
    "sg:phone":"+34 968 62 00 06",
    "sg:postcode":"30560",
    "sg:province":"Murcia",
    "wof:name":"Comunidad De Regantes San Onofre",
    "wof:placetype":"venue"
},
  "geometry": {"coordinates":[-1.2478189468,38.0530853271],"type":"Point"}
}