{
  "type": "Feature",
  "properties": {
    "addr:full":"Calle de Alzukaitz Kalea, 1 Irun Guip\u00f9zcoa 20304",
    "addr:housenumber":"1",
    "addr:postcode":"20304",
    "addr:street":"Calle De Alzukaitz Kalea;Guipu\u0300Zcoa",
    "iso:country":"ES",
    "sg:address":"Calle de Alzukaitz Kalea, 1",
    "sg:city":"Irun",
    "sg:orig_category":"Molduras, Junquillos, Listones Y Molduras Perforadas",
    "sg:phone":"+34 943 62 15 75",
    "sg:postcode":"20304",
    "sg:province":"Guip\u00f9zcoa",
    "wof:name":"Call Phone S.l.",
    "wof:placetype":"venue"
},
  "geometry": {"coordinates":[-1.7795410156,43.3367424011],"type":"Point"}
}