{
  "type": "Feature",
  "properties": {
    "addr:full":"Polig. Ind. A Granxa, 1 Porri\u00f1o Pontevedra 36475",
    "addr:housenumber":"1",
    "addr:postcode":"36475",
    "addr:street":"Polig. Ind. A Granxa",
    "iso:country":"ES",
    "sg:address":"Polig. Ind. A Granxa, 1",
    "sg:city":"Porri\u00f1o",
    "sg:orig_category":"Congelados: Productos Alimentarios (fabricaci\u00d3n, Al Por Mayor)",
    "sg:phone":"+34 986 45 33 60",
    "sg:postcode":"36475",
    "sg:province":"Pontevedra",
    "wof:name":"Pescasilva S.l.",
    "wof:placetype":"venue"
},
  "geometry": {"coordinates":[-8.606926918,42.1053466797],"type":"Point"}
}