{
  "type": "Feature",
  "properties": {
    "iso:country":"ES",
    "sg:address":"Carr Sant Ramon (de), 2",
    "sg:city":"Artesa Lleida",
    "sg:orig_category":"Peluquer\u00cdas, Peluquer\u00cda Mixta",
    "sg:phone":"+34 973 16 75 60",
    "sg:postcode":"25150",
    "sg:province":"Lleida",
    "wof:name":"Gallart Arbones Maria Carme",
    "wof:placetype":"venue"
},
  "geometry": {"coordinates":[0.7057800293,41.5531044006],"type":"Point"}
}