{
  "type": "Feature",
  "properties": {
    "addr:full":"Calle de Rafael Gallego Sainz, 1 Oviedo Asturias 33012",
    "addr:housenumber":"1",
    "addr:postcode":"33012",
    "addr:street":"Calle De Rafael Gallego Sainz",
    "iso:country":"ES",
    "sg:address":"Calle de Rafael Gallego Sainz, 1",
    "sg:city":"Oviedo",
    "sg:orig_category":"Congelados: Productos Alimentarios (al Por Menor)",
    "sg:phone":"+34 985 27 31 77",
    "sg:postcode":"33012",
    "sg:province":"Asturias",
    "wof:name":"Congelados Del Cantabrico S.l.",
    "wof:placetype":"venue"
},
  "geometry": {"coordinates":[-5.8661060333,43.3677978516],"type":"Point"}
}