{
  "type": "Feature",
  "properties": {
    "addr:full":"Hont, 8 Bagergue Lleida 25598",
    "addr:housenumber":"8",
    "addr:postcode":"25598",
    "addr:street":"Hont",
    "iso:country":"ES",
    "sg:address":"Hont, 8",
    "sg:city":"Bagergue",
    "sg:orig_category":"Restaurantes",
    "sg:phone":"+34 973 64 53 87",
    "sg:postcode":"25598",
    "sg:province":"Lleida",
    "wof:name":"Tarrau Tomas Jose Antonio",
    "wof:placetype":"venue"
},
  "geometry": {"coordinates":[0.9334179759,42.6994895935],"type":"Point"}
}