{
  "type": "Feature",
  "properties": {
    "iso:country":"ES",
    "sg:address":"Pase Dr Fernandez Iparraguirre, 14",
    "sg:city":"Guadalajara",
    "sg:orig_category":"Agencias De Trabajo Temporal",
    "sg:phone":"+34 949 22 76 11",
    "sg:postcode":"19001",
    "sg:province":"Guadalajara",
    "wof:name":"United Services Spain Back-office S.l.",
    "wof:placetype":"venue"
},
  "geometry": {"coordinates":[-3.1675269604,40.6296195984],"type":"Point"}
}