{
  "type": "Feature",
  "properties": {
    "iso:country":"ES",
    "sg:address":"Calle de Poeta Llorente, 186",
    "sg:city":"Pobla Vallbona",
    "sg:orig_category":"Venta, Montaje De Neum\u00c1ticos",
    "sg:phone":"+34 962 76 04 41",
    "sg:postcode":"46185",
    "sg:province":"Valencia",
    "wof:name":"Neumaticos David S.l.",
    "wof:placetype":"venue"
},
  "geometry": {"coordinates":[-0.5433109999,39.5892219543],"type":"Point"}
}