{
  "type": "Feature",
  "properties": {
    "iso:country":"ES",
    "sg:address":"Carrer de Rafael Batlle, 17",
    "sg:city":"Barcelona",
    "sg:orig_category":"Confecci\u00d3n (fabricaci\u00d3n, Al Por Mayor)",
    "sg:phone":"+34 932 80 57 98",
    "sg:postcode":"08017",
    "sg:province":"Barcelona",
    "wof:name":"Sabata Mir Maria Isabel",
    "wof:placetype":"venue"
},
  "geometry": {"coordinates":[2.1269440651,41.3961296082],"type":"Point"}
}