{
  "type": "Feature",
  "properties": {
    "iso:country":"ES",
    "sg:address":"Calle de Zear-kalea, 5",
    "sg:city":"Markina-xemein",
    "sg:orig_category":"Artesan\u00cda",
    "sg:phone":"+34 946 16 62 80",
    "sg:postcode":"48270",
    "sg:province":"Vizcaya",
    "wof:name":"Arriaga Arrizabalaga Jose Pablo",
    "wof:placetype":"venue"
},
  "geometry": {"coordinates":[-2.5056610107,43.1866874695],"type":"Point"}
}