{
  "type": "Feature",
  "properties": {
    "iso:country":"ES",
    "sg:address":"C/ Masdevall, 21",
    "sg:city":"Banyoles",
    "sg:orig_category":"Productos Alimentarios",
    "sg:phone":"+34 972 58 01 00",
    "sg:postcode":"17820",
    "sg:province":"Girona",
    "wof:name":"Nutrex Pinsos S.l.",
    "wof:placetype":"venue"
},
  "geometry": {"coordinates":[2.7693500519,42.1146736145],"type":"Point"}
}