{
  "type": "Feature",
  "properties": {
    "addr:full":"Avda Zurriola De, 24 Donostia-san Sebastian Guip\u00f9zcoa 20002",
    "addr:housenumber":"24",
    "addr:postcode":"20002",
    "addr:street":"Avda Zurriola De",
    "iso:country":"ES",
    "sg:address":"Avda Zurriola De, 24",
    "sg:city":"Donostia-san Sebastian",
    "sg:orig_category":"Deportes Y Ocio: Art\u00cdculos Y Ropas (al Por Menor Y Accesorios)",
    "sg:phone":"+34 943 32 00 68",
    "sg:postcode":"20002",
    "sg:province":"Guip\u00f9zcoa",
    "sg:website":"www.pukassurf.com",
    "wof:name":"Pukas Surf S.l.",
    "wof:placetype":"venue"
},
  "geometry": {"coordinates":[-1.9758540392,43.3248901367],"type":"Point"}
}