{
  "type": "Feature",
  "properties": {
    "iso:country":"ES",
    "sg:address":"Avda Conde De Guadalhorce, S/n",
    "sg:city":"Burgos",
    "sg:orig_category":"Organizaciones Internacionales",
    "sg:phone":"+34 947 23 22 22",
    "sg:postcode":"09001",
    "sg:province":"Burgos",
    "wof:name":"Asamblea Provincial De La Cruz Roja",
    "wof:placetype":"venue"
},
  "geometry": {"coordinates":[-3.7081620693,42.3357505798],"type":"Point"}
}