{
  "type": "Feature",
  "properties": {
    "iso:country":"ES",
    "sg:address":"Ptda Partida Materna, 8",
    "sg:city":"Vilella",
    "sg:orig_category":"Empresas De Carpinter\u00cda Met\u00c1lica",
    "sg:phone":"+34 962 45 97 25",
    "sg:postcode":"46600",
    "sg:province":"Valencia",
    "wof:name":"Solaz Vidal Francisco Jose",
    "wof:placetype":"venue"
},
  "geometry": {"coordinates":[-0.4378489852,39.1517295837],"type":"Point"}
}