{
  "type": "Feature",
  "properties": {
    "iso:country":"ES",
    "sg:address":"Calle de Gil De Jaz, 14",
    "sg:city":"Oviedo",
    "sg:orig_category":"Zapatos (al Por Menor)",
    "sg:phone":"+34 985 24 02 63",
    "sg:postcode":"33004",
    "sg:province":"Asturias",
    "wof:name":"Romel S. A.",
    "wof:placetype":"venue"
},
  "geometry": {"coordinates":[-5.8532309532,43.3633728027],"type":"Point"}
}