{
  "type": "Feature",
  "properties": {
    "addr:full":"Avda Eladio Perlado, 51 Burgos Burgos 09007",
    "addr:housenumber":"51",
    "addr:postcode":"09007",
    "addr:street":"Avda Eladio Perlado",
    "iso:country":"ES",
    "sg:address":"Avda Eladio Perlado, 51",
    "sg:city":"Burgos",
    "sg:orig_category":"Animales (al Por Menor)",
    "sg:phone":"+34 947 47 08 50",
    "sg:postcode":"09007",
    "sg:province":"Burgos",
    "wof:name":"Fernandez Villa\u00f1o Isabel",
    "wof:placetype":"venue"
},
  "geometry": {"coordinates":[-3.6664030552,42.3490180969],"type":"Point"}
}