{
  "type": "Feature",
  "properties": {
    "addr:full":"Calle de Orense, 10 Madrid Madrid 28020",
    "addr:housenumber":"10",
    "addr:postcode":"madrid;28020",
    "addr:street":"Calle De Orense",
    "iso:country":"ES",
    "sg:address":"Calle de Orense, 10",
    "sg:city":"Madrid",
    "sg:orig_category":"Asesor\u00cda Fiscal Y Jur\u00cddica",
    "sg:phone":"+34 915 55 01 06",
    "sg:postcode":"28020",
    "sg:province":"Madrid",
    "wof:name":"Solozabal Villanueva Eduardo",
    "wof:placetype":"venue"
},
  "geometry": {"coordinates":[-3.6953380108,40.4487495422],"type":"Point"}
}