{
  "type": "Feature",
  "properties": {
    "addr:full":"Pavias, 8 Archidona M\u00e1laga 29300",
    "addr:housenumber":"8",
    "addr:postcode":"29300",
    "addr:street":"Pavias;Ma\u0301Laga",
    "iso:country":"ES",
    "sg:address":"Pavias, 8",
    "sg:city":"Archidona",
    "sg:orig_category":"Edici\u00d3n De Diarios, Revistas, Boletines",
    "sg:phone":"+34 952 71 43 95",
    "sg:postcode":"29300",
    "sg:province":"M\u00e1laga",
    "sg:website":"www.edicionesaljibe.com",
    "wof:name":"Ediciones Aljibe S.l.",
    "wof:placetype":"venue"
},
  "geometry": {"coordinates":[-4.3897361755,37.0953216553],"type":"Point"}
}