{
  "type": "Feature",
  "properties": {
    "iso:country":"ES",
    "sg:address":"Plaz Puerto Rubio, 20",
    "sg:city":"Madrid",
    "sg:orig_category":"Asociaciones, Organismos Culturales Y Socioeducativos",
    "sg:phone":"+34 914 33 94 50",
    "sg:postcode":"28053",
    "sg:province":"Madrid",
    "wof:name":"Asociacion Cultural Amigos Baile Del Salon",
    "wof:placetype":"venue"
},
  "geometry": {"coordinates":[-3.6676530838,40.3963241577],"type":"Point"}
}