{
  "type": "Feature",
  "properties": {
    "iso:country":"ES",
    "sg:address":"Calle de Imperial, 18",
    "sg:city":"Valladolid",
    "sg:orig_category":"Aparatos, Material Y Suministros Para Laboratorios",
    "sg:phone":"+34 983 35 46 30",
    "sg:postcode":"47003",
    "sg:province":"Valladolid",
    "wof:name":"Casti-lab S.l.",
    "wof:placetype":"venue"
},
  "geometry": {"coordinates":[-4.7287039757,41.6585502625],"type":"Point"}
}