{
  "type": "Feature",
  "properties": {
    "addr:full":"Vilanovi\u00f1a, S/n Meis Pontevedra 36616",
    "addr:housenumber":"/ n",
    "addr:postcode":"36616",
    "addr:street":"Vilanovin\u0303A S",
    "iso:country":"ES",
    "sg:address":"Vilanovi\u00f1a, S/n",
    "sg:city":"Meis",
    "sg:orig_category":"Arenas, Guijarros Y Granulados",
    "sg:phone":"+34 986 71 55 83",
    "sg:postcode":"36616",
    "sg:province":"Pontevedra",
    "wof:name":"Bemposta Vila Carmen",
    "wof:placetype":"venue"
},
  "geometry": {"coordinates":[-8.7120580673,42.549118042],"type":"Point"}
}