{
  "type": "Feature",
  "properties": {
    "addr:full":"Rond Guinardo, 15 Barcelona Barcelona 08024",
    "addr:housenumber":"15",
    "addr:postcode":"08024",
    "addr:street":"Guinardo",
    "iso:country":"ES",
    "sg:address":"Rond Guinardo, 15",
    "sg:city":"Barcelona",
    "sg:orig_category":"Ense\u00d1anza: Peluquer\u00cda Est\u00c9tica",
    "sg:phone":"+34 934 50 39 12",
    "sg:postcode":"08024",
    "sg:province":"Barcelona",
    "wof:name":"Academia De Peluqueria Guinardo 15 S.l.",
    "wof:placetype":"venue"
},
  "geometry": {"coordinates":[2.162159,41.412647],"type":"Point"}
}