{
  "type": "Feature",
  "properties": {
    "addr:full":"Carrer de Calvet, 60 Barcelona Barcelona 08021",
    "addr:housenumber":"60",
    "addr:postcode":"08021",
    "addr:street":"Carrer De Calvet",
    "iso:country":"ES",
    "sg:address":"Carrer de Calvet, 60",
    "sg:city":"Barcelona",
    "sg:orig_category":"Zapatos (al Por Menor)",
    "sg:phone":"+34 934 14 40 24",
    "sg:postcode":"08021",
    "sg:province":"Barcelona",
    "wof:name":"Martinez Almansa Maria Olga",
    "wof:placetype":"venue"
},
  "geometry": {"coordinates":[2.1420350075,41.3960952759],"type":"Point"}
}