{
  "type": "Feature",
  "properties": {
    "addr:full":"Pol Ind Rio Gallego, 28 S. Mateo Gallego Zaragoza 50840",
    "addr:housenumber":"28",
    "addr:postcode":"50840",
    "addr:street":"Gallego;S. Mateo Gallego",
    "iso:country":"ES",
    "sg:address":"Pol Ind Rio Gallego, 28",
    "sg:city":"S. Mateo Gallego",
    "sg:orig_category":"Fabricaci\u00d3n, Venta De Cuadros, Accesorios Para Enmarcar",
    "sg:phone":"+34 976 69 08 44",
    "sg:postcode":"50840",
    "sg:province":"Zaragoza",
    "wof:name":"Argonza S. L.",
    "wof:placetype":"venue"
},
  "geometry": {"coordinates":[-0.8765661716,41.6563491821],"type":"Point"}
}