{
  "type": "Feature",
  "properties": {
    "iso:country":"ES",
    "sg:address":"Calle de Sara, 5",
    "sg:city":"Malaga",
    "sg:orig_category":"Centros De Coordinaci\u00d3n",
    "sg:phone":"+34 952 61 25 79",
    "sg:postcode":"29010",
    "sg:province":"M\u00e1laga",
    "wof:name":"Molina Diaz Dolores",
    "wof:placetype":"venue"
},
  "geometry": {"coordinates":[-4.4508671761,36.7299766541],"type":"Point"}
}