{
  "type": "Feature",
  "properties": {
    "iso:country":"ES",
    "sg:address":"Pg Canalies, 12",
    "sg:city":"S. Joan Despi",
    "sg:orig_category":"Estudios, Instalaci\u00d3n De Climatizaci\u00d3n",
    "sg:phone":"+34 933 73 13 06",
    "sg:postcode":"08970",
    "sg:province":"Barcelona",
    "wof:name":"Martinez Gomez Mercedes",
    "wof:placetype":"venue"
},
  "geometry": {"coordinates":[2.0601530075,41.3680953979],"type":"Point"}
}