{
  "type": "Feature",
  "properties": {
    "iso:country":"ES",
    "sg:address":"Calle de Calatrava, 14",
    "sg:city":"Ciudad Real",
    "sg:orig_category":"Abogados",
    "sg:phone":"+34 926 25 66 17",
    "sg:postcode":"13004",
    "sg:province":"Ciudad Real",
    "wof:name":"Arevalo Sendarrubias Joaquin",
    "wof:placetype":"venue"
},
  "geometry": {"coordinates":[-3.9270164967,38.9875717163],"type":"Point"}
}