{
  "type": "Feature",
  "properties": {
    "iso:country":"ES",
    "sg:address":"Carr Pau Casals, 19",
    "sg:city":"Vidreres",
    "sg:orig_category":"Venta, Instalaci\u00d3n De Cocinas",
    "sg:phone":"+34 972 85 00 93",
    "sg:postcode":"17411",
    "sg:province":"Girona",
    "wof:name":"Restaurant Can Magi S.l.",
    "wof:placetype":"venue"
},
  "geometry": {"coordinates":[2.7794458866,41.7900009155],"type":"Point"}
}