{
  "type": "Feature",
  "properties": {
    "addr:full":"Calle de Vernisa, 4 Rotova Valencia 46725",
    "addr:housenumber":"4",
    "addr:postcode":"46725",
    "addr:street":"Calle De Vernisa",
    "iso:country":"ES",
    "sg:address":"Calle de Vernisa, 4",
    "sg:city":"Rotova",
    "sg:orig_category":"Comerciantes Al Por Mayor De Vinos, Licores Y Alcoholes",
    "sg:phone":"+34 962 83 52 31",
    "sg:postcode":"46725",
    "sg:province":"Valencia",
    "wof:name":"Bodegas Pina S.l.",
    "wof:placetype":"venue"
},
  "geometry": {"coordinates":[-0.2494989932,38.936378479],"type":"Point"}
}