{
  "type": "Feature",
  "properties": {
    "addr:full":"Cent. Com. Aloha, 28 Nueva Andalucia M\u00e1laga 29660",
    "addr:housenumber":"28",
    "addr:postcode":"29660",
    "addr:street":"Nueva Andalucia Ma\u0301Laga",
    "iso:country":"ES",
    "sg:address":"Cent. Com. Aloha, 28",
    "sg:city":"Nueva Andalucia",
    "sg:orig_category":"Electricidad: Equipos Industriales, Componentes (fabricaci\u00d3n)",
    "sg:phone":"+34 952 81 40 73",
    "sg:postcode":"29660",
    "sg:province":"M\u00e1laga",
    "wof:name":"Cef Almacen Material Electrico S.a.",
    "wof:placetype":"venue"
},
  "geometry": {"coordinates":[-4.9572491646,36.4902381897],"type":"Point"}
}