{
  "type": "Feature",
  "properties": {
    "iso:country":"ES",
    "sg:address":"Plaz Rafael Cano, 9",
    "sg:city":"Valladolid",
    "sg:orig_category":"Molduras, Junquillos, Listones Y Molduras Perforadas",
    "sg:phone":"+34 983 39 32 74",
    "sg:postcode":"47005",
    "sg:province":"Valladolid",
    "wof:name":"Espeso Redondo Jose Luis",
    "wof:placetype":"venue"
},
  "geometry": {"coordinates":[-4.7103209496,41.6521873474],"type":"Point"}
}