{
  "type": "Feature",
  "properties": {
    "iso:country":"ES",
    "sg:address":"Plaz Marcelino Soroa, 1",
    "sg:city":"Donostia-san Sebastian",
    "sg:orig_category":"Agentes Generales De Seguros",
    "sg:phone":"+34 943 44 64 20",
    "sg:postcode":"20011",
    "sg:province":"Guip\u00f9zcoa",
    "wof:name":"Abete Aldanondo Alberto",
    "wof:placetype":"venue"
},
  "geometry": {"coordinates":[-1.97417,43.306442],"type":"Point"}
}