{
  "type": "Feature",
  "properties": {
    "iso:country":"ES",
    "sg:address":"Calle de Gaztambide-carrera, 8",
    "sg:city":"Tudela",
    "sg:orig_category":"Asesor\u00cda Sobre Comunicaci\u00d3n De Empresas",
    "sg:phone":"+34 948 40 29 49",
    "sg:postcode":"31500",
    "sg:province":"Navarra",
    "wof:name":"Lobera Lopez Asesores S.l.",
    "wof:placetype":"venue"
},
  "geometry": {"coordinates":[-1.6044420004,42.0617218018],"type":"Point"}
}