{
  "type": "Feature",
  "properties": {
    "iso:country":"ES",
    "sg:address":"Palacios Rubios, S/n",
    "sg:city":"Palacios Rubios",
    "sg:orig_category":"Sanatorios M\u00c9dico",
    "sg:phone":"+34 920 30 17 03",
    "sg:postcode":"05216",
    "sg:province":"\u00c1vila",
    "wof:name":"Ayuntamiento De Nava De Arevalo",
    "wof:placetype":"venue"
},
  "geometry": {"coordinates":[-4.769133091,40.9984931946],"type":"Point"}
}