{
  "type": "Feature",
  "properties": {
    "iso:country":"ES",
    "sg:address":"Plaz Vista Alegre (de), 28",
    "sg:city":"Cordoba",
    "sg:orig_category":"Muebles, Minoristas",
    "sg:phone":"+34 957 23 80 71",
    "sg:postcode":"14004",
    "sg:province":"C\u00f3rdoba",
    "wof:name":"Rodmat S.l.",
    "wof:placetype":"venue"
},
  "geometry": {"coordinates":[-4.7910652161,37.8772468567],"type":"Point"}
}