{
  "type": "Feature",
  "properties": {
    "addr:full":"Av Lleida, 48 Alfarras Lleida 25120",
    "addr:housenumber":"48",
    "addr:postcode":"25120",
    "addr:street":"Av Lleida",
    "iso:country":"ES",
    "sg:address":"Av Lleida, 48",
    "sg:city":"Alfarras",
    "sg:orig_category":"Reposter\u00cdas",
    "sg:phone":"+34 973 76 03 50",
    "sg:postcode":"25120",
    "sg:province":"Lleida",
    "wof:name":"Guitart Merce Merce",
    "wof:placetype":"venue"
},
  "geometry": {"coordinates":[0.5693429708,41.8281021118],"type":"Point"}
}