{
  "type": "Feature",
  "properties": {
    "addr:full":"Plaz Don Antonio Estrada, S/n Cala Moral M\u00e1laga 29720",
    "addr:housenumber":"s",
    "addr:postcode":"29720",
    "addr:street":"Antonio Estrada;/ N;Ma\u0301Laga",
    "iso:country":"ES",
    "sg:address":"Plaz Don Antonio Estrada, S/n",
    "sg:city":"Cala Moral",
    "sg:orig_category":"Bisuter\u00cda, Joyer\u00cda, Relojer\u00cda (al Por Menor)",
    "sg:phone":"+34 952 40 85 13",
    "sg:postcode":"29720",
    "sg:province":"M\u00e1laga",
    "wof:name":"Torres Romero Eva Maria",
    "wof:placetype":"venue"
},
  "geometry": {"coordinates":[-4.325949192,36.7128982544],"type":"Point"}
}