{
  "type": "Feature",
  "properties": {
    "addr:full":"Carrer de Artesans, S/n Valls Tarragona 43800",
    "addr:housenumber":"s",
    "addr:postcode":"43800",
    "addr:street":"Carrer De Artesans;/ N",
    "iso:country":"ES",
    "sg:address":"Carrer de Artesans, S/n",
    "sg:city":"Valls",
    "sg:orig_category":"Comercio De Piezas De Recambio Y De Accesorios De Veh\u00cdculos, Veh\u00cdculos Industriales",
    "sg:phone":"+34 977 61 24 12",
    "sg:postcode":"43800",
    "sg:province":"Tarragona",
    "wof:name":"Funmak S. L.",
    "wof:placetype":"venue"
},
  "geometry": {"coordinates":[1.2628949881,41.3012657166],"type":"Point"}
}