{
  "type": "Feature",
  "properties": {
    "addr:full":"Calle de Castilla Y Leon (de), 4 Jaen Ja\u00e9n 23006",
    "addr:housenumber":"4;jae\u0301n",
    "addr:postcode":"23006",
    "addr:street":"Calle De Castilla Y Leon De",
    "iso:country":"ES",
    "sg:address":"Calle de Castilla Y Leon (de), 4",
    "sg:city":"Jaen",
    "sg:orig_category":"Maquinaria Para Industrias Diversas",
    "sg:phone":"+34 953 22 52 10",
    "sg:postcode":"23006",
    "sg:province":"Ja\u00e9n",
    "wof:name":"Alfa Laval Iberia S.a.",
    "wof:placetype":"venue"
},
  "geometry": {"coordinates":[-3.7891190052,37.7838973999],"type":"Point"}
}