{
  "type": "Feature",
  "properties": {
    "iso:country":"ES",
    "sg:address":"Carrer de Mas, 73",
    "sg:city":"Hospitalet Llobregat",
    "sg:orig_category":"Sociedades, Compa\u00d1\u00cdas Aseguradoras",
    "sg:phone":"+34 934 40 93 04",
    "sg:postcode":"08904",
    "sg:province":"Barcelona",
    "wof:name":"Quintana I Rasel Serveis S.l.",
    "wof:placetype":"venue"
},
  "geometry": {"coordinates":[2.1201150417,41.3715896606],"type":"Point"}
}