{
  "type": "Feature",
  "properties": {
    "iso:country":"ES",
    "sg:address":"Calle de Juan Xxiii, 26",
    "sg:city":"Huercal-overa",
    "sg:orig_category":"Moda",
    "sg:phone":"+34 950 13 57 00",
    "sg:postcode":"04600",
    "sg:province":"Almer\u00eda",
    "sg:website":"www.bebesecologicos.com",
    "wof:name":"Bebes Ecologicos S.l.",
    "wof:placetype":"venue"
},
  "geometry": {"coordinates":[-1.9462180138,37.3927001953],"type":"Point"}
}