{
  "type": "Feature",
  "properties": {
    "addr:full":"Calle de Vizcaya, 42 Coru\u00d1a La Coru\u00f1a 15007",
    "addr:housenumber":"42",
    "addr:postcode":"15007",
    "addr:street":"Calle De Vizcaya;Corun\u0303A",
    "iso:country":"ES",
    "sg:address":"Calle de Vizcaya, 42",
    "sg:city":"Coru\u00d1a",
    "sg:orig_category":"Aparcamientos (infraestructuras, Accesorios)",
    "sg:phone":"+34 981 23 13 27",
    "sg:postcode":"15007",
    "sg:province":"La Coru\u00f1a",
    "wof:name":"Rodriguez Roca Jesus",
    "wof:placetype":"venue"
},
  "geometry": {"coordinates":[-8.4126596451,43.3539390564],"type":"Point"}
}