{
  "type": "Feature",
  "properties": {
    "iso:country":"ES",
    "sg:address":"Rua Nelson Mandela, 12",
    "sg:city":"Perillo",
    "sg:orig_category":"Abogados",
    "sg:phone":"+34 981 63 88 67",
    "sg:postcode":"15172",
    "sg:province":"La Coru\u00f1a",
    "wof:name":"Garcia Seoane Maria Del Rosario",
    "wof:placetype":"venue"
},
  "geometry": {"coordinates":[-8.3731069565,43.3333320618],"type":"Point"}
}