{
  "type": "Feature",
  "properties": {
    "iso:country":"ES",
    "sg:address":"Calle de Rodriguez Acosta, S/n",
    "sg:city":"Nerja",
    "sg:orig_category":"Estancos",
    "sg:phone":"+34 952 52 74 28",
    "sg:postcode":"29780",
    "sg:province":"M\u00e1laga",
    "wof:name":"Rivas Merida Francisco Miguel",
    "wof:placetype":"venue"
},
  "geometry": {"coordinates":[-3.8715639114,36.7491607666],"type":"Point"}
}