{
  "type": "Feature",
  "properties": {
    "addr:full":"Calle de Alferez Quintana Suarez, 36 S.gregorio Las Palmas 35200",
    "addr:housenumber":"36",
    "addr:postcode":"35200",
    "addr:street":"Calle De Alferez Quintana Suarez;Las Palmas",
    "iso:country":"ES",
    "sg:address":"Calle de Alferez Quintana Suarez, 36",
    "sg:city":"S.gregorio",
    "sg:orig_category":"Patatas (al Por Mayor)",
    "sg:phone":"+34 928 69 15 86",
    "sg:postcode":"35200",
    "sg:province":"Las Palmas",
    "wof:name":"Carre\u00f1o Torres Ezequiel",
    "wof:placetype":"venue"
},
  "geometry": {"coordinates":[-15.4300060272,28.1248226166],"type":"Point"}
}