{
  "type": "Feature",
  "properties": {
    "iso:country":"ES",
    "sg:address":"Calle de Canillas, 42",
    "sg:city":"Madrid",
    "sg:orig_category":"Expertos Contables, Revisores De Cuentas",
    "sg:phone":"+34 914 15 61 59",
    "sg:postcode":"28002",
    "sg:province":"Madrid",
    "sg:website":"www.caridadbasauditores.com",
    "wof:name":"Abdon Bas Lopez-luengo Asociados Auditores S.l.",
    "wof:placetype":"venue"
},
  "geometry": {"coordinates":[-3.674126,40.442642],"type":"Point"}
}