{
  "type": "Feature",
  "properties": {
    "addr:full":"Rbla Arago, 51 Lleida Lleida 25003",
    "addr:housenumber":"51",
    "addr:postcode":"25003",
    "addr:street":"Rbla Arago",
    "iso:country":"ES",
    "sg:address":"Rbla Arago, 51",
    "sg:city":"Lleida",
    "sg:orig_category":"Inmobiliaria (agencias)",
    "sg:phone":"+34 973 28 05 37",
    "sg:postcode":"25003",
    "sg:province":"Lleida",
    "sg:website":"www.finquesmallol.com",
    "wof:name":"Promomalle S.l.",
    "wof:placetype":"venue"
},
  "geometry": {"coordinates":[0.6207559705,41.6154403687],"type":"Point"}
}