{
  "type": "Feature",
  "properties": {
    "addr:full":"Rua Orense, 112 Monforte De Lemos Lugo 27400",
    "addr:housenumber":"112",
    "addr:postcode":"27400",
    "addr:street":"Rua Orense",
    "iso:country":"ES",
    "sg:address":"Rua Orense, 112",
    "sg:city":"Monforte De Lemos",
    "sg:orig_category":"Venta, Instalaci\u00d3n, Mantenimiento De Chimeneas De Interior Y Accesorios",
    "sg:phone":"+34 982 40 39 53",
    "sg:postcode":"27400",
    "sg:province":"Lugo",
    "wof:name":"Dacosta Ribera Manuel",
    "wof:placetype":"venue"
},
  "geometry": {"coordinates":[-7.5230269432,42.5195007324],"type":"Point"}
}