{
  "type": "Feature",
  "properties": {
    "addr:full":"Ilugo, 6 Santisteban Puerto Ja\u00e9n 23250",
    "addr:housenumber":"6",
    "addr:postcode":"23250",
    "addr:street":"Ilugo;Jae\u0301N",
    "iso:country":"ES",
    "sg:address":"Ilugo, 6",
    "sg:city":"Santisteban Puerto",
    "sg:orig_category":"Plomeros",
    "sg:phone":"+34 953 40 15 45",
    "sg:postcode":"23250",
    "sg:province":"Ja\u00e9n",
    "wof:name":"Fernandez Romero Sebastian",
    "wof:placetype":"venue"
},
  "geometry": {"coordinates":[-3.2013289928,38.250743866],"type":"Point"}
}