{
  "type": "Feature",
  "properties": {
    "iso:country":"ES",
    "sg:address":"Ptda Espioca, S/n",
    "sg:city":"Picassent",
    "sg:orig_category":"Cooperativas Agr\u00cdcolas",
    "sg:phone":"+34 961 23 24 68",
    "sg:postcode":"46220",
    "sg:province":"Valencia",
    "wof:name":"Llaurant La Llum Sociedad Cooperativa Limitada",
    "wof:placetype":"venue"
},
  "geometry": {"coordinates":[-0.4595290124,39.3631401062],"type":"Point"}
}