{
  "type": "Feature",
  "properties": {
    "iso:country":"ES",
    "sg:address":"Calle de Mayor De Santa Marina, 2",
    "sg:city":"Cordoba",
    "sg:orig_category":"Farmacias",
    "sg:phone":"+34 957 48 02 67",
    "sg:postcode":"14001",
    "sg:province":"C\u00f3rdoba",
    "wof:name":"Dominguez Gonzalez Rafael",
    "wof:placetype":"venue"
},
  "geometry": {"coordinates":[-4.775053978,37.8901786804],"type":"Point"}
}