{
  "type": "Feature",
  "properties": {
    "iso:country":"ES",
    "sg:address":"Carrer de Vilallonga, 15",
    "sg:city":"Reus",
    "sg:orig_category":"Carnicer\u00cdas, Carnicer\u00cdas",
    "sg:phone":"+34 977 75 48 54",
    "sg:postcode":"43204",
    "sg:province":"Tarragona",
    "wof:name":"Gonzalez Gomez Antonio Benito",
    "wof:placetype":"venue"
},
  "geometry": {"coordinates":[1.1157619953,41.1583786011],"type":"Point"}
}