{
  "type": "Feature",
  "properties": {
    "addr:full":"Calle de Mariano Baselga, 32 Zaragoza Zaragoza 50015",
    "addr:housenumber":"32",
    "addr:postcode":"50015",
    "addr:street":"Calle De Mariano Baselga",
    "iso:country":"ES",
    "sg:address":"Calle de Mariano Baselga, 32",
    "sg:city":"Zaragoza",
    "sg:orig_category":"Asilos De Ancianos. Centros Privados",
    "sg:phone":"+34 976 73 62 02",
    "sg:postcode":"50015",
    "sg:province":"Zaragoza",
    "wof:name":"Rs.parque Tio Jorge S.l.",
    "wof:placetype":"venue"
},
  "geometry": {"coordinates":[-0.8787950277,41.6616172791],"type":"Point"}
}