{
  "type": "Feature",
  "properties": {
    "addr:full":"Pintor Paret, 6 Iru\u00f1a Navarra 31008",
    "addr:housenumber":"6",
    "addr:postcode":"31008",
    "addr:street":"Pintor Paret",
    "iso:country":"ES",
    "sg:address":"Pintor Paret, 6",
    "sg:city":"Iru\u00f1a",
    "sg:orig_category":"Arquitectos",
    "sg:phone":"+34 948 17 03 45",
    "sg:postcode":"31008",
    "sg:province":"Navarra",
    "wof:name":"Ochotorena Elicegui Juan Miguel",
    "wof:placetype":"venue"
},
  "geometry": {"coordinates":[-1.6598689556,42.808265686],"type":"Point"}
}