{
  "type": "Feature",
  "properties": {
    "addr:full":"Carretera De Orense-los Peares, 14 Peroxa Ourense 32150",
    "addr:housenumber":"14",
    "addr:postcode":"32150",
    "addr:street":"Carretera De Orense-Los Peares",
    "iso:country":"ES",
    "sg:address":"Carretera De Orense-los Peares, 14",
    "sg:city":"Peroxa",
    "sg:orig_category":"Cajas De Ahorro",
    "sg:phone":"+34 988 20 66 13",
    "sg:postcode":"32150",
    "sg:province":"Ourense",
    "sg:website":"www.caixanova.es",
    "wof:name":"Caixa De Aforros De Vigo Ourense E Pontevedra",
    "wof:placetype":"venue"
},
  "geometry": {"coordinates":[-7.7943491936,42.439704895],"type":"Point"}
}