{
  "type": "Feature",
  "properties": {
    "iso:country":"ES",
    "sg:address":"Benigno Quiroga, S/n",
    "sg:city":"Pobra De San Xiao",
    "sg:orig_category":"Supermercados Y Hipermercados",
    "sg:phone":"+34 982 54 32 52",
    "sg:postcode":"27360",
    "sg:province":"Lugo",
    "wof:name":"Sobrado Castro Arturo",
    "wof:placetype":"venue"
},
  "geometry": {"coordinates":[-7.4446201324,42.8623085022],"type":"Point"}
}