{
  "type": "Feature",
  "properties": {
    "iso:country":"ES",
    "sg:address":"Sant Llorenc, 48",
    "sg:city":"Vilassar",
    "sg:orig_category":"Aparcamientos (infraestructuras, Accesorios)",
    "sg:phone":"+34 937 59 18 49",
    "sg:postcode":"08340",
    "sg:province":"Barcelona",
    "wof:name":"Estacionamientos Y Servicios S.a.",
    "wof:placetype":"venue"
},
  "geometry": {"coordinates":[2.3871059418,41.5004806519],"type":"Point"}
}