{
  "type": "Feature",
  "properties": {
    "iso:country":"ES",
    "sg:address":"Carrer de Oratori, 4",
    "sg:city":"Portals Nous",
    "sg:orig_category":"Internados & Ense\u00d1anza Privada",
    "sg:phone":"+34 971 67 58 50",
    "sg:postcode":"07181",
    "sg:province":"Islas Baleares",
    "wof:name":"King Richard Iii College S.a.",
    "wof:placetype":"venue"
},
  "geometry": {"coordinates":[2.5735080242,39.533870697],"type":"Point"}
}