{
  "type": "Feature",
  "properties": {
    "iso:country":"ES",
    "sg:address":"Carrer de Torreblanca, 10",
    "sg:city":"S. Joan Despi",
    "sg:orig_category":"Laboratorios Y Cl\u00cdnicas Veterinarias",
    "sg:phone":"+34 933 73 18 03",
    "sg:postcode":"08970",
    "sg:province":"Barcelona",
    "wof:name":"Armengol Daga Cristina",
    "wof:placetype":"venue"
},
  "geometry": {"coordinates":[2.0588583946,41.377696991],"type":"Point"}
}