{
  "type": "Feature",
  "properties": {
    "addr:full":"Calle de Juan Bautista Zabala, 3 Getxo Vizcaya 48990",
    "addr:housenumber":"3",
    "addr:postcode":"48990",
    "addr:street":"Calle De Juan Bautista Zabala",
    "iso:country":"ES",
    "sg:address":"Calle de Juan Bautista Zabala, 3",
    "sg:city":"Getxo",
    "sg:orig_category":"M\u00c9dicos: Foniatr\u00cda Y Logopedia",
    "sg:phone":"+34 944 60 38 40",
    "sg:postcode":"48990",
    "sg:province":"Vizcaya",
    "wof:name":"Alfonso M. Mu\u00f1oz Echevarria",
    "wof:placetype":"venue"
},
  "geometry": {"coordinates":[-3.01136446,43.3504905701],"type":"Point"}
}