{
  "type": "Feature",
  "properties": {
    "iso:country":"ES",
    "sg:address":"Pl. Palomas, S/n",
    "sg:city":"Guadix",
    "sg:orig_category":"Administraciones Regionales, Departamentales Y Locales",
    "sg:phone":"+34 958 66 93 00",
    "sg:postcode":"18500",
    "sg:province":"Granada",
    "wof:name":"Ayuntamiento De Guadix",
    "wof:placetype":"venue"
},
  "geometry": {"coordinates":[-3.1343688965,37.303894043],"type":"Point"}
}