{
  "type": "Feature",
  "properties": {
    "addr:full":"Calle de Cabo De Palos, 27 Arganda Madrid 28500",
    "addr:housenumber":"27",
    "addr:postcode":"28500",
    "addr:street":"Calle De Cabo De Palos",
    "iso:country":"ES",
    "sg:address":"Calle de Cabo De Palos, 27",
    "sg:city":"Arganda",
    "sg:orig_category":"Bebidas",
    "sg:phone":"+34 918 70 30 94",
    "sg:postcode":"28500",
    "sg:province":"Madrid",
    "wof:name":"Hermanos Gallego Vaquero S.a.",
    "wof:placetype":"venue"
},
  "geometry": {"coordinates":[-3.4756193161,40.3123474121],"type":"Point"}
}