{
  "type": "Feature",
  "properties": {
    "iso:country":"ES",
    "sg:address":"Calle de Donibane, 6",
    "sg:city":"Urdu\u00e7a-ordu\u00e7a",
    "sg:orig_category":"Productores Recolectores, Venta Directa De Vinos",
    "sg:phone":"+34 945 38 40 98",
    "sg:postcode":"48460",
    "sg:province":"Vizcaya",
    "wof:name":"Vinos Merino S.l.",
    "wof:placetype":"venue"
},
  "geometry": {"coordinates":[-3.0069389343,42.9948730469],"type":"Point"}
}