{
  "type": "Feature",
  "properties": {
    "iso:country":"ES",
    "sg:address":"Avda Condes De San Isidro, S/n",
    "sg:city":"Fuengirola",
    "sg:orig_category":"Bancos",
    "sg:phone":"+34 952 47 31 91",
    "sg:postcode":"29640",
    "sg:province":"M\u00e1laga",
    "sg:website":"www.bancoatlantico.es",
    "wof:name":"Banc Sabadell S.a.",
    "wof:placetype":"venue"
},
  "geometry": {"coordinates":[-4.62687397,36.5329856873],"type":"Point"}
}