{
  "type": "Feature",
  "properties": {
    "iso:country":"ES",
    "sg:address":"Calle de Berastegui, 1",
    "sg:city":"Bilbao",
    "sg:orig_category":"Contables",
    "sg:phone":"+34 944 23 04 69",
    "sg:postcode":"48001",
    "sg:province":"Vizcaya",
    "wof:name":"Fernandez Bobadilla Juan Carlos",
    "wof:placetype":"venue"
},
  "geometry": {"coordinates":[-2.9282104969,43.2616729736],"type":"Point"}
}