{
  "type": "Feature",
  "properties": {
    "addr:full":"Calle de Pascual Y Genis, 21 Valencia Valencia 46002",
    "addr:housenumber":"21",
    "addr:postcode":"46002",
    "addr:street":"Calle De Pascual Y Genis",
    "iso:country":"ES",
    "sg:address":"Calle de Pascual Y Genis, 21",
    "sg:city":"Valencia",
    "sg:orig_category":"Funcionario",
    "sg:phone":"+34 963 51 25 85",
    "sg:postcode":"46002",
    "sg:province":"Valencia",
    "sg:website":"www.cnotarial-valencia.com",
    "wof:name":"Colegio Notarial De Valencia",
    "wof:placetype":"venue"
},
  "geometry": {"coordinates":[-0.3736920059,39.4686203003],"type":"Point"}
}