{
  "type": "Feature",
  "properties": {
    "addr:full":"Calle de Carrero Juan Ramon, 10 Madrid Madrid 28025",
    "addr:housenumber":"10",
    "addr:postcode":"madrid;28025",
    "addr:street":"Calle De Carrero Juan Ramon",
    "iso:country":"ES",
    "sg:address":"Calle de Carrero Juan Ramon, 10",
    "sg:city":"Madrid",
    "sg:orig_category":"Estancos",
    "sg:phone":"+34 915 69 45 28",
    "sg:postcode":"28025",
    "sg:province":"Madrid",
    "wof:name":"Cebrian Guerra Pilar",
    "wof:placetype":"venue"
},
  "geometry": {"coordinates":[-3.7294170856,40.3794364929],"type":"Point"}
}