{
  "type": "Feature",
  "properties": {
    "addr:full":"Avda Santa Amalia, S/n Fuengirola M\u00e1laga 29640",
    "addr:housenumber":"s / n",
    "addr:postcode":"29640",
    "addr:street":"Avda Santa Amalia;Ma\u0301Laga",
    "iso:country":"ES",
    "sg:address":"Avda Santa Amalia, S/n",
    "sg:city":"Fuengirola",
    "sg:orig_category":"Empresarios",
    "sg:phone":"+34 952 47 39 16",
    "sg:postcode":"29640",
    "sg:province":"M\u00e1laga",
    "sg:website":"www.islamenespania.com",
    "wof:name":"Fundacion Centro Cultural Suhail",
    "wof:placetype":"venue"
},
  "geometry": {"coordinates":[-4.6278991699,36.5292243958],"type":"Point"}
}