{
  "type": "Feature",
  "properties": {
    "addr:full":"C/ Arquebisbe Domenech, 21 Alcoi Alicante 03804",
    "addr:housenumber":"21",
    "addr:postcode":"03804",
    "addr:street":"C / Arquebisbe Domenech",
    "iso:country":"ES",
    "sg:address":"C/ Arquebisbe Domenech, 21",
    "sg:city":"Alcoi",
    "sg:orig_category":"Autob\u00das (explotaci\u00d3n Y Servicios De)",
    "sg:phone":"+34 965 33 39 69",
    "sg:postcode":"03804",
    "sg:province":"Alicante",
    "wof:name":"Autocares Gregorio S.l.",
    "wof:placetype":"venue"
},
  "geometry": {"coordinates":[-0.4635230005,38.7080802917],"type":"Point"}
}