{
  "type": "Feature",
  "properties": {
    "iso:country":"ES",
    "sg:address":"Carr Mossen Ferran, 21",
    "sg:city":"Seros",
    "sg:orig_category":"Maquinaria Para Industrias Diversas",
    "sg:phone":"+34 973 78 04 12",
    "sg:postcode":"25183",
    "sg:province":"Lleida",
    "wof:name":"Samprieto Barrafon Francisco",
    "wof:placetype":"venue"
},
  "geometry": {"coordinates":[0.4130969942,41.4650611877],"type":"Point"}
}