{
  "type": "Feature",
  "properties": {
    "addr:full":"Av Montserrat, 8 Roses Girona 17480",
    "addr:housenumber":"8",
    "addr:postcode":"17480",
    "addr:street":"Av Montserrat",
    "iso:country":"ES",
    "sg:address":"Av Montserrat, 8",
    "sg:city":"Roses",
    "sg:orig_category":"Ropa Para Se\u00d1oras Y Caballeros (al Por Menor)",
    "sg:phone":"+34 972 15 33 15",
    "sg:postcode":"17480",
    "sg:province":"Girona",
    "wof:name":"Gomez Boix Montserrat",
    "wof:placetype":"venue"
},
  "geometry": {"coordinates":[3.1806840897,42.2613830566],"type":"Point"}
}