{
  "type": "Feature",
  "properties": {
    "iso:country":"ES",
    "sg:address":"Calle de Puebla (la), 4",
    "sg:city":"Palencia",
    "sg:orig_category":"Prot\u00c9sicos Dentales",
    "sg:phone":"+34 979 72 56 66",
    "sg:postcode":"34002",
    "sg:province":"Palencia",
    "wof:name":"Rio Arruquero Andres Luis Del",
    "wof:placetype":"venue"
},
  "geometry": {"coordinates":[-4.5291237831,42.0085830688],"type":"Point"}
}