{
  "type": "Feature",
  "properties": {
    "addr:full":"Calle de Vitoria, 22 Miranda Ebro Burgos 09200",
    "addr:housenumber":"22",
    "addr:postcode":"09200",
    "addr:street":"Calle De Vitoria",
    "iso:country":"ES",
    "sg:address":"Calle de Vitoria, 22",
    "sg:city":"Miranda Ebro",
    "sg:orig_category":"Alimentaci\u00d3n General (al Por Mayor)",
    "sg:phone":"+34 947 31 08 52",
    "sg:postcode":"09200",
    "sg:province":"Burgos",
    "wof:name":"Salinas Sancho Jose Luis",
    "wof:placetype":"venue"
},
  "geometry": {"coordinates":[-2.9524741173,42.6833839417],"type":"Point"}
}