{
  "type": "Feature",
  "properties": {
    "addr:full":"Calle de Alicante, 2 Valladolid Valladolid 47012",
    "addr:housenumber":"2",
    "addr:postcode":"47012",
    "addr:street":"Calle De Alicante",
    "iso:country":"ES",
    "sg:address":"Calle de Alicante, 2",
    "sg:city":"Valladolid",
    "sg:orig_category":"Servicios De Telecomunicaciones",
    "sg:phone":"+34 983 39 20 20",
    "sg:postcode":"47012",
    "sg:province":"Valladolid",
    "wof:name":"Grupo Telemedia U.t.e.",
    "wof:placetype":"venue"
},
  "geometry": {"coordinates":[-4.7164573669,41.6403007507],"type":"Point"}
}