{
  "type": "Feature",
  "properties": {
    "iso:country":"ES",
    "sg:address":"Calle de San Valeriano, 30",
    "sg:city":"Torrent",
    "sg:orig_category":"Ropa Para Ni\u00d1os (al Por Menor)",
    "sg:phone":"+34 961 56 72 41",
    "sg:postcode":"46900",
    "sg:province":"Valencia",
    "wof:name":"Mora Ros Gerardo",
    "wof:placetype":"venue"
},
  "geometry": {"coordinates":[-0.4768390059,39.433303833],"type":"Point"}
}