{
  "type": "Feature",
  "properties": {
    "addr:full":"Calle de Gran Capitan, 9 Granada Granada 18002",
    "addr:housenumber":"9",
    "addr:postcode":"18002",
    "addr:street":"Calle De Gran Capitan",
    "iso:country":"ES",
    "sg:address":"Calle de Gran Capitan, 9",
    "sg:city":"Granada",
    "sg:orig_category":"Freidur\u00cdas: Equipos Y Suministros",
    "sg:phone":"+34 958 27 71 99",
    "sg:postcode":"18002",
    "sg:province":"Granada",
    "sg:website":"www.conchifrit.com",
    "wof:name":"Lopez Puche Jose",
    "wof:placetype":"venue"
},
  "geometry": {"coordinates":[-3.6037170887,37.1784706116],"type":"Point"}
}