{
  "type": "Feature",
  "properties": {
    "addr:full":"Avda Sierra De Gata, 6 Coria C\u00e1ceres 10800",
    "addr:housenumber":"6",
    "addr:postcode":"10800",
    "addr:street":"Avda Sierra De Gata;Ca\u0301Ceres",
    "iso:country":"ES",
    "sg:address":"Avda Sierra De Gata, 6",
    "sg:city":"Coria",
    "sg:orig_category":"Asesor\u00cda Sobre Comunicaci\u00d3n De Empresas",
    "sg:phone":"+34 927 50 11 04",
    "sg:postcode":"10800",
    "sg:province":"C\u00e1ceres",
    "wof:name":"Sogetebex S.l.",
    "wof:placetype":"venue"
},
  "geometry": {"coordinates":[-6.5369467735,39.9854202271],"type":"Point"}
}