{
  "type": "Feature",
  "properties": {
    "addr:full":"Crta. Quintana De La Serena, 129 La Haba Badajoz 06714",
    "addr:housenumber":"129",
    "addr:postcode":"06714",
    "addr:street":"Crta. Quintana De La Serena",
    "iso:country":"ES",
    "sg:address":"Crta. Quintana De La Serena, 129",
    "sg:city":"La Haba",
    "sg:orig_category":"Ense\u00d1anza, Formaci\u00d3n Profesional: Aprendizaje",
    "sg:phone":"+34 924 82 33 20",
    "sg:postcode":"06714",
    "sg:province":"Badajoz",
    "wof:name":"Ayuntamiento De La Haba",
    "wof:placetype":"venue"
},
  "geometry": {"coordinates":[-5.8037438393,38.8750114441],"type":"Point"}
}