{
  "type": "Feature",
  "properties": {
    "iso:country":"ES",
    "sg:address":"Avda Ana De Viya, 5",
    "sg:city":"Cadiz",
    "sg:orig_category":"Centros P\u00dablicos De Formaci\u00d3n Profesional Y T\u00c9cnica",
    "sg:phone":"+34 956 25 51 58",
    "sg:postcode":"11009",
    "sg:province":"C\u00e1diz",
    "wof:name":"Colegio Oficial De Veterinarios",
    "wof:placetype":"venue"
},
  "geometry": {"coordinates":[-6.280064106,36.5121116638],"type":"Point"}
}