{
  "type": "Feature",
  "properties": {
    "iso:country":"ES",
    "sg:address":"Rbla Rambla, 143",
    "sg:city":"Sabadell",
    "sg:orig_category":"Agentes Generales De Seguros",
    "sg:phone":"+34 937 45 93 40",
    "sg:postcode":"08202",
    "sg:province":"Barcelona",
    "wof:name":"Cano Nogue Jordi",
    "wof:placetype":"venue"
},
  "geometry": {"coordinates":[2.1113801003,41.5421829224],"type":"Point"}
}