{
  "type": "Feature",
  "properties": {
    "addr:full":"Calle de Raval, El, 66 Burriana Castell\u00f3n 12530",
    "addr:housenumber":"66",
    "addr:postcode":"12530",
    "addr:street":"Calle De Raval El",
    "iso:country":"ES",
    "sg:address":"Calle de Raval, El, 66",
    "sg:city":"Burriana",
    "sg:orig_category":"Carnicer\u00cdas, Carnicer\u00cdas",
    "sg:phone":"+34 964 51 81 50",
    "sg:postcode":"12530",
    "sg:province":"Castell\u00f3n",
    "wof:name":"Cristaleria Indalecio Marin S.l.",
    "wof:placetype":"venue"
},
  "geometry": {"coordinates":[-0.0852660015,39.8894195557],"type":"Point"}
}