{
  "type": "Feature",
  "properties": {
    "addr:full":"Calle de Poetisa Leonor Perales, 9 Castellar-oliveral Valencia 46026",
    "addr:housenumber":"9",
    "addr:postcode":"46026",
    "addr:street":"Calle De Poetisa Leonor Perales",
    "iso:country":"ES",
    "sg:address":"Calle de Poetisa Leonor Perales, 9",
    "sg:city":"Castellar-oliveral",
    "sg:orig_category":"Comercio De Piezas De Recambio Y De Accesorios De Veh\u00cdculos, Veh\u00cdculos Industriales",
    "sg:phone":"+34 963 75 00 66",
    "sg:postcode":"46026",
    "sg:province":"Valencia",
    "wof:name":"Moncamio S.l.",
    "wof:placetype":"venue"
},
  "geometry": {"coordinates":[-0.3621790111,39.4282875061],"type":"Point"}
}