{
  "type": "Feature",
  "properties": {
    "iso:country":"ES",
    "sg:address":"Calle de Gata De Gorgos, 34",
    "sg:city":"Alacant",
    "sg:orig_category":"Molduras, Junquillos, Listones Y Molduras Perforadas",
    "sg:phone":"+34 965 17 05 76",
    "sg:postcode":"03009",
    "sg:province":"Alicante",
    "wof:name":"Valor Llorca Maria Trinidad",
    "wof:placetype":"venue"
},
  "geometry": {"coordinates":[-0.5068780184,38.3684272766],"type":"Point"}
}