{
  "type": "Feature",
  "properties": {
    "addr:full":"Calle de Mauricio Legendre, 19 Madrid Madrid 28046",
    "addr:housenumber":"19",
    "addr:postcode":"madrid;28046",
    "addr:street":"Calle De Mauricio Legendre",
    "iso:country":"ES",
    "sg:address":"Calle de Mauricio Legendre, 19",
    "sg:city":"Madrid",
    "sg:orig_category":"Centros Empresariales",
    "sg:phone":"+34 913 08 48 44",
    "sg:postcode":"28046",
    "sg:province":"Madrid",
    "sg:website":"www.aedecc.com",
    "wof:name":"Asociacion Espa\u00f1ola De Centros Comerciales",
    "wof:placetype":"venue"
},
  "geometry": {"coordinates":[-3.6863434315,40.4711799622],"type":"Point"}
}