{
  "type": "Feature",
  "properties": {
    "iso:country":"ES",
    "sg:address":"Pg Comte De Vilardaga, 49",
    "sg:city":"Sant Feliu Llobregat",
    "sg:classifiers":[
        {
            "category":"Autos & Motor Vehicles",
            "subcategory":"Automobile Sales",
            "type":"Retail Goods"
        }
    ],
    "sg:phone":"+34 936 85 53 47",
    "sg:postcode":"08980",
    "sg:province":"Barcelona",
    "sg:website":"www.autoescolarunner.es.vg",
    "wof:name":"Sanchez Marin Sebastian",
    "wof:placetype":"venue"
},
  "geometry": {"coordinates":[2.0512909889,41.3860931396],"type":"Point"}
}