{
  "type": "Feature",
  "properties": {
    "addr:full":"Carrer de Ramon Casas, 49 Mollet Valles Barcelona 08100",
    "addr:housenumber":"49",
    "addr:postcode":"08100",
    "addr:street":"Carrer De Ramon Casas",
    "iso:country":"ES",
    "sg:address":"Carrer de Ramon Casas, 49",
    "sg:city":"Mollet Valles",
    "sg:orig_category":"Molduras, Junquillos, Listones Y Molduras Perforadas",
    "sg:phone":"+34 935 93 76 50",
    "sg:postcode":"08100",
    "sg:province":"Barcelona",
    "wof:name":"Romero Silvestre Manuel",
    "wof:placetype":"venue"
},
  "geometry": {"coordinates":[2.2161250114,41.5383605957],"type":"Point"}
}