{
  "type": "Feature",
  "properties": {
    "addr:full":"Cristo Piedad, 11 Guadamur Toledo 45160",
    "addr:housenumber":"11",
    "addr:postcode":"45160",
    "addr:street":"Piedad",
    "iso:country":"ES",
    "sg:address":"Cristo Piedad, 11",
    "sg:city":"Guadamur",
    "sg:orig_category":"Reposter\u00cdas",
    "sg:phone":"+34 925 29 12 95",
    "sg:postcode":"45160",
    "sg:province":"Toledo",
    "wof:name":"Morales Rodriguez Maria Teresa",
    "wof:placetype":"venue"
},
  "geometry": {"coordinates":[-4.1500692368,39.8121795654],"type":"Point"}
}