{
  "type": "Feature",
  "properties": {
    "iso:country":"ES",
    "sg:address":"Carrer de Foc, 130",
    "sg:city":"Barcelona",
    "sg:orig_category":"Polideportivos",
    "sg:phone":"+34 932 23 42 72",
    "sg:postcode":"08038",
    "sg:province":"Barcelona",
    "wof:name":"Ajuntament De Barcelona",
    "wof:placetype":"venue"
},
  "geometry": {"coordinates":[2.1430044174,41.35704422],"type":"Point"}
}