{
  "type": "Feature",
  "properties": {
    "addr:full":"Ptge Corbi, 1 Mutxamel Alicante 03110",
    "addr:housenumber":"1",
    "addr:postcode":"03110",
    "addr:street":"Ptge Corbi",
    "iso:country":"ES",
    "sg:address":"Ptge Corbi, 1",
    "sg:city":"Mutxamel",
    "sg:orig_category":"Maquinaria Para Industrias Diversas",
    "sg:phone":"+34 965 95 54 47",
    "sg:postcode":"03110",
    "sg:province":"Alicante",
    "wof:name":"Excavaciones Y Demoliciones Martinez S.l.",
    "wof:placetype":"venue"
},
  "geometry": {"coordinates":[-0.4493710101,38.419883728],"type":"Point"}
}