{
  "type": "Feature",
  "properties": {
    "iso:country":"ES",
    "sg:address":"Pl Zona Franca (zona Fca Recinto Fiscal), 18",
    "sg:city":"Cadiz",
    "sg:orig_category":"Asesor\u00cda Sobre Comunicaci\u00d3n De Empresas",
    "sg:phone":"+34 956 26 44 25",
    "sg:postcode":"11011",
    "sg:province":"C\u00e1diz",
    "wof:name":"Sociedad De Garantia Reciproca De Andalucia",
    "wof:placetype":"venue"
},
  "geometry": {"coordinates":[-6.2726240158,36.4999389648],"type":"Point"}
}