{
  "type": "Feature",
  "properties": {
    "addr:full":"Calle de Tomas Borras, 19 Madrid Madrid 28045",
    "addr:housenumber":"19",
    "addr:postcode":"madrid;28045",
    "addr:street":"Calle De Tomas Borras",
    "iso:country":"ES",
    "sg:address":"Calle de Tomas Borras, 19",
    "sg:city":"Madrid",
    "sg:orig_category":"Loter\u00cda Y T\u00d3mbola",
    "sg:phone":"+34 914 73 54 56",
    "sg:postcode":"28045",
    "sg:province":"Madrid",
    "wof:name":"Gines Sobrado Guillermo",
    "wof:placetype":"venue"
},
  "geometry": {"coordinates":[-3.6983590126,40.3949394226],"type":"Point"}
}