{
  "type": "Feature",
  "properties": {
    "iso:country":"ES",
    "sg:address":"J. Echegaray, 8",
    "sg:city":"Parque Empresarial",
    "sg:orig_category":"Asesor\u00cda Sobre Comunicaci\u00d3n De Empresas",
    "sg:phone":"+34 914 31 01 96",
    "sg:postcode":"28232",
    "sg:province":"Madrid",
    "sg:website":"www.gerens.com",
    "wof:name":"Gerens Management Group S.a.",
    "wof:placetype":"venue"
},
  "geometry": {"coordinates":[-3.7003455162,40.4166908264],"type":"Point"}
}