{
  "type": "Feature",
  "properties": {
    "iso:country":"ES",
    "sg:address":"Pol. Ind. La Central, S/n",
    "sg:city":"Central",
    "sg:orig_category":"Plomeros",
    "sg:phone":"+34 985 65 46 71",
    "sg:postcode":"33940",
    "sg:province":"Asturias",
    "wof:name":"Jose Hernandez Rodriguez S.l.",
    "wof:placetype":"venue"
},
  "geometry": {"coordinates":[-5.6435742378,43.2864112854],"type":"Point"}
}