{
  "type": "Feature",
  "properties": {
    "addr:full":"Avda Merida, S/n Alcantara C\u00e1ceres 10980",
    "addr:postcode":"10980",
    "addr:street":"Avda Merida S / N Alcantara Ca\u0301Ceres",
    "iso:country":"ES",
    "sg:address":"Avda Merida, S/n",
    "sg:city":"Alcantara",
    "sg:orig_category":"Alimentaci\u00d3n General (al Por Menor)",
    "sg:phone":"+34 927 39 00 18",
    "sg:postcode":"10980",
    "sg:province":"C\u00e1ceres",
    "wof:name":"Gomez Asensio Rafael",
    "wof:placetype":"venue"
},
  "geometry": {"coordinates":[-6.8839540482,39.713684082],"type":"Point"}
}