{
  "type": "Feature",
  "properties": {
    "addr:full":"Avda Campones, 88 Gijon Asturias 33211",
    "addr:housenumber":"88",
    "addr:postcode":"33211",
    "addr:street":"Avda Campones",
    "iso:country":"ES",
    "sg:address":"Avda Campones, 88",
    "sg:city":"Gijon",
    "sg:orig_category":"Farmacias",
    "sg:phone":"+34 985 32 74 99",
    "sg:postcode":"33211",
    "sg:province":"Asturias",
    "wof:name":"Rodriguez Del Coz Maria Natividad",
    "wof:placetype":"venue"
},
  "geometry": {"coordinates":[-5.6966848373,43.5303421021],"type":"Point"}
}