{
  "type": "Feature",
  "properties": {
    "iso:country":"ES",
    "sg:address":"Carrer de Arc De Bara, 50",
    "sg:city":"Zona Costera",
    "sg:orig_category":"Inmobiliaria (agencias)",
    "sg:phone":"+34 977 80 21 60",
    "sg:postcode":"43883",
    "sg:province":"Tarragona",
    "wof:name":"Diaz Orpinell S.l.",
    "wof:placetype":"venue"
},
  "geometry": {"coordinates":[1.4600640535,41.1879272461],"type":"Point"}
}