{
  "type": "Feature",
  "properties": {
    "addr:full":"Calle de Filiberto Rodrigo, 16 Catarroja Valencia 46470",
    "addr:housenumber":"16",
    "addr:postcode":"46470",
    "addr:street":"Calle De Filiberto Rodrigo",
    "iso:country":"ES",
    "sg:address":"Calle de Filiberto Rodrigo, 16",
    "sg:city":"Catarroja",
    "sg:orig_category":"Confecci\u00d3n De Zapatos",
    "sg:phone":"+34 961 26 32 37",
    "sg:postcode":"46470",
    "sg:province":"Valencia",
    "wof:name":"Calzados Amoros S.l.",
    "wof:placetype":"venue"
},
  "geometry": {"coordinates":[-0.4046840072,39.4076499939],"type":"Point"}
}