{
  "type": "Feature",
  "properties": {
    "addr:full":"Calle de Rector Lucena, 20 Salamanca Salamanca 37002",
    "addr:housenumber":"20",
    "addr:postcode":"37002",
    "addr:street":"Calle De Rector Lucena",
    "iso:country":"ES",
    "sg:address":"Calle de Rector Lucena, 20",
    "sg:city":"Salamanca",
    "sg:orig_category":"Dentistas: Cirujanos Dentistas Cualificados En Ortopedia Odontofacial",
    "sg:phone":"+34 923 21 35 94",
    "sg:postcode":"37002",
    "sg:province":"Salamanca",
    "wof:name":"Terron Miron Fermin",
    "wof:placetype":"venue"
},
  "geometry": {"coordinates":[-5.6630115509,40.9670562744],"type":"Point"}
}