{
  "type": "Feature",
  "properties": {
    "iso:country":"ES",
    "sg:address":"Carr Moll, 1",
    "sg:city":"Alguaire",
    "sg:orig_category":"Lencer\u00cda Femenina, Corseter\u00cda, Trajes De Ba\u00d1o (al Por Menor)",
    "sg:phone":"+34 973 75 61 21",
    "sg:postcode":"25125",
    "sg:province":"Lleida",
    "wof:name":"Costafreda Palau Fernando",
    "wof:placetype":"venue"
},
  "geometry": {"coordinates":[0.5873860121,41.7410583496],"type":"Point"}
}