{
  "type": "Feature",
  "properties": {
    "addr:full":"Luga Poligono 5, 55 Buger Islas Baleares 07311",
    "addr:housenumber":"55",
    "addr:postcode":"07311",
    "addr:street":"Poligono 5",
    "iso:country":"ES",
    "sg:address":"Luga Poligono 5, 55",
    "sg:city":"Buger",
    "sg:orig_category":"Gu\u00cdas Y Gu\u00cdas",
    "sg:phone":"+34 971 50 95 93",
    "sg:postcode":"07311",
    "sg:province":"Islas Baleares",
    "wof:name":"Derstien  Helga",
    "wof:placetype":"venue"
},
  "geometry": {"coordinates":[2.9842550755,39.7585105896],"type":"Point"}
}