{
  "type": "Feature",
  "properties": {
    "iso:country":"ES",
    "sg:address":"Calle de Lerida, 14",
    "sg:city":"Segovia",
    "sg:orig_category":"Centros P\u00dablicos De Formaci\u00d3n Profesional Y T\u00c9cnica",
    "sg:phone":"+34 921 43 72 45",
    "sg:postcode":"40004",
    "sg:province":"Segovia",
    "wof:name":"Colegio Oficial De Emfermeria",
    "wof:placetype":"venue"
},
  "geometry": {"coordinates":[-4.1068329811,40.9469795227],"type":"Point"}
}