{
  "type": "Feature",
  "properties": {
    "iso:country":"ES",
    "sg:address":"Plasencia, 9",
    "sg:city":"Mostoles",
    "sg:orig_category":"Muebles, Minoristas",
    "sg:phone":"+34 916 65 92 22",
    "sg:postcode":"28935",
    "sg:province":"Madrid",
    "wof:name":"Ambientes Y Estilos S.l.",
    "wof:placetype":"venue"
},
  "geometry": {"coordinates":[-3.8800997734,40.3519287109],"type":"Point"}
}