{
  "type": "Feature",
  "properties": {
    "iso:country":"ES",
    "sg:address":"Carr Francesc Macia, 12",
    "sg:city":"Badalona",
    "sg:orig_category":"Cl\u00cdnicas Dentales",
    "sg:phone":"+34 934 60 78 82",
    "sg:postcode":"08912",
    "sg:province":"Barcelona",
    "wof:name":"Centre Odontologic Cladent S.l.",
    "wof:placetype":"venue"
},
  "geometry": {"coordinates":[2.2426218987,41.4479522705],"type":"Point"}
}