{
  "type": "Feature",
  "properties": {
    "addr:full":"Calle de Grisen, 23 Vereda Murcia 30395",
    "addr:housenumber":"23",
    "addr:postcode":"30395",
    "addr:street":"Calle De Grisen",
    "iso:country":"ES",
    "sg:address":"Calle de Grisen, 23",
    "sg:city":"Vereda",
    "sg:orig_category":"Centros Empresariales",
    "sg:phone":"+34 968 31 04 94",
    "sg:postcode":"30395",
    "sg:province":"Murcia",
    "wof:name":"Sanabria Segado Fernando",
    "wof:placetype":"venue"
},
  "geometry": {"coordinates":[-0.9203090072,37.717918396],"type":"Point"}
}