{
  "type": "Feature",
  "properties": {
    "addr:full":"Calle de Via Nueva, S/n Ponferrada Le\u00f3n 24400",
    "addr:housenumber":"s / n",
    "addr:postcode":"24400",
    "addr:street":"Calle De Via Nueva",
    "iso:country":"ES",
    "sg:address":"Calle de Via Nueva, S/n",
    "sg:city":"Ponferrada",
    "sg:orig_category":"Museos",
    "sg:phone":"+34 987 40 35 15",
    "sg:postcode":"24400",
    "sg:province":"Le\u00f3n",
    "wof:name":"Museo Del Ferrocarril",
    "wof:placetype":"venue"
},
  "geometry": {"coordinates":[-6.6049818993,42.5485725403],"type":"Point"}
}