{
  "type": "Feature",
  "properties": {
    "addr:full":"Calle de Cordoba, 3 Sevilla Sevilla 41004",
    "addr:housenumber":"3",
    "addr:postcode":"41004",
    "addr:street":"Calle De Cordoba",
    "iso:country":"ES",
    "sg:address":"Calle de Cordoba, 3",
    "sg:city":"Sevilla",
    "sg:orig_category":"Zapatos (al Por Menor)",
    "sg:phone":"+34 954 21 72 39",
    "sg:postcode":"41004",
    "sg:province":"Sevilla",
    "wof:name":"Garrido Lopez Jose",
    "wof:placetype":"venue"
},
  "geometry": {"coordinates":[-5.9927411079,37.3904190063],"type":"Point"}
}