{
  "type": "Feature",
  "properties": {
    "addr:full":"Av Comte De Llobregat, 107 Martorell Barcelona 08760",
    "addr:housenumber":"107",
    "addr:postcode":"08760",
    "iso:country":"ES",
    "sg:address":"Av Comte De Llobregat, 107",
    "sg:city":"Martorell",
    "sg:orig_category":"Distribuci\u00d3n De Petr\u00d3leo Y Derivados",
    "sg:phone":"+34 937 75 36 52",
    "sg:postcode":"08760",
    "sg:province":"Barcelona",
    "wof:name":"Arque Elias S.l.",
    "wof:placetype":"venue"
},
  "geometry": {"coordinates":[1.9146760702,41.4871902466],"type":"Point"}
}