{
  "type": "Feature",
  "properties": {
    "addr:full":"Pl L'estacio, 2 Barcelona Barcelona 08030",
    "addr:housenumber":"2",
    "addr:postcode":"08030",
    "addr:street":"Pl L'Estacio",
    "iso:country":"ES",
    "sg:address":"Pl L'estacio, 2",
    "sg:city":"Barcelona",
    "sg:orig_category":"Animales (al Por Menor)",
    "sg:phone":"+34 933 45 60 07",
    "sg:postcode":"08030",
    "sg:province":"Barcelona",
    "wof:name":"Saludes Santiba\u00f1ez Eva",
    "wof:placetype":"venue"
},
  "geometry": {"coordinates":[2.1927688122,41.4347305298],"type":"Point"}
}