{
  "type": "Feature",
  "properties": {
    "iso:country":"ES",
    "sg:address":"Calle de Camino De Los Vinateros, 65",
    "sg:city":"Madrid",
    "sg:orig_category":"Quincaller\u00cda (al Por Menor)",
    "sg:phone":"+34 914 39 03 34",
    "sg:postcode":"28030",
    "sg:province":"Madrid",
    "wof:name":"Diego Sainz Celedonio",
    "wof:placetype":"venue"
},
  "geometry": {"coordinates":[-3.6517503262,40.4101409912],"type":"Point"}
}