{
  "type": "Feature",
  "properties": {
    "addr:full":"Calle de Isla De Tenerife, 7 Valsequillo Las Palmas 35217",
    "addr:housenumber":"7",
    "addr:postcode":"35217",
    "addr:street":"Calle De Isla De Tenerife",
    "iso:country":"ES",
    "sg:address":"Calle de Isla De Tenerife, 7",
    "sg:city":"Valsequillo",
    "sg:orig_category":"Masajistas Kinesiterapeutas",
    "sg:phone":"+34 928 70 59 30",
    "sg:postcode":"35217",
    "sg:province":"Las Palmas",
    "wof:name":"Basso Ruiz Ana Maria",
    "wof:placetype":"venue"
},
  "geometry": {"coordinates":[-15.4983139038,27.99127388],"type":"Point"}
}