{
  "type": "Feature",
  "properties": {
    "addr:full":"Trva Casa Agraria (da), 6 Santiago De Compostela La Coru\u00f1a 15705",
    "addr:postcode":"15705",
    "addr:street":"Trva;Corun\u0303A",
    "iso:country":"ES",
    "sg:address":"Trva Casa Agraria (da), 6",
    "sg:city":"Santiago De Compostela",
    "sg:orig_category":"Clases De M\u00dasica Y Canto",
    "sg:phone":"+34 981 58 26 61",
    "sg:postcode":"15705",
    "sg:province":"La Coru\u00f1a",
    "wof:name":"Escuela Hispano-rusa",
    "wof:placetype":"venue"
},
  "geometry": {"coordinates":[-8.5858488083,42.8696060181],"type":"Point"}
}