{
  "type": "Feature",
  "properties": {
    "iso:country":"ES",
    "sg:address":"Sect Foresta, 6",
    "sg:city":"Tres Cantos",
    "sg:orig_category":"Transportes Por Carretera: Lotes Completos, Mercanc\u00cdas Diversas",
    "sg:phone":"+34 918 06 01 57",
    "sg:postcode":"28760",
    "sg:province":"Madrid",
    "wof:name":"El Viejo Tercio S.l.",
    "wof:placetype":"venue"
},
  "geometry": {"coordinates":[-3.7115690708,40.5986709595],"type":"Point"}
}