{
  "type": "Feature",
  "properties": {
    "iso:country":"ES",
    "sg:address":"Calle de Maestro Nicolas, 41",
    "sg:city":"Le\u00f3n",
    "sg:orig_category":"M\u00c1quinas De Coser Y De Hacer Punto (al Por Mayor)",
    "sg:phone":"+34 987 20 54 51",
    "sg:postcode":"24005",
    "sg:province":"Le\u00f3n",
    "wof:name":"Enrique Sacristan Martinez Alfredo Lorenzana C.b",
    "wof:placetype":"venue"
},
  "geometry": {"coordinates":[-5.5679402351,42.5872497559],"type":"Point"}
}