{
  "type": "Feature",
  "properties": {
    "iso:country":"ES",
    "sg:address":"Calle de Pico De Los Artilleros, 1",
    "sg:city":"Madrid",
    "sg:orig_category":"Arquitectos",
    "sg:phone":"+34 917 51 31 77",
    "sg:postcode":"28030",
    "sg:province":"Madrid",
    "wof:name":"Olmos Mecha Carlos",
    "wof:placetype":"venue"
},
  "geometry": {"coordinates":[-3.640417099,40.4090118408],"type":"Point"}
}