{
  "type": "Feature",
  "properties": {
    "iso:country":"ES",
    "sg:address":"Carrer de Pau, 28",
    "sg:city":"Manresa",
    "sg:orig_category":"Mec\u00c1nico Del Autom\u00d3vil",
    "sg:phone":"+34 938 74 34 08",
    "sg:postcode":"08243",
    "sg:province":"Barcelona",
    "wof:name":"Comellas Fontcuberta Juan",
    "wof:placetype":"venue"
},
  "geometry": {"coordinates":[1.8335859776,41.7373428345],"type":"Point"}
}