{
  "type": "Feature",
  "properties": {
    "iso:country":"ES",
    "sg:address":"Avda Atance (el), 11",
    "sg:city":"Guadalajara",
    "sg:orig_category":"Estancos",
    "sg:phone":"+34 949 21 43 18",
    "sg:postcode":"19005",
    "sg:province":"Guadalajara",
    "wof:name":"Fernandez Monje Luis Miguel",
    "wof:placetype":"venue"
},
  "geometry": {"coordinates":[-3.1551909447,40.6412582397],"type":"Point"}
}