{
  "type": "Feature",
  "properties": {
    "iso:country":"ES",
    "sg:address":"Avda Ribados, 16",
    "sg:city":"Burgo",
    "sg:orig_category":"Molduras, Junquillos, Listones Y Molduras Perforadas",
    "sg:phone":"+34 981 65 35 48",
    "sg:postcode":"15670",
    "sg:province":"A Coru\u00f1a",
    "wof:name":"Sistelcom-telemensaje S.a.",
    "wof:placetype":"venue"
},
  "geometry": {"coordinates":[-8.3693180084,43.3144340515],"type":"Point"}
}