{
  "type": "Feature",
  "properties": {
    "iso:country":"ES",
    "sg:address":"Avda Oasis, 139",
    "sg:city":"Ejido",
    "sg:orig_category":"Ense\u00d1anza Secundaria: Colegios Y Escuelas Privadas",
    "sg:phone":"+34 950 48 96 62",
    "sg:postcode":"04700",
    "sg:province":"Almer\u00eda",
    "wof:name":"Junta De Andalucia-instituto De Ense\u00f1anza Secundaria Santo Domingo",
    "wof:placetype":"venue"
},
  "geometry": {"coordinates":[-2.8010590076,36.7683181763],"type":"Point"}
}