{
  "type": "Feature",
  "properties": {
    "addr:full":"Calle de Lope De Haro, 30 Madrid Madrid 28039",
    "addr:housenumber":"30",
    "addr:postcode":"madrid;28039",
    "addr:street":"Calle De Lope De Haro",
    "iso:country":"ES",
    "sg:address":"Calle de Lope De Haro, 30",
    "sg:city":"Madrid",
    "sg:orig_category":"Ropa Para Se\u00d1oras Y Caballeros (al Por Menor)",
    "sg:phone":"+34 913 11 27 97",
    "sg:postcode":"28039",
    "sg:province":"Madrid",
    "wof:name":"Suarez Savurido S.l.",
    "wof:placetype":"venue"
},
  "geometry": {"coordinates":[-3.7043569088,40.456703186],"type":"Point"}
}