{
  "type": "Feature",
  "properties": {
    "iso:country":"ES",
    "sg:address":"Ctra Circunvalacion, 18",
    "sg:city":"Benidorm",
    "sg:orig_category":"Ropa Para Se\u00d1oras Y Caballeros (al Por Menor)",
    "sg:phone":"+34 965 85 96 99",
    "sg:postcode":"03500",
    "sg:province":"Alicante",
    "wof:name":"Yang  Xinmin",
    "wof:placetype":"venue"
},
  "geometry": {"coordinates":[-0.130487293,38.50233078],"type":"Point"}
}