{
  "type": "Feature",
  "properties": {
    "iso:country":"ES",
    "sg:address":"Ctra Palma-soller, Km. 0010,0",
    "sg:city":"Palmanyola",
    "sg:orig_category":"Maquinaria Para Industrias Diversas",
    "sg:phone":"+34 971 14 95 14",
    "sg:postcode":"07193",
    "sg:province":"Islas Baleares",
    "wof:name":"Alfe Renta Catalunya S.a.",
    "wof:placetype":"venue"
},
  "geometry": {"coordinates":[2.6894190311,39.7022666931],"type":"Point"}
}