{
  "type": "Feature",
  "properties": {
    "iso:country":"ES",
    "sg:address":"Carrer de Comas I Sola, 17",
    "sg:city":"Mira-sol",
    "sg:orig_category":"Centros Empresariales",
    "sg:phone":"+34 935 89 32 19",
    "sg:postcode":"08195",
    "sg:province":"Barcelona",
    "wof:name":"Hernandez Herrero Pedro",
    "wof:placetype":"venue"
},
  "geometry": {"coordinates":[2.0655589104,41.4671669006],"type":"Point"}
}