{
  "type": "Feature",
  "properties": {
    "addr:full":"Girona, 13 Platja Aro Girona 17250",
    "addr:housenumber":"13",
    "addr:postcode":"17250",
    "addr:street":"Girona",
    "iso:country":"ES",
    "sg:address":"Girona, 13",
    "sg:city":"Platja Aro",
    "sg:orig_category":"Fabrica De Cer\u00c1micas",
    "sg:phone":"+34 972 82 65 47",
    "sg:postcode":"17250",
    "sg:province":"Girona",
    "sg:website":"www.bobilbondia.com",
    "wof:name":"Bobila Bondia S.l.",
    "wof:placetype":"venue"
},
  "geometry": {"coordinates":[3.0639550686,41.8142547607],"type":"Point"}
}