{
  "type": "Feature",
  "properties": {
    "addr:full":"Calle de Pintor Nu\u00d1ez-cortes, 3 Villarrobledo Albacete 02600",
    "addr:housenumber":"3",
    "addr:postcode":"02600",
    "addr:street":"Calle De Pintor Nun\u0303Ez-Cortes",
    "iso:country":"ES",
    "sg:address":"Calle de Pintor Nu\u00d1ez-cortes, 3",
    "sg:city":"Villarrobledo",
    "sg:orig_category":"Promotores Constructores",
    "sg:phone":"+34 967 14 49 63",
    "sg:postcode":"02600",
    "sg:province":"Albacete",
    "wof:name":"Disenos Y Construcciones De La Mancha Soluciones Integrales S.l.",
    "wof:placetype":"venue"
},
  "geometry": {"coordinates":[-0.6567689776,38.0584983826],"type":"Point"}
}