{
  "type": "Feature",
  "properties": {
    "addr:full":"Galerias Pl. Major, 67 Palma Islas Baleares 07002",
    "addr:housenumber":"67",
    "addr:postcode":"07002",
    "addr:street":"Pl. Major",
    "iso:country":"ES",
    "sg:address":"Galerias Pl. Major, 67",
    "sg:city":"Palma",
    "sg:orig_category":"Ropa Para Se\u00d1oras Y Caballeros (al Por Menor)",
    "sg:phone":"+34 971 72 16 42",
    "sg:postcode":"07002",
    "sg:province":"Islas Baleares",
    "wof:name":"Bolo  Joseth",
    "wof:placetype":"venue"
},
  "geometry": {"coordinates":[2.6469399929,39.5714836121],"type":"Point"}
}