{
  "type": "Feature",
  "properties": {
    "iso:country":"ES",
    "sg:address":"Rasa De Arriba, S/n",
    "sg:city":"Rasa De Arriba",
    "sg:orig_category":"Ense\u00d1anza Variada",
    "sg:phone":"+34 981 82 20 43",
    "sg:postcode":"15200",
    "sg:province":"A Coru\u00f1a",
    "wof:name":"Villar Outeiro Antonio",
    "wof:placetype":"venue"
},
  "geometry": {"coordinates":[-8.8883037567,42.788608551],"type":"Point"}
}