{
  "type": "Feature",
  "properties": {
    "addr:full":"Ctra Fuengirola Mijas, Km. 0004,5 Mijas M\u00e1laga 29650",
    "addr:postcode":"29650",
    "addr:street":"Ctra Fuengirola Mijas Km. 0004,5;Ma\u0301Laga",
    "iso:country":"ES",
    "sg:address":"Ctra Fuengirola Mijas, Km. 0004,5",
    "sg:city":"Mijas",
    "sg:orig_category":"Inmobiliaria (agencias)",
    "sg:phone":"+34 952 48 56 87",
    "sg:postcode":"29650",
    "sg:province":"M\u00e1laga",
    "wof:name":"Andersen And Fox S.cv.",
    "wof:placetype":"venue"
},
  "geometry": {"coordinates":[-4.6318244934,36.599609375],"type":"Point"}
}