{
  "type": "Feature",
  "properties": {
    "iso:country":"ES",
    "sg:address":"Bard Cruz De La, 28",
    "sg:city":"Zona De Los Principes",
    "sg:orig_category":"Promotores Constructores",
    "sg:phone":"+34 959 53 05 20",
    "sg:postcode":"21810",
    "sg:province":"Huelva",
    "wof:name":"Construcciones Y Ferrallas Onubenses S.l.",
    "wof:placetype":"venue"
},
  "geometry": {"coordinates":[-6.8923411369,37.2240829468],"type":"Point"}
}