{
  "type": "Feature",
  "properties": {
    "addr:full":"Rua Calvo Sotelo, 135 Sarria Lugo 27600",
    "addr:housenumber":"135",
    "addr:postcode":"27600",
    "addr:street":"Rua Calvo Sotelo",
    "iso:country":"ES",
    "sg:address":"Rua Calvo Sotelo, 135",
    "sg:city":"Sarria",
    "sg:orig_category":"Ropa Para Se\u00d1oras Y Caballeros (al Por Menor)",
    "sg:phone":"+34 982 53 00 52",
    "sg:postcode":"27600",
    "sg:province":"Lugo",
    "wof:name":"Lopez Rodriguez Olga",
    "wof:placetype":"venue"
},
  "geometry": {"coordinates":[-7.4109339714,42.7789916992],"type":"Point"}
}