{
  "type": "Feature",
  "properties": {
    "iso:country":"ES",
    "sg:address":"Calle de Fernando Guanarteme, 159",
    "sg:city":"Palmas De Gran Canaria",
    "sg:orig_category":"Inform\u00c1tica, Ofim\u00c1tica (estudios, Asesor\u00cda, Ingenier\u00cda, Formaci\u00d3n)",
    "sg:phone":"+34 902 10 04 77",
    "sg:postcode":"35010",
    "sg:province":"Las Palmas",
    "sg:website":"www.megastorecanarias.com",
    "wof:name":"Megastore Computer Canarias S.a.",
    "wof:placetype":"venue"
},
  "geometry": {"coordinates":[-15.4412584305,28.1312828064],"type":"Point"}
}