{
  "type": "Feature",
  "properties": {
    "iso:country":"ES",
    "sg:address":"Calle de Zaire, 2",
    "sg:city":"Almeria",
    "sg:orig_category":"M\u00c1quinas De Escribir, M\u00c1quinas De Oficina (al Por Menor, Reparaci\u00d3n)",
    "sg:phone":"+34 950 14 91 01",
    "sg:postcode":"04009",
    "sg:province":"Almer\u00eda",
    "wof:name":"Gazquezmartinez S.l.",
    "wof:placetype":"venue"
},
  "geometry": {"coordinates":[-2.4429039955,36.8569297791],"type":"Point"}
}