{
  "type": "Feature",
  "properties": {
    "addr:full":"Calle de Bidebarrieta, 16 Bilbao Vizcaya 48005",
    "addr:housenumber":"16",
    "addr:postcode":"48005",
    "addr:street":"Calle De Bidebarrieta",
    "iso:country":"ES",
    "sg:address":"Calle de Bidebarrieta, 16",
    "sg:city":"Bilbao",
    "sg:orig_category":"Bisuter\u00cda, Joyer\u00cda, Relojer\u00cda (al Por Menor)",
    "sg:phone":"+34 944 16 37 65",
    "sg:postcode":"48005",
    "sg:province":"Vizcaya",
    "wof:name":"Jorpa Bisuteria S.l.",
    "wof:placetype":"venue"
},
  "geometry": {"coordinates":[-2.9242455959,43.2576789856],"type":"Point"}
}