{
  "type": "Feature",
  "properties": {
    "addr:full":"Carrer de Cobalt, 12 Hospitalet Llobregat Barcelona 08907",
    "addr:housenumber":"12",
    "addr:postcode":"08907",
    "addr:street":"Carrer De Cobalt",
    "iso:country":"ES",
    "sg:address":"Carrer de Cobalt, 12",
    "sg:city":"Hospitalet Llobregat",
    "sg:orig_category":"Barnizadores",
    "sg:phone":"+34 933 37 97 71",
    "sg:postcode":"08907",
    "sg:province":"Barcelona",
    "wof:name":"Machado Machado Manuel",
    "wof:placetype":"venue"
},
  "geometry": {"coordinates":[2.1145350933,41.3606834412],"type":"Point"}
}