{
  "type": "Feature",
  "properties": {
    "addr:full":"Calle de Santa Maria De La Cabeza, 5 Majadahonda Madrid 28220",
    "addr:postcode":"28220",
    "addr:street":"Calle De Santa;Cabeza",
    "iso:country":"ES",
    "sg:address":"Calle de Santa Maria De La Cabeza, 5",
    "sg:city":"Majadahonda",
    "sg:orig_category":"Tintorer\u00cdas, Limpieza En Seco",
    "sg:phone":"+34 916 39 79 58",
    "sg:postcode":"28220",
    "sg:province":"Madrid",
    "wof:name":"Cogolludo Prudencio Teofilo",
    "wof:placetype":"venue"
},
  "geometry": {"coordinates":[-3.870898962,40.4732933044],"type":"Point"}
}