{
  "type": "Feature",
  "properties": {
    "addr:full":"Calle de Mayor, 19 Cartagena Murcia 30201",
    "addr:housenumber":"19",
    "addr:postcode":"30201",
    "addr:street":"Calle De Mayor",
    "iso:country":"ES",
    "sg:address":"Calle de Mayor, 19",
    "sg:city":"Cartagena",
    "sg:orig_category":"Institutos De Belleza (productos Y Aparatos)",
    "sg:phone":"+34 968 12 32 97",
    "sg:postcode":"30201",
    "sg:province":"Murcia",
    "wof:name":"Marin Lopez Rosario",
    "wof:placetype":"venue"
},
  "geometry": {"coordinates":[-0.9156429768,37.600566864],"type":"Point"}
}