{
  "type": "Feature",
  "properties": {
    "iso:country":"ES",
    "sg:address":"Carrer de Murcia, 17",
    "sg:city":"S. Boi Llobregat",
    "sg:orig_category":"Inform\u00c1tica: Redes",
    "sg:phone":"+34 936 30 70 07",
    "sg:postcode":"08830",
    "sg:province":"Barcelona",
    "wof:name":"Estreus S.l",
    "wof:placetype":"venue"
},
  "geometry": {"coordinates":[2.043735981,41.3296546936],"type":"Point"}
}