{
  "type": "Feature",
  "properties": {
    "iso:country":"ES",
    "sg:address":"Calle de Juan Romero, 8",
    "sg:city":"Daimiel",
    "sg:orig_category":"Abogados",
    "sg:phone":"+34 926 85 35 87",
    "sg:postcode":"13250",
    "sg:province":"Ciudad Real",
    "wof:name":"Ruiz-valdepe\u00f1as Sanchez-hermosilla Jose Luis",
    "wof:placetype":"venue"
},
  "geometry": {"coordinates":[-3.6119589806,39.0676689148],"type":"Point"}
}