{
  "type": "Feature",
  "properties": {
    "iso:country":"ES",
    "sg:address":"Calle de Darro, 30",
    "sg:city":"Madrid",
    "sg:orig_category":"Guarder\u00cdas",
    "sg:phone":"+34 915 63 87 60",
    "sg:postcode":"28002",
    "sg:province":"Madrid",
    "wof:name":"Ferrer Torrelles Albina",
    "wof:placetype":"venue"
},
  "geometry": {"coordinates":[-3.6858081818,40.4509468079],"type":"Point"}
}