{
  "type": "Feature",
  "properties": {
    "addr:full":"Pol Ind, 7 Puerto Lumbreras Murcia 30890",
    "addr:housenumber":"7",
    "addr:postcode":"30890",
    "addr:street":"Ind",
    "iso:country":"ES",
    "sg:address":"Pol Ind, 7",
    "sg:city":"Puerto Lumbreras",
    "sg:orig_category":"Transporte En General",
    "sg:phone":"+34 968 49 65 18",
    "sg:postcode":"30890",
    "sg:province":"Murcia",
    "wof:name":"Hermanos Jimenez Cayuela S.l.",
    "wof:placetype":"venue"
},
  "geometry": {"coordinates":[-1.8125690222,37.5551490784],"type":"Point"}
}