{
  "type": "Feature",
  "properties": {
    "iso:country":"ES",
    "sg:address":"Plaz Pardinal (del), 3",
    "sg:city":"Artana",
    "sg:orig_category":"Art\u00cdculos Funerarios (al Por Menor)",
    "sg:phone":"+34 964 61 13 11",
    "sg:postcode":"12527",
    "sg:province":"Castell\u00f3n",
    "wof:name":"Vilar Coll Jose",
    "wof:placetype":"venue"
},
  "geometry": {"coordinates":[-0.2546119988,39.8906097412],"type":"Point"}
}