{
  "type": "Feature",
  "properties": {
    "iso:country":"ES",
    "sg:address":"Rua Senra (da), 28",
    "sg:city":"Santiago De Compostela",
    "sg:orig_category":"Agencias De Viajes",
    "sg:phone":"+34 981 58 79 11",
    "sg:postcode":"15702",
    "sg:province":"A Coru\u00f1a",
    "wof:name":"Viajes Viloria S. A.",
    "wof:placetype":"venue"
},
  "geometry": {"coordinates":[-8.5457286835,42.8768501282],"type":"Point"}
}