{
  "type": "Feature",
  "properties": {
    "iso:country":"ES",
    "sg:address":"Calle de Labayo, S/n",
    "sg:city":"San Vitero",
    "sg:orig_category":"Producci\u00d3n De Champi\u00d1ones",
    "sg:phone":"+34 980 68 14 11",
    "sg:postcode":"49523",
    "sg:province":"Zamora",
    "wof:name":"Lorenzo Fernandez Cesar",
    "wof:placetype":"venue"
},
  "geometry": {"coordinates":[-6.3494691849,41.7737770081],"type":"Point"}
}