{
  "type": "Feature",
  "properties": {
    "addr:full":"Avda Gran Via, 152 Vigo Pontevedra 36211",
    "addr:housenumber":"152",
    "addr:postcode":"36211",
    "addr:street":"Avda Gran Via",
    "iso:country":"ES",
    "sg:address":"Avda Gran Via, 152",
    "sg:city":"Vigo",
    "sg:orig_category":"Ropa Para Se\u00d1oras (al Por Menor)",
    "sg:phone":"+34 986 47 14 52",
    "sg:postcode":"36211",
    "sg:province":"Pontevedra",
    "wof:name":"Soto Soto Rosa",
    "wof:placetype":"venue"
},
  "geometry": {"coordinates":[-8.7271165848,42.2221832275],"type":"Point"}
}