{
  "type": "Feature",
  "properties": {
    "addr:full":"Calle de Pedro Heredia, 28 Madrid Madrid 28028",
    "addr:housenumber":"28",
    "addr:postcode":"madrid;28028",
    "addr:street":"Calle De Pedro Heredia",
    "iso:country":"ES",
    "sg:address":"Calle de Pedro Heredia, 28",
    "sg:city":"Madrid",
    "sg:orig_category":"Internados & Ense\u00d1anza Privada",
    "sg:phone":"+34 917 26 03 57",
    "sg:postcode":"28028",
    "sg:province":"Madrid",
    "wof:name":"Colegio De Santa Susana",
    "wof:placetype":"venue"
},
  "geometry": {"coordinates":[-3.6634280682,40.4294967651],"type":"Point"}
}