{
  "type": "Feature",
  "properties": {
    "addr:full":"Calle de Boqueron, 33 Marbella M\u00e1laga 29600",
    "addr:housenumber":"33",
    "addr:postcode":"29600",
    "addr:street":"Calle De Boqueron;Ma\u0301Laga",
    "iso:country":"ES",
    "sg:address":"Calle de Boqueron, 33",
    "sg:city":"Marbella",
    "sg:orig_category":"Deportes Diversos",
    "sg:phone":"+34 952 82 48 01",
    "sg:postcode":"29600",
    "sg:province":"M\u00e1laga",
    "wof:name":"Asociacion Deportiva Ajedrez Metro Club",
    "wof:placetype":"venue"
},
  "geometry": {"coordinates":[-4.8821353912,36.5144004822],"type":"Point"}
}