{
  "type": "Feature",
  "properties": {
    "addr:full":"Autovia Logro\u00f1o, Km. 0002,0 Zaragoza Zaragoza 50011",
    "addr:postcode":"50011",
    "addr:street":"Autovia Logron\u0303O Km. 0002,0",
    "iso:country":"ES",
    "sg:address":"Autovia Logro\u00f1o, Km. 0002,0",
    "sg:city":"Zaragoza",
    "sg:orig_category":"Artes Gr\u00c1ficas, Artes Pl\u00c1sticas (curso)",
    "sg:phone":"+34 976 53 19 79",
    "sg:postcode":"50011",
    "sg:province":"Zaragoza",
    "sg:website":"www.zaforsa.es",
    "wof:name":"Zaragozana De Formularios S.a.",
    "wof:placetype":"venue"
},
  "geometry": {"coordinates":[-0.9676982164,41.6829299927],"type":"Point"}
}