{
  "type": "Feature",
  "properties": {
    "addr:full":"Carrer de Princesa, 5 Barcelona Barcelona 08003",
    "addr:housenumber":"5",
    "addr:postcode":"08003",
    "addr:street":"Carrer De Princesa",
    "iso:country":"ES",
    "sg:address":"Carrer de Princesa, 5",
    "sg:city":"Barcelona",
    "sg:orig_category":"Art\u00cdculos De Regalo (al Por Menor)",
    "sg:phone":"+34 933 19 01 01",
    "sg:postcode":"08003",
    "sg:province":"Barcelona",
    "sg:website":"www.verdpoma.",
    "wof:name":"Delriu Ferrando Gloria",
    "wof:placetype":"venue"
},
  "geometry": {"coordinates":[2.1790060997,41.3843193054],"type":"Point"}
}