{
  "type": "Feature",
  "properties": {
    "addr:full":"Calle de Batan De San Sebastian, 1 Palencia Palencia 34002",
    "addr:housenumber":"1",
    "addr:postcode":"34002",
    "addr:street":"Calle De Batan De San Sebastian",
    "iso:country":"ES",
    "sg:address":"Calle de Batan De San Sebastian, 1",
    "sg:city":"Palencia",
    "sg:orig_category":"Electrodom\u00c9sticos (fabricaci\u00d3n, Al Por Mayor)",
    "sg:phone":"+34 979 71 42 52",
    "sg:postcode":"34002",
    "sg:province":"Palencia",
    "sg:website":"www.paginasamarillas.es",
    "wof:name":"T V Paco Electrodomesticos S.l.",
    "wof:placetype":"venue"
},
  "geometry": {"coordinates":[-4.5303487778,42.0038261414],"type":"Point"}
}