{
  "type": "Feature",
  "properties": {
    "addr:full":"Calle de Trascorrales, 8 Zalamea Serena Badajoz 06430",
    "addr:housenumber":"8",
    "addr:postcode":"06430",
    "addr:street":"Calle De Trascorrales",
    "iso:country":"ES",
    "sg:address":"Calle de Trascorrales, 8",
    "sg:city":"Zalamea Serena",
    "sg:orig_category":"Inmobiliaria (agencias)",
    "sg:phone":"+34 924 78 00 80",
    "sg:postcode":"06430",
    "sg:province":"Badajoz",
    "wof:name":"Pizarro Rodriguez Francisco",
    "wof:placetype":"venue"
},
  "geometry": {"coordinates":[-5.6590127945,38.6513786316],"type":"Point"}
}