{
  "type": "Feature",
  "properties": {
    "addr:full":"Calle de Erribera, 11 Ondarroa Vizcaya 48700",
    "addr:housenumber":"11",
    "addr:postcode":"48700",
    "addr:street":"Calle De Erribera",
    "iso:country":"ES",
    "sg:address":"Calle de Erribera, 11",
    "sg:city":"Ondarroa",
    "sg:orig_category":"Restaurantes",
    "sg:phone":"+34 946 83 00 05",
    "sg:postcode":"48700",
    "sg:province":"Vizcaya",
    "wof:name":"Abdassi  Miloudi",
    "wof:placetype":"venue"
},
  "geometry": {"coordinates":[-2.422443,43.320545],"type":"Point"}
}