{
  "type": "Feature",
  "properties": {
    "iso:country":"ES",
    "sg:address":"Calle de Camino Viejo De Leganes, 47",
    "sg:city":"Madrid",
    "sg:orig_category":"Servicio De Salud",
    "sg:phone":"+34 914 72 00 16",
    "sg:postcode":"28019",
    "sg:province":"Madrid",
    "wof:name":"Madro\u00f1al Chamorro Emilio",
    "wof:placetype":"venue"
},
  "geometry": {"coordinates":[-3.7249531746,40.3908119202],"type":"Point"}
}