{
  "type": "Feature",
  "properties": {
    "addr:full":"Pase Generalisimo, S/n Garrucha Almer\u00eda 04630",
    "addr:housenumber":"s / n",
    "addr:postcode":"04630",
    "addr:street":"Generalisimo;Almeri\u0301A",
    "iso:country":"ES",
    "sg:address":"Pase Generalisimo, S/n",
    "sg:city":"Garrucha",
    "sg:orig_category":"Navegaci\u00d3n (equipos Fluviales)",
    "sg:phone":"+34 950 46 03 73",
    "sg:postcode":"04630",
    "sg:province":"Almer\u00eda",
    "wof:name":"Pintor Carmona Jose",
    "wof:placetype":"venue"
},
  "geometry": {"coordinates":[-1.8196489811,37.1859741211],"type":"Point"}
}