{
  "type": "Feature",
  "properties": {
    "addr:full":"Av Fornas Del, 11 Valls Tarragona 43800",
    "addr:housenumber":"11",
    "addr:postcode":"43800",
    "addr:street":"Av Fornas Del",
    "iso:country":"ES",
    "sg:address":"Av Fornas Del, 11",
    "sg:city":"Valls",
    "sg:orig_category":"Alimentaci\u00d3n General (al Por Menor)",
    "sg:phone":"+34 977 61 31 95",
    "sg:postcode":"43800",
    "sg:province":"Tarragona",
    "wof:name":"Guell Leal Jose Luis",
    "wof:placetype":"venue"
},
  "geometry": {"coordinates":[1.2573490143,41.2954597473],"type":"Point"}
}