{
  "type": "Feature",
  "properties": {
    "iso:country":"ES",
    "sg:address":"Calle de Virgen De La Estrella, 13",
    "sg:city":"Sevilla",
    "sg:orig_category":"Marroquiner\u00cda (confecci\u00d3n)",
    "sg:phone":"+34 954 27 60 73",
    "sg:postcode":"41011",
    "sg:province":"Sevilla",
    "wof:name":"Deco De Castro Victor Manuel",
    "wof:placetype":"venue"
},
  "geometry": {"coordinates":[-5.9996957779,37.3740158081],"type":"Point"}
}