{
  "type": "Feature",
  "properties": {
    "iso:country":"ES",
    "sg:address":"Ctra. Torrelaguna-guadalajara, S/n",
    "sg:city":"Torrelaguna",
    "sg:orig_category":"Semiller\u00cdas",
    "sg:phone":"+34 918 43 15 31",
    "sg:postcode":"28180",
    "sg:province":"Madrid",
    "wof:name":"Multigarden E Hidraulica S.l.",
    "wof:placetype":"venue"
},
  "geometry": {"coordinates":[-3.5387859344,40.8266334534],"type":"Point"}
}