{
  "type": "Feature",
  "properties": {
    "iso:country":"ES",
    "sg:address":"Calle de Doscientos (los), 9",
    "sg:city":"Alacant",
    "sg:orig_category":"Abogados",
    "sg:phone":"+34 965 10 55 99",
    "sg:postcode":"03007",
    "sg:province":"Alicante",
    "wof:name":"Garcia Olcina Lidia Maria",
    "wof:placetype":"venue"
},
  "geometry": {"coordinates":[-0.5010535717,38.3420791626],"type":"Point"}
}