{
  "type": "Feature",
  "properties": {
    "addr:full":"Ctra Reus, Km. 0005,5 Campsa Tarragona 43006",
    "addr:postcode":"43006",
    "addr:street":"Ctra Reus Km. 0005,5",
    "iso:country":"ES",
    "sg:address":"Ctra Reus, Km. 0005,5",
    "sg:city":"Campsa",
    "sg:orig_category":"Ense\u00d1anza, Formaci\u00d3n Profesional: Aprendizaje",
    "sg:phone":"+34 977 54 16 68",
    "sg:postcode":"43006",
    "sg:province":"Tarragona",
    "wof:name":"Centre De Telecomunicaciones De Catalunya",
    "wof:placetype":"venue"
},
  "geometry": {"coordinates":[1.2209249735,41.1154441833],"type":"Point"}
}