{
  "type": "Feature",
  "properties": {
    "iso:country":"ES",
    "sg:address":"Calle de Mendez Nu\u00d1ez, 10",
    "sg:city":"Santa Cruz De Tenerife",
    "sg:orig_category":"Muebles Y Accesorios Para Cocinas Y Cuartos De Ba\u00d1o (al Por Menor)",
    "sg:phone":"+34 922 28 24 93",
    "sg:postcode":"38003",
    "sg:province":"Santa Cruz De Tenerife",
    "wof:name":"Cocican S.l.",
    "wof:placetype":"venue"
},
  "geometry": {"coordinates":[-16.3326644897,28.4846744537],"type":"Point"}
}