{
  "type": "Feature",
  "properties": {
    "iso:country":"ES",
    "sg:address":"Plaz Circular, 11",
    "sg:city":"Vista Alegre",
    "sg:orig_category":"M\u00c9dicos: Pediatr\u00cda. Enfermedades De Los Ni\u00d1os",
    "sg:phone":"+34 968 24 05 46",
    "sg:postcode":"30008",
    "sg:province":"Murcia",
    "wof:name":"Nadal Ortega Jose Maria Antonio",
    "wof:placetype":"venue"
},
  "geometry": {"coordinates":[-0.9429799914,37.6082115173],"type":"Point"}
}