{
  "type": "Feature",
  "properties": {
    "iso:country":"ES",
    "sg:address":"Calle de Francia, 22",
    "sg:city":"Vitoria-gasteiz",
    "sg:orig_category":"Quincaller\u00cda (al Por Menor)",
    "sg:phone":"+34 945 25 29 83",
    "sg:postcode":"01002",
    "sg:province":"\u00c1lava",
    "wof:name":"Aizpeolea Arcelus Jose Joaquin",
    "wof:placetype":"venue"
},
  "geometry": {"coordinates":[-2.6684103012,42.8488006592],"type":"Point"}
}