{
  "type": "Feature",
  "properties": {
    "iso:country":"ES",
    "sg:address":"Carrer de Angel (de L'), 6",
    "sg:city":"Tortosa",
    "sg:orig_category":"Perfumer\u00cda (al Por Menor)",
    "sg:phone":"+34 977 44 87 12",
    "sg:postcode":"43500",
    "sg:province":"Tarragona",
    "sg:website":"www.julia.ad",
    "wof:name":"Julia Espa\u00f1a Perfum S.a.",
    "wof:placetype":"venue"
},
  "geometry": {"coordinates":[0.5216119885,40.8122177124],"type":"Point"}
}