{
  "type": "Feature",
  "properties": {
    "iso:country":"ES",
    "sg:address":"Avda Landako Etorbidea, 5",
    "sg:city":"Durango",
    "sg:orig_category":"Inmobiliaria (agencias)",
    "sg:phone":"+34 944 66 84 66",
    "sg:postcode":"48200",
    "sg:province":"Vizcaya",
    "wof:name":"Baskoi S.l",
    "wof:placetype":"venue"
},
  "geometry": {"coordinates":[-2.6327190399,43.1716842651],"type":"Point"}
}