{
  "type": "Feature",
  "properties": {
    "addr:full":"Calle de Vidriera (la), 6 Reinosa Cantabria 39200",
    "addr:postcode":"39200",
    "addr:street":"Calle De Vidriera La 6",
    "iso:country":"ES",
    "sg:address":"Calle de Vidriera (la), 6",
    "sg:city":"Reinosa",
    "sg:orig_category":"Laboratorios Y Trabajos De Fotograf\u00cda, V\u00cddeo Y Cine",
    "sg:phone":"+34 942 75 36 88",
    "sg:postcode":"39200",
    "sg:province":"Cantabria",
    "wof:name":"Miguel Se\u00f1as Eduardo De",
    "wof:placetype":"venue"
},
  "geometry": {"coordinates":[-4.1365141869,42.9990539551],"type":"Point"}
}