{
  "type": "Feature",
  "properties": {
    "addr:full":"Avda Albufera, 153 Madrid Madrid 28038",
    "addr:housenumber":"153",
    "addr:postcode":"28038",
    "addr:street":"Avda Albufera",
    "iso:country":"ES",
    "sg:address":"Avda Albufera, 153",
    "sg:city":"Madrid",
    "sg:orig_category":"Estudios Y Construcci\u00d3n De Acuarios Y Viveros",
    "sg:phone":"+34 914 77 33 42",
    "sg:postcode":"28038",
    "sg:province":"Madrid",
    "wof:name":"A.v.a Y Mascotas S.l.",
    "wof:placetype":"venue"
},
  "geometry": {"coordinates":[-3.6564218998,40.3917388916],"type":"Point"}
}