{
  "type": "Feature",
  "properties": {
    "iso:country":"ES",
    "sg:address":"Coscaros, 2",
    "sg:city":"Siador",
    "sg:orig_category":"Lecher\u00cdas",
    "sg:phone":"+34 986 58 02 41",
    "sg:postcode":"36547",
    "sg:province":"Pontevedra",
    "wof:name":"Louzao Meijomence Miguel",
    "wof:placetype":"venue"
},
  "geometry": {"coordinates":[-8.3007793427,42.6858215332],"type":"Point"}
}