{
  "type": "Feature",
  "properties": {
    "addr:full":"Av Mariner, 14 S. Pau Seguries Girona 17864",
    "addr:housenumber":"14",
    "addr:postcode":"17864",
    "addr:street":"Av Mariner;S. Pau Seguries",
    "iso:country":"ES",
    "sg:address":"Av Mariner, 14",
    "sg:city":"S. Pau Seguries",
    "sg:classifiers":[
        {
            "category":"Taxi",
            "type":"Transportation"
        }
    ],
    "sg:phone":"+34 972 74 70 35",
    "sg:postcode":"17864",
    "sg:province":"Girona",
    "wof:name":"Roura Tallant Maria",
    "wof:placetype":"venue"
},
  "geometry": {"coordinates":[2.3675479889,42.261554718],"type":"Point"}
}