{
  "type": "Feature",
  "properties": {
    "addr:full":"Calle de Poeta Alberola, 17 Valencia Valencia 46018",
    "addr:housenumber":"17",
    "addr:postcode":"46018",
    "addr:street":"Calle De Poeta Alberola",
    "iso:country":"ES",
    "sg:address":"Calle de Poeta Alberola, 17",
    "sg:city":"Valencia",
    "sg:orig_category":"Prot\u00c9sicos Dentales",
    "sg:phone":"+34 963 84 25 60",
    "sg:postcode":"46018",
    "sg:province":"Valencia",
    "wof:name":"Morales Rico Mario",
    "wof:placetype":"venue"
},
  "geometry": {"coordinates":[-0.3939859867,39.4693489075],"type":"Point"}
}