{
  "type": "Feature",
  "properties": {
    "addr:full":"Carr Arbres, 9 Badalona Barcelona 08912",
    "addr:housenumber":"9",
    "addr:postcode":"08912",
    "addr:street":"Carr Arbres",
    "iso:country":"ES",
    "sg:address":"Carr Arbres, 9",
    "sg:city":"Badalona",
    "sg:orig_category":"Molduras, Junquillos, Listones Y Molduras Perforadas",
    "sg:phone":"+34 933 84 55 49",
    "sg:postcode":"08912",
    "sg:province":"Barcelona",
    "wof:name":"Sola Ceren Manuel",
    "wof:placetype":"venue"
},
  "geometry": {"coordinates":[2.2464370728,41.447593689],"type":"Point"}
}