{
  "type": "Feature",
  "properties": {
    "addr:full":"Calle de San Damaso, 2 Talavera Reina Toledo 45600",
    "addr:housenumber":"2",
    "addr:postcode":"45600",
    "addr:street":"Calle De San Damaso",
    "iso:country":"ES",
    "sg:address":"Calle de San Damaso, 2",
    "sg:city":"Talavera Reina",
    "sg:orig_category":"Fabricaci\u00d3n, Alquiler, Venta De Encofrados",
    "sg:phone":"+34 925 82 63 88",
    "sg:postcode":"45600",
    "sg:province":"Toledo",
    "wof:name":"Estructuras Y Forjados San Damaso S.l.",
    "wof:placetype":"venue"
},
  "geometry": {"coordinates":[-4.8528170586,39.9517326355],"type":"Point"}
}