{
  "type": "Feature",
  "properties": {
    "addr:full":"Calle de Rua Antigua, 3 Salamanca Salamanca 37002",
    "addr:housenumber":"3",
    "addr:postcode":"37002",
    "addr:street":"Calle De Rua Antigua",
    "iso:country":"ES",
    "sg:address":"Calle de Rua Antigua, 3",
    "sg:city":"Salamanca",
    "sg:orig_category":"Alimentaci\u00d3n General (al Por Menor)",
    "sg:phone":"+34 923 21 38 37",
    "sg:postcode":"37002",
    "sg:province":"Salamanca",
    "wof:name":"Gonzalez I\u00f1igo Gabriela",
    "wof:placetype":"venue"
},
  "geometry": {"coordinates":[-5.6659498215,40.9625701904],"type":"Point"}
}