{
  "type": "Feature",
  "properties": {
    "iso:country":"ES",
    "sg:address":"Calle de Txabarri, 10",
    "sg:city":"Sodupe",
    "sg:orig_category":"Empresarios",
    "sg:phone":"+34 946 69 23 21",
    "sg:postcode":"48830",
    "sg:province":"Vizcaya",
    "wof:name":"Ari\u00f1o Lambarri Maria Jesus",
    "wof:placetype":"venue"
},
  "geometry": {"coordinates":[-3.0472884178,43.198841095],"type":"Point"}
}