{
  "type": "Feature",
  "properties": {
    "addr:full":"Rua Galiano, 21 Ferrol La Coru\u00f1a 15402",
    "addr:housenumber":"21",
    "addr:postcode":"15402",
    "addr:street":"Rua Galiano;La Corun\u0303A",
    "iso:country":"ES",
    "sg:address":"Rua Galiano, 21",
    "sg:city":"Ferrol",
    "sg:orig_category":"Art\u00cdculos De Regalo (al Por Menor)",
    "sg:phone":"+34 981 32 17 03",
    "sg:postcode":"15402",
    "sg:province":"La Coru\u00f1a",
    "wof:name":"Castro Vazquez Celso",
    "wof:placetype":"venue"
},
  "geometry": {"coordinates":[-8.2298402786,43.4855575562],"type":"Point"}
}