{
  "type": "Feature",
  "properties": {
    "iso:country":"ES",
    "sg:address":"Calle de Arroyomolinos (de), 10",
    "sg:city":"Leganes",
    "sg:orig_category":"Arquitectos",
    "sg:phone":"+34 916 48 56 51",
    "sg:postcode":"28914",
    "sg:province":"Madrid",
    "wof:name":"Martinez De Due\u00f1as Santiago",
    "wof:placetype":"venue"
},
  "geometry": {"coordinates":[-3.7884294987,40.3106460571],"type":"Point"}
}