{
  "type": "Feature",
  "properties": {
    "iso:country":"ES",
    "sg:address":"Urb. Mullo Crusat, 11",
    "sg:city":"Vilamarxant",
    "sg:orig_category":"Audiovisuales (producci\u00d3n, Edici\u00d3n, Realizaci\u00d3n)",
    "sg:phone":"+34 961 65 05 93",
    "sg:postcode":"46191",
    "sg:province":"Valencia",
    "wof:name":"Rgu S.l.",
    "wof:placetype":"venue"
},
  "geometry": {"coordinates":[-0.6272540092,39.5677604675],"type":"Point"}
}