{
  "type": "Feature",
  "properties": {
    "addr:full":"Aeropuerto, S/n Ojos Garza Gando Las Palmas 35219",
    "addr:housenumber":"s / n",
    "addr:postcode":"35219",
    "addr:street":"Ojos Garza Gando Las",
    "iso:country":"ES",
    "sg:address":"Aeropuerto, S/n",
    "sg:city":"Ojos Garza Gando",
    "sg:orig_category":"Agencias De Aduana",
    "sg:phone":"+34 928 13 70 17",
    "sg:postcode":"35219",
    "sg:province":"Las Palmas",
    "wof:name":"Ruben Rodriguez S.a.",
    "wof:placetype":"venue"
},
  "geometry": {"coordinates":[-15.3971271515,27.9631061554],"type":"Point"}
}