{
  "type": "Feature",
  "properties": {
    "iso:country":"ES",
    "sg:address":"Calle de Madrid, 7",
    "sg:city":"Almansa",
    "sg:orig_category":"Venta, Instalaci\u00d3n De Cocinas",
    "sg:phone":"+34 967 34 16 25",
    "sg:postcode":"02640",
    "sg:province":"Albacete",
    "wof:name":"Diaz Martinez Juan",
    "wof:placetype":"venue"
},
  "geometry": {"coordinates":[-1.1033070087,38.8705482483],"type":"Point"}
}