{
  "type": "Feature",
  "properties": {
    "addr:full":"Carrer de Tarragona, 26 Gava Barcelona 08850",
    "addr:housenumber":"26",
    "addr:postcode":"08850",
    "addr:street":"Carrer De Tarragona",
    "iso:country":"ES",
    "sg:address":"Carrer de Tarragona, 26",
    "sg:city":"Gava",
    "sg:orig_category":"Distribuci\u00d3n De Petr\u00d3leo Y Derivados",
    "sg:phone":"+34 936 33 33 03",
    "sg:postcode":"08850",
    "sg:province":"Barcelona",
    "wof:name":"Regas-oil S.l.",
    "wof:placetype":"venue"
},
  "geometry": {"coordinates":[2.0125100613,41.2997894287],"type":"Point"}
}