{
  "type": "Feature",
  "properties": {
    "iso:country":"ES",
    "sg:address":"Calle de Albertina Capeluto, 14",
    "sg:city":"Torremolinos",
    "sg:orig_category":"Caf\u00c9s, Bares, Cervecer\u00cdas",
    "sg:phone":"+34 952 37 60 40",
    "sg:postcode":"29620",
    "sg:province":"M\u00e1laga",
    "wof:name":"Molina Campo Rocio",
    "wof:placetype":"venue"
},
  "geometry": {"coordinates":[-4.5160393715,36.6265563965],"type":"Point"}
}