{
  "type": "Feature",
  "properties": {
    "addr:full":"Mercado De Abastos, S/n S. Juan Alicante Alicante 03550",
    "addr:housenumber":"s",
    "addr:postcode":"03550",
    "addr:street":"/ N S. Juan",
    "iso:country":"ES",
    "sg:address":"Mercado De Abastos, S/n",
    "sg:city":"S. Juan Alicante",
    "sg:orig_category":"Carnicer\u00cdas, Carnicer\u00cdas",
    "sg:phone":"+34 965 65 35 84",
    "sg:postcode":"03550",
    "sg:province":"Alicante",
    "wof:name":"Ivorra Buades Jaime",
    "wof:placetype":"venue"
},
  "geometry": {"coordinates":[-0.4289290011,38.400390625],"type":"Point"}
}