{
  "type": "Feature",
  "properties": {
    "addr:full":"Urb Herrojo (el), 40 Artola M\u00e1laga 29679",
    "addr:postcode":"29679",
    "addr:street":"Urb;El;Artola Ma\u0301Laga",
    "iso:country":"ES",
    "sg:address":"Urb Herrojo (el), 40",
    "sg:city":"Artola",
    "sg:orig_category":"Inversiones",
    "sg:phone":"+34 952 78 12 80",
    "sg:postcode":"29679",
    "sg:province":"M\u00e1laga",
    "wof:name":"Sinventos Invest S.l",
    "wof:placetype":"venue"
},
  "geometry": {"coordinates":[-5.0462741852,36.5238952637],"type":"Point"}
}