{
  "type": "Feature",
  "properties": {
    "iso:country":"ES",
    "sg:address":"Avda Angustias, 1",
    "sg:city":"Navalmoral Mata",
    "sg:orig_category":"Organizaci\u00d3n De Actos, Seminarios Y Congresos",
    "sg:phone":"+34 927 53 28 33",
    "sg:postcode":"10300",
    "sg:province":"C\u00e1ceres",
    "wof:name":"Hermanos Reunidos S.a.",
    "wof:placetype":"venue"
},
  "geometry": {"coordinates":[-5.5450692177,39.8919296265],"type":"Point"}
}