{
  "type": "Feature",
  "properties": {
    "iso:country":"ES",
    "sg:address":"Calle de Blanca De Navarra, 13",
    "sg:city":"Peralta",
    "sg:orig_category":"Farmacias",
    "sg:phone":"+34 948 75 16 04",
    "sg:postcode":"31350",
    "sg:province":"Navarra",
    "wof:name":"Palacios Chaurrondo Raquel",
    "wof:placetype":"venue"
},
  "geometry": {"coordinates":[-1.8018876314,42.3381919861],"type":"Point"}
}