{
  "type": "Feature",
  "properties": {
    "addr:full":"C. Del Cano, S/n Cartama M\u00e1laga 29580",
    "addr:housenumber":"s",
    "addr:postcode":"29580",
    "addr:street":"C. Del Cano;/ N;Ma\u0301Laga",
    "iso:country":"ES",
    "sg:address":"C. Del Cano, S/n",
    "sg:city":"Cartama",
    "sg:classifiers":[
        {
            "category":"Taxi",
            "type":"Transportation"
        }
    ],
    "sg:phone":"+34 952 42 02 25",
    "sg:postcode":"29580",
    "sg:province":"M\u00e1laga",
    "wof:name":"Fuentes Sanchez Andres",
    "wof:placetype":"venue"
},
  "geometry": {"coordinates":[-4.6037940979,36.7364044189],"type":"Point"}
}