{
  "type": "Feature",
  "properties": {
    "addr:full":"Calle de Monte Carmelo, 10 Sevilla Sevilla 41011",
    "addr:housenumber":"10",
    "addr:postcode":"41011",
    "addr:street":"Calle De Monte Carmelo",
    "iso:country":"ES",
    "sg:address":"Calle de Monte Carmelo, 10",
    "sg:city":"Sevilla",
    "sg:orig_category":"Arquitectos",
    "sg:phone":"+34 954 28 17 14",
    "sg:postcode":"41011",
    "sg:province":"Sevilla",
    "wof:name":"Gestain S.l.",
    "wof:placetype":"venue"
},
  "geometry": {"coordinates":[-5.996945858,37.3780784607],"type":"Point"}
}