{
  "type": "Feature",
  "properties": {
    "iso:country":"ES",
    "sg:address":"Calle de Re\u00d1idero, 6",
    "sg:city":"Velez-malaga",
    "sg:orig_category":"Asesor\u00cda Fiscal Y Jur\u00cddica",
    "sg:phone":"+34 952 50 60 18",
    "sg:postcode":"29700",
    "sg:province":"M\u00e1laga",
    "wof:name":"Lopez Y Aranda Asesores S.l.",
    "wof:placetype":"venue"
},
  "geometry": {"coordinates":[-4.1068921089,36.7828292847],"type":"Point"}
}