{
  "type": "Feature",
  "properties": {
    "iso:country":"ES",
    "sg:address":"Ctra Madrid-cadiz, Km. 0552,6",
    "sg:city":"Dos Hermanas",
    "sg:orig_category":"Empresas De Carpinter\u00cda Met\u00c1lica",
    "sg:phone":"+34 954 91 99 99",
    "sg:postcode":"41700",
    "sg:province":"Sevilla",
    "wof:name":"Extruperfil S.a.",
    "wof:placetype":"venue"
},
  "geometry": {"coordinates":[-5.9281339645,37.2829055786],"type":"Point"}
}