{
  "type": "Feature",
  "properties": {
    "iso:country":"ES",
    "sg:address":"Avda Descubrimiento (del), 14",
    "sg:city":"Alcala Henares",
    "sg:orig_category":"Edici\u00d3n De Diarios, Revistas, Boletines",
    "sg:phone":"+34 918 83 20 77",
    "sg:postcode":"28806",
    "sg:province":"Madrid",
    "wof:name":"De Promocion Y Edici",
    "wof:placetype":"venue"
},
  "geometry": {"coordinates":[-3.3950328827,40.501625061],"type":"Point"}
}