{
  "type": "Feature",
  "properties": {
    "iso:country":"ES",
    "sg:address":"Rua Brasil, 4",
    "sg:city":"Meicende",
    "sg:orig_category":"Barnizadores",
    "sg:phone":"+34 981 17 09 31",
    "sg:postcode":"15140",
    "sg:province":"La Coru\u00f1a",
    "wof:name":"Decorga Pintura S.l.",
    "wof:placetype":"venue"
},
  "geometry": {"coordinates":[-8.46671772,43.3288497925],"type":"Point"}
}