{
  "type": "Feature",
  "properties": {
    "iso:country":"ES",
    "sg:address":"Calle de Azorin, 38",
    "sg:city":"Torrent",
    "sg:orig_category":"Ropa Y Art\u00cdculos Pre",
    "sg:phone":"+34 961 56 56 31",
    "sg:postcode":"46900",
    "sg:province":"Valencia",
    "wof:name":"Baby Carrusel C.b.",
    "wof:placetype":"venue"
},
  "geometry": {"coordinates":[-0.4781590104,39.4330711365],"type":"Point"}
}