{
  "type": "Feature",
  "properties": {
    "addr:full":"Carrer de Vinaros, 8 Hospitalet Llobregat Barcelona 08906",
    "addr:housenumber":"8",
    "addr:postcode":"08906",
    "addr:street":"Carrer De Vinaros",
    "iso:country":"ES",
    "sg:address":"Carrer de Vinaros, 8",
    "sg:city":"Hospitalet Llobregat",
    "sg:orig_category":"Arreglo, Reparaci\u00d3n, Piezas Sueltas De Televisi\u00d3n, V\u00cddeo, Hi",
    "sg:phone":"+34 934 37 23 61",
    "sg:postcode":"08906",
    "sg:province":"Barcelona",
    "wof:name":"Tele Antena Masnou S.l.",
    "wof:placetype":"venue"
},
  "geometry": {"coordinates":[2.1038219929,41.3719024658],"type":"Point"}
}