{
  "type": "Feature",
  "properties": {
    "addr:full":"Carrer de Moli, 45 Flix Tarragona 43750",
    "addr:housenumber":"45",
    "addr:postcode":"43750",
    "addr:street":"Carrer De Moli",
    "iso:country":"ES",
    "sg:address":"Carrer de Moli, 45",
    "sg:city":"Flix",
    "sg:orig_category":"Construcci\u00d3n Mec\u00c1nica",
    "sg:phone":"+34 977 41 09 55",
    "sg:postcode":"43750",
    "sg:province":"Tarragona",
    "wof:name":"Carranza Castellvi Juan Jose",
    "wof:placetype":"venue"
},
  "geometry": {"coordinates":[0.5479189754,41.2311096191],"type":"Point"}
}