{
  "type": "Feature",
  "properties": {
    "iso:country":"ES",
    "sg:address":"Carr Migdia, 63",
    "sg:city":"Girona",
    "sg:orig_category":"C\u00c1maras De Comercio E Industria, Oficios, Agricultura",
    "sg:phone":"+34 972 20 45 54",
    "sg:postcode":"17003",
    "sg:province":"Girona",
    "wof:name":"Sabat Font Lluis",
    "wof:placetype":"venue"
},
  "geometry": {"coordinates":[2.8204090595,41.973236084],"type":"Point"}
}