{
  "type": "Feature",
  "properties": {
    "addr:full":"Calle de Valdeolleros, 20 Cordoba C\u00f3rdoba 14006",
    "addr:housenumber":"20",
    "addr:postcode":"14006",
    "addr:street":"Calle De Valdeolleros;Co\u0301Rdoba",
    "iso:country":"ES",
    "sg:address":"Calle de Valdeolleros, 20",
    "sg:city":"Cordoba",
    "sg:orig_category":"Tapicer\u00cdas",
    "sg:phone":"+34 957 27 59 59",
    "sg:postcode":"14006",
    "sg:province":"C\u00f3rdoba",
    "wof:name":"Jimenez Lopez Enrique",
    "wof:placetype":"venue"
},
  "geometry": {"coordinates":[-4.7758569717,37.8979606628],"type":"Point"}
}