{
  "type": "Feature",
  "properties": {
    "addr:full":"Runes, S/n Runes A Coru\u00f1a 15930",
    "addr:housenumber":"s / n",
    "addr:postcode":"15930",
    "addr:street":"Corun\u0303A",
    "iso:country":"ES",
    "sg:address":"Runes, S/n",
    "sg:city":"Runes",
    "sg:orig_category":"Alimentaci\u00d3n General (al Por Menor)",
    "sg:phone":"+34 981 84 59 10",
    "sg:postcode":"15930",
    "sg:province":"A Coru\u00f1a",
    "wof:name":"Vidal Blanco Benigno",
    "wof:placetype":"venue"
},
  "geometry": {"coordinates":[-8.8847093582,42.6471214294],"type":"Point"}
}