{
  "type": "Feature",
  "properties": {
    "iso:country":"ES",
    "sg:address":"Calle de Losero, 1",
    "sg:city":"Palmas De Gran Canaria",
    "sg:orig_category":"Bazares, Art\u00cdculos De Limpieza Y De Cocina (al Por Menor)",
    "sg:phone":"+34 928 38 31 64",
    "sg:postcode":"35002",
    "sg:province":"Las Palmas",
    "wof:name":"Chanrai S.a.",
    "wof:placetype":"venue"
},
  "geometry": {"coordinates":[-15.4147939682,28.104101181],"type":"Point"}
}