{
  "type": "Feature",
  "properties": {
    "addr:full":"Calle de Mayor, 21 Calaceite Teruel 44610",
    "addr:housenumber":"21",
    "addr:postcode":"44610",
    "addr:street":"Calle De Mayor",
    "iso:country":"ES",
    "sg:address":"Calle de Mayor, 21",
    "sg:city":"Calaceite",
    "sg:orig_category":"Carnicer\u00cdas, Carnicer\u00cdas",
    "sg:phone":"+34 978 85 10 57",
    "sg:postcode":"44610",
    "sg:province":"Teruel",
    "wof:name":"Ferrer Alqueza Ramiro",
    "wof:placetype":"venue"
},
  "geometry": {"coordinates":[0.1876080036,41.015953064],"type":"Point"}
}