{
  "type": "Feature",
  "properties": {
    "addr:full":"Calle de Estrella, 20 Madrid Madrid 28004",
    "addr:housenumber":"20",
    "addr:postcode":"madrid;28004",
    "addr:street":"Calle De Estrella",
    "iso:country":"ES",
    "sg:address":"Calle de Estrella, 20",
    "sg:city":"Madrid",
    "sg:orig_category":"Procuradores",
    "sg:phone":"+34 915 21 55 22",
    "sg:postcode":"28004",
    "sg:province":"Madrid",
    "wof:name":"Arnes Bueno Maria Irene",
    "wof:placetype":"venue"
},
  "geometry": {"coordinates":[-3.7074670792,40.4225692749],"type":"Point"}
}