{
  "type": "Feature",
  "properties": {
    "addr:full":"Avgd Abu-masaifa, 12 Xativa Valencia 46800",
    "addr:housenumber":"12",
    "addr:postcode":"46800",
    "addr:street":"Abu-Masaifa",
    "iso:country":"ES",
    "sg:address":"Avgd Abu-masaifa, 12",
    "sg:city":"Xativa",
    "sg:orig_category":"Postigos, Persianas Y Celos\u00cdas",
    "sg:phone":"+34 962 27 00 97",
    "sg:postcode":"46800",
    "sg:province":"Valencia",
    "wof:name":"Soler Macias Vicente Ramon",
    "wof:placetype":"venue"
},
  "geometry": {"coordinates":[-0.5278970003,38.9890823364],"type":"Point"}
}