{
  "type": "Feature",
  "properties": {
    "iso:country":"ES",
    "sg:address":"Calle de Vital Aza, 66",
    "sg:city":"Madrid",
    "sg:orig_category":"Material Y Suministros Para Dentistas, Cirujanos",
    "sg:phone":"+34 914 08 82 31",
    "sg:postcode":"28017",
    "sg:province":"Madrid",
    "wof:name":"Alonso Maillo Carlos",
    "wof:placetype":"venue"
},
  "geometry": {"coordinates":[-3.639300108,40.4331092834],"type":"Point"}
}