{
  "type": "Feature",
  "properties": {
    "addr:full":"Avda Jose Ortiz, 67 Almazora Castell\u00f3n 12550",
    "addr:housenumber":"67",
    "addr:postcode":"12550",
    "addr:street":"Avda Jose Ortiz",
    "iso:country":"ES",
    "sg:address":"Avda Jose Ortiz, 67",
    "sg:city":"Almazora",
    "sg:orig_category":"Telefon\u00cda: Instaladores Varios",
    "sg:phone":"+34 964 50 31 84",
    "sg:postcode":"12550",
    "sg:province":"Castell\u00f3n",
    "wof:name":"Occident  Montania",
    "wof:placetype":"venue"
},
  "geometry": {"coordinates":[-0.0681739971,39.9553756714],"type":"Point"}
}