{
  "type": "Feature",
  "properties": {
    "iso:country":"ES",
    "sg:address":"Carre Enric Soler I Godes, 14",
    "sg:city":"Aldaia",
    "sg:orig_category":"Maquinaria Para Industrias Diversas",
    "sg:phone":"+34 961 98 53 37",
    "sg:postcode":"46960",
    "sg:province":"Valencia",
    "wof:name":"Talleres Fovi S.l.",
    "wof:placetype":"venue"
},
  "geometry": {"coordinates":[-0.4695580006,39.4614944458],"type":"Point"}
}