{
  "type": "Feature",
  "properties": {
    "addr:full":"Calle de Almirante Mourelle, 33 Coru\u00d1a La Coru\u00f1a 15011",
    "addr:housenumber":"33",
    "addr:postcode":"15011",
    "addr:street":"Calle De Almirante Mourelle;Corun\u0303A",
    "iso:country":"ES",
    "sg:address":"Calle de Almirante Mourelle, 33",
    "sg:city":"Coru\u00d1a",
    "sg:orig_category":"Molduras, Junquillos, Listones Y Molduras Perforadas",
    "sg:phone":"+34 981 27 28 05",
    "sg:postcode":"15011",
    "sg:province":"La Coru\u00f1a",
    "wof:name":"Rey Rodriguez Antonio",
    "wof:placetype":"venue"
},
  "geometry": {"coordinates":[-8.422668457,43.3657798767],"type":"Point"}
}