{
  "type": "Feature",
  "properties": {
    "iso:country":"ES",
    "sg:address":"Av Oliva, 22",
    "sg:city":"Pego",
    "sg:orig_category":"Venta, Instalaci\u00d3n, Mantenimiento De Chimeneas De Interior Y Accesorios",
    "sg:phone":"+34 965 57 14 88",
    "sg:postcode":"03780",
    "sg:province":"Alicante",
    "wof:name":"Chimeneas La Llar",
    "wof:placetype":"venue"
},
  "geometry": {"coordinates":[-0.1148490012,38.8471908569],"type":"Point"}
}