{
  "type": "Feature",
  "properties": {
    "addr:full":"Cra. Nacional Ii, S/n S. Andreu Llavaneres Barcelona 08392",
    "addr:housenumber":"s",
    "addr:postcode":"08392",
    "addr:street":"/ N S. Andreu Llavaneres Barcelona",
    "iso:country":"ES",
    "sg:address":"Cra. Nacional Ii, S/n",
    "sg:city":"S. Andreu Llavaneres",
    "sg:orig_category":"Deportes N\u00c1uticos, Acu\u00c1ticos Y Subacu\u00c1ticos: Art\u00cdculos Y Equipo (al Por Menor)",
    "sg:phone":"+34 937 92 73 06",
    "sg:postcode":"08392",
    "sg:province":"Barcelona",
    "wof:name":"Motyvel Yacht Charter S.l.",
    "wof:placetype":"venue"
},
  "geometry": {"coordinates":[2.4849700928,41.5697517395],"type":"Point"}
}