{
  "type": "Feature",
  "properties": {
    "addr:full":"Carrer de Joan Baptista Plana, 17 Tarragona Tarragona 43005",
    "addr:housenumber":"17",
    "addr:postcode":"43005",
    "addr:street":"Carrer De Joan Baptista Plana",
    "iso:country":"ES",
    "sg:address":"Carrer de Joan Baptista Plana, 17",
    "sg:city":"Tarragona",
    "sg:orig_category":"Doctores En Medicina",
    "sg:phone":"+34 977 21 50 64",
    "sg:postcode":"43005",
    "sg:province":"Tarragona",
    "wof:name":"Gazol Soler Maria Dolores",
    "wof:placetype":"venue"
},
  "geometry": {"coordinates":[1.2383379936,41.1196517944],"type":"Point"}
}