{
  "type": "Feature",
  "properties": {
    "iso:country":"ES",
    "sg:address":"Calle de Paseo, 6",
    "sg:city":"Cieza",
    "sg:orig_category":"Agencias De Viajes",
    "sg:phone":"+34 968 76 61 30",
    "sg:postcode":"30530",
    "sg:province":"Murcia",
    "sg:website":"www.halconviajes.com",
    "wof:name":"Viajes Halcon S.a.",
    "wof:placetype":"venue"
},
  "geometry": {"coordinates":[-1.4194630384,38.2388801575],"type":"Point"}
}