{
  "type": "Feature",
  "properties": {
    "iso:country":"ES",
    "sg:address":"Calle de Guadiato, 17",
    "sg:city":"Mairena Aljarafe",
    "sg:orig_category":"Ingenieros Asesor\u00cda",
    "sg:phone":"+34 955 60 95 68",
    "sg:postcode":"41927",
    "sg:province":"Sevilla",
    "wof:name":"Ca\u00f1ete Lopez Francisco Javier",
    "wof:placetype":"venue"
},
  "geometry": {"coordinates":[-6.0664510727,37.3404388428],"type":"Point"}
}