{
  "type": "Feature",
  "properties": {
    "addr:full":"Pol Ind Las Cruces, S/n Fines Almer\u00eda 04869",
    "addr:housenumber":"s / n",
    "addr:postcode":"04869",
    "addr:street":"Las Cruces",
    "iso:country":"ES",
    "sg:address":"Pol Ind Las Cruces, S/n",
    "sg:city":"Fines",
    "sg:orig_category":"Formaci\u00d3n Continuada (variada)",
    "sg:phone":"+34 950 44 42 92",
    "sg:postcode":"04869",
    "sg:province":"Almer\u00eda",
    "wof:name":"Consorcio Escuela Del Marmol De Fines",
    "wof:placetype":"venue"
},
  "geometry": {"coordinates":[-2.2685689926,37.3611907959],"type":"Point"}
}