{
  "type": "Feature",
  "properties": {
    "addr:full":"Avda San Francisco Javier, 22 Sevilla Sevilla 41018",
    "addr:housenumber":"22",
    "addr:postcode":"41018",
    "addr:street":"Avda San Francisco Javier",
    "iso:country":"ES",
    "sg:address":"Avda San Francisco Javier, 22",
    "sg:city":"Sevilla",
    "sg:orig_category":"Bancos",
    "sg:phone":"+34 954 92 16 96",
    "sg:postcode":"41018",
    "sg:province":"Sevilla",
    "wof:name":"Deutsche Bank S.a.e.",
    "wof:placetype":"venue"
},
  "geometry": {"coordinates":[-5.974960804,37.3787727356],"type":"Point"}
}