{
  "type": "Feature",
  "properties": {
    "addr:full":"Cami Parets, 10 Granollers Barcelona 08403",
    "addr:housenumber":"10",
    "addr:postcode":"08403",
    "addr:street":"Parets",
    "iso:country":"ES",
    "sg:address":"Cami Parets, 10",
    "sg:city":"Granollers",
    "sg:orig_category":"Construcci\u00d3n Mec\u00c1nica",
    "sg:phone":"+34 938 40 03 84",
    "sg:postcode":"08403",
    "sg:province":"Barcelona",
    "wof:name":"Promec Valles S.l.",
    "wof:placetype":"venue"
},
  "geometry": {"coordinates":[2.2724730968,41.5829772949],"type":"Point"}
}