{
  "type": "Feature",
  "properties": {
    "iso:country":"ES",
    "sg:address":"Calle de Via Amezaga, 3",
    "sg:city":"Sestao",
    "sg:orig_category":"Herboristas (al Por Menor)",
    "sg:phone":"+34 944 72 17 04",
    "sg:postcode":"48910",
    "sg:province":"Vizcaya",
    "wof:name":"Fidela Roy Hermosilla Y Ascension Gutierrez Monge Cdad",
    "wof:placetype":"venue"
},
  "geometry": {"coordinates":[-3.006289959,43.3080787659],"type":"Point"}
}