{
  "type": "Feature",
  "properties": {
    "addr:full":"Errotaldea, S/n Errotaldea Guip\u00f9zcoa 20260",
    "addr:housenumber":"s / n",
    "addr:postcode":"20260",
    "addr:street":"Errotaldea;Errotaldea Guipu\u0300Zcoa",
    "iso:country":"ES",
    "sg:address":"Errotaldea, S/n",
    "sg:city":"Errotaldea",
    "sg:orig_category":"Maquinaria Para Industrias Diversas",
    "sg:phone":"+34 943 65 28 46",
    "sg:postcode":"20260",
    "sg:province":"Guip\u00f9zcoa",
    "wof:name":"Altuna Aguirrezabala Bartolome",
    "wof:placetype":"venue"
},
  "geometry": {"coordinates":[-2.0985751152,43.094669342],"type":"Point"}
}