{
  "type": "Feature",
  "properties": {
    "iso:country":"ES",
    "sg:address":"Plaz Navarra, 9",
    "sg:city":"Huesca",
    "sg:orig_category":"Estancos",
    "sg:phone":"+34 974 21 15 17",
    "sg:postcode":"22002",
    "sg:province":"Huesca",
    "wof:name":"Benedicto Alcazar Alfonso",
    "wof:placetype":"venue"
},
  "geometry": {"coordinates":[-0.4087800086,42.1364746094],"type":"Point"}
}