{
  "type": "Feature",
  "properties": {
    "addr:full":"Pg Baro De Viver, 46 Argentona Barcelona 08310",
    "addr:housenumber":"46",
    "addr:postcode":"08310",
    "addr:street":"Pg Baro De Viver",
    "iso:country":"ES",
    "sg:address":"Pg Baro De Viver, 46",
    "sg:city":"Argentona",
    "sg:orig_category":"Molduras, Junquillos, Listones Y Molduras Perforadas",
    "sg:phone":"+34 937 97 04 05",
    "sg:postcode":"08310",
    "sg:province":"Barcelona",
    "wof:name":"Rectoret Sarpa Gisela",
    "wof:placetype":"venue"
},
  "geometry": {"coordinates":[2.3972599506,41.5503730774],"type":"Point"}
}