{
  "type": "Feature",
  "properties": {
    "addr:full":"Calle de Lekunberri Kalea, 3 Irun Guip\u00f9zcoa 20305",
    "addr:housenumber":"3",
    "addr:postcode":"20305",
    "addr:street":"Calle De Lekunberri Kalea;Guipu\u0300Zcoa",
    "iso:country":"ES",
    "sg:address":"Calle de Lekunberri Kalea, 3",
    "sg:city":"Irun",
    "sg:orig_category":"Fabricaci\u00d3n Y Venta De Volquetes Y Remolques",
    "sg:phone":"+34 943 61 63 82",
    "sg:postcode":"20305",
    "sg:province":"Guip\u00f9zcoa",
    "wof:name":"Industrias Onyarbi S. A. L.",
    "wof:placetype":"venue"
},
  "geometry": {"coordinates":[-1.7637690306,43.3425445557],"type":"Point"}
}