{
  "type": "Feature",
  "properties": {
    "iso:country":"ES",
    "sg:address":"Avda Teatinos (los), 9",
    "sg:city":"Sevilla",
    "sg:orig_category":"Abogados",
    "sg:phone":"+34 954 29 88 99",
    "sg:postcode":"41013",
    "sg:province":"Sevilla",
    "wof:name":"Alonso Y Garcia Abogados S.l.",
    "wof:placetype":"venue"
},
  "geometry": {"coordinates":[-5.9767513275,37.3688850403],"type":"Point"}
}