{
  "type": "Feature",
  "properties": {
    "iso:country":"ES",
    "sg:address":"Plaz Virgen De La Vega, 8",
    "sg:city":"Benavente",
    "sg:orig_category":"Centros De Educaci\u00d3n Especial",
    "sg:phone":"+34 980 63 76 89",
    "sg:postcode":"49600",
    "sg:province":"Zamora",
    "wof:name":"Colegio San Vicente De Paul",
    "wof:placetype":"venue"
},
  "geometry": {"coordinates":[-5.6767730713,42.0053634644],"type":"Point"}
}