{
  "type": "Feature",
  "properties": {
    "iso:country":"ES",
    "sg:address":"Setenil-arriate, Km 2",
    "sg:city":"Setenil",
    "sg:orig_category":"Poller\u00cda Y Caza (al Por Menor)",
    "sg:phone":"+34 956 23 43 00",
    "sg:postcode":"11692",
    "sg:province":"C\u00e1diz",
    "wof:name":"Francisco Lobato Ortega",
    "wof:placetype":"venue"
},
  "geometry": {"coordinates":[-5.1759090424,36.8626174927],"type":"Point"}
}