{
  "type": "Feature",
  "properties": {
    "iso:country":"ES",
    "sg:address":"Calle de Ca\u00d1o, S/n",
    "sg:city":"Navalmorales",
    "sg:orig_category":"Notarios",
    "sg:phone":"+34 925 40 47 62",
    "sg:postcode":"45140",
    "sg:province":"Toledo",
    "wof:name":"Rodriguez De Prada Maria Victoria",
    "wof:placetype":"venue"
},
  "geometry": {"coordinates":[-4.6140480042,39.7150115967],"type":"Point"}
}