{
  "type": "Feature",
  "properties": {
    "addr:full":"Calle de Hermanos Garcia Noblejas, 143 Madrid Madrid 28037",
    "addr:housenumber":"143",
    "addr:postcode":"28037",
    "addr:street":"Calle De Hermanos Garcia Noblejas",
    "iso:country":"ES",
    "sg:address":"Calle de Hermanos Garcia Noblejas, 143",
    "sg:city":"Madrid",
    "sg:orig_category":"Ense\u00d1anza, Formaci\u00d3n Profesional: Aprendizaje",
    "sg:phone":"+34 913 06 95 46",
    "sg:postcode":"28037",
    "sg:province":"Madrid",
    "wof:name":"Hermanas De La Providencia",
    "wof:placetype":"venue"
},
  "geometry": {"coordinates":[-3.6255888939,40.423538208],"type":"Point"}
}