{
  "type": "Feature",
  "properties": {
    "iso:country":"ES",
    "sg:address":"Pl. Pte Reina, 23",
    "sg:city":"Iru\u00f1a",
    "sg:orig_category":"Reposter\u00cdas",
    "sg:phone":"+34 948 12 65 16",
    "sg:postcode":"31015",
    "sg:province":"Navarra",
    "wof:name":"Cestau Cuadrado Maria Belen",
    "wof:placetype":"venue"
},
  "geometry": {"coordinates":[-1.6339590549,42.8247261047],"type":"Point"}
}