{
  "type": "Feature",
  "properties": {
    "iso:country":"ES",
    "sg:address":"Calle de Espartero, 1",
    "sg:city":"Zaragoza",
    "sg:orig_category":"Servicio De Salud",
    "sg:phone":"+34 976 39 41 50",
    "sg:postcode":"50001",
    "sg:province":"Zaragoza",
    "sg:website":"www.roca.es",
    "wof:name":"Roca Sanitario S.a.",
    "wof:placetype":"venue"
},
  "geometry": {"coordinates":[-0.8760340214,41.6504402161],"type":"Point"}
}