{
  "type": "Feature",
  "properties": {
    "addr:full":"Plaz Constitucion (de La), 1 Alamo Madrid 28607",
    "addr:postcode":"28607",
    "iso:country":"ES",
    "sg:address":"Plaz Constitucion (de La), 1",
    "sg:city":"Alamo",
    "sg:orig_category":"Administraciones Regionales, Departamentales Y Locales",
    "sg:phone":"+34 918 12 05 50",
    "sg:postcode":"28607",
    "sg:province":"Madrid",
    "wof:name":"Ayuntamiento De El Alamo",
    "wof:placetype":"venue"
},
  "geometry": {"coordinates":[-3.9907188416,40.2304725647],"type":"Point"}
}