{
  "type": "Feature",
  "properties": {
    "addr:full":"Carrer de Corsega, 302 Barcelona Barcelona 08008",
    "addr:housenumber":"302",
    "addr:postcode":"08008",
    "addr:street":"Carrer De Corsega",
    "iso:country":"ES",
    "sg:address":"Carrer de Corsega, 302",
    "sg:city":"Barcelona",
    "sg:orig_category":"Asociaciones Y Clubs Deportivos",
    "sg:phone":"+34 932 37 42 00",
    "sg:postcode":"08008",
    "sg:province":"Barcelona",
    "wof:name":"Pique Country Bridge Club",
    "wof:placetype":"venue"
},
  "geometry": {"coordinates":[2.1580340862,41.3953704834],"type":"Point"}
}