{
  "type": "Feature",
  "properties": {
    "iso:country":"ES",
    "sg:address":"Avda Condesa Sagasta, 10",
    "sg:city":"Le\u00f3n",
    "sg:orig_category":"Asesor\u00cda Fiscal Y Jur\u00cddica",
    "sg:phone":"+34 987 22 56 38",
    "sg:postcode":"24001",
    "sg:province":"Le\u00f3n",
    "wof:name":"Condesa 10 Asesores S.l.",
    "wof:placetype":"venue"
},
  "geometry": {"coordinates":[-5.5790891647,42.5979499817],"type":"Point"}
}