{
  "type": "Feature",
  "properties": {
    "iso:country":"ES",
    "sg:address":"Calle de Socuellamos, S/n",
    "sg:city":"Tomelloso",
    "sg:orig_category":"Cintas Transportadoras",
    "sg:phone":"+34 926 50 11 61",
    "sg:postcode":"13700",
    "sg:province":"Ciudad Real",
    "wof:name":"Industrias Mecanicas Medioambientales S.l.",
    "wof:placetype":"venue"
},
  "geometry": {"coordinates":[-3.0140640736,39.1666069031],"type":"Point"}
}