{
  "type": "Feature",
  "properties": {
    "iso:country":"ES",
    "sg:address":"Calle de Projecte 32 - Poligono Industrial, S/n",
    "sg:city":"Catarroja",
    "sg:orig_category":"Molduras, Junquillos, Listones Y Molduras Perforadas",
    "sg:phone":"+34 961 26 61 86",
    "sg:postcode":"46470",
    "sg:province":"Valencia",
    "wof:name":"Resta Mozo Julian",
    "wof:placetype":"venue"
},
  "geometry": {"coordinates":[-0.4032689929,39.4032859802],"type":"Point"}
}