{
  "type": "Feature",
  "properties": {
    "iso:country":"ES",
    "sg:address":"Plaz Escorial, 3",
    "sg:city":"Majadahonda",
    "sg:orig_category":"Soportes L\u00d3gicos, Programas Integradores De Aplicaciones (progiciels)",
    "sg:phone":"+34 916 38 11 24",
    "sg:postcode":"28220",
    "sg:province":"Madrid",
    "wof:name":"Cedomibe S.l.",
    "wof:placetype":"venue"
},
  "geometry": {"coordinates":[-3.8758111,40.4730987549],"type":"Point"}
}