{
  "type": "Feature",
  "properties": {
    "addr:full":"Calle de Teodoro Camino, 6 Albacete Albacete 02002",
    "addr:housenumber":"6",
    "addr:postcode":"02002",
    "addr:street":"Calle De Teodoro Camino",
    "iso:country":"ES",
    "sg:address":"Calle de Teodoro Camino, 6",
    "sg:city":"Albacete",
    "sg:orig_category":"Fabricaci\u00d3n, Venta De Cuadros, Accesorios Para Enmarcar",
    "sg:phone":"+34 967 24 32 89",
    "sg:postcode":"02002",
    "sg:province":"Albacete",
    "wof:name":"Perona Martinez Mercedes",
    "wof:placetype":"venue"
},
  "geometry": {"coordinates":[-1.8547790051,38.9922103882],"type":"Point"}
}