{
  "type": "Feature",
  "properties": {
    "addr:full":"Calle de Eras (las), 9 Azuqueca Henares Guadalajara 19200",
    "addr:housenumber":"9",
    "addr:postcode":"19200",
    "addr:street":"Calle De Eras Las",
    "iso:country":"ES",
    "sg:address":"Calle de Eras (las), 9",
    "sg:city":"Azuqueca Henares",
    "sg:orig_category":"Venta, Alquiler De Instrumentos Y Accesorios De M\u00dasica",
    "sg:phone":"+34 949 26 33 56",
    "sg:postcode":"19200",
    "sg:province":"Guadalajara",
    "wof:name":"Proyectos De Comercio Musicalia S.l.",
    "wof:placetype":"venue"
},
  "geometry": {"coordinates":[-3.2634088993,40.5692863464],"type":"Point"}
}