{
  "type": "Feature",
  "properties": {
    "iso:country":"ES",
    "sg:address":"Calle de Real, 67",
    "sg:city":"Coru\u00d1a",
    "sg:orig_category":"Pod\u00d3logos: Pedicuros",
    "sg:phone":"+34 981 22 49 69",
    "sg:postcode":"15003",
    "sg:province":"La Coru\u00f1a",
    "wof:name":"Rey Carballal Sergio",
    "wof:placetype":"venue"
},
  "geometry": {"coordinates":[-8.4012022018,43.3692779541],"type":"Point"}
}