{
  "type": "Feature",
  "properties": {
    "iso:country":"ES",
    "sg:address":"Calle de Perez Casas, 32",
    "sg:city":"San Jose",
    "sg:orig_category":"Platos Preparados Refrigerados (fabricaci\u00d3n, Al Por Mayor)",
    "sg:phone":"+34 968 47 36 60",
    "sg:postcode":"30800",
    "sg:province":"Murcia",
    "wof:name":"Munuera Abellaneda Antonia",
    "wof:placetype":"venue"
},
  "geometry": {"coordinates":[-1.6905640364,37.680557251],"type":"Point"}
}