{
  "type": "Feature",
  "properties": {
    "iso:country":"ES",
    "sg:address":"Calle de Demostenes, S/n",
    "sg:city":"Malaga",
    "sg:orig_category":"Empresarios",
    "sg:phone":"+34 952 06 84 33",
    "sg:postcode":"29010",
    "sg:province":"M\u00e1laga",
    "wof:name":"Fundacion Imabis",
    "wof:placetype":"venue"
},
  "geometry": {"coordinates":[-4.4760389328,36.7189331055],"type":"Point"}
}