{
  "type": "Feature",
  "properties": {
    "addr:full":"Calle de Gran Via, 58 Madrid Madrid 28013",
    "addr:housenumber":"58",
    "addr:postcode":"madrid;28013",
    "addr:street":"Calle De Gran Via",
    "iso:country":"ES",
    "sg:address":"Calle de Gran Via, 58",
    "sg:city":"Madrid",
    "sg:orig_category":"Zapatos (al Por Menor)",
    "sg:phone":"+34 915 48 79 06",
    "sg:postcode":"28013",
    "sg:province":"Madrid",
    "sg:website":"www.carminashoemker.com",
    "wof:name":"Alta Zapateria Balear S.l.",
    "wof:placetype":"venue"
},
  "geometry": {"coordinates":[-3.7080700397,40.4216079712],"type":"Point"}
}