{
  "type": "Feature",
  "properties": {
    "addr:full":"Estafeta, 68 Iru\u00f1a Navarra 31001",
    "addr:housenumber":"68",
    "addr:postcode":"31001",
    "addr:street":"Estafeta",
    "iso:country":"ES",
    "sg:address":"Estafeta, 68",
    "sg:city":"Iru\u00f1a",
    "sg:orig_category":"Ropa Para Se\u00d1oras (al Por Menor)",
    "sg:phone":"+34 948 22 68 73",
    "sg:postcode":"31001",
    "sg:province":"Navarra",
    "wof:name":"Echeverria Jimenez Modesto Jose",
    "wof:placetype":"venue"
},
  "geometry": {"coordinates":[-1.6414790154,42.8168296814],"type":"Point"}
}