{
  "type": "Feature",
  "properties": {
    "addr:full":"Pase Campo Volantin, 2 Bilbao Vizcaya 48007",
    "addr:housenumber":"2",
    "addr:postcode":"48007",
    "addr:street":"Volantin",
    "iso:country":"ES",
    "sg:address":"Pase Campo Volantin, 2",
    "sg:city":"Bilbao",
    "sg:orig_category":"Inmobiliaria (agencias)",
    "sg:phone":"+34 944 13 20 19",
    "sg:postcode":"48007",
    "sg:province":"Vizcaya",
    "wof:name":"Cifuentes Y Tomas Consultores S.l.",
    "wof:placetype":"venue"
},
  "geometry": {"coordinates":[-2.9241609573,43.2644348145],"type":"Point"}
}