{
  "type": "Feature",
  "properties": {
    "addr:full":"Calle de Abedules, 130 Haro La Rioja 26200",
    "addr:housenumber":"130",
    "addr:postcode":"26200",
    "addr:street":"Calle De Abedules",
    "iso:country":"ES",
    "sg:address":"Calle de Abedules, 130",
    "sg:city":"Haro",
    "sg:orig_category":"Bebidas",
    "sg:phone":"+34 941 31 07 27",
    "sg:postcode":"26200",
    "sg:province":"La Rioja",
    "wof:name":"Gon-cruz S. L.",
    "wof:placetype":"venue"
},
  "geometry": {"coordinates":[-2.835236311,42.557964325],"type":"Point"}
}