{
  "type": "Feature",
  "properties": {
    "addr:full":"Carrer de Joaquim Blume, 1 Santa Maria De Palautordera Barcelona 08460",
    "addr:housenumber":"1",
    "addr:postcode":"08460",
    "addr:street":"Carrer De Joaquim Blume",
    "iso:country":"ES",
    "sg:address":"Carrer de Joaquim Blume, 1",
    "sg:city":"Santa Maria De Palautordera",
    "sg:orig_category":"Art\u00cdculos De Decoraci\u00d3n (fabricaci\u00d3n Y Al Por Mayor)",
    "sg:phone":"+34 938 48 16 60",
    "sg:postcode":"08460",
    "sg:province":"Barcelona",
    "wof:name":"Venilia S.a.",
    "wof:placetype":"venue"
},
  "geometry": {"coordinates":[-97.78224945069999,45.7040786743],"type":"Point"}
}