{
  "type": "Feature",
  "properties": {
    "addr:full":"Calle de Nueva, 2 Alcorcon Madrid 28921",
    "addr:housenumber":"2",
    "addr:postcode":"28921",
    "addr:street":"Calle De Nueva",
    "iso:country":"ES",
    "sg:address":"Calle de Nueva, 2",
    "sg:city":"Alcorcon",
    "sg:orig_category":"Caf\u00c9s (al Por Menor)",
    "sg:phone":"+34 916 44 15 47",
    "sg:postcode":"28921",
    "sg:province":"Madrid",
    "wof:name":"Exclusivas De Proyectos Inmobiliarios Sl",
    "wof:placetype":"venue"
},
  "geometry": {"coordinates":[-3.8274641037,40.3476867676],"type":"Point"}
}