{
  "type": "Feature",
  "properties": {
    "addr:full":"Ctra Valverde, Km. 0210,0 Beas Huelva 21630",
    "addr:postcode":"21630",
    "addr:street":"Ctra Valverde Km. 0210,0;Huelva",
    "iso:country":"ES",
    "sg:address":"Ctra Valverde, Km. 0210,0",
    "sg:city":"Beas",
    "sg:orig_category":"Distribuci\u00d3n De Petr\u00d3leo Y Derivados",
    "sg:phone":"+34 959 30 89 21",
    "sg:postcode":"21630",
    "sg:province":"Huelva",
    "wof:name":"Estacion De Servicio Los Pinos De Valverde S.l.",
    "wof:placetype":"venue"
},
  "geometry": {"coordinates":[-6.7933588028,37.4260787964],"type":"Point"}
}