{
  "type": "Feature",
  "properties": {
    "iso:country":"ES",
    "sg:address":"Calle de Asturias, 7",
    "sg:city":"Valencia",
    "sg:orig_category":"Empresas De Limpieza",
    "sg:phone":"+34 963 37 53 70",
    "sg:postcode":"46023",
    "sg:province":"Valencia",
    "wof:name":"Voraser S.l",
    "wof:placetype":"venue"
},
  "geometry": {"coordinates":[-0.3564757109,39.4654769897],"type":"Point"}
}