{
  "type": "Feature",
  "properties": {
    "addr:full":"Carrer de Riera Baste, 2 S. Boi Llobregat Barcelona 08830",
    "addr:housenumber":"2",
    "addr:postcode":"08830",
    "addr:street":"Carrer De Riera Baste",
    "iso:country":"ES",
    "sg:address":"Carrer de Riera Baste, 2",
    "sg:city":"S. Boi Llobregat",
    "sg:orig_category":"Abogados Especialistas En Derecho Penal",
    "sg:phone":"+34 936 30 43 69",
    "sg:postcode":"08830",
    "sg:province":"Barcelona",
    "wof:name":"Ferrer Rubio Olga",
    "wof:placetype":"venue"
},
  "geometry": {"coordinates":[2.0369160175,41.3476333618],"type":"Point"}
}