{
  "type": "Feature",
  "properties": {
    "addr:full":"Calle de Alcalde Manuel Alberola, 32 Novelda Alicante 03660",
    "addr:housenumber":"32",
    "addr:postcode":"03660",
    "addr:street":"Calle De Alcalde Manuel Alberola",
    "iso:country":"ES",
    "sg:address":"Calle de Alcalde Manuel Alberola, 32",
    "sg:city":"Novelda",
    "sg:orig_category":"Abogados",
    "sg:phone":"+34 965 60 47 98",
    "sg:postcode":"03660",
    "sg:province":"Alicante",
    "wof:name":"Ortiz Lopez Maria Isabel",
    "wof:placetype":"venue"
},
  "geometry": {"coordinates":[-0.7642344832,38.3827285767],"type":"Point"}
}