{
  "type": "Feature",
  "properties": {
    "addr:full":"Carrer de Guillem Tell, 16 Barcelona Barcelona 08006",
    "addr:housenumber":"16",
    "addr:postcode":"08006",
    "addr:street":"Carrer De Guillem Tell",
    "iso:country":"ES",
    "sg:address":"Carrer de Guillem Tell, 16",
    "sg:city":"Barcelona",
    "sg:orig_category":"Cajas De Ahorro",
    "sg:phone":"+34 932 17 96 10",
    "sg:postcode":"08006",
    "sg:province":"Barcelona",
    "wof:name":"Caixa D'estalvis Del Penedes",
    "wof:placetype":"venue"
},
  "geometry": {"coordinates":[2.1489479542,41.402923584],"type":"Point"}
}