{
  "type": "Feature",
  "properties": {
    "addr:full":"Ct Toledo Albacete, Km. 0131,5 Tomelloso Ciudad Real 13700",
    "addr:postcode":"13700",
    "addr:street":"Ct;0131,5",
    "iso:country":"ES",
    "sg:address":"Ct Toledo Albacete, Km. 0131,5",
    "sg:city":"Tomelloso",
    "sg:orig_category":"\u00c1rboles Frutales",
    "sg:phone":"+34 926 53 80 67",
    "sg:postcode":"13700",
    "sg:province":"Ciudad Real",
    "sg:website":"www.pellenc.com",
    "wof:name":"Pellenc Iberica S.l.",
    "wof:placetype":"venue"
},
  "geometry": {"coordinates":[-3.0027339458,39.1652755737],"type":"Point"}
}