{
  "type": "Feature",
  "properties": {
    "iso:country":"ES",
    "sg:address":"Camp Ibaizabal, 6",
    "sg:city":"Bilbao",
    "sg:orig_category":"M\u00c9dicos: Estomatolog\u00cda",
    "sg:phone":"+34 944 15 22 38",
    "sg:postcode":"48003",
    "sg:province":"Vizcaya",
    "wof:name":"Lopez Ibarra Ignacio",
    "wof:placetype":"venue"
},
  "geometry": {"coordinates":[-2.925702095,43.2430267334],"type":"Point"}
}