{
  "type": "Feature",
  "properties": {
    "iso:country":"ES",
    "sg:address":"Calle de Julio Rodriguez Yordi, 2",
    "sg:city":"Coru\u00d1a",
    "sg:orig_category":"Herboristas (al Por Menor)",
    "sg:phone":"+34 981 26 17 37",
    "sg:postcode":"15011",
    "sg:province":"La Coru\u00f1a",
    "wof:name":"Rodriguez Prieto Ana Belen",
    "wof:placetype":"venue"
},
  "geometry": {"coordinates":[-8.4175319672,43.370300293],"type":"Point"}
}