{
  "type": "Feature",
  "properties": {
    "addr:full":"Pase Gigantes Y Cabezudos, 42 Madrid Madrid 28041",
    "addr:housenumber":"42",
    "addr:postcode":"madrid;28041",
    "addr:street":"Gigantes Y Cabezudos",
    "iso:country":"ES",
    "sg:address":"Pase Gigantes Y Cabezudos, 42",
    "sg:city":"Madrid",
    "sg:orig_category":"Centros Empresariales",
    "sg:phone":"+34 917 95 46 26",
    "sg:postcode":"28041",
    "sg:province":"Madrid",
    "wof:name":"Sanchez Sanchez Antonio",
    "wof:placetype":"venue"
},
  "geometry": {"coordinates":[-3.6937580109,40.3557624817],"type":"Point"}
}