{
  "type": "Feature",
  "properties": {
    "addr:full":"Calle de Tres Morillas, 10 Jaen Ja\u00e9n 23001",
    "addr:housenumber":"10;jae\u0301n",
    "addr:postcode":"23001",
    "addr:street":"Calle De Tres Morillas",
    "iso:country":"ES",
    "sg:address":"Calle de Tres Morillas, 10",
    "sg:city":"Jaen",
    "sg:orig_category":"Agencias Y Agentes Comerciales, Representantes",
    "sg:phone":"+34 953 26 51 56",
    "sg:postcode":"23001",
    "sg:province":"Ja\u00e9n",
    "wof:name":"J.h.cabinser S.l",
    "wof:placetype":"venue"
},
  "geometry": {"coordinates":[-3.7844619751,37.7703132629],"type":"Point"}
}