{
  "type": "Feature",
  "properties": {
    "iso:country":"ES",
    "sg:address":"Carrer de Pedrera, 2",
    "sg:city":"Riba-roja D'ebre",
    "sg:orig_category":"Centros Empresariales",
    "sg:phone":"+34 977 41 63 97",
    "sg:postcode":"43790",
    "sg:province":"Tarragona",
    "wof:name":"Rodrigo Garcia Viso Juliana",
    "wof:placetype":"venue"
},
  "geometry": {"coordinates":[1.252884984,41.111492157],"type":"Point"}
}