{
  "type": "Feature",
  "properties": {
    "addr:full":"Calle de Mayor, 37 Mislata Valencia 46920",
    "addr:housenumber":"37",
    "addr:postcode":"46920",
    "addr:street":"Calle De Mayor",
    "iso:country":"ES",
    "sg:address":"Calle de Mayor, 37",
    "sg:city":"Mislata",
    "sg:orig_category":"Loter\u00cda Y T\u00d3mbola",
    "sg:phone":"+34 963 79 57 24",
    "sg:postcode":"46920",
    "sg:province":"Valencia",
    "wof:name":"Ballester Monzo Antonio",
    "wof:placetype":"venue"
},
  "geometry": {"coordinates":[-0.4154349864,39.4741668701],"type":"Point"}
}