{
  "type": "Feature",
  "properties": {
    "iso:country":"ES",
    "sg:address":"Calle de Alminar, 22",
    "sg:city":"Alhaurin Torre",
    "sg:orig_category":"Agencias Y Agentes Comerciales, Representantes",
    "sg:phone":"+34 952 41 64 47",
    "sg:postcode":"29130",
    "sg:province":"M\u00e1laga",
    "wof:name":"Subires Batanas Antonia Maria",
    "wof:placetype":"venue"
},
  "geometry": {"coordinates":[-4.5538787842,36.6631393433],"type":"Point"}
}