{
  "type": "Feature",
  "properties": {
    "iso:country":"ES",
    "sg:address":"Calle de Industrias, 6",
    "sg:city":"Repilado",
    "sg:orig_category":"Sales (al Por Mayor)",
    "sg:phone":"+34 959 12 27 12",
    "sg:postcode":"21360",
    "sg:province":"Huelva",
    "wof:name":"Comercial Jabu S.l.",
    "wof:placetype":"venue"
},
  "geometry": {"coordinates":[-6.7728738785,37.9260597229],"type":"Point"}
}