{
  "type": "Feature",
  "properties": {
    "iso:country":"ES",
    "sg:address":"Calle de Iglesia (la), 9",
    "sg:city":"Navarres",
    "sg:orig_category":"Bisuter\u00cda, Joyer\u00cda, Relojer\u00cda (al Por Menor)",
    "sg:phone":"+34 962 26 63 85",
    "sg:postcode":"46823",
    "sg:province":"Valencia",
    "wof:name":"Joyeria Hermanos Vila S.coop.v.",
    "wof:placetype":"venue"
},
  "geometry": {"coordinates":[-0.6938440204,39.1009559631],"type":"Point"}
}