{
  "type": "Feature",
  "properties": {
    "iso:country":"ES",
    "sg:address":"Avda Menendez Pelayo, 33",
    "sg:city":"Sevilla",
    "sg:orig_category":"Abogados",
    "sg:phone":"+34 954 41 34 89",
    "sg:postcode":"41003",
    "sg:province":"Sevilla",
    "wof:name":"Astola Carretero Julia",
    "wof:placetype":"venue"
},
  "geometry": {"coordinates":[-5.9851784706,37.3874588013],"type":"Point"}
}