{
  "type": "Feature",
  "properties": {
    "addr:full":"Pg Europa, 10 Poblenou Barcelona 08397",
    "addr:housenumber":"10",
    "addr:postcode":"08397",
    "addr:street":"Pg Europa",
    "iso:country":"ES",
    "sg:address":"Pg Europa, 10",
    "sg:city":"Poblenou",
    "sg:orig_category":"Empresas De Limpieza",
    "sg:phone":"+34 937 66 14 92",
    "sg:postcode":"08397",
    "sg:province":"Barcelona",
    "wof:name":"Serveis Galafat S.l.",
    "wof:placetype":"venue"
},
  "geometry": {"coordinates":[2.6717998981,41.6182403564],"type":"Point"}
}