{
  "type": "Feature",
  "properties": {
    "addr:full":"Av. Constitucion, 52 La Solana Ciudad Real 13240",
    "addr:housenumber":"52",
    "addr:postcode":"13240",
    "addr:street":"Av. Constitucion;La",
    "iso:country":"ES",
    "sg:address":"Av. Constitucion, 52",
    "sg:city":"La Solana",
    "sg:orig_category":"Mec\u00c1nico Del Autom\u00d3vil",
    "sg:phone":"+34 926 63 18 16",
    "sg:postcode":"13240",
    "sg:province":"Ciudad Real",
    "wof:name":"Talleres Los Peracos S.l.",
    "wof:placetype":"venue"
},
  "geometry": {"coordinates":[-3.2348649502,38.9376220703],"type":"Point"}
}