{
  "type": "Feature",
  "properties": {
    "iso:country":"ES",
    "sg:address":"Carrer de Japo, 36",
    "sg:city":"Barcelona",
    "sg:orig_category":"Mantenimiento Y Reparaci\u00d3n De Motores Industriales",
    "sg:phone":"+34 932 76 31 98",
    "sg:postcode":"08016",
    "sg:province":"Barcelona",
    "wof:name":"Rectificats Cora S.c.p.",
    "wof:placetype":"venue"
},
  "geometry": {"coordinates":[2.1783690453,41.4413490295],"type":"Point"}
}