{
  "type": "Feature",
  "properties": {
    "iso:country":"ES",
    "sg:address":"Calle de Mata (la), 1",
    "sg:city":"Oca\u00f1a",
    "sg:orig_category":"Alimentaci\u00d3n General (al Por Menor)",
    "sg:phone":"+34 925 13 03 59",
    "sg:postcode":"45300",
    "sg:province":"Toledo",
    "wof:name":"Calero Aganzo Marcial",
    "wof:placetype":"venue"
},
  "geometry": {"coordinates":[-3.5007588863,39.9562797546],"type":"Point"}
}