{
  "type": "Feature",
  "properties": {
    "addr:full":"Carrer de Navas De Tolosa, 270 Barcelona Barcelona 08027",
    "addr:housenumber":"270",
    "addr:postcode":"08027",
    "addr:street":"Carrer De Navas De Tolosa",
    "iso:country":"ES",
    "sg:address":"Carrer de Navas De Tolosa, 270",
    "sg:city":"Barcelona",
    "sg:orig_category":"Ingenier\u00cda, Centros De Estudios (diversos)",
    "sg:phone":"+34 933 52 54 07",
    "sg:postcode":"08027",
    "sg:province":"Barcelona",
    "sg:website":"www.btbsl.com",
    "wof:name":"B.t.b. Enginyeria Electronica Industrial S. L.",
    "wof:placetype":"venue"
},
  "geometry": {"coordinates":[2.1878778934,41.4147796631],"type":"Point"}
}