{
  "type": "Feature",
  "properties": {
    "iso:country":"ES",
    "sg:address":"Carr Major, 10",
    "sg:city":"Vielha",
    "sg:orig_category":"Lencer\u00cda Femenina, Corseter\u00cda, Trajes De Ba\u00d1o (al Por Menor)",
    "sg:phone":"+34 973 64 22 11",
    "sg:postcode":"25530",
    "sg:province":"Lleida",
    "wof:name":"Vidal Vidal Pablo",
    "wof:placetype":"venue"
},
  "geometry": {"coordinates":[0.7948769927,42.7014732361],"type":"Point"}
}