{
  "type": "Feature",
  "properties": {
    "iso:country":"ES",
    "sg:address":"Calle de Marques De Teverga, 3",
    "sg:city":"Oviedo",
    "sg:orig_category":"M\u00c9dicos: Neurolog\u00cda",
    "sg:phone":"+34 985 25 77 77",
    "sg:postcode":"33005",
    "sg:province":"Asturias",
    "wof:name":"Menendez Guisasola Luis",
    "wof:placetype":"venue"
},
  "geometry": {"coordinates":[-5.8553023338,43.3622016907],"type":"Point"}
}