{
  "type": "Feature",
  "properties": {
    "iso:country":"ES",
    "sg:address":"Calle de Mayor, 135",
    "sg:city":"Union",
    "sg:orig_category":"Ropa Para Se\u00d1oras (al Por Menor)",
    "sg:phone":"+34 968 54 04 39",
    "sg:postcode":"30360",
    "sg:province":"Murcia",
    "wof:name":"Perez Ayala Jose Angel",
    "wof:placetype":"venue"
},
  "geometry": {"coordinates":[-0.8742190003,37.6175384521],"type":"Point"}
}