{
  "type": "Feature",
  "properties": {
    "addr:full":"Amarilla Golf, S/n Amarilla Golf Santa Cruz De Tenerife 38639",
    "addr:housenumber":"/ n",
    "addr:postcode":"38639",
    "addr:street":"Golf",
    "iso:country":"ES",
    "sg:address":"Amarilla Golf, S/n",
    "sg:city":"Amarilla Golf",
    "sg:orig_category":"Inmobiliaria (agencias)",
    "sg:phone":"+34 922 73 87 85",
    "sg:postcode":"38639",
    "sg:province":"Santa Cruz De Tenerife",
    "wof:name":"Nesurten S.l.",
    "wof:placetype":"venue"
},
  "geometry": {"coordinates":[-16.6106243134,28.0266799927],"type":"Point"}
}