{
  "type": "Feature",
  "properties": {
    "addr:full":"Calle de Doctor Lopez, 1 Alfambra Teruel 44160",
    "addr:housenumber":"1",
    "addr:postcode":"44160",
    "addr:street":"Calle De Doctor Lopez",
    "iso:country":"ES",
    "sg:address":"Calle de Doctor Lopez, 1",
    "sg:city":"Alfambra",
    "sg:orig_category":"Centros De Educaci\u00d3n Especial",
    "sg:phone":"+34 978 77 03 87",
    "sg:postcode":"44160",
    "sg:province":"Teruel",
    "wof:name":"Colegio Publico De E.g.b",
    "wof:placetype":"venue"
},
  "geometry": {"coordinates":[-1.031883955,40.5464057922],"type":"Point"}
}