{
  "type": "Feature",
  "properties": {
    "addr:full":"Calle de Blanco, 12 Puerto Cruz Santa Cruz De Tenerife 38400",
    "addr:housenumber":"12",
    "addr:postcode":"38400",
    "addr:street":"Calle De Blanco;Puerto Cruz",
    "iso:country":"ES",
    "sg:address":"Calle de Blanco, 12",
    "sg:city":"Puerto Cruz",
    "sg:orig_category":"Pizzer\u00cdas",
    "sg:phone":"+34 922 38 26 05",
    "sg:postcode":"38400",
    "sg:province":"Santa Cruz De Tenerife",
    "wof:name":"Vega Garcia Domingo",
    "wof:placetype":"venue"
},
  "geometry": {"coordinates":[-16.5504665375,28.415189743],"type":"Point"}
}