{
  "type": "Feature",
  "properties": {
    "iso:country":"ES",
    "sg:address":"Calle de Gamonal, 53",
    "sg:city":"Madrid",
    "sg:orig_category":"Transportes Por Carretera: Lotes Completos, Mercanc\u00cdas Diversas",
    "sg:phone":"+34 913 80 01 30",
    "sg:postcode":"28031",
    "sg:province":"Madrid",
    "wof:name":"Tornero Gascue\u00f1a Gregorio",
    "wof:placetype":"venue"
},
  "geometry": {"coordinates":[-3.6404647827,40.3736534119],"type":"Point"}
}