{
  "type": "Feature",
  "properties": {
    "addr:full":"Cra. Nacional Ii, Km. 0639,5 Vilassar Barcelona 08340",
    "addr:postcode":"08340",
    "addr:street":"Km. 0639,5 Vilassar Barcelona",
    "iso:country":"ES",
    "sg:address":"Cra. Nacional Ii, Km. 0639,5",
    "sg:city":"Vilassar",
    "sg:orig_category":"Granos Y Semillas (producci\u00d3n, Al Por Mayor)",
    "sg:phone":"+34 937 50 62 94",
    "sg:postcode":"08340",
    "sg:province":"Barcelona",
    "sg:website":"www.semarsl.es",
    "wof:name":"Semillas Semar S.l.",
    "wof:placetype":"venue"
},
  "geometry": {"coordinates":[2.3907299042,41.5019264221],"type":"Point"}
}