{
  "type": "Feature",
  "properties": {
    "iso:country":"ES",
    "sg:address":"Avda Reino (del), 16",
    "sg:city":"Beniel",
    "sg:orig_category":"Alquiler De V\u00cddeo",
    "sg:phone":"+34 968 60 26 72",
    "sg:postcode":"30130",
    "sg:province":"Murcia",
    "wof:name":"Andreu Lorente Amparo",
    "wof:placetype":"venue"
},
  "geometry": {"coordinates":[-1.0001305342,38.046962738],"type":"Point"}
}