{
  "type": "Feature",
  "properties": {
    "iso:country":"ES",
    "sg:address":"Calle de Escorredor, L', 46",
    "sg:city":"Burriana",
    "sg:orig_category":"Inmobiliaria (agencias)",
    "sg:phone":"+34 964 57 02 65",
    "sg:postcode":"12530",
    "sg:province":"Castell\u00f3n",
    "wof:name":"Monfort Y Piquer S.l.",
    "wof:placetype":"venue"
},
  "geometry": {"coordinates":[-0.0847131014,39.8876876831],"type":"Point"}
}