{
  "type": "Feature",
  "properties": {
    "addr:full":"Pol Ind Nevero, S/n Badajoz Badajoz 06006",
    "addr:housenumber":"s",
    "addr:postcode":"06006",
    "addr:street":"/ N",
    "iso:country":"ES",
    "sg:address":"Pol Ind Nevero, S/n",
    "sg:city":"Badajoz",
    "sg:orig_category":"Contenedores Para Transporte De Mercanc\u00cdas",
    "sg:phone":"+34 924 26 22 24",
    "sg:postcode":"06006",
    "sg:province":"Badajoz",
    "wof:name":"Contenedores De Badajoz S.l.",
    "wof:placetype":"venue"
},
  "geometry": {"coordinates":[-7.0317192078,38.9165992737],"type":"Point"}
}