{
  "type": "Feature",
  "properties": {
    "iso:country":"ES",
    "sg:address":"Carr Isaac Peral, 56",
    "sg:city":"Port D'andratx",
    "sg:orig_category":"Muebles, Minoristas",
    "sg:phone":"+34 971 67 22 58",
    "sg:postcode":"07157",
    "sg:province":"Islas Baleares",
    "wof:name":"Scheepers  Dorothee",
    "wof:placetype":"venue"
},
  "geometry": {"coordinates":[2.388395071,39.543674469],"type":"Point"}
}