{
  "type": "Feature",
  "properties": {
    "iso:country":"ES",
    "sg:address":"Calle de Hermanos Lumiere, 4",
    "sg:city":"Getafe",
    "sg:orig_category":"Agentes, Concesionarios Y Sucursales De Camiones Y Veh\u00cdculos Industriales",
    "sg:phone":"+34 916 82 98 49",
    "sg:postcode":"28906",
    "sg:province":"Madrid",
    "wof:name":"Almacenes Calmera S. A.",
    "wof:placetype":"venue"
},
  "geometry": {"coordinates":[-3.6927742958,40.300491333],"type":"Point"}
}