{
  "type": "Feature",
  "properties": {
    "addr:full":"Carrer de Llobregos, 126 Barcelona Barcelona 08032",
    "addr:housenumber":"126",
    "addr:postcode":"08032",
    "addr:street":"Carrer De Llobregos",
    "iso:country":"ES",
    "sg:address":"Carrer de Llobregos, 126",
    "sg:city":"Barcelona",
    "sg:orig_category":"Cajas De Ahorro",
    "sg:phone":"+34 934 07 40 98",
    "sg:postcode":"08032",
    "sg:province":"Barcelona",
    "wof:name":"Caja De Ahorros De Valencia Castellon Y Alicante",
    "wof:placetype":"venue"
},
  "geometry": {"coordinates":[2.1558439732,41.4243354797],"type":"Point"}
}