{
  "type": "Feature",
  "properties": {
    "iso:country":"ES",
    "sg:address":"G.v. Corts Catalanes, 453",
    "sg:city":"Barcelona",
    "sg:orig_category":"M\u00c9dicos: Estomatolog\u00cda",
    "sg:phone":"+34 934 23 27 32",
    "sg:postcode":"08015",
    "sg:province":"Barcelona",
    "wof:name":"Barrachina Perez Jose",
    "wof:placetype":"venue"
},
  "geometry": {"coordinates":[2.1541059017,41.3792152405],"type":"Point"}
}