{
  "type": "Feature",
  "properties": {
    "addr:full":"Calle de Borujas, 15 Moron Frontera Sevilla 41530",
    "addr:housenumber":"15",
    "addr:postcode":"41530",
    "addr:street":"Calle De Borujas",
    "iso:country":"ES",
    "sg:address":"Calle de Borujas, 15",
    "sg:city":"Moron Frontera",
    "sg:orig_category":"Electricidad: Instaladores",
    "sg:phone":"+34 954 85 00 23",
    "sg:postcode":"41530",
    "sg:province":"Sevilla",
    "wof:name":"Ramirez Estudillo Juan Jose",
    "wof:placetype":"venue"
},
  "geometry": {"coordinates":[-5.445168972,37.1280784607],"type":"Point"}
}