{
  "type": "Feature",
  "properties": {
    "iso:country":"ES",
    "sg:address":"Calle de Padre Damian, 46",
    "sg:city":"Madrid",
    "sg:orig_category":"Urbanistas",
    "sg:phone":"+34 913 45 31 89",
    "sg:postcode":"28036",
    "sg:province":"Madrid",
    "wof:name":"Agosti Sanchez Luis",
    "wof:placetype":"venue"
},
  "geometry": {"coordinates":[-3.6854143143,40.4601364136],"type":"Point"}
}