{
  "type": "Feature",
  "properties": {
    "iso:country":"ES",
    "sg:address":"H (p I Llanos Del Valle), S/n",
    "sg:city":"Jaen",
    "sg:orig_category":"Fabricaci\u00d3n De Mobiliario Met\u00c1lico",
    "sg:phone":"+34 953 24 15 61",
    "sg:postcode":"23009",
    "sg:province":"Ja\u00e9n",
    "wof:name":"Melco S.l.",
    "wof:placetype":"venue"
},
  "geometry": {"coordinates":[-3.7232005596,37.8562049866],"type":"Point"}
}