{
  "type": "Feature",
  "properties": {
    "addr:full":"Calle de Molino, 7 Gallardos Almer\u00eda 04280",
    "addr:housenumber":"7",
    "addr:postcode":"04280",
    "addr:street":"Calle De Molino;Almeri\u0301A",
    "iso:country":"ES",
    "sg:address":"Calle de Molino, 7",
    "sg:city":"Gallardos",
    "sg:orig_category":"Fabricaci\u00d3n De Muebles De Cocina",
    "sg:phone":"+34 950 46 94 20",
    "sg:postcode":"04280",
    "sg:province":"Almer\u00eda",
    "wof:name":"Ruiz Navarro Martin",
    "wof:placetype":"venue"
},
  "geometry": {"coordinates":[-1.9398449659,37.1676063538],"type":"Point"}
}