{
  "type": "Feature",
  "properties": {
    "iso:country":"ES",
    "sg:address":"Cust Palloza, 1",
    "sg:city":"Coru\u00d1a",
    "sg:orig_category":"Cer\u00c1micas: Material Y Suministros",
    "sg:phone":"+34 981 29 86 33",
    "sg:postcode":"15006",
    "sg:province":"La Coru\u00f1a",
    "wof:name":"Espacio S.a.",
    "wof:placetype":"venue"
},
  "geometry": {"coordinates":[-8.403424263,43.3584136963],"type":"Point"}
}