{
  "type": "Feature",
  "properties": {
    "addr:full":"Calle de Maria Guerrero, 15 Almeria Almer\u00eda 04004",
    "addr:housenumber":"15",
    "addr:postcode":"04004",
    "addr:street":"Calle De Maria Guerrero",
    "iso:country":"ES",
    "sg:address":"Calle de Maria Guerrero, 15",
    "sg:city":"Almeria",
    "sg:orig_category":"Ingeniero",
    "sg:phone":"+34 950 24 46 72",
    "sg:postcode":"04004",
    "sg:province":"Almer\u00eda",
    "wof:name":"Eurogip Consultores S.l.",
    "wof:placetype":"venue"
},
  "geometry": {"coordinates":[-2.460848093,36.8433494568],"type":"Point"}
}