{
  "type": "Feature",
  "properties": {
    "iso:country":"ES",
    "sg:address":"Calle de Tembleque, 50",
    "sg:city":"Madrid",
    "sg:orig_category":"Mec\u00c1nico Del Autom\u00d3vil",
    "sg:phone":"+34 915 18 30 93",
    "sg:postcode":"28024",
    "sg:province":"Madrid",
    "wof:name":"Cantera San Martin Julio",
    "wof:placetype":"venue"
},
  "geometry": {"coordinates":[-3.7599179745,40.3955345154],"type":"Point"}
}