{
  "type": "Feature",
  "properties": {
    "iso:country":"ES",
    "sg:address":"Carretera De Gabia Grande, S/n",
    "sg:city":"Ogijares",
    "sg:orig_category":"Molduras, Junquillos, Listones Y Molduras Perforadas",
    "sg:phone":"+34 958 50 78 96",
    "sg:postcode":"18151",
    "sg:province":"Granada",
    "wof:name":"Alabarce Garcia Manuel",
    "wof:placetype":"venue"
},
  "geometry": {"coordinates":[-3.6264514923,37.1190490723],"type":"Point"}
}