{
  "type": "Feature",
  "properties": {
    "addr:full":"Calle de Callao, 2 Pe\u00e7arroya-pueblonuevo C\u00f3rdoba 14200",
    "addr:housenumber":"2",
    "addr:postcode":"14200",
    "addr:street":"Calle De Callao;Co\u0301Rdoba",
    "iso:country":"ES",
    "sg:address":"Calle de Callao, 2",
    "sg:city":"Pe\u00e7arroya-pueblonuevo",
    "sg:orig_category":"Molduras, Junquillos, Listones Y Molduras Perforadas",
    "sg:phone":"+34 957 56 19 01",
    "sg:postcode":"14200",
    "sg:province":"C\u00f3rdoba",
    "wof:name":"Gomez Calderon Manuel",
    "wof:placetype":"venue"
},
  "geometry": {"coordinates":[-4.7791519165,37.884727478],"type":"Point"}
}