{
  "type": "Feature",
  "properties": {
    "addr:full":"Calle de Padre Marin, 23 Logro\u00f1o La Rioja 26004",
    "addr:housenumber":"23",
    "addr:postcode":"26004",
    "addr:street":"Calle De Padre Marin;Rioja",
    "iso:country":"ES",
    "sg:address":"Calle de Padre Marin, 23",
    "sg:city":"Logro\u00f1o",
    "sg:orig_category":"Televisi\u00d3n, V\u00cddeo: Aparatos Y Accesorios (venta)",
    "sg:phone":"+34 941 23 42 47",
    "sg:postcode":"26004",
    "sg:province":"La Rioja",
    "wof:name":"Hernandez Martinez Juan Oscar",
    "wof:placetype":"venue"
},
  "geometry": {"coordinates":[-2.4304790497,42.4655838013],"type":"Point"}
}