{
  "type": "Feature",
  "properties": {
    "iso:country":"ES",
    "sg:address":"Ctra Alcantarilla, 94",
    "sg:city":"Nonduermas",
    "sg:orig_category":"Madera Para Construcci\u00d3n E Industria",
    "sg:phone":"+34 968 26 77 22",
    "sg:postcode":"30166",
    "sg:province":"Murcia",
    "sg:website":"www.abellanros.com",
    "wof:name":"Abellan Ros Jose",
    "wof:placetype":"venue"
},
  "geometry": {"coordinates":[-1.167277,37.97295],"type":"Point"}
}