{
  "type": "Feature",
  "properties": {
    "addr:full":"Calle de Don Quijote, 74 Cordoba C\u00f3rdoba 14014",
    "addr:housenumber":"74",
    "addr:postcode":"14014",
    "addr:street":"Calle De Don Quijote;Co\u0301Rdoba",
    "iso:country":"ES",
    "sg:address":"Calle de Don Quijote, 74",
    "sg:city":"Cordoba",
    "sg:orig_category":"Piedra Natural",
    "sg:phone":"+34 957 48 41 82",
    "sg:postcode":"14014",
    "sg:province":"C\u00f3rdoba",
    "wof:name":"Shinju Import S.l.",
    "wof:placetype":"venue"
},
  "geometry": {"coordinates":[-4.7553129196,37.8880157471],"type":"Point"}
}