{
  "type": "Feature",
  "properties": {
    "addr:full":"Ctra Mas Del Jutge, 51 P.i. Masia Del Juez Valencia 46900",
    "addr:housenumber":"51",
    "addr:postcode":"46900",
    "addr:street":"Ctra Mas Del Jutge;P.I. Masia Del Juez",
    "iso:country":"ES",
    "sg:address":"Ctra Mas Del Jutge, 51",
    "sg:city":"P.i. Masia Del Juez",
    "sg:orig_category":"Empresas De Carpinter\u00cda Met\u00c1lica",
    "sg:phone":"+34 961 55 43 08",
    "sg:postcode":"46900",
    "sg:province":"Valencia",
    "wof:name":"Talleres Sena S.l",
    "wof:placetype":"venue"
},
  "geometry": {"coordinates":[-0.4623290002,39.441619873],"type":"Point"}
}