{
  "type": "Feature",
  "properties": {
    "iso:country":"ES",
    "sg:address":"Carrer de Girona, 80",
    "sg:city":"Manlleu",
    "sg:orig_category":"Partidos Pol\u00cdticos",
    "sg:phone":"+34 938 50 61 37",
    "sg:postcode":"08560",
    "sg:province":"Barcelona",
    "wof:name":"Partit Dels Socialistes De Catalunya Psc-psoe",
    "wof:placetype":"venue"
},
  "geometry": {"coordinates":[2.2783970833,42.0037117004],"type":"Point"}
}