{
  "type": "Feature",
  "properties": {
    "iso:country":"ES",
    "sg:address":"Avda Madrid De, 22",
    "sg:city":"Donostia-san Sebastian",
    "sg:orig_category":"Carnicer\u00cdas, Carnicer\u00cdas",
    "sg:phone":"+34 943 45 25 24",
    "sg:postcode":"20011",
    "sg:province":"Guip\u00f9zcoa",
    "wof:name":"Delikatessen Isabel S.l.",
    "wof:placetype":"venue"
},
  "geometry": {"coordinates":[-1.9760420322,43.3035736084],"type":"Point"}
}