{
  "type": "Feature",
  "properties": {
    "addr:full":"Chayofa, 99 Chayofa Santa Cruz De Tenerife 38652",
    "addr:housenumber":"99",
    "addr:postcode":"38652",
    "addr:street":"Chayofa",
    "iso:country":"ES",
    "sg:address":"Chayofa, 99",
    "sg:city":"Chayofa",
    "sg:orig_category":"Alquiler De Veh\u00cdculos: Turismos Y Utilitarios",
    "sg:phone":"+34 922 72 91 26",
    "sg:postcode":"38652",
    "sg:province":"Santa Cruz De Tenerife",
    "sg:website":"www.tenerifeinfo.te",
    "wof:name":"Albert  Herbert",
    "wof:placetype":"venue"
},
  "geometry": {"coordinates":[-16.6924934387,28.0733604431],"type":"Point"}
}