{
  "type": "Feature",
  "properties": {
    "addr:full":"Avda America, S/n Madrid Madrid 28022",
    "addr:housenumber":"s / n",
    "addr:postcode":"28022",
    "addr:street":"Avda America",
    "iso:country":"ES",
    "sg:address":"Avda America, S/n",
    "sg:city":"Madrid",
    "sg:orig_category":"Complementos De Vestir (al Por Menor)",
    "sg:phone":"+34 915 61 15 88",
    "sg:postcode":"28022",
    "sg:province":"Madrid",
    "wof:name":"Rujas Rodriguez Florian",
    "wof:placetype":"venue"
},
  "geometry": {"coordinates":[-3.6175189018,40.4497718811],"type":"Point"}
}