{
  "type": "Feature",
  "properties": {
    "addr:full":"Calle de Santiago, 19 Elizondo Navarra 31700",
    "addr:housenumber":"19",
    "addr:postcode":"31700",
    "addr:street":"Calle De Santiago;Navarra",
    "iso:country":"ES",
    "sg:address":"Calle de Santiago, 19",
    "sg:city":"Elizondo",
    "sg:orig_category":"Peluquer\u00cdas, Peluquer\u00cda Mixta",
    "sg:phone":"+34 948 58 12 73",
    "sg:postcode":"31700",
    "sg:province":"Navarra",
    "wof:name":"Peluqueria Jaimerena",
    "wof:placetype":"venue"
},
  "geometry": {"coordinates":[-1.5174076557,43.1458625793],"type":"Point"}
}