{
  "type": "Feature",
  "properties": {
    "addr:full":"Calle de San Agustin, 61 Marpeque\u00d1a Las Palmas 35214",
    "addr:housenumber":"61",
    "addr:postcode":"35214",
    "addr:street":"Calle De San Agustin;Las Palmas",
    "iso:country":"ES",
    "sg:address":"Calle de San Agustin, 61",
    "sg:city":"Marpeque\u00d1a",
    "sg:orig_category":"Supermercados Y Hipermercados",
    "sg:phone":"+34 928 13 12 23",
    "sg:postcode":"35214",
    "sg:province":"Las Palmas",
    "wof:name":"Gonzalez Gonzalez Carmen",
    "wof:placetype":"venue"
},
  "geometry": {"coordinates":[-15.3887634277,27.9937648773],"type":"Point"}
}