{
  "type": "Feature",
  "properties": {
    "addr:full":"Doctor Bolibar Kalea, 1 Arrasate Guip\u00f9zcoa 20500",
    "addr:housenumber":"1",
    "addr:postcode":"20500",
    "addr:street":"Doctor Bolibar Kalea;Guipu\u0300Zcoa",
    "iso:country":"ES",
    "sg:address":"Doctor Bolibar Kalea, 1",
    "sg:city":"Arrasate",
    "sg:orig_category":"Delegados, Agentes De Tr\u00c1nsito, Auxiliares De Transporte Internacional",
    "sg:phone":"+34 943 79 05 08",
    "sg:postcode":"20500",
    "sg:province":"Guip\u00f9zcoa",
    "wof:name":"Hernandez Altunez Francisco",
    "wof:placetype":"venue"
},
  "geometry": {"coordinates":[-2.4776189327,43.0692672729],"type":"Point"}
}