{
  "type": "Feature",
  "properties": {
    "addr:full":"Avda Marques De La Vega De Armijo, 98 Montilla C\u00f3rdoba 14550",
    "addr:housenumber":"98",
    "addr:postcode":"14550",
    "addr:street":"Avda Marques De La Vega De Armijo;Co\u0301Rdoba",
    "iso:country":"ES",
    "sg:address":"Avda Marques De La Vega De Armijo, 98",
    "sg:city":"Montilla",
    "sg:orig_category":"Chapister\u00cda",
    "sg:phone":"+34 957 65 14 21",
    "sg:postcode":"14550",
    "sg:province":"C\u00f3rdoba",
    "wof:name":"Ortiz Sojo Domingo",
    "wof:placetype":"venue"
},
  "geometry": {"coordinates":[-4.6333470345,37.5822906494],"type":"Point"}
}