{
  "type": "Feature",
  "properties": {
    "addr:full":"Carr Sant Pere, 86 Borges Blanques Lleida 25400",
    "addr:housenumber":"86",
    "addr:postcode":"25400",
    "addr:street":"Carr Sant Pere",
    "iso:country":"ES",
    "sg:address":"Carr Sant Pere, 86",
    "sg:city":"Borges Blanques",
    "sg:orig_category":"Piedra Natural",
    "sg:phone":"+34 973 14 08 19",
    "sg:postcode":"25400",
    "sg:province":"Lleida",
    "wof:name":"Altarriba Vigata Domenec",
    "wof:placetype":"venue"
},
  "geometry": {"coordinates":[0.8725968003,41.5212745667],"type":"Point"}
}