{
  "type": "Feature",
  "properties": {
    "addr:full":"Calle de Rio Arba, 33 Cuarte Huerva Zaragoza 50410",
    "addr:housenumber":"33",
    "addr:postcode":"50410",
    "addr:street":"Calle De Rio Arba",
    "iso:country":"ES",
    "sg:address":"Calle de Rio Arba, 33",
    "sg:city":"Cuarte Huerva",
    "sg:orig_category":"Materias Pl\u00c1sticas: Art\u00cdculos Para La Industria",
    "sg:phone":"+34 976 50 38 57",
    "sg:postcode":"50410",
    "sg:province":"Zaragoza",
    "wof:name":"Electroplasticos Peber S. L.",
    "wof:placetype":"venue"
},
  "geometry": {"coordinates":[-0.9308530092,41.597820282],"type":"Point"}
}