{
  "type": "Feature",
  "properties": {
    "iso:country":"ES",
    "sg:address":"Calle de Ulises Calle, 4",
    "sg:city":"Madrid",
    "sg:orig_category":"Inform\u00c1tica (estudios, Servicios, Asesor\u00cda, Formaci\u00d3n)",
    "sg:phone":"+34 917 21 87 87",
    "sg:postcode":"28043",
    "sg:province":"Madrid",
    "wof:name":"Delta Software Sl",
    "wof:placetype":"venue"
},
  "geometry": {"coordinates":[-3.655780077,40.4559822083],"type":"Point"}
}