{
  "type": "Feature",
  "properties": {
    "iso:country":"ES",
    "sg:address":"Avda Jose Ortega Y Gasset, 3",
    "sg:city":"Malaga",
    "sg:orig_category":"Panader\u00cdas, Panader\u00cdas",
    "sg:phone":"+34 952 33 21 20",
    "sg:postcode":"29006",
    "sg:province":"M\u00e1laga",
    "wof:name":"Blanco Solis Antonio",
    "wof:placetype":"venue"
},
  "geometry": {"coordinates":[-4.4420351982,36.7119064331],"type":"Point"}
}