{
  "type": "Feature",
  "properties": {
    "iso:country":"ES",
    "sg:address":"Carrer de Riera Baste, S/n",
    "sg:city":"S. Boi Llobregat",
    "sg:orig_category":"Carnicer\u00cdas, Carnicer\u00cdas",
    "sg:phone":"+34 936 54 76 54",
    "sg:postcode":"08830",
    "sg:province":"Barcelona",
    "wof:name":"Gascon Gascon Jose Miguel",
    "wof:placetype":"venue"
},
  "geometry": {"coordinates":[2.0361208916,41.346622467],"type":"Point"}
}