{
  "type": "Feature",
  "properties": {
    "addr:full":"Calle de Tellagorri, 12 Bilbao Vizcaya 48012",
    "addr:housenumber":"12",
    "addr:postcode":"48012",
    "addr:street":"Calle De Tellagorri",
    "iso:country":"ES",
    "sg:address":"Calle de Tellagorri, 12",
    "sg:city":"Bilbao",
    "sg:orig_category":"Art\u00cdculos De Limpieza Y De Cocina (fabricaci\u00d3n, Al Por Mayor)",
    "sg:phone":"+34 944 27 17 96",
    "sg:postcode":"48012",
    "sg:province":"Vizcaya",
    "wof:name":"Ibergallartu Conde Jose Luis",
    "wof:placetype":"venue"
},
  "geometry": {"coordinates":[-2.9499590397,43.2566604614],"type":"Point"}
}