{
  "type": "Feature",
  "properties": {
    "iso:country":"ES",
    "sg:address":"Cibeles, S/n",
    "sg:city":"Torrelamata",
    "sg:orig_category":"Ingenier\u00cda, Centros De Estudios (diversos)",
    "sg:phone":"+34 966 92 01 07",
    "sg:postcode":"03188",
    "sg:province":"Alicante",
    "wof:name":"Pastor Medina S.a.",
    "wof:placetype":"venue"
},
  "geometry": {"coordinates":[-0.6579220295,38.0312385559],"type":"Point"}
}