{
  "type": "Feature",
  "properties": {
    "addr:full":"Avda Libertador Simon Bolivar, 19 Portugalete Vizcaya 48920",
    "addr:housenumber":"19",
    "addr:postcode":"48920",
    "addr:street":"Avda Libertador Simon Bolivar",
    "iso:country":"ES",
    "sg:address":"Avda Libertador Simon Bolivar, 19",
    "sg:city":"Portugalete",
    "sg:classifiers":[
        {
            "category":"Autos & Motor Vehicles",
            "subcategory":"Automobile Sales",
            "type":"Retail Goods"
        }
    ],
    "sg:phone":"+34 944 61 88 66",
    "sg:postcode":"48920",
    "sg:province":"Vizcaya",
    "wof:name":"Diodoro Gonzalez Bascones",
    "wof:placetype":"venue"
},
  "geometry": {"coordinates":[-3.0242800713,43.3217773438],"type":"Point"}
}