{
  "type": "Feature",
  "properties": {
    "addr:full":"Trav San Alfonso(gabatos), S/n Los Dolores Murcia 30310",
    "addr:housenumber":"s / n",
    "addr:postcode":"30310",
    "addr:street":"Trav San Alfonso Gabatos",
    "iso:country":"ES",
    "sg:address":"Trav San Alfonso(gabatos), S/n",
    "sg:city":"Los Dolores",
    "sg:orig_category":"Arquitectos",
    "sg:phone":"+34 968 31 69 53",
    "sg:postcode":"30310",
    "sg:province":"Murcia",
    "wof:name":"Cervantes Sanchez Manuel",
    "wof:placetype":"venue"
},
  "geometry": {"coordinates":[-1.0078120232,37.6387329102],"type":"Point"}
}