{
  "type": "Feature",
  "properties": {
    "addr:full":"Pla\u00c7 Vi (del), 12 Girona Girona 17004",
    "addr:postcode":"17004",
    "iso:country":"ES",
    "sg:address":"Pla\u00c7 Vi (del), 12",
    "sg:city":"Girona",
    "sg:orig_category":"Compraventa De Antig\u00dcedades",
    "sg:phone":"+34 972 20 46 23",
    "sg:postcode":"17004",
    "sg:province":"Girona",
    "wof:name":"Prat Esteba Isabel",
    "wof:placetype":"venue"
},
  "geometry": {"coordinates":[2.8422400951,41.9735031128],"type":"Point"}
}