{
  "type": "Feature",
  "properties": {
    "iso:country":"ES",
    "sg:address":"Rier Miro (de), 46",
    "sg:city":"Reus",
    "sg:orig_category":"Agentes, Concesionarios Y Sucursales De Veh\u00cdculos",
    "sg:phone":"+34 977 12 78 97",
    "sg:postcode":"43202",
    "sg:province":"Tarragona",
    "wof:name":"Distribucio I Manteniment De L'automobil Tcn S.l.",
    "wof:placetype":"venue"
},
  "geometry": {"coordinates":[1.107929945,41.1519889832],"type":"Point"}
}