{
  "type": "Feature",
  "properties": {
    "addr:full":"Via Faraday (de), 2 Boisaca La Coru\u00f1a 15890",
    "addr:postcode":"15890",
    "addr:street":"Via Faraday De 2 Boisaca La Corun\u0303A",
    "iso:country":"ES",
    "sg:address":"Via Faraday (de), 2",
    "sg:city":"Boisaca",
    "sg:orig_category":"Panader\u00cdas, Pasteler\u00cdas, Boller\u00cda Industriale (fabricaci\u00d3n, Al Por Mayor)",
    "sg:phone":"+34 981 55 75 28",
    "sg:postcode":"15890",
    "sg:province":"La Coru\u00f1a",
    "wof:name":"Panrico S.l.u.",
    "wof:placetype":"venue"
},
  "geometry": {"coordinates":[-8.4769210815,42.8835983276],"type":"Point"}
}