{
  "type": "Feature",
  "properties": {
    "iso:country":"ES",
    "sg:address":"Avda Europa (de), 15",
    "sg:city":"Alcobendas",
    "sg:orig_category":"\u00d3ptica: Instrumentos (fabricaci\u00d3n)",
    "sg:phone":"+34 916 61 50 85",
    "sg:postcode":"28108",
    "sg:province":"Madrid",
    "sg:website":"www.loop.vision.com",
    "wof:name":"Navoptik S.l.",
    "wof:placetype":"venue"
},
  "geometry": {"coordinates":[-3.6556329727,40.516960144],"type":"Point"}
}