{
  "type": "Feature",
  "properties": {
    "addr:full":"Calle de Azalea (de La), 231 Alcobendas Madrid 28109",
    "addr:housenumber":"231",
    "addr:postcode":"28109",
    "addr:street":"Calle De Azalea De La",
    "iso:country":"ES",
    "sg:address":"Calle de Azalea (de La), 231",
    "sg:city":"Alcobendas",
    "sg:orig_category":"Material Y Suministros Para Fotocopiadoras, Reprograf\u00cda",
    "sg:phone":"+34 916 50 15 47",
    "sg:postcode":"28109",
    "sg:province":"Madrid",
    "wof:name":"Alliedbrokers S.l.",
    "wof:placetype":"venue"
},
  "geometry": {"coordinates":[-3.6475327015,40.5232009888],"type":"Point"}
}