{
  "type": "Feature",
  "properties": {
    "addr:full":"Carrer de Holanda, 6 Hospitalet Llobregat Barcelona 08903",
    "addr:housenumber":"6",
    "addr:postcode":"08903",
    "addr:street":"Carrer De Holanda",
    "iso:country":"ES",
    "sg:address":"Carrer de Holanda, 6",
    "sg:city":"Hospitalet Llobregat",
    "sg:orig_category":"Radiocomunicaciones, Telefon\u00cda M\u00d3vil, Radiomensajer\u00cda: Servicios, Comercializaci\u00d3n",
    "sg:phone":"+34 934 31 79 43",
    "sg:postcode":"08903",
    "sg:province":"Barcelona",
    "wof:name":"Hamza Grupo De Telecomunicacion S.l.",
    "wof:placetype":"venue"
},
  "geometry": {"coordinates":[2.1276340485,41.3711624146],"type":"Point"}
}