{
  "type": "Feature",
  "properties": {
    "addr:full":"Carrer de Tramuntana, 3 Calders Barcelona 08275",
    "addr:housenumber":"3",
    "addr:postcode":"08275",
    "addr:street":"Carrer De Tramuntana",
    "iso:country":"ES",
    "sg:address":"Carrer de Tramuntana, 3",
    "sg:city":"Calders",
    "sg:orig_category":"Mataderos De Poller\u00cda",
    "sg:phone":"+34 938 30 91 00",
    "sg:postcode":"08275",
    "sg:province":"Barcelona",
    "wof:name":"Pica\u00f1ol Coll Francisco",
    "wof:placetype":"venue"
},
  "geometry": {"coordinates":[1.9962069988,41.7917938232],"type":"Point"}
}