{
  "type": "Feature",
  "properties": {
    "iso:country":"ES",
    "sg:address":"Calle de Cure\u00d1eros, 5",
    "sg:city":"Aracena",
    "sg:orig_category":"Art\u00cdculos De Regalo (al Por Menor)",
    "sg:phone":"+34 959 12 65 74",
    "sg:postcode":"21200",
    "sg:province":"Huelva",
    "wof:name":"Sacristan Martin Mercedes",
    "wof:placetype":"venue"
},
  "geometry": {"coordinates":[-6.5617208481,37.8966903687],"type":"Point"}
}