{
  "type": "Feature",
  "properties": {
    "addr:full":"Calle de Buceta, General, 8 Melilla Melilla 52004",
    "addr:housenumber":"8",
    "addr:postcode":"52004",
    "addr:street":"Calle De Buceta General",
    "iso:country":"ES",
    "sg:address":"Calle de Buceta, General, 8",
    "sg:city":"Melilla",
    "sg:orig_category":"Arreglo, Reparaci\u00d3n, Piezas Sueltas De Televisi\u00d3n, V\u00cddeo, Hi",
    "sg:phone":"+34 952 68 12 08",
    "sg:postcode":"52004",
    "sg:province":"Melilla",
    "wof:name":"Benaisa Mohamed Aomar",
    "wof:placetype":"venue"
},
  "geometry": {"coordinates":[-2.9437329769,35.2909240723],"type":"Point"}
}