{
  "type": "Feature",
  "properties": {
    "iso:country":"ES",
    "sg:address":"Cr Madrid-valencia, Km. 0082,5",
    "sg:city":"Tarancon",
    "sg:orig_category":"Venta, Colocaci\u00d3n, Reparaci\u00d3n De Parabrisas, Techos Descapotables",
    "sg:phone":"+34 969 32 70 46",
    "sg:postcode":"16400",
    "sg:province":"Cuenca",
    "wof:name":"Autocristal Norte S.l.",
    "wof:placetype":"venue"
},
  "geometry": {"coordinates":[-2.997559309,40.0041694641],"type":"Point"}
}