{
  "type": "Feature",
  "properties": {
    "addr:full":"Avda Nueve De Octubre, 20 Puerto Valencia 46520",
    "addr:housenumber":"20",
    "addr:postcode":"46520",
    "addr:street":"Avda Nueve De Octubre",
    "iso:country":"ES",
    "sg:address":"Avda Nueve De Octubre, 20",
    "sg:city":"Puerto",
    "sg:orig_category":"Abogados",
    "sg:phone":"+34 962 68 15 49",
    "sg:postcode":"46520",
    "sg:province":"Valencia",
    "wof:name":"Belda Ferrer Gemma",
    "wof:placetype":"venue"
},
  "geometry": {"coordinates":[-0.2205300033,39.6586380005],"type":"Point"}
}