{
  "type": "Feature",
  "properties": {
    "iso:country":"ES",
    "sg:address":"Avda Profesor Floriano Cumbre\u00d1o, 1",
    "sg:city":"Caceres",
    "sg:orig_category":"Discapacitados",
    "sg:phone":"+34 927 23 63 51",
    "sg:postcode":"10005",
    "sg:province":"C\u00e1ceres",
    "wof:name":"Aspainca",
    "wof:placetype":"venue"
},
  "geometry": {"coordinates":[-6.3850946426,39.4654769897],"type":"Point"}
}