{
  "type": "Feature",
  "properties": {
    "iso:country":"ES",
    "sg:address":"Plaz Corrillo, 4",
    "sg:city":"Valladolid",
    "sg:orig_category":"Peluquer\u00cdas, Peluquer\u00cda Mixta",
    "sg:phone":"+34 983 35 04 42",
    "sg:postcode":"47001",
    "sg:province":"Valladolid",
    "wof:name":"Barciela Rivas Alejandro",
    "wof:placetype":"venue"
},
  "geometry": {"coordinates":[-4.7279400826,41.652721405],"type":"Point"}
}