{
  "type": "Feature",
  "properties": {
    "iso:country":"ES",
    "sg:address":"Av Estatut, 77",
    "sg:city":"Rubi",
    "sg:orig_category":"Contenedores (mercanc\u00cdas)",
    "sg:phone":"+34 935 86 18 43",
    "sg:postcode":"08191",
    "sg:province":"Barcelona",
    "wof:name":"Agencia De Transportes Jormongeika S.l.",
    "wof:placetype":"venue"
},
  "geometry": {"coordinates":[2.0386590958,41.4915962219],"type":"Point"}
}