{
  "type": "Feature",
  "properties": {
    "iso:country":"ES",
    "sg:address":"Calle de Dehesa, 33",
    "sg:city":"Valmojado",
    "sg:orig_category":"Cerrajer\u00cda, Ferrallista",
    "sg:phone":"+34 918 17 07 43",
    "sg:postcode":"45940",
    "sg:province":"Toledo",
    "wof:name":"Ramiro Gomez Jesus",
    "wof:placetype":"venue"
},
  "geometry": {"coordinates":[-4.0935306549,40.2040863037],"type":"Point"}
}