{
  "type": "Feature",
  "properties": {
    "iso:country":"ES",
    "sg:address":"Calle de Blas Infante, 2",
    "sg:city":"Villa Rio",
    "sg:orig_category":"Molduras, Junquillos, Listones Y Molduras Perforadas",
    "sg:phone":"+34 957 17 60 82",
    "sg:postcode":"14640",
    "sg:province":"C\u00f3rdoba",
    "wof:name":"Sanchez Coba Pedro Manuel",
    "wof:placetype":"venue"
},
  "geometry": {"coordinates":[-4.2925581932,37.9820556641],"type":"Point"}
}