{
  "type": "Feature",
  "properties": {
    "addr:full":"Calle de Andres Julia, 9 Valencia Valencia 46008",
    "addr:housenumber":"9",
    "addr:postcode":"46008",
    "addr:street":"Calle De Andres Julia",
    "iso:country":"ES",
    "sg:address":"Calle de Andres Julia, 9",
    "sg:city":"Valencia",
    "sg:orig_category":"Inform\u00c1tica (estudios, Servicios, Asesor\u00cda, Formaci\u00d3n)",
    "sg:phone":"+34 963 92 36 47",
    "sg:postcode":"46008",
    "sg:province":"Valencia",
    "wof:name":"Microrenove S.l.",
    "wof:placetype":"venue"
},
  "geometry": {"coordinates":[-0.3847962916,39.4776077271],"type":"Point"}
}