{
  "type": "Feature",
  "properties": {
    "addr:full":"Calle de Joaquin Maria Lopez, 14 Madrid Madrid 28015",
    "addr:housenumber":"14",
    "addr:postcode":"madrid;28015",
    "addr:street":"Calle De Joaquin Maria Lopez",
    "iso:country":"ES",
    "sg:address":"Calle de Joaquin Maria Lopez, 14",
    "sg:city":"Madrid",
    "sg:orig_category":"Empresarios",
    "sg:phone":"+34 915 35 17 02",
    "sg:postcode":"28015",
    "sg:province":"Madrid",
    "wof:name":"Proyectos Y Obras Barcelo S.l.",
    "wof:placetype":"venue"
},
  "geometry": {"coordinates":[-3.7096366882,40.4375076294],"type":"Point"}
}