{
  "type": "Feature",
  "properties": {
    "addr:full":"Calle de Bailarin Vicente Escudero, 2 Valladolid Valladolid 47005",
    "addr:housenumber":"2",
    "addr:postcode":"47005",
    "addr:street":"Calle De Bailarin Vicente Escudero",
    "iso:country":"ES",
    "sg:address":"Calle de Bailarin Vicente Escudero, 2",
    "sg:city":"Valladolid",
    "sg:orig_category":"Electricidad, Electr\u00d3nica: Material Y Suministros (al Por Mayor)",
    "sg:phone":"+34 983 29 31 72",
    "sg:postcode":"47005",
    "sg:province":"Valladolid",
    "wof:name":"Leal Santos Jesus",
    "wof:placetype":"venue"
},
  "geometry": {"coordinates":[-4.7170395851,41.6497077942],"type":"Point"}
}