{
  "type": "Feature",
  "properties": {
    "iso:country":"ES",
    "sg:address":"Trva Camino Viejo Del Puerto, S/n",
    "sg:city":"San Jose",
    "sg:orig_category":"Rectificaci\u00d3n, Mecanizado, Fresado",
    "sg:phone":"+34 968 46 20 16",
    "sg:postcode":"30800",
    "sg:province":"Murcia",
    "wof:name":"Mecanizados Gines Padilla S.l.",
    "wof:placetype":"venue"
},
  "geometry": {"coordinates":[-1.6905640364,37.680557251],"type":"Point"}
}