{
  "type": "Feature",
  "properties": {
    "iso:country":"ES",
    "sg:address":"Avda Doctor Peset Aleixandre, 126",
    "sg:city":"Valencia",
    "sg:orig_category":"Artes Gr\u00c1ficas, Artes Pl\u00c1sticas (curso)",
    "sg:phone":"+34 963 49 94 49",
    "sg:postcode":"46025",
    "sg:province":"Valencia",
    "wof:name":"Graphimage Graffor S.l.",
    "wof:placetype":"venue"
},
  "geometry": {"coordinates":[-0.3871890008,39.4893226624],"type":"Point"}
}