{
  "type": "Feature",
  "properties": {
    "iso:country":"ES",
    "sg:address":"Calle de Severo Ochoa, 4",
    "sg:city":"Vegas",
    "sg:orig_category":"Doctores En Medicina",
    "sg:phone":"+34 985 57 38 44",
    "sg:postcode":"33404",
    "sg:province":"Asturias",
    "wof:name":"Martin-jordan Cajigal Gonzalo",
    "wof:placetype":"venue"
},
  "geometry": {"coordinates":[-5.9240369797,43.5455207825],"type":"Point"}
}