{
  "type": "Feature",
  "properties": {
    "addr:full":"Calle de Mayor, 16 Briviesca Burgos 09240",
    "addr:housenumber":"16",
    "addr:postcode":"09240",
    "addr:street":"Calle De Mayor",
    "iso:country":"ES",
    "sg:address":"Calle de Mayor, 16",
    "sg:city":"Briviesca",
    "sg:orig_category":"Abogados",
    "sg:phone":"+34 947 59 20 27",
    "sg:postcode":"09240",
    "sg:province":"Burgos",
    "wof:name":"Gabilondo Espinosa Felicitas",
    "wof:placetype":"venue"
},
  "geometry": {"coordinates":[-3.3246610165,42.5496292114],"type":"Point"}
}