{
  "type": "Feature",
  "properties": {
    "iso:country":"ES",
    "sg:address":"Calle de Maria Cristina, 38",
    "sg:city":"Santa Cruz De Tenerife",
    "sg:orig_category":"M\u00c9dicos: An\u00c1lisis Cl\u00cdnicos",
    "sg:phone":"+34 922 27 84 82",
    "sg:postcode":"38004",
    "sg:province":"Santa Cruz De Tenerife",
    "wof:name":"Logatu S.l.",
    "wof:placetype":"venue"
},
  "geometry": {"coordinates":[-16.2581367493,28.4693336487],"type":"Point"}
}