{
  "type": "Feature",
  "properties": {
    "addr:full":"Calle de San Antonio, 27 Vitoria-gasteiz \u00c1lava 01005",
    "addr:housenumber":"27",
    "addr:postcode":"01005",
    "addr:street":"Calle De San Antonio",
    "iso:country":"ES",
    "sg:address":"Calle de San Antonio, 27",
    "sg:city":"Vitoria-gasteiz",
    "sg:orig_category":"Clubes, Asociaciones De Ocio",
    "sg:phone":"+34 945 14 23 57",
    "sg:postcode":"01005",
    "sg:province":"\u00c1lava",
    "wof:name":"Gomez Ugarte Jesus Maria",
    "wof:placetype":"venue"
},
  "geometry": {"coordinates":[-2.6742069721,42.843547821],"type":"Point"}
}