{
  "type": "Feature",
  "properties": {
    "iso:country":"ES",
    "sg:address":"Carrer de Concili De Trento, 265",
    "sg:city":"Barcelona",
    "sg:orig_category":"Congelados: Productos Alimentarios (al Por Menor)",
    "sg:phone":"+34 933 05 16 53",
    "sg:postcode":"08020",
    "sg:province":"Barcelona",
    "wof:name":"Satorres Ibarz Maria De Las Mercedes",
    "wof:placetype":"venue"
},
  "geometry": {"coordinates":[2.2051279545,41.4208679199],"type":"Point"}
}