{
  "type": "Feature",
  "properties": {
    "addr:full":"Calle de Martin El Humano, 12 Valencia Valencia 46008",
    "addr:housenumber":"12",
    "addr:postcode":"46008",
    "addr:street":"Calle De Martin El Humano",
    "iso:country":"ES",
    "sg:address":"Calle de Martin El Humano, 12",
    "sg:city":"Valencia",
    "sg:orig_category":"Edici\u00d3n De Diarios, Revistas, Boletines",
    "sg:phone":"+34 963 82 18 34",
    "sg:postcode":"46008",
    "sg:province":"Valencia",
    "sg:website":"www.patrimonio-ediciones.com",
    "wof:name":"Patrimonio Ediciones S.l.",
    "wof:placetype":"venue"
},
  "geometry": {"coordinates":[-0.5119351745,39.84923172],"type":"Point"}
}