{
  "type": "Feature",
  "properties": {
    "addr:full":"Ctra Ctja Cuesta, S/n Castilleja Cuesta Sevilla 41950",
    "addr:housenumber":"s / n",
    "addr:postcode":"41950",
    "addr:street":"Ctra Ctja Cuesta;Castilleja Cuesta Sevilla",
    "iso:country":"ES",
    "sg:address":"Ctra Ctja Cuesta, S/n",
    "sg:city":"Castilleja Cuesta",
    "sg:orig_category":"Cajas De Ahorro",
    "sg:phone":"+34 954 16 53 81",
    "sg:postcode":"41950",
    "sg:province":"Sevilla",
    "wof:name":"Monte De Piedad Y Caja De Ahorros De Huelva Y Sevilla",
    "wof:placetype":"venue"
},
  "geometry": {"coordinates":[-6.0566887856,37.3854942322],"type":"Point"}
}