{
  "type": "Feature",
  "properties": {
    "addr:full":"Calle de Laponia, 5 Madrid Madrid 28030",
    "addr:housenumber":"5",
    "addr:postcode":"28030",
    "addr:street":"Calle De Laponia",
    "iso:country":"ES",
    "sg:address":"Calle de Laponia, 5",
    "sg:city":"Madrid",
    "sg:orig_category":"Asesor\u00cda Sobre Comunicaci\u00d3n De Empresas",
    "sg:phone":"+34 917 51 06 09",
    "sg:postcode":"28030",
    "sg:province":"Madrid",
    "wof:name":"Grupo Asesor Perez Y Alca\u00f1iz S.l.",
    "wof:placetype":"venue"
},
  "geometry": {"coordinates":[-3.6275091171,40.405456543],"type":"Point"}
}