{
  "type": "Feature",
  "properties": {
    "iso:country":"ES",
    "sg:address":"Avda Abrantes, 97",
    "sg:city":"Madrid",
    "sg:orig_category":"Centros Comerciales Y Grandes Tiendas",
    "sg:phone":"+34 914 69 37 33",
    "sg:postcode":"28025",
    "sg:province":"Madrid",
    "wof:name":"Chen  Xu",
    "wof:placetype":"venue"
},
  "geometry": {"coordinates":[-3.7356529236,40.3745880127],"type":"Point"}
}