{
  "type": "Feature",
  "properties": {
    "iso:country":"ES",
    "sg:address":"Servitas, 17",
    "sg:city":"Banyoles",
    "sg:orig_category":"Sindicatos De Trabajadores",
    "sg:phone":"+34 972 57 31 54",
    "sg:postcode":"17820",
    "sg:province":"Girona",
    "wof:name":"Comissions Obreres",
    "wof:placetype":"venue"
},
  "geometry": {"coordinates":[2.7637000084,42.1192016602],"type":"Point"}
}