{
  "type": "Feature",
  "properties": {
    "addr:full":"Calle de Juan Bravo, 20 Segovia Segovia 40001",
    "addr:housenumber":"20",
    "addr:postcode":"40001",
    "addr:street":"Calle De Juan Bravo",
    "iso:country":"ES",
    "sg:address":"Calle de Juan Bravo, 20",
    "sg:city":"Segovia",
    "sg:orig_category":"Ropa Para Ni\u00d1os (al Por Menor)",
    "sg:phone":"+34 921 46 33 87",
    "sg:postcode":"40001",
    "sg:province":"Segovia",
    "wof:name":"Kiddys's Class S A",
    "wof:placetype":"venue"
},
  "geometry": {"coordinates":[-4.1221041679,40.9488792419],"type":"Point"}
}