{
  "type": "Feature",
  "properties": {
    "iso:country":"ES",
    "sg:address":"Calle de Carrera, 22",
    "sg:city":"Archidona",
    "sg:orig_category":"Abogados",
    "sg:phone":"+34 952 71 40 95",
    "sg:postcode":"29300",
    "sg:province":"M\u00e1laga",
    "wof:name":"Astorga Miranda Jose Vicente",
    "wof:placetype":"venue"
},
  "geometry": {"coordinates":[-4.3884534836,37.0952796936],"type":"Point"}
}