{
  "type": "Feature",
  "properties": {
    "addr:full":"Calle de Cereros, 28 Zaragoza Zaragoza 50003",
    "addr:housenumber":"28",
    "addr:postcode":"50003",
    "addr:street":"Calle De Cereros",
    "iso:country":"ES",
    "sg:address":"Calle de Cereros, 28",
    "sg:city":"Zaragoza",
    "sg:orig_category":"Ense\u00d1anza: Profesiones Art\u00cdsticas",
    "sg:phone":"+34 976 44 25 94",
    "sg:postcode":"50003",
    "sg:province":"Zaragoza",
    "wof:name":"Royo Carrami\u00f1ana Francisco",
    "wof:placetype":"venue"
},
  "geometry": {"coordinates":[-0.8916682005,41.6573066711],"type":"Point"}
}