{
  "type": "Feature",
  "properties": {
    "iso:country":"ES",
    "sg:address":"Calle de Bernal Diaz Del Castillo, 12",
    "sg:city":"Medina Campo",
    "sg:orig_category":"Alimentaci\u00d3n General (al Por Menor)",
    "sg:phone":"+34 983 80 04 36",
    "sg:postcode":"47400",
    "sg:province":"Valladolid",
    "wof:name":"Fuente Reguero Luis De La",
    "wof:placetype":"venue"
},
  "geometry": {"coordinates":[-4.9157056808,41.3096618652],"type":"Point"}
}