{
  "type": "Feature",
  "properties": {
    "iso:country":"ES",
    "sg:address":"Calle de Mayor, 54",
    "sg:city":"Belones",
    "sg:orig_category":"Empresas De Carpinter\u00cda Met\u00c1lica",
    "sg:phone":"+34 968 56 92 39",
    "sg:postcode":"30385",
    "sg:province":"Murcia",
    "wof:name":"Garcia Navarro Miguel",
    "wof:placetype":"venue"
},
  "geometry": {"coordinates":[-0.7782539725,37.6229286194],"type":"Point"}
}