{
  "type": "Feature",
  "properties": {
    "addr:full":"Avda Pedro Mateo Sagasta, 11 Caldas De Reis Pontevedra 36650",
    "addr:housenumber":"11",
    "addr:postcode":"36650",
    "addr:street":"Avda Pedro Mateo Sagasta",
    "iso:country":"ES",
    "sg:address":"Avda Pedro Mateo Sagasta, 11",
    "sg:city":"Caldas De Reis",
    "sg:orig_category":"Institutos De Belleza",
    "sg:phone":"+34 986 54 11 81",
    "sg:postcode":"36650",
    "sg:province":"Pontevedra",
    "wof:name":"Formoso Castro Maria Jose",
    "wof:placetype":"venue"
},
  "geometry": {"coordinates":[-8.6420288086,42.6042861938],"type":"Point"}
}