{
  "type": "Feature",
  "properties": {
    "iso:country":"ES",
    "sg:address":"Calle de Santa Leonor, 61",
    "sg:city":"Madrid",
    "sg:orig_category":"Oficinas: Suministros Para (fabricaci\u00d3n, Al Por Mayor)",
    "sg:phone":"+34 913 27 09 25",
    "sg:postcode":"28037",
    "sg:province":"Madrid",
    "wof:name":"Equipamiento Institucional S.a.",
    "wof:placetype":"venue"
},
  "geometry": {"coordinates":[-3.6287200451,40.4338035583],"type":"Point"}
}