{
  "type": "Feature",
  "properties": {
    "iso:country":"ES",
    "sg:address":"Av Novelda, 10",
    "sg:city":"Elche",
    "sg:orig_category":"Inform\u00c1tica: Material Y Suministros",
    "sg:phone":"+34 966 66 25 25",
    "sg:postcode":"03206",
    "sg:province":"Alicante",
    "sg:website":"www.ctmsoftware.es",
    "wof:name":"Ctm Software S.l.",
    "wof:placetype":"venue"
},
  "geometry": {"coordinates":[-0.7077329755,38.2698898315],"type":"Point"}
}