{
  "type": "Feature",
  "properties": {
    "addr:full":"Calle de Delicias, 3 Fuenlabrada Madrid 28945",
    "addr:housenumber":"3",
    "addr:postcode":"28945",
    "addr:street":"Calle De Delicias",
    "iso:country":"ES",
    "sg:address":"Calle de Delicias, 3",
    "sg:city":"Fuenlabrada",
    "sg:orig_category":"Cl\u00cdnicas Dentales",
    "sg:phone":"+34 916 97 50 73",
    "sg:postcode":"28945",
    "sg:province":"Madrid",
    "wof:name":"Centro Dental Martinez Molinello S.l.",
    "wof:placetype":"venue"
},
  "geometry": {"coordinates":[-3.7973144054,40.2840270996],"type":"Point"}
}