{
  "type": "Feature",
  "properties": {
    "addr:full":"Calle de Teniente Ruiz, 2 Alcala Henares Madrid 28805",
    "addr:housenumber":"2",
    "addr:postcode":"28805",
    "addr:street":"Calle De Teniente Ruiz",
    "iso:country":"ES",
    "sg:address":"Calle de Teniente Ruiz, 2",
    "sg:city":"Alcala Henares",
    "sg:orig_category":"Asesor\u00cda Fiscal Y Jur\u00cddica",
    "sg:phone":"+34 918 89 25 85",
    "sg:postcode":"28805",
    "sg:province":"Madrid",
    "wof:name":"Consultores Y Auditores Complutense S.a.",
    "wof:placetype":"venue"
},
  "geometry": {"coordinates":[-3.3605868816,40.4846343994],"type":"Point"}
}