{
  "type": "Feature",
  "properties": {
    "addr:full":"Poli Ciudad Del Transporte, S/n San Juan De Mozarrifar Zaragoza 50820",
    "addr:housenumber":"s / n",
    "addr:postcode":"50820",
    "addr:street":"Juan;Mozarrifar",
    "iso:country":"ES",
    "sg:address":"Poli Ciudad Del Transporte, S/n",
    "sg:city":"San Juan De Mozarrifar",
    "sg:orig_category":"Suministros Para Carrocer\u00cdas",
    "sg:phone":"+34 976 15 04 58",
    "sg:postcode":"50820",
    "sg:province":"Zaragoza",
    "wof:name":"Servicios De Carrocerias S.l.",
    "wof:placetype":"venue"
},
  "geometry": {"coordinates":[-0.8416489959,41.7171096802],"type":"Point"}
}