{
  "type": "Feature",
  "properties": {
    "iso:country":"ES",
    "sg:address":"Calle de Minas, 6",
    "sg:city":"Utrillas",
    "sg:orig_category":"Fotocopias, Reprograf\u00cda",
    "sg:phone":"+34 978 75 72 36",
    "sg:postcode":"44760",
    "sg:province":"Teruel",
    "wof:name":"Gimenez Clemente Francisco",
    "wof:placetype":"venue"
},
  "geometry": {"coordinates":[-0.8508890271,40.8160400391],"type":"Point"}
}