{
  "type": "Feature",
  "properties": {
    "addr:full":"Calle de Parroco Antonio Gonzalez Abato, 4 Sevilla Sevilla 41013",
    "addr:housenumber":"4",
    "addr:postcode":"41013",
    "addr:street":"Calle De Parroco Antonio Gonzalez Abato",
    "iso:country":"ES",
    "sg:address":"Calle de Parroco Antonio Gonzalez Abato, 4",
    "sg:city":"Sevilla",
    "sg:orig_category":"Arquitectos",
    "sg:phone":"+34 954 23 30 40",
    "sg:postcode":"41013",
    "sg:province":"Sevilla",
    "wof:name":"Reina Fernandez Juan Carlos",
    "wof:placetype":"venue"
},
  "geometry": {"coordinates":[-5.9751939774,37.3665046692],"type":"Point"}
}