{
  "type": "Feature",
  "properties": {
    "addr:full":"Plaz Espa\u00d1a, 3 Castejon Navarra 31590",
    "addr:housenumber":"3",
    "addr:postcode":"31590",
    "addr:street":"Plaz Espan\u0303A",
    "iso:country":"ES",
    "sg:address":"Plaz Espa\u00d1a, 3",
    "sg:city":"Castejon",
    "sg:orig_category":"Partidos Pol\u00cdticos",
    "sg:phone":"+34 948 77 02 68",
    "sg:postcode":"31590",
    "sg:province":"Navarra",
    "wof:name":"Coalicion Electoral Izquierda Unida",
    "wof:placetype":"venue"
},
  "geometry": {"coordinates":[-1.6901530027,42.1714706421],"type":"Point"}
}