{
  "type": "Feature",
  "properties": {
    "addr:full":"Calle de Manuel De Falla, 65 Minas Riotinto Huelva 21660",
    "addr:housenumber":"65",
    "addr:postcode":"21660",
    "addr:street":"Calle De Manuel De Falla",
    "iso:country":"ES",
    "sg:address":"Calle de Manuel De Falla, 65",
    "sg:city":"Minas Riotinto",
    "sg:orig_category":"Promotores Constructores",
    "sg:phone":"+34 959 59 00 65",
    "sg:postcode":"21660",
    "sg:province":"Huelva",
    "wof:name":"Construcciones Zeitung Sl",
    "wof:placetype":"venue"
},
  "geometry": {"coordinates":[-6.5914359093,37.6918411255],"type":"Point"}
}