{
  "type": "Feature",
  "properties": {
    "addr:full":"G.v. Marques Del Turia, 86 Valencia Valencia 46005",
    "addr:housenumber":"86",
    "addr:postcode":"46005",
    "addr:street":"Turia",
    "iso:country":"ES",
    "sg:address":"G.v. Marques Del Turia, 86",
    "sg:city":"Valencia",
    "sg:orig_category":"Sociedades, Compa\u00d1\u00cdas Aseguradoras",
    "sg:phone":"+34 963 34 47 66",
    "sg:postcode":"46005",
    "sg:province":"Valencia",
    "wof:name":"Seguros Catalana Occidente S.a. De Seguros Y Reaseguros",
    "wof:placetype":"venue"
},
  "geometry": {"coordinates":[-0.3643380105,39.4686546326],"type":"Point"}
}