{
  "type": "Feature",
  "properties": {
    "iso:country":"ES",
    "sg:address":"Carr Oliveres (les), 21",
    "sg:city":"Benicasim",
    "sg:orig_category":"Empresas De Carpinter\u00cda De Madera",
    "sg:phone":"+34 964 30 39 51",
    "sg:postcode":"12560",
    "sg:province":"Castell\u00f3n",
    "wof:name":"Belliclau S.l.",
    "wof:placetype":"venue"
},
  "geometry": {"coordinates":[0.0457400009,40.0510292053],"type":"Point"}
}