{
  "type": "Feature",
  "properties": {
    "iso:country":"ES",
    "sg:address":"Calle de Huesca, 3",
    "sg:city":"Gra\u00f1en",
    "sg:orig_category":"Promotores Constructores",
    "sg:phone":"+34 974 39 00 81",
    "sg:postcode":"22260",
    "sg:province":"Huesca",
    "wof:name":"Zabal Ballestar S.c.",
    "wof:placetype":"venue"
},
  "geometry": {"coordinates":[-0.3699550033,41.9400482178],"type":"Point"}
}