{
  "type": "Feature",
  "properties": {
    "iso:country":"ES",
    "sg:address":"Ptda Daimes, S/n",
    "sg:city":"Elche",
    "sg:orig_category":"Asociaciones Ecologistas",
    "sg:phone":"+34 966 67 75 62",
    "sg:postcode":"03294",
    "sg:province":"Alicante",
    "wof:name":"Comunidad De Regantes El Canal",
    "wof:placetype":"venue"
},
  "geometry": {"coordinates":[-0.6838840246,38.2138900757],"type":"Point"}
}