{
  "type": "Feature",
  "properties": {
    "addr:full":"Carrer de Francisco Pizarro (de), S/n Tortosa Tarragona 43500",
    "addr:postcode":"43500",
    "addr:street":"Carrer De Francisco Pizarro De S / N",
    "iso:country":"ES",
    "sg:address":"Carrer de Francisco Pizarro (de), S/n",
    "sg:city":"Tortosa",
    "sg:orig_category":"Reposter\u00cdas",
    "sg:phone":"+34 977 58 03 13",
    "sg:postcode":"43500",
    "sg:province":"Tarragona",
    "wof:name":"Germans Sabate Mur C.b.",
    "wof:placetype":"venue"
},
  "geometry": {"coordinates":[0.5147950053,40.8150138855],"type":"Point"}
}