{
  "type": "Feature",
  "properties": {
    "iso:country":"ES",
    "sg:address":"Pase Martin J.iraola Etorbidea, S/n",
    "sg:city":"San Blas",
    "sg:orig_category":"Asociaciones Y Clubs Deportivos",
    "sg:phone":"+34 943 67 17 49",
    "sg:postcode":"20400",
    "sg:province":"Guip\u00f9zcoa",
    "wof:name":"Tolosa Club De Futbol",
    "wof:placetype":"venue"
},
  "geometry": {"coordinates":[-2.0789339542,43.1339912415],"type":"Point"}
}