{
  "type": "Feature",
  "properties": {
    "addr:full":"Rua Igrexa (da), 1 Xinzo De Limia Ourense 32630",
    "addr:postcode":"32630",
    "addr:street":"Rua Igrexa Da 1",
    "iso:country":"ES",
    "sg:address":"Rua Igrexa (da), 1",
    "sg:city":"Xinzo De Limia",
    "sg:orig_category":"Carnicer\u00cdas, Carnicer\u00cdas",
    "sg:phone":"+34 988 46 07 17",
    "sg:postcode":"32630",
    "sg:province":"Ourense",
    "wof:name":"Ferron Perez Juan Jose",
    "wof:placetype":"venue"
},
  "geometry": {"coordinates":[-7.726984024,42.0632019043],"type":"Point"}
}