{
  "type": "Feature",
  "properties": {
    "iso:country":"ES",
    "sg:address":"Avda Dr Villa Diaz, 12",
    "sg:city":"Carmona",
    "sg:orig_category":"Bazares, Art\u00cdculos De Limpieza Y De Cocina (al Por Menor)",
    "sg:phone":"+34 954 19 18 99",
    "sg:postcode":"41410",
    "sg:province":"Sevilla",
    "wof:name":"Rodriguez Climaco Rosario",
    "wof:placetype":"venue"
},
  "geometry": {"coordinates":[-5.6433792114,37.4708709717],"type":"Point"}
}