{
  "type": "Feature",
  "properties": {
    "addr:full":"Calle de Gipuzkoa, S/n Valle Trapaga Vizcaya 48510",
    "addr:housenumber":"s",
    "addr:postcode":"48510",
    "addr:street":"Calle De Gipuzkoa;/ N;Trapaga",
    "iso:country":"ES",
    "sg:address":"Calle de Gipuzkoa, S/n",
    "sg:city":"Valle Trapaga",
    "sg:orig_category":"Asociaciones, Organismos Culturales Y Socioeducativos",
    "sg:phone":"+34 944 86 30 11",
    "sg:postcode":"48510",
    "sg:province":"Vizcaya",
    "wof:name":"Club Social Zaballa",
    "wof:placetype":"venue"
},
  "geometry": {"coordinates":[-3.0321390629,43.3004112244],"type":"Point"}
}