{
  "type": "Feature",
  "properties": {
    "addr:full":"Ctra. V. Almeria, S/n Rincon Victoria M\u00e1laga 29730",
    "addr:housenumber":"s / n",
    "addr:postcode":"29730",
    "addr:street":"Ctra. V. Almeria;Ma\u0301Laga",
    "iso:country":"ES",
    "sg:address":"Ctra. V. Almeria, S/n",
    "sg:city":"Rincon Victoria",
    "sg:orig_category":"Molduras, Junquillos, Listones Y Molduras Perforadas",
    "sg:phone":"+34 952 40 20 00",
    "sg:postcode":"29730",
    "sg:province":"M\u00e1laga",
    "wof:name":"Gallardo Anaya Manuel",
    "wof:placetype":"venue"
},
  "geometry": {"coordinates":[-4.3441061974,36.7239837646],"type":"Point"}
}