{
  "type": "Feature",
  "properties": {
    "addr:full":"Av Mas De L'oli, 140 P. I. La Cova Valencia 46940",
    "addr:housenumber":"140",
    "addr:postcode":"46940",
    "addr:street":"Av Mas De L'Oli;P. I. La Cova",
    "iso:country":"ES",
    "sg:address":"Av Mas De L'oli, 140",
    "sg:city":"P. I. La Cova",
    "sg:orig_category":"Ropa Para Se\u00d1oras Y Caballeros (al Por Menor)",
    "sg:phone":"+34 961 52 62 74",
    "sg:postcode":"46940",
    "sg:province":"Valencia",
    "wof:name":"Textil Ayelo S.l.",
    "wof:placetype":"venue"
},
  "geometry": {"coordinates":[-0.376819998,39.4691886902],"type":"Point"}
}