{
  "type": "Feature",
  "properties": {
    "addr:full":"Carrer de Mossen Jacint Verdaguer, 108 Premia Mar Barcelona 08330",
    "addr:housenumber":"108",
    "addr:postcode":"08330",
    "addr:street":"Carrer De Mossen Jacint Verdaguer",
    "iso:country":"ES",
    "sg:address":"Carrer de Mossen Jacint Verdaguer, 108",
    "sg:city":"Premia Mar",
    "sg:orig_category":"Cajas De Ahorro",
    "sg:phone":"+34 937 52 45 16",
    "sg:postcode":"08330",
    "sg:province":"Barcelona",
    "wof:name":"Caixa D'estalvis De Catalunya",
    "wof:placetype":"venue"
},
  "geometry": {"coordinates":[2.3589799404,41.4935760498],"type":"Point"}
}