{
  "type": "Feature",
  "properties": {
    "addr:full":"Calle de Santa Cruz De Teijeiro, 3 Castellon Castell\u00f3n 12005",
    "addr:housenumber":"3",
    "addr:postcode":"12005",
    "addr:street":"Calle De Santa Cruz De Teijeiro;Castello\u0301N",
    "iso:country":"ES",
    "sg:address":"Calle de Santa Cruz De Teijeiro, 3",
    "sg:city":"Castellon",
    "sg:orig_category":"Agencias Y Agentes Comerciales, Representantes",
    "sg:phone":"+34 964 22 05 74",
    "sg:postcode":"12005",
    "sg:province":"Castell\u00f3n",
    "wof:name":"Manuel Y Luis Bellido Querol C. B.",
    "wof:placetype":"venue"
},
  "geometry": {"coordinates":[-0.0369740017,39.9803962708],"type":"Point"}
}