{
  "type": "Feature",
  "properties": {
    "iso:country":"ES",
    "sg:address":"Calle de Jose Maria De Pereda, 3",
    "sg:city":"S. Vicente Barquera",
    "sg:orig_category":"Librer\u00cdas",
    "sg:phone":"+34 942 71 16 40",
    "sg:postcode":"39540",
    "sg:province":"Cantabria",
    "wof:name":"Chaves Fernandez Teresa",
    "wof:placetype":"venue"
},
  "geometry": {"coordinates":[-4.4009580612,43.3832893372],"type":"Point"}
}