{
  "type": "Feature",
  "properties": {
    "iso:country":"ES",
    "sg:address":"Calle de Pedro Antonio De Alarcon, 91",
    "sg:city":"Granada",
    "sg:orig_category":"Inform\u00c1tica, Ofim\u00c1tica (estudios, Asesor\u00cda, Ingenier\u00cda, Formaci\u00d3n)",
    "sg:phone":"+34 958 37 30 12",
    "sg:postcode":"18003",
    "sg:province":"Granada",
    "wof:name":"Innova System C.b.",
    "wof:placetype":"venue"
},
  "geometry": {"coordinates":[-3.6089839935,37.1771621704],"type":"Point"}
}