{
  "type": "Feature",
  "properties": {
    "iso:country":"ES",
    "sg:address":"Calle de Campoverde, 34",
    "sg:city":"Almeria",
    "sg:orig_category":"Empresas De Carpinter\u00cda De Madera",
    "sg:phone":"+34 950 23 87 09",
    "sg:postcode":"04008",
    "sg:province":"Almer\u00eda",
    "wof:name":"Nieto Galindo Fulgencio",
    "wof:placetype":"venue"
},
  "geometry": {"coordinates":[-2.4584178925,36.8483810425],"type":"Point"}
}