{
  "type": "Feature",
  "properties": {
    "iso:country":"ES",
    "sg:address":"Avda Independencia, 12",
    "sg:city":"Le\u00f3n",
    "sg:orig_category":"Medias Y Calcetines (al Por Menor)",
    "sg:phone":"+34 987 25 77 25",
    "sg:postcode":"24003",
    "sg:province":"Le\u00f3n",
    "wof:name":"Martinez Robles Angel",
    "wof:placetype":"venue"
},
  "geometry": {"coordinates":[-5.57168293,42.5968856812],"type":"Point"}
}