{
  "type": "Feature",
  "properties": {
    "iso:country":"ES",
    "sg:address":"Calle de Bembibre, 15",
    "sg:city":"Fuenlabrada",
    "sg:orig_category":"Fabricaci\u00d3n De Sobres, Bolsas Y Fundas",
    "sg:phone":"+34 916 42 14 49",
    "sg:postcode":"28947",
    "sg:province":"Madrid",
    "wof:name":"Cirense Borse S.l.",
    "wof:placetype":"venue"
},
  "geometry": {"coordinates":[-3.7468526363,40.2664871216],"type":"Point"}
}