{
  "type": "Feature",
  "properties": {
    "addr:full":"Calle de Nueva, 4 Bonares Huelva 21830",
    "addr:housenumber":"4",
    "addr:postcode":"21830",
    "addr:street":"Calle De Nueva",
    "iso:country":"ES",
    "sg:address":"Calle de Nueva, 4",
    "sg:city":"Bonares",
    "sg:orig_category":"Notarios",
    "sg:phone":"+34 959 36 48 29",
    "sg:postcode":"21830",
    "sg:province":"Huelva",
    "wof:name":"Savona Romero Jacobo",
    "wof:placetype":"venue"
},
  "geometry": {"coordinates":[-6.6812648773,37.321647644],"type":"Point"}
}