{
  "type": "Feature",
  "properties": {
    "addr:full":"Cno. Moliners, S/n Son Ferriol Islas Baleares 07198",
    "addr:housenumber":"s / n",
    "addr:postcode":"07198",
    "addr:street":"Cno. Moliners",
    "iso:country":"ES",
    "sg:address":"Cno. Moliners, S/n",
    "sg:city":"Son Ferriol",
    "sg:orig_category":"Postigos, Persianas Y Celos\u00cdas",
    "sg:phone":"+34 971 42 98 38",
    "sg:postcode":"07198",
    "sg:province":"Islas Baleares",
    "wof:name":"Fusteria Son Ferriol S.l.",
    "wof:placetype":"venue"
},
  "geometry": {"coordinates":[2.7178099155,39.5789794922],"type":"Point"}
}