{
  "type": "Feature",
  "properties": {
    "iso:country":"ES",
    "sg:address":"Av Salle (la), 53",
    "sg:city":"Reus",
    "sg:orig_category":"Molduras, Junquillos, Listones Y Molduras Perforadas",
    "sg:phone":"+34 977 75 10 86",
    "sg:postcode":"43205",
    "sg:province":"Tarragona",
    "wof:name":"Zurita Millan Cb",
    "wof:placetype":"venue"
},
  "geometry": {"coordinates":[1.1069736481,41.1487960815],"type":"Point"}
}