{
  "type": "Feature",
  "properties": {
    "iso:country":"ES",
    "sg:address":"Avda Juan Xxiii, 1",
    "sg:city":"Valencia",
    "sg:orig_category":"M\u00c9dicos: Estomatolog\u00cda",
    "sg:phone":"+34 963 40 84 84",
    "sg:postcode":"46025",
    "sg:province":"Valencia",
    "wof:name":"Solano Lopez Javier",
    "wof:placetype":"venue"
},
  "geometry": {"coordinates":[-0.3825689852,39.4913711548],"type":"Point"}
}