{
  "type": "Feature",
  "properties": {
    "iso:country":"ES",
    "sg:address":"Calle de Virgilio, 11",
    "sg:city":"Arroyo Meaques",
    "sg:orig_category":"Laboratorios Y Trabajos De Fotograf\u00cda, V\u00cddeo Y Cine",
    "sg:phone":"+34 915 18 93 79",
    "sg:postcode":"28223",
    "sg:province":"Madrid",
    "wof:name":"Duplicaciones Singrovideo S.l.",
    "wof:placetype":"venue"
},
  "geometry": {"coordinates":[-3.792552948,40.397277832],"type":"Point"}
}