{
  "type": "Feature",
  "properties": {
    "iso:country":"ES",
    "sg:address":"Rbla Marina, 310",
    "sg:city":"Hospitalet Llobregat",
    "sg:orig_category":"Reposter\u00cdas",
    "sg:phone":"+34 933 35 44 35",
    "sg:postcode":"08907",
    "sg:province":"Barcelona",
    "wof:name":"Salas Rios Manuel",
    "wof:placetype":"venue"
},
  "geometry": {"coordinates":[2.1095099449,41.3529701233],"type":"Point"}
}