{
  "type": "Feature",
  "properties": {
    "addr:full":"Carrer de Hort De Torrella, 8 Palma Islas Baleares 07005",
    "addr:housenumber":"8",
    "addr:postcode":"07005",
    "addr:street":"Carrer De Hort De Torrella",
    "iso:country":"ES",
    "sg:address":"Carrer de Hort De Torrella, 8",
    "sg:city":"Palma",
    "sg:orig_category":"Heladeros",
    "sg:phone":"+34 971 46 66 64",
    "sg:postcode":"07005",
    "sg:province":"Islas Baleares",
    "wof:name":"Heladeria Chopo S.l.",
    "wof:placetype":"venue"
},
  "geometry": {"coordinates":[2.6613390446,39.5741539001],"type":"Point"}
}