{
  "type": "Feature",
  "properties": {
    "iso:country":"ES",
    "sg:address":"Praj Jalvo, 4",
    "sg:city":"Ruini",
    "sg:orig_category":"Delegados, Agentes De Tr\u00c1nsito, Auxiliares De Transporte Internacional",
    "sg:phone":"+34 950 64 60 97",
    "sg:postcode":"04560",
    "sg:province":"Almer\u00eda",
    "wof:name":"Transportes Gonzalez Larios",
    "wof:placetype":"venue"
},
  "geometry": {"coordinates":[-2.4910440445,36.9535560608],"type":"Point"}
}