{
  "type": "Feature",
  "properties": {
    "addr:full":"Plaz Mayor, 8 San Nicolas Murcia 30005",
    "addr:housenumber":"8",
    "addr:postcode":"30005",
    "addr:street":"Plaz Mayor",
    "iso:country":"ES",
    "sg:address":"Plaz Mayor, 8",
    "sg:city":"San Nicolas",
    "sg:classifiers":[
        {
            "category":"Autos & Motor Vehicles",
            "subcategory":"Automobile Sales",
            "type":"Retail Goods"
        }
    ],
    "sg:phone":"+34 968 90 14 36",
    "sg:postcode":"30005",
    "sg:province":"Murcia",
    "wof:name":"Lorca Gambin Francisco",
    "wof:placetype":"venue"
},
  "geometry": {"coordinates":[-1.1302499771,37.9829597473],"type":"Point"}
}