{
  "type": "Feature",
  "properties": {
    "addr:full":"Calle de Margarita Pardo De Cela, 20 Viveiro Lugo 27850",
    "addr:housenumber":"20",
    "addr:postcode":"27850",
    "addr:street":"Calle De Margarita Pardo De Cela",
    "iso:country":"ES",
    "sg:address":"Calle de Margarita Pardo De Cela, 20",
    "sg:city":"Viveiro",
    "sg:orig_category":"Art\u00cdculos De Regalo (al Por Menor)",
    "sg:phone":"+34 982 56 31 08",
    "sg:postcode":"27850",
    "sg:province":"Lugo",
    "wof:name":"Maranta C.b.",
    "wof:placetype":"venue"
},
  "geometry": {"coordinates":[-7.5951189995,43.6631813049],"type":"Point"}
}