{
  "type": "Feature",
  "properties": {
    "iso:country":"ES",
    "sg:address":"Reten, S/n",
    "sg:city":"Reten",
    "sg:orig_category":"Metalurgia",
    "sg:phone":"+34 981 81 24 40",
    "sg:postcode":"15900",
    "sg:province":"La Coru\u00f1a",
    "sg:website":"www.galifar.com",
    "wof:name":"Galifar S.l.",
    "wof:placetype":"venue"
},
  "geometry": {"coordinates":[-8.6475543976,42.7461280823],"type":"Point"}
}