{
  "type": "Feature",
  "properties": {
    "iso:country":"ES",
    "sg:address":"Carrer de Tallers, 24",
    "sg:city":"Colonia Sedo",
    "sg:orig_category":"Cables Y Hilos El\u00c9ctricos (fabricaci\u00d3n, Al Por Mayor)",
    "sg:phone":"+34 937 77 77 18",
    "sg:postcode":"08292",
    "sg:province":"Barcelona",
    "wof:name":"Cables Torroglosa S.l.",
    "wof:placetype":"venue"
},
  "geometry": {"coordinates":[1.867759943,41.5371665955],"type":"Point"}
}