{
  "type": "Feature",
  "properties": {
    "iso:country":"ES",
    "sg:address":"Calle de Ruzafa, 23",
    "sg:city":"Valencia",
    "sg:orig_category":"Electromedicina: Equipo",
    "sg:phone":"+34 963 51 95 44",
    "sg:postcode":"46004",
    "sg:province":"Valencia",
    "wof:name":"Merce V.electromedicina S.l.",
    "wof:placetype":"venue"
},
  "geometry": {"coordinates":[-0.3740319908,39.4656906128],"type":"Point"}
}