{
  "type": "Feature",
  "properties": {
    "addr:full":"Cno. Viejo Xativa, S/n Ontinyent Valencia 46870",
    "addr:housenumber":"s / n",
    "addr:postcode":"46870",
    "addr:street":"Cno. Viejo Xativa",
    "iso:country":"ES",
    "sg:address":"Cno. Viejo Xativa, S/n",
    "sg:city":"Ontinyent",
    "sg:orig_category":"Materias Pl\u00c1sticas: Productos De Consumo Masivo (fabricaci\u00d3n, Al Por Mayor)",
    "sg:phone":"+34 962 91 26 32",
    "sg:postcode":"46870",
    "sg:province":"Valencia",
    "wof:name":"Albert Innovacion S.l.",
    "wof:placetype":"venue"
},
  "geometry": {"coordinates":[-0.6583330035,38.7977752686],"type":"Point"}
}