{
  "type": "Feature",
  "properties": {
    "addr:full":"Avda Arquitecto Gomez Cuesta, 6 Playa Americas Santa Cruz De Tenerife 38660",
    "addr:housenumber":"6",
    "addr:postcode":"38660",
    "addr:street":"Avda Arquitecto Gomez Cuesta;Americas",
    "iso:country":"ES",
    "sg:address":"Avda Arquitecto Gomez Cuesta, 6",
    "sg:city":"Playa Americas",
    "sg:orig_category":"Inmobiliaria (agencias)",
    "sg:phone":"+34 922 75 28 38",
    "sg:postcode":"38660",
    "sg:province":"Santa Cruz De Tenerife",
    "wof:name":"Terrenos Inversiones Y Derivados S.l.",
    "wof:placetype":"venue"
},
  "geometry": {"coordinates":[-16.7317714691,28.0760765076],"type":"Point"}
}