{
  "type": "Feature",
  "properties": {
    "iso:country":"ES",
    "sg:address":"Carrer de Extremadura, 14",
    "sg:city":"S. Joan Despi",
    "sg:orig_category":"Materiales De Aislamiento T\u00c9rmico Y Ac\u00dastico",
    "sg:phone":"+34 934 77 33 03",
    "sg:postcode":"08970",
    "sg:province":"Barcelona",
    "wof:name":"Sistemas Secoplac S.l",
    "wof:placetype":"venue"
},
  "geometry": {"coordinates":[2.0739569664,41.3693656921],"type":"Point"}
}