{
  "type": "Feature",
  "properties": {
    "iso:country":"ES",
    "sg:address":"Carrer de Sant Pere Mes Baix, 21",
    "sg:city":"Barcelona",
    "sg:orig_category":"Ropa Para Se\u00d1oras (al Por Menor)",
    "sg:phone":"+34 933 10 46 11",
    "sg:postcode":"08003",
    "sg:province":"Barcelona",
    "wof:name":"Manufactures Ribas S.l.",
    "wof:placetype":"venue"
},
  "geometry": {"coordinates":[2.1769769192,41.3868865967],"type":"Point"}
}