{
  "type": "Feature",
  "properties": {
    "iso:country":"ES",
    "sg:address":"Calle de Francisco Gourie, 6",
    "sg:city":"Palmas De Gran Canaria",
    "sg:orig_category":"Granos Y Semillas (producci\u00d3n, Al Por Mayor)",
    "sg:phone":"+34 928 37 27 20",
    "sg:postcode":"35002",
    "sg:province":"Las Palmas",
    "wof:name":"Gonzalez Alonso Manuel",
    "wof:placetype":"venue"
},
  "geometry": {"coordinates":[-15.4155921936,28.1058616638],"type":"Point"}
}