{
  "type": "Feature",
  "properties": {
    "addr:full":"Avda Sierra De Gata, 34 Coria C\u00e1ceres 10800",
    "addr:housenumber":"34",
    "addr:postcode":"10800",
    "addr:street":"Avda Sierra De Gata;Ca\u0301Ceres",
    "iso:country":"ES",
    "sg:address":"Avda Sierra De Gata, 34",
    "sg:city":"Coria",
    "sg:orig_category":"Ropa Para Se\u00d1oras Y Caballeros (al Por Menor)",
    "sg:phone":"+34 927 50 10 47",
    "sg:postcode":"10800",
    "sg:province":"C\u00e1ceres",
    "wof:name":"Gutierrez Rodriguez Agustina",
    "wof:placetype":"venue"
},
  "geometry": {"coordinates":[-6.5369467735,39.9854202271],"type":"Point"}
}