{
  "type": "Feature",
  "properties": {
    "iso:country":"ES",
    "sg:address":"Calle de Grabador Jordan, 42",
    "sg:city":"Valencia",
    "sg:orig_category":"Molduras, Junquillos, Listones Y Molduras Perforadas",
    "sg:phone":"+34 963 33 95 34",
    "sg:postcode":"46013",
    "sg:province":"Valencia",
    "wof:name":"Alabau Monrabal M Teresa",
    "wof:placetype":"venue"
},
  "geometry": {"coordinates":[-0.367652595,39.4443817139],"type":"Point"}
}