{
  "type": "Feature",
  "properties": {
    "addr:full":"Plaz Constitucion, 14 Esca\u00d1uela Ja\u00e9n 23657",
    "addr:housenumber":"14",
    "addr:postcode":"23657",
    "addr:street":"Constitucion;Jae\u0301N",
    "iso:country":"ES",
    "sg:address":"Plaz Constitucion, 14",
    "sg:city":"Esca\u00d1uela",
    "sg:orig_category":"Empresas De Carpinter\u00cda De Madera",
    "sg:phone":"+34 953 34 50 27",
    "sg:postcode":"23657",
    "sg:province":"Ja\u00e9n",
    "wof:name":"Ure\u00f1a Serrano Miguel",
    "wof:placetype":"venue"
},
  "geometry": {"coordinates":[-4.033039093,37.8786468506],"type":"Point"}
}