{
  "type": "Feature",
  "properties": {
    "addr:full":"Calle de Pe\u00d1a (la), 35 Epila Zaragoza 50290",
    "addr:housenumber":"35",
    "addr:postcode":"50290",
    "addr:street":"Calle De Pen\u0303A La",
    "iso:country":"ES",
    "sg:address":"Calle de Pe\u00d1a (la), 35",
    "sg:city":"Epila",
    "sg:orig_category":"Empresas De Carpinter\u00cda De Madera",
    "sg:phone":"+34 976 60 30 39",
    "sg:postcode":"50290",
    "sg:province":"Zaragoza",
    "wof:name":"Morala Ramon Gregorio Adolfo",
    "wof:placetype":"venue"
},
  "geometry": {"coordinates":[-1.2804590464,41.6002388],"type":"Point"}
}