{
  "type": "Feature",
  "properties": {
    "addr:full":"Cra. Nacional Ii, S/n S. Andreu Llavaneres Barcelona 08392",
    "addr:housenumber":"s",
    "addr:postcode":"08392",
    "addr:street":"/ N S. Andreu Llavaneres Barcelona",
    "iso:country":"ES",
    "sg:address":"Cra. Nacional Ii, S/n",
    "sg:city":"S. Andreu Llavaneres",
    "sg:orig_category":"Fabricaci\u00d3n, Reparaci\u00d3n Y Mantenimiento De Construcciones Navales Y Fluviales",
    "sg:phone":"+34 937 92 85 26",
    "sg:postcode":"08392",
    "sg:province":"Barcelona",
    "wof:name":"Illa Majo Eudaldo",
    "wof:placetype":"venue"
},
  "geometry": {"coordinates":[2.4849700928,41.5697517395],"type":"Point"}
}