{
  "type": "Feature",
  "properties": {
    "iso:country":"ES",
    "sg:address":"Calle de Rollo, 1",
    "sg:city":"Albalate Zorita",
    "sg:orig_category":"Plomeros",
    "sg:phone":"+34 949 37 60 88",
    "sg:postcode":"19117",
    "sg:province":"Guadalajara",
    "wof:name":"Alcocer Garcia Antonio",
    "wof:placetype":"venue"
},
  "geometry": {"coordinates":[-2.8405911922,40.306388855],"type":"Point"}
}