{
  "type": "Feature",
  "properties": {
    "iso:country":"ES",
    "sg:address":"Barcelona (urb Can Guitart Vell), 13",
    "sg:city":"Cervello",
    "sg:orig_category":"Empresas De Vigilancia, Guardia Y Protecci\u00d3n",
    "sg:phone":"+34 936 60 05 89",
    "sg:postcode":"08758",
    "sg:province":"Barcelona",
    "sg:website":"www.cpsgrupo.com",
    "wof:name":"Cps De Seguretat S.l.",
    "wof:placetype":"venue"
},
  "geometry": {"coordinates":[1.960860014,41.3950843811],"type":"Point"}
}