{
  "type": "Feature",
  "properties": {
    "addr:full":"Carrer de Garrofers (dels), 2 Torredembarra Tarragona 43830",
    "addr:housenumber":"2",
    "addr:postcode":"43830",
    "addr:street":"Carrer De Garrofers Dels",
    "iso:country":"ES",
    "sg:address":"Carrer de Garrofers (dels), 2",
    "sg:city":"Torredembarra",
    "sg:orig_category":"Inmobiliaria (agencias)",
    "sg:phone":"+34 977 13 06 23",
    "sg:postcode":"43830",
    "sg:province":"Tarragona",
    "wof:name":"Masena Inmo S.l.",
    "wof:placetype":"venue"
},
  "geometry": {"coordinates":[1.4041800499,41.1455192566],"type":"Point"}
}