{
  "type": "Feature",
  "properties": {
    "addr:full":"Calle de San Juan, S/n Tolba\u00e7os De Arriba Burgos 09614",
    "addr:housenumber":"s / n",
    "addr:postcode":"09614",
    "addr:street":"Calle De San Juan",
    "iso:country":"ES",
    "sg:address":"Calle de San Juan, S/n",
    "sg:city":"Tolba\u00e7os De Arriba",
    "sg:orig_category":"Cr\u00cda De Animales",
    "sg:phone":"+34 947 38 34 21",
    "sg:postcode":"09614",
    "sg:province":"Burgos",
    "wof:name":"Jose Antonio Y Desiderio Serrano Serrano S.cv.",
    "wof:placetype":"venue"
},
  "geometry": {"coordinates":[-3.08197999,42.1176757812],"type":"Point"}
}