{
  "type": "Feature",
  "properties": {
    "addr:full":"Calle de Bailen, 12 Madrid Madrid 28...",
    "addr:housenumber":"12;28 ...",
    "addr:postcode":"madrid",
    "addr:street":"Calle De Bailen;Madrid",
    "iso:country":"ES",
    "sg:address":"Calle de Bailen, 12",
    "sg:city":"Madrid",
    "sg:orig_category":"Centros Empresariales",
    "sg:phone":"+34 915 38 29 00",
    "sg:postcode":"28...",
    "sg:province":"Madrid",
    "wof:name":"A.gestion Telefonica Oficinas Y Despachos S.l.",
    "wof:placetype":"venue"
},
  "geometry": {"coordinates":[-3.7136571407,40.4141616821],"type":"Point"}
}