{
  "type": "Feature",
  "properties": {
    "addr:full":"Avda Atance (el), 20 Guadalajara Guadalajara 19005",
    "addr:postcode":"19005",
    "addr:street":"Avda Atance El",
    "iso:country":"ES",
    "sg:address":"Avda Atance (el), 20",
    "sg:city":"Guadalajara",
    "sg:orig_category":"Procuradores",
    "sg:phone":"+34 949 21 48 70",
    "sg:postcode":"19005",
    "sg:province":"Guadalajara",
    "wof:name":"Martinez Gutierrez Marta",
    "wof:placetype":"venue"
},
  "geometry": {"coordinates":[-3.1530740261,40.641254425],"type":"Point"}
}