{
  "type": "Feature",
  "properties": {
    "addr:full":"Rua Severino Cobas, 298 Sabaxans Pontevedra 36214",
    "addr:housenumber":"298",
    "addr:postcode":"36214",
    "addr:street":"Rua Severino Cobas",
    "iso:country":"ES",
    "sg:address":"Rua Severino Cobas, 298",
    "sg:city":"Sabaxans",
    "sg:orig_category":"Molduras, Junquillos, Listones Y Molduras Perforadas",
    "sg:phone":"+34 986 27 22 32",
    "sg:postcode":"36214",
    "sg:province":"Pontevedra",
    "wof:name":"Prieto Nu\u00f1ez Enrique",
    "wof:placetype":"venue"
},
  "geometry": {"coordinates":[-8.7059106827,42.2124443054],"type":"Point"}
}