{
  "type": "Feature",
  "properties": {
    "addr:full":"Calle de Francisco Pizarro, 66 Albacete Albacete 02004",
    "addr:housenumber":"66",
    "addr:postcode":"02004",
    "addr:street":"Calle De Francisco Pizarro",
    "iso:country":"ES",
    "sg:address":"Calle de Francisco Pizarro, 66",
    "sg:city":"Albacete",
    "sg:orig_category":"Tapicer\u00cdas",
    "sg:phone":"+34 967 50 91 56",
    "sg:postcode":"02004",
    "sg:province":"Albacete",
    "wof:name":"Cifuentes Arias Jose Luis",
    "wof:placetype":"venue"
},
  "geometry": {"coordinates":[-1.8669589758,38.9913253784],"type":"Point"}
}