{
  "type": "Feature",
  "properties": {
    "iso:country":"ES",
    "sg:address":"Plaza De San Miguel, 3",
    "sg:city":"Morella",
    "sg:orig_category":"Asesor\u00cdas Y Estudios Financieros",
    "sg:phone":"+34 964 17 31 17",
    "sg:postcode":"12300",
    "sg:province":"Castell\u00f3n",
    "wof:name":"Centre Integrat De Serveis Economics S.a.",
    "wof:placetype":"venue"
},
  "geometry": {"coordinates":[-0.0991000012,40.6213607788],"type":"Point"}
}