{
  "type": "Feature",
  "properties": {
    "addr:full":"Calle de Rufino Blanco, 9 Guadalajara Guadalajara 19002",
    "addr:housenumber":"9",
    "addr:postcode":"19002",
    "addr:street":"Calle De Rufino Blanco",
    "iso:country":"ES",
    "sg:address":"Calle de Rufino Blanco, 9",
    "sg:city":"Guadalajara",
    "sg:classifiers":[
        {
            "category":"Personal",
            "subcategory":"Barber",
            "type":"Services"
        }
    ],
    "sg:phone":"+34 949 22 75 56",
    "sg:postcode":"19002",
    "sg:province":"Guadalajara",
    "sg:tags":[
        "caballeros",
        "de",
        "peluqueros"
    ],
    "wof:name":"Manuel Ropero Navarro Y Otros Cdad",
    "wof:placetype":"venue"
},
  "geometry": {"coordinates":[-3.1649289131,40.6262207031],"type":"Point"}
}