{
  "type": "Feature",
  "properties": {
    "addr:full":"Calle de Vendeja, 20 Malaga M\u00e1laga 29001",
    "addr:housenumber":"20",
    "addr:postcode":"29001",
    "addr:street":"Calle De Vendeja;Ma\u0301Laga",
    "iso:country":"ES",
    "sg:address":"Calle de Vendeja, 20",
    "sg:city":"Malaga",
    "sg:orig_category":"Molduras, Junquillos, Listones Y Molduras Perforadas",
    "sg:phone":"+34 952 22 48 44",
    "sg:postcode":"29001",
    "sg:province":"M\u00e1laga",
    "wof:name":"Ruiz Mancera Francisco",
    "wof:placetype":"venue"
},
  "geometry": {"coordinates":[-4.4225621223,36.7167243958],"type":"Point"}
}