{
  "type": "Feature",
  "properties": {
    "addr:full":"Carrer de Aribau, 103 Barcelona Barcelona 08036",
    "addr:housenumber":"103",
    "addr:postcode":"08036",
    "addr:street":"Carrer De Aribau",
    "iso:country":"ES",
    "sg:address":"Carrer de Aribau, 103",
    "sg:city":"Barcelona",
    "sg:orig_category":"M\u00c9dicos: Psiquiatr\u00cda",
    "sg:phone":"+34 934 53 35 13",
    "sg:postcode":"08036",
    "sg:province":"Barcelona",
    "wof:name":"Gabaldon Fraile Sabel",
    "wof:placetype":"venue"
},
  "geometry": {"coordinates":[2.1565220356,41.3903541565],"type":"Point"}
}