{
  "type": "Feature",
  "properties": {
    "iso:country":"ES",
    "sg:address":"Calle de Mayor, 15",
    "sg:city":"S. Isidro",
    "sg:orig_category":"Reposter\u00cdas",
    "sg:phone":"+34 965 48 75 56",
    "sg:postcode":"03349",
    "sg:province":"Alicante",
    "wof:name":"Horno Genares S.l.",
    "wof:placetype":"venue"
},
  "geometry": {"coordinates":[-0.8371959925,38.1715888977],"type":"Point"}
}