{
  "type": "Feature",
  "properties": {
    "addr:full":"Calle de Villaverde, 3 Pola De Siero Asturias 33510",
    "addr:housenumber":"3",
    "addr:postcode":"33510",
    "addr:street":"Calle De Villaverde",
    "iso:country":"ES",
    "sg:address":"Calle de Villaverde, 3",
    "sg:city":"Pola De Siero",
    "sg:orig_category":"M\u00c9dicos: Estomatolog\u00cda",
    "sg:phone":"+34 985 72 42 70",
    "sg:postcode":"33510",
    "sg:province":"Asturias",
    "wof:name":"Vigil-escalera Guisasola S.l.",
    "wof:placetype":"venue"
},
  "geometry": {"coordinates":[-5.6615819931,43.3926887512],"type":"Point"}
}