{
  "type": "Feature",
  "properties": {
    "addr:full":"Cmno Paredes, S/n Paredes Asturias 33420",
    "addr:housenumber":"s / n",
    "addr:postcode":"33420",
    "addr:street":"Cmno Paredes",
    "iso:country":"ES",
    "sg:address":"Cmno Paredes, S/n",
    "sg:city":"Paredes",
    "sg:orig_category":"Ropa Para Se\u00d1oras (al Por Menor)",
    "sg:phone":"+34 985 26 81 35",
    "sg:postcode":"33420",
    "sg:province":"Asturias",
    "wof:name":"Punto Roma S.l.",
    "wof:placetype":"venue"
},
  "geometry": {"coordinates":[-5.8106489182,43.4009132385],"type":"Point"}
}