{
  "type": "Feature",
  "properties": {
    "addr:full":"Calle de Raimundo Fernandez Villaverde, 39 Madrid Madrid 28003",
    "addr:housenumber":"39",
    "addr:postcode":"madrid;28003",
    "addr:street":"Calle De Raimundo Fernandez Villaverde",
    "iso:country":"ES",
    "sg:address":"Calle de Raimundo Fernandez Villaverde, 39",
    "sg:city":"Madrid",
    "sg:orig_category":"Electricidad, Electr\u00d3nica: Material Y Suministros (al Por Mayor)",
    "sg:phone":"+34 915 35 19 35",
    "sg:postcode":"28003",
    "sg:province":"Madrid",
    "wof:name":"Redu-body S.l.",
    "wof:placetype":"venue"
},
  "geometry": {"coordinates":[-3.699534893,40.4467468262],"type":"Point"}
}