{
  "type": "Feature",
  "properties": {
    "addr:full":"Calle de Fray Zacarias Martinez, 9 Vitoria-gasteiz \u00c1lava 01001",
    "addr:housenumber":"9",
    "addr:postcode":"01001",
    "addr:street":"Calle De Fray Zacarias Martinez",
    "iso:country":"ES",
    "sg:address":"Calle de Fray Zacarias Martinez, 9",
    "sg:city":"Vitoria-gasteiz",
    "sg:orig_category":"Electricidad: Instaladores",
    "sg:phone":"+34 945 14 04 90",
    "sg:postcode":"01001",
    "sg:province":"\u00c1lava",
    "wof:name":"Electricidad Ardu S.l.",
    "wof:placetype":"venue"
},
  "geometry": {"coordinates":[-2.6729559898,42.8503494263],"type":"Point"}
}