{
  "type": "Feature",
  "properties": {
    "iso:country":"ES",
    "sg:address":"Pl Urquinaona, 6",
    "sg:city":"Barcelona",
    "sg:orig_category":"Urbanistas",
    "sg:phone":"+34 933 18 64 76",
    "sg:postcode":"08010",
    "sg:province":"Barcelona",
    "wof:name":"Prats De Cerdanya S. A.",
    "wof:placetype":"venue"
},
  "geometry": {"coordinates":[2.1731050014,41.389629364],"type":"Point"}
}