{
  "type": "Feature",
  "properties": {
    "addr:full":"Calle de San Claudio, 7 Le\u00f3n Le\u00f3n 24004",
    "addr:housenumber":"7",
    "addr:postcode":"24004",
    "addr:street":"Calle De San Claudio;Leo\u0301N",
    "iso:country":"ES",
    "sg:address":"Calle de San Claudio, 7",
    "sg:city":"Le\u00f3n",
    "sg:orig_category":"Tiendas De Grano, Frutas Y Legumbres Secas (al Por Menor)",
    "sg:phone":"+34 987 26 06 46",
    "sg:postcode":"24004",
    "sg:province":"Le\u00f3n",
    "wof:name":"Rodriguez Garcia Jesus Antonio",
    "wof:placetype":"venue"
},
  "geometry": {"coordinates":[-5.5736160278,42.5917434692],"type":"Point"}
}