{
  "type": "Feature",
  "properties": {
    "iso:country":"ES",
    "sg:address":"Rua Rai\u00d1a (da), 6",
    "sg:city":"Lugo",
    "sg:orig_category":"Dorados, Plater\u00cda (orfebrer\u00cda)",
    "sg:phone":"+34 982 22 19 62",
    "sg:postcode":"27001",
    "sg:province":"Lugo",
    "wof:name":"Dominguez Casais Adolfo",
    "wof:placetype":"venue"
},
  "geometry": {"coordinates":[-7.5558209419,43.0110092163],"type":"Point"}
}