{
  "type": "Feature",
  "properties": {
    "iso:country":"ES",
    "sg:address":"Avda Alicante, 7",
    "sg:city":"Denia",
    "sg:orig_category":"Venta, Colocaci\u00d3n De Autoradios",
    "sg:phone":"+34 965 78 39 44",
    "sg:postcode":"03700",
    "sg:province":"Alicante",
    "wof:name":"Equipamientos Sapena S.l.",
    "wof:placetype":"venue"
},
  "geometry": {"coordinates":[0.1039299965,38.8374519348],"type":"Point"}
}