{
  "type": "Feature",
  "properties": {
    "addr:full":"Calle de Villa De Plentzia, 28 Arenas -areeta Vizcaya 48930",
    "addr:housenumber":"28;areeta",
    "addr:postcode":"48930",
    "addr:street":"Calle De Villa De Plentzia",
    "iso:country":"ES",
    "sg:address":"Calle de Villa De Plentzia, 28",
    "sg:city":"Arenas -areeta",
    "sg:orig_category":"Agencias Y Agentes Comerciales, Representantes",
    "sg:phone":"+34 944 63 07 65",
    "sg:postcode":"48930",
    "sg:province":"Vizcaya",
    "wof:name":"Burga\u00f1o Cobo Maria Del Mar",
    "wof:placetype":"venue"
},
  "geometry": {"coordinates":[-3.0039970875,43.3328742981],"type":"Point"}
}