{
  "type": "Feature",
  "properties": {
    "iso:country":"ES",
    "sg:address":"Calle de Elorri, 6",
    "sg:city":"Getxo",
    "sg:orig_category":"Mec\u00c1nico Del Autom\u00d3vil",
    "sg:phone":"+34 944 06 03 79",
    "sg:postcode":"48990",
    "sg:province":"Vizcaya",
    "wof:name":"Tomas De Benito Valencia",
    "wof:placetype":"venue"
},
  "geometry": {"coordinates":[-3.008605957,43.3539848328],"type":"Point"}
}