{
  "type": "Feature",
  "properties": {
    "iso:country":"ES",
    "sg:address":"Carrer de Major, 3",
    "sg:city":"S. Feliu Guixols",
    "sg:orig_category":"Ropa Para Se\u00d1oras (al Por Menor)",
    "sg:phone":"+34 972 32 04 21",
    "sg:postcode":"17220",
    "sg:province":"Girona",
    "wof:name":"Rabell Rigau Jorge",
    "wof:placetype":"venue"
},
  "geometry": {"coordinates":[3.0298631191,41.7814788818],"type":"Point"}
}