{
  "type": "Feature",
  "properties": {
    "iso:country":"ES",
    "sg:address":"Av Joan Miro, 313",
    "sg:city":"Sant Agusti",
    "sg:orig_category":"Centros Empresariales",
    "sg:phone":"+34 971 70 75 15",
    "sg:postcode":"07015",
    "sg:province":"Islas Baleares",
    "wof:name":"Garguti Servicios S.l.",
    "wof:placetype":"venue"
},
  "geometry": {"coordinates":[2.6002969742,39.5512161255],"type":"Point"}
}