{
  "type": "Feature",
  "properties": {
    "addr:full":"Moscosa-gusende, S/n Campo Ledesma Salamanca 37140",
    "addr:housenumber":"/ n",
    "addr:postcode":"37140",
    "addr:street":"Moscosa-Gusende S",
    "iso:country":"ES",
    "sg:address":"Moscosa-gusende, S/n",
    "sg:city":"Campo Ledesma",
    "sg:orig_category":"Cr\u00cda De Animales",
    "sg:phone":"+34 923 16 60 99",
    "sg:postcode":"37140",
    "sg:province":"Salamanca",
    "wof:name":"Explotaciones Ganaderas Salmantinas S.a.",
    "wof:placetype":"venue"
},
  "geometry": {"coordinates":[-6.1015210152,41.113445282],"type":"Point"}
}