{
  "type": "Feature",
  "properties": {
    "addr:full":"Calle de Arroyo De San Lorenzo, 2 Cordoba C\u00f3rdoba 14002",
    "addr:housenumber":"2",
    "addr:postcode":"14002",
    "addr:street":"Calle De Arroyo De San Lorenzo;Co\u0301Rdoba",
    "iso:country":"ES",
    "sg:address":"Calle de Arroyo De San Lorenzo, 2",
    "sg:city":"Cordoba",
    "sg:orig_category":"Plomeros",
    "sg:phone":"+34 957 49 18 94",
    "sg:postcode":"14002",
    "sg:province":"C\u00f3rdoba",
    "wof:name":"Fonrala S.l.",
    "wof:placetype":"venue"
},
  "geometry": {"coordinates":[-4.7694044113,37.8879776001],"type":"Point"}
}