{
  "type": "Feature",
  "properties": {
    "iso:country":"ES",
    "sg:address":"Avda Aguirre Lehendakari, 159",
    "sg:city":"Bilbao",
    "sg:orig_category":"Farmacias",
    "sg:phone":"+34 944 76 13 92",
    "sg:postcode":"48015",
    "sg:province":"Vizcaya",
    "sg:website":"ilinazap@medinet.com",
    "wof:name":"Linaza Pe\u00f1a I\u00f1aki",
    "wof:placetype":"venue"
},
  "geometry": {"coordinates":[-2.9615559578,43.2788658142],"type":"Point"}
}