{
  "type": "Feature",
  "properties": {
    "addr:full":"Vali\u00f1o, S/n Mondo\u00f1edo Lugo 27740",
    "addr:postcode":"27740",
    "addr:street":"Valin\u0303O S / N",
    "iso:country":"ES",
    "sg:address":"Vali\u00f1o, S/n",
    "sg:city":"Mondo\u00f1edo",
    "sg:orig_category":"Empresas De Carpinter\u00cda Met\u00c1lica",
    "sg:phone":"+34 982 52 14 36",
    "sg:postcode":"27740",
    "sg:province":"Lugo",
    "wof:name":"Gonzalez Basanta Jose Antonio",
    "wof:placetype":"venue"
},
  "geometry": {"coordinates":[-7.3697309494,43.4380378723],"type":"Point"}
}