{
  "type": "Feature",
  "properties": {
    "addr:full":"Calle de Generacion, 43 Malaga M\u00e1laga 29006",
    "addr:housenumber":"43",
    "addr:postcode":"29006",
    "addr:street":"Calle De Generacion;Ma\u0301Laga",
    "iso:country":"ES",
    "sg:address":"Calle de Generacion, 43",
    "sg:city":"Malaga",
    "sg:orig_category":"Bebidas",
    "sg:phone":"+34 952 17 96 05",
    "sg:postcode":"29006",
    "sg:province":"M\u00e1laga",
    "wof:name":"Distribuciones De Bebidas Santaella S.l.",
    "wof:placetype":"venue"
},
  "geometry": {"coordinates":[-4.51060009,36.7031517029],"type":"Point"}
}