{
  "type": "Feature",
  "properties": {
    "addr:full":"Pase Landabarri Bidea, 50 Landabarri Vizcaya 48940",
    "addr:housenumber":"50",
    "addr:postcode":"48940",
    "addr:street":"Landabarri Bidea",
    "iso:country":"ES",
    "sg:address":"Pase Landabarri Bidea, 50",
    "sg:city":"Landabarri",
    "sg:orig_category":"Inmobiliaria (agencias)",
    "sg:phone":"+34 944 80 09 58",
    "sg:postcode":"48940",
    "sg:province":"Vizcaya",
    "wof:name":"Bartolome Yarza Carmen",
    "wof:placetype":"venue"
},
  "geometry": {"coordinates":[-2.9860789776,43.3275489807],"type":"Point"}
}