{
  "type": "Feature",
  "properties": {
    "iso:country":"ES",
    "sg:address":"Pol Ind Polirrosa, S/n",
    "sg:city":"Huelva",
    "sg:orig_category":"Empresas De Carpinter\u00cda De Madera",
    "sg:phone":"+34 959 23 59 55",
    "sg:postcode":"21007",
    "sg:province":"Huelva",
    "wof:name":"Jerez Arroyo Teresa",
    "wof:placetype":"venue"
},
  "geometry": {"coordinates":[-6.9495940208,37.256313324],"type":"Point"}
}