{
  "type": "Feature",
  "properties": {
    "addr:full":"Calle de Canalejas, 40 Almoradi Alicante 03160",
    "addr:housenumber":"40",
    "addr:postcode":"03160",
    "addr:street":"Calle De Canalejas",
    "iso:country":"ES",
    "sg:address":"Calle de Canalejas, 40",
    "sg:city":"Almoradi",
    "sg:orig_category":"Electricidad Veh\u00cdculo",
    "sg:phone":"+34 965 70 14 36",
    "sg:postcode":"03160",
    "sg:province":"Alicante",
    "wof:name":"Lopez Montiel Juan Carlos",
    "wof:placetype":"venue"
},
  "geometry": {"coordinates":[-0.7907127142,38.1127243042],"type":"Point"}
}