{
  "type": "Feature",
  "properties": {
    "addr:full":"Pla\u00c7 Major, 2 Pollen\u00e7a Islas Baleares 07460",
    "addr:housenumber":"2",
    "addr:postcode":"07460",
    "addr:street":"Pollenc\u0327A",
    "iso:country":"ES",
    "sg:address":"Pla\u00c7 Major, 2",
    "sg:city":"Pollen\u00e7a",
    "sg:orig_category":"Electrodom\u00c9sticos (al Por Menor)",
    "sg:phone":"+34 971 53 42 14",
    "sg:postcode":"07460",
    "sg:province":"Islas Baleares",
    "wof:name":"Alborada S.a.",
    "wof:placetype":"venue"
},
  "geometry": {"coordinates":[3.0375914574,39.8799629211],"type":"Point"}
}