{
  "type": "Feature",
  "properties": {
    "iso:country":"ES",
    "sg:address":"Calle de Rey Fernando, 2",
    "sg:city":"Baena",
    "sg:orig_category":"Estilistas Y Estudios De Estilo De Corte Y Confecci\u00d3n",
    "sg:phone":"+34 957 67 20 01",
    "sg:postcode":"14850",
    "sg:province":"C\u00f3rdoba",
    "wof:name":"Marroquineria Nilo S.l.",
    "wof:placetype":"venue"
},
  "geometry": {"coordinates":[-4.323237896,37.6186027527],"type":"Point"}
}