{
  "type": "Feature",
  "properties": {
    "iso:country":"ES",
    "sg:address":"Carr Maluquer Salvador, 20",
    "sg:city":"Girona",
    "sg:orig_category":"Agencias De Trabajo Temporal",
    "sg:phone":"+34 972 21 05 36",
    "sg:postcode":"17002",
    "sg:province":"Girona",
    "wof:name":"Laborman Trabajo Temporal Ett S.a.",
    "wof:placetype":"venue"
},
  "geometry": {"coordinates":[2.821625948,41.9765815735],"type":"Point"}
}