{
  "type": "Feature",
  "properties": {
    "addr:full":"Calle de Mar Baltico, 6 Madrid Madrid 28033",
    "addr:housenumber":"6",
    "addr:postcode":"28033",
    "addr:street":"Calle De Mar Baltico",
    "iso:country":"ES",
    "sg:address":"Calle de Mar Baltico, 6",
    "sg:city":"Madrid",
    "sg:orig_category":"Asociaciones, Organismos Culturales Y Socioeducativos",
    "sg:phone":"+34 913 81 50 64",
    "sg:postcode":"28033",
    "sg:province":"Madrid",
    "wof:name":"Caritas Diocesana De Madrid",
    "wof:placetype":"venue"
},
  "geometry": {"coordinates":[-3.6426320076,40.4736671448],"type":"Point"}
}