{
  "type": "Feature",
  "properties": {
    "iso:country":"ES",
    "sg:address":"Carr Sindicat, 22",
    "sg:city":"Soses",
    "sg:orig_category":"Poller\u00cda Y Caza (al Por Menor)",
    "sg:phone":"+34 973 79 72 84",
    "sg:postcode":"25181",
    "sg:province":"Lleida",
    "wof:name":"Lopez Diez Carlos",
    "wof:placetype":"venue"
},
  "geometry": {"coordinates":[0.4877899885,41.5330886841],"type":"Point"}
}