{
  "type": "Feature",
  "properties": {
    "addr:full":"Calle de Sor Angela De La Cruz, 27 Madrid Madrid 28020",
    "addr:housenumber":"27",
    "addr:postcode":"madrid;28020",
    "addr:street":"Calle De Sor Angela De La Cruz",
    "iso:country":"ES",
    "sg:address":"Calle de Sor Angela De La Cruz, 27",
    "sg:city":"Madrid",
    "sg:orig_category":"Supermercados Y Hipermercados",
    "sg:phone":"+34 915 71 52 18",
    "sg:postcode":"28020",
    "sg:province":"Madrid",
    "sg:website":"www.capraboacasa.com",
    "wof:name":"Caprabo S.a.",
    "wof:placetype":"venue"
},
  "geometry": {"coordinates":[-3.6965689659,40.4600715637],"type":"Point"}
}