{
  "type": "Feature",
  "properties": {
    "addr:full":"Calle de Jose Montes, 6 Arriate M\u00e1laga 29350",
    "addr:housenumber":"6",
    "addr:postcode":"29350",
    "addr:street":"Calle De Jose Montes;Ma\u0301Laga",
    "iso:country":"ES",
    "sg:address":"Calle de Jose Montes, 6",
    "sg:city":"Arriate",
    "sg:orig_category":"M\u00c1quinas Y Material Para La Industria De La Alimentaci\u00d3n",
    "sg:phone":"+34 952 16 50 77",
    "sg:postcode":"29350",
    "sg:province":"M\u00e1laga",
    "wof:name":"Panaderia Miramon S.l.",
    "wof:placetype":"venue"
},
  "geometry": {"coordinates":[-5.1408410072,36.7984275818],"type":"Point"}
}