{
  "type": "Feature",
  "properties": {
    "iso:country":"ES",
    "sg:address":"Rbla Jaume I, 35",
    "sg:city":"Cambrils",
    "sg:classifiers":[
        {
            "category":"Personal",
            "subcategory":"Barber",
            "type":"Services"
        }
    ],
    "sg:phone":"+34 977 36 35 23",
    "sg:postcode":"43850",
    "sg:province":"Tarragona",
    "sg:tags":[
        "caballeros",
        "de",
        "peluqueros"
    ],
    "wof:name":"Garcia Diaz Noemi",
    "wof:placetype":"venue"
},
  "geometry": {"coordinates":[1.0622099638,41.0674705505],"type":"Point"}
}