{
  "type": "Feature",
  "properties": {
    "addr:full":"Avgd De Francisco Cerda, 52 Ontinyent Valencia 46870",
    "addr:housenumber":"52",
    "addr:postcode":"46870",
    "addr:street":"Cerda",
    "iso:country":"ES",
    "sg:address":"Avgd De Francisco Cerda, 52",
    "sg:city":"Ontinyent",
    "sg:orig_category":"Empresarios",
    "sg:phone":"+34 962 38 39 05",
    "sg:postcode":"46870",
    "sg:province":"Valencia",
    "wof:name":"Forem P.v.",
    "wof:placetype":"venue"
},
  "geometry": {"coordinates":[-0.6005179882,38.8200569153],"type":"Point"}
}