{
  "type": "Feature",
  "properties": {
    "addr:full":"Ctra Almodovar, 2 Puertollano Ciudad Real 13500",
    "addr:housenumber":"2",
    "addr:postcode":"13500",
    "addr:street":"Ctra Almodovar",
    "iso:country":"ES",
    "sg:address":"Ctra Almodovar, 2",
    "sg:city":"Puertollano",
    "sg:orig_category":"Molduras, Junquillos, Listones Y Molduras Perforadas",
    "sg:phone":"+34 926 41 17 44",
    "sg:postcode":"13500",
    "sg:province":"Ciudad Real",
    "wof:name":"Recreativos Chicharro S.l.",
    "wof:placetype":"venue"
},
  "geometry": {"coordinates":[-4.1112709045,38.7010421753],"type":"Point"}
}