{
  "type": "Feature",
  "properties": {
    "iso:country":"ES",
    "sg:address":"Calle de Estartetxe, 5",
    "sg:city":"Estartetxe",
    "sg:orig_category":"Laboratorios Farmac\u00c9uticos",
    "sg:phone":"+34 944 31 61 27",
    "sg:postcode":"48940",
    "sg:province":"Vizcaya",
    "wof:name":"Laboratorios Normon S.a.",
    "wof:placetype":"venue"
},
  "geometry": {"coordinates":[-2.9860789776,43.3275489807],"type":"Point"}
}