{
  "type": "Feature",
  "properties": {
    "iso:country":"ES",
    "sg:address":"Calle de Novelda, 22",
    "sg:city":"San Vicente Del Raspeig-sant Vicent Del Raspeig",
    "sg:orig_category":"Agencias Y Agentes Comerciales, Representantes",
    "sg:phone":"+34 965 67 31 89",
    "sg:postcode":"03690",
    "sg:province":"Alicante",
    "wof:name":"Gomis Roman Jose Joaquin",
    "wof:placetype":"venue"
},
  "geometry": {"coordinates":[-0.5308750272,38.3988723755],"type":"Point"}
}