{
  "type": "Feature",
  "properties": {
    "addr:full":"Ctra Ronda, 40 Baza Granada 18800",
    "addr:housenumber":"40",
    "addr:postcode":"18800",
    "addr:street":"Ctra Ronda",
    "iso:country":"ES",
    "sg:address":"Ctra Ronda, 40",
    "sg:city":"Baza",
    "sg:orig_category":"Abogados",
    "sg:phone":"+34 958 70 03 72",
    "sg:postcode":"18800",
    "sg:province":"Granada",
    "wof:name":"Rodriguez Sanchez Jose Angel",
    "wof:placetype":"venue"
},
  "geometry": {"coordinates":[-2.7776100636,37.4884681702],"type":"Point"}
}