{
  "type": "Feature",
  "properties": {
    "addr:full":"Carr Navata, 31 Badalona Barcelona 08917",
    "addr:housenumber":"31",
    "addr:postcode":"08917",
    "addr:street":"Carr Navata",
    "iso:country":"ES",
    "sg:address":"Carr Navata, 31",
    "sg:city":"Badalona",
    "sg:orig_category":"Empresas De Carpinter\u00cda Met\u00c1lica",
    "sg:phone":"+34 933 97 62 00",
    "sg:postcode":"08917",
    "sg:province":"Barcelona",
    "wof:name":"Garcia Martin Basilio",
    "wof:placetype":"venue"
},
  "geometry": {"coordinates":[2.2257289886,41.4515151978],"type":"Point"}
}