{
  "type": "Feature",
  "properties": {
    "addr:full":"Calle de Calvario, S/n Saelices Cuenca 16430",
    "addr:housenumber":"s / n",
    "addr:postcode":"16430",
    "addr:street":"Calle De Calvario",
    "iso:country":"ES",
    "sg:address":"Calle de Calvario, S/n",
    "sg:city":"Saelices",
    "sg:orig_category":"Contenedores (mercanc\u00cdas)",
    "sg:phone":"+34 969 13 20 74",
    "sg:postcode":"16430",
    "sg:province":"Cuenca",
    "wof:name":"Mu\u00f1oz Villanueva Jose Luis",
    "wof:placetype":"venue"
},
  "geometry": {"coordinates":[-2.8036735058,39.9184265137],"type":"Point"}
}