{
  "type": "Feature",
  "properties": {
    "iso:country":"ES",
    "sg:address":"Avda Aragon, 5",
    "sg:city":"Cantavieja",
    "sg:orig_category":"Panader\u00cdas, Panader\u00cdas",
    "sg:phone":"+34 964 18 52 38",
    "sg:postcode":"44140",
    "sg:province":"Teruel",
    "wof:name":"Tena Simon Amparo",
    "wof:placetype":"venue"
},
  "geometry": {"coordinates":[-0.4060609937,40.5269470215],"type":"Point"}
}