{
  "type": "Feature",
  "properties": {
    "addr:full":"Calle de Capuchinos, 4 Carmen Murcia 30002",
    "addr:housenumber":"4",
    "addr:postcode":"30002",
    "addr:street":"Calle De Capuchinos",
    "iso:country":"ES",
    "sg:address":"Calle de Capuchinos, 4",
    "sg:city":"Carmen",
    "sg:orig_category":"Inform\u00c1tica: Material Y Suministros",
    "sg:phone":"+34 968 26 88 39",
    "sg:postcode":"30002",
    "sg:province":"Murcia",
    "sg:website":"www.phuc.es",
    "wof:name":"Relojeria Valverde S.a.",
    "wof:placetype":"venue"
},
  "geometry": {"coordinates":[-1.1298867464,37.9834747314],"type":"Point"}
}