{
  "type": "Feature",
  "properties": {
    "iso:country":"ES",
    "sg:address":"Calle de Puerto Del Aire, 6",
    "sg:city":"Campotejar",
    "sg:orig_category":"Cerrajer\u00cda, Ferrallista",
    "sg:phone":"+34 958 39 51 27",
    "sg:postcode":"18565",
    "sg:province":"Granada",
    "wof:name":"Hermanos Ramos C.b.",
    "wof:placetype":"venue"
},
  "geometry": {"coordinates":[-3.615044117,37.4830436707],"type":"Point"}
}