{
  "type": "Feature",
  "properties": {
    "iso:country":"ES",
    "sg:address":"Avda Plaza De Toros, 1",
    "sg:city":"Aranjuez",
    "sg:orig_category":"Asesor\u00cda Sobre Comunicaci\u00d3n De Empresas",
    "sg:phone":"+34 918 92 94 42",
    "sg:postcode":"28300",
    "sg:province":"Madrid",
    "wof:name":"Union De Asesores Tributarios S.l.",
    "wof:placetype":"venue"
},
  "geometry": {"coordinates":[-3.6054089069,40.027973175],"type":"Point"}
}