{
  "type": "Feature",
  "properties": {
    "iso:country":"ES",
    "sg:address":"Avda Libertad De La, 32",
    "sg:city":"Donostia-san Sebastian",
    "sg:orig_category":"Abogados",
    "sg:phone":"+34 943 42 75 55",
    "sg:postcode":"20004",
    "sg:province":"Guip\u00f9zcoa",
    "wof:name":"Arambarri Abogados S. L.",
    "wof:placetype":"venue"
},
  "geometry": {"coordinates":[-1.9829845428,43.3192939758],"type":"Point"}
}