{
  "type": "Feature",
  "properties": {
    "addr:full":"Calle de Fajardo, 8 Arrecife Las Palmas 35500",
    "addr:housenumber":"8",
    "addr:postcode":"35500",
    "addr:street":"Calle De Fajardo",
    "iso:country":"ES",
    "sg:address":"Calle de Fajardo, 8",
    "sg:city":"Arrecife",
    "sg:orig_category":"Arquitectos",
    "sg:phone":"+34 928 81 02 85",
    "sg:postcode":"35500",
    "sg:province":"Las Palmas",
    "wof:name":"Estudio Tecnico S.l.",
    "wof:placetype":"venue"
},
  "geometry": {"coordinates":[-13.5496692657,28.9601745605],"type":"Point"}
}