{
  "type": "Feature",
  "properties": {
    "addr:full":"Calle de Bri\u00d1as Luis, 9 Bilbao Vizcaya 48013",
    "addr:housenumber":"9",
    "addr:postcode":"48013",
    "addr:street":"Calle De Brin\u0303As Luis",
    "iso:country":"ES",
    "sg:address":"Calle de Bri\u00d1as Luis, 9",
    "sg:city":"Bilbao",
    "sg:orig_category":"Asesor\u00cda, Estudio Y Control Medioambiental",
    "sg:phone":"+34 944 41 09 37",
    "sg:postcode":"48013",
    "sg:province":"Vizcaya",
    "sg:website":"www.environmentandsistem.com",
    "wof:name":"Enviroment And Systems S.a.",
    "wof:placetype":"venue"
},
  "geometry": {"coordinates":[-2.9474239349,43.2627754211],"type":"Point"}
}