{
  "type": "Feature",
  "properties": {
    "iso:country":"ES",
    "sg:address":"Carrer de Taquigraf Serra, 18",
    "sg:city":"Barcelona",
    "sg:orig_category":"Asesor\u00cdas Y Estudios Financieros",
    "sg:phone":"+34 934 05 03 93",
    "sg:postcode":"08029",
    "sg:province":"Barcelona",
    "wof:name":"Bacs Consultant Fiscal Contable Laboral S.l.",
    "wof:placetype":"venue"
},
  "geometry": {"coordinates":[2.1400370598,41.3864173889],"type":"Point"}
}