{
  "type": "Feature",
  "properties": {
    "iso:country":"ES",
    "sg:address":"Calle de Canovas Del Castillo, 31",
    "sg:city":"Cadiz",
    "sg:orig_category":"Tapiceros Y Tapiceros",
    "sg:phone":"+34 956 22 74 12",
    "sg:postcode":"11001",
    "sg:province":"C\u00e1diz",
    "wof:name":"Ramos Manzano Manuel",
    "wof:placetype":"venue"
},
  "geometry": {"coordinates":[-6.2966790199,36.5335121155],"type":"Point"}
}