{
  "type": "Feature",
  "properties": {
    "iso:country":"ES",
    "sg:address":"Pg Pere Iii, 71",
    "sg:city":"Manresa",
    "sg:orig_category":"Peluqueros: De Se\u00d1oras",
    "sg:phone":"+34 938 74 47 61",
    "sg:postcode":"08242",
    "sg:province":"Barcelona",
    "wof:name":"Peluqueria Comarcal Styl S. C. C. L.",
    "wof:placetype":"venue"
},
  "geometry": {"coordinates":[1.828668952,41.7306938171],"type":"Point"}
}