{
  "type": "Feature",
  "properties": {
    "iso:country":"ES",
    "sg:address":"Ignacio Zuloaga Kalea, 6",
    "sg:city":"Arrasate",
    "sg:orig_category":"Partidos Pol\u00cdticos",
    "sg:phone":"+34 943 71 27 88",
    "sg:postcode":"20500",
    "sg:province":"Guip\u00f9zcoa",
    "wof:name":"Eusko Alkartasuna",
    "wof:placetype":"venue"
},
  "geometry": {"coordinates":[-2.4905159473,43.0666122437],"type":"Point"}
}