{
  "type": "Feature",
  "properties": {
    "iso:country":"ES",
    "sg:address":"Calle de Raco D'ademus, 8",
    "sg:city":"Alaquas",
    "sg:orig_category":"Fabricaci\u00d3n De Muebles",
    "sg:phone":"+34 961 51 06 90",
    "sg:postcode":"46970",
    "sg:province":"Valencia",
    "sg:website":"www.viveti.net",
    "wof:name":"Viveti Mobel S.l.u.",
    "wof:placetype":"venue"
},
  "geometry": {"coordinates":[-0.4652498066,39.4494361877],"type":"Point"}
}