{
  "type": "Feature",
  "properties": {
    "iso:country":"ES",
    "sg:address":"Calle de Monte De Piedad, 12",
    "sg:city":"Le\u00f3n",
    "sg:orig_category":"Transportes Por V\u00cdas Navegables",
    "sg:phone":"+34 987 24 97 22",
    "sg:postcode":"24008",
    "sg:province":"Le\u00f3n",
    "wof:name":"Mieres Mieres Andres",
    "wof:placetype":"venue"
},
  "geometry": {"coordinates":[-5.5724711418,42.6085014343],"type":"Point"}
}