{
  "type": "Feature",
  "properties": {
    "addr:full":"Calle de Vicente Blasco Iba\u00d1ez, 61 Torrevieja Alicante 03180",
    "addr:housenumber":"61",
    "addr:postcode":"03180",
    "addr:street":"Calle De Vicente Blasco Iban\u0303Ez",
    "iso:country":"ES",
    "sg:address":"Calle de Vicente Blasco Iba\u00d1ez, 61",
    "sg:city":"Torrevieja",
    "sg:orig_category":"Ense\u00d1anza: Comercio, Gesti\u00d3n, Inform\u00c1tica",
    "sg:phone":"+34 965 71 65 66",
    "sg:postcode":"03180",
    "sg:province":"Alicante",
    "wof:name":"Informatica Torrevieja S.l",
    "wof:placetype":"venue"
},
  "geometry": {"coordinates":[-0.6791239977,37.979019165],"type":"Point"}
}