{
  "type": "Feature",
  "properties": {
    "addr:full":"Calle de Angel Guimera, 47 Valencia Valencia 46008",
    "addr:housenumber":"47",
    "addr:postcode":"46008",
    "addr:street":"Calle De Angel Guimera",
    "iso:country":"ES",
    "sg:address":"Calle de Angel Guimera, 47",
    "sg:city":"Valencia",
    "sg:classifiers":[
        {
            "category":"Autos & Motor Vehicles",
            "subcategory":"Automobile Sales",
            "type":"Retail Goods"
        }
    ],
    "sg:phone":"+34 963 82 54 20",
    "sg:postcode":"46008",
    "sg:province":"Valencia",
    "sg:website":"www.centrovial.com",
    "wof:name":"Centrovial S.coop.v.",
    "wof:placetype":"venue"
},
  "geometry": {"coordinates":[-0.3886654973,39.469543457],"type":"Point"}
}