{
  "type": "Feature",
  "properties": {
    "addr:full":"C/ Reina Victoria, 73 Elche Alicante 03201",
    "addr:housenumber":"73",
    "addr:postcode":"03201",
    "addr:street":"C / Reina Victoria",
    "iso:country":"ES",
    "sg:address":"C/ Reina Victoria, 73",
    "sg:city":"Elche",
    "sg:orig_category":"Farmacias",
    "sg:phone":"+34 965 44 49 38",
    "sg:postcode":"03201",
    "sg:province":"Alicante",
    "wof:name":"Agullo Pi\u00f1ol Pablo",
    "wof:placetype":"venue"
},
  "geometry": {"coordinates":[-0.7060434222,38.2654304504],"type":"Point"}
}