{
  "type": "Feature",
  "properties": {
    "iso:country":"ES",
    "sg:address":"Carrer de Borriana, 69",
    "sg:city":"Barcelona",
    "sg:orig_category":"Venta, Instalaci\u00d3n De Cocinas",
    "sg:phone":"+34 933 46 48 53",
    "sg:postcode":"08030",
    "sg:province":"Barcelona",
    "wof:name":"Soler Cuixar Pedro",
    "wof:placetype":"venue"
},
  "geometry": {"coordinates":[2.1923120022,41.4308242798],"type":"Point"}
}