{
  "type": "Feature",
  "properties": {
    "iso:country":"ES",
    "sg:address":"Calle de San Juan De Dios, 17",
    "sg:city":"Vitigudino",
    "sg:orig_category":"Promotores Constructores",
    "sg:phone":"+34 923 50 12 07",
    "sg:postcode":"37210",
    "sg:province":"Salamanca",
    "wof:name":"Construcciones Angel Sevillano S.l.",
    "wof:placetype":"venue"
},
  "geometry": {"coordinates":[-6.4356589317,41.0096893311],"type":"Point"}
}