{
  "type": "Feature",
  "properties": {
    "iso:country":"ES",
    "sg:address":"Calle de Mu\u00d1oz Torrero, 2",
    "sg:city":"Badajoz",
    "sg:orig_category":"Servidores Y Editores De Bases De Datos",
    "sg:phone":"+34 924 22 51 56",
    "sg:postcode":"06002",
    "sg:province":"Badajoz",
    "sg:website":"www.planetshow.net",
    "wof:name":"Show Planet S.l.",
    "wof:placetype":"venue"
},
  "geometry": {"coordinates":[-6.9705038071,38.8783035278],"type":"Point"}
}