{
  "type": "Feature",
  "properties": {
    "iso:country":"ES",
    "sg:address":"Electronica (pol Guixeres), 48",
    "sg:city":"Badalona",
    "sg:orig_category":"Armarios Y Cuadros El\u00c9ctricos",
    "sg:phone":"+34 934 65 06 59",
    "sg:postcode":"08915",
    "sg:province":"Barcelona",
    "wof:name":"Automatismos Altronics S.a.",
    "wof:placetype":"venue"
},
  "geometry": {"coordinates":[2.2555799484,41.4609298706],"type":"Point"}
}