{
  "type": "Feature",
  "properties": {
    "addr:full":"Lugar Portor, S/n Negreira La Coru\u00f1a 15830",
    "addr:housenumber":"s / n",
    "addr:postcode":"15830",
    "addr:street":"Lugar Portor;La Corun\u0303A",
    "iso:country":"ES",
    "sg:address":"Lugar Portor, S/n",
    "sg:city":"Negreira",
    "sg:orig_category":"Mec\u00c1nico Del Autom\u00d3vil",
    "sg:phone":"+34 981 88 55 27",
    "sg:postcode":"15830",
    "sg:province":"La Coru\u00f1a",
    "wof:name":"Calo Nieto Jose-maria",
    "wof:placetype":"venue"
},
  "geometry": {"coordinates":[-8.7368841171,42.9089660645],"type":"Point"}
}