{
  "type": "Feature",
  "properties": {
    "addr:full":"Carretera Alcontar, Km. 0001,0 Seron Almer\u00eda 04890",
    "addr:postcode":"04890",
    "addr:street":"Carretera Alcontar Km. 0001,0 Seron Almeri\u0301A",
    "iso:country":"ES",
    "sg:address":"Carretera Alcontar, Km. 0001,0",
    "sg:city":"Seron",
    "sg:orig_category":"Carnicer\u00cdas, Carnicer\u00cdas",
    "sg:phone":"+34 950 42 64 34",
    "sg:postcode":"04890",
    "sg:province":"Almer\u00eda",
    "wof:name":"Casta\u00f1o Cano Antonio",
    "wof:placetype":"venue"
},
  "geometry": {"coordinates":[-2.5226380825,37.3279762268],"type":"Point"}
}