{
  "type": "Feature",
  "properties": {
    "iso:country":"ES",
    "sg:address":"Carrer de Mar (la), 59",
    "sg:city":"Altea",
    "sg:orig_category":"Abogados",
    "sg:phone":"+34 965 84 25 27",
    "sg:postcode":"03590",
    "sg:province":"Alicante",
    "wof:name":"Perez Barber Francisca",
    "wof:placetype":"venue"
},
  "geometry": {"coordinates":[-0.049256999,38.5977935791],"type":"Point"}
}