{
  "type": "Feature",
  "properties": {
    "iso:country":"ES",
    "sg:address":"Ctra. Jimena-san Pablo, S/n",
    "sg:city":"Jimena Frontera",
    "sg:orig_category":"Electrodom\u00c9sticos (al Por Menor)",
    "sg:phone":"+34 956 64 15 89",
    "sg:postcode":"11330",
    "sg:province":"C\u00e1diz",
    "wof:name":"Torre Sanchez Cristobal De La",
    "wof:placetype":"venue"
},
  "geometry": {"coordinates":[-5.4481987953,36.4326057434],"type":"Point"}
}