{
  "type": "Feature",
  "properties": {
    "iso:country":"ES",
    "sg:address":"Calle de Vasco De Gama, 147",
    "sg:city":"Sevilla",
    "sg:orig_category":"Transportes Por V\u00cdas Navegables",
    "sg:phone":"+34 954 65 45 96",
    "sg:postcode":"41006",
    "sg:province":"Sevilla",
    "wof:name":"Cubas Quino S.l.",
    "wof:placetype":"venue"
},
  "geometry": {"coordinates":[-5.9459080696,37.3683052063],"type":"Point"}
}