{
  "type": "Feature",
  "properties": {
    "addr:full":"Calle de Cuadrilla De Laguardia-rioja Alavesa, 1 Vitoria-gasteiz \u00c1lava 01013",
    "addr:housenumber":"1",
    "addr:postcode":"01013",
    "addr:street":"Calle De Cuadrilla De Laguardia-Rioja Alavesa",
    "iso:country":"ES",
    "sg:address":"Calle de Cuadrilla De Laguardia-rioja Alavesa, 1",
    "sg:city":"Vitoria-gasteiz",
    "sg:orig_category":"Asilos De Ancianos. Centros Privados",
    "sg:phone":"+34 945 25 69 00",
    "sg:postcode":"01013",
    "sg:province":"\u00c1lava",
    "wof:name":"Hermanas Mercedarias De La Caridad",
    "wof:placetype":"venue"
},
  "geometry": {"coordinates":[-2.6643743515,42.8586578369],"type":"Point"}
}