{
  "type": "Feature",
  "properties": {
    "iso:country":"ES",
    "sg:address":"Calle de Almirante Carrero Blanco, 37",
    "sg:city":"Coin",
    "sg:orig_category":"Frutas Y Legumbres Frescas (al Por Mayor)",
    "sg:phone":"+34 952 45 13 58",
    "sg:postcode":"29100",
    "sg:province":"M\u00e1laga",
    "wof:name":"Citricos Los Coinos S.l.",
    "wof:placetype":"venue"
},
  "geometry": {"coordinates":[-4.7533831596,36.6618843079],"type":"Point"}
}