{
  "type": "Feature",
  "properties": {
    "addr:full":"Plaz Zaragoza De, 2 Donostia-san Sebastian Guip\u00f9zcoa 20007",
    "addr:postcode":"20007",
    "addr:street":"Plaz",
    "iso:country":"ES",
    "sg:address":"Plaz Zaragoza De, 2",
    "sg:city":"Donostia-san Sebastian",
    "sg:orig_category":"Formaci\u00d3n Continuada (variada)",
    "sg:phone":"+34 943 43 08 11",
    "sg:postcode":"20007",
    "sg:province":"Guip\u00f9zcoa",
    "wof:name":"Lasheras Ochoa Cipriano",
    "wof:placetype":"venue"
},
  "geometry": {"coordinates":[-2.0346250534,43.2695808411],"type":"Point"}
}