{
  "type": "Feature",
  "properties": {
    "addr:full":"Pla\u00c7 Andreu Torrens, 4 Santa Maria Del Cami Islas Baleares 07320",
    "addr:housenumber":"4",
    "addr:postcode":"07320",
    "addr:street":"Torrens;Islas",
    "iso:country":"ES",
    "sg:address":"Pla\u00c7 Andreu Torrens, 4",
    "sg:city":"Santa Maria Del Cami",
    "sg:orig_category":"Centros De Educaci\u00d3n Especial",
    "sg:phone":"+34 971 62 15 47",
    "sg:postcode":"07320",
    "sg:province":"Islas Baleares",
    "wof:name":"Melcior Rossello Y Simonet",
    "wof:placetype":"venue"
},
  "geometry": {"coordinates":[2.7701950073,39.6175346375],"type":"Point"}
}