{
  "type": "Feature",
  "properties": {
    "iso:country":"ES",
    "sg:address":"Carr Barcelona, 3",
    "sg:city":"Eivissa",
    "sg:orig_category":"Molduras, Junquillos, Listones Y Molduras Perforadas",
    "sg:phone":"+34 971 31 72 67",
    "sg:postcode":"07800",
    "sg:province":"Islas Baleares",
    "wof:name":"Roig Serra Jose",
    "wof:placetype":"venue"
},
  "geometry": {"coordinates":[1.4377520084,38.9098587036],"type":"Point"}
}