{
  "type": "Feature",
  "properties": {
    "addr:full":"Praz Santo Domingo, 28 Lugo Lugo 27001",
    "addr:housenumber":"28",
    "addr:postcode":"27001",
    "addr:street":"Praz Santo Domingo",
    "iso:country":"ES",
    "sg:address":"Praz Santo Domingo, 28",
    "sg:city":"Lugo",
    "sg:orig_category":"Alimentaci\u00d3n General (al Por Menor)",
    "sg:phone":"+34 982 23 12 74",
    "sg:postcode":"27001",
    "sg:province":"Lugo",
    "wof:name":"Adarve Publicistas S.l.",
    "wof:placetype":"venue"
},
  "geometry": {"coordinates":[-7.5558686256,43.0113105774],"type":"Point"}
}