{
  "type": "Feature",
  "properties": {
    "addr:full":"Avda Langraiz, 50 Nanclares De La Oca \u00c1lava 01230",
    "addr:housenumber":"50",
    "addr:postcode":"01230",
    "addr:street":"Avda Langraiz;A\u0301Lava",
    "iso:country":"ES",
    "sg:address":"Avda Langraiz, 50",
    "sg:city":"Nanclares De La Oca",
    "sg:orig_category":"Negocio De Materiales De Construcci\u00d3n",
    "sg:phone":"+34 945 37 12 22",
    "sg:postcode":"01230",
    "sg:province":"\u00c1lava",
    "wof:name":"Centro Comercial De La Construccion P.errasti S.l",
    "wof:placetype":"venue"
},
  "geometry": {"coordinates":[-2.8150889874,42.8163604736],"type":"Point"}
}