{
  "type": "Feature",
  "properties": {
    "iso:country":"ES",
    "sg:address":"Calle de Santa Ana, 2",
    "sg:city":"Madrid",
    "sg:orig_category":"Estilistas Y Estudios De Estilo De Corte Y Confecci\u00d3n",
    "sg:phone":"+34 913 65 52 55",
    "sg:postcode":"28005",
    "sg:province":"Madrid",
    "wof:name":"Puente Hernano Jorge",
    "wof:placetype":"venue"
},
  "geometry": {"coordinates":[-3.7081050873,40.410282135],"type":"Point"}
}