{
  "type": "Feature",
  "properties": {
    "addr:full":"Cmno Almenar, 5 Valencia Valencia 46026",
    "addr:housenumber":"5",
    "addr:postcode":"46026",
    "addr:street":"Cmno Almenar",
    "iso:country":"ES",
    "sg:address":"Cmno Almenar, 5",
    "sg:city":"Valencia",
    "sg:orig_category":"Puertas Autom\u00c1ticas, Puertas De Garaje",
    "sg:phone":"+34 963 74 65 45",
    "sg:postcode":"46026",
    "sg:province":"Valencia",
    "sg:website":"www.puertasvtorres.com",
    "wof:name":"Puertas V. Torres S.l.",
    "wof:placetype":"venue"
},
  "geometry": {"coordinates":[-0.3824749887,39.4489784241],"type":"Point"}
}