{
  "type": "Feature",
  "properties": {
    "addr:full":"Calle de San Agustin, 8 Malaga M\u00e1laga 29...",
    "addr:housenumber":"8;29 ...",
    "addr:street":"Calle De San Agustin;Ma\u0301Laga",
    "iso:country":"ES",
    "sg:address":"Calle de San Agustin, 8",
    "sg:city":"Malaga",
    "sg:orig_category":"Museos",
    "sg:phone":"+34 952 12 76 00",
    "sg:postcode":"29...",
    "sg:province":"M\u00e1laga",
    "wof:name":"Fundacion Museo Picasso De Malaga",
    "wof:placetype":"venue"
},
  "geometry": {"coordinates":[-4.4184641838,36.7216339111],"type":"Point"}
}