{
  "type": "Feature",
  "properties": {
    "addr:full":"Calle de Alcalde Luis Silvela, 1 Madrid Madrid 28022",
    "addr:housenumber":"1",
    "addr:postcode":"28022",
    "addr:street":"Calle De Alcalde Luis Silvela",
    "iso:country":"ES",
    "sg:address":"Calle de Alcalde Luis Silvela, 1",
    "sg:city":"Madrid",
    "sg:orig_category":"Publicidad (soportes Y Gesti\u00d3n)",
    "sg:phone":"+34 913 20 21 74",
    "sg:postcode":"28022",
    "sg:province":"Madrid",
    "wof:name":"Vapex S.l.",
    "wof:placetype":"venue"
},
  "geometry": {"coordinates":[-3.5989239216,40.4495620728],"type":"Point"}
}