{
  "type": "Feature",
  "properties": {
    "addr:full":"Carr La Selva, 4 Lleida Lleida 25005",
    "addr:housenumber":"4",
    "addr:postcode":"25005",
    "addr:street":"Carr La Selva",
    "iso:country":"ES",
    "sg:address":"Carr La Selva, 4",
    "sg:city":"Lleida",
    "sg:orig_category":"Agentes, Concesionarios Y Sucursales De Veh\u00cdculos",
    "sg:phone":"+34 973 24 92 66",
    "sg:postcode":"25005",
    "sg:province":"Lleida",
    "wof:name":"Sportmotor S. A.",
    "wof:placetype":"venue"
},
  "geometry": {"coordinates":[0.627129972,41.6145210266],"type":"Point"}
}