{
  "type": "Feature",
  "properties": {
    "iso:country":"ES",
    "sg:address":"Calle de Angustias Vieja, 3",
    "sg:city":"Almu\u00f1ecar",
    "sg:orig_category":"Partidos Pol\u00cdticos",
    "sg:phone":"+34 958 63 48 70",
    "sg:postcode":"18690",
    "sg:province":"Granada",
    "wof:name":"Centro Andaluz",
    "wof:placetype":"venue"
},
  "geometry": {"coordinates":[-3.6904366016,36.7349395752],"type":"Point"}
}