{
  "type": "Feature",
  "properties": {
    "addr:full":"Arillo, S/n Dorneda La Coru\u00f1a 15178",
    "addr:housenumber":"s / n",
    "addr:postcode":"15178",
    "addr:street":"Arillo;La Corun\u0303A",
    "iso:country":"ES",
    "sg:address":"Arillo, S/n",
    "sg:city":"Dorneda",
    "sg:orig_category":"Bibliotecas, Mediatecas",
    "sg:phone":"+34 981 61 41 11",
    "sg:postcode":"15178",
    "sg:province":"La Coru\u00f1a",
    "wof:name":"Concello De Oleiros",
    "wof:placetype":"venue"
},
  "geometry": {"coordinates":[-8.3229408264,43.3542900085],"type":"Point"}
}