{
  "type": "Feature",
  "properties": {
    "iso:country":"ES",
    "sg:address":"Calle de Pinar, S/n",
    "sg:city":"Almazan",
    "sg:orig_category":"Transportes Por V\u00cdas Navegables",
    "sg:phone":"+34 975 30 09 65",
    "sg:postcode":"42200",
    "sg:province":"Soria",
    "wof:name":"Garcia Casado Emilio",
    "wof:placetype":"venue"
},
  "geometry": {"coordinates":[-2.5259280205,41.4837608337],"type":"Point"}
}