{
  "type": "Feature",
  "properties": {
    "iso:country":"ES",
    "sg:address":"Av Sant Jordi, 31",
    "sg:city":"Reus",
    "sg:orig_category":"Librer\u00cdas",
    "sg:phone":"+34 977 34 11 30",
    "sg:postcode":"43201",
    "sg:province":"Tarragona",
    "wof:name":"Calavia Revilla Alfredo",
    "wof:placetype":"venue"
},
  "geometry": {"coordinates":[1.1107150316,41.1613464355],"type":"Point"}
}