{
  "type": "Feature",
  "properties": {
    "iso:country":"ES",
    "sg:address":"Calle de Calvo Sotelo, 13",
    "sg:city":"Logro\u00f1o",
    "sg:orig_category":"Telas Para Tapizar, Cortinas, Pasamaner\u00cda (fabricaci\u00d3n, Al Por Mayor)",
    "sg:phone":"+34 941 25 85 16",
    "sg:postcode":"26003",
    "sg:province":"La Rioja",
    "sg:website":"www.maisondecor.info",
    "wof:name":"Maribel Vazquez Y Marisa Remirez Cb.",
    "wof:placetype":"venue"
},
  "geometry": {"coordinates":[-2.4422838688,42.4640960693],"type":"Point"}
}