{
  "type": "Feature",
  "properties": {
    "iso:country":"ES",
    "sg:address":"Mimbres, S/n",
    "sg:city":"Maracena",
    "sg:orig_category":"Supermercados Y Hipermercados",
    "sg:phone":"+34 958 40 42 76",
    "sg:postcode":"18200",
    "sg:province":"Granada",
    "wof:name":"Supergran S. A.",
    "wof:placetype":"venue"
},
  "geometry": {"coordinates":[-3.6402039528,37.2081184387],"type":"Point"}
}