{
  "type": "Feature",
  "properties": {
    "iso:country":"ES",
    "sg:address":"Plaz Fuerte (del), 14",
    "sg:city":"Calatayud",
    "sg:orig_category":"Asesor\u00cda Fiscal Y Jur\u00cddica",
    "sg:phone":"+34 976 88 56 33",
    "sg:postcode":"50300",
    "sg:province":"Zaragoza",
    "wof:name":"Asesoria Vicor",
    "wof:placetype":"venue"
},
  "geometry": {"coordinates":[-1.6433153152,41.3515052795],"type":"Point"}
}