{
  "type": "Feature",
  "properties": {
    "iso:country":"ES",
    "sg:address":"Calle de Guadalquivir, 9",
    "sg:city":"Madrid",
    "sg:orig_category":"Internados & Ense\u00d1anza Privada",
    "sg:phone":"+34 917 82 35 00",
    "sg:postcode":"28002",
    "sg:province":"Madrid",
    "wof:name":"Colegio De Nuestra Se\u00d1ora De Las Maravil",
    "wof:placetype":"venue"
},
  "geometry": {"coordinates":[-3.6886000633,40.4470367432],"type":"Point"}
}