{
  "type": "Feature",
  "properties": {
    "addr:full":"Calle de En Gil, 5 Valencia Valencia 46001",
    "addr:housenumber":"5",
    "addr:postcode":"46001",
    "addr:street":"Calle De En Gil",
    "iso:country":"ES",
    "sg:address":"Calle de En Gil, 5",
    "sg:city":"Valencia",
    "sg:orig_category":"Molduras, Junquillos, Listones Y Molduras Perforadas",
    "sg:phone":"+34 963 51 48 43",
    "sg:postcode":"46001",
    "sg:province":"Valencia",
    "wof:name":"Llibrer Rodriguez Juan",
    "wof:placetype":"venue"
},
  "geometry": {"coordinates":[-0.3789752126,39.4726409912],"type":"Point"}
}