{
  "type": "Feature",
  "properties": {
    "iso:country":"ES",
    "sg:address":"Calle de Virgen De Guadalupe, 8",
    "sg:city":"Jerez De Los Caballeros",
    "sg:orig_category":"Supermercados Y Hipermercados",
    "sg:phone":"+34 924 73 11 38",
    "sg:postcode":"06380",
    "sg:province":"Badajoz",
    "wof:name":"Duran Escudero S.l.",
    "wof:placetype":"venue"
},
  "geometry": {"coordinates":[-6.7654390335,38.3238182068],"type":"Point"}
}