{
  "type": "Feature",
  "properties": {
    "iso:country":"ES",
    "sg:address":"Calle de Buenos Aires, 14",
    "sg:city":"Muela",
    "sg:orig_category":"Comercio De Piezas De Recambio Y De Accesorios De Veh\u00cdculos, Veh\u00cdculos Industriales",
    "sg:phone":"+34 976 14 44 06",
    "sg:postcode":"50196",
    "sg:province":"Zaragoza",
    "wof:name":"Benteler Iberica Holding S.l.",
    "wof:placetype":"venue"
},
  "geometry": {"coordinates":[-1.0742969513,41.611946106],"type":"Point"}
}