{
  "type": "Feature",
  "properties": {
    "addr:full":"Plaz Antonio Zoido Diaz, 4 Badajoz Badajoz 06010",
    "addr:housenumber":"4",
    "addr:postcode":"06010",
    "addr:street":"Diaz",
    "iso:country":"ES",
    "sg:address":"Plaz Antonio Zoido Diaz, 4",
    "sg:city":"Badajoz",
    "sg:orig_category":"Agencias Y Agentes Comerciales, Representantes",
    "sg:phone":"+34 924 20 75 05",
    "sg:postcode":"06010",
    "sg:province":"Badajoz",
    "wof:name":"Entorno Complementario De Empresas S.l.",
    "wof:placetype":"venue"
},
  "geometry": {"coordinates":[-6.9735751152,38.8687210083],"type":"Point"}
}