{
  "type": "Feature",
  "properties": {
    "addr:full":"Calle de Jorge Luis Borges, 24 Alcala Henares Madrid 28806",
    "addr:housenumber":"24",
    "addr:postcode":"28806",
    "addr:street":"Calle De Jorge Luis Borges",
    "iso:country":"ES",
    "sg:address":"Calle de Jorge Luis Borges, 24",
    "sg:city":"Alcala Henares",
    "sg:orig_category":"Librer\u00cdas",
    "sg:phone":"+34 918 82 34 60",
    "sg:postcode":"28806",
    "sg:province":"Madrid",
    "wof:name":"Diaz Moreno Francisca",
    "wof:placetype":"venue"
},
  "geometry": {"coordinates":[-3.3739171028,40.4961967468],"type":"Point"}
}