{
  "type": "Feature",
  "properties": {
    "addr:full":"Pg Vall D'hebron, S/n Barcelona Barcelona 08031",
    "addr:housenumber":"s / n",
    "addr:postcode":"08031",
    "addr:street":"Pg Vall D'Hebron",
    "iso:country":"ES",
    "sg:address":"Pg Vall D'hebron, S/n",
    "sg:city":"Barcelona",
    "sg:orig_category":"Ense\u00d1anza, Formaci\u00d3n Profesional: Aprendizaje",
    "sg:phone":"+34 934 28 45 85",
    "sg:postcode":"08031",
    "sg:province":"Barcelona",
    "sg:website":"www.fbg.ub.es",
    "wof:name":"Fundacio Bosch I Gimpera",
    "wof:placetype":"venue"
},
  "geometry": {"coordinates":[2.1447529793,41.4293212891],"type":"Point"}
}