{
  "type": "Feature",
  "properties": {
    "iso:country":"ES",
    "sg:address":"Calle de Joaquin Costa, 25",
    "sg:city":"Teruel",
    "sg:orig_category":"Relojer\u00cda (al Por Menor, Reparaci\u00d3n)",
    "sg:phone":"+34 978 60 16 40",
    "sg:postcode":"44001",
    "sg:province":"Teruel",
    "wof:name":"Miguel Angel Argiles Hernandez Y Otros Cdad.",
    "wof:placetype":"venue"
},
  "geometry": {"coordinates":[-1.1045490503,40.3420944214],"type":"Point"}
}