{
  "type": "Feature",
  "properties": {
    "addr:full":"Calle de Donoso Cortes, 15 Madrid Madrid 28015",
    "addr:housenumber":"15",
    "addr:postcode":"madrid;28015",
    "addr:street":"Calle De Donoso Cortes",
    "iso:country":"ES",
    "sg:address":"Calle de Donoso Cortes, 15",
    "sg:city":"Madrid",
    "sg:orig_category":"Comisarios",
    "sg:phone":"+34 915 93 80 60",
    "sg:postcode":"28015",
    "sg:province":"Madrid",
    "wof:name":"El Maestro Relojero S.l.",
    "wof:placetype":"venue"
},
  "geometry": {"coordinates":[-3.7071390152,40.4361076355],"type":"Point"}
}