{
  "type": "Feature",
  "properties": {
    "iso:country":"ES",
    "sg:address":"C/ Mar, De La, 15",
    "sg:city":"S. Antoni Portmany",
    "sg:orig_category":"Institutos De Belleza",
    "sg:phone":"+34 971 34 03 97",
    "sg:postcode":"07820",
    "sg:province":"Islas Baleares",
    "wof:name":"Zarabozo Sanchez Margarita",
    "wof:placetype":"venue"
},
  "geometry": {"coordinates":[1.3016376495,38.9815330505],"type":"Point"}
}