{
  "type": "Feature",
  "properties": {
    "iso:country":"ES",
    "sg:address":"Calle de Fermina (la), 9",
    "sg:city":"Arrecife",
    "sg:orig_category":"Metalurgia",
    "sg:phone":"+34 928 80 62 63",
    "sg:postcode":"35500",
    "sg:province":"Las Palmas",
    "wof:name":"Aislamientos Lanzarote S.l.",
    "wof:placetype":"venue"
},
  "geometry": {"coordinates":[-13.5527219772,28.9685955048],"type":"Point"}
}