{
  "type": "Feature",
  "properties": {
    "iso:country":"ES",
    "sg:address":"Barr Pertxin, S/n",
    "sg:city":"Usansolo",
    "sg:orig_category":"Inmobiliaria (agencias)",
    "sg:phone":"+34 944 36 36 57",
    "sg:postcode":"48960",
    "sg:province":"Vizcaya",
    "wof:name":"Itesa Servicios Inmobiliarios S.l.",
    "wof:placetype":"venue"
},
  "geometry": {"coordinates":[-2.8191649914,43.2167663574],"type":"Point"}
}