{
  "type": "Feature",
  "properties": {
    "iso:country":"ES",
    "sg:address":"Ctra Cuesta La Reina, Km. 0023,0",
    "sg:city":"Villaseca Sagra",
    "sg:orig_category":"Producci\u00d3n, Comercio De Cereales",
    "sg:phone":"+34 925 27 80 46",
    "sg:postcode":"45260",
    "sg:province":"Toledo",
    "wof:name":"Cereales Del Tajo S.l.",
    "wof:placetype":"venue"
},
  "geometry": {"coordinates":[-3.8813800812,39.9579544067],"type":"Point"}
}