{
  "type": "Feature",
  "properties": {
    "iso:country":"ES",
    "sg:address":"Calle de Parque (del), 5",
    "sg:city":"Cartagena",
    "sg:orig_category":"Inform\u00c1tica, Ofim\u00c1tica (estudios, Asesor\u00cda, Ingenier\u00cda, Formaci\u00d3n)",
    "sg:phone":"+34 968 12 39 25",
    "sg:postcode":"30201",
    "sg:province":"Murcia",
    "wof:name":"Anaco Consultoria De Negocios S.l.",
    "wof:placetype":"venue"
},
  "geometry": {"coordinates":[-0.985270083,37.6041183472],"type":"Point"}
}