{
  "type": "Feature",
  "properties": {
    "addr:full":"Calle de Real Sur, 14 Fuentesauco De Fuentidue\u00e7a Segovia 40355",
    "addr:housenumber":"14",
    "addr:postcode":"40355",
    "addr:street":"Calle De Real Sur",
    "iso:country":"ES",
    "sg:address":"Calle de Real Sur, 14",
    "sg:city":"Fuentesauco De Fuentidue\u00e7a",
    "sg:orig_category":"Mec\u00c1nico Del Autom\u00d3vil",
    "sg:phone":"+34 921 16 96 48",
    "sg:postcode":"40355",
    "sg:province":"Segovia",
    "wof:name":"Herrero Villar Marcial",
    "wof:placetype":"venue"
},
  "geometry": {"coordinates":[-4.0650539398,41.4260902405],"type":"Point"}
}