{
  "type": "Feature",
  "properties": {
    "addr:full":"Calle de Constitucion (de La), 67 Fuenlabrada Madrid 28946",
    "addr:housenumber":"67",
    "addr:postcode":"28946",
    "addr:street":"Calle De Constitucion De La",
    "iso:country":"ES",
    "sg:address":"Calle de Constitucion (de La), 67",
    "sg:city":"Fuenlabrada",
    "sg:orig_category":"Pintura Y Barniz (al Por Menor)",
    "sg:phone":"+34 916 06 06 03",
    "sg:postcode":"28946",
    "sg:province":"Madrid",
    "sg:website":"www.grupouvi.com",
    "wof:name":"Angela Gomez Bernardos S.a.",
    "wof:placetype":"venue"
},
  "geometry": {"coordinates":[-3.7837555408,40.2805480957],"type":"Point"}
}