{
  "type": "Feature",
  "properties": {
    "iso:country":"ES",
    "sg:address":"Carrer de Cartagena, 401",
    "sg:city":"Barcelona",
    "sg:orig_category":"Cerrajer\u00cda, Ferrallista",
    "sg:phone":"+34 934 33 46 88",
    "sg:postcode":"08024",
    "sg:province":"Barcelona",
    "wof:name":"Apropteu Cerrajeria S.l.",
    "wof:placetype":"venue"
},
  "geometry": {"coordinates":[2.1693150997,41.4153862],"type":"Point"}
}