{
  "type": "Feature",
  "properties": {
    "iso:country":"ES",
    "sg:address":"Torrelarragoiti Parcela 8, 32 A",
    "sg:city":"Zamudio",
    "sg:orig_category":"Maquinaria Para Industrias Diversas",
    "sg:phone":"+34 944 03 66 86",
    "sg:postcode":"48170",
    "sg:province":"Vizcaya",
    "sg:website":"www.acertra.com",
    "wof:name":"Acertra, S.l.",
    "wof:placetype":"venue"
},
  "geometry": {"coordinates":[-2.8626980782,43.2792701721],"type":"Point"}
}