{
  "type": "Feature",
  "properties": {
    "iso:country":"ES",
    "sg:address":"Ctra Cabo La Nao Pla, Km. 0005,0",
    "sg:city":"Javea",
    "sg:orig_category":"Oficinas Y Gesti\u00d3n De Inmuebles",
    "sg:phone":"+34 965 77 02 61",
    "sg:postcode":"03730",
    "sg:province":"Alicante",
    "wof:name":"Comunidad De Propietarios Ciudad Residencial Toscamar",
    "wof:placetype":"venue"
},
  "geometry": {"coordinates":[0.1570300013,38.7885093689],"type":"Point"}
}