{
  "type": "Feature",
  "properties": {
    "iso:country":"ES",
    "sg:address":"Calle de Conde, 9",
    "sg:city":"Ecija",
    "sg:orig_category":"Cristaler\u00cdas",
    "sg:phone":"+34 954 83 19 22",
    "sg:postcode":"41400",
    "sg:province":"Sevilla",
    "wof:name":"Extruplas S.l.",
    "wof:placetype":"venue"
},
  "geometry": {"coordinates":[-5.0809054375,37.5407943726],"type":"Point"}
}