{
  "type": "Feature",
  "properties": {
    "iso:country":"ES",
    "sg:address":"Calle de Leon Perez Bayo (de), 15",
    "sg:city":"Alcobendas",
    "sg:orig_category":"M\u00c9dicos: Foniatr\u00cda Y Logopedia",
    "sg:phone":"+34 916 62 32 99",
    "sg:postcode":"28100",
    "sg:province":"Madrid",
    "wof:name":"Marmoles Dofer S.l.",
    "wof:placetype":"venue"
},
  "geometry": {"coordinates":[-3.6403200626,40.5425491333],"type":"Point"}
}