{
  "type": "Feature",
  "properties": {
    "addr:full":"Calle de Alfonso Trujillo, 9 Orotava Santa Cruz De Tenerife 38300",
    "addr:housenumber":"9",
    "addr:postcode":"38300",
    "addr:street":"Calle De Alfonso Trujillo",
    "iso:country":"ES",
    "sg:address":"Calle de Alfonso Trujillo, 9",
    "sg:city":"Orotava",
    "sg:orig_category":"Asesor\u00cda De Formaci\u00d3n Y Gesti\u00d3n De Personal",
    "sg:phone":"+34 922 32 33 11",
    "sg:postcode":"38300",
    "sg:province":"Santa Cruz De Tenerife",
    "wof:name":"United Services Spain Back-office S.l.",
    "wof:placetype":"venue"
},
  "geometry": {"coordinates":[-16.5200881958,28.3934993744],"type":"Point"}
}