{
  "type": "Feature",
  "properties": {
    "iso:country":"ES",
    "sg:address":"Calle de Brasil, S/n",
    "sg:city":"San Juan De Aznalfarache",
    "sg:orig_category":"Centros De Educaci\u00d3n Especial",
    "sg:phone":"+34 954 76 37 77",
    "sg:postcode":"41920",
    "sg:province":"Sevilla",
    "wof:name":"Junta De Andalucia-consejeria De Trabajo",
    "wof:placetype":"venue"
},
  "geometry": {"coordinates":[-6.0340209007,37.361492157],"type":"Point"}
}