{
  "type": "Feature",
  "properties": {
    "addr:full":"Calle de Sanz Crespo, 5 Gijon Asturias 33207",
    "addr:housenumber":"5",
    "addr:postcode":"33207",
    "addr:street":"Calle De Sanz Crespo",
    "iso:country":"ES",
    "sg:address":"Calle de Sanz Crespo, 5",
    "sg:city":"Gijon",
    "sg:orig_category":"Expertos Contables",
    "sg:phone":"+34 985 17 57 04",
    "sg:postcode":"33207",
    "sg:province":"Asturias",
    "wof:name":"Adade Asturias S.l.",
    "wof:placetype":"venue"
},
  "geometry": {"coordinates":[-5.6688761711,43.540058136],"type":"Point"}
}