{
  "type": "Feature",
  "properties": {
    "addr:full":"Carrer de Sant Antoni Maria Claret, S/n Artes Barcelona 08271",
    "addr:housenumber":"s / n",
    "addr:postcode":"08271",
    "addr:street":"Carrer De Sant Antoni Maria Claret",
    "iso:country":"ES",
    "sg:address":"Carrer de Sant Antoni Maria Claret, S/n",
    "sg:city":"Artes",
    "sg:orig_category":"Venta, Localizaci\u00d3n, Reparaci\u00d3n De Material E Instrumental M\u00c9dico",
    "sg:phone":"+34 938 30 58 14",
    "sg:postcode":"08271",
    "sg:province":"Barcelona",
    "sg:website":"www.quirosa.com",
    "wof:name":"Quirosa S.a.",
    "wof:placetype":"venue"
},
  "geometry": {"coordinates":[1.933027029,41.7899284363],"type":"Point"}
}