{
  "type": "Feature",
  "properties": {
    "iso:country":"ES",
    "sg:address":"Ctra. Toledo, Km. 0001,2",
    "sg:city":"Totanes",
    "sg:orig_category":"Delegados, Agentes De Tr\u00c1nsito, Auxiliares De Transporte Internacional",
    "sg:phone":"+34 925 40 12 11",
    "sg:postcode":"45163",
    "sg:province":"Toledo",
    "sg:website":"www.cecaman.com",
    "wof:name":"Trans Castellana Manchega De Cargas S.l.",
    "wof:placetype":"venue"
},
  "geometry": {"coordinates":[-4.226744175,39.7114562988],"type":"Point"}
}