{
  "type": "Feature",
  "properties": {
    "iso:country":"ES",
    "sg:address":"Calle de Mezquita, S/n",
    "sg:city":"Almeria",
    "sg:orig_category":"Chapister\u00cda",
    "sg:phone":"+34 950 22 23 53",
    "sg:postcode":"04009",
    "sg:province":"Almer\u00eda",
    "wof:name":"Talleres La Mezquita S.l.",
    "wof:placetype":"venue"
},
  "geometry": {"coordinates":[-2.434169054,36.8423118591],"type":"Point"}
}