{
  "type": "Feature",
  "properties": {
    "iso:country":"ES",
    "sg:address":"Carrer de Born, 6",
    "sg:city":"Manresa",
    "sg:orig_category":"Carnicer\u00cdas, Carnicer\u00cdas",
    "sg:phone":"+34 938 72 59 99",
    "sg:postcode":"08241",
    "sg:province":"Barcelona",
    "wof:name":"Faine Graell Antonia",
    "wof:placetype":"venue"
},
  "geometry": {"coordinates":[1.8246279955,41.7241439819],"type":"Point"}
}