{
  "type": "Feature",
  "properties": {
    "iso:country":"ES",
    "sg:address":"Cordelles, 18",
    "sg:city":"Barcelona",
    "sg:orig_category":"Construcci\u00d3n Mec\u00c1nica",
    "sg:phone":"+34 932 74 46 44",
    "sg:postcode":"08030",
    "sg:province":"Barcelona",
    "sg:website":"www.jofresa.com",
    "wof:name":"Talleres Jofresa S. L.",
    "wof:placetype":"venue"
},
  "geometry": {"coordinates":[2.1981039047,41.433303833],"type":"Point"}
}