{
  "type": "Feature",
  "properties": {
    "addr:full":"Calle de Marcos, 9 Almeria Almer\u00eda 04003",
    "addr:housenumber":"9",
    "addr:postcode":"04003",
    "addr:street":"Calle De Marcos",
    "iso:country":"ES",
    "sg:address":"Calle de Marcos, 9",
    "sg:city":"Almeria",
    "sg:orig_category":"Papeler\u00cdas: Art\u00cdculos (al Por Mayor)",
    "sg:phone":"+34 950 26 70 54",
    "sg:postcode":"04003",
    "sg:province":"Almer\u00eda",
    "wof:name":"Colon Suministros De Oficinas S.l.",
    "wof:placetype":"venue"
},
  "geometry": {"coordinates":[-2.4635500908,36.8426704407],"type":"Point"}
}