{
  "type": "Feature",
  "properties": {
    "iso:country":"ES",
    "sg:address":"Carrer de Independencia, 389",
    "sg:city":"Barcelona",
    "sg:orig_category":"Fabricaci\u00d3n, Importaci\u00d3n, Venta De Material De Telefon\u00cda, Peritelefon\u00cda",
    "sg:phone":"+34 934 56 60 05",
    "sg:postcode":"08041",
    "sg:province":"Barcelona",
    "wof:name":"Escudero Garcia Jose Antonio",
    "wof:placetype":"venue"
},
  "geometry": {"coordinates":[2.1769258976,41.4125442505],"type":"Point"}
}