{
  "type": "Feature",
  "properties": {
    "addr:full":"Ctra Lora Rio, 17 Cantillana Sevilla 41320",
    "addr:housenumber":"17",
    "addr:postcode":"41320",
    "addr:street":"Ctra Lora Rio",
    "iso:country":"ES",
    "sg:address":"Ctra Lora Rio, 17",
    "sg:city":"Cantillana",
    "sg:orig_category":"Farmacias",
    "sg:phone":"+34 955 73 18 56",
    "sg:postcode":"41320",
    "sg:province":"Sevilla",
    "wof:name":"Arias Mira Jose",
    "wof:placetype":"venue"
},
  "geometry": {"coordinates":[-5.8230538368,37.609500885],"type":"Point"}
}