{
  "type": "Feature",
  "properties": {
    "iso:country":"ES",
    "sg:address":"Calle de Mar Rojo (del), 11",
    "sg:city":"Coslada",
    "sg:orig_category":"Peluquer\u00cdas, Peluquer\u00cda Mixta",
    "sg:phone":"+34 916 69 44 72",
    "sg:postcode":"28820",
    "sg:province":"Madrid",
    "wof:name":"Aqua Coslada S.l.",
    "wof:placetype":"venue"
},
  "geometry": {"coordinates":[-3.5719242096,40.4211463928],"type":"Point"}
}