{
  "type": "Feature",
  "properties": {
    "addr:full":"Pase Ezequiel Gonzalez, 34 Segovia Segovia 40002",
    "addr:housenumber":"34",
    "addr:postcode":"40002",
    "addr:street":"Gonzalez",
    "iso:country":"ES",
    "sg:address":"Pase Ezequiel Gonzalez, 34",
    "sg:city":"Segovia",
    "sg:orig_category":"\u00d3ptica: Instrumentos (fabricaci\u00d3n)",
    "sg:phone":"+34 921 42 75 04",
    "sg:postcode":"40002",
    "sg:province":"Segovia",
    "sg:website":"www.paginasamarillas.es",
    "wof:name":"Ramos Rodrigo Pedro",
    "wof:placetype":"venue"
},
  "geometry": {"coordinates":[-4.1186928749,40.942325592],"type":"Point"}
}