{
  "type": "Feature",
  "properties": {
    "iso:country":"ES",
    "sg:address":"Calle de Tirso De Molina, 8",
    "sg:city":"Almeria",
    "sg:orig_category":"Asesor\u00cda Sobre Comunicaci\u00d3n De Empresas",
    "sg:phone":"+34 950 62 29 35",
    "sg:postcode":"04005",
    "sg:province":"Almer\u00eda",
    "wof:name":"Calvache Alarcon Ana",
    "wof:placetype":"venue"
},
  "geometry": {"coordinates":[-2.4577031136,36.8378486633],"type":"Point"}
}