{
  "type": "Feature",
  "properties": {
    "iso:country":"ES",
    "sg:address":"Carrer de Santa Eulalia, 114",
    "sg:city":"Hospitalet Llobregat",
    "sg:orig_category":"Bancos",
    "sg:phone":"+34 934 32 99 90",
    "sg:postcode":"08902",
    "sg:province":"Barcelona",
    "wof:name":"Banco Guipuzcoano S.a.",
    "wof:placetype":"venue"
},
  "geometry": {"coordinates":[2.1264750957,41.3671646118],"type":"Point"}
}