{
  "type": "Feature",
  "properties": {
    "iso:country":"ES",
    "sg:address":"Calle de San Francisco, 8",
    "sg:city":"Alfaro",
    "sg:orig_category":"Quincaller\u00cda (al Por Menor)",
    "sg:phone":"+34 941 18 42 26",
    "sg:postcode":"26540",
    "sg:province":"La Rioja",
    "wof:name":"Fernandez Ordoyo Jose Luis",
    "wof:placetype":"venue"
},
  "geometry": {"coordinates":[-1.7505869865,42.1795692444],"type":"Point"}
}