{
  "type": "Feature",
  "properties": {
    "addr:full":"Calle de Periodista Luis De Vicente, 9 Granada Granada 18011",
    "addr:housenumber":"9",
    "addr:postcode":"18011",
    "addr:street":"Calle De Periodista Luis De Vicente",
    "iso:country":"ES",
    "sg:address":"Calle de Periodista Luis De Vicente, 9",
    "sg:city":"Granada",
    "sg:orig_category":"Doctores En Medicina",
    "sg:phone":"+34 958 15 58 53",
    "sg:postcode":"18011",
    "sg:province":"Granada",
    "wof:name":"Lazo Lazo Agustin",
    "wof:placetype":"venue"
},
  "geometry": {"coordinates":[-3.6011641026,37.200428009],"type":"Point"}
}