{
  "type": "Feature",
  "properties": {
    "iso:country":"ES",
    "sg:address":"Calle de Luis Bu\u00d1uel, 5",
    "sg:city":"Barbastro",
    "sg:orig_category":"Electrodom\u00c9sticos (al Por Menor)",
    "sg:phone":"+34 974 31 33 31",
    "sg:postcode":"22300",
    "sg:province":"Huesca",
    "wof:name":"Laplana Arnal Manuel",
    "wof:placetype":"venue"
},
  "geometry": {"coordinates":[0.1260589957,42.0390739441],"type":"Point"}
}