{
  "type": "Feature",
  "properties": {
    "iso:country":"ES",
    "sg:address":"Carrer de Doctor Crusafont, 1",
    "sg:city":"Barbera Valles",
    "sg:orig_category":"Persianas Interiores, Exteriores",
    "sg:phone":"+34 937 29 03 08",
    "sg:postcode":"08210",
    "sg:province":"Barcelona",
    "wof:name":"Toldos Andres S.l.",
    "wof:placetype":"venue"
},
  "geometry": {"coordinates":[2.1366679668,41.5247421265],"type":"Point"}
}