{
  "type": "Feature",
  "properties": {
    "addr:full":"Pl Farga, 8 Barcelona Barcelona 08014",
    "addr:housenumber":"8",
    "addr:postcode":"08014",
    "addr:street":"Pl Farga",
    "iso:country":"ES",
    "sg:address":"Pl Farga, 8",
    "sg:city":"Barcelona",
    "sg:orig_category":"Ense\u00d1anza, Formaci\u00d3n Profesional: Aprendizaje",
    "sg:phone":"+34 934 21 79 11",
    "sg:postcode":"08014",
    "sg:province":"Barcelona",
    "wof:name":"Centre De Telecomunicaciones De Catalunya",
    "wof:placetype":"venue"
},
  "geometry": {"coordinates":[2.1387679577,41.3720970154],"type":"Point"}
}