{
  "type": "Feature",
  "properties": {
    "iso:country":"ES",
    "sg:address":"Rua Eumenio Ancochea, S/n",
    "sg:city":"Pobra Trives",
    "sg:orig_category":"Ropa Para Se\u00d1oras Y Caballeros (al Por Menor)",
    "sg:phone":"+34 988 33 23 84",
    "sg:postcode":"32780",
    "sg:province":"Ourense",
    "sg:website":"www.adolfo-dominguez.com",
    "wof:name":"Adolfo Dominguez S.a.",
    "wof:placetype":"venue"
},
  "geometry": {"coordinates":[-7.2539000511,42.3393058777],"type":"Point"}
}