{
  "type": "Feature",
  "properties": {
    "addr:full":"Rbla Marina, 151 Hospitalet Llobregat Barcelona 08907",
    "addr:housenumber":"151",
    "addr:postcode":"08907",
    "addr:street":"Rbla Marina",
    "iso:country":"ES",
    "sg:address":"Rbla Marina, 151",
    "sg:city":"Hospitalet Llobregat",
    "sg:orig_category":"Carnicer\u00cdas, Carnicer\u00cdas",
    "sg:phone":"+34 933 35 52 15",
    "sg:postcode":"08907",
    "sg:province":"Barcelona",
    "sg:website":"www.fernandezcados.com",
    "wof:name":"Fernandez Jimenez Domingo",
    "wof:placetype":"venue"
},
  "geometry": {"coordinates":[2.1100599766,41.3503112793],"type":"Point"}
}