{
  "type": "Feature",
  "properties": {
    "iso:country":"ES",
    "sg:address":"Carrer de Vidre (del), 13",
    "sg:city":"Reus",
    "sg:orig_category":"Albergues",
    "sg:phone":"+34 977 34 50 01",
    "sg:postcode":"43201",
    "sg:province":"Tarragona",
    "wof:name":"Potau Rue Ramon Maria",
    "wof:placetype":"venue"
},
  "geometry": {"coordinates":[1.108093977,41.1558609009],"type":"Point"}
}