{
  "type": "Feature",
  "properties": {
    "addr:full":"Mercat Sant Josep, 11 Barcelona Barcelona 08002",
    "addr:housenumber":"11",
    "addr:postcode":"08002",
    "iso:country":"ES",
    "sg:address":"Mercat Sant Josep, 11",
    "sg:city":"Barcelona",
    "sg:orig_category":"Carnes De Carnicer\u00cda (al Por Mayor)",
    "sg:phone":"+34 933 17 57 43",
    "sg:postcode":"08002",
    "sg:province":"Barcelona",
    "wof:name":"Carns R.p. S.a.",
    "wof:placetype":"venue"
},
  "geometry": {"coordinates":[2.1723499298,41.3820495605],"type":"Point"}
}