{
  "type": "Feature",
  "properties": {
    "iso:country":"ES",
    "sg:address":"Avda Gran Capitan (del), 36",
    "sg:city":"Cordoba",
    "sg:orig_category":"Semiller\u00cdas",
    "sg:phone":"+34 957 48 18 65",
    "sg:postcode":"14001",
    "sg:province":"C\u00f3rdoba",
    "wof:name":"Rodriguez Sanchez Antonio",
    "wof:placetype":"venue"
},
  "geometry": {"coordinates":[-4.7825751305,37.8890914917],"type":"Point"}
}