{
  "type": "Feature",
  "properties": {
    "iso:country":"ES",
    "sg:address":"Calle de Iglesia, 4",
    "sg:city":"Perilla Castro",
    "sg:orig_category":"Iglesia Cat\u00d3lica",
    "sg:phone":"+34 980 59 55 48",
    "sg:postcode":"49145",
    "sg:province":"Zamora",
    "wof:name":"Parroquia De Perilla De Castro",
    "wof:placetype":"venue"
},
  "geometry": {"coordinates":[-5.8763508797,41.724155426],"type":"Point"}
}