{
  "type": "Feature",
  "properties": {
    "iso:country":"ES",
    "sg:address":"Calle de Escultor Roque Lopez, 9",
    "sg:city":"San Miguel",
    "sg:orig_category":"Bazares, Art\u00cdculos De Limpieza Y De Cocina (al Por Menor)",
    "sg:phone":"+34 968 23 14 24",
    "sg:postcode":"30008",
    "sg:province":"Murcia",
    "wof:name":"Garcia Lopez Maria Del Carmen",
    "wof:placetype":"venue"
},
  "geometry": {"coordinates":[-1.1318589449,37.9912528992],"type":"Point"}
}