{
  "type": "Feature",
  "properties": {
    "iso:country":"ES",
    "sg:address":"Barr Peruri, 33",
    "sg:city":"Peruri",
    "sg:orig_category":"Agencias De Viajes",
    "sg:phone":"+34 944 60 12 67",
    "sg:postcode":"48940",
    "sg:province":"Vizcaya",
    "sg:website":"www.halconviajes.com",
    "wof:name":"Viajes Halcon S.a.",
    "wof:placetype":"venue"
},
  "geometry": {"coordinates":[-2.9860789776,43.3275489807],"type":"Point"}
}