{
  "type": "Feature",
  "properties": {
    "iso:country":"ES",
    "sg:address":"Carr Luis Vives, 37",
    "sg:city":"Moncada",
    "sg:orig_category":"Centros Empresariales",
    "sg:phone":"+34 961 39 46 68",
    "sg:postcode":"46113",
    "sg:province":"Valencia",
    "wof:name":"Rillo Heredia Priscila",
    "wof:placetype":"venue"
},
  "geometry": {"coordinates":[-0.3959209919,39.5454368591],"type":"Point"}
}