{
  "type": "Feature",
  "properties": {
    "addr:full":"Calle de Ibarra, 10 Galletas Santa Cruz De Tenerife 38631",
    "addr:housenumber":"10",
    "addr:postcode":"38631",
    "addr:street":"Calle De Ibarra",
    "iso:country":"ES",
    "sg:address":"Calle de Ibarra, 10",
    "sg:city":"Galletas",
    "sg:orig_category":"Quincaller\u00cda (al Por Menor)",
    "sg:phone":"+34 922 78 37 86",
    "sg:postcode":"38631",
    "sg:province":"Santa Cruz De Tenerife",
    "wof:name":"Arte Y Dise\u00f1o America S.l.",
    "wof:placetype":"venue"
},
  "geometry": {"coordinates":[-16.6569080353,28.0079078674],"type":"Point"}
}