{
  "type": "Feature",
  "properties": {
    "addr:full":"Rua Campo Da Feira, 2 Vilanova Lugo 27760",
    "addr:housenumber":"2",
    "addr:postcode":"27760",
    "addr:street":"Rua Campo Da Feira",
    "iso:country":"ES",
    "sg:address":"Rua Campo Da Feira, 2",
    "sg:city":"Vilanova",
    "sg:classifiers":[
        {
            "category":"Autos & Motor Vehicles",
            "subcategory":"Automobile Sales",
            "type":"Retail Goods"
        }
    ],
    "sg:phone":"+34 982 12 14 70",
    "sg:postcode":"27760",
    "sg:province":"Lugo",
    "wof:name":"Gestion Fama S.l.",
    "wof:placetype":"venue"
},
  "geometry": {"coordinates":[-7.2977337837,43.4696350098],"type":"Point"}
}