{
  "type": "Feature",
  "properties": {
    "addr:full":"Calle de Menendez Pelayo, 16 Abaran Murcia 30550",
    "addr:housenumber":"16",
    "addr:postcode":"30550",
    "addr:street":"Calle De Menendez Pelayo",
    "iso:country":"ES",
    "sg:address":"Calle de Menendez Pelayo, 16",
    "sg:city":"Abaran",
    "sg:orig_category":"Droguer\u00cdas (al Por Menor)",
    "sg:phone":"+34 968 77 06 20",
    "sg:postcode":"30550",
    "sg:province":"Murcia",
    "wof:name":"Ortega Lorente Carmen",
    "wof:placetype":"venue"
},
  "geometry": {"coordinates":[-1.4016259909,38.2028312683],"type":"Point"}
}