{
  "type": "Feature",
  "properties": {
    "iso:country":"ES",
    "sg:address":"Calle de Asturias, S/n",
    "sg:city":"Pola De Laviana",
    "sg:orig_category":"Centros P\u00dablicos De Formaci\u00d3n Profesional Y T\u00c9cnica",
    "sg:phone":"+34 985 61 03 23",
    "sg:postcode":"33980",
    "sg:province":"Asturias",
    "wof:name":"Ilustre Colegio De Abogados De Asturias",
    "wof:placetype":"venue"
},
  "geometry": {"coordinates":[-5.5628819466,43.2437591553],"type":"Point"}
}