{
  "type": "Feature",
  "properties": {
    "addr:full":"Av Bisbe Llompart, 191 Inca Islas Baleares 07300",
    "addr:housenumber":"191",
    "addr:postcode":"07300",
    "addr:street":"Av Bisbe Llompart",
    "iso:country":"ES",
    "sg:address":"Av Bisbe Llompart, 191",
    "sg:city":"Inca",
    "sg:orig_category":"Quincaller\u00cda (al Por Menor)",
    "sg:phone":"+34 971 50 08 92",
    "sg:postcode":"07300",
    "sg:province":"Islas Baleares",
    "wof:name":"Ferreteria Coll C. B.",
    "wof:placetype":"venue"
},
  "geometry": {"coordinates":[2.9063498974,39.718208313],"type":"Point"}
}