{
  "type": "Feature",
  "properties": {
    "addr:full":"Avda Reyes Catolicos, 5 Chiclana De La Frontera C\u00e1diz 11130",
    "addr:housenumber":"5",
    "addr:postcode":"11130",
    "addr:street":"Avda Reyes Catolicos",
    "iso:country":"ES",
    "sg:address":"Avda Reyes Catolicos, 5",
    "sg:city":"Chiclana De La Frontera",
    "sg:orig_category":"Comercio De Piezas De Recambio Y De Accesorios De Veh\u00cdculos, Veh\u00cdculos Industriales",
    "sg:phone":"+34 956 40 07 41",
    "sg:postcode":"11130",
    "sg:province":"C\u00e1diz",
    "wof:name":"Hermanos Sanchez Peri\u00f1an S.l.",
    "wof:placetype":"venue"
},
  "geometry": {"coordinates":[-6.1429338455,36.414226532],"type":"Point"}
}