{
  "type": "Feature",
  "properties": {
    "addr:full":"Jaras, 10 Monte Encinas Madrid 28669",
    "addr:housenumber":"10",
    "addr:postcode":"28669",
    "addr:street":"Jaras;Monte Encinas",
    "iso:country":"ES",
    "sg:address":"Jaras, 10",
    "sg:city":"Monte Encinas",
    "sg:orig_category":"Inmobiliaria (agencias)",
    "sg:phone":"+34 916 33 00 67",
    "sg:postcode":"28669",
    "sg:province":"Madrid",
    "wof:name":"Montarco S.l.",
    "wof:placetype":"venue"
},
  "geometry": {"coordinates":[-3.8724060059,40.4320068359],"type":"Point"}
}