{
  "type": "Feature",
  "properties": {
    "iso:country":"ES",
    "sg:address":"Lermandabidea, 3",
    "sg:city":"Jundiz",
    "sg:orig_category":"Charcuter\u00cdas (al Por Mayor)",
    "sg:phone":"+34 945 29 00 50",
    "sg:postcode":"01015",
    "sg:province":"\u00c1lava",
    "wof:name":"Carnicas Mirotz S.l.",
    "wof:placetype":"venue"
},
  "geometry": {"coordinates":[-6.1999697685,43.3617782593],"type":"Point"}
}