{
  "type": "Feature",
  "properties": {
    "iso:country":"ES",
    "sg:address":"Avda Generalitat, 11",
    "sg:city":"Palleja",
    "sg:orig_category":"Inmobiliaria (agencias)",
    "sg:phone":"+34 936 63 31 11",
    "sg:postcode":"08780",
    "sg:province":"Barcelona",
    "sg:website":"www.urbisfimar.com",
    "wof:name":"Loimel S.l",
    "wof:placetype":"venue"
},
  "geometry": {"coordinates":[1.9974169731,41.4216499329],"type":"Point"}
}