{
  "type": "Feature",
  "properties": {
    "iso:country":"ES",
    "sg:address":"Calle de Madrid, 34",
    "sg:city":"Alcantarilla",
    "sg:orig_category":"Plomeros",
    "sg:phone":"+34 968 80 17 96",
    "sg:postcode":"30820",
    "sg:province":"Murcia",
    "wof:name":"Gonzalo Lopez Rafael",
    "wof:placetype":"venue"
},
  "geometry": {"coordinates":[-1.2141230106,37.9728546143],"type":"Point"}
}