{
  "type": "Feature",
  "properties": {
    "addr:full":"C/ Pere Joan Perpinya, 33 Elche Alicante 03204",
    "addr:housenumber":"33",
    "addr:postcode":"03204",
    "addr:street":"C / Pere Joan Perpinya",
    "iso:country":"ES",
    "sg:address":"C/ Pere Joan Perpinya, 33",
    "sg:city":"Elche",
    "sg:orig_category":"Caf\u00c9s, Bares, Cervecer\u00cdas",
    "sg:phone":"+34 966 63 12 39",
    "sg:postcode":"03204",
    "sg:province":"Alicante",
    "wof:name":"Campello Pacheco Vicente",
    "wof:placetype":"venue"
},
  "geometry": {"coordinates":[-0.7055630088,38.2587432861],"type":"Point"}
}