{
  "type": "Feature",
  "properties": {
    "addr:full":"Calle de San Pedro De Alcantara, 18 Candeleda \u00c1vila 05480",
    "addr:housenumber":"18",
    "addr:postcode":"05480",
    "addr:street":"Calle De;Alcantara",
    "iso:country":"ES",
    "sg:address":"Calle de San Pedro De Alcantara, 18",
    "sg:city":"Candeleda",
    "sg:orig_category":"Electricidad: Instaladores",
    "sg:phone":"+34 920 38 07 64",
    "sg:postcode":"05480",
    "sg:province":"\u00c1vila",
    "wof:name":"Gonzalez Blazquez Jose Antonio",
    "wof:placetype":"venue"
},
  "geometry": {"coordinates":[-5.2415060997,40.1564788818],"type":"Point"}
}