{
  "type": "Feature",
  "properties": {
    "iso:country":"ES",
    "sg:address":"C/ Curtidores, 20",
    "sg:city":"Elche",
    "sg:orig_category":"Promotores Constructores",
    "sg:phone":"+34 966 61 32 37",
    "sg:postcode":"03203",
    "sg:province":"Alicante",
    "wof:name":"Promociones Candalix Sa",
    "wof:placetype":"venue"
},
  "geometry": {"coordinates":[-0.6950579882,38.2622261047],"type":"Point"}
}