{
  "type": "Feature",
  "properties": {
    "addr:full":"Calle de Mora, 19 Sonseca Toledo 45100",
    "addr:housenumber":"19",
    "addr:postcode":"45100",
    "addr:street":"Calle De Mora",
    "iso:country":"ES",
    "sg:address":"Calle de Mora, 19",
    "sg:city":"Sonseca",
    "sg:orig_category":"Alumbrados",
    "sg:phone":"+34 925 38 27 56",
    "sg:postcode":"45100",
    "sg:province":"Toledo",
    "wof:name":"Rodriguez Martin Maria Del Carmen",
    "wof:placetype":"venue"
},
  "geometry": {"coordinates":[-3.9703478813,39.6760597229],"type":"Point"}
}