{
  "type": "Feature",
  "properties": {
    "iso:country":"ES",
    "sg:address":"Avda Europa, 19",
    "sg:city":"Pozuelo De Alarcon",
    "sg:classifiers":[
        {
            "category":"Manufacturing",
            "subcategory":"Building Materials",
            "type":"Manufacturing & Wholesale Goods"
        }
    ],
    "sg:phone":"+34 913 04 32 40",
    "sg:postcode":"28224",
    "sg:province":"Madrid",
    "sg:tags":[
        "bebidas",
        "para",
        "la",
        "de",
        "y",
        "equipo",
        "industria"
    ],
    "sg:website":"www.gbvinartis.com",
    "wof:name":"Bodegas Vinartis",
    "wof:placetype":"venue"
},
  "geometry": {"coordinates":[-3.7874910831,40.4409637451],"type":"Point"}
}