{
  "type": "Feature",
  "properties": {
    "iso:country":"ES",
    "sg:address":"Ctra Rincon De Soto, S/n",
    "sg:city":"Autol",
    "sg:orig_category":"Charcuter\u00cdas (al Por Mayor)",
    "sg:phone":"+34 941 39 05 15",
    "sg:postcode":"26560",
    "sg:province":"La Rioja",
    "wof:name":"Calvo Mazo Alberto",
    "wof:placetype":"venue"
},
  "geometry": {"coordinates":[-2.004224062,42.2131233215],"type":"Point"}
}