{
  "type": "Feature",
  "properties": {
    "iso:country":"ES",
    "sg:address":"Plaz Andalucia De, S/n",
    "sg:city":"Torremolinos",
    "sg:orig_category":"Retoques De Vestidos",
    "sg:phone":"+34 952 38 06 21",
    "sg:postcode":"29620",
    "sg:province":"M\u00e1laga",
    "wof:name":"Ijurco Orbegozo Bibiano",
    "wof:placetype":"venue"
},
  "geometry": {"coordinates":[-4.4981741905,36.6251296997],"type":"Point"}
}