{
  "type": "Feature",
  "properties": {
    "addr:full":"Carrer de Sant Medir, 3 Barcelona Barcelona 08028",
    "addr:housenumber":"3",
    "addr:postcode":"08028",
    "addr:street":"Carrer De Sant Medir",
    "iso:country":"ES",
    "sg:address":"Carrer de Sant Medir, 3",
    "sg:city":"Barcelona",
    "sg:orig_category":"Zapatos (al Por Menor)",
    "sg:phone":"+34 933 39 54 28",
    "sg:postcode":"08028",
    "sg:province":"Barcelona",
    "wof:name":"Uriarte Mutos Natividad",
    "wof:placetype":"venue"
},
  "geometry": {"coordinates":[2.1329340935,41.3752174377],"type":"Point"}
}