{
  "type": "Feature",
  "properties": {
    "iso:country":"ES",
    "sg:address":"Calle de San Francisco, 34",
    "sg:city":"Donostia-san Sebastian",
    "sg:orig_category":"Relojer\u00cda (al Por Menor, Reparaci\u00d3n)",
    "sg:phone":"+34 943 29 12 00",
    "sg:postcode":"20002",
    "sg:province":"Guip\u00f9zcoa",
    "wof:name":"Anibarro Tanco Victor",
    "wof:placetype":"venue"
},
  "geometry": {"coordinates":[-1.9727908373,43.3246231079],"type":"Point"}
}