{
  "type": "Feature",
  "properties": {
    "addr:full":"Calle de Meliton Corti\u00d1as, 11 Viveiro Lugo 27850",
    "addr:housenumber":"11",
    "addr:postcode":"27850",
    "addr:street":"Calle De Meliton Cortin\u0303As",
    "iso:country":"ES",
    "sg:address":"Calle de Meliton Corti\u00d1as, 11",
    "sg:city":"Viveiro",
    "sg:orig_category":"Peluquer\u00cdas, Peluquer\u00cda Mixta",
    "sg:phone":"+34 982 56 18 14",
    "sg:postcode":"27850",
    "sg:province":"Lugo",
    "wof:name":"Garcia Liz Maria Jose",
    "wof:placetype":"venue"
},
  "geometry": {"coordinates":[-7.5959348679,43.6629714966],"type":"Point"}
}