{
  "type": "Feature",
  "properties": {
    "addr:full":"Calle de Bernardo Balbuena, 5 Valdepe\u00f1as Ciudad Real 13300",
    "addr:housenumber":"5",
    "addr:postcode":"13300",
    "addr:street":"Calle De Bernardo Balbuena",
    "iso:country":"ES",
    "sg:address":"Calle de Bernardo Balbuena, 5",
    "sg:city":"Valdepe\u00f1as",
    "sg:orig_category":"Inform\u00c1tica (estudios, Servicios, Asesor\u00cda, Formaci\u00d3n)",
    "sg:phone":"+34 926 31 60 63",
    "sg:postcode":"13300",
    "sg:province":"Ciudad Real",
    "sg:website":"www.sitec-studio.com",
    "wof:name":"Garcia Mu\u00f1oz Vicente",
    "wof:placetype":"venue"
},
  "geometry": {"coordinates":[-3.3854501247,38.7597618103],"type":"Point"}
}