{
  "type": "Feature",
  "properties": {
    "addr:full":"Avda Xubia, 41 Xubia-casadelos La Coru\u00f1a 15510",
    "addr:housenumber":"41",
    "addr:postcode":"15510",
    "addr:street":"Avda Xubia;La Corun\u0303A",
    "iso:country":"ES",
    "sg:address":"Avda Xubia, 41",
    "sg:city":"Xubia-casadelos",
    "sg:orig_category":"Estancos",
    "sg:phone":"+34 981 38 88 24",
    "sg:postcode":"15510",
    "sg:province":"La Coru\u00f1a",
    "wof:name":"Pesta\u00f1a Pacios Pilar",
    "wof:placetype":"venue"
},
  "geometry": {"coordinates":[-8.1507492065,43.5155944824],"type":"Point"}
}