{
  "type": "Feature",
  "properties": {
    "iso:country":"ES",
    "sg:address":"Carrer de Santa Rosa, 26",
    "sg:city":"S. Celoni",
    "sg:orig_category":"Mec\u00c1nico Del Autom\u00d3vil",
    "sg:phone":"+34 938 67 08 44",
    "sg:postcode":"08470",
    "sg:province":"Barcelona",
    "wof:name":"Prat I Cros S.a.",
    "wof:placetype":"venue"
},
  "geometry": {"coordinates":[2.4914801121,41.6874694824],"type":"Point"}
}