{
  "type": "Feature",
  "properties": {
    "iso:country":"ES",
    "sg:address":"Calle de Alferez Barreiro, 6",
    "sg:city":"Baiona",
    "sg:orig_category":"Relojer\u00cda (al Por Menor, Reparaci\u00d3n)",
    "sg:phone":"+34 986 35 52 29",
    "sg:postcode":"36300",
    "sg:province":"Pontevedra",
    "wof:name":"Ruibal Alfaya Fernando",
    "wof:placetype":"venue"
},
  "geometry": {"coordinates":[-8.8475265503,42.1189537048],"type":"Point"}
}