{
  "type": "Feature",
  "properties": {
    "addr:full":"Avda Aquaola, 1 Cenes Vega Granada 18190",
    "addr:housenumber":"1",
    "addr:postcode":"18190",
    "addr:street":"Avda Aquaola",
    "iso:country":"ES",
    "sg:address":"Avda Aquaola, 1",
    "sg:city":"Cenes Vega",
    "sg:orig_category":"Parques De Atracciones Y Centros De Esparcimiento",
    "sg:phone":"+34 958 48 61 89",
    "sg:postcode":"18190",
    "sg:province":"Granada",
    "wof:name":"Parque Acuatico Aquaola.s.l.",
    "wof:placetype":"venue"
},
  "geometry": {"coordinates":[-3.5423738956,37.1603355408],"type":"Point"}
}