{
  "type": "Feature",
  "properties": {
    "iso:country":"ES",
    "sg:address":"Calle de Benito Perez Galdos (de), 13",
    "sg:city":"Mostoles",
    "sg:orig_category":"Internados & Ense\u00d1anza Privada",
    "sg:phone":"+34 916 17 02 69",
    "sg:postcode":"28935",
    "sg:province":"Madrid",
    "wof:name":"Colegio Villaeuropa",
    "wof:placetype":"venue"
},
  "geometry": {"coordinates":[-3.8772830963,40.3226203918],"type":"Point"}
}