{
  "type": "Feature",
  "properties": {
    "addr:full":"Carrer de Jaume Balmes, 46 S. Pere Ribes Barcelona 08810",
    "addr:housenumber":"46",
    "addr:postcode":"08810",
    "addr:street":"Carrer De Jaume Balmes;S. Pere Ribes Barcelona",
    "iso:country":"ES",
    "sg:address":"Carrer de Jaume Balmes, 46",
    "sg:city":"S. Pere Ribes",
    "sg:orig_category":"Arquitectos",
    "sg:phone":"+34 938 96 01 33",
    "sg:postcode":"08810",
    "sg:province":"Barcelona",
    "wof:name":"Biosca I Casas S.l.",
    "wof:placetype":"venue"
},
  "geometry": {"coordinates":[1.7705169916,41.2604789734],"type":"Point"}
}