{
  "type": "Feature",
  "properties": {
    "iso:country":"ES",
    "sg:address":"Barr Peruri, 33",
    "sg:city":"Peruri",
    "sg:orig_category":"Inform\u00c1tica, Ofim\u00c1tica (estudios, Asesor\u00cda, Ingenier\u00cda, Formaci\u00d3n)",
    "sg:phone":"+34 944 91 28 63",
    "sg:postcode":"48940",
    "sg:province":"Vizcaya",
    "sg:website":"www.citiussoftware.com",
    "wof:name":"Citius Software S.l.",
    "wof:placetype":"venue"
},
  "geometry": {"coordinates":[-2.9860789776,43.3275489807],"type":"Point"}
}