{
  "type": "Feature",
  "properties": {
    "addr:full":"Av J V Foix, 74 Barcelona Barcelona 08034",
    "addr:housenumber":"74",
    "addr:postcode":"08034",
    "addr:street":"Av J V Foix",
    "iso:country":"ES",
    "sg:address":"Av J V Foix, 74",
    "sg:city":"Barcelona",
    "sg:orig_category":"Centros Empresariales",
    "sg:phone":"+34 932 05 26 24",
    "sg:postcode":"08034",
    "sg:province":"Barcelona",
    "wof:name":"Ventura Cisternas Celesti",
    "wof:placetype":"venue"
},
  "geometry": {"coordinates":[2.1203188896,41.3964118958],"type":"Point"}
}