{
  "type": "Feature",
  "properties": {
    "addr:full":"Av Finestrat, 1 Torretes Alicante 03570",
    "addr:housenumber":"1",
    "addr:postcode":"03570",
    "addr:street":"Av Finestrat;Alicante",
    "iso:country":"ES",
    "sg:address":"Av Finestrat, 1",
    "sg:city":"Torretes",
    "sg:orig_category":"Mec\u00c1nico Del Autom\u00d3vil",
    "sg:phone":"+34 965 89 09 03",
    "sg:postcode":"03570",
    "sg:province":"Alicante",
    "wof:name":"Talleres Vila Movil S.l.",
    "wof:placetype":"venue"
},
  "geometry": {"coordinates":[-0.2327190042,38.505821228],"type":"Point"}
}