{
  "type": "Feature",
  "properties": {
    "iso:country":"ES",
    "sg:address":"Av Catalunya, 61",
    "sg:city":"Mas Rampinyo",
    "sg:orig_category":"Molduras, Junquillos, Listones Y Molduras Perforadas",
    "sg:phone":"+34 935 64 01 82",
    "sg:postcode":"08110",
    "sg:province":"Barcelona",
    "wof:name":"Pe\u00f1a Brianso Montse",
    "wof:placetype":"venue"
},
  "geometry": {"coordinates":[2.1828510761,41.4946708679],"type":"Point"}
}