{
  "type": "Feature",
  "properties": {
    "addr:full":"Avda Pilar, 41 Forcall Castell\u00f3n 12310",
    "addr:housenumber":"41",
    "addr:postcode":"12310",
    "addr:street":"Avda Pilar;Castello\u0301N",
    "iso:country":"ES",
    "sg:address":"Avda Pilar, 41",
    "sg:city":"Forcall",
    "sg:orig_category":"Transportes Por V\u00cdas Navegables",
    "sg:phone":"+34 964 17 10 77",
    "sg:postcode":"12310",
    "sg:province":"Castell\u00f3n",
    "wof:name":"Miralles Albesa Manuel",
    "wof:placetype":"venue"
},
  "geometry": {"coordinates":[-0.2052379996,40.646270752],"type":"Point"}
}