{
  "type": "Feature",
  "properties": {
    "iso:country":"ES",
    "sg:address":"Carrer de Lluis Pascual Roca, 63",
    "sg:city":"S. Boi Llobregat",
    "sg:orig_category":"Institutos De Belleza",
    "sg:phone":"+34 936 30 01 41",
    "sg:postcode":"08830",
    "sg:province":"Barcelona",
    "wof:name":"Veron Faria Fatima",
    "wof:placetype":"venue"
},
  "geometry": {"coordinates":[2.0363099575,41.3450012207],"type":"Point"}
}