{
  "type": "Feature",
  "properties": {
    "iso:country":"ES",
    "sg:address":"Carrer de Roger De Lluria, 1",
    "sg:city":"Granollers",
    "sg:orig_category":"Servidores Y Editores De Bases De Datos",
    "sg:phone":"+34 938 79 49 84",
    "sg:postcode":"08401",
    "sg:province":"Barcelona",
    "sg:website":"www.profeline.com",
    "wof:name":"Productora De Formacion En Linea S.l.",
    "wof:placetype":"venue"
},
  "geometry": {"coordinates":[2.2856199741,41.603477478],"type":"Point"}
}