{
  "type": "Feature",
  "properties": {
    "iso:country":"ES",
    "sg:address":"Avda Galicia, 82",
    "sg:city":"Cacabelos",
    "sg:orig_category":"Electricidad Veh\u00cdculo",
    "sg:phone":"+34 987 54 60 82",
    "sg:postcode":"24540",
    "sg:province":"Le\u00f3n",
    "wof:name":"Pintor Fernandez Manuel",
    "wof:placetype":"venue"
},
  "geometry": {"coordinates":[-6.7268538475,42.599281311],"type":"Point"}
}