{
  "type": "Feature",
  "properties": {
    "addr:full":"Carr Cervantes, 53 Villanueva De Castellon Valencia 46270",
    "addr:housenumber":"53",
    "addr:postcode":"46270",
    "addr:street":"Carr Cervantes",
    "iso:country":"ES",
    "sg:address":"Carr Cervantes, 53",
    "sg:city":"Villanueva De Castellon",
    "sg:orig_category":"Chapister\u00cda",
    "sg:phone":"+34 962 45 40 16",
    "sg:postcode":"46270",
    "sg:province":"Valencia",
    "wof:name":"Auto Wagen Cortes S.l.",
    "wof:placetype":"venue"
},
  "geometry": {"coordinates":[-0.5113490224,39.0756912231],"type":"Point"}
}