{
  "type": "Feature",
  "properties": {
    "iso:country":"ES",
    "sg:address":"Calle de Nazario Calonge (de), 7",
    "sg:city":"San Fernando De Henares",
    "sg:orig_category":"Centros De Salud",
    "sg:phone":"+34 916 73 89 87",
    "sg:postcode":"28830",
    "sg:province":"Madrid",
    "wof:name":"Asociacion Para La Prevencion Y Rehabilitacion De Alcoholicos",
    "wof:placetype":"venue"
},
  "geometry": {"coordinates":[-3.5287032127,40.4271697998],"type":"Point"}
}