{
  "type": "Feature",
  "properties": {
    "addr:full":"Calle de Cristobal Bordiu, 63 Madrid Madrid 28003",
    "addr:housenumber":"63",
    "addr:postcode":"madrid;28003",
    "addr:street":"Calle De Cristobal Bordiu",
    "iso:country":"ES",
    "sg:address":"Calle de Cristobal Bordiu, 63",
    "sg:city":"Madrid",
    "sg:orig_category":"Inform\u00c1tica (estudios, Servicios, Asesor\u00cda, Formaci\u00d3n)",
    "sg:phone":"+34 915 33 13 32",
    "sg:postcode":"28003",
    "sg:province":"Madrid",
    "sg:website":"www.laoficinasinpapel.com",
    "wof:name":"La Oficina Sin Papel S.l",
    "wof:placetype":"venue"
},
  "geometry": {"coordinates":[-3.6952412128,40.4428710938],"type":"Point"}
}