{
  "type": "Feature",
  "properties": {
    "iso:country":"ES",
    "sg:address":"Calle de Ramiro Valbuena, 13",
    "sg:city":"Le\u00f3n",
    "sg:orig_category":"Arquitectos",
    "sg:phone":"+34 987 23 41 34",
    "sg:postcode":"24002",
    "sg:province":"Le\u00f3n",
    "wof:name":"Suarez Milian Oscar Luis",
    "wof:placetype":"venue"
},
  "geometry": {"coordinates":[-5.5752739906,42.5998573303],"type":"Point"}
}