{
  "type": "Feature",
  "properties": {
    "addr:full":"Poligono 14, 211 Binissalem Islas Baleares 07350",
    "addr:housenumber":"211",
    "addr:postcode":"07350",
    "addr:street":"Poligono 14",
    "iso:country":"ES",
    "sg:address":"Poligono 14, 211",
    "sg:city":"Binissalem",
    "sg:orig_category":"Inform\u00c1tica (estudios, Servicios, Asesor\u00cda, Formaci\u00d3n)",
    "sg:phone":"+34 971 87 01 20",
    "sg:postcode":"07350",
    "sg:province":"Islas Baleares",
    "wof:name":"Mallorhard S.l.",
    "wof:placetype":"venue"
},
  "geometry": {"coordinates":[2.8477370739,39.6892318726],"type":"Point"}
}