{
  "type": "Feature",
  "properties": {
    "addr:full":"Av. Constitucio, 4 Calig Castell\u00f3n 12589",
    "addr:housenumber":"4",
    "addr:postcode":"12589",
    "addr:street":"Av. Constitucio;Castello\u0301N",
    "iso:country":"ES",
    "sg:address":"Av. Constitucio, 4",
    "sg:city":"Calig",
    "sg:orig_category":"Cajas De Ahorro",
    "sg:phone":"+34 964 49 20 83",
    "sg:postcode":"12589",
    "sg:province":"Castell\u00f3n",
    "wof:name":"Caja De Ahorros De Valencia Castellon Y Alicante",
    "wof:placetype":"venue"
},
  "geometry": {"coordinates":[0.3553420007,40.4625282288],"type":"Point"}
}