{
  "type": "Feature",
  "properties": {
    "addr:full":"Carrer de Doctor Barraquer, 35 Ondara Alicante 03760",
    "addr:housenumber":"35",
    "addr:postcode":"03760",
    "addr:street":"Carrer De Doctor Barraquer",
    "iso:country":"ES",
    "sg:address":"Carrer de Doctor Barraquer, 35",
    "sg:city":"Ondara",
    "sg:orig_category":"Ense\u00d1anza: Comercio, Gesti\u00d3n, Inform\u00c1tica",
    "sg:phone":"+34 965 76 71 73",
    "sg:postcode":"03760",
    "sg:province":"Alicante",
    "wof:name":"Cebolla Segui Francisco",
    "wof:placetype":"venue"
},
  "geometry": {"coordinates":[0.0140800001,38.8289108276],"type":"Point"}
}