{
  "type": "Feature",
  "properties": {
    "addr:full":"Crta. Mazarron, Km. 0002,0 Sangonera Verde Murcia 30833",
    "addr:postcode":"30833",
    "addr:street":"Crta. Mazarron Km. 0002,0 Sangonera Verde",
    "iso:country":"ES",
    "sg:address":"Crta. Mazarron, Km. 0002,0",
    "sg:city":"Sangonera Verde",
    "sg:orig_category":"Frutas Y Legumbres Frescas (al Por Mayor)",
    "sg:phone":"+34 968 86 60 70",
    "sg:postcode":"30833",
    "sg:province":"Murcia",
    "wof:name":"Guerrero Fuentes Pedro",
    "wof:placetype":"venue"
},
  "geometry": {"coordinates":[-1.2069989443,37.9333190918],"type":"Point"}
}