{
  "type": "Feature",
  "properties": {
    "addr:full":"Calle de Solidaridad, 51 Sevilla Sevilla 41006",
    "addr:housenumber":"51",
    "addr:postcode":"41006",
    "addr:street":"Calle De Solidaridad",
    "iso:country":"ES",
    "sg:address":"Calle de Solidaridad, 51",
    "sg:city":"Sevilla",
    "sg:orig_category":"Panader\u00cdas, Panader\u00cdas",
    "sg:phone":"+34 954 25 13 82",
    "sg:postcode":"41006",
    "sg:province":"Sevilla",
    "wof:name":"Garcia Antequera Antonio",
    "wof:placetype":"venue"
},
  "geometry": {"coordinates":[-5.9311671257,37.3735542297],"type":"Point"}
}