{
  "type": "Feature",
  "properties": {
    "iso:country":"ES",
    "sg:address":"Calle de Basilio Paraiso, 5",
    "sg:city":"Madrid",
    "sg:orig_category":"Autob\u00das (explotaci\u00d3n Y Servicios De)",
    "sg:phone":"+34 913 55 61 79",
    "sg:postcode":"28028",
    "sg:province":"Madrid",
    "wof:name":"Autocares Salas S.a.",
    "wof:placetype":"venue"
},
  "geometry": {"coordinates":[-3.6641840935,40.4224090576],"type":"Point"}
}