{
  "type": "Feature",
  "properties": {
    "addr:full":"Calle de David Fahrenheit, 13 Zaragoza Zaragoza 50015",
    "addr:housenumber":"13",
    "addr:postcode":"50015",
    "addr:street":"Calle De David Fahrenheit",
    "iso:country":"ES",
    "sg:address":"Calle de David Fahrenheit, 13",
    "sg:city":"Zaragoza",
    "sg:orig_category":"Restaurantes",
    "sg:phone":"+34 976 73 46 07",
    "sg:postcode":"50015",
    "sg:province":"Zaragoza",
    "wof:name":"Don Churro S.c.",
    "wof:placetype":"venue"
},
  "geometry": {"coordinates":[-0.8655387759,41.6771850586],"type":"Point"}
}