{
  "type": "Feature",
  "properties": {
    "iso:country":"ES",
    "sg:address":"Avda Reyes Catolicos, 53",
    "sg:city":"Alhaurin Torre",
    "sg:orig_category":"Quincaller\u00cda (al Por Menor)",
    "sg:phone":"+34 952 41 54 82",
    "sg:postcode":"29130",
    "sg:province":"M\u00e1laga",
    "wof:name":"Ferreteria Laurofer S.l",
    "wof:placetype":"venue"
},
  "geometry": {"coordinates":[-4.5667190552,36.6618614197],"type":"Point"}
}