{
  "type": "Feature",
  "properties": {
    "iso:country":"ES",
    "sg:address":"Urbz Las Ca\u00f1as I, 3",
    "sg:city":"Arce",
    "sg:orig_category":"Iglesia Cat\u00d3lica",
    "sg:phone":"+34 942 57 54 08",
    "sg:postcode":"39478",
    "sg:province":"Cantabria",
    "wof:name":"Laya Rasines Jose Manuel",
    "wof:placetype":"venue"
},
  "geometry": {"coordinates":[-3.9462940693,43.4310302734],"type":"Point"}
}