{
  "type": "Feature",
  "properties": {
    "addr:full":"Calle de Juan Mari Altuna Kalea, 4 Durango Vizcaya 48200",
    "addr:housenumber":"4",
    "addr:postcode":"48200",
    "addr:street":"Calle De Juan Mari Altuna Kalea",
    "iso:country":"ES",
    "sg:address":"Calle de Juan Mari Altuna Kalea, 4",
    "sg:city":"Durango",
    "sg:orig_category":"Peluqueros: De Se\u00d1oras",
    "sg:phone":"+34 946 20 16 89",
    "sg:postcode":"48200",
    "sg:province":"Vizcaya",
    "wof:name":"Sarabia Garcia Maria Del Carmen",
    "wof:placetype":"venue"
},
  "geometry": {"coordinates":[-2.6280510426,43.1684494019],"type":"Point"}
}