{
  "type": "Feature",
  "properties": {
    "addr:full":"Plaz Iglesia, S/n Pizarra M\u00e1laga 29560",
    "addr:housenumber":"s / n",
    "addr:postcode":"29560",
    "iso:country":"ES",
    "sg:address":"Plaz Iglesia, S/n",
    "sg:city":"Pizarra",
    "sg:orig_category":"Iglesia Cat\u00d3lica",
    "sg:phone":"+34 952 48 31 24",
    "sg:postcode":"29560",
    "sg:province":"M\u00e1laga",
    "wof:name":"Obispado De Malaga",
    "wof:placetype":"venue"
},
  "geometry": {"coordinates":[-4.7088971138,36.7675361633],"type":"Point"}
}