{
  "type": "Feature",
  "properties": {
    "iso:country":"ES",
    "sg:address":"Jose Ma Beobide, 7",
    "sg:city":"Iru\u00f1a",
    "sg:orig_category":"Perfumer\u00cda (al Por Menor)",
    "sg:phone":"+34 948 23 94 82",
    "sg:postcode":"31005",
    "sg:province":"Navarra",
    "wof:name":"Pe\u00f1as Azcona Teresa",
    "wof:placetype":"venue"
},
  "geometry": {"coordinates":[-1.6454520226,42.8038444519],"type":"Point"}
}