{
  "type": "Feature",
  "properties": {
    "iso:country":"ES",
    "sg:address":"C/ Sant Mer, 73",
    "sg:city":"Banyoles",
    "sg:orig_category":"Venta Al Preg\u00d3n",
    "sg:phone":"+34 972 57 03 70",
    "sg:postcode":"17820",
    "sg:province":"Girona",
    "wof:name":"Prat Ayats Jaime",
    "wof:placetype":"venue"
},
  "geometry": {"coordinates":[2.7604949474,42.1227340698],"type":"Point"}
}