{
  "type": "Feature",
  "properties": {
    "iso:country":"ES",
    "sg:address":"Calle de Eretza Monte, 15",
    "sg:city":"Bilbao",
    "sg:orig_category":"Molduras, Junquillos, Listones Y Molduras Perforadas",
    "sg:phone":"+34 944 21 61 17",
    "sg:postcode":"48003",
    "sg:province":"Vizcaya",
    "sg:website":"www.kommeling.com",
    "wof:name":"Profine Iberia S. A.",
    "wof:placetype":"venue"
},
  "geometry": {"coordinates":[-2.9325785637,43.2291870117],"type":"Point"}
}