{
  "type": "Feature",
  "properties": {
    "addr:full":"Calle de Piedra Villazar, 2 Vista De Los Angeles-rumina Almer\u00eda 04638",
    "addr:housenumber":"2",
    "addr:postcode":"04638",
    "addr:street":"Calle De Piedra Villazar;Vista De Los Angeles-Rumina Almeri\u0301A",
    "iso:country":"ES",
    "sg:address":"Calle de Piedra Villazar, 2",
    "sg:city":"Vista De Los Angeles-rumina",
    "sg:orig_category":"Cajas De Ahorro",
    "sg:phone":"+34 950 47 83 12",
    "sg:postcode":"04638",
    "sg:province":"Almer\u00eda",
    "sg:website":"www.lacaixa.es",
    "wof:name":"Caixa D'estalvis I Pensions De Barcelona",
    "wof:placetype":"venue"
},
  "geometry": {"coordinates":[-1.8467450142,37.1402359009],"type":"Point"}
}