{
  "type": "Feature",
  "properties": {
    "iso:country":"ES",
    "sg:address":"Calle de Cochabamba, 17",
    "sg:city":"Madrid",
    "sg:orig_category":"Promotores Constructores",
    "sg:phone":"+34 914 57 62 52",
    "sg:postcode":"28016",
    "sg:province":"Madrid",
    "wof:name":"Voladuras Controladas S. A.",
    "wof:placetype":"venue"
},
  "geometry": {"coordinates":[-3.680205822,40.455745697],"type":"Point"}
}