{
  "type": "Feature",
  "properties": {
    "addr:full":"Calle de Garcia Goyena, 19 Tafalla Navarra 31300",
    "addr:housenumber":"19",
    "addr:postcode":"31300",
    "addr:street":"Calle De Garcia Goyena",
    "iso:country":"ES",
    "sg:address":"Calle de Garcia Goyena, 19",
    "sg:city":"Tafalla",
    "sg:orig_category":"Asociaciones, Organismos Culturales Y Socioeducativos",
    "sg:phone":"+34 948 70 19 74",
    "sg:postcode":"31300",
    "sg:province":"Navarra",
    "wof:name":"Sociedad Gastronomica Balgorra",
    "wof:placetype":"venue"
},
  "geometry": {"coordinates":[-1.6764199734,42.5265350342],"type":"Point"}
}