{
  "type": "Feature",
  "properties": {
    "iso:country":"ES",
    "sg:address":"Calle de Prim, 14",
    "sg:city":"Donostia-san Sebastian",
    "sg:orig_category":"Asesor\u00cda Fiscal Y Jur\u00cddica",
    "sg:phone":"+34 943 46 42 51",
    "sg:postcode":"20006",
    "sg:province":"Guip\u00f9zcoa",
    "wof:name":"Jfk Autogestion S.l.",
    "wof:placetype":"venue"
},
  "geometry": {"coordinates":[-1.9799389839,43.3168411255],"type":"Point"}
}