{
  "type": "Feature",
  "properties": {
    "iso:country":"ES",
    "sg:address":"Carrer de Porta De Jesus, 2",
    "sg:city":"Palma",
    "sg:orig_category":"Peluquer\u00cdas, Peluquer\u00cda Mixta",
    "sg:phone":"+34 971 72 46 33",
    "sg:postcode":"07003",
    "sg:province":"Islas Baleares",
    "wof:name":"Petra Ferragut S.l.",
    "wof:placetype":"venue"
},
  "geometry": {"coordinates":[2.6481759548,39.5753707886],"type":"Point"}
}