{
  "type": "Feature",
  "properties": {
    "iso:country":"ES",
    "sg:address":"Pl Espanya, 4",
    "sg:city":"Prat Llobregat",
    "sg:orig_category":"Peluqueros: De Se\u00d1oras",
    "sg:phone":"+34 933 79 02 74",
    "sg:postcode":"08820",
    "sg:province":"Barcelona",
    "wof:name":"Bollo Anton Francisca",
    "wof:placetype":"venue"
},
  "geometry": {"coordinates":[2.0936799049,41.3313331604],"type":"Point"}
}