{
  "type": "Feature",
  "properties": {
    "addr:full":"Carr Conradors, S/n Cabaneta Islas Baleares 07141",
    "addr:housenumber":"s",
    "addr:postcode":"07141",
    "addr:street":"Carr Conradors;/ N",
    "iso:country":"ES",
    "sg:address":"Carr Conradors, S/n",
    "sg:city":"Cabaneta",
    "sg:orig_category":"Platos Preparados Refrigerados (fabricaci\u00d3n, Al Por Mayor)",
    "sg:phone":"+34 971 22 69 66",
    "sg:postcode":"07141",
    "sg:province":"Islas Baleares",
    "wof:name":"New Business Team S.l.",
    "wof:placetype":"venue"
},
  "geometry": {"coordinates":[2.7445349693,39.6195487976],"type":"Point"}
}