{
  "type": "Feature",
  "properties": {
    "addr:full":"Pla\u00c7 Vila, 21 Eivissa Islas Baleares 07800",
    "addr:postcode":"07800",
    "iso:country":"ES",
    "sg:address":"Pla\u00c7 Vila, 21",
    "sg:city":"Eivissa",
    "sg:orig_category":"Molduras, Junquillos, Listones Y Molduras Perforadas",
    "sg:phone":"+34 971 30 33 11",
    "sg:postcode":"07800",
    "sg:province":"Islas Baleares",
    "wof:name":"Woodward Crowley Anthony",
    "wof:placetype":"venue"
},
  "geometry": {"coordinates":[1.4323778152,38.9088554382],"type":"Point"}
}