{
  "type": "Feature",
  "properties": {
    "addr:full":"Calle de Doctor Fleming, 15 Coru\u00d1a La Coru\u00f1a 15005",
    "addr:housenumber":"15",
    "addr:postcode":"15005",
    "addr:street":"Calle De Doctor Fleming;La Corun\u0303A",
    "iso:country":"ES",
    "sg:address":"Calle de Doctor Fleming, 15",
    "sg:city":"Coru\u00d1a",
    "sg:orig_category":"Electricidad Veh\u00cdculo",
    "sg:phone":"+34 981 25 94 94",
    "sg:postcode":"15005",
    "sg:province":"La Coru\u00f1a",
    "wof:name":"Prado Fachal Eugenio",
    "wof:placetype":"venue"
},
  "geometry": {"coordinates":[-8.4082145691,43.3601913452],"type":"Point"}
}