{
  "type": "Feature",
  "properties": {
    "iso:country":"ES",
    "sg:address":"Crta Fuensanta De Martos, S/n",
    "sg:city":"Martos",
    "sg:orig_category":"Mec\u00c1nico Del Autom\u00d3vil",
    "sg:phone":"+34 953 55 02 48",
    "sg:postcode":"23600",
    "sg:province":"Ja\u00e9n",
    "wof:name":"Marchal Lopez Manuel",
    "wof:placetype":"venue"
},
  "geometry": {"coordinates":[-3.9675738811,37.7077941895],"type":"Point"}
}