{
  "type": "Feature",
  "properties": {
    "iso:country":"ES",
    "sg:address":"Avda Agustin Gonzalez, S/n",
    "sg:city":"Posada",
    "sg:orig_category":"Promotores Constructores",
    "sg:phone":"+34 985 77 12 94",
    "sg:postcode":"33424",
    "sg:province":"Asturias",
    "wof:name":"Construcciones Marinelli S.a.",
    "wof:placetype":"venue"
},
  "geometry": {"coordinates":[-5.8504490852,43.4400978088],"type":"Point"}
}