{
  "type": "Feature",
  "properties": {
    "addr:full":"Calle de Palleter, 21 Alginet Valencia 46230",
    "addr:housenumber":"21",
    "addr:postcode":"46230",
    "addr:street":"Calle De Palleter",
    "iso:country":"ES",
    "sg:address":"Calle de Palleter, 21",
    "sg:city":"Alginet",
    "sg:orig_category":"Institutos De Belleza",
    "sg:phone":"+34 961 75 19 26",
    "sg:postcode":"46230",
    "sg:province":"Valencia",
    "wof:name":"Centre De Estetica Simo C.b.",
    "wof:placetype":"venue"
},
  "geometry": {"coordinates":[-0.4695790112,39.2660903931],"type":"Point"}
}