{
  "type": "Feature",
  "properties": {
    "iso:country":"ES",
    "sg:address":"Calle de Monleon, 16",
    "sg:city":"Salamanca",
    "sg:orig_category":"Carnicer\u00cdas, Carnicer\u00cdas",
    "sg:phone":"+34 923 25 58 33",
    "sg:postcode":"37004",
    "sg:province":"Salamanca",
    "wof:name":"Garcia Gomez Toribio",
    "wof:placetype":"venue"
},
  "geometry": {"coordinates":[-5.6494960785,40.9756851196],"type":"Point"}
}