{
  "type": "Feature",
  "properties": {
    "addr:full":"Calle de Alferez Arguelles, 17 Langreo Asturias 33930",
    "addr:housenumber":"17",
    "addr:postcode":"33930",
    "addr:street":"Calle De Alferez Arguelles",
    "iso:country":"ES",
    "sg:address":"Calle de Alferez Arguelles, 17",
    "sg:city":"Langreo",
    "sg:classifiers":[
        {
            "category":"Personal",
            "subcategory":"Barber",
            "type":"Services"
        }
    ],
    "sg:phone":"+34 985 69 73 15",
    "sg:postcode":"33930",
    "sg:province":"Asturias",
    "sg:tags":[
        "caballeros",
        "de",
        "peluqueros"
    ],
    "wof:name":"Martinez Montes Manuel Faustino",
    "wof:placetype":"venue"
},
  "geometry": {"coordinates":[-5.6918544769,43.3094749451],"type":"Point"}
}