{
  "type": "Feature",
  "properties": {
    "iso:country":"ES",
    "sg:address":"Carrer de Rector B Martorell, 4",
    "sg:city":"Vileta -son Rapinya",
    "sg:orig_category":"Papeler\u00cdas, Librer\u00cdas",
    "sg:phone":"+34 971 79 81 38",
    "sg:postcode":"07013",
    "sg:province":"Islas Baleares",
    "wof:name":"Correa Latorre Patricia",
    "wof:placetype":"venue"
},
  "geometry": {"coordinates":[2.6116199493,39.5895957947],"type":"Point"}
}