{
  "type": "Feature",
  "properties": {
    "iso:country":"ES",
    "sg:address":"Calle de Amor De Dios, 29",
    "sg:city":"Sevilla",
    "sg:orig_category":"M\u00c1rmoles, Granitos Y Piedras Naturales",
    "sg:phone":"+34 954 38 26 56",
    "sg:postcode":"41002",
    "sg:province":"Sevilla",
    "wof:name":"Garcia Criado Olga Maria",
    "wof:placetype":"venue"
},
  "geometry": {"coordinates":[-5.9945211411,37.3952484131],"type":"Point"}
}