{
  "type": "Feature",
  "properties": {
    "addr:full":"Carrer de Gremi De Boters, 17 Poligon Industrial De Son Castello Islas Baleares 07009",
    "addr:housenumber":"17",
    "addr:postcode":"07009",
    "addr:street":"Carrer De Gremi De Boters;Islas",
    "iso:country":"ES",
    "sg:address":"Carrer de Gremi De Boters, 17",
    "sg:city":"Poligon Industrial De Son Castello",
    "sg:orig_category":"Aluminio Y Aleaciones (producci\u00d3n, Transformaci\u00d3n, Negocio)",
    "sg:phone":"+34 971 43 21 29",
    "sg:postcode":"07009",
    "sg:province":"Islas Baleares",
    "wof:name":"Aluminio Las Islas S.l.",
    "wof:placetype":"venue"
},
  "geometry": {"coordinates":[2.8577105999,39.5341796875],"type":"Point"}
}