{
  "type": "Feature",
  "properties": {
    "addr:full":"Pla\u00c7 Josep Roca, 28 Peramola Lleida 25790",
    "addr:housenumber":"28",
    "addr:postcode":"25790",
    "addr:street":"Roca",
    "iso:country":"ES",
    "sg:address":"Pla\u00c7 Josep Roca, 28",
    "sg:city":"Peramola",
    "sg:orig_category":"Agricultura: Abastecimiento Y Cosechado (negocio)",
    "sg:phone":"+34 973 47 02 73",
    "sg:postcode":"25790",
    "sg:province":"Lleida",
    "wof:name":"Ribera Sinca Hilario",
    "wof:placetype":"venue"
},
  "geometry": {"coordinates":[1.3136800528,42.0673789978],"type":"Point"}
}