{
  "type": "Feature",
  "properties": {
    "addr:full":"Plaz Maestro Mateo, 4 Coru\u00d1a A Coru\u00f1a 15004",
    "addr:housenumber":"4",
    "addr:postcode":"15004",
    "addr:street":"Plaz Maestro Mateo;Corun\u0303A",
    "iso:country":"ES",
    "sg:address":"Plaz Maestro Mateo, 4",
    "sg:city":"Coru\u00d1a",
    "sg:orig_category":"Ense\u00d1anza Variada",
    "sg:phone":"+34 900 25 05 00",
    "sg:postcode":"15004",
    "sg:province":"A Coru\u00f1a",
    "sg:website":"www.tagformacion.com",
    "wof:name":"Tag Formacion S.l.",
    "wof:placetype":"venue"
},
  "geometry": {"coordinates":[-8.4113264084,43.3663291931],"type":"Point"}
}