{
  "type": "Feature",
  "properties": {
    "addr:full":"Calle de Santa Teresa De Jesus, 22 Oviedo Asturias 33005",
    "addr:housenumber":"22",
    "addr:postcode":"33005",
    "addr:street":"Calle De Santa Teresa De Jesus",
    "iso:country":"ES",
    "sg:address":"Calle de Santa Teresa De Jesus, 22",
    "sg:city":"Oviedo",
    "sg:orig_category":"Perfumer\u00cda (al Por Menor)",
    "sg:phone":"+34 985 23 49 72",
    "sg:postcode":"33005",
    "sg:province":"Asturias",
    "wof:name":"Garcia Alvarez Maria Jose",
    "wof:placetype":"venue"
},
  "geometry": {"coordinates":[-5.8537192345,43.3610153198],"type":"Point"}
}