{
  "type": "Feature",
  "properties": {
    "addr:full":"Avda Port, Del, 9 San Gabriel Alicante 03710",
    "addr:housenumber":"9",
    "addr:postcode":"03710",
    "addr:street":"Avda Port Del",
    "iso:country":"ES",
    "sg:address":"Avda Port, Del, 9",
    "sg:city":"San Gabriel",
    "sg:orig_category":"Art\u00cdculos De Regalo (al Por Menor)",
    "sg:phone":"+34 965 83 89 61",
    "sg:postcode":"03710",
    "sg:province":"Alicante",
    "wof:name":"Souvenirs Desiree S.l.l.",
    "wof:placetype":"venue"
},
  "geometry": {"coordinates":[0.0535200015,38.6515808105],"type":"Point"}
}