{
  "type": "Feature",
  "properties": {
    "iso:country":"ES",
    "sg:address":"Calle de Carrion, 8",
    "sg:city":"Posada",
    "sg:orig_category":"Librer\u00cdas",
    "sg:phone":"+34 985 77 22 71",
    "sg:postcode":"33424",
    "sg:province":"Asturias",
    "wof:name":"Rodriguez Alonso Rosa Maria",
    "wof:placetype":"venue"
},
  "geometry": {"coordinates":[-5.8494944572,43.4392852783],"type":"Point"}
}