{
  "type": "Feature",
  "properties": {
    "addr:full":"Plaz Espa\u00d1a, 14 Carbonero El Mayor Segovia 40270",
    "addr:housenumber":"14",
    "addr:postcode":"40270",
    "addr:street":"Plaz Espan\u0303A",
    "iso:country":"ES",
    "sg:address":"Plaz Espa\u00d1a, 14",
    "sg:city":"Carbonero El Mayor",
    "sg:orig_category":"Carnicer\u00cdas, Carnicer\u00cdas",
    "sg:phone":"+34 921 56 04 64",
    "sg:postcode":"40270",
    "sg:province":"Segovia",
    "wof:name":"Garcia Manso Honorio",
    "wof:placetype":"venue"
},
  "geometry": {"coordinates":[-4.2684340477,41.1229743958],"type":"Point"}
}