{
  "type": "Feature",
  "properties": {
    "addr:full":"Carrer de Ciprer (del), 6 Gata Gorgos Alicante 03740",
    "addr:housenumber":"6",
    "addr:postcode":"03740",
    "addr:street":"Carrer De Ciprer Del",
    "iso:country":"ES",
    "sg:address":"Carrer de Ciprer (del), 6",
    "sg:city":"Gata Gorgos",
    "sg:orig_category":"Delegados, Agentes De Tr\u00c1nsito, Auxiliares De Transporte Internacional",
    "sg:phone":"+34 965 75 66 47",
    "sg:postcode":"03740",
    "sg:province":"Alicante",
    "wof:name":"Agudo Jimenez Nicolas",
    "wof:placetype":"venue"
},
  "geometry": {"coordinates":[0.1276915073,38.8164672852],"type":"Point"}
}