{
  "type": "Feature",
  "properties": {
    "iso:country":"ES",
    "sg:address":"Avda Ciudad De Barcelona, 178",
    "sg:city":"Madrid",
    "sg:orig_category":"Farmacias",
    "sg:phone":"+34 915 52 31 24",
    "sg:postcode":"28007",
    "sg:province":"Madrid",
    "wof:name":"Gomez-chacon Fernandez Isabel",
    "wof:placetype":"venue"
},
  "geometry": {"coordinates":[-3.6759710312,40.4017066956],"type":"Point"}
}