{
  "type": "Feature",
  "properties": {
    "iso:country":"ES",
    "sg:address":"Carr Pietat, S/n",
    "sg:city":"Villarreal",
    "sg:orig_category":"Decoraci\u00d3n: Instalaci\u00d3n Y Talleres",
    "sg:phone":"+34 964 52 16 66",
    "sg:postcode":"12540",
    "sg:province":"Castell\u00f3n",
    "wof:name":"Limo Casals Juan Jose",
    "wof:placetype":"venue"
},
  "geometry": {"coordinates":[-0.1145277992,39.93542099],"type":"Point"}
}