{
  "type": "Feature",
  "properties": {
    "iso:country":"ES",
    "sg:address":"Calle de Sevilla, 7",
    "sg:city":"Valencia",
    "sg:orig_category":"Mudanzas",
    "sg:phone":"+34 963 74 59 12",
    "sg:postcode":"46006",
    "sg:province":"Valencia",
    "wof:name":"Signes Mudanzas S. A.",
    "wof:placetype":"venue"
},
  "geometry": {"coordinates":[-0.3740609884,39.4641418457],"type":"Point"}
}