{
  "type": "Feature",
  "properties": {
    "addr:full":"Pol Ind Juyarco, S/n Denia Alicante 03700",
    "addr:housenumber":"s",
    "addr:postcode":"03700",
    "addr:street":"/ N",
    "iso:country":"ES",
    "sg:address":"Pol Ind Juyarco, S/n",
    "sg:city":"Denia",
    "sg:orig_category":"Insecticidas, Fumigaci\u00d3n",
    "sg:phone":"+34 965 78 13 37",
    "sg:postcode":"03700",
    "sg:province":"Alicante",
    "wof:name":"Promociones Y Desarrollo Agricola S.l.",
    "wof:placetype":"venue"
},
  "geometry": {"coordinates":[0.1114400029,38.8428153992],"type":"Point"}
}