{
  "type": "Feature",
  "properties": {
    "addr:full":"Calle de Sol (del), 3 Linea De La Concepcion C\u00e1diz 11300",
    "addr:housenumber":"3",
    "addr:postcode":"11300",
    "addr:street":"Calle De Sol Del;Ca\u0301Diz",
    "iso:country":"ES",
    "sg:address":"Calle de Sol (del), 3",
    "sg:city":"Linea De La Concepcion",
    "sg:orig_category":"Telas Y Sedas (al Por Menor)",
    "sg:phone":"+34 956 17 31 75",
    "sg:postcode":"11300",
    "sg:province":"C\u00e1diz",
    "wof:name":"Umbria Morales Francisco",
    "wof:placetype":"venue"
},
  "geometry": {"coordinates":[-5.34851408,36.1618919373],"type":"Point"}
}