{
  "type": "Feature",
  "properties": {
    "iso:country":"ES",
    "sg:address":"Calle de Mar Egeo, S/n",
    "sg:city":"Majadahonda",
    "sg:orig_category":"Peluquer\u00cdas, Peluquer\u00cda Mixta",
    "sg:phone":"+34 916 38 87 51",
    "sg:postcode":"28220",
    "sg:province":"Madrid",
    "wof:name":"Bucles S.a.l.",
    "wof:placetype":"venue"
},
  "geometry": {"coordinates":[-3.8656980991,40.4674491882],"type":"Point"}
}