{
  "type": "Feature",
  "properties": {
    "addr:full":"Pl. Los Fueros, 19 Estella Navarra 31200",
    "addr:housenumber":"19",
    "addr:postcode":"31200",
    "addr:street":"Los Fueros",
    "iso:country":"ES",
    "sg:address":"Pl. Los Fueros, 19",
    "sg:city":"Estella",
    "sg:orig_category":"Pescader\u00cdas (al Por Menor)",
    "sg:phone":"+34 948 55 07 02",
    "sg:postcode":"31200",
    "sg:province":"Navarra",
    "wof:name":"Pescaderia La Blanca S.l.",
    "wof:placetype":"venue"
},
  "geometry": {"coordinates":[-2.0317780972,42.6725387573],"type":"Point"}
}