{
  "type": "Feature",
  "properties": {
    "iso:country":"ES",
    "sg:address":"Carr Metge Trueta, S/n",
    "sg:city":"Almenar",
    "sg:orig_category":"Material Y Suministros Para Perforaciones, Sondeos",
    "sg:phone":"+34 973 77 05 50",
    "sg:postcode":"25126",
    "sg:province":"Lleida",
    "wof:name":"Cases Vilagrosa Josep",
    "wof:placetype":"venue"
},
  "geometry": {"coordinates":[0.5716549754,41.795173645],"type":"Point"}
}