{
  "type": "Feature",
  "properties": {
    "iso:country":"ES",
    "sg:address":"Calle de Marques De Remisa, 13",
    "sg:city":"Tarancon",
    "sg:orig_category":"Electricidad: Instaladores",
    "sg:phone":"+34 969 32 41 51",
    "sg:postcode":"16400",
    "sg:province":"Cuenca",
    "wof:name":"Martinez Cuenca Jose Luis",
    "wof:placetype":"venue"
},
  "geometry": {"coordinates":[-3.0074884892,40.0123939514],"type":"Point"}
}