{
  "type": "Feature",
  "properties": {
    "addr:full":"Carr Reis Catolics, 64 Gandia Valencia 46700",
    "addr:housenumber":"64",
    "addr:postcode":"46700",
    "addr:street":"Carr Reis Catolics;Valencia",
    "iso:country":"ES",
    "sg:address":"Carr Reis Catolics, 64",
    "sg:city":"Gandia",
    "sg:orig_category":"Cl\u00cdnicas M\u00c9dicas",
    "sg:phone":"+34 962 87 50 15",
    "sg:postcode":"46700",
    "sg:province":"Valencia",
    "wof:name":"Haba Ruiz Maria Inmaculada",
    "wof:placetype":"venue"
},
  "geometry": {"coordinates":[-0.1913339943,38.960735321],"type":"Point"}
}