{
  "type": "Feature",
  "properties": {
    "iso:country":"ES",
    "sg:address":"Calle de Alonso Cano, 62",
    "sg:city":"Madrid",
    "sg:orig_category":"Art\u00cdculos De Decoraci\u00d3n",
    "sg:phone":"+34 915 53 14 67",
    "sg:postcode":"28003",
    "sg:province":"Madrid",
    "wof:name":"Galaxia 62 S.l.",
    "wof:placetype":"venue"
},
  "geometry": {"coordinates":[-3.6973845959,40.443069458],"type":"Point"}
}