{
  "type": "Feature",
  "properties": {
    "addr:full":"Carr Colinas, 10 Provensals Islas Baleares 07589",
    "addr:housenumber":"10",
    "addr:postcode":"07589",
    "addr:street":"Carr Colinas;Islas",
    "iso:country":"ES",
    "sg:address":"Carr Colinas, 10",
    "sg:city":"Provensals",
    "sg:orig_category":"Doctores En Medicina",
    "sg:phone":"+34 971 56 48 01",
    "sg:postcode":"07589",
    "sg:province":"Islas Baleares",
    "wof:name":"Mas Quetglas Enric",
    "wof:placetype":"venue"
},
  "geometry": {"coordinates":[3.4299299717,39.7455406189],"type":"Point"}
}