{
  "type": "Feature",
  "properties": {
    "addr:full":"Ptdo. Fte. D. Pedro, 39 Ronda M\u00e1laga 29400",
    "addr:postcode":"29400",
    "addr:street":"Ronda Ma\u0301Laga",
    "iso:country":"ES",
    "sg:address":"Ptdo. Fte. D. Pedro, 39",
    "sg:city":"Ronda",
    "sg:orig_category":"Promotores Constructores",
    "sg:phone":"+34 952 87 82 80",
    "sg:postcode":"29400",
    "sg:province":"M\u00e1laga",
    "wof:name":"Ladrisur 1010 S.l.",
    "wof:placetype":"venue"
},
  "geometry": {"coordinates":[-5.1662788391,36.7417945862],"type":"Point"}
}