{
  "type": "Feature",
  "properties": {
    "iso:country":"ES",
    "sg:address":"Calle de Gaviota, 4",
    "sg:city":"Valverdon",
    "sg:orig_category":"Panader\u00cdas, Panader\u00cdas",
    "sg:phone":"+34 923 32 11 69",
    "sg:postcode":"37185",
    "sg:province":"Salamanca",
    "wof:name":"Miguel Fraile E Hijos S.l.",
    "wof:placetype":"venue"
},
  "geometry": {"coordinates":[-5.7685217857,41.0463676453],"type":"Point"}
}