{
  "type": "Feature",
  "properties": {
    "addr:full":"Dr. A. San Martin, 3 Iru\u00f1a Navarra 31012",
    "addr:housenumber":"3",
    "addr:postcode":"31012",
    "addr:street":"Dr. A. San Martin",
    "iso:country":"ES",
    "sg:address":"Dr. A. San Martin, 3",
    "sg:city":"Iru\u00f1a",
    "sg:orig_category":"Bazares, Art\u00cdculos De Limpieza Y De Cocina (al Por Menor)",
    "sg:phone":"+34 948 17 61 19",
    "sg:postcode":"31012",
    "sg:province":"Navarra",
    "wof:name":"Sanchez Menaut Maria Luisa",
    "wof:placetype":"venue"
},
  "geometry": {"coordinates":[-1.6674330235,42.8193778992],"type":"Point"}
}