{
  "type": "Feature",
  "properties": {
    "addr:full":"Calle de Cerradilla, S/n Sartaguda Navarra 31589",
    "addr:housenumber":"s / n",
    "addr:postcode":"31589",
    "addr:street":"Calle De Cerradilla",
    "iso:country":"ES",
    "sg:address":"Calle de Cerradilla, S/n",
    "sg:city":"Sartaguda",
    "sg:orig_category":"Agricultura: Abastecimiento Y Cosechado (negocio)",
    "sg:phone":"+34 948 66 70 58",
    "sg:postcode":"31589",
    "sg:province":"Navarra",
    "wof:name":"Sociedad Cooperativa Agrupacion De Agricultores",
    "wof:placetype":"venue"
},
  "geometry": {"coordinates":[-2.0554490089,42.3789749146],"type":"Point"}
}