{
  "type": "Feature",
  "properties": {
    "iso:country":"ES",
    "sg:address":"Avda Andalucia, 98",
    "sg:city":"Torre Mar",
    "sg:orig_category":"Inmobiliaria (agencias)",
    "sg:phone":"+34 952 54 61 61",
    "sg:postcode":"29740",
    "sg:province":"M\u00e1laga",
    "sg:website":"www.unicasa.es",
    "wof:name":"Estudio Unico Asociados S.l.",
    "wof:placetype":"venue"
},
  "geometry": {"coordinates":[-4.4472260475,36.7155342102],"type":"Point"}
}