{
  "type": "Feature",
  "properties": {
    "iso:country":"ES",
    "sg:address":"Avda Ana De Viya, 11",
    "sg:city":"Cadiz",
    "sg:orig_category":"M\u00c9dicos: Estomatolog\u00cda",
    "sg:phone":"+34 956 27 93 79",
    "sg:postcode":"11009",
    "sg:province":"C\u00e1diz",
    "wof:name":"Gonzalez Macias Manuel",
    "wof:placetype":"venue"
},
  "geometry": {"coordinates":[-6.2794117928,36.5109710693],"type":"Point"}
}