{
  "type": "Feature",
  "properties": {
    "iso:country":"ES",
    "sg:address":"Carrer de Maria Cortina I Pascual, 2",
    "sg:city":"Reus",
    "sg:classifiers":[
        {
            "category":"Banks & Credit Unions",
            "subcategory":"Bureau De Change",
            "type":"Services"
        }
    ],
    "sg:phone":"+34 977 30 20 08",
    "sg:postcode":"43204",
    "sg:province":"Tarragona",
    "sg:tags":[
        "organismos",
        "control"
    ],
    "sg:website":"www.gocsa.es",
    "wof:name":"Goc S.a.",
    "wof:placetype":"venue"
},
  "geometry": {"coordinates":[1.1194460392,41.1568183899],"type":"Point"}
}