{
  "type": "Feature",
  "properties": {
    "iso:country":"ES",
    "sg:address":"Calle de Carretera Artajona, S/n",
    "sg:city":"Tafalla",
    "sg:orig_category":"Chapister\u00cda",
    "sg:phone":"+34 948 70 28 35",
    "sg:postcode":"31300",
    "sg:province":"Navarra",
    "wof:name":"Mogica Fatas Mariano",
    "wof:placetype":"venue"
},
  "geometry": {"coordinates":[-1.6955091953,42.5188484192],"type":"Point"}
}