{
  "type": "Feature",
  "properties": {
    "iso:country":"ES",
    "sg:address":"Avda Andalucia, 47",
    "sg:city":"Cadiz",
    "sg:orig_category":"M\u00c9dicos: Gastroenterolog\u00cda Y Hepatolog\u00cda (aparato Digestivo)",
    "sg:phone":"+34 956 27 52 96",
    "sg:postcode":"11007",
    "sg:province":"C\u00e1diz",
    "wof:name":"Bellon Alcantara Antonio Jesus",
    "wof:placetype":"venue"
},
  "geometry": {"coordinates":[-6.2850518227,36.5208854675],"type":"Point"}
}