{
  "type": "Feature",
  "properties": {
    "addr:full":"Las Caba\u00f1as, S/n Lugones Asturias 33420",
    "addr:housenumber":"/ n",
    "addr:postcode":"33420",
    "addr:street":"Caban\u0303As S",
    "iso:country":"ES",
    "sg:address":"Las Caba\u00f1as, S/n",
    "sg:city":"Lugones",
    "sg:orig_category":"Estudios Y Construcci\u00d3n De Acuarios Y Viveros",
    "sg:phone":"+34 985 26 40 83",
    "sg:postcode":"33420",
    "sg:province":"Asturias",
    "wof:name":"Acuabierzo S.l.",
    "wof:placetype":"venue"
},
  "geometry": {"coordinates":[-5.8103342056,43.4049339294],"type":"Point"}
}