{
  "type": "Feature",
  "properties": {
    "addr:full":"Avda Agrupacion Cordoba, 19 Cordoba C\u00f3rdoba 14007",
    "addr:housenumber":"19",
    "addr:postcode":"14007",
    "addr:street":"Avda Agrupacion Cordoba;Co\u0301Rdoba",
    "iso:country":"ES",
    "sg:address":"Avda Agrupacion Cordoba, 19",
    "sg:city":"Cordoba",
    "sg:orig_category":"Lencer\u00cda Femenina, Corseter\u00cda, Trajes De Ba\u00d1o (al Por Menor)",
    "sg:phone":"+34 957 40 42 08",
    "sg:postcode":"14007",
    "sg:province":"C\u00f3rdoba",
    "wof:name":"Artesania Marigall S.l.",
    "wof:placetype":"venue"
},
  "geometry": {"coordinates":[-4.7659721375,37.8975105286],"type":"Point"}
}