{
  "type": "Feature",
  "properties": {
    "addr:full":"Carrer de Castell Vell, 27 Crevillent Alicante 03330",
    "addr:housenumber":"27",
    "addr:postcode":"03330",
    "addr:street":"Carrer De Castell Vell",
    "iso:country":"ES",
    "sg:address":"Carrer de Castell Vell, 27",
    "sg:city":"Crevillent",
    "sg:orig_category":"Comercio, Reparaci\u00d3n De Motocicletas, Bicicletas Y Piezas Sueltas",
    "sg:phone":"+34 965 40 50 67",
    "sg:postcode":"03330",
    "sg:province":"Alicante",
    "wof:name":"Parres Lledo Cristina",
    "wof:placetype":"venue"
},
  "geometry": {"coordinates":[-0.8128989935,38.2532806396],"type":"Point"}
}