{
  "type": "Feature",
  "properties": {
    "addr:full":"Sect Foresta, 23 Tres Cantos Madrid 28760",
    "addr:housenumber":"23",
    "addr:postcode":"28760",
    "addr:street":"Foresta",
    "iso:country":"ES",
    "sg:address":"Sect Foresta, 23",
    "sg:city":"Tres Cantos",
    "sg:orig_category":"Art\u00cdculos De Decoraci\u00d3n (fabricaci\u00d3n Y Al Por Mayor)",
    "sg:phone":"+34 918 04 66 90",
    "sg:postcode":"28760",
    "sg:province":"Madrid",
    "wof:name":"Christel Thiele Arnold",
    "wof:placetype":"venue"
},
  "geometry": {"coordinates":[-3.7094860077,40.6122627258],"type":"Point"}
}