{
  "type": "Feature",
  "properties": {
    "iso:country":"ES",
    "sg:address":"Carrer de Pere Iv, 98",
    "sg:city":"Barcelona",
    "sg:orig_category":"Confecci\u00d3n De Corbatas",
    "sg:phone":"+34 933 17 90 31",
    "sg:postcode":"08005",
    "sg:province":"Barcelona",
    "sg:website":"www.sebastianandreu.com",
    "wof:name":"Manufacturas Andreu S. A.",
    "wof:placetype":"venue"
},
  "geometry": {"coordinates":[2.194740057,41.3991394043],"type":"Point"}
}