{
  "type": "Feature",
  "properties": {
    "addr:full":"Calle de Almirante Cristobal Mello, 18 Portugalete Vizcaya 48920",
    "addr:housenumber":"18",
    "addr:postcode":"48920",
    "addr:street":"Calle De Almirante Cristobal Mello",
    "iso:country":"ES",
    "sg:address":"Calle de Almirante Cristobal Mello, 18",
    "sg:city":"Portugalete",
    "sg:orig_category":"Ingenier\u00cda, Centros De Estudios (diversos)",
    "sg:phone":"+34 944 61 86 50",
    "sg:postcode":"48920",
    "sg:province":"Vizcaya",
    "wof:name":"Prosertek, S.l",
    "wof:placetype":"venue"
},
  "geometry": {"coordinates":[-3.0203535557,43.323890686],"type":"Point"}
}