{
  "type": "Feature",
  "properties": {
    "iso:country":"ES",
    "sg:address":"Ctra Manresa, 20",
    "sg:city":"Solsona",
    "sg:orig_category":"Molduras, Junquillos, Listones Y Molduras Perforadas",
    "sg:phone":"+34 973 48 36 52",
    "sg:postcode":"25280",
    "sg:province":"Lleida",
    "wof:name":"Lopez Garcia Josep",
    "wof:placetype":"venue"
},
  "geometry": {"coordinates":[1.5225429535,41.9947738647],"type":"Point"}
}