{
  "type": "Feature",
  "properties": {
    "addr:full":"Pase Zorrilla, 15 Valladolid Valladolid 47007",
    "addr:housenumber":"15",
    "addr:postcode":"47007",
    "addr:street":"Zorrilla",
    "iso:country":"ES",
    "sg:address":"Pase Zorrilla, 15",
    "sg:city":"Valladolid",
    "sg:orig_category":"Agencias De Viajes",
    "sg:phone":"+34 983 47 65 56",
    "sg:postcode":"47007",
    "sg:province":"Valladolid",
    "sg:website":"www.halconviajes.com",
    "wof:name":"Viajes Halcon S.a.",
    "wof:placetype":"venue"
},
  "geometry": {"coordinates":[-4.7361302376,41.6427154541],"type":"Point"}
}