{
  "type": "Feature",
  "properties": {
    "iso:country":"ES",
    "sg:address":"Calle de Pedrera, 64",
    "sg:city":"Arahal",
    "sg:orig_category":"Bisuter\u00cda, Joyer\u00cda, Relojer\u00cda (al Por Menor)",
    "sg:phone":"+34 955 84 07 99",
    "sg:postcode":"41600",
    "sg:province":"Sevilla",
    "wof:name":"Calasan Alamo Eduardo",
    "wof:placetype":"venue"
},
  "geometry": {"coordinates":[-5.5450959206,37.2593307495],"type":"Point"}
}