{
  "type": "Feature",
  "properties": {
    "addr:full":"Calle de Francesa (la), 3 Dos Hermanas Sevilla 41700",
    "addr:housenumber":"3",
    "addr:postcode":"41700",
    "addr:street":"Calle De Francesa La;Sevilla",
    "iso:country":"ES",
    "sg:address":"Calle de Francesa (la), 3",
    "sg:city":"Dos Hermanas",
    "sg:orig_category":"Ropa Para Se\u00d1oras (al Por Menor)",
    "sg:phone":"+34 955 67 02 00",
    "sg:postcode":"41700",
    "sg:province":"Sevilla",
    "wof:name":"Ruiz Valladares Concepcion",
    "wof:placetype":"venue"
},
  "geometry": {"coordinates":[-5.925632,37.2829284668],"type":"Point"}
}