{
  "type": "Feature",
  "properties": {
    "iso:country":"ES",
    "sg:address":"Calle de Pablillos, 16",
    "sg:city":"Andujar",
    "sg:orig_category":"Reposter\u00cdas",
    "sg:phone":"+34 953 50 29 26",
    "sg:postcode":"23740",
    "sg:province":"Ja\u00e9n",
    "wof:name":"Bonachela Casta\u00f1os Patricio",
    "wof:placetype":"venue"
},
  "geometry": {"coordinates":[-4.0493011475,38.0371284485],"type":"Point"}
}