{
  "type": "Feature",
  "properties": {
    "iso:country":"ES",
    "sg:address":"Calle de Febo, 6",
    "sg:city":"Sevilla",
    "sg:classifiers":[
        {
            "category":"Personal",
            "subcategory":"Barber",
            "type":"Services"
        }
    ],
    "sg:phone":"+34 954 28 39 90",
    "sg:postcode":"41010",
    "sg:province":"Sevilla",
    "sg:tags":[
        "caballeros",
        "de",
        "peluqueros"
    ],
    "wof:name":"Romero Rodriguez Francisco Javier",
    "wof:placetype":"venue"
},
  "geometry": {"coordinates":[-6.0037541389,37.3809509277],"type":"Point"}
}