{
  "type": "Feature",
  "properties": {
    "addr:full":"Rua Corredoira, 46 Monforte De Lemos Lugo 27400",
    "addr:housenumber":"46",
    "addr:postcode":"27400",
    "addr:street":"Rua Corredoira",
    "iso:country":"ES",
    "sg:address":"Rua Corredoira, 46",
    "sg:city":"Monforte De Lemos",
    "sg:orig_category":"Reparaci\u00d3n, Mantenimiento De Calefacciones",
    "sg:phone":"+34 982 40 11 57",
    "sg:postcode":"27400",
    "sg:province":"Lugo",
    "wof:name":"Paseva S.l.",
    "wof:placetype":"venue"
},
  "geometry": {"coordinates":[-7.5206990242,42.5265693665],"type":"Point"}
}