{
  "type": "Feature",
  "properties": {
    "addr:full":"Carrer de Jaume Isern, 69 Mataro Barcelona 08302",
    "addr:housenumber":"69",
    "addr:postcode":"08302",
    "addr:street":"Carrer De Jaume Isern",
    "iso:country":"ES",
    "sg:address":"Carrer de Jaume Isern, 69",
    "sg:city":"Mataro",
    "sg:orig_category":"Electrodom\u00c9sticos (fabricaci\u00d3n, Al Por Mayor)",
    "sg:phone":"+34 937 98 19 86",
    "sg:postcode":"08302",
    "sg:province":"Barcelona",
    "wof:name":"Bru Roldos Miguel",
    "wof:placetype":"venue"
},
  "geometry": {"coordinates":[2.4360671043,41.5404205322],"type":"Point"}
}