{
  "type": "Feature",
  "properties": {
    "addr:full":"Ctra Moron-pruna, Km. 0001,0 Pruna Sevilla 41670",
    "addr:postcode":"41670",
    "addr:street":"Ctra Moron-Pruna Km. 0001,0",
    "iso:country":"ES",
    "sg:address":"Ctra Moron-pruna, Km. 0001,0",
    "sg:city":"Pruna",
    "sg:orig_category":"Aceites Y Grasas Alimentarias (fabricaci\u00d3n, Al Por Mayor)",
    "sg:phone":"+34 954 85 85 30",
    "sg:postcode":"41670",
    "sg:province":"Sevilla",
    "wof:name":"Cooperativa Del Campo San Anton",
    "wof:placetype":"venue"
},
  "geometry": {"coordinates":[-5.2234740257,36.9747581482],"type":"Point"}
}