{
  "type": "Feature",
  "properties": {
    "iso:country":"ES",
    "sg:address":"Barr Pe\u00d1uca (la), S/n",
    "sg:city":"Cabez\u00f3n Sal",
    "sg:orig_category":"Alimentaci\u00d3n General (al Por Mayor)",
    "sg:phone":"+34 942 70 02 23",
    "sg:postcode":"39500",
    "sg:province":"Cantabria",
    "wof:name":"Piensos Cano S.l",
    "wof:placetype":"venue"
},
  "geometry": {"coordinates":[-4.2374691963,43.3085784912],"type":"Point"}
}