{
  "type": "Feature",
  "properties": {
    "iso:country":"ES",
    "sg:address":"Carr Moreres, 36",
    "sg:city":"Mao",
    "sg:orig_category":"Laboratorios Y Trabajos De Fotograf\u00cda, V\u00cddeo Y Cine",
    "sg:phone":"+34 971 35 35 42",
    "sg:postcode":"07702",
    "sg:province":"Islas Baleares",
    "wof:name":"Prest I Be S.c.",
    "wof:placetype":"venue"
},
  "geometry": {"coordinates":[4.265625,39.8903694153],"type":"Point"}
}