{
  "type": "Feature",
  "properties": {
    "addr:full":"Calle de Congosto, 37 Madrid Madrid 28031",
    "addr:housenumber":"37",
    "addr:postcode":"madrid;28031",
    "addr:street":"Calle De Congosto",
    "iso:country":"ES",
    "sg:address":"Calle de Congosto, 37",
    "sg:city":"Madrid",
    "sg:orig_category":"Empresarios",
    "sg:phone":"+34 913 32 24 45",
    "sg:postcode":"28031",
    "sg:province":"Madrid",
    "wof:name":"Moreno Cano Martin Felix",
    "wof:placetype":"venue"
},
  "geometry": {"coordinates":[-3.6184725761,40.3715209961],"type":"Point"}
}