{
  "type": "Feature",
  "properties": {
    "addr:full":"Ctra Mena, 26 Badalona Barcelona 08913",
    "addr:housenumber":"26",
    "addr:postcode":"08913",
    "addr:street":"Ctra Mena",
    "iso:country":"ES",
    "sg:address":"Ctra Mena, 26",
    "sg:city":"Badalona",
    "sg:orig_category":"Alquiler De Veh\u00cdculos: Turismos Y Utilitarios",
    "sg:phone":"+34 934 60 58 44",
    "sg:postcode":"08913",
    "sg:province":"Barcelona",
    "wof:name":"Over Rent S.a.",
    "wof:placetype":"venue"
},
  "geometry": {"coordinates":[2.2206430435,41.4358444214],"type":"Point"}
}