{
  "type": "Feature",
  "properties": {
    "addr:full":"Laubide Auzoa, 27 Legazpi Guip\u00f9zcoa 20230",
    "addr:housenumber":"27",
    "addr:postcode":"20230",
    "addr:street":"Laubide Auzoa;Guipu\u0300Zcoa",
    "iso:country":"ES",
    "sg:address":"Laubide Auzoa, 27",
    "sg:city":"Legazpi",
    "sg:orig_category":"Muebles Y Accesorios Para Cocinas Y Cuartos De Ba\u00d1o (al Por Menor)",
    "sg:phone":"+34 943 73 70 70",
    "sg:postcode":"20230",
    "sg:province":"Guip\u00f9zcoa",
    "wof:name":"Gremios Y Servicios S.coop.",
    "wof:placetype":"venue"
},
  "geometry": {"coordinates":[-2.3373305798,43.057510376],"type":"Point"}
}