{
  "type": "Feature",
  "properties": {
    "iso:country":"ES",
    "sg:address":"Carretera De Ribaforada, Km. 0001,0",
    "sg:city":"Ablitas",
    "sg:orig_category":"Productores Recolectores, Venta Directa De Vinos",
    "sg:phone":"+34 948 81 34 71",
    "sg:postcode":"31523",
    "sg:province":"Navarra",
    "wof:name":"Bodega Cooperativa Nuestra Se\u00f1ora Del Rosario",
    "wof:placetype":"venue"
},
  "geometry": {"coordinates":[-1.6404190063,41.9752693176],"type":"Point"}
}