{
  "type": "Feature",
  "properties": {
    "iso:country":"ES",
    "sg:address":"Calle de Real, 86",
    "sg:city":"Brenes",
    "sg:orig_category":"Artesan\u00cda",
    "sg:phone":"+34 954 79 62 35",
    "sg:postcode":"41310",
    "sg:province":"Sevilla",
    "wof:name":"Fernandez Y Enriquez S.l.",
    "wof:placetype":"venue"
},
  "geometry": {"coordinates":[-5.8736810684,37.550037384],"type":"Point"}
}