{
  "type": "Feature",
  "properties": {
    "addr:full":"Ctra Avila, S/n Villacastin Segovia 40150",
    "addr:postcode":"40150",
    "addr:street":"Ctra Avila S / N Villacastin Segovia",
    "iso:country":"ES",
    "sg:address":"Ctra Avila, S/n",
    "sg:city":"Villacastin",
    "sg:orig_category":"Venta, Instalaci\u00d3n De Cocinas",
    "sg:phone":"+34 921 19 85 70",
    "sg:postcode":"40150",
    "sg:province":"Segovia",
    "wof:name":"Garcia Fernandez Marcial",
    "wof:placetype":"venue"
},
  "geometry": {"coordinates":[-4.4154639244,40.779712677],"type":"Point"}
}