{
  "type": "Feature",
  "properties": {
    "addr:full":"Calle de Joaquin Costa, 22 Palmas De Gran Canaria Las Palmas 35007",
    "addr:postcode":"35007",
    "addr:street":"Calle De Joaquin Costa 22",
    "iso:country":"ES",
    "sg:address":"Calle de Joaquin Costa, 22",
    "sg:city":"Palmas De Gran Canaria",
    "sg:orig_category":"Material Y Suministros Para Imprenta E Industrias Gr\u00c1ficas",
    "sg:phone":"+34 928 22 38 01",
    "sg:postcode":"35007",
    "sg:province":"Las Palmas",
    "wof:name":"Insular Grafica S. L.",
    "wof:placetype":"venue"
},
  "geometry": {"coordinates":[-15.4342031479,28.1379871368],"type":"Point"}
}