{
  "type": "Feature",
  "properties": {
    "addr:full":"Rond Andalucia (de), S/n Santaella C\u00f3rdoba 14546",
    "addr:housenumber":"/ n",
    "addr:postcode":"14546",
    "addr:street":"Rond Andalucia De S;Co\u0301Rdoba",
    "iso:country":"ES",
    "sg:address":"Rond Andalucia (de), S/n",
    "sg:city":"Santaella",
    "sg:orig_category":"Fabricaci\u00d3n De Muebles",
    "sg:phone":"+34 957 31 37 73",
    "sg:postcode":"14546",
    "sg:province":"C\u00f3rdoba",
    "wof:name":"Muebles Y Carpinteria Carmona S.l.",
    "wof:placetype":"venue"
},
  "geometry": {"coordinates":[-4.8459119797,37.5659446716],"type":"Point"}
}