{
  "type": "Feature",
  "properties": {
    "addr:full":"Carrer de Eduard Brossa, 39 Sabadell Barcelona 08204",
    "addr:housenumber":"39",
    "addr:postcode":"08204",
    "addr:street":"Carrer De Eduard Brossa",
    "iso:country":"ES",
    "sg:address":"Carrer de Eduard Brossa, 39",
    "sg:city":"Sabadell",
    "sg:orig_category":"Empresas De Operaciones Portuarias Y Elevaci\u00d3n De Mercanc\u00cdas",
    "sg:phone":"+34 937 10 56 59",
    "sg:postcode":"08204",
    "sg:province":"Barcelona",
    "wof:name":"Garcia Casa\u00f1e Juan",
    "wof:placetype":"venue"
},
  "geometry": {"coordinates":[2.1162641048,41.5260391235],"type":"Point"}
}