{
  "type": "Feature",
  "properties": {
    "iso:country":"ES",
    "sg:address":"Carr Mossen Agusti Sala, S/n",
    "sg:city":"Centre Urba",
    "sg:orig_category":"Grafistas",
    "sg:phone":"+34 972 71 45 19",
    "sg:postcode":"17500",
    "sg:province":"Girona",
    "wof:name":"Quimeres Solucions Visuals S.c.p",
    "wof:placetype":"venue"
},
  "geometry": {"coordinates":[2.1959049702,42.1965866089],"type":"Point"}
}