{
  "type": "Feature",
  "properties": {
    "iso:country":"ES",
    "sg:address":"Avda Ribera De Axpe, 50",
    "sg:city":"Altzaga",
    "sg:orig_category":"Pintura, Barniz, Productos Asimilables (fabricaci\u00d3n, Al Por Mayor)",
    "sg:phone":"+34 944 63 19 66",
    "sg:postcode":"48950",
    "sg:province":"Vizcaya",
    "wof:name":"Akzo Nobel Industrial Paints S.l.",
    "wof:placetype":"venue"
},
  "geometry": {"coordinates":[-2.9800858498,43.3115539551],"type":"Point"}
}