{
  "type": "Feature",
  "properties": {
    "iso:country":"ES",
    "sg:address":"Calle de Koskojales, 44",
    "sg:city":"Irauregi",
    "sg:orig_category":"Electricidad: Instaladores",
    "sg:phone":"+34 944 98 01 15",
    "sg:postcode":"48810",
    "sg:province":"Vizcaya",
    "wof:name":"Instalaciones Ceyma S.l.",
    "wof:placetype":"venue"
},
  "geometry": {"coordinates":[-2.9891839027,43.2450904846],"type":"Point"}
}