{
  "type": "Feature",
  "properties": {
    "iso:country":"ES",
    "sg:address":"P. Ori, 8",
    "sg:city":"Iru\u00f1a",
    "sg:orig_category":"Carnicer\u00cdas, Carnicer\u00cdas",
    "sg:phone":"+34 948 23 30 56",
    "sg:postcode":"31006",
    "sg:province":"Navarra",
    "wof:name":"Valencia Rodriguez Eusebio",
    "wof:placetype":"venue"
},
  "geometry": {"coordinates":[-1.633991003,42.8048553467],"type":"Point"}
}