{
  "type": "Feature",
  "properties": {
    "addr:full":"Cra Santa Creu De Calafell, Km. 0003,6 Gava Barcelona 08850",
    "addr:postcode":"08850",
    "addr:street":"Km. 0003,6 Gava",
    "iso:country":"ES",
    "sg:address":"Cra Santa Creu De Calafell, Km. 0003,6",
    "sg:city":"Gava",
    "sg:orig_category":"Limpieza Con Chorro De Arena Y Con Granalla, Pulido",
    "sg:phone":"+34 936 62 62 11",
    "sg:postcode":"08850",
    "sg:province":"Barcelona",
    "wof:name":"Univex 320 S.l.",
    "wof:placetype":"venue"
},
  "geometry": {"coordinates":[2.0109639168,41.3062591553],"type":"Point"}
}