{
  "type": "Feature",
  "properties": {
    "iso:country":"ES",
    "sg:address":"Calle de Molino De Viento, 1",
    "sg:city":"Trigueros",
    "sg:orig_category":"Veh\u00cdculos, Transporte",
    "sg:phone":"+34 959 30 61 78",
    "sg:postcode":"21620",
    "sg:province":"Huelva",
    "wof:name":"Cardenas Caro Pedro Antonio",
    "wof:placetype":"venue"
},
  "geometry": {"coordinates":[-6.8325648308,37.3840255737],"type":"Point"}
}