{
  "type": "Feature",
  "properties": {
    "addr:full":"Calle de General Vives, 49 Palmas De Gran Canaria Las Palmas 35007",
    "addr:postcode":"35007",
    "addr:street":"Calle De General Vives 49",
    "iso:country":"ES",
    "sg:address":"Calle de General Vives, 49",
    "sg:city":"Palmas De Gran Canaria",
    "sg:orig_category":"Asociaciones Y Clubs Deportivos",
    "sg:phone":"+34 928 22 69 97",
    "sg:postcode":"35007",
    "sg:province":"Las Palmas",
    "wof:name":"Adolfo Suanzes S.a.",
    "wof:placetype":"venue"
},
  "geometry": {"coordinates":[-15.4312906265,28.1382045746],"type":"Point"}
}