{
  "type": "Feature",
  "properties": {
    "iso:country":"ES",
    "sg:address":"Ctra Sierra (de La), S/n",
    "sg:city":"Granada",
    "sg:orig_category":"Procuradores",
    "sg:phone":"+34 958 22 25 62",
    "sg:postcode":"18008",
    "sg:province":"Granada",
    "wof:name":"Morcillo Casado Sofia",
    "wof:placetype":"venue"
},
  "geometry": {"coordinates":[-3.5831239223,37.1659317017],"type":"Point"}
}