{
  "type": "Feature",
  "properties": {
    "iso:country":"ES",
    "sg:address":"Calle de Ollerias, 6",
    "sg:city":"Andujar",
    "sg:orig_category":"Confecci\u00d3n (fabricaci\u00d3n, Al Por Mayor)",
    "sg:phone":"+34 953 50 57 03",
    "sg:postcode":"23740",
    "sg:province":"Ja\u00e9n",
    "wof:name":"Exposito Laguna Pedro",
    "wof:placetype":"venue"
},
  "geometry": {"coordinates":[-4.0523910522,38.0377655029],"type":"Point"}
}