{
  "type": "Feature",
  "properties": {
    "addr:full":"Calle de San Miguel, 2 Zamora Zamora 49015",
    "addr:housenumber":"2",
    "addr:postcode":"49015",
    "addr:street":"Calle De San Miguel",
    "iso:country":"ES",
    "sg:address":"Calle de San Miguel, 2",
    "sg:city":"Zamora",
    "sg:orig_category":"Abogados",
    "sg:phone":"+34 980 51 80 20",
    "sg:postcode":"49015",
    "sg:province":"Zamora",
    "sg:website":"www.abogados.frs.nu",
    "wof:name":"Bahamonde Abogados Asociados S.l.",
    "wof:placetype":"venue"
},
  "geometry": {"coordinates":[-5.7424697876,41.5054855347],"type":"Point"}
}