{
  "type": "Feature",
  "properties": {
    "addr:full":"Pol Ind Valle Almanzora, 10 Cuevas Almanzora Almer\u00eda 04610",
    "addr:housenumber":"10",
    "addr:postcode":"04610",
    "addr:street":"Almanzora;Almeri\u0301A",
    "iso:country":"ES",
    "sg:address":"Pol Ind Valle Almanzora, 10",
    "sg:city":"Cuevas Almanzora",
    "sg:orig_category":"Arboricultura Y Producci\u00d3n De Frutas",
    "sg:phone":"+34 950 45 68 01",
    "sg:postcode":"04610",
    "sg:province":"Almer\u00eda",
    "wof:name":"S.a.t. Cirera N\u00ba Al-0017",
    "wof:placetype":"venue"
},
  "geometry": {"coordinates":[-1.8781139851,37.2911911011],"type":"Point"}
}