{
  "type": "Feature",
  "properties": {
    "addr:full":"Calle de Cosa Juan De La, 23 Bilbao Vizcaya 48004",
    "addr:housenumber":"23",
    "addr:postcode":"48004",
    "addr:street":"Calle De Cosa Juan De La",
    "iso:country":"ES",
    "sg:address":"Calle de Cosa Juan De La, 23",
    "sg:city":"Bilbao",
    "sg:orig_category":"Electricidad: Instaladores",
    "sg:phone":"+34 944 12 43 61",
    "sg:postcode":"48004",
    "sg:province":"Vizcaya",
    "wof:name":"J.a.martin, S.l",
    "wof:placetype":"venue"
},
  "geometry": {"coordinates":[-2.9112930298,43.251285553],"type":"Point"}
}