{
  "type": "Feature",
  "properties": {
    "iso:country":"ES",
    "sg:address":"Calle de Zubiaur Tar Kepa, 4",
    "sg:city":"Bermeo",
    "sg:orig_category":"Agentes, Concesionarios Y Sucursales De Veh\u00cdculos",
    "sg:phone":"+34 946 88 24 26",
    "sg:postcode":"48370",
    "sg:province":"Vizcaya",
    "wof:name":"Javier Larrauri Muruaga",
    "wof:placetype":"venue"
},
  "geometry": {"coordinates":[-2.7266609669,43.4194335938],"type":"Point"}
}