{
  "type": "Feature",
  "properties": {
    "addr:full":"Plaz Constitucion, S/n Casas-iba\u00e7ez Albacete 02200",
    "addr:postcode":"02200",
    "addr:street":"Constitucion S / N",
    "iso:country":"ES",
    "sg:address":"Plaz Constitucion, S/n",
    "sg:city":"Casas-iba\u00e7ez",
    "sg:orig_category":"Asociaciones Humanitarias, De Cooperaci\u00d3n, De Acci\u00d3n Social",
    "sg:phone":"+34 967 46 01 93",
    "sg:postcode":"02200",
    "sg:province":"Albacete",
    "wof:name":"Asociacion Comarcal De Alcoholicos Rehabilitados",
    "wof:placetype":"venue"
},
  "geometry": {"coordinates":[-1.8600701094,38.9976501465],"type":"Point"}
}