{
  "type": "Feature",
  "properties": {
    "addr:full":"Calle de Gloria, 7 Aljucer Murcia 30152",
    "addr:housenumber":"7",
    "addr:postcode":"30152",
    "addr:street":"Calle De Gloria",
    "iso:country":"ES",
    "sg:address":"Calle de Gloria, 7",
    "sg:city":"Aljucer",
    "sg:orig_category":"Agencias Y Agentes Comerciales, Representantes",
    "sg:phone":"+34 968 34 61 26",
    "sg:postcode":"30152",
    "sg:province":"Murcia",
    "wof:name":"Valverde Alarcon Federico",
    "wof:placetype":"venue"
},
  "geometry": {"coordinates":[-1.151345253,37.9562225342],"type":"Point"}
}