{
  "type": "Feature",
  "properties": {
    "addr:full":"Avda Alemania De, 39 Aviles Asturias 33401",
    "addr:housenumber":"39",
    "addr:postcode":"33401",
    "addr:street":"Avda Alemania De",
    "iso:country":"ES",
    "sg:address":"Avda Alemania De, 39",
    "sg:city":"Aviles",
    "sg:orig_category":"Panader\u00cdas, Panader\u00cdas",
    "sg:phone":"+34 985 56 09 11",
    "sg:postcode":"33401",
    "sg:province":"Asturias",
    "wof:name":"Panaderia Armonia S.l.",
    "wof:placetype":"venue"
},
  "geometry": {"coordinates":[-5.9275889397,43.5612983704],"type":"Point"}
}