{
  "type": "Feature",
  "properties": {
    "iso:country":"ES",
    "sg:address":"Ctra Ayerbe-ejea, S/n",
    "sg:city":"Valpalmas",
    "sg:orig_category":"Poller\u00cda Y Caza (al Por Menor)",
    "sg:phone":"+34 976 69 14 09",
    "sg:postcode":"50615",
    "sg:province":"Zaragoza",
    "wof:name":"Granja Azute S.cv.",
    "wof:placetype":"venue"
},
  "geometry": {"coordinates":[-0.8625440001,42.1924552917],"type":"Point"}
}