{
  "type": "Feature",
  "properties": {
    "addr:full":"Avda Fernandez Latorre, 57 Coru\u00d1a La Coru\u00f1a 15006",
    "addr:housenumber":"57",
    "addr:postcode":"15006",
    "addr:street":"Avda Fernandez Latorre;Corun\u0303A",
    "iso:country":"ES",
    "sg:address":"Avda Fernandez Latorre, 57",
    "sg:city":"Coru\u00d1a",
    "sg:orig_category":"M\u00c9dicos: Medicina Interna",
    "sg:phone":"+34 981 29 45 17",
    "sg:postcode":"15006",
    "sg:province":"La Coru\u00f1a",
    "wof:name":"Irimia Mazoy Manuel",
    "wof:placetype":"venue"
},
  "geometry": {"coordinates":[-8.403963089,43.3549346924],"type":"Point"}
}