{
  "type": "Feature",
  "properties": {
    "iso:country":"ES",
    "sg:address":"Carr Bailen, 12",
    "sg:city":"Vilanova I La Geltru",
    "sg:orig_category":"Promotores Constructores",
    "sg:phone":"+34 938 15 47 42",
    "sg:postcode":"08800",
    "sg:province":"Barcelona",
    "wof:name":"Construccions Fernandez Trems S.l.",
    "wof:placetype":"venue"
},
  "geometry": {"coordinates":[1.7148300409,41.2241630554],"type":"Point"}
}