{
  "type": "Feature",
  "properties": {
    "addr:full":"Carrer de Rambla, 8 Barona Castell\u00f3n 12193",
    "addr:housenumber":"8",
    "addr:postcode":"12193",
    "addr:street":"Carrer De Rambla;Castello\u0301N",
    "iso:country":"ES",
    "sg:address":"Carrer de Rambla, 8",
    "sg:city":"Barona",
    "sg:orig_category":"Aceites Y Grasas Alimentarias (fabricaci\u00d3n, Al Por Mayor)",
    "sg:phone":"+34 964 32 03 64",
    "sg:postcode":"12193",
    "sg:province":"Castell\u00f3n",
    "wof:name":"J.m.robres S.l.",
    "wof:placetype":"venue"
},
  "geometry": {"coordinates":[-0.063914001,40.1663513184],"type":"Point"}
}