{
  "type": "Feature",
  "properties": {
    "iso:country":"ES",
    "sg:address":"Carr Pietat, 25",
    "sg:city":"Badalona",
    "sg:orig_category":"Lencer\u00cda Femenina, Corseter\u00cda, Trajes De Ba\u00d1o (al Por Menor)",
    "sg:phone":"+34 933 84 06 03",
    "sg:postcode":"08911",
    "sg:province":"Barcelona",
    "wof:name":"Gali Canals Pedro",
    "wof:placetype":"venue"
},
  "geometry": {"coordinates":[2.2481820583,41.4483947754],"type":"Point"}
}