{
  "type": "Feature",
  "properties": {
    "addr:full":"Ctra Santa Olalla, Km. 0036,5 Segura Leon Badajoz 06270",
    "addr:postcode":"06270",
    "addr:street":"Ctra Santa Olalla Km. 0036,5 Segura",
    "iso:country":"ES",
    "sg:address":"Ctra Santa Olalla, Km. 0036,5",
    "sg:city":"Segura Leon",
    "sg:orig_category":"Veh\u00cdculos De Ocasi\u00d3n",
    "sg:phone":"+34 924 70 32 12",
    "sg:postcode":"06270",
    "sg:province":"Badajoz",
    "wof:name":"Hervas Sanchez Francisco",
    "wof:placetype":"venue"
},
  "geometry": {"coordinates":[-6.5268640518,38.116065979],"type":"Point"}
}