{
  "type": "Feature",
  "properties": {
    "iso:country":"ES",
    "sg:address":"Avda Mediterraneo, 27",
    "sg:city":"Benidorm",
    "sg:orig_category":"Fotograf\u00cda Art\u00cdstica Y Retratos",
    "sg:phone":"+34 966 80 38 07",
    "sg:postcode":"03500",
    "sg:province":"Alicante",
    "wof:name":"Herrerias Domene Juan",
    "wof:placetype":"venue"
},
  "geometry": {"coordinates":[-0.1164639965,38.5366325378],"type":"Point"}
}