{
  "type": "Feature",
  "properties": {
    "addr:full":"Afueras, S/n Arta Islas Baleares 07570",
    "addr:postcode":"07570",
    "addr:street":"Afueras S / N Arta Islas Baleares",
    "iso:country":"ES",
    "sg:address":"Afueras, S/n",
    "sg:city":"Arta",
    "sg:orig_category":"Pintura Y Barniz (al Por Menor)",
    "sg:phone":"+34 971 83 53 54",
    "sg:postcode":"07570",
    "sg:province":"Islas Baleares",
    "wof:name":"Pinturas Santadreu Arta S.l.",
    "wof:placetype":"venue"
},
  "geometry": {"coordinates":[3.326939106,39.7053108215],"type":"Point"}
}