{
  "type": "Feature",
  "properties": {
    "iso:country":"ES",
    "sg:address":"Calle de Alava, 9",
    "sg:city":"Sevilla",
    "sg:orig_category":"Pintura, Barniz, Productos Asimilables (fabricaci\u00d3n, Al Por Mayor)",
    "sg:phone":"+34 954 51 61 22",
    "sg:postcode":"41007",
    "sg:province":"Sevilla",
    "wof:name":"Industrias Juno S. A.",
    "wof:placetype":"venue"
},
  "geometry": {"coordinates":[-5.941947937,37.3867721558],"type":"Point"}
}