{
  "type": "Feature",
  "properties": {
    "iso:country":"ES",
    "sg:address":"Calle de Mateo Errota, 9",
    "sg:city":"Donostia-san Sebastian",
    "sg:orig_category":"Electricidad: Instaladores",
    "sg:phone":"+34 943 46 45 34",
    "sg:postcode":"20014",
    "sg:province":"Guip\u00f9zcoa",
    "wof:name":"Talleres Indel S.l.",
    "wof:placetype":"venue"
},
  "geometry": {"coordinates":[-1.9445539713,43.3022842407],"type":"Point"}
}