{
  "type": "Feature",
  "properties": {
    "iso:country":"ES",
    "sg:address":"Urb Poligono Juncaril, S/n",
    "sg:city":"Albolote",
    "sg:orig_category":"Autob\u00das (explotaci\u00d3n Y Servicios De)",
    "sg:phone":"+34 958 46 55 98",
    "sg:postcode":"18220",
    "sg:province":"Granada",
    "wof:name":"Autocares Jose Gonzalez S.l.",
    "wof:placetype":"venue"
},
  "geometry": {"coordinates":[-3.6585440636,37.2332839966],"type":"Point"}
}