{
  "type": "Feature",
  "properties": {
    "addr:full":"R. Bel, 1 Atarrabia Navarra 31610",
    "addr:housenumber":"1",
    "addr:postcode":"31610",
    "addr:street":"Bel",
    "iso:country":"ES",
    "sg:address":"R. Bel, 1",
    "sg:city":"Atarrabia",
    "sg:orig_category":"Droguer\u00cdas (al Por Menor)",
    "sg:phone":"+34 948 36 31 58",
    "sg:postcode":"31610",
    "sg:province":"Navarra",
    "wof:name":"Droguera Navarra S.l.",
    "wof:placetype":"venue"
},
  "geometry": {"coordinates":[-1.6098489761,42.8311386108],"type":"Point"}
}