{
  "type": "Feature",
  "properties": {
    "addr:full":"Calle de Iparragirre, 4 Gernika-lumo Vizcaya 48300",
    "addr:housenumber":"4",
    "addr:postcode":"48300",
    "addr:street":"Calle De Iparragirre",
    "iso:country":"ES",
    "sg:address":"Calle de Iparragirre, 4",
    "sg:city":"Gernika-lumo",
    "sg:orig_category":"Ropa Para Ni\u00d1os (al Por Menor)",
    "sg:phone":"+34 946 25 67 17",
    "sg:postcode":"48300",
    "sg:province":"Vizcaya",
    "wof:name":"Umeak S.l",
    "wof:placetype":"venue"
},
  "geometry": {"coordinates":[-2.6768739223,43.3143463135],"type":"Point"}
}