{
  "type": "Feature",
  "properties": {
    "addr:full":"Gebala, 14 Estella Navarra 31200",
    "addr:housenumber":"14",
    "addr:postcode":"31200",
    "addr:street":"Gebala",
    "iso:country":"ES",
    "sg:address":"Gebala, 14",
    "sg:city":"Estella",
    "sg:orig_category":"Inform\u00c1tica (estudios, Servicios, Asesor\u00cda, Formaci\u00d3n)",
    "sg:phone":"+34 948 55 46 05",
    "sg:postcode":"31200",
    "sg:province":"Navarra",
    "wof:name":"Echeverria Erce Antonio",
    "wof:placetype":"venue"
},
  "geometry": {"coordinates":[-2.0353488922,42.6726417542],"type":"Point"}
}