{
  "type": "Feature",
  "properties": {
    "iso:country":"ES",
    "sg:address":"Avda Valladolid, 42",
    "sg:city":"Soria",
    "sg:orig_category":"Inform\u00c1tica: Soportes De Informaci\u00d3n, Suministros & Accesorios",
    "sg:phone":"+34 975 21 25 42",
    "sg:postcode":"42004",
    "sg:province":"Soria",
    "wof:name":"Inforcopy S.c.",
    "wof:placetype":"venue"
},
  "geometry": {"coordinates":[-2.4801299572,41.7670707703],"type":"Point"}
}