{
  "type": "Feature",
  "properties": {
    "addr:full":"Carr Major, 5 Seros Lleida 25183",
    "addr:housenumber":"5",
    "addr:postcode":"25183",
    "addr:street":"Carr Major",
    "iso:country":"ES",
    "sg:address":"Carr Major, 5",
    "sg:city":"Seros",
    "sg:orig_category":"Alquiler De V\u00cddeo",
    "sg:phone":"+34 973 78 00 77",
    "sg:postcode":"25183",
    "sg:province":"Lleida",
    "wof:name":"Miralbes Mercade Geronimo",
    "wof:placetype":"venue"
},
  "geometry": {"coordinates":[0.410048008,41.4631080627],"type":"Point"}
}