{
  "type": "Feature",
  "properties": {
    "addr:full":"Avda Madrid (de), 21 Avila \u00c1vila 05001",
    "addr:housenumber":"21",
    "addr:postcode":"05001",
    "addr:street":"Avda Madrid De;A\u0301Vila",
    "iso:country":"ES",
    "sg:address":"Avda Madrid (de), 21",
    "sg:city":"Avila",
    "sg:orig_category":"Ingenier\u00cda, Centros De Estudios (diversos)",
    "sg:phone":"+34 920 25 47 52",
    "sg:postcode":"05001",
    "sg:province":"\u00c1vila",
    "wof:name":"Indepro Avila 2000 Sl",
    "wof:placetype":"venue"
},
  "geometry": {"coordinates":[-4.6929812431,40.6579551697],"type":"Point"}
}