{
  "type": "Feature",
  "properties": {
    "iso:country":"ES",
    "sg:address":"Pase Milicias De Garachico, 1",
    "sg:city":"Santa Cruz De Tenerife",
    "sg:orig_category":"Abogados",
    "sg:phone":"+34 922 24 92 93",
    "sg:postcode":"38002",
    "sg:province":"Santa Cruz De Tenerife",
    "wof:name":"Bufete Machado S.l.",
    "wof:placetype":"venue"
},
  "geometry": {"coordinates":[-17.2191944122,28.1820106506],"type":"Point"}
}