{
  "type": "Feature",
  "properties": {
    "iso:country":"ES",
    "sg:address":"Carrer de Ferrer Bassa, 2",
    "sg:city":"Barcelona",
    "sg:orig_category":"Caf\u00c9s, Bares, Cervecer\u00cdas",
    "sg:phone":"+34 933 14 48 52",
    "sg:postcode":"08019",
    "sg:province":"Barcelona",
    "wof:name":"Gonzalez Reyes Rafael",
    "wof:placetype":"venue"
},
  "geometry": {"coordinates":[2.2146129608,41.4152870178],"type":"Point"}
}