{
  "type": "Feature",
  "properties": {
    "iso:country":"ES",
    "sg:address":"Villarroa\u00f1e, S/n",
    "sg:city":"Sta Olaja Ribera",
    "sg:orig_category":"Electricidad (montaje, Ensamblaje De Componentes)",
    "sg:phone":"+34 987 26 11 60",
    "sg:postcode":"24199",
    "sg:province":"Le\u00f3n",
    "wof:name":"Talleres Texauto S.l",
    "wof:placetype":"venue"
},
  "geometry": {"coordinates":[-5.5478792191,42.5467681885],"type":"Point"}
}