{
  "type": "Feature",
  "properties": {
    "iso:country":"ES",
    "sg:address":"Calle de Juan De Robles, 8",
    "sg:city":"Malaga",
    "sg:orig_category":"Doctores En Medicina",
    "sg:phone":"+34 952 28 68 47",
    "sg:postcode":"29010",
    "sg:province":"M\u00e1laga",
    "wof:name":"Neumologia Infantil Malaga S.l.",
    "wof:placetype":"venue"
},
  "geometry": {"coordinates":[-4.4570307732,36.7238578796],"type":"Point"}
}