{
  "type": "Feature",
  "properties": {
    "iso:country":"ES",
    "sg:address":"Avda Pais Valencia, 108",
    "sg:city":"Pobla Farnals",
    "sg:classifiers":[
        {
            "category":"Personal",
            "subcategory":"Barber",
            "type":"Services"
        }
    ],
    "sg:phone":"+34 961 45 05 42",
    "sg:postcode":"46139",
    "sg:province":"Valencia",
    "sg:tags":[
        "caballeros",
        "de",
        "peluqueros"
    ],
    "wof:name":"Guijarro Lara Pedro",
    "wof:placetype":"venue"
},
  "geometry": {"coordinates":[-0.327068001,39.5776863098],"type":"Point"}
}