{
  "type": "Feature",
  "properties": {
    "addr:full":"Pda Luesa, S/n Tarazona Zaragoza 50500",
    "addr:housenumber":"s",
    "addr:postcode":"50500",
    "addr:street":"/ N",
    "iso:country":"ES",
    "sg:address":"Pda Luesa, S/n",
    "sg:city":"Tarazona",
    "sg:orig_category":"Poller\u00cda Y Caza (al Por Menor)",
    "sg:phone":"+34 976 19 00 37",
    "sg:postcode":"50500",
    "sg:province":"Zaragoza",
    "wof:name":"Repolo S.l.",
    "wof:placetype":"venue"
},
  "geometry": {"coordinates":[-1.7390789986,41.90467453],"type":"Point"}
}