{
  "type": "Feature",
  "properties": {
    "addr:full":"Avda General Franco, 28 Santa Uxia De Ribeira La Coru\u00f1a 15960",
    "addr:housenumber":"28",
    "addr:postcode":"15960",
    "addr:street":"Avda General Franco;Corun\u0303A",
    "iso:country":"ES",
    "sg:address":"Avda General Franco, 28",
    "sg:city":"Santa Uxia De Ribeira",
    "sg:orig_category":"Bancos",
    "sg:phone":"+34 981 87 10 38",
    "sg:postcode":"15960",
    "sg:province":"La Coru\u00f1a",
    "sg:website":"www.gruposantander.es",
    "wof:name":"Bt Espa\u00d1a Compa\u00d1ia De Servicios Globales De Telecomunicaciones S.a.u.",
    "wof:placetype":"venue"
},
  "geometry": {"coordinates":[-8.9913883209,42.5561332703],"type":"Point"}
}