{
  "type": "Feature",
  "properties": {
    "addr:full":"Plaz Virgen, S/n Valencia Valencia 46003",
    "addr:housenumber":"s / n",
    "addr:postcode":"46003",
    "addr:street":"Plaz Virgen",
    "iso:country":"ES",
    "sg:address":"Plaz Virgen, S/n",
    "sg:city":"Valencia",
    "sg:orig_category":"Empresarios",
    "sg:phone":"+34 963 91 52 79",
    "sg:postcode":"46003",
    "sg:province":"Valencia",
    "wof:name":"Luis Batalla S.a.",
    "wof:placetype":"venue"
},
  "geometry": {"coordinates":[-0.3769130111,39.4687919617],"type":"Point"}
}