{
  "type": "Feature",
  "properties": {
    "addr:full":"Calle de Santa Teresa, 1 Barco De Avila \u00c1vila 05600",
    "addr:housenumber":"1",
    "addr:postcode":"05600",
    "addr:street":"Calle De Santa Teresa;A\u0301Vila",
    "iso:country":"ES",
    "sg:address":"Calle de Santa Teresa, 1",
    "sg:city":"Barco De Avila",
    "sg:orig_category":"Quincaller\u00cda (al Por Menor)",
    "sg:phone":"+34 920 34 00 60",
    "sg:postcode":"05600",
    "sg:province":"\u00c1vila",
    "wof:name":"Perez Moreno Luis",
    "wof:placetype":"venue"
},
  "geometry": {"coordinates":[-5.5230169296,40.3574981689],"type":"Point"}
}