{
  "type": "Feature",
  "properties": {
    "addr:full":"Calle de Cambados, 21 Madrid Madrid 28050",
    "addr:housenumber":"21",
    "addr:postcode":"madrid;28050",
    "addr:street":"Calle De Cambados",
    "iso:country":"ES",
    "sg:address":"Calle de Cambados, 21",
    "sg:city":"Madrid",
    "sg:orig_category":"Venta, Instalaci\u00d3n De Calefacci\u00d3n",
    "sg:phone":"+34 913 81 77 63",
    "sg:postcode":"28050",
    "sg:province":"Madrid",
    "wof:name":"Herramientas Lexsa S.l.",
    "wof:placetype":"venue"
},
  "geometry": {"coordinates":[-3.6275467873,40.4786643982],"type":"Point"}
}