{
  "type": "Feature",
  "properties": {
    "addr:full":"Carr Corts Catalanes, 13 Lleida Lleida 25005",
    "addr:housenumber":"13",
    "addr:postcode":"25005",
    "addr:street":"Carr Corts Catalanes",
    "iso:country":"ES",
    "sg:address":"Carr Corts Catalanes, 13",
    "sg:city":"Lleida",
    "sg:classifiers":[
        {
            "category":"Taxi",
            "type":"Transportation"
        }
    ],
    "sg:phone":"+34 973 23 99 00",
    "sg:postcode":"25005",
    "sg:province":"Lleida",
    "wof:name":"Lleidataxi S.c.c.l.",
    "wof:placetype":"venue"
},
  "geometry": {"coordinates":[0.6265429854,41.6253662109],"type":"Point"}
}