{
  "type": "Feature",
  "properties": {
    "addr:full":"Barro Do Carme, 2 Borraxeiros Pontevedra 36525",
    "addr:housenumber":"2",
    "addr:postcode":"36525",
    "addr:street":"Carme",
    "iso:country":"ES",
    "sg:address":"Barro Do Carme, 2",
    "sg:city":"Borraxeiros",
    "sg:orig_category":"Charcuter\u00cdas (al Por Mayor)",
    "sg:phone":"+34 986 78 82 45",
    "sg:postcode":"36525",
    "sg:province":"Pontevedra",
    "wof:name":"Embutidos Farelo S.l.",
    "wof:placetype":"venue"
},
  "geometry": {"coordinates":[-8.0167131424,42.8462600708],"type":"Point"}
}