{
  "type": "Feature",
  "properties": {
    "addr:full":"Calle de Txapinene, 3 Donostia-san Sebastian Guip\u00f9zcoa 20016",
    "addr:housenumber":"3",
    "addr:postcode":"20016",
    "addr:street":"Calle De Txapinene",
    "iso:country":"ES",
    "sg:address":"Calle de Txapinene, 3",
    "sg:city":"Donostia-san Sebastian",
    "sg:orig_category":"Molduras, Junquillos, Listones Y Molduras Perforadas",
    "sg:phone":"+34 943 35 34 80",
    "sg:postcode":"20016",
    "sg:province":"Guip\u00f9zcoa",
    "wof:name":"Callphone S.l",
    "wof:placetype":"venue"
},
  "geometry": {"coordinates":[-1.9414600134,43.323551178],"type":"Point"}
}