{
  "type": "Feature",
  "properties": {
    "addr:full":"Calle de Camara La, 12 Aviles Asturias 33402",
    "addr:housenumber":"12",
    "addr:postcode":"33402",
    "addr:street":"Calle De Camara La",
    "iso:country":"ES",
    "sg:address":"Calle de Camara La, 12",
    "sg:city":"Aviles",
    "sg:orig_category":"Abogados",
    "sg:phone":"+34 985 56 91 74",
    "sg:postcode":"33402",
    "sg:province":"Asturias",
    "wof:name":"Veca Juristas C.b.",
    "wof:placetype":"venue"
},
  "geometry": {"coordinates":[-5.9225769043,43.5559196472],"type":"Point"}
}