{
  "type": "Feature",
  "properties": {
    "addr:full":"Cra Monzon, S/n Almunia San Juan Huesca 22420",
    "addr:housenumber":"s / n",
    "addr:postcode":"22420",
    "iso:country":"ES",
    "sg:address":"Cra Monzon, S/n",
    "sg:city":"Almunia San Juan",
    "sg:orig_category":"Calderer\u00cda",
    "sg:phone":"+34 974 40 30 55",
    "sg:postcode":"22420",
    "sg:province":"Huesca",
    "wof:name":"Cistas S.l",
    "wof:placetype":"venue"
},
  "geometry": {"coordinates":[0.2437330037,41.9334564209],"type":"Point"}
}