{
  "type": "Feature",
  "properties": {
    "addr:full":"Avda Habana, 122 Pontes Garcia Rodriguez La Coru\u00f1a 15320",
    "addr:housenumber":"122",
    "addr:postcode":"15320",
    "addr:street":"Avda Habana;Corun\u0303A",
    "iso:country":"ES",
    "sg:address":"Avda Habana, 122",
    "sg:city":"Pontes Garcia Rodriguez",
    "sg:orig_category":"Ropa Para Beb\u00c9s Y Ni\u00d1os (confecci\u00d3n, Al Por Mayor)",
    "sg:phone":"+34 981 45 20 35",
    "sg:postcode":"15320",
    "sg:province":"La Coru\u00f1a",
    "wof:name":"Bouza Bouza Antonia",
    "wof:placetype":"venue"
},
  "geometry": {"coordinates":[-7.8458108902,43.4492225647],"type":"Point"}
}