{
  "type": "Feature",
  "properties": {
    "iso:country":"ES",
    "sg:address":"Calle de Urda, 127",
    "sg:city":"Consuegra",
    "sg:orig_category":"Empresarios",
    "sg:phone":"+34 925 47 56 50",
    "sg:postcode":"45700",
    "sg:province":"Toledo",
    "wof:name":"Compunga S.l.",
    "wof:placetype":"venue"
},
  "geometry": {"coordinates":[-3.6074590683,39.4586410522],"type":"Point"}
}