{
  "type": "Feature",
  "properties": {
    "iso:country":"ES",
    "sg:address":"Ptda Dels Sifons, 3",
    "sg:city":"Banyeres Mariola",
    "sg:orig_category":"Ropa Para Ni\u00d1os (al Por Menor)",
    "sg:phone":"+34 965 56 75 36",
    "sg:postcode":"03450",
    "sg:province":"Alicante",
    "wof:name":"Mora Ferre E Hijos S.l.",
    "wof:placetype":"venue"
},
  "geometry": {"coordinates":[-0.6580740213,38.7120857239],"type":"Point"}
}