{
  "type": "Feature",
  "properties": {
    "addr:full":"Calle de San Isidro Labrador, 1 Segorbe Castell\u00f3n 12400",
    "addr:housenumber":"1",
    "addr:postcode":"12400",
    "addr:street":"Calle De San Isidro Labrador",
    "iso:country":"ES",
    "sg:address":"Calle de San Isidro Labrador, 1",
    "sg:city":"Segorbe",
    "sg:orig_category":"Comercio, Reparaci\u00d3n De Bicicletas, De Motocicletas, De Accesorios",
    "sg:phone":"+34 964 71 14 57",
    "sg:postcode":"12400",
    "sg:province":"Castell\u00f3n",
    "wof:name":"Bici-sport Sergobe S.l.",
    "wof:placetype":"venue"
},
  "geometry": {"coordinates":[-0.4870890081,39.8477287292],"type":"Point"}
}