{
  "type": "Feature",
  "properties": {
    "iso:country":"ES",
    "sg:address":"Calle de Angel Del Alcazar, 19",
    "sg:city":"Talavera Reina",
    "sg:orig_category":"Florister\u00cdas",
    "sg:phone":"+34 925 81 65 08",
    "sg:postcode":"45600",
    "sg:province":"Toledo",
    "sg:website":"www.interflora.es/clio",
    "wof:name":"Rodriguez Garcia Jose Manuel",
    "wof:placetype":"venue"
},
  "geometry": {"coordinates":[-4.8205451965,39.9633522034],"type":"Point"}
}