{
  "type": "Feature",
  "properties": {
    "iso:country":"ES",
    "sg:address":"Poli Industrial, 16",
    "sg:city":"Ablitas",
    "sg:orig_category":"Sales (al Por Mayor)",
    "sg:phone":"+34 948 81 35 75",
    "sg:postcode":"31523",
    "sg:province":"Navarra",
    "wof:name":"Leon Marco Jose Ignacio",
    "wof:placetype":"venue"
},
  "geometry": {"coordinates":[-1.6386940479,41.9736442566],"type":"Point"}
}