{
  "type": "Feature",
  "properties": {
    "addr:full":"Calle de Concejo, 17 Sorzano La Rioja 26191",
    "addr:housenumber":"17",
    "addr:postcode":"26191",
    "addr:street":"Calle De Concejo;Sorzano;Rioja",
    "iso:country":"ES",
    "sg:address":"Calle de Concejo, 17",
    "sg:city":"Sorzano",
    "sg:orig_category":"Empresarios",
    "sg:phone":"+34 941 44 73 47",
    "sg:postcode":"26191",
    "sg:province":"La Rioja",
    "wof:name":"Calvo Martinez Pedro",
    "wof:placetype":"venue"
},
  "geometry": {"coordinates":[-2.5287280083,42.3430747986],"type":"Point"}
}