{
  "type": "Feature",
  "properties": {
    "addr:full":"Pl Espanya, 9 Sitges Barcelona 08870",
    "addr:housenumber":"9",
    "addr:postcode":"08870",
    "addr:street":"Pl Espanya",
    "iso:country":"ES",
    "sg:address":"Pl Espanya, 9",
    "sg:city":"Sitges",
    "sg:classifiers":[
        {
            "category":"Personal",
            "subcategory":"Barber",
            "type":"Services"
        }
    ],
    "sg:phone":"+34 938 94 18 94",
    "sg:postcode":"08870",
    "sg:province":"Barcelona",
    "sg:tags":[
        "caballeros",
        "de",
        "peluqueros"
    ],
    "wof:name":"Batik Nueve S.c.p.",
    "wof:placetype":"venue"
},
  "geometry": {"coordinates":[1.8059170246,41.2363166809],"type":"Point"}
}