{
  "type": "Feature",
  "properties": {
    "addr:full":"Calle de Goya, 5 Madrid Madrid 28001",
    "addr:housenumber":"5",
    "addr:postcode":"28001",
    "addr:street":"Calle De Goya",
    "iso:country":"ES",
    "sg:address":"Calle de Goya, 5",
    "sg:city":"Madrid",
    "sg:orig_category":"Financiaci\u00d3n Y Cr\u00c9ditos",
    "sg:phone":"+34 915 76 74 20",
    "sg:postcode":"28001",
    "sg:province":"Madrid",
    "wof:name":"Dedalo Capital Desarrollo S.l.",
    "wof:placetype":"venue"
},
  "geometry": {"coordinates":[-3.6889019012,40.4256782532],"type":"Point"}
}