{
  "type": "Feature",
  "properties": {
    "iso:country":"ES",
    "sg:address":"Carr Avall, D', 34",
    "sg:city":"Sineu",
    "sg:orig_category":"Molduras, Junquillos, Listones Y Molduras Perforadas",
    "sg:phone":"+34 971 52 01 70",
    "sg:postcode":"07510",
    "sg:province":"Islas Baleares",
    "wof:name":"Matas Real Joan",
    "wof:placetype":"venue"
},
  "geometry": {"coordinates":[3.0133590698,39.6453285217],"type":"Point"}
}