{
  "type": "Feature",
  "properties": {
    "addr:full":"Calle de Panaderos, 26 Valladolid Valladolid 47004",
    "addr:housenumber":"26",
    "addr:postcode":"47004",
    "addr:street":"Calle De Panaderos",
    "iso:country":"ES",
    "sg:address":"Calle de Panaderos, 26",
    "sg:city":"Valladolid",
    "sg:orig_category":"Prendas Y Chalecos De Punto (al Por Menor)",
    "sg:phone":"+34 983 30 18 43",
    "sg:postcode":"47004",
    "sg:province":"Valladolid",
    "wof:name":"Sanchez Sevillano Angel",
    "wof:placetype":"venue"
},
  "geometry": {"coordinates":[-4.7232170105,41.6469841003],"type":"Point"}
}