{
  "type": "Feature",
  "properties": {
    "iso:country":"ES",
    "sg:address":"Pase General Davila, 129",
    "sg:city":"Santander",
    "sg:orig_category":"Bater\u00cdas",
    "sg:phone":"+34 942 32 40 72",
    "sg:postcode":"39010",
    "sg:province":"Cantabria",
    "wof:name":"Imprex Europa S.l.",
    "wof:placetype":"venue"
},
  "geometry": {"coordinates":[-3.8100090027,43.4614982605],"type":"Point"}
}