{
  "type": "Feature",
  "properties": {
    "iso:country":"ES",
    "sg:address":"Ptge Josep Ros, 2",
    "sg:city":"Martorell",
    "sg:orig_category":"Radiocomunicaciones, Telefon\u00cda M\u00d3vil, Radiomensajer\u00cda: Servicios, Comercializaci\u00d3n",
    "sg:phone":"+34 937 75 18 00",
    "sg:postcode":"08760",
    "sg:province":"Barcelona",
    "wof:name":"Comunicaciones Molins S.l.",
    "wof:placetype":"venue"
},
  "geometry": {"coordinates":[1.9141490459,41.4772033691],"type":"Point"}
}