{
  "type": "Feature",
  "properties": {
    "iso:country":"ES",
    "sg:address":"Bodegueros (p I El Lirio), S/n",
    "sg:city":"Bollullos Par Condado",
    "sg:orig_category":"Centros Empresariales",
    "sg:phone":"+34 959 41 38 94",
    "sg:postcode":"21710",
    "sg:province":"Huelva",
    "wof:name":"Ramos Sierra S.a.",
    "wof:placetype":"venue"
},
  "geometry": {"coordinates":[-6.5419588089,37.3506317139],"type":"Point"}
}