{
  "type": "Feature",
  "properties": {
    "addr:full":"Calle de Juan Ramon Jimenez, 2 Villa Rio C\u00f3rdoba 14640",
    "addr:housenumber":"2",
    "addr:postcode":"14640",
    "addr:street":"Calle De Juan Ramon Jimenez;Villa Rio Co\u0301Rdoba",
    "iso:country":"ES",
    "sg:address":"Calle de Juan Ramon Jimenez, 2",
    "sg:city":"Villa Rio",
    "sg:orig_category":"Asesor\u00cda Fiscal Y Jur\u00cddica",
    "sg:phone":"+34 957 17 75 65",
    "sg:postcode":"14640",
    "sg:province":"C\u00f3rdoba",
    "wof:name":"Proasa Cordoba S.l.",
    "wof:placetype":"venue"
},
  "geometry": {"coordinates":[-4.2939839363,37.9821434021],"type":"Point"}
}