{
  "type": "Feature",
  "properties": {
    "addr:full":"Avda Costa (da), S/n Ferreira Lugo 27770",
    "addr:postcode":"27770",
    "addr:street":"Avda Costa Da S / N Ferreira",
    "iso:country":"ES",
    "sg:address":"Avda Costa (da), S/n",
    "sg:city":"Ferreira",
    "sg:orig_category":"Reposter\u00cdas",
    "sg:phone":"+34 982 57 44 78",
    "sg:postcode":"27770",
    "sg:province":"Lugo",
    "wof:name":"Trigo Mendez Maria Del Carmen",
    "wof:placetype":"venue"
},
  "geometry": {"coordinates":[-7.4394249916,43.5531730652],"type":"Point"}
}