{
  "type": "Feature",
  "properties": {
    "iso:country":"ES",
    "sg:address":"Calle de Mayor, S/n",
    "sg:city":"Berroeta",
    "sg:orig_category":"Cr\u00cda De Animales",
    "sg:phone":"+34 948 58 50 44",
    "sg:postcode":"31796",
    "sg:province":"Navarra",
    "wof:name":"Echenique Vicondoa Juana Mari Maritorena Iturralde Lorenzo",
    "wof:placetype":"venue"
},
  "geometry": {"coordinates":[-1.5800379515,43.1118125916],"type":"Point"}
}