{
  "type": "Feature",
  "properties": {
    "addr:full":"Calle de Acero Del, 13 Aviles Asturias 33403",
    "addr:housenumber":"13",
    "addr:postcode":"33403",
    "addr:street":"Calle De Acero Del",
    "iso:country":"ES",
    "sg:address":"Calle de Acero Del, 13",
    "sg:city":"Aviles",
    "sg:orig_category":"Alquiler De Gr\u00daas",
    "sg:phone":"+34 985 51 08 96",
    "sg:postcode":"33403",
    "sg:province":"Asturias",
    "wof:name":"Gruas Vega S.l.",
    "wof:placetype":"venue"
},
  "geometry": {"coordinates":[-5.9144730568,43.551410675],"type":"Point"}
}