{
  "type": "Feature",
  "properties": {
    "addr:full":"Avda Buenos Aires, 23 Carballi\u00f1o Ourense 32500",
    "addr:housenumber":"23",
    "addr:postcode":"32500",
    "addr:street":"Avda Buenos Aires",
    "iso:country":"ES",
    "sg:address":"Avda Buenos Aires, 23",
    "sg:city":"Carballi\u00f1o",
    "sg:orig_category":"Mec\u00c1nico Del Autom\u00d3vil",
    "sg:phone":"+34 988 27 20 80",
    "sg:postcode":"32500",
    "sg:province":"Ourense",
    "wof:name":"Reinoso Bernardez Ramon",
    "wof:placetype":"venue"
},
  "geometry": {"coordinates":[-8.0741043091,42.433265686],"type":"Point"}
}