{
  "type": "Feature",
  "properties": {
    "iso:country":"ES",
    "sg:address":"Avda Atlantida, 74",
    "sg:city":"Vigo",
    "sg:orig_category":"Librer\u00cdas",
    "sg:phone":"+34 986 24 07 00",
    "sg:postcode":"36208",
    "sg:province":"Pontevedra",
    "wof:name":"Nu\u00f1ez Costas Dolores",
    "wof:placetype":"venue"
},
  "geometry": {"coordinates":[-8.759062767,42.2217178345],"type":"Point"}
}