{
  "type": "Feature",
  "properties": {
    "addr:full":"Plaz Gerardo Armesto, 2 Vitoria-gasteiz \u00c1lava 01008",
    "addr:housenumber":"2",
    "addr:postcode":"01008",
    "addr:street":"Armesto",
    "iso:country":"ES",
    "sg:address":"Plaz Gerardo Armesto, 2",
    "sg:city":"Vitoria-gasteiz",
    "sg:orig_category":"Caf\u00c9s, Bares, Cervecer\u00cdas",
    "sg:phone":"+34 945 24 94 87",
    "sg:postcode":"01008",
    "sg:province":"\u00c1lava",
    "wof:name":"Bravo Requies Juan Maria",
    "wof:placetype":"venue"
},
  "geometry": {"coordinates":[-2.6823670864,42.8463096619],"type":"Point"}
}