{
  "type": "Feature",
  "properties": {
    "iso:country":"ES",
    "sg:address":"Ctra Rafal, 26",
    "sg:city":"Carretera De Rafal",
    "sg:orig_category":"Medias Y Calcetines (al Por Menor)",
    "sg:phone":"+34 965 31 16 26",
    "sg:postcode":"03360",
    "sg:province":"Alicante",
    "wof:name":"Cuadrado Cutillas Jose",
    "wof:placetype":"venue"
},
  "geometry": {"coordinates":[-0.8739690185,38.1261291504],"type":"Point"}
}