{
  "type": "Feature",
  "properties": {
    "iso:country":"ES",
    "sg:address":"Avda Galicia, 10",
    "sg:city":"Vegadeo",
    "sg:orig_category":"T\u00c9cnicos Veterinarios",
    "sg:phone":"+34 985 63 46 73",
    "sg:postcode":"33770",
    "sg:province":"Asturias",
    "wof:name":"Rego Fernandez Jose Luis",
    "wof:placetype":"venue"
},
  "geometry": {"coordinates":[-7.0533261299,43.4646911621],"type":"Point"}
}