{
  "type": "Feature",
  "properties": {
    "addr:full":"Calle de Doctor Garcia Reyes, 5 Albacete Albacete 02002",
    "addr:housenumber":"5",
    "addr:postcode":"02002",
    "addr:street":"Calle De Doctor Garcia Reyes",
    "iso:country":"ES",
    "sg:address":"Calle de Doctor Garcia Reyes, 5",
    "sg:city":"Albacete",
    "sg:orig_category":"Garajes De Veh\u00cdculos",
    "sg:phone":"+34 967 22 14 69",
    "sg:postcode":"02002",
    "sg:province":"Albacete",
    "wof:name":"Garaje Rosario S.l.",
    "wof:placetype":"venue"
},
  "geometry": {"coordinates":[-1.8587498665,38.9843673706],"type":"Point"}
}