{
  "type": "Feature",
  "properties": {
    "addr:full":"Calle de Amargura, 21 Priego Cordoba C\u00f3rdoba 14800",
    "addr:housenumber":"21",
    "addr:postcode":"14800",
    "addr:street":"Calle De Amargura;Cordoba Co\u0301Rdoba",
    "iso:country":"ES",
    "sg:address":"Calle de Amargura, 21",
    "sg:city":"Priego Cordoba",
    "sg:orig_category":"Pintura, Barniz, Productos Asimilables (fabricaci\u00d3n, Al Por Mayor)",
    "sg:phone":"+34 957 54 10 59",
    "sg:postcode":"14800",
    "sg:province":"C\u00f3rdoba",
    "wof:name":"Sanchez Madrid Rafael",
    "wof:placetype":"venue"
},
  "geometry": {"coordinates":[-4.1984848976,37.4364814758],"type":"Point"}
}