{
  "type": "Feature",
  "properties": {
    "iso:country":"ES",
    "sg:address":"Cra Fuente De San Luis, 13",
    "sg:city":"Valencia",
    "sg:orig_category":"Abogados",
    "sg:phone":"+34 963 74 17 96",
    "sg:postcode":"46006",
    "sg:province":"Valencia",
    "wof:name":"Fernandez Fernandez Jose Maria",
    "wof:placetype":"venue"
},
  "geometry": {"coordinates":[-0.3716369867,39.4576911926],"type":"Point"}
}