{
  "type": "Feature",
  "properties": {
    "iso:country":"ES",
    "sg:address":"Calle de Batalla De Lepanto, 24",
    "sg:city":"Zaragoza",
    "sg:orig_category":"Molduras, Junquillos, Listones Y Molduras Perforadas",
    "sg:phone":"+34 976 42 89 32",
    "sg:postcode":"50002",
    "sg:province":"Zaragoza",
    "wof:name":"Zhuo  Alalfen",
    "wof:placetype":"venue"
},
  "geometry": {"coordinates":[-0.864941299,41.6447143555],"type":"Point"}
}