{
  "type": "Feature",
  "properties": {
    "iso:country":"ES",
    "sg:address":"Calle de Juan Carlos I Rey De Espa\u00d1a, 9",
    "sg:city":"Rute",
    "sg:orig_category":"\u00d3ptica: Instrumentos (fabricaci\u00d3n)",
    "sg:phone":"+34 957 53 24 22",
    "sg:postcode":"14960",
    "sg:province":"C\u00f3rdoba",
    "wof:name":"Alvarez Salvatierra Francisca",
    "wof:placetype":"venue"
},
  "geometry": {"coordinates":[-4.3711476326,37.3259620667],"type":"Point"}
}