{
  "type": "Feature",
  "properties": {
    "iso:country":"ES",
    "sg:address":"Calle de Hospital, S/n",
    "sg:city":"Navaluenga",
    "sg:orig_category":"Molduras, Junquillos, Listones Y Molduras Perforadas",
    "sg:phone":"+34 920 28 61 04",
    "sg:postcode":"05100",
    "sg:province":"\u00c1vila",
    "wof:name":"Pe\u00f1a Lopez Jose",
    "wof:placetype":"venue"
},
  "geometry": {"coordinates":[-4.7079491615,40.412979126],"type":"Point"}
}