{
  "type": "Feature",
  "properties": {
    "iso:country":"ES",
    "sg:address":"Sadar, 2",
    "sg:city":"Iru\u00f1a",
    "sg:orig_category":"Garajes De Veh\u00cdculos",
    "sg:phone":"+34 948 24 90 83",
    "sg:postcode":"31006",
    "sg:province":"Navarra",
    "sg:website":"www.taller-alzorriz.com",
    "wof:name":"Ayerra Irisarri S.l.",
    "wof:placetype":"venue"
},
  "geometry": {"coordinates":[-1.6425750256,42.7985610962],"type":"Point"}
}