{
  "type": "Feature",
  "properties": {
    "iso:country":"ES",
    "sg:address":"Calle de Luis Lopez Oses, 16",
    "sg:city":"Arenas -areeta",
    "sg:orig_category":"Peluqueros: De Se\u00d1oras",
    "sg:phone":"+34 944 63 38 97",
    "sg:postcode":"48930",
    "sg:province":"Vizcaya",
    "wof:name":"Alonso Diego Miren Edurne",
    "wof:placetype":"venue"
},
  "geometry": {"coordinates":[-3.0059766769,43.3303718567],"type":"Point"}
}