{
  "type": "Feature",
  "properties": {
    "addr:full":"Calle de Caucho, 25 Torrejon Ardoz Madrid 28850",
    "addr:housenumber":"25",
    "addr:postcode":"28850",
    "addr:street":"Calle De Caucho",
    "iso:country":"ES",
    "sg:address":"Calle de Caucho, 25",
    "sg:city":"Torrejon Ardoz",
    "sg:orig_category":"Veh\u00cdculos De Ocasi\u00d3n",
    "sg:phone":"+34 916 76 62 11",
    "sg:postcode":"28850",
    "sg:province":"Madrid",
    "wof:name":"Automoviles De La Morena S.l.",
    "wof:placetype":"venue"
},
  "geometry": {"coordinates":[-3.4541900158,40.4522247314],"type":"Point"}
}