{
  "type": "Feature",
  "properties": {
    "iso:country":"ES",
    "sg:address":"Calle de Eusebio Navarro, 8",
    "sg:city":"Palmas De Gran Canaria",
    "sg:orig_category":"Aguas (distribuci\u00d3n, Servicios)",
    "sg:phone":"+34 928 36 86 42",
    "sg:postcode":"35003",
    "sg:province":"Las Palmas",
    "wof:name":"Canarias Conservacion S.l.",
    "wof:placetype":"venue"
},
  "geometry": {"coordinates":[-15.4222106934,28.1127338409],"type":"Point"}
}