{
  "type": "Feature",
  "properties": {
    "addr:full":"Calle de Rosa De Los Vientos, 38 Malaga M\u00e1laga 29006",
    "addr:housenumber":"38",
    "addr:postcode":"29006",
    "addr:street":"Calle De Rosa De Los Vientos;Ma\u0301Laga",
    "iso:country":"ES",
    "sg:address":"Calle de Rosa De Los Vientos, 38",
    "sg:city":"Malaga",
    "sg:orig_category":"Caf\u00c9s, Bares, Cervecer\u00cdas",
    "sg:phone":"+34 952 32 43 00",
    "sg:postcode":"29006",
    "sg:province":"M\u00e1laga",
    "wof:name":"Antonio Vega Y Francisco Rodriguez Cb",
    "wof:placetype":"venue"
},
  "geometry": {"coordinates":[-4.484603405,36.7108306885],"type":"Point"}
}