{
  "type": "Feature",
  "properties": {
    "iso:country":"ES",
    "sg:address":"Cno. Huerta De Bicho, 15",
    "sg:city":"Barranco De Las Lajas",
    "sg:orig_category":"Carnicer\u00cdas, Carnicer\u00cdas",
    "sg:phone":"+34 922 58 47 84",
    "sg:postcode":"38355",
    "sg:province":"Santa Cruz De Tenerife",
    "wof:name":"Marichal Gil Ismael",
    "wof:placetype":"venue"
},
  "geometry": {"coordinates":[-16.4059047699,28.4648990631],"type":"Point"}
}