{
  "type": "Feature",
  "properties": {
    "addr:full":"Carrer de Prat De La Riba, 6 Martorell Barcelona 08760",
    "addr:housenumber":"6",
    "addr:postcode":"08760",
    "addr:street":"Carrer De Prat De La Riba",
    "iso:country":"ES",
    "sg:address":"Carrer de Prat De La Riba, 6",
    "sg:city":"Martorell",
    "sg:orig_category":"Productos Qu\u00cdmicos (fabricaci\u00d3n, Al Por Mayor)",
    "sg:phone":"+34 937 75 09 56",
    "sg:postcode":"08760",
    "sg:province":"Barcelona",
    "wof:name":"Entorn Quimic Sl",
    "wof:placetype":"venue"
},
  "geometry": {"coordinates":[1.9125460386,41.4785957336],"type":"Point"}
}