{
  "type": "Feature",
  "properties": {
    "iso:country":"ES",
    "sg:address":"Calle de Azara, 1",
    "sg:city":"Almeria",
    "sg:orig_category":"Abogados",
    "sg:phone":"+34 950 24 38 47",
    "sg:postcode":"04001",
    "sg:province":"Almer\u00eda",
    "wof:name":"Galvez Lopez Manuel Jesus",
    "wof:placetype":"venue"
},
  "geometry": {"coordinates":[-2.4657196999,36.8407211304],"type":"Point"}
}