{
  "type": "Feature",
  "properties": {
    "addr:full":"Calle de Capitan Cortes, 2 Logro\u00f1o La Rioja 26003",
    "addr:housenumber":"2",
    "addr:postcode":"26003",
    "addr:street":"Calle De Capitan Cortes;Rioja",
    "iso:country":"ES",
    "sg:address":"Calle de Capitan Cortes, 2",
    "sg:city":"Logro\u00f1o",
    "sg:orig_category":"Formaci\u00d3n Continuada (variada)",
    "sg:phone":"+34 941 25 19 65",
    "sg:postcode":"26003",
    "sg:province":"La Rioja",
    "wof:name":"Zarate Ibarra Teodulo Lorenzo",
    "wof:placetype":"venue"
},
  "geometry": {"coordinates":[-2.442347765,42.4649772644],"type":"Point"}
}