{
  "type": "Feature",
  "properties": {
    "iso:country":"ES",
    "sg:address":"Camp De La Podadora, S/n",
    "sg:city":"Canovelles",
    "sg:orig_category":"M\u00c1rmoles, Granitos Y Piedras Naturales",
    "sg:phone":"+34 938 49 47 73",
    "sg:postcode":"08420",
    "sg:province":"Barcelona",
    "wof:name":"Marmoles Canovelles S.c.p.",
    "wof:placetype":"venue"
},
  "geometry": {"coordinates":[2.2780098915,41.6220703125],"type":"Point"}
}