{
  "type": "Feature",
  "properties": {
    "addr:full":"Rua San Pedro, 8 Maceda Ourense 32700",
    "addr:housenumber":"8",
    "addr:postcode":"32700",
    "addr:street":"Rua San Pedro",
    "iso:country":"ES",
    "sg:address":"Rua San Pedro, 8",
    "sg:city":"Maceda",
    "sg:orig_category":"Lavado, Limpieza De Veh\u00cdculos",
    "sg:phone":"+34 988 46 32 37",
    "sg:postcode":"32700",
    "sg:province":"Ourense",
    "wof:name":"Carballo Ramos Antonio",
    "wof:placetype":"venue"
},
  "geometry": {"coordinates":[-7.6531739235,42.2673873901],"type":"Point"}
}