{
  "type": "Feature",
  "properties": {
    "iso:country":"ES",
    "sg:address":"Calle de Ebanisteria (la), 8",
    "sg:city":"Alacant",
    "sg:orig_category":"Inform\u00c1tica (estudios, Servicios, Asesor\u00cda, Formaci\u00d3n)",
    "sg:phone":"+34 965 11 08 59",
    "sg:postcode":"03008",
    "sg:province":"Alicante",
    "wof:name":"Comerciantes De Electrodomesticos Alicante S.a.",
    "wof:placetype":"venue"
},
  "geometry": {"coordinates":[-0.5129470825,38.3347244263],"type":"Point"}
}