{
  "type": "Feature",
  "properties": {
    "iso:country":"ES",
    "sg:address":"Afores, S/n",
    "sg:city":"Camp-redo",
    "sg:orig_category":"Producci\u00d3n, Venta De Productos De Agricultura Biol\u00d3gica",
    "sg:phone":"+34 977 59 71 48",
    "sg:postcode":"43897",
    "sg:province":"Tarragona",
    "wof:name":"Raventos Pages Pau Y Cia C.b.",
    "wof:placetype":"venue"
},
  "geometry": {"coordinates":[0.5545499921,40.7676849365],"type":"Point"}
}