{
  "type": "Feature",
  "properties": {
    "iso:country":"ES",
    "sg:address":"Calle de San Ignacio De Loyola, 11",
    "sg:city":"Zaragoza",
    "sg:orig_category":"Asociaciones Y Clubs Deportivos",
    "sg:phone":"+34 976 30 12 42",
    "sg:postcode":"50008",
    "sg:province":"Zaragoza",
    "wof:name":"Tst Shops S.l.",
    "wof:placetype":"venue"
},
  "geometry": {"coordinates":[-0.8845695257,41.6462745667],"type":"Point"}
}