{
  "type": "Feature",
  "properties": {
    "addr:full":"Calle de Canal De Suez, 36 Madrid Madrid 28042",
    "addr:housenumber":"36",
    "addr:postcode":"madrid;28042",
    "addr:street":"Calle De Canal De Suez",
    "iso:country":"ES",
    "sg:address":"Calle de Canal De Suez, 36",
    "sg:city":"Madrid",
    "sg:orig_category":"Inmobiliaria (agencias)",
    "sg:phone":"+34 913 12 16 00",
    "sg:postcode":"28042",
    "sg:province":"Madrid",
    "wof:name":"Valhondo Europea S.l.",
    "wof:placetype":"venue"
},
  "geometry": {"coordinates":[-3.5793089867,40.4731636047],"type":"Point"}
}