{
  "type": "Feature",
  "properties": {
    "addr:full":"Calle de Escritor Torquemada, 1 Cordoba C\u00f3rdoba 14011",
    "addr:housenumber":"1",
    "addr:postcode":"14011",
    "addr:street":"Calle De Escritor Torquemada;Co\u0301Rdoba",
    "iso:country":"ES",
    "sg:address":"Calle de Escritor Torquemada, 1",
    "sg:city":"Cordoba",
    "sg:orig_category":"Almacenes Para Venta: Muebles Y Varios",
    "sg:phone":"+34 957 27 28 30",
    "sg:postcode":"14011",
    "sg:province":"C\u00f3rdoba",
    "wof:name":"M.j.c.p. Sur E Hijos S.l.",
    "wof:placetype":"venue"
},
  "geometry": {"coordinates":[-4.7908058167,37.8914108276],"type":"Point"}
}