{
  "type": "Feature",
  "properties": {
    "addr:full":"Avda Oviedo, 31 Nore\u00f1a Asturias 33180",
    "addr:housenumber":"31",
    "addr:postcode":"33180",
    "addr:street":"Avda Oviedo;Asturias",
    "iso:country":"ES",
    "sg:address":"Avda Oviedo, 31",
    "sg:city":"Nore\u00f1a",
    "sg:orig_category":"Conservas De Carnes (fabricaci\u00d3n, Al Por Mayor)",
    "sg:phone":"+34 985 74 02 76",
    "sg:postcode":"33180",
    "sg:province":"Asturias",
    "wof:name":"Productos Nore\u00f1enses S. L.",
    "wof:placetype":"venue"
},
  "geometry": {"coordinates":[-5.7020292282,43.4001083374],"type":"Point"}
}