{
  "type": "Feature",
  "properties": {
    "iso:country":"ES",
    "sg:address":"Carrer de Eduard Toda, 76",
    "sg:city":"Barcelona",
    "sg:orig_category":"Supermercados Y Hipermercados",
    "sg:phone":"+34 934 27 16 69",
    "sg:postcode":"08031",
    "sg:province":"Barcelona",
    "wof:name":"Rodriguez Sanchez Hortensia",
    "wof:placetype":"venue"
},
  "geometry": {"coordinates":[2.1559400558,41.4362602234],"type":"Point"}
}