{
  "type": "Feature",
  "properties": {
    "addr:full":"Calle de Cabestany, 5 Huesca Huesca 22005",
    "addr:housenumber":"5",
    "addr:postcode":"22005",
    "addr:street":"Calle De Cabestany",
    "iso:country":"ES",
    "sg:address":"Calle de Cabestany, 5",
    "sg:city":"Huesca",
    "sg:orig_category":"Reposter\u00cdas",
    "sg:phone":"+34 974 24 49 22",
    "sg:postcode":"22005",
    "sg:province":"Huesca",
    "wof:name":"Comercial Alto Aragonesa De Reposteria S.l.",
    "wof:placetype":"venue"
},
  "geometry": {"coordinates":[-0.4082624912,42.134262085],"type":"Point"}
}