{
  "type": "Feature",
  "properties": {
    "iso:country":"ES",
    "sg:address":"Carrer de Major, 109",
    "sg:city":"Manresa",
    "sg:orig_category":"Empresas De Limpieza",
    "sg:phone":"+34 938 77 40 88",
    "sg:postcode":"08242",
    "sg:province":"Barcelona",
    "wof:name":"Iglesias Chorro Maria Del Carmen",
    "wof:placetype":"venue"
},
  "geometry": {"coordinates":[1.8268239498,41.7340202332],"type":"Point"}
}