{
  "type": "Feature",
  "properties": {
    "addr:full":"Pla\u00c7 Ajuntament, 8 Igualada Barcelona 08700",
    "addr:housenumber":"8",
    "addr:postcode":"08700",
    "iso:country":"ES",
    "sg:address":"Pla\u00c7 Ajuntament, 8",
    "sg:city":"Igualada",
    "sg:orig_category":"Carnicer\u00cdas, Carnicer\u00cdas",
    "sg:phone":"+34 938 03 18 67",
    "sg:postcode":"08700",
    "sg:province":"Barcelona",
    "wof:name":"Iba\u00d1ez Domenech Maria",
    "wof:placetype":"venue"
},
  "geometry": {"coordinates":[1.6129490137,41.5849189758],"type":"Point"}
}