{
  "type": "Feature",
  "properties": {
    "addr:full":"Aingeru Guarda Pasealekua, 5 Eskoriatza Guip\u00f9zcoa 20540",
    "addr:housenumber":"5",
    "addr:postcode":"20540",
    "addr:street":"Aingeru Guarda Pasealekua;Guipu\u0300Zcoa",
    "iso:country":"ES",
    "sg:address":"Aingeru Guarda Pasealekua, 5",
    "sg:city":"Eskoriatza",
    "sg:orig_category":"Limpieza Con Chorro De Arena Y Con Granalla, Pulido",
    "sg:phone":"+34 943 71 47 31",
    "sg:postcode":"20540",
    "sg:province":"Guip\u00f9zcoa",
    "wof:name":"Pulimentos Txiki S.l.",
    "wof:placetype":"venue"
},
  "geometry": {"coordinates":[-2.5259990692,43.0180892944],"type":"Point"}
}