{
  "type": "Feature",
  "properties": {
    "iso:country":"ES",
    "sg:address":"Calle de Toledo, 53",
    "sg:city":"Madrid",
    "sg:orig_category":"Cl\u00cdnicas Dentales",
    "sg:phone":"+34 913 65 24 22",
    "sg:postcode":"28005",
    "sg:province":"Madrid",
    "wof:name":"Egabil Dental S.l.",
    "wof:placetype":"venue"
},
  "geometry": {"coordinates":[-3.7079861164,40.4115486145],"type":"Point"}
}