{
  "type": "Feature",
  "properties": {
    "iso:country":"ES",
    "sg:address":"Feira, 7",
    "sg:city":"Seijo",
    "sg:orig_category":"Tintes (fabricaci\u00d3n, Al Por Mayor)",
    "sg:phone":"+34 986 62 27 94",
    "sg:postcode":"36740",
    "sg:province":"Pontevedra",
    "wof:name":"Abalo Lubians Juan Francisco",
    "wof:placetype":"venue"
},
  "geometry": {"coordinates":[-8.744693,41.991955],"type":"Point"}
}