{
  "type": "Feature",
  "properties": {
    "iso:country":"ES",
    "sg:address":"Calle de Roteta, 7",
    "sg:city":"Donostia-san Sebastian",
    "sg:orig_category":"Vinos Y Licores (venta Al Por Menor)",
    "sg:phone":"+34 943 35 70 13",
    "sg:postcode":"20017",
    "sg:province":"Guip\u00f9zcoa",
    "wof:name":"Moreno Bueno Rafael",
    "wof:placetype":"venue"
},
  "geometry": {"coordinates":[-1.9313540459,43.3175964355],"type":"Point"}
}