{
  "type": "Feature",
  "properties": {
    "iso:country":"ES",
    "sg:address":"Carrer de Josep Pla, 163",
    "sg:city":"Barcelona",
    "sg:orig_category":"Fabricaci\u00d3n De Art\u00cdculos Y Equipos Deportivos Y De Ocio",
    "sg:phone":"+34 933 03 78 40",
    "sg:postcode":"08020",
    "sg:province":"Barcelona",
    "wof:name":"Asafe S.l.",
    "wof:placetype":"venue"
},
  "geometry": {"coordinates":[2.2071743011,41.415348053],"type":"Point"}
}