{
  "type": "Feature",
  "properties": {
    "iso:country":"ES",
    "sg:address":"Urb Alta Vista, S/n",
    "sg:city":"San Pedro Alcantara",
    "sg:orig_category":"Inmobiliaria (agencias)",
    "sg:phone":"+34 952 85 36 96",
    "sg:postcode":"29670",
    "sg:province":"M\u00e1laga",
    "wof:name":"Prosavi Promociones Y Explotaciones Inmobiliarias S.l.",
    "wof:placetype":"venue"
},
  "geometry": {"coordinates":[-5.003718853,36.4735946655],"type":"Point"}
}