{
  "type": "Feature",
  "properties": {
    "addr:full":"Calle de Perro Del, 2 Bilbao Vizcaya 48005",
    "addr:housenumber":"2",
    "addr:postcode":"48005",
    "addr:street":"Calle De Perro Del",
    "iso:country":"ES",
    "sg:address":"Calle de Perro Del, 2",
    "sg:city":"Bilbao",
    "sg:orig_category":"Restaurantes",
    "sg:phone":"+34 944 15 97 72",
    "sg:postcode":"48005",
    "sg:province":"Vizcaya",
    "wof:name":"Ruiz Bombin Santiago",
    "wof:placetype":"venue"
},
  "geometry": {"coordinates":[-2.9250349998,43.2576293945],"type":"Point"}
}