{
  "type": "Feature",
  "properties": {
    "addr:full":"Avda Doctor Meca, S/n Puerto Mazarron Murcia 30860",
    "addr:housenumber":"s / n",
    "addr:postcode":"30860",
    "addr:street":"Avda Doctor Meca",
    "iso:country":"ES",
    "sg:address":"Avda Doctor Meca, S/n",
    "sg:city":"Puerto Mazarron",
    "sg:orig_category":"Inmobiliaria (agencias)",
    "sg:phone":"+34 968 59 56 21",
    "sg:postcode":"30860",
    "sg:province":"Murcia",
    "wof:name":"Spanish Sunset Propiety Consultants",
    "wof:placetype":"venue"
},
  "geometry": {"coordinates":[-1.2648539543,37.5711860657],"type":"Point"}
}