{
  "type": "Feature",
  "properties": {
    "iso:country":"ES",
    "sg:address":"Ctra Pineda (de), 3",
    "sg:city":"Sevilla",
    "sg:orig_category":"Mercer\u00cda, Lencer\u00cda (al Por Menor)",
    "sg:phone":"+34 954 61 73 00",
    "sg:postcode":"41013",
    "sg:province":"Sevilla",
    "wof:name":"Morillo Sollero Isabel",
    "wof:placetype":"venue"
},
  "geometry": {"coordinates":[-5.9752588272,37.3515090942],"type":"Point"}
}