{
  "type": "Feature",
  "properties": {
    "addr:full":"Calle de Nu\u00d1ez De Balboa, 96 Madrid Madrid 28006",
    "addr:housenumber":"96",
    "addr:postcode":"madrid;28006",
    "addr:street":"Calle De Nun\u0303Ez De Balboa",
    "iso:country":"ES",
    "sg:address":"Calle de Nu\u00d1ez De Balboa, 96",
    "sg:city":"Madrid",
    "sg:orig_category":"Ropa Para Se\u00d1oras (al Por Menor)",
    "sg:phone":"+34 915 61 31 32",
    "sg:postcode":"28006",
    "sg:province":"Madrid",
    "wof:name":"Santos Rubio Maria Teresa",
    "wof:placetype":"venue"
},
  "geometry": {"coordinates":[-3.6818470955,40.4342346191],"type":"Point"}
}