{
  "type": "Feature",
  "properties": {
    "addr:full":"Ctra Carretera De Algemesi, 2 Alzira Valencia 46600",
    "addr:housenumber":"2",
    "addr:postcode":"46600",
    "addr:street":"Ctra Carretera De Algemesi",
    "iso:country":"ES",
    "sg:address":"Ctra Carretera De Algemesi, 2",
    "sg:city":"Alzira",
    "sg:orig_category":"Material Y Herramientas Agr\u00cdcolas",
    "sg:phone":"+34 962 41 78 24",
    "sg:postcode":"46600",
    "sg:province":"Valencia",
    "wof:name":"Inoxidables Y Mecanizados Bejasi S.a.",
    "wof:placetype":"venue"
},
  "geometry": {"coordinates":[-0.4412097037,39.1528320312],"type":"Point"}
}