{
  "type": "Feature",
  "properties": {
    "addr:full":"Calle de Mercedes (las), 25 Arenas -areeta Vizcaya 48930",
    "addr:housenumber":"25;areeta",
    "addr:postcode":"48930",
    "addr:street":"Calle De Mercedes Las",
    "iso:country":"ES",
    "sg:address":"Calle de Mercedes (las), 25",
    "sg:city":"Arenas -areeta",
    "sg:orig_category":"Venta, Instalaci\u00d3n De Calefacci\u00d3n",
    "sg:phone":"+34 944 80 06 62",
    "sg:postcode":"48930",
    "sg:province":"Vizcaya",
    "wof:name":"Articulos Domestico-industriales Calefaccion S.l.",
    "wof:placetype":"venue"
},
  "geometry": {"coordinates":[-3.0149412155,43.3260879517],"type":"Point"}
}