{
  "type": "Feature",
  "properties": {
    "addr:full":"Bard C.r. Maria Auxiliadora, 23 Chiclana De La Frontera C\u00e1diz 11130",
    "addr:housenumber":"23",
    "addr:postcode":"11130",
    "addr:street":"Bard C.R. Maria Auxiliadora",
    "iso:country":"ES",
    "sg:address":"Bard C.r. Maria Auxiliadora, 23",
    "sg:city":"Chiclana De La Frontera",
    "sg:orig_category":"Iglesia Cat\u00d3lica",
    "sg:phone":"+34 956 40 62 26",
    "sg:postcode":"11130",
    "sg:province":"C\u00e1diz",
    "wof:name":"Parroquia De San Antonio",
    "wof:placetype":"venue"
},
  "geometry": {"coordinates":[-6.1447038651,36.4212188721],"type":"Point"}
}