{
  "type": "Feature",
  "properties": {
    "addr:full":"Av Pavos (els), 8 Blanes Girona 17300",
    "addr:housenumber":"8",
    "addr:postcode":"17300",
    "addr:street":"Av Pavos Els",
    "iso:country":"ES",
    "sg:address":"Av Pavos (els), 8",
    "sg:city":"Blanes",
    "sg:orig_category":"Frutas Y Legumbres Frescas (al Por Mayor)",
    "sg:phone":"+34 972 33 85 44",
    "sg:postcode":"17300",
    "sg:province":"Girona",
    "wof:name":"Frutas Jordi Gasol S.l.",
    "wof:placetype":"venue"
},
  "geometry": {"coordinates":[2.7836201191,41.677406311],"type":"Point"}
}