{
  "type": "Feature",
  "properties": {
    "addr:full":"Calle de Condesa Vega Del Pozo, 8 Madrid Madrid 28032",
    "addr:housenumber":"8",
    "addr:postcode":"madrid;28032",
    "addr:street":"Calle De Condesa Vega Del Pozo",
    "iso:country":"ES",
    "sg:address":"Calle de Condesa Vega Del Pozo, 8",
    "sg:city":"Madrid",
    "sg:orig_category":"Inmobiliaria (agencias)",
    "sg:phone":"+34 913 71 97 86",
    "sg:postcode":"28032",
    "sg:province":"Madrid",
    "wof:name":"Boreal Intermediacion S.l.",
    "wof:placetype":"venue"
},
  "geometry": {"coordinates":[-3.6079618931,40.4034919739],"type":"Point"}
}