{
  "type": "Feature",
  "properties": {
    "iso:country":"ES",
    "sg:address":"Av Pas D'arro, 38",
    "sg:city":"Vielha",
    "sg:orig_category":"Hoteles",
    "sg:phone":"+34 973 64 02 00",
    "sg:postcode":"25530",
    "sg:province":"Lleida",
    "wof:name":"Aran Viola Enriqueta",
    "wof:placetype":"venue"
},
  "geometry": {"coordinates":[0.7984170914,42.700378418],"type":"Point"}
}