{
  "type": "Feature",
  "properties": {
    "iso:country":"ES",
    "sg:address":"Calle de Germanies, 47",
    "sg:city":"Torrent",
    "sg:orig_category":"Arreglo, Reparaci\u00d3n, Piezas Sueltas De Televisi\u00d3n, V\u00cddeo, Hi",
    "sg:phone":"+34 961 55 53 15",
    "sg:postcode":"46900",
    "sg:province":"Valencia",
    "wof:name":"Cruz Fernandez Pascual",
    "wof:placetype":"venue"
},
  "geometry": {"coordinates":[-0.4728110135,39.4333953857],"type":"Point"}
}