{
  "type": "Feature",
  "properties": {
    "iso:country":"ES",
    "sg:address":"Calle de Emilio Castelar, 36",
    "sg:city":"Algeciras",
    "sg:orig_category":"M\u00c9dicos: Estomatolog\u00cda",
    "sg:phone":"+34 956 63 25 55",
    "sg:postcode":"11201",
    "sg:province":"C\u00e1diz",
    "wof:name":"Minguez Ma\u00f1anes Jose Javier",
    "wof:placetype":"venue"
},
  "geometry": {"coordinates":[-5.4478058815,36.1287384033],"type":"Point"}
}