{
  "type": "Feature",
  "properties": {
    "addr:full":"Carrer de Argullos, 89 Barcelona Barcelona 08016",
    "addr:housenumber":"89",
    "addr:postcode":"08016",
    "addr:street":"Carrer De Argullos",
    "iso:country":"ES",
    "sg:address":"Carrer de Argullos, 89",
    "sg:city":"Barcelona",
    "sg:orig_category":"Loter\u00cda Y T\u00d3mbola",
    "sg:phone":"+34 932 76 09 80",
    "sg:postcode":"08016",
    "sg:province":"Barcelona",
    "wof:name":"Torres Moreno Dolores",
    "wof:placetype":"venue"
},
  "geometry": {"coordinates":[2.1813089848,41.4418182373],"type":"Point"}
}