{
  "type": "Feature",
  "properties": {
    "addr:full":"Calle de Diego De Urbina, 4 Alcala Henares Madrid 28805",
    "addr:housenumber":"4",
    "addr:postcode":"28805",
    "addr:street":"Calle De Diego De Urbina",
    "iso:country":"ES",
    "sg:address":"Calle de Diego De Urbina, 4",
    "sg:city":"Alcala Henares",
    "sg:orig_category":"Ropa Para Se\u00d1oras Y Caballeros (al Por Menor)",
    "sg:phone":"+34 918 89 08 43",
    "sg:postcode":"28805",
    "sg:province":"Madrid",
    "wof:name":"Diaz Diaz Juan",
    "wof:placetype":"venue"
},
  "geometry": {"coordinates":[-3.3556654453,40.4868965149],"type":"Point"}
}