{
  "type": "Feature",
  "properties": {
    "iso:country":"ES",
    "sg:address":"Calle de Conde Real Agrado, 1",
    "sg:city":"Gijon",
    "sg:orig_category":"Asilos De Ancianos. Centros Privados",
    "sg:phone":"+34 985 33 54 06",
    "sg:postcode":"33205",
    "sg:province":"Asturias",
    "wof:name":"Residencial Zarracina S.l.",
    "wof:placetype":"venue"
},
  "geometry": {"coordinates":[-5.6568922997,43.5370063782],"type":"Point"}
}