{
  "type": "Feature",
  "properties": {
    "addr:full":"Plaz Gernikako Arbola, 1 Urretxu Guip\u00f9zcoa 20700",
    "addr:housenumber":"1",
    "addr:postcode":"20700",
    "addr:street":"Plaz Gernikako Arbola;Guipu\u0300Zcoa",
    "iso:country":"ES",
    "sg:address":"Plaz Gernikako Arbola, 1",
    "sg:city":"Urretxu",
    "sg:classifiers":[
        {
            "category":"Autos & Motor Vehicles",
            "subcategory":"Automobile Sales",
            "type":"Retail Goods"
        }
    ],
    "sg:phone":"+34 943 03 64 63",
    "sg:postcode":"20700",
    "sg:province":"Guip\u00f9zcoa",
    "wof:name":"Urretxindorra, S.l.",
    "wof:placetype":"venue"
},
  "geometry": {"coordinates":[-2.3144009113,43.092010498],"type":"Point"}
}