{
  "type": "Feature",
  "properties": {
    "addr:full":"Av Catalunya, 20 Segur Calafell Tarragona 43882",
    "addr:housenumber":"20",
    "addr:postcode":"43882",
    "addr:street":"Av Catalunya",
    "iso:country":"ES",
    "sg:address":"Av Catalunya, 20",
    "sg:city":"Segur Calafell",
    "sg:orig_category":"Ingeniero",
    "sg:phone":"+34 977 67 36 29",
    "sg:postcode":"43882",
    "sg:province":"Tarragona",
    "wof:name":"Xammar Ferrer Jose Luis De",
    "wof:placetype":"venue"
},
  "geometry": {"coordinates":[1.6054645777,41.1950340271],"type":"Point"}
}