{
  "type": "Feature",
  "properties": {
    "addr:full":"Calle de Pio Loperena, 26 Burlada Navarra 31600",
    "addr:housenumber":"26",
    "addr:postcode":"31600",
    "addr:street":"Calle De Pio Loperena",
    "iso:country":"ES",
    "sg:address":"Calle de Pio Loperena, 26",
    "sg:city":"Burlada",
    "sg:orig_category":"Florister\u00cdas",
    "sg:phone":"+34 948 23 88 39",
    "sg:postcode":"31600",
    "sg:province":"Navarra",
    "wof:name":"Ascension Y Margarita Garralda S.c.i.",
    "wof:placetype":"venue"
},
  "geometry": {"coordinates":[-1.6152230501,42.8230171204],"type":"Point"}
}