{
  "type": "Feature",
  "properties": {
    "iso:country":"ES",
    "sg:address":"Avda Carlos V, 2",
    "sg:city":"Carrizal",
    "sg:orig_category":"Farmacias",
    "sg:phone":"+34 928 78 06 30",
    "sg:postcode":"35240",
    "sg:province":"Las Palmas",
    "wof:name":"Megias Martin Monica Inmaculada",
    "wof:placetype":"venue"
},
  "geometry": {"coordinates":[-15.4078788757,27.9093894958],"type":"Point"}
}