{
  "type": "Feature",
  "properties": {
    "addr:full":"Cra Capuchinos, 62 Malaga M\u00e1laga 29014",
    "addr:housenumber":"62",
    "addr:postcode":"29014",
    "addr:street":"Capuchinos;Ma\u0301Laga",
    "iso:country":"ES",
    "sg:address":"Cra Capuchinos, 62",
    "sg:city":"Malaga",
    "sg:orig_category":"Comercio De Piezas De Recambio Y De Accesorios De Veh\u00cdculos, Veh\u00cdculos Industriales",
    "sg:phone":"+34 952 25 11 41",
    "sg:postcode":"29014",
    "sg:province":"M\u00e1laga",
    "wof:name":"Autorecambios Oni S.l.",
    "wof:placetype":"venue"
},
  "geometry": {"coordinates":[-4.423210144,36.765007019],"type":"Point"}
}