{
  "type": "Feature",
  "properties": {
    "iso:country":"ES",
    "sg:address":"Carrer de Rin, 13",
    "sg:city":"Segur Calafell",
    "sg:orig_category":"Caf\u00c9s, Bares, Cervecer\u00cdas",
    "sg:phone":"+34 977 16 44 49",
    "sg:postcode":"43882",
    "sg:province":"Tarragona",
    "wof:name":"Trepat Vila Ramon",
    "wof:placetype":"venue"
},
  "geometry": {"coordinates":[1.604344964,41.1909370422],"type":"Point"}
}