{
  "type": "Feature",
  "properties": {
    "addr:full":"Cuartel, 4 Candeleda \u00c1vila 05480",
    "addr:housenumber":"4",
    "addr:postcode":"05480",
    "addr:street":"Cuartel",
    "iso:country":"ES",
    "sg:address":"Cuartel, 4",
    "sg:city":"Candeleda",
    "sg:orig_category":"Supermercados Y Hipermercados",
    "sg:phone":"+34 920 38 23 09",
    "sg:postcode":"05480",
    "sg:province":"\u00c1vila",
    "wof:name":"Union Almanzor S.l.",
    "wof:placetype":"venue"
},
  "geometry": {"coordinates":[-5.240790844,40.1553764343],"type":"Point"}
}