{
  "type": "Feature",
  "properties": {
    "addr:full":"Avda Escaleritas, 130 Palmas De Gran Canaria Las Palmas 35011",
    "addr:housenumber":"130",
    "addr:postcode":"35011",
    "addr:street":"Avda Escaleritas",
    "iso:country":"ES",
    "sg:address":"Avda Escaleritas, 130",
    "sg:city":"Palmas De Gran Canaria",
    "sg:orig_category":"Agencias Y Agentes Comerciales, Representantes",
    "sg:phone":"+34 928 20 46 76",
    "sg:postcode":"35011",
    "sg:province":"Las Palmas",
    "wof:name":"Miralles Morales Bernardo",
    "wof:placetype":"venue"
},
  "geometry": {"coordinates":[-15.4404172897,28.1066856384],"type":"Point"}
}