{
  "type": "Feature",
  "properties": {
    "iso:country":"ES",
    "sg:address":"Calle de Francisco Javier Martin Abril, 3",
    "sg:city":"Valladolid",
    "sg:orig_category":"Formaci\u00d3n Continuada (variada)",
    "sg:phone":"+34 983 30 57 82",
    "sg:postcode":"47002",
    "sg:province":"Valladolid",
    "wof:name":"Val Redondo Jaime Del",
    "wof:placetype":"venue"
},
  "geometry": {"coordinates":[-4.7218298912,41.6507911682],"type":"Point"}
}