{
  "type": "Feature",
  "properties": {
    "addr:full":"Carrer de Enric Prat De La Riba, 240 Hospitalet Llobregat Barcelona 08901",
    "addr:housenumber":"240",
    "addr:postcode":"08901",
    "addr:street":"Carrer De Enric Prat De La Riba",
    "iso:country":"ES",
    "sg:address":"Carrer de Enric Prat De La Riba, 240",
    "sg:city":"Hospitalet Llobregat",
    "sg:orig_category":"Droguer\u00cdas (al Por Menor)",
    "sg:phone":"+34 933 38 98 38",
    "sg:postcode":"08901",
    "sg:province":"Barcelona",
    "wof:name":"Lorenzo Gomez Maria Elena",
    "wof:placetype":"venue"
},
  "geometry": {"coordinates":[2.1040248871,41.3605461121],"type":"Point"}
}