{
  "type": "Feature",
  "properties": {
    "iso:country":"ES",
    "sg:address":"Calle de Jesus, 82",
    "sg:city":"Fuente Cantos",
    "sg:orig_category":"Ense\u00d1anza, Formaci\u00d3n Profesional: Aprendizaje",
    "sg:phone":"+34 924 50 10 26",
    "sg:postcode":"06240",
    "sg:province":"Badajoz",
    "wof:name":"Registro De La Propiedad",
    "wof:placetype":"venue"
},
  "geometry": {"coordinates":[-6.3020091057,38.246509552],"type":"Point"}
}