{
  "type": "Feature",
  "properties": {
    "iso:country":"ES",
    "sg:address":"Carr Mn. Cinto Verdaguer, 2",
    "sg:city":"Hostalric",
    "sg:orig_category":"Electrodom\u00c9sticos (al Por Menor)",
    "sg:phone":"+34 972 86 52 54",
    "sg:postcode":"17450",
    "sg:province":"Girona",
    "wof:name":"Lozano Vizcaya Victor",
    "wof:placetype":"venue"
},
  "geometry": {"coordinates":[2.6260728836,41.7446250916],"type":"Point"}
}