{
  "type": "Feature",
  "properties": {
    "iso:country":"ES",
    "sg:address":"Calle de Extramuros, 16",
    "sg:city":"Piedrahita",
    "sg:orig_category":"Transporte En General",
    "sg:phone":"+34 920 36 02 32",
    "sg:postcode":"05500",
    "sg:province":"\u00c1vila",
    "wof:name":"Lopez Avezuela Santiago",
    "wof:placetype":"venue"
},
  "geometry": {"coordinates":[-5.3262438774,40.4658622742],"type":"Point"}
}