{
  "type": "Feature",
  "properties": {
    "iso:country":"ES",
    "sg:address":"Carr Escolapis, 30",
    "sg:city":"Vilanova I La Geltru",
    "sg:orig_category":"Ense\u00d1anza: Profesiones Art\u00cdsticas",
    "sg:phone":"+34 938 14 31 69",
    "sg:postcode":"08800",
    "sg:province":"Barcelona",
    "wof:name":"Tracart S.c.p",
    "wof:placetype":"venue"
},
  "geometry": {"coordinates":[1.7263799906,41.2223892212],"type":"Point"}
}