{
  "type": "Feature",
  "properties": {
    "addr:full":"Av Canal, 180 Prat Llobregat Barcelona 08820",
    "addr:housenumber":"180",
    "addr:postcode":"08820",
    "addr:street":"Av Canal;Llobregat",
    "iso:country":"ES",
    "sg:address":"Av Canal, 180",
    "sg:city":"Prat Llobregat",
    "sg:orig_category":"Muebles, Minoristas",
    "sg:phone":"+34 933 79 19 98",
    "sg:postcode":"08820",
    "sg:province":"Barcelona",
    "wof:name":"Cersa Mobles S.a.",
    "wof:placetype":"venue"
},
  "geometry": {"coordinates":[2.092772007,41.3239555359],"type":"Point"}
}