{
  "type": "Feature",
  "properties": {
    "iso:country":"ES",
    "sg:address":"Calle de Jardines De Lisboa, 22",
    "sg:city":"Zaragoza",
    "sg:orig_category":"Peluqueros: De Se\u00d1oras",
    "sg:phone":"+34 976 28 52 94",
    "sg:postcode":"50003",
    "sg:province":"Zaragoza",
    "wof:name":"Gistas Albalate Marta",
    "wof:placetype":"venue"
},
  "geometry": {"coordinates":[-0.9055989981,41.6602249146],"type":"Point"}
}