{
  "type": "Feature",
  "properties": {
    "iso:country":"ES",
    "sg:address":"Cno Vjo De Albal A Carcer, S/n",
    "sg:city":"Beniparrell",
    "sg:orig_category":"Muebles, Minoristas",
    "sg:phone":"+34 961 20 08 14",
    "sg:postcode":"46469",
    "sg:province":"Valencia",
    "wof:name":"L'aldana Wood S.l.",
    "wof:placetype":"venue"
},
  "geometry": {"coordinates":[-0.4116789997,39.383228302],"type":"Point"}
}