{
  "type": "Feature",
  "properties": {
    "iso:country":"ES",
    "sg:address":"Calle de Virgen Del Carmen, 60",
    "sg:city":"Donostia-san Sebastian",
    "sg:orig_category":"Asociaciones, Organismos Culturales Y Socioeducativos",
    "sg:phone":"+34 943 32 21 97",
    "sg:postcode":"20012",
    "sg:province":"Guip\u00f9zcoa",
    "wof:name":"Ttan-ttakun Aisialdiko Gazte Elkartea",
    "wof:placetype":"venue"
},
  "geometry": {"coordinates":[-1.9664779902,43.3187675476],"type":"Point"}
}