{
  "type": "Feature",
  "properties": {
    "addr:full":"Avda Ordo\u00d1o Ii, 30 Le\u00f3n Le\u00f3n 24001",
    "addr:housenumber":"30",
    "addr:postcode":"24001",
    "addr:street":"Avda Ordon\u0303O Ii;Leo\u0301N",
    "iso:country":"ES",
    "sg:address":"Avda Ordo\u00d1o Ii, 30",
    "sg:city":"Le\u00f3n",
    "sg:orig_category":"Peluqueros: De Se\u00d1oras",
    "sg:phone":"+34 987 22 01 00",
    "sg:postcode":"24001",
    "sg:province":"Le\u00f3n",
    "wof:name":"Gonzalez Casado Maria Consily",
    "wof:placetype":"venue"
},
  "geometry": {"coordinates":[-5.577067852,42.5966720581],"type":"Point"}
}