{
  "type": "Feature",
  "properties": {
    "iso:country":"ES",
    "sg:address":"Poli Pol.indust. Cami Dels Frares, S/n",
    "sg:city":"Lleida",
    "sg:orig_category":"Quincaller\u00cda (al Por Menor)",
    "sg:phone":"+34 973 24 77 00",
    "sg:postcode":"25191",
    "sg:province":"Lleida",
    "wof:name":"Martinez Poyatos Juan",
    "wof:placetype":"venue"
},
  "geometry": {"coordinates":[0.6831650138,41.5832138062],"type":"Point"}
}