{
  "type": "Feature",
  "properties": {
    "addr:full":"Cami Sant Jeroni De Murtra, 38 Badalona Barcelona 08917",
    "addr:housenumber":"38",
    "addr:postcode":"08917",
    "addr:street":"Sant",
    "iso:country":"ES",
    "sg:address":"Cami Sant Jeroni De Murtra, 38",
    "sg:city":"Badalona",
    "sg:orig_category":"Cl\u00cdnicas Psiqui\u00c1tricas",
    "sg:phone":"+34 933 95 67 05",
    "sg:postcode":"08917",
    "sg:province":"Barcelona",
    "wof:name":"Associacio Civica D'ajuda Mutua",
    "wof:placetype":"venue"
},
  "geometry": {"coordinates":[2.2313380241,41.4580879211],"type":"Point"}
}