{
  "type": "Feature",
  "properties": {
    "addr:full":"Calle de Tiradores Bajos A, 25 Cuenca Cuenca 16001",
    "addr:housenumber":"25",
    "addr:postcode":"16001",
    "addr:street":"Calle De Tiradores;A",
    "iso:country":"ES",
    "sg:address":"Calle de Tiradores Bajos A, 25",
    "sg:city":"Cuenca",
    "sg:orig_category":"M\u00c1quinas De Escribir, M\u00c1quinas De Oficina (al Por Menor, Reparaci\u00d3n)",
    "sg:phone":"+34 969 21 45 24",
    "sg:postcode":"16001",
    "sg:province":"Cuenca",
    "wof:name":"Durango Martinez Francisco",
    "wof:placetype":"venue"
},
  "geometry": {"coordinates":[-2.1305370331,40.0736885071],"type":"Point"}
}