{
  "type": "Feature",
  "properties": {
    "iso:country":"ES",
    "sg:address":"Carrer de Trafalgar (de), 33",
    "sg:city":"Tarragona",
    "sg:orig_category":"Hielo Artificial (fabricaci\u00d3n, Distribuci\u00d3n)",
    "sg:phone":"+34 977 24 44 07",
    "sg:postcode":"43004",
    "sg:province":"Tarragona",
    "wof:name":"Olivier Olivier Rafael",
    "wof:placetype":"venue"
},
  "geometry": {"coordinates":[1.2411990166,41.1096534729],"type":"Point"}
}