{
  "type": "Feature",
  "properties": {
    "iso:country":"ES",
    "sg:address":"Cmno Callejones (de Los), S/n",
    "sg:city":"Santaella",
    "sg:orig_category":"Frutos Y Legumbres",
    "sg:phone":"+34 957 31 40 61",
    "sg:postcode":"14546",
    "sg:province":"C\u00f3rdoba",
    "wof:name":"Arcadio Sanchez E Hijos S.l.",
    "wof:placetype":"venue"
},
  "geometry": {"coordinates":[-4.8526129723,37.5647506714],"type":"Point"}
}