{
  "type": "Feature",
  "properties": {
    "addr:full":"Aveni Madre Paula Montalt, 21 Dos Hermanas Sevilla 41089",
    "addr:housenumber":"21",
    "addr:postcode":"41089",
    "addr:street":"Montalt",
    "iso:country":"ES",
    "sg:address":"Aveni Madre Paula Montalt, 21",
    "sg:city":"Dos Hermanas",
    "sg:orig_category":"Transportes Por Carretera: Lotes Completos, Mercanc\u00cdas Diversas",
    "sg:phone":"+34 954 12 06 63",
    "sg:postcode":"41089",
    "sg:province":"Sevilla",
    "wof:name":"Casado Fernandez Jose Antonio",
    "wof:placetype":"venue"
},
  "geometry": {"coordinates":[-5.9278612137,37.3393440247],"type":"Point"}
}