{
  "type": "Feature",
  "properties": {
    "iso:country":"ES",
    "sg:address":"Carrer de Juan De La Cierva, 52",
    "sg:city":"Romanica",
    "sg:orig_category":"M\u00c1quinas, Material Y Suministros Para Cajas Y Embalajes",
    "sg:phone":"+34 937 18 38 13",
    "sg:postcode":"08210",
    "sg:province":"Barcelona",
    "wof:name":"Maquinaria De Envase Y Embalaje Paris S.a.",
    "wof:placetype":"venue"
},
  "geometry": {"coordinates":[2.133728981,41.5171012878],"type":"Point"}
}