{
  "type": "Feature",
  "properties": {
    "addr:full":"Rua Macal, 92 Carneiras Pontevedra 36213",
    "addr:housenumber":"92",
    "addr:postcode":"36213",
    "addr:street":"Rua Macal",
    "iso:country":"ES",
    "sg:address":"Rua Macal, 92",
    "sg:city":"Carneiras",
    "sg:orig_category":"Farmacias",
    "sg:phone":"+34 986 20 53 25",
    "sg:postcode":"36213",
    "sg:province":"Pontevedra",
    "wof:name":"Preciado Barrera Maria Concepcion",
    "wof:placetype":"venue"
},
  "geometry": {"coordinates":[-8.7210121155,42.1948318481],"type":"Point"}
}