{
  "type": "Feature",
  "properties": {
    "iso:country":"ES",
    "sg:address":"C. Atalaya, 1",
    "sg:city":"Minas Riotinto",
    "sg:orig_category":"Promotores Constructores",
    "sg:phone":"+34 959 59 03 38",
    "sg:postcode":"21660",
    "sg:province":"Huelva",
    "wof:name":"Geotexan S.a",
    "wof:placetype":"venue"
},
  "geometry": {"coordinates":[-6.5947198868,37.6976127625],"type":"Point"}
}