{
  "type": "Feature",
  "properties": {
    "iso:country":"ES",
    "sg:address":"Ptge Josep Ros, 2",
    "sg:city":"Martorell",
    "sg:orig_category":"Laboratorios Y Trabajos De Fotograf\u00cda, V\u00cddeo Y Cine",
    "sg:phone":"+34 937 74 33 60",
    "sg:postcode":"08760",
    "sg:province":"Barcelona",
    "wof:name":"Montes Perez Montserrat",
    "wof:placetype":"venue"
},
  "geometry": {"coordinates":[1.9141490459,41.4772033691],"type":"Point"}
}