{
  "type": "Feature",
  "properties": {
    "addr:full":"Calle de San Fernando, 20 Madrid Madrid 28032",
    "addr:housenumber":"20",
    "addr:postcode":"madrid;28032",
    "addr:street":"Calle De San Fernando",
    "iso:country":"ES",
    "sg:address":"Calle de San Fernando, 20",
    "sg:city":"Madrid",
    "sg:orig_category":"Empresas De Carpinter\u00cda",
    "sg:phone":"+34 917 76 49 24",
    "sg:postcode":"28032",
    "sg:province":"Madrid",
    "wof:name":"Del Valle Raez Manuel",
    "wof:placetype":"venue"
},
  "geometry": {"coordinates":[-3.6073439121,40.4040794373],"type":"Point"}
}