{
  "type": "Feature",
  "properties": {
    "addr:full":"Calle de Dama De Elche, 7 Valencia Valencia 46023",
    "addr:housenumber":"7",
    "addr:postcode":"46023",
    "addr:street":"Calle De Dama De Elche",
    "iso:country":"ES",
    "sg:address":"Calle de Dama De Elche, 7",
    "sg:city":"Valencia",
    "sg:orig_category":"Electricidad, Electr\u00d3nica: Suministros (al Por Menor)",
    "sg:phone":"+34 963 30 21 93",
    "sg:postcode":"46023",
    "sg:province":"Valencia",
    "wof:name":"Montreal Import S.l.",
    "wof:placetype":"venue"
},
  "geometry": {"coordinates":[-0.3429653049,39.4624786377],"type":"Point"}
}