{
  "type": "Feature",
  "properties": {
    "addr:full":"Avda Burgos, 58 Logro\u00f1o La Rioja 26006",
    "addr:housenumber":"58",
    "addr:postcode":"26006",
    "addr:street":"Avda Burgos;Rioja",
    "iso:country":"ES",
    "sg:address":"Avda Burgos, 58",
    "sg:city":"Logro\u00f1o",
    "sg:orig_category":"Asesor\u00cda Sobre Comunicaci\u00d3n De Empresas",
    "sg:phone":"+34 941 20 69 94",
    "sg:postcode":"26006",
    "sg:province":"La Rioja",
    "wof:name":"Proyectos Asesoria Y Servicios S.a.",
    "wof:placetype":"venue"
},
  "geometry": {"coordinates":[-2.4712779522,42.461391449],"type":"Point"}
}