{
  "type": "Feature",
  "properties": {
    "addr:full":"Avgd Pais Valencia, 22 Muro Alcoy Alicante 03830",
    "addr:housenumber":"22",
    "addr:postcode":"03830",
    "addr:street":"Valencia",
    "iso:country":"ES",
    "sg:address":"Avgd Pais Valencia, 22",
    "sg:city":"Muro Alcoy",
    "sg:orig_category":"Quincaller\u00cda (al Por Menor)",
    "sg:phone":"+34 965 53 01 27",
    "sg:postcode":"03830",
    "sg:province":"Alicante",
    "wof:name":"Segui Ferrandiz Constantino",
    "wof:placetype":"venue"
},
  "geometry": {"coordinates":[-0.4414289892,38.7812538147],"type":"Point"}
}