{
  "type": "Feature",
  "properties": {
    "iso:country":"ES",
    "sg:address":"Calle de Estrella, 17",
    "sg:city":"Madrid",
    "sg:orig_category":"Peleter\u00cdas",
    "sg:phone":"+34 915 31 58 55",
    "sg:postcode":"28004",
    "sg:province":"Madrid",
    "wof:name":"Peleterias Jacinto Rodriguez S.a.",
    "wof:placetype":"venue"
},
  "geometry": {"coordinates":[-3.7072520256,40.4223442078],"type":"Point"}
}