{
  "type": "Feature",
  "properties": {
    "addr:full":"Avda Blasco Iba\u00d1ez, 75 Valencia Valencia 46021",
    "addr:housenumber":"75",
    "addr:postcode":"46021",
    "addr:street":"Avda Blasco Iban\u0303Ez",
    "iso:country":"ES",
    "sg:address":"Avda Blasco Iba\u00d1ez, 75",
    "sg:city":"Valencia",
    "sg:orig_category":"Promotores Constructores",
    "sg:phone":"+34 963 69 32 38",
    "sg:postcode":"46021",
    "sg:province":"Valencia",
    "wof:name":"Font Belenguer Vicente",
    "wof:placetype":"venue"
},
  "geometry": {"coordinates":[-0.3487229943,39.4748153687],"type":"Point"}
}