{
  "type": "Feature",
  "properties": {
    "iso:country":"ES",
    "sg:address":"Calle de Doctor Arruga, 3",
    "sg:city":"Sevilla",
    "sg:orig_category":"Promotores Constructores",
    "sg:phone":"+34 954 53 87 84",
    "sg:postcode":"41008",
    "sg:province":"Sevilla",
    "wof:name":"Pinto Gomez Lorenzo",
    "wof:placetype":"venue"
},
  "geometry": {"coordinates":[-5.9781117439,37.3952407837],"type":"Point"}
}