{
  "type": "Feature",
  "properties": {
    "iso:country":"ES",
    "sg:address":"Barr Vallin, S/n",
    "sg:city":"Grullos",
    "sg:orig_category":"Iglesia Cat\u00d3lica",
    "sg:phone":"+34 985 82 80 55",
    "sg:postcode":"33829",
    "sg:province":"Asturias",
    "wof:name":"Diocesis De Oviedo",
    "wof:placetype":"venue"
},
  "geometry": {"coordinates":[-6.0617032051,43.4346122742],"type":"Point"}
}