{
  "type": "Feature",
  "properties": {
    "addr:full":"Calle de Primero De Mayo, 6 Castrillon Asturias 33450",
    "addr:housenumber":"6",
    "addr:postcode":"33450",
    "addr:street":"Calle De Primero;Mayo;Asturias",
    "iso:country":"ES",
    "sg:address":"Calle de Primero De Mayo, 6",
    "sg:city":"Castrillon",
    "sg:orig_category":"Peluqueros: De Se\u00d1oras",
    "sg:phone":"+34 985 53 06 57",
    "sg:postcode":"33450",
    "sg:province":"Asturias",
    "wof:name":"M\u00aa Delfina Vega Menendez",
    "wof:placetype":"venue"
},
  "geometry": {"coordinates":[-5.9743847847,43.5619316101],"type":"Point"}
}