{
  "type": "Feature",
  "properties": {
    "addr:full":"Carrer de Setze De Juliol, 30 Poligon Industrial De Son Castello Islas Baleares 07009",
    "addr:housenumber":"30",
    "addr:postcode":"07009",
    "addr:street":"Carrer De Setze De Juliol;Islas",
    "iso:country":"ES",
    "sg:address":"Carrer de Setze De Juliol, 30",
    "sg:city":"Poligon Industrial De Son Castello",
    "sg:orig_category":"Comercio De Mobiliario De Oficina",
    "sg:phone":"+34 971 43 02 56",
    "sg:postcode":"07009",
    "sg:province":"Islas Baleares",
    "wof:name":"Instalaciones Comerciales Bagur S.a.",
    "wof:placetype":"venue"
},
  "geometry": {"coordinates":[2.6741399765,39.6011390686],"type":"Point"}
}