{
  "type": "Feature",
  "properties": {
    "iso:country":"ES",
    "sg:address":"Calle de Real, 55",
    "sg:city":"Torrenueva",
    "sg:orig_category":"Carnes De Carnicer\u00cda (al Por Mayor)",
    "sg:phone":"+34 926 34 47 20",
    "sg:postcode":"13740",
    "sg:province":"Ciudad Real",
    "wof:name":"Encarfre S.l.",
    "wof:placetype":"venue"
},
  "geometry": {"coordinates":[-3.3647589684,38.6421852112],"type":"Point"}
}