{
  "type": "Feature",
  "properties": {
    "iso:country":"ES",
    "sg:address":"Avda Pablo Iglesias, 4",
    "sg:city":"Madrid",
    "sg:orig_category":"Agencias Y Agentes Comerciales, Representantes",
    "sg:phone":"+34 915 33 17 71",
    "sg:postcode":"28003",
    "sg:province":"Madrid",
    "wof:name":"Talaverano Barranquero Mariano",
    "wof:placetype":"venue"
},
  "geometry": {"coordinates":[-3.7055220604,40.443572998],"type":"Point"}
}