{
  "type": "Feature",
  "properties": {
    "addr:full":"Pintor Nicolau, 27 Los Narejos Murcia 30710",
    "addr:housenumber":"27",
    "addr:postcode":"30710",
    "addr:street":"Pintor Nicolau;Los Narejos",
    "iso:country":"ES",
    "sg:address":"Pintor Nicolau, 27",
    "sg:city":"Los Narejos",
    "sg:orig_category":"Int\u00c9rpretes",
    "sg:phone":"+34 968 58 24 78",
    "sg:postcode":"30710",
    "sg:province":"Murcia",
    "wof:name":"El Ouardy  Hanan",
    "wof:placetype":"venue"
},
  "geometry": {"coordinates":[-0.8319429755,37.7605133057],"type":"Point"}
}