{
  "type": "Feature",
  "properties": {
    "iso:country":"ES",
    "sg:address":"Rbla Marina, 429",
    "sg:city":"Hospitalet Llobregat",
    "sg:orig_category":"Institutos M\u00c9dicos",
    "sg:phone":"+34 933 38 37 70",
    "sg:postcode":"08901",
    "sg:province":"Barcelona",
    "wof:name":"Amex S.a.",
    "wof:placetype":"venue"
},
  "geometry": {"coordinates":[2.1021962166,41.3588600159],"type":"Point"}
}