{
  "type": "Feature",
  "properties": {
    "iso:country":"ES",
    "sg:address":"Avda Rioseco, 10",
    "sg:city":"Pola De Laviana",
    "sg:orig_category":"Centros Empresariales",
    "sg:phone":"+34 985 60 00 08",
    "sg:postcode":"33980",
    "sg:province":"Asturias",
    "wof:name":"Gonzalez Begega Jose Manuel",
    "wof:placetype":"venue"
},
  "geometry": {"coordinates":[-5.5561637878,43.2384262085],"type":"Point"}
}