{
  "type": "Feature",
  "properties": {
    "iso:country":"ES",
    "sg:address":"Calle de Aita Donostia, 16",
    "sg:city":"Errenteria",
    "sg:orig_category":"Carnicer\u00cdas, Carnicer\u00cdas",
    "sg:phone":"+34 943 51 70 88",
    "sg:postcode":"20100",
    "sg:province":"Guip\u00f9zcoa",
    "wof:name":"Martin Balerdi Jauregui",
    "wof:placetype":"venue"
},
  "geometry": {"coordinates":[-1.9110451937,43.3104782104],"type":"Point"}
}