{
  "type": "Feature",
  "properties": {
    "addr:full":"Ctra Franca, Km. 0036,0 Mollo Girona 17868",
    "addr:postcode":"17868",
    "addr:street":"Ctra Franca Km. 0036,0",
    "iso:country":"ES",
    "sg:address":"Ctra Franca, Km. 0036,0",
    "sg:city":"Mollo",
    "sg:orig_category":"Distribuci\u00d3n De Petr\u00d3leo Y Derivados",
    "sg:phone":"+34 972 13 04 49",
    "sg:postcode":"17868",
    "sg:province":"Girona",
    "wof:name":"Movil S. A.",
    "wof:placetype":"venue"
},
  "geometry": {"coordinates":[2.4043900967,42.3481445312],"type":"Point"}
}