{
  "type": "Feature",
  "properties": {
    "addr:full":"Cmno Ronda (de), 39 Granada Granada 18004",
    "addr:housenumber":"39",
    "addr:postcode":"18004",
    "addr:street":"Cmno Ronda De",
    "iso:country":"ES",
    "sg:address":"Cmno Ronda (de), 39",
    "sg:city":"Granada",
    "sg:orig_category":"Bancos",
    "sg:phone":"+34 958 25 21 66",
    "sg:postcode":"18004",
    "sg:province":"Granada",
    "wof:name":"Banco Bilbao Vizcaya Argentaria S.a.",
    "wof:placetype":"venue"
},
  "geometry": {"coordinates":[-3.6041240692,37.1671562195],"type":"Point"}
}