{
  "type": "Feature",
  "properties": {
    "addr:full":"Cmno Le\u00d1adores, S/n Palmar  O Lugar De Don Juan Murcia 30120",
    "addr:housenumber":"s",
    "addr:postcode":"30120",
    "addr:street":"Cmno Len\u0303Adores;/ N;Lugar",
    "iso:country":"ES",
    "sg:address":"Cmno Le\u00d1adores, S/n",
    "sg:city":"Palmar  O Lugar De Don Juan",
    "sg:orig_category":"Metacrilato: Art\u00cdculos (fabricaci\u00d3n Y Al Por Mayor)",
    "sg:phone":"+34 968 88 32 36",
    "sg:postcode":"30120",
    "sg:province":"Murcia",
    "wof:name":"Joaquin Martinez S.a.",
    "wof:placetype":"venue"
},
  "geometry": {"coordinates":[-1.1617540121,37.9424057007],"type":"Point"}
}