{
  "type": "Feature",
  "properties": {
    "iso:country":"ES",
    "sg:address":"Ctra San Roque, 13",
    "sg:city":"San Roque",
    "sg:orig_category":"Agentes, Concesionarios Y Sucursales De Veh\u00cdculos",
    "sg:phone":"+34 986 61 13 09",
    "sg:postcode":"36789",
    "sg:province":"Pontevedra",
    "wof:name":"Estacion De Servicio San Roque S.l.",
    "wof:placetype":"venue"
},
  "geometry": {"coordinates":[-8.8557891846,41.9191131592],"type":"Point"}
}