{
  "type": "Feature",
  "properties": {
    "addr:full":"Ctra Nal Iii, Km. 0270,0 Utiel Valencia 46300",
    "addr:postcode":"46300",
    "addr:street":"Ctra Nal Iii Km. 0270,0",
    "iso:country":"ES",
    "sg:address":"Ctra Nal Iii, Km. 0270,0",
    "sg:city":"Utiel",
    "sg:orig_category":"Mec\u00c1nico Del Autom\u00d3vil",
    "sg:phone":"+34 962 17 03 22",
    "sg:postcode":"46300",
    "sg:province":"Valencia",
    "wof:name":"Talleres Hermanos Berlanga S.l.",
    "wof:placetype":"venue"
},
  "geometry": {"coordinates":[-1.2064390182,39.5707588196],"type":"Point"}
}