{
  "type": "Feature",
  "properties": {
    "addr:full":"Carr Espartero, 2 Burjassot Valencia 46100",
    "addr:housenumber":"2",
    "addr:postcode":"46100",
    "addr:street":"Carr Espartero",
    "iso:country":"ES",
    "sg:address":"Carr Espartero, 2",
    "sg:city":"Burjassot",
    "sg:orig_category":"Internados & Ense\u00d1anza Privada",
    "sg:phone":"+34 963 63 52 62",
    "sg:postcode":"46100",
    "sg:province":"Valencia",
    "wof:name":"Parroquia La Natividad De Nuestra Se\u00d1ora",
    "wof:placetype":"venue"
},
  "geometry": {"coordinates":[-0.4131869972,39.5026893616],"type":"Point"}
}