{
  "type": "Feature",
  "properties": {
    "addr:full":"Calle de Silos, 11 Puebla Calzada Badajoz 06490",
    "addr:housenumber":"11",
    "addr:postcode":"06490",
    "addr:street":"Calle De Silos;Calzada Badajoz",
    "iso:country":"ES",
    "sg:address":"Calle de Silos, 11",
    "sg:city":"Puebla Calzada",
    "sg:orig_category":"Cajas De Ahorro",
    "sg:phone":"+34 924 45 71 15",
    "sg:postcode":"06490",
    "sg:province":"Badajoz",
    "wof:name":"Caja De Badajoz",
    "wof:placetype":"venue"
},
  "geometry": {"coordinates":[-6.6259059906,38.893371582],"type":"Point"}
}