{
  "type": "Feature",
  "properties": {
    "iso:country":"ES",
    "sg:address":"Calle de Fatas, 7",
    "sg:city":"Huesca",
    "sg:orig_category":"Comercios E Industrias (cesi\u00d3n Y Reactivaci\u00d3n)",
    "sg:phone":"+34 974 22 78 53",
    "sg:postcode":"22002",
    "sg:province":"Huesca",
    "wof:name":"Oscense De Actividades S.a",
    "wof:placetype":"venue"
},
  "geometry": {"coordinates":[-0.4071800113,42.1360054016],"type":"Point"}
}