{
  "type": "Feature",
  "properties": {
    "iso:country":"ES",
    "sg:address":"Calle de Portugal, 39",
    "sg:city":"Fuenlabrada",
    "sg:orig_category":"Laboratorios Y Trabajos De Fotograf\u00cda, V\u00cddeo Y Cine",
    "sg:phone":"+34 916 08 63 13",
    "sg:postcode":"28943",
    "sg:province":"Madrid",
    "wof:name":"Zhang  Xiong",
    "wof:placetype":"venue"
},
  "geometry": {"coordinates":[-3.8095231056,40.2845077515],"type":"Point"}
}