{
  "type": "Feature",
  "properties": {
    "iso:country":"ES",
    "sg:address":"Calle de Infanta Elena, 2",
    "sg:city":"Campo Abajo",
    "sg:orig_category":"Tapicer\u00cdas",
    "sg:phone":"+34 968 71 90 57",
    "sg:postcode":"30510",
    "sg:province":"Murcia",
    "wof:name":"Novointer Yecla S.l",
    "wof:placetype":"venue"
},
  "geometry": {"coordinates":[-1.0633502007,38.6166152954],"type":"Point"}
}