{
  "type": "Feature",
  "properties": {
    "iso:country":"ES",
    "sg:address":"Calle de Gomez Marcelo, 17",
    "sg:city":"Ceuta",
    "sg:orig_category":"Inform\u00c1tica (estudios, Servicios, Asesor\u00cda, Formaci\u00d3n)",
    "sg:phone":"+34 856 20 02 71",
    "sg:postcode":"51001",
    "sg:province":"Ceuta",
    "wof:name":"Indalo Ceuta S.l.l.",
    "wof:placetype":"venue"
},
  "geometry": {"coordinates":[-5.3302302361,35.8947601318],"type":"Point"}
}