{
  "type": "Feature",
  "properties": {
    "addr:full":"Calle de Real, 82 Padul Granada 18640",
    "addr:housenumber":"82",
    "addr:postcode":"18640",
    "addr:street":"Calle De Real",
    "iso:country":"ES",
    "sg:address":"Calle de Real, 82",
    "sg:city":"Padul",
    "sg:orig_category":"Bisuter\u00cda, Joyer\u00cda, Relojer\u00cda (al Por Menor)",
    "sg:phone":"+34 958 79 09 01",
    "sg:postcode":"18640",
    "sg:province":"Granada",
    "wof:name":"Joyeria Villanueva Garcia S.l.",
    "wof:placetype":"venue"
},
  "geometry": {"coordinates":[-3.6258990765,37.0248184204],"type":"Point"}
}