{
  "type": "Feature",
  "properties": {
    "addr:full":"Pla\u00c7 Manuel Bertrand, 17 Mollerussa Lleida 25230",
    "addr:housenumber":"17",
    "addr:postcode":"25230",
    "addr:street":"Manuel Bertrand",
    "iso:country":"ES",
    "sg:address":"Pla\u00c7 Manuel Bertrand, 17",
    "sg:city":"Mollerussa",
    "sg:orig_category":"Papeler\u00cdas: Art\u00cdculos (al Por Mayor)",
    "sg:phone":"+34 973 71 19 01",
    "sg:postcode":"25230",
    "sg:province":"Lleida",
    "wof:name":"Rebost Del Paper S.c.p.",
    "wof:placetype":"venue"
},
  "geometry": {"coordinates":[0.8936949968,41.6300392151],"type":"Point"}
}