{
  "type": "Feature",
  "properties": {
    "iso:country":"ES",
    "sg:address":"Plaz Salvador (del), 7",
    "sg:city":"Segovia",
    "sg:orig_category":"Alimentaci\u00d3n General (al Por Menor)",
    "sg:phone":"+34 921 41 23 17",
    "sg:postcode":"40001",
    "sg:province":"Segovia",
    "wof:name":"Asociacion Cultural La Esteba Grupo Danza",
    "wof:placetype":"venue"
},
  "geometry": {"coordinates":[-4.1137671471,40.9468994141],"type":"Point"}
}