{
  "type": "Feature",
  "properties": {
    "iso:country":"ES",
    "sg:address":"Avda J. Solis Ruiz, 14",
    "sg:city":"Cabra",
    "sg:orig_category":"Tintorer\u00cdas, Limpieza En Seco",
    "sg:phone":"+34 957 52 00 60",
    "sg:postcode":"14940",
    "sg:province":"C\u00f3rdoba",
    "wof:name":"Sanchez Cobo Carmen",
    "wof:placetype":"venue"
},
  "geometry": {"coordinates":[-4.4449448586,37.4721870422],"type":"Point"}
}