{
  "type": "Feature",
  "properties": {
    "addr:full":"Dos Pol. Pla Rasca\u00f1a, S/n Lliria Valencia 46160",
    "addr:housenumber":"s / n",
    "addr:postcode":"46160",
    "addr:street":"Dos Pol. Pla Rascan\u0303A",
    "iso:country":"ES",
    "sg:address":"Dos Pol. Pla Rasca\u00f1a, S/n",
    "sg:city":"Lliria",
    "sg:orig_category":"Molduras, Junquillos, Listones Y Molduras Perforadas",
    "sg:phone":"+34 962 78 18 84",
    "sg:postcode":"46160",
    "sg:province":"Valencia",
    "wof:name":"Rodriguez Garcia Edmundo Antonio",
    "wof:placetype":"venue"
},
  "geometry": {"coordinates":[-0.5952839851,39.6247406006],"type":"Point"}
}