{
  "type": "Feature",
  "properties": {
    "iso:country":"ES",
    "sg:address":"Calle de Getaria, 2",
    "sg:city":"Donostia-san Sebastian",
    "sg:orig_category":"Ropa Para Ni\u00d1os (al Por Menor)",
    "sg:phone":"+34 943 42 87 24",
    "sg:postcode":"20005",
    "sg:province":"Guip\u00f9zcoa",
    "sg:website":"www.e-stradivarius.com",
    "wof:name":"Stradivarius Espa\u00f1a S.a.",
    "wof:placetype":"venue"
},
  "geometry": {"coordinates":[-1.9816490412,43.3192939758],"type":"Point"}
}