{
  "type": "Feature",
  "properties": {
    "addr:full":"Calle de Doctor Nuez Aguilar, 17 Palmas De Gran Canaria Las Palmas 35001",
    "addr:housenumber":"17",
    "addr:postcode":"35001",
    "addr:street":"Calle De Doctor Nuez Aguilar",
    "iso:country":"ES",
    "sg:address":"Calle de Doctor Nuez Aguilar, 17",
    "sg:city":"Palmas De Gran Canaria",
    "sg:orig_category":"Asesor\u00cda De Formaci\u00d3n Y Gesti\u00d3n De Personal",
    "sg:phone":"+34 928 32 20 22",
    "sg:postcode":"35001",
    "sg:province":"Las Palmas",
    "wof:name":"Reyes Quintana Victorio Jesus",
    "wof:placetype":"venue"
},
  "geometry": {"coordinates":[-15.4157400131,28.0969390869],"type":"Point"}
}