{
  "type": "Feature",
  "properties": {
    "iso:country":"ES",
    "sg:address":"Barr Ace\u00d1as, S/n",
    "sg:city":"Viveiro",
    "sg:orig_category":"Vinos Y Licores (venta Al Por Menor)",
    "sg:phone":"+34 982 55 03 62",
    "sg:postcode":"27850",
    "sg:province":"Lugo",
    "wof:name":"Vivariun S.l.",
    "wof:placetype":"venue"
},
  "geometry": {"coordinates":[-7.5788974762,43.6448402405],"type":"Point"}
}