{
  "type": "Feature",
  "properties": {
    "iso:country":"ES",
    "sg:address":"Calle de Felix Manuel Martinez, 6",
    "sg:city":"Tarancon",
    "sg:orig_category":"Metalurgia",
    "sg:phone":"+34 969 32 07 79",
    "sg:postcode":"16400",
    "sg:province":"Cuenca",
    "wof:name":"Aislamientos Prasan S.l.",
    "wof:placetype":"venue"
},
  "geometry": {"coordinates":[-3.0138971806,40.0168533325],"type":"Point"}
}