{
  "type": "Feature",
  "properties": {
    "iso:country":"ES",
    "sg:address":"Avda Lancia, 4",
    "sg:city":"Le\u00f3n",
    "sg:orig_category":"Cl\u00cdnicas M\u00c9dicas",
    "sg:phone":"+34 987 20 61 12",
    "sg:postcode":"24004",
    "sg:province":"Le\u00f3n",
    "wof:name":"Sanatorio Lopez-otazu S. L.",
    "wof:placetype":"venue"
},
  "geometry": {"coordinates":[-5.5729680061,42.5939979553],"type":"Point"}
}