{
  "type": "Feature",
  "properties": {
    "iso:country":"ES",
    "sg:address":"Pol Ind Red, Km. 0004,8",
    "sg:city":"Alcala Guadaira",
    "sg:orig_category":"Construcciones Met\u00c1licas",
    "sg:phone":"+34 955 63 20 46",
    "sg:postcode":"41500",
    "sg:province":"Sevilla",
    "wof:name":"Astral Pool Espa\u00f1a S.a.u.",
    "wof:placetype":"venue"
},
  "geometry": {"coordinates":[-5.9962949753,37.3826408386],"type":"Point"}
}