{
  "type": "Feature",
  "properties": {
    "addr:full":"Calle de General Rincon, 10 Coin M\u00e1laga 29100",
    "addr:housenumber":"10",
    "addr:postcode":"29100",
    "addr:street":"Calle De General Rincon;Ma\u0301Laga",
    "iso:country":"ES",
    "sg:address":"Calle de General Rincon, 10",
    "sg:city":"Coin",
    "sg:classifiers":[
        {
            "category":"Autos & Motor Vehicles",
            "subcategory":"Automobile Sales",
            "type":"Retail Goods"
        }
    ],
    "sg:phone":"+34 952 45 04 96",
    "sg:postcode":"29100",
    "sg:province":"M\u00e1laga",
    "wof:name":"Santos Navarro Cristobal",
    "wof:placetype":"venue"
},
  "geometry": {"coordinates":[-4.7551388741,36.6584281921],"type":"Point"}
}