{
  "type": "Feature",
  "properties": {
    "addr:full":"Calle de Baron De La Torre, S/n Cintruenigo Navarra 31592",
    "addr:housenumber":"s / n",
    "addr:postcode":"31592",
    "addr:street":"Calle De Baron De La Torre",
    "iso:country":"ES",
    "sg:address":"Calle de Baron De La Torre, S/n",
    "sg:city":"Cintruenigo",
    "sg:orig_category":"Agricultores, Agricultores",
    "sg:phone":"+34 948 81 14 78",
    "sg:postcode":"31592",
    "sg:province":"Navarra",
    "wof:name":"Sociedad Agraria De Transformacion Las Alegas",
    "wof:placetype":"venue"
},
  "geometry": {"coordinates":[-1.8085589409,42.0796546936],"type":"Point"}
}