{
  "type": "Feature",
  "properties": {
    "addr:full":"Calle de Ventanilla, 15 Granada Granada 18001",
    "addr:housenumber":"15",
    "addr:postcode":"18001",
    "addr:street":"Calle De Ventanilla",
    "iso:country":"ES",
    "sg:address":"Calle de Ventanilla, 15",
    "sg:city":"Granada",
    "sg:orig_category":"Inform\u00c1tica (estudios, Servicios, Asesor\u00cda, Formaci\u00d3n)",
    "sg:phone":"+34 958 20 16 70",
    "sg:postcode":"18001",
    "sg:province":"Granada",
    "wof:name":"Leyva Martinez Jose Antonio",
    "wof:placetype":"venue"
},
  "geometry": {"coordinates":[-3.6035180092,37.1816902161],"type":"Point"}
}