{
  "type": "Feature",
  "properties": {
    "iso:country":"ES",
    "sg:address":"Calle de Dendari Kalea, 43",
    "sg:city":"Lekeitio",
    "sg:orig_category":"Barnizadores",
    "sg:phone":"+34 946 84 23 29",
    "sg:postcode":"48280",
    "sg:province":"Vizcaya",
    "wof:name":"Grandoso Pinto Irineo",
    "wof:placetype":"venue"
},
  "geometry": {"coordinates":[-2.5052602291,43.3620986938],"type":"Point"}
}