{
  "type": "Feature",
  "properties": {
    "iso:country":"ES",
    "sg:address":"Calle de Maestro Bartolome, 5",
    "sg:city":"Jaen",
    "sg:orig_category":"Abogados",
    "sg:phone":"+34 953 27 58 06",
    "sg:postcode":"23007",
    "sg:province":"Ja\u00e9n",
    "wof:name":"Alvarez Moreno Maria Bego\u00f1a",
    "wof:placetype":"venue"
},
  "geometry": {"coordinates":[-3.790522337,37.7708053589],"type":"Point"}
}