{
  "type": "Feature",
  "properties": {
    "addr:full":"Calle de Eras Bajas De Pinos Puente, S/n Pinos-puente Granada 18240",
    "addr:housenumber":"s",
    "addr:postcode":"18240",
    "addr:street":"Calle De Eras Bajas De Pinos Puente;/ N",
    "iso:country":"ES",
    "sg:address":"Calle de Eras Bajas De Pinos Puente, S/n",
    "sg:city":"Pinos-puente",
    "sg:orig_category":"Venta, Instalaci\u00d3n, Reparaci\u00d3n De Antenas Para Televisi\u00d3n",
    "sg:phone":"+34 958 45 08 02",
    "sg:postcode":"18240",
    "sg:province":"Granada",
    "wof:name":"T.v.c. Pinos Puente S.l.",
    "wof:placetype":"venue"
},
  "geometry": {"coordinates":[-3.7521839142,37.2517814636],"type":"Point"}
}