{
  "type": "Feature",
  "properties": {
    "addr:full":"Calle de Virgen De Lourdes, 4 Palmas De Gran Canaria Las Palmas 35013",
    "addr:housenumber":"4",
    "addr:postcode":"35013",
    "addr:street":"Calle De Virgen De Lourdes",
    "iso:country":"ES",
    "sg:address":"Calle de Virgen De Lourdes, 4",
    "sg:city":"Palmas De Gran Canaria",
    "sg:orig_category":"Loter\u00cda Y T\u00d3mbola",
    "sg:phone":"+34 928 36 07 61",
    "sg:postcode":"35013",
    "sg:province":"Las Palmas",
    "wof:name":"Gonzalez Naranjo Pedro",
    "wof:placetype":"venue"
},
  "geometry": {"coordinates":[-15.4325113297,28.1056079865],"type":"Point"}
}