{
  "type": "Feature",
  "properties": {
    "addr:full":"Calle de Rodrigo Rebolledo, 10 Zaragoza Zaragoza 50002",
    "addr:housenumber":"10",
    "addr:postcode":"50002",
    "addr:street":"Calle De Rodrigo Rebolledo",
    "iso:country":"ES",
    "sg:address":"Calle de Rodrigo Rebolledo, 10",
    "sg:city":"Zaragoza",
    "sg:orig_category":"Confecci\u00d3n (fabricaci\u00d3n, Al Por Mayor)",
    "sg:phone":"+34 976 42 77 48",
    "sg:postcode":"50002",
    "sg:province":"Zaragoza",
    "wof:name":"Coronas Vallespin Enrique",
    "wof:placetype":"venue"
},
  "geometry": {"coordinates":[-0.8649240136,41.6461143494],"type":"Point"}
}