{
  "type": "Feature",
  "properties": {
    "iso:country":"ES",
    "sg:address":"Calle de Benijofar, 13",
    "sg:city":"Palacios",
    "sg:orig_category":"Electromec\u00c1nica",
    "sg:phone":"+34 966 71 43 16",
    "sg:postcode":"03179",
    "sg:province":"Alicante",
    "wof:name":"Box Carratala Manuel",
    "wof:placetype":"venue"
},
  "geometry": {"coordinates":[-0.7332012057,38.0815391541],"type":"Point"}
}