{
  "type": "Feature",
  "properties": {
    "addr:full":"Carrer de Carbo (d'en), 10 Tortosa Tarragona 43500",
    "addr:housenumber":"10",
    "addr:postcode":"43500",
    "addr:street":"Carrer De Carbo D'En",
    "iso:country":"ES",
    "sg:address":"Carrer de Carbo (d'en), 10",
    "sg:city":"Tortosa",
    "sg:orig_category":"Librer\u00cdas",
    "sg:phone":"+34 977 44 24 09",
    "sg:postcode":"43500",
    "sg:province":"Tarragona",
    "wof:name":"Izquierdo Aguilar Francisco",
    "wof:placetype":"venue"
},
  "geometry": {"coordinates":[0.5211369991,40.8116264343],"type":"Point"}
}