{
  "type": "Feature",
  "properties": {
    "iso:country":"ES",
    "sg:address":"Plaz Reina Sofia, 1",
    "sg:city":"Cuenca",
    "sg:orig_category":"Promotores Constructores",
    "sg:phone":"+34 969 22 31 22",
    "sg:postcode":"16003",
    "sg:province":"Cuenca",
    "wof:name":"Maquinas Obras Publicas Saiz S.l.",
    "wof:placetype":"venue"
},
  "geometry": {"coordinates":[-2.1362390518,40.0720710754],"type":"Point"}
}