{
  "type": "Feature",
  "properties": {
    "iso:country":"ES",
    "sg:address":"Calle de Sierra De Guadarrama (de La), 82",
    "sg:city":"Poligono De San Fernando De Henares",
    "sg:orig_category":"Suministros Para Hoteles",
    "sg:phone":"+34 916 75 10 23",
    "sg:postcode":"28830",
    "sg:province":"Madrid",
    "wof:name":"Hosteleria Dise\u00f1o Y Tecnologia S.l.",
    "wof:placetype":"venue"
},
  "geometry": {"coordinates":[-3.4966640472,40.4518547058],"type":"Point"}
}