{
  "type": "Feature",
  "properties": {
    "addr:full":"Ctra Badajoz, 10 Alconchel Badajoz 06131",
    "addr:housenumber":"10",
    "addr:postcode":"06131",
    "addr:street":"Ctra Badajoz",
    "iso:country":"ES",
    "sg:address":"Ctra Badajoz, 10",
    "sg:city":"Alconchel",
    "sg:orig_category":"Estancos",
    "sg:phone":"+34 924 42 03 96",
    "sg:postcode":"06131",
    "sg:province":"Badajoz",
    "wof:name":"Lucas Calaco Jose",
    "wof:placetype":"venue"
},
  "geometry": {"coordinates":[-7.0678539276,38.5165748596],"type":"Point"}
}