{
  "type": "Feature",
  "properties": {
    "addr:full":"Avda Madrid, 2 Valderrobres Teruel 44580",
    "addr:housenumber":"2",
    "addr:postcode":"44580",
    "addr:street":"Avda Madrid",
    "iso:country":"ES",
    "sg:address":"Avda Madrid, 2",
    "sg:city":"Valderrobres",
    "sg:orig_category":"Centros De Educaci\u00d3n Especial",
    "sg:phone":"+34 978 85 06 55",
    "sg:postcode":"44580",
    "sg:province":"Teruel",
    "wof:name":"Colegio Publico Vicente Ferrer",
    "wof:placetype":"venue"
},
  "geometry": {"coordinates":[0.1556870043,40.8730735779],"type":"Point"}
}