{
  "type": "Feature",
  "properties": {
    "addr:full":"Ctra Madrid N-iv, S/n Cordoba C\u00f3rdoba 14014",
    "addr:housenumber":"s",
    "addr:postcode":"14014",
    "addr:street":"Ctra Madrid N-Iv;/ N;Co\u0301Rdoba",
    "iso:country":"ES",
    "sg:address":"Ctra Madrid N-iv, S/n",
    "sg:city":"Cordoba",
    "sg:orig_category":"M\u00c1rmoles, Granitos Y Piedras Naturales",
    "sg:phone":"+34 957 32 52 95",
    "sg:postcode":"14014",
    "sg:province":"C\u00f3rdoba",
    "wof:name":"Rubia Nieto Miguel De La",
    "wof:placetype":"venue"
},
  "geometry": {"coordinates":[-4.6691141129,37.9341316223],"type":"Point"}
}