{
  "type": "Feature",
  "properties": {
    "addr:full":"Av Marina Alta (de La), 190 Gata Gorgos Alicante 03740",
    "addr:housenumber":"190",
    "addr:postcode":"03740",
    "addr:street":"Av",
    "iso:country":"ES",
    "sg:address":"Av Marina Alta (de La), 190",
    "sg:city":"Gata Gorgos",
    "sg:orig_category":"Fabricaci\u00d3n, Comercio De Muebles En Ca\u00d1a, Mimbre",
    "sg:phone":"+34 965 75 68 44",
    "sg:postcode":"03740",
    "sg:province":"Alicante",
    "wof:name":"Pedros Mengual Maria",
    "wof:placetype":"venue"
},
  "geometry": {"coordinates":[0.0899199992,38.7722892761],"type":"Point"}
}