{
  "type": "Feature",
  "properties": {
    "iso:country":"ES",
    "sg:address":"Calle de Princesa, 3",
    "sg:city":"Madrid",
    "sg:orig_category":"Empresarios",
    "sg:phone":"+34 915 47 04 17",
    "sg:postcode":"28008",
    "sg:province":"Madrid",
    "wof:name":"Mulas Puente Ignacio",
    "wof:placetype":"venue"
},
  "geometry": {"coordinates":[-3.712594986,40.4251708984],"type":"Point"}
}