{
  "type": "Feature",
  "properties": {
    "addr:full":"Calle de Panadera, 3 Puebla Montalban Toledo 45516",
    "addr:housenumber":"3",
    "addr:postcode":"45516",
    "addr:street":"Calle De Panadera",
    "iso:country":"ES",
    "sg:address":"Calle de Panadera, 3",
    "sg:city":"Puebla Montalban",
    "sg:orig_category":"Alimentaci\u00d3n General (al Por Menor)",
    "sg:phone":"+34 925 75 08 82",
    "sg:postcode":"45516",
    "sg:province":"Toledo",
    "wof:name":"Casta\u00f1o Del Valle Jose Luis",
    "wof:placetype":"venue"
},
  "geometry": {"coordinates":[-4.3602538109,39.860710144],"type":"Point"}
}