{
  "type": "Feature",
  "properties": {
    "iso:country":"ES",
    "sg:address":"Calle de Vicenta Garcia Miranda, 3",
    "sg:city":"Badajoz",
    "sg:orig_category":"Comercio, Reparaci\u00d3n De Motocicletas, Bicicletas Y Piezas Sueltas",
    "sg:phone":"+34 924 24 28 41",
    "sg:postcode":"06009",
    "sg:province":"Badajoz",
    "wof:name":"Craveiro Reis Costa Ricardo Jorge",
    "wof:placetype":"venue"
},
  "geometry": {"coordinates":[-6.9618291855,38.8752937317],"type":"Point"}
}