{
  "type": "Feature",
  "properties": {
    "addr:full":"Calle de Padre Mendez, 75 Torrent Valencia 46900",
    "addr:housenumber":"75",
    "addr:postcode":"46900",
    "addr:street":"Calle De Padre Mendez;Valencia",
    "iso:country":"ES",
    "sg:address":"Calle de Padre Mendez, 75",
    "sg:city":"Torrent",
    "sg:orig_category":"Puertas Y Portales",
    "sg:phone":"+34 961 58 01 54",
    "sg:postcode":"46900",
    "sg:province":"Valencia",
    "wof:name":"Puertas Aguilera S.l.",
    "wof:placetype":"venue"
},
  "geometry": {"coordinates":[-0.4685879946,39.4335098267],"type":"Point"}
}