{
  "type": "Feature",
  "properties": {
    "addr:full":"Barrachina, 62 Mas De Pavia Valencia 46900",
    "addr:housenumber":"62",
    "addr:postcode":"46900",
    "addr:street":"Barrachina;De",
    "iso:country":"ES",
    "sg:address":"Barrachina, 62",
    "sg:city":"Mas De Pavia",
    "sg:orig_category":"Empresarios",
    "sg:phone":"+34 962 11 13 87",
    "sg:postcode":"46900",
    "sg:province":"Valencia",
    "wof:name":"Reyconova S.l.",
    "wof:placetype":"venue"
},
  "geometry": {"coordinates":[-0.4623290002,39.441619873],"type":"Point"}
}