{
  "type": "Feature",
  "properties": {
    "addr:full":"Ctra Cuesta Ramon, S/n Marzagan Las Palmas 35016",
    "addr:housenumber":"s",
    "addr:postcode":"35016",
    "addr:street":"Ctra Cuesta Ramon;/ N Marzagan Las",
    "iso:country":"ES",
    "sg:address":"Ctra Cuesta Ramon, S/n",
    "sg:city":"Marzagan",
    "sg:orig_category":"Frutas Y Legumbres Frescas (al Por Mayor)",
    "sg:phone":"+34 928 71 16 88",
    "sg:postcode":"35016",
    "sg:province":"Las Palmas",
    "wof:name":"Torres Valido Carmelo",
    "wof:placetype":"venue"
},
  "geometry": {"coordinates":[-15.4306898117,28.0386505127],"type":"Point"}
}