{
  "type": "Feature",
  "properties": {
    "addr:full":"Ctra. Nijar, 396 Almeria Almer\u00eda 04007",
    "addr:housenumber":"396",
    "addr:postcode":"04007",
    "addr:street":"Ctra. Nijar",
    "iso:country":"ES",
    "sg:address":"Ctra. Nijar, 396",
    "sg:city":"Almeria",
    "sg:orig_category":"Adaptaciones, Acondicionamientos Especiales Para Veh\u00cdculos, Veh\u00cdculos Industriales",
    "sg:phone":"+34 950 22 16 52",
    "sg:postcode":"04007",
    "sg:province":"Almer\u00eda",
    "wof:name":"Automecanica Lopez E Hijos S.l.",
    "wof:placetype":"venue"
},
  "geometry": {"coordinates":[-2.4374930859,36.8442459106],"type":"Point"}
}