{
  "type": "Feature",
  "properties": {
    "addr:full":"Calle de Sor Angela De La Cruz, 17 Madrid Madrid 28020",
    "addr:housenumber":"17",
    "addr:postcode":"madrid;28020",
    "addr:street":"Calle De Sor Angela De La Cruz",
    "iso:country":"ES",
    "sg:address":"Calle de Sor Angela De La Cruz, 17",
    "sg:city":"Madrid",
    "sg:orig_category":"M\u00c9dicos: Alergolog\u00cda",
    "sg:phone":"+34 915 70 09 09",
    "sg:postcode":"28020",
    "sg:province":"Madrid",
    "wof:name":"Sainz Martin Teofilo",
    "wof:placetype":"venue"
},
  "geometry": {"coordinates":[-3.6963028908,40.4598274231],"type":"Point"}
}