{
  "type": "Feature",
  "properties": {
    "addr:full":"Rua De Compostela, 20 Ordes La Coru\u00f1a 15680",
    "addr:housenumber":"20",
    "addr:postcode":"15680",
    "addr:street":"Rua De Compostela;La Corun\u0303A",
    "iso:country":"ES",
    "sg:address":"Rua De Compostela, 20",
    "sg:city":"Ordes",
    "sg:orig_category":"Art\u00cdculos De Regalo (al Por Menor)",
    "sg:phone":"+34 981 68 12 68",
    "sg:postcode":"15680",
    "sg:province":"La Coru\u00f1a",
    "wof:name":"Candal Vazquez Maria Del Carmen",
    "wof:placetype":"venue"
},
  "geometry": {"coordinates":[-8.4097900391,43.077671051],"type":"Point"}
}