{
  "type": "Feature",
  "properties": {
    "iso:country":"ES",
    "sg:address":"Calle de Castro Urdiales, 10",
    "sg:city":"Vitoria-gasteiz",
    "sg:orig_category":"Asesor\u00cda Sobre Comunicaci\u00d3n De Empresas",
    "sg:phone":"+34 945 14 53 08",
    "sg:postcode":"01006",
    "sg:province":"\u00c1lava",
    "sg:website":"www.secot.org",
    "wof:name":"Seniors Espa\u00d1oles Para La Cooperacion Tecnica",
    "wof:placetype":"venue"
},
  "geometry": {"coordinates":[-2.6649570465,42.8393554688],"type":"Point"}
}