{
  "type": "Feature",
  "properties": {
    "iso:country":"ES",
    "sg:address":"Calle de Concepcion, 10",
    "sg:city":"Algodonales",
    "sg:orig_category":"Reposter\u00cdas",
    "sg:phone":"+34 956 13 77 43",
    "sg:postcode":"11680",
    "sg:province":"C\u00e1diz",
    "wof:name":"Marchena Escorza Rosario",
    "wof:placetype":"venue"
},
  "geometry": {"coordinates":[-5.407166481,36.8825187683],"type":"Point"}
}