{
  "type": "Feature",
  "properties": {
    "addr:full":"Calle de Monjitas, 1 Majadahonda Madrid 28220",
    "addr:housenumber":"1",
    "addr:postcode":"28220",
    "addr:street":"Calle De Monjitas",
    "iso:country":"ES",
    "sg:address":"Calle de Monjitas, 1",
    "sg:city":"Majadahonda",
    "sg:orig_category":"Ropa Para Se\u00d1oras (al Por Menor)",
    "sg:phone":"+34 916 38 62 93",
    "sg:postcode":"28220",
    "sg:province":"Madrid",
    "wof:name":"Hernangil Martinez Carolina Monica",
    "wof:placetype":"venue"
},
  "geometry": {"coordinates":[-3.8717041016,40.4713401794],"type":"Point"}
}