{
  "type": "Feature",
  "properties": {
    "addr:full":"Plaz Espa\u00d1a (de), S/n Alberite La Rioja 26141",
    "addr:housenumber":"s",
    "addr:postcode":"26141",
    "addr:street":"Plaz;/ N Alberite;Rioja",
    "iso:country":"ES",
    "sg:address":"Plaz Espa\u00d1a (de), S/n",
    "sg:city":"Alberite",
    "sg:orig_category":"Molduras, Junquillos, Listones Y Molduras Perforadas",
    "sg:phone":"+34 941 43 63 64",
    "sg:postcode":"26141",
    "sg:province":"La Rioja",
    "wof:name":"Sanchez Torres Domingo",
    "wof:placetype":"venue"
},
  "geometry": {"coordinates":[-2.4409348965,42.4059753418],"type":"Point"}
}