{
  "type": "Feature",
  "properties": {
    "addr:full":"Ptda Volta, S/n Tosalet Castell\u00f3n 12200",
    "addr:housenumber":"s",
    "addr:postcode":"12200",
    "addr:street":"Ptda Volta;/ N Tosalet Castello\u0301N",
    "iso:country":"ES",
    "sg:address":"Ptda Volta, S/n",
    "sg:city":"Tosalet",
    "sg:orig_category":"Empresarios",
    "sg:phone":"+34 964 60 31 16",
    "sg:postcode":"12200",
    "sg:province":"Castell\u00f3n",
    "wof:name":"Cerezuela Robles Pedro",
    "wof:placetype":"venue"
},
  "geometry": {"coordinates":[-0.2620640099,39.9651794434],"type":"Point"}
}