{
  "type": "Feature",
  "properties": {
    "addr:full":"Av Diagonal, 621 Barcelona Barcelona 08028",
    "addr:housenumber":"621",
    "addr:postcode":"08028",
    "addr:street":"Av Diagonal",
    "iso:country":"ES",
    "sg:address":"Av Diagonal, 621",
    "sg:city":"Barcelona",
    "sg:orig_category":"Inform\u00c1tica: Material Y Suministros",
    "sg:phone":"+34 934 90 47 97",
    "sg:postcode":"08028",
    "sg:province":"Barcelona",
    "wof:name":"Sun Microsystems Iberica S.a.",
    "wof:placetype":"venue"
},
  "geometry": {"coordinates":[2.1267530918,41.3878173828],"type":"Point"}
}