{
  "type": "Feature",
  "properties": {
    "addr:full":"Av Miraflores, 78 Hospitalet Llobregat Barcelona 08905",
    "addr:housenumber":"78",
    "addr:postcode":"08905",
    "addr:street":"Av Miraflores",
    "iso:country":"ES",
    "sg:address":"Av Miraflores, 78",
    "sg:city":"Hospitalet Llobregat",
    "sg:orig_category":"Inmobiliaria (agencias)",
    "sg:phone":"+34 934 48 25 45",
    "sg:postcode":"08905",
    "sg:province":"Barcelona",
    "wof:name":"Inmobiliaria Hospitalet Ciudad S.l.",
    "wof:placetype":"venue"
},
  "geometry": {"coordinates":[2.1074240208,41.3724708557],"type":"Point"}
}