{
  "type": "Feature",
  "properties": {
    "iso:country":"ES",
    "sg:address":"Carrer de Joan Oro, 21",
    "sg:city":"S. Esteve Sesrovires",
    "sg:orig_category":"Estudios, Instalaci\u00d3n De Climatizaci\u00d3n",
    "sg:phone":"+34 937 71 48 98",
    "sg:postcode":"08635",
    "sg:province":"Barcelona",
    "wof:name":"Electricidad Benaiges S. C. C. L.",
    "wof:placetype":"venue"
},
  "geometry": {"coordinates":[1.8753750324,41.4788246155],"type":"Point"}
}