{
  "type": "Feature",
  "properties": {
    "addr:full":"Ctra. Nal. Iii, 1 Requena Valencia 46340",
    "addr:housenumber":"1",
    "addr:postcode":"46340",
    "addr:street":"Ctra. Nal. Iii",
    "iso:country":"ES",
    "sg:address":"Ctra. Nal. Iii, 1",
    "sg:city":"Requena",
    "sg:orig_category":"Mec\u00c1nico Del Autom\u00d3vil",
    "sg:phone":"+34 962 30 56 30",
    "sg:postcode":"46340",
    "sg:province":"Valencia",
    "wof:name":"Servicios Oleana S.l.",
    "wof:placetype":"venue"
},
  "geometry": {"coordinates":[-1.0998990536,39.4906158447],"type":"Point"}
}