{
  "type": "Feature",
  "properties": {
    "addr:full":"Avda Rufo G Rendueles, 19 Gijon Asturias 33203",
    "addr:housenumber":"19",
    "addr:postcode":"33203",
    "addr:street":"Avda Rufo G Rendueles",
    "iso:country":"ES",
    "sg:address":"Avda Rufo G Rendueles, 19",
    "sg:city":"Gijon",
    "sg:orig_category":"Doctores En Medicina",
    "sg:phone":"+34 985 33 70 20",
    "sg:postcode":"33203",
    "sg:province":"Asturias",
    "wof:name":"Benavides Benavides Ana",
    "wof:placetype":"venue"
},
  "geometry": {"coordinates":[-5.6462907791,43.5403327942],"type":"Point"}
}