{
  "type": "Feature",
  "properties": {
    "addr:full":"Calle de Luz, 26 Ciudad Real Ciudad Real 13003",
    "addr:housenumber":"26",
    "addr:postcode":"13003",
    "addr:street":"Calle De Luz",
    "iso:country":"ES",
    "sg:address":"Calle de Luz, 26",
    "sg:city":"Ciudad Real",
    "sg:orig_category":"Aceites Y Grasas Alimentarias (fabricaci\u00d3n, Al Por Mayor)",
    "sg:phone":"+34 926 22 33 35",
    "sg:postcode":"13003",
    "sg:province":"Ciudad Real",
    "wof:name":"Aceites Ibericos Acisa S.a.",
    "wof:placetype":"venue"
},
  "geometry": {"coordinates":[-3.9274353981,38.9906044006],"type":"Point"}
}