{
  "type": "Feature",
  "properties": {
    "iso:country":"ES",
    "sg:address":"Gta Tres Culturas (de Las), S/n",
    "sg:city":"Cordoba",
    "sg:orig_category":"Confecci\u00d3n De Corbatas",
    "sg:phone":"+34 957 27 40 75",
    "sg:postcode":"14011",
    "sg:province":"C\u00f3rdoba",
    "wof:name":"The Tie Gallery Espa\u00f1a S.a.",
    "wof:placetype":"venue"
},
  "geometry": {"coordinates":[-4.7898287773,37.8890190125],"type":"Point"}
}