{
  "type": "Feature",
  "properties": {
    "iso:country":"ES",
    "sg:address":"Calle de Tafetana, 4",
    "sg:city":"Chafiras",
    "sg:orig_category":"Quincaller\u00cda (al Por Menor)",
    "sg:phone":"+34 902 40 06 26",
    "sg:postcode":"38639",
    "sg:province":"Santa Cruz De Tenerife",
    "wof:name":"Las Chafiras S.a.",
    "wof:placetype":"venue"
},
  "geometry": {"coordinates":[-16.6115474701,28.0350246429],"type":"Point"}
}