{
  "type": "Feature",
  "properties": {
    "iso:country":"ES",
    "sg:address":"Calle de Padre Santaella, 10",
    "sg:city":"Almeria",
    "sg:orig_category":"Peluqueros: De Se\u00d1oras",
    "sg:phone":"+34 950 25 66 07",
    "sg:postcode":"04004",
    "sg:province":"Almer\u00eda",
    "wof:name":"Marin Perez Carolina",
    "wof:placetype":"venue"
},
  "geometry": {"coordinates":[-2.461714983,36.8379554749],"type":"Point"}
}