{
  "type": "Feature",
  "properties": {
    "addr:full":"General Franco, 14 Figueras Asturias 33794",
    "addr:housenumber":"14",
    "addr:postcode":"33794",
    "addr:street":"Franco",
    "iso:country":"ES",
    "sg:address":"General Franco, 14",
    "sg:city":"Figueras",
    "sg:classifiers":[
        {
            "category":"Taxi",
            "type":"Transportation"
        }
    ],
    "sg:phone":"+34 985 63 61 20",
    "sg:postcode":"33794",
    "sg:province":"Asturias",
    "wof:name":"Lopez Perez Jose",
    "wof:placetype":"venue"
},
  "geometry": {"coordinates":[-7.0207791328,43.539642334],"type":"Point"}
}