{
  "type": "Feature",
  "properties": {
    "iso:country":"ES",
    "sg:address":"Ptge Merce Rodoreda, 6",
    "sg:city":"Castelldefels",
    "sg:orig_category":"Electricidad: Instaladores",
    "sg:phone":"+34 936 36 16 53",
    "sg:postcode":"08860",
    "sg:province":"Barcelona",
    "wof:name":"Urares Ingenieria Y Servicios S.l.",
    "wof:placetype":"venue"
},
  "geometry": {"coordinates":[1.9743510485,41.2828559875],"type":"Point"}
}