{
  "type": "Feature",
  "properties": {
    "addr:full":"C/ Cala Antena, S/n Cales Mallorca Islas Baleares 07689",
    "addr:housenumber":"s / n",
    "addr:postcode":"07689",
    "addr:street":"C / Cala Antena",
    "iso:country":"ES",
    "sg:address":"C/ Cala Antena, S/n",
    "sg:city":"Cales Mallorca",
    "sg:orig_category":"Alquiler De V\u00cddeo",
    "sg:phone":"+34 971 83 38 62",
    "sg:postcode":"07689",
    "sg:province":"Islas Baleares",
    "wof:name":"Roiguride C.b.",
    "wof:placetype":"venue"
},
  "geometry": {"coordinates":[3.2774689198,39.4669189453],"type":"Point"}
}