{
  "type": "Feature",
  "properties": {
    "iso:country":"ES",
    "sg:address":"Calle de Mayor De Ramon Y Cajal, 24",
    "sg:city":"Orihuela",
    "sg:orig_category":"Administradores De Bienes Y Delegados De Comunidades De Propietarios",
    "sg:phone":"+34 966 73 81 36",
    "sg:postcode":"03300",
    "sg:province":"Alicante",
    "wof:name":"Canovas Servicios Integrales S.l.",
    "wof:placetype":"venue"
},
  "geometry": {"coordinates":[-0.9474490285,38.0856590271],"type":"Point"}
}