{
  "type": "Feature",
  "properties": {
    "addr:full":"Calle de Padre Alfonso, 9 Villanueva Arzobispo Ja\u00e9n 23330",
    "addr:housenumber":"9",
    "addr:postcode":"23330",
    "addr:street":"Calle De Padre Alfonso",
    "iso:country":"ES",
    "sg:address":"Calle de Padre Alfonso, 9",
    "sg:city":"Villanueva Arzobispo",
    "sg:orig_category":"Carpinteros",
    "sg:phone":"+34 953 45 00 32",
    "sg:postcode":"23330",
    "sg:province":"Ja\u00e9n",
    "wof:name":"Rubio Baena Antonio",
    "wof:placetype":"venue"
},
  "geometry": {"coordinates":[-3.0041589737,38.1703109741],"type":"Point"}
}