{
  "type": "Feature",
  "properties": {
    "addr:full":"Carrer de Doctor Junyent, 19 Vic Barcelona 08500",
    "addr:housenumber":"19",
    "addr:postcode":"08500",
    "addr:street":"Carrer De Doctor Junyent",
    "iso:country":"ES",
    "sg:address":"Carrer de Doctor Junyent, 19",
    "sg:city":"Vic",
    "sg:orig_category":"Cristaler\u00cdas",
    "sg:phone":"+34 938 85 08 00",
    "sg:postcode":"08500",
    "sg:province":"Barcelona",
    "wof:name":"Vidres Barnolas S.a.",
    "wof:placetype":"venue"
},
  "geometry": {"coordinates":[2.2492198944,41.9281311035],"type":"Point"}
}