{
  "type": "Feature",
  "properties": {
    "iso:country":"ES",
    "sg:address":"Calle de Mu\u00d1oz Torrero, 164",
    "sg:city":"Azuaga",
    "sg:orig_category":"Alimentaci\u00d3n General (al Por Menor)",
    "sg:phone":"+34 924 89 05 47",
    "sg:postcode":"06920",
    "sg:province":"Badajoz",
    "wof:name":"Alejandre Guillen Encarnacion",
    "wof:placetype":"venue"
},
  "geometry": {"coordinates":[-5.6803984642,38.2621574402],"type":"Point"}
}