{
  "type": "Feature",
  "properties": {
    "addr:full":"Carr Maestro Ramon Nef, 30 Turis Valencia 46389",
    "addr:housenumber":"30",
    "addr:postcode":"46389",
    "addr:street":"Carr Maestro Ramon Nef",
    "iso:country":"ES",
    "sg:address":"Carr Maestro Ramon Nef, 30",
    "sg:city":"Turis",
    "sg:orig_category":"Producci\u00d3n, Comercio De Cereales",
    "sg:phone":"+34 962 52 60 17",
    "sg:postcode":"46389",
    "sg:province":"Valencia",
    "wof:name":"Cereales Diana S.l.",
    "wof:placetype":"venue"
},
  "geometry": {"coordinates":[-0.7117450237,39.3915214539],"type":"Point"}
}