{
  "type": "Feature",
  "properties": {
    "addr:full":"Avda Constitucion (la), 1 Alcala Guadaira Sevilla 41500",
    "addr:postcode":"41500",
    "addr:street":"Avda Constitucion La 1",
    "iso:country":"ES",
    "sg:address":"Avda Constitucion (la), 1",
    "sg:city":"Alcala Guadaira",
    "sg:orig_category":"Frutas, Legumbres Frescas Y Tempranas (al Por Menor)",
    "sg:phone":"+34 954 10 28 54",
    "sg:postcode":"41500",
    "sg:province":"Sevilla",
    "wof:name":"Campos Dominguez Ana",
    "wof:placetype":"venue"
},
  "geometry": {"coordinates":[-5.8442931175,37.3490104675],"type":"Point"}
}