{
  "type": "Feature",
  "properties": {
    "addr:full":"Calle de Alhambra, 1 Atarfe Granada 18230",
    "addr:housenumber":"1",
    "addr:postcode":"18230",
    "addr:street":"Calle De Alhambra",
    "iso:country":"ES",
    "sg:address":"Calle de Alhambra, 1",
    "sg:city":"Atarfe",
    "sg:orig_category":"Restaurantes",
    "sg:phone":"+34 958 43 79 13",
    "sg:postcode":"18230",
    "sg:province":"Granada",
    "wof:name":"Fernandez Martin Mercedes",
    "wof:placetype":"venue"
},
  "geometry": {"coordinates":[-3.6905779839,37.2231521606],"type":"Point"}
}