{
  "type": "Feature",
  "properties": {
    "iso:country":"ES",
    "sg:address":"Calle de Garay, 5",
    "sg:city":"Almunia De Do\u00e7a Godina",
    "sg:orig_category":"Iglesia Cat\u00d3lica",
    "sg:phone":"+34 976 60 08 91",
    "sg:postcode":"50100",
    "sg:province":"Zaragoza",
    "wof:name":"Parroquia Ntra Sra De La Asuncion",
    "wof:placetype":"venue"
},
  "geometry": {"coordinates":[-1.3744239807,41.4770240784],"type":"Point"}
}