{
  "type": "Feature",
  "properties": {
    "iso:country":"ES",
    "sg:address":"Avda Ramon Y Cajal, 14",
    "sg:city":"Bilbao",
    "sg:orig_category":"Locales Y Clases De Danza",
    "sg:phone":"+34 944 75 26 58",
    "sg:postcode":"48014",
    "sg:province":"Vizcaya",
    "wof:name":"Cabrera Solveira Maria Pilar",
    "wof:placetype":"venue"
},
  "geometry": {"coordinates":[-2.9435191154,43.2721786499],"type":"Point"}
}