{
  "type": "Feature",
  "properties": {
    "iso:country":"ES",
    "sg:address":"Calle de Iglesia (la), 6",
    "sg:city":"Bujaraloz",
    "sg:orig_category":"Quincaller\u00cda (al Por Menor)",
    "sg:phone":"+34 976 17 30 68",
    "sg:postcode":"50177",
    "sg:province":"Zaragoza",
    "wof:name":"Samper Flordelis Pilar",
    "wof:placetype":"venue"
},
  "geometry": {"coordinates":[-0.1537690014,41.4984016418],"type":"Point"}
}