{
  "type": "Feature",
  "properties": {
    "iso:country":"ES",
    "sg:address":"Calle de Hoyo De Esparteros, 9",
    "sg:city":"Malaga",
    "sg:orig_category":"Abogados",
    "sg:phone":"+34 952 21 29 02",
    "sg:postcode":"29005",
    "sg:province":"M\u00e1laga",
    "wof:name":"Perez Conejo Ceferino",
    "wof:placetype":"venue"
},
  "geometry": {"coordinates":[-4.4247989655,36.7181243896],"type":"Point"}
}