{
  "type": "Feature",
  "properties": {
    "addr:full":"Rua Bispo Varela Fondevila Y Verea, 20 Melide La Coru\u00f1a 15800",
    "addr:housenumber":"20",
    "addr:postcode":"15800",
    "addr:street":"Rua Bispo Varela Fondevila Y Verea;La Corun\u0303A",
    "iso:country":"ES",
    "sg:address":"Rua Bispo Varela Fondevila Y Verea, 20",
    "sg:city":"Melide",
    "sg:orig_category":"Productos Qu\u00cdmicos (fabricaci\u00d3n, Al Por Mayor)",
    "sg:phone":"+34 981 50 54 13",
    "sg:postcode":"15800",
    "sg:province":"La Coru\u00f1a",
    "wof:name":"Quimica Industrial Proquintas S.a.",
    "wof:placetype":"venue"
},
  "geometry": {"coordinates":[-8.010184288,42.9141578674],"type":"Point"}
}