{
  "type": "Feature",
  "properties": {
    "iso:country":"ES",
    "sg:address":"Avda Menendez Pelayo, 2",
    "sg:city":"Madrid",
    "sg:orig_category":"Delineantes",
    "sg:phone":"+34 917 81 12 44",
    "sg:postcode":"28009",
    "sg:province":"Madrid",
    "wof:name":"Union Castellana De Alimentacion",
    "wof:placetype":"venue"
},
  "geometry": {"coordinates":[-3.6800730228,40.421421051],"type":"Point"}
}