{
  "type": "Feature",
  "properties": {
    "iso:country":"ES",
    "sg:address":"Crta. Nal. 420, Km. 0166,0",
    "sg:city":"Argamasilla Calatrava",
    "sg:orig_category":"Fotocopias, Reprograf\u00cda",
    "sg:phone":"+34 926 47 81 82",
    "sg:postcode":"13440",
    "sg:province":"Ciudad Real",
    "wof:name":"Gonzalez De La Aleja Lopez Ramona",
    "wof:placetype":"venue"
},
  "geometry": {"coordinates":[-4.0790791512,38.7305603027],"type":"Point"}
}