{
  "type": "Feature",
  "properties": {
    "addr:full":"Calle de C, S/n Argamasilla Calatrava Ciudad Real 13440",
    "addr:housenumber":"s / n",
    "addr:postcode":"13440",
    "addr:street":"Calle De C",
    "iso:country":"ES",
    "sg:address":"Calle de C, S/n",
    "sg:city":"Argamasilla Calatrava",
    "sg:orig_category":"Animales (al Por Menor)",
    "sg:phone":"+34 926 47 83 05",
    "sg:postcode":"13440",
    "sg:province":"Ciudad Real",
    "wof:name":"Carnicas Madrigal S.l.",
    "wof:placetype":"venue"
},
  "geometry": {"coordinates":[-4.0888910294,38.7146034241],"type":"Point"}
}