{
  "type": "Feature",
  "properties": {
    "iso:country":"ES",
    "sg:address":"Calle de Profesor Lucena Conde, 10",
    "sg:city":"Cordoba",
    "sg:orig_category":"Doctores En Medicina",
    "sg:phone":"+34 957 40 26 66",
    "sg:postcode":"14012",
    "sg:province":"C\u00f3rdoba",
    "wof:name":"Herranz Ortega Jesus Jose",
    "wof:placetype":"venue"
},
  "geometry": {"coordinates":[-4.7836737633,37.8997764587],"type":"Point"}
}