{
  "type": "Feature",
  "properties": {
    "addr:full":"Luga Pe\u00d1ucal, 17 Quintueles Asturias 33314",
    "addr:housenumber":"17",
    "addr:postcode":"33314",
    "addr:street":"Pen\u0303Ucal;Asturias",
    "iso:country":"ES",
    "sg:address":"Luga Pe\u00d1ucal, 17",
    "sg:city":"Quintueles",
    "sg:orig_category":"Agencias Y Agentes Comerciales, Representantes",
    "sg:phone":"+34 985 89 48 67",
    "sg:postcode":"33314",
    "sg:province":"Asturias",
    "wof:name":"Martinez Garcia Jose Manuel",
    "wof:placetype":"venue"
},
  "geometry": {"coordinates":[-5.5745491982,43.5401992798],"type":"Point"}
}