{
  "type": "Feature",
  "properties": {
    "addr:full":"Avda Constitucion, 2 Merida Badajoz 06800",
    "addr:housenumber":"2",
    "addr:postcode":"06800",
    "addr:street":"Avda Constitucion",
    "iso:country":"ES",
    "sg:address":"Avda Constitucion, 2",
    "sg:city":"Merida",
    "sg:orig_category":"Agentes, Concesionarios Y Sucursales De Veh\u00cdculos",
    "sg:phone":"+34 924 37 19 60",
    "sg:postcode":"06800",
    "sg:province":"Badajoz",
    "wof:name":"Coliseo Movil, S.l.",
    "wof:placetype":"venue"
},
  "geometry": {"coordinates":[-6.3562850952,38.9114494324],"type":"Point"}
}