{
  "type": "Feature",
  "properties": {
    "addr:full":"Calle de Caputxins, 2 Alzira Valencia 46600",
    "addr:housenumber":"2",
    "addr:postcode":"46600",
    "addr:street":"Calle De Caputxins",
    "iso:country":"ES",
    "sg:address":"Calle de Caputxins, 2",
    "sg:city":"Alzira",
    "sg:orig_category":"Instalaci\u00d3n, Reparaci\u00d3n De Ascensores Y Montacargas",
    "sg:phone":"+34 962 40 57 53",
    "sg:postcode":"46600",
    "sg:province":"Valencia",
    "wof:name":"Division De Mantenimiento Tremon S.l.",
    "wof:placetype":"venue"
},
  "geometry": {"coordinates":[-0.438824594,39.1477966309],"type":"Point"}
}