{
  "type": "Feature",
  "properties": {
    "iso:country":"ES",
    "sg:address":"Av Guatemala, 16",
    "sg:city":"S. Andreu Barca",
    "sg:orig_category":"Ropa Para Ni\u00d1os (al Por Menor)",
    "sg:phone":"+34 936 82 25 45",
    "sg:postcode":"08740",
    "sg:province":"Barcelona",
    "wof:name":"Hurtado Martinez Maria",
    "wof:placetype":"venue"
},
  "geometry": {"coordinates":[1.9764200449,41.4477310181],"type":"Point"}
}