{
  "type": "Feature",
  "properties": {
    "iso:country":"ES",
    "sg:address":"Avgd Alameda Jaume I, 17",
    "sg:city":"Xativa",
    "sg:orig_category":"Arquitectos",
    "sg:phone":"+34 962 27 65 61",
    "sg:postcode":"46800",
    "sg:province":"Valencia",
    "wof:name":"Bolinches Roig Vicente",
    "wof:placetype":"venue"
},
  "geometry": {"coordinates":[-0.5237929821,38.9893226624],"type":"Point"}
}