{
  "type": "Feature",
  "properties": {
    "addr:full":"Calle de Entrepe\u00d1as, 35 Coru\u00d1a La Coru\u00f1a 15010",
    "addr:housenumber":"35",
    "addr:postcode":"15010",
    "addr:street":"Calle De Entrepen\u0303As;Corun\u0303A",
    "iso:country":"ES",
    "sg:address":"Calle de Entrepe\u00d1as, 35",
    "sg:city":"Coru\u00d1a",
    "sg:orig_category":"Molduras, Junquillos, Listones Y Molduras Perforadas",
    "sg:phone":"+34 981 27 94 39",
    "sg:postcode":"15010",
    "sg:province":"La Coru\u00f1a",
    "wof:name":"Aparecida Palmero Dulcinila",
    "wof:placetype":"venue"
},
  "geometry": {"coordinates":[-8.421245575,43.3630905151],"type":"Point"}
}