{
  "type": "Feature",
  "properties": {
    "addr:full":"Calle de Chorretones, 7 Cuellar Segovia 40200",
    "addr:housenumber":"7",
    "addr:postcode":"40200",
    "addr:street":"Calle De Chorretones",
    "iso:country":"ES",
    "sg:address":"Calle de Chorretones, 7",
    "sg:city":"Cuellar",
    "sg:orig_category":"Herboristas (al Por Menor)",
    "sg:phone":"+34 921 14 04 62",
    "sg:postcode":"40200",
    "sg:province":"Segovia",
    "wof:name":"Velasco Ojosnegros Maria Victoria",
    "wof:placetype":"venue"
},
  "geometry": {"coordinates":[-4.3114957809,41.3988189697],"type":"Point"}
}