{
  "type": "Feature",
  "properties": {
    "iso:country":"ES",
    "sg:address":"Carrer de Cremat, 22",
    "sg:city":"Terrassa",
    "sg:orig_category":"Ropa Para Se\u00d1oras (al Por Menor)",
    "sg:phone":"+34 937 33 63 95",
    "sg:postcode":"08221",
    "sg:province":"Barcelona",
    "sg:website":"www.ferrarferrer.com",
    "wof:name":"Euroris S.a.",
    "wof:placetype":"venue"
},
  "geometry": {"coordinates":[2.0102510452,41.5626411438],"type":"Point"}
}