{
  "type": "Feature",
  "properties": {
    "iso:country":"ES",
    "sg:address":"Calle de Ramon Y Cajal, 22",
    "sg:city":"Hellin",
    "sg:orig_category":"Agencias Y Agentes Comerciales, Representantes",
    "sg:phone":"+34 967 30 36 03",
    "sg:postcode":"02400",
    "sg:province":"Albacete",
    "wof:name":"Martinez Rodriguez Manuel",
    "wof:placetype":"venue"
},
  "geometry": {"coordinates":[-1.6886390448,38.5060386658],"type":"Point"}
}