{
  "type": "Feature",
  "properties": {
    "addr:full":"Calle de Trinidad, 23 Valverde Camino Huelva 21600",
    "addr:housenumber":"23",
    "addr:postcode":"21600",
    "addr:street":"Calle De Trinidad;Camino Huelva",
    "iso:country":"ES",
    "sg:address":"Calle de Trinidad, 23",
    "sg:city":"Valverde Camino",
    "sg:orig_category":"Medias Y Calcetines (al Por Menor)",
    "sg:phone":"+34 959 55 23 11",
    "sg:postcode":"21600",
    "sg:province":"Huelva",
    "sg:website":"www.moddo.com/moreno",
    "wof:name":"Moreno Arrayas Juan Manuel",
    "wof:placetype":"venue"
},
  "geometry": {"coordinates":[-6.7561979294,37.5725402832],"type":"Point"}
}