{
  "type": "Feature",
  "properties": {
    "addr:full":"Calle de Cucarro, 85 Almeria Almer\u00eda 04008",
    "addr:housenumber":"85",
    "addr:postcode":"04008",
    "addr:street":"Calle De Cucarro",
    "iso:country":"ES",
    "sg:address":"Calle de Cucarro, 85",
    "sg:city":"Almeria",
    "sg:orig_category":"Librer\u00cdas",
    "sg:phone":"+34 950 26 55 64",
    "sg:postcode":"04008",
    "sg:province":"Almer\u00eda",
    "wof:name":"Garcia Caballero Guillermo Gaston",
    "wof:placetype":"venue"
},
  "geometry": {"coordinates":[-2.4634621143,36.8478050232],"type":"Point"}
}