{
  "type": "Feature",
  "properties": {
    "addr:full":"Pg Ferrocarril, 339 Castelldefels Barcelona 08860",
    "addr:housenumber":"339",
    "addr:postcode":"08860",
    "addr:street":"Pg Ferrocarril",
    "iso:country":"ES",
    "sg:address":"Pg Ferrocarril, 339",
    "sg:city":"Castelldefels",
    "sg:orig_category":"Inform\u00c1tica: Mantenimiento Y Reparaci\u00d3n De Ordenadores",
    "sg:phone":"+34 936 64 64 21",
    "sg:postcode":"08860",
    "sg:province":"Barcelona",
    "wof:name":"As Software S.a.",
    "wof:placetype":"venue"
},
  "geometry": {"coordinates":[1.9746786356,41.2747154236],"type":"Point"}
}