{
  "type": "Feature",
  "properties": {
    "addr:full":"Calle de Trujillo, 10 Zorita C\u00e1ceres 10130",
    "addr:housenumber":"10",
    "addr:postcode":"10130",
    "addr:street":"Calle De Trujillo",
    "iso:country":"ES",
    "sg:address":"Calle de Trujillo, 10",
    "sg:city":"Zorita",
    "sg:orig_category":"Mercer\u00cda, Lencer\u00cda (al Por Menor)",
    "sg:phone":"+34 927 34 00 37",
    "sg:postcode":"10130",
    "sg:province":"C\u00e1ceres",
    "wof:name":"Fuentes Grande Fernando",
    "wof:placetype":"venue"
},
  "geometry": {"coordinates":[-5.699119091,39.2850036621],"type":"Point"}
}