{
  "type": "Feature",
  "properties": {
    "addr:full":"Calle de Pepin Rivero, 1 Coru\u00d1a La Coru\u00f1a 15011",
    "addr:housenumber":"1",
    "addr:postcode":"15011",
    "addr:street":"Calle De Pepin Rivero;La Corun\u0303A",
    "iso:country":"ES",
    "sg:address":"Calle de Pepin Rivero, 1",
    "sg:city":"Coru\u00d1a",
    "sg:classifiers":[
        {
            "category":"Personal",
            "subcategory":"Barber",
            "type":"Services"
        }
    ],
    "sg:phone":"+34 981 26 70 73",
    "sg:postcode":"15011",
    "sg:province":"La Coru\u00f1a",
    "sg:tags":[
        "caballeros",
        "de",
        "peluqueros"
    ],
    "wof:name":"Sanchez Sanchez Francisco",
    "wof:placetype":"venue"
},
  "geometry": {"coordinates":[-8.4230060577,43.3709487915],"type":"Point"}
}