{
  "type": "Feature",
  "properties": {
    "addr:full":"Calle de Pormetxeta, 15 Barakaldo Vizcaya 48901",
    "addr:housenumber":"15",
    "addr:postcode":"48901",
    "addr:street":"Calle De Pormetxeta",
    "iso:country":"ES",
    "sg:address":"Calle de Pormetxeta, 15",
    "sg:city":"Barakaldo",
    "sg:orig_category":"Empresas De Carpinter\u00cda Met\u00c1lica",
    "sg:phone":"+34 944 37 26 26",
    "sg:postcode":"48901",
    "sg:province":"Vizcaya",
    "wof:name":"Industrias Metalicas Baracaldo , C.b.",
    "wof:placetype":"venue"
},
  "geometry": {"coordinates":[-2.9832251072,43.2981948853],"type":"Point"}
}