{
  "type": "Feature",
  "properties": {
    "iso:country":"ES",
    "sg:address":"Calle de Cisterniga, 5",
    "sg:city":"Valladolid",
    "sg:orig_category":"Negocio De Materiales De Construcci\u00d3n",
    "sg:phone":"+34 983 20 96 41",
    "sg:postcode":"47005",
    "sg:province":"Valladolid",
    "wof:name":"Obeso Fernandez Maria Esther",
    "wof:placetype":"venue"
},
  "geometry": {"coordinates":[-4.7158064842,41.6469764709],"type":"Point"}
}