{
  "type": "Feature",
  "properties": {
    "addr:full":"Carrer de Prat De La Riba, 56 Viladecans Barcelona 08840",
    "addr:housenumber":"56",
    "addr:postcode":"08840",
    "addr:street":"Carrer De Prat De La Riba",
    "iso:country":"ES",
    "sg:address":"Carrer de Prat De La Riba, 56",
    "sg:city":"Viladecans",
    "sg:orig_category":"Inmobiliaria (agencias)",
    "sg:phone":"+34 936 59 21 80",
    "sg:postcode":"08840",
    "sg:province":"Barcelona",
    "wof:name":"Asto S.l.",
    "wof:placetype":"venue"
},
  "geometry": {"coordinates":[2.0095427036,41.3149719238],"type":"Point"}
}