{
  "type": "Feature",
  "properties": {
    "iso:country":"ES",
    "sg:address":"Luga Cala Llonga, 52",
    "sg:city":"Cala Llonga",
    "sg:orig_category":"Farmacias",
    "sg:phone":"+34 971 19 66 67",
    "sg:postcode":"07849",
    "sg:province":"Islas Baleares",
    "wof:name":"Soler Vidal Maria Josefa",
    "wof:placetype":"venue"
},
  "geometry": {"coordinates":[1.5182499886,38.9548492432],"type":"Point"}
}