{
  "type": "Feature",
  "properties": {
    "addr:full":"Avgd Alcalde Recasens, 47 Lleida Lleida 25005",
    "addr:housenumber":"47",
    "addr:postcode":"25005",
    "addr:street":"Alcalde Recasens",
    "iso:country":"ES",
    "sg:address":"Avgd Alcalde Recasens, 47",
    "sg:city":"Lleida",
    "sg:orig_category":"Peluqueros: De Se\u00d1oras",
    "sg:phone":"+34 973 24 27 40",
    "sg:postcode":"25005",
    "sg:province":"Lleida",
    "wof:name":"Puertas Peinado Angeles",
    "wof:placetype":"venue"
},
  "geometry": {"coordinates":[0.6226670146,41.6262702942],"type":"Point"}
}