{
  "type": "Feature",
  "properties": {
    "iso:country":"ES",
    "sg:address":"Carrer de Marina, 285",
    "sg:city":"Barcelona",
    "sg:orig_category":"Ingeniero",
    "sg:phone":"+34 934 33 55 11",
    "sg:postcode":"08025",
    "sg:province":"Barcelona",
    "sg:website":"www.sadect.com",
    "wof:name":"Sadect S. A.",
    "wof:placetype":"venue"
},
  "geometry": {"coordinates":[2.1725358963,41.4057502747],"type":"Point"}
}