{
  "type": "Feature",
  "properties": {
    "addr:full":"Avda Madrid (de), S/n Sanlucar De Barrameda C\u00e1diz 11540",
    "addr:housenumber":"/ n",
    "addr:postcode":"11540",
    "addr:street":"Avda Madrid De S;Ca\u0301Diz",
    "iso:country":"ES",
    "sg:address":"Avda Madrid (de), S/n",
    "sg:city":"Sanlucar De Barrameda",
    "sg:orig_category":"Institutos M\u00c9dicos",
    "sg:phone":"+34 956 38 17 57",
    "sg:postcode":"11540",
    "sg:province":"C\u00e1diz",
    "wof:name":"Servicio Andaluz De Salud",
    "wof:placetype":"venue"
},
  "geometry": {"coordinates":[-6.3528389931,36.76720047],"type":"Point"}
}