{
  "type": "Feature",
  "properties": {
    "iso:country":"ES",
    "sg:address":"Calle de Dalia (de La), 10",
    "sg:city":"Alcobendas",
    "sg:orig_category":"Arquitectos",
    "sg:phone":"+34 916 50 32 07",
    "sg:postcode":"28109",
    "sg:province":"Madrid",
    "wof:name":"Mico Perez De Diego Alvaro Pedro",
    "wof:placetype":"venue"
},
  "geometry": {"coordinates":[-3.6474196911,40.5190086365],"type":"Point"}
}