{
  "type": "Feature",
  "properties": {
    "iso:country":"ES",
    "sg:address":"Caserio De Cazulas, S/n",
    "sg:city":"Otivar",
    "sg:orig_category":"Cooperativas Agr\u00cdcolas",
    "sg:phone":"+34 958 64 50 58",
    "sg:postcode":"18698",
    "sg:province":"Granada",
    "wof:name":"Sociedad Cooperativa Del Campo De Cazulas",
    "wof:placetype":"venue"
},
  "geometry": {"coordinates":[-3.6809790134,36.8169250488],"type":"Point"}
}