{
  "type": "Feature",
  "properties": {
    "addr:full":"Calle de Infanta Mercedes, 98 Madrid Madrid 28020",
    "addr:housenumber":"98",
    "addr:postcode":"madrid;28020",
    "addr:street":"Calle De Infanta Mercedes",
    "iso:country":"ES",
    "sg:address":"Calle de Infanta Mercedes, 98",
    "sg:city":"Madrid",
    "sg:orig_category":"Inmobiliaria (agencias)",
    "sg:phone":"+34 915 79 55 96",
    "sg:postcode":"28020",
    "sg:province":"Madrid",
    "wof:name":"Inmobiliaria Camino De Las Berzosas S.l.",
    "wof:placetype":"venue"
},
  "geometry": {"coordinates":[-3.6929941177,40.4638290405],"type":"Point"}
}