{
  "type": "Feature",
  "properties": {
    "iso:country":"ES",
    "sg:address":"Avd Poeta M. Reina, 19",
    "sg:city":"Puente-genil",
    "sg:orig_category":"Agencias Y Asesores De Publicidad",
    "sg:phone":"+34 957 60 65 44",
    "sg:postcode":"14500",
    "sg:province":"C\u00f3rdoba",
    "wof:name":"Publimagen 2000 S.l.",
    "wof:placetype":"venue"
},
  "geometry": {"coordinates":[-4.7677721977,37.3913955688],"type":"Point"}
}