{
  "type": "Feature",
  "properties": {
    "iso:country":"ES",
    "sg:address":"Pg Miramar, 6",
    "sg:city":"Cambrils",
    "sg:orig_category":"Inmobiliaria (agencias)",
    "sg:phone":"+34 977 36 45 62",
    "sg:postcode":"43850",
    "sg:province":"Tarragona",
    "wof:name":"Hermanos Guibe S.a.",
    "wof:placetype":"venue"
},
  "geometry": {"coordinates":[1.0630249977,41.0657081604],"type":"Point"}
}