{
  "type": "Feature",
  "properties": {
    "addr:full":"Calle de San Millan, 41 San Lorenzo De El Escorial Madrid 28200",
    "addr:housenumber":"41",
    "addr:postcode":"28200",
    "addr:street":"Calle De San Millan",
    "iso:country":"ES",
    "sg:address":"Calle de San Millan, 41",
    "sg:city":"San Lorenzo De El Escorial",
    "sg:orig_category":"Plomeros",
    "sg:phone":"+34 918 90 29 03",
    "sg:postcode":"28200",
    "sg:province":"Madrid",
    "wof:name":"Soriano Martin Herranz S.l.",
    "wof:placetype":"venue"
},
  "geometry": {"coordinates":[-4.1480793953,40.5939598083],"type":"Point"}
}