{
  "type": "Feature",
  "properties": {
    "addr:full":"Calle de Benito Coll, 48 Binefar Huesca 22500",
    "addr:housenumber":"48",
    "addr:postcode":"22500",
    "addr:street":"Calle De Benito Coll",
    "iso:country":"ES",
    "sg:address":"Calle de Benito Coll, 48",
    "sg:city":"Binefar",
    "sg:orig_category":"Promotores Constructores",
    "sg:phone":"+34 974 43 09 17",
    "sg:postcode":"22500",
    "sg:province":"Huesca",
    "wof:name":"Perallon Plana Juan Jose",
    "wof:placetype":"venue"
},
  "geometry": {"coordinates":[0.299017787,41.8478851318],"type":"Point"}
}