{
  "type": "Feature",
  "properties": {
    "iso:country":"ES",
    "sg:address":"Ctra General Mao - Ciutadella, Km. 0039,8",
    "sg:city":"Tudons",
    "sg:orig_category":"Cr\u00cda De Animales",
    "sg:phone":"+34 971 48 00 20",
    "sg:postcode":"07760",
    "sg:province":"Islas Baleares",
    "wof:name":"Arenetas S.r.m.",
    "wof:placetype":"venue"
},
  "geometry": {"coordinates":[2.8577105999,39.5341796875],"type":"Point"}
}