{
  "type": "Feature",
  "properties": {
    "addr:full":"Calle de Urbieta, 66 Donostia-san Sebastian Guip\u00f9zcoa 20006",
    "addr:housenumber":"66",
    "addr:postcode":"20006",
    "addr:street":"Calle De Urbieta",
    "iso:country":"ES",
    "sg:address":"Calle de Urbieta, 66",
    "sg:city":"Donostia-san Sebastian",
    "sg:orig_category":"Agencias De Viajes",
    "sg:phone":"+34 943 45 29 18",
    "sg:postcode":"20006",
    "sg:province":"Guip\u00f9zcoa",
    "wof:name":"Savia Amadeus S.a.",
    "wof:placetype":"venue"
},
  "geometry": {"coordinates":[-1.9804749489,43.3135528564],"type":"Point"}
}