{
  "type": "Feature",
  "properties": {
    "iso:country":"ES",
    "sg:address":"Calle de Barquilla, 1",
    "sg:city":"Marbella",
    "sg:orig_category":"Iglesias Cristianas Diversas",
    "sg:phone":"+34 952 82 49 44",
    "sg:postcode":"29600",
    "sg:province":"M\u00e1laga",
    "wof:name":"Asociacion De Los Testigos Cristianos De Jehova",
    "wof:placetype":"venue"
},
  "geometry": {"coordinates":[-4.874671936,36.5103149414],"type":"Point"}
}