{
  "type": "Feature",
  "properties": {
    "addr:full":"Carrer de Cornella Modern, 34 Cornella Llobregat Barcelona 08940",
    "addr:housenumber":"34",
    "addr:postcode":"08940",
    "addr:street":"Carrer De;Modern",
    "iso:country":"ES",
    "sg:address":"Carrer de Cornella Modern, 34",
    "sg:city":"Cornella Llobregat",
    "sg:orig_category":"Iglesias Cristianas Diversas",
    "sg:phone":"+34 934 71 11 66",
    "sg:postcode":"08940",
    "sg:province":"Barcelona",
    "wof:name":"Testigos Cristianos De Jehova",
    "wof:placetype":"venue"
},
  "geometry": {"coordinates":[2.075026989,41.362537384],"type":"Point"}
}