{
  "type": "Feature",
  "properties": {
    "addr:full":"Calle de Belgica, 16 Zaragoza Zaragoza 50017",
    "addr:housenumber":"16",
    "addr:postcode":"50017",
    "addr:street":"Calle De Belgica",
    "iso:country":"ES",
    "sg:address":"Calle de Belgica, 16",
    "sg:city":"Zaragoza",
    "sg:orig_category":"Empresas De Impermeabilizaci\u00d3n",
    "sg:phone":"+34 976 34 69 92",
    "sg:postcode":"50017",
    "sg:province":"Zaragoza",
    "wof:name":"Arteaga Gracia Antonio",
    "wof:placetype":"venue"
},
  "geometry": {"coordinates":[-0.9062063098,41.6509475708],"type":"Point"}
}