{
  "type": "Feature",
  "properties": {
    "addr:full":"Calle de Aranjuez, S/n Alcala Henares Madrid 28805",
    "addr:housenumber":"s",
    "addr:postcode":"28805",
    "addr:street":"Calle De Aranjuez;/ N",
    "iso:country":"ES",
    "sg:address":"Calle de Aranjuez, S/n",
    "sg:city":"Alcala Henares",
    "sg:orig_category":"Inform\u00c1tica: Mantenimiento Y Reparaci\u00d3n De Ordenadores",
    "sg:phone":"+34 918 82 29 29",
    "sg:postcode":"28805",
    "sg:province":"Madrid",
    "wof:name":"Soluciones Informaticas Adv S.a.",
    "wof:placetype":"venue"
},
  "geometry": {"coordinates":[-3.3515443802,40.4939155579],"type":"Point"}
}