{
  "type": "Feature",
  "properties": {
    "iso:country":"ES",
    "sg:address":"Avda General Mola (del), 14",
    "sg:city":"Santa Cruz De Tenerife",
    "sg:orig_category":"Centros Comerciales Y Grandes Tiendas",
    "sg:phone":"+34 922 27 71 17",
    "sg:postcode":"38006",
    "sg:province":"Santa Cruz De Tenerife",
    "wof:name":"Mas Bertran Pedro",
    "wof:placetype":"venue"
},
  "geometry": {"coordinates":[-16.2632923126,28.4678554535],"type":"Point"}
}