{
  "type": "Feature",
  "properties": {
    "iso:country":"ES",
    "sg:address":"Calle de Alferez Baanante, 5",
    "sg:city":"Chantada",
    "sg:orig_category":"Carnicer\u00cdas, Carnicer\u00cdas",
    "sg:phone":"+34 982 46 21 72",
    "sg:postcode":"27500",
    "sg:province":"Lugo",
    "wof:name":"Meilan Pardo Jose Antonio",
    "wof:placetype":"venue"
},
  "geometry": {"coordinates":[-7.7960119247,42.6083450317],"type":"Point"}
}