{
  "type": "Feature",
  "properties": {
    "addr:full":"Trva San Mateo, 1 Madrid Madrid 28004",
    "addr:housenumber":"1",
    "addr:postcode":"28004",
    "addr:street":"Trva San Mateo",
    "iso:country":"ES",
    "sg:address":"Trva San Mateo, 1",
    "sg:city":"Madrid",
    "sg:orig_category":"Albergues",
    "sg:phone":"+34 913 10 24 92",
    "sg:postcode":"28004",
    "sg:province":"Madrid",
    "wof:name":"Lopez De Barrera Gomez Pedro",
    "wof:placetype":"venue"
},
  "geometry": {"coordinates":[-3.6984140873,40.4257698059],"type":"Point"}
}