{
  "type": "Feature",
  "properties": {
    "addr:full":"Calle de Lagrima, 19 Malaga M\u00e1laga 29014",
    "addr:housenumber":"19",
    "addr:postcode":"29014",
    "addr:street":"Calle De Lagrima;Ma\u0301Laga",
    "iso:country":"ES",
    "sg:address":"Calle de Lagrima, 19",
    "sg:city":"Malaga",
    "sg:orig_category":"Asociaciones Y Clubs Deportivos",
    "sg:phone":"+34 952 65 26 00",
    "sg:postcode":"29014",
    "sg:province":"M\u00e1laga",
    "wof:name":"Asociacion Deportiva Cortijillo Bazan",
    "wof:placetype":"venue"
},
  "geometry": {"coordinates":[-4.4152626991,36.7461280823],"type":"Point"}
}