{
  "type": "Feature",
  "properties": {
    "addr:full":"Av Constitucio, 152 Castelldefels Barcelona 08860",
    "addr:housenumber":"152",
    "addr:postcode":"08860",
    "addr:street":"Av Constitucio",
    "iso:country":"ES",
    "sg:address":"Av Constitucio, 152",
    "sg:city":"Castelldefels",
    "sg:orig_category":"Bisuter\u00cda, Joyer\u00cda, Relojer\u00cda (al Por Menor)",
    "sg:phone":"+34 936 65 23 45",
    "sg:postcode":"08860",
    "sg:province":"Barcelona",
    "wof:name":"Mendoza Marruedo Ramiro",
    "wof:placetype":"venue"
},
  "geometry": {"coordinates":[1.9777090549,41.2787704468],"type":"Point"}
}