{
  "type": "Feature",
  "properties": {
    "addr:full":"Carrer de Forn, 3 Sabadell Barcelona 08208",
    "addr:housenumber":"3",
    "addr:postcode":"08208",
    "addr:street":"Carrer De Forn",
    "iso:country":"ES",
    "sg:address":"Carrer de Forn, 3",
    "sg:city":"Sabadell",
    "sg:orig_category":"Aparcamientos (infraestructuras, Accesorios)",
    "sg:phone":"+34 937 25 23 28",
    "sg:postcode":"08208",
    "sg:province":"Barcelona",
    "wof:name":"Valls Moreto Francisco",
    "wof:placetype":"venue"
},
  "geometry": {"coordinates":[2.1046071053,41.5530471802],"type":"Point"}
}