{
  "type": "Feature",
  "properties": {
    "addr:full":"Calle de Calatayud, 1 Zaragoza Zaragoza 50005",
    "addr:housenumber":"1",
    "addr:postcode":"50005",
    "addr:street":"Calle De Calatayud",
    "iso:country":"ES",
    "sg:address":"Calle de Calatayud, 1",
    "sg:city":"Zaragoza",
    "sg:orig_category":"Dorados, Plater\u00cda (orfebrer\u00cda)",
    "sg:phone":"+34 976 30 14 44",
    "sg:postcode":"50005",
    "sg:province":"Zaragoza",
    "wof:name":"Sergio-concha S.l.",
    "wof:placetype":"venue"
},
  "geometry": {"coordinates":[-0.8920040131,41.645072937],"type":"Point"}
}