{
  "type": "Feature",
  "properties": {
    "iso:country":"ES",
    "sg:address":"Vva Cordoba, 15",
    "sg:city":"Pozoblanco",
    "sg:orig_category":"Maquinaria Para Industrias Diversas",
    "sg:phone":"+34 957 13 09 72",
    "sg:postcode":"14400",
    "sg:province":"C\u00f3rdoba",
    "wof:name":"Mansilla Y Morales S.l.",
    "wof:placetype":"venue"
},
  "geometry": {"coordinates":[-4.8547101021,38.3795509338],"type":"Point"}
}