{
  "type": "Feature",
  "properties": {
    "iso:country":"ES",
    "sg:address":"Calle de Moratin, 17",
    "sg:city":"Alacant",
    "sg:orig_category":"Promotores Constructores",
    "sg:phone":"+34 965 21 99 18",
    "sg:postcode":"03008",
    "sg:province":"Alicante",
    "sg:website":"www.grupoprasa.es",
    "wof:name":"Grupo Prasa",
    "wof:placetype":"venue"
},
  "geometry": {"coordinates":[-0.5224840045,38.2840309143],"type":"Point"}
}