{
  "type": "Feature",
  "properties": {
    "addr:full":"Calle de Isaac Albeniz, 7 Palacios Y Villafranca Sevilla 41720",
    "addr:housenumber":"7",
    "addr:postcode":"41720",
    "addr:street":"Calle De Isaac Albeniz",
    "iso:country":"ES",
    "sg:address":"Calle de Isaac Albeniz, 7",
    "sg:city":"Palacios Y Villafranca",
    "sg:orig_category":"Urbanistas",
    "sg:phone":"+34 955 81 06 98",
    "sg:postcode":"41720",
    "sg:province":"Sevilla",
    "wof:name":"Ponce Nu\u00f1ez Francisco Manuel",
    "wof:placetype":"venue"
},
  "geometry": {"coordinates":[-5.9228758812,37.1613922119],"type":"Point"}
}