{
  "type": "Feature",
  "properties": {
    "iso:country":"ES",
    "sg:address":"Avda Juan Xxiii, 36",
    "sg:city":"Jaca",
    "sg:orig_category":"Arquitectos",
    "sg:phone":"+34 974 36 06 23",
    "sg:postcode":"22700",
    "sg:province":"Huesca",
    "wof:name":"Mandado Collado Jesus",
    "wof:placetype":"venue"
},
  "geometry": {"coordinates":[-0.5519520044,42.5658493042],"type":"Point"}
}