{
  "type": "Feature",
  "properties": {
    "iso:country":"ES",
    "sg:address":"Calle de Doctor Fleming, 2",
    "sg:city":"Avila",
    "sg:orig_category":"Inmobiliaria (agencias)",
    "sg:phone":"+34 920 21 22 22",
    "sg:postcode":"05001",
    "sg:province":"\u00c1vila",
    "wof:name":"Camarasa S.l.",
    "wof:placetype":"venue"
},
  "geometry": {"coordinates":[-4.6937861443,40.6568031311],"type":"Point"}
}