{
  "type": "Feature",
  "properties": {
    "iso:country":"ES",
    "sg:address":"Ctra. Nacional V, Km. 0196,0",
    "sg:city":"Almaraz",
    "sg:orig_category":"Reparaciones Y Remolcado De Veh\u00cdculos",
    "sg:phone":"+34 927 54 43 11",
    "sg:postcode":"10350",
    "sg:province":"C\u00e1ceres",
    "wof:name":"Almagruas Internacional Sl",
    "wof:placetype":"venue"
},
  "geometry": {"coordinates":[-5.6773509979,39.7912712097],"type":"Point"}
}