{
  "type": "Feature",
  "properties": {
    "addr:full":"Carr Josep Grabulosa, 1 Santa Coloma De Farners Girona 17430",
    "addr:housenumber":"1",
    "addr:postcode":"17430",
    "addr:street":"Carr Josep Grabulosa",
    "iso:country":"ES",
    "sg:address":"Carr Josep Grabulosa, 1",
    "sg:city":"Santa Coloma De Farners",
    "sg:orig_category":"Florister\u00cdas",
    "sg:phone":"+34 972 84 15 02",
    "sg:postcode":"17430",
    "sg:province":"Girona",
    "wof:name":"Maynegra Frigole Jose",
    "wof:placetype":"venue"
},
  "geometry": {"coordinates":[2.6707110405,41.8583145142],"type":"Point"}
}