{
  "type": "Feature",
  "properties": {
    "addr:full":"Cmno Iglesia, 6 Arboleja Murcia 30009",
    "addr:housenumber":"6",
    "addr:postcode":"30009",
    "addr:street":"Cmno Iglesia",
    "iso:country":"ES",
    "sg:address":"Cmno Iglesia, 6",
    "sg:city":"Arboleja",
    "sg:orig_category":"Estilistas Y Estudios De Estilo De Corte Y Confecci\u00d3n",
    "sg:phone":"+34 968 29 45 88",
    "sg:postcode":"30009",
    "sg:province":"Murcia",
    "wof:name":"Zaragoza Lozano Mateo",
    "wof:placetype":"venue"
},
  "geometry": {"coordinates":[-1.1298867464,37.9834747314],"type":"Point"}
}