{
  "type": "Feature",
  "properties": {
    "addr:full":"Carretera La Peza, S/n Ba\u00d1os Granada 18517",
    "addr:housenumber":"s",
    "addr:postcode":"18517",
    "addr:street":"Carretera La Peza;/ N Ban\u0303Os",
    "iso:country":"ES",
    "sg:address":"Carretera La Peza, S/n",
    "sg:city":"Ba\u00d1os",
    "sg:orig_category":"Producci\u00d3n, Venta De Productos De Agricultura Biol\u00d3gica",
    "sg:phone":"+34 958 67 07 15",
    "sg:postcode":"18517",
    "sg:province":"Granada",
    "wof:name":"La Zajare\u00f1a S.l.",
    "wof:placetype":"venue"
},
  "geometry": {"coordinates":[-3.5979290009,37.176486969],"type":"Point"}
}