{
  "type": "Feature",
  "properties": {
    "addr:full":"Barro Iturrigorri, 6 Basauri Vizcaya 48970",
    "addr:housenumber":"6",
    "addr:postcode":"48970",
    "addr:street":"Iturrigorri",
    "iso:country":"ES",
    "sg:address":"Barro Iturrigorri, 6",
    "sg:city":"Basauri",
    "sg:classifiers":[
        {
            "category":"Banks & Credit Unions",
            "subcategory":"Bureau De Change",
            "type":"Services"
        }
    ],
    "sg:phone":"+34 944 49 15 55",
    "sg:postcode":"48970",
    "sg:province":"Vizcaya",
    "sg:tags":[
        "organismos",
        "control"
    ],
    "wof:name":"Margarita Ramirez Caballero",
    "wof:placetype":"venue"
},
  "geometry": {"coordinates":[-2.8870439529,43.2375488281],"type":"Point"}
}