{
  "type": "Feature",
  "properties": {
    "iso:country":"ES",
    "sg:address":"Calle de Los Trigales, 26",
    "sg:city":"Caceres",
    "sg:orig_category":"Cerrajer\u00cda, Ferrallista",
    "sg:phone":"+34 927 18 23 86",
    "sg:postcode":"10004",
    "sg:province":"C\u00e1ceres",
    "wof:name":"Borrella Castela Jose Carlos",
    "wof:placetype":"venue"
},
  "geometry": {"coordinates":[-6.3600058556,39.4991836548],"type":"Point"}
}