{
  "type": "Feature",
  "properties": {
    "iso:country":"ES",
    "sg:address":"Carrer de Gran De Sant Andreu, 124",
    "sg:city":"Barcelona",
    "sg:orig_category":"Cl\u00cdnicas Dentales",
    "sg:phone":"+34 932 74 12 36",
    "sg:postcode":"08030",
    "sg:province":"Barcelona",
    "wof:name":"Instituts Bucodentals De Barcelona S.l.",
    "wof:placetype":"venue"
},
  "geometry": {"coordinates":[2.1896760464,41.4309616089],"type":"Point"}
}