{
  "type": "Feature",
  "properties": {
    "addr:full":"Carr Guillem Timoner, S/n Felanitx Islas Baleares 07200",
    "addr:housenumber":"s",
    "addr:postcode":"07200",
    "addr:street":"Carr Guillem Timoner;/ N",
    "iso:country":"ES",
    "sg:address":"Carr Guillem Timoner, S/n",
    "sg:city":"Felanitx",
    "sg:orig_category":"Muebles Y Accesorios Para Cocinas Y Cuartos De Ba\u00d1o (al Por Menor)",
    "sg:phone":"+34 971 58 27 93",
    "sg:postcode":"07200",
    "sg:province":"Islas Baleares",
    "wof:name":"Cuinart Fel S.l.",
    "wof:placetype":"venue"
},
  "geometry": {"coordinates":[3.1435880661,39.470916748],"type":"Point"}
}