{
  "type": "Feature",
  "properties": {
    "iso:country":"ES",
    "sg:address":"Calle de Rayo, 4",
    "sg:city":"Dos Hermanas",
    "sg:orig_category":"Doctores En Medicina",
    "sg:phone":"+34 955 66 38 81",
    "sg:postcode":"41700",
    "sg:province":"Sevilla",
    "wof:name":"Bautista Lorite Andres",
    "wof:placetype":"venue"
},
  "geometry": {"coordinates":[-5.948056221,37.2817192078],"type":"Point"}
}