{
  "type": "Feature",
  "properties": {
    "iso:country":"ES",
    "sg:address":"Cmno Hormigueras, 119",
    "sg:city":"Madrid",
    "sg:orig_category":"Material Y Suministros Para Dentistas, Cirujanos",
    "sg:phone":"+34 913 03 68 63",
    "sg:postcode":"28031",
    "sg:province":"Madrid",
    "wof:name":"Incotrading S.a.",
    "wof:placetype":"venue"
},
  "geometry": {"coordinates":[-3.6453390121,40.3742599487],"type":"Point"}
}