{
  "type": "Feature",
  "properties": {
    "iso:country":"ES",
    "sg:address":"Calle de Pescaderia, 3",
    "sg:city":"Jaen",
    "sg:orig_category":"Estudios Y Construcci\u00d3n De Acuarios Y Viveros",
    "sg:phone":"+34 953 24 26 03",
    "sg:postcode":"23001",
    "sg:province":"Ja\u00e9n",
    "wof:name":"Viedma Lopez Rafael",
    "wof:placetype":"venue"
},
  "geometry": {"coordinates":[-3.7887270451,37.7668457031],"type":"Point"}
}