{
  "type": "Feature",
  "properties": {
    "iso:country":"ES",
    "sg:address":"Calle de Uria, 6",
    "sg:city":"Gijon",
    "sg:orig_category":"Agentes Generales De Seguros",
    "sg:phone":"+34 985 36 13 49",
    "sg:postcode":"33202",
    "sg:province":"Asturias",
    "wof:name":"Tomas Amado Correduria De Seguros S.l.",
    "wof:placetype":"venue"
},
  "geometry": {"coordinates":[-5.656867981,43.5390357971],"type":"Point"}
}