{
  "type": "Feature",
  "properties": {
    "iso:country":"ES",
    "sg:address":"Calle de San Luis Gonzaga, 7",
    "sg:city":"Alaquas",
    "sg:orig_category":"Reposter\u00cdas",
    "sg:phone":"+34 961 98 53 51",
    "sg:postcode":"46970",
    "sg:province":"Valencia",
    "wof:name":"Piqueras Barbera Pedro Miguel",
    "wof:placetype":"venue"
},
  "geometry": {"coordinates":[-0.4653098881,39.4552879333],"type":"Point"}
}