{
  "type": "Feature",
  "properties": {
    "iso:country":"ES",
    "sg:address":"Calle de San Isidro, 63",
    "sg:city":"Valladolid",
    "sg:orig_category":"Librer\u00cdas",
    "sg:phone":"+34 983 29 04 76",
    "sg:postcode":"47012",
    "sg:province":"Valladolid",
    "wof:name":"Domingo De Isabel Angel Alberto",
    "wof:placetype":"venue"
},
  "geometry": {"coordinates":[-4.7137718201,41.6438674927],"type":"Point"}
}