{
  "type": "Feature",
  "properties": {
    "iso:country":"ES",
    "sg:address":"Calle de Rui Perez, 8",
    "sg:city":"Aviles",
    "sg:orig_category":"Ropa Para Caballeros (al Por Menor)",
    "sg:phone":"+34 985 56 10 81",
    "sg:postcode":"33402",
    "sg:province":"Asturias",
    "wof:name":"Gonzalez Fernandez Agustin",
    "wof:placetype":"venue"
},
  "geometry": {"coordinates":[-5.9238548279,43.5577011108],"type":"Point"}
}