{
  "type": "Feature",
  "properties": {
    "iso:country":"ES",
    "sg:address":"Calle de Mayor, 45",
    "sg:city":"Puente Tocinos",
    "sg:orig_category":"Automatizaci\u00d3n De Procesos Industriales Y De Edificaci\u00d3n (estudios, Instalaci\u00d3n)",
    "sg:phone":"+34 968 23 58 03",
    "sg:postcode":"30006",
    "sg:province":"Murcia",
    "wof:name":"Tecnologias Electricas Mediterraneas S.l.",
    "wof:placetype":"venue"
},
  "geometry": {"coordinates":[-1.1058169603,37.9923324585],"type":"Point"}
}