{
  "type": "Feature",
  "properties": {
    "addr:full":"Calle de Hurtado De Amezaga, 27 Bilbao Vizcaya 48008",
    "addr:housenumber":"27",
    "addr:postcode":"48008",
    "addr:street":"Calle De Hurtado De Amezaga",
    "iso:country":"ES",
    "sg:address":"Calle de Hurtado De Amezaga, 27",
    "sg:city":"Bilbao",
    "sg:orig_category":"Prot\u00c9sicos Dentales",
    "sg:phone":"+34 944 21 44 53",
    "sg:postcode":"48008",
    "sg:province":"Vizcaya",
    "wof:name":"Anabitarte Labaca Joaquin Maria",
    "wof:placetype":"venue"
},
  "geometry": {"coordinates":[-2.9307403564,43.2592430115],"type":"Point"}
}