{
  "type": "Feature",
  "properties": {
    "addr:full":"Carr Carlos Sarthou, 4 Xativa Valencia 46800",
    "addr:housenumber":"4",
    "addr:postcode":"46800",
    "addr:street":"Carr Carlos Sarthou",
    "iso:country":"ES",
    "sg:address":"Carr Carlos Sarthou, 4",
    "sg:city":"Xativa",
    "sg:orig_category":"Centros P\u00dablicos De Formaci\u00d3n Profesional Y T\u00c9cnica",
    "sg:phone":"+34 962 28 19 33",
    "sg:postcode":"46800",
    "sg:province":"Valencia",
    "wof:name":"Colegio Oficial De Arquitectos De La Comunidad De Valencia",
    "wof:placetype":"venue"
},
  "geometry": {"coordinates":[-0.5215700269,38.9907608032],"type":"Point"}
}