{
  "type": "Feature",
  "properties": {
    "addr:full":"Els Sombrerers, 3 P.i. Masia Del Juez Valencia 46900",
    "addr:housenumber":"3",
    "addr:postcode":"46900",
    "addr:street":"Sombrerers;P.I. Masia Del Juez",
    "iso:country":"ES",
    "sg:address":"Els Sombrerers, 3",
    "sg:city":"P.i. Masia Del Juez",
    "sg:orig_category":"Fabricaci\u00d3n De Revestimientos De Suelos Pl\u00c1sticos Y De Goma",
    "sg:phone":"+34 961 57 31 37",
    "sg:postcode":"46900",
    "sg:province":"Valencia",
    "wof:name":"Gomez Bonet Jose",
    "wof:placetype":"venue"
},
  "geometry": {"coordinates":[-0.4623290002,39.441619873],"type":"Point"}
}