{
  "type": "Feature",
  "properties": {
    "iso:country":"ES",
    "sg:address":"Carrer de Ferran Valls I Taberner, 20",
    "sg:city":"Barcelona",
    "sg:orig_category":"M\u00c9dicos: Gastroenterolog\u00cda Y Hepatolog\u00cda (aparato Digestivo)",
    "sg:phone":"+34 934 17 43 59",
    "sg:postcode":"08006",
    "sg:province":"Barcelona",
    "wof:name":"Mu\u00f1oz Benitez Jose Maria",
    "wof:placetype":"venue"
},
  "geometry": {"coordinates":[2.1409599781,41.4034996033],"type":"Point"}
}