{
  "type": "Feature",
  "properties": {
    "iso:country":"ES",
    "sg:address":"Calle de Geranio, 27",
    "sg:city":"Puebla Alfinden",
    "sg:orig_category":"Material Y Suministros Para Perforaciones, Sondeos",
    "sg:phone":"+34 976 10 82 27",
    "sg:postcode":"50171",
    "sg:province":"Zaragoza",
    "wof:name":"Talleres Pcj S.l.",
    "wof:placetype":"venue"
},
  "geometry": {"coordinates":[-0.7687630057,41.6391067505],"type":"Point"}
}