{
  "type": "Feature",
  "properties": {
    "addr:full":"Calle de Rafael Alberti, 64 Almoradi Alicante 03160",
    "addr:housenumber":"64",
    "addr:postcode":"03160",
    "addr:street":"Calle De Rafael Alberti",
    "iso:country":"ES",
    "sg:address":"Calle de Rafael Alberti, 64",
    "sg:city":"Almoradi",
    "sg:orig_category":"Sociedades, Compa\u00d1\u00cdas Aseguradoras",
    "sg:phone":"+34 965 70 08 47",
    "sg:postcode":"03160",
    "sg:province":"Alicante",
    "wof:name":"Navarro Ruiz Jose",
    "wof:placetype":"venue"
},
  "geometry": {"coordinates":[-0.796167016,38.1081390381],"type":"Point"}
}