{
  "type": "Feature",
  "properties": {
    "iso:country":"ES",
    "sg:address":"Plaz Castilla Y Leon, 3",
    "sg:city":"Valladolid",
    "sg:orig_category":"Abogados",
    "sg:phone":"+34 983 24 41 48",
    "sg:postcode":"47008",
    "sg:province":"Valladolid",
    "wof:name":"Diez Roig Jesus Maria",
    "wof:placetype":"venue"
},
  "geometry": {"coordinates":[-4.7518978119,41.6105690002],"type":"Point"}
}