{
  "type": "Feature",
  "properties": {
    "iso:country":"ES",
    "sg:address":"Otero De Bodas, S/n",
    "sg:city":"Ferreras Arriba",
    "sg:orig_category":"Empresas De Carpinter\u00cda Met\u00c1lica",
    "sg:phone":"+34 980 59 30 67",
    "sg:postcode":"49335",
    "sg:province":"Zamora",
    "wof:name":"Carpinteria Metalica Peral S.l.",
    "wof:placetype":"venue"
},
  "geometry": {"coordinates":[-6.1929039955,41.898979187],"type":"Point"}
}