{
  "type": "Feature",
  "properties": {
    "addr:full":"Pg Carme, 36 Vilanova I La Geltru Barcelona 08800",
    "addr:housenumber":"36",
    "addr:postcode":"08800",
    "addr:street":"Pg Carme",
    "iso:country":"ES",
    "sg:address":"Pg Carme, 36",
    "sg:city":"Vilanova I La Geltru",
    "sg:orig_category":"Restaurantes",
    "sg:phone":"+34 938 15 15 78",
    "sg:postcode":"08800",
    "sg:province":"Barcelona",
    "wof:name":"Ca\u00f1amero Ortiz Andres",
    "wof:placetype":"venue"
},
  "geometry": {"coordinates":[1.7275400162,41.2152290344],"type":"Point"}
}