{
  "type": "Feature",
  "properties": {
    "addr:full":"Avda Boliches De Los, 15 Fuengirola M\u00e1laga 29640",
    "addr:postcode":"29640",
    "addr:street":"Avda Boliches De Los;Ma\u0301Laga",
    "iso:country":"ES",
    "sg:address":"Avda Boliches De Los, 15",
    "sg:city":"Fuengirola",
    "sg:orig_category":"Empresas De Vigilancia, Guardia Y Protecci\u00d3n",
    "sg:phone":"+34 952 47 22 81",
    "sg:postcode":"29640",
    "sg:province":"M\u00e1laga",
    "wof:name":"Starprotec S.l.",
    "wof:placetype":"venue"
},
  "geometry": {"coordinates":[-4.6129088402,36.5560112],"type":"Point"}
}