{
  "type": "Feature",
  "properties": {
    "addr:full":"Carr Jueus, 9 Seu D'urgell Lleida 25700",
    "addr:housenumber":"9",
    "addr:postcode":"25700",
    "addr:street":"Carr Jueus",
    "iso:country":"ES",
    "sg:address":"Carr Jueus, 9",
    "sg:city":"Seu D'urgell",
    "sg:orig_category":"Inmobiliaria (agencias)",
    "sg:phone":"+34 973 35 55 77",
    "sg:postcode":"25700",
    "sg:province":"Lleida",
    "wof:name":"Ferrer Majoral Francesc Xavier",
    "wof:placetype":"venue"
},
  "geometry": {"coordinates":[0.6457189918,41.6027946472],"type":"Point"}
}