{
  "type": "Feature",
  "properties": {
    "iso:country":"ES",
    "sg:address":"Calle de Cristo Rey, 7",
    "sg:city":"Jaen",
    "sg:orig_category":"Arquitectos",
    "sg:phone":"+34 953 27 63 61",
    "sg:postcode":"23007",
    "sg:province":"Ja\u00e9n",
    "wof:name":"Pajares Gutierrez Francisco Javier",
    "wof:placetype":"venue"
},
  "geometry": {"coordinates":[-3.7900805473,37.7744216919],"type":"Point"}
}