{
  "type": "Feature",
  "properties": {
    "addr:full":"Moble, S/n Beniparrell Valencia 46469",
    "addr:housenumber":"moble s / n",
    "addr:postcode":"46469",
    "iso:country":"ES",
    "sg:address":"Moble, S/n",
    "sg:city":"Beniparrell",
    "sg:orig_category":"Comercio De Muebles De Estilo Y Contempor\u00c1neos",
    "sg:phone":"+34 961 21 05 54",
    "sg:postcode":"46469",
    "sg:province":"Valencia",
    "wof:name":"Proyecto Silleros S.l.",
    "wof:placetype":"venue"
},
  "geometry": {"coordinates":[-0.4141589999,39.386428833],"type":"Point"}
}