{
  "type": "Feature",
  "properties": {
    "iso:country":"ES",
    "sg:address":"Calle de Marques Del Muni, 18",
    "sg:city":"Santa Maria De Guia",
    "sg:orig_category":"Imprenta",
    "sg:phone":"+34 928 88 00 94",
    "sg:postcode":"35450",
    "sg:province":"Las Palmas",
    "wof:name":"Diaz Gonzalez Reyes",
    "wof:placetype":"venue"
},
  "geometry": {"coordinates":[-15.6324386597,28.1398906708],"type":"Point"}
}