{
  "type": "Feature",
  "properties": {
    "iso:country":"ES",
    "sg:address":"Avda Santander (de) (herrera), 62",
    "sg:city":"Herrera",
    "sg:orig_category":"Art\u00cdculos De Aluminio",
    "sg:phone":"+34 942 25 00 94",
    "sg:postcode":"39608",
    "sg:province":"Cantabria",
    "wof:name":"Climaplas S. L.",
    "wof:placetype":"venue"
},
  "geometry": {"coordinates":[-3.8830139637,43.4323272705],"type":"Point"}
}