{
  "type": "Feature",
  "properties": {
    "addr:full":"Rbla Passeig, 65 Vic Barcelona 08500",
    "addr:housenumber":"65",
    "addr:postcode":"08500",
    "addr:street":"Passeig",
    "iso:country":"ES",
    "sg:address":"Rbla Passeig, 65",
    "sg:city":"Vic",
    "sg:orig_category":"Ortopedia General",
    "sg:phone":"+34 938 86 17 20",
    "sg:postcode":"08500",
    "sg:province":"Barcelona",
    "wof:name":"Aparells Ortopedics Curto S. L.",
    "wof:placetype":"venue"
},
  "geometry": {"coordinates":[2.2579519749,41.9298477173],"type":"Point"}
}