{
  "type": "Feature",
  "properties": {
    "addr:full":"Ctra Cordoba-malaga, 447 Montilla C\u00f3rdoba 14550",
    "addr:housenumber":"447",
    "addr:postcode":"14550",
    "addr:street":"Ctra Cordoba-Malaga;Co\u0301Rdoba",
    "iso:country":"ES",
    "sg:address":"Ctra Cordoba-malaga, 447",
    "sg:city":"Montilla",
    "sg:orig_category":"Transportes Por V\u00cdas Navegables",
    "sg:phone":"+34 957 65 12 06",
    "sg:postcode":"14550",
    "sg:province":"C\u00f3rdoba",
    "wof:name":"Gruas Y Contenedores Migamar S.l.",
    "wof:placetype":"venue"
},
  "geometry": {"coordinates":[-4.6535210609,37.5716629028],"type":"Point"}
}