{
  "type": "Feature",
  "properties": {
    "iso:country":"ES",
    "sg:address":"Cmno Viejo De Silla, S/n",
    "sg:city":"Albal",
    "sg:orig_category":"Afilado",
    "sg:phone":"+34 961 26 21 62",
    "sg:postcode":"46470",
    "sg:province":"Valencia",
    "wof:name":"Tres G Utiles Del Mediterraneo S.l.",
    "wof:placetype":"venue"
},
  "geometry": {"coordinates":[-0.4010640085,39.3901252747],"type":"Point"}
}