{
  "type": "Feature",
  "properties": {
    "addr:full":"Carrer de Alcarria, 22 Sabadell Barcelona 08207",
    "addr:housenumber":"22",
    "addr:postcode":"08207",
    "addr:street":"Carrer De Alcarria",
    "iso:country":"ES",
    "sg:address":"Carrer de Alcarria, 22",
    "sg:city":"Sabadell",
    "sg:orig_category":"Peluquer\u00cdas, Peluquer\u00cda Mixta",
    "sg:phone":"+34 937 17 94 18",
    "sg:postcode":"08207",
    "sg:province":"Barcelona",
    "wof:name":"Casado Belda Ana",
    "wof:placetype":"venue"
},
  "geometry": {"coordinates":[2.0950989723,41.5655097961],"type":"Point"}
}