{
  "type": "Feature",
  "properties": {
    "addr:full":"Calle de Angel Mugica, 7 Madrid Madrid 28034",
    "addr:housenumber":"7",
    "addr:postcode":"madrid;28034",
    "addr:street":"Calle De Angel Mugica",
    "iso:country":"ES",
    "sg:address":"Calle de Angel Mugica, 7",
    "sg:city":"Madrid",
    "sg:orig_category":"Ense\u00d1anza Variada",
    "sg:phone":"+34 913 58 40 38",
    "sg:postcode":"28034",
    "sg:province":"Madrid",
    "wof:name":"Barroso Perez Fernando",
    "wof:placetype":"venue"
},
  "geometry": {"coordinates":[-3.6855680943,40.4853019714],"type":"Point"}
}