{
  "type": "Feature",
  "properties": {
    "iso:country":"ES",
    "sg:address":"Calle de Caballero De Rodas, 113",
    "sg:city":"Torrevieja",
    "sg:orig_category":"Asesor\u00cda Sobre Comunicaci\u00d3n De Empresas",
    "sg:phone":"+34 965 70 59 62",
    "sg:postcode":"03180",
    "sg:province":"Alicante",
    "sg:website":"www.ribeiroymontesinos.com",
    "wof:name":"Ribeiro Y Montesinos Asesores S.l",
    "wof:placetype":"venue"
},
  "geometry": {"coordinates":[-0.6778293252,37.9780731201],"type":"Point"}
}