{
  "type": "Feature",
  "properties": {
    "iso:country":"ES",
    "sg:address":"Calle de Sepulcro, 19",
    "sg:city":"Cartagena",
    "sg:orig_category":"Reposter\u00cdas",
    "sg:phone":"+34 968 50 31 63",
    "sg:postcode":"30202",
    "sg:province":"Murcia",
    "wof:name":"Segado Panaderia Y Confiteria S.l.",
    "wof:placetype":"venue"
},
  "geometry": {"coordinates":[-0.9711790085,37.5987701416],"type":"Point"}
}