{
  "type": "Feature",
  "properties": {
    "iso:country":"ES",
    "sg:address":"Carrer de Sancho De Avila, 178",
    "sg:city":"Barcelona",
    "sg:orig_category":"Centros De Coordinaci\u00d3n",
    "sg:phone":"+34 933 20 84 44",
    "sg:postcode":"08018",
    "sg:province":"Barcelona",
    "sg:website":"www.asesorialemasa.com",
    "wof:name":"Asesoria Lemasa",
    "wof:placetype":"venue"
},
  "geometry": {"coordinates":[2.1965754032,41.403591156],"type":"Point"}
}