{
  "type": "Feature",
  "properties": {
    "addr:full":"Las Ventas, S/n Somo Cantabria 39140",
    "addr:housenumber":"s / n",
    "addr:postcode":"39140",
    "addr:street":"Las Ventas",
    "iso:country":"ES",
    "sg:address":"Las Ventas, S/n",
    "sg:city":"Somo",
    "sg:orig_category":"Bazares, Art\u00cdculos De Limpieza Y De Cocina (al Por Menor)",
    "sg:phone":"+34 942 51 01 95",
    "sg:postcode":"39140",
    "sg:province":"Cantabria",
    "wof:name":"Somo Tiempo Libre S.c.",
    "wof:placetype":"venue"
},
  "geometry": {"coordinates":[-3.739757061,43.4527320862],"type":"Point"}
}