{
  "type": "Feature",
  "properties": {
    "iso:country":"ES",
    "sg:address":"Pase Conde De Los Gaitanes (del), 51",
    "sg:city":"Alcobendas",
    "sg:orig_category":"Organizaci\u00d3n De Actos, Seminarios Y Congresos",
    "sg:phone":"+34 916 25 25 20",
    "sg:postcode":"28109",
    "sg:province":"Madrid",
    "sg:website":"www.lamorelejabusinessresort.es",
    "wof:name":"La Moraleja Business Resort S. L.",
    "wof:placetype":"venue"
},
  "geometry": {"coordinates":[-3.6279110909,40.5232124329],"type":"Point"}
}