{
  "type": "Feature",
  "properties": {
    "addr:full":"Av Pais Valencia, 33 Elche Alicante 03201",
    "addr:housenumber":"33",
    "addr:postcode":"03201",
    "addr:street":"Av Pais Valencia",
    "iso:country":"ES",
    "sg:address":"Av Pais Valencia, 33",
    "sg:city":"Elche",
    "sg:orig_category":"Asesor\u00cda Fiscal Y Jur\u00cddica",
    "sg:phone":"+34 966 66 55 91",
    "sg:postcode":"03201",
    "sg:province":"Alicante",
    "wof:name":"Salvador Campos Asesor Auditor S.l.",
    "wof:placetype":"venue"
},
  "geometry": {"coordinates":[-0.7004609704,38.2687416077],"type":"Point"}
}