{
  "type": "Feature",
  "properties": {
    "iso:country":"ES",
    "sg:address":"Avda San Sebastian, 51",
    "sg:city":"Santa Cruz De Tenerife",
    "sg:orig_category":"Poller\u00cda Y Caza (al Por Menor)",
    "sg:phone":"+34 922 22 03 10",
    "sg:postcode":"38003",
    "sg:province":"Santa Cruz De Tenerife",
    "wof:name":"Alonso Morales Lucia Sotera",
    "wof:placetype":"venue"
},
  "geometry": {"coordinates":[-16.252243042,28.4637069702],"type":"Point"}
}