{
  "type": "Feature",
  "properties": {
    "iso:country":"ES",
    "sg:address":"Av Gran Via De Valencia, 1",
    "sg:city":"Mutxamel",
    "sg:orig_category":"Carnicer\u00cdas, Carnicer\u00cdas",
    "sg:phone":"+34 965 95 40 48",
    "sg:postcode":"03110",
    "sg:province":"Alicante",
    "wof:name":"Jurado Torrico Gabriel",
    "wof:placetype":"venue"
},
  "geometry": {"coordinates":[-0.4461979866,38.4179153442],"type":"Point"}
}