{
  "type": "Feature",
  "properties": {
    "iso:country":"ES",
    "sg:address":"Calle de Alozaina, 16",
    "sg:city":"Yunquera",
    "sg:classifiers":[
        {
            "category":"Taxi",
            "type":"Transportation"
        }
    ],
    "sg:phone":"+34 952 48 27 36",
    "sg:postcode":"29410",
    "sg:province":"M\u00e1laga",
    "wof:name":"Rivas Diaz Juan",
    "wof:placetype":"venue"
},
  "geometry": {"coordinates":[-4.9166750908,36.7316360474],"type":"Point"}
}