{
  "type": "Feature",
  "properties": {
    "iso:country":"ES",
    "sg:address":"Eix Transversal, Km. 0111,5",
    "sg:city":"Sant Pere Sallavinera",
    "sg:orig_category":"Producci\u00d3n, Distribuci\u00d3n De Gas Butano Y Propano",
    "sg:phone":"+34 938 68 04 31",
    "sg:postcode":"08281",
    "sg:province":"Barcelona",
    "wof:name":"Repsol Ypf S.a.",
    "wof:placetype":"venue"
},
  "geometry": {"coordinates":[1.5431449413,41.7850608826],"type":"Point"}
}