{
  "type": "Feature",
  "properties": {
    "iso:country":"ES",
    "sg:address":"Calle de Urkizuaran, 15",
    "sg:city":"Elorrio",
    "sg:orig_category":"Promotores Constructores",
    "sg:phone":"+34 946 58 23 66",
    "sg:postcode":"48230",
    "sg:province":"Vizcaya",
    "wof:name":"Construcciones Iralgi S.l.",
    "wof:placetype":"venue"
},
  "geometry": {"coordinates":[-2.5379109383,43.1265068054],"type":"Point"}
}