{
  "type": "Feature",
  "properties": {
    "addr:full":"Luga Poligono Industrial, 16 Cabanillas Campo Guadalajara 19171",
    "addr:housenumber":"16",
    "addr:postcode":"19171",
    "addr:street":"Poligono Industrial",
    "iso:country":"ES",
    "sg:address":"Luga Poligono Industrial, 16",
    "sg:city":"Cabanillas Campo",
    "sg:orig_category":"Venta Y Colocaci\u00d3n De Techos, Falsos Techos",
    "sg:phone":"+34 949 20 27 72",
    "sg:postcode":"19171",
    "sg:province":"Guadalajara",
    "wof:name":"Decoracion Escayolas Guadalajara S.a.",
    "wof:placetype":"venue"
},
  "geometry": {"coordinates":[-3.2374420166,40.6377639771],"type":"Point"}
}