{
  "type": "Feature",
  "properties": {
    "addr:full":"Avda Baunatal (de), 21 San Sebastian De Los Reyes Madrid 28700",
    "addr:housenumber":"21",
    "addr:postcode":"28700",
    "addr:street":"Avda Baunatal De",
    "iso:country":"ES",
    "sg:address":"Avda Baunatal (de), 21",
    "sg:city":"San Sebastian De Los Reyes",
    "sg:orig_category":"Torrefactado De Caf\u00c9",
    "sg:phone":"+34 916 63 97 23",
    "sg:postcode":"28700",
    "sg:province":"Madrid",
    "wof:name":"Sanz Santacruz Carlos",
    "wof:placetype":"venue"
},
  "geometry": {"coordinates":[-3.6329259872,40.5538330078],"type":"Point"}
}