{
  "type": "Feature",
  "properties": {
    "addr:full":"Carrer de Joan Maragall, 4 Sitges Barcelona 08870",
    "addr:housenumber":"4",
    "addr:postcode":"08870",
    "addr:street":"Carrer De Joan Maragall",
    "iso:country":"ES",
    "sg:address":"Carrer de Joan Maragall, 4",
    "sg:city":"Sitges",
    "sg:orig_category":"Pod\u00d3logos: Pedicuros",
    "sg:phone":"+34 938 94 90 55",
    "sg:postcode":"08870",
    "sg:province":"Barcelona",
    "wof:name":"Matas Montane Maria Concepcion",
    "wof:placetype":"venue"
},
  "geometry": {"coordinates":[1.812844038,41.2369384766],"type":"Point"}
}