{
  "type": "Feature",
  "properties": {
    "iso:country":"ES",
    "sg:address":"Calle de Joaquina Eguaras, 8",
    "sg:city":"Granada",
    "sg:orig_category":"Peluqueros: De Se\u00d1oras",
    "sg:phone":"+34 958 15 71 45",
    "sg:postcode":"18013",
    "sg:province":"Granada",
    "wof:name":"Collado Romero Maria Luisa",
    "wof:placetype":"venue"
},
  "geometry": {"coordinates":[-3.6122889519,37.2067184448],"type":"Point"}
}