{
  "type": "Feature",
  "properties": {
    "addr:full":"Calle de Mayor, 1 Donostia-san Sebastian Guip\u00f9zcoa 20003",
    "addr:housenumber":"1",
    "addr:postcode":"20003",
    "addr:street":"Calle De Mayor",
    "iso:country":"ES",
    "sg:address":"Calle de Mayor, 1",
    "sg:city":"Donostia-san Sebastian",
    "sg:orig_category":"Juegos Y Juguetes (al Por Menor)",
    "sg:phone":"+34 943 42 71 94",
    "sg:postcode":"20003",
    "sg:province":"Guip\u00f9zcoa",
    "wof:name":"Mari Angeles Cruciegui, S.l.",
    "wof:placetype":"venue"
},
  "geometry": {"coordinates":[-1.9856599569,43.3221588135],"type":"Point"}
}