{
  "type": "Feature",
  "properties": {
    "iso:country":"ES",
    "sg:address":"Rcial Parque Aracena, 23",
    "sg:city":"Aracena",
    "sg:orig_category":"Electricidad: Instaladores",
    "sg:phone":"+34 959 12 81 49",
    "sg:postcode":"21200",
    "sg:province":"Huelva",
    "wof:name":"Montajes Electricos Sanchez Contreras C.b.",
    "wof:placetype":"venue"
},
  "geometry": {"coordinates":[-6.5563879013,37.8901901245],"type":"Point"}
}