{
  "type": "Feature",
  "properties": {
    "addr:full":"Calle de Benito Caparroso Pa\u00d1os, 12 Tudela Navarra 31500",
    "addr:housenumber":"12",
    "addr:postcode":"31500",
    "addr:street":"Calle De Benito Caparroso Pan\u0303Os",
    "iso:country":"ES",
    "sg:address":"Calle de Benito Caparroso Pa\u00d1os, 12",
    "sg:city":"Tudela",
    "sg:orig_category":"Electricidad (montaje, Ensamblaje De Componentes)",
    "sg:phone":"+34 948 41 01 23",
    "sg:postcode":"31500",
    "sg:province":"Navarra",
    "wof:name":"Saso Sandua Luis Miguel",
    "wof:placetype":"venue"
},
  "geometry": {"coordinates":[-1.6066089869,42.0562782288],"type":"Point"}
}