{
  "type": "Feature",
  "properties": {
    "addr:full":"Ctra Tudela, S/n Montemayor Pililla Valladolid 47320",
    "addr:housenumber":"s / n",
    "addr:postcode":"47320",
    "addr:street":"Ctra Tudela",
    "iso:country":"ES",
    "sg:address":"Ctra Tudela, S/n",
    "sg:city":"Montemayor Pililla",
    "sg:orig_category":"Carnicer\u00cdas, Carnicer\u00cdas",
    "sg:phone":"+34 983 69 44 79",
    "sg:postcode":"47320",
    "sg:province":"Valladolid",
    "wof:name":"Sanz Bachiller Mariano",
    "wof:placetype":"venue"
},
  "geometry": {"coordinates":[-4.460103035,41.506855011],"type":"Point"}
}