{
  "type": "Feature",
  "properties": {
    "addr:full":"Carrer de Guillem Magro, 24 Crevillent Alicante 03330",
    "addr:housenumber":"24",
    "addr:postcode":"03330",
    "addr:street":"Carrer De Guillem Magro",
    "iso:country":"ES",
    "sg:address":"Carrer de Guillem Magro, 24",
    "sg:city":"Crevillent",
    "sg:orig_category":"Abogados",
    "sg:phone":"+34 965 40 51 08",
    "sg:postcode":"03330",
    "sg:province":"Alicante",
    "wof:name":"Pascual Lledo Manuel",
    "wof:placetype":"venue"
},
  "geometry": {"coordinates":[-0.8099330068,38.2468147278],"type":"Point"}
}