{
  "type": "Feature",
  "properties": {
    "addr:full":"Calle de Pedro Iii El Grande, 3 Zaragoza Zaragoza 50009",
    "addr:housenumber":"3",
    "addr:postcode":"50009",
    "addr:street":"Calle De Pedro Iii El Grande",
    "iso:country":"ES",
    "sg:address":"Calle de Pedro Iii El Grande, 3",
    "sg:city":"Zaragoza",
    "sg:orig_category":"Asociaciones Y Clubs Deportivos",
    "sg:phone":"+34 976 55 97 45",
    "sg:postcode":"50009",
    "sg:province":"Zaragoza",
    "sg:website":"www.cdzaragozano.com",
    "wof:name":"Club Deportivo Zaragoza De Gimnasia",
    "wof:placetype":"venue"
},
  "geometry": {"coordinates":[-0.9060840011,41.6374053955],"type":"Point"}
}