{
  "type": "Feature",
  "properties": {
    "addr:full":"Plaz Rinconada, 12 Valladolid Valladolid 47001",
    "addr:housenumber":"12",
    "addr:postcode":"47001",
    "addr:street":"Rinconada",
    "iso:country":"ES",
    "sg:address":"Plaz Rinconada, 12",
    "sg:city":"Valladolid",
    "sg:orig_category":"Abogados",
    "sg:phone":"+34 983 36 26 98",
    "sg:postcode":"47001",
    "sg:province":"Valladolid",
    "wof:name":"Arribas Aparicio Carolina",
    "wof:placetype":"venue"
},
  "geometry": {"coordinates":[-4.7293806076,41.6533050537],"type":"Point"}
}