{
  "type": "Feature",
  "properties": {
    "addr:full":"Pase Russafa, 5 Valencia Valencia 46002",
    "addr:housenumber":"5",
    "addr:postcode":"46002",
    "addr:street":"Russafa",
    "iso:country":"ES",
    "sg:address":"Pase Russafa, 5",
    "sg:city":"Valencia",
    "sg:orig_category":"Librer\u00cdas",
    "sg:phone":"+34 963 52 19 76",
    "sg:postcode":"46002",
    "sg:province":"Valencia",
    "wof:name":"Montiven C.b.",
    "wof:placetype":"venue"
},
  "geometry": {"coordinates":[-0.375169009,39.468460083],"type":"Point"}
}