{
  "type": "Feature",
  "properties": {
    "iso:country":"ES",
    "sg:address":"Calle de General Diaz Porlier, 36",
    "sg:city":"Madrid",
    "sg:orig_category":"Animales (al Por Menor)",
    "sg:phone":"+34 914 02 65 43",
    "sg:postcode":"28001",
    "sg:province":"Madrid",
    "wof:name":"Fernandez Alonso Esther",
    "wof:placetype":"venue"
},
  "geometry": {"coordinates":[-3.6767880917,40.4280586243],"type":"Point"}
}