{
  "type": "Feature",
  "properties": {
    "iso:country":"ES",
    "sg:address":"Calle de Pablo Vi, S/n",
    "sg:city":"Barrios",
    "sg:orig_category":"Bebidas",
    "sg:phone":"+34 956 62 06 89",
    "sg:postcode":"11370",
    "sg:province":"C\u00e1diz",
    "wof:name":"Schweppes S.a.",
    "wof:placetype":"venue"
},
  "geometry": {"coordinates":[-5.4930238724,36.1817398071],"type":"Point"}
}