{
  "type": "Feature",
  "properties": {
    "addr:full":"Calle de Doctor Fleming, 9 Requena Valencia 46340",
    "addr:housenumber":"9",
    "addr:postcode":"46340",
    "addr:street":"Calle De Doctor Fleming",
    "iso:country":"ES",
    "sg:address":"Calle de Doctor Fleming, 9",
    "sg:city":"Requena",
    "sg:orig_category":"Sociedades, Compa\u00d1\u00cdas Aseguradoras",
    "sg:phone":"+34 962 30 08 59",
    "sg:postcode":"46340",
    "sg:province":"Valencia",
    "wof:name":"A.n.l. Agrupacion De Servicios S.l.",
    "wof:placetype":"venue"
},
  "geometry": {"coordinates":[-1.1009119749,39.490901947],"type":"Point"}
}