{
  "type": "Feature",
  "properties": {
    "addr:full":"Calle de Faisan, 7 Sobradillo Santa Cruz De Tenerife 38108",
    "addr:housenumber":"7",
    "addr:postcode":"38108",
    "addr:street":"Calle De Faisan",
    "iso:country":"ES",
    "sg:address":"Calle de Faisan, 7",
    "sg:city":"Sobradillo",
    "sg:orig_category":"Congelados: Productos Alimentarios (fabricaci\u00d3n, Al Por Mayor)",
    "sg:phone":"+34 922 62 08 09",
    "sg:postcode":"38108",
    "sg:province":"Santa Cruz De Tenerife",
    "wof:name":"Rodriguez Niebla Luis",
    "wof:placetype":"venue"
},
  "geometry": {"coordinates":[-16.2957706451,28.4491081238],"type":"Point"}
}