{
  "type": "Feature",
  "properties": {
    "addr:full":"Eduardo Gorosarri Plaza, 8 Eskoriatza Guip\u00f9zcoa 20540",
    "addr:housenumber":"8",
    "addr:postcode":"20540",
    "addr:street":"Eduardo Gorosarri Plaza;Guipu\u0300Zcoa",
    "iso:country":"ES",
    "sg:address":"Eduardo Gorosarri Plaza, 8",
    "sg:city":"Eskoriatza",
    "sg:classifiers":[
        {
            "category":"Taxi",
            "type":"Transportation"
        }
    ],
    "sg:phone":"+34 943 71 40 59",
    "sg:postcode":"20540",
    "sg:province":"Guip\u00f9zcoa",
    "wof:name":"Guede Fari\u00f1as Delfin",
    "wof:placetype":"venue"
},
  "geometry": {"coordinates":[-2.5256872177,43.0182723999],"type":"Point"}
}