{
  "type": "Feature",
  "properties": {
    "iso:country":"ES",
    "sg:address":"Carrer de Monges, 1",
    "sg:city":"Barcelona",
    "sg:orig_category":"Electrodom\u00c9sticos (al Por Menor)",
    "sg:phone":"+34 933 11 59 01",
    "sg:postcode":"08030",
    "sg:province":"Barcelona",
    "wof:name":"Corredor Martinez Ismael",
    "wof:placetype":"venue"
},
  "geometry": {"coordinates":[2.1878271103,41.430316925],"type":"Point"}
}