{
  "type": "Feature",
  "properties": {
    "iso:country":"ES",
    "sg:address":"Avda Vilagarcia, 100",
    "sg:city":"Cambados",
    "sg:orig_category":"Productores Recolectores, Venta Directa De Vinos",
    "sg:phone":"+34 986 54 29 47",
    "sg:postcode":"36630",
    "sg:province":"Pontevedra",
    "wof:name":"Adegas Terra Santa",
    "wof:placetype":"venue"
},
  "geometry": {"coordinates":[-8.8053407669,42.528553009],"type":"Point"}
}