{
  "type": "Feature",
  "properties": {
    "iso:country":"ES",
    "sg:address":"Calle de Marquesa De Canillejas, 30",
    "sg:city":"Pola De Siero",
    "sg:orig_category":"Perfumer\u00cda (al Por Menor)",
    "sg:phone":"+34 985 72 35 51",
    "sg:postcode":"33510",
    "sg:province":"Asturias",
    "wof:name":"Dapargel",
    "wof:placetype":"venue"
},
  "geometry": {"coordinates":[-5.6626691818,43.3889884949],"type":"Point"}
}