{
  "type": "Feature",
  "properties": {
    "addr:full":"Ptda Molla, S/n Riba-roja Turia Valencia 46190",
    "addr:housenumber":"s / n",
    "addr:postcode":"46190",
    "addr:street":"Ptda Molla",
    "iso:country":"ES",
    "sg:address":"Ptda Molla, S/n",
    "sg:city":"Riba-roja Turia",
    "sg:orig_category":"Ense\u00d1anza Secundaria: Colegios Y Escuelas Privadas",
    "sg:phone":"+34 962 77 17 61",
    "sg:postcode":"46190",
    "sg:province":"Valencia",
    "wof:name":"Generalitat Valenciana",
    "wof:placetype":"venue"
},
  "geometry": {"coordinates":[-0.3768048882,39.4702377319],"type":"Point"}
}