{
  "type": "Feature",
  "properties": {
    "iso:country":"ES",
    "sg:address":"Calle de Buenos Aires, 3",
    "sg:city":"Pe\u00f1ascosa",
    "sg:orig_category":"Centros De Salud",
    "sg:phone":"+34 967 38 24 17",
    "sg:postcode":"02313",
    "sg:province":"Albacete",
    "wof:name":"Ayuntamiento De Pe\u00d1ascosa",
    "wof:placetype":"venue"
},
  "geometry": {"coordinates":[-2.4121251106,38.6719284058],"type":"Point"}
}