{
  "type": "Feature",
  "properties": {
    "iso:country":"ES",
    "sg:address":"Plaz Mercado (del), 10",
    "sg:city":"Jodar",
    "sg:orig_category":"Alimentaci\u00d3n General (al Por Menor)",
    "sg:phone":"+34 953 78 50 79",
    "sg:postcode":"23500",
    "sg:province":"Ja\u00e9n",
    "wof:name":"Diaz Latorre Lino",
    "wof:placetype":"venue"
},
  "geometry": {"coordinates":[-3.3511819839,37.8434257507],"type":"Point"}
}