{
  "type": "Feature",
  "properties": {
    "addr:full":"Calle de Ramon Gonzalez, 12 Ribadeo Lugo 27700",
    "addr:housenumber":"12",
    "addr:postcode":"27700",
    "addr:street":"Calle De Ramon Gonzalez",
    "iso:country":"ES",
    "sg:address":"Calle de Ramon Gonzalez, 12",
    "sg:city":"Ribadeo",
    "sg:orig_category":"Electricidad: Instaladores",
    "sg:phone":"+34 982 12 83 62",
    "sg:postcode":"27700",
    "sg:province":"Lugo",
    "wof:name":"Gutierrez Oliveros Jose Maria",
    "wof:placetype":"venue"
},
  "geometry": {"coordinates":[-7.0435647964,43.536781311],"type":"Point"}
}