{
  "type": "Feature",
  "properties": {
    "addr:full":"Calle de Obispo Miranda, 1 Tamarite Litera Huesca 22550",
    "addr:housenumber":"1",
    "addr:postcode":"22550",
    "addr:street":"Calle De Obispo Miranda",
    "iso:country":"ES",
    "sg:address":"Calle de Obispo Miranda, 1",
    "sg:city":"Tamarite Litera",
    "sg:orig_category":"Estancos",
    "sg:phone":"+34 974 42 02 11",
    "sg:postcode":"22550",
    "sg:province":"Huesca",
    "wof:name":"Bendicho Castet Esteban",
    "wof:placetype":"venue"
},
  "geometry": {"coordinates":[0.4210720062,41.8692855835],"type":"Point"}
}