{
  "type": "Feature",
  "properties": {
    "addr:full":"Carrer de Dos De Maig, 217 Barcelona Barcelona 08013",
    "addr:housenumber":"217",
    "addr:postcode":"08013",
    "addr:street":"Carrer De Dos De Maig",
    "iso:country":"ES",
    "sg:address":"Carrer de Dos De Maig, 217",
    "sg:city":"Barcelona",
    "sg:orig_category":"Compraventa De Antig\u00dcedades",
    "sg:phone":"+34 932 32 20 79",
    "sg:postcode":"08013",
    "sg:province":"Barcelona",
    "wof:name":"Temps Enlla S.c.p.",
    "wof:placetype":"venue"
},
  "geometry": {"coordinates":[2.1834919453,41.4057769775],"type":"Point"}
}