{
  "type": "Feature",
  "properties": {
    "addr:full":"Calle de Jubilados, 33 Massamagrell Valencia 46130",
    "addr:housenumber":"33",
    "addr:postcode":"46130",
    "addr:street":"Calle De Jubilados",
    "iso:country":"ES",
    "sg:address":"Calle de Jubilados, 33",
    "sg:city":"Massamagrell",
    "sg:orig_category":"Arquitectos",
    "sg:phone":"+34 961 44 37 91",
    "sg:postcode":"46130",
    "sg:province":"Valencia",
    "wof:name":"Prieto Rodriguez Maria Amalia",
    "wof:placetype":"venue"
},
  "geometry": {"coordinates":[-0.3342640102,39.5732650757],"type":"Point"}
}