{
  "type": "Feature",
  "properties": {
    "iso:country":"ES",
    "sg:address":"Calle de Alamo, El, 19",
    "sg:city":"Valencia",
    "sg:orig_category":"Molduras, Junquillos, Listones Y Molduras Perforadas",
    "sg:phone":"+34 963 48 30 92",
    "sg:postcode":"46025",
    "sg:province":"Valencia",
    "wof:name":"Palacios Collados Eusebio",
    "wof:placetype":"venue"
},
  "geometry": {"coordinates":[-0.3907617033,39.4922027588],"type":"Point"}
}