{
  "type": "Feature",
  "properties": {
    "iso:country":"ES",
    "sg:address":"Avda Canarias, 2",
    "sg:city":"Vecindario",
    "sg:orig_category":"Veh\u00cdculos De Ocasi\u00d3n",
    "sg:phone":"+34 928 75 42 02",
    "sg:postcode":"35110",
    "sg:province":"Las Palmas",
    "wof:name":"Suarez Medina Lorenzo",
    "wof:placetype":"venue"
},
  "geometry": {"coordinates":[-15.4406194687,27.8517799377],"type":"Point"}
}