{
  "type": "Feature",
  "properties": {
    "addr:full":"Carr Bs Torras I Bages, 12 Igualada Barcelona 08700",
    "addr:housenumber":"12",
    "addr:postcode":"08700",
    "addr:street":"Carr Bs Torras I Bages",
    "iso:country":"ES",
    "sg:address":"Carr Bs Torras I Bages, 12",
    "sg:city":"Igualada",
    "sg:orig_category":"Procuradores",
    "sg:phone":"+34 938 05 09 17",
    "sg:postcode":"08700",
    "sg:province":"Barcelona",
    "wof:name":"Gabarro Rosell Maria Concepcio",
    "wof:placetype":"venue"
},
  "geometry": {"coordinates":[1.6120589972,41.5834121704],"type":"Point"}
}