{
  "type": "Feature",
  "properties": {
    "iso:country":"ES",
    "sg:address":"Calle de San Julian, 3",
    "sg:city":"Mozar",
    "sg:orig_category":"Negocio De Materiales De Construcci\u00d3n",
    "sg:phone":"+34 980 64 06 75",
    "sg:postcode":"49698",
    "sg:province":"Zamora",
    "wof:name":"Almacenes De Construccion Jose Maria Iglesias S.l.l.",
    "wof:placetype":"venue"
},
  "geometry": {"coordinates":[-5.7771639824,41.9532699585],"type":"Point"}
}