{
  "type": "Feature",
  "properties": {
    "addr:full":"Ctra. Navalmoral-plasencia, Km. 0009,7 Casatejada C\u00e1ceres 10520",
    "addr:postcode":"10520",
    "addr:street":"Ctra. Navalmoral-Plasencia Km. 0009,7;Ca\u0301Ceres",
    "iso:country":"ES",
    "sg:address":"Ctra. Navalmoral-plasencia, Km. 0009,7",
    "sg:city":"Casatejada",
    "sg:orig_category":"Distribuci\u00d3n De Petr\u00d3leo Y Derivados",
    "sg:phone":"+34 927 54 70 49",
    "sg:postcode":"10520",
    "sg:province":"C\u00e1ceres",
    "wof:name":"Blanco Romero S.a.",
    "wof:placetype":"venue"
},
  "geometry": {"coordinates":[-5.6820940971,39.8860855103],"type":"Point"}
}