{
  "type": "Feature",
  "properties": {
    "iso:country":"ES",
    "sg:address":"Mayorazgo, 901",
    "sg:city":"Sta Cruz Tenerife",
    "sg:orig_category":"Transporte En General",
    "sg:phone":"+34 922 65 75 84",
    "sg:postcode":"38010",
    "sg:province":"Santa Cruz De Tenerife",
    "wof:name":"Eurotour Expres S.l.",
    "wof:placetype":"venue"
},
  "geometry": {"coordinates":[-16.2857913971,28.4462871552],"type":"Point"}
}