{
  "type": "Feature",
  "properties": {
    "addr:full":"Cta Grupo Escolar, 23 Gata Gorgos Alicante 03740",
    "addr:postcode":"03740",
    "addr:street":"Cta Grupo",
    "iso:country":"ES",
    "sg:address":"Cta Grupo Escolar, 23",
    "sg:city":"Gata Gorgos",
    "sg:orig_category":"Serigraf\u00cda (material Y Suministros)",
    "sg:phone":"+34 965 75 69 56",
    "sg:postcode":"03740",
    "sg:province":"Alicante",
    "wof:name":"Navalmoral Del Olmo Angel",
    "wof:placetype":"venue"
},
  "geometry": {"coordinates":[0.084187001,38.770980835],"type":"Point"}
}