{
  "type": "Feature",
  "properties": {
    "iso:country":"ES",
    "sg:address":"Carrer de Princesa, 12",
    "sg:city":"Mora D'ebre",
    "sg:orig_category":"Maquinaria Para Industrias Diversas",
    "sg:phone":"+34 977 40 18 98",
    "sg:postcode":"43740",
    "sg:province":"Tarragona",
    "sg:website":"www.itpservice.com",
    "wof:name":"International Testing Pipelines S.a.",
    "wof:placetype":"venue"
},
  "geometry": {"coordinates":[1.2246249914,41.1203613281],"type":"Point"}
}