{
  "type": "Feature",
  "properties": {
    "iso:country":"ES",
    "sg:address":"Calle de Carmelo Tecedor, 6",
    "sg:city":"Villamediana Iregua",
    "sg:orig_category":"Promotores Constructores",
    "sg:phone":"+34 941 43 55 71",
    "sg:postcode":"26142",
    "sg:province":"La Rioja",
    "wof:name":"Constructora Obras Y Vias S.a",
    "wof:placetype":"venue"
},
  "geometry": {"coordinates":[-2.4212872982,42.4242095947],"type":"Point"}
}