{
  "type": "Feature",
  "properties": {
    "iso:country":"ES",
    "sg:address":"Calle de Juan Morales Navarro, 5",
    "sg:city":"Santa Brigida",
    "sg:orig_category":"Laboratorios Y Trabajos De Fotograf\u00cda, V\u00cddeo Y Cine",
    "sg:phone":"+34 928 64 01 04",
    "sg:postcode":"35300",
    "sg:province":"Las Palmas",
    "wof:name":"Gonzalez Velazquez Jacobo",
    "wof:placetype":"venue"
},
  "geometry": {"coordinates":[-15.4989643097,28.0343437195],"type":"Point"}
}