{
  "type": "Feature",
  "properties": {
    "iso:country":"ES",
    "sg:address":"Agricultores (p I Gandul), 7",
    "sg:city":"Mairena Alcor",
    "sg:orig_category":"Electricidad: Instaladores",
    "sg:phone":"+34 955 74 48 68",
    "sg:postcode":"41510",
    "sg:province":"Sevilla",
    "wof:name":"Copelec S.c.a.",
    "wof:placetype":"venue"
},
  "geometry": {"coordinates":[-5.7574009895,37.3628311157],"type":"Point"}
}