{
  "type": "Feature",
  "properties": {
    "addr:full":"Torrent (el), 7 Mataro Barcelona 08302",
    "addr:postcode":"08302",
    "iso:country":"ES",
    "sg:address":"Torrent (el), 7",
    "sg:city":"Mataro",
    "sg:orig_category":"M\u00c9dicos: Pediatr\u00cda. Enfermedades De Los Ni\u00d1os",
    "sg:phone":"+34 937 41 01 74",
    "sg:postcode":"08302",
    "sg:province":"Barcelona",
    "wof:name":"Guitart Peralta Jose",
    "wof:placetype":"venue"
},
  "geometry": {"coordinates":[2.4324100018,41.5336990356],"type":"Point"}
}