{
  "type": "Feature",
  "properties": {
    "addr:full":"Carrer de Basses De Sant Pere, 4 Barcelona Barcelona 08003",
    "addr:housenumber":"4",
    "addr:postcode":"08003",
    "addr:street":"Carrer De Basses De Sant Pere",
    "iso:country":"ES",
    "sg:address":"Carrer de Basses De Sant Pere, 4",
    "sg:city":"Barcelona",
    "sg:orig_category":"Negocio De Materiales De Construcci\u00d3n",
    "sg:phone":"+34 933 19 86 56",
    "sg:postcode":"08003",
    "sg:province":"Barcelona",
    "wof:name":"Rovira Albadalejo Mercedes",
    "wof:placetype":"venue"
},
  "geometry": {"coordinates":[2.1802630424,41.3884315491],"type":"Point"}
}