{
  "type": "Feature",
  "properties": {
    "addr:full":"Calle de San Juan De Los Reyes, 38 Granada Granada 18010",
    "addr:housenumber":"38",
    "addr:postcode":"18010",
    "addr:street":"Calle De San;Los Reyes",
    "iso:country":"ES",
    "sg:address":"Calle de San Juan De Los Reyes, 38",
    "sg:city":"Granada",
    "sg:orig_category":"Albergues",
    "sg:phone":"+34 958 22 50 52",
    "sg:postcode":"18010",
    "sg:province":"Granada",
    "wof:name":"Hermanos Obreros De Maria",
    "wof:placetype":"venue"
},
  "geometry": {"coordinates":[-3.5936999321,37.179069519],"type":"Point"}
}