{
  "type": "Feature",
  "properties": {
    "iso:country":"ES",
    "sg:address":"Calle de Ancha, 8",
    "sg:city":"Salamanca",
    "sg:orig_category":"Asociaciones Y Clubs Deportivos",
    "sg:phone":"+34 923 21 70 56",
    "sg:postcode":"37002",
    "sg:province":"Salamanca",
    "sg:website":"paginasamarillas.es",
    "wof:name":"Gimnasio Pasadena Salamanca Cb",
    "wof:placetype":"venue"
},
  "geometry": {"coordinates":[-5.6677150726,40.9648551941],"type":"Point"}
}