{
  "type": "Feature",
  "properties": {
    "iso:country":"ES",
    "sg:address":"Av Jaume Iii, 24",
    "sg:city":"Palma",
    "sg:orig_category":"Agencias De Viajes",
    "sg:phone":"+34 971 72 50 87",
    "sg:postcode":"07012",
    "sg:province":"Islas Baleares",
    "wof:name":"Viatjes Perla Tours S.l.",
    "wof:placetype":"venue"
},
  "geometry": {"coordinates":[2.6430609226,39.5726127625],"type":"Point"}
}