{
  "type": "Feature",
  "properties": {
    "iso:country":"ES",
    "sg:address":"Avda Cristo Rey (de), 77",
    "sg:city":"Villarrubia De Los Ojos",
    "sg:orig_category":"Muebles Y Accesorios Para Cocinas Y Cuartos De Ba\u00d1o (al Por Menor)",
    "sg:phone":"+34 926 89 80 95",
    "sg:postcode":"13670",
    "sg:province":"Ciudad Real",
    "wof:name":"Amado Navarro Maria Del Carmen",
    "wof:placetype":"venue"
},
  "geometry": {"coordinates":[-3.6143360138,39.2174873352],"type":"Point"}
}