{
  "type": "Feature",
  "properties": {
    "iso:country":"ES",
    "sg:address":"Pg Verdaguer, 102",
    "sg:city":"Igualada",
    "sg:orig_category":"Doctores En Medicina",
    "sg:phone":"+34 938 03 03 41",
    "sg:postcode":"08700",
    "sg:province":"Barcelona",
    "wof:name":"Miquel Torras Xavier",
    "wof:placetype":"venue"
},
  "geometry": {"coordinates":[1.6213400364,41.5805931091],"type":"Point"}
}