{
  "type": "Feature",
  "properties": {
    "addr:full":"Avda Ximenez De Rada, 79 Cazorla Ja\u00e9n 23470",
    "addr:housenumber":"79",
    "addr:postcode":"23470",
    "addr:street":"Avda Ximenez De Rada",
    "iso:country":"ES",
    "sg:address":"Avda Ximenez De Rada, 79",
    "sg:city":"Cazorla",
    "sg:orig_category":"Farmacias",
    "sg:phone":"+34 953 71 01 20",
    "sg:postcode":"23470",
    "sg:province":"Ja\u00e9n",
    "wof:name":"Cano Perez Julio",
    "wof:placetype":"venue"
},
  "geometry": {"coordinates":[-3.0018069744,37.9174804688],"type":"Point"}
}