{
  "type": "Feature",
  "properties": {
    "addr:full":"Pol Ind Poligran, Km. 0426,0 Peligros Granada 18210",
    "addr:postcode":"18210",
    "addr:street":"Poligran Km. 0426,0",
    "iso:country":"ES",
    "sg:address":"Pol Ind Poligran, Km. 0426,0",
    "sg:city":"Peligros",
    "sg:orig_category":"M\u00c1rmoles, Granitos Y Piedras Naturales",
    "sg:phone":"+34 958 40 21 32",
    "sg:postcode":"18210",
    "sg:province":"Granada",
    "wof:name":"Yepes Campoy Miguel Angel",
    "wof:placetype":"venue"
},
  "geometry": {"coordinates":[-3.6268463135,37.2365036011],"type":"Point"}
}