{
  "type": "Feature",
  "properties": {
    "iso:country":"ES",
    "sg:address":"Avda Comuneros, 28",
    "sg:city":"Salamanca",
    "sg:orig_category":"Alimentaci\u00d3n General (al Por Menor)",
    "sg:phone":"+34 923 18 80 92",
    "sg:postcode":"37003",
    "sg:province":"Salamanca",
    "wof:name":"Martin Gonzalez Agapito",
    "wof:placetype":"venue"
},
  "geometry": {"coordinates":[-5.6506237984,40.9684715271],"type":"Point"}
}