{
  "type": "Feature",
  "properties": {
    "iso:country":"ES",
    "sg:address":"Cmno Viejo De Simancas, Km. 0006,5",
    "sg:city":"Simancas",
    "sg:orig_category":"Impermeabilizantes",
    "sg:phone":"+34 983 59 07 59",
    "sg:postcode":"47130",
    "sg:province":"Valladolid",
    "wof:name":"Roberto Herrero Merino S.l.",
    "wof:placetype":"venue"
},
  "geometry": {"coordinates":[-4.8235812187,41.5907974243],"type":"Point"}
}