{
  "type": "Feature",
  "properties": {
    "iso:country":"ES",
    "sg:address":"Carrer de Dofi, 3",
    "sg:city":"Can Pastilla",
    "sg:orig_category":"Comerciantes Al Por Mayor De Vinos, Licores Y Alcoholes",
    "sg:phone":"+34 971 26 70 11",
    "sg:postcode":"07610",
    "sg:province":"Islas Baleares",
    "wof:name":"Niell Mas Bartolome",
    "wof:placetype":"venue"
},
  "geometry": {"coordinates":[2.7179949284,39.5362663269],"type":"Point"}
}