{
  "type": "Feature",
  "properties": {
    "addr:full":"Avda Independencia (de La), 43 San Sebastian De Los Reyes Madrid 28700",
    "addr:housenumber":"43",
    "addr:postcode":"28700",
    "addr:street":"Avda Independencia De La",
    "iso:country":"ES",
    "sg:address":"Avda Independencia (de La), 43",
    "sg:city":"San Sebastian De Los Reyes",
    "sg:orig_category":"Doctores En Medicina",
    "sg:phone":"+34 916 53 15 26",
    "sg:postcode":"28700",
    "sg:province":"Madrid",
    "wof:name":"Emedsanse S.l.",
    "wof:placetype":"venue"
},
  "geometry": {"coordinates":[-3.6349470615,40.553894043],"type":"Point"}
}