{
  "type": "Feature",
  "properties": {
    "iso:country":"ES",
    "sg:address":"Calle de Carolina, 2",
    "sg:city":"Piedrabuena",
    "sg:orig_category":"Asesor\u00cda Fiscal Y Jur\u00cddica",
    "sg:phone":"+34 926 76 02 08",
    "sg:postcode":"13100",
    "sg:province":"Ciudad Real",
    "wof:name":"Eustaquio Rodriguez Asesoria Minerva",
    "wof:placetype":"venue"
},
  "geometry": {"coordinates":[-4.1728587151,39.0346870422],"type":"Point"}
}