{
  "type": "Feature",
  "properties": {
    "iso:country":"ES",
    "sg:address":"Carrer de Lope De Vega, 26",
    "sg:city":"Barcelona",
    "sg:orig_category":"Electricidad (montaje, Ensamblaje De Componentes)",
    "sg:phone":"+34 932 66 44 07",
    "sg:postcode":"08005",
    "sg:province":"Barcelona",
    "wof:name":"Cornejo Moyano Maria Josefa",
    "wof:placetype":"venue"
},
  "geometry": {"coordinates":[2.2061929703,41.40259552],"type":"Point"}
}