{
  "type": "Feature",
  "properties": {
    "addr:full":"Calle de San Martin De Porres, 1 Atalaya Las Palmas 35450",
    "addr:housenumber":"1",
    "addr:postcode":"35450",
    "addr:street":"Calle De San Martin De Porres",
    "iso:country":"ES",
    "sg:address":"Calle de San Martin De Porres, 1",
    "sg:city":"Atalaya",
    "sg:orig_category":"Mec\u00c1nico Del Autom\u00d3vil",
    "sg:phone":"+34 928 88 10 31",
    "sg:postcode":"35450",
    "sg:province":"Las Palmas",
    "wof:name":"Diaz Santiago Juan",
    "wof:placetype":"venue"
},
  "geometry": {"coordinates":[-15.6322259903,28.1515045166],"type":"Point"}
}