{
  "type": "Feature",
  "properties": {
    "addr:full":"Avda Federico Garcia Lorca, 96 Nijar Almer\u00eda 04100",
    "addr:housenumber":"96",
    "addr:postcode":"04100",
    "addr:street":"Avda Federico Garcia Lorca;Almeri\u0301A",
    "iso:country":"ES",
    "sg:address":"Avda Federico Garcia Lorca, 96",
    "sg:city":"Nijar",
    "sg:orig_category":"Farmacias",
    "sg:phone":"+34 950 36 02 00",
    "sg:postcode":"04100",
    "sg:province":"Almer\u00eda",
    "wof:name":"Montoya Priego Maria Dolores",
    "wof:placetype":"venue"
},
  "geometry": {"coordinates":[-2.2062458992,36.9612922668],"type":"Point"}
}