{
  "type": "Feature",
  "properties": {
    "iso:country":"ES",
    "sg:address":"Calle de Benito De Castro, 5",
    "sg:city":"Madrid",
    "sg:orig_category":"Venta, Instalaci\u00d3n, Reparaci\u00d3n De Antenas Para Televisi\u00d3n",
    "sg:phone":"+34 917 25 16 66",
    "sg:postcode":"28028",
    "sg:province":"Madrid",
    "wof:name":"Hiper-antena S. A.",
    "wof:placetype":"venue"
},
  "geometry": {"coordinates":[-3.6676549911,40.4263114929],"type":"Point"}
}