{
  "type": "Feature",
  "properties": {
    "iso:country":"ES",
    "sg:address":"Carrer de Jose Vargas Ponce, 32",
    "sg:city":"Coll De'n Rabassa",
    "sg:orig_category":"Agencias Y Agentes Comerciales, Representantes",
    "sg:phone":"+34 971 74 37 78",
    "sg:postcode":"07007",
    "sg:province":"Islas Baleares",
    "wof:name":"Monto Gestion S.l.",
    "wof:placetype":"venue"
},
  "geometry": {"coordinates":[2.9117100239,39.6136398315],"type":"Point"}
}