{
  "type": "Feature",
  "properties": {
    "addr:full":"Pda Fila Del Divendres, S/n Xativa Valencia 46800",
    "addr:housenumber":"pda;s",
    "addr:postcode":"46800",
    "addr:street":"/ N",
    "iso:country":"ES",
    "sg:address":"Pda Fila Del Divendres, S/n",
    "sg:city":"Xativa",
    "sg:orig_category":"Control T\u00c9cnico De Veh\u00cdculos",
    "sg:phone":"+34 962 28 70 45",
    "sg:postcode":"46800",
    "sg:province":"Valencia",
    "sg:website":"www.itv.com",
    "wof:name":"Aseguramiento Tecnico De La Calidad S.a.",
    "wof:placetype":"venue"
},
  "geometry": {"coordinates":[-0.5163311958,38.9969673157],"type":"Point"}
}