{
  "type": "Feature",
  "properties": {
    "addr:full":"Carrer de Sagrera, 182 Barcelona Barcelona 08027",
    "addr:housenumber":"182",
    "addr:postcode":"08027",
    "addr:street":"Carrer De Sagrera",
    "iso:country":"ES",
    "sg:address":"Carrer de Sagrera, 182",
    "sg:city":"Barcelona",
    "sg:orig_category":"Empresas De Carpinter\u00cda Met\u00c1lica",
    "sg:phone":"+34 934 08 22 32",
    "sg:postcode":"08027",
    "sg:province":"Barcelona",
    "wof:name":"Coinvial S.l.",
    "wof:placetype":"venue"
},
  "geometry": {"coordinates":[2.1911571026,41.4267082214],"type":"Point"}
}