{
  "type": "Feature",
  "properties": {
    "iso:country":"ES",
    "sg:address":"Calle de Virgen De La Paz, 27",
    "sg:city":"Torrent",
    "sg:orig_category":"Comercio De Piezas De Recambio Y De Accesorios De Veh\u00cdculos, Veh\u00cdculos Industriales",
    "sg:phone":"+34 961 57 57 12",
    "sg:postcode":"46900",
    "sg:province":"Valencia",
    "wof:name":"Autorapid Torrent A-6 S.l.",
    "wof:placetype":"venue"
},
  "geometry": {"coordinates":[-0.4716250002,39.4344787598],"type":"Point"}
}