{
  "type": "Feature",
  "properties": {
    "addr:full":"Calle de Santa Clara, 8 Zamora Zamora 49003",
    "addr:housenumber":"8",
    "addr:postcode":"49003",
    "addr:street":"Calle De Santa Clara",
    "iso:country":"ES",
    "sg:address":"Calle de Santa Clara, 8",
    "sg:city":"Zamora",
    "sg:orig_category":"Asesor\u00cda Fiscal Y Jur\u00cddica",
    "sg:phone":"+34 980 53 06 94",
    "sg:postcode":"49003",
    "sg:province":"Zamora",
    "wof:name":"Lorenzo Sanchez Rafael",
    "wof:placetype":"venue"
},
  "geometry": {"coordinates":[-5.744342804,41.5046005249],"type":"Point"}
}