{
  "type": "Feature",
  "properties": {
    "addr:full":"Calle de Coslada, 26 Madrid Madrid 28028",
    "addr:housenumber":"26",
    "addr:postcode":"madrid;28028",
    "addr:street":"Calle De Coslada",
    "iso:country":"ES",
    "sg:address":"Calle de Coslada, 26",
    "sg:city":"Madrid",
    "sg:orig_category":"Molduras, Junquillos, Listones Y Molduras Perforadas",
    "sg:phone":"+34 913 56 29 37",
    "sg:postcode":"28028",
    "sg:province":"Madrid",
    "wof:name":"Pin Pin Maria Soledad",
    "wof:placetype":"venue"
},
  "geometry": {"coordinates":[-3.6737952232,40.4380607605],"type":"Point"}
}