{
  "type": "Feature",
  "properties": {
    "addr:full":"Andres Segovia, S/n Xirivella Valencia 46950",
    "addr:housenumber":"/ n",
    "addr:postcode":"46950",
    "addr:street":"Segovia S",
    "iso:country":"ES",
    "sg:address":"Andres Segovia, S/n",
    "sg:city":"Xirivella",
    "sg:orig_category":"Alimentaci\u00d3n General (al Por Menor)",
    "sg:phone":"+34 963 79 27 74",
    "sg:postcode":"46950",
    "sg:province":"Valencia",
    "wof:name":"Ruiz Castillo Sagrario",
    "wof:placetype":"venue"
},
  "geometry": {"coordinates":[-0.4150890112,39.4662284851],"type":"Point"}
}