{
  "type": "Feature",
  "properties": {
    "iso:country":"ES",
    "sg:address":"Avda Carlos I, 91",
    "sg:city":"Salamanca",
    "sg:orig_category":"Teatros Y Salas De Espect\u00c1culos",
    "sg:phone":"+34 923 21 26 58",
    "sg:postcode":"37008",
    "sg:province":"Salamanca",
    "wof:name":"Martin Sanchez Miguel",
    "wof:placetype":"venue"
},
  "geometry": {"coordinates":[-5.6647491455,40.9497413635],"type":"Point"}
}