{
  "type": "Feature",
  "properties": {
    "addr:full":"Pl Duc De Medinaceli, 6 Barcelona Barcelona 08002",
    "addr:housenumber":"6",
    "addr:postcode":"08002",
    "addr:street":"Pl Duc De Medinaceli",
    "iso:country":"ES",
    "sg:address":"Pl Duc De Medinaceli, 6",
    "sg:city":"Barcelona",
    "sg:orig_category":"Sindicatos De Trabajadores",
    "sg:phone":"+34 933 17 05 47",
    "sg:postcode":"08002",
    "sg:province":"Barcelona",
    "wof:name":"Confederacion Nacional Del Trabajo",
    "wof:placetype":"venue"
},
  "geometry": {"coordinates":[2.1789419651,41.3779754639],"type":"Point"}
}