{
  "type": "Feature",
  "properties": {
    "addr:full":"Calle de Pablo Picasso, 27 Villa Rio C\u00f3rdoba 14640",
    "addr:housenumber":"27",
    "addr:postcode":"14640",
    "addr:street":"Calle De Pablo Picasso;Rio Co\u0301Rdoba",
    "iso:country":"ES",
    "sg:address":"Calle de Pablo Picasso, 27",
    "sg:city":"Villa Rio",
    "sg:orig_category":"Tapicer\u00cdas",
    "sg:phone":"+34 957 17 61 40",
    "sg:postcode":"14640",
    "sg:province":"C\u00f3rdoba",
    "wof:name":"Rodriguez Cachinero Miguel",
    "wof:placetype":"venue"
},
  "geometry": {"coordinates":[-4.289208889,37.9823913574],"type":"Point"}
}