{
  "type": "Feature",
  "properties": {
    "addr:full":"Ctra. Madrid-cadiz, 294 Bailen Ja\u00e9n 23710",
    "addr:housenumber":"294",
    "addr:postcode":"23710",
    "addr:street":"Ctra. Madrid-Cadiz;Jae\u0301N",
    "iso:country":"ES",
    "sg:address":"Ctra. Madrid-cadiz, 294",
    "sg:city":"Bailen",
    "sg:orig_category":"Mec\u00c1nico Del Autom\u00d3vil",
    "sg:phone":"+34 953 67 12 65",
    "sg:postcode":"23710",
    "sg:province":"Ja\u00e9n",
    "wof:name":"Hijos De Antonio Mozas Parras S.l.",
    "wof:placetype":"venue"
},
  "geometry": {"coordinates":[-3.7828431129,38.0902023315],"type":"Point"}
}