{
  "type": "Feature",
  "properties": {
    "iso:country":"ES",
    "sg:address":"Calle de Infante Don Fernando, 11",
    "sg:city":"Antequera",
    "sg:orig_category":"Fabricaci\u00d3n, Importaci\u00d3n De L\u00c1mparas Y Bombillas",
    "sg:phone":"+34 952 70 18 71",
    "sg:postcode":"29200",
    "sg:province":"M\u00e1laga",
    "wof:name":"Perez Mu\u00f1oz Jose Luis",
    "wof:placetype":"venue"
},
  "geometry": {"coordinates":[-4.5599241257,37.0167884827],"type":"Point"}
}