{
  "type": "Feature",
  "properties": {
    "iso:country":"ES",
    "sg:address":"La Pe\u00f1a, 21",
    "sg:city":"El Pedernoso",
    "sg:orig_category":"Mec\u00c1nico Del Autom\u00d3vil",
    "sg:phone":"+34 967 16 43 42",
    "sg:postcode":"16638",
    "sg:province":"Cuenca",
    "wof:name":"Azcona Vieco S.l.",
    "wof:placetype":"venue"
},
  "geometry": {"coordinates":[-2.7463510036,39.4868049622],"type":"Point"}
}