{
  "type": "Feature",
  "properties": {
    "addr:full":"Plaz Espa\u00d1a, 10 Calamonte Badajoz 06810",
    "addr:housenumber":"10",
    "addr:postcode":"06810",
    "addr:street":"Plaz Espan\u0303A",
    "iso:country":"ES",
    "sg:address":"Plaz Espa\u00d1a, 10",
    "sg:city":"Calamonte",
    "sg:orig_category":"Molduras, Junquillos, Listones Y Molduras Perforadas",
    "sg:phone":"+34 924 32 38 64",
    "sg:postcode":"06810",
    "sg:province":"Badajoz",
    "wof:name":"Moreno Fernandez Alfonso Manuel",
    "wof:placetype":"venue"
},
  "geometry": {"coordinates":[-6.3847208023,38.88514328],"type":"Point"}
}