{
  "type": "Feature",
  "properties": {
    "addr:full":"Calle de Princesa, 13 Madrid Madrid 28008",
    "addr:housenumber":"13",
    "addr:postcode":"madrid;28008",
    "addr:street":"Calle De Princesa",
    "iso:country":"ES",
    "sg:address":"Calle de Princesa, 13",
    "sg:city":"Madrid",
    "sg:orig_category":"M\u00c9dicos: Oftalmolog\u00cda",
    "sg:phone":"+34 915 42 63 40",
    "sg:postcode":"28008",
    "sg:province":"Madrid",
    "wof:name":"Estudio Oftalmologico S. L.",
    "wof:placetype":"venue"
},
  "geometry": {"coordinates":[-3.712829113,40.4255981445],"type":"Point"}
}