{
  "type": "Feature",
  "properties": {
    "iso:country":"ES",
    "sg:address":"Calle de Espada, 24",
    "sg:city":"Alcorcon",
    "sg:orig_category":"Centros Comerciales Y Grandes Tiendas",
    "sg:phone":"+34 914 86 06 98",
    "sg:postcode":"28921",
    "sg:province":"Madrid",
    "wof:name":"Dong Xx  Boyong",
    "wof:placetype":"venue"
},
  "geometry": {"coordinates":[-3.8263499737,40.3461837769],"type":"Point"}
}