{
  "type": "Feature",
  "properties": {
    "iso:country":"ES",
    "sg:address":"Afueras, S/n",
    "sg:city":"S. Joan Labritja",
    "sg:orig_category":"Distribuci\u00d3n De Petr\u00d3leo Y Derivados",
    "sg:phone":"+34 971 33 31 97",
    "sg:postcode":"07810",
    "sg:province":"Islas Baleares",
    "wof:name":"Petroleos San Juan S.a.",
    "wof:placetype":"venue"
},
  "geometry": {"coordinates":[1.5125099421,39.0776100159],"type":"Point"}
}