{
  "type": "Feature",
  "properties": {
    "addr:full":"Carrer de Buenaventura Mu\u00d1oz, 23 Barcelona Barcelona 08018",
    "addr:housenumber":"23",
    "addr:postcode":"08018",
    "addr:street":"Carrer De Buenaventura Mun\u0303Oz",
    "iso:country":"ES",
    "sg:address":"Carrer de Buenaventura Mu\u00d1oz, 23",
    "sg:city":"Barcelona",
    "sg:orig_category":"Fabricaci\u00d3n, Venta De Cuadros, Accesorios Para Enmarcar",
    "sg:phone":"+34 933 00 02 93",
    "sg:postcode":"08018",
    "sg:province":"Barcelona",
    "wof:name":"Acutangle S.l.l.",
    "wof:placetype":"venue"
},
  "geometry": {"coordinates":[2.1849012375,41.391746521],"type":"Point"}
}