{
  "type": "Feature",
  "properties": {
    "iso:country":"ES",
    "sg:address":"C/ Capita Gaspar Ortiz, 37",
    "sg:city":"Elche",
    "sg:orig_category":"Confecci\u00d3n De Zapatos",
    "sg:phone":"+34 965 46 66 05",
    "sg:postcode":"03201",
    "sg:province":"Alicante",
    "wof:name":"Tapia Sanchez Rosario",
    "wof:placetype":"venue"
},
  "geometry": {"coordinates":[-0.7090280056,38.2653846741],"type":"Point"}
}