{
  "type": "Feature",
  "properties": {
    "iso:country":"ES",
    "sg:address":"Calle de Colegiata, 12",
    "sg:city":"Madrid",
    "sg:orig_category":"Fabricaci\u00d3n De Sobres, Bolsas Y Fundas",
    "sg:phone":"+34 913 65 34 34",
    "sg:postcode":"28012",
    "sg:province":"Madrid",
    "wof:name":"Simon Martin Francisco",
    "wof:placetype":"venue"
},
  "geometry": {"coordinates":[-3.706715107,40.413269043],"type":"Point"}
}