{
  "type": "Feature",
  "properties": {
    "addr:full":"Calle de San Martin, S/n Imarcoain Navarra 31119",
    "addr:housenumber":"s / n",
    "addr:postcode":"31119",
    "addr:street":"Calle De San Martin",
    "iso:country":"ES",
    "sg:address":"Calle de San Martin, S/n",
    "sg:city":"Imarcoain",
    "sg:orig_category":"Asociaciones, Organismos Culturales Y Socioeducativos",
    "sg:phone":"+34 948 31 27 32",
    "sg:postcode":"31119",
    "sg:province":"Navarra",
    "wof:name":"S.d.r.c. Urdi\u00f1a",
    "wof:placetype":"venue"
},
  "geometry": {"coordinates":[-1.5951639414,42.7345542908],"type":"Point"}
}