{
  "type": "Feature",
  "properties": {
    "iso:country":"ES",
    "sg:address":"Cami Creu, 32",
    "sg:city":"S. Cugat Valles",
    "sg:orig_category":"Contenedores (mercanc\u00cdas)",
    "sg:phone":"+34 936 74 16 70",
    "sg:postcode":"08172",
    "sg:province":"Barcelona",
    "wof:name":"Martinez Llamas Pedro",
    "wof:placetype":"venue"
},
  "geometry": {"coordinates":[2.0873019695,41.4763832092],"type":"Point"}
}