{
  "type": "Feature",
  "properties": {
    "iso:country":"ES",
    "sg:address":"Plaz Espa\u00d1a, 1",
    "sg:city":"Ciudad Real",
    "sg:orig_category":"Suministros Para Hoteles",
    "sg:phone":"+34 926 22 46 50",
    "sg:postcode":"13003",
    "sg:province":"Ciudad Real",
    "wof:name":"Distribucion Hostelera Rabadan S.l.l.",
    "wof:placetype":"venue"
},
  "geometry": {"coordinates":[-3.9272470474,38.9926757812],"type":"Point"}
}