{
  "type": "Feature",
  "properties": {
    "addr:full":"Calle de Congrio, 7 Negras Almer\u00eda 04116",
    "addr:housenumber":"7",
    "addr:postcode":"04116",
    "addr:street":"Calle De Congrio;Almeri\u0301A",
    "iso:country":"ES",
    "sg:address":"Calle de Congrio, 7",
    "sg:city":"Negras",
    "sg:orig_category":"Asociaciones, Organismos Culturales Y Socioeducativos",
    "sg:phone":"+34 950 38 81 58",
    "sg:postcode":"04116",
    "sg:province":"Almer\u00eda",
    "wof:name":"Jimenez Gallardo Diego",
    "wof:placetype":"venue"
},
  "geometry": {"coordinates":[-2.4679217339,36.8401641846],"type":"Point"}
}