{
  "type": "Feature",
  "properties": {
    "iso:country":"ES",
    "sg:address":"Calle de Playa De Louro, 4",
    "sg:city":"Estacion",
    "sg:orig_category":"Comercio, Reparaci\u00d3n De Bicicletas, De Motocicletas, De Accesorios",
    "sg:phone":"+34 918 51 02 30",
    "sg:postcode":"28400",
    "sg:province":"Madrid",
    "wof:name":"Moreno Rubio Angel",
    "wof:placetype":"venue"
},
  "geometry": {"coordinates":[-4.0075421333,40.6203231812],"type":"Point"}
}