{
  "type": "Feature",
  "properties": {
    "iso:country":"ES",
    "sg:address":"Calle de Silvio Abad (de), 10",
    "sg:city":"San Sebastian De Los Reyes",
    "sg:orig_category":"Agencias De Trabajo Temporal",
    "sg:phone":"+34 916 53 98 11",
    "sg:postcode":"28700",
    "sg:province":"Madrid",
    "sg:website":"www.altagestion.es",
    "wof:name":"Alta Gestion S.a.",
    "wof:placetype":"venue"
},
  "geometry": {"coordinates":[-3.6274347305,40.5436820984],"type":"Point"}
}