{
  "type": "Feature",
  "properties": {
    "addr:full":"Pi\u00f1eiro, 36 Pontesampaio Pontevedra 36690",
    "addr:housenumber":"36",
    "addr:postcode":"36690",
    "addr:street":"Pin\u0303Eiro",
    "iso:country":"ES",
    "sg:address":"Pi\u00f1eiro, 36",
    "sg:city":"Pontesampaio",
    "sg:orig_category":"Mercer\u00cda, Lencer\u00cda (al Por Menor)",
    "sg:phone":"+34 986 70 01 87",
    "sg:postcode":"36690",
    "sg:province":"Pontevedra",
    "wof:name":"Gonzalez Blanco Jose",
    "wof:placetype":"venue"
},
  "geometry": {"coordinates":[-8.6055440903,42.3392410278],"type":"Point"}
}