{
  "type": "Feature",
  "properties": {
    "addr:full":"Carr Jaume Ii, 48 Alcudia Islas Baleares 07400",
    "addr:housenumber":"48",
    "addr:postcode":"07400",
    "addr:street":"Carr Jaume Ii",
    "iso:country":"ES",
    "sg:address":"Carr Jaume Ii, 48",
    "sg:city":"Alcudia",
    "sg:orig_category":"Muebles, Minoristas",
    "sg:phone":"+34 971 54 71 16",
    "sg:postcode":"07400",
    "sg:province":"Islas Baleares",
    "wof:name":"Muebles Mestre S.l.",
    "wof:placetype":"venue"
},
  "geometry": {"coordinates":[3.1271100044,39.85105896],"type":"Point"}
}