{
  "type": "Feature",
  "properties": {
    "addr:full":"Calle de Ibiza, 29 Madrid Madrid 28009",
    "addr:housenumber":"29",
    "addr:postcode":"madrid;28009",
    "addr:street":"Calle De Ibiza",
    "iso:country":"ES",
    "sg:address":"Calle de Ibiza, 29",
    "sg:city":"Madrid",
    "sg:orig_category":"Cajas De Ahorro",
    "sg:phone":"+34 915 74 79 08",
    "sg:postcode":"28009",
    "sg:province":"Madrid",
    "sg:website":"www.ibercaja.es",
    "wof:name":"Caja De Ahorros Y Monte De Piedad De Zaragoza Aragon Y Rioja",
    "wof:placetype":"venue"
},
  "geometry": {"coordinates":[-3.6749839783,40.4184074402],"type":"Point"}
}