{
  "type": "Feature",
  "properties": {
    "addr:full":"Calle de Real, 111 Parla Madrid 28980",
    "addr:housenumber":"111",
    "addr:postcode":"28980",
    "addr:street":"Calle De Real",
    "iso:country":"ES",
    "sg:address":"Calle de Real, 111",
    "sg:city":"Parla",
    "sg:orig_category":"Mutuas De Seguros",
    "sg:phone":"+34 916 99 16 04",
    "sg:postcode":"28980",
    "sg:province":"Madrid",
    "wof:name":"Ibermutuamur",
    "wof:placetype":"venue"
},
  "geometry": {"coordinates":[-3.7684020996,40.2439651489],"type":"Point"}
}