{
  "type": "Feature",
  "properties": {
    "addr:full":"Carrer de Mossen Jacint Verdaguer, 115 Sant Vicen\u00c7 Dels Horts Barcelona 08620",
    "addr:housenumber":"115",
    "addr:postcode":"08620",
    "addr:street":"Carrer De Mossen Jacint Verdaguer;Sant Vicenc\u0327 Dels Horts Barcelona",
    "iso:country":"ES",
    "sg:address":"Carrer de Mossen Jacint Verdaguer, 115",
    "sg:city":"Sant Vicen\u00c7 Dels Horts",
    "sg:orig_category":"Bancos",
    "sg:phone":"+34 936 56 93 29",
    "sg:postcode":"08620",
    "sg:province":"Barcelona",
    "wof:name":"Auna Telecomunicaciones S.a.u.",
    "wof:placetype":"venue"
},
  "geometry": {"coordinates":[2.0079169273,41.3969802856],"type":"Point"}
}