{
  "type": "Feature",
  "properties": {
    "addr:full":"Calle de Augusto Gonzalez Linares, 36 Torrelavega Cantabria 39300",
    "addr:housenumber":"36",
    "addr:postcode":"39300",
    "addr:street":"Calle De Augusto Gonzalez Linares",
    "iso:country":"ES",
    "sg:address":"Calle de Augusto Gonzalez Linares, 36",
    "sg:city":"Torrelavega",
    "sg:orig_category":"Abogados",
    "sg:phone":"+34 942 89 20 38",
    "sg:postcode":"39300",
    "sg:province":"Cantabria",
    "wof:name":"Cano Vinagrero Severino",
    "wof:placetype":"venue"
},
  "geometry": {"coordinates":[-4.0482163429,43.3471374512],"type":"Point"}
}