{
  "type": "Feature",
  "properties": {
    "addr:full":"Huerto Buenavista, S/n Cullera Valencia 46400",
    "addr:housenumber":"s / n",
    "addr:postcode":"46400",
    "addr:street":"Buenavista",
    "iso:country":"ES",
    "sg:address":"Huerto Buenavista, S/n",
    "sg:city":"Cullera",
    "sg:orig_category":"Pe\u00d1as Y Asociaciones Varias",
    "sg:phone":"+34 961 72 10 50",
    "sg:postcode":"46400",
    "sg:province":"Valencia",
    "wof:name":"Cooperativa De Viviendas Jaime I",
    "wof:placetype":"venue"
},
  "geometry": {"coordinates":[-0.2562240064,39.1653251648],"type":"Point"}
}