{
  "type": "Feature",
  "properties": {
    "iso:country":"ES",
    "sg:address":"Calle de Loiola, 14",
    "sg:city":"Donostia-san Sebastian",
    "sg:orig_category":"Centros De Coordinaci\u00d3n",
    "sg:phone":"+34 943 42 84 20",
    "sg:postcode":"20005",
    "sg:province":"Guip\u00f9zcoa",
    "wof:name":"Centro Profesional De Programacion De Viviendas S.l.",
    "wof:placetype":"venue"
},
  "geometry": {"coordinates":[-1.9822740555,43.3174705505],"type":"Point"}
}