{
  "type": "Feature",
  "properties": {
    "addr:full":"Carr Joanot Martorell, De, 6 Carcaixent Valencia 46740",
    "addr:postcode":"46740",
    "addr:street":"Carr Joanot;De 6",
    "iso:country":"ES",
    "sg:address":"Carr Joanot Martorell, De, 6",
    "sg:city":"Carcaixent",
    "sg:orig_category":"Electromec\u00c1nica",
    "sg:phone":"+34 962 43 37 77",
    "sg:postcode":"46740",
    "sg:province":"Valencia",
    "wof:name":"Puig Llopis Bernardo Jose",
    "wof:placetype":"venue"
},
  "geometry": {"coordinates":[-0.4539079964,39.1210174561],"type":"Point"}
}