{
  "type": "Feature",
  "properties": {
    "iso:country":"ES",
    "sg:address":"Calle de Laracha, 11",
    "sg:city":"Coru\u00d1a",
    "sg:orig_category":"Electrodom\u00c9sticos (al Por Menor)",
    "sg:phone":"+34 981 27 45 81",
    "sg:postcode":"15010",
    "sg:province":"La Coru\u00f1a",
    "wof:name":"Pi\u00f1eiro Lago Divina",
    "wof:placetype":"venue"
},
  "geometry": {"coordinates":[-8.4189100266,43.3624687195],"type":"Point"}
}