{
  "type": "Feature",
  "properties": {
    "addr:full":"Calle de Idorsolo Kalea, 5 San Esteban Derio Vizcaya 48160",
    "addr:housenumber":"5",
    "addr:postcode":"48160",
    "addr:street":"Calle De Idorsolo Kalea",
    "iso:country":"ES",
    "sg:address":"Calle de Idorsolo Kalea, 5",
    "sg:city":"San Esteban Derio",
    "sg:orig_category":"Plomeros",
    "sg:phone":"+34 944 54 51 73",
    "sg:postcode":"48160",
    "sg:province":"Vizcaya",
    "wof:name":"York Bilbao S.l.",
    "wof:placetype":"venue"
},
  "geometry": {"coordinates":[-2.8826534748,43.3077392578],"type":"Point"}
}