{
  "type": "Feature",
  "properties": {
    "addr:full":"Calle de Oro, 54 Valladolid Valladolid 47012",
    "addr:housenumber":"54",
    "addr:postcode":"47012",
    "addr:street":"Calle De Oro",
    "iso:country":"ES",
    "sg:address":"Calle de Oro, 54",
    "sg:city":"Valladolid",
    "sg:orig_category":"Fabricaci\u00d3n De Cajas De Cart\u00d3n",
    "sg:phone":"+34 983 21 03 87",
    "sg:postcode":"47012",
    "sg:province":"Valladolid",
    "wof:name":"Cartonajes Valladolid S.l.",
    "wof:placetype":"venue"
},
  "geometry": {"coordinates":[-4.7096829414,41.6144485474],"type":"Point"}
}