{
  "type": "Feature",
  "properties": {
    "addr:full":"Pase Ramon Y Cajal, 1 Huesca Huesca 22001",
    "addr:housenumber":"1",
    "addr:postcode":"22001",
    "addr:street":"Ramon Y Cajal",
    "iso:country":"ES",
    "sg:address":"Pase Ramon Y Cajal, 1",
    "sg:city":"Huesca",
    "sg:orig_category":"Guarder\u00cdas",
    "sg:phone":"+34 974 24 42 60",
    "sg:postcode":"22001",
    "sg:province":"Huesca",
    "wof:name":"Banzo Ferrer Roberto",
    "wof:placetype":"venue"
},
  "geometry": {"coordinates":[-0.4044219851,42.1394119263],"type":"Point"}
}