{
  "type": "Feature",
  "properties": {
    "iso:country":"ES",
    "sg:address":"Calle de San Deogracias, 11",
    "sg:city":"Madrid",
    "sg:orig_category":"Centros Empresariales",
    "sg:phone":"+34 915 08 87 42",
    "sg:postcode":"28044",
    "sg:province":"Madrid",
    "wof:name":"El Espino Multiservicios S.l",
    "wof:placetype":"venue"
},
  "geometry": {"coordinates":[-3.7598259449,40.3714790344],"type":"Point"}
}