{
  "type": "Feature",
  "properties": {
    "addr:full":"Carr Osca, S/n Lleida Lleida 25198",
    "addr:housenumber":"s",
    "addr:postcode":"25198",
    "addr:street":"Carr Osca;/ N",
    "iso:country":"ES",
    "sg:address":"Carr Osca, S/n",
    "sg:city":"Lleida",
    "sg:orig_category":"Aguas (distribuci\u00d3n, Servicios)",
    "sg:phone":"+34 973 22 06 64",
    "sg:postcode":"25198",
    "sg:province":"Lleida",
    "wof:name":"Seragua S.a. Y Fomento De Construcciones",
    "wof:placetype":"venue"
},
  "geometry": {"coordinates":[0.5550400019,41.6703491211],"type":"Point"}
}