{
  "type": "Feature",
  "properties": {
    "iso:country":"ES",
    "sg:address":"Calle de Martin Romo, 80",
    "sg:city":"Santa Amalia",
    "sg:orig_category":"Asesor\u00cda Fiscal Y Jur\u00cddica",
    "sg:phone":"+34 924 83 04 43",
    "sg:postcode":"06410",
    "sg:province":"Badajoz",
    "wof:name":"Facila Barroso Jose Angel",
    "wof:placetype":"venue"
},
  "geometry": {"coordinates":[-6.0347437859,39.0760536194],"type":"Point"}
}