{
  "type": "Feature",
  "properties": {
    "addr:full":"Avgd Pius Xii, S/n Villarreal Castell\u00f3n 12540",
    "addr:housenumber":"s / n",
    "addr:postcode":"12540",
    "addr:street":"Xii",
    "iso:country":"ES",
    "sg:address":"Avgd Pius Xii, S/n",
    "sg:city":"Villarreal",
    "sg:orig_category":"Supermercados Y Hipermercados",
    "sg:phone":"+34 964 52 52 92",
    "sg:postcode":"12540",
    "sg:province":"Castell\u00f3n",
    "sg:website":"www.capraboacasa.com",
    "wof:name":"Caprabo S.a.",
    "wof:placetype":"venue"
},
  "geometry": {"coordinates":[-0.0952939987,39.9453048706],"type":"Point"}
}