{
  "type": "Feature",
  "properties": {
    "iso:country":"ES",
    "sg:address":"Poli Umbria (la), S/n",
    "sg:city":"Andorra",
    "sg:orig_category":"Negocio De Materiales De Construcci\u00d3n",
    "sg:phone":"+34 978 84 30 53",
    "sg:postcode":"44500",
    "sg:province":"Teruel",
    "wof:name":"Algal S.l.",
    "wof:placetype":"venue"
},
  "geometry": {"coordinates":[-0.4313729107,41.0184288025],"type":"Point"}
}