{
  "type": "Feature",
  "properties": {
    "iso:country":"ES",
    "sg:address":"Calle de Virgen Del Carmen, 10",
    "sg:city":"Donostia-san Sebastian",
    "sg:orig_category":"Ense\u00d1anza, Formaci\u00d3n Profesional: Aprendizaje",
    "sg:phone":"+34 943 27 26 28",
    "sg:postcode":"20012",
    "sg:province":"Guip\u00f9zcoa",
    "wof:name":"Fundacion Sarea",
    "wof:placetype":"venue"
},
  "geometry": {"coordinates":[-1.9714989662,43.3165664673],"type":"Point"}
}