{
  "type": "Feature",
  "properties": {
    "iso:country":"ES",
    "sg:address":"Calle de Real, 13",
    "sg:city":"Buzanada",
    "sg:orig_category":"Peluqueros: De Se\u00d1oras",
    "sg:phone":"+34 922 76 55 11",
    "sg:postcode":"38626",
    "sg:province":"Santa Cruz De Tenerife",
    "wof:name":"Gonzalez Perez Valentin",
    "wof:placetype":"venue"
},
  "geometry": {"coordinates":[-16.6548480988,28.0722541809],"type":"Point"}
}