{
  "type": "Feature",
  "properties": {
    "iso:country":"ES",
    "sg:address":"Calle de Pozo, 5",
    "sg:city":"Valdestillas",
    "sg:orig_category":"Librer\u00cdas",
    "sg:phone":"+34 983 55 11 18",
    "sg:postcode":"47240",
    "sg:province":"Valladolid",
    "wof:name":"Lozano Alvarez Angel",
    "wof:placetype":"venue"
},
  "geometry": {"coordinates":[-4.7702522278,41.4785842896],"type":"Point"}
}