{
  "type": "Feature",
  "properties": {
    "iso:country":"ES",
    "sg:address":"Avda Rey Don Jaime, 98",
    "sg:city":"Castellon",
    "sg:orig_category":"Asesor\u00cda Fiscal Y Jur\u00cddica",
    "sg:phone":"+34 964 25 12 17",
    "sg:postcode":"12001",
    "sg:province":"Castell\u00f3n",
    "wof:name":"Barrios Martinez Eva Maria",
    "wof:placetype":"venue"
},
  "geometry": {"coordinates":[-0.0390900001,39.9866714478],"type":"Point"}
}