{
  "type": "Feature",
  "properties": {
    "addr:full":"Plaz De Santa Maria, 12 Benavente Zamora 49600",
    "addr:housenumber":"12",
    "addr:postcode":"49600",
    "addr:street":"Plaz;Santa Maria",
    "iso:country":"ES",
    "sg:address":"Plaz De Santa Maria, 12",
    "sg:city":"Benavente",
    "sg:orig_category":"\u00d3ptica: Instrumentos (fabricaci\u00d3n)",
    "sg:phone":"+34 980 63 09 24",
    "sg:postcode":"49600",
    "sg:province":"Zamora",
    "wof:name":"Conde De Castro C.b.",
    "wof:placetype":"venue"
},
  "geometry": {"coordinates":[-5.6865839958,42.0086174011],"type":"Point"}
}