{
  "type": "Feature",
  "properties": {
    "addr:full":"Rbla Brasil, 29 Barcelona Barcelona 08028",
    "addr:housenumber":"29",
    "addr:postcode":"08028",
    "addr:street":"Rbla Brasil",
    "iso:country":"ES",
    "sg:address":"Rbla Brasil, 29",
    "sg:city":"Barcelona",
    "sg:orig_category":"Molduras, Junquillos, Listones Y Molduras Perforadas",
    "sg:phone":"+34 934 90 91 09",
    "sg:postcode":"08028",
    "sg:province":"Barcelona",
    "wof:name":"Pont Simon Maria Eulalia",
    "wof:placetype":"venue"
},
  "geometry": {"coordinates":[2.1293940544,41.3774147034],"type":"Point"}
}