{
  "type": "Feature",
  "properties": {
    "addr:full":"Prj Hoya Panduro, S/n Las Eras Albacete 02214",
    "addr:housenumber":"s / n",
    "addr:postcode":"02214",
    "addr:street":"Las Eras",
    "iso:country":"ES",
    "sg:address":"Prj Hoya Panduro, S/n",
    "sg:city":"Las Eras",
    "sg:orig_category":"Productores Recolectores, Venta Directa De Vinos",
    "sg:phone":"+34 967 58 60 05",
    "sg:postcode":"02214",
    "sg:province":"Albacete",
    "wof:name":"Cooperativa Vinicola Erzul S.c.l.",
    "wof:placetype":"venue"
},
  "geometry": {"coordinates":[-1.2513289452,39.2607116699],"type":"Point"}
}