{
  "type": "Feature",
  "properties": {
    "addr:full":"Pque. Tecn. De Asturias, S/n Cayes Asturias 33428",
    "addr:housenumber":"s / n",
    "addr:postcode":"33428",
    "iso:country":"ES",
    "sg:address":"Pque. Tecn. De Asturias, S/n",
    "sg:city":"Cayes",
    "sg:orig_category":"Estudios, Instalaci\u00d3n De Climatizaci\u00d3n",
    "sg:phone":"+34 985 26 91 00",
    "sg:postcode":"33428",
    "sg:province":"Asturias",
    "wof:name":"Suministros E Instalaciones Medioambientales Y Tecnicas De La Edificacion S.l.",
    "wof:placetype":"venue"
},
  "geometry": {"coordinates":[-5.8358402252,43.4143867493],"type":"Point"}
}