{
  "type": "Feature",
  "properties": {
    "iso:country":"ES",
    "sg:address":"Calle de Lagasca, 142",
    "sg:city":"Madrid",
    "sg:orig_category":"Jefes De Obra Y Construcciones",
    "sg:phone":"+34 915 61 56 31",
    "sg:postcode":"28006",
    "sg:province":"Madrid",
    "wof:name":"Asesores Construccion S. A.",
    "wof:placetype":"venue"
},
  "geometry": {"coordinates":[-3.6842384338,40.43724823],"type":"Point"}
}