{
  "type": "Feature",
  "properties": {
    "addr:full":"Avda Andalucia, 17 Carrion De Los Cespedes Sevilla 41820",
    "addr:housenumber":"17",
    "addr:postcode":"41820",
    "addr:street":"Avda Andalucia",
    "iso:country":"ES",
    "sg:address":"Avda Andalucia, 17",
    "sg:city":"Carrion De Los Cespedes",
    "sg:orig_category":"Cervecer\u00cdas",
    "sg:phone":"+34 954 75 50 34",
    "sg:postcode":"41820",
    "sg:province":"Sevilla",
    "wof:name":"Eurotel-sur S.l.",
    "wof:placetype":"venue"
},
  "geometry": {"coordinates":[-6.3281121254,37.3670196533],"type":"Point"}
}