{
  "type": "Feature",
  "properties": {
    "iso:country":"ES",
    "sg:address":"Carrer de Newton, 18",
    "sg:city":"S. Esteve Sesrovires",
    "sg:orig_category":"Comercio De Piezas De Recambio Y De Accesorios De Veh\u00cdculos, Veh\u00cdculos Industriales",
    "sg:phone":"+34 937 71 55 02",
    "sg:postcode":"08635",
    "sg:province":"Barcelona",
    "wof:name":"Lignotock S.a.",
    "wof:placetype":"venue"
},
  "geometry": {"coordinates":[1.8827209473,41.481262207],"type":"Point"}
}