{
  "type": "Feature",
  "properties": {
    "addr:full":"Rua Gradin, S/n Estrada Pontevedra 36680",
    "addr:housenumber":"s / n",
    "addr:postcode":"36680",
    "addr:street":"Rua Gradin;Estrada Pontevedra",
    "iso:country":"ES",
    "sg:address":"Rua Gradin, S/n",
    "sg:city":"Estrada",
    "sg:orig_category":"Torneros Sobre Madera",
    "sg:phone":"+34 986 57 09 82",
    "sg:postcode":"36680",
    "sg:province":"Pontevedra",
    "wof:name":"Industrias La Moderna S.c.t.",
    "wof:placetype":"venue"
},
  "geometry": {"coordinates":[-8.4898071289,42.692440033],"type":"Point"}
}