{
  "type": "Feature",
  "properties": {
    "iso:country":"ES",
    "sg:address":"Rua Romana, 24",
    "sg:city":"Olite",
    "sg:orig_category":"Panader\u00cdas, Panader\u00cdas",
    "sg:phone":"+34 948 74 01 17",
    "sg:postcode":"31390",
    "sg:province":"Navarra",
    "wof:name":"Umbresarre Sl",
    "wof:placetype":"venue"
},
  "geometry": {"coordinates":[-1.6518290043,42.4796409607],"type":"Point"}
}