{
  "type": "Feature",
  "properties": {
    "iso:country":"ES",
    "sg:address":"Carrer de Sant Isidre, 47",
    "sg:city":"Calella",
    "sg:orig_category":"Florister\u00cdas",
    "sg:phone":"+34 937 66 16 90",
    "sg:postcode":"08370",
    "sg:province":"Barcelona",
    "wof:name":"Bancells Gascons Juan",
    "wof:placetype":"venue"
},
  "geometry": {"coordinates":[2.6558890343,41.6128158569],"type":"Point"}
}