{
  "type": "Feature",
  "properties": {
    "iso:country":"ES",
    "sg:address":"Calle de Crucero Baleares, 56",
    "sg:city":"Puerto De Santa Maria",
    "sg:orig_category":"Peluquer\u00cdas, Peluquer\u00cda Mixta",
    "sg:phone":"+34 956 85 08 34",
    "sg:postcode":"11500",
    "sg:province":"C\u00e1diz",
    "wof:name":"Deriu Mangatia Maria",
    "wof:placetype":"venue"
},
  "geometry": {"coordinates":[-6.2381010056,36.5932159424],"type":"Point"}
}