{
  "type": "Feature",
  "properties": {
    "iso:country":"ES",
    "sg:address":"Calle de Soledad, 5",
    "sg:city":"Jaraiz Vera",
    "sg:orig_category":"Ense\u00d1anza: Profesiones Art\u00cdsticas",
    "sg:phone":"+34 927 17 06 55",
    "sg:postcode":"10400",
    "sg:province":"C\u00e1ceres",
    "wof:name":"Merino Gutierrez Manuel",
    "wof:placetype":"venue"
},
  "geometry": {"coordinates":[-5.7516927719,40.0606231689],"type":"Point"}
}