{
  "type": "Feature",
  "properties": {
    "addr:full":"Calle de Progreso, 10 Espinosa De Los Monteros Burgos 09560",
    "addr:housenumber":"10",
    "addr:postcode":"09560",
    "addr:street":"Calle De Progreso",
    "iso:country":"ES",
    "sg:address":"Calle de Progreso, 10",
    "sg:city":"Espinosa De Los Monteros",
    "sg:orig_category":"Asociaciones, Organismos Culturales Y Socioeducativos",
    "sg:phone":"+34 947 12 00 03",
    "sg:postcode":"09560",
    "sg:province":"Burgos",
    "wof:name":"Caja De Ahorros Municipal De Burgos",
    "wof:placetype":"venue"
},
  "geometry": {"coordinates":[-3.5473821163,43.0753707886],"type":"Point"}
}