{
  "type": "Feature",
  "properties": {
    "iso:country":"ES",
    "sg:address":"Calle de Corredera (la), 52",
    "sg:city":"Montilla",
    "sg:orig_category":"Alimentaci\u00d3n General (al Por Menor)",
    "sg:phone":"+34 957 65 08 28",
    "sg:postcode":"14550",
    "sg:province":"C\u00f3rdoba",
    "wof:name":"Armenta Redondo Manuel",
    "wof:placetype":"venue"
},
  "geometry": {"coordinates":[-4.6387248039,37.5883483887],"type":"Point"}
}