{
  "type": "Feature",
  "properties": {
    "addr:full":"Pol Ind Juan Carlos I, S/n Almussafes Valencia 46440",
    "addr:housenumber":"s / n",
    "addr:postcode":"46440",
    "addr:street":"Carlos I",
    "iso:country":"ES",
    "sg:address":"Pol Ind Juan Carlos I, S/n",
    "sg:city":"Almussafes",
    "sg:orig_category":"Maquinaria Para Industrias Diversas",
    "sg:phone":"+34 961 76 72 00",
    "sg:postcode":"46440",
    "sg:province":"Valencia",
    "wof:name":"Mecanizados S. A.",
    "wof:placetype":"venue"
},
  "geometry": {"coordinates":[-0.4169729948,39.3076934814],"type":"Point"}
}