{
  "type": "Feature",
  "properties": {
    "addr:full":"Calle de Gonzalez Adalid, 12 Catedral Murcia 30001",
    "addr:housenumber":"12",
    "addr:postcode":"30001",
    "addr:street":"Calle De Gonzalez Adalid",
    "iso:country":"ES",
    "sg:address":"Calle de Gonzalez Adalid, 12",
    "sg:city":"Catedral",
    "sg:orig_category":"Ropa Para Se\u00d1oras (al Por Menor)",
    "sg:phone":"+34 968 22 11 08",
    "sg:postcode":"30001",
    "sg:province":"Murcia",
    "wof:name":"Mami Cavi S.l.",
    "wof:placetype":"venue"
},
  "geometry": {"coordinates":[-1.1295150518,37.98620224],"type":"Point"}
}