{
  "type": "Feature",
  "properties": {
    "addr:full":"Carrobide, 15 Atarrabia Navarra 31610",
    "addr:housenumber":"15",
    "addr:postcode":"31610",
    "addr:street":"Carrobide",
    "iso:country":"ES",
    "sg:address":"Carrobide, 15",
    "sg:city":"Atarrabia",
    "sg:orig_category":"Molduras, Junquillos, Listones Y Molduras Perforadas",
    "sg:phone":"+34 948 33 32 71",
    "sg:postcode":"31610",
    "sg:province":"Navarra",
    "wof:name":"Sistelcom-telemensaje S.a.",
    "wof:placetype":"venue"
},
  "geometry": {"coordinates":[-1.6118479967,42.8337860107],"type":"Point"}
}