{
  "type": "Feature",
  "properties": {
    "addr:full":"Plaz General Monasterio, 2 Lanzahita \u00c1vila 05490",
    "addr:housenumber":"2",
    "addr:postcode":"05490",
    "addr:street":"Monasterio;A\u0301Vila",
    "iso:country":"ES",
    "sg:address":"Plaz General Monasterio, 2",
    "sg:city":"Lanzahita",
    "sg:orig_category":"Farmacias",
    "sg:phone":"+34 920 37 88 93",
    "sg:postcode":"05490",
    "sg:province":"\u00c1vila",
    "wof:name":"Martin Del Pozo Ana Maria",
    "wof:placetype":"venue"
},
  "geometry": {"coordinates":[-4.9367699623,40.2035636902],"type":"Point"}
}