{
  "type": "Feature",
  "properties": {
    "addr:full":"Calle de Visconti, 20 Tarazona Zaragoza 50500",
    "addr:housenumber":"20",
    "addr:postcode":"50500",
    "addr:street":"Calle De Visconti",
    "iso:country":"ES",
    "sg:address":"Calle de Visconti, 20",
    "sg:city":"Tarazona",
    "sg:orig_category":"Muebles, Minoristas",
    "sg:phone":"+34 976 64 11 91",
    "sg:postcode":"50500",
    "sg:province":"Zaragoza",
    "wof:name":"Docando Lamana Jose Luis",
    "wof:placetype":"venue"
},
  "geometry": {"coordinates":[-1.7260789871,41.9052009583],"type":"Point"}
}