{
  "type": "Feature",
  "properties": {
    "addr:full":"Carrer de Ample, 11 Terrassa Barcelona 08225",
    "addr:housenumber":"11",
    "addr:postcode":"08225",
    "addr:street":"Carrer De Ample",
    "iso:country":"ES",
    "sg:address":"Carrer de Ample, 11",
    "sg:city":"Terrassa",
    "sg:orig_category":"Arquitectos",
    "sg:phone":"+34 937 35 12 89",
    "sg:postcode":"08225",
    "sg:province":"Barcelona",
    "wof:name":"Graell Escobar Josep Maria",
    "wof:placetype":"venue"
},
  "geometry": {"coordinates":[2.0142290592,41.5727043152],"type":"Point"}
}