{
  "type": "Feature",
  "properties": {
    "addr:full":"Calle de Zubigane, 8 Sopelana Vizcaya 48600",
    "addr:housenumber":"8",
    "addr:postcode":"48600",
    "addr:street":"Calle De Zubigane",
    "iso:country":"ES",
    "sg:address":"Calle de Zubigane, 8",
    "sg:city":"Sopelana",
    "sg:orig_category":"Caf\u00c9s, Bares, Cervecer\u00cdas",
    "sg:phone":"+34 946 76 44 52",
    "sg:postcode":"48600",
    "sg:province":"Vizcaya",
    "wof:name":"Javier Mu\u00f1oz Madariaga",
    "wof:placetype":"venue"
},
  "geometry": {"coordinates":[-2.9801719189,43.3798446655],"type":"Point"}
}