{
  "type": "Feature",
  "properties": {
    "iso:country":"ES",
    "sg:address":"Calle de Antonio Concha, 4",
    "sg:city":"Navalmoral Mata",
    "sg:orig_category":"Doctores En Medicina",
    "sg:phone":"+34 927 53 31 73",
    "sg:postcode":"10300",
    "sg:province":"C\u00e1ceres",
    "wof:name":"Nieto Oviedo Eva Beatriz",
    "wof:placetype":"venue"
},
  "geometry": {"coordinates":[-5.5346736908,39.8902397156],"type":"Point"}
}