{
  "type": "Feature",
  "properties": {
    "addr:full":"Calle de Puerto Neveros, 1 Nieves-el Lucero Madrid 28935",
    "addr:housenumber":"1",
    "addr:postcode":"28935",
    "addr:street":"Calle De Puerto Neveros;Nieves-El",
    "iso:country":"ES",
    "sg:address":"Calle de Puerto Neveros, 1",
    "sg:city":"Nieves-el Lucero",
    "sg:orig_category":"Edici\u00d3n De Diarios, Revistas, Boletines",
    "sg:phone":"+34 916 16 53 63",
    "sg:postcode":"28935",
    "sg:province":"Madrid",
    "sg:website":"www.autoestudio.net",
    "wof:name":"Driving Academy Consulting S.l.",
    "wof:placetype":"venue"
},
  "geometry": {"coordinates":[-3.9280939102,40.3081817627],"type":"Point"}
}