{
  "type": "Feature",
  "properties": {
    "addr:full":"Carr Ramon Soldevila, 7 Lleida Lleida 25002",
    "addr:housenumber":"7",
    "addr:postcode":"25002",
    "addr:street":"Carr Ramon Soldevila",
    "iso:country":"ES",
    "sg:address":"Carr Ramon Soldevila, 7",
    "sg:city":"Lleida",
    "sg:orig_category":"Deportes Diversos",
    "sg:phone":"+34 973 27 93 44",
    "sg:postcode":"25002",
    "sg:province":"Lleida",
    "wof:name":"Federacio Catalana De Caea",
    "wof:placetype":"venue"
},
  "geometry": {"coordinates":[0.6202409863,41.6104125977],"type":"Point"}
}