{
  "type": "Feature",
  "properties": {
    "iso:country":"ES",
    "sg:address":"Cno Membrio (zona Industrial), S/n",
    "sg:city":"San Vicente Alcantara",
    "sg:orig_category":"Fabricaci\u00d3n, Instalaci\u00d3n Y Reparaci\u00d3n De Bombas",
    "sg:phone":"+34 924 41 06 37",
    "sg:postcode":"06500",
    "sg:province":"Badajoz",
    "wof:name":"Ormapa Suministros Industriales S.l.",
    "wof:placetype":"venue"
},
  "geometry": {"coordinates":[-7.1375741959,39.3639183044],"type":"Point"}
}