{
  "type": "Feature",
  "properties": {
    "iso:country":"ES",
    "sg:address":"Calle de Padre Bayle, 11",
    "sg:city":"Caceres",
    "sg:orig_category":"Farmacias",
    "sg:phone":"+34 927 24 49 61",
    "sg:postcode":"10004",
    "sg:province":"C\u00e1ceres",
    "wof:name":"Sanguino Sanchez Francisco Javier",
    "wof:placetype":"venue"
},
  "geometry": {"coordinates":[-6.3754248619,39.4789352417],"type":"Point"}
}