{
  "type": "Feature",
  "properties": {
    "iso:country":"ES",
    "sg:address":"Avda General Sanjurjo, 146",
    "sg:city":"Coru\u00d1a",
    "sg:orig_category":"Supermercados Y Hipermercados",
    "sg:phone":"+34 981 13 07 31",
    "sg:postcode":"15006",
    "sg:province":"La Coru\u00f1a",
    "wof:name":"Distribuidora Internacional De Alimentacion",
    "wof:placetype":"venue"
},
  "geometry": {"coordinates":[-8.3938140869,43.353603363],"type":"Point"}
}