{
  "type": "Feature",
  "properties": {
    "addr:full":"Carr Picasso, 41 Mao Islas Baleares 07703",
    "addr:housenumber":"41",
    "addr:postcode":"07703",
    "addr:street":"Carr Picasso",
    "iso:country":"ES",
    "sg:address":"Carr Picasso, 41",
    "sg:city":"Mao",
    "sg:orig_category":"Reciclaje, Desguace De Veh\u00cdculos",
    "sg:phone":"+34 971 36 71 02",
    "sg:postcode":"07703",
    "sg:province":"Islas Baleares",
    "wof:name":"Alarcon Cuadros S.l.",
    "wof:placetype":"venue"
},
  "geometry": {"coordinates":[4.2599854469,39.8798942566],"type":"Point"}
}