{
  "type": "Feature",
  "properties": {
    "addr:full":"Av Baladrar-baladrar, 20 Baladrar-punta Estrella Alicante 03720",
    "addr:housenumber":"20",
    "addr:postcode":"03720",
    "addr:street":"Av Baladrar-Baladrar",
    "iso:country":"ES",
    "sg:address":"Av Baladrar-baladrar, 20",
    "sg:city":"Baladrar-punta Estrella",
    "sg:orig_category":"Quincaller\u00cda (al Por Menor)",
    "sg:phone":"+34 966 49 89 44",
    "sg:postcode":"03720",
    "sg:province":"Alicante",
    "wof:name":"Ivars Ivars Vicente",
    "wof:placetype":"venue"
},
  "geometry": {"coordinates":[-0.4810059965,38.3452033997],"type":"Point"}
}