{
  "type": "Feature",
  "properties": {
    "addr:full":"Calle de Union (de La), 3 Alcobendas Madrid 28100",
    "addr:postcode":"28100",
    "addr:street":"Calle De Union De La 3",
    "iso:country":"ES",
    "sg:address":"Calle de Union (de La), 3",
    "sg:city":"Alcobendas",
    "sg:orig_category":"Inform\u00c1tica: Soportes De Informaci\u00d3n, Suministros & Accesorios",
    "sg:phone":"+34 916 52 21 05",
    "sg:postcode":"28100",
    "sg:province":"Madrid",
    "sg:website":"www.cleverimpresion.com",
    "wof:name":"Clever Tiendas De Ocio S.l.",
    "wof:placetype":"venue"
},
  "geometry": {"coordinates":[-3.6308629513,40.5441627502],"type":"Point"}
}