{
  "type": "Feature",
  "properties": {
    "iso:country":"ES",
    "sg:address":"Carrer de Asensi Vega, 9",
    "sg:city":"Caldes Montbui",
    "sg:orig_category":"Panader\u00cdas, Panader\u00cdas",
    "sg:phone":"+34 938 65 47 00",
    "sg:postcode":"08140",
    "sg:province":"Barcelona",
    "wof:name":"Especialitats Forn De S. Jaume S. L.",
    "wof:placetype":"venue"
},
  "geometry": {"coordinates":[2.1631948948,41.6323928833],"type":"Point"}
}