{
  "type": "Feature",
  "properties": {
    "addr:full":"Cami Can Calders, 8 S. Cugat Valles Barcelona 08173",
    "addr:housenumber":"8",
    "addr:postcode":"08173",
    "addr:street":"Barcelona",
    "iso:country":"ES",
    "sg:address":"Cami Can Calders, 8",
    "sg:city":"S. Cugat Valles",
    "sg:orig_category":"Aparatos, Material Y Suministros Para Laboratorios",
    "sg:phone":"+34 935 83 63 49",
    "sg:postcode":"08173",
    "sg:province":"Barcelona",
    "sg:website":"www.dpcweb.com",
    "wof:name":"Dpc Dipesa S.a.",
    "wof:placetype":"venue"
},
  "geometry": {"coordinates":[2.0999219418,41.4724197388],"type":"Point"}
}