{
  "type": "Feature",
  "properties": {
    "addr:full":"Carrer de Moli, 48 Esplugues Llobregat Barcelona 08950",
    "addr:housenumber":"48",
    "addr:postcode":"08950",
    "addr:street":"Carrer De Moli",
    "iso:country":"ES",
    "sg:address":"Carrer de Moli, 48",
    "sg:city":"Esplugues Llobregat",
    "sg:orig_category":"Organismos De Turismo",
    "sg:phone":"+34 934 73 16 93",
    "sg:postcode":"08950",
    "sg:province":"Barcelona",
    "sg:website":"www.hosteltur.com",
    "wof:name":"Ideas Y Publicidad De Baleares S.a.",
    "wof:placetype":"venue"
},
  "geometry": {"coordinates":[2.097315073,41.3717956543],"type":"Point"}
}