{
  "type": "Feature",
  "properties": {
    "addr:full":"Jose Ana Fdez., 7 Bre\u00f1a Baja Santa Cruz De Tenerife 38712",
    "addr:housenumber":"7",
    "addr:postcode":"38712",
    "addr:street":"Fdez.",
    "iso:country":"ES",
    "sg:address":"Jose Ana Fdez., 7",
    "sg:city":"Bre\u00f1a Baja",
    "sg:orig_category":"Ense\u00d1anza, Formaci\u00d3n Profesional: Aprendizaje",
    "sg:phone":"+34 922 42 05 08",
    "sg:postcode":"38712",
    "sg:province":"Santa Cruz De Tenerife",
    "wof:name":"Fundacion Galileo Galilei - Inaf Fundacion Canaria",
    "wof:placetype":"venue"
},
  "geometry": {"coordinates":[-17.7672138214,28.6476554871],"type":"Point"}
}