{
  "type": "Feature",
  "properties": {
    "iso:country":"ES",
    "sg:address":"Ctra Madrid-lisboa, Km. 0179,5",
    "sg:city":"Navalmoral Mata",
    "sg:orig_category":"Empresas De Portes Y Mensajer\u00cda",
    "sg:phone":"+34 927 53 82 03",
    "sg:postcode":"10300",
    "sg:province":"C\u00e1ceres",
    "wof:name":"Arroyotrans-tdi S.l.",
    "wof:placetype":"venue"
},
  "geometry": {"coordinates":[-5.5292825699,39.892074585],"type":"Point"}
}