{
  "type": "Feature",
  "properties": {
    "iso:country":"ES",
    "sg:address":"Carrer de Frederic Soler, 7",
    "sg:city":"Prat Llobregat",
    "sg:orig_category":"Ropa Para Se\u00d1oras (al Por Menor)",
    "sg:phone":"+34 933 79 42 32",
    "sg:postcode":"08820",
    "sg:province":"Barcelona",
    "wof:name":"Peula Ruiz Maria Del Carmen",
    "wof:placetype":"venue"
},
  "geometry": {"coordinates":[2.0949840546,41.3278541565],"type":"Point"}
}