{
  "type": "Feature",
  "properties": {
    "iso:country":"ES",
    "sg:address":"Calle de Domingo Garcia De La Fuente, 4",
    "sg:city":"Gijon",
    "sg:orig_category":"Librer\u00cdas",
    "sg:phone":"+34 985 99 08 79",
    "sg:postcode":"33205",
    "sg:province":"Asturias",
    "wof:name":"Pentagono Multiple De Escritura De Papeleria S.l.",
    "wof:placetype":"venue"
},
  "geometry": {"coordinates":[-5.6623249054,43.5366821289],"type":"Point"}
}