{
  "type": "Feature",
  "properties": {
    "iso:country":"ES",
    "sg:address":"Tv. P. Ori, 8",
    "sg:city":"Iru\u00f1a",
    "sg:orig_category":"Molduras, Junquillos, Listones Y Molduras Perforadas",
    "sg:phone":"+34 948 24 80 68",
    "sg:postcode":"31006",
    "sg:province":"Navarra",
    "wof:name":"Suarez Rojas Luis Arturo",
    "wof:placetype":"venue"
},
  "geometry": {"coordinates":[-1.6437540054,42.81275177],"type":"Point"}
}