{
  "type": "Feature",
  "properties": {
    "addr:full":"Calle de Diputacion Provincial, S/n Nerja M\u00e1laga 29780",
    "addr:postcode":"29780",
    "addr:street":"Calle De Diputacion Provincial S / N",
    "iso:country":"ES",
    "sg:address":"Calle de Diputacion Provincial, S/n",
    "sg:city":"Nerja",
    "sg:orig_category":"Fabricaci\u00d3n De Peines Y De Accesorios De Peluquer\u00cda",
    "sg:phone":"+34 952 52 57 94",
    "sg:postcode":"29780",
    "sg:province":"M\u00e1laga",
    "wof:name":"Sanchez Martin Maria Victoria",
    "wof:placetype":"venue"
},
  "geometry": {"coordinates":[-3.8787889481,36.7454528809],"type":"Point"}
}