{
  "type": "Feature",
  "properties": {
    "addr:full":"Plaz De San Francisco, 4 Benavente Zamora 49600",
    "addr:housenumber":"4",
    "addr:postcode":"49600",
    "addr:street":"Plaz;San Francisco",
    "iso:country":"ES",
    "sg:address":"Plaz De San Francisco, 4",
    "sg:city":"Benavente",
    "sg:orig_category":"Abogados",
    "sg:phone":"+34 980 63 00 88",
    "sg:postcode":"49600",
    "sg:province":"Zamora",
    "wof:name":"Administracion De Justicia",
    "wof:placetype":"venue"
},
  "geometry": {"coordinates":[-5.6756453514,42.0028800964],"type":"Point"}
}