{
  "type": "Feature",
  "properties": {
    "iso:country":"ES",
    "sg:address":"Galerias Pl. Major, 44",
    "sg:city":"Palma",
    "sg:orig_category":"Camiser\u00cda Y Ropa Interior Masculina (al Por Menor)",
    "sg:phone":"+34 971 71 67 06",
    "sg:postcode":"07002",
    "sg:province":"Islas Baleares",
    "wof:name":"Capella Ferra Alejandro",
    "wof:placetype":"venue"
},
  "geometry": {"coordinates":[2.6469399929,39.5714836121],"type":"Point"}
}