{
  "type": "Feature",
  "properties": {
    "iso:country":"ES",
    "sg:address":"Calle de Television Espa\u00d1ola, 40",
    "sg:city":"Prado Del Rey",
    "sg:orig_category":"Productores Recolectores, Venta Directa De Vinos",
    "sg:phone":"+34 956 72 30 98",
    "sg:postcode":"11660",
    "sg:province":"C\u00e1diz",
    "wof:name":"Holgado Escudero Maria Mercedes",
    "wof:placetype":"venue"
},
  "geometry": {"coordinates":[-5.5539288521,36.7886886597],"type":"Point"}
}