{
  "type": "Feature",
  "properties": {
    "iso:country":"ES",
    "sg:address":"Calle de Virgen De Setefilla, 1",
    "sg:city":"Sevilla",
    "sg:orig_category":"Asociaciones Y Clubs Deportivos",
    "sg:phone":"+34 954 27 63 69",
    "sg:postcode":"41011",
    "sg:province":"Sevilla",
    "wof:name":"Kim  Tai Myung",
    "wof:placetype":"venue"
},
  "geometry": {"coordinates":[-5.9993810654,37.3787231445],"type":"Point"}
}