{
  "type": "Feature",
  "properties": {
    "addr:full":"Ctra Arcos, S/n Burgos Burgos 09001",
    "addr:housenumber":"s / n",
    "addr:postcode":"09001",
    "addr:street":"Ctra Arcos",
    "iso:country":"ES",
    "sg:address":"Ctra Arcos, S/n",
    "sg:city":"Burgos",
    "sg:orig_category":"Lecher\u00cdas",
    "sg:phone":"+34 947 20 86 14",
    "sg:postcode":"09001",
    "sg:province":"Burgos",
    "wof:name":"Gonzalez Andres Alejandro",
    "wof:placetype":"venue"
},
  "geometry": {"coordinates":[-3.7175500393,42.3179740906],"type":"Point"}
}