{
  "type": "Feature",
  "properties": {
    "iso:country":"ES",
    "sg:address":"Carrer de Nord, 71",
    "sg:city":"Premia Mar",
    "sg:orig_category":"Asociaciones, Organismos Culturales Y Socioeducativos",
    "sg:phone":"+34 937 52 44 78",
    "sg:postcode":"08330",
    "sg:province":"Barcelona",
    "wof:name":"Iniciativas Culturals Del Baix Maresme S.c.p.",
    "wof:placetype":"venue"
},
  "geometry": {"coordinates":[2.3587529659,41.4910125732],"type":"Point"}
}