{
  "type": "Feature",
  "properties": {
    "addr:full":"Calle de Muro, 8 Medina-sidonia C\u00e1diz 11170",
    "addr:housenumber":"8",
    "addr:postcode":"11170",
    "addr:street":"Calle De Muro;Ca\u0301Diz",
    "iso:country":"ES",
    "sg:address":"Calle de Muro, 8",
    "sg:city":"Medina-sidonia",
    "sg:classifiers":[
        {
            "category":"Taxi",
            "type":"Transportation"
        }
    ],
    "sg:phone":"+34 956 41 08 00",
    "sg:postcode":"11170",
    "sg:province":"C\u00e1diz",
    "wof:name":"Estudillo Galindo Francisco",
    "wof:placetype":"venue"
},
  "geometry": {"coordinates":[-5.9275488853,36.4591217041],"type":"Point"}
}