{
  "type": "Feature",
  "properties": {
    "addr:full":"Cmno Vial De Los Cipreses, 3 Alacant Alicante 03006",
    "addr:housenumber":"3",
    "addr:postcode":"03006",
    "addr:street":"Cmno Vial De Los Cipreses",
    "iso:country":"ES",
    "sg:address":"Cmno Vial De Los Cipreses, 3",
    "sg:city":"Alacant",
    "sg:orig_category":"Empresas De Carpinter\u00cda",
    "sg:phone":"+34 965 10 60 05",
    "sg:postcode":"03006",
    "sg:province":"Alicante",
    "wof:name":"Aluminios Guardiola Sl",
    "wof:placetype":"venue"
},
  "geometry": {"coordinates":[-0.5254821777,38.3460235596],"type":"Point"}
}