{
  "type": "Feature",
  "properties": {
    "iso:country":"ES",
    "sg:address":"Calle de De Los Lagares, 13",
    "sg:city":"Benavente",
    "sg:orig_category":"Art\u00cdculos De Regalo (al Por Menor)",
    "sg:phone":"+34 980 63 07 39",
    "sg:postcode":"49600",
    "sg:province":"Zamora",
    "wof:name":"Garcia Losada Luis",
    "wof:placetype":"venue"
},
  "geometry": {"coordinates":[-5.6789383888,42.0043144226],"type":"Point"}
}