{
  "type": "Feature",
  "properties": {
    "iso:country":"ES",
    "sg:address":"Calle de Jimenez Aranda, 19",
    "sg:city":"Sevilla",
    "sg:orig_category":"Agentes Generales De Seguros",
    "sg:phone":"+34 954 53 63 56",
    "sg:postcode":"41018",
    "sg:province":"Sevilla",
    "wof:name":"Anguiano Ales Josefa",
    "wof:placetype":"venue"
},
  "geometry": {"coordinates":[-5.9813766479,37.3856658936],"type":"Point"}
}