{
  "type": "Feature",
  "properties": {
    "addr:full":"Carr Alfons Xiii, 14 Ciutadella Menorca Islas Baleares 07760",
    "addr:housenumber":"14",
    "addr:postcode":"07760",
    "addr:street":"Carr Alfons Xiii",
    "iso:country":"ES",
    "sg:address":"Carr Alfons Xiii, 14",
    "sg:city":"Ciutadella Menorca",
    "sg:orig_category":"Zapater\u00cdas",
    "sg:phone":"+34 971 38 04 82",
    "sg:postcode":"07760",
    "sg:province":"Islas Baleares",
    "wof:name":"Torrent Ciudadela S. L.",
    "wof:placetype":"venue"
},
  "geometry": {"coordinates":[3.8398718834,40.0052108765],"type":"Point"}
}