{
  "type": "Feature",
  "properties": {
    "addr:full":"Carrer de Montsant, 2 Bellmunt Priorat Tarragona 43738",
    "addr:housenumber":"2",
    "addr:postcode":"43738",
    "addr:street":"Carrer De Montsant",
    "iso:country":"ES",
    "sg:address":"Carrer de Montsant, 2",
    "sg:city":"Bellmunt Priorat",
    "sg:orig_category":"Productores Recolectores, Venta Directa De Vinos",
    "sg:phone":"+34 977 83 06 75",
    "sg:postcode":"43738",
    "sg:province":"Tarragona",
    "wof:name":"Cellers Fuentes S.l",
    "wof:placetype":"venue"
},
  "geometry": {"coordinates":[0.7655500174,41.1633491516],"type":"Point"}
}