{
  "type": "Feature",
  "properties": {
    "addr:full":"Av Matadepera, 43 Sabadell Barcelona 08207",
    "addr:housenumber":"43",
    "addr:postcode":"08207",
    "addr:street":"Av Matadepera",
    "iso:country":"ES",
    "sg:address":"Av Matadepera, 43",
    "sg:city":"Sabadell",
    "sg:orig_category":"Ropa Para Ni\u00d1os (al Por Menor)",
    "sg:phone":"+34 937 23 85 36",
    "sg:postcode":"08207",
    "sg:province":"Barcelona",
    "wof:name":"Francisco Salvador Garcia S. L.",
    "wof:placetype":"venue"
},
  "geometry": {"coordinates":[2.0899720192,41.5647926331],"type":"Point"}
}