{
  "type": "Feature",
  "properties": {
    "addr:full":"Calle de Damaso Alonso, 55 Talavera Reina Toledo 45600",
    "addr:housenumber":"55",
    "addr:postcode":"45600",
    "addr:street":"Calle De Damaso Alonso",
    "iso:country":"ES",
    "sg:address":"Calle de Damaso Alonso, 55",
    "sg:city":"Talavera Reina",
    "sg:classifiers":[
        {
            "category":"Casinos & Gambling",
            "type":"Entertainment"
        }
    ],
    "sg:phone":"+34 925 82 58 61",
    "sg:postcode":"45600",
    "sg:province":"Toledo",
    "sg:tags":[
        "locale",
        "de",
        "juego"
    ],
    "wof:name":"Elvira Diaz Maria Del Carmen",
    "wof:placetype":"venue"
},
  "geometry": {"coordinates":[-4.8161568642,39.9609832764],"type":"Point"}
}