{
  "type": "Feature",
  "properties": {
    "addr:full":"Calle de Escancho, 3 Chafiras Santa Cruz De Tenerife 38639",
    "addr:housenumber":"3",
    "addr:postcode":"38639",
    "addr:street":"Calle De Escancho",
    "iso:country":"ES",
    "sg:address":"Calle de Escancho, 3",
    "sg:city":"Chafiras",
    "sg:orig_category":"Limpieza Industrial",
    "sg:phone":"+34 922 73 60 91",
    "sg:postcode":"38639",
    "sg:province":"Santa Cruz De Tenerife",
    "wof:name":"Servis Tabona S.l.",
    "wof:placetype":"venue"
},
  "geometry": {"coordinates":[-16.6115474701,28.0350246429],"type":"Point"}
}