{
  "type": "Feature",
  "properties": {
    "addr:full":"Avda Jose Luis Lasa, 69 Arroyo De La Encomienda Valladolid 47195",
    "addr:housenumber":"69",
    "addr:postcode":"47195",
    "addr:street":"Avda Jose Luis Lasa",
    "iso:country":"ES",
    "sg:address":"Avda Jose Luis Lasa, 69",
    "sg:city":"Arroyo De La Encomienda",
    "sg:orig_category":"Albergues Sociales",
    "sg:phone":"+34 983 40 70 82",
    "sg:postcode":"47195",
    "sg:province":"Valladolid",
    "wof:name":"Proinlasa",
    "wof:placetype":"venue"
},
  "geometry": {"coordinates":[-4.7912130356,41.6108055115],"type":"Point"}
}