{
  "type": "Feature",
  "properties": {
    "addr:full":"Avda Andalucia, 41 Santiago Espada Ja\u00e9n 23290",
    "addr:housenumber":"41",
    "addr:postcode":"23290",
    "addr:street":"Avda Andalucia;Jae\u0301N",
    "iso:country":"ES",
    "sg:address":"Avda Andalucia, 41",
    "sg:city":"Santiago Espada",
    "sg:orig_category":"Hormigonados",
    "sg:phone":"+34 953 43 84 23",
    "sg:postcode":"23290",
    "sg:province":"Ja\u00e9n",
    "wof:name":"Arribas Pardo Pablo",
    "wof:placetype":"venue"
},
  "geometry": {"coordinates":[-2.5542900562,38.1097412109],"type":"Point"}
}