{
  "type": "Feature",
  "properties": {
    "addr:full":"Avda Andalucia, 28 Fuente Piedra M\u00e1laga 29520",
    "addr:housenumber":"28",
    "addr:postcode":"29520",
    "addr:street":"Avda Andalucia;Piedra Ma\u0301Laga",
    "iso:country":"ES",
    "sg:address":"Avda Andalucia, 28",
    "sg:city":"Fuente Piedra",
    "sg:orig_category":"Bares, Piano",
    "sg:phone":"+34 952 73 50 09",
    "sg:postcode":"29520",
    "sg:province":"M\u00e1laga",
    "wof:name":"Distribuiciones Cortes Y Romero Sl",
    "wof:placetype":"venue"
},
  "geometry": {"coordinates":[-4.7309727669,37.1344261169],"type":"Point"}
}