{
  "type": "Feature",
  "properties": {
    "iso:country":"ES",
    "sg:address":"Carrer de Peniscola, 11",
    "sg:city":"Reus",
    "sg:orig_category":"Molduras, Junquillos, Listones Y Molduras Perforadas",
    "sg:phone":"+34 977 75 15 66",
    "sg:postcode":"43205",
    "sg:province":"Tarragona",
    "wof:name":"Martinez Caparros Jose",
    "wof:placetype":"venue"
},
  "geometry": {"coordinates":[1.10709095,41.1458625793],"type":"Point"}
}