{
  "type": "Feature",
  "properties": {
    "iso:country":"ES",
    "sg:address":"La Dama, S/n",
    "sg:city":"La Dama",
    "sg:orig_category":"Producci\u00d3n, Venta De Productos De Agricultura Biol\u00d3gica",
    "sg:phone":"+34 922 80 30 48",
    "sg:postcode":"38869",
    "sg:province":"Santa Cruz De Tenerife",
    "wof:name":"Compa\u00f1ia Agricola La Dama S.a.",
    "wof:placetype":"venue"
},
  "geometry": {"coordinates":[-17.3009357452,28.0543289185],"type":"Point"}
}