{
  "type": "Feature",
  "properties": {
    "addr:full":"Av Can Cabanyes, 2 Rubi Barcelona 08191",
    "addr:housenumber":"2",
    "addr:postcode":"08191",
    "addr:street":"Av;Cabanyes",
    "iso:country":"ES",
    "sg:address":"Av Can Cabanyes, 2",
    "sg:city":"Rubi",
    "sg:orig_category":"Molduras, Junquillos, Listones Y Molduras Perforadas",
    "sg:phone":"+34 935 88 50 18",
    "sg:postcode":"08191",
    "sg:province":"Barcelona",
    "wof:name":"Rodriguez Moreno Juan",
    "wof:placetype":"venue"
},
  "geometry": {"coordinates":[2.0317668915,41.4857559204],"type":"Point"}
}