{
  "type": "Feature",
  "properties": {
    "iso:country":"ES",
    "sg:address":"Calle de Ramon Franco, 8",
    "sg:city":"Calvario",
    "sg:orig_category":"Ense\u00d1anza Variada",
    "sg:phone":"+34 986 62 52 07",
    "sg:postcode":"36770",
    "sg:province":"Pontevedra",
    "wof:name":"Comunidad De Propietarios Ramon Franco",
    "wof:placetype":"venue"
},
  "geometry": {"coordinates":[-8.8362493515,41.9370346069],"type":"Point"}
}