{
  "type": "Feature",
  "properties": {
    "addr:full":"Ctra. Logro\u00f1o, Km. 0009,0 Garrapinillos Zaragoza 50190",
    "addr:postcode":"50190",
    "addr:street":"Ctra. Logron\u0303O Km. 0009,0 Garrapinillos",
    "iso:country":"ES",
    "sg:address":"Ctra. Logro\u00f1o, Km. 0009,0",
    "sg:city":"Garrapinillos",
    "sg:orig_category":"Fabricaci\u00d3n De Enlosados, Soler\u00cdas",
    "sg:phone":"+34 976 77 41 61",
    "sg:postcode":"50190",
    "sg:province":"Zaragoza",
    "sg:website":"www.acysaceramicas.com",
    "wof:name":"Aragonesa De Ceramicas Y Saneamientos S.l.",
    "wof:placetype":"venue"
},
  "geometry": {"coordinates":[-1.0150372982,41.7103691101],"type":"Point"}
}