{
  "type": "Feature",
  "properties": {
    "addr:full":"El Almendro, S/n Benahavis M\u00e1laga 29679",
    "addr:housenumber":"s / n",
    "addr:postcode":"29679",
    "addr:street":"El Almendro;Ma\u0301Laga",
    "iso:country":"ES",
    "sg:address":"El Almendro, S/n",
    "sg:city":"Benahavis",
    "sg:orig_category":"Promotores Constructores",
    "sg:phone":"+34 952 78 88 41",
    "sg:postcode":"29679",
    "sg:province":"M\u00e1laga",
    "wof:name":"Alacruz Base S.l",
    "wof:placetype":"venue"
},
  "geometry": {"coordinates":[-4.9892292023,36.4894714355],"type":"Point"}
}