{
  "type": "Feature",
  "properties": {
    "iso:country":"ES",
    "sg:address":"Calle de Francisco De Jorge Gallardo, 8",
    "sg:city":"Torremolinos",
    "sg:orig_category":"Diplomas Diversos",
    "sg:phone":"+34 952 38 96 55",
    "sg:postcode":"29620",
    "sg:province":"M\u00e1laga",
    "wof:name":"Baixeraf Llano Elena",
    "wof:placetype":"venue"
},
  "geometry": {"coordinates":[-4.5153717995,36.6067810059],"type":"Point"}
}