{
  "type": "Feature",
  "properties": {
    "addr:full":"Calle de Nardos, 2 Zubia Granada 18140",
    "addr:housenumber":"2",
    "addr:postcode":"18140",
    "addr:street":"Calle De Nardos",
    "iso:country":"ES",
    "sg:address":"Calle de Nardos, 2",
    "sg:city":"Zubia",
    "sg:orig_category":"Institutos De Belleza",
    "sg:phone":"+34 958 59 29 05",
    "sg:postcode":"18140",
    "sg:province":"Granada",
    "wof:name":"Mejias Martin Maria Teresa",
    "wof:placetype":"venue"
},
  "geometry": {"coordinates":[-3.59106493,37.1151924133],"type":"Point"}
}