{
  "type": "Feature",
  "properties": {
    "addr:full":"Avda Askatasun Etorbidea, 29 Durango Vizcaya 48200",
    "addr:housenumber":"29",
    "addr:postcode":"48200",
    "addr:street":"Avda Askatasun Etorbidea",
    "iso:country":"ES",
    "sg:address":"Avda Askatasun Etorbidea, 29",
    "sg:city":"Durango",
    "sg:orig_category":"Agencias Y Agentes Comerciales, Representantes",
    "sg:phone":"+34 946 03 35 83",
    "sg:postcode":"48200",
    "sg:province":"Vizcaya",
    "wof:name":"Muley Zaharrena S.l",
    "wof:placetype":"venue"
},
  "geometry": {"coordinates":[-2.6393680573,43.1692199707],"type":"Point"}
}