{
  "type": "Feature",
  "properties": {
    "iso:country":"ES",
    "sg:address":"Rua Rio Sil, 10",
    "sg:city":"Laxe",
    "sg:orig_category":"Inmobiliaria (agencias)",
    "sg:phone":"+34 981 66 17 69",
    "sg:postcode":"15174",
    "sg:province":"La Coru\u00f1a",
    "wof:name":"Inmobiliaria Culleredo S.a.",
    "wof:placetype":"venue"
},
  "geometry": {"coordinates":[-8.3826389313,43.3110656738],"type":"Point"}
}