{
  "type": "Feature",
  "properties": {
    "addr:full":"Calle de Ruiz De Padron, 7 S. Sebastian Gomera Santa Cruz De Tenerife 38800",
    "addr:housenumber":"7",
    "addr:postcode":"38800",
    "addr:street":"Calle De Ruiz De Padron",
    "iso:country":"ES",
    "sg:address":"Calle de Ruiz De Padron, 7",
    "sg:city":"S. Sebastian Gomera",
    "sg:orig_category":"Bisuter\u00cda, Joyer\u00cda, Relojer\u00cda (al Por Menor)",
    "sg:phone":"+34 922 14 10 29",
    "sg:postcode":"38800",
    "sg:province":"Santa Cruz De Tenerife",
    "wof:name":"Zerpa Gonzalez S.l.",
    "wof:placetype":"venue"
},
  "geometry": {"coordinates":[-17.1107196808,28.0906944275],"type":"Point"}
}