{
  "type": "Feature",
  "properties": {
    "addr:full":"Maritorrija, 13 Ecija Sevilla 41400",
    "addr:housenumber":"13",
    "addr:postcode":"41400",
    "addr:street":"Maritorrija",
    "iso:country":"ES",
    "sg:address":"Maritorrija, 13",
    "sg:city":"Ecija",
    "sg:orig_category":"Asociaciones Humanitarias, De Cooperaci\u00d3n, De Acci\u00d3n Social",
    "sg:phone":"+34 955 90 41 89",
    "sg:postcode":"41400",
    "sg:province":"Sevilla",
    "wof:name":"Asociacion Comarcal Familiares De Alzehimer Valle Del Genil",
    "wof:placetype":"venue"
},
  "geometry": {"coordinates":[-5.0769138336,37.5382041931],"type":"Point"}
}