{
  "type": "Feature",
  "properties": {
    "iso:country":"ES",
    "sg:address":"Calle de Puerto, 4",
    "sg:city":"Huelva",
    "sg:orig_category":"Abogados",
    "sg:phone":"+34 959 24 43 46",
    "sg:postcode":"21001",
    "sg:province":"Huelva",
    "wof:name":"Vizcaino Romero S.c.",
    "wof:placetype":"venue"
},
  "geometry": {"coordinates":[-6.9512491226,37.258392334],"type":"Point"}
}