{
  "type": "Feature",
  "properties": {
    "addr:full":"Calle de Ercilla, 34 Bilbao Vizcaya 48011",
    "addr:housenumber":"34",
    "addr:postcode":"48011",
    "addr:street":"Calle De Ercilla",
    "iso:country":"ES",
    "sg:address":"Calle de Ercilla, 34",
    "sg:city":"Bilbao",
    "sg:orig_category":"Ingenier\u00cda, Centros De Estudios (diversos)",
    "sg:phone":"+34 944 10 46 01",
    "sg:postcode":"48011",
    "sg:province":"Vizcaya",
    "wof:name":"Astigarraga Urquiza Julio",
    "wof:placetype":"venue"
},
  "geometry": {"coordinates":[-2.938201189,43.2615127563],"type":"Point"}
}