{
  "type": "Feature",
  "properties": {
    "iso:country":"ES",
    "sg:address":"Calle de Menorca, 40",
    "sg:city":"Madrid",
    "sg:orig_category":"Abogados",
    "sg:phone":"+34 915 04 49 27",
    "sg:postcode":"28009",
    "sg:province":"Madrid",
    "wof:name":"Sanguino Gomez Luis Miguel",
    "wof:placetype":"venue"
},
  "geometry": {"coordinates":[-3.6737999916,40.4191818237],"type":"Point"}
}