{
  "type": "Feature",
  "properties": {
    "addr:full":"Ctra Madrid, Km. 0066,2 Toledo Toledo 45003",
    "addr:postcode":"45003",
    "addr:street":"Ctra Madrid Km. 0066,2",
    "iso:country":"ES",
    "sg:address":"Ctra Madrid, Km. 0066,2",
    "sg:city":"Toledo",
    "sg:orig_category":"Comercio De Hierro",
    "sg:phone":"+34 925 22 89 82",
    "sg:postcode":"45003",
    "sg:province":"Toledo",
    "wof:name":"Hierros Abel S.l.",
    "wof:placetype":"venue"
},
  "geometry": {"coordinates":[-4.025138855,39.8618774414],"type":"Point"}
}