{
  "type": "Feature",
  "properties": {
    "addr:full":"Mercat Torrent Gornal, 100 Hospitalet Llobregat Barcelona 08904",
    "addr:housenumber":"100",
    "addr:postcode":"08904",
    "addr:street":"Gornal",
    "iso:country":"ES",
    "sg:address":"Mercat Torrent Gornal, 100",
    "sg:city":"Hospitalet Llobregat",
    "sg:orig_category":"Lencer\u00cda Femenina, Corseter\u00cda, Trajes De Ba\u00d1o (al Por Menor)",
    "sg:phone":"+34 933 33 05 79",
    "sg:postcode":"08904",
    "sg:province":"Barcelona",
    "wof:name":"Perez Saavedra Maria Jesus",
    "wof:placetype":"venue"
},
  "geometry": {"coordinates":[2.1127030849,41.3732337952],"type":"Point"}
}