{
  "type": "Feature",
  "properties": {
    "iso:country":"ES",
    "sg:address":"Rua Manuel Lemos, 22",
    "sg:city":"Ramallosa",
    "sg:orig_category":"Cl\u00cdnicas M\u00c9dicas",
    "sg:phone":"+34 986 35 30 41",
    "sg:postcode":"36379",
    "sg:province":"Pontevedra",
    "wof:name":"Garin Arevalo Sara",
    "wof:placetype":"venue"
},
  "geometry": {"coordinates":[-8.8128118515,42.1174888611],"type":"Point"}
}