{
  "type": "Feature",
  "properties": {
    "addr:full":"Ctra. Montefrio-alcala La Real, S/n Montefrio Granada 18270",
    "addr:housenumber":"s / n",
    "addr:postcode":"18270",
    "addr:street":"Ctra. Montefrio-Alcala",
    "iso:country":"ES",
    "sg:address":"Ctra. Montefrio-alcala La Real, S/n",
    "sg:city":"Montefrio",
    "sg:orig_category":"Mec\u00c1nico Del Autom\u00d3vil",
    "sg:phone":"+34 958 33 61 00",
    "sg:postcode":"18270",
    "sg:province":"Granada",
    "wof:name":"Tirado Toro Manuel",
    "wof:placetype":"venue"
},
  "geometry": {"coordinates":[-4.0050649643,37.3236503601],"type":"Point"}
}