{
  "type": "Feature",
  "properties": {
    "addr:full":"Calle de Sierra Dorada, 10 Benidorm Alicante 03500",
    "addr:housenumber":"10",
    "addr:postcode":"03500",
    "addr:street":"Calle De Sierra Dorada",
    "iso:country":"ES",
    "sg:address":"Calle de Sierra Dorada, 10",
    "sg:city":"Benidorm",
    "sg:orig_category":"Traductores",
    "sg:phone":"+34 966 81 10 24",
    "sg:postcode":"03500",
    "sg:province":"Alicante",
    "wof:name":"Brooke  Gerald",
    "wof:placetype":"venue"
},
  "geometry": {"coordinates":[-0.1047699973,38.5320510864],"type":"Point"}
}