{
  "type": "Feature",
  "properties": {
    "addr:full":"Avda Levante, 1 Molina Segura Murcia 30500",
    "addr:housenumber":"1",
    "addr:postcode":"30500",
    "addr:street":"Avda Levante",
    "iso:country":"ES",
    "sg:address":"Avda Levante, 1",
    "sg:city":"Molina Segura",
    "sg:orig_category":"Electricidad, Electr\u00d3nica: Suministros (al Por Menor)",
    "sg:phone":"+34 968 64 27 46",
    "sg:postcode":"30500",
    "sg:province":"Murcia",
    "wof:name":"Sonido Levante S.l.",
    "wof:placetype":"venue"
},
  "geometry": {"coordinates":[-1.2111239433,38.0598678589],"type":"Point"}
}