{
  "type": "Feature",
  "properties": {
    "addr:full":"Calle de Principe Asturias, 53 Salinas Asturias 33405",
    "addr:housenumber":"53",
    "addr:postcode":"33405",
    "addr:street":"Calle De Principe Asturias",
    "iso:country":"ES",
    "sg:address":"Calle de Principe Asturias, 53",
    "sg:city":"Salinas",
    "sg:orig_category":"Restaurantes",
    "sg:phone":"+34 985 50 00 05",
    "sg:postcode":"33405",
    "sg:province":"Asturias",
    "wof:name":"Perez Mu\u00f1iz Javier",
    "wof:placetype":"venue"
},
  "geometry": {"coordinates":[-5.9631228447,43.5749855042],"type":"Point"}
}