{
  "type": "Feature",
  "properties": {
    "addr:full":"Carrer de Radas, 38 Barcelona Barcelona 08004",
    "addr:housenumber":"38",
    "addr:postcode":"08004",
    "addr:street":"Carrer De Radas",
    "iso:country":"ES",
    "sg:address":"Carrer de Radas, 38",
    "sg:city":"Barcelona",
    "sg:orig_category":"Molduras, Junquillos, Listones Y Molduras Perforadas",
    "sg:phone":"+34 933 24 80 61",
    "sg:postcode":"08004",
    "sg:province":"Barcelona",
    "wof:name":"Iglesia Gonzalez Miguel",
    "wof:placetype":"venue"
},
  "geometry": {"coordinates":[2.1602730751,41.3723449707],"type":"Point"}
}