{
  "type": "Feature",
  "properties": {
    "iso:country":"ES",
    "sg:address":"Calle de San Mateo, 13",
    "sg:city":"Madrid",
    "sg:orig_category":"Museos",
    "sg:phone":"+34 914 48 10 45",
    "sg:postcode":"28004",
    "sg:province":"Madrid",
    "wof:name":"Ministerio De Educacion Cultura Y Deporte",
    "wof:placetype":"venue"
},
  "geometry": {"coordinates":[-3.6988136768,40.4257965088],"type":"Point"}
}