{
  "type": "Feature",
  "properties": {
    "iso:country":"ES",
    "sg:address":"Plaz Pontevedra, 10",
    "sg:city":"Coru\u00d1a",
    "sg:orig_category":"M\u00c9dicos: Dermatolog\u00cda Y Venereolog\u00cda",
    "sg:phone":"+34 981 20 11 81",
    "sg:postcode":"15003",
    "sg:province":"A Coru\u00f1a",
    "wof:name":"Verea Hernando Maria Magdalena",
    "wof:placetype":"venue"
},
  "geometry": {"coordinates":[-8.4063863754,43.3679389954],"type":"Point"}
}