{
  "type": "Feature",
  "properties": {
    "iso:country":"ES",
    "sg:address":"Carr Magdalena, 4",
    "sg:city":"Lleida",
    "sg:orig_category":"Ropa Para Ni\u00d1os (al Por Menor)",
    "sg:phone":"+34 973 22 23 62",
    "sg:postcode":"25007",
    "sg:province":"Lleida",
    "wof:name":"Mele Gamon Cristina",
    "wof:placetype":"venue"
},
  "geometry": {"coordinates":[0.6294370294,41.6181259155],"type":"Point"}
}