{
  "type": "Feature",
  "properties": {
    "iso:country":"ES",
    "sg:address":"Calle de Emilio Gastesi Fernandez, 7",
    "sg:city":"Madrid",
    "sg:orig_category":"Peluquer\u00cdas, Peluquer\u00cda Mixta",
    "sg:phone":"+34 914 08 72 12",
    "sg:postcode":"28027",
    "sg:province":"Madrid",
    "wof:name":"Tal Cual C.b.",
    "wof:placetype":"venue"
},
  "geometry": {"coordinates":[-3.6474890709,40.4358596802],"type":"Point"}
}