{
  "type": "Feature",
  "properties": {
    "addr:full":"Calle de Juan Xxiii, 16 Santurtzi Vizcaya 48980",
    "addr:housenumber":"16",
    "addr:postcode":"48980",
    "addr:street":"Calle De Juan Xxiii",
    "iso:country":"ES",
    "sg:address":"Calle de Juan Xxiii, 16",
    "sg:city":"Santurtzi",
    "sg:orig_category":"Inmobiliaria (agencias)",
    "sg:phone":"+34 944 62 46 10",
    "sg:postcode":"48980",
    "sg:province":"Vizcaya",
    "wof:name":"Elices Aguado Jose Carlos",
    "wof:placetype":"venue"
},
  "geometry": {"coordinates":[-3.0340619087,43.3309059143],"type":"Point"}
}