{
  "type": "Feature",
  "properties": {
    "addr:full":"Avda Perez Colino, 12 Ponferrada Le\u00f3n 24400",
    "addr:housenumber":"12",
    "addr:postcode":"24400",
    "addr:street":"Avda Perez Colino",
    "iso:country":"ES",
    "sg:address":"Avda Perez Colino, 12",
    "sg:city":"Ponferrada",
    "sg:orig_category":"Zapatos (al Por Menor)",
    "sg:phone":"+34 987 42 49 94",
    "sg:postcode":"24400",
    "sg:province":"Le\u00f3n",
    "wof:name":"Franbeda S.l",
    "wof:placetype":"venue"
},
  "geometry": {"coordinates":[-6.5972762108,42.5463600159],"type":"Point"}
}