{
  "type": "Feature",
  "properties": {
    "iso:country":"ES",
    "sg:address":"Culleredo, 74",
    "sg:city":"Culleredo",
    "sg:orig_category":"Mercer\u00cda, Lencer\u00cda (al Por Menor)",
    "sg:phone":"+34 981 67 70 06",
    "sg:postcode":"15189",
    "sg:province":"La Coru\u00f1a",
    "wof:name":"Pallares Parada Juan",
    "wof:placetype":"venue"
},
  "geometry": {"coordinates":[-8.3897981644,43.2883262634],"type":"Point"}
}