{
  "type": "Feature",
  "properties": {
    "addr:full":"Carrer de Batlle Joan Deu, 6 Sentmenat Barcelona 08181",
    "addr:housenumber":"6",
    "addr:postcode":"08181",
    "addr:street":"Carrer De Batlle Joan Deu",
    "iso:country":"ES",
    "sg:address":"Carrer de Batlle Joan Deu, 6",
    "sg:city":"Sentmenat",
    "sg:orig_category":"Frutas, Legumbres Frescas Y Tempranas (al Por Menor)",
    "sg:phone":"+34 937 15 24 44",
    "sg:postcode":"08181",
    "sg:province":"Barcelona",
    "wof:name":"Bordas Cruells Dolores",
    "wof:placetype":"venue"
},
  "geometry": {"coordinates":[2.1362159252,41.6087837219],"type":"Point"}
}