{
  "type": "Feature",
  "properties": {
    "iso:country":"ES",
    "sg:address":"Calle de Santa Apolonia, 67",
    "sg:city":"Aviles",
    "sg:orig_category":"Peluqueros: De Se\u00d1oras",
    "sg:phone":"+34 985 57 20 50",
    "sg:postcode":"33403",
    "sg:province":"Asturias",
    "wof:name":"Perez Diaz Maria Luz",
    "wof:placetype":"venue"
},
  "geometry": {"coordinates":[-5.9029040337,43.5445518494],"type":"Point"}
}