{
  "type": "Feature",
  "properties": {
    "iso:country":"ES",
    "sg:address":"Calle de Alcaiceria De La Loza, 24",
    "sg:city":"Sevilla",
    "sg:orig_category":"Loter\u00cda Y T\u00d3mbola",
    "sg:phone":"+34 954 22 61 84",
    "sg:postcode":"41004",
    "sg:province":"Sevilla",
    "wof:name":"Ramirez Rivero Luis",
    "wof:placetype":"venue"
},
  "geometry": {"coordinates":[-5.9912729263,37.3903961182],"type":"Point"}
}