{
  "type": "Feature",
  "properties": {
    "iso:country":"ES",
    "sg:address":"Calle de Santa Eugenia, 23",
    "sg:city":"Getxo",
    "sg:orig_category":"Carnicer\u00cdas, Carnicer\u00cdas",
    "sg:phone":"+34 944 80 14 48",
    "sg:postcode":"48930",
    "sg:province":"Vizcaya",
    "wof:name":"Sebastian Serrano Moral",
    "wof:placetype":"venue"
},
  "geometry": {"coordinates":[-3.0079638958,43.3258171082],"type":"Point"}
}