{
  "type": "Feature",
  "properties": {
    "iso:country":"ES",
    "sg:address":"C/ Canal, 27",
    "sg:city":"Banyoles",
    "sg:orig_category":"Servicios Gsm",
    "sg:phone":"+34 972 58 04 80",
    "sg:postcode":"17820",
    "sg:province":"Girona",
    "wof:name":"Professional Comunications S.l.",
    "wof:placetype":"venue"
},
  "geometry": {"coordinates":[2.7647089958,42.1188812256],"type":"Point"}
}