{
  "type": "Feature",
  "properties": {
    "addr:full":"Calle de Planillo, S/n Logro\u00f1o La Rioja 26006",
    "addr:housenumber":"s / n",
    "addr:postcode":"26006",
    "addr:street":"Calle De Planillo;Rioja",
    "iso:country":"ES",
    "sg:address":"Calle de Planillo, S/n",
    "sg:city":"Logro\u00f1o",
    "sg:orig_category":"Zapatos: Material, Suministros, Accesorios (fabricaci\u00d3n, Al Por Mayor)",
    "sg:phone":"+34 941 24 39 71",
    "sg:postcode":"26006",
    "sg:province":"La Rioja",
    "wof:name":"Troquelados Y Aparados Coimsa Sal",
    "wof:placetype":"venue"
},
  "geometry": {"coordinates":[-2.4093360901,42.4527206421],"type":"Point"}
}