{
  "type": "Feature",
  "properties": {
    "iso:country":"ES",
    "sg:address":"Calle de San Antonio, 25",
    "sg:city":"Totana",
    "sg:orig_category":"Muebles, Minoristas",
    "sg:phone":"+34 968 42 41 00",
    "sg:postcode":"30850",
    "sg:province":"Murcia",
    "wof:name":"Hermesa 85 S.l.",
    "wof:placetype":"venue"
},
  "geometry": {"coordinates":[-1.5046620369,37.7690467834],"type":"Point"}
}