{
  "type": "Feature",
  "properties": {
    "addr:full":"Calle de Bernardo Castet, 2 Portugalete Vizcaya 48920",
    "addr:housenumber":"2",
    "addr:postcode":"48920",
    "addr:street":"Calle De Bernardo Castet",
    "iso:country":"ES",
    "sg:address":"Calle de Bernardo Castet, 2",
    "sg:city":"Portugalete",
    "sg:orig_category":"Reposter\u00cdas",
    "sg:phone":"+34 944 83 15 66",
    "sg:postcode":"48920",
    "sg:province":"Vizcaya",
    "wof:name":"Tecnicos Panaderos S.a.",
    "wof:placetype":"venue"
},
  "geometry": {"coordinates":[-3.0213489532,43.3196029663],"type":"Point"}
}