{
  "type": "Feature",
  "properties": {
    "addr:full":"Avda Portugal, 13 Zamora Zamora 49016",
    "addr:housenumber":"13",
    "addr:postcode":"49016",
    "addr:street":"Avda Portugal",
    "iso:country":"ES",
    "sg:address":"Avda Portugal, 13",
    "sg:city":"Zamora",
    "sg:orig_category":"Muebles, Minoristas",
    "sg:phone":"+34 980 67 22 67",
    "sg:postcode":"49016",
    "sg:province":"Zamora",
    "sg:website":"www.kubosmuebles.com",
    "wof:name":"Kubos La Geometria Del Mueble S.l.",
    "wof:placetype":"venue"
},
  "geometry": {"coordinates":[-5.7396430969,41.5040512085],"type":"Point"}
}