{
  "type": "Feature",
  "properties": {
    "iso:country":"ES",
    "sg:address":"Calle de Fuensanta, 49",
    "sg:city":"Torrevieja",
    "sg:orig_category":"Mec\u00c1nico Del Autom\u00d3vil",
    "sg:phone":"+34 965 70 59 44",
    "sg:postcode":"03180",
    "sg:province":"Alicante",
    "wof:name":"Sobejano Servicios S.l.",
    "wof:placetype":"venue"
},
  "geometry": {"coordinates":[-0.6730819941,37.9798126221],"type":"Point"}
}