{
  "type": "Feature",
  "properties": {
    "iso:country":"ES",
    "sg:address":"Calle de Juan De La Cierva, 7",
    "sg:city":"Salamanca",
    "sg:orig_category":"Laboratorios Y Trabajos De Fotograf\u00cda, V\u00cddeo Y Cine",
    "sg:phone":"+34 923 25 24 09",
    "sg:postcode":"37004",
    "sg:province":"Salamanca",
    "wof:name":"Oterino Madruga Ignacio",
    "wof:placetype":"venue"
},
  "geometry": {"coordinates":[-5.6544070244,40.9754333496],"type":"Point"}
}