{
  "type": "Feature",
  "properties": {
    "iso:country":"ES",
    "sg:address":"Calle de Hornos (los), 12",
    "sg:city":"Ponferrada",
    "sg:orig_category":"Telas Y Sedas (al Por Menor)",
    "sg:phone":"+34 987 41 14 20",
    "sg:postcode":"24400",
    "sg:province":"Le\u00f3n",
    "wof:name":"Ruiperez S. L.",
    "wof:placetype":"venue"
},
  "geometry": {"coordinates":[-6.5960798264,42.546333313],"type":"Point"}
}