{
  "type": "Feature",
  "properties": {
    "addr:full":"Calle de Raimundo Fernandez Villaverde, 52 Madrid Madrid 28003",
    "addr:housenumber":"52",
    "addr:postcode":"madrid;28003",
    "addr:street":"Calle De Raimundo Fernandez Villaverde",
    "iso:country":"ES",
    "sg:address":"Calle de Raimundo Fernandez Villaverde, 52",
    "sg:city":"Madrid",
    "sg:orig_category":"Caf\u00c9s, Bares, Cervecer\u00cdas",
    "sg:phone":"+34 915 35 15 21",
    "sg:postcode":"28003",
    "sg:province":"Madrid",
    "wof:name":"Hernandez Sanchez Pedro",
    "wof:placetype":"venue"
},
  "geometry": {"coordinates":[-3.6960721016,40.4465904236],"type":"Point"}
}