{
  "type": "Feature",
  "properties": {
    "iso:country":"ES",
    "sg:address":"Calle de Sobrarbe, 33",
    "sg:city":"Zaragoza",
    "sg:orig_category":"Laboratorios Y Trabajos De Fotograf\u00cda, V\u00cddeo Y Cine",
    "sg:phone":"+34 976 52 53 35",
    "sg:postcode":"50015",
    "sg:province":"Zaragoza",
    "wof:name":"Arag\u00dces Laporta Antonio Fernando",
    "wof:placetype":"venue"
},
  "geometry": {"coordinates":[-0.8740708232,41.6595230103],"type":"Point"}
}