{
  "type": "Feature",
  "properties": {
    "iso:country":"ES",
    "sg:address":"Calle de Decano Sancho De Olivera, 1",
    "sg:city":"Torremolinos",
    "sg:orig_category":"Agencias De Viajes",
    "sg:phone":"+34 952 38 23 53",
    "sg:postcode":"29620",
    "sg:province":"M\u00e1laga",
    "wof:name":"Diaz Cordero Antonio Francisco",
    "wof:placetype":"venue"
},
  "geometry": {"coordinates":[-4.5104980469,36.6134796143],"type":"Point"}
}