{
  "type": "Feature",
  "properties": {
    "addr:full":"Calle de Mendez Alvaro, 57 Madrid Madrid 28045",
    "addr:housenumber":"57",
    "addr:postcode":"madrid;28045",
    "addr:street":"Calle De Mendez Alvaro",
    "iso:country":"ES",
    "sg:address":"Calle de Mendez Alvaro, 57",
    "sg:city":"Madrid",
    "sg:orig_category":"Administradores De Bienes Y Delegados De Comunidades De Propietarios",
    "sg:phone":"+34 914 67 67 97",
    "sg:postcode":"28045",
    "sg:province":"Madrid",
    "wof:name":"Pe\u00f1alvento S.l.",
    "wof:placetype":"venue"
},
  "geometry": {"coordinates":[-3.6824519634,40.3972625732],"type":"Point"}
}