{
  "type": "Feature",
  "properties": {
    "iso:country":"ES",
    "sg:address":"Carrer de Major, 15",
    "sg:city":"Vilalba Dels Arcs",
    "sg:orig_category":"Producci\u00d3n, Venta De Productos De Agricultura Biol\u00d3gica",
    "sg:phone":"+34 977 43 80 01",
    "sg:postcode":"43782",
    "sg:province":"Tarragona",
    "wof:name":"Domenech Guiu Francesc",
    "wof:placetype":"venue"
},
  "geometry": {"coordinates":[0.4092929959,41.1206893921],"type":"Point"}
}