{
  "type": "Feature",
  "properties": {
    "iso:country":"ES",
    "sg:address":"Calle de Molino Viento, S/n",
    "sg:city":"Fuengirola",
    "sg:orig_category":"Art\u00cdculos De Regalo (al Por Menor)",
    "sg:phone":"+34 952 47 63 90",
    "sg:postcode":"29640",
    "sg:province":"M\u00e1laga",
    "wof:name":"Ladron De Guevara Martinez Maria Del Carmen",
    "wof:placetype":"venue"
},
  "geometry": {"coordinates":[-4.6286940575,36.5360488892],"type":"Point"}
}