{
  "type": "Feature",
  "properties": {
    "addr:full":"Avda Hytasa, S/n Sevilla Sevilla 41006",
    "addr:housenumber":"s / n",
    "addr:postcode":"41006",
    "addr:street":"Avda Hytasa",
    "iso:country":"ES",
    "sg:address":"Avda Hytasa, S/n",
    "sg:city":"Sevilla",
    "sg:orig_category":"Abogados",
    "sg:phone":"+34 954 64 75 21",
    "sg:postcode":"41006",
    "sg:province":"Sevilla",
    "wof:name":"Rivas Martin Jose Antonio",
    "wof:placetype":"venue"
},
  "geometry": {"coordinates":[-5.9637942314,37.3729705811],"type":"Point"}
}