{
  "type": "Feature",
  "properties": {
    "iso:country":"ES",
    "sg:address":"Rond Alfons X El Savi (d'), 84",
    "sg:city":"Mataro",
    "sg:orig_category":"Abogados",
    "sg:phone":"+34 937 90 55 55",
    "sg:postcode":"08301",
    "sg:province":"Barcelona",
    "wof:name":"Acosta Oliveras Antonio",
    "wof:placetype":"venue"
},
  "geometry": {"coordinates":[2.4628870487,41.5474433899],"type":"Point"}
}