{
  "type": "Feature",
  "properties": {
    "addr:full":"Carrer de Major, 21 Montornes Centre Barcelona 08170",
    "addr:housenumber":"21",
    "addr:postcode":"08170",
    "addr:street":"Carrer De Major;Centre Barcelona",
    "iso:country":"ES",
    "sg:address":"Carrer de Major, 21",
    "sg:city":"Montornes Centre",
    "sg:orig_category":"Reposter\u00cdas",
    "sg:phone":"+34 935 68 46 62",
    "sg:postcode":"08170",
    "sg:province":"Barcelona",
    "wof:name":"Eurofleca 2000 S.l.",
    "wof:placetype":"venue"
},
  "geometry": {"coordinates":[2.2656269073,41.5424308777],"type":"Point"}
}