{
  "type": "Feature",
  "properties": {
    "iso:country":"ES",
    "sg:address":"Avda Marques De Los Velez, 13",
    "sg:city":"Vista Alegre",
    "sg:orig_category":"Inmobiliaria (agencias)",
    "sg:phone":"+34 968 27 17 56",
    "sg:postcode":"30008",
    "sg:province":"Murcia",
    "wof:name":"Lorente Mero\u00f1o Carlos",
    "wof:placetype":"venue"
},
  "geometry": {"coordinates":[-1.1299079657,37.993927002],"type":"Point"}
}