{
  "type": "Feature",
  "properties": {
    "iso:country":"ES",
    "sg:address":"Carrer de Jacint Verdaguer, 8",
    "sg:city":"Vic",
    "sg:orig_category":"Sociedades, Compa\u00d1\u00cdas Aseguradoras",
    "sg:phone":"+34 938 85 21 51",
    "sg:postcode":"08500",
    "sg:province":"Barcelona",
    "wof:name":"M. Y J. Vila Corredoria D'assegurances S. L.",
    "wof:placetype":"venue"
},
  "geometry": {"coordinates":[2.2525279522,41.9306411743],"type":"Point"}
}