{
  "type": "Feature",
  "properties": {
    "addr:full":"Avda Benigno Rivera, 9 Lugo Lugo 27003",
    "addr:housenumber":"9",
    "addr:postcode":"27003",
    "addr:street":"Avda Benigno Rivera",
    "iso:country":"ES",
    "sg:address":"Avda Benigno Rivera, 9",
    "sg:city":"Lugo",
    "sg:orig_category":"Comercio De Piezas De Recambio Y De Accesorios De Veh\u00cdculos, Veh\u00cdculos Industriales",
    "sg:phone":"+34 982 20 98 41",
    "sg:postcode":"27003",
    "sg:province":"Lugo",
    "wof:name":"Villasante Pereiro Santiago",
    "wof:placetype":"venue"
},
  "geometry": {"coordinates":[-7.5739607811,43.0371246338],"type":"Point"}
}