{
  "type": "Feature",
  "properties": {
    "iso:country":"ES",
    "sg:address":"Carrer de L'alzina, 48",
    "sg:city":"Barcelona",
    "sg:orig_category":"Librer\u00cdas",
    "sg:phone":"+34 932 13 10 54",
    "sg:postcode":"08024",
    "sg:province":"Barcelona",
    "sg:website":"www.paginasamarillas.es",
    "wof:name":"Instibeste S.l.",
    "wof:placetype":"venue"
},
  "geometry": {"coordinates":[2.1556088924,41.4073257446],"type":"Point"}
}