{
  "type": "Feature",
  "properties": {
    "iso:country":"ES",
    "sg:address":"Calle de Arcediano Gomez Gonzalez, S/n",
    "sg:city":"Cuellar",
    "sg:orig_category":"Promotores Constructores",
    "sg:phone":"+34 921 14 30 35",
    "sg:postcode":"40200",
    "sg:province":"Segovia",
    "wof:name":"Olmos Arribas Julian",
    "wof:placetype":"venue"
},
  "geometry": {"coordinates":[-4.3088960648,41.3952064514],"type":"Point"}
}