{
  "type": "Feature",
  "properties": {
    "iso:country":"ES",
    "sg:address":"Eusko Gudarien Kalea, 9",
    "sg:city":"Orio",
    "sg:orig_category":"Bancos",
    "sg:phone":"+34 943 83 07 95",
    "sg:postcode":"20810",
    "sg:province":"Guip\u00f9zcoa",
    "sg:website":"www.santandercentralhispano.es",
    "wof:name":"Bt Espa\u00d1a Compa\u00d1ia De Servicios Globales De Telecomunicaciones S.a.u.",
    "wof:placetype":"venue"
},
  "geometry": {"coordinates":[-2.1279170513,43.2765083313],"type":"Point"}
}