{
  "type": "Feature",
  "properties": {
    "iso:country":"ES",
    "sg:address":"Calle de Padre Fernando Casanova Benlloch, S.j., 8",
    "sg:city":"Valencia",
    "sg:orig_category":"Promotores Constructores",
    "sg:phone":"+34 963 45 94 74",
    "sg:postcode":"46015",
    "sg:province":"Valencia",
    "wof:name":"Construcciones Picea S.l.",
    "wof:placetype":"venue"
},
  "geometry": {"coordinates":[-0.3959150016,39.4876098633],"type":"Point"}
}