{
  "type": "Feature",
  "properties": {
    "addr:full":"Avda Osa Mayor, 120 Madrid Madrid 28023",
    "addr:housenumber":"120",
    "addr:postcode":"28023",
    "addr:street":"Avda Osa Mayor",
    "iso:country":"ES",
    "sg:address":"Avda Osa Mayor, 120",
    "sg:city":"Madrid",
    "sg:orig_category":"Importaci\u00d3n",
    "sg:phone":"+34 917 40 20 92",
    "sg:postcode":"28023",
    "sg:province":"Madrid",
    "wof:name":"Alliance Albors Y Prado S.l.",
    "wof:placetype":"venue"
},
  "geometry": {"coordinates":[-3.7895576954,40.4580383301],"type":"Point"}
}