{
  "type": "Feature",
  "properties": {
    "iso:country":"ES",
    "sg:address":"Calle de Calderon De La Barca, 5",
    "sg:city":"San Lorenzo De El Escorial",
    "sg:orig_category":"Abogados",
    "sg:phone":"+34 918 90 01 45",
    "sg:postcode":"28200",
    "sg:province":"Madrid",
    "wof:name":"Aguilera Siller Carlos",
    "wof:placetype":"venue"
},
  "geometry": {"coordinates":[-4.1506290436,40.592414856],"type":"Point"}
}