{
  "type": "Feature",
  "properties": {
    "addr:full":"Calle de Santa Cristina, 2 Ejido Almer\u00eda 04700",
    "addr:housenumber":"2",
    "addr:postcode":"04700",
    "addr:street":"Calle De Santa Cristina;Almeri\u0301A",
    "iso:country":"ES",
    "sg:address":"Calle de Santa Cristina, 2",
    "sg:city":"Ejido",
    "sg:orig_category":"Ingeniero",
    "sg:phone":"+34 950 48 15 62",
    "sg:postcode":"04700",
    "sg:province":"Almer\u00eda",
    "wof:name":"Santaella Rodriguez Agustin",
    "wof:placetype":"venue"
},
  "geometry": {"coordinates":[-2.8093490601,36.7760047913],"type":"Point"}
}