{
  "type": "Feature",
  "properties": {
    "addr:full":"Calle de Marques De Canillejas, 1 Llanes Asturias 33500",
    "addr:housenumber":"1",
    "addr:postcode":"33500",
    "addr:street":"Calle De Marques De Canillejas",
    "iso:country":"ES",
    "sg:address":"Calle de Marques De Canillejas, 1",
    "sg:city":"Llanes",
    "sg:orig_category":"Arquitectos",
    "sg:phone":"+34 985 40 28 38",
    "sg:postcode":"33500",
    "sg:province":"Asturias",
    "wof:name":"Estudio Jose Luis Batalla S.l.",
    "wof:placetype":"venue"
},
  "geometry": {"coordinates":[-4.7549939156,43.4207191467],"type":"Point"}
}