{
  "type": "Feature",
  "properties": {
    "iso:country":"ES",
    "sg:address":"Calle de Constitucion (de La), 75",
    "sg:city":"Fuenlabrada",
    "sg:orig_category":"Agentes, Concesionarios Y Sucursales De Veh\u00cdculos",
    "sg:phone":"+34 916 06 13 21",
    "sg:postcode":"28946",
    "sg:province":"Madrid",
    "sg:website":"www.hyundai.es",
    "wof:name":"Yuncar Motor S.l.",
    "wof:placetype":"venue"
},
  "geometry": {"coordinates":[-3.7821195126,40.280166626],"type":"Point"}
}