{
  "type": "Feature",
  "properties": {
    "addr:full":"Cmno Abades (madrona), 15 Madrona Segovia 40154",
    "addr:housenumber":"15",
    "addr:postcode":"40154",
    "addr:street":"Cmno Abades Madrona",
    "iso:country":"ES",
    "sg:address":"Cmno Abades (madrona), 15",
    "sg:city":"Madrona",
    "sg:orig_category":"Promotores Constructores",
    "sg:phone":"+34 921 48 51 66",
    "sg:postcode":"40154",
    "sg:province":"Segovia",
    "wof:name":"Gordo Mu\u00f1oz S.l.u.",
    "wof:placetype":"venue"
},
  "geometry": {"coordinates":[-4.1778311729,40.8970680237],"type":"Point"}
}