{
  "type": "Feature",
  "properties": {
    "addr:full":"Txiriboga Auzoa, 1 Zestoa Guip\u00f9zcoa 20740",
    "addr:housenumber":"1",
    "addr:postcode":"20740",
    "addr:street":"Txiriboga Auzoa;Guipu\u0300Zcoa",
    "iso:country":"ES",
    "sg:address":"Txiriboga Auzoa, 1",
    "sg:city":"Zestoa",
    "sg:orig_category":"Forjas Y Altos Hornos",
    "sg:phone":"+34 943 14 76 45",
    "sg:postcode":"20740",
    "sg:province":"Guip\u00f9zcoa",
    "wof:name":"Forjas De Iraeta S.a.",
    "wof:placetype":"venue"
},
  "geometry": {"coordinates":[-2.2547819614,43.2549362183],"type":"Point"}
}