{
  "type": "Feature",
  "properties": {
    "addr:full":"Bodeus, S/n Bodeus La Coru\u00f1a 15379",
    "addr:postcode":"15379",
    "addr:street":"Bodeus S / N Bodeus La Corun\u0303A",
    "iso:country":"ES",
    "sg:address":"Bodeus, S/n",
    "sg:city":"Bodeus",
    "sg:orig_category":"Caf\u00c9s, Bares, Cervecer\u00cdas",
    "sg:phone":"+34 981 78 63 88",
    "sg:postcode":"15379",
    "sg:province":"La Coru\u00f1a",
    "wof:name":"Aldudo Collazo Jose Maria",
    "wof:placetype":"venue"
},
  "geometry": {"coordinates":[-8.1442403793,43.1275787354],"type":"Point"}
}