{
  "type": "Feature",
  "properties": {
    "iso:country":"ES",
    "sg:address":"Avda Zaragoza, 6",
    "sg:city":"Almunia De Do\u00e7a Godina",
    "sg:orig_category":"Mec\u00c1nico Del Autom\u00d3vil",
    "sg:phone":"+34 976 81 25 28",
    "sg:postcode":"50100",
    "sg:province":"Zaragoza",
    "wof:name":"Garaje Blas S.a.",
    "wof:placetype":"venue"
},
  "geometry": {"coordinates":[-1.3710800409,41.4833717346],"type":"Point"}
}