{
  "type": "Feature",
  "properties": {
    "iso:country":"ES",
    "sg:address":"Pase Castellana, 240",
    "sg:city":"Madrid",
    "sg:orig_category":"Agentes, Concesionarios Y Sucursales De Veh\u00cdculos",
    "sg:phone":"+34 913 14 06 90",
    "sg:postcode":"28046",
    "sg:province":"Madrid",
    "wof:name":"Auto Da Vinci S.a.",
    "wof:placetype":"venue"
},
  "geometry": {"coordinates":[-3.6876664162,40.4706459045],"type":"Point"}
}