{
  "type": "Feature",
  "properties": {
    "iso:country":"ES",
    "sg:address":"Ptda La Vila, S/n",
    "sg:city":"Sagunt",
    "sg:orig_category":"Vidrio (m\u00c1quinas Y Herramientas Para Trabajar El)",
    "sg:phone":"+34 962 65 05 89",
    "sg:postcode":"46500",
    "sg:province":"Valencia",
    "wof:name":"Cristaleria Cerezuela S.l.",
    "wof:placetype":"venue"
},
  "geometry": {"coordinates":[-0.2783089876,39.6799659729],"type":"Point"}
}