{
  "type": "Feature",
  "properties": {
    "iso:country":"ES",
    "sg:address":"Avda Aurelio Cabrera, 4",
    "sg:city":"Alburquerque",
    "sg:orig_category":"Financiaci\u00d3n Y Cr\u00c9ditos",
    "sg:phone":"+34 924 40 20 32",
    "sg:postcode":"06510",
    "sg:province":"Badajoz",
    "wof:name":"Caja Rural De Almendralejo",
    "wof:placetype":"venue"
},
  "geometry": {"coordinates":[-7.0014820099,39.2195892334],"type":"Point"}
}