{
  "type": "Feature",
  "properties": {
    "addr:full":"Pase Fernando El Catolico, 2 Zaragoza Zaragoza 50005",
    "addr:housenumber":"2",
    "addr:postcode":"50005",
    "addr:street":"Fernando El Catolico",
    "iso:country":"ES",
    "sg:address":"Pase Fernando El Catolico, 2",
    "sg:city":"Zaragoza",
    "sg:orig_category":"Loter\u00cda Y T\u00d3mbola",
    "sg:phone":"+34 976 55 72 59",
    "sg:postcode":"50005",
    "sg:province":"Zaragoza",
    "wof:name":"Herrero Galvez Maria Teresa",
    "wof:placetype":"venue"
},
  "geometry": {"coordinates":[-0.8923041224,41.6439361572],"type":"Point"}
}