{
  "type": "Feature",
  "properties": {
    "addr:full":"Ctra Chinchon (de), Km. 0002,5 Puente De Arganda Madrid 28500",
    "addr:postcode":"28500",
    "addr:street":"Ctra Chinchon De Km. 0002,5 Puente De Arganda",
    "iso:country":"ES",
    "sg:address":"Ctra Chinchon (de), Km. 0002,5",
    "sg:city":"Puente De Arganda",
    "sg:orig_category":"Fabricaci\u00d3n De Bibliotecas Y Estanter\u00cdas",
    "sg:phone":"+34 918 71 95 04",
    "sg:postcode":"28500",
    "sg:province":"Madrid",
    "sg:website":"www.tecny-stand.com",
    "wof:name":"Tecny Stand S. A.",
    "wof:placetype":"venue"
},
  "geometry": {"coordinates":[-3.4406979084,40.2999954224],"type":"Point"}
}