{
  "type": "Feature",
  "properties": {
    "addr:full":"Calle de Rio, 10 Beas Segura Ja\u00e9n 23280",
    "addr:housenumber":"10",
    "addr:postcode":"23280",
    "addr:street":"Calle De Rio",
    "iso:country":"ES",
    "sg:address":"Calle de Rio, 10",
    "sg:city":"Beas Segura",
    "sg:orig_category":"Electrodom\u00c9sticos (al Por Menor)",
    "sg:phone":"+34 953 45 81 04",
    "sg:postcode":"23280",
    "sg:province":"Ja\u00e9n",
    "wof:name":"Rodriguez Herrera Manuel",
    "wof:placetype":"venue"
},
  "geometry": {"coordinates":[-2.8860259056,38.2494773865],"type":"Point"}
}