{
  "type": "Feature",
  "properties": {
    "addr:full":"Avda Manzanares, 214 Madrid Madrid 28026",
    "addr:housenumber":"214",
    "addr:postcode":"28026",
    "addr:street":"Avda Manzanares",
    "iso:country":"ES",
    "sg:address":"Avda Manzanares, 214",
    "sg:city":"Madrid",
    "sg:orig_category":"Zapatos: Material, Suministros, Accesorios (fabricaci\u00d3n, Al Por Mayor)",
    "sg:phone":"+34 914 75 03 13",
    "sg:postcode":"28026",
    "sg:province":"Madrid",
    "wof:name":"Perniscarpe S.l.",
    "wof:placetype":"venue"
},
  "geometry": {"coordinates":[-3.699944973,40.389881134],"type":"Point"}
}