{
  "type": "Feature",
  "properties": {
    "addr:full":"Calle de Doctor Iranzo, 49 Zaragoza Zaragoza 50002",
    "addr:housenumber":"49",
    "addr:postcode":"50002",
    "addr:street":"Calle De Doctor Iranzo",
    "iso:country":"ES",
    "sg:address":"Calle de Doctor Iranzo, 49",
    "sg:city":"Zaragoza",
    "sg:orig_category":"Talleres: Ropa A Medida",
    "sg:phone":"+34 976 42 04 76",
    "sg:postcode":"50002",
    "sg:province":"Zaragoza",
    "wof:name":"Lapresta Lahuerta Federico Carlos",
    "wof:placetype":"venue"
},
  "geometry": {"coordinates":[-0.8641154766,41.6464729309],"type":"Point"}
}