{
  "type": "Feature",
  "properties": {
    "addr:full":"Avda Corts Valencianes, 43 Burriana Castell\u00f3n 12530",
    "addr:housenumber":"43",
    "addr:postcode":"12530",
    "addr:street":"Avda Corts Valencianes",
    "iso:country":"ES",
    "sg:address":"Avda Corts Valencianes, 43",
    "sg:city":"Burriana",
    "sg:orig_category":"Pizzer\u00cdas",
    "sg:phone":"+34 964 51 66 75",
    "sg:postcode":"12530",
    "sg:province":"Castell\u00f3n",
    "wof:name":"Capella Granell Eva",
    "wof:placetype":"venue"
},
  "geometry": {"coordinates":[-0.0814889967,39.8853492737],"type":"Point"}
}