{
  "type": "Feature",
  "properties": {
    "addr:full":"Partida Freixa, S/n Valls Tarragona 43800",
    "addr:housenumber":"s",
    "addr:postcode":"43800",
    "addr:street":"Partida Freixa;/ N",
    "iso:country":"ES",
    "sg:address":"Partida Freixa, S/n",
    "sg:city":"Valls",
    "sg:orig_category":"Muebles, Minoristas",
    "sg:phone":"+34 977 60 89 85",
    "sg:postcode":"43800",
    "sg:province":"Tarragona",
    "wof:name":"Nuria Sanchez Serra S.l.",
    "wof:placetype":"venue"
},
  "geometry": {"coordinates":[1.2525299788,41.2871513367],"type":"Point"}
}