{
  "type": "Feature",
  "properties": {
    "addr:full":"Ctra. Iturgoyen, S/n Riezu Navarra 31176",
    "addr:housenumber":"s",
    "addr:postcode":"31176",
    "addr:street":"Ctra. Iturgoyen;/ N Riezu Navarra",
    "iso:country":"ES",
    "sg:address":"Ctra. Iturgoyen, S/n",
    "sg:city":"Riezu",
    "sg:orig_category":"Sindicatos Y Colegios Profesionales",
    "sg:phone":"+34 948 54 20 30",
    "sg:postcode":"31176",
    "sg:province":"Navarra",
    "wof:name":"Sociedad Rezumendia",
    "wof:placetype":"venue"
},
  "geometry": {"coordinates":[-1.9324040413,42.7541732788],"type":"Point"}
}