{
  "type": "Feature",
  "properties": {
    "addr:full":"Calle de Capitan Haya, 61 Madrid Madrid 28020",
    "addr:housenumber":"61",
    "addr:postcode":"madrid;28020",
    "addr:street":"Calle De Capitan Haya",
    "iso:country":"ES",
    "sg:address":"Calle de Capitan Haya, 61",
    "sg:city":"Madrid",
    "sg:classifiers":[
        {
            "category":"Professional",
            "subcategory":"Research",
            "type":"Services"
        }
    ],
    "sg:phone":"+34 915 70 11 74",
    "sg:postcode":"28020",
    "sg:province":"Madrid",
    "sg:tags":[
        "mercado",
        "de",
        "estudios"
    ],
    "wof:name":"Asociacion Para La Investigacion De Los Medios De Comunicacion",
    "wof:placetype":"venue"
},
  "geometry": {"coordinates":[-3.6915090084,40.4649810791],"type":"Point"}
}