{
  "type": "Feature",
  "properties": {
    "addr:full":"Carrer de Partions, Ses, 22 Cala D'or Islas Baleares 07660",
    "addr:housenumber":"22",
    "addr:postcode":"07660",
    "addr:street":"Carrer De Partions Ses",
    "iso:country":"ES",
    "sg:address":"Carrer de Partions, Ses, 22",
    "sg:city":"Cala D'or",
    "sg:orig_category":"Electricidad, Electr\u00d3nica: Suministros (al Por Menor)",
    "sg:phone":"+34 971 64 31 74",
    "sg:postcode":"07660",
    "sg:province":"Islas Baleares",
    "wof:name":"Ferrer Roig Margarita",
    "wof:placetype":"venue"
},
  "geometry": {"coordinates":[2.9117100239,39.6136398315],"type":"Point"}
}