{
  "type": "Feature",
  "properties": {
    "addr:full":"Carrer de Jordi Joan, 4 Crevillent Alicante 03330",
    "addr:housenumber":"4",
    "addr:postcode":"03330",
    "addr:street":"Carrer De Jordi Joan",
    "iso:country":"ES",
    "sg:address":"Carrer de Jordi Joan, 4",
    "sg:city":"Crevillent",
    "sg:orig_category":"Reposter\u00cdas",
    "sg:phone":"+34 965 40 12 98",
    "sg:postcode":"03330",
    "sg:province":"Alicante",
    "wof:name":"Fuentes Marcial Antonio",
    "wof:placetype":"venue"
},
  "geometry": {"coordinates":[-0.8116459846,38.2513046265],"type":"Point"}
}