{
  "type": "Feature",
  "properties": {
    "iso:country":"ES",
    "sg:address":"Ctra Manresa, 24",
    "sg:city":"Igualada",
    "sg:orig_category":"Ense\u00d1anza: Peluquer\u00cda Est\u00c9tica",
    "sg:phone":"+34 938 05 47 41",
    "sg:postcode":"08700",
    "sg:province":"Barcelona",
    "wof:name":"Cano Domenech Soledad",
    "wof:placetype":"venue"
},
  "geometry": {"coordinates":[1.6136879921,41.5838127136],"type":"Point"}
}