{
  "type": "Feature",
  "properties": {
    "addr:full":"Av Mas De L'oli, 70 Manises Valencia 46940",
    "addr:housenumber":"70",
    "addr:postcode":"46940",
    "addr:street":"Av Mas De L'Oli",
    "iso:country":"ES",
    "sg:address":"Av Mas De L'oli, 70",
    "sg:city":"Manises",
    "sg:orig_category":"Muebles Y Accesorios Para Cocinas Y Cuartos De Ba\u00d1o (al Por Menor)",
    "sg:phone":"+34 961 53 37 14",
    "sg:postcode":"46940",
    "sg:province":"Valencia",
    "wof:name":"Hiperkit Cocinas S.l.",
    "wof:placetype":"venue"
},
  "geometry": {"coordinates":[-0.4884000123,39.5034790039],"type":"Point"}
}