{
  "type": "Feature",
  "properties": {
    "iso:country":"ES",
    "sg:address":"Calle de Fray Diego De Cadiz, 154",
    "sg:city":"Moron Frontera",
    "sg:orig_category":"Agencias De Viajes",
    "sg:phone":"+34 955 85 37 33",
    "sg:postcode":"41530",
    "sg:province":"Sevilla",
    "wof:name":"Johurco S.l.",
    "wof:placetype":"venue"
},
  "geometry": {"coordinates":[-5.4584088326,37.1217803955],"type":"Point"}
}