{
  "type": "Feature",
  "properties": {
    "addr:full":"Avgd Ausias March, 31 Alboraya Valencia 46120",
    "addr:housenumber":"31",
    "addr:postcode":"46120",
    "addr:street":"March",
    "iso:country":"ES",
    "sg:address":"Avgd Ausias March, 31",
    "sg:city":"Alboraya",
    "sg:orig_category":"Plomeros",
    "sg:phone":"+34 961 85 81 15",
    "sg:postcode":"46120",
    "sg:province":"Valencia",
    "wof:name":"Vivas Saez Elias",
    "wof:placetype":"venue"
},
  "geometry": {"coordinates":[-0.3502804935,39.495929718],"type":"Point"}
}