{
  "type": "Feature",
  "properties": {
    "addr:full":"Casa Puig, 1 Vila\u00fcr Girona 17483",
    "addr:housenumber":"1",
    "addr:postcode":"17483",
    "addr:street":"Vilauer Girona",
    "iso:country":"ES",
    "sg:address":"Casa Puig, 1",
    "sg:city":"Vila\u00fcr",
    "sg:orig_category":"Agricultura: Abastecimiento Y Cosechado (negocio)",
    "sg:phone":"+34 972 79 50 05",
    "sg:postcode":"17483",
    "sg:province":"Girona",
    "wof:name":"Valles Oriol S.l.",
    "wof:placetype":"venue"
},
  "geometry": {"coordinates":[2.9104669094,42.1579017639],"type":"Point"}
}