{
  "type": "Feature",
  "properties": {
    "addr:full":"Av Onze De Setembre, 77 Sant Joan De Palamos Girona 17230",
    "addr:housenumber":"77",
    "addr:postcode":"17230",
    "addr:street":"Av Onze De Setembre",
    "iso:country":"ES",
    "sg:address":"Av Onze De Setembre, 77",
    "sg:city":"Sant Joan De Palamos",
    "sg:orig_category":"Agencias De Viajes",
    "sg:phone":"+34 972 31 63 36",
    "sg:postcode":"17230",
    "sg:province":"Girona",
    "sg:website":"www.paretours.com",
    "wof:name":"Viatges Paretours S.a.",
    "wof:placetype":"venue"
},
  "geometry": {"coordinates":[3.1279499531,41.8474006653],"type":"Point"}
}