{
  "type": "Feature",
  "properties": {
    "iso:country":"ES",
    "sg:address":"Pla\u00c7 Major, 17",
    "sg:city":"Mollerussa",
    "sg:orig_category":"Perfumer\u00cda (al Por Menor)",
    "sg:phone":"+34 973 60 05 24",
    "sg:postcode":"25230",
    "sg:province":"Lleida",
    "wof:name":"Ixent Perfumeria Y Estetica S.l.",
    "wof:placetype":"venue"
},
  "geometry": {"coordinates":[0.8936949968,41.6300392151],"type":"Point"}
}