{
  "type": "Feature",
  "properties": {
    "iso:country":"ES",
    "sg:address":"Calle de Condes De Aragon, 9",
    "sg:city":"Zaragoza",
    "sg:orig_category":"Internados & Ense\u00d1anza Privada",
    "sg:phone":"+34 976 35 48 80",
    "sg:postcode":"50009",
    "sg:province":"Zaragoza",
    "wof:name":"Condes De Aragon Sociedad Cooperativa Limitada",
    "wof:placetype":"venue"
},
  "geometry": {"coordinates":[-0.9054237008,41.6390266418],"type":"Point"}
}