{
  "type": "Feature",
  "properties": {
    "addr:full":"Calle de San Juan, 15 Terriente Teruel 44120",
    "addr:housenumber":"15",
    "addr:postcode":"44120",
    "addr:street":"Calle De San Juan",
    "iso:country":"ES",
    "sg:address":"Calle de San Juan, 15",
    "sg:city":"Terriente",
    "sg:orig_category":"Cr\u00cda De Animales",
    "sg:phone":"+34 978 70 50 49",
    "sg:postcode":"44120",
    "sg:province":"Teruel",
    "wof:name":"Chico Andreu Cesar",
    "wof:placetype":"venue"
},
  "geometry": {"coordinates":[-1.5042179823,40.2982978821],"type":"Point"}
}