{
  "type": "Feature",
  "properties": {
    "addr:full":"Calle de Buenavista, 1 Parla Madrid 28980",
    "addr:housenumber":"1",
    "addr:postcode":"28980",
    "addr:street":"Calle De Buenavista",
    "iso:country":"ES",
    "sg:address":"Calle de Buenavista, 1",
    "sg:city":"Parla",
    "sg:orig_category":"Agentes, Concesionarios Y Sucursales De Veh\u00cdculos",
    "sg:phone":"+34 902 20 66 07",
    "sg:postcode":"28980",
    "sg:province":"Madrid",
    "sg:website":"www.hvt.es",
    "wof:name":"Hermanos Vi\u00d1ares Toledo S.a.",
    "wof:placetype":"venue"
},
  "geometry": {"coordinates":[-3.7727413177,40.237537384],"type":"Point"}
}