{
  "type": "Feature",
  "properties": {
    "addr:full":"Calle de Doctor Mara\u00d1on, 14 Aspe Alicante 03680",
    "addr:housenumber":"14",
    "addr:postcode":"03680",
    "addr:street":"Calle De Doctor Maran\u0303On",
    "iso:country":"ES",
    "sg:address":"Calle de Doctor Mara\u00d1on, 14",
    "sg:city":"Aspe",
    "sg:classifiers":[
        {
            "category":"Autos & Motor Vehicles",
            "subcategory":"Automobile Sales",
            "type":"Retail Goods"
        }
    ],
    "sg:phone":"+34 965 49 10 97",
    "sg:postcode":"03680",
    "sg:province":"Alicante",
    "wof:name":"Formacion Vial Saez S.l.",
    "wof:placetype":"venue"
},
  "geometry": {"coordinates":[-0.7654886246,38.3463592529],"type":"Point"}
}