{
  "type": "Feature",
  "properties": {
    "addr:full":"Carr Francesc Layret, 12 Badalona Barcelona 08911",
    "addr:housenumber":"12",
    "addr:postcode":"08911",
    "addr:street":"Carr Francesc Layret",
    "iso:country":"ES",
    "sg:address":"Carr Francesc Layret, 12",
    "sg:city":"Badalona",
    "sg:orig_category":"Fabrica De Cer\u00c1micas",
    "sg:phone":"+34 933 89 21 60",
    "sg:postcode":"08911",
    "sg:province":"Barcelona",
    "wof:name":"Guerao Martinez Encarna",
    "wof:placetype":"venue"
},
  "geometry": {"coordinates":[2.2462608814,41.4494552612],"type":"Point"}
}