{
  "type": "Feature",
  "properties": {
    "addr:full":"Pl Campfasso, 1 Cornella Llobregat Barcelona 08940",
    "addr:housenumber":"1",
    "addr:postcode":"08940",
    "addr:street":"Pl Campfasso",
    "iso:country":"ES",
    "sg:address":"Pl Campfasso, 1",
    "sg:city":"Cornella Llobregat",
    "sg:orig_category":"Reposter\u00cdas",
    "sg:phone":"+34 933 75 23 04",
    "sg:postcode":"08940",
    "sg:province":"Barcelona",
    "wof:name":"Gestion Hostelera Allofeal",
    "wof:placetype":"venue"
},
  "geometry": {"coordinates":[2.0761671066,41.3626098633],"type":"Point"}
}