{
  "type": "Feature",
  "properties": {
    "iso:country":"ES",
    "sg:address":"Calle de Corresponsal Tino Rebustiello, 5",
    "sg:city":"Pola De Lena",
    "sg:orig_category":"Pescader\u00cdas (al Por Menor)",
    "sg:phone":"+34 985 49 28 49",
    "sg:postcode":"33630",
    "sg:province":"Asturias",
    "wof:name":"Alvarez Tu\u00f1on Santos",
    "wof:placetype":"venue"
},
  "geometry": {"coordinates":[-5.8286514282,43.1595230103],"type":"Point"}
}