{
  "type": "Feature",
  "properties": {
    "iso:country":"ES",
    "sg:address":"Calle de Gran Via, 4",
    "sg:city":"Majadahonda",
    "sg:orig_category":"Estancos",
    "sg:phone":"+34 916 34 58 73",
    "sg:postcode":"28220",
    "sg:province":"Madrid",
    "wof:name":"Sanz Millan Isabel",
    "wof:placetype":"venue"
},
  "geometry": {"coordinates":[-3.8721590042,40.4749145508],"type":"Point"}
}