{
  "type": "Feature",
  "properties": {
    "iso:country":"ES",
    "sg:address":"Carr Diputat Josep Ribas, 8",
    "sg:city":"Eivissa",
    "sg:orig_category":"Asociaciones Y Clubs Deportivos",
    "sg:phone":"+34 971 31 04 50",
    "sg:postcode":"07800",
    "sg:province":"Islas Baleares",
    "wof:name":"Marras  Chrietelle Monique Liliane",
    "wof:placetype":"venue"
},
  "geometry": {"coordinates":[1.4342310429,38.9121932983],"type":"Point"}
}