{
  "type": "Feature",
  "properties": {
    "addr:full":"Avda Galicia, 11 Porto Do Son La Coru\u00f1a 15970",
    "addr:housenumber":"11",
    "addr:postcode":"15970",
    "addr:street":"Avda Galicia;Corun\u0303A",
    "iso:country":"ES",
    "sg:address":"Avda Galicia, 11",
    "sg:city":"Porto Do Son",
    "sg:orig_category":"Art\u00cdculos De Regalo (al Por Menor)",
    "sg:phone":"+34 981 85 31 52",
    "sg:postcode":"15970",
    "sg:province":"La Coru\u00f1a",
    "wof:name":"Blanco Santamaria Jose",
    "wof:placetype":"venue"
},
  "geometry": {"coordinates":[-9.0017986298,42.7256393433],"type":"Point"}
}