{
  "type": "Feature",
  "properties": {
    "iso:country":"ES",
    "sg:address":"Calle de Perindolas, 10",
    "sg:city":"Madrid",
    "sg:orig_category":"Mec\u00c1nico Del Autom\u00d3vil",
    "sg:phone":"+34 917 34 44 86",
    "sg:postcode":"28034",
    "sg:province":"Madrid",
    "wof:name":"Locer Nasan Diesel S.l.",
    "wof:placetype":"venue"
},
  "geometry": {"coordinates":[-3.6896591187,40.4972419739],"type":"Point"}
}