{
  "type": "Feature",
  "properties": {
    "iso:country":"ES",
    "sg:address":"Carrer de Marina, 114",
    "sg:city":"Barcelona",
    "sg:classifiers":[
        {
            "category":"Autos & Motor Vehicles",
            "subcategory":"Automobile Sales",
            "type":"Retail Goods"
        }
    ],
    "sg:phone":"+34 933 00 17 44",
    "sg:postcode":"08018",
    "sg:province":"Barcelona",
    "wof:name":"Sanz Santos Neus",
    "wof:placetype":"venue"
},
  "geometry": {"coordinates":[2.1874070168,41.3945999146],"type":"Point"}
}