{
  "type": "Feature",
  "properties": {
    "addr:full":"Oria Etorbidea-avenida De Oria, 8 Oria Guip\u00f9zcoa 20160",
    "addr:housenumber":"8",
    "addr:postcode":"20160",
    "addr:street":"Oria;Guipu\u0300Zcoa",
    "iso:country":"ES",
    "sg:address":"Oria Etorbidea-avenida De Oria, 8",
    "sg:city":"Oria",
    "sg:orig_category":"Servidores Y Editores De Bases De Datos",
    "sg:phone":"+34 943 36 12 21",
    "sg:postcode":"20160",
    "sg:province":"Guip\u00f9zcoa",
    "wof:name":"Hernandez Asensio Elena",
    "wof:placetype":"venue"
},
  "geometry": {"coordinates":[-2.020414114,43.2698173523],"type":"Point"}
}