{
  "type": "Feature",
  "properties": {
    "iso:country":"ES",
    "sg:address":"Calle de Moreras, 2",
    "sg:city":"Majadahonda",
    "sg:orig_category":"Agencias Y Agentes Comerciales, Representantes",
    "sg:phone":"+34 916 38 66 52",
    "sg:postcode":"28220",
    "sg:province":"Madrid",
    "wof:name":"5asec S.a.",
    "wof:placetype":"venue"
},
  "geometry": {"coordinates":[-3.861031,40.459377],"type":"Point"}
}