{
  "type": "Feature",
  "properties": {
    "iso:country":"ES",
    "sg:address":"Calle de Teresa De Leon, 13",
    "sg:city":"Nava De Abajo",
    "sg:orig_category":"Congelados: Productos Alimentarios (al Por Menor)",
    "sg:phone":"+34 967 29 30 15",
    "sg:postcode":"02142",
    "sg:province":"Albacete",
    "wof:name":"Hielo Cubinava S.l.",
    "wof:placetype":"venue"
},
  "geometry": {"coordinates":[-1.8685510159,38.6668243408],"type":"Point"}
}