{
  "type": "Feature",
  "properties": {
    "addr:full":"Calle de San Sebastian (de), 69 Colmenar Viejo Madrid 28770",
    "addr:postcode":"28770",
    "addr:street":"Calle De",
    "iso:country":"ES",
    "sg:address":"Calle de San Sebastian (de), 69",
    "sg:city":"Colmenar Viejo",
    "sg:orig_category":"Librer\u00cdas",
    "sg:phone":"+34 918 45 17 09",
    "sg:postcode":"28770",
    "sg:province":"Madrid",
    "wof:name":"Francisco Hoyo Basilio",
    "wof:placetype":"venue"
},
  "geometry": {"coordinates":[-3.7695860863,40.6648292542],"type":"Point"}
}