{
  "type": "Feature",
  "properties": {
    "iso:country":"ES",
    "sg:address":"Calle de Santa Marina, S/n",
    "sg:city":"Mirabel",
    "sg:orig_category":"Asociaciones, Organismos Culturales Y Socioeducativos",
    "sg:phone":"+34 927 45 02 79",
    "sg:postcode":"10540",
    "sg:province":"C\u00e1ceres",
    "wof:name":"Ayuntamiento De Mirabel",
    "wof:placetype":"venue"
},
  "geometry": {"coordinates":[-6.2327876091,39.8617973328],"type":"Point"}
}