{
  "type": "Feature",
  "properties": {
    "iso:country":"ES",
    "sg:address":"Calle de Polvoranca, 9",
    "sg:city":"Alcorcon",
    "sg:orig_category":"Muebles, Minoristas",
    "sg:phone":"+34 916 19 52 48",
    "sg:postcode":"28921",
    "sg:province":"Madrid",
    "wof:name":"Style Decoracion Fasion S.l.",
    "wof:placetype":"venue"
},
  "geometry": {"coordinates":[-3.7699546814,40.3267555237],"type":"Point"}
}