{
  "type": "Feature",
  "properties": {
    "iso:country":"ES",
    "sg:address":"Ctra Del Rocio, 163",
    "sg:city":"Almonte",
    "sg:orig_category":"Abogados",
    "sg:phone":"+34 959 45 14 55",
    "sg:postcode":"21730",
    "sg:province":"Huelva",
    "wof:name":"Mondaca Ba\u00f1ez Alberto",
    "wof:placetype":"venue"
},
  "geometry": {"coordinates":[-6.5203309059,37.2566375732],"type":"Point"}
}