{
  "type": "Feature",
  "properties": {
    "iso:country":"ES",
    "sg:address":"Pg Platans, 59",
    "sg:city":"Reus",
    "sg:orig_category":"Contenedores (mercanc\u00cdas)",
    "sg:phone":"+34 977 31 02 57",
    "sg:postcode":"43205",
    "sg:province":"Tarragona",
    "wof:name":"Jornet Batlle Joan",
    "wof:placetype":"venue"
},
  "geometry": {"coordinates":[1.0931680202,41.1479721069],"type":"Point"}
}