{
  "type": "Feature",
  "properties": {
    "iso:country":"ES",
    "sg:address":"Calle de Benito Perez Galdos, 40",
    "sg:city":"Alzira",
    "sg:orig_category":"Ropa Para Ni\u00d1os (al Por Menor)",
    "sg:phone":"+34 962 41 97 10",
    "sg:postcode":"46600",
    "sg:province":"Valencia",
    "wof:name":"Avima-2003 S.l.",
    "wof:placetype":"venue"
},
  "geometry": {"coordinates":[-0.4347409904,39.1500511169],"type":"Point"}
}