{
  "type": "Feature",
  "properties": {
    "iso:country":"ES",
    "sg:address":"Espirito Santo, 20",
    "sg:city":"So\u00f1eiro",
    "sg:orig_category":"Agricultores, Agricultores",
    "sg:phone":"+34 981 61 16 86",
    "sg:postcode":"15168",
    "sg:province":"La Coru\u00f1a",
    "wof:name":"Garcia Gomez Francisco",
    "wof:placetype":"venue"
},
  "geometry": {"coordinates":[-8.2781639099,43.3678283691],"type":"Point"}
}