{
  "type": "Feature",
  "properties": {
    "addr:full":"Carr Bisbe Huix, Del, 1 Eivissa Islas Baleares 07800",
    "addr:housenumber":"1",
    "addr:postcode":"07800",
    "addr:street":"Carr Bisbe Huix Del",
    "iso:country":"ES",
    "sg:address":"Carr Bisbe Huix, Del, 1",
    "sg:city":"Eivissa",
    "sg:orig_category":"Asesor\u00cda Fiscal Y Jur\u00cddica",
    "sg:phone":"+34 971 39 30 09",
    "sg:postcode":"07800",
    "sg:province":"Islas Baleares",
    "wof:name":"Cardona Tur Bartolome",
    "wof:placetype":"venue"
},
  "geometry": {"coordinates":[1.4296460152,38.9085350037],"type":"Point"}
}