{
  "type": "Feature",
  "properties": {
    "addr:full":"Carrer de Verge De Montserrat, 21 Santa Perpetua De Mogoda Barcelona 08130",
    "addr:housenumber":"21",
    "addr:postcode":"08130",
    "addr:street":"Carrer De Verge De Montserrat",
    "iso:country":"ES",
    "sg:address":"Carrer de Verge De Montserrat, 21",
    "sg:city":"Santa Perpetua De Mogoda",
    "sg:orig_category":"Confecci\u00d3n, Alquiler Y Venta De Maniqu\u00cdes De Escaparate",
    "sg:phone":"+34 935 60 31 36",
    "sg:postcode":"08130",
    "sg:province":"Barcelona",
    "wof:name":"Maniquies Aguado S.l",
    "wof:placetype":"venue"
},
  "geometry": {"coordinates":[2.1799199581,41.5378913879],"type":"Point"}
}