{
  "type": "Feature",
  "properties": {
    "iso:country":"ES",
    "sg:address":"Avda Balaidos, 41",
    "sg:city":"Vigo",
    "sg:orig_category":"Deportes Y Ocio: Art\u00cdculos Y Ropas (al Por Menor Y Accesorios)",
    "sg:phone":"+34 986 24 44 13",
    "sg:postcode":"36210",
    "sg:province":"Pontevedra",
    "sg:website":"www.deportesathletics.com",
    "wof:name":"Deportes Athletics Aventura S.l.",
    "wof:placetype":"venue"
},
  "geometry": {"coordinates":[-8.7353725433,42.2127075195],"type":"Point"}
}