{
  "type": "Feature",
  "properties": {
    "iso:country":"ES",
    "sg:address":"Carrer de Alfonso Xii, 81",
    "sg:city":"Mutxamel",
    "sg:orig_category":"Chapister\u00cda",
    "sg:phone":"+34 965 95 58 73",
    "sg:postcode":"03110",
    "sg:province":"Alicante",
    "wof:name":"Talleres Muchamel Coop.v",
    "wof:placetype":"venue"
},
  "geometry": {"coordinates":[-0.448864013,38.4230117798],"type":"Point"}
}