{
  "type": "Feature",
  "properties": {
    "addr:full":"Carr De Joan Xxiii, 8 Ontinyent Valencia 46870",
    "addr:housenumber":"8",
    "addr:postcode":"46870",
    "addr:street":"Carr De Joan Xxiii",
    "iso:country":"ES",
    "sg:address":"Carr De Joan Xxiii, 8",
    "sg:city":"Ontinyent",
    "sg:orig_category":"Carnicer\u00cdas, Carnicer\u00cdas",
    "sg:phone":"+34 962 38 26 57",
    "sg:postcode":"46870",
    "sg:province":"Valencia",
    "wof:name":"Gandia Pla Empresas S.l.",
    "wof:placetype":"venue"
},
  "geometry": {"coordinates":[-0.6130111814,38.8242683411],"type":"Point"}
}