{
  "type": "Feature",
  "properties": {
    "iso:country":"ES",
    "sg:address":"Calle de San Luis, 6",
    "sg:city":"Valladolid",
    "sg:orig_category":"Alimentaci\u00d3n General (al Por Menor)",
    "sg:phone":"+34 983 29 54 71",
    "sg:postcode":"47004",
    "sg:province":"Valladolid",
    "wof:name":"Villegas Ortega Vicente",
    "wof:placetype":"venue"
},
  "geometry": {"coordinates":[-4.7199759483,41.6467819214],"type":"Point"}
}