{
  "type": "Feature",
  "properties": {
    "iso:country":"ES",
    "sg:address":"Gipuzkoa Plaza, 2",
    "sg:city":"Alde Zaharra",
    "sg:orig_category":"Arquitectos",
    "sg:phone":"+34 943 64 25 89",
    "sg:postcode":"20280",
    "sg:province":"Guip\u00f9zcoa",
    "wof:name":"Abr & Arquitectos S.l.",
    "wof:placetype":"venue"
},
  "geometry": {"coordinates":[-1.79288,43.363831],"type":"Point"}
}