{
  "type": "Feature",
  "properties": {
    "iso:country":"ES",
    "sg:address":"Calle de Joaquin Costa, 8",
    "sg:city":"Le\u00f3n",
    "sg:orig_category":"Material Y Suministros Para Imprenta E Industrias Gr\u00c1ficas",
    "sg:phone":"+34 987 22 66 72",
    "sg:postcode":"24002",
    "sg:province":"Le\u00f3n",
    "wof:name":"Imprenta Rubin S.l.",
    "wof:placetype":"venue"
},
  "geometry": {"coordinates":[-5.5733270645,42.5997886658],"type":"Point"}
}