{
  "type": "Feature",
  "properties": {
    "addr:full":"Carr Pompeu Fabra, 22 Bisbal D'emporda Girona 17100",
    "addr:housenumber":"22",
    "addr:postcode":"17100",
    "addr:street":"Carr Pompeu Fabra",
    "iso:country":"ES",
    "sg:address":"Carr Pompeu Fabra, 22",
    "sg:city":"Bisbal D'emporda",
    "sg:orig_category":"Arquitectos",
    "sg:phone":"+34 972 64 04 44",
    "sg:postcode":"17100",
    "sg:province":"Girona",
    "wof:name":"Pales Pi Maria Marta",
    "wof:placetype":"venue"
},
  "geometry": {"coordinates":[2.8226881027,41.9813690186],"type":"Point"}
}