{
  "type": "Feature",
  "properties": {
    "addr:full":"Calle de Saladillo, 12 Estepa Sevilla 41560",
    "addr:housenumber":"12",
    "addr:postcode":"41560",
    "addr:street":"Calle De Saladillo;Sevilla",
    "iso:country":"ES",
    "sg:address":"Calle de Saladillo, 12",
    "sg:city":"Estepa",
    "sg:orig_category":"Oficinas De Turismo, Asociaciones De Iniciativa",
    "sg:phone":"+34 955 91 25 10",
    "sg:postcode":"41560",
    "sg:province":"Sevilla",
    "sg:website":"www.estepa.com",
    "wof:name":"Ayuntamiento De Estepa",
    "wof:placetype":"venue"
},
  "geometry": {"coordinates":[-4.8793635368,37.2897377014],"type":"Point"}
}