{
  "type": "Feature",
  "properties": {
    "iso:country":"ES",
    "sg:address":"Calle de Tarragona, 15",
    "sg:city":"Madrid",
    "sg:orig_category":"Bares, Piano",
    "sg:phone":"+34 915 39 96 96",
    "sg:postcode":"28045",
    "sg:province":"Madrid",
    "wof:name":"La Varita Magica S.l.",
    "wof:placetype":"venue"
},
  "geometry": {"coordinates":[-3.6966240406,40.4017181396],"type":"Point"}
}