{
  "type": "Feature",
  "properties": {
    "addr:full":"Sierra De Lujar, 3 Orgiva Granada 18400",
    "addr:housenumber":"3",
    "addr:postcode":"18400",
    "addr:street":"Sierra;Lujar",
    "iso:country":"ES",
    "sg:address":"Sierra De Lujar, 3",
    "sg:city":"Orgiva",
    "sg:orig_category":"Reposter\u00cdas",
    "sg:phone":"+34 958 78 56 48",
    "sg:postcode":"18400",
    "sg:province":"Granada",
    "wof:name":"Quevedo Sanchez Jose",
    "wof:placetype":"venue"
},
  "geometry": {"coordinates":[-3.423897028,36.9025421143],"type":"Point"}
}