{
  "type": "Feature",
  "properties": {
    "iso:country":"ES",
    "sg:address":"Avgd Puigfred, 16",
    "sg:city":"Badalona",
    "sg:orig_category":"Electrodom\u00c9sticos (al Por Menor)",
    "sg:phone":"+34 933 97 45 76",
    "sg:postcode":"08917",
    "sg:province":"Barcelona",
    "wof:name":"Meson Reche Felix",
    "wof:placetype":"venue"
},
  "geometry": {"coordinates":[2.2338500023,41.4534416199],"type":"Point"}
}