{
  "type": "Feature",
  "properties": {
    "addr:full":"Pase Olof Palme, S/n Badalona Barcelona 08917",
    "addr:housenumber":"s / n",
    "addr:postcode":"08917",
    "addr:street":"Olof Palme",
    "iso:country":"ES",
    "sg:address":"Pase Olof Palme, S/n",
    "sg:city":"Badalona",
    "sg:orig_category":"Ropa Para Caballeros (al Por Menor)",
    "sg:phone":"+34 934 65 85 70",
    "sg:postcode":"08917",
    "sg:province":"Barcelona",
    "sg:website":"www.spf.com",
    "wof:name":"Cortefiel S.a.",
    "wof:placetype":"venue"
},
  "geometry": {"coordinates":[2.2269508839,41.4548301697],"type":"Point"}
}