{
  "type": "Feature",
  "properties": {
    "iso:country":"ES",
    "sg:address":"Avda Reina Victoria, 6",
    "sg:city":"Santander",
    "sg:orig_category":"Farmacias",
    "sg:phone":"+34 942 21 66 60",
    "sg:postcode":"39004",
    "sg:province":"Cantabria",
    "wof:name":"Acebo Gomez Engracia",
    "wof:placetype":"venue"
},
  "geometry": {"coordinates":[-3.7880020142,43.4637489319],"type":"Point"}
}