{
  "type": "Feature",
  "properties": {
    "iso:country":"ES",
    "sg:address":"Calle de Jose Antonio Primo De Rivera, 20",
    "sg:city":"Ingenio",
    "sg:orig_category":"Alimentaci\u00d3n General (al Por Menor)",
    "sg:phone":"+34 928 78 05 29",
    "sg:postcode":"35250",
    "sg:province":"Las Palmas",
    "wof:name":"Vega Oliva Antonia",
    "wof:placetype":"venue"
},
  "geometry": {"coordinates":[-15.4358100891,27.9194412231],"type":"Point"}
}