{
  "type": "Feature",
  "properties": {
    "iso:country":"ES",
    "sg:address":"Calle de San Sebastian (de), 12",
    "sg:city":"Boadilla Del Monte",
    "sg:orig_category":"Caf\u00c9s, Bares, Cervecer\u00cdas",
    "sg:phone":"+34 916 33 11 59",
    "sg:postcode":"28660",
    "sg:province":"Madrid",
    "wof:name":"Llorente Llorente Estanislao",
    "wof:placetype":"venue"
},
  "geometry": {"coordinates":[-3.8772480488,40.4077186584],"type":"Point"}
}