{
  "type": "Feature",
  "properties": {
    "addr:full":"Pase Estacion (de La), 1 Aguilas Murcia 30880",
    "addr:postcode":"30880",
    "iso:country":"ES",
    "sg:address":"Pase Estacion (de La), 1",
    "sg:city":"Aguilas",
    "sg:orig_category":"Farmacias",
    "sg:phone":"+34 968 44 73 26",
    "sg:postcode":"30880",
    "sg:province":"Murcia",
    "wof:name":"Gil Barnes Blanca",
    "wof:placetype":"venue"
},
  "geometry": {"coordinates":[-1.5839740038,37.4077987671],"type":"Point"}
}