{
  "type": "Feature",
  "properties": {
    "addr:full":"Mas Saboya, S/n Bas Girona 17176",
    "addr:housenumber":"s",
    "addr:postcode":"17176",
    "addr:street":"/ N Bas Girona",
    "iso:country":"ES",
    "sg:address":"Mas Saboya, S/n",
    "sg:city":"Bas",
    "sg:orig_category":"Fabricaci\u00d3n De Taburetes, Sillas Y Sillones",
    "sg:phone":"+34 972 69 01 54",
    "sg:postcode":"17176",
    "sg:province":"Girona",
    "wof:name":"Dorca Duran David",
    "wof:placetype":"venue"
},
  "geometry": {"coordinates":[2.4526050091,42.1201705933],"type":"Point"}
}