{
  "type": "Feature",
  "properties": {
    "iso:country":"ES",
    "sg:address":"Avda Virgen De La Luz, 10",
    "sg:city":"Arroyo Luz",
    "sg:orig_category":"Estancos",
    "sg:phone":"+34 927 27 05 95",
    "sg:postcode":"10900",
    "sg:province":"C\u00e1ceres",
    "wof:name":"Montero Carrero Maria Angeles",
    "wof:placetype":"venue"
},
  "geometry": {"coordinates":[-6.5835771561,39.4866218567],"type":"Point"}
}