{
  "type": "Feature",
  "properties": {
    "iso:country":"ES",
    "sg:address":"M Poligono Comarca I, 19",
    "sg:city":"Orkoien",
    "sg:orig_category":"Construcciones Met\u00c1licas",
    "sg:phone":"+34 948 32 15 10",
    "sg:postcode":"31160",
    "sg:province":"Navarra",
    "wof:name":"Metalicas Berrioplano S.l.",
    "wof:placetype":"venue"
},
  "geometry": {"coordinates":[-1.7060990334,42.8219032288],"type":"Point"}
}