{
  "type": "Feature",
  "properties": {
    "addr:full":"Carrer de Roger De Flor, 125 Barcelona Barcelona 08013",
    "addr:housenumber":"125",
    "addr:postcode":"08013",
    "addr:street":"Carrer De Roger De Flor",
    "iso:country":"ES",
    "sg:address":"Carrer de Roger De Flor, 125",
    "sg:city":"Barcelona",
    "sg:orig_category":"Masajistas Kinesiterapeutas",
    "sg:phone":"+34 932 65 50 49",
    "sg:postcode":"08013",
    "sg:province":"Barcelona",
    "wof:name":"Pinillos Moya Nora Elcira",
    "wof:placetype":"venue"
},
  "geometry": {"coordinates":[2.1755421162,41.396396637],"type":"Point"}
}