{
  "type": "Feature",
  "properties": {
    "iso:country":"ES",
    "sg:address":"Calle de Real, 165",
    "sg:city":"S. Fernando",
    "sg:orig_category":"Lencer\u00cda Femenina, Corseter\u00cda, Trajes De Ba\u00d1o (al Por Menor)",
    "sg:phone":"+34 956 88 64 98",
    "sg:postcode":"11100",
    "sg:province":"C\u00e1diz",
    "wof:name":"Martinez Reyes Manuel",
    "wof:placetype":"venue"
},
  "geometry": {"coordinates":[-6.1990151405,36.4628677368],"type":"Point"}
}