{
  "type": "Feature",
  "properties": {
    "addr:full":"Calle de Manuel De Falla, 7 Santa Maria Aguila Almer\u00eda 04710",
    "addr:housenumber":"7",
    "addr:postcode":"04710",
    "addr:street":"Calle De Manuel De Falla;Almeri\u0301A",
    "iso:country":"ES",
    "sg:address":"Calle de Manuel De Falla, 7",
    "sg:city":"Santa Maria Aguila",
    "sg:orig_category":"Centros De Educaci\u00d3n Especial",
    "sg:phone":"+34 950 58 09 37",
    "sg:postcode":"04710",
    "sg:province":"Almer\u00eda",
    "wof:name":"Junta De Andalucia",
    "wof:placetype":"venue"
},
  "geometry": {"coordinates":[-2.7752890587,36.7839698792],"type":"Point"}
}