{
  "type": "Feature",
  "properties": {
    "addr:full":"Carrer de Thomas Alva Edison, 15 S. Esteve Sesrovires Barcelona 08635",
    "addr:housenumber":"15",
    "addr:postcode":"08635",
    "addr:street":"Carrer De Thomas Alva Edison;S. Esteve Sesrovires Barcelona",
    "iso:country":"ES",
    "sg:address":"Carrer de Thomas Alva Edison, 15",
    "sg:city":"S. Esteve Sesrovires",
    "sg:orig_category":"Tratamientos De Conversi\u00d3n Qu\u00cdmica O Electrol\u00cdtica De Metales",
    "sg:phone":"+34 937 79 86 08",
    "sg:postcode":"08635",
    "sg:province":"Barcelona",
    "wof:name":"Industrial Electrolitica Cano S.a.",
    "wof:placetype":"venue"
},
  "geometry": {"coordinates":[1.8731199503,41.4965515137],"type":"Point"}
}