{
  "type": "Feature",
  "properties": {
    "iso:country":"ES",
    "sg:address":"Masti-loidi, 3 B",
    "sg:city":"Errenteria",
    "sg:classifiers":[
        {
            "category":"Manufacturing",
            "subcategory":"Metals",
            "type":"Manufacturing & Wholesale Goods"
        }
    ],
    "sg:phone":"+34 943 34 47 62",
    "sg:postcode":"20100",
    "sg:province":"Guip\u00f9zcoa",
    "sg:tags":[
        "en",
        "fundiciones"
    ],
    "wof:name":"Fundiciones Gastesi,s.l.",
    "wof:placetype":"venue"
},
  "geometry": {"coordinates":[-1.8996850252,43.314365387],"type":"Point"}
}