{
  "type": "Feature",
  "properties": {
    "addr:full":"Calle de Beurko, 51 San Vicente De Barakaldo Vizcaya 48902",
    "addr:housenumber":"51",
    "addr:postcode":"48902",
    "addr:street":"Calle De Beurko",
    "iso:country":"ES",
    "sg:address":"Calle de Beurko, 51",
    "sg:city":"San Vicente De Barakaldo",
    "sg:orig_category":"Peluqueros: De Se\u00d1oras",
    "sg:phone":"+34 944 38 16 44",
    "sg:postcode":"48902",
    "sg:province":"Vizcaya",
    "wof:name":"Urraca Iglesias Enrique Javier",
    "wof:placetype":"venue"
},
  "geometry": {"coordinates":[-2.9940509796,43.2998161316],"type":"Point"}
}