{
  "type": "Feature",
  "properties": {
    "addr:full":"Nafarroa Kalea, 19 Zarautz Guip\u00f9zcoa 20800",
    "addr:housenumber":"19",
    "addr:postcode":"20800",
    "addr:street":"Nafarroa Kalea;Guipu\u0300Zcoa",
    "iso:country":"ES",
    "sg:address":"Nafarroa Kalea, 19",
    "sg:city":"Zarautz",
    "sg:orig_category":"M\u00c9dicos: Fisioterapia Y Rehabilitaci\u00d3n",
    "sg:phone":"+34 943 89 43 09",
    "sg:postcode":"20800",
    "sg:province":"Guip\u00f9zcoa",
    "wof:name":"Fundacion Jose Matia Calvo",
    "wof:placetype":"venue"
},
  "geometry": {"coordinates":[-2.1703948975,43.2862243652],"type":"Point"}
}