{
  "type": "Feature",
  "properties": {
    "addr:full":"Plaz Espa\u00d1a, 1 Zorita C\u00e1ceres 10130",
    "addr:housenumber":"1",
    "addr:postcode":"10130",
    "addr:street":"Plaz Espan\u0303A",
    "iso:country":"ES",
    "sg:address":"Plaz Espa\u00d1a, 1",
    "sg:city":"Zorita",
    "sg:orig_category":"Administraciones Regionales, Departamentales Y Locales",
    "sg:phone":"+34 927 34 00 02",
    "sg:postcode":"10130",
    "sg:province":"C\u00e1ceres",
    "wof:name":"Ayuntamiento De Zorita",
    "wof:placetype":"venue"
},
  "geometry": {"coordinates":[-5.7009339333,39.2863883972],"type":"Point"}
}