{
  "type": "Feature",
  "properties": {
    "iso:country":"ES",
    "sg:address":"Baiuca, S/n",
    "sg:city":"Baiuca",
    "sg:orig_category":"Equipo De Refrigeraci\u00d3n Industrial",
    "sg:phone":"+34 981 84 32 70",
    "sg:postcode":"15940",
    "sg:province":"La Coru\u00f1a",
    "wof:name":"Albacora S.a.",
    "wof:placetype":"venue"
},
  "geometry": {"coordinates":[-8.5049972534,43.3068466187],"type":"Point"}
}