{
  "type": "Feature",
  "properties": {
    "addr:full":"Ctra Medellin, Km. 2300,0 Caceres C\u00e1ceres 10005",
    "addr:postcode":"10005",
    "addr:street":"Ctra Medellin Km. 2300,0;Ca\u0301Ceres",
    "iso:country":"ES",
    "sg:address":"Ctra Medellin, Km. 2300,0",
    "sg:city":"Caceres",
    "sg:orig_category":"Ambulancias",
    "sg:phone":"+34 927 21 00 16",
    "sg:postcode":"10005",
    "sg:province":"C\u00e1ceres",
    "wof:name":"Ambulancias Angeles Amigos S.l.",
    "wof:placetype":"venue"
},
  "geometry": {"coordinates":[-6.3646349907,39.4518585205],"type":"Point"}
}