{
  "type": "Feature",
  "properties": {
    "iso:country":"ES",
    "sg:address":"Rua Jose Antonio, 61",
    "sg:city":"Silleda",
    "sg:orig_category":"Droguer\u00cdas (al Por Menor)",
    "sg:phone":"+34 986 58 01 97",
    "sg:postcode":"36540",
    "sg:province":"Pontevedra",
    "wof:name":"Gonzalez Carames Alfonso",
    "wof:placetype":"venue"
},
  "geometry": {"coordinates":[-8.2462425232,42.7017364502],"type":"Point"}
}