{
  "type": "Feature",
  "properties": {
    "iso:country":"ES",
    "sg:address":"Avda Ramon Y Cajal, 71",
    "sg:city":"Madrid",
    "sg:orig_category":"Marketing Telef\u00d3nico",
    "sg:phone":"+34 915 10 05 92",
    "sg:postcode":"28016",
    "sg:province":"Madrid",
    "wof:name":"Mirastiri S.l.",
    "wof:placetype":"venue"
},
  "geometry": {"coordinates":[-3.6684939861,40.4525337219],"type":"Point"}
}