{
  "type": "Feature",
  "properties": {
    "addr:full":"Avda Siete Villas, 12 Argo\u00f1os Cantabria 39197",
    "addr:housenumber":"12",
    "addr:postcode":"39197",
    "addr:street":"Avda Siete Villas",
    "iso:country":"ES",
    "sg:address":"Avda Siete Villas, 12",
    "sg:city":"Argo\u00f1os",
    "sg:orig_category":"Electricidad: Instaladores",
    "sg:phone":"+34 942 62 64 49",
    "sg:postcode":"39197",
    "sg:province":"Cantabria",
    "wof:name":"Electricidad Elesant S.l.",
    "wof:placetype":"venue"
},
  "geometry": {"coordinates":[-3.4865620136,43.4570808411],"type":"Point"}
}