{
  "type": "Feature",
  "properties": {
    "addr:full":"Avda Bierzo (el), 18 Bembibre Le\u00f3n 24300",
    "addr:postcode":"24300",
    "addr:street":"Avda Bierzo El;Leo\u0301N",
    "iso:country":"ES",
    "sg:address":"Avda Bierzo (el), 18",
    "sg:city":"Bembibre",
    "sg:orig_category":"Estancos",
    "sg:phone":"+34 987 51 02 45",
    "sg:postcode":"24300",
    "sg:province":"Le\u00f3n",
    "wof:name":"Alvarez Alvarez Maria Purificacion",
    "wof:placetype":"venue"
},
  "geometry": {"coordinates":[-6.4162068367,42.6166229248],"type":"Point"}
}