{
  "type": "Feature",
  "properties": {
    "addr:full":"Calle de Eduardo Coste, 9 Arenas -areeta Vizcaya 48930",
    "addr:housenumber":"9;areeta",
    "addr:postcode":"48930",
    "addr:street":"Calle De Eduardo Coste",
    "iso:country":"ES",
    "sg:address":"Calle de Eduardo Coste, 9",
    "sg:city":"Arenas -areeta",
    "sg:orig_category":"Fabricaci\u00d3n De Papeles Especiales Y Para Usos T\u00c9cnicos",
    "sg:phone":"+34 944 80 21 97",
    "sg:postcode":"48930",
    "sg:province":"Vizcaya",
    "sg:website":"www.polyrey.com",
    "wof:name":"Polyrey S.l.",
    "wof:placetype":"venue"
},
  "geometry": {"coordinates":[-3.0138859749,43.3226623535],"type":"Point"}
}