{
  "type": "Feature",
  "properties": {
    "iso:country":"ES",
    "sg:address":"Calle de Asociacion, 45",
    "sg:city":"Molina Segura",
    "sg:orig_category":"Maquinaria Para Industrias Diversas",
    "sg:phone":"+34 968 64 46 45",
    "sg:postcode":"30500",
    "sg:province":"Murcia",
    "wof:name":"R.m. Ofimatica S.l.",
    "wof:placetype":"venue"
},
  "geometry": {"coordinates":[-1.214545846,38.0601921082],"type":"Point"}
}