{
  "type": "Feature",
  "properties": {
    "iso:country":"ES",
    "sg:address":"Calle de Navarra, 1",
    "sg:city":"Rozas De Madrid",
    "sg:orig_category":"Administradores De Bienes Y Delegados De Comunidades De Propietarios",
    "sg:phone":"+34 916 36 15 30",
    "sg:postcode":"28230",
    "sg:province":"Madrid",
    "wof:name":"Afinser S.l.",
    "wof:placetype":"venue"
},
  "geometry": {"coordinates":[-3.8763916492,40.4931526184],"type":"Point"}
}