{
  "type": "Feature",
  "properties": {
    "addr:full":"Calle de Santa Natalia, 5 Nules Castell\u00f3n 12520",
    "addr:housenumber":"5",
    "addr:postcode":"12520",
    "addr:street":"Calle De Santa Natalia",
    "iso:country":"ES",
    "sg:address":"Calle de Santa Natalia, 5",
    "sg:city":"Nules",
    "sg:orig_category":"Carnicer\u00cdas, Carnicer\u00cdas",
    "sg:phone":"+34 964 67 27 13",
    "sg:postcode":"12520",
    "sg:province":"Castell\u00f3n",
    "wof:name":"Sorribes Martinez Alberto Antonio",
    "wof:placetype":"venue"
},
  "geometry": {"coordinates":[-0.157506004,39.8543968201],"type":"Point"}
}