{
  "type": "Feature",
  "properties": {
    "iso:country":"ES",
    "sg:address":"Calle de Ramon Perez De Ayala, 26",
    "sg:city":"Mieres",
    "sg:classifiers":[
        {
            "category":"Utilities",
            "subcategory":"Natural Gas",
            "type":"Services"
        }
    ],
    "sg:phone":"+34 985 45 41 24",
    "sg:postcode":"33600",
    "sg:province":"Asturias",
    "sg:tags":[
        "te",
        "de",
        "salones"
    ],
    "wof:name":"Alvarez Ca\u00f1edo Maria Jose",
    "wof:placetype":"venue"
},
  "geometry": {"coordinates":[-5.7780213356,43.2526130676],"type":"Point"}
}