{
  "type": "Feature",
  "properties": {
    "iso:country":"ES",
    "sg:address":"Calle de Sertorio, 3",
    "sg:city":"Denia",
    "sg:orig_category":"Art\u00cdculos De Decoraci\u00d3n",
    "sg:phone":"+34 965 78 71 44",
    "sg:postcode":"03700",
    "sg:province":"Alicante",
    "wof:name":"Fornasetti S.l.",
    "wof:placetype":"venue"
},
  "geometry": {"coordinates":[0.106945999,38.8374481201],"type":"Point"}
}