{
  "type": "Feature",
  "properties": {
    "iso:country":"ES",
    "sg:address":"Calle de Real De Burgos, 7",
    "sg:city":"Valladolid",
    "sg:orig_category":"Peluquer\u00cdas, Peluquer\u00cda Mixta",
    "sg:phone":"+34 983 25 38 97",
    "sg:postcode":"47011",
    "sg:province":"Valladolid",
    "wof:name":"Hernando Abia S.l.",
    "wof:placetype":"venue"
},
  "geometry": {"coordinates":[-4.7187361717,41.6580467224],"type":"Point"}
}