{
  "type": "Feature",
  "properties": {
    "addr:full":"Avda Republica Argentina, 30 Le\u00f3n Le\u00f3n 24004",
    "addr:housenumber":"30",
    "addr:postcode":"24004",
    "addr:street":"Avda Republica Argentina;Leo\u0301N",
    "iso:country":"ES",
    "sg:address":"Avda Republica Argentina, 30",
    "sg:city":"Le\u00f3n",
    "sg:orig_category":"Abogados",
    "sg:phone":"+34 987 26 06 20",
    "sg:postcode":"24004",
    "sg:province":"Le\u00f3n",
    "wof:name":"Saenz De Miera Carnicer Maria Teresa",
    "wof:placetype":"venue"
},
  "geometry": {"coordinates":[-5.5758328438,42.5955505371],"type":"Point"}
}