{
  "type": "Feature",
  "properties": {
    "iso:country":"ES",
    "sg:address":"Carr Anselm Clave, 93",
    "sg:city":"Blanes",
    "sg:orig_category":"Centros M\u00c9dicos Y Sociales, Dispensarios",
    "sg:phone":"+34 972 35 35 25",
    "sg:postcode":"17300",
    "sg:province":"Girona",
    "wof:name":"General Lab S.a.",
    "wof:placetype":"venue"
},
  "geometry": {"coordinates":[2.7841329575,41.678943634],"type":"Point"}
}