{
  "type": "Feature",
  "properties": {
    "iso:country":"ES",
    "sg:address":"Carrer de Doctor Mallafre Guasch, 3",
    "sg:city":"Tarragona",
    "sg:orig_category":"Servicios De Telecomunicaciones",
    "sg:phone":"+34 977 22 99 75",
    "sg:postcode":"43007",
    "sg:province":"Tarragona",
    "wof:name":"Arpo Telecomunicaciones S.l.",
    "wof:placetype":"venue"
},
  "geometry": {"coordinates":[1.2602227926,41.1433296204],"type":"Point"}
}