{
  "type": "Feature",
  "properties": {
    "iso:country":"ES",
    "sg:address":"Calle de Alcalde Gil Rodriguez, 7",
    "sg:city":"Langreo",
    "sg:orig_category":"Artes Gr\u00c1ficas, Artes Pl\u00c1sticas (curso)",
    "sg:phone":"+34 985 69 24 75",
    "sg:postcode":"33900",
    "sg:province":"Asturias",
    "wof:name":"Martinez Fernandez Carlos",
    "wof:placetype":"venue"
},
  "geometry": {"coordinates":[-5.6696782112,43.2890129089],"type":"Point"}
}