{
  "type": "Feature",
  "properties": {
    "iso:country":"ES",
    "sg:address":"Carr Cavallers, 42",
    "sg:city":"Bisbal D'emporda",
    "sg:orig_category":"Chapister\u00cda",
    "sg:phone":"+34 972 64 03 38",
    "sg:postcode":"17100",
    "sg:province":"Girona",
    "wof:name":"Trias Pareras Jordi",
    "wof:placetype":"venue"
},
  "geometry": {"coordinates":[2.8000710011,41.9957542419],"type":"Point"}
}