{
  "type": "Feature",
  "properties": {
    "iso:country":"ES",
    "sg:address":"Rua Cruz (da), 18",
    "sg:city":"Lugo",
    "sg:orig_category":"Deportes Y Ocio: Art\u00cdculos Y Ropas (al Por Menor Y Accesorios)",
    "sg:phone":"+34 982 22 90 54",
    "sg:postcode":"27001",
    "sg:province":"Lugo",
    "sg:website":"www.coroneltapiocca.com",
    "wof:name":"Coronel Tapioca S.a.",
    "wof:placetype":"venue"
},
  "geometry": {"coordinates":[-7.5578751564,43.010269165],"type":"Point"}
}