{
  "type": "Feature",
  "properties": {
    "addr:full":"Calle de Santa Teresa, 37 Malia\u00d1o Cantabria 39600",
    "addr:housenumber":"37",
    "addr:postcode":"39600",
    "addr:street":"Calle De Santa Teresa",
    "iso:country":"ES",
    "sg:address":"Calle de Santa Teresa, 37",
    "sg:city":"Malia\u00d1o",
    "sg:orig_category":"Empresas De Carpinter\u00cda De Madera",
    "sg:phone":"+34 942 25 38 33",
    "sg:postcode":"39600",
    "sg:province":"Cantabria",
    "wof:name":"Fernandez Sustacha Anselmo",
    "wof:placetype":"venue"
},
  "geometry": {"coordinates":[-3.8376019001,43.4190444946],"type":"Point"}
}