{
  "type": "Feature",
  "properties": {
    "iso:country":"ES",
    "sg:address":"Emilio Arrieta, 6",
    "sg:city":"Iru\u00f1a",
    "sg:classifiers":[
        {
            "category":"Professional",
            "subcategory":"Research",
            "type":"Services"
        }
    ],
    "sg:phone":"+34 948 22 76 71",
    "sg:postcode":"31002",
    "sg:province":"Navarra",
    "sg:tags":[
        "mercado",
        "de",
        "estudios"
    ],
    "wof:name":"Araldi S.l.",
    "wof:placetype":"venue"
},
  "geometry": {"coordinates":[-1.6403497458,42.8144187927],"type":"Point"}
}