{
  "type": "Feature",
  "properties": {
    "iso:country":"ES",
    "sg:address":"Poli Industrial C/x, 8",
    "sg:city":"Rozas De Madrid",
    "sg:orig_category":"Muebles, Minoristas",
    "sg:phone":"+34 916 36 02 49",
    "sg:postcode":"28230",
    "sg:province":"Madrid",
    "wof:name":"Juan Parrabera S.l.",
    "wof:placetype":"venue"
},
  "geometry": {"coordinates":[-3.8913800716,40.5247497559],"type":"Point"}
}