{
  "type": "Feature",
  "properties": {
    "iso:country":"ES",
    "sg:address":"Trss Industrial, 177",
    "sg:city":"Hospitalet Llobregat",
    "sg:orig_category":"Lavado, Limpieza De Veh\u00cdculos",
    "sg:phone":"+34 933 36 43 02",
    "sg:postcode":"08907",
    "sg:province":"Barcelona",
    "wof:name":"Areas Del Servicio Del Automovil Numero Dos S. A.",
    "wof:placetype":"venue"
},
  "geometry": {"coordinates":[2.1699187756,41.3879165649],"type":"Point"}
}