{
  "type": "Feature",
  "properties": {
    "addr:full":"C/ Gloria, 35 Inca Islas Baleares 07300",
    "addr:housenumber":"35",
    "addr:postcode":"07300",
    "addr:street":"C / Gloria",
    "iso:country":"ES",
    "sg:address":"C/ Gloria, 35",
    "sg:city":"Inca",
    "sg:orig_category":"Gases Industriales",
    "sg:phone":"+34 971 50 02 64",
    "sg:postcode":"07300",
    "sg:province":"Islas Baleares",
    "wof:name":"Distribuidora Foranea De Gas S.l.",
    "wof:placetype":"venue"
},
  "geometry": {"coordinates":[2.9104180336,39.7222175598],"type":"Point"}
}