{
  "type": "Feature",
  "properties": {
    "iso:country":"ES",
    "sg:address":"Carrer de Ponent, 24",
    "sg:city":"Molins Rei",
    "sg:orig_category":"Peluqueros: De Se\u00d1oras",
    "sg:phone":"+34 936 68 14 19",
    "sg:postcode":"08750",
    "sg:province":"Barcelona",
    "wof:name":"Pintado Martinez Francisco",
    "wof:placetype":"venue"
},
  "geometry": {"coordinates":[2.0637829304,41.4432868958],"type":"Point"}
}