{
  "type": "Feature",
  "properties": {
    "addr:full":"Calle de Puerta De Granada, 7 Roda Albacete 02630",
    "addr:housenumber":"7",
    "addr:postcode":"02630",
    "addr:street":"Calle De Puerta De Granada",
    "iso:country":"ES",
    "sg:address":"Calle de Puerta De Granada, 7",
    "sg:city":"Roda",
    "sg:orig_category":"Negocio De Materiales De Construcci\u00d3n",
    "sg:phone":"+34 967 44 03 40",
    "sg:postcode":"02630",
    "sg:province":"Albacete",
    "wof:name":"Zalve Escudero Gabriel",
    "wof:placetype":"venue"
},
  "geometry": {"coordinates":[-2.1608641148,39.204082489],"type":"Point"}
}