{
  "type": "Feature",
  "properties": {
    "iso:country":"ES",
    "sg:address":"La Aldea, 2",
    "sg:city":"San Miguel Camino",
    "sg:orig_category":"Cl\u00cdnicas M\u00c9dicas",
    "sg:phone":"+34 987 30 34 49",
    "sg:postcode":"24391",
    "sg:province":"Le\u00f3n",
    "wof:name":"Clinica El Camino S.l.",
    "wof:placetype":"venue"
},
  "geometry": {"coordinates":[-5.6244401932,42.5436477661],"type":"Point"}
}