{
  "type": "Feature",
  "properties": {
    "addr:full":"Calle de Covadonga, 22 Oviedo Asturias 33002",
    "addr:housenumber":"22",
    "addr:postcode":"33002",
    "addr:street":"Calle De Covadonga",
    "iso:country":"ES",
    "sg:address":"Calle de Covadonga, 22",
    "sg:city":"Oviedo",
    "sg:orig_category":"Pescader\u00cdas (al Por Menor)",
    "sg:phone":"+34 985 22 69 30",
    "sg:postcode":"33002",
    "sg:province":"Asturias",
    "wof:name":"Bri S. A.",
    "wof:placetype":"venue"
},
  "geometry": {"coordinates":[-5.8488945961,43.3643913269],"type":"Point"}
}