{
  "type": "Feature",
  "properties": {
    "iso:country":"ES",
    "sg:address":"Calle de Mondragon, S/n",
    "sg:city":"Malaga",
    "sg:orig_category":"Abogados",
    "sg:phone":"+34 952 25 18 38",
    "sg:postcode":"29014",
    "sg:province":"M\u00e1laga",
    "wof:name":"Morales Morales Salvador",
    "wof:placetype":"venue"
},
  "geometry": {"coordinates":[-4.4238538742,36.7441940308],"type":"Point"}
}