{
  "type": "Feature",
  "properties": {
    "addr:full":"Carrer de Seneca, 29 Barcelona Barcelona 08006",
    "addr:housenumber":"29",
    "addr:postcode":"08006",
    "addr:street":"Carrer De Seneca",
    "iso:country":"ES",
    "sg:address":"Carrer de Seneca, 29",
    "sg:city":"Barcelona",
    "sg:orig_category":"Clubes, Asociaciones De Ocio",
    "sg:phone":"+34 932 37 45 39",
    "sg:postcode":"08006",
    "sg:province":"Barcelona",
    "wof:name":"Cordero Maramotti Ernesto",
    "wof:placetype":"venue"
},
  "geometry": {"coordinates":[2.1558749676,41.3964576721],"type":"Point"}
}