{
  "type": "Feature",
  "properties": {
    "addr:full":"Rua Michelena, 32 Pontevedra Pontevedra 36002",
    "addr:housenumber":"32",
    "addr:postcode":"36002",
    "addr:street":"Rua Michelena",
    "iso:country":"ES",
    "sg:address":"Rua Michelena, 32",
    "sg:city":"Pontevedra",
    "sg:orig_category":"Reposter\u00cdas",
    "sg:phone":"+34 986 84 44 09",
    "sg:postcode":"36002",
    "sg:province":"Pontevedra",
    "wof:name":"Acupan S.l.",
    "wof:placetype":"venue"
},
  "geometry": {"coordinates":[-8.6463499069,42.4315872192],"type":"Point"}
}