{
  "type": "Feature",
  "properties": {
    "iso:country":"ES",
    "sg:address":"Avda Washington, 30",
    "sg:city":"Malaga",
    "sg:orig_category":"Muebles, Minoristas",
    "sg:phone":"+34 952 03 88 12",
    "sg:postcode":"29006",
    "sg:province":"M\u00e1laga",
    "wof:name":"Viva Art Import S.l.",
    "wof:placetype":"venue"
},
  "geometry": {"coordinates":[-4.482758522,36.7106628418],"type":"Point"}
}