{
  "type": "Feature",
  "properties": {
    "iso:country":"ES",
    "sg:address":"Calle de Agricultura (de La), 24",
    "sg:city":"Huesca",
    "sg:orig_category":"Electricidad (montaje, Ensamblaje De Componentes)",
    "sg:phone":"+34 974 23 24 71",
    "sg:postcode":"22006",
    "sg:province":"Huesca",
    "wof:name":"Electricidad Del Automovil Sanchez Campo S.l.u.",
    "wof:placetype":"venue"
},
  "geometry": {"coordinates":[-0.4078809023,42.1469345093],"type":"Point"}
}