{
  "type": "Feature",
  "properties": {
    "addr:full":"Calle de Berrocal, 5 Madrid Madrid 28021",
    "addr:housenumber":"5",
    "addr:postcode":"28021",
    "addr:street":"Calle De Berrocal",
    "iso:country":"ES",
    "sg:address":"Calle de Berrocal, 5",
    "sg:city":"Madrid",
    "sg:orig_category":"Cajas De Ahorro",
    "sg:phone":"+34 917 23 06 93",
    "sg:postcode":"28021",
    "sg:province":"Madrid",
    "wof:name":"Caja De Ahorros Y Monte De Piedad De Zaragoza Aragon Y Rioja",
    "wof:placetype":"venue"
},
  "geometry": {"coordinates":[-3.676915884,40.346370697],"type":"Point"}
}