{
  "type": "Feature",
  "properties": {
    "iso:country":"ES",
    "sg:address":"Calle de Goya, 7",
    "sg:city":"Aldeatejada",
    "sg:orig_category":"Empresas De Desmonte",
    "sg:phone":"+34 923 34 11 27",
    "sg:postcode":"37187",
    "sg:province":"Salamanca",
    "wof:name":"Sanchez Azabal Jose Antonio",
    "wof:placetype":"venue"
},
  "geometry": {"coordinates":[-5.6928792,40.9266853333],"type":"Point"}
}