{
  "type": "Feature",
  "properties": {
    "iso:country":"ES",
    "sg:address":"Calle de Madrid, 29",
    "sg:city":"Ejido",
    "sg:orig_category":"Partidos Pol\u00cdticos",
    "sg:phone":"+34 950 48 94 46",
    "sg:postcode":"04700",
    "sg:province":"Almer\u00eda",
    "wof:name":"Partido Popular",
    "wof:placetype":"venue"
},
  "geometry": {"coordinates":[-2.8116900921,36.7724838257],"type":"Point"}
}