{
  "type": "Feature",
  "properties": {
    "iso:country":"ES",
    "sg:address":"Avda Guadalquivir, 23",
    "sg:city":"Cadiz",
    "sg:orig_category":"Alimentaci\u00d3n General (al Por Menor)",
    "sg:phone":"+34 956 25 39 14",
    "sg:postcode":"11012",
    "sg:province":"C\u00e1diz",
    "wof:name":"Cordoba Ruiz Manuel",
    "wof:placetype":"venue"
},
  "geometry": {"coordinates":[-6.2771291733,36.5191764832],"type":"Point"}
}