{
  "type": "Feature",
  "properties": {
    "addr:full":"Ctra Constantina-pedroso, Km. 0001,0 Constantina Sevilla 41450",
    "addr:postcode":"41450",
    "addr:street":"Ctra Constantina-Pedroso Km. 0001,0",
    "iso:country":"ES",
    "sg:address":"Ctra Constantina-pedroso, Km. 0001,0",
    "sg:city":"Constantina",
    "sg:orig_category":"Oficinas De Turismo, Asociaciones De Iniciativa",
    "sg:phone":"+34 955 88 15 97",
    "sg:postcode":"41450",
    "sg:province":"Sevilla",
    "wof:name":"Empresa De Gestion Medio Ambiental S.a.",
    "wof:placetype":"venue"
},
  "geometry": {"coordinates":[-5.6193537712,37.8619995117],"type":"Point"}
}