{
  "type": "Feature",
  "properties": {
    "addr:full":"Carrer de Orient, 78 S. Cugat Valles Barcelona 08172",
    "addr:housenumber":"78",
    "addr:postcode":"08172",
    "addr:street":"Carrer De Orient;S. Cugat Valles Barcelona",
    "iso:country":"ES",
    "sg:address":"Carrer de Orient, 78",
    "sg:city":"S. Cugat Valles",
    "sg:orig_category":"Centros Empresariales",
    "sg:phone":"+34 935 44 23 92",
    "sg:postcode":"08172",
    "sg:province":"Barcelona",
    "wof:name":"Freitag Mu\u00f1oz Carlos Enrique",
    "wof:placetype":"venue"
},
  "geometry": {"coordinates":[2.091835022,41.4746932983],"type":"Point"}
}