{
  "type": "Feature",
  "properties": {
    "addr:full":"Calle de Sauquillo, 10 Aldea Real Segovia 40293",
    "addr:housenumber":"10",
    "addr:postcode":"40293",
    "addr:street":"Calle De Sauquillo",
    "iso:country":"ES",
    "sg:address":"Calle de Sauquillo, 10",
    "sg:city":"Aldea Real",
    "sg:orig_category":"Contenedores (mercanc\u00cdas)",
    "sg:phone":"+34 921 57 06 14",
    "sg:postcode":"40293",
    "sg:province":"Segovia",
    "wof:name":"Rosa Lomillos Jesus",
    "wof:placetype":"venue"
},
  "geometry": {"coordinates":[-4.1844592094,41.259979248],"type":"Point"}
}