{
  "type": "Feature",
  "properties": {
    "addr:full":"Calle de Algarrobo, 16 Malaga M\u00e1laga 29018",
    "addr:housenumber":"16",
    "addr:postcode":"29018",
    "addr:street":"Calle De Algarrobo;Ma\u0301Laga",
    "iso:country":"ES",
    "sg:address":"Calle de Algarrobo, 16",
    "sg:city":"Malaga",
    "sg:orig_category":"Mec\u00c1nico Del Autom\u00d3vil",
    "sg:phone":"+34 952 29 22 86",
    "sg:postcode":"29018",
    "sg:province":"M\u00e1laga",
    "wof:name":"Sancho Montenegro Francisco",
    "wof:placetype":"venue"
},
  "geometry": {"coordinates":[-4.3505487442,36.7222747803],"type":"Point"}
}