{
  "type": "Feature",
  "properties": {
    "addr:full":"Pase Casta\u00d1os (los), S/n Aguadulce Almer\u00eda 04720",
    "addr:postcode":"04720",
    "addr:street":"Los S / N;Almeri\u0301A",
    "iso:country":"ES",
    "sg:address":"Pase Casta\u00d1os (los), S/n",
    "sg:city":"Aguadulce",
    "sg:orig_category":"Inversiones",
    "sg:phone":"+34 950 34 22 46",
    "sg:postcode":"04720",
    "sg:province":"Almer\u00eda",
    "wof:name":"Menfer Inversiones S.l.",
    "wof:placetype":"venue"
},
  "geometry": {"coordinates":[-2.5709340572,36.8139152527],"type":"Point"}
}