{
  "type": "Feature",
  "properties": {
    "addr:full":"Calle de San Andres, S/n Aizpun Navarra 31172",
    "addr:housenumber":"s",
    "addr:postcode":"31172",
    "addr:street":"Calle De San Andres;/ N Aizpun Navarra",
    "iso:country":"ES",
    "sg:address":"Calle de San Andres, S/n",
    "sg:city":"Aizpun",
    "sg:orig_category":"Producci\u00d3n, Comercio De Cereales",
    "sg:phone":"+34 948 32 83 00",
    "sg:postcode":"31172",
    "sg:province":"Navarra",
    "wof:name":"Sociedad Cooperativa Limitada Cerealista De Urroz Villa",
    "wof:placetype":"venue"
},
  "geometry": {"coordinates":[-1.8750239611,42.8321914673],"type":"Point"}
}