{
  "type": "Feature",
  "properties": {
    "iso:country":"ES",
    "sg:address":"Carr Masia De La Cova, 21",
    "sg:city":"Manises",
    "sg:orig_category":"Molduras, Junquillos, Listones Y Molduras Perforadas",
    "sg:phone":"+34 961 52 07 68",
    "sg:postcode":"46940",
    "sg:province":"Valencia",
    "wof:name":"Chaparro Alfaro Jose Luis",
    "wof:placetype":"venue"
},
  "geometry": {"coordinates":[-0.462056011,39.4937973022],"type":"Point"}
}