{
  "type": "Feature",
  "properties": {
    "iso:country":"ES",
    "sg:address":"Pla\u00c7 Virgen De Loreto, 10",
    "sg:city":"Olleria",
    "sg:orig_category":"Cajas De Ahorro",
    "sg:phone":"+34 962 20 04 31",
    "sg:postcode":"46850",
    "sg:province":"Valencia",
    "sg:website":"www.bancaja.es",
    "wof:name":"Caja De Ahorros De Valencia Castellon Y Alicante",
    "wof:placetype":"venue"
},
  "geometry": {"coordinates":[-0.549266994,38.9136238098],"type":"Point"}
}