{
  "type": "Feature",
  "properties": {
    "iso:country":"ES",
    "sg:address":"Pl. De Jose Antonio, S/n",
    "sg:city":"Utrillas",
    "sg:orig_category":"Centros De Educaci\u00d3n Especial",
    "sg:phone":"+34 978 75 71 60",
    "sg:postcode":"44760",
    "sg:province":"Teruel",
    "wof:name":"Diputacion General De Aragon",
    "wof:placetype":"venue"
},
  "geometry": {"coordinates":[-0.8442590237,40.8141403198],"type":"Point"}
}