{
  "type": "Feature",
  "properties": {
    "addr:full":"Carrer de Proven\u00c7a, 104 Barcelona Barcelona 08029",
    "addr:housenumber":"104",
    "addr:postcode":"08029",
    "addr:street":"Carrer De Provenc\u0327A",
    "iso:country":"ES",
    "sg:address":"Carrer de Proven\u00c7a, 104",
    "sg:city":"Barcelona",
    "sg:orig_category":"Azafatas Para Recepciones",
    "sg:phone":"+34 934 05 11 41",
    "sg:postcode":"08029",
    "sg:province":"Barcelona",
    "wof:name":"Associacio D'ensenyament General I Professional",
    "wof:placetype":"venue"
},
  "geometry": {"coordinates":[2.1487987041,41.3851547241],"type":"Point"}
}