{
  "type": "Feature",
  "properties": {
    "addr:full":"Calle de Samaniego, 4 Laguardia \u00c1lava 01300",
    "addr:housenumber":"4",
    "addr:postcode":"01300",
    "addr:street":"Calle De Samaniego",
    "iso:country":"ES",
    "sg:address":"Calle de Samaniego, 4",
    "sg:city":"Laguardia",
    "sg:orig_category":"Reposter\u00cdas",
    "sg:phone":"+34 945 60 01 88",
    "sg:postcode":"01300",
    "sg:province":"\u00c1lava",
    "wof:name":"Torres Fernandez Jose Luis",
    "wof:placetype":"venue"
},
  "geometry": {"coordinates":[-2.5853629112,42.5538635254],"type":"Point"}
}