{
  "type": "Feature",
  "properties": {
    "addr:full":"Carr Gran, 36 Garriguella Girona 17780",
    "addr:housenumber":"36",
    "addr:postcode":"17780",
    "addr:street":"Carr Gran",
    "iso:country":"ES",
    "sg:address":"Carr Gran, 36",
    "sg:city":"Garriguella",
    "sg:orig_category":"Alimentaci\u00d3n General (al Por Menor)",
    "sg:phone":"+34 972 55 23 30",
    "sg:postcode":"17780",
    "sg:province":"Girona",
    "wof:name":"Acosta Santana Flor",
    "wof:placetype":"venue"
},
  "geometry": {"coordinates":[3.0646841526,42.3442382812],"type":"Point"}
}