{
  "type": "Feature",
  "properties": {
    "addr:full":"Grup Coliseo, 3 Campos Asturias 33404",
    "addr:postcode":"33404",
    "iso:country":"ES",
    "sg:address":"Grup Coliseo, 3",
    "sg:city":"Campos",
    "sg:orig_category":"Suministros Para Hoteles",
    "sg:phone":"+34 985 57 80 50",
    "sg:postcode":"33404",
    "sg:province":"Asturias",
    "wof:name":"Fernandez Fernandez Antonio",
    "wof:placetype":"venue"
},
  "geometry": {"coordinates":[-5.9240369797,43.5455207825],"type":"Point"}
}