{
  "type": "Feature",
  "properties": {
    "addr:full":"Calle de Hermanos Garcia De La Torre, 4 Palmas De Gran Canaria Las Palmas 35005",
    "addr:housenumber":"4",
    "addr:postcode":"35005",
    "addr:street":"Calle De Hermanos Garcia De La Torre",
    "iso:country":"ES",
    "sg:address":"Calle de Hermanos Garcia De La Torre, 4",
    "sg:city":"Palmas De Gran Canaria",
    "sg:orig_category":"Centros De Educaci\u00d3n Especial",
    "sg:phone":"+34 928 23 46 41",
    "sg:postcode":"35005",
    "sg:province":"Las Palmas",
    "wof:name":"Escuela Maternal Infantil Doctor Sanchez S.l.",
    "wof:placetype":"venue"
},
  "geometry": {"coordinates":[-15.4311037064,28.1274852753],"type":"Point"}
}