{
  "type": "Feature",
  "properties": {
    "addr:full":"Ctra Osuna-lantejuela, Km. 0008,0 Osuna Sevilla 41640",
    "addr:postcode":"41640",
    "addr:street":"Ctra Osuna-Lantejuela Km. 0008,0",
    "iso:country":"ES",
    "sg:address":"Ctra Osuna-lantejuela, Km. 0008,0",
    "sg:city":"Osuna",
    "sg:orig_category":"Agricultura: Abastecimiento Y Cosechado (negocio)",
    "sg:phone":"+34 955 95 81 43",
    "sg:postcode":"41640",
    "sg:province":"Sevilla",
    "wof:name":"Mayorazgo Agricola Y Ganadera S.a.",
    "wof:placetype":"venue"
},
  "geometry": {"coordinates":[-5.1028141975,37.2371253967],"type":"Point"}
}