{
  "type": "Feature",
  "properties": {
    "addr:full":"C/ Pont Dels Ortissos, 6 Elche Alicante 03202",
    "addr:housenumber":"6",
    "addr:postcode":"03202",
    "addr:street":"C / Pont Dels Ortissos",
    "iso:country":"ES",
    "sg:address":"C/ Pont Dels Ortissos, 6",
    "sg:city":"Elche",
    "sg:orig_category":"Abogados",
    "sg:phone":"+34 965 45 20 41",
    "sg:postcode":"03202",
    "sg:province":"Alicante",
    "wof:name":"Marcos Gonzalez Juan",
    "wof:placetype":"venue"
},
  "geometry": {"coordinates":[-0.6951839924,38.2662124634],"type":"Point"}
}