{
  "type": "Feature",
  "properties": {
    "addr:full":"Avda Rosaleda, 12 Malaga M\u00e1laga 29008",
    "addr:housenumber":"12",
    "addr:postcode":"29008",
    "addr:street":"Avda Rosaleda;Ma\u0301Laga",
    "iso:country":"ES",
    "sg:address":"Avda Rosaleda, 12",
    "sg:city":"Malaga",
    "sg:orig_category":"Tapicer\u00cdas",
    "sg:phone":"+34 952 21 40 94",
    "sg:postcode":"29008",
    "sg:province":"M\u00e1laga",
    "wof:name":"Nu\u00f1ez Santero Andres",
    "wof:placetype":"venue"
},
  "geometry": {"coordinates":[-4.4253082275,36.7236366272],"type":"Point"}
}