{
  "type": "Feature",
  "properties": {
    "addr:full":"San Federico Echajui, S/n Dos Hermanas Sevilla 41700",
    "addr:postcode":"41700",
    "addr:street":"San;Echajui S / N Dos",
    "iso:country":"ES",
    "sg:address":"San Federico Echajui, S/n",
    "sg:city":"Dos Hermanas",
    "sg:orig_category":"Maquinaria Para Industrias Diversas",
    "sg:phone":"+34 955 95 08 83",
    "sg:postcode":"41700",
    "sg:province":"Sevilla",
    "wof:name":"Matriceria Reyes S.l.",
    "wof:placetype":"venue"
},
  "geometry": {"coordinates":[-5.9281339645,37.2829055786],"type":"Point"}
}