{
  "type": "Feature",
  "properties": {
    "iso:country":"ES",
    "sg:address":"Calle de Copo, 5",
    "sg:city":"San Pedro Alcantara",
    "sg:orig_category":"Caf\u00c9s, Bares, Cervecer\u00cdas",
    "sg:phone":"+34 952 78 30 86",
    "sg:postcode":"29670",
    "sg:province":"M\u00e1laga",
    "wof:name":"Castillo Romero Jose",
    "wof:placetype":"venue"
},
  "geometry": {"coordinates":[-4.9908499718,36.4844245911],"type":"Point"}
}