{
  "type": "Feature",
  "properties": {
    "iso:country":"ES",
    "sg:address":"Av Diputacio, 64",
    "sg:city":"Cambrils",
    "sg:orig_category":"Restaurantes",
    "sg:phone":"+34 977 79 29 24",
    "sg:postcode":"43850",
    "sg:province":"Tarragona",
    "wof:name":"Tem Restaurant C.b.",
    "wof:placetype":"venue"
},
  "geometry": {"coordinates":[1.08890903,41.0663375854],"type":"Point"}
}