{
  "type": "Feature",
  "properties": {
    "iso:country":"ES",
    "sg:address":"Calle de Marques De La Valdavia (del), 117",
    "sg:city":"Alcobendas",
    "sg:orig_category":"Molduras, Junquillos, Listones Y Molduras Perforadas",
    "sg:phone":"+34 916 61 56 89",
    "sg:postcode":"28100",
    "sg:province":"Madrid",
    "wof:name":"Perez Esteban Victor Manuel",
    "wof:placetype":"venue"
},
  "geometry": {"coordinates":[-3.655497551,40.5469169617],"type":"Point"}
}