{
  "type": "Feature",
  "properties": {
    "iso:country":"ES",
    "sg:address":"Calle de Calvo Sotelo, 115",
    "sg:city":"Marin",
    "sg:orig_category":"Librer\u00cdas",
    "sg:phone":"+34 986 89 03 78",
    "sg:postcode":"36900",
    "sg:province":"Pontevedra",
    "wof:name":"Vilar Nu\u00f1ez Maria Virtuosa",
    "wof:placetype":"venue"
},
  "geometry": {"coordinates":[-8.6926240921,42.3948898315],"type":"Point"}
}