{
  "type": "Feature",
  "properties": {
    "addr:full":"Plaz Rollo (del), 18 Avila \u00c1vila 05002",
    "addr:housenumber":"18",
    "addr:postcode":"05002",
    "addr:street":"Plaz Rollo Del;A\u0301Vila",
    "iso:country":"ES",
    "sg:address":"Plaz Rollo (del), 18",
    "sg:city":"Avila",
    "sg:orig_category":"Tintes (fabricaci\u00d3n, Al Por Mayor)",
    "sg:phone":"+34 920 22 79 70",
    "sg:postcode":"05002",
    "sg:province":"\u00c1vila",
    "sg:website":"www.pressto.com",
    "wof:name":"Byr Prestavila S.l.",
    "wof:placetype":"venue"
},
  "geometry": {"coordinates":[-4.6992030144,40.6503982544],"type":"Point"}
}