{
  "type": "Feature",
  "properties": {
    "addr:full":"Calle de Tirso De Molina, 29 Valladolid Valladolid 47010",
    "addr:housenumber":"29",
    "addr:postcode":"47010",
    "addr:street":"Calle De Tirso De Molina",
    "iso:country":"ES",
    "sg:address":"Calle de Tirso De Molina, 29",
    "sg:city":"Valladolid",
    "sg:classifiers":[
        {
            "category":"Personal",
            "subcategory":"Barber",
            "type":"Services"
        }
    ],
    "sg:phone":"+34 983 31 06 20",
    "sg:postcode":"47010",
    "sg:province":"Valladolid",
    "sg:tags":[
        "caballeros",
        "de",
        "peluqueros"
    ],
    "wof:name":"Lucio Sanchez Pedro",
    "wof:placetype":"venue"
},
  "geometry": {"coordinates":[-4.7248277664,41.6605567932],"type":"Point"}
}