{
  "type": "Feature",
  "properties": {
    "iso:country":"ES",
    "sg:address":"Pase Acacias, 1",
    "sg:city":"Madrid",
    "sg:orig_category":"Ropa Y Accesorios",
    "sg:phone":"+34 915 17 26 63",
    "sg:postcode":"28005",
    "sg:province":"Madrid",
    "wof:name":"Alonso Mayoral Ricardo",
    "wof:placetype":"venue"
},
  "geometry": {"coordinates":[-3.7034986019,40.4047660828],"type":"Point"}
}