{
  "type": "Feature",
  "properties": {
    "iso:country":"ES",
    "sg:address":"Calle de San Gines, 13",
    "sg:city":"San Nicolas",
    "sg:orig_category":"Tapicer\u00cdas",
    "sg:phone":"+34 968 83 29 67",
    "sg:postcode":"30009",
    "sg:province":"Murcia",
    "wof:name":"Roman Rubio Maria Dolores",
    "wof:placetype":"venue"
},
  "geometry": {"coordinates":[-1.1615669727,37.997844696],"type":"Point"}
}