{
  "type": "Feature",
  "properties": {
    "iso:country":"ES",
    "sg:address":"Archena, 6",
    "sg:city":"Molina Segura",
    "sg:orig_category":"Materias Pl\u00c1sticas: Art\u00cdculos Para La Industria",
    "sg:phone":"+34 968 29 57 00",
    "sg:postcode":"30500",
    "sg:province":"Murcia",
    "sg:website":"www.nuevaterrain.com",
    "wof:name":"Nueva Terrain S.l.",
    "wof:placetype":"venue"
},
  "geometry": {"coordinates":[-1.2119740248,38.0535736084],"type":"Point"}
}