{
  "type": "Feature",
  "properties": {
    "addr:full":"Carrer de Portalet (del), 8 Tarragona Tarragona 43003",
    "addr:housenumber":"8",
    "addr:postcode":"43003",
    "addr:street":"Carrer De Portalet Del",
    "iso:country":"ES",
    "sg:address":"Carrer de Portalet (del), 8",
    "sg:city":"Tarragona",
    "sg:orig_category":"Infograf\u00cda",
    "sg:phone":"+34 977 21 49 90",
    "sg:postcode":"43003",
    "sg:province":"Tarragona",
    "sg:website":"www.productora3d.com",
    "wof:name":"Pujol Male Miquel",
    "wof:placetype":"venue"
},
  "geometry": {"coordinates":[1.2557309866,41.1162719727],"type":"Point"}
}