{
  "type": "Feature",
  "properties": {
    "addr:full":"Calle de Antonio Chacon, S/n Malaga M\u00e1laga 29003",
    "addr:postcode":"29003",
    "addr:street":"Calle De Antonio Chacon S / N;Ma\u0301Laga",
    "iso:country":"ES",
    "sg:address":"Calle de Antonio Chacon, S/n",
    "sg:city":"Malaga",
    "sg:orig_category":"Caf\u00c9s, Bares, Cervecer\u00cdas",
    "sg:phone":"+34 952 33 51 18",
    "sg:postcode":"29003",
    "sg:province":"M\u00e1laga",
    "wof:name":"Castillo Rodriguez Francisco",
    "wof:placetype":"venue"
},
  "geometry": {"coordinates":[-4.4485015869,36.6988983154],"type":"Point"}
}