{
  "type": "Feature",
  "properties": {
    "iso:country":"ES",
    "sg:address":"Juan Hormaechea, S/n",
    "sg:city":"Isla",
    "sg:orig_category":"Organismos De Turismo",
    "sg:phone":"+34 942 67 97 20",
    "sg:postcode":"39195",
    "sg:province":"Cantabria",
    "sg:website":"www.islacantabrica.com",
    "wof:name":"Centro De Iniciativas Turisticas",
    "wof:placetype":"venue"
},
  "geometry": {"coordinates":[-3.5499229431,43.4939041138],"type":"Point"}
}