{
  "type": "Feature",
  "properties": {
    "iso:country":"ES",
    "sg:address":"Av Generalitat De Catalunya, 25",
    "sg:city":"Papiol",
    "sg:orig_category":"Medias Y Calcetines (al Por Menor)",
    "sg:phone":"+34 936 73 15 73",
    "sg:postcode":"08754",
    "sg:province":"Barcelona",
    "wof:name":"Treinoxfer S.l.",
    "wof:placetype":"venue"
},
  "geometry": {"coordinates":[2.0103919506,41.4366378784],"type":"Point"}
}