{
  "type": "Feature",
  "properties": {
    "addr:full":"Calle de Daniel Moyano, 25 Corredoria Asturias 33011",
    "addr:housenumber":"25",
    "addr:postcode":"33011",
    "addr:street":"Calle De Daniel Moyano;Asturias",
    "iso:country":"ES",
    "sg:address":"Calle de Daniel Moyano, 25",
    "sg:city":"Corredoria",
    "sg:orig_category":"Peluquer\u00cdas, Peluquer\u00cda Mixta",
    "sg:phone":"+34 985 28 94 77",
    "sg:postcode":"33011",
    "sg:province":"Asturias",
    "wof:name":"Blanco Fernandez Ana Maria",
    "wof:placetype":"venue"
},
  "geometry": {"coordinates":[-5.8230648041,43.3839912415],"type":"Point"}
}