{
  "type": "Feature",
  "properties": {
    "iso:country":"ES",
    "sg:address":"Avda Castilla (de), 1",
    "sg:city":"Poligono De San Fernando De Henares",
    "sg:orig_category":"Seguridad En El Trabajo Y Prevenci\u00d3n De Riesgos Laborales",
    "sg:phone":"+34 916 78 13 93",
    "sg:postcode":"28830",
    "sg:province":"Madrid",
    "sg:website":"www.bacou-dalloz.com",
    "wof:name":"Bacou S.a.",
    "wof:placetype":"venue"
},
  "geometry": {"coordinates":[-3.5366938114,40.4255332947],"type":"Point"}
}