{
  "type": "Feature",
  "properties": {
    "addr:full":"Avgd Mexic, 4 Platja D'alcudia Islas Baleares 07408",
    "addr:housenumber":"4",
    "addr:postcode":"07408",
    "addr:street":"Mexic;D'Alcudia",
    "iso:country":"ES",
    "sg:address":"Avgd Mexic, 4",
    "sg:city":"Platja D'alcudia",
    "sg:orig_category":"Art\u00cdculos De Regalo (al Por Menor)",
    "sg:phone":"+34 971 89 19 79",
    "sg:postcode":"07408",
    "sg:province":"Islas Baleares",
    "wof:name":"Isabel Crespi Socias Y Otros Cdad.",
    "wof:placetype":"venue"
},
  "geometry": {"coordinates":[3.1255340576,39.8456192017],"type":"Point"}
}