{
  "type": "Feature",
  "properties": {
    "iso:country":"ES",
    "sg:address":"Carrer de Poeta Josep Punsola, 13",
    "sg:city":"Mataro",
    "sg:orig_category":"Reposter\u00cdas",
    "sg:phone":"+34 937 96 49 01",
    "sg:postcode":"08304",
    "sg:province":"Barcelona",
    "wof:name":"Garcia Villa Maria Pastora",
    "wof:placetype":"venue"
},
  "geometry": {"coordinates":[2.4507770538,41.5478057861],"type":"Point"}
}