{
  "type": "Feature",
  "properties": {
    "addr:full":"Calle de Viento-bardena, 11 Bardena Del Caudillo Zaragoza 50694",
    "addr:housenumber":"11",
    "addr:postcode":"50694",
    "addr:street":"Calle De Viento-Bardena",
    "iso:country":"ES",
    "sg:address":"Calle de Viento-bardena, 11",
    "sg:city":"Bardena Del Caudillo",
    "sg:orig_category":"Asociaciones Y Clubs Deportivos",
    "sg:phone":"+34 976 66 81 06",
    "sg:postcode":"50694",
    "sg:province":"Zaragoza",
    "wof:name":"Rodriguez Fernandez Antonio",
    "wof:placetype":"venue"
},
  "geometry": {"coordinates":[-1.3349239826,42.1956138611],"type":"Point"}
}