{
  "type": "Feature",
  "properties": {
    "addr:full":"Calle de Ramon Y Cajal, 35 Alcantarilla Murcia 30820",
    "addr:housenumber":"35",
    "addr:postcode":"30820",
    "addr:street":"Calle De Ramon Y Cajal",
    "iso:country":"ES",
    "sg:address":"Calle de Ramon Y Cajal, 35",
    "sg:city":"Alcantarilla",
    "sg:orig_category":"Caf\u00c9s, Bares, Cervecer\u00cdas",
    "sg:phone":"+34 968 89 43 65",
    "sg:postcode":"30820",
    "sg:province":"Murcia",
    "wof:name":"Alfonso Moya Molina S.l.",
    "wof:placetype":"venue"
},
  "geometry": {"coordinates":[-1.2115161419,37.9733085632],"type":"Point"}
}