{
  "type": "Feature",
  "properties": {
    "iso:country":"ES",
    "sg:address":"Calle de Varela Silvari, 39",
    "sg:city":"Coru\u00d1a",
    "sg:classifiers":[
        {
            "category":"Personal",
            "subcategory":"Barber",
            "type":"Services"
        }
    ],
    "sg:phone":"+34 981 20 56 46",
    "sg:postcode":"15001",
    "sg:province":"A Coru\u00f1a",
    "sg:tags":[
        "caballeros",
        "de",
        "peluqueros"
    ],
    "wof:name":"Vales Mendez Salvador",
    "wof:placetype":"venue"
},
  "geometry": {"coordinates":[-8.3195390701,43.1524581909],"type":"Point"}
}