{
  "type": "Feature",
  "properties": {
    "addr:full":"Calle de Sol El, 1 Nore\u00f1a Asturias 33180",
    "addr:housenumber":"1",
    "addr:postcode":"33180",
    "addr:street":"Calle De Sol El;Asturias",
    "iso:country":"ES",
    "sg:address":"Calle de Sol El, 1",
    "sg:city":"Nore\u00f1a",
    "sg:orig_category":"Asfaltadores",
    "sg:phone":"+34 985 74 36 85",
    "sg:postcode":"33180",
    "sg:province":"Asturias",
    "wof:name":"Asfalsiero S.l.",
    "wof:placetype":"venue"
},
  "geometry": {"coordinates":[-5.7073640823,43.3991699219],"type":"Point"}
}