{
  "type": "Feature",
  "properties": {
    "addr:full":"Calle de Arrasate, 1 Donostia-san Sebastian Guip\u00f9zcoa 20005",
    "addr:housenumber":"1",
    "addr:postcode":"20005",
    "addr:street":"Calle De Arrasate",
    "iso:country":"ES",
    "sg:address":"Calle de Arrasate, 1",
    "sg:city":"Donostia-san Sebastian",
    "sg:orig_category":"Abogados",
    "sg:phone":"+34 943 42 55 74",
    "sg:postcode":"20005",
    "sg:province":"Guip\u00f9zcoa",
    "wof:name":"Gonzalez Finat Carlos",
    "wof:placetype":"venue"
},
  "geometry": {"coordinates":[-1.9794137478,43.3189926147],"type":"Point"}
}