{
  "type": "Feature",
  "properties": {
    "addr:full":"Carrer de Barcelona, 4 Casc Antic Barcelona 08150",
    "addr:housenumber":"4",
    "addr:postcode":"08150",
    "addr:street":"Carrer De Barcelona",
    "iso:country":"ES",
    "sg:address":"Carrer de Barcelona, 4",
    "sg:city":"Casc Antic",
    "sg:orig_category":"Estancos",
    "sg:phone":"+34 935 62 14 18",
    "sg:postcode":"08150",
    "sg:province":"Barcelona",
    "wof:name":"Gorina Esteve Maria",
    "wof:placetype":"venue"
},
  "geometry": {"coordinates":[2.2293000221,41.5678787231],"type":"Point"}
}