{
  "type": "Feature",
  "properties": {
    "iso:country":"ES",
    "sg:address":"Plaz Doctor Fleming, 8",
    "sg:city":"Chiva",
    "sg:orig_category":"Procuradores",
    "sg:phone":"+34 962 52 00 59",
    "sg:postcode":"46370",
    "sg:province":"Valencia",
    "wof:name":"Alcaiz Garcia Enrique",
    "wof:placetype":"venue"
},
  "geometry": {"coordinates":[-0.7173628211,39.4734115601],"type":"Point"}
}