{
  "type": "Feature",
  "properties": {
    "addr:full":"Calle de Era Del Moro, 1 Le\u00f3n Le\u00f3n 24002",
    "addr:housenumber":"1",
    "addr:postcode":"24002",
    "addr:street":"Calle De Era Del Moro;Leo\u0301N",
    "iso:country":"ES",
    "sg:address":"Calle de Era Del Moro, 1",
    "sg:city":"Le\u00f3n",
    "sg:orig_category":"Inform\u00c1tica, Ofim\u00c1tica (estudios, Asesor\u00cda, Ingenier\u00cda, Formaci\u00d3n)",
    "sg:phone":"+34 987 22 44 14",
    "sg:postcode":"24002",
    "sg:province":"Le\u00f3n",
    "wof:name":"Abide-software, S.l.",
    "wof:placetype":"venue"
},
  "geometry": {"coordinates":[-5.571098,42.602589],"type":"Point"}
}