{
  "type": "Feature",
  "properties": {
    "iso:country":"ES",
    "sg:address":"Calle de Cueva De La Mora, 7",
    "sg:city":"Villaviciosa Odon",
    "sg:orig_category":"Art\u00cdculos De Regalo (al Por Menor)",
    "sg:phone":"+34 916 16 47 64",
    "sg:postcode":"28670",
    "sg:province":"Madrid",
    "wof:name":"Repaser Trebol S.l.",
    "wof:placetype":"venue"
},
  "geometry": {"coordinates":[-3.9075036049,40.3571128845],"type":"Point"}
}