{
  "type": "Feature",
  "properties": {
    "iso:country":"ES",
    "sg:address":"Calle de Leon Xiii, 8",
    "sg:city":"Zaragoza",
    "sg:orig_category":"Florister\u00cdas",
    "sg:phone":"+34 976 21 09 27",
    "sg:postcode":"50008",
    "sg:province":"Zaragoza",
    "wof:name":"Nacho Bergara S.l.",
    "wof:placetype":"venue"
},
  "geometry": {"coordinates":[-0.8812230229,41.6465530396],"type":"Point"}
}