{
  "type": "Feature",
  "properties": {
    "iso:country":"ES",
    "sg:address":"Calle de Doce De Octubre, 4",
    "sg:city":"Le\u00f3n",
    "sg:orig_category":"Chapister\u00cda",
    "sg:phone":"+34 987 23 22 80",
    "sg:postcode":"24010",
    "sg:province":"Le\u00f3n",
    "wof:name":"Oblanca Casado Julio",
    "wof:placetype":"venue"
},
  "geometry": {"coordinates":[-5.5892233849,42.6054229736],"type":"Point"}
}