{
  "type": "Feature",
  "properties": {
    "addr:full":"Pase Ba\u00d1os (los), S/n Roquetas Mar Almer\u00eda 04740",
    "addr:postcode":"04740",
    "addr:street":"Los S / N Roquetas Mar Almeri\u0301A",
    "iso:country":"ES",
    "sg:address":"Pase Ba\u00d1os (los), S/n",
    "sg:city":"Roquetas Mar",
    "sg:orig_category":"Comercio, Reparaci\u00d3n De Motocicletas, Bicicletas Y Piezas Sueltas",
    "sg:phone":"+34 950 32 25 29",
    "sg:postcode":"04740",
    "sg:province":"Almer\u00eda",
    "wof:name":"Vivancos Mendez Juan",
    "wof:placetype":"venue"
},
  "geometry": {"coordinates":[-2.4679217339,36.8401641846],"type":"Point"}
}