{
  "type": "Feature",
  "properties": {
    "addr:full":"Calle de Ramon Benito Ace\u00d1a, 8 Garray Soria 42162",
    "addr:housenumber":"8",
    "addr:postcode":"42162",
    "addr:street":"Calle De Ramon Benito Acen\u0303A",
    "iso:country":"ES",
    "sg:address":"Calle de Ramon Benito Ace\u00d1a, 8",
    "sg:city":"Garray",
    "sg:orig_category":"Farmacias",
    "sg:phone":"+34 975 25 21 14",
    "sg:postcode":"42162",
    "sg:province":"Soria",
    "wof:name":"Gonzalez Gesteiro Inmaculada",
    "wof:placetype":"venue"
},
  "geometry": {"coordinates":[-2.4466300011,41.8146858215],"type":"Point"}
}