{
  "type": "Feature",
  "properties": {
    "addr:full":"Calle de Plaza, 1 Torre De Santa Maria C\u00e1ceres 10186",
    "addr:housenumber":"1",
    "addr:postcode":"10186",
    "addr:street":"Calle De Plaza",
    "iso:country":"ES",
    "sg:address":"Calle de Plaza, 1",
    "sg:city":"Torre De Santa Maria",
    "sg:orig_category":"Administraciones Regionales, Departamentales Y Locales",
    "sg:phone":"+34 927 38 81 27",
    "sg:postcode":"10186",
    "sg:province":"C\u00e1ceres",
    "wof:name":"Ayuntamiento De Torre De Santa Maria",
    "wof:placetype":"venue"
},
  "geometry": {"coordinates":[-6.3720030785,39.4745063782],"type":"Point"}
}