{
  "type": "Feature",
  "properties": {
    "addr:full":"Calle de Barrenkalea, 28 Durango Vizcaya 48200",
    "addr:housenumber":"28",
    "addr:postcode":"48200",
    "addr:street":"Calle De Barrenkalea",
    "iso:country":"ES",
    "sg:address":"Calle de Barrenkalea, 28",
    "sg:city":"Durango",
    "sg:orig_category":"Sindicatos De Trabajadores",
    "sg:phone":"+34 946 81 85 09",
    "sg:postcode":"48200",
    "sg:province":"Vizcaya",
    "wof:name":"Langile Abertzaleen Batzordeak",
    "wof:placetype":"venue"
},
  "geometry": {"coordinates":[-2.6322929859,43.1669158936],"type":"Point"}
}