{
  "type": "Feature",
  "properties": {
    "iso:country":"ES",
    "sg:address":"Calle de Milan, 7",
    "sg:city":"Alcala Henares",
    "sg:orig_category":"Revestimiento De Suelos Industriales",
    "sg:phone":"+34 918 88 67 12",
    "sg:postcode":"28805",
    "sg:province":"Madrid",
    "wof:name":"Horpavin S. A.",
    "wof:placetype":"venue"
},
  "geometry": {"coordinates":[-3.3376789093,40.4971618652],"type":"Point"}
}