{
  "type": "Feature",
  "properties": {
    "addr:full":"C/ Josep Tarradellas, 18 Banyoles Girona 17820",
    "addr:housenumber":"18",
    "addr:postcode":"17820",
    "addr:street":"C / Josep Tarradellas",
    "iso:country":"ES",
    "sg:address":"C/ Josep Tarradellas, 18",
    "sg:city":"Banyoles",
    "sg:orig_category":"Ingenier\u00cda, Centros De Estudios (diversos)",
    "sg:phone":"+34 972 58 32 78",
    "sg:postcode":"17820",
    "sg:province":"Girona",
    "wof:name":"Pitecno Sl",
    "wof:placetype":"venue"
},
  "geometry": {"coordinates":[2.7621939182,42.1246414185],"type":"Point"}
}