{
  "type": "Feature",
  "properties": {
    "addr:full":"Camino De Las Canteras, 19 Jamilena Ja\u00e9n 23658",
    "addr:housenumber":"19",
    "addr:postcode":"23658",
    "addr:street":"Camino De Las Canteras",
    "iso:country":"ES",
    "sg:address":"Camino De Las Canteras, 19",
    "sg:city":"Jamilena",
    "sg:orig_category":"Centros Empresariales",
    "sg:phone":"+34 953 56 64 03",
    "sg:postcode":"23658",
    "sg:province":"Ja\u00e9n",
    "wof:name":"Cazalla Cazalla Jose Manuel Jesus C.b.",
    "wof:placetype":"venue"
},
  "geometry": {"coordinates":[-3.9169139862,37.749080658],"type":"Point"}
}