{
  "type": "Feature",
  "properties": {
    "addr:full":"Av Marina Baixa, 68 Cala Alicante 03509",
    "addr:housenumber":"68",
    "addr:postcode":"03509",
    "addr:street":"Av Marina Baixa",
    "iso:country":"ES",
    "sg:address":"Av Marina Baixa, 68",
    "sg:city":"Cala",
    "sg:orig_category":"Servicios De Telecomunicaciones",
    "sg:phone":"+34 966 83 05 37",
    "sg:postcode":"03509",
    "sg:province":"Alicante",
    "wof:name":"Moya Moya Dolores",
    "wof:placetype":"venue"
},
  "geometry": {"coordinates":[-0.2106740028,38.5691642761],"type":"Point"}
}