{
  "type": "Feature",
  "properties": {
    "iso:country":"ES",
    "sg:address":"Estacio Ferrocarril, S/n",
    "sg:city":"Tarragona",
    "sg:orig_category":"Sindicatos De Trabajadores",
    "sg:phone":"+34 977 24 51 97",
    "sg:postcode":"43004",
    "sg:province":"Tarragona",
    "wof:name":"Union General De Trabajadores Federacion De Transportes Comunicaciones Y Mar",
    "wof:placetype":"venue"
},
  "geometry": {"coordinates":[1.2541049719,41.1169281006],"type":"Point"}
}