{
  "type": "Feature",
  "properties": {
    "iso:country":"ES",
    "sg:address":"Huelva Portugal, Km. 0133,5",
    "sg:city":"Ayamonte",
    "sg:orig_category":"Arenas, Guijarros Y Granulados",
    "sg:phone":"+34 959 50 21 83",
    "sg:postcode":"21400",
    "sg:province":"Huelva",
    "wof:name":"Aridos Normalizados De Riego S.a.",
    "wof:placetype":"venue"
},
  "geometry": {"coordinates":[-7.4081339836,37.2138366699],"type":"Point"}
}