{
  "type": "Feature",
  "properties": {
    "addr:full":"Calle de Pedro Hidalgo, S/n Quesada Ja\u00e9n 23480",
    "addr:postcode":"23480",
    "addr:street":"Calle De Pedro Hidalgo S / N;Jae\u0301N",
    "iso:country":"ES",
    "sg:address":"Calle de Pedro Hidalgo, S/n",
    "sg:city":"Quesada",
    "sg:orig_category":"Molduras, Junquillos, Listones Y Molduras Perforadas",
    "sg:phone":"+34 953 73 40 57",
    "sg:postcode":"23480",
    "sg:province":"Ja\u00e9n",
    "wof:name":"Eurotel Sur S.l.",
    "wof:placetype":"venue"
},
  "geometry": {"coordinates":[-3.0670909882,37.8421630859],"type":"Point"}
}