{
  "type": "Feature",
  "properties": {
    "addr:full":"Avda Buenos Aires-estacion De Guadix, 40 Estacion De Guadix Granada 18500",
    "addr:housenumber":"40",
    "addr:postcode":"18500",
    "addr:street":"Avda Buenos Aires-Estacion;Estacion De;Granada",
    "iso:country":"ES",
    "sg:address":"Avda Buenos Aires-estacion De Guadix, 40",
    "sg:city":"Estacion De Guadix",
    "sg:orig_category":"Cl\u00cdnicas M\u00c9dicas",
    "sg:phone":"+34 958 66 63 80",
    "sg:postcode":"18500",
    "sg:province":"Granada",
    "wof:name":"Centro Clinico Pastor Slu",
    "wof:placetype":"venue"
},
  "geometry": {"coordinates":[-3.1343688965,37.303894043],"type":"Point"}
}