{
  "type": "Feature",
  "properties": {
    "addr:full":"Pase Santa Maria De La Cabeza, 52 Madrid Madrid 28045",
    "addr:housenumber":"52",
    "addr:postcode":"madrid;28045",
    "addr:street":"Cabeza",
    "iso:country":"ES",
    "sg:address":"Pase Santa Maria De La Cabeza, 52",
    "sg:city":"Madrid",
    "sg:orig_category":"Enfermeras: Consultas, Atenci\u00d3n A Domicilio",
    "sg:phone":"+34 915 30 36 24",
    "sg:postcode":"28045",
    "sg:province":"Madrid",
    "wof:name":"Perez Leal Jesus",
    "wof:placetype":"venue"
},
  "geometry": {"coordinates":[-3.6983909607,40.402130127],"type":"Point"}
}