{
  "type": "Feature",
  "properties": {
    "iso:country":"ES",
    "sg:address":"Ctra Tembleque, S/n",
    "sg:city":"Villaca\u00f1as",
    "sg:orig_category":"Empresas De Carpinter\u00cda De Madera",
    "sg:phone":"+34 925 20 07 48",
    "sg:postcode":"45860",
    "sg:province":"Toledo",
    "wof:name":"Saelices Perez Agustin",
    "wof:placetype":"venue"
},
  "geometry": {"coordinates":[-3.3508689404,39.6168746948],"type":"Point"}
}