{
  "type": "Feature",
  "properties": {
    "addr:full":"Carrer de Marques De Mulhacen, 3 Barcelona Barcelona 08034",
    "addr:housenumber":"3",
    "addr:postcode":"08034",
    "addr:street":"Carrer De Marques De Mulhacen",
    "iso:country":"ES",
    "sg:address":"Carrer de Marques De Mulhacen, 3",
    "sg:city":"Barcelona",
    "sg:orig_category":"Electromedicina: Equipo",
    "sg:phone":"+34 932 04 03 12",
    "sg:postcode":"08034",
    "sg:province":"Barcelona",
    "sg:website":"www.begil.com",
    "wof:name":"Begil S.a.",
    "wof:placetype":"venue"
},
  "geometry": {"coordinates":[2.1206159592,41.3903617859],"type":"Point"}
}