{
  "type": "Feature",
  "properties": {
    "iso:country":"ES",
    "sg:address":"Ctra Dehesas (las), 1",
    "sg:city":"Dehesas",
    "sg:orig_category":"Quincaller\u00cda (al Por Menor)",
    "sg:phone":"+34 922 38 45 13",
    "sg:postcode":"38400",
    "sg:province":"Santa Cruz De Tenerife",
    "wof:name":"Reyes Diaz S.a.",
    "wof:placetype":"venue"
},
  "geometry": {"coordinates":[-16.5473842621,28.4141807556],"type":"Point"}
}