{
  "type": "Feature",
  "properties": {
    "iso:country":"ES",
    "sg:address":"Calle de Arturo Soria, 320",
    "sg:city":"Madrid",
    "sg:orig_category":"Bisuteros (fabricaci\u00d3n, Al Por Mayor)",
    "sg:phone":"+34 917 66 09 33",
    "sg:postcode":"28033",
    "sg:province":"Madrid",
    "sg:website":"www.lacaseta.es",
    "wof:name":"Petshop La Caseta S.l.",
    "wof:placetype":"venue"
},
  "geometry": {"coordinates":[-3.6680297852,40.4781990051],"type":"Point"}
}