{
  "type": "Feature",
  "properties": {
    "iso:country":"ES",
    "sg:address":"Calle de Jose Maria Pe\u00d1aranda, S/n",
    "sg:city":"Monzon",
    "sg:orig_category":"Mec\u00c1nico Del Autom\u00d3vil",
    "sg:phone":"+34 974 40 20 12",
    "sg:postcode":"22400",
    "sg:province":"Huesca",
    "wof:name":"Murillo Abril Ramon",
    "wof:placetype":"venue"
},
  "geometry": {"coordinates":[0.1915819943,41.9130134583],"type":"Point"}
}