{
  "type": "Feature",
  "properties": {
    "addr:full":"Carrer de Viladomat, 243 Barcelona Barcelona 08029",
    "addr:housenumber":"243",
    "addr:postcode":"08029",
    "addr:street":"Carrer De Viladomat",
    "iso:country":"ES",
    "sg:address":"Carrer de Viladomat, 243",
    "sg:city":"Barcelona",
    "sg:orig_category":"Empresas De Pintura Y Revestimientos",
    "sg:phone":"+34 934 39 66 76",
    "sg:postcode":"08029",
    "sg:province":"Barcelona",
    "wof:name":"Gotor Pallares Jose",
    "wof:placetype":"venue"
},
  "geometry": {"coordinates":[2.1486101151,41.3860435486],"type":"Point"}
}