{
  "type": "Feature",
  "properties": {
    "addr:full":"Ctra Valladolid, Km. 0002,3 Poligono Industrial Los Villares Salamanca 37184",
    "addr:postcode":"37184",
    "addr:street":"Ctra Valladolid Km. 0002,3 Poligono Industrial",
    "iso:country":"ES",
    "sg:address":"Ctra Valladolid, Km. 0002,3",
    "sg:city":"Poligono Industrial Los Villares",
    "sg:orig_category":"Fabrica De Cer\u00c1micas",
    "sg:phone":"+34 923 24 38 11",
    "sg:postcode":"37184",
    "sg:province":"Salamanca",
    "sg:website":"www.porcelanosa.com",
    "wof:name":"Leoncer S.a.",
    "wof:placetype":"venue"
},
  "geometry": {"coordinates":[-5.6469841003,41.0071716309],"type":"Point"}
}