{
  "type": "Feature",
  "properties": {
    "iso:country":"ES",
    "sg:address":"Mercat Majoristes, S/n",
    "sg:city":"Canonja",
    "sg:orig_category":"Frutas Y Legumbres Frescas (al Por Mayor)",
    "sg:phone":"+34 977 55 30 71",
    "sg:postcode":"43110",
    "sg:province":"Tarragona",
    "wof:name":"Butille Ferre Domenech Esteve",
    "wof:placetype":"venue"
},
  "geometry": {"coordinates":[1.1817840338,41.1208381653],"type":"Point"}
}