{
  "type": "Feature",
  "properties": {
    "addr:full":"Carrer de Amilcar, 163 Barcelona Barcelona 08032",
    "addr:housenumber":"163",
    "addr:postcode":"08032",
    "addr:street":"Carrer De Amilcar",
    "iso:country":"ES",
    "sg:address":"Carrer de Amilcar, 163",
    "sg:city":"Barcelona",
    "sg:orig_category":"Comercio, Reparaci\u00d3n De Motocicletas, Bicicletas Y Piezas Sueltas",
    "sg:phone":"+34 934 56 03 82",
    "sg:postcode":"08032",
    "sg:province":"Barcelona",
    "wof:name":"Fernandez Martinez Fernando",
    "wof:placetype":"venue"
},
  "geometry": {"coordinates":[2.1727879047,41.4238700867],"type":"Point"}
}