{
  "type": "Feature",
  "properties": {
    "addr:full":"Carr Cervantes, 20 Cullera Valencia 46400",
    "addr:housenumber":"20",
    "addr:postcode":"46400",
    "addr:street":"Carr Cervantes",
    "iso:country":"ES",
    "sg:address":"Carr Cervantes, 20",
    "sg:city":"Cullera",
    "sg:orig_category":"Internados & Ense\u00d1anza Privada",
    "sg:phone":"+34 961 72 02 31",
    "sg:postcode":"46400",
    "sg:province":"Valencia",
    "wof:name":"Compa\u00d1ia Hijas De La Caridad De S Vicente De Paul Prov De Sevilla Cdad Casa S Vicente De Paul Sevill",
    "wof:placetype":"venue"
},
  "geometry": {"coordinates":[-0.2574880123,39.1655044556],"type":"Point"}
}