{
  "type": "Feature",
  "properties": {
    "addr:full":"Pla\u00c7 Sant Esteve, 13 Caldes Malavella Girona 17455",
    "addr:housenumber":"13",
    "addr:postcode":"17455",
    "iso:country":"ES",
    "sg:address":"Pla\u00c7 Sant Esteve, 13",
    "sg:city":"Caldes Malavella",
    "sg:classifiers":[
        {
            "category":"Personal",
            "subcategory":"Barber",
            "type":"Services"
        }
    ],
    "sg:phone":"+34 972 47 01 33",
    "sg:postcode":"17455",
    "sg:province":"Girona",
    "sg:tags":[
        "caballeros",
        "de",
        "peluqueros"
    ],
    "wof:name":"Llinas Camos Engracia",
    "wof:placetype":"venue"
},
  "geometry": {"coordinates":[2.8018240929,41.8385505676],"type":"Point"}
}