{
  "type": "Feature",
  "properties": {
    "addr:full":"Carrer de Bilbao, 33 Barcelona Barcelona 08005",
    "addr:housenumber":"33",
    "addr:postcode":"08005",
    "addr:street":"Carrer De Bilbao",
    "iso:country":"ES",
    "sg:address":"Carrer de Bilbao, 33",
    "sg:city":"Barcelona",
    "sg:orig_category":"Empresas De Limpieza",
    "sg:phone":"+34 933 20 81 85",
    "sg:postcode":"08005",
    "sg:province":"Barcelona",
    "sg:website":"www.limptres.com",
    "wof:name":"Limp Tres S.l.",
    "wof:placetype":"venue"
},
  "geometry": {"coordinates":[2.2034699917,41.4029312134],"type":"Point"}
}