{
  "type": "Feature",
  "properties": {
    "iso:country":"ES",
    "sg:address":"Calle de Rio Chico, 8",
    "sg:city":"Guardo",
    "sg:orig_category":"Agentes Generales De Seguros",
    "sg:phone":"+34 979 85 33 86",
    "sg:postcode":"34880",
    "sg:province":"Palencia",
    "sg:website":"www.paginasamarillas.es",
    "wof:name":"Prieto Granda Jose Fernando",
    "wof:placetype":"venue"
},
  "geometry": {"coordinates":[-4.846036911,42.7897987366],"type":"Point"}
}