{
  "type": "Feature",
  "properties": {
    "addr:full":"Carrer de Catalunya, 2 Vimbodi Tarragona 43430",
    "addr:housenumber":"2",
    "addr:postcode":"43430",
    "addr:street":"Carrer De Catalunya",
    "iso:country":"ES",
    "sg:address":"Carrer de Catalunya, 2",
    "sg:city":"Vimbodi",
    "sg:orig_category":"Producci\u00d3n, Venta De Productos De Agricultura Biol\u00d3gica",
    "sg:phone":"+34 977 87 82 92",
    "sg:postcode":"43430",
    "sg:province":"Tarragona",
    "wof:name":"Puig Tora Jose",
    "wof:placetype":"venue"
},
  "geometry": {"coordinates":[1.053599,41.400478363],"type":"Point"}
}