{
  "type": "Feature",
  "properties": {
    "addr:full":"Calle de General Iba\u00d1ez De Ibero, 2 Madrid Madrid 28003",
    "addr:housenumber":"2",
    "addr:postcode":"28003",
    "addr:street":"Calle De General Iban\u0303Ez De Ibero",
    "iso:country":"ES",
    "sg:address":"Calle de General Iba\u00d1ez De Ibero, 2",
    "sg:city":"Madrid",
    "sg:orig_category":"Centros De Coordinaci\u00d3n",
    "sg:phone":"+34 915 54 40 79",
    "sg:postcode":"28003",
    "sg:province":"Madrid",
    "wof:name":"Gestoria De La Madrid S.l",
    "wof:placetype":"venue"
},
  "geometry": {"coordinates":[-3.7106599808,40.445640564],"type":"Point"}
}