{
  "type": "Feature",
  "properties": {
    "iso:country":"ES",
    "sg:address":"Calle de Madrid, 66",
    "sg:city":"Getafe",
    "sg:orig_category":"Fabricaci\u00d3n, Importaci\u00d3n, Venta De Material De Telefon\u00cda, Peritelefon\u00cda",
    "sg:phone":"+34 916 84 30 41",
    "sg:postcode":"28902",
    "sg:province":"Madrid",
    "wof:name":"Phone Warehouse S.l.",
    "wof:placetype":"venue"
},
  "geometry": {"coordinates":[-3.7289152145,40.3091773987],"type":"Point"}
}