{
  "type": "Feature",
  "properties": {
    "iso:country":"ES",
    "sg:address":"Calle de Fernandez Ruano, 17",
    "sg:city":"Cordoba",
    "sg:orig_category":"Carnicer\u00cdas, Carnicer\u00cdas",
    "sg:phone":"+34 957 29 45 70",
    "sg:postcode":"14003",
    "sg:province":"C\u00f3rdoba",
    "wof:name":"Gomez Peralbo Juan Jose",
    "wof:placetype":"venue"
},
  "geometry": {"coordinates":[-4.7834653854,37.8809700012],"type":"Point"}
}