{
  "type": "Feature",
  "properties": {
    "iso:country":"ES",
    "sg:address":"Carr Silvestre Ivars, 5",
    "sg:city":"Benissa",
    "sg:orig_category":"Cristaler\u00cdas",
    "sg:phone":"+34 965 73 18 31",
    "sg:postcode":"03720",
    "sg:province":"Alicante",
    "wof:name":"Ivars Crespo S.l",
    "wof:placetype":"venue"
},
  "geometry": {"coordinates":[0.0574159995,38.7166442871],"type":"Point"}
}