{
  "type": "Feature",
  "properties": {
    "addr:full":"Villamayor, S/n Ordes La Coru\u00f1a 15680",
    "addr:housenumber":"s / n",
    "addr:postcode":"15680",
    "addr:street":"Villamayor;La Corun\u0303A",
    "iso:country":"ES",
    "sg:address":"Villamayor, S/n",
    "sg:city":"Ordes",
    "sg:orig_category":"Confecci\u00d3n De Trajes Para Se\u00d1oras",
    "sg:phone":"+34 981 19 94 35",
    "sg:postcode":"15680",
    "sg:province":"La Coru\u00f1a",
    "wof:name":"Nasemen S. L.",
    "wof:placetype":"venue"
},
  "geometry": {"coordinates":[-8.4072790146,43.0771408081],"type":"Point"}
}