{
  "type": "Feature",
  "properties": {
    "addr:full":"Calle de Mercadillo, 9 Purullena Granada 18519",
    "addr:housenumber":"9",
    "addr:postcode":"18519",
    "addr:street":"Calle De Mercadillo",
    "iso:country":"ES",
    "sg:address":"Calle de Mercadillo, 9",
    "sg:city":"Purullena",
    "sg:orig_category":"Tapicer\u00cdas",
    "sg:phone":"+34 958 69 03 02",
    "sg:postcode":"18519",
    "sg:province":"Granada",
    "wof:name":"Soriano Rosillo Jose",
    "wof:placetype":"venue"
},
  "geometry": {"coordinates":[-3.1839678288,37.3177566528],"type":"Point"}
}