{
  "type": "Feature",
  "properties": {
    "iso:country":"ES",
    "sg:address":"Avda Paz (de La), 3",
    "sg:city":"Villaca\u00f1as",
    "sg:orig_category":"Alquiler De V\u00cddeo",
    "sg:phone":"+34 925 20 15 84",
    "sg:postcode":"45860",
    "sg:province":"Toledo",
    "wof:name":"Zamorano Avila Julia",
    "wof:placetype":"venue"
},
  "geometry": {"coordinates":[-3.3347351551,39.6195602417],"type":"Point"}
}