{
  "type": "Feature",
  "properties": {
    "iso:country":"ES",
    "sg:address":"Premin De Iru\u00f1a, 2",
    "sg:city":"Iru\u00f1a",
    "sg:orig_category":"Sociedades, Compa\u00d1\u00cdas Aseguradoras",
    "sg:phone":"+34 948 18 44 75",
    "sg:postcode":"31008",
    "sg:province":"Navarra",
    "wof:name":"Mittel Salvo S.l.",
    "wof:placetype":"venue"
},
  "geometry": {"coordinates":[-1.6706000566,42.8082466125],"type":"Point"}
}