{
  "type": "Feature",
  "properties": {
    "addr:full":"La Inquisicion, 2 Cervera Pisuerga Palencia 34840",
    "addr:housenumber":"2",
    "addr:postcode":"34840",
    "iso:country":"ES",
    "sg:address":"La Inquisicion, 2",
    "sg:city":"Cervera Pisuerga",
    "sg:orig_category":"Asesor\u00cda Fiscal Y Jur\u00cddica",
    "sg:phone":"+34 979 87 04 06",
    "sg:postcode":"34840",
    "sg:province":"Palencia",
    "wof:name":"Asesoria Jose Luis Martin S.l.",
    "wof:placetype":"venue"
},
  "geometry": {"coordinates":[-4.4976963997,42.8649635315],"type":"Point"}
}