{
  "type": "Feature",
  "properties": {
    "addr:full":"Plaz Tte Cor Franco, 5 Palma Islas Baleares 07008",
    "addr:housenumber":"5",
    "addr:postcode":"07008",
    "addr:street":"Plaz Tte Cor Franco",
    "iso:country":"ES",
    "sg:address":"Plaz Tte Cor Franco, 5",
    "sg:city":"Palma",
    "sg:orig_category":"Agencias De Viajes",
    "sg:phone":"+34 971 24 09 40",
    "sg:postcode":"07008",
    "sg:province":"Islas Baleares",
    "sg:website":"www.voltes@juniper.es",
    "wof:name":"Viajes Voltes S.l.",
    "wof:placetype":"venue"
},
  "geometry": {"coordinates":[2.6689169407,39.5770874023],"type":"Point"}
}