{
  "type": "Feature",
  "properties": {
    "addr:full":"Carrer de Vallespir (del), 20 Olot Girona 17800",
    "addr:housenumber":"20",
    "addr:postcode":"17800",
    "addr:street":"Carrer De Vallespir Del",
    "iso:country":"ES",
    "sg:address":"Carrer de Vallespir (del), 20",
    "sg:city":"Olot",
    "sg:orig_category":"Gases Industriales",
    "sg:phone":"+34 972 26 20 44",
    "sg:postcode":"17800",
    "sg:province":"Girona",
    "wof:name":"Agromecanica Olot S.l.",
    "wof:placetype":"venue"
},
  "geometry": {"coordinates":[2.496414,42.19907],"type":"Point"}
}