{
  "type": "Feature",
  "properties": {
    "iso:country":"ES",
    "sg:address":"Calle de Don Gonzalo, 38",
    "sg:city":"Puente-genil",
    "sg:orig_category":"Arquitectos",
    "sg:phone":"+34 957 60 45 01",
    "sg:postcode":"14500",
    "sg:province":"C\u00f3rdoba",
    "wof:name":"Reina Montero Eduardo",
    "wof:placetype":"venue"
},
  "geometry": {"coordinates":[-4.7788267136,37.389465332],"type":"Point"}
}