{
  "type": "Feature",
  "properties": {
    "addr:full":"Carr Havana, L', 16 Vilanova I La Geltru Barcelona 08800",
    "addr:housenumber":"16",
    "addr:postcode":"08800",
    "addr:street":"Carr Havana L '",
    "iso:country":"ES",
    "sg:address":"Carr Havana, L', 16",
    "sg:city":"Vilanova I La Geltru",
    "sg:orig_category":"Peluqueros: De Se\u00d1oras",
    "sg:phone":"+34 938 15 62 03",
    "sg:postcode":"08800",
    "sg:province":"Barcelona",
    "wof:name":"Rubio Gonzalez Catalina",
    "wof:placetype":"venue"
},
  "geometry": {"coordinates":[1.724421978,41.2213134766],"type":"Point"}
}