{
  "type": "Feature",
  "properties": {
    "iso:country":"ES",
    "sg:address":"Calle de Molino De Las Armas, 45",
    "sg:city":"Zaragoza",
    "sg:orig_category":"Chapister\u00cda",
    "sg:phone":"+34 976 39 77 90",
    "sg:postcode":"50014",
    "sg:province":"Zaragoza",
    "wof:name":"Cascante Garcia Juan Manuel",
    "wof:placetype":"venue"
},
  "geometry": {"coordinates":[-0.8631510139,41.6609077454],"type":"Point"}
}