{
  "type": "Feature",
  "properties": {
    "iso:country":"ES",
    "sg:address":"Calle de Maria Cristina, S/n",
    "sg:city":"Brihuega",
    "sg:orig_category":"Cajas Para Embalar",
    "sg:phone":"+34 949 28 06 05",
    "sg:postcode":"19400",
    "sg:province":"Guadalajara",
    "wof:name":"Caja Rural Provincial De Toledo",
    "wof:placetype":"venue"
},
  "geometry": {"coordinates":[-2.8704121113,40.7630805969],"type":"Point"}
}