{
  "type": "Feature",
  "properties": {
    "iso:country":"ES",
    "sg:address":"Calle de Sagasta, 17",
    "sg:city":"Cadiz",
    "sg:orig_category":"Farmacias",
    "sg:phone":"+34 956 21 29 22",
    "sg:postcode":"11001",
    "sg:province":"C\u00e1diz",
    "wof:name":"Martinez Cansino Maria De Los Angeles",
    "wof:placetype":"venue"
},
  "geometry": {"coordinates":[-6.2980108261,36.5333976746],"type":"Point"}
}