{
  "type": "Feature",
  "properties": {
    "addr:full":"Calle de Castilleja De La Cuesta, 31 Camas Sevilla 41900",
    "addr:housenumber":"31",
    "addr:postcode":"41900",
    "addr:street":"Calle De Castilleja;La Cuesta",
    "iso:country":"ES",
    "sg:address":"Calle de Castilleja De La Cuesta, 31",
    "sg:city":"Camas",
    "sg:orig_category":"Contenedores (mercanc\u00cdas)",
    "sg:phone":"+34 954 39 32 70",
    "sg:postcode":"41900",
    "sg:province":"Sevilla",
    "wof:name":"Gonzalez Moreno Maria Reyes",
    "wof:placetype":"venue"
},
  "geometry": {"coordinates":[-6.032283783,37.3874702454],"type":"Point"}
}