{
  "type": "Feature",
  "properties": {
    "addr:full":"Calle de Majadilla, 1 Carcabuey C\u00f3rdoba 14810",
    "addr:housenumber":"1",
    "addr:postcode":"14810",
    "addr:street":"Calle De Majadilla",
    "iso:country":"ES",
    "sg:address":"Calle de Majadilla, 1",
    "sg:city":"Carcabuey",
    "sg:orig_category":"Oficinas De Turismo, Asociaciones De Iniciativa",
    "sg:phone":"+34 957 70 41 40",
    "sg:postcode":"14810",
    "sg:province":"C\u00f3rdoba",
    "sg:website":"www.carcabueyturismorural.com",
    "wof:name":"Ayuntamiento De Carcabuey",
    "wof:placetype":"venue"
},
  "geometry": {"coordinates":[-4.2736802101,37.443939209],"type":"Point"}
}