{
  "type": "Feature",
  "properties": {
    "iso:country":"ES",
    "sg:address":"Calle de Carlos Iii, 18",
    "sg:city":"Fuente Palmera",
    "sg:orig_category":"Molduras, Junquillos, Listones Y Molduras Perforadas",
    "sg:phone":"+34 957 63 86 63",
    "sg:postcode":"14120",
    "sg:province":"C\u00f3rdoba",
    "wof:name":"Martinez Carmona Juan",
    "wof:placetype":"venue"
},
  "geometry": {"coordinates":[-5.1039276123,37.7051582336],"type":"Point"}
}