{
  "type": "Feature",
  "properties": {
    "iso:country":"ES",
    "sg:address":"Calle de San Marcos, 10",
    "sg:city":"Errenteria",
    "sg:orig_category":"Plomeros",
    "sg:phone":"+34 943 34 19 14",
    "sg:postcode":"20100",
    "sg:province":"Guip\u00f9zcoa",
    "wof:name":"Moreno Carrasco Sergio",
    "wof:placetype":"venue"
},
  "geometry": {"coordinates":[-1.9134169817,43.3094749451],"type":"Point"}
}