{
  "type": "Feature",
  "properties": {
    "iso:country":"ES",
    "sg:address":"Urb Sue\u00f1o Azul, 1",
    "sg:city":"Gran Alacant",
    "sg:orig_category":"Inmobiliaria (agencias)",
    "sg:phone":"+34 966 69 84 58",
    "sg:postcode":"03130",
    "sg:province":"Alicante",
    "wof:name":"Segurinter Mares S.l.",
    "wof:placetype":"venue"
},
  "geometry": {"coordinates":[-0.55775702,38.2050170898],"type":"Point"}
}