{
  "type": "Feature",
  "properties": {
    "addr:full":"Calle de Corredera Del Cristo, 21 Talavera Reina Toledo 45600",
    "addr:housenumber":"21",
    "addr:postcode":"45600",
    "addr:street":"Calle De Corredera Del Cristo",
    "iso:country":"ES",
    "sg:address":"Calle de Corredera Del Cristo, 21",
    "sg:city":"Talavera Reina",
    "sg:orig_category":"Talleres: Ropa A Medida",
    "sg:phone":"+34 925 80 08 22",
    "sg:postcode":"45600",
    "sg:province":"Toledo",
    "wof:name":"Serra Roldan Carmen",
    "wof:placetype":"venue"
},
  "geometry": {"coordinates":[-4.8321061134,39.960105896],"type":"Point"}
}