{
  "type": "Feature",
  "properties": {
    "iso:country":"ES",
    "sg:address":"Plaz Iglesia (la), S/n",
    "sg:city":"Centro",
    "sg:orig_category":"Iglesia Cat\u00d3lica",
    "sg:phone":"+34 975 32 60 59",
    "sg:postcode":"42240",
    "sg:province":"Soria",
    "wof:name":"Parroquia De San Juan Bautista",
    "wof:placetype":"venue"
},
  "geometry": {"coordinates":[-2.4357540607,41.1723670959],"type":"Point"}
}