{
  "type": "Feature",
  "properties": {
    "iso:country":"ES",
    "sg:address":"Avda San Antonio, 1",
    "sg:city":"Puerto Santiago",
    "sg:orig_category":"Imprenta",
    "sg:phone":"+34 922 86 70 97",
    "sg:postcode":"38683",
    "sg:province":"Santa Cruz De Tenerife",
    "wof:name":"Imprenta Santiago S.l.",
    "wof:placetype":"venue"
},
  "geometry": {"coordinates":[-16.833984375,28.2351074219],"type":"Point"}
}