{
  "type": "Feature",
  "properties": {
    "iso:country":"ES",
    "sg:address":"Calle de Virgen (la), 75",
    "sg:city":"Barraco",
    "sg:orig_category":"Chapister\u00cda",
    "sg:phone":"+34 920 28 11 94",
    "sg:postcode":"05110",
    "sg:province":"\u00c1vila",
    "wof:name":"Somoza Gomez Luis Mariano",
    "wof:placetype":"venue"
},
  "geometry": {"coordinates":[-4.6375980377,40.472984314],"type":"Point"}
}