{
  "type": "Feature",
  "properties": {
    "iso:country":"ES",
    "sg:address":"Plaz Mayor, 3",
    "sg:city":"Medina Rioseco",
    "sg:orig_category":"Molduras, Junquillos, Listones Y Molduras Perforadas",
    "sg:phone":"+34 983 70 12 65",
    "sg:postcode":"47800",
    "sg:province":"Valladolid",
    "wof:name":"Espinaco Contreras Carlos",
    "wof:placetype":"venue"
},
  "geometry": {"coordinates":[-5.0413942337,41.8812446594],"type":"Point"}
}