{
  "type": "Feature",
  "properties": {
    "addr:full":"Calle de Arq. Perez Carasa, 12 Huelva Huelva 21001",
    "addr:housenumber":"12",
    "addr:postcode":"21001",
    "addr:street":"Calle De Arq. Perez Carasa",
    "iso:country":"ES",
    "sg:address":"Calle de Arq. Perez Carasa, 12",
    "sg:city":"Huelva",
    "sg:orig_category":"Ropa Para Se\u00d1oras (al Por Menor)",
    "sg:phone":"+34 959 28 54 26",
    "sg:postcode":"21001",
    "sg:province":"Huelva",
    "wof:name":"Sisditex S.l.",
    "wof:placetype":"venue"
},
  "geometry": {"coordinates":[-6.9503278732,37.2559127808],"type":"Point"}
}