{
  "type": "Feature",
  "properties": {
    "iso:country":"ES",
    "sg:address":"Calle de Torredonjimeno, 17",
    "sg:city":"Jaen",
    "sg:orig_category":"Seguridad Social",
    "sg:phone":"+34 953 24 99 09",
    "sg:postcode":"23009",
    "sg:province":"Ja\u00e9n",
    "wof:name":"Sociedad De Prevencion De Asepeyo Sociedad Limitada",
    "wof:placetype":"venue"
},
  "geometry": {"coordinates":[-3.7791919708,37.7981376648],"type":"Point"}
}