{
  "type": "Feature",
  "properties": {
    "iso:country":"ES",
    "sg:address":"Calle de Navarro Rodrigo, 4",
    "sg:city":"Almeria",
    "sg:orig_category":"Bisuter\u00cda, Joyer\u00cda, Relojer\u00cda (al Por Menor)",
    "sg:phone":"+34 950 23 72 87",
    "sg:postcode":"04001",
    "sg:province":"Almer\u00eda",
    "wof:name":"Leon Carre\u00f1o Federico",
    "wof:placetype":"venue"
},
  "geometry": {"coordinates":[-2.4632349014,36.8394508362],"type":"Point"}
}