{
  "type": "Feature",
  "properties": {
    "iso:country":"ES",
    "sg:address":"Calle de Nueva De San Anton, 1",
    "sg:city":"Granada",
    "sg:orig_category":"Abogados",
    "sg:phone":"+34 958 26 32 14",
    "sg:postcode":"18005",
    "sg:province":"Granada",
    "wof:name":"Hernandez-carrillo Abogados C. De B.",
    "wof:placetype":"venue"
},
  "geometry": {"coordinates":[-3.599832058,37.1708106995],"type":"Point"}
}