{
  "type": "Feature",
  "properties": {
    "iso:country":"ES",
    "sg:address":"Pl Alcasser, 3",
    "sg:city":"Portals Nous",
    "sg:orig_category":"Centros M\u00c9dicos Y Sociales, Dispensarios",
    "sg:phone":"+34 971 67 63 34",
    "sg:postcode":"07181",
    "sg:province":"Islas Baleares",
    "wof:name":"Centro Medico Portals Nous S.l.",
    "wof:placetype":"venue"
},
  "geometry": {"coordinates":[2.5727860928,39.5353507996],"type":"Point"}
}