{
  "type": "Feature",
  "properties": {
    "addr:full":"Calle de Molino Bajo, 14 Ejea De Los Caballeros Zaragoza 50600",
    "addr:housenumber":"14",
    "addr:postcode":"50600",
    "addr:street":"Calle De Molino Bajo",
    "iso:country":"ES",
    "sg:address":"Calle de Molino Bajo, 14",
    "sg:city":"Ejea De Los Caballeros",
    "sg:orig_category":"Escayola Y Productos De Escayola (fabricaci\u00d3n, Al Por Mayor)",
    "sg:phone":"+34 976 66 39 24",
    "sg:postcode":"50600",
    "sg:province":"Zaragoza",
    "wof:name":"Bellido Sesma Luis Miguel",
    "wof:placetype":"venue"
},
  "geometry": {"coordinates":[-1.1327680349,42.126033783],"type":"Point"}
}