{
  "type": "Feature",
  "properties": {
    "iso:country":"ES",
    "sg:address":"Avda Florida, 49",
    "sg:city":"Vigo",
    "sg:orig_category":"Alquiler De V\u00cddeo",
    "sg:phone":"+34 986 23 97 10",
    "sg:postcode":"36210",
    "sg:province":"Pontevedra",
    "wof:name":"Pombo Pereira Antonio",
    "wof:placetype":"venue"
},
  "geometry": {"coordinates":[-8.7486486435,42.2094497681],"type":"Point"}
}