{
  "type": "Feature",
  "properties": {
    "iso:country":"ES",
    "sg:address":"Calle de Jose Posada Herrera, 4",
    "sg:city":"Torrelavega",
    "sg:orig_category":"Cl\u00cdnicas Dentales",
    "sg:phone":"+34 942 88 27 84",
    "sg:postcode":"39300",
    "sg:province":"Cantabria",
    "wof:name":"Gallut Sa\u00f1udo Juan Carlos",
    "wof:placetype":"venue"
},
  "geometry": {"coordinates":[-4.0525760651,43.3493270874],"type":"Point"}
}