{
  "type": "Feature",
  "properties": {
    "iso:country":"ES",
    "sg:address":"Calle de Teniente Ruiz, 10",
    "sg:city":"Alcala Henares",
    "sg:orig_category":"Asesor\u00cda Fiscal Y Jur\u00cddica",
    "sg:phone":"+34 918 83 11 55",
    "sg:postcode":"28805",
    "sg:province":"Madrid",
    "wof:name":"Salfec Asesores S.l.",
    "wof:placetype":"venue"
},
  "geometry": {"coordinates":[-3.359292984,40.4841384888],"type":"Point"}
}