{
  "type": "Feature",
  "properties": {
    "iso:country":"ES",
    "sg:address":"Rua Hospital, 24",
    "sg:city":"Rianxo",
    "sg:orig_category":"Asociaciones Y Clubs Deportivos",
    "sg:phone":"+34 981 86 07 24",
    "sg:postcode":"15920",
    "sg:province":"La Coru\u00f1a",
    "wof:name":"Bravo Gago Angel",
    "wof:placetype":"venue"
},
  "geometry": {"coordinates":[-8.8185091019,42.6506996155],"type":"Point"}
}