{
  "type": "Feature",
  "properties": {
    "iso:country":"ES",
    "sg:address":"S Fernando, S/n",
    "sg:city":"S. Agustin-playa Ingles",
    "sg:orig_category":"Cerrajer\u00cda, Ferrallista",
    "sg:phone":"+34 928 77 14 83",
    "sg:postcode":"35100",
    "sg:province":"Las Palmas",
    "wof:name":"Aleman Quevedo Jose Manuel",
    "wof:placetype":"venue"
},
  "geometry": {"coordinates":[-15.4300060272,28.1248226166],"type":"Point"}
}