{
  "type": "Feature",
  "properties": {
    "iso:country":"ES",
    "sg:address":"Olaizola Kalea, S/n",
    "sg:city":"Lezo",
    "sg:orig_category":"Promotores Constructores",
    "sg:phone":"+34 943 49 30 27",
    "sg:postcode":"20100",
    "sg:province":"Guip\u00f9zcoa",
    "wof:name":"Tecnicos De Estabilizaciones E Inyecciones S.a.",
    "wof:placetype":"venue"
},
  "geometry": {"coordinates":[-1.8682130575,43.322971344],"type":"Point"}
}