{
  "type": "Feature",
  "properties": {
    "addr:full":"Av Ballester, 3 Viladecans Barcelona 08840",
    "addr:housenumber":"3",
    "addr:postcode":"08840",
    "addr:street":"Av Ballester",
    "iso:country":"ES",
    "sg:address":"Av Ballester, 3",
    "sg:city":"Viladecans",
    "sg:orig_category":"Delegados, Agentes De Tr\u00c1nsito, Auxiliares De Transporte Internacional",
    "sg:phone":"+34 936 37 92 33",
    "sg:postcode":"08840",
    "sg:province":"Barcelona",
    "wof:name":"Osete Galera Jose Manuel",
    "wof:placetype":"venue"
},
  "geometry": {"coordinates":[2.00770998,41.3188018799],"type":"Point"}
}