{
  "type": "Feature",
  "properties": {
    "addr:full":"Avda Constitucion (la), 1 Arona Santa Cruz De Tenerife 38640",
    "addr:housenumber":"1",
    "addr:postcode":"38640",
    "addr:street":"Avda Constitucion La",
    "iso:country":"ES",
    "sg:address":"Avda Constitucion (la), 1",
    "sg:city":"Arona",
    "sg:orig_category":"Cajas De Ahorro",
    "sg:phone":"+34 922 72 55 50",
    "sg:postcode":"38640",
    "sg:province":"Santa Cruz De Tenerife",
    "sg:website":"www.lacaixa.es",
    "wof:name":"Caixa D'estalvis I Pensions De Barcelona",
    "wof:placetype":"venue"
},
  "geometry": {"coordinates":[-16.6821174622,28.0978507996],"type":"Point"}
}