{
  "type": "Feature",
  "properties": {
    "iso:country":"ES",
    "sg:address":"Calle de Doctor Fleming, 35",
    "sg:city":"San Vicente Del Raspeig-sant Vicent Del Raspeig",
    "sg:orig_category":"Molduras, Junquillos, Listones Y Molduras Perforadas",
    "sg:phone":"+34 965 66 77 57",
    "sg:postcode":"03690",
    "sg:province":"Alicante",
    "wof:name":"Martinez Perez Mariana",
    "wof:placetype":"venue"
},
  "geometry": {"coordinates":[-0.5216860175,38.4004745483],"type":"Point"}
}