{
  "type": "Feature",
  "properties": {
    "addr:full":"Calle de Traviesas, 13 Jerez De La Frontera C\u00e1diz 11405",
    "addr:housenumber":"13",
    "addr:postcode":"11405",
    "addr:street":"Calle De Traviesas",
    "iso:country":"ES",
    "sg:address":"Calle de Traviesas, 13",
    "sg:city":"Jerez De La Frontera",
    "sg:orig_category":"Ense\u00d1anza: Profesiones Art\u00cdsticas",
    "sg:phone":"+34 956 34 75 48",
    "sg:postcode":"11405",
    "sg:province":"C\u00e1diz",
    "wof:name":"Garcia Alvarez Luis",
    "wof:placetype":"venue"
},
  "geometry": {"coordinates":[-6.1250572205,36.6883049011],"type":"Point"}
}