{
  "type": "Feature",
  "properties": {
    "addr:full":"Carrer de Ramon De Trinxeria, 1 Sant Feliu Llobregat Barcelona 08980",
    "addr:housenumber":"1",
    "addr:postcode":"08980",
    "addr:street":"Carrer De Ramon De Trinxeria",
    "iso:country":"ES",
    "sg:address":"Carrer de Ramon De Trinxeria, 1",
    "sg:city":"Sant Feliu Llobregat",
    "sg:orig_category":"Molduras, Junquillos, Listones Y Molduras Perforadas",
    "sg:phone":"+34 936 66 85 62",
    "sg:postcode":"08980",
    "sg:province":"Barcelona",
    "wof:name":"Furgonetas De Alquiler S.a.",
    "wof:placetype":"venue"
},
  "geometry": {"coordinates":[2.0346980095,41.387714386],"type":"Point"}
}