{
  "type": "Feature",
  "properties": {
    "iso:country":"ES",
    "sg:address":"Pase Chopera (de La), 158",
    "sg:city":"Alcobendas",
    "sg:orig_category":"Lencer\u00cda Femenina, Corseter\u00cda, Trajes De Ba\u00d1o (al Por Menor)",
    "sg:phone":"+34 916 61 61 29",
    "sg:postcode":"28100",
    "sg:province":"Madrid",
    "wof:name":"Ya\u00f1ez Gonzalez Susana",
    "wof:placetype":"venue"
},
  "geometry": {"coordinates":[-3.6549487114,40.5451431274],"type":"Point"}
}