{
  "type": "Feature",
  "properties": {
    "addr:full":"Carmen, S/n Los Garres Murcia 30158",
    "addr:housenumber":"s / n",
    "addr:postcode":"30158",
    "addr:street":"Carmen;Los Garres",
    "iso:country":"ES",
    "sg:address":"Carmen, S/n",
    "sg:city":"Los Garres",
    "sg:orig_category":"Cajas De Ahorro",
    "sg:phone":"+34 968 82 06 77",
    "sg:postcode":"30158",
    "sg:province":"Murcia",
    "sg:website":"www.cam.es",
    "wof:name":"Caja De Ahorros Del Mediterraneo",
    "wof:placetype":"venue"
},
  "geometry": {"coordinates":[-1.0940910578,37.9564247131],"type":"Point"}
}