{
  "type": "Feature",
  "properties": {
    "addr:full":"Pueblo Marinero, S/n Benalmadena-costa M\u00e1laga 29630",
    "addr:housenumber":"s",
    "addr:postcode":"29630",
    "addr:street":"Marinero;/ N Benalmadena-Costa Ma\u0301Laga",
    "iso:country":"ES",
    "sg:address":"Pueblo Marinero, S/n",
    "sg:city":"Benalmadena-costa",
    "sg:orig_category":"Discotecas Y Salas De Baile",
    "sg:phone":"+34 952 44 66 00",
    "sg:postcode":"29630",
    "sg:province":"M\u00e1laga",
    "wof:name":"Orange Corp S.l.",
    "wof:placetype":"venue"
},
  "geometry": {"coordinates":[-4.521381855,36.5971374512],"type":"Point"}
}