{
  "type": "Feature",
  "properties": {
    "iso:country":"ES",
    "sg:address":"Calle de Caridad, 8",
    "sg:city":"Santa Pola",
    "sg:orig_category":"Supermercados Y Hipermercados",
    "sg:phone":"+34 966 69 45 81",
    "sg:postcode":"03130",
    "sg:province":"Alicante",
    "wof:name":"Dialsur S.a.",
    "wof:placetype":"venue"
},
  "geometry": {"coordinates":[-0.5565090179,38.190448761],"type":"Point"}
}