{
  "type": "Feature",
  "properties": {
    "addr:full":"Cmno Casabermeja, 98 Malaga M\u00e1laga 29014",
    "addr:housenumber":"98",
    "addr:postcode":"29014",
    "addr:street":"Cmno Casabermeja;Ma\u0301Laga",
    "iso:country":"ES",
    "sg:address":"Cmno Casabermeja, 98",
    "sg:city":"Malaga",
    "sg:orig_category":"Maquinaria Para Industrias Diversas",
    "sg:phone":"+34 952 30 28 08",
    "sg:postcode":"29014",
    "sg:province":"M\u00e1laga",
    "wof:name":"Cosien S.a.",
    "wof:placetype":"venue"
},
  "geometry": {"coordinates":[-4.4250249863,36.7556152344],"type":"Point"}
}