{
  "type": "Feature",
  "properties": {
    "addr:full":"Calle de Lauaxeta Olerkari, 11 Mungia Vizcaya 48100",
    "addr:housenumber":"11",
    "addr:postcode":"48100",
    "addr:street":"Calle De Lauaxeta Olerkari",
    "iso:country":"ES",
    "sg:address":"Calle de Lauaxeta Olerkari, 11",
    "sg:city":"Mungia",
    "sg:orig_category":"Carnicer\u00cdas, Carnicer\u00cdas",
    "sg:phone":"+34 946 74 09 33",
    "sg:postcode":"48100",
    "sg:province":"Vizcaya",
    "wof:name":"Carniceria Ortzipe S.l.l.",
    "wof:placetype":"venue"
},
  "geometry": {"coordinates":[-2.8487999439,43.3560028076],"type":"Point"}
}