{
  "type": "Feature",
  "properties": {
    "addr:full":"Calle de Canonigo, 106 Dos Hermanas Sevilla 41700",
    "addr:housenumber":"106",
    "addr:postcode":"41700",
    "addr:street":"Calle De Canonigo;Sevilla",
    "iso:country":"ES",
    "sg:address":"Calle de Canonigo, 106",
    "sg:city":"Dos Hermanas",
    "sg:orig_category":"Bancos",
    "sg:phone":"+34 954 72 38 25",
    "sg:postcode":"41700",
    "sg:province":"Sevilla",
    "sg:website":"www.bancopopular.es",
    "wof:name":"Banco Popular Espa\u00f1ol S. A.",
    "wof:placetype":"venue"
},
  "geometry": {"coordinates":[-5.9219398499,37.2821350098],"type":"Point"}
}