{
  "type": "Feature",
  "properties": {
    "addr:full":"Ctra Jaen (de), S/n Granada Granada 18100",
    "addr:housenumber":"/ n",
    "addr:postcode":"18100",
    "addr:street":"Ctra Jaen De S",
    "iso:country":"ES",
    "sg:address":"Ctra Jaen (de), S/n",
    "sg:city":"Granada",
    "sg:orig_category":"Autob\u00das (explotaci\u00d3n Y Servicios De)",
    "sg:phone":"+34 958 15 91 97",
    "sg:postcode":"18100",
    "sg:province":"Granada",
    "sg:website":"www.alsinagraells.net",
    "wof:name":"Transportes Alsina Graell Sur S.a.",
    "wof:placetype":"venue"
},
  "geometry": {"coordinates":[-3.6119110584,37.1988677979],"type":"Point"}
}