{
  "type": "Feature",
  "properties": {
    "addr:full":"Calle de Somera, 19 Bilbao Vizcaya 48005",
    "addr:housenumber":"19",
    "addr:postcode":"48005",
    "addr:street":"Calle De Somera",
    "iso:country":"ES",
    "sg:address":"Calle de Somera, 19",
    "sg:city":"Bilbao",
    "sg:orig_category":"Ropa Para Se\u00d1oras Y Caballeros (al Por Menor)",
    "sg:phone":"+34 944 15 38 21",
    "sg:postcode":"48005",
    "sg:province":"Vizcaya",
    "wof:name":"Chekroun Chairi Rachid",
    "wof:placetype":"venue"
},
  "geometry": {"coordinates":[-2.9230589867,43.2562561035],"type":"Point"}
}