{
  "type": "Feature",
  "properties": {
    "addr:full":"Calle de Isabel La Catolica, 9 Santander Cantabria 39007",
    "addr:housenumber":"9",
    "addr:postcode":"39007",
    "addr:street":"Calle De Isabel La Catolica",
    "iso:country":"ES",
    "sg:address":"Calle de Isabel La Catolica, 9",
    "sg:city":"Santander",
    "sg:orig_category":"Telas Y Sedas (al Por Menor)",
    "sg:phone":"+34 942 37 15 11",
    "sg:postcode":"39007",
    "sg:province":"Cantabria",
    "wof:name":"Ruiz Exposito Rosa",
    "wof:placetype":"venue"
},
  "geometry": {"coordinates":[-3.8143029213,43.4623832703],"type":"Point"}
}