{
  "type": "Feature",
  "properties": {
    "addr:full":"Calle de Antonio Huertas Remigio, S/n Maracena Granada 18200",
    "addr:housenumber":"s / n",
    "addr:postcode":"18200",
    "addr:street":"Calle De Antonio Huertas Remigio",
    "iso:country":"ES",
    "sg:address":"Calle de Antonio Huertas Remigio, S/n",
    "sg:city":"Maracena",
    "sg:orig_category":"Mantenimiento Industrial",
    "sg:phone":"+34 958 42 13 30",
    "sg:postcode":"18200",
    "sg:province":"Granada",
    "wof:name":"Taller Y Suministros Orellana S.l.",
    "wof:placetype":"venue"
},
  "geometry": {"coordinates":[-3.6424939632,37.2034950256],"type":"Point"}
}