{
  "type": "Feature",
  "properties": {
    "iso:country":"ES",
    "sg:address":"Carrer de Montserrat, 20",
    "sg:city":"Arenys Mar",
    "sg:orig_category":"Electricidad: Equipos Industriales, Componentes (fabricaci\u00d3n)",
    "sg:phone":"+34 937 92 25 15",
    "sg:postcode":"08350",
    "sg:province":"Barcelona",
    "wof:name":"Matelecsa S.a.",
    "wof:placetype":"venue"
},
  "geometry": {"coordinates":[2.5444049835,41.5862579346],"type":"Point"}
}