{
  "type": "Feature",
  "properties": {
    "addr:full":"Poli Poligon Industrial, S/n Picassent Valencia 46220",
    "addr:postcode":"46220",
    "addr:street":"Industrial S / N",
    "iso:country":"ES",
    "sg:address":"Poli Poligon Industrial, S/n",
    "sg:city":"Picassent",
    "sg:orig_category":"Cajas Y Embalajes De Pl\u00c1stico",
    "sg:phone":"+34 961 24 18 00",
    "sg:postcode":"46220",
    "sg:province":"Valencia",
    "sg:website":"www.ifcosistems.es",
    "wof:name":"Ifco Systems Espa\u00d1a S.l.",
    "wof:placetype":"venue"
},
  "geometry": {"coordinates":[-0.4524689913,39.3585700989],"type":"Point"}
}