{
  "type": "Feature",
  "properties": {
    "addr:full":"C/ Menor, 21 Alaior Islas Baleares 07730",
    "addr:housenumber":"21",
    "addr:postcode":"07730",
    "addr:street":"C / Menor",
    "iso:country":"ES",
    "sg:address":"C/ Menor, 21",
    "sg:city":"Alaior",
    "sg:orig_category":"Obras Y Organismos Sociales",
    "sg:phone":"+34 971 37 11 10",
    "sg:postcode":"07730",
    "sg:province":"Islas Baleares",
    "wof:name":"Caritas Diocesana Menorca-fundacion Mestral",
    "wof:placetype":"venue"
},
  "geometry": {"coordinates":[4.1391611099,39.934387207],"type":"Point"}
}