{
  "type": "Feature",
  "properties": {
    "iso:country":"ES",
    "sg:address":"Avda San Josemaria Escriva, 10",
    "sg:city":"Barbastro",
    "sg:orig_category":"M\u00c9dicos: Oftalmolog\u00cda",
    "sg:phone":"+34 974 31 06 83",
    "sg:postcode":"22300",
    "sg:province":"Huesca",
    "wof:name":"Chacon Valles Manuel",
    "wof:placetype":"venue"
},
  "geometry": {"coordinates":[0.1279940009,42.0360984802],"type":"Point"}
}