{
  "type": "Feature",
  "properties": {
    "addr:full":"Calle de Alferez Provisional, S/n Palmas De Gran Canaria Las Palmas 35012",
    "addr:housenumber":"s",
    "addr:postcode":"35012",
    "addr:street":"Calle De Alferez Provisional;/ N",
    "iso:country":"ES",
    "sg:address":"Calle de Alferez Provisional, S/n",
    "sg:city":"Palmas De Gran Canaria",
    "sg:orig_category":"Pescader\u00cdas (al Por Menor)",
    "sg:phone":"+34 928 41 90 38",
    "sg:postcode":"35012",
    "sg:province":"Las Palmas",
    "wof:name":"Freiremar Comercial S.a.",
    "wof:placetype":"venue"
},
  "geometry": {"coordinates":[-15.4464273453,28.1114730835],"type":"Point"}
}