{
  "type": "Feature",
  "properties": {
    "addr:full":"Calle de Dels Tapissers, 6 Paiporta Valencia 46200",
    "addr:housenumber":"6",
    "addr:postcode":"46200",
    "addr:street":"Calle De Dels Tapissers",
    "iso:country":"ES",
    "sg:address":"Calle de Dels Tapissers, 6",
    "sg:city":"Paiporta",
    "sg:orig_category":"Fabricaci\u00d3n De Etiquetas",
    "sg:phone":"+34 963 97 27 98",
    "sg:postcode":"46200",
    "sg:province":"Valencia",
    "wof:name":"Eticinco Dionisio Garcia S.l.",
    "wof:placetype":"venue"
},
  "geometry": {"coordinates":[-0.4100160003,39.4241371155],"type":"Point"}
}