{
  "type": "Feature",
  "properties": {
    "addr:full":"Calle de Rodriguez San Pedro, 2 Madrid Madrid 28015",
    "addr:housenumber":"2",
    "addr:postcode":"28015",
    "addr:street":"Calle De Rodriguez San Pedro",
    "iso:country":"ES",
    "sg:address":"Calle de Rodriguez San Pedro, 2",
    "sg:city":"Madrid",
    "sg:orig_category":"Centros Empresariales",
    "sg:phone":"+34 915 94 54 23",
    "sg:postcode":"28015",
    "sg:province":"Madrid",
    "wof:name":"Gonzalez De Lara Mingo Cesar",
    "wof:placetype":"venue"
},
  "geometry": {"coordinates":[-3.7054820061,40.4315795898],"type":"Point"}
}