{
  "type": "Feature",
  "properties": {
    "iso:country":"ES",
    "sg:address":"Carr Guadassuar, S/n",
    "sg:city":"Alcudia",
    "sg:orig_category":"Rectificaci\u00d3n, Mecanizado, Fresado",
    "sg:phone":"+34 962 99 76 83",
    "sg:postcode":"46250",
    "sg:province":"Valencia",
    "wof:name":"Rectificats L'alcudia S.l.l.",
    "wof:placetype":"venue"
},
  "geometry": {"coordinates":[-0.5070289969,39.1940689087],"type":"Point"}
}