{
  "type": "Feature",
  "properties": {
    "addr:full":"Calle de Venezuela, 14 Coria Rio Sevilla 41100",
    "addr:housenumber":"14",
    "addr:postcode":"41100",
    "addr:street":"Calle De Venezuela;Rio Sevilla",
    "iso:country":"ES",
    "sg:address":"Calle de Venezuela, 14",
    "sg:city":"Coria Rio",
    "sg:orig_category":"Electrodom\u00c9sticos (al Por Menor)",
    "sg:phone":"+34 954 77 12 12",
    "sg:postcode":"41100",
    "sg:province":"Sevilla",
    "wof:name":"Electrodomesticos Parrado S.l.",
    "wof:placetype":"venue"
},
  "geometry": {"coordinates":[-6.0518789291,37.2867660522],"type":"Point"}
}