{
  "type": "Feature",
  "properties": {
    "iso:country":"ES",
    "sg:address":"Plaz Ayuntamiento, 29",
    "sg:city":"Valencia",
    "sg:orig_category":"Arboricultura Y Producci\u00d3n De Frutas",
    "sg:phone":"+34 963 51 35 85",
    "sg:postcode":"46002",
    "sg:province":"Valencia",
    "wof:name":"Federacion De Exportadores De Citricos De La Provincia De Valencia",
    "wof:placetype":"venue"
},
  "geometry": {"coordinates":[-0.3766640127,39.4691390991],"type":"Point"}
}