{
  "type": "Feature",
  "properties": {
    "addr:full":"Calle de Castillo, 2 Santa Fe Granada 18320",
    "addr:housenumber":"2",
    "addr:postcode":"18320",
    "addr:street":"Calle De Castillo;Fe",
    "iso:country":"ES",
    "sg:address":"Calle de Castillo, 2",
    "sg:city":"Santa Fe",
    "sg:orig_category":"Ebanister\u00cda",
    "sg:phone":"+34 958 44 11 78",
    "sg:postcode":"18320",
    "sg:province":"Granada",
    "wof:name":"Puig Cervera Angel",
    "wof:placetype":"venue"
},
  "geometry": {"coordinates":[-3.7182841301,37.1898040771],"type":"Point"}
}