{
  "type": "Feature",
  "properties": {
    "addr:full":"Avda Salsidu, 36 Getxo Vizcaya 48990",
    "addr:housenumber":"36",
    "addr:postcode":"48990",
    "addr:street":"Avda Salsidu",
    "iso:country":"ES",
    "sg:address":"Avda Salsidu, 36",
    "sg:city":"Getxo",
    "sg:orig_category":"Fabricaci\u00d3n, Importaci\u00d3n De L\u00c1mparas Y Bombillas",
    "sg:phone":"+34 944 30 19 13",
    "sg:postcode":"48990",
    "sg:province":"Vizcaya",
    "wof:name":"Electricidad Getxo, S.l",
    "wof:placetype":"venue"
},
  "geometry": {"coordinates":[-3.0056619644,43.3526878357],"type":"Point"}
}