{
  "type": "Feature",
  "properties": {
    "iso:country":"ES",
    "sg:address":"Calle de Huertas-isla, S/n",
    "sg:city":"Almedinilla",
    "sg:orig_category":"Aceites Y Grasas Alimentarias (fabricaci\u00d3n, Al Por Mayor)",
    "sg:phone":"+34 957 70 34 74",
    "sg:postcode":"14812",
    "sg:province":"C\u00f3rdoba",
    "wof:name":"Oleocenter Espa?a S.l.",
    "wof:placetype":"venue"
},
  "geometry": {"coordinates":[-4.088283062,37.4425354004],"type":"Point"}
}