{
  "type": "Feature",
  "properties": {
    "iso:country":"ES",
    "sg:address":"Calle de Narvaez, 72",
    "sg:city":"Madrid",
    "sg:orig_category":"Tiendas De Grano, Frutas Y Legumbres Secas (al Por Menor)",
    "sg:phone":"+34 914 09 03 22",
    "sg:postcode":"28009",
    "sg:province":"Madrid",
    "wof:name":"Jin  Feng",
    "wof:placetype":"venue"
},
  "geometry": {"coordinates":[-3.6763637066,40.4174995422],"type":"Point"}
}