{
  "type": "Feature",
  "properties": {
    "addr:full":"Calle de Andalucia, 17 Toledo Toledo 45005",
    "addr:housenumber":"17",
    "addr:postcode":"45005",
    "addr:street":"Calle De Andalucia",
    "iso:country":"ES",
    "sg:address":"Calle de Andalucia, 17",
    "sg:city":"Toledo",
    "sg:orig_category":"Carnicer\u00cdas, Carnicer\u00cdas",
    "sg:phone":"+34 925 25 08 98",
    "sg:postcode":"45005",
    "sg:province":"Toledo",
    "wof:name":"Guerrero Ballesteros Jesus",
    "wof:placetype":"venue"
},
  "geometry": {"coordinates":[-4.0370435715,39.8741989136],"type":"Point"}
}