{
  "type": "Feature",
  "properties": {
    "addr:full":"Barrio Bajo, S/n Larrion Navarra 31290",
    "addr:housenumber":"s",
    "addr:postcode":"31290",
    "addr:street":"Bajo;/ N Larrion Navarra",
    "iso:country":"ES",
    "sg:address":"Barrio Bajo, S/n",
    "sg:city":"Larrion",
    "sg:orig_category":"Iglesia Cat\u00d3lica",
    "sg:phone":"+34 948 54 04 42",
    "sg:postcode":"31290",
    "sg:province":"Navarra",
    "wof:name":"Parroquia De La Asuncion",
    "wof:placetype":"venue"
},
  "geometry": {"coordinates":[-2.0757501125,42.7091140747],"type":"Point"}
}