{
  "type": "Feature",
  "properties": {
    "iso:country":"ES",
    "sg:address":"Calle de Cienfuegos, 3",
    "sg:city":"Gijon",
    "sg:orig_category":"Librer\u00cdas",
    "sg:phone":"+34 985 36 82 45",
    "sg:postcode":"33205",
    "sg:province":"Asturias",
    "wof:name":"Salas Ledesma Jose Enrique",
    "wof:placetype":"venue"
},
  "geometry": {"coordinates":[-5.6559820175,43.5353660583],"type":"Point"}
}