{
  "type": "Feature",
  "properties": {
    "iso:country":"ES",
    "sg:address":"Calle de Teja, 5",
    "sg:city":"Martos",
    "sg:orig_category":"Molduras, Junquillos, Listones Y Molduras Perforadas",
    "sg:phone":"+34 953 70 42 57",
    "sg:postcode":"23600",
    "sg:province":"Ja\u00e9n",
    "wof:name":"Miranda Molina Manuel",
    "wof:placetype":"venue"
},
  "geometry": {"coordinates":[-3.9679620266,37.71900177],"type":"Point"}
}