{
  "type": "Feature",
  "properties": {
    "addr:full":"Calle de Luna, S/n Ledesma Salamanca 37100",
    "addr:housenumber":"s / n",
    "addr:postcode":"37100",
    "addr:street":"Calle De Luna",
    "iso:country":"ES",
    "sg:address":"Calle de Luna, S/n",
    "sg:city":"Ledesma",
    "sg:orig_category":"Reposter\u00cdas",
    "sg:phone":"+34 923 57 02 76",
    "sg:postcode":"37100",
    "sg:province":"Salamanca",
    "wof:name":"Rodriguez Martin Juan Agustin",
    "wof:placetype":"venue"
},
  "geometry": {"coordinates":[-6.0044989586,41.087059021],"type":"Point"}
}