{
  "type": "Feature",
  "properties": {
    "iso:country":"ES",
    "sg:address":"Carrer de Avinyonet, 6",
    "sg:city":"Vilafranca Penedes",
    "sg:orig_category":"Equipos De Marcado, Etiquetado",
    "sg:phone":"+34 938 18 10 02",
    "sg:postcode":"08720",
    "sg:province":"Barcelona",
    "wof:name":"Serrano Lopez Antoni-domingo",
    "wof:placetype":"venue"
},
  "geometry": {"coordinates":[1.7097649574,41.3494415283],"type":"Point"}
}