{
  "type": "Feature",
  "properties": {
    "iso:country":"ES",
    "sg:address":"Calle de Puente Colgante, 44",
    "sg:city":"Valladolid",
    "sg:orig_category":"M\u00c9dicos: Pediatr\u00cda. Enfermedades De Los Ni\u00d1os",
    "sg:phone":"+34 983 23 78 97",
    "sg:postcode":"47006",
    "sg:province":"Valladolid",
    "wof:name":"Carrero Mu\u00f1oz Pablo",
    "wof:placetype":"venue"
},
  "geometry": {"coordinates":[-4.7388429642,41.6408576965],"type":"Point"}
}