{
  "type": "Feature",
  "properties": {
    "addr:full":"Calle de Santa Margarita, 16 Torre Mar M\u00e1laga 29740",
    "addr:housenumber":"16",
    "addr:postcode":"29740",
    "addr:street":"Calle De Santa Margarita;Ma\u0301Laga",
    "iso:country":"ES",
    "sg:address":"Calle de Santa Margarita, 16",
    "sg:city":"Torre Mar",
    "sg:orig_category":"M\u00c9dicos: Cirug\u00cda Pl\u00c1stica, Reconstructiva Y Est\u00c9tica",
    "sg:phone":"+34 952 54 69 38",
    "sg:postcode":"29740",
    "sg:province":"M\u00e1laga",
    "wof:name":"Hospital De Dia Cma S.l.",
    "wof:placetype":"venue"
},
  "geometry": {"coordinates":[-4.4206790924,36.7209701538],"type":"Point"}
}