{
  "type": "Feature",
  "properties": {
    "addr:full":"Calle de Ruecas, 31 Casasimarro Cuenca 16239",
    "addr:housenumber":"31",
    "addr:postcode":"16239",
    "addr:street":"Calle De Ruecas",
    "iso:country":"ES",
    "sg:address":"Calle de Ruecas, 31",
    "sg:city":"Casasimarro",
    "sg:orig_category":"Arreglo, Reparaci\u00d3n, Piezas Sueltas De Televisi\u00d3n, V\u00cddeo, Hi",
    "sg:phone":"+34 967 48 74 02",
    "sg:postcode":"16239",
    "sg:province":"Cuenca",
    "wof:name":"Sevilla Saiz Juan Ramon",
    "wof:placetype":"venue"
},
  "geometry": {"coordinates":[-2.0424571037,39.3905029297],"type":"Point"}
}