{
  "type": "Feature",
  "properties": {
    "addr:full":"Carrer de Montpalau, 6 Pineda Mar Barcelona 08397",
    "addr:housenumber":"6",
    "addr:postcode":"08397",
    "addr:street":"Carrer De Montpalau;Barcelona",
    "iso:country":"ES",
    "sg:address":"Carrer de Montpalau, 6",
    "sg:city":"Pineda Mar",
    "sg:orig_category":"Sociedades, Compa\u00d1\u00cdas Aseguradoras",
    "sg:phone":"+34 937 67 05 50",
    "sg:postcode":"08397",
    "sg:province":"Barcelona",
    "wof:name":"Duran Pons Gestio I Assessorament S. A.",
    "wof:placetype":"venue"
},
  "geometry": {"coordinates":[2.6882629395,41.6279563904],"type":"Point"}
}