{
  "type": "Feature",
  "properties": {
    "addr:full":"Carr Escut Emporita, 5 Bisbal D'emporda Girona 17100",
    "addr:housenumber":"5",
    "addr:postcode":"17100",
    "addr:street":"Carr Escut Emporita",
    "iso:country":"ES",
    "sg:address":"Carr Escut Emporita, 5",
    "sg:city":"Bisbal D'emporda",
    "sg:orig_category":"Venta, Instalaci\u00d3n De Calefacci\u00d3n",
    "sg:phone":"+34 972 64 18 77",
    "sg:postcode":"17100",
    "sg:province":"Girona",
    "wof:name":"Electrica Ampurda S.l.",
    "wof:placetype":"venue"
},
  "geometry": {"coordinates":[2.813131094,41.9749221802],"type":"Point"}
}