{
  "type": "Feature",
  "properties": {
    "addr:full":"Calle de Bego\u00d1a, 9 Humanes De Madrid Madrid 28970",
    "addr:housenumber":"9",
    "addr:postcode":"28970",
    "addr:street":"Calle De Begon\u0303A",
    "iso:country":"ES",
    "sg:address":"Calle de Bego\u00d1a, 9",
    "sg:city":"Humanes De Madrid",
    "sg:orig_category":"Bebidas",
    "sg:phone":"+34 916 90 44 09",
    "sg:postcode":"28970",
    "sg:province":"Madrid",
    "wof:name":"Distribuidora La Nueva Castilla S.a.",
    "wof:placetype":"venue"
},
  "geometry": {"coordinates":[-3.8269588947,40.2540245056],"type":"Point"}
}