{
  "type": "Feature",
  "properties": {
    "iso:country":"ES",
    "sg:address":"Carrer de Perera, 38",
    "sg:city":"Barcelona",
    "sg:orig_category":"Abogados",
    "sg:phone":"+34 932 68 41 79",
    "sg:postcode":"08010",
    "sg:province":"Barcelona",
    "wof:name":"Airas Airas Leopoldo",
    "wof:placetype":"venue"
},
  "geometry": {"coordinates":[2.1033556461,41.4276046753],"type":"Point"}
}