{
  "type": "Feature",
  "properties": {
    "addr:full":"Fte. De Sta. Cruz, 4 Montanchez C\u00e1ceres 10170",
    "addr:housenumber":"4",
    "addr:postcode":"10170",
    "addr:street":"Sta. Cruz;Ca\u0301Ceres",
    "iso:country":"ES",
    "sg:address":"Fte. De Sta. Cruz, 4",
    "sg:city":"Montanchez",
    "sg:orig_category":"Carnicer\u00cdas, Carnicer\u00cdas",
    "sg:phone":"+34 927 38 00 87",
    "sg:postcode":"10170",
    "sg:province":"C\u00e1ceres",
    "wof:name":"Caravaca Caballero Antonio",
    "wof:placetype":"venue"
},
  "geometry": {"coordinates":[-6.1525287628,39.2250938416],"type":"Point"}
}