{
  "type": "Feature",
  "properties": {
    "iso:country":"ES",
    "sg:address":"Mayor, 137",
    "sg:city":"Monovar",
    "sg:orig_category":"Lencer\u00cda Femenina, Corseter\u00cda, Trajes De Ba\u00d1o (al Por Menor)",
    "sg:phone":"+34 965 47 11 22",
    "sg:postcode":"03640",
    "sg:province":"Alicante",
    "wof:name":"Ballester Martinez Pilar",
    "wof:placetype":"venue"
},
  "geometry": {"coordinates":[-0.8396289945,38.434135437],"type":"Point"}
}