{
  "type": "Feature",
  "properties": {
    "iso:country":"ES",
    "sg:address":"Carr President Macia, 13",
    "sg:city":"Mollerussa",
    "sg:orig_category":"Quincaller\u00cda (al Por Menor)",
    "sg:phone":"+34 973 60 06 51",
    "sg:postcode":"25230",
    "sg:province":"Lleida",
    "wof:name":"Ferrreteria Baro S.c.p.",
    "wof:placetype":"venue"
},
  "geometry": {"coordinates":[0.8840519786,41.6299095154],"type":"Point"}
}