{
  "type": "Feature",
  "properties": {
    "iso:country":"ES",
    "sg:address":"Avda Mediterraneo (del), 147",
    "sg:city":"Rincon Victoria",
    "sg:orig_category":"Reposter\u00cdas",
    "sg:phone":"+34 952 40 10 55",
    "sg:postcode":"29730",
    "sg:province":"M\u00e1laga",
    "wof:name":"Panificadora El Bambi",
    "wof:placetype":"venue"
},
  "geometry": {"coordinates":[-4.279668808,36.7145004272],"type":"Point"}
}