{
  "type": "Feature",
  "properties": {
    "iso:country":"ES",
    "sg:address":"Calle de Mexico, 26",
    "sg:city":"Cordoba",
    "sg:orig_category":"Fabricaci\u00d3n De Muebles",
    "sg:phone":"+34 957 28 36 74",
    "sg:postcode":"14012",
    "sg:province":"C\u00f3rdoba",
    "wof:name":"El Copete Artesanos De La Madera S.l.",
    "wof:placetype":"venue"
},
  "geometry": {"coordinates":[-4.7964792252,37.909450531],"type":"Point"}
}