{
  "type": "Feature",
  "properties": {
    "addr:full":"Calle de Solarillo De Gracia, 7 Granada Granada 18002",
    "addr:housenumber":"7",
    "addr:postcode":"18002",
    "addr:street":"Calle De Solarillo De Gracia",
    "iso:country":"ES",
    "sg:address":"Calle de Solarillo De Gracia, 7",
    "sg:city":"Granada",
    "sg:orig_category":"Organizaciones Internacionales",
    "sg:phone":"+34 958 26 23 15",
    "sg:postcode":"18002",
    "sg:province":"Granada",
    "wof:name":"Asociacion Espiritual Mundial Brahma Kumaris",
    "wof:placetype":"venue"
},
  "geometry": {"coordinates":[-3.603918314,37.1727638245],"type":"Point"}
}