{
  "type": "Feature",
  "properties": {
    "iso:country":"ES",
    "sg:address":"Calle de Hornachos, 95",
    "sg:city":"Villafranca De Los Barros",
    "sg:orig_category":"Mec\u00c1nico Del Autom\u00d3vil",
    "sg:phone":"+34 924 52 03 30",
    "sg:postcode":"06220",
    "sg:province":"Badajoz",
    "wof:name":"Lopez Garcia Isabel",
    "wof:placetype":"venue"
},
  "geometry": {"coordinates":[-6.3313288689,38.5574798584],"type":"Point"}
}