{
  "type": "Feature",
  "properties": {
    "iso:country":"ES",
    "sg:address":"Ctra La Ina, Km. 0002,5",
    "sg:city":"Jerez",
    "sg:orig_category":"Producci\u00d3n, Venta De Productos De Agricultura Biol\u00d3gica",
    "sg:phone":"+34 956 15 64 96",
    "sg:postcode":"11406",
    "sg:province":"C\u00e1diz",
    "wof:name":"Agarrado Castro Jose",
    "wof:placetype":"venue"
},
  "geometry": {"coordinates":[-6.0992994308,36.7017936707],"type":"Point"}
}