{
  "type": "Feature",
  "properties": {
    "addr:full":"Calle de Prim, 32 Carmona Sevilla 41410",
    "addr:housenumber":"32",
    "addr:postcode":"41410",
    "addr:street":"Calle De Prim",
    "iso:country":"ES",
    "sg:address":"Calle de Prim, 32",
    "sg:city":"Carmona",
    "sg:orig_category":"Cajas De Ahorro",
    "sg:phone":"+34 954 14 11 18",
    "sg:postcode":"41410",
    "sg:province":"Sevilla",
    "sg:website":"www.elmonte.es",
    "wof:name":"Monte De Piedad Y Caja De Ahorros De Huelva Y Sevilla",
    "wof:placetype":"venue"
},
  "geometry": {"coordinates":[-5.6400918961,37.4714126587],"type":"Point"}
}