{
  "type": "Feature",
  "properties": {
    "iso:country":"ES",
    "sg:address":"Calle de Garcia Requena, 19",
    "sg:city":"Jaen",
    "sg:orig_category":"Reposter\u00cdas",
    "sg:phone":"+34 953 23 87 05",
    "sg:postcode":"23002",
    "sg:province":"Ja\u00e9n",
    "wof:name":"Panaderia San Rafael E Y Hijos S.l.",
    "wof:placetype":"venue"
},
  "geometry": {"coordinates":[-3.7901320457,37.7630844116],"type":"Point"}
}