{
  "type": "Feature",
  "properties": {
    "iso:country":"ES",
    "sg:address":"Pedro I, 1",
    "sg:city":"Iru\u00f1a",
    "sg:orig_category":"Procuradores",
    "sg:phone":"+34 948 17 21 33",
    "sg:postcode":"31007",
    "sg:province":"Navarra",
    "wof:name":"Gonzalez Oteiza Miguel",
    "wof:placetype":"venue"
},
  "geometry": {"coordinates":[-1.6545009613,42.8041992188],"type":"Point"}
}