{
  "type": "Feature",
  "properties": {
    "addr:full":"Calle de Antonio Izu, 5 Etxauri Navarra 31174",
    "addr:housenumber":"5",
    "addr:postcode":"31174",
    "addr:street":"Calle De Antonio Izu",
    "iso:country":"ES",
    "sg:address":"Calle de Antonio Izu, 5",
    "sg:city":"Etxauri",
    "sg:orig_category":"Delineantes",
    "sg:phone":"+34 948 32 95 47",
    "sg:postcode":"31174",
    "sg:province":"Navarra",
    "wof:name":"Martinez Rada Jesus",
    "wof:placetype":"venue"
},
  "geometry": {"coordinates":[-1.7913312912,42.7926635742],"type":"Point"}
}