{
  "type": "Feature",
  "properties": {
    "addr:full":"Calle de Convento, 5 Castilleja Cuesta Sevilla 41950",
    "addr:housenumber":"5",
    "addr:postcode":"41950",
    "addr:street":"Calle De Convento;Cuesta Sevilla",
    "iso:country":"ES",
    "sg:address":"Calle de Convento, 5",
    "sg:city":"Castilleja Cuesta",
    "sg:orig_category":"Partidos Pol\u00cdticos",
    "sg:phone":"+34 954 16 43 02",
    "sg:postcode":"41950",
    "sg:province":"Sevilla",
    "wof:name":"Partido Popular",
    "wof:placetype":"venue"
},
  "geometry": {"coordinates":[-6.0523600578,37.3873023987],"type":"Point"}
}