{
  "type": "Feature",
  "properties": {
    "addr:full":"Calle de Altamira, 6 Almazan Soria 42200",
    "addr:housenumber":"6",
    "addr:postcode":"42200",
    "addr:street":"Calle De Altamira",
    "iso:country":"ES",
    "sg:address":"Calle de Altamira, 6",
    "sg:city":"Almazan",
    "sg:orig_category":"Contenedores (mercanc\u00cdas)",
    "sg:phone":"+34 975 30 07 55",
    "sg:postcode":"42200",
    "sg:province":"Soria",
    "wof:name":"Rodriguez Turia Emerita",
    "wof:placetype":"venue"
},
  "geometry": {"coordinates":[-2.5281586647,41.4837112427],"type":"Point"}
}