{
  "type": "Feature",
  "properties": {
    "addr:full":"Calle de Fontilles, 19 Valencia Valencia 46024",
    "addr:housenumber":"19",
    "addr:postcode":"46024",
    "addr:street":"Calle De Fontilles",
    "iso:country":"ES",
    "sg:address":"Calle de Fontilles, 19",
    "sg:city":"Valencia",
    "sg:orig_category":"Arte, Cultura, Edici\u00d3n",
    "sg:phone":"+34 963 67 12 94",
    "sg:postcode":"46024",
    "sg:province":"Valencia",
    "wof:name":"Pe\u00f1a Taurina Juan Antonio Ruiz Espartaco",
    "wof:placetype":"venue"
},
  "geometry": {"coordinates":[-0.334374994,39.4499969482],"type":"Point"}
}