{
  "type": "Feature",
  "properties": {
    "addr:full":"Carrer de Sots-tinent Navarro, 22 Barcelona Barcelona 08002",
    "addr:housenumber":"22",
    "addr:postcode":"08002",
    "addr:street":"Carrer De Sots-Tinent Navarro",
    "iso:country":"ES",
    "sg:address":"Carrer de Sots-tinent Navarro, 22",
    "sg:city":"Barcelona",
    "sg:orig_category":"Bazares, Art\u00cdculos De Limpieza Y De Cocina (al Por Menor)",
    "sg:phone":"+34 933 15 24 09",
    "sg:postcode":"08002",
    "sg:province":"Barcelona",
    "wof:name":"Padilla Garcia Jose",
    "wof:placetype":"venue"
},
  "geometry": {"coordinates":[2.1797420979,41.3825454712],"type":"Point"}
}