{
  "type": "Feature",
  "properties": {
    "iso:country":"ES",
    "sg:address":"Calle de Doce De Octubre, 2",
    "sg:city":"Le\u00f3n",
    "sg:orig_category":"Fabricaci\u00d3n Y Refinado De Az\u00dacares",
    "sg:phone":"+34 987 22 62 62",
    "sg:postcode":"24010",
    "sg:province":"Le\u00f3n",
    "wof:name":"Azucares De Leon S. L.",
    "wof:placetype":"venue"
},
  "geometry": {"coordinates":[-5.589073658,42.605255127],"type":"Point"}
}