{
  "type": "Feature",
  "properties": {
    "iso:country":"ES",
    "sg:address":"Ptda Solades, 262",
    "sg:city":"Solades",
    "sg:orig_category":"Arboricultura Y Producci\u00d3n De Frutas",
    "sg:phone":"+34 964 52 08 49",
    "sg:postcode":"12540",
    "sg:province":"Castell\u00f3n",
    "wof:name":"Benjamin Beltran S.a.",
    "wof:placetype":"venue"
},
  "geometry": {"coordinates":[-0.0952939987,39.9453048706],"type":"Point"}
}