{
  "type": "Feature",
  "properties": {
    "addr:full":"Ctra Cebreros (de), 11 Tiemblo \u00c1vila 05270",
    "addr:housenumber":"11",
    "addr:postcode":"05270",
    "addr:street":"Ctra Cebreros De;A\u0301Vila",
    "iso:country":"ES",
    "sg:address":"Ctra Cebreros (de), 11",
    "sg:city":"Tiemblo",
    "sg:orig_category":"Electrodom\u00c9sticos (al Por Menor)",
    "sg:phone":"+34 918 62 71 28",
    "sg:postcode":"05270",
    "sg:province":"\u00c1vila",
    "wof:name":"Varas Gonzalez Arturo",
    "wof:placetype":"venue"
},
  "geometry": {"coordinates":[-4.4868559837,40.4094276428],"type":"Point"}
}