{
  "type": "Feature",
  "properties": {
    "iso:country":"ES",
    "sg:address":"Calle de Santa Teresa (de), 1",
    "sg:city":"Pinto",
    "sg:orig_category":"Sociedades, Compa\u00d1\u00cdas Aseguradoras",
    "sg:phone":"+34 916 91 59 25",
    "sg:postcode":"28320",
    "sg:province":"Madrid",
    "wof:name":"Salamanca Cazorla Carmen",
    "wof:placetype":"venue"
},
  "geometry": {"coordinates":[-3.697551012,40.2403640747],"type":"Point"}
}