{
  "type": "Feature",
  "properties": {
    "iso:country":"ES",
    "sg:address":"Calle de Barrio San Jose, 50",
    "sg:city":"Pobla Vallbona",
    "sg:orig_category":"Fabricaci\u00d3n De Harinas, S\u00c9molas, Productos De Elaboraci\u00d3n Del Grano",
    "sg:phone":"+34 961 66 13 23",
    "sg:postcode":"46185",
    "sg:province":"Valencia",
    "wof:name":"Raga Alejos Francisco",
    "wof:placetype":"venue"
},
  "geometry": {"coordinates":[-0.556186676,39.5946121216],"type":"Point"}
}