{
  "type": "Feature",
  "properties": {
    "iso:country":"ES",
    "sg:address":"Pase Perdiz De La, 2",
    "sg:city":"Cartaya",
    "sg:orig_category":"Asesor\u00cda De Formaci\u00d3n Y Gesti\u00d3n De Personal",
    "sg:phone":"+34 959 39 07 05",
    "sg:postcode":"21450",
    "sg:province":"Huelva",
    "wof:name":"Ayza Garcia Javier",
    "wof:placetype":"venue"
},
  "geometry": {"coordinates":[-7.1508507729,37.2814178467],"type":"Point"}
}