{
  "type": "Feature",
  "properties": {
    "addr:full":"Ptda Ciscar, S/n Canet Berenguer Valencia 46529",
    "addr:housenumber":"s / n",
    "addr:postcode":"46529",
    "addr:street":"Ptda Ciscar",
    "iso:country":"ES",
    "sg:address":"Ptda Ciscar, S/n",
    "sg:city":"Canet Berenguer",
    "sg:orig_category":"Cl\u00cdnicas M\u00c9dicas",
    "sg:phone":"+34 962 68 18 01",
    "sg:postcode":"46529",
    "sg:province":"Valencia",
    "wof:name":"Sometur S.a.",
    "wof:placetype":"venue"
},
  "geometry": {"coordinates":[-0.2035830021,39.6909866333],"type":"Point"}
}