{
  "type": "Feature",
  "properties": {
    "addr:full":"Calle de Mercado, S/n Navalmoral Mata C\u00e1ceres 10300",
    "addr:postcode":"10300",
    "addr:street":"Calle De Mercado S / N Navalmoral Mata Ca\u0301Ceres",
    "iso:country":"ES",
    "sg:address":"Calle de Mercado, S/n",
    "sg:city":"Navalmoral Mata",
    "sg:orig_category":"Ropa Para Se\u00d1oras Y Caballeros (al Por Menor)",
    "sg:phone":"+34 927 53 54 54",
    "sg:postcode":"10300",
    "sg:province":"C\u00e1ceres",
    "wof:name":"Trujillo Medina Juan Carlos",
    "wof:placetype":"venue"
},
  "geometry": {"coordinates":[-5.5387191772,39.8892631531],"type":"Point"}
}