{
  "type": "Feature",
  "properties": {
    "iso:country":"ES",
    "sg:address":"Afores, S/n",
    "sg:city":"Ma\u00e7anet Selva",
    "sg:orig_category":"Fabricaci\u00d3n Y Comercio De M\u00c1quinas",
    "sg:phone":"+34 972 16 54 50",
    "sg:postcode":"17412",
    "sg:province":"Girona",
    "wof:name":"Safam S.a.",
    "wof:placetype":"venue"
},
  "geometry": {"coordinates":[2.7342700958,41.7778396606],"type":"Point"}
}