{
  "type": "Feature",
  "properties": {
    "iso:country":"ES",
    "sg:address":"Cami Riu (del), 20",
    "sg:city":"Valls",
    "sg:orig_category":"Promotores Constructores",
    "sg:phone":"+34 977 61 37 73",
    "sg:postcode":"43800",
    "sg:province":"Tarragona",
    "wof:name":"Obres I Serveis Martinez Arlandes S.l.",
    "wof:placetype":"venue"
},
  "geometry": {"coordinates":[1.2404090166,41.2787208557],"type":"Point"}
}