{
  "type": "Feature",
  "properties": {
    "iso:country":"ES",
    "sg:address":"Calle de Doctor Garcia Mu\u00d1oz, 1",
    "sg:city":"Benavente",
    "sg:orig_category":"Zapatos (al Por Menor)",
    "sg:phone":"+34 980 63 11 64",
    "sg:postcode":"49600",
    "sg:province":"Zamora",
    "wof:name":"Llamas Aparicio Ana",
    "wof:placetype":"venue"
},
  "geometry": {"coordinates":[-5.6810851097,42.0011634827],"type":"Point"}
}