{
  "type": "Feature",
  "properties": {
    "addr:full":"Calle de Sirera Y Dara, 16 Novelda Alicante 03660",
    "addr:housenumber":"16",
    "addr:postcode":"03660",
    "addr:street":"Calle De Sirera Y Dara",
    "iso:country":"ES",
    "sg:address":"Calle de Sirera Y Dara, 16",
    "sg:city":"Novelda",
    "sg:orig_category":"Art\u00cdculos Funerarios (al Por Menor)",
    "sg:phone":"+34 965 60 15 75",
    "sg:postcode":"03660",
    "sg:province":"Alicante",
    "wof:name":"Funeraria Santa Maria Magdalena S.l.",
    "wof:placetype":"venue"
},
  "geometry": {"coordinates":[-0.7645329833,38.3864707947],"type":"Point"}
}