{
  "type": "Feature",
  "properties": {
    "addr:full":"Calle de Almibar (del), 21 Aranjuez Madrid 28300",
    "addr:housenumber":"21",
    "addr:postcode":"28300",
    "addr:street":"Calle De Almibar Del",
    "iso:country":"ES",
    "sg:address":"Calle de Almibar (del), 21",
    "sg:city":"Aranjuez",
    "sg:orig_category":"Asesor\u00cda Sobre Comunicaci\u00d3n De Empresas",
    "sg:phone":"+34 918 92 23 73",
    "sg:postcode":"28300",
    "sg:province":"Madrid",
    "wof:name":"Galvez Castellanos Angel",
    "wof:placetype":"venue"
},
  "geometry": {"coordinates":[-3.6025595665,40.0341949463],"type":"Point"}
}