{
  "type": "Feature",
  "properties": {
    "iso:country":"ES",
    "sg:address":"Plaz Profesor Tamarit Olmos, 15",
    "sg:city":"Valencia",
    "sg:orig_category":"Peluqueros: De Se\u00d1oras",
    "sg:phone":"+34 963 60 17 45",
    "sg:postcode":"46010",
    "sg:province":"Valencia",
    "wof:name":"Del Valle Rey Maria Del Carmen",
    "wof:placetype":"venue"
},
  "geometry": {"coordinates":[-0.3624010086,39.4801254272],"type":"Point"}
}