{
  "type": "Feature",
  "properties": {
    "iso:country":"ES",
    "sg:address":"Calle de Fesa, S/n",
    "sg:city":"San Pio X",
    "sg:orig_category":"Papel (al Por Mayor)",
    "sg:phone":"+34 968 25 65 41",
    "sg:postcode":"30012",
    "sg:province":"Murcia",
    "wof:name":"Francisco Solaz Ordu\u00f1a Y Carmen Monzo Cerezo C.b.",
    "wof:placetype":"venue"
},
  "geometry": {"coordinates":[-1.1298867464,37.9834747314],"type":"Point"}
}