{
  "type": "Feature",
  "properties": {
    "iso:country":"ES",
    "sg:address":"Av Euskadi, 10",
    "sg:city":"Jonquera",
    "sg:orig_category":"Fabrica De Cer\u00c1micas",
    "sg:phone":"+34 972 55 55 70",
    "sg:postcode":"17700",
    "sg:province":"Girona",
    "wof:name":"Som Ceramica S.l.",
    "wof:placetype":"venue"
},
  "geometry": {"coordinates":[2.8806200027,42.3981361389],"type":"Point"}
}