{
  "type": "Feature",
  "properties": {
    "addr:full":"Poli Poligono Industrial De Quintos, 6 Fontanar De Quintos C\u00f3rdoba 14710",
    "addr:housenumber":"6",
    "addr:postcode":"14710",
    "addr:street":"Poligono Industrial De Quintos",
    "iso:country":"ES",
    "sg:address":"Poli Poligono Industrial De Quintos, 6",
    "sg:city":"Fontanar De Quintos",
    "sg:orig_category":"Asesor\u00cda Para La Organizaci\u00d3n Y Gesti\u00d3n Del Transporte",
    "sg:phone":"+34 957 32 46 13",
    "sg:postcode":"14710",
    "sg:province":"C\u00f3rdoba",
    "wof:name":"Cargo Suriberica S.l.",
    "wof:placetype":"venue"
},
  "geometry": {"coordinates":[-4.9146289825,37.8490753174],"type":"Point"}
}