{
  "type": "Feature",
  "properties": {
    "addr:full":"Calle de Almogavares, 2 Huesca Huesca 22002",
    "addr:housenumber":"2",
    "addr:postcode":"22002",
    "addr:street":"Calle De Almogavares",
    "iso:country":"ES",
    "sg:address":"Calle de Almogavares, 2",
    "sg:city":"Huesca",
    "sg:orig_category":"Empleado Administrativo",
    "sg:phone":"+34 974 21 25 13",
    "sg:postcode":"22002",
    "sg:province":"Huesca",
    "wof:name":"Ardanuy Ardanuy Ramon",
    "wof:placetype":"venue"
},
  "geometry": {"coordinates":[-0.411947608,42.1358222961],"type":"Point"}
}