{
  "type": "Feature",
  "properties": {
    "iso:country":"ES",
    "sg:address":"Calle de Perdomo, 6",
    "sg:city":"Palmas De Gran Canaria",
    "sg:orig_category":"Centros Empresariales",
    "sg:phone":"+34 928 43 27 83",
    "sg:postcode":"35002",
    "sg:province":"Las Palmas",
    "wof:name":"Gestion De Librerias Canarias S.l.",
    "wof:placetype":"venue"
},
  "geometry": {"coordinates":[-15.4168386459,28.1066627502],"type":"Point"}
}