{
  "type": "Feature",
  "properties": {
    "addr:full":"Calle de Atocha, 62 Madrid Madrid 28012",
    "addr:housenumber":"62",
    "addr:postcode":"madrid;28012",
    "addr:street":"Calle De Atocha",
    "iso:country":"ES",
    "sg:address":"Calle de Atocha, 62",
    "sg:city":"Madrid",
    "sg:orig_category":"Cuchiller\u00cda (al Por Menor)",
    "sg:phone":"+34 913 69 34 95",
    "sg:postcode":"28012",
    "sg:province":"Madrid",
    "wof:name":"Vi\u00f1as Simarro Arturo",
    "wof:placetype":"venue"
},
  "geometry": {"coordinates":[-3.6982359886,40.4118728638],"type":"Point"}
}