{
  "type": "Feature",
  "properties": {
    "iso:country":"ES",
    "sg:address":"Carr Major, 14",
    "sg:city":"Castellfollit Roca",
    "sg:orig_category":"Ingenier\u00cda, Centros De Estudios (industria)",
    "sg:phone":"+34 972 29 45 62",
    "sg:postcode":"17856",
    "sg:province":"Girona",
    "sg:website":"www.tcore.net",
    "wof:name":"Tcore Desings S.l.",
    "wof:placetype":"venue"
},
  "geometry": {"coordinates":[2.5282709599,42.2711982727],"type":"Point"}
}