{
  "type": "Feature",
  "properties": {
    "addr:full":"Calle de Doctor Manuel Perez Bryan, 3 Malaga M\u00e1laga 29005",
    "addr:housenumber":"3",
    "addr:postcode":"29005",
    "addr:street":"Calle De Doctor Manuel Perez Bryan;Ma\u0301Laga",
    "iso:country":"ES",
    "sg:address":"Calle de Doctor Manuel Perez Bryan, 3",
    "sg:city":"Malaga",
    "sg:orig_category":"Abogados",
    "sg:phone":"+34 952 06 11 24",
    "sg:postcode":"29005",
    "sg:province":"M\u00e1laga",
    "wof:name":"Martin Alonso Abogados S.l.",
    "wof:placetype":"venue"
},
  "geometry": {"coordinates":[-4.421995163,36.7199554443],"type":"Point"}
}