{
  "type": "Feature",
  "properties": {
    "addr:full":"Calle de Gutierrez Herrero De, 48 Aviles Asturias 33402",
    "addr:housenumber":"48",
    "addr:postcode":"33402",
    "addr:street":"Calle De Gutierrez Herrero De",
    "iso:country":"ES",
    "sg:address":"Calle de Gutierrez Herrero De, 48",
    "sg:city":"Aviles",
    "sg:orig_category":"Farmacias",
    "sg:phone":"+34 985 54 33 38",
    "sg:postcode":"33402",
    "sg:province":"Asturias",
    "wof:name":"Gonzalez Suarez Maria Isabel",
    "wof:placetype":"venue"
},
  "geometry": {"coordinates":[-5.9162683487,43.5487594604],"type":"Point"}
}