{
  "type": "Feature",
  "properties": {
    "iso:country":"ES",
    "sg:address":"Calle de Fabrica Vieja, 4",
    "sg:city":"Granada",
    "sg:orig_category":"Talleres: Ropa A Medida",
    "sg:phone":"+34 958 27 96 79",
    "sg:postcode":"18002",
    "sg:province":"Granada",
    "wof:name":"Diaz Jimenez Emilio",
    "wof:placetype":"venue"
},
  "geometry": {"coordinates":[-3.6021900177,37.1764030457],"type":"Point"}
}