{
  "type": "Feature",
  "properties": {
    "addr:full":"Avda Madro\u00d1os, 23 Madrid Madrid 28043",
    "addr:housenumber":"23",
    "addr:postcode":"madrid;28043",
    "addr:street":"Avda Madron\u0303Os",
    "iso:country":"ES",
    "sg:address":"Avda Madro\u00d1os, 23",
    "sg:city":"Madrid",
    "sg:orig_category":"Asociaciones Y Clubs Deportivos",
    "sg:phone":"+34 913 00 02 58",
    "sg:postcode":"28043",
    "sg:province":"Madrid",
    "wof:name":"Colegio Club Natacion Jimenez",
    "wof:placetype":"venue"
},
  "geometry": {"coordinates":[-3.645414114,40.4553184509],"type":"Point"}
}