{
  "type": "Feature",
  "properties": {
    "iso:country":"ES",
    "sg:address":"S. Anton Auzoa, 14",
    "sg:city":"Bergara",
    "sg:orig_category":"Material Y Suministros Para Horticultura, Arboricultura",
    "sg:phone":"+34 943 76 29 55",
    "sg:postcode":"20570",
    "sg:province":"Guip\u00f9zcoa",
    "wof:name":"Elcoro-berecibar Odriozola Emeterio",
    "wof:placetype":"venue"
},
  "geometry": {"coordinates":[-2.4233329296,43.1255264282],"type":"Point"}
}