{
  "type": "Feature",
  "properties": {
    "addr:full":"Calle de Jose Payan, 39 Camas Sevilla 41900",
    "addr:housenumber":"39",
    "addr:postcode":"41900",
    "addr:street":"Calle De Jose Payan",
    "iso:country":"ES",
    "sg:address":"Calle de Jose Payan, 39",
    "sg:city":"Camas",
    "sg:orig_category":"Farmacias",
    "sg:phone":"+34 954 39 06 44",
    "sg:postcode":"41900",
    "sg:province":"Sevilla",
    "wof:name":"Garcia Beltran C.b.",
    "wof:placetype":"venue"
},
  "geometry": {"coordinates":[-6.0348348618,37.3989944458],"type":"Point"}
}