{
  "type": "Feature",
  "properties": {
    "iso:country":"ES",
    "sg:address":"Carrer de Sant Antoni Maria Claret, 6",
    "sg:city":"Olot",
    "sg:orig_category":"Ense\u00d1anza: Peluquer\u00cda Est\u00c9tica",
    "sg:phone":"+34 972 26 68 91",
    "sg:postcode":"17800",
    "sg:province":"Girona",
    "wof:name":"Escola Noves Tendencies S.l",
    "wof:placetype":"venue"
},
  "geometry": {"coordinates":[2.4809939861,42.1831474304],"type":"Point"}
}