{
  "type": "Feature",
  "properties": {
    "iso:country":"ES",
    "sg:address":"Ctra General Del Norte, 185",
    "sg:city":"Cantillo",
    "sg:orig_category":"Restaurantes",
    "sg:phone":"+34 922 56 03 37",
    "sg:postcode":"38350",
    "sg:province":"Santa Cruz De Tenerife",
    "wof:name":"Iglesias Rivera Antonio",
    "wof:placetype":"venue"
},
  "geometry": {"coordinates":[-16.4174289703,28.4756546021],"type":"Point"}
}