{
  "type": "Feature",
  "properties": {
    "addr:full":"Ctra Daimiel, 40 Bola\u00e7os De Calatrava Ciudad Real 13260",
    "addr:housenumber":"40",
    "addr:postcode":"13260",
    "addr:street":"Ctra Daimiel",
    "iso:country":"ES",
    "sg:address":"Ctra Daimiel, 40",
    "sg:city":"Bola\u00e7os De Calatrava",
    "sg:orig_category":"Mec\u00c1nico Del Autom\u00d3vil",
    "sg:phone":"+34 926 87 05 42",
    "sg:postcode":"13260",
    "sg:province":"Ciudad Real",
    "wof:name":"Arreaza Paredes Antonio",
    "wof:placetype":"venue"
},
  "geometry": {"coordinates":[-3.9272627831,38.9860954285],"type":"Point"}
}