{
  "type": "Feature",
  "properties": {
    "iso:country":"ES",
    "sg:address":"Pase Canteras Las, 32",
    "sg:city":"Palmas De Gran Canaria",
    "sg:orig_category":"Abogados",
    "sg:phone":"+34 928 26 51 57",
    "sg:postcode":"35007",
    "sg:province":"Las Palmas",
    "wof:name":"Cuyas Hidalgo Cayetano",
    "wof:placetype":"venue"
},
  "geometry": {"coordinates":[-15.435631752,28.1405677795],"type":"Point"}
}