{
  "type": "Feature",
  "properties": {
    "iso:country":"ES",
    "sg:address":"Calle de Santa Catalina, 8",
    "sg:city":"Segovia",
    "sg:orig_category":"Peluquer\u00cdas, Peluquer\u00cda Mixta",
    "sg:phone":"+34 921 44 03 66",
    "sg:postcode":"40003",
    "sg:province":"Segovia",
    "wof:name":"Esteban Romero Maria",
    "wof:placetype":"venue"
},
  "geometry": {"coordinates":[-4.1122641563,40.9516296387],"type":"Point"}
}