{
  "type": "Feature",
  "properties": {
    "addr:full":"Calle de Gran Via, 17 Zaragoza Zaragoza 50006",
    "addr:housenumber":"17",
    "addr:postcode":"50006",
    "addr:street":"Calle De Gran Via",
    "iso:country":"ES",
    "sg:address":"Calle de Gran Via, 17",
    "sg:city":"Zaragoza",
    "sg:orig_category":"Asistencia Social",
    "sg:phone":"+34 976 48 49 49",
    "sg:postcode":"50006",
    "sg:province":"Zaragoza",
    "wof:name":"Asociacion Celiaca Aragonesa",
    "wof:placetype":"venue"
},
  "geometry": {"coordinates":[-0.8879138827,41.6460113525],"type":"Point"}
}