{
  "type": "Feature",
  "properties": {
    "addr:full":"Carrer de Bejar, 39 Barcelona Barcelona 08014",
    "addr:housenumber":"39",
    "addr:postcode":"08014",
    "addr:street":"Carrer De Bejar",
    "iso:country":"ES",
    "sg:address":"Carrer de Bejar, 39",
    "sg:city":"Barcelona",
    "sg:orig_category":"Construcci\u00d3n Mec\u00c1nica",
    "sg:phone":"+34 933 25 69 98",
    "sg:postcode":"08014",
    "sg:province":"Barcelona",
    "wof:name":"Mecanics Creatius S.l.",
    "wof:placetype":"venue"
},
  "geometry": {"coordinates":[2.145334959,41.3769607544],"type":"Point"}
}