{
  "type": "Feature",
  "properties": {
    "iso:country":"ES",
    "sg:address":"Calle de Doctor Vallejo, 12",
    "sg:city":"Madrid",
    "sg:orig_category":"Peluqueros: De Se\u00d1oras",
    "sg:phone":"+34 914 07 97 16",
    "sg:postcode":"28027",
    "sg:province":"Madrid",
    "wof:name":"Hinojosa Vera Josefa",
    "wof:placetype":"venue"
},
  "geometry": {"coordinates":[-3.6437935829,40.4369316101],"type":"Point"}
}