{
  "type": "Feature",
  "properties": {
    "iso:country":"ES",
    "sg:address":"Calle de Real, 41",
    "sg:city":"Almeria",
    "sg:orig_category":"Molduras, Junquillos, Listones Y Molduras Perforadas",
    "sg:phone":"+34 950 24 24 07",
    "sg:postcode":"04001",
    "sg:province":"Almer\u00eda",
    "wof:name":"Yelamos Sola Antonio",
    "wof:placetype":"venue"
},
  "geometry": {"coordinates":[-2.4655489922,36.8389663696],"type":"Point"}
}