{
  "type": "Feature",
  "properties": {
    "addr:full":"Atva. Zaragoza-logro\u00f1o, 4 Casetas Zaragoza 50620",
    "addr:housenumber":"4",
    "addr:postcode":"50620",
    "addr:street":"Zaragoza-Logron\u0303O",
    "iso:country":"ES",
    "sg:address":"Atva. Zaragoza-logro\u00f1o, 4",
    "sg:city":"Casetas",
    "sg:orig_category":"Agencias Y Agentes Comerciales, Representantes",
    "sg:phone":"+34 976 77 46 37",
    "sg:postcode":"50620",
    "sg:province":"Zaragoza",
    "wof:name":"Lorente Martinez Ana",
    "wof:placetype":"venue"
},
  "geometry": {"coordinates":[-1.0322844982,41.7186965942],"type":"Point"}
}