{
  "type": "Feature",
  "properties": {
    "iso:country":"ES",
    "sg:address":"Calle de Regalado, 4",
    "sg:city":"Valladolid",
    "sg:orig_category":"Mercer\u00cda, Lencer\u00cda (al Por Menor)",
    "sg:phone":"+34 983 30 20 32",
    "sg:postcode":"47001",
    "sg:province":"Valladolid",
    "wof:name":"Miguel Angel Sanchez Rodriguez Y Leopoldo Adiego Arranz C.b.",
    "wof:placetype":"venue"
},
  "geometry": {"coordinates":[-4.7260637283,41.6514968872],"type":"Point"}
}