{
  "type": "Feature",
  "properties": {
    "addr:full":"Calle de Izer, 15 Amorebieta Vizcaya 48340",
    "addr:housenumber":"15",
    "addr:postcode":"48340",
    "addr:street":"Calle De Izer",
    "iso:country":"ES",
    "sg:address":"Calle de Izer, 15",
    "sg:city":"Amorebieta",
    "sg:orig_category":"Plomeros",
    "sg:phone":"+34 946 73 21 18",
    "sg:postcode":"48340",
    "sg:province":"Vizcaya",
    "wof:name":"Francisco Casasaltas Tinoco Y Manuela Lopez Cuartero.c.b",
    "wof:placetype":"venue"
},
  "geometry": {"coordinates":[-2.7349100113,43.2233352661],"type":"Point"}
}