{
  "type": "Feature",
  "properties": {
    "iso:country":"ES",
    "sg:address":"Avda Canarias, 1",
    "sg:city":"Vecindario",
    "sg:orig_category":"M\u00c9dicos: Evaluaci\u00d3n Y Tratamiento Del Dolor",
    "sg:phone":"+34 928 14 97 01",
    "sg:postcode":"35110",
    "sg:province":"Las Palmas",
    "wof:name":"Instituto Odontologico Canario S.l.",
    "wof:placetype":"venue"
},
  "geometry": {"coordinates":[-15.4408693314,27.8513793945],"type":"Point"}
}