{
  "type": "Feature",
  "properties": {
    "iso:country":"ES",
    "sg:address":"Calle de Garay Juan De, 2",
    "sg:city":"Bilbao",
    "sg:orig_category":"Farmacias",
    "sg:phone":"+34 944 43 35 49",
    "sg:postcode":"48003",
    "sg:province":"Vizcaya",
    "wof:name":"Ca\u00f1as Capellan Maria Teresa",
    "wof:placetype":"venue"
},
  "geometry": {"coordinates":[-2.9334709644,43.2561149597],"type":"Point"}
}