{
  "type": "Feature",
  "properties": {
    "iso:country":"ES",
    "sg:address":"Carr Marques De Solferit, 2",
    "sg:city":"Quart Poblet",
    "sg:orig_category":"Mercer\u00cda, Lencer\u00cda (al Por Menor)",
    "sg:phone":"+34 961 54 30 73",
    "sg:postcode":"46930",
    "sg:province":"Valencia",
    "wof:name":"Lola Ruiz Morales S.l.",
    "wof:placetype":"venue"
},
  "geometry": {"coordinates":[-0.4381139874,39.4824256897],"type":"Point"}
}