{
  "type": "Feature",
  "properties": {
    "addr:full":"Calle de Mina Las Musas, 6 Azuaga Badajoz 06920",
    "addr:housenumber":"6",
    "addr:postcode":"06920",
    "addr:street":"Calle De Mina Las Musas",
    "iso:country":"ES",
    "sg:address":"Calle de Mina Las Musas, 6",
    "sg:city":"Azuaga",
    "sg:orig_category":"Plomeros",
    "sg:phone":"+34 924 89 19 36",
    "sg:postcode":"06920",
    "sg:province":"Badajoz",
    "wof:name":"Comercial Zatira S.l",
    "wof:placetype":"venue"
},
  "geometry": {"coordinates":[-5.6924037933,38.260799408],"type":"Point"}
}