{
  "type": "Feature",
  "properties": {
    "iso:country":"ES",
    "sg:address":"Plaz Fuente, 7",
    "sg:city":"Navahermosa",
    "sg:orig_category":"Equipo De Refrigeraci\u00d3n Industrial",
    "sg:phone":"+34 925 42 90 05",
    "sg:postcode":"45150",
    "sg:province":"Toledo",
    "wof:name":"Electromecanica Vicfrio S.l.",
    "wof:placetype":"venue"
},
  "geometry": {"coordinates":[-4.472495079,39.6325378418],"type":"Point"}
}