{
  "type": "Feature",
  "properties": {
    "iso:country":"ES",
    "sg:address":"Behobia Au., 17",
    "sg:city":"Irun",
    "sg:orig_category":"Molduras, Junquillos, Listones Y Molduras Perforadas",
    "sg:phone":"+34 943 62 10 26",
    "sg:postcode":"20305",
    "sg:province":"Guip\u00f9zcoa",
    "wof:name":"Elosua Urbieta Jose",
    "wof:placetype":"venue"
},
  "geometry": {"coordinates":[-1.7587490082,43.3390426636],"type":"Point"}
}