{
  "type": "Feature",
  "properties": {
    "addr:full":"Ctra Gral, S/n Villanueva Cantabria 39690",
    "addr:postcode":"39690",
    "addr:street":"Ctra Gral S / N",
    "iso:country":"ES",
    "sg:address":"Ctra Gral, S/n",
    "sg:city":"Villanueva",
    "sg:orig_category":"Alimentaci\u00d3n Animal (fabricaci\u00d3n, Al Por Mayor)",
    "sg:phone":"+34 942 55 52 23",
    "sg:postcode":"39690",
    "sg:province":"Cantabria",
    "wof:name":"Gomez Crespo Fernando",
    "wof:placetype":"venue"
},
  "geometry": {"coordinates":[-3.860033989,43.3670692444],"type":"Point"}
}