{
  "type": "Feature",
  "properties": {
    "addr:full":"Calle de Cervantes, 7 Merida Badajoz 06800",
    "addr:housenumber":"7",
    "addr:postcode":"06800",
    "addr:street":"Calle De Cervantes",
    "iso:country":"ES",
    "sg:address":"Calle de Cervantes, 7",
    "sg:city":"Merida",
    "sg:orig_category":"Asociaciones Humanitarias, De Cooperaci\u00d3n, De Acci\u00d3n Social",
    "sg:phone":"+34 924 31 03 00",
    "sg:postcode":"06800",
    "sg:province":"Badajoz",
    "wof:name":"Asociaion Deficientes Auditivos De Badajoz",
    "wof:placetype":"venue"
},
  "geometry": {"coordinates":[-6.3851943016,38.8869895935],"type":"Point"}
}