{
  "type": "Feature",
  "properties": {
    "iso:country":"ES",
    "sg:address":"Carrer de Pi I Margall, 22",
    "sg:city":"Barcelona",
    "sg:orig_category":"Abogados",
    "sg:phone":"+34 932 85 35 00",
    "sg:postcode":"08025",
    "sg:province":"Barcelona",
    "wof:name":"Argiz Fernandez Juan Manuel",
    "wof:placetype":"venue"
},
  "geometry": {"coordinates":[2.1632835865,41.4065322876],"type":"Point"}
}