{
  "type": "Feature",
  "properties": {
    "addr:full":"Calle de Jose Maria Mortes Lerma, 30 Valencia Valencia 46014",
    "addr:housenumber":"30",
    "addr:postcode":"46014",
    "addr:street":"Calle De Jose Maria Mortes Lerma",
    "iso:country":"ES",
    "sg:address":"Calle de Jose Maria Mortes Lerma, 30",
    "sg:city":"Valencia",
    "sg:orig_category":"Doctores En Medicina",
    "sg:phone":"+34 963 78 66 34",
    "sg:postcode":"46014",
    "sg:province":"Valencia",
    "wof:name":"Asociacion Juvenil Club Dardo",
    "wof:placetype":"venue"
},
  "geometry": {"coordinates":[-0.4019697011,39.4629135132],"type":"Point"}
}