{
  "type": "Feature",
  "properties": {
    "addr:full":"Calle de Urquiza, 16 Sevilla Sevilla 41003",
    "addr:housenumber":"16",
    "addr:postcode":"41003",
    "addr:street":"Calle De Urquiza",
    "iso:country":"ES",
    "sg:address":"Calle de Urquiza, 16",
    "sg:city":"Sevilla",
    "sg:orig_category":"Cursos Particulares, Asistencia Escolar",
    "sg:phone":"+34 954 41 73 38",
    "sg:postcode":"41003",
    "sg:province":"Sevilla",
    "wof:name":"Martin Rodriguez Celso",
    "wof:placetype":"venue"
},
  "geometry": {"coordinates":[-5.9796280861,37.3942489624],"type":"Point"}
}