{
  "type": "Feature",
  "properties": {
    "addr:full":"Calle de Velazquez, S/n Huecas Toledo 45511",
    "addr:housenumber":"s",
    "addr:postcode":"45511",
    "addr:street":"Calle De Velazquez;/ N Huecas",
    "iso:country":"ES",
    "sg:address":"Calle de Velazquez, S/n",
    "sg:city":"Huecas",
    "sg:orig_category":"Animales (al Por Menor)",
    "sg:phone":"+34 925 73 02 49",
    "sg:postcode":"45511",
    "sg:province":"Toledo",
    "wof:name":"Especialidades Energeticas S.l.",
    "wof:placetype":"venue"
},
  "geometry": {"coordinates":[-4.2035741806,40.0326538086],"type":"Point"}
}