{
  "type": "Feature",
  "properties": {
    "addr:full":"Urb Casablanca, 85 Casablanca Sevilla 41710",
    "addr:housenumber":"85",
    "addr:postcode":"41710",
    "addr:street":"Urb Casablanca",
    "iso:country":"ES",
    "sg:address":"Urb Casablanca, 85",
    "sg:city":"Casablanca",
    "sg:orig_category":"Plomeros",
    "sg:phone":"+34 954 86 01 63",
    "sg:postcode":"41710",
    "sg:province":"Sevilla",
    "wof:name":"Garrido Castro Jose",
    "wof:placetype":"venue"
},
  "geometry": {"coordinates":[-5.779173851,37.184223175],"type":"Point"}
}