{
  "type": "Feature",
  "properties": {
    "addr:full":"Calle de Txalaparta, 2 Vitoria-gasteiz \u00c1lava 01006",
    "addr:housenumber":"2",
    "addr:postcode":"01006",
    "addr:street":"Calle De Txalaparta",
    "iso:country":"ES",
    "sg:address":"Calle de Txalaparta, 2",
    "sg:city":"Vitoria-gasteiz",
    "sg:classifiers":[
        {
            "category":"Personal",
            "subcategory":"Barber",
            "type":"Services"
        }
    ],
    "sg:phone":"+34 945 14 65 78",
    "sg:postcode":"01006",
    "sg:province":"\u00c1lava",
    "sg:tags":[
        "caballeros",
        "de",
        "peluqueros"
    ],
    "wof:name":"Tejedor Trejo Javier",
    "wof:placetype":"venue"
},
  "geometry": {"coordinates":[-2.6652560234,42.8375968933],"type":"Point"}
}