{
  "type": "Feature",
  "properties": {
    "addr:full":"Rua Villar, 56 Ourense Ourense 32005",
    "addr:housenumber":"56",
    "addr:postcode":"32005",
    "addr:street":"Rua Villar",
    "iso:country":"ES",
    "sg:address":"Rua Villar, 56",
    "sg:city":"Ourense",
    "sg:orig_category":"Zapatos (al Por Menor)",
    "sg:phone":"+34 988 24 72 79",
    "sg:postcode":"32005",
    "sg:province":"Ourense",
    "wof:name":"Cacheiro Sanmiguel Angel",
    "wof:placetype":"venue"
},
  "geometry": {"coordinates":[-7.8649687767,42.3321113586],"type":"Point"}
}