{
  "type": "Feature",
  "properties": {
    "addr:full":"Calle de Lopan, 83 Almeria Almer\u00eda 04008",
    "addr:housenumber":"83",
    "addr:postcode":"04008",
    "addr:street":"Calle De Lopan",
    "iso:country":"ES",
    "sg:address":"Calle de Lopan, 83",
    "sg:city":"Almeria",
    "sg:orig_category":"Centros M\u00c9dicos Y Sociales, Dispensarios",
    "sg:phone":"+34 950 26 48 86",
    "sg:postcode":"04008",
    "sg:province":"Almer\u00eda",
    "wof:name":"Guil Salvador Jose Manuel",
    "wof:placetype":"venue"
},
  "geometry": {"coordinates":[-2.4565498829,36.8494796753],"type":"Point"}
}