{
  "type": "Feature",
  "properties": {
    "addr:full":"Barr Cristo (el), S/n Entrambasaguas Cantabria 39715",
    "addr:housenumber":"s",
    "addr:postcode":"39715",
    "addr:street":"/ N",
    "iso:country":"ES",
    "sg:address":"Barr Cristo (el), S/n",
    "sg:city":"Entrambasaguas",
    "sg:orig_category":"Centros De Educaci\u00d3n Especial",
    "sg:phone":"+34 942 52 40 37",
    "sg:postcode":"39715",
    "sg:province":"Cantabria",
    "wof:name":"Ayuntamiento De Entrambasaguas",
    "wof:placetype":"venue"
},
  "geometry": {"coordinates":[-3.6833701134,43.3752861023],"type":"Point"}
}