{
  "type": "Feature",
  "properties": {
    "iso:country":"ES",
    "sg:address":"Laias, S/n",
    "sg:city":"Laias",
    "sg:orig_category":"Venta, Instalaci\u00d3n De Calefacci\u00d3n",
    "sg:phone":"+34 988 28 00 92",
    "sg:postcode":"32459",
    "sg:province":"Ourense",
    "wof:name":"Pazos Pousa Remigio",
    "wof:placetype":"venue"
},
  "geometry": {"coordinates":[-8.0925722122,42.2746047974],"type":"Point"}
}