{
  "type": "Feature",
  "properties": {
    "addr:full":"Calle de Fernando Casariego, 39 Langreo Asturias 33930",
    "addr:housenumber":"39",
    "addr:postcode":"33930",
    "addr:street":"Calle De Fernando Casariego",
    "iso:country":"ES",
    "sg:address":"Calle de Fernando Casariego, 39",
    "sg:city":"Langreo",
    "sg:orig_category":"Agentes, Concesionarios Y Sucursales De Veh\u00cdculos",
    "sg:phone":"+34 985 67 57 23",
    "sg:postcode":"33930",
    "sg:province":"Asturias",
    "wof:name":"Juber Motor S.l.",
    "wof:placetype":"venue"
},
  "geometry": {"coordinates":[-5.6966438293,43.3077964783],"type":"Point"}
}