{
  "type": "Feature",
  "properties": {
    "addr:full":"Calle de Islas Cies, 18 Madrid Madrid 28035",
    "addr:housenumber":"18",
    "addr:postcode":"madrid;28035",
    "addr:street":"Calle De Islas Cies",
    "iso:country":"ES",
    "sg:address":"Calle de Islas Cies, 18",
    "sg:city":"Madrid",
    "sg:orig_category":"Doctores En Medicina",
    "sg:phone":"+34 917 39 50 51",
    "sg:postcode":"28035",
    "sg:province":"Madrid",
    "wof:name":"Vasco Merino Maria Del Pilar",
    "wof:placetype":"venue"
},
  "geometry": {"coordinates":[-3.7192080021,40.4805526733],"type":"Point"}
}