{
  "type": "Feature",
  "properties": {
    "iso:country":"ES",
    "sg:address":"Pase Velasco (el), 33",
    "sg:city":"Lierganes",
    "sg:orig_category":"Comerciantes Al Por Mayor De Vinos, Licores Y Alcoholes",
    "sg:phone":"+34 942 52 82 75",
    "sg:postcode":"39727",
    "sg:province":"Cantabria",
    "wof:name":"Herrero Gomez Marcos",
    "wof:placetype":"venue"
},
  "geometry": {"coordinates":[-3.7443940639,43.3425941467],"type":"Point"}
}