{
  "type": "Feature",
  "properties": {
    "iso:country":"ES",
    "sg:address":"Calle de Colegio, 2",
    "sg:city":"Portillo",
    "sg:orig_category":"Transportes Por V\u00cdas Navegables",
    "sg:phone":"+34 983 55 64 20",
    "sg:postcode":"47160",
    "sg:province":"Valladolid",
    "wof:name":"Fernandez Pilar Jesus",
    "wof:placetype":"venue"
},
  "geometry": {"coordinates":[-4.5906424522,41.4791641235],"type":"Point"}
}