{
  "type": "Feature",
  "properties": {
    "addr:full":"Alcazaba Zoco, S/n Manga Mar Menor Murcia 30380",
    "addr:housenumber":"s / n",
    "addr:postcode":"30380",
    "iso:country":"ES",
    "sg:address":"Alcazaba Zoco, S/n",
    "sg:city":"Manga Mar Menor",
    "sg:orig_category":"Artesan\u00cda",
    "sg:phone":"+34 968 14 22 49",
    "sg:postcode":"30380",
    "sg:province":"Murcia",
    "wof:name":"Hernandez Lopez Roberto",
    "wof:placetype":"venue"
},
  "geometry": {"coordinates":[-0.7281540036,37.6686553955],"type":"Point"}
}