{
  "type": "Feature",
  "properties": {
    "iso:country":"ES",
    "sg:address":"Calle de Puerto De La Bonaigua, 30",
    "sg:city":"Madrid",
    "sg:orig_category":"Caf\u00c9s, Bares, Cervecer\u00cdas",
    "sg:phone":"+34 914 78 24 95",
    "sg:postcode":"28018",
    "sg:province":"Madrid",
    "wof:name":"Los Amigos C.b.",
    "wof:placetype":"venue"
},
  "geometry": {"coordinates":[-3.6645140648,40.3873405457],"type":"Point"}
}