{
  "type": "Feature",
  "properties": {
    "addr:full":"Pl Tereses (de Les), 26 Mataro Barcelona 08302",
    "addr:housenumber":"26",
    "addr:postcode":"08302",
    "addr:street":"Pl Tereses De Les",
    "iso:country":"ES",
    "sg:address":"Pl Tereses (de Les), 26",
    "sg:city":"Mataro",
    "sg:orig_category":"Importaci\u00d3n, Exportaci\u00d3n Y Comercios De Productos Textiles",
    "sg:phone":"+34 937 96 15 05",
    "sg:postcode":"08302",
    "sg:province":"Barcelona",
    "wof:name":"Gay De Vesa S.c.p.",
    "wof:placetype":"venue"
},
  "geometry": {"coordinates":[2.4419510365,41.5382728577],"type":"Point"}
}