{
  "type": "Feature",
  "properties": {
    "iso:country":"ES",
    "sg:address":"Calle de Prado, Del, 10",
    "sg:city":"Talavera Reina",
    "sg:orig_category":"Centros Comerciales Y Grandes Tiendas",
    "sg:phone":"+34 925 81 56 49",
    "sg:postcode":"45600",
    "sg:province":"Toledo",
    "wof:name":"La Vajilla S. L.",
    "wof:placetype":"venue"
},
  "geometry": {"coordinates":[-4.8326292038,39.9584884644],"type":"Point"}
}