{
  "type": "Feature",
  "properties": {
    "addr:full":"Calle de Calvario, 37 Burgos Burgos 09002",
    "addr:housenumber":"37",
    "addr:postcode":"09002",
    "addr:street":"Calle De Calvario",
    "iso:country":"ES",
    "sg:address":"Calle de Calvario, 37",
    "sg:city":"Burgos",
    "sg:orig_category":"Publicidad (soportes Y Gesti\u00d3n)",
    "sg:phone":"+34 947 26 08 00",
    "sg:postcode":"09002",
    "sg:province":"Burgos",
    "wof:name":"Garcia De Miguel Salvador",
    "wof:placetype":"venue"
},
  "geometry": {"coordinates":[-3.6959011555,42.334941864],"type":"Point"}
}