{
  "type": "Feature",
  "properties": {
    "addr:full":"Calle de Jose Silva, 11 Madrid Madrid 28043",
    "addr:housenumber":"11",
    "addr:postcode":"madrid;28043",
    "addr:street":"Calle De Jose Silva",
    "iso:country":"ES",
    "sg:address":"Calle de Jose Silva, 11",
    "sg:city":"Madrid",
    "sg:orig_category":"Centros Empresariales",
    "sg:phone":"+34 914 13 35 03",
    "sg:postcode":"28043",
    "sg:province":"Madrid",
    "wof:name":"Torres Fernandez Pablo",
    "wof:placetype":"venue"
},
  "geometry": {"coordinates":[-3.6576700211,40.455039978],"type":"Point"}
}