{
  "type": "Feature",
  "properties": {
    "addr:full":"Calle de Constitucion (de La), 124 Fuenlabrada Madrid 28946",
    "addr:housenumber":"124",
    "addr:postcode":"28946",
    "addr:street":"Calle De Constitucion De La",
    "iso:country":"ES",
    "sg:address":"Calle de Constitucion (de La), 124",
    "sg:city":"Fuenlabrada",
    "sg:orig_category":"Promotores Constructores",
    "sg:phone":"+34 916 06 85 78",
    "sg:postcode":"28946",
    "sg:province":"Madrid",
    "wof:name":"Julpermi Obras Y Construcciones S.l.",
    "wof:placetype":"venue"
},
  "geometry": {"coordinates":[-3.7702815533,40.2794647217],"type":"Point"}
}