{
  "type": "Feature",
  "properties": {
    "iso:country":"ES",
    "sg:address":"Calle de Pedro Coca, 12",
    "sg:city":"Albacete",
    "sg:orig_category":"Pod\u00d3logos: Pedicuros",
    "sg:phone":"+34 967 50 10 55",
    "sg:postcode":"02004",
    "sg:province":"Albacete",
    "wof:name":"Combadiera Colmenero Rafael",
    "wof:placetype":"venue"
},
  "geometry": {"coordinates":[-1.8605940342,38.9932632446],"type":"Point"}
}