{
  "type": "Feature",
  "properties": {
    "addr:full":"Calle de San Anton, 72 Parla Madrid 28980",
    "addr:housenumber":"72",
    "addr:postcode":"28980",
    "addr:street":"Calle De San Anton",
    "iso:country":"ES",
    "sg:address":"Calle de San Anton, 72",
    "sg:city":"Parla",
    "sg:orig_category":"Estilistas Y Estudios De Estilo De Corte Y Confecci\u00d3n",
    "sg:phone":"+34 916 99 73 33",
    "sg:postcode":"28980",
    "sg:province":"Madrid",
    "wof:name":"Confecciones Martinez Campos Sl",
    "wof:placetype":"venue"
},
  "geometry": {"coordinates":[-3.7676420212,40.2420387268],"type":"Point"}
}