{
  "type": "Feature",
  "properties": {
    "addr:full":"Calle de Maestro Priego Lopez, 27 Cordoba C\u00f3rdoba 14004",
    "addr:housenumber":"27",
    "addr:postcode":"14004",
    "addr:street":"Calle De Maestro Priego Lopez;Co\u0301Rdoba",
    "iso:country":"ES",
    "sg:address":"Calle de Maestro Priego Lopez, 27",
    "sg:city":"Cordoba",
    "sg:classifiers":[
        {
            "category":"Personal",
            "subcategory":"Barber",
            "type":"Services"
        }
    ],
    "sg:phone":"+34 957 41 23 91",
    "sg:postcode":"14004",
    "sg:province":"C\u00f3rdoba",
    "sg:tags":[
        "caballeros",
        "de",
        "peluqueros"
    ],
    "wof:name":"Mu\u00f1oz Estevez Jose",
    "wof:placetype":"venue"
},
  "geometry": {"coordinates":[-4.7908267975,37.8805007935],"type":"Point"}
}