{
  "type": "Feature",
  "properties": {
    "addr:full":"Avda Mogan (de), S/n Puerto Rico Las Palmas 35130",
    "addr:housenumber":"/ n",
    "addr:postcode":"35130",
    "addr:street":"Avda Mogan De S;Rico",
    "iso:country":"ES",
    "sg:address":"Avda Mogan (de), S/n",
    "sg:city":"Puerto Rico",
    "sg:orig_category":"Ense\u00d1anza, Formaci\u00d3n Profesional: Aprendizaje",
    "sg:phone":"+34 928 56 00 29",
    "sg:postcode":"35130",
    "sg:province":"Las Palmas",
    "wof:name":"Ayuntamiento De Mogan",
    "wof:placetype":"venue"
},
  "geometry": {"coordinates":[-15.7155609131,27.7860527039],"type":"Point"}
}