{
  "type": "Feature",
  "properties": {
    "iso:country":"ES",
    "sg:address":"Avda Valladolid, 41",
    "sg:city":"Valencia",
    "sg:orig_category":"Carnicer\u00cdas, Carnicer\u00cdas",
    "sg:phone":"+34 963 62 77 60",
    "sg:postcode":"46020",
    "sg:province":"Valencia",
    "wof:name":"Guillot Estarlich Enrique",
    "wof:placetype":"venue"
},
  "geometry": {"coordinates":[-0.3608416915,39.489238739],"type":"Point"}
}