{
  "type": "Feature",
  "properties": {
    "addr:full":"Ctra Toledo Oca\u00d1a, S/n Poligono Sta M. De Benquerencia Toledo 45007",
    "addr:housenumber":"s / n",
    "addr:postcode":"45007",
    "addr:street":"Ctra Toledo Ocan\u0303A;Poligono Sta M. De Benquerencia",
    "iso:country":"ES",
    "sg:address":"Ctra Toledo Oca\u00d1a, S/n",
    "sg:city":"Poligono Sta M. De Benquerencia",
    "sg:orig_category":"Art\u00cdculos De Regalo (al Por Menor)",
    "sg:phone":"+34 925 23 13 23",
    "sg:postcode":"45007",
    "sg:province":"Toledo",
    "wof:name":"Fraile Serrano Manuel",
    "wof:placetype":"venue"
},
  "geometry": {"coordinates":[-4.0244760513,39.8567771912],"type":"Point"}
}