{
  "type": "Feature",
  "properties": {
    "addr:full":"Calle de Dehesa De Mari-martin, 11 Dehesa De Marimartin Madrid 28600",
    "addr:housenumber":"11",
    "addr:postcode":"28600",
    "addr:street":"Calle De Dehesa;Mari-Martin",
    "iso:country":"ES",
    "sg:address":"Calle de Dehesa De Mari-martin, 11",
    "sg:city":"Dehesa De Marimartin",
    "sg:orig_category":"Chapister\u00cda",
    "sg:phone":"+34 918 11 22 51",
    "sg:postcode":"28600",
    "sg:province":"Madrid",
    "wof:name":"Autos Niclar S.l.",
    "wof:placetype":"venue"
},
  "geometry": {"coordinates":[-4.0136671066,40.28490448],"type":"Point"}
}