{
  "type": "Feature",
  "properties": {
    "iso:country":"ES",
    "sg:address":"Bo. Bolivar, S/n",
    "sg:city":"Bolibar",
    "sg:orig_category":"Construcciones Met\u00c1licas",
    "sg:phone":"+34 946 16 40 66",
    "sg:postcode":"48279",
    "sg:province":"Vizcaya",
    "wof:name":"Calvo Crespo Manuel",
    "wof:placetype":"venue"
},
  "geometry": {"coordinates":[-2.50780797,43.2668037415],"type":"Point"}
}