{
  "type": "Feature",
  "properties": {
    "iso:country":"ES",
    "sg:address":"Calle de Voluntad, 34",
    "sg:city":"Sevilla",
    "sg:orig_category":"Pintura, Barniz, Productos Asimilables (fabricaci\u00d3n, Al Por Mayor)",
    "sg:phone":"+34 954 27 50 38",
    "sg:postcode":"41010",
    "sg:province":"Sevilla",
    "wof:name":"Quijano Escobar Jose",
    "wof:placetype":"venue"
},
  "geometry": {"coordinates":[-6.0058479309,37.3789176941],"type":"Point"}
}