{
  "type": "Feature",
  "properties": {
    "iso:country":"ES",
    "sg:address":"Avda Rey Juan Carlos I, 184",
    "sg:city":"Roquetas Mar",
    "sg:orig_category":"Servicios De Higiene Y Peluquer\u00cda Para Perros Y Gatos",
    "sg:phone":"+34 950 32 78 76",
    "sg:postcode":"04740",
    "sg:province":"Almer\u00eda",
    "wof:name":"Clinica Veterinaria Algaida S.c.",
    "wof:placetype":"venue"
},
  "geometry": {"coordinates":[-2.61282897,36.765411377],"type":"Point"}
}