{
  "type": "Feature",
  "properties": {
    "addr:full":"Trva Brasil, S/n Guarda Pontevedra 36780",
    "addr:postcode":"36780",
    "addr:street":"Trva Brasil S / N",
    "iso:country":"ES",
    "sg:address":"Trva Brasil, S/n",
    "sg:city":"Guarda",
    "sg:orig_category":"Masajistas Kinesiterapeutas",
    "sg:phone":"+34 986 61 07 62",
    "sg:postcode":"36780",
    "sg:province":"Pontevedra",
    "wof:name":"Alonso Fajar Jorge",
    "wof:placetype":"venue"
},
  "geometry": {"coordinates":[-8.8679180145,41.9051933289],"type":"Point"}
}