{
  "type": "Feature",
  "properties": {
    "addr:full":"Calle de Allariz, 4 Madrid Madrid 28044",
    "addr:housenumber":"4",
    "addr:postcode":"28044",
    "addr:street":"Calle De Allariz",
    "iso:country":"ES",
    "sg:address":"Calle de Allariz, 4",
    "sg:city":"Madrid",
    "sg:orig_category":"Farmacias",
    "sg:phone":"+34 915 08 38 44",
    "sg:postcode":"28044",
    "sg:province":"Madrid",
    "wof:name":"Serrano Rodriguez Carmen Purificacion",
    "wof:placetype":"venue"
},
  "geometry": {"coordinates":[-3.7538919449,40.3675918579],"type":"Point"}
}