{
  "type": "Feature",
  "properties": {
    "iso:country":"ES",
    "sg:address":"Los Palacios, 3",
    "sg:city":"Sanlucar",
    "sg:orig_category":"Empresas De Carpinter\u00cda De Madera",
    "sg:phone":"+34 956 36 87 85",
    "sg:postcode":"11540",
    "sg:province":"C\u00e1diz",
    "wof:name":"Cadena Rodriguez Eduardo",
    "wof:placetype":"venue"
},
  "geometry": {"coordinates":[-6.3382620811,36.7789077759],"type":"Point"}
}