{
  "type": "Feature",
  "properties": {
    "addr:full":"Plaz Inmaculada (la), 1 Tamarite Litera Huesca 22550",
    "addr:postcode":"22550",
    "addr:street":"La 1 Tamarite",
    "iso:country":"ES",
    "sg:address":"Plaz Inmaculada (la), 1",
    "sg:city":"Tamarite Litera",
    "sg:orig_category":"Estancos",
    "sg:phone":"+34 974 42 00 15",
    "sg:postcode":"22550",
    "sg:province":"Huesca",
    "wof:name":"Anaya Sanz Patrocinio",
    "wof:placetype":"venue"
},
  "geometry": {"coordinates":[0.4218989909,41.8682518005],"type":"Point"}
}