{
  "type": "Feature",
  "properties": {
    "iso:country":"ES",
    "sg:address":"Carrer de Montserrat, 10",
    "sg:city":"Sabadell",
    "sg:orig_category":"Fabricaci\u00d3n, Venta De Cuadros, Accesorios Para Enmarcar",
    "sg:phone":"+34 937 26 06 00",
    "sg:postcode":"08201",
    "sg:province":"Barcelona",
    "wof:name":"Vila Vila Jose",
    "wof:placetype":"venue"
},
  "geometry": {"coordinates":[2.1100480556,41.5433731079],"type":"Point"}
}