{
  "type": "Feature",
  "properties": {
    "addr:full":"Barr Requejada, S/n Requejada Cantabria 39312",
    "addr:housenumber":"s / n",
    "addr:postcode":"39312",
    "addr:street":"Requejada",
    "iso:country":"ES",
    "sg:address":"Barr Requejada, S/n",
    "sg:city":"Requejada",
    "sg:orig_category":"Comercio De Piezas De Recambio Y De Accesorios De Veh\u00cdculos, Veh\u00cdculos Industriales",
    "sg:phone":"+34 942 82 58 58",
    "sg:postcode":"39312",
    "sg:province":"Cantabria",
    "wof:name":"Recambios Bastida S.l.",
    "wof:placetype":"venue"
},
  "geometry": {"coordinates":[-4.0313191414,43.3870658875],"type":"Point"}
}