{
  "type": "Feature",
  "properties": {
    "iso:country":"ES",
    "sg:address":"Rava Fora, 33",
    "sg:city":"Sabadell",
    "sg:orig_category":"Fisioterapia",
    "sg:phone":"+34 937 27 27 43",
    "sg:postcode":"08202",
    "sg:province":"Barcelona",
    "wof:name":"Torrell Rubio Albert",
    "wof:placetype":"venue"
},
  "geometry": {"coordinates":[2.125674963,41.5481300354],"type":"Point"}
}