{
  "type": "Feature",
  "properties": {
    "addr:full":"Rbla Sant Joan, 182 Badalona Barcelona 08917",
    "addr:housenumber":"182",
    "addr:postcode":"08917",
    "addr:street":"Rbla Sant Joan",
    "iso:country":"ES",
    "sg:address":"Rbla Sant Joan, 182",
    "sg:city":"Badalona",
    "sg:orig_category":"Farmacias",
    "sg:phone":"+34 933 87 38 93",
    "sg:postcode":"08917",
    "sg:province":"Barcelona",
    "wof:name":"Monguio Soliva Teresa",
    "wof:placetype":"venue"
},
  "geometry": {"coordinates":[2.2350649834,41.4498558044],"type":"Point"}
}