{
  "type": "Feature",
  "properties": {
    "addr:full":"Santiago Kalea, 22 Azpeitia Guip\u00f9zcoa 20730",
    "addr:housenumber":"22",
    "addr:postcode":"20730",
    "addr:street":"Santiago Kalea;Guipu\u0300Zcoa",
    "iso:country":"ES",
    "sg:address":"Santiago Kalea, 22",
    "sg:city":"Azpeitia",
    "sg:orig_category":"Electrodom\u00c9sticos (al Por Menor)",
    "sg:phone":"+34 943 81 12 26",
    "sg:postcode":"20730",
    "sg:province":"Guip\u00f9zcoa",
    "wof:name":"Arrieta Electrodomesticos S.l",
    "wof:placetype":"venue"
},
  "geometry": {"coordinates":[-2.2651081085,43.1855201721],"type":"Point"}
}