{
  "type": "Feature",
  "properties": {
    "iso:country":"ES",
    "sg:address":"Calle de Maria Teresa Saenz De Heredia, 18",
    "sg:city":"Madrid",
    "sg:orig_category":"Psic\u00d3logos",
    "sg:phone":"+34 914 03 38 44",
    "sg:postcode":"28017",
    "sg:province":"Madrid",
    "wof:name":"Grupo De Expertos En Terapia Y Rehabilitacion S.a.",
    "wof:placetype":"venue"
},
  "geometry": {"coordinates":[-3.6533999443,40.4234046936],"type":"Point"}
}