{
  "type": "Feature",
  "properties": {
    "iso:country":"ES",
    "sg:address":"Crta. Tabernes, S/n",
    "sg:city":"Guadassuar",
    "sg:orig_category":"Cerrajer\u00cda, Ferrallista",
    "sg:phone":"+34 962 57 05 40",
    "sg:postcode":"46610",
    "sg:province":"Valencia",
    "sg:website":"www.guadaforja.com",
    "wof:name":"Guadaforja S.l.",
    "wof:placetype":"venue"
},
  "geometry": {"coordinates":[-0.4772889912,39.1815376282],"type":"Point"}
}