{
  "type": "Feature",
  "properties": {
    "addr:full":"Calle de Ronda, 53 Puerto Serrano C\u00e1diz 11659",
    "addr:housenumber":"53",
    "addr:postcode":"11659",
    "addr:street":"Calle De Ronda;Ca\u0301Diz",
    "iso:country":"ES",
    "sg:address":"Calle de Ronda, 53",
    "sg:city":"Puerto Serrano",
    "sg:orig_category":"Ense\u00d1anza: Profesiones Art\u00cdsticas",
    "sg:phone":"+34 956 13 61 92",
    "sg:postcode":"11659",
    "sg:province":"C\u00e1diz",
    "wof:name":"Moreno Poley Gema",
    "wof:placetype":"venue"
},
  "geometry": {"coordinates":[-5.5446820259,36.9235153198],"type":"Point"}
}