{
  "type": "Feature",
  "properties": {
    "iso:country":"ES",
    "sg:address":"Carrer de Ramon Berenguer Iii, 33",
    "sg:city":"Granollers",
    "sg:orig_category":"Inmobiliaria (agencias)",
    "sg:phone":"+34 938 46 35 88",
    "sg:postcode":"08401",
    "sg:province":"Barcelona",
    "sg:website":"www.icasa.es",
    "wof:name":"Comunidad De Propietarios Ramon Berenguer Iii 33",
    "wof:placetype":"venue"
},
  "geometry": {"coordinates":[2.2877500057,41.6148109436],"type":"Point"}
}