{
  "type": "Feature",
  "properties": {
    "iso:country":"ES",
    "sg:address":"Avda Alcalde Miguel Casta\u00d1o, 95",
    "sg:city":"Le\u00f3n",
    "sg:orig_category":"Servicios Gsm",
    "sg:phone":"+34 987 21 50 56",
    "sg:postcode":"24005",
    "sg:province":"Le\u00f3n",
    "wof:name":"Offitelefonia S.a",
    "wof:placetype":"venue"
},
  "geometry": {"coordinates":[-5.5597901344,42.5866394043],"type":"Point"}
}