{
  "type": "Feature",
  "properties": {
    "iso:country":"ES",
    "sg:address":"Ctra Union, Km. 0003,0",
    "sg:city":"Cartagena",
    "sg:orig_category":"Negocio De Madera",
    "sg:phone":"+34 968 12 50 08",
    "sg:postcode":"30392",
    "sg:province":"Murcia",
    "wof:name":"General Espa\u00f1ola De Maderas Gemsa S.a.",
    "wof:placetype":"venue"
},
  "geometry": {"coordinates":[-0.9694439769,37.6158447266],"type":"Point"}
}