{
  "type": "Feature",
  "properties": {
    "iso:country":"ES",
    "sg:address":"Av Sarria, 25",
    "sg:city":"Barcelona",
    "sg:orig_category":"Bancos",
    "sg:phone":"+34 934 30 77 19",
    "sg:postcode":"08029",
    "sg:province":"Barcelona",
    "wof:name":"Banco Popular Espa\u00f1ol S.a.",
    "wof:placetype":"venue"
},
  "geometry": {"coordinates":[2.1450080872,41.3901481628],"type":"Point"}
}