{
  "type": "Feature",
  "properties": {
    "iso:country":"ES",
    "sg:address":"Calle de Alfonso I, 23",
    "sg:city":"Zaragoza",
    "sg:orig_category":"Cajas De Ahorro",
    "sg:phone":"+34 976 39 43 91",
    "sg:postcode":"50003",
    "sg:province":"Zaragoza",
    "wof:name":"Caja De Ahorros Y Monte De Piedad De Zaragoza Aragon Y Rioja",
    "wof:placetype":"venue"
},
  "geometry": {"coordinates":[-0.8807681203,41.6544189453],"type":"Point"}
}