{
  "type": "Feature",
  "properties": {
    "addr:full":"Avda Mar, Del, 3 Castellon Castell\u00f3n 12003",
    "addr:housenumber":"3",
    "addr:postcode":"12003",
    "addr:street":"Avda Mar Del;Castello\u0301N",
    "iso:country":"ES",
    "sg:address":"Avda Mar, Del, 3",
    "sg:city":"Castellon",
    "sg:classifiers":[
        {
            "category":"Autos & Motor Vehicles",
            "subcategory":"Automobile Sales",
            "type":"Retail Goods"
        }
    ],
    "sg:phone":"+34 964 22 66 74",
    "sg:postcode":"12003",
    "sg:province":"Castell\u00f3n",
    "wof:name":"Autoescola Gallen S.l.",
    "wof:placetype":"venue"
},
  "geometry": {"coordinates":[-0.0077,39.9838409424],"type":"Point"}
}