{
  "type": "Feature",
  "properties": {
    "iso:country":"ES",
    "sg:address":"Calle de Oreja Marcelino, 7",
    "sg:city":"Bilbao",
    "sg:classifiers":[
        {
            "category":"Home & Garden",
            "subcategory":"Building Materials",
            "type":"Retail Goods"
        }
    ],
    "sg:phone":"+34 944 21 51 27",
    "sg:postcode":"48010",
    "sg:province":"Vizcaya",
    "sg:tags":[
        "accesorios",
        "para",
        "bares",
        "cervecer\u00cdas",
        "caf\u00c9s",
        "y"
    ],
    "wof:name":"Arce Garcia Miguel Angel",
    "wof:placetype":"venue"
},
  "geometry": {"coordinates":[-2.9400036335,43.2583122253],"type":"Point"}
}