{
  "type": "Feature",
  "properties": {
    "addr:full":"Calle de Costa Brava, 2 Valladolid Valladolid 47010",
    "addr:housenumber":"2",
    "addr:postcode":"47010",
    "addr:street":"Calle De Costa Brava",
    "iso:country":"ES",
    "sg:address":"Calle de Costa Brava, 2",
    "sg:city":"Valladolid",
    "sg:orig_category":"Animales (al Por Menor)",
    "sg:phone":"+34 983 25 99 03",
    "sg:postcode":"47010",
    "sg:province":"Valladolid",
    "wof:name":"Gomez Gomez Julian",
    "wof:placetype":"venue"
},
  "geometry": {"coordinates":[-4.710474968,41.6691665649],"type":"Point"}
}