{
  "type": "Feature",
  "properties": {
    "addr:full":"Barr Saro De Abajo, S/n Saro Cantabria 39639",
    "addr:housenumber":"s / n",
    "addr:postcode":"39639",
    "addr:street":"Abajo",
    "iso:country":"ES",
    "sg:address":"Barr Saro De Abajo, S/n",
    "sg:city":"Saro",
    "sg:orig_category":"Agricultores, Agricultores",
    "sg:phone":"+34 942 74 82 92",
    "sg:postcode":"39639",
    "sg:province":"Cantabria",
    "wof:name":"S.a.t. Hermanos Valencia",
    "wof:placetype":"venue"
},
  "geometry": {"coordinates":[-3.8433699608,43.2601280212],"type":"Point"}
}