{
  "type": "Feature",
  "properties": {
    "iso:country":"ES",
    "sg:address":"Calle de Alcala, 1",
    "sg:city":"Benidorm",
    "sg:orig_category":"Estancos",
    "sg:phone":"+34 965 85 36 91",
    "sg:postcode":"03500",
    "sg:province":"Alicante",
    "wof:name":"Rodriguez Ortiz Daniel",
    "wof:placetype":"venue"
},
  "geometry": {"coordinates":[-0.1332771033,38.5445671082],"type":"Point"}
}