{
  "type": "Feature",
  "properties": {
    "addr:full":"Calle de Fernando Guanarteme, 93 Cruce I Las Palmas 35110",
    "addr:housenumber":"93",
    "addr:postcode":"35110",
    "addr:street":"Calle De Fernando Guanarteme;I Las",
    "iso:country":"ES",
    "sg:address":"Calle de Fernando Guanarteme, 93",
    "sg:city":"Cruce I",
    "sg:orig_category":"Ortopedia General",
    "sg:phone":"+34 928 75 82 60",
    "sg:postcode":"35110",
    "sg:province":"Las Palmas",
    "wof:name":"Centro Ortopedico Insular S.l.",
    "wof:placetype":"venue"
},
  "geometry": {"coordinates":[-15.4440488815,27.8556194305],"type":"Point"}
}