{
  "type": "Feature",
  "properties": {
    "addr:full":"Monte Sequeiros, S/n Breto\u00f1a Pontevedra 36191",
    "addr:housenumber":"s / n",
    "addr:postcode":"36191",
    "iso:country":"ES",
    "sg:address":"Monte Sequeiros, S/n",
    "sg:city":"Breto\u00f1a",
    "sg:orig_category":"Bares, Piano",
    "sg:phone":"+34 986 71 32 22",
    "sg:postcode":"36191",
    "sg:province":"Pontevedra",
    "wof:name":"Almacen Distribuidor De Exclusivas De Galicia S.l.",
    "wof:placetype":"venue"
},
  "geometry": {"coordinates":[-8.6673822403,42.5035896301],"type":"Point"}
}