{
  "type": "Feature",
  "properties": {
    "addr:full":"Manuel Lekuona Etorbidea, 8 Elizalde Guip\u00f9zcoa 20180",
    "addr:housenumber":"8",
    "addr:postcode":"20180",
    "addr:street":"Manuel Lekuona Etorbidea;Guipu\u0300Zcoa",
    "iso:country":"ES",
    "sg:address":"Manuel Lekuona Etorbidea, 8",
    "sg:city":"Elizalde",
    "sg:orig_category":"Fabricaci\u00d3n De Motores El\u00c9ctricos",
    "sg:phone":"+34 943 49 21 11",
    "sg:postcode":"20180",
    "sg:province":"Guip\u00f9zcoa",
    "sg:website":"www.mebsa.com",
    "wof:name":"Maquinaria Electrica Bilbao S. A.",
    "wof:placetype":"venue"
},
  "geometry": {"coordinates":[-1.8629590273,43.2992401123],"type":"Point"}
}