{
  "type": "Feature",
  "properties": {
    "addr:full":"Calle de Salinero, 14 Torrevieja Alicante 03180",
    "addr:housenumber":"14",
    "addr:postcode":"03180",
    "addr:street":"Calle De Salinero",
    "iso:country":"ES",
    "sg:address":"Calle de Salinero, 14",
    "sg:city":"Torrevieja",
    "sg:orig_category":"Farmacias",
    "sg:phone":"+34 965 71 11 57",
    "sg:postcode":"03180",
    "sg:province":"Alicante",
    "wof:name":"Gomez Garcia Jose Maria",
    "wof:placetype":"venue"
},
  "geometry": {"coordinates":[-0.6744840145,37.9841308594],"type":"Point"}
}