{
  "type": "Feature",
  "properties": {
    "addr:full":"Carrer de Amistat, 9 Manlleu Barcelona 08560",
    "addr:housenumber":"9",
    "addr:postcode":"08560",
    "addr:street":"Carrer De Amistat",
    "iso:country":"ES",
    "sg:address":"Carrer de Amistat, 9",
    "sg:city":"Manlleu",
    "sg:orig_category":"Carnicer\u00cdas, Carnicer\u00cdas",
    "sg:phone":"+34 938 50 69 95",
    "sg:postcode":"08560",
    "sg:province":"Barcelona",
    "wof:name":"Gasa Agramunt Luis Antonio",
    "wof:placetype":"venue"
},
  "geometry": {"coordinates":[2.2798669338,42.0034599304],"type":"Point"}
}