{
  "type": "Feature",
  "properties": {
    "addr:full":"Calle de Castillo De Alcala De Guadaira, 25 Sevilla Sevilla 41013",
    "addr:housenumber":"25",
    "addr:postcode":"41013",
    "addr:street":"Calle De Castillo De Alcala;Guadaira",
    "iso:country":"ES",
    "sg:address":"Calle de Castillo De Alcala De Guadaira, 25",
    "sg:city":"Sevilla",
    "sg:orig_category":"Agencias Y Agentes Comerciales, Representantes",
    "sg:phone":"+34 954 23 51 28",
    "sg:postcode":"41013",
    "sg:province":"Sevilla",
    "wof:name":"Balon Molero Jose Luis",
    "wof:placetype":"venue"
},
  "geometry": {"coordinates":[-5.9762477875,37.3596839905],"type":"Point"}
}