{
  "type": "Feature",
  "properties": {
    "addr:full":"Calle de Morote, 13 Huescar Granada 18830",
    "addr:housenumber":"13",
    "addr:postcode":"18830",
    "addr:street":"Calle De Morote",
    "iso:country":"ES",
    "sg:address":"Calle de Morote, 13",
    "sg:city":"Huescar",
    "sg:orig_category":"Art\u00cdculos De Regalo (al Por Menor)",
    "sg:phone":"+34 958 74 01 12",
    "sg:postcode":"18830",
    "sg:province":"Granada",
    "wof:name":"Berbel Hernandez Pedro",
    "wof:placetype":"venue"
},
  "geometry": {"coordinates":[-2.5411069393,37.8088874817],"type":"Point"}
}