{
  "type": "Feature",
  "properties": {
    "iso:country":"ES",
    "sg:address":"Av M. Celayeta, 6",
    "sg:city":"Iru\u00f1a",
    "sg:orig_category":"Tintes (fabricaci\u00d3n, Al Por Mayor)",
    "sg:phone":"+34 948 12 22 28",
    "sg:postcode":"31014",
    "sg:province":"Navarra",
    "wof:name":"Elizalde Rada Javier",
    "wof:placetype":"venue"
},
  "geometry": {"coordinates":[-1.6437540054,42.81275177],"type":"Point"}
}