{
  "type": "Feature",
  "properties": {
    "addr:full":"Carr Forn Nou, 12 Figueres Girona 17600",
    "addr:housenumber":"12",
    "addr:postcode":"17600",
    "addr:street":"Carr Forn Nou",
    "iso:country":"ES",
    "sg:address":"Carr Forn Nou, 12",
    "sg:city":"Figueres",
    "sg:orig_category":"Artes Gr\u00c1ficas, Artes Pl\u00c1sticas (curso)",
    "sg:phone":"+34 972 67 18 12",
    "sg:postcode":"17600",
    "sg:province":"Girona",
    "wof:name":"Academia Aurea S.c.",
    "wof:placetype":"venue"
},
  "geometry": {"coordinates":[2.962147,42.266052],"type":"Point"}
}