{
  "type": "Feature",
  "properties": {
    "iso:country":"ES",
    "sg:address":"Cmno Vial De Los Cipreses, 41",
    "sg:city":"Alacant",
    "sg:orig_category":"Cerrajer\u00cda, Ferrallista",
    "sg:phone":"+34 965 11 62 00",
    "sg:postcode":"03006",
    "sg:province":"Alicante",
    "wof:name":"Cerrajeria Arques S.l.",
    "wof:placetype":"venue"
},
  "geometry": {"coordinates":[-0.5288389921,38.3511505127],"type":"Point"}
}