{
  "type": "Feature",
  "properties": {
    "iso:country":"ES",
    "sg:address":"Calle de Cazo, 14",
    "sg:city":"Pesquera Duero",
    "sg:orig_category":"Supermercados Y Hipermercados",
    "sg:phone":"+34 983 87 01 83",
    "sg:postcode":"47315",
    "sg:province":"Valladolid",
    "wof:name":"Alimentacion Rondiez S.l.",
    "wof:placetype":"venue"
},
  "geometry": {"coordinates":[-4.156648159,41.6414794922],"type":"Point"}
}