{
  "type": "Feature",
  "properties": {
    "iso:country":"ES",
    "sg:address":"Calle de Cristobal Colon, 21",
    "sg:city":"Herrera Pisuerga",
    "sg:orig_category":"Electricidad, Electr\u00d3nica: Suministros (al Por Menor)",
    "sg:phone":"+34 979 13 02 69",
    "sg:postcode":"34400",
    "sg:province":"Palencia",
    "wof:name":"Ildefonso Matanza C.b.",
    "wof:placetype":"venue"
},
  "geometry": {"coordinates":[-4.3303236961,42.595413208],"type":"Point"}
}