{
  "type": "Feature",
  "properties": {
    "iso:country":"ES",
    "sg:address":"Calle de Ceferino, 2",
    "sg:city":"San Antolin",
    "sg:orig_category":"Alimentaci\u00d3n General (al Por Menor)",
    "sg:phone":"+34 968 29 68 21",
    "sg:postcode":"30004",
    "sg:province":"Murcia",
    "wof:name":"Garcia Ruiperez Jose Manuel",
    "wof:placetype":"venue"
},
  "geometry": {"coordinates":[-1.1298867464,37.9834747314],"type":"Point"}
}