{
  "type": "Feature",
  "properties": {
    "addr:full":"Carrer de Doctor Joan Bonet, 101 Deltebre Tarragona 43580",
    "addr:housenumber":"101",
    "addr:postcode":"43580",
    "addr:street":"Carrer De Doctor Joan Bonet",
    "iso:country":"ES",
    "sg:address":"Carrer de Doctor Joan Bonet, 101",
    "sg:city":"Deltebre",
    "sg:orig_category":"Promotores Constructores",
    "sg:phone":"+34 977 48 97 63",
    "sg:postcode":"43580",
    "sg:province":"Tarragona",
    "wof:name":"Construccions I Reformes Gan Iv, Sl",
    "wof:placetype":"venue"
},
  "geometry": {"coordinates":[0.7100600004,40.7226104736],"type":"Point"}
}