{
  "type": "Feature",
  "properties": {
    "iso:country":"ES",
    "sg:address":"Pl Mayor, 1",
    "sg:city":"Sumacarcer",
    "sg:orig_category":"Administraciones Regionales, Departamentales Y Locales",
    "sg:phone":"+34 962 59 52 80",
    "sg:postcode":"46295",
    "sg:province":"Valencia",
    "wof:name":"Ayuntamiento De Sumacarcer",
    "wof:placetype":"venue"
},
  "geometry": {"coordinates":[-0.5877490044,39.0313339233],"type":"Point"}
}