{
  "type": "Feature",
  "properties": {
    "iso:country":"ES",
    "sg:address":"Calle de Covadonga, 5",
    "sg:city":"Gijon",
    "sg:classifiers":[
        {
            "category":"Professional",
            "subcategory":"Research",
            "type":"Services"
        }
    ],
    "sg:phone":"+34 985 34 02 63",
    "sg:postcode":"33201",
    "sg:province":"Asturias",
    "sg:tags":[
        "mercado",
        "de",
        "estudios"
    ],
    "wof:name":"Ipsos Operaciones",
    "wof:placetype":"venue"
},
  "geometry": {"coordinates":[-5.6586470604,43.539516449],"type":"Point"}
}