{
  "type": "Feature",
  "properties": {
    "addr:full":"Calle de Pablo Iglesias, 13 Zaragoza Zaragoza 50018",
    "addr:housenumber":"13",
    "addr:postcode":"50018",
    "addr:street":"Calle De Pablo Iglesias",
    "iso:country":"ES",
    "sg:address":"Calle de Pablo Iglesias, 13",
    "sg:city":"Zaragoza",
    "sg:orig_category":"Frutas, Legumbres Frescas Y Tempranas (al Por Menor)",
    "sg:phone":"+34 976 73 18 80",
    "sg:postcode":"50018",
    "sg:province":"Zaragoza",
    "wof:name":"Lacruz Alonso Juan Alberto",
    "wof:placetype":"venue"
},
  "geometry": {"coordinates":[-0.8874071836,41.6773948669],"type":"Point"}
}