{
  "type": "Feature",
  "properties": {
    "iso:country":"ES",
    "sg:address":"Calle de Azalea (de La), 1",
    "sg:city":"Alcobendas",
    "sg:orig_category":"Agencias De Viajes",
    "sg:phone":"+34 916 50 77 11",
    "sg:postcode":"28109",
    "sg:province":"Madrid",
    "wof:name":"Azimut Travel S.a.",
    "wof:placetype":"venue"
},
  "geometry": {"coordinates":[-3.6503260136,40.5188751221],"type":"Point"}
}