{
  "type": "Feature",
  "properties": {
    "iso:country":"ES",
    "sg:address":"Calle de Bolivia, 10",
    "sg:city":"Vitoria-gasteiz",
    "sg:orig_category":"Textil",
    "sg:phone":"+34 945 22 08 63",
    "sg:postcode":"01009",
    "sg:province":"\u00c1lava",
    "wof:name":"Bermejo Vaquero Electino",
    "wof:placetype":"venue"
},
  "geometry": {"coordinates":[-2.6825489998,42.8535308838],"type":"Point"}
}