{
  "type": "Feature",
  "properties": {
    "addr:full":"Ctra Rodilana, Km. 0010,0 Medina Campo Valladolid 47400",
    "addr:postcode":"47400",
    "addr:street":"Ctra Rodilana Km. 0010,0",
    "iso:country":"ES",
    "sg:address":"Ctra Rodilana, Km. 0010,0",
    "sg:city":"Medina Campo",
    "sg:orig_category":"Fabricaci\u00d3n, Distribuci\u00d3n De Material Para La Climatizaci\u00d3n, Aireaci\u00d3n Y Ventilaci\u00d3n",
    "sg:phone":"+34 983 80 15 17",
    "sg:postcode":"47400",
    "sg:province":"Valladolid",
    "wof:name":"Cafoygas S.l.",
    "wof:placetype":"venue"
},
  "geometry": {"coordinates":[-4.913184166,41.3120155334],"type":"Point"}
}