{
  "type": "Feature",
  "properties": {
    "iso:country":"ES",
    "sg:address":"Ctra Madrid-irun, Km. 0243,0",
    "sg:city":"Burgos",
    "sg:orig_category":"Transportes Por Carretera: Lotes Completos, Mercanc\u00cdas Diversas",
    "sg:phone":"+34 947 48 04 94",
    "sg:postcode":"09007",
    "sg:province":"Burgos",
    "wof:name":"Sociedad Distribuidora De Alimentacion S.l.",
    "wof:placetype":"venue"
},
  "geometry": {"coordinates":[-3.6532809734,42.3579711914],"type":"Point"}
}