{
  "type": "Feature",
  "properties": {
    "iso:country":"ES",
    "sg:address":"Carr Francesc Moragas, 11",
    "sg:city":"Santa Coloma De Farners",
    "sg:orig_category":"Electricidad (montaje, Ensamblaje De Componentes)",
    "sg:phone":"+34 972 84 05 67",
    "sg:postcode":"17430",
    "sg:province":"Girona",
    "wof:name":"Insmator 2005 S.l.",
    "wof:placetype":"venue"
},
  "geometry": {"coordinates":[2.66456604,41.8606262207],"type":"Point"}
}