{
  "type": "Feature",
  "properties": {
    "iso:country":"ES",
    "sg:address":"Calle de Salvago, 3",
    "sg:city":"Malaga",
    "sg:orig_category":"Peluqueros: De Se\u00d1oras",
    "sg:phone":"+34 952 21 36 62",
    "sg:postcode":"29005",
    "sg:province":"M\u00e1laga",
    "wof:name":"Fernandez Cordero Rafael",
    "wof:placetype":"venue"
},
  "geometry": {"coordinates":[-4.4229121208,36.7210121155],"type":"Point"}
}