{
  "type": "Feature",
  "properties": {
    "addr:full":"Avda Marconi, 7 Cadiz C\u00e1diz 11009",
    "addr:housenumber":"7",
    "addr:postcode":"11009",
    "addr:street":"Avda Marconi",
    "iso:country":"ES",
    "sg:address":"Avda Marconi, 7",
    "sg:city":"Cadiz",
    "sg:orig_category":"Plomeros",
    "sg:phone":"+34 956 28 84 52",
    "sg:postcode":"11009",
    "sg:province":"C\u00e1diz",
    "wof:name":"Santos Caro Manuel",
    "wof:placetype":"venue"
},
  "geometry": {"coordinates":[-6.2768478394,36.5082015991],"type":"Point"}
}