{
  "type": "Feature",
  "properties": {
    "addr:full":"Carrer de Apol.lo, 10 Terrassa Barcelona 08228",
    "addr:housenumber":"10",
    "addr:postcode":"08228",
    "addr:street":"Carrer De Apol.Lo",
    "iso:country":"ES",
    "sg:address":"Carrer de Apol.lo, 10",
    "sg:city":"Terrassa",
    "sg:orig_category":"Ebanister\u00cda",
    "sg:phone":"+34 937 86 36 80",
    "sg:postcode":"08228",
    "sg:province":"Barcelona",
    "wof:name":"Mabus S.a.",
    "wof:placetype":"venue"
},
  "geometry": {"coordinates":[2.0379009247,41.5410804749],"type":"Point"}
}