{
  "type": "Feature",
  "properties": {
    "iso:country":"ES",
    "sg:address":"Avda Benidorm, 24",
    "sg:city":"Arnedo",
    "sg:orig_category":"Reposter\u00cdas",
    "sg:phone":"+34 941 38 20 32",
    "sg:postcode":"26580",
    "sg:province":"La Rioja",
    "wof:name":"Maria Del Carmen Abad Perez Medrano Y Dos Mas S.cv.",
    "wof:placetype":"venue"
},
  "geometry": {"coordinates":[-2.0983090401,42.2256698608],"type":"Point"}
}