{
  "type": "Feature",
  "properties": {
    "addr:full":"Calle de Arenal, 6 Abenojar Ciudad Real 13180",
    "addr:housenumber":"6",
    "addr:postcode":"13180",
    "addr:street":"Calle De Arenal",
    "iso:country":"ES",
    "sg:address":"Calle de Arenal, 6",
    "sg:city":"Abenojar",
    "sg:orig_category":"T\u00c9cnicos Veterinarios",
    "sg:phone":"+34 926 83 50 46",
    "sg:postcode":"13180",
    "sg:province":"Ciudad Real",
    "wof:name":"Placeres Hurtado Juan Antonio",
    "wof:placetype":"venue"
},
  "geometry": {"coordinates":[-4.3556656837,38.8794517517],"type":"Point"}
}