{
  "type": "Feature",
  "properties": {
    "addr:full":"Calle de Severiano Masides, S/n Aldeanueva Camino C\u00e1ceres 10740",
    "addr:housenumber":"s",
    "addr:postcode":"10740",
    "addr:street":"Calle De Severiano Masides;/ N Aldeanueva Camino Ca\u0301Ceres",
    "iso:country":"ES",
    "sg:address":"Calle de Severiano Masides, S/n",
    "sg:city":"Aldeanueva Camino",
    "sg:orig_category":"Ense\u00d1anza, Formaci\u00d3n Profesional: Aprendizaje",
    "sg:phone":"+34 927 47 91 71",
    "sg:postcode":"10740",
    "sg:province":"C\u00e1ceres",
    "wof:name":"Ayuntamiento De Aldeanueva Del Camino",
    "wof:placetype":"venue"
},
  "geometry": {"coordinates":[-5.9262280464,40.26039505],"type":"Point"}
}