{
  "type": "Feature",
  "properties": {
    "addr:full":"Calle de Mayor, 102 Alberca De Las Torres Murcia 30150",
    "addr:housenumber":"102",
    "addr:postcode":"30150",
    "addr:street":"Calle De Mayor",
    "iso:country":"ES",
    "sg:address":"Calle de Mayor, 102",
    "sg:city":"Alberca De Las Torres",
    "sg:orig_category":"Electrodom\u00c9sticos (al Por Menor)",
    "sg:phone":"+34 968 84 31 40",
    "sg:postcode":"30150",
    "sg:province":"Murcia",
    "wof:name":"Electrodomesticos Jose Martinez S.l.",
    "wof:placetype":"venue"
},
  "geometry": {"coordinates":[-1.1447889805,37.9411697388],"type":"Point"}
}