{
  "type": "Feature",
  "properties": {
    "addr:full":"Calle de Don Jaime I, 39 Zaragoza Zaragoza 50003",
    "addr:housenumber":"39",
    "addr:postcode":"50003",
    "addr:street":"Calle De Don Jaime I",
    "iso:country":"ES",
    "sg:address":"Calle de Don Jaime I, 39",
    "sg:city":"Zaragoza",
    "sg:orig_category":"Aparatos De Iluminaci\u00d3n (al Por Menor)",
    "sg:phone":"+34 976 29 36 78",
    "sg:postcode":"50003",
    "sg:province":"Zaragoza",
    "wof:name":"Muebles La Gran Breta\u00f1a S.l.",
    "wof:placetype":"venue"
},
  "geometry": {"coordinates":[-0.8773378134,41.6544952393],"type":"Point"}
}