{
  "type": "Feature",
  "properties": {
    "addr:full":"Crt Provencio, 1 Villarrobledo Albacete 02600",
    "addr:housenumber":"1",
    "addr:postcode":"02600",
    "addr:street":"Crt Provencio",
    "iso:country":"ES",
    "sg:address":"Crt Provencio, 1",
    "sg:city":"Villarrobledo",
    "sg:orig_category":"Herramientas Y Suministros Para Plomeros",
    "sg:phone":"+34 967 14 56 51",
    "sg:postcode":"02600",
    "sg:province":"Albacete",
    "wof:name":"Emiliano Y Federico Rubio S L",
    "wof:placetype":"venue"
},
  "geometry": {"coordinates":[-2.6013379097,39.2801322937],"type":"Point"}
}