{
  "type": "Feature",
  "properties": {
    "iso:country":"ES",
    "sg:address":"Uxio Souto, 8",
    "sg:city":"Cuntis",
    "sg:classifiers":[
        {
            "category":"Autos & Motor Vehicles",
            "subcategory":"Automobile Sales",
            "type":"Retail Goods"
        }
    ],
    "sg:phone":"+34 986 54 82 24",
    "sg:postcode":"36670",
    "sg:province":"Pontevedra",
    "wof:name":"Parama Loureiro Jesus",
    "wof:placetype":"venue"
},
  "geometry": {"coordinates":[-8.5611791611,42.6424484253],"type":"Point"}
}