{
  "type": "Feature",
  "properties": {
    "iso:country":"ES",
    "sg:address":"Tran Riacho, 1",
    "sg:city":"Orihuela",
    "sg:orig_category":"M\u00c9dicos: Estomatolog\u00cda",
    "sg:phone":"+34 966 74 34 47",
    "sg:postcode":"03300",
    "sg:province":"Alicante",
    "wof:name":"Vicea Sanchez Maria Dolores",
    "wof:placetype":"venue"
},
  "geometry": {"coordinates":[-0.9452869892,38.0845222473],"type":"Point"}
}