{
  "type": "Feature",
  "properties": {
    "iso:country":"ES",
    "sg:address":"Gta Valle De Oro, 10",
    "sg:city":"Madrid",
    "sg:orig_category":"Distribuci\u00d3n De Petr\u00d3leo Y Derivados",
    "sg:phone":"+34 914 71 35 50",
    "sg:postcode":"28019",
    "sg:province":"Madrid",
    "wof:name":"Geservicio S.l.",
    "wof:placetype":"venue"
},
  "geometry": {"coordinates":[-3.729749918,40.3880767822],"type":"Point"}
}