{
  "type": "Feature",
  "properties": {
    "addr:full":"Ctra Zafra, Km. 0032,0 Fregenal Sierra Badajoz 06340",
    "addr:postcode":"06340",
    "addr:street":"Ctra Zafra Km. 0032,0",
    "iso:country":"ES",
    "sg:address":"Ctra Zafra, Km. 0032,0",
    "sg:city":"Fregenal Sierra",
    "sg:orig_category":"Agricultores, Agricultores",
    "sg:phone":"+34 924 14 80 08",
    "sg:postcode":"06340",
    "sg:province":"Badajoz",
    "wof:name":"Explotacion Agropecuaria La Parrilla S.a.",
    "wof:placetype":"venue"
},
  "geometry": {"coordinates":[-6.6505317688,38.1659088135],"type":"Point"}
}