{
  "type": "Feature",
  "properties": {
    "iso:country":"ES",
    "sg:address":"Calle de Dr Layna Serrano, 2",
    "sg:city":"Guadalajara",
    "sg:orig_category":"Arquitectos",
    "sg:phone":"+34 949 21 62 39",
    "sg:postcode":"19002",
    "sg:province":"Guadalajara",
    "wof:name":"Sancho Redero Maria Librada",
    "wof:placetype":"venue"
},
  "geometry": {"coordinates":[-3.172000885,40.6267089844],"type":"Point"}
}