{
  "type": "Feature",
  "properties": {
    "iso:country":"ES",
    "sg:address":"Calle de Marques De Casa Valdes, 35",
    "sg:city":"Gijon",
    "sg:classifiers":[
        {
            "category":"Personal",
            "subcategory":"Barber",
            "type":"Services"
        }
    ],
    "sg:phone":"+34 985 34 98 35",
    "sg:postcode":"33202",
    "sg:province":"Asturias",
    "sg:tags":[
        "caballeros",
        "de",
        "peluqueros"
    ],
    "wof:name":"Bergu\u00f1o Fernandez Luis",
    "wof:placetype":"venue"
},
  "geometry": {"coordinates":[-5.6561131477,43.5400428772],"type":"Point"}
}