{
  "type": "Feature",
  "properties": {
    "iso:country":"ES",
    "sg:address":"Valdeallin, 9",
    "sg:city":"Estella",
    "sg:orig_category":"Parques De Atracciones Y Centros De Esparcimiento",
    "sg:phone":"+34 948 55 61 89",
    "sg:postcode":"31200",
    "sg:province":"Navarra",
    "wof:name":"Garcia Anaya Manuel",
    "wof:placetype":"venue"
},
  "geometry": {"coordinates":[-2.0304269791,42.6722755432],"type":"Point"}
}