{
  "type": "Feature",
  "properties": {
    "addr:full":"Calle de Aguila, 8 Leganes Madrid 28911",
    "addr:housenumber":"8",
    "addr:postcode":"28911",
    "addr:street":"Calle De Aguila",
    "iso:country":"ES",
    "sg:address":"Calle de Aguila, 8",
    "sg:city":"Leganes",
    "sg:orig_category":"Artes Gr\u00c1ficas, Artes Pl\u00c1sticas (curso)",
    "sg:phone":"+34 916 93 75 62",
    "sg:postcode":"28911",
    "sg:province":"Madrid",
    "wof:name":"Industrias De La Impresion S.a.",
    "wof:placetype":"venue"
},
  "geometry": {"coordinates":[-3.7704262733,40.3264389038],"type":"Point"}
}