{
  "type": "Feature",
  "properties": {
    "addr:full":"Calle de Antonio Machado, 8 Hornachuelos C\u00f3rdoba 14740",
    "addr:housenumber":"8",
    "addr:postcode":"14740",
    "addr:street":"Calle De Antonio Machado",
    "iso:country":"ES",
    "sg:address":"Calle de Antonio Machado, 8",
    "sg:city":"Hornachuelos",
    "sg:orig_category":"Controles De Edificaci\u00d3n (construcci\u00d3n, Seguridad)",
    "sg:phone":"+34 957 64 03 28",
    "sg:postcode":"14740",
    "sg:province":"C\u00f3rdoba",
    "wof:name":"Hornachuelos De Desarrollo Economico S.a.a.",
    "wof:placetype":"venue"
},
  "geometry": {"coordinates":[-5.2419018745,37.8306694031],"type":"Point"}
}