{
  "type": "Feature",
  "properties": {
    "iso:country":"ES",
    "sg:address":"Avda Doctor Fleming, 4",
    "sg:city":"Yuncos",
    "sg:orig_category":"Cl\u00cdnicas Dentales",
    "sg:phone":"+34 925 55 38 27",
    "sg:postcode":"45210",
    "sg:province":"Toledo",
    "wof:name":"Maferden S.l.",
    "wof:placetype":"venue"
},
  "geometry": {"coordinates":[-3.8733589649,40.088180542],"type":"Point"}
}