{
  "type": "Feature",
  "properties": {
    "iso:country":"ES",
    "sg:address":"Avda Fuente Piedra, S/n",
    "sg:city":"Sierra Yeguas",
    "sg:orig_category":"Fabricaci\u00d3n De Productos L\u00c1cteos Y Derivados",
    "sg:phone":"+34 952 74 64 98",
    "sg:postcode":"29328",
    "sg:province":"M\u00e1laga",
    "wof:name":"Sierra Lactea Sociedad Cooperativa Andaluza",
    "wof:placetype":"venue"
},
  "geometry": {"coordinates":[-4.863779068,37.1266899109],"type":"Point"}
}