{
  "type": "Feature",
  "properties": {
    "iso:country":"ES",
    "sg:address":"Cami La Coma, S/n",
    "sg:city":"Picassent",
    "sg:orig_category":"Producci\u00d3n De Abonos Y De Fertilizantes",
    "sg:phone":"+34 961 23 30 80",
    "sg:postcode":"46220",
    "sg:province":"Valencia",
    "wof:name":"Semillas Diago S. L.",
    "wof:placetype":"venue"
},
  "geometry": {"coordinates":[-0.4480639994,39.3482246399],"type":"Point"}
}