{
  "type": "Feature",
  "properties": {
    "iso:country":"ES",
    "sg:address":"Jose Codo\u00f1er Casa\u00f1, 35",
    "sg:city":"Massanassa",
    "sg:orig_category":"Pescader\u00cdas (al Por Menor)",
    "sg:phone":"+34 961 25 14 06",
    "sg:postcode":"46470",
    "sg:province":"Valencia",
    "wof:name":"Pescados E. Guillem S. L.",
    "wof:placetype":"venue"
},
  "geometry": {"coordinates":[-0.3984389901,39.4128303528],"type":"Point"}
}