{
  "type": "Feature",
  "properties": {
    "addr:full":"Carr Metge Vicent Portoles (del), 16 Lliria Valencia 46160",
    "addr:housenumber":"16",
    "addr:postcode":"46160",
    "addr:street":"Carr Metge Vicent Portoles Del",
    "iso:country":"ES",
    "sg:address":"Carr Metge Vicent Portoles (del), 16",
    "sg:city":"Lliria",
    "sg:orig_category":"Electricidad: Instaladores",
    "sg:phone":"+34 962 78 09 23",
    "sg:postcode":"46160",
    "sg:province":"Valencia",
    "wof:name":"Electro Bori S. L.",
    "wof:placetype":"venue"
},
  "geometry": {"coordinates":[-0.5946540236,39.6267852783],"type":"Point"}
}