{
  "type": "Feature",
  "properties": {
    "addr:full":"Calle de Hospital, 2 Torrejon Ardoz Madrid 28850",
    "addr:housenumber":"2",
    "addr:postcode":"28850",
    "addr:street":"Calle De Hospital",
    "iso:country":"ES",
    "sg:address":"Calle de Hospital, 2",
    "sg:city":"Torrejon Ardoz",
    "sg:orig_category":"Partidos Pol\u00cdticos",
    "sg:phone":"+34 916 56 23 85",
    "sg:postcode":"28850",
    "sg:province":"Madrid",
    "wof:name":"Alianza Popular",
    "wof:placetype":"venue"
},
  "geometry": {"coordinates":[-3.4789311886,40.4588394165],"type":"Point"}
}