{
  "type": "Feature",
  "properties": {
    "iso:country":"ES",
    "sg:address":"Cami Masia Frederic, 40",
    "sg:city":"Vilanova I La Geltru",
    "sg:orig_category":"Promotores Constructores",
    "sg:phone":"+34 938 14 42 36",
    "sg:postcode":"08800",
    "sg:province":"Barcelona",
    "wof:name":"Construcciones Felix Monago S.cp.",
    "wof:placetype":"venue"
},
  "geometry": {"coordinates":[1.72458601,41.2322807312],"type":"Point"}
}