{
  "type": "Feature",
  "properties": {
    "iso:country":"ES",
    "sg:address":"Carrer de Sant Salvador, 23",
    "sg:city":"Roda De Bara",
    "sg:orig_category":"Inmobiliaria (agencias)",
    "sg:phone":"+34 977 80 99 11",
    "sg:postcode":"43883",
    "sg:province":"Tarragona",
    "wof:name":"Innovahogar S.l.",
    "wof:placetype":"venue"
},
  "geometry": {"coordinates":[1.4552140236,41.1841697693],"type":"Point"}
}