{
  "type": "Feature",
  "properties": {
    "addr:full":"Calle de Sur, 4 Logro\u00f1o La Rioja 26005",
    "addr:housenumber":"4",
    "addr:postcode":"26005",
    "addr:street":"Calle De Sur;Rioja",
    "iso:country":"ES",
    "sg:address":"Calle de Sur, 4",
    "sg:city":"Logro\u00f1o",
    "sg:orig_category":"Promotores Constructores",
    "sg:phone":"+34 941 20 31 11",
    "sg:postcode":"26005",
    "sg:province":"La Rioja",
    "wof:name":"Zangroniz Samaniego S.a.",
    "wof:placetype":"venue"
},
  "geometry": {"coordinates":[-2.4550695419,42.4611968994],"type":"Point"}
}