{
  "type": "Feature",
  "properties": {
    "iso:country":"ES",
    "sg:address":"Carrer de Carme, 41",
    "sg:city":"Senia",
    "sg:orig_category":"Reposter\u00cdas",
    "sg:phone":"+34 977 71 31 23",
    "sg:postcode":"43560",
    "sg:province":"Tarragona",
    "wof:name":"Matamoros Torta Antonio",
    "wof:placetype":"venue"
},
  "geometry": {"coordinates":[0.2798919976,40.6358718872],"type":"Point"}
}