{
  "type": "Feature",
  "properties": {
    "iso:country":"ES",
    "sg:address":"Carrer de Corsega, 607",
    "sg:city":"Barcelona",
    "sg:orig_category":"M\u00c9dicos: Medicina General Orientada A La Acupuntura",
    "sg:phone":"+34 934 55 48 11",
    "sg:postcode":"08025",
    "sg:province":"Barcelona",
    "wof:name":"Monaco Rosich Antonio",
    "wof:placetype":"venue"
},
  "geometry": {"coordinates":[2.1749529839,41.4084777832],"type":"Point"}
}