{
  "type": "Feature",
  "properties": {
    "iso:country":"ES",
    "sg:address":"Calle de Real De Torre, 14",
    "sg:city":"Velilla",
    "sg:orig_category":"Tapiceros Y Tapiceros",
    "sg:phone":"+34 983 79 23 65",
    "sg:postcode":"47114",
    "sg:province":"Valladolid",
    "wof:name":"Fernandez Vizcaino Carlos",
    "wof:placetype":"venue"
},
  "geometry": {"coordinates":[-5.0042300224,41.5571289062],"type":"Point"}
}