{
  "type": "Feature",
  "properties": {
    "iso:country":"ES",
    "sg:address":"Avda Constitucion (la), 3",
    "sg:city":"Villanueva Rio Y Minas",
    "sg:orig_category":"Aguas (distribuci\u00d3n, Servicios)",
    "sg:phone":"+34 954 74 89 00",
    "sg:postcode":"41350",
    "sg:province":"Sevilla",
    "wof:name":"Aguas Del Huesna S.l.",
    "wof:placetype":"venue"
},
  "geometry": {"coordinates":[-5.713145256,37.6519126892],"type":"Point"}
}