{
  "type": "Feature",
  "properties": {
    "iso:country":"ES",
    "sg:address":"A Igrexa, 11",
    "sg:city":"Breto\u00f1a",
    "sg:orig_category":"Reposter\u00cdas",
    "sg:phone":"+34 982 34 91 83",
    "sg:postcode":"27286",
    "sg:province":"Lugo",
    "wof:name":"Panaderia Seivane S.l.",
    "wof:placetype":"venue"
},
  "geometry": {"coordinates":[-7.3240408897,43.3316688538],"type":"Point"}
}