{
  "type": "Feature",
  "properties": {
    "iso:country":"ES",
    "sg:address":"Ctra Canillas, 41",
    "sg:city":"Madrid",
    "sg:orig_category":"Ropa Para Se\u00d1oras Y Caballeros (al Por Menor)",
    "sg:phone":"+34 913 88 14 89",
    "sg:postcode":"28043",
    "sg:province":"Madrid",
    "wof:name":"Burgos Hierro Maria Gloria",
    "wof:placetype":"venue"
},
  "geometry": {"coordinates":[-3.6476740837,40.4632987976],"type":"Point"}
}