{
  "type": "Feature",
  "properties": {
    "addr:full":"Cmno Oliva, S/n Tudela Duero Valladolid 47320",
    "addr:housenumber":"s",
    "addr:postcode":"47320",
    "addr:street":"Cmno Oliva;/ N",
    "iso:country":"ES",
    "sg:address":"Cmno Oliva, S/n",
    "sg:city":"Tudela Duero",
    "sg:orig_category":"M\u00c1rmoles, Granitos Y Piedras Naturales",
    "sg:phone":"+34 983 52 26 07",
    "sg:postcode":"47320",
    "sg:province":"Valladolid",
    "wof:name":"Marmoles Tudela De Duero S.l.l",
    "wof:placetype":"venue"
},
  "geometry": {"coordinates":[-4.5823941231,41.5873565674],"type":"Point"}
}