{
  "type": "Feature",
  "properties": {
    "addr:full":"Calle de Mesones, 35 Mansilla Mulas Le\u00f3n 24210",
    "addr:housenumber":"35",
    "addr:postcode":"24210",
    "addr:street":"Calle De Mesones",
    "iso:country":"ES",
    "sg:address":"Calle de Mesones, 35",
    "sg:city":"Mansilla Mulas",
    "sg:orig_category":"Muebles, Minoristas",
    "sg:phone":"+34 987 31 00 11",
    "sg:postcode":"24210",
    "sg:province":"Le\u00f3n",
    "wof:name":"Ramos Gonzalez Jesus Manuel",
    "wof:placetype":"venue"
},
  "geometry": {"coordinates":[-5.4187488556,42.4996299744],"type":"Point"}
}