{
  "type": "Feature",
  "properties": {
    "iso:country":"ES",
    "sg:address":"Calle de Alberique, 38",
    "sg:city":"Madrid",
    "sg:orig_category":"Asociaciones Y Clubs Deportivos",
    "sg:phone":"+34 913 06 16 41",
    "sg:postcode":"28037",
    "sg:province":"Madrid",
    "wof:name":"Herrera Del Rio Julian",
    "wof:placetype":"venue"
},
  "geometry": {"coordinates":[-3.6207094193,40.4285812378],"type":"Point"}
}