{
  "type": "Feature",
  "properties": {
    "addr:full":"Real, S/n Ogijares Granada 18151",
    "addr:housenumber":"s / n",
    "addr:postcode":"18151",
    "addr:street":"Real",
    "iso:country":"ES",
    "sg:address":"Real, S/n",
    "sg:city":"Ogijares",
    "sg:orig_category":"Electrodom\u00c9sticos (al Por Menor)",
    "sg:phone":"+34 958 59 77 45",
    "sg:postcode":"18151",
    "sg:province":"Granada",
    "wof:name":"Urbano Dominguez Nicolas",
    "wof:placetype":"venue"
},
  "geometry": {"coordinates":[-3.6069641113,37.1214294434],"type":"Point"}
}