{
  "type": "Feature",
  "properties": {
    "addr:full":"Malo De Molina, 14 Burgo Osma Soria 42300",
    "addr:housenumber":"14",
    "addr:postcode":"42300",
    "addr:street":"Molina",
    "iso:country":"ES",
    "sg:address":"Malo De Molina, 14",
    "sg:city":"Burgo Osma",
    "sg:orig_category":"Agencias Y Agentes Comerciales, Representantes",
    "sg:phone":"+34 975 34 06 09",
    "sg:postcode":"42300",
    "sg:province":"Soria",
    "wof:name":"Carleson Hernanz Carl Gunnar",
    "wof:placetype":"venue"
},
  "geometry": {"coordinates":[-3.0742990971,41.5880050659],"type":"Point"}
}