{
  "type": "Feature",
  "properties": {
    "iso:country":"ES",
    "sg:address":"Plaz Mayor, S/n",
    "sg:city":"Priorato",
    "sg:orig_category":"Cajas De Ahorro",
    "sg:phone":"+34 955 80 50 04",
    "sg:postcode":"41440",
    "sg:province":"Sevilla",
    "sg:website":"www.cajasanfernando.es",
    "wof:name":"Caja San Fernando De Sevilla Y Jerez",
    "wof:placetype":"venue"
},
  "geometry": {"coordinates":[-5.5281839371,37.659828186],"type":"Point"}
}