{
  "type": "Feature",
  "properties": {
    "addr:full":"Calle de Mi\u00d1o (del), 10 Coslada Madrid 28820",
    "addr:housenumber":"10",
    "addr:postcode":"28820",
    "addr:street":"Calle De Min\u0303O Del",
    "iso:country":"ES",
    "sg:address":"Calle de Mi\u00d1o (del), 10",
    "sg:city":"Coslada",
    "sg:orig_category":"Molduras, Junquillos, Listones Y Molduras Perforadas",
    "sg:phone":"+34 916 73 93 36",
    "sg:postcode":"28820",
    "sg:province":"Madrid",
    "wof:name":"Veguilla Pirado Miguel",
    "wof:placetype":"venue"
},
  "geometry": {"coordinates":[-3.5375299454,40.4240379333],"type":"Point"}
}