{
  "type": "Feature",
  "properties": {
    "addr:full":"Plaz Cruz Roja, 11 San Juan Murcia 30003",
    "addr:housenumber":"11",
    "addr:postcode":"30003",
    "addr:street":"Plaz;Roja",
    "iso:country":"ES",
    "sg:address":"Plaz Cruz Roja, 11",
    "sg:city":"San Juan",
    "sg:orig_category":"Traductores",
    "sg:phone":"+34 968 21 08 67",
    "sg:postcode":"30003",
    "sg:province":"Murcia",
    "wof:name":"Thomas  Philip",
    "wof:placetype":"venue"
},
  "geometry": {"coordinates":[-1.1302499771,37.9829597473],"type":"Point"}
}