{
  "type": "Feature",
  "properties": {
    "iso:country":"ES",
    "sg:address":"Ctra. N. 340, S/n",
    "sg:city":"Huercal-overa",
    "sg:orig_category":"Lencer\u00cda Femenina, Corseter\u00cda, Trajes De Ba\u00d1o (al Por Menor)",
    "sg:phone":"+34 950 61 61 17",
    "sg:postcode":"04600",
    "sg:province":"Almer\u00eda",
    "wof:name":"Asociacion Alzheimer Huercal Overa",
    "wof:placetype":"venue"
},
  "geometry": {"coordinates":[-1.9436843395,37.390625],"type":"Point"}
}