{
  "type": "Feature",
  "properties": {
    "addr:full":"Calle de Emilio Mari, 7 Valencia Valencia 46025",
    "addr:housenumber":"7",
    "addr:postcode":"46025",
    "addr:street":"Calle De Emilio Mari",
    "iso:country":"ES",
    "sg:address":"Calle de Emilio Mari, 7",
    "sg:city":"Valencia",
    "sg:orig_category":"Comunidades Religiosas",
    "sg:phone":"+34 963 48 80 00",
    "sg:postcode":"46025",
    "sg:province":"Valencia",
    "wof:name":"Parroquia Nuestra Se\u00f1ora De Tejeda",
    "wof:placetype":"venue"
},
  "geometry": {"coordinates":[-0.3941729963,39.4941139221],"type":"Point"}
}