{
  "type": "Feature",
  "properties": {
    "addr:full":"Calle de Mayor, 60 Nules Castell\u00f3n 12520",
    "addr:housenumber":"60",
    "addr:postcode":"12520",
    "addr:street":"Calle De Mayor",
    "iso:country":"ES",
    "sg:address":"Calle de Mayor, 60",
    "sg:city":"Nules",
    "sg:orig_category":"Farmacias",
    "sg:phone":"+34 964 67 00 40",
    "sg:postcode":"12520",
    "sg:province":"Castell\u00f3n",
    "wof:name":"Galver Sanz Maria Angeles",
    "wof:placetype":"venue"
},
  "geometry": {"coordinates":[-0.1554040015,39.8530197144],"type":"Point"}
}