{
  "type": "Feature",
  "properties": {
    "addr:full":"Cami Canivell (de), S/n Tortosa Tarragona 43500",
    "addr:housenumber":"s",
    "addr:postcode":"43500",
    "addr:street":"/ N",
    "iso:country":"ES",
    "sg:address":"Cami Canivell (de), S/n",
    "sg:city":"Tortosa",
    "sg:orig_category":"M\u00c9dicos: Neumolog\u00cda",
    "sg:phone":"+34 977 44 47 03",
    "sg:postcode":"43500",
    "sg:province":"Tarragona",
    "wof:name":"Manresa Presas Jose Maria",
    "wof:placetype":"venue"
},
  "geometry": {"coordinates":[0.5317749977,40.8048210144],"type":"Point"}
}