{
  "type": "Feature",
  "properties": {
    "iso:country":"ES",
    "sg:address":"Calle de Capilla San Andres, 2",
    "sg:city":"Granada",
    "sg:orig_category":"Iglesia Cat\u00d3lica",
    "sg:phone":"+34 958 29 18 00",
    "sg:postcode":"18010",
    "sg:province":"Granada",
    "wof:name":"Parroquia De San Andres",
    "wof:placetype":"venue"
},
  "geometry": {"coordinates":[-3.5993402004,37.1810112],"type":"Point"}
}