{
  "type": "Feature",
  "properties": {
    "addr:full":"Zubitxo Kalea, 27 Lezo Guip\u00f9zcoa 20100",
    "addr:housenumber":"27",
    "addr:postcode":"20100",
    "addr:street":"Zubitxo Kalea;Guipu\u0300Zcoa",
    "iso:country":"ES",
    "sg:address":"Zubitxo Kalea, 27",
    "sg:city":"Lezo",
    "sg:orig_category":"Caf\u00c9s, Bares, Cervecer\u00cdas",
    "sg:phone":"+34 943 51 74 47",
    "sg:postcode":"20100",
    "sg:province":"Guip\u00f9zcoa",
    "wof:name":"Espasandin Pino Jose Maria",
    "wof:placetype":"venue"
},
  "geometry": {"coordinates":[-1.895252943,43.3212852478],"type":"Point"}
}