{
  "type": "Feature",
  "properties": {
    "iso:country":"ES",
    "sg:address":"Calle de Ricardo Ortiz, S/n",
    "sg:city":"Madrid",
    "sg:orig_category":"Librer\u00cdas",
    "sg:phone":"+34 913 61 42 21",
    "sg:postcode":"28017",
    "sg:province":"Madrid",
    "wof:name":"Medina Escobar Pablo",
    "wof:placetype":"venue"
},
  "geometry": {"coordinates":[-3.6579990387,40.426574707],"type":"Point"}
}