{
  "type": "Feature",
  "properties": {
    "addr:full":"Calle de Averroes, 78 Miajadas C\u00e1ceres 10100",
    "addr:housenumber":"78",
    "addr:postcode":"10100",
    "addr:street":"Calle De Averroes;Ca\u0301Ceres",
    "iso:country":"ES",
    "sg:address":"Calle de Averroes, 78",
    "sg:city":"Miajadas",
    "sg:orig_category":"Empresas De Carpinter\u00cda Met\u00c1lica",
    "sg:phone":"+34 927 34 72 15",
    "sg:postcode":"10100",
    "sg:province":"C\u00e1ceres",
    "wof:name":"Taller De Artesania Candelo C.b.",
    "wof:placetype":"venue"
},
  "geometry": {"coordinates":[-5.9143791199,39.1515312195],"type":"Point"}
}