{
  "type": "Feature",
  "properties": {
    "addr:full":"Calle de Otero Blas De, 61 Bilbao Vizcaya 48014",
    "addr:housenumber":"61",
    "addr:postcode":"48014",
    "addr:street":"Calle De Otero Blas De",
    "iso:country":"ES",
    "sg:address":"Calle de Otero Blas De, 61",
    "sg:city":"Bilbao",
    "sg:orig_category":"Asesor\u00cda Sobre Comunicaci\u00d3n De Empresas",
    "sg:phone":"+34 944 75 14 02",
    "sg:postcode":"48014",
    "sg:province":"Vizcaya",
    "wof:name":"Salvador Nadal Jose Maria Javier",
    "wof:placetype":"venue"
},
  "geometry": {"coordinates":[-2.9526638985,43.2697639465],"type":"Point"}
}