{
  "type": "Feature",
  "properties": {
    "addr:full":"Calle de Tigris, 4 Sevilla Sevilla 41020",
    "addr:housenumber":"4",
    "addr:postcode":"41020",
    "addr:street":"Calle De Tigris",
    "iso:country":"ES",
    "sg:address":"Calle de Tigris, 4",
    "sg:city":"Sevilla",
    "sg:orig_category":"Artes Gr\u00c1ficas, Artes Pl\u00c1sticas: Material Y Suministros (al Por Menor)",
    "sg:phone":"+34 954 25 08 79",
    "sg:postcode":"41020",
    "sg:province":"Sevilla",
    "wof:name":"Ramirez Bellido Inmaculada",
    "wof:placetype":"venue"
},
  "geometry": {"coordinates":[-5.9376091957,37.4075088501],"type":"Point"}
}