{
  "type": "Feature",
  "properties": {
    "addr:full":"Calle de Juan Thalamas Labandibar, 67 Irun Guip\u00f9zcoa 20305",
    "addr:housenumber":"67",
    "addr:postcode":"20305",
    "addr:street":"Calle De Juan Thalamas Labandibar;Guipu\u0300Zcoa",
    "iso:country":"ES",
    "sg:address":"Calle de Juan Thalamas Labandibar, 67",
    "sg:city":"Irun",
    "sg:orig_category":"Institutos De Belleza",
    "sg:phone":"+34 943 63 51 58",
    "sg:postcode":"20305",
    "sg:province":"Guip\u00f9zcoa",
    "wof:name":"Hernandez Garcia Guillermo",
    "wof:placetype":"venue"
},
  "geometry": {"coordinates":[-1.7631030083,43.3427658081],"type":"Point"}
}