{
  "type": "Feature",
  "properties": {
    "addr:full":"Calle de Ramon Gomez De La Serna, 23 Marbella M\u00e1laga 29600",
    "addr:housenumber":"23",
    "addr:postcode":"29600",
    "addr:street":"Calle De Ramon Gomez De La Serna;Ma\u0301Laga",
    "iso:country":"ES",
    "sg:address":"Calle de Ramon Gomez De La Serna, 23",
    "sg:city":"Marbella",
    "sg:orig_category":"Artes Gr\u00c1ficas, Artes Pl\u00c1sticas: Material Y Suministros (al Por Menor)",
    "sg:phone":"+34 952 86 46 46",
    "sg:postcode":"29600",
    "sg:province":"M\u00e1laga",
    "wof:name":"Advanced Commercial Activities S.l",
    "wof:placetype":"venue"
},
  "geometry": {"coordinates":[-4.8988652229,36.509677887],"type":"Point"}
}