{
  "type": "Feature",
  "properties": {
    "iso:country":"ES",
    "sg:address":"Calle de Parroco Segundo Vega, 115",
    "sg:city":"Palmas De Gran Canaria",
    "sg:orig_category":"Suministros Para Hoteles",
    "sg:phone":"+34 928 33 11 28",
    "sg:postcode":"35015",
    "sg:province":"Las Palmas",
    "sg:website":"www.canary-guide.com/gc/ramsuar.com",
    "wof:name":"Ramsuar Hosteleria Y Servicios Canarias S.l.",
    "wof:placetype":"venue"
},
  "geometry": {"coordinates":[-15.4309368134,28.0943164825],"type":"Point"}
}