{
  "type": "Feature",
  "properties": {
    "iso:country":"ES",
    "sg:address":"Mayor, S/n",
    "sg:city":"Usi",
    "sg:orig_category":"Fabricaci\u00d3n, Distribuci\u00d3n De Discos, V\u00cddeodiscos Y Musicassettes",
    "sg:phone":"+34 948 30 32 60",
    "sg:postcode":"31193",
    "sg:province":"Navarra",
    "wof:name":"Producciones Navarras S.l.",
    "wof:placetype":"venue"
},
  "geometry": {"coordinates":[-1.6971100569,42.8987503052],"type":"Point"}
}