{
  "type": "Feature",
  "properties": {
    "iso:country":"ES",
    "sg:address":"Alacant, 6",
    "sg:city":"Sedavi",
    "sg:orig_category":"Fabricaci\u00d3n, Venta, Instalaci\u00d3n De R\u00d3tulos, De R\u00d3tulos Luminosos",
    "sg:phone":"+34 963 75 70 07",
    "sg:postcode":"46910",
    "sg:province":"Valencia",
    "wof:name":"Rotulos Torralba S.l.",
    "wof:placetype":"venue"
},
  "geometry": {"coordinates":[-0.3904080093,39.4265785217],"type":"Point"}
}