{
  "type": "Feature",
  "properties": {
    "addr:full":"Autovia Logro\u00f1o Pol Ind Europa, 10 Zaragoza Zaragoza 50011",
    "addr:housenumber":"10",
    "addr:postcode":"50011",
    "addr:street":"Autovia Logron\u0303O Pol;Europa",
    "iso:country":"ES",
    "sg:address":"Autovia Logro\u00f1o Pol Ind Europa, 10",
    "sg:city":"Zaragoza",
    "sg:orig_category":"Asistencia Y Seguros De Automovilistas Y Turistas",
    "sg:phone":"+34 976 46 07 47",
    "sg:postcode":"50011",
    "sg:province":"Zaragoza",
    "wof:name":"Grumaza 2003 Sl",
    "wof:placetype":"venue"
},
  "geometry": {"coordinates":[-1.0011901855,41.6566925049],"type":"Point"}
}