{
  "type": "Feature",
  "properties": {
    "iso:country":"ES",
    "sg:address":"Carrer de Mossen Jacint Verdaguer, 31",
    "sg:city":"Premia Mar",
    "sg:orig_category":"Florister\u00cdas",
    "sg:phone":"+34 937 52 30 38",
    "sg:postcode":"08330",
    "sg:province":"Barcelona",
    "wof:name":"Batlle Canals Ismael",
    "wof:placetype":"venue"
},
  "geometry": {"coordinates":[2.3554348946,41.4923973083],"type":"Point"}
}