{
  "type": "Feature",
  "properties": {
    "iso:country":"ES",
    "sg:address":"Rua Perez Viondi, S/n",
    "sg:city":"Estrada",
    "sg:orig_category":"Abogados",
    "sg:phone":"+34 986 57 03 91",
    "sg:postcode":"36680",
    "sg:province":"Pontevedra",
    "wof:name":"Sanmartin Losada Miguel",
    "wof:placetype":"venue"
},
  "geometry": {"coordinates":[-8.4910736084,42.6887664795],"type":"Point"}
}