{
  "type": "Feature",
  "properties": {
    "addr:full":"Calle de Carlos Iii, 47 Cartagena Murcia 30203",
    "addr:housenumber":"47",
    "addr:postcode":"30203",
    "addr:street":"Calle De Carlos Iii",
    "iso:country":"ES",
    "sg:address":"Calle de Carlos Iii, 47",
    "sg:city":"Cartagena",
    "sg:orig_category":"Agencias Y Agentes Comerciales, Representantes",
    "sg:phone":"+34 968 50 67 09",
    "sg:postcode":"30203",
    "sg:province":"Murcia",
    "wof:name":"Saez Gomez Simon",
    "wof:placetype":"venue"
},
  "geometry": {"coordinates":[-0.9826989174,37.6059303284],"type":"Point"}
}