{
  "type": "Feature",
  "properties": {
    "addr:full":"Calle de Argandona, 59 Gijon Asturias 33208",
    "addr:housenumber":"59",
    "addr:postcode":"33208",
    "addr:street":"Calle De Argandona",
    "iso:country":"ES",
    "sg:address":"Calle de Argandona, 59",
    "sg:city":"Gijon",
    "sg:orig_category":"Peluquer\u00cdas, Peluquer\u00cda Mixta",
    "sg:phone":"+34 985 14 52 45",
    "sg:postcode":"33208",
    "sg:province":"Asturias",
    "wof:name":"Orfila Rodriguez Rufina",
    "wof:placetype":"venue"
},
  "geometry": {"coordinates":[-5.6624846458,43.5325164795],"type":"Point"}
}