{
  "type": "Feature",
  "properties": {
    "addr:full":"Ctra. Montijo, S/n Merida Badajoz 06800",
    "addr:housenumber":"s",
    "addr:postcode":"06800",
    "addr:street":"Ctra. Montijo;/ N",
    "iso:country":"ES",
    "sg:address":"Ctra. Montijo, S/n",
    "sg:city":"Merida",
    "sg:orig_category":"Contenedores (mercanc\u00cdas)",
    "sg:phone":"+34 924 31 18 33",
    "sg:postcode":"06800",
    "sg:province":"Badajoz",
    "wof:name":"De La Hiz-trans S.l.",
    "wof:placetype":"venue"
},
  "geometry": {"coordinates":[-6.5217728615,38.964099884],"type":"Point"}
}