{
  "type": "Feature",
  "properties": {
    "iso:country":"ES",
    "sg:address":"Calle de Antonio Machado, 14",
    "sg:city":"Villa Rio",
    "sg:orig_category":"Inmobiliaria (agencias)",
    "sg:phone":"+34 957 17 73 33",
    "sg:postcode":"14640",
    "sg:province":"C\u00f3rdoba",
    "wof:name":"F.y G. Asesores C.b.",
    "wof:placetype":"venue"
},
  "geometry": {"coordinates":[-4.2949872017,37.9816818237],"type":"Point"}
}