{
  "type": "Feature",
  "properties": {
    "addr:full":"Rosalia De Castro, 10 Padron La Coru\u00f1a 15900",
    "addr:housenumber":"10",
    "addr:postcode":"15900",
    "addr:street":"Rosalia De Castro;Padron La Corun\u0303A",
    "iso:country":"ES",
    "sg:address":"Rosalia De Castro, 10",
    "sg:city":"Padron",
    "sg:orig_category":"Jardiner\u00cdas, Vegetales, Art\u00cdculos De Jardiner\u00cda (al Por Menor)",
    "sg:phone":"+34 981 81 21 06",
    "sg:postcode":"15900",
    "sg:province":"La Coru\u00f1a",
    "wof:name":"Agrogal S. L.",
    "wof:placetype":"venue"
},
  "geometry": {"coordinates":[-8.6597175598,42.7392845154],"type":"Point"}
}