{
  "type": "Feature",
  "properties": {
    "iso:country":"ES",
    "sg:address":"Calle de Ruiz Gomez, 14",
    "sg:city":"Gijon",
    "sg:orig_category":"Muebles, Minoristas",
    "sg:phone":"+34 985 19 58 02",
    "sg:postcode":"33202",
    "sg:province":"Asturias",
    "wof:name":"Divalau S.l.",
    "wof:placetype":"venue"
},
  "geometry": {"coordinates":[-5.6568069458,43.5396652222],"type":"Point"}
}