{
  "type": "Feature",
  "properties": {
    "addr:full":"Rua B, 49 Lalin Pontevedra 36500",
    "addr:housenumber":"49",
    "addr:postcode":"36500",
    "addr:street":"Rua B",
    "iso:country":"ES",
    "sg:address":"Rua B, 49",
    "sg:city":"Lalin",
    "sg:orig_category":"Automatizaci\u00d3n De Procesos Industriales Y De Edificaci\u00d3n (estudios, Instalaci\u00d3n)",
    "sg:phone":"+34 986 78 18 57",
    "sg:postcode":"36500",
    "sg:province":"Pontevedra",
    "wof:name":"Villanueva Fernandez Manuel",
    "wof:placetype":"venue"
},
  "geometry": {"coordinates":[-8.1109790802,42.657169342],"type":"Point"}
}