{
  "type": "Feature",
  "properties": {
    "iso:country":"ES",
    "sg:address":"Calle de Obispo Marcelo, 29",
    "sg:city":"Cuatrovientos",
    "sg:orig_category":"Electrodom\u00c9sticos (al Por Menor)",
    "sg:phone":"+34 987 42 94 28",
    "sg:postcode":"24400",
    "sg:province":"Le\u00f3n",
    "wof:name":"Electroestar Bierzo S.l.",
    "wof:placetype":"venue"
},
  "geometry": {"coordinates":[-6.6211071014,42.5582580566],"type":"Point"}
}