{
  "type": "Feature",
  "properties": {
    "addr:full":"Calle de Carretero, 148 Coria Rio Sevilla 41100",
    "addr:housenumber":"148",
    "addr:postcode":"41100",
    "addr:street":"Calle De Carretero;Rio Sevilla",
    "iso:country":"ES",
    "sg:address":"Calle de Carretero, 148",
    "sg:city":"Coria Rio",
    "sg:orig_category":"Alquiler De V\u00cddeo",
    "sg:phone":"+34 954 77 45 18",
    "sg:postcode":"41100",
    "sg:province":"Sevilla",
    "wof:name":"Corea Multiocios S.c.",
    "wof:placetype":"venue"
},
  "geometry": {"coordinates":[-6.0579099655,37.2874107361],"type":"Point"}
}