{
  "type": "Feature",
  "properties": {
    "addr:full":"Calle de San Roque, 35 Ribadeo Lugo 27700",
    "addr:housenumber":"35",
    "addr:postcode":"27700",
    "addr:street":"Calle De San Roque",
    "iso:country":"ES",
    "sg:address":"Calle de San Roque, 35",
    "sg:city":"Ribadeo",
    "sg:orig_category":"Bisuter\u00cda, Joyer\u00cda, Relojer\u00cda (al Por Menor)",
    "sg:phone":"+34 982 13 11 39",
    "sg:postcode":"27700",
    "sg:province":"Lugo",
    "wof:name":"Lillo Requejo Maria Jose",
    "wof:placetype":"venue"
},
  "geometry": {"coordinates":[-7.0450692177,43.5376281738],"type":"Point"}
}