{
  "type": "Feature",
  "properties": {
    "iso:country":"ES",
    "sg:address":"Av M. Celayeta, 75",
    "sg:city":"Iru\u00f1a",
    "sg:orig_category":"Inform\u00c1tica (estudios, Servicios, Asesor\u00cda, Formaci\u00d3n)",
    "sg:phone":"+34 948 38 47 37",
    "sg:postcode":"31014",
    "sg:province":"Navarra",
    "sg:website":"www.interamedia.com",
    "wof:name":"Interamedia Events S.l.",
    "wof:placetype":"venue"
},
  "geometry": {"coordinates":[-1.6437540054,42.81275177],"type":"Point"}
}