{
  "type": "Feature",
  "properties": {
    "addr:full":"Ctra. Adanero-gijon, Km. 0195,0 Valladolid Valladolid 47009",
    "addr:postcode":"47009",
    "addr:street":"Ctra. Adanero-Gijon Km. 0195,0",
    "iso:country":"ES",
    "sg:address":"Ctra. Adanero-gijon, Km. 0195,0",
    "sg:city":"Valladolid",
    "sg:orig_category":"Agentes, Concesionarios Y Sucursales De Veh\u00cdculos",
    "sg:phone":"+34 983 35 50 55",
    "sg:postcode":"47009",
    "sg:province":"Valladolid",
    "wof:name":"Autojucar S.a.",
    "wof:placetype":"venue"
},
  "geometry": {"coordinates":[-4.7737565041,41.6607093811],"type":"Point"}
}