{
  "type": "Feature",
  "properties": {
    "addr:full":"Carrer de Brutau, 35 Sabadell Barcelona 08203",
    "addr:housenumber":"35",
    "addr:postcode":"08203",
    "addr:street":"Carrer De Brutau",
    "iso:country":"ES",
    "sg:address":"Carrer de Brutau, 35",
    "sg:city":"Sabadell",
    "sg:orig_category":"Ropa De Trabajo Y Profesionales (al Por Menor)",
    "sg:phone":"+34 937 10 64 12",
    "sg:postcode":"08203",
    "sg:province":"Barcelona",
    "wof:name":"Elezos Uniformes S.l.",
    "wof:placetype":"venue"
},
  "geometry": {"coordinates":[2.1113131046,41.5365867615],"type":"Point"}
}