{
  "type": "Feature",
  "properties": {
    "addr:full":"Calle de Castellon, 14 Navajas Castell\u00f3n 12470",
    "addr:housenumber":"14",
    "addr:postcode":"12470",
    "addr:street":"Calle De Castellon;Castello\u0301N",
    "iso:country":"ES",
    "sg:address":"Calle de Castellon, 14",
    "sg:city":"Navajas",
    "sg:orig_category":"Cajas De Ahorro",
    "sg:phone":"+34 964 71 16 90",
    "sg:postcode":"12470",
    "sg:province":"Castell\u00f3n",
    "sg:website":"www.bancaja.es",
    "wof:name":"Caja De Ahorros De Valencia Castellon Y Alicante",
    "wof:placetype":"venue"
},
  "geometry": {"coordinates":[-0.5076140165,39.8775291443],"type":"Point"}
}