{
  "type": "Feature",
  "properties": {
    "addr:full":"Calle de Camino Del Hierro (trasera), 6 Santa Cruz De Tenerife Santa Cruz De Tenerife 38009",
    "addr:housenumber":"6",
    "addr:postcode":"38009",
    "addr:street":"Calle De Camino Del Hierro Trasera",
    "iso:country":"ES",
    "sg:address":"Calle de Camino Del Hierro (trasera), 6",
    "sg:city":"Santa Cruz De Tenerife",
    "sg:orig_category":"Artes Gr\u00c1ficas, Artes Pl\u00c1sticas (curso)",
    "sg:phone":"+34 922 20 26 16",
    "sg:postcode":"38009",
    "sg:province":"Santa Cruz De Tenerife",
    "wof:name":"Gobierno De Canarias",
    "wof:placetype":"venue"
},
  "geometry": {"coordinates":[-16.2764835358,28.4607124329],"type":"Point"}
}