{
  "type": "Feature",
  "properties": {
    "addr:full":"Calle de Arane, 11 Bilbao Vizcaya 48012",
    "addr:housenumber":"11",
    "addr:postcode":"48012",
    "addr:street":"Calle De Arane",
    "iso:country":"ES",
    "sg:address":"Calle de Arane, 11",
    "sg:city":"Bilbao",
    "sg:orig_category":"Alquiler De V\u00cddeo",
    "sg:phone":"+34 944 10 46 76",
    "sg:postcode":"48012",
    "sg:province":"Vizcaya",
    "wof:name":"Arane Video,c.b.",
    "wof:placetype":"venue"
},
  "geometry": {"coordinates":[-2.9371767044,43.2501716614],"type":"Point"}
}