{
  "type": "Feature",
  "properties": {
    "iso:country":"ES",
    "sg:address":"Ctra Cobre (al), 143",
    "sg:city":"Algeciras",
    "sg:orig_category":"Farmacias",
    "sg:phone":"+34 956 60 12 07",
    "sg:postcode":"11206",
    "sg:province":"C\u00e1diz",
    "wof:name":"Mejias Larque Fabiola",
    "wof:placetype":"venue"
},
  "geometry": {"coordinates":[-5.4615569115,36.1137046814],"type":"Point"}
}