{
  "type": "Feature",
  "properties": {
    "addr:full":"Calle de San Juan, 53 Arganda Madrid 28500",
    "addr:housenumber":"53",
    "addr:postcode":"28500",
    "addr:street":"Calle De San Juan",
    "iso:country":"ES",
    "sg:address":"Calle de San Juan, 53",
    "sg:city":"Arganda",
    "sg:orig_category":"Molduras, Junquillos, Listones Y Molduras Perforadas",
    "sg:phone":"+34 918 70 43 62",
    "sg:postcode":"28500",
    "sg:province":"Madrid",
    "wof:name":"Rinaldi Capparelli Flavio",
    "wof:placetype":"venue"
},
  "geometry": {"coordinates":[-3.4406979084,40.2999954224],"type":"Point"}
}