{
  "type": "Feature",
  "properties": {
    "iso:country":"ES",
    "sg:address":"Calle de Nogaredo, S/n",
    "sg:city":"Seoane Do Courel",
    "sg:orig_category":"Farmacias",
    "sg:phone":"+34 982 18 55 80",
    "sg:postcode":"27324",
    "sg:province":"Lugo",
    "wof:name":"Prieto Barros Jorge Jesus",
    "wof:placetype":"venue"
},
  "geometry": {"coordinates":[-7.5693798065,43.0095100403],"type":"Point"}
}