{
  "type": "Feature",
  "properties": {
    "addr:full":"Carrer de Passerell, 19 Barcelona Barcelona 08032",
    "addr:housenumber":"19",
    "addr:postcode":"08032",
    "addr:street":"Carrer De Passerell",
    "iso:country":"ES",
    "sg:address":"Carrer de Passerell, 19",
    "sg:city":"Barcelona",
    "sg:orig_category":"Promotores Constructores",
    "sg:phone":"+34 934 20 74 97",
    "sg:postcode":"08032",
    "sg:province":"Barcelona",
    "wof:name":"Jimenez Martin Maria A.",
    "wof:placetype":"venue"
},
  "geometry": {"coordinates":[2.1585850716,41.4208831787],"type":"Point"}
}