{
  "type": "Feature",
  "properties": {
    "iso:country":"ES",
    "sg:address":"Carrer de Mercat, 16",
    "sg:city":"Sant Joan D'alacant",
    "sg:orig_category":"Fabricaci\u00d3n, Importaci\u00d3n, Venta De Material De Telefon\u00cda, Peritelefon\u00cda",
    "sg:phone":"+34 965 65 40 90",
    "sg:postcode":"03550",
    "sg:province":"Alicante",
    "wof:name":"Aguilar Arcos Faustino",
    "wof:placetype":"venue"
},
  "geometry": {"coordinates":[-0.4337727129,38.3993911743],"type":"Point"}
}