{
  "type": "Feature",
  "properties": {
    "addr:full":"Calle de Cervantes, 2 Ceuta Ceuta 51001",
    "addr:housenumber":"2",
    "addr:postcode":"51001",
    "addr:street":"Calle De Cervantes",
    "iso:country":"ES",
    "sg:address":"Calle de Cervantes, 2",
    "sg:city":"Ceuta",
    "sg:orig_category":"Ropa Para Se\u00d1oras (al Por Menor)",
    "sg:phone":"+34 956 51 50 00",
    "sg:postcode":"51001",
    "sg:province":"Ceuta",
    "wof:name":"De Juan Rodriguez Rosa Maria",
    "wof:placetype":"venue"
},
  "geometry": {"coordinates":[-5.3104739189,35.8864936829],"type":"Point"}
}