{
  "type": "Feature",
  "properties": {
    "iso:country":"ES",
    "sg:address":"Carrer de Doctor Trueta, 13",
    "sg:city":"S. Celoni",
    "sg:orig_category":"Cl\u00cdnicas Dentales",
    "sg:phone":"+34 938 67 25 10",
    "sg:postcode":"08470",
    "sg:province":"Barcelona",
    "wof:name":"Sant Celoni Dental Dent S.c.p.",
    "wof:placetype":"venue"
},
  "geometry": {"coordinates":[2.4881000519,41.6855506897],"type":"Point"}
}