{
  "type": "Feature",
  "properties": {
    "iso:country":"ES",
    "sg:address":"Calle de Metalurgicos, 3",
    "sg:city":"Callfersa",
    "sg:orig_category":"Agentes, Concesionarios Y Sucursales De Veh\u00cdculos",
    "sg:phone":"+34 916 85 20 67",
    "sg:postcode":"28942",
    "sg:province":"Madrid",
    "wof:name":"Vehinter S.a.",
    "wof:placetype":"venue"
},
  "geometry": {"coordinates":[-3.8370990753,40.2988739014],"type":"Point"}
}