{
  "type": "Feature",
  "properties": {
    "addr:full":"Carrer de Comerc, 9 Vilafranca Penedes Barcelona 08720",
    "addr:housenumber":"9",
    "addr:postcode":"08720",
    "addr:street":"Carrer De Comerc;Penedes Barcelona",
    "iso:country":"ES",
    "sg:address":"Carrer de Comerc, 9",
    "sg:city":"Vilafranca Penedes",
    "sg:orig_category":"Promotores Constructores",
    "sg:phone":"+34 938 17 44 33",
    "sg:postcode":"08720",
    "sg:province":"Barcelona",
    "wof:name":"Treima S.l",
    "wof:placetype":"venue"
},
  "geometry": {"coordinates":[1.7049789429,41.3457603455],"type":"Point"}
}