{
  "type": "Feature",
  "properties": {
    "addr:full":"Crta Xerta, S/n Jesus Tarragona 43590",
    "addr:housenumber":"s / n",
    "addr:postcode":"43590",
    "addr:street":"Crta Xerta",
    "iso:country":"ES",
    "sg:address":"Crta Xerta, S/n",
    "sg:city":"Jesus",
    "sg:orig_category":"Negocio De Materiales De Construcci\u00d3n",
    "sg:phone":"+34 977 50 03 06",
    "sg:postcode":"43590",
    "sg:province":"Tarragona",
    "wof:name":"Materials Gisbert C.b.",
    "wof:placetype":"venue"
},
  "geometry": {"coordinates":[0.5111449957,40.8273506165],"type":"Point"}
}