{
  "type": "Feature",
  "properties": {
    "iso:country":"ES",
    "sg:address":"Calle de Camino Viejo De Getafe (del), 45",
    "sg:city":"Fuenlabrada",
    "sg:orig_category":"Aperitivos (fabricaci\u00d3n Y Al Por Mayor)",
    "sg:phone":"+34 916 15 75 15",
    "sg:postcode":"28946",
    "sg:province":"Madrid",
    "wof:name":"Aperitivos Trebol S.l.",
    "wof:placetype":"venue"
},
  "geometry": {"coordinates":[-3.7775092125,40.2821235657],"type":"Point"}
}