{
  "type": "Feature",
  "properties": {
    "addr:full":"Plaz Constitucion (de La), 5 Conil De La Frontera C\u00e1diz 11140",
    "addr:housenumber":"5",
    "addr:postcode":"11140",
    "iso:country":"ES",
    "sg:address":"Plaz Constitucion (de La), 5",
    "sg:city":"Conil De La Frontera",
    "sg:orig_category":"Fabricaci\u00d3n, Instalaci\u00d3n Y Reparaci\u00d3n De Bombas",
    "sg:phone":"+34 956 45 60 00",
    "sg:postcode":"11140",
    "sg:province":"C\u00e1diz",
    "wof:name":"Perforaciones Conil Sondeos Y Aguas S.l.",
    "wof:placetype":"venue"
},
  "geometry": {"coordinates":[-6.0878691673,36.2776184082],"type":"Point"}
}