{
  "type": "Feature",
  "properties": {
    "addr:full":"Calle de Reina Fabiola, 31 Zaragoza Zaragoza 50008",
    "addr:housenumber":"31",
    "addr:postcode":"50008",
    "addr:street":"Calle De Reina Fabiola",
    "iso:country":"ES",
    "sg:address":"Calle de Reina Fabiola, 31",
    "sg:city":"Zaragoza",
    "sg:orig_category":"Bisuter\u00cda, Joyer\u00cda, Relojer\u00cda (al Por Menor)",
    "sg:phone":"+34 976 49 16 81",
    "sg:postcode":"50008",
    "sg:province":"Zaragoza",
    "wof:name":"Ralla Larriba Julio",
    "wof:placetype":"venue"
},
  "geometry": {"coordinates":[-0.8753399849,41.6447486877],"type":"Point"}
}