{
  "type": "Feature",
  "properties": {
    "iso:country":"ES",
    "sg:address":"Rua Cancean, 1",
    "sg:city":"Culleredo",
    "sg:orig_category":"Carnicer\u00cdas, Carnicer\u00cdas",
    "sg:phone":"+34 981 67 70 58",
    "sg:postcode":"15189",
    "sg:province":"A Coru\u00f1a",
    "wof:name":"Vazquez Miguez Juan",
    "wof:placetype":"venue"
},
  "geometry": {"coordinates":[-8.3889083862,43.2941017151],"type":"Point"}
}