{
  "type": "Feature",
  "properties": {
    "iso:country":"ES",
    "sg:address":"Calle de Lasaga Larreta, 7",
    "sg:city":"Torrelavega",
    "sg:orig_category":"Hilaturas, Hilos Y Actividades Relacionadas",
    "sg:phone":"+34 942 80 04 60",
    "sg:postcode":"39300",
    "sg:province":"Cantabria",
    "wof:name":"Geonorte S.l.",
    "wof:placetype":"venue"
},
  "geometry": {"coordinates":[-4.0520658493,43.3501167297],"type":"Point"}
}