{
  "type": "Feature",
  "properties": {
    "addr:full":"Carr Closa D'en Llop, 116 Escala Girona 17130",
    "addr:housenumber":"116",
    "addr:postcode":"17130",
    "addr:street":"Carr Closa D'En Llop",
    "iso:country":"ES",
    "sg:address":"Carr Closa D'en Llop, 116",
    "sg:city":"Escala",
    "sg:orig_category":"Deportes N\u00c1uticos, Acu\u00c1ticos Y Subacu\u00c1ticos: Art\u00cdculos Y Equipo (al Por Menor)",
    "sg:phone":"+34 972 77 07 55",
    "sg:postcode":"17130",
    "sg:province":"Girona",
    "wof:name":"Palau Oliveras Abel",
    "wof:placetype":"venue"
},
  "geometry": {"coordinates":[3.1279199123,42.1169548035],"type":"Point"}
}