{
  "type": "Feature",
  "properties": {
    "addr:full":"Calle de Reyes Catolicos, 3 Toledo Toledo 45002",
    "addr:housenumber":"3",
    "addr:postcode":"45002",
    "addr:street":"Calle De Reyes Catolicos",
    "iso:country":"ES",
    "sg:address":"Calle de Reyes Catolicos, 3",
    "sg:city":"Toledo",
    "sg:orig_category":"Art\u00cdculos De Regalo (al Por Menor)",
    "sg:phone":"+34 925 21 52 26",
    "sg:postcode":"45002",
    "sg:province":"Toledo",
    "wof:name":"Parra Diaz Maria Pilar",
    "wof:placetype":"venue"
},
  "geometry": {"coordinates":[-4.0302209854,39.8559494019],"type":"Point"}
}