{
  "type": "Feature",
  "properties": {
    "iso:country":"ES",
    "sg:address":"Calle de Fray Julian Garces, 16",
    "sg:city":"Zaragoza",
    "sg:classifiers":[
        {
            "category":"Casinos & Gambling",
            "type":"Entertainment"
        }
    ],
    "sg:phone":"+34 976 38 20 55",
    "sg:postcode":"50007",
    "sg:province":"Zaragoza",
    "sg:tags":[
        "locale",
        "de",
        "juego"
    ],
    "wof:name":"Oper Ortiz S.a.",
    "wof:placetype":"venue"
},
  "geometry": {"coordinates":[-0.8865399957,41.6311988831],"type":"Point"}
}