{
  "type": "Feature",
  "properties": {
    "addr:full":"Pza Mayor, S/n Movera Zaragoza 50194",
    "addr:housenumber":"s",
    "addr:postcode":"50194",
    "addr:street":"Pza Mayor;/ N Movera",
    "iso:country":"ES",
    "sg:address":"Pza Mayor, S/n",
    "sg:city":"Movera",
    "sg:orig_category":"Iglesia Cat\u00d3lica",
    "sg:phone":"+34 976 58 64 83",
    "sg:postcode":"50194",
    "sg:province":"Zaragoza",
    "wof:name":"Parroquia De Nuestra Se\u00f1ora De Movera",
    "wof:placetype":"venue"
},
  "geometry": {"coordinates":[-0.8220970035,41.6496505737],"type":"Point"}
}