{
  "type": "Feature",
  "properties": {
    "iso:country":"ES",
    "sg:address":"Pase Arroyomolinos (de), 36",
    "sg:city":"Mostoles",
    "sg:orig_category":"Maquinaria Y Herramientas Para Madera, Pvc, Aluminio Y Aperos (fabricaci\u00d3n, Comercio)",
    "sg:phone":"+34 916 13 77 13",
    "sg:postcode":"28938",
    "sg:province":"Madrid",
    "wof:name":"Cesteros Ortega Angel",
    "wof:placetype":"venue"
},
  "geometry": {"coordinates":[-3.8882100582,40.2945251465],"type":"Point"}
}