{
  "type": "Feature",
  "properties": {
    "addr:full":"Carr Xaloc, 7 Gantxo Alicante 03690",
    "addr:housenumber":"7",
    "addr:postcode":"03690",
    "addr:street":"Carr Xaloc;Alicante",
    "iso:country":"ES",
    "sg:address":"Carr Xaloc, 7",
    "sg:city":"Gantxo",
    "sg:orig_category":"Alquiler De Veh\u00cdculos: Turismos Y Utilitarios",
    "sg:phone":"+34 965 66 05 24",
    "sg:postcode":"03690",
    "sg:province":"Alicante",
    "wof:name":"Celex Broker S.l.",
    "wof:placetype":"venue"
},
  "geometry": {"coordinates":[-0.5231339931,38.3981590271],"type":"Point"}
}