{
  "type": "Feature",
  "properties": {
    "iso:country":"ES",
    "sg:address":"Calle de Fernandez De Ribera, 14",
    "sg:city":"Sevilla",
    "sg:orig_category":"Cristaler\u00cdas",
    "sg:phone":"+34 954 65 23 78",
    "sg:postcode":"41005",
    "sg:province":"Sevilla",
    "wof:name":"Rodriguez Rocha Maria",
    "wof:placetype":"venue"
},
  "geometry": {"coordinates":[-5.9693408012,37.3765182495],"type":"Point"}
}