{
  "type": "Feature",
  "properties": {
    "iso:country":"ES",
    "sg:address":"Plaz Conde Del Valle De Suchil, 7",
    "sg:city":"Madrid",
    "sg:orig_category":"Expertos Contables, Revisores De Cuentas",
    "sg:phone":"+34 914 44 56 14",
    "sg:postcode":"28015",
    "sg:province":"Madrid",
    "wof:name":"Atenea Auditores S.l.",
    "wof:placetype":"venue"
},
  "geometry": {"coordinates":[-3.7105116844,40.4304542542],"type":"Point"}
}