{
  "type": "Feature",
  "properties": {
    "addr:full":"Carrer de Ausias March, 16 Palma Islas Baleares 07003",
    "addr:housenumber":"16",
    "addr:postcode":"07003",
    "addr:street":"Carrer De Ausias March",
    "iso:country":"ES",
    "sg:address":"Carrer de Ausias March, 16",
    "sg:city":"Palma",
    "sg:orig_category":"Promotores Constructores",
    "sg:phone":"+34 971 75 79 42",
    "sg:postcode":"07003",
    "sg:province":"Islas Baleares",
    "wof:name":"Construcciones Palma 97 S.l.",
    "wof:placetype":"venue"
},
  "geometry": {"coordinates":[2.6508231163,39.5824165344],"type":"Point"}
}