{
  "type": "Feature",
  "properties": {
    "addr:full":"G.v. Escultor Francisco Salzillo, 13 Santa Catalina Murcia 30004",
    "addr:housenumber":"13",
    "addr:postcode":"30004",
    "addr:street":"Escultor Francisco Salzillo",
    "iso:country":"ES",
    "sg:address":"G.v. Escultor Francisco Salzillo, 13",
    "sg:city":"Santa Catalina",
    "sg:orig_category":"Cl\u00cdnicas M\u00c9dicas",
    "sg:phone":"+34 968 22 24 22",
    "sg:postcode":"30004",
    "sg:province":"Murcia",
    "wof:name":"Illan Albert Isabel",
    "wof:placetype":"venue"
},
  "geometry": {"coordinates":[-1.1320450306,37.9855918884],"type":"Point"}
}