{
  "type": "Feature",
  "properties": {
    "addr:full":"Calle de Aldehuela (la), 14 Barco De Avila \u00c1vila 05600",
    "addr:housenumber":"14",
    "addr:postcode":"05600",
    "addr:street":"Calle De Aldehuela La;A\u0301Vila",
    "iso:country":"ES",
    "sg:address":"Calle de Aldehuela (la), 14",
    "sg:city":"Barco De Avila",
    "sg:orig_category":"Venta Al Preg\u00d3n",
    "sg:phone":"+34 920 34 04 24",
    "sg:postcode":"05600",
    "sg:province":"\u00c1vila",
    "wof:name":"Justo Martin Chapinal",
    "wof:placetype":"venue"
},
  "geometry": {"coordinates":[-5.513958931,40.3574028015],"type":"Point"}
}