{
  "type": "Feature",
  "properties": {
    "addr:full":"Calle de Juan Fernandez, 31 Valle De Guerra Santa Cruz De Tenerife 38270",
    "addr:housenumber":"31",
    "addr:postcode":"38270",
    "addr:street":"Calle De Juan Fernandez",
    "iso:country":"ES",
    "sg:address":"Calle de Juan Fernandez, 31",
    "sg:city":"Valle De Guerra",
    "sg:orig_category":"Pescader\u00cdas (al Por Menor)",
    "sg:phone":"+34 922 54 39 72",
    "sg:postcode":"38270",
    "sg:province":"Santa Cruz De Tenerife",
    "wof:name":"Herrera Fernandez Juan Roque",
    "wof:placetype":"venue"
},
  "geometry": {"coordinates":[-16.3963832855,28.5111694336],"type":"Point"}
}