{
  "type": "Feature",
  "properties": {
    "iso:country":"ES",
    "sg:address":"Calle de Brasil, 8",
    "sg:city":"Zaragoza",
    "sg:orig_category":"Inmobiliaria (agencias)",
    "sg:phone":"+34 976 38 03 13",
    "sg:postcode":"50007",
    "sg:province":"Zaragoza",
    "wof:name":"Topaz Cedece S.l",
    "wof:placetype":"venue"
},
  "geometry": {"coordinates":[-0.8749939799,41.628452301],"type":"Point"}
}