{
  "type": "Feature",
  "properties": {
    "addr:full":"Carrer de Eixampla, 45 Premia Mar Barcelona 08330",
    "addr:housenumber":"45",
    "addr:postcode":"08330",
    "addr:street":"Carrer De Eixampla",
    "iso:country":"ES",
    "sg:address":"Carrer de Eixampla, 45",
    "sg:city":"Premia Mar",
    "sg:classifiers":[
        {
            "category":"Autos & Motor Vehicles",
            "subcategory":"Automobile Sales",
            "type":"Retail Goods"
        }
    ],
    "sg:phone":"+34 937 52 03 97",
    "sg:postcode":"08330",
    "sg:province":"Barcelona",
    "wof:name":"Gregal Mix S.l.",
    "wof:placetype":"venue"
},
  "geometry": {"coordinates":[2.3575189114,41.4913482666],"type":"Point"}
}