{
  "type": "Feature",
  "properties": {
    "addr:full":"Carrer de Proven\u00c7a, 504 Barcelona Barcelona 08025",
    "addr:housenumber":"504",
    "addr:postcode":"08025",
    "addr:street":"Carrer De Provenc\u0327A",
    "iso:country":"ES",
    "sg:address":"Carrer de Proven\u00c7a, 504",
    "sg:city":"Barcelona",
    "sg:orig_category":"Artesan\u00cda Y Trabajos Manuales: Suministros (al Por Menor)",
    "sg:phone":"+34 934 50 37 99",
    "sg:postcode":"08025",
    "sg:province":"Barcelona",
    "wof:name":"Martinez Martinez Nuria",
    "wof:placetype":"venue"
},
  "geometry": {"coordinates":[2.177628994,41.4066696167],"type":"Point"}
}