{
  "type": "Feature",
  "properties": {
    "iso:country":"ES",
    "sg:address":"Rua Redondela, 4",
    "sg:city":"Ribadavia",
    "sg:orig_category":"Explotaci\u00d3n De Canteras",
    "sg:phone":"+34 988 47 07 10",
    "sg:postcode":"32400",
    "sg:province":"Ourense",
    "wof:name":"Canteras Quinteiro Canal S.l.",
    "wof:placetype":"venue"
},
  "geometry": {"coordinates":[-8.1475667953,42.2839393616],"type":"Point"}
}