{
  "type": "Feature",
  "properties": {
    "iso:country":"ES",
    "sg:address":"Calle de Azorin, 22",
    "sg:city":"Almeria",
    "sg:orig_category":"Promotores Constructores",
    "sg:phone":"+34 950 22 13 11",
    "sg:postcode":"04005",
    "sg:province":"Almer\u00eda",
    "wof:name":"Geyco S.l.",
    "wof:placetype":"venue"
},
  "geometry": {"coordinates":[-2.4558103085,36.838344574],"type":"Point"}
}