{
  "type": "Feature",
  "properties": {
    "addr:full":"Rua Doctor Casares, 21 Monforte De Lemos Lugo 27400",
    "addr:housenumber":"21",
    "addr:postcode":"27400",
    "addr:street":"Rua Doctor Casares",
    "iso:country":"ES",
    "sg:address":"Rua Doctor Casares, 21",
    "sg:city":"Monforte De Lemos",
    "sg:orig_category":"Sanatorios M\u00c9dico",
    "sg:phone":"+34 982 40 47 12",
    "sg:postcode":"27400",
    "sg:province":"Lugo",
    "wof:name":"Sergas-atencion Primaria Lugo",
    "wof:placetype":"venue"
},
  "geometry": {"coordinates":[-7.5103502274,42.5263061523],"type":"Point"}
}