{
  "type": "Feature",
  "properties": {
    "iso:country":"ES",
    "sg:address":"Avda Ciudad De Almeria, 36",
    "sg:city":"Purisima -barriomar",
    "sg:orig_category":"Edici\u00d3n De Diarios, Revistas, Boletines",
    "sg:phone":"+34 968 34 09 68",
    "sg:postcode":"30010",
    "sg:province":"Murcia",
    "wof:name":"Producciones Mic S.l.",
    "wof:placetype":"venue"
},
  "geometry": {"coordinates":[-1.1492689848,37.9747200012],"type":"Point"}
}