{
  "type": "Feature",
  "properties": {
    "iso:country":"ES",
    "sg:address":"Fraga Do Rei, S/n",
    "sg:city":"Fraga Do Rei",
    "sg:orig_category":"Asociaciones, Organismos Culturales Y Socioeducativos",
    "sg:phone":"+34 986 49 78 32",
    "sg:postcode":"36843",
    "sg:province":"Pontevedra",
    "wof:name":"Sociedad Cultural Y Recreativa Moscoso",
    "wof:placetype":"venue"
},
  "geometry": {"coordinates":[-8.5313234329,42.3119163513],"type":"Point"}
}