{
  "type": "Feature",
  "properties": {
    "iso:country":"ES",
    "sg:address":"Rua Castelao, 2",
    "sg:city":"Burela",
    "sg:classifiers":[
        {
            "category":"Recreation",
            "type":"Entertainment"
        }
    ],
    "sg:phone":"+34 982 58 50 25",
    "sg:postcode":"27880",
    "sg:province":"Lugo",
    "sg:tags":[
        "caza",
        "pr\u00c1ctica",
        "la",
        "de",
        "pesca",
        "y"
    ],
    "wof:name":"Antonio Maya Fernandez Y Otros C.b.",
    "wof:placetype":"venue"
},
  "geometry": {"coordinates":[-7.3588643074,43.6614990234],"type":"Point"}
}