{
  "type": "Feature",
  "properties": {
    "iso:country":"ES",
    "sg:address":"Avda Antonio Tore Tore, S/n",
    "sg:city":"Torre Mar",
    "sg:orig_category":"Cr\u00cda De Perros Y De Gatos",
    "sg:phone":"+34 952 54 24 31",
    "sg:postcode":"29740",
    "sg:province":"M\u00e1laga",
    "wof:name":"Lopez Mata Christian",
    "wof:placetype":"venue"
},
  "geometry": {"coordinates":[-4.0975542068,36.7368202209],"type":"Point"}
}