{
  "type": "Feature",
  "properties": {
    "iso:country":"ES",
    "sg:address":"Calle de Badostain, S/n",
    "sg:city":"Huarte O Uharte",
    "sg:orig_category":"Charcuter\u00cdas (al Por Menor)",
    "sg:phone":"+34 948 33 02 29",
    "sg:postcode":"31620",
    "sg:province":"Navarra",
    "wof:name":"Mendia Martinez Francisco",
    "wof:placetype":"venue"
},
  "geometry": {"coordinates":[-1.6050490141,42.8258056641],"type":"Point"}
}