{
  "type": "Feature",
  "properties": {
    "iso:country":"ES",
    "sg:address":"Carr Sant Josep, 23",
    "sg:city":"Picanya",
    "sg:orig_category":"Estancos",
    "sg:phone":"+34 961 59 20 86",
    "sg:postcode":"46210",
    "sg:province":"Valencia",
    "wof:name":"Almenar Canoves Elena",
    "wof:placetype":"venue"
},
  "geometry": {"coordinates":[-0.4361309111,39.4337882996],"type":"Point"}
}