{
  "type": "Feature",
  "properties": {
    "addr:full":"Calle de Viera Y Clavijo, 19 Palmas De Gran Canaria Las Palmas 35002",
    "addr:housenumber":"19",
    "addr:postcode":"35002",
    "addr:street":"Calle De Viera Y Clavijo",
    "iso:country":"ES",
    "sg:address":"Calle de Viera Y Clavijo, 19",
    "sg:city":"Palmas De Gran Canaria",
    "sg:orig_category":"M\u00c9dicos: Otorrinolaringolog\u00cda",
    "sg:phone":"+34 928 37 26 36",
    "sg:postcode":"35002",
    "sg:province":"Las Palmas",
    "wof:name":"Cuyas De Torres Jose Maria",
    "wof:placetype":"venue"
},
  "geometry": {"coordinates":[-15.417678833,28.1059436798],"type":"Point"}
}