{
  "type": "Feature",
  "properties": {
    "iso:country":"ES",
    "sg:address":"Calle de Alamillo, 2",
    "sg:city":"Ontigola",
    "sg:orig_category":"Inmobiliaria (agencias)",
    "sg:phone":"+34 925 14 21 96",
    "sg:postcode":"45340",
    "sg:province":"Toledo",
    "wof:name":"Fincas Alamillo S.l.",
    "wof:placetype":"venue"
},
  "geometry": {"coordinates":[-3.5758035183,40.0049476624],"type":"Point"}
}