{
  "type": "Feature",
  "properties": {
    "iso:country":"ES",
    "sg:address":"Calle de Artatza, 6",
    "sg:city":"Artatza",
    "sg:orig_category":"Caf\u00c9s, Bares, Cervecer\u00cdas",
    "sg:phone":"+34 944 91 24 78",
    "sg:postcode":"48940",
    "sg:province":"Vizcaya",
    "wof:name":"Llavero Cuadros Marcelino",
    "wof:placetype":"venue"
},
  "geometry": {"coordinates":[-2.9983971119,43.3328323364],"type":"Point"}
}