{
  "type": "Feature",
  "properties": {
    "addr:full":"Calle de Carlos I, 21 Cuacos Yuste C\u00e1ceres 10430",
    "addr:housenumber":"21",
    "addr:postcode":"10430",
    "addr:street":"Calle De Carlos I;Ca\u0301Ceres",
    "iso:country":"ES",
    "sg:address":"Calle de Carlos I, 21",
    "sg:city":"Cuacos Yuste",
    "sg:orig_category":"Reposter\u00cdas",
    "sg:phone":"+34 927 17 20 08",
    "sg:postcode":"10430",
    "sg:province":"C\u00e1ceres",
    "wof:name":"I\u00f1igo Mu\u00f1oz Juan",
    "wof:placetype":"venue"
},
  "geometry": {"coordinates":[-5.7245864868,40.1051445007],"type":"Point"}
}