{
  "type": "Feature",
  "properties": {
    "addr:full":"Av 27 Gener, 46 Aitona Lleida 25182",
    "addr:housenumber":"46",
    "addr:postcode":"25182",
    "addr:street":"Av 27 Gener",
    "iso:country":"ES",
    "sg:address":"Av 27 Gener, 46",
    "sg:city":"Aitona",
    "sg:orig_category":"Droguer\u00cdas (al Por Menor)",
    "sg:phone":"+34 973 79 44 28",
    "sg:postcode":"25182",
    "sg:province":"Lleida",
    "sg:website":"www.schlecker.com",
    "wof:name":"Schlecker S.a.",
    "wof:placetype":"venue"
},
  "geometry": {"coordinates":[0.4595000148,41.4930076599],"type":"Point"}
}