{
  "type": "Feature",
  "properties": {
    "addr:full":"Carrer de Francisco De Vitoria, 50 Terrassa Barcelona 08225",
    "addr:housenumber":"50",
    "addr:postcode":"08225",
    "addr:street":"Carrer De Francisco De Vitoria",
    "iso:country":"ES",
    "sg:address":"Carrer de Francisco De Vitoria, 50",
    "sg:city":"Terrassa",
    "sg:orig_category":"Asesor\u00cda Fiscal Y Jur\u00cddica",
    "sg:phone":"+34 937 88 62 60",
    "sg:postcode":"08225",
    "sg:province":"Barcelona",
    "wof:name":"Couso Mu\u00f1oz Jose Luis",
    "wof:placetype":"venue"
},
  "geometry": {"coordinates":[2.0018041134,41.5728111267],"type":"Point"}
}