{
  "type": "Feature",
  "properties": {
    "addr:full":"Carrer de Oscar Espla, 9 Crevillent Alicante 03330",
    "addr:housenumber":"9",
    "addr:postcode":"03330",
    "addr:street":"Carrer De Oscar Espla",
    "iso:country":"ES",
    "sg:address":"Carrer de Oscar Espla, 9",
    "sg:city":"Crevillent",
    "sg:orig_category":"Artes Gr\u00c1ficas, Artes Pl\u00c1sticas (curso)",
    "sg:phone":"+34 965 40 06 34",
    "sg:postcode":"03330",
    "sg:province":"Alicante",
    "wof:name":"Adan Macia Jose Antonio",
    "wof:placetype":"venue"
},
  "geometry": {"coordinates":[-0.8093270063,38.2446060181],"type":"Point"}
}