{
  "type": "Feature",
  "properties": {
    "iso:country":"ES",
    "sg:address":"Carrer de Villarroel, 214",
    "sg:city":"Barcelona",
    "sg:orig_category":"Ense\u00d1ante, Direcci\u00d3n",
    "sg:phone":"+34 934 30 18 19",
    "sg:postcode":"08036",
    "sg:province":"Barcelona",
    "wof:name":"Perez Alberdi Augusto",
    "wof:placetype":"venue"
},
  "geometry": {"coordinates":[2.1479690075,41.3920326233],"type":"Point"}
}