{
  "type": "Feature",
  "properties": {
    "iso:country":"ES",
    "sg:address":"Calle de Alfonso Xiii, 19",
    "sg:city":"Membrilla",
    "sg:orig_category":"M\u00c9dicos: Medicina Del Trabajo",
    "sg:phone":"+34 926 63 65 85",
    "sg:postcode":"13230",
    "sg:province":"Ciudad Real",
    "wof:name":"Prevencion Y Salud Roman Menchen S.l.",
    "wof:placetype":"venue"
},
  "geometry": {"coordinates":[-3.3402295113,38.9738235474],"type":"Point"}
}