{
  "type": "Feature",
  "properties": {
    "iso:country":"ES",
    "sg:address":"Pl Prim, 5",
    "sg:city":"Reus",
    "sg:orig_category":"Abogados",
    "sg:phone":"+34 977 34 04 67",
    "sg:postcode":"43201",
    "sg:province":"Tarragona",
    "wof:name":"Rodon Ibarz Francisco",
    "wof:placetype":"venue"
},
  "geometry": {"coordinates":[1.1070300341,41.1559295654],"type":"Point"}
}