{
  "type": "Feature",
  "properties": {
    "addr:full":"Calle de San Pedro, 15 Torrijo Campo Teruel 44393",
    "addr:housenumber":"15",
    "addr:postcode":"44393",
    "addr:street":"Calle De San Pedro",
    "iso:country":"ES",
    "sg:address":"Calle de San Pedro, 15",
    "sg:city":"Torrijo Campo",
    "sg:orig_category":"Contenedores (mercanc\u00cdas)",
    "sg:phone":"+34 978 86 22 05",
    "sg:postcode":"44393",
    "sg:province":"Teruel",
    "wof:name":"Lahoz Lamota Fermin",
    "wof:placetype":"venue"
},
  "geometry": {"coordinates":[-1.3364390135,40.8271217346],"type":"Point"}
}