{
  "type": "Feature",
  "properties": {
    "iso:country":"ES",
    "sg:address":"Calle de Montero, 40",
    "sg:city":"Mostoles",
    "sg:orig_category":"Colchones (fabricaci\u00d3n, Al Por Mayor, Al Por Menor)",
    "sg:phone":"+34 916 13 91 25",
    "sg:postcode":"28934",
    "sg:province":"Madrid",
    "wof:name":"Benitez Garcia Maria",
    "wof:placetype":"venue"
},
  "geometry": {"coordinates":[-3.8674058914,40.3203392029],"type":"Point"}
}