{
  "type": "Feature",
  "properties": {
    "addr:full":"Calle de Molinos, 32 Granada Granada 18009",
    "addr:housenumber":"32",
    "addr:postcode":"18009",
    "addr:street":"Calle De Molinos",
    "iso:country":"ES",
    "sg:address":"Calle de Molinos, 32",
    "sg:city":"Granada",
    "sg:orig_category":"Farmacias",
    "sg:phone":"+34 958 22 46 33",
    "sg:postcode":"18009",
    "sg:province":"Granada",
    "wof:name":"Perez Jimenez Maria Dolores",
    "wof:placetype":"venue"
},
  "geometry": {"coordinates":[-3.5924828053,37.1725959778],"type":"Point"}
}