{
  "type": "Feature",
  "properties": {
    "addr:full":"Calle de Pintor Luis Alvarez, 3 Cangas Narcea Asturias 33800",
    "addr:housenumber":"3",
    "addr:postcode":"33800",
    "addr:street":"Calle De Pintor Luis Alvarez",
    "iso:country":"ES",
    "sg:address":"Calle de Pintor Luis Alvarez, 3",
    "sg:city":"Cangas Narcea",
    "sg:classifiers":[
        {
            "category":"Autos & Motor Vehicles",
            "subcategory":"Automobile Sales",
            "type":"Retail Goods"
        }
    ],
    "sg:phone":"+34 985 81 02 29",
    "sg:postcode":"33800",
    "sg:province":"Asturias",
    "wof:name":"Autoescuela Narcea C.b.",
    "wof:placetype":"venue"
},
  "geometry": {"coordinates":[-6.5522990227,43.1782112122],"type":"Point"}
}