{
  "type": "Feature",
  "properties": {
    "iso:country":"ES",
    "sg:address":"Carrer de Muntaner, 267",
    "sg:city":"Barcelona",
    "sg:orig_category":"Agencias Y Asesores De Publicidad",
    "sg:phone":"+34 932 01 08 25",
    "sg:postcode":"08021",
    "sg:province":"Barcelona",
    "wof:name":"Saga Comunicacion S.l.",
    "wof:placetype":"venue"
},
  "geometry": {"coordinates":[2.1473660469,41.3955535889],"type":"Point"}
}