{
  "type": "Feature",
  "properties": {
    "addr:full":"Avda Marques De Villanueva Del Prado, 15 Paz Santa Cruz De Tenerife 38400",
    "addr:housenumber":"15",
    "addr:postcode":"38400",
    "addr:street":"Avda Marques De Villanueva Del Prado",
    "iso:country":"ES",
    "sg:address":"Avda Marques De Villanueva Del Prado, 15",
    "sg:city":"Paz",
    "sg:orig_category":"Peluquer\u00cdas, Peluquer\u00cda Mixta",
    "sg:phone":"+34 922 38 80 78",
    "sg:postcode":"38400",
    "sg:province":"Santa Cruz De Tenerife",
    "wof:name":"Kruhai  Cristina Elisabeth Maria",
    "wof:placetype":"venue"
},
  "geometry": {"coordinates":[-16.5366001129,28.4118213654],"type":"Point"}
}