{
  "type": "Feature",
  "properties": {
    "addr:full":"Calle de Laureano Salgado, 20 Baiona Pontevedra 36300",
    "addr:housenumber":"20",
    "addr:postcode":"36300",
    "addr:street":"Calle De Laureano Salgado",
    "iso:country":"ES",
    "sg:address":"Calle de Laureano Salgado, 20",
    "sg:city":"Baiona",
    "sg:orig_category":"Arquitectos",
    "sg:phone":"+34 986 38 50 20",
    "sg:postcode":"36300",
    "sg:province":"Pontevedra",
    "wof:name":"Luis Miguel Zozaya Servera S.l.",
    "wof:placetype":"venue"
},
  "geometry": {"coordinates":[-97.78224945069999,45.7040786743],"type":"Point"}
}