{
  "type": "Feature",
  "properties": {
    "addr:full":"Plaz Lastra, S/n Sotillo Rincon Soria 42166",
    "addr:housenumber":"s / n",
    "addr:postcode":"42166",
    "addr:street":"Plaz Lastra",
    "iso:country":"ES",
    "sg:address":"Plaz Lastra, S/n",
    "sg:city":"Sotillo Rincon",
    "sg:orig_category":"Charcuter\u00cdas (al Por Mayor)",
    "sg:phone":"+34 975 27 31 32",
    "sg:postcode":"42166",
    "sg:province":"Soria",
    "wof:name":"Gomez Zardoya S.l.",
    "wof:placetype":"venue"
},
  "geometry": {"coordinates":[-2.5827510357,41.9240379333],"type":"Point"}
}