{
  "type": "Feature",
  "properties": {
    "addr:full":"Poligono Ind. Vincios, S/n Vincios Pontevedra 36316",
    "addr:housenumber":"s",
    "addr:postcode":"36316",
    "addr:street":"Poligono Ind. Vincios;/ N",
    "iso:country":"ES",
    "sg:address":"Poligono Ind. Vincios, S/n",
    "sg:city":"Vincios",
    "sg:orig_category":"Carros Elevadores, Carros De Operaciones Portuarias",
    "sg:phone":"+34 986 46 94 48",
    "sg:postcode":"36316",
    "sg:province":"Pontevedra",
    "wof:name":"Talleres Garcia Barreiro S.l.",
    "wof:placetype":"venue"
},
  "geometry": {"coordinates":[-8.7297039032,42.1394195557],"type":"Point"}
}