{
  "type": "Feature",
  "properties": {
    "addr:full":"Urb. Stio Calahonda, S/n Mijas Costa M\u00e1laga 29649",
    "addr:housenumber":"s / n",
    "addr:postcode":"29649",
    "addr:street":"Calahonda",
    "iso:country":"ES",
    "sg:address":"Urb. Stio Calahonda, S/n",
    "sg:city":"Mijas Costa",
    "sg:classifiers":[
        {
            "category":"Sports & Exercise",
            "subcategory":"Golf",
            "type":"Entertainment"
        }
    ],
    "sg:phone":"+34 952 93 33 62",
    "sg:postcode":"29649",
    "sg:province":"M\u00e1laga",
    "sg:tags":[
        "y",
        "de",
        "campos",
        "clases"
    ],
    "wof:name":"Asociacion Deportiva Club De Golf La Siesta",
    "wof:placetype":"venue"
},
  "geometry": {"coordinates":[-4.6411604881,36.5099143982],"type":"Point"}
}