{
  "type": "Feature",
  "properties": {
    "addr:full":"Estd Abaro, 10 Bilbao Vizcaya 48013",
    "addr:housenumber":"10",
    "addr:postcode":"48013",
    "addr:street":"Abaro",
    "iso:country":"ES",
    "sg:address":"Estd Abaro, 10",
    "sg:city":"Bilbao",
    "sg:orig_category":"Inmobiliaria (agencias)",
    "sg:phone":"+34 944 85 04 54",
    "sg:postcode":"48013",
    "sg:province":"Vizcaya",
    "sg:website":"www.tecnocasa.es",
    "wof:name":"Estudio Desarrollo Zorroza Sd33 S.l.",
    "wof:placetype":"venue"
},
  "geometry": {"coordinates":[-2.973154068,43.2761878967],"type":"Point"}
}