{
  "type": "Feature",
  "properties": {
    "addr:full":"Pol Ind Castillo Alto, 321 Nerja M\u00e1laga 29780",
    "addr:housenumber":"321",
    "addr:postcode":"29780",
    "addr:street":"Ma\u0301Laga",
    "iso:country":"ES",
    "sg:address":"Pol Ind Castillo Alto, 321",
    "sg:city":"Nerja",
    "sg:orig_category":"Contenedores (mercanc\u00cdas)",
    "sg:phone":"+34 952 52 46 04",
    "sg:postcode":"29780",
    "sg:province":"M\u00e1laga",
    "wof:name":"Agronerja S.l.l.",
    "wof:placetype":"venue"
},
  "geometry": {"coordinates":[-3.834998,36.795696],"type":"Point"}
}