{
  "type": "Feature",
  "properties": {
    "iso:country":"ES",
    "sg:address":"Ega\u00d1a Kalea, 9",
    "sg:city":"Zarautz",
    "sg:orig_category":"Clases De M\u00dasica Y Canto",
    "sg:phone":"+34 943 13 32 83",
    "sg:postcode":"20800",
    "sg:province":"Guip\u00f9zcoa",
    "wof:name":"Mendizabal Irigoyen Karmel Bedita",
    "wof:placetype":"venue"
},
  "geometry": {"coordinates":[-2.1734759808,43.2813339233],"type":"Point"}
}