{
  "type": "Feature",
  "properties": {
    "addr:full":"Avgd Major, 5 Massamagrell Valencia 46130",
    "addr:housenumber":"5",
    "addr:postcode":"46130",
    "iso:country":"ES",
    "sg:address":"Avgd Major, 5",
    "sg:city":"Massamagrell",
    "sg:orig_category":"\u00d3ptica: Instrumentos (fabricaci\u00d3n)",
    "sg:phone":"+34 961 44 02 39",
    "sg:postcode":"46130",
    "sg:province":"Valencia",
    "wof:name":"Rausell Garcia Maria Pilar",
    "wof:placetype":"venue"
},
  "geometry": {"coordinates":[-0.3318049908,39.569694519],"type":"Point"}
}