{
  "type": "Feature",
  "properties": {
    "iso:country":"ES",
    "sg:address":"Calle de Rafael Alberti, 20",
    "sg:city":"Coru\u00d1a",
    "sg:orig_category":"Centros P\u00dablicos De Formaci\u00d3n Profesional Y T\u00c9cnica",
    "sg:phone":"+34 981 29 23 34",
    "sg:postcode":"15008",
    "sg:province":"La Coru\u00f1a",
    "wof:name":"Quintana Garcia Juan",
    "wof:placetype":"venue"
},
  "geometry": {"coordinates":[-8.407497406,43.3463630676],"type":"Point"}
}