{
  "type": "Feature",
  "properties": {
    "addr:full":"Ctra Castellar, 3 Terrassa Barcelona 08222",
    "addr:housenumber":"3",
    "addr:postcode":"08222",
    "addr:street":"Ctra Castellar",
    "iso:country":"ES",
    "sg:address":"Ctra Castellar, 3",
    "sg:city":"Terrassa",
    "sg:orig_category":"Artes Gr\u00c1ficas, Artes Pl\u00c1sticas (curso)",
    "sg:phone":"+34 937 31 82 53",
    "sg:postcode":"08222",
    "sg:province":"Barcelona",
    "wof:name":"Copiaescola S.l.",
    "wof:placetype":"venue"
},
  "geometry": {"coordinates":[2.0224440098,41.5645904541],"type":"Point"}
}