{
  "type": "Feature",
  "properties": {
    "addr:full":"Carretera, S/n Plana Mont-ros Lleida 25510",
    "addr:postcode":"25510",
    "addr:street":"Carretera S / N Plana",
    "iso:country":"ES",
    "sg:address":"Carretera, S/n",
    "sg:city":"Plana Mont-ros",
    "sg:orig_category":"Grifer\u00cda",
    "sg:phone":"+34 973 66 30 97",
    "sg:postcode":"25510",
    "sg:province":"Lleida",
    "wof:name":"Badet Segues Jordi",
    "wof:placetype":"venue"
},
  "geometry": {"coordinates":[0.9674940109,42.3747367859],"type":"Point"}
}