{
  "type": "Feature",
  "properties": {
    "iso:country":"ES",
    "sg:address":"Carr Mallorca, 36",
    "sg:city":"Portol",
    "sg:orig_category":"Carnicer\u00cdas, Carnicer\u00cdas",
    "sg:phone":"+34 971 60 37 58",
    "sg:postcode":"07141",
    "sg:province":"Islas Baleares",
    "wof:name":"Yedro Martin Raquel",
    "wof:placetype":"venue"
},
  "geometry": {"coordinates":[2.7644240856,39.6154212952],"type":"Point"}
}