{
  "type": "Feature",
  "properties": {
    "iso:country":"ES",
    "sg:address":"Carr Cardenal Cisneros, 7",
    "sg:city":"Gandia",
    "sg:classifiers":[
        {
            "category":"Manufacturing",
            "subcategory":"Metals",
            "type":"Manufacturing & Wholesale Goods"
        }
    ],
    "sg:phone":"+34 962 87 12 05",
    "sg:postcode":"46700",
    "sg:province":"Valencia",
    "sg:tags":[
        "en",
        "fundiciones"
    ],
    "wof:name":"Albelda Climent Ricardo",
    "wof:placetype":"venue"
},
  "geometry": {"coordinates":[-0.1779233962,38.9721298218],"type":"Point"}
}