{
  "type": "Feature",
  "properties": {
    "iso:country":"ES",
    "sg:address":"C/ Vicente Blasco Iba\u00d1ez, 47",
    "sg:city":"Elche",
    "sg:orig_category":"Almacenes De Venta: Muebles, Equipo Para El Hogar",
    "sg:phone":"+34 965 46 48 72",
    "sg:postcode":"03201",
    "sg:province":"Alicante",
    "wof:name":"Muebles Meseguer S.l.",
    "wof:placetype":"venue"
},
  "geometry": {"coordinates":[-0.7044559717,38.2678642273],"type":"Point"}
}