{
  "type": "Feature",
  "properties": {
    "iso:country":"ES",
    "sg:address":"Calle de Aldabe, 7",
    "sg:city":"Vitoria-gasteiz",
    "sg:orig_category":"Asesor\u00cda Sobre Comunicaci\u00d3n De Empresas",
    "sg:phone":"+34 945 14 64 11",
    "sg:postcode":"01012",
    "sg:province":"\u00c1lava",
    "wof:name":"Grupo Empresarial De Gestion Adigest Sl",
    "wof:placetype":"venue"
},
  "geometry": {"coordinates":[-2.6759829521,42.8511428833],"type":"Point"}
}