{
  "type": "Feature",
  "properties": {
    "addr:full":"Av Generalitat De Catalunya, 15 S. Just Desvern Barcelona 08960",
    "addr:housenumber":"15",
    "addr:postcode":"08960",
    "addr:street":"Av Generalitat De Catalunya",
    "iso:country":"ES",
    "sg:address":"Av Generalitat De Catalunya, 15",
    "sg:city":"S. Just Desvern",
    "sg:orig_category":"Agencias De Relaciones P\u00dablicas",
    "sg:phone":"+34 934 73 99 84",
    "sg:postcode":"08960",
    "sg:province":"Barcelona",
    "wof:name":"Integracion Ejecutiva De Espa\u00f1a S.l.",
    "wof:placetype":"venue"
},
  "geometry": {"coordinates":[2.0733160973,41.3786277771],"type":"Point"}
}