{
  "type": "Feature",
  "properties": {
    "iso:country":"ES",
    "sg:address":"Av Pau Casals, 22",
    "sg:city":"Barcelona",
    "sg:orig_category":"Abogados",
    "sg:phone":"+34 934 14 47 87",
    "sg:postcode":"08021",
    "sg:province":"Barcelona",
    "wof:name":"Reina Bernaldez Victor",
    "wof:placetype":"venue"
},
  "geometry": {"coordinates":[2.1424911022,41.3941116333],"type":"Point"}
}