{
  "type": "Feature",
  "properties": {
    "iso:country":"ES",
    "sg:address":"Cami Can Muntanyola, 2",
    "sg:city":"Granollers",
    "sg:orig_category":"Negocio De Materiales De Construcci\u00d3n",
    "sg:phone":"+34 938 79 02 67",
    "sg:postcode":"08401",
    "sg:province":"Barcelona",
    "sg:website":"www.prefabricatslomar.com",
    "wof:name":"Prefabricats Lomar S.l.",
    "wof:placetype":"venue"
},
  "geometry": {"coordinates":[2.2846341133,41.5940818787],"type":"Point"}
}