{
  "type": "Feature",
  "properties": {
    "addr:full":"Cmno Cementerio, 19 Valladolid Valladolid 47011",
    "addr:housenumber":"19",
    "addr:postcode":"47011",
    "addr:street":"Cmno Cementerio",
    "iso:country":"ES",
    "sg:address":"Cmno Cementerio, 19",
    "sg:city":"Valladolid",
    "sg:orig_category":"Mec\u00c1nico Del Autom\u00d3vil",
    "sg:phone":"+34 983 25 85 25",
    "sg:postcode":"47011",
    "sg:province":"Valladolid",
    "wof:name":"Vaquero Luengo Anselmo",
    "wof:placetype":"venue"
},
  "geometry": {"coordinates":[-4.7059187889,41.6647796631],"type":"Point"}
}