{
  "type": "Feature",
  "properties": {
    "addr:full":"Pol Ind San Jorge, S/n Palos Frontera Huelva 21810",
    "addr:housenumber":"s / n",
    "addr:postcode":"21810",
    "addr:street":"Jorge;Palos Frontera",
    "iso:country":"ES",
    "sg:address":"Pol Ind San Jorge, S/n",
    "sg:city":"Palos Frontera",
    "sg:orig_category":"Contenedores (mercanc\u00cdas)",
    "sg:phone":"+34 959 35 02 50",
    "sg:postcode":"21810",
    "sg:province":"Huelva",
    "wof:name":"Vazquez Perez Jose",
    "wof:placetype":"venue"
},
  "geometry": {"coordinates":[-6.8923411369,37.2240829468],"type":"Point"}
}