{
  "type": "Feature",
  "properties": {
    "addr:full":"Pl Espa\u00f1a, S/n Albaida Aljarafe Sevilla 41809",
    "addr:housenumber":"s / n",
    "addr:postcode":"41809",
    "addr:street":"Pl Espan\u0303A",
    "iso:country":"ES",
    "sg:address":"Pl Espa\u00f1a, S/n",
    "sg:city":"Albaida Aljarafe",
    "sg:orig_category":"Asistencia Social",
    "sg:phone":"+34 954 11 00 01",
    "sg:postcode":"41809",
    "sg:province":"Sevilla",
    "wof:name":"Parroquia Nuestra Se\u00f1ora De La Asuncion",
    "wof:placetype":"venue"
},
  "geometry": {"coordinates":[-6.1658987999,37.4270706177],"type":"Point"}
}