{
  "type": "Feature",
  "properties": {
    "iso:country":"ES",
    "sg:address":"Calle de Canoa, 18",
    "sg:city":"Madrid",
    "sg:orig_category":"Doctores En Medicina",
    "sg:phone":"+34 917 42 99 41",
    "sg:postcode":"28042",
    "sg:province":"Madrid",
    "wof:name":"Mu\u00f1oz Avila Antonio",
    "wof:placetype":"venue"
},
  "geometry": {"coordinates":[-3.591506958,40.4535064697],"type":"Point"}
}