{
  "type": "Feature",
  "properties": {
    "iso:country":"ES",
    "sg:address":"Calle de Arco, 8",
    "sg:city":"Montalbo",
    "sg:orig_category":"Cajas De Ahorro",
    "sg:phone":"+34 969 13 00 58",
    "sg:postcode":"16440",
    "sg:province":"Cuenca",
    "sg:website":"www.ccm.es",
    "wof:name":"Caja De Ahorros De Castilla La Mancha",
    "wof:placetype":"venue"
},
  "geometry": {"coordinates":[-2.6717123985,39.8793563843],"type":"Point"}
}