{
  "type": "Feature",
  "properties": {
    "iso:country":"ES",
    "sg:address":"Calle de Ciego De Arjona, 3",
    "sg:city":"Granada",
    "sg:orig_category":"M\u00c9dicos: Pediatr\u00cda. Enfermedades De Los Ni\u00d1os",
    "sg:phone":"+34 958 20 63 55",
    "sg:postcode":"18012",
    "sg:province":"Granada",
    "wof:name":"Molina Font Juan Antonio",
    "wof:placetype":"venue"
},
  "geometry": {"coordinates":[-3.6065948009,37.1864547729],"type":"Point"}
}