{
  "type": "Feature",
  "properties": {
    "addr:full":"Ctra. Llubi, Km. 0000,8 Sa Pobla Islas Baleares 07420",
    "addr:postcode":"07420",
    "addr:street":"Ctra. Llubi Km. 0000,8",
    "iso:country":"ES",
    "sg:address":"Ctra. Llubi, Km. 0000,8",
    "sg:city":"Sa Pobla",
    "sg:orig_category":"Frutas Y Legumbres Frescas (al Por Mayor)",
    "sg:phone":"+34 971 54 07 77",
    "sg:postcode":"07420",
    "sg:province":"Islas Baleares",
    "wof:name":"Illacamp S.a.t.",
    "wof:placetype":"venue"
},
  "geometry": {"coordinates":[3.025769949,39.7738304138],"type":"Point"}
}