{
  "type": "Feature",
  "properties": {
    "iso:country":"ES",
    "sg:address":"Poli Los Ca\u00d1os, S/n",
    "sg:city":"Zafra",
    "sg:orig_category":"Empresas De Carpinter\u00cda De Madera",
    "sg:phone":"+34 924 55 02 25",
    "sg:postcode":"06300",
    "sg:province":"Badajoz",
    "wof:name":"Talleres Coinma S.l.",
    "wof:placetype":"venue"
},
  "geometry": {"coordinates":[-6.4134092331,38.4236793518],"type":"Point"}
}