{
  "type": "Feature",
  "properties": {
    "addr:full":"Iglesias, 26 Calamonte Badajoz 06810",
    "addr:housenumber":"26",
    "addr:postcode":"06810",
    "addr:street":"Iglesias",
    "iso:country":"ES",
    "sg:address":"Iglesias, 26",
    "sg:city":"Calamonte",
    "sg:orig_category":"M\u00c9dicos: Estomatolog\u00cda",
    "sg:phone":"+34 924 32 40 66",
    "sg:postcode":"06810",
    "sg:province":"Badajoz",
    "wof:name":"Fernandez-turue\u00f1o Vazquez Guadalupe Mercedes",
    "wof:placetype":"venue"
},
  "geometry": {"coordinates":[-6.3868570328,38.8898696899],"type":"Point"}
}