{
  "type": "Feature",
  "properties": {
    "addr:full":"C/ General Prieto, 3 Alcoi Alicante 03804",
    "addr:housenumber":"3",
    "addr:postcode":"03804",
    "addr:street":"C / General Prieto",
    "iso:country":"ES",
    "sg:address":"C/ General Prieto, 3",
    "sg:city":"Alcoi",
    "sg:orig_category":"Reposter\u00cdas",
    "sg:phone":"+34 965 33 00 70",
    "sg:postcode":"03804",
    "sg:province":"Alicante",
    "wof:name":"Jose Antonio Cortes Cerda S.l.",
    "wof:placetype":"venue"
},
  "geometry": {"coordinates":[-0.4704465866,38.7076416016],"type":"Point"}
}