{
  "type": "Feature",
  "properties": {
    "iso:country":"ES",
    "sg:address":"Carrer de Autonomia, 83",
    "sg:city":"Terrassa",
    "sg:orig_category":"Aparatos De Iluminaci\u00d3n (al Por Menor)",
    "sg:phone":"+34 937 35 21 28",
    "sg:postcode":"08225",
    "sg:province":"Barcelona",
    "wof:name":"Relacions Electriques S.a.",
    "wof:placetype":"venue"
},
  "geometry": {"coordinates":[2.0147171021,41.5742721558],"type":"Point"}
}