{
  "type": "Feature",
  "properties": {
    "iso:country":"ES",
    "sg:address":"Avda Parsi, 5",
    "sg:city":"Sevilla",
    "sg:orig_category":"Molduras, Junquillos, Listones Y Molduras Perforadas",
    "sg:phone":"+34 954 25 00 07",
    "sg:postcode":"41016",
    "sg:province":"Sevilla",
    "wof:name":"Pertel S.cv.",
    "wof:placetype":"venue"
},
  "geometry": {"coordinates":[-5.9191088676,37.3811836243],"type":"Point"}
}