{
  "type": "Feature",
  "properties": {
    "iso:country":"ES",
    "sg:address":"Calle de Jardin, 16",
    "sg:city":"Fuentepelayo",
    "sg:orig_category":"Molduras, Junquillos, Listones Y Molduras Perforadas",
    "sg:phone":"+34 921 57 42 11",
    "sg:postcode":"40260",
    "sg:province":"Segovia",
    "wof:name":"Delgado Martin Jose Manuel",
    "wof:placetype":"venue"
},
  "geometry": {"coordinates":[-4.1763291359,41.2240715027],"type":"Point"}
}