{
  "type": "Feature",
  "properties": {
    "iso:country":"ES",
    "sg:address":"Calle de Rascon, 22",
    "sg:city":"Huelva",
    "sg:orig_category":"Controles De Edificaci\u00d3n (construcci\u00d3n, Seguridad)",
    "sg:phone":"+34 959 24 74 65",
    "sg:postcode":"21001",
    "sg:province":"Huelva",
    "wof:name":"Marblanc S.a.",
    "wof:placetype":"venue"
},
  "geometry": {"coordinates":[-6.9532318115,37.2563056946],"type":"Point"}
}