{
  "type": "Feature",
  "properties": {
    "iso:country":"ES",
    "sg:address":"Calle de Conde De Pe\u00d1alver, 58",
    "sg:city":"Madrid",
    "sg:orig_category":"Promotores Constructores",
    "sg:phone":"+34 914 01 88 49",
    "sg:postcode":"28006",
    "sg:province":"Madrid",
    "wof:name":"Rumpal S.l.",
    "wof:placetype":"venue"
},
  "geometry": {"coordinates":[-3.675216198,40.4307785034],"type":"Point"}
}