{
  "type": "Feature",
  "properties": {
    "iso:country":"ES",
    "sg:address":"Carr Escalante, 4",
    "sg:city":"Manises",
    "sg:orig_category":"Fabrica De Cer\u00c1micas",
    "sg:phone":"+34 961 54 53 23",
    "sg:postcode":"46940",
    "sg:province":"Valencia",
    "wof:name":"Arte Estudio Valenciano S.l.",
    "wof:placetype":"venue"
},
  "geometry": {"coordinates":[-0.4639233947,39.4889564514],"type":"Point"}
}