{
  "type": "Feature",
  "properties": {
    "addr:full":"Calle de Nieves Cano, 29 Vitoria-gasteiz \u00c1lava 01006",
    "addr:housenumber":"29",
    "addr:postcode":"01006",
    "addr:street":"Calle De Nieves Cano",
    "iso:country":"ES",
    "sg:address":"Calle de Nieves Cano, 29",
    "sg:city":"Vitoria-gasteiz",
    "sg:orig_category":"Asesor\u00cdas Y Estudios Financieros",
    "sg:phone":"+34 945 15 41 75",
    "sg:postcode":"01006",
    "sg:province":"\u00c1lava",
    "wof:name":"Lautada, Sl",
    "wof:placetype":"venue"
},
  "geometry": {"coordinates":[-2.6714439392,42.8383636475],"type":"Point"}
}