{
  "type": "Feature",
  "properties": {
    "iso:country":"ES",
    "sg:address":"Calle de Rio De Oro, S/n",
    "sg:city":"Gijon",
    "sg:orig_category":"Florister\u00cdas",
    "sg:phone":"+34 985 16 39 97",
    "sg:postcode":"33209",
    "sg:province":"Asturias",
    "wof:name":"Flores Y Plantas Gijon S.l.",
    "wof:placetype":"venue"
},
  "geometry": {"coordinates":[-5.6639389992,43.5266647339],"type":"Point"}
}