{
  "type": "Feature",
  "properties": {
    "iso:country":"ES",
    "sg:address":"Carrer de Assagador (el), 16",
    "sg:city":"Aspre",
    "sg:orig_category":"Alfarer\u00cda",
    "sg:phone":"+34 965 58 32 23",
    "sg:postcode":"03790",
    "sg:province":"Alicante",
    "wof:name":"Berenguer Morell Juan Miguel",
    "wof:placetype":"venue"
},
  "geometry": {"coordinates":[-0.0627880022,38.7796516418],"type":"Point"}
}