{
  "type": "Feature",
  "properties": {
    "iso:country":"ES",
    "sg:address":"Carrer de Santa Rosalia, 139",
    "sg:city":"Barcelona",
    "sg:orig_category":"Molduras, Junquillos, Listones Y Molduras Perforadas",
    "sg:phone":"+34 933 57 91 52",
    "sg:postcode":"08032",
    "sg:province":"Barcelona",
    "wof:name":"Barrio Rodenas Sandra",
    "wof:placetype":"venue"
},
  "geometry": {"coordinates":[2.1509039402,41.4248466492],"type":"Point"}
}