{
  "type": "Feature",
  "properties": {
    "addr:full":"Carrer de Ausias Marc, 51 Barcelona Barcelona 08010",
    "addr:housenumber":"51",
    "addr:postcode":"08010",
    "addr:street":"Carrer De Ausias Marc",
    "iso:country":"ES",
    "sg:address":"Carrer de Ausias Marc, 51",
    "sg:city":"Barcelona",
    "sg:orig_category":"Tintes (fabricaci\u00d3n, Al Por Mayor)",
    "sg:phone":"+34 932 65 13 80",
    "sg:postcode":"08010",
    "sg:province":"Barcelona",
    "wof:name":"Blasco Sanz Leonor",
    "wof:placetype":"venue"
},
  "geometry": {"coordinates":[2.177366972,41.3928565979],"type":"Point"}
}