{
  "type": "Feature",
  "properties": {
    "iso:country":"ES",
    "sg:address":"Carrer de Copernico, 35",
    "sg:city":"S. Esteve Sesrovires",
    "sg:orig_category":"Fabricaci\u00d3n, Importaci\u00d3n De L\u00c1mparas Y Bombillas",
    "sg:phone":"+34 937 71 31 60",
    "sg:postcode":"08635",
    "sg:province":"Barcelona",
    "wof:name":"Sport-luz S.l.",
    "wof:placetype":"venue"
},
  "geometry": {"coordinates":[1.8829549551,41.4799575806],"type":"Point"}
}