{
  "type": "Feature",
  "properties": {
    "iso:country":"ES",
    "sg:address":"Rbla Badal, 153",
    "sg:city":"Barcelona",
    "sg:orig_category":"Puertas Y Portales",
    "sg:phone":"+34 934 22 18 30",
    "sg:postcode":"08028",
    "sg:province":"Barcelona",
    "wof:name":"Creixell Castellarnau Jaime",
    "wof:placetype":"venue"
},
  "geometry": {"coordinates":[2.1306419373,41.3742141724],"type":"Point"}
}