{
  "type": "Feature",
  "properties": {
    "addr:full":"Ctra Terrassa, 106 Rubi Barcelona 08191",
    "addr:housenumber":"106",
    "addr:postcode":"08191",
    "addr:street":"Ctra Terrassa",
    "iso:country":"ES",
    "sg:address":"Ctra Terrassa, 106",
    "sg:city":"Rubi",
    "sg:orig_category":"Caf\u00c9s, Bares, Cervecer\u00cdas",
    "sg:phone":"+34 936 97 91 51",
    "sg:postcode":"08191",
    "sg:province":"Barcelona",
    "wof:name":"Solugras S.l.",
    "wof:placetype":"venue"
},
  "geometry": {"coordinates":[2.0332899094,41.5023803711],"type":"Point"}
}