{
  "type": "Feature",
  "properties": {
    "addr:full":"Plaz Espa\u00d1a, 1 Boqui\u00f1eni Zaragoza 50641",
    "addr:housenumber":"1",
    "addr:postcode":"50641",
    "addr:street":"Plaz Espan\u0303A",
    "iso:country":"ES",
    "sg:address":"Plaz Espa\u00d1a, 1",
    "sg:city":"Boqui\u00f1eni",
    "sg:orig_category":"Estancos",
    "sg:phone":"+34 976 65 14 55",
    "sg:postcode":"50641",
    "sg:province":"Zaragoza",
    "wof:name":"Dominguez Martinez Ana",
    "wof:placetype":"venue"
},
  "geometry": {"coordinates":[-1.2503299713,41.8481826782],"type":"Point"}
}