{
  "type": "Feature",
  "properties": {
    "iso:country":"ES",
    "sg:address":"Calle de Carmona, 30",
    "sg:city":"Campana",
    "sg:orig_category":"Cr\u00cda De Animales",
    "sg:phone":"+34 954 19 95 57",
    "sg:postcode":"41429",
    "sg:province":"Sevilla",
    "wof:name":"Cabello Fernandez Manuel",
    "wof:placetype":"venue"
},
  "geometry": {"coordinates":[-5.4278116226,37.5693511963],"type":"Point"}
}