{
  "type": "Feature",
  "properties": {
    "iso:country":"ES",
    "sg:address":"Calle de Musico Peydro, 14",
    "sg:city":"Valencia",
    "sg:orig_category":"Lanas (al Por Mayor)",
    "sg:phone":"+34 963 51 22 35",
    "sg:postcode":"46001",
    "sg:province":"Valencia",
    "wof:name":"Perez Cebrian Ascension",
    "wof:placetype":"venue"
},
  "geometry": {"coordinates":[-0.3782489896,39.4719772339],"type":"Point"}
}