{
  "type": "Feature",
  "properties": {
    "addr:full":"Jardines, S/n Pobra Carami\u00f1al La Coru\u00f1a 15940",
    "addr:housenumber":"s / n",
    "addr:postcode":"15940",
    "addr:street":"Pobra Caramin\u0303Al La Corun\u0303A",
    "iso:country":"ES",
    "sg:address":"Jardines, S/n",
    "sg:city":"Pobra Carami\u00f1al",
    "sg:orig_category":"Librer\u00cdas",
    "sg:phone":"+34 981 83 19 52",
    "sg:postcode":"15940",
    "sg:province":"La Coru\u00f1a",
    "wof:name":"Ouvi\u00f1a Castillo Jose Manuel",
    "wof:placetype":"venue"
},
  "geometry": {"coordinates":[-8.9388437271,42.6042404175],"type":"Point"}
}