{
  "type": "Feature",
  "properties": {
    "iso:country":"ES",
    "sg:address":"Calle de Agustin Rodriguez Sahagun, 30",
    "sg:city":"Avila",
    "sg:orig_category":"Alquiler De V\u00cddeo",
    "sg:phone":"+34 920 22 35 08",
    "sg:postcode":"05003",
    "sg:province":"\u00c1vila",
    "wof:name":"Esquilas Martin Pablo",
    "wof:placetype":"venue"
},
  "geometry": {"coordinates":[-4.6807465553,40.6482086182],"type":"Point"}
}