{
  "type": "Feature",
  "properties": {
    "iso:country":"ES",
    "sg:address":"Rua Mui\u00d1o (do), 9",
    "sg:city":"Vilalba",
    "sg:orig_category":"Moda",
    "sg:phone":"+34 982 51 20 06",
    "sg:postcode":"27800",
    "sg:province":"Lugo",
    "wof:name":"Carber  Moda",
    "wof:placetype":"venue"
},
  "geometry": {"coordinates":[-7.6796050072,43.2969589233],"type":"Point"}
}