{
  "type": "Feature",
  "properties": {
    "iso:country":"ES",
    "sg:address":"Carr Major, 163",
    "sg:city":"Alcarras",
    "sg:orig_category":"Tintes (fabricaci\u00d3n, Al Por Mayor)",
    "sg:phone":"+34 973 79 50 71",
    "sg:postcode":"25180",
    "sg:province":"Lleida",
    "wof:name":"Buixadera Benseny Margarita",
    "wof:placetype":"venue"
},
  "geometry": {"coordinates":[0.5230929852,41.5624961853],"type":"Point"}
}