{
  "type": "Feature",
  "properties": {
    "addr:full":"Calle de Santiago, 55 Elizondo Navarra 31700",
    "addr:housenumber":"55",
    "addr:postcode":"31700",
    "addr:street":"Calle De Santiago;Navarra",
    "iso:country":"ES",
    "sg:address":"Calle de Santiago, 55",
    "sg:city":"Elizondo",
    "sg:orig_category":"Arquitectos",
    "sg:phone":"+34 948 58 19 72",
    "sg:postcode":"31700",
    "sg:province":"Navarra",
    "wof:name":"Cenizo Iribarren Nestor",
    "wof:placetype":"venue"
},
  "geometry": {"coordinates":[-1.5216599703,43.142124176],"type":"Point"}
}