{
  "type": "Feature",
  "properties": {
    "iso:country":"ES",
    "sg:address":"Carr Princep De Viana, 34",
    "sg:city":"Lleida",
    "sg:orig_category":"Agentes, Concesionarios Y Sucursales De Veh\u00cdculos",
    "sg:phone":"+34 973 72 76 05",
    "sg:postcode":"25004",
    "sg:province":"Lleida",
    "sg:website":"www.autodalser.com",
    "wof:name":"Auto Dalser S.l.",
    "wof:placetype":"venue"
},
  "geometry": {"coordinates":[0.6293948293,41.6219673157],"type":"Point"}
}