{
  "type": "Feature",
  "properties": {
    "addr:full":"Untzaga Plaza, 11 Eibar Guip\u00f9zcoa 20600",
    "addr:postcode":"20600",
    "addr:street":"Guipu\u0300Zcoa",
    "iso:country":"ES",
    "sg:address":"Untzaga Plaza, 11",
    "sg:city":"Eibar",
    "sg:orig_category":"Electrodom\u00c9sticos (al Por Menor)",
    "sg:phone":"+34 943 70 26 97",
    "sg:postcode":"20600",
    "sg:province":"Guip\u00f9zcoa",
    "wof:name":"Perez Des Ernesto",
    "wof:placetype":"venue"
},
  "geometry": {"coordinates":[-2.4731938839,43.1840209961],"type":"Point"}
}