{
  "type": "Feature",
  "properties": {
    "iso:country":"ES",
    "sg:address":"Rua Xeneral Franco, 15",
    "sg:city":"Bande",
    "sg:orig_category":"Supermercados Y Hipermercados",
    "sg:phone":"+34 988 44 30 47",
    "sg:postcode":"32840",
    "sg:province":"Ourense",
    "wof:name":"Vidal Alvarez Adolfo",
    "wof:placetype":"venue"
},
  "geometry": {"coordinates":[-7.9751491547,42.0315208435],"type":"Point"}
}