{
  "type": "Feature",
  "properties": {
    "iso:country":"ES",
    "sg:address":"Calle de Hornachuelos, S/n",
    "sg:city":"Fuente Palmera",
    "sg:orig_category":"Centros De Educaci\u00d3n Especial",
    "sg:phone":"+34 957 63 70 54",
    "sg:postcode":"14120",
    "sg:province":"C\u00f3rdoba",
    "wof:name":"Ayuntamiento De Fuente Palmera",
    "wof:placetype":"venue"
},
  "geometry": {"coordinates":[-5.1028094292,37.7053070068],"type":"Point"}
}