{
  "type": "Feature",
  "properties": {
    "iso:country":"ES",
    "sg:address":"Calle de Cabo De Trafalgar, 3",
    "sg:city":"Arganda",
    "sg:orig_category":"Materias Pl\u00c1sticas: Art\u00cdculos Para La Industria",
    "sg:phone":"+34 918 76 08 60",
    "sg:postcode":"28500",
    "sg:province":"Madrid",
    "wof:name":"R & D Depeltronik",
    "wof:placetype":"venue"
},
  "geometry": {"coordinates":[-3.4757738113,40.3113250732],"type":"Point"}
}