{
  "type": "Feature",
  "properties": {
    "iso:country":"ES",
    "sg:address":"Carr Major, 68",
    "sg:city":"Vallfogona Balaguer",
    "sg:orig_category":"Estancos",
    "sg:phone":"+34 973 43 20 13",
    "sg:postcode":"25680",
    "sg:province":"Lleida",
    "wof:name":"Flauria Costafreda Placido",
    "wof:placetype":"venue"
},
  "geometry": {"coordinates":[0.8158649802,41.7522468567],"type":"Point"}
}