{
  "type": "Feature",
  "properties": {
    "iso:country":"ES",
    "sg:address":"Plaz Pedro Mi\u00d1or, 39",
    "sg:city":"Oviedo",
    "sg:orig_category":"Electrodom\u00c9sticos (al Por Menor)",
    "sg:phone":"+34 985 25 39 52",
    "sg:postcode":"33013",
    "sg:province":"Asturias",
    "wof:name":"Garcia Garcia Adolfo Artemio",
    "wof:placetype":"venue"
},
  "geometry": {"coordinates":[-5.880235672,43.3592948914],"type":"Point"}
}