{
  "type": "Feature",
  "properties": {
    "addr:full":"Avda Colon, 18 Logro\u00f1o La Rioja 26003",
    "addr:housenumber":"18",
    "addr:postcode":"26003",
    "addr:street":"Avda Colon;Rioja",
    "iso:country":"ES",
    "sg:address":"Avda Colon, 18",
    "sg:city":"Logro\u00f1o",
    "sg:orig_category":"Administradores De Bienes Y Delegados De Comunidades De Propietarios",
    "sg:phone":"+34 941 24 62 46",
    "sg:postcode":"26003",
    "sg:province":"La Rioja",
    "wof:name":"Fincas Corral S.l.",
    "wof:placetype":"venue"
},
  "geometry": {"coordinates":[-2.4401938915,42.4623756409],"type":"Point"}
}