{
  "type": "Feature",
  "properties": {
    "addr:full":"Calle de Laguna, 44 Sada A Coru\u00f1a 15160",
    "addr:housenumber":"44",
    "addr:postcode":"15160",
    "addr:street":"Calle De Laguna",
    "iso:country":"ES",
    "sg:address":"Calle de Laguna, 44",
    "sg:city":"Sada",
    "sg:orig_category":"Arquitectos",
    "sg:phone":"+34 981 62 20 53",
    "sg:postcode":"15160",
    "sg:province":"A Coru\u00f1a",
    "wof:name":"Vazquez Freire Enrique",
    "wof:placetype":"venue"
},
  "geometry": {"coordinates":[-8.2548141479,43.3510665894],"type":"Point"}
}