{
  "type": "Feature",
  "properties": {
    "iso:country":"ES",
    "sg:address":"Calle de Miguel Hernandez, 11",
    "sg:city":"Caudete",
    "sg:orig_category":"Asesor\u00cda Fiscal Y Jur\u00cddica",
    "sg:phone":"+34 965 82 75 04",
    "sg:postcode":"02660",
    "sg:province":"Albacete",
    "wof:name":"Jm Y Ft S.l.",
    "wof:placetype":"venue"
},
  "geometry": {"coordinates":[-0.9845039845,38.7036476135],"type":"Point"}
}