{
  "type": "Feature",
  "properties": {
    "addr:full":"Calle de Princesa Guayarmina, 61 Palmas De Gran Canaria Las Palmas 35009",
    "addr:housenumber":"61",
    "addr:postcode":"35009",
    "addr:street":"Calle De Princesa Guayarmina",
    "iso:country":"ES",
    "sg:address":"Calle de Princesa Guayarmina, 61",
    "sg:city":"Palmas De Gran Canaria",
    "sg:orig_category":"Electricidad: Instaladores",
    "sg:phone":"+34 928 46 28 19",
    "sg:postcode":"35009",
    "sg:province":"Las Palmas",
    "wof:name":"Mendez Gonzalez Aurelio Eladio",
    "wof:placetype":"venue"
},
  "geometry": {"coordinates":[-15.4291391373,28.1519069672],"type":"Point"}
}