{
  "type": "Feature",
  "properties": {
    "iso:country":"ES",
    "sg:address":"Calle de Carlos V, 34",
    "sg:city":"Melilla",
    "sg:orig_category":"Comercio De Piezas De Recambio Y De Accesorios De Veh\u00cdculos, Veh\u00cdculos Industriales",
    "sg:phone":"+34 952 67 30 48",
    "sg:postcode":"52006",
    "sg:province":"Melilla",
    "wof:name":"Kachoua-mohamed Omar Ahmed",
    "wof:placetype":"venue"
},
  "geometry": {"coordinates":[-2.9391789436,35.2811775208],"type":"Point"}
}