{
  "type": "Feature",
  "properties": {
    "iso:country":"ES",
    "sg:address":"Calle de Real, 13",
    "sg:city":"Piedrabuena",
    "sg:orig_category":"Equitaci\u00d3n: Guarnicioner\u00cda, Equipo (al Por Menor)",
    "sg:phone":"+34 926 76 02 77",
    "sg:postcode":"13100",
    "sg:province":"Ciudad Real",
    "wof:name":"Rodriguez Garcia-sacedon Vicente",
    "wof:placetype":"venue"
},
  "geometry": {"coordinates":[-4.1718878746,39.0343399048],"type":"Point"}
}