{
  "type": "Feature",
  "properties": {
    "addr:full":"Calle de Julio Burell, 16 Iznajar C\u00f3rdoba 14970",
    "addr:housenumber":"16",
    "addr:postcode":"14970",
    "addr:street":"Calle De Julio Burell;Co\u0301Rdoba",
    "iso:country":"ES",
    "sg:address":"Calle de Julio Burell, 16",
    "sg:city":"Iznajar",
    "sg:orig_category":"Iglesia Cat\u00d3lica",
    "sg:phone":"+34 957 53 40 65",
    "sg:postcode":"14970",
    "sg:province":"C\u00f3rdoba",
    "wof:name":"Parroquia De Santiago Apostol",
    "wof:placetype":"venue"
},
  "geometry": {"coordinates":[-4.3083348274,37.2573356628],"type":"Point"}
}