{
  "type": "Feature",
  "properties": {
    "iso:country":"ES",
    "sg:address":"Carrer de Llull, 98",
    "sg:city":"Barcelona",
    "sg:orig_category":"Inmobiliaria (agencias)",
    "sg:phone":"+34 933 00 22 11",
    "sg:postcode":"08005",
    "sg:province":"Barcelona",
    "wof:name":"Inmobiliaria Camfor S.a.",
    "wof:placetype":"venue"
},
  "geometry": {"coordinates":[2.1957359314,41.3960800171],"type":"Point"}
}