{
  "type": "Feature",
  "properties": {
    "addr:full":"Av Catalunya (de), 51 Tortosa Tarragona 43500",
    "addr:housenumber":"51",
    "addr:postcode":"43500",
    "addr:street":"Av Catalunya De",
    "iso:country":"ES",
    "sg:address":"Av Catalunya (de), 51",
    "sg:city":"Tortosa",
    "sg:orig_category":"Frutas, Legumbres Frescas Y Tempranas (al Por Menor)",
    "sg:phone":"+34 977 50 29 14",
    "sg:postcode":"43500",
    "sg:province":"Tarragona",
    "wof:name":"Benaiges Bru Angel",
    "wof:placetype":"venue"
},
  "geometry": {"coordinates":[0.5150799751,40.8156394958],"type":"Point"}
}