{
  "type": "Feature",
  "properties": {
    "addr:full":"Carrer de Mestre Jose Esteve Solbes, 4 Muro Alcoy Alicante 03830",
    "addr:housenumber":"4",
    "addr:postcode":"03830",
    "addr:street":"Carrer De Mestre Jose Esteve Solbes",
    "iso:country":"ES",
    "sg:address":"Carrer de Mestre Jose Esteve Solbes, 4",
    "sg:city":"Muro Alcoy",
    "sg:orig_category":"Electricidad: Instaladores",
    "sg:phone":"+34 965 53 01 63",
    "sg:postcode":"03830",
    "sg:province":"Alicante",
    "wof:name":"Electricidad F.m.tormo S.c.",
    "wof:placetype":"venue"
},
  "geometry": {"coordinates":[-0.438161999,38.7787513733],"type":"Point"}
}