{
  "type": "Feature",
  "properties": {
    "addr:full":"Calle de Huerta, 18 Camino De Yuncos Toledo 45220",
    "addr:housenumber":"18",
    "addr:postcode":"45220",
    "addr:street":"Calle De Huerta;Camino De Yuncos",
    "iso:country":"ES",
    "sg:address":"Calle de Huerta, 18",
    "sg:city":"Camino De Yuncos",
    "sg:orig_category":"Lanas (al Por Mayor)",
    "sg:phone":"+34 925 59 24 25",
    "sg:postcode":"45220",
    "sg:province":"Toledo",
    "wof:name":"Serrano Garcia Javier",
    "wof:placetype":"venue"
},
  "geometry": {"coordinates":[-3.8059339523,40.1223945618],"type":"Point"}
}