{
  "type": "Feature",
  "properties": {
    "addr:full":"Calle de Preciados, 52 Madrid Madrid 28013",
    "addr:housenumber":"52",
    "addr:postcode":"madrid;28013",
    "addr:street":"Calle De Preciados",
    "iso:country":"ES",
    "sg:address":"Calle de Preciados, 52",
    "sg:city":"Madrid",
    "sg:orig_category":"Peleter\u00cdas",
    "sg:phone":"+34 915 47 50 48",
    "sg:postcode":"28013",
    "sg:province":"Madrid",
    "wof:name":"Peleteria Siber S.l.",
    "wof:placetype":"venue"
},
  "geometry": {"coordinates":[-3.7077889442,40.4198188782],"type":"Point"}
}