{
  "type": "Feature",
  "properties": {
    "iso:country":"ES",
    "sg:address":"Calle de Alta, 41",
    "sg:city":"Castro Rio",
    "sg:orig_category":"M\u00c9dicos: Estomatolog\u00cda",
    "sg:phone":"+34 957 37 22 53",
    "sg:postcode":"14840",
    "sg:province":"C\u00f3rdoba",
    "wof:name":"Zurita Lopez Fernando Luis",
    "wof:placetype":"venue"
},
  "geometry": {"coordinates":[-4.4824523926,37.6918334961],"type":"Point"}
}