{
  "type": "Feature",
  "properties": {
    "iso:country":"ES",
    "sg:address":"Carr Victor Daras (de), S/n",
    "sg:city":"Oasi De Sant Vicent",
    "sg:orig_category":"Asociaciones Y Clubs Deportivos",
    "sg:phone":"+34 962 78 14 10",
    "sg:postcode":"46160",
    "sg:province":"Valencia",
    "wof:name":"Club De Tenis La Senyera",
    "wof:placetype":"venue"
},
  "geometry": {"coordinates":[-0.5952839851,39.6247406006],"type":"Point"}
}