{
  "type": "Feature",
  "properties": {
    "addr:full":"Mar Mediterrania(p I Torre Rector), 5 Sta. Perpetua Mogoda Barcelona 08130",
    "addr:housenumber":"5",
    "addr:postcode":"08130",
    "addr:street":"Rector",
    "iso:country":"ES",
    "sg:address":"Mar Mediterrania(p I Torre Rector), 5",
    "sg:city":"Sta. Perpetua Mogoda",
    "sg:orig_category":"Electricidad: Instaladores",
    "sg:phone":"+34 935 74 34 27",
    "sg:postcode":"08130",
    "sg:province":"Barcelona",
    "wof:name":"Electro Sistemas Bach S.a.",
    "wof:placetype":"venue"
},
  "geometry": {"coordinates":[2.1867010593,41.5471725464],"type":"Point"}
}