{
  "type": "Feature",
  "properties": {
    "iso:country":"ES",
    "sg:address":"Urb. St. Feliu, S/n",
    "sg:city":"Celra",
    "sg:orig_category":"Pescader\u00cdas (al Por Menor)",
    "sg:phone":"+34 972 49 41 47",
    "sg:postcode":"17460",
    "sg:province":"Girona",
    "wof:name":"Conteh  Banbeh",
    "wof:placetype":"venue"
},
  "geometry": {"coordinates":[2.8776299953,42.0278434753],"type":"Point"}
}