{
  "type": "Feature",
  "properties": {
    "iso:country":"ES",
    "sg:address":"Calle de Capitan Blanco Argibay, 174",
    "sg:city":"Madrid",
    "sg:orig_category":"Molduras, Junquillos, Listones Y Molduras Perforadas",
    "sg:phone":"+34 913 23 50 44",
    "sg:postcode":"28029",
    "sg:province":"Madrid",
    "wof:name":"Higes Diaz Ildefonso Pedro",
    "wof:placetype":"venue"
},
  "geometry": {"coordinates":[-3.7061498165,40.467716217],"type":"Point"}
}