{
  "type": "Feature",
  "properties": {
    "iso:country":"ES",
    "sg:address":"Calle de Bebricio, 9",
    "sg:city":"Calahorra",
    "sg:orig_category":"Supermercados Y Hipermercados",
    "sg:phone":"+34 941 13 55 33",
    "sg:postcode":"26500",
    "sg:province":"La Rioja",
    "wof:name":"Eroski Sociedad Cooperativa",
    "wof:placetype":"venue"
},
  "geometry": {"coordinates":[-1.96884799,42.3056144714],"type":"Point"}
}