{
  "type": "Feature",
  "properties": {
    "iso:country":"ES",
    "sg:address":"Pase Extremadura, 48",
    "sg:city":"Madrid",
    "sg:orig_category":"Ropa Para Se\u00d1oras (al Por Menor)",
    "sg:phone":"+34 914 64 55 19",
    "sg:postcode":"28011",
    "sg:province":"Madrid",
    "wof:name":"La Kokett S.l.",
    "wof:placetype":"venue"
},
  "geometry": {"coordinates":[-3.7297260761,40.4133415222],"type":"Point"}
}