{
  "type": "Feature",
  "properties": {
    "iso:country":"ES",
    "sg:address":"Calle de Cinca, 1",
    "sg:city":"Bosque",
    "sg:orig_category":"Inversiones",
    "sg:phone":"+34 916 16 89 60",
    "sg:postcode":"28670",
    "sg:province":"Madrid",
    "wof:name":"Proiluan S.a.",
    "wof:placetype":"venue"
},
  "geometry": {"coordinates":[-3.9272828102,40.3735618591],"type":"Point"}
}