{
  "type": "Feature",
  "properties": {
    "iso:country":"ES",
    "sg:address":"Calle de San Agustin, 16",
    "sg:city":"Requena",
    "sg:orig_category":"Asociaciones Y Clubs Deportivos",
    "sg:phone":"+34 962 30 11 92",
    "sg:postcode":"46340",
    "sg:province":"Valencia",
    "wof:name":"Martinez Benito Francisco",
    "wof:placetype":"venue"
},
  "geometry": {"coordinates":[-1.1011430025,39.4887008667],"type":"Point"}
}