{
  "type": "Feature",
  "properties": {
    "addr:full":"Avda Amalio Gimeno, 12 Castellon Castell\u00f3n 12005",
    "addr:housenumber":"12",
    "addr:postcode":"12005",
    "addr:street":"Avda Amalio Gimeno",
    "iso:country":"ES",
    "sg:address":"Avda Amalio Gimeno, 12",
    "sg:city":"Castellon",
    "sg:orig_category":"Muebles, Minoristas",
    "sg:phone":"+34 964 21 09 82",
    "sg:postcode":"12005",
    "sg:province":"Castell\u00f3n",
    "wof:name":"Almacenes Marti Cdad",
    "wof:placetype":"venue"
},
  "geometry": {"coordinates":[-0.0434666015,39.9780464172],"type":"Point"}
}