{
  "type": "Feature",
  "properties": {
    "addr:full":"Calle de Serrablo (de), 75 Sabi\u00f1anigo Huesca 22600",
    "addr:housenumber":"75",
    "addr:postcode":"22600",
    "addr:street":"Calle De Serrablo De",
    "iso:country":"ES",
    "sg:address":"Calle de Serrablo (de), 75",
    "sg:city":"Sabi\u00f1anigo",
    "sg:orig_category":"Agencias De Viajes",
    "sg:phone":"+34 974 48 11 89",
    "sg:postcode":"22600",
    "sg:province":"Huesca",
    "wof:name":"Martin Mendez Ramon Jose",
    "wof:placetype":"venue"
},
  "geometry": {"coordinates":[-0.3663820028,42.5180969238],"type":"Point"}
}