{
  "type": "Feature",
  "properties": {
    "iso:country":"ES",
    "sg:address":"Avda Diputacion (de La), S/n",
    "sg:city":"Chiclana De La Frontera",
    "sg:orig_category":"Farmacias",
    "sg:phone":"+34 956 40 01 06",
    "sg:postcode":"11130",
    "sg:province":"C\u00e1diz",
    "wof:name":"Jimenez Dominguez C.b.",
    "wof:placetype":"venue"
},
  "geometry": {"coordinates":[-6.1596856117,36.4157333374],"type":"Point"}
}