{
  "type": "Feature",
  "properties": {
    "addr:full":"Avda Estacion, 15 Ayerbe Huesca 22800",
    "addr:housenumber":"15",
    "addr:postcode":"22800",
    "addr:street":"Avda Estacion",
    "iso:country":"ES",
    "sg:address":"Avda Estacion, 15",
    "sg:city":"Ayerbe",
    "sg:orig_category":"Empresas De Carpinter\u00cda Met\u00c1lica",
    "sg:phone":"+34 974 38 00 71",
    "sg:postcode":"22800",
    "sg:province":"Huesca",
    "wof:name":"Orleans Carcavilla Eduardo",
    "wof:placetype":"venue"
},
  "geometry": {"coordinates":[-0.6871190071,42.2733039856],"type":"Point"}
}