{
  "type": "Feature",
  "properties": {
    "addr:full":"Calle de Zamora, 77 Salamanca Salamanca 37002",
    "addr:housenumber":"77",
    "addr:postcode":"37002",
    "addr:street":"Calle De Zamora",
    "iso:country":"ES",
    "sg:address":"Calle de Zamora, 77",
    "sg:city":"Salamanca",
    "sg:orig_category":"Art\u00cdculos De Decoraci\u00d3n (fabricaci\u00d3n Y Al Por Mayor)",
    "sg:phone":"+34 923 26 89 21",
    "sg:postcode":"37002",
    "sg:province":"Salamanca",
    "wof:name":"Victoria Fortes S.l.",
    "wof:placetype":"venue"
},
  "geometry": {"coordinates":[-5.6637988091,40.9693870544],"type":"Point"}
}