{
  "type": "Feature",
  "properties": {
    "addr:full":"Avda Ferrol (del), 1 Viveiro Lugo 27850",
    "addr:housenumber":"1",
    "addr:postcode":"27850",
    "addr:street":"Avda Ferrol Del",
    "iso:country":"ES",
    "sg:address":"Avda Ferrol (del), 1",
    "sg:city":"Viveiro",
    "sg:orig_category":"Electrodom\u00c9sticos (al Por Menor)",
    "sg:phone":"+34 982 56 03 75",
    "sg:postcode":"27850",
    "sg:province":"Lugo",
    "wof:name":"Martinez Millor Carlos",
    "wof:placetype":"venue"
},
  "geometry": {"coordinates":[-7.5992488861,43.6569519043],"type":"Point"}
}