{
  "type": "Feature",
  "properties": {
    "iso:country":"ES",
    "sg:address":"San Franzisko Kalea, 3",
    "sg:city":"Elgoibar",
    "sg:orig_category":"Carnicer\u00cdas, Carnicer\u00cdas",
    "sg:phone":"+34 943 74 38 27",
    "sg:postcode":"20870",
    "sg:province":"Guip\u00f9zcoa",
    "wof:name":"Barrutia Larra\u00f1aga Jesus (barrutia Harategia)",
    "wof:placetype":"venue"
},
  "geometry": {"coordinates":[-2.4151909351,43.2155075073],"type":"Point"}
}