{
  "type": "Feature",
  "properties": {
    "addr:full":"Calle de Pio Bermejillo, 15 Balmaseda Vizcaya 48800",
    "addr:housenumber":"15",
    "addr:postcode":"48800",
    "addr:street":"Calle De Pio Bermejillo",
    "iso:country":"ES",
    "sg:address":"Calle de Pio Bermejillo, 15",
    "sg:city":"Balmaseda",
    "sg:orig_category":"Molduras, Junquillos, Listones Y Molduras Perforadas",
    "sg:phone":"+34 946 80 10 71",
    "sg:postcode":"48800",
    "sg:province":"Vizcaya",
    "wof:name":"Phone Euskadi S. L.",
    "wof:placetype":"venue"
},
  "geometry": {"coordinates":[-3.1936271191,43.1948509216],"type":"Point"}
}