{
  "type": "Feature",
  "properties": {
    "iso:country":"ES",
    "sg:address":"Pg Can Feu, 36",
    "sg:city":"Sabadell",
    "sg:orig_category":"Ebanister\u00cda",
    "sg:phone":"+34 937 25 43 42",
    "sg:postcode":"08205",
    "sg:province":"Barcelona",
    "wof:name":"Coll Cardona Xavier",
    "wof:placetype":"venue"
},
  "geometry": {"coordinates":[2.0939519405,41.5439949036],"type":"Point"}
}