{
  "type": "Feature",
  "properties": {
    "addr:full":"Calle de Oca\u00d1a, 61 Madrid Madrid 28047",
    "addr:housenumber":"61",
    "addr:postcode":"madrid;28047",
    "addr:street":"Calle De Ocan\u0303A",
    "iso:country":"ES",
    "sg:address":"Calle de Oca\u00d1a, 61",
    "sg:city":"Madrid",
    "sg:orig_category":"Molduras, Junquillos, Listones Y Molduras Perforadas",
    "sg:phone":"+34 914 65 15 85",
    "sg:postcode":"28047",
    "sg:province":"Madrid",
    "wof:name":"Fernandez Santos Mercedes",
    "wof:placetype":"venue"
},
  "geometry": {"coordinates":[-3.7539479733,40.3852615356],"type":"Point"}
}