{
  "type": "Feature",
  "properties": {
    "iso:country":"ES",
    "sg:address":"Rio Eo(pol Ind), S/n",
    "sg:city":"Lorqui",
    "sg:orig_category":"Fabricaci\u00d3n, Instalaci\u00d3n Y Reparaci\u00d3n De Bombas",
    "sg:phone":"+34 968 67 62 81",
    "sg:postcode":"30564",
    "sg:province":"Murcia",
    "wof:name":"Solana Rojo Manuel",
    "wof:placetype":"venue"
},
  "geometry": {"coordinates":[-1.2377489805,38.1005744934],"type":"Point"}
}