{
  "type": "Feature",
  "properties": {
    "addr:full":"Avda Juan Carlos I, 12 Aguilas Murcia 30880",
    "addr:housenumber":"12",
    "addr:postcode":"30880",
    "addr:street":"Avda Juan Carlos I",
    "iso:country":"ES",
    "sg:address":"Avda Juan Carlos I, 12",
    "sg:city":"Aguilas",
    "sg:orig_category":"Ropa Para Se\u00d1oras Y Caballeros (al Por Menor)",
    "sg:phone":"+34 968 44 71 69",
    "sg:postcode":"30880",
    "sg:province":"Murcia",
    "wof:name":"Sharp Martinez Jacoba Isabel",
    "wof:placetype":"venue"
},
  "geometry": {"coordinates":[-1.5842030048,37.4050521851],"type":"Point"}
}