{
  "type": "Feature",
  "properties": {
    "addr:full":"Calle de Zurita, 20 Madrid Madrid 28012",
    "addr:housenumber":"20",
    "addr:postcode":"madrid;28012",
    "addr:street":"Calle De Zurita",
    "iso:country":"ES",
    "sg:address":"Calle de Zurita, 20",
    "sg:city":"Madrid",
    "sg:orig_category":"Servicios Diversos",
    "sg:phone":"+34 915 39 25 18",
    "sg:postcode":"28012",
    "sg:province":"Madrid",
    "wof:name":"Fundacion Festivales Alternativos",
    "wof:placetype":"venue"
},
  "geometry": {"coordinates":[-3.6993980408,40.4095726013],"type":"Point"}
}