{
  "type": "Feature",
  "properties": {
    "addr:full":"Calle de Canovas Del Castillo, 9 Santa Eulalia Murcia 30003",
    "addr:housenumber":"9",
    "addr:postcode":"30003",
    "addr:street":"Calle De Canovas Del Castillo",
    "iso:country":"ES",
    "sg:address":"Calle de Canovas Del Castillo, 9",
    "sg:city":"Santa Eulalia",
    "sg:orig_category":"Supermercados Y Hipermercados",
    "sg:phone":"+34 968 21 07 73",
    "sg:postcode":"30003",
    "sg:province":"Murcia",
    "wof:name":"Pujante Herrera Carmen",
    "wof:placetype":"venue"
},
  "geometry": {"coordinates":[-1.1258610487,37.9841918945],"type":"Point"}
}