{
  "type": "Feature",
  "properties": {
    "iso:country":"ES",
    "sg:address":"Av Doctor Pujol, 2",
    "sg:city":"Creixell",
    "sg:orig_category":"Laboratorios Y Trabajos De Fotograf\u00cda, V\u00cddeo Y Cine",
    "sg:phone":"+34 977 80 14 66",
    "sg:postcode":"43839",
    "sg:province":"Tarragona",
    "wof:name":"Cano Diaz Antonio",
    "wof:placetype":"venue"
},
  "geometry": {"coordinates":[1.4385019541,41.1682662964],"type":"Point"}
}