{
  "type": "Feature",
  "properties": {
    "addr:full":"Foru Ibilbidea, 4 Azpeitia Guip\u00f9zcoa 20730",
    "addr:housenumber":"4",
    "addr:postcode":"20730",
    "addr:street":"Foru Ibilbidea;Guipu\u0300Zcoa",
    "iso:country":"ES",
    "sg:address":"Foru Ibilbidea, 4",
    "sg:city":"Azpeitia",
    "sg:orig_category":"Pescader\u00cdas (al Por Menor)",
    "sg:phone":"+34 943 81 19 46",
    "sg:postcode":"20730",
    "sg:province":"Guip\u00f9zcoa",
    "wof:name":"Jon Iparraguirre Larra\u00f1aga",
    "wof:placetype":"venue"
},
  "geometry": {"coordinates":[-2.2657878399,43.1828613281],"type":"Point"}
}