{
  "type": "Feature",
  "properties": {
    "addr:full":"Cmno Torrejon (de), 268 Marchena Murcia 30815",
    "addr:housenumber":"268",
    "addr:postcode":"30815",
    "addr:street":"Cmno Torrejon De",
    "iso:country":"ES",
    "sg:address":"Cmno Torrejon (de), 268",
    "sg:city":"Marchena",
    "sg:orig_category":"Agricultores, Agricultores",
    "sg:phone":"+34 968 47 38 58",
    "sg:postcode":"30815",
    "sg:province":"Murcia",
    "wof:name":"Frangarsan S.l.",
    "wof:placetype":"venue"
},
  "geometry": {"coordinates":[-1.5774840117,37.5886192322],"type":"Point"}
}