{
  "type": "Feature",
  "properties": {
    "addr:full":"Carr Bonaire, 2 Mao Islas Baleares 07703",
    "addr:housenumber":"2",
    "addr:postcode":"07703",
    "addr:street":"Carr Bonaire",
    "iso:country":"ES",
    "sg:address":"Carr Bonaire, 2",
    "sg:city":"Mao",
    "sg:orig_category":"Perfumer\u00cda, Art\u00cdculos De Ba\u00d1o (fabricaci\u00d3n, Al Por Mayor)",
    "sg:phone":"+34 971 35 36 36",
    "sg:postcode":"07703",
    "sg:province":"Islas Baleares",
    "wof:name":"Fontana  Mariano",
    "wof:placetype":"venue"
},
  "geometry": {"coordinates":[4.265625,39.8903694153],"type":"Point"}
}