{
  "type": "Feature",
  "properties": {
    "addr:full":"Calle de Polvoranca, 20 Getafe Madrid 28901",
    "addr:housenumber":"20",
    "addr:postcode":"28901",
    "addr:street":"Calle De Polvoranca",
    "iso:country":"ES",
    "sg:address":"Calle de Polvoranca, 20",
    "sg:city":"Getafe",
    "sg:orig_category":"Alimentaci\u00d3n General (al Por Menor)",
    "sg:phone":"+34 916 95 85 18",
    "sg:postcode":"28901",
    "sg:province":"Madrid",
    "wof:name":"Ye  Xiangjun",
    "wof:placetype":"venue"
},
  "geometry": {"coordinates":[-3.7349469662,40.3046073914],"type":"Point"}
}