{
  "type": "Feature",
  "properties": {
    "addr:full":"Carrer de Calderon De La Barca, 25 Barcelona Barcelona 08032",
    "addr:housenumber":"25",
    "addr:postcode":"08032",
    "addr:street":"Carrer De Calderon De La Barca",
    "iso:country":"ES",
    "sg:address":"Carrer de Calderon De La Barca, 25",
    "sg:city":"Barcelona",
    "sg:orig_category":"Confecci\u00d3n (fabricaci\u00d3n, Al Por Mayor)",
    "sg:phone":"+34 934 20 68 26",
    "sg:postcode":"08032",
    "sg:province":"Barcelona",
    "wof:name":"Fernandez Ortiz Antonio",
    "wof:placetype":"venue"
},
  "geometry": {"coordinates":[2.1554009914,41.4225463867],"type":"Point"}
}