{
  "type": "Feature",
  "properties": {
    "iso:country":"ES",
    "sg:address":"Calle de Rosario, 1",
    "sg:city":"Mazuecos",
    "sg:orig_category":"Farmacias",
    "sg:phone":"+34 949 38 90 82",
    "sg:postcode":"19114",
    "sg:province":"Guadalajara",
    "wof:name":"Garcia Garcia Maria Paz",
    "wof:placetype":"venue"
},
  "geometry": {"coordinates":[-3.0105791092,40.2628211975],"type":"Point"}
}