{
  "type": "Feature",
  "properties": {
    "iso:country":"ES",
    "sg:address":"Rua Ramon Gonzalez, 53",
    "sg:city":"Porri\u00f1o",
    "sg:orig_category":"Panader\u00cdas, Panader\u00cdas",
    "sg:phone":"+34 986 33 21 57",
    "sg:postcode":"36400",
    "sg:province":"Pontevedra",
    "wof:name":"Confiteria Porri\u00f1o S.l.",
    "wof:placetype":"venue"
},
  "geometry": {"coordinates":[-8.6213293076,42.1625709534],"type":"Point"}
}