{
  "type": "Feature",
  "properties": {
    "iso:country":"ES",
    "sg:address":"Calle de Rabadanes, 109",
    "sg:city":"Cabezas S. Juan",
    "sg:orig_category":"Producci\u00d3n, Venta De Productos De Agricultura Biol\u00d3gica",
    "sg:phone":"+34 955 87 13 74",
    "sg:postcode":"41730",
    "sg:province":"Sevilla",
    "wof:name":"Jarana Vidal Benito",
    "wof:placetype":"venue"
},
  "geometry": {"coordinates":[-5.9385008812,36.9853210449],"type":"Point"}
}