{
  "type": "Feature",
  "properties": {
    "addr:full":"Calle de Reina, 1 Granada Granada 18015",
    "addr:housenumber":"1",
    "addr:postcode":"18015",
    "addr:street":"Calle De Reina",
    "iso:country":"ES",
    "sg:address":"Calle de Reina, 1",
    "sg:city":"Granada",
    "sg:orig_category":"Carnicer\u00cdas, Carnicer\u00cdas",
    "sg:phone":"+34 958 20 24 17",
    "sg:postcode":"18015",
    "sg:province":"Granada",
    "wof:name":"Gonzalez Fernandez Francisco",
    "wof:placetype":"venue"
},
  "geometry": {"coordinates":[-3.6233539581,37.1895446777],"type":"Point"}
}