{
  "type": "Feature",
  "properties": {
    "iso:country":"ES",
    "sg:address":"Ctra Carretera Nacional V, S/n",
    "sg:city":"Trujillo",
    "sg:orig_category":"Autob\u00das (explotaci\u00d3n Y Servicios De)",
    "sg:phone":"+34 927 32 12 02",
    "sg:postcode":"10200",
    "sg:province":"C\u00e1ceres",
    "wof:name":"Auto Res S.l.",
    "wof:placetype":"venue"
},
  "geometry": {"coordinates":[-5.9621105194,39.561050415],"type":"Point"}
}