{
  "type": "Feature",
  "properties": {
    "addr:full":"Carr Barcelona, 15 Girona Girona 17002",
    "addr:housenumber":"15",
    "addr:postcode":"17002",
    "addr:street":"Carr Barcelona",
    "iso:country":"ES",
    "sg:address":"Carr Barcelona, 15",
    "sg:city":"Girona",
    "sg:orig_category":"Librer\u00cdas",
    "sg:phone":"+34 972 22 75 44",
    "sg:postcode":"17002",
    "sg:province":"Girona",
    "wof:name":"Vares Comalada Maria Roser",
    "wof:placetype":"venue"
},
  "geometry": {"coordinates":[2.8188068867,41.9807891846],"type":"Point"}
}