{
  "type": "Feature",
  "properties": {
    "iso:country":"ES",
    "sg:address":"Carr Pintor Sorolla, 49",
    "sg:city":"Alcudia",
    "sg:orig_category":"Aguas (distribuci\u00d3n, Servicios)",
    "sg:phone":"+34 962 54 15 50",
    "sg:postcode":"46250",
    "sg:province":"Valencia",
    "wof:name":"Implantaciones De Sistemas De Gestion S.",
    "wof:placetype":"venue"
},
  "geometry": {"coordinates":[-0.5070289969,39.1940689087],"type":"Point"}
}