{
  "type": "Feature",
  "properties": {
    "addr:full":"Rua Curros Enriquez, 25 Ourense Ourense 32003",
    "addr:postcode":"32003",
    "addr:street":"Rua Curros Enriquez",
    "iso:country":"ES",
    "sg:address":"Rua Curros Enriquez, 25",
    "sg:city":"Ourense",
    "sg:orig_category":"Sociedades, Compa\u00d1\u00cdas Aseguradoras",
    "sg:phone":"+34 988 37 19 50",
    "sg:postcode":"32003",
    "sg:province":"Ourense",
    "wof:name":"Mutua Universal Mugenat Matepss N 10",
    "wof:placetype":"venue"
},
  "geometry": {"coordinates":[-7.8628878593,42.34349823],"type":"Point"}
}