{
  "type": "Feature",
  "properties": {
    "addr:full":"Calle de Victor Hugo, 17 Palmas De Gran Canaria Las Palmas 35006",
    "addr:postcode":"35006",
    "addr:street":"Calle De Victor",
    "iso:country":"ES",
    "sg:address":"Calle de Victor Hugo, 17",
    "sg:city":"Palmas De Gran Canaria",
    "sg:orig_category":"Metalurgia",
    "sg:phone":"+34 928 24 51 89",
    "sg:postcode":"35006",
    "sg:province":"Las Palmas",
    "wof:name":"Acosta Herrera Fernando",
    "wof:placetype":"venue"
},
  "geometry": {"coordinates":[-15.4309654236,28.1319770813],"type":"Point"}
}