{
  "type": "Feature",
  "properties": {
    "addr:full":"Empalme, S/n Empalme La Coru\u00f1a 15111",
    "addr:housenumber":"s / n",
    "addr:postcode":"15111",
    "addr:street":"Corun\u0303A",
    "iso:country":"ES",
    "sg:address":"Empalme, S/n",
    "sg:city":"Empalme",
    "sg:orig_category":"Alfarer\u00cda",
    "sg:phone":"+34 981 71 15 31",
    "sg:postcode":"15111",
    "sg:province":"La Coru\u00f1a",
    "wof:name":"Mindiringuin S.l.",
    "wof:placetype":"venue"
},
  "geometry": {"coordinates":[-8.7833986282,43.2669487],"type":"Point"}
}