{
  "type": "Feature",
  "properties": {
    "iso:country":"ES",
    "sg:address":"Plaz Durangoko Plateruen Plaza, 1",
    "sg:city":"Durango",
    "sg:orig_category":"Asesor\u00cda Fiscal Y Jur\u00cddica",
    "sg:phone":"+34 944 66 81 18",
    "sg:postcode":"48200",
    "sg:province":"Vizcaya",
    "wof:name":"Asesoria Hernanz, S.l.",
    "wof:placetype":"venue"
},
  "geometry": {"coordinates":[-2.6322972775,43.1705284119],"type":"Point"}
}