{
  "type": "Feature",
  "properties": {
    "addr:full":"Calle de General Yague, 1 Llanos De Aridane Santa Cruz De Tenerife 38760",
    "addr:housenumber":"1",
    "addr:postcode":"38760",
    "addr:street":"Calle De General Yague",
    "iso:country":"ES",
    "sg:address":"Calle de General Yague, 1",
    "sg:city":"Llanos De Aridane",
    "sg:orig_category":"Ropa De Hogar (al Por Menor)",
    "sg:phone":"+34 922 40 26 17",
    "sg:postcode":"38760",
    "sg:province":"Santa Cruz De Tenerife",
    "wof:name":"Gran Bazar Textil S.l.",
    "wof:placetype":"venue"
},
  "geometry": {"coordinates":[-17.9129676819,28.6568698883],"type":"Point"}
}