{
  "type": "Feature",
  "properties": {
    "addr:full":"Calle de Matematico Pedrayes, 1 Oviedo Asturias 33005",
    "addr:housenumber":"1",
    "addr:postcode":"33005",
    "addr:street":"Calle De Matematico Pedrayes",
    "iso:country":"ES",
    "sg:address":"Calle de Matematico Pedrayes, 1",
    "sg:city":"Oviedo",
    "sg:orig_category":"Herboristas (al Por Menor)",
    "sg:phone":"+34 985 27 39 71",
    "sg:postcode":"33005",
    "sg:province":"Asturias",
    "wof:name":"Housediet S.l Sociedad Unipersonal",
    "wof:placetype":"venue"
},
  "geometry": {"coordinates":[-5.85587883,43.3628997803],"type":"Point"}
}