{
  "type": "Feature",
  "properties": {
    "addr:full":"Carrer de Major, 62 Salou Tarragona 43840",
    "addr:housenumber":"62",
    "addr:postcode":"43840",
    "addr:street":"Carrer De Major",
    "iso:country":"ES",
    "sg:address":"Carrer de Major, 62",
    "sg:city":"Salou",
    "sg:orig_category":"Empresas De Carpinter\u00cda De Madera",
    "sg:phone":"+34 977 38 03 26",
    "sg:postcode":"43840",
    "sg:province":"Tarragona",
    "wof:name":"Perez Farre Ramon",
    "wof:placetype":"venue"
},
  "geometry": {"coordinates":[1.143682003,41.0752944946],"type":"Point"}
}