{
  "type": "Feature",
  "properties": {
    "iso:country":"ES",
    "sg:address":"Carrer de Casp, 156",
    "sg:city":"Barcelona",
    "sg:orig_category":"Ropa Para Se\u00d1oras (al Por Menor)",
    "sg:phone":"+34 932 45 69 48",
    "sg:postcode":"08013",
    "sg:province":"Barcelona",
    "wof:name":"Privet Plushy Drive S.l.",
    "wof:placetype":"venue"
},
  "geometry": {"coordinates":[2.1805849075,41.3965911865],"type":"Point"}
}