{
  "type": "Feature",
  "properties": {
    "addr:full":"Iglesia, S/n Mestanza Ciudad Real 13592",
    "addr:housenumber":"s / n",
    "addr:postcode":"mestanza;13592",
    "iso:country":"ES",
    "sg:address":"Iglesia, S/n",
    "sg:city":"Mestanza",
    "sg:orig_category":"Iglesia Cat\u00d3lica",
    "sg:phone":"+34 926 48 55 41",
    "sg:postcode":"13592",
    "sg:province":"Ciudad Real",
    "wof:name":"Parroquia De San Esteban",
    "wof:placetype":"venue"
},
  "geometry": {"coordinates":[-4.0696840286,38.5736732483],"type":"Point"}
}