{
  "type": "Feature",
  "properties": {
    "addr:full":"Avgd Abu-masaifa, 2 Xativa Valencia 46800",
    "addr:housenumber":"2",
    "addr:postcode":"46800",
    "addr:street":"Abu-Masaifa",
    "iso:country":"ES",
    "sg:address":"Avgd Abu-masaifa, 2",
    "sg:city":"Xativa",
    "sg:orig_category":"Agencias Y Agentes Comerciales, Representantes",
    "sg:phone":"+34 962 27 56 89",
    "sg:postcode":"46800",
    "sg:province":"Valencia",
    "wof:name":"Borreguero Hervas Magdalena",
    "wof:placetype":"venue"
},
  "geometry": {"coordinates":[-0.5271130204,38.9895057678],"type":"Point"}
}