{
  "type": "Feature",
  "properties": {
    "iso:country":"ES",
    "sg:address":"Sixto, S/n",
    "sg:city":"Sixto",
    "sg:orig_category":"Cr\u00cda De Poller\u00cda Y De Conejos",
    "sg:phone":"+34 981 74 35 01",
    "sg:postcode":"15153",
    "sg:province":"La Coru\u00f1a",
    "wof:name":"San Antonio Cunicula S.l.",
    "wof:placetype":"venue"
},
  "geometry": {"coordinates":[-9.2308635712,42.9432144165],"type":"Point"}
}