{
  "type": "Feature",
  "properties": {
    "iso:country":"ES",
    "sg:address":"Carr Francesc Macia, 39",
    "sg:city":"Badalona",
    "sg:orig_category":"Art\u00cdculos De Decoraci\u00d3n",
    "sg:phone":"+34 933 89 90 84",
    "sg:postcode":"08912",
    "sg:province":"Barcelona",
    "wof:name":"Marzo Diez S.l.",
    "wof:placetype":"venue"
},
  "geometry": {"coordinates":[2.2394599915,41.4451293945],"type":"Point"}
}