{
  "type": "Feature",
  "properties": {
    "iso:country":"ES",
    "sg:address":"Calle de Mercurio, 9",
    "sg:city":"Madrid",
    "sg:orig_category":"Centros M\u00c9dicos Y Sociales, Dispensarios",
    "sg:phone":"+34 917 76 62 50",
    "sg:postcode":"28032",
    "sg:province":"Madrid",
    "wof:name":"Centro Medico Mercurio S.l.",
    "wof:placetype":"venue"
},
  "geometry": {"coordinates":[-3.6071250439,40.4054679871],"type":"Point"}
}