{
  "type": "Feature",
  "properties": {
    "addr:full":"Carrer de Sant Antoni Maria Claret, 30 Tarragona Tarragona 43002",
    "addr:housenumber":"30",
    "addr:postcode":"43002",
    "addr:street":"Carrer De Sant Antoni Maria Claret",
    "iso:country":"ES",
    "sg:address":"Carrer de Sant Antoni Maria Claret, 30",
    "sg:city":"Tarragona",
    "sg:orig_category":"Peluquer\u00cdas, Peluquer\u00cda Mixta",
    "sg:phone":"+34 977 21 52 30",
    "sg:postcode":"43002",
    "sg:province":"Tarragona",
    "wof:name":"Ferre Vilches Lidia",
    "wof:placetype":"venue"
},
  "geometry": {"coordinates":[1.2456380129,41.1215591431],"type":"Point"}
}