{
  "type": "Feature",
  "properties": {
    "iso:country":"ES",
    "sg:address":"Carrer de Gloria, 5",
    "sg:city":"Hospitalet Llobregat",
    "sg:orig_category":"Comercio De Piezas De Recambio Y De Accesorios De Veh\u00cdculos, Veh\u00cdculos Industriales",
    "sg:phone":"+34 933 32 32 78",
    "sg:postcode":"08902",
    "sg:province":"Barcelona",
    "wof:name":"Tallers Mercur Sociedad Limitada",
    "wof:placetype":"venue"
},
  "geometry": {"coordinates":[2.1191949844,41.3667068481],"type":"Point"}
}