{
  "type": "Feature",
  "properties": {
    "iso:country":"ES",
    "sg:address":"Calle de Colon, 34",
    "sg:city":"Bejar",
    "sg:orig_category":"Formaci\u00d3n Continuada (variada)",
    "sg:phone":"+34 923 41 10 20",
    "sg:postcode":"37700",
    "sg:province":"Salamanca",
    "wof:name":"Perez Hernandez Dulcinea",
    "wof:placetype":"venue"
},
  "geometry": {"coordinates":[-5.7676215172,40.3858337402],"type":"Point"}
}