{
  "type": "Feature",
  "properties": {
    "iso:country":"ES",
    "sg:address":"Calle de Ciervo, 17",
    "sg:city":"Humera-somosaguas-prado Del Rey",
    "sg:orig_category":"Aceros Especiales",
    "sg:phone":"+34 913 52 08 95",
    "sg:postcode":"28223",
    "sg:province":"Madrid",
    "wof:name":"Jofre Soubrier Alvaro",
    "wof:placetype":"venue"
},
  "geometry": {"coordinates":[-3.7003455162,40.4166908264],"type":"Point"}
}