{
  "type": "Feature",
  "properties": {
    "iso:country":"ES",
    "sg:address":"Calle de Nardos, S/n",
    "sg:city":"Palomares Rio",
    "sg:orig_category":"Agencias Y Agentes Comerciales, Representantes",
    "sg:phone":"+34 955 76 32 53",
    "sg:postcode":"41928",
    "sg:province":"Sevilla",
    "wof:name":"Barea Velasco Maria De Los Angeles",
    "wof:placetype":"venue"
},
  "geometry": {"coordinates":[-6.0653281212,37.3136405945],"type":"Point"}
}