{
  "type": "Feature",
  "properties": {
    "addr:full":"Calle de Zabala Bruno Mauricio, 59 Bilbao Vizcaya 48003",
    "addr:housenumber":"59",
    "addr:postcode":"48003",
    "addr:street":"Calle De Zabala Bruno Mauricio",
    "iso:country":"ES",
    "sg:address":"Calle de Zabala Bruno Mauricio, 59",
    "sg:city":"Bilbao",
    "sg:orig_category":"Alimentaci\u00d3n General (al Por Menor)",
    "sg:phone":"+34 944 15 74 97",
    "sg:postcode":"48003",
    "sg:province":"Vizcaya",
    "wof:name":"Arranz Casta\u00f1o Juan Carlos",
    "wof:placetype":"venue"
},
  "geometry": {"coordinates":[-2.9325225353,43.2536048889],"type":"Point"}
}