{
  "type": "Feature",
  "properties": {
    "iso:country":"ES",
    "sg:address":"Calle de Infantes, 29",
    "sg:city":"Torre Mar",
    "sg:orig_category":"Producci\u00d3n, Venta De Productos De Agricultura Biol\u00d3gica",
    "sg:phone":"+34 952 54 64 21",
    "sg:postcode":"29740",
    "sg:province":"M\u00e1laga",
    "wof:name":"Emalba S.l.",
    "wof:placetype":"venue"
},
  "geometry": {"coordinates":[-4.4374341965,36.7016029358],"type":"Point"}
}