{
  "type": "Feature",
  "properties": {
    "iso:country":"ES",
    "sg:address":"Avda Cosculluela, 5",
    "sg:city":"Ejea De Los Caballeros",
    "sg:orig_category":"Lencer\u00cda Femenina, Corseter\u00cda, Trajes De Ba\u00d1o (al Por Menor)",
    "sg:phone":"+34 976 66 14 40",
    "sg:postcode":"50600",
    "sg:province":"Zaragoza",
    "wof:name":"Maguichu S.c.",
    "wof:placetype":"venue"
},
  "geometry": {"coordinates":[-1.1386950016,42.1233825684],"type":"Point"}
}