{
  "type": "Feature",
  "properties": {
    "iso:country":"ES",
    "sg:address":"Calle de Numa Guilhou, 24",
    "sg:city":"Mieres",
    "sg:orig_category":"Caf\u00c9s, Bares, Cervecer\u00cdas",
    "sg:phone":"+34 985 45 39 60",
    "sg:postcode":"33600",
    "sg:province":"Asturias",
    "wof:name":"Fernandez Fernandez Teresa De Jesus",
    "wof:placetype":"venue"
},
  "geometry": {"coordinates":[-5.7756848335,43.2520484924],"type":"Point"}
}