{
  "type": "Feature",
  "properties": {
    "addr:full":"Ecce Homo, 3 Orihuela Alicante 03300",
    "addr:housenumber":"3",
    "addr:postcode":"03300",
    "addr:street":"Ecce Homo",
    "iso:country":"ES",
    "sg:address":"Ecce Homo, 3",
    "sg:city":"Orihuela",
    "sg:orig_category":"Asesor\u00cda Fiscal Y Jur\u00cddica",
    "sg:phone":"+34 965 30 13 58",
    "sg:postcode":"03300",
    "sg:province":"Alicante",
    "wof:name":"Asesoria De Empresas S. Sala Y Asociados",
    "wof:placetype":"venue"
},
  "geometry": {"coordinates":[-0.9080343246,38.081451416],"type":"Point"}
}