{
  "type": "Feature",
  "properties": {
    "iso:country":"ES",
    "sg:address":"Calle de Francisco Aritio, 158",
    "sg:city":"Guadalajara",
    "sg:orig_category":"Restaurantes",
    "sg:phone":"+34 949 20 01 06",
    "sg:postcode":"19004",
    "sg:province":"Guadalajara",
    "wof:name":"Albahaca C.b.",
    "wof:placetype":"venue"
},
  "geometry": {"coordinates":[-3.1990499496,40.6237640381],"type":"Point"}
}