{
  "type": "Feature",
  "properties": {
    "iso:country":"ES",
    "sg:address":"Calle de General Orgaz, 12",
    "sg:city":"Madrid",
    "sg:orig_category":"Florister\u00cdas",
    "sg:phone":"+34 915 70 66 62",
    "sg:postcode":"28020",
    "sg:province":"Madrid",
    "wof:name":"Conhi Bahamonde Maria Isabel",
    "wof:placetype":"venue"
},
  "geometry": {"coordinates":[-3.6966218948,40.4539604187],"type":"Point"}
}