{
  "type": "Feature",
  "properties": {
    "iso:country":"ES",
    "sg:address":"Calle de Cardenal Paya, 27",
    "sg:city":"Onil",
    "sg:orig_category":"Electricidad (montaje, Ensamblaje De Componentes)",
    "sg:phone":"+34 965 56 59 52",
    "sg:postcode":"03430",
    "sg:province":"Alicante",
    "wof:name":"Jose Luis Castello Verdu S.l.",
    "wof:placetype":"venue"
},
  "geometry": {"coordinates":[-0.6695073843,38.6291618347],"type":"Point"}
}