{
  "type": "Feature",
  "properties": {
    "iso:country":"ES",
    "sg:address":"Calle de Litografo Pascual Y Abad, 29",
    "sg:city":"Valencia",
    "sg:orig_category":"Agencias Y Asesores De Publicidad",
    "sg:phone":"+34 963 57 93 84",
    "sg:postcode":"46017",
    "sg:province":"Valencia",
    "wof:name":"T.d.p. S.l.",
    "wof:placetype":"venue"
},
  "geometry": {"coordinates":[-0.3900690079,39.4507713318],"type":"Point"}
}