{
  "type": "Feature",
  "properties": {
    "iso:country":"ES",
    "sg:address":"Rava Montserrat, S/n",
    "sg:city":"Terrassa",
    "sg:orig_category":"Poller\u00cda Y Caza (al Por Menor)",
    "sg:phone":"+34 937 88 77 29",
    "sg:postcode":"08221",
    "sg:province":"Barcelona",
    "wof:name":"Florensa Clapes Jaume",
    "wof:placetype":"venue"
},
  "geometry": {"coordinates":[2.0086789131,41.5634384155],"type":"Point"}
}