{
  "type": "Feature",
  "properties": {
    "addr:full":"Calle de Arrecife, 3 Rota C\u00e1diz 11520",
    "addr:housenumber":"3",
    "addr:postcode":"11520",
    "addr:street":"Calle De Arrecife;Ca\u0301Diz",
    "iso:country":"ES",
    "sg:address":"Calle de Arrecife, 3",
    "sg:city":"Rota",
    "sg:orig_category":"Centros Empresariales",
    "sg:phone":"+34 956 81 07 91",
    "sg:postcode":"11520",
    "sg:province":"C\u00e1diz",
    "wof:name":"Juanazul S.l.",
    "wof:placetype":"venue"
},
  "geometry": {"coordinates":[-6.3816542625,36.627532959],"type":"Point"}
}