{
  "type": "Feature",
  "properties": {
    "iso:country":"ES",
    "sg:address":"Calle de Campo, 8",
    "sg:city":"Barbastro",
    "sg:orig_category":"Chapister\u00cda",
    "sg:phone":"+34 974 31 11 92",
    "sg:postcode":"22300",
    "sg:province":"Huesca",
    "wof:name":"Chapa-color Rami Soc. Coop. Arag.",
    "wof:placetype":"venue"
},
  "geometry": {"coordinates":[0.1319382042,42.0417022705],"type":"Point"}
}