{
  "type": "Feature",
  "properties": {
    "addr:full":"Rua Sol, 77 Ferrol La Coru\u00f1a 15402",
    "addr:housenumber":"77",
    "addr:postcode":"15402",
    "addr:street":"Rua Sol;La Corun\u0303A",
    "iso:country":"ES",
    "sg:address":"Rua Sol, 77",
    "sg:city":"Ferrol",
    "sg:orig_category":"Abogados",
    "sg:phone":"+34 981 35 17 71",
    "sg:postcode":"15402",
    "sg:province":"La Coru\u00f1a",
    "wof:name":"Ramonde Lago Manuel Angel",
    "wof:placetype":"venue"
},
  "geometry": {"coordinates":[-8.2338628769,43.4848175049],"type":"Point"}
}