{
  "type": "Feature",
  "properties": {
    "iso:country":"ES",
    "sg:address":"Avda Francisco Fernandez Ordo\u00d1ez, 37",
    "sg:city":"Getafe",
    "sg:orig_category":"Empresas De Carpinter\u00cda Met\u00c1lica",
    "sg:phone":"+34 916 82 01 39",
    "sg:postcode":"28903",
    "sg:province":"Madrid",
    "wof:name":"Lucena Perez Antonio",
    "wof:placetype":"venue"
},
  "geometry": {"coordinates":[-3.7141952515,40.314781189],"type":"Point"}
}