{
  "type": "Feature",
  "properties": {
    "iso:country":"ES",
    "sg:address":"Calle de Conde, 33",
    "sg:city":"Ecija",
    "sg:orig_category":"Librer\u00cdas",
    "sg:phone":"+34 955 90 27 46",
    "sg:postcode":"41400",
    "sg:province":"Sevilla",
    "wof:name":"Serrano Zurita Jose Antonio",
    "wof:placetype":"venue"
},
  "geometry": {"coordinates":[-5.0823488235,37.5403747559],"type":"Point"}
}