{
  "type": "Feature",
  "properties": {
    "addr:full":"Carr Hostal De La Bordeta, 44 Lleida Lleida 25001",
    "addr:housenumber":"44",
    "addr:postcode":"25001",
    "addr:street":"Carr Hostal De La Bordeta",
    "iso:country":"ES",
    "sg:address":"Carr Hostal De La Bordeta, 44",
    "sg:city":"Lleida",
    "sg:orig_category":"Tintes (fabricaci\u00d3n, Al Por Mayor)",
    "sg:phone":"+34 973 21 36 70",
    "sg:postcode":"25001",
    "sg:province":"Lleida",
    "wof:name":"Tintoreria Dit I Net S.c.p.",
    "wof:placetype":"venue"
},
  "geometry": {"coordinates":[0.6441699862,41.6030464172],"type":"Point"}
}