{
  "type": "Feature",
  "properties": {
    "iso:country":"ES",
    "sg:address":"Pescaderia, 20",
    "sg:city":"Pontedeume",
    "sg:orig_category":"Panader\u00cdas, Panader\u00cdas",
    "sg:phone":"+34 981 43 33 22",
    "sg:postcode":"15600",
    "sg:province":"La Coru\u00f1a",
    "wof:name":"Feal Dopico Beatriz",
    "wof:placetype":"venue"
},
  "geometry": {"coordinates":[-8.17141819,43.4065628052],"type":"Point"}
}