{
  "type": "Feature",
  "properties": {
    "addr:full":"Avda Vega Baja, 58 Palacios Alicante 03179",
    "addr:housenumber":"58",
    "addr:postcode":"03179",
    "addr:street":"Avda Vega Baja",
    "iso:country":"ES",
    "sg:address":"Avda Vega Baja, 58",
    "sg:city":"Palacios",
    "sg:orig_category":"Suministros Para Hoteles",
    "sg:phone":"+34 965 72 40 83",
    "sg:postcode":"03179",
    "sg:province":"Alicante",
    "sg:website":"www.multihosteleria.com",
    "wof:name":"Broers  Conrardus Johan",
    "wof:placetype":"venue"
},
  "geometry": {"coordinates":[-0.7275000215,38.0882873535],"type":"Point"}
}