{
  "type": "Feature",
  "properties": {
    "iso:country":"ES",
    "sg:address":"Ctra. Murcia, 5",
    "sg:city":"Albacete",
    "sg:orig_category":"Lavado, Limpieza De Veh\u00cdculos",
    "sg:phone":"+34 967 24 40 98",
    "sg:postcode":"02002",
    "sg:province":"Albacete",
    "wof:name":"Antonio Simarro Barbero C.b.",
    "wof:placetype":"venue"
},
  "geometry": {"coordinates":[-1.8504304886,38.9896850586],"type":"Point"}
}