{
  "type": "Feature",
  "properties": {
    "iso:country":"ES",
    "sg:address":"Carrer de Santalo, 85",
    "sg:city":"Barcelona",
    "sg:orig_category":"M\u00c9dicos: Cirug\u00cda Ortop\u00c9dica Y Traumatolog\u00cda",
    "sg:phone":"+34 932 00 14 12",
    "sg:postcode":"08021",
    "sg:province":"Barcelona",
    "wof:name":"Poal-manresa Cantarell Alejandro",
    "wof:placetype":"venue"
},
  "geometry": {"coordinates":[2.1431219578,41.3975791931],"type":"Point"}
}