{
  "type": "Feature",
  "properties": {
    "addr:full":"Avda Cauchil, 21 Bornos C\u00e1diz 11640",
    "addr:housenumber":"21",
    "addr:postcode":"11640",
    "addr:street":"Avda Cauchil;Ca\u0301Diz",
    "iso:country":"ES",
    "sg:address":"Avda Cauchil, 21",
    "sg:city":"Bornos",
    "sg:orig_category":"Asociaciones Y Clubs Deportivos",
    "sg:phone":"+34 956 72 80 27",
    "sg:postcode":"11640",
    "sg:province":"C\u00e1diz",
    "wof:name":"Franesport Distribuciones Deportivas S.l.",
    "wof:placetype":"venue"
},
  "geometry": {"coordinates":[-5.7452449799,36.8190689087],"type":"Point"}
}