{
  "type": "Feature",
  "properties": {
    "addr:full":"Mas Potau, S/n Borges Del Camp Tarragona 43350",
    "addr:housenumber":"s",
    "addr:postcode":"43350",
    "addr:street":"/ N Borges Del Camp",
    "iso:country":"ES",
    "sg:address":"Mas Potau, S/n",
    "sg:city":"Borges Del Camp",
    "sg:orig_category":"Agricultura: Abastecimiento Y Cosechado (negocio)",
    "sg:phone":"+34 977 81 70 04",
    "sg:postcode":"43350",
    "sg:province":"Tarragona",
    "wof:name":"Camprubi Potau Mercedes",
    "wof:placetype":"venue"
},
  "geometry": {"coordinates":[1.0211700201,41.1718292236],"type":"Point"}
}