{
  "type": "Feature",
  "properties": {
    "addr:full":"Calle de Orobal, 13 Camella Santa Cruz De Tenerife 38627",
    "addr:housenumber":"13",
    "addr:postcode":"38627",
    "addr:street":"Calle De Orobal",
    "iso:country":"ES",
    "sg:address":"Calle de Orobal, 13",
    "sg:city":"Camella",
    "sg:orig_category":"Empresas De Limpieza",
    "sg:phone":"+34 922 72 14 74",
    "sg:postcode":"38627",
    "sg:province":"Santa Cruz De Tenerife",
    "wof:name":"Limpieza Teidesur S.l.",
    "wof:placetype":"venue"
},
  "geometry": {"coordinates":[-16.6819610596,28.0780124664],"type":"Point"}
}