{
  "type": "Feature",
  "properties": {
    "iso:country":"ES",
    "sg:address":"Urbitarte, S/n",
    "sg:city":"Tra\u00f1a-matiena",
    "sg:orig_category":"Seguridad Social",
    "sg:phone":"+34 946 81 18 20",
    "sg:postcode":"48220",
    "sg:province":"Vizcaya",
    "sg:website":"www.fremap.es",
    "wof:name":"Fremap-mutua De Accidentes De Trabajo Y Enfermedades Profesionales De La Seguridad Social",
    "wof:placetype":"venue"
},
  "geometry": {"coordinates":[-2.6079039574,43.1692581177],"type":"Point"}
}