{
  "type": "Feature",
  "properties": {
    "iso:country":"ES",
    "sg:address":"Calle de Mendez Alvaro, 44",
    "sg:city":"Madrid",
    "sg:orig_category":"Transporte En General",
    "sg:phone":"+34 915 06 52 00",
    "sg:postcode":"28...",
    "sg:province":"Madrid",
    "wof:name":"Compa\u00d1ia Logistica De Hidrocarburos Clh S.a.",
    "wof:placetype":"venue"
},
  "geometry": {"coordinates":[-3.6833748817,40.3981513977],"type":"Point"}
}