{
  "type": "Feature",
  "properties": {
    "iso:country":"ES",
    "sg:address":"Calle de Candelario, 2",
    "sg:city":"Salamanca",
    "sg:orig_category":"Caf\u00c9s, Bares, Cervecer\u00cdas",
    "sg:phone":"+34 923 23 85 68",
    "sg:postcode":"37007",
    "sg:province":"Salamanca",
    "wof:name":"Romero Calvo Andres",
    "wof:placetype":"venue"
},
  "geometry": {"coordinates":[-5.6713905334,40.9723854065],"type":"Point"}
}