{
  "type": "Feature",
  "properties": {
    "addr:full":"Carrer de Miquel Servet, 16 Terrassa Barcelona 08222",
    "addr:housenumber":"16",
    "addr:postcode":"08222",
    "addr:street":"Carrer De Miquel Servet",
    "iso:country":"ES",
    "sg:address":"Carrer de Miquel Servet, 16",
    "sg:city":"Terrassa",
    "sg:orig_category":"Fabricaci\u00d3n, Importaci\u00d3n De L\u00c1mparas Y Bombillas",
    "sg:phone":"+34 937 85 92 40",
    "sg:postcode":"08222",
    "sg:province":"Barcelona",
    "wof:name":"Escanez Garcia Diego",
    "wof:placetype":"venue"
},
  "geometry": {"coordinates":[2.0215489864,41.5594825745],"type":"Point"}
}