{
  "type": "Feature",
  "properties": {
    "iso:country":"ES",
    "sg:address":"Avda Andalucia, 234",
    "sg:city":"Dos Hermanas",
    "sg:orig_category":"Materias Pl\u00c1sticas: Art\u00cdculos Para La Industria",
    "sg:phone":"+34 955 66 64 64",
    "sg:postcode":"41700",
    "sg:province":"Sevilla",
    "wof:name":"Arkema Quimica S.a.",
    "wof:placetype":"venue"
},
  "geometry": {"coordinates":[-6.0534763336,37.2818527222],"type":"Point"}
}