{
  "type": "Feature",
  "properties": {
    "iso:country":"ES",
    "sg:address":"E Aperador(b Progreso), 15",
    "sg:city":"Murcia",
    "sg:orig_category":"Empresas De Carpinter\u00cda Met\u00c1lica",
    "sg:phone":"+34 968 34 24 47",
    "sg:postcode":"30012",
    "sg:province":"Murcia",
    "wof:name":"Domingo Galvez Juan Miguel",
    "wof:placetype":"venue"
},
  "geometry": {"coordinates":[-1.1206640005,37.9650650024],"type":"Point"}
}