{
  "type": "Feature",
  "properties": {
    "iso:country":"ES",
    "sg:address":"Avgd Marti Pujol, 294",
    "sg:city":"Badalona",
    "sg:orig_category":"Delegados, Agentes De Tr\u00c1nsito, Auxiliares De Transporte Internacional",
    "sg:phone":"+34 933 84 16 12",
    "sg:postcode":"08911",
    "sg:province":"Barcelona",
    "wof:name":"Martin Trujillo Francisco",
    "wof:placetype":"venue"
},
  "geometry": {"coordinates":[2.2433290482,41.4531478882],"type":"Point"}
}