{
  "type": "Feature",
  "properties": {
    "addr:full":"Carrer de Sant Fermi, 2 S. Celoni Barcelona 08470",
    "addr:housenumber":"2",
    "addr:postcode":"08470",
    "addr:street":"Carrer De Sant Fermi",
    "iso:country":"ES",
    "sg:address":"Carrer de Sant Fermi, 2",
    "sg:city":"S. Celoni",
    "sg:orig_category":"Comercio De Hierro",
    "sg:phone":"+34 938 67 00 74",
    "sg:postcode":"08470",
    "sg:province":"Barcelona",
    "wof:name":"Hierros Berenguer S.a.",
    "wof:placetype":"venue"
},
  "geometry": {"coordinates":[2.4880189896,41.6807861328],"type":"Point"}
}