{
  "type": "Feature",
  "properties": {
    "iso:country":"ES",
    "sg:address":"Calle de Nutria (de La), 17",
    "sg:city":"Alcobendas",
    "sg:orig_category":"Asesor\u00cdas Y Estudios Financieros",
    "sg:phone":"+34 916 50 88 24",
    "sg:postcode":"28109",
    "sg:province":"Madrid",
    "wof:name":"Zardoya Arana Javier",
    "wof:placetype":"venue"
},
  "geometry": {"coordinates":[-3.6286170483,40.5257568359],"type":"Point"}
}