{
  "type": "Feature",
  "properties": {
    "iso:country":"ES",
    "sg:address":"Calle de Medico Ruiz, 37",
    "sg:city":"Estepa",
    "sg:orig_category":"Asociaciones Y Clubs Deportivos",
    "sg:phone":"+34 954 82 07 44",
    "sg:postcode":"41560",
    "sg:province":"Sevilla",
    "wof:name":"Paez Y Fernandez S.l.",
    "wof:placetype":"venue"
},
  "geometry": {"coordinates":[-4.8774018288,37.2923545837],"type":"Point"}
}