{
  "type": "Feature",
  "properties": {
    "addr:full":"Calle de Comandante Vallespin, 58 Oviedo Asturias 33013",
    "addr:housenumber":"58",
    "addr:postcode":"33013",
    "addr:street":"Calle De Comandante Vallespin",
    "iso:country":"ES",
    "sg:address":"Calle de Comandante Vallespin, 58",
    "sg:city":"Oviedo",
    "sg:orig_category":"Ense\u00d1anza: Idiomas",
    "sg:phone":"+34 985 25 23 40",
    "sg:postcode":"33013",
    "sg:province":"Asturias",
    "wof:name":"Shelman  Larry",
    "wof:placetype":"venue"
},
  "geometry": {"coordinates":[-5.8636288643,43.3635101318],"type":"Point"}
}