{
  "type": "Feature",
  "properties": {
    "addr:full":"Calle de Moncada, 122 Madrid Madrid 28021",
    "addr:housenumber":"122",
    "addr:postcode":"28021",
    "addr:street":"Calle De Moncada",
    "iso:country":"ES",
    "sg:address":"Calle de Moncada, 122",
    "sg:city":"Madrid",
    "sg:orig_category":"Molduras, Junquillos, Listones Y Molduras Perforadas",
    "sg:phone":"+34 917 97 20 94",
    "sg:postcode":"28021",
    "sg:province":"Madrid",
    "wof:name":"Faraldos Garcia Gaudencio",
    "wof:placetype":"venue"
},
  "geometry": {"coordinates":[-3.691988945,40.3397331238],"type":"Point"}
}