{
  "type": "Feature",
  "properties": {
    "iso:country":"ES",
    "sg:address":"Avda Mediterraneo, 53",
    "sg:city":"Madrid",
    "sg:orig_category":"Ingenier\u00cda, Centros De Estudios (diversos)",
    "sg:phone":"+34 915 73 14 05",
    "sg:postcode":"28007",
    "sg:province":"Madrid",
    "wof:name":"Andres Gil Francisco Javier",
    "wof:placetype":"venue"
},
  "geometry": {"coordinates":[-3.6681308746,40.4068374634],"type":"Point"}
}