{
  "type": "Feature",
  "properties": {
    "addr:full":"Avda Santa Lucia, 10 Alcala Guadaira Sevilla 41500",
    "addr:housenumber":"10",
    "addr:postcode":"41500",
    "addr:street":"Avda Santa Lucia",
    "iso:country":"ES",
    "sg:address":"Avda Santa Lucia, 10",
    "sg:city":"Alcala Guadaira",
    "sg:orig_category":"Muebles Y Accesorios Para Cocinas Y Cuartos De Ba\u00d1o (al Por Menor)",
    "sg:phone":"+34 955 68 31 68",
    "sg:postcode":"41500",
    "sg:province":"Sevilla",
    "sg:website":"www.cocinova.com",
    "wof:name":"Cocinova, Montajes De Cocinas S.l.",
    "wof:placetype":"venue"
},
  "geometry": {"coordinates":[-5.8372440338,37.3333244324],"type":"Point"}
}