{
  "type": "Feature",
  "properties": {
    "addr:full":"Calle de Pintor Ferrer Calatayud, 13 Valencia Valencia 46022",
    "addr:housenumber":"13",
    "addr:postcode":"46022",
    "addr:street":"Calle De Pintor Ferrer Calatayud",
    "iso:country":"ES",
    "sg:address":"Calle de Pintor Ferrer Calatayud, 13",
    "sg:city":"Valencia",
    "sg:orig_category":"Carnicer\u00cdas, Carnicer\u00cdas",
    "sg:phone":"+34 963 72 48 60",
    "sg:postcode":"46022",
    "sg:province":"Valencia",
    "wof:name":"Vivo Cortell Renan",
    "wof:placetype":"venue"
},
  "geometry": {"coordinates":[-0.3377321959,39.4676322937],"type":"Point"}
}