{
  "type": "Feature",
  "properties": {
    "iso:country":"ES",
    "sg:address":"Avda Gregorio Gea, 83",
    "sg:city":"Mislata",
    "sg:orig_category":"Farmacias",
    "sg:phone":"+34 963 83 69 48",
    "sg:postcode":"46920",
    "sg:province":"Valencia",
    "wof:name":"Clerigues Belloch Mercedes",
    "wof:placetype":"venue"
},
  "geometry": {"coordinates":[-0.4217790067,39.4751586914],"type":"Point"}
}