{
  "type": "Feature",
  "properties": {
    "iso:country":"ES",
    "sg:address":"Carrer de Joan Prim, 242",
    "sg:city":"Granollers",
    "sg:orig_category":"Panader\u00cdas, Panader\u00cdas",
    "sg:phone":"+34 938 49 04 29",
    "sg:postcode":"08402",
    "sg:province":"Barcelona",
    "wof:name":"Colomer Mas Valerio",
    "wof:placetype":"venue"
},
  "geometry": {"coordinates":[2.291410923,41.6161994934],"type":"Point"}
}