{
  "type": "Feature",
  "properties": {
    "addr:full":"Rua Emilia Pardo Bazan, 18 Allariz Ourense 32660",
    "addr:housenumber":"18",
    "addr:postcode":"32660",
    "addr:street":"Rua Emilia Pardo Bazan",
    "iso:country":"ES",
    "sg:address":"Rua Emilia Pardo Bazan, 18",
    "sg:city":"Allariz",
    "sg:orig_category":"Art\u00cdculos De Regalo (al Por Menor)",
    "sg:phone":"+34 988 44 03 87",
    "sg:postcode":"32660",
    "sg:province":"Ourense",
    "wof:name":"Miranda Babarro Maria Alicia",
    "wof:placetype":"venue"
},
  "geometry": {"coordinates":[-7.8028831482,42.1877746582],"type":"Point"}
}