{
  "type": "Feature",
  "properties": {
    "addr:full":"Calle de Pintor Rodriguez Luna, 5 Montoro C\u00f3rdoba 14600",
    "addr:housenumber":"5",
    "addr:postcode":"14600",
    "addr:street":"Calle De Pintor Rodriguez Luna;Co\u0301Rdoba",
    "iso:country":"ES",
    "sg:address":"Calle de Pintor Rodriguez Luna, 5",
    "sg:city":"Montoro",
    "sg:orig_category":"Ferreter\u00cda Artesanal",
    "sg:phone":"+34 957 16 13 80",
    "sg:postcode":"14600",
    "sg:province":"C\u00f3rdoba",
    "wof:name":"Arroyo Lara Francisco",
    "wof:placetype":"venue"
},
  "geometry": {"coordinates":[-4.3828015327,38.0184555054],"type":"Point"}
}