{
  "type": "Feature",
  "properties": {
    "iso:country":"ES",
    "sg:address":"Calle de Fuenterrabia, 50",
    "sg:city":"Donostia-san Sebastian",
    "sg:orig_category":"Estudios De Grabaci\u00d3n Sonora",
    "sg:phone":"+34 943 46 86 11",
    "sg:postcode":"20005",
    "sg:province":"Guip\u00f9zcoa",
    "wof:name":"Jose Ramon Echeverria Carrere Y Otro Cdad",
    "wof:placetype":"venue"
},
  "geometry": {"coordinates":[-1.9801100492,43.3158683777],"type":"Point"}
}