{
  "type": "Feature",
  "properties": {
    "iso:country":"ES",
    "sg:address":"Calle de Carmen Sanchez Carrascosa, 7",
    "sg:city":"Madrid",
    "sg:orig_category":"Inmobiliaria (agencias)",
    "sg:phone":"+34 913 23 29 49",
    "sg:postcode":"28046",
    "sg:province":"Madrid",
    "sg:website":"www.sifoxa.com",
    "wof:name":"Suministros Foxa, S.l.",
    "wof:placetype":"venue"
},
  "geometry": {"coordinates":[-3.6871209145,40.4689483643],"type":"Point"}
}