{
  "type": "Feature",
  "properties": {
    "addr:full":"Plaz Generalisimo, 15 Villaviciosa Asturias 33300",
    "addr:housenumber":"15",
    "addr:postcode":"33300",
    "addr:street":"Plaz Generalisimo",
    "iso:country":"ES",
    "sg:address":"Plaz Generalisimo, 15",
    "sg:city":"Villaviciosa",
    "sg:orig_category":"Cajas De Ahorro",
    "sg:phone":"+34 985 89 00 92",
    "sg:postcode":"33300",
    "sg:province":"Asturias",
    "sg:website":"www.cajastur.es",
    "wof:name":"Caja De Ahorros De Asturias",
    "wof:placetype":"venue"
},
  "geometry": {"coordinates":[-5.4336237907,43.4811897278],"type":"Point"}
}