{
  "type": "Feature",
  "properties": {
    "iso:country":"ES",
    "sg:address":"Carrer de Sant Vicent, 38",
    "sg:city":"Campello",
    "sg:orig_category":"Agencias Y Agentes Comerciales, Representantes",
    "sg:phone":"+34 965 63 04 39",
    "sg:postcode":"03560",
    "sg:province":"Alicante",
    "wof:name":"Mira Abad Jose",
    "wof:placetype":"venue"
},
  "geometry": {"coordinates":[-0.3891009986,38.4282150269],"type":"Point"}
}