{
  "type": "Feature",
  "properties": {
    "addr:full":"Carrer de Proven\u00c7a, 546 Barcelona Barcelona 08025",
    "addr:housenumber":"546",
    "addr:postcode":"08025",
    "addr:street":"Carrer De Provenc\u0327A",
    "iso:country":"ES",
    "sg:address":"Carrer de Proven\u00c7a, 546",
    "sg:city":"Barcelona",
    "sg:orig_category":"Agencias Y Agentes Comerciales, Representantes",
    "sg:phone":"+34 933 47 53 59",
    "sg:postcode":"08025",
    "sg:province":"Barcelona",
    "wof:name":"Vargas Sanchez Carlos",
    "wof:placetype":"venue"
},
  "geometry": {"coordinates":[2.1798770428,41.4083251953],"type":"Point"}
}