{
  "type": "Feature",
  "properties": {
    "addr:full":"Ctra Berlanga (de), S/n Atienza Guadalajara 19270",
    "addr:postcode":"19270",
    "addr:street":"Ctra Berlanga De S / N Atienza",
    "iso:country":"ES",
    "sg:address":"Ctra Berlanga (de), S/n",
    "sg:city":"Atienza",
    "sg:orig_category":"Distribuci\u00d3n De Petr\u00d3leo Y Derivados",
    "sg:phone":"+34 949 39 91 68",
    "sg:postcode":"19270",
    "sg:province":"Guadalajara",
    "wof:name":"Garcia Garcia Joaquin",
    "wof:placetype":"venue"
},
  "geometry": {"coordinates":[-2.8690900803,41.1993293762],"type":"Point"}
}