{
  "type": "Feature",
  "properties": {
    "addr:full":"Rua Rio Ladra, 16 Lugo Lugo 27003",
    "addr:housenumber":"16",
    "addr:postcode":"27003",
    "addr:street":"Rua;Ladra",
    "iso:country":"ES",
    "sg:address":"Rua Rio Ladra, 16",
    "sg:city":"Lugo",
    "sg:orig_category":"Empresas De Carpinter\u00cda Met\u00c1lica",
    "sg:phone":"+34 982 21 16 66",
    "sg:postcode":"27003",
    "sg:province":"Lugo",
    "wof:name":"Talleres M.sordo S.l.",
    "wof:placetype":"venue"
},
  "geometry": {"coordinates":[-7.5674300194,43.0247383118],"type":"Point"}
}