{
  "type": "Feature",
  "properties": {
    "addr:full":"Calle de Libertad, 63 Calamonte Badajoz 06810",
    "addr:housenumber":"63",
    "addr:postcode":"06810",
    "addr:street":"Calle De Libertad",
    "iso:country":"ES",
    "sg:address":"Calle de Libertad, 63",
    "sg:city":"Calamonte",
    "sg:orig_category":"Peluquer\u00cdas, Peluquer\u00cda Mixta",
    "sg:phone":"+34 924 32 41 80",
    "sg:postcode":"06810",
    "sg:province":"Badajoz",
    "wof:name":"Fernandez Almoaril Luz Maria",
    "wof:placetype":"venue"
},
  "geometry": {"coordinates":[-6.3859090805,38.8825492859],"type":"Point"}
}