{
  "type": "Feature",
  "properties": {
    "addr:full":"Calle de Derecha Al Coso, 41 Pe\u00f1afiel Valladolid 47300",
    "addr:housenumber":"41",
    "addr:postcode":"47300",
    "addr:street":"Calle De Derecha Al Coso",
    "iso:country":"ES",
    "sg:address":"Calle de Derecha Al Coso, 41",
    "sg:city":"Pe\u00f1afiel",
    "sg:orig_category":"Iglesia Cat\u00d3lica",
    "sg:phone":"+34 983 88 09 05",
    "sg:postcode":"47300",
    "sg:province":"Valladolid",
    "wof:name":"Parroquia De San Miguel Arcangel",
    "wof:placetype":"venue"
},
  "geometry": {"coordinates":[-4.1183786392,41.5948219299],"type":"Point"}
}