{
  "type": "Feature",
  "properties": {
    "addr:full":"Avda Hispanidad, 2 Santa Fe Granada 18320",
    "addr:housenumber":"2",
    "addr:postcode":"18320",
    "addr:street":"Avda Hispanidad;Fe",
    "iso:country":"ES",
    "sg:address":"Avda Hispanidad, 2",
    "sg:city":"Santa Fe",
    "sg:orig_category":"Bancos",
    "sg:phone":"+34 958 44 01 25",
    "sg:postcode":"18320",
    "sg:province":"Granada",
    "sg:website":"www.gruposantander.es",
    "wof:name":"Bt Espa\u00d1a Compa\u00d1ia De Servicios Globales De Telecomunicaciones S.a.u.",
    "wof:placetype":"venue"
},
  "geometry": {"coordinates":[-3.7110290527,37.1915245056],"type":"Point"}
}