{
  "type": "Feature",
  "properties": {
    "iso:country":"ES",
    "sg:address":"Avda Gijon, 80",
    "sg:city":"Valladolid",
    "sg:orig_category":"Mec\u00c1nico Del Autom\u00d3vil",
    "sg:phone":"+34 983 33 40 41",
    "sg:postcode":"47009",
    "sg:province":"Valladolid",
    "wof:name":"Rioseco Motor S.l.",
    "wof:placetype":"venue"
},
  "geometry": {"coordinates":[-4.7517518997,41.6608695984],"type":"Point"}
}