{
  "type": "Feature",
  "properties": {
    "iso:country":"ES",
    "sg:address":"Ptge Miquel Carreras, 21",
    "sg:city":"Sabadell",
    "sg:orig_category":"Guarder\u00cdas",
    "sg:phone":"+34 937 27 59 86",
    "sg:postcode":"08206",
    "sg:province":"Barcelona",
    "wof:name":"Fundacio Privada Jaume Viladoms",
    "wof:placetype":"venue"
},
  "geometry": {"coordinates":[2.0941562653,41.5476837158],"type":"Point"}
}