{
  "type": "Feature",
  "properties": {
    "addr:full":"Plaz Espa\u00d1a, 9 Binefar Huesca 22500",
    "addr:housenumber":"9",
    "addr:postcode":"22500",
    "addr:street":"Plaz Espan\u0303A",
    "iso:country":"ES",
    "sg:address":"Plaz Espa\u00d1a, 9",
    "sg:city":"Binefar",
    "sg:orig_category":"Agencias De Viajes",
    "sg:phone":"+34 974 42 80 33",
    "sg:postcode":"22500",
    "sg:province":"Huesca",
    "wof:name":"Catalana Condal S.l.",
    "wof:placetype":"venue"
},
  "geometry": {"coordinates":[0.2930839956,41.8510017395],"type":"Point"}
}