{
  "type": "Feature",
  "properties": {
    "addr:full":"Calle de Francos, 24 Sevilla Sevilla 41004",
    "addr:housenumber":"24",
    "addr:postcode":"41004",
    "addr:street":"Calle De Francos",
    "iso:country":"ES",
    "sg:address":"Calle de Francos, 24",
    "sg:city":"Sevilla",
    "sg:orig_category":"Moda",
    "sg:phone":"+34 954 22 57 13",
    "sg:postcode":"41004",
    "sg:province":"Sevilla",
    "wof:name":"Pino Ferrer Guillermo Del",
    "wof:placetype":"venue"
},
  "geometry": {"coordinates":[-5.9927501678,37.3889503479],"type":"Point"}
}