{
  "type": "Feature",
  "properties": {
    "iso:country":"ES",
    "sg:address":"Pol Ind Vda Castro, 3",
    "sg:city":"Lucena",
    "sg:orig_category":"Albergues",
    "sg:phone":"+34 957 51 36 26",
    "sg:postcode":"14900",
    "sg:province":"C\u00f3rdoba",
    "wof:name":"Ruiz Pino Francisco",
    "wof:placetype":"venue"
},
  "geometry": {"coordinates":[-4.4935312271,37.4047622681],"type":"Point"}
}