{
  "type": "Feature",
  "properties": {
    "addr:full":"Calle de Gascon De Gotor, 23 Zaragoza Zaragoza 50006",
    "addr:housenumber":"23",
    "addr:postcode":"50006",
    "addr:street":"Calle De Gascon De Gotor",
    "iso:country":"ES",
    "sg:address":"Calle de Gascon De Gotor, 23",
    "sg:city":"Zaragoza",
    "sg:orig_category":"Molduras, Junquillos, Listones Y Molduras Perforadas",
    "sg:phone":"+34 976 37 70 62",
    "sg:postcode":"50006",
    "sg:province":"Zaragoza",
    "wof:name":"Lahoz Dominguez Carmelo",
    "wof:placetype":"venue"
},
  "geometry": {"coordinates":[-0.8887408972,41.6386299133],"type":"Point"}
}