{
  "type": "Feature",
  "properties": {
    "iso:country":"ES",
    "sg:address":"Calle de Dolores Ibarruri Pasionaria, 1",
    "sg:city":"Torremolinos",
    "sg:orig_category":"Art\u00cdculos De Regalo (al Por Menor)",
    "sg:phone":"+34 952 05 43 46",
    "sg:postcode":"29620",
    "sg:province":"M\u00e1laga",
    "wof:name":"Velasco Cisneros Silvia",
    "wof:placetype":"venue"
},
  "geometry": {"coordinates":[-4.5071339607,36.6187591553],"type":"Point"}
}