{
  "type": "Feature",
  "properties": {
    "addr:full":"Calle de Juan Manuel Duran Gonzalez, 47 Palmas De Gran Canaria Las Palmas 35010",
    "addr:housenumber":"47",
    "addr:postcode":"35010",
    "addr:street":"Calle De Juan Manuel Duran Gonzalez",
    "iso:country":"ES",
    "sg:address":"Calle de Juan Manuel Duran Gonzalez, 47",
    "sg:city":"Palmas De Gran Canaria",
    "sg:orig_category":"Sociedades, Compa\u00d1\u00cdas Aseguradoras",
    "sg:phone":"+34 928 22 79 66",
    "sg:postcode":"35010",
    "sg:province":"Las Palmas",
    "sg:website":"www.infoservicios.com",
    "wof:name":"Curto Nu\u00f1ez Ricardo",
    "wof:placetype":"venue"
},
  "geometry": {"coordinates":[-15.4350690842,28.1351585388],"type":"Point"}
}