{
  "type": "Feature",
  "properties": {
    "iso:country":"ES",
    "sg:address":"Ptda Caxola, S/n",
    "sg:city":"Finestrat",
    "sg:orig_category":"Frutas Y Legumbres Frescas (al Por Mayor)",
    "sg:phone":"+34 966 80 47 03",
    "sg:postcode":"03509",
    "sg:province":"Alicante",
    "wof:name":"Bahia Invest- Fund S.l.u.",
    "wof:placetype":"venue"
},
  "geometry": {"coordinates":[-0.2106740028,38.5691642761],"type":"Point"}
}