{
  "type": "Feature",
  "properties": {
    "iso:country":"ES",
    "sg:address":"Calle de Miguel Artigas, 6",
    "sg:city":"Santander",
    "sg:orig_category":"Ropa Para Ni\u00d1os (al Por Menor)",
    "sg:phone":"+34 942 36 56 45",
    "sg:postcode":"39007",
    "sg:province":"Cantabria",
    "sg:website":"www.neckandneck.com",
    "wof:name":"Neck Child S.a.",
    "wof:placetype":"venue"
},
  "geometry": {"coordinates":[-3.8113179207,43.4623146057],"type":"Point"}
}