{
  "type": "Feature",
  "properties": {
    "iso:country":"ES",
    "sg:address":"Carr Nou, 22",
    "sg:city":"Mao",
    "sg:orig_category":"Confiter\u00cdas, Chocolater\u00cdas (al Por Menor)",
    "sg:phone":"+34 971 36 28 98",
    "sg:postcode":"07701",
    "sg:province":"Islas Baleares",
    "sg:website":"www.elturronero.com",
    "wof:name":"Jomovicam C.b",
    "wof:placetype":"venue"
},
  "geometry": {"coordinates":[4.265625,39.8903694153],"type":"Point"}
}