{
  "type": "Feature",
  "properties": {
    "addr:full":"Jose Artetxe Kalea, 10 Azpeitia Guip\u00f9zcoa 20730",
    "addr:housenumber":"10",
    "addr:postcode":"20730",
    "addr:street":"Jose Artetxe Kalea;Guipu\u0300Zcoa",
    "iso:country":"ES",
    "sg:address":"Jose Artetxe Kalea, 10",
    "sg:city":"Azpeitia",
    "sg:orig_category":"Herboristas (al Por Menor)",
    "sg:phone":"+34 943 81 45 41",
    "sg:postcode":"20730",
    "sg:province":"Guip\u00f9zcoa",
    "wof:name":"Ana Ugarte Y Otro C.b.",
    "wof:placetype":"venue"
},
  "geometry": {"coordinates":[-2.2671365738,43.1818962097],"type":"Point"}
}