{
  "type": "Feature",
  "properties": {
    "iso:country":"ES",
    "sg:address":"Carrer de Pere Benavent, 24",
    "sg:city":"Reus",
    "sg:orig_category":"Molduras, Junquillos, Listones Y Molduras Perforadas",
    "sg:phone":"+34 977 77 68 06",
    "sg:postcode":"43205",
    "sg:province":"Tarragona",
    "wof:name":"Gonzalez Montalvo Cb.",
    "wof:placetype":"venue"
},
  "geometry": {"coordinates":[1.107929945,41.1519889832],"type":"Point"}
}