{
  "type": "Feature",
  "properties": {
    "iso:country":"ES",
    "sg:address":"Avda Castros (los), 38",
    "sg:city":"Santander",
    "sg:orig_category":"Abogados",
    "sg:phone":"+34 942 27 20 61",
    "sg:postcode":"39005",
    "sg:province":"Cantabria",
    "wof:name":"Madrazo Feliu Baldomero",
    "wof:placetype":"venue"
},
  "geometry": {"coordinates":[-3.7917399406,43.4726638794],"type":"Point"}
}