{
  "type": "Feature",
  "properties": {
    "addr:full":"Calle de Collado (el), 41 Soria Soria 42002",
    "addr:housenumber":"41",
    "addr:postcode":"42002",
    "addr:street":"Calle De Collado El",
    "iso:country":"ES",
    "sg:address":"Calle de Collado (el), 41",
    "sg:city":"Soria",
    "sg:orig_category":"Lencer\u00cda Femenina, Corseter\u00cda, Trajes De Ba\u00d1o (al Por Menor)",
    "sg:phone":"+34 975 22 53 68",
    "sg:postcode":"42002",
    "sg:province":"Soria",
    "wof:name":"Ceartex S.l.",
    "wof:placetype":"venue"
},
  "geometry": {"coordinates":[-2.4668824673,41.7642555237],"type":"Point"}
}