{
  "type": "Feature",
  "properties": {
    "addr:full":"Poble Espanyol, S/n Barcelona Barcelona 08038",
    "addr:housenumber":"s",
    "addr:postcode":"08038",
    "addr:street":"/ N",
    "iso:country":"ES",
    "sg:address":"Poble Espanyol, S/n",
    "sg:city":"Barcelona",
    "sg:orig_category":"Fabricaci\u00d3n De Art\u00cdculos Y Ornamentos Religiosos",
    "sg:phone":"+34 934 23 49 21",
    "sg:postcode":"08038",
    "sg:province":"Barcelona",
    "wof:name":"Angulo Santa Maria Isabel",
    "wof:placetype":"venue"
},
  "geometry": {"coordinates":[2.1470000744,41.3689994812],"type":"Point"}
}