{
  "type": "Feature",
  "properties": {
    "iso:country":"ES",
    "sg:address":"Calle de Margarita, 35",
    "sg:city":"Fuengirola",
    "sg:orig_category":"Empresas De Carpinter\u00cda",
    "sg:phone":"+34 952 46 95 87",
    "sg:postcode":"29640",
    "sg:province":"M\u00e1laga",
    "wof:name":"Fernande Jimenez Jose",
    "wof:placetype":"venue"
},
  "geometry": {"coordinates":[-4.6257758141,36.533203125],"type":"Point"}
}