{
  "type": "Feature",
  "properties": {
    "addr:full":"Calle de Herrerias, 43 Ejea De Los Caballeros Zaragoza 50600",
    "addr:housenumber":"43",
    "addr:postcode":"50600",
    "addr:street":"Calle De Herrerias",
    "iso:country":"ES",
    "sg:address":"Calle de Herrerias, 43",
    "sg:city":"Ejea De Los Caballeros",
    "sg:orig_category":"Material Y Suministros Para Perforaciones, Sondeos",
    "sg:phone":"+34 976 66 16 06",
    "sg:postcode":"50600",
    "sg:province":"Zaragoza",
    "wof:name":"Marcellan Benavente Jose Antonio",
    "wof:placetype":"venue"
},
  "geometry": {"coordinates":[-1.1369576454,42.1288070679],"type":"Point"}
}