{
  "type": "Feature",
  "properties": {
    "addr:full":"Avda Reyes Catolicos, 20 Burgos Burgos 09005",
    "addr:housenumber":"20",
    "addr:postcode":"09005",
    "addr:street":"Avda Reyes Catolicos",
    "iso:country":"ES",
    "sg:address":"Avda Reyes Catolicos, 20",
    "sg:city":"Burgos",
    "sg:orig_category":"Ense\u00d1anza: Profesiones Art\u00cdsticas",
    "sg:phone":"+34 947 21 58 22",
    "sg:postcode":"09005",
    "sg:province":"Burgos",
    "wof:name":"Fernandez Manjon Lupicinio",
    "wof:placetype":"venue"
},
  "geometry": {"coordinates":[-3.6935789585,42.3469467163],"type":"Point"}
}