{
  "type": "Feature",
  "properties": {
    "iso:country":"ES",
    "sg:address":"Avda Manzanares, 144",
    "sg:city":"Madrid",
    "sg:orig_category":"Laboratorios Y Trabajos De Fotograf\u00cda, V\u00cddeo Y Cine",
    "sg:phone":"+34 915 60 86 49",
    "sg:postcode":"28019",
    "sg:province":"Madrid",
    "wof:name":"Prieto Cernuda Eduardo",
    "wof:placetype":"venue"
},
  "geometry": {"coordinates":[-3.7104270458,40.3962097168],"type":"Point"}
}