{
  "type": "Feature",
  "properties": {
    "addr:full":"Calle de Galache Hoyuelos, 4 Badajoz Badajoz 06008",
    "addr:housenumber":"4",
    "addr:postcode":"06008",
    "addr:street":"Calle De Galache Hoyuelos",
    "iso:country":"ES",
    "sg:address":"Calle de Galache Hoyuelos, 4",
    "sg:city":"Badajoz",
    "sg:orig_category":"Grifer\u00cda",
    "sg:phone":"+34 924 23 62 83",
    "sg:postcode":"06008",
    "sg:province":"Badajoz",
    "sg:website":"www.griferiasrome.com",
    "wof:name":"Griferia Y Accesorios Rome S.l.",
    "wof:placetype":"venue"
},
  "geometry": {"coordinates":[-6.961271286,38.8793792725],"type":"Point"}
}