{
  "type": "Feature",
  "properties": {
    "iso:country":"ES",
    "sg:address":"Calle de San Fernando, 10",
    "sg:city":"Santander",
    "sg:orig_category":"Abogados",
    "sg:phone":"+34 942 37 47 09",
    "sg:postcode":"39010",
    "sg:province":"Cantabria",
    "wof:name":"Franco Rodriguez Tomas",
    "wof:placetype":"venue"
},
  "geometry": {"coordinates":[-3.818928957,43.4607582092],"type":"Point"}
}