{
  "type": "Feature",
  "properties": {
    "iso:country":"ES",
    "sg:address":"Avda Doctor Fedriani, S/n",
    "sg:city":"Sevilla",
    "sg:orig_category":"Agentes, Concesionarios Y Sucursales De Veh\u00cdculos",
    "sg:phone":"+34 954 37 25 51",
    "sg:postcode":"41009",
    "sg:province":"Sevilla",
    "sg:website":"www.cocisaalcor.citroen.es",
    "wof:name":"Comercial Citroen S. A.",
    "wof:placetype":"venue"
},
  "geometry": {"coordinates":[-5.984249115,37.410369873],"type":"Point"}
}