{
  "type": "Feature",
  "properties": {
    "iso:country":"ES",
    "sg:address":"Carr Les Roses, 10",
    "sg:city":"Lleida",
    "sg:orig_category":"Fabricaci\u00d3n De Peines Y De Accesorios De Peluquer\u00cda",
    "sg:phone":"+34 973 20 05 04",
    "sg:postcode":"25001",
    "sg:province":"Lleida",
    "wof:name":"Magatzem Del Perruquer S.l.",
    "wof:placetype":"venue"
},
  "geometry": {"coordinates":[0.6414020061,41.604057312],"type":"Point"}
}