{
  "type": "Feature",
  "properties": {
    "iso:country":"ES",
    "sg:address":"Calle de Ibiza, 6",
    "sg:city":"Benidorm",
    "sg:orig_category":"Alimentaci\u00d3n General (al Por Menor)",
    "sg:phone":"+34 965 85 83 97",
    "sg:postcode":"03500",
    "sg:province":"Alicante",
    "wof:name":"Yu  Shao Jing",
    "wof:placetype":"venue"
},
  "geometry": {"coordinates":[-0.1193009987,38.5398902893],"type":"Point"}
}