{
  "type": "Feature",
  "properties": {
    "addr:full":"Calle de Moreno De Vargas, 3 Merida Badajoz 06800",
    "addr:housenumber":"3",
    "addr:postcode":"06800",
    "addr:street":"Calle De Moreno De Vargas",
    "iso:country":"ES",
    "sg:address":"Calle de Moreno De Vargas, 3",
    "sg:city":"Merida",
    "sg:orig_category":"Ropa Para Caballeros (al Por Menor)",
    "sg:phone":"+34 924 31 81 06",
    "sg:postcode":"06800",
    "sg:province":"Badajoz",
    "wof:name":"Lavado Gonzalez Juan Lino",
    "wof:placetype":"venue"
},
  "geometry": {"coordinates":[-6.3464841843,38.916053772],"type":"Point"}
}