{
  "type": "Feature",
  "properties": {
    "addr:full":"Calle de Chirama, 49 Alisios Santa Cruz De Tenerife 38109",
    "addr:housenumber":"49",
    "addr:postcode":"38109",
    "addr:street":"Calle De Chirama",
    "iso:country":"ES",
    "sg:address":"Calle de Chirama, 49",
    "sg:city":"Alisios",
    "sg:orig_category":"M\u00c9dicos: Estomatolog\u00cda",
    "sg:phone":"+34 922 62 09 18",
    "sg:postcode":"38109",
    "sg:province":"Santa Cruz De Tenerife",
    "wof:name":"Navarro Bello Maria De Los Angeles",
    "wof:placetype":"venue"
},
  "geometry": {"coordinates":[-16.2548561096,28.4698104858],"type":"Point"}
}