{
  "type": "Feature",
  "properties": {
    "addr:full":"Plaz Constitucion, 2 Badajoz Badajoz 06004",
    "addr:housenumber":"2",
    "addr:postcode":"06004",
    "addr:street":"Constitucion",
    "iso:country":"ES",
    "sg:address":"Plaz Constitucion, 2",
    "sg:city":"Badajoz",
    "sg:orig_category":"Cajas De Ahorro",
    "sg:phone":"+34 924 24 91 84",
    "sg:postcode":"06004",
    "sg:province":"Badajoz",
    "sg:website":"www.cajasur.es",
    "wof:name":"Caja De Ahorros Y Monte De Piedad De Cordoba",
    "wof:placetype":"venue"
},
  "geometry": {"coordinates":[-6.9730491638,38.8733520508],"type":"Point"}
}