{
  "type": "Feature",
  "properties": {
    "addr:full":"Calle de Empedrada, 112 Montalban De Cordoba C\u00f3rdoba 14548",
    "addr:housenumber":"112",
    "addr:postcode":"14548",
    "addr:street":"Calle De Empedrada;Co\u0301Rdoba",
    "iso:country":"ES",
    "sg:address":"Calle de Empedrada, 112",
    "sg:city":"Montalban De Cordoba",
    "sg:orig_category":"Supermercados Y Hipermercados",
    "sg:phone":"+34 957 31 08 71",
    "sg:postcode":"14548",
    "sg:province":"C\u00f3rdoba",
    "wof:name":"Montalbe\u00f1a De Alimentacion S.l.",
    "wof:placetype":"venue"
},
  "geometry": {"coordinates":[-4.7496237755,37.5807800293],"type":"Point"}
}