{
  "type": "Feature",
  "properties": {
    "iso:country":"ES",
    "sg:address":"Carrer de Ferran, 25",
    "sg:city":"Barcelona",
    "sg:orig_category":"Caf\u00c9s, Bares, Cervecer\u00cdas",
    "sg:phone":"+34 933 02 15 23",
    "sg:postcode":"08002",
    "sg:province":"Barcelona",
    "sg:website":"www.starbucks.es",
    "wof:name":"Starbuck Coffee Espa\u00f1a S.l.",
    "wof:placetype":"venue"
},
  "geometry": {"coordinates":[2.1751749516,41.3812408447],"type":"Point"}
}