{
  "type": "Feature",
  "properties": {
    "iso:country":"ES",
    "sg:address":"Rbla Jaume I, 41",
    "sg:city":"Cambrils",
    "sg:orig_category":"Inform\u00c1tica, Ofim\u00c1tica (estudios, Asesor\u00cda, Ingenier\u00cda, Formaci\u00d3n)",
    "sg:phone":"+34 977 36 05 39",
    "sg:postcode":"43850",
    "sg:province":"Tarragona",
    "wof:name":"Computer Cambrils S.l.",
    "wof:placetype":"venue"
},
  "geometry": {"coordinates":[1.0645140409,41.0668830872],"type":"Point"}
}