{
  "type": "Feature",
  "properties": {
    "addr:full":"Calle de Pozo Amarillo, 36 Salamanca Salamanca 37001",
    "addr:housenumber":"36",
    "addr:postcode":"37001",
    "addr:street":"Calle De Pozo Amarillo",
    "iso:country":"ES",
    "sg:address":"Calle de Pozo Amarillo, 36",
    "sg:city":"Salamanca",
    "sg:orig_category":"Telas Y Sedas (al Por Menor)",
    "sg:phone":"+34 923 21 50 67",
    "sg:postcode":"37001",
    "sg:province":"Salamanca",
    "wof:name":"Mulas Fernandez Jose Manuel",
    "wof:placetype":"venue"
},
  "geometry": {"coordinates":[-5.6613049507,40.9664649963],"type":"Point"}
}