{
  "type": "Feature",
  "properties": {
    "iso:country":"ES",
    "sg:address":"Calle de Pedro Muguruza, 6",
    "sg:city":"Madrid",
    "sg:orig_category":"Asociaciones Y Clubs Deportivos",
    "sg:phone":"+34 913 45 18 29",
    "sg:postcode":"28036",
    "sg:province":"Madrid",
    "wof:name":"Hob Nob S.l.",
    "wof:placetype":"venue"
},
  "geometry": {"coordinates":[-3.6860001087,40.4621047974],"type":"Point"}
}