{
  "type": "Feature",
  "properties": {
    "addr:full":"Calle de Pablo Picasso, S/n Montalban De Cordoba C\u00f3rdoba 14548",
    "addr:housenumber":"s / n",
    "addr:postcode":"14548",
    "addr:street":"Calle De Pablo Picasso;Co\u0301Rdoba",
    "iso:country":"ES",
    "sg:address":"Calle de Pablo Picasso, S/n",
    "sg:city":"Montalban De Cordoba",
    "sg:orig_category":"Transportes Por V\u00cdas Navegables",
    "sg:phone":"+34 957 31 02 92",
    "sg:postcode":"14548",
    "sg:province":"C\u00f3rdoba",
    "wof:name":"Castillero Salces Manuel",
    "wof:placetype":"venue"
},
  "geometry": {"coordinates":[-4.7513017654,37.5804824829],"type":"Point"}
}