{
  "type": "Feature",
  "properties": {
    "iso:country":"ES",
    "sg:address":"Urbanizacion El Pinar, 2",
    "sg:city":"Medina Pomar",
    "sg:orig_category":"Guarder\u00cdas",
    "sg:phone":"+34 947 19 08 38",
    "sg:postcode":"09500",
    "sg:province":"Burgos",
    "wof:name":"Guarderia Los Peque\u00d1ines",
    "wof:placetype":"venue"
},
  "geometry": {"coordinates":[-3.4830858707,42.9295463562],"type":"Point"}
}