{
  "type": "Feature",
  "properties": {
    "iso:country":"ES",
    "sg:address":"Avda Pais Valencia, 21",
    "sg:city":"Torrent",
    "sg:orig_category":"Arquitectos",
    "sg:phone":"+34 961 56 67 58",
    "sg:postcode":"46900",
    "sg:province":"Valencia",
    "wof:name":"Garces Tordera Antonio",
    "wof:placetype":"venue"
},
  "geometry": {"coordinates":[-0.4669930041,39.436000824],"type":"Point"}
}