{
  "type": "Feature",
  "properties": {
    "iso:country":"ES",
    "sg:address":"Carrer de Sant Jordi, 29",
    "sg:city":"S. Cugat Valles",
    "sg:orig_category":"Asesor\u00cda Fiscal Y Jur\u00cddica",
    "sg:phone":"+34 935 89 09 00",
    "sg:postcode":"08172",
    "sg:province":"Barcelona",
    "wof:name":"A.p.f. Sant Cugat S.l.",
    "wof:placetype":"venue"
},
  "geometry": {"coordinates":[2.0345506668,41.4955863953],"type":"Point"}
}