{
  "type": "Feature",
  "properties": {
    "addr:full":"Calle de Sierra Santos, 4 Madrid Madrid 28031",
    "addr:housenumber":"4",
    "addr:postcode":"28031",
    "addr:street":"Calle De Sierra Santos",
    "iso:country":"ES",
    "sg:address":"Calle de Sierra Santos, 4",
    "sg:city":"Madrid",
    "sg:orig_category":"Empresas De Carpinter\u00cda De Madera",
    "sg:phone":"+34 913 32 34 77",
    "sg:postcode":"28031",
    "sg:province":"Madrid",
    "wof:name":"Cristobal Pozo Lorenzo",
    "wof:placetype":"venue"
},
  "geometry": {"coordinates":[-3.6200060844,40.3737716675],"type":"Point"}
}