{
  "type": "Feature",
  "properties": {
    "addr:full":"Avda Duque De Ahumada, 15 Marbella M\u00e1laga 29600",
    "addr:housenumber":"15",
    "addr:postcode":"29600",
    "addr:street":"Avda Duque De Ahumada;Ma\u0301Laga",
    "iso:country":"ES",
    "sg:address":"Avda Duque De Ahumada, 15",
    "sg:city":"Marbella",
    "sg:orig_category":"Confecci\u00d3n De Trajes De Ba\u00d1o Y De Ropa De Playa",
    "sg:phone":"+34 952 82 56 59",
    "sg:postcode":"29600",
    "sg:province":"M\u00e1laga",
    "wof:name":"Corcia Belilty Moises",
    "wof:placetype":"venue"
},
  "geometry": {"coordinates":[-4.8892889023,36.5071983337],"type":"Point"}
}