{
  "type": "Feature",
  "properties": {
    "iso:country":"ES",
    "sg:address":"Urb Urbanova I, 13",
    "sg:city":"Urbanova",
    "sg:orig_category":"Cervecer\u00cdas",
    "sg:phone":"+34 965 18 87 49",
    "sg:postcode":"03008",
    "sg:province":"Alicante",
    "wof:name":"Cerda Mas Angel",
    "wof:placetype":"venue"
},
  "geometry": {"coordinates":[-0.5224840045,38.2840309143],"type":"Point"}
}