{
  "type": "Feature",
  "properties": {
    "addr:full":"Pg Mossen Lluis Constans, 297 Banyoles Girona 17820",
    "addr:housenumber":"297",
    "addr:postcode":"17820",
    "addr:street":"Pg Mossen Lluis Constans",
    "iso:country":"ES",
    "sg:address":"Pg Mossen Lluis Constans, 297",
    "sg:city":"Banyoles",
    "sg:orig_category":"Frutas Y Legumbres Secas (al Por Mayor)",
    "sg:phone":"+34 972 57 57 76",
    "sg:postcode":"17820",
    "sg:province":"Girona",
    "wof:name":"Ribas Robert Xavier",
    "wof:placetype":"venue"
},
  "geometry": {"coordinates":[2.7679419518,42.1116981506],"type":"Point"}
}