{
  "type": "Feature",
  "properties": {
    "addr:full":"Calle de Adelfas (de Las), 40 Alcazares Murcia 30710",
    "addr:housenumber":"40",
    "addr:postcode":"30710",
    "addr:street":"Calle De Adelfas De Las",
    "iso:country":"ES",
    "sg:address":"Calle de Adelfas (de Las), 40",
    "sg:city":"Alcazares",
    "sg:orig_category":"Propiedad Industrial: Patentes De Inventos, Marcas, Modelos, Dise\u00d1os",
    "sg:phone":"+34 968 58 27 74",
    "sg:postcode":"30710",
    "sg:province":"Murcia",
    "wof:name":"Pardo Caballero Rita Maria",
    "wof:placetype":"venue"
},
  "geometry": {"coordinates":[-0.8568655252,37.7404174805],"type":"Point"}
}