{
  "type": "Feature",
  "properties": {
    "iso:country":"ES",
    "sg:address":"Calle de Hospital De La Misericordia, 5",
    "sg:city":"Ciudad Real",
    "sg:orig_category":"Promotores Constructores",
    "sg:phone":"+34 926 22 82 11",
    "sg:postcode":"13003",
    "sg:province":"Ciudad Real",
    "wof:name":"Asociacion De Profesionales Por La Integracion En Castilla La Mancha",
    "wof:placetype":"venue"
},
  "geometry": {"coordinates":[-3.9258463383,38.9941482544],"type":"Point"}
}