{
  "type": "Feature",
  "properties": {
    "addr:full":"Plaz Constitucion (de La), 2 Pezuela Torres Madrid 28812",
    "addr:housenumber":"2",
    "addr:postcode":"28812",
    "addr:street":"Pezuela Torres",
    "iso:country":"ES",
    "sg:address":"Plaz Constitucion (de La), 2",
    "sg:city":"Pezuela Torres",
    "sg:classifiers":[
        {
            "category":"Taxi",
            "type":"Transportation"
        }
    ],
    "sg:phone":"+34 918 86 91 03",
    "sg:postcode":"28812",
    "sg:province":"Madrid",
    "wof:name":"Castillo Paez Andrea",
    "wof:placetype":"venue"
},
  "geometry": {"coordinates":[-3.2993910313,40.4177055359],"type":"Point"}
}