{
  "type": "Feature",
  "properties": {
    "addr:full":"Carrer de Pardo, 55 Barcelona Barcelona 08016",
    "addr:housenumber":"55",
    "addr:postcode":"08016",
    "addr:street":"Carrer De Pardo",
    "iso:country":"ES",
    "sg:address":"Carrer de Pardo, 55",
    "sg:city":"Barcelona",
    "sg:orig_category":"Electricidad Veh\u00cdculo",
    "sg:phone":"+34 933 46 18 04",
    "sg:postcode":"08016",
    "sg:province":"Barcelona",
    "wof:name":"Montilla Martinez Antonio",
    "wof:placetype":"venue"
},
  "geometry": {"coordinates":[2.1823949814,41.4292068481],"type":"Point"}
}