{
  "type": "Feature",
  "properties": {
    "addr:full":"Ctra Gral, 182 Molledo Cantabria 39430",
    "addr:housenumber":"182",
    "addr:postcode":"39430",
    "addr:street":"Ctra Gral",
    "iso:country":"ES",
    "sg:address":"Ctra Gral, 182",
    "sg:city":"Molledo",
    "sg:orig_category":"Construcciones Met\u00c1licas",
    "sg:phone":"+34 942 82 80 80",
    "sg:postcode":"39430",
    "sg:province":"Cantabria",
    "wof:name":"Construcciones Metalicas Marcano S.c.",
    "wof:placetype":"venue"
},
  "geometry": {"coordinates":[-4.0418391228,43.1512908936],"type":"Point"}
}