{
  "type": "Feature",
  "properties": {
    "iso:country":"ES",
    "sg:address":"Ctra De Ba\u00f1os (p I La Zarzuela), 5",
    "sg:city":"Linares",
    "sg:orig_category":"Conservas De Pescados Y Salazones Mar\u00cdtimos (fabricaci\u00d3n, Al Por Mayor)",
    "sg:phone":"+34 953 65 28 53",
    "sg:postcode":"23700",
    "sg:province":"Ja\u00e9n",
    "wof:name":"Conservas Friscos S.a.",
    "wof:placetype":"venue"
},
  "geometry": {"coordinates":[-3.6358809471,38.0944404602],"type":"Point"}
}