{
  "type": "Feature",
  "properties": {
    "addr:full":"Ctra. Palma-arta, Km. 0048,0 Manacor Islas Baleares 07500",
    "addr:postcode":"07500",
    "addr:street":"Ctra. Palma-Arta Km. 0048,0",
    "iso:country":"ES",
    "sg:address":"Ctra. Palma-arta, Km. 0048,0",
    "sg:city":"Manacor",
    "sg:orig_category":"Negocio De Madera",
    "sg:phone":"+34 971 84 37 06",
    "sg:postcode":"07500",
    "sg:province":"Islas Baleares",
    "wof:name":"Cooperativa De Fabricantes Reunidos De Manacor",
    "wof:placetype":"venue"
},
  "geometry": {"coordinates":[3.1796910763,39.573474884],"type":"Point"}
}