{
  "type": "Feature",
  "properties": {
    "addr:full":"Calle de Santa Eulalia, 18 Merida Badajoz 06800",
    "addr:housenumber":"18",
    "addr:postcode":"06800",
    "addr:street":"Calle De Santa Eulalia",
    "iso:country":"ES",
    "sg:address":"Calle de Santa Eulalia, 18",
    "sg:city":"Merida",
    "sg:orig_category":"Farmacias",
    "sg:phone":"+34 924 31 16 05",
    "sg:postcode":"06800",
    "sg:province":"Badajoz",
    "wof:name":"Gomez-pantoja Cumplido Jose Manuel",
    "wof:placetype":"venue"
},
  "geometry": {"coordinates":[-6.3448638916,38.9166564941],"type":"Point"}
}