{
  "type": "Feature",
  "properties": {
    "addr:full":"Avda Virgen De Gracia, 66 Caudete Albacete 02660",
    "addr:housenumber":"66",
    "addr:postcode":"02660",
    "addr:street":"Avda Virgen De Gracia",
    "iso:country":"ES",
    "sg:address":"Avda Virgen De Gracia, 66",
    "sg:city":"Caudete",
    "sg:orig_category":"Centros De Educaci\u00d3n Especial",
    "sg:phone":"+34 965 82 76 41",
    "sg:postcode":"02660",
    "sg:province":"Albacete",
    "wof:name":"Colegio Publico Alcazar Y Serrano",
    "wof:placetype":"venue"
},
  "geometry": {"coordinates":[-0.9842910171,38.700969696],"type":"Point"}
}