{
  "type": "Feature",
  "properties": {
    "addr:full":"Avda San Jose, 146 Zaragoza Zaragoza 50007",
    "addr:housenumber":"146",
    "addr:postcode":"50007",
    "addr:street":"Avda San Jose",
    "iso:country":"ES",
    "sg:address":"Avda San Jose, 146",
    "sg:city":"Zaragoza",
    "sg:orig_category":"Mercer\u00cda, Lencer\u00cda (al Por Menor)",
    "sg:phone":"+34 976 27 24 71",
    "sg:postcode":"50007",
    "sg:province":"Zaragoza",
    "wof:name":"Diaz-lombar S.cv.",
    "wof:placetype":"venue"
},
  "geometry": {"coordinates":[-0.8778430223,41.636920929],"type":"Point"}
}