{
  "type": "Feature",
  "properties": {
    "addr:full":"Carrer de Rocafort, 104 Barcelona Barcelona 08015",
    "addr:housenumber":"104",
    "addr:postcode":"08015",
    "addr:street":"Carrer De Rocafort",
    "iso:country":"ES",
    "sg:address":"Carrer de Rocafort, 104",
    "sg:city":"Barcelona",
    "sg:orig_category":"Asesor\u00cda De Formaci\u00d3n Y Gesti\u00d3n De Personal",
    "sg:phone":"+34 934 23 83 04",
    "sg:postcode":"08015",
    "sg:province":"Barcelona",
    "wof:name":"Agil Assessorament S.c.c.l.",
    "wof:placetype":"venue"
},
  "geometry": {"coordinates":[2.152053833,41.3802757263],"type":"Point"}
}