{
  "type": "Feature",
  "properties": {
    "addr:full":"Avda Raco De La Marquesa, 4 Sant Mateu Castell\u00f3n 12170",
    "addr:housenumber":"4",
    "addr:postcode":"12170",
    "addr:street":"Avda Raco De La Marquesa",
    "iso:country":"ES",
    "sg:address":"Avda Raco De La Marquesa, 4",
    "sg:city":"Sant Mateu",
    "sg:orig_category":"Discotecas Y Salas De Baile",
    "sg:phone":"+34 964 41 65 10",
    "sg:postcode":"12170",
    "sg:province":"Castell\u00f3n",
    "wof:name":"Dance Jocky S.l.",
    "wof:placetype":"venue"
},
  "geometry": {"coordinates":[0.1785899997,40.4668502808],"type":"Point"}
}