{
  "type": "Feature",
  "properties": {
    "addr:full":"Calle de Matias Perello, 52 Valencia Valencia 46005",
    "addr:housenumber":"52",
    "addr:postcode":"46005",
    "addr:street":"Calle De Matias Perello",
    "iso:country":"ES",
    "sg:address":"Calle de Matias Perello, 52",
    "sg:city":"Valencia",
    "sg:orig_category":"Restaurantes",
    "sg:phone":"+34 963 73 41 37",
    "sg:postcode":"46005",
    "sg:province":"Valencia",
    "wof:name":"Compa\u00f1ia General De Hosteleria Bicego S.l.",
    "wof:placetype":"venue"
},
  "geometry": {"coordinates":[-0.3654739857,39.4622993469],"type":"Point"}
}