{
  "type": "Feature",
  "properties": {
    "addr:full":"Calle de Sanclemente, 25 Zaragoza Zaragoza 50001",
    "addr:housenumber":"25",
    "addr:postcode":"50001",
    "addr:street":"Calle De Sanclemente",
    "iso:country":"ES",
    "sg:address":"Calle de Sanclemente, 25",
    "sg:city":"Zaragoza",
    "sg:orig_category":"Pe\u00d1as Y Asociaciones Varias",
    "sg:phone":"+34 976 30 27 55",
    "sg:postcode":"50001",
    "sg:province":"Zaragoza",
    "sg:website":"www.pydum.com",
    "wof:name":"Proyectos Y Desarrollos Urbanos Man Sl",
    "wof:placetype":"venue"
},
  "geometry": {"coordinates":[-0.8800089955,41.6492385864],"type":"Point"}
}