{
  "type": "Feature",
  "properties": {
    "iso:country":"ES",
    "sg:address":"Calle de Pedro Martinez Gutierrez, 24",
    "sg:city":"Albacete",
    "sg:orig_category":"Molduras, Junquillos, Listones Y Molduras Perforadas",
    "sg:phone":"+34 967 50 41 19",
    "sg:postcode":"02004",
    "sg:province":"Albacete",
    "wof:name":"Maeso Cerdan S.l.",
    "wof:placetype":"venue"
},
  "geometry": {"coordinates":[-1.861379981,38.9939346313],"type":"Point"}
}