{
  "type": "Feature",
  "properties": {
    "addr:full":"Poli Poliviso, S/n Viso Del Alcor Sevilla 41520",
    "addr:housenumber":"s",
    "addr:postcode":"41520",
    "addr:street":"/ N",
    "iso:country":"ES",
    "sg:address":"Poli Poliviso, S/n",
    "sg:city":"Viso Del Alcor",
    "sg:orig_category":"Deportes Y Ocio: Art\u00cdculos Y Ropas (al Por Menor Y Accesorios)",
    "sg:phone":"+34 955 94 61 99",
    "sg:postcode":"41520",
    "sg:province":"Sevilla",
    "wof:name":"Hermanos Martinez Morillo S.l.",
    "wof:placetype":"venue"
},
  "geometry": {"coordinates":[-5.7141880989,37.3890113831],"type":"Point"}
}