{
  "type": "Feature",
  "properties": {
    "addr:full":"Rua Sanchez Freire (de), 79 Santiago De Compostela La Coru\u00f1a 15706",
    "addr:housenumber":"79",
    "addr:postcode":"15706",
    "addr:street":"Rua Sanchez Freire De;Corun\u0303A",
    "iso:country":"ES",
    "sg:address":"Rua Sanchez Freire (de), 79",
    "sg:city":"Santiago De Compostela",
    "sg:orig_category":"Estancos",
    "sg:phone":"+34 981 52 10 34",
    "sg:postcode":"15706",
    "sg:province":"La Coru\u00f1a",
    "wof:name":"Marti Fernandez Alfredo",
    "wof:placetype":"venue"
},
  "geometry": {"coordinates":[-8.5552921295,42.8644790649],"type":"Point"}
}