{
  "type": "Feature",
  "properties": {
    "addr:full":"Carrer de Montal, 7 Arenys Mar Barcelona 08350",
    "addr:housenumber":"7",
    "addr:postcode":"08350",
    "addr:street":"Carrer De Montal;Mar Barcelona",
    "iso:country":"ES",
    "sg:address":"Carrer de Montal, 7",
    "sg:city":"Arenys Mar",
    "sg:orig_category":"Empresarios Y Productoras De Espect\u00c1culos",
    "sg:phone":"+34 937 92 01 25",
    "sg:postcode":"08350",
    "sg:province":"Barcelona",
    "wof:name":"Grup Espectacles Frank S.c.p",
    "wof:placetype":"venue"
},
  "geometry": {"coordinates":[2.5441749096,41.586894989],"type":"Point"}
}