{
  "type": "Feature",
  "properties": {
    "addr:full":"Av Gabriel Roca, 18 Palma Islas Baleares 07014",
    "addr:housenumber":"18",
    "addr:postcode":"07014",
    "addr:street":"Av Gabriel Roca",
    "iso:country":"ES",
    "sg:address":"Av Gabriel Roca, 18",
    "sg:city":"Palma",
    "sg:orig_category":"Ingeniero",
    "sg:phone":"+34 971 28 74 92",
    "sg:postcode":"07014",
    "sg:province":"Islas Baleares",
    "wof:name":"Serviticket S.a.",
    "wof:placetype":"venue"
},
  "geometry": {"coordinates":[2.6289050579,39.5654296875],"type":"Point"}
}