{
  "type": "Feature",
  "properties": {
    "iso:country":"ES",
    "sg:address":"Barrena Kalea, 16",
    "sg:city":"Eibar",
    "sg:orig_category":"T\u00c9cnicos Veterinarios",
    "sg:phone":"+34 943 12 19 86",
    "sg:postcode":"20600",
    "sg:province":"Guip\u00f9zcoa",
    "wof:name":"Guisasola Sangroniz Andoni",
    "wof:placetype":"venue"
},
  "geometry": {"coordinates":[-2.459831953,43.1884307861],"type":"Point"}
}