{
  "type": "Feature",
  "properties": {
    "iso:country":"ES",
    "sg:address":"Calle de Padre Cantero, 52",
    "sg:city":"Campanario",
    "sg:orig_category":"Agentes, Concesionarios Y Sucursales De Veh\u00cdculos",
    "sg:phone":"+34 924 83 13 26",
    "sg:postcode":"06460",
    "sg:province":"Badajoz",
    "wof:name":"Talleres Y Autos Sevilla S.l.",
    "wof:placetype":"venue"
},
  "geometry": {"coordinates":[-5.6193823814,38.8588409424],"type":"Point"}
}