{
  "type": "Feature",
  "properties": {
    "addr:full":"Carrer de Corsega, 176 Barcelona Barcelona 08036",
    "addr:housenumber":"176",
    "addr:postcode":"08036",
    "addr:street":"Carrer De Corsega",
    "iso:country":"ES",
    "sg:address":"Carrer de Corsega, 176",
    "sg:city":"Barcelona",
    "sg:orig_category":"Traductores",
    "sg:phone":"+34 933 63 18 64",
    "sg:postcode":"08036",
    "sg:province":"Barcelona",
    "sg:website":"www.ilustrationstock.com",
    "wof:name":"Ilustration Stock Scp",
    "wof:placetype":"venue"
},
  "geometry": {"coordinates":[2.1501150131,41.3893966675],"type":"Point"}
}