{
  "type": "Feature",
  "properties": {
    "addr:full":"Calle de Agua, 28 Villarta Cuenca 16280",
    "addr:housenumber":"28",
    "addr:postcode":"16280",
    "addr:street":"Calle De Agua",
    "iso:country":"ES",
    "sg:address":"Calle de Agua, 28",
    "sg:city":"Villarta",
    "sg:orig_category":"Mec\u00c1nico Del Autom\u00d3vil",
    "sg:phone":"+34 962 18 92 30",
    "sg:postcode":"16280",
    "sg:province":"Cuenca",
    "wof:name":"Fernandez Garcia Miguel",
    "wof:placetype":"venue"
},
  "geometry": {"coordinates":[-1.6498138905,39.4419136047],"type":"Point"}
}