{
  "type": "Feature",
  "properties": {
    "iso:country":"ES",
    "sg:address":"Calle de Fuente Nueva (sp), S/n",
    "sg:city":"San Pedro Alcantara",
    "sg:orig_category":"Jardiner\u00cdas, Vegetales, Art\u00cdculos De Jardiner\u00cda (al Por Menor)",
    "sg:phone":"+34 952 78 92 55",
    "sg:postcode":"29670",
    "sg:province":"M\u00e1laga",
    "wof:name":"Ecological Garden S.l.l.",
    "wof:placetype":"venue"
},
  "geometry": {"coordinates":[-4.9891839027,36.4912452698],"type":"Point"}
}