{
  "type": "Feature",
  "properties": {
    "addr:full":"Calle de Alcalde Parrondo, 1 Pola De Siero Asturias 33510",
    "addr:housenumber":"1",
    "addr:postcode":"33510",
    "addr:street":"Calle De Alcalde Parrondo",
    "iso:country":"ES",
    "sg:address":"Calle de Alcalde Parrondo, 1",
    "sg:city":"Pola De Siero",
    "sg:orig_category":"Fisioterapia",
    "sg:phone":"+34 985 72 01 43",
    "sg:postcode":"33510",
    "sg:province":"Asturias",
    "wof:name":"Guiraldo Blas Ignacio",
    "wof:placetype":"venue"
},
  "geometry": {"coordinates":[-5.6612157822,43.3913383484],"type":"Point"}
}