{
  "type": "Feature",
  "properties": {
    "iso:country":"ES",
    "sg:address":"Ctra Almazora/grao Cs A Termino Almazora, Km. 0001,8",
    "sg:city":"Grao",
    "sg:orig_category":"Acondicionamiento, Mantenimiento De Jardines Y Parques",
    "sg:phone":"+34 964 28 54 09",
    "sg:postcode":"12100",
    "sg:province":"Castell\u00f3n",
    "wof:name":"Vicmar Garden S.l.",
    "wof:placetype":"venue"
},
  "geometry": {"coordinates":[0.0176999997,39.9888801575],"type":"Point"}
}