{
  "type": "Feature",
  "properties": {
    "addr:full":"Carrer de Sant Antoni Maria Claret, 124 Barcelona Barcelona 08025",
    "addr:housenumber":"124",
    "addr:postcode":"08025",
    "addr:street":"Carrer De Sant Antoni Maria Claret",
    "iso:country":"ES",
    "sg:address":"Carrer de Sant Antoni Maria Claret, 124",
    "sg:city":"Barcelona",
    "sg:orig_category":"Asesor\u00cda Sobre Comunicaci\u00d3n De Empresas",
    "sg:phone":"+34 934 50 30 35",
    "sg:postcode":"08025",
    "sg:province":"Barcelona",
    "wof:name":"Agesem Assessorament I Gestio Empresarial S. L.",
    "wof:placetype":"venue"
},
  "geometry": {"coordinates":[2.0835642815,41.3691749573],"type":"Point"}
}