{
  "type": "Feature",
  "properties": {
    "iso:country":"ES",
    "sg:address":"Calle de Vitoria, 55",
    "sg:city":"Burgos",
    "sg:orig_category":"Papeler\u00cdas, Librer\u00cdas",
    "sg:phone":"+34 947 27 19 01",
    "sg:postcode":"09004",
    "sg:province":"Burgos",
    "wof:name":"Comercial Sagredo S.a.",
    "wof:placetype":"venue"
},
  "geometry": {"coordinates":[-3.686909914,42.3439369202],"type":"Point"}
}