{
  "type": "Feature",
  "properties": {
    "addr:full":"Carr Mossen Cinto Verdaguer, 4 Alcarras Lleida 25180",
    "addr:housenumber":"4",
    "addr:postcode":"25180",
    "addr:street":"Carr Mossen Cinto Verdaguer",
    "iso:country":"ES",
    "sg:address":"Carr Mossen Cinto Verdaguer, 4",
    "sg:city":"Alcarras",
    "sg:orig_category":"Supermercados Y Hipermercados",
    "sg:phone":"+34 973 79 10 40",
    "sg:postcode":"25180",
    "sg:province":"Lleida",
    "wof:name":"Elhammar  Mohammed",
    "wof:placetype":"venue"
},
  "geometry": {"coordinates":[0.5226550102,41.5623664856],"type":"Point"}
}