{
  "type": "Feature",
  "properties": {
    "addr:full":"Av Constitucio (la), 31 Banyeres Mariola Alicante 03450",
    "addr:housenumber":"31",
    "addr:postcode":"03450",
    "addr:street":"Av Constitucio La",
    "iso:country":"ES",
    "sg:address":"Av Constitucio (la), 31",
    "sg:city":"Banyeres Mariola",
    "sg:orig_category":"Promotores Constructores",
    "sg:phone":"+34 965 56 73 41",
    "sg:postcode":"03450",
    "sg:province":"Alicante",
    "wof:name":"Pedro Clemente Sl",
    "wof:placetype":"venue"
},
  "geometry": {"coordinates":[-0.6612250209,38.7161712646],"type":"Point"}
}