{
  "type": "Feature",
  "properties": {
    "iso:country":"ES",
    "sg:address":"Avda Constitucion (la), 27",
    "sg:city":"Sevilla",
    "sg:orig_category":"Asilos De Ancianos. Centros Privados",
    "sg:phone":"+34 954 50 21 74",
    "sg:postcode":"41004",
    "sg:province":"Sevilla",
    "wof:name":"Almahe Puerta Jerez S.l.",
    "wof:placetype":"venue"
},
  "geometry": {"coordinates":[-5.9934468269,37.383430481],"type":"Point"}
}