{
  "type": "Feature",
  "properties": {
    "iso:country":"ES",
    "sg:address":"Av. Catalunya, 3",
    "sg:city":"S. Fost Campsentelles",
    "sg:orig_category":"Molduras, Junquillos, Listones Y Molduras Perforadas",
    "sg:phone":"+34 935 70 55 48",
    "sg:postcode":"08105",
    "sg:province":"Barcelona",
    "wof:name":"Font Torrents Rosa",
    "wof:placetype":"venue"
},
  "geometry": {"coordinates":[2.229872942,41.5234375],"type":"Point"}
}