{
  "type": "Feature",
  "properties": {
    "addr:full":"Avda Bilbao, 49 Torrelavega Cantabria 39300",
    "addr:housenumber":"49",
    "addr:postcode":"39300",
    "addr:street":"Avda Bilbao",
    "iso:country":"ES",
    "sg:address":"Avda Bilbao, 49",
    "sg:city":"Torrelavega",
    "sg:orig_category":"Agentes, Concesionarios Y Sucursales De Veh\u00cdculos",
    "sg:phone":"+34 942 80 71 81",
    "sg:postcode":"39300",
    "sg:province":"Cantabria",
    "wof:name":"Car Mustang S.l.",
    "wof:placetype":"venue"
},
  "geometry": {"coordinates":[-4.0380649567,43.3453598022],"type":"Point"}
}