{
  "type": "Feature",
  "properties": {
    "addr:full":"Calle de Carpinteria, 12 Madrid Madrid 28037",
    "addr:housenumber":"12",
    "addr:postcode":"madrid;28037",
    "addr:street":"Calle De Carpinteria",
    "iso:country":"ES",
    "sg:address":"Calle de Carpinteria, 12",
    "sg:city":"Madrid",
    "sg:orig_category":"Asociaciones Humanitarias, De Cooperaci\u00d3n, De Acci\u00d3n Social",
    "sg:phone":"+34 913 24 09 54",
    "sg:postcode":"28037",
    "sg:province":"Madrid",
    "wof:name":"F.injucam",
    "wof:placetype":"venue"
},
  "geometry": {"coordinates":[-3.6216897964,40.4259414673],"type":"Point"}
}