{
  "type": "Feature",
  "properties": {
    "iso:country":"ES",
    "sg:address":"Calle de Prior, 6",
    "sg:city":"Salamanca",
    "sg:orig_category":"\u00d3ptica: Instrumentos (fabricaci\u00d3n)",
    "sg:phone":"+34 923 26 89 93",
    "sg:postcode":"37002",
    "sg:province":"Salamanca",
    "wof:name":"Asensio Pascual Maria Paloma",
    "wof:placetype":"venue"
},
  "geometry": {"coordinates":[-5.6650042534,40.9649124146],"type":"Point"}
}