{
  "type": "Feature",
  "properties": {
    "addr:full":"Calle de Jose Lopez Oca\u00d1a, 7 Aviles Asturias 33401",
    "addr:housenumber":"7",
    "addr:postcode":"33401",
    "addr:street":"Calle De Jose;Ocan\u0303A",
    "iso:country":"ES",
    "sg:address":"Calle de Jose Lopez Oca\u00d1a, 7",
    "sg:city":"Aviles",
    "sg:orig_category":"Institutos De Belleza",
    "sg:phone":"+34 985 56 37 81",
    "sg:postcode":"33401",
    "sg:province":"Asturias",
    "wof:name":"Perez De La Rosa Jesus",
    "wof:placetype":"venue"
},
  "geometry": {"coordinates":[-5.9268059731,43.5580406189],"type":"Point"}
}