{
  "type": "Feature",
  "properties": {
    "iso:country":"ES",
    "sg:address":"Trva Colombia, 5",
    "sg:city":"Toledo",
    "sg:orig_category":"Ropa Para Ni\u00d1os (al Por Menor)",
    "sg:phone":"+34 925 25 56 49",
    "sg:postcode":"45004",
    "sg:province":"Toledo",
    "sg:website":"www.neckandneck.com",
    "wof:name":"Roig Mateos S.l.",
    "wof:placetype":"venue"
},
  "geometry": {"coordinates":[-4.0316691399,39.8676567078],"type":"Point"}
}