{
  "type": "Feature",
  "properties": {
    "iso:country":"ES",
    "sg:address":"Avda Pablo Iglesias, 49",
    "sg:city":"Gijon",
    "sg:orig_category":"Institutos De Belleza",
    "sg:phone":"+34 985 37 27 80",
    "sg:postcode":"33205",
    "sg:province":"Asturias",
    "wof:name":"Alonso Garcia Yolanda",
    "wof:placetype":"venue"
},
  "geometry": {"coordinates":[-5.6543097496,43.5356330872],"type":"Point"}
}