{
  "type": "Feature",
  "properties": {
    "iso:country":"ES",
    "sg:address":"Pol Barrios, S/n",
    "sg:city":"Rojales",
    "sg:orig_category":"Barnizadores",
    "sg:phone":"+34 966 79 23 93",
    "sg:postcode":"03170",
    "sg:province":"Alicante",
    "wof:name":"Ruiz Ferris Angel",
    "wof:placetype":"venue"
},
  "geometry": {"coordinates":[-0.6972389817,38.0653991699],"type":"Point"}
}