{
  "type": "Feature",
  "properties": {
    "addr:full":"Calle de Fuencarral, 112 Madrid Madrid 28010",
    "addr:housenumber":"112",
    "addr:postcode":"28010",
    "addr:street":"Calle De Fuencarral",
    "iso:country":"ES",
    "sg:address":"Calle de Fuencarral, 112",
    "sg:city":"Madrid",
    "sg:orig_category":"Parques De Atracciones Y Centros De Esparcimiento",
    "sg:phone":"+34 914 48 46 65",
    "sg:postcode":"28010",
    "sg:province":"Madrid",
    "wof:name":"Recreativos Electronicos S.a.",
    "wof:placetype":"venue"
},
  "geometry": {"coordinates":[-3.7023990154,40.4295272827],"type":"Point"}
}