{
  "type": "Feature",
  "properties": {
    "iso:country":"ES",
    "sg:address":"Avda Mantecado (del), 51",
    "sg:city":"Estepa",
    "sg:orig_category":"Aluminio Y Aleaciones (producci\u00d3n, Transformaci\u00d3n, Negocio)",
    "sg:phone":"+34 954 82 07 04",
    "sg:postcode":"41560",
    "sg:province":"Sevilla",
    "wof:name":"Proveedora De Aluminio Estepa S.l.",
    "wof:placetype":"venue"
},
  "geometry": {"coordinates":[-4.8838977814,37.2937393188],"type":"Point"}
}