{
  "type": "Feature",
  "properties": {
    "addr:full":"Calle de Santo (el), 29 Villamartin C\u00e1diz 11650",
    "addr:housenumber":"29",
    "addr:postcode":"11650",
    "addr:street":"Calle De Santo El;Ca\u0301Diz",
    "iso:country":"ES",
    "sg:address":"Calle de Santo (el), 29",
    "sg:city":"Villamartin",
    "sg:orig_category":"Producci\u00d3n, Distribuci\u00d3n De Gas Butano Y Propano",
    "sg:phone":"+34 956 73 04 08",
    "sg:postcode":"11650",
    "sg:province":"C\u00e1diz",
    "wof:name":"Mogugas S.l.",
    "wof:placetype":"venue"
},
  "geometry": {"coordinates":[-5.6350450516,36.8572502136],"type":"Point"}
}