{
  "type": "Feature",
  "properties": {
    "iso:country":"ES",
    "sg:address":"Rond Segovia, 7",
    "sg:city":"Madrid",
    "sg:orig_category":"Asesor\u00cda Sobre Comunicaci\u00d3n De Empresas",
    "sg:phone":"+34 913 66 55 99",
    "sg:postcode":"28005",
    "sg:province":"Madrid",
    "wof:name":"Asesoria Setem S. L.",
    "wof:placetype":"venue"
},
  "geometry": {"coordinates":[-3.7175045013,40.4126472473],"type":"Point"}
}