{
  "type": "Feature",
  "properties": {
    "addr:full":"Calle de Platino, 59 Illescas Toledo 45200",
    "addr:housenumber":"59",
    "addr:postcode":"45200",
    "addr:street":"Calle De Platino",
    "iso:country":"ES",
    "sg:address":"Calle de Platino, 59",
    "sg:city":"Illescas",
    "sg:orig_category":"Metales (labores, Pulido)",
    "sg:phone":"+34 925 51 21 61",
    "sg:postcode":"45200",
    "sg:province":"Toledo",
    "wof:name":"Perficort Toledo S.l.",
    "wof:placetype":"venue"
},
  "geometry": {"coordinates":[-3.8528740406,40.116104126],"type":"Point"}
}