{
  "type": "Feature",
  "properties": {
    "iso:country":"ES",
    "sg:address":"Calle de Norte (del) (madrona), 4",
    "sg:city":"Madrona",
    "sg:orig_category":"Marketing Telef\u00d3nico",
    "sg:phone":"+34 921 48 52 39",
    "sg:postcode":"40154",
    "sg:province":"Segovia",
    "wof:name":"Moreno Rincon Ignacio",
    "wof:placetype":"venue"
},
  "geometry": {"coordinates":[-4.1698060036,40.898059845],"type":"Point"}
}