{
  "type": "Feature",
  "properties": {
    "addr:full":"Carrer de Menorca, 20 S. Celoni Barcelona 08470",
    "addr:housenumber":"20",
    "addr:postcode":"08470",
    "addr:street":"Carrer De Menorca;S. Celoni Barcelona",
    "iso:country":"ES",
    "sg:address":"Carrer de Menorca, 20",
    "sg:city":"S. Celoni",
    "sg:orig_category":"Fabricaci\u00d3n De Ventanas",
    "sg:phone":"+34 938 67 19 05",
    "sg:postcode":"08470",
    "sg:province":"Barcelona",
    "wof:name":"Lopez Pujolas Francisco",
    "wof:placetype":"venue"
},
  "geometry": {"coordinates":[2.4970960617,41.6898155212],"type":"Point"}
}