{
  "type": "Feature",
  "properties": {
    "iso:country":"ES",
    "sg:address":"Carrer de Alta Cortada, 25",
    "sg:city":"Manlleu",
    "sg:orig_category":"Tintes (fabricaci\u00d3n, Al Por Mayor)",
    "sg:phone":"+34 938 50 67 65",
    "sg:postcode":"08560",
    "sg:province":"Barcelona",
    "wof:name":"Doblas Martin Carlos Jose",
    "wof:placetype":"venue"
},
  "geometry": {"coordinates":[2.2819650173,42.0005950928],"type":"Point"}
}