{
  "type": "Feature",
  "properties": {
    "addr:full":"Ctra Alcantarilla, 346 Generala Murcia 30167",
    "addr:housenumber":"346",
    "addr:postcode":"30167",
    "addr:street":"Ctra Alcantarilla;Generala Murcia",
    "iso:country":"ES",
    "sg:address":"Ctra Alcantarilla, 346",
    "sg:city":"Generala",
    "sg:orig_category":"Piedra, Vidrio, Cer\u00c1mica Y Porcelana",
    "sg:phone":"+34 968 35 13 78",
    "sg:postcode":"30167",
    "sg:province":"Murcia",
    "wof:name":"Procemur S.l.",
    "wof:placetype":"venue"
},
  "geometry": {"coordinates":[-1.1818890572,37.9727287292],"type":"Point"}
}