{
  "type": "Feature",
  "properties": {
    "iso:country":"ES",
    "sg:address":"Av Catalunya, 33",
    "sg:city":"Puigcerda",
    "sg:orig_category":"Electricidad: Instaladores",
    "sg:phone":"+34 972 14 06 78",
    "sg:postcode":"17520",
    "sg:province":"Girona",
    "wof:name":"Tecnica Industrial Del Bergueda S. A.",
    "wof:placetype":"venue"
},
  "geometry": {"coordinates":[1.9294840097,42.4293937683],"type":"Point"}
}