{
  "type": "Feature",
  "properties": {
    "iso:country":"ES",
    "sg:address":"Calle de Bailen, 2",
    "sg:city":"Valladolid",
    "sg:orig_category":"M\u00c9dicos: Otorrinolaringolog\u00cda",
    "sg:phone":"+34 983 30 31 70",
    "sg:postcode":"47004",
    "sg:province":"Valladolid",
    "wof:name":"Freijanes Valdes Jose Luis",
    "wof:placetype":"venue"
},
  "geometry": {"coordinates":[-4.725924015,41.6461791992],"type":"Point"}
}