{
  "type": "Feature",
  "properties": {
    "iso:country":"ES",
    "sg:address":"Carrer de Providencia, 129",
    "sg:city":"Barcelona",
    "sg:orig_category":"Empresarios",
    "sg:phone":"+34 932 84 62 24",
    "sg:postcode":"08024",
    "sg:province":"Barcelona",
    "wof:name":"Fundacio Privada Fontanilles",
    "wof:placetype":"venue"
},
  "geometry": {"coordinates":[2.1620559692,41.4096717834],"type":"Point"}
}