{
  "type": "Feature",
  "properties": {
    "iso:country":"ES",
    "sg:address":"Carrer de Doctor Ramon Solanich I Riera, 13",
    "sg:city":"Hospitalet Llobregat",
    "sg:orig_category":"Guarder\u00cdas",
    "sg:phone":"+34 933 33 72 61",
    "sg:postcode":"08905",
    "sg:province":"Barcelona",
    "wof:name":"Escarp Pardell Rosa",
    "wof:placetype":"venue"
},
  "geometry": {"coordinates":[2.1083929539,41.374168396],"type":"Point"}
}