{
  "type": "Feature",
  "properties": {
    "addr:full":"Pase Arco De Ladrillo, 81 Valladolid Valladolid 47008",
    "addr:housenumber":"81",
    "addr:postcode":"47008",
    "addr:street":"Ladrillo",
    "iso:country":"ES",
    "sg:address":"Pase Arco De Ladrillo, 81",
    "sg:city":"Valladolid",
    "sg:orig_category":"Alimentaci\u00d3n General (al Por Menor)",
    "sg:phone":"+34 983 27 09 46",
    "sg:postcode":"47008",
    "sg:province":"Valladolid",
    "wof:name":"Rosa Del Barrio Jesus De La",
    "wof:placetype":"venue"
},
  "geometry": {"coordinates":[-4.7280220985,41.6315116882],"type":"Point"}
}