{
  "type": "Feature",
  "properties": {
    "addr:full":"Carrer de Fusteria, 10 Barcelona Barcelona 08002",
    "addr:housenumber":"10",
    "addr:postcode":"08002",
    "addr:street":"Carrer De Fusteria",
    "iso:country":"ES",
    "sg:address":"Carrer de Fusteria, 10",
    "sg:city":"Barcelona",
    "sg:orig_category":"Alimentaci\u00d3n General (al Por Menor)",
    "sg:phone":"+34 933 10 43 85",
    "sg:postcode":"08002",
    "sg:province":"Barcelona",
    "wof:name":"Mehmood Bhatti Mohammed",
    "wof:placetype":"venue"
},
  "geometry": {"coordinates":[2.1809639931,41.3812294006],"type":"Point"}
}