{
  "type": "Feature",
  "properties": {
    "iso:country":"ES",
    "sg:address":"Calle de Juderia Vieja (la), 12",
    "sg:city":"Segovia",
    "sg:orig_category":"Librer\u00cdas",
    "sg:phone":"+34 921 46 14 26",
    "sg:postcode":"40001",
    "sg:province":"Segovia",
    "wof:name":"Sefarad Certeza S.l.",
    "wof:placetype":"venue"
},
  "geometry": {"coordinates":[-4.1248149872,40.9496459961],"type":"Point"}
}