{
  "type": "Feature",
  "properties": {
    "iso:country":"ES",
    "sg:address":"Cami Sant Carles, 11",
    "sg:city":"Port D'andratx",
    "sg:orig_category":"Inmobiliaria (agencias)",
    "sg:phone":"+34 971 67 43 40",
    "sg:postcode":"07157",
    "sg:province":"Islas Baleares",
    "wof:name":"Barcelo Porcel Rosa",
    "wof:placetype":"venue"
},
  "geometry": {"coordinates":[2.3838438988,39.5413360596],"type":"Point"}
}