{
  "type": "Feature",
  "properties": {
    "addr:full":"Ctra. Madrid-coru\u00f1a, S/n Benavente Zamora 49600",
    "addr:housenumber":"s / n",
    "addr:postcode":"49600",
    "addr:street":"Ctra. Madrid-Corun\u0303A",
    "iso:country":"ES",
    "sg:address":"Ctra. Madrid-coru\u00f1a, S/n",
    "sg:city":"Benavente",
    "sg:orig_category":"Serrer\u00cdas De Madera",
    "sg:phone":"+34 980 56 32 87",
    "sg:postcode":"49600",
    "sg:province":"Zamora",
    "wof:name":"Maderas Y Chapas Grami S.l.",
    "wof:placetype":"venue"
},
  "geometry": {"coordinates":[-5.7058868408,42.0713653564],"type":"Point"}
}