{
  "type": "Feature",
  "properties": {
    "iso:country":"ES",
    "sg:address":"Calle de Romea, 5",
    "sg:city":"Linares",
    "sg:orig_category":"Asistencia Domiciliaria",
    "sg:phone":"+34 953 65 16 01",
    "sg:postcode":"23700",
    "sg:province":"Ja\u00e9n",
    "wof:name":"Claros S.c.a.",
    "wof:placetype":"venue"
},
  "geometry": {"coordinates":[-3.6307599545,38.0991516113],"type":"Point"}
}