{
  "type": "Feature",
  "properties": {
    "addr:full":"Calle de Sendeja, 4 Bilbao Vizcaya 48007",
    "addr:housenumber":"4",
    "addr:postcode":"48007",
    "addr:street":"Calle De Sendeja",
    "iso:country":"ES",
    "sg:address":"Calle de Sendeja, 4",
    "sg:city":"Bilbao",
    "sg:orig_category":"Perfumer\u00cda (al Por Menor)",
    "sg:phone":"+34 944 45 32 93",
    "sg:postcode":"48007",
    "sg:province":"Vizcaya",
    "wof:name":"Gonzalez Angulo Isabel",
    "wof:placetype":"venue"
},
  "geometry": {"coordinates":[-2.9228620529,43.2628746033],"type":"Point"}
}