{
  "type": "Feature",
  "properties": {
    "addr:full":"Calle de Joaquin Sorolla, 3 Zaragoza Zaragoza 50007",
    "addr:housenumber":"3",
    "addr:postcode":"50007",
    "addr:street":"Calle De Joaquin Sorolla",
    "iso:country":"ES",
    "sg:address":"Calle de Joaquin Sorolla, 3",
    "sg:city":"Zaragoza",
    "sg:orig_category":"Peluqueros: De Se\u00d1oras",
    "sg:phone":"+34 976 25 56 06",
    "sg:postcode":"50007",
    "sg:province":"Zaragoza",
    "wof:name":"Franco Pellejero Adela Esther",
    "wof:placetype":"venue"
},
  "geometry": {"coordinates":[-0.8776440024,41.634853363],"type":"Point"}
}