{
  "type": "Feature",
  "properties": {
    "iso:country":"ES",
    "sg:address":"Avgd Serra, 44",
    "sg:city":"Massamagrell",
    "sg:orig_category":"Molduras, Junquillos, Listones Y Molduras Perforadas",
    "sg:phone":"+34 961 44 34 08",
    "sg:postcode":"46130",
    "sg:province":"Valencia",
    "wof:name":"Bleda De La Torre Juan",
    "wof:placetype":"venue"
},
  "geometry": {"coordinates":[-0.3458400071,39.5792427063],"type":"Point"}
}