{
  "type": "Feature",
  "properties": {
    "iso:country":"ES",
    "sg:address":"Calle de Fermin Caballero, 38",
    "sg:city":"Madrid",
    "sg:orig_category":"Administradores De Bienes Y Delegados De Comunidades De Propietarios",
    "sg:phone":"+34 917 40 50 72",
    "sg:postcode":"28034",
    "sg:province":"Madrid",
    "wof:name":"Sanchez Martin Francisco Jose",
    "wof:placetype":"venue"
},
  "geometry": {"coordinates":[-3.7043800354,40.4851150513],"type":"Point"}
}