{
  "type": "Feature",
  "properties": {
    "addr:full":"Calle de Lagasca, 48 Madrid Madrid 28001",
    "addr:housenumber":"48",
    "addr:postcode":"madrid;28001",
    "addr:street":"Calle De Lagasca",
    "iso:country":"ES",
    "sg:address":"Calle de Lagasca, 48",
    "sg:city":"Madrid",
    "sg:orig_category":"Camiser\u00cda Y Ropa Interior Masculina (al Por Menor)",
    "sg:phone":"+34 914 31 12 47",
    "sg:postcode":"28001",
    "sg:province":"Madrid",
    "wof:name":"Cordero Alonso Eduardo",
    "wof:placetype":"venue"
},
  "geometry": {"coordinates":[-3.6851348877,40.4259300232],"type":"Point"}
}