{
  "type": "Feature",
  "properties": {
    "addr:full":"Calle de Hernani, 66 Madrid Madrid 28020",
    "addr:housenumber":"66",
    "addr:postcode":"madrid;28020",
    "addr:street":"Calle De Hernani",
    "iso:country":"ES",
    "sg:address":"Calle de Hernani, 66",
    "sg:city":"Madrid",
    "sg:orig_category":"Psic\u00d3logos",
    "sg:phone":"+34 915 35 38 88",
    "sg:postcode":"28020",
    "sg:province":"Madrid",
    "wof:name":"Rodriguez Corcoles Helena",
    "wof:placetype":"venue"
},
  "geometry": {"coordinates":[-3.6964631081,40.4478492737],"type":"Point"}
}