{
  "type": "Feature",
  "properties": {
    "iso:country":"ES",
    "sg:address":"Carrer de Napols, 218",
    "sg:city":"Barcelona",
    "sg:classifiers":[
        {
            "category":"Manufacturing",
            "subcategory":"Building Materials",
            "type":"Manufacturing & Wholesale Goods"
        }
    ],
    "sg:phone":"+34 934 58 20 11",
    "sg:postcode":"08013",
    "sg:province":"Barcelona",
    "sg:tags":[
        "cemento",
        "y",
        "de",
        "fabricaci\u00d3n",
        "cal"
    ],
    "wof:name":"Comercial Plans S.a.",
    "wof:placetype":"venue"
},
  "geometry": {"coordinates":[2.1730959415,41.4003639221],"type":"Point"}
}