{
  "type": "Feature",
  "properties": {
    "iso:country":"ES",
    "sg:address":"Carr Anselm Clave, 32",
    "sg:city":"Lleida",
    "sg:orig_category":"Venta, Instalaci\u00d3n De Cocinas",
    "sg:phone":"+34 973 22 32 37",
    "sg:postcode":"25004",
    "sg:province":"Lleida",
    "wof:name":"La Cocota S.c.p.",
    "wof:placetype":"venue"
},
  "geometry": {"coordinates":[0.6291009784,41.6209106445],"type":"Point"}
}