{
  "type": "Feature",
  "properties": {
    "iso:country":"ES",
    "sg:address":"Carrer de Sebastia Juan Arbo, 46",
    "sg:city":"Amposta",
    "sg:orig_category":"Doctores En Medicina",
    "sg:phone":"+34 977 70 22 15",
    "sg:postcode":"43870",
    "sg:province":"Tarragona",
    "wof:name":"Gonzalez Lagunilla Jesus Jose",
    "wof:placetype":"venue"
},
  "geometry": {"coordinates":[0.578306973,40.7062797546],"type":"Point"}
}