{
  "type": "Feature",
  "properties": {
    "iso:country":"ES",
    "sg:address":"Rua Magdalena, 59",
    "sg:city":"Ferrol",
    "sg:orig_category":"Lencer\u00cda Femenina, Corseter\u00cda, Trajes De Ba\u00d1o (al Por Menor)",
    "sg:phone":"+34 981 35 91 15",
    "sg:postcode":"15402",
    "sg:province":"La Coru\u00f1a",
    "wof:name":"Lenceria Sanjurjo S.l.",
    "wof:placetype":"venue"
},
  "geometry": {"coordinates":[-8.2315416336,43.484085083],"type":"Point"}
}