{
  "type": "Feature",
  "properties": {
    "addr:full":"Carr Major, 65 Vilanova D'alcolea Castell\u00f3n 12183",
    "addr:housenumber":"65",
    "addr:postcode":"12183",
    "addr:street":"Carr Major",
    "iso:country":"ES",
    "sg:address":"Carr Major, 65",
    "sg:city":"Vilanova D'alcolea",
    "sg:orig_category":"M\u00c1rmoles, Granitos Y Piedras Naturales",
    "sg:phone":"+34 964 70 70 49",
    "sg:postcode":"12183",
    "sg:province":"Castell\u00f3n",
    "wof:name":"Marmoles Y Piedras Casmar S.l.",
    "wof:placetype":"venue"
},
  "geometry": {"coordinates":[-0.0358190015,39.986782074],"type":"Point"}
}