{
  "type": "Feature",
  "properties": {
    "iso:country":"ES",
    "sg:address":"Poligono La Herrera I, S/n",
    "sg:city":"Saelices Sabero",
    "sg:orig_category":"Carnicer\u00cdas, Carnicer\u00cdas",
    "sg:phone":"+34 987 71 82 10",
    "sg:postcode":"24812",
    "sg:province":"Le\u00f3n",
    "wof:name":"Moreiras Fernandez Jesus",
    "wof:placetype":"venue"
},
  "geometry": {"coordinates":[-5.150428772,42.8362884521],"type":"Point"}
}