{
  "type": "Feature",
  "properties": {
    "iso:country":"ES",
    "sg:address":"Rua Rollo, 9",
    "sg:city":"Betanzos",
    "sg:orig_category":"Bazares, Art\u00cdculos De Limpieza Y De Cocina (al Por Menor)",
    "sg:phone":"+34 981 77 07 81",
    "sg:postcode":"15300",
    "sg:province":"La Coru\u00f1a",
    "wof:name":"Lista Villa Jose Esteban",
    "wof:placetype":"venue"
},
  "geometry": {"coordinates":[-8.2119092941,43.279914856],"type":"Point"}
}