{
  "type": "Feature",
  "properties": {
    "addr:full":"Ctra Nijar Alquian, Km. 0008,4 Alquian Almer\u00eda 04130",
    "addr:postcode":"04130",
    "addr:street":"Ctra Nijar Alquian Km. 0008,4 Alquian Almeri\u0301A",
    "iso:country":"ES",
    "sg:address":"Ctra Nijar Alquian, Km. 0008,4",
    "sg:city":"Alquian",
    "sg:orig_category":"Frutas Y Legumbres Frescas (al Por Mayor)",
    "sg:phone":"+34 950 29 74 33",
    "sg:postcode":"04130",
    "sg:province":"Almer\u00eda",
    "sg:website":"www.frutascaparros.com",
    "wof:name":"Frutas Caparros S.l.",
    "wof:placetype":"venue"
},
  "geometry": {"coordinates":[-2.3529150486,36.8523406982],"type":"Point"}
}