{
  "type": "Feature",
  "properties": {
    "iso:country":"ES",
    "sg:address":"Avda Iparragirre, 22",
    "sg:city":"Elexalde",
    "sg:orig_category":"M\u00c9dicos: Estomatolog\u00cda",
    "sg:phone":"+34 944 64 64 14",
    "sg:postcode":"48940",
    "sg:province":"Vizcaya",
    "wof:name":"Basterra Vicario Alejandro",
    "wof:placetype":"venue"
},
  "geometry": {"coordinates":[-2.9898400307,43.3265724182],"type":"Point"}
}