{
  "type": "Feature",
  "properties": {
    "addr:full":"Calle de Obispo Rocamora, 31 Orihuela Alicante 03300",
    "addr:housenumber":"31",
    "addr:postcode":"03300",
    "addr:street":"Calle De Obispo Rocamora",
    "iso:country":"ES",
    "sg:address":"Calle de Obispo Rocamora, 31",
    "sg:city":"Orihuela",
    "sg:orig_category":"Alquiler De V\u00cddeo",
    "sg:phone":"+34 965 30 55 46",
    "sg:postcode":"03300",
    "sg:province":"Alicante",
    "wof:name":"Gestion Del Video 10 S.l.",
    "wof:placetype":"venue"
},
  "geometry": {"coordinates":[-0.9427509904,38.0835075378],"type":"Point"}
}