{
  "type": "Feature",
  "properties": {
    "iso:country":"ES",
    "sg:address":"Carrer de Fortuny, 5",
    "sg:city":"Hospitalet Llobregat",
    "sg:orig_category":"Imprenta",
    "sg:phone":"+34 934 48 08 73",
    "sg:postcode":"08903",
    "sg:province":"Barcelona",
    "wof:name":"Papers 99 Sociedad Coop Catalana Limitada",
    "wof:placetype":"venue"
},
  "geometry": {"coordinates":[2.1209790707,41.3736572266],"type":"Point"}
}