{
  "type": "Feature",
  "properties": {
    "addr:full":"Calle de Maestro Ricardo, 6 Burgos Burgos 09002",
    "addr:housenumber":"6",
    "addr:postcode":"09002",
    "addr:street":"Calle De Maestro Ricardo",
    "iso:country":"ES",
    "sg:address":"Calle de Maestro Ricardo, 6",
    "sg:city":"Burgos",
    "sg:orig_category":"Fabricaci\u00d3n De Ventanas",
    "sg:phone":"+34 947 20 09 68",
    "sg:postcode":"09002",
    "sg:province":"Burgos",
    "wof:name":"Valdezate Medrano Oscar Raul",
    "wof:placetype":"venue"
},
  "geometry": {"coordinates":[-3.6883089542,42.3394470215],"type":"Point"}
}