{
  "type": "Feature",
  "properties": {
    "iso:country":"ES",
    "sg:address":"Calle de Mar Negro, 4",
    "sg:city":"Madrid",
    "sg:orig_category":"Alimentaci\u00d3n General (al Por Menor)",
    "sg:phone":"+34 913 81 35 47",
    "sg:postcode":"28033",
    "sg:province":"Madrid",
    "wof:name":"Robledillo Ramos Miguel",
    "wof:placetype":"venue"
},
  "geometry": {"coordinates":[-3.6430768967,40.4740142822],"type":"Point"}
}