{
  "type": "Feature",
  "properties": {
    "addr:full":"Urb Montenebros Ii, S/n Estacion Madrid 28400",
    "addr:housenumber":"s / n",
    "addr:postcode":"28400",
    "addr:street":"Urb;Ii",
    "iso:country":"ES",
    "sg:address":"Urb Montenebros Ii, S/n",
    "sg:city":"Estacion",
    "sg:orig_category":"Energ\u00cda Solar Y Nuevas Energ\u00cdas (equipo, Estudios)",
    "sg:phone":"+34 918 50 43 32",
    "sg:postcode":"28400",
    "sg:province":"Madrid",
    "wof:name":"Barahona Blanco Lorenzo",
    "wof:placetype":"venue"
},
  "geometry": {"coordinates":[-3.9919650555,40.6455612183],"type":"Point"}
}