{
  "type": "Feature",
  "properties": {
    "iso:country":"ES",
    "sg:address":"Carr Barcelona, 17",
    "sg:city":"Mas Aliu",
    "sg:orig_category":"Automatizaci\u00d3n De Procesos Industriales Y De Edificaci\u00d3n (estudios, Instalaci\u00d3n)",
    "sg:phone":"+34 972 24 55 03",
    "sg:postcode":"17181",
    "sg:province":"Girona",
    "wof:name":"Sapli S.l.",
    "wof:placetype":"venue"
},
  "geometry": {"coordinates":[2.7634348869,41.938041687],"type":"Point"}
}