{
  "type": "Feature",
  "properties": {
    "addr:full":"Portu Auzoa, 9 Hernani Guip\u00f9zcoa 20120",
    "addr:housenumber":"9",
    "addr:postcode":"20120",
    "addr:street":"Portu Auzoa;Guipu\u0300Zcoa",
    "iso:country":"ES",
    "sg:address":"Portu Auzoa, 9",
    "sg:city":"Hernani",
    "sg:orig_category":"Mec\u00c1nico Del Autom\u00d3vil",
    "sg:phone":"+34 943 55 01 83",
    "sg:postcode":"20120",
    "sg:province":"Guip\u00f9zcoa",
    "wof:name":"Agustin Redondo Dominguez Y Otro C.b.",
    "wof:placetype":"venue"
},
  "geometry": {"coordinates":[-1.9741390944,43.2631454468],"type":"Point"}
}