{
  "type": "Feature",
  "properties": {
    "iso:country":"ES",
    "sg:address":"Calle de Cervantes, 18",
    "sg:city":"Merida",
    "sg:orig_category":"Ropa Para Se\u00d1oras (al Por Menor)",
    "sg:phone":"+34 924 30 19 68",
    "sg:postcode":"06800",
    "sg:province":"Badajoz",
    "wof:name":"Almeida Machuca S.a.",
    "wof:placetype":"venue"
},
  "geometry": {"coordinates":[-6.3849964142,38.8864250183],"type":"Point"}
}