{
  "type": "Feature",
  "properties": {
    "iso:country":"ES",
    "sg:address":"Calle de Bogota, 4",
    "sg:city":"Benidorm",
    "sg:orig_category":"Bazares, Art\u00cdculos De Limpieza Y De Cocina (al Por Menor)",
    "sg:phone":"+34 965 85 73 03",
    "sg:postcode":"03500",
    "sg:province":"Alicante",
    "wof:name":"Marchioni  Marta Edith",
    "wof:placetype":"venue"
},
  "geometry": {"coordinates":[-0.1421418041,38.5455970764],"type":"Point"}
}