{
  "type": "Feature",
  "properties": {
    "addr:full":"Pase Melancolicos, 5 Madrid Madrid 28005",
    "addr:housenumber":"5",
    "addr:postcode":"28005",
    "addr:street":"Melancolicos",
    "iso:country":"ES",
    "sg:address":"Pase Melancolicos, 5",
    "sg:city":"Madrid",
    "sg:orig_category":"Venta, Montaje De Neum\u00c1ticos",
    "sg:phone":"+34 913 65 14 00",
    "sg:postcode":"28005",
    "sg:province":"Madrid",
    "wof:name":"Neumaticos Mampaso S. L.",
    "wof:placetype":"venue"
},
  "geometry": {"coordinates":[-3.7196390629,40.4081687927],"type":"Point"}
}