{
  "type": "Feature",
  "properties": {
    "iso:country":"ES",
    "sg:address":"C/ San Ramon, 28",
    "sg:city":"Moncofa",
    "sg:orig_category":"Ingeniero",
    "sg:phone":"+34 964 58 06 07",
    "sg:postcode":"12593",
    "sg:province":"Castell\u00f3n",
    "wof:name":"Paradis Paradis Jose",
    "wof:placetype":"venue"
},
  "geometry": {"coordinates":[-0.1429889947,39.8067741394],"type":"Point"}
}