{
  "type": "Feature",
  "properties": {
    "addr:full":"Calle de Gamazo, 12 Valladolid Valladolid 47004",
    "addr:housenumber":"12",
    "addr:postcode":"47004",
    "addr:street":"Calle De Gamazo",
    "iso:country":"ES",
    "sg:address":"Calle de Gamazo, 12",
    "sg:city":"Valladolid",
    "sg:orig_category":"Procuradores",
    "sg:phone":"+34 983 21 83 33",
    "sg:postcode":"47004",
    "sg:province":"Valladolid",
    "wof:name":"Javier Gallego Brizuela Y Otros Cdad",
    "wof:placetype":"venue"
},
  "geometry": {"coordinates":[-4.7261371613,41.6465911865],"type":"Point"}
}