{
  "type": "Feature",
  "properties": {
    "addr:full":"Carr Nou, 25 Girona Girona 17001",
    "addr:housenumber":"25",
    "addr:postcode":"17001",
    "addr:street":"Carr Nou",
    "iso:country":"ES",
    "sg:address":"Carr Nou, 25",
    "sg:city":"Girona",
    "sg:orig_category":"Muebles, Minoristas",
    "sg:phone":"+34 972 20 01 78",
    "sg:postcode":"17001",
    "sg:province":"Girona",
    "wof:name":"Cal Rei S.a.",
    "wof:placetype":"venue"
},
  "geometry": {"coordinates":[2.8187448978,41.9808616638],"type":"Point"}
}