{
  "type": "Feature",
  "properties": {
    "addr:full":"Carr Juan Xxiii, 22 Puerto De Pollen\u00c7a Islas Baleares 07470",
    "addr:housenumber":"22",
    "addr:postcode":"07470",
    "addr:street":"Carr Juan Xxiii",
    "iso:country":"ES",
    "sg:address":"Carr Juan Xxiii, 22",
    "sg:city":"Puerto De Pollen\u00c7a",
    "sg:orig_category":"Supermercados Y Hipermercados",
    "sg:phone":"+34 971 86 81 47",
    "sg:postcode":"07470",
    "sg:province":"Islas Baleares",
    "wof:name":"Distribucions Mercat S.a.",
    "wof:placetype":"venue"
},
  "geometry": {"coordinates":[3.0826599598,39.9063415527],"type":"Point"}
}