{
  "type": "Feature",
  "properties": {
    "iso:country":"ES",
    "sg:address":"Avda Aragon (de), 10",
    "sg:city":"Teruel",
    "sg:orig_category":"Bazares, Art\u00cdculos De Limpieza Y De Cocina (al Por Menor)",
    "sg:phone":"+34 978 60 61 30",
    "sg:postcode":"44002",
    "sg:province":"Teruel",
    "wof:name":"Domingo Perez Eva",
    "wof:placetype":"venue"
},
  "geometry": {"coordinates":[-1.1036789417,40.3332138062],"type":"Point"}
}