{
  "type": "Feature",
  "properties": {
    "addr:full":"Avda Manuel Torres, 8 Malaga M\u00e1laga 29003",
    "addr:housenumber":"8",
    "addr:postcode":"29003",
    "addr:street":"Avda Manuel Torres;Ma\u0301Laga",
    "iso:country":"ES",
    "sg:address":"Avda Manuel Torres, 8",
    "sg:city":"Malaga",
    "sg:orig_category":"Mec\u00c1nico Del Autom\u00d3vil",
    "sg:phone":"+34 952 35 67 04",
    "sg:postcode":"29003",
    "sg:province":"M\u00e1laga",
    "wof:name":"Automoviles Onieva S. A.",
    "wof:placetype":"venue"
},
  "geometry": {"coordinates":[-4.4476861954,36.7002105713],"type":"Point"}
}