{
  "type": "Feature",
  "properties": {
    "addr:full":"Calle de Alcalde Manuel Alberola, 16 Novelda Alicante 03660",
    "addr:housenumber":"16",
    "addr:postcode":"03660",
    "addr:street":"Calle De Alcalde Manuel Alberola",
    "iso:country":"ES",
    "sg:address":"Calle de Alcalde Manuel Alberola, 16",
    "sg:city":"Novelda",
    "sg:orig_category":"Droguer\u00cdas (al Por Menor)",
    "sg:phone":"+34 965 60 07 79",
    "sg:postcode":"03660",
    "sg:province":"Alicante",
    "wof:name":"Esteban I\u00f1esta Jose",
    "wof:placetype":"venue"
},
  "geometry": {"coordinates":[-0.7647312284,38.3838386536],"type":"Point"}
}