{
  "type": "Feature",
  "properties": {
    "addr:full":"Calle de Lope De Vega, 25 Alcala Henares Madrid 28805",
    "addr:housenumber":"25",
    "addr:postcode":"28805",
    "addr:street":"Calle De Lope De Vega",
    "iso:country":"ES",
    "sg:address":"Calle de Lope De Vega, 25",
    "sg:city":"Alcala Henares",
    "sg:orig_category":"Carnicer\u00cdas, Carnicer\u00cdas",
    "sg:phone":"+34 918 89 14 10",
    "sg:postcode":"28805",
    "sg:province":"Madrid",
    "wof:name":"Galan Sanchez Moises",
    "wof:placetype":"venue"
},
  "geometry": {"coordinates":[-3.3596580029,40.4898033142],"type":"Point"}
}