{
  "type": "Feature",
  "properties": {
    "addr:full":"Carrer de Cami Dels Monjos, 89 Terrassa Barcelona 08227",
    "addr:housenumber":"89",
    "addr:postcode":"08227",
    "addr:street":"Carrer De;Dels Monjos",
    "iso:country":"ES",
    "sg:address":"Carrer de Cami Dels Monjos, 89",
    "sg:city":"Terrassa",
    "sg:orig_category":"Panader\u00cdas, Panader\u00cdas",
    "sg:phone":"+34 937 31 84 51",
    "sg:postcode":"08227",
    "sg:province":"Barcelona",
    "wof:name":"Especialitats Gurmet C.b.",
    "wof:placetype":"venue"
},
  "geometry": {"coordinates":[2.0407550335,41.5610046387],"type":"Point"}
}