{
  "type": "Feature",
  "properties": {
    "iso:country":"ES",
    "sg:address":"Calle de Mariano Vela, 18",
    "sg:city":"Madrid",
    "sg:orig_category":"Electromec\u00c1nica",
    "sg:phone":"+34 914 69 81 10",
    "sg:postcode":"28026",
    "sg:province":"Madrid",
    "wof:name":"Saz Gutierrez Jose",
    "wof:placetype":"venue"
},
  "geometry": {"coordinates":[-3.7108230591,40.3849105835],"type":"Point"}
}