{
  "type": "Feature",
  "properties": {
    "addr:full":"Viduedo, S/n Cea Ourense 32130",
    "addr:housenumber":"/ n",
    "addr:postcode":"32130",
    "addr:street":"Viduedo S",
    "iso:country":"ES",
    "sg:address":"Viduedo, S/n",
    "sg:city":"Cea",
    "sg:orig_category":"Quincaller\u00cda (al Por Menor)",
    "sg:phone":"+34 988 28 21 89",
    "sg:postcode":"32130",
    "sg:province":"Ourense",
    "wof:name":"Grupo Casa Alen S.l.",
    "wof:placetype":"venue"
},
  "geometry": {"coordinates":[-7.9660973549,42.4832992554],"type":"Point"}
}