{
  "type": "Feature",
  "properties": {
    "addr:full":"Calle de Santa Isabel, 14 Zaragoza Zaragoza 50003",
    "addr:housenumber":"14",
    "addr:postcode":"50003",
    "addr:street":"Calle De Santa Isabel",
    "iso:country":"ES",
    "sg:address":"Calle de Santa Isabel, 14",
    "sg:city":"Zaragoza",
    "sg:orig_category":"Compraventa De Antig\u00dcedades",
    "sg:phone":"+34 976 39 24 07",
    "sg:postcode":"50003",
    "sg:province":"Zaragoza",
    "wof:name":"Esteban Maturen Antonio",
    "wof:placetype":"venue"
},
  "geometry": {"coordinates":[-0.8808789849,41.655418396],"type":"Point"}
}