{
  "type": "Feature",
  "properties": {
    "addr:full":"Calle de Jaul, 1 Almeria Almer\u00eda 04007",
    "addr:housenumber":"1",
    "addr:postcode":"04007",
    "addr:street":"Calle De Jaul",
    "iso:country":"ES",
    "sg:address":"Calle de Jaul, 1",
    "sg:city":"Almeria",
    "sg:orig_category":"Material Y Suministros Para Pesca Y Piscicultura",
    "sg:phone":"+34 950 26 30 73",
    "sg:postcode":"04007",
    "sg:province":"Almer\u00eda",
    "wof:name":"Deportes Iceberg",
    "wof:placetype":"venue"
},
  "geometry": {"coordinates":[-2.4510951042,36.8288269043],"type":"Point"}
}