{
  "type": "Feature",
  "properties": {
    "addr:full":"Calle de Rafael Fernandez Hijicos, 12 Madrid Madrid 28038",
    "addr:housenumber":"12",
    "addr:postcode":"madrid;28038",
    "addr:street":"Calle De Rafael;Hijicos",
    "iso:country":"ES",
    "sg:address":"Calle de Rafael Fernandez Hijicos, 12",
    "sg:city":"Madrid",
    "sg:orig_category":"Edici\u00d3n De Diarios, Revistas, Boletines",
    "sg:phone":"+34 917 78 14 28",
    "sg:postcode":"28038",
    "sg:province":"Madrid",
    "sg:website":"www.edimicros.es",
    "wof:name":"Edimicros S.l.",
    "wof:placetype":"venue"
},
  "geometry": {"coordinates":[-3.6355640888,40.3912162781],"type":"Point"}
}