{
  "type": "Feature",
  "properties": {
    "iso:country":"ES",
    "sg:address":"Rua General Franco, 77",
    "sg:city":"Silleda",
    "sg:orig_category":"Librer\u00cdas",
    "sg:phone":"+34 986 58 13 66",
    "sg:postcode":"36540",
    "sg:province":"Pontevedra",
    "wof:name":"Libreria Galicia S.c.",
    "wof:placetype":"venue"
},
  "geometry": {"coordinates":[-8.2418241501,42.6958084106],"type":"Point"}
}