{
  "type": "Feature",
  "properties": {
    "addr:full":"Avda Fisterra, 84 Arteixo A Coru\u00f1a 15142",
    "addr:housenumber":"84",
    "addr:postcode":"15142",
    "addr:street":"Avda Fisterra;Corun\u0303A",
    "iso:country":"ES",
    "sg:address":"Avda Fisterra, 84",
    "sg:city":"Arteixo",
    "sg:orig_category":"Electrodom\u00c9sticos (al Por Menor)",
    "sg:phone":"+34 981 60 21 73",
    "sg:postcode":"15142",
    "sg:province":"A Coru\u00f1a",
    "wof:name":"Servicio Tecnico Satelite S.l.",
    "wof:placetype":"venue"
},
  "geometry": {"coordinates":[-8.5084037781,43.305770874],"type":"Point"}
}