{
  "type": "Feature",
  "properties": {
    "iso:country":"ES",
    "sg:address":"Calle de Maria De Molina, 5",
    "sg:city":"Valladolid",
    "sg:orig_category":"Arquitectos",
    "sg:phone":"+34 983 34 18 78",
    "sg:postcode":"47001",
    "sg:province":"Valladolid",
    "wof:name":"Isidro Rodriguez Jose Antonio",
    "wof:placetype":"venue"
},
  "geometry": {"coordinates":[-4.7302360535,41.6497421265],"type":"Point"}
}