{
  "type": "Feature",
  "properties": {
    "addr:full":"Trav. Cala En Busquets, S/n Alaior Islas Baleares 07730",
    "addr:housenumber":"s / n",
    "addr:postcode":"07730",
    "addr:street":"Cala;Busquets",
    "iso:country":"ES",
    "sg:address":"Trav. Cala En Busquets, S/n",
    "sg:city":"Alaior",
    "sg:orig_category":"Alquiler De Veh\u00cdculos: Turismos Y Utilitarios",
    "sg:phone":"+34 971 37 18 02",
    "sg:postcode":"07730",
    "sg:province":"Islas Baleares",
    "wof:name":"M.m.property Rentals S.l.",
    "wof:placetype":"venue"
},
  "geometry": {"coordinates":[4.1417298317,39.9292907715],"type":"Point"}
}