{
  "type": "Feature",
  "properties": {
    "iso:country":"ES",
    "sg:address":"Calle de Cristobal Bordiu, 50",
    "sg:city":"Madrid",
    "sg:orig_category":"M\u00c9dicos: Estomatolog\u00cda",
    "sg:phone":"+34 915 54 84 85",
    "sg:postcode":"28003",
    "sg:province":"Madrid",
    "wof:name":"Ramirez Luque Alicia",
    "wof:placetype":"venue"
},
  "geometry": {"coordinates":[-3.6963000298,40.4429130554],"type":"Point"}
}