{
  "type": "Feature",
  "properties": {
    "iso:country":"ES",
    "sg:address":"Carrer de Villarroel, 20",
    "sg:city":"Barcelona",
    "sg:orig_category":"Ferreter\u00cda (diversos)",
    "sg:phone":"+34 934 23 37 64",
    "sg:postcode":"08011",
    "sg:province":"Barcelona",
    "wof:name":"Quatermass Negocios S.l",
    "wof:placetype":"venue"
},
  "geometry": {"coordinates":[2.161962986,41.3814811707],"type":"Point"}
}