{
  "type": "Feature",
  "properties": {
    "iso:country":"ES",
    "sg:address":"Rond Muralla (da), 2",
    "sg:city":"Lugo",
    "sg:orig_category":"Sociedades, Compa\u00d1\u00cdas Aseguradoras",
    "sg:phone":"+34 982 22 26 56",
    "sg:postcode":"27001",
    "sg:province":"Lugo",
    "wof:name":"Vizoso Iglesias Pablo S.a.",
    "wof:placetype":"venue"
},
  "geometry": {"coordinates":[-7.5558686256,43.0113105774],"type":"Point"}
}