{
  "type": "Feature",
  "properties": {
    "iso:country":"ES",
    "sg:address":"Carrer de Quintana, 4",
    "sg:city":"Barcelona",
    "sg:orig_category":"Arquitectos",
    "sg:phone":"+34 933 17 31 88",
    "sg:postcode":"08002",
    "sg:province":"Barcelona",
    "wof:name":"Garces Bruses Jordi",
    "wof:placetype":"venue"
},
  "geometry": {"coordinates":[2.1741440296,41.3812255859],"type":"Point"}
}