{
  "type": "Feature",
  "properties": {
    "iso:country":"ES",
    "sg:address":"Calle de Torrijos, 9",
    "sg:city":"Escalonilla",
    "sg:orig_category":"Trajes Y Adornos De Boda (confecci\u00d3n, Al Por Menor)",
    "sg:phone":"+34 925 75 80 41",
    "sg:postcode":"45517",
    "sg:province":"Toledo",
    "wof:name":"Gonzalez Alonso Miriam Yolanda",
    "wof:placetype":"venue"
},
  "geometry": {"coordinates":[-4.3448591232,39.9274482727],"type":"Point"}
}