{
  "type": "Feature",
  "properties": {
    "addr:full":"Calle de Calvo Sotelo, 18 Tui Pontevedra 36700",
    "addr:housenumber":"18",
    "addr:postcode":"36700",
    "addr:street":"Calle De Calvo Sotelo",
    "iso:country":"ES",
    "sg:address":"Calle de Calvo Sotelo, 18",
    "sg:city":"Tui",
    "sg:orig_category":"Ropa Para Caballeros (al Por Menor)",
    "sg:phone":"+34 986 60 32 45",
    "sg:postcode":"36700",
    "sg:province":"Pontevedra",
    "wof:name":"Martinez Novas Maria Dolores",
    "wof:placetype":"venue"
},
  "geometry": {"coordinates":[-8.6447677612,42.047416687],"type":"Point"}
}