{
  "type": "Feature",
  "properties": {
    "iso:country":"ES",
    "sg:address":"Calle de Moreno Cortes, 14",
    "sg:city":"Cabezo Torres",
    "sg:orig_category":"Tintes (fabricaci\u00d3n, Al Por Mayor)",
    "sg:phone":"+34 968 30 58 77",
    "sg:postcode":"30110",
    "sg:province":"Murcia",
    "wof:name":"Carnes De El Bierzo-leon S.r.l.",
    "wof:placetype":"venue"
},
  "geometry": {"coordinates":[-1.1252180338,38.0250320435],"type":"Point"}
}