{
  "type": "Feature",
  "properties": {
    "addr:full":"Avda Mar Mediterraneo (del), 73 Valdemoro Madrid 28340",
    "addr:housenumber":"73",
    "addr:postcode":"28340",
    "addr:street":"Avda Mar Mediterraneo Del",
    "iso:country":"ES",
    "sg:address":"Avda Mar Mediterraneo (del), 73",
    "sg:city":"Valdemoro",
    "sg:orig_category":"Alimentaci\u00d3n General (al Por Menor)",
    "sg:phone":"+34 918 08 47 30",
    "sg:postcode":"28340",
    "sg:province":"Madrid",
    "wof:name":"Vila Cao Arturo",
    "wof:placetype":"venue"
},
  "geometry": {"coordinates":[-3.6831400394,40.1817703247],"type":"Point"}
}