{
  "type": "Feature",
  "properties": {
    "iso:country":"ES",
    "sg:address":"Calle de Reyes Catolicos, 14",
    "sg:city":"Avila",
    "sg:orig_category":"Ropa De Trabajo Y Profesionales (fabricaci\u00d3n, Al Por Mayor)",
    "sg:phone":"+34 920 25 01 17",
    "sg:postcode":"05001",
    "sg:province":"\u00c1vila",
    "wof:name":"Sociedad Cooperativa Limitada De Trabajo Asociados Jarica",
    "wof:placetype":"venue"
},
  "geometry": {"coordinates":[-4.6991119385,40.6557121277],"type":"Point"}
}