{
  "type": "Feature",
  "properties": {
    "addr:full":"P. Matadero, 3 Malaga M\u00e1laga 29002",
    "addr:housenumber":"3",
    "addr:postcode":"29002",
    "addr:street":"P. Matadero;Ma\u0301Laga",
    "iso:country":"ES",
    "sg:address":"P. Matadero, 3",
    "sg:city":"Malaga",
    "sg:orig_category":"Abogados",
    "sg:phone":"+34 952 32 57 55",
    "sg:postcode":"29002",
    "sg:province":"M\u00e1laga",
    "wof:name":"Perez Gomez Gines",
    "wof:placetype":"venue"
},
  "geometry": {"coordinates":[-4.4265289307,36.7114982605],"type":"Point"}
}