{
  "type": "Feature",
  "properties": {
    "iso:country":"ES",
    "sg:address":"Carrer de Cavallers, 61",
    "sg:city":"Esparreguera",
    "sg:orig_category":"Peluquer\u00cdas, Peluquer\u00cda Mixta",
    "sg:phone":"+34 937 77 50 55",
    "sg:postcode":"08292",
    "sg:province":"Barcelona",
    "wof:name":"Calleja Martinez Ana Maria",
    "wof:placetype":"venue"
},
  "geometry": {"coordinates":[1.8127340078,41.5431747437],"type":"Point"}
}