{
  "type": "Feature",
  "properties": {
    "addr:full":"Calle de Brasilia, 27 Malaga M\u00e1laga 29006",
    "addr:housenumber":"27",
    "addr:postcode":"29006",
    "addr:street":"Calle De Brasilia;Ma\u0301Laga",
    "iso:country":"ES",
    "sg:address":"Calle de Brasilia, 27",
    "sg:city":"Malaga",
    "sg:orig_category":"Material Y Suministros Para Dentistas, Cirujanos",
    "sg:phone":"+34 952 32 94 63",
    "sg:postcode":"29006",
    "sg:province":"M\u00e1laga",
    "wof:name":"Ingenieria,informatica Y Medio Ambiente S.a.",
    "wof:placetype":"venue"
},
  "geometry": {"coordinates":[-4.4754190445,36.7133865356],"type":"Point"}
}