{
  "type": "Feature",
  "properties": {
    "iso:country":"ES",
    "sg:address":"Ctra. Pelayos Presa, Km. 0008,0",
    "sg:city":"Cadalso",
    "sg:orig_category":"Explotaci\u00d3n De Canteras",
    "sg:phone":"+34 918 64 07 86",
    "sg:postcode":"28640",
    "sg:province":"Madrid",
    "wof:name":"Graniblanco S.l.",
    "wof:placetype":"venue"
},
  "geometry": {"coordinates":[-4.4287810326,40.3056602478],"type":"Point"}
}