{
  "type": "Feature",
  "properties": {
    "addr:full":"Calle de Fernando Gutierrez, 17 Villaralbo Zamora 49159",
    "addr:housenumber":"17",
    "addr:postcode":"49159",
    "addr:street":"Calle De Fernando Gutierrez",
    "iso:country":"ES",
    "sg:address":"Calle de Fernando Gutierrez, 17",
    "sg:city":"Villaralbo",
    "sg:orig_category":"Caf\u00c9s, Bares, Cervecer\u00cdas",
    "sg:phone":"+34 980 53 92 38",
    "sg:postcode":"49159",
    "sg:province":"Zamora",
    "wof:name":"Bragado Pelayo S.l.",
    "wof:placetype":"venue"
},
  "geometry": {"coordinates":[-5.6848192215,41.4921798706],"type":"Point"}
}