{
  "type": "Feature",
  "properties": {
    "addr:full":"Calle de Alberola, 61 Alacant Alicante 03007",
    "addr:housenumber":"61",
    "addr:postcode":"03007",
    "addr:street":"Calle De Alberola",
    "iso:country":"ES",
    "sg:address":"Calle de Alberola, 61",
    "sg:city":"Alacant",
    "sg:orig_category":"Ense\u00d1anza Variada",
    "sg:phone":"+34 965 13 33 55",
    "sg:postcode":"03007",
    "sg:province":"Alicante",
    "wof:name":"Centro De Nuevas Tecnologias Y Reciclaje Empresarial S.l.",
    "wof:placetype":"venue"
},
  "geometry": {"coordinates":[-0.4990336001,38.3396682739],"type":"Point"}
}