{
  "type": "Feature",
  "properties": {
    "addr:full":"Calle de Cura Francisco Lopez Hurtado, S/n Alcantarilla Murcia 30820",
    "addr:housenumber":"s",
    "addr:postcode":"30820",
    "addr:street":"Calle De Cura Francisco Lopez Hurtado;/ N",
    "iso:country":"ES",
    "sg:address":"Calle de Cura Francisco Lopez Hurtado, S/n",
    "sg:city":"Alcantarilla",
    "sg:orig_category":"Alimentaci\u00d3n General (al Por Menor)",
    "sg:phone":"+34 968 80 65 19",
    "sg:postcode":"30820",
    "sg:province":"Murcia",
    "wof:name":"Jimenez Bernal Julian",
    "wof:placetype":"venue"
},
  "geometry": {"coordinates":[-1.2026087046,37.9724578857],"type":"Point"}
}