{
  "type": "Feature",
  "properties": {
    "addr:full":"Calle de Heraclio Sanchez, 30 San Cristobal De La Laguna Santa Cruz De Tenerife 38204",
    "addr:housenumber":"30",
    "addr:postcode":"38204",
    "addr:street":"Calle De Heraclio Sanchez",
    "iso:country":"ES",
    "sg:address":"Calle de Heraclio Sanchez, 30",
    "sg:city":"San Cristobal De La Laguna",
    "sg:orig_category":"Estancos",
    "sg:phone":"+34 922 25 09 96",
    "sg:postcode":"38204",
    "sg:province":"Santa Cruz De Tenerife",
    "wof:name":"Barella Pacheco Victoria Carmen",
    "wof:placetype":"venue"
},
  "geometry": {"coordinates":[-16.3158187866,28.4852619171],"type":"Point"}
}