{
  "type": "Feature",
  "properties": {
    "addr:full":"Calle de Alfredo Calderon, 64 Palmas De Gran Canaria Las Palmas 35006",
    "addr:postcode":"35006",
    "addr:street":"Calle De Alfredo Calderon 64",
    "iso:country":"ES",
    "sg:address":"Calle de Alfredo Calderon, 64",
    "sg:city":"Palmas De Gran Canaria",
    "sg:orig_category":"Importaci\u00d3n",
    "sg:phone":"+34 928 29 13 44",
    "sg:postcode":"35006",
    "sg:province":"Las Palmas",
    "wof:name":"Jicomar S.l.",
    "wof:placetype":"venue"
},
  "geometry": {"coordinates":[-15.4339141846,28.130531311],"type":"Point"}
}