{
  "type": "Feature",
  "properties": {
    "addr:full":"Calle de Doctor Severo Ochoa, S/n Arrecife Las Palmas 35500",
    "addr:housenumber":"s / n",
    "addr:postcode":"35500",
    "addr:street":"Calle De Doctor Severo Ochoa",
    "iso:country":"ES",
    "sg:address":"Calle de Doctor Severo Ochoa, S/n",
    "sg:city":"Arrecife",
    "sg:orig_category":"Centros De Educaci\u00d3n Especial",
    "sg:phone":"+34 928 81 42 12",
    "sg:postcode":"35500",
    "sg:province":"Las Palmas",
    "wof:name":"Gobierno De Canarias",
    "wof:placetype":"venue"
},
  "geometry": {"coordinates":[-13.558300972,28.9672050476],"type":"Point"}
}