{
  "type": "Feature",
  "properties": {
    "iso:country":"ES",
    "sg:address":"Calle de Melonares (de Los), 6",
    "sg:city":"Galapagar",
    "sg:orig_category":"Reposter\u00cdas",
    "sg:phone":"+34 918 59 76 93",
    "sg:postcode":"28260",
    "sg:province":"Madrid",
    "wof:name":"Rejano Ruiz Maria Soledad",
    "wof:placetype":"venue"
},
  "geometry": {"coordinates":[-4.0011138916,40.5794487],"type":"Point"}
}