{
  "type": "Feature",
  "properties": {
    "iso:country":"ES",
    "sg:address":"Gurutze Kalea, 4",
    "sg:city":"Zestoa",
    "sg:orig_category":"Ense\u00d1anza: Comercio, Gesti\u00d3n, Inform\u00c1tica",
    "sg:phone":"+34 943 14 75 49",
    "sg:postcode":"20740",
    "sg:province":"Guip\u00f9zcoa",
    "wof:name":"Sociedad Informatica Del Gobierno Vasco-ejie",
    "wof:placetype":"venue"
},
  "geometry": {"coordinates":[-2.2570590973,43.239364624],"type":"Point"}
}