{
  "type": "Feature",
  "properties": {
    "addr:full":"Luga Diseminado Matorral, 6 Castillo Las Palmas 35610",
    "addr:housenumber":"6",
    "addr:postcode":"35610",
    "addr:street":"Luga Diseminado Matorral;Castillo Las",
    "iso:country":"ES",
    "sg:address":"Luga Diseminado Matorral, 6",
    "sg:city":"Castillo",
    "sg:orig_category":"Maquinaria Para Industrias Diversas",
    "sg:phone":"+34 928 16 00 41",
    "sg:postcode":"35610",
    "sg:province":"Las Palmas",
    "sg:website":"www.gamalquiler.com",
    "wof:name":"Gam Canarias S.l.",
    "wof:placetype":"venue"
},
  "geometry": {"coordinates":[-13.863199234,28.3980941772],"type":"Point"}
}