{
  "type": "Feature",
  "properties": {
    "iso:country":"ES",
    "sg:address":"Calle de Santa Marta, 43",
    "sg:city":"Aceuchal",
    "sg:orig_category":"Molinos",
    "sg:phone":"+34 924 68 01 28",
    "sg:postcode":"06207",
    "sg:province":"Badajoz",
    "wof:name":"Antonio Franganillo Y Hermanos C.b.",
    "wof:placetype":"venue"
},
  "geometry": {"coordinates":[-6.4915361404,38.6455078125],"type":"Point"}
}