{
  "type": "Feature",
  "properties": {
    "iso:country":"ES",
    "sg:address":"Avda Reyes Catolicos, 4",
    "sg:city":"Baza",
    "sg:orig_category":"Pod\u00d3logos: Pedicuros",
    "sg:phone":"+34 958 86 15 13",
    "sg:postcode":"18800",
    "sg:province":"Granada",
    "wof:name":"Gonzalez Fernandez Antonio Manuel",
    "wof:placetype":"venue"
},
  "geometry": {"coordinates":[-2.7745041847,37.4926147461],"type":"Point"}
}