{
  "type": "Feature",
  "properties": {
    "iso:country":"ES",
    "sg:address":"Carrer de Anselm Clave, 31",
    "sg:city":"Mollet Valles",
    "sg:orig_category":"Lencer\u00cda Femenina, Corseter\u00cda, Trajes De Ba\u00d1o (al Por Menor)",
    "sg:phone":"+34 935 79 03 39",
    "sg:postcode":"08100",
    "sg:province":"Barcelona",
    "wof:name":"L'angora S.c.p.",
    "wof:placetype":"venue"
},
  "geometry": {"coordinates":[2.2151260376,41.5394477844],"type":"Point"}
}