{
  "type": "Feature",
  "properties": {
    "iso:country":"ES",
    "sg:address":"Calle de Bermudez De Castro, 22",
    "sg:city":"Oviedo",
    "sg:orig_category":"Bazares, Art\u00cdculos De Limpieza Y De Cocina (al Por Menor)",
    "sg:phone":"+34 985 28 85 88",
    "sg:postcode":"33011",
    "sg:province":"Asturias",
    "wof:name":"Colunga Garcia Maria Luz",
    "wof:placetype":"venue"
},
  "geometry": {"coordinates":[-5.8380289078,43.3699226379],"type":"Point"}
}