{
  "type": "Feature",
  "properties": {
    "addr:full":"Calle de Zamora, 24 Salamanca Salamanca 37002",
    "addr:housenumber":"24",
    "addr:postcode":"37002",
    "addr:street":"Calle De Zamora",
    "iso:country":"ES",
    "sg:address":"Calle de Zamora, 24",
    "sg:city":"Salamanca",
    "sg:orig_category":"Cl\u00cdnicas Dentales",
    "sg:phone":"+34 923 21 15 06",
    "sg:postcode":"37002",
    "sg:province":"Salamanca",
    "wof:name":"Clinica Dental Salamanca S.l",
    "wof:placetype":"venue"
},
  "geometry": {"coordinates":[-5.6639380455,40.9664726257],"type":"Point"}
}