{
  "type": "Feature",
  "properties": {
    "iso:country":"ES",
    "sg:address":"Calle de General Zuvillaga, 9",
    "sg:city":"Oviedo",
    "sg:orig_category":"Caf\u00c9s, Bares, Cervecer\u00cdas",
    "sg:phone":"+34 985 27 44 02",
    "sg:postcode":"33005",
    "sg:province":"Asturias",
    "wof:name":"Negocios Y Gestion De Hosteleria S.a",
    "wof:placetype":"venue"
},
  "geometry": {"coordinates":[-5.8579268456,43.362197876],"type":"Point"}
}