{
  "type": "Feature",
  "properties": {
    "iso:country":"ES",
    "sg:address":"Calle de Julian De Apraiz, 11",
    "sg:city":"Vitoria-gasteiz",
    "sg:orig_category":"Mec\u00c1nico Del Autom\u00d3vil",
    "sg:phone":"+34 945 24 28 55",
    "sg:postcode":"01012",
    "sg:province":"\u00c1lava",
    "wof:name":"Serviauto Instant S.l.",
    "wof:placetype":"venue"
},
  "geometry": {"coordinates":[-2.6747279167,42.8545074463],"type":"Point"}
}