{
  "type": "Feature",
  "properties": {
    "addr:full":"Calle de Marques De Larios, 7 Malaga M\u00e1laga 29015",
    "addr:housenumber":"7",
    "addr:postcode":"29015",
    "addr:street":"Calle De Marques De Larios;Ma\u0301Laga",
    "iso:country":"ES",
    "sg:address":"Calle de Marques De Larios, 7",
    "sg:city":"Malaga",
    "sg:orig_category":"Panader\u00cdas, Panader\u00cdas",
    "sg:phone":"+34 952 22 62 21",
    "sg:postcode":"29015",
    "sg:province":"M\u00e1laga",
    "wof:name":"Confipanto S.a.",
    "wof:placetype":"venue"
},
  "geometry": {"coordinates":[-4.4213838577,36.7190895081],"type":"Point"}
}