{
  "type": "Feature",
  "properties": {
    "addr:full":"Calle de Padre Javier De Valladolid, 5 Le\u00f3n Le\u00f3n 24005",
    "addr:housenumber":"5",
    "addr:postcode":"24005",
    "addr:street":"Calle De Padre Javier De Valladolid;Leo\u0301N",
    "iso:country":"ES",
    "sg:address":"Calle de Padre Javier De Valladolid, 5",
    "sg:city":"Le\u00f3n",
    "sg:orig_category":"Psic\u00d3logos",
    "sg:phone":"+34 987 21 63 19",
    "sg:postcode":"24005",
    "sg:province":"Le\u00f3n",
    "wof:name":"Allende Alvarez Jose Ramon",
    "wof:placetype":"venue"
},
  "geometry": {"coordinates":[-5.5459785461,42.5785369873],"type":"Point"}
}