{
  "type": "Feature",
  "properties": {
    "addr:full":"Calle de Fuenterrabia, 1 Irun Guip\u00f9zcoa 20301",
    "addr:housenumber":"1",
    "addr:postcode":"20301",
    "addr:street":"Calle De Fuenterrabia;Guipu\u0300Zcoa",
    "iso:country":"ES",
    "sg:address":"Calle de Fuenterrabia, 1",
    "sg:city":"Irun",
    "sg:orig_category":"Delegados, Agentes De Tr\u00c1nsito, Auxiliares De Transporte Internacional",
    "sg:phone":"+34 943 61 58 37",
    "sg:postcode":"20301",
    "sg:province":"Guip\u00f9zcoa",
    "wof:name":"Lautrans S.l.",
    "wof:placetype":"venue"
},
  "geometry": {"coordinates":[-1.7895462513,43.3637886047],"type":"Point"}
}