{
  "type": "Feature",
  "properties": {
    "addr:full":"Mercat Guineueta, S/n Barcelona Barcelona 08016",
    "addr:housenumber":"s / n",
    "addr:postcode":"08016",
    "iso:country":"ES",
    "sg:address":"Mercat Guineueta, S/n",
    "sg:city":"Barcelona",
    "sg:orig_category":"Carnicer\u00cdas, Carnicer\u00cdas",
    "sg:phone":"+34 933 59 50 85",
    "sg:postcode":"08016",
    "sg:province":"Barcelona",
    "wof:name":"Franco Busquets Vicente",
    "wof:placetype":"venue"
},
  "geometry": {"coordinates":[2.1666939259,41.4401321411],"type":"Point"}
}