{
  "type": "Feature",
  "properties": {
    "addr:full":"Avda Jesus Morante Borras, 121 Valencia Valencia 46012",
    "addr:housenumber":"121",
    "addr:postcode":"46012",
    "addr:street":"Avda Jesus Morante Borras",
    "iso:country":"ES",
    "sg:address":"Avda Jesus Morante Borras, 121",
    "sg:city":"Valencia",
    "sg:orig_category":"Limpieza Industrial",
    "sg:phone":"+34 963 67 11 71",
    "sg:postcode":"46012",
    "sg:province":"Valencia",
    "wof:name":"Romeu Iba\u00f1ez Fernando",
    "wof:placetype":"venue"
},
  "geometry": {"coordinates":[-0.3436610103,39.4453163147],"type":"Point"}
}