{
  "type": "Feature",
  "properties": {
    "iso:country":"ES",
    "sg:address":"Calle de Orzan, 130",
    "sg:city":"Coru\u00d1a",
    "sg:orig_category":"Venta, Instalaci\u00d3n De Cocinas",
    "sg:phone":"+34 981 22 04 21",
    "sg:postcode":"15003",
    "sg:province":"La Coru\u00f1a",
    "wof:name":"Montes Matos Gerardo Antonio",
    "wof:placetype":"venue"
},
  "geometry": {"coordinates":[-8.4041595459,43.3700180054],"type":"Point"}
}