{
  "type": "Feature",
  "properties": {
    "iso:country":"ES",
    "sg:address":"Av Torre D'en Mateu, 66",
    "sg:city":"Barbera Valles",
    "sg:orig_category":"Negocio De Madera",
    "sg:phone":"+34 937 29 23 95",
    "sg:postcode":"08210",
    "sg:province":"Barcelona",
    "wof:name":"Fustes Castella S.l.",
    "wof:placetype":"venue"
},
  "geometry": {"coordinates":[2.1700499058,41.3857192993],"type":"Point"}
}