{
  "type": "Feature",
  "properties": {
    "addr:full":"Pl Fius I Pala, 1 Manresa Barcelona 08241",
    "addr:postcode":"08241",
    "addr:street":"Pl Fius I Pala",
    "iso:country":"ES",
    "sg:address":"Pl Fius I Pala, 1",
    "sg:city":"Manresa",
    "sg:orig_category":"Notarios",
    "sg:phone":"+34 938 76 80 85",
    "sg:postcode":"08241",
    "sg:province":"Barcelona",
    "wof:name":"Nielles Sanchez Alexandre",
    "wof:placetype":"venue"
},
  "geometry": {"coordinates":[1.8241080046,41.7246360779],"type":"Point"}
}