{
  "type": "Feature",
  "properties": {
    "addr:full":"Calle de Chopo (del), 107 Molinos Madrid 28460",
    "addr:housenumber":"107",
    "addr:postcode":"28460",
    "addr:street":"Calle De Chopo Del",
    "iso:country":"ES",
    "sg:address":"Calle de Chopo (del), 107",
    "sg:city":"Molinos",
    "sg:orig_category":"Fotograf\u00cda Art\u00cdstica Y Retratos",
    "sg:phone":"+34 918 55 15 82",
    "sg:postcode":"28460",
    "sg:province":"Madrid",
    "sg:website":"www.ferfoto.es",
    "wof:name":"Garcia Benavent Eva",
    "wof:placetype":"venue"
},
  "geometry": {"coordinates":[-4.0806593895,40.7239151001],"type":"Point"}
}