{
  "type": "Feature",
  "properties": {
    "addr:full":"Calle de Mayor, S/n Blecua Huesca 22133",
    "addr:housenumber":"s / n",
    "addr:postcode":"22133",
    "addr:street":"Calle De Mayor",
    "iso:country":"ES",
    "sg:address":"Calle de Mayor, S/n",
    "sg:city":"Blecua",
    "sg:orig_category":"Museos",
    "sg:phone":"+34 974 26 01 50",
    "sg:postcode":"22133",
    "sg:province":"Huesca",
    "wof:name":"Ayuntamiento",
    "wof:placetype":"venue"
},
  "geometry": {"coordinates":[-0.1877489984,42.0571556091],"type":"Point"}
}