{
  "type": "Feature",
  "properties": {
    "iso:country":"ES",
    "sg:address":"Calle de Marques De La Valdavia (del), 98",
    "sg:city":"Alcobendas",
    "sg:orig_category":"Aparatos De Iluminaci\u00d3n (al Por Menor)",
    "sg:phone":"+34 916 54 03 48",
    "sg:postcode":"28100",
    "sg:province":"Madrid",
    "wof:name":"Luz Actual S.l.",
    "wof:placetype":"venue"
},
  "geometry": {"coordinates":[-3.6470780373,40.5464477539],"type":"Point"}
}