{
  "type": "Feature",
  "properties": {
    "addr:full":"Calle de Doctor Nacher, 60 Chiva Valencia 46370",
    "addr:housenumber":"60",
    "addr:postcode":"46370",
    "addr:street":"Calle De Doctor Nacher",
    "iso:country":"ES",
    "sg:address":"Calle de Doctor Nacher, 60",
    "sg:city":"Chiva",
    "sg:orig_category":"Asesor\u00cda Fiscal Y Jur\u00cddica",
    "sg:phone":"+34 962 52 05 04",
    "sg:postcode":"46370",
    "sg:province":"Valencia",
    "wof:name":"Villalba Mora S.l.",
    "wof:placetype":"venue"
},
  "geometry": {"coordinates":[-0.7168470025,39.4711914062],"type":"Point"}
}