{
  "type": "Feature",
  "properties": {
    "addr:full":"Calle de Hemingway, 1 Malaga M\u00e1laga 29004",
    "addr:housenumber":"1",
    "addr:postcode":"29004",
    "addr:street":"Calle De Hemingway;Ma\u0301Laga",
    "iso:country":"ES",
    "sg:address":"Calle de Hemingway, 1",
    "sg:city":"Malaga",
    "sg:orig_category":"Inmobiliaria (agencias)",
    "sg:phone":"+34 952 24 04 00",
    "sg:postcode":"29004",
    "sg:province":"M\u00e1laga",
    "wof:name":"Max-frio S.l.",
    "wof:placetype":"venue"
},
  "geometry": {"coordinates":[-4.4725193977,36.6868896484],"type":"Point"}
}