{
  "type": "Feature",
  "properties": {
    "iso:country":"ES",
    "sg:address":"Calle de Gainza, S/n",
    "sg:city":"Madrid",
    "sg:orig_category":"Asociaciones Y Clubs Deportivos",
    "sg:phone":"+34 913 41 83 28",
    "sg:postcode":"28041",
    "sg:province":"Madrid",
    "wof:name":"Club Deportivo Alzola",
    "wof:placetype":"venue"
},
  "geometry": {"coordinates":[-3.7187390327,40.3700752258],"type":"Point"}
}