{
  "type": "Feature",
  "properties": {
    "addr:full":"Calle de Perdomo, 33 Palmas De Gran Canaria Las Palmas 35002",
    "addr:housenumber":"33",
    "addr:postcode":"35002",
    "addr:street":"Calle De Perdomo",
    "iso:country":"ES",
    "sg:address":"Calle de Perdomo, 33",
    "sg:city":"Palmas De Gran Canaria",
    "sg:orig_category":"Telas Para Tapizar, Cortinas, Pasamaner\u00cda (fabricaci\u00d3n, Al Por Mayor)",
    "sg:phone":"+34 928 36 41 87",
    "sg:postcode":"35002",
    "sg:province":"Las Palmas",
    "wof:name":"Medina Brito Juan Vidal",
    "wof:placetype":"venue"
},
  "geometry": {"coordinates":[-15.4178466797,28.1061935425],"type":"Point"}
}