{
  "type": "Feature",
  "properties": {
    "addr:full":"Calle de Do\u00d1a Marina, 4 Sonseca Toledo 45100",
    "addr:housenumber":"4",
    "addr:postcode":"45100",
    "addr:street":"Calle De Don\u0303A Marina",
    "iso:country":"ES",
    "sg:address":"Calle de Do\u00d1a Marina, 4",
    "sg:city":"Sonseca",
    "sg:orig_category":"Panader\u00cdas, Panader\u00cdas",
    "sg:phone":"+34 925 38 02 67",
    "sg:postcode":"45100",
    "sg:province":"Toledo",
    "wof:name":"Garcia De Blas Rodriguez Angel",
    "wof:placetype":"venue"
},
  "geometry": {"coordinates":[-3.9775168896,39.6787643433],"type":"Point"}
}