{
  "type": "Feature",
  "properties": {
    "iso:country":"ES",
    "sg:address":"Trva Reyes Catolicos, 11",
    "sg:city":"Ponferrada",
    "sg:orig_category":"Chapister\u00cda",
    "sg:phone":"+34 987 41 12 74",
    "sg:postcode":"24400",
    "sg:province":"Le\u00f3n",
    "wof:name":"Fernandez Garcia Ernesto",
    "wof:placetype":"venue"
},
  "geometry": {"coordinates":[-6.5996961594,42.4982566833],"type":"Point"}
}