{
  "type": "Feature",
  "properties": {
    "addr:full":"Carrer de Madrazo, 33 Barcelona Barcelona 08006",
    "addr:housenumber":"33",
    "addr:postcode":"08006",
    "addr:street":"Carrer De Madrazo",
    "iso:country":"ES",
    "sg:address":"Carrer de Madrazo, 33",
    "sg:city":"Barcelona",
    "sg:orig_category":"Abogados",
    "sg:phone":"+34 934 15 06 77",
    "sg:postcode":"08006",
    "sg:province":"Barcelona",
    "sg:website":"www.domenechmascaro.com",
    "wof:name":"Domenech Advocats, Scp",
    "wof:placetype":"venue"
},
  "geometry": {"coordinates":[2.149422884,41.4003753662],"type":"Point"}
}