{
  "type": "Feature",
  "properties": {
    "addr:full":"Calle de Jovellanos, 12 Pravia Asturias 33120",
    "addr:housenumber":"12",
    "addr:postcode":"33120",
    "addr:street":"Calle De Jovellanos",
    "iso:country":"ES",
    "sg:address":"Calle de Jovellanos, 12",
    "sg:city":"Pravia",
    "sg:orig_category":"Asesor\u00cda De Formaci\u00d3n Y Gesti\u00d3n De Personal",
    "sg:phone":"+34 985 82 01 59",
    "sg:postcode":"33120",
    "sg:province":"Asturias",
    "wof:name":"Diaz Suarez Jose Ramon",
    "wof:placetype":"venue"
},
  "geometry": {"coordinates":[-6.1137018204,43.4902801514],"type":"Point"}
}