{
  "type": "Feature",
  "properties": {
    "addr:full":"Avda Boliches De Los, S/n Fuengirola M\u00e1laga 29640",
    "addr:postcode":"29640",
    "addr:street":"Avda Boliches De Los S / N;Ma\u0301Laga",
    "iso:country":"ES",
    "sg:address":"Avda Boliches De Los, S/n",
    "sg:city":"Fuengirola",
    "sg:orig_category":"Bancos",
    "sg:phone":"+34 952 58 16 02",
    "sg:postcode":"29640",
    "sg:province":"M\u00e1laga",
    "sg:website":"www.bancozaragozano.es",
    "wof:name":"Barclays Bank S.a.e.",
    "wof:placetype":"venue"
},
  "geometry": {"coordinates":[-4.6134839058,36.5549163818],"type":"Point"}
}