{
  "type": "Feature",
  "properties": {
    "addr:full":"Urune, 35 Lezo Guip\u00f9zcoa 20100",
    "addr:housenumber":"35",
    "addr:postcode":"20100",
    "addr:street":"Urune;Guipu\u0300Zcoa",
    "iso:country":"ES",
    "sg:address":"Urune, 35",
    "sg:city":"Lezo",
    "sg:orig_category":"Ambulancias",
    "sg:phone":"+34 902 15 04 04",
    "sg:postcode":"20100",
    "sg:province":"Guip\u00f9zcoa",
    "sg:website":"www.larrialiak-grupo.com",
    "wof:name":"Ambulancias Larrialdiak S.coop.",
    "wof:placetype":"venue"
},
  "geometry": {"coordinates":[-1.8726514578,43.3278617859],"type":"Point"}
}