{
  "type": "Feature",
  "properties": {
    "iso:country":"ES",
    "sg:address":"Luga Prado, S/n",
    "sg:city":"Siete Iglesias De Trabancos",
    "sg:orig_category":"Cooperativas Agr\u00cdcolas",
    "sg:phone":"+34 983 81 61 02",
    "sg:postcode":"47511",
    "sg:province":"Valladolid",
    "wof:name":"Cooperativa Del Campo San Pelayo",
    "wof:placetype":"venue"
},
  "geometry": {"coordinates":[-5.1825971603,41.3519973755],"type":"Point"}
}