{
  "type": "Feature",
  "properties": {
    "iso:country":"ES",
    "sg:address":"Plaz Ss.mm. Los Reyes De Espa\u00d1a, 8",
    "sg:city":"Benidorm",
    "sg:orig_category":"Alimentaci\u00d3n General (al Por Menor)",
    "sg:phone":"+34 965 85 41 75",
    "sg:postcode":"03500",
    "sg:province":"Alicante",
    "wof:name":"Berenguer Domenech Juan",
    "wof:placetype":"venue"
},
  "geometry": {"coordinates":[-0.1743289977,38.5408058167],"type":"Point"}
}