{
  "type": "Feature",
  "properties": {
    "addr:full":"Carrer de Doctor Antoni Pujadas, 2 S. Boi Llobregat Barcelona 08830",
    "addr:housenumber":"2",
    "addr:postcode":"08830",
    "addr:street":"Carrer De Doctor Antoni Pujadas",
    "iso:country":"ES",
    "sg:address":"Carrer de Doctor Antoni Pujadas, 2",
    "sg:city":"S. Boi Llobregat",
    "sg:orig_category":"Molduras, Junquillos, Listones Y Molduras Perforadas",
    "sg:phone":"+34 936 54 67 05",
    "sg:postcode":"08830",
    "sg:province":"Barcelona",
    "wof:name":"Vizcaino Torres S. L.",
    "wof:placetype":"venue"
},
  "geometry": {"coordinates":[2.0396726131,41.3486251831],"type":"Point"}
}