{
  "type": "Feature",
  "properties": {
    "iso:country":"ES",
    "sg:address":"Avda Euro, 2",
    "sg:city":"Valladolid",
    "sg:classifiers":[
        {
            "category":"Taxi",
            "type":"Transportation"
        }
    ],
    "sg:phone":"+34 983 29 14 44",
    "sg:postcode":"47009",
    "sg:province":"Valladolid",
    "wof:name":"Sociedad Cooperativa Limitada Radio-taxi Valladolid",
    "wof:placetype":"venue"
},
  "geometry": {"coordinates":[-4.7380590439,41.6613121033],"type":"Point"}
}