{
  "type": "Feature",
  "properties": {
    "iso:country":"ES",
    "sg:address":"Calle de Zamacola, 132",
    "sg:city":"Bilbao",
    "sg:orig_category":"Pintura Y Barniz (al Por Menor)",
    "sg:phone":"+34 944 79 22 72",
    "sg:postcode":"48003",
    "sg:province":"Vizcaya",
    "wof:name":"La Pe\u00f1a Color S.l.",
    "wof:placetype":"venue"
},
  "geometry": {"coordinates":[-2.9249269962,43.2415084839],"type":"Point"}
}