{
  "type": "Feature",
  "properties": {
    "iso:country":"ES",
    "sg:address":"Calle de Antonio Lopez, 57",
    "sg:city":"Madrid",
    "sg:orig_category":"Bisuter\u00cda, Joyer\u00cda, Relojer\u00cda (al Por Menor)",
    "sg:phone":"+34 914 60 67 25",
    "sg:postcode":"28019",
    "sg:province":"Madrid",
    "wof:name":"Garcia Campelo Fulgencio",
    "wof:placetype":"venue"
},
  "geometry": {"coordinates":[-3.7090895176,40.3945617676],"type":"Point"}
}