{
  "type": "Feature",
  "properties": {
    "iso:country":"ES",
    "sg:address":"Calle de Colon De Larreategui, 13",
    "sg:city":"Bilbao",
    "sg:orig_category":"Asilos De Ancianos. Centros Privados",
    "sg:phone":"+34 944 24 06 50",
    "sg:postcode":"48001",
    "sg:province":"Vizcaya",
    "wof:name":"Anton Gomez Margarita",
    "wof:placetype":"venue"
},
  "geometry": {"coordinates":[-2.9285120964,43.2626571655],"type":"Point"}
}