{
  "type": "Feature",
  "properties": {
    "iso:country":"ES",
    "sg:address":"Calle de San Clemente, 13",
    "sg:city":"Jaen",
    "sg:orig_category":"Ropa Para Caballeros (al Por Menor)",
    "sg:phone":"+34 953 24 34 29",
    "sg:postcode":"23003",
    "sg:province":"Ja\u00e9n",
    "sg:website":"www.spf.com",
    "wof:name":"Cortefiel S.a.",
    "wof:placetype":"venue"
},
  "geometry": {"coordinates":[-3.7891368866,37.7683143616],"type":"Point"}
}