{
  "type": "Feature",
  "properties": {
    "addr:full":"Estd Abaro, 8 Bilbao Vizcaya 48013",
    "addr:housenumber":"8",
    "addr:postcode":"48013",
    "addr:street":"Abaro",
    "iso:country":"ES",
    "sg:address":"Estd Abaro, 8",
    "sg:city":"Bilbao",
    "sg:orig_category":"Comerciantes Al Por Mayor De Vinos, Licores Y Alcoholes",
    "sg:phone":"+34 944 82 00 89",
    "sg:postcode":"48013",
    "sg:province":"Vizcaya",
    "wof:name":"Luzuriaga Sanchez Amaya",
    "wof:placetype":"venue"
},
  "geometry": {"coordinates":[-2.9727919102,43.27602005],"type":"Point"}
}