{
  "type": "Feature",
  "properties": {
    "iso:country":"ES",
    "sg:address":"Cra. Fran\u00e7a, Km. 0182,0",
    "sg:city":"Bossost",
    "sg:orig_category":"Zonas De Acampada, Aparcamiento Para Caravanas",
    "sg:phone":"+34 973 64 83 10",
    "sg:postcode":"25550",
    "sg:province":"Lleida",
    "wof:name":"Lema Nu\u00f1ez Fidel",
    "wof:placetype":"venue"
},
  "geometry": {"coordinates":[0.6915392876,42.7787971497],"type":"Point"}
}