{
  "type": "Feature",
  "properties": {
    "iso:country":"ES",
    "sg:address":"Calle de Antonio Maura, 1",
    "sg:city":"Cordoba",
    "sg:orig_category":"Procuradores",
    "sg:phone":"+34 957 23 27 04",
    "sg:postcode":"14004",
    "sg:province":"C\u00f3rdoba",
    "wof:name":"Timoteo Castiel Eva Maria",
    "wof:placetype":"venue"
},
  "geometry": {"coordinates":[-4.7871108055,37.882976532],"type":"Point"}
}