{
  "type": "Feature",
  "properties": {
    "iso:country":"ES",
    "sg:address":"Calle de Pilar, 11",
    "sg:city":"Hinojosa Del Duque",
    "sg:orig_category":"Fabricaci\u00d3n De Quesos",
    "sg:phone":"+34 957 14 04 59",
    "sg:postcode":"14270",
    "sg:province":"C\u00f3rdoba",
    "wof:name":"Casimiro Molera S.l.",
    "wof:placetype":"venue"
},
  "geometry": {"coordinates":[-5.1391348839,38.4930343628],"type":"Point"}
}