{
  "type": "Feature",
  "properties": {
    "iso:country":"ES",
    "sg:address":"Carr Institut (de L'), 30",
    "sg:city":"Agramunt",
    "sg:orig_category":"Empresas De Pintura Y Revestimientos",
    "sg:phone":"+34 973 39 24 40",
    "sg:postcode":"25310",
    "sg:province":"Lleida",
    "wof:name":"Pacitti  Massimo",
    "wof:placetype":"venue"
},
  "geometry": {"coordinates":[1.097990036,41.7824821472],"type":"Point"}
}