{
  "type": "Feature",
  "properties": {
    "addr:full":"Carr Sant Maximia, 3 Blanes Girona 17300",
    "addr:housenumber":"3",
    "addr:postcode":"17300",
    "addr:street":"Carr Sant Maximia",
    "iso:country":"ES",
    "sg:address":"Carr Sant Maximia, 3",
    "sg:city":"Blanes",
    "sg:orig_category":"Carnicer\u00cdas, Carnicer\u00cdas",
    "sg:phone":"+34 972 33 59 03",
    "sg:postcode":"17300",
    "sg:province":"Girona",
    "wof:name":"Raya Troya Pedro",
    "wof:placetype":"venue"
},
  "geometry": {"coordinates":[2.7859210968,41.6704330444],"type":"Point"}
}