{
  "type": "Feature",
  "properties": {
    "iso:country":"ES",
    "sg:address":"Calle de Ca\u00d1ada, 2",
    "sg:city":"Madrid",
    "sg:orig_category":"Molduras, Junquillos, Listones Y Molduras Perforadas",
    "sg:phone":"+34 913 05 05 92",
    "sg:postcode":"28030",
    "sg:province":"Madrid",
    "wof:name":"Villalba Escobedo Rosa Norcidia",
    "wof:placetype":"venue"
},
  "geometry": {"coordinates":[-3.6442530155,40.40366745],"type":"Point"}
}