{
  "type": "Feature",
  "properties": {
    "iso:country":"ES",
    "sg:address":"Rua Republica De El Salvador (da), 22",
    "sg:city":"Santiago De Compostela",
    "sg:orig_category":"Loter\u00cda Y T\u00d3mbola",
    "sg:phone":"+34 981 59 59 60",
    "sg:postcode":"15701",
    "sg:province":"La Coru\u00f1a",
    "wof:name":"Cortizo Reino Francisco Javier",
    "wof:placetype":"venue"
},
  "geometry": {"coordinates":[-8.5477819443,42.8746299744],"type":"Point"}
}