{
  "type": "Feature",
  "properties": {
    "iso:country":"ES",
    "sg:address":"Calle de Union Mercantil La, 38",
    "sg:city":"Malaga",
    "sg:orig_category":"Ingeniero",
    "sg:phone":"+34 952 24 03 96",
    "sg:postcode":"29004",
    "sg:province":"M\u00e1laga",
    "wof:name":"Perez De Vargas Rubio Francisco Adrian",
    "wof:placetype":"venue"
},
  "geometry": {"coordinates":[-4.4513020515,36.686794281],"type":"Point"}
}