{
  "type": "Feature",
  "properties": {
    "addr:full":"Calle de Garcia Andreu, 49 Alacant Alicante 03007",
    "addr:housenumber":"49",
    "addr:postcode":"03007",
    "addr:street":"Calle De Garcia Andreu",
    "iso:country":"ES",
    "sg:address":"Calle de Garcia Andreu, 49",
    "sg:city":"Alacant",
    "sg:orig_category":"Administradores De Bienes Y Delegados De Comunidades De Propietarios",
    "sg:phone":"+34 965 12 07 76",
    "sg:postcode":"03007",
    "sg:province":"Alicante",
    "wof:name":"Clemente Garcia Felix",
    "wof:placetype":"venue"
},
  "geometry": {"coordinates":[-0.4962829947,38.3403434753],"type":"Point"}
}