{
  "type": "Feature",
  "properties": {
    "iso:country":"ES",
    "sg:address":"Calle de Juan Xxiii, 11",
    "sg:city":"Hellin",
    "sg:orig_category":"Molduras, Junquillos, Listones Y Molduras Perforadas",
    "sg:phone":"+34 967 30 01 04",
    "sg:postcode":"02400",
    "sg:province":"Albacete",
    "wof:name":"Lopez Sanchez Domingo",
    "wof:placetype":"venue"
},
  "geometry": {"coordinates":[-1.701004982,38.5102577209],"type":"Point"}
}