{
  "type": "Feature",
  "properties": {
    "addr:full":"Pg Verdaguer, 18 Igualada Barcelona 08700",
    "addr:housenumber":"18",
    "addr:postcode":"08700",
    "addr:street":"Pg Verdaguer",
    "iso:country":"ES",
    "sg:address":"Pg Verdaguer, 18",
    "sg:city":"Igualada",
    "sg:orig_category":"Grafistas",
    "sg:phone":"+34 938 05 24 64",
    "sg:postcode":"08700",
    "sg:province":"Barcelona",
    "sg:website":"www.pepvalls.com",
    "wof:name":"Pep Valls Estudi S.l.",
    "wof:placetype":"venue"
},
  "geometry": {"coordinates":[1.6161830425,41.5835914612],"type":"Point"}
}