{
  "type": "Feature",
  "properties": {
    "iso:country":"ES",
    "sg:address":"Carrer de Aigo Dol\u00c7a (s'), 2",
    "sg:city":"Palma",
    "sg:orig_category":"Molduras, Junquillos, Listones Y Molduras Perforadas",
    "sg:phone":"+34 971 73 14 74",
    "sg:postcode":"07014",
    "sg:province":"Islas Baleares",
    "wof:name":"Juan Cantallops Juan",
    "wof:placetype":"venue"
},
  "geometry": {"coordinates":[2.6271600723,39.5652084351],"type":"Point"}
}