{
  "type": "Feature",
  "properties": {
    "addr:full":"Calle de Bidebarri, 8 Algorta Vizcaya 48991",
    "addr:housenumber":"8",
    "addr:postcode":"48991",
    "addr:street":"Calle De Bidebarri",
    "iso:country":"ES",
    "sg:address":"Calle de Bidebarri, 8",
    "sg:city":"Algorta",
    "sg:classifiers":[
        {
            "category":"Professional",
            "subcategory":"Management & Consulting",
            "type":"Services"
        }
    ],
    "sg:phone":"+34 944 31 90 55",
    "sg:postcode":"48991",
    "sg:province":"Vizcaya",
    "sg:tags":[
        "asesor\u00cda",
        "en",
        "marketing"
    ],
    "wof:name":"Zertegi 2000 S.l.",
    "wof:placetype":"venue"
},
  "geometry": {"coordinates":[-3.0084810257,43.352684021],"type":"Point"}
}