{
  "type": "Feature",
  "properties": {
    "addr:full":"Carrer de Sant Rafel, 22 Olot Girona 17800",
    "addr:housenumber":"22",
    "addr:postcode":"17800",
    "addr:street":"Carrer De Sant Rafel",
    "iso:country":"ES",
    "sg:address":"Carrer de Sant Rafel, 22",
    "sg:city":"Olot",
    "sg:orig_category":"Ropa Para Caballeros (al Por Menor)",
    "sg:phone":"+34 972 27 68 00",
    "sg:postcode":"17800",
    "sg:province":"Girona",
    "wof:name":"Tarres Fluvia S.l.",
    "wof:placetype":"venue"
},
  "geometry": {"coordinates":[2.4868218899,42.1815757751],"type":"Point"}
}