{
  "type": "Feature",
  "properties": {
    "iso:country":"ES",
    "sg:address":"Ctra Ronda (de), 151",
    "sg:city":"Almeria",
    "sg:orig_category":"Agentes Generales De Seguros",
    "sg:phone":"+34 950 17 00 21",
    "sg:postcode":"04004",
    "sg:province":"Almer\u00eda",
    "wof:name":"Martinez Camacho Jose Antonio",
    "wof:placetype":"venue"
},
  "geometry": {"coordinates":[-2.4564709663,36.8360519409],"type":"Point"}
}