{
  "type": "Feature",
  "properties": {
    "iso:country":"ES",
    "sg:address":"Calle de Luis Montoto, 105",
    "sg:city":"Sevilla",
    "sg:orig_category":"Ropa Para Se\u00d1oras (al Por Menor)",
    "sg:phone":"+34 954 57 19 37",
    "sg:postcode":"41007",
    "sg:province":"Sevilla",
    "wof:name":"Zubiri Bayon Maria Bella",
    "wof:placetype":"venue"
},
  "geometry": {"coordinates":[-5.9707369804,37.3874664307],"type":"Point"}
}