{
  "type": "Feature",
  "properties": {
    "addr:full":"Calle de Alcornoque, 16 Badajoz Badajoz 06011",
    "addr:housenumber":"16",
    "addr:postcode":"06011",
    "addr:street":"Calle De Alcornoque",
    "iso:country":"ES",
    "sg:address":"Calle de Alcornoque, 16",
    "sg:city":"Badajoz",
    "sg:orig_category":"Fabricaci\u00d3n De Muebles",
    "sg:phone":"+34 924 26 26 23",
    "sg:postcode":"06011",
    "sg:province":"Badajoz",
    "sg:website":"www.ebanisterialinoarroyo.com",
    "wof:name":"Arroyo Rueda Lino",
    "wof:placetype":"venue"
},
  "geometry": {"coordinates":[-6.990758419,38.8569107056],"type":"Point"}
}