{
  "type": "Feature",
  "properties": {
    "iso:country":"ES",
    "sg:address":"Pg Vall D'hebron, 208",
    "sg:city":"Barcelona",
    "sg:orig_category":"Asociaciones Humanitarias, De Cooperaci\u00d3n, De Acci\u00d3n Social",
    "sg:phone":"+34 934 27 12 53",
    "sg:postcode":"08035",
    "sg:province":"Barcelona",
    "wof:name":"Asociacion De Padres De Ni\u00f1os Con Cancer De Baleares",
    "wof:placetype":"venue"
},
  "geometry": {"coordinates":[2.1458377838,41.4316520691],"type":"Point"}
}