{
  "type": "Feature",
  "properties": {
    "addr:full":"Rond Sant Pere, 52 Barcelona Barcelona 08010",
    "addr:housenumber":"52",
    "addr:postcode":"08010",
    "addr:street":"Sant Pere",
    "iso:country":"ES",
    "sg:address":"Rond Sant Pere, 52",
    "sg:city":"Barcelona",
    "sg:orig_category":"Abogados Especialistas En Derecho Penal",
    "sg:phone":"+34 932 68 32 66",
    "sg:postcode":"08010",
    "sg:province":"Barcelona",
    "wof:name":"Centre De Telecomunicaciones De Catalunya",
    "wof:placetype":"venue"
},
  "geometry": {"coordinates":[2.176707983,41.3903007507],"type":"Point"}
}