{
  "type": "Feature",
  "properties": {
    "iso:country":"ES",
    "sg:address":"Calle de Buenos Aires, 21",
    "sg:city":"Alberca De Las Torres",
    "sg:orig_category":"M\u00c9dicos: Cirug\u00cda Ortop\u00c9dica Y Traumatolog\u00cda",
    "sg:phone":"+34 968 84 17 27",
    "sg:postcode":"30150",
    "sg:province":"Murcia",
    "wof:name":"Hernandez Cabrera Jose Antonio",
    "wof:placetype":"venue"
},
  "geometry": {"coordinates":[-1.1403268576,37.9367446899],"type":"Point"}
}