{
  "type": "Feature",
  "properties": {
    "addr:full":"Pase Zorrilla, 352 Valladolid Valladolid 47008",
    "addr:housenumber":"352",
    "addr:postcode":"47008",
    "addr:street":"Zorrilla",
    "iso:country":"ES",
    "sg:address":"Pase Zorrilla, 352",
    "sg:city":"Valladolid",
    "sg:orig_category":"Muebles Y Accesorios Para Cocinas Y Cuartos De Ba\u00d1o (al Por Menor)",
    "sg:phone":"+34 983 24 59 39",
    "sg:postcode":"47008",
    "sg:province":"Valladolid",
    "wof:name":"Sanalmen S.l.",
    "wof:placetype":"venue"
},
  "geometry": {"coordinates":[-4.7485032082,41.6181335449],"type":"Point"}
}