{
  "type": "Feature",
  "properties": {
    "addr:full":"Calle de Noguera, 22 Valencia Valencia 46023",
    "addr:housenumber":"22",
    "addr:postcode":"46023",
    "addr:street":"Calle De Noguera",
    "iso:country":"ES",
    "sg:address":"Calle de Noguera, 22",
    "sg:city":"Valencia",
    "sg:orig_category":"Rectificaci\u00d3n, Mecanizado, Fresado",
    "sg:phone":"+34 963 30 87 57",
    "sg:postcode":"46023",
    "sg:province":"Valencia",
    "wof:name":"Mecanismos Tecnicos Y De Laboratirio S.l.",
    "wof:placetype":"venue"
},
  "geometry": {"coordinates":[-0.3426569998,39.4606895447],"type":"Point"}
}