{
  "type": "Feature",
  "properties": {
    "addr:full":"Carr Nord, 12 Mao Islas Baleares 07702",
    "addr:housenumber":"12",
    "addr:postcode":"07702",
    "addr:street":"Carr Nord",
    "iso:country":"ES",
    "sg:address":"Carr Nord, 12",
    "sg:city":"Mao",
    "sg:orig_category":"Abogados",
    "sg:phone":"+34 971 35 21 46",
    "sg:postcode":"07702",
    "sg:province":"Islas Baleares",
    "wof:name":"Abogados Asociados Caballero La Fuente Y Mercadal S.c.",
    "wof:placetype":"venue"
},
  "geometry": {"coordinates":[4.265767,39.887924],"type":"Point"}
}