{
  "type": "Feature",
  "properties": {
    "iso:country":"ES",
    "sg:address":"Carrer de Proven\u00c7a, 216",
    "sg:city":"Barcelona",
    "sg:classifiers":[
        {
            "category":"Professional",
            "subcategory":"Research",
            "type":"Services"
        }
    ],
    "sg:phone":"+34 934 54 81 62",
    "sg:postcode":"08036",
    "sg:province":"Barcelona",
    "sg:tags":[
        "mercado",
        "de",
        "estudios"
    ],
    "sg:website":"www.iberinform.es",
    "wof:name":"Iberinform Internacional S. A.",
    "wof:placetype":"venue"
},
  "geometry": {"coordinates":[2.1561629772,41.390537262],"type":"Point"}
}