{
  "type": "Feature",
  "properties": {
    "iso:country":"ES",
    "sg:address":"Calle de Franco Y Lopez, 18",
    "sg:city":"Zaragoza",
    "sg:orig_category":"Molduras, Junquillos, Listones Y Molduras Perforadas",
    "sg:phone":"+34 976 35 67 09",
    "sg:postcode":"50005",
    "sg:province":"Zaragoza",
    "wof:name":"Palomino E Hijo S.c.",
    "wof:placetype":"venue"
},
  "geometry": {"coordinates":[-0.9008949995,41.6467628479],"type":"Point"}
}