{
  "type": "Feature",
  "properties": {
    "addr:full":"Carrer de Joan Salvado I Voltas (de), 4 Vila-seca Tarragona 43480",
    "addr:housenumber":"4",
    "addr:postcode":"43480",
    "addr:street":"Carrer De Joan Salvado I Voltas De",
    "iso:country":"ES",
    "sg:address":"Carrer de Joan Salvado I Voltas (de), 4",
    "sg:city":"Vila-seca",
    "sg:orig_category":"Peluquer\u00cdas, Peluquer\u00cda Mixta",
    "sg:phone":"+34 977 39 17 23",
    "sg:postcode":"43480",
    "sg:province":"Tarragona",
    "wof:name":"Angullo Arias Luis",
    "wof:placetype":"venue"
},
  "geometry": {"coordinates":[1.1438424587,41.1115493774],"type":"Point"}
}