{
  "type": "Feature",
  "properties": {
    "iso:country":"ES",
    "sg:address":"Presb\u00edtero Vidaurreta, S/n",
    "sg:city":"Antequera",
    "sg:orig_category":"Universidades",
    "sg:phone":"+34 952 84 28 81",
    "sg:postcode":"29200",
    "sg:province":"M\u00e1laga",
    "wof:name":"Fundacion Maria Inmaculada",
    "wof:placetype":"venue"
},
  "geometry": {"coordinates":[-4.5637841225,37.0218048096],"type":"Point"}
}