{
  "type": "Feature",
  "properties": {
    "iso:country":"ES",
    "sg:address":"Major, 88",
    "sg:city":"Sarria Ter",
    "sg:orig_category":"Cajas De Ahorro",
    "sg:phone":"+34 972 17 16 00",
    "sg:postcode":"17840",
    "sg:province":"Girona",
    "sg:website":"www.caixadecatalunya.es",
    "wof:name":"Caixa D'estalvis De Catalunya",
    "wof:placetype":"venue"
},
  "geometry": {"coordinates":[2.8253400326,42.0173683167],"type":"Point"}
}