{
  "type": "Feature",
  "properties": {
    "iso:country":"ES",
    "sg:address":"Carrer de Loreto, 54",
    "sg:city":"Barcelona",
    "sg:orig_category":"Arquitectos",
    "sg:phone":"+34 933 21 97 31",
    "sg:postcode":"08029",
    "sg:province":"Barcelona",
    "wof:name":"Rovira-beleta Cuyas Enrique",
    "wof:placetype":"venue"
},
  "geometry": {"coordinates":[2.1427910328,41.3916473389],"type":"Point"}
}