{
  "type": "Feature",
  "properties": {
    "addr:full":"Rua Zamora, 60 Vigo Pontevedra 36203",
    "addr:housenumber":"60",
    "addr:postcode":"36203",
    "addr:street":"Rua Zamora",
    "iso:country":"ES",
    "sg:address":"Rua Zamora, 60",
    "sg:city":"Vigo",
    "sg:classifiers":[
        {
            "category":"Personal",
            "subcategory":"Barber",
            "type":"Services"
        }
    ],
    "sg:phone":"+34 986 42 07 90",
    "sg:postcode":"36203",
    "sg:province":"Pontevedra",
    "sg:tags":[
        "caballeros",
        "de",
        "peluqueros"
    ],
    "wof:name":"Costas Garcia Jose",
    "wof:placetype":"venue"
},
  "geometry": {"coordinates":[-8.7233781815,42.2251663208],"type":"Point"}
}