{
  "type": "Feature",
  "properties": {
    "iso:country":"ES",
    "sg:address":"Calle de Nuestra Se\u00d1ora Del Carmen, 21",
    "sg:city":"Utebo",
    "sg:orig_category":"Empresas De Desmonte",
    "sg:phone":"+34 976 77 09 34",
    "sg:postcode":"50180",
    "sg:province":"Zaragoza",
    "wof:name":"Cortes Benito Eugenio",
    "wof:placetype":"venue"
},
  "geometry": {"coordinates":[-1.0011390448,41.7080802917],"type":"Point"}
}