{
  "type": "Feature",
  "properties": {
    "addr:full":"Calle de Literato Azorin, 36 Valencia Valencia 46006",
    "addr:housenumber":"36",
    "addr:postcode":"46006",
    "addr:street":"Calle De Literato Azorin",
    "iso:country":"ES",
    "sg:address":"Calle de Literato Azorin, 36",
    "sg:city":"Valencia",
    "sg:orig_category":"Chapister\u00cda",
    "sg:phone":"+34 963 41 48 72",
    "sg:postcode":"46006",
    "sg:province":"Valencia",
    "wof:name":"Navarro Chornet Juan",
    "wof:placetype":"venue"
},
  "geometry": {"coordinates":[-0.3765459955,39.4595680237],"type":"Point"}
}