{
  "type": "Feature",
  "properties": {
    "addr:full":"Ctra Alfaro, 26 Tudela Navarra 31500",
    "addr:housenumber":"26",
    "addr:postcode":"31500",
    "addr:street":"Ctra Alfaro",
    "iso:country":"ES",
    "sg:address":"Ctra Alfaro, 26",
    "sg:city":"Tudela",
    "sg:orig_category":"Panader\u00cdas, Panader\u00cdas",
    "sg:phone":"+34 948 82 85 99",
    "sg:postcode":"31500",
    "sg:province":"Navarra",
    "wof:name":"Panaderia Pasteleria Cafeteria Cruz S.l.",
    "wof:placetype":"venue"
},
  "geometry": {"coordinates":[-1.6134910583,42.0639762878],"type":"Point"}
}