{
  "type": "Feature",
  "properties": {
    "addr:full":"Carrer de Balmes, 184 Barcelona Barcelona 08006",
    "addr:housenumber":"184",
    "addr:postcode":"08006",
    "addr:street":"Carrer De Balmes",
    "iso:country":"ES",
    "sg:address":"Carrer de Balmes, 184",
    "sg:city":"Barcelona",
    "sg:orig_category":"Arquitectos",
    "sg:phone":"+34 932 17 19 13",
    "sg:postcode":"08006",
    "sg:province":"Barcelona",
    "wof:name":"Agusti Dominguez Fernando",
    "wof:placetype":"venue"
},
  "geometry": {"coordinates":[2.1533808708,41.3963890076],"type":"Point"}
}