{
  "type": "Feature",
  "properties": {
    "iso:country":"ES",
    "sg:address":"Calle de Cordeleros, 1",
    "sg:city":"Huesca",
    "sg:orig_category":"Venta, Montaje De Neum\u00c1ticos",
    "sg:phone":"+34 974 22 34 52",
    "sg:postcode":"22006",
    "sg:province":"Huesca",
    "wof:name":"Ferrer Sempere Carmelo",
    "wof:placetype":"venue"
},
  "geometry": {"coordinates":[-0.3963097036,42.1457710266],"type":"Point"}
}