{
  "type": "Feature",
  "properties": {
    "iso:country":"ES",
    "sg:address":"Calle de Bravo Murillo, 127",
    "sg:city":"Madrid",
    "sg:orig_category":"Heladeros",
    "sg:phone":"+34 915 53 98 29",
    "sg:postcode":"28020",
    "sg:province":"Madrid",
    "wof:name":"Palazzo Cea S. A.",
    "wof:placetype":"venue"
},
  "geometry": {"coordinates":[-3.7036173344,40.4495124817],"type":"Point"}
}