{
  "type": "Feature",
  "properties": {
    "iso:country":"ES",
    "sg:address":"Calle de Mayorazgo, 7",
    "sg:city":"Palmas De Gran Canaria",
    "sg:orig_category":"Agencias Y Agentes Comerciales, Representantes",
    "sg:phone":"+34 928 46 41 46",
    "sg:postcode":"35009",
    "sg:province":"Las Palmas",
    "wof:name":"Tacoronte Marrero Antonio",
    "wof:placetype":"venue"
},
  "geometry": {"coordinates":[-15.4311647415,28.1510620117],"type":"Point"}
}