{
  "type": "Feature",
  "properties": {
    "addr:full":"Calle de Mercado, 21 Frias Burgos 09211",
    "addr:housenumber":"21",
    "addr:postcode":"09211",
    "addr:street":"Calle De Mercado",
    "iso:country":"ES",
    "sg:address":"Calle de Mercado, 21",
    "sg:city":"Frias",
    "sg:orig_category":"Venta, Instalaci\u00d3n De Cocinas",
    "sg:phone":"+34 947 35 70 67",
    "sg:postcode":"09211",
    "sg:province":"Burgos",
    "wof:name":"Ortiz Vallejo Maria Del Carmen",
    "wof:placetype":"venue"
},
  "geometry": {"coordinates":[-3.2960119247,42.761631012],"type":"Point"}
}