{
  "type": "Feature",
  "properties": {
    "iso:country":"ES",
    "sg:address":"Masti-loidi, 15 H",
    "sg:city":"Errenteria",
    "sg:orig_category":"Rectificaci\u00d3n, Mecanizado, Fresado",
    "sg:phone":"+34 943 51 97 30",
    "sg:postcode":"20100",
    "sg:province":"Guip\u00f9zcoa",
    "wof:name":"Mecanizados Susperregui, S.l",
    "wof:placetype":"venue"
},
  "geometry": {"coordinates":[-1.9022496939,43.3027992249],"type":"Point"}
}