{
  "type": "Feature",
  "properties": {
    "iso:country":"ES",
    "sg:address":"Calle de Hinojosa, 73",
    "sg:city":"Viso",
    "sg:orig_category":"Molduras, Junquillos, Listones Y Molduras Perforadas",
    "sg:phone":"+34 957 12 70 32",
    "sg:postcode":"14470",
    "sg:province":"C\u00f3rdoba",
    "wof:name":"Fernandez Lopez Demetrio",
    "wof:placetype":"venue"
},
  "geometry": {"coordinates":[-4.9589109421,38.48387146],"type":"Point"}
}