{
  "type": "Feature",
  "properties": {
    "iso:country":"ES",
    "sg:address":"Carr Soledat, 13",
    "sg:city":"Badalona",
    "sg:orig_category":"Tintes (fabricaci\u00d3n, Al Por Mayor)",
    "sg:phone":"+34 933 89 16 47",
    "sg:postcode":"08911",
    "sg:province":"Barcelona",
    "wof:name":"Pedro Huerta Jordi",
    "wof:placetype":"venue"
},
  "geometry": {"coordinates":[2.2473700047,41.4487724304],"type":"Point"}
}