{
  "type": "Feature",
  "properties": {
    "addr:full":"Calle de Historiador Clapes, 29 Santa Eulalia Islas Baleares 07840",
    "addr:housenumber":"29",
    "addr:postcode":"07840",
    "addr:street":"Calle De Historiador Clapes",
    "iso:country":"ES",
    "sg:address":"Calle de Historiador Clapes, 29",
    "sg:city":"Santa Eulalia",
    "sg:orig_category":"Int\u00c9rpretes",
    "sg:phone":"+34 971 31 94 90",
    "sg:postcode":"07840",
    "sg:province":"Islas Baleares",
    "wof:name":"Traverso  Martin Gonzalo",
    "wof:placetype":"venue"
},
  "geometry": {"coordinates":[1.5363420248,38.9873085022],"type":"Point"}
}