{
  "type": "Feature",
  "properties": {
    "iso:country":"ES",
    "sg:address":"Ctra Granada (de), Km. 0314,0",
    "sg:city":"Castro Rio",
    "sg:orig_category":"Mec\u00c1nico Del Autom\u00d3vil",
    "sg:phone":"+34 957 37 02 05",
    "sg:postcode":"14840",
    "sg:province":"C\u00f3rdoba",
    "wof:name":"Millan Molina Antonio",
    "wof:placetype":"venue"
},
  "geometry": {"coordinates":[-4.4765949249,37.6923103333],"type":"Point"}
}