{
  "type": "Feature",
  "properties": {
    "iso:country":"ES",
    "sg:address":"Carrer de Comte Borrell, 38",
    "sg:city":"Barcelona",
    "sg:orig_category":"Ropa Para Se\u00d1oras (al Por Menor)",
    "sg:phone":"+34 934 41 02 47",
    "sg:postcode":"08015",
    "sg:province":"Barcelona",
    "wof:name":"Trainning Comunicaciones S.l.",
    "wof:placetype":"venue"
},
  "geometry": {"coordinates":[2.1631031036,41.3772125244],"type":"Point"}
}