{
  "type": "Feature",
  "properties": {
    "addr:full":"Calle de Jara, 31 Cartagena Murcia 30201",
    "addr:housenumber":"31",
    "addr:postcode":"30201",
    "addr:street":"Calle De Jara",
    "iso:country":"ES",
    "sg:address":"Calle de Jara, 31",
    "sg:city":"Cartagena",
    "sg:orig_category":"M\u00c9dicos: Estomatolog\u00cda",
    "sg:phone":"+34 968 50 16 35",
    "sg:postcode":"30201",
    "sg:province":"Murcia",
    "wof:name":"Bermejo Tudela Ambrosio",
    "wof:placetype":"venue"
},
  "geometry": {"coordinates":[-0.9862700105,37.6017036438],"type":"Point"}
}