{
  "type": "Feature",
  "properties": {
    "addr:full":"Calle de Askao, 2 Bilbao Vizcaya 48005",
    "addr:housenumber":"2",
    "addr:postcode":"48005",
    "addr:street":"Calle De Askao",
    "iso:country":"ES",
    "sg:address":"Calle de Askao, 2",
    "sg:city":"Bilbao",
    "sg:orig_category":"Fabricaci\u00d3n De Telas Y Sedas",
    "sg:phone":"+34 944 16 92 94",
    "sg:postcode":"48005",
    "sg:province":"Vizcaya",
    "wof:name":"Ana Sebastian Ipi\u00f1a Y Sebastian Boone Hupkes C.b.",
    "wof:placetype":"venue"
},
  "geometry": {"coordinates":[-2.9220542908,43.2594528198],"type":"Point"}
}