{
  "type": "Feature",
  "properties": {
    "addr:full":"Calle de Gibraltar Espa\u00d1ol, S/n Torredelcampo Ja\u00e9n 23640",
    "addr:housenumber":"s",
    "addr:postcode":"23640",
    "addr:street":"Calle De Gibraltar Espan\u0303Ol;/ N;Jae\u0301N",
    "iso:country":"ES",
    "sg:address":"Calle de Gibraltar Espa\u00d1ol, S/n",
    "sg:city":"Torredelcampo",
    "sg:orig_category":"Empresas De Carpinter\u00cda De Madera",
    "sg:phone":"+34 953 56 70 65",
    "sg:postcode":"23640",
    "sg:province":"Ja\u00e9n",
    "wof:name":"Molina Vilches Tomas",
    "wof:placetype":"venue"
},
  "geometry": {"coordinates":[-3.899559021,37.7692108154],"type":"Point"}
}