{
  "type": "Feature",
  "properties": {
    "iso:country":"ES",
    "sg:address":"Calle de Juan Xxiii, 2",
    "sg:city":"Ubrique",
    "sg:orig_category":"Servicios De Telecomunicaciones",
    "sg:phone":"+34 956 46 24 38",
    "sg:postcode":"11600",
    "sg:province":"C\u00e1diz",
    "wof:name":"Fornitel Ubrimore S.l.u.",
    "wof:placetype":"venue"
},
  "geometry": {"coordinates":[-5.4453969002,36.6780662537],"type":"Point"}
}