{
  "type": "Feature",
  "properties": {
    "iso:country":"ES",
    "sg:address":"Edif Renta Sevilla, 1",
    "sg:city":"Sevilla",
    "sg:orig_category":"Fabricaci\u00d3n, Importaci\u00d3n De Material Y Sistemas De Telecomunicaciones",
    "sg:phone":"+34 954 51 14 49",
    "sg:postcode":"41020",
    "sg:province":"Sevilla",
    "wof:name":"Landata Ingenieria S.a.",
    "wof:placetype":"venue"
},
  "geometry": {"coordinates":[-5.9333291054,37.4165763855],"type":"Point"}
}