{
  "type": "Feature",
  "properties": {
    "iso:country":"ES",
    "sg:address":"Avda Santiago Ramon Y Cajal, 2",
    "sg:city":"Badajoz",
    "sg:orig_category":"Librer\u00cdas",
    "sg:phone":"+34 924 24 58 56",
    "sg:postcode":"06001",
    "sg:province":"Badajoz",
    "wof:name":"Casado Martin Jose Maria",
    "wof:placetype":"venue"
},
  "geometry": {"coordinates":[-6.9734659195,38.8750076294],"type":"Point"}
}