{
  "type": "Feature",
  "properties": {
    "addr:full":"Barr Ugarte Goikoa, 1 Ugarte Vizcaya 48392",
    "addr:housenumber":"1",
    "addr:postcode":"48392",
    "addr:street":"Goikoa",
    "iso:country":"ES",
    "sg:address":"Barr Ugarte Goikoa, 1",
    "sg:city":"Ugarte",
    "sg:orig_category":"Transportes Especiales",
    "sg:phone":"+34 946 25 28 03",
    "sg:postcode":"48392",
    "sg:province":"Vizcaya",
    "wof:name":"Badiola Idazabal Juan Luis",
    "wof:placetype":"venue"
},
  "geometry": {"coordinates":[-2.7138524055,43.2934989929],"type":"Point"}
}