{
  "type": "Feature",
  "properties": {
    "iso:country":"ES",
    "sg:address":"Calle de Rafael De Riego, 14",
    "sg:city":"Madrid",
    "sg:orig_category":"Aparcamientos (infraestructuras, Accesorios)",
    "sg:phone":"+34 915 30 76 72",
    "sg:postcode":"28045",
    "sg:province":"Madrid",
    "wof:name":"Hijos De Ovidio Martinez S. A.",
    "wof:placetype":"venue"
},
  "geometry": {"coordinates":[-3.6922369003,40.4049186707],"type":"Point"}
}