{
  "type": "Feature",
  "properties": {
    "addr:full":"Calle de Jacinto Benavente, 2 Alberic Valencia 46260",
    "addr:housenumber":"2",
    "addr:postcode":"46260",
    "addr:street":"Calle De Jacinto Benavente",
    "iso:country":"ES",
    "sg:address":"Calle de Jacinto Benavente, 2",
    "sg:city":"Alberic",
    "sg:orig_category":"Promotores Constructores",
    "sg:phone":"+34 962 44 60 29",
    "sg:postcode":"46260",
    "sg:province":"Valencia",
    "sg:website":"www.ohl.es",
    "wof:name":"Obrascon Huarte Lain S.a.",
    "wof:placetype":"venue"
},
  "geometry": {"coordinates":[-0.5249829888,39.1176757812],"type":"Point"}
}