{
  "type": "Feature",
  "properties": {
    "addr:full":"Plaz Espa\u00d1a (de), 16 Maella Zaragoza 50710",
    "addr:postcode":"50710",
    "addr:street":"Plaz",
    "iso:country":"ES",
    "sg:address":"Plaz Espa\u00d1a (de), 16",
    "sg:city":"Maella",
    "sg:orig_category":"Lencer\u00cda Femenina, Corseter\u00cda, Trajes De Ba\u00d1o (al Por Menor)",
    "sg:phone":"+34 976 63 85 81",
    "sg:postcode":"50710",
    "sg:province":"Zaragoza",
    "wof:name":"Fina Y Maria S.c.",
    "wof:placetype":"venue"
},
  "geometry": {"coordinates":[0.139240995,41.1226272583],"type":"Point"}
}