{
  "type": "Feature",
  "properties": {
    "addr:full":"Calle de Canonigo Isidoro Diaz Murugarren, S/n Burgos Burgos 09007",
    "addr:housenumber":"s / n",
    "addr:postcode":"09007",
    "addr:street":"Calle De Canonigo Isidoro Diaz Murugarren",
    "iso:country":"ES",
    "sg:address":"Calle de Canonigo Isidoro Diaz Murugarren, S/n",
    "sg:city":"Burgos",
    "sg:orig_category":"Institutos De Belleza",
    "sg:phone":"+34 947 21 53 93",
    "sg:postcode":"09007",
    "sg:province":"Burgos",
    "wof:name":"Garcia De La Camara Maria Angeles",
    "wof:placetype":"venue"
},
  "geometry": {"coordinates":[-3.6319131851,42.365978241],"type":"Point"}
}