{
  "type": "Feature",
  "properties": {
    "addr:full":"Avda Puebla, 30 Ponferrada Le\u00f3n 24400",
    "addr:housenumber":"30",
    "addr:postcode":"24400",
    "addr:street":"Avda Puebla",
    "iso:country":"ES",
    "sg:address":"Avda Puebla, 30",
    "sg:city":"Ponferrada",
    "sg:orig_category":"Inmobiliaria (agencias)",
    "sg:phone":"+34 987 40 93 42",
    "sg:postcode":"24400",
    "sg:province":"Le\u00f3n",
    "wof:name":"Business & Hogar Servicios Inmobiliarios, S. L.",
    "wof:placetype":"venue"
},
  "geometry": {"coordinates":[-6.5955867767,42.5476417542],"type":"Point"}
}