{
  "type": "Feature",
  "properties": {
    "addr:full":"Trva Pastoriza, 42 Pastoriza La Coru\u00f1a 15140",
    "addr:housenumber":"42",
    "addr:postcode":"15140",
    "addr:street":"Trva Pastoriza;La Corun\u0303A",
    "iso:country":"ES",
    "sg:address":"Trva Pastoriza, 42",
    "sg:city":"Pastoriza",
    "sg:orig_category":"Chapister\u00cda",
    "sg:phone":"+34 981 60 73 03",
    "sg:postcode":"15140",
    "sg:province":"La Coru\u00f1a",
    "wof:name":"Gonzalez Lopez Jose Luis",
    "wof:placetype":"venue"
},
  "geometry": {"coordinates":[-8.46671772,43.3288497925],"type":"Point"}
}