{
  "type": "Feature",
  "properties": {
    "addr:full":"Calle de San Valero, 9 Valencia Valencia 46005",
    "addr:housenumber":"9",
    "addr:postcode":"46005",
    "addr:street":"Calle De San Valero",
    "iso:country":"ES",
    "sg:address":"Calle de San Valero, 9",
    "sg:city":"Valencia",
    "sg:orig_category":"Doctores En Medicina",
    "sg:phone":"+34 963 33 29 98",
    "sg:postcode":"46005",
    "sg:province":"Valencia",
    "wof:name":"Albors Gil Juan Luciano",
    "wof:placetype":"venue"
},
  "geometry": {"coordinates":[-0.3720411062,39.4636878967],"type":"Point"}
}