{
  "type": "Feature",
  "properties": {
    "addr:full":"Cmno Suarez, 2 Malaga M\u00e1laga 29010",
    "addr:housenumber":"2",
    "addr:postcode":"29010",
    "addr:street":"Cmno Suarez;Ma\u0301Laga",
    "iso:country":"ES",
    "sg:address":"Cmno Suarez, 2",
    "sg:city":"Malaga",
    "sg:orig_category":"Colchones (fabricaci\u00d3n, Al Por Mayor, Al Por Menor)",
    "sg:phone":"+34 952 07 21 37",
    "sg:postcode":"29010",
    "sg:province":"M\u00e1laga",
    "sg:website":"www.colchoneriaelpalo.com",
    "wof:name":"Grupo Mi Colchon S.l",
    "wof:placetype":"venue"
},
  "geometry": {"coordinates":[-4.4351315498,36.7269668579],"type":"Point"}
}