{
  "type": "Feature",
  "properties": {
    "addr:full":"Calle de Montoyas, S/n Cigales Valladolid 47270",
    "addr:housenumber":"s / n",
    "addr:postcode":"47270",
    "addr:street":"Calle De Montoyas",
    "iso:country":"ES",
    "sg:address":"Calle de Montoyas, S/n",
    "sg:city":"Cigales",
    "sg:orig_category":"Promotores Constructores",
    "sg:phone":"+34 983 58 02 56",
    "sg:postcode":"47270",
    "sg:province":"Valladolid",
    "wof:name":"Constructora Reca E Hijos S.l.",
    "wof:placetype":"venue"
},
  "geometry": {"coordinates":[-4.6993708611,41.7592811584],"type":"Point"}
}