{
  "type": "Feature",
  "properties": {
    "iso:country":"ES",
    "sg:address":"Avda Bulevar De El Ejido, 301",
    "sg:city":"Ejido",
    "sg:orig_category":"Ropa Para Ni\u00d1os (al Por Menor)",
    "sg:phone":"+34 950 48 68 52",
    "sg:postcode":"04700",
    "sg:province":"Almer\u00eda",
    "sg:website":"www.e-stradivarius.com",
    "wof:name":"Stradivarius Espa\u00d1a S.a",
    "wof:placetype":"venue"
},
  "geometry": {"coordinates":[-2.8176040649,36.7727012634],"type":"Point"}
}