{
  "type": "Feature",
  "properties": {
    "iso:country":"ES",
    "sg:address":"Calle de Maria De Molina, 1",
    "sg:city":"Madrid",
    "sg:orig_category":"Empresarios",
    "sg:phone":"+34 914 11 92 20",
    "sg:postcode":"28006",
    "sg:province":"Madrid",
    "sg:website":"www.fundacionbarreiros.org",
    "wof:name":"Fundacion Eduardo Barreiros",
    "wof:placetype":"venue"
},
  "geometry": {"coordinates":[-3.6900420189,40.4380531311],"type":"Point"}
}