{
  "type": "Feature",
  "properties": {
    "iso:country":"ES",
    "sg:address":"J Vicente Casaban Sena, 7",
    "sg:city":"Xirivella",
    "sg:orig_category":"Empresas De Pintura Y Revestimientos",
    "sg:phone":"+34 963 79 97 05",
    "sg:postcode":"46950",
    "sg:province":"Valencia",
    "wof:name":"Bueno Arenas Victoriano",
    "wof:placetype":"venue"
},
  "geometry": {"coordinates":[-0.4357140064,39.4631652832],"type":"Point"}
}