{
  "type": "Feature",
  "properties": {
    "iso:country":"ES",
    "sg:address":"Carrer de Zamora, 45",
    "sg:city":"Barcelona",
    "sg:orig_category":"Agencias Y Asesores De Publicidad",
    "sg:phone":"+34 933 20 93 92",
    "sg:postcode":"08005",
    "sg:province":"Barcelona",
    "wof:name":"Signes I Lletres S.l.",
    "wof:placetype":"venue"
},
  "geometry": {"coordinates":[2.1927330494,41.3935890198],"type":"Point"}
}