{
  "type": "Feature",
  "properties": {
    "addr:full":"Calle de Bazan, 6 Gijon Asturias 33211",
    "addr:housenumber":"6",
    "addr:postcode":"33211",
    "addr:street":"Calle De Bazan",
    "iso:country":"ES",
    "sg:address":"Calle de Bazan, 6",
    "sg:city":"Gijon",
    "sg:orig_category":"Vulcanizado",
    "sg:phone":"+34 985 30 06 10",
    "sg:postcode":"33211",
    "sg:province":"Asturias",
    "wof:name":"Vulcanizados Trancho S.a.",
    "wof:placetype":"venue"
},
  "geometry": {"coordinates":[-5.6938638687,43.5329475403],"type":"Point"}
}