{
  "type": "Feature",
  "properties": {
    "addr:full":"Carr De Ferreres Breto, 10 Benicarlo Castell\u00f3n 12580",
    "addr:housenumber":"10",
    "addr:postcode":"12580",
    "addr:street":"Carr De Ferreres Breto",
    "iso:country":"ES",
    "sg:address":"Carr De Ferreres Breto, 10",
    "sg:city":"Benicarlo",
    "sg:orig_category":"C\u00c1maras De Comercio E Industria, Oficios, Agricultura",
    "sg:phone":"+34 964 47 51 44",
    "sg:postcode":"12580",
    "sg:province":"Castell\u00f3n",
    "wof:name":"Camara Oficial Comercio Industria Y Nave",
    "wof:placetype":"venue"
},
  "geometry": {"coordinates":[0.4042100012,40.4457893372],"type":"Point"}
}