{
  "type": "Feature",
  "properties": {
    "iso:country":"ES",
    "sg:address":"Rua Princesa, 1",
    "sg:city":"Pontevedra",
    "sg:orig_category":"Internados & Ense\u00d1anza Privada",
    "sg:phone":"+34 986 86 19 90",
    "sg:postcode":"36002",
    "sg:province":"Pontevedra",
    "wof:name":"Cooperativa De Ense\u00f1anza San Jose",
    "wof:placetype":"venue"
},
  "geometry": {"coordinates":[-8.6455087662,42.4327507019],"type":"Point"}
}