{
  "type": "Feature",
  "properties": {
    "iso:country":"ES",
    "sg:address":"Carr S Jaume, 1",
    "sg:city":"Igualada",
    "sg:orig_category":"Institutos De Belleza",
    "sg:phone":"+34 938 03 30 23",
    "sg:postcode":"08700",
    "sg:province":"Barcelona",
    "wof:name":"Pelfort Roset Jordi",
    "wof:placetype":"venue"
},
  "geometry": {"coordinates":[1.6179250479,41.5780715942],"type":"Point"}
}