{
  "type": "Feature",
  "properties": {
    "addr:full":"As Gruncheiras, 2 Gruncheiras Pontevedra 36947",
    "addr:housenumber":"2",
    "addr:postcode":"36947",
    "addr:street":"Gruncheiras",
    "iso:country":"ES",
    "sg:address":"As Gruncheiras, 2",
    "sg:city":"Gruncheiras",
    "sg:orig_category":"Asesor\u00cda Fiscal Y Jur\u00cddica",
    "sg:phone":"+34 986 30 59 04",
    "sg:postcode":"36947",
    "sg:province":"Pontevedra",
    "wof:name":"Interpyme S.l.",
    "wof:placetype":"venue"
},
  "geometry": {"coordinates":[-8.7655076981,42.2693367004],"type":"Point"}
}