{
  "type": "Feature",
  "properties": {
    "addr:full":"Calle de Marques Del Muni, 25 Santa Maria De Guia Las Palmas 35450",
    "addr:housenumber":"25",
    "addr:postcode":"35450",
    "addr:street":"Calle De Marques Del Muni",
    "iso:country":"ES",
    "sg:address":"Calle de Marques Del Muni, 25",
    "sg:city":"Santa Maria De Guia",
    "sg:orig_category":"Geolog\u00cda Y Geof\u00cdsica",
    "sg:phone":"+34 928 55 12 88",
    "sg:postcode":"35450",
    "sg:province":"Las Palmas",
    "wof:name":"Martinez Martinez Jesus Joaquin",
    "wof:placetype":"venue"
},
  "geometry": {"coordinates":[-15.6324939728,28.140165329],"type":"Point"}
}