{
  "type": "Feature",
  "properties": {
    "iso:country":"ES",
    "sg:address":"Plce Cruz Verde, 11",
    "sg:city":"Granada",
    "sg:orig_category":"Inform\u00c1tica Equipo Y Programas (al Por Mayor)",
    "sg:phone":"+34 958 22 00 00",
    "sg:postcode":"18010",
    "sg:province":"Granada",
    "wof:name":"Beltran Cuesta Angela Margarita",
    "wof:placetype":"venue"
},
  "geometry": {"coordinates":[-3.5949540138,37.1790885925],"type":"Point"}
}