{
  "type": "Feature",
  "properties": {
    "addr:full":"Calle de Amargura, 8 Socuellamos Ciudad Real 13630",
    "addr:housenumber":"8",
    "addr:postcode":"13630",
    "addr:street":"Calle De Amargura",
    "iso:country":"ES",
    "sg:address":"Calle de Amargura, 8",
    "sg:city":"Socuellamos",
    "sg:orig_category":"Agencias Y Agentes Comerciales, Representantes",
    "sg:phone":"+34 926 53 06 47",
    "sg:postcode":"13630",
    "sg:province":"Ciudad Real",
    "wof:name":"Alarcon Jimenez Jose Luis",
    "wof:placetype":"venue"
},
  "geometry": {"coordinates":[-2.7919352055,39.2892723083],"type":"Point"}
}