{
  "type": "Feature",
  "properties": {
    "iso:country":"ES",
    "sg:address":"Calle de Rio Sil, 4",
    "sg:city":"Villablino",
    "sg:orig_category":"Alimentaci\u00d3n General (al Por Menor)",
    "sg:phone":"+34 987 47 08 05",
    "sg:postcode":"24100",
    "sg:province":"Le\u00f3n",
    "wof:name":"Supermercado Rio Sil S.l.",
    "wof:placetype":"venue"
},
  "geometry": {"coordinates":[-6.3170537949,42.9384651184],"type":"Point"}
}