{
  "type": "Feature",
  "properties": {
    "addr:full":"Rua Ponte De San Lazaro (da), 11 Santiago De Compostela La Coru\u00f1a 15703",
    "addr:postcode":"15703",
    "addr:street":"Rua Ponte De San;Da;Corun\u0303A",
    "iso:country":"ES",
    "sg:address":"Rua Ponte De San Lazaro (da), 11",
    "sg:city":"Santiago De Compostela",
    "sg:orig_category":"Internados & Ense\u00d1anza Privada",
    "sg:phone":"+34 981 55 41 50",
    "sg:postcode":"15703",
    "sg:province":"La Coru\u00f1a",
    "wof:name":"Federacion De Escuelas Familiares De Galicia",
    "wof:placetype":"venue"
},
  "geometry": {"coordinates":[-8.5086040497,42.8875961304],"type":"Point"}
}