{
  "type": "Feature",
  "properties": {
    "iso:country":"ES",
    "sg:address":"Calle de Villacarrillo (blq), 13",
    "sg:city":"Madrid",
    "sg:orig_category":"T\u00c9cnicos Veterinarios",
    "sg:phone":"+34 915 48 13 44",
    "sg:postcode":"28008",
    "sg:province":"Madrid",
    "wof:name":"Vaquero Sanchez Salvador",
    "wof:placetype":"venue"
},
  "geometry": {"coordinates":[-3.663697958,40.3759269714],"type":"Point"}
}