{
  "type": "Feature",
  "properties": {
    "addr:full":"San Silvestre (p I S Silvestre), 8 Huercal Almeria Almer\u00eda 04230",
    "addr:housenumber":"8",
    "addr:postcode":"04230",
    "addr:street":"P I S Silvestre;Almeri\u0301A",
    "iso:country":"ES",
    "sg:address":"San Silvestre (p I S Silvestre), 8",
    "sg:city":"Huercal Almeria",
    "sg:orig_category":"Bebidas",
    "sg:phone":"+34 950 14 02 62",
    "sg:postcode":"04230",
    "sg:province":"Almer\u00eda",
    "wof:name":"Compa\u00d1ia De Bebidas Pepsico S.l.",
    "wof:placetype":"venue"
},
  "geometry": {"coordinates":[-2.4445779324,36.8744163513],"type":"Point"}
}