{
  "type": "Feature",
  "properties": {
    "iso:country":"ES",
    "sg:address":"Poli Ventorrillo, S/n",
    "sg:city":"Coru\u00d1a",
    "sg:orig_category":"Carnicer\u00cdas, Carnicer\u00cdas",
    "sg:phone":"+34 981 25 46 36",
    "sg:postcode":"15010",
    "sg:province":"La Coru\u00f1a",
    "wof:name":"Dopico Lopez Maria Dolores",
    "wof:placetype":"venue"
},
  "geometry": {"coordinates":[-8.4224596024,43.3594779968],"type":"Point"}
}