{
  "type": "Feature",
  "properties": {
    "iso:country":"ES",
    "sg:address":"Calle de Maestro Clave, 3",
    "sg:city":"Valencia",
    "sg:orig_category":"Quiropr\u00c1cticos",
    "sg:phone":"+34 963 52 72 20",
    "sg:postcode":"46001",
    "sg:province":"Valencia",
    "wof:name":"Blazquez Rodriguez Manuela",
    "wof:placetype":"venue"
},
  "geometry": {"coordinates":[-0.3783859909,39.4711723328],"type":"Point"}
}