{
  "type": "Feature",
  "properties": {
    "iso:country":"ES",
    "sg:address":"Carrer de Cinema Bel, 12",
    "sg:city":"Cornella Llobregat",
    "sg:orig_category":"Mec\u00c1nico Del Autom\u00d3vil",
    "sg:phone":"+34 933 77 67 17",
    "sg:postcode":"08940",
    "sg:province":"Barcelona",
    "wof:name":"Nieto Gonzalez Delfin",
    "wof:placetype":"venue"
},
  "geometry": {"coordinates":[2.0700650215,41.3542861938],"type":"Point"}
}