{
  "type": "Feature",
  "properties": {
    "addr:full":"Rua Pi Y Margall, 37 Vigo Pontevedra 36202",
    "addr:housenumber":"37",
    "addr:postcode":"36202",
    "addr:street":"Rua Pi Y Margall",
    "iso:country":"ES",
    "sg:address":"Rua Pi Y Margall, 37",
    "sg:city":"Vigo",
    "sg:orig_category":"Agencias Y Agentes Comerciales, Representantes",
    "sg:phone":"+34 986 43 68 66",
    "sg:postcode":"36202",
    "sg:province":"Pontevedra",
    "wof:name":"Fuentes Migon Miguel Angel",
    "wof:placetype":"venue"
},
  "geometry": {"coordinates":[-8.7293615341,42.2342948914],"type":"Point"}
}