{
  "type": "Feature",
  "properties": {
    "iso:country":"ES",
    "sg:address":"C/ Zurbano, 40",
    "sg:city":"Cerdanyola Valles",
    "sg:orig_category":"Planchado",
    "sg:phone":"+34 936 91 44 68",
    "sg:postcode":"08290",
    "sg:province":"Barcelona",
    "wof:name":"Planchado Artesanal S.l.",
    "wof:placetype":"venue"
},
  "geometry": {"coordinates":[2.1299090385,41.4890518188],"type":"Point"}
}