{
  "type": "Feature",
  "properties": {
    "addr:full":"Calle de Arga, 8 Madrid Madrid 28002",
    "addr:housenumber":"8",
    "addr:postcode":"madrid;28002",
    "addr:street":"Calle De Arga",
    "iso:country":"ES",
    "sg:address":"Calle de Arga, 8",
    "sg:city":"Madrid",
    "sg:orig_category":"Centros Empresariales",
    "sg:phone":"+34 915 61 30 02",
    "sg:postcode":"28002",
    "sg:province":"Madrid",
    "wof:name":"Latacar S.l.",
    "wof:placetype":"venue"
},
  "geometry": {"coordinates":[-3.6819326878,40.4494590759],"type":"Point"}
}