{
  "type": "Feature",
  "properties": {
    "iso:country":"ES",
    "sg:address":"Plaz Vicente Aleixandre, 13",
    "sg:city":"Aznalcollar",
    "sg:orig_category":"Bazares, Art\u00cdculos De Limpieza Y De Cocina (al Por Menor)",
    "sg:phone":"+34 954 13 50 02",
    "sg:postcode":"41870",
    "sg:province":"Sevilla",
    "wof:name":"Ojeda Delgado Jose Antonio",
    "wof:placetype":"venue"
},
  "geometry": {"coordinates":[-6.2651400566,37.5163993835],"type":"Point"}
}