{
  "type": "Feature",
  "properties": {
    "iso:country":"ES",
    "sg:address":"Calle de Arcipreste De Hita, 5",
    "sg:city":"Le\u00f3n",
    "sg:orig_category":"Armarios Y Cuadros El\u00c9ctricos",
    "sg:phone":"+34 987 25 22 62",
    "sg:postcode":"24004",
    "sg:province":"Le\u00f3n",
    "wof:name":"Armarios Magvi S.l.",
    "wof:placetype":"venue"
},
  "geometry": {"coordinates":[-5.5732927322,42.5900039673],"type":"Point"}
}