{
  "type": "Feature",
  "properties": {
    "iso:country":"ES",
    "sg:address":"Carr Jacint Verdaguer, 5",
    "sg:city":"Mollerussa",
    "sg:orig_category":"Librer\u00cdas",
    "sg:phone":"+34 973 60 09 85",
    "sg:postcode":"25230",
    "sg:province":"Lleida",
    "wof:name":"Llibreria Dalmases S.l.",
    "wof:placetype":"venue"
},
  "geometry": {"coordinates":[0.8944630027,41.6294784546],"type":"Point"}
}