{
  "type": "Feature",
  "properties": {
    "iso:country":"ES",
    "sg:address":"Plaz Aragon, 1",
    "sg:city":"Burgos",
    "sg:orig_category":"Vinos Y Licores (venta Al Por Menor)",
    "sg:phone":"+34 947 27 81 83",
    "sg:postcode":"09001",
    "sg:province":"Burgos",
    "wof:name":"Valdellanos S.l.",
    "wof:placetype":"venue"
},
  "geometry": {"coordinates":[-3.7063000202,42.3305511475],"type":"Point"}
}