{
  "type": "Feature",
  "properties": {
    "addr:full":"Calle de Ramon Y Cajal, 9 Teruel Teruel 44001",
    "addr:housenumber":"9",
    "addr:postcode":"44001",
    "addr:street":"Calle De Ramon Y Cajal",
    "iso:country":"ES",
    "sg:address":"Calle de Ramon Y Cajal, 9",
    "sg:city":"Teruel",
    "sg:orig_category":"Lencer\u00cda Femenina, Corseter\u00cda, Trajes De Ba\u00d1o (al Por Menor)",
    "sg:phone":"+34 978 60 88 52",
    "sg:postcode":"44001",
    "sg:province":"Teruel",
    "wof:name":"Perruca Rico Maria Jesus",
    "wof:placetype":"venue"
},
  "geometry": {"coordinates":[-1.1068429947,40.3422355652],"type":"Point"}
}