{
  "type": "Feature",
  "properties": {
    "addr:full":"Ctra Extremadura, S/n Talavera Reina Toledo 45600",
    "addr:postcode":"45600",
    "addr:street":"Ctra Extremadura S / N",
    "iso:country":"ES",
    "sg:address":"Ctra Extremadura, S/n",
    "sg:city":"Talavera Reina",
    "sg:orig_category":"Organismos Y Centros De Vacaciones Y Esparcimiento Para Ni\u00d1os Y Adolescentes",
    "sg:phone":"+34 902 20 06 03",
    "sg:postcode":"45600",
    "sg:province":"Toledo",
    "sg:website":"www.festivalatlanta.net",
    "wof:name":"Festival Atlanta C.b.",
    "wof:placetype":"venue"
},
  "geometry": {"coordinates":[-4.8200387955,39.9617500305],"type":"Point"}
}