{
  "type": "Feature",
  "properties": {
    "addr:full":"Crt Albacete-cuenca, S/n Villanueva Jara Cuenca 16230",
    "addr:postcode":"16230",
    "addr:street":"Albacete-Cuenca S / N;Jara",
    "iso:country":"ES",
    "sg:address":"Crt Albacete-cuenca, S/n",
    "sg:city":"Villanueva Jara",
    "sg:orig_category":"Poller\u00cda Y Caza (al Por Menor)",
    "sg:phone":"+34 967 57 10 83",
    "sg:postcode":"16230",
    "sg:province":"Cuenca",
    "wof:name":"Lopez Cebrian Pedro Antonio",
    "wof:placetype":"venue"
},
  "geometry": {"coordinates":[-1.9583890438,39.4429244995],"type":"Point"}
}