{
  "type": "Feature",
  "properties": {
    "iso:country":"ES",
    "sg:address":"Muel Ca\u00d1onero Dato, 49",
    "sg:city":"Ceuta",
    "sg:orig_category":"Agencias Y Agentes Comerciales, Representantes",
    "sg:phone":"+34 956 50 88 87",
    "sg:postcode":"51001",
    "sg:province":"Ceuta",
    "wof:name":"Garcia Hernandez Angel",
    "wof:placetype":"venue"
},
  "geometry": {"coordinates":[-5.3302302361,35.8947601318],"type":"Point"}
}