{
  "type": "Feature",
  "properties": {
    "iso:country":"ES",
    "sg:address":"Calle de Serrano, 72",
    "sg:city":"Madrid",
    "sg:orig_category":"Camiser\u00cda Y Ropa Interior Masculina (al Por Menor)",
    "sg:phone":"+34 915 77 26 53",
    "sg:postcode":"28001",
    "sg:province":"Madrid",
    "wof:name":"Mu\u00f1oz Ugena Pedro",
    "wof:placetype":"venue"
},
  "geometry": {"coordinates":[-3.6867640018,40.4302253723],"type":"Point"}
}