{
  "type": "Feature",
  "properties": {
    "addr:full":"Avda Constitucion (de La), 41 Nueva-carteya C\u00f3rdoba 14857",
    "addr:housenumber":"41",
    "addr:postcode":"14857",
    "addr:street":"Avda Constitucion De La;Co\u0301Rdoba",
    "iso:country":"ES",
    "sg:address":"Avda Constitucion (de La), 41",
    "sg:city":"Nueva-carteya",
    "sg:orig_category":"Electricidad Veh\u00cdculo",
    "sg:phone":"+34 957 67 84 01",
    "sg:postcode":"14857",
    "sg:province":"C\u00f3rdoba",
    "wof:name":"Cabello De Alba Garcia Jose Luis",
    "wof:placetype":"venue"
},
  "geometry": {"coordinates":[-4.4729208946,37.5880508423],"type":"Point"}
}