{
  "type": "Feature",
  "properties": {
    "iso:country":"ES",
    "sg:address":"Calle de Francisco Pizarro, 13",
    "sg:city":"Albacete",
    "sg:orig_category":"Material Y Suministros Para Fotocopiadoras, Reprograf\u00cda",
    "sg:phone":"+34 967 50 69 10",
    "sg:postcode":"02004",
    "sg:province":"Albacete",
    "wof:name":"Departamento Tecnico Informatico S.a.l.",
    "wof:placetype":"venue"
},
  "geometry": {"coordinates":[-1.8621419668,38.9932556152],"type":"Point"}
}