{
  "type": "Feature",
  "properties": {
    "addr:full":"Calle de Olmo, 23 Motilleja Albacete 02220",
    "addr:housenumber":"23",
    "addr:postcode":"02220",
    "addr:street":"Calle De Olmo",
    "iso:country":"ES",
    "sg:address":"Calle de Olmo, 23",
    "sg:city":"Motilleja",
    "sg:orig_category":"Centros De Educaci\u00d3n Especial",
    "sg:phone":"+34 967 49 36 87",
    "sg:postcode":"02220",
    "sg:province":"Albacete",
    "wof:name":"Colegio Rural Agrupado De Cenizate",
    "wof:placetype":"venue"
},
  "geometry": {"coordinates":[-1.7887639999,39.1791763306],"type":"Point"}
}