{
  "type": "Feature",
  "properties": {
    "iso:country":"ES",
    "sg:address":"Carrer de Mare De Deu De Port, 379",
    "sg:city":"Barcelona",
    "sg:orig_category":"Peluqueros: De Se\u00d1oras",
    "sg:phone":"+34 934 32 10 09",
    "sg:postcode":"08038",
    "sg:province":"Barcelona",
    "wof:name":"Qui\u00f1onero Campano Isabel",
    "wof:placetype":"venue"
},
  "geometry": {"coordinates":[2.1393671036,41.3629608154],"type":"Point"}
}