{
  "type": "Feature",
  "properties": {
    "addr:full":"Carrer de Notari Closells, 1 Olot Girona 17800",
    "addr:housenumber":"1",
    "addr:postcode":"17800",
    "addr:street":"Carrer De Notari Closells",
    "iso:country":"ES",
    "sg:address":"Carrer de Notari Closells, 1",
    "sg:city":"Olot",
    "sg:orig_category":"Agencias De Trabajo Temporal",
    "sg:phone":"+34 972 27 21 20",
    "sg:postcode":"17800",
    "sg:province":"Girona",
    "wof:name":"Creyf's Trabajo Temporal Ett S.a.",
    "wof:placetype":"venue"
},
  "geometry": {"coordinates":[2.4817559719,42.1793823242],"type":"Point"}
}