{
  "type": "Feature",
  "properties": {
    "iso:country":"ES",
    "sg:address":"Avda Espa\u00d1a (de), S/n",
    "sg:city":"Dos Hermanas",
    "sg:orig_category":"Electricidad: Instaladores",
    "sg:phone":"+34 955 67 76 95",
    "sg:postcode":"41700",
    "sg:province":"Sevilla",
    "wof:name":"Gonzalez Lopez Julio",
    "wof:placetype":"venue"
},
  "geometry": {"coordinates":[-5.9342660904,37.2805404663],"type":"Point"}
}