{
  "type": "Feature",
  "properties": {
    "addr:full":"Calle de Fermin Calbeton, 6 Irun Guip\u00f9zcoa 20302",
    "addr:housenumber":"6",
    "addr:postcode":"20302",
    "addr:street":"Calle De Fermin Calbeton;Guipu\u0300Zcoa",
    "iso:country":"ES",
    "sg:address":"Calle de Fermin Calbeton, 6",
    "sg:city":"Irun",
    "sg:orig_category":"Renovaci\u00d3n Inmobiliaria",
    "sg:phone":"+34 943 63 98 18",
    "sg:postcode":"20302",
    "sg:province":"Guip\u00f9zcoa",
    "wof:name":"Oiasso S.a.",
    "wof:placetype":"venue"
},
  "geometry": {"coordinates":[-1.7883930206,43.3394355774],"type":"Point"}
}