{
  "type": "Feature",
  "properties": {
    "iso:country":"ES",
    "sg:address":"Calle de Puerto De Somport, 22",
    "sg:city":"Sevilla",
    "sg:classifiers":[
        {
            "category":"Personal",
            "subcategory":"Barber",
            "type":"Services"
        }
    ],
    "sg:phone":"+34 954 63 68 29",
    "sg:postcode":"41006",
    "sg:province":"Sevilla",
    "sg:tags":[
        "caballeros",
        "de",
        "peluqueros"
    ],
    "wof:name":"Sierra Valverde Jose Ignacio",
    "wof:placetype":"venue"
},
  "geometry": {"coordinates":[-5.9554729462,37.3746910095],"type":"Point"}
}