{
  "type": "Feature",
  "properties": {
    "addr:full":"Carrer de Cardenal Tedeschini, 61 Barcelona Barcelona 08027",
    "addr:housenumber":"61",
    "addr:postcode":"08027",
    "addr:street":"Carrer De Cardenal Tedeschini",
    "iso:country":"ES",
    "sg:address":"Carrer de Cardenal Tedeschini, 61",
    "sg:city":"Barcelona",
    "sg:orig_category":"Empresarios",
    "sg:phone":"+34 933 52 82 06",
    "sg:postcode":"08027",
    "sg:province":"Barcelona",
    "wof:name":"Fundacio 'la Caixa'",
    "wof:placetype":"venue"
},
  "geometry": {"coordinates":[2.1808259487,41.4264755249],"type":"Point"}
}