{
  "type": "Feature",
  "properties": {
    "iso:country":"ES",
    "sg:address":"Ugaldeguren I Poligonoa, S/n",
    "sg:city":"Ugaldeguren",
    "sg:orig_category":"Equipo De Refrigeraci\u00d3n Industrial",
    "sg:phone":"+34 944 76 22 46",
    "sg:postcode":"48170",
    "sg:province":"Vizcaya",
    "sg:website":"www.pecomark.com",
    "wof:name":"Pecomark S.a.",
    "wof:placetype":"venue"
},
  "geometry": {"coordinates":[-2.8633139133,43.280834198],"type":"Point"}
}