{
  "type": "Feature",
  "properties": {
    "addr:full":"Calle de Tajo, 10 Puertollano Ciudad Real 13500",
    "addr:housenumber":"10",
    "addr:postcode":"13500",
    "addr:street":"Calle De Tajo",
    "iso:country":"ES",
    "sg:address":"Calle de Tajo, 10",
    "sg:city":"Puertollano",
    "sg:orig_category":"Rejas Y Cortinas Met\u00c1licas",
    "sg:phone":"+34 926 42 61 90",
    "sg:postcode":"13500",
    "sg:province":"Ciudad Real",
    "wof:name":"Ferryforja S.l.",
    "wof:placetype":"venue"
},
  "geometry": {"coordinates":[-4.0926661491,38.6776351929],"type":"Point"}
}