{
  "type": "Feature",
  "properties": {
    "addr:full":"Urba Motes (les), S/n Grau I Platja Valencia 46730",
    "addr:postcode":"46730",
    "addr:street":"Les S / N",
    "iso:country":"ES",
    "sg:address":"Urba Motes (les), S/n",
    "sg:city":"Grau I Platja",
    "sg:orig_category":"Inmobiliaria (agencias)",
    "sg:phone":"+34 962 84 27 28",
    "sg:postcode":"46730",
    "sg:province":"Valencia",
    "wof:name":"Castella Miralles Vicente",
    "wof:placetype":"venue"
},
  "geometry": {"coordinates":[-0.1727419943,39.0098228455],"type":"Point"}
}