{
  "type": "Feature",
  "properties": {
    "addr:full":"Plaz Ventas, 2 Bu\u00f1ol Valencia 46360",
    "addr:housenumber":"2",
    "addr:postcode":"46360",
    "addr:street":"Plaz Ventas",
    "iso:country":"ES",
    "sg:address":"Plaz Ventas, 2",
    "sg:city":"Bu\u00f1ol",
    "sg:orig_category":"Bancos",
    "sg:phone":"+34 962 50 07 01",
    "sg:postcode":"46360",
    "sg:province":"Valencia",
    "wof:name":"Banco Espa\u00f1ol De Credito S.a.",
    "wof:placetype":"venue"
},
  "geometry": {"coordinates":[-0.7906309962,39.4240646362],"type":"Point"}
}