{
  "type": "Feature",
  "properties": {
    "iso:country":"ES",
    "sg:address":"Calle de Fernando Amor Y Mayor, S/n",
    "sg:city":"Cordoba",
    "sg:orig_category":"Estudios, Instalaci\u00d3n De Climatizaci\u00d3n",
    "sg:phone":"+34 957 46 46 09",
    "sg:postcode":"14011",
    "sg:province":"C\u00f3rdoba",
    "wof:name":"Proteclisa S.l.",
    "wof:placetype":"venue"
},
  "geometry": {"coordinates":[-4.7955889702,37.8874702454],"type":"Point"}
}