{
  "type": "Feature",
  "properties": {
    "addr:full":"Peridiello, S/n Serin Asturias 33697",
    "addr:housenumber":"/ n",
    "addr:postcode":"33697",
    "addr:street":"Peridiello S",
    "iso:country":"ES",
    "sg:address":"Peridiello, S/n",
    "sg:city":"Serin",
    "sg:orig_category":"Poller\u00cda Y Caza (al Por Menor)",
    "sg:phone":"+34 985 97 67 81",
    "sg:postcode":"33697",
    "sg:province":"Asturias",
    "wof:name":"Granja Los Pinos S.a.t.",
    "wof:placetype":"venue"
},
  "geometry": {"coordinates":[-5.8097090721,43.5093383789],"type":"Point"}
}