{
  "type": "Feature",
  "properties": {
    "iso:country":"ES",
    "sg:address":"Ptda Campo Alto, 33",
    "sg:city":"Elda",
    "sg:orig_category":"Empresarios",
    "sg:phone":"+34 965 39 46 19",
    "sg:postcode":"03600",
    "sg:province":"Alicante",
    "wof:name":"Chinchilla Obras Y Reformas S.l.",
    "wof:placetype":"venue"
},
  "geometry": {"coordinates":[-0.7961040139,38.475315094],"type":"Point"}
}