{
  "type": "Feature",
  "properties": {
    "iso:country":"ES",
    "sg:address":"Plaz Ribera De Castilla, 7",
    "sg:city":"Valladolid",
    "sg:orig_category":"Molduras, Junquillos, Listones Y Molduras Perforadas",
    "sg:phone":"+34 983 25 04 53",
    "sg:postcode":"47010",
    "sg:province":"Valladolid",
    "wof:name":"Gonzalez Rodriguez Francisco Julian",
    "wof:placetype":"venue"
},
  "geometry": {"coordinates":[-4.7186889648,41.6649513245],"type":"Point"}
}