{
  "type": "Feature",
  "properties": {
    "addr:full":"Calle de Marcos Zapata, 13 Zaragoza Zaragoza 50010",
    "addr:housenumber":"13",
    "addr:postcode":"50010",
    "addr:street":"Calle De Marcos Zapata",
    "iso:country":"ES",
    "sg:address":"Calle de Marcos Zapata, 13",
    "sg:city":"Zaragoza",
    "sg:orig_category":"Cooperativas Agr\u00cdcolas",
    "sg:phone":"+34 976 32 46 63",
    "sg:postcode":"50010",
    "sg:province":"Zaragoza",
    "wof:name":"Shalom Sociedad Cooperativa Limitada",
    "wof:placetype":"venue"
},
  "geometry": {"coordinates":[-0.9061899781,41.6536712646],"type":"Point"}
}