{
  "type": "Feature",
  "properties": {
    "iso:country":"ES",
    "sg:address":"Calle de Pedro Heredia, 8",
    "sg:city":"Madrid",
    "sg:orig_category":"Prot\u00c9sicos Dentales",
    "sg:phone":"+34 917 26 43 25",
    "sg:postcode":"28028",
    "sg:province":"Madrid",
    "wof:name":"Protesis Avanzada S.l.",
    "wof:placetype":"venue"
},
  "geometry": {"coordinates":[-3.6657121181,40.4283447266],"type":"Point"}
}