{
  "type": "Feature",
  "properties": {
    "addr:full":"Calle de Jesus, 58 Valencia Valencia 46007",
    "addr:housenumber":"58",
    "addr:postcode":"46007",
    "addr:street":"Calle De Jesus",
    "iso:country":"ES",
    "sg:address":"Calle de Jesus, 58",
    "sg:city":"Valencia",
    "sg:orig_category":"Institutos De Belleza",
    "sg:phone":"+34 963 84 93 95",
    "sg:postcode":"46007",
    "sg:province":"Valencia",
    "wof:name":"Sarrion Jordan Maria Desamparados",
    "wof:placetype":"venue"
},
  "geometry": {"coordinates":[-0.3846850097,39.4649848938],"type":"Point"}
}