{
  "type": "Feature",
  "properties": {
    "addr:full":"Calle de Clavel, 3 Zamora Zamora 49010",
    "addr:housenumber":"3",
    "addr:postcode":"49010",
    "addr:street":"Calle De Clavel",
    "iso:country":"ES",
    "sg:address":"Calle de Clavel, 3",
    "sg:city":"Zamora",
    "sg:orig_category":"Piedra Natural",
    "sg:phone":"+34 980 51 48 15",
    "sg:postcode":"49010",
    "sg:province":"Zamora",
    "wof:name":"Miguel De Mena Eugenio",
    "wof:placetype":"venue"
},
  "geometry": {"coordinates":[-5.7416729927,41.5139427185],"type":"Point"}
}