{
  "type": "Feature",
  "properties": {
    "iso:country":"ES",
    "sg:address":"Librilla, S/n",
    "sg:city":"Espinardo",
    "sg:orig_category":"Comercio, Reparaci\u00d3n De Motocicletas, Bicicletas Y Piezas Sueltas",
    "sg:phone":"+34 968 83 04 89",
    "sg:postcode":"30100",
    "sg:province":"Murcia",
    "wof:name":"Motos Marian Mari S.l",
    "wof:placetype":"venue"
},
  "geometry": {"coordinates":[-1.1572519541,38.0077667236],"type":"Point"}
}