{
  "type": "Feature",
  "properties": {
    "iso:country":"ES",
    "sg:address":"Calle de Jose Maria Fernandez Lanseros, 4",
    "sg:city":"Madrid",
    "sg:orig_category":"Colchones (fabricaci\u00d3n, Al Por Mayor, Al Por Menor)",
    "sg:phone":"+34 917 26 89 61",
    "sg:postcode":"28017",
    "sg:province":"Madrid",
    "wof:name":"Caballero Martinez Luis Miguel",
    "wof:placetype":"venue"
},
  "geometry": {"coordinates":[-3.6577138901,40.4314613342],"type":"Point"}
}