{
  "type": "Feature",
  "properties": {
    "iso:country":"ES",
    "sg:address":"Av Jaume Iii, 18",
    "sg:city":"Palma",
    "sg:orig_category":"Notarios",
    "sg:phone":"+34 971 72 41 11",
    "sg:postcode":"07012",
    "sg:province":"Islas Baleares",
    "wof:name":"Jimenez Gallego Carlos",
    "wof:placetype":"venue"
},
  "geometry": {"coordinates":[2.643979311,39.5723419189],"type":"Point"}
}