{
  "type": "Feature",
  "properties": {
    "iso:country":"ES",
    "sg:address":"Calle de Tres Carabelas, 29",
    "sg:city":"Huelva",
    "sg:orig_category":"Producci\u00d3n De Abonos Y De Fertilizantes",
    "sg:phone":"+34 959 15 04 19",
    "sg:postcode":"21002",
    "sg:province":"Huelva",
    "wof:name":"Lopez Valero Rosario",
    "wof:placetype":"venue"
},
  "geometry": {"coordinates":[-6.9476208687,37.2774810791],"type":"Point"}
}