{
  "type": "Feature",
  "properties": {
    "iso:country":"ES",
    "sg:address":"Calle de Eskalmendi, 9",
    "sg:city":"Vitoria-gasteiz",
    "sg:orig_category":"Reposter\u00cdas",
    "sg:phone":"+34 945 27 75 94",
    "sg:postcode":"01013",
    "sg:province":"\u00c1lava",
    "wof:name":"Panaderia El Horno S. A.",
    "wof:placetype":"venue"
},
  "geometry": {"coordinates":[-2.6424520016,42.8726463318],"type":"Point"}
}