{
  "type": "Feature",
  "properties": {
    "addr:full":"Calle de Larga, 36 Molina Guadalajara 19300",
    "addr:housenumber":"36",
    "addr:postcode":"19300",
    "addr:street":"Calle De Larga",
    "iso:country":"ES",
    "sg:address":"Calle de Larga, 36",
    "sg:city":"Molina",
    "sg:orig_category":"Alimentaci\u00d3n General (al Por Menor)",
    "sg:phone":"+34 949 83 17 78",
    "sg:postcode":"19300",
    "sg:province":"Guadalajara",
    "wof:name":"Gascon Ortega Tomas",
    "wof:placetype":"venue"
},
  "geometry": {"coordinates":[-1.8909790516,40.846408844],"type":"Point"}
}