{
  "type": "Feature",
  "properties": {
    "addr:full":"Calle de Tomas Pelayo, 18 Zaragoza Zaragoza 50009",
    "addr:housenumber":"18",
    "addr:postcode":"50009",
    "addr:street":"Calle De Tomas Pelayo",
    "iso:country":"ES",
    "sg:address":"Calle de Tomas Pelayo, 18",
    "sg:city":"Zaragoza",
    "sg:orig_category":"Comercio De Piezas De Recambio Y De Accesorios De Veh\u00cdculos, Veh\u00cdculos Industriales",
    "sg:phone":"+34 976 56 12 67",
    "sg:postcode":"50009",
    "sg:province":"Zaragoza",
    "wof:name":"Recambios San Jose S.l.",
    "wof:placetype":"venue"
},
  "geometry": {"coordinates":[-0.9101700187,41.6319770813],"type":"Point"}
}