{
  "type": "Feature",
  "properties": {
    "addr:full":"Av. America, 7 Alcorcon Madrid 28922",
    "addr:housenumber":"7",
    "addr:postcode":"28922",
    "addr:street":"Av. America",
    "iso:country":"ES",
    "sg:address":"Av. America, 7",
    "sg:city":"Alcorcon",
    "sg:orig_category":"Muebles, Minoristas",
    "sg:phone":"+34 916 11 55 74",
    "sg:postcode":"28922",
    "sg:province":"Madrid",
    "sg:website":"www.azcue.com",
    "wof:name":"Aguado Mobiliario Tresaguas S.l.",
    "wof:placetype":"venue"
},
  "geometry": {"coordinates":[-3.831130743,40.3590545654],"type":"Point"}
}