{
  "type": "Feature",
  "properties": {
    "addr:full":"Calle de Tenderina, 66 Oviedo Asturias 33010",
    "addr:housenumber":"66",
    "addr:postcode":"33010",
    "addr:street":"Calle De Tenderina",
    "iso:country":"ES",
    "sg:address":"Calle de Tenderina, 66",
    "sg:city":"Oviedo",
    "sg:orig_category":"Bancos",
    "sg:phone":"+34 985 20 25 00",
    "sg:postcode":"33010",
    "sg:province":"Asturias",
    "wof:name":"Banc Sabadell S.a.",
    "wof:placetype":"venue"
},
  "geometry": {"coordinates":[-5.8327941895,43.3652153015],"type":"Point"}
}