{
  "type": "Feature",
  "properties": {
    "iso:country":"ES",
    "sg:address":"Calle de Sierra De Aralar, 50",
    "sg:city":"Donostia-san Sebastian",
    "sg:orig_category":"Molduras, Junquillos, Listones Y Molduras Perforadas",
    "sg:phone":"+34 943 45 09 86",
    "sg:postcode":"20014",
    "sg:province":"Guip\u00f9zcoa",
    "wof:name":"Ezcurdia Gorospe Juana Maria",
    "wof:placetype":"venue"
},
  "geometry": {"coordinates":[-1.9659149647,43.3094978333],"type":"Point"}
}