{
  "type": "Feature",
  "properties": {
    "iso:country":"ES",
    "sg:address":"Pl Santa Anna, 4",
    "sg:city":"Martorell",
    "sg:orig_category":"Publicidad (soportes Y Gesti\u00d3n)",
    "sg:phone":"+34 937 74 80 99",
    "sg:postcode":"08760",
    "sg:province":"Barcelona",
    "wof:name":"La Publicidad A Su Alcance S.l.l.",
    "wof:placetype":"venue"
},
  "geometry": {"coordinates":[1.9227950573,41.4784812927],"type":"Point"}
}