{
  "type": "Feature",
  "properties": {
    "addr:full":"Calle de Garcia Cabrelles, 4 Melilla Melilla 52002",
    "addr:housenumber":"4",
    "addr:postcode":"52002",
    "addr:street":"Calle De Garcia Cabrelles",
    "iso:country":"ES",
    "sg:address":"Calle de Garcia Cabrelles, 4",
    "sg:city":"Melilla",
    "sg:orig_category":"Alimentaci\u00d3n General (al Por Menor)",
    "sg:phone":"+34 952 68 03 53",
    "sg:postcode":"52002",
    "sg:province":"Melilla",
    "wof:name":"Ahmed Duduh Abdeselam",
    "wof:placetype":"venue"
},
  "geometry": {"coordinates":[-2.9461386204,35.2974395752],"type":"Point"}
}