{
  "type": "Feature",
  "properties": {
    "addr:full":"Calle de Rua De Dato, 6 Calatayud Zaragoza 50300",
    "addr:housenumber":"6",
    "addr:postcode":"50300",
    "addr:street":"Calle De Rua De Dato",
    "iso:country":"ES",
    "sg:address":"Calle de Rua De Dato, 6",
    "sg:city":"Calatayud",
    "sg:orig_category":"Panader\u00cdas, Panader\u00cdas",
    "sg:phone":"+34 976 88 12 43",
    "sg:postcode":"50300",
    "sg:province":"Zaragoza",
    "wof:name":"Ruiz De Morales Muscat Maria Isabel",
    "wof:placetype":"venue"
},
  "geometry": {"coordinates":[-1.6425559521,41.3526229858],"type":"Point"}
}