{
  "type": "Feature",
  "properties": {
    "addr:full":"Calle de Lujan Perez, 19 Atalaya Las Palmas 35450",
    "addr:housenumber":"19",
    "addr:postcode":"35450",
    "addr:street":"Calle De Lujan Perez",
    "iso:country":"ES",
    "sg:address":"Calle de Lujan Perez, 19",
    "sg:city":"Atalaya",
    "sg:orig_category":"Estancos",
    "sg:phone":"+34 928 88 27 88",
    "sg:postcode":"35450",
    "sg:province":"Las Palmas",
    "wof:name":"Mendoza Moreno Antonio",
    "wof:placetype":"venue"
},
  "geometry": {"coordinates":[-15.6319208145,28.1403903961],"type":"Point"}
}