{
  "type": "Feature",
  "properties": {
    "addr:full":"Calle de Carril Del Conde, 57 Madrid Madrid 28043",
    "addr:housenumber":"57",
    "addr:postcode":"madrid;28043",
    "addr:street":"Calle De Carril Del Conde",
    "iso:country":"ES",
    "sg:address":"Calle de Carril Del Conde, 57",
    "sg:city":"Madrid",
    "sg:orig_category":"Asociaciones, Organismos Culturales Y Socioeducativos",
    "sg:phone":"+34 913 00 52 40",
    "sg:postcode":"28043",
    "sg:province":"Madrid",
    "wof:name":"Derechos Civiles",
    "wof:placetype":"venue"
},
  "geometry": {"coordinates":[-3.6542720795,40.4611206055],"type":"Point"}
}