{
  "type": "Feature",
  "properties": {
    "addr:full":"Ctra Mancha Real, S/n Peal Becerro Ja\u00e9n 23460",
    "addr:housenumber":"s / n",
    "addr:postcode":"23460",
    "addr:street":"Ctra Mancha Real",
    "iso:country":"ES",
    "sg:address":"Ctra Mancha Real, S/n",
    "sg:city":"Peal Becerro",
    "sg:orig_category":"Productores Recolectores, Venta Directa De Vinos",
    "sg:phone":"+34 953 12 41 73",
    "sg:postcode":"23460",
    "sg:province":"Ja\u00e9n",
    "wof:name":"Berlanga Reyes Antonio",
    "wof:placetype":"venue"
},
  "geometry": {"coordinates":[-3.1217041016,37.9136810303],"type":"Point"}
}