{
  "type": "Feature",
  "properties": {
    "addr:full":"Calle de Cruces, S/n Villalpando Zamora 49630",
    "addr:housenumber":"s / n",
    "addr:postcode":"49630",
    "addr:street":"Calle De Cruces",
    "iso:country":"ES",
    "sg:address":"Calle de Cruces, S/n",
    "sg:city":"Villalpando",
    "sg:orig_category":"Procuradores",
    "sg:phone":"+34 980 66 04 39",
    "sg:postcode":"49630",
    "sg:province":"Zamora",
    "wof:name":"Carton Sancho Fernando",
    "wof:placetype":"venue"
},
  "geometry": {"coordinates":[-5.4124369621,41.8614768982],"type":"Point"}
}