{
  "type": "Feature",
  "properties": {
    "iso:country":"ES",
    "sg:address":"Calle de Ortega Y Gasset, 21",
    "sg:city":"Carrizal",
    "sg:orig_category":"Carnicer\u00cdas, Carnicer\u00cdas",
    "sg:phone":"+34 928 78 64 59",
    "sg:postcode":"35240",
    "sg:province":"Las Palmas",
    "wof:name":"Cadena Munich S.l.",
    "wof:placetype":"venue"
},
  "geometry": {"coordinates":[-15.4028100967,27.9109764099],"type":"Point"}
}