{
  "type": "Feature",
  "properties": {
    "addr:full":"Carrer de Reina M Cristina, 75 Palma Islas Baleares 07004",
    "addr:housenumber":"75",
    "addr:postcode":"07004",
    "addr:street":"Carrer De Reina M Cristina",
    "iso:country":"ES",
    "sg:address":"Carrer de Reina M Cristina, 75",
    "sg:city":"Palma",
    "sg:orig_category":"Promotores Constructores",
    "sg:phone":"+34 971 20 03 86",
    "sg:postcode":"07004",
    "sg:province":"Islas Baleares",
    "wof:name":"Grupo Mienes S.l.",
    "wof:placetype":"venue"
},
  "geometry": {"coordinates":[2.6568479538,39.5822906494],"type":"Point"}
}