{
  "type": "Feature",
  "properties": {
    "addr:full":"Calle de Argumosa, 19 Madrid Madrid 28012",
    "addr:housenumber":"19",
    "addr:postcode":"madrid;28012",
    "addr:street":"Calle De Argumosa",
    "iso:country":"ES",
    "sg:address":"Calle de Argumosa, 19",
    "sg:city":"Madrid",
    "sg:orig_category":"Centros Comerciales Y Grandes Tiendas",
    "sg:phone":"+34 915 27 60 59",
    "sg:postcode":"28012",
    "sg:province":"Madrid",
    "sg:website":"www.trofesport.es",
    "wof:name":"Trofesport S.l.",
    "wof:placetype":"venue"
},
  "geometry": {"coordinates":[-3.6986989975,40.4082450867],"type":"Point"}
}