{
  "type": "Feature",
  "properties": {
    "addr:full":"Ctra. Madrid, 64 Torrijos Toledo 45500",
    "addr:housenumber":"64",
    "addr:postcode":"45500",
    "addr:street":"Ctra. Madrid",
    "iso:country":"ES",
    "sg:address":"Ctra. Madrid, 64",
    "sg:city":"Torrijos",
    "sg:orig_category":"Agentes, Concesionarios Y Sucursales De Veh\u00cdculos",
    "sg:phone":"+34 925 76 19 12",
    "sg:postcode":"45500",
    "sg:province":"Toledo",
    "sg:website":"www.red.renault.es/martinandino",
    "wof:name":"Auto Martin-andino S. L.",
    "wof:placetype":"venue"
},
  "geometry": {"coordinates":[-4.2818388939,39.9835548401],"type":"Point"}
}