{
  "type": "Feature",
  "properties": {
    "iso:country":"ES",
    "sg:address":"Avda Polizon, S/n",
    "sg:city":"Playa De Arinaga",
    "sg:orig_category":"Promotores Constructores",
    "sg:phone":"+34 928 18 26 71",
    "sg:postcode":"35118",
    "sg:province":"Las Palmas",
    "wof:name":"Construcciones Gescor Arinaga S.l.",
    "wof:placetype":"venue"
},
  "geometry": {"coordinates":[-15.3931341171,27.855884552],"type":"Point"}
}