{
  "type": "Feature",
  "properties": {
    "addr:full":"Carrer de L'alcalde De Mostoles, 4 Barcelona Barcelona 08025",
    "addr:housenumber":"4",
    "addr:postcode":"08025",
    "addr:street":"Carrer De L'Alcalde De Mostoles",
    "iso:country":"ES",
    "sg:address":"Carrer de L'alcalde De Mostoles, 4",
    "sg:city":"Barcelona",
    "sg:orig_category":"Alimentaci\u00d3n General (al Por Menor)",
    "sg:phone":"+34 933 47 95 54",
    "sg:postcode":"08025",
    "sg:province":"Barcelona",
    "wof:name":"Dominguez Hernandez Emiliano",
    "wof:placetype":"venue"
},
  "geometry": {"coordinates":[2.167214632,41.4100532532],"type":"Point"}
}