{
  "type": "Feature",
  "properties": {
    "iso:country":"ES",
    "sg:address":"Avda Cala Llonga, 66",
    "sg:city":"Cala Llonga",
    "sg:orig_category":"Comerciantes Al Por Mayor De Vinos, Licores Y Alcoholes",
    "sg:phone":"+34 971 19 65 61",
    "sg:postcode":"07849",
    "sg:province":"Islas Baleares",
    "wof:name":"Oliva Gil Juan Ricardo",
    "wof:placetype":"venue"
},
  "geometry": {"coordinates":[1.5182499886,38.9548492432],"type":"Point"}
}