{
  "type": "Feature",
  "properties": {
    "addr:full":"Carrer de Alcanar, 35 Barcelona Barcelona 08003",
    "addr:housenumber":"35",
    "addr:postcode":"08003",
    "addr:street":"Carrer De Alcanar",
    "iso:country":"ES",
    "sg:address":"Carrer de Alcanar, 35",
    "sg:city":"Barcelona",
    "sg:orig_category":"Reposter\u00cdas",
    "sg:phone":"+34 932 21 51 19",
    "sg:postcode":"08003",
    "sg:province":"Barcelona",
    "wof:name":"Escopan S.a.",
    "wof:placetype":"venue"
},
  "geometry": {"coordinates":[2.1912889481,41.3789291382],"type":"Point"}
}