{
  "type": "Feature",
  "properties": {
    "addr:full":"Desvio Distante, S/n Isla Cristina Huelva 21410",
    "addr:housenumber":"s / n",
    "addr:postcode":"21410",
    "iso:country":"ES",
    "sg:address":"Desvio Distante, S/n",
    "sg:city":"Isla Cristina",
    "sg:orig_category":"Electrodom\u00c9sticos (al Por Menor)",
    "sg:phone":"+34 959 33 03 13",
    "sg:postcode":"21410",
    "sg:province":"Huelva",
    "wof:name":"Alvarez Rivas Antonio",
    "wof:placetype":"venue"
},
  "geometry": {"coordinates":[-7.2976617813,37.2327346802],"type":"Point"}
}