{
  "type": "Feature",
  "properties": {
    "addr:full":"Avda Reyes Catolicos, 6 Majadahonda Madrid 28220",
    "addr:housenumber":"6",
    "addr:postcode":"28220",
    "addr:street":"Avda Reyes Catolicos",
    "iso:country":"ES",
    "sg:address":"Avda Reyes Catolicos, 6",
    "sg:city":"Majadahonda",
    "sg:orig_category":"Fotograf\u00cda Y Cine: Aparatos, Pel\u00cdculas Y Accesorios (fabricaci\u00d3n, Al Por Mayor)",
    "sg:phone":"+34 916 34 11 28",
    "sg:postcode":"28220",
    "sg:province":"Madrid",
    "wof:name":"27 Iso S.l.",
    "wof:placetype":"venue"
},
  "geometry": {"coordinates":[-3.872219,40.47541],"type":"Point"}
}