{
  "type": "Feature",
  "properties": {
    "iso:country":"ES",
    "sg:address":"Carr Industria, 490",
    "sg:city":"Badalona",
    "sg:orig_category":"Artes Gr\u00c1ficas, Artes Pl\u00c1sticas (curso)",
    "sg:phone":"+34 933 98 73 46",
    "sg:postcode":"08918",
    "sg:province":"Barcelona",
    "wof:name":"Industria Grafica Mycval S.l.",
    "wof:placetype":"venue"
},
  "geometry": {"coordinates":[2.2355639935,41.4345779419],"type":"Point"}
}