{
  "type": "Feature",
  "properties": {
    "iso:country":"ES",
    "sg:address":"Avda. San Pelayo, 1",
    "sg:city":"Biloda",
    "sg:orig_category":"Electricidad: Instaladores",
    "sg:phone":"+34 945 36 40 85",
    "sg:postcode":"01195",
    "sg:province":"\u00c1lava",
    "wof:name":"Iba\u00f1ez Arrondo Jose",
    "wof:placetype":"venue"
},
  "geometry": {"coordinates":[-2.7876389027,42.8310089111],"type":"Point"}
}