{
  "type": "Feature",
  "properties": {
    "iso:country":"ES",
    "sg:address":"Avda Costa, 60",
    "sg:city":"Gijon",
    "sg:orig_category":"Librer\u00cdas",
    "sg:phone":"+34 985 33 77 12",
    "sg:postcode":"33201",
    "sg:province":"Asturias",
    "wof:name":"Magazin Cb",
    "wof:placetype":"venue"
},
  "geometry": {"coordinates":[-5.6586837769,43.5376701355],"type":"Point"}
}