{
  "type": "Feature",
  "properties": {
    "iso:country":"ES",
    "sg:address":"Carr Virtut, S/n",
    "sg:city":"Igualada",
    "sg:orig_category":"Transportes Por Carretera: Lotes Completos, Mercanc\u00cdas Diversas",
    "sg:phone":"+34 938 03 69 61",
    "sg:postcode":"08700",
    "sg:province":"Barcelona",
    "wof:name":"Sole Giral Filomena",
    "wof:placetype":"venue"
},
  "geometry": {"coordinates":[1.6223330498,41.5784225464],"type":"Point"}
}