{
  "type": "Feature",
  "properties": {
    "iso:country":"ES",
    "sg:address":"Calle de Camino De Marruecos, S/n",
    "sg:city":"Carmona",
    "sg:orig_category":"Ense\u00d1anza, Formaci\u00d3n Profesional: Aprendizaje",
    "sg:phone":"+34 954 19 60 59",
    "sg:postcode":"41410",
    "sg:province":"Sevilla",
    "sg:website":"www.losalcores.org",
    "wof:name":"Fomento Los Alcores S.l.",
    "wof:placetype":"venue"
},
  "geometry": {"coordinates":[-5.6037464142,37.4634742737],"type":"Point"}
}