{
  "type": "Feature",
  "properties": {
    "iso:country":"ES",
    "sg:address":"Calle de Julio Romero De Torres, 22",
    "sg:city":"Torreperogil",
    "sg:orig_category":"Empresas De Desmonte",
    "sg:phone":"+34 953 77 67 42",
    "sg:postcode":"23320",
    "sg:province":"Ja\u00e9n",
    "wof:name":"Lopez Urrutia Antonio Manuel",
    "wof:placetype":"venue"
},
  "geometry": {"coordinates":[-3.2909300327,38.0379333496],"type":"Point"}
}