{
  "type": "Feature",
  "properties": {
    "addr:full":"Calle de Vega De Contranquil, 5 Cangas Onis Asturias 33550",
    "addr:housenumber":"5",
    "addr:postcode":"33550",
    "addr:street":"Calle De Vega De Contranquil;Onis Asturias",
    "iso:country":"ES",
    "sg:address":"Calle de Vega De Contranquil, 5",
    "sg:city":"Cangas Onis",
    "sg:orig_category":"Ense\u00d1anza: Idiomas",
    "sg:phone":"+34 985 84 82 83",
    "sg:postcode":"33550",
    "sg:province":"Asturias",
    "wof:name":"Carrio Castro Mirian",
    "wof:placetype":"venue"
},
  "geometry": {"coordinates":[-5.1302790642,43.3507957458],"type":"Point"}
}