{
  "type": "Feature",
  "properties": {
    "iso:country":"ES",
    "sg:address":"Carr Hort De Bordes, 9",
    "sg:city":"Benissa",
    "sg:orig_category":"Molduras, Junquillos, Listones Y Molduras Perforadas",
    "sg:phone":"+34 965 73 20 54",
    "sg:postcode":"03720",
    "sg:province":"Alicante",
    "wof:name":"Santa Creus Bertomeu Consuelo",
    "wof:placetype":"venue"
},
  "geometry": {"coordinates":[0.0480309986,38.7143936157],"type":"Point"}
}