{
  "type": "Feature",
  "properties": {
    "iso:country":"ES",
    "sg:address":"Avda Eusebio Gomez, 20",
    "sg:city":"Saron",
    "sg:orig_category":"Supermercados Y Hipermercados",
    "sg:phone":"+34 942 56 43 77",
    "sg:postcode":"39620",
    "sg:province":"Cantabria",
    "wof:name":"Servicios Alimentarios Sarom 2000 S.l.",
    "wof:placetype":"venue"
},
  "geometry": {"coordinates":[-3.8528900146,43.3240203857],"type":"Point"}
}