{
  "type": "Feature",
  "properties": {
    "iso:country":"ES",
    "sg:address":"Urb Torre Guil, S/n",
    "sg:city":"Sangonera La Verde O Ermita Nueva",
    "sg:orig_category":"Administraci\u00d3n En Agricultura",
    "sg:phone":"+34 968 86 82 00",
    "sg:postcode":"30833",
    "sg:province":"Murcia",
    "wof:name":"Sociedad Agraria De Transformacion Num 255",
    "wof:placetype":"venue"
},
  "geometry": {"coordinates":[-1.2069989443,37.9333190918],"type":"Point"}
}