{
  "type": "Feature",
  "properties": {
    "iso:country":"ES",
    "sg:address":"Calle de Carrera, 39",
    "sg:city":"Toledo",
    "sg:orig_category":"Construcci\u00d3n De Edificios Residenciales Y No Residenciales",
    "sg:phone":"+34 925 25 23 35",
    "sg:postcode":"45003",
    "sg:province":"Toledo",
    "wof:name":"Construcciones Angel Fermin S.l.",
    "wof:placetype":"venue"
},
  "geometry": {"coordinates":[-4.021490097,39.862953186],"type":"Point"}
}