{
  "type": "Feature",
  "properties": {
    "iso:country":"ES",
    "sg:address":"Ctra Nacional 620, Km. 0004,5",
    "sg:city":"Calabazanos",
    "sg:orig_category":"Agentes, Concesionarios Y Sucursales De Veh\u00cdculos",
    "sg:phone":"+34 979 77 60 36",
    "sg:postcode":"34190",
    "sg:province":"Palencia",
    "sg:website":"www.autopal.com",
    "wof:name":"Autopal S.a.",
    "wof:placetype":"venue"
},
  "geometry": {"coordinates":[-4.5164442062,41.9515914917],"type":"Point"}
}