{
  "type": "Feature",
  "properties": {
    "addr:full":"Calle de Calderon De La Barca, 9 Granada Granada 18006",
    "addr:housenumber":"9",
    "addr:postcode":"18006",
    "addr:street":"Calle De Calderon De La Barca",
    "iso:country":"ES",
    "sg:address":"Calle de Calderon De La Barca, 9",
    "sg:city":"Granada",
    "sg:orig_category":"Cajas De Ahorro",
    "sg:phone":"+34 958 81 55 62",
    "sg:postcode":"18006",
    "sg:province":"Granada",
    "wof:name":"Cajagranada",
    "wof:placetype":"venue"
},
  "geometry": {"coordinates":[-3.5951650143,37.1654510498],"type":"Point"}
}