{
  "type": "Feature",
  "properties": {
    "addr:full":"Pol Ind La Vi\u00f1a, 35 Algaba Sevilla 41980",
    "addr:housenumber":"35",
    "addr:postcode":"41980",
    "addr:street":"Vin\u0303A",
    "iso:country":"ES",
    "sg:address":"Pol Ind La Vi\u00f1a, 35",
    "sg:city":"Algaba",
    "sg:orig_category":"Herboristas (al Por Menor)",
    "sg:phone":"+34 954 37 28 81",
    "sg:postcode":"41980",
    "sg:province":"Sevilla",
    "wof:name":"Herbodis S. L.",
    "wof:placetype":"venue"
},
  "geometry": {"coordinates":[-6.0153942108,37.4607162476],"type":"Point"}
}