{
  "type": "Feature",
  "properties": {
    "iso:country":"ES",
    "sg:address":"Calle de Mirasierra (de), 12",
    "sg:city":"Fuenlabrada",
    "sg:orig_category":"Doctores En Medicina",
    "sg:phone":"+34 916 15 12 81",
    "sg:postcode":"28941",
    "sg:province":"Madrid",
    "wof:name":"Gordo Martinez Jose Antonio",
    "wof:placetype":"venue"
},
  "geometry": {"coordinates":[-3.8011500835,40.2888412476],"type":"Point"}
}