{
  "type": "Feature",
  "properties": {
    "addr:full":"Calle de Ibarruri Dolores, 1 Bilbao Vizcaya 48012",
    "addr:housenumber":"1",
    "addr:postcode":"48012",
    "addr:street":"Calle De Ibarruri Dolores",
    "iso:country":"ES",
    "sg:address":"Calle de Ibarruri Dolores, 1",
    "sg:city":"Bilbao",
    "sg:orig_category":"Venta, Instalaci\u00d3n De Calefacci\u00d3n",
    "sg:phone":"+34 944 22 40 36",
    "sg:postcode":"48012",
    "sg:province":"Vizcaya",
    "wof:name":"Incafrisa",
    "wof:placetype":"venue"
},
  "geometry": {"coordinates":[-2.941879034,43.2555274963],"type":"Point"}
}