{
  "type": "Feature",
  "properties": {
    "iso:country":"ES",
    "sg:address":"Calle de Pormetxeta, 4",
    "sg:city":"San Vicente De Barakaldo",
    "sg:orig_category":"Inmobiliaria (agencias)",
    "sg:phone":"+34 944 38 75 45",
    "sg:postcode":"48901",
    "sg:province":"Vizcaya",
    "wof:name":"Promociones Castilla Munibe S.l.",
    "wof:placetype":"venue"
},
  "geometry": {"coordinates":[-2.9849500656,43.2972946167],"type":"Point"}
}