{
  "type": "Feature",
  "properties": {
    "iso:country":"ES",
    "sg:address":"Avda Aurora, 59",
    "sg:city":"Malaga",
    "sg:orig_category":"Formaci\u00d3n Continuada (variada)",
    "sg:phone":"+34 952 31 91 84",
    "sg:postcode":"29002",
    "sg:province":"M\u00e1laga",
    "wof:name":"Ab Servicios Profesionales S.l.",
    "wof:placetype":"venue"
},
  "geometry": {"coordinates":[-4.438571,36.715557],"type":"Point"}
}