{
  "type": "Feature",
  "properties": {
    "iso:country":"ES",
    "sg:address":"Trva Maragateria, 14",
    "sg:city":"Astorga",
    "sg:orig_category":"Alquiler De Gr\u00daas",
    "sg:phone":"+34 987 61 87 29",
    "sg:postcode":"24700",
    "sg:province":"Le\u00f3n",
    "wof:name":"Alonso Perez Agustin Felipe",
    "wof:placetype":"venue"
},
  "geometry": {"coordinates":[-6.0573301315,42.4597511292],"type":"Point"}
}