{
  "type": "Feature",
  "properties": {
    "iso:country":"ES",
    "sg:address":"Carr Mossen Jacint Verdaguer, 39",
    "sg:city":"Palamos",
    "sg:orig_category":"Hoteles",
    "sg:phone":"+34 972 31 43 86",
    "sg:postcode":"17230",
    "sg:province":"Girona",
    "wof:name":"Hostal Residencia Catalina",
    "wof:placetype":"venue"
},
  "geometry": {"coordinates":[3.1326699257,41.8490753174],"type":"Point"}
}