{
  "type": "Feature",
  "properties": {
    "addr:full":"Carrer de Doctor Trueta, 4 Manresa Barcelona 08243",
    "addr:housenumber":"4",
    "addr:postcode":"08243",
    "addr:street":"Carrer De Doctor Trueta",
    "iso:country":"ES",
    "sg:address":"Carrer de Doctor Trueta, 4",
    "sg:city":"Manresa",
    "sg:orig_category":"Ropa Para Se\u00d1oras (al Por Menor)",
    "sg:phone":"+34 938 73 73 04",
    "sg:postcode":"08243",
    "sg:province":"Barcelona",
    "wof:name":"Mendoza Gimenez Gerardo",
    "wof:placetype":"venue"
},
  "geometry": {"coordinates":[1.8322900534,41.7349967957],"type":"Point"}
}