{
  "type": "Feature",
  "properties": {
    "iso:country":"ES",
    "sg:address":"Calle de Claudio Marcelo, 8",
    "sg:city":"Cordoba",
    "sg:orig_category":"Relojer\u00cda (al Por Menor, Reparaci\u00d3n)",
    "sg:phone":"+34 957 47 00 66",
    "sg:postcode":"14002",
    "sg:province":"C\u00f3rdoba",
    "wof:name":"Vazquez Cepero Manuel",
    "wof:placetype":"venue"
},
  "geometry": {"coordinates":[-4.7776827812,37.8846359253],"type":"Point"}
}