{
  "type": "Feature",
  "properties": {
    "iso:country":"ES",
    "sg:address":"Cami Oliva (de L'), 20",
    "sg:city":"Oliva",
    "sg:orig_category":"Inmobiliaria (agencias)",
    "sg:phone":"+34 977 21 76 84",
    "sg:postcode":"43007",
    "sg:province":"Tarragona",
    "wof:name":"Vital S.l.",
    "wof:placetype":"venue"
},
  "geometry": {"coordinates":[1.2524516582,41.1261405945],"type":"Point"}
}