{
  "type": "Feature",
  "properties": {
    "addr:full":"Carrer de Sant Narcis, 3 Barcelona Barcelona 08030",
    "addr:housenumber":"3",
    "addr:postcode":"08030",
    "addr:street":"Carrer De Sant Narcis",
    "iso:country":"ES",
    "sg:address":"Carrer de Sant Narcis, 3",
    "sg:city":"Barcelona",
    "sg:orig_category":"Empresas De Carpinter\u00cda De Madera",
    "sg:phone":"+34 933 11 25 56",
    "sg:postcode":"08030",
    "sg:province":"Barcelona",
    "wof:name":"Fernandez Carrera Jose Maria",
    "wof:placetype":"venue"
},
  "geometry": {"coordinates":[2.1924619675,41.4312858582],"type":"Point"}
}