{
  "type": "Feature",
  "properties": {
    "addr:full":"Calle de Juan Xxiii, 2 Aviles Asturias 33401",
    "addr:housenumber":"2",
    "addr:postcode":"33401",
    "addr:street":"Calle De Juan Xxiii",
    "iso:country":"ES",
    "sg:address":"Calle de Juan Xxiii, 2",
    "sg:city":"Aviles",
    "sg:orig_category":"Porcelanas, Azulejos (fabricaci\u00d3n, Al Por Mayor)",
    "sg:phone":"+34 985 56 46 57",
    "sg:postcode":"33401",
    "sg:province":"Asturias",
    "wof:name":"Gonzalez Rodriguez Jose Maria",
    "wof:placetype":"venue"
},
  "geometry": {"coordinates":[-5.9280838966,43.5559883118],"type":"Point"}
}