{
  "type": "Feature",
  "properties": {
    "iso:country":"ES",
    "sg:address":"Rio Mi\u00f1o, 15",
    "sg:city":"Pqe. Boadilla",
    "sg:orig_category":"Edici\u00d3n De Diarios, Revistas, Boletines",
    "sg:phone":"+34 915 47 18 59",
    "sg:postcode":"28669",
    "sg:province":"Madrid",
    "sg:website":"www.ed-mediterraneo.com",
    "wof:name":"Agedime S.l.",
    "wof:placetype":"venue"
},
  "geometry": {"coordinates":[-3.8769915104,40.4052467346],"type":"Point"}
}