{
  "type": "Feature",
  "properties": {
    "iso:country":"ES",
    "sg:address":"Calle de Zubiaga, 16",
    "sg:city":"Mungia",
    "sg:orig_category":"Carnicer\u00cdas, Carnicer\u00cdas",
    "sg:phone":"+34 946 74 01 19",
    "sg:postcode":"48100",
    "sg:province":"Vizcaya",
    "wof:name":"Oar Canales Carlos",
    "wof:placetype":"venue"
},
  "geometry": {"coordinates":[-2.8481490612,43.3554077148],"type":"Point"}
}