{
  "type": "Feature",
  "properties": {
    "addr:full":"Avda Principe De Espa\u00d1a, 11 San Felipe Santa Cruz De Tenerife 38430",
    "addr:housenumber":"11",
    "addr:postcode":"38430",
    "addr:street":"Avda Principe De Espan\u0303A",
    "iso:country":"ES",
    "sg:address":"Avda Principe De Espa\u00d1a, 11",
    "sg:city":"San Felipe",
    "sg:orig_category":"M\u00c9dicos: Cirug\u00cda Ortop\u00c9dica Y Traumatolog\u00cda",
    "sg:phone":"+34 922 81 50 50",
    "sg:postcode":"38430",
    "sg:province":"Santa Cruz De Tenerife",
    "wof:name":"Ulibarri Catalano Nestor Luis",
    "wof:placetype":"venue"
},
  "geometry": {"coordinates":[-16.7204761505,28.3677654266],"type":"Point"}
}