{
  "type": "Feature",
  "properties": {
    "addr:full":"Pase Cementerio, 28 Consuegra Toledo 45700",
    "addr:housenumber":"28",
    "addr:postcode":"45700",
    "addr:street":"Cementerio",
    "iso:country":"ES",
    "sg:address":"Pase Cementerio, 28",
    "sg:city":"Consuegra",
    "sg:orig_category":"Cerrajer\u00cda, Ferrallista",
    "sg:phone":"+34 925 48 05 86",
    "sg:postcode":"45700",
    "sg:province":"Toledo",
    "wof:name":"Villarejo Torres Sebastian",
    "wof:placetype":"venue"
},
  "geometry": {"coordinates":[-3.6054260731,39.4659919739],"type":"Point"}
}