{
  "type": "Feature",
  "properties": {
    "addr:full":"Pase Estacion (de La), 62 Valdemoro Madrid 28340",
    "addr:postcode":"28340",
    "iso:country":"ES",
    "sg:address":"Pase Estacion (de La), 62",
    "sg:city":"Valdemoro",
    "sg:orig_category":"Inmobiliaria (agencias)",
    "sg:phone":"+34 918 09 57 39",
    "sg:postcode":"28340",
    "sg:province":"Madrid",
    "wof:name":"Jamersoni S.l.",
    "wof:placetype":"venue"
},
  "geometry": {"coordinates":[-3.6738090515,40.1909751892],"type":"Point"}
}