{
  "type": "Feature",
  "properties": {
    "iso:country":"ES",
    "sg:address":"Calle de Calzada De Ponga, 38",
    "sg:city":"Cangas Onis",
    "sg:orig_category":"Promotores Constructores",
    "sg:phone":"+34 985 84 89 13",
    "sg:postcode":"33550",
    "sg:province":"Asturias",
    "wof:name":"Construcciones Cadenaba 2003 S.l.",
    "wof:placetype":"venue"
},
  "geometry": {"coordinates":[-5.1304678917,43.3474006653],"type":"Point"}
}