{
  "type": "Feature",
  "properties": {
    "addr:full":"Calle de Mayor, 27 Burlada Navarra 31600",
    "addr:housenumber":"27",
    "addr:postcode":"31600",
    "addr:street":"Calle De Mayor",
    "iso:country":"ES",
    "sg:address":"Calle de Mayor, 27",
    "sg:city":"Burlada",
    "sg:orig_category":"Supermercados Y Hipermercados",
    "sg:phone":"+34 948 38 23 86",
    "sg:postcode":"31600",
    "sg:province":"Navarra",
    "wof:name":"Distribuidora Internacional De Alimentacion S.a.",
    "wof:placetype":"venue"
},
  "geometry": {"coordinates":[-1.6172850132,42.8247756958],"type":"Point"}
}