{
  "type": "Feature",
  "properties": {
    "iso:country":"ES",
    "sg:address":"Carrer de Nuria, 62",
    "sg:city":"Premia Mar",
    "sg:orig_category":"Guarder\u00cdas",
    "sg:phone":"+34 937 51 39 67",
    "sg:postcode":"08330",
    "sg:province":"Barcelona",
    "wof:name":"Mateo Carrion Angeles",
    "wof:placetype":"venue"
},
  "geometry": {"coordinates":[2.3573110104,41.4967765808],"type":"Point"}
}