{
  "type": "Feature",
  "properties": {
    "addr:full":"Pol Ind Las Labradas, 9999 Tudela Navarra 31500",
    "addr:postcode":"9999;31500",
    "addr:street":"Labradas",
    "iso:country":"ES",
    "sg:address":"Pol Ind Las Labradas, 9999",
    "sg:city":"Tudela",
    "sg:orig_category":"Acero: Productos Sider\u00dargicos Y Transformados (fabricaci\u00d3n, Negocio)",
    "sg:phone":"+34 948 82 68 98",
    "sg:postcode":"31500",
    "sg:province":"Navarra",
    "sg:website":"www.acinesgon.com",
    "wof:name":"Acinesgon Navarra S.l.",
    "wof:placetype":"venue"
},
  "geometry": {"coordinates":[-1.4821481705,42.1872329712],"type":"Point"}
}