{
  "type": "Feature",
  "properties": {
    "addr:full":"Calle de Bentaguayre, 1 Palmas De Gran Canaria Las Palmas 35009",
    "addr:housenumber":"1",
    "addr:postcode":"35009",
    "addr:street":"Calle De Bentaguayre",
    "iso:country":"ES",
    "sg:address":"Calle de Bentaguayre, 1",
    "sg:city":"Palmas De Gran Canaria",
    "sg:orig_category":"Estancos",
    "sg:phone":"+34 928 46 74 22",
    "sg:postcode":"35009",
    "sg:province":"Las Palmas",
    "wof:name":"Gonzalez Santana Maria Del Pino",
    "wof:placetype":"venue"
},
  "geometry": {"coordinates":[-15.4292421341,28.1526260376],"type":"Point"}
}