{
  "type": "Feature",
  "properties": {
    "addr:full":"Carr De Pius Xii, 16 Benicarlo Castell\u00f3n 12580",
    "addr:housenumber":"16",
    "addr:postcode":"12580",
    "addr:street":"Carr De Pius Xii",
    "iso:country":"ES",
    "sg:address":"Carr De Pius Xii, 16",
    "sg:city":"Benicarlo",
    "sg:orig_category":"Ropa Para Beb\u00c9s Y Ni\u00d1os (confecci\u00d3n, Al Por Mayor)",
    "sg:phone":"+34 964 47 37 59",
    "sg:postcode":"12580",
    "sg:province":"Castell\u00f3n",
    "wof:name":"Martinez Fibla Consuelo",
    "wof:placetype":"venue"
},
  "geometry": {"coordinates":[0.4253610075,40.417263031],"type":"Point"}
}