{
  "type": "Feature",
  "properties": {
    "addr:full":"Calle de Tetuan, 3 Sevilla Sevilla 41001",
    "addr:housenumber":"3",
    "addr:postcode":"41001",
    "addr:street":"Calle De Tetuan",
    "iso:country":"ES",
    "sg:address":"Calle de Tetuan, 3",
    "sg:city":"Sevilla",
    "sg:orig_category":"Loter\u00cda Y T\u00d3mbola",
    "sg:phone":"+34 954 21 49 22",
    "sg:postcode":"41001",
    "sg:province":"Sevilla",
    "wof:name":"Montero Gomez Maria De Los Angeles",
    "wof:placetype":"venue"
},
  "geometry": {"coordinates":[-5.9951038361,37.389995575],"type":"Point"}
}