{
  "type": "Feature",
  "properties": {
    "iso:country":"ES",
    "sg:address":"Irizar Pasealekua, 2",
    "sg:city":"Bergara",
    "sg:orig_category":"Bancos",
    "sg:phone":"+34 943 76 29 47",
    "sg:postcode":"20570",
    "sg:province":"Guip\u00f9zcoa",
    "wof:name":"Banco Espa\u00f1ol De Credito S.a.",
    "wof:placetype":"venue"
},
  "geometry": {"coordinates":[-2.4135479927,43.1189041138],"type":"Point"}
}