{
  "type": "Feature",
  "properties": {
    "addr:full":"Svdor Dali, 1 Aljaraque Huelva 21110",
    "addr:housenumber":"1",
    "addr:postcode":"21110",
    "addr:street":"Dali",
    "iso:country":"ES",
    "sg:address":"Svdor Dali, 1",
    "sg:city":"Aljaraque",
    "sg:orig_category":"Administradores De Bienes Y Delegados De Comunidades De Propietarios",
    "sg:phone":"+34 959 52 15 80",
    "sg:postcode":"21110",
    "sg:province":"Huelva",
    "wof:name":"Castillo Guerrero Manuel",
    "wof:placetype":"venue"
},
  "geometry": {"coordinates":[-7.0241990089,37.2709159851],"type":"Point"}
}