{
  "type": "Feature",
  "properties": {
    "addr:full":"Plaz Dean Mazas, 4 Jaen Ja\u00e9n 23001",
    "addr:housenumber":"4;jae\u0301n",
    "addr:postcode":"23001",
    "addr:street":"Plaz Dean Mazas",
    "iso:country":"ES",
    "sg:address":"Plaz Dean Mazas, 4",
    "sg:city":"Jaen",
    "sg:orig_category":"Asesor\u00cda Fiscal Y Jur\u00cddica",
    "sg:phone":"+34 953 19 08 49",
    "sg:postcode":"23001",
    "sg:province":"Ja\u00e9n",
    "wof:name":"Aguera Checa Juan",
    "wof:placetype":"venue"
},
  "geometry": {"coordinates":[-3.7873268127,37.7660217285],"type":"Point"}
}