{
  "type": "Feature",
  "properties": {
    "addr:full":"Calle de Inventor La Cierva, 22 Langreo Asturias 33930",
    "addr:housenumber":"22",
    "addr:postcode":"33930",
    "addr:street":"Calle De Inventor La Cierva",
    "iso:country":"ES",
    "sg:address":"Calle de Inventor La Cierva, 22",
    "sg:city":"Langreo",
    "sg:orig_category":"Fisioterapia",
    "sg:phone":"+34 985 67 38 11",
    "sg:postcode":"33930",
    "sg:province":"Asturias",
    "wof:name":"Fernandez Rodriguez Amparo",
    "wof:placetype":"venue"
},
  "geometry": {"coordinates":[-5.6954188347,43.3069725037],"type":"Point"}
}