{
  "type": "Feature",
  "properties": {
    "addr:full":"Ctra Manresa, S/n Solsona Lleida 25280",
    "addr:housenumber":"s / n",
    "addr:postcode":"25280",
    "addr:street":"Ctra Manresa",
    "iso:country":"ES",
    "sg:address":"Ctra Manresa, S/n",
    "sg:city":"Solsona",
    "sg:orig_category":"Tapiceros Y Tapiceros",
    "sg:phone":"+34 973 48 11 45",
    "sg:postcode":"25280",
    "sg:province":"Lleida",
    "wof:name":"Bgv S.l.",
    "wof:placetype":"venue"
},
  "geometry": {"coordinates":[1.5221300125,41.995059967],"type":"Point"}
}