{
  "type": "Feature",
  "properties": {
    "addr:full":"Romeral, S/n Arcos Frontera C\u00e1diz 11630",
    "addr:housenumber":"s / n",
    "addr:postcode":"11630",
    "addr:street":"Romeral",
    "iso:country":"ES",
    "sg:address":"Romeral, S/n",
    "sg:city":"Arcos Frontera",
    "sg:orig_category":"Fabricaci\u00d3n De Tapices Y Moquetas Para Suelos Y Paredes",
    "sg:phone":"+34 956 70 14 66",
    "sg:postcode":"11630",
    "sg:province":"C\u00e1diz",
    "wof:name":"Naqsh S.a.l.",
    "wof:placetype":"venue"
},
  "geometry": {"coordinates":[-5.8115739822,36.7515716553],"type":"Point"}
}