{
  "type": "Feature",
  "properties": {
    "addr:full":"Ptda El Altet, S/n Alqueria Asnar Alicante 03829",
    "addr:housenumber":"s / n",
    "addr:postcode":"03829",
    "addr:street":"Ptda El Altet",
    "iso:country":"ES",
    "sg:address":"Ptda El Altet, S/n",
    "sg:city":"Alqueria Asnar",
    "sg:orig_category":"Hilaturas, Hilos Y Actividades Relacionadas",
    "sg:phone":"+34 965 33 57 75",
    "sg:postcode":"03829",
    "sg:province":"Alicante",
    "wof:name":"Orejuela Garcia Manuel",
    "wof:placetype":"venue"
},
  "geometry": {"coordinates":[-0.4268589914,38.7745857239],"type":"Point"}
}