{
  "type": "Feature",
  "properties": {
    "iso:country":"ES",
    "sg:address":"Carr Marti Rubi-secretari, 101",
    "sg:city":"Cabaneta",
    "sg:orig_category":"Electricidad: Instaladores",
    "sg:phone":"+34 971 60 26 78",
    "sg:postcode":"07141",
    "sg:province":"Islas Baleares",
    "wof:name":"Comercial Instaladora Marratxi Sl",
    "wof:placetype":"venue"
},
  "geometry": {"coordinates":[2.741590023,39.6156005859],"type":"Point"}
}