{
  "type": "Feature",
  "properties": {
    "addr:full":"Els Gremis, 3 Xativa Valencia 46800",
    "addr:housenumber":"3",
    "addr:postcode":"46800",
    "addr:street":"Gremis",
    "iso:country":"ES",
    "sg:address":"Els Gremis, 3",
    "sg:city":"Xativa",
    "sg:orig_category":"Transportes Internacionales",
    "sg:phone":"+34 962 28 72 20",
    "sg:postcode":"46800",
    "sg:province":"Valencia",
    "wof:name":"Camarrosa Export S.l.",
    "wof:placetype":"venue"
},
  "geometry": {"coordinates":[-0.5200830102,38.9934272766],"type":"Point"}
}