{
  "type": "Feature",
  "properties": {
    "addr:full":"Calle de Pravia, 3 Mieres Asturias 33600",
    "addr:housenumber":"3",
    "addr:postcode":"33600",
    "addr:street":"Calle De Pravia",
    "iso:country":"ES",
    "sg:address":"Calle de Pravia, 3",
    "sg:city":"Mieres",
    "sg:orig_category":"T\u00c9cnicos Veterinarios",
    "sg:phone":"+34 984 18 01 65",
    "sg:postcode":"33600",
    "sg:province":"Asturias",
    "wof:name":"Maria Llaneza Fernandez (clinica Veterinaria)",
    "wof:placetype":"venue"
},
  "geometry": {"coordinates":[-5.7793149948,43.2551116943],"type":"Point"}
}