{
  "type": "Feature",
  "properties": {
    "addr:full":"Plaz General Primo De Rivera, 1 Oviedo Asturias 33001",
    "addr:housenumber":"1",
    "addr:postcode":"33001",
    "addr:street":"Rivera",
    "iso:country":"ES",
    "sg:address":"Plaz General Primo De Rivera, 1",
    "sg:city":"Oviedo",
    "sg:orig_category":"Bordado, Marcado A Medida",
    "sg:phone":"+34 985 28 91 62",
    "sg:postcode":"33001",
    "sg:province":"Asturias",
    "wof:name":"Lopez Garcia Julia",
    "wof:placetype":"venue"
},
  "geometry": {"coordinates":[-5.8500437737,43.3675575256],"type":"Point"}
}