{
  "type": "Feature",
  "properties": {
    "addr:full":"Calle de Rafael Sarandeses, 5 Lugones Asturias 33420",
    "addr:housenumber":"5",
    "addr:postcode":"33420",
    "addr:street":"Calle De Rafael Sarandeses",
    "iso:country":"ES",
    "sg:address":"Calle de Rafael Sarandeses, 5",
    "sg:city":"Lugones",
    "sg:orig_category":"Doctores En Medicina",
    "sg:phone":"+34 985 26 78 40",
    "sg:postcode":"33420",
    "sg:province":"Asturias",
    "wof:name":"Vigil Rio Ana Valentina",
    "wof:placetype":"venue"
},
  "geometry": {"coordinates":[-5.8088469505,43.4020614624],"type":"Point"}
}