{
  "type": "Feature",
  "properties": {
    "addr:full":"Calle de Policarpo Balzola, 10 Irun Guip\u00f9zcoa 20302",
    "addr:housenumber":"10",
    "addr:postcode":"20302",
    "addr:street":"Calle De Policarpo Balzola;Guipu\u0300Zcoa",
    "iso:country":"ES",
    "sg:address":"Calle de Policarpo Balzola, 10",
    "sg:city":"Irun",
    "sg:orig_category":"M\u00c9dicos: Otorrinolaringolog\u00cda",
    "sg:phone":"+34 943 61 16 25",
    "sg:postcode":"20302",
    "sg:province":"Guip\u00f9zcoa",
    "wof:name":"Tellechea Urtizberea Pedro",
    "wof:placetype":"venue"
},
  "geometry": {"coordinates":[-1.7932130098,43.342250824],"type":"Point"}
}