{
  "type": "Feature",
  "properties": {
    "iso:country":"ES",
    "sg:address":"Calle de Mediodia Chica, 6",
    "sg:city":"Madrid",
    "sg:orig_category":"Comerciantes Al Por Mayor De Vinos, Licores Y Alcoholes",
    "sg:phone":"+34 913 66 53 15",
    "sg:postcode":"28005",
    "sg:province":"Madrid",
    "wof:name":"Martos Rozas Abel",
    "wof:placetype":"venue"
},
  "geometry": {"coordinates":[-3.7115740776,40.409866333],"type":"Point"}
}