{
  "type": "Feature",
  "properties": {
    "addr:full":"Avda Paz De (la), 21 Logro\u00f1o La Rioja 26004",
    "addr:housenumber":"21",
    "addr:postcode":"26004",
    "addr:street":"Avda Paz De La;Rioja",
    "iso:country":"ES",
    "sg:address":"Avda Paz De (la), 21",
    "sg:city":"Logro\u00f1o",
    "sg:orig_category":"M\u00c9dicos: Ginecolog\u00cda Y Obstetricia",
    "sg:phone":"+34 941 25 38 40",
    "sg:postcode":"26004",
    "sg:province":"La Rioja",
    "wof:name":"Campeny Talleda Esteban",
    "wof:placetype":"venue"
},
  "geometry": {"coordinates":[-2.4377861023,42.4653549194],"type":"Point"}
}