{
  "type": "Feature",
  "properties": {
    "iso:country":"ES",
    "sg:address":"Calle de Gaztambide, 19",
    "sg:city":"Madrid",
    "sg:orig_category":"Producci\u00d3n, Venta De Productos De Agricultura Biol\u00d3gica",
    "sg:phone":"+34 915 44 71 59",
    "sg:postcode":"28015",
    "sg:province":"Madrid",
    "wof:name":"Aulago S. A.",
    "wof:placetype":"venue"
},
  "geometry": {"coordinates":[-3.7156944275,40.4324836731],"type":"Point"}
}