{
  "type": "Feature",
  "properties": {
    "iso:country":"ES",
    "sg:address":"Calle de B - Poligono Industrial De Asipo, S/n",
    "sg:city":"Coru\u00d1o",
    "sg:orig_category":"Farmacias (repartici\u00d3n Y Al Por Mayor)",
    "sg:phone":"+34 985 26 31 47",
    "sg:postcode":"33428",
    "sg:province":"Asturias",
    "wof:name":"Centro Farmaceutico Del Norte S. A.",
    "wof:placetype":"venue"
},
  "geometry": {"coordinates":[-5.8358402252,43.4143867493],"type":"Point"}
}