{
  "type": "Feature",
  "properties": {
    "iso:country":"ES",
    "sg:address":"Carrer de Balmes, 305",
    "sg:city":"Barcelona",
    "sg:orig_category":"Impuestos, Tesoro P\u00dablico",
    "sg:phone":"+34 932 00 31 51",
    "sg:postcode":"08006",
    "sg:province":"Barcelona",
    "wof:name":"Juan Alfonso Mestres Morral S. L.",
    "wof:placetype":"venue"
},
  "geometry": {"coordinates":[2.1454029083,41.4022445679],"type":"Point"}
}