{
  "type": "Feature",
  "properties": {
    "addr:full":"Ctra Circunvalacion, 1 Ubeda Ja\u00e9n 23400",
    "addr:housenumber":"1",
    "addr:postcode":"23400",
    "addr:street":"Ctra Circunvalacion;Jae\u0301N",
    "iso:country":"ES",
    "sg:address":"Ctra Circunvalacion, 1",
    "sg:city":"Ubeda",
    "sg:orig_category":"Acero: Productos Sider\u00dargicos Y Transformados (fabricaci\u00d3n, Negocio)",
    "sg:phone":"+34 953 79 50 44",
    "sg:postcode":"23400",
    "sg:province":"Ja\u00e9n",
    "wof:name":"Marceliano Martin S.a.",
    "wof:placetype":"venue"
},
  "geometry": {"coordinates":[-3.3701190948,38.0197181702],"type":"Point"}
}