{
  "type": "Feature",
  "properties": {
    "iso:country":"ES",
    "sg:address":"Calle de Palafox, 27",
    "sg:city":"Madrid",
    "sg:orig_category":"Reposter\u00cdas",
    "sg:phone":"+34 914 48 91 41",
    "sg:postcode":"28010",
    "sg:province":"Madrid",
    "wof:name":"Lanagran Gay Diego",
    "wof:placetype":"venue"
},
  "geometry": {"coordinates":[-3.7015891075,40.4321556091],"type":"Point"}
}