{
  "type": "Feature",
  "properties": {
    "iso:country":"ES",
    "sg:address":"Avda Numancia, 36",
    "sg:city":"Calahorra",
    "sg:orig_category":"Centros De Coordinaci\u00d3n",
    "sg:phone":"+34 941 13 00 02",
    "sg:postcode":"26500",
    "sg:province":"La Rioja",
    "wof:name":"Calvo Jimenez Maria Pilar",
    "wof:placetype":"venue"
},
  "geometry": {"coordinates":[-1.968659997,42.3028678894],"type":"Point"}
}