{
  "type": "Feature",
  "properties": {
    "iso:country":"ES",
    "sg:address":"Calle de Marques De Lozoya, 38",
    "sg:city":"Madrid",
    "sg:orig_category":"Promotores Constructores",
    "sg:phone":"+34 915 73 26 10",
    "sg:postcode":"28007",
    "sg:province":"Madrid",
    "wof:name":"Alderrustic S.l",
    "wof:placetype":"venue"
},
  "geometry": {"coordinates":[-3.6628870964,40.4188499451],"type":"Point"}
}