{
  "type": "Feature",
  "properties": {
    "addr:full":"Av. Puxeiros, 17 Mos Pontevedra 36416",
    "addr:housenumber":"17",
    "addr:postcode":"36416",
    "addr:street":"Av. Puxeiros",
    "iso:country":"ES",
    "sg:address":"Av. Puxeiros, 17",
    "sg:city":"Mos",
    "sg:orig_category":"M\u00c1rmoles, Granitos Y Piedras Naturales",
    "sg:phone":"+34 986 33 63 42",
    "sg:postcode":"36416",
    "sg:province":"Pontevedra",
    "wof:name":"Grabados R.s. S.l.",
    "wof:placetype":"venue"
},
  "geometry": {"coordinates":[-8.6025533676,42.2035369873],"type":"Point"}
}