{
  "type": "Feature",
  "properties": {
    "iso:country":"ES",
    "sg:address":"Calle de Julio Cesar, 3",
    "sg:city":"Camas",
    "sg:orig_category":"Formaci\u00d3n Continuada (variada)",
    "sg:phone":"+34 955 98 13 38",
    "sg:postcode":"41900",
    "sg:province":"Sevilla",
    "wof:name":"Pozo Trinidad Emilio",
    "wof:placetype":"venue"
},
  "geometry": {"coordinates":[-6.0391840935,37.4028396606],"type":"Point"}
}