{
  "type": "Feature",
  "properties": {
    "iso:country":"ES",
    "sg:address":"Rua Policarpo Sanz, 17",
    "sg:city":"Vigo",
    "sg:orig_category":"Asesor\u00cda Sobre Comunicaci\u00d3n De Empresas",
    "sg:phone":"+34 986 22 90 45",
    "sg:postcode":"36202",
    "sg:province":"Pontevedra",
    "wof:name":"Santiago Y Alonso Asesores C.b.",
    "wof:placetype":"venue"
},
  "geometry": {"coordinates":[-8.7224769592,42.237651825],"type":"Point"}
}