{
  "type": "Feature",
  "properties": {
    "iso:country":"ES",
    "sg:address":"Avda Juan Carlos I, 6",
    "sg:city":"Burgo Osma",
    "sg:orig_category":"Ense\u00d1anza, Formaci\u00d3n Profesional: Aprendizaje",
    "sg:phone":"+34 975 36 04 56",
    "sg:postcode":"42300",
    "sg:province":"Soria",
    "wof:name":"Delegacion Territorial De Soria",
    "wof:placetype":"venue"
},
  "geometry": {"coordinates":[-3.0679440498,41.5875282288],"type":"Point"}
}