{
  "type": "Feature",
  "properties": {
    "iso:country":"ES",
    "sg:address":"Calle de Micer Masco, 15",
    "sg:city":"Valencia",
    "sg:orig_category":"Profesiones M\u00c9dicas, Param\u00c9dicas",
    "sg:phone":"+34 963 62 31 37",
    "sg:postcode":"46010",
    "sg:province":"Valencia",
    "wof:name":"Estelles Catala Francisco Jose",
    "wof:placetype":"venue"
},
  "geometry": {"coordinates":[-0.362428993,39.475566864],"type":"Point"}
}