{
  "type": "Feature",
  "properties": {
    "addr:full":"Carrer de Paris, 151 Barcelona Barcelona 08036",
    "addr:housenumber":"151",
    "addr:postcode":"08036",
    "addr:street":"Carrer De Paris",
    "iso:country":"ES",
    "sg:address":"Carrer de Paris, 151",
    "sg:city":"Barcelona",
    "sg:orig_category":"Artes Gr\u00c1ficas, Artes Pl\u00c1sticas: Material Y Suministros (al Por Menor)",
    "sg:phone":"+34 933 21 13 74",
    "sg:postcode":"08036",
    "sg:province":"Barcelona",
    "wof:name":"Interventa 2000 S.l.",
    "wof:placetype":"venue"
},
  "geometry": {"coordinates":[2.150580883,41.3917694092],"type":"Point"}
}