{
  "type": "Feature",
  "properties": {
    "addr:full":"Calle de Marques De Figueroa, 4 Coru\u00d1a La Coru\u00f1a 15007",
    "addr:housenumber":"4",
    "addr:postcode":"15007",
    "addr:street":"Calle De Marques De Figueroa;La Corun\u0303A",
    "iso:country":"ES",
    "sg:address":"Calle de Marques De Figueroa, 4",
    "sg:city":"Coru\u00d1a",
    "sg:orig_category":"Ingeniero",
    "sg:phone":"+34 981 15 37 74",
    "sg:postcode":"15007",
    "sg:province":"La Coru\u00f1a",
    "sg:website":"www.inpenor.com",
    "wof:name":"Inpenor S.l.",
    "wof:placetype":"venue"
},
  "geometry": {"coordinates":[-8.4073505402,43.3541221619],"type":"Point"}
}