{
  "type": "Feature",
  "properties": {
    "addr:full":"Calle de Cuna, 51 Sevilla Sevilla 41004",
    "addr:housenumber":"51",
    "addr:postcode":"41004",
    "addr:street":"Calle De Cuna",
    "iso:country":"ES",
    "sg:address":"Calle de Cuna, 51",
    "sg:city":"Sevilla",
    "sg:orig_category":"Fabricaci\u00d3n, Venta De Cuadros, Accesorios Para Enmarcar",
    "sg:phone":"+34 954 22 99 94",
    "sg:postcode":"41004",
    "sg:province":"Sevilla",
    "wof:name":"Molduras Y Laminas S.l.",
    "wof:placetype":"venue"
},
  "geometry": {"coordinates":[-5.9933190346,37.3905677795],"type":"Point"}
}