{
  "type": "Feature",
  "properties": {
    "addr:full":"Avda Compostela, 37 Padron A Coru\u00f1a 15900",
    "addr:housenumber":"37",
    "addr:postcode":"15900",
    "addr:street":"Avda Compostela;Padron A Corun\u0303A",
    "iso:country":"ES",
    "sg:address":"Avda Compostela, 37",
    "sg:city":"Padron",
    "sg:orig_category":"Art\u00cdculos De Regalo (al Por Menor)",
    "sg:phone":"+34 981 81 70 41",
    "sg:postcode":"15900",
    "sg:province":"A Coru\u00f1a",
    "wof:name":"Suarez Bandin Sara",
    "wof:placetype":"venue"
},
  "geometry": {"coordinates":[-8.6594991684,42.7372970581],"type":"Point"}
}