{
  "type": "Feature",
  "properties": {
    "addr:full":"Rua Conde De Vallellano, 45 Carballi\u00f1o Ourense 32500",
    "addr:housenumber":"45",
    "addr:postcode":"32500",
    "addr:street":"Rua Conde De Vallellano",
    "iso:country":"ES",
    "sg:address":"Rua Conde De Vallellano, 45",
    "sg:city":"Carballi\u00f1o",
    "sg:classifiers":[
        {
            "category":"Autos & Motor Vehicles",
            "subcategory":"Automobile Sales",
            "type":"Retail Goods"
        }
    ],
    "sg:phone":"+34 988 27 27 05",
    "sg:postcode":"32500",
    "sg:province":"Ourense",
    "wof:name":"Autoescola Carballi\u00f1o S.a.",
    "wof:placetype":"venue"
},
  "geometry": {"coordinates":[-8.0768079758,42.430934906],"type":"Point"}
}