{
  "type": "Feature",
  "properties": {
    "addr:full":"Calle de Marques De Nervion, 14 Sevilla Sevilla 41005",
    "addr:housenumber":"14",
    "addr:postcode":"41005",
    "addr:street":"Calle De Marques De Nervion",
    "iso:country":"ES",
    "sg:address":"Calle de Marques De Nervion, 14",
    "sg:city":"Sevilla",
    "sg:orig_category":"Maquinaria Para Industrias Diversas",
    "sg:phone":"+34 954 58 41 83",
    "sg:postcode":"41005",
    "sg:province":"Sevilla",
    "wof:name":"Crispaima S.l.",
    "wof:placetype":"venue"
},
  "geometry": {"coordinates":[-5.9679942131,37.3864097595],"type":"Point"}
}