{
  "type": "Feature",
  "properties": {
    "addr:full":"Plaz Reyna Manescau, 2 Malaga M\u00e1laga 29002",
    "addr:housenumber":"2",
    "addr:postcode":"29002",
    "addr:street":"Malaga Ma\u0301Laga",
    "iso:country":"ES",
    "sg:address":"Plaz Reyna Manescau, 2",
    "sg:city":"Malaga",
    "sg:orig_category":"Arreglo, Reparaci\u00d3n, Piezas Sueltas De Televisi\u00d3n, V\u00cddeo, Hi",
    "sg:phone":"+34 952 32 07 10",
    "sg:postcode":"29002",
    "sg:province":"M\u00e1laga",
    "wof:name":"Morales Salcedo Miguel",
    "wof:placetype":"venue"
},
  "geometry": {"coordinates":[-4.434469223,36.7052383423],"type":"Point"}
}