{
  "type": "Feature",
  "properties": {
    "iso:country":"ES",
    "sg:address":"Rua Don Gonzalo (de), 18",
    "sg:city":"Pontevedra",
    "sg:orig_category":"Quincaller\u00cda (al Por Menor)",
    "sg:phone":"+34 986 85 44 66",
    "sg:postcode":"36002",
    "sg:province":"Pontevedra",
    "wof:name":"Varela Pedrosa Rafael German",
    "wof:placetype":"venue"
},
  "geometry": {"coordinates":[-8.6439981461,42.4327774048],"type":"Point"}
}