{
  "type": "Feature",
  "properties": {
    "iso:country":"ES",
    "sg:address":"Rua Peregrina (da), 51",
    "sg:city":"Pontevedra",
    "sg:orig_category":"Asociaciones Y Clubs Deportivos",
    "sg:phone":"+34 986 86 32 77",
    "sg:postcode":"36003",
    "sg:province":"Pontevedra",
    "wof:name":"Couceiro Raposeiras Jose Manuel",
    "wof:placetype":"venue"
},
  "geometry": {"coordinates":[-8.6416492462,42.4282646179],"type":"Point"}
}