{
  "type": "Feature",
  "properties": {
    "addr:full":"Calle de Santos Martires, 9 Talavera Reina Toledo 45600",
    "addr:housenumber":"9",
    "addr:postcode":"45600",
    "addr:street":"Calle De Santos Martires",
    "iso:country":"ES",
    "sg:address":"Calle de Santos Martires, 9",
    "sg:city":"Talavera Reina",
    "sg:orig_category":"Pintura Y Barniz (al Por Menor)",
    "sg:phone":"+34 925 80 39 17",
    "sg:postcode":"45600",
    "sg:province":"Toledo",
    "wof:name":"Industrias Quimicas Talavera S. A.",
    "wof:placetype":"venue"
},
  "geometry": {"coordinates":[-4.8314089775,39.9643440247],"type":"Point"}
}