{
  "type": "Feature",
  "properties": {
    "iso:country":"ES",
    "sg:address":"La Virreina, 5",
    "sg:city":"Agoitz",
    "sg:orig_category":"Confecci\u00d3n De Trajes Para Se\u00d1oras",
    "sg:phone":"+34 948 33 60 60",
    "sg:postcode":"31430",
    "sg:province":"Navarra",
    "wof:name":"Goiburu Oqui\u00f1ena Maria Luisa",
    "wof:placetype":"venue"
},
  "geometry": {"coordinates":[-1.3684949875,42.7859115601],"type":"Point"}
}