{
  "type": "Feature",
  "properties": {
    "iso:country":"ES",
    "sg:address":"A. Golf, S/n",
    "sg:city":"Nueva Andalucia",
    "sg:orig_category":"Asociaciones Y Clubs Deportivos",
    "sg:phone":"+34 952 81 47 55",
    "sg:postcode":"29660",
    "sg:province":"M\u00e1laga",
    "wof:name":"Mangas Espuche Jose Luis",
    "wof:placetype":"venue"
},
  "geometry": {"coordinates":[-4.9586529732,36.5108718872],"type":"Point"}
}