{
  "type": "Feature",
  "properties": {
    "addr:full":"Calle de Avena (de La), 44 Leganes Madrid 28914",
    "addr:housenumber":"44",
    "addr:postcode":"28914",
    "addr:street":"Calle De Avena De La",
    "iso:country":"ES",
    "sg:address":"Calle de Avena (de La), 44",
    "sg:city":"Leganes",
    "sg:orig_category":"Promotores Constructores",
    "sg:phone":"+34 916 89 83 41",
    "sg:postcode":"28914",
    "sg:province":"Madrid",
    "wof:name":"Proyectados Prozam S.l.",
    "wof:placetype":"venue"
},
  "geometry": {"coordinates":[-3.7837758064,40.3289489746],"type":"Point"}
}