{
  "type": "Feature",
  "properties": {
    "iso:country":"ES",
    "sg:address":"Mercat Corts, 95",
    "sg:city":"Barcelona",
    "sg:orig_category":"Frutas Y Legumbres Frescas (al Por Mayor)",
    "sg:phone":"+34 934 91 38 18",
    "sg:postcode":"08014",
    "sg:province":"Barcelona",
    "wof:name":"Repolles Contel Roberto",
    "wof:placetype":"venue"
},
  "geometry": {"coordinates":[2.1317999363,41.3847885132],"type":"Point"}
}