{
  "type": "Feature",
  "properties": {
    "addr:full":"Ctra Valencia (de), S/n Campillo Altobuey Cuenca 16210",
    "addr:postcode":"16210",
    "addr:street":"Ctra Valencia De S / N Campillo",
    "iso:country":"ES",
    "sg:address":"Ctra Valencia (de), S/n",
    "sg:city":"Campillo Altobuey",
    "sg:orig_category":"Mec\u00c1nico Del Autom\u00d3vil",
    "sg:phone":"+34 969 33 72 48",
    "sg:postcode":"16210",
    "sg:province":"Cuenca",
    "wof:name":"Moragon Mazcu\u00f1an Emiliano",
    "wof:placetype":"venue"
},
  "geometry": {"coordinates":[-1.7931189537,39.6124000549],"type":"Point"}
}