{
  "type": "Feature",
  "properties": {
    "addr:full":"Calle de Almanzor, 27 Coria C\u00e1ceres 10800",
    "addr:housenumber":"27",
    "addr:postcode":"10800",
    "addr:street":"Calle De Almanzor;Ca\u0301Ceres",
    "iso:country":"ES",
    "sg:address":"Calle de Almanzor, 27",
    "sg:city":"Coria",
    "sg:orig_category":"Fotograf\u00cda Art\u00cdstica Y Retratos",
    "sg:phone":"+34 927 50 09 13",
    "sg:postcode":"10800",
    "sg:province":"C\u00e1ceres",
    "sg:website":"www.karpint.com",
    "wof:name":"Carpintero Garcia Luis Felipe",
    "wof:placetype":"venue"
},
  "geometry": {"coordinates":[-6.5345153809,39.9847335815],"type":"Point"}
}