{
  "type": "Feature",
  "properties": {
    "iso:country":"ES",
    "sg:address":"Av Catalunya, 12",
    "sg:city":"Agramunt",
    "sg:orig_category":"Art\u00cdculos Funerarios (al Por Menor)",
    "sg:phone":"+34 973 39 08 62",
    "sg:postcode":"25310",
    "sg:province":"Lleida",
    "wof:name":"Torne Creus Jose Maria",
    "wof:placetype":"venue"
},
  "geometry": {"coordinates":[1.0961270332,41.7840766907],"type":"Point"}
}