{
  "type": "Feature",
  "properties": {
    "addr:full":"Calle de Merida, 2 Montijo Badajoz 06480",
    "addr:housenumber":"2",
    "addr:postcode":"06480",
    "addr:street":"Calle De Merida",
    "iso:country":"ES",
    "sg:address":"Calle de Merida, 2",
    "sg:city":"Montijo",
    "sg:orig_category":"Peluqueros: De Se\u00d1oras",
    "sg:phone":"+34 924 45 52 70",
    "sg:postcode":"06480",
    "sg:province":"Badajoz",
    "wof:name":"Lechon Naranjo Fernando",
    "wof:placetype":"venue"
},
  "geometry": {"coordinates":[-6.6134586334,38.9081230164],"type":"Point"}
}