{
  "type": "Feature",
  "properties": {
    "addr:full":"Calle de Libertad, 44 Ejea De Los Caballeros Zaragoza 50600",
    "addr:housenumber":"44",
    "addr:postcode":"50600",
    "addr:street":"Calle De Libertad",
    "iso:country":"ES",
    "sg:address":"Calle de Libertad, 44",
    "sg:city":"Ejea De Los Caballeros",
    "sg:orig_category":"Mec\u00c1nico Del Autom\u00d3vil",
    "sg:phone":"+34 976 66 08 34",
    "sg:postcode":"50600",
    "sg:province":"Zaragoza",
    "wof:name":"Talleres Villarreal Y Casanova S.l",
    "wof:placetype":"venue"
},
  "geometry": {"coordinates":[-1.1400003433,42.1228752136],"type":"Point"}
}