{
  "type": "Feature",
  "properties": {
    "addr:full":"Calle de Fuente Canonigos, S/n Tudela Navarra 31500",
    "addr:housenumber":"s",
    "addr:postcode":"31500",
    "addr:street":"Calle De Fuente Canonigos;/ N",
    "iso:country":"ES",
    "sg:address":"Calle de Fuente Canonigos, S/n",
    "sg:city":"Tudela",
    "sg:orig_category":"Comercio, Reparaci\u00d3n De Motocicletas, Bicicletas Y Piezas Sueltas",
    "sg:phone":"+34 948 84 71 03",
    "sg:postcode":"31500",
    "sg:province":"Navarra",
    "wof:name":"Ciclos Gamen S.l.",
    "wof:placetype":"venue"
},
  "geometry": {"coordinates":[-1.5997630358,42.0562133789],"type":"Point"}
}