{
  "type": "Feature",
  "properties": {
    "addr:full":"Pl. S. Fortia, 1 Figueres Girona 17600",
    "addr:housenumber":"1",
    "addr:postcode":"17600",
    "addr:street":"Pl. S. Fortia",
    "iso:country":"ES",
    "sg:address":"Pl. S. Fortia, 1",
    "sg:city":"Figueres",
    "sg:orig_category":"Inmobiliaria (agencias)",
    "sg:phone":"+34 972 50 71 88",
    "sg:postcode":"17600",
    "sg:province":"Girona",
    "wof:name":"Cdad.propietarios Pl.sibila De Fortia 1",
    "wof:placetype":"venue"
},
  "geometry": {"coordinates":[2.9581100941,42.2656898499],"type":"Point"}
}