{
  "type": "Feature",
  "properties": {
    "iso:country":"ES",
    "sg:address":"Calle de Velarde, 16",
    "sg:city":"Palmas De Gran Canaria",
    "sg:orig_category":"Promotores Constructores",
    "sg:phone":"+34 928 22 33 40",
    "sg:postcode":"35010",
    "sg:province":"Las Palmas",
    "wof:name":"Comunidad De Propietarios De Velarde N\u00ba 16",
    "wof:placetype":"venue"
},
  "geometry": {"coordinates":[-15.4397764206,28.1326389313],"type":"Point"}
}