{
  "type": "Feature",
  "properties": {
    "iso:country":"ES",
    "sg:address":"C. Colom, 1",
    "sg:city":"Llagostera",
    "sg:orig_category":"Ropa Para Se\u00d1oras (al Por Menor)",
    "sg:phone":"+34 972 83 16 40",
    "sg:postcode":"17240",
    "sg:province":"Girona",
    "wof:name":"Martin Pareja Maria Elvira",
    "wof:placetype":"venue"
},
  "geometry": {"coordinates":[2.9727549553,41.8591918945],"type":"Point"}
}