{
  "type": "Feature",
  "properties": {
    "iso:country":"ES",
    "sg:address":"C/ Antonio Machado, 32",
    "sg:city":"Paterna",
    "sg:orig_category":"Electricidad: Instaladores",
    "sg:phone":"+34 961 36 50 94",
    "sg:postcode":"46980",
    "sg:province":"Valencia",
    "wof:name":"Nucoa S. L.",
    "wof:placetype":"venue"
},
  "geometry": {"coordinates":[-0.4470039904,39.5050468445],"type":"Point"}
}