{
  "type": "Feature",
  "properties": {
    "addr:full":"Cmno Vado (del), 2 Zaragoza Zaragoza 50014",
    "addr:housenumber":"2",
    "addr:postcode":"50014",
    "addr:street":"Cmno Vado Del",
    "iso:country":"ES",
    "sg:address":"Cmno Vado (del), 2",
    "sg:city":"Zaragoza",
    "sg:orig_category":"Cer\u00c1micas: Material Y Suministros",
    "sg:phone":"+34 976 29 01 33",
    "sg:postcode":"50014",
    "sg:province":"Zaragoza",
    "wof:name":"Multiceramica S.l.",
    "wof:placetype":"venue"
},
  "geometry": {"coordinates":[-0.8813189864,41.6517295837],"type":"Point"}
}