{
  "type": "Feature",
  "properties": {
    "addr:full":"Avda Sierra Pambley, 51 Villablino Le\u00f3n 24100",
    "addr:housenumber":"51",
    "addr:postcode":"24100",
    "addr:street":"Avda Sierra Pambley",
    "iso:country":"ES",
    "sg:address":"Avda Sierra Pambley, 51",
    "sg:city":"Villablino",
    "sg:orig_category":"Empresas De Limpieza",
    "sg:phone":"+34 987 47 17 38",
    "sg:postcode":"24100",
    "sg:province":"Le\u00f3n",
    "wof:name":"Gomez Balsera Maximo",
    "wof:placetype":"venue"
},
  "geometry": {"coordinates":[-6.3163490295,42.9398651123],"type":"Point"}
}