{
  "type": "Feature",
  "properties": {
    "iso:country":"ES",
    "sg:address":"Carrer de Marina, 48",
    "sg:city":"Lloret Mar",
    "sg:orig_category":"Empresarios",
    "sg:phone":"+34 972 37 42 22",
    "sg:postcode":"17310",
    "sg:province":"Girona",
    "wof:name":"Promocions I Explotacions Costa Brava S.l.",
    "wof:placetype":"venue"
},
  "geometry": {"coordinates":[2.8525600433,41.7030487061],"type":"Point"}
}