{
  "type": "Feature",
  "properties": {
    "iso:country":"ES",
    "sg:address":"C/ Blas Orts Sanchez, 15",
    "sg:city":"Elche",
    "sg:orig_category":"Sindicatos Y Colegios Profesionales",
    "sg:phone":"+34 965 42 77 77",
    "sg:postcode":"03203",
    "sg:province":"Alicante",
    "wof:name":"Asociacion Local De Empresarios De Auto Taxis",
    "wof:placetype":"venue"
},
  "geometry": {"coordinates":[-0.6961209774,38.2564620972],"type":"Point"}
}