{
  "type": "Feature",
  "properties": {
    "addr:full":"Avda Rosario (del), 10 Cuarte Huerva Zaragoza 50410",
    "addr:housenumber":"10",
    "addr:postcode":"50410",
    "addr:street":"Avda Rosario Del",
    "iso:country":"ES",
    "sg:address":"Avda Rosario (del), 10",
    "sg:city":"Cuarte Huerva",
    "sg:orig_category":"Piscinas, Accesorios, Suministros (fabricaci\u00d3n, Al Por Mayor)",
    "sg:phone":"+34 976 46 34 50",
    "sg:postcode":"50410",
    "sg:province":"Zaragoza",
    "sg:website":"www.sepp.es",
    "wof:name":"Sociedad Espa\u00f1ola De Productos Y Pistinas S.a.",
    "wof:placetype":"venue"
},
  "geometry": {"coordinates":[-0.9331629872,41.6001396179],"type":"Point"}
}