{
  "type": "Feature",
  "properties": {
    "addr:full":"Calle de Hernan Perez, 20 Sinarcas Valencia 46320",
    "addr:housenumber":"20",
    "addr:postcode":"46320",
    "addr:street":"Calle De Hernan Perez",
    "iso:country":"ES",
    "sg:address":"Calle de Hernan Perez, 20",
    "sg:city":"Sinarcas",
    "sg:orig_category":"Intercambios, Trueques",
    "sg:phone":"+34 962 31 50 54",
    "sg:postcode":"46320",
    "sg:province":"Valencia",
    "wof:name":"Garcia Monterde Angel",
    "wof:placetype":"venue"
},
  "geometry": {"coordinates":[-1.2294889688,39.7340316772],"type":"Point"}
}