{
  "type": "Feature",
  "properties": {
    "iso:country":"ES",
    "sg:address":"Carrer de Proven\u00c7a, 138",
    "sg:city":"Barcelona",
    "sg:orig_category":"Delineantes",
    "sg:phone":"+34 934 51 78 58",
    "sg:postcode":"08029",
    "sg:province":"Barcelona",
    "wof:name":"Serra Soler Lluis",
    "wof:placetype":"venue"
},
  "geometry": {"coordinates":[2.1513030529,41.386882782],"type":"Point"}
}