{
  "type": "Feature",
  "properties": {
    "iso:country":"ES",
    "sg:address":"Calle de Mariano Pola, 66",
    "sg:city":"Gijon",
    "sg:orig_category":"Agencias Y Agentes Comerciales, Representantes",
    "sg:phone":"+34 985 32 28 74",
    "sg:postcode":"33212",
    "sg:province":"Asturias",
    "wof:name":"Europa Representaciones Industriales S.l.",
    "wof:placetype":"venue"
},
  "geometry": {"coordinates":[-5.6814689636,43.540271759],"type":"Point"}
}