{
  "type": "Feature",
  "properties": {
    "iso:country":"ES",
    "sg:address":"Carr Raval, 45",
    "sg:city":"Hostalric",
    "sg:orig_category":"Ense\u00d1anza Secundaria: Colegios Y Escuelas Privadas",
    "sg:phone":"+34 972 86 40 11",
    "sg:postcode":"17450",
    "sg:province":"Girona",
    "wof:name":"Ajuntament D'hostalric",
    "wof:placetype":"venue"
},
  "geometry": {"coordinates":[2.631333828,41.743057251],"type":"Point"}
}