{
  "type": "Feature",
  "properties": {
    "addr:full":"Calle de Progreso, 19 Burriana Castell\u00f3n 12530",
    "addr:housenumber":"19",
    "addr:postcode":"12530",
    "addr:street":"Calle De Progreso",
    "iso:country":"ES",
    "sg:address":"Calle de Progreso, 19",
    "sg:city":"Burriana",
    "sg:orig_category":"Carnicer\u00cdas, Carnicer\u00cdas",
    "sg:phone":"+34 964 51 41 59",
    "sg:postcode":"12530",
    "sg:province":"Castell\u00f3n",
    "wof:name":"Gual Vilalta Joaquin",
    "wof:placetype":"venue"
},
  "geometry": {"coordinates":[-0.0916189998,39.887550354],"type":"Point"}
}