{
  "type": "Feature",
  "properties": {
    "iso:country":"ES",
    "sg:address":"Calle de Rocio (del), 12",
    "sg:city":"Linea De La Concepcion",
    "sg:orig_category":"Molduras, Junquillos, Listones Y Molduras Perforadas",
    "sg:phone":"+34 956 17 54 78",
    "sg:postcode":"11300",
    "sg:province":"C\u00e1diz",
    "wof:name":"Pe\u00f1a Flamenca Cultural Linense",
    "wof:placetype":"venue"
},
  "geometry": {"coordinates":[-5.3580589294,36.1639900208],"type":"Point"}
}