{
  "type": "Feature",
  "properties": {
    "iso:country":"ES",
    "sg:address":"Calle de Martinez Izquierdo, 48",
    "sg:city":"Madrid",
    "sg:orig_category":"Arquitectos",
    "sg:phone":"+34 913 56 16 06",
    "sg:postcode":"28028",
    "sg:province":"Madrid",
    "wof:name":"Navarro Mossenta Nogal Arquitectos S.l",
    "wof:placetype":"venue"
},
  "geometry": {"coordinates":[-3.6664969921,40.4348526001],"type":"Point"}
}