{
  "type": "Feature",
  "properties": {
    "iso:country":"ES",
    "sg:address":"Calle de Dolores Romero, 6",
    "sg:city":"Madrid",
    "sg:orig_category":"Ense\u00d1anza, Formaci\u00d3n Profesional: Aprendizaje",
    "sg:phone":"+34 917 25 07 58",
    "sg:postcode":"28028",
    "sg:province":"Madrid",
    "wof:name":"Hermanos De Las Escuelas Cristianas F S C Distrito Central Curia Provincial",
    "wof:placetype":"venue"
},
  "geometry": {"coordinates":[-3.6646940708,40.4251441956],"type":"Point"}
}