{
  "type": "Feature",
  "properties": {
    "addr:full":"Calle de Manuel Lasala, 4 Zaragoza Zaragoza 50006",
    "addr:housenumber":"4",
    "addr:postcode":"50006",
    "addr:street":"Calle De Manuel Lasala",
    "iso:country":"ES",
    "sg:address":"Calle de Manuel Lasala, 4",
    "sg:city":"Zaragoza",
    "sg:orig_category":"Moquetas, Alfombras (al Por Menor)",
    "sg:phone":"+34 976 38 21 01",
    "sg:postcode":"50006",
    "sg:province":"Zaragoza",
    "wof:name":"Alfombras Persas Yasmina S.l.",
    "wof:placetype":"venue"
},
  "geometry": {"coordinates":[-0.8905115724,41.6403007507],"type":"Point"}
}