{
  "type": "Feature",
  "properties": {
    "iso:country":"ES",
    "sg:address":"Carrer de Sant Ferran, 42",
    "sg:city":"Premia Mar",
    "sg:orig_category":"Electricidad, Electr\u00d3nica: Material Y Suministros (al Por Mayor)",
    "sg:phone":"+34 937 51 48 15",
    "sg:postcode":"08330",
    "sg:province":"Barcelona",
    "wof:name":"Cantero Rodena Esther",
    "wof:placetype":"venue"
},
  "geometry": {"coordinates":[2.3517930508,41.495136261],"type":"Point"}
}