{
  "type": "Feature",
  "properties": {
    "addr:full":"Pase Malecon (del), 85 Garrucha Almer\u00eda 04630",
    "addr:housenumber":"85",
    "addr:postcode":"04630",
    "addr:street":"Malecon Del;Almeri\u0301A",
    "iso:country":"ES",
    "sg:address":"Pase Malecon (del), 85",
    "sg:city":"Garrucha",
    "sg:orig_category":"Distribuci\u00d3n De Petr\u00d3leo Y Derivados",
    "sg:phone":"+34 950 13 20 29",
    "sg:postcode":"04630",
    "sg:province":"Almer\u00eda",
    "wof:name":"Garcia Martinez Lazaro",
    "wof:placetype":"venue"
},
  "geometry": {"coordinates":[-1.8293952942,37.1894836426],"type":"Point"}
}