{
  "type": "Feature",
  "properties": {
    "iso:country":"ES",
    "sg:address":"Gain Argi, 4",
    "sg:city":"Segura",
    "sg:orig_category":"Empresas De Desmonte",
    "sg:phone":"+34 943 80 17 77",
    "sg:postcode":"20214",
    "sg:province":"Guip\u00f9zcoa",
    "wof:name":"Orru\u00f1o Villamor Maria Cristina",
    "wof:placetype":"venue"
},
  "geometry": {"coordinates":[-2.2544219494,43.0043296814],"type":"Point"}
}