{
  "type": "Feature",
  "properties": {
    "iso:country":"ES",
    "sg:address":"Poli Poligono Industrial 'la Piel', S/n",
    "sg:city":"Ubrique",
    "sg:orig_category":"Textil",
    "sg:phone":"+34 956 46 49 09",
    "sg:postcode":"11600",
    "sg:province":"C\u00e1diz",
    "wof:name":"Gutierrez Gil Manuel",
    "wof:placetype":"venue"
},
  "geometry": {"coordinates":[-5.4672961235,36.6675033569],"type":"Point"}
}