{
  "type": "Feature",
  "properties": {
    "addr:full":"Calle de Cadiz, 18 Santander Cantabria 39002",
    "addr:housenumber":"18",
    "addr:postcode":"39002",
    "addr:street":"Calle De Cadiz",
    "iso:country":"ES",
    "sg:address":"Calle de Cadiz, 18",
    "sg:city":"Santander",
    "sg:orig_category":"Abogados",
    "sg:phone":"+34 942 36 19 68",
    "sg:postcode":"39002",
    "sg:province":"Cantabria",
    "wof:name":"Palazuelos Juarez Gema",
    "wof:placetype":"venue"
},
  "geometry": {"coordinates":[-3.8070220947,43.4602470398],"type":"Point"}
}