{
  "type": "Feature",
  "properties": {
    "addr:full":"Calle de Costanillas, 14 Ribafrecha La Rioja 26130",
    "addr:housenumber":"14",
    "addr:postcode":"26130",
    "addr:street":"Calle De Costanillas;Rioja",
    "iso:country":"ES",
    "sg:address":"Calle de Costanillas, 14",
    "sg:city":"Ribafrecha",
    "sg:orig_category":"M\u00c1rmoles, Granitos Y Piedras Naturales",
    "sg:phone":"+34 941 43 42 79",
    "sg:postcode":"26130",
    "sg:province":"La Rioja",
    "wof:name":"I\u00f1iguez Santolaya Eusebio",
    "wof:placetype":"venue"
},
  "geometry": {"coordinates":[-2.3883492947,42.3549385071],"type":"Point"}
}