{
  "type": "Feature",
  "properties": {
    "iso:country":"ES",
    "sg:address":"Carrer de Moli Dels Frares, 30",
    "sg:city":"Sant Vicen\u00c7 Dels Horts",
    "sg:orig_category":"Seguridad En El Trabajo Y Prevenci\u00d3n De Riesgos Laborales",
    "sg:phone":"+34 935 88 99 50",
    "sg:postcode":"08620",
    "sg:province":"Barcelona",
    "wof:name":"Moldex-metric Ag & Co. Kg",
    "wof:placetype":"venue"
},
  "geometry": {"coordinates":[1.9979079962,41.4024963379],"type":"Point"}
}