{
  "type": "Feature",
  "properties": {
    "iso:country":"ES",
    "sg:address":"C/ Alvarez De Castro, 37",
    "sg:city":"Banyoles",
    "sg:orig_category":"M\u00c9dicos: Medicina Y Biolog\u00cda Del Deporte",
    "sg:phone":"+34 972 57 59 27",
    "sg:postcode":"17820",
    "sg:province":"Girona",
    "wof:name":"Molera Bartroli Joan",
    "wof:placetype":"venue"
},
  "geometry": {"coordinates":[2.7649009228,42.1168327332],"type":"Point"}
}