{
  "type": "Feature",
  "properties": {
    "iso:country":"ES",
    "sg:address":"Calle de San Fermin, 21",
    "sg:city":"Torrent",
    "sg:orig_category":"Ropa De Hogar (al Por Menor)",
    "sg:phone":"+34 961 55 03 58",
    "sg:postcode":"46900",
    "sg:province":"Valencia",
    "wof:name":"Huerta Hernandez Carmen",
    "wof:placetype":"venue"
},
  "geometry": {"coordinates":[-0.4726130068,39.4342842102],"type":"Point"}
}