{
  "type": "Feature",
  "properties": {
    "addr:full":"Calle de San Pedro, S/n Mucientes Valladolid 47194",
    "addr:postcode":"47194",
    "addr:street":"Calle De San Pedro S / N",
    "iso:country":"ES",
    "sg:address":"Calle de San Pedro, S/n",
    "sg:city":"Mucientes",
    "sg:orig_category":"Cajas Para Embalar",
    "sg:phone":"+34 983 58 77 70",
    "sg:postcode":"47194",
    "sg:province":"Valladolid",
    "wof:name":"Caja Rural Del Duero",
    "wof:placetype":"venue"
},
  "geometry": {"coordinates":[-4.7596888542,41.7441101074],"type":"Point"}
}