{
  "type": "Feature",
  "properties": {
    "addr:full":"Calle de Santa Lucia, 7 Aranda Duero Burgos 09400",
    "addr:housenumber":"7",
    "addr:postcode":"09400",
    "addr:street":"Calle De Santa Lucia",
    "iso:country":"ES",
    "sg:address":"Calle de Santa Lucia, 7",
    "sg:city":"Aranda Duero",
    "sg:orig_category":"Electrodom\u00c9sticos (al Por Menor)",
    "sg:phone":"+34 947 50 62 13",
    "sg:postcode":"09400",
    "sg:province":"Burgos",
    "wof:name":"Rodriguez Criado Jose",
    "wof:placetype":"venue"
},
  "geometry": {"coordinates":[-3.687171936,41.6702003479],"type":"Point"}
}