{
  "type": "Feature",
  "properties": {
    "addr:full":"Calle de Paz (de La), 10 Mostoles Madrid 28931",
    "addr:housenumber":"10",
    "addr:postcode":"28931",
    "addr:street":"Calle De Paz De La",
    "iso:country":"ES",
    "sg:address":"Calle de Paz (de La), 10",
    "sg:city":"Mostoles",
    "sg:orig_category":"Gastronom\u00cda: Especialidades Regionales Y Extranjeras (producci\u00d3n, Al Por Mayor)",
    "sg:phone":"+34 916 64 37 38",
    "sg:postcode":"28931",
    "sg:province":"Madrid",
    "wof:name":"Obi  Kingsley",
    "wof:placetype":"venue"
},
  "geometry": {"coordinates":[-3.8595659733,40.3255653381],"type":"Point"}
}