{
  "type": "Feature",
  "properties": {
    "iso:country":"ES",
    "sg:address":"Calle de Marquesa De Torrelaguna (de La), 3",
    "sg:city":"Torrelaguna",
    "sg:orig_category":"Construcci\u00d3n Mec\u00c1nica",
    "sg:phone":"+34 918 43 06 88",
    "sg:postcode":"28180",
    "sg:province":"Madrid",
    "wof:name":"Industrias Mecanicas Jolmar S.l.",
    "wof:placetype":"venue"
},
  "geometry": {"coordinates":[-3.5386669636,40.8265304565],"type":"Point"}
}