{
  "type": "Feature",
  "properties": {
    "iso:country":"ES",
    "sg:address":"Carrer de Cabrera, 22",
    "sg:city":"S. Quirze Valles",
    "sg:orig_category":"Contenedores (mercanc\u00cdas)",
    "sg:phone":"+34 937 21 60 60",
    "sg:postcode":"08192",
    "sg:province":"Barcelona",
    "wof:name":"Transnaser Diagonal S.l.",
    "wof:placetype":"venue"
},
  "geometry": {"coordinates":[2.0945599079,41.5212135315],"type":"Point"}
}