{
  "type": "Feature",
  "properties": {
    "iso:country":"ES",
    "sg:address":"Carrer de Alt De Sant Pere, 58",
    "sg:city":"Torredembarra",
    "sg:orig_category":"Reposter\u00cdas",
    "sg:phone":"+34 977 64 39 29",
    "sg:postcode":"43830",
    "sg:province":"Tarragona",
    "wof:name":"Maes Flequers I Pastissers S.a",
    "wof:placetype":"venue"
},
  "geometry": {"coordinates":[1.4005999565,41.1461601257],"type":"Point"}
}