{
  "type": "Feature",
  "properties": {
    "addr:full":"Calle de Gomera, 15 Pto. Rosario Las Palmas 35600",
    "addr:housenumber":"15",
    "addr:postcode":"35600",
    "addr:street":"Calle De Gomera;Pto. Rosario Las",
    "iso:country":"ES",
    "sg:address":"Calle de Gomera, 15",
    "sg:city":"Pto. Rosario",
    "sg:orig_category":"Servicios De Telecomunicaciones",
    "sg:phone":"+34 928 53 22 35",
    "sg:postcode":"35600",
    "sg:province":"Las Palmas",
    "wof:name":"Martinez Pereira Jose",
    "wof:placetype":"venue"
},
  "geometry": {"coordinates":[-13.8660173416,28.5016136169],"type":"Point"}
}