{
  "type": "Feature",
  "properties": {
    "iso:country":"ES",
    "sg:address":"Calle de Aparisi Y Guijarro, 7",
    "sg:city":"Valencia",
    "sg:classifiers":[
        {
            "category":"Arts & Performance",
            "subcategory":"Art Gallery",
            "type":"Entertainment"
        }
    ],
    "sg:phone":"+34 963 91 52 84",
    "sg:postcode":"46003",
    "sg:province":"Valencia",
    "sg:tags":[
        "arte",
        "de",
        "galer\u00cdas"
    ],
    "sg:website":"www.tomasmarch.com",
    "wof:name":"Galeria Tomas March S.l.",
    "wof:placetype":"venue"
},
  "geometry": {"coordinates":[-0.3720386922,39.4754333496],"type":"Point"}
}