{
  "type": "Feature",
  "properties": {
    "iso:country":"ES",
    "sg:address":"Calle de Velazquez, 2",
    "sg:city":"Sabi\u00f1anigo",
    "sg:orig_category":"Escayola Y Productos De Escayola (fabricaci\u00d3n, Al Por Mayor)",
    "sg:phone":"+34 974 48 30 85",
    "sg:postcode":"22600",
    "sg:province":"Huesca",
    "wof:name":"Marquez Carrillo Manuel",
    "wof:placetype":"venue"
},
  "geometry": {"coordinates":[-0.3562609851,42.5077590942],"type":"Point"}
}