{
  "type": "Feature",
  "properties": {
    "addr:full":"Calle de Francisco Cubria, 3 Santander Cantabria 39007",
    "addr:housenumber":"3",
    "addr:postcode":"39007",
    "addr:street":"Calle De Francisco Cubria",
    "iso:country":"ES",
    "sg:address":"Calle de Francisco Cubria, 3",
    "sg:city":"Santander",
    "sg:orig_category":"Madera Para Construcci\u00d3n E Industria",
    "sg:phone":"+34 942 37 04 99",
    "sg:postcode":"39007",
    "sg:province":"Cantabria",
    "wof:name":"Garcia Canales Juan Carlos",
    "wof:placetype":"venue"
},
  "geometry": {"coordinates":[-3.8195645809,43.4618492126],"type":"Point"}
}