{
  "type": "Feature",
  "properties": {
    "iso:country":"ES",
    "sg:address":"C/ Gavarres, 1",
    "sg:city":"Salt",
    "sg:orig_category":"Delegados, Agentes De Tr\u00c1nsito, Auxiliares De Transporte Internacional",
    "sg:phone":"+34 972 24 44 51",
    "sg:postcode":"17190",
    "sg:province":"Girona",
    "wof:name":"Pages Nonell Lluis",
    "wof:placetype":"venue"
},
  "geometry": {"coordinates":[2.7877790928,41.9694137573],"type":"Point"}
}