{
  "type": "Feature",
  "properties": {
    "iso:country":"ES",
    "sg:address":"Avda Coru\u00d1a (da), S/n",
    "sg:city":"Lugo",
    "sg:orig_category":"Ense\u00d1anza Secundaria: Colegios Y Escuelas Privadas",
    "sg:phone":"+34 982 21 17 51",
    "sg:postcode":"27003",
    "sg:province":"Lugo",
    "wof:name":"Centro Especifico De Educacion De Adultos De Albeiros De Lugo",
    "wof:placetype":"venue"
},
  "geometry": {"coordinates":[-7.5593738556,43.0159034729],"type":"Point"}
}