{
  "type": "Feature",
  "properties": {
    "addr:full":"Cra Sevilla-p I Romeralejo, Km. 0637,0 Huelva Huelva 21006",
    "addr:postcode":"21006",
    "addr:street":"Romeralejo Km. 0637,0",
    "iso:country":"ES",
    "sg:address":"Cra Sevilla-p I Romeralejo, Km. 0637,0",
    "sg:city":"Huelva",
    "sg:orig_category":"Chapister\u00cda",
    "sg:phone":"+34 959 22 00 16",
    "sg:postcode":"21006",
    "sg:province":"Huelva",
    "wof:name":"Talleres San Cristobal C.b.",
    "wof:placetype":"venue"
},
  "geometry": {"coordinates":[-6.9495940208,37.256313324],"type":"Point"}
}