{
  "type": "Feature",
  "properties": {
    "addr:full":"Pase Goya (de), 21 Mostoles Madrid 28932",
    "addr:postcode":"28932",
    "addr:street":"Mostoles",
    "iso:country":"ES",
    "sg:address":"Pase Goya (de), 21",
    "sg:city":"Mostoles",
    "sg:orig_category":"Sindicatos De Trabajadores",
    "sg:phone":"+34 916 13 75 71",
    "sg:postcode":"28932",
    "sg:province":"Madrid",
    "wof:name":"U.g.t.-union Comarcal Oeste",
    "wof:placetype":"venue"
},
  "geometry": {"coordinates":[-3.8649389744,40.3230667114],"type":"Point"}
}