{
  "type": "Feature",
  "properties": {
    "iso:country":"ES",
    "sg:address":"Calle de Tio Pino, S/n",
    "sg:city":"Santa Cruz De Tenerife",
    "sg:orig_category":"Quincaller\u00cda (al Por Menor)",
    "sg:phone":"+34 922 21 15 01",
    "sg:postcode":"38009",
    "sg:province":"Santa Cruz De Tenerife",
    "wof:name":"Aguafuerte S.l.u",
    "wof:placetype":"venue"
},
  "geometry": {"coordinates":[-16.273809433,28.4599189758],"type":"Point"}
}