{
  "type": "Feature",
  "properties": {
    "iso:country":"ES",
    "sg:address":"Avda Doctor Federico Rubio Y Gali, 19",
    "sg:city":"Madrid",
    "sg:orig_category":"Mec\u00c1nico Del Autom\u00d3vil",
    "sg:phone":"+34 915 53 10 86",
    "sg:postcode":"28039",
    "sg:province":"Madrid",
    "sg:website":"www.minicentre.es",
    "wof:name":"Mini Centre Espa\u00f1a.s.a.",
    "wof:placetype":"venue"
},
  "geometry": {"coordinates":[-3.7095088959,40.4499092102],"type":"Point"}
}