{
  "type": "Feature",
  "properties": {
    "iso:country":"ES",
    "sg:address":"Calle de Pilar Del Amo, 24",
    "sg:city":"Iscar",
    "sg:orig_category":"Pintura, Barniz, Productos Asimilables (fabricaci\u00d3n, Al Por Mayor)",
    "sg:phone":"+34 983 61 15 25",
    "sg:postcode":"47420",
    "sg:province":"Valladolid",
    "wof:name":"Lopez De Iscar Antonio",
    "wof:placetype":"venue"
},
  "geometry": {"coordinates":[-4.5311250687,41.3576622009],"type":"Point"}
}