{
  "type": "Feature",
  "properties": {
    "iso:country":"ES",
    "sg:address":"Luga San Cucao, 44",
    "sg:city":"San Cucao",
    "sg:orig_category":"Cr\u00cda De Animales",
    "sg:phone":"+34 985 77 07 65",
    "sg:postcode":"33425",
    "sg:province":"Asturias",
    "wof:name":"Fernandez Paredes Fermin",
    "wof:placetype":"venue"
},
  "geometry": {"coordinates":[-5.8985657692,43.4188995361],"type":"Point"}
}