{
  "type": "Feature",
  "properties": {
    "addr:full":"Calle de Villaamil, 72 Mostoles Madrid 28934",
    "addr:housenumber":"72",
    "addr:postcode":"28934",
    "addr:street":"Calle De Villaamil",
    "iso:country":"ES",
    "sg:address":"Calle de Villaamil, 72",
    "sg:city":"Mostoles",
    "sg:orig_category":"Guarda",
    "sg:phone":"+34 916 14 82 46",
    "sg:postcode":"28934",
    "sg:province":"Madrid",
    "wof:name":"Mudanzas Vargas S.l.",
    "wof:placetype":"venue"
},
  "geometry": {"coordinates":[-3.8738610744,40.3202362061],"type":"Point"}
}