{
  "type": "Feature",
  "properties": {
    "iso:country":"ES",
    "sg:address":"Calle de Jose Estevez, 1",
    "sg:city":"Pozoblanco",
    "sg:orig_category":"Inform\u00c1tica, Ofim\u00c1tica (estudios, Asesor\u00cda, Ingenier\u00cda, Formaci\u00d3n)",
    "sg:phone":"+34 957 13 09 52",
    "sg:postcode":"14400",
    "sg:province":"C\u00f3rdoba",
    "wof:name":"Milano Data Digital S.l.",
    "wof:placetype":"venue"
},
  "geometry": {"coordinates":[-4.848484993,38.3785667419],"type":"Point"}
}