{
  "type": "Feature",
  "properties": {
    "iso:country":"ES",
    "sg:address":"Avda Alicante, 79",
    "sg:city":"Villena",
    "sg:orig_category":"Chapister\u00cda",
    "sg:phone":"+34 965 34 07 35",
    "sg:postcode":"03400",
    "sg:province":"Alicante",
    "wof:name":"Taller San Isidro C.b.",
    "wof:placetype":"venue"
},
  "geometry": {"coordinates":[-0.8549200296,38.6298332214],"type":"Point"}
}