{
  "type": "Feature",
  "properties": {
    "iso:country":"ES",
    "sg:address":"Calle de Mateo Errota, 13",
    "sg:city":"Donostia-san Sebastian",
    "sg:orig_category":"Empresas De Portes Y Mensajer\u00cda",
    "sg:phone":"+34 943 44 56 06",
    "sg:postcode":"20014",
    "sg:province":"Guip\u00f9zcoa",
    "wof:name":"Buzonrapid Donosti S.l.",
    "wof:placetype":"venue"
},
  "geometry": {"coordinates":[-1.9435440302,43.3023834229],"type":"Point"}
}