{
  "type": "Feature",
  "properties": {
    "addr:full":"Mimosas, S/n Sta. Cristina Aro Girona 17246",
    "addr:housenumber":"s / n",
    "addr:postcode":"17246",
    "addr:street":"Mimosas",
    "iso:country":"ES",
    "sg:address":"Mimosas, S/n",
    "sg:city":"Sta. Cristina Aro",
    "sg:orig_category":"Abogados",
    "sg:phone":"+34 972 83 80 85",
    "sg:postcode":"17246",
    "sg:province":"Girona",
    "wof:name":"Carreras Advocats S.l.",
    "wof:placetype":"venue"
},
  "geometry": {"coordinates":[2.9987950325,41.8115959167],"type":"Point"}
}