{
  "type": "Feature",
  "properties": {
    "addr:full":"Calle de Arco De Las Orejas, 3 Granada Granada 18001",
    "addr:housenumber":"3",
    "addr:postcode":"18001",
    "addr:street":"Calle De Arco De Las Orejas",
    "iso:country":"ES",
    "sg:address":"Calle de Arco De Las Orejas, 3",
    "sg:city":"Granada",
    "sg:orig_category":"Arquitectos",
    "sg:phone":"+34 958 52 26 45",
    "sg:postcode":"18001",
    "sg:province":"Granada",
    "wof:name":"Corral Del Campo Francisco Jose Del",
    "wof:placetype":"venue"
},
  "geometry": {"coordinates":[-3.5998661518,37.1745948792],"type":"Point"}
}