{
  "type": "Feature",
  "properties": {
    "iso:country":"ES",
    "sg:address":"Calle de Pablo Picasso, S/n",
    "sg:city":"Pinto",
    "sg:orig_category":"Servicios Gsm",
    "sg:phone":"+34 916 91 58 81",
    "sg:postcode":"28320",
    "sg:province":"Madrid",
    "wof:name":"Avenir Telecom S. A.",
    "wof:placetype":"venue"
},
  "geometry": {"coordinates":[-3.6941823959,40.2382888794],"type":"Point"}
}