{
  "type": "Feature",
  "properties": {
    "addr:full":"Cmno Olmos, S/n Renedo De Esgueva Valladolid 47170",
    "addr:housenumber":"s / n",
    "addr:postcode":"47170",
    "addr:street":"Cmno Olmos",
    "iso:country":"ES",
    "sg:address":"Cmno Olmos, S/n",
    "sg:city":"Renedo De Esgueva",
    "sg:orig_category":"Asociaciones Humanitarias, De Cooperaci\u00d3n, De Acci\u00d3n Social",
    "sg:phone":"+34 983 50 80 68",
    "sg:postcode":"47170",
    "sg:province":"Valladolid",
    "wof:name":"Asociacion Vallisoletana De Proteccion De Autistas",
    "wof:placetype":"venue"
},
  "geometry": {"coordinates":[-4.6531090736,41.6446037292],"type":"Point"}
}