{
  "type": "Feature",
  "properties": {
    "addr:full":"Iturriotz Kalea, 7 Arrasate Guip\u00f9zcoa 20500",
    "addr:housenumber":"7",
    "addr:postcode":"20500",
    "addr:street":"Iturriotz Kalea;Guipu\u0300Zcoa",
    "iso:country":"ES",
    "sg:address":"Iturriotz Kalea, 7",
    "sg:city":"Arrasate",
    "sg:orig_category":"Molduras, Junquillos, Listones Y Molduras Perforadas",
    "sg:phone":"+34 943 71 20 89",
    "sg:postcode":"20500",
    "sg:province":"Guip\u00f9zcoa",
    "wof:name":"Albizu Echeverria Ignacio",
    "wof:placetype":"venue"
},
  "geometry": {"coordinates":[-2.4894723892,43.0658187866],"type":"Point"}
}