{
  "type": "Feature",
  "properties": {
    "addr:full":"Calle de Carrera, 52 Martos Ja\u00e9n 23600",
    "addr:housenumber":"52",
    "addr:postcode":"23600",
    "addr:street":"Calle De Carrera;Jae\u0301N",
    "iso:country":"ES",
    "sg:address":"Calle de Carrera, 52",
    "sg:city":"Martos",
    "sg:orig_category":"Art\u00cdculos De Regalo (al Por Menor)",
    "sg:phone":"+34 953 55 16 99",
    "sg:postcode":"23600",
    "sg:province":"Ja\u00e9n",
    "wof:name":"Castro Merino Vicente",
    "wof:placetype":"venue"
},
  "geometry": {"coordinates":[-3.9696888924,37.7189216614],"type":"Point"}
}