{
  "type": "Feature",
  "properties": {
    "iso:country":"ES",
    "sg:address":"Carrer de Rabassa, 29",
    "sg:city":"Barcelona",
    "sg:orig_category":"Dorados, Plater\u00cda (orfebrer\u00cda)",
    "sg:phone":"+34 932 84 00 52",
    "sg:postcode":"08024",
    "sg:province":"Barcelona",
    "wof:name":"Mir Culell Dolores",
    "wof:placetype":"venue"
},
  "geometry": {"coordinates":[2.1577270031,41.4077072144],"type":"Point"}
}