{
  "type": "Feature",
  "properties": {
    "addr:full":"Calle de Easo, 47 Donostia-san Sebastian Guip\u00f9zcoa 20006",
    "addr:housenumber":"47",
    "addr:postcode":"20006",
    "addr:street":"Calle De Easo",
    "iso:country":"ES",
    "sg:address":"Calle de Easo, 47",
    "sg:city":"Donostia-san Sebastian",
    "sg:orig_category":"Sales (al Por Mayor)",
    "sg:phone":"+34 943 45 15 89",
    "sg:postcode":"20006",
    "sg:province":"Guip\u00f9zcoa",
    "wof:name":"Garcia Irazusta Maria Teresa",
    "wof:placetype":"venue"
},
  "geometry": {"coordinates":[-1.9824746847,43.314868927],"type":"Point"}
}