{
  "type": "Feature",
  "properties": {
    "iso:country":"ES",
    "sg:address":"Av Princep D'asturies, 46",
    "sg:city":"Barcelona",
    "sg:orig_category":"M\u00c9dicos: An\u00c1lisis Cl\u00cdnicos",
    "sg:phone":"+34 932 17 74 43",
    "sg:postcode":"08012",
    "sg:province":"Barcelona",
    "wof:name":"Labori Claveguera Juana",
    "wof:placetype":"venue"
},
  "geometry": {"coordinates":[2.1503639221,41.4044761658],"type":"Point"}
}