{
  "type": "Feature",
  "properties": {
    "iso:country":"ES",
    "sg:address":"Calle de Balate, 23",
    "sg:city":"Sang\u00fcesa",
    "sg:orig_category":"Promotores Constructores",
    "sg:phone":"+34 948 43 02 96",
    "sg:postcode":"31400",
    "sg:province":"Navarra",
    "wof:name":"Construcciones Andres Huarte S.l.",
    "wof:placetype":"venue"
},
  "geometry": {"coordinates":[-1.2820589542,42.5739898682],"type":"Point"}
}