{
  "type": "Feature",
  "properties": {
    "iso:country":"ES",
    "sg:address":"Carrer de Sant Antoni, 17",
    "sg:city":"S. Celoni",
    "sg:orig_category":"Almacenes Y Tiendas De Productos Variados",
    "sg:phone":"+34 938 67 04 67",
    "sg:postcode":"08470",
    "sg:province":"Barcelona",
    "wof:name":"Costa Pascual Juan",
    "wof:placetype":"venue"
},
  "geometry": {"coordinates":[2.4934461117,41.6901435852],"type":"Point"}
}