{
  "type": "Feature",
  "properties": {
    "addr:full":"Calle de Nogal (del), 8 Humanes De Madrid Madrid 28970",
    "addr:housenumber":"8",
    "addr:postcode":"28970",
    "addr:street":"Calle De Nogal Del",
    "iso:country":"ES",
    "sg:address":"Calle de Nogal (del), 8",
    "sg:city":"Humanes De Madrid",
    "sg:orig_category":"Transportes Por V\u00cdas Navegables",
    "sg:phone":"+34 914 98 22 16",
    "sg:postcode":"28970",
    "sg:province":"Madrid",
    "wof:name":"Koimbra Gestion Transporte S.l.",
    "wof:placetype":"venue"
},
  "geometry": {"coordinates":[-3.8126499653,40.2669181824],"type":"Point"}
}