{
  "type": "Feature",
  "properties": {
    "iso:country":"ES",
    "sg:address":"Calle de San Martin De Porres, 47",
    "sg:city":"Madrid",
    "sg:orig_category":"Abogados",
    "sg:phone":"+34 913 16 49 37",
    "sg:postcode":"28035",
    "sg:province":"Madrid",
    "wof:name":"Ni\u00f1o Leon Jose",
    "wof:placetype":"venue"
},
  "geometry": {"coordinates":[-3.7287619114,40.4702949524],"type":"Point"}
}