{
  "type": "Feature",
  "properties": {
    "iso:country":"ES",
    "sg:address":"Calle de Menendez Pelayo, 5",
    "sg:city":"Cordoba",
    "sg:orig_category":"Institutos De Belleza",
    "sg:phone":"+34 957 47 36 13",
    "sg:postcode":"14008",
    "sg:province":"C\u00f3rdoba",
    "wof:name":"Marin Franco Maria Soledad",
    "wof:placetype":"venue"
},
  "geometry": {"coordinates":[-4.7831330299,37.8853378296],"type":"Point"}
}