{
  "type": "Feature",
  "properties": {
    "iso:country":"ES",
    "sg:address":"Calle de Real, S/n",
    "sg:city":"Lopera",
    "sg:orig_category":"Asesor\u00cda De Formaci\u00d3n Y Gesti\u00d3n De Personal",
    "sg:phone":"+34 953 51 60 98",
    "sg:postcode":"23780",
    "sg:province":"Ja\u00e9n",
    "wof:name":"Toledano & Asesores S.l.",
    "wof:placetype":"venue"
},
  "geometry": {"coordinates":[-4.2139091492,37.9449386597],"type":"Point"}
}