{
  "type": "Feature",
  "properties": {
    "iso:country":"ES",
    "sg:address":"Calle de Real, S/n",
    "sg:city":"Trescasas",
    "sg:orig_category":"Molduras, Junquillos, Listones Y Molduras Perforadas",
    "sg:phone":"+34 921 40 60 64",
    "sg:postcode":"40194",
    "sg:province":"Segovia",
    "wof:name":"Gomez Gomez Teogenes",
    "wof:placetype":"venue"
},
  "geometry": {"coordinates":[-4.0362730026,40.9644584656],"type":"Point"}
}