{
  "type": "Feature",
  "properties": {
    "addr:full":"Calle de San Orencio, 4 Huesca Huesca 22001",
    "addr:housenumber":"4",
    "addr:postcode":"22001",
    "addr:street":"Calle De San Orencio",
    "iso:country":"ES",
    "sg:address":"Calle de San Orencio, 4",
    "sg:city":"Huesca",
    "sg:orig_category":"Quincaller\u00cda (al Por Menor)",
    "sg:phone":"+34 974 22 47 79",
    "sg:postcode":"22001",
    "sg:province":"Huesca",
    "wof:name":"Galan Morte Fernando",
    "wof:placetype":"venue"
},
  "geometry": {"coordinates":[-0.4076350033,42.136592865],"type":"Point"}
}