{
  "type": "Feature",
  "properties": {
    "iso:country":"ES",
    "sg:address":"Los Molinos, 14",
    "sg:city":"Puebla Almoradiel",
    "sg:orig_category":"Reposter\u00cdas",
    "sg:phone":"+34 925 17 81 65",
    "sg:postcode":"45840",
    "sg:province":"Toledo",
    "wof:name":"Hernando Manzaneque Victoriano",
    "wof:placetype":"venue"
},
  "geometry": {"coordinates":[-3.1242120266,39.6001091003],"type":"Point"}
}