{
  "type": "Feature",
  "properties": {
    "addr:full":"Calle de Barranco (el), 4 Valle S. Lorenzo Santa Cruz De Tenerife 38626",
    "addr:housenumber":"4",
    "addr:postcode":"38626",
    "addr:street":"Calle De Barranco El;S. Lorenzo",
    "iso:country":"ES",
    "sg:address":"Calle de Barranco (el), 4",
    "sg:city":"Valle S. Lorenzo",
    "sg:orig_category":"Centros Empresariales",
    "sg:phone":"+34 922 76 40 21",
    "sg:postcode":"38626",
    "sg:province":"Santa Cruz De Tenerife",
    "wof:name":"It. Consulting Insulation And Intelligen",
    "wof:placetype":"venue"
},
  "geometry": {"coordinates":[-16.6586322784,28.0910282135],"type":"Point"}
}