{
  "type": "Feature",
  "properties": {
    "addr:full":"Avda Andalucia, 66 Malaga M\u00e1laga 29007",
    "addr:housenumber":"66",
    "addr:postcode":"29007",
    "addr:street":"Avda Andalucia;Ma\u0301Laga",
    "iso:country":"ES",
    "sg:address":"Avda Andalucia, 66",
    "sg:city":"Malaga",
    "sg:orig_category":"Fabricaci\u00d3n, Venta, Instalaci\u00d3n De R\u00d3tulos, De R\u00d3tulos Luminosos",
    "sg:phone":"+34 952 61 00 01",
    "sg:postcode":"29007",
    "sg:province":"M\u00e1laga",
    "wof:name":"Luminosos Manuel Espa\u00f1a S.c.",
    "wof:placetype":"venue"
},
  "geometry": {"coordinates":[-4.443377018,36.7162399292],"type":"Point"}
}