{
  "type": "Feature",
  "properties": {
    "addr:full":"Calle de Niebla, 1 Huelva Huelva 21007",
    "addr:housenumber":"1",
    "addr:postcode":"21007",
    "addr:street":"Calle De Niebla",
    "iso:country":"ES",
    "sg:address":"Calle de Niebla, 1",
    "sg:city":"Huelva",
    "sg:orig_category":"Dietistas",
    "sg:phone":"+34 959 22 20 48",
    "sg:postcode":"21007",
    "sg:province":"Huelva",
    "wof:name":"Albimend S.l.",
    "wof:placetype":"venue"
},
  "geometry": {"coordinates":[-6.9356412888,37.2574806213],"type":"Point"}
}