{
  "type": "Feature",
  "properties": {
    "iso:country":"ES",
    "sg:address":"Calle de Primo De Rivera, 15",
    "sg:city":"Caspe",
    "sg:orig_category":"Procuradores",
    "sg:phone":"+34 976 63 06 25",
    "sg:postcode":"50700",
    "sg:province":"Zaragoza",
    "wof:name":"Albiac Guiu Santiago",
    "wof:placetype":"venue"
},
  "geometry": {"coordinates":[-0.0421000011,41.2391281128],"type":"Point"}
}