{
  "type": "Feature",
  "properties": {
    "iso:country":"ES",
    "sg:address":"Calle de Zarza, 48",
    "sg:city":"Villanueva Cordoba",
    "sg:orig_category":"Orquestas De Variedades",
    "sg:phone":"+34 957 12 15 98",
    "sg:postcode":"14440",
    "sg:province":"C\u00f3rdoba",
    "wof:name":"Benitez Ferrero Bernardo",
    "wof:placetype":"venue"
},
  "geometry": {"coordinates":[-4.620598793,38.3223800659],"type":"Point"}
}