{
  "type": "Feature",
  "properties": {
    "addr:full":"Avda Andalucia, S/n Peligros Granada 18210",
    "addr:housenumber":"/ n",
    "addr:postcode":"18210",
    "addr:street":"Avda Andalucia S",
    "iso:country":"ES",
    "sg:address":"Avda Andalucia, S/n",
    "sg:city":"Peligros",
    "sg:orig_category":"Electrodom\u00c9sticos (al Por Menor)",
    "sg:phone":"+34 958 40 03 08",
    "sg:postcode":"18210",
    "sg:province":"Granada",
    "wof:name":"Frhygra S.r.l.",
    "wof:placetype":"venue"
},
  "geometry": {"coordinates":[-3.6257588863,37.2260017395],"type":"Point"}
}