{
  "type": "Feature",
  "properties": {
    "addr:full":"Carrer de L'argenter, 12 Barcelona Barcelona 08003",
    "addr:housenumber":"12",
    "addr:postcode":"08003",
    "addr:street":"Carrer De L'Argenter",
    "iso:country":"ES",
    "sg:address":"Carrer de L'argenter, 12",
    "sg:city":"Barcelona",
    "sg:orig_category":"Arquitectos",
    "sg:phone":"+34 932 68 88 78",
    "sg:postcode":"08003",
    "sg:province":"Barcelona",
    "wof:name":"Mizien S.l.",
    "wof:placetype":"venue"
},
  "geometry": {"coordinates":[2.1770439148,41.3881607056],"type":"Point"}
}