{
  "type": "Feature",
  "properties": {
    "addr:full":"Calle de Santander, 13 Colindres Cantabria 39750",
    "addr:housenumber":"13",
    "addr:postcode":"39750",
    "addr:street":"Calle De Santander",
    "iso:country":"ES",
    "sg:address":"Calle de Santander, 13",
    "sg:city":"Colindres",
    "sg:orig_category":"Mercer\u00cda, Lencer\u00cda (al Por Menor)",
    "sg:phone":"+34 942 65 07 88",
    "sg:postcode":"39750",
    "sg:province":"Cantabria",
    "wof:name":"Nu\u00f1ez Sisniega Braulio",
    "wof:placetype":"venue"
},
  "geometry": {"coordinates":[-3.4501368999,43.3989257812],"type":"Point"}
}