{
  "type": "Feature",
  "properties": {
    "iso:country":"ES",
    "sg:address":"Carr Xativa, 27",
    "sg:city":"Moncada",
    "sg:orig_category":"Inmobiliaria (agencias)",
    "sg:phone":"+34 961 39 33 38",
    "sg:postcode":"46113",
    "sg:province":"Valencia",
    "wof:name":"Exposito Suanes Angel",
    "wof:placetype":"venue"
},
  "geometry": {"coordinates":[-0.3982529938,39.5452728271],"type":"Point"}
}