{
  "type": "Feature",
  "properties": {
    "iso:country":"ES",
    "sg:address":"Urb Hispanidad (la), 10",
    "sg:city":"Olula Rio",
    "sg:classifiers":[
        {
            "category":"Taxi",
            "type":"Transportation"
        }
    ],
    "sg:phone":"+34 950 44 13 57",
    "sg:postcode":"04860",
    "sg:province":"Almer\u00eda",
    "wof:name":"Garrido Lopez Juan Carlos",
    "wof:placetype":"venue"
},
  "geometry": {"coordinates":[-2.4679217339,36.8401641846],"type":"Point"}
}