{
  "type": "Feature",
  "properties": {
    "addr:full":"Carrer de Consell De Cent, 354 Barcelona Barcelona 08009",
    "addr:housenumber":"354",
    "addr:postcode":"08009",
    "addr:street":"Carrer De Consell De Cent",
    "iso:country":"ES",
    "sg:address":"Carrer de Consell De Cent, 354",
    "sg:city":"Barcelona",
    "sg:orig_category":"Bisuter\u00cda, Joyer\u00cda, Relojer\u00cda (al Por Menor)",
    "sg:phone":"+34 934 88 03 62",
    "sg:postcode":"08009",
    "sg:province":"Barcelona",
    "wof:name":"Ferrandiz Pico Enric",
    "wof:placetype":"venue"
},
  "geometry": {"coordinates":[2.169604063,41.3938446045],"type":"Point"}
}