{
  "type": "Feature",
  "properties": {
    "addr:full":"Calle de Goya, S/n Lorqui Murcia 30564",
    "addr:housenumber":"s",
    "addr:postcode":"30564",
    "addr:street":"Calle De Goya;/ N",
    "iso:country":"ES",
    "sg:address":"Calle de Goya, S/n",
    "sg:city":"Lorqui",
    "sg:orig_category":"Supermercados Y Hipermercados",
    "sg:phone":"+34 968 69 01 00",
    "sg:postcode":"30564",
    "sg:province":"Murcia",
    "wof:name":"Lidercarne S.l.l.",
    "wof:placetype":"venue"
},
  "geometry": {"coordinates":[-1.2562739849,38.0816917419],"type":"Point"}
}