{
  "type": "Feature",
  "properties": {
    "addr:full":"Av Paisos Catalans, 107 Reus Tarragona 43205",
    "addr:housenumber":"107",
    "addr:postcode":"43205",
    "addr:street":"Av Paisos Catalans",
    "iso:country":"ES",
    "sg:address":"Av Paisos Catalans, 107",
    "sg:city":"Reus",
    "sg:orig_category":"Producci\u00d3n De Abonos Y De Fertilizantes",
    "sg:phone":"+34 977 32 38 59",
    "sg:postcode":"43205",
    "sg:province":"Tarragona",
    "wof:name":"Tortosa Roig Jose",
    "wof:placetype":"venue"
},
  "geometry": {"coordinates":[1.0979199409,41.1507606506],"type":"Point"}
}