{
  "type": "Feature",
  "properties": {
    "addr:full":"Trva Carlos Mackintosh, S/n Marbella M\u00e1laga 29600",
    "addr:housenumber":"s / n",
    "addr:postcode":"29600",
    "addr:street":"Trva Carlos Mackintosh;Ma\u0301Laga",
    "iso:country":"ES",
    "sg:address":"Trva Carlos Mackintosh, S/n",
    "sg:city":"Marbella",
    "sg:orig_category":"Cobro De Pr\u00c9stamos",
    "sg:phone":"+34 952 77 14 19",
    "sg:postcode":"29600",
    "sg:province":"M\u00e1laga",
    "wof:name":"Patronato De Recaudacion Provincial De Malaga",
    "wof:placetype":"venue"
},
  "geometry": {"coordinates":[-4.8863840103,36.5087165833],"type":"Point"}
}