{
  "type": "Feature",
  "properties": {
    "addr:full":"Calle de Mayor, 92 Alcala Henares Madrid 28801",
    "addr:housenumber":"92",
    "addr:postcode":"28801",
    "addr:street":"Calle De Mayor",
    "iso:country":"ES",
    "sg:address":"Calle de Mayor, 92",
    "sg:city":"Alcala Henares",
    "sg:orig_category":"Librer\u00cdas",
    "sg:phone":"+34 918 83 47 49",
    "sg:postcode":"28801",
    "sg:province":"Madrid",
    "wof:name":"Blanco Garcia Maria Luisa",
    "wof:placetype":"venue"
},
  "geometry": {"coordinates":[-3.3686499596,40.4813079834],"type":"Point"}
}