{
  "type": "Feature",
  "properties": {
    "iso:country":"ES",
    "sg:address":"Calle de Ramon Lujan, 36",
    "sg:city":"Madrid",
    "sg:orig_category":"Peluqueros: De Se\u00d1oras",
    "sg:phone":"+34 914 75 61 43",
    "sg:postcode":"28026",
    "sg:province":"Madrid",
    "wof:name":"Diaz-garzon Comendador Santiago",
    "wof:placetype":"venue"
},
  "geometry": {"coordinates":[-3.7046399117,40.3854675293],"type":"Point"}
}