{
  "type": "Feature",
  "properties": {
    "addr:full":"Trva Basqui\u00d1os (dos), 5 Santiago De Compostela La Coru\u00f1a 15704",
    "addr:housenumber":"5",
    "addr:postcode":"15704",
    "addr:street":"Trva Basquin\u0303Os Dos;Corun\u0303A",
    "iso:country":"ES",
    "sg:address":"Trva Basqui\u00d1os (dos), 5",
    "sg:city":"Santiago De Compostela",
    "sg:orig_category":"Peluquer\u00cdas, Peluquer\u00cda Mixta",
    "sg:phone":"+34 981 58 76 44",
    "sg:postcode":"15704",
    "sg:province":"La Coru\u00f1a",
    "wof:name":"Garcia Vazquez Maria Trinidad",
    "wof:placetype":"venue"
},
  "geometry": {"coordinates":[-8.537771225,42.8864784241],"type":"Point"}
}