{
  "type": "Feature",
  "properties": {
    "addr:full":"Calle de San Pedro, S/n Illescas Toledo 45200",
    "addr:housenumber":"/ n",
    "addr:postcode":"45200",
    "addr:street":"Calle De San Pedro S",
    "iso:country":"ES",
    "sg:address":"Calle de San Pedro, S/n",
    "sg:city":"Illescas",
    "sg:orig_category":"Polideportivos",
    "sg:phone":"+34 925 51 29 22",
    "sg:postcode":"45200",
    "sg:province":"Toledo",
    "wof:name":"Ayuntamiento De Illescas",
    "wof:placetype":"venue"
},
  "geometry": {"coordinates":[-3.8518652916,40.1295204163],"type":"Point"}
}