{
  "type": "Feature",
  "properties": {
    "addr:full":"Calle de Tempul, 9 Barca De La Florida C\u00e1diz 11570",
    "addr:housenumber":"9",
    "addr:postcode":"11570",
    "addr:street":"Calle De Tempul;Ca\u0301Diz",
    "iso:country":"ES",
    "sg:address":"Calle de Tempul, 9",
    "sg:city":"Barca De La Florida",
    "sg:orig_category":"Negocio De Materiales De Construcci\u00d3n",
    "sg:phone":"+34 956 39 00 30",
    "sg:postcode":"11570",
    "sg:province":"C\u00e1diz",
    "wof:name":"Caleria Gregorio S.l.",
    "wof:placetype":"venue"
},
  "geometry": {"coordinates":[-5.9332890511,36.6488265991],"type":"Point"}
}