{
  "type": "Feature",
  "properties": {
    "iso:country":"ES",
    "sg:address":"Calle de Carde\u00d1osa, 9",
    "sg:city":"Avila",
    "sg:orig_category":"Herramientas Y Suministros Para Plomeros",
    "sg:phone":"+34 920 21 21 31",
    "sg:postcode":"05005",
    "sg:province":"\u00c1vila",
    "wof:name":"Martin Mulas Manuel",
    "wof:placetype":"venue"
},
  "geometry": {"coordinates":[-4.7007246017,40.6607093811],"type":"Point"}
}