{
  "type": "Feature",
  "properties": {
    "iso:country":"ES",
    "sg:address":"Ctra Olivenza, Km. 0010,0",
    "sg:city":"Badajoz",
    "sg:orig_category":"Frutas Y Legumbres Secas (al Por Mayor)",
    "sg:phone":"+34 924 14 05 59",
    "sg:postcode":"06011",
    "sg:province":"Badajoz",
    "wof:name":"Frutos Secos Espa\u00d1oles S.l.",
    "wof:placetype":"venue"
},
  "geometry": {"coordinates":[-6.9874491692,38.8595428467],"type":"Point"}
}