{
  "type": "Feature",
  "properties": {
    "addr:full":"Calle de Real, 37 Almarcha Cuenca 16740",
    "addr:housenumber":"37",
    "addr:postcode":"16740",
    "addr:street":"Calle De Real",
    "iso:country":"ES",
    "sg:address":"Calle de Real, 37",
    "sg:city":"Almarcha",
    "sg:orig_category":"Cajas De Ahorro",
    "sg:phone":"+34 969 29 10 36",
    "sg:postcode":"16740",
    "sg:province":"Cuenca",
    "wof:name":"Caja De Ahorros De Castilla La Mancha",
    "wof:placetype":"venue"
},
  "geometry": {"coordinates":[-2.3830111027,39.6885032654],"type":"Point"}
}