{
  "type": "Feature",
  "properties": {
    "iso:country":"ES",
    "sg:address":"Calle de Virgen De Consolacion, 23",
    "sg:city":"Utrera",
    "sg:orig_category":"Telas Para Tapizar, Cortinas, Pasamaner\u00cda (fabricaci\u00d3n, Al Por Mayor)",
    "sg:phone":"+34 955 86 57 05",
    "sg:postcode":"41710",
    "sg:province":"Sevilla",
    "wof:name":"Utrestilo S.l.",
    "wof:placetype":"venue"
},
  "geometry": {"coordinates":[-5.7791371346,37.1823997498],"type":"Point"}
}