{
  "type": "Feature",
  "properties": {
    "addr:full":"Calle de Rio Alberche (del), 1 Humanes De Madrid Madrid 28970",
    "addr:housenumber":"1",
    "addr:postcode":"28970",
    "addr:street":"Calle De Rio Alberche Del",
    "iso:country":"ES",
    "sg:address":"Calle de Rio Alberche (del), 1",
    "sg:city":"Humanes De Madrid",
    "sg:orig_category":"Fabricaci\u00d3n De Moldes Y Modelos",
    "sg:phone":"+34 916 04 84 84",
    "sg:postcode":"28970",
    "sg:province":"Madrid",
    "wof:name":"Matriceria Y Proyectos S.a.",
    "wof:placetype":"venue"
},
  "geometry": {"coordinates":[-3.8141689301,40.2660484314],"type":"Point"}
}