{
  "type": "Feature",
  "properties": {
    "addr:full":"Plaz Espa\u00d1a, 25 Ribadeo Lugo 27700",
    "addr:housenumber":"25",
    "addr:postcode":"27700",
    "addr:street":"Plaz Espan\u0303A",
    "iso:country":"ES",
    "sg:address":"Plaz Espa\u00d1a, 25",
    "sg:city":"Ribadeo",
    "sg:orig_category":"Bares, Piano",
    "sg:phone":"+34 982 12 90 59",
    "sg:postcode":"27700",
    "sg:province":"Lugo",
    "wof:name":"Alvarez Casado Maria De Los Reyes",
    "wof:placetype":"venue"
},
  "geometry": {"coordinates":[-7.1036396027,43.5224914551],"type":"Point"}
}