{
  "type": "Feature",
  "properties": {
    "addr:full":"Carrer de Sant Carles, 6 Santa Coloma De Gramenet Barcelona 08921",
    "addr:housenumber":"6",
    "addr:postcode":"08921",
    "addr:street":"Carrer De Sant Carles",
    "iso:country":"ES",
    "sg:address":"Carrer de Sant Carles, 6",
    "sg:city":"Santa Coloma De Gramenet",
    "sg:orig_category":"Cajas De Ahorro",
    "sg:phone":"+34 933 86 45 12",
    "sg:postcode":"08921",
    "sg:province":"Barcelona",
    "wof:name":"Caixa D'estalvis I Pensions De Barcelona",
    "wof:placetype":"venue"
},
  "geometry": {"coordinates":[2.2067189217,41.4531135559],"type":"Point"}
}