{
  "type": "Feature",
  "properties": {
    "addr:full":"Carrer de Pau Casals, 4 Castelldefels Barcelona 08860",
    "addr:housenumber":"4",
    "addr:postcode":"08860",
    "addr:street":"Carrer De Pau Casals",
    "iso:country":"ES",
    "sg:address":"Carrer de Pau Casals, 4",
    "sg:city":"Castelldefels",
    "sg:orig_category":"Asesor\u00cdas Y Estudios Financieros",
    "sg:phone":"+34 936 36 38 08",
    "sg:postcode":"08860",
    "sg:province":"Barcelona",
    "sg:website":"www.cabsa.es",
    "wof:name":"Central De Analisis De Balances S.a.",
    "wof:placetype":"venue"
},
  "geometry": {"coordinates":[1.9803570509,41.2803421021],"type":"Point"}
}