{
  "type": "Feature",
  "properties": {
    "iso:country":"ES",
    "sg:address":"Calle de Jucar, 12",
    "sg:city":"Jerez De La Frontera",
    "sg:orig_category":"Empresas De Pintura Y Revestimientos",
    "sg:phone":"+34 956 34 45 58",
    "sg:postcode":"11406",
    "sg:province":"C\u00e1diz",
    "wof:name":"Arana Aguilera Miguel",
    "wof:placetype":"venue"
},
  "geometry": {"coordinates":[-6.1005740166,36.6881942749],"type":"Point"}
}