{
  "type": "Feature",
  "properties": {
    "addr:full":"Calle de Trauko, 27 Bilbao Vizcaya 48007",
    "addr:housenumber":"27",
    "addr:postcode":"48007",
    "addr:street":"Calle De Trauko",
    "iso:country":"ES",
    "sg:address":"Calle de Trauko, 27",
    "sg:city":"Bilbao",
    "sg:orig_category":"Asesor\u00cda Fiscal Y Jur\u00cddica",
    "sg:phone":"+34 944 13 10 42",
    "sg:postcode":"48007",
    "sg:province":"Vizcaya",
    "wof:name":"Askedi, S.l.",
    "wof:placetype":"venue"
},
  "geometry": {"coordinates":[-2.9171369076,43.2663040161],"type":"Point"}
}