{
  "type": "Feature",
  "properties": {
    "addr:full":"Calle de Castilla La Vieja (de), 5 Fuenlabrada Madrid 28941",
    "addr:postcode":"28941",
    "addr:street":"Calle De Castilla La",
    "iso:country":"ES",
    "sg:address":"Calle de Castilla La Vieja (de), 5",
    "sg:city":"Fuenlabrada",
    "sg:orig_category":"Papeler\u00cdas, Librer\u00cdas",
    "sg:phone":"+34 916 09 82 56",
    "sg:postcode":"28941",
    "sg:province":"Madrid",
    "wof:name":"Toro Argenta Luis Miguel",
    "wof:placetype":"venue"
},
  "geometry": {"coordinates":[-3.8010869026,40.2910499573],"type":"Point"}
}