{
  "type": "Feature",
  "properties": {
    "iso:country":"ES",
    "sg:address":"Calle de Huertas (las), 4",
    "sg:city":"Santo\u00f1a",
    "sg:orig_category":"Asociaciones Y Clubs Deportivos",
    "sg:phone":"+34 942 67 17 54",
    "sg:postcode":"39740",
    "sg:province":"Cantabria",
    "wof:name":"Nature Extreme 2004 Sl",
    "wof:placetype":"venue"
},
  "geometry": {"coordinates":[-3.4549880028,43.4429779053],"type":"Point"}
}