{
  "type": "Feature",
  "properties": {
    "iso:country":"ES",
    "sg:address":"Avda Somorrostro (del), 48",
    "sg:city":"San Fernando De Henares",
    "sg:orig_category":"Escayola Y Productos De Escayola (fabricaci\u00d3n, Al Por Mayor)",
    "sg:phone":"+34 916 74 21 36",
    "sg:postcode":"28830",
    "sg:province":"Madrid",
    "wof:name":"Yesos Zarco S.l.l.",
    "wof:placetype":"venue"
},
  "geometry": {"coordinates":[-3.5224061012,40.4154624939],"type":"Point"}
}