{
  "type": "Feature",
  "properties": {
    "iso:country":"ES",
    "sg:address":"Tafalla, 10",
    "sg:city":"Iru\u00f1a",
    "sg:orig_category":"Parques De Atracciones Y Centros De Esparcimiento",
    "sg:phone":"+34 948 23 58 04",
    "sg:postcode":"31004",
    "sg:province":"Navarra",
    "wof:name":"Recreativos Cenzano S.a.",
    "wof:placetype":"venue"
},
  "geometry": {"coordinates":[-1.6367820501,42.8126945496],"type":"Point"}
}