{
  "type": "Feature",
  "properties": {
    "addr:full":"Calle de Teniente General Gutierrez Mellado, S/n Fama Murcia 30008",
    "addr:housenumber":"s / n",
    "addr:postcode":"30008",
    "addr:street":"Calle De Teniente General Gutierrez Mellado",
    "iso:country":"ES",
    "sg:address":"Calle de Teniente General Gutierrez Mellado, S/n",
    "sg:city":"Fama",
    "sg:orig_category":"Caf\u00c9s, Bares, Cervecer\u00cdas",
    "sg:phone":"+34 968 23 31 91",
    "sg:postcode":"30008",
    "sg:province":"Murcia",
    "wof:name":"Garcia Gomez Ricardo",
    "wof:placetype":"venue"
},
  "geometry": {"coordinates":[-1.1283069849,37.9897270203],"type":"Point"}
}