{
  "type": "Feature",
  "properties": {
    "addr:full":"Carrer de Joan Gil, 11 Ondara Alicante 03760",
    "addr:housenumber":"11",
    "addr:postcode":"03760",
    "addr:street":"Carrer De Joan Gil",
    "iso:country":"ES",
    "sg:address":"Carrer de Joan Gil, 11",
    "sg:city":"Ondara",
    "sg:orig_category":"Plomeros",
    "sg:phone":"+34 965 76 74 56",
    "sg:postcode":"03760",
    "sg:province":"Alicante",
    "wof:name":"Salgado Ortega Javier",
    "wof:placetype":"venue"
},
  "geometry": {"coordinates":[0.0171610005,38.8232765198],"type":"Point"}
}