{
  "type": "Feature",
  "properties": {
    "iso:country":"ES",
    "sg:address":"Trva San Pelayo, 4 A",
    "sg:city":"Ermua",
    "sg:orig_category":"Bisuter\u00cda, Joyer\u00cda, Relojer\u00cda (al Por Menor)",
    "sg:phone":"+34 943 17 61 60",
    "sg:postcode":"48260",
    "sg:province":"Vizcaya",
    "sg:website":"www.senen.org",
    "wof:name":"Joyerias Senen, Santos Senen Bravo",
    "wof:placetype":"venue"
},
  "geometry": {"coordinates":[-2.4973800182,43.1792488098],"type":"Point"}
}