{
  "type": "Feature",
  "properties": {
    "addr:full":"Calle de Tres Marias, 7 Zafarraya Granada 18128",
    "addr:housenumber":"7",
    "addr:postcode":"18128",
    "addr:street":"Calle De Tres Marias",
    "iso:country":"ES",
    "sg:address":"Calle de Tres Marias, 7",
    "sg:city":"Zafarraya",
    "sg:orig_category":"Art\u00cdculos Funerarios (al Por Menor)",
    "sg:phone":"+34 958 36 25 82",
    "sg:postcode":"18128",
    "sg:province":"Granada",
    "wof:name":"Portillo Sanchez Felix",
    "wof:placetype":"venue"
},
  "geometry": {"coordinates":[-4.1448688507,36.9735107422],"type":"Point"}
}