{
  "type": "Feature",
  "properties": {
    "addr:full":"Calle de Arcilla, 9 Gloria Almer\u00eda 04230",
    "addr:housenumber":"9",
    "addr:postcode":"04230",
    "addr:street":"Calle De Arcilla;Almeri\u0301A",
    "iso:country":"ES",
    "sg:address":"Calle de Arcilla, 9",
    "sg:city":"Gloria",
    "sg:orig_category":"Albergues Sociales",
    "sg:phone":"+34 950 30 19 92",
    "sg:postcode":"04230",
    "sg:province":"Almer\u00eda",
    "wof:name":"Inalgra S.l",
    "wof:placetype":"venue"
},
  "geometry": {"coordinates":[-2.4679217339,36.8401641846],"type":"Point"}
}