{
  "type": "Feature",
  "properties": {
    "iso:country":"ES",
    "sg:address":"Calle de Princesa Dacil, 35",
    "sg:city":"Alvarados",
    "sg:orig_category":"Organismos De Turismo",
    "sg:phone":"+34 928 35 39 36",
    "sg:postcode":"35310",
    "sg:province":"Las Palmas",
    "wof:name":"Martin Betancor Francisco",
    "wof:placetype":"venue"
},
  "geometry": {"coordinates":[-15.4758090973,28.0502548218],"type":"Point"}
}