{
  "type": "Feature",
  "properties": {
    "iso:country":"ES",
    "sg:address":"Avda Aguirre Lehendakari, 13",
    "sg:city":"Bilbao",
    "sg:orig_category":"Molduras, Junquillos, Listones Y Molduras Perforadas",
    "sg:phone":"+34 944 02 92 25",
    "sg:postcode":"48014",
    "sg:province":"Vizcaya",
    "wof:name":"Carlos Arteagoitia Vivian",
    "wof:placetype":"venue"
},
  "geometry": {"coordinates":[-2.9463489056,43.2717704773],"type":"Point"}
}