{
  "type": "Feature",
  "properties": {
    "addr:full":"Av Tarragona, S/n Vilafranca Penedes Barcelona 08720",
    "addr:postcode":"08720",
    "addr:street":"Av Tarragona S / N Vilafranca Penedes Barcelona",
    "iso:country":"ES",
    "sg:address":"Av Tarragona, S/n",
    "sg:city":"Vilafranca Penedes",
    "sg:classifiers":[
        {
            "category":"Home & Garden",
            "subcategory":"Household Appliances",
            "type":"Retail Goods"
        }
    ],
    "sg:phone":"+34 938 90 23 07",
    "sg:postcode":"08720",
    "sg:province":"Barcelona",
    "sg:tags":[
        "bodega",
        "de",
        "vino",
        "acondicionamiento"
    ],
    "wof:name":"Antonio Mascaro S.l.",
    "wof:placetype":"venue"
},
  "geometry": {"coordinates":[1.6867825985,41.3362731934],"type":"Point"}
}