{
  "type": "Feature",
  "properties": {
    "addr:full":"Cra De Canillas De Albaida, Km. 0001,0 Competa M\u00e1laga 29754",
    "addr:postcode":"29754",
    "addr:street":"Albaida Km. 0001,0 Competa Ma\u0301Laga",
    "iso:country":"ES",
    "sg:address":"Cra De Canillas De Albaida, Km. 0001,0",
    "sg:city":"Competa",
    "sg:orig_category":"Productores Recolectores, Venta Directa De Vinos",
    "sg:phone":"+34 952 55 32 85",
    "sg:postcode":"29754",
    "sg:province":"M\u00e1laga",
    "wof:name":"Bodegas Almijara S.l.",
    "wof:placetype":"venue"
},
  "geometry": {"coordinates":[-3.9767189026,36.8319282532],"type":"Point"}
}