{
  "type": "Feature",
  "properties": {
    "addr:full":"Avda Caceres, 12 Sierra Fuentes C\u00e1ceres 10181",
    "addr:housenumber":"12",
    "addr:postcode":"10181",
    "addr:street":"Avda Caceres;Sierra Fuentes Ca\u0301Ceres",
    "iso:country":"ES",
    "sg:address":"Avda Caceres, 12",
    "sg:city":"Sierra Fuentes",
    "sg:orig_category":"Cajas De Ahorro",
    "sg:phone":"+34 927 20 00 07",
    "sg:postcode":"10181",
    "sg:province":"C\u00e1ceres",
    "sg:website":"www.cajaextremadura.es",
    "wof:name":"Caja De Ahorros Y Monte De Piedad De Extremadura",
    "wof:placetype":"venue"
},
  "geometry": {"coordinates":[-6.2746992111,39.4375991821],"type":"Point"}
}