{
  "type": "Feature",
  "properties": {
    "iso:country":"ES",
    "sg:address":"Calle de Licurgo, 24",
    "sg:city":"Malaga",
    "sg:orig_category":"Inmobiliaria (agencias)",
    "sg:phone":"+34 952 17 64 25",
    "sg:postcode":"29004",
    "sg:province":"M\u00e1laga",
    "wof:name":"Barbara Inversiones S.l.",
    "wof:placetype":"venue"
},
  "geometry": {"coordinates":[-4.4630389214,36.6907615662],"type":"Point"}
}