{
  "type": "Feature",
  "properties": {
    "addr:full":"Pg Misericordia, 12 Reus Tarragona 43205",
    "addr:housenumber":"12",
    "addr:postcode":"43205",
    "addr:street":"Pg Misericordia",
    "iso:country":"ES",
    "sg:address":"Pg Misericordia, 12",
    "sg:city":"Reus",
    "sg:orig_category":"Muebles, Minoristas",
    "sg:phone":"+34 977 77 48 41",
    "sg:postcode":"43205",
    "sg:province":"Tarragona",
    "wof:name":"Vanzanki S.l.",
    "wof:placetype":"venue"
},
  "geometry": {"coordinates":[1.1052320004,41.1484909058],"type":"Point"}
}