{
  "type": "Feature",
  "properties": {
    "iso:country":"ES",
    "sg:address":"Calle de Bobalar, S/n",
    "sg:city":"Massamagrell",
    "sg:orig_category":"Frutas Y Legumbres Frescas (al Por Mayor)",
    "sg:phone":"+34 961 45 03 36",
    "sg:postcode":"46130",
    "sg:province":"Valencia",
    "wof:name":"Alcover Oltra Vicente",
    "wof:placetype":"venue"
},
  "geometry": {"coordinates":[-0.3382818997,39.5885887146],"type":"Point"}
}