{
  "type": "Feature",
  "properties": {
    "addr:full":"Avda Ciudad De Mataro, 10 Cehegin Murcia 30430",
    "addr:housenumber":"10",
    "addr:postcode":"30430",
    "addr:street":"Avda Ciudad De Mataro",
    "iso:country":"ES",
    "sg:address":"Avda Ciudad De Mataro, 10",
    "sg:city":"Cehegin",
    "sg:orig_category":"Abogados",
    "sg:phone":"+34 968 74 36 18",
    "sg:postcode":"30430",
    "sg:province":"Murcia",
    "wof:name":"Ruiz Martinez Juan Manuel",
    "wof:placetype":"venue"
},
  "geometry": {"coordinates":[-1.7979459763,38.0936012268],"type":"Point"}
}