{
  "type": "Feature",
  "properties": {
    "addr:full":"Urb Parque (el), 1 Antequera M\u00e1laga 29200",
    "addr:postcode":"29200",
    "addr:street":"Urb;El;Ma\u0301Laga",
    "iso:country":"ES",
    "sg:address":"Urb Parque (el), 1",
    "sg:city":"Antequera",
    "sg:orig_category":"Procuradores",
    "sg:phone":"+34 952 70 14 09",
    "sg:postcode":"29200",
    "sg:province":"M\u00e1laga",
    "wof:name":"Montoro Mantilla Enriqueta",
    "wof:placetype":"venue"
},
  "geometry": {"coordinates":[-4.5667471886,37.0212974548],"type":"Point"}
}