{
  "type": "Feature",
  "properties": {
    "iso:country":"ES",
    "sg:address":"Ctra Palamos, 58",
    "sg:city":"Celra",
    "sg:classifiers":[
        {
            "category":"Autos & Motor Vehicles",
            "subcategory":"Automobile Sales",
            "type":"Retail Goods"
        }
    ],
    "sg:phone":"+34 972 49 23 47",
    "sg:postcode":"17460",
    "sg:province":"Girona",
    "wof:name":"Auto Escola Llado S. A.",
    "wof:placetype":"venue"
},
  "geometry": {"coordinates":[2.8775780201,42.0284004211],"type":"Point"}
}