{
  "type": "Feature",
  "properties": {
    "addr:full":"Carrer de Escipio, 51 Sabadell Barcelona 08208",
    "addr:housenumber":"51",
    "addr:postcode":"08208",
    "addr:street":"Carrer De Escipio",
    "iso:country":"ES",
    "sg:address":"Carrer de Escipio, 51",
    "sg:city":"Sabadell",
    "sg:orig_category":"Empresas De Carpinter\u00cda",
    "sg:phone":"+34 937 24 00 54",
    "sg:postcode":"08208",
    "sg:province":"Barcelona",
    "wof:name":"Aluesgar S.l.",
    "wof:placetype":"venue"
},
  "geometry": {"coordinates":[2.1064836979,41.5648880005],"type":"Point"}
}