{
  "type": "Feature",
  "properties": {
    "iso:country":"ES",
    "sg:address":"Pol Ind Eras De La Ventilla, S/n",
    "sg:city":"Pegalajar",
    "sg:orig_category":"Negocio De Materiales De Construcci\u00d3n",
    "sg:phone":"+34 953 36 01 30",
    "sg:postcode":"23110",
    "sg:province":"Ja\u00e9n",
    "wof:name":"Prefabricados Cordero S.a.",
    "wof:placetype":"venue"
},
  "geometry": {"coordinates":[-3.6396489143,37.7409286499],"type":"Point"}
}