{
  "type": "Feature",
  "properties": {
    "addr:full":"Calle de Zorrilla, 60 Elda Alicante 03600",
    "addr:housenumber":"60",
    "addr:postcode":"03600",
    "addr:street":"Calle De Zorrilla",
    "iso:country":"ES",
    "sg:address":"Calle de Zorrilla, 60",
    "sg:city":"Elda",
    "sg:orig_category":"Deportes Diversos",
    "sg:phone":"+34 965 39 07 00",
    "sg:postcode":"03600",
    "sg:province":"Alicante",
    "wof:name":"Federacion De Natacion De La Comunidad Valenciana",
    "wof:placetype":"venue"
},
  "geometry": {"coordinates":[-0.7921190262,38.474571228],"type":"Point"}
}