{
  "type": "Feature",
  "properties": {
    "addr:full":"Calle de Embajadores, 204 Madrid Madrid 28045",
    "addr:housenumber":"204",
    "addr:postcode":"28045",
    "addr:street":"Calle De Embajadores",
    "iso:country":"ES",
    "sg:address":"Calle de Embajadores, 204",
    "sg:city":"Madrid",
    "sg:orig_category":"Estudios, Instalaci\u00d3n De Climatizaci\u00d3n",
    "sg:phone":"+34 915 28 82 61",
    "sg:postcode":"28045",
    "sg:province":"Madrid",
    "sg:website":"www.euroclimamadrid.com",
    "wof:name":"Euroclima Madrid S.l.",
    "wof:placetype":"venue"
},
  "geometry": {"coordinates":[-3.6930909157,40.3912162781],"type":"Point"}
}