{
  "type": "Feature",
  "properties": {
    "addr:full":"Calle de Poeta Jose Luis Hidalgo, 3 Torrelavega Cantabria 39300",
    "addr:postcode":"39300",
    "addr:street":"Calle De Poeta Jose Luis Hidalgo 3",
    "iso:country":"ES",
    "sg:address":"Calle de Poeta Jose Luis Hidalgo, 3",
    "sg:city":"Torrelavega",
    "sg:orig_category":"Agentes Generales De Seguros",
    "sg:phone":"+34 942 80 10 06",
    "sg:postcode":"39300",
    "sg:province":"Cantabria",
    "wof:name":"Fernandez Villegas Vivencio",
    "wof:placetype":"venue"
},
  "geometry": {"coordinates":[-4.0547661781,43.3495178223],"type":"Point"}
}