{
  "type": "Feature",
  "properties": {
    "iso:country":"ES",
    "sg:address":"Pl Mayor, 5",
    "sg:city":"Palleja",
    "sg:orig_category":"Bisuter\u00cda, Joyer\u00cda, Relojer\u00cda (al Por Menor)",
    "sg:phone":"+34 936 63 05 91",
    "sg:postcode":"08780",
    "sg:province":"Barcelona",
    "wof:name":"Novajoia 2006 S.l.",
    "wof:placetype":"venue"
},
  "geometry": {"coordinates":[1.9970400333,41.4223861694],"type":"Point"}
}