{
  "type": "Feature",
  "properties": {
    "iso:country":"ES",
    "sg:address":"Avda Pruna, 8",
    "sg:city":"Moron Frontera",
    "sg:orig_category":"Herradores, Herreros, Carreteros",
    "sg:phone":"+34 955 85 12 89",
    "sg:postcode":"41530",
    "sg:province":"Sevilla",
    "wof:name":"Suministros De Ferreteria Solano S.l.",
    "wof:placetype":"venue"
},
  "geometry": {"coordinates":[-5.4528231621,37.1294212341],"type":"Point"}
}