{
  "type": "Feature",
  "properties": {
    "iso:country":"ES",
    "sg:address":"Carrer de Pere Iv, 208",
    "sg:city":"Barcelona",
    "sg:orig_category":"Molduras, Junquillos, Listones Y Molduras Perforadas",
    "sg:phone":"+34 934 85 01 00",
    "sg:postcode":"08005",
    "sg:province":"Barcelona",
    "wof:name":"Tenza Maroto Carlos",
    "wof:placetype":"venue"
},
  "geometry": {"coordinates":[2.1986410618,41.4036750793],"type":"Point"}
}