{
  "type": "Feature",
  "properties": {
    "iso:country":"ES",
    "sg:address":"Carrer de Pica D'estats, S/n",
    "sg:city":"S. Fruitos Bages",
    "sg:orig_category":"Aparatos De Medida, Control, Regulaci\u00d3n Y Detecci\u00d3n",
    "sg:phone":"+34 938 73 88 77",
    "sg:postcode":"08272",
    "sg:province":"Barcelona",
    "sg:website":"www.teinco.com",
    "wof:name":"Automatica De Control Teinco S.l.",
    "wof:placetype":"venue"
},
  "geometry": {"coordinates":[1.8217660189,41.7293052673],"type":"Point"}
}