{
  "type": "Feature",
  "properties": {
    "addr:full":"Calle de Velarde, 29 Malaga M\u00e1laga 29009",
    "addr:housenumber":"29",
    "addr:postcode":"29009",
    "addr:street":"Calle De Velarde;Ma\u0301Laga",
    "iso:country":"ES",
    "sg:address":"Calle de Velarde, 29",
    "sg:city":"Malaga",
    "sg:orig_category":"Sociedades, Compa\u00d1\u00cdas Aseguradoras",
    "sg:phone":"+34 952 28 51 50",
    "sg:postcode":"29009",
    "sg:province":"M\u00e1laga",
    "wof:name":"Oficina Directa S.l.",
    "wof:placetype":"venue"
},
  "geometry": {"coordinates":[-4.4345550537,36.7266921997],"type":"Point"}
}