{
  "type": "Feature",
  "properties": {
    "iso:country":"ES",
    "sg:address":"Calle de San Miguel, 23",
    "sg:city":"Onda",
    "sg:orig_category":"Centros Comerciales Y Grandes Tiendas",
    "sg:phone":"+34 964 60 03 22",
    "sg:postcode":"12200",
    "sg:province":"Castell\u00f3n",
    "wof:name":"Sansano Marti Juan",
    "wof:placetype":"venue"
},
  "geometry": {"coordinates":[-0.2637479901,39.9627189636],"type":"Point"}
}