{
  "type": "Feature",
  "properties": {
    "addr:full":"Plaz Cristo Rey, S/n Madrid Madrid 28040",
    "addr:housenumber":"s / n",
    "addr:postcode":"28040",
    "addr:street":"Cristo Rey",
    "iso:country":"ES",
    "sg:address":"Plaz Cristo Rey, S/n",
    "sg:city":"Madrid",
    "sg:orig_category":"Transporte En General",
    "sg:phone":"+34 915 49 87 36",
    "sg:postcode":"28040",
    "sg:province":"Madrid",
    "sg:website":"www.philips.es",
    "wof:name":"Philips Iberica S.a.",
    "wof:placetype":"venue"
},
  "geometry": {"coordinates":[-3.7174949646,40.4394187927],"type":"Point"}
}