{
  "type": "Feature",
  "properties": {
    "iso:country":"ES",
    "sg:address":"Calle de Virgen Blanca (la), 12",
    "sg:city":"Le\u00f3n",
    "sg:orig_category":"Asociaciones Y Clubs Deportivos",
    "sg:phone":"+34 987 21 25 29",
    "sg:postcode":"24006",
    "sg:province":"Le\u00f3n",
    "wof:name":"Teran Alonso Jose Antonio",
    "wof:placetype":"venue"
},
  "geometry": {"coordinates":[-5.5628080368,42.5971412659],"type":"Point"}
}