{
  "type": "Feature",
  "properties": {
    "addr:full":"Avda Europa, 6 Sierra Altea Alicante 03590",
    "addr:housenumber":"6",
    "addr:postcode":"03590",
    "addr:street":"Avda Europa;Sierra Altea",
    "iso:country":"ES",
    "sg:address":"Avda Europa, 6",
    "sg:city":"Sierra Altea",
    "sg:orig_category":"Agencias Y Agentes Comerciales, Representantes",
    "sg:phone":"+34 966 88 81 01",
    "sg:postcode":"03590",
    "sg:province":"Alicante",
    "wof:name":"Bozenikova  Ivana",
    "wof:placetype":"venue"
},
  "geometry": {"coordinates":[-0.0522690006,38.601108551],"type":"Point"}
}