{
  "type": "Feature",
  "properties": {
    "addr:full":"Plaz Angela Mu\u00d1oz, S/n Arevalo \u00c1vila 05200",
    "addr:postcode":"05200",
    "addr:street":"Mun\u0303Oz S / N",
    "iso:country":"ES",
    "sg:address":"Plaz Angela Mu\u00d1oz, S/n",
    "sg:city":"Arevalo",
    "sg:orig_category":"Asilos De Ancianos. Centros Privados",
    "sg:phone":"+34 920 30 00 23",
    "sg:postcode":"05200",
    "sg:province":"\u00c1vila",
    "wof:name":"Residencia De Ancianos San Miguel Arcangel",
    "wof:placetype":"venue"
},
  "geometry": {"coordinates":[-4.7187438011,41.061504364],"type":"Point"}
}