{
  "type": "Feature",
  "properties": {
    "addr:full":"M. Montija, S/n Villalonquejar Burgos 09001",
    "addr:housenumber":"s / n",
    "addr:postcode":"09001",
    "iso:country":"ES",
    "sg:address":"M. Montija, S/n",
    "sg:city":"Villalonquejar",
    "sg:orig_category":"Ebanister\u00cda",
    "sg:phone":"+34 947 29 80 48",
    "sg:postcode":"09001",
    "sg:province":"Burgos",
    "wof:name":"Carpinteria Ebanisteria Gonzalez M. S.l.",
    "wof:placetype":"venue"
},
  "geometry": {"coordinates":[-3.7355909348,42.375667572],"type":"Point"}
}