{
  "type": "Feature",
  "properties": {
    "addr:full":"Calle de Gabasti, 7 Madrid Madrid 28027",
    "addr:housenumber":"7",
    "addr:postcode":"madrid;28027",
    "addr:street":"Calle De Gabasti",
    "iso:country":"ES",
    "sg:address":"Calle de Gabasti, 7",
    "sg:city":"Madrid",
    "sg:orig_category":"Fotocopias, Reprograf\u00cda",
    "sg:phone":"+34 914 08 15 58",
    "sg:postcode":"28027",
    "sg:province":"Madrid",
    "wof:name":"Atimo S.l.",
    "wof:placetype":"venue"
},
  "geometry": {"coordinates":[-3.644554615,40.4371757507],"type":"Point"}
}