{
  "type": "Feature",
  "properties": {
    "iso:country":"ES",
    "sg:address":"Carrer de Congost, 18",
    "sg:city":"Centelles",
    "sg:orig_category":"Construcciones Met\u00c1licas",
    "sg:phone":"+34 938 81 04 17",
    "sg:postcode":"08540",
    "sg:province":"Barcelona",
    "wof:name":"Vi\u00f1as Planas Juan",
    "wof:placetype":"venue"
},
  "geometry": {"coordinates":[2.2236161232,41.795337677],"type":"Point"}
}