{
  "type": "Feature",
  "properties": {
    "addr:full":"Pase Ermita Del Santo, S/n Madrid Madrid 28019",
    "addr:housenumber":"s / n",
    "addr:postcode":"28019",
    "iso:country":"ES",
    "sg:address":"Pase Ermita Del Santo, S/n",
    "sg:city":"Madrid",
    "sg:orig_category":"Fabricaci\u00d3n, Venta, Instalaci\u00d3n De R\u00d3tulos, De R\u00d3tulos Luminosos",
    "sg:phone":"+34 915 60 10 03",
    "sg:postcode":"28019",
    "sg:province":"Madrid",
    "wof:name":"Carralon Rivas Jose Luis",
    "wof:placetype":"venue"
},
  "geometry": {"coordinates":[-3.7246890068,40.4024658203],"type":"Point"}
}