{
  "type": "Feature",
  "properties": {
    "iso:country":"ES",
    "sg:address":"Calle de Camino De Velez, 22",
    "sg:city":"Periana",
    "sg:orig_category":"Cajas Para Embalar",
    "sg:phone":"+34 952 53 61 66",
    "sg:postcode":"29710",
    "sg:province":"M\u00e1laga",
    "wof:name":"Cajamar",
    "wof:placetype":"venue"
},
  "geometry": {"coordinates":[-4.1911039352,36.9303092957],"type":"Point"}
}