{
  "type": "Feature",
  "properties": {
    "iso:country":"ES",
    "sg:address":"Rua Romero Ortiz, 19",
    "sg:city":"Vilagarcia",
    "sg:orig_category":"Administradores De Bienes Y Delegados De Comunidades De Propietarios",
    "sg:phone":"+34 986 50 58 91",
    "sg:postcode":"36600",
    "sg:province":"Pontevedra",
    "wof:name":"Lema Administracion De Fincas S.l.",
    "wof:placetype":"venue"
},
  "geometry": {"coordinates":[-8.7652978897,42.5917396545],"type":"Point"}
}