{
  "type": "Feature",
  "properties": {
    "iso:country":"ES",
    "sg:address":"Calle de Esteban Saez Alvarado, 7",
    "sg:city":"Burgos",
    "sg:orig_category":"Empresarios",
    "sg:phone":"+34 947 48 03 17",
    "sg:postcode":"09007",
    "sg:province":"Burgos",
    "wof:name":"Casado Pascual Miguel Angel",
    "wof:placetype":"venue"
},
  "geometry": {"coordinates":[-3.6637239456,42.3559265137],"type":"Point"}
}