{
  "type": "Feature",
  "properties": {
    "addr:full":"Carr Lauri Volpi, 49 Burjassot Valencia 46100",
    "addr:housenumber":"49",
    "addr:postcode":"46100",
    "addr:street":"Carr Lauri Volpi",
    "iso:country":"ES",
    "sg:address":"Carr Lauri Volpi, 49",
    "sg:city":"Burjassot",
    "sg:orig_category":"Florister\u00cdas",
    "sg:phone":"+34 963 90 06 58",
    "sg:postcode":"46100",
    "sg:province":"Valencia",
    "wof:name":"Esteban Rodriguez Santiago De",
    "wof:placetype":"venue"
},
  "geometry": {"coordinates":[-0.4128690064,39.5173301697],"type":"Point"}
}