{
  "type": "Feature",
  "properties": {
    "iso:country":"ES",
    "sg:address":"Calle de San Zoilo, 23",
    "sg:city":"Carrion De Los Condes",
    "sg:orig_category":"Asociaciones, Organismos Culturales Y Socioeducativos",
    "sg:phone":"+34 979 88 09 02",
    "sg:postcode":"34120",
    "sg:province":"Palencia",
    "wof:name":"Centro De Iniciativas Turisticas Camino De Santiago Palentino",
    "wof:placetype":"venue"
},
  "geometry": {"coordinates":[-4.6083688736,42.3396606445],"type":"Point"}
}