{
  "type": "Feature",
  "properties": {
    "addr:full":"La Balsa, S/n Baldellou Huesca 22571",
    "addr:housenumber":"s",
    "addr:postcode":"22571",
    "addr:street":"/ N Baldellou",
    "iso:country":"ES",
    "sg:address":"La Balsa, S/n",
    "sg:city":"Baldellou",
    "sg:orig_category":"Producci\u00d3n, Comercio De Cereales",
    "sg:phone":"+34 974 43 33 25",
    "sg:postcode":"22571",
    "sg:province":"Huesca",
    "wof:name":"Ramon Camarasa S.l.",
    "wof:placetype":"venue"
},
  "geometry": {"coordinates":[0.5464079976,41.9182319641],"type":"Point"}
}