{
  "type": "Feature",
  "properties": {
    "iso:country":"ES",
    "sg:address":"Calle de Asturias, 2",
    "sg:city":"Grado",
    "sg:orig_category":"Asociaciones Y Clubs Deportivos",
    "sg:phone":"+34 985 75 00 14",
    "sg:postcode":"33820",
    "sg:province":"Asturias",
    "wof:name":"Pantalla 2000 S.l.",
    "wof:placetype":"venue"
},
  "geometry": {"coordinates":[-6.072239399,43.387966156],"type":"Point"}
}