{
  "type": "Feature",
  "properties": {
    "iso:country":"ES",
    "sg:address":"Calle de Ingeniero Juan Romero Carrasco, 28",
    "sg:city":"Ubrique",
    "sg:orig_category":"Agentes Generales De Seguros",
    "sg:phone":"+34 956 46 27 12",
    "sg:postcode":"11600",
    "sg:province":"C\u00e1diz",
    "sg:website":"www.fiatc.es",
    "wof:name":"Gomez Chacon Rafael",
    "wof:placetype":"venue"
},
  "geometry": {"coordinates":[-5.4457988739,36.6738586426],"type":"Point"}
}