{
  "type": "Feature",
  "properties": {
    "iso:country":"ES",
    "sg:address":"Calle de Escoriaza Y Fabro, 38",
    "sg:city":"Zaragoza",
    "sg:orig_category":"Comercio De Mobiliario De Oficina",
    "sg:phone":"+34 976 53 68 38",
    "sg:postcode":"50010",
    "sg:province":"Zaragoza",
    "wof:name":"Andreu Plano S.l.",
    "wof:placetype":"venue"
},
  "geometry": {"coordinates":[-0.898283124,41.6543045044],"type":"Point"}
}