{
  "type": "Feature",
  "properties": {
    "iso:country":"ES",
    "sg:address":"Praz Cervantes (de), 4",
    "sg:city":"Santiago De Compostela",
    "sg:orig_category":"Centros De Reservas Hoteleras",
    "sg:phone":"+34 981 57 39 11",
    "sg:postcode":"15704",
    "sg:province":"A Coru\u00f1a",
    "wof:name":"Xho Xestiona Hosteleria Sc",
    "wof:placetype":"venue"
},
  "geometry": {"coordinates":[-8.537771225,42.8864784241],"type":"Point"}
}