{
  "type": "Feature",
  "properties": {
    "addr:full":"Calle de Fernando Sastre, 1 Mislata Valencia 46920",
    "addr:housenumber":"1",
    "addr:postcode":"46920",
    "addr:street":"Calle De Fernando Sastre",
    "iso:country":"ES",
    "sg:address":"Calle de Fernando Sastre, 1",
    "sg:city":"Mislata",
    "sg:orig_category":"Alimentaci\u00d3n General (al Por Menor)",
    "sg:phone":"+34 963 83 66 36",
    "sg:postcode":"46920",
    "sg:province":"Valencia",
    "wof:name":"Mercado Tradicional De Mislata A.i.e.",
    "wof:placetype":"venue"
},
  "geometry": {"coordinates":[-0.415255487,39.4735374451],"type":"Point"}
}