{
  "type": "Feature",
  "properties": {
    "iso:country":"ES",
    "sg:address":"Calle de Libertad (de La), 47",
    "sg:city":"Mostoles",
    "sg:orig_category":"Molduras, Junquillos, Listones Y Molduras Perforadas",
    "sg:phone":"+34 916 46 76 67",
    "sg:postcode":"28936",
    "sg:province":"Madrid",
    "wof:name":"Garcia Moreno Francisco",
    "wof:placetype":"venue"
},
  "geometry": {"coordinates":[-3.8527810574,40.3249931335],"type":"Point"}
}