{
  "type": "Feature",
  "properties": {
    "addr:full":"Avda Pablo Gargallo, 9 Zaragoza Zaragoza 50003",
    "addr:housenumber":"9",
    "addr:postcode":"50003",
    "addr:street":"Avda Pablo Gargallo",
    "iso:country":"ES",
    "sg:address":"Avda Pablo Gargallo, 9",
    "sg:city":"Zaragoza",
    "sg:orig_category":"Dise\u00d1o Industrial",
    "sg:phone":"+34 976 44 19 43",
    "sg:postcode":"50003",
    "sg:province":"Zaragoza",
    "wof:name":"Aguerri Poderos Javier Vicente",
    "wof:placetype":"venue"
},
  "geometry": {"coordinates":[-0.8947842717,41.6587982178],"type":"Point"}
}