{
  "type": "Feature",
  "properties": {
    "addr:full":"Carrer de Major, 12 Gratallops Tarragona 43737",
    "addr:housenumber":"12",
    "addr:postcode":"43737",
    "addr:street":"Carrer De Major",
    "iso:country":"ES",
    "sg:address":"Carrer de Major, 12",
    "sg:city":"Gratallops",
    "sg:orig_category":"Productores Recolectores, Venta Directa De Vinos",
    "sg:phone":"+34 977 83 93 61",
    "sg:postcode":"43737",
    "sg:province":"Tarragona",
    "wof:name":"Ripoll Cubells Oscar",
    "wof:placetype":"venue"
},
  "geometry": {"coordinates":[0.7773519754,41.193145752],"type":"Point"}
}