{
  "type": "Feature",
  "properties": {
    "addr:full":"Calle de Marques De La Valdavia (del), 20 Alcobendas Madrid 28100",
    "addr:postcode":"28100",
    "addr:street":"Calle De Marques De La Valdavia Del;Alcobendas",
    "iso:country":"ES",
    "sg:address":"Calle de Marques De La Valdavia (del), 20",
    "sg:city":"Alcobendas",
    "sg:orig_category":"Aparcamientos (infraestructuras, Accesorios)",
    "sg:phone":"+34 916 63 60 36",
    "sg:postcode":"28100",
    "sg:province":"Madrid",
    "wof:name":"Jesfimar S.l.",
    "wof:placetype":"venue"
},
  "geometry": {"coordinates":[-3.6368978024,40.5408592224],"type":"Point"}
}