{
  "type": "Feature",
  "properties": {
    "addr:full":"Ctra Pinos Puente, Km. 0427,0 Atarfe Granada 18230",
    "addr:postcode":"18230",
    "addr:street":"Ctra Pinos Puente Km. 0427,0",
    "iso:country":"ES",
    "sg:address":"Ctra Pinos Puente, Km. 0427,0",
    "sg:city":"Atarfe",
    "sg:orig_category":"Soldadura Y Recortado Con Soplete",
    "sg:phone":"+34 958 43 46 09",
    "sg:postcode":"18230",
    "sg:province":"Granada",
    "wof:name":"Sevilla Carballar Felipe",
    "wof:placetype":"venue"
},
  "geometry": {"coordinates":[-3.6903159618,37.2228775024],"type":"Point"}
}