{
  "type": "Feature",
  "properties": {
    "iso:country":"ES",
    "sg:address":"Calle de Dec. Higueras Del Castillo, 64",
    "sg:city":"Torremolinos",
    "sg:orig_category":"Quincaller\u00cda (al Por Menor)",
    "sg:phone":"+34 952 37 47 07",
    "sg:postcode":"29620",
    "sg:province":"M\u00e1laga",
    "wof:name":"Clavijo Liendo Gustavo",
    "wof:placetype":"venue"
},
  "geometry": {"coordinates":[-4.5015897751,36.6145133972],"type":"Point"}
}