{
  "type": "Feature",
  "properties": {
    "addr:full":"Calle de Blasco Iba\u00d1ez, 2 Chiva Valencia 46370",
    "addr:housenumber":"2",
    "addr:postcode":"46370",
    "addr:street":"Calle De Blasco Iban\u0303Ez",
    "iso:country":"ES",
    "sg:address":"Calle de Blasco Iba\u00d1ez, 2",
    "sg:city":"Chiva",
    "sg:orig_category":"Empresas De Portes Y Mensajer\u00cda",
    "sg:phone":"+34 962 52 23 69",
    "sg:postcode":"46370",
    "sg:province":"Valencia",
    "wof:name":"Chiva Currier S.l.",
    "wof:placetype":"venue"
},
  "geometry": {"coordinates":[-0.7147020102,39.4724731445],"type":"Point"}
}