{
  "type": "Feature",
  "properties": {
    "iso:country":"ES",
    "sg:address":"Calle de Doctor Bonardell, 15",
    "sg:city":"Alcazar S. Juan",
    "sg:orig_category":"Herboristas (al Por Menor)",
    "sg:phone":"+34 926 55 08 94",
    "sg:postcode":"13600",
    "sg:province":"Ciudad Real",
    "wof:name":"Ayla Herbal S.l.",
    "wof:placetype":"venue"
},
  "geometry": {"coordinates":[-3.2135241032,39.3889350891],"type":"Point"}
}