{
  "type": "Feature",
  "properties": {
    "iso:country":"ES",
    "sg:address":"Calle de Balbino Marron, S/n",
    "sg:city":"Sevilla",
    "sg:orig_category":"Promotores Constructores",
    "sg:phone":"+34 954 93 39 31",
    "sg:postcode":"41018",
    "sg:province":"Sevilla",
    "sg:website":"www.quatinvegest.com",
    "wof:name":"Quat Inversiones S.l.",
    "wof:placetype":"venue"
},
  "geometry": {"coordinates":[-5.9776940346,37.3797416687],"type":"Point"}
}