{
  "type": "Feature",
  "properties": {
    "iso:country":"ES",
    "sg:address":"Av Moli, 41",
    "sg:city":"Viladecans",
    "sg:orig_category":"Reposter\u00cdas",
    "sg:phone":"+34 936 37 58 49",
    "sg:postcode":"08840",
    "sg:province":"Barcelona",
    "wof:name":"Distribuidora Del Gornal S. A.",
    "wof:placetype":"venue"
},
  "geometry": {"coordinates":[2.0099198818,41.3216590881],"type":"Point"}
}