{
  "type": "Feature",
  "properties": {
    "addr:full":"Calle de Oceano Antartico, 13 Caceres C\u00e1ceres 10005",
    "addr:housenumber":"13",
    "addr:postcode":"10005",
    "addr:street":"Calle De Oceano Antartico;Ca\u0301Ceres",
    "iso:country":"ES",
    "sg:address":"Calle de Oceano Antartico, 13",
    "sg:city":"Caceres",
    "sg:orig_category":"Mec\u00c1nico Del Autom\u00d3vil",
    "sg:phone":"+34 927 21 00 72",
    "sg:postcode":"10005",
    "sg:province":"C\u00e1ceres",
    "wof:name":"Talleres Juan Pacheco S.l.",
    "wof:placetype":"venue"
},
  "geometry": {"coordinates":[-6.3681578636,39.4541282654],"type":"Point"}
}