{
  "type": "Feature",
  "properties": {
    "addr:full":"Jose Antonio, 7 Sepulveda Segovia 40300",
    "addr:housenumber":"7",
    "addr:postcode":"40300",
    "addr:street":"Jose Antonio",
    "iso:country":"ES",
    "sg:address":"Jose Antonio, 7",
    "sg:city":"Sepulveda",
    "sg:orig_category":"Peluquer\u00cdas, Peluquer\u00cda Mixta",
    "sg:phone":"+34 921 54 04 07",
    "sg:postcode":"40300",
    "sg:province":"Segovia",
    "wof:name":"Sanz Roman Pilar",
    "wof:placetype":"venue"
},
  "geometry": {"coordinates":[-3.7487390041,41.2972755432],"type":"Point"}
}