{
  "type": "Feature",
  "properties": {
    "iso:country":"ES",
    "sg:address":"Avda Lebrija (de), S/n",
    "sg:city":"Jerez De La Frontera",
    "sg:orig_category":"Comerciantes Al Por Mayor De Vinos, Licores Y Alcoholes",
    "sg:phone":"+34 956 31 21 76",
    "sg:postcode":"11407",
    "sg:province":"C\u00e1diz",
    "sg:website":"www.gonzalezbyass.com",
    "wof:name":"Gonzalez Byass S. A.",
    "wof:placetype":"venue"
},
  "geometry": {"coordinates":[-6.129445076,36.7043418884],"type":"Point"}
}