{
  "type": "Feature",
  "properties": {
    "iso:country":"ES",
    "sg:address":"Calle de Luz (la), 25",
    "sg:city":"Estacion",
    "sg:orig_category":"Negocio De Materiales De Construcci\u00d3n",
    "sg:phone":"+34 950 46 42 33",
    "sg:postcode":"04640",
    "sg:province":"Almer\u00eda",
    "wof:name":"Jose Cervantes Caparros S.l.",
    "wof:placetype":"venue"
},
  "geometry": {"coordinates":[-1.7441509962,37.4136390686],"type":"Point"}
}