{
  "type": "Feature",
  "properties": {
    "addr:full":"Avda Constitucion, 68 Jaraiz Vera C\u00e1ceres 10400",
    "addr:housenumber":"68",
    "addr:postcode":"10400",
    "addr:street":"Avda Constitucion",
    "iso:country":"ES",
    "sg:address":"Avda Constitucion, 68",
    "sg:city":"Jaraiz Vera",
    "sg:orig_category":"Bancos",
    "sg:phone":"+34 927 17 02 83",
    "sg:postcode":"10400",
    "sg:province":"C\u00e1ceres",
    "wof:name":"Banco Caixa Geral S.a.",
    "wof:placetype":"venue"
},
  "geometry": {"coordinates":[-5.7516927719,40.0606231689],"type":"Point"}
}