{
  "type": "Feature",
  "properties": {
    "addr:full":"Calle de Simancas, 4 Ciudad Real Ciudad Real 13001",
    "addr:housenumber":"4",
    "addr:postcode":"13001",
    "addr:street":"Calle De Simancas",
    "iso:country":"ES",
    "sg:address":"Calle de Simancas, 4",
    "sg:city":"Ciudad Real",
    "sg:orig_category":"Electrodom\u00c9sticos (al Por Menor)",
    "sg:phone":"+34 926 22 19 66",
    "sg:postcode":"13001",
    "sg:province":"Ciudad Real",
    "wof:name":"Satelci S.l.",
    "wof:placetype":"venue"
},
  "geometry": {"coordinates":[-3.9304590225,38.9809036255],"type":"Point"}
}