{
  "type": "Feature",
  "properties": {
    "iso:country":"ES",
    "sg:address":"Calle de Serranitos, 39",
    "sg:city":"Monterrubio De Armu\u00e7a",
    "sg:orig_category":"Encuadernaci\u00d3n E Impresi\u00d3n De Folletos",
    "sg:phone":"+34 923 28 84 68",
    "sg:postcode":"37184",
    "sg:province":"Salamanca",
    "wof:name":"Fernandez Gonzalez Maria Bego\u00f1a",
    "wof:placetype":"venue"
},
  "geometry": {"coordinates":[-5.6469841003,41.0071716309],"type":"Point"}
}