{
  "type": "Feature",
  "properties": {
    "iso:country":"ES",
    "sg:address":"Calle de Pintor Sorolla, 24",
    "sg:city":"Calpe",
    "sg:orig_category":"Cr\u00cda De Animales",
    "sg:phone":"+34 965 83 37 20",
    "sg:postcode":"03710",
    "sg:province":"Alicante",
    "wof:name":"Villanueva Arcos Luis",
    "wof:placetype":"venue"
},
  "geometry": {"coordinates":[0.0529600009,38.6438407898],"type":"Point"}
}