{
  "type": "Feature",
  "properties": {
    "addr:full":"Rond Levante, 17 Vista Alegre Murcia 30008",
    "addr:housenumber":"17",
    "addr:postcode":"30008",
    "addr:street":"Rond Levante",
    "iso:country":"ES",
    "sg:address":"Rond Levante, 17",
    "sg:city":"Vista Alegre",
    "sg:orig_category":"Cajas De Ahorro",
    "sg:phone":"+34 968 20 42 42",
    "sg:postcode":"30008",
    "sg:province":"Murcia",
    "wof:name":"Caixa D'estalvis De Catalunya",
    "wof:placetype":"venue"
},
  "geometry": {"coordinates":[-1.127292037,37.9918136597],"type":"Point"}
}