{
  "type": "Feature",
  "properties": {
    "addr:full":"Carr Montgri, 56 Torroella Montgri Girona 17257",
    "addr:housenumber":"56",
    "addr:postcode":"17257",
    "addr:street":"Carr Montgri",
    "iso:country":"ES",
    "sg:address":"Carr Montgri, 56",
    "sg:city":"Torroella Montgri",
    "sg:classifiers":[
        {
            "category":"Taxi",
            "type":"Transportation"
        }
    ],
    "sg:phone":"+34 972 75 81 43",
    "sg:postcode":"17257",
    "sg:province":"Girona",
    "wof:name":"Casademont Massot Juan",
    "wof:placetype":"venue"
},
  "geometry": {"coordinates":[3.1277420521,42.042766571],"type":"Point"}
}