{
  "type": "Feature",
  "properties": {
    "iso:country":"ES",
    "sg:address":"Calle de Benadalid, 29",
    "sg:city":"Malaga",
    "sg:orig_category":"Fabricaci\u00d3n De Pernos, Tornillos Y Clavos",
    "sg:phone":"+34 952 35 00 45",
    "sg:postcode":"29006",
    "sg:province":"M\u00e1laga",
    "wof:name":"Leon Calderon Jose",
    "wof:placetype":"venue"
},
  "geometry": {"coordinates":[-4.4678931236,36.7011833191],"type":"Point"}
}