{
  "type": "Feature",
  "properties": {
    "iso:country":"ES",
    "sg:address":"Pol Ind San Pedro Alcantara, S/n",
    "sg:city":"San Pedro Alcantara",
    "sg:orig_category":"Veh\u00cdculos De Ocasi\u00d3n",
    "sg:phone":"+34 952 79 91 22",
    "sg:postcode":"29670",
    "sg:province":"M\u00e1laga",
    "wof:name":"Marbecar S.a.",
    "wof:placetype":"venue"
},
  "geometry": {"coordinates":[-4.9902391434,36.4866333008],"type":"Point"}
}