{
  "type": "Feature",
  "properties": {
    "iso:country":"ES",
    "sg:address":"Carrer de Pla\u00c7a, 35",
    "sg:city":"Premia Mar",
    "sg:orig_category":"Internados & Ense\u00d1anza Privada",
    "sg:phone":"+34 937 52 41 71",
    "sg:postcode":"08330",
    "sg:province":"Barcelona",
    "wof:name":"Escola D Asis",
    "wof:placetype":"venue"
},
  "geometry": {"coordinates":[2.356128931,41.4908103943],"type":"Point"}
}