{
  "type": "Feature",
  "properties": {
    "iso:country":"ES",
    "sg:address":"Calle de Cura Barqueros, 1",
    "sg:city":"Puebla De Soto",
    "sg:orig_category":"Fabricaci\u00d3n De Productos Textiles Sin Tejer",
    "sg:phone":"+34 968 80 24 65",
    "sg:postcode":"30836",
    "sg:province":"Murcia",
    "wof:name":"Jimenez Lopez Pedro",
    "wof:placetype":"venue"
},
  "geometry": {"coordinates":[-1.1965776682,37.9762039185],"type":"Point"}
}