{
  "type": "Feature",
  "properties": {
    "addr:full":"Calle de Jose Gorostizaga Lopez, 4 Alhama Murcia Murcia 30840",
    "addr:housenumber":"4",
    "addr:postcode":"30840",
    "addr:street":"Calle De Jose Gorostizaga Lopez",
    "iso:country":"ES",
    "sg:address":"Calle de Jose Gorostizaga Lopez, 4",
    "sg:city":"Alhama Murcia",
    "sg:orig_category":"Reposter\u00cdas",
    "sg:phone":"+34 968 63 18 52",
    "sg:postcode":"30840",
    "sg:province":"Murcia",
    "wof:name":"Ba\u00f1o Martinez Ana Maria",
    "wof:placetype":"venue"
},
  "geometry": {"coordinates":[-1.4283659458,37.8533287048],"type":"Point"}
}