{
  "type": "Feature",
  "properties": {
    "iso:country":"ES",
    "sg:address":"Calle de Alonso De Ojeda, 15",
    "sg:city":"Salamanca",
    "sg:orig_category":"Ense\u00d1anza Superior Privada",
    "sg:phone":"+34 923 25 78 62",
    "sg:postcode":"37005",
    "sg:province":"Salamanca",
    "wof:name":"Colegio Mayor El Salvador-fundacion",
    "wof:placetype":"venue"
},
  "geometry": {"coordinates":[-5.6583271027,40.9734306335],"type":"Point"}
}