{
  "type": "Feature",
  "properties": {
    "addr:full":"Belladonna, 2 Velez-rubio Almer\u00eda 04820",
    "addr:housenumber":"2",
    "addr:postcode":"04820",
    "addr:street":"Belladonna;Almeri\u0301A",
    "iso:country":"ES",
    "sg:address":"Belladonna, 2",
    "sg:city":"Velez-rubio",
    "sg:orig_category":"Promotores Constructores",
    "sg:phone":"+34 950 41 14 03",
    "sg:postcode":"04820",
    "sg:province":"Almer\u00eda",
    "wof:name":"Urbanizadora Valle De Mahimon S.l.",
    "wof:placetype":"venue"
},
  "geometry": {"coordinates":[-2.074794054,37.6459579468],"type":"Point"}
}