{
  "type": "Feature",
  "properties": {
    "iso:country":"ES",
    "sg:address":"Av Cardenal Vidal I Barraquer, 2",
    "sg:city":"Tarragona",
    "sg:orig_category":"Peluquer\u00cdas, Peluquer\u00cda Mixta",
    "sg:phone":"+34 977 22 42 24",
    "sg:postcode":"43005",
    "sg:province":"Tarragona",
    "wof:name":"Marquez Martinez Mercedes",
    "wof:placetype":"venue"
},
  "geometry": {"coordinates":[1.240721941,41.1206626892],"type":"Point"}
}