{
  "type": "Feature",
  "properties": {
    "addr:full":"Carrer de Didac Priu, 50 S. Boi Llobregat Barcelona 08830",
    "addr:housenumber":"50",
    "addr:postcode":"08830",
    "addr:street":"Carrer De Didac Priu",
    "iso:country":"ES",
    "sg:address":"Carrer de Didac Priu, 50",
    "sg:city":"S. Boi Llobregat",
    "sg:orig_category":"Mercer\u00cda, Lencer\u00cda (al Por Menor)",
    "sg:phone":"+34 936 52 11 61",
    "sg:postcode":"08830",
    "sg:province":"Barcelona",
    "wof:name":"Mesa Garcia Natalia",
    "wof:placetype":"venue"
},
  "geometry": {"coordinates":[2.0430529118,41.3384132385],"type":"Point"}
}