{
  "type": "Feature",
  "properties": {
    "iso:country":"ES",
    "sg:address":"Calle de Guadalquivir, 8",
    "sg:city":"Lora Rio",
    "sg:orig_category":"Inmobiliaria (agencias)",
    "sg:phone":"+34 954 80 40 92",
    "sg:postcode":"41440",
    "sg:province":"Sevilla",
    "wof:name":"Hermanos Caro Cepera S.l.",
    "wof:placetype":"venue"
},
  "geometry": {"coordinates":[-5.524058342,37.659236908],"type":"Point"}
}