{
  "type": "Feature",
  "properties": {
    "addr:full":"Calle de Margarita Pardo De Cela, 25 Viveiro Lugo 27850",
    "addr:housenumber":"25",
    "addr:postcode":"27850",
    "addr:street":"Calle De Margarita Pardo De Cela",
    "iso:country":"ES",
    "sg:address":"Calle de Margarita Pardo De Cela, 25",
    "sg:city":"Viveiro",
    "sg:orig_category":"Esmaltado De Metales",
    "sg:phone":"+34 982 55 03 40",
    "sg:postcode":"27850",
    "sg:province":"Lugo",
    "wof:name":"Parafarmacia Arnica C.b.",
    "wof:placetype":"venue"
},
  "geometry": {"coordinates":[-7.595179081,43.6631202698],"type":"Point"}
}