{
  "type": "Feature",
  "properties": {
    "addr:full":"Calle de Granada, 4 Benahadux Almer\u00eda 04410",
    "addr:housenumber":"4",
    "addr:postcode":"04410",
    "addr:street":"Calle De Granada",
    "iso:country":"ES",
    "sg:address":"Calle de Granada, 4",
    "sg:city":"Benahadux",
    "sg:orig_category":"Lecher\u00cdas",
    "sg:phone":"+34 950 31 12 82",
    "sg:postcode":"04410",
    "sg:province":"Almer\u00eda",
    "wof:name":"Puleva Food S.l.",
    "wof:placetype":"venue"
},
  "geometry": {"coordinates":[-2.4586799145,36.9279403687],"type":"Point"}
}