{
  "type": "Feature",
  "properties": {
    "iso:country":"ES",
    "sg:address":"Calle de General Campomanes, 15",
    "sg:city":"Villaviciosa",
    "sg:orig_category":"Peluquer\u00cdas, Peluquer\u00cda Mixta",
    "sg:phone":"+34 985 89 14 60",
    "sg:postcode":"33300",
    "sg:province":"Asturias",
    "wof:name":"Rozas Martinez Maria Carmen",
    "wof:placetype":"venue"
},
  "geometry": {"coordinates":[-5.4339990616,43.4796562195],"type":"Point"}
}