{
  "type": "Feature",
  "properties": {
    "iso:country":"ES",
    "sg:address":"Calle de Pan Y Toros, 9",
    "sg:city":"Madrid",
    "sg:orig_category":"Estancos",
    "sg:phone":"+34 913 17 24 49",
    "sg:postcode":"28041",
    "sg:province":"Madrid",
    "wof:name":"Nu\u00f1ez Lopez Bermejo Juan",
    "wof:placetype":"venue"
},
  "geometry": {"coordinates":[-3.6947078705,40.3601799011],"type":"Point"}
}