{
  "type": "Feature",
  "properties": {
    "iso:country":"ES",
    "sg:address":"Calle de Charco, 4",
    "sg:city":"Palacios Y Villafranca",
    "sg:orig_category":"Perfumer\u00cda, Art\u00cdculos De Ba\u00d1o (fabricaci\u00d3n, Al Por Mayor)",
    "sg:phone":"+34 955 81 54 43",
    "sg:postcode":"41720",
    "sg:province":"Sevilla",
    "wof:name":"Curado Villazan Adela",
    "wof:placetype":"venue"
},
  "geometry": {"coordinates":[-5.9269361496,37.1594810486],"type":"Point"}
}