{
  "type": "Feature",
  "properties": {
    "addr:full":"Calle de La Paloma, 5 Vitoria-gasteiz \u00c1lava 01002",
    "addr:housenumber":"5",
    "addr:postcode":"01002",
    "addr:street":"Calle De La Paloma",
    "iso:country":"ES",
    "sg:address":"Calle de La Paloma, 5",
    "sg:city":"Vitoria-gasteiz",
    "sg:orig_category":"Herboristas (al Por Menor)",
    "sg:phone":"+34 945 26 75 11",
    "sg:postcode":"01002",
    "sg:province":"\u00c1lava",
    "wof:name":"Biosalud S.l.",
    "wof:placetype":"venue"
},
  "geometry": {"coordinates":[-2.6664869785,42.8494338989],"type":"Point"}
}