{
  "type": "Feature",
  "properties": {
    "addr:full":"Carr Nadal Meroles, 12 Lleida Lleida 25008",
    "addr:housenumber":"12",
    "addr:postcode":"25008",
    "addr:street":"Carr Nadal Meroles",
    "iso:country":"ES",
    "sg:address":"Carr Nadal Meroles, 12",
    "sg:city":"Lleida",
    "sg:orig_category":"Material Y Suministros Para Fotocopiadoras, Reprograf\u00cda",
    "sg:phone":"+34 973 23 09 18",
    "sg:postcode":"25008",
    "sg:province":"Lleida",
    "wof:name":"Ilerdense De Copiadores S.l.",
    "wof:placetype":"venue"
},
  "geometry": {"coordinates":[0.6203410029,41.6224365234],"type":"Point"}
}