{
  "type": "Feature",
  "properties": {
    "iso:country":"ES",
    "sg:address":"Carrer de Atlantida (l'), 31",
    "sg:city":"Palleja",
    "sg:orig_category":"Electricidad: Instaladores",
    "sg:phone":"+34 936 63 20 85",
    "sg:postcode":"08780",
    "sg:province":"Barcelona",
    "wof:name":"Instalaciones Alonso Guerrero S.l.",
    "wof:placetype":"venue"
},
  "geometry": {"coordinates":[1.9986979961,41.4182929993],"type":"Point"}
}