{
  "type": "Feature",
  "properties": {
    "addr:full":"Plaz Virgen De Lepanto, 17 Castellar-oliveral Valencia 46026",
    "addr:housenumber":"17",
    "addr:postcode":"46026",
    "addr:street":"Plaz Virgen De Lepanto",
    "iso:country":"ES",
    "sg:address":"Plaz Virgen De Lepanto, 17",
    "sg:city":"Castellar-oliveral",
    "sg:orig_category":"Iglesia Cat\u00d3lica",
    "sg:phone":"+34 963 96 20 18",
    "sg:postcode":"46026",
    "sg:province":"Valencia",
    "wof:name":"Parroquia De Nuestra Se\u00f1ora De Lepanto",
    "wof:placetype":"venue"
},
  "geometry": {"coordinates":[-0.3631820083,39.4300231934],"type":"Point"}
}