{
  "type": "Feature",
  "properties": {
    "iso:country":"ES",
    "sg:address":"Calle de Manuel Pereira, 8",
    "sg:city":"Ourense",
    "sg:orig_category":"Detectives, Agentes Investigadores Privados",
    "sg:phone":"+34 988 23 15 05",
    "sg:postcode":"32003",
    "sg:province":"Ourense",
    "wof:name":"Doval Esperanza Carlos",
    "wof:placetype":"venue"
},
  "geometry": {"coordinates":[-7.8661170006,42.3389396667],"type":"Point"}
}