{
  "type": "Feature",
  "properties": {
    "addr:full":"Calle de Doctor Mara\u00d1on, 13 Petrer Alicante 03610",
    "addr:housenumber":"13",
    "addr:postcode":"03610",
    "addr:street":"Calle De Doctor Maran\u0303On",
    "iso:country":"ES",
    "sg:address":"Calle de Doctor Mara\u00d1on, 13",
    "sg:city":"Petrer",
    "sg:orig_category":"Cueros Y Pieles (al Por Mayor)",
    "sg:phone":"+34 965 37 75 60",
    "sg:postcode":"03610",
    "sg:province":"Alicante",
    "wof:name":"Sanz Pieles S.l.",
    "wof:placetype":"venue"
},
  "geometry": {"coordinates":[-0.7739089727,38.4808197021],"type":"Point"}
}