{
  "type": "Feature",
  "properties": {
    "addr:full":"Carr Palau, 13 Mollerussa Lleida 25230",
    "addr:housenumber":"13",
    "addr:postcode":"25230",
    "addr:street":"Carr Palau",
    "iso:country":"ES",
    "sg:address":"Carr Palau, 13",
    "sg:city":"Mollerussa",
    "sg:orig_category":"Electricidad: Instaladores",
    "sg:phone":"+34 973 60 34 42",
    "sg:postcode":"25230",
    "sg:province":"Lleida",
    "wof:name":"Gorgues Majoral Sociedad De Responsabilidades Limitada",
    "wof:placetype":"venue"
},
  "geometry": {"coordinates":[0.8936949968,41.6300392151],"type":"Point"}
}