{
  "type": "Feature",
  "properties": {
    "iso:country":"ES",
    "sg:address":"Calle de Valle, 18",
    "sg:city":"Sevilla",
    "sg:orig_category":"Promotores Constructores",
    "sg:phone":"+34 954 41 07 57",
    "sg:postcode":"41003",
    "sg:province":"Sevilla",
    "wof:name":"Hermanos Vides S. L.",
    "wof:placetype":"venue"
},
  "geometry": {"coordinates":[-5.9841389656,37.3944282532],"type":"Point"}
}