{
  "type": "Feature",
  "properties": {
    "iso:country":"ES",
    "sg:address":"Carr Bellavista, 10",
    "sg:city":"Girona",
    "sg:orig_category":"Explotaci\u00d3n De Canteras",
    "sg:phone":"+34 972 20 60 98",
    "sg:postcode":"17004",
    "sg:province":"Girona",
    "wof:name":"Tallers Anglada S.coop.c.l.",
    "wof:placetype":"venue"
},
  "geometry": {"coordinates":[2.8422400951,41.9735031128],"type":"Point"}
}