{
  "type": "Feature",
  "properties": {
    "iso:country":"ES",
    "sg:address":"Calle de Cura (del), 70",
    "sg:city":"Casar Caceres",
    "sg:orig_category":"Promotores Constructores",
    "sg:phone":"+34 927 29 19 71",
    "sg:postcode":"10190",
    "sg:province":"C\u00e1ceres",
    "wof:name":"Corchado Cantero Juan Jose",
    "wof:placetype":"venue"
},
  "geometry": {"coordinates":[-6.416490078,39.5581245422],"type":"Point"}
}