{
  "type": "Feature",
  "properties": {
    "iso:country":"ES",
    "sg:address":"Calle de Marques De Mondejar, 11",
    "sg:city":"Granada",
    "sg:orig_category":"Carnicer\u00cdas, Carnicer\u00cdas",
    "sg:phone":"+34 958 26 04 48",
    "sg:postcode":"18005",
    "sg:province":"Granada",
    "wof:name":"Garcia Sanchez Francisco Javier",
    "wof:placetype":"venue"
},
  "geometry": {"coordinates":[-3.6016581059,37.1682090759],"type":"Point"}
}