{
  "type": "Feature",
  "properties": {
    "iso:country":"ES",
    "sg:address":"Del Pe\u00f1on, 10",
    "sg:city":"Puente Arzobispo",
    "sg:orig_category":"Fabrica De Cer\u00c1micas",
    "sg:phone":"+34 925 43 62 87",
    "sg:postcode":"45570",
    "sg:province":"Toledo",
    "wof:name":"Casas C.b Fabrica De Ceramica",
    "wof:placetype":"venue"
},
  "geometry": {"coordinates":[-5.1731991768,39.8003387451],"type":"Point"}
}