{
  "type": "Feature",
  "properties": {
    "addr:full":"Calle de O'donnell, General, 37 Melilla Melilla 52001",
    "addr:housenumber":"37",
    "addr:postcode":"52001",
    "addr:street":"Calle De O'Donnell General",
    "iso:country":"ES",
    "sg:address":"Calle de O'donnell, General, 37",
    "sg:city":"Melilla",
    "sg:orig_category":"Colchones (fabricaci\u00d3n, Al Por Mayor, Al Por Menor)",
    "sg:phone":"+34 952 68 35 18",
    "sg:postcode":"52001",
    "sg:province":"Melilla",
    "wof:name":"Rengel Palomo Antonio",
    "wof:placetype":"venue"
},
  "geometry": {"coordinates":[-2.9434149265,35.2970504761],"type":"Point"}
}