{
  "type": "Feature",
  "properties": {
    "iso:country":"ES",
    "sg:address":"Carr Patricio Redondo, S/n",
    "sg:city":"Puigverd Lleida",
    "sg:orig_category":"Cerrajer\u00cda, Ferrallista",
    "sg:phone":"+34 973 16 73 03",
    "sg:postcode":"25153",
    "sg:province":"Lleida",
    "wof:name":"Garcia Lopez Jose Antonio",
    "wof:placetype":"venue"
},
  "geometry": {"coordinates":[0.7358800173,41.5425415039],"type":"Point"}
}