{
  "type": "Feature",
  "properties": {
    "iso:country":"ES",
    "sg:address":"Pje Finca Las Cabezuelas, S/n",
    "sg:city":"Ayamonte",
    "sg:orig_category":"Promotores Constructores",
    "sg:phone":"+34 959 32 40 02",
    "sg:postcode":"21400",
    "sg:province":"Huelva",
    "sg:website":"www.fadesa.es",
    "wof:name":"Fadesa Inmobiliaria S.a.",
    "wof:placetype":"venue"
},
  "geometry": {"coordinates":[-7.4089279175,37.2172279358],"type":"Point"}
}