{
  "type": "Feature",
  "properties": {
    "iso:country":"ES",
    "sg:address":"Calle de Seis De Junio, 15",
    "sg:city":"Valdepe\u00f1as",
    "sg:orig_category":"Arquitectos",
    "sg:phone":"+34 926 32 17 88",
    "sg:postcode":"13300",
    "sg:province":"Ciudad Real",
    "wof:name":"Moliterni Moya Ivan",
    "wof:placetype":"venue"
},
  "geometry": {"coordinates":[-3.3891029358,38.7545166016],"type":"Point"}
}