{
  "type": "Feature",
  "properties": {
    "addr:full":"Calle de Mayor, 67 Pozoblanco C\u00f3rdoba 14400",
    "addr:housenumber":"67",
    "addr:postcode":"14400",
    "addr:street":"Calle De Mayor",
    "iso:country":"ES",
    "sg:address":"Calle de Mayor, 67",
    "sg:city":"Pozoblanco",
    "sg:orig_category":"Florister\u00cdas",
    "sg:phone":"+34 957 77 32 54",
    "sg:postcode":"14400",
    "sg:province":"C\u00f3rdoba",
    "wof:name":"Garcia Garcia Julia",
    "wof:placetype":"venue"
},
  "geometry": {"coordinates":[-4.8497581482,38.3806762695],"type":"Point"}
}