{
  "type": "Feature",
  "properties": {
    "iso:country":"ES",
    "sg:address":"Carrer de Alaba, 22",
    "sg:city":"Barcelona",
    "sg:orig_category":"Cine: Pel\u00cdculas Educativas, Industriales Y Publicitarias (producci\u00d3n)",
    "sg:phone":"+34 932 24 03 58",
    "sg:postcode":"08005",
    "sg:province":"Barcelona",
    "sg:website":"www.europeanproductions.com",
    "wof:name":"Adriana European Productions S. L.",
    "wof:placetype":"venue"
},
  "geometry": {"coordinates":[2.1975347996,41.393787384],"type":"Point"}
}