{
  "type": "Feature",
  "properties": {
    "iso:country":"ES",
    "sg:address":"Soterra\u00f1a, S/n",
    "sg:city":"Sta M. Real Nieva",
    "sg:orig_category":"Distribuci\u00d3n De Petr\u00d3leo Y Derivados",
    "sg:phone":"+34 921 59 50 15",
    "sg:postcode":"40440",
    "sg:province":"Segovia",
    "wof:name":"Combustibles Carbonero S.l.",
    "wof:placetype":"venue"
},
  "geometry": {"coordinates":[-4.4044442177,41.0687294006],"type":"Point"}
}