{
  "type": "Feature",
  "properties": {
    "iso:country":"ES",
    "sg:address":"Rua Real, 67",
    "sg:city":"Ferrol",
    "sg:orig_category":"Electrodom\u00c9sticos (al Por Menor)",
    "sg:phone":"+34 981 35 01 04",
    "sg:postcode":"15402",
    "sg:province":"La Coru\u00f1a",
    "wof:name":"Mui\u00f1os Pena Juan Antonio Jose",
    "wof:placetype":"venue"
},
  "geometry": {"coordinates":[-8.2315626144,43.4843902588],"type":"Point"}
}