{
  "type": "Feature",
  "properties": {
    "addr:full":"Pase San Francisco De Sales, 4 Madrid Madrid 28003",
    "addr:housenumber":"4",
    "addr:postcode":"28003",
    "addr:street":"Francisco De Sales",
    "iso:country":"ES",
    "sg:address":"Pase San Francisco De Sales, 4",
    "sg:city":"Madrid",
    "sg:orig_category":"Peluquer\u00cdas, Peluquer\u00cda Mixta",
    "sg:phone":"+34 915 43 03 10",
    "sg:postcode":"28003",
    "sg:province":"Madrid",
    "sg:website":"www.llongueras.com",
    "wof:name":"Isuc S.a.",
    "wof:placetype":"venue"
},
  "geometry": {"coordinates":[-3.7167110443,40.4396476746],"type":"Point"}
}