{
  "type": "Feature",
  "properties": {
    "iso:country":"ES",
    "sg:address":"Luga Pandenes, S/n",
    "sg:city":"Pandenes",
    "sg:orig_category":"Ebanister\u00cda",
    "sg:phone":"+34 985 97 63 69",
    "sg:postcode":"33539",
    "sg:province":"Asturias",
    "wof:name":"Fernandez Perez Jaime",
    "wof:placetype":"venue"
},
  "geometry": {"coordinates":[-5.4095377922,43.3347473145],"type":"Point"}
}