{
  "type": "Feature",
  "properties": {
    "addr:full":"Calle de Azahar, 19 Cantillana Sevilla 41320",
    "addr:housenumber":"19",
    "addr:postcode":"41320",
    "addr:street":"Calle De Azahar",
    "iso:country":"ES",
    "sg:address":"Calle de Azahar, 19",
    "sg:city":"Cantillana",
    "sg:orig_category":"Empresas De Carpinter\u00cda Met\u00c1lica",
    "sg:phone":"+34 955 73 04 78",
    "sg:postcode":"41320",
    "sg:province":"Sevilla",
    "wof:name":"Gonzalez Rios Manuel",
    "wof:placetype":"venue"
},
  "geometry": {"coordinates":[-5.8198385239,37.6135406494],"type":"Point"}
}