{
  "type": "Feature",
  "properties": {
    "addr:full":"Calle de Poligono (del), 5 Becerril Sierra Madrid 28490",
    "addr:housenumber":"5",
    "addr:postcode":"28490",
    "addr:street":"Calle De Poligono Del",
    "iso:country":"ES",
    "sg:address":"Calle de Poligono (del), 5",
    "sg:city":"Becerril Sierra",
    "sg:orig_category":"Grabados Y Decoraci\u00d3n De Metales",
    "sg:phone":"+34 918 55 50 26",
    "sg:postcode":"28490",
    "sg:province":"Madrid",
    "wof:name":"Estevan Collado Alejandro",
    "wof:placetype":"venue"
},
  "geometry": {"coordinates":[-3.993019104,40.7075462341],"type":"Point"}
}