{
  "type": "Feature",
  "properties": {
    "addr:full":"Carrer de Conca De Tremp, 20 Barcelona Barcelona 08032",
    "addr:housenumber":"20",
    "addr:postcode":"08032",
    "addr:street":"Carrer De Conca De Tremp",
    "iso:country":"ES",
    "sg:address":"Carrer de Conca De Tremp, 20",
    "sg:city":"Barcelona",
    "sg:orig_category":"Herboristas (al Por Menor)",
    "sg:phone":"+34 934 29 25 47",
    "sg:postcode":"08032",
    "sg:province":"Barcelona",
    "wof:name":"Angulo Escudero Maria Luisa",
    "wof:placetype":"venue"
},
  "geometry": {"coordinates":[2.1555840969,41.4233779907],"type":"Point"}
}