{
  "type": "Feature",
  "properties": {
    "iso:country":"ES",
    "sg:address":"Calle de Sancho Perez, 5",
    "sg:city":"Merida",
    "sg:orig_category":"M\u00c9dicos: Cirug\u00cda Pl\u00c1stica, Reconstructiva Y Est\u00c9tica",
    "sg:phone":"+34 924 31 41 51",
    "sg:postcode":"06800",
    "sg:province":"Badajoz",
    "wof:name":"Hurtado Sendin Maria Del Mar",
    "wof:placetype":"venue"
},
  "geometry": {"coordinates":[-6.3528399467,38.9254570007],"type":"Point"}
}