{
  "type": "Feature",
  "properties": {
    "addr:full":"Calle de Daoiz, 20 Bormujos Sevilla 41930",
    "addr:housenumber":"20",
    "addr:postcode":"41930",
    "addr:street":"Calle De Daoiz",
    "iso:country":"ES",
    "sg:address":"Calle de Daoiz, 20",
    "sg:city":"Bormujos",
    "sg:orig_category":"Asociaciones Y Clubs Deportivos",
    "sg:phone":"+34 955 72 45 40",
    "sg:postcode":"41930",
    "sg:province":"Sevilla",
    "wof:name":"Pe\u00f1a Sevillista",
    "wof:placetype":"venue"
},
  "geometry": {"coordinates":[-6.0717773438,37.3717308044],"type":"Point"}
}