{
  "type": "Feature",
  "properties": {
    "addr:full":"Rond General Mitre, 200 Barcelona Barcelona 08006",
    "addr:housenumber":"200",
    "addr:postcode":"08006",
    "addr:street":"Mitre",
    "iso:country":"ES",
    "sg:address":"Rond General Mitre, 200",
    "sg:city":"Barcelona",
    "sg:orig_category":"Publicidad (soportes Y Gesti\u00d3n)",
    "sg:phone":"+34 934 17 54 85",
    "sg:postcode":"08006",
    "sg:province":"Barcelona",
    "wof:name":"Creatius Compra Venda S.l.",
    "wof:placetype":"venue"
},
  "geometry": {"coordinates":[2.1448280811,41.4054031372],"type":"Point"}
}