{
  "type": "Feature",
  "properties": {
    "iso:country":"ES",
    "sg:address":"Calle de Islas Cies (de Las), 13",
    "sg:city":"Humanes De Madrid",
    "sg:orig_category":"Electrodom\u00c9sticos (fabricaci\u00d3n, Al Por Mayor)",
    "sg:phone":"+34 916 90 76 16",
    "sg:postcode":"28970",
    "sg:province":"Madrid",
    "wof:name":"Cadena De Electrodomesticos De Leganes S.l.",
    "wof:placetype":"venue"
},
  "geometry": {"coordinates":[-3.8132379055,40.2734718323],"type":"Point"}
}