{
  "type": "Feature",
  "properties": {
    "iso:country":"ES",
    "sg:address":"Calle de Sancho Arroyo, 2",
    "sg:city":"Zaragoza",
    "sg:orig_category":"Zapatos (al Por Menor)",
    "sg:phone":"+34 976 42 67 97",
    "sg:postcode":"50002",
    "sg:province":"Zaragoza",
    "wof:name":"Calzados Cordon S. Cv.",
    "wof:placetype":"venue"
},
  "geometry": {"coordinates":[-0.8660759926,41.6457748413],"type":"Point"}
}