{
  "type": "Feature",
  "properties": {
    "iso:country":"ES",
    "sg:address":"Calle de Blasco De Garay, 3",
    "sg:city":"Madrid",
    "sg:orig_category":"Ense\u00d1anza: Profesiones Art\u00cdsticas",
    "sg:phone":"+34 915 59 78 19",
    "sg:postcode":"28015",
    "sg:province":"Madrid",
    "wof:name":"Garcia Sanchez Jorge",
    "wof:placetype":"venue"
},
  "geometry": {"coordinates":[-3.7118346691,40.4304962158],"type":"Point"}
}