{
  "type": "Feature",
  "properties": {
    "addr:full":"Calle de Santa Cruz, 6 Ecija Sevilla 41400",
    "addr:housenumber":"6",
    "addr:postcode":"41400",
    "addr:street":"Calle De Santa Cruz",
    "iso:country":"ES",
    "sg:address":"Calle de Santa Cruz, 6",
    "sg:city":"Ecija",
    "sg:orig_category":"Herboristas (al Por Menor)",
    "sg:phone":"+34 955 90 23 11",
    "sg:postcode":"41400",
    "sg:province":"Sevilla",
    "wof:name":"Meridional De Dietetica S.l.",
    "wof:placetype":"venue"
},
  "geometry": {"coordinates":[-5.0803999901,37.5424041748],"type":"Point"}
}