{
  "type": "Feature",
  "properties": {
    "addr:full":"Calle de Monte De Piedad, S/n Xirivella Valencia 46950",
    "addr:housenumber":"s / n",
    "addr:postcode":"46950",
    "addr:street":"Calle De Monte De Piedad",
    "iso:country":"ES",
    "sg:address":"Calle de Monte De Piedad, S/n",
    "sg:city":"Xirivella",
    "sg:orig_category":"Iglesia Cat\u00d3lica",
    "sg:phone":"+34 963 79 22 39",
    "sg:postcode":"46950",
    "sg:province":"Valencia",
    "wof:name":"Parroquia San Ramon Y San Vicente",
    "wof:placetype":"venue"
},
  "geometry": {"coordinates":[-0.4330689907,39.4641799927],"type":"Point"}
}