{
  "type": "Feature",
  "properties": {
    "iso:country":"ES",
    "sg:address":"Avda Don Antonio Huertas, 45",
    "sg:city":"Tomelloso",
    "sg:orig_category":"Asesor\u00cda Fiscal Y Jur\u00cddica",
    "sg:phone":"+34 926 50 10 20",
    "sg:postcode":"13700",
    "sg:province":"Ciudad Real",
    "wof:name":"Agefis S.l.",
    "wof:placetype":"venue"
},
  "geometry": {"coordinates":[-3.0207417011,39.149105072],"type":"Point"}
}