{
  "type": "Feature",
  "properties": {
    "addr:full":"Av. Madrid, 9 Sedavi Valencia 46910",
    "addr:housenumber":"9",
    "addr:postcode":"46910",
    "addr:street":"Av. Madrid",
    "iso:country":"ES",
    "sg:address":"Av. Madrid, 9",
    "sg:city":"Sedavi",
    "sg:orig_category":"Estudios, Instalaci\u00d3n De Climatizaci\u00d3n",
    "sg:phone":"+34 963 75 51 76",
    "sg:postcode":"46910",
    "sg:province":"Valencia",
    "wof:name":"Ferreteria Hogar Rachadell S.l.",
    "wof:placetype":"venue"
},
  "geometry": {"coordinates":[-0.3826059997,39.4261894226],"type":"Point"}
}