{
  "type": "Feature",
  "properties": {
    "addr:full":"Calle de Eras, 2 Palazuelo De Vedija Valladolid 47812",
    "addr:housenumber":"2",
    "addr:postcode":"47812",
    "addr:street":"Calle De Eras",
    "iso:country":"ES",
    "sg:address":"Calle de Eras, 2",
    "sg:city":"Palazuelo De Vedija",
    "sg:orig_category":"Centros De Educaci\u00d3n Especial",
    "sg:phone":"+34 983 70 13 33",
    "sg:postcode":"47812",
    "sg:province":"Valladolid",
    "wof:name":"Colegio Publico Rural Agrupado De Medina De Rioseco",
    "wof:placetype":"venue"
},
  "geometry": {"coordinates":[-5.1444687843,41.9281005859],"type":"Point"}
}