{
  "type": "Feature",
  "properties": {
    "addr:full":"Carrer de Horts, 20 Palma Islas Baleares 07003",
    "addr:housenumber":"20",
    "addr:postcode":"07003",
    "addr:street":"Carrer De Horts",
    "iso:country":"ES",
    "sg:address":"Carrer de Horts, 20",
    "sg:city":"Palma",
    "sg:orig_category":"Librer\u00cdas",
    "sg:phone":"+34 971 71 38 98",
    "sg:postcode":"07003",
    "sg:province":"Islas Baleares",
    "wof:name":"Book-inn S.l.",
    "wof:placetype":"venue"
},
  "geometry": {"coordinates":[2.6499199867,39.573841095],"type":"Point"}
}