{
  "type": "Feature",
  "properties": {
    "iso:country":"ES",
    "sg:address":"Calle de Alferez Cabrera Tavio, 11",
    "sg:city":"Arrecife",
    "sg:orig_category":"Estilistas Y Estudios De Estilo De Corte Y Confecci\u00d3n",
    "sg:phone":"+34 928 84 48 91",
    "sg:postcode":"35500",
    "sg:province":"Las Palmas",
    "wof:name":"Novedades Medina S.l.",
    "wof:placetype":"venue"
},
  "geometry": {"coordinates":[-13.5497264862,28.959438324],"type":"Point"}
}