{
  "type": "Feature",
  "properties": {
    "addr:full":"Calle de Elvira, 5 Granada Granada 18010",
    "addr:housenumber":"5",
    "addr:postcode":"18010",
    "addr:street":"Calle De Elvira",
    "iso:country":"ES",
    "sg:address":"Calle de Elvira, 5",
    "sg:city":"Granada",
    "sg:orig_category":"Artesan\u00cda",
    "sg:phone":"+34 958 22 64 26",
    "sg:postcode":"18010",
    "sg:province":"Granada",
    "wof:name":"Acien Reyes Ana Maria",
    "wof:placetype":"venue"
},
  "geometry": {"coordinates":[-3.5975039005,37.1773071289],"type":"Point"}
}