{
  "type": "Feature",
  "properties": {
    "addr:full":"Calle de Blasco De Garay, 12 Albacete Albacete 02003",
    "addr:housenumber":"12",
    "addr:postcode":"02003",
    "addr:street":"Calle De Blasco De Garay",
    "iso:country":"ES",
    "sg:address":"Calle de Blasco De Garay, 12",
    "sg:city":"Albacete",
    "sg:orig_category":"Contables",
    "sg:phone":"+34 967 22 14 19",
    "sg:postcode":"02003",
    "sg:province":"Albacete",
    "wof:name":"Mu\u00f1oz Medrano Pedro",
    "wof:placetype":"venue"
},
  "geometry": {"coordinates":[-1.8590686321,38.9918136597],"type":"Point"}
}