{
  "type": "Feature",
  "properties": {
    "addr:full":"Av J.m.quadrado, 7 Mao Islas Baleares 07703",
    "addr:housenumber":"7",
    "addr:postcode":"07703",
    "addr:street":"Av J.M.Quadrado",
    "iso:country":"ES",
    "sg:address":"Av J.m.quadrado, 7",
    "sg:city":"Mao",
    "sg:orig_category":"Art\u00cdculos De Regalo (al Por Menor)",
    "sg:phone":"+34 971 36 03 61",
    "sg:postcode":"07703",
    "sg:province":"Islas Baleares",
    "wof:name":"Serba 100 S.l.",
    "wof:placetype":"venue"
},
  "geometry": {"coordinates":[4.2583870888,39.8881874084],"type":"Point"}
}