{
  "type": "Feature",
  "properties": {
    "addr:full":"Calle de Concordia, 3 Jacarilla Alicante 03310",
    "addr:housenumber":"3",
    "addr:postcode":"03310",
    "addr:street":"Calle De Concordia",
    "iso:country":"ES",
    "sg:address":"Calle de Concordia, 3",
    "sg:city":"Jacarilla",
    "sg:orig_category":"Cepiller\u00cdas",
    "sg:phone":"+34 966 77 06 93",
    "sg:postcode":"03310",
    "sg:province":"Alicante",
    "wof:name":"Cevepas S.l.",
    "wof:placetype":"venue"
},
  "geometry": {"coordinates":[-0.867625773,38.0611228943],"type":"Point"}
}