{
  "type": "Feature",
  "properties": {
    "iso:country":"ES",
    "sg:address":"Cuns, S/n",
    "sg:city":"Ponte Nafonso",
    "sg:orig_category":"Empresarios",
    "sg:phone":"+34 981 76 96 99",
    "sg:postcode":"15286",
    "sg:province":"A Coru\u00f1a",
    "wof:name":"Taller Da Pedra Represa S.l",
    "wof:placetype":"venue"
},
  "geometry": {"coordinates":[-8.8856506348,42.8085136414],"type":"Point"}
}