{
  "type": "Feature",
  "properties": {
    "addr:full":"Travesia Del Rio, 3 Velez-malaga M\u00e1laga 29700",
    "addr:housenumber":"3",
    "addr:postcode":"29700",
    "addr:street":"Travesia Del Rio",
    "iso:country":"ES",
    "sg:address":"Travesia Del Rio, 3",
    "sg:city":"Velez-malaga",
    "sg:orig_category":"Periodistas Profesionales",
    "sg:phone":"+34 952 50 78 21",
    "sg:postcode":"29700",
    "sg:province":"M\u00e1laga",
    "wof:name":"Zapata Navas Antonio Jesus",
    "wof:placetype":"venue"
},
  "geometry": {"coordinates":[-4.1059103012,36.7805290222],"type":"Point"}
}