{
  "type": "Feature",
  "properties": {
    "addr:full":"Calle de Mayor, 8 Villaca\u00f1as Toledo 45860",
    "addr:housenumber":"8",
    "addr:postcode":"45860",
    "addr:street":"Calle De Mayor",
    "iso:country":"ES",
    "sg:address":"Calle de Mayor, 8",
    "sg:city":"Villaca\u00f1as",
    "sg:orig_category":"Loter\u00cda Y T\u00d3mbola",
    "sg:phone":"+34 925 20 08 58",
    "sg:postcode":"45860",
    "sg:province":"Toledo",
    "wof:name":"Zaragoza Sanchez Gonzalo",
    "wof:placetype":"venue"
},
  "geometry": {"coordinates":[-3.3326580524,39.6245079041],"type":"Point"}
}