{
  "type": "Feature",
  "properties": {
    "iso:country":"ES",
    "sg:address":"Calle de Lopez Botas, 8",
    "sg:city":"Palmas De Gran Canaria",
    "sg:orig_category":"Empresarios",
    "sg:phone":"+34 928 33 36 82",
    "sg:postcode":"35001",
    "sg:province":"Las Palmas",
    "wof:name":"Fundacion Canaria San Fernando",
    "wof:placetype":"venue"
},
  "geometry": {"coordinates":[-15.417383194,28.0988197327],"type":"Point"}
}