{
  "type": "Feature",
  "properties": {
    "addr:full":"Calle de Rey Juan Carlos I, 1 Tocina Sevilla 41340",
    "addr:housenumber":"1",
    "addr:postcode":"41340",
    "addr:street":"Calle De Rey Juan Carlos I",
    "iso:country":"ES",
    "sg:address":"Calle de Rey Juan Carlos I, 1",
    "sg:city":"Tocina",
    "sg:orig_category":"Droguer\u00cdas (al Por Menor)",
    "sg:phone":"+34 954 74 01 33",
    "sg:postcode":"41340",
    "sg:province":"Sevilla",
    "wof:name":"Rodriguez Rosales Ines",
    "wof:placetype":"venue"
},
  "geometry": {"coordinates":[-5.7335247993,37.6095542908],"type":"Point"}
}