{
  "type": "Feature",
  "properties": {
    "iso:country":"ES",
    "sg:address":"Carrer de Mossen Cinto Verdaguer, 15",
    "sg:city":"Sentmenat",
    "sg:classifiers":[
        {
            "category":"Personal",
            "subcategory":"Barber",
            "type":"Services"
        }
    ],
    "sg:phone":"+34 937 15 25 61",
    "sg:postcode":"08181",
    "sg:province":"Barcelona",
    "sg:tags":[
        "caballeros",
        "de",
        "peluqueros"
    ],
    "sg:website":"www.laprea.net",
    "wof:name":"Laprea Puertas Raul",
    "wof:placetype":"venue"
},
  "geometry": {"coordinates":[2.1321089268,41.6124954224],"type":"Point"}
}