{
  "type": "Feature",
  "properties": {
    "addr:full":"Calle de Carabela La Pinta, 8 Baiona Pontevedra 36300",
    "addr:housenumber":"8",
    "addr:postcode":"36300",
    "addr:street":"Calle De Carabela La Pinta",
    "iso:country":"ES",
    "sg:address":"Calle de Carabela La Pinta, 8",
    "sg:city":"Baiona",
    "sg:orig_category":"Asociaciones Y Clubs Deportivos",
    "sg:phone":"+34 986 35 65 57",
    "sg:postcode":"36300",
    "sg:province":"Pontevedra",
    "wof:name":"Fernandez Fernandez Maria Esperanza",
    "wof:placetype":"venue"
},
  "geometry": {"coordinates":[-8.8502540588,42.1204032898],"type":"Point"}
}