{
  "type": "Feature",
  "properties": {
    "addr:full":"Carr Catalunya, 39 Vidreres Girona 17411",
    "addr:housenumber":"39",
    "addr:postcode":"17411",
    "addr:street":"Carr Catalunya",
    "iso:country":"ES",
    "sg:address":"Carr Catalunya, 39",
    "sg:city":"Vidreres",
    "sg:orig_category":"Promotores Constructores",
    "sg:phone":"+34 972 87 55 12",
    "sg:postcode":"17411",
    "sg:province":"Girona",
    "wof:name":"Formas Modernes Vidreres S.l.",
    "wof:placetype":"venue"
},
  "geometry": {"coordinates":[2.780684948,41.7898826599],"type":"Point"}
}