{
  "type": "Feature",
  "properties": {
    "addr:full":"Calle de Iba\u00d1ez De Bilbao, 9 Bilbao Vizcaya 48009",
    "addr:housenumber":"9",
    "addr:postcode":"48009",
    "addr:street":"Calle De Iban\u0303Ez De Bilbao",
    "iso:country":"ES",
    "sg:address":"Calle de Iba\u00d1ez De Bilbao, 9",
    "sg:city":"Bilbao",
    "sg:orig_category":"Inversiones",
    "sg:phone":"+34 944 00 03 00",
    "sg:postcode":"48009",
    "sg:province":"Vizcaya",
    "wof:name":"Fineco Sociedad De Valores, S.a.",
    "wof:placetype":"venue"
},
  "geometry": {"coordinates":[-2.9293251038,43.2633018494],"type":"Point"}
}