{
  "type": "Feature",
  "properties": {
    "addr:full":"Calle de Arca, 3 Vitoria-gasteiz \u00c1lava 01005",
    "addr:housenumber":"3",
    "addr:postcode":"01005",
    "addr:street":"Calle De Arca",
    "iso:country":"ES",
    "sg:address":"Calle de Arca, 3",
    "sg:city":"Vitoria-gasteiz",
    "sg:orig_category":"M\u00c9dicos: Estomatolog\u00cda",
    "sg:phone":"+34 945 13 39 23",
    "sg:postcode":"01005",
    "sg:province":"\u00c1lava",
    "wof:name":"Clinica Dental Arca",
    "wof:placetype":"venue"
},
  "geometry": {"coordinates":[-2.6721754074,42.8438415527],"type":"Point"}
}