{
  "type": "Feature",
  "properties": {
    "addr:full":"Calle de Venezuela, 5 Totana Murcia 30850",
    "addr:housenumber":"5",
    "addr:postcode":"30850",
    "addr:street":"Calle De Venezuela",
    "iso:country":"ES",
    "sg:address":"Calle de Venezuela, 5",
    "sg:city":"Totana",
    "sg:orig_category":"Cr\u00cda De Animales",
    "sg:phone":"+34 968 42 07 23",
    "sg:postcode":"30850",
    "sg:province":"Murcia",
    "wof:name":"Costa Garcia Juan",
    "wof:placetype":"venue"
},
  "geometry": {"coordinates":[-1.5045759678,37.7639007568],"type":"Point"}
}