{
  "type": "Feature",
  "properties": {
    "iso:country":"ES",
    "sg:address":"Carrer de Olivera, 23",
    "sg:city":"Barcelona",
    "sg:orig_category":"Carnicer\u00cdas, Carnicer\u00cdas",
    "sg:phone":"+34 934 23 40 97",
    "sg:postcode":"08004",
    "sg:province":"Barcelona",
    "wof:name":"Casanellas Costa Rosa",
    "wof:placetype":"venue"
},
  "geometry": {"coordinates":[2.1581759453,41.3735694885],"type":"Point"}
}