{
  "type": "Feature",
  "properties": {
    "iso:country":"ES",
    "sg:address":"Cmno Venta, 936",
    "sg:city":"Columbrianos",
    "sg:orig_category":"Empresas De Carpinter\u00cda Met\u00c1lica",
    "sg:phone":"+34 987 42 96 56",
    "sg:postcode":"24490",
    "sg:province":"Le\u00f3n",
    "wof:name":"Tarvinor S.l.",
    "wof:placetype":"venue"
},
  "geometry": {"coordinates":[-6.6118087769,42.5740661621],"type":"Point"}
}