{
  "type": "Feature",
  "properties": {
    "iso:country":"ES",
    "sg:address":"Calle de Real, 1",
    "sg:city":"S. Leonardo Yag\u00fce",
    "sg:orig_category":"Flores Y Plantas Naturales (al Por Mayor)",
    "sg:phone":"+34 975 37 65 88",
    "sg:postcode":"42140",
    "sg:province":"Soria",
    "wof:name":"Leon Carretero Teodoro",
    "wof:placetype":"venue"
},
  "geometry": {"coordinates":[-3.0625391006,41.8294868469],"type":"Point"}
}