{
  "type": "Feature",
  "properties": {
    "addr:full":"Carrer de Gran, 3 Argentona Barcelona 08310",
    "addr:housenumber":"3",
    "addr:postcode":"08310",
    "addr:street":"Carrer De Gran",
    "iso:country":"ES",
    "sg:address":"Carrer de Gran, 3",
    "sg:city":"Argentona",
    "sg:orig_category":"Cajas De Ahorro",
    "sg:phone":"+34 937 97 01 56",
    "sg:postcode":"08310",
    "sg:province":"Barcelona",
    "wof:name":"Caixa D'estalvis Laietana",
    "wof:placetype":"venue"
},
  "geometry": {"coordinates":[2.402105093,41.5543251038],"type":"Point"}
}