{
  "type": "Feature",
  "properties": {
    "iso:country":"ES",
    "sg:address":"Carrer de Colomeres (les), 135",
    "sg:city":"Gava",
    "sg:orig_category":"Mercer\u00cda, Lencer\u00cda (al Por Menor)",
    "sg:phone":"+34 936 38 48 09",
    "sg:postcode":"08850",
    "sg:province":"Barcelona",
    "wof:name":"Lopez Perez Francisca",
    "wof:placetype":"venue"
},
  "geometry": {"coordinates":[1.9993009567,41.3068084717],"type":"Point"}
}