{
  "type": "Feature",
  "properties": {
    "iso:country":"ES",
    "sg:address":"Calle de Hoyos, 21",
    "sg:city":"Iscar",
    "sg:orig_category":"Empresas De Carpinter\u00cda De Madera",
    "sg:phone":"+34 983 61 18 81",
    "sg:postcode":"47420",
    "sg:province":"Valladolid",
    "wof:name":"Sanz Garcia Damian",
    "wof:placetype":"venue"
},
  "geometry": {"coordinates":[-4.5292100906,41.3641548157],"type":"Point"}
}