{
  "type": "Feature",
  "properties": {
    "addr:full":"Calle de Eucaliptus, 67 Malaga M\u00e1laga 29018",
    "addr:housenumber":"67",
    "addr:postcode":"29018",
    "addr:street":"Calle De Eucaliptus;Ma\u0301Laga",
    "iso:country":"ES",
    "sg:address":"Calle de Eucaliptus, 67",
    "sg:city":"Malaga",
    "sg:orig_category":"Empresas De Carpinter\u00cda De Madera",
    "sg:phone":"+34 952 29 25 11",
    "sg:postcode":"29018",
    "sg:province":"M\u00e1laga",
    "wof:name":"Rekalde Muebles Originales Scda.coop.andaluza",
    "wof:placetype":"venue"
},
  "geometry": {"coordinates":[-4.3709549904,36.7310218811],"type":"Point"}
}