{
  "type": "Feature",
  "properties": {
    "iso:country":"ES",
    "sg:address":"Calle de Mariano Ribera, 31",
    "sg:city":"Valencia",
    "sg:orig_category":"Centros Empresariales",
    "sg:phone":"+34 963 82 11 15",
    "sg:postcode":"46018",
    "sg:province":"Valencia",
    "wof:name":"Godos Carrion Maria Jose",
    "wof:placetype":"venue"
},
  "geometry": {"coordinates":[-0.3936020136,39.4651298523],"type":"Point"}
}