{
  "type": "Feature",
  "properties": {
    "iso:country":"ES",
    "sg:address":"Av Valles, 484",
    "sg:city":"Terrassa",
    "sg:orig_category":"Bebidas",
    "sg:phone":"+34 937 31 20 00",
    "sg:postcode":"08227",
    "sg:province":"Barcelona",
    "wof:name":"Begudes Del Valles S.a.",
    "wof:placetype":"venue"
},
  "geometry": {"coordinates":[2.0339889526,41.562461853],"type":"Point"}
}