{
  "type": "Feature",
  "properties": {
    "addr:full":"Calle de Rojas, 8 Ecija Sevilla 41400",
    "addr:housenumber":"8",
    "addr:postcode":"41400",
    "addr:street":"Calle De Rojas",
    "iso:country":"ES",
    "sg:address":"Calle de Rojas, 8",
    "sg:city":"Ecija",
    "sg:classifiers":[
        {
            "category":"Communications",
            "type":"Services"
        }
    ],
    "sg:phone":"+34 955 90 47 71",
    "sg:postcode":"41400",
    "sg:province":"Sevilla",
    "sg:tags":[
        "televisiones",
        "y",
        "radio"
    ],
    "sg:website":"www.telecija.com",
    "wof:name":"G & M Difusion Sociedad Cooperativa Andaluza",
    "wof:placetype":"venue"
},
  "geometry": {"coordinates":[-5.0756831169,37.5412940979],"type":"Point"}
}