{
  "type": "Feature",
  "properties": {
    "iso:country":"ES",
    "sg:address":"Pl Sales I Ferre, 15",
    "sg:city":"Ulldecona",
    "sg:orig_category":"Poller\u00cda Y Caza (al Por Menor)",
    "sg:phone":"+34 977 57 30 61",
    "sg:postcode":"43550",
    "sg:province":"Tarragona",
    "wof:name":"Pitarch Estupi\u00f1a Antonio",
    "wof:placetype":"venue"
},
  "geometry": {"coordinates":[0.4456399977,40.5960197449],"type":"Point"}
}