{
  "type": "Feature",
  "properties": {
    "addr:full":"Calle de Reyes Catolicos, S/n Cordoba C\u00f3rdoba 14001",
    "addr:housenumber":"s / n",
    "addr:postcode":"14001",
    "addr:street":"Calle De Reyes Catolicos;Co\u0301Rdoba",
    "iso:country":"ES",
    "sg:address":"Calle de Reyes Catolicos, S/n",
    "sg:city":"Cordoba",
    "sg:orig_category":"Centros De Coordinaci\u00d3n",
    "sg:phone":"+34 957 47 37 79",
    "sg:postcode":"14001",
    "sg:province":"C\u00f3rdoba",
    "wof:name":"Atlanta Solutions S.l.",
    "wof:placetype":"venue"
},
  "geometry": {"coordinates":[-4.7812080383,37.8892440796],"type":"Point"}
}