{
  "type": "Feature",
  "properties": {
    "addr:full":"Pg Del Penyal D'ifach, 40 Coma Valencia 46980",
    "addr:housenumber":"40",
    "addr:postcode":"46980",
    "addr:street":"Pg Del Penyal D'Ifach",
    "iso:country":"ES",
    "sg:address":"Pg Del Penyal D'ifach, 40",
    "sg:city":"Coma",
    "sg:orig_category":"Oficinas: Suministros Para (fabricaci\u00d3n, Al Por Mayor)",
    "sg:phone":"+34 961 38 91 59",
    "sg:postcode":"46980",
    "sg:province":"Valencia",
    "wof:name":"Lediberg Espa\u00f1a S.a.",
    "wof:placetype":"venue"
},
  "geometry": {"coordinates":[-0.4262197018,39.521522522],"type":"Point"}
}