{
  "type": "Feature",
  "properties": {
    "iso:country":"ES",
    "sg:address":"Avda Hytasa, 3",
    "sg:city":"Sevilla",
    "sg:orig_category":"Electromedicina: Equipo",
    "sg:phone":"+34 954 92 00 41",
    "sg:postcode":"41006",
    "sg:province":"Sevilla",
    "wof:name":"Hucoa Erloss S.a.",
    "wof:placetype":"venue"
},
  "geometry": {"coordinates":[-5.9638681412,37.3731956482],"type":"Point"}
}