{
  "type": "Feature",
  "properties": {
    "iso:country":"ES",
    "sg:address":"Calle de Alejandro De Vida Hidalgo, 43",
    "sg:city":"Cabra",
    "sg:orig_category":"Electricidad: Instaladores",
    "sg:phone":"+34 957 52 32 02",
    "sg:postcode":"14940",
    "sg:province":"C\u00f3rdoba",
    "wof:name":"Castro Roldan Antonio",
    "wof:placetype":"venue"
},
  "geometry": {"coordinates":[-4.443230629,37.4689331055],"type":"Point"}
}