{
  "type": "Feature",
  "properties": {
    "iso:country":"ES",
    "sg:address":"Calle de Cooperativa Vieja, 2",
    "sg:city":"Villa Don Fadrique",
    "sg:orig_category":"Arquitectos",
    "sg:phone":"+34 925 19 54 41",
    "sg:postcode":"45850",
    "sg:province":"Toledo",
    "wof:name":"Canalejas Escribano Jesus",
    "wof:placetype":"venue"
},
  "geometry": {"coordinates":[-3.210672617,39.6119346619],"type":"Point"}
}