{
  "type": "Feature",
  "properties": {
    "iso:country":"ES",
    "sg:address":"Luga Ca\u00d1ada (la), S/n",
    "sg:city":"Calzada Tera",
    "sg:orig_category":"Delegados, Agentes De Tr\u00c1nsito, Auxiliares De Transporte Internacional",
    "sg:phone":"+34 980 64 59 35",
    "sg:postcode":"49332",
    "sg:province":"Zamora",
    "wof:name":"Ganado Mayo Gregorio",
    "wof:placetype":"venue"
},
  "geometry": {"coordinates":[-6.0767960548,41.9845962524],"type":"Point"}
}