{
  "type": "Feature",
  "properties": {
    "iso:country":"ES",
    "sg:address":"Avda Yecla (de), S/n",
    "sg:city":"Jumilla",
    "sg:orig_category":"Agricultura: Abastecimiento Y Cosechado (negocio)",
    "sg:phone":"+34 968 78 35 00",
    "sg:postcode":"30520",
    "sg:province":"Murcia",
    "wof:name":"Agricola Jumillana Sociedad Cooperativa",
    "wof:placetype":"venue"
},
  "geometry": {"coordinates":[-1.3217301369,38.4845581055],"type":"Point"}
}