{
  "type": "Feature",
  "properties": {
    "addr:full":"Portal, 25 Pobleta Bellvei Lleida 25513",
    "addr:postcode":"25513",
    "iso:country":"ES",
    "sg:address":"Portal, 25",
    "sg:city":"Pobleta Bellvei",
    "sg:orig_category":"Deportes Y Programas De Aventura",
    "sg:phone":"+34 973 66 17 17",
    "sg:postcode":"25513",
    "sg:province":"Lleida",
    "wof:name":"L'era Del Marxant S.l.",
    "wof:placetype":"venue"
},
  "geometry": {"coordinates":[1.0205830336,42.3321685791],"type":"Point"}
}