{
  "type": "Feature",
  "properties": {
    "iso:country":"ES",
    "sg:address":"Carrer de Sant Cristofol, 8",
    "sg:city":"Palma De Cervello",
    "sg:orig_category":"Deportes Y Programas De Aventura",
    "sg:phone":"+34 936 72 04 38",
    "sg:postcode":"08756",
    "sg:province":"Barcelona",
    "sg:website":"www.barcelonapaintball.com",
    "wof:name":"Masdeu Lopez Antonio",
    "wof:placetype":"venue"
},
  "geometry": {"coordinates":[1.9711380005,41.4110641479],"type":"Point"}
}