{
  "type": "Feature",
  "properties": {
    "addr:full":"Rua Vidales Tome, 6 Ponteareas Pontevedra 36860",
    "addr:housenumber":"6",
    "addr:postcode":"36860",
    "addr:street":"Rua Vidales Tome",
    "iso:country":"ES",
    "sg:address":"Rua Vidales Tome, 6",
    "sg:city":"Ponteareas",
    "sg:orig_category":"Herboristas (al Por Menor)",
    "sg:phone":"+34 986 64 05 48",
    "sg:postcode":"36860",
    "sg:province":"Pontevedra",
    "wof:name":"Gonzalez Leandrez Jose",
    "wof:placetype":"venue"
},
  "geometry": {"coordinates":[-8.5026950836,42.1759567261],"type":"Point"}
}