{
  "type": "Feature",
  "properties": {
    "addr:full":"Avda Vigo, 224 Angoren Pontevedra 36320",
    "addr:housenumber":"224",
    "addr:postcode":"36320",
    "addr:street":"Avda Vigo",
    "iso:country":"ES",
    "sg:address":"Avda Vigo, 224",
    "sg:city":"Angoren",
    "sg:orig_category":"Ense\u00d1anza Variada",
    "sg:phone":"+34 986 45 00 25",
    "sg:postcode":"36320",
    "sg:province":"Pontevedra",
    "wof:name":"Alfa Meta Formacion S.l.",
    "wof:placetype":"venue"
},
  "geometry": {"coordinates":[-8.6480531693,42.4336204529],"type":"Point"}
}