{
  "type": "Feature",
  "properties": {
    "iso:country":"ES",
    "sg:address":"Calle de Rio Taju\u00d1a, 8",
    "sg:city":"Mostoles",
    "sg:orig_category":"Empresas De Limpieza",
    "sg:phone":"+34 916 14 45 62",
    "sg:postcode":"28934",
    "sg:province":"Madrid",
    "wof:name":"Limpiezas Hirsan S.l.",
    "wof:placetype":"venue"
},
  "geometry": {"coordinates":[-3.8686139584,40.3196296692],"type":"Point"}
}