{
  "type": "Feature",
  "properties": {
    "addr:full":"Avda Alcoy, 90 Alacant Alicante 03010",
    "addr:housenumber":"90",
    "addr:postcode":"03010",
    "addr:street":"Avda Alcoy",
    "iso:country":"ES",
    "sg:address":"Avda Alcoy, 90",
    "sg:city":"Alacant",
    "sg:orig_category":"Farmacias",
    "sg:phone":"+34 965 24 36 97",
    "sg:postcode":"03010",
    "sg:province":"Alicante",
    "wof:name":"Lopez Martinez Milagros",
    "wof:placetype":"venue"
},
  "geometry": {"coordinates":[-0.4909600019,38.3595581055],"type":"Point"}
}