{
  "type": "Feature",
  "properties": {
    "addr:full":"Calle de Trento, 4 Donostia-san Sebastian Guip\u00f9zcoa 20018",
    "addr:housenumber":"4",
    "addr:postcode":"20018",
    "addr:street":"Calle De Trento",
    "iso:country":"ES",
    "sg:address":"Calle de Trento, 4",
    "sg:city":"Donostia-san Sebastian",
    "sg:orig_category":"Panader\u00cdas, Panader\u00cdas",
    "sg:phone":"+34 943 21 38 49",
    "sg:postcode":"20018",
    "sg:province":"Guip\u00f9zcoa",
    "wof:name":"Lords Echave S.l.",
    "wof:placetype":"venue"
},
  "geometry": {"coordinates":[-2.0057780743,43.313785553],"type":"Point"}
}