{
  "type": "Feature",
  "properties": {
    "iso:country":"ES",
    "sg:address":"Calle de Sancho Abarca, 13",
    "sg:city":"Huesca",
    "sg:orig_category":"Arquitectos",
    "sg:phone":"+34 974 24 61 54",
    "sg:postcode":"22002",
    "sg:province":"Huesca",
    "wof:name":"Sanchez Climent Joaquin",
    "wof:placetype":"venue"
},
  "geometry": {"coordinates":[-0.4092499912,42.1386260986],"type":"Point"}
}