{
  "type": "Feature",
  "properties": {
    "addr:full":"Carr Nou, 33 Girona Girona 17001",
    "addr:housenumber":"33",
    "addr:postcode":"17001",
    "addr:street":"Carr Nou",
    "iso:country":"ES",
    "sg:address":"Carr Nou, 33",
    "sg:city":"Girona",
    "sg:orig_category":"Cajas De Ahorro",
    "sg:phone":"+34 972 22 20 48",
    "sg:postcode":"17001",
    "sg:province":"Girona",
    "wof:name":"Caixa De Girona",
    "wof:placetype":"venue"
},
  "geometry": {"coordinates":[2.8187448978,41.9808616638],"type":"Point"}
}