{
  "type": "Feature",
  "properties": {
    "iso:country":"ES",
    "sg:address":"Carrer de Cartagena, 267",
    "sg:city":"Barcelona",
    "sg:orig_category":"Farmacias",
    "sg:phone":"+34 934 36 40 41",
    "sg:postcode":"08025",
    "sg:province":"Barcelona",
    "wof:name":"Terradellas Bosch Maria Angels",
    "wof:placetype":"venue"
},
  "geometry": {"coordinates":[2.1771659851,41.408821106],"type":"Point"}
}