{
  "type": "Feature",
  "properties": {
    "iso:country":"ES",
    "sg:address":"Pg Gran Passeig Ronda, 61",
    "sg:city":"Lleida",
    "sg:orig_category":"Inform\u00c1tica: Material Y Suministros",
    "sg:phone":"+34 973 28 25 70",
    "sg:postcode":"25006",
    "sg:province":"Lleida",
    "wof:name":"Vilanova Vall Merce",
    "wof:placetype":"venue"
},
  "geometry": {"coordinates":[0.6132599711,41.6166000366],"type":"Point"}
}