{
  "type": "Feature",
  "properties": {
    "iso:country":"ES",
    "sg:address":"Calle de Guayedra, 13",
    "sg:city":"Monta\u00e7eta Del Calero",
    "sg:orig_category":"Electricidad, Electr\u00d3nica: Material Y Suministros (al Por Mayor)",
    "sg:phone":"+34 928 68 14 46",
    "sg:postcode":"35200",
    "sg:province":"Las Palmas",
    "wof:name":"Quintana Rivero Josefa Antonia",
    "wof:placetype":"venue"
},
  "geometry": {"coordinates":[-15.4144220352,28.0029888153],"type":"Point"}
}