{
  "type": "Feature",
  "properties": {
    "addr:full":"Calle de Capitan Haya, 1 Madrid Madrid 28020",
    "addr:housenumber":"1",
    "addr:postcode":"28020",
    "addr:street":"Calle De Capitan Haya",
    "iso:country":"ES",
    "sg:address":"Calle de Capitan Haya, 1",
    "sg:city":"Madrid",
    "sg:orig_category":"Promotores Constructores",
    "sg:phone":"+34 915 75 02 78",
    "sg:postcode":"28020",
    "sg:province":"Madrid",
    "sg:website":"www.gruporayet.com",
    "wof:name":"Grupo Rayet S.a.",
    "wof:placetype":"venue"
},
  "geometry": {"coordinates":[-3.6926243305,40.4532432556],"type":"Point"}
}