{
  "type": "Feature",
  "properties": {
    "iso:country":"ES",
    "sg:address":"Calle de Corredera Alta, 29",
    "sg:city":"Chiclana De La Frontera",
    "sg:orig_category":"Quincaller\u00cda (al Por Menor)",
    "sg:phone":"+34 956 40 06 05",
    "sg:postcode":"11130",
    "sg:province":"C\u00e1diz",
    "wof:name":"Morales Morales Alfonso",
    "wof:placetype":"venue"
},
  "geometry": {"coordinates":[-6.1477847099,36.4191665649],"type":"Point"}
}