{
  "type": "Feature",
  "properties": {
    "iso:country":"ES",
    "sg:address":"Calle de General Aguilera, 6",
    "sg:city":"Ciudad Real",
    "sg:orig_category":"M\u00c9dicos: Estomatolog\u00cda",
    "sg:phone":"+34 926 21 66 66",
    "sg:postcode":"13001",
    "sg:province":"Ciudad Real",
    "wof:name":"Tellez Delgado Ana",
    "wof:placetype":"venue"
},
  "geometry": {"coordinates":[-3.9284229279,38.9843101501],"type":"Point"}
}