{
  "type": "Feature",
  "properties": {
    "addr:full":"Ctra Nijar La Ca\u00d1ada, 202 Ca\u00e7ada De San Urbano Almer\u00eda 04120",
    "addr:housenumber":"202",
    "addr:postcode":"04120",
    "addr:street":"Ctra Nijar La Can\u0303Ada;Almeri\u0301A",
    "iso:country":"ES",
    "sg:address":"Ctra Nijar La Ca\u00d1ada, 202",
    "sg:city":"Ca\u00e7ada De San Urbano",
    "sg:orig_category":"Radiocomunicaciones, Telefon\u00cda M\u00d3vil, Radiomensajer\u00cda: Servicios, Comercializaci\u00d3n",
    "sg:phone":"+34 950 62 62 62",
    "sg:postcode":"04120",
    "sg:province":"Almer\u00eda",
    "wof:name":"J.j.telecomunicaciones C.b.",
    "wof:placetype":"venue"
},
  "geometry": {"coordinates":[-2.4082989693,36.840461731],"type":"Point"}
}