{
  "type": "Feature",
  "properties": {
    "addr:full":"Ctra Cadiz (de), Km. 0189,0 Marbella M\u00e1laga 29600",
    "addr:postcode":"29600",
    "addr:street":"Ctra Cadiz De Km. 0189,0;Ma\u0301Laga",
    "iso:country":"ES",
    "sg:address":"Ctra Cadiz (de), Km. 0189,0",
    "sg:city":"Marbella",
    "sg:orig_category":"Agentes, Concesionarios Y Sucursales De Veh\u00cdculos",
    "sg:phone":"+34 952 86 17 55",
    "sg:postcode":"29600",
    "sg:province":"M\u00e1laga",
    "wof:name":"Automoviles Marbella S. A.",
    "wof:placetype":"venue"
},
  "geometry": {"coordinates":[-4.8833007812,36.5079956055],"type":"Point"}
}