{
  "type": "Feature",
  "properties": {
    "addr:full":"Pg Olot, 121 Girona Girona 17006",
    "addr:housenumber":"121",
    "addr:postcode":"17006",
    "addr:street":"Pg Olot",
    "iso:country":"ES",
    "sg:address":"Pg Olot, 121",
    "sg:city":"Girona",
    "sg:orig_category":"Ingenier\u00cda, Centros De Estudios (diversos)",
    "sg:phone":"+34 972 40 24 50",
    "sg:postcode":"17006",
    "sg:province":"Girona",
    "sg:website":"www.sinergis.biz",
    "wof:name":"Sinergis Ingenieria S.l.",
    "wof:placetype":"venue"
},
  "geometry": {"coordinates":[2.8017890453,41.9743041992],"type":"Point"}
}