{
  "type": "Feature",
  "properties": {
    "iso:country":"ES",
    "sg:address":"Calle de Sara Montiel, 6",
    "sg:city":"Montiel",
    "sg:classifiers":[
        {
            "category":"Taxi",
            "type":"Transportation"
        }
    ],
    "sg:phone":"+34 926 35 32 11",
    "sg:postcode":"13326",
    "sg:province":"Ciudad Real",
    "wof:name":"Arias Guerra Juan Jose",
    "wof:placetype":"venue"
},
  "geometry": {"coordinates":[-2.866963625,38.6978912354],"type":"Point"}
}