{
  "type": "Feature",
  "properties": {
    "addr:full":"Carr Cementerio, S/n Manises Valencia 46940",
    "addr:housenumber":"s / n",
    "addr:postcode":"46940",
    "addr:street":"Carr Cementerio",
    "iso:country":"ES",
    "sg:address":"Carr Cementerio, S/n",
    "sg:city":"Manises",
    "sg:orig_category":"Iglesia Cat\u00d3lica",
    "sg:phone":"+34 961 54 60 61",
    "sg:postcode":"46940",
    "sg:province":"Valencia",
    "wof:name":"Parroquia De San Juan Bautista De Manises",
    "wof:placetype":"venue"
},
  "geometry": {"coordinates":[-0.4624490142,39.4875259399],"type":"Point"}
}