{
  "type": "Feature",
  "properties": {
    "addr:full":"Rua Benito Corbal, 24 Pontevedra Pontevedra 36001",
    "addr:housenumber":"24",
    "addr:postcode":"36001",
    "addr:street":"Rua Benito Corbal",
    "iso:country":"ES",
    "sg:address":"Rua Benito Corbal, 24",
    "sg:city":"Pontevedra",
    "sg:orig_category":"Cl\u00cdnicas M\u00c9dicas",
    "sg:phone":"+34 986 85 02 66",
    "sg:postcode":"36001",
    "sg:province":"Pontevedra",
    "sg:website":"www.mutual-cyclops.com",
    "wof:name":"Mutual Midat Cyclops Mutua De Accidentes De Trabajo Y Enfermedades Profesionales De La Seguridad Soc",
    "wof:placetype":"venue"
},
  "geometry": {"coordinates":[-8.641251564,42.4302062988],"type":"Point"}
}