{
  "type": "Feature",
  "properties": {
    "addr:full":"Calle de Real De La Plaza, 5 Teror Las Palmas 35330",
    "addr:housenumber":"5",
    "addr:postcode":"35330",
    "addr:street":"Calle De Real De La Plaza",
    "iso:country":"ES",
    "sg:address":"Calle de Real De La Plaza, 5",
    "sg:city":"Teror",
    "sg:orig_category":"Confecci\u00d3n (fabricaci\u00d3n, Al Por Mayor)",
    "sg:phone":"+34 928 63 07 98",
    "sg:postcode":"35330",
    "sg:province":"Las Palmas",
    "wof:name":"Hepogue S.l.",
    "wof:placetype":"venue"
},
  "geometry": {"coordinates":[-15.5470056534,28.0603199005],"type":"Point"}
}