{
  "type": "Feature",
  "properties": {
    "iso:country":"ES",
    "sg:address":"Cami Plana (de La), 2",
    "sg:city":"Lloren\u00e7 Penedes",
    "sg:orig_category":"Asociaciones Y Clubs Deportivos",
    "sg:phone":"+34 977 67 72 05",
    "sg:postcode":"43712",
    "sg:province":"Tarragona",
    "wof:name":"Cata Boada Gabriel",
    "wof:placetype":"venue"
},
  "geometry": {"coordinates":[1.5482150316,41.282371521],"type":"Point"}
}