{
  "type": "Feature",
  "properties": {
    "iso:country":"ES",
    "sg:address":"Calle de Catalu\u00d1a, 23",
    "sg:city":"Sevilla",
    "sg:orig_category":"Inmobiliaria (agencias)",
    "sg:phone":"+34 954 91 57 82",
    "sg:postcode":"41015",
    "sg:province":"Sevilla",
    "wof:name":"Estudio San Jeronimo 2003 S.l.",
    "wof:placetype":"venue"
},
  "geometry": {"coordinates":[-5.9839711189,37.424331665],"type":"Point"}
}