{
  "type": "Feature",
  "properties": {
    "iso:country":"ES",
    "sg:address":"Calle de Pajaritos, 25",
    "sg:city":"Malaga",
    "sg:orig_category":"Deportes Y Programas De Aventura",
    "sg:phone":"+34 952 07 08 88",
    "sg:postcode":"29009",
    "sg:province":"M\u00e1laga",
    "wof:name":"Td. Entrenamiento Y Salud S.l.",
    "wof:placetype":"venue"
},
  "geometry": {"coordinates":[-4.4349341393,36.7251663208],"type":"Point"}
}