{
  "type": "Feature",
  "properties": {
    "addr:full":"Carrer de Major, 42 Selva Del Camp Tarragona 43470",
    "addr:housenumber":"42",
    "addr:postcode":"43470",
    "addr:street":"Carrer De Major",
    "iso:country":"ES",
    "sg:address":"Carrer de Major, 42",
    "sg:city":"Selva Del Camp",
    "sg:orig_category":"Carnicer\u00cdas, Carnicer\u00cdas",
    "sg:phone":"+34 977 84 44 48",
    "sg:postcode":"43470",
    "sg:province":"Tarragona",
    "wof:name":"Mila Ciurana Josep Maria",
    "wof:placetype":"venue"
},
  "geometry": {"coordinates":[1.1378760338,41.2153320312],"type":"Point"}
}