{
  "type": "Feature",
  "properties": {
    "iso:country":"ES",
    "sg:address":"C/ Sardana, 202",
    "sg:city":"Banyoles",
    "sg:orig_category":"Asilos De Ancianos. Centros Privados",
    "sg:phone":"+34 972 57 66 34",
    "sg:postcode":"17820",
    "sg:province":"Girona",
    "wof:name":"Residencia La Solana S.l.",
    "wof:placetype":"venue"
},
  "geometry": {"coordinates":[2.758660078,42.1191215515],"type":"Point"}
}