{
  "type": "Feature",
  "properties": {
    "addr:full":"Carrer de Sant Nicasi, 11 Gava Barcelona 08850",
    "addr:housenumber":"11",
    "addr:postcode":"08850",
    "addr:street":"Carrer De Sant Nicasi",
    "iso:country":"ES",
    "sg:address":"Carrer de Sant Nicasi, 11",
    "sg:city":"Gava",
    "sg:orig_category":"Ropa De Hogar (al Por Menor)",
    "sg:phone":"+34 936 62 37 09",
    "sg:postcode":"08850",
    "sg:province":"Barcelona",
    "wof:name":"Marques Gil Antonio",
    "wof:placetype":"venue"
},
  "geometry": {"coordinates":[2.003344059,41.3046836853],"type":"Point"}
}