{
  "type": "Feature",
  "properties": {
    "addr:full":"Rond Zamenhof, 100 Sabadell Barcelona 08208",
    "addr:housenumber":"100",
    "addr:postcode":"08208",
    "addr:street":"Zamenhof",
    "iso:country":"ES",
    "sg:address":"Rond Zamenhof, 100",
    "sg:city":"Sabadell",
    "sg:orig_category":"Arquitectos",
    "sg:phone":"+34 937 27 39 02",
    "sg:postcode":"08208",
    "sg:province":"Barcelona",
    "wof:name":"Campistron I Doc Grup D'arquitectes Associats S.l.",
    "wof:placetype":"venue"
},
  "geometry": {"coordinates":[2.1004939079,41.5507698059],"type":"Point"}
}