{
  "type": "Feature",
  "properties": {
    "addr:full":"Calle de San Francisco, 21 Lucena C\u00f3rdoba 14900",
    "addr:housenumber":"21",
    "addr:postcode":"14900",
    "addr:street":"Calle De San Francisco",
    "iso:country":"ES",
    "sg:address":"Calle de San Francisco, 21",
    "sg:city":"Lucena",
    "sg:orig_category":"Bisuter\u00cda, Joyer\u00cda, Relojer\u00cda (al Por Menor)",
    "sg:phone":"+34 957 51 51 44",
    "sg:postcode":"14900",
    "sg:province":"C\u00f3rdoba",
    "wof:name":"Aguilera Pineda Elias",
    "wof:placetype":"venue"
},
  "geometry": {"coordinates":[-4.4852924347,37.4148788452],"type":"Point"}
}