{
  "type": "Feature",
  "properties": {
    "addr:full":"Avda Leopoldo Querol, 77 Vinaros Castell\u00f3n 12500",
    "addr:housenumber":"77",
    "addr:postcode":"12500",
    "addr:street":"Avda Leopoldo Querol",
    "iso:country":"ES",
    "sg:address":"Avda Leopoldo Querol, 77",
    "sg:city":"Vinaros",
    "sg:orig_category":"Peluquer\u00cdas, Peluquer\u00cda Mixta",
    "sg:phone":"+34 964 45 68 34",
    "sg:postcode":"12500",
    "sg:province":"Castell\u00f3n",
    "wof:name":"Miralles Grau Rosario",
    "wof:placetype":"venue"
},
  "geometry": {"coordinates":[0.4749250114,40.4759368896],"type":"Point"}
}