{
  "type": "Feature",
  "properties": {
    "iso:country":"ES",
    "sg:address":"Pol Ind Majaravique, S/n",
    "sg:city":"Rinconada",
    "sg:orig_category":"Promotores Constructores",
    "sg:phone":"+34 954 90 47 93",
    "sg:postcode":"41309",
    "sg:province":"Sevilla",
    "wof:name":"Pavimentos Impresos Majaravique Sl",
    "wof:placetype":"venue"
},
  "geometry": {"coordinates":[-5.9782538414,37.492855072],"type":"Point"}
}