{
  "type": "Feature",
  "properties": {
    "addr:full":"Calle de Mayor, 18 Guardo Palencia 34880",
    "addr:housenumber":"18",
    "addr:postcode":"34880",
    "addr:street":"Calle De Mayor",
    "iso:country":"ES",
    "sg:address":"Calle de Mayor, 18",
    "sg:city":"Guardo",
    "sg:orig_category":"Quincaller\u00cda (al Por Menor)",
    "sg:phone":"+34 979 85 00 98",
    "sg:postcode":"34880",
    "sg:province":"Palencia",
    "wof:name":"Heras Dominguez Francisco",
    "wof:placetype":"venue"
},
  "geometry": {"coordinates":[-4.843706131,42.788860321],"type":"Point"}
}