{
  "type": "Feature",
  "properties": {
    "addr:full":"Plaz Espa\u00d1a, 12 Villafranca De Los Barros Badajoz 06220",
    "addr:housenumber":"12",
    "addr:postcode":"06220",
    "addr:street":"Plaz Espan\u0303A",
    "iso:country":"ES",
    "sg:address":"Plaz Espa\u00d1a, 12",
    "sg:city":"Villafranca De Los Barros",
    "sg:orig_category":"Diarios, Revistas Y Boletines (suscripciones)",
    "sg:phone":"+34 924 52 44 89",
    "sg:postcode":"06220",
    "sg:province":"Badajoz",
    "wof:name":"Garcia Gaspar Francisco",
    "wof:placetype":"venue"
},
  "geometry": {"coordinates":[-6.3438782692,38.5860748291],"type":"Point"}
}