{
  "type": "Feature",
  "properties": {
    "iso:country":"ES",
    "sg:address":"Avda Ciudad De Barcelona, 39",
    "sg:city":"Madrid",
    "sg:orig_category":"Complementos De Vestir (al Por Menor)",
    "sg:phone":"+34 914 34 92 35",
    "sg:postcode":"28007",
    "sg:province":"Madrid",
    "wof:name":"Alonso Vi\u00f1uela Ana Belen",
    "wof:placetype":"venue"
},
  "geometry": {"coordinates":[-3.6792654991,40.4036636353],"type":"Point"}
}