{
  "type": "Feature",
  "properties": {
    "iso:country":"ES",
    "sg:address":"Ctra Alcoi (d'), 24",
    "sg:city":"Albaida",
    "sg:orig_category":"Fabricaci\u00d3n De Su\u00c9ters Y Chalecos De Punto",
    "sg:phone":"+34 962 90 12 14",
    "sg:postcode":"46860",
    "sg:province":"Valencia",
    "wof:name":"Cerda Satorres Antonio",
    "wof:placetype":"venue"
},
  "geometry": {"coordinates":[-0.5158039927,38.8357467651],"type":"Point"}
}