{
  "type": "Feature",
  "properties": {
    "addr:full":"Calle de Renueva, 6 Le\u00f3n Le\u00f3n 24002",
    "addr:housenumber":"6",
    "addr:postcode":"24002",
    "addr:street":"Calle De Renueva;Leo\u0301N",
    "iso:country":"ES",
    "sg:address":"Calle de Renueva, 6",
    "sg:city":"Le\u00f3n",
    "sg:orig_category":"M\u00c9dicos: Naturistas",
    "sg:phone":"+34 987 23 64 89",
    "sg:postcode":"24002",
    "sg:province":"Le\u00f3n",
    "wof:name":"Olivera Perez Maria Francisca",
    "wof:placetype":"venue"
},
  "geometry": {"coordinates":[-5.5723848343,42.6019096375],"type":"Point"}
}