{
  "type": "Feature",
  "properties": {
    "iso:country":"ES",
    "sg:address":"Carrer de Sant Isidre, 154",
    "sg:city":"Sabadell",
    "sg:orig_category":"Deportes Y Ocio: Art\u00cdculos Y Ropas (al Por Menor Y Accesorios)",
    "sg:phone":"+34 937 23 20 99",
    "sg:postcode":"08208",
    "sg:province":"Barcelona",
    "wof:name":"Fras Dosmil S.l.",
    "wof:placetype":"venue"
},
  "geometry": {"coordinates":[2.0997140408,41.5530700684],"type":"Point"}
}