{
  "type": "Feature",
  "properties": {
    "iso:country":"ES",
    "sg:address":"Melida, 2",
    "sg:city":"Pe\u00f1afiel",
    "sg:orig_category":"Productores Recolectores, Venta Directa De Vinos",
    "sg:phone":"+34 983 87 80 07",
    "sg:postcode":"47300",
    "sg:province":"Valladolid",
    "wof:name":"Bodegas Valpincia S.l.",
    "wof:placetype":"venue"
},
  "geometry": {"coordinates":[-4.1118798256,41.5944213867],"type":"Point"}
}