{
  "type": "Feature",
  "properties": {
    "iso:country":"ES",
    "sg:address":"Calle de Nuestra Se\u00d1ora De La Luz, 46",
    "sg:city":"Madrid",
    "sg:orig_category":"Centros Empresariales",
    "sg:phone":"+34 914 22 01 55",
    "sg:postcode":"28025",
    "sg:province":"Madrid",
    "wof:name":"Alternative Tunning S.l.",
    "wof:placetype":"venue"
},
  "geometry": {"coordinates":[-3.7459402084,40.383769989],"type":"Point"}
}