{
  "type": "Feature",
  "properties": {
    "addr:full":"Avda Antonio Trueba, 38 San Juan De Muskiz Vizcaya 48550",
    "addr:housenumber":"38",
    "addr:postcode":"48550",
    "addr:street":"Avda Antonio Trueba",
    "iso:country":"ES",
    "sg:address":"Avda Antonio Trueba, 38",
    "sg:city":"San Juan De Muskiz",
    "sg:orig_category":"Imprenta",
    "sg:phone":"+34 946 70 64 08",
    "sg:postcode":"48550",
    "sg:province":"Vizcaya",
    "wof:name":"Fernandez Ruano Maria Carmen",
    "wof:placetype":"venue"
},
  "geometry": {"coordinates":[-3.1170110703,43.3204231262],"type":"Point"}
}