{
  "type": "Feature",
  "properties": {
    "addr:full":"Carrer de Barcelona, 2 Hospitalet Llobregat Barcelona 08901",
    "addr:housenumber":"2",
    "addr:postcode":"08901",
    "addr:street":"Carrer De Barcelona",
    "iso:country":"ES",
    "sg:address":"Carrer de Barcelona, 2",
    "sg:city":"Hospitalet Llobregat",
    "sg:orig_category":"Art\u00cdculos De Decoraci\u00d3n",
    "sg:phone":"+34 932 61 19 34",
    "sg:postcode":"08901",
    "sg:province":"Barcelona",
    "sg:website":"www.zarahome.com",
    "wof:name":"Zara Home Espa\u00d1a S.a.",
    "wof:placetype":"venue"
},
  "geometry": {"coordinates":[2.1050786972,41.3615913391],"type":"Point"}
}