{
  "type": "Feature",
  "properties": {
    "addr:full":"Calle de Comandante Izarduy, 16 Vitoria-gasteiz \u00c1lava 01006",
    "addr:housenumber":"16",
    "addr:postcode":"01006",
    "addr:street":"Calle De Comandante Izarduy",
    "iso:country":"ES",
    "sg:address":"Calle de Comandante Izarduy, 16",
    "sg:city":"Vitoria-gasteiz",
    "sg:orig_category":"Transportes Por V\u00cdas Navegables",
    "sg:phone":"+34 945 13 65 31",
    "sg:postcode":"01006",
    "sg:province":"\u00c1lava",
    "wof:name":"Moral Elvira Juan",
    "wof:placetype":"venue"
},
  "geometry": {"coordinates":[-2.6689078808,42.8377189636],"type":"Point"}
}