{
  "type": "Feature",
  "properties": {
    "iso:country":"ES",
    "sg:address":"Pase Ramon Maria Lili, 4",
    "sg:city":"Donostia-san Sebastian",
    "sg:orig_category":"M\u00c9dicos: Neurolog\u00cda",
    "sg:phone":"+34 943 28 18 15",
    "sg:postcode":"20002",
    "sg:province":"Guip\u00f9zcoa",
    "wof:name":"Urcola Echeverria Javier",
    "wof:placetype":"venue"
},
  "geometry": {"coordinates":[-1.9783380032,43.3226470947],"type":"Point"}
}