{
  "type": "Feature",
  "properties": {
    "addr:full":"Calle de Ramon Y Cajal, 2 Ciudad Real Ciudad Real 13001",
    "addr:housenumber":"2",
    "addr:postcode":"13001",
    "addr:street":"Calle De Ramon Y Cajal",
    "iso:country":"ES",
    "sg:address":"Calle de Ramon Y Cajal, 2",
    "sg:city":"Ciudad Real",
    "sg:orig_category":"Asesor\u00cda Sobre Comunicaci\u00d3n De Empresas",
    "sg:phone":"+34 926 27 12 51",
    "sg:postcode":"13001",
    "sg:province":"Ciudad Real",
    "wof:name":"J.c.j. Inverbroker S.l.",
    "wof:placetype":"venue"
},
  "geometry": {"coordinates":[-3.9270019531,38.9844055176],"type":"Point"}
}