{
  "type": "Feature",
  "properties": {
    "iso:country":"ES",
    "sg:address":"Calle de Mallorca, 36",
    "sg:city":"Melilla",
    "sg:orig_category":"Edici\u00d3n De Diarios, Revistas, Boletines",
    "sg:phone":"+34 952 67 86 88",
    "sg:postcode":"52006",
    "sg:province":"Melilla",
    "wof:name":"Calzado Gimenez Dubhe",
    "wof:placetype":"venue"
},
  "geometry": {"coordinates":[-2.9434680939,35.2751197815],"type":"Point"}
}