{
  "type": "Feature",
  "properties": {
    "addr:full":"Calle de San Atilano, 7 Zamora Zamora 49003",
    "addr:housenumber":"7",
    "addr:postcode":"49003",
    "addr:street":"Calle De San Atilano",
    "iso:country":"ES",
    "sg:address":"Calle de San Atilano, 7",
    "sg:city":"Zamora",
    "sg:orig_category":"Mudanzas",
    "sg:phone":"+34 980 53 58 53",
    "sg:postcode":"49003",
    "sg:province":"Zamora",
    "wof:name":"Reto A La Esperanza Asociacion",
    "wof:placetype":"venue"
},
  "geometry": {"coordinates":[-5.7436270714,41.5038261414],"type":"Point"}
}