{
  "type": "Feature",
  "properties": {
    "addr:full":"Calle de Reina, 36 Barrios C\u00e1diz 11370",
    "addr:housenumber":"36",
    "addr:postcode":"11370",
    "addr:street":"Calle De Reina;Ca\u0301Diz",
    "iso:country":"ES",
    "sg:address":"Calle de Reina, 36",
    "sg:city":"Barrios",
    "sg:orig_category":"Ense\u00d1anza, Formaci\u00d3n Profesional: Aprendizaje",
    "sg:phone":"+34 956 62 09 64",
    "sg:postcode":"11370",
    "sg:province":"C\u00e1diz",
    "wof:name":"Servicio Andaluz De Empleo",
    "wof:placetype":"venue"
},
  "geometry": {"coordinates":[-5.493227005,36.1859970093],"type":"Point"}
}