{
  "type": "Feature",
  "properties": {
    "iso:country":"ES",
    "sg:address":"Venus, 79",
    "sg:city":"Can Parellada",
    "sg:orig_category":"Bares, Piano",
    "sg:phone":"+34 937 36 36 20",
    "sg:postcode":"08228",
    "sg:province":"Barcelona",
    "wof:name":"Exclusivas Egara S.a.",
    "wof:placetype":"venue"
},
  "geometry": {"coordinates":[2.0362648964,41.5310096741],"type":"Point"}
}