{
  "type": "Feature",
  "properties": {
    "addr:full":"Pg Verdum, 10 Barcelona Barcelona 08016",
    "addr:housenumber":"10",
    "addr:postcode":"08016",
    "addr:street":"Pg Verdum",
    "iso:country":"ES",
    "sg:address":"Pg Verdum, 10",
    "sg:city":"Barcelona",
    "sg:orig_category":"Talleres: Ropa A Medida",
    "sg:phone":"+34 933 59 83 95",
    "sg:postcode":"08016",
    "sg:province":"Barcelona",
    "wof:name":"R.oliveras Deulofeu S.a.",
    "wof:placetype":"venue"
},
  "geometry": {"coordinates":[2.1728310585,41.4361228943],"type":"Point"}
}