{
  "type": "Feature",
  "properties": {
    "addr:full":"Carr Sucrera, 8 Termens Lleida 25670",
    "addr:housenumber":"8",
    "addr:postcode":"25670",
    "addr:street":"Carr Sucrera",
    "iso:country":"ES",
    "sg:address":"Carr Sucrera, 8",
    "sg:city":"Termens",
    "sg:orig_category":"Mec\u00c1nico Del Autom\u00d3vil",
    "sg:phone":"+34 973 18 00 38",
    "sg:postcode":"25670",
    "sg:province":"Lleida",
    "wof:name":"Mayals Garrofer Albert",
    "wof:placetype":"venue"
},
  "geometry": {"coordinates":[0.7597749829,41.7178993225],"type":"Point"}
}