{
  "type": "Feature",
  "properties": {
    "addr:full":"Calle de Periodista Antonio Herrero, 11 Vista Alegre Murcia 30007",
    "addr:housenumber":"11",
    "addr:postcode":"30007",
    "addr:street":"Calle De Periodista Antonio Herrero",
    "iso:country":"ES",
    "sg:address":"Calle de Periodista Antonio Herrero, 11",
    "sg:city":"Vista Alegre",
    "sg:orig_category":"M\u00c9dicos: Enfermedades De La Sangre (hematolog\u00cda)",
    "sg:phone":"+34 968 20 22 38",
    "sg:postcode":"30007",
    "sg:province":"Murcia",
    "wof:name":"Rosique Cortina Pedro Luis",
    "wof:placetype":"venue"
},
  "geometry": {"coordinates":[-1.1314690113,37.9989547729],"type":"Point"}
}