{
  "type": "Feature",
  "properties": {
    "addr:full":"Ctra Mami A Viator (del), Km. 0002,0 Ca\u00e7ada De San Urbano Almer\u00eda 04120",
    "addr:postcode":"04120",
    "addr:street":"Ctra Mami A Viator Del Km. 0002,0;Almeri\u0301A",
    "iso:country":"ES",
    "sg:address":"Ctra Mami A Viator (del), Km. 0002,0",
    "sg:city":"Ca\u00e7ada De San Urbano",
    "sg:orig_category":"Cajas Y Embalajes De Madera",
    "sg:phone":"+34 950 62 60 53",
    "sg:postcode":"04120",
    "sg:province":"Almer\u00eda",
    "wof:name":"Envases Moya S.l.",
    "wof:placetype":"venue"
},
  "geometry": {"coordinates":[-2.3877189159,36.83644104],"type":"Point"}
}