{
  "type": "Feature",
  "properties": {
    "addr:full":"Pol Ind Siete, S/n Silla Valencia 46460",
    "addr:housenumber":"s / n",
    "addr:postcode":"46460",
    "iso:country":"ES",
    "sg:address":"Pol Ind Siete, S/n",
    "sg:city":"Silla",
    "sg:orig_category":"Fabricaci\u00d3n De Juguetes Autom\u00c1ticos",
    "sg:phone":"+34 961 21 21 48",
    "sg:postcode":"46460",
    "sg:province":"Valencia",
    "wof:name":"Magarin S.l.",
    "wof:placetype":"venue"
},
  "geometry": {"coordinates":[-0.417858988,39.3685531616],"type":"Point"}
}