{
  "type": "Feature",
  "properties": {
    "addr:full":"Calle de Maestro Nicolas, 54 Le\u00f3n Le\u00f3n 24005",
    "addr:housenumber":"54",
    "addr:postcode":"24005",
    "addr:street":"Calle De Maestro Nicolas;Leo\u0301N",
    "iso:country":"ES",
    "sg:address":"Calle de Maestro Nicolas, 54",
    "sg:city":"Le\u00f3n",
    "sg:orig_category":"Audiovisuales (producci\u00d3n, Edici\u00d3n, Realizaci\u00d3n)",
    "sg:phone":"+34 987 21 48 58",
    "sg:postcode":"24005",
    "sg:province":"Le\u00f3n",
    "wof:name":"Adiver S. L.",
    "wof:placetype":"venue"
},
  "geometry": {"coordinates":[-5.5663933754,42.587436676],"type":"Point"}
}