{
  "type": "Feature",
  "properties": {
    "iso:country":"ES",
    "sg:address":"Av Republica Argentina, 67",
    "sg:city":"Barcelona",
    "sg:orig_category":"Farmacias",
    "sg:phone":"+34 932 84 55 70",
    "sg:postcode":"08023",
    "sg:province":"Barcelona",
    "wof:name":"Rubies Mallol Maria Lourdes",
    "wof:placetype":"venue"
},
  "geometry": {"coordinates":[2.1459970474,41.4098472595],"type":"Point"}
}