{
  "type": "Feature",
  "properties": {
    "iso:country":"ES",
    "sg:address":"Calle de Subida Del Fronton, 16",
    "sg:city":"Santa Cruz De Campezo",
    "sg:orig_category":"Plomeros",
    "sg:phone":"+34 945 41 53 12",
    "sg:postcode":"01110",
    "sg:province":"\u00c1lava",
    "wof:name":"Araico Iba\u00f1ez Miguel Angel",
    "wof:placetype":"venue"
},
  "geometry": {"coordinates":[-2.3488740921,42.6701850891],"type":"Point"}
}