{
  "type": "Feature",
  "properties": {
    "addr:full":"Calle de Divino Morales, 15 Azuaga Badajoz 06920",
    "addr:housenumber":"15",
    "addr:postcode":"06920",
    "addr:street":"Calle De Divino Morales",
    "iso:country":"ES",
    "sg:address":"Calle de Divino Morales, 15",
    "sg:city":"Azuaga",
    "sg:orig_category":"Ebanister\u00cda",
    "sg:phone":"+34 924 89 20 36",
    "sg:postcode":"06920",
    "sg:province":"Badajoz",
    "wof:name":"Cordero Moruno Jose Antonio",
    "wof:placetype":"venue"
},
  "geometry": {"coordinates":[-5.6839675903,38.2620010376],"type":"Point"}
}