{
  "type": "Feature",
  "properties": {
    "addr:full":"Nieva, S/n Santa Maria Nieva Almer\u00eda 04693",
    "addr:housenumber":"s / n",
    "addr:postcode":"04693",
    "iso:country":"ES",
    "sg:address":"Nieva, S/n",
    "sg:city":"Santa Maria Nieva",
    "sg:orig_category":"Aceites Y Grasas Alimentarias (fabricaci\u00d3n, Al Por Mayor)",
    "sg:phone":"+34 950 13 71 56",
    "sg:postcode":"04693",
    "sg:province":"Almer\u00eda",
    "wof:name":"Avila Perez Francisco",
    "wof:placetype":"venue"
},
  "geometry": {"coordinates":[-2.0006389618,37.471321106],"type":"Point"}
}