{
  "type": "Feature",
  "properties": {
    "addr:full":"Carr Luis Vives, 13 Moncada Valencia 46113",
    "addr:housenumber":"13",
    "addr:postcode":"46113",
    "addr:street":"Carr Luis Vives",
    "iso:country":"ES",
    "sg:address":"Carr Luis Vives, 13",
    "sg:city":"Moncada",
    "sg:orig_category":"Asilos De Ancianos. Centros Privados",
    "sg:phone":"+34 961 39 25 58",
    "sg:postcode":"46113",
    "sg:province":"Valencia",
    "wof:name":"Asociacion Democratica Provincial De Jubilados Y Pensionistas De Valencia",
    "wof:placetype":"venue"
},
  "geometry": {"coordinates":[-0.4157994092,39.5063819885],"type":"Point"}
}