{
  "type": "Feature",
  "properties": {
    "addr:full":"Calle de San Salvador, 20 Tablero Las Palmas 35100",
    "addr:housenumber":"20",
    "addr:postcode":"35100",
    "addr:street":"Calle De San Salvador;Las",
    "iso:country":"ES",
    "sg:address":"Calle de San Salvador, 20",
    "sg:city":"Tablero",
    "sg:orig_category":"Bisuteros (fabricaci\u00d3n, Al Por Mayor)",
    "sg:phone":"+34 928 14 08 52",
    "sg:postcode":"35100",
    "sg:province":"Las Palmas",
    "wof:name":"Perez Garcia Manuel",
    "wof:placetype":"venue"
},
  "geometry": {"coordinates":[-15.6077814102,27.767118454],"type":"Point"}
}