{
  "type": "Feature",
  "properties": {
    "addr:full":"Calle de Abenda\u00d1o, 26 Vitoria-gasteiz \u00c1lava 01008",
    "addr:housenumber":"26",
    "addr:postcode":"01008",
    "addr:street":"Calle De Abendan\u0303O",
    "iso:country":"ES",
    "sg:address":"Calle de Abenda\u00d1o, 26",
    "sg:city":"Vitoria-gasteiz",
    "sg:orig_category":"Molduras, Junquillos, Listones Y Molduras Perforadas",
    "sg:phone":"+34 945 14 19 46",
    "sg:postcode":"01008",
    "sg:province":"\u00c1lava",
    "wof:name":"Union 84 S. A.",
    "wof:placetype":"venue"
},
  "geometry": {"coordinates":[-2.6833729744,42.8448066711],"type":"Point"}
}