{
  "type": "Feature",
  "properties": {
    "iso:country":"ES",
    "sg:address":"Carrer de Sugranyes, 2",
    "sg:city":"Barcelona",
    "sg:orig_category":"Arquitectos",
    "sg:phone":"+34 934 31 26 88",
    "sg:postcode":"08028",
    "sg:province":"Barcelona",
    "wof:name":"Fulleda Garganta Vicenc",
    "wof:placetype":"venue"
},
  "geometry": {"coordinates":[2.1271440983,41.3754081726],"type":"Point"}
}