{
  "type": "Feature",
  "properties": {
    "iso:country":"ES",
    "sg:address":"Calle de Leon Y Castillo, 421",
    "sg:city":"Palmas De Gran Canaria",
    "sg:orig_category":"Peritos Mar\u00cdtimos",
    "sg:phone":"+34 928 26 08 50",
    "sg:postcode":"35007",
    "sg:province":"Las Palmas",
    "wof:name":"Miller Y Compa\u00f1ia S.a.",
    "wof:placetype":"venue"
},
  "geometry": {"coordinates":[-15.4305677414,28.1383552551],"type":"Point"}
}