{
  "type": "Feature",
  "properties": {
    "addr:full":"Calle de Barrio Verde, 2 Alfaro La Rioja 26540",
    "addr:housenumber":"2",
    "addr:postcode":"26540",
    "addr:street":"Calle De Barrio Verde;Rioja",
    "iso:country":"ES",
    "sg:address":"Calle de Barrio Verde, 2",
    "sg:city":"Alfaro",
    "sg:orig_category":"Sindicatos De Trabajadores",
    "sg:phone":"+34 941 18 40 50",
    "sg:postcode":"26540",
    "sg:province":"La Rioja",
    "wof:name":"Union Comarcal De Comisiones Obreras",
    "wof:placetype":"venue"
},
  "geometry": {"coordinates":[-1.7488039732,42.1796760559],"type":"Point"}
}