{
  "type": "Feature",
  "properties": {
    "iso:country":"ES",
    "sg:address":"Carr Independencia, 13",
    "sg:city":"Burjassot",
    "sg:orig_category":"Empresas De Carpinter\u00cda De Madera",
    "sg:phone":"+34 963 63 64 78",
    "sg:postcode":"46100",
    "sg:province":"Valencia",
    "wof:name":"Gutierrez Gomez Miguel",
    "wof:placetype":"venue"
},
  "geometry": {"coordinates":[-0.4150649905,39.5094261169],"type":"Point"}
}