{
  "type": "Feature",
  "properties": {
    "iso:country":"ES",
    "sg:address":"Ctra. De Rios, S/n",
    "sg:city":"Vilardevos",
    "sg:orig_category":"Panader\u00cdas, Panader\u00cdas",
    "sg:phone":"+34 988 41 70 70",
    "sg:postcode":"32616",
    "sg:province":"Ourense",
    "wof:name":"Panaderia Alvaro S.l.",
    "wof:placetype":"venue"
},
  "geometry": {"coordinates":[-7.3127841949,41.9064903259],"type":"Point"}
}