{
  "type": "Feature",
  "properties": {
    "iso:country":"ES",
    "sg:address":"Calle de Ciudad Real, S/n",
    "sg:city":"Alcorcon",
    "sg:orig_category":"Negocio De Materiales De Construcci\u00d3n",
    "sg:phone":"+34 916 43 17 71",
    "sg:postcode":"28922",
    "sg:province":"Madrid",
    "wof:name":"Quijano Marcos Minervino",
    "wof:placetype":"venue"
},
  "geometry": {"coordinates":[-3.8292369843,40.3444595337],"type":"Point"}
}