{
  "type": "Feature",
  "properties": {
    "iso:country":"ES",
    "sg:address":"Calle de Juan Lorenzo Segura, 4",
    "sg:city":"Le\u00f3n",
    "sg:orig_category":"Muebles, Minoristas",
    "sg:phone":"+34 987 27 15 82",
    "sg:postcode":"24001",
    "sg:province":"Le\u00f3n",
    "sg:website":"www.paginasamarillas.es",
    "wof:name":"Tanalot Decoracion Sl",
    "wof:placetype":"venue"
},
  "geometry": {"coordinates":[-5.5767621994,42.597492218],"type":"Point"}
}