{
  "type": "Feature",
  "properties": {
    "iso:country":"ES",
    "sg:address":"Plaz Condes De Gamazo, 1",
    "sg:city":"Boecillo",
    "sg:orig_category":"Administraciones Regionales, Departamentales Y Locales",
    "sg:phone":"+34 983 54 67 00",
    "sg:postcode":"47151",
    "sg:province":"Valladolid",
    "sg:website":"www.ayto-boecillo.info",
    "wof:name":"Ayuntamiento De Boecillo",
    "wof:placetype":"venue"
},
  "geometry": {"coordinates":[-4.6995711327,41.5411376953],"type":"Point"}
}