{
  "type": "Feature",
  "properties": {
    "addr:full":"Carr Sant Antoni, 1 Mollerussa Lleida 25230",
    "addr:housenumber":"1",
    "addr:postcode":"25230",
    "addr:street":"Carr Sant Antoni",
    "iso:country":"ES",
    "sg:address":"Carr Sant Antoni, 1",
    "sg:city":"Mollerussa",
    "sg:orig_category":"Bancos",
    "sg:phone":"+34 973 71 18 33",
    "sg:postcode":"25230",
    "sg:province":"Lleida",
    "wof:name":"Recolta Ripoll Alvaro",
    "wof:placetype":"venue"
},
  "geometry": {"coordinates":[0.895506978,41.6241950989],"type":"Point"}
}