{
  "type": "Feature",
  "properties": {
    "addr:full":"Calle de Lope Gisbert, 26 Santiago Murcia 30800",
    "addr:housenumber":"26",
    "addr:postcode":"30800",
    "addr:street":"Calle De Lope Gisbert",
    "iso:country":"ES",
    "sg:address":"Calle de Lope Gisbert, 26",
    "sg:city":"Santiago",
    "sg:orig_category":"Molduras, Junquillos, Listones Y Molduras Perforadas",
    "sg:phone":"+34 968 46 89 62",
    "sg:postcode":"30800",
    "sg:province":"Murcia",
    "wof:name":"Mi\u00f1arro Gomez Jose",
    "wof:placetype":"venue"
},
  "geometry": {"coordinates":[-1.6905640364,37.680557251],"type":"Point"}
}