{
  "type": "Feature",
  "properties": {
    "addr:full":"Paseo De La Estacion, 4 Espinosa Henares Guadalajara 19292",
    "addr:housenumber":"4",
    "addr:postcode":"19292",
    "addr:street":"Paseo De La Estacion",
    "iso:country":"ES",
    "sg:address":"Paseo De La Estacion, 4",
    "sg:city":"Espinosa Henares",
    "sg:orig_category":"Aluminio Y Aleaciones (producci\u00d3n, Transformaci\u00d3n, Negocio)",
    "sg:phone":"+34 949 85 87 66",
    "sg:postcode":"19292",
    "sg:province":"Guadalajara",
    "wof:name":"Martinez Simon Arturo",
    "wof:placetype":"venue"
},
  "geometry": {"coordinates":[-3.0717039108,40.9046096802],"type":"Point"}
}