{
  "type": "Feature",
  "properties": {
    "addr:full":"Calle de Vicente Baldovi, 1 Palmar Valencia 46012",
    "addr:housenumber":"1",
    "addr:postcode":"46012",
    "addr:street":"Calle De Vicente Baldovi",
    "iso:country":"ES",
    "sg:address":"Calle de Vicente Baldovi, 1",
    "sg:city":"Palmar",
    "sg:orig_category":"Agricultura: Abastecimiento Y Cosechado (negocio)",
    "sg:phone":"+34 961 62 01 08",
    "sg:postcode":"46012",
    "sg:province":"Valencia",
    "wof:name":"Cooperativa Valenciana De Agricultores Del Palmar",
    "wof:placetype":"venue"
},
  "geometry": {"coordinates":[-0.3178429902,39.3111686707],"type":"Point"}
}