{
  "type": "Feature",
  "properties": {
    "addr:full":"Calle de Cantarranas, S/n Alhaurin El Grande M\u00e1laga 29120",
    "addr:housenumber":"s",
    "addr:postcode":"29120",
    "addr:street":"Calle De Cantarranas;/ N",
    "iso:country":"ES",
    "sg:address":"Calle de Cantarranas, S/n",
    "sg:city":"Alhaurin El Grande",
    "sg:orig_category":"M\u00c1rmoles, Granitos Y Piedras Naturales",
    "sg:phone":"+34 952 49 10 86",
    "sg:postcode":"29120",
    "sg:province":"M\u00e1laga",
    "wof:name":"Farfan Morales Jose",
    "wof:placetype":"venue"
},
  "geometry": {"coordinates":[-4.68810606,36.643989563],"type":"Point"}
}