{
  "type": "Feature",
  "properties": {
    "addr:full":"Rua Mendez Nu\u00d1ez, 28 Marin Pontevedra 36900",
    "addr:housenumber":"28",
    "addr:postcode":"36900",
    "addr:street":"Rua Mendez Nun\u0303Ez",
    "iso:country":"ES",
    "sg:address":"Rua Mendez Nu\u00d1ez, 28",
    "sg:city":"Marin",
    "sg:orig_category":"Ropa Para Se\u00d1oras (al Por Menor)",
    "sg:phone":"+34 986 88 43 98",
    "sg:postcode":"36900",
    "sg:province":"Pontevedra",
    "wof:name":"Xanela C.b.",
    "wof:placetype":"venue"
},
  "geometry": {"coordinates":[-8.7015333176,42.3926544189],"type":"Point"}
}