{
  "type": "Feature",
  "properties": {
    "iso:country":"ES",
    "sg:address":"Calle de Leones, 6",
    "sg:city":"Montejicar",
    "sg:orig_category":"Electrodom\u00c9sticos (al Por Menor)",
    "sg:phone":"+34 958 39 34 98",
    "sg:postcode":"18561",
    "sg:province":"Granada",
    "wof:name":"Josemart Electronica S.l.",
    "wof:placetype":"venue"
},
  "geometry": {"coordinates":[-3.5051450729,37.571182251],"type":"Point"}
}