{
  "type": "Feature",
  "properties": {
    "addr:full":"Calle de Prado Sancho, 21 Avila \u00c1vila 05005",
    "addr:housenumber":"21",
    "addr:postcode":"05005",
    "addr:street":"Calle De Prado Sancho;A\u0301Vila",
    "iso:country":"ES",
    "sg:address":"Calle de Prado Sancho, 21",
    "sg:city":"Avila",
    "sg:orig_category":"Distribuci\u00d3n De Petr\u00d3leo Y Derivados",
    "sg:phone":"+34 920 22 39 19",
    "sg:postcode":"05005",
    "sg:province":"\u00c1vila",
    "wof:name":"Carburantes Avila S.l.",
    "wof:placetype":"venue"
},
  "geometry": {"coordinates":[-4.6967849731,40.661441803],"type":"Point"}
}