{
  "type": "Feature",
  "properties": {
    "addr:full":"Calle de Conde Ofalia, 9 Almeria Almer\u00eda 04001",
    "addr:housenumber":"9",
    "addr:postcode":"04001",
    "addr:street":"Calle De Conde Ofalia",
    "iso:country":"ES",
    "sg:address":"Calle de Conde Ofalia, 9",
    "sg:city":"Almeria",
    "sg:orig_category":"Cl\u00cdnicas Dentales",
    "sg:phone":"+34 950 23 08 05",
    "sg:postcode":"04001",
    "sg:province":"Almer\u00eda",
    "wof:name":"Abellan Garcia Antonio",
    "wof:placetype":"venue"
},
  "geometry": {"coordinates":[-2.463943,36.838329],"type":"Point"}
}