{
  "type": "Feature",
  "properties": {
    "iso:country":"ES",
    "sg:address":"Calle de Lope De Irigoyen, 10",
    "sg:city":"Irun",
    "sg:orig_category":"Agencias De Aduana",
    "sg:phone":"+34 943 61 10 04",
    "sg:postcode":"20301",
    "sg:province":"Guip\u00f9zcoa",
    "wof:name":"Comisionistas De Aduanas Y Transportes Iruneses, S.a. (catir)",
    "wof:placetype":"venue"
},
  "geometry": {"coordinates":[7.5249300003,51.0156097412],"type":"Point"}
}