{
  "type": "Feature",
  "properties": {
    "iso:country":"ES",
    "sg:address":"Calle de Heroes Del Tollo, 17",
    "sg:city":"Utiel",
    "sg:orig_category":"Electricidad Veh\u00cdculo",
    "sg:phone":"+34 962 17 21 57",
    "sg:postcode":"46300",
    "sg:province":"Valencia",
    "wof:name":"Latorre Tello Rafael",
    "wof:placetype":"venue"
},
  "geometry": {"coordinates":[-1.2079160213,39.5666007996],"type":"Point"}
}