{
  "type": "Feature",
  "properties": {
    "iso:country":"ES",
    "sg:address":"Calle de Miguel Bueno, 4",
    "sg:city":"Fuengirola",
    "sg:classifiers":[
        {
            "category":"Taxi",
            "type":"Transportation"
        }
    ],
    "sg:phone":"+34 952 47 33 44",
    "sg:postcode":"29640",
    "sg:province":"M\u00e1laga",
    "wof:name":"Lopez Campos Angel",
    "wof:placetype":"venue"
},
  "geometry": {"coordinates":[-4.6256890297,36.5458374023],"type":"Point"}
}