{
  "type": "Feature",
  "properties": {
    "addr:full":"Carr Coral, 9 Port D'alcudia Islas Baleares 07410",
    "addr:housenumber":"9",
    "addr:postcode":"07410",
    "addr:street":"Carr Coral",
    "iso:country":"ES",
    "sg:address":"Carr Coral, 9",
    "sg:city":"Port D'alcudia",
    "sg:orig_category":"Restaurantes",
    "sg:phone":"+34 971 54 79 19",
    "sg:postcode":"07410",
    "sg:province":"Islas Baleares",
    "wof:name":"Meng Lee's S.l.",
    "wof:placetype":"venue"
},
  "geometry": {"coordinates":[3.1312530041,39.84349823],"type":"Point"}
}