{
  "type": "Feature",
  "properties": {
    "addr:full":"Lazo, 8 Pozo Alcon Ja\u00e9n 23485",
    "addr:housenumber":"8",
    "addr:postcode":"23485",
    "addr:street":"Lazo;Alcon Jae\u0301N",
    "iso:country":"ES",
    "sg:address":"Lazo, 8",
    "sg:city":"Pozo Alcon",
    "sg:orig_category":"Carnicer\u00cdas, Carnicer\u00cdas",
    "sg:phone":"+34 953 71 82 66",
    "sg:postcode":"23485",
    "sg:province":"Ja\u00e9n",
    "wof:name":"Cruz Fuertes Amable",
    "wof:placetype":"venue"
},
  "geometry": {"coordinates":[-2.9345779419,37.7048301697],"type":"Point"}
}