{
  "type": "Feature",
  "properties": {
    "addr:full":"Avda Coru\u00d1a (da), 97 Lugo Lugo 27003",
    "addr:housenumber":"97",
    "addr:postcode":"27003",
    "addr:street":"Avda Corun\u0303A Da",
    "iso:country":"ES",
    "sg:address":"Avda Coru\u00d1a (da), 97",
    "sg:city":"Lugo",
    "sg:orig_category":"Dietistas",
    "sg:phone":"+34 982 20 09 68",
    "sg:postcode":"27003",
    "sg:province":"Lugo",
    "wof:name":"Lamas Conde Mercedes",
    "wof:placetype":"venue"
},
  "geometry": {"coordinates":[-7.5612688065,43.0179405212],"type":"Point"}
}