{
  "type": "Feature",
  "properties": {
    "addr:full":"Calle de Donostia-san Sebastian, 15 Errenteria Guip\u00f9zcoa 20100",
    "addr:postcode":"15;20100",
    "addr:street":"Calle De;Guipu\u0300Zcoa",
    "iso:country":"ES",
    "sg:address":"Calle de Donostia-san Sebastian, 15",
    "sg:city":"Errenteria",
    "sg:orig_category":"Asociaciones Y Clubs Deportivos",
    "sg:phone":"+34 943 01 98 19",
    "sg:postcode":"20100",
    "sg:province":"Guip\u00f9zcoa",
    "wof:name":"Gimnasio Arin C.b.",
    "wof:placetype":"venue"
},
  "geometry": {"coordinates":[-1.9032919407,43.3153762817],"type":"Point"}
}