{
  "type": "Feature",
  "properties": {
    "addr:full":"Calle de Torregorda, 17 Sevilla Sevilla 41016",
    "addr:housenumber":"17",
    "addr:postcode":"41016",
    "addr:street":"Calle De Torregorda",
    "iso:country":"ES",
    "sg:address":"Calle de Torregorda, 17",
    "sg:city":"Sevilla",
    "sg:orig_category":"Muebles Y Accesorios Para Cocinas Y Cuartos De Ba\u00d1o (al Por Menor)",
    "sg:phone":"+34 954 40 55 58",
    "sg:postcode":"41016",
    "sg:province":"Sevilla",
    "wof:name":"Bercocina S.l.",
    "wof:placetype":"venue"
},
  "geometry": {"coordinates":[-5.9039487839,37.3842201233],"type":"Point"}
}