{
  "type": "Feature",
  "properties": {
    "addr:full":"Amaya-amaia, 33 Iru\u00f1a Navarra 31004",
    "addr:housenumber":"33",
    "addr:postcode":"31004",
    "addr:street":"Amaya-Amaia",
    "iso:country":"ES",
    "sg:address":"Amaya-amaia, 33",
    "sg:city":"Iru\u00f1a",
    "sg:orig_category":"Ropa Y Art\u00cdculos Pre",
    "sg:phone":"+34 948 23 50 77",
    "sg:postcode":"31004",
    "sg:province":"Navarra",
    "wof:name":"Cochecitos Perez S.l.",
    "wof:placetype":"venue"
},
  "geometry": {"coordinates":[-1.6344319582,42.8102798462],"type":"Point"}
}