{
  "type": "Feature",
  "properties": {
    "addr:full":"Poligono Industrial, S/n Pol. Ind. Onzonilla Le\u00f3n 24231",
    "addr:postcode":"24231",
    "addr:street":"Industrial S / N Pol. Ind. Onzonilla Leo\u0301N",
    "iso:country":"ES",
    "sg:address":"Poligono Industrial, S/n",
    "sg:city":"Pol. Ind. Onzonilla",
    "sg:orig_category":"Maquinaria Para Industrias Diversas",
    "sg:phone":"+34 987 27 90 21",
    "sg:postcode":"24231",
    "sg:province":"Le\u00f3n",
    "wof:name":"Leonesa De Conductos S.l.",
    "wof:placetype":"venue"
},
  "geometry": {"coordinates":[-5.5844950676,42.5004310608],"type":"Point"}
}