{
  "type": "Feature",
  "properties": {
    "iso:country":"ES",
    "sg:address":"Pg Maragall, 334",
    "sg:city":"Barcelona",
    "sg:orig_category":"Comercio, Reparaci\u00d3n De Motocicletas, Bicicletas Y Piezas Sueltas",
    "sg:phone":"+34 934 20 32 96",
    "sg:postcode":"08031",
    "sg:province":"Barcelona",
    "wof:name":"Endurance Superbike S.l.",
    "wof:placetype":"venue"
},
  "geometry": {"coordinates":[2.1674830914,41.4277038574],"type":"Point"}
}