{
  "type": "Feature",
  "properties": {
    "addr:full":"Calle de Metalurgia, 63 Sevilla Sevilla 41007",
    "addr:housenumber":"63",
    "addr:postcode":"41007",
    "addr:street":"Calle De Metalurgia",
    "iso:country":"ES",
    "sg:address":"Calle de Metalurgia, 63",
    "sg:city":"Sevilla",
    "sg:orig_category":"Alquiler De Veh\u00cdculos: Turismos Y Utilitarios",
    "sg:phone":"+34 954 35 32 00",
    "sg:postcode":"41007",
    "sg:province":"Sevilla",
    "sg:website":"www.multirenting.net",
    "wof:name":"Occidental Rent A Car S.l.",
    "wof:placetype":"venue"
},
  "geometry": {"coordinates":[-5.9548311234,37.4120178223],"type":"Point"}
}