{
  "type": "Feature",
  "properties": {
    "addr:full":"Calle de Lledoner, 10 Meliana Valencia 46133",
    "addr:housenumber":"10",
    "addr:postcode":"46133",
    "addr:street":"Calle De Lledoner",
    "iso:country":"ES",
    "sg:address":"Calle de Lledoner, 10",
    "sg:city":"Meliana",
    "sg:orig_category":"Molduras, Junquillos, Listones Y Molduras Perforadas",
    "sg:phone":"+34 961 49 33 21",
    "sg:postcode":"46133",
    "sg:province":"Valencia",
    "wof:name":"Domenech Marti Federico",
    "wof:placetype":"venue"
},
  "geometry": {"coordinates":[-0.3500489891,39.527381897],"type":"Point"}
}