{
  "type": "Feature",
  "properties": {
    "addr:full":"C/ Parets, 15 Celra Girona 17460",
    "addr:housenumber":"15",
    "addr:postcode":"17460",
    "addr:street":"C / Parets",
    "iso:country":"ES",
    "sg:address":"C/ Parets, 15",
    "sg:city":"Celra",
    "sg:orig_category":"Producci\u00d3n De Abonos Y De Fertilizantes",
    "sg:phone":"+34 972 49 20 86",
    "sg:postcode":"17460",
    "sg:province":"Girona",
    "wof:name":"Coll Pages Angel",
    "wof:placetype":"venue"
},
  "geometry": {"coordinates":[2.8782980442,42.0279083252],"type":"Point"}
}