{
  "type": "Feature",
  "properties": {
    "addr:full":"Calle de Juan Xxiii, 12 Tavernes Blanques Valencia 46016",
    "addr:housenumber":"12",
    "addr:postcode":"46016",
    "addr:street":"Calle De Juan Xxiii",
    "iso:country":"ES",
    "sg:address":"Calle de Juan Xxiii, 12",
    "sg:city":"Tavernes Blanques",
    "sg:orig_category":"Muebles Y Accesorios Para Cocinas Y Cuartos De Ba\u00d1o (al Por Menor)",
    "sg:phone":"+34 963 17 13 17",
    "sg:postcode":"46016",
    "sg:province":"Valencia",
    "wof:name":"Lizan Nu\u00f1ez Sebastian",
    "wof:placetype":"venue"
},
  "geometry": {"coordinates":[-0.3616710007,39.5079917908],"type":"Point"}
}