{
  "type": "Feature",
  "properties": {
    "addr:full":"Carrer de Lepanto, 9 Cambrils Tarragona 43850",
    "addr:housenumber":"9",
    "addr:postcode":"43850",
    "addr:street":"Carrer De Lepanto",
    "iso:country":"ES",
    "sg:address":"Carrer de Lepanto, 9",
    "sg:city":"Cambrils",
    "sg:orig_category":"Navegaci\u00d3n (equipos Fluviales)",
    "sg:phone":"+34 977 79 42 86",
    "sg:postcode":"43850",
    "sg:province":"Tarragona",
    "wof:name":"Morell Rom Juan",
    "wof:placetype":"venue"
},
  "geometry": {"coordinates":[1.0598109961,41.0663414001],"type":"Point"}
}