{
  "type": "Feature",
  "properties": {
    "addr:full":"Poli Las Capellanias, S/n Caceres C\u00e1ceres 10005",
    "addr:housenumber":"s",
    "addr:postcode":"10005",
    "addr:street":"/ N;Ca\u0301Ceres",
    "iso:country":"ES",
    "sg:address":"Poli Las Capellanias, S/n",
    "sg:city":"Caceres",
    "sg:orig_category":"Madera Para Construcci\u00d3n E Industria",
    "sg:phone":"+34 927 23 02 83",
    "sg:postcode":"10005",
    "sg:province":"C\u00e1ceres",
    "wof:name":"Maderas Tovar Feijoo S.a.",
    "wof:placetype":"venue"
},
  "geometry": {"coordinates":[-6.5341739655,39.4675254822],"type":"Point"}
}