{
  "type": "Feature",
  "properties": {
    "iso:country":"ES",
    "sg:address":"Calle de Sansomendi, 5",
    "sg:city":"Vitoria-gasteiz",
    "sg:orig_category":"Florister\u00cdas",
    "sg:phone":"+34 945 22 49 01",
    "sg:postcode":"01010",
    "sg:province":"\u00c1lava",
    "wof:name":"Garcia Villanueva Maria Yolanda",
    "wof:placetype":"venue"
},
  "geometry": {"coordinates":[-2.6990358829,42.8548164368],"type":"Point"}
}