{
  "type": "Feature",
  "properties": {
    "addr:full":"Av Catalunya, 2 Amposta Tarragona 43870",
    "addr:housenumber":"2",
    "addr:postcode":"43870",
    "addr:street":"Av Catalunya",
    "iso:country":"ES",
    "sg:address":"Av Catalunya, 2",
    "sg:city":"Amposta",
    "sg:orig_category":"Ense\u00d1anza, Formaci\u00d3n Profesional: Aprendizaje",
    "sg:phone":"+34 977 70 53 37",
    "sg:postcode":"43870",
    "sg:province":"Tarragona",
    "wof:name":"Centre De Telecomunicaciones De Catalunya",
    "wof:placetype":"venue"
},
  "geometry": {"coordinates":[0.5789189935,40.7040367126],"type":"Point"}
}