{
  "type": "Feature",
  "properties": {
    "iso:country":"ES",
    "sg:address":"Plaz Espa\u00d1a, 5",
    "sg:city":"Guare\u00f1a",
    "sg:orig_category":"Quincaller\u00cda (al Por Menor)",
    "sg:phone":"+34 924 35 01 08",
    "sg:postcode":"06470",
    "sg:province":"Badajoz",
    "wof:name":"Perez Monago Manuel",
    "wof:placetype":"venue"
},
  "geometry": {"coordinates":[-6.1024541855,38.8637237549],"type":"Point"}
}