{
  "type": "Feature",
  "properties": {
    "addr:full":"Av Joan Miro, 17 Palma Islas Baleares 07014",
    "addr:housenumber":"17",
    "addr:postcode":"07014",
    "addr:street":"Av Joan Miro",
    "iso:country":"ES",
    "sg:address":"Av Joan Miro, 17",
    "sg:city":"Palma",
    "sg:orig_category":"M\u00c9dicos: Ginecolog\u00cda M\u00c9dica, Obstetricia",
    "sg:phone":"+34 971 73 30 50",
    "sg:postcode":"07014",
    "sg:province":"Islas Baleares",
    "wof:name":"Morato Vives Rafael",
    "wof:placetype":"venue"
},
  "geometry": {"coordinates":[2.6262431145,39.5641136169],"type":"Point"}
}