{
  "type": "Feature",
  "properties": {
    "iso:country":"ES",
    "sg:address":"Av Abat Marcet, 227",
    "sg:city":"Terrassa",
    "sg:orig_category":"Artes Gr\u00c1ficas, Artes Pl\u00c1sticas (curso)",
    "sg:phone":"+34 937 88 28 01",
    "sg:postcode":"08225",
    "sg:province":"Barcelona",
    "wof:name":"Rimeba S.l.",
    "wof:placetype":"venue"
},
  "geometry": {"coordinates":[2.0083520412,41.5745887756],"type":"Point"}
}