{
  "type": "Feature",
  "properties": {
    "iso:country":"ES",
    "sg:address":"Calle de Iglesia De (la), S/n",
    "sg:city":"Uleila Del Campo",
    "sg:orig_category":"Administraciones Regionales, Departamentales Y Locales",
    "sg:phone":"+34 950 36 31 30",
    "sg:postcode":"04279",
    "sg:province":"Almer\u00eda",
    "wof:name":"Ayuntamiento De Uleila Del Campo",
    "wof:placetype":"venue"
},
  "geometry": {"coordinates":[-2.202953577,37.1856575012],"type":"Point"}
}