{
  "type": "Feature",
  "properties": {
    "addr:full":"Carrer de Sant Agusti, 31 Alcanar Tarragona 43530",
    "addr:housenumber":"31",
    "addr:postcode":"43530",
    "addr:street":"Carrer De Sant Agusti",
    "iso:country":"ES",
    "sg:address":"Carrer de Sant Agusti, 31",
    "sg:city":"Alcanar",
    "sg:orig_category":"Pescader\u00cdas (al Por Menor)",
    "sg:phone":"+34 977 73 00 48",
    "sg:postcode":"43530",
    "sg:province":"Tarragona",
    "wof:name":"Beltran Matamoros Antonio",
    "wof:placetype":"venue"
},
  "geometry": {"coordinates":[0.4786509871,40.545425415],"type":"Point"}
}