{
  "type": "Feature",
  "properties": {
    "addr:full":"Trss Carril, 2 Girona Girona 17001",
    "addr:housenumber":"2",
    "addr:postcode":"17001",
    "addr:street":"Carril",
    "iso:country":"ES",
    "sg:address":"Trss Carril, 2",
    "sg:city":"Girona",
    "sg:orig_category":"Caf\u00c9s, Bares, Cervecer\u00cdas",
    "sg:phone":"+34 972 21 21 06",
    "sg:postcode":"17001",
    "sg:province":"Girona",
    "wof:name":"La Maduixa-alvarez Alvarez C.b.",
    "wof:placetype":"venue"
},
  "geometry": {"coordinates":[2.8187448978,41.9808616638],"type":"Point"}
}