{
  "type": "Feature",
  "properties": {
    "iso:country":"ES",
    "sg:address":"Grup Parque Monteflor, S/n",
    "sg:city":"Sevilla",
    "sg:classifiers":[
        {
            "category":"Personal",
            "subcategory":"Barber",
            "type":"Services"
        }
    ],
    "sg:phone":"+34 954 43 83 14",
    "sg:postcode":"41008",
    "sg:province":"Sevilla",
    "sg:tags":[
        "caballeros",
        "de",
        "peluqueros"
    ],
    "wof:name":"Medrano Carmona Enrique",
    "wof:placetype":"venue"
},
  "geometry": {"coordinates":[-5.9759988785,37.4043693542],"type":"Point"}
}