{
  "type": "Feature",
  "properties": {
    "addr:full":"Calle de Severo Ochoa, S/n Chiclana De La Frontera C\u00e1diz 11130",
    "addr:housenumber":"s / n",
    "addr:postcode":"11130",
    "addr:street":"Calle De Severo Ochoa",
    "iso:country":"ES",
    "sg:address":"Calle de Severo Ochoa, S/n",
    "sg:city":"Chiclana De La Frontera",
    "sg:orig_category":"Ebanistas Y Talladores De Muebles Y Objetos De Arte",
    "sg:phone":"+34 956 40 04 98",
    "sg:postcode":"11130",
    "sg:province":"C\u00e1diz",
    "wof:name":"Bioreciclaje De Cadiz S.a.",
    "wof:placetype":"venue"
},
  "geometry": {"coordinates":[-6.1546092033,36.4254341125],"type":"Point"}
}