{
  "type": "Feature",
  "properties": {
    "addr:full":"Calle de Angel Lozano, 18 Alacant Alicante 03001",
    "addr:housenumber":"18",
    "addr:postcode":"03001",
    "addr:street":"Calle De Angel Lozano",
    "iso:country":"ES",
    "sg:address":"Calle de Angel Lozano, 18",
    "sg:city":"Alacant",
    "sg:orig_category":"Agencias Y Agentes Comerciales, Representantes",
    "sg:phone":"+34 965 21 22 04",
    "sg:postcode":"03001",
    "sg:province":"Alicante",
    "wof:name":"Garcia Ribelles Eduardo",
    "wof:placetype":"venue"
},
  "geometry": {"coordinates":[-0.4886119962,38.3466148376],"type":"Point"}
}