{
  "type": "Feature",
  "properties": {
    "addr:full":"Calle de Abu Zeyan, 11 Denia Alicante 03700",
    "addr:housenumber":"11",
    "addr:postcode":"03700",
    "addr:street":"Calle De Abu Zeyan",
    "iso:country":"ES",
    "sg:address":"Calle de Abu Zeyan, 11",
    "sg:city":"Denia",
    "sg:orig_category":"Centros Empresariales",
    "sg:phone":"+34 965 78 01 87",
    "sg:postcode":"03700",
    "sg:province":"Alicante",
    "wof:name":"Aqualia Gestion Integral Del Agua S.a.",
    "wof:placetype":"venue"
},
  "geometry": {"coordinates":[0.0840215012,38.8309745789],"type":"Point"}
}