{
  "type": "Feature",
  "properties": {
    "addr:full":"Av Doctor Vilaseca, 1 Reus Tarragona 43202",
    "addr:housenumber":"1",
    "addr:postcode":"43202",
    "addr:street":"Av Doctor Vilaseca",
    "iso:country":"ES",
    "sg:address":"Av Doctor Vilaseca, 1",
    "sg:city":"Reus",
    "sg:orig_category":"M\u00c9dicos: Psiquiatr\u00cda",
    "sg:phone":"+34 977 32 24 58",
    "sg:postcode":"43202",
    "sg:province":"Tarragona",
    "wof:name":"Roig Panisello Jose Luis",
    "wof:placetype":"venue"
},
  "geometry": {"coordinates":[1.1013640165,41.1563911438],"type":"Point"}
}