{
  "type": "Feature",
  "properties": {
    "iso:country":"ES",
    "sg:address":"Calle de Yebenes, 70",
    "sg:city":"Madrid",
    "sg:orig_category":"Ense\u00d1anza: Idiomas",
    "sg:phone":"+34 917 17 59 75",
    "sg:postcode":"28047",
    "sg:province":"Madrid",
    "wof:name":"Ians School S.l.",
    "wof:placetype":"venue"
},
  "geometry": {"coordinates":[-3.753704071,40.3938179016],"type":"Point"}
}