{
  "type": "Feature",
  "properties": {
    "iso:country":"ES",
    "sg:address":"Pase Rihuete (del), 45",
    "sg:city":"Puerto Mazarron",
    "sg:orig_category":"Inmobiliaria (agencias)",
    "sg:phone":"+34 968 15 37 75",
    "sg:postcode":"30860",
    "sg:province":"Murcia",
    "wof:name":"Arbajo S.l.",
    "wof:placetype":"venue"
},
  "geometry": {"coordinates":[-1.2543795109,37.5705337524],"type":"Point"}
}