{
  "type": "Feature",
  "properties": {
    "iso:country":"ES",
    "sg:address":"Calle de Madrid, 74",
    "sg:city":"Getafe",
    "sg:orig_category":"Servicios Gsm",
    "sg:phone":"+34 916 65 11 75",
    "sg:postcode":"28902",
    "sg:province":"Madrid",
    "wof:name":"Estudios Integrales De Comunicacion S.l.",
    "wof:placetype":"venue"
},
  "geometry": {"coordinates":[-3.7285780907,40.3096809387],"type":"Point"}
}