{
  "type": "Feature",
  "properties": {
    "iso:country":"ES",
    "sg:address":"Plaz Andalucia (de), 1",
    "sg:city":"Muela",
    "sg:orig_category":"Estancos",
    "sg:phone":"+34 956 13 89 00",
    "sg:postcode":"11689",
    "sg:province":"C\u00e1diz",
    "wof:name":"Salguero Rodriguez Francisca",
    "wof:placetype":"venue"
},
  "geometry": {"coordinates":[-5.4073238373,36.9342803955],"type":"Point"}
}