{
  "type": "Feature",
  "properties": {
    "iso:country":"ES",
    "sg:address":"Calle de Santa Alicia, 7",
    "sg:city":"Madrid",
    "sg:orig_category":"Artes Gr\u00c1ficas, Artes Pl\u00c1sticas (curso)",
    "sg:phone":"+34 914 77 38 64",
    "sg:postcode":"28053",
    "sg:province":"Madrid",
    "wof:name":"Imprenta Sanchez Sandoval S.l.",
    "wof:placetype":"venue"
},
  "geometry": {"coordinates":[-3.6673190594,40.3878440857],"type":"Point"}
}