{
  "type": "Feature",
  "properties": {
    "addr:full":"Calle de Carrer Del Mur, 1 Alzira Valencia 46600",
    "addr:housenumber":"1",
    "addr:postcode":"46600",
    "addr:street":"Calle De Carrer Del Mur",
    "iso:country":"ES",
    "sg:address":"Calle de Carrer Del Mur, 1",
    "sg:city":"Alzira",
    "sg:orig_category":"Aperitivos (fabricaci\u00d3n Y Al Por Mayor)",
    "sg:phone":"+34 962 40 10 55",
    "sg:postcode":"46600",
    "sg:province":"Valencia",
    "wof:name":"Grefusa S.l.",
    "wof:placetype":"venue"
},
  "geometry": {"coordinates":[-0.4030939937,39.1432685852],"type":"Point"}
}