{
  "type": "Feature",
  "properties": {
    "addr:full":"Plaz Nueva, 2 Bilbao Vizcaya 48005",
    "addr:housenumber":"2",
    "addr:postcode":"48005",
    "addr:street":"Plaz Nueva",
    "iso:country":"ES",
    "sg:address":"Plaz Nueva, 2",
    "sg:city":"Bilbao",
    "sg:orig_category":"Complementos De Vestir (al Por Menor)",
    "sg:phone":"+34 944 15 28 59",
    "sg:postcode":"48005",
    "sg:province":"Vizcaya",
    "sg:website":"www.skunksunk.com",
    "wof:name":"B Y Zz Hectic S.l.",
    "wof:placetype":"venue"
},
  "geometry": {"coordinates":[-2.9255690575,43.2587852478],"type":"Point"}
}