{
  "type": "Feature",
  "properties": {
    "iso:country":"ES",
    "sg:address":"Carrer de Tarragona, 1",
    "sg:city":"Senia",
    "sg:orig_category":"Cajas De Ahorro",
    "sg:phone":"+34 977 71 33 32",
    "sg:postcode":"43560",
    "sg:province":"Tarragona",
    "wof:name":"Caixa D'estalvis I Pensions De Barcelona",
    "wof:placetype":"venue"
},
  "geometry": {"coordinates":[0.2824349999,40.6357192993],"type":"Point"}
}