{
  "type": "Feature",
  "properties": {
    "addr:full":"Carrer de Josep Aparici, 14 Sabadell Barcelona 08208",
    "addr:housenumber":"14",
    "addr:postcode":"08208",
    "addr:street":"Carrer De Josep Aparici",
    "iso:country":"ES",
    "sg:address":"Carrer de Josep Aparici, 14",
    "sg:city":"Sabadell",
    "sg:orig_category":"Peluquer\u00cdas, Peluquer\u00cda Mixta",
    "sg:phone":"+34 937 17 91 10",
    "sg:postcode":"08208",
    "sg:province":"Barcelona",
    "wof:name":"Quilon Espallardo Monica",
    "wof:placetype":"venue"
},
  "geometry": {"coordinates":[2.1025280952,41.5595779419],"type":"Point"}
}