{
  "type": "Feature",
  "properties": {
    "addr:full":"Calle de Peral, 10 Marbella M\u00e1laga 29600",
    "addr:housenumber":"10",
    "addr:postcode":"29600",
    "addr:street":"Calle De Peral;Ma\u0301Laga",
    "iso:country":"ES",
    "sg:address":"Calle de Peral, 10",
    "sg:city":"Marbella",
    "sg:orig_category":"Inversiones",
    "sg:phone":"+34 952 86 89 23",
    "sg:postcode":"29600",
    "sg:province":"M\u00e1laga",
    "wof:name":"Mariscal Ruiz Mercedes",
    "wof:placetype":"venue"
},
  "geometry": {"coordinates":[-4.8860788345,36.5107727051],"type":"Point"}
}