{
  "type": "Feature",
  "properties": {
    "addr:full":"Carrer de Enten\u00c7a, 128 Barcelona Barcelona 08015",
    "addr:housenumber":"128",
    "addr:postcode":"08015",
    "addr:street":"Carrer De Entenc\u0327A",
    "iso:country":"ES",
    "sg:address":"Carrer de Enten\u00c7a, 128",
    "sg:city":"Barcelona",
    "sg:orig_category":"Agencias De Viajes",
    "sg:phone":"+34 932 26 88 92",
    "sg:postcode":"08015",
    "sg:province":"Barcelona",
    "wof:name":"Viatges Eslavis S.l.",
    "wof:placetype":"venue"
},
  "geometry": {"coordinates":[2.1482689381,41.3815307617],"type":"Point"}
}