{
  "type": "Feature",
  "properties": {
    "addr:full":"Calle de Carolinas, 7 Madrid Madrid 28039",
    "addr:housenumber":"7",
    "addr:postcode":"madrid;28039",
    "addr:street":"Calle De Carolinas",
    "iso:country":"ES",
    "sg:address":"Calle de Carolinas, 7",
    "sg:city":"Madrid",
    "sg:orig_category":"Empresarios",
    "sg:phone":"+34 915 53 33 62",
    "sg:postcode":"28039",
    "sg:province":"Madrid",
    "wof:name":"Pryser S.l.",
    "wof:placetype":"venue"
},
  "geometry": {"coordinates":[-3.7040839195,40.4511299133],"type":"Point"}
}