{
  "type": "Feature",
  "properties": {
    "iso:country":"ES",
    "sg:address":"Calle de Viteri, 34",
    "sg:city":"Errenteria",
    "sg:orig_category":"\u00d3ptica: Instrumentos (fabricaci\u00d3n)",
    "sg:phone":"+34 943 52 67 53",
    "sg:postcode":"20100",
    "sg:province":"Guip\u00f9zcoa",
    "wof:name":"Eli Urkia Gogortza",
    "wof:placetype":"venue"
},
  "geometry": {"coordinates":[-1.9022339582,43.3140411377],"type":"Point"}
}