{
  "type": "Feature",
  "properties": {
    "iso:country":"ES",
    "sg:address":"Carr Pintor Claros, 27",
    "sg:city":"Sueca",
    "sg:orig_category":"Promotores Constructores",
    "sg:phone":"+34 961 70 20 59",
    "sg:postcode":"46410",
    "sg:province":"Valencia",
    "wof:name":"Dabesco S. L.",
    "wof:placetype":"venue"
},
  "geometry": {"coordinates":[-0.3075560033,39.199344635],"type":"Point"}
}