{
  "type": "Feature",
  "properties": {
    "iso:country":"ES",
    "sg:address":"Calle de Saltona, 19",
    "sg:city":"Argana Alta",
    "sg:orig_category":"Arreglo E Instalaci\u00d3n De Caf\u00c9s, Hoteles Y Restaurantes",
    "sg:phone":"+34 928 80 77 55",
    "sg:postcode":"35500",
    "sg:province":"Las Palmas",
    "wof:name":"Paycan S.l.",
    "wof:placetype":"venue"
},
  "geometry": {"coordinates":[-13.5692892075,28.9773769379],"type":"Point"}
}