{
  "type": "Feature",
  "properties": {
    "addr:full":"Calle de Gonzalo Antonio Serrano, S/n Cordoba C\u00f3rdoba 14014",
    "addr:housenumber":"/ n",
    "addr:postcode":"14014",
    "addr:street":"Calle De Gonzalo Antonio Serrano S;Co\u0301Rdoba",
    "iso:country":"ES",
    "sg:address":"Calle de Gonzalo Antonio Serrano, S/n",
    "sg:city":"Cordoba",
    "sg:orig_category":"Material Y Suministros Para Imprenta E Industrias Gr\u00c1ficas",
    "sg:phone":"+34 957 32 67 32",
    "sg:postcode":"14014",
    "sg:province":"C\u00f3rdoba",
    "wof:name":"Construcciones Leal Y Revaliente S.l.",
    "wof:placetype":"venue"
},
  "geometry": {"coordinates":[-4.720664978,37.903427124],"type":"Point"}
}