{
  "type": "Feature",
  "properties": {
    "addr:full":"Ctra. Burgos, Km. 0319,0 Almenar Soria Soria 42130",
    "addr:postcode":"42130",
    "addr:street":"Ctra. Burgos Km. 0319,0",
    "iso:country":"ES",
    "sg:address":"Ctra. Burgos, Km. 0319,0",
    "sg:city":"Almenar Soria",
    "sg:orig_category":"Comercio De Carburantes",
    "sg:phone":"+34 975 39 01 02",
    "sg:postcode":"42130",
    "sg:province":"Soria",
    "wof:name":"Sanz Gonzalo Angel",
    "wof:placetype":"venue"
},
  "geometry": {"coordinates":[-2.2014091015,41.6827316284],"type":"Point"}
}