{
  "type": "Feature",
  "properties": {
    "addr:full":"Calle de Guillem De Castro, 117 Valencia Valencia 46008",
    "addr:housenumber":"117",
    "addr:postcode":"46008",
    "addr:street":"Calle De Guillem De Castro",
    "iso:country":"ES",
    "sg:address":"Calle de Guillem De Castro, 117",
    "sg:city":"Valencia",
    "sg:orig_category":"Armas Y Municiones (fabricaci\u00d3n, Al Por Mayor)",
    "sg:phone":"+34 963 91 53 58",
    "sg:postcode":"46008",
    "sg:province":"Valencia",
    "wof:name":"Solaz Lopez Esteban",
    "wof:placetype":"venue"
},
  "geometry": {"coordinates":[-0.3840695024,39.4746131897],"type":"Point"}
}