{
  "type": "Feature",
  "properties": {
    "addr:full":"Calle de Cardenal Tavera, 5 Ciudad Rodrigo Salamanca 37500",
    "addr:housenumber":"5",
    "addr:postcode":"37500",
    "addr:street":"Calle De Cardenal Tavera",
    "iso:country":"ES",
    "sg:address":"Calle de Cardenal Tavera, 5",
    "sg:city":"Ciudad Rodrigo",
    "sg:orig_category":"Centros Empresariales",
    "sg:phone":"+34 923 48 24 27",
    "sg:postcode":"37500",
    "sg:province":"Salamanca",
    "wof:name":"Ditsal Oeste S.l.",
    "wof:placetype":"venue"
},
  "geometry": {"coordinates":[-6.5143089294,40.6336593628],"type":"Point"}
}