{
  "type": "Feature",
  "properties": {
    "addr:full":"Carrer de Carretera, S/n Sallent Barcelona 08650",
    "addr:postcode":"08650",
    "addr:street":"Carrer De Carretera S / N",
    "iso:country":"ES",
    "sg:address":"Carrer de Carretera, S/n",
    "sg:city":"Sallent",
    "sg:orig_category":"Explotaci\u00d3n De Minas",
    "sg:phone":"+34 938 37 00 25",
    "sg:postcode":"08650",
    "sg:province":"Barcelona",
    "wof:name":"Iberpotash S.a.",
    "wof:placetype":"venue"
},
  "geometry": {"coordinates":[1.8918360472,41.8243789673],"type":"Point"}
}