{
  "type": "Feature",
  "properties": {
    "addr:full":"Avda Blasco Iba\u00d1ez, 95 Valencia Valencia 46022",
    "addr:housenumber":"95",
    "addr:postcode":"46022",
    "addr:street":"Avda Blasco Iban\u0303Ez",
    "iso:country":"ES",
    "sg:address":"Avda Blasco Iba\u00d1ez, 95",
    "sg:city":"Valencia",
    "sg:orig_category":"Asesor\u00cdas Y Estudios Financieros",
    "sg:phone":"+34 963 56 21 22",
    "sg:postcode":"46022",
    "sg:province":"Valencia",
    "wof:name":"Sastre Correcher Juan Jose",
    "wof:placetype":"venue"
},
  "geometry": {"coordinates":[-0.3463410139,39.47397995],"type":"Point"}
}