{
  "type": "Feature",
  "properties": {
    "iso:country":"ES",
    "sg:address":"Ctra. Guijuelo, S/n",
    "sg:city":"Macotera",
    "sg:orig_category":"Asilos De Ancianos. Centros Privados",
    "sg:phone":"+34 923 55 50 37",
    "sg:postcode":"37310",
    "sg:province":"Salamanca",
    "wof:name":"Fundacion Residencia El Cerro",
    "wof:placetype":"venue"
},
  "geometry": {"coordinates":[-5.2848639488,40.8340301514],"type":"Point"}
}