{
  "type": "Feature",
  "properties": {
    "addr:full":"Pg Muntanya, 96 Granollers Barcelona 08402",
    "addr:housenumber":"96",
    "addr:postcode":"08402",
    "addr:street":"Pg Muntanya",
    "iso:country":"ES",
    "sg:address":"Pg Muntanya, 96",
    "sg:city":"Granollers",
    "sg:orig_category":"Carnicer\u00cdas, Carnicer\u00cdas",
    "sg:phone":"+34 938 79 24 36",
    "sg:postcode":"08402",
    "sg:province":"Barcelona",
    "wof:name":"Carns Toreent I Bonet S. L.",
    "wof:placetype":"venue"
},
  "geometry": {"coordinates":[2.2937669754,41.6093139648],"type":"Point"}
}