{
  "type": "Feature",
  "properties": {
    "iso:country":"ES",
    "sg:address":"Av Portossaler, S/n",
    "sg:city":"S. Francesc Formentera",
    "sg:orig_category":"Clases De M\u00dasica Y Canto",
    "sg:phone":"+34 971 32 33 55",
    "sg:postcode":"07860",
    "sg:province":"Islas Baleares",
    "wof:name":"Ajuntament De Formentera",
    "wof:placetype":"venue"
},
  "geometry": {"coordinates":[1.4263385534,38.7073287964],"type":"Point"}
}