{
  "type": "Feature",
  "properties": {
    "iso:country":"ES",
    "sg:address":"Calle de Lerida, 30",
    "sg:city":"Valencia",
    "sg:orig_category":"Fotocopias, Reprograf\u00cda",
    "sg:phone":"+34 963 46 25 25",
    "sg:postcode":"46009",
    "sg:province":"Valencia",
    "wof:name":"Digital Copy S.l.",
    "wof:placetype":"venue"
},
  "geometry": {"coordinates":[-0.3785519898,39.4839820862],"type":"Point"}
}