{
  "type": "Feature",
  "properties": {
    "addr:full":"Carrer de Argentona (d'), 14 Mataro Barcelona 08302",
    "addr:housenumber":"14",
    "addr:postcode":"08302",
    "addr:street":"Carrer De Argentona D '",
    "iso:country":"ES",
    "sg:address":"Carrer de Argentona (d'), 14",
    "sg:city":"Mataro",
    "sg:orig_category":"Asociaciones, Organismos Culturales Y Socioeducativos",
    "sg:phone":"+34 937 98 20 44",
    "sg:postcode":"08302",
    "sg:province":"Barcelona",
    "wof:name":"Pe\u00f1a Barcelonista Mataro",
    "wof:placetype":"venue"
},
  "geometry": {"coordinates":[2.4434890747,41.541229248],"type":"Point"}
}