{
  "type": "Feature",
  "properties": {
    "addr:full":"Calle de Isla Sumatra, 1 Madrid Madrid 28034",
    "addr:housenumber":"1",
    "addr:postcode":"28034",
    "addr:street":"Calle De Isla Sumatra",
    "iso:country":"ES",
    "sg:address":"Calle de Isla Sumatra, 1",
    "sg:city":"Madrid",
    "sg:orig_category":"Maquinaria Para Industrias Diversas",
    "sg:phone":"+34 917 29 05 64",
    "sg:postcode":"28034",
    "sg:province":"Madrid",
    "wof:name":"Iglesias Gil Maria Concepcion",
    "wof:placetype":"venue"
},
  "geometry": {"coordinates":[-3.6875879765,40.4956436157],"type":"Point"}
}