{
  "type": "Feature",
  "properties": {
    "addr:full":"Calle de Lechuga, 3 Madrid Madrid 28012",
    "addr:housenumber":"3",
    "addr:postcode":"28012",
    "addr:street":"Calle De Lechuga",
    "iso:country":"ES",
    "sg:address":"Calle de Lechuga, 3",
    "sg:city":"Madrid",
    "sg:orig_category":"Molduras, Junquillos, Listones Y Molduras Perforadas",
    "sg:phone":"+34 913 65 10 87",
    "sg:postcode":"28012",
    "sg:province":"Madrid",
    "wof:name":"Restaurante El Cogollo S.l.",
    "wof:placetype":"venue"
},
  "geometry": {"coordinates":[-3.7065858841,40.4143409729],"type":"Point"}
}