{
  "type": "Feature",
  "properties": {
    "addr:full":"Calle de Doctor Barraquer, 7 Cordoba C\u00f3rdoba 14004",
    "addr:housenumber":"7",
    "addr:postcode":"14004",
    "addr:street":"Calle De Doctor Barraquer;Co\u0301Rdoba",
    "iso:country":"ES",
    "sg:address":"Calle de Doctor Barraquer, 7",
    "sg:city":"Cordoba",
    "sg:orig_category":"Centros Comerciales Y Grandes Tiendas",
    "sg:phone":"+34 957 29 56 73",
    "sg:postcode":"14004",
    "sg:province":"C\u00f3rdoba",
    "wof:name":"Serrano Gomez Rafael",
    "wof:placetype":"venue"
},
  "geometry": {"coordinates":[-4.7841649055,37.8772926331],"type":"Point"}
}