{
  "type": "Feature",
  "properties": {
    "addr:full":"Carrer de Pintor Murillo, 41 Rubi Barcelona 08191",
    "addr:housenumber":"41",
    "addr:postcode":"08191",
    "addr:street":"Carrer De Pintor Murillo",
    "iso:country":"ES",
    "sg:address":"Carrer de Pintor Murillo, 41",
    "sg:city":"Rubi",
    "sg:orig_category":"Fisioterapia",
    "sg:phone":"+34 936 97 11 00",
    "sg:postcode":"08191",
    "sg:province":"Barcelona",
    "wof:name":"Mendez Vilaseca Maria Isabel",
    "wof:placetype":"venue"
},
  "geometry": {"coordinates":[2.0310161114,41.4880485535],"type":"Point"}
}