{
  "type": "Feature",
  "properties": {
    "addr:full":"Carr Portal Del Lleo, 4 Xativa Valencia 46800",
    "addr:housenumber":"4",
    "addr:postcode":"46800",
    "addr:street":"Carr Portal Del Lleo",
    "iso:country":"ES",
    "sg:address":"Carr Portal Del Lleo, 4",
    "sg:city":"Xativa",
    "sg:orig_category":"Arquitectos",
    "sg:phone":"+34 962 28 08 80",
    "sg:postcode":"46800",
    "sg:province":"Valencia",
    "wof:name":"Lopez Oliver Francisco Jose",
    "wof:placetype":"venue"
},
  "geometry": {"coordinates":[-0.5193229914,38.9896888733],"type":"Point"}
}