{
  "type": "Feature",
  "properties": {
    "addr:full":"Calle de Montero, 29 Mostoles Madrid 28934",
    "addr:housenumber":"29",
    "addr:postcode":"28934",
    "addr:street":"Calle De Montero",
    "iso:country":"ES",
    "sg:address":"Calle de Montero, 29",
    "sg:city":"Mostoles",
    "sg:orig_category":"Fabricaci\u00d3n De Su\u00c9ters Y Chalecos De Punto",
    "sg:phone":"+34 916 13 63 84",
    "sg:postcode":"28934",
    "sg:province":"Madrid",
    "wof:name":"Confecciones Herrero S.a.",
    "wof:placetype":"venue"
},
  "geometry": {"coordinates":[-3.8673939705,40.321598053],"type":"Point"}
}