{
  "type": "Feature",
  "properties": {
    "iso:country":"ES",
    "sg:address":"Calle de Conde Ansurez, 1",
    "sg:city":"Valladolid",
    "sg:orig_category":"Alimentaci\u00d3n General (al Por Menor)",
    "sg:phone":"+34 983 35 82 51",
    "sg:postcode":"47003",
    "sg:province":"Valladolid",
    "wof:name":"Martin Perez Lorenza",
    "wof:placetype":"venue"
},
  "geometry": {"coordinates":[-4.727619648,41.6535949707],"type":"Point"}
}