{
  "type": "Feature",
  "properties": {
    "addr:full":"Pase Lomas (las), 1 Ejido Almer\u00eda 04700",
    "addr:postcode":"04700",
    "addr:street":"Las;Ejido Almeri\u0301A",
    "iso:country":"ES",
    "sg:address":"Pase Lomas (las), 1",
    "sg:city":"Ejido",
    "sg:orig_category":"Cajas De Ahorro",
    "sg:phone":"+34 950 48 23 54",
    "sg:postcode":"04700",
    "sg:province":"Almer\u00eda",
    "wof:name":"Unicaja",
    "wof:placetype":"venue"
},
  "geometry": {"coordinates":[-2.8176040649,36.7727012634],"type":"Point"}
}