{
  "type": "Feature",
  "properties": {
    "addr:full":"Calle de Dorada (la), 16 Alacant Alicante 03540",
    "addr:postcode":"03540",
    "addr:street":"Calle De Dorada La",
    "iso:country":"ES",
    "sg:address":"Calle de Dorada (la), 16",
    "sg:city":"Alacant",
    "sg:orig_category":"Electrodom\u00c9sticos (al Por Menor)",
    "sg:phone":"+34 965 16 08 32",
    "sg:postcode":"03540",
    "sg:province":"Alicante",
    "wof:name":"Cafe Alcala S.l.",
    "wof:placetype":"venue"
},
  "geometry": {"coordinates":[-0.4126743078,38.3617134094],"type":"Point"}
}