{
  "type": "Feature",
  "properties": {
    "iso:country":"ES",
    "sg:address":"Avda Galtzaraborda, 47",
    "sg:city":"Errenteria",
    "sg:orig_category":"Pescader\u00cdas (al Por Menor)",
    "sg:phone":"+34 943 52 06 17",
    "sg:postcode":"20100",
    "sg:province":"Guip\u00f9zcoa",
    "wof:name":"Pastor Olcor Pedro",
    "wof:placetype":"venue"
},
  "geometry": {"coordinates":[-1.9110460281,43.3109664917],"type":"Point"}
}