{
  "type": "Feature",
  "properties": {
    "addr:full":"Calle de Fuentidue\u00d1a, 8 Madrid Madrid 28031",
    "addr:housenumber":"8",
    "addr:postcode":"madrid;28031",
    "addr:street":"Calle De Fuentiduen\u0303A",
    "iso:country":"ES",
    "sg:address":"Calle de Fuentidue\u00d1a, 8",
    "sg:city":"Madrid",
    "sg:orig_category":"Tapicer\u00cdas",
    "sg:phone":"+34 913 32 72 70",
    "sg:postcode":"28031",
    "sg:province":"Madrid",
    "wof:name":"Montilla Lopez Juan",
    "wof:placetype":"venue"
},
  "geometry": {"coordinates":[-3.6225290298,40.3726730347],"type":"Point"}
}