{
  "type": "Feature",
  "properties": {
    "addr:full":"C/ Terrassa, 10 Alcoi Alicante 03804",
    "addr:housenumber":"10",
    "addr:postcode":"03804",
    "addr:street":"C / Terrassa",
    "iso:country":"ES",
    "sg:address":"C/ Terrassa, 10",
    "sg:city":"Alcoi",
    "sg:orig_category":"Asociaciones Y Clubs Deportivos",
    "sg:phone":"+34 965 33 23 28",
    "sg:postcode":"03804",
    "sg:province":"Alicante",
    "wof:name":"Sociedad De Cazadores La Protectora",
    "wof:placetype":"venue"
},
  "geometry": {"coordinates":[-0.4677940011,38.7079925537],"type":"Point"}
}