{
  "type": "Feature",
  "properties": {
    "addr:full":"Av. Dr. Gomez Ferrer, 3 Sedavi Valencia 46910",
    "addr:housenumber":"3",
    "addr:postcode":"46910",
    "addr:street":"Av. Dr. Gomez Ferrer",
    "iso:country":"ES",
    "sg:address":"Av. Dr. Gomez Ferrer, 3",
    "sg:city":"Sedavi",
    "sg:orig_category":"Promotores Constructores",
    "sg:phone":"+34 963 75 06 71",
    "sg:postcode":"46910",
    "sg:province":"Valencia",
    "wof:name":"Arcion S. A.",
    "wof:placetype":"venue"
},
  "geometry": {"coordinates":[-0.3865427971,39.4252853394],"type":"Point"}
}