{
  "type": "Feature",
  "properties": {
    "addr:full":"Rua Jose Antonio, 23 Silleda Pontevedra 36540",
    "addr:housenumber":"23",
    "addr:postcode":"36540",
    "addr:street":"Rua Jose Antonio",
    "iso:country":"ES",
    "sg:address":"Rua Jose Antonio, 23",
    "sg:city":"Silleda",
    "sg:orig_category":"Pescader\u00cdas (al Por Menor)",
    "sg:phone":"+34 986 58 12 23",
    "sg:postcode":"36540",
    "sg:province":"Pontevedra",
    "wof:name":"Reimondez Agra Ana Belen",
    "wof:placetype":"venue"
},
  "geometry": {"coordinates":[-8.2460689545,42.7014503479],"type":"Point"}
}