{
  "type": "Feature",
  "properties": {
    "iso:country":"ES",
    "sg:address":"Calle de Pilar, 5",
    "sg:city":"Aceuchal",
    "sg:orig_category":"Quincaller\u00cda (al Por Menor)",
    "sg:phone":"+34 924 68 01 58",
    "sg:postcode":"06207",
    "sg:province":"Badajoz",
    "wof:name":"Mu\u00f1oz Rangel Aurora Alejandra",
    "wof:placetype":"venue"
},
  "geometry": {"coordinates":[-6.4876928329,38.6465454102],"type":"Point"}
}