{
  "type": "Feature",
  "properties": {
    "iso:country":"ES",
    "sg:address":"Plaz Maestro Mateo, 2",
    "sg:city":"Coru\u00d1a",
    "sg:orig_category":"M\u00c9dicos: Cirug\u00cda Pl\u00c1stica, Reconstructiva Y Est\u00c9tica",
    "sg:phone":"+34 981 14 50 90",
    "sg:postcode":"15004",
    "sg:province":"La Coru\u00f1a",
    "wof:name":"Martelo Villar Francisco",
    "wof:placetype":"venue"
},
  "geometry": {"coordinates":[-8.411280632,43.3666610718],"type":"Point"}
}