{
  "type": "Feature",
  "properties": {
    "iso:country":"ES",
    "sg:address":"Calle de Roa De La Vega, 4",
    "sg:city":"Le\u00f3n",
    "sg:orig_category":"Ingenier\u00cda, Centros De Estudios (diversos)",
    "sg:phone":"+34 987 22 32 14",
    "sg:postcode":"24002",
    "sg:province":"Le\u00f3n",
    "wof:name":"Jimenez-alfaro Carranza Juan Jose",
    "wof:placetype":"venue"
},
  "geometry": {"coordinates":[-5.576488018,42.6012496948],"type":"Point"}
}