{
  "type": "Feature",
  "properties": {
    "addr:full":"Avda Fama, 10 Paz Murcia 30003",
    "addr:housenumber":"10",
    "addr:postcode":"30003",
    "addr:street":"Avda Fama",
    "iso:country":"ES",
    "sg:address":"Avda Fama, 10",
    "sg:city":"Paz",
    "sg:orig_category":"Inmobiliaria (agencias)",
    "sg:phone":"+34 968 35 06 88",
    "sg:postcode":"30003",
    "sg:province":"Murcia",
    "wof:name":"Api Proa S.l.",
    "wof:placetype":"venue"
},
  "geometry": {"coordinates":[-1.1298867464,37.9834747314],"type":"Point"}
}