{
  "type": "Feature",
  "properties": {
    "addr:full":"Pl Major, S/n Benidorm Alicante 03500",
    "addr:housenumber":"s / n",
    "addr:postcode":"03500",
    "addr:street":"Pl Major",
    "iso:country":"ES",
    "sg:address":"Pl Major, S/n",
    "sg:city":"Benidorm",
    "sg:orig_category":"Orquestas De Variedades",
    "sg:phone":"+34 965 85 33 56",
    "sg:postcode":"03500",
    "sg:province":"Alicante",
    "wof:name":"Union Musical De Benidorm",
    "wof:placetype":"venue"
},
  "geometry": {"coordinates":[-0.1305699944,38.5367431641],"type":"Point"}
}