{
  "type": "Feature",
  "properties": {
    "addr:full":"Carr Sant Josep, De, 58 Casco Urbano Valencia 46760",
    "addr:housenumber":"58",
    "addr:postcode":"46760",
    "addr:street":"Carr Sant Josep De",
    "iso:country":"ES",
    "sg:address":"Carr Sant Josep, De, 58",
    "sg:city":"Casco Urbano",
    "sg:orig_category":"Iglesia Cat\u00d3lica",
    "sg:phone":"+34 962 82 19 16",
    "sg:postcode":"46760",
    "sg:province":"Valencia",
    "wof:name":"Parroquia De San Jose",
    "wof:placetype":"venue"
},
  "geometry": {"coordinates":[-0.2594090104,39.0749702454],"type":"Point"}
}