{
  "type": "Feature",
  "properties": {
    "iso:country":"ES",
    "sg:address":"Camino De San Antonio, S/n",
    "sg:city":"Pulianas",
    "sg:orig_category":"Electrodom\u00c9sticos (al Por Menor)",
    "sg:phone":"+34 958 42 62 07",
    "sg:postcode":"18197",
    "sg:province":"Granada",
    "wof:name":"Hermanos Ruiz E Hijos S.l.",
    "wof:placetype":"venue"
},
  "geometry": {"coordinates":[-3.5950171947,37.1861877441],"type":"Point"}
}