{
  "type": "Feature",
  "properties": {
    "addr:full":"Carrer de L'agricultura, 225 Barcelona Barcelona 08020",
    "addr:housenumber":"225",
    "addr:postcode":"08020",
    "addr:street":"Carrer De L'Agricultura",
    "iso:country":"ES",
    "sg:address":"Carrer de L'agricultura, 225",
    "sg:city":"Barcelona",
    "sg:orig_category":"Inform\u00c1tica (estudios, Servicios, Asesor\u00cda, Formaci\u00d3n)",
    "sg:phone":"+34 932 78 28 50",
    "sg:postcode":"08020",
    "sg:province":"Barcelona",
    "wof:name":"Vidal Casta\u00f1e Ricard",
    "wof:placetype":"venue"
},
  "geometry": {"coordinates":[2.2021064758,41.4174728394],"type":"Point"}
}