{
  "type": "Feature",
  "properties": {
    "addr:full":"Ctra Tomares, Km. 0001,0 San J. Aznalfarache Sevilla 41920",
    "addr:postcode":"41920",
    "addr:street":"Ctra Tomares Km. 0001,0 San J. Aznalfarache",
    "iso:country":"ES",
    "sg:address":"Ctra Tomares, Km. 0001,0",
    "sg:city":"San J. Aznalfarache",
    "sg:orig_category":"Caf\u00c9s, Bares, Cervecer\u00cdas",
    "sg:phone":"+34 954 76 65 50",
    "sg:postcode":"41920",
    "sg:province":"Sevilla",
    "wof:name":"Zena Grupo De Restauracion S.a.",
    "wof:placetype":"venue"
},
  "geometry": {"coordinates":[-6.0306563377,37.3853378296],"type":"Point"}
}