{
  "type": "Feature",
  "properties": {
    "addr:full":"Fouco, 1 Fouco Pontevedra 36389",
    "addr:housenumber":"1",
    "addr:postcode":"36389",
    "addr:street":"Fouco",
    "iso:country":"ES",
    "sg:address":"Fouco, 1",
    "sg:city":"Fouco",
    "sg:classifiers":[
        {
            "category":"Taxi",
            "type":"Transportation"
        }
    ],
    "sg:phone":"+34 986 36 08 97",
    "sg:postcode":"36389",
    "sg:province":"Pontevedra",
    "wof:name":"Salgueiro Freiria Jose",
    "wof:placetype":"venue"
},
  "geometry": {"coordinates":[-8.7404689789,42.1420402527],"type":"Point"}
}