{
  "type": "Feature",
  "properties": {
    "addr:full":"Avda Barcelona (de), 19 Granada Granada 18006",
    "addr:housenumber":"19",
    "addr:postcode":"18006",
    "addr:street":"Avda Barcelona De",
    "iso:country":"ES",
    "sg:address":"Avda Barcelona (de), 19",
    "sg:city":"Granada",
    "sg:orig_category":"Comercio De Piezas De Recambio Y De Accesorios De Veh\u00cdculos, Veh\u00cdculos Industriales",
    "sg:phone":"+34 958 13 06 62",
    "sg:postcode":"18006",
    "sg:province":"Granada",
    "wof:name":"Repuestos Marin S.l.",
    "wof:placetype":"venue"
},
  "geometry": {"coordinates":[-3.6005890369,37.1607551575],"type":"Point"}
}