{
  "type": "Feature",
  "properties": {
    "addr:full":"Calle de Duende, 8 Almagro Ciudad Real 13270",
    "addr:housenumber":"8",
    "addr:postcode":"13270",
    "addr:street":"Calle De Duende",
    "iso:country":"ES",
    "sg:address":"Calle de Duende, 8",
    "sg:city":"Almagro",
    "sg:orig_category":"Transportes Por Carretera: Lotes Completos, Mercanc\u00cdas Diversas",
    "sg:phone":"+34 926 88 28 95",
    "sg:postcode":"13270",
    "sg:province":"Ciudad Real",
    "wof:name":"Nu\u00f1ez De Arenas Ros Antonio",
    "wof:placetype":"venue"
},
  "geometry": {"coordinates":[-3.7106924057,38.8836898804],"type":"Point"}
}