{
  "type": "Feature",
  "properties": {
    "iso:country":"ES",
    "sg:address":"Calle de Ledesma, 6",
    "sg:city":"Bilbao",
    "sg:orig_category":"Obras Y Organismos Sociales",
    "sg:phone":"+34 944 24 80 11",
    "sg:postcode":"48001",
    "sg:province":"Vizcaya",
    "wof:name":"Club De Leones De Bilbao",
    "wof:placetype":"venue"
},
  "geometry": {"coordinates":[-2.9271810055,43.2620239258],"type":"Point"}
}