{
  "type": "Feature",
  "properties": {
    "iso:country":"ES",
    "sg:address":"Calle de Eugenia De Montijo, 109",
    "sg:city":"Madrid",
    "sg:orig_category":"Supermercados Y Hipermercados",
    "sg:phone":"+34 915 08 06 64",
    "sg:postcode":"28044",
    "sg:province":"Madrid",
    "wof:name":"Ecozar S.a.",
    "wof:placetype":"venue"
},
  "geometry": {"coordinates":[-3.7511150837,40.373916626],"type":"Point"}
}