{
  "type": "Feature",
  "properties": {
    "iso:country":"ES",
    "sg:address":"Jose Migel Iturriotz Kalea, 4",
    "sg:city":"Beasain",
    "sg:orig_category":"Molduras, Junquillos, Listones Y Molduras Perforadas",
    "sg:phone":"+34 943 88 20 26",
    "sg:postcode":"20200",
    "sg:province":"Guip\u00f9zcoa",
    "wof:name":"Antton Aramburu (bikale Taberna)",
    "wof:placetype":"venue"
},
  "geometry": {"coordinates":[-2.194204092,43.0473480225],"type":"Point"}
}