{
  "type": "Feature",
  "properties": {
    "iso:country":"ES",
    "sg:address":"Av Palma, 17",
    "sg:city":"Tossa",
    "sg:orig_category":"Restaurantes",
    "sg:phone":"+34 972 34 24 31",
    "sg:postcode":"17320",
    "sg:province":"Girona",
    "wof:name":"Restaurante Victor S.c",
    "wof:placetype":"venue"
},
  "geometry": {"coordinates":[2.9310429096,41.7223815918],"type":"Point"}
}