{
  "type": "Feature",
  "properties": {
    "iso:country":"ES",
    "sg:address":"Avda Constitucion, 10",
    "sg:city":"Callosa Segura",
    "sg:orig_category":"Bazares, Art\u00cdculos De Limpieza Y De Cocina (al Por Menor)",
    "sg:phone":"+34 966 75 83 92",
    "sg:postcode":"03360",
    "sg:province":"Alicante",
    "wof:name":"Comercial Nieto Lizon S.l.",
    "wof:placetype":"venue"
},
  "geometry": {"coordinates":[-0.8775449991,38.1261177063],"type":"Point"}
}