{
  "type": "Feature",
  "properties": {
    "iso:country":"ES",
    "sg:address":"Avda Jose Aguado, 20",
    "sg:city":"Le\u00f3n",
    "sg:orig_category":"Reposter\u00cdas",
    "sg:phone":"+34 987 25 35 75",
    "sg:postcode":"24005",
    "sg:province":"Le\u00f3n",
    "wof:name":"Cabero Martinez Andres",
    "wof:placetype":"venue"
},
  "geometry": {"coordinates":[-5.5656018257,42.5903968811],"type":"Point"}
}