{
  "type": "Feature",
  "properties": {
    "addr:full":"Calle de Miguel De Cervantes, 29 Ibi Alicante 03440",
    "addr:housenumber":"29",
    "addr:postcode":"03440",
    "addr:street":"Calle De Miguel De Cervantes",
    "iso:country":"ES",
    "sg:address":"Calle de Miguel De Cervantes, 29",
    "sg:city":"Ibi",
    "sg:orig_category":"Promotores Constructores",
    "sg:phone":"+34 966 55 30 45",
    "sg:postcode":"03440",
    "sg:province":"Alicante",
    "wof:name":"Construcciones Chis Cor S.l.",
    "wof:placetype":"venue"
},
  "geometry": {"coordinates":[-0.5775930285,38.6203727722],"type":"Point"}
}