{
  "type": "Feature",
  "properties": {
    "addr:full":"Avgd Maria Ros, 11 Burjassot Valencia 46100",
    "addr:housenumber":"11",
    "addr:postcode":"46100",
    "iso:country":"ES",
    "sg:address":"Avgd Maria Ros, 11",
    "sg:city":"Burjassot",
    "sg:orig_category":"Supermercados Y Hipermercados",
    "sg:phone":"+34 963 63 04 81",
    "sg:postcode":"46100",
    "sg:province":"Valencia",
    "wof:name":"Carnes A. Soriano E Hijos S. L.",
    "wof:placetype":"venue"
},
  "geometry": {"coordinates":[-0.4132629931,39.5149230957],"type":"Point"}
}