{
  "type": "Feature",
  "properties": {
    "iso:country":"ES",
    "sg:address":"Calle de Valdehunco, 18",
    "sg:city":"Villanueva Campo",
    "sg:orig_category":"Telas Y Sedas (al Por Menor)",
    "sg:phone":"+34 980 66 60 42",
    "sg:postcode":"49100",
    "sg:province":"Zamora",
    "wof:name":"Fermoso Buron Antonio",
    "wof:placetype":"venue"
},
  "geometry": {"coordinates":[-5.4073028564,41.983757019],"type":"Point"}
}