{
  "type": "Feature",
  "properties": {
    "addr:full":"Calle de Camino Viejo De Leganes, 131 Madrid Madrid 28025",
    "addr:housenumber":"131",
    "addr:postcode":"28025",
    "addr:street":"Calle De Camino Viejo De Leganes",
    "iso:country":"ES",
    "sg:address":"Calle de Camino Viejo De Leganes, 131",
    "sg:city":"Madrid",
    "sg:orig_category":"Ropa Para Se\u00d1oras (al Por Menor)",
    "sg:phone":"+34 914 62 31 46",
    "sg:postcode":"28025",
    "sg:province":"Madrid",
    "wof:name":"Hernandez Losada Ascension",
    "wof:placetype":"venue"
},
  "geometry": {"coordinates":[-3.728358984,40.3848991394],"type":"Point"}
}