{
  "type": "Feature",
  "properties": {
    "iso:country":"ES",
    "sg:address":"Rua Pravia (da), 10",
    "sg:city":"Vilalba",
    "sg:orig_category":"Electricidad Veh\u00cdculo",
    "sg:phone":"+34 982 52 30 20",
    "sg:postcode":"27800",
    "sg:province":"Lugo",
    "wof:name":"Corredoira Car-audio S.l.",
    "wof:placetype":"venue"
},
  "geometry": {"coordinates":[-7.6814098358,43.2981719971],"type":"Point"}
}