{
  "type": "Feature",
  "properties": {
    "addr:full":"Calle de Lentini, 3 San Rafael Las Palmas 35110",
    "addr:housenumber":"3",
    "addr:postcode":"35110",
    "addr:street":"Calle De Lentini",
    "iso:country":"ES",
    "sg:address":"Calle de Lentini, 3",
    "sg:city":"San Rafael",
    "sg:orig_category":"Centros Empresariales",
    "sg:phone":"+34 928 12 50 45",
    "sg:postcode":"35110",
    "sg:province":"Las Palmas",
    "wof:name":"Gonzalez Omar Fernando",
    "wof:placetype":"venue"
},
  "geometry": {"coordinates":[-15.4485340118,27.8392906189],"type":"Point"}
}