{
  "type": "Feature",
  "properties": {
    "addr:full":"Calle de Baeza, 1 Jaen Ja\u00e9n 23008",
    "addr:housenumber":"1;jae\u0301n",
    "addr:postcode":"23008",
    "addr:street":"Calle De Baeza",
    "iso:country":"ES",
    "sg:address":"Calle de Baeza, 1",
    "sg:city":"Jaen",
    "sg:orig_category":"Arquitectos",
    "sg:phone":"+34 953 27 56 47",
    "sg:postcode":"23008",
    "sg:province":"Ja\u00e9n",
    "wof:name":"Fernandez Noves Juan Manuel",
    "wof:placetype":"venue"
},
  "geometry": {"coordinates":[-3.7887964249,37.773223877],"type":"Point"}
}