{
  "type": "Feature",
  "properties": {
    "addr:full":"Trva Valderrama, 2 Santander Cantabria 39010",
    "addr:housenumber":"2",
    "addr:postcode":"39010",
    "addr:street":"Trva Valderrama",
    "iso:country":"ES",
    "sg:address":"Trva Valderrama, 2",
    "sg:city":"Santander",
    "sg:orig_category":"Promotores Constructores",
    "sg:phone":"+34 942 37 14 53",
    "sg:postcode":"39010",
    "sg:province":"Cantabria",
    "wof:name":"Jam S. A.",
    "wof:placetype":"venue"
},
  "geometry": {"coordinates":[-3.8244950771,43.4593200684],"type":"Point"}
}