{
  "type": "Feature",
  "properties": {
    "iso:country":"ES",
    "sg:address":"Calle de Fragua (de La), S/n",
    "sg:city":"Poligono Industrial De Arinaga",
    "sg:orig_category":"Bazares, Art\u00cdculos De Limpieza Y De Cocina (al Por Menor)",
    "sg:phone":"+34 928 18 11 68",
    "sg:postcode":"35118",
    "sg:province":"Las Palmas",
    "wof:name":"Bazar Autoservicio Hermanos Garcia Do S.",
    "wof:placetype":"venue"
},
  "geometry": {"coordinates":[-15.4319887161,27.8808555603],"type":"Point"}
}