{
  "type": "Feature",
  "properties": {
    "iso:country":"ES",
    "sg:address":"Calle de Ezcurdia, 101",
    "sg:city":"Gijon",
    "sg:orig_category":"Farmacias",
    "sg:phone":"+34 985 36 03 45",
    "sg:postcode":"33203",
    "sg:province":"Asturias",
    "wof:name":"Fermin",
    "wof:placetype":"venue"
},
  "geometry": {"coordinates":[-5.6442990303,43.5357589722],"type":"Point"}
}