{
  "type": "Feature",
  "properties": {
    "addr:full":"Nuevo Relleno, S/n Cee La Coru\u00f1a 15270",
    "addr:housenumber":"s / n",
    "addr:postcode":"15270",
    "addr:street":"La",
    "iso:country":"ES",
    "sg:address":"Nuevo Relleno, S/n",
    "sg:city":"Cee",
    "sg:orig_category":"Centros De Coordinaci\u00d3n",
    "sg:phone":"+34 981 74 58 98",
    "sg:postcode":"15270",
    "sg:province":"La Coru\u00f1a",
    "wof:name":"Lari\u00f1o Ares Maria",
    "wof:placetype":"venue"
},
  "geometry": {"coordinates":[-9.187494278,42.9554710388],"type":"Point"}
}