{
  "type": "Feature",
  "properties": {
    "addr:full":"Avda Cantabria, 30 Madrid Madrid 28042",
    "addr:housenumber":"30",
    "addr:postcode":"madrid;28042",
    "addr:street":"Avda Cantabria",
    "iso:country":"ES",
    "sg:address":"Avda Cantabria, 30",
    "sg:city":"Madrid",
    "sg:classifiers":[
        {
            "category":"Personal",
            "subcategory":"Barber",
            "type":"Services"
        }
    ],
    "sg:phone":"+34 917 47 35 47",
    "sg:postcode":"28042",
    "sg:province":"Madrid",
    "sg:tags":[
        "caballeros",
        "de",
        "peluqueros"
    ],
    "wof:name":"Cruz Hernandez Alejandro",
    "wof:placetype":"venue"
},
  "geometry": {"coordinates":[-3.5863170624,40.4569740295],"type":"Point"}
}