{
  "type": "Feature",
  "properties": {
    "addr:full":"Pg Federico Garcia Lorca, S/n Cala Anguila-cala Mendia Islas Baleares 07689",
    "addr:housenumber":"/ n",
    "addr:postcode":"07689",
    "addr:street":"Pg Federico Garcia Lorca S;Anguila-Cala;Islas",
    "iso:country":"ES",
    "sg:address":"Pg Federico Garcia Lorca, S/n",
    "sg:city":"Cala Anguila-cala Mendia",
    "sg:orig_category":"Doctores En Medicina",
    "sg:phone":"+34 971 55 83 00",
    "sg:postcode":"07689",
    "sg:province":"Islas Baleares",
    "wof:name":"Vidal Mulet Gabriel",
    "wof:placetype":"venue"
},
  "geometry": {"coordinates":[3.2705500126,39.4597702026],"type":"Point"}
}