{
  "type": "Feature",
  "properties": {
    "iso:country":"ES",
    "sg:address":"Av Catalunya, 16",
    "sg:city":"S. Adria Besos",
    "sg:orig_category":"Zapatos (al Por Menor)",
    "sg:phone":"+34 933 81 11 19",
    "sg:postcode":"08930",
    "sg:province":"Barcelona",
    "wof:name":"Jimeno Pastor Montserrat",
    "wof:placetype":"venue"
},
  "geometry": {"coordinates":[2.2162709236,41.4319496155],"type":"Point"}
}