{
  "type": "Feature",
  "properties": {
    "iso:country":"ES",
    "sg:address":"Carrer de Higini Angles, 10",
    "sg:city":"Tarragona",
    "sg:orig_category":"Farmacias (repartici\u00d3n Y Al Por Mayor)",
    "sg:phone":"+34 977 21 57 33",
    "sg:postcode":"43001",
    "sg:province":"Tarragona",
    "wof:name":"Abadias Sierra Miguel Angel",
    "wof:placetype":"venue"
},
  "geometry": {"coordinates":[1.244865,41.117664],"type":"Point"}
}