{
  "type": "Feature",
  "properties": {
    "iso:country":"ES",
    "sg:address":"Rond Ingenioso Hidalgo, 43",
    "sg:city":"Madrid",
    "sg:orig_category":"Centros Empresariales",
    "sg:phone":"+34 913 72 15 85",
    "sg:postcode":"28034",
    "sg:province":"Madrid",
    "wof:name":"Merasur S.l.",
    "wof:placetype":"venue"
},
  "geometry": {"coordinates":[-3.6911408901,40.5013771057],"type":"Point"}
}