{
  "type": "Feature",
  "properties": {
    "addr:full":"Plaz Cueva Santa, 8 Segorbe Castell\u00f3n 12400",
    "addr:housenumber":"8",
    "addr:postcode":"12400",
    "addr:street":"Santa",
    "iso:country":"ES",
    "sg:address":"Plaz Cueva Santa, 8",
    "sg:city":"Segorbe",
    "sg:orig_category":"Reposter\u00cdas",
    "sg:phone":"+34 964 71 06 59",
    "sg:postcode":"12400",
    "sg:province":"Castell\u00f3n",
    "wof:name":"Salvador Gomez Maria Pilar",
    "wof:placetype":"venue"
},
  "geometry": {"coordinates":[-0.4885739982,39.8518714905],"type":"Point"}
}