{
  "type": "Feature",
  "properties": {
    "iso:country":"ES",
    "sg:address":"Rond Paisos Catalans (dels), 18",
    "sg:city":"Mataro",
    "sg:orig_category":"Delegados, Agentes De Tr\u00c1nsito, Auxiliares De Transporte Internacional",
    "sg:phone":"+34 937 98 08 00",
    "sg:postcode":"08304",
    "sg:province":"Barcelona",
    "wof:name":"Prados Linares Salvador",
    "wof:placetype":"venue"
},
  "geometry": {"coordinates":[2.4379780293,41.5533294678],"type":"Point"}
}