{
  "type": "Feature",
  "properties": {
    "iso:country":"ES",
    "sg:address":"Calle de Adarve, 5",
    "sg:city":"Utiel",
    "sg:orig_category":"Ense\u00d1anza, Formaci\u00d3n Profesional: Aprendizaje",
    "sg:phone":"+34 962 17 35 86",
    "sg:postcode":"46300",
    "sg:province":"Valencia",
    "wof:name":"Mancomunidad Del Interior Tierra Del Vino",
    "wof:placetype":"venue"
},
  "geometry": {"coordinates":[-1.2046599388,39.5678634644],"type":"Point"}
}