{
  "type": "Feature",
  "properties": {
    "iso:country":"ES",
    "sg:address":"Rua Tomas Mirambell, 19",
    "sg:city":"San Xoan",
    "sg:orig_category":"Pescader\u00cdas (al Por Mayor)",
    "sg:phone":"+34 986 38 30 50",
    "sg:postcode":"36340",
    "sg:province":"Pontevedra",
    "wof:name":"Pescados Y Mariscos Cabado Castro S.l.",
    "wof:placetype":"venue"
},
  "geometry": {"coordinates":[-8.8254985809,42.1492385864],"type":"Point"}
}