{
  "type": "Feature",
  "properties": {
    "addr:full":"Plaz Doctor Fortun, 1 Aguilas Murcia 30880",
    "addr:housenumber":"1",
    "addr:postcode":"30880",
    "addr:street":"Fortun",
    "iso:country":"ES",
    "sg:address":"Plaz Doctor Fortun, 1",
    "sg:city":"Aguilas",
    "sg:classifiers":[
        {
            "category":"Autos & Motor Vehicles",
            "subcategory":"Automobile Sales",
            "type":"Retail Goods"
        }
    ],
    "sg:phone":"+34 968 41 15 28",
    "sg:postcode":"30880",
    "sg:province":"Murcia",
    "wof:name":"Sanchez Morales Juan",
    "wof:placetype":"venue"
},
  "geometry": {"coordinates":[-1.5798319578,37.4052352905],"type":"Point"}
}