{
  "type": "Feature",
  "properties": {
    "iso:country":"ES",
    "sg:address":"Plaz Batallas, 13",
    "sg:city":"Valladolid",
    "sg:orig_category":"Peluquer\u00cdas, Peluquer\u00cda Mixta",
    "sg:phone":"+34 983 29 10 09",
    "sg:postcode":"47005",
    "sg:province":"Valladolid",
    "wof:name":"Panero Villace Julia",
    "wof:placetype":"venue"
},
  "geometry": {"coordinates":[-4.7133350372,41.6537971497],"type":"Point"}
}