{
  "type": "Feature",
  "properties": {
    "iso:country":"ES",
    "sg:address":"Calle de Susana Gonzalez, 40",
    "sg:city":"Bembibre",
    "sg:orig_category":"Cueros Y Pieles (al Por Mayor)",
    "sg:phone":"+34 987 51 00 18",
    "sg:postcode":"24300",
    "sg:province":"Le\u00f3n",
    "wof:name":"Martinez Garcia Casimiro",
    "wof:placetype":"venue"
},
  "geometry": {"coordinates":[-6.4170489311,42.614654541],"type":"Point"}
}