{
  "type": "Feature",
  "properties": {
    "addr:full":"Calle de Aluminio, 15 Arganda Madrid 28500",
    "addr:housenumber":"15",
    "addr:postcode":"28500",
    "addr:street":"Calle De Aluminio",
    "iso:country":"ES",
    "sg:address":"Calle de Aluminio, 15",
    "sg:city":"Arganda",
    "sg:orig_category":"Artes Gr\u00c1ficas, Artes Pl\u00c1sticas (curso)",
    "sg:phone":"+34 918 71 59 71",
    "sg:postcode":"28500",
    "sg:province":"Madrid",
    "wof:name":"Garo Manipulados Y Retractilados S.l.",
    "wof:placetype":"venue"
},
  "geometry": {"coordinates":[-3.4710972309,40.3015937805],"type":"Point"}
}