{
  "type": "Feature",
  "properties": {
    "addr:full":"Outeiro, 14 Outeiro La Coru\u00f1a 15147",
    "addr:housenumber":"14",
    "addr:postcode":"15147",
    "addr:street":"Outeiro;La Corun\u0303A",
    "iso:country":"ES",
    "sg:address":"Outeiro, 14",
    "sg:city":"Outeiro",
    "sg:orig_category":"Mec\u00c1nico Del Autom\u00d3vil",
    "sg:phone":"+34 981 73 45 16",
    "sg:postcode":"15147",
    "sg:province":"La Coru\u00f1a",
    "wof:name":"Mato Abelenda Ramon",
    "wof:placetype":"venue"
},
  "geometry": {"coordinates":[-8.8095941544,43.1652450562],"type":"Point"}
}