{
  "type": "Feature",
  "properties": {
    "iso:country":"ES",
    "sg:address":"Ctra. Madrid-irun, Km. 0115,0",
    "sg:city":"Boceguillas",
    "sg:orig_category":"Venta, Instalaci\u00d3n De Cocinas",
    "sg:phone":"+34 921 54 37 03",
    "sg:postcode":"40560",
    "sg:province":"Segovia",
    "wof:name":"Restaurante Tienda Area De Boceguillas S.l.",
    "wof:placetype":"venue"
},
  "geometry": {"coordinates":[-3.640734911,41.3357543945],"type":"Point"}
}