{
  "type": "Feature",
  "properties": {
    "iso:country":"ES",
    "sg:address":"Pase Arco De Ladrillo, 64",
    "sg:city":"Valladolid",
    "sg:orig_category":"Empresas De Vigilancia, Guardia Y Protecci\u00d3n",
    "sg:phone":"+34 983 22 82 10",
    "sg:postcode":"47008",
    "sg:province":"Valladolid",
    "wof:name":"Securitas Seguridad Espa\u00f1a S.a.",
    "wof:placetype":"venue"
},
  "geometry": {"coordinates":[-4.7270679474,41.6277236938],"type":"Point"}
}