{
  "type": "Feature",
  "properties": {
    "addr:full":"Calle de Salvia (la), 1 Cuenca Cuenca 16004",
    "addr:housenumber":"1",
    "addr:postcode":"16004",
    "addr:street":"Calle De Salvia La",
    "iso:country":"ES",
    "sg:address":"Calle de Salvia (la), 1",
    "sg:city":"Cuenca",
    "sg:orig_category":"Arquitectos",
    "sg:phone":"+34 969 22 09 62",
    "sg:postcode":"16004",
    "sg:province":"Cuenca",
    "wof:name":"Sarcon S.l.",
    "wof:placetype":"venue"
},
  "geometry": {"coordinates":[-2.134855032,40.0662536621],"type":"Point"}
}