{
  "type": "Feature",
  "properties": {
    "addr:full":"Carr Doctora Castells, 40 Lleida Lleida 25001",
    "addr:housenumber":"40",
    "addr:postcode":"25001",
    "addr:street":"Carr Doctora Castells",
    "iso:country":"ES",
    "sg:address":"Carr Doctora Castells, 40",
    "sg:city":"Lleida",
    "sg:orig_category":"Fabricaci\u00d3n, Importaci\u00d3n De Material Y Sistemas De Telecomunicaciones",
    "sg:phone":"+34 973 21 09 93",
    "sg:postcode":"25001",
    "sg:province":"Lleida",
    "wof:name":"B.t. Ce%ular Audio Catalunya S.l.",
    "wof:placetype":"venue"
},
  "geometry": {"coordinates":[0.6271240115,41.6085166931],"type":"Point"}
}