{
  "type": "Feature",
  "properties": {
    "iso:country":"ES",
    "sg:address":"Calle de Antonio Ayala Garre, 40",
    "sg:city":"Torre-pacheco",
    "sg:orig_category":"Agencias De Trabajo Temporal",
    "sg:phone":"+34 968 57 89 73",
    "sg:postcode":"30700",
    "sg:province":"Murcia",
    "sg:website":"www.interempleo.es",
    "wof:name":"Interempleo Empresa De Trabajo Temporal S.l.",
    "wof:placetype":"venue"
},
  "geometry": {"coordinates":[-0.9576895833,37.7465820312],"type":"Point"}
}