{
  "type": "Feature",
  "properties": {
    "addr:full":"Calle de Salvador Dali, 11 Majadahonda Madrid 28220",
    "addr:housenumber":"11",
    "addr:postcode":"28220",
    "addr:street":"Calle De Salvador Dali",
    "iso:country":"ES",
    "sg:address":"Calle de Salvador Dali, 11",
    "sg:city":"Majadahonda",
    "sg:orig_category":"Reposter\u00cdas",
    "sg:phone":"+34 916 34 51 23",
    "sg:postcode":"28220",
    "sg:province":"Madrid",
    "wof:name":"Marcos Diez Maria Del Carmen",
    "wof:placetype":"venue"
},
  "geometry": {"coordinates":[-3.8716540337,40.4739151001],"type":"Point"}
}