{
  "type": "Feature",
  "properties": {
    "addr:full":"Pol Ind Rio San Pedro, 3 Pto Real C\u00e1diz 11510",
    "addr:housenumber":"3",
    "addr:postcode":"11510",
    "addr:street":"San Pedro;Ca\u0301Diz",
    "iso:country":"ES",
    "sg:address":"Pol Ind Rio San Pedro, 3",
    "sg:city":"Pto Real",
    "sg:orig_category":"Fabricaci\u00d3n, Reparaci\u00d3n Y Mantenimiento De Construcciones Navales Y Fluviales",
    "sg:phone":"+34 956 47 32 65",
    "sg:postcode":"11510",
    "sg:province":"C\u00e1diz",
    "wof:name":"Mantdesur S.l.",
    "wof:placetype":"venue"
},
  "geometry": {"coordinates":[-6.1980991364,36.5308990479],"type":"Point"}
}