{
  "type": "Feature",
  "properties": {
    "addr:full":"Carrer de Balmes, 22 S. Cugat Valles Barcelona 08172",
    "addr:housenumber":"22",
    "addr:postcode":"08172",
    "addr:street":"Carrer De Balmes;S. Cugat Valles Barcelona",
    "iso:country":"ES",
    "sg:address":"Carrer de Balmes, 22",
    "sg:city":"S. Cugat Valles",
    "sg:orig_category":"Institutos De Belleza",
    "sg:phone":"+34 936 75 47 27",
    "sg:postcode":"08172",
    "sg:province":"Barcelona",
    "wof:name":"Delinea Sant Cugat S.l.",
    "wof:placetype":"venue"
},
  "geometry": {"coordinates":[2.0844919682,41.4723014832],"type":"Point"}
}