{
  "type": "Feature",
  "properties": {
    "addr:full":"Tv. Cuevas, 4 Santander Cantabria 39010",
    "addr:housenumber":"4",
    "addr:postcode":"39010",
    "addr:street":"Cuevas",
    "iso:country":"ES",
    "sg:address":"Tv. Cuevas, 4",
    "sg:city":"Santander",
    "sg:orig_category":"Parques De Atracciones Y Centros De Esparcimiento",
    "sg:phone":"+34 942 23 50 30",
    "sg:postcode":"39010",
    "sg:province":"Cantabria",
    "wof:name":"Salones Azar Santander S.l.",
    "wof:placetype":"venue"
},
  "geometry": {"coordinates":[-3.8100090027,43.4614982605],"type":"Point"}
}