{
  "type": "Feature",
  "properties": {
    "iso:country":"ES",
    "sg:address":"Requena, S/n",
    "sg:city":"Casas De Eufemia",
    "sg:orig_category":"Productores Recolectores, Venta Directa De Vinos",
    "sg:phone":"+34 962 33 41 81",
    "sg:postcode":"46352",
    "sg:province":"Valencia",
    "wof:name":"Cooperativa Agricola Inmaculada",
    "wof:placetype":"venue"
},
  "geometry": {"coordinates":[-1.2116940022,39.4490509033],"type":"Point"}
}