{
  "type": "Feature",
  "properties": {
    "addr:full":"Rua Pedregas, S/n Sarria Lugo 27600",
    "addr:housenumber":"s / n",
    "addr:postcode":"27600",
    "addr:street":"Rua Pedregas",
    "iso:country":"ES",
    "sg:address":"Rua Pedregas, S/n",
    "sg:city":"Sarria",
    "sg:orig_category":"Zapatos (al Por Menor)",
    "sg:phone":"+34 982 53 22 72",
    "sg:postcode":"27600",
    "sg:province":"Lugo",
    "wof:name":"Diaz Ponton Manuel",
    "wof:placetype":"venue"
},
  "geometry": {"coordinates":[-7.4145851135,42.779209137],"type":"Point"}
}