{
  "type": "Feature",
  "properties": {
    "addr:full":"Trav De Gracia, 209 Barcelona Barcelona 08012",
    "addr:housenumber":"209",
    "addr:postcode":"08012",
    "addr:street":"Trav De Gracia",
    "iso:country":"ES",
    "sg:address":"Trav De Gracia, 209",
    "sg:city":"Barcelona",
    "sg:orig_category":"Prendas Y Chalecos De Punto (al Por Menor)",
    "sg:phone":"+34 932 13 78 15",
    "sg:postcode":"08012",
    "sg:province":"Barcelona",
    "wof:name":"Sauri Arrive Jose Oriol",
    "wof:placetype":"venue"
},
  "geometry": {"coordinates":[2.1605670452,41.4031524658],"type":"Point"}
}