{
  "type": "Feature",
  "properties": {
    "addr:full":"Cami Del Serral-llarg, S/n Viladecans Barcelona 08840",
    "addr:housenumber":"s / n",
    "addr:postcode":"08840",
    "addr:street":"Cami Del Serral-Llarg",
    "iso:country":"ES",
    "sg:address":"Cami Del Serral-llarg, S/n",
    "sg:city":"Viladecans",
    "sg:orig_category":"Contenedores (mercanc\u00cdas)",
    "sg:phone":"+34 936 35 70 98",
    "sg:postcode":"08840",
    "sg:province":"Barcelona",
    "wof:name":"Bolet Trans S.l.",
    "wof:placetype":"venue"
},
  "geometry": {"coordinates":[2.0462100506,41.2784729004],"type":"Point"}
}