{
  "type": "Feature",
  "properties": {
    "addr:full":"Fermin Calbeton Kalea, 4 Eibar Guip\u00f9zcoa 20600",
    "addr:housenumber":"4",
    "addr:postcode":"20600",
    "addr:street":"Fermin Calbeton Kalea;Guipu\u0300Zcoa",
    "iso:country":"ES",
    "sg:address":"Fermin Calbeton Kalea, 4",
    "sg:city":"Eibar",
    "sg:orig_category":"Complementos De Vestir (al Por Menor)",
    "sg:phone":"+34 943 70 13 85",
    "sg:postcode":"20600",
    "sg:province":"Guip\u00f9zcoa",
    "wof:name":"Eguia Iturriaga S. A.",
    "wof:placetype":"venue"
},
  "geometry": {"coordinates":[-2.4725339413,43.1840133667],"type":"Point"}
}