{
  "type": "Feature",
  "properties": {
    "iso:country":"ES",
    "sg:address":"Calle de Cristo, 33",
    "sg:city":"Mostoles",
    "sg:orig_category":"M\u00c9dicos: Otorrinolaringolog\u00cda",
    "sg:phone":"+34 916 13 25 99",
    "sg:postcode":"28934",
    "sg:province":"Madrid",
    "wof:name":"Perez Arroyo Francisco",
    "wof:placetype":"venue"
},
  "geometry": {"coordinates":[-3.8668005466,40.321723938],"type":"Point"}
}