{
  "type": "Feature",
  "properties": {
    "addr:full":"Calle de Andres Segovia, S/n Rozas De Madrid Madrid 28230",
    "addr:postcode":"28230",
    "addr:street":"Calle De Andres Segovia S / N Rozas",
    "iso:country":"ES",
    "sg:address":"Calle de Andres Segovia, S/n",
    "sg:city":"Rozas De Madrid",
    "sg:orig_category":"Electricidad, Electr\u00d3nica: Material Y Suministros (al Por Mayor)",
    "sg:phone":"+34 916 36 01 55",
    "sg:postcode":"28230",
    "sg:province":"Madrid",
    "sg:website":"www.optomation.es",
    "wof:name":"Optomation Systems S.l.",
    "wof:placetype":"venue"
},
  "geometry": {"coordinates":[-3.8723623753,40.4901123047],"type":"Point"}
}