{
  "type": "Feature",
  "properties": {
    "addr:full":"Pl Mercat, 10 Barcelona Barcelona 08018",
    "addr:housenumber":"10",
    "addr:postcode":"08018",
    "addr:street":"Pl Mercat",
    "iso:country":"ES",
    "sg:address":"Pl Mercat, 10",
    "sg:city":"Barcelona",
    "sg:orig_category":"Zapatos (al Por Menor)",
    "sg:phone":"+34 932 45 39 32",
    "sg:postcode":"08018",
    "sg:province":"Barcelona",
    "wof:name":"Eljarrat Beniflah Mair",
    "wof:placetype":"venue"
},
  "geometry": {"coordinates":[2.1884551048,41.4071502686],"type":"Point"}
}