{
  "type": "Feature",
  "properties": {
    "addr:full":"Calle de Capuchinas, 1 Huesca Huesca 22003",
    "addr:housenumber":"1",
    "addr:postcode":"22003",
    "addr:street":"Calle De Capuchinas",
    "iso:country":"ES",
    "sg:address":"Calle de Capuchinas, 1",
    "sg:city":"Huesca",
    "sg:orig_category":"Transporte En General",
    "sg:phone":"+34 974 24 18 71",
    "sg:postcode":"22003",
    "sg:province":"Huesca",
    "wof:name":"Dagesa",
    "wof:placetype":"venue"
},
  "geometry": {"coordinates":[-0.4134446979,42.1394577026],"type":"Point"}
}