{
  "type": "Feature",
  "properties": {
    "addr:full":"Avda Obispo Perez Caceres, 16 G\u00fcimar Santa Cruz De Tenerife 38500",
    "addr:housenumber":"16",
    "addr:postcode":"38500",
    "addr:street":"Avda Obispo Perez Caceres",
    "iso:country":"ES",
    "sg:address":"Avda Obispo Perez Caceres, 16",
    "sg:city":"G\u00fcimar",
    "sg:orig_category":"Instalaci\u00d3n, Reparaci\u00d3n De Calefacci\u00d3n El\u00c9ctrica",
    "sg:phone":"+34 922 51 32 17",
    "sg:postcode":"38500",
    "sg:province":"Santa Cruz De Tenerife",
    "wof:name":"Gonzalez Estevez Juan",
    "wof:placetype":"venue"
},
  "geometry": {"coordinates":[-16.4101734161,28.3158569336],"type":"Point"}
}