{
  "type": "Feature",
  "properties": {
    "iso:country":"ES",
    "sg:address":"Calle de Cristo, 47",
    "sg:city":"Valdepe\u00f1as",
    "sg:orig_category":"Asesor\u00cdas",
    "sg:phone":"+34 926 32 42 59",
    "sg:postcode":"13300",
    "sg:province":"Ciudad Real",
    "wof:name":"Gefisa Gestion S.l.",
    "wof:placetype":"venue"
},
  "geometry": {"coordinates":[-3.3906621933,38.7592544556],"type":"Point"}
}