{
  "type": "Feature",
  "properties": {
    "addr:full":"Pase Castellana, 46 Madrid Madrid 28046",
    "addr:housenumber":"46",
    "addr:postcode":"madrid;28046",
    "addr:street":"Castellana",
    "iso:country":"ES",
    "sg:address":"Pase Castellana, 46",
    "sg:city":"Madrid",
    "sg:orig_category":"Centros Empresariales",
    "sg:phone":"+34 915 75 80 82",
    "sg:postcode":"28046",
    "sg:province":"Madrid",
    "wof:name":"Oficina De Pesca Maritima De Irlanda",
    "wof:placetype":"venue"
},
  "geometry": {"coordinates":[-3.6881580353,40.4340591431],"type":"Point"}
}