{
  "type": "Feature",
  "properties": {
    "addr:full":"Po. Maritim, 4 Cala Bona Islas Baleares 07559",
    "addr:housenumber":"4",
    "addr:postcode":"07559",
    "addr:street":"Po. Maritim",
    "iso:country":"ES",
    "sg:address":"Po. Maritim, 4",
    "sg:city":"Cala Bona",
    "sg:orig_category":"Hoteles",
    "sg:phone":"+34 971 58 52 83",
    "sg:postcode":"07559",
    "sg:province":"Islas Baleares",
    "wof:name":"Sonlluc S.a.",
    "wof:placetype":"venue"
},
  "geometry": {"coordinates":[3.3866999149,39.6109313965],"type":"Point"}
}