{
  "type": "Feature",
  "properties": {
    "addr:full":"Calle de Saturnino Abuin, 9 Tordesillas Valladolid 47100",
    "addr:housenumber":"9",
    "addr:postcode":"47100",
    "addr:street":"Calle De Saturnino Abuin",
    "iso:country":"ES",
    "sg:address":"Calle de Saturnino Abuin, 9",
    "sg:city":"Tordesillas",
    "sg:orig_category":"Material Y Herramientas Agr\u00cdcolas",
    "sg:phone":"+34 983 77 11 77",
    "sg:postcode":"47100",
    "sg:province":"Valladolid",
    "wof:name":"Merino Gonzalez Andres",
    "wof:placetype":"venue"
},
  "geometry": {"coordinates":[-4.9959888458,41.5072059631],"type":"Point"}
}