{
  "type": "Feature",
  "properties": {
    "addr:full":"Calle de Oreitiasolo, 2 Vitoria-gasteiz \u00c1lava 01006",
    "addr:housenumber":"2",
    "addr:postcode":"01006",
    "addr:street":"Calle De Oreitiasolo",
    "iso:country":"ES",
    "sg:address":"Calle de Oreitiasolo, 2",
    "sg:city":"Vitoria-gasteiz",
    "sg:orig_category":"Hormig\u00d3n Listo Para Usar",
    "sg:phone":"+34 945 13 93 13",
    "sg:postcode":"01006",
    "sg:province":"\u00c1lava",
    "wof:name":"Morteros Alaveses S.l.",
    "wof:placetype":"venue"
},
  "geometry": {"coordinates":[-2.6564838886,42.8382949829],"type":"Point"}
}