{
  "type": "Feature",
  "properties": {
    "addr:full":"Ctra Cartama (de), 3 Alhaurin El Grande M\u00e1laga 29120",
    "addr:postcode":"29120",
    "addr:street":"Ctra Cartama De 3",
    "iso:country":"ES",
    "sg:address":"Ctra Cartama (de), 3",
    "sg:city":"Alhaurin El Grande",
    "sg:orig_category":"Inmobiliaria (agencias)",
    "sg:phone":"+34 952 49 91 64",
    "sg:postcode":"29120",
    "sg:province":"M\u00e1laga",
    "wof:name":"Vale Estates S.l.",
    "wof:placetype":"venue"
},
  "geometry": {"coordinates":[-4.6828818321,36.6442680359],"type":"Point"}
}