{
  "type": "Feature",
  "properties": {
    "addr:full":"Carrer de Pompeu Fabra, 232 Terrassa Barcelona 08226",
    "addr:housenumber":"232",
    "addr:postcode":"08226",
    "addr:street":"Carrer De Pompeu Fabra",
    "iso:country":"ES",
    "sg:address":"Carrer de Pompeu Fabra, 232",
    "sg:city":"Terrassa",
    "sg:orig_category":"Agencias Y Asesores De Publicidad",
    "sg:phone":"+34 937 35 71 34",
    "sg:postcode":"08226",
    "sg:province":"Barcelona",
    "wof:name":"B2b Barcelona Business S.l.",
    "wof:placetype":"venue"
},
  "geometry": {"coordinates":[2.023291111,41.5796737671],"type":"Point"}
}