{
  "type": "Feature",
  "properties": {
    "iso:country":"ES",
    "sg:address":"Cra Laurea Miro, 256",
    "sg:city":"Sant Feliu Llobregat",
    "sg:orig_category":"Poller\u00cda Y Caza (al Por Menor)",
    "sg:phone":"+34 936 66 97 34",
    "sg:postcode":"08980",
    "sg:province":"Barcelona",
    "wof:name":"Pamplona Sancho Maria Concepcion",
    "wof:placetype":"venue"
},
  "geometry": {"coordinates":[2.0428450108,41.3820266724],"type":"Point"}
}