{
  "type": "Feature",
  "properties": {
    "iso:country":"ES",
    "sg:address":"Ctra. Sabi\u00f1anigo, S/n",
    "sg:city":"Jaca",
    "sg:orig_category":"Poller\u00cda Y Caza (al Por Menor)",
    "sg:phone":"+34 974 36 06 84",
    "sg:postcode":"22700",
    "sg:province":"Huesca",
    "wof:name":"Betran Val Vicente",
    "wof:placetype":"venue"
},
  "geometry": {"coordinates":[-0.5463190079,42.5656318665],"type":"Point"}
}