{
  "type": "Feature",
  "properties": {
    "iso:country":"ES",
    "sg:address":"Calle de San Lorenzo, 5",
    "sg:city":"Porcuna",
    "sg:orig_category":"Transporte En General",
    "sg:phone":"+34 953 54 42 21",
    "sg:postcode":"23790",
    "sg:province":"Ja\u00e9n",
    "wof:name":"Toribio Huerta Manuel Francisco",
    "wof:placetype":"venue"
},
  "geometry": {"coordinates":[-4.1870388985,37.8736343384],"type":"Point"}
}