{
  "type": "Feature",
  "properties": {
    "iso:country":"ES",
    "sg:address":"Rua Ourense, 22",
    "sg:city":"Portonovo",
    "sg:orig_category":"Alimentaci\u00d3n General (al Por Menor)",
    "sg:phone":"+34 986 72 30 68",
    "sg:postcode":"36970",
    "sg:province":"Pontevedra",
    "wof:name":"Torres Magari\u00f1os Manuel",
    "wof:placetype":"venue"
},
  "geometry": {"coordinates":[-8.8257932663,42.3923416138],"type":"Point"}
}