{
  "type": "Feature",
  "properties": {
    "iso:country":"ES",
    "sg:address":"Calle de Ntra Sra Del Salz, 7",
    "sg:city":"Zaragoza",
    "sg:orig_category":"Limpieza Con Chorro De Arena Y Con Granalla, Pulido",
    "sg:phone":"+34 976 32 85 32",
    "sg:postcode":"50017",
    "sg:province":"Zaragoza",
    "wof:name":"Garcia Magdalena Vicente",
    "wof:placetype":"venue"
},
  "geometry": {"coordinates":[-0.914929986,41.6499786377],"type":"Point"}
}