{
  "type": "Feature",
  "properties": {
    "iso:country":"ES",
    "sg:address":"Calle de Chiquinquira, 26",
    "sg:city":"Madrid",
    "sg:orig_category":"Inform\u00c1tica (estudios, Servicios, Asesor\u00cda, Formaci\u00d3n)",
    "sg:phone":"+34 913 81 23 70",
    "sg:postcode":"28033",
    "sg:province":"Madrid",
    "sg:website":"www.mustang-system.net",
    "wof:name":"Mustang Systems S.l.",
    "wof:placetype":"venue"
},
  "geometry": {"coordinates":[-3.6370720863,40.4717788696],"type":"Point"}
}