{
  "type": "Feature",
  "properties": {
    "addr:full":"Carrer de Villa, 5 S. Cugat Valles Barcelona 08172",
    "addr:housenumber":"5",
    "addr:postcode":"08172",
    "addr:street":"Carrer De Villa;Barcelona",
    "iso:country":"ES",
    "sg:address":"Carrer de Villa, 5",
    "sg:city":"S. Cugat Valles",
    "sg:orig_category":"M\u00c9dicos: Foniatr\u00cda Y Logopedia",
    "sg:phone":"+34 935 89 12 15",
    "sg:postcode":"08172",
    "sg:province":"Barcelona",
    "wof:name":"Terapeutes Associats Villa",
    "wof:placetype":"venue"
},
  "geometry": {"coordinates":[2.0796918869,41.4678268433],"type":"Point"}
}