{
  "type": "Feature",
  "properties": {
    "addr:full":"Calle de Salvador Minguijon, 15 Zaragoza Zaragoza 50002",
    "addr:housenumber":"15",
    "addr:postcode":"50002",
    "addr:street":"Calle De Salvador Minguijon",
    "iso:country":"ES",
    "sg:address":"Calle de Salvador Minguijon, 15",
    "sg:city":"Zaragoza",
    "sg:orig_category":"Zapatos (al Por Menor)",
    "sg:phone":"+34 976 49 16 23",
    "sg:postcode":"50002",
    "sg:province":"Zaragoza",
    "wof:name":"Bailo Yecora Angel",
    "wof:placetype":"venue"
},
  "geometry": {"coordinates":[-0.8620120287,41.6462783813],"type":"Point"}
}