{
  "type": "Feature",
  "properties": {
    "addr:full":"Rond Pinar Del Conde (del), 1 Puerto De Santa Maria C\u00e1diz 11500",
    "addr:postcode":"11500",
    "addr:street":"Del 1;Ca\u0301Diz",
    "iso:country":"ES",
    "sg:address":"Rond Pinar Del Conde (del), 1",
    "sg:city":"Puerto De Santa Maria",
    "sg:orig_category":"Serigraf\u00cda (material Y Suministros)",
    "sg:phone":"+34 956 87 48 02",
    "sg:postcode":"11500",
    "sg:province":"C\u00e1diz",
    "wof:name":"Macias Gatica Carlos",
    "wof:placetype":"venue"
},
  "geometry": {"coordinates":[-6.2353339195,36.6017379761],"type":"Point"}
}