{
  "type": "Feature",
  "properties": {
    "iso:country":"ES",
    "sg:address":"Calle de Gonzalo Bilbao, 24",
    "sg:city":"Sevilla",
    "sg:orig_category":"Agentes, Concesionarios Y Sucursales De Veh\u00cdculos",
    "sg:phone":"+34 954 53 38 16",
    "sg:postcode":"41003",
    "sg:province":"Sevilla",
    "wof:name":"Repuestos Jofer S.a.",
    "wof:placetype":"venue"
},
  "geometry": {"coordinates":[-5.9795088768,37.3913612366],"type":"Point"}
}