{
  "type": "Feature",
  "properties": {
    "iso:country":"ES",
    "sg:address":"Ptda Carrio I, 14",
    "sg:city":"Calpe",
    "sg:orig_category":"Institutos De Belleza",
    "sg:phone":"+34 965 83 10 01",
    "sg:postcode":"03710",
    "sg:province":"Alicante",
    "wof:name":"Euro Touch S.l.",
    "wof:placetype":"venue"
},
  "geometry": {"coordinates":[0.0535200015,38.6515808105],"type":"Point"}
}