{
  "type": "Feature",
  "properties": {
    "iso:country":"ES",
    "sg:address":"Avda Jose Luis Arrese, 32",
    "sg:city":"Valladolid",
    "sg:orig_category":"Asesor\u00cda Sobre Comunicaci\u00d3n De Empresas",
    "sg:phone":"+34 983 33 29 55",
    "sg:postcode":"47014",
    "sg:province":"Valladolid",
    "wof:name":"Applus Norcontrol S.l.u.",
    "wof:placetype":"venue"
},
  "geometry": {"coordinates":[-4.7429046631,41.6522064209],"type":"Point"}
}