{
  "type": "Feature",
  "properties": {
    "addr:full":"Carrer de Pare Palau, S/n Valls Tarragona 43800",
    "addr:housenumber":"s / n",
    "addr:postcode":"43800",
    "addr:street":"Carrer De Pare Palau",
    "iso:country":"ES",
    "sg:address":"Carrer de Pare Palau, S/n",
    "sg:city":"Valls",
    "sg:orig_category":"Ense\u00d1anza, Formaci\u00d3n Profesional: Aprendizaje",
    "sg:phone":"+34 977 61 21 64",
    "sg:postcode":"43800",
    "sg:province":"Tarragona",
    "wof:name":"Ajuntament De Valls",
    "wof:placetype":"venue"
},
  "geometry": {"coordinates":[1.2567251921,41.2871627808],"type":"Point"}
}