{
  "type": "Feature",
  "properties": {
    "iso:country":"ES",
    "sg:address":"Avda Campones, 2",
    "sg:city":"Gijon",
    "sg:orig_category":"Reparaciones Y Remolcado De Veh\u00cdculos",
    "sg:phone":"+34 985 32 78 95",
    "sg:postcode":"33211",
    "sg:province":"Asturias",
    "wof:name":"Autolavado Los Campones S.l",
    "wof:placetype":"venue"
},
  "geometry": {"coordinates":[-5.6929793358,43.5325164795],"type":"Point"}
}