{
  "type": "Feature",
  "properties": {
    "iso:country":"ES",
    "sg:address":"Camino De La Dehesa, S/n",
    "sg:city":"Portillo",
    "sg:orig_category":"Alfarer\u00cda",
    "sg:phone":"+34 983 55 60 84",
    "sg:postcode":"47160",
    "sg:province":"Valladolid",
    "wof:name":"Garnacho Tranque Policarpo",
    "wof:placetype":"venue"
},
  "geometry": {"coordinates":[-4.6011743546,41.4759483337],"type":"Point"}
}