{
  "type": "Feature",
  "properties": {
    "iso:country":"ES",
    "sg:address":"Calle de San Andres, 155",
    "sg:city":"Coru\u00d1a",
    "sg:orig_category":"Moquetas, Alfombras (al Por Menor)",
    "sg:phone":"+34 981 22 88 49",
    "sg:postcode":"15003",
    "sg:province":"La Coru\u00f1a",
    "wof:name":"El Palacio De Las Alfombras S.l.",
    "wof:placetype":"venue"
},
  "geometry": {"coordinates":[-8.4059095383,43.3680686951],"type":"Point"}
}