{
  "type": "Feature",
  "properties": {
    "iso:country":"ES",
    "sg:address":"Mirador Despe\u00f1aperros, 14",
    "sg:city":"Collado Villalba",
    "sg:orig_category":"Urbanistas",
    "sg:phone":"+34 918 51 09 72",
    "sg:postcode":"28400",
    "sg:province":"Madrid",
    "wof:name":"Pereira Gawendo Raquel",
    "wof:placetype":"venue"
},
  "geometry": {"coordinates":[-3.9766728878,40.6452484131],"type":"Point"}
}