{
  "type": "Feature",
  "properties": {
    "iso:country":"ES",
    "sg:address":"Carr Moll, 20",
    "sg:city":"Alcudia",
    "sg:orig_category":"Mercer\u00cda, Lencer\u00cda (al Por Menor)",
    "sg:phone":"+34 971 54 66 43",
    "sg:postcode":"07400",
    "sg:province":"Islas Baleares",
    "wof:name":"Fepperatu Comunidad De Bienes",
    "wof:placetype":"venue"
},
  "geometry": {"coordinates":[3.1242699623,39.8452415466],"type":"Point"}
}