{
  "type": "Feature",
  "properties": {
    "addr:full":"Calle de Prado, 7 Moreruela De Los Infanzones Zamora 49731",
    "addr:housenumber":"7",
    "addr:postcode":"49731",
    "addr:street":"Calle De Prado",
    "iso:country":"ES",
    "sg:address":"Calle de Prado, 7",
    "sg:city":"Moreruela De Los Infanzones",
    "sg:orig_category":"Producci\u00d3n, Venta De Productos De Agricultura Biol\u00d3gica",
    "sg:phone":"+34 980 50 45 09",
    "sg:postcode":"49731",
    "sg:province":"Zamora",
    "wof:name":"Martin Fariza Eleodoro",
    "wof:placetype":"venue"
},
  "geometry": {"coordinates":[-5.7022800446,41.6326179504],"type":"Point"}
}