{
  "type": "Feature",
  "properties": {
    "iso:country":"ES",
    "sg:address":"Calle de Mayor, 27",
    "sg:city":"Alcorcon",
    "sg:orig_category":"Electrodom\u00c9sticos (al Por Menor)",
    "sg:phone":"+34 916 43 86 25",
    "sg:postcode":"28921",
    "sg:province":"Madrid",
    "sg:website":"www.mateosmobiliario.es",
    "wof:name":"Mateos Davila Juan",
    "wof:placetype":"venue"
},
  "geometry": {"coordinates":[-3.8277239799,40.3473930359],"type":"Point"}
}