{
  "type": "Feature",
  "properties": {
    "addr:full":"Carrer de Pallars, 403 Barcelona Barcelona 08019",
    "addr:housenumber":"403",
    "addr:postcode":"08019",
    "addr:street":"Carrer De Pallars",
    "iso:country":"ES",
    "sg:address":"Carrer de Pallars, 403",
    "sg:city":"Barcelona",
    "sg:orig_category":"Fabricaci\u00d3n De Papel Pintado",
    "sg:phone":"+34 932 66 26 60",
    "sg:postcode":"08019",
    "sg:province":"Barcelona",
    "wof:name":"Salleras Papeles Pintados Y Material Para Decoracion S. A.",
    "wof:placetype":"venue"
},
  "geometry": {"coordinates":[2.2092630863,41.4099807739],"type":"Point"}
}