{
  "type": "Feature",
  "properties": {
    "addr:full":"Ausias March, 2 Genoves Valencia 46894",
    "addr:housenumber":"2",
    "addr:postcode":"46894",
    "addr:street":"March",
    "iso:country":"ES",
    "sg:address":"Ausias March, 2",
    "sg:city":"Genoves",
    "sg:orig_category":"Arboricultura Y Producci\u00d3n De Frutas",
    "sg:phone":"+34 962 22 93 17",
    "sg:postcode":"46894",
    "sg:province":"Valencia",
    "wof:name":"Sanchis Llopis Pascual",
    "wof:placetype":"venue"
},
  "geometry": {"coordinates":[-0.4655770063,38.9892692566],"type":"Point"}
}