{
  "type": "Feature",
  "properties": {
    "addr:full":"Calle de Conquistadores, 6 Ca\u00f1amero C\u00e1ceres 10136",
    "addr:housenumber":"6",
    "addr:postcode":"10136",
    "addr:street":"Calle De Conquistadores;Ca\u0301Ceres",
    "iso:country":"ES",
    "sg:address":"Calle de Conquistadores, 6",
    "sg:city":"Ca\u00f1amero",
    "sg:orig_category":"Contenedores (mercanc\u00cdas)",
    "sg:phone":"+34 927 36 92 82",
    "sg:postcode":"10136",
    "sg:province":"C\u00e1ceres",
    "wof:name":"Torres Sanchez Rufino",
    "wof:placetype":"venue"
},
  "geometry": {"coordinates":[-5.3891911507,39.3806304932],"type":"Point"}
}