{
  "type": "Feature",
  "properties": {
    "addr:full":"Calle de Jeronimo Sainz De La Maza, 10 Santander Cantabria 39008",
    "addr:housenumber":"10",
    "addr:postcode":"39008",
    "addr:street":"Calle De Jeronimo Sainz De La Maza",
    "iso:country":"ES",
    "sg:address":"Calle de Jeronimo Sainz De La Maza, 10",
    "sg:city":"Santander",
    "sg:orig_category":"Ortopedia General",
    "sg:phone":"+34 942 34 77 50",
    "sg:postcode":"39008",
    "sg:province":"Cantabria",
    "wof:name":"Gutierrez Gomez Miguel",
    "wof:placetype":"venue"
},
  "geometry": {"coordinates":[-3.8267560005,43.4573287964],"type":"Point"}
}