{
  "type": "Feature",
  "properties": {
    "iso:country":"ES",
    "sg:address":"Calle de Leon Y Castillo, 182",
    "sg:city":"Palmas De Gran Canaria",
    "sg:orig_category":"Peluqueros: De Se\u00d1oras",
    "sg:phone":"+34 928 29 04 91",
    "sg:postcode":"35004",
    "sg:province":"Las Palmas",
    "wof:name":"Perez Morales Sandra",
    "wof:placetype":"venue"
},
  "geometry": {"coordinates":[-15.4237804413,28.117767334],"type":"Point"}
}