{
  "type": "Feature",
  "properties": {
    "iso:country":"ES",
    "sg:address":"Carrer de Major, 61",
    "sg:city":"Molins Rei",
    "sg:orig_category":"Talleres: Ropa A Medida",
    "sg:phone":"+34 936 68 19 41",
    "sg:postcode":"08750",
    "sg:province":"Barcelona",
    "wof:name":"Casajuana Orive Jose",
    "wof:placetype":"venue"
},
  "geometry": {"coordinates":[2.0176739693,41.4125175476],"type":"Point"}
}