{
  "type": "Feature",
  "properties": {
    "addr:full":"Altozano Arzobispo Jose Manuel Estepa, 5 Andujar Ja\u00e9n 23740",
    "addr:housenumber":"5",
    "addr:postcode":"23740",
    "addr:street":"Altozano;Jose;Estepa",
    "iso:country":"ES",
    "sg:address":"Altozano Arzobispo Jose Manuel Estepa, 5",
    "sg:city":"Andujar",
    "sg:orig_category":"Cooperativas Agr\u00cdcolas",
    "sg:phone":"+34 953 51 37 21",
    "sg:postcode":"23740",
    "sg:province":"Ja\u00e9n",
    "wof:name":"Agencia Estatal De Administracion Tributaria",
    "wof:placetype":"venue"
},
  "geometry": {"coordinates":[-4.0286779404,38.2897567749],"type":"Point"}
}