{
  "type": "Feature",
  "properties": {
    "iso:country":"ES",
    "sg:address":"Calle de Villalba, General, 30",
    "sg:city":"Melilla",
    "sg:orig_category":"Cajas De Ahorro",
    "sg:phone":"+34 952 69 61 59",
    "sg:postcode":"52006",
    "sg:province":"Melilla",
    "sg:website":"www.unicaja.es",
    "wof:name":"Unicaja",
    "wof:placetype":"venue"
},
  "geometry": {"coordinates":[-2.9391715527,35.276184082],"type":"Point"}
}