{
  "type": "Feature",
  "properties": {
    "addr:full":"Calle de Mata Linares, 16 S. Vicente Barquera Cantabria 39540",
    "addr:housenumber":"16",
    "addr:postcode":"39540",
    "addr:street":"Calle De Mata Linares;S. Vicente",
    "iso:country":"ES",
    "sg:address":"Calle de Mata Linares, 16",
    "sg:city":"S. Vicente Barquera",
    "sg:orig_category":"Mec\u00c1nico Del Autom\u00d3vil",
    "sg:phone":"+34 942 71 25 25",
    "sg:postcode":"39540",
    "sg:province":"Cantabria",
    "wof:name":"Talleres Okey S.l.",
    "wof:placetype":"venue"
},
  "geometry": {"coordinates":[-4.4006986618,43.3827857971],"type":"Point"}
}