{
  "type": "Feature",
  "properties": {
    "addr:full":"Calle de Barcelo, 3 Madrid Madrid 28004",
    "addr:housenumber":"3",
    "addr:postcode":"28004",
    "addr:street":"Calle De Barcelo",
    "iso:country":"ES",
    "sg:address":"Calle de Barcelo, 3",
    "sg:city":"Madrid",
    "sg:orig_category":"Pescader\u00cdas (al Por Mayor)",
    "sg:phone":"+34 917 01 05 28",
    "sg:postcode":"28004",
    "sg:province":"Madrid",
    "sg:website":"www.neginter.com",
    "wof:name":"Neginter Euroamericana S.l.",
    "wof:placetype":"venue"
},
  "geometry": {"coordinates":[-3.7009193897,40.4263954163],"type":"Point"}
}