{
  "type": "Feature",
  "properties": {
    "addr:full":"Puerta De San Roman De Hornija, 3 Toro Zamora 49800",
    "addr:housenumber":"3",
    "addr:postcode":"49800",
    "iso:country":"ES",
    "sg:address":"Puerta De San Roman De Hornija, 3",
    "sg:city":"Toro",
    "sg:orig_category":"T\u00c9cnicos Veterinarios",
    "sg:phone":"+34 980 69 01 65",
    "sg:postcode":"49800",
    "sg:province":"Zamora",
    "wof:name":"Gabriel Garcia Miguel",
    "wof:placetype":"venue"
},
  "geometry": {"coordinates":[-5.3906588554,41.525844574],"type":"Point"}
}