{
  "type": "Feature",
  "properties": {
    "iso:country":"ES",
    "sg:address":"Rbla Marina, 183",
    "sg:city":"Hospitalet Llobregat",
    "sg:orig_category":"Muebles, Minoristas",
    "sg:phone":"+34 933 35 30 23",
    "sg:postcode":"08907",
    "sg:province":"Barcelona",
    "wof:name":"Miret Salvat Liberto",
    "wof:placetype":"venue"
},
  "geometry": {"coordinates":[2.1099541187,41.3503570557],"type":"Point"}
}