{
  "type": "Feature",
  "properties": {
    "iso:country":"ES",
    "sg:address":"Av Onze De Setembre, 81",
    "sg:city":"Sant Joan De Palamos",
    "sg:orig_category":"Molduras, Junquillos, Listones Y Molduras Perforadas",
    "sg:phone":"+34 972 31 69 08",
    "sg:postcode":"17230",
    "sg:province":"Girona",
    "wof:name":"Riba Berengueras Carlos",
    "wof:placetype":"venue"
},
  "geometry": {"coordinates":[3.1279499531,41.8474006653],"type":"Point"}
}