{
  "type": "Feature",
  "properties": {
    "iso:country":"ES",
    "sg:address":"Carr Estacio, 35",
    "sg:city":"Termens",
    "sg:orig_category":"Comunidades Religiosas",
    "sg:phone":"+34 973 18 00 55",
    "sg:postcode":"25670",
    "sg:province":"Lleida",
    "wof:name":"Bisbat D'urgell",
    "wof:placetype":"venue"
},
  "geometry": {"coordinates":[0.7597749829,41.7178993225],"type":"Point"}
}