{
  "type": "Feature",
  "properties": {
    "iso:country":"ES",
    "sg:address":"Avda Extremadura, 31",
    "sg:city":"Castuera",
    "sg:orig_category":"Negocio De Materiales De Construcci\u00d3n",
    "sg:phone":"+34 924 76 08 64",
    "sg:postcode":"06420",
    "sg:province":"Badajoz",
    "wof:name":"Morillo Rosa Amparo",
    "wof:placetype":"venue"
},
  "geometry": {"coordinates":[-5.5462827682,38.7295532227],"type":"Point"}
}