{
  "type": "Feature",
  "properties": {
    "addr:full":"G.v. Corts Catalanes, 428 Barcelona Barcelona 08015",
    "addr:housenumber":"428",
    "addr:postcode":"08015",
    "addr:street":"Catalanes",
    "iso:country":"ES",
    "sg:address":"G.v. Corts Catalanes, 428",
    "sg:city":"Barcelona",
    "sg:orig_category":"Centros Empresariales",
    "sg:phone":"+34 933 25 18 98",
    "sg:postcode":"08015",
    "sg:province":"Barcelona",
    "wof:name":"Gremi De Comerciants De Materials De Construccio",
    "wof:placetype":"venue"
},
  "geometry": {"coordinates":[2.1533660889,41.3777961731],"type":"Point"}
}