{
  "type": "Feature",
  "properties": {
    "addr:full":"Carrer de Sant Benilde, 10 Zona Eixample Tarragona 43006",
    "addr:housenumber":"10",
    "addr:postcode":"43006",
    "addr:street":"Carrer De Sant Benilde",
    "iso:country":"ES",
    "sg:address":"Carrer de Sant Benilde, 10",
    "sg:city":"Zona Eixample",
    "sg:orig_category":"Molduras, Junquillos, Listones Y Molduras Perforadas",
    "sg:phone":"+34 977 55 02 10",
    "sg:postcode":"43006",
    "sg:province":"Tarragona",
    "wof:name":"Galindo Ortiz Ambrosio",
    "wof:placetype":"venue"
},
  "geometry": {"coordinates":[1.2120889425,41.1192741394],"type":"Point"}
}