{
  "type": "Feature",
  "properties": {
    "addr:full":"Calle de Sierra De Monchique, 7 Madrid Madrid 28053",
    "addr:housenumber":"7",
    "addr:postcode":"madrid;28053",
    "addr:street":"Calle De Sierra De Monchique",
    "iso:country":"ES",
    "sg:address":"Calle de Sierra De Monchique, 7",
    "sg:city":"Madrid",
    "sg:orig_category":"Vinos Y Licores (venta Al Por Menor)",
    "sg:phone":"+34 914 77 50 71",
    "sg:postcode":"28053",
    "sg:province":"Madrid",
    "wof:name":"Martin Garcia Miguel",
    "wof:placetype":"venue"
},
  "geometry": {"coordinates":[-3.6678800583,40.3929977417],"type":"Point"}
}