{
  "type": "Feature",
  "properties": {
    "iso:country":"ES",
    "sg:address":"Ctra Almeria, S/n",
    "sg:city":"Vera",
    "sg:orig_category":"Suministros Y Materiales Industriales",
    "sg:phone":"+34 950 39 33 40",
    "sg:postcode":"04620",
    "sg:province":"Almer\u00eda",
    "wof:name":"Juan Gonzalez Parra S.l.",
    "wof:placetype":"venue"
},
  "geometry": {"coordinates":[-1.8765989542,37.2511405945],"type":"Point"}
}