{
  "type": "Feature",
  "properties": {
    "iso:country":"ES",
    "sg:address":"Cami Francesos, 14",
    "sg:city":"Buvisa",
    "sg:orig_category":"Fabricaci\u00d3n De Sobres, Bolsas Y Fundas",
    "sg:phone":"+34 937 54 80 49",
    "sg:postcode":"08338",
    "sg:province":"Barcelona",
    "wof:name":"Ferran Alcaide S.l.",
    "wof:placetype":"venue"
},
  "geometry": {"coordinates":[2.3460769653,41.505153656],"type":"Point"}
}