{
  "type": "Feature",
  "properties": {
    "addr:full":"Calle de San Agustin, 22 Requena Valencia 46340",
    "addr:housenumber":"22",
    "addr:postcode":"46340",
    "addr:street":"Calle De San Agustin",
    "iso:country":"ES",
    "sg:address":"Calle de San Agustin, 22",
    "sg:city":"Requena",
    "sg:classifiers":[
        {
            "category":"Autos & Motor Vehicles",
            "subcategory":"Automobile Sales",
            "type":"Retail Goods"
        }
    ],
    "sg:phone":"+34 962 30 32 50",
    "sg:postcode":"46340",
    "sg:province":"Valencia",
    "wof:name":"Cuenca Martinez Alejandro Daniel",
    "wof:placetype":"venue"
},
  "geometry": {"coordinates":[-1.1017940044,39.488910675],"type":"Point"}
}