{
  "type": "Feature",
  "properties": {
    "iso:country":"ES",
    "sg:address":"Ibargarai Hiribidea, 20",
    "sg:city":"Bergara",
    "sg:orig_category":"Sociedades, Compa\u00d1\u00cdas Aseguradoras",
    "sg:phone":"+34 943 76 57 85",
    "sg:postcode":"20570",
    "sg:province":"Guip\u00f9zcoa",
    "wof:name":"Casimiro Briz Seguros S.l.",
    "wof:placetype":"venue"
},
  "geometry": {"coordinates":[-2.414509058,43.116558075],"type":"Point"}
}