{
  "type": "Feature",
  "properties": {
    "addr:full":"Calle de Augusto Figueroa, 16 Madrid Madrid 28004",
    "addr:housenumber":"16",
    "addr:postcode":"madrid;28004",
    "addr:street":"Calle De Augusto Figueroa",
    "iso:country":"ES",
    "sg:address":"Calle de Augusto Figueroa, 16",
    "sg:city":"Madrid",
    "sg:orig_category":"Tintorer\u00cdas, Limpieza En Seco",
    "sg:phone":"+34 915 32 18 73",
    "sg:postcode":"28004",
    "sg:province":"Madrid",
    "wof:name":"Gil Gonzalez Isaac",
    "wof:placetype":"venue"
},
  "geometry": {"coordinates":[-3.6988623142,40.4225273132],"type":"Point"}
}