{
  "type": "Feature",
  "properties": {
    "iso:country":"ES",
    "sg:address":"Calle de Hermanos Martinez Perez, 8",
    "sg:city":"Paredes Nava",
    "sg:orig_category":"Obras Y Organismos Sociales",
    "sg:phone":"+34 979 83 08 69",
    "sg:postcode":"34300",
    "sg:province":"Palencia",
    "wof:name":"Asoc Edad Dorada Mensajeros De La Paz Castilla Y Leon",
    "wof:placetype":"venue"
},
  "geometry": {"coordinates":[-4.6927051544,42.1530075073],"type":"Point"}
}