{
  "type": "Feature",
  "properties": {
    "addr:full":"Carrer de Rocafort, 221 Barcelona Barcelona 08029",
    "addr:housenumber":"221",
    "addr:postcode":"08029",
    "addr:street":"Carrer De Rocafort",
    "iso:country":"ES",
    "sg:address":"Carrer de Rocafort, 221",
    "sg:city":"Barcelona",
    "sg:orig_category":"Agencias Y Agentes Comerciales, Representantes",
    "sg:phone":"+34 933 22 51 56",
    "sg:postcode":"08029",
    "sg:province":"Barcelona",
    "wof:name":"Val Redon Eusebio",
    "wof:placetype":"venue"
},
  "geometry": {"coordinates":[2.146281004,41.3844032288],"type":"Point"}
}