{
  "type": "Feature",
  "properties": {
    "iso:country":"ES",
    "sg:address":"Plaz Mayor, 52",
    "sg:city":"Maside",
    "sg:orig_category":"Molduras, Junquillos, Listones Y Molduras Perforadas",
    "sg:phone":"+34 988 28 83 29",
    "sg:postcode":"32570",
    "sg:province":"Ourense",
    "wof:name":"Fernandez Garcia Juan",
    "wof:placetype":"venue"
},
  "geometry": {"coordinates":[-8.0248470306,42.4111824036],"type":"Point"}
}