{
  "type": "Feature",
  "properties": {
    "iso:country":"ES",
    "sg:address":"Carr Pi, 57",
    "sg:city":"Port D'andratx",
    "sg:orig_category":"Administradores De Bienes Y Delegados De Comunidades De Propietarios",
    "sg:phone":"+34 971 67 16 86",
    "sg:postcode":"07157",
    "sg:province":"Islas Baleares",
    "wof:name":"La Mola Sea Breeze",
    "wof:placetype":"venue"
},
  "geometry": {"coordinates":[2.3702039719,39.5334243774],"type":"Point"}
}