{
  "type": "Feature",
  "properties": {
    "iso:country":"ES",
    "sg:address":"Estd Masustegi, 12",
    "sg:city":"Bilbao",
    "sg:orig_category":"Plomeros",
    "sg:phone":"+34 944 42 13 07",
    "sg:postcode":"48002",
    "sg:province":"Vizcaya",
    "wof:name":"Beltran Sanchez Francisco",
    "wof:placetype":"venue"
},
  "geometry": {"coordinates":[-2.9529640675,43.2562065125],"type":"Point"}
}