{
  "type": "Feature",
  "properties": {
    "addr:full":"Calle de Ancha, 42 Cabezas S. Juan Sevilla 41730",
    "addr:housenumber":"42",
    "addr:postcode":"41730",
    "addr:street":"Calle De Ancha;S.",
    "iso:country":"ES",
    "sg:address":"Calle de Ancha, 42",
    "sg:city":"Cabezas S. Juan",
    "sg:orig_category":"Centros M\u00c9dicos Y Sociales, Dispensarios",
    "sg:phone":"+34 955 87 02 53",
    "sg:postcode":"41730",
    "sg:province":"Sevilla",
    "wof:name":"Saad Al-saad Ali",
    "wof:placetype":"venue"
},
  "geometry": {"coordinates":[-5.9369969368,36.9839630127],"type":"Point"}
}