{
  "type": "Feature",
  "properties": {
    "iso:country":"ES",
    "sg:address":"Avda Miguel De Cervantes, 37",
    "sg:city":"Ecija",
    "sg:orig_category":"Inform\u00c1tica (estudios, Servicios, Asesor\u00cda, Formaci\u00d3n)",
    "sg:phone":"+34 954 83 40 52",
    "sg:postcode":"41400",
    "sg:province":"Sevilla",
    "wof:name":"Mora Rosa Manuel Antonio",
    "wof:placetype":"venue"
},
  "geometry": {"coordinates":[-5.0777621269,37.5385475159],"type":"Point"}
}