{
  "type": "Feature",
  "properties": {
    "iso:country":"ES",
    "sg:address":"Calle de Astarloa, 10",
    "sg:city":"Barakaldo",
    "sg:orig_category":"Muebles Y Accesorios Para Cocinas Y Cuartos De Ba\u00d1o (al Por Menor)",
    "sg:phone":"+34 944 99 21 11",
    "sg:postcode":"48902",
    "sg:province":"Vizcaya",
    "wof:name":"Muebles Y Decoracion Astarloa S.a.l.",
    "wof:placetype":"venue"
},
  "geometry": {"coordinates":[-2.9896183014,43.2928543091],"type":"Point"}
}