{
  "type": "Feature",
  "properties": {
    "iso:country":"ES",
    "sg:address":"Calle de Metalurgia, 45",
    "sg:city":"Sevilla",
    "sg:orig_category":"Electricidad: Equipos Industriales, Componentes (fabricaci\u00d3n)",
    "sg:phone":"+34 954 35 03 97",
    "sg:postcode":"41007",
    "sg:province":"Sevilla",
    "sg:website":"www.claved.es",
    "wof:name":"Claved S.a.",
    "wof:placetype":"venue"
},
  "geometry": {"coordinates":[-5.9564590454,37.4092597961],"type":"Point"}
}