{
  "type": "Feature",
  "properties": {
    "addr:full":"Ctra Caudete, Km. 0002,8 Villena Alicante 03400",
    "addr:postcode":"03400",
    "addr:street":"Ctra Caudete Km. 0002,8",
    "iso:country":"ES",
    "sg:address":"Ctra Caudete, Km. 0002,8",
    "sg:city":"Villena",
    "sg:orig_category":"Vulcanizado",
    "sg:phone":"+34 965 81 35 53",
    "sg:postcode":"03400",
    "sg:province":"Alicante",
    "wof:name":"Moldeados Caucho-vi S. L.",
    "wof:placetype":"venue"
},
  "geometry": {"coordinates":[-0.8657540083,38.6356544495],"type":"Point"}
}