{
  "type": "Feature",
  "properties": {
    "addr:full":"Cmno Faro, 11 Alacant Alicante 03540",
    "addr:housenumber":"11",
    "addr:postcode":"03540",
    "addr:street":"Cmno Faro",
    "iso:country":"ES",
    "sg:address":"Cmno Faro, 11",
    "sg:city":"Alacant",
    "sg:orig_category":"Servicios De Higiene Y Peluquer\u00cda Para Perros Y Gatos",
    "sg:phone":"+34 965 15 07 94",
    "sg:postcode":"03540",
    "sg:province":"Alicante",
    "wof:name":"Yurrebaso Etxebarria Olatz",
    "wof:placetype":"venue"
},
  "geometry": {"coordinates":[-0.4120363891,38.3560295105],"type":"Point"}
}