{
  "type": "Feature",
  "properties": {
    "iso:country":"ES",
    "sg:address":"Ibarkurutze Plaza, 8",
    "sg:city":"Eibar",
    "sg:orig_category":"Herradores, Herreros, Carreteros",
    "sg:phone":"+34 943 20 12 27",
    "sg:postcode":"20600",
    "sg:province":"Guip\u00f9zcoa",
    "wof:name":"Laspiur S. A.",
    "wof:placetype":"venue"
},
  "geometry": {"coordinates":[-2.4884390831,43.1800117493],"type":"Point"}
}