{
  "type": "Feature",
  "properties": {
    "iso:country":"ES",
    "sg:address":"Avda Juan Carlos I, 50",
    "sg:city":"Aspe",
    "sg:orig_category":"Centros Empresariales",
    "sg:phone":"+34 965 49 36 82",
    "sg:postcode":"03680",
    "sg:province":"Alicante",
    "wof:name":"Hernandez Almodobar Sergio",
    "wof:placetype":"venue"
},
  "geometry": {"coordinates":[-0.7614539862,38.3423118591],"type":"Point"}
}