{
  "type": "Feature",
  "properties": {
    "iso:country":"ES",
    "sg:address":"Calle de Godofredo Ortega Y Mu\u00d1oz, 39",
    "sg:city":"Badajoz",
    "sg:orig_category":"Inform\u00c1tica: Material Y Suministros",
    "sg:phone":"+34 924 23 92 92",
    "sg:postcode":"06011",
    "sg:province":"Badajoz",
    "wof:name":"Valle Linares Juan",
    "wof:placetype":"venue"
},
  "geometry": {"coordinates":[-6.9874410629,38.8657264709],"type":"Point"}
}