{
  "type": "Feature",
  "properties": {
    "iso:country":"ES",
    "sg:address":"Carretera De La Lancha, S/n",
    "sg:city":"Pe\u00f1allana",
    "sg:orig_category":"Obras Y Organismos Sociales",
    "sg:phone":"+34 953 54 90 89",
    "sg:postcode":"23740",
    "sg:province":"Ja\u00e9n",
    "wof:name":"Hijas De La Caridad De San Vicente De Paul",
    "wof:placetype":"venue"
},
  "geometry": {"coordinates":[-3.7895176411,37.7657394409],"type":"Point"}
}