{
  "type": "Feature",
  "properties": {
    "addr:full":"Calle de Reyes Catolicos, 76 Castalla Alicante 03420",
    "addr:housenumber":"76",
    "addr:postcode":"03420",
    "addr:street":"Calle De Reyes Catolicos",
    "iso:country":"ES",
    "sg:address":"Calle de Reyes Catolicos, 76",
    "sg:city":"Castalla",
    "sg:orig_category":"Doctores En Medicina",
    "sg:phone":"+34 966 56 03 61",
    "sg:postcode":"03420",
    "sg:province":"Alicante",
    "wof:name":"Santisteban Casanova Rosa",
    "wof:placetype":"venue"
},
  "geometry": {"coordinates":[-0.6686419845,38.5912246704],"type":"Point"}
}