{
  "type": "Feature",
  "properties": {
    "iso:country":"ES",
    "sg:address":"Calle de San Vicente Martir, 16",
    "sg:city":"Valencia",
    "sg:orig_category":"Moda",
    "sg:phone":"+34 963 92 46 04",
    "sg:postcode":"46002",
    "sg:province":"Valencia",
    "wof:name":"Punch Producciones S.l.",
    "wof:placetype":"venue"
},
  "geometry": {"coordinates":[-0.3767690063,39.4725151062],"type":"Point"}
}