{
  "type": "Feature",
  "properties": {
    "addr:full":"Calle de Resurreccion, 4 Getafe Madrid 28901",
    "addr:housenumber":"4",
    "addr:postcode":"28901",
    "addr:street":"Calle De Resurreccion",
    "iso:country":"ES",
    "sg:address":"Calle de Resurreccion, 4",
    "sg:city":"Getafe",
    "sg:orig_category":"Ingeniero",
    "sg:phone":"+34 916 82 60 20",
    "sg:postcode":"28901",
    "sg:province":"Madrid",
    "wof:name":"Montalvo Garrobo Jose Maria",
    "wof:placetype":"venue"
},
  "geometry": {"coordinates":[-3.7324268818,40.3029403687],"type":"Point"}
}