{
  "type": "Feature",
  "properties": {
    "iso:country":"ES",
    "sg:address":"Calzada, S/n",
    "sg:city":"S. Miguel Due\u00f1as",
    "sg:orig_category":"Cerrajer\u00cda, Ferrallista",
    "sg:phone":"+34 987 46 70 44",
    "sg:postcode":"24398",
    "sg:province":"Le\u00f3n",
    "wof:name":"Alvarez Lopez Mariano",
    "wof:placetype":"venue"
},
  "geometry": {"coordinates":[-6.5217041969,42.5857925415],"type":"Point"}
}