{
  "type": "Feature",
  "properties": {
    "iso:country":"ES",
    "sg:address":"Calle de Harrison, 10",
    "sg:city":"Amorebieta",
    "sg:orig_category":"Agencias Y Agentes Comerciales, Representantes",
    "sg:phone":"+34 946 30 85 39",
    "sg:postcode":"48340",
    "sg:province":"Vizcaya",
    "wof:name":"Ibaizabal Barri S.l.",
    "wof:placetype":"venue"
},
  "geometry": {"coordinates":[-2.7337212563,43.2219390869],"type":"Point"}
}