{
  "type": "Feature",
  "properties": {
    "iso:country":"ES",
    "sg:address":"Plaz San Roque, S/n",
    "sg:city":"Jatiel",
    "sg:orig_category":"Asociaciones, Organismos Culturales Y Socioeducativos",
    "sg:phone":"+34 978 82 15 14",
    "sg:postcode":"44592",
    "sg:province":"Teruel",
    "wof:name":"Asociacion Cultural Triador",
    "wof:placetype":"venue"
},
  "geometry": {"coordinates":[-0.3813093901,41.2199287415],"type":"Point"}
}