{
  "type": "Feature",
  "properties": {
    "iso:country":"ES",
    "sg:address":"Plaz Cristo (el), 1",
    "sg:city":"Ponferrada",
    "sg:orig_category":"Loter\u00cda Y T\u00d3mbola",
    "sg:phone":"+34 987 41 94 21",
    "sg:postcode":"24400",
    "sg:province":"Le\u00f3n",
    "wof:name":"Salas Perez Jose Luis",
    "wof:placetype":"venue"
},
  "geometry": {"coordinates":[-6.5970311165,42.5471763611],"type":"Point"}
}