{
  "type": "Feature",
  "properties": {
    "iso:country":"ES",
    "sg:address":"Carrer de Estatut, 10",
    "sg:city":"S. Andreu Barca",
    "sg:orig_category":"Bisuter\u00cda, Joyer\u00cda, Relojer\u00cda (al Por Menor)",
    "sg:phone":"+34 936 53 52 17",
    "sg:postcode":"08740",
    "sg:province":"Barcelona",
    "wof:name":"Garcia Perez Gines",
    "wof:placetype":"venue"
},
  "geometry": {"coordinates":[1.9706200361,41.4476509094],"type":"Point"}
}