{
  "type": "Feature",
  "properties": {
    "iso:country":"ES",
    "sg:address":"Calle de Legazpi, 1",
    "sg:city":"Estepona",
    "sg:orig_category":"Loter\u00cda Y T\u00d3mbola",
    "sg:phone":"+34 952 79 56 03",
    "sg:postcode":"29680",
    "sg:province":"M\u00e1laga",
    "wof:name":"Lopez De Bustamante Simon Victoria",
    "wof:placetype":"venue"
},
  "geometry": {"coordinates":[-5.1505031586,36.4205970764],"type":"Point"}
}