{
  "type": "Feature",
  "properties": {
    "addr:full":"Carrer de Pau Casals, 46 Cambrils Tarragona 43850",
    "addr:housenumber":"46",
    "addr:postcode":"43850",
    "addr:street":"Carrer De Pau Casals",
    "iso:country":"ES",
    "sg:address":"Carrer de Pau Casals, 46",
    "sg:city":"Cambrils",
    "sg:orig_category":"Panader\u00cdas, Panader\u00cdas",
    "sg:phone":"+34 977 36 41 56",
    "sg:postcode":"43850",
    "sg:province":"Tarragona",
    "wof:name":"Rovira Minguella Joan",
    "wof:placetype":"venue"
},
  "geometry": {"coordinates":[1.062507987,41.0669403076],"type":"Point"}
}