{
  "type": "Feature",
  "properties": {
    "iso:country":"ES",
    "sg:address":"Avda Giorgeta, 8",
    "sg:city":"Valencia",
    "sg:orig_category":"Transportes Internacionales",
    "sg:phone":"+34 963 17 40 90",
    "sg:postcode":"46007",
    "sg:province":"Valencia",
    "wof:name":"Maotrans S.l.",
    "wof:placetype":"venue"
},
  "geometry": {"coordinates":[-0.3864220083,39.4616203308],"type":"Point"}
}