{
  "type": "Feature",
  "properties": {
    "addr:full":"I Guadalmina(guadalmina Alta), 27 San Pedro Alcantara M\u00e1laga 29670",
    "addr:housenumber":"27",
    "addr:postcode":"29670",
    "addr:street":"I;Guadalmina Alta",
    "iso:country":"ES",
    "sg:address":"I Guadalmina(guadalmina Alta), 27",
    "sg:city":"San Pedro Alcantara",
    "sg:orig_category":"Centros Empresariales",
    "sg:phone":"+34 952 92 87 40",
    "sg:postcode":"29670",
    "sg:province":"M\u00e1laga",
    "wof:name":"Dopico Plazas Francisco",
    "wof:placetype":"venue"
},
  "geometry": {"coordinates":[-4.9902391434,36.4866333008],"type":"Point"}
}