{
  "type": "Feature",
  "properties": {
    "addr:full":"Barr Quintana, 162 Cobreces Cantabria 39320",
    "addr:housenumber":"162",
    "addr:postcode":"39320",
    "addr:street":"Quintana",
    "iso:country":"ES",
    "sg:address":"Barr Quintana, 162",
    "sg:city":"Cobreces",
    "sg:orig_category":"Empresas De Desmonte",
    "sg:phone":"+34 942 72 50 51",
    "sg:postcode":"39320",
    "sg:province":"Cantabria",
    "wof:name":"Rabago Garcia Gumersindo",
    "wof:placetype":"venue"
},
  "geometry": {"coordinates":[-4.2107009888,43.3850250244],"type":"Point"}
}