{
  "type": "Feature",
  "properties": {
    "addr:full":"Pase Zorrilla, 94 Valladolid Valladolid 47006",
    "addr:housenumber":"94",
    "addr:postcode":"47006",
    "addr:street":"Zorrilla",
    "iso:country":"ES",
    "sg:address":"Pase Zorrilla, 94",
    "sg:city":"Valladolid",
    "sg:orig_category":"Doctores En Medicina",
    "sg:phone":"+34 983 27 38 12",
    "sg:postcode":"47006",
    "sg:province":"Valladolid",
    "wof:name":"Merino Garcia Luis Carlos",
    "wof:placetype":"venue"
},
  "geometry": {"coordinates":[-4.7383871078,41.6397171021],"type":"Point"}
}