{
  "type": "Feature",
  "properties": {
    "iso:country":"ES",
    "sg:address":"Calle de Paseo Del Agua, 11",
    "sg:city":"Brenes",
    "sg:orig_category":"Molduras, Junquillos, Listones Y Molduras Perforadas",
    "sg:phone":"+34 954 79 72 91",
    "sg:postcode":"41310",
    "sg:province":"Sevilla",
    "wof:name":"Jimenez Romano Francisco",
    "wof:placetype":"venue"
},
  "geometry": {"coordinates":[-5.8695273399,37.5561141968],"type":"Point"}
}