{
  "type": "Feature",
  "properties": {
    "iso:country":"ES",
    "sg:address":"Carr Rei, Del, 12",
    "sg:city":"Algaida",
    "sg:orig_category":"Sociedades, Compa\u00d1\u00cdas Aseguradoras",
    "sg:phone":"+34 971 66 55 00",
    "sg:postcode":"07210",
    "sg:province":"Islas Baleares",
    "wof:name":"Agencia De Seguros Antonio Pericas S.l.",
    "wof:placetype":"venue"
},
  "geometry": {"coordinates":[2.8944027424,39.5593528748],"type":"Point"}
}