{
  "type": "Feature",
  "properties": {
    "iso:country":"ES",
    "sg:address":"Avda Alcalde Clemente Diaz Ruiz, 36",
    "sg:city":"Fuengirola",
    "sg:orig_category":"Aparcamientos (infraestructuras, Accesorios)",
    "sg:phone":"+34 952 66 40 07",
    "sg:postcode":"29640",
    "sg:province":"M\u00e1laga",
    "wof:name":"Garaje Victoria S.a.",
    "wof:placetype":"venue"
},
  "geometry": {"coordinates":[-4.6249842644,36.5448226929],"type":"Point"}
}