{
  "type": "Feature",
  "properties": {
    "iso:country":"ES",
    "sg:address":"Pol Ind Moli D'en Serra, 2",
    "sg:city":"Sta. Oliva",
    "sg:classifiers":[
        {
            "category":"Home & Garden",
            "subcategory":"Household Appliances",
            "type":"Retail Goods"
        }
    ],
    "sg:phone":"+34 977 15 51 48",
    "sg:postcode":"43710",
    "sg:province":"Tarragona",
    "sg:tags":[
        "bodega",
        "de",
        "vino",
        "acondicionamiento"
    ],
    "wof:name":"Gaya Aguilera Jose",
    "wof:placetype":"venue"
},
  "geometry": {"coordinates":[1.5496400595,41.2515296936],"type":"Point"}
}