{
  "type": "Feature",
  "properties": {
    "iso:country":"ES",
    "sg:address":"Ctra. Sta. Eularia(jesus), Km. 0003,0",
    "sg:city":"Ntra. Sra. Jesus",
    "sg:orig_category":"Servicios Diversos",
    "sg:phone":"+34 971 31 85 96",
    "sg:postcode":"07819",
    "sg:province":"Islas Baleares",
    "sg:website":"www.ibiza-connections.com",
    "wof:name":"Ibiza Connections S.l.",
    "wof:placetype":"venue"
},
  "geometry": {"coordinates":[1.444257021,38.934135437],"type":"Point"}
}