{
  "type": "Feature",
  "properties": {
    "iso:country":"ES",
    "sg:address":"Calle de Balsas (las), 16",
    "sg:city":"Logro\u00f1o",
    "sg:orig_category":"Materiales De Construcci\u00d3n, Herramientas",
    "sg:phone":"+34 941 25 93 18",
    "sg:postcode":"26006",
    "sg:province":"La Rioja",
    "wof:name":"Mavyal S.l.",
    "wof:placetype":"venue"
},
  "geometry": {"coordinates":[-2.4079389572,42.4700889587],"type":"Point"}
}