{
  "type": "Feature",
  "properties": {
    "iso:country":"ES",
    "sg:address":"Afores, S/n",
    "sg:city":"Gratallops",
    "sg:orig_category":"Productores Recolectores, Venta Directa De Vinos",
    "sg:phone":"+34 977 83 91 71",
    "sg:postcode":"43737",
    "sg:province":"Tarragona",
    "wof:name":"Clos Mogador S.c.c.l.",
    "wof:placetype":"venue"
},
  "geometry": {"coordinates":[0.7500169873,41.1864280701],"type":"Point"}
}