{
  "type": "Feature",
  "properties": {
    "iso:country":"ES",
    "sg:address":"C/ Tap (el), 8",
    "sg:city":"Alcoi",
    "sg:orig_category":"Zapatos (al Por Menor)",
    "sg:phone":"+34 965 54 18 85",
    "sg:postcode":"03801",
    "sg:province":"Alicante",
    "wof:name":"Gisbert Ribera Julian",
    "wof:placetype":"venue"
},
  "geometry": {"coordinates":[-0.4735479951,38.6964530945],"type":"Point"}
}