{
  "type": "Feature",
  "properties": {
    "addr:full":"Cami Serra, S/n Ripollet Barcelona 08291",
    "addr:postcode":"08291",
    "addr:street":"Serra S / N",
    "iso:country":"ES",
    "sg:address":"Cami Serra, S/n",
    "sg:city":"Ripollet",
    "sg:orig_category":"Charcuter\u00cdas (al Por Mayor)",
    "sg:phone":"+34 935 80 32 37",
    "sg:postcode":"08291",
    "sg:province":"Barcelona",
    "wof:name":"Antonijoan S.a.",
    "wof:placetype":"venue"
},
  "geometry": {"coordinates":[2.1662299633,41.4994125366],"type":"Point"}
}