{
  "type": "Feature",
  "properties": {
    "addr:full":"Avda Escuelas, 43 Torresandino Burgos 09310",
    "addr:housenumber":"43",
    "addr:postcode":"09310",
    "addr:street":"Avda Escuelas",
    "iso:country":"ES",
    "sg:address":"Avda Escuelas, 43",
    "sg:city":"Torresandino",
    "sg:orig_category":"Centros De Educaci\u00d3n Especial",
    "sg:phone":"+34 947 55 11 30",
    "sg:postcode":"09310",
    "sg:province":"Burgos",
    "wof:name":"C.r.a. Antonio De Nebrija",
    "wof:placetype":"venue"
},
  "geometry": {"coordinates":[-3.9106678963,41.8281211853],"type":"Point"}
}