{
  "type": "Feature",
  "properties": {
    "addr:full":"Calle de Doctor Esquerdo, 110 Madrid Madrid 28007",
    "addr:housenumber":"110",
    "addr:postcode":"28007",
    "addr:street":"Calle De Doctor Esquerdo",
    "iso:country":"ES",
    "sg:address":"Calle de Doctor Esquerdo, 110",
    "sg:city":"Madrid",
    "sg:orig_category":"Asesor\u00cda Sobre Comunicaci\u00d3n De Empresas",
    "sg:phone":"+34 915 52 78 74",
    "sg:postcode":"28007",
    "sg:province":"Madrid",
    "wof:name":"Ascal Asesores S.l",
    "wof:placetype":"venue"
},
  "geometry": {"coordinates":[-3.670122385,40.4092330933],"type":"Point"}
}