{
  "type": "Feature",
  "properties": {
    "addr:full":"Carrer de Bruixa, 46 Barcelona Barcelona 08014",
    "addr:housenumber":"46",
    "addr:postcode":"08014",
    "addr:street":"Carrer De Bruixa",
    "iso:country":"ES",
    "sg:address":"Carrer de Bruixa, 46",
    "sg:city":"Barcelona",
    "sg:orig_category":"Comercio De Piezas De Recambio Y De Accesorios De Veh\u00cdculos, Veh\u00cdculos Industriales",
    "sg:phone":"+34 934 90 16 20",
    "sg:postcode":"08014",
    "sg:province":"Barcelona",
    "wof:name":"Accesorios Confeccion Nabet S.a.",
    "wof:placetype":"venue"
},
  "geometry": {"coordinates":[2.1336567402,41.3843727112],"type":"Point"}
}