{
  "type": "Feature",
  "properties": {
    "addr:full":"Calle de Estaciones, S/n Torrejon Ardoz Madrid 28850",
    "addr:housenumber":"s / n",
    "addr:postcode":"28850",
    "addr:street":"Calle De Estaciones",
    "iso:country":"ES",
    "sg:address":"Calle de Estaciones, S/n",
    "sg:city":"Torrejon Ardoz",
    "sg:orig_category":"Reposter\u00cdas",
    "sg:phone":"+34 916 48 71 22",
    "sg:postcode":"28850",
    "sg:province":"Madrid",
    "wof:name":"Panificadora Empuriabrava S.l.",
    "wof:placetype":"venue"
},
  "geometry": {"coordinates":[-3.4813890457,40.454410553],"type":"Point"}
}