{
  "type": "Feature",
  "properties": {
    "iso:country":"ES",
    "sg:address":"Rua Real, 119",
    "sg:city":"Ferrol",
    "sg:orig_category":"Abogados",
    "sg:phone":"+34 981 35 24 98",
    "sg:postcode":"15402",
    "sg:province":"A Coru\u00f1a",
    "wof:name":"Suarez Santiso David",
    "wof:placetype":"venue"
},
  "geometry": {"coordinates":[-8.2336473465,43.4835395813],"type":"Point"}
}