{
  "type": "Feature",
  "properties": {
    "iso:country":"ES",
    "sg:address":"Ctra. Huelva, Km. 0103,0",
    "sg:city":"Cartaya",
    "sg:orig_category":"Frutos Y Legumbres",
    "sg:phone":"+34 959 39 38 52",
    "sg:postcode":"21450",
    "sg:province":"Huelva",
    "wof:name":"S.a.t.citroluz",
    "wof:placetype":"venue"
},
  "geometry": {"coordinates":[-7.1528987885,37.2844581604],"type":"Point"}
}