{
  "type": "Feature",
  "properties": {
    "iso:country":"ES",
    "sg:address":"Pl Espanya, 14",
    "sg:city":"Alcoi",
    "sg:orig_category":"Grafistas",
    "sg:phone":"+34 965 54 01 68",
    "sg:postcode":"03801",
    "sg:province":"Alicante",
    "wof:name":"Sempere Gonzalez Santiago",
    "wof:placetype":"venue"
},
  "geometry": {"coordinates":[-0.4728589952,38.6980361938],"type":"Point"}
}