{
  "type": "Feature",
  "properties": {
    "addr:full":"Asturies, S/n Bellavista Barcelona 08521",
    "addr:housenumber":"/ n",
    "addr:postcode":"08521",
    "addr:street":"Asturies S",
    "iso:country":"ES",
    "sg:address":"Asturies, S/n",
    "sg:city":"Bellavista",
    "sg:orig_category":"Bibliotecas, Mediatecas",
    "sg:phone":"+34 938 40 38 90",
    "sg:postcode":"08521",
    "sg:province":"Barcelona",
    "wof:name":"Ajuntament De Les Franqueses Del Valles",
    "wof:placetype":"venue"
},
  "geometry": {"coordinates":[2.3004341125,41.6213912964],"type":"Point"}
}