{
  "type": "Feature",
  "properties": {
    "addr:full":"Plaz Constitucion, 4 Donostia-san Sebastian Guip\u00f9zcoa 20003",
    "addr:housenumber":"4",
    "addr:postcode":"20003",
    "addr:street":"Constitucion",
    "iso:country":"ES",
    "sg:address":"Plaz Constitucion, 4",
    "sg:city":"Donostia-san Sebastian",
    "sg:orig_category":"Agencias Y Agentes Comerciales, Representantes",
    "sg:phone":"+34 943 42 44 63",
    "sg:postcode":"20003",
    "sg:province":"Guip\u00f9zcoa",
    "wof:name":"Urrestarazu Fernandez Berridi Jose Maria",
    "wof:placetype":"venue"
},
  "geometry": {"coordinates":[-1.9849809408,43.3238182068],"type":"Point"}
}