{
  "type": "Feature",
  "properties": {
    "addr:full":"Calle de Huelva, 2 Jerez De La Frontera C\u00e1diz 11408",
    "addr:housenumber":"2",
    "addr:postcode":"11408",
    "addr:street":"Calle De Huelva",
    "iso:country":"ES",
    "sg:address":"Calle de Huelva, 2",
    "sg:city":"Jerez De La Frontera",
    "sg:orig_category":"Iglesia Cat\u00d3lica",
    "sg:phone":"+34 956 30 24 04",
    "sg:postcode":"11408",
    "sg:province":"C\u00e1diz",
    "wof:name":"Parroquia Madre De La Iglesia",
    "wof:placetype":"venue"
},
  "geometry": {"coordinates":[-6.1051588058,36.6972236633],"type":"Point"}
}