{
  "type": "Feature",
  "properties": {
    "addr:full":"Calle de Antonio Martelo, 5 Malaga M\u00e1laga 29006",
    "addr:housenumber":"5",
    "addr:postcode":"29006",
    "addr:street":"Calle De Antonio Martelo;Ma\u0301Laga",
    "iso:country":"ES",
    "sg:address":"Calle de Antonio Martelo, 5",
    "sg:city":"Malaga",
    "sg:orig_category":"Bisuter\u00cda, Joyer\u00cda, Relojer\u00cda (al Por Menor)",
    "sg:phone":"+34 952 31 75 97",
    "sg:postcode":"29006",
    "sg:province":"M\u00e1laga",
    "wof:name":"Gonzalez Vasco Luis",
    "wof:placetype":"venue"
},
  "geometry": {"coordinates":[-4.4413928986,36.7112426758],"type":"Point"}
}