{
  "type": "Feature",
  "properties": {
    "addr:full":"Pase Alameda De Osuna, 55 Madrid Madrid 28042",
    "addr:housenumber":"55",
    "addr:postcode":"madrid;28042",
    "addr:street":"Alameda;Osuna",
    "iso:country":"ES",
    "sg:address":"Pase Alameda De Osuna, 55",
    "sg:city":"Madrid",
    "sg:orig_category":"Audiovisuales (producci\u00d3n, Edici\u00d3n, Realizaci\u00d3n)",
    "sg:phone":"+34 913 20 29 78",
    "sg:postcode":"28042",
    "sg:province":"Madrid",
    "wof:name":"Jlf Producciones Audiovisuales S.l.",
    "wof:placetype":"venue"
},
  "geometry": {"coordinates":[-3.5921339989,40.4564361572],"type":"Point"}
}