{
  "type": "Feature",
  "properties": {
    "addr:full":"Calle de Siete, 5 Pinoso Alicante 03650",
    "addr:housenumber":"5",
    "addr:postcode":"03650",
    "addr:street":"Calle De Siete;Alicante",
    "iso:country":"ES",
    "sg:address":"Calle de Siete, 5",
    "sg:city":"Pinoso",
    "sg:orig_category":"Artes Gr\u00c1ficas, Artes Pl\u00c1sticas: Material Y Suministros (al Por Menor)",
    "sg:phone":"+34 965 47 75 93",
    "sg:postcode":"03650",
    "sg:province":"Alicante",
    "wof:name":"Viflex S.l.",
    "wof:placetype":"venue"
},
  "geometry": {"coordinates":[-1.0357757807,38.4052886963],"type":"Point"}
}