{
  "type": "Feature",
  "properties": {
    "addr:full":"Po. Del Mar, 22 Palmanova Islas Baleares 07181",
    "addr:housenumber":"22",
    "addr:postcode":"07181",
    "addr:street":"Po. Del Mar",
    "iso:country":"ES",
    "sg:address":"Po. Del Mar, 22",
    "sg:city":"Palmanova",
    "sg:orig_category":"Loter\u00cda Y T\u00d3mbola",
    "sg:phone":"+34 971 68 19 44",
    "sg:postcode":"07181",
    "sg:province":"Islas Baleares",
    "wof:name":"Salinas Valbuena Maria Luisa",
    "wof:placetype":"venue"
},
  "geometry": {"coordinates":[2.5384700298,39.5234489441],"type":"Point"}
}