{
  "type": "Feature",
  "properties": {
    "iso:country":"ES",
    "sg:address":"Carr Futur, S/n",
    "sg:city":"Algimia De Alfara",
    "sg:orig_category":"Asilos De Ancianos. Centros Privados",
    "sg:phone":"+34 962 62 70 45",
    "sg:postcode":"46148",
    "sg:province":"Valencia",
    "wof:name":"Resiter Algecasa S.l.",
    "wof:placetype":"venue"
},
  "geometry": {"coordinates":[-0.3615689874,39.7550582886],"type":"Point"}
}