{
  "type": "Feature",
  "properties": {
    "iso:country":"ES",
    "sg:address":"Calle de Amado Nervo, 5",
    "sg:city":"Madrid",
    "sg:orig_category":"Confecci\u00d3n De Trajes Para Se\u00d1oras",
    "sg:phone":"+34 915 52 18 94",
    "sg:postcode":"28007",
    "sg:province":"Madrid",
    "wof:name":"Borda Alvarez Blanca",
    "wof:placetype":"venue"
},
  "geometry": {"coordinates":[-3.6761779785,40.4101524353],"type":"Point"}
}