{
  "type": "Feature",
  "properties": {
    "iso:country":"ES",
    "sg:address":"Calle de Silos, S/n",
    "sg:city":"Alcala Guadaira",
    "sg:orig_category":"Asesor\u00cda Sobre Comunicaci\u00d3n De Empresas",
    "sg:phone":"+34 955 61 51 25",
    "sg:postcode":"41500",
    "sg:province":"Sevilla",
    "wof:name":"Calvo Amo Carlos",
    "wof:placetype":"venue"
},
  "geometry": {"coordinates":[-5.8456888199,37.3450737],"type":"Point"}
}