{
  "type": "Feature",
  "properties": {
    "addr:full":"Carrer de Sant Tomas, 52 Terrassa Barcelona 08222",
    "addr:housenumber":"52",
    "addr:postcode":"08222",
    "addr:street":"Carrer De Sant Tomas",
    "iso:country":"ES",
    "sg:address":"Carrer de Sant Tomas, 52",
    "sg:city":"Terrassa",
    "sg:orig_category":"Comercio De Minerales, F\u00d3siles Y Conchas",
    "sg:phone":"+34 937 85 00 57",
    "sg:postcode":"08222",
    "sg:province":"Barcelona",
    "wof:name":"Marisqueria Los Remos S.l.",
    "wof:placetype":"venue"
},
  "geometry": {"coordinates":[2.0307950974,41.5655250549],"type":"Point"}
}