{
  "type": "Feature",
  "properties": {
    "iso:country":"ES",
    "sg:address":"Calle de Musico Peydro, 35",
    "sg:city":"Valencia",
    "sg:orig_category":"Zapatos (al Por Menor)",
    "sg:phone":"+34 963 52 40 41",
    "sg:postcode":"46001",
    "sg:province":"Valencia",
    "wof:name":"Roic Ferriz Consuelo",
    "wof:placetype":"venue"
},
  "geometry": {"coordinates":[-0.3789480031,39.4706382751],"type":"Point"}
}