{
  "type": "Feature",
  "properties": {
    "addr:full":"Plaz Espa\u00d1a, 12 Graus Huesca 22430",
    "addr:housenumber":"12",
    "addr:postcode":"22430",
    "addr:street":"Plaz Espan\u0303A",
    "iso:country":"ES",
    "sg:address":"Plaz Espa\u00d1a, 12",
    "sg:city":"Graus",
    "sg:orig_category":"Supermercados Y Hipermercados",
    "sg:phone":"+34 974 54 09 44",
    "sg:postcode":"22430",
    "sg:province":"Huesca",
    "wof:name":"Trell Martinez Valentin",
    "wof:placetype":"venue"
},
  "geometry": {"coordinates":[0.3397000134,42.192024231],"type":"Point"}
}