{
  "type": "Feature",
  "properties": {
    "addr:full":"Carrer de Beatriu De Pinos, 36 Palma Islas Baleares 07005",
    "addr:housenumber":"36",
    "addr:postcode":"07005",
    "addr:street":"Carrer De Beatriu De Pinos",
    "iso:country":"ES",
    "sg:address":"Carrer de Beatriu De Pinos, 36",
    "sg:city":"Palma",
    "sg:orig_category":"Iglesia Cat\u00d3lica",
    "sg:phone":"+34 971 46 67 17",
    "sg:postcode":"07005",
    "sg:province":"Islas Baleares",
    "wof:name":"Obispado De Mallorca",
    "wof:placetype":"venue"
},
  "geometry": {"coordinates":[2.6616919041,39.5740661621],"type":"Point"}
}