{
  "type": "Feature",
  "properties": {
    "addr:full":"Calle de Virgen Del Pilar, 51 Almoradi Alicante 03160",
    "addr:housenumber":"51",
    "addr:postcode":"03160",
    "addr:street":"Calle De Virgen Del Pilar",
    "iso:country":"ES",
    "sg:address":"Calle de Virgen Del Pilar, 51",
    "sg:city":"Almoradi",
    "sg:orig_category":"Agencias Y Agentes Comerciales, Representantes",
    "sg:phone":"+34 965 70 08 12",
    "sg:postcode":"03160",
    "sg:province":"Alicante",
    "wof:name":"Ruiz Torres Maria Del Carmen",
    "wof:placetype":"venue"
},
  "geometry": {"coordinates":[-0.7892130017,38.111656189],"type":"Point"}
}