{
  "type": "Feature",
  "properties": {
    "iso:country":"ES",
    "sg:address":"Calle de Salvador Y Merino, 6",
    "sg:city":"Coru\u00d1a",
    "sg:orig_category":"Electromec\u00c1nica",
    "sg:phone":"+34 981 23 46 75",
    "sg:postcode":"15008",
    "sg:province":"La Coru\u00f1a",
    "wof:name":"Lema Suarez Antonio",
    "wof:placetype":"venue"
},
  "geometry": {"coordinates":[-8.4082555771,43.3508644104],"type":"Point"}
}