{
  "type": "Feature",
  "properties": {
    "iso:country":"ES",
    "sg:address":"Pla\u00c7 Catalunya, 4",
    "sg:city":"Alpicat",
    "sg:orig_category":"Producci\u00d3n, Venta De Productos De Agricultura Biol\u00d3gica",
    "sg:phone":"+34 973 73 63 46",
    "sg:postcode":"25110",
    "sg:province":"Lleida",
    "wof:name":"Bosch Escuer Jose",
    "wof:placetype":"venue"
},
  "geometry": {"coordinates":[0.5569900274,41.6662216187],"type":"Point"}
}