{
  "type": "Feature",
  "properties": {
    "addr:full":"Calle de San Isidro, 49 Valladolid Valladolid 47012",
    "addr:housenumber":"49",
    "addr:postcode":"47012",
    "addr:street":"Calle De San Isidro",
    "iso:country":"ES",
    "sg:address":"Calle de San Isidro, 49",
    "sg:city":"Valladolid",
    "sg:orig_category":"Transportes Por Carretera: Lotes Completos, Mercanc\u00cdas Diversas",
    "sg:phone":"+34 983 30 84 97",
    "sg:postcode":"47012",
    "sg:province":"Valladolid",
    "wof:name":"Distribuidora Internacional De Alimentacion S.a.",
    "wof:placetype":"venue"
},
  "geometry": {"coordinates":[-4.7140488625,41.6441841125],"type":"Point"}
}