{
  "type": "Feature",
  "properties": {
    "iso:country":"ES",
    "sg:address":"Calle de Simon Bolivar, S/n",
    "sg:city":"Albolote",
    "sg:orig_category":"Poller\u00cda Y Caza (al Por Menor)",
    "sg:phone":"+34 958 46 87 30",
    "sg:postcode":"18220",
    "sg:province":"Granada",
    "wof:name":"Avicola Garrido Garcia",
    "wof:placetype":"venue"
},
  "geometry": {"coordinates":[-3.6590335369,37.2269935608],"type":"Point"}
}