{
  "type": "Feature",
  "properties": {
    "iso:country":"ES",
    "sg:address":"Pl Jaume Ii (d'en), 12",
    "sg:city":"Perello",
    "sg:orig_category":"Electrodom\u00c9sticos (al Por Menor)",
    "sg:phone":"+34 977 49 03 32",
    "sg:postcode":"43519",
    "sg:province":"Tarragona",
    "wof:name":"Electronica Margalef S.l.",
    "wof:placetype":"venue"
},
  "geometry": {"coordinates":[0.7125660181,40.8756065369],"type":"Point"}
}