{
  "type": "Feature",
  "properties": {
    "addr:full":"C/ Benlliure, 1 Moncofa Castell\u00f3n 12593",
    "addr:housenumber":"1",
    "addr:postcode":"12593",
    "addr:street":"C / Benlliure;Castello\u0301N",
    "iso:country":"ES",
    "sg:address":"C/ Benlliure, 1",
    "sg:city":"Moncofa",
    "sg:orig_category":"Frutas Y Legumbres Frescas (al Por Mayor)",
    "sg:phone":"+34 964 58 04 93",
    "sg:postcode":"12593",
    "sg:province":"Castell\u00f3n",
    "wof:name":"Tena Simarro Rosa",
    "wof:placetype":"venue"
},
  "geometry": {"coordinates":[-0.1439500004,39.807056427],"type":"Point"}
}