{
  "type": "Feature",
  "properties": {
    "addr:full":"Av. Massets (pol Massets), S/n Bellvei Tarragona 43719",
    "addr:housenumber":"/ n",
    "addr:postcode":"43719",
    "addr:street":"Av. Massets;Massets S",
    "iso:country":"ES",
    "sg:address":"Av. Massets (pol Massets), S/n",
    "sg:city":"Bellvei",
    "sg:classifiers":[
        {
            "category":"Manufacturing",
            "subcategory":"Building Materials",
            "type":"Manufacturing & Wholesale Goods"
        }
    ],
    "sg:phone":"+34 977 66 25 57",
    "sg:postcode":"43719",
    "sg:province":"Tarragona",
    "sg:tags":[
        "cemento",
        "y",
        "de",
        "fabricaci\u00d3n",
        "cal"
    ],
    "wof:name":"Tarmac Iberia S.a.u.",
    "wof:placetype":"venue"
},
  "geometry": {"coordinates":[1.5590419769,41.2341995239],"type":"Point"}
}