{
  "type": "Feature",
  "properties": {
    "iso:country":"ES",
    "sg:address":"Calle de Dolores De La Rocha, 26",
    "sg:city":"Palmas De Gran Canaria",
    "sg:orig_category":"Pintores",
    "sg:phone":"+34 928 33 30 36",
    "sg:postcode":"35001",
    "sg:province":"Las Palmas",
    "wof:name":"Utrera Henriquez Mariano",
    "wof:placetype":"venue"
},
  "geometry": {"coordinates":[-15.4133367538,28.0971946716],"type":"Point"}
}