{
  "type": "Feature",
  "properties": {
    "addr:full":"Carr Verge Del Remei (de La), 5 Albaida Valencia 46860",
    "addr:housenumber":"5",
    "addr:postcode":"46860",
    "addr:street":"Carr Verge Del Remei De La",
    "iso:country":"ES",
    "sg:address":"Carr Verge Del Remei (de La), 5",
    "sg:city":"Albaida",
    "sg:orig_category":"Agencias Y Agentes Comerciales, Representantes",
    "sg:phone":"+34 962 39 02 93",
    "sg:postcode":"46860",
    "sg:province":"Valencia",
    "wof:name":"Albert Quiles Vicente",
    "wof:placetype":"venue"
},
  "geometry": {"coordinates":[-0.5173367262,38.8390083313],"type":"Point"}
}