{
  "type": "Feature",
  "properties": {
    "addr:full":"Udad. Act. Indus. I, S/n Ventas Retamosa Toledo 45183",
    "addr:housenumber":"s",
    "addr:postcode":"45183",
    "addr:street":"/ N",
    "iso:country":"ES",
    "sg:address":"Udad. Act. Indus. I, S/n",
    "sg:city":"Ventas Retamosa",
    "sg:orig_category":"Productos Qu\u00cdmicos (fabricaci\u00d3n, Al Por Mayor)",
    "sg:phone":"+34 918 17 33 96",
    "sg:postcode":"45183",
    "sg:province":"Toledo",
    "wof:name":"Deter Quimica S.l.",
    "wof:placetype":"venue"
},
  "geometry": {"coordinates":[-4.1120891571,40.1551246643],"type":"Point"}
}