{
  "type": "Feature",
  "properties": {
    "addr:full":"Carr Ter, 1 Platja D'aro Girona 17250",
    "addr:housenumber":"1",
    "addr:postcode":"17250",
    "addr:street":"Carr Ter",
    "iso:country":"ES",
    "sg:address":"Carr Ter, 1",
    "sg:city":"Platja D'aro",
    "sg:orig_category":"Agencias Y Agentes Comerciales, Representantes",
    "sg:phone":"+34 972 82 71 48",
    "sg:postcode":"17250",
    "sg:province":"Girona",
    "wof:name":"Shadrina  Nina",
    "wof:placetype":"venue"
},
  "geometry": {"coordinates":[2.8163490295,41.9701499939],"type":"Point"}
}