{
  "type": "Feature",
  "properties": {
    "iso:country":"ES",
    "sg:address":"Calle de Maria Teresa Saenz De Heredia, 11",
    "sg:city":"Madrid",
    "sg:orig_category":"Diarios, Revistas Y Boletines (suscripciones)",
    "sg:phone":"+34 913 56 33 90",
    "sg:postcode":"28017",
    "sg:province":"Madrid",
    "wof:name":"Reyes Fuentes Rafael",
    "wof:placetype":"venue"
},
  "geometry": {"coordinates":[-3.654433012,40.4223327637],"type":"Point"}
}