{
  "type": "Feature",
  "properties": {
    "iso:country":"ES",
    "sg:address":"Calle de Republica Argentina, 1",
    "sg:city":"Castro Urdiales",
    "sg:orig_category":"Cl\u00cdnicas M\u00c9dicas",
    "sg:phone":"+34 942 86 09 96",
    "sg:postcode":"39700",
    "sg:province":"Cantabria",
    "wof:name":"Clinica Castro S.l.",
    "wof:placetype":"venue"
},
  "geometry": {"coordinates":[-3.2183759212,43.3809394836],"type":"Point"}
}