{
  "type": "Feature",
  "properties": {
    "iso:country":"ES",
    "sg:address":"Ctra. Arroyo (p I Almendralejo), S/n",
    "sg:city":"Almendralejo",
    "sg:orig_category":"Fabricaci\u00d3n Y Comercio De M\u00c1quinas",
    "sg:phone":"+34 924 66 70 59",
    "sg:postcode":"06200",
    "sg:province":"Badajoz",
    "wof:name":"Gallardo Martin Maria Asuncion",
    "wof:placetype":"venue"
},
  "geometry": {"coordinates":[-6.408894062,38.6888008118],"type":"Point"}
}