{
  "type": "Feature",
  "properties": {
    "iso:country":"ES",
    "sg:address":"E, 1",
    "sg:city":"Arazuri Landaben",
    "sg:orig_category":"Centros Empresariales",
    "sg:phone":"+34 948 32 41 42",
    "sg:postcode":"31012",
    "sg:province":"Navarra",
    "wof:name":"Truck And Wheel Logistics S. L.",
    "wof:placetype":"venue"
},
  "geometry": {"coordinates":[-1.6124099493,42.6127204895],"type":"Point"}
}