{
  "type": "Feature",
  "properties": {
    "iso:country":"ES",
    "sg:address":"Calle de Matadero, 1",
    "sg:city":"Miajadas",
    "sg:orig_category":"Administraci\u00d3n En Agricultura",
    "sg:phone":"+34 927 16 02 44",
    "sg:postcode":"10100",
    "sg:province":"C\u00e1ceres",
    "wof:name":"Union De Peque\u00f1os Agricultores De Extremadura",
    "wof:placetype":"venue"
},
  "geometry": {"coordinates":[-5.907968998,39.151889801],"type":"Point"}
}