{
  "type": "Feature",
  "properties": {
    "iso:country":"ES",
    "sg:address":"Calle de Formigal, S/n",
    "sg:city":"Fresno Vega",
    "sg:orig_category":"Agricultores, Agricultores",
    "sg:phone":"+34 987 77 00 60",
    "sg:postcode":"24223",
    "sg:province":"Le\u00f3n",
    "wof:name":"Asociacion Ganadera Esla Oteros",
    "wof:placetype":"venue"
},
  "geometry": {"coordinates":[-5.5353002548,42.3457069397],"type":"Point"}
}