{
  "type": "Feature",
  "properties": {
    "addr:full":"Avda Camilo Jose Cela, 39 Cuellar Segovia 40200",
    "addr:housenumber":"39",
    "addr:postcode":"40200",
    "addr:street":"Avda Camilo Jose Cela",
    "iso:country":"ES",
    "sg:address":"Avda Camilo Jose Cela, 39",
    "sg:city":"Cuellar",
    "sg:orig_category":"Jardiner\u00cdas, Vegetales, Art\u00cdculos De Jardiner\u00cda (al Por Menor)",
    "sg:phone":"+34 921 14 33 97",
    "sg:postcode":"40200",
    "sg:province":"Segovia",
    "wof:name":"Agroshop Cuecar S.l.",
    "wof:placetype":"venue"
},
  "geometry": {"coordinates":[-4.309346199,41.3987426758],"type":"Point"}
}