{
  "type": "Feature",
  "properties": {
    "iso:country":"ES",
    "sg:address":"Calle de Limonero, 8",
    "sg:city":"Montesinos",
    "sg:orig_category":"Laboratorios Y Cl\u00cdnicas Veterinarias",
    "sg:phone":"+34 966 72 10 95",
    "sg:postcode":"03187",
    "sg:province":"Alicante",
    "wof:name":"Centro Veterinario Los Montesinos S.l.",
    "wof:placetype":"venue"
},
  "geometry": {"coordinates":[-0.7426900268,38.0251693726],"type":"Point"}
}