{
  "type": "Feature",
  "properties": {
    "iso:country":"ES",
    "sg:address":"Carrer de Corsega, 307",
    "sg:city":"Barcelona",
    "sg:orig_category":"Confecci\u00d3n De Zapatos",
    "sg:phone":"+34 932 17 07 36",
    "sg:postcode":"08008",
    "sg:province":"Barcelona",
    "wof:name":"Desarrollos Insulares S.a.",
    "wof:placetype":"venue"
},
  "geometry": {"coordinates":[2.1572189331,41.3951225281],"type":"Point"}
}