{
  "type": "Feature",
  "properties": {
    "addr:full":"Calle de Jose Aguirre, 4 Valencia Valencia 46011",
    "addr:housenumber":"4",
    "addr:postcode":"46011",
    "addr:street":"Calle De Jose Aguirre",
    "iso:country":"ES",
    "sg:address":"Calle de Jose Aguirre, 4",
    "sg:city":"Valencia",
    "sg:orig_category":"Mantenimiento Y Reparaci\u00d3n De Motores Industriales",
    "sg:phone":"+34 963 67 11 82",
    "sg:postcode":"46011",
    "sg:province":"Valencia",
    "wof:name":"Talleres Tomas Pascual S. L.",
    "wof:placetype":"venue"
},
  "geometry": {"coordinates":[-0.3375279903,39.4621582031],"type":"Point"}
}