{
  "type": "Feature",
  "properties": {
    "addr:full":"Calle de Carre\u00d1o Miranda, 37 Mieres Asturias 33600",
    "addr:housenumber":"37",
    "addr:postcode":"33600",
    "addr:street":"Calle De Carren\u0303O Miranda",
    "iso:country":"ES",
    "sg:address":"Calle de Carre\u00d1o Miranda, 37",
    "sg:city":"Mieres",
    "sg:orig_category":"Molduras, Junquillos, Listones Y Molduras Perforadas",
    "sg:phone":"+34 985 46 89 00",
    "sg:postcode":"33600",
    "sg:province":"Asturias",
    "wof:name":"Pinto Da Fonseca Antonio",
    "wof:placetype":"venue"
},
  "geometry": {"coordinates":[-5.7771677971,43.2525482178],"type":"Point"}
}