{
  "type": "Feature",
  "properties": {
    "addr:full":"Calle de Fuente De Piedra, 4 Madrid Madrid 28018",
    "addr:housenumber":"4",
    "addr:postcode":"28018",
    "addr:street":"Calle De Fuente;Piedra",
    "iso:country":"ES",
    "sg:address":"Calle de Fuente De Piedra, 4",
    "sg:city":"Madrid",
    "sg:orig_category":"Plomeros",
    "sg:phone":"+34 913 03 81 92",
    "sg:postcode":"28018",
    "sg:province":"Madrid",
    "wof:name":"Horcajada Tello Jesus",
    "wof:placetype":"venue"
},
  "geometry": {"coordinates":[-3.6415884495,40.3821907043],"type":"Point"}
}