{
  "type": "Feature",
  "properties": {
    "addr:full":"Plaz Paz (de La), S/n Sanlucar De Barrameda C\u00e1diz 11540",
    "addr:housenumber":"s",
    "addr:postcode":"11540",
    "addr:street":"Plaz;/ N;Ca\u0301Diz",
    "iso:country":"ES",
    "sg:address":"Plaz Paz (de La), S/n",
    "sg:city":"Sanlucar De Barrameda",
    "sg:orig_category":"Arreglo, Reparaci\u00d3n, Piezas Sueltas De Televisi\u00d3n, V\u00cddeo, Hi",
    "sg:phone":"+34 956 36 27 08",
    "sg:postcode":"11540",
    "sg:province":"C\u00e1diz",
    "wof:name":"Reyes Vega Antonio",
    "wof:placetype":"venue"
},
  "geometry": {"coordinates":[-6.3575987816,36.777721405],"type":"Point"}
}