{
  "type": "Feature",
  "properties": {
    "addr:full":"Carr Pujades, 6 Figueres Girona 17600",
    "addr:housenumber":"6",
    "addr:postcode":"17600",
    "addr:street":"Carr Pujades",
    "iso:country":"ES",
    "sg:address":"Carr Pujades, 6",
    "sg:city":"Figueres",
    "sg:orig_category":"Electricidad Veh\u00cdculo",
    "sg:phone":"+34 972 50 42 35",
    "sg:postcode":"17600",
    "sg:province":"Girona",
    "wof:name":"Electromovil Romans S.c.",
    "wof:placetype":"venue"
},
  "geometry": {"coordinates":[2.9653460979,42.2611885071],"type":"Point"}
}