{
  "type": "Feature",
  "properties": {
    "addr:full":"Calle de Franco Garcia Sanchez, 118 Arroyo S Servan Badajoz 06850",
    "addr:housenumber":"118",
    "addr:postcode":"06850",
    "addr:street":"Calle De Franco Garcia Sanchez;Arroyo S Servan",
    "iso:country":"ES",
    "sg:address":"Calle de Franco Garcia Sanchez, 118",
    "sg:city":"Arroyo S Servan",
    "sg:orig_category":"Electricidad: Instaladores",
    "sg:phone":"+34 924 34 31 59",
    "sg:postcode":"06850",
    "sg:province":"Badajoz",
    "wof:name":"Diaz Capote Francisco",
    "wof:placetype":"venue"
},
  "geometry": {"coordinates":[-6.4543747902,38.8560295105],"type":"Point"}
}