{
  "type": "Feature",
  "properties": {
    "iso:country":"ES",
    "sg:address":"Avda Modesto Hernandez Gonzalez, 80",
    "sg:city":"Chafiras",
    "sg:orig_category":"Inform\u00c1tica, Ofim\u00c1tica (estudios, Asesor\u00cda, Ingenier\u00cda, Formaci\u00d3n)",
    "sg:phone":"+34 922 73 61 95",
    "sg:postcode":"38639",
    "sg:province":"Santa Cruz De Tenerife",
    "wof:name":"Perez Vilari\u00f1o Ricardo",
    "wof:placetype":"venue"
},
  "geometry": {"coordinates":[-16.6115474701,28.0350246429],"type":"Point"}
}