{
  "type": "Feature",
  "properties": {
    "iso:country":"ES",
    "sg:address":"Calle de Carteya, 9",
    "sg:city":"Linea De La Concepcion",
    "sg:orig_category":"Producci\u00d3n, Distribuci\u00d3n De Electricidad",
    "sg:phone":"+34 956 17 22 02",
    "sg:postcode":"11300",
    "sg:province":"C\u00e1diz",
    "wof:name":"Sola Earle Manuel J De",
    "wof:placetype":"venue"
},
  "geometry": {"coordinates":[-5.350880146,36.1633796692],"type":"Point"}
}