{
  "type": "Feature",
  "properties": {
    "addr:full":"Calle de Cristobal Colon, 17 Torredelcampo Ja\u00e9n 23640",
    "addr:housenumber":"17",
    "addr:postcode":"23640",
    "addr:street":"Calle De Cristobal Colon;Jae\u0301N",
    "iso:country":"ES",
    "sg:address":"Calle de Cristobal Colon, 17",
    "sg:city":"Torredelcampo",
    "sg:classifiers":[
        {
            "category":"Autos & Motor Vehicles",
            "subcategory":"Automobile Sales",
            "type":"Retail Goods"
        }
    ],
    "sg:phone":"+34 953 56 83 18",
    "sg:postcode":"23640",
    "sg:province":"Ja\u00e9n",
    "wof:name":"Autoescuela Arroyo Juan S.l.",
    "wof:placetype":"venue"
},
  "geometry": {"coordinates":[-3.8977410793,37.7718925476],"type":"Point"}
}