{
  "type": "Feature",
  "properties": {
    "iso:country":"ES",
    "sg:address":"Calle de Gran Avenida, 22",
    "sg:city":"Coria Rio",
    "sg:orig_category":"Frutas Y Legumbres Frescas (al Por Mayor)",
    "sg:phone":"+34 954 77 30 67",
    "sg:postcode":"41100",
    "sg:province":"Sevilla",
    "wof:name":"Frutas Coria S.l.",
    "wof:placetype":"venue"
},
  "geometry": {"coordinates":[-6.0466961861,37.2950172424],"type":"Point"}
}