{
  "type": "Feature",
  "properties": {
    "iso:country":"ES",
    "sg:address":"Carrer de Joncs, 8",
    "sg:city":"Hospitalet Llobregat",
    "sg:orig_category":"Reposter\u00cdas",
    "sg:phone":"+34 932 63 39 05",
    "sg:postcode":"08902",
    "sg:province":"Barcelona",
    "wof:name":"Distribuidora Del Gornal S. A.",
    "wof:placetype":"venue"
},
  "geometry": {"coordinates":[2.1187500954,41.3576202393],"type":"Point"}
}