{
  "type": "Feature",
  "properties": {
    "addr:full":"Calle de San Gines, 27 Guare\u00f1a Badajoz 06470",
    "addr:housenumber":"27",
    "addr:postcode":"06470",
    "addr:street":"Calle De San Gines",
    "iso:country":"ES",
    "sg:address":"Calle de San Gines, 27",
    "sg:city":"Guare\u00f1a",
    "sg:orig_category":"Promotores Constructores",
    "sg:phone":"+34 924 35 09 45",
    "sg:postcode":"06470",
    "sg:province":"Badajoz",
    "wof:name":"Alba\u00f1ileria Y Construcciones De Badajoz S.l.",
    "wof:placetype":"venue"
},
  "geometry": {"coordinates":[-6.1038165092,38.8634338379],"type":"Point"}
}