{
  "type": "Feature",
  "properties": {
    "addr:full":"Calle de General Oraa, 84 Madrid Madrid 28006",
    "addr:housenumber":"84",
    "addr:postcode":"madrid;28006",
    "addr:street":"Calle De General Oraa",
    "iso:country":"ES",
    "sg:address":"Calle de General Oraa, 84",
    "sg:city":"Madrid",
    "sg:orig_category":"Asesor\u00cda Sobre Comunicaci\u00d3n De Empresas",
    "sg:phone":"+34 915 61 34 26",
    "sg:postcode":"28006",
    "sg:province":"Madrid",
    "wof:name":"Rodrigo Salmeron Jesus",
    "wof:placetype":"venue"
},
  "geometry": {"coordinates":[-3.6765840054,40.4356689453],"type":"Point"}
}