{
  "type": "Feature",
  "properties": {
    "iso:country":"ES",
    "sg:address":"Rguez. De La Fuente, S/n",
    "sg:city":"Prado Del Rey",
    "sg:orig_category":"Mec\u00c1nico Del Autom\u00d3vil",
    "sg:phone":"+34 956 72 33 05",
    "sg:postcode":"11660",
    "sg:province":"C\u00e1diz",
    "wof:name":"Talleres Gomez S.c",
    "wof:placetype":"venue"
},
  "geometry": {"coordinates":[-5.5597438812,36.7833709717],"type":"Point"}
}