{
  "type": "Feature",
  "properties": {
    "addr:full":"Calle de San Fernando, 32 Quintanar Orden Toledo 45800",
    "addr:housenumber":"32",
    "addr:postcode":"45800",
    "addr:street":"Calle De San Fernando",
    "iso:country":"ES",
    "sg:address":"Calle de San Fernando, 32",
    "sg:city":"Quintanar Orden",
    "sg:orig_category":"Muebles, Minoristas",
    "sg:phone":"+34 925 56 40 25",
    "sg:postcode":"45800",
    "sg:province":"Toledo",
    "wof:name":"Muebles Garcia Romeral S.l.",
    "wof:placetype":"venue"
},
  "geometry": {"coordinates":[-3.0458700657,39.5940093994],"type":"Point"}
}