{
  "type": "Feature",
  "properties": {
    "addr:full":"Calle de Calvo Sotelo, 1 Barbate C\u00e1diz 11160",
    "addr:housenumber":"1",
    "addr:postcode":"11160",
    "addr:street":"Calle De Calvo Sotelo",
    "iso:country":"ES",
    "sg:address":"Calle de Calvo Sotelo, 1",
    "sg:city":"Barbate",
    "sg:orig_category":"Farmacias",
    "sg:phone":"+34 956 43 01 82",
    "sg:postcode":"11160",
    "sg:province":"C\u00e1diz",
    "wof:name":"Farmacia Lara C.b.",
    "wof:placetype":"venue"
},
  "geometry": {"coordinates":[-5.9185128212,36.1914138794],"type":"Point"}
}