{
  "type": "Feature",
  "properties": {
    "iso:country":"ES",
    "sg:address":"Ctra Carabanchel, Km. 0002,3",
    "sg:city":"Leganes",
    "sg:orig_category":"Construcciones Met\u00c1licas",
    "sg:phone":"+34 917 65 18 27",
    "sg:postcode":"28914",
    "sg:province":"Madrid",
    "wof:name":"Avila Valleros Tiburcio",
    "wof:placetype":"venue"
},
  "geometry": {"coordinates":[-3.7295315266,40.3538742065],"type":"Point"}
}