{
  "type": "Feature",
  "properties": {
    "iso:country":"ES",
    "sg:address":"Carrer de Zamora, 38",
    "sg:city":"Barcelona",
    "sg:orig_category":"Farmacias",
    "sg:phone":"+34 933 09 38 07",
    "sg:postcode":"08005",
    "sg:province":"Barcelona",
    "wof:name":"Sole Janer Angela",
    "wof:placetype":"venue"
},
  "geometry": {"coordinates":[2.1933860779,41.3931083679],"type":"Point"}
}