{
  "type": "Feature",
  "properties": {
    "addr:full":"Calle de Roldan Y Marin, 8 Jaen Ja\u00e9n 23001",
    "addr:housenumber":"8;jae\u0301n",
    "addr:postcode":"23001",
    "addr:street":"Calle De Roldan Y Marin",
    "iso:country":"ES",
    "sg:address":"Calle de Roldan Y Marin, 8",
    "sg:city":"Jaen",
    "sg:orig_category":"Asistencia Y Consejos",
    "sg:phone":"+34 953 24 06 25",
    "sg:postcode":"23001",
    "sg:province":"Ja\u00e9n",
    "wof:name":"Campos Lopez Purificacion",
    "wof:placetype":"venue"
},
  "geometry": {"coordinates":[-3.7879319191,37.7688407898],"type":"Point"}
}