{
  "type": "Feature",
  "properties": {
    "addr:full":"Calle de Atocha, 35 Madrid Madrid 28012",
    "addr:housenumber":"35",
    "addr:postcode":"madrid;28012",
    "addr:street":"Calle De Atocha",
    "iso:country":"ES",
    "sg:address":"Calle de Atocha, 35",
    "sg:city":"Madrid",
    "sg:orig_category":"Fabricaci\u00d3n De Telas Y Sedas",
    "sg:phone":"+34 913 69 16 34",
    "sg:postcode":"28012",
    "sg:province":"Madrid",
    "wof:name":"Calella S. A.",
    "wof:placetype":"venue"
},
  "geometry": {"coordinates":[-3.7020885944,40.413684845],"type":"Point"}
}