{
  "type": "Feature",
  "properties": {
    "iso:country":"ES",
    "sg:address":"Disseminat, S/n",
    "sg:city":"S. Salvador Torroella",
    "sg:orig_category":"Agricultura: Abastecimiento Y Cosechado (negocio)",
    "sg:phone":"+34 938 69 64 29",
    "sg:postcode":"08679",
    "sg:province":"Barcelona",
    "wof:name":"Torroella Ramadera S.l.",
    "wof:placetype":"venue"
},
  "geometry": {"coordinates":[1.780755043,41.9793510437],"type":"Point"}
}