{
  "type": "Feature",
  "properties": {
    "addr:full":"Ctra Competa, 11 Moraleda Zafayona Granada 18370",
    "addr:housenumber":"11;zafayona",
    "addr:postcode":"18370",
    "addr:street":"Ctra Competa",
    "iso:country":"ES",
    "sg:address":"Ctra Competa, 11",
    "sg:city":"Moraleda Zafayona",
    "sg:orig_category":"Venta, Montaje De Neum\u00c1ticos",
    "sg:phone":"+34 958 44 33 62",
    "sg:postcode":"18370",
    "sg:province":"Granada",
    "wof:name":"Terron Sanchez Francisco",
    "wof:placetype":"venue"
},
  "geometry": {"coordinates":[-3.9674110413,37.1681900024],"type":"Point"}
}