{
  "type": "Feature",
  "properties": {
    "iso:country":"ES",
    "sg:address":"Carrer de Gravina, 30",
    "sg:city":"Roses",
    "sg:orig_category":"Armas Y Municiones (fabricaci\u00d3n, Al Por Mayor)",
    "sg:phone":"+34 972 25 31 54",
    "sg:postcode":"17480",
    "sg:province":"Girona",
    "sg:website":"www.armeriaroses.com",
    "wof:name":"Armeria Roses S.l.",
    "wof:placetype":"venue"
},
  "geometry": {"coordinates":[3.1810283661,42.2621040344],"type":"Point"}
}