{
  "type": "Feature",
  "properties": {
    "iso:country":"ES",
    "sg:address":"Rua Montero Rios (de), 40",
    "sg:city":"Santiago De Compostela",
    "sg:orig_category":"Parques De Atracciones Y Centros De Esparcimiento",
    "sg:phone":"+34 981 56 16 07",
    "sg:postcode":"15706",
    "sg:province":"La Coru\u00f1a",
    "wof:name":"Electronicos Erma S.a.",
    "wof:placetype":"venue"
},
  "geometry": {"coordinates":[-8.5481767654,42.8755073547],"type":"Point"}
}