{
  "type": "Feature",
  "properties": {
    "addr:full":"Rua Mondo\u00d1edo, 14 Lugo Lugo 27004",
    "addr:housenumber":"14",
    "addr:postcode":"27004",
    "addr:street":"Rua Mondon\u0303Edo",
    "iso:country":"ES",
    "sg:address":"Rua Mondo\u00d1edo, 14",
    "sg:city":"Lugo",
    "sg:orig_category":"Ingenier\u00cda, Centros De Estudios (diversos)",
    "sg:phone":"+34 982 24 20 72",
    "sg:postcode":"27004",
    "sg:province":"Lugo",
    "wof:name":"Euroestudios S.l.",
    "wof:placetype":"venue"
},
  "geometry": {"coordinates":[-7.5629529953,43.0148468018],"type":"Point"}
}