{
  "type": "Feature",
  "properties": {
    "addr:full":"Avda. Constitucion, 66 Moreda Asturias 33670",
    "addr:housenumber":"66",
    "addr:postcode":"33670",
    "addr:street":"Avda. Constitucion",
    "iso:country":"ES",
    "sg:address":"Avda. Constitucion, 66",
    "sg:city":"Moreda",
    "sg:orig_category":"Muebles, Minoristas",
    "sg:phone":"+34 985 48 31 73",
    "sg:postcode":"33670",
    "sg:province":"Asturias",
    "wof:name":"Pando Trapiello Vidal",
    "wof:placetype":"venue"
},
  "geometry": {"coordinates":[-5.7376289368,43.1678504944],"type":"Point"}
}