{
  "type": "Feature",
  "properties": {
    "addr:full":"Calle de Sitios (los), 12 Astorga Le\u00f3n 24700",
    "addr:postcode":"24700",
    "addr:street":"Calle De Sitios Los;Astorga Leo\u0301N",
    "iso:country":"ES",
    "sg:address":"Calle de Sitios (los), 12",
    "sg:city":"Astorga",
    "sg:orig_category":"Panader\u00cdas, Panader\u00cdas",
    "sg:phone":"+34 987 60 26 72",
    "sg:postcode":"24700",
    "sg:province":"Le\u00f3n",
    "wof:name":"Alonso Fernandez Cesar Luis",
    "wof:placetype":"venue"
},
  "geometry": {"coordinates":[-6.0549535751,42.4571800232],"type":"Point"}
}