{
  "type": "Feature",
  "properties": {
    "addr:full":"Avda Constitucion, 60 Gijon Asturias 33207",
    "addr:housenumber":"60",
    "addr:postcode":"33207",
    "addr:street":"Avda Constitucion",
    "iso:country":"ES",
    "sg:address":"Avda Constitucion, 60",
    "sg:city":"Gijon",
    "sg:orig_category":"Muebles, Minoristas",
    "sg:phone":"+34 985 17 00 54",
    "sg:postcode":"33207",
    "sg:province":"Asturias",
    "wof:name":"Jose Sabino Antu\u00f1a De Alaiz",
    "wof:placetype":"venue"
},
  "geometry": {"coordinates":[-5.6697692871,43.5336456299],"type":"Point"}
}