{
  "type": "Feature",
  "properties": {
    "addr:full":"Pg Cordelles, 9 Cerdanyola Valles Barcelona 08290",
    "addr:housenumber":"9",
    "addr:postcode":"08290",
    "addr:street":"Pg Cordelles;Valles Barcelona",
    "iso:country":"ES",
    "sg:address":"Pg Cordelles, 9",
    "sg:city":"Cerdanyola Valles",
    "sg:orig_category":"Cl\u00cdnicas Dentales",
    "sg:phone":"+34 936 92 54 80",
    "sg:postcode":"08290",
    "sg:province":"Barcelona",
    "wof:name":"Espadas Garcia Manuel",
    "wof:placetype":"venue"
},
  "geometry": {"coordinates":[2.1394369602,41.4922103882],"type":"Point"}
}