{
  "type": "Feature",
  "properties": {
    "iso:country":"ES",
    "sg:address":"Calle de Jose Maria Usandizaga, 6",
    "sg:city":"Errenteria",
    "sg:orig_category":"Empresas De Carpinter\u00cda De Madera",
    "sg:phone":"+34 943 52 07 49",
    "sg:postcode":"20100",
    "sg:province":"Guip\u00f9zcoa",
    "wof:name":"Gonzalez Carballude Manuel",
    "wof:placetype":"venue"
},
  "geometry": {"coordinates":[-1.9136669636,43.3099975586],"type":"Point"}
}