{
  "type": "Feature",
  "properties": {
    "addr:full":"Calle de Rua Mayor, 12 Salamanca Salamanca 37002",
    "addr:housenumber":"12",
    "addr:postcode":"37002",
    "addr:street":"Calle De Rua Mayor",
    "iso:country":"ES",
    "sg:address":"Calle de Rua Mayor, 12",
    "sg:city":"Salamanca",
    "sg:orig_category":"Discotecas Y Salas De Baile",
    "sg:phone":"+34 923 27 09 85",
    "sg:postcode":"37002",
    "sg:province":"Salamanca",
    "wof:name":"Discale S. A.",
    "wof:placetype":"venue"
},
  "geometry": {"coordinates":[-5.6650238037,40.9636878967],"type":"Point"}
}