{
  "type": "Feature",
  "properties": {
    "addr:full":"Breto\u00f1a, 5 Curro Pontevedra 36692",
    "addr:housenumber":"5",
    "addr:postcode":"36692",
    "addr:street":"Breton\u0303A",
    "iso:country":"ES",
    "sg:address":"Breto\u00f1a, 5",
    "sg:city":"Curro",
    "sg:orig_category":"Puertas Y Portales",
    "sg:phone":"+34 986 71 32 73",
    "sg:postcode":"36692",
    "sg:province":"Pontevedra",
    "wof:name":"Comercial Vilanova S.l.",
    "wof:placetype":"venue"
},
  "geometry": {"coordinates":[-8.663807869,42.5055503845],"type":"Point"}
}