{
  "type": "Feature",
  "properties": {
    "addr:full":"Calle de Monteaveruelo, 140 Sotolargo Guadalajara 19176",
    "addr:housenumber":"140",
    "addr:postcode":"19176",
    "addr:street":"Calle De Monteaveruelo",
    "iso:country":"ES",
    "sg:address":"Calle de Monteaveruelo, 140",
    "sg:city":"Sotolargo",
    "sg:orig_category":"Administradores De Bienes Y Delegados De Comunidades De Propietarios",
    "sg:phone":"+34 949 33 95 91",
    "sg:postcode":"19176",
    "sg:province":"Guadalajara",
    "wof:name":"Pallares Holz Maria Del Carmen",
    "wof:placetype":"venue"
},
  "geometry": {"coordinates":[-3.3054642677,40.6372337341],"type":"Point"}
}