{
  "type": "Feature",
  "properties": {
    "iso:country":"ES",
    "sg:address":"Plaz San Lazaro, 4",
    "sg:city":"Palencia",
    "sg:orig_category":"Comercio De Piezas De Recambio Y De Accesorios De Veh\u00cdculos, Veh\u00cdculos Industriales",
    "sg:phone":"+34 979 72 36 82",
    "sg:postcode":"34001",
    "sg:province":"Palencia",
    "wof:name":"Auto Recambios Solas S.a.",
    "wof:placetype":"venue"
},
  "geometry": {"coordinates":[-4.5290322304,42.0093078613],"type":"Point"}
}