{
  "type": "Feature",
  "properties": {
    "addr:full":"Ntra. Sra. Mayor Afliccion, 29 Jerez C\u00e1diz 11406",
    "addr:housenumber":"29",
    "addr:postcode":"11406",
    "addr:street":"Afliccion",
    "iso:country":"ES",
    "sg:address":"Ntra. Sra. Mayor Afliccion, 29",
    "sg:city":"Jerez",
    "sg:orig_category":"Empresas De Desmonte",
    "sg:phone":"+34 956 32 33 36",
    "sg:postcode":"11406",
    "sg:province":"C\u00e1diz",
    "wof:name":"Juan Romo S.a.",
    "wof:placetype":"venue"
},
  "geometry": {"coordinates":[-6.1049957275,36.6741828918],"type":"Point"}
}