{
  "type": "Feature",
  "properties": {
    "addr:full":"Carrer de Corsega, 300 Barcelona Barcelona 08008",
    "addr:housenumber":"300",
    "addr:postcode":"08008",
    "addr:street":"Carrer De Corsega",
    "iso:country":"ES",
    "sg:address":"Carrer de Corsega, 300",
    "sg:city":"Barcelona",
    "sg:orig_category":"Ense\u00d1anza Variada",
    "sg:phone":"+34 932 12 56 26",
    "sg:postcode":"08008",
    "sg:province":"Barcelona",
    "wof:name":"Francina Modelling Agency S.l.",
    "wof:placetype":"venue"
},
  "geometry": {"coordinates":[2.1579740047,41.3953590393],"type":"Point"}
}