{
  "type": "Feature",
  "properties": {
    "addr:full":"Trav. Salas, 99 Quintanilla Agua Burgos 09347",
    "addr:housenumber":"99",
    "addr:postcode":"09347",
    "addr:street":"Salas",
    "iso:country":"ES",
    "sg:address":"Trav. Salas, 99",
    "sg:city":"Quintanilla Agua",
    "sg:orig_category":"Agricultores, Agricultores",
    "sg:phone":"+34 947 17 45 36",
    "sg:postcode":"09347",
    "sg:province":"Burgos",
    "wof:name":"Lozano Izquierdo Alberto",
    "wof:placetype":"venue"
},
  "geometry": {"coordinates":[-3.5831389427,42.0423812866],"type":"Point"}
}