{
  "type": "Feature",
  "properties": {
    "iso:country":"ES",
    "sg:address":"Pase Constitucion (la), 16",
    "sg:city":"Zaragoza",
    "sg:orig_category":"Telas Para Tapizar, Cortinas, Pasamaner\u00cda (fabricaci\u00d3n, Al Por Mayor)",
    "sg:phone":"+34 976 23 47 34",
    "sg:postcode":"50008",
    "sg:province":"Zaragoza",
    "sg:website":"www.ka-international.com",
    "wof:name":"Pueyo Vi\u00f1uales Elena",
    "wof:placetype":"venue"
},
  "geometry": {"coordinates":[-0.8818839788,41.6476821899],"type":"Point"}
}