{
  "type": "Feature",
  "properties": {
    "addr:full":"Ctra Madrid-cadiz (pi Palmera), Km. 0550,6 Sevilla Sevilla 41014",
    "addr:postcode":"41014",
    "addr:street":"Ctra Madrid-Cadiz;Palmera Km. 0550,6",
    "iso:country":"ES",
    "sg:address":"Ctra Madrid-cadiz (pi Palmera), Km. 0550,6",
    "sg:city":"Sevilla",
    "sg:orig_category":"Aceites Y Grasas Alimentarias (fabricaci\u00d3n, Al Por Mayor)",
    "sg:phone":"+34 954 69 23 06",
    "sg:postcode":"41014",
    "sg:province":"Sevilla",
    "wof:name":"Actividades Oleicolas S. A.",
    "wof:placetype":"venue"
},
  "geometry": {"coordinates":[-5.9647536278,37.3367156982],"type":"Point"}
}