{
  "type": "Feature",
  "properties": {
    "iso:country":"ES",
    "sg:address":"Calle de Laurel, 1",
    "sg:city":"Puebla Almoradiel",
    "sg:orig_category":"Enfermeras: Consultas, Atenci\u00d3n A Domicilio",
    "sg:phone":"+34 925 17 81 53",
    "sg:postcode":"45840",
    "sg:province":"Toledo",
    "wof:name":"Basas Vaquero Felix",
    "wof:placetype":"venue"
},
  "geometry": {"coordinates":[-3.1204578876,39.6008110046],"type":"Point"}
}