{
  "type": "Feature",
  "properties": {
    "addr:full":"Calle de Cesar Augusto, 51 Torreciega Murcia 30392",
    "addr:housenumber":"51",
    "addr:postcode":"30392",
    "addr:street":"Calle De Cesar Augusto",
    "iso:country":"ES",
    "sg:address":"Calle de Cesar Augusto, 51",
    "sg:city":"Torreciega",
    "sg:orig_category":"Albergues",
    "sg:phone":"+34 968 32 07 38",
    "sg:postcode":"30392",
    "sg:province":"Murcia",
    "wof:name":"Sanchez Velasco Jose Carlos",
    "wof:placetype":"venue"
},
  "geometry": {"coordinates":[-0.9673542976,37.6147155762],"type":"Point"}
}