{
  "type": "Feature",
  "properties": {
    "addr:full":"Calle de San Lucas, 42 Santa Cruz De Tenerife Santa Cruz De Tenerife 38002",
    "addr:housenumber":"42",
    "addr:postcode":"38002",
    "addr:street":"Calle De San Lucas",
    "iso:country":"ES",
    "sg:address":"Calle de San Lucas, 42",
    "sg:city":"Santa Cruz De Tenerife",
    "sg:orig_category":"M\u00c9dicos: Nefrolog\u00cda",
    "sg:phone":"+34 922 28 48 10",
    "sg:postcode":"38002",
    "sg:province":"Santa Cruz De Tenerife",
    "wof:name":"Garcia Perez Jose Javier",
    "wof:placetype":"venue"
},
  "geometry": {"coordinates":[-17.2191944122,28.1820106506],"type":"Point"}
}