{
  "type": "Feature",
  "properties": {
    "addr:full":"Pase Pamplona, 7 Tudela Navarra 31500",
    "addr:housenumber":"7",
    "addr:postcode":"31500",
    "addr:street":"Pamplona",
    "iso:country":"ES",
    "sg:address":"Pase Pamplona, 7",
    "sg:city":"Tudela",
    "sg:orig_category":"Organizaciones Internacionales",
    "sg:phone":"+34 948 82 74 50",
    "sg:postcode":"31500",
    "sg:province":"Navarra",
    "sg:website":"www.cruzroja.es",
    "wof:name":"Cruz Roja Espa\u00f1ola",
    "wof:placetype":"venue"
},
  "geometry": {"coordinates":[-1.60295403,42.0619239807],"type":"Point"}
}