{
  "type": "Feature",
  "properties": {
    "addr:full":"Calle de Plaza, 17 Villaseco De Los Reyes Salamanca 37150",
    "addr:housenumber":"17",
    "addr:postcode":"37150",
    "addr:street":"Calle De Plaza",
    "iso:country":"ES",
    "sg:address":"Calle de Plaza, 17",
    "sg:city":"Villaseco De Los Reyes",
    "sg:orig_category":"Fabricaci\u00d3n De Juguetes Autom\u00c1ticos",
    "sg:phone":"+34 923 57 51 17",
    "sg:postcode":"37150",
    "sg:province":"Salamanca",
    "wof:name":"Elena Vacas Juan Jose",
    "wof:placetype":"venue"
},
  "geometry": {"coordinates":[-6.1831321716,41.1644592285],"type":"Point"}
}