{
  "type": "Feature",
  "properties": {
    "addr:full":"Carr Manuel Simo Marin, 16 Ontinyent Valencia 46870",
    "addr:housenumber":"16",
    "addr:postcode":"46870",
    "addr:street":"Carr Manuel Simo Marin",
    "iso:country":"ES",
    "sg:address":"Carr Manuel Simo Marin, 16",
    "sg:city":"Ontinyent",
    "sg:orig_category":"Partidos Pol\u00cdticos",
    "sg:phone":"+34 962 91 09 29",
    "sg:postcode":"46870",
    "sg:province":"Valencia",
    "wof:name":"Esquerra Unida Del Pais Valencia",
    "wof:placetype":"venue"
},
  "geometry": {"coordinates":[-0.6038280129,38.8213157654],"type":"Point"}
}