{
  "type": "Feature",
  "properties": {
    "addr:full":"Calle de Portillo San Antonio, 8 San Miguel Murcia 30005",
    "addr:housenumber":"8",
    "addr:postcode":"30005",
    "addr:street":"Calle De Portillo San Antonio",
    "iso:country":"ES",
    "sg:address":"Calle de Portillo San Antonio, 8",
    "sg:city":"San Miguel",
    "sg:orig_category":"Laboratorios Farmac\u00c9uticos",
    "sg:phone":"+34 968 28 42 65",
    "sg:postcode":"30005",
    "sg:province":"Murcia",
    "wof:name":"Jimenez Serrano Jose Luis",
    "wof:placetype":"venue"
},
  "geometry": {"coordinates":[-1.1326550245,37.988910675],"type":"Point"}
}