{
  "type": "Feature",
  "properties": {
    "iso:country":"ES",
    "sg:address":"Carr Verge De Montserrat, 32",
    "sg:city":"Picanya",
    "sg:orig_category":"Guarder\u00cdas",
    "sg:phone":"+34 961 59 33 31",
    "sg:postcode":"46210",
    "sg:province":"Valencia",
    "wof:name":"Escola Infantil El Cuquet C.b.",
    "wof:placetype":"venue"
},
  "geometry": {"coordinates":[-0.4392960072,39.4358253479],"type":"Point"}
}