{
  "type": "Feature",
  "properties": {
    "iso:country":"ES",
    "sg:address":"Pol. Ind. Erletxes, 119",
    "sg:city":"Gumuzio",
    "sg:orig_category":"Pintura Industrial (trabajos De)",
    "sg:phone":"+34 946 33 40 98",
    "sg:postcode":"48960",
    "sg:province":"Vizcaya",
    "wof:name":"Santos Recio Juan Manuel",
    "wof:placetype":"venue"
},
  "geometry": {"coordinates":[-2.8470389843,43.2298049927],"type":"Point"}
}