{
  "type": "Feature",
  "properties": {
    "iso:country":"ES",
    "sg:address":"Z Parque Comercial Galaria, 1",
    "sg:city":"Cordovilla",
    "sg:orig_category":"Ropa Para Se\u00d1oras Y Caballeros (al Por Menor)",
    "sg:phone":"+34 948 15 08 17",
    "sg:postcode":"31191",
    "sg:province":"Navarra",
    "sg:website":"www.pullbear.com",
    "wof:name":"Pull & Bear Espa\u00f1a S.a.",
    "wof:placetype":"venue"
},
  "geometry": {"coordinates":[-1.6518089771,42.7533912659],"type":"Point"}
}