{
  "type": "Feature",
  "properties": {
    "iso:country":"ES",
    "sg:address":"Carrer de Josep Argila, 2",
    "sg:city":"Casco Urbano",
    "sg:orig_category":"Porcelanas, Azulejos (fabricaci\u00d3n, Al Por Mayor)",
    "sg:phone":"+34 938 41 18 89",
    "sg:postcode":"08450",
    "sg:province":"Barcelona",
    "wof:name":"Ingenieria Ceramicas Casillas S.l.",
    "wof:placetype":"venue"
},
  "geometry": {"coordinates":[2.4019749165,41.6397705078],"type":"Point"}
}