{
  "type": "Feature",
  "properties": {
    "addr:full":"Calle de Juan Xxiii, 11 Aviles Asturias 33401",
    "addr:housenumber":"11",
    "addr:postcode":"33401",
    "addr:street":"Calle De Juan Xxiii",
    "iso:country":"ES",
    "sg:address":"Calle de Juan Xxiii, 11",
    "sg:city":"Aviles",
    "sg:orig_category":"Ense\u00d1anza: Idiomas",
    "sg:phone":"+34 985 52 20 56",
    "sg:postcode":"33401",
    "sg:province":"Asturias",
    "wof:name":"Hello English C B",
    "wof:placetype":"venue"
},
  "geometry": {"coordinates":[-5.9311690331,43.5558853149],"type":"Point"}
}