{
  "type": "Feature",
  "properties": {
    "addr:full":"Calle de Augusto Figueroa, 49 Madrid Madrid 28004",
    "addr:housenumber":"49",
    "addr:postcode":"madrid;28004",
    "addr:street":"Calle De Augusto Figueroa",
    "iso:country":"ES",
    "sg:address":"Calle de Augusto Figueroa, 49",
    "sg:city":"Madrid",
    "sg:orig_category":"Abogados",
    "sg:phone":"+34 915 21 58 81",
    "sg:postcode":"28004",
    "sg:province":"Madrid",
    "wof:name":"Gonzalez Izpizua Margarita",
    "wof:placetype":"venue"
},
  "geometry": {"coordinates":[-3.6958072186,40.4219360352],"type":"Point"}
}