{
  "type": "Feature",
  "properties": {
    "addr:full":"Carr Vilafant, 49 Figueres Girona 17600",
    "addr:housenumber":"49",
    "addr:postcode":"17600",
    "addr:street":"Carr Vilafant",
    "iso:country":"ES",
    "sg:address":"Carr Vilafant, 49",
    "sg:city":"Figueres",
    "sg:orig_category":"Frutas, Legumbres Frescas Y Tempranas (al Por Menor)",
    "sg:phone":"+34 972 67 23 66",
    "sg:postcode":"17600",
    "sg:province":"Girona",
    "wof:name":"Marti Poch Angela",
    "wof:placetype":"venue"
},
  "geometry": {"coordinates":[2.9594619274,42.2644538879],"type":"Point"}
}