{
  "type": "Feature",
  "properties": {
    "iso:country":"ES",
    "sg:address":"Calle de Francos Rodriguez, 15",
    "sg:city":"Madrid",
    "sg:orig_category":"Loter\u00cda Y T\u00d3mbola",
    "sg:phone":"+34 913 11 57 22",
    "sg:postcode":"28039",
    "sg:province":"Madrid",
    "wof:name":"Pedruelo Descals Santiago",
    "wof:placetype":"venue"
},
  "geometry": {"coordinates":[-3.7046473026,40.4561729431],"type":"Point"}
}