{
  "type": "Feature",
  "properties": {
    "iso:country":"ES",
    "sg:address":"Carr Joan Pau Climent, 1",
    "sg:city":"Villafranca Cid",
    "sg:orig_category":"Centros Empresariales",
    "sg:phone":"+34 964 44 02 25",
    "sg:postcode":"12150",
    "sg:province":"Castell\u00f3n",
    "wof:name":"Labuiga Albert Eugeni",
    "wof:placetype":"venue"
},
  "geometry": {"coordinates":[-0.2569360137,40.4276580811],"type":"Point"}
}