{
  "type": "Feature",
  "properties": {
    "addr:full":"Estd Castela, 573 Ponto La Coru\u00f1a 15570",
    "addr:housenumber":"573",
    "addr:postcode":"15570",
    "addr:street":"Castela;Corun\u0303A",
    "iso:country":"ES",
    "sg:address":"Estd Castela, 573",
    "sg:city":"Ponto",
    "sg:orig_category":"Reposter\u00cdas",
    "sg:phone":"+34 981 38 26 19",
    "sg:postcode":"15570",
    "sg:province":"La Coru\u00f1a",
    "wof:name":"Forno E Ferreteria Foso S.l.",
    "wof:placetype":"venue"
},
  "geometry": {"coordinates":[-8.1647539139,43.5165405273],"type":"Point"}
}