{
  "type": "Feature",
  "properties": {
    "iso:country":"ES",
    "sg:address":"Calle de Numa Guilhou, 2",
    "sg:city":"Mieres",
    "sg:orig_category":"Fisioterapia",
    "sg:phone":"+34 985 45 16 36",
    "sg:postcode":"33600",
    "sg:province":"Asturias",
    "wof:name":"Alvarez Juberias Daniel",
    "wof:placetype":"venue"
},
  "geometry": {"coordinates":[-5.7761521339,43.2504310608],"type":"Point"}
}