{
  "type": "Feature",
  "properties": {
    "iso:country":"ES",
    "sg:address":"Pase Canalejas, 25",
    "sg:city":"Salamanca",
    "sg:orig_category":"Radiocomunicaciones, Telefon\u00cda M\u00d3vil, Radiomensajer\u00cda: Servicios, Comercializaci\u00d3n",
    "sg:phone":"+34 923 27 07 40",
    "sg:postcode":"37001",
    "sg:province":"Salamanca",
    "wof:name":"Herpri Telefonia S.l.",
    "wof:placetype":"venue"
},
  "geometry": {"coordinates":[-5.6576337814,40.9663124084],"type":"Point"}
}