{
  "type": "Feature",
  "properties": {
    "addr:full":"Ctra Vcia-alicante, Km. 0154,0 Alfas Pi Alicante 03580",
    "addr:postcode":"03580",
    "addr:street":"Ctra Vcia-Alicante Km. 0154,0 Alfas;Alicante",
    "iso:country":"ES",
    "sg:address":"Ctra Vcia-alicante, Km. 0154,0",
    "sg:city":"Alfas Pi",
    "sg:orig_category":"Impermeabilizantes",
    "sg:phone":"+34 966 86 69 44",
    "sg:postcode":"03580",
    "sg:province":"Alicante",
    "wof:name":"Amador Lope Arbeteta Sociedad Limitada",
    "wof:placetype":"venue"
},
  "geometry": {"coordinates":[-0.4810059965,38.3452033997],"type":"Point"}
}