{
  "type": "Feature",
  "properties": {
    "iso:country":"ES",
    "sg:address":"Calle de Zazuar, 3",
    "sg:city":"Aranda Duero",
    "sg:orig_category":"Molduras, Junquillos, Listones Y Molduras Perforadas",
    "sg:phone":"+34 947 50 02 56",
    "sg:postcode":"09400",
    "sg:province":"Burgos",
    "wof:name":"Maroto Maroto Teresa",
    "wof:placetype":"venue"
},
  "geometry": {"coordinates":[-3.6767609119,41.6719779968],"type":"Point"}
}