{
  "type": "Feature",
  "properties": {
    "iso:country":"ES",
    "sg:address":"Calle de Almona Del Boqueron, 10",
    "sg:city":"Granada",
    "sg:orig_category":"Molduras, Junquillos, Listones Y Molduras Perforadas",
    "sg:phone":"+34 958 20 35 21",
    "sg:postcode":"18001",
    "sg:province":"Granada",
    "wof:name":"Afrodisia C.b.",
    "wof:placetype":"venue"
},
  "geometry": {"coordinates":[-3.600976944,37.180721283],"type":"Point"}
}