{
  "type": "Feature",
  "properties": {
    "addr:full":"Avda Republica Argentina, 25 Sevilla Sevilla 41011",
    "addr:housenumber":"25",
    "addr:postcode":"41011",
    "addr:street":"Avda Republica Argentina",
    "iso:country":"ES",
    "sg:address":"Avda Republica Argentina, 25",
    "sg:city":"Sevilla",
    "sg:orig_category":"Abogados",
    "sg:phone":"+34 954 27 61 44",
    "sg:postcode":"41011",
    "sg:province":"Sevilla",
    "wof:name":"Zarraluqui Abogados De Familia En Sevilla S.l.",
    "wof:placetype":"venue"
},
  "geometry": {"coordinates":[-6.0020904541,37.3777389526],"type":"Point"}
}