{
  "type": "Feature",
  "properties": {
    "iso:country":"ES",
    "sg:address":"Carrer de Mare De Deu De Fatima, 31",
    "sg:city":"Rubi",
    "sg:orig_category":"Congelados: Productos Alimentarios (al Por Menor)",
    "sg:phone":"+34 935 88 60 19",
    "sg:postcode":"08191",
    "sg:province":"Barcelona",
    "wof:name":"Sola Juarez Francisco",
    "wof:placetype":"venue"
},
  "geometry": {"coordinates":[2.0281500816,41.4989509583],"type":"Point"}
}