{
  "type": "Feature",
  "properties": {
    "iso:country":"ES",
    "sg:address":"Calle de Tercia, 8",
    "sg:city":"Porzuna",
    "sg:orig_category":"Venta, Montaje De Neum\u00c1ticos",
    "sg:phone":"+34 926 78 00 11",
    "sg:postcode":"13120",
    "sg:province":"Ciudad Real",
    "wof:name":"Hervas Pedraza Andres",
    "wof:placetype":"venue"
},
  "geometry": {"coordinates":[-4.1543469429,39.1474113464],"type":"Point"}
}