{
  "type": "Feature",
  "properties": {
    "iso:country":"ES",
    "sg:address":"Gurmendi Kalea, 4",
    "sg:city":"Zarautz",
    "sg:orig_category":"Carnicer\u00cdas, Carnicer\u00cdas",
    "sg:phone":"+34 943 83 49 58",
    "sg:postcode":"20800",
    "sg:province":"Guip\u00f9zcoa",
    "wof:name":"Jose Benito Esnal Ancin Y Otra C.b.",
    "wof:placetype":"venue"
},
  "geometry": {"coordinates":[-2.1729400158,43.2824249268],"type":"Point"}
}