{
  "type": "Feature",
  "properties": {
    "addr:full":"Carrer de Riu Glorieta, S/n Torreforta Tarragona 43006",
    "addr:housenumber":"s",
    "addr:postcode":"43006",
    "addr:street":"Carrer De Riu Glorieta;/ N Torreforta",
    "iso:country":"ES",
    "sg:address":"Carrer de Riu Glorieta, S/n",
    "sg:city":"Torreforta",
    "sg:orig_category":"Productos Qu\u00cdmicos (fabricaci\u00d3n, Al Por Mayor)",
    "sg:phone":"+34 977 54 89 13",
    "sg:postcode":"43006",
    "sg:province":"Tarragona",
    "wof:name":"Laboratoris Vidal S.l.",
    "wof:placetype":"venue"
},
  "geometry": {"coordinates":[1.215520978,41.1161956787],"type":"Point"}
}