{
  "type": "Feature",
  "properties": {
    "iso:country":"ES",
    "sg:address":"Calle de General Franco, 1",
    "sg:city":"Cristianos",
    "sg:orig_category":"Quincaller\u00cda (al Por Menor)",
    "sg:phone":"+34 922 79 07 80",
    "sg:postcode":"38650",
    "sg:province":"Santa Cruz De Tenerife",
    "wof:name":"Cris Abora S.a.",
    "wof:placetype":"venue"
},
  "geometry": {"coordinates":[-16.7150497437,28.0529670715],"type":"Point"}
}