{
  "type": "Feature",
  "properties": {
    "iso:country":"ES",
    "sg:address":"Calle de Rua Mayor, 44",
    "sg:city":"Salamanca",
    "sg:orig_category":"Art\u00cdculos De Regalo (al Por Menor)",
    "sg:phone":"+34 923 21 15 63",
    "sg:postcode":"37008",
    "sg:province":"Salamanca",
    "wof:name":"Hernandez Sanchez Jose",
    "wof:placetype":"venue"
},
  "geometry": {"coordinates":[-5.6661372185,40.9621810913],"type":"Point"}
}