{
  "type": "Feature",
  "properties": {
    "iso:country":"ES",
    "sg:address":"Calle de Leon, 7",
    "sg:city":"Getafe",
    "sg:orig_category":"Limpieza Industrial",
    "sg:phone":"+34 916 95 65 03",
    "sg:postcode":"28903",
    "sg:province":"Madrid",
    "sg:website":"www.lingesa.com",
    "wof:name":"Limpieza Getafe S. A.",
    "wof:placetype":"venue"
},
  "geometry": {"coordinates":[-3.7218434811,40.3101959229],"type":"Point"}
}