{
  "type": "Feature",
  "properties": {
    "addr:full":"Calle de Yebenes, 159 Madrid Madrid 28047",
    "addr:housenumber":"159",
    "addr:postcode":"28047",
    "addr:street":"Calle De Yebenes",
    "iso:country":"ES",
    "sg:address":"Calle de Yebenes, 159",
    "sg:city":"Madrid",
    "sg:orig_category":"Agencias Y Agentes Comerciales, Representantes",
    "sg:phone":"+34 917 17 25 85",
    "sg:postcode":"28047",
    "sg:province":"Madrid",
    "wof:name":"Hermanos Garcia Callejas C.b.",
    "wof:placetype":"venue"
},
  "geometry": {"coordinates":[-3.7515389919,40.392993927],"type":"Point"}
}