{
  "type": "Feature",
  "properties": {
    "addr:full":"Carrer de Ases, 7 Barcelona Barcelona 08003",
    "addr:housenumber":"7",
    "addr:postcode":"08003",
    "addr:street":"Carrer De Ases",
    "iso:country":"ES",
    "sg:address":"Carrer de Ases, 7",
    "sg:city":"Barcelona",
    "sg:orig_category":"Molduras, Junquillos, Listones Y Molduras Perforadas",
    "sg:phone":"+34 932 68 05 02",
    "sg:postcode":"08003",
    "sg:province":"Barcelona",
    "wof:name":"Guerrero Grifols Victor",
    "wof:placetype":"venue"
},
  "geometry": {"coordinates":[2.1827731133,41.3836936951],"type":"Point"}
}