{
  "type": "Feature",
  "properties": {
    "iso:country":"ES",
    "sg:address":"Calle de Arzobispo Morcillo, 48",
    "sg:city":"Madrid",
    "sg:orig_category":"Venta, Localizaci\u00d3n, Reparaci\u00d3n De Material E Instrumental M\u00c9dico",
    "sg:phone":"+34 913 14 07 79",
    "sg:postcode":"28029",
    "sg:province":"Madrid",
    "wof:name":"Medican S.l.",
    "wof:placetype":"venue"
},
  "geometry": {"coordinates":[-3.6969220638,40.4834403992],"type":"Point"}
}