{
  "type": "Feature",
  "properties": {
    "addr:full":"Calle de Juan Bautista De Toledo, 20 Madrid Madrid 28002",
    "addr:housenumber":"20",
    "addr:postcode":"madrid;28002",
    "addr:street":"Calle De Juan Bautista De Toledo",
    "iso:country":"ES",
    "sg:address":"Calle de Juan Bautista De Toledo, 20",
    "sg:city":"Madrid",
    "sg:orig_category":"Agencias Y Agentes Comerciales, Representantes",
    "sg:phone":"+34 915 10 05 11",
    "sg:postcode":"28002",
    "sg:province":"Madrid",
    "wof:name":"Sancho Palomo Angela",
    "wof:placetype":"venue"
},
  "geometry": {"coordinates":[-3.6728889942,40.4426651001],"type":"Point"}
}