{
  "type": "Feature",
  "properties": {
    "addr:full":"Calle de Capitan Claudio Vazquez, 44 Ceuta Ceuta 51002",
    "addr:housenumber":"44",
    "addr:postcode":"51002",
    "addr:street":"Calle De Capitan;Vazquez",
    "iso:country":"ES",
    "sg:address":"Calle de Capitan Claudio Vazquez, 44",
    "sg:city":"Ceuta",
    "sg:orig_category":"Alimentaci\u00d3n General (al Por Menor)",
    "sg:phone":"+34 956 50 23 94",
    "sg:postcode":"51002",
    "sg:province":"Ceuta",
    "wof:name":"Gonzalez Doblas Miguel",
    "wof:placetype":"venue"
},
  "geometry": {"coordinates":[-5.3431954384,35.8851356506],"type":"Point"}
}