{
  "type": "Feature",
  "properties": {
    "iso:country":"ES",
    "sg:address":"Rua Urzaiz, 182",
    "sg:city":"Vigo",
    "sg:orig_category":"Ropa Para Se\u00d1oras Y Caballeros (al Por Menor)",
    "sg:phone":"+34 986 27 75 19",
    "sg:postcode":"36205",
    "sg:province":"Pontevedra",
    "wof:name":"Nevereta Parda S.l.",
    "wof:placetype":"venue"
},
  "geometry": {"coordinates":[-8.7024364471,42.2308807373],"type":"Point"}
}