{
  "type": "Feature",
  "properties": {
    "addr:full":"Calle de Maruja Garcia Romero, S/n Madrid Madrid 28038",
    "addr:housenumber":"s / n",
    "addr:postcode":"28038",
    "addr:street":"Calle De Maruja Garcia Romero",
    "iso:country":"ES",
    "sg:address":"Calle de Maruja Garcia Romero, S/n",
    "sg:city":"Madrid",
    "sg:orig_category":"Promotores Constructores",
    "sg:phone":"+34 914 30 77 58",
    "sg:postcode":"28038",
    "sg:province":"Madrid",
    "sg:website":"www.grupo-sanjose.com",
    "wof:name":"Constructora Avalos S.a.",
    "wof:placetype":"venue"
},
  "geometry": {"coordinates":[-3.6558959484,40.4013366699],"type":"Point"}
}