{
  "type": "Feature",
  "properties": {
    "iso:country":"ES",
    "sg:address":"Mayor, S/n",
    "sg:city":"Quintanilla Onesimo",
    "sg:orig_category":"Metalurgia: Maquinaria Y Equipos",
    "sg:phone":"+34 983 68 00 53",
    "sg:postcode":"47350",
    "sg:province":"Valladolid",
    "wof:name":"Mendez Gomez Jose",
    "wof:placetype":"venue"
},
  "geometry": {"coordinates":[-4.3638358116,41.6267051697],"type":"Point"}
}