{
  "type": "Feature",
  "properties": {
    "addr:full":"Monte De Iba\u00f1eta, 7 Iru\u00f1a Navarra 31006",
    "addr:housenumber":"7",
    "addr:postcode":"31006",
    "addr:street":"Irun\u0303A Navarra",
    "iso:country":"ES",
    "sg:address":"Monte De Iba\u00f1eta, 7",
    "sg:city":"Iru\u00f1a",
    "sg:orig_category":"Mec\u00c1nico Del Autom\u00d3vil",
    "sg:phone":"+34 948 29 09 66",
    "sg:postcode":"31006",
    "sg:province":"Navarra",
    "wof:name":"Albisu Aizcorbe Ivan Jesus Y Hernandez Romero Gust",
    "wof:placetype":"venue"
},
  "geometry": {"coordinates":[-1.6340786219,42.8037796021],"type":"Point"}
}