{
  "type": "Feature",
  "properties": {
    "addr:full":"Calle de Doctor Nieto, 40 Alacant Alicante 03013",
    "addr:housenumber":"40",
    "addr:postcode":"03013",
    "addr:street":"Calle De Doctor Nieto",
    "iso:country":"ES",
    "sg:address":"Calle de Doctor Nieto, 40",
    "sg:city":"Alacant",
    "sg:orig_category":"Mercer\u00cda, Lencer\u00cda (al Por Menor)",
    "sg:phone":"+34 965 20 02 80",
    "sg:postcode":"03013",
    "sg:province":"Alicante",
    "wof:name":"Genma Cristalin S.l.",
    "wof:placetype":"venue"
},
  "geometry": {"coordinates":[-0.4778836966,38.3570747375],"type":"Point"}
}