{
  "type": "Feature",
  "properties": {
    "addr:full":"Camino Del Martinete, 10 Fuente Vaqueros Granada 18340",
    "addr:housenumber":"10",
    "addr:postcode":"18340",
    "addr:street":"Camino Del Martinete",
    "iso:country":"ES",
    "sg:address":"Camino Del Martinete, 10",
    "sg:city":"Fuente Vaqueros",
    "sg:orig_category":"Doctores En Medicina",
    "sg:phone":"+34 958 51 60 06",
    "sg:postcode":"18340",
    "sg:province":"Granada",
    "wof:name":"Hernandez Roldan Jose Luis",
    "wof:placetype":"venue"
},
  "geometry": {"coordinates":[-3.7846159935,37.2165145874],"type":"Point"}
}