{
  "type": "Feature",
  "properties": {
    "addr:full":"Urb Nieves (las), S/n Finca Espa\u00e7a Santa Cruz De Tenerife 38320",
    "addr:postcode":"38320",
    "addr:street":"Urb Nieves Las S / N Finca",
    "iso:country":"ES",
    "sg:address":"Urb Nieves (las), S/n",
    "sg:city":"Finca Espa\u00e7a",
    "sg:classifiers":[
        {
            "category":"Communications",
            "type":"Services"
        }
    ],
    "sg:phone":"+34 922 64 79 53",
    "sg:postcode":"38320",
    "sg:province":"Santa Cruz De Tenerife",
    "sg:tags":[
        "televisiones",
        "y",
        "radio"
    ],
    "wof:name":"Radio Nacional De Espa\u00f1a S.a.",
    "wof:placetype":"venue"
},
  "geometry": {"coordinates":[-16.2880134583,28.468454361],"type":"Point"}
}