{
  "type": "Feature",
  "properties": {
    "iso:country":"ES",
    "sg:address":"Carrer de Vendrell (de), 12",
    "sg:city":"Salou",
    "sg:orig_category":"Residencias De Turismo, Residencias Hoteleras",
    "sg:phone":"+34 977 35 24 01",
    "sg:postcode":"43840",
    "sg:province":"Tarragona",
    "wof:name":"Iberbrisa Internacional S.l.",
    "wof:placetype":"venue"
},
  "geometry": {"coordinates":[1.152870059,41.0687408447],"type":"Point"}
}