{
  "type": "Feature",
  "properties": {
    "addr:full":"Calle de Leonardo Da Vinci, 9 Mi\u00e7ano Menor \u00c1lava 01510",
    "addr:housenumber":"9",
    "addr:postcode":"01510",
    "addr:street":"Calle De Leonardo Da Vinci",
    "iso:country":"ES",
    "sg:address":"Calle de Leonardo Da Vinci, 9",
    "sg:city":"Mi\u00e7ano Menor",
    "sg:orig_category":"M\u00c9dicos: Medicina General",
    "sg:phone":"+34 945 29 69 42",
    "sg:postcode":"01510",
    "sg:province":"\u00c1lava",
    "sg:website":"www.cardgirus.com",
    "wof:name":"Cardgirus I.d.i. S.l.",
    "wof:placetype":"venue"
},
  "geometry": {"coordinates":[-2.6422491074,42.9813613892],"type":"Point"}
}