{
  "type": "Feature",
  "properties": {
    "addr:full":"Carrer de Tres Rieres, 24 Esparreguera Barcelona 08292",
    "addr:housenumber":"24",
    "addr:postcode":"08292",
    "addr:street":"Carrer De Tres Rieres",
    "iso:country":"ES",
    "sg:address":"Carrer de Tres Rieres, 24",
    "sg:city":"Esparreguera",
    "sg:orig_category":"V\u00c1lvulas",
    "sg:phone":"+34 937 77 84 73",
    "sg:postcode":"08292",
    "sg:province":"Barcelona",
    "wof:name":"Pictor Valves S.l.",
    "wof:placetype":"venue"
},
  "geometry": {"coordinates":[1.8769949675,41.526714325],"type":"Point"}
}