{
  "type": "Feature",
  "properties": {
    "addr:full":"Carrer de Riereta, 32 Barcelona Barcelona 08001",
    "addr:housenumber":"32",
    "addr:postcode":"08001",
    "addr:street":"Carrer De Riereta",
    "iso:country":"ES",
    "sg:address":"Carrer de Riereta, 32",
    "sg:city":"Barcelona",
    "sg:orig_category":"Multimedia: Servicios En L\u00cdnea, Acceso En L\u00cdnea, Cd",
    "sg:phone":"+34 934 43 23 09",
    "sg:postcode":"08001",
    "sg:province":"Barcelona",
    "wof:name":"Straddle 3 Constructors S.l.",
    "wof:placetype":"venue"
},
  "geometry": {"coordinates":[2.1694779396,41.3771896362],"type":"Point"}
}