{
  "type": "Feature",
  "properties": {
    "iso:country":"ES",
    "sg:address":"Plaz Tres Carabelas, 2",
    "sg:city":"Cadiz",
    "sg:orig_category":"Promotores Constructores",
    "sg:phone":"+34 956 22 63 77",
    "sg:postcode":"11004",
    "sg:province":"C\u00e1diz",
    "wof:name":"Dragados S.a.",
    "wof:placetype":"venue"
},
  "geometry": {"coordinates":[-6.2905540466,36.5367965698],"type":"Point"}
}