{
  "type": "Feature",
  "properties": {
    "addr:full":"Barr Tolda De Castela, S/n Lugo Lugo 27002",
    "addr:housenumber":"s / n",
    "addr:postcode":"27002",
    "iso:country":"ES",
    "sg:address":"Barr Tolda De Castela, S/n",
    "sg:city":"Lugo",
    "sg:orig_category":"L\u00c1ser (fabricaci\u00d3n Y Aplicaciones)",
    "sg:phone":"+34 982 30 59 03",
    "sg:postcode":"27002",
    "sg:province":"Lugo",
    "wof:name":"Talleres Doval S. L.",
    "wof:placetype":"venue"
},
  "geometry": {"coordinates":[-7.5469670296,43.0077133179],"type":"Point"}
}