{
  "type": "Feature",
  "properties": {
    "iso:country":"ES",
    "sg:address":"Calle de Mayor, 3",
    "sg:city":"Huete",
    "sg:orig_category":"Notarios",
    "sg:phone":"+34 969 37 10 70",
    "sg:postcode":"16500",
    "sg:province":"Cuenca",
    "wof:name":"Perez Hereza Mercedes",
    "wof:placetype":"venue"
},
  "geometry": {"coordinates":[-2.6911180019,40.1445655823],"type":"Point"}
}