{
  "type": "Feature",
  "properties": {
    "addr:full":"Calle de Hermanos Alvarez Quintero, 2 Madrid Madrid 28004",
    "addr:housenumber":"2",
    "addr:postcode":"28004",
    "addr:street":"Calle De Hermanos Alvarez Quintero",
    "iso:country":"ES",
    "sg:address":"Calle de Hermanos Alvarez Quintero, 2",
    "sg:city":"Madrid",
    "sg:orig_category":"Arquitectos",
    "sg:phone":"+34 914 45 38 02",
    "sg:postcode":"28004",
    "sg:province":"Madrid",
    "wof:name":"Ramirez Montesinos Herran Francisco",
    "wof:placetype":"venue"
},
  "geometry": {"coordinates":[-3.697384119,40.4278068542],"type":"Point"}
}