{
  "type": "Feature",
  "properties": {
    "addr:full":"Trva Calle de Mayor, 2 Doneztebe Navarra 31740",
    "addr:housenumber":"2",
    "addr:postcode":"31740",
    "addr:street":"Trva Calle De Mayor;Navarra",
    "iso:country":"ES",
    "sg:address":"Trva Calle de Mayor, 2",
    "sg:city":"Doneztebe",
    "sg:orig_category":"Ingenier\u00cda, Centros De Estudios (diversos)",
    "sg:phone":"+34 948 45 17 18",
    "sg:postcode":"31740",
    "sg:province":"Navarra",
    "wof:name":"Obras Y Preparacion De Terrenos S.l.",
    "wof:placetype":"venue"
},
  "geometry": {"coordinates":[-1.6688699722,43.1323471069],"type":"Point"}
}