{
  "type": "Feature",
  "properties": {
    "iso:country":"ES",
    "sg:address":"Avda Extremadura, 11",
    "sg:city":"Talavera Real",
    "sg:orig_category":"Agricultores, Agricultores",
    "sg:phone":"+34 924 44 06 07",
    "sg:postcode":"06140",
    "sg:province":"Badajoz",
    "wof:name":"Tomates Extreme\u00f1os S.coop.",
    "wof:placetype":"venue"
},
  "geometry": {"coordinates":[-6.7713742256,38.8796882629],"type":"Point"}
}