{
  "type": "Feature",
  "properties": {
    "iso:country":"ES",
    "sg:address":"Calle de Tintor, 34",
    "sg:city":"Puente-genil",
    "sg:orig_category":"Panader\u00cdas, Panader\u00cdas",
    "sg:phone":"+34 957 60 55 09",
    "sg:postcode":"14500",
    "sg:province":"C\u00f3rdoba",
    "wof:name":"Lopez Prieto Jesus",
    "wof:placetype":"venue"
},
  "geometry": {"coordinates":[-4.7738080025,37.387878418],"type":"Point"}
}