{
  "type": "Feature",
  "properties": {
    "addr:full":"Av Angel Sallent, 58 Terrassa Barcelona 08224",
    "addr:housenumber":"58",
    "addr:postcode":"08224",
    "addr:street":"Av Angel Sallent",
    "iso:country":"ES",
    "sg:address":"Av Angel Sallent, 58",
    "sg:city":"Terrassa",
    "sg:orig_category":"Bazares, Art\u00cdculos De Limpieza Y De Cocina (al Por Menor)",
    "sg:phone":"+34 937 88 81 69",
    "sg:postcode":"08224",
    "sg:province":"Barcelona",
    "wof:name":"Bazar Fu Gui Chao Shi S.c.p.",
    "wof:placetype":"venue"
},
  "geometry": {"coordinates":[2.0004599094,41.5572624207],"type":"Point"}
}