{
  "type": "Feature",
  "properties": {
    "iso:country":"ES",
    "sg:address":"Pl Pau Casals, 3",
    "sg:city":"Segur Calafell",
    "sg:orig_category":"Laboratorios Y Cl\u00cdnicas Veterinarias",
    "sg:phone":"+34 977 67 29 69",
    "sg:postcode":"43882",
    "sg:province":"Tarragona",
    "wof:name":"Tot Viu S.l.",
    "wof:placetype":"venue"
},
  "geometry": {"coordinates":[1.6050579548,41.195476532],"type":"Point"}
}