{
  "type": "Feature",
  "properties": {
    "iso:country":"ES",
    "sg:address":"Avda Camp De Morvedre, 113",
    "sg:city":"Puerto",
    "sg:orig_category":"Ingeniero",
    "sg:phone":"+34 962 67 05 56",
    "sg:postcode":"46520",
    "sg:province":"Valencia",
    "wof:name":"Galvez Jimenez Rafael",
    "wof:placetype":"venue"
},
  "geometry": {"coordinates":[-0.2232829928,39.6631698608],"type":"Point"}
}