{
  "type": "Feature",
  "properties": {
    "addr:full":"Calle de Bronce (del), S/n Collado Mediano Madrid 28450",
    "addr:housenumber":"/ n",
    "addr:postcode":"28450",
    "addr:street":"Calle De Bronce Del S",
    "iso:country":"ES",
    "sg:address":"Calle de Bronce (del), S/n",
    "sg:city":"Collado Mediano",
    "sg:orig_category":"Distribuci\u00d3n De Petr\u00d3leo Y Derivados",
    "sg:phone":"+34 918 55 70 75",
    "sg:postcode":"28450",
    "sg:province":"Madrid",
    "wof:name":"Gasoleos Galapagar S.l.",
    "wof:placetype":"venue"
},
  "geometry": {"coordinates":[-4.0185875893,40.6877479553],"type":"Point"}
}