{
  "type": "Feature",
  "properties": {
    "iso:country":"ES",
    "sg:address":"Calle de Portillo San Antonio, 2",
    "sg:city":"San Miguel",
    "sg:orig_category":"M\u00c9dicos: Gastroenterolog\u00cda Y Hepatolog\u00cda (aparato Digestivo)",
    "sg:phone":"+34 968 28 27 43",
    "sg:postcode":"30005",
    "sg:province":"Murcia",
    "wof:name":"Serrano Alarcon Francisco",
    "wof:placetype":"venue"
},
  "geometry": {"coordinates":[-1.1325229406,37.9880828857],"type":"Point"}
}