{
  "type": "Feature",
  "properties": {
    "iso:country":"ES",
    "sg:address":"Calle de Andalucia, 56",
    "sg:city":"Bollullos Par Condado",
    "sg:orig_category":"Negocio De Materiales De Construcci\u00d3n",
    "sg:phone":"+34 959 41 22 21",
    "sg:postcode":"21710",
    "sg:province":"Huelva",
    "wof:name":"Gabriel Ramos E Hijos S.l.",
    "wof:placetype":"venue"
},
  "geometry": {"coordinates":[-6.5383410454,37.3447380066],"type":"Point"}
}