{
  "type": "Feature",
  "properties": {
    "iso:country":"ES",
    "sg:address":"Calle de Mayor, 148",
    "sg:city":"Torreaguera",
    "sg:orig_category":"Institutos De Belleza",
    "sg:phone":"+34 968 82 38 88",
    "sg:postcode":"30579",
    "sg:province":"Murcia",
    "wof:name":"Carrillo Sanchez Manuela",
    "wof:placetype":"venue"
},
  "geometry": {"coordinates":[-1.0508069992,37.9833488464],"type":"Point"}
}