{
  "type": "Feature",
  "properties": {
    "addr:full":"Calle de Castielfabib, 9 Valencia Valencia 46015",
    "addr:housenumber":"9",
    "addr:postcode":"46015",
    "addr:street":"Calle De Castielfabib",
    "iso:country":"ES",
    "sg:address":"Calle de Castielfabib, 9",
    "sg:city":"Valencia",
    "sg:orig_category":"Reposter\u00cdas",
    "sg:phone":"+34 963 40 61 32",
    "sg:postcode":"46015",
    "sg:province":"Valencia",
    "wof:name":"Soriano Genoves Ricardo",
    "wof:placetype":"venue"
},
  "geometry": {"coordinates":[-0.3956842124,39.4782333374],"type":"Point"}
}