{
  "type": "Feature",
  "properties": {
    "addr:full":"Ctra Palmar, 575 Palmar  O Lugar De Don Juan Murcia 30120",
    "addr:housenumber":"575",
    "addr:postcode":"30120",
    "addr:street":"Ctra Palmar;Lugar",
    "iso:country":"ES",
    "sg:address":"Ctra Palmar, 575",
    "sg:city":"Palmar  O Lugar De Don Juan",
    "sg:orig_category":"Deportes N\u00c1uticos, Acu\u00c1ticos Y Subacu\u00c1ticos: Art\u00cdculos Y Equipo (al Por Menor)",
    "sg:phone":"+34 968 88 43 55",
    "sg:postcode":"30120",
    "sg:province":"Murcia",
    "wof:name":"Fernandez Gomariz Jose Antonio",
    "wof:placetype":"venue"
},
  "geometry": {"coordinates":[-1.1302490234,37.9829597473],"type":"Point"}
}