{
  "type": "Feature",
  "properties": {
    "addr:full":"Calle de Pilar (el), 10 Santa Cruz De Tenerife Santa Cruz De Tenerife 38002",
    "addr:housenumber":"10",
    "addr:postcode":"38002",
    "addr:street":"Calle De Pilar El",
    "iso:country":"ES",
    "sg:address":"Calle de Pilar (el), 10",
    "sg:city":"Santa Cruz De Tenerife",
    "sg:orig_category":"\u00d3ptica: Instrumentos (fabricaci\u00d3n)",
    "sg:phone":"+34 922 28 77 58",
    "sg:postcode":"38002",
    "sg:province":"Santa Cruz De Tenerife",
    "wof:name":"Opticas Europeas S.l.",
    "wof:placetype":"venue"
},
  "geometry": {"coordinates":[-16.2514858246,28.4690341949],"type":"Point"}
}