{
  "type": "Feature",
  "properties": {
    "iso:country":"ES",
    "sg:address":"Avda Castelao, 12",
    "sg:city":"Cedeira",
    "sg:orig_category":"Restaurantes",
    "sg:phone":"+34 981 48 03 92",
    "sg:postcode":"15350",
    "sg:province":"La Coru\u00f1a",
    "wof:name":"Lourido Rodriguez Luis",
    "wof:placetype":"venue"
},
  "geometry": {"coordinates":[-8.0528659821,43.6600418091],"type":"Point"}
}