{
  "type": "Feature",
  "properties": {
    "addr:full":"Av Vidal I Barraquer, 17 Cambrils Tarragona 43850",
    "addr:housenumber":"17",
    "addr:postcode":"43850",
    "addr:street":"Av Vidal I Barraquer",
    "iso:country":"ES",
    "sg:address":"Av Vidal I Barraquer, 17",
    "sg:city":"Cambrils",
    "sg:orig_category":"Molduras, Junquillos, Listones Y Molduras Perforadas",
    "sg:phone":"+34 977 36 88 23",
    "sg:postcode":"43850",
    "sg:province":"Tarragona",
    "wof:name":"Eurotel Sur S.l.",
    "wof:placetype":"venue"
},
  "geometry": {"coordinates":[1.0525039434,41.070438385],"type":"Point"}
}