{
  "type": "Feature",
  "properties": {
    "iso:country":"ES",
    "sg:address":"Calle de Basoa, 4",
    "sg:city":"Vitoria-gasteiz",
    "sg:orig_category":"Estancos",
    "sg:phone":"+34 945 21 30 70",
    "sg:postcode":"01012",
    "sg:province":"\u00c1lava",
    "wof:name":"Vega Pardo Laura Maria",
    "wof:placetype":"venue"
},
  "geometry": {"coordinates":[-2.6770160198,42.8548583984],"type":"Point"}
}