{
  "type": "Feature",
  "properties": {
    "addr:full":"Calle de Duque De Sevilla, 5 Madrid Madrid 28002",
    "addr:housenumber":"5",
    "addr:postcode":"28002",
    "addr:street":"Calle De Duque De Sevilla",
    "iso:country":"ES",
    "sg:address":"Calle de Duque De Sevilla, 5",
    "sg:city":"Madrid",
    "sg:orig_category":"Institutos De Belleza",
    "sg:phone":"+34 915 62 75 12",
    "sg:postcode":"28002",
    "sg:province":"Madrid",
    "wof:name":"Gonzalez Castilla Hipolito",
    "wof:placetype":"venue"
},
  "geometry": {"coordinates":[-3.6799240112,40.4422492981],"type":"Point"}
}