{
  "type": "Feature",
  "properties": {
    "addr:full":"Rua Castelao, S/n Grove Pontevedra 36980",
    "addr:housenumber":"s",
    "addr:postcode":"36980",
    "addr:street":"Rua Castelao;/ N Grove",
    "iso:country":"ES",
    "sg:address":"Rua Castelao, S/n",
    "sg:city":"Grove",
    "sg:orig_category":"Alimentaci\u00d3n General (al Por Menor)",
    "sg:phone":"+34 986 73 00 24",
    "sg:postcode":"36980",
    "sg:province":"Pontevedra",
    "wof:name":"Lucio Prol Maria Jose",
    "wof:placetype":"venue"
},
  "geometry": {"coordinates":[-8.8574838638,42.4878883362],"type":"Point"}
}