{
  "type": "Feature",
  "properties": {
    "iso:country":"ES",
    "sg:address":"Plaz San Francisco De Asis, 2",
    "sg:city":"Alcala Henares",
    "sg:orig_category":"Molduras, Junquillos, Listones Y Molduras Perforadas",
    "sg:phone":"+34 918 81 43 55",
    "sg:postcode":"28802",
    "sg:province":"Madrid",
    "wof:name":"Bravo Exposito Luisa",
    "wof:placetype":"venue"
},
  "geometry": {"coordinates":[-3.3771290779,40.4765090942],"type":"Point"}
}