{
  "type": "Feature",
  "properties": {
    "iso:country":"ES",
    "sg:address":"Carrer de Caterina Albert, 4",
    "sg:city":"Hospitalet Llobregat",
    "sg:orig_category":"Asociaciones Y Clubs Deportivos",
    "sg:phone":"+34 933 35 50 09",
    "sg:postcode":"08907",
    "sg:province":"Barcelona",
    "wof:name":"Associacio Esportiva Campi",
    "wof:placetype":"venue"
},
  "geometry": {"coordinates":[2.1141939163,41.3585357666],"type":"Point"}
}