{
  "type": "Feature",
  "properties": {
    "addr:full":"Rua Illa De Arousa, 4 Boa Vista Pontevedra 36005",
    "addr:housenumber":"4",
    "addr:postcode":"36005",
    "addr:street":"Rua Illa De Arousa",
    "iso:country":"ES",
    "sg:address":"Rua Illa De Arousa, 4",
    "sg:city":"Boa Vista",
    "sg:orig_category":"Electrodom\u00c9sticos (al Por Menor)",
    "sg:phone":"+34 986 87 33 19",
    "sg:postcode":"36005",
    "sg:province":"Pontevedra",
    "wof:name":"Catergest",
    "wof:placetype":"venue"
},
  "geometry": {"coordinates":[-8.6331739426,42.4493751526],"type":"Point"}
}