{
  "type": "Feature",
  "properties": {
    "iso:country":"ES",
    "sg:address":"Av Costa Brava, 6",
    "sg:city":"Palafolls",
    "sg:orig_category":"Muebles, Minoristas",
    "sg:phone":"+34 937 65 22 58",
    "sg:postcode":"08389",
    "sg:province":"Barcelona",
    "sg:website":"www.praicor.com",
    "wof:name":"Praicor S.l.",
    "wof:placetype":"venue"
},
  "geometry": {"coordinates":[2.74979496,41.6681594849],"type":"Point"}
}