{
  "type": "Feature",
  "properties": {
    "addr:full":"Calle de Dureo, S/n Olombrada Segovia 40220",
    "addr:housenumber":"s",
    "addr:postcode":"40220",
    "addr:street":"Calle De Dureo;/ N Olombrada Segovia",
    "iso:country":"ES",
    "sg:address":"Calle de Dureo, S/n",
    "sg:city":"Olombrada",
    "sg:orig_category":"Mec\u00c1nico Del Autom\u00d3vil",
    "sg:phone":"+34 921 16 45 57",
    "sg:postcode":"40220",
    "sg:province":"Segovia",
    "wof:name":"Cabrero Sanz Luis",
    "wof:placetype":"venue"
},
  "geometry": {"coordinates":[-4.1606807709,41.4130363464],"type":"Point"}
}