{
  "type": "Feature",
  "properties": {
    "iso:country":"ES",
    "sg:address":"Calle de Pitagoras, 62",
    "sg:city":"Getafe",
    "sg:orig_category":"Promotores Constructores",
    "sg:phone":"+34 916 82 54 16",
    "sg:postcode":"28906",
    "sg:province":"Madrid",
    "wof:name":"Hernandez Paino Promociones S.l.",
    "wof:placetype":"venue"
},
  "geometry": {"coordinates":[-3.7050299644,40.2982025146],"type":"Point"}
}