{
  "type": "Feature",
  "properties": {
    "addr:full":"Calle de Reyes Catolicos, 2 Consuegra Toledo 45700",
    "addr:housenumber":"2",
    "addr:postcode":"45700",
    "addr:street":"Calle De Reyes Catolicos",
    "iso:country":"ES",
    "sg:address":"Calle de Reyes Catolicos, 2",
    "sg:city":"Consuegra",
    "sg:orig_category":"Centros De Educaci\u00d3n Especial",
    "sg:phone":"+34 925 48 06 12",
    "sg:postcode":"45700",
    "sg:province":"Toledo",
    "wof:name":"Centro Educacion Permanente De Adultos",
    "wof:placetype":"venue"
},
  "geometry": {"coordinates":[-3.6078350544,39.4623680115],"type":"Point"}
}