{
  "type": "Feature",
  "properties": {
    "addr:full":"Via Aurelia, 33 Sabadell Barcelona 08206",
    "addr:housenumber":"33",
    "addr:postcode":"08206",
    "addr:street":"Via Aurelia",
    "iso:country":"ES",
    "sg:address":"Via Aurelia, 33",
    "sg:city":"Sabadell",
    "sg:orig_category":"Ense\u00d1anza: Peluquer\u00cda Est\u00c9tica",
    "sg:phone":"+34 937 17 44 52",
    "sg:postcode":"08206",
    "sg:province":"Barcelona",
    "wof:name":"Canal Vidal Montserrat",
    "wof:placetype":"venue"
},
  "geometry": {"coordinates":[2.0947909355,41.5557746887],"type":"Point"}
}