{
  "type": "Feature",
  "properties": {
    "addr:full":"Calle de Manuel Llaneza, 46 Mieres Asturias 33600",
    "addr:housenumber":"46",
    "addr:postcode":"33600",
    "addr:street":"Calle De Manuel Llaneza",
    "iso:country":"ES",
    "sg:address":"Calle de Manuel Llaneza, 46",
    "sg:city":"Mieres",
    "sg:orig_category":"Electrodom\u00c9sticos (al Por Menor)",
    "sg:phone":"+34 985 46 11 45",
    "sg:postcode":"33600",
    "sg:province":"Asturias",
    "wof:name":"Milar Alfonso S.l.",
    "wof:placetype":"venue"
},
  "geometry": {"coordinates":[-5.7771940231,43.2505187988],"type":"Point"}
}