{
  "type": "Feature",
  "properties": {
    "addr:full":"Calle de Ebanisteria, 4 Madrid Madrid 28037",
    "addr:housenumber":"4",
    "addr:postcode":"28037",
    "addr:street":"Calle De Ebanisteria",
    "iso:country":"ES",
    "sg:address":"Calle de Ebanisteria, 4",
    "sg:city":"Madrid",
    "sg:orig_category":"Iglesia Cat\u00d3lica",
    "sg:phone":"+34 913 06 08 82",
    "sg:postcode":"28037",
    "sg:province":"Madrid",
    "wof:name":"Parroquia De San Joaquin",
    "wof:placetype":"venue"
},
  "geometry": {"coordinates":[-3.6222159863,40.4253845215],"type":"Point"}
}