{
  "type": "Feature",
  "properties": {
    "iso:country":"ES",
    "sg:address":"Calle de Pedro Romero, 3",
    "sg:city":"Palencia",
    "sg:orig_category":"Fabricaci\u00d3n, Instalaci\u00d3n De Armarios",
    "sg:phone":"+34 979 75 16 47",
    "sg:postcode":"34001",
    "sg:province":"Palencia",
    "sg:website":"www.master-oregon.com",
    "wof:name":"Cep Oregon S.l.",
    "wof:placetype":"venue"
},
  "geometry": {"coordinates":[-4.5344500542,42.0103912354],"type":"Point"}
}