{
  "type": "Feature",
  "properties": {
    "addr:full":"Rond Carralero, 2 Majadahonda Madrid 28220",
    "addr:postcode":"28220",
    "addr:street":"Carralero",
    "iso:country":"ES",
    "sg:address":"Rond Carralero, 2",
    "sg:city":"Majadahonda",
    "sg:orig_category":"Alquiler De Veh\u00cdculos: Turismos Y Utilitarios",
    "sg:phone":"+34 916 34 03 59",
    "sg:postcode":"28220",
    "sg:province":"Madrid",
    "wof:name":"Avis Alquile Un Coche S.a.",
    "wof:placetype":"venue"
},
  "geometry": {"coordinates":[-3.872781992,40.4582748413],"type":"Point"}
}