{
  "type": "Feature",
  "properties": {
    "addr:full":"Calle de Miraflores (de), 2 Alcobendas Madrid 28100",
    "addr:postcode":"28100",
    "addr:street":"Calle De Miraflores De 2",
    "iso:country":"ES",
    "sg:address":"Calle de Miraflores (de), 2",
    "sg:city":"Alcobendas",
    "sg:orig_category":"Lencer\u00cda Femenina, Corseter\u00cda, Trajes De Ba\u00d1o (al Por Menor)",
    "sg:phone":"+34 916 54 92 39",
    "sg:postcode":"28100",
    "sg:province":"Madrid",
    "wof:name":"Fernandez Novez Aurora",
    "wof:placetype":"venue"
},
  "geometry": {"coordinates":[-3.6375238895,40.5433883667],"type":"Point"}
}