{
  "type": "Feature",
  "properties": {
    "iso:country":"ES",
    "sg:address":"Carr Mare Nostrum, 2",
    "sg:city":"Perello",
    "sg:orig_category":"Complementos De Vestir (al Por Menor)",
    "sg:phone":"+34 961 77 21 06",
    "sg:postcode":"46420",
    "sg:province":"Valencia",
    "wof:name":"Darder Navarro Jose Vicente",
    "wof:placetype":"venue"
},
  "geometry": {"coordinates":[-0.2740719914,39.2769966125],"type":"Point"}
}