{
  "type": "Feature",
  "properties": {
    "addr:full":"Pl Ajuntament, 14 S. Boi Llobregat Barcelona 08830",
    "addr:housenumber":"14",
    "addr:postcode":"08830",
    "addr:street":"Pl Ajuntament",
    "iso:country":"ES",
    "sg:address":"Pl Ajuntament, 14",
    "sg:city":"S. Boi Llobregat",
    "sg:orig_category":"Deportes N\u00c1uticos, Acu\u00c1ticos Y Subacu\u00c1ticos: Art\u00cdculos Y Equipo (al Por Menor)",
    "sg:phone":"+34 936 52 33 02",
    "sg:postcode":"08830",
    "sg:province":"Barcelona",
    "wof:name":"Mil Ochenta S.c.p",
    "wof:placetype":"venue"
},
  "geometry": {"coordinates":[2.042910099,41.3470687866],"type":"Point"}
}