{
  "type": "Feature",
  "properties": {
    "addr:full":"Calle de Nicanor Pi\u00d1ole, 6 Arriondas Asturias 33540",
    "addr:housenumber":"6",
    "addr:postcode":"33540",
    "addr:street":"Calle De Nicanor Pin\u0303Ole",
    "iso:country":"ES",
    "sg:address":"Calle de Nicanor Pi\u00d1ole, 6",
    "sg:city":"Arriondas",
    "sg:orig_category":"Perfumer\u00cda (al Por Menor)",
    "sg:phone":"+34 985 84 07 05",
    "sg:postcode":"33540",
    "sg:province":"Asturias",
    "wof:name":"Perfumeria M.v",
    "wof:placetype":"venue"
},
  "geometry": {"coordinates":[-5.1852741241,43.3902168274],"type":"Point"}
}