{
  "type": "Feature",
  "properties": {
    "iso:country":"ES",
    "sg:address":"Carrer de Mare De Deu Del Coll, 110",
    "sg:city":"Barcelona",
    "sg:orig_category":"Inmobiliaria (agencias)",
    "sg:phone":"+34 932 84 77 94",
    "sg:postcode":"08023",
    "sg:province":"Barcelona",
    "wof:name":"Inmobiliaria Alrami S.a.",
    "wof:placetype":"venue"
},
  "geometry": {"coordinates":[2.14706707,41.4125289917],"type":"Point"}
}