{
  "type": "Feature",
  "properties": {
    "iso:country":"ES",
    "sg:address":"Rond General Mitre, 84",
    "sg:city":"Barcelona",
    "sg:orig_category":"Fabricaci\u00d3n De Telas Y Sedas",
    "sg:phone":"+34 932 02 25 74",
    "sg:postcode":"08021",
    "sg:province":"Barcelona",
    "wof:name":"Valls Rusi\u00f1ol Isidro",
    "wof:placetype":"venue"
},
  "geometry": {"coordinates":[2.1344399452,41.3994064331],"type":"Point"}
}