{
  "type": "Feature",
  "properties": {
    "addr:full":"Av Antoni Gaudi, 3 Mollet Valles Barcelona 08100",
    "addr:housenumber":"3",
    "addr:postcode":"08100",
    "addr:street":"Av Antoni Gaudi",
    "iso:country":"ES",
    "sg:address":"Av Antoni Gaudi, 3",
    "sg:city":"Mollet Valles",
    "sg:orig_category":"Fabricaci\u00d3n, Importaci\u00d3n De L\u00c1mparas Y Bombillas",
    "sg:phone":"+34 935 70 96 86",
    "sg:postcode":"08100",
    "sg:province":"Barcelona",
    "wof:name":"Da Mei Xing",
    "wof:placetype":"venue"
},
  "geometry": {"coordinates":[2.2173559666,41.5447998047],"type":"Point"}
}