{
  "type": "Feature",
  "properties": {
    "iso:country":"ES",
    "sg:address":"Calle de Albeniz, 1",
    "sg:city":"Pliego",
    "sg:orig_category":"Empresas De Carpinter\u00cda",
    "sg:phone":"+34 968 66 60 93",
    "sg:postcode":"30176",
    "sg:province":"Murcia",
    "wof:name":"Tecnicas De Aluminio Y Pvc C.b.",
    "wof:placetype":"venue"
},
  "geometry": {"coordinates":[-1.5084689856,37.992351532],"type":"Point"}
}