{
  "type": "Feature",
  "properties": {
    "addr:full":"Urb. Miramar, S/n Benalmadena-costa M\u00e1laga 29630",
    "addr:housenumber":"s",
    "addr:postcode":"29630",
    "addr:street":"/ N Benalmadena-Costa Ma\u0301Laga",
    "iso:country":"ES",
    "sg:address":"Urb. Miramar, S/n",
    "sg:city":"Benalmadena-costa",
    "sg:orig_category":"Cerrajer\u00cda, Ferrallista",
    "sg:phone":"+34 952 57 50 07",
    "sg:postcode":"29630",
    "sg:province":"M\u00e1laga",
    "wof:name":"Quintana Marquez Salvadora",
    "wof:placetype":"venue"
},
  "geometry": {"coordinates":[-4.5260858536,36.5976753235],"type":"Point"}
}