{
  "type": "Feature",
  "properties": {
    "addr:full":"Calle de Chile, 1 Valencia Valencia 46021",
    "addr:housenumber":"1",
    "addr:postcode":"46021",
    "addr:street":"Calle De Chile",
    "iso:country":"ES",
    "sg:address":"Calle de Chile, 1",
    "sg:city":"Valencia",
    "sg:orig_category":"Molduras, Junquillos, Listones Y Molduras Perforadas",
    "sg:phone":"+34 963 60 14 42",
    "sg:postcode":"46021",
    "sg:province":"Valencia",
    "wof:name":"Pascual Sebastia Concha",
    "wof:placetype":"venue"
},
  "geometry": {"coordinates":[-0.3579992056,39.4703369141],"type":"Point"}
}