{
  "type": "Feature",
  "properties": {
    "iso:country":"ES",
    "sg:address":"Calle de San Anton, 11",
    "sg:city":"Aranda Duero",
    "sg:orig_category":"Ebanister\u00cda",
    "sg:phone":"+34 947 50 30 58",
    "sg:postcode":"09400",
    "sg:province":"Burgos",
    "wof:name":"Martin Serrano Cirilo",
    "wof:placetype":"venue"
},
  "geometry": {"coordinates":[-3.6859829426,41.6722755432],"type":"Point"}
}