{
  "type": "Feature",
  "properties": {
    "iso:country":"ES",
    "sg:address":"Calle de Carpintero, 8",
    "sg:city":"Playa De Salinetas",
    "sg:orig_category":"Transporte En General",
    "sg:phone":"+34 928 22 87 01",
    "sg:postcode":"35214",
    "sg:province":"Las Palmas",
    "sg:website":"www.naturhouse.com",
    "wof:name":"Kiluva Diet S.l.",
    "wof:placetype":"venue"
},
  "geometry": {"coordinates":[-15.382566452,27.9773864746],"type":"Point"}
}