{
  "type": "Feature",
  "properties": {
    "iso:country":"ES",
    "sg:address":"Calle de San Pedro De Carde\u00d1a, 94",
    "sg:city":"Burgos",
    "sg:orig_category":"Mec\u00c1nico Del Autom\u00d3vil",
    "sg:phone":"+34 947 26 72 94",
    "sg:postcode":"09002",
    "sg:province":"Burgos",
    "wof:name":"Talleres Automotor S.t",
    "wof:placetype":"venue"
},
  "geometry": {"coordinates":[-3.6863660812,42.3397712708],"type":"Point"}
}