{
  "type": "Feature",
  "properties": {
    "iso:country":"ES",
    "sg:address":"Carr Granat, 1",
    "sg:city":"Escandinavia",
    "sg:orig_category":"Promotores Constructores",
    "sg:phone":"+34 965 88 75 06",
    "sg:postcode":"03580",
    "sg:province":"Alicante",
    "wof:name":"Cas Actual Madrid Guida,s.l.",
    "wof:placetype":"venue"
},
  "geometry": {"coordinates":[-0.1017019972,38.5834732056],"type":"Point"}
}