{
  "type": "Feature",
  "properties": {
    "addr:full":"Calle de Corbeta, 7 Calpe Alicante 03710",
    "addr:housenumber":"7",
    "addr:postcode":"03710",
    "addr:street":"Calle De Corbeta",
    "iso:country":"ES",
    "sg:address":"Calle de Corbeta, 7",
    "sg:city":"Calpe",
    "sg:orig_category":"Abogados",
    "sg:phone":"+34 965 83 77 04",
    "sg:postcode":"03710",
    "sg:province":"Alicante",
    "wof:name":"Asesoria Pineda Torres S.l.",
    "wof:placetype":"venue"
},
  "geometry": {"coordinates":[0.0489421003,38.6441879272],"type":"Point"}
}