{
  "type": "Feature",
  "properties": {
    "iso:country":"ES",
    "sg:address":"Calle de Pelayo Sola, 23",
    "sg:city":"S. Adrian",
    "sg:orig_category":"Sales (al Por Mayor)",
    "sg:phone":"+34 948 67 02 31",
    "sg:postcode":"31570",
    "sg:province":"Navarra",
    "wof:name":"Conservas Salcedo S.l.",
    "wof:placetype":"venue"
},
  "geometry": {"coordinates":[-1.9344129562,42.336391449],"type":"Point"}
}