{
  "type": "Feature",
  "properties": {
    "iso:country":"ES",
    "sg:address":"Carr Moll De Llevant, 325",
    "sg:city":"Mao",
    "sg:orig_category":"Alimentaci\u00d3n General (al Por Menor)",
    "sg:phone":"+34 971 36 12 41",
    "sg:postcode":"07703",
    "sg:province":"Islas Baleares",
    "wof:name":"Alia\u00d1o Garriga Catalina",
    "wof:placetype":"venue"
},
  "geometry": {"coordinates":[4.274998188,39.8870353699],"type":"Point"}
}