{
  "type": "Feature",
  "properties": {
    "addr:full":"Av Verge De Montserrat, 50 Barbera Valles Barcelona 08210",
    "addr:housenumber":"50",
    "addr:postcode":"08210",
    "addr:street":"Av Verge De Montserrat",
    "iso:country":"ES",
    "sg:address":"Av Verge De Montserrat, 50",
    "sg:city":"Barbera Valles",
    "sg:orig_category":"Asesor\u00cda Sobre Comunicaci\u00d3n De Empresas",
    "sg:phone":"+34 937 18 42 73",
    "sg:postcode":"08210",
    "sg:province":"Barcelona",
    "wof:name":"H.l. Consulting S.c.c.l.",
    "wof:placetype":"venue"
},
  "geometry": {"coordinates":[2.1238570213,41.5139503479],"type":"Point"}
}