{
  "type": "Feature",
  "properties": {
    "addr:full":"Calle de Sabina, 49 Illescas Toledo 45200",
    "addr:housenumber":"49",
    "addr:postcode":"45200",
    "addr:street":"Calle De Sabina",
    "iso:country":"ES",
    "sg:address":"Calle de Sabina, 49",
    "sg:city":"Illescas",
    "sg:orig_category":"Empresarios",
    "sg:phone":"+34 925 51 42 45",
    "sg:postcode":"45200",
    "sg:province":"Toledo",
    "wof:name":"Multiservicios Garba S.l.",
    "wof:placetype":"venue"
},
  "geometry": {"coordinates":[-3.8358821869,40.1342430115],"type":"Point"}
}