{
  "type": "Feature",
  "properties": {
    "addr:full":"Calle de Constitucion, 24 Guadalajara Guadalajara 19003",
    "addr:postcode":"19003",
    "addr:street":"Calle De Constitucion 24",
    "iso:country":"ES",
    "sg:address":"Calle de Constitucion, 24",
    "sg:city":"Guadalajara",
    "sg:orig_category":"Ortopedia General",
    "sg:phone":"+34 949 21 56 81",
    "sg:postcode":"19003",
    "sg:province":"Guadalajara",
    "wof:name":"Fraguas Hervias Bernardino",
    "wof:placetype":"venue"
},
  "geometry": {"coordinates":[-3.1784687042,40.6300773621],"type":"Point"}
}