{
  "type": "Feature",
  "properties": {
    "iso:country":"ES",
    "sg:address":"Avda Marinas (las), 96",
    "sg:city":"Marinas",
    "sg:orig_category":"Transportes Ferroviarios",
    "sg:phone":"+34 950 33 47 66",
    "sg:postcode":"04740",
    "sg:province":"Almer\u00eda",
    "wof:name":"Roquetren C.b.",
    "wof:placetype":"venue"
},
  "geometry": {"coordinates":[-2.6339890957,36.7305793762],"type":"Point"}
}