{
  "type": "Feature",
  "properties": {
    "addr:full":"Calle de Nuestra Se\u00d1ora De Sonsoles, 41 Avila \u00c1vila 05002",
    "addr:housenumber":"41",
    "addr:postcode":"05002",
    "addr:street":"Calle De Nuestra Sen\u0303Ora De Sonsoles;A\u0301Vila",
    "iso:country":"ES",
    "sg:address":"Calle de Nuestra Se\u00d1ora De Sonsoles, 41",
    "sg:city":"Avila",
    "sg:orig_category":"Inmobiliaria (agencias)",
    "sg:phone":"+34 920 35 29 35",
    "sg:postcode":"05002",
    "sg:province":"\u00c1vila",
    "wof:name":"Domus Avila, S.l.",
    "wof:placetype":"venue"
},
  "geometry": {"coordinates":[-4.6971578598,40.6515655518],"type":"Point"}
}