{
  "type": "Feature",
  "properties": {
    "addr:full":"Rua Montiron, 99 Lugo Lugo 27002",
    "addr:housenumber":"99",
    "addr:postcode":"27002",
    "addr:street":"Rua Montiron",
    "iso:country":"ES",
    "sg:address":"Rua Montiron, 99",
    "sg:city":"Lugo",
    "sg:orig_category":"Impuestos, Tesoro P\u00dablico",
    "sg:phone":"+34 982 25 01 95",
    "sg:postcode":"27002",
    "sg:province":"Lugo",
    "wof:name":"Peritajes Galicia S.l.",
    "wof:placetype":"venue"
},
  "geometry": {"coordinates":[-7.5459160805,43.0018844604],"type":"Point"}
}