{
  "type": "Feature",
  "properties": {
    "iso:country":"ES",
    "sg:address":"Avda Fernando Blanco, 28",
    "sg:city":"Cee",
    "sg:orig_category":"Lanas (al Por Mayor)",
    "sg:phone":"+34 981 74 71 55",
    "sg:postcode":"15270",
    "sg:province":"A Coru\u00f1a",
    "wof:name":"Waldomar Caama\u00f1o Manuela Josefa",
    "wof:placetype":"venue"
},
  "geometry": {"coordinates":[-9.1875562668,42.9552841187],"type":"Point"}
}