{
  "type": "Feature",
  "properties": {
    "iso:country":"ES",
    "sg:address":"Trav Dalt, 48",
    "sg:city":"Barcelona",
    "sg:orig_category":"Papeler\u00cdas, Librer\u00cdas",
    "sg:phone":"+34 932 10 53 03",
    "sg:postcode":"08024",
    "sg:province":"Barcelona",
    "wof:name":"Gil Carre\u00f1o Maria Angeles",
    "wof:placetype":"venue"
},
  "geometry": {"coordinates":[2.1544449329,41.409160614],"type":"Point"}
}