{
  "type": "Feature",
  "properties": {
    "addr:full":"Plaz Marques Del Turia, 2 Marbella M\u00e1laga 29600",
    "addr:housenumber":"2",
    "addr:postcode":"29600",
    "addr:street":"Marques Del Turia;Ma\u0301Laga",
    "iso:country":"ES",
    "sg:address":"Plaz Marques Del Turia, 2",
    "sg:city":"Marbella",
    "sg:orig_category":"Promotores Constructores",
    "sg:phone":"+34 952 77 33 77",
    "sg:postcode":"29600",
    "sg:province":"M\u00e1laga",
    "wof:name":"Construcciones Hibar Mena Aplacado Y Solado S.l.",
    "wof:placetype":"venue"
},
  "geometry": {"coordinates":[-4.8767647743,36.5106735229],"type":"Point"}
}