{
  "type": "Feature",
  "properties": {
    "iso:country":"ES",
    "sg:address":"Pase Blanco De Cela, 6",
    "sg:city":"Astorga",
    "sg:orig_category":"Guarder\u00cdas",
    "sg:phone":"+34 987 61 87 99",
    "sg:postcode":"24700",
    "sg:province":"Le\u00f3n",
    "wof:name":"Jardin De Infancia La Muralla",
    "wof:placetype":"venue"
},
  "geometry": {"coordinates":[-6.0532841682,42.4577598572],"type":"Point"}
}