{
  "type": "Feature",
  "properties": {
    "addr:full":"Calle de Puldon-natero, 27 Cruz Santa Santa Cruz De Tenerife 38413",
    "addr:housenumber":"27",
    "addr:postcode":"38413",
    "addr:street":"Calle De Puldon-Natero;Santa",
    "iso:country":"ES",
    "sg:address":"Calle de Puldon-natero, 27",
    "sg:city":"Cruz Santa",
    "sg:orig_category":"Cl\u00cdnicas Dentales",
    "sg:phone":"+34 922 34 04 92",
    "sg:postcode":"38413",
    "sg:province":"Santa Cruz De Tenerife",
    "wof:name":"Concep Dent S.l.",
    "wof:placetype":"venue"
},
  "geometry": {"coordinates":[-16.5606460571,28.3570613861],"type":"Point"}
}