{
  "type": "Feature",
  "properties": {
    "addr:full":"Carrer de Rector Ubach, 53 Barcelona Barcelona 08021",
    "addr:housenumber":"53",
    "addr:postcode":"08021",
    "addr:street":"Carrer De Rector Ubach",
    "iso:country":"ES",
    "sg:address":"Carrer de Rector Ubach, 53",
    "sg:city":"Barcelona",
    "sg:orig_category":"Peluquer\u00cdas, Peluquer\u00cda Mixta",
    "sg:phone":"+34 932 01 24 67",
    "sg:postcode":"08021",
    "sg:province":"Barcelona",
    "wof:name":"Garcia Campoy Ana",
    "wof:placetype":"venue"
},
  "geometry": {"coordinates":[2.1419219971,41.396774292],"type":"Point"}
}