{
  "type": "Feature",
  "properties": {
    "addr:full":"Calle de Orense, 30 Madrid Madrid 28020",
    "addr:housenumber":"30",
    "addr:postcode":"madrid;28020",
    "addr:street":"Calle De Orense",
    "iso:country":"ES",
    "sg:address":"Calle de Orense, 30",
    "sg:city":"Madrid",
    "sg:orig_category":"Ingenier\u00cda, Centros De Estudios (diversos)",
    "sg:phone":"+34 915 56 49 28",
    "sg:postcode":"28020",
    "sg:province":"Madrid",
    "wof:name":"Synconsult S.l.",
    "wof:placetype":"venue"
},
  "geometry": {"coordinates":[-3.6947669983,40.4534187317],"type":"Point"}
}