{
  "type": "Feature",
  "properties": {
    "iso:country":"ES",
    "sg:address":"Carrer de Antoni Isern, 2",
    "sg:city":"Reus",
    "sg:orig_category":"Asesor\u00cda De Formaci\u00d3n Y Gesti\u00d3n De Personal",
    "sg:phone":"+34 977 77 52 53",
    "sg:postcode":"43205",
    "sg:province":"Tarragona",
    "wof:name":"Sanz I Martorell Assessors S.l.l.",
    "wof:placetype":"venue"
},
  "geometry": {"coordinates":[1.1004630327,41.145149231],"type":"Point"}
}