{
  "type": "Feature",
  "properties": {
    "addr:full":"Olarte Kalea, 12 Arrasate Guip\u00f9zcoa 20500",
    "addr:housenumber":"12",
    "addr:postcode":"20500",
    "addr:street":"Olarte Kalea;Guipu\u0300Zcoa",
    "iso:country":"ES",
    "sg:address":"Olarte Kalea, 12",
    "sg:city":"Arrasate",
    "sg:orig_category":"Partidos Pol\u00cdticos",
    "sg:phone":"+34 943 79 69 42",
    "sg:postcode":"20500",
    "sg:province":"Guip\u00f9zcoa",
    "wof:name":"Partido Socialista Obrero Espa\u00f1ol",
    "wof:placetype":"venue"
},
  "geometry": {"coordinates":[-2.4910531044,43.0661201477],"type":"Point"}
}