{
  "type": "Feature",
  "properties": {
    "addr:full":"Avda Algeciras, 40 Neda La Coru\u00f1a 15510",
    "addr:housenumber":"40",
    "addr:postcode":"15510",
    "addr:street":"Avda Algeciras;La Corun\u0303A",
    "iso:country":"ES",
    "sg:address":"Avda Algeciras, 40",
    "sg:city":"Neda",
    "sg:orig_category":"Alquiler De V\u00cddeo",
    "sg:phone":"+34 981 34 74 04",
    "sg:postcode":"15510",
    "sg:province":"La Coru\u00f1a",
    "wof:name":"A Fervenza Videoclub S.c",
    "wof:placetype":"venue"
},
  "geometry": {"coordinates":[-8.1578149796,43.5004615784],"type":"Point"}
}