{
  "type": "Feature",
  "properties": {
    "iso:country":"ES",
    "sg:address":"Calle de E(san Rafael), 28",
    "sg:city":"Hellin",
    "sg:orig_category":"Bebidas",
    "sg:phone":"+34 967 30 12 59",
    "sg:postcode":"02400",
    "sg:province":"Albacete",
    "wof:name":"Rodriguez Mas Juan Mariano",
    "wof:placetype":"venue"
},
  "geometry": {"coordinates":[-1.7025450468,38.5134124756],"type":"Point"}
}