{
  "type": "Feature",
  "properties": {
    "addr:full":"Calle de Sol Alta, 41 Alba Tormes Salamanca 37800",
    "addr:housenumber":"41",
    "addr:postcode":"37800",
    "addr:street":"Calle De Sol Alta",
    "iso:country":"ES",
    "sg:address":"Calle de Sol Alta, 41",
    "sg:city":"Alba Tormes",
    "sg:orig_category":"Contenedores (mercanc\u00cdas)",
    "sg:phone":"+34 923 30 00 88",
    "sg:postcode":"37800",
    "sg:province":"Salamanca",
    "wof:name":"Manuel Elices E Hijos S.l.",
    "wof:placetype":"venue"
},
  "geometry": {"coordinates":[-5.5114722252,40.8238334656],"type":"Point"}
}