{
  "type": "Feature",
  "properties": {
    "iso:country":"ES",
    "sg:address":"Calle de Comedias, 2",
    "sg:city":"Antequera",
    "sg:orig_category":"Bisuter\u00cda, Joyer\u00cda, Relojer\u00cda (al Por Menor)",
    "sg:phone":"+34 952 84 11 54",
    "sg:postcode":"29200",
    "sg:province":"M\u00e1laga",
    "wof:name":"Rodriguez Garcia Francisca",
    "wof:placetype":"venue"
},
  "geometry": {"coordinates":[-4.5612978935,37.0181388855],"type":"Point"}
}