{
  "type": "Feature",
  "properties": {
    "addr:full":"C/ Espronceda, 52 Elche Alicante 03204",
    "addr:housenumber":"52",
    "addr:postcode":"03204",
    "addr:street":"C / Espronceda",
    "iso:country":"ES",
    "sg:address":"C/ Espronceda, 52",
    "sg:city":"Elche",
    "sg:orig_category":"Lencer\u00cda Femenina, Corseter\u00cda, Trajes De Ba\u00d1o (al Por Menor)",
    "sg:phone":"+34 966 63 36 93",
    "sg:postcode":"03204",
    "sg:province":"Alicante",
    "wof:name":"Irel'la Dise\u00f1o S.l.",
    "wof:placetype":"venue"
},
  "geometry": {"coordinates":[-0.7063189745,38.2614402771],"type":"Point"}
}