{
  "type": "Feature",
  "properties": {
    "addr:full":"Poligono Industrial Uno, S/n Pu\u00e7ol Valencia 46530",
    "addr:housenumber":"s",
    "addr:postcode":"46530",
    "addr:street":"Uno;/ N",
    "iso:country":"ES",
    "sg:address":"Poligono Industrial Uno, S/n",
    "sg:city":"Pu\u00e7ol",
    "sg:orig_category":"Garajes De Veh\u00cdculos",
    "sg:phone":"+34 961 46 41 84",
    "sg:postcode":"46530",
    "sg:province":"Valencia",
    "wof:name":"Valenciana De Suministros Y Contratas Industriales S.l.",
    "wof:placetype":"venue"
},
  "geometry": {"coordinates":[-0.3008790016,39.6156044006],"type":"Point"}
}