{
  "type": "Feature",
  "properties": {
    "addr:full":"Avda Madrid, 48 Torrejon Ardoz Madrid 28850",
    "addr:housenumber":"48",
    "addr:postcode":"28850",
    "addr:street":"Avda Madrid",
    "iso:country":"ES",
    "sg:address":"Avda Madrid, 48",
    "sg:city":"Torrejon Ardoz",
    "sg:orig_category":"Electrodom\u00c9sticos (al Por Menor)",
    "sg:phone":"+34 916 76 84 47",
    "sg:postcode":"28850",
    "sg:province":"Madrid",
    "wof:name":"Selles Ramos Jesus",
    "wof:placetype":"venue"
},
  "geometry": {"coordinates":[-3.4651350975,40.4639129639],"type":"Point"}
}