{
  "type": "Feature",
  "properties": {
    "iso:country":"ES",
    "sg:address":"Carrer de Major De Sarria, 83",
    "sg:city":"Barcelona",
    "sg:orig_category":"Congelados: Productos Alimentarios (al Por Menor)",
    "sg:phone":"+34 932 05 32 06",
    "sg:postcode":"08017",
    "sg:province":"Barcelona",
    "wof:name":"Chics Prendes S.l",
    "wof:placetype":"venue"
},
  "geometry": {"coordinates":[2.1221170425,41.3989715576],"type":"Point"}
}