{
  "type": "Feature",
  "properties": {
    "addr:full":"Avda Constitucion (de La), 9 Pedro Mu\u00e7oz Ciudad Real 13620",
    "addr:postcode":"13620",
    "addr:street":"Avda Constitucion De La 9 Pedro Muc\u0327Oz",
    "iso:country":"ES",
    "sg:address":"Avda Constitucion (de La), 9",
    "sg:city":"Pedro Mu\u00e7oz",
    "sg:orig_category":"Armer\u00cdas",
    "sg:phone":"+34 926 58 70 85",
    "sg:postcode":"13620",
    "sg:province":"Ciudad Real",
    "wof:name":"Rodriguez Rodrigo Felipe",
    "wof:placetype":"venue"
},
  "geometry": {"coordinates":[-2.955878973,39.4055213928],"type":"Point"}
}