{
  "type": "Feature",
  "properties": {
    "addr:full":"Carrer de Can Valero, 54 Poligon Industrial De Can Valero Islas Baleares 07011",
    "addr:housenumber":"54",
    "addr:postcode":"07011",
    "addr:street":"Carrer De Can Valero;Islas",
    "iso:country":"ES",
    "sg:address":"Carrer de Can Valero, 54",
    "sg:city":"Poligon Industrial De Can Valero",
    "sg:orig_category":"Transportes Por Carretera: Lotes Completos, Mercanc\u00cdas Diversas",
    "sg:phone":"+34 971 20 90 11",
    "sg:postcode":"07011",
    "sg:province":"Islas Baleares",
    "wof:name":"Rullan Navarro Dos S.l.",
    "wof:placetype":"venue"
},
  "geometry": {"coordinates":[2.6205170155,39.5930747986],"type":"Point"}
}