{
  "type": "Feature",
  "properties": {
    "iso:country":"ES",
    "sg:address":"Av Generalitat (de La), 165",
    "sg:city":"Tortosa",
    "sg:orig_category":"Delegados, Agentes De Tr\u00c1nsito, Auxiliares De Transporte Internacional",
    "sg:phone":"+34 977 44 93 04",
    "sg:postcode":"43500",
    "sg:province":"Tarragona",
    "wof:name":"Tarracodis S.a.",
    "wof:placetype":"venue"
},
  "geometry": {"coordinates":[0.5205950141,40.8035392761],"type":"Point"}
}