{
  "type": "Feature",
  "properties": {
    "iso:country":"ES",
    "sg:address":"Calle de Especeria, 5",
    "sg:city":"Malaga",
    "sg:orig_category":"Sindicatos Y Colegios Profesionales",
    "sg:phone":"+34 952 22 41 65",
    "sg:postcode":"29005",
    "sg:province":"M\u00e1laga",
    "wof:name":"Centro Historico De Malaga",
    "wof:placetype":"venue"
},
  "geometry": {"coordinates":[-4.4229688644,36.7208251953],"type":"Point"}
}