{
  "type": "Feature",
  "properties": {
    "addr:full":"C/ Capita Alfons Vives, 95 Elche Alicante 03204",
    "addr:housenumber":"95",
    "addr:postcode":"03204",
    "addr:street":"C / Capita Alfons Vives",
    "iso:country":"ES",
    "sg:address":"C/ Capita Alfons Vives, 95",
    "sg:city":"Elche",
    "sg:orig_category":"Plomeros",
    "sg:phone":"+34 966 63 41 44",
    "sg:postcode":"03204",
    "sg:province":"Alicante",
    "wof:name":"Fontaneria La Cruz Azul Slu",
    "wof:placetype":"venue"
},
  "geometry": {"coordinates":[-0.7100459933,38.2608337402],"type":"Point"}
}