{
  "type": "Feature",
  "properties": {
    "addr:full":"Estacion Alamedilla Guadahortuna, S/n Alamedilla Granada 18520",
    "addr:housenumber":"s / n",
    "addr:postcode":"18520",
    "addr:street":"Guadahortuna",
    "iso:country":"ES",
    "sg:address":"Estacion Alamedilla Guadahortuna, S/n",
    "sg:city":"Alamedilla",
    "sg:orig_category":"Producci\u00d3n, Venta De Productos De Agricultura Biol\u00d3gica",
    "sg:phone":"+34 958 39 26 61",
    "sg:postcode":"18520",
    "sg:province":"Granada",
    "wof:name":"Hermanos Diaz Lopez C.b.",
    "wof:placetype":"venue"
},
  "geometry": {"coordinates":[-3.2447559834,37.5830001831],"type":"Point"}
}