{
  "type": "Feature",
  "properties": {
    "addr:full":"Calle de Galicia, 20 Sevilla Sevilla 41006",
    "addr:housenumber":"20",
    "addr:postcode":"41006",
    "addr:street":"Calle De Galicia",
    "iso:country":"ES",
    "sg:address":"Calle de Galicia, 20",
    "sg:city":"Sevilla",
    "sg:orig_category":"Artes Gr\u00c1ficas, Artes Pl\u00c1sticas (curso)",
    "sg:phone":"+34 954 66 02 59",
    "sg:postcode":"41006",
    "sg:province":"Sevilla",
    "wof:name":"Artes Graficas Ramos",
    "wof:placetype":"venue"
},
  "geometry": {"coordinates":[-5.9572424889,37.3697776794],"type":"Point"}
}