{
  "type": "Feature",
  "properties": {
    "iso:country":"ES",
    "sg:address":"Psaj Fernando De Rojas, 6",
    "sg:city":"Burgos",
    "sg:orig_category":"Carnicer\u00cdas, Carnicer\u00cdas",
    "sg:phone":"+34 947 48 77 88",
    "sg:postcode":"09007",
    "sg:province":"Burgos",
    "wof:name":"Franco Lorenzo Jose Luis",
    "wof:placetype":"venue"
},
  "geometry": {"coordinates":[-3.6659829617,42.3491363525],"type":"Point"}
}