{
  "type": "Feature",
  "properties": {
    "iso:country":"ES",
    "sg:address":"Calle de Guardia Civil, 9",
    "sg:city":"Madrid",
    "sg:orig_category":"Tintorer\u00cdas, Limpieza En Seco",
    "sg:phone":"+34 913 76 05 15",
    "sg:postcode":"28048",
    "sg:province":"Madrid",
    "wof:name":"Santos Lazaro Maria Emilia",
    "wof:placetype":"venue"
},
  "geometry": {"coordinates":[-3.7776529789,40.5192184448],"type":"Point"}
}