{
  "type": "Feature",
  "properties": {
    "iso:country":"ES",
    "sg:address":"Carr Almata, 2",
    "sg:city":"Balaguer",
    "sg:orig_category":"Empresas De Limpieza",
    "sg:phone":"+34 973 45 10 64",
    "sg:postcode":"25600",
    "sg:province":"Lleida",
    "wof:name":"Limpiezas La Nogera S.c.p.",
    "wof:placetype":"venue"
},
  "geometry": {"coordinates":[0.8084130287,41.7873497009],"type":"Point"}
}