{
  "type": "Feature",
  "properties": {
    "addr:full":"Ctra. Arevalo-madrigal, S/n Aldeaseca \u00c1vila 05214",
    "addr:housenumber":"s / n",
    "addr:postcode":"05214",
    "addr:street":"Ctra. Arevalo-Madrigal;Aldeaseca A\u0301Vila",
    "iso:country":"ES",
    "sg:address":"Ctra. Arevalo-madrigal, S/n",
    "sg:city":"Aldeaseca",
    "sg:orig_category":"Producci\u00d3n, Venta De Productos De Agricultura Biol\u00d3gica",
    "sg:phone":"+34 920 30 62 23",
    "sg:postcode":"05214",
    "sg:province":"\u00c1vila",
    "wof:name":"Sociedad Cooperativa Del Campo Labradores De La Mora\u00f1a",
    "wof:placetype":"venue"
},
  "geometry": {"coordinates":[-4.64108181,40.920715332],"type":"Point"}
}