{
  "type": "Feature",
  "properties": {
    "addr:full":"Carrer de Pep Ventura, 17 Santpedor Barcelona 08251",
    "addr:housenumber":"17",
    "addr:postcode":"08251",
    "addr:street":"Carrer De Pep Ventura",
    "iso:country":"ES",
    "sg:address":"Carrer de Pep Ventura, 17",
    "sg:city":"Santpedor",
    "sg:orig_category":"M\u00dasicos Int\u00c9rpretes",
    "sg:phone":"+34 938 32 04 54",
    "sg:postcode":"08251",
    "sg:province":"Barcelona",
    "wof:name":"Musifesta S.c.c.l",
    "wof:placetype":"venue"
},
  "geometry": {"coordinates":[1.8401110172,41.7877883911],"type":"Point"}
}