{
  "type": "Feature",
  "properties": {
    "iso:country":"ES",
    "sg:address":"Pase Pocillo, 2",
    "sg:city":"San Ildefonso O La Granja",
    "sg:orig_category":"Asesor\u00cda Sobre Comunicaci\u00d3n De Empresas",
    "sg:phone":"+34 921 47 13 26",
    "sg:postcode":"40100",
    "sg:province":"Segovia",
    "wof:name":"Escudero Marcos Pilar",
    "wof:placetype":"venue"
},
  "geometry": {"coordinates":[-4.005592823,40.9037399292],"type":"Point"}
}