{
  "type": "Feature",
  "properties": {
    "addr:full":"Calle de Bahia De Santander, 95 Madrid Madrid 28042",
    "addr:housenumber":"95",
    "addr:postcode":"madrid;28042",
    "addr:street":"Calle De Bahia De Santander",
    "iso:country":"ES",
    "sg:address":"Calle de Bahia De Santander, 95",
    "sg:city":"Madrid",
    "sg:orig_category":"Arquitectos",
    "sg:phone":"+34 917 47 03 12",
    "sg:postcode":"28042",
    "sg:province":"Madrid",
    "wof:name":"Miranda Naranjo Maria Elena",
    "wof:placetype":"venue"
},
  "geometry": {"coordinates":[-3.5929434299,40.4669380188],"type":"Point"}
}