{
  "type": "Feature",
  "properties": {
    "addr:full":"Av Alameda (l'), 67 Alcoi Alicante 03803",
    "addr:housenumber":"67",
    "addr:postcode":"03803",
    "addr:street":"Av Alameda L '",
    "iso:country":"ES",
    "sg:address":"Av Alameda (l'), 67",
    "sg:city":"Alcoi",
    "sg:orig_category":"Albergues",
    "sg:phone":"+34 965 52 10 95",
    "sg:postcode":"03803",
    "sg:province":"Alicante",
    "wof:name":"Dominguez Richart Maria Soledad",
    "wof:placetype":"venue"
},
  "geometry": {"coordinates":[-0.4759199917,38.7033996582],"type":"Point"}
}