{
  "type": "Feature",
  "properties": {
    "iso:country":"ES",
    "sg:address":"Avda Ciudad De Linares (de La), 6",
    "sg:city":"Ubeda",
    "sg:orig_category":"Electricidad: Material Y Suministros De Instalaci\u00d3n (fabricaci\u00d3n)",
    "sg:phone":"+34 953 75 56 77",
    "sg:postcode":"23400",
    "sg:province":"Ja\u00e9n",
    "wof:name":"Carmen Miras Martinez Y Otra S.c.p.",
    "wof:placetype":"venue"
},
  "geometry": {"coordinates":[-3.3772819042,38.0133018494],"type":"Point"}
}