{
  "type": "Feature",
  "properties": {
    "addr:full":"Calle de Arrabal Del Carmen, 37 Paredes Nava Palencia 34300",
    "addr:housenumber":"37",
    "addr:postcode":"34300",
    "addr:street":"Calle De Arrabal Del Carmen",
    "iso:country":"ES",
    "sg:address":"Calle de Arrabal Del Carmen, 37",
    "sg:city":"Paredes Nava",
    "sg:orig_category":"Electricidad: Instaladores",
    "sg:phone":"+34 979 83 01 44",
    "sg:postcode":"34300",
    "sg:province":"Palencia",
    "wof:name":"Herga Paredes De Nava S.l.",
    "wof:placetype":"venue"
},
  "geometry": {"coordinates":[-4.6959462166,42.1529083252],"type":"Point"}
}