{
  "type": "Feature",
  "properties": {
    "iso:country":"ES",
    "sg:address":"Plaz Lerida, 1",
    "sg:city":"Huesca",
    "sg:orig_category":"Empresas De Pintura Y Revestimientos",
    "sg:phone":"+34 974 21 81 19",
    "sg:postcode":"22004",
    "sg:province":"Huesca",
    "wof:name":"Cortijo Serrate Antonio Enrique",
    "wof:placetype":"venue"
},
  "geometry": {"coordinates":[-0.4166490138,42.1438980103],"type":"Point"}
}