{
  "type": "Feature",
  "properties": {
    "iso:country":"ES",
    "sg:address":"Ctra Agost, 68",
    "sg:city":"San Vicente Del Raspeig-sant Vicent Del Raspeig",
    "sg:orig_category":"Afilado",
    "sg:phone":"+34 965 67 14 11",
    "sg:postcode":"03690",
    "sg:province":"Alicante",
    "wof:name":"Perez Carbonell Jose Juan",
    "wof:placetype":"venue"
},
  "geometry": {"coordinates":[-0.5371990204,38.4021911621],"type":"Point"}
}