{
  "type": "Feature",
  "properties": {
    "addr:full":"Calle de Madrid, 65 Getafe Madrid 28901",
    "addr:housenumber":"65",
    "addr:postcode":"28901",
    "addr:street":"Calle De Madrid",
    "iso:country":"ES",
    "sg:address":"Calle de Madrid, 65",
    "sg:city":"Getafe",
    "sg:orig_category":"Edici\u00d3n De Diarios, Revistas, Boletines",
    "sg:phone":"+34 916 84 04 92",
    "sg:postcode":"28901",
    "sg:province":"Madrid",
    "wof:name":"Madrid Captsur S.l.",
    "wof:placetype":"venue"
},
  "geometry": {"coordinates":[-3.729542017,40.3081855774],"type":"Point"}
}