{
  "type": "Feature",
  "properties": {
    "iso:country":"ES",
    "sg:address":"Calle de Calvo Sotelo, 5",
    "sg:city":"Torres Cotillas",
    "sg:orig_category":"Carnicer\u00cdas, Carnicer\u00cdas",
    "sg:phone":"+34 968 62 62 15",
    "sg:postcode":"30565",
    "sg:province":"Murcia",
    "wof:name":"Fuentes Lopez Jose",
    "wof:placetype":"venue"
},
  "geometry": {"coordinates":[-1.2421241999,38.0208473206],"type":"Point"}
}