{
  "type": "Feature",
  "properties": {
    "iso:country":"ES",
    "sg:address":"Calle de Santander, 19",
    "sg:city":"Burgos",
    "sg:orig_category":"Ense\u00d1anza Variada",
    "sg:phone":"+34 947 20 53 59",
    "sg:postcode":"09004",
    "sg:province":"Burgos",
    "wof:name":"Lopez Del Valle Miguel Angel",
    "wof:placetype":"venue"
},
  "geometry": {"coordinates":[-3.6995100975,42.3424797058],"type":"Point"}
}