{
  "type": "Feature",
  "properties": {
    "addr:full":"Avda Cervantes (de), 3 Guardamar Segura Alicante 03140",
    "addr:housenumber":"3",
    "addr:postcode":"03140",
    "addr:street":"Avda Cervantes De",
    "iso:country":"ES",
    "sg:address":"Avda Cervantes (de), 3",
    "sg:city":"Guardamar Segura",
    "sg:orig_category":"Restaurantes",
    "sg:phone":"+34 966 72 68 54",
    "sg:postcode":"03140",
    "sg:province":"Alicante",
    "wof:name":"Restaurante La Tanda S.l.",
    "wof:placetype":"venue"
},
  "geometry": {"coordinates":[-0.648499012,38.0896072388],"type":"Point"}
}