{
  "type": "Feature",
  "properties": {
    "iso:country":"ES",
    "sg:address":"Ctra. Recas, S/n",
    "sg:city":"Lominchar",
    "sg:orig_category":"Construcciones Met\u00c1licas",
    "sg:phone":"+34 925 55 80 17",
    "sg:postcode":"45212",
    "sg:province":"Toledo",
    "sg:website":"www.cmmadrigal.com",
    "wof:name":"Grupo Miradia S.l.",
    "wof:placetype":"venue"
},
  "geometry": {"coordinates":[-3.964164257,40.0870132446],"type":"Point"}
}