{
  "type": "Feature",
  "properties": {
    "addr:full":"Calle de Fernando Poo, 50 Madrid Madrid 28045",
    "addr:housenumber":"50",
    "addr:postcode":"madrid;28045",
    "addr:street":"Calle De Fernando Poo",
    "iso:country":"ES",
    "sg:address":"Calle de Fernando Poo, 50",
    "sg:city":"Madrid",
    "sg:orig_category":"Inform\u00c1tica (estudios, Servicios, Asesor\u00cda, Formaci\u00d3n)",
    "sg:phone":"+34 914 74 02 93",
    "sg:postcode":"28045",
    "sg:province":"Madrid",
    "wof:name":"Martinez Martinez Juan Cristobal",
    "wof:placetype":"venue"
},
  "geometry": {"coordinates":[-3.7002210617,40.3955192566],"type":"Point"}
}