{
  "type": "Feature",
  "properties": {
    "addr:full":"Acacias De Guadalmar, 1 Malaga M\u00e1laga 29004",
    "addr:housenumber":"1",
    "addr:postcode":"29004",
    "addr:street":"Malaga Ma\u0301Laga",
    "iso:country":"ES",
    "sg:address":"Acacias De Guadalmar, 1",
    "sg:city":"Malaga",
    "sg:orig_category":"Inmobiliaria (agencias)",
    "sg:phone":"+34 952 23 28 02",
    "sg:postcode":"29004",
    "sg:province":"M\u00e1laga",
    "wof:name":"Lumassan Dogipp Jusulumi L&m S.l",
    "wof:placetype":"venue"
},
  "geometry": {"coordinates":[-4.4568572044,36.6642913818],"type":"Point"}
}