{
  "type": "Feature",
  "properties": {
    "addr:full":"Avda Duquesa De La Victoria, 1 Melilla Melilla 52004",
    "addr:housenumber":"1",
    "addr:postcode":"52004",
    "addr:street":"Avda Duquesa De La Victoria",
    "iso:country":"ES",
    "sg:address":"Avda Duquesa De La Victoria, 1",
    "sg:city":"Melilla",
    "sg:orig_category":"Sindicatos De Trabajadores",
    "sg:phone":"+34 952 69 61 44",
    "sg:postcode":"52004",
    "sg:province":"Melilla",
    "wof:name":"Confederacion De Sindicatos Independientes Y Sindical De Funcionarios",
    "wof:placetype":"venue"
},
  "geometry": {"coordinates":[-2.9428489208,35.2909240723],"type":"Point"}
}