{
  "type": "Feature",
  "properties": {
    "iso:country":"ES",
    "sg:address":"Avda Arcadio Pardi\u00d1as, 144",
    "sg:city":"Burela",
    "sg:orig_category":"Abogados",
    "sg:phone":"+34 982 57 50 44",
    "sg:postcode":"27880",
    "sg:province":"Lugo",
    "wof:name":"Mendez Pedrero Francisco Jose",
    "wof:placetype":"venue"
},
  "geometry": {"coordinates":[-7.3566088676,43.6538887024],"type":"Point"}
}