{
  "type": "Feature",
  "properties": {
    "iso:country":"ES",
    "sg:address":"Carr Ricard Vi\u00d1es, S/n",
    "sg:city":"S. Guim Freixenet",
    "sg:orig_category":"Centros De Educaci\u00d3n Especial",
    "sg:phone":"+34 973 55 62 86",
    "sg:postcode":"25270",
    "sg:province":"Lleida",
    "wof:name":"Ajuntament De Sant Guim De Freixenet",
    "wof:placetype":"venue"
},
  "geometry": {"coordinates":[1.4212981462,41.6572303772],"type":"Point"}
}