{
  "type": "Feature",
  "properties": {
    "addr:full":"Sarmiento Aguilar, 36 Mairena Alcor Sevilla 41510",
    "addr:housenumber":"36",
    "addr:postcode":"41510",
    "addr:street":"Sarmiento Aguilar",
    "iso:country":"ES",
    "sg:address":"Sarmiento Aguilar, 36",
    "sg:city":"Mairena Alcor",
    "sg:orig_category":"Peluquer\u00cdas",
    "sg:phone":"+34 955 94 32 10",
    "sg:postcode":"41510",
    "sg:province":"Sevilla",
    "wof:name":"Navarro Perez Manuel",
    "wof:placetype":"venue"
},
  "geometry": {"coordinates":[-5.7501440048,37.3717765808],"type":"Point"}
}