{
  "type": "Feature",
  "properties": {
    "addr:full":"Av Carles Iii (de), 3 Vilassar De Mar Barcelona 08340",
    "addr:postcode":"08340",
    "addr:street":"Av Carles Iii De",
    "iso:country":"ES",
    "sg:address":"Av Carles Iii (de), 3",
    "sg:city":"Vilassar De Mar",
    "sg:orig_category":"Material Y Suministros Para Dentistas, Cirujanos",
    "sg:phone":"+34 937 59 78 40",
    "sg:postcode":"08340",
    "sg:province":"Barcelona",
    "wof:name":"Broker Dental S.l.",
    "wof:placetype":"venue"
},
  "geometry": {"coordinates":[2.3870899677,41.5058403015],"type":"Point"}
}