{
  "type": "Feature",
  "properties": {
    "addr:full":"Pl Santa Anna, S/n Esparreguera Barcelona 08292",
    "addr:housenumber":"s",
    "addr:postcode":"08292",
    "addr:street":"Pl Santa Anna;/ N",
    "iso:country":"ES",
    "sg:address":"Pl Santa Anna, S/n",
    "sg:city":"Esparreguera",
    "sg:orig_category":"Carnicer\u00cdas, Carnicer\u00cdas",
    "sg:phone":"+34 937 77 37 55",
    "sg:postcode":"08292",
    "sg:province":"Barcelona",
    "wof:name":"Escriu Garcia Margarita",
    "wof:placetype":"venue"
},
  "geometry": {"coordinates":[1.8681600094,41.5377349854],"type":"Point"}
}