{
  "type": "Feature",
  "properties": {
    "addr:full":"C/ Maximilia Thous, 107 Elche Alicante 03204",
    "addr:housenumber":"107",
    "addr:postcode":"03204",
    "addr:street":"C / Maximilia Thous",
    "iso:country":"ES",
    "sg:address":"C/ Maximilia Thous, 107",
    "sg:city":"Elche",
    "sg:orig_category":"Ofim\u00c1tica: Material (fabricaci\u00d3n, Al Por Mayor)",
    "sg:phone":"+34 966 65 52 33",
    "sg:postcode":"03204",
    "sg:province":"Alicante",
    "wof:name":"Equipos De Oficina De Elche S.l.",
    "wof:placetype":"venue"
},
  "geometry": {"coordinates":[-0.705910027,38.2555961609],"type":"Point"}
}