{
  "type": "Feature",
  "properties": {
    "iso:country":"ES",
    "sg:address":"Calle de Pano Y Ruata, 13",
    "sg:city":"Zaragoza",
    "sg:orig_category":"Molduras, Junquillos, Listones Y Molduras Perforadas",
    "sg:phone":"+34 976 51 67 76",
    "sg:postcode":"50015",
    "sg:province":"Zaragoza",
    "wof:name":"Torres Paulos Maria Dolores",
    "wof:placetype":"venue"
},
  "geometry": {"coordinates":[-0.8746464849,41.6611595154],"type":"Point"}
}