{
  "type": "Feature",
  "properties": {
    "addr:full":"Avda Suel Urb Ajolin, S/n Fuengirola M\u00e1laga 29640",
    "addr:housenumber":"s / n",
    "addr:postcode":"29640",
    "addr:street":"Avda Suel Urb Ajolin;Ma\u0301Laga",
    "iso:country":"ES",
    "sg:address":"Avda Suel Urb Ajolin, S/n",
    "sg:city":"Fuengirola",
    "sg:orig_category":"Aparcamientos (infraestructuras, Accesorios)",
    "sg:phone":"+34 952 46 24 84",
    "sg:postcode":"29640",
    "sg:province":"M\u00e1laga",
    "wof:name":"Alfa Once S.l.",
    "wof:placetype":"venue"
},
  "geometry": {"coordinates":[-4.6088852882,36.5691261292],"type":"Point"}
}