{
  "type": "Feature",
  "properties": {
    "addr:full":"Calle de Isla De La Graciosa, 6 Pto. Rosario Las Palmas 35600",
    "addr:housenumber":"6",
    "addr:postcode":"35600",
    "addr:street":"Calle De Isla De La Graciosa;Pto. Rosario Las",
    "iso:country":"ES",
    "sg:address":"Calle de Isla De La Graciosa, 6",
    "sg:city":"Pto. Rosario",
    "sg:orig_category":"Peluquer\u00cdas, Peluquer\u00cda Mixta",
    "sg:phone":"+34 928 85 82 75",
    "sg:postcode":"35600",
    "sg:province":"Las Palmas",
    "wof:name":"Peluqueria Spejo S.l.",
    "wof:placetype":"venue"
},
  "geometry": {"coordinates":[-13.8670139313,28.5011920929],"type":"Point"}
}