{
  "type": "Feature",
  "properties": {
    "iso:country":"ES",
    "sg:address":"Carr Arbres (dels), 63",
    "sg:city":"Algemesi",
    "sg:orig_category":"T\u00c9cnicos Veterinarios",
    "sg:phone":"+34 962 48 24 15",
    "sg:postcode":"46680",
    "sg:province":"Valencia",
    "wof:name":"Clinica Veterinaria Ordas C.b.",
    "wof:placetype":"venue"
},
  "geometry": {"coordinates":[-0.440418005,39.1932220459],"type":"Point"}
}