{
  "type": "Feature",
  "properties": {
    "iso:country":"ES",
    "sg:address":"Calle de Carmen Bellido, 44",
    "sg:city":"Cortes",
    "sg:orig_category":"Carnicer\u00cdas, Carnicer\u00cdas",
    "sg:phone":"+34 948 80 06 68",
    "sg:postcode":"31530",
    "sg:province":"Navarra",
    "wof:name":"Belio Marques Jose",
    "wof:placetype":"venue"
},
  "geometry": {"coordinates":[-1.4221390486,41.9245109558],"type":"Point"}
}