{
  "type": "Feature",
  "properties": {
    "addr:full":"Avda Santa Isabel, 166 Zaragoza Zaragoza 50016",
    "addr:housenumber":"166",
    "addr:postcode":"50016",
    "addr:street":"Avda Santa Isabel",
    "iso:country":"ES",
    "sg:address":"Avda Santa Isabel, 166",
    "sg:city":"Zaragoza",
    "sg:orig_category":"Centros De Educaci\u00d3n Especial",
    "sg:phone":"+34 976 57 09 58",
    "sg:postcode":"50016",
    "sg:province":"Zaragoza",
    "wof:name":"Ferrer Mateo Maria Jesus",
    "wof:placetype":"venue"
},
  "geometry": {"coordinates":[-0.8264529705,41.6665725708],"type":"Point"}
}