{
  "type": "Feature",
  "properties": {
    "iso:country":"ES",
    "sg:address":"Cjto Olivar (el), 12",
    "sg:city":"Torre Benagalbon",
    "sg:orig_category":"Traductores",
    "sg:phone":"+34 952 97 80 43",
    "sg:postcode":"29738",
    "sg:province":"M\u00e1laga",
    "wof:name":"Euro Interpretes S.l.",
    "wof:placetype":"venue"
},
  "geometry": {"coordinates":[-4.2562980652,36.7710762024],"type":"Point"}
}