{
  "type": "Feature",
  "properties": {
    "addr:full":"Calle de Trascorrales, 35 Zalamea Serena Badajoz 06430",
    "addr:housenumber":"35",
    "addr:postcode":"06430",
    "addr:street":"Calle De Trascorrales",
    "iso:country":"ES",
    "sg:address":"Calle de Trascorrales, 35",
    "sg:city":"Zalamea Serena",
    "sg:orig_category":"Panader\u00cdas, Panader\u00cdas",
    "sg:phone":"+34 924 78 04 76",
    "sg:postcode":"06430",
    "sg:province":"Badajoz",
    "wof:name":"Ventura Garcia Tome Y Antonio Garcia Benitez C. B.",
    "wof:placetype":"venue"
},
  "geometry": {"coordinates":[-5.658208847,38.6504592896],"type":"Point"}
}