{
  "type": "Feature",
  "properties": {
    "iso:country":"ES",
    "sg:address":"Calle de Augusto G Linares, 18",
    "sg:city":"Santander",
    "sg:orig_category":"Electricidad: Instaladores",
    "sg:phone":"+34 942 36 06 36",
    "sg:postcode":"39006",
    "sg:province":"Cantabria",
    "wof:name":"Instalaciones Electricas Feljul S.l.",
    "wof:placetype":"venue"
},
  "geometry": {"coordinates":[-3.7980713844,43.470123291],"type":"Point"}
}