{
  "type": "Feature",
  "properties": {
    "iso:country":"ES",
    "sg:address":"Urb Cincuenta Ca\u00d1os, S/n",
    "sg:city":"Segorbe",
    "sg:orig_category":"Asociaciones Y Clubs Deportivos",
    "sg:phone":"+34 964 71 29 75",
    "sg:postcode":"12400",
    "sg:province":"Castell\u00f3n",
    "wof:name":"Club De Tenis Segorbe",
    "wof:placetype":"venue"
},
  "geometry": {"coordinates":[-0.4885739982,39.8518714905],"type":"Point"}
}