{
  "type": "Feature",
  "properties": {
    "addr:full":"Calle de San Fernando, 104 Santa Pola Alicante 03130",
    "addr:housenumber":"104",
    "addr:postcode":"03130",
    "addr:street":"Calle De San Fernando",
    "iso:country":"ES",
    "sg:address":"Calle de San Fernando, 104",
    "sg:city":"Santa Pola",
    "sg:orig_category":"Caf\u00c9s, Bares, Cervecer\u00cdas",
    "sg:phone":"+34 966 69 16 04",
    "sg:postcode":"03130",
    "sg:province":"Alicante",
    "wof:name":"Sempere Miralles Jose Francisco",
    "wof:placetype":"venue"
},
  "geometry": {"coordinates":[-0.5565090179,38.190448761],"type":"Point"}
}