{
  "type": "Feature",
  "properties": {
    "addr:full":"Avda Buenos Aires, 125 Ourense Ourense 32004",
    "addr:housenumber":"125",
    "addr:postcode":"32004",
    "addr:street":"Avda Buenos Aires",
    "iso:country":"ES",
    "sg:address":"Avda Buenos Aires, 125",
    "sg:city":"Ourense",
    "sg:orig_category":"Mercer\u00cda, Lencer\u00cda (al Por Menor)",
    "sg:phone":"+34 988 22 07 66",
    "sg:postcode":"32004",
    "sg:province":"Ourense",
    "wof:name":"Cidon Diaz Manuel",
    "wof:placetype":"venue"
},
  "geometry": {"coordinates":[-7.8570017815,42.342250824],"type":"Point"}
}