{
  "type": "Feature",
  "properties": {
    "addr:full":"Calle de Patricio Ferrandiz, 45 Denia Alicante 03700",
    "addr:housenumber":"45",
    "addr:postcode":"03700",
    "addr:street":"Calle De Patricio Ferrandiz",
    "iso:country":"ES",
    "sg:address":"Calle de Patricio Ferrandiz, 45",
    "sg:city":"Denia",
    "sg:orig_category":"Veh\u00cdculos De Ocasi\u00d3n",
    "sg:phone":"+34 965 78 42 75",
    "sg:postcode":"03700",
    "sg:province":"Alicante",
    "wof:name":"Auto Gata S.l.",
    "wof:placetype":"venue"
},
  "geometry": {"coordinates":[0.109207198,38.8390045166],"type":"Point"}
}