{
  "type": "Feature",
  "properties": {
    "addr:full":"Cmno Cantalpino, Km. 0000,0 Arabayona De Mogica Salamanca 37418",
    "addr:postcode":"37418",
    "addr:street":"Cmno Cantalpino Km. 0000,0",
    "iso:country":"ES",
    "sg:address":"Cmno Cantalpino, Km. 0000,0",
    "sg:city":"Arabayona De Mogica",
    "sg:orig_category":"Frutas Y Legumbres Frescas (al Por Mayor)",
    "sg:phone":"+34 923 36 11 50",
    "sg:postcode":"37418",
    "sg:province":"Salamanca",
    "wof:name":"S.a.t. Ifaca",
    "wof:placetype":"venue"
},
  "geometry": {"coordinates":[-5.3869891167,41.047908783],"type":"Point"}
}