{
  "type": "Feature",
  "properties": {
    "iso:country":"ES",
    "sg:address":"Calle de Heroes Dos De Mayo, 48",
    "sg:city":"Muriedas",
    "sg:orig_category":"Barbacoas Y Accesorios",
    "sg:phone":"+34 942 26 14 08",
    "sg:postcode":"39600",
    "sg:province":"Cantabria",
    "wof:name":"Diaz Canales Antonio",
    "wof:placetype":"venue"
},
  "geometry": {"coordinates":[-3.8572258949,43.4208259583],"type":"Point"}
}