{
  "type": "Feature",
  "properties": {
    "addr:full":"Calle de Nuestra Se\u00d1ora, 59 Pe\u00e7aranda De Bracamonte Salamanca 37300",
    "addr:housenumber":"59",
    "addr:postcode":"37300",
    "addr:street":"Calle De Nuestra Sen\u0303Ora",
    "iso:country":"ES",
    "sg:address":"Calle de Nuestra Se\u00d1ora, 59",
    "sg:city":"Pe\u00e7aranda De Bracamonte",
    "sg:orig_category":"Molduras, Junquillos, Listones Y Molduras Perforadas",
    "sg:phone":"+34 923 54 01 08",
    "sg:postcode":"37300",
    "sg:province":"Salamanca",
    "wof:name":"Flores Hernandez Sinforiano",
    "wof:placetype":"venue"
},
  "geometry": {"coordinates":[-5.2008280754,40.8997993469],"type":"Point"}
}