{
  "type": "Feature",
  "properties": {
    "addr:full":"Calle de Correos, 10 Portugalete Vizcaya 48920",
    "addr:housenumber":"10",
    "addr:postcode":"48920",
    "addr:street":"Calle De Correos",
    "iso:country":"ES",
    "sg:address":"Calle de Correos, 10",
    "sg:city":"Portugalete",
    "sg:orig_category":"Caf\u00c9s, Bares, Cervecer\u00cdas",
    "sg:phone":"+34 944 96 48 33",
    "sg:postcode":"48920",
    "sg:province":"Vizcaya",
    "wof:name":"Ufano Carrascal Argimiro",
    "wof:placetype":"venue"
},
  "geometry": {"coordinates":[-3.0196261406,43.3198242188],"type":"Point"}
}