{
  "type": "Feature",
  "properties": {
    "addr:full":"Carrer de Calderon De La Barca, 26 Rubi Barcelona 08191",
    "addr:housenumber":"26",
    "addr:postcode":"08191",
    "addr:street":"Carrer De Calderon De La Barca",
    "iso:country":"ES",
    "sg:address":"Carrer de Calderon De La Barca, 26",
    "sg:city":"Rubi",
    "sg:orig_category":"Reposter\u00cdas",
    "sg:phone":"+34 935 88 09 53",
    "sg:postcode":"08191",
    "sg:province":"Barcelona",
    "wof:name":"Fem Pa I Pastiseria S.l.",
    "wof:placetype":"venue"
},
  "geometry": {"coordinates":[2.0371439457,41.4928207397],"type":"Point"}
}