{
  "type": "Feature",
  "properties": {
    "iso:country":"ES",
    "sg:address":"Calle de Magdalena, 4",
    "sg:city":"Marbella",
    "sg:orig_category":"Agencias Y Agentes Comerciales, Representantes",
    "sg:phone":"+34 952 82 01 50",
    "sg:postcode":"29600",
    "sg:province":"M\u00e1laga",
    "wof:name":"Comunidad De Propietarios Edf. San Francisco 3",
    "wof:placetype":"venue"
},
  "geometry": {"coordinates":[-4.8870968819,36.5176048279],"type":"Point"}
}