{
  "type": "Feature",
  "properties": {
    "addr:full":"Calle de Crevillente, 5 Valencia Valencia 46022",
    "addr:housenumber":"5",
    "addr:postcode":"46022",
    "addr:street":"Calle De Crevillente",
    "iso:country":"ES",
    "sg:address":"Calle de Crevillente, 5",
    "sg:city":"Valencia",
    "sg:orig_category":"Centros Empresariales",
    "sg:phone":"+34 963 72 35 34",
    "sg:postcode":"46022",
    "sg:province":"Valencia",
    "wof:name":"Servicios Integrales Montes S.l.",
    "wof:placetype":"venue"
},
  "geometry": {"coordinates":[-0.3402059972,39.4685707092],"type":"Point"}
}