{
  "type": "Feature",
  "properties": {
    "addr:full":"Ctra. Alcorcon-plasencia, Km. 0028,2 Villanueva De Perales Madrid 28609",
    "addr:postcode":"28609",
    "addr:street":"Ctra. Alcorcon-Plasencia Km. 0028,2",
    "iso:country":"ES",
    "sg:address":"Ctra. Alcorcon-plasencia, Km. 0028,2",
    "sg:city":"Villanueva De Perales",
    "sg:orig_category":"Venta Y Reparaci\u00d3n De Naves De Recreo, Accesorios",
    "sg:phone":"+34 918 16 43 68",
    "sg:postcode":"28609",
    "sg:province":"Madrid",
    "wof:name":"Mercaviveros S.l.",
    "wof:placetype":"venue"
},
  "geometry": {"coordinates":[-4.0282459259,40.3476791382],"type":"Point"}
}