{
  "type": "Feature",
  "properties": {
    "addr:full":"Calle de Agirre Solarte, 11 Lekeitio Vizcaya 48280",
    "addr:housenumber":"11",
    "addr:postcode":"48280",
    "addr:street":"Calle De Agirre Solarte",
    "iso:country":"ES",
    "sg:address":"Calle de Agirre Solarte, 11",
    "sg:city":"Lekeitio",
    "sg:orig_category":"Asesor\u00cda Fiscal Y Jur\u00cddica",
    "sg:phone":"+34 946 84 25 85",
    "sg:postcode":"48280",
    "sg:province":"Vizcaya",
    "wof:name":"Asesoria Izayfer",
    "wof:placetype":"venue"
},
  "geometry": {"coordinates":[-2.5076396465,43.363571167],"type":"Point"}
}