{
  "type": "Feature",
  "properties": {
    "addr:full":"Av Verge Montserrat, 99 Prat Llobregat Barcelona 08820",
    "addr:housenumber":"99",
    "addr:postcode":"08820",
    "addr:street":"Av Verge Montserrat;Llobregat",
    "iso:country":"ES",
    "sg:address":"Av Verge Montserrat, 99",
    "sg:city":"Prat Llobregat",
    "sg:orig_category":"M\u00c9dicos: Estomatolog\u00cda",
    "sg:phone":"+34 933 70 33 06",
    "sg:postcode":"08820",
    "sg:province":"Barcelona",
    "wof:name":"Aguilera Montero Roberto",
    "wof:placetype":"venue"
},
  "geometry": {"coordinates":[2.0959761143,41.3261032104],"type":"Point"}
}