{
  "type": "Feature",
  "properties": {
    "addr:full":"Ctra. Sineu, Km. 0004,1 Inca Islas Baleares 07300",
    "addr:postcode":"07300",
    "addr:street":"Ctra. Sineu Km. 0004,1",
    "iso:country":"ES",
    "sg:address":"Ctra. Sineu, Km. 0004,1",
    "sg:city":"Inca",
    "sg:orig_category":"Alcoholes Y Aguardientes (fabricaci\u00d3n, Al Por Mayor)",
    "sg:phone":"+34 971 18 22 02",
    "sg:postcode":"07300",
    "sg:province":"Islas Baleares",
    "wof:name":"S.a.t.agrocoll Pastor",
    "wof:placetype":"venue"
},
  "geometry": {"coordinates":[2.9208989143,39.7179527283],"type":"Point"}
}