{
  "type": "Feature",
  "properties": {
    "addr:full":"Calle de Bolivar Simon, 3 Bilbao Vizcaya 48010",
    "addr:housenumber":"3",
    "addr:postcode":"48010",
    "addr:street":"Calle De Bolivar Simon",
    "iso:country":"ES",
    "sg:address":"Calle de Bolivar Simon, 3",
    "sg:city":"Bilbao",
    "sg:orig_category":"Alquiler De Casas Y Habitaciones Amuebladas",
    "sg:phone":"+34 944 21 05 47",
    "sg:postcode":"48010",
    "sg:province":"Vizcaya",
    "wof:name":"Instituto Catequista Dolores Sope\u00f1a",
    "wof:placetype":"venue"
},
  "geometry": {"coordinates":[-2.9405939579,43.2597427368],"type":"Point"}
}