{
  "type": "Feature",
  "properties": {
    "iso:country":"ES",
    "sg:address":"Calle de Enrique Segura Ota\u00d1o, 1",
    "sg:city":"Badajoz",
    "sg:orig_category":"Abogados",
    "sg:phone":"+34 924 24 61 44",
    "sg:postcode":"06004",
    "sg:province":"Badajoz",
    "wof:name":"Sanchez-simon Mu\u00f1oz Luis",
    "wof:placetype":"venue"
},
  "geometry": {"coordinates":[-6.9710059166,38.8731460571],"type":"Point"}
}