{
  "type": "Feature",
  "properties": {
    "addr:full":"Calle de Rejilla (de La), 12 Mostoles Madrid 28931",
    "addr:housenumber":"12",
    "addr:postcode":"28931",
    "addr:street":"Calle De Rejilla De La",
    "iso:country":"ES",
    "sg:address":"Calle de Rejilla (de La), 12",
    "sg:city":"Mostoles",
    "sg:orig_category":"Mec\u00c1nico Del Autom\u00d3vil",
    "sg:phone":"+34 916 13 44 41",
    "sg:postcode":"28931",
    "sg:province":"Madrid",
    "wof:name":"Fernandez Fernandez Antonio Manuel",
    "wof:placetype":"venue"
},
  "geometry": {"coordinates":[-3.8649311066,40.3249435425],"type":"Point"}
}