{
  "type": "Feature",
  "properties": {
    "iso:country":"ES",
    "sg:address":"Calle de Acera Recoletos, 6",
    "sg:city":"Valladolid",
    "sg:orig_category":"Abogados",
    "sg:phone":"+34 983 33 01 94",
    "sg:postcode":"47004",
    "sg:province":"Valladolid",
    "wof:name":"Sanz Fernandez-lomana Enrique",
    "wof:placetype":"venue"
},
  "geometry": {"coordinates":[-4.7283291817,41.6471366882],"type":"Point"}
}