{
  "type": "Feature",
  "properties": {
    "iso:country":"ES",
    "sg:address":"Calle de Parral (el), 5",
    "sg:city":"Quintana Redonda",
    "sg:orig_category":"Fabricaci\u00d3n De Su\u00c9ters Y Chalecos De Punto",
    "sg:phone":"+34 975 30 80 36",
    "sg:postcode":"42291",
    "sg:province":"Soria",
    "wof:name":"Textil Gui-san S.l.",
    "wof:placetype":"venue"
},
  "geometry": {"coordinates":[-2.6140871048,41.6395568848],"type":"Point"}
}