{
  "type": "Feature",
  "properties": {
    "iso:country":"ES",
    "sg:address":"Avda Gipuzkoa, S/n",
    "sg:city":"Ermua",
    "sg:orig_category":"Empresas De Carpinter\u00cda Met\u00c1lica",
    "sg:phone":"+34 943 17 62 71",
    "sg:postcode":"48260",
    "sg:province":"Vizcaya",
    "wof:name":"Silvan Rodriguez Isidro",
    "wof:placetype":"venue"
},
  "geometry": {"coordinates":[-2.4989349842,43.1816139221],"type":"Point"}
}