{
  "type": "Feature",
  "properties": {
    "iso:country":"ES",
    "sg:address":"Calle de Domingo Guerra Del Rio, 52",
    "sg:city":"Palmas De Gran Canaria",
    "sg:orig_category":"Bazares, Art\u00cdculos De Limpieza Y De Cocina (al Por Menor)",
    "sg:phone":"+34 928 36 47 89",
    "sg:postcode":"35014",
    "sg:province":"Las Palmas",
    "wof:name":"Ortega Santana Carmelo",
    "wof:placetype":"venue"
},
  "geometry": {"coordinates":[-15.4199829102,28.1046543121],"type":"Point"}
}