{
  "type": "Feature",
  "properties": {
    "iso:country":"ES",
    "sg:address":"Calle de La Economia, 42",
    "sg:city":"Barakaldo",
    "sg:orig_category":"Promotores Constructores",
    "sg:phone":"+34 944 85 09 73",
    "sg:postcode":"48902",
    "sg:province":"Vizcaya",
    "wof:name":"Construcciones Baracons, S.l.",
    "wof:placetype":"venue"
},
  "geometry": {"coordinates":[-2.995043993,43.2928657532],"type":"Point"}
}