{
  "type": "Feature",
  "properties": {
    "iso:country":"ES",
    "sg:address":"Avda Leon, 276",
    "sg:city":"Carbajal Legua",
    "sg:orig_category":"Jardiner\u00cdas, Vegetales, Art\u00cdculos De Jardiner\u00cda (al Por Menor)",
    "sg:phone":"+34 987 28 84 49",
    "sg:postcode":"24196",
    "sg:province":"Le\u00f3n",
    "wof:name":"Paclana S.l.",
    "wof:placetype":"venue"
},
  "geometry": {"coordinates":[-5.6067891121,42.6558914185],"type":"Point"}
}