{
  "type": "Feature",
  "properties": {
    "addr:full":"Calle de Villaluenga, 4 Yuncler Toledo 45529",
    "addr:housenumber":"4",
    "addr:postcode":"45529",
    "addr:street":"Calle De Villaluenga",
    "iso:country":"ES",
    "sg:address":"Calle de Villaluenga, 4",
    "sg:city":"Yuncler",
    "sg:orig_category":"Reposter\u00cdas",
    "sg:phone":"+34 925 53 12 30",
    "sg:postcode":"45529",
    "sg:province":"Toledo",
    "wof:name":"Fernandez Morales Juan Antonio",
    "wof:placetype":"venue"
},
  "geometry": {"coordinates":[-3.9032599926,40.0407676697],"type":"Point"}
}