{
  "type": "Feature",
  "properties": {
    "iso:country":"ES",
    "sg:address":"Carr Santa Lucia, 10",
    "sg:city":"Olleria",
    "sg:orig_category":"Art\u00cdculos De Madera (fabricaci\u00d3n Y Al Por Mayor)",
    "sg:phone":"+34 962 20 20 05",
    "sg:postcode":"46850",
    "sg:province":"Valencia",
    "wof:name":"Almobax L'oyeria S.l.",
    "wof:placetype":"venue"
},
  "geometry": {"coordinates":[-0.5451020002,38.9148406982],"type":"Point"}
}