{
  "type": "Feature",
  "properties": {
    "iso:country":"ES",
    "sg:address":"Vilar De Astres, 11",
    "sg:city":"Vilar Astres",
    "sg:orig_category":"Poller\u00cda Y Caza (al Por Menor)",
    "sg:phone":"+34 988 21 76 41",
    "sg:postcode":"32981",
    "sg:province":"Ourense",
    "wof:name":"Berta Barroso Y Otro C.b.",
    "wof:placetype":"venue"
},
  "geometry": {"coordinates":[-7.89747715,42.3912582397],"type":"Point"}
}