{
  "type": "Feature",
  "properties": {
    "addr:full":"Pl Merce, 9 Elche Alicante 03202",
    "addr:housenumber":"9",
    "addr:postcode":"03202",
    "addr:street":"Pl Merce",
    "iso:country":"ES",
    "sg:address":"Pl Merce, 9",
    "sg:city":"Elche",
    "sg:orig_category":"M\u00c9dicos: An\u00c1lisis Cl\u00cdnicos",
    "sg:phone":"+34 965 45 40 74",
    "sg:postcode":"03202",
    "sg:province":"Alicante",
    "wof:name":"Fajardo Gimenez Laboratorio C.b",
    "wof:placetype":"venue"
},
  "geometry": {"coordinates":[-0.6959949732,38.2669792175],"type":"Point"}
}