{
  "type": "Feature",
  "properties": {
    "iso:country":"ES",
    "sg:address":"Carr Malva, S/n",
    "sg:city":"Santa Coloma De Farners",
    "sg:orig_category":"Electrodom\u00c9sticos (al Por Menor)",
    "sg:phone":"+34 972 87 79 38",
    "sg:postcode":"17430",
    "sg:province":"Girona",
    "wof:name":"Ajuntament De Santa Coloma De Farners",
    "wof:placetype":"venue"
},
  "geometry": {"coordinates":[2.6657159328,41.8589515686],"type":"Point"}
}