{
  "type": "Feature",
  "properties": {
    "iso:country":"ES",
    "sg:address":"Plaz Espa\u00d1a, 8",
    "sg:city":"Miranda Ebro",
    "sg:orig_category":"Administraciones Regionales, Departamentales Y Locales",
    "sg:phone":"+34 947 34 91 00",
    "sg:postcode":"09...",
    "sg:province":"Burgos",
    "wof:name":"Ayuntamiento De Miranda De Ebro",
    "wof:placetype":"venue"
},
  "geometry": {"coordinates":[-2.9475934505,42.6873435974],"type":"Point"}
}