{
  "type": "Feature",
  "properties": {
    "iso:country":"ES",
    "sg:address":"Carr Bautista Aparici (de), 12",
    "sg:city":"Aielo Malferit",
    "sg:orig_category":"Producci\u00d3n, Venta De Productos De Agricultura Biol\u00d3gica",
    "sg:phone":"+34 962 36 02 34",
    "sg:postcode":"46812",
    "sg:province":"Valencia",
    "wof:name":"Vidal Mompo Juan",
    "wof:placetype":"venue"
},
  "geometry": {"coordinates":[-0.5892890096,38.8797683716],"type":"Point"}
}