{
  "type": "Feature",
  "properties": {
    "addr:full":"Calle de Jeronima Llorente, 36 Madrid Madrid 28039",
    "addr:housenumber":"36",
    "addr:postcode":"madrid;28039",
    "addr:street":"Calle De Jeronima Llorente",
    "iso:country":"ES",
    "sg:address":"Calle de Jeronima Llorente, 36",
    "sg:city":"Madrid",
    "sg:orig_category":"Frutas, Legumbres Frescas Y Tempranas (al Por Menor)",
    "sg:phone":"+34 914 50 29 97",
    "sg:postcode":"28039",
    "sg:province":"Madrid",
    "wof:name":"Castillo Pollan Francisco",
    "wof:placetype":"venue"
},
  "geometry": {"coordinates":[-3.707005024,40.4546546936],"type":"Point"}
}