{
  "type": "Feature",
  "properties": {
    "addr:full":"Calle de Maestro Palau, 7 Valencia Valencia 46008",
    "addr:housenumber":"7",
    "addr:postcode":"46008",
    "addr:street":"Calle De Maestro Palau",
    "iso:country":"ES",
    "sg:address":"Calle de Maestro Palau, 7",
    "sg:city":"Valencia",
    "sg:orig_category":"M\u00c9dicos: Alergolog\u00cda",
    "sg:phone":"+34 963 92 11 01",
    "sg:postcode":"46008",
    "sg:province":"Valencia",
    "wof:name":"Ferris Gil Juan Manuel",
    "wof:placetype":"venue"
},
  "geometry": {"coordinates":[-0.3847590089,39.4712715149],"type":"Point"}
}