{
  "type": "Feature",
  "properties": {
    "iso:country":"ES",
    "sg:address":"Calle de Real, 22",
    "sg:city":"Mengibar",
    "sg:classifiers":[
        {
            "category":"Personal",
            "subcategory":"Barber",
            "type":"Services"
        }
    ],
    "sg:phone":"+34 953 37 24 14",
    "sg:postcode":"23620",
    "sg:province":"Ja\u00e9n",
    "sg:tags":[
        "caballeros",
        "de",
        "peluqueros"
    ],
    "wof:name":"Torralbo Gallardo Ignacio",
    "wof:placetype":"venue"
},
  "geometry": {"coordinates":[-3.8079888821,37.9698181152],"type":"Point"}
}