{
  "type": "Feature",
  "properties": {
    "addr:full":"Urb Golf Costa Brava, S/n Urbanitzacio Golf Costa Brava Girona 17246",
    "addr:housenumber":"s",
    "addr:postcode":"17246",
    "addr:street":"Brava;/ N Urbanitzacio;Costa",
    "iso:country":"ES",
    "sg:address":"Urb Golf Costa Brava, S/n",
    "sg:city":"Urbanitzacio Golf Costa Brava",
    "sg:classifiers":[
        {
            "category":"Sports & Exercise",
            "subcategory":"Golf",
            "type":"Entertainment"
        }
    ],
    "sg:phone":"+34 972 83 74 60",
    "sg:postcode":"17246",
    "sg:province":"Girona",
    "sg:tags":[
        "y",
        "de",
        "campos",
        "clases"
    ],
    "sg:website":"www.santacristina.net/hotelgolf.net",
    "wof:name":"Sanchez Catlla Monica",
    "wof:placetype":"venue"
},
  "geometry": {"coordinates":[2.9876329899,41.8070983887],"type":"Point"}
}