{
  "type": "Feature",
  "properties": {
    "iso:country":"ES",
    "sg:address":"Calle de Pinar De Los Pajaros, 10",
    "sg:city":"Pilas",
    "sg:orig_category":"Asesor\u00cda De Formaci\u00d3n Y Gesti\u00d3n De Personal",
    "sg:phone":"+34 955 75 31 38",
    "sg:postcode":"41840",
    "sg:province":"Sevilla",
    "wof:name":"Servicios Contables De Pilas S.l.",
    "wof:placetype":"venue"
},
  "geometry": {"coordinates":[-6.2944750786,37.2958755493],"type":"Point"}
}