{
  "type": "Feature",
  "properties": {
    "iso:country":"ES",
    "sg:address":"Calle de Jenaro Oraa, 9",
    "sg:city":"Santurtzi",
    "sg:orig_category":"Agencias De Viajes",
    "sg:phone":"+34 944 83 17 87",
    "sg:postcode":"48980",
    "sg:province":"Vizcaya",
    "sg:website":"www.halcon viajes.com",
    "wof:name":"Viajes Halcon S.a.",
    "wof:placetype":"venue"
},
  "geometry": {"coordinates":[-3.0322840214,43.3277549744],"type":"Point"}
}