{
  "type": "Feature",
  "properties": {
    "iso:country":"ES",
    "sg:address":"El Hornillo, S/n",
    "sg:city":"Vinuesa",
    "sg:orig_category":"Art\u00cdculos De Madera (fabricaci\u00d3n Y Al Por Mayor)",
    "sg:phone":"+34 975 37 84 25",
    "sg:postcode":"42150",
    "sg:province":"Soria",
    "sg:website":"www.bastidoresmoreno.com",
    "wof:name":"Bastidores Moreno Lopez S.l.",
    "wof:placetype":"venue"
},
  "geometry": {"coordinates":[-2.7598340511,41.9107093811],"type":"Point"}
}