{
  "type": "Feature",
  "properties": {
    "addr:full":"Via Augusta, 10 Salou Tarragona 43840",
    "addr:housenumber":"10",
    "addr:postcode":"43840",
    "addr:street":"Via Augusta",
    "iso:country":"ES",
    "sg:address":"Via Augusta, 10",
    "sg:city":"Salou",
    "sg:orig_category":"Cajas De Ahorro",
    "sg:phone":"+34 977 35 10 36",
    "sg:postcode":"43840",
    "sg:province":"Tarragona",
    "wof:name":"Caja De Ahorros De La Inmaculada",
    "wof:placetype":"venue"
},
  "geometry": {"coordinates":[1.1316100359,41.079372406],"type":"Point"}
}