{
  "type": "Feature",
  "properties": {
    "addr:full":"Calle de Fernando De Llera Y Diaz, 9 Fuentes De Andalucia Sevilla 41420",
    "addr:housenumber":"9",
    "addr:postcode":"41420",
    "addr:street":"Calle De Fernando De Llera Y Diaz",
    "iso:country":"ES",
    "sg:address":"Calle de Fernando De Llera Y Diaz, 9",
    "sg:city":"Fuentes De Andalucia",
    "sg:orig_category":"Obras Y Organismos Sociales",
    "sg:phone":"+34 954 83 76 09",
    "sg:postcode":"41420",
    "sg:province":"Sevilla",
    "wof:name":"Junta De Andalucia",
    "wof:placetype":"venue"
},
  "geometry": {"coordinates":[-5.3480801582,37.4626579285],"type":"Point"}
}