{
  "type": "Feature",
  "properties": {
    "addr:full":"Carrer de Balmes, 53 Barcelona Barcelona 08007",
    "addr:housenumber":"53",
    "addr:postcode":"08007",
    "addr:street":"Carrer De Balmes",
    "iso:country":"ES",
    "sg:address":"Carrer de Balmes, 53",
    "sg:city":"Barcelona",
    "sg:orig_category":"Agencias Y Asesores De Publicidad",
    "sg:phone":"+34 934 54 59 82",
    "sg:postcode":"08007",
    "sg:province":"Barcelona",
    "wof:name":"Ruax Pique Maria Luisa",
    "wof:placetype":"venue"
},
  "geometry": {"coordinates":[2.1622319221,41.3894233704],"type":"Point"}
}