{
  "type": "Feature",
  "properties": {
    "iso:country":"ES",
    "sg:address":"Calle de Fernando El Santo, 11",
    "sg:city":"Madrid",
    "sg:orig_category":"Inmobiliaria (agencias)",
    "sg:phone":"+34 915 47 74 58",
    "sg:postcode":"28010",
    "sg:province":"Madrid",
    "wof:name":"Consulting Vaher S.a.",
    "wof:placetype":"venue"
},
  "geometry": {"coordinates":[-3.6931769848,40.4282951355],"type":"Point"}
}