{
  "type": "Feature",
  "properties": {
    "addr:full":"Plaz Julian Sanchez El Charro, S/n Salamanca Salamanca 37005",
    "addr:housenumber":"/ n",
    "addr:postcode":"37005",
    "addr:street":"Plaz;El Charro S",
    "iso:country":"ES",
    "sg:address":"Plaz Julian Sanchez El Charro, S/n",
    "sg:city":"Salamanca",
    "sg:orig_category":"Poller\u00cda Y Caza (al Por Menor)",
    "sg:phone":"+34 923 22 19 63",
    "sg:postcode":"37005",
    "sg:province":"Salamanca",
    "wof:name":"Hermanos Valiente De Salamanca Cdad.",
    "wof:placetype":"venue"
},
  "geometry": {"coordinates":[-5.6611638069,40.9704360962],"type":"Point"}
}