{
  "type": "Feature",
  "properties": {
    "addr:full":"Dolar(pol Atalayas), S/n Alacant Alicante 03006",
    "addr:housenumber":"/ n",
    "addr:postcode":"03006",
    "addr:street":"Atalayas S",
    "iso:country":"ES",
    "sg:address":"Dolar(pol Atalayas), S/n",
    "sg:city":"Alacant",
    "sg:orig_category":"Farmacias (repartici\u00d3n Y Al Por Mayor)",
    "sg:phone":"+34 965 11 58 76",
    "sg:postcode":"03006",
    "sg:province":"Alicante",
    "wof:name":"Safa Galenica S.a.",
    "wof:placetype":"venue"
},
  "geometry": {"coordinates":[-0.5621370077,38.3399162292],"type":"Point"}
}