{
  "type": "Feature",
  "properties": {
    "iso:country":"ES",
    "sg:address":"Calle de Duero (del), 40",
    "sg:city":"Mejorada Campo",
    "sg:orig_category":"Cerrajer\u00cda, Ferrallista",
    "sg:phone":"+34 916 79 29 36",
    "sg:postcode":"28840",
    "sg:province":"Madrid",
    "wof:name":"Moreno Serrano Jose",
    "wof:placetype":"venue"
},
  "geometry": {"coordinates":[-3.478631258,40.3866500854],"type":"Point"}
}