{
  "type": "Feature",
  "properties": {
    "iso:country":"ES",
    "sg:address":"Calle de Rosal, S/n",
    "sg:city":"Rincon Victoria",
    "sg:orig_category":"Asilos De Ancianos. Centros Privados",
    "sg:phone":"+34 952 97 11 12",
    "sg:postcode":"29730",
    "sg:province":"M\u00e1laga",
    "wof:name":"Olimata S.l.",
    "wof:placetype":"venue"
},
  "geometry": {"coordinates":[-4.2710089684,36.7168388367],"type":"Point"}
}