{
  "type": "Feature",
  "properties": {
    "iso:country":"ES",
    "sg:address":"El Puente, 38",
    "sg:city":"Huerga Frailes",
    "sg:orig_category":"Material Y Herramientas Agr\u00cdcolas",
    "sg:phone":"+34 987 37 41 00",
    "sg:postcode":"24356",
    "sg:province":"Le\u00f3n",
    "wof:name":"Diez Sanchez Diamantino",
    "wof:placetype":"venue"
},
  "geometry": {"coordinates":[-5.8473391533,42.3903503418],"type":"Point"}
}