{
  "type": "Feature",
  "properties": {
    "addr:full":"Avda Doctor Rafael Gonzalez, 17 Arrecife Las Palmas 35500",
    "addr:housenumber":"17",
    "addr:postcode":"35500",
    "addr:street":"Avda Doctor Rafael Gonzalez",
    "iso:country":"ES",
    "sg:address":"Avda Doctor Rafael Gonzalez, 17",
    "sg:city":"Arrecife",
    "sg:orig_category":"Cl\u00cdnicas Dentales",
    "sg:phone":"+34 928 81 77 22",
    "sg:postcode":"35500",
    "sg:province":"Las Palmas",
    "wof:name":"Plata Rocio Francisco Javier",
    "wof:placetype":"venue"
},
  "geometry": {"coordinates":[-13.5535354614,28.9578990936],"type":"Point"}
}