{
  "type": "Feature",
  "properties": {
    "iso:country":"ES",
    "sg:address":"Psaj Doctor Serra, 3",
    "sg:city":"Valencia",
    "sg:orig_category":"Asociaciones, Organismos Culturales Y Socioeducativos",
    "sg:phone":"+34 963 52 59 83",
    "sg:postcode":"46004",
    "sg:province":"Valencia",
    "wof:name":"Asociacion Hindu De Valencia",
    "wof:placetype":"venue"
},
  "geometry": {"coordinates":[-0.3751814067,39.4669761658],"type":"Point"}
}