{
  "type": "Feature",
  "properties": {
    "iso:country":"ES",
    "sg:address":"Calle de Argumosa, 23",
    "sg:city":"Madrid",
    "sg:orig_category":"Molduras, Junquillos, Listones Y Molduras Perforadas",
    "sg:phone":"+34 915 27 73 67",
    "sg:postcode":"28012",
    "sg:province":"Madrid",
    "wof:name":"Revuelta Fernandez Miguel",
    "wof:placetype":"venue"
},
  "geometry": {"coordinates":[-3.6982975006,40.4080619812],"type":"Point"}
}