{
  "type": "Feature",
  "properties": {
    "addr:full":"Calle de Guadiana, 34 Ciudad Real Ciudad Real 13002",
    "addr:housenumber":"34",
    "addr:postcode":"13002",
    "addr:street":"Calle De Guadiana",
    "iso:country":"ES",
    "sg:address":"Calle de Guadiana, 34",
    "sg:city":"Ciudad Real",
    "sg:orig_category":"Tapicer\u00cdas",
    "sg:phone":"+34 926 21 11 55",
    "sg:postcode":"13002",
    "sg:province":"Ciudad Real",
    "wof:name":"Donoso Bastante Diego",
    "wof:placetype":"venue"
},
  "geometry": {"coordinates":[-3.9345219135,38.9849777222],"type":"Point"}
}