{
  "type": "Feature",
  "properties": {
    "iso:country":"ES",
    "sg:address":"Afueras, S/n",
    "sg:city":"Fuentes Ebro",
    "sg:orig_category":"Aparatos E Instalaci\u00d3n De Regad\u00cdos",
    "sg:phone":"+34 976 16 07 82",
    "sg:postcode":"50740",
    "sg:province":"Zaragoza",
    "wof:name":"Irritecnica S.l.",
    "wof:placetype":"venue"
},
  "geometry": {"coordinates":[-0.6268740296,41.5112380981],"type":"Point"}
}