{
  "type": "Feature",
  "properties": {
    "iso:country":"ES",
    "sg:address":"Plaz Marquesa De Cruilles, S/n",
    "sg:city":"Eliana",
    "sg:orig_category":"Supermercados Y Hipermercados",
    "sg:phone":"+34 962 74 07 28",
    "sg:postcode":"46183",
    "sg:province":"Valencia",
    "wof:name":"Fortea Serra Consuelo",
    "wof:placetype":"venue"
},
  "geometry": {"coordinates":[-0.5362110138,39.5613555908],"type":"Point"}
}