{
  "type": "Feature",
  "properties": {
    "iso:country":"ES",
    "sg:address":"Plaz Concordia, 1",
    "sg:city":"Cabezon.barrio Viejo",
    "sg:orig_category":"Cajas Para Embalar",
    "sg:phone":"+34 983 50 02 82",
    "sg:postcode":"47260",
    "sg:province":"Valladolid",
    "wof:name":"Caja Rural Del Duero",
    "wof:placetype":"venue"
},
  "geometry": {"coordinates":[-4.6468057632,41.733455658],"type":"Point"}
}