{
  "type": "Feature",
  "properties": {
    "addr:full":"Urb. Os Rueiros 3 (illa Toxa), S/n Grove Pontevedra 36991",
    "addr:housenumber":"3;s",
    "addr:postcode":"36991",
    "addr:street":"Rueiros;Toxa;/ N Grove",
    "iso:country":"ES",
    "sg:address":"Urb. Os Rueiros 3 (illa Toxa), S/n",
    "sg:city":"Grove",
    "sg:orig_category":"Asesor\u00cdas Y Estudios Financieros",
    "sg:phone":"+34 986 73 29 01",
    "sg:postcode":"36991",
    "sg:province":"Pontevedra",
    "wof:name":"Manteiga Esquer Antonio",
    "wof:placetype":"venue"
},
  "geometry": {"coordinates":[-8.8467092514,42.4828300476],"type":"Point"}
}