{
  "type": "Feature",
  "properties": {
    "iso:country":"ES",
    "sg:address":"Calle de Aguila, 8",
    "sg:city":"Madrid",
    "sg:orig_category":"Papeler\u00cdas, Librer\u00cdas",
    "sg:phone":"+34 913 65 61 98",
    "sg:postcode":"28005",
    "sg:province":"Madrid",
    "wof:name":"Martin Losada Maria Del Pilar",
    "wof:placetype":"venue"
},
  "geometry": {"coordinates":[-3.7122187614,40.4098243713],"type":"Point"}
}