{
  "type": "Feature",
  "properties": {
    "addr:full":"Avda San Isidro Labrador, 19 Santa Marta Badajoz 06150",
    "addr:housenumber":"19",
    "addr:postcode":"06150",
    "addr:street":"Avda San Isidro Labrador",
    "iso:country":"ES",
    "sg:address":"Avda San Isidro Labrador, 19",
    "sg:city":"Santa Marta",
    "sg:orig_category":"Asilos De Ancianos. Centros Privados",
    "sg:phone":"+34 924 69 06 24",
    "sg:postcode":"06150",
    "sg:province":"Badajoz",
    "wof:name":"Ayuntamiento De Santa Marta De Los Barros",
    "wof:placetype":"venue"
},
  "geometry": {"coordinates":[-6.6248731613,38.6112976074],"type":"Point"}
}