{
  "type": "Feature",
  "properties": {
    "iso:country":"ES",
    "sg:address":"La Mergulleira, S/n",
    "sg:city":"S. Antolin Ibias",
    "sg:orig_category":"Negocio De Materiales De Construcci\u00d3n",
    "sg:phone":"+34 985 81 61 85",
    "sg:postcode":"33810",
    "sg:province":"Asturias",
    "wof:name":"Alvarez Lopez Higinio",
    "wof:placetype":"venue"
},
  "geometry": {"coordinates":[-6.8633770943,43.026599884],"type":"Point"}
}