{
  "type": "Feature",
  "properties": {
    "addr:full":"Calle de Primo De Rivera, 27 Lucillos Toledo 45554",
    "addr:housenumber":"27",
    "addr:postcode":"45554",
    "addr:street":"Calle De Primo De Rivera",
    "iso:country":"ES",
    "sg:address":"Calle de Primo De Rivera, 27",
    "sg:city":"Lucillos",
    "sg:orig_category":"Cajas Para Embalar",
    "sg:phone":"+34 925 86 50 27",
    "sg:postcode":"45554",
    "sg:province":"Toledo",
    "sg:website":"www.cajarural.es/toledo",
    "wof:name":"Caja Rural Provincial De Toledo",
    "wof:placetype":"venue"
},
  "geometry": {"coordinates":[-4.6111979485,39.983707428],"type":"Point"}
}