{
  "type": "Feature",
  "properties": {
    "iso:country":"ES",
    "sg:address":"Avda Pasajes San Pedro, 47",
    "sg:city":"Donostia-san Sebastian",
    "sg:orig_category":"Inmobiliaria (agencias)",
    "sg:phone":"+34 943 40 40 33",
    "sg:postcode":"20017",
    "sg:province":"Guip\u00f9zcoa",
    "sg:website":"www.remaxgipuzkoa.com",
    "wof:name":"Maxin House S.l.",
    "wof:placetype":"venue"
},
  "geometry": {"coordinates":[-1.9794000387,43.3173789978],"type":"Point"}
}