{
  "type": "Feature",
  "properties": {
    "addr:full":"Zona Aeroport, 2 Prat Llobregat Barcelona 08820",
    "addr:housenumber":"2",
    "addr:postcode":"08820",
    "addr:street":"Aeroport;Llobregat",
    "iso:country":"ES",
    "sg:address":"Zona Aeroport, 2",
    "sg:city":"Prat Llobregat",
    "sg:orig_category":"Zapatos (al Por Menor)",
    "sg:phone":"+34 934 78 72 08",
    "sg:postcode":"08820",
    "sg:province":"Barcelona",
    "wof:name":"Comercial Catalana De Zapaterias S.a.",
    "wof:placetype":"venue"
},
  "geometry": {"coordinates":[2.0864720345,41.3289909363],"type":"Point"}
}