{
  "type": "Feature",
  "properties": {
    "iso:country":"ES",
    "sg:address":"Calle de San Isidro, 2",
    "sg:city":"Tarancon",
    "sg:orig_category":"Comercio De Piezas De Recambio Y De Accesorios De Veh\u00cdculos, Veh\u00cdculos Industriales",
    "sg:phone":"+34 969 32 07 59",
    "sg:postcode":"16400",
    "sg:province":"Cuenca",
    "wof:name":"Auto Recambios Comare S.l.",
    "wof:placetype":"venue"
},
  "geometry": {"coordinates":[-3.0112431049,40.0087890625],"type":"Point"}
}