{
  "type": "Feature",
  "properties": {
    "iso:country":"ES",
    "sg:address":"Avda Jose Maria Torres Murcian, 26",
    "sg:city":"Marbella",
    "sg:orig_category":"Persianas Interiores, Exteriores",
    "sg:phone":"+34 952 77 67 31",
    "sg:postcode":"29600",
    "sg:province":"M\u00e1laga",
    "wof:name":"Ruiz Urbano Jose Antonio",
    "wof:placetype":"venue"
},
  "geometry": {"coordinates":[-4.8759789467,36.5145187378],"type":"Point"}
}