{
  "type": "Feature",
  "properties": {
    "addr:full":"Carr Comte De Rossello, 6 Eivissa Islas Baleares 07800",
    "addr:housenumber":"6",
    "addr:postcode":"07800",
    "addr:street":"Carr Comte De Rossello",
    "iso:country":"ES",
    "sg:address":"Carr Comte De Rossello, 6",
    "sg:city":"Eivissa",
    "sg:orig_category":"Confecci\u00d3n De Sombreros Y Tocados",
    "sg:phone":"+34 971 31 06 68",
    "sg:postcode":"07800",
    "sg:province":"Islas Baleares",
    "wof:name":"Boned Boned Juan",
    "wof:placetype":"venue"
},
  "geometry": {"coordinates":[1.4350420237,38.9094619751],"type":"Point"}
}