{
  "type": "Feature",
  "properties": {
    "iso:country":"ES",
    "sg:address":"Calle de Francisco Silveira, 2",
    "sg:city":"Fregenal Sierra",
    "sg:orig_category":"Alimentaci\u00d3n General (al Por Menor)",
    "sg:phone":"+34 924 70 09 04",
    "sg:postcode":"06340",
    "sg:province":"Badajoz",
    "wof:name":"Castillo Benitez Maria Jose",
    "wof:placetype":"venue"
},
  "geometry": {"coordinates":[-6.6532468796,38.1699562073],"type":"Point"}
}