{
  "type": "Feature",
  "properties": {
    "iso:country":"ES",
    "sg:address":"Pol Ind San Roque, 7",
    "sg:city":"Blanca",
    "sg:classifiers":[
        {
            "category":"Food & Beverages",
            "subcategory":"Candy",
            "type":"Retail Goods"
        }
    ],
    "sg:phone":"+34 968 77 50 32",
    "sg:postcode":"30540",
    "sg:province":"Murcia",
    "sg:tags":[
        "confiter\u00cdas",
        "y",
        "de",
        "fabricaci\u00d3n",
        "chocolate"
    ],
    "wof:name":"Aunon Sweets S.l.",
    "wof:placetype":"venue"
},
  "geometry": {"coordinates":[-1.369478941,38.1796684265],"type":"Point"}
}