{
  "type": "Feature",
  "properties": {
    "addr:full":"Carrer de Numancia, 47 Barcelona Barcelona 08029",
    "addr:housenumber":"47",
    "addr:postcode":"08029",
    "addr:street":"Carrer De Numancia",
    "iso:country":"ES",
    "sg:address":"Carrer de Numancia, 47",
    "sg:city":"Barcelona",
    "sg:orig_category":"Asociaciones, Organismos Culturales Y Socioeducativos",
    "sg:phone":"+34 933 21 07 38",
    "sg:postcode":"08029",
    "sg:province":"Barcelona",
    "wof:name":"Emprius Club Opinio",
    "wof:placetype":"venue"
},
  "geometry": {"coordinates":[2.1387760639,41.3832702637],"type":"Point"}
}