{
  "type": "Feature",
  "properties": {
    "iso:country":"ES",
    "sg:address":"Carrer de Puig Castellar, 17",
    "sg:city":"Barcelona",
    "sg:orig_category":"Confecci\u00d3n (fabricaci\u00d3n, Al Por Mayor)",
    "sg:phone":"+34 934 29 36 40",
    "sg:postcode":"08032",
    "sg:province":"Barcelona",
    "wof:name":"Souto Guntin Severino",
    "wof:placetype":"venue"
},
  "geometry": {"coordinates":[2.155600071,41.4257392883],"type":"Point"}
}