{
  "type": "Feature",
  "properties": {
    "iso:country":"ES",
    "sg:address":"Avda Cadiz (de), S/n",
    "sg:city":"Granada",
    "sg:orig_category":"Ropa Para Ni\u00d1os (al Por Menor)",
    "sg:phone":"+34 958 13 07 20",
    "sg:postcode":"18006",
    "sg:province":"Granada",
    "wof:name":"Legaza Sanchez Purificacion",
    "wof:placetype":"venue"
},
  "geometry": {"coordinates":[-3.6031639576,37.1560401917],"type":"Point"}
}