{
  "type": "Feature",
  "properties": {
    "iso:country":"ES",
    "sg:address":"Calle de Dato, 4",
    "sg:city":"Zaragoza",
    "sg:orig_category":"Restaurantes",
    "sg:phone":"+34 976 22 11 07",
    "sg:postcode":"50005",
    "sg:province":"Zaragoza",
    "wof:name":"Antiguo Paraiso S.l.",
    "wof:placetype":"venue"
},
  "geometry": {"coordinates":[-0.8898671865,41.6456604004],"type":"Point"}
}