{
  "type": "Feature",
  "properties": {
    "iso:country":"ES",
    "sg:address":"Carrer de Sant Quirze, 26",
    "sg:city":"Sabadell",
    "sg:orig_category":"Laboratorios Y Trabajos De Fotograf\u00cda, V\u00cddeo Y Cine",
    "sg:phone":"+34 937 27 29 00",
    "sg:postcode":"08201",
    "sg:province":"Barcelona",
    "wof:name":"Alteu Estil Abaloris I Fornituras S.l.",
    "wof:placetype":"venue"
},
  "geometry": {"coordinates":[2.1066963673,41.5464820862],"type":"Point"}
}