{
  "type": "Feature",
  "properties": {
    "addr:full":"Plaz Manuel Becerra, 19 Madrid Madrid 28028",
    "addr:housenumber":"19",
    "addr:postcode":"madrid;28028",
    "addr:street":"Manuel Becerra",
    "iso:country":"ES",
    "sg:address":"Plaz Manuel Becerra, 19",
    "sg:city":"Madrid",
    "sg:orig_category":"Restaurantes",
    "sg:phone":"+34 913 09 12 80",
    "sg:postcode":"28028",
    "sg:province":"Madrid",
    "wof:name":"Mar Vivo De Hosteleria S.l.",
    "wof:placetype":"venue"
},
  "geometry": {"coordinates":[-3.6690459251,40.4276504517],"type":"Point"}
}