{
  "type": "Feature",
  "properties": {
    "addr:full":"Cr Almod-alamillo, Km. 0039,0 Almodovar Campo Ciudad Real 13580",
    "addr:postcode":"13580",
    "addr:street":"Cr Almod-Alamillo Km. 0039,0;Campo",
    "iso:country":"ES",
    "sg:address":"Cr Almod-alamillo, Km. 0039,0",
    "sg:city":"Almodovar Campo",
    "sg:orig_category":"Fabricaci\u00d3n De Quesos",
    "sg:phone":"+34 926 69 83 26",
    "sg:postcode":"13580",
    "sg:province":"Ciudad Real",
    "wof:name":"Qualia Lacteos S.l.u.",
    "wof:placetype":"venue"
},
  "geometry": {"coordinates":[-4.1820688248,38.7115097046],"type":"Point"}
}