{
  "type": "Feature",
  "properties": {
    "iso:country":"ES",
    "sg:address":"Ctra Crevil-torrevieja, Km. 0006,8",
    "sg:city":"Catral",
    "sg:orig_category":"Distribuci\u00d3n De Petr\u00d3leo Y Derivados",
    "sg:phone":"+34 965 72 32 18",
    "sg:postcode":"03158",
    "sg:province":"Alicante",
    "wof:name":"Briogas S. L.",
    "wof:placetype":"venue"
},
  "geometry": {"coordinates":[-0.8036230206,38.1610221863],"type":"Point"}
}