{
  "type": "Feature",
  "properties": {
    "addr:full":"Calle de Mayor, 17 Irun Guip\u00f9zcoa 20304",
    "addr:housenumber":"17",
    "addr:postcode":"20304",
    "addr:street":"Calle De Mayor;Guipu\u0300Zcoa",
    "iso:country":"ES",
    "sg:address":"Calle de Mayor, 17",
    "sg:city":"Irun",
    "sg:orig_category":"Electricidad, Electr\u00d3nica: Suministros (al Por Menor)",
    "sg:phone":"+34 943 63 61 09",
    "sg:postcode":"20304",
    "sg:province":"Guip\u00f9zcoa",
    "wof:name":"Tds Electronicos",
    "wof:placetype":"venue"
},
  "geometry": {"coordinates":[-1.7902489901,43.3380966187],"type":"Point"}
}