{
  "type": "Feature",
  "properties": {
    "addr:full":"Calle de Matadero, S/n Zubia Granada 18140",
    "addr:housenumber":"/ n",
    "addr:postcode":"18140",
    "addr:street":"Calle De Matadero S;Zubia Granada",
    "iso:country":"ES",
    "sg:address":"Calle de Matadero, S/n",
    "sg:city":"Zubia",
    "sg:orig_category":"Fabricaci\u00d3n, Distribuci\u00d3n De Material Para La Climatizaci\u00d3n, Aireaci\u00d3n Y Ventilaci\u00d3n",
    "sg:phone":"+34 958 59 16 84",
    "sg:postcode":"18140",
    "sg:province":"Granada",
    "wof:name":"J.lara Gas S.l.",
    "wof:placetype":"venue"
},
  "geometry": {"coordinates":[-3.5849890709,37.1218681335],"type":"Point"}
}