{
  "type": "Feature",
  "properties": {
    "addr:full":"Avda San Francisco Javier, 22 Sevilla Sevilla 41018",
    "addr:housenumber":"22",
    "addr:postcode":"41018",
    "addr:street":"Avda San Francisco Javier",
    "iso:country":"ES",
    "sg:address":"Avda San Francisco Javier, 22",
    "sg:city":"Sevilla",
    "sg:orig_category":"Edici\u00d3n De Diarios, Revistas, Boletines",
    "sg:phone":"+34 954 66 23 61",
    "sg:postcode":"41018",
    "sg:province":"Sevilla",
    "sg:website":"www.cisspraxis.es",
    "wof:name":"Wolters Kluwer Espa\u00d1a S.a.",
    "wof:placetype":"venue"
},
  "geometry": {"coordinates":[-5.9746484756,37.3791542053],"type":"Point"}
}