{
  "type": "Feature",
  "properties": {
    "iso:country":"ES",
    "sg:address":"Calle de Navarro Rodrigo, 8",
    "sg:city":"Almeria",
    "sg:orig_category":"Ropa Para Ni\u00d1os (al Por Menor)",
    "sg:phone":"+34 950 23 00 83",
    "sg:postcode":"04001",
    "sg:province":"Almer\u00eda",
    "wof:name":"Lopez Pardo Antonio",
    "wof:placetype":"venue"
},
  "geometry": {"coordinates":[-2.4629580975,36.8394775391],"type":"Point"}
}