{
  "type": "Feature",
  "properties": {
    "addr:full":"Calle de Comandante Salvador Carrasco, 9 Ronda M\u00e1laga 29400",
    "addr:housenumber":"9",
    "addr:postcode":"29400",
    "addr:street":"Calle De Comandante Salvador Carrasco;Ronda Ma\u0301Laga",
    "iso:country":"ES",
    "sg:address":"Calle de Comandante Salvador Carrasco, 9",
    "sg:city":"Ronda",
    "sg:orig_category":"Empresas De Carpinter\u00cda",
    "sg:phone":"+34 952 87 10 06",
    "sg:postcode":"29400",
    "sg:province":"M\u00e1laga",
    "wof:name":"Aluminios Hermanos Velasco S.l.",
    "wof:placetype":"venue"
},
  "geometry": {"coordinates":[-5.1657657623,36.7463417053],"type":"Point"}
}