{
  "type": "Feature",
  "properties": {
    "addr:full":"Calle de Collado Mediano, 32 Rozas De Madrid Madrid 28230",
    "addr:housenumber":"32",
    "addr:postcode":"28230",
    "addr:street":"Calle De Collado Mediano",
    "iso:country":"ES",
    "sg:address":"Calle de Collado Mediano, 32",
    "sg:city":"Rozas De Madrid",
    "sg:orig_category":"Inform\u00c1tica (estudios, Servicios, Asesor\u00cda, Formaci\u00d3n)",
    "sg:phone":"+34 916 36 14 40",
    "sg:postcode":"28230",
    "sg:province":"Madrid",
    "wof:name":"Conver Format 98 S.l.",
    "wof:placetype":"venue"
},
  "geometry": {"coordinates":[-3.8746378422,40.4978179932],"type":"Point"}
}