{
  "type": "Feature",
  "properties": {
    "addr:full":"Calle de Conducto, 2 Cartagena Murcia 30201",
    "addr:housenumber":"2",
    "addr:postcode":"30201",
    "addr:street":"Calle De Conducto",
    "iso:country":"ES",
    "sg:address":"Calle de Conducto, 2",
    "sg:city":"Cartagena",
    "sg:orig_category":"Abogados",
    "sg:phone":"+34 968 52 47 52",
    "sg:postcode":"30201",
    "sg:province":"Murcia",
    "wof:name":"Linares Navarro Jose Carlos",
    "wof:placetype":"venue"
},
  "geometry": {"coordinates":[-0.9882839918,37.6027832031],"type":"Point"}
}