{
  "type": "Feature",
  "properties": {
    "addr:full":"Calle de Mayor, 13 Almedina Ciudad Real 13328",
    "addr:housenumber":"13",
    "addr:postcode":"13328",
    "addr:street":"Calle De Mayor",
    "iso:country":"ES",
    "sg:address":"Calle de Mayor, 13",
    "sg:city":"Almedina",
    "sg:orig_category":"Cajas Para Embalar",
    "sg:phone":"+34 926 35 64 25",
    "sg:postcode":"13328",
    "sg:province":"Ciudad Real",
    "wof:name":"Caja Rural De Ciudad Real",
    "wof:placetype":"venue"
},
  "geometry": {"coordinates":[-2.9546160698,38.6243934631],"type":"Point"}
}