{
  "type": "Feature",
  "properties": {
    "iso:country":"ES",
    "sg:address":"Calle de Santa Gema, 2",
    "sg:city":"Alcorcon",
    "sg:classifiers":[
        {
            "category":"Personal",
            "subcategory":"Barber",
            "type":"Services"
        }
    ],
    "sg:phone":"+34 916 43 10 51",
    "sg:postcode":"28921",
    "sg:province":"Madrid",
    "sg:tags":[
        "caballeros",
        "de",
        "peluqueros"
    ],
    "wof:name":"Arellano Garcia Jose Daniel",
    "wof:placetype":"venue"
},
  "geometry": {"coordinates":[-3.8271448612,40.3449935913],"type":"Point"}
}