{
  "type": "Feature",
  "properties": {
    "addr:full":"Calle de Recreo, 33 Bejar Salamanca 37700",
    "addr:housenumber":"33",
    "addr:postcode":"37700",
    "addr:street":"Calle De Recreo",
    "iso:country":"ES",
    "sg:address":"Calle de Recreo, 33",
    "sg:city":"Bejar",
    "sg:orig_category":"Quincaller\u00cda (al Por Menor)",
    "sg:phone":"+34 923 40 02 11",
    "sg:postcode":"37700",
    "sg:province":"Salamanca",
    "wof:name":"Apolinar Fraile S.a.",
    "wof:placetype":"venue"
},
  "geometry": {"coordinates":[-5.7550253868,40.3880004883],"type":"Point"}
}