{
  "type": "Feature",
  "properties": {
    "addr:full":"Pase Delicias (las), 5 Jerez De La Frontera C\u00e1diz 11406",
    "addr:postcode":"11406",
    "addr:street":"Las",
    "iso:country":"ES",
    "sg:address":"Pase Delicias (las), 5",
    "sg:city":"Jerez De La Frontera",
    "sg:orig_category":"T\u00c9cnicos Veterinarios",
    "sg:phone":"+34 956 34 85 47",
    "sg:postcode":"11406",
    "sg:province":"C\u00e1diz",
    "wof:name":"Abad Alfaro Francisco",
    "wof:placetype":"venue"
},
  "geometry": {"coordinates":[-6.104996,36.674183],"type":"Point"}
}