{
  "type": "Feature",
  "properties": {
    "addr:full":"Carrer de Sol, 2 Pobla Claramunt Barcelona 08787",
    "addr:housenumber":"2",
    "addr:postcode":"08787",
    "addr:street":"Carrer De Sol",
    "iso:country":"ES",
    "sg:address":"Carrer de Sol, 2",
    "sg:city":"Pobla Claramunt",
    "sg:orig_category":"Aguas (distribuci\u00d3n, Servicios)",
    "sg:phone":"+34 938 08 71 11",
    "sg:postcode":"08787",
    "sg:province":"Barcelona",
    "wof:name":"Aigua De Rigat S.a",
    "wof:placetype":"venue"
},
  "geometry": {"coordinates":[1.6126612425,41.578414917],"type":"Point"}
}