{
  "type": "Feature",
  "properties": {
    "addr:full":"Gil Y Pablos, 23 Melgar Fernamental Burgos 09100",
    "addr:housenumber":"23",
    "addr:postcode":"09100",
    "addr:street":"Fernamental",
    "iso:country":"ES",
    "sg:address":"Gil Y Pablos, 23",
    "sg:city":"Melgar Fernamental",
    "sg:orig_category":"Iglesia Cat\u00d3lica",
    "sg:phone":"+34 947 37 21 41",
    "sg:postcode":"09100",
    "sg:province":"Burgos",
    "wof:name":"Parroquia De La Asuncion",
    "wof:placetype":"venue"
},
  "geometry": {"coordinates":[-4.2453022003,42.4037704468],"type":"Point"}
}