{
  "type": "Feature",
  "properties": {
    "iso:country":"ES",
    "sg:address":"Fortuna, 12",
    "sg:city":"Pto Sta Maria",
    "sg:orig_category":"Fotograf\u00cda Y Cine: Aparatos, Pel\u00cdculas Y Accesorios (al Por Menor)",
    "sg:phone":"+34 956 54 24 25",
    "sg:postcode":"11500",
    "sg:province":"C\u00e1diz",
    "sg:website":"www.idalyfa.com",
    "wof:name":"Idalyfa S.l.",
    "wof:placetype":"venue"
},
  "geometry": {"coordinates":[-6.2118601799,36.6263847351],"type":"Point"}
}