{
  "type": "Feature",
  "properties": {
    "addr:full":"Rbla Blas Infante, 15 Castelldefels Barcelona 08860",
    "addr:housenumber":"15",
    "addr:postcode":"08860",
    "addr:street":"Rbla Blas Infante",
    "iso:country":"ES",
    "sg:address":"Rbla Blas Infante, 15",
    "sg:city":"Castelldefels",
    "sg:orig_category":"Asociaciones, Organismos Culturales Y Socioeducativos",
    "sg:phone":"+34 936 36 51 00",
    "sg:postcode":"08860",
    "sg:province":"Barcelona",
    "wof:name":"Grup De Dones De Castelldefels",
    "wof:placetype":"venue"
},
  "geometry": {"coordinates":[1.9773770571,41.2874526978],"type":"Point"}
}