{
  "type": "Feature",
  "properties": {
    "iso:country":"ES",
    "sg:address":"Calle de Horno, 6",
    "sg:city":"Pulpi",
    "sg:orig_category":"Reposter\u00cdas",
    "sg:phone":"+34 950 46 40 10",
    "sg:postcode":"04640",
    "sg:province":"Almer\u00eda",
    "wof:name":"Panaderia Crispan S.l.l.",
    "wof:placetype":"venue"
},
  "geometry": {"coordinates":[-1.7451440096,37.4111557007],"type":"Point"}
}