{
  "type": "Feature",
  "properties": {
    "iso:country":"ES",
    "sg:address":"Rond Pilar, 8",
    "sg:city":"Badajoz",
    "sg:orig_category":"M\u00c9dicos: Cirug\u00cda General",
    "sg:phone":"+34 924 23 99 99",
    "sg:postcode":"06002",
    "sg:province":"Badajoz",
    "wof:name":"Martin Rodriguez Jose Maria",
    "wof:placetype":"venue"
},
  "geometry": {"coordinates":[-6.9699621201,38.875289917],"type":"Point"}
}