{
  "type": "Feature",
  "properties": {
    "addr:full":"Calle de Dolores Ibarruri, S/n Cordoba C\u00f3rdoba 14011",
    "addr:housenumber":"s / n",
    "addr:postcode":"14011",
    "addr:street":"Calle De Dolores Ibarruri;Co\u0301Rdoba",
    "iso:country":"ES",
    "sg:address":"Calle de Dolores Ibarruri, S/n",
    "sg:city":"Cordoba",
    "sg:orig_category":"Cajas De Ahorro",
    "sg:phone":"+34 957 76 78 87",
    "sg:postcode":"14011",
    "sg:province":"C\u00f3rdoba",
    "wof:name":"Monte De Piedad Y Caja De Ahorros De Huelva Y Sevilla",
    "wof:placetype":"venue"
},
  "geometry": {"coordinates":[-4.7943434715,37.8962440491],"type":"Point"}
}