{
  "type": "Feature",
  "properties": {
    "addr:full":"Calle de Bonifaz, 22 Santander Cantabria 39003",
    "addr:housenumber":"22",
    "addr:postcode":"39003",
    "addr:street":"Calle De Bonifaz",
    "iso:country":"ES",
    "sg:address":"Calle de Bonifaz, 22",
    "sg:city":"Santander",
    "sg:orig_category":"Arquitectos",
    "sg:phone":"+34 942 31 28 60",
    "sg:postcode":"39003",
    "sg:province":"Cantabria",
    "wof:name":"Garcia-baron Portoles Abilio",
    "wof:placetype":"venue"
},
  "geometry": {"coordinates":[-3.796964407,43.4640235901],"type":"Point"}
}