{
  "type": "Feature",
  "properties": {
    "iso:country":"ES",
    "sg:address":"Carrer de Villa, 9",
    "sg:city":"S. Cugat Valles",
    "sg:orig_category":"Ropa Para Ni\u00d1os (al Por Menor)",
    "sg:phone":"+34 935 90 10 53",
    "sg:postcode":"08172",
    "sg:province":"Barcelona",
    "sg:website":"www.gocco.es",
    "wof:name":"Gocco Confeg S.a.",
    "wof:placetype":"venue"
},
  "geometry": {"coordinates":[2.0795190334,41.4675712585],"type":"Point"}
}