{
  "type": "Feature",
  "properties": {
    "iso:country":"ES",
    "sg:address":"Las Petunias-fase Dos, S/n",
    "sg:city":"San Pedro Alcantara",
    "sg:orig_category":"Promotores Constructores",
    "sg:phone":"+34 952 78 47 10",
    "sg:postcode":"29670",
    "sg:province":"M\u00e1laga",
    "wof:name":"Constructora Inmobiliaria Villanueva S.l.",
    "wof:placetype":"venue"
},
  "geometry": {"coordinates":[-5.003718853,36.4735946655],"type":"Point"}
}