{
  "type": "Feature",
  "properties": {
    "iso:country":"ES",
    "sg:address":"Calle de Francisco De Moncada, 4",
    "sg:city":"Cabezo Torres",
    "sg:orig_category":"Grafistas",
    "sg:phone":"+34 968 30 84 30",
    "sg:postcode":"30110",
    "sg:province":"Murcia",
    "wof:name":"Gsm Comunicacion Grafica C.b.",
    "wof:placetype":"venue"
},
  "geometry": {"coordinates":[-1.1309742928,38.0248794556],"type":"Point"}
}