{
  "type": "Feature",
  "properties": {
    "addr:full":"Ocho, 18 Camarles Tarragona 43894",
    "addr:housenumber":"18",
    "addr:postcode":"43894",
    "addr:street":"Ocho",
    "iso:country":"ES",
    "sg:address":"Ocho, 18",
    "sg:city":"Camarles",
    "sg:orig_category":"Limpieza Con Chorro De Arena Y Con Granalla, Pulido",
    "sg:phone":"+34 977 47 02 35",
    "sg:postcode":"43894",
    "sg:province":"Tarragona",
    "wof:name":"Prats Salvan Ramon",
    "wof:placetype":"venue"
},
  "geometry": {"coordinates":[0.6696299911,40.7704162598],"type":"Point"}
}