{
  "type": "Feature",
  "properties": {
    "addr:full":"Ctra Tarajal (del), 61 Principe Felipe Ceuta 51003",
    "addr:housenumber":"61",
    "addr:postcode":"51003",
    "addr:street":"Ctra Tarajal Del",
    "iso:country":"ES",
    "sg:address":"Ctra Tarajal (del), 61",
    "sg:city":"Principe Felipe",
    "sg:orig_category":"Alimentaci\u00d3n General (al Por Menor)",
    "sg:phone":"+34 956 50 66 55",
    "sg:postcode":"51003",
    "sg:province":"Ceuta",
    "wof:name":"Comercial Anumas Ceuta Sl",
    "wof:placetype":"venue"
},
  "geometry": {"coordinates":[-5.3157300949,35.8891601562],"type":"Point"}
}