{
  "type": "Feature",
  "properties": {
    "addr:full":"Calle de Comandante Fontanes, 7 Coru\u00d1a La Coru\u00f1a 15003",
    "addr:housenumber":"7",
    "addr:postcode":"15003",
    "addr:street":"Calle De Comandante Fontanes;La Corun\u0303A",
    "iso:country":"ES",
    "sg:address":"Calle de Comandante Fontanes, 7",
    "sg:city":"Coru\u00d1a",
    "sg:orig_category":"Ense\u00d1anza, Formaci\u00d3n Profesional: Aprendizaje",
    "sg:phone":"+34 981 21 63 10",
    "sg:postcode":"15003",
    "sg:province":"La Coru\u00f1a",
    "wof:name":"Ministerio De Economia Y Hacienda",
    "wof:placetype":"venue"
},
  "geometry": {"coordinates":[-8.4053792953,43.3696556091],"type":"Point"}
}