{
  "type": "Feature",
  "properties": {
    "addr:full":"Calle de Tirez, 40 Villaca\u00f1as Toledo 45860",
    "addr:housenumber":"40",
    "addr:postcode":"45860",
    "addr:street":"Calle De Tirez",
    "iso:country":"ES",
    "sg:address":"Calle de Tirez, 40",
    "sg:city":"Villaca\u00f1as",
    "sg:orig_category":"Centros Empresariales",
    "sg:phone":"+34 925 16 05 61",
    "sg:postcode":"45860",
    "sg:province":"Toledo",
    "wof:name":"Martin Y Moreno Consultores S. L.",
    "wof:placetype":"venue"
},
  "geometry": {"coordinates":[-3.3339400291,39.618221283],"type":"Point"}
}