{
  "type": "Feature",
  "properties": {
    "addr:full":"Av Alemanya, 1 Palma Islas Baleares 07003",
    "addr:housenumber":"1",
    "addr:postcode":"07003",
    "addr:street":"Av Alemanya",
    "iso:country":"ES",
    "sg:address":"Av Alemanya, 1",
    "sg:city":"Palma",
    "sg:orig_category":"\u00d3ptica: Instrumentos (fabricaci\u00d3n)",
    "sg:phone":"+34 971 72 17 87",
    "sg:postcode":"07003",
    "sg:province":"Islas Baleares",
    "wof:name":"Optica Alemania S. A.",
    "wof:placetype":"venue"
},
  "geometry": {"coordinates":[2.6489300728,39.5786399841],"type":"Point"}
}