{
  "type": "Feature",
  "properties": {
    "addr:full":"Plaz Espa\u00d1a, 25 Sepulveda Segovia 40300",
    "addr:housenumber":"25",
    "addr:postcode":"40300",
    "addr:street":"Plaz Espan\u0303A",
    "iso:country":"ES",
    "sg:address":"Plaz Espa\u00d1a, 25",
    "sg:city":"Sepulveda",
    "sg:orig_category":"Alimentaci\u00d3n General (al Por Menor)",
    "sg:phone":"+34 921 54 00 17",
    "sg:postcode":"40300",
    "sg:province":"Segovia",
    "wof:name":"Sanz Manrique Domingo",
    "wof:placetype":"venue"
},
  "geometry": {"coordinates":[-3.7487390041,41.2972755432],"type":"Point"}
}