{
  "type": "Feature",
  "properties": {
    "iso:country":"ES",
    "sg:address":"Calle de Mi\u00d1o, 15",
    "sg:city":"Ajalvir",
    "sg:orig_category":"Asesor\u00cda Para La Organizaci\u00d3n Y Gesti\u00d3n Del Transporte",
    "sg:phone":"+34 918 84 30 94",
    "sg:postcode":"28864",
    "sg:province":"Madrid",
    "wof:name":"Stu Expres Service S. A.",
    "wof:placetype":"venue"
},
  "geometry": {"coordinates":[-3.4800050259,40.5013999939],"type":"Point"}
}