{
  "type": "Feature",
  "properties": {
    "addr:full":"Ed. Val Aran, S/n Vielha Lleida 25530",
    "addr:housenumber":"s / n",
    "addr:postcode":"25530",
    "iso:country":"ES",
    "sg:address":"Ed. Val Aran, S/n",
    "sg:city":"Vielha",
    "sg:orig_category":"Fabricaci\u00d3n, Venta, Instalaci\u00d3n De R\u00d3tulos, De R\u00d3tulos Luminosos",
    "sg:phone":"+34 973 64 28 41",
    "sg:postcode":"25530",
    "sg:province":"Lleida",
    "wof:name":"Aran Y Arte S.l.",
    "wof:placetype":"venue"
},
  "geometry": {"coordinates":[0.79727,42.7036247253],"type":"Point"}
}