{
  "type": "Feature",
  "properties": {
    "iso:country":"ES",
    "sg:address":"Calle de Pareja, S/n",
    "sg:city":"Loja",
    "sg:orig_category":"Empresas De Carpinter\u00cda De Madera",
    "sg:phone":"+34 958 32 56 12",
    "sg:postcode":"18300",
    "sg:province":"Granada",
    "wof:name":"Galvez Cobos Antonio Jesus",
    "wof:placetype":"venue"
},
  "geometry": {"coordinates":[-4.1509199142,37.1719284058],"type":"Point"}
}