{
  "type": "Feature",
  "properties": {
    "iso:country":"ES",
    "sg:address":"Avda Madrid, 2",
    "sg:city":"Logro\u00f1o",
    "sg:orig_category":"Supermercados Y Hipermercados",
    "sg:phone":"+34 941 22 45 00",
    "sg:postcode":"26006",
    "sg:province":"La Rioja",
    "wof:name":"Supermercados Champion S.a.",
    "wof:placetype":"venue"
},
  "geometry": {"coordinates":[-2.4479980469,42.4554977417],"type":"Point"}
}