{
  "type": "Feature",
  "properties": {
    "addr:full":"Avda Colon, 11 Montijo Badajoz 06480",
    "addr:housenumber":"11",
    "addr:postcode":"06480",
    "addr:street":"Avda Colon",
    "iso:country":"ES",
    "sg:address":"Avda Colon, 11",
    "sg:city":"Montijo",
    "sg:orig_category":"Venta, Montaje De Neum\u00c1ticos",
    "sg:phone":"+34 924 45 90 15",
    "sg:postcode":"06480",
    "sg:province":"Badajoz",
    "sg:website":"www.grupoavenida.com",
    "wof:name":"Neumaticos Avenida S.l.",
    "wof:placetype":"venue"
},
  "geometry": {"coordinates":[-6.6206440926,38.9016456604],"type":"Point"}
}