{
  "type": "Feature",
  "properties": {
    "addr:full":"Tafalla, 14 Iru\u00f1a Navarra 31004",
    "addr:housenumber":"14",
    "addr:postcode":"31004",
    "addr:street":"Tafalla",
    "iso:country":"ES",
    "sg:address":"Tafalla, 14",
    "sg:city":"Iru\u00f1a",
    "sg:orig_category":"Lencer\u00cda Femenina, Corseter\u00cda, Trajes De Ba\u00d1o (al Por Menor)",
    "sg:phone":"+34 948 24 78 26",
    "sg:postcode":"31004",
    "sg:province":"Navarra",
    "wof:name":"Ab S.l.",
    "wof:placetype":"venue"
},
  "geometry": {"coordinates":[-1.637155,42.812317],"type":"Point"}
}