{
  "type": "Feature",
  "properties": {
    "addr:full":"Schez. Oca\u00f1a, 7 Bejar Salamanca 37700",
    "addr:housenumber":"7",
    "addr:postcode":"37700",
    "addr:street":"Ocan\u0303A",
    "iso:country":"ES",
    "sg:address":"Schez. Oca\u00f1a, 7",
    "sg:city":"Bejar",
    "sg:orig_category":"Ropa Para Se\u00d1oras (al Por Menor)",
    "sg:phone":"+34 923 40 22 26",
    "sg:postcode":"37700",
    "sg:province":"Salamanca",
    "wof:name":"Soria Gonzalez Tomas",
    "wof:placetype":"venue"
},
  "geometry": {"coordinates":[-5.7694392204,40.3868637085],"type":"Point"}
}