{
  "type": "Feature",
  "properties": {
    "addr:full":"Carrer de Senia Del Barral, 36 Lloret Mar Girona 17310",
    "addr:housenumber":"36",
    "addr:postcode":"17310",
    "addr:street":"Carrer De Senia Del Barral",
    "iso:country":"ES",
    "sg:address":"Carrer de Senia Del Barral, 36",
    "sg:city":"Lloret Mar",
    "sg:orig_category":"Laboratorios Y Cl\u00cdnicas Veterinarias",
    "sg:phone":"+34 972 36 80 07",
    "sg:postcode":"17310",
    "sg:province":"Girona",
    "wof:name":"Macia Termes Rosa",
    "wof:placetype":"venue"
},
  "geometry": {"coordinates":[2.8510699272,41.7014083862],"type":"Point"}
}