{
  "type": "Feature",
  "properties": {
    "addr:full":"Carr Maria Auxiliadora, 166 Badalona Barcelona 08912",
    "addr:housenumber":"166",
    "addr:postcode":"08912",
    "addr:street":"Carr Maria Auxiliadora",
    "iso:country":"ES",
    "sg:address":"Carr Maria Auxiliadora, 166",
    "sg:city":"Badalona",
    "sg:orig_category":"Barnizadores",
    "sg:phone":"+34 933 87 02 03",
    "sg:postcode":"08912",
    "sg:province":"Barcelona",
    "wof:name":"Plazas Lopez Juan",
    "wof:placetype":"venue"
},
  "geometry": {"coordinates":[2.2390499115,41.4431266785],"type":"Point"}
}