{
  "type": "Feature",
  "properties": {
    "iso:country":"ES",
    "sg:address":"Carrer de Regal, 71",
    "sg:city":"Palma",
    "sg:orig_category":"Electrodom\u00c9sticos (al Por Menor)",
    "sg:phone":"+34 971 42 06 49",
    "sg:postcode":"07008",
    "sg:province":"Islas Baleares",
    "wof:name":"Recreativos Jayda S.l.",
    "wof:placetype":"venue"
},
  "geometry": {"coordinates":[2.6712450981,39.5766716003],"type":"Point"}
}