{
  "type": "Feature",
  "properties": {
    "addr:full":"Cllo Martinez, 5 Antequera M\u00e1laga 29200",
    "addr:postcode":"29200",
    "addr:street":"Ma\u0301Laga",
    "iso:country":"ES",
    "sg:address":"Cllo Martinez, 5",
    "sg:city":"Antequera",
    "sg:orig_category":"Ense\u00d1anza Variada",
    "sg:phone":"+34 952 84 62 29",
    "sg:postcode":"29200",
    "sg:province":"M\u00e1laga",
    "wof:name":"Sanchez Compa\u00f1a Maria Teresa",
    "wof:placetype":"venue"
},
  "geometry": {"coordinates":[-4.5595788956,37.0201072693],"type":"Point"}
}