{
  "type": "Feature",
  "properties": {
    "iso:country":"ES",
    "sg:address":"Calle de Genova, 7",
    "sg:city":"Madrid",
    "sg:orig_category":"Universidades",
    "sg:phone":"+34 913 10 03 20",
    "sg:postcode":"28004",
    "sg:province":"Madrid",
    "sg:website":"www.torresaza.com",
    "wof:name":"Aza Casablanca Antonio",
    "wof:placetype":"venue"
},
  "geometry": {"coordinates":[-3.6948590279,40.4273529053],"type":"Point"}
}