{
  "type": "Feature",
  "properties": {
    "iso:country":"ES",
    "sg:address":"Riera Del Pare Fita, 56",
    "sg:city":"Arenys Mar",
    "sg:orig_category":"Fabricaci\u00d3n De Mobiliario De Oficina",
    "sg:phone":"+34 937 95 70 66",
    "sg:postcode":"08350",
    "sg:province":"Barcelona",
    "wof:name":"Distribucions Per Detalls S. A.",
    "wof:placetype":"venue"
},
  "geometry": {"coordinates":[2.5476779938,41.583820343],"type":"Point"}
}