{
  "type": "Feature",
  "properties": {
    "iso:country":"ES",
    "sg:address":"Calle de Natalio Rivas, 29",
    "sg:city":"Adra",
    "sg:orig_category":"Farmacias",
    "sg:phone":"+34 950 40 06 25",
    "sg:postcode":"04770",
    "sg:province":"Almer\u00eda",
    "wof:name":"Guillen Esturillo Juan Maria",
    "wof:placetype":"venue"
},
  "geometry": {"coordinates":[-3.0152490139,36.7488365173],"type":"Point"}
}