{
  "type": "Feature",
  "properties": {
    "addr:full":"Calle de Manuel Ocharan, S/n Cain De Valdeon Le\u00f3n 24915",
    "addr:housenumber":"s / n",
    "addr:postcode":"24915",
    "addr:street":"Calle De Manuel Ocharan",
    "iso:country":"ES",
    "sg:address":"Calle de Manuel Ocharan, S/n",
    "sg:city":"Cain De Valdeon",
    "sg:orig_category":"Centros De Educaci\u00d3n Especial",
    "sg:phone":"+34 987 74 27 64",
    "sg:postcode":"24915",
    "sg:province":"Le\u00f3n",
    "wof:name":"Cra Posada De Valdeon",
    "wof:placetype":"venue"
},
  "geometry": {"coordinates":[-4.9049868584,43.2130775452],"type":"Point"}
}