{
  "type": "Feature",
  "properties": {
    "iso:country":"ES",
    "sg:address":"Calle de Eduardo Dato, 18",
    "sg:city":"Vitoria-gasteiz",
    "sg:orig_category":"Delineantes",
    "sg:phone":"+34 945 13 45 84",
    "sg:postcode":"01005",
    "sg:province":"\u00c1lava",
    "wof:name":"Eskil Inter S. A.",
    "wof:placetype":"venue"
},
  "geometry": {"coordinates":[-2.67258811,42.8443717957],"type":"Point"}
}