{
  "type": "Feature",
  "properties": {
    "iso:country":"ES",
    "sg:address":"Avda Ancha De Castelar, 32",
    "sg:city":"San Vicente Del Raspeig-sant Vicent Del Raspeig",
    "sg:orig_category":"Cortinas, Visillos Y Tejidos Para Muebles (al Por Menor)",
    "sg:phone":"+34 965 66 98 19",
    "sg:postcode":"03690",
    "sg:province":"Alicante",
    "wof:name":"Guijarro Baeza Teresa",
    "wof:placetype":"venue"
},
  "geometry": {"coordinates":[-0.5213320255,38.3961868286],"type":"Point"}
}