{
  "type": "Feature",
  "properties": {
    "iso:country":"ES",
    "sg:address":"Ctra. Gijon-sevilla, 4",
    "sg:city":"Aldeaseca Armu\u00f1a",
    "sg:orig_category":"Distribuci\u00d3n De Petr\u00d3leo Y Derivados",
    "sg:phone":"+34 923 22 32 89",
    "sg:postcode":"37189",
    "sg:province":"Salamanca",
    "wof:name":"Estacion De Servicio El Helmantico S.l.",
    "wof:placetype":"venue"
},
  "geometry": {"coordinates":[-5.6705870628,41.0207595825],"type":"Point"}
}