{
  "type": "Feature",
  "properties": {
    "addr:full":"Calle de San Lesmes, 1 Burgos Burgos 09004",
    "addr:housenumber":"1",
    "addr:postcode":"09004",
    "addr:street":"Calle De San Lesmes",
    "iso:country":"ES",
    "sg:address":"Calle de San Lesmes, 1",
    "sg:city":"Burgos",
    "sg:orig_category":"Sociedades Y Organismos Burs\u00c1tiles",
    "sg:phone":"+34 947 25 60 30",
    "sg:postcode":"09004",
    "sg:province":"Burgos",
    "sg:website":"www.morganstanley.es",
    "wof:name":"Morgan Stanley S.v.s.a.u.",
    "wof:placetype":"venue"
},
  "geometry": {"coordinates":[-3.6963229179,42.3418388367],"type":"Point"}
}