{
  "type": "Feature",
  "properties": {
    "iso:country":"ES",
    "sg:address":"Plaz Carbayon Del, 6",
    "sg:city":"Oviedo",
    "sg:orig_category":"Abogados",
    "sg:phone":"+34 985 21 22 14",
    "sg:postcode":"33001",
    "sg:province":"Asturias",
    "wof:name":"Linares Guallart Maria Eugenia",
    "wof:placetype":"venue"
},
  "geometry": {"coordinates":[-5.8464198112,43.3667869568],"type":"Point"}
}