{
  "type": "Feature",
  "properties": {
    "iso:country":"ES",
    "sg:address":"Calle de Arrandi, 24",
    "sg:city":"Barakaldo",
    "sg:orig_category":"Abogados",
    "sg:phone":"+34 944 38 29 70",
    "sg:postcode":"48901",
    "sg:province":"Vizcaya",
    "wof:name":"Hilario Rodriguez Ramon",
    "wof:placetype":"venue"
},
  "geometry": {"coordinates":[-2.9862527847,43.2955856323],"type":"Point"}
}