{
  "type": "Feature",
  "properties": {
    "addr:full":"Rua Colon, 10 Carballo La Coru\u00f1a 15100",
    "addr:housenumber":"10",
    "addr:postcode":"15100",
    "addr:street":"Rua Colon;La Corun\u0303A",
    "iso:country":"ES",
    "sg:address":"Rua Colon, 10",
    "sg:city":"Carballo",
    "sg:orig_category":"Partidos Pol\u00cdticos",
    "sg:phone":"+34 981 75 66 99",
    "sg:postcode":"15100",
    "sg:province":"La Coru\u00f1a",
    "wof:name":"Partido Popular",
    "wof:placetype":"venue"
},
  "geometry": {"coordinates":[-8.6898136139,43.2132606506],"type":"Point"}
}