{
  "type": "Feature",
  "properties": {
    "iso:country":"ES",
    "sg:address":"Calle de Santiago De Chile (de), S/n",
    "sg:city":"Jerez De La Frontera",
    "sg:orig_category":"Internados & Ense\u00d1anza Privada",
    "sg:phone":"+34 956 30 81 04",
    "sg:postcode":"11407",
    "sg:province":"C\u00e1diz",
    "wof:name":"Centro Internacional El Astillo",
    "wof:placetype":"venue"
},
  "geometry": {"coordinates":[-6.1219792366,36.7055397034],"type":"Point"}
}