{
  "type": "Feature",
  "properties": {
    "addr:full":"Carrer de Llanera, 70 Sabadell Barcelona 08207",
    "addr:housenumber":"70",
    "addr:postcode":"08207",
    "addr:street":"Carrer De Llanera",
    "iso:country":"ES",
    "sg:address":"Carrer de Llanera, 70",
    "sg:city":"Sabadell",
    "sg:orig_category":"Molduras, Junquillos, Listones Y Molduras Perforadas",
    "sg:phone":"+34 937 17 28 98",
    "sg:postcode":"08207",
    "sg:province":"Barcelona",
    "wof:name":"Pe\u00f1a Sola Rosa Maria",
    "wof:placetype":"venue"
},
  "geometry": {"coordinates":[2.0908529758,41.5688438416],"type":"Point"}
}