{
  "type": "Feature",
  "properties": {
    "iso:country":"ES",
    "sg:address":"Ctra Alicante-cartagena, Km. 0032,7",
    "sg:city":"Guardamar Segura",
    "sg:orig_category":"Distribuci\u00d3n De Petr\u00d3leo Y Derivados",
    "sg:phone":"+34 965 72 83 39",
    "sg:postcode":"03140",
    "sg:province":"Alicante",
    "wof:name":"Agip Espa\u00d1a S.a.",
    "wof:placetype":"venue"
},
  "geometry": {"coordinates":[-0.6602991223,38.1088104248],"type":"Point"}
}