{
  "type": "Feature",
  "properties": {
    "iso:country":"ES",
    "sg:address":"Calle de Hermanos Pinzon (de Los), 17",
    "sg:city":"Mostoles",
    "sg:orig_category":"Papeler\u00cdas, Librer\u00cdas",
    "sg:phone":"+34 914 96 94 71",
    "sg:postcode":"28936",
    "sg:province":"Madrid",
    "wof:name":"Prensa Y Papeleria Cervantes",
    "wof:placetype":"venue"
},
  "geometry": {"coordinates":[-3.8519809246,40.3225364685],"type":"Point"}
}