{
  "type": "Feature",
  "properties": {
    "addr:full":"Avda Pais Valencia (del), 21 Onda Castell\u00f3n 12200",
    "addr:postcode":"12200",
    "addr:street":"Avda Pais;Del;Castello\u0301N",
    "iso:country":"ES",
    "sg:address":"Avda Pais Valencia (del), 21",
    "sg:city":"Onda",
    "sg:classifiers":[
        {
            "category":"Autos & Motor Vehicles",
            "subcategory":"Automobile Sales",
            "type":"Retail Goods"
        }
    ],
    "sg:phone":"+34 964 77 19 24",
    "sg:postcode":"12200",
    "sg:province":"Castell\u00f3n",
    "wof:name":"Autoescuela Mijares S.l.",
    "wof:placetype":"venue"
},
  "geometry": {"coordinates":[-0.2606877089,39.9652061462],"type":"Point"}
}