{
  "type": "Feature",
  "properties": {
    "iso:country":"ES",
    "sg:address":"Autop De Colon, 33",
    "sg:city":"Albolote",
    "sg:orig_category":"Zapatos (al Por Menor)",
    "sg:phone":"+34 958 46 84 57",
    "sg:postcode":"18220",
    "sg:province":"Granada",
    "wof:name":"Alvarez Ollero Roberto",
    "wof:placetype":"venue"
},
  "geometry": {"coordinates":[-3.6521158218,37.230682373],"type":"Point"}
}