{
  "type": "Feature",
  "properties": {
    "addr:full":"Avda Madrid, 43 Daroca Zaragoza 50360",
    "addr:housenumber":"43",
    "addr:postcode":"50360",
    "addr:street":"Avda Madrid",
    "iso:country":"ES",
    "sg:address":"Avda Madrid, 43",
    "sg:city":"Daroca",
    "sg:orig_category":"Fabricaci\u00d3n De Pastas Alimentarias",
    "sg:phone":"+34 976 80 20 28",
    "sg:postcode":"50360",
    "sg:province":"Zaragoza",
    "sg:website":"www.pastasromero.com",
    "wof:name":"Pastas Alimenticias Romero S. A.",
    "wof:placetype":"venue"
},
  "geometry": {"coordinates":[-1.4178349972,41.1106414795],"type":"Point"}
}