{
  "type": "Feature",
  "properties": {
    "iso:country":"ES",
    "sg:address":"Poligono, 32",
    "sg:city":"Aldaia",
    "sg:orig_category":"Muebles",
    "sg:phone":"+34 961 51 85 17",
    "sg:postcode":"46960",
    "sg:province":"Valencia",
    "wof:name":"Vitrilux S.l.",
    "wof:placetype":"venue"
},
  "geometry": {"coordinates":[-0.4712519944,39.4689102173],"type":"Point"}
}