{
  "type": "Feature",
  "properties": {
    "iso:country":"ES",
    "sg:address":"Carr Alaior, 38",
    "sg:city":"Ciutadella Menorca",
    "sg:orig_category":"Telas Y Sedas (al Por Menor)",
    "sg:phone":"+34 971 38 28 24",
    "sg:postcode":"07760",
    "sg:province":"Islas Baleares",
    "wof:name":"Salord Bosch Maria",
    "wof:placetype":"venue"
},
  "geometry": {"coordinates":[3.8416149616,40.0027542114],"type":"Point"}
}