{
  "type": "Feature",
  "properties": {
    "addr:full":"Calle de Eras, 15 Val De Santo Domingo Toledo 45519",
    "addr:housenumber":"15",
    "addr:postcode":"45519",
    "addr:street":"Calle De Eras",
    "iso:country":"ES",
    "sg:address":"Calle de Eras, 15",
    "sg:city":"Val De Santo Domingo",
    "sg:orig_category":"Fabricaci\u00d3n De Muebles",
    "sg:phone":"+34 925 77 90 34",
    "sg:postcode":"45519",
    "sg:province":"Toledo",
    "wof:name":"Mucoba S. L.",
    "wof:placetype":"venue"
},
  "geometry": {"coordinates":[-4.2703337669,40.0481987],"type":"Point"}
}