{
  "type": "Feature",
  "properties": {
    "addr:full":"Entd Roseldo, 4 Castellar-oliveral Valencia 46026",
    "addr:housenumber":"4",
    "addr:postcode":"46026",
    "addr:street":"Castellar-Oliveral",
    "iso:country":"ES",
    "sg:address":"Entd Roseldo, 4",
    "sg:city":"Castellar-oliveral",
    "sg:orig_category":"Empresas De Carpinter\u00cda Met\u00c1lica",
    "sg:phone":"+34 963 96 14 02",
    "sg:postcode":"46026",
    "sg:province":"Valencia",
    "wof:name":"Moreno Morcillo Daniel",
    "wof:placetype":"venue"
},
  "geometry": {"coordinates":[-0.3618139923,39.4263076782],"type":"Point"}
}