{
  "type": "Feature",
  "properties": {
    "iso:country":"ES",
    "sg:address":"Avda Santa Isabel, 90",
    "sg:city":"Zaragoza",
    "sg:orig_category":"Panader\u00cdas, Panader\u00cdas",
    "sg:phone":"+34 976 57 72 66",
    "sg:postcode":"50016",
    "sg:province":"Zaragoza",
    "wof:name":"Sainz Martinez Sagrario",
    "wof:placetype":"venue"
},
  "geometry": {"coordinates":[-0.8313609958,41.6667823792],"type":"Point"}
}