{
  "type": "Feature",
  "properties": {
    "addr:full":"Avda Salamanca, 75 Ciudad Rodrigo Salamanca 37500",
    "addr:housenumber":"75",
    "addr:postcode":"37500",
    "addr:street":"Avda Salamanca",
    "iso:country":"ES",
    "sg:address":"Avda Salamanca, 75",
    "sg:city":"Ciudad Rodrigo",
    "sg:orig_category":"Transportes Por V\u00cdas Navegables",
    "sg:phone":"+34 923 46 11 48",
    "sg:postcode":"37500",
    "sg:province":"Salamanca",
    "wof:name":"Alaejos Paniagua Julian",
    "wof:placetype":"venue"
},
  "geometry": {"coordinates":[-6.5270342827,40.6057319641],"type":"Point"}
}