{
  "type": "Feature",
  "properties": {
    "addr:full":"Carrer de Franklin, 10 Zona Industrial Barcelona 08397",
    "addr:housenumber":"10",
    "addr:postcode":"08397",
    "addr:street":"Carrer De Franklin",
    "iso:country":"ES",
    "sg:address":"Carrer de Franklin, 10",
    "sg:city":"Zona Industrial",
    "sg:orig_category":"Empresas De Carpinter\u00cda",
    "sg:phone":"+34 937 62 49 11",
    "sg:postcode":"08397",
    "sg:province":"Barcelona",
    "wof:name":"Fusteria Villaret S.l.",
    "wof:placetype":"venue"
},
  "geometry": {"coordinates":[2.6924219131,41.6221199036],"type":"Point"}
}