{
  "type": "Feature",
  "properties": {
    "addr:full":"Calle de San Rafael, 14 S. Fernando C\u00e1diz 11100",
    "addr:housenumber":"14",
    "addr:postcode":"11100",
    "addr:street":"Calle De San Rafael;S. Fernando Ca\u0301Diz",
    "iso:country":"ES",
    "sg:address":"Calle de San Rafael, 14",
    "sg:city":"S. Fernando",
    "sg:orig_category":"Carnicer\u00cdas, Carnicer\u00cdas",
    "sg:phone":"+34 956 88 64 76",
    "sg:postcode":"11100",
    "sg:province":"C\u00e1diz",
    "wof:name":"Sa\u00f1udo Vega Pastora",
    "wof:placetype":"venue"
},
  "geometry": {"coordinates":[-6.195789814,36.4688262939],"type":"Point"}
}