{
  "type": "Feature",
  "properties": {
    "iso:country":"ES",
    "sg:address":"Calle de Mayor, 72",
    "sg:city":"Almaden",
    "sg:orig_category":"Agentes Generales De Seguros",
    "sg:phone":"+34 926 71 23 14",
    "sg:postcode":"13400",
    "sg:province":"Ciudad Real",
    "wof:name":"Murillo Rodriguez Ignacio",
    "wof:placetype":"venue"
},
  "geometry": {"coordinates":[-4.833717823,38.7755699158],"type":"Point"}
}