{
  "type": "Feature",
  "properties": {
    "addr:full":"Avda Navarra, 12 Logro\u00f1o La Rioja 26001",
    "addr:housenumber":"12",
    "addr:postcode":"26001",
    "addr:street":"Avda Navarra;Rioja",
    "iso:country":"ES",
    "sg:address":"Avda Navarra, 12",
    "sg:city":"Logro\u00f1o",
    "sg:orig_category":"Fotocopias, Reprograf\u00cda",
    "sg:phone":"+34 941 23 06 90",
    "sg:postcode":"26001",
    "sg:province":"La Rioja",
    "wof:name":"Romarlovi S.l.",
    "wof:placetype":"venue"
},
  "geometry": {"coordinates":[-2.4415099621,42.467048645],"type":"Point"}
}