{
  "type": "Feature",
  "properties": {
    "addr:full":"Calle de Irala, 8 Bilbao Vizcaya 48012",
    "addr:housenumber":"8",
    "addr:postcode":"48012",
    "addr:street":"Calle De Irala",
    "iso:country":"ES",
    "sg:address":"Calle de Irala, 8",
    "sg:city":"Bilbao",
    "sg:orig_category":"Ense\u00d1anza, Formaci\u00d3n Profesional: Aprendizaje",
    "sg:phone":"+34 944 10 00 34",
    "sg:postcode":"48012",
    "sg:province":"Vizcaya",
    "wof:name":"Padres Franciscanos Iralabarri",
    "wof:placetype":"venue"
},
  "geometry": {"coordinates":[-2.9364407063,43.2546920776],"type":"Point"}
}