{
  "type": "Feature",
  "properties": {
    "addr:full":"Ctra Prat, 39 Viladecans Barcelona 08840",
    "addr:housenumber":"39",
    "addr:postcode":"08840",
    "addr:street":"Ctra Prat",
    "iso:country":"ES",
    "sg:address":"Ctra Prat, 39",
    "sg:city":"Viladecans",
    "sg:orig_category":"Producci\u00d3n De Abonos Y De Fertilizantes",
    "sg:phone":"+34 936 58 07 97",
    "sg:postcode":"08840",
    "sg:province":"Barcelona",
    "wof:name":"Garrigosa Valls Jose",
    "wof:placetype":"venue"
},
  "geometry": {"coordinates":[2.0265200138,41.3170394897],"type":"Point"}
}