{
  "type": "Feature",
  "properties": {
    "iso:country":"ES",
    "sg:address":"Carrer de Navarra, 63",
    "sg:city":"Granollers",
    "sg:orig_category":"Confecci\u00d3n De Botones",
    "sg:phone":"+34 938 70 12 66",
    "sg:postcode":"08401",
    "sg:province":"Barcelona",
    "wof:name":"Pearly Gold S.l.",
    "wof:placetype":"venue"
},
  "geometry": {"coordinates":[2.2848548889,41.6038818359],"type":"Point"}
}