{
  "type": "Feature",
  "properties": {
    "iso:country":"ES",
    "sg:address":"Calle de San Bernardo, 19",
    "sg:city":"Palmas De Gran Canaria",
    "sg:orig_category":"Supermercados Y Hipermercados",
    "sg:phone":"+34 928 36 68 52",
    "sg:postcode":"35002",
    "sg:province":"Las Palmas",
    "wof:name":"Establecimientos La Garriguella S. L.",
    "wof:placetype":"venue"
},
  "geometry": {"coordinates":[-15.4180059433,28.1051216125],"type":"Point"}
}