{
  "type": "Feature",
  "properties": {
    "addr:full":"Calle de San Andres, 139 Coru\u00d1a La Coru\u00f1a 15003",
    "addr:housenumber":"139",
    "addr:postcode":"15003",
    "addr:street":"Calle De San Andres;La Corun\u0303A",
    "iso:country":"ES",
    "sg:address":"Calle de San Andres, 139",
    "sg:city":"Coru\u00d1a",
    "sg:orig_category":"Arquitectos",
    "sg:phone":"+34 981 22 75 25",
    "sg:postcode":"15003",
    "sg:province":"La Coru\u00f1a",
    "wof:name":"Marti\u00f1an Soler Jose Manuel",
    "wof:placetype":"venue"
},
  "geometry": {"coordinates":[-8.4048576355,43.3681030273],"type":"Point"}
}