{
  "type": "Feature",
  "properties": {
    "addr:full":"F. Daoiz, 3 Iru\u00f1a Navarra 31015",
    "addr:housenumber":"3",
    "addr:postcode":"31015",
    "addr:street":"F. Daoiz",
    "iso:country":"ES",
    "sg:address":"F. Daoiz, 3",
    "sg:city":"Iru\u00f1a",
    "sg:orig_category":"Carnicer\u00cdas, Carnicer\u00cdas",
    "sg:phone":"+34 948 14 41 62",
    "sg:postcode":"31015",
    "sg:province":"Navarra",
    "wof:name":"Buldain Miqueo Miguel",
    "wof:placetype":"venue"
},
  "geometry": {"coordinates":[-1.6242640018,42.8301048279],"type":"Point"}
}