{
  "type": "Feature",
  "properties": {
    "addr:full":"Calle de Garcia Ortu\u00d1o, 1 Catral Alicante 03158",
    "addr:housenumber":"1",
    "addr:postcode":"03158",
    "addr:street":"Calle De Garcia Ortun\u0303O",
    "iso:country":"ES",
    "sg:address":"Calle de Garcia Ortu\u00d1o, 1",
    "sg:city":"Catral",
    "sg:orig_category":"Abogados",
    "sg:phone":"+34 965 72 35 19",
    "sg:postcode":"03158",
    "sg:province":"Alicante",
    "wof:name":"Salinas Garcia Maria Asuncion",
    "wof:placetype":"venue"
},
  "geometry": {"coordinates":[-0.803556025,38.1592903137],"type":"Point"}
}