{
  "type": "Feature",
  "properties": {
    "iso:country":"ES",
    "sg:address":"Carrer de Narcis Giralt, 9",
    "sg:city":"Sabadell",
    "sg:orig_category":"Abogados",
    "sg:phone":"+34 937 46 60 95",
    "sg:postcode":"08202",
    "sg:province":"Barcelona",
    "wof:name":"Domingo Hernando Luisa",
    "wof:placetype":"venue"
},
  "geometry": {"coordinates":[2.1104199886,41.5463867188],"type":"Point"}
}