{
  "type": "Feature",
  "properties": {
    "iso:country":"ES",
    "sg:address":"Calle de Jose Luis Ortiz Massaguer, 4",
    "sg:city":"Ronda",
    "sg:orig_category":"Muebles",
    "sg:phone":"+34 952 87 34 34",
    "sg:postcode":"29400",
    "sg:province":"M\u00e1laga",
    "wof:name":"Marquez Torrealba Alfonso",
    "wof:placetype":"venue"
},
  "geometry": {"coordinates":[-5.1532549858,36.748878479],"type":"Point"}
}