{
  "type": "Feature",
  "properties": {
    "addr:full":"Calle de San Rafael, 80 Villacarrillo Ja\u00e9n 23300",
    "addr:housenumber":"80",
    "addr:postcode":"23300",
    "addr:street":"Calle De San Rafael;Jae\u0301N",
    "iso:country":"ES",
    "sg:address":"Calle de San Rafael, 80",
    "sg:city":"Villacarrillo",
    "sg:orig_category":"Cajas De Ahorro",
    "sg:phone":"+34 953 44 40 02",
    "sg:postcode":"23300",
    "sg:province":"Ja\u00e9n",
    "sg:website":"www.cajaen.es",
    "wof:name":"Caja De Jaen",
    "wof:placetype":"venue"
},
  "geometry": {"coordinates":[-3.0824480057,38.1152114868],"type":"Point"}
}