{
  "type": "Feature",
  "properties": {
    "addr:full":"Carrer de Sant Isidre, 79 Sabadell Barcelona 08208",
    "addr:housenumber":"79",
    "addr:postcode":"08208",
    "addr:street":"Carrer De Sant Isidre",
    "iso:country":"ES",
    "sg:address":"Carrer de Sant Isidre, 79",
    "sg:city":"Sabadell",
    "sg:orig_category":"Doctores En Medicina",
    "sg:phone":"+34 937 23 68 12",
    "sg:postcode":"08208",
    "sg:province":"Barcelona",
    "wof:name":"Falgueras Batlle Antonio",
    "wof:placetype":"venue"
},
  "geometry": {"coordinates":[2.1000099182,41.5530128479],"type":"Point"}
}