{
  "type": "Feature",
  "properties": {
    "addr:full":"Calle de Libreros, 5 Madrid Madrid 28004",
    "addr:housenumber":"5",
    "addr:postcode":"28004",
    "addr:street":"Calle De Libreros",
    "iso:country":"ES",
    "sg:address":"Calle de Libreros, 5",
    "sg:city":"Madrid",
    "sg:orig_category":"Empresarios Y Productoras De Espect\u00c1culos",
    "sg:phone":"+34 915 21 88 21",
    "sg:postcode":"28004",
    "sg:province":"Madrid",
    "wof:name":"Mateos Mateos Carmen",
    "wof:placetype":"venue"
},
  "geometry": {"coordinates":[-3.7066760063,40.4217147827],"type":"Point"}
}