{
  "type": "Feature",
  "properties": {
    "addr:full":"P. La Villa, S/n Huetor-tajar Granada 18360",
    "addr:housenumber":"s",
    "addr:postcode":"18360",
    "addr:street":"P.;/ N Huetor-Tajar",
    "iso:country":"ES",
    "sg:address":"P. La Villa, S/n",
    "sg:city":"Huetor-tajar",
    "sg:orig_category":"Centros De Reservas Hoteleras",
    "sg:phone":"+34 958 33 32 04",
    "sg:postcode":"18360",
    "sg:province":"Granada",
    "wof:name":"Complejo Taxara S.l.",
    "wof:placetype":"venue"
},
  "geometry": {"coordinates":[-4.0432047844,37.1958732605],"type":"Point"}
}