{
  "type": "Feature",
  "properties": {
    "iso:country":"ES",
    "sg:address":"Carrer de Angel Guimera, 123",
    "sg:city":"Esplugues Llobregat",
    "sg:orig_category":"Confiter\u00cdas, Chocolater\u00cdas (al Por Menor)",
    "sg:phone":"+34 933 71 44 85",
    "sg:postcode":"08950",
    "sg:province":"Barcelona",
    "wof:name":"Jimenez Medina Francisca",
    "wof:placetype":"venue"
},
  "geometry": {"coordinates":[2.0804738998,41.3750267029],"type":"Point"}
}