{
  "type": "Feature",
  "properties": {
    "addr:full":"Calle de San Agustin, 3 Coru\u00d1a La Coru\u00f1a 15001",
    "addr:housenumber":"3",
    "addr:postcode":"15001",
    "addr:street":"Calle De San Agustin;La Corun\u0303A",
    "iso:country":"ES",
    "sg:address":"Calle de San Agustin, 3",
    "sg:city":"Coru\u00d1a",
    "sg:orig_category":"Alimentaci\u00d3n General (al Por Menor)",
    "sg:phone":"+34 981 22 52 66",
    "sg:postcode":"15001",
    "sg:province":"La Coru\u00f1a",
    "wof:name":"Pan Veira Maria Concepcion",
    "wof:placetype":"venue"
},
  "geometry": {"coordinates":[-8.3965415955,43.3717727661],"type":"Point"}
}