{
  "type": "Feature",
  "properties": {
    "iso:country":"ES",
    "sg:address":"Calle de Gutierrez Orejon, 3",
    "sg:city":"Guadalajara",
    "sg:orig_category":"Peluqueros: De Se\u00d1oras",
    "sg:phone":"+34 949 22 00 12",
    "sg:postcode":"19001",
    "sg:province":"Guadalajara",
    "wof:name":"Landeira Mayoral Rosana",
    "wof:placetype":"venue"
},
  "geometry": {"coordinates":[-3.1628479958,40.6313552856],"type":"Point"}
}