{
  "type": "Feature",
  "properties": {
    "iso:country":"ES",
    "sg:address":"Sierra Oro(urb Monte Pinar), S/n",
    "sg:city":"Esparragal",
    "sg:orig_category":"Alquiler De V\u00cddeo",
    "sg:phone":"+34 968 85 34 86",
    "sg:postcode":"30163",
    "sg:province":"Murcia",
    "wof:name":"Olmos Torralba Agustina",
    "wof:placetype":"venue"
},
  "geometry": {"coordinates":[-1.0736939907,38.0533943176],"type":"Point"}
}