{
  "type": "Feature",
  "properties": {
    "iso:country":"ES",
    "sg:address":"Salvador Allende, 10",
    "sg:city":"Nos",
    "sg:orig_category":"Alimentaci\u00d3n General (al Por Menor)",
    "sg:phone":"+34 981 66 06 15",
    "sg:postcode":"15176",
    "sg:province":"La Coru\u00f1a",
    "wof:name":"Ponte Barbeito Jesus",
    "wof:placetype":"venue"
},
  "geometry": {"coordinates":[-8.3265943527,43.3246536255],"type":"Point"}
}