{
  "type": "Feature",
  "properties": {
    "addr:full":"Calle de Bravo Murillo, 248 Madrid Madrid 28020",
    "addr:housenumber":"248",
    "addr:postcode":"28020",
    "addr:street":"Calle De Bravo Murillo",
    "iso:country":"ES",
    "sg:address":"Calle de Bravo Murillo, 248",
    "sg:city":"Madrid",
    "sg:orig_category":"Ropa Para Se\u00d1oras (al Por Menor)",
    "sg:phone":"+34 915 79 10 71",
    "sg:postcode":"28020",
    "sg:province":"Madrid",
    "wof:name":"Segovia Ochaita Angel",
    "wof:placetype":"venue"
},
  "geometry": {"coordinates":[-3.6992719173,40.4595680237],"type":"Point"}
}