{
  "type": "Feature",
  "properties": {
    "addr:full":"C/ San Crispin, 1 Torrellano Alicante 03320",
    "addr:housenumber":"1",
    "addr:postcode":"03320",
    "addr:street":"C / San Crispin",
    "iso:country":"ES",
    "sg:address":"C/ San Crispin, 1",
    "sg:city":"Torrellano",
    "sg:orig_category":"Dorados, Plater\u00cda (orfebrer\u00cda)",
    "sg:phone":"+34 965 68 24 79",
    "sg:postcode":"03320",
    "sg:province":"Alicante",
    "wof:name":"Esclapez Martinez Ana",
    "wof:placetype":"venue"
},
  "geometry": {"coordinates":[-0.5875089765,38.2937011719],"type":"Point"}
}