{
  "type": "Feature",
  "properties": {
    "addr:full":"Calle de Argensola, 15 Madrid Madrid 28004",
    "addr:housenumber":"15",
    "addr:postcode":"madrid;28004",
    "addr:street":"Calle De Argensola",
    "iso:country":"ES",
    "sg:address":"Calle de Argensola, 15",
    "sg:city":"Madrid",
    "sg:orig_category":"Carnicer\u00cdas, Carnicer\u00cdas",
    "sg:phone":"+34 913 19 23 85",
    "sg:postcode":"28004",
    "sg:province":"Madrid",
    "wof:name":"Moran Perez Maria Consolacion",
    "wof:placetype":"venue"
},
  "geometry": {"coordinates":[-3.6946558952,40.4256477356],"type":"Point"}
}