{
  "type": "Feature",
  "properties": {
    "addr:full":"Rua Fari\u00d1a Ferre\u00d1o, 23 Vilagarcia Pontevedra 36600",
    "addr:housenumber":"23",
    "addr:postcode":"36600",
    "addr:street":"Rua Farin\u0303A Ferren\u0303O",
    "iso:country":"ES",
    "sg:address":"Rua Fari\u00d1a Ferre\u00d1o, 23",
    "sg:city":"Vilagarcia",
    "sg:orig_category":"Librer\u00cdas",
    "sg:phone":"+34 986 50 79 66",
    "sg:postcode":"36600",
    "sg:province":"Pontevedra",
    "wof:name":"Diaz Romero Jose Alfredo",
    "wof:placetype":"venue"
},
  "geometry": {"coordinates":[-8.763215065,42.5929031372],"type":"Point"}
}