{
  "type": "Feature",
  "properties": {
    "addr:full":"Avda Francia (de), 13 Playa Del Ingles Las Palmas 35100",
    "addr:housenumber":"13",
    "addr:postcode":"35100",
    "addr:street":"Avda Francia De",
    "iso:country":"ES",
    "sg:address":"Avda Francia (de), 13",
    "sg:city":"Playa Del Ingles",
    "sg:orig_category":"Peluquer\u00cdas, Peluquer\u00cda Mixta",
    "sg:phone":"+34 928 76 06 09",
    "sg:postcode":"35100",
    "sg:province":"Las Palmas",
    "wof:name":"Rolfes  Karl Heinz",
    "wof:placetype":"venue"
},
  "geometry": {"coordinates":[-15.5794820786,27.7506103516],"type":"Point"}
}