{
  "type": "Feature",
  "properties": {
    "iso:country":"ES",
    "sg:address":"Calle de Dibujante Manuel Gago, 6",
    "sg:city":"Valencia",
    "sg:orig_category":"Doctores En Medicina",
    "sg:phone":"+34 963 80 39 85",
    "sg:postcode":"46018",
    "sg:province":"Valencia",
    "wof:name":"Maronda Frutos Jose Jesus",
    "wof:placetype":"venue"
},
  "geometry": {"coordinates":[-0.3906660974,39.4620666504],"type":"Point"}
}