{
  "type": "Feature",
  "properties": {
    "addr:full":"Calle de Ricardo Del Arco, 1 Huesca Huesca 22003",
    "addr:housenumber":"1",
    "addr:postcode":"22003",
    "addr:street":"Calle De Ricardo Del Arco",
    "iso:country":"ES",
    "sg:address":"Calle de Ricardo Del Arco, 1",
    "sg:city":"Huesca",
    "sg:orig_category":"Asociaciones Y Clubs Deportivos",
    "sg:phone":"+34 974 22 29 58",
    "sg:postcode":"22003",
    "sg:province":"Huesca",
    "wof:name":"Deportes Arcosport S. L.",
    "wof:placetype":"venue"
},
  "geometry": {"coordinates":[-0.4141770005,42.1397209167],"type":"Point"}
}