{
  "type": "Feature",
  "properties": {
    "iso:country":"ES",
    "sg:address":"Pase San Frantzisko Ibiltokia, 15",
    "sg:city":"Tolosa",
    "sg:orig_category":"Lencer\u00cda Femenina, Corseter\u00cda, Trajes De Ba\u00d1o (al Por Menor)",
    "sg:phone":"+34 943 69 82 13",
    "sg:postcode":"20400",
    "sg:province":"Guip\u00f9zcoa",
    "wof:name":"Segurola Inchausti Maria Rosario",
    "wof:placetype":"venue"
},
  "geometry": {"coordinates":[-2.075387001,43.1357421875],"type":"Point"}
}