{
  "type": "Feature",
  "properties": {
    "iso:country":"ES",
    "sg:address":"Calle de Alcarria, 32",
    "sg:city":"Leganes",
    "sg:orig_category":"Molduras, Junquillos, Listones Y Molduras Perforadas",
    "sg:phone":"+34 916 87 93 38",
    "sg:postcode":"28915",
    "sg:province":"Madrid",
    "wof:name":"Zayas Garcia Jose Antonio",
    "wof:placetype":"venue"
},
  "geometry": {"coordinates":[-3.7571172714,40.3318710327],"type":"Point"}
}