{
  "type": "Feature",
  "properties": {
    "iso:country":"ES",
    "sg:address":"Calle de Carromajada, 19",
    "sg:city":"Arroyo De La Encomienda",
    "sg:orig_category":"Promotores Constructores",
    "sg:phone":"+34 983 40 62 82",
    "sg:postcode":"47195",
    "sg:province":"Valladolid",
    "wof:name":"Guerrero Sanchez Patricia",
    "wof:placetype":"venue"
},
  "geometry": {"coordinates":[-4.7758765221,41.6269836426],"type":"Point"}
}