{
  "type": "Feature",
  "properties": {
    "iso:country":"ES",
    "sg:address":"Calle de Avenida Pamplona, 7",
    "sg:city":"Mutiloabeiti",
    "sg:orig_category":"Farmacias",
    "sg:phone":"+34 948 24 30 55",
    "sg:postcode":"31192",
    "sg:province":"Navarra",
    "wof:name":"Urbistondo Arotzarena Maria Dolores",
    "wof:placetype":"venue"
},
  "geometry": {"coordinates":[-1.6151809692,42.7892303467],"type":"Point"}
}