{
  "type": "Feature",
  "properties": {
    "addr:full":"Av Lluc, 85 Inca Islas Baleares 07300",
    "addr:housenumber":"85",
    "addr:postcode":"07300",
    "addr:street":"Av Lluc",
    "iso:country":"ES",
    "sg:address":"Av Lluc, 85",
    "sg:city":"Inca",
    "sg:orig_category":"Peluqueros: De Se\u00d1oras",
    "sg:phone":"+34 971 50 17 54",
    "sg:postcode":"07300",
    "sg:province":"Islas Baleares",
    "wof:name":"Caimari Garau Maria",
    "wof:placetype":"venue"
},
  "geometry": {"coordinates":[2.9118299484,39.7250518799],"type":"Point"}
}