{
  "type": "Feature",
  "properties": {
    "iso:country":"ES",
    "sg:address":"Ctra Oca\u00d1a, S/n",
    "sg:city":"Alacant",
    "sg:orig_category":"Veh\u00cdculos De Ocasi\u00d3n",
    "sg:phone":"+34 965 28 65 42",
    "sg:postcode":"03006",
    "sg:province":"Alicante",
    "wof:name":"Sorio Y Borja S.a.",
    "wof:placetype":"venue"
},
  "geometry": {"coordinates":[-0.5382739902,38.34400177],"type":"Point"}
}