{
  "type": "Feature",
  "properties": {
    "iso:country":"ES",
    "sg:address":"Carrer de Bosch I Gimpera, S/n",
    "sg:city":"Mataro",
    "sg:orig_category":"Distribuci\u00d3n De Petr\u00d3leo Y Derivados",
    "sg:phone":"+34 937 57 76 68",
    "sg:postcode":"08302",
    "sg:province":"Barcelona",
    "wof:name":"Continental Bussiness Europe S.l.",
    "wof:placetype":"venue"
},
  "geometry": {"coordinates":[2.4308590889,41.5301208496],"type":"Point"}
}