{
  "type": "Feature",
  "properties": {
    "iso:country":"ES",
    "sg:address":"Calle de Le\u00d1adores, 25",
    "sg:city":"Zubia",
    "sg:orig_category":"Perfumer\u00cda (al Por Menor)",
    "sg:phone":"+34 958 89 12 39",
    "sg:postcode":"18140",
    "sg:province":"Granada",
    "wof:name":"Magina4 S.l.",
    "wof:placetype":"venue"
},
  "geometry": {"coordinates":[-3.580313921,37.1155052185],"type":"Point"}
}