{
  "type": "Feature",
  "properties": {
    "addr:full":"Calle de Sol, 1 Toro Zamora 49800",
    "addr:housenumber":"1",
    "addr:postcode":"49800",
    "addr:street":"Calle De Sol",
    "iso:country":"ES",
    "sg:address":"Calle de Sol, 1",
    "sg:city":"Toro",
    "sg:orig_category":"Zapatos (al Por Menor)",
    "sg:phone":"+34 980 69 18 87",
    "sg:postcode":"49800",
    "sg:province":"Zamora",
    "wof:name":"Tabares Gutierrez Jesus Felix",
    "wof:placetype":"venue"
},
  "geometry": {"coordinates":[-5.3919258118,41.522151947],"type":"Point"}
}