{
  "type": "Feature",
  "properties": {
    "iso:country":"ES",
    "sg:address":"Plaz Espa\u00d1a, 1",
    "sg:city":"Gallur",
    "sg:orig_category":"Servicios Y Funcionarios De Polic\u00cda",
    "sg:phone":"+34 976 86 40 64",
    "sg:postcode":"50650",
    "sg:province":"Zaragoza",
    "wof:name":"Ayuntamiento De Gallur",
    "wof:placetype":"venue"
},
  "geometry": {"coordinates":[-1.3180890083,41.8687858582],"type":"Point"}
}