{
  "type": "Feature",
  "properties": {
    "addr:full":"Pase Tinteiro (do), 4 Ourense Ourense 32001",
    "addr:postcode":"32001",
    "iso:country":"ES",
    "sg:address":"Pase Tinteiro (do), 4",
    "sg:city":"Ourense",
    "sg:orig_category":"Carnes De Carnicer\u00cda (al Por Mayor)",
    "sg:phone":"+34 988 37 17 70",
    "sg:postcode":"32001",
    "sg:province":"Ourense",
    "wof:name":"Lourecar S.l.",
    "wof:placetype":"venue"
},
  "geometry": {"coordinates":[-7.8779501915,42.3494224548],"type":"Point"}
}