{
  "type": "Feature",
  "properties": {
    "addr:full":"Calle de Peregrinos Los, 192 Goro Las Palmas 35215",
    "addr:housenumber":"192",
    "addr:postcode":"35215",
    "addr:street":"Calle De Peregrinos Los",
    "iso:country":"ES",
    "sg:address":"Calle de Peregrinos Los, 192",
    "sg:city":"Goro",
    "sg:orig_category":"Fabricaci\u00d3n De Juguetes Autom\u00c1ticos",
    "sg:phone":"+34 928 70 05 33",
    "sg:postcode":"35215",
    "sg:province":"Las Palmas",
    "wof:name":"Sorex S. A.",
    "wof:placetype":"venue"
},
  "geometry": {"coordinates":[-15.3912210464,27.9679450989],"type":"Point"}
}