{
  "type": "Feature",
  "properties": {
    "iso:country":"ES",
    "sg:address":"Av Barcelona, 44",
    "sg:city":"Molins Rei",
    "sg:orig_category":"Cl\u00cdnicas Dentales",
    "sg:phone":"+34 936 68 67 28",
    "sg:postcode":"08750",
    "sg:province":"Barcelona",
    "wof:name":"Centre Dental Molins De Rei S. C. P.",
    "wof:placetype":"venue"
},
  "geometry": {"coordinates":[2.0203199387,41.4090919495],"type":"Point"}
}