{
  "type": "Feature",
  "properties": {
    "iso:country":"ES",
    "sg:address":"Pl Nova, 3",
    "sg:city":"Ametlla Mar",
    "sg:orig_category":"Restaurantes",
    "sg:phone":"+34 977 45 70 72",
    "sg:postcode":"43860",
    "sg:province":"Tarragona",
    "wof:name":"Restaurant Placa Nova Cdad",
    "wof:placetype":"venue"
},
  "geometry": {"coordinates":[0.8028619885,40.8838844299],"type":"Point"}
}