{
  "type": "Feature",
  "properties": {
    "addr:full":"Ctra Madrid-irun (de), Km. 0037,0 Molar Madrid 28710",
    "addr:postcode":"28710",
    "addr:street":"Ctra Madrid-Irun De Km. 0037,0",
    "iso:country":"ES",
    "sg:address":"Ctra Madrid-irun (de), Km. 0037,0",
    "sg:city":"Molar",
    "sg:orig_category":"Organizaci\u00d3n De Actos, Seminarios Y Congresos",
    "sg:phone":"+34 918 41 20 99",
    "sg:postcode":"28710",
    "sg:province":"Madrid",
    "sg:website":"www.castillodemonteviejo.com",
    "wof:name":"Reserboda S.l.",
    "wof:placetype":"venue"
},
  "geometry": {"coordinates":[-3.5814239979,40.7349357605],"type":"Point"}
}