{
  "type": "Feature",
  "properties": {
    "addr:full":"Calle de Reyes Catolicos, 28 Granada Granada 18009",
    "addr:housenumber":"28",
    "addr:postcode":"18009",
    "addr:street":"Calle De Reyes Catolicos",
    "iso:country":"ES",
    "sg:address":"Calle de Reyes Catolicos, 28",
    "sg:city":"Granada",
    "sg:orig_category":"Dorados, Plater\u00cda (orfebrer\u00cda)",
    "sg:phone":"+34 958 22 99 16",
    "sg:postcode":"18009",
    "sg:province":"Granada",
    "wof:name":"Talleres De Arte Moreno S. L.",
    "wof:placetype":"venue"
},
  "geometry": {"coordinates":[-3.5983870029,37.1752319336],"type":"Point"}
}