{
  "type": "Feature",
  "properties": {
    "iso:country":"ES",
    "sg:address":"Rua Zaragoza, 18",
    "sg:city":"Vigo",
    "sg:orig_category":"Tapicer\u00cdas",
    "sg:phone":"+34 986 42 14 15",
    "sg:postcode":"36203",
    "sg:province":"Pontevedra",
    "wof:name":"Mari\u00f1o Ledo Jose Luis",
    "wof:placetype":"venue"
},
  "geometry": {"coordinates":[-8.7238740921,42.2264404297],"type":"Point"}
}