{
  "type": "Feature",
  "properties": {
    "iso:country":"ES",
    "sg:address":"Calle de Azogue, 1",
    "sg:city":"Rueda",
    "sg:orig_category":"Reposter\u00cdas",
    "sg:phone":"+34 983 86 80 77",
    "sg:postcode":"47490",
    "sg:province":"Valladolid",
    "wof:name":"Perez Martin Raul",
    "wof:placetype":"venue"
},
  "geometry": {"coordinates":[-4.9583978653,41.4125976562],"type":"Point"}
}