{
  "type": "Feature",
  "properties": {
    "iso:country":"ES",
    "sg:address":"Calle de Haya (de La), 3",
    "sg:city":"Parque Coimbra",
    "sg:orig_category":"Inmobiliaria (agencias)",
    "sg:phone":"+34 916 47 02 55",
    "sg:postcode":"28935",
    "sg:province":"Madrid",
    "wof:name":"Comercial E Inmuebles Duran S.l.",
    "wof:placetype":"venue"
},
  "geometry": {"coordinates":[-3.9281079769,40.3094520569],"type":"Point"}
}