{
  "type": "Feature",
  "properties": {
    "addr:full":"Calle de Chile, 33 Vitoria-gasteiz \u00c1lava 01009",
    "addr:housenumber":"33",
    "addr:postcode":"01009",
    "addr:street":"Calle De Chile",
    "iso:country":"ES",
    "sg:address":"Calle de Chile, 33",
    "sg:city":"Vitoria-gasteiz",
    "sg:orig_category":"Caf\u00c9s, Bares, Cervecer\u00cdas",
    "sg:phone":"+34 945 22 46 42",
    "sg:postcode":"01009",
    "sg:province":"\u00c1lava",
    "wof:name":"Ladritel Gasteiz S.l.",
    "wof:placetype":"venue"
},
  "geometry": {"coordinates":[-2.6868515015,42.8522911072],"type":"Point"}
}