{
  "type": "Feature",
  "properties": {
    "addr:full":"Avda Santa Cruz (de), 58 G\u00fcimar Santa Cruz De Tenerife 38500",
    "addr:housenumber":"58",
    "addr:postcode":"38500",
    "addr:street":"Avda Santa Cruz De",
    "iso:country":"ES",
    "sg:address":"Avda Santa Cruz (de), 58",
    "sg:city":"G\u00fcimar",
    "sg:orig_category":"Veh\u00cdculos De Ocasi\u00d3n",
    "sg:phone":"+34 922 52 44 50",
    "sg:postcode":"38500",
    "sg:province":"Santa Cruz De Tenerife",
    "wof:name":"Chavez Coello Guillermo Juan",
    "wof:placetype":"venue"
},
  "geometry": {"coordinates":[-16.4080848694,28.3186244965],"type":"Point"}
}