{
  "type": "Feature",
  "properties": {
    "iso:country":"ES",
    "sg:address":"Avda Virgen Del Rocio, S/n",
    "sg:city":"Huevar",
    "sg:orig_category":"Aceites Y Grasas Alimentarias (fabricaci\u00d3n, Al Por Mayor)",
    "sg:phone":"+34 954 75 62 36",
    "sg:postcode":"41830",
    "sg:province":"Sevilla",
    "wof:name":"Galan Gonzalez Juan Antonio",
    "wof:placetype":"venue"
},
  "geometry": {"coordinates":[-6.2821221352,37.3545608521],"type":"Point"}
}