{
  "type": "Feature",
  "properties": {
    "addr:full":"Calle de Alarcos, 3 Ciudad Real Ciudad Real 13001",
    "addr:housenumber":"3",
    "addr:postcode":"13001",
    "addr:street":"Calle De Alarcos",
    "iso:country":"ES",
    "sg:address":"Calle de Alarcos, 3",
    "sg:city":"Ciudad Real",
    "sg:orig_category":"Sociedades, Compa\u00d1\u00cdas Aseguradoras",
    "sg:phone":"+34 926 21 30 42",
    "sg:postcode":"13001",
    "sg:province":"Ciudad Real",
    "wof:name":"Seguros Catalana Occidente S.a. De Seguros Y Reaseguros",
    "wof:placetype":"venue"
},
  "geometry": {"coordinates":[-3.9299221039,38.9833641052],"type":"Point"}
}