{
  "type": "Feature",
  "properties": {
    "addr:full":"Avda Lanzagorta, 3 Mimetiz Vizcaya 48860",
    "addr:housenumber":"3",
    "addr:postcode":"48860",
    "addr:street":"Avda Lanzagorta",
    "iso:country":"ES",
    "sg:address":"Avda Lanzagorta, 3",
    "sg:city":"Mimetiz",
    "sg:orig_category":"Cl\u00cdnicas Dentales",
    "sg:phone":"+34 946 67 01 74",
    "sg:postcode":"48860",
    "sg:province":"Vizcaya",
    "wof:name":"Murga Fernandez Blanca Aurora",
    "wof:placetype":"venue"
},
  "geometry": {"coordinates":[-3.1315560341,43.2133140564],"type":"Point"}
}