{
  "type": "Feature",
  "properties": {
    "iso:country":"ES",
    "sg:address":"Calle de Estrella Polar, 12",
    "sg:city":"Madrid",
    "sg:orig_category":"Escultores, Estatuarios E Imagineros",
    "sg:phone":"+34 915 74 32 56",
    "sg:postcode":"28007",
    "sg:province":"Madrid",
    "wof:name":"Garcia Muela Carlos",
    "wof:placetype":"venue"
},
  "geometry": {"coordinates":[-3.6667990685,40.4107208252],"type":"Point"}
}