{
  "type": "Feature",
  "properties": {
    "addr:full":"Calle de Duque De Tetuan, 37 Lucena Cid Castell\u00f3n 12120",
    "addr:housenumber":"37",
    "addr:postcode":"12120",
    "addr:street":"Calle De Duque De Tetuan;Castello\u0301N",
    "iso:country":"ES",
    "sg:address":"Calle de Duque De Tetuan, 37",
    "sg:city":"Lucena Cid",
    "sg:orig_category":"Empresas De Desmonte",
    "sg:phone":"+34 964 38 02 50",
    "sg:postcode":"12120",
    "sg:province":"Castell\u00f3n",
    "wof:name":"Excavaciones Franjo S.l.",
    "wof:placetype":"venue"
},
  "geometry": {"coordinates":[-0.2812924087,40.1375389099],"type":"Point"}
}