{
  "type": "Feature",
  "properties": {
    "iso:country":"ES",
    "sg:address":"Carr Escultor Esteve, 20",
    "sg:city":"Xativa",
    "sg:orig_category":"Enfermeras: Consultas, Atenci\u00d3n A Domicilio",
    "sg:phone":"+34 962 27 08 56",
    "sg:postcode":"46800",
    "sg:province":"Valencia",
    "wof:name":"Lladosa Quiles Maria Del Carmen",
    "wof:placetype":"venue"
},
  "geometry": {"coordinates":[-0.5253030062,38.991153717],"type":"Point"}
}