{
  "type": "Feature",
  "properties": {
    "addr:full":"Arboledas, S/n Lorqui Murcia 30564",
    "addr:postcode":"30564",
    "addr:street":"S / N",
    "iso:country":"ES",
    "sg:address":"Arboledas, S/n",
    "sg:city":"Lorqui",
    "sg:orig_category":"Organizaci\u00d3n De Actos, Seminarios Y Congresos",
    "sg:phone":"+34 968 43 25 32",
    "sg:postcode":"30564",
    "sg:province":"Murcia",
    "wof:name":"Bermejo Cifuentes Jose Antonio",
    "wof:placetype":"venue"
},
  "geometry": {"coordinates":[-1.2517440319,38.0802001953],"type":"Point"}
}