{
  "type": "Feature",
  "properties": {
    "addr:full":"Avda Alicante, 90 Monforte Cid Alicante 03670",
    "addr:housenumber":"90",
    "addr:postcode":"03670",
    "addr:street":"Avda Alicante",
    "iso:country":"ES",
    "sg:address":"Avda Alicante, 90",
    "sg:city":"Monforte Cid",
    "sg:orig_category":"Frutas Y Legumbres Frescas (al Por Mayor)",
    "sg:phone":"+34 965 62 17 92",
    "sg:postcode":"03670",
    "sg:province":"Alicante",
    "wof:name":"Sociedad Agraria De Transformacion Uvas El Llano",
    "wof:placetype":"venue"
},
  "geometry": {"coordinates":[-0.7265099883,38.3780937195],"type":"Point"}
}