{
  "type": "Feature",
  "properties": {
    "addr:full":"Calle de Mayor, 8 Caspe Zaragoza 50700",
    "addr:housenumber":"8",
    "addr:postcode":"50700",
    "addr:street":"Calle De Mayor",
    "iso:country":"ES",
    "sg:address":"Calle de Mayor, 8",
    "sg:city":"Caspe",
    "sg:orig_category":"\u00d3ptica: Instrumentos (fabricaci\u00d3n)",
    "sg:phone":"+34 976 63 01 40",
    "sg:postcode":"50700",
    "sg:province":"Zaragoza",
    "wof:name":"Masats Alconchel Jorge",
    "wof:placetype":"venue"
},
  "geometry": {"coordinates":[-0.0392186008,41.236618042],"type":"Point"}
}