{
  "type": "Feature",
  "properties": {
    "iso:country":"ES",
    "sg:address":"Calle de Felisa Gale, 3",
    "sg:city":"Zaragoza",
    "sg:orig_category":"Reposter\u00cdas",
    "sg:phone":"+34 976 47 08 73",
    "sg:postcode":"50014",
    "sg:province":"Zaragoza",
    "wof:name":"Pe\u00f1a Perez Crescencio",
    "wof:placetype":"venue"
},
  "geometry": {"coordinates":[-0.861011982,41.6634407043],"type":"Point"}
}