{
  "type": "Feature",
  "properties": {
    "iso:country":"ES",
    "sg:address":"Rua Ramon Otero Pedrayo, 4",
    "sg:city":"Ribadavia",
    "sg:orig_category":"Fabricaci\u00d3n De Muebles",
    "sg:phone":"+34 988 47 10 34",
    "sg:postcode":"32400",
    "sg:province":"Ourense",
    "wof:name":"Muebles Cui\u00f1as S.c.",
    "wof:placetype":"venue"
},
  "geometry": {"coordinates":[-8.1465368271,42.2862243652],"type":"Point"}
}