{
  "type": "Feature",
  "properties": {
    "addr:full":"Carr Nuestra Se\u00d1ora Del Socorro, 70 Benetusser Valencia 46910",
    "addr:housenumber":"70",
    "addr:postcode":"46910",
    "addr:street":"Carr Nuestra Sen\u0303Ora Del Socorro",
    "iso:country":"ES",
    "sg:address":"Carr Nuestra Se\u00d1ora Del Socorro, 70",
    "sg:city":"Benetusser",
    "sg:orig_category":"Madera Para Construcci\u00d3n E Industria",
    "sg:phone":"+34 963 75 41 57",
    "sg:postcode":"46910",
    "sg:province":"Valencia",
    "wof:name":"Chaspas Y Tableros Temar S.l.",
    "wof:placetype":"venue"
},
  "geometry": {"coordinates":[-0.3968169987,39.4220848083],"type":"Point"}
}