{
  "type": "Feature",
  "properties": {
    "addr:full":"Calle de Lorenzo Abru\u00d1edo, 21 Oviedo Asturias 33012",
    "addr:housenumber":"21",
    "addr:postcode":"33012",
    "addr:street":"Calle De Lorenzo Abrun\u0303Edo",
    "iso:country":"ES",
    "sg:address":"Calle de Lorenzo Abru\u00d1edo, 21",
    "sg:city":"Oviedo",
    "sg:orig_category":"Procuradores",
    "sg:phone":"+34 985 29 44 54",
    "sg:postcode":"33012",
    "sg:province":"Asturias",
    "wof:name":"Gonzalez De Cabo Delfina",
    "wof:placetype":"venue"
},
  "geometry": {"coordinates":[-5.8559908867,43.3698272705],"type":"Point"}
}