{
  "type": "Feature",
  "properties": {
    "addr:full":"Rua Real, 51 Muros La Coru\u00f1a 15250",
    "addr:housenumber":"51",
    "addr:postcode":"15250",
    "addr:street":"Rua Real;La Corun\u0303A",
    "iso:country":"ES",
    "sg:address":"Rua Real, 51",
    "sg:city":"Muros",
    "sg:orig_category":"Congelados: Productos Alimentarios (fabricaci\u00d3n, Al Por Mayor)",
    "sg:phone":"+34 981 82 64 22",
    "sg:postcode":"15250",
    "sg:province":"La Coru\u00f1a",
    "wof:name":"Gonzalez Estalote Y Otro C.b.",
    "wof:placetype":"venue"
},
  "geometry": {"coordinates":[-9.0594110489,42.7757072449],"type":"Point"}
}