{
  "type": "Feature",
  "properties": {
    "addr:full":"Calle de San Vicente De Paul, 7 Utrillas Teruel 44760",
    "addr:housenumber":"7",
    "addr:postcode":"44760",
    "addr:street":"Calle De San Vicente De Paul",
    "iso:country":"ES",
    "sg:address":"Calle de San Vicente De Paul, 7",
    "sg:city":"Utrillas",
    "sg:orig_category":"Electrodom\u00c9sticos (al Por Menor)",
    "sg:phone":"+34 978 75 72 82",
    "sg:postcode":"44760",
    "sg:province":"Teruel",
    "wof:name":"Conde Miguel Gabriel",
    "wof:placetype":"venue"
},
  "geometry": {"coordinates":[-0.8445410132,40.8114547729],"type":"Point"}
}