{
  "type": "Feature",
  "properties": {
    "iso:country":"ES",
    "sg:address":"Calle de Blanquerias, 5",
    "sg:city":"Valencia",
    "sg:orig_category":"Venta, Colocaci\u00d3n De Moquetas, Revestimiento De Suelos Y De Paredes",
    "sg:phone":"+34 963 92 40 34",
    "sg:postcode":"46003",
    "sg:province":"Valencia",
    "sg:website":"www.decoval.net",
    "wof:name":"Osca Wolf S.l.",
    "wof:placetype":"venue"
},
  "geometry": {"coordinates":[-0.3767940998,39.4795951843],"type":"Point"}
}