{
  "type": "Feature",
  "properties": {
    "addr:full":"Avda Taramundi, 11 Vegadeo Asturias 33770",
    "addr:housenumber":"11",
    "addr:postcode":"33770",
    "addr:street":"Avda Taramundi",
    "iso:country":"ES",
    "sg:address":"Avda Taramundi, 11",
    "sg:city":"Vegadeo",
    "sg:orig_category":"Institutos De Belleza",
    "sg:phone":"+34 985 63 48 39",
    "sg:postcode":"33770",
    "sg:province":"Asturias",
    "wof:name":"Prado Amor Maria Isabel",
    "wof:placetype":"venue"
},
  "geometry": {"coordinates":[-7.0507087708,43.4619407654],"type":"Point"}
}