{
  "type": "Feature",
  "properties": {
    "addr:full":"Carr Agustins, S/n Lleida Lleida 25001",
    "addr:housenumber":"s",
    "addr:postcode":"25001",
    "addr:street":"Carr Agustins;/ N",
    "iso:country":"ES",
    "sg:address":"Carr Agustins, S/n",
    "sg:city":"Lleida",
    "sg:orig_category":"Iglesia Cat\u00d3lica",
    "sg:phone":"+34 973 21 19 28",
    "sg:postcode":"25001",
    "sg:province":"Lleida",
    "wof:name":"Parroquia Sagrada Familia",
    "wof:placetype":"venue"
},
  "geometry": {"coordinates":[0.6346250176,41.6098442078],"type":"Point"}
}