{
  "type": "Feature",
  "properties": {
    "iso:country":"ES",
    "sg:address":"Calle de Yague De Salas, 13",
    "sg:city":"Teruel",
    "sg:orig_category":"Agentes Generales De Seguros",
    "sg:phone":"+34 978 61 70 28",
    "sg:postcode":"44001",
    "sg:province":"Teruel",
    "wof:name":"Argente Calvo Seguros S.l.",
    "wof:placetype":"venue"
},
  "geometry": {"coordinates":[-1.108206749,40.3428955078],"type":"Point"}
}