{
  "type": "Feature",
  "properties": {
    "iso:country":"ES",
    "sg:address":"Calle de Padre Francisco Piquer, 33",
    "sg:city":"Ronda",
    "sg:orig_category":"Dise\u00d1o Industrial",
    "sg:phone":"+34 952 87 16 26",
    "sg:postcode":"29400",
    "sg:province":"M\u00e1laga",
    "wof:name":"Ayala Gilardon Jesus",
    "wof:placetype":"venue"
},
  "geometry": {"coordinates":[-5.1523265839,36.7522544861],"type":"Point"}
}