{
  "type": "Feature",
  "properties": {
    "addr:full":"Calle de Castillo, 1 Isla Cristina Huelva 21410",
    "addr:housenumber":"1",
    "addr:postcode":"21410",
    "addr:street":"Calle De Castillo",
    "iso:country":"ES",
    "sg:address":"Calle de Castillo, 1",
    "sg:city":"Isla Cristina",
    "sg:orig_category":"Promotores Constructores",
    "sg:phone":"+34 959 33 27 08",
    "sg:postcode":"21410",
    "sg:province":"Huelva",
    "wof:name":"Rodriguez Zamora Manuel Jesus",
    "wof:placetype":"venue"
},
  "geometry": {"coordinates":[-7.327352047,37.2003936768],"type":"Point"}
}