{
  "type": "Feature",
  "properties": {
    "addr:full":"Carrer de Rafael De Casanova, 99 Sant Vicen\u00c7 Dels Horts Barcelona 08620",
    "addr:housenumber":"99",
    "addr:postcode":"08620",
    "addr:street":"Carrer De Rafael De Casanova",
    "iso:country":"ES",
    "sg:address":"Carrer de Rafael De Casanova, 99",
    "sg:city":"Sant Vicen\u00c7 Dels Horts",
    "sg:orig_category":"Bisuter\u00cda, Joyer\u00cda, Relojer\u00cda (al Por Menor)",
    "sg:phone":"+34 936 56 37 11",
    "sg:postcode":"08620",
    "sg:province":"Barcelona",
    "wof:name":"Esteve Recasens Juan",
    "wof:placetype":"venue"
},
  "geometry": {"coordinates":[2.0102798939,41.3913002014],"type":"Point"}
}