{
  "type": "Feature",
  "properties": {
    "addr:full":"Ctra. Valencia Alcantara-badajoz, Km. 0040,0 Alburquerque Badajoz 06510",
    "addr:street":"Ctra. Valencia Alcantara-Badajoz Km. 0040,0",
    "iso:country":"ES",
    "sg:address":"Ctra. Valencia Alcantara-badajoz, Km. 0040,0",
    "sg:city":"Alburquerque",
    "sg:orig_category":"Agricultores, Agricultores",
    "sg:phone":"+34 924 14 10 60",
    "sg:postcode":"06510",
    "sg:province":"Badajoz",
    "wof:name":"Jeronimo Piriz Francisco",
    "wof:placetype":"venue"
},
  "geometry": {"coordinates":[-7.0059947968,39.2234420776],"type":"Point"}
}