{
  "type": "Feature",
  "properties": {
    "iso:country":"ES",
    "sg:address":"Trav Dalt, 6",
    "sg:city":"Barcelona",
    "sg:orig_category":"Mec\u00c1nico Del Autom\u00d3vil",
    "sg:phone":"+34 932 37 21 81",
    "sg:postcode":"08024",
    "sg:province":"Barcelona",
    "sg:website":"www.autosantalo.com",
    "wof:name":"Auto Santalo S. L",
    "wof:placetype":"venue"
},
  "geometry": {"coordinates":[2.1628940105,41.4073600769],"type":"Point"}
}