{
  "type": "Feature",
  "properties": {
    "addr:full":"Calle de Iglesias, 1 Sierra Yeguas M\u00e1laga 29328",
    "addr:housenumber":"1",
    "addr:postcode":"29328",
    "addr:street":"Calle De Iglesias",
    "iso:country":"ES",
    "sg:address":"Calle de Iglesias, 1",
    "sg:city":"Sierra Yeguas",
    "sg:orig_category":"Iglesia Cat\u00d3lica",
    "sg:phone":"+34 952 74 60 55",
    "sg:postcode":"29328",
    "sg:province":"M\u00e1laga",
    "wof:name":"Obispado De Malaga",
    "wof:placetype":"venue"
},
  "geometry": {"coordinates":[-4.8684921265,37.1239242554],"type":"Point"}
}