{
  "type": "Feature",
  "properties": {
    "addr:full":"Avda Taco (de), 147 Taco Santa Cruz De Tenerife 38108",
    "addr:housenumber":"147",
    "addr:postcode":"38108",
    "addr:street":"Avda Taco De",
    "iso:country":"ES",
    "sg:address":"Avda Taco (de), 147",
    "sg:city":"Taco",
    "sg:orig_category":"\u00d3ptica: Instrumentos (fabricaci\u00d3n)",
    "sg:phone":"+34 922 62 90 45",
    "sg:postcode":"38108",
    "sg:province":"Santa Cruz De Tenerife",
    "wof:name":"Cobos Y Plasencia S.l.",
    "wof:placetype":"venue"
},
  "geometry": {"coordinates":[-16.297876358,28.4479541779],"type":"Point"}
}