{
  "type": "Feature",
  "properties": {
    "iso:country":"ES",
    "sg:address":"Pol Ind Augalevada(barro), 28",
    "sg:city":"Noia",
    "sg:orig_category":"Fabricaci\u00d3n, Venta, Instalaci\u00d3n De R\u00d3tulos, De R\u00d3tulos Luminosos",
    "sg:phone":"+34 981 82 89 19",
    "sg:postcode":"15200",
    "sg:province":"La Coru\u00f1a",
    "wof:name":"Rotal S.c.",
    "wof:placetype":"venue"
},
  "geometry": {"coordinates":[-8.8883037567,42.788608551],"type":"Point"}
}