{
  "type": "Feature",
  "properties": {
    "addr:full":"Colom, 479 Can Parellada Barcelona 08228",
    "addr:housenumber":"479",
    "addr:postcode":"08228",
    "addr:street":"Colom",
    "iso:country":"ES",
    "sg:address":"Colom, 479",
    "sg:city":"Can Parellada",
    "sg:orig_category":"Promotores Constructores",
    "sg:phone":"+34 937 85 60 16",
    "sg:postcode":"08228",
    "sg:province":"Barcelona",
    "wof:name":"Construcciones Juanes S.a.",
    "wof:placetype":"venue"
},
  "geometry": {"coordinates":[2.0362648964,41.5310096741],"type":"Point"}
}