{
  "type": "Feature",
  "properties": {
    "addr:full":"Rua Real, 35 Vigo Pontevedra 36202",
    "addr:housenumber":"35",
    "addr:postcode":"36202",
    "addr:street":"Rua Real",
    "iso:country":"ES",
    "sg:address":"Rua Real, 35",
    "sg:city":"Vigo",
    "sg:orig_category":"Molduras, Junquillos, Listones Y Molduras Perforadas",
    "sg:phone":"+34 986 43 02 81",
    "sg:postcode":"36202",
    "sg:province":"Pontevedra",
    "wof:name":"Perez Sanchez Jose",
    "wof:placetype":"venue"
},
  "geometry": {"coordinates":[-8.7282581329,42.2384147644],"type":"Point"}
}