{
  "type": "Feature",
  "properties": {
    "addr:full":"Calle de Pablo Picasso, 15 Pinto Madrid 28320",
    "addr:housenumber":"15",
    "addr:postcode":"28320",
    "addr:street":"Calle De Pablo Picasso",
    "iso:country":"ES",
    "sg:address":"Calle de Pablo Picasso, 15",
    "sg:city":"Pinto",
    "sg:orig_category":"Asesor\u00cda Fiscal Y Jur\u00cddica",
    "sg:phone":"+34 916 92 55 09",
    "sg:postcode":"28320",
    "sg:province":"Madrid",
    "wof:name":"Torres Esperante Maria Del Pilar",
    "wof:placetype":"venue"
},
  "geometry": {"coordinates":[-3.694699049,40.2379798889],"type":"Point"}
}