{
  "type": "Feature",
  "properties": {
    "addr:full":"Afueras, S/n Almoharin C\u00e1ceres 10132",
    "addr:postcode":"10132",
    "addr:street":"Afueras S / N Almoharin Ca\u0301Ceres",
    "iso:country":"ES",
    "sg:address":"Afueras, S/n",
    "sg:city":"Almoharin",
    "sg:orig_category":"Cr\u00cda De Cerdos",
    "sg:phone":"+34 927 19 60 14",
    "sg:postcode":"10132",
    "sg:province":"C\u00e1ceres",
    "wof:name":"Vicente Y Jaime Castello C.b.",
    "wof:placetype":"venue"
},
  "geometry": {"coordinates":[-6.0440888405,39.1764564514],"type":"Point"}
}