{
  "type": "Feature",
  "properties": {
    "addr:full":"Calle de Guelfo (el), 6 Matorral Las Palmas 35610",
    "addr:housenumber":"6",
    "addr:postcode":"35610",
    "addr:street":"Calle De Guelfo El",
    "iso:country":"ES",
    "sg:address":"Calle de Guelfo (el), 6",
    "sg:city":"Matorral",
    "sg:orig_category":"Quincaller\u00cda (al Por Menor)",
    "sg:phone":"+34 928 86 90 57",
    "sg:postcode":"35610",
    "sg:province":"Las Palmas",
    "wof:name":"Yusi Jaber S.l.",
    "wof:placetype":"venue"
},
  "geometry": {"coordinates":[-13.8707475662,28.4395484924],"type":"Point"}
}