{
  "type": "Feature",
  "properties": {
    "addr:full":"Avda Navarra (de), 6 Alberite La Rioja 26141",
    "addr:postcode":"26141",
    "addr:street":"Avda Navarra De 6 Alberite;Rioja",
    "iso:country":"ES",
    "sg:address":"Avda Navarra (de), 6",
    "sg:city":"Alberite",
    "sg:orig_category":"Caf\u00c9s, Bares, Cervecer\u00cdas",
    "sg:phone":"+34 941 43 62 45",
    "sg:postcode":"26141",
    "sg:province":"La Rioja",
    "wof:name":"Sistelcom-telemensaje S.a.",
    "wof:placetype":"venue"
},
  "geometry": {"coordinates":[-2.4403378963,42.4052009583],"type":"Point"}
}