{
  "type": "Feature",
  "properties": {
    "iso:country":"ES",
    "sg:address":"Rbla Blas Infante, 11",
    "sg:city":"Castelldefels",
    "sg:orig_category":"Ense\u00d1anza: Idiomas",
    "sg:phone":"+34 936 34 21 45",
    "sg:postcode":"08860",
    "sg:province":"Barcelona",
    "wof:name":"Forum I Arrels S.l.",
    "wof:placetype":"venue"
},
  "geometry": {"coordinates":[1.9776710272,41.2873268127],"type":"Point"}
}