{
  "type": "Feature",
  "properties": {
    "addr:full":"Calle de Honsario, 17 Jerez De La Frontera C\u00e1diz 11402",
    "addr:housenumber":"17",
    "addr:postcode":"11402",
    "addr:street":"Calle De Honsario",
    "iso:country":"ES",
    "sg:address":"Calle de Honsario, 17",
    "sg:city":"Jerez De La Frontera",
    "sg:orig_category":"Asociaciones Humanitarias, De Cooperaci\u00d3n, De Acci\u00d3n Social",
    "sg:phone":"+34 956 33 00 00",
    "sg:postcode":"11402",
    "sg:province":"C\u00e1diz",
    "wof:name":"Asociacion De Diabeticos De Jerez",
    "wof:placetype":"venue"
},
  "geometry": {"coordinates":[-6.1323504448,36.684879303],"type":"Point"}
}