{
  "type": "Feature",
  "properties": {
    "addr:full":"La Ca\u00f1ada-ctro Comercial, 75 Marbella M\u00e1laga 29600",
    "addr:housenumber":"75",
    "addr:postcode":"29600",
    "addr:street":"Comercial;Ma\u0301Laga",
    "iso:country":"ES",
    "sg:address":"La Ca\u00f1ada-ctro Comercial, 75",
    "sg:city":"Marbella",
    "sg:orig_category":"Art\u00cdculos De Regalo (al Por Menor)",
    "sg:phone":"+34 952 86 65 16",
    "sg:postcode":"29600",
    "sg:province":"M\u00e1laga",
    "wof:name":"Tropico Montigala S.l.",
    "wof:placetype":"venue"
},
  "geometry": {"coordinates":[-4.8833007812,36.5079956055],"type":"Point"}
}