{
  "type": "Feature",
  "properties": {
    "iso:country":"ES",
    "sg:address":"Calle de Baja, 29",
    "sg:city":"Villafranca Cordoba",
    "sg:orig_category":"Supermercados Y Hipermercados",
    "sg:phone":"+34 957 19 01 47",
    "sg:postcode":"14420",
    "sg:province":"C\u00f3rdoba",
    "wof:name":"Autoservicio Mari Carmen",
    "wof:placetype":"venue"
},
  "geometry": {"coordinates":[-4.5441617966,37.9621047974],"type":"Point"}
}