{
  "type": "Feature",
  "properties": {
    "iso:country":"ES",
    "sg:address":"Calle de Mariano Pola, 55",
    "sg:city":"Gijon",
    "sg:orig_category":"Imprenta",
    "sg:phone":"+34 985 31 41 50",
    "sg:postcode":"33212",
    "sg:province":"Asturias",
    "wof:name":"Artes Graficas Asturias Sa",
    "wof:placetype":"venue"
},
  "geometry": {"coordinates":[-5.6808838844,43.5402755737],"type":"Point"}
}