{
  "type": "Feature",
  "properties": {
    "addr:full":"Avda Andalucia, 54 Peal Becerro Ja\u00e9n 23460",
    "addr:housenumber":"54",
    "addr:postcode":"23460",
    "addr:street":"Avda Andalucia",
    "iso:country":"ES",
    "sg:address":"Avda Andalucia, 54",
    "sg:city":"Peal Becerro",
    "sg:orig_category":"Aceites Y Grasas Alimentarias (fabricaci\u00d3n, Al Por Mayor)",
    "sg:phone":"+34 953 71 63 70",
    "sg:postcode":"23460",
    "sg:province":"Ja\u00e9n",
    "wof:name":"O.p.r.nuestra Se\u00f1ora De La Encarnacion",
    "wof:placetype":"venue"
},
  "geometry": {"coordinates":[-3.1198499203,37.91355896],"type":"Point"}
}