{
  "type": "Feature",
  "properties": {
    "addr:full":"Carrer de Figuera, 1 Playa Muchavista Alicante 03560",
    "addr:housenumber":"1",
    "addr:postcode":"03560",
    "addr:street":"Carrer De Figuera;Muchavista",
    "iso:country":"ES",
    "sg:address":"Carrer de Figuera, 1",
    "sg:city":"Playa Muchavista",
    "sg:orig_category":"Cervecer\u00cdas",
    "sg:phone":"+34 965 65 68 69",
    "sg:postcode":"03560",
    "sg:province":"Alicante",
    "wof:name":"Caro Carmona Jose Antonio",
    "wof:placetype":"venue"
},
  "geometry": {"coordinates":[-0.4075799882,38.4058418274],"type":"Point"}
}