{
  "type": "Feature",
  "properties": {
    "addr:full":"Cra. Torre-serona, Km. 0002,5 Lleida Lleida 25091",
    "addr:postcode":"25091",
    "addr:street":"Torre-Serona Km. 0002,5",
    "iso:country":"ES",
    "sg:address":"Cra. Torre-serona, Km. 0002,5",
    "sg:city":"Lleida",
    "sg:orig_category":"Negocio De Madera",
    "sg:phone":"+34 973 24 01 40",
    "sg:postcode":"25091",
    "sg:province":"Lleida",
    "wof:name":"Maderas Llop Obiols S.a.",
    "wof:placetype":"venue"
},
  "geometry": {"coordinates":[0.6406300068,41.6501808167],"type":"Point"}
}