{
  "type": "Feature",
  "properties": {
    "addr:full":"Calle de Manantiales (los), S/n Cazalla Sierra Sevilla 41370",
    "addr:postcode":"41370",
    "addr:street":"Calle De Manantiales Los S / N Cazalla",
    "iso:country":"ES",
    "sg:address":"Calle de Manantiales (los), S/n",
    "sg:city":"Cazalla Sierra",
    "sg:orig_category":"Centros Empresariales",
    "sg:phone":"+34 954 88 30 98",
    "sg:postcode":"41370",
    "sg:province":"Sevilla",
    "wof:name":"A.d.r Sierra Morena Sevillana",
    "wof:placetype":"venue"
},
  "geometry": {"coordinates":[-5.7615084648,37.9382591248],"type":"Point"}
}