{
  "type": "Feature",
  "properties": {
    "iso:country":"ES",
    "sg:address":"Avda Fuentesauco, 8",
    "sg:city":"Poligono Industrial Los Villares",
    "sg:orig_category":"Bares, Piano",
    "sg:phone":"+34 923 22 79 12",
    "sg:postcode":"37184",
    "sg:province":"Salamanca",
    "wof:name":"Sociedad Cooperativa Limitada Distribuciones Salmantinas",
    "wof:placetype":"venue"
},
  "geometry": {"coordinates":[-5.6457591057,40.9924507141],"type":"Point"}
}