{
  "type": "Feature",
  "properties": {
    "addr:full":"Biduido De Arriba, S/n Biduido La Coru\u00f1a 15895",
    "addr:housenumber":"s / n",
    "addr:postcode":"15895",
    "addr:street":"Arriba;La Corun\u0303A",
    "iso:country":"ES",
    "sg:address":"Biduido De Arriba, S/n",
    "sg:city":"Biduido",
    "sg:orig_category":"Inform\u00c1tica: Mantenimiento Y Reparaci\u00d3n De Ordenadores",
    "sg:phone":"+34 981 53 02 61",
    "sg:postcode":"15895",
    "sg:province":"La Coru\u00f1a",
    "wof:name":"Bram Sistemas Sl",
    "wof:placetype":"venue"
},
  "geometry": {"coordinates":[-8.5794343948,42.8416137695],"type":"Point"}
}