{
  "type": "Feature",
  "properties": {
    "iso:country":"ES",
    "sg:address":"C/ Ciutat D'onda, 26",
    "sg:city":"Paterna",
    "sg:orig_category":"Productos Alimentarios",
    "sg:phone":"+34 961 32 19 36",
    "sg:postcode":"46988",
    "sg:province":"Valencia",
    "wof:name":"Montaner Aguado Higinio",
    "wof:placetype":"venue"
},
  "geometry": {"coordinates":[-0.4408999979,39.5301818848],"type":"Point"}
}