{
  "type": "Feature",
  "properties": {
    "addr:full":"Calle de Santander, 9 Burgos Burgos 09004",
    "addr:housenumber":"9",
    "addr:postcode":"09004",
    "addr:street":"Calle De Santander",
    "iso:country":"ES",
    "sg:address":"Calle de Santander, 9",
    "sg:city":"Burgos",
    "sg:orig_category":"Informaci\u00d3n Financiera Y Comercial",
    "sg:phone":"+34 947 27 38 94",
    "sg:postcode":"09004",
    "sg:province":"Burgos",
    "wof:name":"Payno Diaz De La Espina Eduardo",
    "wof:placetype":"venue"
},
  "geometry": {"coordinates":[-3.6998050213,42.342048645],"type":"Point"}
}