{
  "type": "Feature",
  "properties": {
    "iso:country":"ES",
    "sg:address":"Plaz Guridi Musico, 5",
    "sg:city":"Bilbao",
    "sg:orig_category":"Ense\u00d1anza: Profesiones Art\u00cdsticas",
    "sg:phone":"+34 944 46 56 27",
    "sg:postcode":"48007",
    "sg:province":"Vizcaya",
    "wof:name":"Cereceda Grijalba Isidoro",
    "wof:placetype":"venue"
},
  "geometry": {"coordinates":[-2.9165980816,43.2649345398],"type":"Point"}
}