{
  "type": "Feature",
  "properties": {
    "iso:country":"ES",
    "sg:address":"Berezao Auzoa, S/n",
    "sg:city":"Berezao",
    "sg:orig_category":"Reposter\u00cdas",
    "sg:phone":"+34 943 78 23 45",
    "sg:postcode":"20560",
    "sg:province":"Guip\u00f9zcoa",
    "wof:name":"Gure Labeak S.l.",
    "wof:placetype":"venue"
},
  "geometry": {"coordinates":[-2.4041144848,43.0228309631],"type":"Point"}
}