{
  "type": "Feature",
  "properties": {
    "iso:country":"ES",
    "sg:address":"Rbla Josep Maria Marti, 12",
    "sg:city":"Puigcerda",
    "sg:orig_category":"Venta, Instalaci\u00d3n De Cocinas",
    "sg:phone":"+34 972 88 22 46",
    "sg:postcode":"17520",
    "sg:province":"Girona",
    "wof:name":"Vazquez Gendrau Maria Dolores",
    "wof:placetype":"venue"
},
  "geometry": {"coordinates":[1.9259940386,42.4328613281],"type":"Point"}
}