{
  "type": "Feature",
  "properties": {
    "addr:full":"Calle de Pinilla, 61 Madrid Madrid 28023",
    "addr:housenumber":"61",
    "addr:postcode":"madrid;28023",
    "addr:street":"Calle De Pinilla",
    "iso:country":"ES",
    "sg:address":"Calle de Pinilla, 61",
    "sg:city":"Madrid",
    "sg:orig_category":"Ingeniero",
    "sg:phone":"+34 913 07 10 05",
    "sg:postcode":"28023",
    "sg:province":"Madrid",
    "wof:name":"Internet E Informatica Aplicada S.l.",
    "wof:placetype":"venue"
},
  "geometry": {"coordinates":[-3.7799649239,40.4563827515],"type":"Point"}
}