{
  "type": "Feature",
  "properties": {
    "addr:full":"Plaz Universidad, 3 Valladolid Valladolid 47002",
    "addr:postcode":"47002",
    "addr:street":"Universidad",
    "iso:country":"ES",
    "sg:address":"Plaz Universidad, 3",
    "sg:city":"Valladolid",
    "sg:orig_category":"Agencias De Viajes",
    "sg:phone":"+34 983 21 20 22",
    "sg:postcode":"47002",
    "sg:province":"Valladolid",
    "sg:website":"www.trearural.com",
    "wof:name":"Cabezas Pascual Pilar",
    "wof:placetype":"venue"
},
  "geometry": {"coordinates":[-4.7218551636,41.6532058716],"type":"Point"}
}