{
  "type": "Feature",
  "properties": {
    "iso:country":"ES",
    "sg:address":"Calle de Ultramar, 5",
    "sg:city":"Valladolid",
    "sg:orig_category":"Carnicer\u00cdas, Carnicer\u00cdas",
    "sg:phone":"+34 983 27 75 96",
    "sg:postcode":"47006",
    "sg:province":"Valladolid",
    "wof:name":"Galache Anton Juan Jose",
    "wof:placetype":"venue"
},
  "geometry": {"coordinates":[-4.7408218384,41.6394691467],"type":"Point"}
}