{
  "type": "Feature",
  "properties": {
    "addr:full":"Pase Mina (de La), S/n Castellote Teruel 44560",
    "addr:housenumber":"s",
    "addr:postcode":"44560",
    "addr:street":"/ N",
    "iso:country":"ES",
    "sg:address":"Pase Mina (de La), S/n",
    "sg:city":"Castellote",
    "sg:orig_category":"Albergues",
    "sg:phone":"+34 978 88 75 96",
    "sg:postcode":"44560",
    "sg:province":"Teruel",
    "wof:name":"Hostal Castellote S.l.",
    "wof:placetype":"venue"
},
  "geometry": {"coordinates":[-0.3181439936,40.7997589111],"type":"Point"}
}