{
  "type": "Feature",
  "properties": {
    "iso:country":"ES",
    "sg:address":"Avda Palmeras Las, S/n",
    "sg:city":"Arroyo De La Miel-benalmadena Costa",
    "sg:orig_category":"Supermercados Y Hipermercados",
    "sg:phone":"+34 952 56 75 53",
    "sg:postcode":"29630",
    "sg:province":"M\u00e1laga",
    "sg:website":"www.mercadona.es",
    "wof:name":"Mercadona S A",
    "wof:placetype":"venue"
},
  "geometry": {"coordinates":[-4.5356974602,36.5922088623],"type":"Point"}
}