{
  "type": "Feature",
  "properties": {
    "iso:country":"ES",
    "sg:address":"Carrer de Gabriel Maura, 21",
    "sg:city":"Palma",
    "sg:orig_category":"Molduras, Junquillos, Listones Y Molduras Perforadas",
    "sg:phone":"+34 971 46 10 48",
    "sg:postcode":"07005",
    "sg:province":"Islas Baleares",
    "wof:name":"Vidal Vilanova Jose Miguel",
    "wof:placetype":"venue"
},
  "geometry": {"coordinates":[2.6588389874,39.5783081055],"type":"Point"}
}