{
  "type": "Feature",
  "properties": {
    "iso:country":"ES",
    "sg:address":"Calle de Emiliano Cabot, 19",
    "sg:city":"Isla Cristina",
    "sg:orig_category":"Guarder\u00cdas",
    "sg:phone":"+34 959 34 38 68",
    "sg:postcode":"21410",
    "sg:province":"Huelva",
    "wof:name":"Carrillo Martin Maria",
    "wof:placetype":"venue"
},
  "geometry": {"coordinates":[-7.3219909668,37.1996841431],"type":"Point"}
}