{
  "type": "Feature",
  "properties": {
    "addr:full":"Plaz Monterrey, 2 Salamanca Salamanca 37002",
    "addr:housenumber":"2",
    "addr:postcode":"37002",
    "addr:street":"Monterrey",
    "iso:country":"ES",
    "sg:address":"Plaz Monterrey, 2",
    "sg:city":"Salamanca",
    "sg:orig_category":"Agricultores, Agricultores",
    "sg:phone":"+34 923 21 29 33",
    "sg:postcode":"37002",
    "sg:province":"Salamanca",
    "wof:name":"Agralsa S. A.",
    "wof:placetype":"venue"
},
  "geometry": {"coordinates":[-5.666451931,40.9652557373],"type":"Point"}
}