{
  "type": "Feature",
  "properties": {
    "iso:country":"ES",
    "sg:address":"Calle de Cervera, Km. 0001,3",
    "sg:city":"Talavera Reina",
    "sg:orig_category":"Forjas Y Altos Hornos",
    "sg:phone":"+34 925 80 28 25",
    "sg:postcode":"45600",
    "sg:province":"Toledo",
    "wof:name":"Melchor De La Cruz Francisco",
    "wof:placetype":"venue"
},
  "geometry": {"coordinates":[-4.8324790001,39.9657020569],"type":"Point"}
}