{
  "type": "Feature",
  "properties": {
    "iso:country":"ES",
    "sg:address":"Carr Miguel De Cervantes, 19",
    "sg:city":"Palamos",
    "sg:orig_category":"Electrodom\u00c9sticos (al Por Menor)",
    "sg:phone":"+34 972 31 64 73",
    "sg:postcode":"17230",
    "sg:province":"Girona",
    "wof:name":"Electrodomesticos Felix Roa S.l.",
    "wof:placetype":"venue"
},
  "geometry": {"coordinates":[3.1293830872,41.8495063782],"type":"Point"}
}