{
  "type": "Feature",
  "properties": {
    "addr:full":"Calle de Nicolas Estevanez, 2 Puntillas Las Palmas 35240",
    "addr:housenumber":"2",
    "addr:postcode":"35240",
    "addr:street":"Calle De Nicolas Estevanez;Las Palmas",
    "iso:country":"ES",
    "sg:address":"Calle de Nicolas Estevanez, 2",
    "sg:city":"Puntillas",
    "sg:orig_category":"Mec\u00c1nico Del Autom\u00d3vil",
    "sg:phone":"+34 928 78 13 04",
    "sg:postcode":"35240",
    "sg:province":"Las Palmas",
    "wof:name":"Sanchez Ramirez Francisco Miguel",
    "wof:placetype":"venue"
},
  "geometry": {"coordinates":[-15.4088487625,27.9120388031],"type":"Point"}
}