{
  "type": "Feature",
  "properties": {
    "iso:country":"ES",
    "sg:address":"Carrer de Pere Iv, 78",
    "sg:city":"Barcelona",
    "sg:orig_category":"C\u00c1maras De Comercio E Industria, Oficios, Agricultura",
    "sg:phone":"+34 934 86 73 00",
    "sg:postcode":"08...",
    "sg:province":"Barcelona",
    "sg:website":"www-cir-sa.com",
    "wof:name":"Compa\u00d1ia De Informes Y Registros Mp S.a.",
    "wof:placetype":"venue"
},
  "geometry": {"coordinates":[2.1932981014,41.3971633911],"type":"Point"}
}