{
  "type": "Feature",
  "properties": {
    "addr:full":"Avda Obispo Perez Caceres, 6 G\u00fcimar Santa Cruz De Tenerife 38500",
    "addr:housenumber":"6",
    "addr:postcode":"38500",
    "addr:street":"Avda Obispo Perez Caceres",
    "iso:country":"ES",
    "sg:address":"Avda Obispo Perez Caceres, 6",
    "sg:city":"G\u00fcimar",
    "sg:orig_category":"Doctores En Medicina",
    "sg:phone":"+34 922 51 21 09",
    "sg:postcode":"38500",
    "sg:province":"Santa Cruz De Tenerife",
    "wof:name":"Alfonso Martin Sixto Carlos",
    "wof:placetype":"venue"
},
  "geometry": {"coordinates":[-16.4104862213,28.3144779205],"type":"Point"}
}