{
  "type": "Feature",
  "properties": {
    "addr:full":"Calle de Rodriguez De La Borbolla, 44 Algaba Sevilla 41980",
    "addr:housenumber":"44",
    "addr:postcode":"41980",
    "addr:street":"Calle De Rodriguez De La Borbolla",
    "iso:country":"ES",
    "sg:address":"Calle de Rodriguez De La Borbolla, 44",
    "sg:city":"Algaba",
    "sg:orig_category":"Asociaciones Y Clubs Deportivos",
    "sg:phone":"+34 955 78 81 27",
    "sg:postcode":"41980",
    "sg:province":"Sevilla",
    "wof:name":"Pe\u00f1a Sevillista Algabe\u00f1a",
    "wof:placetype":"venue"
},
  "geometry": {"coordinates":[-6.0153942108,37.4607162476],"type":"Point"}
}