{
  "type": "Feature",
  "properties": {
    "addr:full":"Calle de Leon Y Castillo, 324 Palmas De Gran Canaria Las Palmas 35007",
    "addr:housenumber":"324",
    "addr:postcode":"35007",
    "addr:street":"Calle De Leon Y Castillo",
    "iso:country":"ES",
    "sg:address":"Calle de Leon Y Castillo, 324",
    "sg:city":"Palmas De Gran Canaria",
    "sg:orig_category":"Bancos",
    "sg:phone":"+34 928 49 47 60",
    "sg:postcode":"35007",
    "sg:province":"Las Palmas",
    "wof:name":"Banc Sabadell S.a.",
    "wof:placetype":"venue"
},
  "geometry": {"coordinates":[-15.4295730591,28.1364860535],"type":"Point"}
}