{
  "type": "Feature",
  "properties": {
    "addr:full":"Avda Regimiento De Galicia, 15 Jaca Huesca 22700",
    "addr:housenumber":"15",
    "addr:postcode":"22700",
    "addr:street":"Avda Regimiento De Galicia",
    "iso:country":"ES",
    "sg:address":"Avda Regimiento De Galicia, 15",
    "sg:city":"Jaca",
    "sg:orig_category":"Producci\u00d3n, Distribuci\u00d3n De Gas Butano Y Propano",
    "sg:phone":"+34 974 36 22 42",
    "sg:postcode":"22700",
    "sg:province":"Huesca",
    "wof:name":"Viscasillas Samitier David",
    "wof:placetype":"venue"
},
  "geometry": {"coordinates":[-0.553113997,42.5681266785],"type":"Point"}
}