{
  "type": "Feature",
  "properties": {
    "addr:full":"Calle de Maninidra, 114 Cruce De Arinaga Las Palmas 35118",
    "addr:housenumber":"114",
    "addr:postcode":"35118",
    "addr:street":"Calle De Maninidra",
    "iso:country":"ES",
    "sg:address":"Calle de Maninidra, 114",
    "sg:city":"Cruce De Arinaga",
    "sg:orig_category":"Quincaller\u00cda (al Por Menor)",
    "sg:phone":"+34 928 18 13 32",
    "sg:postcode":"35118",
    "sg:province":"Las Palmas",
    "wof:name":"Sacramento Hernandez Pedro",
    "wof:placetype":"venue"
},
  "geometry": {"coordinates":[-15.426861763,27.8762836456],"type":"Point"}
}