{
  "type": "Feature",
  "properties": {
    "addr:full":"Calle de Camarena, 250 Madrid Madrid 28047",
    "addr:housenumber":"250",
    "addr:postcode":"28047",
    "addr:street":"Calle De Camarena",
    "iso:country":"ES",
    "sg:address":"Calle de Camarena, 250",
    "sg:city":"Madrid",
    "sg:orig_category":"Farmacias",
    "sg:phone":"+34 917 17 18 30",
    "sg:postcode":"28047",
    "sg:province":"Madrid",
    "wof:name":"Fernandez Bernal Jose Ramon",
    "wof:placetype":"venue"
},
  "geometry": {"coordinates":[-3.7573215961,40.3868522644],"type":"Point"}
}