{
  "type": "Feature",
  "properties": {
    "iso:country":"ES",
    "sg:address":"Joaquin Puig Bella Casa, 5",
    "sg:city":"Viver",
    "sg:orig_category":"Producci\u00d3n, Venta De Productos De Agricultura Biol\u00d3gica",
    "sg:phone":"+34 964 14 13 56",
    "sg:postcode":"12460",
    "sg:province":"Castell\u00f3n",
    "wof:name":"Movimientos Y Excavaciones Viver Sl",
    "wof:placetype":"venue"
},
  "geometry": {"coordinates":[-0.5972579718,39.9202728271],"type":"Point"}
}