{
  "type": "Feature",
  "properties": {
    "iso:country":"ES",
    "sg:address":"C/ Julio Hervas Sainz, 8",
    "sg:city":"Elche",
    "sg:orig_category":"Zapater\u00cdas",
    "sg:phone":"+34 965 45 00 00",
    "sg:postcode":"03203",
    "sg:province":"Alicante",
    "wof:name":"Suelas Asencio Aznar S.l.",
    "wof:placetype":"venue"
},
  "geometry": {"coordinates":[-0.6967049837,38.2548446655],"type":"Point"}
}