{
  "type": "Feature",
  "properties": {
    "iso:country":"ES",
    "sg:address":"Camino Viejo Simancas, 12",
    "sg:city":"Valladolid",
    "sg:orig_category":"T\u00c9cnicos Veterinarios",
    "sg:phone":"+34 983 47 34 01",
    "sg:postcode":"47008",
    "sg:province":"Valladolid",
    "wof:name":"Gonzalez Vallinas Delgado Pedro Luis Emiliano",
    "wof:placetype":"venue"
},
  "geometry": {"coordinates":[-4.7459931374,41.6272888184],"type":"Point"}
}