{
  "type": "Feature",
  "properties": {
    "iso:country":"ES",
    "sg:address":"Calle de General Casta\u00d1os, 20",
    "sg:city":"Portugalete",
    "sg:orig_category":"Ropa Para Ni\u00d1os (al Por Menor)",
    "sg:phone":"+34 944 95 21 98",
    "sg:postcode":"48920",
    "sg:province":"Vizcaya",
    "wof:name":"Monica Garcia Dura\u00f1ona",
    "wof:placetype":"venue"
},
  "geometry": {"coordinates":[-3.0196909904,43.3205604553],"type":"Point"}
}