{
  "type": "Feature",
  "properties": {
    "iso:country":"ES",
    "sg:address":"Avda Ategorrieta De, 29",
    "sg:city":"Donostia-san Sebastian",
    "sg:orig_category":"Material Y Herramientas Agr\u00cdcolas",
    "sg:phone":"+34 943 28 27 62",
    "sg:postcode":"20013",
    "sg:province":"Guip\u00f9zcoa",
    "wof:name":"Lantegia Makinaria Lopetegi",
    "wof:placetype":"venue"
},
  "geometry": {"coordinates":[-1.9681659937,43.3222503662],"type":"Point"}
}