{
  "type": "Feature",
  "properties": {
    "iso:country":"ES",
    "sg:address":"Calle de Enrique Ii, 8",
    "sg:city":"Pola De Siero",
    "sg:orig_category":"Cl\u00cdnicas Dentales",
    "sg:phone":"+34 985 72 20 94",
    "sg:postcode":"33510",
    "sg:province":"Asturias",
    "wof:name":"Gonzalez Ordiales Maria Pilar Jovita",
    "wof:placetype":"venue"
},
  "geometry": {"coordinates":[-5.6613211632,43.3928451538],"type":"Point"}
}