{
  "type": "Feature",
  "properties": {
    "iso:country":"ES",
    "sg:address":"Avda Cervantes (de), 12",
    "sg:city":"Cordoba",
    "sg:orig_category":"Expertos Contables",
    "sg:phone":"+34 957 48 57 02",
    "sg:postcode":"14008",
    "sg:province":"C\u00f3rdoba",
    "wof:name":"Gestoria Zafra S.l.",
    "wof:placetype":"venue"
},
  "geometry": {"coordinates":[-4.7847690582,37.8882865906],"type":"Point"}
}