{
  "type": "Feature",
  "properties": {
    "addr:full":"Carr Olot, 14 Besalu Girona 17850",
    "addr:housenumber":"14",
    "addr:postcode":"17850",
    "addr:street":"Carr Olot",
    "iso:country":"ES",
    "sg:address":"Carr Olot, 14",
    "sg:city":"Besalu",
    "sg:orig_category":"Carnicer\u00cdas, Carnicer\u00cdas",
    "sg:phone":"+34 972 59 04 44",
    "sg:postcode":"17850",
    "sg:province":"Girona",
    "wof:name":"Junca Gratacos Ramon",
    "wof:placetype":"venue"
},
  "geometry": {"coordinates":[2.6976718903,42.2003211975],"type":"Point"}
}