{
  "type": "Feature",
  "properties": {
    "addr:full":"Carr Major, 57 Esterri D'aneu Lleida 25580",
    "addr:housenumber":"57",
    "addr:postcode":"25580",
    "addr:street":"Carr Major",
    "iso:country":"ES",
    "sg:address":"Carr Major, 57",
    "sg:city":"Esterri D'aneu",
    "sg:orig_category":"Quincaller\u00cda (al Por Menor)",
    "sg:phone":"+34 973 62 60 65",
    "sg:postcode":"25580",
    "sg:province":"Lleida",
    "wof:name":"Casa Balbino S.l.",
    "wof:placetype":"venue"
},
  "geometry": {"coordinates":[0.6250849962,41.6137962341],"type":"Point"}
}