{
  "type": "Feature",
  "properties": {
    "iso:country":"ES",
    "sg:address":"Minguillos, S/n",
    "sg:city":"Andujar",
    "sg:orig_category":"Psic\u00d3logos",
    "sg:phone":"+34 953 50 61 07",
    "sg:postcode":"23740",
    "sg:province":"Ja\u00e9n",
    "wof:name":"Soler Hermosilla Rosa Maria",
    "wof:placetype":"venue"
},
  "geometry": {"coordinates":[-4.0338988304,38.039768219],"type":"Point"}
}