{
  "type": "Feature",
  "properties": {
    "addr:full":"Calle de Virgen Del Puig, 20 Valencia Valencia 46011",
    "addr:housenumber":"20",
    "addr:postcode":"46011",
    "addr:street":"Calle De Virgen Del Puig",
    "iso:country":"ES",
    "sg:address":"Calle de Virgen Del Puig, 20",
    "sg:city":"Valencia",
    "sg:orig_category":"Mantenimiento Industrial",
    "sg:phone":"+34 963 67 29 09",
    "sg:postcode":"46011",
    "sg:province":"Valencia",
    "wof:name":"Reductores Ref S.l.",
    "wof:placetype":"venue"
},
  "geometry": {"coordinates":[-0.3359290063,39.462726593],"type":"Point"}
}