{
  "type": "Feature",
  "properties": {
    "iso:country":"ES",
    "sg:address":"Calle de Sierra (la), 7",
    "sg:city":"Noja",
    "sg:orig_category":"Hoteles",
    "sg:phone":"+34 942 67 54 20",
    "sg:postcode":"39180",
    "sg:province":"Cantabria",
    "wof:name":"Cano Quintana S.a.",
    "wof:placetype":"venue"
},
  "geometry": {"coordinates":[-3.5217471123,43.4916191101],"type":"Point"}
}