{
  "type": "Feature",
  "properties": {
    "iso:country":"ES",
    "sg:address":"Calle de Francisco De Quevedo, 1",
    "sg:city":"Granada",
    "sg:orig_category":"Molduras, Junquillos, Listones Y Molduras Perforadas",
    "sg:phone":"+34 958 12 09 78",
    "sg:postcode":"18006",
    "sg:province":"Granada",
    "sg:website":"www.teczone.es",
    "wof:name":"Teczone Espa\u00f1ola S.a.",
    "wof:placetype":"venue"
},
  "geometry": {"coordinates":[-3.5974140167,37.1636314392],"type":"Point"}
}