{
  "type": "Feature",
  "properties": {
    "addr:full":"Carrer de Vicen\u00c7 J Rossello, 30 Palma Islas Baleares 07013",
    "addr:housenumber":"30",
    "addr:postcode":"07013",
    "addr:street":"Carrer De Vicenc\u0327 J Rossello",
    "iso:country":"ES",
    "sg:address":"Carrer de Vicen\u00c7 J Rossello, 30",
    "sg:city":"Palma",
    "sg:orig_category":"Transporte En General",
    "sg:phone":"+34 971 45 03 89",
    "sg:postcode":"07013",
    "sg:province":"Islas Baleares",
    "wof:name":"Bombas Y Servicios Son Dameto S.l",
    "wof:placetype":"venue"
},
  "geometry": {"coordinates":[2.6315529346,39.5792808533],"type":"Point"}
}