{
  "type": "Feature",
  "properties": {
    "addr:full":"Carrer de Tomas Edison, 17 Ondara Alicante 03760",
    "addr:housenumber":"17",
    "addr:postcode":"03760",
    "addr:street":"Carrer De Tomas Edison",
    "iso:country":"ES",
    "sg:address":"Carrer de Tomas Edison, 17",
    "sg:city":"Ondara",
    "sg:orig_category":"Quincaller\u00cda (al Por Menor)",
    "sg:phone":"+34 965 76 70 79",
    "sg:postcode":"03760",
    "sg:province":"Alicante",
    "wof:name":"Ferreteria Els Poblets S.l.",
    "wof:placetype":"venue"
},
  "geometry": {"coordinates":[0.0206179991,38.8207244873],"type":"Point"}
}