{
  "type": "Feature",
  "properties": {
    "addr:full":"Carrer de Violant Hongria R Arago, 59 Barcelona Barcelona 08028",
    "addr:housenumber":"hongria;59",
    "addr:postcode":"08028",
    "addr:street":"Carrer De Violant;R Arago",
    "iso:country":"ES",
    "sg:address":"Carrer de Violant Hongria R Arago, 59",
    "sg:city":"Barcelona",
    "sg:orig_category":"Suministros Para Exposiciones, Ferias, Salones",
    "sg:phone":"+34 934 90 77 34",
    "sg:postcode":"08028",
    "sg:province":"Barcelona",
    "wof:name":"Eina S.l.",
    "wof:placetype":"venue"
},
  "geometry": {"coordinates":[2.1289379597,41.3783798218],"type":"Point"}
}