{
  "type": "Feature",
  "properties": {
    "iso:country":"ES",
    "sg:address":"Calle de Poeta Francisco Antonio Jimenez, S/n",
    "sg:city":"Yecla",
    "sg:orig_category":"Empresas De Carpinter\u00cda Met\u00c1lica",
    "sg:phone":"+34 968 71 88 04",
    "sg:postcode":"30510",
    "sg:province":"Murcia",
    "wof:name":"Yeclaperfil S.l.l.",
    "wof:placetype":"venue"
},
  "geometry": {"coordinates":[-1.173699379,38.6051635742],"type":"Point"}
}