{
  "type": "Feature",
  "properties": {
    "iso:country":"ES",
    "sg:address":"Calle de Paz, 40",
    "sg:city":"Valencia",
    "sg:orig_category":"Procuradores",
    "sg:phone":"+34 963 51 14 13",
    "sg:postcode":"46003",
    "sg:province":"Valencia",
    "wof:name":"Llorente Sanchez Beatriz",
    "wof:placetype":"venue"
},
  "geometry": {"coordinates":[-0.3714663088,39.4729804993],"type":"Point"}
}