{
  "type": "Feature",
  "properties": {
    "addr:full":"Calle de Pradilla, 16 Zaragoza Zaragoza 50007",
    "addr:housenumber":"16",
    "addr:postcode":"50007",
    "addr:street":"Calle De Pradilla",
    "iso:country":"ES",
    "sg:address":"Calle de Pradilla, 16",
    "sg:city":"Zaragoza",
    "sg:orig_category":"Alquiler De Casas Y Habitaciones Amuebladas",
    "sg:phone":"+34 976 38 56 51",
    "sg:postcode":"50007",
    "sg:province":"Zaragoza",
    "wof:name":"Garcia Rebollo Laura",
    "wof:placetype":"venue"
},
  "geometry": {"coordinates":[-0.8836460114,41.637046814],"type":"Point"}
}