{
  "type": "Feature",
  "properties": {
    "iso:country":"ES",
    "sg:address":"Calle de Islas Cies, 3",
    "sg:city":"Caceres",
    "sg:orig_category":"Psic\u00d3logos",
    "sg:phone":"+34 927 29 21 25",
    "sg:postcode":"10001",
    "sg:province":"C\u00e1ceres",
    "wof:name":"Moreno Bartolome Coronada",
    "wof:placetype":"venue"
},
  "geometry": {"coordinates":[-6.3864579201,39.4745521545],"type":"Point"}
}