{
  "type": "Feature",
  "properties": {
    "addr:full":"Av Catalunya, 20 Blanes Girona 17300",
    "addr:housenumber":"20",
    "addr:postcode":"17300",
    "addr:street":"Av Catalunya",
    "iso:country":"ES",
    "sg:address":"Av Catalunya, 20",
    "sg:city":"Blanes",
    "sg:orig_category":"Carnicer\u00cdas, Carnicer\u00cdas",
    "sg:phone":"+34 972 33 37 01",
    "sg:postcode":"17300",
    "sg:province":"Girona",
    "wof:name":"Fernandez Esteo Juan Antonio",
    "wof:placetype":"venue"
},
  "geometry": {"coordinates":[2.7744510174,41.6670875549],"type":"Point"}
}