{
  "type": "Feature",
  "properties": {
    "addr:full":"Calle de Reina Fabiola, 20 Zaragoza Zaragoza 50008",
    "addr:housenumber":"20",
    "addr:postcode":"50008",
    "addr:street":"Calle De Reina Fabiola",
    "iso:country":"ES",
    "sg:address":"Calle de Reina Fabiola, 20",
    "sg:city":"Zaragoza",
    "sg:orig_category":"Comercio, Reparaci\u00d3n De Bicicletas, De Motocicletas, De Accesorios",
    "sg:phone":"+34 976 42 60 40",
    "sg:postcode":"50008",
    "sg:province":"Zaragoza",
    "wof:name":"Ciclos Marcen S.l.",
    "wof:placetype":"venue"
},
  "geometry": {"coordinates":[-0.8744609952,41.6454277039],"type":"Point"}
}