{
  "type": "Feature",
  "properties": {
    "addr:full":"R. Laporta, 9 Cantalapiedra Salamanca 37400",
    "addr:housenumber":"9",
    "addr:postcode":"37400",
    "addr:street":"Laporta",
    "iso:country":"ES",
    "sg:address":"R. Laporta, 9",
    "sg:city":"Cantalapiedra",
    "sg:orig_category":"Bancos",
    "sg:phone":"+34 923 53 00 32",
    "sg:postcode":"37400",
    "sg:province":"Salamanca",
    "sg:website":"www.bancocastilla.es",
    "wof:name":"Banco De Castilla",
    "wof:placetype":"venue"
},
  "geometry": {"coordinates":[-5.1837949753,41.1258163452],"type":"Point"}
}