{
  "type": "Feature",
  "properties": {
    "addr:full":"Cno. Reis, 619 Sa Indioteria Islas Baleares 07009",
    "addr:housenumber":"619",
    "addr:postcode":"07009",
    "addr:street":"Cno. Reis;Islas",
    "iso:country":"ES",
    "sg:address":"Cno. Reis, 619",
    "sg:city":"Sa Indioteria",
    "sg:orig_category":"Producci\u00d3n De Abonos Y De Fertilizantes",
    "sg:phone":"+34 971 29 17 31",
    "sg:postcode":"07009",
    "sg:province":"Islas Baleares",
    "wof:name":"Carrio Salom Jose",
    "wof:placetype":"venue"
},
  "geometry": {"coordinates":[2.6776249409,39.6072845459],"type":"Point"}
}