{
  "type": "Feature",
  "properties": {
    "iso:country":"ES",
    "sg:address":"Avda Aduana (la), 11",
    "sg:city":"Roquetas Mar",
    "sg:orig_category":"Notarios",
    "sg:phone":"+34 950 32 60 72",
    "sg:postcode":"04740",
    "sg:province":"Almer\u00eda",
    "wof:name":"Pe\u00f1a Pe\u00f1a Y Lopez Monzo S.c.",
    "wof:placetype":"venue"
},
  "geometry": {"coordinates":[-2.6109991074,36.7681999207],"type":"Point"}
}