{
  "type": "Feature",
  "properties": {
    "addr:full":"Avda Industria (de La), 3 Coslada Madrid 28820",
    "addr:housenumber":"3",
    "addr:postcode":"28820",
    "addr:street":"Avda Industria De La",
    "iso:country":"ES",
    "sg:address":"Avda Industria (de La), 3",
    "sg:city":"Coslada",
    "sg:orig_category":"Art\u00cdculos De Decoraci\u00d3n",
    "sg:phone":"+34 916 74 61 90",
    "sg:postcode":"28820",
    "sg:province":"Madrid",
    "wof:name":"Decoraciones Quintana S.a.",
    "wof:placetype":"venue"
},
  "geometry": {"coordinates":[-3.5494089127,40.4359092712],"type":"Point"}
}