{
  "type": "Feature",
  "properties": {
    "addr:full":"Calle de Vega, 1 Chiclana De La Frontera C\u00e1diz 11130",
    "addr:housenumber":"1",
    "addr:postcode":"11130",
    "addr:street":"Calle De Vega",
    "iso:country":"ES",
    "sg:address":"Calle de Vega, 1",
    "sg:city":"Chiclana De La Frontera",
    "sg:orig_category":"Zapatos (al Por Menor)",
    "sg:phone":"+34 956 40 21 07",
    "sg:postcode":"11130",
    "sg:province":"C\u00e1diz",
    "wof:name":"Caprishoes S.l.",
    "wof:placetype":"venue"
},
  "geometry": {"coordinates":[-6.1472520828,36.4209976196],"type":"Point"}
}