{
  "type": "Feature",
  "properties": {
    "addr:full":"Calle de Tronperri Kalea, 6 Durango Vizcaya 48200",
    "addr:housenumber":"6",
    "addr:postcode":"48200",
    "addr:street":"Calle De Tronperri Kalea",
    "iso:country":"ES",
    "sg:address":"Calle de Tronperri Kalea, 6",
    "sg:city":"Durango",
    "sg:orig_category":"Plomeros",
    "sg:phone":"+34 946 81 39 20",
    "sg:postcode":"48200",
    "sg:province":"Vizcaya",
    "wof:name":"Fontaneria Matiena S.l.",
    "wof:placetype":"venue"
},
  "geometry": {"coordinates":[-2.634196043,43.1701698303],"type":"Point"}
}