{
  "type": "Feature",
  "properties": {
    "iso:country":"ES",
    "sg:address":"Avda Giorgeta, 24",
    "sg:city":"Valencia",
    "sg:orig_category":"Consultas M\u00c9dicas",
    "sg:phone":"+34 963 80 85 98",
    "sg:postcode":"46007",
    "sg:province":"Valencia",
    "wof:name":"Centro Provincial De Reconocimiento De Conductores De Valencia S.a.",
    "wof:placetype":"venue"
},
  "geometry": {"coordinates":[-0.3849189878,39.4595222473],"type":"Point"}
}