{
  "type": "Feature",
  "properties": {
    "iso:country":"ES",
    "sg:address":"Av Trabucaires, 12",
    "sg:city":"Solsona",
    "sg:orig_category":"Teatros Y Salas De Espect\u00c1culos",
    "sg:phone":"+34 973 48 09 73",
    "sg:postcode":"25280",
    "sg:province":"Lleida",
    "wof:name":"Klick Cavern S.l.",
    "wof:placetype":"venue"
},
  "geometry": {"coordinates":[1.5205470324,41.9956932068],"type":"Point"}
}