{
  "type": "Feature",
  "properties": {
    "iso:country":"ES",
    "sg:address":"Carrer de Pare Roldos, 7",
    "sg:city":"Barcelona",
    "sg:orig_category":"Asociaciones, Organismos Culturales Y Socioeducativos",
    "sg:phone":"+34 934 08 36 15",
    "sg:postcode":"08041",
    "sg:province":"Barcelona",
    "wof:name":"Asociacion Cultura Phenix",
    "wof:placetype":"venue"
},
  "geometry": {"coordinates":[2.1794638634,41.4210662842],"type":"Point"}
}