{
  "type": "Feature",
  "properties": {
    "addr:full":"C/ Sant Antoni, 11 Cerdanyola Valles Barcelona 08290",
    "addr:housenumber":"11",
    "addr:postcode":"08290",
    "addr:street":"C / Sant Antoni;Valles Barcelona",
    "iso:country":"ES",
    "sg:address":"C/ Sant Antoni, 11",
    "sg:city":"Cerdanyola Valles",
    "sg:orig_category":"Peluqueros: De Se\u00d1oras",
    "sg:phone":"+34 935 80 05 42",
    "sg:postcode":"08290",
    "sg:province":"Barcelona",
    "wof:name":"Rodriguez Garcia Maria Jose",
    "wof:placetype":"venue"
},
  "geometry": {"coordinates":[2.137485981,41.4919586182],"type":"Point"}
}