{
  "type": "Feature",
  "properties": {
    "addr:full":"Plaz Princi Jerez, 12 Jerez De La Frontera C\u00e1diz 11406",
    "addr:housenumber":"12",
    "addr:postcode":"11406",
    "addr:street":"Jerez",
    "iso:country":"ES",
    "sg:address":"Plaz Princi Jerez, 12",
    "sg:city":"Jerez De La Frontera",
    "sg:orig_category":"M\u00c9dicos: Estomatolog\u00cda",
    "sg:phone":"+34 956 33 02 52",
    "sg:postcode":"11406",
    "sg:province":"C\u00e1diz",
    "wof:name":"Garcia Solis Jorge",
    "wof:placetype":"venue"
},
  "geometry": {"coordinates":[-6.116918087,36.6822319031],"type":"Point"}
}