{
  "type": "Feature",
  "properties": {
    "iso:country":"ES",
    "sg:address":"Ctra Piedrabuena, 33",
    "sg:city":"Ciudad Real",
    "sg:orig_category":"Maquinaria Para Industrias Diversas",
    "sg:phone":"+34 926 21 65 11",
    "sg:postcode":"13002",
    "sg:province":"Ciudad Real",
    "wof:name":"Excavaciones Calatrava S.l.",
    "wof:placetype":"venue"
},
  "geometry": {"coordinates":[-3.9398999214,38.9774055481],"type":"Point"}
}