{
  "type": "Feature",
  "properties": {
    "addr:full":"Calle de Ramon J. Sender, 8 Alca\u00f1iz Teruel 44600",
    "addr:housenumber":"8",
    "addr:postcode":"44600",
    "addr:street":"Calle De Ramon J. Sender",
    "iso:country":"ES",
    "sg:address":"Calle de Ramon J. Sender, 8",
    "sg:city":"Alca\u00f1iz",
    "sg:orig_category":"Creaci\u00d3n De Sitios, Hosting Internet",
    "sg:phone":"+34 978 83 22 01",
    "sg:postcode":"44600",
    "sg:province":"Teruel",
    "sg:website":"www.sedinet.com",
    "wof:name":"Sedinet S.l.",
    "wof:placetype":"venue"
},
  "geometry": {"coordinates":[-0.1285450011,41.0509796143],"type":"Point"}
}