{
  "type": "Feature",
  "properties": {
    "iso:country":"ES",
    "sg:address":"Avgd Balmes, 5",
    "sg:city":"Lleida",
    "sg:orig_category":"Asesor\u00cda Fiscal Y Jur\u00cddica",
    "sg:phone":"+34 973 27 41 33",
    "sg:postcode":"25006",
    "sg:province":"Lleida",
    "wof:name":"L'assessoria Fiscal Comptabilitats Consultoria S.l.",
    "wof:placetype":"venue"
},
  "geometry": {"coordinates":[0.5619999766,41.6497535706],"type":"Point"}
}