{
  "type": "Feature",
  "properties": {
    "iso:country":"ES",
    "sg:address":"Av Can Castells, 14",
    "sg:city":"Can Castells",
    "sg:orig_category":"Quincaller\u00cda (al Por Menor)",
    "sg:phone":"+34 938 40 20 44",
    "sg:postcode":"08420",
    "sg:province":"Barcelona",
    "wof:name":"Suministros Industriales Rifa S.a.",
    "wof:placetype":"venue"
},
  "geometry": {"coordinates":[2.2783401012,41.6220207214],"type":"Point"}
}