{
  "type": "Feature",
  "properties": {
    "addr:full":"Calle de San Anton, 26 San Anton Murcia 30009",
    "addr:housenumber":"26",
    "addr:postcode":"30009",
    "addr:street":"Calle De San Anton",
    "iso:country":"ES",
    "sg:address":"Calle de San Anton, 26",
    "sg:city":"San Anton",
    "sg:orig_category":"Fabricaci\u00d3n De Muebles",
    "sg:phone":"+34 968 28 22 31",
    "sg:postcode":"30009",
    "sg:province":"Murcia",
    "sg:website":"www.tocamadera.es",
    "wof:name":"Tocar Madera Amueblamientos S.l.",
    "wof:placetype":"venue"
},
  "geometry": {"coordinates":[-1.1405960321,37.9911575317],"type":"Point"}
}