{
  "type": "Feature",
  "properties": {
    "addr:full":"Calle de Koskojales, 2 Irauregi Vizcaya 48810",
    "addr:housenumber":"2",
    "addr:postcode":"48810",
    "addr:street":"Calle De Koskojales",
    "iso:country":"ES",
    "sg:address":"Calle de Koskojales, 2",
    "sg:city":"Irauregi",
    "sg:orig_category":"Peluquer\u00cdas, Peluquer\u00cda Mixta",
    "sg:phone":"+34 944 98 00 94",
    "sg:postcode":"48810",
    "sg:province":"Vizcaya",
    "wof:name":"Maria Teresa Ruedas E Iratxe Garcia C.b.",
    "wof:placetype":"venue"
},
  "geometry": {"coordinates":[-2.9891839027,43.2450904846],"type":"Point"}
}