{
  "type": "Feature",
  "properties": {
    "iso:country":"ES",
    "sg:address":"Ctra Cordoba-malaga, Km. 0437,5",
    "sg:city":"Montemayor",
    "sg:orig_category":"M\u00c1rmoles, Granitos Y Piedras Naturales",
    "sg:phone":"+34 957 33 20 22",
    "sg:postcode":"14530",
    "sg:province":"C\u00f3rdoba",
    "wof:name":"Trillo Herrador Pedro",
    "wof:placetype":"venue"
},
  "geometry": {"coordinates":[-4.7028717995,37.6450195312],"type":"Point"}
}