{
  "type": "Feature",
  "properties": {
    "iso:country":"ES",
    "sg:address":"Avda Pio Xii, 4",
    "sg:city":"Sig\u00fcenza",
    "sg:orig_category":"Centros De Coordinaci\u00d3n",
    "sg:phone":"+34 949 39 03 50",
    "sg:postcode":"19250",
    "sg:province":"Guadalajara",
    "wof:name":"Pedro Moreno E Hijos S.l.",
    "wof:placetype":"venue"
},
  "geometry": {"coordinates":[-2.6456980705,41.0673561096],"type":"Point"}
}