{
  "type": "Feature",
  "properties": {
    "addr:full":"Calle de Forcarey, 24 Coru\u00d1a La Coru\u00f1a 15002",
    "addr:housenumber":"24",
    "addr:postcode":"15002",
    "addr:street":"Calle De Forcarey;La Corun\u0303A",
    "iso:country":"ES",
    "sg:address":"Calle de Forcarey, 24",
    "sg:city":"Coru\u00d1a",
    "sg:orig_category":"Molduras, Junquillos, Listones Y Molduras Perforadas",
    "sg:phone":"+34 981 21 14 05",
    "sg:postcode":"15002",
    "sg:province":"La Coru\u00f1a",
    "wof:name":"Lema Blanco Jose Maria",
    "wof:placetype":"venue"
},
  "geometry": {"coordinates":[-8.4055223465,43.3787078857],"type":"Point"}
}