{
  "type": "Feature",
  "properties": {
    "addr:full":"Avda Carretera De Granada, 31 Caravaca Cruz Murcia 30400",
    "addr:housenumber":"31",
    "addr:postcode":"30400",
    "addr:street":"Avda Carretera De Granada",
    "iso:country":"ES",
    "sg:address":"Avda Carretera De Granada, 31",
    "sg:city":"Caravaca Cruz",
    "sg:orig_category":"Alimentaci\u00d3n General (al Por Menor)",
    "sg:phone":"+34 968 70 14 52",
    "sg:postcode":"30400",
    "sg:province":"Murcia",
    "wof:name":"Carre\u00f1o Y Montiel",
    "wof:placetype":"venue"
},
  "geometry": {"coordinates":[-1.8659420013,38.1019973755],"type":"Point"}
}