{
  "type": "Feature",
  "properties": {
    "iso:country":"ES",
    "sg:address":"Pase San Vicente, 61",
    "sg:city":"Valladolid",
    "sg:orig_category":"Alquiler De Salones",
    "sg:phone":"+34 983 21 77 66",
    "sg:postcode":"47013",
    "sg:province":"Valladolid",
    "wof:name":"Casaolid S.l.",
    "wof:placetype":"venue"
},
  "geometry": {"coordinates":[-4.7193050385,41.6421775818],"type":"Point"}
}