{
  "type": "Feature",
  "properties": {
    "addr:full":"Calle de Cinco De Marzo, 18 Zaragoza Zaragoza 50004",
    "addr:housenumber":"18",
    "addr:postcode":"50004",
    "addr:street":"Calle De Cinco De Marzo",
    "iso:country":"ES",
    "sg:address":"Calle de Cinco De Marzo, 18",
    "sg:city":"Zaragoza",
    "sg:orig_category":"Perfumer\u00cda (al Por Menor)",
    "sg:phone":"+34 976 21 45 34",
    "sg:postcode":"50004",
    "sg:province":"Zaragoza",
    "sg:website":"www.paginasamarillas.es",
    "wof:name":"Barrera Laguna Pilar",
    "wof:placetype":"venue"
},
  "geometry": {"coordinates":[-0.8833960295,41.6521110535],"type":"Point"}
}