{
  "type": "Feature",
  "properties": {
    "addr:full":"Av Saler, 9 Silla Valencia 46460",
    "addr:housenumber":"9",
    "addr:postcode":"46460",
    "addr:street":"Av Saler",
    "iso:country":"ES",
    "sg:address":"Av Saler, 9",
    "sg:city":"Silla",
    "sg:orig_category":"Intercambios, Trueques",
    "sg:phone":"+34 961 21 60 61",
    "sg:postcode":"46460",
    "sg:province":"Valencia",
    "wof:name":"Espacio Global Trading S.l.",
    "wof:placetype":"venue"
},
  "geometry": {"coordinates":[-0.4077360034,39.3747520447],"type":"Point"}
}