{
  "type": "Feature",
  "properties": {
    "iso:country":"ES",
    "sg:address":"Avda Doctor Gregorio Mara\u00d1on, 78",
    "sg:city":"Torrevieja",
    "sg:orig_category":"Persianas Interiores, Exteriores",
    "sg:phone":"+34 966 70 12 13",
    "sg:postcode":"03180",
    "sg:province":"Alicante",
    "wof:name":"Decoraciones Barron S.l.",
    "wof:placetype":"venue"
},
  "geometry": {"coordinates":[-0.684607029,37.9756202698],"type":"Point"}
}