{
  "type": "Feature",
  "properties": {
    "addr:full":"Calle de Vi\u00d1a (de La), 6 Collado Mediano Madrid 28450",
    "addr:housenumber":"6",
    "addr:postcode":"28450",
    "addr:street":"Calle De Vin\u0303A De La",
    "iso:country":"ES",
    "sg:address":"Calle de Vi\u00d1a (de La), 6",
    "sg:city":"Collado Mediano",
    "sg:orig_category":"Pizzer\u00cdas",
    "sg:phone":"+34 918 55 73 81",
    "sg:postcode":"28450",
    "sg:province":"Madrid",
    "wof:name":"Martin Alonso Celestino",
    "wof:placetype":"venue"
},
  "geometry": {"coordinates":[-4.0258069038,40.6947174072],"type":"Point"}
}