{
  "type": "Feature",
  "properties": {
    "iso:country":"ES",
    "sg:address":"Carrer de Vint-i-un, 43",
    "sg:city":"Bonavista",
    "sg:orig_category":"Reposter\u00cdas",
    "sg:phone":"+34 977 55 06 98",
    "sg:postcode":"43100",
    "sg:province":"Tarragona",
    "wof:name":"Fleca Flaque S.a.",
    "wof:placetype":"venue"
},
  "geometry": {"coordinates":[1.1947499514,41.1214942932],"type":"Point"}
}