{
  "type": "Feature",
  "properties": {
    "iso:country":"ES",
    "sg:address":"Pase Xunqueira (da), 11",
    "sg:city":"Redondela",
    "sg:orig_category":"Frutas, Legumbres Frescas Y Tempranas (al Por Menor)",
    "sg:phone":"+34 986 40 13 19",
    "sg:postcode":"36800",
    "sg:province":"Pontevedra",
    "wof:name":"Frucogal Frutera Comercial Gallega S.l.",
    "wof:placetype":"venue"
},
  "geometry": {"coordinates":[-8.6090641022,42.2820243835],"type":"Point"}
}