{
  "type": "Feature",
  "properties": {
    "addr:full":"Plaz Constitucion, S/n Valdepe\u00e7as De Jaen Ja\u00e9n 23150",
    "addr:postcode":"23150",
    "addr:street":"Constitucion S / N",
    "iso:country":"ES",
    "sg:address":"Plaz Constitucion, S/n",
    "sg:city":"Valdepe\u00e7as De Jaen",
    "sg:orig_category":"Cajas De Ahorro",
    "sg:phone":"+34 953 31 01 25",
    "sg:postcode":"23150",
    "sg:province":"Ja\u00e9n",
    "wof:name":"Caixa D'estalvis I Pensions De Barcelona",
    "wof:placetype":"venue"
},
  "geometry": {"coordinates":[-3.8200590611,37.5903167725],"type":"Point"}
}