{
  "type": "Feature",
  "properties": {
    "addr:full":"Carrer de Alfons Xiii, 7 Sabadell Barcelona 08202",
    "addr:housenumber":"7",
    "addr:postcode":"08202",
    "addr:street":"Carrer De Alfons Xiii",
    "iso:country":"ES",
    "sg:address":"Carrer de Alfons Xiii, 7",
    "sg:city":"Sabadell",
    "sg:orig_category":"Cajas De Ahorro",
    "sg:phone":"+34 937 45 90 66",
    "sg:postcode":"08202",
    "sg:province":"Barcelona",
    "wof:name":"Caixa D'estalvis De Manresa",
    "wof:placetype":"venue"
},
  "geometry": {"coordinates":[2.1101059914,41.5458030701],"type":"Point"}
}