{
  "type": "Feature",
  "properties": {
    "addr:full":"Calle de Francisco Guzman, 28 Madrid Madrid 28025",
    "addr:housenumber":"28",
    "addr:postcode":"madrid;28025",
    "addr:street":"Calle De Francisco Guzman",
    "iso:country":"ES",
    "sg:address":"Calle de Francisco Guzman, 28",
    "sg:city":"Madrid",
    "sg:orig_category":"Asociaciones, Organismos Culturales Y Socioeducativos",
    "sg:phone":"+34 915 60 14 79",
    "sg:postcode":"28025",
    "sg:province":"Madrid",
    "wof:name":"Teatro En El Aire S.l",
    "wof:placetype":"venue"
},
  "geometry": {"coordinates":[-3.7288200855,40.3856620789],"type":"Point"}
}