{
  "type": "Feature",
  "properties": {
    "addr:full":"Calle de Ruiz Mu\u00d1iz, 22 Ejido Las Palmas 35200",
    "addr:housenumber":"22 ejido",
    "addr:postcode":"35200",
    "addr:street":"Calle De Ruiz Mun\u0303Iz;Las Palmas",
    "iso:country":"ES",
    "sg:address":"Calle de Ruiz Mu\u00d1iz, 22",
    "sg:city":"Ejido",
    "sg:orig_category":"Maquinaria Neum\u00c1tica",
    "sg:phone":"+34 928 69 28 61",
    "sg:postcode":"35200",
    "sg:province":"Las Palmas",
    "wof:name":"Oleohidraulica M. A. J. A. S. A.",
    "wof:placetype":"venue"
},
  "geometry": {"coordinates":[-15.4300985336,27.9896793365],"type":"Point"}
}