{
  "type": "Feature",
  "properties": {
    "iso:country":"ES",
    "sg:address":"Plaz San Bruno, 12",
    "sg:city":"Burgos",
    "sg:orig_category":"Mercer\u00cda, Lencer\u00cda (al Por Menor)",
    "sg:phone":"+34 947 24 17 97",
    "sg:postcode":"09007",
    "sg:province":"Burgos",
    "wof:name":"Rodriguez Rodriguez Elisa",
    "wof:placetype":"venue"
},
  "geometry": {"coordinates":[-3.6717169285,42.349861145],"type":"Point"}
}