{
  "type": "Feature",
  "properties": {
    "addr:full":"C/ Gabriel Y Galan, 25 Elche Alicante 03202",
    "addr:housenumber":"25",
    "addr:postcode":"03202",
    "addr:street":"C / Gabriel Y Galan",
    "iso:country":"ES",
    "sg:address":"C/ Gabriel Y Galan, 25",
    "sg:city":"Elche",
    "sg:orig_category":"Inmobiliaria (agencias)",
    "sg:phone":"+34 965 45 31 12",
    "sg:postcode":"03202",
    "sg:province":"Alicante",
    "wof:name":"Promociones Anton Bonet S.l.",
    "wof:placetype":"venue"
},
  "geometry": {"coordinates":[-0.6919109821,38.2684555054],"type":"Point"}
}