{
  "type": "Feature",
  "properties": {
    "addr:full":"Calle de Santa Maria, 6 Roa Burgos 09300",
    "addr:housenumber":"6",
    "addr:postcode":"09300",
    "addr:street":"Calle De Santa Maria",
    "iso:country":"ES",
    "sg:address":"Calle de Santa Maria, 6",
    "sg:city":"Roa",
    "sg:orig_category":"Cajas Para Embalar",
    "sg:phone":"+34 947 54 02 55",
    "sg:postcode":"09300",
    "sg:province":"Burgos",
    "wof:name":"Caja Rural De Burgos",
    "wof:placetype":"venue"
},
  "geometry": {"coordinates":[-3.9286220074,41.6970024109],"type":"Point"}
}