{
  "type": "Feature",
  "properties": {
    "iso:country":"ES",
    "sg:address":"San Fermin, 59",
    "sg:city":"Iru\u00f1a",
    "sg:orig_category":"Agencias De Viajes",
    "sg:phone":"+34 948 15 15 16",
    "sg:postcode":"31003",
    "sg:province":"Navarra",
    "sg:website":"www.viajesiberia.com",
    "wof:name":"Viajes Iberia S.a.",
    "wof:placetype":"venue"
},
  "geometry": {"coordinates":[-1.6417479515,42.8103713989],"type":"Point"}
}