{
  "type": "Feature",
  "properties": {
    "addr:full":"Calle de Grupo Escolar, 27 Zarzadilla De Totana Murcia 30814",
    "addr:postcode":"30814",
    "addr:street":"Calle De Grupo",
    "iso:country":"ES",
    "sg:address":"Calle de Grupo Escolar, 27",
    "sg:city":"Zarzadilla De Totana",
    "sg:orig_category":"Poller\u00cda Y Caza (al Por Menor)",
    "sg:phone":"+34 968 49 40 56",
    "sg:postcode":"30814",
    "sg:province":"Murcia",
    "wof:name":"Guillen Rojo Mateo",
    "wof:placetype":"venue"
},
  "geometry": {"coordinates":[-1.7063320875,37.8786506653],"type":"Point"}
}