{
  "type": "Feature",
  "properties": {
    "iso:country":"ES",
    "sg:address":"Avda Libertad (de La), 91",
    "sg:city":"Alcazares",
    "sg:orig_category":"Institutos De Belleza",
    "sg:phone":"+34 968 17 13 33",
    "sg:postcode":"30710",
    "sg:province":"Murcia",
    "wof:name":"Zamora Ubeda Isabel",
    "wof:placetype":"venue"
},
  "geometry": {"coordinates":[-0.8496543765,37.7435836792],"type":"Point"}
}