{
  "type": "Feature",
  "properties": {
    "addr:full":"Carrer de Sant Josep, 48 Santa Coloma De Gramenet Barcelona 08922",
    "addr:housenumber":"48",
    "addr:postcode":"08922",
    "addr:street":"Carrer De Sant Josep",
    "iso:country":"ES",
    "sg:address":"Carrer de Sant Josep, 48",
    "sg:city":"Santa Coloma De Gramenet",
    "sg:orig_category":"Comit\u00c9s De Organizaci\u00d3n De Exposiciones, Ferias, Salones",
    "sg:phone":"+34 934 66 11 98",
    "sg:postcode":"08922",
    "sg:province":"Barcelona",
    "wof:name":"Perarnau Cornelles Sergi",
    "wof:placetype":"venue"
},
  "geometry": {"coordinates":[2.212747097,41.4499969482],"type":"Point"}
}