{
  "type": "Feature",
  "properties": {
    "addr:full":"Avda Mimbreras, 14 Majadahonda Madrid 28220",
    "addr:housenumber":"14",
    "addr:postcode":"28220",
    "addr:street":"Avda Mimbreras",
    "iso:country":"ES",
    "sg:address":"Avda Mimbreras, 14",
    "sg:city":"Majadahonda",
    "sg:orig_category":"Inmobiliaria (agencias)",
    "sg:phone":"+34 916 34 45 78",
    "sg:postcode":"28220",
    "sg:province":"Madrid",
    "wof:name":"Wabi Sabi S.l.",
    "wof:placetype":"venue"
},
  "geometry": {"coordinates":[-3.8596348763,40.4757614136],"type":"Point"}
}