{
  "type": "Feature",
  "properties": {
    "addr:full":"Calle de Jacinto Verdaguer, 35 Madrid Madrid 28019",
    "addr:housenumber":"35",
    "addr:postcode":"madrid;28019",
    "addr:street":"Calle De Jacinto Verdaguer",
    "iso:country":"ES",
    "sg:address":"Calle de Jacinto Verdaguer, 35",
    "sg:city":"Madrid",
    "sg:orig_category":"Venta, Alquiler De Plataformas Y Barquillas Elevadoras",
    "sg:phone":"+34 914 71 08 88",
    "sg:postcode":"28019",
    "sg:province":"Madrid",
    "wof:name":"Full Elev S.l.",
    "wof:placetype":"venue"
},
  "geometry": {"coordinates":[-3.7187390327,40.395362854],"type":"Point"}
}