{
  "type": "Feature",
  "properties": {
    "addr:full":"Calle de Atenea, 24 Curva Almer\u00eda 04770",
    "addr:housenumber":"24",
    "addr:postcode":"04770",
    "addr:street":"Calle De Atenea;Almeri\u0301A",
    "iso:country":"ES",
    "sg:address":"Calle de Atenea, 24",
    "sg:city":"Curva",
    "sg:orig_category":"Contenedores (mercanc\u00cdas)",
    "sg:phone":"+34 950 60 70 28",
    "sg:postcode":"04770",
    "sg:province":"Almer\u00eda",
    "wof:name":"Garcia Guerrero Antonio",
    "wof:placetype":"venue"
},
  "geometry": {"coordinates":[-2.9807116985,36.7602844238],"type":"Point"}
}