{
  "type": "Feature",
  "properties": {
    "addr:full":"Calle de Cordoba, 11 Malaga M\u00e1laga 29001",
    "addr:housenumber":"11",
    "addr:postcode":"29001",
    "addr:street":"Calle De Cordoba;Ma\u0301Laga",
    "iso:country":"ES",
    "sg:address":"Calle de Cordoba, 11",
    "sg:city":"Malaga",
    "sg:orig_category":"Ropa Para Se\u00d1oras (al Por Menor)",
    "sg:phone":"+34 952 22 59 57",
    "sg:postcode":"29001",
    "sg:province":"M\u00e1laga",
    "wof:name":"Saez Mochon Maria De Las Mercedes",
    "wof:placetype":"venue"
},
  "geometry": {"coordinates":[-4.4219059944,36.7163391113],"type":"Point"}
}