{
  "type": "Feature",
  "properties": {
    "iso:country":"ES",
    "sg:address":"Pase Isabel La Catolica, S/n",
    "sg:city":"Zaragoza",
    "sg:orig_category":"Edici\u00d3n De Diarios, Revistas, Boletines",
    "sg:phone":"+34 976 56 73 71",
    "sg:postcode":"50009",
    "sg:province":"Zaragoza",
    "wof:name":"Diario As S.l.",
    "wof:placetype":"venue"
},
  "geometry": {"coordinates":[-0.9003189802,41.6357536316],"type":"Point"}
}