{
  "type": "Feature",
  "properties": {
    "addr:full":"Unic, S/n Pont Alentorn Lleida 25739",
    "addr:housenumber":"s / n",
    "addr:postcode":"25739",
    "addr:street":"Unic;Pont Alentorn",
    "iso:country":"ES",
    "sg:address":"Unic, S/n",
    "sg:city":"Pont Alentorn",
    "sg:orig_category":"Abrasivos Y Superabrasivos (fabricaci\u00d3n, Al Por Mayor)",
    "sg:phone":"+34 973 40 22 01",
    "sg:postcode":"25739",
    "sg:province":"Lleida",
    "wof:name":"Abrasivos Jadeca S.l.",
    "wof:placetype":"venue"
},
  "geometry": {"coordinates":[1.070114,41.908897],"type":"Point"}
}