{
  "type": "Feature",
  "properties": {
    "iso:country":"ES",
    "sg:address":"Avda Alcalde J.elosegi, 114",
    "sg:city":"Donostia-san Sebastian",
    "sg:orig_category":"Servicio De Salud",
    "sg:phone":"+34 943 39 85 28",
    "sg:postcode":"20016",
    "sg:province":"Guip\u00f9zcoa",
    "sg:website":"antonioelosegui@teleline.es",
    "wof:name":"Saneamientos Antonio Elosegui S.l.",
    "wof:placetype":"venue"
},
  "geometry": {"coordinates":[-1.9426399469,43.3202476501],"type":"Point"}
}