{
  "type": "Feature",
  "properties": {
    "iso:country":"ES",
    "sg:address":"Calle de Florencio Quintero, 26",
    "sg:city":"Sevilla",
    "sg:orig_category":"Frutas, Legumbres Frescas Y Tempranas (al Por Menor)",
    "sg:phone":"+34 954 38 17 36",
    "sg:postcode":"41009",
    "sg:province":"Sevilla",
    "wof:name":"Valencia Gomez Jesus",
    "wof:placetype":"venue"
},
  "geometry": {"coordinates":[-5.9845237732,37.4028053284],"type":"Point"}
}