{
  "type": "Feature",
  "properties": {
    "addr:full":"Pol. Domenys Ll, S/n Vilafranca Penedes Barcelona 08720",
    "addr:housenumber":"s / n",
    "addr:postcode":"08720",
    "addr:street":"Pol. Domenys Ll;Penedes Barcelona",
    "iso:country":"ES",
    "sg:address":"Pol. Domenys Ll, S/n",
    "sg:city":"Vilafranca Penedes",
    "sg:orig_category":"Pintura, Barniz, Productos Asimilables (fabricaci\u00d3n, Al Por Mayor)",
    "sg:phone":"+34 938 19 10 00",
    "sg:postcode":"08720",
    "sg:province":"Barcelona",
    "wof:name":"Ici Packaging Coatings S.a.",
    "wof:placetype":"venue"
},
  "geometry": {"coordinates":[1.6992199421,41.3447799683],"type":"Point"}
}