{
  "type": "Feature",
  "properties": {
    "iso:country":"ES",
    "sg:address":"Avda Garcia Barbon, 30",
    "sg:city":"Vigo",
    "sg:orig_category":"Apicultura",
    "sg:phone":"+34 986 43 68 68",
    "sg:postcode":"36201",
    "sg:province":"Pontevedra",
    "wof:name":"Asociacion De Apicultores El Colmenar De Vigo",
    "wof:placetype":"venue"
},
  "geometry": {"coordinates":[-8.7165489197,42.2368125916],"type":"Point"}
}