{
  "type": "Feature",
  "properties": {
    "iso:country":"ES",
    "sg:address":"Cra. Nal. Cent Cinquanta Dos, Km. 0043,8",
    "sg:city":"Tagamanent",
    "sg:orig_category":"Limpieza Con Chorro De Arena Y Con Granalla, Pulido",
    "sg:phone":"+34 938 42 80 59",
    "sg:postcode":"08593",
    "sg:province":"Barcelona",
    "wof:name":"Guillt Ruiz Josefa",
    "wof:placetype":"venue"
},
  "geometry": {"coordinates":[2.2670049667,41.7381896973],"type":"Point"}
}