{
  "type": "Feature",
  "properties": {
    "addr:full":"Carrer de Moragas, 22 Barcelona Barcelona 08022",
    "addr:housenumber":"22",
    "addr:postcode":"08022",
    "addr:street":"Carrer De Moragas",
    "iso:country":"ES",
    "sg:address":"Carrer de Moragas, 22",
    "sg:city":"Barcelona",
    "sg:orig_category":"M\u00c9dicos: Radioterapia (radioterapia Como Opci\u00d3n Oncol\u00d3gica)",
    "sg:phone":"+34 932 12 86 88",
    "sg:postcode":"08022",
    "sg:province":"Barcelona",
    "wof:name":"Gomez Gomez Antonio",
    "wof:placetype":"venue"
},
  "geometry": {"coordinates":[2.1369249821,41.4080734253],"type":"Point"}
}