{
  "type": "Feature",
  "properties": {
    "iso:country":"ES",
    "sg:address":"Avda Cid Campeador, 16",
    "sg:city":"Burgos",
    "sg:orig_category":"Delegados, Agentes De Tr\u00c1nsito, Auxiliares De Transporte Internacional",
    "sg:phone":"+34 947 47 47 13",
    "sg:postcode":"09005",
    "sg:province":"Burgos",
    "wof:name":"Transportes Ferrolanos Montero S.l.",
    "wof:placetype":"venue"
},
  "geometry": {"coordinates":[-3.6980009079,42.3451805115],"type":"Point"}
}