{
  "type": "Feature",
  "properties": {
    "addr:full":"Calle de General Diaz Porlier, 14 Madrid Madrid 28001",
    "addr:housenumber":"14",
    "addr:postcode":"madrid;28001",
    "addr:street":"Calle De General Diaz Porlier",
    "iso:country":"ES",
    "sg:address":"Calle de General Diaz Porlier, 14",
    "sg:city":"Madrid",
    "sg:orig_category":"\u00d3ptica: Instrumentos (fabricaci\u00d3n)",
    "sg:phone":"+34 914 35 23 26",
    "sg:postcode":"28001",
    "sg:province":"Madrid",
    "wof:name":"Optica Casado S. L.",
    "wof:placetype":"venue"
},
  "geometry": {"coordinates":[-3.6769340038,40.426399231],"type":"Point"}
}