{
  "type": "Feature",
  "properties": {
    "iso:country":"ES",
    "sg:address":"Calle de Xuquer, 62",
    "sg:city":"Alzira",
    "sg:orig_category":"Arboricultura Y Producci\u00d3n De Frutas",
    "sg:phone":"+34 962 40 13 59",
    "sg:postcode":"46600",
    "sg:province":"Valencia",
    "wof:name":"Frutas Fuster S.l.",
    "wof:placetype":"venue"
},
  "geometry": {"coordinates":[-0.4371629953,39.1539306641],"type":"Point"}
}