{
  "type": "Feature",
  "properties": {
    "iso:country":"ES",
    "sg:address":"Calle de Isabel La Catolica, 22",
    "sg:city":"Cadiz",
    "sg:orig_category":"Bancos",
    "sg:phone":"+34 956 22 70 77",
    "sg:postcode":"11004",
    "sg:province":"C\u00e1diz",
    "wof:name":"Bancofar S.a.",
    "wof:placetype":"venue"
},
  "geometry": {"coordinates":[-6.2948489189,36.5359611511],"type":"Point"}
}