{
  "type": "Feature",
  "properties": {
    "addr:full":"Ctra Arroyomolinos (de), Km. 0008,5 Moraleja Enmedio Madrid 28950",
    "addr:postcode":"28950",
    "addr:street":"Ctra Arroyomolinos De Km. 0008,5",
    "iso:country":"ES",
    "sg:address":"Ctra Arroyomolinos (de), Km. 0008,5",
    "sg:city":"Moraleja Enmedio",
    "sg:orig_category":"Imprenta",
    "sg:phone":"+34 916 09 41 92",
    "sg:postcode":"28950",
    "sg:province":"Madrid",
    "wof:name":"De Castro Bermejo Roberto",
    "wof:placetype":"venue"
},
  "geometry": {"coordinates":[-3.8522839546,40.2605247498],"type":"Point"}
}