{
  "type": "Feature",
  "properties": {
    "addr:full":"Sect I, 1 Torre De La Higuera O Matalasca\u00e7as Huelva 21760",
    "addr:housenumber":"1",
    "addr:postcode":"21760",
    "addr:street":"Sect I",
    "iso:country":"ES",
    "sg:address":"Sect I, 1",
    "sg:city":"Torre De La Higuera O Matalasca\u00e7as",
    "sg:orig_category":"Empresas De Electricidad En General",
    "sg:phone":"+34 959 43 00 24",
    "sg:postcode":"21760",
    "sg:province":"Huelva",
    "wof:name":"Endesa Servicios S.l.u.",
    "wof:placetype":"venue"
},
  "geometry": {"coordinates":[-6.9495940208,37.256313324],"type":"Point"}
}