{
  "type": "Feature",
  "properties": {
    "addr:full":"Calle de Eras, 17 Ferez Albacete 02436",
    "addr:housenumber":"17",
    "addr:postcode":"02436",
    "addr:street":"Calle De Eras",
    "iso:country":"ES",
    "sg:address":"Calle de Eras, 17",
    "sg:city":"Ferez",
    "sg:orig_category":"Ambulancias",
    "sg:phone":"+34 967 42 03 25",
    "sg:postcode":"02436",
    "sg:province":"Albacete",
    "wof:name":"Espinosa Clavijos Maria De Los Angeles",
    "wof:placetype":"venue"
},
  "geometry": {"coordinates":[-2.0072779655,38.3570976257],"type":"Point"}
}