{
  "type": "Feature",
  "properties": {
    "iso:country":"ES",
    "sg:address":"Carrer de Agnes De Pacs, 6",
    "sg:city":"Palma",
    "sg:orig_category":"Electricidad: Instaladores",
    "sg:phone":"+34 971 20 38 22",
    "sg:postcode":"07010",
    "sg:province":"Islas Baleares",
    "wof:name":"Electrotecnia Monrabal S. L.",
    "wof:placetype":"venue"
},
  "geometry": {"coordinates":[2.6532158852,39.5946273804],"type":"Point"}
}