{
  "type": "Feature",
  "properties": {
    "iso:country":"ES",
    "sg:address":"Calle de Luis De Salazar, 1",
    "sg:city":"Madrid",
    "sg:orig_category":"Comercio De Piezas De Recambio Y De Accesorios De Veh\u00cdculos, Veh\u00cdculos Industriales",
    "sg:phone":"+34 914 13 34 05",
    "sg:postcode":"28002",
    "sg:province":"Madrid",
    "wof:name":"Hernandez Hernandez Francisco",
    "wof:placetype":"venue"
},
  "geometry": {"coordinates":[-3.6673519611,40.4476661682],"type":"Point"}
}