{
  "type": "Feature",
  "properties": {
    "addr:full":"Calle de Abastos (de), 6 Aranjuez Madrid 28300",
    "addr:postcode":"28300",
    "addr:street":"Calle De",
    "iso:country":"ES",
    "sg:address":"Calle de Abastos (de), 6",
    "sg:city":"Aranjuez",
    "sg:orig_category":"Transportes Por Carretera: Lotes Completos, Mercanc\u00cdas Diversas",
    "sg:phone":"+34 918 92 02 55",
    "sg:postcode":"28300",
    "sg:province":"Madrid",
    "wof:name":"Sociedad Anonima De Supermercados Y Autoservicios",
    "wof:placetype":"venue"
},
  "geometry": {"coordinates":[-3.6089639664,40.0320587158],"type":"Point"}
}