{
  "type": "Feature",
  "properties": {
    "addr:full":"Carr Joan Benejam Vives, 2 Ciutadella Menorca Islas Baleares 07760",
    "addr:housenumber":"2",
    "addr:postcode":"07760",
    "addr:street":"Carr Joan Benejam Vives",
    "iso:country":"ES",
    "sg:address":"Carr Joan Benejam Vives, 2",
    "sg:city":"Ciutadella Menorca",
    "sg:orig_category":"Arquitectos",
    "sg:phone":"+34 971 48 02 68",
    "sg:postcode":"07760",
    "sg:province":"Islas Baleares",
    "wof:name":"Ventura Saborido Joan Enric",
    "wof:placetype":"venue"
},
  "geometry": {"coordinates":[3.83613801,40.000087738],"type":"Point"}
}