{
  "type": "Feature",
  "properties": {
    "iso:country":"ES",
    "sg:address":"Carrer de Garbi, S/n",
    "sg:city":"Can Volart",
    "sg:orig_category":"Embalajes",
    "sg:phone":"+34 935 62 36 11",
    "sg:postcode":"08150",
    "sg:province":"Barcelona",
    "sg:website":"www.catimport.com",
    "wof:name":"Catalunya Import S.a.",
    "wof:placetype":"venue"
},
  "geometry": {"coordinates":[2.2293000221,41.5678787231],"type":"Point"}
}