{
  "type": "Feature",
  "properties": {
    "iso:country":"ES",
    "sg:address":"Calle de Felix Rodriguez De La Fuente, 2",
    "sg:city":"Alcala Guadaira",
    "sg:orig_category":"Compresores",
    "sg:phone":"+34 954 10 07 93",
    "sg:postcode":"41500",
    "sg:province":"Sevilla",
    "wof:name":"Tecnicas Neumaticas Hidraulicas Del Sur S.a.",
    "wof:placetype":"venue"
},
  "geometry": {"coordinates":[-5.8317728043,37.342540741],"type":"Point"}
}