{
  "type": "Feature",
  "properties": {
    "addr:full":"Calle de Sardinera (la), 22 Esperanza Santa Cruz De Tenerife 38290",
    "addr:housenumber":"22",
    "addr:postcode":"38290",
    "addr:street":"Calle De Sardinera La",
    "iso:country":"ES",
    "sg:address":"Calle de Sardinera (la), 22",
    "sg:city":"Esperanza",
    "sg:orig_category":"Inform\u00c1tica, Ofim\u00c1tica (estudios, Asesor\u00cda, Ingenier\u00cda, Formaci\u00d3n)",
    "sg:phone":"+34 922 54 80 43",
    "sg:postcode":"38290",
    "sg:province":"Santa Cruz De Tenerife",
    "wof:name":"Ramos Exposito Jose Manuel",
    "wof:placetype":"venue"
},
  "geometry": {"coordinates":[-16.3645210266,28.4525661469],"type":"Point"}
}