{
  "type": "Feature",
  "properties": {
    "addr:full":"Carrer de Vinyals, 36 Barcelona Barcelona 08041",
    "addr:housenumber":"36",
    "addr:postcode":"08041",
    "addr:street":"Carrer De Vinyals",
    "iso:country":"ES",
    "sg:address":"Carrer de Vinyals, 36",
    "sg:city":"Barcelona",
    "sg:orig_category":"Limpieza De Alfombras",
    "sg:phone":"+34 934 50 33 73",
    "sg:postcode":"08041",
    "sg:province":"Barcelona",
    "wof:name":"Plusnet S.c.p.",
    "wof:placetype":"venue"
},
  "geometry": {"coordinates":[2.1749520302,41.4203681946],"type":"Point"}
}