{
  "type": "Feature",
  "properties": {
    "addr:full":"Carr Valencia, 12 Silla Valencia 46460",
    "addr:housenumber":"12",
    "addr:postcode":"46460",
    "addr:street":"Carr Valencia",
    "iso:country":"ES",
    "sg:address":"Carr Valencia, 12",
    "sg:city":"Silla",
    "sg:orig_category":"Zapatos (al Por Menor)",
    "sg:phone":"+34 961 20 38 98",
    "sg:postcode":"46460",
    "sg:province":"Valencia",
    "wof:name":"Navarro Rodriguez Angel Rafael",
    "wof:placetype":"venue"
},
  "geometry": {"coordinates":[-0.4107789993,39.3662223816],"type":"Point"}
}