{
  "type": "Feature",
  "properties": {
    "iso:country":"ES",
    "sg:address":"Calle de San Bernardo, 4",
    "sg:city":"Palmas De Gran Canaria",
    "sg:orig_category":"Molduras, Junquillos, Listones Y Molduras Perforadas",
    "sg:phone":"+34 928 36 26 01",
    "sg:postcode":"35002",
    "sg:province":"Las Palmas",
    "wof:name":"Aleman Diaz Maria Josefa",
    "wof:placetype":"venue"
},
  "geometry": {"coordinates":[-15.4174900055,28.1056079865],"type":"Point"}
}