{
  "type": "Feature",
  "properties": {
    "addr:full":"Plaz Poligono Industrial La Torrecilla, S/n Cordoba C\u00f3rdoba 14013",
    "addr:housenumber":"s / n",
    "addr:postcode":"14013",
    "addr:street":"Plaz Poligono Industrial La Torrecilla;Co\u0301Rdoba",
    "iso:country":"ES",
    "sg:address":"Plaz Poligono Industrial La Torrecilla, S/n",
    "sg:city":"Cordoba",
    "sg:orig_category":"Asesor\u00cda Para La Organizaci\u00d3n Y Gesti\u00d3n Del Transporte",
    "sg:phone":"+34 957 42 98 15",
    "sg:postcode":"14013",
    "sg:province":"C\u00f3rdoba",
    "wof:name":"Nutracor S.a.",
    "wof:placetype":"venue"
},
  "geometry": {"coordinates":[-4.7784028053,37.8779411316],"type":"Point"}
}