{
  "type": "Feature",
  "properties": {
    "addr:full":"Calle de Corredera, 24 Almansa Albacete 02640",
    "addr:housenumber":"24",
    "addr:postcode":"02640",
    "addr:street":"Calle De Corredera",
    "iso:country":"ES",
    "sg:address":"Calle de Corredera, 24",
    "sg:city":"Almansa",
    "sg:orig_category":"Ingenier\u00cda, Centros De Estudios (diversos)",
    "sg:phone":"+34 967 31 00 78",
    "sg:postcode":"02640",
    "sg:province":"Albacete",
    "wof:name":"Estudio Tecnico Almansa S.l.",
    "wof:placetype":"venue"
},
  "geometry": {"coordinates":[-1.0965852737,38.867931366],"type":"Point"}
}