{
  "type": "Feature",
  "properties": {
    "addr:full":"Calle de Maestros Organeros, 6 Lerin Navarra 31260",
    "addr:housenumber":"6",
    "addr:postcode":"31260",
    "addr:street":"Calle De Maestros Organeros",
    "iso:country":"ES",
    "sg:address":"Calle de Maestros Organeros, 6",
    "sg:city":"Lerin",
    "sg:orig_category":"Cr\u00cda De Cerdos",
    "sg:phone":"+34 948 39 50 54",
    "sg:postcode":"31260",
    "sg:province":"Navarra",
    "wof:name":"Marchev Traykov Planen",
    "wof:placetype":"venue"
},
  "geometry": {"coordinates":[-1.9700479507,42.4850540161],"type":"Point"}
}