{
  "type": "Feature",
  "properties": {
    "iso:country":"ES",
    "sg:address":"Montmell (pol. Albornar), 3",
    "sg:city":"Sta. Oliva",
    "sg:orig_category":"Comercio De Piezas De Recambio Y De Accesorios De Veh\u00cdculos, Veh\u00cdculos Industriales",
    "sg:phone":"+34 977 16 90 25",
    "sg:postcode":"43710",
    "sg:province":"Tarragona",
    "wof:name":"Ytec Europa S.a.",
    "wof:placetype":"venue"
},
  "geometry": {"coordinates":[1.2454571724,41.11901474],"type":"Point"}
}