{
  "type": "Feature",
  "properties": {
    "addr:full":"S. Vicente Ferrer, 2 Lliria Valencia 46160",
    "addr:housenumber":"2",
    "addr:postcode":"46160",
    "addr:street":"S.;Ferrer",
    "iso:country":"ES",
    "sg:address":"S. Vicente Ferrer, 2",
    "sg:city":"Lliria",
    "sg:orig_category":"Inmobiliaria (agencias)",
    "sg:phone":"+34 962 79 25 64",
    "sg:postcode":"46160",
    "sg:province":"Valencia",
    "wof:name":"Lliria Invest S.l.",
    "wof:placetype":"venue"
},
  "geometry": {"coordinates":[-0.5955740213,39.6270294189],"type":"Point"}
}