{
  "type": "Feature",
  "properties": {
    "iso:country":"ES",
    "sg:address":"Pase Sagastieder De, 10",
    "sg:city":"Donostia-san Sebastian",
    "sg:orig_category":"Bazares, Art\u00cdculos De Limpieza Y De Cocina (al Por Menor)",
    "sg:phone":"+34 943 28 64 42",
    "sg:postcode":"20015",
    "sg:province":"Guip\u00f9zcoa",
    "wof:name":"Martinez Alvarez Pedro",
    "wof:placetype":"venue"
},
  "geometry": {"coordinates":[-1.9572099447,43.313117981],"type":"Point"}
}