{
  "type": "Feature",
  "properties": {
    "iso:country":"ES",
    "sg:address":"Carrer de Sant Antoni, 3",
    "sg:city":"Benidorm",
    "sg:orig_category":"Electricidad, Electr\u00d3nica: Suministros (al Por Menor)",
    "sg:phone":"+34 965 86 77 40",
    "sg:postcode":"03500",
    "sg:province":"Alicante",
    "wof:name":"Martinez Ca\u00f1adas Jose Antonio",
    "wof:placetype":"venue"
},
  "geometry": {"coordinates":[-0.1315899938,38.5395889282],"type":"Point"}
}