{
  "type": "Feature",
  "properties": {
    "addr:full":"Foranies, S/n La Rierada Barcelona 08750",
    "addr:housenumber":"/ n",
    "addr:postcode":"08750",
    "addr:street":"Foranies S",
    "iso:country":"ES",
    "sg:address":"Foranies, S/n",
    "sg:city":"La Rierada",
    "sg:orig_category":"Poller\u00cda Y Caza (al Por Menor)",
    "sg:phone":"+34 936 68 26 78",
    "sg:postcode":"08750",
    "sg:province":"Barcelona",
    "wof:name":"Can Castellvi Centres Naturals D'atraccio S.l.",
    "wof:placetype":"venue"
},
  "geometry": {"coordinates":[2.0164849758,41.414604187],"type":"Point"}
}