{
  "type": "Feature",
  "properties": {
    "addr:full":"Polig. Ind. A Granxa, 177 Porri\u00f1o Pontevedra 36475",
    "addr:housenumber":"177",
    "addr:postcode":"36475",
    "addr:street":"Polig. Ind. A Granxa",
    "iso:country":"ES",
    "sg:address":"Polig. Ind. A Granxa, 177",
    "sg:city":"Porri\u00f1o",
    "sg:orig_category":"Suministros Y Materiales Industriales",
    "sg:phone":"+34 986 34 22 30",
    "sg:postcode":"36475",
    "sg:province":"Pontevedra",
    "wof:name":"Suministros Porri\u00d1o S.l.",
    "wof:placetype":"venue"
},
  "geometry": {"coordinates":[-8.606926918,42.1053466797],"type":"Point"}
}