{
  "type": "Feature",
  "properties": {
    "iso:country":"ES",
    "sg:address":"Carrer de Santa Anna, 13",
    "sg:city":"Hospitalet Llobregat",
    "sg:orig_category":"Chapister\u00cda",
    "sg:phone":"+34 933 37 29 43",
    "sg:postcode":"08901",
    "sg:province":"Barcelona",
    "wof:name":"Calduch Camus Manuel",
    "wof:placetype":"venue"
},
  "geometry": {"coordinates":[2.1010730267,41.3588600159],"type":"Point"}
}