{
  "type": "Feature",
  "properties": {
    "addr:full":"Calle de Canterac, 35 Valladolid Valladolid 47012",
    "addr:housenumber":"35",
    "addr:postcode":"47012",
    "addr:street":"Calle De Canterac",
    "iso:country":"ES",
    "sg:address":"Calle de Canterac, 35",
    "sg:city":"Valladolid",
    "sg:orig_category":"Televisi\u00d3n, V\u00cddeo: Aparatos Y Accesorios (venta)",
    "sg:phone":"+34 983 29 74 70",
    "sg:postcode":"47012",
    "sg:province":"Valladolid",
    "wof:name":"Comercial Vallisoletana De Servicios De Comunicaciones S.l.",
    "wof:placetype":"venue"
},
  "geometry": {"coordinates":[-4.7182221413,41.6406860352],"type":"Point"}
}