{
  "type": "Feature",
  "properties": {
    "iso:country":"ES",
    "sg:address":"Calle de Nogal, 1",
    "sg:city":"Valladolid",
    "sg:orig_category":"Animales (al Por Menor)",
    "sg:phone":"+34 983 39 32 55",
    "sg:postcode":"47004",
    "sg:province":"Valladolid",
    "wof:name":"Veteanpe S.l.",
    "wof:placetype":"venue"
},
  "geometry": {"coordinates":[-4.7216358185,41.6454544067],"type":"Point"}
}