{
  "type": "Feature",
  "properties": {
    "iso:country":"ES",
    "sg:address":"Carrer de Pelai, 17",
    "sg:city":"Castelldefels",
    "sg:orig_category":"Electromec\u00c1nica",
    "sg:phone":"+34 936 64 25 52",
    "sg:postcode":"08860",
    "sg:province":"Barcelona",
    "wof:name":"Talleres Sanchez Castelldefels S.l.",
    "wof:placetype":"venue"
},
  "geometry": {"coordinates":[1.9769669771,41.28647995],"type":"Point"}
}