{
  "type": "Feature",
  "properties": {
    "iso:country":"ES",
    "sg:address":"Av Barcelona, 51",
    "sg:city":"Rubi",
    "sg:orig_category":"Pescader\u00cdas (al Por Menor)",
    "sg:phone":"+34 936 97 85 01",
    "sg:postcode":"08191",
    "sg:province":"Barcelona",
    "wof:name":"Rubio Espin Xavier",
    "wof:placetype":"venue"
},
  "geometry": {"coordinates":[2.0311911106,41.4880447388],"type":"Point"}
}