{
  "type": "Feature",
  "properties": {
    "iso:country":"ES",
    "sg:address":"Cmno Huertas, 2",
    "sg:city":"Morata Jalon",
    "sg:orig_category":"Comerciantes Al Por Mayor De Vinos, Licores Y Alcoholes",
    "sg:phone":"+34 976 60 50 07",
    "sg:postcode":"50260",
    "sg:province":"Zaragoza",
    "wof:name":"Torcal Borniquel Maria Luisa",
    "wof:placetype":"venue"
},
  "geometry": {"coordinates":[-1.4774739742,41.4757156372],"type":"Point"}
}