{
  "type": "Feature",
  "properties": {
    "iso:country":"ES",
    "sg:address":"Calle de Iglesia (la) (cacicedo), 3",
    "sg:city":"Cacicedo",
    "sg:orig_category":"Piedra Natural",
    "sg:phone":"+34 942 25 21 45",
    "sg:postcode":"39608",
    "sg:province":"Cantabria",
    "wof:name":"Arce Bezanilla Jose Antonio",
    "wof:placetype":"venue"
},
  "geometry": {"coordinates":[-3.873257637,43.4343070984],"type":"Point"}
}