{
  "type": "Feature",
  "properties": {
    "iso:country":"ES",
    "sg:address":"Reus, 6",
    "sg:city":"Miami Platja",
    "sg:orig_category":"Flores Y Plantas Naturales (al Por Mayor)",
    "sg:phone":"+34 977 17 07 53",
    "sg:postcode":"43892",
    "sg:province":"Tarragona",
    "wof:name":"Plantes Miami S.c.p",
    "wof:placetype":"venue"
},
  "geometry": {"coordinates":[0.9393600225,41.0107383728],"type":"Point"}
}