{
  "type": "Feature",
  "properties": {
    "iso:country":"ES",
    "sg:address":"Carrer de Antoni Gaudi, 3",
    "sg:city":"Deltebre",
    "sg:orig_category":"Art\u00cdculos De Pvc (fabricaci\u00d3n Y Al Por Mayor)",
    "sg:phone":"+34 977 48 92 93",
    "sg:postcode":"43580",
    "sg:province":"Tarragona",
    "wof:name":"Subirats Franch David",
    "wof:placetype":"venue"
},
  "geometry": {"coordinates":[0.7275599837,40.7214546204],"type":"Point"}
}