{
  "type": "Feature",
  "properties": {
    "iso:country":"ES",
    "sg:address":"Calle de Elexabarri, 3",
    "sg:city":"Bilbao",
    "sg:orig_category":"Sanatorios M\u00c9dico",
    "sg:phone":"+34 944 10 24 52",
    "sg:postcode":"48002",
    "sg:province":"Vizcaya",
    "wof:name":"Martinez Sacristan Maria Jesus",
    "wof:placetype":"venue"
},
  "geometry": {"coordinates":[-2.9451787472,43.2542572021],"type":"Point"}
}