{
  "type": "Feature",
  "properties": {
    "iso:country":"ES",
    "sg:address":"Avgd Garrigues, 21",
    "sg:city":"Lleida",
    "sg:orig_category":"Agencias Y Agentes Comerciales, Representantes",
    "sg:phone":"+34 973 20 48 81",
    "sg:postcode":"25001",
    "sg:province":"Lleida",
    "wof:name":"Escriba Bonastre Jose",
    "wof:placetype":"venue"
},
  "geometry": {"coordinates":[0.6324769855,41.6113090515],"type":"Point"}
}