{
  "type": "Feature",
  "properties": {
    "iso:country":"ES",
    "sg:address":"Cadiz, 15",
    "sg:city":"Cornella Llobregat",
    "sg:orig_category":"Electricidad, Electr\u00d3nica: Material Y Suministros (al Por Mayor)",
    "sg:phone":"+34 934 75 11 30",
    "sg:postcode":"08940",
    "sg:province":"Barcelona",
    "sg:website":"www.choose-buy.com",
    "wof:name":"Choose & Buy S.l.",
    "wof:placetype":"venue"
},
  "geometry": {"coordinates":[2.0708940029,41.3559417725],"type":"Point"}
}