{
  "type": "Feature",
  "properties": {
    "iso:country":"ES",
    "sg:address":"Oseiro, S/n",
    "sg:city":"Arteixo",
    "sg:orig_category":"Iglesia Cat\u00d3lica",
    "sg:phone":"+34 981 60 05 61",
    "sg:postcode":"15141",
    "sg:province":"La Coru\u00f1a",
    "wof:name":"Parroquia De San Tirso De Oseiro",
    "wof:placetype":"venue"
},
  "geometry": {"coordinates":[-8.4823741913,43.3233413696],"type":"Point"}
}