{
  "type": "Feature",
  "properties": {
    "addr:full":"Carr Sant Pau, 34 Figueres Girona 17600",
    "addr:housenumber":"34",
    "addr:postcode":"17600",
    "addr:street":"Carr Sant Pau",
    "iso:country":"ES",
    "sg:address":"Carr Sant Pau, 34",
    "sg:city":"Figueres",
    "sg:orig_category":"Inmobiliaria (agencias)",
    "sg:phone":"+34 972 51 36 72",
    "sg:postcode":"17600",
    "sg:province":"Girona",
    "sg:website":"www.finquesfigueres.com",
    "wof:name":"Finques Figueres S.l.",
    "wof:placetype":"venue"
},
  "geometry": {"coordinates":[2.9581100941,42.2656898499],"type":"Point"}
}