{
  "type": "Feature",
  "properties": {
    "iso:country":"ES",
    "sg:address":"Plaz San Juan Bautista De La Salle, 2",
    "sg:city":"Valladolid",
    "sg:orig_category":"Fotocopias, Reprograf\u00cda",
    "sg:phone":"+34 983 36 17 75",
    "sg:postcode":"47006",
    "sg:province":"Valladolid",
    "wof:name":"Ramajo Martin Eliseo",
    "wof:placetype":"venue"
},
  "geometry": {"coordinates":[-4.7342300415,41.6452484131],"type":"Point"}
}