{
  "type": "Feature",
  "properties": {
    "iso:country":"ES",
    "sg:address":"Calle de Vazquez Coronado, 5",
    "sg:city":"Salamanca",
    "sg:orig_category":"Ense\u00d1anza: Idiomas",
    "sg:phone":"+34 923 21 38 35",
    "sg:postcode":"37002",
    "sg:province":"Salamanca",
    "sg:website":"www.mester.com",
    "wof:name":"Batilo S.l.",
    "wof:placetype":"venue"
},
  "geometry": {"coordinates":[-5.663351059,40.9681968689],"type":"Point"}
}