{
  "type": "Feature",
  "properties": {
    "iso:country":"ES",
    "sg:address":"Calle de Julian Romea, 2",
    "sg:city":"Madrid",
    "sg:orig_category":"Ropa Para Se\u00d1oras (al Por Menor)",
    "sg:phone":"+34 915 34 38 13",
    "sg:postcode":"28003",
    "sg:province":"Madrid",
    "wof:name":"Thovar Veloso Pilar",
    "wof:placetype":"venue"
},
  "geometry": {"coordinates":[-3.7128665447,40.4426460266],"type":"Point"}
}