{
  "type": "Feature",
  "properties": {
    "iso:country":"ES",
    "sg:address":"Carr Conquista, 19",
    "sg:city":"Badalona",
    "sg:orig_category":"Quiropr\u00c1cticos",
    "sg:phone":"+34 933 83 89 07",
    "sg:postcode":"08912",
    "sg:province":"Barcelona",
    "wof:name":"Bejiga Serra Domingo",
    "wof:placetype":"venue"
},
  "geometry": {"coordinates":[2.2448899746,41.4442024231],"type":"Point"}
}