{
  "type": "Feature",
  "properties": {
    "iso:country":"ES",
    "sg:address":"Carrer de Galio, 10",
    "sg:city":"Magaluf",
    "sg:orig_category":"Molduras, Junquillos, Listones Y Molduras Perforadas",
    "sg:phone":"+34 971 13 13 47",
    "sg:postcode":"07181",
    "sg:province":"Islas Baleares",
    "wof:name":"Ca\u00f1ueto Castro Maria Purificacion",
    "wof:placetype":"venue"
},
  "geometry": {"coordinates":[2.532006979,39.5103492737],"type":"Point"}
}