{
  "type": "Feature",
  "properties": {
    "addr:full":"Carr Sequia Assut, 5 Gandia Valencia 46700",
    "addr:housenumber":"5",
    "addr:postcode":"46700",
    "addr:street":"Carr Sequia Assut;Valencia",
    "iso:country":"ES",
    "sg:address":"Carr Sequia Assut, 5",
    "sg:city":"Gandia",
    "sg:orig_category":"Agencias Y Asesores De Publicidad",
    "sg:phone":"+34 962 87 06 16",
    "sg:postcode":"46700",
    "sg:province":"Valencia",
    "wof:name":"Gestion De Medios Publicitarios M&m S.l.",
    "wof:placetype":"venue"
},
  "geometry": {"coordinates":[-0.1913339943,38.960735321],"type":"Point"}
}