{
  "type": "Feature",
  "properties": {
    "iso:country":"ES",
    "sg:address":"C/ Capita Antoni Mena, 17",
    "sg:city":"Elche",
    "sg:orig_category":"Caf\u00c9s, Bares, Cervecer\u00cdas",
    "sg:phone":"+34 966 67 25 30",
    "sg:postcode":"03201",
    "sg:province":"Alicante",
    "wof:name":"Mateo Miralles Ana Maria",
    "wof:placetype":"venue"
},
  "geometry": {"coordinates":[-0.7076969743,38.2665367126],"type":"Point"}
}