{
  "type": "Feature",
  "properties": {
    "addr:full":"Avda Ejercito (del), 14 Puerto De Santa Maria C\u00e1diz 11500",
    "addr:postcode":"11500",
    "addr:street":"Avda Ejercito Del 14 Puerto De Santa;Ca\u0301Diz",
    "iso:country":"ES",
    "sg:address":"Avda Ejercito (del), 14",
    "sg:city":"Puerto De Santa Maria",
    "sg:orig_category":"M\u00c9dicos: Estomatolog\u00cda",
    "sg:phone":"+34 956 87 33 55",
    "sg:postcode":"11500",
    "sg:province":"C\u00e1diz",
    "wof:name":"Azagra Rexach Maria Teresa",
    "wof:placetype":"venue"
},
  "geometry": {"coordinates":[-6.2356600761,36.5937995911],"type":"Point"}
}