{
  "type": "Feature",
  "properties": {
    "addr:full":"Carrer de Mar, 34 Malgrat Mar Barcelona 08380",
    "addr:housenumber":"34",
    "addr:postcode":"08380",
    "addr:street":"Carrer De Mar",
    "iso:country":"ES",
    "sg:address":"Carrer de Mar, 34",
    "sg:city":"Malgrat Mar",
    "sg:orig_category":"Ropa Para Se\u00d1oras (al Por Menor)",
    "sg:phone":"+34 937 65 42 74",
    "sg:postcode":"08380",
    "sg:province":"Barcelona",
    "wof:name":"Pret-chic S.l.",
    "wof:placetype":"venue"
},
  "geometry": {"coordinates":[2.7429258823,41.6447906494],"type":"Point"}
}