{
  "type": "Feature",
  "properties": {
    "iso:country":"ES",
    "sg:address":"Calle de Real, 14",
    "sg:city":"Villalbilla De Burgos",
    "sg:orig_category":"Farmacias",
    "sg:phone":"+34 947 29 12 30",
    "sg:postcode":"09197",
    "sg:province":"Burgos",
    "wof:name":"Garcia Gomez Jose Luis",
    "wof:placetype":"venue"
},
  "geometry": {"coordinates":[-3.7801239491,42.3464660645],"type":"Point"}
}