{
  "type": "Feature",
  "properties": {
    "iso:country":"ES",
    "sg:address":"Carrer de Milton, 1",
    "sg:city":"Barcelona",
    "sg:orig_category":"Peluquer\u00cdas, Peluquer\u00cda Mixta",
    "sg:phone":"+34 932 17 42 83",
    "sg:postcode":"08012",
    "sg:province":"Barcelona",
    "wof:name":"Llado Perruquers S.l.",
    "wof:placetype":"venue"
},
  "geometry": {"coordinates":[2.153439045,41.3992805481],"type":"Point"}
}