{
  "type": "Feature",
  "properties": {
    "iso:country":"ES",
    "sg:address":"Avda Miguel Hernandez, 8",
    "sg:city":"Alaquas",
    "sg:orig_category":"Art\u00cdculos De Decoraci\u00d3n",
    "sg:phone":"+34 961 50 37 03",
    "sg:postcode":"46970",
    "sg:province":"Valencia",
    "wof:name":"Artero Mercado Juan",
    "wof:placetype":"venue"
},
  "geometry": {"coordinates":[-0.4545353055,39.4580917358],"type":"Point"}
}