{
  "type": "Feature",
  "properties": {
    "addr:full":"Calle de Mina (la), 2 Dos Hermanas Sevilla 41700",
    "addr:housenumber":"2",
    "addr:postcode":"41700",
    "addr:street":"Calle De Mina La;Sevilla",
    "iso:country":"ES",
    "sg:address":"Calle de Mina (la), 2",
    "sg:city":"Dos Hermanas",
    "sg:orig_category":"Promotores Constructores",
    "sg:phone":"+34 955 67 91 19",
    "sg:postcode":"41700",
    "sg:province":"Sevilla",
    "wof:name":"Alicatados Lacruz S.l.",
    "wof:placetype":"venue"
},
  "geometry": {"coordinates":[-5.9218220711,37.2829284668],"type":"Point"}
}