{
  "type": "Feature",
  "properties": {
    "addr:full":"Pase Pilar Coloma, 48 Las Villas Castell\u00f3n 12560",
    "addr:housenumber":"48",
    "addr:postcode":"12560",
    "addr:street":"Coloma;Castello\u0301N",
    "iso:country":"ES",
    "sg:address":"Pase Pilar Coloma, 48",
    "sg:city":"Las Villas",
    "sg:orig_category":"Arquitectos",
    "sg:phone":"+34 964 30 02 39",
    "sg:postcode":"12560",
    "sg:province":"Castell\u00f3n",
    "wof:name":"Beltran Sanz Angel Cesar",
    "wof:placetype":"venue"
},
  "geometry": {"coordinates":[0.0590550005,40.0523414612],"type":"Point"}
}