{
  "type": "Feature",
  "properties": {
    "iso:country":"ES",
    "sg:address":"Calle de Morera, 25",
    "sg:city":"Portillo Toledo",
    "sg:orig_category":"Electrodom\u00c9sticos (al Por Menor)",
    "sg:phone":"+34 925 78 50 31",
    "sg:postcode":"45512",
    "sg:province":"Toledo",
    "wof:name":"Electrodomesticos Gil S.l.",
    "wof:placetype":"venue"
},
  "geometry": {"coordinates":[-4.2280888557,40.059173584],"type":"Point"}
}