{
  "type": "Feature",
  "properties": {
    "addr:full":"Ctra. Valladolid-soria, Km. 0312,4 Padilla De Duero Valladolid 47314",
    "addr:postcode":"47314",
    "addr:street":"Ctra. Valladolid-Soria Km. 0312,4",
    "iso:country":"ES",
    "sg:address":"Ctra. Valladolid-soria, Km. 0312,4",
    "sg:city":"Padilla De Duero",
    "sg:orig_category":"Productores Recolectores, Venta Directa De Vinos",
    "sg:phone":"+34 983 88 12 36",
    "sg:postcode":"47314",
    "sg:province":"Valladolid",
    "sg:website":"www.bodegasalion.com",
    "wof:name":"Bodegas Y Vi\u00f1edos Alion S.a.",
    "wof:placetype":"venue"
},
  "geometry": {"coordinates":[-4.1950340271,41.573348999],"type":"Point"}
}