{
  "type": "Feature",
  "properties": {
    "addr:full":"Avenida Villaricos, S/n Palomares Almer\u00eda 04618",
    "addr:housenumber":"s / n",
    "addr:postcode":"04618",
    "addr:street":"Avenida Villaricos;Almeri\u0301A",
    "iso:country":"ES",
    "sg:address":"Avenida Villaricos, S/n",
    "sg:city":"Palomares",
    "sg:orig_category":"Promotores Constructores",
    "sg:phone":"+34 950 46 74 11",
    "sg:postcode":"04618",
    "sg:province":"Almer\u00eda",
    "wof:name":"Villaricos S.l.",
    "wof:placetype":"venue"
},
  "geometry": {"coordinates":[-1.8115489483,37.2733306885],"type":"Point"}
}