{
  "type": "Feature",
  "properties": {
    "iso:country":"ES",
    "sg:address":"Avda Delicias (de Las), S/n",
    "sg:city":"Caceres",
    "sg:orig_category":"Cementerios",
    "sg:phone":"+34 927 24 55 89",
    "sg:postcode":"10004",
    "sg:province":"C\u00e1ceres",
    "wof:name":"Ayuntamiento De Caceres",
    "wof:placetype":"venue"
},
  "geometry": {"coordinates":[-6.3722691536,39.4804649353],"type":"Point"}
}