{
  "type": "Feature",
  "properties": {
    "addr:full":"Singerlin, 2 Huelma Ja\u00e9n 23560",
    "addr:housenumber":"2",
    "addr:postcode":"23560",
    "addr:street":"Singerlin",
    "iso:country":"ES",
    "sg:address":"Singerlin, 2",
    "sg:city":"Huelma",
    "sg:orig_category":"Lavado, Limpieza De Veh\u00cdculos",
    "sg:phone":"+34 953 39 04 32",
    "sg:postcode":"23560",
    "sg:province":"Ja\u00e9n",
    "wof:name":"Martinez Linde Julio",
    "wof:placetype":"venue"
},
  "geometry": {"coordinates":[-3.4526491165,37.6476287842],"type":"Point"}
}