{
  "type": "Feature",
  "properties": {
    "iso:country":"ES",
    "sg:address":"Calle de Maria De Molina, 10",
    "sg:city":"Madrid",
    "sg:orig_category":"Muebles Y Accesorios Para Cocinas Y Cuartos De Ba\u00d1o (al Por Menor)",
    "sg:phone":"+34 915 61 33 03",
    "sg:postcode":"28006",
    "sg:province":"Madrid",
    "sg:website":"www.verdicocinas.com",
    "wof:name":"Estudio De Cocina Verdi S.l.",
    "wof:placetype":"venue"
},
  "geometry": {"coordinates":[-3.6883831024,40.4377098083],"type":"Point"}
}