{
  "type": "Feature",
  "properties": {
    "addr:full":"Calle de Cabellera De Berenice, 63 Madrid Madrid 28023",
    "addr:housenumber":"63",
    "addr:postcode":"madrid;28023",
    "addr:street":"Calle De Cabellera De Berenice",
    "iso:country":"ES",
    "sg:address":"Calle de Cabellera De Berenice, 63",
    "sg:city":"Madrid",
    "sg:orig_category":"Promotores Constructores",
    "sg:phone":"+34 913 57 51 02",
    "sg:postcode":"28023",
    "sg:province":"Madrid",
    "wof:name":"Ortiz Construcciones Y Proyectos S.a.",
    "wof:placetype":"venue"
},
  "geometry": {"coordinates":[-3.7869505882,40.4711608887],"type":"Point"}
}