{
  "type": "Feature",
  "properties": {
    "addr:full":"Av Paral.lel, 124 Barcelona Barcelona 08015",
    "addr:housenumber":"124",
    "addr:postcode":"08015",
    "addr:street":"Av Paral.Lel",
    "iso:country":"ES",
    "sg:address":"Av Paral.lel, 124",
    "sg:city":"Barcelona",
    "sg:orig_category":"Agentes, Concesionarios Y Sucursales De Veh\u00cdculos",
    "sg:phone":"+34 933 29 70 90",
    "sg:postcode":"08015",
    "sg:province":"Barcelona",
    "wof:name":"Hispanomocion S.a.",
    "wof:placetype":"venue"
},
  "geometry": {"coordinates":[2.1623198986,41.3750915527],"type":"Point"}
}