{
  "type": "Feature",
  "properties": {
    "iso:country":"ES",
    "sg:address":"Calle de Ca\u00d1uelo (del), 12",
    "sg:city":"Navarredonda Gredos",
    "sg:orig_category":"Asesor\u00cda Fiscal Y Jur\u00cddica",
    "sg:phone":"+34 920 34 80 61",
    "sg:postcode":"05635",
    "sg:province":"\u00c1vila",
    "wof:name":"Asesoria Quero Martin S.l.",
    "wof:placetype":"venue"
},
  "geometry": {"coordinates":[-5.1352095604,40.3618392944],"type":"Point"}
}