{
  "type": "Feature",
  "properties": {
    "addr:full":"Ravanell(valterna), 6 Paterna Valencia 46980",
    "addr:housenumber":"6",
    "addr:postcode":"46980",
    "addr:street":"Valterna",
    "iso:country":"ES",
    "sg:address":"Ravanell(valterna), 6",
    "sg:city":"Paterna",
    "sg:orig_category":"Caf\u00c9s, Bares, Cervecer\u00cdas",
    "sg:phone":"+34 961 35 69 50",
    "sg:postcode":"46980",
    "sg:province":"Valencia",
    "wof:name":"Cafeteria Mentxu S.l.s.u",
    "wof:placetype":"venue"
},
  "geometry": {"coordinates":[-0.4395389855,39.500629425],"type":"Point"}
}