{
  "type": "Feature",
  "properties": {
    "addr:full":"Avda. Erasa, 3 Benalmadena-costa M\u00e1laga 29630",
    "addr:housenumber":"3",
    "addr:postcode":"29630",
    "addr:street":"Avda. Erasa;Ma\u0301Laga",
    "iso:country":"ES",
    "sg:address":"Avda. Erasa, 3",
    "sg:city":"Benalmadena-costa",
    "sg:orig_category":"Zapatos (al Por Menor)",
    "sg:phone":"+34 952 56 79 85",
    "sg:postcode":"29630",
    "sg:province":"M\u00e1laga",
    "wof:name":"Mu\u00f1oz Rodriguez Manuela Capilla",
    "wof:placetype":"venue"
},
  "geometry": {"coordinates":[-4.521381855,36.5971374512],"type":"Point"}
}