{
  "type": "Feature",
  "properties": {
    "iso:country":"ES",
    "sg:address":"Calle de Muller, 41",
    "sg:city":"Madrid",
    "sg:orig_category":"Abogados",
    "sg:phone":"+34 915 79 72 24",
    "sg:postcode":"28039",
    "sg:province":"Madrid",
    "sg:website":"www.paginasamarillas.es",
    "wof:name":"Egido Lozano Maria Pilar",
    "wof:placetype":"venue"
},
  "geometry": {"coordinates":[-3.6986880302,40.4650192261],"type":"Point"}
}