{
  "type": "Feature",
  "properties": {
    "addr:full":"Avda Mediterraneo (del), 224 Almeria Almer\u00eda 04006",
    "addr:housenumber":"224",
    "addr:postcode":"04006",
    "addr:street":"Avda Mediterraneo Del",
    "iso:country":"ES",
    "sg:address":"Avda Mediterraneo (del), 224",
    "sg:city":"Almeria",
    "sg:orig_category":"Inform\u00c1tica (estudios, Servicios, Asesor\u00cda, Formaci\u00d3n)",
    "sg:phone":"+34 950 22 30 00",
    "sg:postcode":"04006",
    "sg:province":"Almer\u00eda",
    "wof:name":"Victor Computer S.l.",
    "wof:placetype":"venue"
},
  "geometry": {"coordinates":[-2.4471058846,36.8450813293],"type":"Point"}
}