{
  "type": "Feature",
  "properties": {
    "iso:country":"ES",
    "sg:address":"Pase Malecon (del), 116",
    "sg:city":"Garrucha",
    "sg:orig_category":"Art\u00cdculos De Regalo (al Por Menor)",
    "sg:phone":"+34 950 13 30 20",
    "sg:postcode":"04630",
    "sg:province":"Almer\u00eda",
    "wof:name":"Flores Flores Francisco",
    "wof:placetype":"venue"
},
  "geometry": {"coordinates":[-1.8196489811,37.1859741211],"type":"Point"}
}