{
  "type": "Feature",
  "properties": {
    "iso:country":"ES",
    "sg:address":"Luga Horno (el), S/n",
    "sg:city":"Horno",
    "sg:orig_category":"Ense\u00d1anza, Formaci\u00d3n Profesional: Aprendizaje",
    "sg:phone":"+34 928 15 91 08",
    "sg:postcode":"35140",
    "sg:province":"Las Palmas",
    "wof:name":"Ayuntamiento De Mogan",
    "wof:placetype":"venue"
},
  "geometry": {"coordinates":[-15.7237386703,27.8846378326],"type":"Point"}
}