{
  "type": "Feature",
  "properties": {
    "iso:country":"ES",
    "sg:address":"Avda Andalucia, 58",
    "sg:city":"Guillena",
    "sg:orig_category":"Asociaciones Y Clubs Deportivos",
    "sg:phone":"+34 955 78 57 24",
    "sg:postcode":"41210",
    "sg:province":"Sevilla",
    "wof:name":"Alava Bermudez Julian",
    "wof:placetype":"venue"
},
  "geometry": {"coordinates":[-6.0563077927,37.5418624878],"type":"Point"}
}