{
  "type": "Feature",
  "properties": {
    "iso:country":"ES",
    "sg:address":"Plaz Nazaret, S/n",
    "sg:city":"Malaga",
    "sg:orig_category":"Ense\u00d1anza Variada",
    "sg:phone":"+34 952 65 06 98",
    "sg:postcode":"29014",
    "sg:province":"M\u00e1laga",
    "wof:name":"Garrido Martin Maria Isabel",
    "wof:placetype":"venue"
},
  "geometry": {"coordinates":[-4.4209837914,36.7384910583],"type":"Point"}
}