{
  "type": "Feature",
  "properties": {
    "iso:country":"ES",
    "sg:address":"Calle de Marquesa Viuda De Aldama (de La), 4",
    "sg:city":"Alcobendas",
    "sg:orig_category":"Madera Para Construcci\u00d3n E Industria",
    "sg:phone":"+34 916 23 94 47",
    "sg:postcode":"28100",
    "sg:province":"Madrid",
    "wof:name":"Gfb De Cantabria S.a.",
    "wof:placetype":"venue"
},
  "geometry": {"coordinates":[-3.6333510876,40.540977478],"type":"Point"}
}