{
  "type": "Feature",
  "properties": {
    "addr:full":"Calle de Mayor, 9 Puntal Murcia 30100",
    "addr:housenumber":"9",
    "addr:postcode":"30100",
    "addr:street":"Calle De Mayor",
    "iso:country":"ES",
    "sg:address":"Calle de Mayor, 9",
    "sg:city":"Puntal",
    "sg:orig_category":"Abogados",
    "sg:phone":"+34 968 83 17 09",
    "sg:postcode":"30100",
    "sg:province":"Murcia",
    "wof:name":"Martinez Martinez Fermin",
    "wof:placetype":"venue"
},
  "geometry": {"coordinates":[-1.1536929607,38.0136032104],"type":"Point"}
}