{
  "type": "Feature",
  "properties": {
    "addr:full":"Avda Lapurdi, 5 Bilbao Vizcaya 48012",
    "addr:housenumber":"5",
    "addr:postcode":"48012",
    "addr:street":"Avda Lapurdi",
    "iso:country":"ES",
    "sg:address":"Avda Lapurdi, 5",
    "sg:city":"Bilbao",
    "sg:orig_category":"Mec\u00c1nico Del Autom\u00d3vil",
    "sg:phone":"+34 944 43 52 31",
    "sg:postcode":"48012",
    "sg:province":"Vizcaya",
    "wof:name":"Miguel Ruiz Martinez Jose Jacinto Gamo Reguero S. Cv.",
    "wof:placetype":"venue"
},
  "geometry": {"coordinates":[-2.9350728989,43.25573349],"type":"Point"}
}