{
  "type": "Feature",
  "properties": {
    "addr:full":"Calle de Duque De Fernan Nu\u00d1ez, 2 Madrid Madrid 28012",
    "addr:housenumber":"2",
    "addr:postcode":"28012",
    "addr:street":"Calle De Duque De Fernan Nun\u0303Ez",
    "iso:country":"ES",
    "sg:address":"Calle de Duque De Fernan Nu\u00d1ez, 2",
    "sg:city":"Madrid",
    "sg:orig_category":"Ropa Para Se\u00d1oras Y Caballeros (al Por Menor)",
    "sg:phone":"+34 913 69 10 07",
    "sg:postcode":"28012",
    "sg:province":"Madrid",
    "wof:name":"Olalla Fuentenebro Maria Soledad",
    "wof:placetype":"venue"
},
  "geometry": {"coordinates":[-3.6983108521,40.4117126465],"type":"Point"}
}