{
  "type": "Feature",
  "properties": {
    "addr:full":"Calle de Monjas, 6 Solana Ciudad Real 13240",
    "addr:housenumber":"6",
    "addr:postcode":"solana;13240",
    "addr:street":"Calle De Monjas;Real",
    "iso:country":"ES",
    "sg:address":"Calle de Monjas, 6",
    "sg:city":"Solana",
    "sg:orig_category":"Farmacias",
    "sg:phone":"+34 926 63 15 52",
    "sg:postcode":"13240",
    "sg:province":"Ciudad Real",
    "wof:name":"Antequera Recio Juan",
    "wof:placetype":"venue"
},
  "geometry": {"coordinates":[-3.240424633,38.9420547485],"type":"Point"}
}