{
  "type": "Feature",
  "properties": {
    "iso:country":"ES",
    "sg:address":"Pase Salamanca, 13",
    "sg:city":"Le\u00f3n",
    "sg:orig_category":"Agricultura: Abastecimiento Y Cosechado (negocio)",
    "sg:phone":"+34 987 22 46 00",
    "sg:postcode":"24009",
    "sg:province":"Le\u00f3n",
    "wof:name":"Gonzalez Martin Francisco Javier",
    "wof:placetype":"venue"
},
  "geometry": {"coordinates":[-5.5810880661,42.5971412659],"type":"Point"}
}