{
  "type": "Feature",
  "properties": {
    "addr:full":"Calle de Ateneo Obrero De La Calzada, 2 Gijon Asturias 33213",
    "addr:housenumber":"2",
    "addr:postcode":"33213",
    "addr:street":"Calle De Ateneo;De La Calzada",
    "iso:country":"ES",
    "sg:address":"Calle de Ateneo Obrero De La Calzada, 2",
    "sg:city":"Gijon",
    "sg:orig_category":"Carnicer\u00cdas, Carnicer\u00cdas",
    "sg:phone":"+34 985 31 07 00",
    "sg:postcode":"33213",
    "sg:province":"Asturias",
    "wof:name":"Menendez Lopez Jose Mario",
    "wof:placetype":"venue"
},
  "geometry": {"coordinates":[-5.6947231293,43.5392227173],"type":"Point"}
}