{
  "type": "Feature",
  "properties": {
    "addr:full":"Avda Derechos Humanos (los), S/n Laredo Cantabria 39770",
    "addr:postcode":"39770",
    "addr:street":"Avda Derechos Humanos Los S / N",
    "iso:country":"ES",
    "sg:address":"Avda Derechos Humanos (los), S/n",
    "sg:city":"Laredo",
    "sg:orig_category":"Asociaciones Humanitarias, De Cooperaci\u00d3n, De Acci\u00d3n Social",
    "sg:phone":"+34 942 61 32 03",
    "sg:postcode":"39770",
    "sg:province":"Cantabria",
    "wof:name":"Ampros-c.d.l.",
    "wof:placetype":"venue"
},
  "geometry": {"coordinates":[-3.441139698,43.4141349792],"type":"Point"}
}