{
  "type": "Feature",
  "properties": {
    "addr:full":"Carr Rutlla, 5 Figueres Girona 17600",
    "addr:housenumber":"5",
    "addr:postcode":"17600",
    "addr:street":"Carr Rutlla",
    "iso:country":"ES",
    "sg:address":"Carr Rutlla, 5",
    "sg:city":"Figueres",
    "sg:orig_category":"Librer\u00cdas",
    "sg:phone":"+34 972 67 34 35",
    "sg:postcode":"17600",
    "sg:province":"Girona",
    "wof:name":"Heras Isac Carmen",
    "wof:placetype":"venue"
},
  "geometry": {"coordinates":[2.9633119106,42.2662467957],"type":"Point"}
}