{
  "type": "Feature",
  "properties": {
    "iso:country":"ES",
    "sg:address":"Carrer de Cardenal Rossell, S/n",
    "sg:city":"Coll De'n Rabassa",
    "sg:orig_category":"Florister\u00cdas",
    "sg:phone":"+34 971 49 00 88",
    "sg:postcode":"07007",
    "sg:province":"Islas Baleares",
    "wof:name":"Oliver Capella Lorenzo",
    "wof:placetype":"venue"
},
  "geometry": {"coordinates":[2.9117100239,39.6136398315],"type":"Point"}
}