{
  "type": "Feature",
  "properties": {
    "iso:country":"ES",
    "sg:address":"Calle de Aduana, 11",
    "sg:city":"Puertollano",
    "sg:orig_category":"Bisuter\u00cda, Joyer\u00cda, Relojer\u00cda (al Por Menor)",
    "sg:phone":"+34 926 42 49 13",
    "sg:postcode":"13500",
    "sg:province":"Ciudad Real",
    "wof:name":"Garcia Rodero Juan Carlos",
    "wof:placetype":"venue"
},
  "geometry": {"coordinates":[-4.1094002724,38.6868743896],"type":"Point"}
}