{
  "type": "Feature",
  "properties": {
    "iso:country":"ES",
    "sg:address":"Carrer de Gaia, 4",
    "sg:city":"Barcelona",
    "sg:orig_category":"Molduras, Junquillos, Listones Y Molduras Perforadas",
    "sg:phone":"+34 933 32 10 02",
    "sg:postcode":"08038",
    "sg:province":"Barcelona",
    "wof:name":"Gomez Perez Manuel",
    "wof:placetype":"venue"
},
  "geometry": {"coordinates":[2.1410589218,41.3620376587],"type":"Point"}
}