{
  "type": "Feature",
  "properties": {
    "addr:full":"Comtes De Trigona, 31 Massanassa Valencia 46470",
    "addr:housenumber":"31",
    "addr:postcode":"46470",
    "iso:country":"ES",
    "sg:address":"Comtes De Trigona, 31",
    "sg:city":"Massanassa",
    "sg:orig_category":"Ense\u00d1anza, Formaci\u00d3n Profesional: Aprendizaje",
    "sg:phone":"+34 961 25 03 63",
    "sg:postcode":"46470",
    "sg:province":"Valencia",
    "wof:name":"Ajuntament De Massanassa",
    "wof:placetype":"venue"
},
  "geometry": {"coordinates":[-0.397854507,39.4113998413],"type":"Point"}
}