{
  "type": "Feature",
  "properties": {
    "iso:country":"ES",
    "sg:address":"Plaz Tendillas (las), 1",
    "sg:city":"Sevilla",
    "sg:orig_category":"Quincaller\u00cda (al Por Menor)",
    "sg:phone":"+34 954 67 36 79",
    "sg:postcode":"41019",
    "sg:province":"Sevilla",
    "wof:name":"Bellido Amaro Francisco",
    "wof:placetype":"venue"
},
  "geometry": {"coordinates":[-5.9230351448,37.407169342],"type":"Point"}
}