{
  "type": "Feature",
  "properties": {
    "addr:full":"Calle de Manuel Birlanga, 7 Almoradi Alicante 03160",
    "addr:housenumber":"7",
    "addr:postcode":"03160",
    "addr:street":"Calle De Manuel Birlanga",
    "iso:country":"ES",
    "sg:address":"Calle de Manuel Birlanga, 7",
    "sg:city":"Almoradi",
    "sg:orig_category":"Alquiler De V\u00cddeo",
    "sg:phone":"+34 965 70 18 08",
    "sg:postcode":"03160",
    "sg:province":"Alicante",
    "wof:name":"Cinebank Almoradi C.b.",
    "wof:placetype":"venue"
},
  "geometry": {"coordinates":[-0.7934479713,38.1089172363],"type":"Point"}
}