{
  "type": "Feature",
  "properties": {
    "iso:country":"ES",
    "sg:address":"Calle de Purisima, 38",
    "sg:city":"Bigastro",
    "sg:orig_category":"Ropa Para Beb\u00c9s Y Ni\u00d1os (confecci\u00d3n, Al Por Mayor)",
    "sg:phone":"+34 965 35 09 65",
    "sg:postcode":"03380",
    "sg:province":"Alicante",
    "wof:name":"Villagordo Caba\u00f1es Alicia",
    "wof:placetype":"venue"
},
  "geometry": {"coordinates":[-0.8976479769,38.0628204346],"type":"Point"}
}