{
  "type": "Feature",
  "properties": {
    "addr:full":"Carrer de Cervantes, 24 Sabadell Barcelona 08201",
    "addr:housenumber":"24",
    "addr:postcode":"08201",
    "addr:street":"Carrer De Cervantes",
    "iso:country":"ES",
    "sg:address":"Carrer de Cervantes, 24",
    "sg:city":"Sabadell",
    "sg:orig_category":"Promotores Constructores",
    "sg:phone":"+34 937 27 73 46",
    "sg:postcode":"08201",
    "sg:province":"Barcelona",
    "wof:name":"Icm Lift Iberica S.l.",
    "wof:placetype":"venue"
},
  "geometry": {"coordinates":[2.1102619171,41.5416526794],"type":"Point"}
}