{
  "type": "Feature",
  "properties": {
    "addr:full":"Plaz Portugal, S/n Badajoz Badajoz 06001",
    "addr:housenumber":"s / n",
    "addr:postcode":"06001",
    "addr:street":"Portugal",
    "iso:country":"ES",
    "sg:address":"Plaz Portugal, S/n",
    "sg:city":"Badajoz",
    "sg:orig_category":"Filatelia",
    "sg:phone":"+34 924 22 37 37",
    "sg:postcode":"06001",
    "sg:province":"Badajoz",
    "wof:name":"Montenegro De Tena-davila Juan Pedro",
    "wof:placetype":"venue"
},
  "geometry": {"coordinates":[-6.9760041237,38.8787460327],"type":"Point"}
}