{
  "type": "Feature",
  "properties": {
    "addr:full":"Calle de Conde De Cardenas, 1 Cordoba C\u00f3rdoba 14002",
    "addr:postcode":"14002",
    "addr:street":"Calle De Conde De Cardenas 1 Cordoba Co\u0301Rdoba",
    "iso:country":"ES",
    "sg:address":"Calle de Conde De Cardenas, 1",
    "sg:city":"Cordoba",
    "sg:orig_category":"Confecci\u00d3n De Sombreros Y Tocados",
    "sg:phone":"+34 957 47 79 53",
    "sg:postcode":"14002",
    "sg:province":"C\u00f3rdoba",
    "wof:name":"Herederos De J.rusi C.b.",
    "wof:placetype":"venue"
},
  "geometry": {"coordinates":[-4.7771582603,37.8841934204],"type":"Point"}
}