{
  "type": "Feature",
  "properties": {
    "addr:full":"Calle de Erdikokale, 3 Mutriku Guip\u00f9zcoa 20830",
    "addr:housenumber":"3",
    "addr:postcode":"20830",
    "addr:street":"Calle De Erdikokale;Guipu\u0300Zcoa",
    "iso:country":"ES",
    "sg:address":"Calle de Erdikokale, 3",
    "sg:city":"Mutriku",
    "sg:orig_category":"Peluqueros: De Se\u00d1oras",
    "sg:phone":"+34 943 60 37 10",
    "sg:postcode":"20830",
    "sg:province":"Guip\u00f9zcoa",
    "wof:name":"Azpiazu Aramberri Maria Lourdes",
    "wof:placetype":"venue"
},
  "geometry": {"coordinates":[-2.3865399361,43.3074073792],"type":"Point"}
}