{
  "type": "Feature",
  "properties": {
    "addr:full":"Calle de Padilla, 5 Medina Campo Valladolid 47400",
    "addr:housenumber":"5",
    "addr:postcode":"47400",
    "addr:street":"Calle De Padilla",
    "iso:country":"ES",
    "sg:address":"Calle de Padilla, 5",
    "sg:city":"Medina Campo",
    "sg:orig_category":"Bisuter\u00cda, Joyer\u00cda, Relojer\u00cda (al Por Menor)",
    "sg:phone":"+34 983 80 02 42",
    "sg:postcode":"47400",
    "sg:province":"Valladolid",
    "wof:name":"Ordo\u00f1ez Hernandez Justino",
    "wof:placetype":"venue"
},
  "geometry": {"coordinates":[-4.9150657654,41.3094406128],"type":"Point"}
}