{
  "type": "Feature",
  "properties": {
    "addr:full":"Urb La Zenia, 10 La Zenia Alicante 03189",
    "addr:housenumber":"10",
    "addr:postcode":"03189",
    "addr:street":"La Zenia",
    "iso:country":"ES",
    "sg:address":"Urb La Zenia, 10",
    "sg:city":"La Zenia",
    "sg:orig_category":"Comercio De Piezas De Recambio Y De Accesorios De Veh\u00cdculos, Veh\u00cdculos Industriales",
    "sg:phone":"+34 966 76 04 04",
    "sg:postcode":"03189",
    "sg:province":"Alicante",
    "wof:name":"Repuestos Alameda S.l.",
    "wof:placetype":"venue"
},
  "geometry": {"coordinates":[-0.7534540296,37.9003753662],"type":"Point"}
}