{
  "type": "Feature",
  "properties": {
    "addr:full":"Avda Cervantes, 49 Arizgoiti Vizcaya 48970",
    "addr:housenumber":"49",
    "addr:postcode":"48970",
    "addr:street":"Avda Cervantes",
    "iso:country":"ES",
    "sg:address":"Avda Cervantes, 49",
    "sg:city":"Arizgoiti",
    "sg:orig_category":"Talleres De Corte Y Confecci\u00d3n",
    "sg:phone":"+34 944 26 06 88",
    "sg:postcode":"48970",
    "sg:province":"Vizcaya",
    "wof:name":"Jazkilan S.l.",
    "wof:placetype":"venue"
},
  "geometry": {"coordinates":[-2.8811762333,43.2426109314],"type":"Point"}
}