{
  "type": "Feature",
  "properties": {
    "iso:country":"ES",
    "sg:address":"Carrer de Victor Catala, S/n",
    "sg:city":"Reus",
    "sg:orig_category":"Reparaci\u00d3n Y Restauraci\u00d3n De Objetos Diversos",
    "sg:phone":"+34 977 31 32 17",
    "sg:postcode":"43206",
    "sg:province":"Tarragona",
    "wof:name":"Andres Romero Neumaticos S.l.",
    "wof:placetype":"venue"
},
  "geometry": {"coordinates":[1.0823786259,41.1555480957],"type":"Point"}
}