{
  "type": "Feature",
  "properties": {
    "iso:country":"ES",
    "sg:address":"Calle de Alhamar, 9",
    "sg:city":"Granada",
    "sg:orig_category":"Servicios Gsm",
    "sg:phone":"+34 958 25 24 86",
    "sg:postcode":"18005",
    "sg:province":"Granada",
    "wof:name":"Retevgran S.l.",
    "wof:placetype":"venue"
},
  "geometry": {"coordinates":[-3.6004703045,37.1689834595],"type":"Point"}
}