{
  "type": "Feature",
  "properties": {
    "addr:full":"Plaz Vivar Tellez, 4 Tijola Almer\u00eda 04880",
    "addr:housenumber":"4",
    "addr:postcode":"04880",
    "addr:street":"Plaz Vivar Tellez;Almeri\u0301A",
    "iso:country":"ES",
    "sg:address":"Plaz Vivar Tellez, 4",
    "sg:city":"Tijola",
    "sg:orig_category":"Transporte En General",
    "sg:phone":"+34 950 42 03 17",
    "sg:postcode":"04880",
    "sg:province":"Almer\u00eda",
    "wof:name":"Carrion Martinez Jose Antonio",
    "wof:placetype":"venue"
},
  "geometry": {"coordinates":[-2.4365708828,37.3452377319],"type":"Point"}
}