{
  "type": "Feature",
  "properties": {
    "iso:country":"ES",
    "sg:address":"Calle de Mayor, 40",
    "sg:city":"Tudela Duero",
    "sg:orig_category":"Abogados",
    "sg:phone":"+34 983 52 20 35",
    "sg:postcode":"47320",
    "sg:province":"Valladolid",
    "wof:name":"Sanz Rojo Dulce",
    "wof:placetype":"venue"
},
  "geometry": {"coordinates":[-4.5808138847,41.5862884521],"type":"Point"}
}