{
  "type": "Feature",
  "properties": {
    "iso:country":"ES",
    "sg:address":"Calle de Virgen De La Estrella, 21",
    "sg:city":"Malaga",
    "sg:orig_category":"Formaci\u00d3n Continuada (variada)",
    "sg:phone":"+34 952 33 80 69",
    "sg:postcode":"29007",
    "sg:province":"M\u00e1laga",
    "wof:name":"Palomo Bravo Asuncion",
    "wof:placetype":"venue"
},
  "geometry": {"coordinates":[-4.4426341057,36.7149391174],"type":"Point"}
}