{
  "type": "Feature",
  "properties": {
    "iso:country":"ES",
    "sg:address":"Avda Playas (las), 65",
    "sg:city":"Puerto Del Carmen",
    "sg:orig_category":"Supermercados Y Hipermercados",
    "sg:phone":"+34 928 51 60 26",
    "sg:postcode":"35510",
    "sg:province":"Las Palmas",
    "wof:name":"Supermercado Marcial S.l.",
    "wof:placetype":"venue"
},
  "geometry": {"coordinates":[-13.6543092728,28.9192905426],"type":"Point"}
}