{
  "type": "Feature",
  "properties": {
    "addr:full":"Carrer de Sardenya, 54 Barcelona Barcelona 08005",
    "addr:housenumber":"54",
    "addr:postcode":"08005",
    "addr:street":"Carrer De Sardenya",
    "iso:country":"ES",
    "sg:address":"Carrer de Sardenya, 54",
    "sg:city":"Barcelona",
    "sg:orig_category":"Administradores De Bienes Y Delegados De Comunidades De Propietarios",
    "sg:phone":"+34 932 21 54 73",
    "sg:postcode":"08005",
    "sg:province":"Barcelona",
    "sg:website":"www.barnagest.com",
    "wof:name":"Barnagest S.l.",
    "wof:placetype":"venue"
},
  "geometry": {"coordinates":[2.1900210381,41.3909683228],"type":"Point"}
}