{
  "type": "Feature",
  "properties": {
    "iso:country":"ES",
    "sg:address":"Carr Sant Sebastia, 12",
    "sg:city":"Ma\u00e7anet Selva",
    "sg:orig_category":"Zapatos (al Por Menor)",
    "sg:phone":"+34 972 85 81 67",
    "sg:postcode":"17412",
    "sg:province":"Girona",
    "wof:name":"Figueras Llinas Juan",
    "wof:placetype":"venue"
},
  "geometry": {"coordinates":[2.730907917,41.7769355774],"type":"Point"}
}