{
  "type": "Feature",
  "properties": {
    "iso:country":"ES",
    "sg:address":"Calle de Francisco Gervas (de), 5",
    "sg:city":"Alcobendas",
    "sg:orig_category":"Maquinaria Para Industrias Diversas",
    "sg:phone":"+34 916 62 03 01",
    "sg:postcode":"28108",
    "sg:province":"Madrid",
    "sg:website":"www.talcobendas.es",
    "wof:name":"Talleres Alcobendas S. A.",
    "wof:placetype":"venue"
},
  "geometry": {"coordinates":[-3.6517357826,40.5319366455],"type":"Point"}
}