{
  "type": "Feature",
  "properties": {
    "addr:full":"Avda El Ferial, 32 Benavente Zamora 49600",
    "addr:housenumber":"32",
    "addr:postcode":"49600",
    "addr:street":"Avda El Ferial",
    "iso:country":"ES",
    "sg:address":"Avda El Ferial, 32",
    "sg:city":"Benavente",
    "sg:orig_category":"Agricultores, Agricultores",
    "sg:phone":"+34 980 63 37 10",
    "sg:postcode":"49600",
    "sg:province":"Zamora",
    "wof:name":"Cortes Fernandez Benita",
    "wof:placetype":"venue"
},
  "geometry": {"coordinates":[-5.6743888855,42.0017700195],"type":"Point"}
}