{
  "type": "Feature",
  "properties": {
    "iso:country":"ES",
    "sg:address":"Calle de Malva, 11",
    "sg:city":"Girasoles",
    "sg:orig_category":"Negocio De Materiales De Construcci\u00d3n",
    "sg:phone":"+34 955 98 06 56",
    "sg:postcode":"41907",
    "sg:province":"Sevilla",
    "sg:website":"www.cecois.es",
    "wof:name":"Cecois S.l.",
    "wof:placetype":"venue"
},
  "geometry": {"coordinates":[-6.0776147842,37.4170455933],"type":"Point"}
}