{
  "type": "Feature",
  "properties": {
    "addr:full":"Calle de Trafalgar, 56 Guadalajara Guadalajara 19004",
    "addr:housenumber":"56",
    "addr:postcode":"19004",
    "addr:street":"Calle De Trafalgar",
    "iso:country":"ES",
    "sg:address":"Calle de Trafalgar, 56",
    "sg:city":"Guadalajara",
    "sg:orig_category":"Garajes De Veh\u00cdculos",
    "sg:phone":"+34 949 20 20 85",
    "sg:postcode":"19004",
    "sg:province":"Guadalajara",
    "sg:website":"www.autodasa.com",
    "wof:name":"Automoviles Guadalajara, S. A.",
    "wof:placetype":"venue"
},
  "geometry": {"coordinates":[-3.1935689449,40.6253700256],"type":"Point"}
}