{
  "type": "Feature",
  "properties": {
    "iso:country":"ES",
    "sg:address":"C.v. Alboraya C.v., 28",
    "sg:city":"Valencia",
    "sg:orig_category":"Bisuteros (fabricaci\u00d3n, Al Por Mayor)",
    "sg:phone":"+34 963 62 77 66",
    "sg:postcode":"46020",
    "sg:province":"Valencia",
    "wof:name":"Bellido Caparros Francisco Gabriel",
    "wof:placetype":"venue"
},
  "geometry": {"coordinates":[-0.3769130111,39.4687919617],"type":"Point"}
}