{
  "type": "Feature",
  "properties": {
    "addr:full":"Calle de Serrano Galvache, 5 Madrid Madrid 28033",
    "addr:housenumber":"5",
    "addr:postcode":"28033",
    "addr:street":"Calle De Serrano Galvache",
    "iso:country":"ES",
    "sg:address":"Calle de Serrano Galvache, 5",
    "sg:city":"Madrid",
    "sg:orig_category":"Centros Empresariales",
    "sg:phone":"+34 913 02 62 11",
    "sg:postcode":"28033",
    "sg:province":"Madrid",
    "wof:name":"Logs Consultores S. A.",
    "wof:placetype":"venue"
},
  "geometry": {"coordinates":[-3.6683928967,40.4712638855],"type":"Point"}
}