{
  "type": "Feature",
  "properties": {
    "addr:full":"Calle de Grande, 18 Calahorra La Rioja 26500",
    "addr:housenumber":"18",
    "addr:postcode":"26500",
    "addr:street":"Calle De Grande",
    "iso:country":"ES",
    "sg:address":"Calle de Grande, 18",
    "sg:city":"Calahorra",
    "sg:orig_category":"Ropa Para Se\u00d1oras (al Por Menor)",
    "sg:phone":"+34 941 13 23 45",
    "sg:postcode":"26500",
    "sg:province":"La Rioja",
    "wof:name":"Beajar S.l.",
    "wof:placetype":"venue"
},
  "geometry": {"coordinates":[-1.9622189999,42.3017883301],"type":"Point"}
}