{
  "type": "Feature",
  "properties": {
    "iso:country":"ES",
    "sg:address":"Calle de Caleras, 6",
    "sg:city":"Herencia",
    "sg:orig_category":"Plomeros",
    "sg:phone":"+34 926 57 25 80",
    "sg:postcode":"13640",
    "sg:province":"Ciudad Real",
    "wof:name":"Calefaccion Y Fontaneria Nuevo Milenio S.l.",
    "wof:placetype":"venue"
},
  "geometry": {"coordinates":[-3.3543639183,39.3616142273],"type":"Point"}
}