{
  "type": "Feature",
  "properties": {
    "addr:full":"Cmno San Rafael, S/n Utebo Zaragoza 50180",
    "addr:housenumber":"s / n",
    "addr:postcode":"50180",
    "addr:street":"Cmno San Rafael",
    "iso:country":"ES",
    "sg:address":"Cmno San Rafael, S/n",
    "sg:city":"Utebo",
    "sg:orig_category":"Centros De Educaci\u00d3n Especial",
    "sg:phone":"+34 976 77 44 42",
    "sg:postcode":"50180",
    "sg:province":"Zaragoza",
    "wof:name":"Colegio Publico De Utebo",
    "wof:placetype":"venue"
},
  "geometry": {"coordinates":[-1.0217050314,41.7092208862],"type":"Point"}
}