{
  "type": "Feature",
  "properties": {
    "iso:country":"ES",
    "sg:address":"Calle de Nuestra Se\u00d1ora De La Soledad, 34",
    "sg:city":"Rute",
    "sg:orig_category":"Armas Y Municiones (fabricaci\u00d3n, Al Por Mayor)",
    "sg:phone":"+34 957 53 91 65",
    "sg:postcode":"14960",
    "sg:province":"C\u00f3rdoba",
    "wof:name":"Reyes Jimenez Pedro",
    "wof:placetype":"venue"
},
  "geometry": {"coordinates":[-4.3670558929,37.3282737732],"type":"Point"}
}