{
  "type": "Feature",
  "properties": {
    "addr:full":"Avgd Sants Patrons, S/n Alzira Valencia 46600",
    "addr:housenumber":"s / n",
    "addr:postcode":"46600",
    "addr:street":"Patrons",
    "iso:country":"ES",
    "sg:address":"Avgd Sants Patrons, S/n",
    "sg:city":"Alzira",
    "sg:classifiers":[
        {
            "category":"Taxi",
            "type":"Transportation"
        }
    ],
    "sg:phone":"+34 962 41 09 75",
    "sg:postcode":"46600",
    "sg:province":"Valencia",
    "wof:name":"Taxis Alzira",
    "wof:placetype":"venue"
},
  "geometry": {"coordinates":[-0.4378489852,39.1517295837],"type":"Point"}
}