{
  "type": "Feature",
  "properties": {
    "iso:country":"ES",
    "sg:address":"Afueras, 9",
    "sg:city":"S. Josep Talaia",
    "sg:orig_category":"Servicios Diversos",
    "sg:phone":"+34 971 18 73 53",
    "sg:postcode":"07830",
    "sg:province":"Islas Baleares",
    "sg:website":"www.ibizaecologic.com",
    "wof:name":"Ibiza Ecologic",
    "wof:placetype":"venue"
},
  "geometry": {"coordinates":[1.2472629547,38.9165306091],"type":"Point"}
}