{
  "type": "Feature",
  "properties": {
    "iso:country":"ES",
    "sg:address":"La Senda, 10",
    "sg:city":"Estepa",
    "sg:orig_category":"Empresas De Carpinter\u00cda De Madera",
    "sg:phone":"+34 955 91 23 00",
    "sg:postcode":"41560",
    "sg:province":"Sevilla",
    "wof:name":"Fernandez Fernandez Miguel Nicolas",
    "wof:placetype":"venue"
},
  "geometry": {"coordinates":[-4.8760910034,37.2955474854],"type":"Point"}
}