{
  "type": "Feature",
  "properties": {
    "addr:full":"Ctra Tavernes Valldigna-lliria, 48 Vilamarxant Valencia 46191",
    "addr:housenumber":"48",
    "addr:postcode":"46191",
    "addr:street":"Ctra Tavernes Valldigna-Lliria",
    "iso:country":"ES",
    "sg:address":"Ctra Tavernes Valldigna-lliria, 48",
    "sg:city":"Vilamarxant",
    "sg:orig_category":"Molduras, Junquillos, Listones Y Molduras Perforadas",
    "sg:phone":"+34 962 71 20 80",
    "sg:postcode":"46191",
    "sg:province":"Valencia",
    "wof:name":"Garcia Zarzo Salvador",
    "wof:placetype":"venue"
},
  "geometry": {"coordinates":[-0.6488505006,39.5570449829],"type":"Point"}
}