{
  "type": "Feature",
  "properties": {
    "addr:full":"Calle de Salinas, S/n Fuengirola M\u00e1laga 29640",
    "addr:housenumber":"s / n",
    "addr:postcode":"29640",
    "addr:street":"Calle De Salinas;Ma\u0301Laga",
    "iso:country":"ES",
    "sg:address":"Calle de Salinas, S/n",
    "sg:city":"Fuengirola",
    "sg:orig_category":"Fabricaci\u00d3n De Muebles",
    "sg:phone":"+34 952 66 63 62",
    "sg:postcode":"29640",
    "sg:province":"M\u00e1laga",
    "wof:name":"Muebles Caparros E Hijos S.l.",
    "wof:placetype":"venue"
},
  "geometry": {"coordinates":[-4.6145648956,36.5552330017],"type":"Point"}
}