{
  "type": "Feature",
  "properties": {
    "iso:country":"ES",
    "sg:address":"Calle de Torre De Ugao, 2",
    "sg:city":"Ugao-miraballes",
    "sg:orig_category":"Plomeros",
    "sg:phone":"+34 946 48 11 14",
    "sg:postcode":"48490",
    "sg:province":"Vizcaya",
    "wof:name":"Ugao Instalaciones S.l.",
    "wof:placetype":"venue"
},
  "geometry": {"coordinates":[-2.9049639702,43.1779060364],"type":"Point"}
}