{
  "type": "Feature",
  "properties": {
    "iso:country":"ES",
    "sg:address":"Carrer de Major, 1",
    "sg:city":"Aig\u00fces",
    "sg:orig_category":"Carnicer\u00cdas, Carnicer\u00cdas",
    "sg:phone":"+34 965 69 00 21",
    "sg:postcode":"03569",
    "sg:province":"Alicante",
    "wof:name":"Iborra Garcia Jose",
    "wof:placetype":"venue"
},
  "geometry": {"coordinates":[-0.3638910055,38.5004730225],"type":"Point"}
}