{
  "type": "Feature",
  "properties": {
    "iso:country":"ES",
    "sg:address":"Calle de Garciez, S/n",
    "sg:city":"Torredelcampo",
    "sg:orig_category":"Instalaci\u00d3n, Reparaci\u00d3n De Ascensores Y Montacargas",
    "sg:phone":"+34 953 56 73 83",
    "sg:postcode":"23640",
    "sg:province":"Ja\u00e9n",
    "wof:name":"Decoraciones Cabinas Y Componentes S.l.",
    "wof:placetype":"venue"
},
  "geometry": {"coordinates":[-3.8970820904,37.7760620117],"type":"Point"}
}