{
  "type": "Feature",
  "properties": {
    "addr:full":"Jaume Balmes, 14 S. Quirze Besora Barcelona 08580",
    "addr:housenumber":"14",
    "addr:postcode":"08580",
    "addr:street":"Jaume Balmes",
    "iso:country":"ES",
    "sg:address":"Jaume Balmes, 14",
    "sg:city":"S. Quirze Besora",
    "sg:orig_category":"Ingeniero",
    "sg:phone":"+34 938 52 91 85",
    "sg:postcode":"08580",
    "sg:province":"Barcelona",
    "wof:name":"Muntatges Serradell S.c.p.",
    "wof:placetype":"venue"
},
  "geometry": {"coordinates":[2.2146670818,42.1001625061],"type":"Point"}
}