{
  "type": "Feature",
  "properties": {
    "iso:country":"ES",
    "sg:address":"Calle de Isabel La Catolica, S/n",
    "sg:city":"Madrigal Altas Torres",
    "sg:orig_category":"Sanatorios M\u00c9dico",
    "sg:phone":"+34 920 32 04 58",
    "sg:postcode":"05220",
    "sg:province":"\u00c1vila",
    "wof:name":"Gerencia De Atencion Primaria De Avila",
    "wof:placetype":"venue"
},
  "geometry": {"coordinates":[-4.9958200455,41.0881195068],"type":"Point"}
}