{
  "type": "Feature",
  "properties": {
    "iso:country":"ES",
    "sg:address":"Calle de Torres Quevedo (de), 2",
    "sg:city":"Fuenlabrada",
    "sg:orig_category":"Productos Qu\u00cdmicos (fabricaci\u00d3n, Al Por Mayor)",
    "sg:phone":"+34 916 15 42 88",
    "sg:postcode":"28946",
    "sg:province":"Madrid",
    "wof:name":"Deterin S.a.",
    "wof:placetype":"venue"
},
  "geometry": {"coordinates":[-3.7799530029,40.2816352844],"type":"Point"}
}