{
  "type": "Feature",
  "properties": {
    "iso:country":"ES",
    "sg:address":"Avda Espa\u00d1a (de), 30",
    "sg:city":"Ubrique",
    "sg:orig_category":"Arte, Cultura, Edici\u00d3n",
    "sg:phone":"+34 956 46 46 94",
    "sg:postcode":"11600",
    "sg:province":"C\u00e1diz",
    "wof:name":"Asoc.espa\u00f1ola Del Perro De Agua Espa\u00f1ol",
    "wof:placetype":"venue"
},
  "geometry": {"coordinates":[-5.4467277527,36.6756439209],"type":"Point"}
}