{
  "type": "Feature",
  "properties": {
    "iso:country":"ES",
    "sg:address":"Cmno Real Alta, 27",
    "sg:city":"Mota Cuervo",
    "sg:orig_category":"Alquiler De Veh\u00cdculos: Turismos Y Utilitarios",
    "sg:phone":"+34 967 18 10 92",
    "sg:postcode":"16630",
    "sg:province":"Cuenca",
    "wof:name":"Chacon Mujeriego Eduardo",
    "wof:placetype":"venue"
},
  "geometry": {"coordinates":[-2.871309042,39.503036499],"type":"Point"}
}