{
  "type": "Feature",
  "properties": {
    "addr:full":"Calle de San Rosendo, 25 Coru\u00d1a La Coru\u00f1a 15007",
    "addr:housenumber":"25",
    "addr:postcode":"15007",
    "addr:street":"Calle De San Rosendo;La Corun\u0303A",
    "iso:country":"ES",
    "sg:address":"Calle de San Rosendo, 25",
    "sg:city":"Coru\u00d1a",
    "sg:orig_category":"Construcci\u00d3n Mec\u00c1nica",
    "sg:phone":"+34 981 23 14 60",
    "sg:postcode":"15007",
    "sg:province":"La Coru\u00f1a",
    "wof:name":"Mu\u00f1iz Caama\u00f1o Jose Manuel",
    "wof:placetype":"venue"
},
  "geometry": {"coordinates":[-8.4126853943,43.3528862],"type":"Point"}
}