{
  "type": "Feature",
  "properties": {
    "iso:country":"ES",
    "sg:address":"Avda Guijar (del), 3",
    "sg:city":"Arganda",
    "sg:orig_category":"Chapister\u00cda",
    "sg:phone":"+34 918 70 16 92",
    "sg:postcode":"28500",
    "sg:province":"Madrid",
    "wof:name":"Ferjus S.l.",
    "wof:placetype":"venue"
},
  "geometry": {"coordinates":[-3.4630761147,40.3186721802],"type":"Point"}
}