{
  "type": "Feature",
  "properties": {
    "iso:country":"ES",
    "sg:address":"Calle de Tejares, 11",
    "sg:city":"Malaga",
    "sg:orig_category":"Afilado",
    "sg:phone":"+34 952 30 03 45",
    "sg:postcode":"29011",
    "sg:province":"M\u00e1laga",
    "wof:name":"Martin Palacios Antonio Jeronimo",
    "wof:placetype":"venue"
},
  "geometry": {"coordinates":[-4.4358649254,36.7283096313],"type":"Point"}
}