{
  "type": "Feature",
  "properties": {
    "addr:full":"Carrer de Jaume Balmes, 16 Mataro Barcelona 08301",
    "addr:housenumber":"16",
    "addr:postcode":"08301",
    "addr:street":"Carrer De Jaume Balmes",
    "iso:country":"ES",
    "sg:address":"Carrer de Jaume Balmes, 16",
    "sg:city":"Mataro",
    "sg:orig_category":"Fabricaci\u00d3n De Correas De Transmisi\u00d3n",
    "sg:phone":"+34 937 90 19 35",
    "sg:postcode":"08301",
    "sg:province":"Barcelona",
    "sg:website":"www.soler.com",
    "wof:name":"Soler Ridameya Francisco",
    "wof:placetype":"venue"
},
  "geometry": {"coordinates":[2.4461369514,41.5363464355],"type":"Point"}
}