{
  "type": "Feature",
  "properties": {
    "addr:full":"Carrer de Mar, 3 Malgrat Mar Barcelona 08380",
    "addr:housenumber":"3",
    "addr:postcode":"08380",
    "addr:street":"Carrer De Mar",
    "iso:country":"ES",
    "sg:address":"Carrer de Mar, 3",
    "sg:city":"Malgrat Mar",
    "sg:orig_category":"Cajas De Ahorro",
    "sg:phone":"+34 937 61 95 10",
    "sg:postcode":"08380",
    "sg:province":"Barcelona",
    "wof:name":"Caja De Ahorros Del Mediterraneo",
    "wof:placetype":"venue"
},
  "geometry": {"coordinates":[2.7417109013,41.6457595825],"type":"Point"}
}