{
  "type": "Feature",
  "properties": {
    "iso:country":"ES",
    "sg:address":"Calle de Miguel De Unamuno, 22",
    "sg:city":"Fuenlabrada",
    "sg:orig_category":"Alquiler De V\u00cddeo",
    "sg:phone":"+34 916 06 86 14",
    "sg:postcode":"28944",
    "sg:province":"Madrid",
    "wof:name":"Cruz Rodriguez Bonifacio",
    "wof:placetype":"venue"
},
  "geometry": {"coordinates":[-3.7908649445,40.284362793],"type":"Point"}
}