{
  "type": "Feature",
  "properties": {
    "addr:full":"Carrer de Joaquim Valls, 90 Barcelona Barcelona 08042",
    "addr:housenumber":"90",
    "addr:postcode":"08042",
    "addr:street":"Carrer De Joaquim Valls",
    "iso:country":"ES",
    "sg:address":"Carrer de Joaquim Valls, 90",
    "sg:city":"Barcelona",
    "sg:orig_category":"Papeler\u00cdas, Librer\u00cdas",
    "sg:phone":"+34 933 54 48 19",
    "sg:postcode":"08042",
    "sg:province":"Barcelona",
    "wof:name":"Guil Arque Francisco",
    "wof:placetype":"venue"
},
  "geometry": {"coordinates":[2.1786360741,41.4446601868],"type":"Point"}
}