{
  "type": "Feature",
  "properties": {
    "iso:country":"ES",
    "sg:address":"Calle de Antillon, 7",
    "sg:city":"Madrid",
    "sg:orig_category":"\u00d3ptica: Instrumentos (fabricaci\u00d3n)",
    "sg:phone":"+34 914 64 28 73",
    "sg:postcode":"28011",
    "sg:province":"Madrid",
    "wof:name":"Garcia Alonso Carlos",
    "wof:placetype":"venue"
},
  "geometry": {"coordinates":[-3.7281799316,40.4128494263],"type":"Point"}
}