{
  "type": "Feature",
  "properties": {
    "addr:full":"Plaz Agua, 1 Siles Ja\u00e9n 23380",
    "addr:housenumber":"1",
    "addr:postcode":"23380",
    "addr:street":"Agua",
    "iso:country":"ES",
    "sg:address":"Plaz Agua, 1",
    "sg:city":"Siles",
    "sg:orig_category":"Administraciones Regionales, Departamentales Y Locales",
    "sg:phone":"+34 953 49 00 11",
    "sg:postcode":"23380",
    "sg:province":"Ja\u00e9n",
    "wof:name":"Ayuntamiento De Siles",
    "wof:placetype":"venue"
},
  "geometry": {"coordinates":[-2.5846040249,38.389289856],"type":"Point"}
}