{
  "type": "Feature",
  "properties": {
    "iso:country":"ES",
    "sg:address":"Rua Oza Dos Rios, 3",
    "sg:city":"Sada",
    "sg:orig_category":"Cl\u00cdnicas Dentales",
    "sg:phone":"+34 981 61 91 08",
    "sg:postcode":"15160",
    "sg:province":"La Coru\u00f1a",
    "wof:name":"De Paz Rodriguez Hugo",
    "wof:placetype":"venue"
},
  "geometry": {"coordinates":[-8.2543935776,43.3506126404],"type":"Point"}
}