{
  "type": "Feature",
  "properties": {
    "iso:country":"ES",
    "sg:address":"Cabecero, 7",
    "sg:city":"Terroso",
    "sg:orig_category":"Madera Para Construcci\u00d3n E Industria",
    "sg:phone":"+34 980 62 31 62",
    "sg:postcode":"49394",
    "sg:province":"Zamora",
    "wof:name":"Maderas Terroso S.l.",
    "wof:placetype":"venue"
},
  "geometry": {"coordinates":[-6.7428569794,42.0307655334],"type":"Point"}
}