{
  "type": "Feature",
  "properties": {
    "iso:country":"ES",
    "sg:address":"Avgd Pau Casals, 22",
    "sg:city":"Igualada",
    "sg:orig_category":"Institutos De Belleza",
    "sg:phone":"+34 938 04 48 05",
    "sg:postcode":"08700",
    "sg:province":"Barcelona",
    "wof:name":"Logar & Anoia S.l.",
    "wof:placetype":"venue"
},
  "geometry": {"coordinates":[1.6291630268,41.5785484314],"type":"Point"}
}