{
  "type": "Feature",
  "properties": {
    "addr:full":"Calle de Cultura, 42 San Jose Rinconada Sevilla 41300",
    "addr:housenumber":"42",
    "addr:postcode":"41300",
    "addr:street":"Calle De Cultura",
    "iso:country":"ES",
    "sg:address":"Calle de Cultura, 42",
    "sg:city":"San Jose Rinconada",
    "sg:orig_category":"Zapatos (al Por Menor)",
    "sg:phone":"+34 955 79 40 20",
    "sg:postcode":"41300",
    "sg:province":"Sevilla",
    "wof:name":"Calzados Seyos,s.l.",
    "wof:placetype":"venue"
},
  "geometry": {"coordinates":[-5.9429178238,37.4877586365],"type":"Point"}
}