{
  "type": "Feature",
  "properties": {
    "addr:full":"Calle de Alfaro, 1 Pinto Madrid 28320",
    "addr:housenumber":"1",
    "addr:postcode":"28320",
    "addr:street":"Calle De Alfaro;Pinto",
    "iso:country":"ES",
    "sg:address":"Calle de Alfaro, 1",
    "sg:city":"Pinto",
    "sg:orig_category":"Inmobiliaria (agencias)",
    "sg:phone":"+34 916 92 59 17",
    "sg:postcode":"28320",
    "sg:province":"Madrid",
    "wof:name":"T.p.c Gestiones Y Consulting Inmobiliario S.l.",
    "wof:placetype":"venue"
},
  "geometry": {"coordinates":[-3.6977119446,40.2444381714],"type":"Point"}
}