{
  "type": "Feature",
  "properties": {
    "addr:full":"Mcdo Central, 61 Zaragoza Zaragoza 50003",
    "addr:housenumber":"61",
    "addr:postcode":"50003",
    "iso:country":"ES",
    "sg:address":"Mcdo Central, 61",
    "sg:city":"Zaragoza",
    "sg:orig_category":"Pescader\u00cdas (al Por Menor)",
    "sg:phone":"+34 976 44 13 35",
    "sg:postcode":"50003",
    "sg:province":"Zaragoza",
    "wof:name":"Lopez Jimenez Jose Luis",
    "wof:placetype":"venue"
},
  "geometry": {"coordinates":[-0.8949292898,41.6613044739],"type":"Point"}
}