{
  "type": "Feature",
  "properties": {
    "iso:country":"ES",
    "sg:address":"Carrer de Rafael Batlle, 22",
    "sg:city":"Barcelona",
    "sg:orig_category":"Librer\u00cdas",
    "sg:phone":"+34 932 04 73 55",
    "sg:postcode":"08017",
    "sg:province":"Barcelona",
    "wof:name":"Huanca Hijar Silvia",
    "wof:placetype":"venue"
},
  "geometry": {"coordinates":[2.1271491051,41.3962783813],"type":"Point"}
}