{
  "type": "Feature",
  "properties": {
    "addr:full":"Avda Comunidad De Murcia, 67 Campo Criptana Ciudad Real 13610",
    "addr:housenumber":"67",
    "addr:postcode":"13610",
    "addr:street":"Avda Comunidad De Murcia;Criptana",
    "iso:country":"ES",
    "sg:address":"Avda Comunidad De Murcia, 67",
    "sg:city":"Campo Criptana",
    "sg:orig_category":"Lubrificantes (fabricaci\u00d3n, Al Por Mayor)",
    "sg:phone":"+34 926 56 18 85",
    "sg:postcode":"13610",
    "sg:province":"Ciudad Real",
    "wof:name":"Lubrimansa S.l.",
    "wof:placetype":"venue"
},
  "geometry": {"coordinates":[-3.1378788948,39.3997306824],"type":"Point"}
}