{
  "type": "Feature",
  "properties": {
    "iso:country":"ES",
    "sg:address":"Carr Josep Pla, 34",
    "sg:city":"Mas Flassia",
    "sg:orig_category":"Contenedores (mercanc\u00cdas)",
    "sg:phone":"+34 972 85 03 79",
    "sg:postcode":"17411",
    "sg:province":"Girona",
    "wof:name":"Fernandez Ortega Jose",
    "wof:placetype":"venue"
},
  "geometry": {"coordinates":[2.7773220539,41.789768219],"type":"Point"}
}