{
  "type": "Feature",
  "properties": {
    "addr:full":"Via Hispanidad, 61 Zaragoza Zaragoza 50012",
    "addr:housenumber":"61",
    "addr:postcode":"50012",
    "addr:street":"Via Hispanidad",
    "iso:country":"ES",
    "sg:address":"Via Hispanidad, 61",
    "sg:city":"Zaragoza",
    "sg:orig_category":"Asilos De Ancianos. Centros Privados",
    "sg:phone":"+34 976 32 03 93",
    "sg:postcode":"50012",
    "sg:province":"Zaragoza",
    "wof:name":"Aragonesa De Servicios Asistenciales La Paz S.c.",
    "wof:placetype":"venue"
},
  "geometry": {"coordinates":[-0.9148296118,41.6411399841],"type":"Point"}
}