{
  "type": "Feature",
  "properties": {
    "iso:country":"ES",
    "sg:address":"Calle de Lagrima, 9",
    "sg:city":"Malaga",
    "sg:orig_category":"Cajas Y Embalajes De Cart\u00d3n Y Papel",
    "sg:phone":"+34 952 26 58 51",
    "sg:postcode":"29014",
    "sg:province":"M\u00e1laga",
    "wof:name":"Martin Carrasquilla Jose Gregorio",
    "wof:placetype":"venue"
},
  "geometry": {"coordinates":[-4.4159932137,36.746471405],"type":"Point"}
}