{
  "type": "Feature",
  "properties": {
    "iso:country":"ES",
    "sg:address":"Avda Juan Carlos I, 11",
    "sg:city":"Aguilas",
    "sg:orig_category":"Ropa Para Se\u00d1oras Y Caballeros (al Por Menor)",
    "sg:phone":"+34 968 44 85 12",
    "sg:postcode":"30880",
    "sg:province":"Murcia",
    "wof:name":"Lopez Soto Rosa Maria",
    "wof:placetype":"venue"
},
  "geometry": {"coordinates":[-1.5846600533,37.4043045044],"type":"Point"}
}