{
  "type": "Feature",
  "properties": {
    "addr:full":"Carrer de Catalans, 21 Cornella Llobregat Barcelona 08940",
    "addr:housenumber":"21",
    "addr:postcode":"08940",
    "addr:street":"Carrer De Catalans",
    "iso:country":"ES",
    "sg:address":"Carrer de Catalans, 21",
    "sg:city":"Cornella Llobregat",
    "sg:orig_category":"Fachadas",
    "sg:phone":"+34 933 76 34 21",
    "sg:postcode":"08940",
    "sg:province":"Barcelona",
    "wof:name":"Villena Rossell Guido Jaime",
    "wof:placetype":"venue"
},
  "geometry": {"coordinates":[2.0775749683,41.3633308411],"type":"Point"}
}