{
  "type": "Feature",
  "properties": {
    "addr:full":"Bidegaina Kalea, 12 Elizalde Guip\u00f9zcoa 20180",
    "addr:housenumber":"12",
    "addr:postcode":"20180",
    "addr:street":"Bidegaina Kalea;Guipu\u0300Zcoa",
    "iso:country":"ES",
    "sg:address":"Bidegaina Kalea, 12",
    "sg:city":"Elizalde",
    "sg:classifiers":[
        {
            "category":"Personal",
            "subcategory":"Barber",
            "type":"Services"
        }
    ],
    "sg:phone":"+34 943 49 44 64",
    "sg:postcode":"20180",
    "sg:province":"Guip\u00f9zcoa",
    "sg:tags":[
        "caballeros",
        "de",
        "peluqueros"
    ],
    "wof:name":"Errazkin Ofretorio Mikel",
    "wof:placetype":"venue"
},
  "geometry": {"coordinates":[-1.8629590273,43.2992401123],"type":"Point"}
}