{
  "type": "Feature",
  "properties": {
    "addr:full":"Avda Vega (p I Antequera), 14 Antequera M\u00e1laga 29200",
    "addr:housenumber":"14",
    "addr:postcode":"29200",
    "addr:street":"Avda Vega P;Antequera",
    "iso:country":"ES",
    "sg:address":"Avda Vega (p I Antequera), 14",
    "sg:city":"Antequera",
    "sg:orig_category":"Persianas Interiores, Exteriores",
    "sg:phone":"+34 952 70 50 83",
    "sg:postcode":"29200",
    "sg:province":"M\u00e1laga",
    "wof:name":"Hurtatolt S.l.l.",
    "wof:placetype":"venue"
},
  "geometry": {"coordinates":[-4.561384201,37.0216293335],"type":"Point"}
}