{
  "type": "Feature",
  "properties": {
    "iso:country":"ES",
    "sg:address":"Avda Gran Via Rey Juan Carlos I, 40",
    "sg:city":"Logro\u00f1o",
    "sg:orig_category":"Tapicer\u00cdas",
    "sg:phone":"+34 941 20 69 25",
    "sg:postcode":"26005",
    "sg:province":"La Rioja",
    "wof:name":"Arrieta Hermanos S. A.",
    "wof:placetype":"venue"
},
  "geometry": {"coordinates":[-2.4513883591,42.4645805359],"type":"Point"}
}