{
  "type": "Feature",
  "properties": {
    "iso:country":"ES",
    "sg:address":"Calle de Pablo Neruda, 47",
    "sg:city":"Arroyo De La Miel-benalmadena Costa",
    "sg:orig_category":"Promotores Constructores",
    "sg:phone":"+34 952 57 12 64",
    "sg:postcode":"29631",
    "sg:province":"M\u00e1laga",
    "wof:name":"Proyectos, Obras Y Carretera S.l.",
    "wof:placetype":"venue"
},
  "geometry": {"coordinates":[-4.5482521057,36.6017608643],"type":"Point"}
}