{
  "type": "Feature",
  "properties": {
    "addr:full":"Calle de Allue Salvador, 13 Zaragoza Zaragoza 50001",
    "addr:housenumber":"13",
    "addr:postcode":"50001",
    "addr:street":"Calle De Allue Salvador",
    "iso:country":"ES",
    "sg:address":"Calle de Allue Salvador, 13",
    "sg:city":"Zaragoza",
    "sg:orig_category":"Multimedia: Servicios En L\u00cdnea, Acceso En L\u00cdnea, Cd",
    "sg:phone":"+34 976 23 98 68",
    "sg:postcode":"50001",
    "sg:province":"Zaragoza",
    "sg:website":"www.azormultimedia.com",
    "wof:name":"Azor Multimedia S.l.l.",
    "wof:placetype":"venue"
},
  "geometry": {"coordinates":[-0.8777130246,41.6485023499],"type":"Point"}
}