{
  "type": "Feature",
  "properties": {
    "iso:country":"ES",
    "sg:address":"Av Cister, 44",
    "sg:city":"Secar De La Real",
    "sg:orig_category":"Molduras, Junquillos, Listones Y Molduras Perforadas",
    "sg:phone":"+34 971 76 50 54",
    "sg:postcode":"07010",
    "sg:province":"Islas Baleares",
    "wof:name":"Rohulam  Fatima",
    "wof:placetype":"venue"
},
  "geometry": {"coordinates":[2.6370019913,39.6080665588],"type":"Point"}
}