{
  "type": "Feature",
  "properties": {
    "iso:country":"ES",
    "sg:address":"Calle de O'daly, 52",
    "sg:city":"Santa Cruz Palma",
    "sg:orig_category":"Radiocomunicaciones, Telefon\u00cda M\u00d3vil, Radiomensajer\u00cda: Servicios, Comercializaci\u00d3n",
    "sg:phone":"+34 922 41 19 56",
    "sg:postcode":"38700",
    "sg:province":"Santa Cruz De Tenerife",
    "wof:name":"Telyco La Palma S.l.",
    "wof:placetype":"venue"
},
  "geometry": {"coordinates":[-16.3033008575,28.4396839142],"type":"Point"}
}