{
  "type": "Feature",
  "properties": {
    "iso:country":"ES",
    "sg:address":"Costa De Ses Piques, 15",
    "sg:city":"Mao",
    "sg:orig_category":"Empresas De Carpinter\u00cda De Madera",
    "sg:phone":"+34 971 36 03 67",
    "sg:postcode":"07701",
    "sg:province":"Islas Baleares",
    "wof:name":"Carpinteria Hermanos Pons Carreras S.l.",
    "wof:placetype":"venue"
},
  "geometry": {"coordinates":[4.2572569847,39.8935852051],"type":"Point"}
}