{
  "type": "Feature",
  "properties": {
    "iso:country":"ES",
    "sg:address":"Calle de Bizkai, 51",
    "sg:city":"Galdakao",
    "sg:orig_category":"Reposter\u00cdas",
    "sg:phone":"+34 944 57 30 79",
    "sg:postcode":"48960",
    "sg:province":"Vizcaya",
    "wof:name":"Pilar Garcia Lemona, Panaderia Lemona",
    "wof:placetype":"venue"
},
  "geometry": {"coordinates":[-2.8452033997,43.2340660095],"type":"Point"}
}