{
  "type": "Feature",
  "properties": {
    "addr:full":"Calle de Campo (del), 1 Guia Isora Santa Cruz De Tenerife 38680",
    "addr:housenumber":"1",
    "addr:postcode":"38680",
    "addr:street":"Calle De Campo Del",
    "iso:country":"ES",
    "sg:address":"Calle de Campo (del), 1",
    "sg:city":"Guia Isora",
    "sg:orig_category":"Carnicer\u00cdas, Carnicer\u00cdas",
    "sg:phone":"+34 922 85 07 81",
    "sg:postcode":"38680",
    "sg:province":"Santa Cruz De Tenerife",
    "wof:name":"Barreto Dominguez Martin Alberto",
    "wof:placetype":"venue"
},
  "geometry": {"coordinates":[-16.7799282074,28.21159935],"type":"Point"}
}