{
  "type": "Feature",
  "properties": {
    "addr:full":"Calle de Sauce, 58 Torrejon Ardoz Madrid 28850",
    "addr:housenumber":"58",
    "addr:postcode":"28850",
    "addr:street":"Calle De Sauce",
    "iso:country":"ES",
    "sg:address":"Calle de Sauce, 58",
    "sg:city":"Torrejon Ardoz",
    "sg:orig_category":"Electricidad: Instaladores",
    "sg:phone":"+34 916 76 40 46",
    "sg:postcode":"28850",
    "sg:province":"Madrid",
    "wof:name":"Tecnologia Electronica Y Desarrollo Industrial S.l.",
    "wof:placetype":"venue"
},
  "geometry": {"coordinates":[-3.4545381069,40.4529685974],"type":"Point"}
}