{
  "type": "Feature",
  "properties": {
    "iso:country":"ES",
    "sg:address":"Carrer de Sant Josep, 22",
    "sg:city":"Sitges",
    "sg:orig_category":"Peluquer\u00cdas, Peluquer\u00cda Mixta",
    "sg:phone":"+34 938 94 02 83",
    "sg:postcode":"08870",
    "sg:province":"Barcelona",
    "wof:name":"Romero Padilla Maria Jose",
    "wof:placetype":"venue"
},
  "geometry": {"coordinates":[1.8070260286,41.2374305725],"type":"Point"}
}