{
  "type": "Feature",
  "properties": {
    "addr:full":"Carr Metge Vicent Portoles (del), 19 Lliria Valencia 46160",
    "addr:housenumber":"19",
    "addr:postcode":"46160",
    "addr:street":"Carr Metge Vicent Portoles Del",
    "iso:country":"ES",
    "sg:address":"Carr Metge Vicent Portoles (del), 19",
    "sg:city":"Lliria",
    "sg:orig_category":"Abogados",
    "sg:phone":"+34 962 78 18 09",
    "sg:postcode":"46160",
    "sg:province":"Valencia",
    "wof:name":"Romero Moros Jose Francisco",
    "wof:placetype":"venue"
},
  "geometry": {"coordinates":[-0.5945640206,39.6270370483],"type":"Point"}
}