{
  "type": "Feature",
  "properties": {
    "iso:country":"ES",
    "sg:address":"Carrer de Ferran Puig, 38",
    "sg:city":"Prat Llobregat",
    "sg:orig_category":"Librer\u00cdas",
    "sg:phone":"+34 934 78 35 48",
    "sg:postcode":"08820",
    "sg:province":"Barcelona",
    "wof:name":"Sarra Reverte Josep",
    "wof:placetype":"venue"
},
  "geometry": {"coordinates":[2.0936000347,41.3291893005],"type":"Point"}
}