{
  "type": "Feature",
  "properties": {
    "addr:full":"Calle de Mayor, 79 Alcantarilla Murcia 30820",
    "addr:housenumber":"79",
    "addr:postcode":"30820",
    "addr:street":"Calle De Mayor",
    "iso:country":"ES",
    "sg:address":"Calle de Mayor, 79",
    "sg:city":"Alcantarilla",
    "sg:orig_category":"Estancos",
    "sg:phone":"+34 968 80 07 42",
    "sg:postcode":"30820",
    "sg:province":"Murcia",
    "wof:name":"Sandoval Perez Maria Dolores",
    "wof:placetype":"venue"
},
  "geometry": {"coordinates":[-1.2120079994,37.9707489014],"type":"Point"}
}