{
  "type": "Feature",
  "properties": {
    "iso:country":"ES",
    "sg:address":"Calle de Chorrillo (el), 10",
    "sg:city":"Vejer De La Frontera",
    "sg:orig_category":"Producci\u00d3n, Venta De Productos De Agricultura Biol\u00d3gica",
    "sg:phone":"+34 956 45 03 54",
    "sg:postcode":"11150",
    "sg:province":"C\u00e1diz",
    "wof:name":"Rodriguez Morillo Salvador",
    "wof:placetype":"venue"
},
  "geometry": {"coordinates":[-5.9684262276,36.2497291565],"type":"Point"}
}