{
  "type": "Feature",
  "properties": {
    "addr:full":"Carr Jovades, 32 Santa Margalida Islas Baleares 07450",
    "addr:housenumber":"32",
    "addr:postcode":"07450",
    "addr:street":"Carr Jovades",
    "iso:country":"ES",
    "sg:address":"Carr Jovades, 32",
    "sg:city":"Santa Margalida",
    "sg:orig_category":"Agentes, Concesionarios Y Sucursales De Veh\u00cdculos",
    "sg:phone":"+34 971 52 31 32",
    "sg:postcode":"07450",
    "sg:province":"Islas Baleares",
    "wof:name":"Pep Perello S.l.",
    "wof:placetype":"venue"
},
  "geometry": {"coordinates":[3.1038069725,39.7055664062],"type":"Point"}
}