{
  "type": "Feature",
  "properties": {
    "addr:full":"Calle de Alferez Provisional (del), 9 Segovia Segovia 40005",
    "addr:housenumber":"9",
    "addr:postcode":"40005",
    "addr:street":"Calle De Alferez Provisional Del",
    "iso:country":"ES",
    "sg:address":"Calle de Alferez Provisional (del), 9",
    "sg:city":"Segovia",
    "sg:orig_category":"Maquinaria Para Industrias Diversas",
    "sg:phone":"+34 921 41 31 85",
    "sg:postcode":"40005",
    "sg:province":"Segovia",
    "wof:name":"Nespral Espacio Comunicacion",
    "wof:placetype":"venue"
},
  "geometry": {"coordinates":[-4.1149392128,40.943321228],"type":"Point"}
}