{
  "type": "Feature",
  "properties": {
    "addr:full":"Calle de Sur, 6 Isla Cristina Huelva 21410",
    "addr:housenumber":"6",
    "addr:postcode":"21410",
    "addr:street":"Calle De Sur",
    "iso:country":"ES",
    "sg:address":"Calle de Sur, 6",
    "sg:city":"Isla Cristina",
    "sg:orig_category":"Ropa Para Se\u00d1oras Y Caballeros (al Por Menor)",
    "sg:phone":"+34 959 33 13 05",
    "sg:postcode":"21410",
    "sg:province":"Huelva",
    "wof:name":"Fernandez Perez Pedro",
    "wof:placetype":"venue"
},
  "geometry": {"coordinates":[-7.3237500191,37.2017097473],"type":"Point"}
}