{
  "type": "Feature",
  "properties": {
    "addr:full":"Cm\u00d1o Regueiro, 11 Vigo Pontevedra 36211",
    "addr:housenumber":"11",
    "addr:postcode":"36211",
    "addr:street":"Regueiro",
    "iso:country":"ES",
    "sg:address":"Cm\u00d1o Regueiro, 11",
    "sg:city":"Vigo",
    "sg:orig_category":"Molduras, Junquillos, Listones Y Molduras Perforadas",
    "sg:phone":"+34 986 41 96 05",
    "sg:postcode":"36211",
    "sg:province":"Pontevedra",
    "wof:name":"Justo Fidalgo Jose",
    "wof:placetype":"venue"
},
  "geometry": {"coordinates":[-8.7289953232,42.222366333],"type":"Point"}
}