{
  "type": "Feature",
  "properties": {
    "addr:full":"Carrer de Llobregat, 8 Sant Vicen\u00c7 Dels Horts Barcelona 08620",
    "addr:housenumber":"8",
    "addr:postcode":"08620",
    "addr:street":"Carrer De Llobregat",
    "iso:country":"ES",
    "sg:address":"Carrer de Llobregat, 8",
    "sg:city":"Sant Vicen\u00c7 Dels Horts",
    "sg:orig_category":"Confiter\u00cdas, Chocolater\u00cdas (al Por Menor)",
    "sg:phone":"+34 936 76 80 11",
    "sg:postcode":"08620",
    "sg:province":"Barcelona",
    "wof:name":"Golobasi S.l.",
    "wof:placetype":"venue"
},
  "geometry": {"coordinates":[2.0061740875,41.3996162415],"type":"Point"}
}