{
  "type": "Feature",
  "properties": {
    "addr:full":"Calle de Carrera Del Sabado, 13 Zaragoza Zaragoza 50006",
    "addr:housenumber":"13",
    "addr:postcode":"50006",
    "addr:street":"Calle De Carrera Del Sabado",
    "iso:country":"ES",
    "sg:address":"Calle de Carrera Del Sabado, 13",
    "sg:city":"Zaragoza",
    "sg:orig_category":"Confecci\u00d3n De Trajes Para Se\u00d1oras",
    "sg:phone":"+34 976 37 74 04",
    "sg:postcode":"50006",
    "sg:province":"Zaragoza",
    "wof:name":"Copuysa, S. L.",
    "wof:placetype":"venue"
},
  "geometry": {"coordinates":[-0.8891659975,41.639591217],"type":"Point"}
}