{
  "type": "Feature",
  "properties": {
    "iso:country":"ES",
    "sg:address":"Carrer de Diputacio, 241",
    "sg:city":"Barcelona",
    "sg:orig_category":"Agencias De Viajes",
    "sg:phone":"+34 934 96 74 00",
    "sg:postcode":"08...",
    "sg:province":"Barcelona",
    "sg:website":"www.bestours.es",
    "wof:name":"Bestours S.a.",
    "wof:placetype":"venue"
},
  "geometry": {"coordinates":[2.1646409035,41.3887825012],"type":"Point"}
}