{
  "type": "Feature",
  "properties": {
    "addr:full":"Pg Elx, 17 Crevillent Alicante 03330",
    "addr:housenumber":"17",
    "addr:postcode":"03330",
    "addr:street":"Pg Elx",
    "iso:country":"ES",
    "sg:address":"Pg Elx, 17",
    "sg:city":"Crevillent",
    "sg:orig_category":"Confecci\u00d3n (fabricaci\u00d3n, Al Por Mayor)",
    "sg:phone":"+34 966 68 09 03",
    "sg:postcode":"03330",
    "sg:province":"Alicante",
    "wof:name":"Confecciones Gonvi 2000 S.l.",
    "wof:placetype":"venue"
},
  "geometry": {"coordinates":[-0.801379025,38.2479705811],"type":"Point"}
}