{
  "type": "Feature",
  "properties": {
    "addr:full":"Calle de Izoria, 5 Llodio \u00c1lava 01400",
    "addr:housenumber":"5",
    "addr:postcode":"01400",
    "addr:street":"Calle De Izoria",
    "iso:country":"ES",
    "sg:address":"Calle de Izoria, 5",
    "sg:city":"Llodio",
    "sg:orig_category":"M\u00c9dicos: Oftalmolog\u00cda",
    "sg:phone":"+34 946 72 97 82",
    "sg:postcode":"01400",
    "sg:province":"\u00c1lava",
    "wof:name":"Bilboftal S. L.",
    "wof:placetype":"venue"
},
  "geometry": {"coordinates":[-2.960089922,43.1445655823],"type":"Point"}
}