{
  "type": "Feature",
  "properties": {
    "addr:full":"Pseo. Constitucion, 48 Beas Segura Ja\u00e9n 23280",
    "addr:housenumber":"48",
    "addr:postcode":"23280",
    "addr:street":"Constitucion",
    "iso:country":"ES",
    "sg:address":"Pseo. Constitucion, 48",
    "sg:city":"Beas Segura",
    "sg:orig_category":"Abogados",
    "sg:phone":"+34 953 42 48 78",
    "sg:postcode":"23280",
    "sg:province":"Ja\u00e9n",
    "wof:name":"Gomar Martinez Antonio",
    "wof:placetype":"venue"
},
  "geometry": {"coordinates":[-2.8957929611,38.25440979],"type":"Point"}
}