{
  "type": "Feature",
  "properties": {
    "addr:full":"Calle de Juan Sebastian Elcano, 7 Ciudad Rodrigo Salamanca 37500",
    "addr:housenumber":"7",
    "addr:postcode":"37500",
    "addr:street":"Calle De Juan Sebastian Elcano",
    "iso:country":"ES",
    "sg:address":"Calle de Juan Sebastian Elcano, 7",
    "sg:city":"Ciudad Rodrigo",
    "sg:orig_category":"Muebles, Minoristas",
    "sg:phone":"+34 923 46 24 31",
    "sg:postcode":"37500",
    "sg:province":"Salamanca",
    "wof:name":"Davila Buron Ernesto",
    "wof:placetype":"venue"
},
  "geometry": {"coordinates":[-6.5279769897,40.605632782],"type":"Point"}
}