{
  "type": "Feature",
  "properties": {
    "iso:country":"ES",
    "sg:address":"Rua A Golpa, S/n",
    "sg:city":"Perillo",
    "sg:orig_category":"Frutas, Legumbres Frescas Y Tempranas (al Por Menor)",
    "sg:phone":"+34 981 63 84 02",
    "sg:postcode":"15172",
    "sg:province":"La Coru\u00f1a",
    "wof:name":"Rocha Pati\u00f1o Maria",
    "wof:placetype":"venue"
},
  "geometry": {"coordinates":[-8.3717241287,43.3336982727],"type":"Point"}
}