{
  "type": "Feature",
  "properties": {
    "iso:country":"ES",
    "sg:address":"Carr Migdia, 28",
    "sg:city":"Girona",
    "sg:orig_category":"Electricidad, Electr\u00d3nica: Suministros (al Por Menor)",
    "sg:phone":"+34 972 20 46 20",
    "sg:postcode":"17002",
    "sg:province":"Girona",
    "wof:name":"Peraferrer Bramon Josep",
    "wof:placetype":"venue"
},
  "geometry": {"coordinates":[2.8203589916,41.976234436],"type":"Point"}
}