{
  "type": "Feature",
  "properties": {
    "addr:full":"Hidalga Kalea, 5 Eskoriatza Guip\u00f9zcoa 20540",
    "addr:housenumber":"5",
    "addr:postcode":"20540",
    "addr:street":"Hidalga Kalea;Guipu\u0300Zcoa",
    "iso:country":"ES",
    "sg:address":"Hidalga Kalea, 5",
    "sg:city":"Eskoriatza",
    "sg:orig_category":"Molduras, Junquillos, Listones Y Molduras Perforadas",
    "sg:phone":"+34 943 71 47 29",
    "sg:postcode":"20540",
    "sg:province":"Guip\u00f9zcoa",
    "wof:name":"Elisea Gutierrez Barbero",
    "wof:placetype":"venue"
},
  "geometry": {"coordinates":[-2.5263741016,43.0170974731],"type":"Point"}
}