{
  "type": "Feature",
  "properties": {
    "iso:country":"ES",
    "sg:address":"Avda Costa, 104",
    "sg:city":"Gijon",
    "sg:orig_category":"Bazares, Art\u00cdculos De Limpieza Y De Cocina (al Por Menor)",
    "sg:phone":"+34 985 13 42 42",
    "sg:postcode":"33205",
    "sg:province":"Asturias",
    "wof:name":"Mier Sanchez Jose Manuel",
    "wof:placetype":"venue"
},
  "geometry": {"coordinates":[-5.6534509659,43.5372924805],"type":"Point"}
}