{
  "type": "Feature",
  "properties": {
    "iso:country":"ES",
    "sg:address":"Avda Pio Xii, 2",
    "sg:city":"Valencia",
    "sg:orig_category":"Ropa Para Ni\u00d1os (al Por Menor)",
    "sg:phone":"+34 963 49 24 55",
    "sg:postcode":"46009",
    "sg:province":"Valencia",
    "wof:name":"Jenny Spain S.a.",
    "wof:placetype":"venue"
},
  "geometry": {"coordinates":[-0.3912586868,39.479598999],"type":"Point"}
}