{
  "type": "Feature",
  "properties": {
    "iso:country":"ES",
    "sg:address":"Calle de Carretas, S/n",
    "sg:city":"Cabezon.barrio Viejo",
    "sg:orig_category":"Asilos De Ancianos. Centros Privados",
    "sg:phone":"+34 983 50 04 88",
    "sg:postcode":"47260",
    "sg:province":"Valladolid",
    "wof:name":"Residencia 3 Edad El Castillo S.l.",
    "wof:placetype":"venue"
},
  "geometry": {"coordinates":[-4.7283878326,41.6529464722],"type":"Point"}
}