{
  "type": "Feature",
  "properties": {
    "addr:full":"Pg Verdaguer, 132 Igualada Barcelona 08700",
    "addr:housenumber":"132",
    "addr:postcode":"08700",
    "addr:street":"Pg Verdaguer",
    "iso:country":"ES",
    "sg:address":"Pg Verdaguer, 132",
    "sg:city":"Igualada",
    "sg:orig_category":"Inmobiliaria (agencias)",
    "sg:phone":"+34 938 05 39 34",
    "sg:postcode":"08700",
    "sg:province":"Barcelona",
    "wof:name":"Noves Extensions S.l.",
    "wof:placetype":"venue"
},
  "geometry": {"coordinates":[1.6260050535,41.5790405273],"type":"Point"}
}