{
  "type": "Feature",
  "properties": {
    "iso:country":"ES",
    "sg:address":"Calle de Beatas, 4",
    "sg:city":"Alcala Henares",
    "sg:orig_category":"Centros Empresariales",
    "sg:phone":"+34 918 83 44 52",
    "sg:postcode":"28801",
    "sg:province":"Madrid",
    "wof:name":"Complutum Consulting S.l.",
    "wof:placetype":"venue"
},
  "geometry": {"coordinates":[-3.3628911972,40.4838371277],"type":"Point"}
}