{
  "type": "Feature",
  "properties": {
    "addr:full":"Ctra Motores (los), 121 Campillo Del Moro Almer\u00eda 04720",
    "addr:housenumber":"121",
    "addr:postcode":"04720",
    "addr:street":"Ctra Motores Los",
    "iso:country":"ES",
    "sg:address":"Ctra Motores (los), 121",
    "sg:city":"Campillo Del Moro",
    "sg:orig_category":"Edici\u00d3n De Diarios, Revistas, Boletines",
    "sg:phone":"+34 950 34 74 74",
    "sg:postcode":"04720",
    "sg:province":"Almer\u00eda",
    "wof:name":"Verdiland Ediciones S.l.",
    "wof:placetype":"venue"
},
  "geometry": {"coordinates":[-2.5741510391,36.8138160706],"type":"Point"}
}