{
  "type": "Feature",
  "properties": {
    "addr:full":"Carrer de Benlliure, 6 Castalla Alicante 03420",
    "addr:housenumber":"6",
    "addr:postcode":"03420",
    "addr:street":"Carrer De Benlliure",
    "iso:country":"ES",
    "sg:address":"Carrer de Benlliure, 6",
    "sg:city":"Castalla",
    "sg:orig_category":"Cristaler\u00cdas",
    "sg:phone":"+34 965 56 18 73",
    "sg:postcode":"03420",
    "sg:province":"Alicante",
    "wof:name":"Vidal Berbegal Juan Jose",
    "wof:placetype":"venue"
},
  "geometry": {"coordinates":[-0.6731759906,38.5907020569],"type":"Point"}
}