{
  "type": "Feature",
  "properties": {
    "iso:country":"ES",
    "sg:address":"Nuestra Se\u00f1ora De La Soledad, 10",
    "sg:city":"Guadiana Caudillo",
    "sg:orig_category":"Producci\u00d3n, Distribuci\u00d3n De Gas Butano Y Propano",
    "sg:phone":"+34 924 47 02 33",
    "sg:postcode":"06186",
    "sg:province":"Badajoz",
    "wof:name":"Butano Hermanos Molina Lopez S.l.",
    "wof:placetype":"venue"
},
  "geometry": {"coordinates":[-6.6902589798,38.9282913208],"type":"Point"}
}