{
  "type": "Feature",
  "properties": {
    "addr:full":"Avda Francisco Aguirre, 326 Talavera Reina Toledo 45600",
    "addr:housenumber":"326",
    "addr:postcode":"45600",
    "addr:street":"Avda Francisco Aguirre",
    "iso:country":"ES",
    "sg:address":"Avda Francisco Aguirre, 326",
    "sg:city":"Talavera Reina",
    "sg:orig_category":"Limpieza Con Chorro De Arena Y Con Granalla, Pulido",
    "sg:phone":"+34 925 82 53 24",
    "sg:postcode":"45600",
    "sg:province":"Toledo",
    "wof:name":"Pulimentos Ruiz Y Granados S.l.",
    "wof:placetype":"venue"
},
  "geometry": {"coordinates":[-4.8408689499,39.9633293152],"type":"Point"}
}