{
  "type": "Feature",
  "properties": {
    "addr:full":"Avgd Alfons Xiii, 476 Badalona Barcelona 08913",
    "addr:housenumber":"476",
    "addr:postcode":"08913",
    "addr:street":"Alfons Xiii",
    "iso:country":"ES",
    "sg:address":"Avgd Alfons Xiii, 476",
    "sg:city":"Badalona",
    "sg:orig_category":"Dietistas",
    "sg:phone":"+34 933 87 42 99",
    "sg:postcode":"08913",
    "sg:province":"Barcelona",
    "wof:name":"Relat Vidal Jordi",
    "wof:placetype":"venue"
},
  "geometry": {"coordinates":[2.2217450142,41.4361534119],"type":"Point"}
}