{
  "type": "Feature",
  "properties": {
    "iso:country":"ES",
    "sg:address":"Calle de Estacion, 9",
    "sg:city":"Molina Segura",
    "sg:orig_category":"Perfumer\u00cda (al Por Menor)",
    "sg:phone":"+34 968 61 37 93",
    "sg:postcode":"30500",
    "sg:province":"Murcia",
    "wof:name":"Perfumerias Gala S.l.",
    "wof:placetype":"venue"
},
  "geometry": {"coordinates":[-1.2129559517,38.0535621643],"type":"Point"}
}