{
  "type": "Feature",
  "properties": {
    "addr:full":"Barr Zurbaranbarri, 42 Bilbao Vizcaya 48007",
    "addr:housenumber":"42",
    "addr:postcode":"48007",
    "addr:street":"Zurbaranbarri",
    "iso:country":"ES",
    "sg:address":"Barr Zurbaranbarri, 42",
    "sg:city":"Bilbao",
    "sg:orig_category":"Contenedores (mercanc\u00cdas)",
    "sg:phone":"+34 944 46 16 48",
    "sg:postcode":"48007",
    "sg:province":"Vizcaya",
    "wof:name":"Llamazares Viejo Perfecta",
    "wof:placetype":"venue"
},
  "geometry": {"coordinates":[-2.910779953,43.2652397156],"type":"Point"}
}