{
  "type": "Feature",
  "properties": {
    "addr:full":"Calle de Pablo Picasso, 25 Gijon Asturias 33210",
    "addr:housenumber":"25",
    "addr:postcode":"33210",
    "addr:street":"Calle De Pablo Picasso",
    "iso:country":"ES",
    "sg:address":"Calle de Pablo Picasso, 25",
    "sg:city":"Gijon",
    "sg:orig_category":"Mec\u00c1nico Del Autom\u00d3vil",
    "sg:phone":"+34 985 16 17 15",
    "sg:postcode":"33210",
    "sg:province":"Asturias",
    "wof:name":"Talleres Macanicos Picasso C.b",
    "wof:placetype":"venue"
},
  "geometry": {"coordinates":[-5.6765055656,43.5246582031],"type":"Point"}
}