{
  "type": "Feature",
  "properties": {
    "addr:full":"Calle de Cruz De Santa Ana, 7 Plasencia C\u00e1ceres 10600",
    "addr:housenumber":"7",
    "addr:postcode":"10600",
    "addr:street":"Calle De Cruz De Santa Ana;Ca\u0301Ceres",
    "iso:country":"ES",
    "sg:address":"Calle de Cruz De Santa Ana, 7",
    "sg:city":"Plasencia",
    "sg:orig_category":"Tiendas De Grano, Frutas Y Legumbres Secas (al Por Menor)",
    "sg:phone":"+34 927 41 92 54",
    "sg:postcode":"10600",
    "sg:province":"C\u00e1ceres",
    "wof:name":"Awad Nasra Suzan",
    "wof:placetype":"venue"
},
  "geometry": {"coordinates":[-6.0880589485,40.031539917],"type":"Point"}
}