{
  "type": "Feature",
  "properties": {
    "addr:full":"Calle de Mendizabal, 125 Almansa Albacete 02640",
    "addr:housenumber":"125",
    "addr:postcode":"02640",
    "addr:street":"Calle De Mendizabal",
    "iso:country":"ES",
    "sg:address":"Calle de Mendizabal, 125",
    "sg:city":"Almansa",
    "sg:orig_category":"Cajas Y Embalajes De Cart\u00d3n Y Papel",
    "sg:phone":"+34 967 34 05 90",
    "sg:postcode":"02640",
    "sg:province":"Albacete",
    "wof:name":"Amadeo Sanchez Sociedad Limitada.",
    "wof:placetype":"venue"
},
  "geometry": {"coordinates":[-1.101827383,38.8694419861],"type":"Point"}
}