{
  "type": "Feature",
  "properties": {
    "iso:country":"ES",
    "sg:address":"Dos(polig. Ind.), S/n",
    "sg:city":"Massanassa",
    "sg:orig_category":"Abrasivos Y Superabrasivos (fabricaci\u00d3n, Al Por Mayor)",
    "sg:phone":"+34 961 25 31 26",
    "sg:postcode":"46470",
    "sg:province":"Valencia",
    "wof:name":"Abrasivos Valencia S.l.",
    "wof:placetype":"venue"
},
  "geometry": {"coordinates":[-0.400201,39.411301],"type":"Point"}
}