{
  "type": "Feature",
  "properties": {
    "iso:country":"ES",
    "sg:address":"Calle de Serrano, 30",
    "sg:city":"S. Pedro Pinatar",
    "sg:classifiers":[
        {
            "category":"Taxi",
            "type":"Transportation"
        }
    ],
    "sg:phone":"+34 968 18 08 08",
    "sg:postcode":"30740",
    "sg:province":"Murcia",
    "wof:name":"Gomez Garcia Manuel",
    "wof:placetype":"venue"
},
  "geometry": {"coordinates":[-0.7916989923,37.832988739],"type":"Point"}
}