{
  "type": "Feature",
  "properties": {
    "addr:full":"Carrer de Nou, 202 Torello Barcelona 08570",
    "addr:housenumber":"202",
    "addr:postcode":"08570",
    "addr:street":"Carrer De Nou",
    "iso:country":"ES",
    "sg:address":"Carrer de Nou, 202",
    "sg:city":"Torello",
    "sg:orig_category":"Lavado, Limpieza De Veh\u00cdculos",
    "sg:phone":"+34 938 59 25 02",
    "sg:postcode":"08570",
    "sg:province":"Barcelona",
    "wof:name":"Crosas Puigvi Jose",
    "wof:placetype":"venue"
},
  "geometry": {"coordinates":[2.2709898949,42.0419616699],"type":"Point"}
}