{
  "type": "Feature",
  "properties": {
    "iso:country":"ES",
    "sg:address":"Carrer de Major, 28",
    "sg:city":"Sitges",
    "sg:orig_category":"Ropa Para Se\u00d1oras Y Caballeros (al Por Menor)",
    "sg:phone":"+34 938 11 32 29",
    "sg:postcode":"08870",
    "sg:province":"Barcelona",
    "wof:name":"Elegants People S.l.l.",
    "wof:placetype":"venue"
},
  "geometry": {"coordinates":[1.8106689453,41.2362098694],"type":"Point"}
}