{
  "type": "Feature",
  "properties": {
    "addr:full":"Calle de Trafalgar, 16 Madrid Madrid 28010",
    "addr:housenumber":"16",
    "addr:postcode":"madrid;28010",
    "addr:street":"Calle De Trafalgar",
    "iso:country":"ES",
    "sg:address":"Calle de Trafalgar, 16",
    "sg:city":"Madrid",
    "sg:orig_category":"Inmobiliaria (agencias)",
    "sg:phone":"+34 914 46 17 37",
    "sg:postcode":"28010",
    "sg:province":"Madrid",
    "wof:name":"Madridmaria",
    "wof:placetype":"venue"
},
  "geometry": {"coordinates":[-3.700304985,40.4315452576],"type":"Point"}
}