{
  "type": "Feature",
  "properties": {
    "addr:full":"Calle de Bateria De San Juan, 26 Palmas De Gran Canaria Las Palmas 35015",
    "addr:housenumber":"26",
    "addr:postcode":"35015",
    "addr:street":"Calle De Bateria;San Juan",
    "iso:country":"ES",
    "sg:address":"Calle de Bateria De San Juan, 26",
    "sg:city":"Palmas De Gran Canaria",
    "sg:orig_category":"Panader\u00cdas, Panader\u00cdas",
    "sg:phone":"+34 928 33 72 76",
    "sg:postcode":"35015",
    "sg:province":"Las Palmas",
    "wof:name":"Suarez Santana Pablo",
    "wof:placetype":"venue"
},
  "geometry": {"coordinates":[-15.4211444855,28.0956096649],"type":"Point"}
}