{
  "type": "Feature",
  "properties": {
    "addr:full":"Pase Chopera (de La), 160 Alcobendas Madrid 28100",
    "addr:housenumber":"160",
    "addr:postcode":"28100",
    "addr:street":"Alcobendas",
    "iso:country":"ES",
    "sg:address":"Pase Chopera (de La), 160",
    "sg:city":"Alcobendas",
    "sg:orig_category":"Sociedades, Compa\u00d1\u00cdas Aseguradoras",
    "sg:phone":"+34 914 90 11 72",
    "sg:postcode":"28100",
    "sg:province":"Madrid",
    "sg:website":"www.mapfre.com",
    "wof:name":"Mapfre Servicios De Informatica S.a.",
    "wof:placetype":"venue"
},
  "geometry": {"coordinates":[-3.6552529335,40.5451316833],"type":"Point"}
}