{
  "type": "Feature",
  "properties": {
    "iso:country":"ES",
    "sg:address":"Calle de Fueros, 1",
    "sg:city":"Irun",
    "sg:orig_category":"Abogados",
    "sg:phone":"+34 943 62 36 24",
    "sg:postcode":"20302",
    "sg:province":"Guip\u00f9zcoa",
    "wof:name":"Giron Alonso Cristina",
    "wof:placetype":"venue"
},
  "geometry": {"coordinates":[-1.7900203466,43.3383331299],"type":"Point"}
}