{
  "type": "Feature",
  "properties": {
    "addr:full":"Calle de Lope De Vega, 4 Alginet Valencia 46230",
    "addr:housenumber":"4",
    "addr:postcode":"46230",
    "addr:street":"Calle De Lope De Vega",
    "iso:country":"ES",
    "sg:address":"Calle de Lope De Vega, 4",
    "sg:city":"Alginet",
    "sg:orig_category":"Organizaciones Profesionales",
    "sg:phone":"+34 961 75 42 94",
    "sg:postcode":"46230",
    "sg:province":"Valencia",
    "wof:name":"Sanchis Asins Ramon",
    "wof:placetype":"venue"
},
  "geometry": {"coordinates":[-0.4669750035,39.2673072815],"type":"Point"}
}