{
  "type": "Feature",
  "properties": {
    "iso:country":"ES",
    "sg:address":"Rua Cruz Gallastegui, 16",
    "sg:city":"Pontevedra",
    "sg:orig_category":"Perfumer\u00cda (al Por Menor)",
    "sg:phone":"+34 986 84 71 44",
    "sg:postcode":"36001",
    "sg:province":"Pontevedra",
    "wof:name":"Asoral Cosmeticos S.l.",
    "wof:placetype":"venue"
},
  "geometry": {"coordinates":[-8.6397790909,42.4292526245],"type":"Point"}
}