{
  "type": "Feature",
  "properties": {
    "iso:country":"ES",
    "sg:address":"Pl Major, 12",
    "sg:city":"Vic",
    "sg:orig_category":"Librer\u00cdas",
    "sg:phone":"+34 938 86 00 79",
    "sg:postcode":"08500",
    "sg:province":"Barcelona",
    "wof:name":"Anglada Solanelles Llucia",
    "wof:placetype":"venue"
},
  "geometry": {"coordinates":[2.2538163662,41.9303207397],"type":"Point"}
}