{
  "type": "Feature",
  "properties": {
    "iso:country":"ES",
    "sg:address":"Avda Del Mediterrani, 33",
    "sg:city":"Onda",
    "sg:orig_category":"Mec\u00c1nico Del Autom\u00d3vil",
    "sg:phone":"+34 964 60 11 71",
    "sg:postcode":"12200",
    "sg:province":"Castell\u00f3n",
    "wof:name":"Talleres Auto-onda S.l.",
    "wof:placetype":"venue"
},
  "geometry": {"coordinates":[-0.2024990022,39.9556541443],"type":"Point"}
}