{
  "type": "Feature",
  "properties": {
    "iso:country":"ES",
    "sg:address":"Calle de Pinto, S/n",
    "sg:city":"Parla",
    "sg:orig_category":"Ropa Para Ni\u00d1os (al Por Menor)",
    "sg:phone":"+34 916 99 08 96",
    "sg:postcode":"28980",
    "sg:province":"Madrid",
    "sg:website":"www.torero.com",
    "wof:name":"Edeljua Medelma S.l.",
    "wof:placetype":"venue"
},
  "geometry": {"coordinates":[-3.7651889324,40.2395362854],"type":"Point"}
}