{
  "type": "Feature",
  "properties": {
    "iso:country":"ES",
    "sg:address":"Carrer de Gaiter Del Llobregat (lo), 97",
    "sg:city":"Prat Llobregat",
    "sg:orig_category":"Art\u00cdculos De Decoraci\u00d3n",
    "sg:phone":"+34 934 78 75 18",
    "sg:postcode":"08820",
    "sg:province":"Barcelona",
    "wof:name":"Diaz Pozas Antonio",
    "wof:placetype":"venue"
},
  "geometry": {"coordinates":[2.0989398956,41.3297996521],"type":"Point"}
}