{
  "type": "Feature",
  "properties": {
    "iso:country":"ES",
    "sg:address":"Carrer de Hercegovina, 24",
    "sg:city":"Barcelona",
    "sg:orig_category":"Molduras, Junquillos, Listones Y Molduras Perforadas",
    "sg:phone":"+34 932 09 69 12",
    "sg:postcode":"08006",
    "sg:province":"Barcelona",
    "wof:name":"Badia Ciurana Miguel",
    "wof:placetype":"venue"
},
  "geometry": {"coordinates":[2.1399390697,41.4029502869],"type":"Point"}
}