{
  "type": "Feature",
  "properties": {
    "addr:full":"Carrer de Professor Barraquer, 24 Esplugues Llobregat Barcelona 08950",
    "addr:housenumber":"24",
    "addr:postcode":"08950",
    "addr:street":"Carrer De Professor Barraquer",
    "iso:country":"ES",
    "sg:address":"Carrer de Professor Barraquer, 24",
    "sg:city":"Esplugues Llobregat",
    "sg:orig_category":"Centros De Coordinaci\u00d3n",
    "sg:phone":"+34 934 70 00 52",
    "sg:postcode":"08950",
    "sg:province":"Barcelona",
    "wof:name":"Felip Garcia Associats S.l.",
    "wof:placetype":"venue"
},
  "geometry": {"coordinates":[2.0975699425,41.3851509094],"type":"Point"}
}