{
  "type": "Feature",
  "properties": {
    "iso:country":"ES",
    "sg:address":"Calle de San Antonio, 43",
    "sg:city":"Vitoria-gasteiz",
    "sg:orig_category":"Internados & Ense\u00d1anza Privada",
    "sg:phone":"+34 945 23 07 80",
    "sg:postcode":"01005",
    "sg:province":"\u00c1lava",
    "wof:name":"Centro De Formacion Profesional Bermar S.l.",
    "wof:placetype":"venue"
},
  "geometry": {"coordinates":[-2.6743049622,42.8418197632],"type":"Point"}
}