{
  "type": "Feature",
  "properties": {
    "iso:country":"ES",
    "sg:address":"Calle de General Ricardos, 179",
    "sg:city":"Madrid",
    "sg:orig_category":"Ense\u00d1anza, Formaci\u00d3n Profesional: Aprendizaje",
    "sg:phone":"+34 914 22 00 82",
    "sg:postcode":"28025",
    "sg:province":"Madrid",
    "wof:name":"Comunidad Autonoma De Madrid-centros De Educacion",
    "wof:placetype":"venue"
},
  "geometry": {"coordinates":[-3.741091013,40.3833961487],"type":"Point"}
}