{
  "type": "Feature",
  "properties": {
    "addr:full":"Calle de Corona, 7 Valencia Valencia 46003",
    "addr:housenumber":"7",
    "addr:postcode":"46003",
    "addr:street":"Calle De Corona",
    "iso:country":"ES",
    "sg:address":"Calle de Corona, 7",
    "sg:city":"Valencia",
    "sg:orig_category":"Restaurantes",
    "sg:phone":"+34 963 92 63 36",
    "sg:postcode":"46003",
    "sg:province":"Valencia",
    "wof:name":"Tasca Corona 7 S.l.",
    "wof:placetype":"venue"
},
  "geometry": {"coordinates":[-0.3811734915,39.477771759],"type":"Point"}
}