{
  "type": "Feature",
  "properties": {
    "addr:full":"Ctra. Cilleros, Km. 0000,3 Moraleja C\u00e1ceres 10840",
    "addr:postcode":"10840",
    "addr:street":"Ctra. Cilleros Km. 0000,3",
    "iso:country":"ES",
    "sg:address":"Ctra. Cilleros, Km. 0000,3",
    "sg:city":"Moraleja",
    "sg:orig_category":"Cerrajer\u00cda, Ferrallista",
    "sg:phone":"+34 927 51 63 06",
    "sg:postcode":"10840",
    "sg:province":"C\u00e1ceres",
    "wof:name":"Salvado Rodriguez Andidio",
    "wof:placetype":"venue"
},
  "geometry": {"coordinates":[-6.6580691338,40.0709648132],"type":"Point"}
}