{
  "type": "Feature",
  "properties": {
    "iso:country":"ES",
    "sg:address":"Ergobia Pasealekua, 3",
    "sg:city":"Astigarraga",
    "sg:orig_category":"Electrodom\u00c9sticos (al Por Menor)",
    "sg:phone":"+34 943 33 11 40",
    "sg:postcode":"20115",
    "sg:province":"Guip\u00f9zcoa",
    "wof:name":"Olaso Zumeaga Jose Luis",
    "wof:placetype":"venue"
},
  "geometry": {"coordinates":[-1.9534130096,43.2776947021],"type":"Point"}
}