{
  "type": "Feature",
  "properties": {
    "iso:country":"ES",
    "sg:address":"C/ Alacant, D', 18",
    "sg:city":"S. Antoni Portmany",
    "sg:orig_category":"Agentes, Concesionarios Y Sucursales De Veh\u00cdculos",
    "sg:phone":"+34 971 34 04 11",
    "sg:postcode":"07820",
    "sg:province":"Islas Baleares",
    "wof:name":"Frare Motor S.l.",
    "wof:placetype":"venue"
},
  "geometry": {"coordinates":[2.9117100239,39.6136398315],"type":"Point"}
}