{
  "type": "Feature",
  "properties": {
    "addr:full":"Plg Indust Pp Iv, 25 Manzanares Ciudad Real 13200",
    "addr:postcode":"13200",
    "iso:country":"ES",
    "sg:address":"Plg Indust Pp Iv, 25",
    "sg:city":"Manzanares",
    "sg:orig_category":"Negocio De Materiales De Construcci\u00d3n",
    "sg:phone":"+34 926 61 22 38",
    "sg:postcode":"13200",
    "sg:province":"Ciudad Real",
    "wof:name":"Bola\u00f1os Lozano S.l.",
    "wof:placetype":"venue"
},
  "geometry": {"coordinates":[-3.373128891,38.994140625],"type":"Point"}
}