{
  "type": "Feature",
  "properties": {
    "iso:country":"ES",
    "sg:address":"Avda Badajoz, 62",
    "sg:city":"San Vicente Alcantara",
    "sg:orig_category":"Cl\u00cdnicas M\u00c9dicas",
    "sg:phone":"+34 924 41 12 29",
    "sg:postcode":"06500",
    "sg:province":"Badajoz",
    "sg:website":"www.centromedicosantajovita.com",
    "wof:name":"Centro Medico Santa Jovita S.l.",
    "wof:placetype":"venue"
},
  "geometry": {"coordinates":[-7.1347851753,39.3631896973],"type":"Point"}
}