{
  "type": "Feature",
  "properties": {
    "iso:country":"ES",
    "sg:address":"Carrer de Anselm Clave, 21",
    "sg:city":"Santa Perpetua De Mogoda",
    "sg:orig_category":"Electricidad (montaje, Ensamblaje De Componentes)",
    "sg:phone":"+34 935 60 39 52",
    "sg:postcode":"08130",
    "sg:province":"Barcelona",
    "wof:name":"Amores Carrillo Raquel",
    "wof:placetype":"venue"
},
  "geometry": {"coordinates":[2.1770410538,41.5346069336],"type":"Point"}
}