{
  "type": "Feature",
  "properties": {
    "iso:country":"ES",
    "sg:address":"Av Generalitat, 101",
    "sg:city":"Viladecans",
    "sg:orig_category":"Asociaciones Y Clubs Deportivos",
    "sg:phone":"+34 936 37 83 34",
    "sg:postcode":"08840",
    "sg:province":"Barcelona",
    "wof:name":"Larrosa Cazorla Marcos",
    "wof:placetype":"venue"
},
  "geometry": {"coordinates":[2.0183401108,41.3131408691],"type":"Point"}
}