{
  "type": "Feature",
  "properties": {
    "addr:full":"Calle de Garcilaso De La Vega, 1 Zaragoza Zaragoza 50017",
    "addr:housenumber":"1",
    "addr:postcode":"50017",
    "addr:street":"Calle De Garcilaso De La Vega",
    "iso:country":"ES",
    "sg:address":"Calle de Garcilaso De La Vega, 1",
    "sg:city":"Zaragoza",
    "sg:orig_category":"Zapatos (al Por Menor)",
    "sg:phone":"+34 976 46 05 33",
    "sg:postcode":"50017",
    "sg:province":"Zaragoza",
    "wof:name":"Khafor Sport 2000 S.l",
    "wof:placetype":"venue"
},
  "geometry": {"coordinates":[-0.9127719998,41.6516952515],"type":"Point"}
}