{
  "type": "Feature",
  "properties": {
    "addr:full":"Calle de Jazmin, 38 Madrid Madrid 28033",
    "addr:housenumber":"38",
    "addr:postcode":"madrid;28033",
    "addr:street":"Calle De Jazmin",
    "iso:country":"ES",
    "sg:address":"Calle de Jazmin, 38",
    "sg:city":"Madrid",
    "sg:orig_category":"Empresas De Portes Y Mensajer\u00cda",
    "sg:phone":"+34 913 83 46 30",
    "sg:postcode":"28033",
    "sg:province":"Madrid",
    "wof:name":"Mensanor 33 S.l.",
    "wof:placetype":"venue"
},
  "geometry": {"coordinates":[-3.6669108868,40.4784965515],"type":"Point"}
}