{
  "type": "Feature",
  "properties": {
    "addr:full":"Calle de Pablo Penaguilas, 171 Palmas De Gran Canaria Las Palmas 35012",
    "addr:housenumber":"171",
    "addr:postcode":"35012",
    "addr:street":"Calle De Pablo Penaguilas",
    "iso:country":"ES",
    "sg:address":"Calle de Pablo Penaguilas, 171",
    "sg:city":"Palmas De Gran Canaria",
    "sg:orig_category":"Negocio De Materiales De Construcci\u00d3n",
    "sg:phone":"+34 928 20 93 89",
    "sg:postcode":"35012",
    "sg:province":"Las Palmas",
    "wof:name":"Rovira Penichet Jose Luis",
    "wof:placetype":"venue"
},
  "geometry": {"coordinates":[-15.43800354,28.1088581085],"type":"Point"}
}