{
  "type": "Feature",
  "properties": {
    "iso:country":"ES",
    "sg:address":"Rua Rio Sil, 7",
    "sg:city":"Lugo",
    "sg:orig_category":"Ingeniero",
    "sg:phone":"+34 982 23 08 06",
    "sg:postcode":"27003",
    "sg:province":"Lugo",
    "wof:name":"Luvesa S. L.",
    "wof:placetype":"venue"
},
  "geometry": {"coordinates":[-7.5562229156,43.0161552429],"type":"Point"}
}