{
  "type": "Feature",
  "properties": {
    "iso:country":"ES",
    "sg:address":"San Silvestre, S/n",
    "sg:city":"Ayamonte",
    "sg:orig_category":"Comercio, Reparaci\u00d3n De Motocicletas, Bicicletas Y Piezas Sueltas",
    "sg:phone":"+34 959 47 16 91",
    "sg:postcode":"21400",
    "sg:province":"Huelva",
    "wof:name":"Moreno Abreu Juan Esteban",
    "wof:placetype":"venue"
},
  "geometry": {"coordinates":[-7.4060988426,37.208480835],"type":"Point"}
}