{
  "type": "Feature",
  "properties": {
    "iso:country":"ES",
    "sg:address":"Avda Zaragoza, 81",
    "sg:city":"Utebo",
    "sg:orig_category":"Inmobiliaria (agencias)",
    "sg:phone":"+34 976 78 55 89",
    "sg:postcode":"50180",
    "sg:province":"Zaragoza",
    "wof:name":"Anves De Inversiones S.l.",
    "wof:placetype":"venue"
},
  "geometry": {"coordinates":[-0.9997010231,41.7035179138],"type":"Point"}
}