{
  "type": "Feature",
  "properties": {
    "iso:country":"ES",
    "sg:address":"Calle de Marques De Dos Aguas, 5",
    "sg:city":"Valencia",
    "sg:orig_category":"Abogados",
    "sg:phone":"+34 963 52 47 50",
    "sg:postcode":"46002",
    "sg:province":"Valencia",
    "wof:name":"Ineba Sevil Antonio",
    "wof:placetype":"venue"
},
  "geometry": {"coordinates":[-0.3742170036,39.4730300903],"type":"Point"}
}