{
  "type": "Feature",
  "properties": {
    "addr:full":"Calle de Pozo, 35 Moraleja Vino Zamora 49150",
    "addr:housenumber":"35",
    "addr:postcode":"49150",
    "addr:street":"Calle De Pozo;Zamora",
    "iso:country":"ES",
    "sg:address":"Calle de Pozo, 35",
    "sg:city":"Moraleja Vino",
    "sg:orig_category":"Asociaciones Ecologistas",
    "sg:phone":"+34 980 57 19 84",
    "sg:postcode":"49150",
    "sg:province":"Zamora",
    "wof:name":"Comunidad De Regantes Virgen Del Aviso",
    "wof:placetype":"venue"
},
  "geometry": {"coordinates":[-5.6580519676,41.4647026062],"type":"Point"}
}