{
  "type": "Feature",
  "properties": {
    "addr:full":"C. Castillo, 15 Moron Frontera Sevilla 41530",
    "addr:housenumber":"15",
    "addr:postcode":"41530",
    "addr:street":"C. Castillo",
    "iso:country":"ES",
    "sg:address":"C. Castillo, 15",
    "sg:city":"Moron Frontera",
    "sg:orig_category":"Cajas De Ahorro",
    "sg:phone":"+34 954 85 10 34",
    "sg:postcode":"41530",
    "sg:province":"Sevilla",
    "sg:website":"www.unicaja.es",
    "wof:name":"Unicaja",
    "wof:placetype":"venue"
},
  "geometry": {"coordinates":[-5.44734478,37.1324615479],"type":"Point"}
}