{
  "type": "Feature",
  "properties": {
    "addr:full":"Calle de San Torcuato, 38 Zamora Zamora 49014",
    "addr:housenumber":"38",
    "addr:postcode":"49014",
    "addr:street":"Calle De San Torcuato",
    "iso:country":"ES",
    "sg:address":"Calle de San Torcuato, 38",
    "sg:city":"Zamora",
    "sg:orig_category":"Estilistas Y Estudios De Estilo De Corte Y Confecci\u00d3n",
    "sg:phone":"+34 980 53 62 77",
    "sg:postcode":"49014",
    "sg:province":"Zamora",
    "wof:name":"Confecciones Cardigan S.a.",
    "wof:placetype":"venue"
},
  "geometry": {"coordinates":[-5.7437491417,41.5068206787],"type":"Point"}
}