{
  "type": "Feature",
  "properties": {
    "addr:full":"Pintor Pedro Flores, 10 Murcia Murcia 30002",
    "addr:housenumber":"10",
    "addr:postcode":"30002",
    "addr:street":"Pintor Pedro Flores",
    "iso:country":"ES",
    "sg:address":"Pintor Pedro Flores, 10",
    "sg:city":"Murcia",
    "sg:orig_category":"Herramientas Manuales (fabricaci\u00d3n, Al Por Mayor)",
    "sg:phone":"+34 968 34 52 92",
    "sg:postcode":"30002",
    "sg:province":"Murcia",
    "wof:name":"Stanley Iberia S.l.",
    "wof:placetype":"venue"
},
  "geometry": {"coordinates":[-1.1270400286,37.9754371643],"type":"Point"}
}