{
  "type": "Feature",
  "properties": {
    "iso:country":"ES",
    "sg:address":"Calle de Cid, 19",
    "sg:city":"Bu\u00f1ol",
    "sg:orig_category":"Partidos Pol\u00cdticos",
    "sg:phone":"+34 962 50 17 67",
    "sg:postcode":"46360",
    "sg:province":"Valencia",
    "wof:name":"Partido Socialista Obrero Espa\u00f1ol",
    "wof:placetype":"venue"
},
  "geometry": {"coordinates":[-0.7906736135,39.4181518555],"type":"Point"}
}