{
  "type": "Feature",
  "properties": {
    "iso:country":"ES",
    "sg:address":"Calle de Cesareo Marco Yague, 20",
    "sg:city":"Utiel",
    "sg:orig_category":"Fotograf\u00cda Y Cine: Aparatos, Pel\u00cdculas Y Accesorios (fabricaci\u00d3n, Al Por Mayor)",
    "sg:phone":"+34 962 17 43 99",
    "sg:postcode":"46300",
    "sg:province":"Valencia",
    "wof:name":"Abdelrahman Musa Mazuz",
    "wof:placetype":"venue"
},
  "geometry": {"coordinates":[-1.231362,39.624668],"type":"Point"}
}