{
  "type": "Feature",
  "properties": {
    "iso:country":"ES",
    "sg:address":"Calle de Jose Latorre, 1",
    "sg:city":"Caspe",
    "sg:orig_category":"Ludotecas",
    "sg:phone":"+34 976 63 32 05",
    "sg:postcode":"50700",
    "sg:province":"Zaragoza",
    "wof:name":"Metronet S.c",
    "wof:placetype":"venue"
},
  "geometry": {"coordinates":[-0.0438840017,41.2381248474],"type":"Point"}
}