{
  "type": "Feature",
  "properties": {
    "iso:country":"ES",
    "sg:address":"Calle de Porvera, 61",
    "sg:city":"Jerez De La Frontera",
    "sg:orig_category":"Loter\u00cda Y T\u00d3mbola",
    "sg:phone":"+34 956 33 10 09",
    "sg:postcode":"11403",
    "sg:province":"C\u00e1diz",
    "wof:name":"Mera Ferrer Josefa",
    "wof:placetype":"venue"
},
  "geometry": {"coordinates":[-6.1409091949,36.6883583069],"type":"Point"}
}