{
  "type": "Feature",
  "properties": {
    "iso:country":"ES",
    "sg:address":"Calle de Casado Del Alisal, 24",
    "sg:city":"Huesca",
    "sg:orig_category":"Bazares, Art\u00cdculos De Limpieza Y De Cocina (al Por Menor)",
    "sg:phone":"+34 974 24 55 91",
    "sg:postcode":"22005",
    "sg:province":"Huesca",
    "wof:name":"Bartolome Menendez Antonio",
    "wof:placetype":"venue"
},
  "geometry": {"coordinates":[-0.4059019983,42.1318435669],"type":"Point"}
}