{
  "type": "Feature",
  "properties": {
    "iso:country":"ES",
    "sg:address":"Calle de San Bernardo, 19",
    "sg:city":"Vista Alegre",
    "sg:orig_category":"Farmacias",
    "sg:phone":"+34 968 52 82 68",
    "sg:postcode":"30392",
    "sg:province":"Murcia",
    "wof:name":"Martinez Martinez Lucia",
    "wof:placetype":"venue"
},
  "geometry": {"coordinates":[-0.9430549741,37.607837677],"type":"Point"}
}