{
  "type": "Feature",
  "properties": {
    "addr:full":"Calle de Monachil, 4 Peligros Granada 18210",
    "addr:housenumber":"4",
    "addr:postcode":"18210",
    "addr:street":"Calle De Monachil",
    "iso:country":"ES",
    "sg:address":"Calle de Monachil, 4",
    "sg:city":"Peligros",
    "sg:orig_category":"Pintura, Barniz, Productos Asimilables (fabricaci\u00d3n, Al Por Mayor)",
    "sg:phone":"+34 958 29 39 80",
    "sg:postcode":"18210",
    "sg:province":"Granada",
    "wof:name":"Auto Paint's S.l.",
    "wof:placetype":"venue"
},
  "geometry": {"coordinates":[-3.6276938915,37.2295036316],"type":"Point"}
}