{
  "type": "Feature",
  "properties": {
    "addr:full":"Calle de Carretera, 2 Martin Del Rio Teruel 44750",
    "addr:housenumber":"2",
    "addr:postcode":"44750",
    "addr:street":"Calle De Carretera",
    "iso:country":"ES",
    "sg:address":"Calle de Carretera, 2",
    "sg:city":"Martin Del Rio",
    "sg:orig_category":"Arenas, Guijarros Y Granulados",
    "sg:phone":"+34 978 75 03 27",
    "sg:postcode":"44750",
    "sg:province":"Teruel",
    "wof:name":"Aridos Y Transportes Azuara Mallen S.l.",
    "wof:placetype":"venue"
},
  "geometry": {"coordinates":[-0.8962503076,40.8437423706],"type":"Point"}
}