{
  "type": "Feature",
  "properties": {
    "iso:country":"ES",
    "sg:address":"Calle de Fuente De La Puchera, S/n",
    "sg:city":"Jarandilla Vera",
    "sg:orig_category":"Granos Y Forrajes",
    "sg:phone":"+34 927 56 00 16",
    "sg:postcode":"10450",
    "sg:province":"C\u00e1ceres",
    "wof:name":"Jara Servicios Agroforestales Sl",
    "wof:placetype":"venue"
},
  "geometry": {"coordinates":[-5.6633038521,40.1293830872],"type":"Point"}
}