{
  "type": "Feature",
  "properties": {
    "addr:full":"Calle de Principe, 8 San Javier Murcia 30730",
    "addr:housenumber":"8",
    "addr:postcode":"30730",
    "addr:street":"Calle De Principe",
    "iso:country":"ES",
    "sg:address":"Calle de Principe, 8",
    "sg:city":"San Javier",
    "sg:orig_category":"Albergues",
    "sg:phone":"+34 968 57 29 01",
    "sg:postcode":"30730",
    "sg:province":"Murcia",
    "wof:name":"Nenico Cb",
    "wof:placetype":"venue"
},
  "geometry": {"coordinates":[-0.8340079784,37.8066101074],"type":"Point"}
}