{
  "type": "Feature",
  "properties": {
    "addr:full":"C/ Convent, 37 Llucmajor Islas Baleares 07620",
    "addr:housenumber":"37",
    "addr:postcode":"07620",
    "addr:street":"C / Convent",
    "iso:country":"ES",
    "sg:address":"C/ Convent, 37",
    "sg:city":"Llucmajor",
    "sg:orig_category":"Transportes Por Carretera: Lotes Completos, Mercanc\u00cdas Diversas",
    "sg:phone":"+34 971 66 03 91",
    "sg:postcode":"07620",
    "sg:province":"Islas Baleares",
    "wof:name":"Cristalflor S.l.",
    "wof:placetype":"venue"
},
  "geometry": {"coordinates":[2.8937499523,39.4900436401],"type":"Point"}
}