{
  "type": "Feature",
  "properties": {
    "addr:full":"Calle de Camino Viejo, 1 Fontiveros \u00c1vila 05310",
    "addr:housenumber":"1",
    "addr:postcode":"05310",
    "addr:street":"Calle De Camino Viejo;A\u0301Vila",
    "iso:country":"ES",
    "sg:address":"Calle de Camino Viejo, 1",
    "sg:city":"Fontiveros",
    "sg:orig_category":"Sanatorios M\u00c9dico",
    "sg:phone":"+34 920 24 50 06",
    "sg:postcode":"05310",
    "sg:province":"\u00c1vila",
    "wof:name":"Gerencia De Atencion Primaria De Avila",
    "wof:placetype":"venue"
},
  "geometry": {"coordinates":[-4.9608778954,40.926612854],"type":"Point"}
}