{
  "type": "Feature",
  "properties": {
    "iso:country":"ES",
    "sg:address":"Plaz Nuestra Se\u00d1ora De Vico, 11",
    "sg:city":"Arnedo",
    "sg:orig_category":"Agencias De Viajes",
    "sg:phone":"+34 941 38 41 00",
    "sg:postcode":"26580",
    "sg:province":"La Rioja",
    "sg:website":"www.travelrioja.com",
    "wof:name":"Travel Rioja S.a.",
    "wof:placetype":"venue"
},
  "geometry": {"coordinates":[-2.1004989147,42.2278594971],"type":"Point"}
}