{
  "type": "Feature",
  "properties": {
    "iso:country":"ES",
    "sg:address":"Carr Cases Noves, 105",
    "sg:city":"Palafrugell",
    "sg:orig_category":"Venta, Instalaci\u00d3n, Mantenimiento De Chimeneas De Interior Y Accesorios",
    "sg:phone":"+34 972 30 00 91",
    "sg:postcode":"17200",
    "sg:province":"Girona",
    "wof:name":"Ferro I Foc Stil S.l.",
    "wof:placetype":"venue"
},
  "geometry": {"coordinates":[3.1597599983,41.9181594849],"type":"Point"}
}