{
  "type": "Feature",
  "properties": {
    "addr:full":"Carr Sant Isidre, 3 Pu\u00e7ol Valencia 46530",
    "addr:housenumber":"3",
    "addr:postcode":"46530",
    "addr:street":"Carr Sant Isidre",
    "iso:country":"ES",
    "sg:address":"Carr Sant Isidre, 3",
    "sg:city":"Pu\u00e7ol",
    "sg:orig_category":"Supermercados Y Hipermercados",
    "sg:phone":"+34 961 46 47 04",
    "sg:postcode":"46530",
    "sg:province":"Valencia",
    "sg:website":"www.mercadona.es",
    "wof:name":"Mercadona S.a.",
    "wof:placetype":"venue"
},
  "geometry": {"coordinates":[-0.3008790016,39.6156044006],"type":"Point"}
}