{
  "type": "Feature",
  "properties": {
    "iso:country":"ES",
    "sg:address":"Infantes De Lara, 6",
    "sg:city":"Salas Infantes",
    "sg:orig_category":"Empresas De Carpinter\u00cda",
    "sg:phone":"+34 947 38 09 15",
    "sg:postcode":"09600",
    "sg:province":"Burgos",
    "wof:name":"Vicente Benito Jesus",
    "wof:placetype":"venue"
},
  "geometry": {"coordinates":[-3.286329031,42.0221138],"type":"Point"}
}