{
  "type": "Feature",
  "properties": {
    "addr:full":"G.v. Marques Del Turia, 7 Valencia Valencia 46005",
    "addr:housenumber":"7",
    "addr:postcode":"46005",
    "addr:street":"Turia",
    "iso:country":"ES",
    "sg:address":"G.v. Marques Del Turia, 7",
    "sg:city":"Valencia",
    "sg:orig_category":"M\u00c9dicos: Cardiolog\u00cda Y Afecciones Cardiovasculares",
    "sg:phone":"+34 963 52 62 04",
    "sg:postcode":"46005",
    "sg:province":"Valencia",
    "wof:name":"Velasco Rami Jose Antonio",
    "wof:placetype":"venue"
},
  "geometry": {"coordinates":[-0.3731040061,39.4653739929],"type":"Point"}
}