{
  "type": "Feature",
  "properties": {
    "iso:country":"ES",
    "sg:address":"Sumoi(pol Ind Pla Clota), 40",
    "sg:city":"S. Miquel Olerdola",
    "sg:orig_category":"Ropa Para Se\u00d1oras Y Caballeros (al Por Menor)",
    "sg:phone":"+34 938 92 10 18",
    "sg:postcode":"08734",
    "sg:province":"Barcelona",
    "wof:name":"Mapijorvi S.a.",
    "wof:placetype":"venue"
},
  "geometry": {"coordinates":[1.7167370319,41.3229942322],"type":"Point"}
}