{
  "type": "Feature",
  "properties": {
    "iso:country":"ES",
    "sg:address":"Pl Catalunya, 6",
    "sg:city":"Prat Llobregat",
    "sg:orig_category":"Peluquer\u00cdas, Peluquer\u00cda Mixta",
    "sg:phone":"+34 933 70 25 56",
    "sg:postcode":"08820",
    "sg:province":"Barcelona",
    "wof:name":"Gomez Morente Montserrat",
    "wof:placetype":"venue"
},
  "geometry": {"coordinates":[2.0926270485,41.3218650818],"type":"Point"}
}