{
  "type": "Feature",
  "properties": {
    "addr:full":"Calle de San Jose, 70 Pedro\u00d1eras Cuenca 16660",
    "addr:housenumber":"70",
    "addr:postcode":"16660",
    "addr:street":"Calle De San;Pedron\u0303Eras Cuenca",
    "iso:country":"ES",
    "sg:address":"Calle de San Jose, 70",
    "sg:city":"Pedro\u00d1eras",
    "sg:orig_category":"Delegados, Agentes De Tr\u00c1nsito, Auxiliares De Transporte Internacional",
    "sg:phone":"+34 967 16 03 18",
    "sg:postcode":"16660",
    "sg:province":"Cuenca",
    "wof:name":"Ramirez Araque Rafael",
    "wof:placetype":"venue"
},
  "geometry": {"coordinates":[-2.6739699841,39.4551811218],"type":"Point"}
}