{
  "type": "Feature",
  "properties": {
    "iso:country":"ES",
    "sg:address":"Plaz Colon (de), 21",
    "sg:city":"Cordoba",
    "sg:orig_category":"Doctores En Medicina",
    "sg:phone":"+34 957 47 04 46",
    "sg:postcode":"14001",
    "sg:province":"C\u00f3rdoba",
    "wof:name":"Cabrera Altolaguirre Maria Eugenia",
    "wof:placetype":"venue"
},
  "geometry": {"coordinates":[-4.7782101631,37.8911323547],"type":"Point"}
}