{
  "type": "Feature",
  "properties": {
    "addr:full":"Carr Fuentes (las), 3 Oliva Valencia 46780",
    "addr:housenumber":"3",
    "addr:postcode":"46780",
    "addr:street":"Carr Fuentes Las",
    "iso:country":"ES",
    "sg:address":"Carr Fuentes (las), 3",
    "sg:city":"Oliva",
    "sg:orig_category":"Parques De Atracciones Y Centros De Esparcimiento",
    "sg:phone":"+34 962 83 86 58",
    "sg:postcode":"46780",
    "sg:province":"Valencia",
    "wof:name":"Recreativos Las 3 Bolas S.l.",
    "wof:placetype":"venue"
},
  "geometry": {"coordinates":[-0.1179220006,38.9189491272],"type":"Point"}
}