{
  "type": "Feature",
  "properties": {
    "iso:country":"ES",
    "sg:address":"Avda Salamanca, 31",
    "sg:city":"Alacant",
    "sg:orig_category":"Producci\u00d3n, Distribuci\u00d3n De Electricidad",
    "sg:phone":"+34 965 92 89 75",
    "sg:postcode":"03005",
    "sg:province":"Alicante",
    "wof:name":"Electronormalux S.l.",
    "wof:placetype":"venue"
},
  "geometry": {"coordinates":[-0.4939610064,38.3478317261],"type":"Point"}
}