{
  "type": "Feature",
  "properties": {
    "addr:full":"Pl Carruaje, 3 Lorca Murcia 30800",
    "addr:housenumber":"3",
    "addr:postcode":"30800",
    "addr:street":"Pl Carruaje",
    "iso:country":"ES",
    "sg:address":"Pl Carruaje, 3",
    "sg:city":"Lorca",
    "sg:orig_category":"Cr\u00cda De Animales",
    "sg:phone":"+34 968 46 77 87",
    "sg:postcode":"30800",
    "sg:province":"Murcia",
    "wof:name":"Gimenez Alcazar Alfonso",
    "wof:placetype":"venue"
},
  "geometry": {"coordinates":[-1.6905640364,37.680557251],"type":"Point"}
}