{
  "type": "Feature",
  "properties": {
    "iso:country":"ES",
    "sg:address":"Carrer de Serral, 36",
    "sg:city":"Sant Vicen\u00c7 Dels Horts",
    "sg:orig_category":"Ingeniero",
    "sg:phone":"+34 936 56 15 58",
    "sg:postcode":"08620",
    "sg:province":"Barcelona",
    "wof:name":"Ribas Marsal Juan",
    "wof:placetype":"venue"
},
  "geometry": {"coordinates":[2.0062999725,41.4031486511],"type":"Point"}
}