{
  "type": "Feature",
  "properties": {
    "addr:full":"Poulo(valdovi\u00f1o), 64 Lago La Coru\u00f1a 15551",
    "addr:housenumber":"64",
    "addr:postcode":"15551",
    "addr:street":"Valdovin\u0303O;Lago La Corun\u0303A",
    "iso:country":"ES",
    "sg:address":"Poulo(valdovi\u00f1o), 64",
    "sg:city":"Lago",
    "sg:orig_category":"Art\u00cdculos De Madera (fabricaci\u00d3n Y Al Por Mayor)",
    "sg:phone":"+34 981 48 60 47",
    "sg:postcode":"15551",
    "sg:province":"La Coru\u00f1a",
    "wof:name":"Maderas Poulo S.l.",
    "wof:placetype":"venue"
},
  "geometry": {"coordinates":[-8.1630191803,43.5905342102],"type":"Point"}
}