{
  "type": "Feature",
  "properties": {
    "iso:country":"ES",
    "sg:address":"Cra Sant Pere De Ribes, S/n",
    "sg:city":"Sitges",
    "sg:orig_category":"Agentes, Concesionarios Y Sucursales De Veh\u00cdculos",
    "sg:phone":"+34 938 94 06 17",
    "sg:postcode":"08870",
    "sg:province":"Barcelona",
    "wof:name":"Jaime Torremorell S. L.",
    "wof:placetype":"venue"
},
  "geometry": {"coordinates":[1.8054499626,41.2342414856],"type":"Point"}
}