{
  "type": "Feature",
  "properties": {
    "addr:full":"Av. Blasco Iba\u00f1ez, 10 Playa Canet Berenguer Valencia 46529",
    "addr:housenumber":"10",
    "addr:postcode":"46529",
    "addr:street":"Av. Blasco Iban\u0303Ez",
    "iso:country":"ES",
    "sg:address":"Av. Blasco Iba\u00f1ez, 10",
    "sg:city":"Playa Canet Berenguer",
    "sg:orig_category":"Discotecas Y Salas De Baile",
    "sg:phone":"+34 962 60 83 81",
    "sg:postcode":"46529",
    "sg:province":"Valencia",
    "wof:name":"Canet Y Fuster S.l.",
    "wof:placetype":"venue"
},
  "geometry": {"coordinates":[-0.2214439958,39.6797904968],"type":"Point"}
}