{
  "type": "Feature",
  "properties": {
    "iso:country":"ES",
    "sg:address":"Calle de Borrero, S/n",
    "sg:city":"Pedro\u00d1eras",
    "sg:orig_category":"Ense\u00d1anza, Formaci\u00d3n Profesional: Aprendizaje",
    "sg:phone":"+34 967 16 00 16",
    "sg:postcode":"16660",
    "sg:province":"Cuenca",
    "wof:name":"Direccion General De La Guardia Civil",
    "wof:placetype":"venue"
},
  "geometry": {"coordinates":[-2.676858902,39.4508552551],"type":"Point"}
}