{
  "type": "Feature",
  "properties": {
    "iso:country":"ES",
    "sg:address":"Carr Dr Joan Llado, 1",
    "sg:city":"Igualada",
    "sg:orig_category":"Tintes (fabricaci\u00d3n, Al Por Mayor)",
    "sg:phone":"+34 938 04 10 52",
    "sg:postcode":"08700",
    "sg:province":"Barcelona",
    "wof:name":"Coll Casajoana Josep",
    "wof:placetype":"venue"
},
  "geometry": {"coordinates":[1.6176760197,41.584777832],"type":"Point"}
}