{
  "type": "Feature",
  "properties": {
    "iso:country":"ES",
    "sg:address":"Carrer de Font (la), 29",
    "sg:city":"Vilafranca Penedes",
    "sg:orig_category":"Dietistas",
    "sg:phone":"+34 938 92 42 40",
    "sg:postcode":"08720",
    "sg:province":"Barcelona",
    "wof:name":"Ruiz Ecija Rosario",
    "wof:placetype":"venue"
},
  "geometry": {"coordinates":[1.699516058,41.3476715088],"type":"Point"}
}