{
  "type": "Feature",
  "properties": {
    "iso:country":"ES",
    "sg:address":"Calle de Vendimia (de La), 12",
    "sg:city":"Montilla",
    "sg:orig_category":"Peluqueros: De Se\u00d1oras",
    "sg:phone":"+34 957 65 13 80",
    "sg:postcode":"14550",
    "sg:province":"C\u00f3rdoba",
    "wof:name":"Espejo Espejo Carmen",
    "wof:placetype":"venue"
},
  "geometry": {"coordinates":[-4.6422591209,37.5830841064],"type":"Point"}
}