{
  "type": "Feature",
  "properties": {
    "iso:country":"ES",
    "sg:address":"Calle de Don Bernardino Correa Viera, 20",
    "sg:city":"Palmas De Gran Canaria",
    "sg:orig_category":"Venta, Instalaci\u00d3n, Reparaci\u00d3n De Antenas Para Televisi\u00d3n",
    "sg:phone":"+34 928 36 82 49",
    "sg:postcode":"35001",
    "sg:province":"Las Palmas",
    "wof:name":"Sistemas De Telecomunicaciones Canarios S.l",
    "wof:placetype":"venue"
},
  "geometry": {"coordinates":[-15.4207792282,28.0997257233],"type":"Point"}
}