{
  "type": "Feature",
  "properties": {
    "addr:full":"Calle de Padre Claret, 1 Arrecife Las Palmas 35500",
    "addr:housenumber":"1",
    "addr:postcode":"35500",
    "addr:street":"Calle De Padre Claret",
    "iso:country":"ES",
    "sg:address":"Calle de Padre Claret, 1",
    "sg:city":"Arrecife",
    "sg:orig_category":"Florister\u00cdas",
    "sg:phone":"+34 928 80 64 22",
    "sg:postcode":"35500",
    "sg:province":"Las Palmas",
    "wof:name":"Novias Flor Floristas S.l.",
    "wof:placetype":"venue"
},
  "geometry": {"coordinates":[-13.5462141037,28.9741077423],"type":"Point"}
}