{
  "type": "Feature",
  "properties": {
    "addr:full":"Teide, 3 S Sebasti\u00e1n Reyes Madrid 28700",
    "addr:housenumber":"3",
    "addr:postcode":"28700",
    "addr:street":"Teide;S Sebastia\u0301N Reyes",
    "iso:country":"ES",
    "sg:address":"Teide, 3",
    "sg:city":"S Sebasti\u00e1n Reyes",
    "sg:orig_category":"Venta, Localizaci\u00d3n, Reparaci\u00d3n De Material E Instrumental M\u00c9dico",
    "sg:phone":"+34 916 59 17 54",
    "sg:postcode":"28700",
    "sg:province":"Madrid",
    "sg:website":"www.laerdal.es",
    "wof:name":"Laerdal Espa\u00d1a S.l.",
    "wof:placetype":"venue"
},
  "geometry": {"coordinates":[-3.7057700157,40.42029953],"type":"Point"}
}