{
  "type": "Feature",
  "properties": {
    "addr:full":"Rua Cruceiro De Sar (do), 97 Santiago De Compostela La Coru\u00f1a 15702",
    "addr:housenumber":"97",
    "addr:postcode":"15702",
    "addr:street":"Rua Cruceiro De;Corun\u0303A",
    "iso:country":"ES",
    "sg:address":"Rua Cruceiro De Sar (do), 97",
    "sg:city":"Santiago De Compostela",
    "sg:orig_category":"Molduras, Junquillos, Listones Y Molduras Perforadas",
    "sg:phone":"+34 981 59 20 17",
    "sg:postcode":"15702",
    "sg:province":"La Coru\u00f1a",
    "wof:name":"Pereira Dono Enrique",
    "wof:placetype":"venue"
},
  "geometry": {"coordinates":[-8.5298089981,42.8665618896],"type":"Point"}
}