{
  "type": "Feature",
  "properties": {
    "iso:country":"ES",
    "sg:address":"Carr Sant Marti, 59",
    "sg:city":"Lleida",
    "sg:orig_category":"Parques De Atracciones Y Centros De Esparcimiento",
    "sg:phone":"+34 973 24 88 28",
    "sg:postcode":"25004",
    "sg:province":"Lleida",
    "wof:name":"Gracia Cruellas Elena",
    "wof:placetype":"venue"
},
  "geometry": {"coordinates":[0.6205719709,41.6193237305],"type":"Point"}
}