{
  "type": "Feature",
  "properties": {
    "addr:full":"Calle de Alfonso X El Sabio, 22 Cartagena Murcia 30204",
    "addr:housenumber":"22",
    "addr:postcode":"30204",
    "addr:street":"Calle De Alfonso X El Sabio",
    "iso:country":"ES",
    "sg:address":"Calle de Alfonso X El Sabio, 22",
    "sg:city":"Cartagena",
    "sg:orig_category":"Agentes Generales De Seguros",
    "sg:phone":"+34 968 52 51 21",
    "sg:postcode":"30204",
    "sg:province":"Murcia",
    "wof:name":"Segado Zamora Encarnacion",
    "wof:placetype":"venue"
},
  "geometry": {"coordinates":[-0.989471972,37.6114959717],"type":"Point"}
}