{
  "type": "Feature",
  "properties": {
    "iso:country":"ES",
    "sg:address":"Carr Migdia, 25",
    "sg:city":"Girona",
    "sg:classifiers":[
        {
            "category":"Personal",
            "subcategory":"Barber",
            "type":"Services"
        }
    ],
    "sg:phone":"+34 972 21 72 91",
    "sg:postcode":"17002",
    "sg:province":"Girona",
    "sg:tags":[
        "caballeros",
        "de",
        "peluqueros"
    ],
    "wof:name":"Vila Daroca Juan",
    "wof:placetype":"venue"
},
  "geometry": {"coordinates":[2.8206748962,41.9760894775],"type":"Point"}
}