{
  "type": "Feature",
  "properties": {
    "addr:full":"Carrer de Girona, 7 Barcelona Barcelona 08010",
    "addr:housenumber":"7",
    "addr:postcode":"08010",
    "addr:street":"Carrer De Girona",
    "iso:country":"ES",
    "sg:address":"Carrer de Girona, 7",
    "sg:city":"Barcelona",
    "sg:orig_category":"Arquitectos",
    "sg:phone":"+34 932 11 11 50",
    "sg:postcode":"08010",
    "sg:province":"Barcelona",
    "wof:name":"Rahola Aguade Victor",
    "wof:placetype":"venue"
},
  "geometry": {"coordinates":[2.1760540009,41.3909072876],"type":"Point"}
}