{
  "type": "Feature",
  "properties": {
    "addr:full":"Avda Ca\u00d1ada (de La), 48 Coslada Madrid 28820",
    "addr:housenumber":"48",
    "addr:postcode":"28820",
    "addr:street":"Avda Can\u0303Ada De La",
    "iso:country":"ES",
    "sg:address":"Avda Ca\u00d1ada (de La), 48",
    "sg:city":"Coslada",
    "sg:orig_category":"Agentes, Concesionarios Y Sucursales De Veh\u00cdculos",
    "sg:phone":"+34 916 73 70 15",
    "sg:postcode":"28820",
    "sg:province":"Madrid",
    "wof:name":"Barral Auto S.l.",
    "wof:placetype":"venue"
},
  "geometry": {"coordinates":[-3.5389471054,40.4320068359],"type":"Point"}
}