{
  "type": "Feature",
  "properties": {
    "addr:full":"Poligon C, S/n Xativa Valencia 46800",
    "addr:housenumber":"/ n",
    "addr:postcode":"46800",
    "addr:street":"C S",
    "iso:country":"ES",
    "sg:address":"Poligon C, S/n",
    "sg:city":"Xativa",
    "sg:orig_category":"Chapister\u00cda",
    "sg:phone":"+34 962 27 01 21",
    "sg:postcode":"46800",
    "sg:province":"Valencia",
    "wof:name":"Talleres Galbis S.l.",
    "wof:placetype":"venue"
},
  "geometry": {"coordinates":[-0.5055789948,38.9977607727],"type":"Point"}
}