{
  "type": "Feature",
  "properties": {
    "addr:full":"Calle de Naval La, 65 Palmas De Gran Canaria Las Palmas 35008",
    "addr:postcode":"35008",
    "addr:street":"Calle De Naval La 65",
    "iso:country":"ES",
    "sg:address":"Calle de Naval La, 65",
    "sg:city":"Palmas De Gran Canaria",
    "sg:orig_category":"Bazares, Art\u00cdculos De Limpieza Y De Cocina (al Por Menor)",
    "sg:phone":"+34 928 46 02 55",
    "sg:postcode":"35008",
    "sg:province":"Las Palmas",
    "wof:name":"Yajia Shabgdian S.l",
    "wof:placetype":"venue"
},
  "geometry": {"coordinates":[-15.4205284119,28.1505336761],"type":"Point"}
}