{
  "type": "Feature",
  "properties": {
    "addr:full":"Pg Paisos Catalans, 61 Salt Girona 17190",
    "addr:housenumber":"61",
    "addr:postcode":"17190",
    "addr:street":"Pg Paisos Catalans",
    "iso:country":"ES",
    "sg:address":"Pg Paisos Catalans, 61",
    "sg:city":"Salt",
    "sg:orig_category":"Peluquer\u00cdas, Peluquer\u00cda Mixta",
    "sg:phone":"+34 972 24 06 02",
    "sg:postcode":"17190",
    "sg:province":"Girona",
    "wof:name":"Martinez Moreno Monica",
    "wof:placetype":"venue"
},
  "geometry": {"coordinates":[2.7859020233,41.9717750549],"type":"Point"}
}