{
  "type": "Feature",
  "properties": {
    "addr:full":"Can Manent, 42 Togores Barcelona 08202",
    "addr:housenumber":"42",
    "addr:postcode":"08202",
    "addr:street":"Togores Barcelona",
    "iso:country":"ES",
    "sg:address":"Can Manent, 42",
    "sg:city":"Togores",
    "sg:orig_category":"Transporte En General",
    "sg:phone":"+34 937 15 53 34",
    "sg:postcode":"08202",
    "sg:province":"Barcelona",
    "wof:name":"Compa\u00f1ia Internacional De Almacenaje S.a.",
    "wof:placetype":"venue"
},
  "geometry": {"coordinates":[2.125674963,41.5481300354],"type":"Point"}
}