{
  "type": "Feature",
  "properties": {
    "iso:country":"ES",
    "sg:address":"Pase Curas (de Los), 6",
    "sg:city":"Alcala Henares",
    "sg:orig_category":"Caf\u00c9s, Bares, Cervecer\u00cdas",
    "sg:phone":"+34 918 78 81 42",
    "sg:postcode":"28803",
    "sg:province":"Madrid",
    "wof:name":"Berlinches Moreno Jesus",
    "wof:placetype":"venue"
},
  "geometry": {"coordinates":[-3.3719210625,40.4783554077],"type":"Point"}
}