{
  "type": "Feature",
  "properties": {
    "iso:country":"ES",
    "sg:address":"Calle de General Ricardos, 109",
    "sg:city":"Madrid",
    "sg:orig_category":"Bazares, Art\u00cdculos De Limpieza Y De Cocina (al Por Menor)",
    "sg:phone":"+34 914 71 20 61",
    "sg:postcode":"28019",
    "sg:province":"Madrid",
    "wof:name":"Bartolome Flores Francisco",
    "wof:placetype":"venue"
},
  "geometry": {"coordinates":[-3.7258551121,40.3920936584],"type":"Point"}
}