{
  "type": "Feature",
  "properties": {
    "addr:full":"Carrer de Balaguer, 16 Sabadell Barcelona 08207",
    "addr:housenumber":"16",
    "addr:postcode":"08207",
    "addr:street":"Carrer De Balaguer",
    "iso:country":"ES",
    "sg:address":"Carrer de Balaguer, 16",
    "sg:city":"Sabadell",
    "sg:orig_category":"Centros De Educaci\u00d3n Especial",
    "sg:phone":"+34 937 16 29 07",
    "sg:postcode":"08207",
    "sg:province":"Barcelona",
    "wof:name":"Ajuntament De Sabadell",
    "wof:placetype":"venue"
},
  "geometry": {"coordinates":[2.0922014713,41.564414978],"type":"Point"}
}