{
  "type": "Feature",
  "properties": {
    "iso:country":"ES",
    "sg:address":"Calle de Adelfa, 4",
    "sg:city":"Puebla Alfinden",
    "sg:orig_category":"Panader\u00cdas, Pasteler\u00cdas, Boller\u00cda Industriale (fabricaci\u00d3n, Al Por Mayor)",
    "sg:phone":"+34 976 10 84 75",
    "sg:postcode":"50171",
    "sg:province":"Zaragoza",
    "wof:name":"Distribuciones Jimenez Palacio S.c.",
    "wof:placetype":"venue"
},
  "geometry": {"coordinates":[-0.7659859061,41.6427383423],"type":"Point"}
}