{
  "type": "Feature",
  "properties": {
    "addr:full":"Calle de Pedro De Villandrado, S/n Marbella M\u00e1laga 29600",
    "addr:housenumber":"s / n",
    "addr:postcode":"29600",
    "addr:street":"Calle De Pedro De Villandrado;Ma\u0301Laga",
    "iso:country":"ES",
    "sg:address":"Calle de Pedro De Villandrado, S/n",
    "sg:city":"Marbella",
    "sg:orig_category":"Peluqueros: De Se\u00d1oras",
    "sg:phone":"+34 952 77 26 81",
    "sg:postcode":"29600",
    "sg:province":"M\u00e1laga",
    "wof:name":"Lopez Sanchez Silvia",
    "wof:placetype":"venue"
},
  "geometry": {"coordinates":[-4.8787789345,36.5162239075],"type":"Point"}
}