{
  "type": "Feature",
  "properties": {
    "iso:country":"ES",
    "sg:address":"Carrer de Mallorca, 441",
    "sg:city":"Barcelona",
    "sg:orig_category":"Reposter\u00cdas",
    "sg:phone":"+34 934 55 09 15",
    "sg:postcode":"08013",
    "sg:province":"Barcelona",
    "wof:name":"Garcia Armas Luz",
    "wof:placetype":"venue"
},
  "geometry": {"coordinates":[2.1778550148,41.4055175781],"type":"Point"}
}