{
  "type": "Feature",
  "properties": {
    "iso:country":"ES",
    "sg:address":"Avda San Pedro De Alcantara, 5",
    "sg:city":"Caceres",
    "sg:orig_category":"M\u00c9dicos: Foniatr\u00cda Y Logopedia",
    "sg:phone":"+34 927 22 56 81",
    "sg:postcode":"10001",
    "sg:province":"C\u00e1ceres",
    "wof:name":"Gomez Vivas Raquel",
    "wof:placetype":"venue"
},
  "geometry": {"coordinates":[-6.3790431023,39.4706535339],"type":"Point"}
}