{
  "type": "Feature",
  "properties": {
    "addr:full":"Pol. Ind. Castilla, S/n Pol. Ind. Castilla Valencia 46380",
    "addr:housenumber":"s / n",
    "addr:postcode":"46380",
    "addr:street":"Pol. Ind. Castilla",
    "iso:country":"ES",
    "sg:address":"Pol. Ind. Castilla, S/n",
    "sg:city":"Pol. Ind. Castilla",
    "sg:orig_category":"Negocio De Metales No Ferrosos",
    "sg:phone":"+34 962 51 23 89",
    "sg:postcode":"46380",
    "sg:province":"Valencia",
    "wof:name":"Bathroom Fiting S.l.",
    "wof:placetype":"venue"
},
  "geometry": {"coordinates":[-0.6874480247,39.4945602417],"type":"Point"}
}