{
  "type": "Feature",
  "properties": {
    "addr:full":"Calle de Goya, 8 Alcazar S. Juan Ciudad Real 13600",
    "addr:housenumber":"8",
    "addr:postcode":"13600",
    "addr:street":"Calle De Goya;Alcazar S. Juan Ciudad Real",
    "iso:country":"ES",
    "sg:address":"Calle de Goya, 8",
    "sg:city":"Alcazar S. Juan",
    "sg:orig_category":"Cl\u00cdnicas Dentales",
    "sg:phone":"+34 926 54 49 48",
    "sg:postcode":"13600",
    "sg:province":"Ciudad Real",
    "wof:name":"Clinica Dental Jesus Caballero S.l.",
    "wof:placetype":"venue"
},
  "geometry": {"coordinates":[-3.2016189098,39.3903961182],"type":"Point"}
}