{
  "type": "Feature",
  "properties": {
    "iso:country":"ES",
    "sg:address":"Calle de Guijo, 63",
    "sg:city":"Coria",
    "sg:orig_category":"Molduras, Junquillos, Listones Y Molduras Perforadas",
    "sg:phone":"+34 927 50 61 58",
    "sg:postcode":"10800",
    "sg:province":"C\u00e1ceres",
    "wof:name":"Hernandez Corchete Maria Jose",
    "wof:placetype":"venue"
},
  "geometry": {"coordinates":[-6.533572197,39.9880447388],"type":"Point"}
}