{
  "type": "Feature",
  "properties": {
    "addr:full":"Carrer de Sant Cristofol, 183 Amposta Tarragona 43870",
    "addr:housenumber":"183",
    "addr:postcode":"43870",
    "addr:street":"Carrer De Sant Cristofol",
    "iso:country":"ES",
    "sg:address":"Carrer de Sant Cristofol, 183",
    "sg:city":"Amposta",
    "sg:orig_category":"Promotores Constructores",
    "sg:phone":"+34 977 70 80 97",
    "sg:postcode":"43870",
    "sg:province":"Tarragona",
    "wof:name":"Rumat Monsia",
    "wof:placetype":"venue"
},
  "geometry": {"coordinates":[0.576695025,40.7019500732],"type":"Point"}
}