{
  "type": "Feature",
  "properties": {
    "addr:full":"Pl Estacio, S/n Reus Tarragona 43202",
    "addr:housenumber":"s / n",
    "addr:postcode":"43202",
    "addr:street":"Pl Estacio",
    "iso:country":"ES",
    "sg:address":"Pl Estacio, S/n",
    "sg:city":"Reus",
    "sg:orig_category":"Servicios Gsm",
    "sg:phone":"+34 977 31 30 48",
    "sg:postcode":"43202",
    "sg:province":"Tarragona",
    "sg:website":"www.intermobils.com",
    "wof:name":"Inter-mobils 33 S.l.",
    "wof:placetype":"venue"
},
  "geometry": {"coordinates":[1.1004970074,41.1605567932],"type":"Point"}
}