{
  "type": "Feature",
  "properties": {
    "iso:country":"ES",
    "sg:address":"Avda Espa\u00d1a De, S/n",
    "sg:city":"Torremolinos",
    "sg:orig_category":"Molduras, Junquillos, Listones Y Molduras Perforadas",
    "sg:phone":"+34 952 37 69 24",
    "sg:postcode":"29620",
    "sg:province":"M\u00e1laga",
    "wof:name":"Aljawara 29 S.l.",
    "wof:placetype":"venue"
},
  "geometry": {"coordinates":[-4.5102648735,36.6032752991],"type":"Point"}
}