{
  "type": "Feature",
  "properties": {
    "addr:full":"Calle de Trinquete, 14 Elda Alicante 03600",
    "addr:housenumber":"14",
    "addr:postcode":"03600",
    "addr:street":"Calle De Trinquete",
    "iso:country":"ES",
    "sg:address":"Calle de Trinquete, 14",
    "sg:city":"Elda",
    "sg:orig_category":"Supermercados Y Hipermercados",
    "sg:phone":"+34 965 38 39 15",
    "sg:postcode":"03600",
    "sg:province":"Alicante",
    "wof:name":"Autoservicio Ba\u00f1on Del Valle S.l.u",
    "wof:placetype":"venue"
},
  "geometry": {"coordinates":[-0.7935560942,38.4739837646],"type":"Point"}
}