{
  "type": "Feature",
  "properties": {
    "addr:full":"Calle de Concejo Del, 17 Trigueros Huelva 21620",
    "addr:housenumber":"17",
    "addr:postcode":"21620",
    "addr:street":"Calle De Concejo Del",
    "iso:country":"ES",
    "sg:address":"Calle de Concejo Del, 17",
    "sg:city":"Trigueros",
    "sg:orig_category":"Comerciantes Al Por Mayor De Vinos, Licores Y Alcoholes",
    "sg:phone":"+34 959 30 52 96",
    "sg:postcode":"21620",
    "sg:province":"Huelva",
    "wof:name":"Freire Barranco Juan Miguel",
    "wof:placetype":"venue"
},
  "geometry": {"coordinates":[-6.8359885216,37.3847351074],"type":"Point"}
}