{
  "type": "Feature",
  "properties": {
    "addr:full":"Calle de Aguila, 12 Madrid Madrid 28005",
    "addr:housenumber":"12",
    "addr:postcode":"madrid;28005",
    "addr:street":"Calle De Aguila",
    "iso:country":"ES",
    "sg:address":"Calle de Aguila, 12",
    "sg:city":"Madrid",
    "sg:classifiers":[
        {
            "category":"Manufacturing",
            "subcategory":"Building Materials",
            "type":"Manufacturing & Wholesale Goods"
        }
    ],
    "sg:phone":"+34 913 65 66 29",
    "sg:postcode":"28005",
    "sg:province":"Madrid",
    "sg:tags":[
        "bebidas",
        "para",
        "la",
        "de",
        "y",
        "equipo",
        "industria"
    ],
    "wof:name":"Rodriguez Rodriguez Julio",
    "wof:placetype":"venue"
},
  "geometry": {"coordinates":[-3.7123725414,40.4096488953],"type":"Point"}
}