{
  "type": "Feature",
  "properties": {
    "addr:full":"Can Bernat (pol Torrent Puig), 25 Arenys Munt Barcelona 08358",
    "addr:housenumber":"25",
    "addr:postcode":"08358",
    "addr:street":"Puig;Munt Barcelona",
    "iso:country":"ES",
    "sg:address":"Can Bernat (pol Torrent Puig), 25",
    "sg:city":"Arenys Munt",
    "sg:orig_category":"Electricidad: Material Y Suministros De Instalaci\u00d3n (fabricaci\u00d3n)",
    "sg:phone":"+34 937 95 14 18",
    "sg:postcode":"08358",
    "sg:province":"Barcelona",
    "wof:name":"Tallers Fil-sol S.l.",
    "wof:placetype":"venue"
},
  "geometry": {"coordinates":[2.5408000946,41.6117286682],"type":"Point"}
}