{
  "type": "Feature",
  "properties": {
    "iso:country":"ES",
    "sg:address":"Calle de Santa Leonor, 37",
    "sg:city":"Madrid",
    "sg:orig_category":"Panader\u00cdas, Panader\u00cdas",
    "sg:phone":"+34 913 04 70 64",
    "sg:postcode":"28037",
    "sg:province":"Madrid",
    "wof:name":"Ortiz Del Alamo Dolores",
    "wof:placetype":"venue"
},
  "geometry": {"coordinates":[-3.6307940483,40.4369430542],"type":"Point"}
}