{
  "type": "Feature",
  "properties": {
    "iso:country":"ES",
    "sg:address":"Gran, 12",
    "sg:city":"Alins",
    "sg:classifiers":[
        {
            "category":"Taxi",
            "type":"Transportation"
        }
    ],
    "sg:phone":"+34 973 62 43 53",
    "sg:postcode":"25574",
    "sg:province":"Lleida",
    "wof:name":"Llor Bringue Jose Maria",
    "wof:placetype":"venue"
},
  "geometry": {"coordinates":[1.3177839518,42.5497512817],"type":"Point"}
}