{
  "type": "Feature",
  "properties": {
    "iso:country":"ES",
    "sg:address":"Valencia(palanc.), Km. 0085,0",
    "sg:city":"Cuenca",
    "sg:orig_category":"M\u00c1rmoles, Granitos Y Piedras Naturales",
    "sg:phone":"+34 969 22 88 57",
    "sg:postcode":"16004",
    "sg:province":"Cuenca",
    "wof:name":"Garcia Lopez Carlos",
    "wof:placetype":"venue"
},
  "geometry": {"coordinates":[-1.9685826302,40.0261421204],"type":"Point"}
}