{
  "type": "Feature",
  "properties": {
    "iso:country":"ES",
    "sg:address":"Calle de Juan Bravo, 42",
    "sg:city":"Segovia",
    "sg:orig_category":"Ropa Para Se\u00d1oras Y Caballeros (al Por Menor)",
    "sg:phone":"+34 921 46 27 54",
    "sg:postcode":"40001",
    "sg:province":"Segovia",
    "sg:website":"www.lacoste.es",
    "wof:name":"Marta Y Esther C.b",
    "wof:placetype":"venue"
},
  "geometry": {"coordinates":[-4.121286869,40.9482917786],"type":"Point"}
}