{
  "type": "Feature",
  "properties": {
    "iso:country":"ES",
    "sg:address":"Calle de Rio Manzanas, S/n",
    "sg:city":"Zamora",
    "sg:orig_category":"Centros De Educaci\u00d3n Especial",
    "sg:phone":"+34 980 51 04 48",
    "sg:postcode":"49024",
    "sg:province":"Zamora",
    "wof:name":"Colegio Publico Riomanzanas",
    "wof:placetype":"venue"
},
  "geometry": {"coordinates":[-5.7495732307,41.5154571533],"type":"Point"}
}