{
  "type": "Feature",
  "properties": {
    "iso:country":"ES",
    "sg:address":"Avda Modesto Lafuente, 29",
    "sg:city":"Palencia",
    "sg:orig_category":"Ropa Para Se\u00d1oras (al Por Menor)",
    "sg:phone":"+34 979 72 44 82",
    "sg:postcode":"34002",
    "sg:province":"Palencia",
    "wof:name":"Gonzalez Redondo Milagros",
    "wof:placetype":"venue"
},
  "geometry": {"coordinates":[-4.5273389816,42.0042037964],"type":"Point"}
}