{
  "type": "Feature",
  "properties": {
    "iso:country":"ES",
    "sg:address":"Calle de Humilladeros, 24",
    "sg:city":"Paterna Campo",
    "sg:orig_category":"Producci\u00d3n De Abonos Y De Fertilizantes",
    "sg:phone":"+34 959 42 90 22",
    "sg:postcode":"21880",
    "sg:province":"Huelva",
    "wof:name":"Agrimartin Fertilizantes S.l.",
    "wof:placetype":"venue"
},
  "geometry": {"coordinates":[-6.3978114128,37.4192008972],"type":"Point"}
}