{
  "type": "Feature",
  "properties": {
    "addr:full":"G.v. Corts Catalanes, 569 Barcelona Barcelona 08011",
    "addr:housenumber":"569",
    "addr:postcode":"08011",
    "addr:street":"Catalanes",
    "iso:country":"ES",
    "sg:address":"G.v. Corts Catalanes, 569",
    "sg:city":"Barcelona",
    "sg:orig_category":"Asociaciones Humanitarias, De Cooperaci\u00d3n, De Acci\u00d3n Social",
    "sg:phone":"+34 934 51 64 42",
    "sg:postcode":"08011",
    "sg:province":"Barcelona",
    "wof:name":"Instituto Neuro Psico Pedagogico Guru De Barcelona",
    "wof:placetype":"venue"
},
  "geometry": {"coordinates":[2.1616039276,41.384803772],"type":"Point"}
}