{
  "type": "Feature",
  "properties": {
    "addr:full":"Pg Maragall, 166 Barcelona Barcelona 08027",
    "addr:housenumber":"166",
    "addr:postcode":"08027",
    "addr:street":"Pg Maragall",
    "iso:country":"ES",
    "sg:address":"Pg Maragall, 166",
    "sg:city":"Barcelona",
    "sg:orig_category":"Agencias De Viajes",
    "sg:phone":"+34 934 08 66 97",
    "sg:postcode":"08027",
    "sg:province":"Barcelona",
    "sg:website":"www.viajesiberia.com",
    "wof:name":"Viajes Iberia S.a.",
    "wof:placetype":"venue"
},
  "geometry": {"coordinates":[2.1771531105,41.4244804382],"type":"Point"}
}