{
  "type": "Feature",
  "properties": {
    "addr:full":"Carr Riu (del), 12 Cullera Valencia 46400",
    "addr:postcode":"46400",
    "addr:street":"Carr Riu Del",
    "iso:country":"ES",
    "sg:address":"Carr Riu (del), 12",
    "sg:city":"Cullera",
    "sg:orig_category":"Muebles, Minoristas",
    "sg:phone":"+34 961 72 03 62",
    "sg:postcode":"46400",
    "sg:province":"Valencia",
    "sg:website":"www.mueblessapi\u00f1a.com",
    "wof:name":"Muebles Sapi\u00d1a S.l.",
    "wof:placetype":"venue"
},
  "geometry": {"coordinates":[-0.2562240064,39.1653251648],"type":"Point"}
}