{
  "type": "Feature",
  "properties": {
    "iso:country":"ES",
    "sg:address":"Calle de Senda Del Infante, 15",
    "sg:city":"Madrid",
    "sg:orig_category":"Tintes (fabricaci\u00d3n, Al Por Mayor)",
    "sg:phone":"+34 917 30 37 69",
    "sg:postcode":"28035",
    "sg:province":"Madrid",
    "wof:name":"Molina Laveda Antonio",
    "wof:placetype":"venue"
},
  "geometry": {"coordinates":[-3.7203724384,40.4893455505],"type":"Point"}
}