{
  "type": "Feature",
  "properties": {
    "iso:country":"ES",
    "sg:address":"Rua Sagunto, 57",
    "sg:city":"Vigo",
    "sg:orig_category":"Molduras, Junquillos, Listones Y Molduras Perforadas",
    "sg:phone":"+34 986 27 52 65",
    "sg:postcode":"36205",
    "sg:province":"Pontevedra",
    "wof:name":"Rey Penedo Rosa",
    "wof:placetype":"venue"
},
  "geometry": {"coordinates":[-8.7017002106,42.2281646729],"type":"Point"}
}