{
  "type": "Feature",
  "properties": {
    "iso:country":"ES",
    "sg:address":"Calle de Marques De La Ensenada, 16",
    "sg:city":"Madrid",
    "sg:orig_category":"Molduras, Junquillos, Listones Y Molduras Perforadas",
    "sg:phone":"+34 913 19 40 98",
    "sg:postcode":"28004",
    "sg:province":"Madrid",
    "wof:name":"Mama Carlota S.l.",
    "wof:placetype":"venue"
},
  "geometry": {"coordinates":[-3.692214489,40.4252853394],"type":"Point"}
}