{
  "type": "Feature",
  "properties": {
    "addr:full":"Calle de Linares, 23 Puente-genil C\u00f3rdoba 14500",
    "addr:housenumber":"23",
    "addr:postcode":"14500",
    "addr:street":"Calle De Linares;Co\u0301Rdoba",
    "iso:country":"ES",
    "sg:address":"Calle de Linares, 23",
    "sg:city":"Puente-genil",
    "sg:orig_category":"Conservas De Legumbres (fabricaci\u00d3n, Al Por Mayor)",
    "sg:phone":"+34 957 60 07 33",
    "sg:postcode":"14500",
    "sg:province":"C\u00f3rdoba",
    "sg:website":"www.membrillera.com",
    "wof:name":"Membrillera Industrial S. A.",
    "wof:placetype":"venue"
},
  "geometry": {"coordinates":[-4.7743091583,37.3902244568],"type":"Point"}
}