{
  "type": "Feature",
  "properties": {
    "addr:full":"Calle de Severo Catalina, 9 Cuenca Cuenca 16001",
    "addr:housenumber":"9",
    "addr:postcode":"16001",
    "addr:street":"Calle De Severo Catalina",
    "iso:country":"ES",
    "sg:address":"Calle de Severo Catalina, 9",
    "sg:city":"Cuenca",
    "sg:orig_category":"Alimentaci\u00d3n General (al Por Menor)",
    "sg:phone":"+34 969 22 90 17",
    "sg:postcode":"16001",
    "sg:province":"Cuenca",
    "wof:name":"Pasaron Lopez Jose Maria",
    "wof:placetype":"venue"
},
  "geometry": {"coordinates":[-2.1302680969,40.0781288147],"type":"Point"}
}