{
  "type": "Feature",
  "properties": {
    "iso:country":"ES",
    "sg:address":"Rio Jalon, S/n",
    "sg:city":"Sto. Domingo",
    "sg:orig_category":"Internados & Ense\u00d1anza Privada",
    "sg:phone":"+34 961 98 00 70",
    "sg:postcode":"46370",
    "sg:province":"Valencia",
    "sg:website":"www.sek.net",
    "wof:name":"Colegio Internacional Del Levante S.a.",
    "wof:placetype":"venue"
},
  "geometry": {"coordinates":[-0.5592240095,39.433052063],"type":"Point"}
}