{
  "type": "Feature",
  "properties": {
    "addr:full":"Calle de Martinez Izquierdo, 80 Madrid Madrid 28028",
    "addr:housenumber":"80",
    "addr:postcode":"madrid;28028",
    "addr:street":"Calle De Martinez Izquierdo",
    "iso:country":"ES",
    "sg:address":"Calle de Martinez Izquierdo, 80",
    "sg:city":"Madrid",
    "sg:orig_category":"Asociaciones Humanitarias, De Cooperaci\u00d3n, De Acci\u00d3n Social",
    "sg:phone":"+34 917 26 20 07",
    "sg:postcode":"28028",
    "sg:province":"Madrid",
    "wof:name":"Asociacion Deporte Y Vida",
    "wof:placetype":"venue"
},
  "geometry": {"coordinates":[-3.6629397869,40.435218811],"type":"Point"}
}