{
  "type": "Feature",
  "properties": {
    "addr:full":"Calle de Genoveses (los), 6 Cordoba C\u00f3rdoba 14006",
    "addr:housenumber":"6",
    "addr:postcode":"14006",
    "addr:street":"Calle De Genoveses Los;Co\u0301Rdoba",
    "iso:country":"ES",
    "sg:address":"Calle de Genoveses (los), 6",
    "sg:city":"Cordoba",
    "sg:orig_category":"Promotores Constructores",
    "sg:phone":"+34 957 40 56 99",
    "sg:postcode":"14006",
    "sg:province":"C\u00f3rdoba",
    "wof:name":"Cordobesa De Planificaciones Sociedad Cooperativa Andaluza",
    "wof:placetype":"venue"
},
  "geometry": {"coordinates":[-4.7742948532,37.8968086243],"type":"Point"}
}