{
  "type": "Feature",
  "properties": {
    "iso:country":"ES",
    "sg:address":"C\u00d1ad Real, 202",
    "sg:city":"Valladolid",
    "sg:orig_category":"Artes Gr\u00c1ficas, Artes Pl\u00c1sticas (curso)",
    "sg:phone":"+34 983 24 64 73",
    "sg:postcode":"47008",
    "sg:province":"Valladolid",
    "wof:name":"Josja C.b.",
    "wof:placetype":"venue"
},
  "geometry": {"coordinates":[-4.7927489281,41.6193618774],"type":"Point"}
}