{
  "type": "Feature",
  "properties": {
    "iso:country":"ES",
    "sg:address":"Calle de Doctor Mesa Moles, 3",
    "sg:city":"Granada",
    "sg:orig_category":"Electrodom\u00c9sticos (al Por Menor)",
    "sg:phone":"+34 958 29 58 12",
    "sg:postcode":"18012",
    "sg:province":"Granada",
    "wof:name":"Garcia Gomez Antonio",
    "wof:placetype":"venue"
},
  "geometry": {"coordinates":[-3.6085078716,37.189540863],"type":"Point"}
}