{
  "type": "Feature",
  "properties": {
    "iso:country":"ES",
    "sg:address":"Avda Domingo Bueno, 2",
    "sg:city":"Pontenova",
    "sg:orig_category":"Molduras, Junquillos, Listones Y Molduras Perforadas",
    "sg:phone":"+34 986 33 83 09",
    "sg:postcode":"36400",
    "sg:province":"Pontevedra",
    "wof:name":"Arsenio Y Suso C.b.",
    "wof:placetype":"venue"
},
  "geometry": {"coordinates":[-8.6480531693,42.4336204529],"type":"Point"}
}