{
  "type": "Feature",
  "properties": {
    "addr:full":"Carrer de (p. I. Cami Dels Frares), S/n Lleida Lleida 25191",
    "addr:housenumber":"s / n",
    "addr:postcode":"25191",
    "addr:street":"Carrer De P. I. Cami Dels Frares",
    "iso:country":"ES",
    "sg:address":"Carrer de (p. I. Cami Dels Frares), S/n",
    "sg:city":"Lleida",
    "sg:orig_category":"Rectificaci\u00d3n, Mecanizado, Fresado",
    "sg:phone":"+34 973 23 30 99",
    "sg:postcode":"25191",
    "sg:province":"Lleida",
    "wof:name":"La Rectificadora Espa\u00f1ola S.l.",
    "wof:placetype":"venue"
},
  "geometry": {"coordinates":[0.6831650138,41.5832138062],"type":"Point"}
}