{
  "type": "Feature",
  "properties": {
    "iso:country":"ES",
    "sg:address":"Calle de Sol, 10",
    "sg:city":"Villaviciosa",
    "sg:orig_category":"Ropa Para Ni\u00d1os (al Por Menor)",
    "sg:phone":"+34 985 89 22 97",
    "sg:postcode":"33300",
    "sg:province":"Asturias",
    "wof:name":"Gonzalez Longo Miguel Angel",
    "wof:placetype":"venue"
},
  "geometry": {"coordinates":[-5.4341039658,43.4812889099],"type":"Point"}
}