{
  "type": "Feature",
  "properties": {
    "addr:full":"Av Paral.lel, 136 Barcelona Barcelona 08015",
    "addr:housenumber":"136",
    "addr:postcode":"08015",
    "addr:street":"Av Paral.Lel",
    "iso:country":"ES",
    "sg:address":"Av Paral.lel, 136",
    "sg:city":"Barcelona",
    "sg:orig_category":"Veh\u00cdculos De Ocasi\u00d3n",
    "sg:phone":"+34 934 23 17 50",
    "sg:postcode":"08015",
    "sg:province":"Barcelona",
    "wof:name":"Automoviles Monterroso S.l.",
    "wof:placetype":"venue"
},
  "geometry": {"coordinates":[2.1605799198,41.3751411438],"type":"Point"}
}