{
  "type": "Feature",
  "properties": {
    "iso:country":"ES",
    "sg:address":"Calle de Atilano Rodriguez, 11",
    "sg:city":"Santander",
    "sg:orig_category":"M\u00c9dicos: Psiquiatr\u00cda",
    "sg:phone":"+34 942 22 45 44",
    "sg:postcode":"39002",
    "sg:province":"Cantabria",
    "wof:name":"Servicios Socio-sanitarios Rodero S.l.",
    "wof:placetype":"venue"
},
  "geometry": {"coordinates":[-3.8101260662,43.4584884644],"type":"Point"}
}