{
  "type": "Feature",
  "properties": {
    "iso:country":"ES",
    "sg:address":"La Riera, S/n",
    "sg:city":"Riera",
    "sg:classifiers":[
        {
            "category":"Taxi",
            "type":"Transportation"
        }
    ],
    "sg:phone":"+34 985 85 62 62",
    "sg:postcode":"33324",
    "sg:province":"Asturias",
    "wof:name":"Alonso Vicente Filiberto",
    "wof:placetype":"venue"
},
  "geometry": {"coordinates":[-5.2832627296,43.4757881165],"type":"Point"}
}