{
  "type": "Feature",
  "properties": {
    "addr:full":"Cami Capellanets, 39 Mataro Barcelona 08303",
    "addr:housenumber":"39",
    "addr:postcode":"08303",
    "addr:street":"Capellanets",
    "iso:country":"ES",
    "sg:address":"Cami Capellanets, 39",
    "sg:city":"Mataro",
    "sg:orig_category":"Telas Para Tapizar, Cortinas, Pasamaner\u00cda (fabricaci\u00d3n, Al Por Mayor)",
    "sg:phone":"+34 937 57 40 05",
    "sg:postcode":"08303",
    "sg:province":"Barcelona",
    "wof:name":"Cabanillas Lopez Luciano",
    "wof:placetype":"venue"
},
  "geometry": {"coordinates":[2.4264969826,41.543800354],"type":"Point"}
}