{
  "type": "Feature",
  "properties": {
    "addr:full":"Calle de Alfonso Xii, 34 Tomelloso Ciudad Real 13700",
    "addr:housenumber":"34",
    "addr:postcode":"13700",
    "addr:street":"Calle De Alfonso Xii",
    "iso:country":"ES",
    "sg:address":"Calle de Alfonso Xii, 34",
    "sg:city":"Tomelloso",
    "sg:orig_category":"Panader\u00cdas, Pasteler\u00cdas, Boller\u00cda Industriale (fabricaci\u00d3n, Al Por Mayor)",
    "sg:phone":"+34 926 51 10 30",
    "sg:postcode":"13700",
    "sg:province":"Ciudad Real",
    "wof:name":"Lucendo Martin Angel",
    "wof:placetype":"venue"
},
  "geometry": {"coordinates":[-3.0250446796,39.1592025757],"type":"Point"}
}