{
  "type": "Feature",
  "properties": {
    "iso:country":"ES",
    "sg:address":"Carrer de Mart, 36",
    "sg:city":"S. Adria Besos",
    "sg:orig_category":"Peluquer\u00cdas, Peluquer\u00cda Mixta",
    "sg:phone":"+34 933 81 92 54",
    "sg:postcode":"08930",
    "sg:province":"Barcelona",
    "wof:name":"Fernandez Lopez Argentina",
    "wof:placetype":"venue"
},
  "geometry": {"coordinates":[2.2196190357,41.4205284119],"type":"Point"}
}