{
  "type": "Feature",
  "properties": {
    "addr:full":"Plaz Mayor, 9 Elciego \u00c1lava 01340",
    "addr:housenumber":"9",
    "addr:postcode":"01340",
    "addr:street":"Plaz Mayor",
    "iso:country":"ES",
    "sg:address":"Plaz Mayor, 9",
    "sg:city":"Elciego",
    "sg:orig_category":"Cajas De Ahorro",
    "sg:phone":"+34 945 60 62 03",
    "sg:postcode":"01340",
    "sg:province":"\u00c1lava",
    "sg:website":"www.cajavital.es",
    "wof:name":"Caja De Ahorros De Vitoria Y Alava",
    "wof:placetype":"venue"
},
  "geometry": {"coordinates":[-2.6165480614,42.5144920349],"type":"Point"}
}