{
  "type": "Feature",
  "properties": {
    "iso:country":"ES",
    "sg:address":"Calle de Castilla La Nueva (de), 21",
    "sg:city":"Fuenlabrada",
    "sg:orig_category":"Peluquer\u00cdas, Peluquer\u00cda Mixta",
    "sg:phone":"+34 916 97 41 41",
    "sg:postcode":"28941",
    "sg:province":"Madrid",
    "wof:name":"Alea C.b.",
    "wof:placetype":"venue"
},
  "geometry": {"coordinates":[-3.7973423004,40.2936553955],"type":"Point"}
}