{
  "type": "Feature",
  "properties": {
    "addr:full":"Pase Conde De Sepulveda (del), 36 Segovia Segovia 40006",
    "addr:housenumber":"36",
    "addr:postcode":"40006",
    "addr:street":"Conde;Sepulveda Del",
    "iso:country":"ES",
    "sg:address":"Pase Conde De Sepulveda (del), 36",
    "sg:city":"Segovia",
    "sg:orig_category":"Electricidad, Electr\u00d3nica: Suministros (al Por Menor)",
    "sg:phone":"+34 921 44 27 01",
    "sg:postcode":"40006",
    "sg:province":"Segovia",
    "wof:name":"Atencion Digital S.l.",
    "wof:placetype":"venue"
},
  "geometry": {"coordinates":[-4.2025856972,40.8924293518],"type":"Point"}
}