{
  "type": "Feature",
  "properties": {
    "addr:full":"Carrer de Diputacio, 92 Barcelona Barcelona 08015",
    "addr:housenumber":"92",
    "addr:postcode":"08015",
    "addr:street":"Carrer De Diputacio",
    "iso:country":"ES",
    "sg:address":"Carrer de Diputacio, 92",
    "sg:city":"Barcelona",
    "sg:orig_category":"Ense\u00d1anza: Idiomas",
    "sg:phone":"+34 934 88 13 31",
    "sg:postcode":"08015",
    "sg:province":"Barcelona",
    "sg:website":"www.enforex.es",
    "wof:name":"Enforex English Executives S.l.",
    "wof:placetype":"venue"
},
  "geometry": {"coordinates":[2.1545379162,41.3808021545],"type":"Point"}
}