{
  "type": "Feature",
  "properties": {
    "iso:country":"ES",
    "sg:address":"Calle de San Martin, S/n",
    "sg:city":"Casco Viejo",
    "sg:orig_category":"Contenedores (mercanc\u00cdas)",
    "sg:phone":"+34 948 31 00 48",
    "sg:postcode":"31191",
    "sg:province":"Navarra",
    "wof:name":"Oroz Arizcuren Jose Maria",
    "wof:placetype":"venue"
},
  "geometry": {"coordinates":[-1.6518089771,42.7533912659],"type":"Point"}
}