{
  "type": "Feature",
  "properties": {
    "iso:country":"ES",
    "sg:address":"Rua Rosalia De Castro, 16",
    "sg:city":"Calle",
    "sg:orig_category":"Confiter\u00cdas, Chocolater\u00cdas (al Por Menor)",
    "sg:phone":"+34 986 70 10 24",
    "sg:postcode":"36690",
    "sg:province":"Pontevedra",
    "wof:name":"Golfi C.b.",
    "wof:placetype":"venue"
},
  "geometry": {"coordinates":[-8.6101989746,42.3416519165],"type":"Point"}
}