{
  "type": "Feature",
  "properties": {
    "iso:country":"ES",
    "sg:address":"Carr Paterna, 1",
    "sg:city":"Manises",
    "sg:orig_category":"Molduras, Junquillos, Listones Y Molduras Perforadas",
    "sg:phone":"+34 961 52 45 55",
    "sg:postcode":"46940",
    "sg:province":"Valencia",
    "wof:name":"Oscar Moyano Maria Julia",
    "wof:placetype":"venue"
},
  "geometry": {"coordinates":[-0.452026993,39.4868431091],"type":"Point"}
}