{
  "type": "Feature",
  "properties": {
    "iso:country":"ES",
    "sg:address":"Calle de Doctor Ramon Muncharaz, S/n",
    "sg:city":"Rozas De Madrid",
    "sg:orig_category":"Agencias Y Agentes Comerciales, Representantes",
    "sg:phone":"+34 916 37 72 00",
    "sg:postcode":"28230",
    "sg:province":"Madrid",
    "wof:name":"Cortes Garcia Maria Del Carmen",
    "wof:placetype":"venue"
},
  "geometry": {"coordinates":[-3.8764190674,40.4943389893],"type":"Point"}
}