{
  "type": "Feature",
  "properties": {
    "addr:full":"Plaz Ave Maria (del), 3 Puerto De Santa Maria C\u00e1diz 11500",
    "addr:postcode":"11500",
    "addr:street":"Plaz Ave Maria Del 3;Ca\u0301Diz",
    "iso:country":"ES",
    "sg:address":"Plaz Ave Maria (del), 3",
    "sg:city":"Puerto De Santa Maria",
    "sg:orig_category":"Iglesia Cat\u00d3lica",
    "sg:phone":"+34 956 85 09 61",
    "sg:postcode":"11500",
    "sg:province":"C\u00e1diz",
    "wof:name":"Parroquia De San Francisco",
    "wof:placetype":"venue"
},
  "geometry": {"coordinates":[-6.2197542191,36.6056632996],"type":"Point"}
}