{
  "type": "Feature",
  "properties": {
    "addr:full":"Peroleira, 32 Peroleira Pontevedra 36389",
    "addr:housenumber":"32",
    "addr:postcode":"36389",
    "addr:street":"Peroleira",
    "iso:country":"ES",
    "sg:address":"Peroleira, 32",
    "sg:city":"Peroleira",
    "sg:orig_category":"Asociaciones, Organismos Culturales Y Socioeducativos",
    "sg:phone":"+34 986 38 90 84",
    "sg:postcode":"36389",
    "sg:province":"Pontevedra",
    "wof:name":"Centro Recreativo De Peiteiros Gondomar",
    "wof:placetype":"venue"
},
  "geometry": {"coordinates":[-8.7404689789,42.1420402527],"type":"Point"}
}