{
  "type": "Feature",
  "properties": {
    "addr:full":"Calle de Mayor, 14 Villama\u00f1an Le\u00f3n 24234",
    "addr:housenumber":"14",
    "addr:postcode":"24234",
    "addr:street":"Calle De Mayor;Leo\u0301N",
    "iso:country":"ES",
    "sg:address":"Calle de Mayor, 14",
    "sg:city":"Villama\u00f1an",
    "sg:orig_category":"Caf\u00c9s, Bares, Cervecer\u00cdas",
    "sg:phone":"+34 987 76 82 12",
    "sg:postcode":"24234",
    "sg:province":"Le\u00f3n",
    "wof:name":"Tomas Martinez Maria Jose",
    "wof:placetype":"venue"
},
  "geometry": {"coordinates":[-5.5823187828,42.3222618103],"type":"Point"}
}