{
  "type": "Feature",
  "properties": {
    "iso:country":"ES",
    "sg:address":"Rua Barcelona, 45",
    "sg:city":"Vigo",
    "sg:orig_category":"M\u00c9dicos: Estomatolog\u00cda",
    "sg:phone":"+34 986 48 30 92",
    "sg:postcode":"36203",
    "sg:province":"Pontevedra",
    "wof:name":"Baima  Carmen Francisca",
    "wof:placetype":"venue"
},
  "geometry": {"coordinates":[-8.7243318558,42.2252807617],"type":"Point"}
}