{
  "type": "Feature",
  "properties": {
    "iso:country":"ES",
    "sg:address":"Almendral, 43",
    "sg:city":"Merida",
    "sg:orig_category":"Estancos",
    "sg:phone":"+34 924 31 46 20",
    "sg:postcode":"06800",
    "sg:province":"Badajoz",
    "wof:name":"Mario Alvarez Manuel",
    "wof:placetype":"venue"
},
  "geometry": {"coordinates":[-6.3442401886,38.9197921753],"type":"Point"}
}