{
  "type": "Feature",
  "properties": {
    "addr:full":"Carrer de Vallespir, 157 Barcelona Barcelona 08014",
    "addr:housenumber":"157",
    "addr:postcode":"08014",
    "addr:street":"Carrer De Vallespir",
    "iso:country":"ES",
    "sg:address":"Carrer de Vallespir, 157",
    "sg:city":"Barcelona",
    "sg:orig_category":"Maquinaria Para Industrias Diversas",
    "sg:phone":"+34 934 90 36 18",
    "sg:postcode":"08014",
    "sg:province":"Barcelona",
    "wof:name":"Puig Llobet Miguel",
    "wof:placetype":"venue"
},
  "geometry": {"coordinates":[2.1341888905,41.3834342957],"type":"Point"}
}