{
  "type": "Feature",
  "properties": {
    "iso:country":"ES",
    "sg:address":"Calle de Ventura Rodriguez / Ventura Rodriguez Kalea, 2",
    "sg:city":"Noain",
    "sg:orig_category":"Estancos",
    "sg:phone":"+34 948 31 26 78",
    "sg:postcode":"31110",
    "sg:province":"Navarra",
    "wof:name":"Lopez Ruiz De Alejos Raquel",
    "wof:placetype":"venue"
},
  "geometry": {"coordinates":[-1.6338239908,42.7598800659],"type":"Point"}
}