{
  "type": "Feature",
  "properties": {
    "addr:full":"Cami Vell Del Grau, S/n Grau I Platja Valencia 46730",
    "addr:housenumber":"s / n",
    "addr:postcode":"46730",
    "addr:street":"Cami Vell Del Grau",
    "iso:country":"ES",
    "sg:address":"Cami Vell Del Grau, S/n",
    "sg:city":"Grau I Platja",
    "sg:orig_category":"Bisuter\u00cda, Joyer\u00cda, Relojer\u00cda (al Por Menor)",
    "sg:phone":"+34 962 84 01 36",
    "sg:postcode":"46730",
    "sg:province":"Valencia",
    "wof:name":"Castillo Revenga Sergio",
    "wof:placetype":"venue"
},
  "geometry": {"coordinates":[-0.1643390059,38.992805481],"type":"Point"}
}