{
  "type": "Feature",
  "properties": {
    "addr:full":"Calle de Gonzalo Jimenez De Quesada, S/n Granada Granada 18006",
    "addr:housenumber":"s / n",
    "addr:postcode":"18006",
    "addr:street":"Calle De Gonzalo Jimenez De Quesada",
    "iso:country":"ES",
    "sg:address":"Calle de Gonzalo Jimenez De Quesada, S/n",
    "sg:city":"Granada",
    "sg:orig_category":"Transporte En General",
    "sg:phone":"+34 958 12 83 04",
    "sg:postcode":"18006",
    "sg:province":"Granada",
    "wof:name":"Quesada Ramirez Luis",
    "wof:placetype":"venue"
},
  "geometry": {"coordinates":[-3.6000769138,37.1634559631],"type":"Point"}
}