{
  "type": "Feature",
  "properties": {
    "iso:country":"ES",
    "sg:address":"Calle de Ruzafa, 9",
    "sg:city":"Valencia",
    "sg:orig_category":"Ropa Y Accesorios",
    "sg:phone":"+34 963 94 45 52",
    "sg:postcode":"46004",
    "sg:province":"Valencia",
    "wof:name":"Albert Tortosa Juan Francisco",
    "wof:placetype":"venue"
},
  "geometry": {"coordinates":[-0.3746221066,39.4665336609],"type":"Point"}
}