{
  "type": "Feature",
  "properties": {
    "addr:full":"Ctra Malaga (de), 136 Granada Granada 18015",
    "addr:housenumber":"136",
    "addr:postcode":"18015",
    "addr:street":"Ctra Malaga De",
    "iso:country":"ES",
    "sg:address":"Ctra Malaga (de), 136",
    "sg:city":"Granada",
    "sg:orig_category":"Construcciones Met\u00c1licas",
    "sg:phone":"+34 958 27 25 23",
    "sg:postcode":"18015",
    "sg:province":"Granada",
    "wof:name":"Metalisteria La Chana S.l.",
    "wof:placetype":"venue"
},
  "geometry": {"coordinates":[-3.6299889088,37.18983078],"type":"Point"}
}