{
  "type": "Feature",
  "properties": {
    "iso:country":"ES",
    "sg:address":"Avda Yecla (de), 59",
    "sg:city":"Jumilla",
    "sg:orig_category":"Mec\u00c1nico Del Autom\u00d3vil",
    "sg:phone":"+34 968 78 11 28",
    "sg:postcode":"30520",
    "sg:province":"Murcia",
    "wof:name":"T. Autoavenida S.l.",
    "wof:placetype":"venue"
},
  "geometry": {"coordinates":[-1.3216949701,38.482170105],"type":"Point"}
}