{
  "type": "Feature",
  "properties": {
    "iso:country":"ES",
    "sg:address":"Rua Progreso (do), 89",
    "sg:city":"Ourense",
    "sg:orig_category":"Seguridad Social",
    "sg:phone":"+34 988 21 17 10",
    "sg:postcode":"32003",
    "sg:province":"Ourense",
    "wof:name":"Caritas Diocesana",
    "wof:placetype":"venue"
},
  "geometry": {"coordinates":[-7.8661937714,42.3387184143],"type":"Point"}
}