{
  "type": "Feature",
  "properties": {
    "iso:country":"ES",
    "sg:address":"Avgd Antic Regne De Valencia, 28",
    "sg:city":"Quart Poblet",
    "sg:orig_category":"Electrodom\u00c9sticos (al Por Menor)",
    "sg:phone":"+34 961 54 04 80",
    "sg:postcode":"46930",
    "sg:province":"Valencia",
    "wof:name":"Martinez Lopez Nicolas",
    "wof:placetype":"venue"
},
  "geometry": {"coordinates":[-0.4387840033,39.4833183289],"type":"Point"}
}