{
  "type": "Feature",
  "properties": {
    "iso:country":"ES",
    "sg:address":"Calle de Durango, 48",
    "sg:city":"Madrid",
    "sg:orig_category":"M\u00c9dicos: Medicina Legal, Peritajes M\u00c9dicos",
    "sg:phone":"+34 913 07 69 95",
    "sg:postcode":"28023",
    "sg:province":"Madrid",
    "wof:name":"Ruiz Mialdea Victoria",
    "wof:placetype":"venue"
},
  "geometry": {"coordinates":[-3.8231470585,40.4716453552],"type":"Point"}
}