{
  "type": "Feature",
  "properties": {
    "addr:full":"Calle de Carlos I, 3 Medina Campo Valladolid 47400",
    "addr:housenumber":"3",
    "addr:postcode":"47400",
    "addr:street":"Calle De Carlos I",
    "iso:country":"ES",
    "sg:address":"Calle de Carlos I, 3",
    "sg:city":"Medina Campo",
    "sg:orig_category":"Inform\u00c1tica (estudios, Servicios, Asesor\u00cda, Formaci\u00d3n)",
    "sg:phone":"+34 983 81 25 07",
    "sg:postcode":"47400",
    "sg:province":"Valladolid",
    "sg:website":"www.tcti.es",
    "wof:name":"Infotec Ti S.l.",
    "wof:placetype":"venue"
},
  "geometry": {"coordinates":[-4.920170784,41.3088378906],"type":"Point"}
}