{
  "type": "Feature",
  "properties": {
    "iso:country":"ES",
    "sg:address":"Calle de Errementari, 2",
    "sg:city":"Mungia",
    "sg:orig_category":"Renovaci\u00d3n Inmobiliaria",
    "sg:phone":"+34 946 74 20 96",
    "sg:postcode":"48100",
    "sg:province":"Vizcaya",
    "wof:name":"Rehabilitacion Edificios Antiguos Etxezar",
    "wof:placetype":"venue"
},
  "geometry": {"coordinates":[-2.84801507,43.3550834656],"type":"Point"}
}