{
  "type": "Feature",
  "properties": {
    "addr:full":"Carr Del Trinquet De Gomis, 35 Ontinyent Valencia 46870",
    "addr:housenumber":"35",
    "addr:postcode":"46870",
    "addr:street":"Carr Del Trinquet De Gomis",
    "iso:country":"ES",
    "sg:address":"Carr Del Trinquet De Gomis, 35",
    "sg:city":"Ontinyent",
    "sg:orig_category":"M\u00c1rmoles, Granitos Y Piedras Naturales",
    "sg:phone":"+34 962 38 21 39",
    "sg:postcode":"46870",
    "sg:province":"Valencia",
    "wof:name":"Belda Reig Juan",
    "wof:placetype":"venue"
},
  "geometry": {"coordinates":[-0.6030989885,38.8258895874],"type":"Point"}
}