{
  "type": "Feature",
  "properties": {
    "iso:country":"ES",
    "sg:address":"Carrer de Iberia, 16",
    "sg:city":"Hospitalet Llobregat",
    "sg:orig_category":"Reposter\u00cdas",
    "sg:phone":"+34 934 37 05 78",
    "sg:postcode":"08906",
    "sg:province":"Barcelona",
    "wof:name":"Forn De Pa Iberia S. A.",
    "wof:placetype":"venue"
},
  "geometry": {"coordinates":[2.1043550968,41.3731689453],"type":"Point"}
}