{
  "type": "Feature",
  "properties": {
    "addr:full":"Carr Jorge Juan, 57 Burjassot Valencia 46100",
    "addr:housenumber":"57",
    "addr:postcode":"46100",
    "addr:street":"Carr Jorge Juan",
    "iso:country":"ES",
    "sg:address":"Carr Jorge Juan, 57",
    "sg:city":"Burjassot",
    "sg:orig_category":"Empresas De Limpieza",
    "sg:phone":"+34 963 63 15 20",
    "sg:postcode":"46100",
    "sg:province":"Valencia",
    "wof:name":"Pe\u00d1arrocha Abad Vicente",
    "wof:placetype":"venue"
},
  "geometry": {"coordinates":[-0.4090259969,39.5073127747],"type":"Point"}
}