{
  "type": "Feature",
  "properties": {
    "addr:full":"Calle de Libertad (de La), 64 Navalcarnero Madrid 28600",
    "addr:housenumber":"64",
    "addr:postcode":"28600",
    "addr:street":"Calle De Libertad De La",
    "iso:country":"ES",
    "sg:address":"Calle de Libertad (de La), 64",
    "sg:city":"Navalcarnero",
    "sg:orig_category":"Art\u00cdculos De Decoraci\u00d3n",
    "sg:phone":"+34 918 11 24 97",
    "sg:postcode":"28600",
    "sg:province":"Madrid",
    "wof:name":"Decoraciones Zafiro S.l.",
    "wof:placetype":"venue"
},
  "geometry": {"coordinates":[-4.0131411552,40.2904014587],"type":"Point"}
}