{
  "type": "Feature",
  "properties": {
    "addr:full":"Carrer de Guillem Forteza, 8 Palma Islas Baleares 07010",
    "addr:housenumber":"8",
    "addr:postcode":"07010",
    "addr:street":"Carrer De Guillem Forteza",
    "iso:country":"ES",
    "sg:address":"Carrer de Guillem Forteza, 8",
    "sg:city":"Palma",
    "sg:orig_category":"Mec\u00c1nico Del Autom\u00d3vil",
    "sg:phone":"+34 971 29 88 05",
    "sg:postcode":"07010",
    "sg:province":"Islas Baleares",
    "wof:name":"Taller Joan Uvi\u00f1a S.l.",
    "wof:placetype":"venue"
},
  "geometry": {"coordinates":[2.6461179256,39.5873832703],"type":"Point"}
}