{
  "type": "Feature",
  "properties": {
    "addr:full":"Calle de Doctor Ruiz Jimenez, 7 Malaga M\u00e1laga 29010",
    "addr:housenumber":"7",
    "addr:postcode":"29010",
    "addr:street":"Calle De Doctor Ruiz Jimenez;Ma\u0301Laga",
    "iso:country":"ES",
    "sg:address":"Calle de Doctor Ruiz Jimenez, 7",
    "sg:city":"Malaga",
    "sg:orig_category":"Grabados",
    "sg:phone":"+34 952 27 12 54",
    "sg:postcode":"29010",
    "sg:province":"M\u00e1laga",
    "wof:name":"Romero Garcia Elena",
    "wof:placetype":"venue"
},
  "geometry": {"coordinates":[-4.4415669441,36.7225914001],"type":"Point"}
}