{
  "type": "Feature",
  "properties": {
    "iso:country":"ES",
    "sg:address":"Calle de Blasco, 7",
    "sg:city":"Alca\u00f1iz",
    "sg:orig_category":"Muebles",
    "sg:phone":"+34 978 83 13 56",
    "sg:postcode":"44600",
    "sg:province":"Teruel",
    "wof:name":"Milian Esteban Carmen",
    "wof:placetype":"venue"
},
  "geometry": {"coordinates":[-0.1310532987,41.0509223938],"type":"Point"}
}