{
  "type": "Feature",
  "properties": {
    "iso:country":"ES",
    "sg:address":"Ctra. Sagunto Burgos, S/n",
    "sg:city":"Calatayud",
    "sg:orig_category":"Centros De Educaci\u00d3n Especial",
    "sg:phone":"+34 976 88 16 52",
    "sg:postcode":"50300",
    "sg:province":"Zaragoza",
    "wof:name":"Colegio Publico Baltasar Gracian",
    "wof:placetype":"venue"
},
  "geometry": {"coordinates":[-1.6394540071,41.3522415161],"type":"Point"}
}