{
  "type": "Feature",
  "properties": {
    "addr:full":"Plaz Merced, 5 Azuaga Badajoz 06920",
    "addr:housenumber":"5",
    "addr:postcode":"06920",
    "addr:street":"Plaz Merced",
    "iso:country":"ES",
    "sg:address":"Plaz Merced, 5",
    "sg:city":"Azuaga",
    "sg:orig_category":"Arquitectos",
    "sg:phone":"+34 924 89 21 04",
    "sg:postcode":"06920",
    "sg:province":"Badajoz",
    "wof:name":"Duran Navarro Victoriano",
    "wof:placetype":"venue"
},
  "geometry": {"coordinates":[-5.6749858856,38.2585334778],"type":"Point"}
}