{
  "type": "Feature",
  "properties": {
    "iso:country":"ES",
    "sg:address":"Praz Espa\u00d1a, 3",
    "sg:city":"Pontevedra",
    "sg:orig_category":"Abogados",
    "sg:phone":"+34 986 84 22 24",
    "sg:postcode":"36002",
    "sg:province":"Pontevedra",
    "wof:name":"Fari\u00f1a Lopez Blanca",
    "wof:placetype":"venue"
},
  "geometry": {"coordinates":[-8.6233987808,42.4448699951],"type":"Point"}
}