{
  "type": "Feature",
  "properties": {
    "iso:country":"ES",
    "sg:address":"Calle de Sacedon, 2",
    "sg:city":"Guadalajara",
    "sg:orig_category":"Supermercados Y Hipermercados",
    "sg:phone":"+34 949 21 79 07",
    "sg:postcode":"19002",
    "sg:province":"Guadalajara",
    "wof:name":"Madrile\u00f1a De Negocios S.a.",
    "wof:placetype":"venue"
},
  "geometry": {"coordinates":[-3.1701569557,40.6263694763],"type":"Point"}
}