{
  "type": "Feature",
  "properties": {
    "iso:country":"ES",
    "sg:address":"Calle de Madre Petra, 6",
    "sg:city":"Valle Abdalajis",
    "sg:orig_category":"Asilos De Ancianos. Centros Privados",
    "sg:phone":"+34 952 48 90 72",
    "sg:postcode":"29240",
    "sg:province":"M\u00e1laga",
    "wof:name":"Madres De Los Desamparados Y De San Jose De La Monta\u00f1a",
    "wof:placetype":"venue"
},
  "geometry": {"coordinates":[-4.6803431511,36.9339485168],"type":"Point"}
}