{
  "type": "Feature",
  "properties": {
    "addr:full":"Trav De Gracia, 163 Barcelona Barcelona 08012",
    "addr:housenumber":"163",
    "addr:postcode":"08012",
    "addr:street":"Trav De Gracia",
    "iso:country":"ES",
    "sg:address":"Trav De Gracia, 163",
    "sg:city":"Barcelona",
    "sg:orig_category":"Complementos De Vestir (al Por Menor)",
    "sg:phone":"+34 932 17 88 87",
    "sg:postcode":"08012",
    "sg:province":"Barcelona",
    "wof:name":"Mu\u00f1oz Argueta Sergio",
    "wof:placetype":"venue"
},
  "geometry": {"coordinates":[2.1575899124,41.401309967],"type":"Point"}
}