{
  "type": "Feature",
  "properties": {
    "iso:country":"ES",
    "sg:address":"Carretera, 3",
    "sg:city":"Pueblica De Valverde",
    "sg:orig_category":"Organizaci\u00d3n De Actos, Seminarios Y Congresos",
    "sg:phone":"+34 980 65 90 05",
    "sg:postcode":"49697",
    "sg:province":"Zamora",
    "wof:name":"Furones Llamas Acelino",
    "wof:placetype":"venue"
},
  "geometry": {"coordinates":[-5.8178601265,41.9535713196],"type":"Point"}
}