{
  "type": "Feature",
  "properties": {
    "addr:full":"Calle de Moreno De Pedrajas, 13 Villanueva Cordoba C\u00f3rdoba 14440",
    "addr:housenumber":"13;cordoba co\u0301rdoba",
    "addr:postcode":"14440",
    "addr:street":"Calle De Moreno;Pedrajas",
    "iso:country":"ES",
    "sg:address":"Calle de Moreno De Pedrajas, 13",
    "sg:city":"Villanueva Cordoba",
    "sg:classifiers":[
        {
            "category":"Autos & Motor Vehicles",
            "subcategory":"Automobile Sales",
            "type":"Retail Goods"
        }
    ],
    "sg:phone":"+34 957 12 04 00",
    "sg:postcode":"14440",
    "sg:province":"C\u00f3rdoba",
    "wof:name":"Garcia Higuera Juan Antonio",
    "wof:placetype":"venue"
},
  "geometry": {"coordinates":[-4.6293058395,38.3199806213],"type":"Point"}
}