{
  "type": "Feature",
  "properties": {
    "addr:full":"Calle de Santa Lucia, 1 Laracha La Coru\u00f1a 15145",
    "addr:housenumber":"1",
    "addr:postcode":"15145",
    "addr:street":"Calle De Santa Lucia;La Corun\u0303A",
    "iso:country":"ES",
    "sg:address":"Calle de Santa Lucia, 1",
    "sg:city":"Laracha",
    "sg:orig_category":"Farmacias",
    "sg:phone":"+34 981 60 55 91",
    "sg:postcode":"15145",
    "sg:province":"La Coru\u00f1a",
    "wof:name":"Astray Troche Valentina",
    "wof:placetype":"venue"
},
  "geometry": {"coordinates":[-8.5864372253,43.2475776672],"type":"Point"}
}