{
  "type": "Feature",
  "properties": {
    "iso:country":"ES",
    "sg:address":"Av Caritat Serinyana, 17",
    "sg:city":"Cadaques",
    "sg:orig_category":"Empresas De Labores Complejas De Carga Y Descarga, Montaje Con Elevadores",
    "sg:phone":"+34 972 25 88 76",
    "sg:postcode":"17488",
    "sg:province":"Girona",
    "wof:name":"Dive Creus Sotamar S.l.",
    "wof:placetype":"venue"
},
  "geometry": {"coordinates":[3.2753629684,42.2899360657],"type":"Point"}
}