{
  "type": "Feature",
  "properties": {
    "iso:country":"ES",
    "sg:address":"Carrer de Sant Sebastia, 229",
    "sg:city":"Terrassa",
    "sg:orig_category":"Limpieza Industrial",
    "sg:phone":"+34 937 31 74 77",
    "sg:postcode":"08223",
    "sg:province":"Barcelona",
    "wof:name":"Artcofil S.l.",
    "wof:placetype":"venue"
},
  "geometry": {"coordinates":[2.0109872818,41.5550079346],"type":"Point"}
}