{
  "type": "Feature",
  "properties": {
    "iso:country":"ES",
    "sg:address":"Carr Riu Vinalopo, 106",
    "sg:city":"Pai I Capellans",
    "sg:orig_category":"Negocio De Materiales De Construcci\u00d3n",
    "sg:phone":"+34 961 57 90 34",
    "sg:postcode":"46930",
    "sg:province":"Valencia",
    "wof:name":"Materiales De Construccion Esmo S.l.",
    "wof:placetype":"venue"
},
  "geometry": {"coordinates":[-0.4419890046,39.482711792],"type":"Point"}
}