{
  "type": "Feature",
  "properties": {
    "iso:country":"ES",
    "sg:address":"Calle de Manuel Hermosilla, 7",
    "sg:city":"Puerto De Santa Maria",
    "sg:orig_category":"Mec\u00c1nico Del Autom\u00d3vil",
    "sg:phone":"+34 956 87 66 04",
    "sg:postcode":"11500",
    "sg:province":"C\u00e1diz",
    "wof:name":"Guelfo Mora Jose Luis",
    "wof:placetype":"venue"
},
  "geometry": {"coordinates":[-6.2360429764,36.5957794189],"type":"Point"}
}