{
  "type": "Feature",
  "properties": {
    "addr:full":"Calle de Finisterre (de), 3 Humanes De Madrid Madrid 28970",
    "addr:postcode":"28970",
    "addr:street":"Calle De Finisterre De 3",
    "iso:country":"ES",
    "sg:address":"Calle de Finisterre (de), 3",
    "sg:city":"Humanes De Madrid",
    "sg:orig_category":"Centros Empresariales",
    "sg:phone":"+34 916 04 10 36",
    "sg:postcode":"28970",
    "sg:province":"Madrid",
    "wof:name":"Arquibasic S.l.",
    "wof:placetype":"venue"
},
  "geometry": {"coordinates":[-3.8197729588,40.2604179382],"type":"Point"}
}