{
  "type": "Feature",
  "properties": {
    "iso:country":"ES",
    "sg:address":"Psaj Gutierrez Ortega, 2",
    "sg:city":"Ciudad Real",
    "sg:orig_category":"El Hogar: Amueblado, Acondicionamiento, Decoraci\u00d3n Y Mantenimiento",
    "sg:phone":"+34 926 21 03 27",
    "sg:postcode":"13001",
    "sg:province":"Ciudad Real",
    "wof:name":"Alberdi Bellon Miguel Angel",
    "wof:placetype":"venue"
},
  "geometry": {"coordinates":[-3.9296827316,38.9832305908],"type":"Point"}
}