{
  "type": "Feature",
  "properties": {
    "iso:country":"ES",
    "sg:address":"Calle de Mayor, 104",
    "sg:city":"Puente Tocinos",
    "sg:orig_category":"Farmacias",
    "sg:phone":"+34 968 30 18 80",
    "sg:postcode":"30006",
    "sg:province":"Murcia",
    "wof:name":"Carazo Fernandez Antonio",
    "wof:placetype":"venue"
},
  "geometry": {"coordinates":[-1.10136199,37.9936943054],"type":"Point"}
}