{
  "type": "Feature",
  "properties": {
    "iso:country":"ES",
    "sg:address":"S. Mart\u00edn, 2",
    "sg:city":"Mucientes",
    "sg:orig_category":"Carnicer\u00cdas, Carnicer\u00cdas",
    "sg:phone":"+34 983 58 77 02",
    "sg:postcode":"47194",
    "sg:province":"Valladolid",
    "wof:name":"Pinacho Centeno Aurelio",
    "wof:placetype":"venue"
},
  "geometry": {"coordinates":[-4.7640891075,41.7066612244],"type":"Point"}
}