{
  "type": "Feature",
  "properties": {
    "addr:full":"Calle de Emilio Castelar, 82 Novelda Alicante 03660",
    "addr:housenumber":"82",
    "addr:postcode":"03660",
    "addr:street":"Calle De Emilio Castelar",
    "iso:country":"ES",
    "sg:address":"Calle de Emilio Castelar, 82",
    "sg:city":"Novelda",
    "sg:orig_category":"Farmacias",
    "sg:phone":"+34 965 60 06 90",
    "sg:postcode":"03660",
    "sg:province":"Alicante",
    "wof:name":"Rio Salanova Juan Javier",
    "wof:placetype":"venue"
},
  "geometry": {"coordinates":[-0.7682579756,38.384601593],"type":"Point"}
}