{
  "type": "Feature",
  "properties": {
    "iso:country":"ES",
    "sg:address":"Ego-gain Kalea, 4",
    "sg:city":"Eibar",
    "sg:orig_category":"T\u00c9cnicos Veterinarios",
    "sg:phone":"+34 943 20 21 53",
    "sg:postcode":"20600",
    "sg:province":"Guip\u00f9zcoa",
    "wof:name":"Centro Veterinario Ego-gain S.l.",
    "wof:placetype":"venue"
},
  "geometry": {"coordinates":[-2.4741539955,43.1840858459],"type":"Point"}
}