{
  "type": "Feature",
  "properties": {
    "addr:full":"Mercado Barr. Hogar, S/n Albacete Albacete 02004",
    "addr:housenumber":"/ n",
    "addr:postcode":"02004",
    "addr:street":"S",
    "iso:country":"ES",
    "sg:address":"Mercado Barr. Hogar, S/n",
    "sg:city":"Albacete",
    "sg:orig_category":"Pescader\u00cdas (al Por Menor)",
    "sg:phone":"+34 967 23 72 99",
    "sg:postcode":"02004",
    "sg:province":"Albacete",
    "wof:name":"Picazo Cuesta Angel",
    "wof:placetype":"venue"
},
  "geometry": {"coordinates":[-1.8540610075,38.9950675964],"type":"Point"}
}