{
  "type": "Feature",
  "properties": {
    "iso:country":"ES",
    "sg:address":"Ctra N-152, Km. 0021,0",
    "sg:city":"Can Gosc",
    "sg:orig_category":"Laboratorios Farmac\u00c9uticos",
    "sg:phone":"+34 935 73 10 52",
    "sg:postcode":"08150",
    "sg:province":"Barcelona",
    "wof:name":"Grifols S.a.",
    "wof:placetype":"venue"
},
  "geometry": {"coordinates":[2.2319469452,41.5694198608],"type":"Point"}
}