{
  "type": "Feature",
  "properties": {
    "iso:country":"ES",
    "sg:address":"Avgd Sucro, 2",
    "sg:city":"Alzira",
    "sg:orig_category":"Comercio De Piezas De Recambio Y De Accesorios De Veh\u00cdculos, Veh\u00cdculos Industriales",
    "sg:phone":"+34 962 41 05 34",
    "sg:postcode":"46600",
    "sg:province":"Valencia",
    "wof:name":"Sucesores De Constantino Simon S. L.",
    "wof:placetype":"venue"
},
  "geometry": {"coordinates":[-0.4379369915,39.1499061584],"type":"Point"}
}