{
  "type": "Feature",
  "properties": {
    "addr:full":"Avgd Garrigues, 66 Lleida Lleida 25001",
    "addr:housenumber":"66",
    "addr:postcode":"25001",
    "iso:country":"ES",
    "sg:address":"Avgd Garrigues, 66",
    "sg:city":"Lleida",
    "sg:orig_category":"Sociedades, Compa\u00d1\u00cdas Aseguradoras",
    "sg:phone":"+34 973 21 25 85",
    "sg:postcode":"25001",
    "sg:province":"Lleida",
    "wof:name":"Lega-mur Correduria De Seguros S.l.",
    "wof:placetype":"venue"
},
  "geometry": {"coordinates":[0.6339179873,41.6095695496],"type":"Point"}
}