{
  "type": "Feature",
  "properties": {
    "addr:full":"Avgd Hispanitat, 5 Alzira Valencia 46600",
    "addr:housenumber":"5",
    "addr:postcode":"46600",
    "addr:street":"Hispanitat",
    "iso:country":"ES",
    "sg:address":"Avgd Hispanitat, 5",
    "sg:city":"Alzira",
    "sg:orig_category":"Sociedades, Compa\u00d1\u00cdas Aseguradoras",
    "sg:phone":"+34 962 40 14 34",
    "sg:postcode":"46600",
    "sg:province":"Valencia",
    "wof:name":"Santa Lucia S.a.",
    "wof:placetype":"venue"
},
  "geometry": {"coordinates":[-0.439752996,39.1488075256],"type":"Point"}
}