{
  "type": "Feature",
  "properties": {
    "addr:full":"Calle de Doctor Gil Y Morte, 17 Valencia Valencia 46007",
    "addr:housenumber":"17",
    "addr:postcode":"46007",
    "addr:street":"Calle De Doctor Gil Y Morte",
    "iso:country":"ES",
    "sg:address":"Calle de Doctor Gil Y Morte, 17",
    "sg:city":"Valencia",
    "sg:orig_category":"Doctores En Medicina",
    "sg:phone":"+34 963 41 10 94",
    "sg:postcode":"46007",
    "sg:province":"Valencia",
    "wof:name":"Hernandez Benhamou Maria Del Mar",
    "wof:placetype":"venue"
},
  "geometry": {"coordinates":[-0.3806765079,39.4621658325],"type":"Point"}
}