{
  "type": "Feature",
  "properties": {
    "addr:full":"Calle de Virgen De Criptana, 27 Campo Criptana Ciudad Real 13610",
    "addr:housenumber":"27",
    "addr:postcode":"13610",
    "addr:street":"Calle De Virgen De Criptana;Criptana",
    "iso:country":"ES",
    "sg:address":"Calle de Virgen De Criptana, 27",
    "sg:city":"Campo Criptana",
    "sg:orig_category":"Agencias De Viajes",
    "sg:phone":"+34 926 56 18 84",
    "sg:postcode":"13610",
    "sg:province":"Ciudad Real",
    "wof:name":"Alces Travel S.l.",
    "wof:placetype":"venue"
},
  "geometry": {"coordinates":[-3.1227762699,39.4055595398],"type":"Point"}
}