{
  "type": "Feature",
  "properties": {
    "addr:full":"Carr Sant Anastasi, 18 Badalona Barcelona 08911",
    "addr:housenumber":"18",
    "addr:postcode":"08911",
    "addr:street":"Carr Sant Anastasi",
    "iso:country":"ES",
    "sg:address":"Carr Sant Anastasi, 18",
    "sg:city":"Badalona",
    "sg:orig_category":"Ropa Para Ni\u00d1os (al Por Menor)",
    "sg:phone":"+34 933 84 25 51",
    "sg:postcode":"08911",
    "sg:province":"Barcelona",
    "wof:name":"Li  Yun",
    "wof:placetype":"venue"
},
  "geometry": {"coordinates":[2.2470929623,41.4506721497],"type":"Point"}
}