{
  "type": "Feature",
  "properties": {
    "iso:country":"ES",
    "sg:address":"Calle de San Juan Bosco, 37",
    "sg:city":"Sevilla",
    "sg:orig_category":"Pod\u00d3logos: Pedicuros",
    "sg:phone":"+34 954 54 15 29",
    "sg:postcode":"41008",
    "sg:province":"Sevilla",
    "wof:name":"Torres Perez Manuel",
    "wof:placetype":"venue"
},
  "geometry": {"coordinates":[-5.9777989388,37.396030426],"type":"Point"}
}