{
  "type": "Feature",
  "properties": {
    "addr:full":"Calle de Gran Via, 25 Madrid Madrid 28013",
    "addr:housenumber":"25",
    "addr:postcode":"madrid;28013",
    "addr:street":"Calle De Gran Via",
    "iso:country":"ES",
    "sg:address":"Calle de Gran Via, 25",
    "sg:city":"Madrid",
    "sg:orig_category":"Parques De Atracciones Y Centros De Esparcimiento",
    "sg:phone":"+34 915 31 68 14",
    "sg:postcode":"28013",
    "sg:province":"Madrid",
    "wof:name":"J R 25 S. A.",
    "wof:placetype":"venue"
},
  "geometry": {"coordinates":[-3.7031860352,40.4200057983],"type":"Point"}
}