{
  "type": "Feature",
  "properties": {
    "iso:country":"ES",
    "sg:address":"Carrer de Bartomeu Sureda Mi, 5",
    "sg:city":"Vileta -son Rapinya",
    "sg:classifiers":[
        {
            "category":"Autos & Motor Vehicles",
            "subcategory":"Automobile Sales",
            "type":"Retail Goods"
        }
    ],
    "sg:phone":"+34 971 60 68 92",
    "sg:postcode":"07013",
    "sg:province":"Islas Baleares",
    "wof:name":"Autoscola Kalet S.l.",
    "wof:placetype":"venue"
},
  "geometry": {"coordinates":[2.6230180264,39.5879669189],"type":"Point"}
}