{
  "type": "Feature",
  "properties": {
    "addr:full":"Calle de Doctor Jose Ponce Arias, 3 Palmas De Gran Canaria Las Palmas 35005",
    "addr:housenumber":"3",
    "addr:postcode":"35005",
    "addr:street":"Calle De Doctor Jose Ponce Arias",
    "iso:country":"ES",
    "sg:address":"Calle de Doctor Jose Ponce Arias, 3",
    "sg:city":"Palmas De Gran Canaria",
    "sg:orig_category":"Centros De Educaci\u00d3n Especial",
    "sg:phone":"+34 928 24 17 23",
    "sg:postcode":"35005",
    "sg:province":"Las Palmas",
    "wof:name":"Bethencourt Mateos Maria Pilar",
    "wof:placetype":"venue"
},
  "geometry": {"coordinates":[-15.4305763245,28.1288642883],"type":"Point"}
}