{
  "type": "Feature",
  "properties": {
    "iso:country":"ES",
    "sg:address":"Calle de San Bernardo, 39",
    "sg:city":"Madrid",
    "sg:orig_category":"Farmacias",
    "sg:phone":"+34 915 42 09 13",
    "sg:postcode":"28015",
    "sg:province":"Madrid",
    "wof:name":"Deleuze Isasi Alberto",
    "wof:placetype":"venue"
},
  "geometry": {"coordinates":[-3.7076289654,40.4236297607],"type":"Point"}
}