{
  "type": "Feature",
  "properties": {
    "iso:country":"ES",
    "sg:address":"Calle de Hilarion Eslava, 29",
    "sg:city":"Burlada",
    "sg:orig_category":"Pescader\u00cdas (al Por Menor)",
    "sg:phone":"+34 948 23 68 86",
    "sg:postcode":"31600",
    "sg:province":"Navarra",
    "wof:name":"Uterga Berasain Aracely",
    "wof:placetype":"venue"
},
  "geometry": {"coordinates":[-1.6137980223,42.8236923218],"type":"Point"}
}