{
  "type": "Feature",
  "properties": {
    "iso:country":"ES",
    "sg:address":"Urb Pinar De Don Jesus, S/n",
    "sg:city":"Barrosa",
    "sg:orig_category":"Reposter\u00cdas",
    "sg:phone":"+34 956 49 64 32",
    "sg:postcode":"11130",
    "sg:province":"C\u00e1diz",
    "wof:name":"Panaderia La Barrosa S.l.",
    "wof:placetype":"venue"
},
  "geometry": {"coordinates":[-6.1447038651,36.4212188721],"type":"Point"}
}