{
  "type": "Feature",
  "properties": {
    "iso:country":"ES",
    "sg:address":"Avda Espa\u00d1a, 31",
    "sg:city":"Majadahonda",
    "sg:orig_category":"Cuidado Del Cabello",
    "sg:phone":"+34 916 34 24 48",
    "sg:postcode":"28220",
    "sg:province":"Madrid",
    "sg:website":"www.centrocapilarmarianogarcia.com",
    "wof:name":"Centro Capilar Mariano Garcia S.l.",
    "wof:placetype":"venue"
},
  "geometry": {"coordinates":[-3.8678328991,40.4718933105],"type":"Point"}
}