{
  "type": "Feature",
  "properties": {
    "addr:full":"Virgen Del Puy, 6 Iru\u00f1a Navarra 31011",
    "addr:housenumber":"6",
    "addr:postcode":"31011",
    "addr:street":"Virgen;Puy",
    "iso:country":"ES",
    "sg:address":"Virgen Del Puy, 6",
    "sg:city":"Iru\u00f1a",
    "sg:orig_category":"Art\u00cdculos De Regalo (al Por Menor)",
    "sg:phone":"+34 948 17 52 94",
    "sg:postcode":"31011",
    "sg:province":"Navarra",
    "wof:name":"Zalba Gaston Juan Antonio",
    "wof:placetype":"venue"
},
  "geometry": {"coordinates":[-1.6597594023,42.8166122437],"type":"Point"}
}