{
  "type": "Feature",
  "properties": {
    "iso:country":"ES",
    "sg:address":"Calle de Libertad, 11",
    "sg:city":"Manzanares",
    "sg:orig_category":"Electrodom\u00c9sticos (al Por Menor)",
    "sg:phone":"+34 926 62 05 50",
    "sg:postcode":"13200",
    "sg:province":"Ciudad Real",
    "wof:name":"Molina Hurtado Jose Maria",
    "wof:placetype":"venue"
},
  "geometry": {"coordinates":[-3.3689172268,39.0013160706],"type":"Point"}
}