{
  "type": "Feature",
  "properties": {
    "addr:full":"Calle de Rioja, 71 Leganes Madrid 28915",
    "addr:housenumber":"71",
    "addr:postcode":"28915",
    "addr:street":"Calle De Rioja",
    "iso:country":"ES",
    "sg:address":"Calle de Rioja, 71",
    "sg:city":"Leganes",
    "sg:orig_category":"Electricidad: Instaladores",
    "sg:phone":"+34 916 80 93 13",
    "sg:postcode":"28915",
    "sg:province":"Madrid",
    "wof:name":"Montajes Rubelux S.l.",
    "wof:placetype":"venue"
},
  "geometry": {"coordinates":[-3.7554740906,40.33020401],"type":"Point"}
}