{
  "type": "Feature",
  "properties": {
    "iso:country":"ES",
    "sg:address":"Rbla Lluis Companys, 5",
    "sg:city":"Vilanova I La Geltru",
    "sg:orig_category":"Centros M\u00c9dicos Y Sociales, Dispensarios",
    "sg:phone":"+34 938 15 54 28",
    "sg:postcode":"08800",
    "sg:province":"Barcelona",
    "wof:name":"Delmas Lillo Gerardo",
    "wof:placetype":"venue"
},
  "geometry": {"coordinates":[1.7250820398,41.2153701782],"type":"Point"}
}