{
  "type": "Feature",
  "properties": {
    "iso:country":"ES",
    "sg:address":"Calle de Camino Del Cura, 8",
    "sg:city":"Alcobendas",
    "sg:orig_category":"Centros De Educaci\u00d3n Especial",
    "sg:phone":"+34 916 25 24 01",
    "sg:postcode":"28109",
    "sg:province":"Madrid",
    "sg:website":"www.laescuelitadelencinar.com",
    "wof:name":"Arcos",
    "wof:placetype":"venue"
},
  "geometry": {"coordinates":[-3.6356260777,40.5082321167],"type":"Point"}
}