{
  "type": "Feature",
  "properties": {
    "iso:country":"ES",
    "sg:address":"Avda Dionisio Cifuentes De, S/n",
    "sg:city":"Gijon",
    "sg:orig_category":"Caf\u00c9s, Bares, Cervecer\u00cdas",
    "sg:phone":"+34 985 36 69 50",
    "sg:postcode":"33203",
    "sg:province":"Asturias",
    "wof:name":"Caso Gonzalez Maria Jesus Esther",
    "wof:placetype":"venue"
},
  "geometry": {"coordinates":[-5.6222920418,43.5364685059],"type":"Point"}
}