{
  "type": "Feature",
  "properties": {
    "iso:country":"ES",
    "sg:address":"Carr Berenguer Carnicer, 2",
    "sg:city":"Girona",
    "sg:orig_category":"Abogados",
    "sg:phone":"+34 972 20 82 00",
    "sg:postcode":"17001",
    "sg:province":"Girona",
    "wof:name":"Oliver Codina Jordi",
    "wof:placetype":"venue"
},
  "geometry": {"coordinates":[2.8225109577,41.9873313904],"type":"Point"}
}