{
  "type": "Feature",
  "properties": {
    "iso:country":"ES",
    "sg:address":"Calle de Camelia, 50",
    "sg:city":"Zaragoza",
    "sg:orig_category":"Fiesta: Art\u00cdculos De (al Por Menor)",
    "sg:phone":"+34 976 75 96 96",
    "sg:postcode":"50012",
    "sg:province":"Zaragoza",
    "wof:name":"Productos Fiesta S. A.",
    "wof:placetype":"venue"
},
  "geometry": {"coordinates":[-0.9262741208,41.6407203674],"type":"Point"}
}