{
  "type": "Feature",
  "properties": {
    "addr:full":"Carrer de Santa Joana D'arc, 43 Barcelona Barcelona 08032",
    "addr:housenumber":"43",
    "addr:postcode":"08032",
    "addr:street":"Carrer De Santa Joana D'Arc",
    "iso:country":"ES",
    "sg:address":"Carrer de Santa Joana D'arc, 43",
    "sg:city":"Barcelona",
    "sg:orig_category":"Empresas De Limpieza",
    "sg:phone":"+34 934 46 00 82",
    "sg:postcode":"08032",
    "sg:province":"Barcelona",
    "wof:name":"Limpiezas Del Hogar Econet S.l.",
    "wof:placetype":"venue"
},
  "geometry": {"coordinates":[2.158367157,41.4288825989],"type":"Point"}
}