{
  "type": "Feature",
  "properties": {
    "addr:full":"Calle de Marques De Nervion, 116 Sevilla Sevilla 41005",
    "addr:housenumber":"116",
    "addr:postcode":"41005",
    "addr:street":"Calle De Marques De Nervion",
    "iso:country":"ES",
    "sg:address":"Calle de Marques De Nervion, 116",
    "sg:city":"Sevilla",
    "sg:orig_category":"Promotores Constructores",
    "sg:phone":"+34 954 93 21 37",
    "sg:postcode":"41005",
    "sg:province":"Sevilla",
    "wof:name":"Ingenieria Global S.l.",
    "wof:placetype":"venue"
},
  "geometry": {"coordinates":[-5.9642291069,37.3813362122],"type":"Point"}
}