{
  "type": "Feature",
  "properties": {
    "iso:country":"ES",
    "sg:address":"Gta Marife De Triana, S/n",
    "sg:city":"Arroyo De La Miel-benalmadena Costa",
    "sg:orig_category":"Ense\u00d1anza, Formaci\u00d3n Profesional: Aprendizaje",
    "sg:phone":"+34 952 56 06 75",
    "sg:postcode":"29631",
    "sg:province":"M\u00e1laga",
    "wof:name":"Ayuntamiento De Benalmadena",
    "wof:placetype":"venue"
},
  "geometry": {"coordinates":[-4.5482521057,36.6017608643],"type":"Point"}
}