{
  "type": "Feature",
  "properties": {
    "addr:full":"Avda Primero De Mayo, 32 Palmas De Gran Canaria Las Palmas 35002",
    "addr:postcode":"35002",
    "addr:street":"Avda Primero De Mayo 32",
    "iso:country":"ES",
    "sg:address":"Avda Primero De Mayo, 32",
    "sg:city":"Palmas De Gran Canaria",
    "sg:orig_category":"Agencias Y Agentes Comerciales, Representantes",
    "sg:phone":"+34 928 38 50 08",
    "sg:postcode":"35002",
    "sg:province":"Las Palmas",
    "wof:name":"Garcia Gomez Carmelo",
    "wof:placetype":"venue"
},
  "geometry": {"coordinates":[-15.419262886,28.1050300598],"type":"Point"}
}