{
  "type": "Feature",
  "properties": {
    "iso:country":"ES",
    "sg:address":"Calle de General Prim, 47",
    "sg:city":"Alcala Guadaira",
    "sg:orig_category":"Delegados, Agentes De Tr\u00c1nsito, Auxiliares De Transporte Internacional",
    "sg:phone":"+34 955 62 70 32",
    "sg:postcode":"41500",
    "sg:province":"Sevilla",
    "wof:name":"Mensajeria Alcala Bort S.l.",
    "wof:placetype":"venue"
},
  "geometry": {"coordinates":[-5.8385357857,37.3444786072],"type":"Point"}
}