{
  "type": "Feature",
  "properties": {
    "iso:country":"ES",
    "sg:address":"Avda Islas Canarias, S/n",
    "sg:city":"Costa Teguise",
    "sg:orig_category":"M\u00c9dicos: Estomatolog\u00cda",
    "sg:phone":"+34 928 59 00 23",
    "sg:postcode":"35509",
    "sg:province":"Las Palmas",
    "wof:name":"Odontoestoma De Lanzarote S.l.",
    "wof:placetype":"venue"
},
  "geometry": {"coordinates":[-13.5916891098,28.955160141],"type":"Point"}
}