{
  "type": "Feature",
  "properties": {
    "iso:country":"ES",
    "sg:address":"Calle de Comercio, 41",
    "sg:city":"Rincon Victoria",
    "sg:orig_category":"Agencias Y Agentes Comerciales, Representantes",
    "sg:phone":"+34 952 97 82 60",
    "sg:postcode":"29730",
    "sg:province":"M\u00e1laga",
    "wof:name":"Lopez Ramirez Fco. 000398205a S.l.n.e.",
    "wof:placetype":"venue"
},
  "geometry": {"coordinates":[-4.284717083,36.7160987854],"type":"Point"}
}