{
  "type": "Feature",
  "properties": {
    "addr:full":"Rbla Rambla, 26 Sabadell Barcelona 08201",
    "addr:housenumber":"26",
    "addr:postcode":"08201",
    "addr:street":"Rambla",
    "iso:country":"ES",
    "sg:address":"Rbla Rambla, 26",
    "sg:city":"Sabadell",
    "sg:orig_category":"Farmacias",
    "sg:phone":"+34 937 25 73 19",
    "sg:postcode":"08201",
    "sg:province":"Barcelona",
    "wof:name":"Segalas Carreras Maria Mercedes",
    "wof:placetype":"venue"
},
  "geometry": {"coordinates":[2.1095299721,41.5454063416],"type":"Point"}
}