{
  "type": "Feature",
  "properties": {
    "addr:full":"Avda Redondela, 4 Angoren Pontevedra 36320",
    "addr:housenumber":"4",
    "addr:postcode":"36320",
    "addr:street":"Avda Redondela",
    "iso:country":"ES",
    "sg:address":"Avda Redondela, 4",
    "sg:city":"Angoren",
    "sg:orig_category":"Veh\u00cdculos De Ocasi\u00d3n",
    "sg:phone":"+34 986 45 05 36",
    "sg:postcode":"36320",
    "sg:province":"Pontevedra",
    "wof:name":"Cabalcar S.l.",
    "wof:placetype":"venue"
},
  "geometry": {"coordinates":[-8.6428003311,42.4304618835],"type":"Point"}
}