{
  "type": "Feature",
  "properties": {
    "addr:full":"Avda Libertad De La, 25 Donostia-san Sebastian Guip\u00f9zcoa 20004",
    "addr:housenumber":"25",
    "addr:postcode":"20004",
    "addr:street":"Avda Libertad De La",
    "iso:country":"ES",
    "sg:address":"Avda Libertad De La, 25",
    "sg:city":"Donostia-san Sebastian",
    "sg:orig_category":"Agentes Generales De Seguros",
    "sg:phone":"+34 943 42 68 18",
    "sg:postcode":"20004",
    "sg:province":"Guip\u00f9zcoa",
    "wof:name":"M.c. Erquicia Y Otros. C.b.",
    "wof:placetype":"venue"
},
  "geometry": {"coordinates":[-1.9827469587,43.3191413879],"type":"Point"}
}