{
  "type": "Feature",
  "properties": {
    "iso:country":"ES",
    "sg:address":"Avda Aldehuela, S/n",
    "sg:city":"Salamanca",
    "sg:orig_category":"Materias Pl\u00c1sticas: Productos De Consumo Masivo (fabricaci\u00d3n, Al Por Mayor)",
    "sg:phone":"+34 923 18 42 89",
    "sg:postcode":"37008",
    "sg:province":"Salamanca",
    "wof:name":"Diaz Rodriguez Felicisimo",
    "wof:placetype":"venue"
},
  "geometry": {"coordinates":[-5.6582660675,40.95936203],"type":"Point"}
}