{
  "type": "Feature",
  "properties": {
    "addr:full":"Atlantico, 17 Morro Jable Las Palmas 35625",
    "addr:housenumber":"17",
    "addr:postcode":"35625",
    "addr:street":"Atlantico",
    "iso:country":"ES",
    "sg:address":"Atlantico, 17",
    "sg:city":"Morro Jable",
    "sg:orig_category":"Promotores Constructores",
    "sg:phone":"+34 928 54 11 66",
    "sg:postcode":"35625",
    "sg:province":"Las Palmas",
    "wof:name":"Corpe S.l.",
    "wof:placetype":"venue"
},
  "geometry": {"coordinates":[-14.3567991257,28.0517597198],"type":"Point"}
}