{
  "type": "Feature",
  "properties": {
    "addr:full":"Calle de Via Carpetana, 230 Madrid Madrid 28047",
    "addr:housenumber":"230",
    "addr:postcode":"28047",
    "addr:street":"Calle De Via Carpetana",
    "iso:country":"ES",
    "sg:address":"Calle de Via Carpetana, 230",
    "sg:city":"Madrid",
    "sg:orig_category":"Talleres: Ropa A Medida",
    "sg:phone":"+34 914 62 45 65",
    "sg:postcode":"28047",
    "sg:province":"Madrid",
    "wof:name":"Importaciones Y Exportaciones Ribas 2000 S.l:",
    "wof:placetype":"venue"
},
  "geometry": {"coordinates":[-3.7390639782,40.3944778442],"type":"Point"}
}