{
  "type": "Feature",
  "properties": {
    "iso:country":"ES",
    "sg:address":"Avda Leon, S/n",
    "sg:city":"Villanueva Carrizo",
    "sg:orig_category":"Serrer\u00cdas De Madera",
    "sg:phone":"+34 987 35 70 40",
    "sg:postcode":"24270",
    "sg:province":"Le\u00f3n",
    "wof:name":"Fernandez Salvadores Manuel",
    "wof:placetype":"venue"
},
  "geometry": {"coordinates":[-5.8181591034,42.5817565918],"type":"Point"}
}