{
  "type": "Feature",
  "properties": {
    "addr:full":"Calle de Vicente Blanch Picot, 10 Torremolinos M\u00e1laga 29620",
    "addr:housenumber":"10",
    "addr:postcode":"29620",
    "addr:street":"Calle De Vicente Blanch Picot;Ma\u0301Laga",
    "iso:country":"ES",
    "sg:address":"Calle de Vicente Blanch Picot, 10",
    "sg:city":"Torremolinos",
    "sg:orig_category":"Venta, Alquiler De V\u00cddeo",
    "sg:phone":"+34 952 96 20 13",
    "sg:postcode":"29620",
    "sg:province":"M\u00e1laga",
    "wof:name":"Yuste Ruiz Jose Francisco",
    "wof:placetype":"venue"
},
  "geometry": {"coordinates":[-4.5180487633,36.6142196655],"type":"Point"}
}