{
  "type": "Feature",
  "properties": {
    "addr:full":"Carrer de Santa Agata, 10 Barcelona Barcelona 08012",
    "addr:housenumber":"10",
    "addr:postcode":"08012",
    "addr:street":"Carrer De Santa Agata",
    "iso:country":"ES",
    "sg:address":"Carrer de Santa Agata, 10",
    "sg:city":"Barcelona",
    "sg:orig_category":"Artes Gr\u00c1ficas, Artes Pl\u00c1sticas: Material Y Suministros (al Por Menor)",
    "sg:phone":"+34 934 15 27 29",
    "sg:postcode":"08012",
    "sg:province":"Barcelona",
    "wof:name":"Calidos S.cp.",
    "wof:placetype":"venue"
},
  "geometry": {"coordinates":[2.1523399353,41.4039916992],"type":"Point"}
}