{
  "type": "Feature",
  "properties": {
    "addr:full":"Xiii (p I Redonda), S/n Santa Maria Aguila Almer\u00eda 04710",
    "addr:postcode":"04710",
    "addr:street":"P I Redonda S / N;Almeri\u0301A",
    "iso:country":"ES",
    "sg:address":"Xiii (p I Redonda), S/n",
    "sg:city":"Santa Maria Aguila",
    "sg:classifiers":[
        {
            "category":"Banks & Credit Unions",
            "subcategory":"Bureau De Change",
            "type":"Services"
        }
    ],
    "sg:phone":"+34 950 58 08 34",
    "sg:postcode":"04710",
    "sg:province":"Almer\u00eda",
    "sg:tags":[
        "organismos",
        "control"
    ],
    "wof:name":"Entidad De Control Y Certificacion S.l.",
    "wof:placetype":"venue"
},
  "geometry": {"coordinates":[-2.7759139538,36.7795753479],"type":"Point"}
}