{
  "type": "Feature",
  "properties": {
    "addr:full":"Rua Ponte Dena, 19 Ponte Dena Pontevedra 36967",
    "addr:housenumber":"19",
    "addr:postcode":"36967",
    "addr:street":"Rua Ponte Dena",
    "iso:country":"ES",
    "sg:address":"Rua Ponte Dena, 19",
    "sg:city":"Ponte Dena",
    "sg:orig_category":"Molduras, Junquillos, Listones Y Molduras Perforadas",
    "sg:phone":"+34 986 74 30 05",
    "sg:postcode":"36967",
    "sg:province":"Pontevedra",
    "wof:name":"Otero Salgeiro Cristian",
    "wof:placetype":"venue"
},
  "geometry": {"coordinates":[-8.8113698959,42.4530296326],"type":"Point"}
}