{
  "type": "Feature",
  "properties": {
    "iso:country":"ES",
    "sg:address":"Henry Purcell (ctm), 4",
    "sg:city":"Malaga",
    "sg:orig_category":"Transportes Frigor\u00cdficos",
    "sg:phone":"+34 952 17 80 64",
    "sg:postcode":"29010",
    "sg:province":"M\u00e1laga",
    "wof:name":"Transfisur S.c.a.",
    "wof:placetype":"venue"
},
  "geometry": {"coordinates":[-4.5110387802,36.7164916992],"type":"Point"}
}