{
  "type": "Feature",
  "properties": {
    "addr:full":"Carrer de Balmes, 396 Barcelona Barcelona 08022",
    "addr:housenumber":"396",
    "addr:postcode":"08022",
    "addr:street":"Carrer De Balmes",
    "iso:country":"ES",
    "sg:address":"Carrer de Balmes, 396",
    "sg:city":"Barcelona",
    "sg:orig_category":"Doctores En Medicina",
    "sg:phone":"+34 934 17 45 88",
    "sg:postcode":"08022",
    "sg:province":"Barcelona",
    "wof:name":"Roldan Lozano Luis",
    "wof:placetype":"venue"
},
  "geometry": {"coordinates":[2.1394178867,41.405632019],"type":"Point"}
}