{
  "type": "Feature",
  "properties": {
    "addr:full":"Due\u00f1as-villademar, S/n S. Juan Pi\u00f1era Asturias 33159",
    "addr:postcode":"33159",
    "addr:street":"Duen\u0303As-Villademar S / N S. Juan Pin\u0303Era Asturias",
    "iso:country":"ES",
    "sg:address":"Due\u00f1as-villademar, S/n",
    "sg:city":"S. Juan Pi\u00f1era",
    "sg:orig_category":"Chapister\u00cda",
    "sg:phone":"+34 985 59 09 72",
    "sg:postcode":"33159",
    "sg:province":"Asturias",
    "wof:name":"Compo Perez Blancanieves",
    "wof:placetype":"venue"
},
  "geometry": {"coordinates":[-6.2036042213,43.5223693848],"type":"Point"}
}