{
  "type": "Feature",
  "properties": {
    "addr:full":"Calle de Ubeda, S/n Nerja M\u00e1laga 29780",
    "addr:housenumber":"s / n",
    "addr:postcode":"29780",
    "addr:street":"Calle De Ubeda",
    "iso:country":"ES",
    "sg:address":"Calle de Ubeda, S/n",
    "sg:city":"Nerja",
    "sg:orig_category":"Centros Empresariales",
    "sg:phone":"+34 952 52 74 55",
    "sg:postcode":"29780",
    "sg:province":"M\u00e1laga",
    "wof:name":"Embel Procedimientos Sl",
    "wof:placetype":"venue"
},
  "geometry": {"coordinates":[-3.8702099323,36.7532424927],"type":"Point"}
}