{
  "type": "Feature",
  "properties": {
    "addr:full":"Carr Aigues, 14 Seu D'urgell Lleida 25700",
    "addr:housenumber":"14",
    "addr:postcode":"25700",
    "addr:street":"Carr Aigues",
    "iso:country":"ES",
    "sg:address":"Carr Aigues, 14",
    "sg:city":"Seu D'urgell",
    "sg:orig_category":"Mec\u00c1nico Del Autom\u00d3vil",
    "sg:phone":"+34 973 35 24 63",
    "sg:postcode":"25700",
    "sg:province":"Lleida",
    "wof:name":"Auto Reparacions Mompo S.l.",
    "wof:placetype":"venue"
},
  "geometry": {"coordinates":[1.458224535,42.3611564636],"type":"Point"}
}