{
  "type": "Feature",
  "properties": {
    "iso:country":"ES",
    "sg:address":"Av Robert Graupera, 220",
    "sg:city":"Deltebre",
    "sg:orig_category":"Librer\u00cdas",
    "sg:phone":"+34 977 48 93 84",
    "sg:postcode":"43580",
    "sg:province":"Tarragona",
    "wof:name":"Roig Valldeperez Maria Carmen",
    "wof:placetype":"venue"
},
  "geometry": {"coordinates":[0.7146660089,40.7192764282],"type":"Point"}
}