{
  "type": "Feature",
  "properties": {
    "addr:full":"Calle de Jose Maria Fernandez Lanseros, 2 Madrid Madrid 28017",
    "addr:housenumber":"2",
    "addr:postcode":"28017",
    "addr:street":"Calle De Jose Maria Fernandez Lanseros",
    "iso:country":"ES",
    "sg:address":"Calle de Jose Maria Fernandez Lanseros, 2",
    "sg:city":"Madrid",
    "sg:orig_category":"Ropa Para Se\u00d1oras (al Por Menor)",
    "sg:phone":"+34 917 25 10 84",
    "sg:postcode":"28017",
    "sg:province":"Madrid",
    "wof:name":"Charo Vazquez S.l.",
    "wof:placetype":"venue"
},
  "geometry": {"coordinates":[-3.6577429771,40.4315986633],"type":"Point"}
}