{
  "type": "Feature",
  "properties": {
    "addr:full":"Calle de San Francisco, 2 Villamartin C\u00e1diz 11650",
    "addr:housenumber":"2",
    "addr:postcode":"11650",
    "addr:street":"Calle De San Francisco;Ca\u0301Diz",
    "iso:country":"ES",
    "sg:address":"Calle de San Francisco, 2",
    "sg:city":"Villamartin",
    "sg:orig_category":"Quincaller\u00cda (al Por Menor)",
    "sg:phone":"+34 956 73 04 86",
    "sg:postcode":"11650",
    "sg:province":"C\u00e1diz",
    "wof:name":"Poley Orozco Jose",
    "wof:placetype":"venue"
},
  "geometry": {"coordinates":[-5.6428890228,36.8603210449],"type":"Point"}
}