{
  "type": "Feature",
  "properties": {
    "addr:full":"Cabo Azohia, 3 Urb. Golf Madrid 28290",
    "addr:postcode":"28290",
    "addr:street":"Azohia;Urb.",
    "iso:country":"ES",
    "sg:address":"Cabo Azohia, 3",
    "sg:city":"Urb. Golf",
    "sg:orig_category":"Promotores Constructores",
    "sg:phone":"+34 916 30 45 60",
    "sg:postcode":"28290",
    "sg:province":"Madrid",
    "wof:name":"Cacsa S.a.",
    "wof:placetype":"venue"
},
  "geometry": {"coordinates":[-3.900621891,40.5461578369],"type":"Point"}
}