{
  "type": "Feature",
  "properties": {
    "iso:country":"ES",
    "sg:address":"Calle de Conde Del Real Agrado, 19",
    "sg:city":"Luanco",
    "sg:orig_category":"Empresarios",
    "sg:phone":"+34 985 88 23 54",
    "sg:postcode":"33440",
    "sg:province":"Asturias",
    "wof:name":"Estebanez Garcia Agustin",
    "wof:placetype":"venue"
},
  "geometry": {"coordinates":[-5.7969498634,43.6147079468],"type":"Point"}
}