{
  "type": "Feature",
  "properties": {
    "iso:country":"ES",
    "sg:address":"Carrer de Jaume I, 15",
    "sg:city":"Sabadell",
    "sg:orig_category":"Perfumer\u00cda Y Cosm\u00c9tica (fabricaci\u00d3n, Al Por Mayor)",
    "sg:phone":"+34 937 16 83 47",
    "sg:postcode":"08206",
    "sg:province":"Barcelona",
    "wof:name":"Maijo Natural S.l.",
    "wof:placetype":"venue"
},
  "geometry": {"coordinates":[2.0949840546,41.5575942993],"type":"Point"}
}