{
  "type": "Feature",
  "properties": {
    "iso:country":"ES",
    "sg:address":"Plaz Ruben Beloki, 1",
    "sg:city":"Burlada",
    "sg:orig_category":"Edici\u00d3n De Diarios, Revistas, Boletines",
    "sg:phone":"+34 948 13 48 06",
    "sg:postcode":"31600",
    "sg:province":"Navarra",
    "wof:name":"Domench Garcia Jose Maria",
    "wof:placetype":"venue"
},
  "geometry": {"coordinates":[-1.6187809706,42.8290672302],"type":"Point"}
}