{
  "type": "Feature",
  "properties": {
    "iso:country":"ES",
    "sg:address":"Fca La Venta, S/n",
    "sg:city":"Bonillo",
    "sg:orig_category":"Promotores Constructores",
    "sg:phone":"+34 967 58 50 36",
    "sg:postcode":"02610",
    "sg:province":"Albacete",
    "wof:name":"Epico S.a.",
    "wof:placetype":"venue"
},
  "geometry": {"coordinates":[-2.535777092,38.952495575],"type":"Point"}
}