{
  "type": "Feature",
  "properties": {
    "addr:full":"Calle de Pasion, S/n Osorno Palencia 34460",
    "addr:housenumber":"s / n",
    "addr:postcode":"34460",
    "addr:street":"Calle De Pasion",
    "iso:country":"ES",
    "sg:address":"Calle de Pasion, S/n",
    "sg:city":"Osorno",
    "sg:orig_category":"Bebidas",
    "sg:phone":"+34 979 15 02 23",
    "sg:postcode":"34460",
    "sg:province":"Palencia",
    "wof:name":"Marin Due\u00f1as Benjamin",
    "wof:placetype":"venue"
},
  "geometry": {"coordinates":[-4.3629889488,42.4107666016],"type":"Point"}
}