{
  "type": "Feature",
  "properties": {
    "iso:country":"ES",
    "sg:address":"Carr Duc De Lliria (del), 7",
    "sg:city":"Lliria",
    "sg:orig_category":"Servicio De Salud",
    "sg:phone":"+34 962 78 01 71",
    "sg:postcode":"46160",
    "sg:province":"Valencia",
    "wof:name":"Torner Alama Juan Luis",
    "wof:placetype":"venue"
},
  "geometry": {"coordinates":[-0.594636023,39.6276550293],"type":"Point"}
}