{
  "type": "Feature",
  "properties": {
    "iso:country":"ES",
    "sg:address":"Sant Salvador, 13",
    "sg:city":"Granollers",
    "sg:orig_category":"Tintes (fabricaci\u00d3n, Al Por Mayor)",
    "sg:phone":"+34 938 70 67 97",
    "sg:postcode":"08402",
    "sg:province":"Barcelona",
    "wof:name":"Barcelo Nogue Esteban",
    "wof:placetype":"venue"
},
  "geometry": {"coordinates":[2.289192915,41.6067276001],"type":"Point"}
}