{
  "type": "Feature",
  "properties": {
    "addr:full":"Calle de Aguila, 4 Valladolid Valladolid 47012",
    "addr:housenumber":"4",
    "addr:postcode":"47012",
    "addr:street":"Calle De Aguila",
    "iso:country":"ES",
    "sg:address":"Calle de Aguila, 4",
    "sg:city":"Valladolid",
    "sg:classifiers":[
        {
            "category":"Personal",
            "subcategory":"Barber",
            "type":"Services"
        }
    ],
    "sg:phone":"+34 983 30 26 54",
    "sg:postcode":"47012",
    "sg:province":"Valladolid",
    "sg:tags":[
        "caballeros",
        "de",
        "peluqueros"
    ],
    "wof:name":"Maestro Hernandez Angel",
    "wof:placetype":"venue"
},
  "geometry": {"coordinates":[-4.7102537155,41.647480011],"type":"Point"}
}