{
  "type": "Feature",
  "properties": {
    "iso:country":"ES",
    "sg:address":"Calle de Angel, 16",
    "sg:city":"Madrid",
    "sg:orig_category":"Empresarios Y Productoras De Espect\u00c1culos",
    "sg:phone":"+34 913 64 00 03",
    "sg:postcode":"28005",
    "sg:province":"Madrid",
    "wof:name":"Hinojosa Vazquez Enrique Angel",
    "wof:placetype":"venue"
},
  "geometry": {"coordinates":[-3.7129459381,40.4098548889],"type":"Point"}
}