{
  "type": "Feature",
  "properties": {
    "iso:country":"ES",
    "sg:address":"Carrer de Coromines, 2",
    "sg:city":"Sentmenat",
    "sg:orig_category":"Supermercados Y Hipermercados",
    "sg:phone":"+34 937 15 20 60",
    "sg:postcode":"08181",
    "sg:province":"Barcelona",
    "wof:name":"Vazquez Luna Ana Maria",
    "wof:placetype":"venue"
},
  "geometry": {"coordinates":[2.1366069317,41.6092071533],"type":"Point"}
}