{
  "type": "Feature",
  "properties": {
    "iso:country":"ES",
    "sg:address":"Calle de Fuente, S/n",
    "sg:city":"Saelices Del Payuelo",
    "sg:orig_category":"Cr\u00cda De Animales",
    "sg:phone":"+34 987 33 64 75",
    "sg:postcode":"24920",
    "sg:province":"Le\u00f3n",
    "wof:name":"S. L. Agropayuelos",
    "wof:placetype":"venue"
},
  "geometry": {"coordinates":[-5.280605793,42.5337524414],"type":"Point"}
}