{
  "type": "Feature",
  "properties": {
    "addr:full":"Pase Chopera (de La), 68 Alcobendas Madrid 28100",
    "addr:postcode":"28100",
    "iso:country":"ES",
    "sg:address":"Pase Chopera (de La), 68",
    "sg:city":"Alcobendas",
    "sg:orig_category":"Transportes Por Carretera: Lotes Completos, Mercanc\u00cdas Diversas",
    "sg:phone":"+34 916 62 13 73",
    "sg:postcode":"28100",
    "sg:province":"Madrid",
    "wof:name":"Comercial Distribuidora Ruiz S. A.",
    "wof:placetype":"venue"
},
  "geometry": {"coordinates":[-3.6415090561,40.5417175293],"type":"Point"}
}