{
  "type": "Feature",
  "properties": {
    "addr:full":"Avda Paseo De Almeria, 52 Almeria Almer\u00eda 04001",
    "addr:housenumber":"52",
    "addr:postcode":"04001",
    "addr:street":"Avda Paseo De Almeria",
    "iso:country":"ES",
    "sg:address":"Avda Paseo De Almeria, 52",
    "sg:city":"Almeria",
    "sg:orig_category":"Centros Empresariales",
    "sg:phone":"+34 950 26 58 58",
    "sg:postcode":"04001",
    "sg:province":"Almer\u00eda",
    "wof:name":"Ruiz Moreno Irene",
    "wof:placetype":"venue"
},
  "geometry": {"coordinates":[-2.4608390331,36.8422698975],"type":"Point"}
}