{
  "type": "Feature",
  "properties": {
    "addr:full":"Ctra Bassella, 28 Solsona Lleida 25280",
    "addr:housenumber":"28",
    "addr:postcode":"25280",
    "addr:street":"Ctra Bassella",
    "iso:country":"ES",
    "sg:address":"Ctra Bassella, 28",
    "sg:city":"Solsona",
    "sg:orig_category":"Fabricaci\u00d3n De Su\u00c9ters Y Chalecos De Punto",
    "sg:phone":"+34 973 48 07 89",
    "sg:postcode":"25280",
    "sg:province":"Lleida",
    "wof:name":"Gelabert Cabo Pilar",
    "wof:placetype":"venue"
},
  "geometry": {"coordinates":[1.5184766054,41.9963569641],"type":"Point"}
}