{
  "type": "Feature",
  "properties": {
    "iso:country":"ES",
    "sg:address":"Calle de Guijo, 59",
    "sg:city":"Coria",
    "sg:orig_category":"Estancos",
    "sg:phone":"+34 927 50 05 79",
    "sg:postcode":"10800",
    "sg:province":"C\u00e1ceres",
    "wof:name":"Iglesias Clemente Carmen",
    "wof:placetype":"venue"
},
  "geometry": {"coordinates":[-6.5334291458,39.9880905151],"type":"Point"}
}