{
  "type": "Feature",
  "properties": {
    "addr:full":"Rua Galicia, 6 Ourense Ourense 32005",
    "addr:housenumber":"6",
    "addr:postcode":"32005",
    "addr:street":"Rua Galicia",
    "iso:country":"ES",
    "sg:address":"Rua Galicia, 6",
    "sg:city":"Ourense",
    "sg:orig_category":"Ropa Para Se\u00d1oras (al Por Menor)",
    "sg:phone":"+34 988 22 89 68",
    "sg:postcode":"32005",
    "sg:province":"Ourense",
    "wof:name":"Lopez Rodriguez Mari Carmen",
    "wof:placetype":"venue"
},
  "geometry": {"coordinates":[-7.8633317947,42.3303527832],"type":"Point"}
}