{
  "type": "Feature",
  "properties": {
    "addr:full":"S. Pedro De Guantes, Paraje, S/n Villanueva Arriba Palencia 34879",
    "addr:postcode":"34879",
    "addr:street":"Paraje S / N",
    "iso:country":"ES",
    "sg:address":"S. Pedro De Guantes, Paraje, S/n",
    "sg:city":"Villanueva Arriba",
    "sg:orig_category":"Pirotecnia (espect\u00c1culos)",
    "sg:phone":"+34 979 18 60 06",
    "sg:postcode":"34879",
    "sg:province":"Palencia",
    "wof:name":"Pirotecnia Devita S.l.",
    "wof:placetype":"venue"
},
  "geometry": {"coordinates":[-4.7485952377,42.7669143677],"type":"Point"}
}