{
  "type": "Feature",
  "properties": {
    "addr:full":"Calle de Real, 1 Madridejos Toledo 45710",
    "addr:housenumber":"1",
    "addr:postcode":"45710",
    "addr:street":"Calle De Real",
    "iso:country":"ES",
    "sg:address":"Calle de Real, 1",
    "sg:city":"Madridejos",
    "sg:orig_category":"Fotograf\u00cda Y Cine: Aparatos, Pel\u00cdculas Y Accesorios (al Por Menor)",
    "sg:phone":"+34 925 46 15 41",
    "sg:postcode":"45710",
    "sg:province":"Toledo",
    "wof:name":"Garcia-consuegra Aguirre Antonio",
    "wof:placetype":"venue"
},
  "geometry": {"coordinates":[-3.5345740318,39.4686431885],"type":"Point"}
}