{
  "type": "Feature",
  "properties": {
    "iso:country":"ES",
    "sg:address":"Avda Viveiro, S/n",
    "sg:city":"Ferrol",
    "sg:orig_category":"Aparcamientos (infraestructuras, Accesorios)",
    "sg:phone":"+34 981 31 81 20",
    "sg:postcode":"15403",
    "sg:province":"La Coru\u00f1a",
    "wof:name":"Portanova Park S.a.",
    "wof:placetype":"venue"
},
  "geometry": {"coordinates":[-8.2229290009,43.4895362854],"type":"Point"}
}