{
  "type": "Feature",
  "properties": {
    "addr:full":"Joaquin Sorolla, 116 Rivas Vaciamadrid Madrid 28529",
    "addr:housenumber":"116",
    "addr:postcode":"28529",
    "addr:street":"Sorolla",
    "iso:country":"ES",
    "sg:address":"Joaquin Sorolla, 116",
    "sg:city":"Rivas Vaciamadrid",
    "sg:orig_category":"Ropa Y Accesorios",
    "sg:phone":"+34 914 99 28 64",
    "sg:postcode":"28529",
    "sg:province":"Madrid",
    "sg:website":"www.areazero.biz",
    "wof:name":"Samafe S.l.",
    "wof:placetype":"venue"
},
  "geometry": {"coordinates":[-3.5322959423,40.3464775085],"type":"Point"}
}