{
  "type": "Feature",
  "properties": {
    "iso:country":"ES",
    "sg:address":"Calle de Mayor, 26",
    "sg:city":"Fresneda",
    "sg:orig_category":"Alimentaci\u00d3n General (al Por Menor)",
    "sg:phone":"+34 978 85 45 45",
    "sg:postcode":"44596",
    "sg:province":"Teruel",
    "wof:name":"Latorre Mora Maria Luisa",
    "wof:placetype":"venue"
},
  "geometry": {"coordinates":[0.0741340965,40.9280509949],"type":"Point"}
}