{
  "type": "Feature",
  "properties": {
    "addr:full":"Carr Raval De Sant Roc, 119 Raval Valencia 46680",
    "addr:housenumber":"119",
    "addr:postcode":"46680",
    "addr:street":"Carr Raval De Sant Roc",
    "iso:country":"ES",
    "sg:address":"Carr Raval De Sant Roc, 119",
    "sg:city":"Raval",
    "sg:orig_category":"Arte, Cultura, Edici\u00d3n",
    "sg:phone":"+34 962 42 10 70",
    "sg:postcode":"46680",
    "sg:province":"Valencia",
    "wof:name":"Walter Torres Miguel Angel",
    "wof:placetype":"venue"
},
  "geometry": {"coordinates":[-0.4472692907,39.1975135803],"type":"Point"}
}