{
  "type": "Feature",
  "properties": {
    "iso:country":"ES",
    "sg:address":"Beballara, S/n",
    "sg:city":"Beballara",
    "sg:orig_category":"Ferreter\u00cda (diversos)",
    "sg:phone":"+34 943 69 11 85",
    "sg:postcode":"20159",
    "sg:province":"Guip\u00f9zcoa",
    "wof:name":"Hierros Vicu\u00f1a S.a.",
    "wof:placetype":"venue"
},
  "geometry": {"coordinates":[-2.0742990971,43.1991958618],"type":"Point"}
}