{
  "type": "Feature",
  "properties": {
    "addr:full":"Av. Blasco Iba\u00f1ez, 113 Massanassa Valencia 46470",
    "addr:housenumber":"113",
    "addr:postcode":"46470",
    "addr:street":"Av. Blasco Iban\u0303Ez",
    "iso:country":"ES",
    "sg:address":"Av. Blasco Iba\u00f1ez, 113",
    "sg:city":"Massanassa",
    "sg:orig_category":"Agencias De Viajes",
    "sg:phone":"+34 961 25 06 16",
    "sg:postcode":"46470",
    "sg:province":"Valencia",
    "wof:name":"Tarazona Baixauli Francisca Emilia",
    "wof:placetype":"venue"
},
  "geometry": {"coordinates":[-0.3991590142,39.4133224487],"type":"Point"}
}