{
  "type": "Feature",
  "properties": {
    "addr:full":"C/ Concepcion Arenal, 156 Elche Alicante 03204",
    "addr:housenumber":"156",
    "addr:postcode":"03204",
    "addr:street":"C / Concepcion Arenal",
    "iso:country":"ES",
    "sg:address":"C/ Concepcion Arenal, 156",
    "sg:city":"Elche",
    "sg:orig_category":"Peluqueros: De Se\u00d1oras",
    "sg:phone":"+34 966 63 50 86",
    "sg:postcode":"03204",
    "sg:province":"Alicante",
    "wof:name":"Peluqueria Noemi S.l.",
    "wof:placetype":"venue"
},
  "geometry": {"coordinates":[-0.7079679966,38.2595672607],"type":"Point"}
}