{
  "type": "Feature",
  "properties": {
    "addr:full":"Calle de Juan Perez, 5 Teruel Teruel 44001",
    "addr:housenumber":"5",
    "addr:postcode":"44001",
    "addr:street":"Calle De Juan Perez",
    "iso:country":"ES",
    "sg:address":"Calle de Juan Perez, 5",
    "sg:city":"Teruel",
    "sg:orig_category":"Ropa Para Beb\u00c9s Y Ni\u00d1os (confecci\u00d3n, Al Por Mayor)",
    "sg:phone":"+34 978 60 46 64",
    "sg:postcode":"44001",
    "sg:province":"Teruel",
    "wof:name":"Blasco Terren Manuela",
    "wof:placetype":"venue"
},
  "geometry": {"coordinates":[-1.1068470478,40.3436088562],"type":"Point"}
}