{
  "type": "Feature",
  "properties": {
    "iso:country":"ES",
    "sg:address":"Calle de Solis, 1",
    "sg:city":"Ceuta",
    "sg:orig_category":"Zapater\u00cdas",
    "sg:phone":"+34 956 51 92 71",
    "sg:postcode":"51001",
    "sg:province":"Ceuta",
    "wof:name":"Faddal Mohamed Mohamed",
    "wof:placetype":"venue"
},
  "geometry": {"coordinates":[-5.3089709282,35.8883857727],"type":"Point"}
}