{
  "type": "Feature",
  "properties": {
    "addr:full":"Carrer de Flors, 10 Tiana Barcelona 08391",
    "addr:housenumber":"10",
    "addr:postcode":"08391",
    "addr:street":"Carrer De Flors",
    "iso:country":"ES",
    "sg:address":"Carrer de Flors, 10",
    "sg:city":"Tiana",
    "sg:orig_category":"Fabricaci\u00d3n De Productos Textiles Sin Tejer",
    "sg:phone":"+34 933 95 30 02",
    "sg:postcode":"08391",
    "sg:province":"Barcelona",
    "wof:name":"Pompas Funebres De Badalona S.a.",
    "wof:placetype":"venue"
},
  "geometry": {"coordinates":[2.2693018913,41.4833946228],"type":"Point"}
}