{
  "type": "Feature",
  "properties": {
    "iso:country":"ES",
    "sg:address":"Barr Murtatza, S/n",
    "sg:city":"Murtatza",
    "sg:orig_category":"Herramientas Manuales (fabricaci\u00d3n, Al Por Mayor)",
    "sg:phone":"+34 946 31 38 67",
    "sg:postcode":"48390",
    "sg:province":"Vizcaya",
    "wof:name":"Manufacturas Uther S. A.",
    "wof:placetype":"venue"
},
  "geometry": {"coordinates":[-2.8106722832,43.2135391235],"type":"Point"}
}