{
  "type": "Feature",
  "properties": {
    "addr:full":"Calle de Ricardo Del Arco, 27 Zaragoza Zaragoza 50015",
    "addr:housenumber":"27",
    "addr:postcode":"50015",
    "addr:street":"Calle De Ricardo Del Arco",
    "iso:country":"ES",
    "sg:address":"Calle de Ricardo Del Arco, 27",
    "sg:city":"Zaragoza",
    "sg:orig_category":"Escotaduras, Torneados",
    "sg:phone":"+34 976 52 27 68",
    "sg:postcode":"50015",
    "sg:province":"Zaragoza",
    "wof:name":"Solanas Rodriguez Angel",
    "wof:placetype":"venue"
},
  "geometry": {"coordinates":[-0.8782222867,41.6599884033],"type":"Point"}
}