{
  "type": "Feature",
  "properties": {
    "addr:full":"C/ Tramuntana, De La, 12 Porto Cristo Islas Baleares 07680",
    "addr:housenumber":"12",
    "addr:postcode":"07680",
    "addr:street":"C / Tramuntana De La;Islas Baleares",
    "iso:country":"ES",
    "sg:address":"C/ Tramuntana, De La, 12",
    "sg:city":"Porto Cristo",
    "sg:orig_category":"Plomeros",
    "sg:phone":"+34 971 82 22 02",
    "sg:postcode":"07680",
    "sg:province":"Islas Baleares",
    "wof:name":"Jp Instalacions Sanitaries S.l",
    "wof:placetype":"venue"
},
  "geometry": {"coordinates":[3.3359000683,39.5415039062],"type":"Point"}
}