{
  "type": "Feature",
  "properties": {
    "iso:country":"ES",
    "sg:address":"Calle de Sant Miquel, 16",
    "sg:city":"Vilafames",
    "sg:orig_category":"Asesor\u00cda Sobre Comunicaci\u00d3n De Empresas",
    "sg:phone":"+34 964 33 50 34",
    "sg:postcode":"12192",
    "sg:province":"Castell\u00f3n",
    "wof:name":"Julve Capdevilla Maria Amparo",
    "wof:placetype":"venue"
},
  "geometry": {"coordinates":[-0.0640499964,40.1220092773],"type":"Point"}
}