{
  "type": "Feature",
  "properties": {
    "iso:country":"ES",
    "sg:address":"Carrer de Homer, 46",
    "sg:city":"Barcelona",
    "sg:orig_category":"Importaci\u00d3n",
    "sg:phone":"+34 934 18 94 36",
    "sg:postcode":"08023",
    "sg:province":"Barcelona",
    "wof:name":"Jocar De Carlos Osca S.l.",
    "wof:placetype":"venue"
},
  "geometry": {"coordinates":[2.1447970867,41.4083595276],"type":"Point"}
}