{
  "type": "Feature",
  "properties": {
    "iso:country":"ES",
    "sg:address":"Calle de Concha Espina, 9",
    "sg:city":"Sevilla",
    "sg:orig_category":"Molduras, Junquillos, Listones Y Molduras Perforadas",
    "sg:phone":"+34 954 27 63 40",
    "sg:postcode":"41010",
    "sg:province":"Sevilla",
    "wof:name":"Bar Tribuna S.c.",
    "wof:placetype":"venue"
},
  "geometry": {"coordinates":[-6.0031628609,37.3797569275],"type":"Point"}
}