{
  "type": "Feature",
  "properties": {
    "iso:country":"ES",
    "sg:address":"Avda Pinos (los), 7",
    "sg:city":"Quinto",
    "sg:orig_category":"Ropa Para Se\u00d1oras Y Caballeros (al Por Menor)",
    "sg:phone":"+34 954 12 56 88",
    "sg:postcode":"41089",
    "sg:province":"Sevilla",
    "wof:name":"Juan Antonio Donoso Gonzalez S.l.",
    "wof:placetype":"venue"
},
  "geometry": {"coordinates":[-5.9332537651,37.3442153931],"type":"Point"}
}