{
  "type": "Feature",
  "properties": {
    "iso:country":"ES",
    "sg:address":"Calle de San Narciso, 26",
    "sg:city":"Madrid",
    "sg:orig_category":"Pod\u00d3logos: Pedicuros",
    "sg:phone":"+34 917 42 23 62",
    "sg:postcode":"28022",
    "sg:province":"Madrid",
    "wof:name":"Sanchez Carrasco Antonio",
    "wof:placetype":"venue"
},
  "geometry": {"coordinates":[-3.6096849442,40.445350647],"type":"Point"}
}