{
  "type": "Feature",
  "properties": {
    "addr:full":"Rua Mendez Nu\u00d1ez, 51 Marin Pontevedra 36900",
    "addr:housenumber":"51",
    "addr:postcode":"36900",
    "addr:street":"Rua Mendez Nun\u0303Ez",
    "iso:country":"ES",
    "sg:address":"Rua Mendez Nu\u00d1ez, 51",
    "sg:city":"Marin",
    "sg:orig_category":"Ense\u00d1anza, Formaci\u00d3n Profesional: Aprendizaje",
    "sg:phone":"+34 986 88 00 04",
    "sg:postcode":"36900",
    "sg:province":"Pontevedra",
    "wof:name":"Concello De Marin",
    "wof:placetype":"venue"
},
  "geometry": {"coordinates":[-8.697637558,42.3925209045],"type":"Point"}
}