{
  "type": "Feature",
  "properties": {
    "iso:country":"ES",
    "sg:address":"Calle de Prado, S/n",
    "sg:city":"Arroyo Cuellar",
    "sg:orig_category":"Material Y Suministros Para Veterinarios",
    "sg:phone":"+34 921 15 53 40",
    "sg:postcode":"40215",
    "sg:province":"Segovia",
    "wof:name":"Jagar Arroyo S.l.",
    "wof:placetype":"venue"
},
  "geometry": {"coordinates":[-4.3708438873,41.3344535828],"type":"Point"}
}