{
  "type": "Feature",
  "properties": {
    "iso:country":"ES",
    "sg:address":"Calle de Prosperidad, 7",
    "sg:city":"Villa Don Fadrique",
    "sg:orig_category":"Hielo Artificial (fabricaci\u00d3n, Distribuci\u00d3n)",
    "sg:phone":"+34 925 20 41 03",
    "sg:postcode":"45850",
    "sg:province":"Toledo",
    "wof:name":"Vela Zaballos Felix",
    "wof:placetype":"venue"
},
  "geometry": {"coordinates":[-3.2169840336,39.6096878052],"type":"Point"}
}