{
  "type": "Feature",
  "properties": {
    "addr:full":"Avda Barrie De La Maza, 90 Sada La Coru\u00f1a 15160",
    "addr:housenumber":"90",
    "addr:postcode":"15160",
    "addr:street":"Avda Barrie De La Maza;La",
    "iso:country":"ES",
    "sg:address":"Avda Barrie De La Maza, 90",
    "sg:city":"Sada",
    "sg:orig_category":"Venta, Montaje De Neum\u00c1ticos",
    "sg:phone":"+34 981 62 15 16",
    "sg:postcode":"15160",
    "sg:province":"La Coru\u00f1a",
    "wof:name":"Mosquera Pernas Juan Antonio",
    "wof:placetype":"venue"
},
  "geometry": {"coordinates":[-8.2584314346,43.3514480591],"type":"Point"}
}