{
  "type": "Feature",
  "properties": {
    "addr:full":"Calle de Mayor, 4 Palazuelo De Vedija Valladolid 47812",
    "addr:housenumber":"4",
    "addr:postcode":"47812",
    "addr:street":"Calle De Mayor",
    "iso:country":"ES",
    "sg:address":"Calle de Mayor, 4",
    "sg:city":"Palazuelo De Vedija",
    "sg:orig_category":"Material Y Suministros Para Veterinarios",
    "sg:phone":"+34 983 70 08 85",
    "sg:postcode":"47812",
    "sg:province":"Valladolid",
    "wof:name":"Los Marraneros S.l",
    "wof:placetype":"venue"
},
  "geometry": {"coordinates":[-5.1451439857,41.9285736084],"type":"Point"}
}