{
  "type": "Feature",
  "properties": {
    "addr:full":"Avda Virgen De Argeme, 43 Coria C\u00e1ceres 10800",
    "addr:housenumber":"43",
    "addr:postcode":"10800",
    "addr:street":"Avda Virgen De Argeme;Ca\u0301Ceres",
    "iso:country":"ES",
    "sg:address":"Avda Virgen De Argeme, 43",
    "sg:city":"Coria",
    "sg:orig_category":"M\u00c9dicos: Foniatr\u00cda Y Logopedia",
    "sg:phone":"+34 927 50 18 38",
    "sg:postcode":"10800",
    "sg:province":"C\u00e1ceres",
    "wof:name":"Versus C.b",
    "wof:placetype":"venue"
},
  "geometry": {"coordinates":[-6.5433421135,39.9939079285],"type":"Point"}
}