{
  "type": "Feature",
  "properties": {
    "addr:full":"Calle de Poeta Zorrilla, 12 Alacant Alicante 03012",
    "addr:housenumber":"12",
    "addr:postcode":"03012",
    "addr:street":"Calle De Poeta Zorrilla",
    "iso:country":"ES",
    "sg:address":"Calle de Poeta Zorrilla, 12",
    "sg:city":"Alacant",
    "sg:orig_category":"Soportes L\u00d3gicos, Programas Integradores De Aplicaciones (progiciels)",
    "sg:phone":"+34 965 14 71 59",
    "sg:postcode":"03012",
    "sg:province":"Alicante",
    "wof:name":"Carrion Rodriguez Maria",
    "wof:placetype":"venue"
},
  "geometry": {"coordinates":[-0.481810987,38.3553009033],"type":"Point"}
}