{
  "type": "Feature",
  "properties": {
    "addr:full":"Calle de Diputacion, S/n Ermua Vizcaya 48260",
    "addr:housenumber":"s",
    "addr:postcode":"48260",
    "addr:street":"Calle De Diputacion;/ N",
    "iso:country":"ES",
    "sg:address":"Calle de Diputacion, S/n",
    "sg:city":"Ermua",
    "sg:orig_category":"Carnicer\u00cdas, Carnicer\u00cdas",
    "sg:phone":"+34 943 17 05 84",
    "sg:postcode":"48260",
    "sg:province":"Vizcaya",
    "wof:name":"Urquizu Manterola Francisco",
    "wof:placetype":"venue"
},
  "geometry": {"coordinates":[-2.504584074,43.1867485046],"type":"Point"}
}