{
  "type": "Feature",
  "properties": {
    "iso:country":"ES",
    "sg:address":"Avda Toledo, Km. 0163,4",
    "sg:city":"Puebla Montalban",
    "sg:orig_category":"Distribuci\u00d3n De Petr\u00d3leo Y Derivados",
    "sg:phone":"+34 925 75 00 58",
    "sg:postcode":"45516",
    "sg:province":"Toledo",
    "wof:name":"Farruco S.a.",
    "wof:placetype":"venue"
},
  "geometry": {"coordinates":[-4.3588690758,39.8725013733],"type":"Point"}
}