{
  "type": "Feature",
  "properties": {
    "addr:full":"Calle de Santiago Rusi\u00d1ol, 6 Zaragoza Zaragoza 50002",
    "addr:housenumber":"6",
    "addr:postcode":"50002",
    "addr:street":"Calle De Santiago Rusin\u0303Ol",
    "iso:country":"ES",
    "sg:address":"Calle de Santiago Rusi\u00d1ol, 6",
    "sg:city":"Zaragoza",
    "sg:orig_category":"Extinci\u00d3n De Incendios: Material Y Suministros (fabricaci\u00d3n, Al Por Mayor)",
    "sg:phone":"+34 976 59 57 68",
    "sg:postcode":"50002",
    "sg:province":"Zaragoza",
    "wof:name":"Arqcoin S.l. Arquitectura Contra Incendios",
    "wof:placetype":"venue"
},
  "geometry": {"coordinates":[-0.8685764074,41.646282196],"type":"Point"}
}