{
  "type": "Feature",
  "properties": {
    "iso:country":"ES",
    "sg:address":"Calle de Caja De Ahorros, 24",
    "sg:city":"Getxo",
    "sg:orig_category":"Molduras, Junquillos, Listones Y Molduras Perforadas",
    "sg:phone":"+34 944 63 04 18",
    "sg:postcode":"48930",
    "sg:province":"Vizcaya",
    "wof:name":"Jose Maria Larrinaga Diaz Corcuera",
    "wof:placetype":"venue"
},
  "geometry": {"coordinates":[-3.0080783367,43.327003479],"type":"Point"}
}