{
  "type": "Feature",
  "properties": {
    "iso:country":"ES",
    "sg:address":"Calle de Vicente Camaron, 23",
    "sg:city":"Madrid",
    "sg:orig_category":"Promotores Constructores",
    "sg:phone":"+34 914 63 91 14",
    "sg:postcode":"28011",
    "sg:province":"Madrid",
    "wof:name":"Puerto Mestanza S.a.",
    "wof:placetype":"venue"
},
  "geometry": {"coordinates":[-3.7389450073,40.405960083],"type":"Point"}
}