{
  "type": "Feature",
  "properties": {
    "addr:full":"G.v. Puig De Galatzo, 10 Santa Pon\u00c7a Islas Baleares 07180",
    "addr:housenumber":"10",
    "addr:postcode":"07180",
    "addr:street":"Santa Ponc\u0327A",
    "iso:country":"ES",
    "sg:address":"G.v. Puig De Galatzo, 10",
    "sg:city":"Santa Pon\u00c7a",
    "sg:orig_category":"Institutos De Belleza",
    "sg:phone":"+34 971 69 09 58",
    "sg:postcode":"07180",
    "sg:province":"Islas Baleares",
    "wof:name":"Mayer  Ursula",
    "wof:placetype":"venue"
},
  "geometry": {"coordinates":[2.4985899925,39.5253143311],"type":"Point"}
}