{
  "type": "Feature",
  "properties": {
    "iso:country":"ES",
    "sg:address":"Rava Lleida (de), Km. 0070,4",
    "sg:city":"Borges Blanques",
    "sg:orig_category":"Paneles De Madera: Contrachapados, Fibras, Particulados, Estratificados (fabricaci\u00d3n, Venta)",
    "sg:phone":"+34 973 14 23 00",
    "sg:postcode":"25400",
    "sg:province":"Lleida",
    "wof:name":"Cuartero Valera Enrique",
    "wof:placetype":"venue"
},
  "geometry": {"coordinates":[0.8711360097,41.5198669434],"type":"Point"}
}