{
  "type": "Feature",
  "properties": {
    "addr:full":"Calle de Versalles, 10 Mostoles Madrid 28937",
    "addr:housenumber":"10",
    "addr:postcode":"28937",
    "addr:street":"Calle De Versalles",
    "iso:country":"ES",
    "sg:address":"Calle de Versalles, 10",
    "sg:city":"Mostoles",
    "sg:orig_category":"Muebles Y Accesorios Para Cocinas Y Cuartos De Ba\u00d1o (al Por Menor)",
    "sg:phone":"+34 916 45 44 95",
    "sg:postcode":"28937",
    "sg:province":"Madrid",
    "wof:name":"Vadillo Cortes Maria",
    "wof:placetype":"venue"
},
  "geometry": {"coordinates":[-3.852889061,40.3171539307],"type":"Point"}
}