{
  "type": "Feature",
  "properties": {
    "addr:full":"Via Laietana, 30 Barcelona Barcelona 08003",
    "addr:housenumber":"30",
    "addr:postcode":"08003",
    "addr:street":"Via Laietana",
    "iso:country":"ES",
    "sg:address":"Via Laietana, 30",
    "sg:city":"Barcelona",
    "sg:orig_category":"Edici\u00d3n De Diarios, Revistas, Boletines",
    "sg:phone":"+34 933 10 02 44",
    "sg:postcode":"08003",
    "sg:province":"Barcelona",
    "wof:name":"Editorial Alpha Sociedad Limitada",
    "wof:placetype":"venue"
},
  "geometry": {"coordinates":[2.1776719093,41.3849868774],"type":"Point"}
}