{
  "type": "Feature",
  "properties": {
    "iso:country":"ES",
    "sg:address":"Calle de Ontanilla, 11",
    "sg:city":"Carcar",
    "sg:orig_category":"Telas Y Sedas (al Por Menor)",
    "sg:phone":"+34 948 67 41 98",
    "sg:postcode":"31579",
    "sg:province":"Navarra",
    "wof:name":"Pardo Chalezquer Maximo",
    "wof:placetype":"venue"
},
  "geometry": {"coordinates":[-1.976849556,42.3921165466],"type":"Point"}
}