{
  "type": "Feature",
  "properties": {
    "addr:full":"Calle de Santiago, 24 Utebo Zaragoza 50180",
    "addr:housenumber":"24",
    "addr:postcode":"50180",
    "addr:street":"Calle De Santiago",
    "iso:country":"ES",
    "sg:address":"Calle de Santiago, 24",
    "sg:city":"Utebo",
    "sg:orig_category":"Delegados, Agentes De Tr\u00c1nsito, Auxiliares De Transporte Internacional",
    "sg:phone":"+34 976 78 42 07",
    "sg:postcode":"50180",
    "sg:province":"Zaragoza",
    "wof:name":"Rebollo Sanchez Juan Pablo",
    "wof:placetype":"venue"
},
  "geometry": {"coordinates":[-1.0005090237,41.7073745728],"type":"Point"}
}