{
  "type": "Feature",
  "properties": {
    "addr:full":"Calle de Hospital De San Jose, 25 Getafe Madrid 28901",
    "addr:postcode":"28901",
    "addr:street":"Calle De Hospital",
    "iso:country":"ES",
    "sg:address":"Calle de Hospital De San Jose, 25",
    "sg:city":"Getafe",
    "sg:orig_category":"Institutos De Belleza",
    "sg:phone":"+34 916 65 08 09",
    "sg:postcode":"28901",
    "sg:province":"Madrid",
    "wof:name":"Menchus Peluqueros S.l.",
    "wof:placetype":"venue"
},
  "geometry": {"coordinates":[-3.7291800976,40.3059616089],"type":"Point"}
}