{
  "type": "Feature",
  "properties": {
    "addr:full":"Carrer de Rossello, 27 Granollers Barcelona 08401",
    "addr:housenumber":"27",
    "addr:postcode":"08401",
    "addr:street":"Carrer De Rossello",
    "iso:country":"ES",
    "sg:address":"Carrer de Rossello, 27",
    "sg:city":"Granollers",
    "sg:orig_category":"Discapacitados",
    "sg:phone":"+34 938 46 71 14",
    "sg:postcode":"08401",
    "sg:province":"Barcelona",
    "wof:name":"Fundacio Privada Valles Oriental Per A Disminuits Psiquics",
    "wof:placetype":"venue"
},
  "geometry": {"coordinates":[2.2888491154,41.6151237488],"type":"Point"}
}