{
  "type": "Feature",
  "properties": {
    "addr:full":"Calle de Juan De Lanuza, 1 Monzon Huesca 22400",
    "addr:housenumber":"1",
    "addr:postcode":"22400",
    "addr:street":"Calle De Juan De Lanuza",
    "iso:country":"ES",
    "sg:address":"Calle de Juan De Lanuza, 1",
    "sg:city":"Monzon",
    "sg:orig_category":"Peluquer\u00cdas, Peluquer\u00cda Mixta",
    "sg:phone":"+34 974 40 02 52",
    "sg:postcode":"22400",
    "sg:province":"Huesca",
    "wof:name":"Camara Rivera Maria Luisa",
    "wof:placetype":"venue"
},
  "geometry": {"coordinates":[0.1915899962,41.9113197327],"type":"Point"}
}