{
  "type": "Feature",
  "properties": {
    "iso:country":"ES",
    "sg:address":"Calle de San Roque, 5",
    "sg:city":"Coru\u00d1a",
    "sg:orig_category":"Telas Para Tapizar, Cortinas, Pasamaner\u00cda (fabricaci\u00d3n, Al Por Mayor)",
    "sg:phone":"+34 981 20 35 52",
    "sg:postcode":"15002",
    "sg:province":"La Coru\u00f1a",
    "wof:name":"Martinez Cayazzo Maria Dolores Lucia",
    "wof:placetype":"venue"
},
  "geometry": {"coordinates":[-8.3975496292,43.3734092712],"type":"Point"}
}