{
  "type": "Feature",
  "properties": {
    "addr:full":"Calle de Jose Palanca, 12 Malaga M\u00e1laga 29003",
    "addr:housenumber":"12",
    "addr:postcode":"29003",
    "addr:street":"Calle De Jose Palanca;Ma\u0301Laga",
    "iso:country":"ES",
    "sg:address":"Calle de Jose Palanca, 12",
    "sg:city":"Malaga",
    "sg:orig_category":"Extinci\u00d3n De Incendios: Material Y Suministros (fabricaci\u00d3n, Al Por Mayor)",
    "sg:phone":"+34 952 35 43 74",
    "sg:postcode":"29003",
    "sg:province":"M\u00e1laga",
    "wof:name":"Extintores J.atienza S.l.",
    "wof:placetype":"venue"
},
  "geometry": {"coordinates":[-4.4464130402,36.7002067566],"type":"Point"}
}