{
  "type": "Feature",
  "properties": {
    "addr:full":"Carrer de Carretera Marina, 64 Prat Llobregat Barcelona 08820",
    "addr:housenumber":"64",
    "addr:postcode":"08820",
    "addr:street":"Carrer De Carretera Marina;Llobregat",
    "iso:country":"ES",
    "sg:address":"Carrer de Carretera Marina, 64",
    "sg:city":"Prat Llobregat",
    "sg:orig_category":"Cajas De Ahorro",
    "sg:phone":"+34 933 79 34 69",
    "sg:postcode":"08820",
    "sg:province":"Barcelona",
    "wof:name":"Caixa D'estalvis Del Penedes",
    "wof:placetype":"venue"
},
  "geometry": {"coordinates":[2.0864720345,41.3289909363],"type":"Point"}
}