{
  "type": "Feature",
  "properties": {
    "addr:full":"Calle de Puerta Del Sol, 10 Illescas Toledo 45200",
    "addr:housenumber":"10",
    "addr:postcode":"45200",
    "addr:street":"Calle De Puerta Del Sol",
    "iso:country":"ES",
    "sg:address":"Calle de Puerta Del Sol, 10",
    "sg:city":"Illescas",
    "sg:orig_category":"Caf\u00c9s, Bares, Cervecer\u00cdas",
    "sg:phone":"+34 925 51 36 32",
    "sg:postcode":"45200",
    "sg:province":"Toledo",
    "wof:name":"Urquiaga Eizaguirre Zigor",
    "wof:placetype":"venue"
},
  "geometry": {"coordinates":[-3.8472938538,40.1233329773],"type":"Point"}
}