{
  "type": "Feature",
  "properties": {
    "addr:full":"Calle de San Anton, 6 Logro\u00f1o La Rioja 26002",
    "addr:housenumber":"6",
    "addr:postcode":"26002",
    "addr:street":"Calle De San Anton;Rioja",
    "iso:country":"ES",
    "sg:address":"Calle de San Anton, 6",
    "sg:city":"Logro\u00f1o",
    "sg:orig_category":"Peluqueros: De Se\u00d1oras",
    "sg:phone":"+34 941 24 47 18",
    "sg:postcode":"26002",
    "sg:province":"La Rioja",
    "wof:name":"Jimenez Cordon Alicia Catalina",
    "wof:placetype":"venue"
},
  "geometry": {"coordinates":[-2.4470670223,42.4625587463],"type":"Point"}
}