{
  "type": "Feature",
  "properties": {
    "addr:full":"Avda Nuestra Se\u00d1ora De Fatima, 18 Madrid Madrid 28047",
    "addr:housenumber":"18",
    "addr:postcode":"madrid;28047",
    "addr:street":"Avda Nuestra Sen\u0303Ora De Fatima",
    "iso:country":"ES",
    "sg:address":"Avda Nuestra Se\u00d1ora De Fatima, 18",
    "sg:city":"Madrid",
    "sg:orig_category":"Fisioterapia",
    "sg:phone":"+34 914 62 87 14",
    "sg:postcode":"28047",
    "sg:province":"Madrid",
    "wof:name":"Fernandez Lopez Jose Carlos",
    "wof:placetype":"venue"
},
  "geometry": {"coordinates":[-3.7447481155,40.385925293],"type":"Point"}
}