{
  "type": "Feature",
  "properties": {
    "addr:full":"Calle de Armando Mu\u00d1oz Calero, 14 Aguilas Murcia 30880",
    "addr:housenumber":"14",
    "addr:postcode":"30880",
    "addr:street":"Calle De Armando Mun\u0303Oz Calero",
    "iso:country":"ES",
    "sg:address":"Calle de Armando Mu\u00d1oz Calero, 14",
    "sg:city":"Aguilas",
    "sg:orig_category":"Papeler\u00cdas, Librer\u00cdas",
    "sg:phone":"+34 968 44 80 45",
    "sg:postcode":"30880",
    "sg:province":"Murcia",
    "wof:name":"Carrillo Lopez Maria Del Carmen",
    "wof:placetype":"venue"
},
  "geometry": {"coordinates":[-1.5860538483,37.4045791626],"type":"Point"}
}