{
  "type": "Feature",
  "properties": {
    "iso:country":"ES",
    "sg:address":"Pl America, S/n",
    "sg:city":"Senia",
    "sg:orig_category":"Empresas De Carpinter\u00cda De Madera",
    "sg:phone":"+34 977 71 32 88",
    "sg:postcode":"43560",
    "sg:province":"Tarragona",
    "wof:name":"Fusteria Sintart S.l.",
    "wof:placetype":"venue"
},
  "geometry": {"coordinates":[0.2800700068,40.6382217407],"type":"Point"}
}