{
  "type": "Feature",
  "properties": {
    "addr:full":"Av. Gral. Franco, 3 Noia La Coru\u00f1a 15200",
    "addr:housenumber":"3",
    "addr:postcode":"15200",
    "addr:street":"Av. Gral. Franco;La Corun\u0303A",
    "iso:country":"ES",
    "sg:address":"Av. Gral. Franco, 3",
    "sg:city":"Noia",
    "sg:orig_category":"Delegados, Agentes De Tr\u00c1nsito, Auxiliares De Transporte Internacional",
    "sg:phone":"+34 981 82 02 68",
    "sg:postcode":"15200",
    "sg:province":"La Coru\u00f1a",
    "wof:name":"Blanco Filgueira Ramon",
    "wof:placetype":"venue"
},
  "geometry": {"coordinates":[-8.8883037567,42.788608551],"type":"Point"}
}