{
  "type": "Feature",
  "properties": {
    "iso:country":"ES",
    "sg:address":"Carrer de Europa, 26",
    "sg:city":"Barcelona",
    "sg:orig_category":"Prendas Y Chalecos De Punto (al Por Menor)",
    "sg:phone":"+34 934 30 77 47",
    "sg:postcode":"08028",
    "sg:province":"Barcelona",
    "wof:name":"Massagues Amat Rosa Maria",
    "wof:placetype":"venue"
},
  "geometry": {"coordinates":[2.1304290295,41.387134552],"type":"Point"}
}