{
  "type": "Feature",
  "properties": {
    "addr:full":"Calle de Pintor Obdulio Lopez De Uralde, 3 Vitoria-gasteiz \u00c1lava 01008",
    "addr:housenumber":"3",
    "addr:postcode":"01008",
    "addr:street":"Calle De Pintor Obdulio Lopez De Uralde",
    "iso:country":"ES",
    "sg:address":"Calle de Pintor Obdulio Lopez De Uralde, 3",
    "sg:city":"Vitoria-gasteiz",
    "sg:orig_category":"Laboratorios",
    "sg:phone":"+34 945 20 00 15",
    "sg:postcode":"01008",
    "sg:province":"\u00c1lava",
    "wof:name":"Laboratorios Bromatologicos Araba S.a.",
    "wof:placetype":"venue"
},
  "geometry": {"coordinates":[-2.6864891052,42.8453559875],"type":"Point"}
}