{
  "type": "Feature",
  "properties": {
    "addr:full":"Carrer de Comer\u00c7, 7 Hospitalet Llobregat Barcelona 08902",
    "addr:housenumber":"7",
    "addr:postcode":"08902",
    "addr:street":"Carrer De Comerc\u0327",
    "iso:country":"ES",
    "sg:address":"Carrer de Comer\u00c7, 7",
    "sg:city":"Hospitalet Llobregat",
    "sg:orig_category":"Fabricaci\u00d3n De Muebles",
    "sg:phone":"+34 934 32 21 80",
    "sg:postcode":"08902",
    "sg:province":"Barcelona",
    "wof:name":"Picot 7 S.c.p.",
    "wof:placetype":"venue"
},
  "geometry": {"coordinates":[2.1259870529,41.3664932251],"type":"Point"}
}