{
  "type": "Feature",
  "properties": {
    "iso:country":"ES",
    "sg:address":"Carrer de Ruben Dario, 125",
    "sg:city":"Barcelona",
    "sg:orig_category":"Juegos Y Juguetes (al Por Menor)",
    "sg:phone":"+34 933 45 21 03",
    "sg:postcode":"08030",
    "sg:province":"Barcelona",
    "sg:website":"www.naipsbcn.com",
    "wof:name":"Naips Bcn S.l.",
    "wof:placetype":"venue"
},
  "geometry": {"coordinates":[2.1844780445,41.4345855713],"type":"Point"}
}