{
  "type": "Feature",
  "properties": {
    "addr:full":"Calle de Teniente Mu\u00d1oz Diaz, 10 Madrid Madrid 28018",
    "addr:housenumber":"10",
    "addr:postcode":"madrid;28018",
    "addr:street":"Calle De Teniente Mun\u0303Oz Diaz",
    "iso:country":"ES",
    "sg:address":"Calle de Teniente Mu\u00d1oz Diaz, 10",
    "sg:city":"Madrid",
    "sg:orig_category":"Importaci\u00d3n",
    "sg:phone":"+34 917 57 01 49",
    "sg:postcode":"28018",
    "sg:province":"Madrid",
    "wof:name":"Sandaly Import-export S.l.",
    "wof:placetype":"venue"
},
  "geometry": {"coordinates":[-3.6552569866,40.3916625977],"type":"Point"}
}