{
  "type": "Feature",
  "properties": {
    "iso:country":"ES",
    "sg:address":"Calle de Cuatro Picos (de), 17",
    "sg:city":"Nogal",
    "sg:orig_category":"Tintorer\u00cdas, Limpieza En Seco",
    "sg:phone":"+34 916 28 93 43",
    "sg:postcode":"28110",
    "sg:province":"Madrid",
    "wof:name":"La Nueva Lavanderia Constanza S.l.",
    "wof:placetype":"venue"
},
  "geometry": {"coordinates":[-3.7003455162,40.4166908264],"type":"Point"}
}