{
  "type": "Feature",
  "properties": {
    "addr:full":"Calle de Doctores Castroviejo, 48 Calahorra La Rioja 26500",
    "addr:housenumber":"48",
    "addr:postcode":"26500",
    "addr:street":"Calle De Doctores Castroviejo",
    "iso:country":"ES",
    "sg:address":"Calle de Doctores Castroviejo, 48",
    "sg:city":"Calahorra",
    "sg:orig_category":"Transportes Por V\u00cdas Navegables",
    "sg:phone":"+34 941 13 00 33",
    "sg:postcode":"26500",
    "sg:province":"La Rioja",
    "wof:name":"Gil Aguilar Francisco",
    "wof:placetype":"venue"
},
  "geometry": {"coordinates":[-1.9690862894,42.3103790283],"type":"Point"}
}