{
  "type": "Feature",
  "properties": {
    "addr:full":"Calle de Costa Brava, 16 Madrid Madrid 28034",
    "addr:housenumber":"16",
    "addr:postcode":"madrid;28034",
    "addr:street":"Calle De Costa Brava",
    "iso:country":"ES",
    "sg:address":"Calle de Costa Brava, 16",
    "sg:city":"Madrid",
    "sg:orig_category":"Abogados",
    "sg:phone":"+34 917 34 03 41",
    "sg:postcode":"28034",
    "sg:province":"Madrid",
    "wof:name":"Antequera Arce Juan",
    "wof:placetype":"venue"
},
  "geometry": {"coordinates":[-3.7091486454,40.4984321594],"type":"Point"}
}