{
  "type": "Feature",
  "properties": {
    "addr:full":"Rua Asturias, 1 Vigo Pontevedra 36206",
    "addr:housenumber":"1",
    "addr:postcode":"36206",
    "addr:street":"Rua Asturias",
    "iso:country":"ES",
    "sg:address":"Rua Asturias, 1",
    "sg:city":"Vigo",
    "sg:orig_category":"Peluquer\u00cdas, Peluquer\u00cda Mixta",
    "sg:phone":"+34 986 25 18 78",
    "sg:postcode":"36206",
    "sg:province":"Pontevedra",
    "wof:name":"Gonzalez Calvo Miguel Angel",
    "wof:placetype":"venue"
},
  "geometry": {"coordinates":[-8.7071619034,42.2336502075],"type":"Point"}
}