{
  "type": "Feature",
  "properties": {
    "addr:full":"Calle de Mar Caspio, 7 Sevilla Sevilla 41009",
    "addr:housenumber":"7",
    "addr:postcode":"41009",
    "addr:street":"Calle De Mar Caspio",
    "iso:country":"ES",
    "sg:address":"Calle de Mar Caspio, 7",
    "sg:city":"Sevilla",
    "sg:orig_category":"Lencer\u00cda Femenina, Corseter\u00cda, Trajes De Ba\u00d1o (al Por Menor)",
    "sg:phone":"+34 954 35 66 47",
    "sg:postcode":"41009",
    "sg:province":"Sevilla",
    "wof:name":"Selecciones Chamy S.l.",
    "wof:placetype":"venue"
},
  "geometry": {"coordinates":[-5.9788761139,37.4081802368],"type":"Point"}
}