{
  "type": "Feature",
  "properties": {
    "addr:full":"Urb Soto (el), S/n Soto Guadalajara 19462",
    "addr:housenumber":"/ n",
    "addr:postcode":"19462",
    "addr:street":"Urb Soto El S",
    "iso:country":"ES",
    "sg:address":"Urb Soto (el), S/n",
    "sg:city":"Soto",
    "sg:orig_category":"Quincaller\u00cda (al Por Menor)",
    "sg:phone":"+34 969 14 83 66",
    "sg:postcode":"19462",
    "sg:province":"Guadalajara",
    "wof:name":"Alonso Roldan Jesus",
    "wof:placetype":"venue"
},
  "geometry": {"coordinates":[-3.1664927006,40.6298179626],"type":"Point"}
}