{
  "type": "Feature",
  "properties": {
    "addr:full":"Calle de Montejano, 57 Pedro\u00d1eras Cuenca 16660",
    "addr:housenumber":"57",
    "addr:postcode":"16660",
    "addr:street":"Calle De Montejano",
    "iso:country":"ES",
    "sg:address":"Calle de Montejano, 57",
    "sg:city":"Pedro\u00d1eras",
    "sg:orig_category":"Abogados",
    "sg:phone":"+34 967 16 04 10",
    "sg:postcode":"16660",
    "sg:province":"Cuenca",
    "wof:name":"Tortosa Ruiz Maria Dolores",
    "wof:placetype":"venue"
},
  "geometry": {"coordinates":[-2.6746330261,39.4505271912],"type":"Point"}
}