{
  "type": "Feature",
  "properties": {
    "addr:full":"Calle de Calixto Hornedo, 41 Daimiel Ciudad Real 13250",
    "addr:housenumber":"41",
    "addr:postcode":"13250",
    "addr:street":"Calle De Calixto Hornedo",
    "iso:country":"ES",
    "sg:address":"Calle de Calixto Hornedo, 41",
    "sg:city":"Daimiel",
    "sg:orig_category":"Reposter\u00cdas",
    "sg:phone":"+34 926 85 00 54",
    "sg:postcode":"13250",
    "sg:province":"Ciudad Real",
    "wof:name":"Panificadora San Honorato De Daimiel S.a.l.",
    "wof:placetype":"venue"
},
  "geometry": {"coordinates":[-3.6070291996,39.067276001],"type":"Point"}
}