{
  "type": "Feature",
  "properties": {
    "iso:country":"ES",
    "sg:address":"Calle de Juan Espa\u00d1ol, 38",
    "sg:city":"Madrid",
    "sg:orig_category":"Fabricaci\u00d3n De Juegos Y Juguetes",
    "sg:phone":"+34 914 69 49 97",
    "sg:postcode":"28026",
    "sg:province":"Madrid",
    "wof:name":"Rodriguez Portillo Alfredo",
    "wof:placetype":"venue"
},
  "geometry": {"coordinates":[-3.7129580975,40.386505127],"type":"Point"}
}