{
  "type": "Feature",
  "properties": {
    "iso:country":"ES",
    "sg:address":"Carrer de Sardenya, 221",
    "sg:city":"Barcelona",
    "sg:orig_category":"Agencias Y Agentes Comerciales, Representantes",
    "sg:phone":"+34 932 31 28 65",
    "sg:postcode":"08013",
    "sg:province":"Barcelona",
    "wof:name":"Garcia Domenech Francisco",
    "wof:placetype":"venue"
},
  "geometry": {"coordinates":[2.1778569221,41.3997879028],"type":"Point"}
}