{
  "type": "Feature",
  "properties": {
    "iso:country":"ES",
    "sg:address":"Calle de Amara, 9",
    "sg:city":"Donostia-san Sebastian",
    "sg:orig_category":"M\u00c9dicos: Fisioterapia Y Rehabilitaci\u00d3n",
    "sg:phone":"+34 943 46 31 44",
    "sg:postcode":"20006",
    "sg:province":"Guip\u00f9zcoa",
    "wof:name":"Centro De Rehabilitacion Zuzpertu S.l.",
    "wof:placetype":"venue"
},
  "geometry": {"coordinates":[-1.9835641384,43.3131790161],"type":"Point"}
}