{
  "type": "Feature",
  "properties": {
    "iso:country":"ES",
    "sg:address":"Calle de Don Pedro Gonzalez, 17",
    "sg:city":"Galaroza",
    "sg:orig_category":"Asociaciones Humanitarias, De Cooperaci\u00d3n, De Acci\u00d3n Social",
    "sg:phone":"+34 959 12 33 26",
    "sg:postcode":"21291",
    "sg:province":"Huelva",
    "wof:name":"Asociacion Protectora De Deficientes Psiquicos Paz Y Bien De Sevilla",
    "wof:placetype":"venue"
},
  "geometry": {"coordinates":[-6.712618351,37.9256210327],"type":"Point"}
}