{
  "type": "Feature",
  "properties": {
    "iso:country":"ES",
    "sg:address":"Calle de Jorge Juan, 83",
    "sg:city":"Madrid",
    "sg:orig_category":"Cl\u00cdnicas Dentales",
    "sg:phone":"+34 915 78 13 11",
    "sg:postcode":"28009",
    "sg:province":"Madrid",
    "wof:name":"Dentin S.l.",
    "wof:placetype":"venue"
},
  "geometry": {"coordinates":[-3.6750369072,40.4234657288],"type":"Point"}
}