{
  "type": "Feature",
  "properties": {
    "iso:country":"ES",
    "sg:address":"Calle de Algaba, 18",
    "sg:city":"Madrid",
    "sg:orig_category":"Mercer\u00cda, Lencer\u00cda (al Por Menor)",
    "sg:phone":"+34 914 65 12 13",
    "sg:postcode":"28019",
    "sg:province":"Madrid",
    "wof:name":"Sanchez Gutierrez Margarita",
    "wof:placetype":"venue"
},
  "geometry": {"coordinates":[-3.7370710373,40.3916015625],"type":"Point"}
}