{
  "type": "Feature",
  "properties": {
    "addr:full":"Calle de Puerto, 15 Donostia-san Sebastian Guip\u00f9zcoa 20003",
    "addr:housenumber":"15",
    "addr:postcode":"20003",
    "addr:street":"Calle De Puerto",
    "iso:country":"ES",
    "sg:address":"Calle de Puerto, 15",
    "sg:city":"Donostia-san Sebastian",
    "sg:orig_category":"Artesan\u00cda",
    "sg:phone":"+34 943 42 03 16",
    "sg:postcode":"20003",
    "sg:province":"Guip\u00f9zcoa",
    "wof:name":"Viviana Rodriguez Perez",
    "wof:placetype":"venue"
},
  "geometry": {"coordinates":[-1.98645401,43.3231048584],"type":"Point"}
}