{
  "type": "Feature",
  "properties": {
    "iso:country":"ES",
    "sg:address":"Calle de Goya, 6",
    "sg:city":"Zaidin",
    "sg:orig_category":"Agencias Y Agentes Comerciales, Representantes",
    "sg:phone":"+34 974 47 80 48",
    "sg:postcode":"22530",
    "sg:province":"Huesca",
    "wof:name":"Garcia Ibarz Jose Luis",
    "wof:placetype":"venue"
},
  "geometry": {"coordinates":[0.2672669888,41.6038780212],"type":"Point"}
}