{
  "type": "Feature",
  "properties": {
    "iso:country":"ES",
    "sg:address":"Via Portugal, 16",
    "sg:city":"Manacor",
    "sg:orig_category":"Bisuteros (fabricaci\u00d3n, Al Por Mayor)",
    "sg:phone":"+34 971 55 11 21",
    "sg:postcode":"07500",
    "sg:province":"Islas Baleares",
    "wof:name":"Celimar Joyeria S.a.",
    "wof:placetype":"venue"
},
  "geometry": {"coordinates":[3.2144069672,39.5664405823],"type":"Point"}
}