{
  "type": "Feature",
  "properties": {
    "iso:country":"ES",
    "sg:address":"Calle de Adrian Pulido, 7",
    "sg:city":"Madrid",
    "sg:orig_category":"Ense\u00d1anza Variada",
    "sg:phone":"+34 914 59 42 61",
    "sg:postcode":"28039",
    "sg:province":"Madrid",
    "wof:name":"Learning Innovaciones Pedagogicas S. A.",
    "wof:placetype":"venue"
},
  "geometry": {"coordinates":[-3.7059311867,40.4538002014],"type":"Point"}
}