{
  "type": "Feature",
  "properties": {
    "iso:country":"ES",
    "sg:address":"Calle de Viejo Pancho, 9",
    "sg:city":"Ribadeo",
    "sg:orig_category":"Florister\u00cdas",
    "sg:phone":"+34 982 13 09 11",
    "sg:postcode":"27700",
    "sg:province":"Lugo",
    "wof:name":"Garcia Perez Maria Isabel",
    "wof:placetype":"venue"
},
  "geometry": {"coordinates":[-7.0408220291,43.5371055603],"type":"Point"}
}