{
  "type": "Feature",
  "properties": {
    "addr:full":"Avda Pardo (el), 3 Sax Alicante 03630",
    "addr:housenumber":"3",
    "addr:postcode":"03630",
    "addr:street":"Avda Pardo El",
    "iso:country":"ES",
    "sg:address":"Avda Pardo (el), 3",
    "sg:city":"Sax",
    "sg:orig_category":"Textil",
    "sg:phone":"+34 966 96 76 20",
    "sg:postcode":"03630",
    "sg:province":"Alicante",
    "wof:name":"Bloken Iberica S.l.",
    "wof:placetype":"venue"
},
  "geometry": {"coordinates":[-0.8217530251,38.5324630737],"type":"Point"}
}