{
  "type": "Feature",
  "properties": {
    "addr:full":"Luga Granda, S/n Granda Asturias 33199",
    "addr:housenumber":"/ n",
    "addr:postcode":"33199",
    "addr:street":"S",
    "iso:country":"ES",
    "sg:address":"Luga Granda, S/n",
    "sg:city":"Granda",
    "sg:orig_category":"Negocio De Madera",
    "sg:phone":"+34 985 98 51 06",
    "sg:postcode":"33199",
    "sg:province":"Asturias",
    "wof:name":"Maderas Adriano Perez E Hijos S.a.",
    "wof:placetype":"venue"
},
  "geometry": {"coordinates":[-5.7986898422,43.3584632874],"type":"Point"}
}