{
  "type": "Feature",
  "properties": {
    "iso:country":"ES",
    "sg:address":"Plaz Espa\u00d1a (de), S/n",
    "sg:city":"Valdepe\u00f1as",
    "sg:orig_category":"Molduras, Junquillos, Listones Y Molduras Perforadas",
    "sg:phone":"+34 926 31 23 51",
    "sg:postcode":"13300",
    "sg:province":"Ciudad Real",
    "wof:name":"Francisco De La Due\u00f1a Gutierrez Y Otro Cdad",
    "wof:placetype":"venue"
},
  "geometry": {"coordinates":[-3.4151580334,38.763469696],"type":"Point"}
}