{
  "type": "Feature",
  "properties": {
    "addr:full":"Calle de Serena, 26 Madrid Madrid 28053",
    "addr:housenumber":"26",
    "addr:postcode":"madrid;28053",
    "addr:street":"Calle De Serena",
    "iso:country":"ES",
    "sg:address":"Calle de Serena, 26",
    "sg:city":"Madrid",
    "sg:orig_category":"Asilos De Ancianos. Centros Privados",
    "sg:phone":"+34 915 07 33 80",
    "sg:postcode":"28053",
    "sg:province":"Madrid",
    "wof:name":"Club Pensionistas Centro Socio Cultural De Entrevias",
    "wof:placetype":"venue"
},
  "geometry": {"coordinates":[-3.6657218933,40.3790473938],"type":"Point"}
}