{
  "type": "Feature",
  "properties": {
    "iso:country":"ES",
    "sg:address":"Finca Las Perdices, S/n",
    "sg:city":"Los Pocicos",
    "sg:orig_category":"Producci\u00d3n, Comercio De Cereales",
    "sg:phone":"+34 967 58 40 03",
    "sg:postcode":"02129",
    "sg:province":"Albacete",
    "wof:name":"Pedro Ortiz Ortiz Y Francisco Sanchez Garcia Cdad",
    "wof:placetype":"venue"
},
  "geometry": {"coordinates":[-2.0263590813,38.6925010681],"type":"Point"}
}