{
  "type": "Feature",
  "properties": {
    "iso:country":"ES",
    "sg:address":"Avda Alpujarra, 11",
    "sg:city":"Lanjaron",
    "sg:orig_category":"Peluquer\u00cdas, Peluquer\u00cda Mixta",
    "sg:phone":"+34 958 77 09 37",
    "sg:postcode":"18420",
    "sg:province":"Granada",
    "wof:name":"Lopez Gutierrez Amparo",
    "wof:placetype":"venue"
},
  "geometry": {"coordinates":[-3.4888560772,36.9190063477],"type":"Point"}
}