{
  "type": "Feature",
  "properties": {
    "addr:full":"Calle de Bolivar Simon, 26 Bilbao Vizcaya 48013",
    "addr:housenumber":"26",
    "addr:postcode":"48013",
    "addr:street":"Calle De Bolivar Simon",
    "iso:country":"ES",
    "sg:address":"Calle de Bolivar Simon, 26",
    "sg:city":"Bilbao",
    "sg:orig_category":"Inform\u00c1tica (estudios, Servicios, Asesor\u00cda, Formaci\u00d3n)",
    "sg:phone":"+34 944 42 30 79",
    "sg:postcode":"48013",
    "sg:province":"Vizcaya",
    "sg:website":"www.ftworldonline.com",
    "wof:name":"Future World S.l.",
    "wof:placetype":"venue"
},
  "geometry": {"coordinates":[-2.9457228184,43.2608642578],"type":"Point"}
}