{
  "type": "Feature",
  "properties": {
    "addr:full":"Pg Dintre (de), 13 Blanes Girona 17300",
    "addr:housenumber":"13",
    "addr:postcode":"17300",
    "addr:street":"Pg Dintre De",
    "iso:country":"ES",
    "sg:address":"Pg Dintre (de), 13",
    "sg:city":"Blanes",
    "sg:orig_category":"Cajas De Ahorro",
    "sg:phone":"+34 972 33 73 71",
    "sg:postcode":"17300",
    "sg:province":"Girona",
    "wof:name":"Caixa D'estalvis Del Penedes",
    "wof:placetype":"venue"
},
  "geometry": {"coordinates":[2.7920889854,41.6741943359],"type":"Point"}
}