{
  "type": "Feature",
  "properties": {
    "addr:full":"Luisa Conde, 7 Simancas Valladolid 47130",
    "addr:housenumber":"7",
    "addr:postcode":"47130",
    "addr:street":"Conde",
    "iso:country":"ES",
    "sg:address":"Luisa Conde, 7",
    "sg:city":"Simancas",
    "sg:orig_category":"Pintores",
    "sg:phone":"+34 983 59 01 31",
    "sg:postcode":"47130",
    "sg:province":"Valladolid",
    "wof:name":"Gaona Huidobro Gabino",
    "wof:placetype":"venue"
},
  "geometry": {"coordinates":[-4.8267989159,41.5895195007],"type":"Point"}
}