{
  "type": "Feature",
  "properties": {
    "addr:full":"Calle de Doctor Esquerdo, 91 Madrid Madrid 28007",
    "addr:housenumber":"91",
    "addr:postcode":"madrid;28007",
    "addr:street":"Calle De Doctor Esquerdo",
    "iso:country":"ES",
    "sg:address":"Calle de Doctor Esquerdo, 91",
    "sg:city":"Madrid",
    "sg:orig_category":"Arreglo, Reparaci\u00d3n, Piezas Sueltas De Televisi\u00d3n, V\u00cddeo, Hi",
    "sg:phone":"+34 915 04 04 00",
    "sg:postcode":"28007",
    "sg:province":"Madrid",
    "wof:name":"De Francisco Martin Leandro",
    "wof:placetype":"venue"
},
  "geometry": {"coordinates":[-3.6692168713,40.4172477722],"type":"Point"}
}