{
  "type": "Feature",
  "properties": {
    "iso:country":"ES",
    "sg:address":"Avda Bilbao, 8",
    "sg:city":"Ortuella",
    "sg:orig_category":"Partidos Pol\u00cdticos",
    "sg:phone":"+34 946 64 14 67",
    "sg:postcode":"48530",
    "sg:province":"Vizcaya",
    "wof:name":"Partido Socialista Obrero Espa\u00f1ol",
    "wof:placetype":"venue"
},
  "geometry": {"coordinates":[-3.0524570942,43.3085289001],"type":"Point"}
}