{
  "type": "Feature",
  "properties": {
    "iso:country":"ES",
    "sg:address":"Calle de Santa Isabel, 8",
    "sg:city":"Cordoba",
    "sg:orig_category":"Electricidad: Equipos Industriales, Componentes (fabricaci\u00d3n)",
    "sg:phone":"+34 957 48 64 03",
    "sg:postcode":"14001",
    "sg:province":"C\u00f3rdoba",
    "sg:website":"www.antelec.com",
    "wof:name":"Antelec S.l.",
    "wof:placetype":"venue"
},
  "geometry": {"coordinates":[-4.7747707367,37.8890724182],"type":"Point"}
}