{
  "type": "Feature",
  "properties": {
    "addr:full":"Carr Llobregat, 4 Figueres Girona 17600",
    "addr:housenumber":"4",
    "addr:postcode":"17600",
    "addr:street":"Carr Llobregat",
    "iso:country":"ES",
    "sg:address":"Carr Llobregat, 4",
    "sg:city":"Figueres",
    "sg:orig_category":"Caf\u00c9s, Bares, Cervecer\u00cdas",
    "sg:phone":"+34 972 50 14 91",
    "sg:postcode":"17600",
    "sg:province":"Girona",
    "wof:name":"El Suprem S.c.",
    "wof:placetype":"venue"
},
  "geometry": {"coordinates":[2.9581100941,42.2656898499],"type":"Point"}
}