{
  "type": "Feature",
  "properties": {
    "iso:country":"ES",
    "sg:address":"Av Girona, 56",
    "sg:city":"Olot",
    "sg:orig_category":"Juegos Y Juguetes (al Por Menor)",
    "sg:phone":"+34 972 26 27 05",
    "sg:postcode":"17800",
    "sg:province":"Girona",
    "wof:name":"Familia Vila Morera S.l.",
    "wof:placetype":"venue"
},
  "geometry": {"coordinates":[2.4964940548,42.186870575],"type":"Point"}
}