{
  "type": "Feature",
  "properties": {
    "addr:full":"Pque Sagrado Corazon, S/n Cedeira La Coru\u00f1a 15350",
    "addr:housenumber":"s / n",
    "addr:postcode":"15350",
    "addr:street":"La Corun\u0303A",
    "iso:country":"ES",
    "sg:address":"Pque Sagrado Corazon, S/n",
    "sg:city":"Cedeira",
    "sg:orig_category":"Molduras, Junquillos, Listones Y Molduras Perforadas",
    "sg:phone":"+34 981 48 04 96",
    "sg:postcode":"15350",
    "sg:province":"La Coru\u00f1a",
    "wof:name":"Brandeiro Rey Amable",
    "wof:placetype":"venue"
},
  "geometry": {"coordinates":[-8.0549125671,43.6599960327],"type":"Point"}
}