{
  "type": "Feature",
  "properties": {
    "iso:country":"ES",
    "sg:address":"Calle de Doramas, 9",
    "sg:city":"Puerto Del Carmen",
    "sg:orig_category":"Alquiler De Veh\u00cdculos: Turismos Y Utilitarios",
    "sg:phone":"+34 928 51 38 30",
    "sg:postcode":"35510",
    "sg:province":"Las Palmas",
    "wof:name":"Autos Cabrera Medina S.l.",
    "wof:placetype":"venue"
},
  "geometry": {"coordinates":[-13.6594486237,28.9212207794],"type":"Point"}
}