{
  "type": "Feature",
  "properties": {
    "addr:full":"Calle de Fray Gabriel San Antonio, 28 Marchamalo Guadalajara 19180",
    "addr:housenumber":"28",
    "addr:postcode":"19180",
    "addr:street":"Calle De Fray Gabriel San Antonio",
    "iso:country":"ES",
    "sg:address":"Calle de Fray Gabriel San Antonio, 28",
    "sg:city":"Marchamalo",
    "sg:orig_category":"Controles De Edificaci\u00d3n (construcci\u00d3n, Seguridad)",
    "sg:phone":"+34 949 21 34 02",
    "sg:postcode":"19180",
    "sg:province":"Guadalajara",
    "wof:name":"Pearza S.l.",
    "wof:placetype":"venue"
},
  "geometry": {"coordinates":[-3.2014870644,40.6685218811],"type":"Point"}
}