{
  "type": "Feature",
  "properties": {
    "addr:full":"Avda Navarra, 2 Tarazona Zaragoza 50500",
    "addr:housenumber":"2",
    "addr:postcode":"50500",
    "addr:street":"Avda Navarra",
    "iso:country":"ES",
    "sg:address":"Avda Navarra, 2",
    "sg:city":"Tarazona",
    "sg:orig_category":"Cajas De Ahorro",
    "sg:phone":"+34 976 64 18 24",
    "sg:postcode":"50500",
    "sg:province":"Zaragoza",
    "wof:name":"Caja De Ahorros Y Monte De Piedad De Zaragoza Aragon Y Rioja",
    "wof:placetype":"venue"
},
  "geometry": {"coordinates":[-1.7246769667,41.9085273743],"type":"Point"}
}