{
  "type": "Feature",
  "properties": {
    "addr:full":"Calle de Federico Garcia Lorca, 1 Valladolid Valladolid 47008",
    "addr:housenumber":"1",
    "addr:postcode":"47008",
    "addr:street":"Calle De Federico Garcia Lorca",
    "iso:country":"ES",
    "sg:address":"Calle de Federico Garcia Lorca, 1",
    "sg:city":"Valladolid",
    "sg:orig_category":"Deportes Diversos",
    "sg:phone":"+34 983 24 94 26",
    "sg:postcode":"47008",
    "sg:province":"Valladolid",
    "wof:name":"Federacion De Tenis Castilla Y Leon",
    "wof:placetype":"venue"
},
  "geometry": {"coordinates":[-4.7511062622,41.6155700684],"type":"Point"}
}