{
  "type": "Feature",
  "properties": {
    "addr:full":"Pol. Ind. La Guera, S/n Burgo Osma Soria 42300",
    "addr:housenumber":"s / n",
    "addr:postcode":"42300",
    "iso:country":"ES",
    "sg:address":"Pol. Ind. La Guera, S/n",
    "sg:city":"Burgo Osma",
    "sg:orig_category":"Contenedores (mercanc\u00cdas)",
    "sg:phone":"+34 975 36 82 02",
    "sg:postcode":"42300",
    "sg:province":"Soria",
    "wof:name":"Logistica Y Transportes De Pedro",
    "wof:placetype":"venue"
},
  "geometry": {"coordinates":[-3.0742990971,41.5880050659],"type":"Point"}
}