{
  "type": "Feature",
  "properties": {
    "iso:country":"ES",
    "sg:address":"Calle de Cervantes, 2",
    "sg:city":"Callosa Segura",
    "sg:orig_category":"M\u00c9dicos: Oftalmolog\u00cda",
    "sg:phone":"+34 965 31 13 58",
    "sg:postcode":"03360",
    "sg:province":"Alicante",
    "wof:name":"Minguez Rives Abelardo",
    "wof:placetype":"venue"
},
  "geometry": {"coordinates":[-0.8778319955,38.1242866516],"type":"Point"}
}