{
  "type": "Feature",
  "properties": {
    "iso:country":"ES",
    "sg:address":"Rua Celso Emilio Ferreiro, 11",
    "sg:city":"Celanova",
    "sg:orig_category":"Florister\u00cdas",
    "sg:phone":"+34 988 45 12 73",
    "sg:postcode":"32800",
    "sg:province":"Ourense",
    "wof:name":"Maisi\u00f1a S.l.l.",
    "wof:placetype":"venue"
},
  "geometry": {"coordinates":[-7.9562039375,42.1530151367],"type":"Point"}
}