{
  "type": "Feature",
  "properties": {
    "addr:full":"Avda Gaiarre Julian, 27 Bilbao Vizcaya 48004",
    "addr:housenumber":"27",
    "addr:postcode":"48004",
    "addr:street":"Avda Gaiarre Julian",
    "iso:country":"ES",
    "sg:address":"Avda Gaiarre Julian, 27",
    "sg:city":"Bilbao",
    "sg:orig_category":"Ingenier\u00cda, Centros De Estudios (diversos)",
    "sg:phone":"+34 944 12 93 33",
    "sg:postcode":"48004",
    "sg:province":"Vizcaya",
    "wof:name":"Ingisa Proyectos S.l.",
    "wof:placetype":"venue"
},
  "geometry": {"coordinates":[-2.9021420479,43.2533912659],"type":"Point"}
}