{
  "type": "Feature",
  "properties": {
    "addr:full":"Calle de Francisco Yufera, 1 Puerto Mazarron Murcia 30860",
    "addr:housenumber":"1",
    "addr:postcode":"30860",
    "addr:street":"Calle De Francisco Yufera",
    "iso:country":"ES",
    "sg:address":"Calle de Francisco Yufera, 1",
    "sg:city":"Puerto Mazarron",
    "sg:orig_category":"Bazares, Art\u00cdculos De Limpieza Y De Cocina (al Por Menor)",
    "sg:phone":"+34 968 59 43 93",
    "sg:postcode":"30860",
    "sg:province":"Murcia",
    "wof:name":"Rivas Saez Enrique",
    "wof:placetype":"venue"
},
  "geometry": {"coordinates":[-1.2600530386,37.5637626648],"type":"Point"}
}