{
  "type": "Feature",
  "properties": {
    "iso:country":"ES",
    "sg:address":"Rua Sol, 7",
    "sg:city":"Melide",
    "sg:orig_category":"Empresas De Carpinter\u00cda De Madera",
    "sg:phone":"+34 981 50 52 83",
    "sg:postcode":"15800",
    "sg:province":"La Coru\u00f1a",
    "wof:name":"Laya Varela Joaquin",
    "wof:placetype":"venue"
},
  "geometry": {"coordinates":[-8.0127782822,42.9128036499],"type":"Point"}
}