{
  "type": "Feature",
  "properties": {
    "iso:country":"ES",
    "sg:address":"Avda Burgos, S/n",
    "sg:city":"Aguilar Campoo",
    "sg:orig_category":"Metales (labores, Pulido)",
    "sg:phone":"+34 979 12 28 05",
    "sg:postcode":"34800",
    "sg:province":"Palencia",
    "wof:name":"Serna Villanueva Andres",
    "wof:placetype":"venue"
},
  "geometry": {"coordinates":[-4.2548642159,42.7931556702],"type":"Point"}
}