{
  "type": "Feature",
  "properties": {
    "iso:country":"ES",
    "sg:address":"Carrer de Avinyo, 18",
    "sg:city":"Barcelona",
    "sg:orig_category":"Ropa Para Se\u00d1oras (al Por Menor)",
    "sg:phone":"+34 933 01 00 06",
    "sg:postcode":"08002",
    "sg:province":"Barcelona",
    "wof:name":"Esteve Murt Jaume",
    "wof:placetype":"venue"
},
  "geometry": {"coordinates":[2.1765329838,41.3810539246],"type":"Point"}
}