{
  "type": "Feature",
  "properties": {
    "iso:country":"ES",
    "sg:address":"Rbla Marina, 247",
    "sg:city":"Hospitalet Llobregat",
    "sg:orig_category":"Caf\u00c9s, Bares, Cervecer\u00cdas",
    "sg:phone":"+34 932 61 85 89",
    "sg:postcode":"08907",
    "sg:province":"Barcelona",
    "wof:name":"Artola Franco Matias",
    "wof:placetype":"venue"
},
  "geometry": {"coordinates":[2.1085247993,41.3513679504],"type":"Point"}
}