{
  "type": "Feature",
  "properties": {
    "addr:full":"Carr Alemanya, 45 Igualada Barcelona 08700",
    "addr:housenumber":"45",
    "addr:postcode":"08700",
    "addr:street":"Carr Alemanya",
    "iso:country":"ES",
    "sg:address":"Carr Alemanya, 45",
    "sg:city":"Igualada",
    "sg:orig_category":"Fabricaci\u00d3n De Su\u00c9ters Y Chalecos De Punto",
    "sg:phone":"+34 938 03 94 50",
    "sg:postcode":"08700",
    "sg:province":"Barcelona",
    "wof:name":"Piernas Rodriguez Josep Maria",
    "wof:placetype":"venue"
},
  "geometry": {"coordinates":[1.6329250336,41.5854301453],"type":"Point"}
}