{
  "type": "Feature",
  "properties": {
    "iso:country":"ES",
    "sg:address":"Titet, 5",
    "sg:city":"S. Antonio Benageber",
    "sg:orig_category":"Estudios De Grabaci\u00d3n Sonora",
    "sg:phone":"+34 961 35 14 20",
    "sg:postcode":"46184",
    "sg:province":"Valencia",
    "wof:name":"Colinas Musica S.l.",
    "wof:placetype":"venue"
},
  "geometry": {"coordinates":[-0.4932470024,39.5485115051],"type":"Point"}
}