{
  "type": "Feature",
  "properties": {
    "iso:country":"ES",
    "sg:address":"Calle de Jose Nogales, 13",
    "sg:city":"Aracena",
    "sg:orig_category":"Institutos De Belleza",
    "sg:phone":"+34 959 12 80 12",
    "sg:postcode":"21200",
    "sg:province":"Huelva",
    "wof:name":"Brenes Pineda Refugio",
    "wof:placetype":"venue"
},
  "geometry": {"coordinates":[-6.5597219467,37.8939285278],"type":"Point"}
}