{
  "type": "Feature",
  "properties": {
    "iso:country":"ES",
    "sg:address":"Plaz San Antonio, 1",
    "sg:city":"Avila",
    "sg:orig_category":"Comunidades Religiosas",
    "sg:phone":"+34 920 22 64 83",
    "sg:postcode":"05005",
    "sg:province":"\u00c1vila",
    "wof:name":"Convento De San Antonio",
    "wof:placetype":"venue"
},
  "geometry": {"coordinates":[-4.7116389275,40.6626739502],"type":"Point"}
}