{
  "type": "Feature",
  "properties": {
    "iso:country":"ES",
    "sg:address":"Barr Quintana (la) (somahoz), 57",
    "sg:city":"Somahoz",
    "sg:orig_category":"Producci\u00d3n De Abonos Y De Fertilizantes",
    "sg:phone":"+34 942 83 02 16",
    "sg:postcode":"39400",
    "sg:province":"Cantabria",
    "wof:name":"Agrobuelna S.c.",
    "wof:placetype":"venue"
},
  "geometry": {"coordinates":[-3.9878427982,43.1828384399],"type":"Point"}
}