{
  "type": "Feature",
  "properties": {
    "iso:country":"ES",
    "sg:address":"Calle de Cuenca, 25",
    "sg:city":"Valencia",
    "sg:orig_category":"Chapister\u00cda",
    "sg:phone":"+34 963 84 27 59",
    "sg:postcode":"46007",
    "sg:province":"Valencia",
    "wof:name":"Gutierrez Alvarez Angel",
    "wof:placetype":"venue"
},
  "geometry": {"coordinates":[-0.3856261969,39.4674491882],"type":"Point"}
}