{
  "type": "Feature",
  "properties": {
    "addr:full":"Polig Pol\u00edgono Ind. Autopista Sur Km. 64 Nave 21 Castellon De La Plana Castell\u00f3n 12006",
    "addr:housenumber":"nave 21",
    "addr:postcode":"12006",
    "addr:street":"Polig Poli\u0301Gono;Autopista Sur Km. 64",
    "iso:country":"ES",
    "sg:address":"Polig Pol\u00edgono Ind. Autopista Sur Km. 64 Nave 21",
    "sg:city":"Castellon De La Plana",
    "sg:orig_category":"Revestimiento De Suelos Industriales",
    "sg:phone":"+34 964 63 06 85",
    "sg:postcode":"12006",
    "sg:province":"Castell\u00f3n",
    "sg:website":"www.pavihor.com",
    "wof:name":"Pavihor S.a.",
    "wof:placetype":"venue"
},
  "geometry": {"coordinates":[-0.1404139996,40.0213813782],"type":"Point"}
}