{
  "type": "Feature",
  "properties": {
    "addr:full":"Ctra Vilches, S/n Ubeda Ja\u00e9n 23400",
    "addr:housenumber":"s / n",
    "addr:postcode":"23400",
    "addr:street":"Ctra Vilches;Ubeda Jae\u0301N",
    "iso:country":"ES",
    "sg:address":"Ctra Vilches, S/n",
    "sg:city":"Ubeda",
    "sg:orig_category":"Agricultura: Abastecimiento Y Cosechado (negocio)",
    "sg:phone":"+34 953 75 36 02",
    "sg:postcode":"23400",
    "sg:province":"Ja\u00e9n",
    "wof:name":"Agroquimicos Campos S. A.",
    "wof:placetype":"venue"
},
  "geometry": {"coordinates":[-3.3708982468,38.0233268738],"type":"Point"}
}