{
  "type": "Feature",
  "properties": {
    "iso:country":"ES",
    "sg:address":"Moll De Drassanes, S/n",
    "sg:city":"Barcelona",
    "sg:orig_category":"Organizaciones Profesionales",
    "sg:phone":"+34 933 24 83 26",
    "sg:postcode":"08039",
    "sg:province":"Barcelona",
    "wof:name":"Compa\u00d1ia Barcelonesa De Consignaciones S.a.",
    "wof:placetype":"venue"
},
  "geometry": {"coordinates":[2.1784780025,41.3758430481],"type":"Point"}
}