{
  "type": "Feature",
  "properties": {
    "iso:country":"ES",
    "sg:address":"Calle de Mercaderes, 11",
    "sg:city":"Llanes",
    "sg:orig_category":"Droguer\u00cdas (al Por Menor)",
    "sg:phone":"+34 985 40 09 49",
    "sg:postcode":"33500",
    "sg:province":"Asturias",
    "wof:name":"Buj Suarez Antonio Luis",
    "wof:placetype":"venue"
},
  "geometry": {"coordinates":[-4.7542347908,43.4195823669],"type":"Point"}
}