{
  "type": "Feature",
  "properties": {
    "addr:full":"Calle de Alcala, 456 Madrid Madrid 28027",
    "addr:housenumber":"456",
    "addr:postcode":"28027",
    "addr:street":"Calle De Alcala",
    "iso:country":"ES",
    "sg:address":"Calle de Alcala, 456",
    "sg:city":"Madrid",
    "sg:orig_category":"Reposter\u00cdas",
    "sg:phone":"+34 913 04 44 16",
    "sg:postcode":"28027",
    "sg:province":"Madrid",
    "wof:name":"Dominguez Recio Francisca",
    "wof:placetype":"venue"
},
  "geometry": {"coordinates":[-3.6342480183,40.438835144],"type":"Point"}
}