{
  "type": "Feature",
  "properties": {
    "iso:country":"ES",
    "sg:address":"Ctra Marenya, S/n",
    "sg:city":"Tallada Emporda",
    "sg:orig_category":"Reparaciones Y Remolcado De Veh\u00cdculos",
    "sg:phone":"+34 972 78 05 65",
    "sg:postcode":"17134",
    "sg:province":"Girona",
    "wof:name":"Roura Figueras Jordi",
    "wof:placetype":"venue"
},
  "geometry": {"coordinates":[3.0554099083,42.080291748],"type":"Point"}
}