{
  "type": "Feature",
  "properties": {
    "addr:full":"Avda Torcuato Fernandez Miranda, 22 Gijon Asturias 33203",
    "addr:housenumber":"22",
    "addr:postcode":"33203",
    "addr:street":"Avda Torcuato Fernandez Miranda",
    "iso:country":"ES",
    "sg:address":"Avda Torcuato Fernandez Miranda, 22",
    "sg:city":"Gijon",
    "sg:orig_category":"Agencias Y Agentes Comerciales, Representantes",
    "sg:phone":"+34 985 37 06 45",
    "sg:postcode":"33203",
    "sg:province":"Asturias",
    "wof:name":"Hernando Rodriguez Jose Maria",
    "wof:placetype":"venue"
},
  "geometry": {"coordinates":[-5.6442728043,43.5369758606],"type":"Point"}
}