{
  "type": "Feature",
  "properties": {
    "iso:country":"ES",
    "sg:address":"Calle de Santo Domingo Guzman, S/n",
    "sg:city":"Veguellina Orbigo",
    "sg:orig_category":"Reposter\u00cdas",
    "sg:phone":"+34 987 37 50 76",
    "sg:postcode":"24350",
    "sg:province":"Le\u00f3n",
    "wof:name":"Panaderia Desiderio Escalada Sa\u00f1udo C.b.",
    "wof:placetype":"venue"
},
  "geometry": {"coordinates":[-5.8852372169,42.4383964539],"type":"Point"}
}