{
  "type": "Feature",
  "properties": {
    "addr:full":"Calle de Alfonso De Montalvo, 1 Avila \u00c1vila 05001",
    "addr:housenumber":"1",
    "addr:postcode":"05001",
    "addr:street":"Calle De Alfonso De Montalvo;A\u0301Vila",
    "iso:country":"ES",
    "sg:address":"Calle de Alfonso De Montalvo, 1",
    "sg:city":"Avila",
    "sg:orig_category":"Inmobiliaria (agencias)",
    "sg:phone":"+34 920 21 24 17",
    "sg:postcode":"05001",
    "sg:province":"\u00c1vila",
    "wof:name":"Compa\u00f1ia Inmobiliaria Busque S.r.l.",
    "wof:placetype":"venue"
},
  "geometry": {"coordinates":[-4.6886954308,40.6555328369],"type":"Point"}
}