{
  "type": "Feature",
  "properties": {
    "iso:country":"ES",
    "sg:address":"Avda Luchon, S/n",
    "sg:city":"Benasque",
    "sg:orig_category":"Pizzer\u00cdas",
    "sg:phone":"+34 974 55 15 92",
    "sg:postcode":"22440",
    "sg:province":"Huesca",
    "wof:name":"Malvesada Alvarez Jose Luis",
    "wof:placetype":"venue"
},
  "geometry": {"coordinates":[0.5245320201,42.605255127],"type":"Point"}
}