{
  "type": "Feature",
  "properties": {
    "iso:country":"ES",
    "sg:address":"Avda Pirralos (los), 34",
    "sg:city":"Dos Hermanas",
    "sg:orig_category":"Inmobiliaria (agencias)",
    "sg:phone":"+34 955 67 56 40",
    "sg:postcode":"41700",
    "sg:province":"Sevilla",
    "wof:name":"Gonzalez Salas Sonia",
    "wof:placetype":"venue"
},
  "geometry": {"coordinates":[-5.9289798737,37.2798728943],"type":"Point"}
}