{
  "type": "Feature",
  "properties": {
    "addr:full":"Calle de Aldai Kalea, 2 Amurrio \u00c1lava 01470",
    "addr:housenumber":"2",
    "addr:postcode":"01470",
    "addr:street":"Calle De Aldai Kalea",
    "iso:country":"ES",
    "sg:address":"Calle de Aldai Kalea, 2",
    "sg:city":"Amurrio",
    "sg:orig_category":"Peluquer\u00cdas",
    "sg:phone":"+34 945 89 24 02",
    "sg:postcode":"01470",
    "sg:province":"\u00c1lava",
    "wof:name":"Peluqueria Formas",
    "wof:placetype":"venue"
},
  "geometry": {"coordinates":[-3.0016462803,43.0511474609],"type":"Point"}
}