{
  "type": "Feature",
  "properties": {
    "addr:full":"El Nogal, 9 Velez Benaudalla Granada 18670",
    "addr:housenumber":"9",
    "addr:postcode":"18670",
    "addr:street":"El Nogal;Benaudalla",
    "iso:country":"ES",
    "sg:address":"El Nogal, 9",
    "sg:city":"Velez Benaudalla",
    "sg:orig_category":"Materias Pl\u00c1sticas: Productos De Consumo Masivo (fabricaci\u00d3n, Al Por Mayor)",
    "sg:phone":"+34 958 65 83 19",
    "sg:postcode":"18670",
    "sg:province":"Granada",
    "wof:name":"Rodriguez Garcia Jose Luis",
    "wof:placetype":"venue"
},
  "geometry": {"coordinates":[-3.5169899464,36.8334274292],"type":"Point"}
}