{
  "type": "Feature",
  "properties": {
    "addr:full":"Calle de Claudio Coello, 51 Madrid Madrid 28001",
    "addr:housenumber":"51",
    "addr:postcode":"madrid;28001",
    "addr:street":"Calle De Claudio Coello",
    "iso:country":"ES",
    "sg:address":"Calle de Claudio Coello, 51",
    "sg:city":"Madrid",
    "sg:orig_category":"Cajas De Ahorro",
    "sg:phone":"+34 915 78 19 05",
    "sg:postcode":"28001",
    "sg:province":"Madrid",
    "wof:name":"Caja De Ahorros De Valencia Castellon Y Alicante",
    "wof:placetype":"venue"
},
  "geometry": {"coordinates":[-3.686494112,40.4269981384],"type":"Point"}
}