{
  "type": "Feature",
  "properties": {
    "iso:country":"ES",
    "sg:address":"Lledo, S/n",
    "sg:city":"Villamayor",
    "sg:orig_category":"Cerrajer\u00cda, Ferrallista",
    "sg:phone":"+34 985 70 70 07",
    "sg:postcode":"33583",
    "sg:province":"Asturias",
    "wof:name":"Lleuhormat S.l.",
    "wof:placetype":"venue"
},
  "geometry": {"coordinates":[-5.3137249947,43.3825111389],"type":"Point"}
}