{
  "type": "Feature",
  "properties": {
    "addr:full":"Calle de Fuente Nueva, 6 Toledo Toledo 45006",
    "addr:housenumber":"6",
    "addr:postcode":"45006",
    "addr:street":"Calle De Fuente Nueva",
    "iso:country":"ES",
    "sg:address":"Calle de Fuente Nueva, 6",
    "sg:city":"Toledo",
    "sg:orig_category":"Ropa Para Se\u00d1oras (al Por Menor)",
    "sg:phone":"+34 925 25 56 91",
    "sg:postcode":"45006",
    "sg:province":"Toledo",
    "wof:name":"Galvez Sierra Azucena",
    "wof:placetype":"venue"
},
  "geometry": {"coordinates":[-4.0012569427,39.8613967896],"type":"Point"}
}