{
  "type": "Feature",
  "properties": {
    "iso:country":"ES",
    "sg:address":"Av De Cordoba, S/n",
    "sg:city":"Ronda",
    "sg:orig_category":"Lavado, Limpieza De Veh\u00cdculos",
    "sg:phone":"+34 952 87 90 18",
    "sg:postcode":"29400",
    "sg:province":"M\u00e1laga",
    "wof:name":"Talleres Florencio E Hijos S.l",
    "wof:placetype":"venue"
},
  "geometry": {"coordinates":[-5.1600341797,36.7486763],"type":"Point"}
}