{
  "type": "Feature",
  "properties": {
    "addr:full":"Autovia Zaragoza-logro\u00f1o, Km. 0010,0 Monzalbarba Zaragoza 50120",
    "addr:postcode":"50120",
    "addr:street":"Autovia Zaragoza-Logron\u0303O Km. 0010,0 Monzalbarba",
    "iso:country":"ES",
    "sg:address":"Autovia Zaragoza-logro\u00f1o, Km. 0010,0",
    "sg:city":"Monzalbarba",
    "sg:orig_category":"Venta, Montaje De Neum\u00c1ticos",
    "sg:phone":"+34 976 77 28 06",
    "sg:postcode":"50120",
    "sg:province":"Zaragoza",
    "wof:name":"Euronet Spain S.a.",
    "wof:placetype":"venue"
},
  "geometry": {"coordinates":[-0.9511139989,41.723651886],"type":"Point"}
}