{
  "type": "Feature",
  "properties": {
    "iso:country":"ES",
    "sg:address":"Carrer de Pere Badia (de), 20",
    "sg:city":"Torredembarra",
    "sg:orig_category":"Centros Comerciales Y Grandes Tiendas",
    "sg:phone":"+34 977 64 11 26",
    "sg:postcode":"43830",
    "sg:province":"Tarragona",
    "wof:name":"Martinez Garcia Maria",
    "wof:placetype":"venue"
},
  "geometry": {"coordinates":[1.4026550055,41.1445579529],"type":"Point"}
}