{
  "type": "Feature",
  "properties": {
    "iso:country":"ES",
    "sg:address":"Calle de Albeniz, 4",
    "sg:city":"Durazno",
    "sg:orig_category":"Arquitectos",
    "sg:phone":"+34 922 38 26 32",
    "sg:postcode":"38400",
    "sg:province":"Santa Cruz De Tenerife",
    "wof:name":"Arroyo Temprano Paula",
    "wof:placetype":"venue"
},
  "geometry": {"coordinates":[-16.5392875671,28.4066295624],"type":"Point"}
}