{
  "type": "Feature",
  "properties": {
    "iso:country":"ES",
    "sg:address":"Calle de Iparraguirre, 7",
    "sg:city":"Bilbao",
    "sg:orig_category":"M\u00c9dicos: Pediatr\u00cda. Enfermedades De Los Ni\u00d1os",
    "sg:phone":"+34 944 23 30 90",
    "sg:postcode":"48009",
    "sg:province":"Vizcaya",
    "wof:name":"Arroyo De Diego Jose Luis",
    "wof:placetype":"venue"
},
  "geometry": {"coordinates":[-2.9350776672,43.2664299011],"type":"Point"}
}