{
  "type": "Feature",
  "properties": {
    "addr:full":"Calle de Aponte, 10 Sevilla Sevilla 41002",
    "addr:housenumber":"10",
    "addr:postcode":"41002",
    "addr:street":"Calle De Aponte",
    "iso:country":"ES",
    "sg:address":"Calle de Aponte, 10",
    "sg:city":"Sevilla",
    "sg:orig_category":"Bisuter\u00cda, Joyer\u00cda, Relojer\u00cda (al Por Menor)",
    "sg:phone":"+34 954 38 21 76",
    "sg:postcode":"41002",
    "sg:province":"Sevilla",
    "wof:name":"Salice  Emilse",
    "wof:placetype":"venue"
},
  "geometry": {"coordinates":[-5.9958181381,37.3939094543],"type":"Point"}
}