{
  "type": "Feature",
  "properties": {
    "iso:country":"ES",
    "sg:address":"Calle de Maluquer, 4",
    "sg:city":"Caceres",
    "sg:orig_category":"M\u00c9dicos: Oftalmolog\u00cda",
    "sg:phone":"+34 927 22 68 67",
    "sg:postcode":"10002",
    "sg:province":"C\u00e1ceres",
    "wof:name":"Vazquez Gonzalez-sandoval Jorge",
    "wof:placetype":"venue"
},
  "geometry": {"coordinates":[-6.3770680428,39.4694213867],"type":"Point"}
}