{
  "type": "Feature",
  "properties": {
    "addr:full":"Dr. Ciurana, 2 S. Pere Pescador Girona 17470",
    "addr:housenumber":"2",
    "addr:postcode":"17470",
    "addr:street":"S. Pere Pescador",
    "iso:country":"ES",
    "sg:address":"Dr. Ciurana, 2",
    "sg:city":"S. Pere Pescador",
    "sg:orig_category":"Maquinaria Para Industrias Diversas",
    "sg:phone":"+34 972 52 10 00",
    "sg:postcode":"17470",
    "sg:province":"Girona",
    "wof:name":"Maquinaria Agricola Jofercan S.l.",
    "wof:placetype":"venue"
},
  "geometry": {"coordinates":[3.0805599689,42.1881332397],"type":"Point"}
}