{
  "type": "Feature",
  "properties": {
    "addr:full":"Via San Fernando, 9 Zaragoza Zaragoza 50007",
    "addr:housenumber":"9",
    "addr:postcode":"50007",
    "addr:street":"Via San Fernando",
    "iso:country":"ES",
    "sg:address":"Via San Fernando, 9",
    "sg:city":"Zaragoza",
    "sg:orig_category":"Confecci\u00d3n (fabricaci\u00d3n, Al Por Mayor)",
    "sg:phone":"+34 976 38 59 60",
    "sg:postcode":"50007",
    "sg:province":"Zaragoza",
    "wof:name":"Benitez Garcia Jose Maria",
    "wof:placetype":"venue"
},
  "geometry": {"coordinates":[-0.8839470148,41.6352615356],"type":"Point"}
}