{
  "type": "Feature",
  "properties": {
    "iso:country":"ES",
    "sg:address":"Plaz Serrana De La, 78",
    "sg:city":"Huelva",
    "sg:orig_category":"Construcci\u00d3n De Edificios Residenciales Y No Residenciales",
    "sg:phone":"+34 959 80 39 01",
    "sg:postcode":"21006",
    "sg:province":"Huelva",
    "wof:name":"Valenciano Borrero Jose",
    "wof:placetype":"venue"
},
  "geometry": {"coordinates":[-6.9495940208,37.256313324],"type":"Point"}
}