{
  "type": "Feature",
  "properties": {
    "iso:country":"ES",
    "sg:address":"Avda Extremadura, 4",
    "sg:city":"San Vicente Alcantara",
    "sg:orig_category":"Venta, Instalaci\u00d3n De Calefacci\u00d3n",
    "sg:phone":"+34 924 41 10 12",
    "sg:postcode":"06500",
    "sg:province":"Badajoz",
    "wof:name":"Alcantara De Gas S.l.",
    "wof:placetype":"venue"
},
  "geometry": {"coordinates":[-7.1360731125,39.3600883484],"type":"Point"}
}