{
  "type": "Feature",
  "properties": {
    "addr:full":"Calle de Pelayo, 1 Aviles Asturias 33402",
    "addr:housenumber":"1",
    "addr:postcode":"33402",
    "addr:street":"Calle De Pelayo",
    "iso:country":"ES",
    "sg:address":"Calle de Pelayo, 1",
    "sg:city":"Aviles",
    "sg:orig_category":"Molduras, Junquillos, Listones Y Molduras Perforadas",
    "sg:phone":"+34 985 54 74 93",
    "sg:postcode":"33402",
    "sg:province":"Asturias",
    "wof:name":"Longueira Botana Jose Luis",
    "wof:placetype":"venue"
},
  "geometry": {"coordinates":[-5.9175291061,43.5497055054],"type":"Point"}
}