{
  "type": "Feature",
  "properties": {
    "addr:full":"Ctra Aranda, 26 Illueca Zaragoza 50250",
    "addr:housenumber":"26",
    "addr:postcode":"50250",
    "addr:street":"Ctra Aranda",
    "iso:country":"ES",
    "sg:address":"Ctra Aranda, 26",
    "sg:city":"Illueca",
    "sg:orig_category":"Quiropr\u00c1cticos",
    "sg:phone":"+34 976 82 24 89",
    "sg:postcode":"50250",
    "sg:province":"Zaragoza",
    "wof:name":"Sisamon Ibarzu Rosa Natividad",
    "wof:placetype":"venue"
},
  "geometry": {"coordinates":[-1.6350140572,41.5382957458],"type":"Point"}
}