{
  "type": "Feature",
  "properties": {
    "iso:country":"ES",
    "sg:address":"Calle de Verge De La Murta, 2",
    "sg:city":"Alzira",
    "sg:orig_category":"Carnicer\u00cdas, Carnicer\u00cdas",
    "sg:phone":"+34 962 41 60 93",
    "sg:postcode":"46600",
    "sg:province":"Valencia",
    "wof:name":"Caro Llinares Carlos",
    "wof:placetype":"venue"
},
  "geometry": {"coordinates":[-0.4316860139,39.1511192322],"type":"Point"}
}