{
  "type": "Feature",
  "properties": {
    "addr:full":"Carrer de Industria, S/n Balsareny Barcelona 08660",
    "addr:housenumber":"/ n",
    "addr:postcode":"08660",
    "addr:street":"Carrer De Industria S",
    "iso:country":"ES",
    "sg:address":"Carrer de Industria, S/n",
    "sg:city":"Balsareny",
    "sg:orig_category":"Filtros Y Elementos Filtradores",
    "sg:phone":"+34 938 20 02 35",
    "sg:postcode":"08660",
    "sg:province":"Barcelona",
    "sg:website":"www.servaqua.com",
    "wof:name":"Servaqua 2 S.a.",
    "wof:placetype":"venue"
},
  "geometry": {"coordinates":[1.8748699427,41.858543396],"type":"Point"}
}