{
  "type": "Feature",
  "properties": {
    "iso:country":"ES",
    "sg:address":"Calle de Esperanza, 28",
    "sg:city":"Segorbe",
    "sg:orig_category":"Artes Gr\u00c1ficas, Artes Pl\u00c1sticas (curso)",
    "sg:phone":"+34 964 71 08 48",
    "sg:postcode":"12400",
    "sg:province":"Castell\u00f3n",
    "wof:name":"Graficas Samuel S.l.",
    "wof:placetype":"venue"
},
  "geometry": {"coordinates":[-0.4914410114,39.8535003662],"type":"Point"}
}