{
  "type": "Feature",
  "properties": {
    "addr:full":"C/ Major, 24 Inca Islas Baleares 07300",
    "addr:housenumber":"24",
    "addr:postcode":"07300",
    "addr:street":"C / Major",
    "iso:country":"ES",
    "sg:address":"C/ Major, 24",
    "sg:city":"Inca",
    "sg:orig_category":"Artes Gr\u00c1ficas, Artes Pl\u00c1sticas (curso)",
    "sg:phone":"+34 971 88 15 40",
    "sg:postcode":"07300",
    "sg:province":"Islas Baleares",
    "wof:name":"Navarro Valle Paulina",
    "wof:placetype":"venue"
},
  "geometry": {"coordinates":[2.9104800224,39.7212791443],"type":"Point"}
}