{
  "type": "Feature",
  "properties": {
    "addr:full":"Villafranca, 4 Iru\u00f1a Navarra 31015",
    "addr:housenumber":"4",
    "addr:postcode":"31015",
    "addr:street":"Villafranca",
    "iso:country":"ES",
    "sg:address":"Villafranca, 4",
    "sg:city":"Iru\u00f1a",
    "sg:orig_category":"Venta, Instalaci\u00d3n De Calefacci\u00d3n",
    "sg:phone":"+34 948 14 02 43",
    "sg:postcode":"31015",
    "sg:province":"Navarra",
    "wof:name":"Idoate Ardanaz Francisco Javier",
    "wof:placetype":"venue"
},
  "geometry": {"coordinates":[-1.6294929981,42.8319854736],"type":"Point"}
}