{
  "type": "Feature",
  "properties": {
    "addr:full":"Calle de Sancho Iv El Bravo, 8 Tarifa C\u00e1diz 11380",
    "addr:housenumber":"8",
    "addr:postcode":"11380",
    "addr:street":"Calle De Sancho Iv El Bravo;Ca\u0301Diz",
    "iso:country":"ES",
    "sg:address":"Calle de Sancho Iv El Bravo, 8",
    "sg:city":"Tarifa",
    "sg:orig_category":"Iglesia Cat\u00d3lica",
    "sg:phone":"+34 956 68 43 10",
    "sg:postcode":"11380",
    "sg:province":"C\u00e1diz",
    "wof:name":"Parroquia De San Mateo",
    "wof:placetype":"venue"
},
  "geometry": {"coordinates":[-5.6030640602,36.0127944946],"type":"Point"}
}