{
  "type": "Feature",
  "properties": {
    "iso:country":"ES",
    "sg:address":"Ctra. Del Puerto, Km. 0023,6",
    "sg:city":"Sanlucar",
    "sg:orig_category":"Contenedores (mercanc\u00cdas)",
    "sg:phone":"+34 956 38 07 59",
    "sg:postcode":"11540",
    "sg:province":"C\u00e1diz",
    "wof:name":"Asociacion Local De Transportes Ligeros De Mercancias De Sanlucar De Barrameda",
    "wof:placetype":"venue"
},
  "geometry": {"coordinates":[-6.3534770012,36.7716293335],"type":"Point"}
}