{
  "type": "Feature",
  "properties": {
    "iso:country":"ES",
    "sg:address":"Carrer de Puig Del Ravell, 39",
    "sg:city":"Martorell",
    "sg:orig_category":"Agencias Y Agentes Comerciales, Representantes",
    "sg:phone":"+34 937 75 32 43",
    "sg:postcode":"08760",
    "sg:province":"Barcelona",
    "wof:name":"Jordan Lopez Rosario",
    "wof:placetype":"venue"
},
  "geometry": {"coordinates":[1.9127399921,41.4777908325],"type":"Point"}
}