{
  "type": "Feature",
  "properties": {
    "addr:full":"Plaz Espa\u00d1a, 9 Borja Zaragoza 50540",
    "addr:housenumber":"9",
    "addr:postcode":"50540",
    "addr:street":"Plaz Espan\u0303A",
    "iso:country":"ES",
    "sg:address":"Plaz Espa\u00d1a, 9",
    "sg:city":"Borja",
    "sg:orig_category":"Inform\u00c1tica (estudios, Servicios, Asesor\u00cda, Formaci\u00d3n)",
    "sg:phone":"+34 976 86 87 30",
    "sg:postcode":"50540",
    "sg:province":"Zaragoza",
    "wof:name":"Mapfre Servicios De Informatica",
    "wof:placetype":"venue"
},
  "geometry": {"coordinates":[-1.5402326584,41.8895072937],"type":"Point"}
}