{
  "type": "Feature",
  "properties": {
    "addr:full":"Carrer de Pablo Picasso, 39 Mollet Valles Barcelona 08100",
    "addr:housenumber":"39",
    "addr:postcode":"08100",
    "addr:street":"Carrer De Pablo Picasso",
    "iso:country":"ES",
    "sg:address":"Carrer de Pablo Picasso, 39",
    "sg:city":"Mollet Valles",
    "sg:orig_category":"Artes Gr\u00c1ficas, Artes Pl\u00c1sticas: Material Y Suministros (al Por Menor)",
    "sg:phone":"+34 935 70 37 37",
    "sg:postcode":"08100",
    "sg:province":"Barcelona",
    "wof:name":"Trullas Salellas Magdalena",
    "wof:placetype":"venue"
},
  "geometry": {"coordinates":[2.21570611,41.545249939],"type":"Point"}
}