{
  "type": "Feature",
  "properties": {
    "addr:full":"Calle de Aldamar, 4 Donostia-san Sebastian Guip\u00f9zcoa 20003",
    "addr:housenumber":"4",
    "addr:postcode":"20003",
    "addr:street":"Calle De Aldamar",
    "iso:country":"ES",
    "sg:address":"Calle de Aldamar, 4",
    "sg:city":"Donostia-san Sebastian",
    "sg:orig_category":"Ense\u00d1anza: Turismo, Cocina, Hosteler\u00cda",
    "sg:phone":"+34 943 42 22 18",
    "sg:postcode":"20003",
    "sg:province":"Guip\u00f9zcoa",
    "sg:website":"www.eltxocodelgourmet.com",
    "wof:name":"Casa Armendariz S.a.",
    "wof:placetype":"venue"
},
  "geometry": {"coordinates":[-1.982139349,43.3230781555],"type":"Point"}
}