{
  "type": "Feature",
  "properties": {
    "addr:full":"Calle de Virgen De Legarda, S/n Mendavia Navarra 31587",
    "addr:housenumber":"s / n",
    "addr:postcode":"31587",
    "addr:street":"Calle De Virgen De Legarda",
    "iso:country":"ES",
    "sg:address":"Calle de Virgen De Legarda, S/n",
    "sg:city":"Mendavia",
    "sg:orig_category":"Conservas De Legumbres (fabricaci\u00d3n, Al Por Mayor)",
    "sg:phone":"+34 948 68 50 00",
    "sg:postcode":"31587",
    "sg:province":"Navarra",
    "sg:website":"www.vdadecayo.com",
    "wof:name":"Viuda De Cayo Sainz S.l.",
    "wof:placetype":"venue"
},
  "geometry": {"coordinates":[-2.2047996521,42.4386940002],"type":"Point"}
}