{
  "type": "Feature",
  "properties": {
    "addr:full":"Cmno Feli, 495 Ca\u00d1arejo Murcia 30800",
    "addr:housenumber":"495",
    "addr:postcode":"30800",
    "addr:street":"Cmno Feli",
    "iso:country":"ES",
    "sg:address":"Cmno Feli, 495",
    "sg:city":"Ca\u00d1arejo",
    "sg:orig_category":"Contenedores (mercanc\u00cdas)",
    "sg:phone":"+34 968 46 41 67",
    "sg:postcode":"30800",
    "sg:province":"Murcia",
    "wof:name":"Translorca Hnos Cano S.l.",
    "wof:placetype":"venue"
},
  "geometry": {"coordinates":[-1.6905640364,37.680557251],"type":"Point"}
}