{
  "type": "Feature",
  "properties": {
    "addr:full":"Cno. Huertas, S/n Torrelaguna Madrid 28180",
    "addr:housenumber":"/ n",
    "addr:postcode":"28180",
    "addr:street":"Cno. Huertas S",
    "iso:country":"ES",
    "sg:address":"Cno. Huertas, S/n",
    "sg:city":"Torrelaguna",
    "sg:orig_category":"Comercio De Muebles De Estilo Y Contempor\u00c1neos",
    "sg:phone":"+34 918 43 15 07",
    "sg:postcode":"28180",
    "sg:province":"Madrid",
    "wof:name":"Sanz Page Carmen",
    "wof:placetype":"venue"
},
  "geometry": {"coordinates":[-3.5416240692,40.8245201111],"type":"Point"}
}