{
  "type": "Feature",
  "properties": {
    "iso:country":"ES",
    "sg:address":"Avda Jose De Mora, 6",
    "sg:city":"Baza",
    "sg:orig_category":"Asesor\u00cda Sobre Comunicaci\u00d3n De Empresas",
    "sg:phone":"+34 958 70 38 15",
    "sg:postcode":"18800",
    "sg:province":"Granada",
    "wof:name":"Gutierrez Y Martinez Asesores S.l.l.",
    "wof:placetype":"venue"
},
  "geometry": {"coordinates":[-2.7723250389,37.4890289307],"type":"Point"}
}