{
  "type": "Feature",
  "properties": {
    "iso:country":"ES",
    "sg:address":"Avda Santiago, 88",
    "sg:city":"Vista Alegre",
    "sg:orig_category":"Agencias Y Asesores De Publicidad",
    "sg:phone":"+34 968 23 57 23",
    "sg:postcode":"30007",
    "sg:province":"Murcia",
    "wof:name":"Asuncion Barcelo Miguel",
    "wof:placetype":"venue"
},
  "geometry": {"coordinates":[-1.1298867464,37.9834747314],"type":"Point"}
}