{
  "type": "Feature",
  "properties": {
    "addr:full":"Calle de Alhambra, 33 Lorqui Murcia 30564",
    "addr:housenumber":"33",
    "addr:postcode":"30564",
    "addr:street":"Calle De Alhambra",
    "iso:country":"ES",
    "sg:address":"Calle de Alhambra, 33",
    "sg:city":"Lorqui",
    "sg:orig_category":"Negocio De Materiales De Construcci\u00d3n",
    "sg:phone":"+34 968 69 44 66",
    "sg:postcode":"30564",
    "sg:province":"Murcia",
    "wof:name":"Materiales De Construccion Las Mellizas S.l.",
    "wof:placetype":"venue"
},
  "geometry": {"coordinates":[-1.2478115559,38.0764045715],"type":"Point"}
}