{
  "type": "Feature",
  "properties": {
    "addr:full":"Calle de Palencia, 5 Granada Granada 18007",
    "addr:housenumber":"5",
    "addr:postcode":"18007",
    "addr:street":"Calle De Palencia",
    "iso:country":"ES",
    "sg:address":"Calle de Palencia, 5",
    "sg:city":"Granada",
    "sg:orig_category":"Zapatos (al Por Menor)",
    "sg:phone":"+34 958 12 05 57",
    "sg:postcode":"18007",
    "sg:province":"Granada",
    "wof:name":"Rodriguez Aviles Jose",
    "wof:placetype":"venue"
},
  "geometry": {"coordinates":[-3.5985589027,37.1602172852],"type":"Point"}
}