{
  "type": "Feature",
  "properties": {
    "iso:country":"ES",
    "sg:address":"Av Eramprunya (l'), 18",
    "sg:city":"Gava",
    "sg:orig_category":"Molduras, Junquillos, Listones Y Molduras Perforadas",
    "sg:phone":"+34 936 62 73 01",
    "sg:postcode":"08850",
    "sg:province":"Barcelona",
    "wof:name":"Paz Vachet Alicia Lidia",
    "wof:placetype":"venue"
},
  "geometry": {"coordinates":[1.9980469942,41.3094596863],"type":"Point"}
}