{
  "type": "Feature",
  "properties": {
    "iso:country":"ES",
    "sg:address":"Carrer de Sant Antoni Maria Claret, 6",
    "sg:city":"Barcelona",
    "sg:orig_category":"Laboratorios Y Trabajos De Fotograf\u00cda, V\u00cddeo Y Cine",
    "sg:phone":"+34 934 58 43 86",
    "sg:postcode":"08037",
    "sg:province":"Barcelona",
    "wof:name":"Cipres Mompel Agueda",
    "wof:placetype":"venue"
},
  "geometry": {"coordinates":[2.1634600163,41.4028205872],"type":"Point"}
}