{
  "type": "Feature",
  "properties": {
    "iso:country":"ES",
    "sg:address":"Calle de Sagunto, S/n",
    "sg:city":"Cordoba",
    "sg:orig_category":"Ense\u00d1anza, Formaci\u00d3n Profesional: Aprendizaje",
    "sg:phone":"+34 957 43 38 78",
    "sg:postcode":"14007",
    "sg:province":"C\u00f3rdoba",
    "wof:name":"Cruz Roja Espa\u00f1ola Asamblea Provincial",
    "wof:placetype":"venue"
},
  "geometry": {"coordinates":[-4.7601518631,37.8947143555],"type":"Point"}
}