{
  "type": "Feature",
  "properties": {
    "iso:country":"ES",
    "sg:address":"C/ Estrella, De S', 9",
    "sg:city":"Manacor",
    "sg:orig_category":"Abogados",
    "sg:phone":"+34 971 55 08 90",
    "sg:postcode":"07500",
    "sg:province":"Islas Baleares",
    "wof:name":"Sastre Gornals Antonio",
    "wof:placetype":"venue"
},
  "geometry": {"coordinates":[3.2092959881,39.5690345764],"type":"Point"}
}