{
  "type": "Feature",
  "properties": {
    "addr:full":"Calle de Calera, 35 Burgos Burgos 09002",
    "addr:housenumber":"35",
    "addr:postcode":"09002",
    "addr:street":"Calle De Calera",
    "iso:country":"ES",
    "sg:address":"Calle de Calera, 35",
    "sg:city":"Burgos",
    "sg:orig_category":"Deportes Diversos",
    "sg:phone":"+34 947 20 61 22",
    "sg:postcode":"09002",
    "sg:province":"Burgos",
    "wof:name":"Federacion Autonomica De Baloncesto De Castilla Y Leon",
    "wof:placetype":"venue"
},
  "geometry": {"coordinates":[-3.6991043091,42.33852005],"type":"Point"}
}