{
  "type": "Feature",
  "properties": {
    "addr:full":"Calle de Pe\u00d1a Sorrapia, 68 Madrid Madrid 28031",
    "addr:housenumber":"68",
    "addr:postcode":"madrid;28031",
    "addr:street":"Calle De Pen\u0303A Sorrapia",
    "iso:country":"ES",
    "sg:address":"Calle de Pe\u00d1a Sorrapia, 68",
    "sg:city":"Madrid",
    "sg:orig_category":"Empresas De Pintura Y Revestimientos",
    "sg:phone":"+34 913 32 40 07",
    "sg:postcode":"28031",
    "sg:province":"Madrid",
    "wof:name":"Garcia Martinez Antonio",
    "wof:placetype":"venue"
},
  "geometry": {"coordinates":[-3.6230790615,40.3720588684],"type":"Point"}
}