{
  "type": "Feature",
  "properties": {
    "addr:full":"Calle de Ripa, 4 Bilbao Vizcaya 48001",
    "addr:housenumber":"4",
    "addr:postcode":"48001",
    "addr:street":"Calle De Ripa",
    "iso:country":"ES",
    "sg:address":"Calle de Ripa, 4",
    "sg:city":"Bilbao",
    "sg:orig_category":"Quincaller\u00cda (al Por Menor)",
    "sg:phone":"+34 944 23 14 45",
    "sg:postcode":"48001",
    "sg:province":"Vizcaya",
    "wof:name":"Sanz Recalde Luis Carlos",
    "wof:placetype":"venue"
},
  "geometry": {"coordinates":[-2.9245140553,43.2622680664],"type":"Point"}
}