{
  "type": "Feature",
  "properties": {
    "iso:country":"ES",
    "sg:address":"Calle de Lain Calvo, 3",
    "sg:city":"Villarcayo",
    "sg:orig_category":"Enfermeras: Consultas, Atenci\u00d3n A Domicilio",
    "sg:phone":"+34 947 13 13 52",
    "sg:postcode":"09550",
    "sg:province":"Burgos",
    "wof:name":"Perez Carazo Jose Antonio",
    "wof:placetype":"venue"
},
  "geometry": {"coordinates":[-3.5756709576,42.9363327026],"type":"Point"}
}