{
  "type": "Feature",
  "properties": {
    "iso:country":"ES",
    "sg:address":"Carr Santa Eugenia, 64",
    "sg:city":"Girona",
    "sg:orig_category":"Negocio De Materiales De Construcci\u00d3n",
    "sg:phone":"+34 972 23 65 11",
    "sg:postcode":"17005",
    "sg:province":"Girona",
    "wof:name":"Girop S. A.",
    "wof:placetype":"venue"
},
  "geometry": {"coordinates":[2.8136353493,41.9801597595],"type":"Point"}
}