{
  "type": "Feature",
  "properties": {
    "addr:full":"Avda Mayorga, S/n Valencia De Don Juan Le\u00f3n 24200",
    "addr:housenumber":"s / n",
    "addr:postcode":"24200",
    "addr:street":"Avda Mayorga",
    "iso:country":"ES",
    "sg:address":"Avda Mayorga, S/n",
    "sg:city":"Valencia De Don Juan",
    "sg:orig_category":"Mec\u00c1nico Del Autom\u00d3vil",
    "sg:phone":"+34 987 75 25 54",
    "sg:postcode":"24200",
    "sg:province":"Le\u00f3n",
    "wof:name":"Marinelli Garcia Ramon",
    "wof:placetype":"venue"
},
  "geometry": {"coordinates":[-5.5139641762,42.2898635864],"type":"Point"}
}