{
  "type": "Feature",
  "properties": {
    "addr:full":"Calle de Francisco Cabezas, 6 Getafe Madrid 28903",
    "addr:housenumber":"6",
    "addr:postcode":"28903",
    "addr:street":"Calle De Francisco Cabezas",
    "iso:country":"ES",
    "sg:address":"Calle de Francisco Cabezas, 6",
    "sg:city":"Getafe",
    "sg:orig_category":"Mudanzas",
    "sg:phone":"+34 916 82 11 39",
    "sg:postcode":"28903",
    "sg:province":"Madrid",
    "wof:name":"Gonzalez Romero Antonia",
    "wof:placetype":"venue"
},
  "geometry": {"coordinates":[-3.7228419781,40.3230247498],"type":"Point"}
}