{
  "type": "Feature",
  "properties": {
    "addr:full":"Ca\u00f1ada Castillo, S/n Calasparra Murcia 30420",
    "addr:housenumber":"s / n",
    "addr:postcode":"30420",
    "addr:street":"Can\u0303Ada Castillo",
    "iso:country":"ES",
    "sg:address":"Ca\u00f1ada Castillo, S/n",
    "sg:city":"Calasparra",
    "sg:orig_category":"Empresas De Carpinter\u00cda",
    "sg:phone":"+34 968 72 30 12",
    "sg:postcode":"30420",
    "sg:province":"Murcia",
    "wof:name":"Sanchez Martinez Pedro Luis",
    "wof:placetype":"venue"
},
  "geometry": {"coordinates":[-1.6932770014,38.2291603088],"type":"Point"}
}