{
  "type": "Feature",
  "properties": {
    "iso:country":"ES",
    "sg:address":"Calle de Corredera, S/n",
    "sg:city":"Fuente Maestre",
    "sg:orig_category":"Hospitales",
    "sg:phone":"+34 924 53 00 86",
    "sg:postcode":"06360",
    "sg:province":"Badajoz",
    "wof:name":"Servicio Extreme\u00d1o De Salud",
    "wof:placetype":"venue"
},
  "geometry": {"coordinates":[-6.4486842155,38.5262031555],"type":"Point"}
}