{
  "type": "Feature",
  "properties": {
    "addr:full":"Carr Hannover, 48 Mao Islas Baleares 07703",
    "addr:housenumber":"48",
    "addr:postcode":"07703",
    "addr:street":"Carr Hannover",
    "iso:country":"ES",
    "sg:address":"Carr Hannover, 48",
    "sg:city":"Mao",
    "sg:orig_category":"Procuradores",
    "sg:phone":"+34 971 36 17 26",
    "sg:postcode":"07703",
    "sg:province":"Islas Baleares",
    "wof:name":"Vidal Crespo Marta",
    "wof:placetype":"venue"
},
  "geometry": {"coordinates":[4.265625,39.8903694153],"type":"Point"}
}