{
  "type": "Feature",
  "properties": {
    "iso:country":"ES",
    "sg:address":"Calle de Islas Cies, 22",
    "sg:city":"Dos Hermanas",
    "sg:orig_category":"Caf\u00c9s, Bares, Cervecer\u00cdas",
    "sg:phone":"+34 955 66 50 11",
    "sg:postcode":"41700",
    "sg:province":"Sevilla",
    "wof:name":"Jimenez Acosta Rafael Manuel",
    "wof:placetype":"venue"
},
  "geometry": {"coordinates":[-5.9222788811,37.2914848328],"type":"Point"}
}