{
  "type": "Feature",
  "properties": {
    "iso:country":"ES",
    "sg:address":"Carretera De Cordoba, S/n",
    "sg:city":"Loja",
    "sg:orig_category":"Agencias Y Agentes Comerciales, Representantes",
    "sg:phone":"+34 958 32 10 92",
    "sg:postcode":"18300",
    "sg:province":"Granada",
    "wof:name":"Delgado Perea Adelaida",
    "wof:placetype":"venue"
},
  "geometry": {"coordinates":[-4.1453537941,37.1661262512],"type":"Point"}
}