{
  "type": "Feature",
  "properties": {
    "iso:country":"ES",
    "sg:address":"Calle de Ana Teresa, 1",
    "sg:city":"Madrid",
    "sg:orig_category":"Asilos De Ancianos. Centros Privados",
    "sg:phone":"+34 913 07 06 08",
    "sg:postcode":"28023",
    "sg:province":"Madrid",
    "wof:name":"Residencial Alsean S.l.",
    "wof:placetype":"venue"
},
  "geometry": {"coordinates":[-3.7802600861,40.4606933594],"type":"Point"}
}