{
  "type": "Feature",
  "properties": {
    "addr:full":"Carrer de Congres, 91 Barcelona Barcelona 08031",
    "addr:housenumber":"91",
    "addr:postcode":"08031",
    "addr:street":"Carrer De Congres",
    "iso:country":"ES",
    "sg:address":"Carrer de Congres, 91",
    "sg:city":"Barcelona",
    "sg:classifiers":[
        {
            "category":"Parking",
            "subcategory":"Lot",
            "type":"Transportation"
        }
    ],
    "sg:phone":"+34 934 27 68 61",
    "sg:postcode":"08031",
    "sg:province":"Barcelona",
    "sg:tags":[
        "de",
        "fabricaci\u00d3n",
        "parquet"
    ],
    "wof:name":"Triparquet S.l.",
    "wof:placetype":"venue"
},
  "geometry": {"coordinates":[2.1600298882,41.4373588562],"type":"Point"}
}