{
  "type": "Feature",
  "properties": {
    "iso:country":"ES",
    "sg:address":"C/ Calvari, 44",
    "sg:city":"Ripollet",
    "sg:orig_category":"Empresas De Carpinter\u00cda De Madera",
    "sg:phone":"+34 936 92 08 67",
    "sg:postcode":"08291",
    "sg:province":"Barcelona",
    "wof:name":"Rios Ruiz Felix",
    "wof:placetype":"venue"
},
  "geometry": {"coordinates":[2.1573200226,41.4962692261],"type":"Point"}
}