{
  "type": "Feature",
  "properties": {
    "iso:country":"ES",
    "sg:address":"Calle de Monte Naranco, 14",
    "sg:city":"Sese\u00e7a Nuevo",
    "sg:orig_category":"Transporte En General",
    "sg:phone":"+34 918 01 29 65",
    "sg:postcode":"45224",
    "sg:province":"Toledo",
    "sg:website":"www.cch.es",
    "wof:name":"Servicios Auxiliares Cch S.l.",
    "wof:placetype":"venue"
},
  "geometry": {"coordinates":[-3.6411440372,40.0999412537],"type":"Point"}
}