{
  "type": "Feature",
  "properties": {
    "iso:country":"ES",
    "sg:address":"Major, 31",
    "sg:city":"Sarria Ter",
    "sg:orig_category":"Pintura Y Barniz (al Por Menor)",
    "sg:phone":"+34 972 17 06 31",
    "sg:postcode":"17840",
    "sg:province":"Girona",
    "wof:name":"Brugada Vidal Marta",
    "wof:placetype":"venue"
},
  "geometry": {"coordinates":[2.8244490623,42.0156745911],"type":"Point"}
}