{
  "type": "Feature",
  "properties": {
    "addr:full":"Cno. Oropesa, 3 Talavera Reina Toledo 45600",
    "addr:housenumber":"3",
    "addr:postcode":"45600",
    "addr:street":"Oropesa",
    "iso:country":"ES",
    "sg:address":"Cno. Oropesa, 3",
    "sg:city":"Talavera Reina",
    "sg:orig_category":"Fabricaci\u00d3n De Productos L\u00c1cteos Y Derivados",
    "sg:phone":"+34 925 82 47 40",
    "sg:postcode":"45600",
    "sg:province":"Toledo",
    "wof:name":"Bonilac S.l.",
    "wof:placetype":"venue"
},
  "geometry": {"coordinates":[-4.8326292038,39.9584884644],"type":"Point"}
}