{
  "type": "Feature",
  "properties": {
    "iso:country":"ES",
    "sg:address":"Calle de Garay Juan De, 55",
    "sg:city":"Bilbao",
    "sg:orig_category":"Carnicer\u00cdas, Carnicer\u00cdas",
    "sg:phone":"+34 944 10 12 20",
    "sg:postcode":"48003",
    "sg:province":"Vizcaya",
    "wof:name":"Azkona Pe\u00f1a Pablo",
    "wof:placetype":"venue"
},
  "geometry": {"coordinates":[-2.9343435764,43.2531089783],"type":"Point"}
}