{
  "type": "Feature",
  "properties": {
    "addr:full":"Calle de Autonomia, 1 Donostia-san Sebastian Guip\u00f9zcoa 20006",
    "addr:housenumber":"1",
    "addr:postcode":"20006",
    "addr:street":"Calle De Autonomia",
    "iso:country":"ES",
    "sg:address":"Calle de Autonomia, 1",
    "sg:city":"Donostia-san Sebastian",
    "sg:orig_category":"Molduras, Junquillos, Listones Y Molduras Perforadas",
    "sg:phone":"+34 943 45 96 99",
    "sg:postcode":"20006",
    "sg:province":"Guip\u00f9zcoa",
    "wof:name":"Larxe Campos Maria Jose",
    "wof:placetype":"venue"
},
  "geometry": {"coordinates":[-1.9825656414,43.3138504028],"type":"Point"}
}