{
  "type": "Feature",
  "properties": {
    "iso:country":"ES",
    "sg:address":"Calle de Hortolans, 9",
    "sg:city":"Burriana",
    "sg:orig_category":"Importaci\u00d3n",
    "sg:phone":"+34 964 51 80 41",
    "sg:postcode":"12530",
    "sg:province":"Castell\u00f3n",
    "wof:name":"Pedro Monsonis S.a.",
    "wof:placetype":"venue"
},
  "geometry": {"coordinates":[-0.0880070031,39.8926048279],"type":"Point"}
}