{
  "type": "Feature",
  "properties": {
    "addr:full":"Calle de Cirilo Amoros, 4 Valencia Valencia 46004",
    "addr:housenumber":"4",
    "addr:postcode":"46004",
    "addr:street":"Calle De Cirilo Amoros",
    "iso:country":"ES",
    "sg:address":"Calle de Cirilo Amoros, 4",
    "sg:city":"Valencia",
    "sg:orig_category":"Asesor\u00cdas Y Estudios Financieros",
    "sg:phone":"+34 963 52 01 98",
    "sg:postcode":"46004",
    "sg:province":"Valencia",
    "wof:name":"Garcia Royo Jose",
    "wof:placetype":"venue"
},
  "geometry": {"coordinates":[-0.3741236925,39.4661941528],"type":"Point"}
}