{
  "type": "Feature",
  "properties": {
    "addr:full":"Calle de Virgen De La Soledad, 11 Guadalajara Guadalajara 19003",
    "addr:postcode":"19003",
    "addr:street":"Calle De Virgen De La Soledad 11",
    "iso:country":"ES",
    "sg:address":"Calle de Virgen De La Soledad, 11",
    "sg:city":"Guadalajara",
    "sg:orig_category":"Mercer\u00cda, Lencer\u00cda (al Por Menor)",
    "sg:phone":"+34 949 22 00 76",
    "sg:postcode":"19003",
    "sg:province":"Guadalajara",
    "wof:name":"Perez Cristobal Maria Antonia",
    "wof:placetype":"venue"
},
  "geometry": {"coordinates":[-3.1656289101,40.6282348633],"type":"Point"}
}