{
  "type": "Feature",
  "properties": {
    "addr:full":"Avda Domingo Bueno, 50 Pontenova Pontevedra 36400",
    "addr:housenumber":"50",
    "addr:postcode":"36400",
    "addr:street":"Avda Domingo Bueno",
    "iso:country":"ES",
    "sg:address":"Avda Domingo Bueno, 50",
    "sg:city":"Pontenova",
    "sg:orig_category":"Mutuas De Seguros",
    "sg:phone":"+34 986 33 69 55",
    "sg:postcode":"36400",
    "sg:province":"Pontevedra",
    "wof:name":"Fraternidad-muprespa Mutua De Accidentes De Trabajo Y Enfermedades Profesionales",
    "wof:placetype":"venue"
},
  "geometry": {"coordinates":[-8.6179990768,42.1610298157],"type":"Point"}
}