{
  "type": "Feature",
  "properties": {
    "iso:country":"ES",
    "sg:address":"Carrer de Agudells, 36",
    "sg:city":"Barcelona",
    "sg:orig_category":"Carnicer\u00cdas, Carnicer\u00cdas",
    "sg:phone":"+34 934 20 45 94",
    "sg:postcode":"08032",
    "sg:province":"Barcelona",
    "wof:name":"Blasco Cespedes Maria Rosa",
    "wof:placetype":"venue"
},
  "geometry": {"coordinates":[2.1579089165,41.4234619141],"type":"Point"}
}