{
  "type": "Feature",
  "properties": {
    "iso:country":"ES",
    "sg:address":"Av Castell D'aro, 74",
    "sg:city":"Platja D'aro",
    "sg:orig_category":"Ropa Para Se\u00d1oras Y Caballeros (al Por Menor)",
    "sg:phone":"+34 972 81 79 77",
    "sg:postcode":"17250",
    "sg:province":"Girona",
    "wof:name":"Bustins Frigola Rosa",
    "wof:placetype":"venue"
},
  "geometry": {"coordinates":[2.8271551132,41.988822937],"type":"Point"}
}