{
  "type": "Feature",
  "properties": {
    "addr:full":"Rua Principe, 28 Vigo Pontevedra 36202",
    "addr:housenumber":"28",
    "addr:postcode":"36202",
    "addr:street":"Rua Principe",
    "iso:country":"ES",
    "sg:address":"Rua Principe, 28",
    "sg:city":"Vigo",
    "sg:orig_category":"Art\u00cdculos De Regalo (al Por Menor)",
    "sg:phone":"+34 986 43 59 05",
    "sg:postcode":"36202",
    "sg:province":"Pontevedra",
    "wof:name":"Estevez Abalde Maria Jose",
    "wof:placetype":"venue"
},
  "geometry": {"coordinates":[-8.7230730057,42.2368354797],"type":"Point"}
}