{
  "type": "Feature",
  "properties": {
    "addr:full":"C/ 108, 19 Ca\u00d1ada Valencia 46182",
    "addr:housenumber":"19",
    "addr:postcode":"46182",
    "addr:street":"C / 108",
    "iso:country":"ES",
    "sg:address":"C/ 108, 19",
    "sg:city":"Ca\u00d1ada",
    "sg:orig_category":"M\u00c1quinas De Escribir, M\u00c1quinas De Oficina (al Por Menor, Reparaci\u00d3n)",
    "sg:phone":"+34 961 32 44 72",
    "sg:postcode":"46182",
    "sg:province":"Valencia",
    "wof:name":"Chirivella Vilaplana Manuel",
    "wof:placetype":"venue"
},
  "geometry": {"coordinates":[-0.4852339923,39.5221443176],"type":"Point"}
}