{
  "type": "Feature",
  "properties": {
    "iso:country":"ES",
    "sg:address":"Casta\u00f1o, 3",
    "sg:city":"Vilaflor",
    "sg:orig_category":"M\u00c1quinas Y Material Para La Industria De La Alimentaci\u00d3n",
    "sg:phone":"+34 922 70 90 94",
    "sg:postcode":"38613",
    "sg:province":"Santa Cruz De Tenerife",
    "wof:name":"Lorenzo Fumero Candelaria",
    "wof:placetype":"venue"
},
  "geometry": {"coordinates":[-16.6351242065,28.1678848267],"type":"Point"}
}