{
  "type": "Feature",
  "properties": {
    "iso:country":"ES",
    "sg:address":"Jaume Carner, 56",
    "sg:city":"El Vendrell",
    "sg:orig_category":"Restaurantes",
    "sg:phone":"+34 977 66 71 13",
    "sg:postcode":"43700",
    "sg:province":"Tarragona",
    "wof:name":"Maixu S.c.p.",
    "wof:placetype":"venue"
},
  "geometry": {"coordinates":[1.5357480049,41.2174606323],"type":"Point"}
}