{
  "type": "Feature",
  "properties": {
    "iso:country":"ES",
    "sg:address":"Garrofa(roses), 1",
    "sg:city":"Pozo-estrecho",
    "sg:orig_category":"Transportes Por Carretera: Lotes Completos, Mercanc\u00cdas Diversas",
    "sg:phone":"+34 968 16 62 64",
    "sg:postcode":"30594",
    "sg:province":"Murcia",
    "wof:name":"Transportes Conejo Murcia S.l.",
    "wof:placetype":"venue"
},
  "geometry": {"coordinates":[-0.9950090051,37.7132110596],"type":"Point"}
}