{
  "type": "Feature",
  "properties": {
    "iso:country":"ES",
    "sg:address":"Avgd Alfons Xiii, 248",
    "sg:city":"Badalona",
    "sg:orig_category":"Cervecer\u00cdas",
    "sg:phone":"+34 933 87 10 81",
    "sg:postcode":"08914",
    "sg:province":"Barcelona",
    "wof:name":"Castany Gomez Maria Asuncion",
    "wof:placetype":"venue"
},
  "geometry": {"coordinates":[2.2293119431,41.4400787354],"type":"Point"}
}