{
  "type": "Feature",
  "properties": {
    "addr:full":"Calle de Becquer, 42 Sevilla Sevilla 41002",
    "addr:housenumber":"42",
    "addr:postcode":"41002",
    "addr:street":"Calle De Becquer",
    "iso:country":"ES",
    "sg:address":"Calle de Becquer, 42",
    "sg:city":"Sevilla",
    "sg:orig_category":"Empresarios Y Productoras De Espect\u00c1culos",
    "sg:phone":"+34 954 37 09 87",
    "sg:postcode":"41002",
    "sg:province":"Sevilla",
    "wof:name":"Girasol Producciones S.l.",
    "wof:placetype":"venue"
},
  "geometry": {"coordinates":[-5.9918284416,37.4028930664],"type":"Point"}
}