{
  "type": "Feature",
  "properties": {
    "addr:full":"Carrer de Eduardo Dato, 3 Palma Islas Baleares 07004",
    "addr:housenumber":"3",
    "addr:postcode":"07004",
    "addr:street":"Carrer De Eduardo Dato",
    "iso:country":"ES",
    "sg:address":"Carrer de Eduardo Dato, 3",
    "sg:city":"Palma",
    "sg:orig_category":"Aparatos Digitales",
    "sg:phone":"+34 971 29 68 55",
    "sg:postcode":"07004",
    "sg:province":"Islas Baleares",
    "wof:name":"Mazmen Fotografia C.b.",
    "wof:placetype":"venue"
},
  "geometry": {"coordinates":[2.6509180069,39.5874824524],"type":"Point"}
}