{
  "type": "Feature",
  "properties": {
    "iso:country":"ES",
    "sg:address":"Pg Fabra I Puig, 383",
    "sg:city":"Barcelona",
    "sg:orig_category":"Farmacias",
    "sg:phone":"+34 932 74 93 63",
    "sg:postcode":"08031",
    "sg:province":"Barcelona",
    "wof:name":"Oliva Duran Juan",
    "wof:placetype":"venue"
},
  "geometry": {"coordinates":[2.1632559299,41.4337882996],"type":"Point"}
}