{
  "type": "Feature",
  "properties": {
    "addr:full":"Calle de Sierra Blanca, 8 Malaga M\u00e1laga 29003",
    "addr:housenumber":"8",
    "addr:postcode":"29003",
    "addr:street":"Calle De Sierra Blanca;Ma\u0301Laga",
    "iso:country":"ES",
    "sg:address":"Calle de Sierra Blanca, 8",
    "sg:city":"Malaga",
    "sg:orig_category":"Estudios, Instalaci\u00d3n De Climatizaci\u00d3n",
    "sg:phone":"+34 952 04 20 31",
    "sg:postcode":"29003",
    "sg:province":"M\u00e1laga",
    "wof:name":"Condiziodata S.l.",
    "wof:placetype":"venue"
},
  "geometry": {"coordinates":[-4.4504961967,36.6982421875],"type":"Point"}
}