{
  "type": "Feature",
  "properties": {
    "addr:full":"Calle de Almaden De La Plata, 21 Sevilla Sevilla 41008",
    "addr:housenumber":"21",
    "addr:postcode":"41008",
    "addr:street":"Calle De Almaden De La Plata",
    "iso:country":"ES",
    "sg:address":"Calle de Almaden De La Plata, 21",
    "sg:city":"Sevilla",
    "sg:orig_category":"Agentes, Concesionarios Y Sucursales De Veh\u00cdculos",
    "sg:phone":"+34 954 35 48 65",
    "sg:postcode":"41008",
    "sg:province":"Sevilla",
    "wof:name":"Retamal Automoviles S.l.",
    "wof:placetype":"venue"
},
  "geometry": {"coordinates":[-5.9779548645,37.4001464844],"type":"Point"}
}