{
  "type": "Feature",
  "properties": {
    "addr:full":"Carrer de Botanica, 35 Hospitalet Llobregat Barcelona 08908",
    "addr:housenumber":"35",
    "addr:postcode":"08908",
    "addr:street":"Carrer De Botanica",
    "iso:country":"ES",
    "sg:address":"Carrer de Botanica, 35",
    "sg:city":"Hospitalet Llobregat",
    "sg:orig_category":"Materias Pl\u00c1sticas: Productos De Consumo Masivo (fabricaci\u00d3n, Al Por Mayor)",
    "sg:phone":"+34 932 63 09 03",
    "sg:postcode":"08908",
    "sg:province":"Barcelona",
    "wof:name":"Riuplastic S.a.",
    "wof:placetype":"venue"
},
  "geometry": {"coordinates":[2.1301000118,41.3514099121],"type":"Point"}
}