{
  "type": "Feature",
  "properties": {
    "addr:full":"C/ Jose Maria Peman, 1 Elche Alicante 03201",
    "addr:housenumber":"1",
    "addr:postcode":"03201",
    "addr:street":"C / Jose Maria Peman",
    "iso:country":"ES",
    "sg:address":"C/ Jose Maria Peman, 1",
    "sg:city":"Elche",
    "sg:orig_category":"Cuidado Del Cabello",
    "sg:phone":"+34 965 43 51 94",
    "sg:postcode":"03201",
    "sg:province":"Alicante",
    "sg:website":"www.svenson.es",
    "wof:name":"Svenson S.l.",
    "wof:placetype":"venue"
},
  "geometry": {"coordinates":[-0.7037199736,38.2652511597],"type":"Point"}
}