{
  "type": "Feature",
  "properties": {
    "addr:full":"Calle de San Miguel Alta, 16 Granada Granada 18002",
    "addr:housenumber":"16",
    "addr:postcode":"18002",
    "addr:street":"Calle De San;Alta",
    "iso:country":"ES",
    "sg:address":"Calle de San Miguel Alta, 16",
    "sg:city":"Granada",
    "sg:orig_category":"Artesan\u00cda",
    "sg:phone":"+34 958 26 61 24",
    "sg:postcode":"18002",
    "sg:province":"Granada",
    "wof:name":"Navarro Linares Candido",
    "wof:placetype":"venue"
},
  "geometry": {"coordinates":[-3.6037073135,37.173614502],"type":"Point"}
}