{
  "type": "Feature",
  "properties": {
    "addr:full":"Calle de Becerro De Bengoa, 10 Palencia Palencia 34002",
    "addr:housenumber":"10",
    "addr:postcode":"34002",
    "addr:street":"Calle De Becerro De Bengoa",
    "iso:country":"ES",
    "sg:address":"Calle de Becerro De Bengoa, 10",
    "sg:city":"Palencia",
    "sg:orig_category":"Abogados",
    "sg:phone":"+34 979 75 01 99",
    "sg:postcode":"34002",
    "sg:province":"Palencia",
    "wof:name":"Martin Bustos Alberto",
    "wof:placetype":"venue"
},
  "geometry": {"coordinates":[-4.5315208435,42.0089454651],"type":"Point"}
}