{
  "type": "Feature",
  "properties": {
    "addr:full":"Manolo Gomez Bur, 52 Bailen Ja\u00e9n 23710",
    "addr:housenumber":"52",
    "addr:postcode":"23710",
    "addr:street":"Jae\u0301N",
    "iso:country":"ES",
    "sg:address":"Manolo Gomez Bur, 52",
    "sg:city":"Bailen",
    "sg:orig_category":"Delegados, Agentes De Tr\u00c1nsito, Auxiliares De Transporte Internacional",
    "sg:phone":"+34 953 67 32 06",
    "sg:postcode":"23710",
    "sg:province":"Ja\u00e9n",
    "wof:name":"Reyes Mondejar Rafael",
    "wof:placetype":"venue"
},
  "geometry": {"coordinates":[-3.779558897,38.0967903137],"type":"Point"}
}