{
  "type": "Feature",
  "properties": {
    "addr:full":"Calle de San Isidro, 7 Valdemoro Madrid 28340",
    "addr:housenumber":"7",
    "addr:postcode":"28340",
    "addr:street":"Calle De San Isidro",
    "iso:country":"ES",
    "sg:address":"Calle de San Isidro, 7",
    "sg:city":"Valdemoro",
    "sg:orig_category":"Cl\u00cdnicas Dentales",
    "sg:phone":"+34 918 08 14 20",
    "sg:postcode":"28340",
    "sg:province":"Madrid",
    "wof:name":"Valdesalud S.l.",
    "wof:placetype":"venue"
},
  "geometry": {"coordinates":[-3.6765999794,40.1934394836],"type":"Point"}
}