{
  "type": "Feature",
  "properties": {
    "addr:full":"Calle de Fresa, S/n Majadahonda Madrid 28220",
    "addr:postcode":"28220",
    "addr:street":"Calle De Fresa S / N",
    "iso:country":"ES",
    "sg:address":"Calle de Fresa, S/n",
    "sg:city":"Majadahonda",
    "sg:orig_category":"Perfumer\u00cda (al Por Menor)",
    "sg:phone":"+34 916 39 06 77",
    "sg:postcode":"28220",
    "sg:province":"Madrid",
    "wof:name":"Caoba Cosmetics S.l.",
    "wof:placetype":"venue"
},
  "geometry": {"coordinates":[-3.8717639446,40.4534339905],"type":"Point"}
}