{
  "type": "Feature",
  "properties": {
    "iso:country":"ES",
    "sg:address":"Av Barbera, 439",
    "sg:city":"Sabadell",
    "sg:orig_category":"Cajas De Ahorro",
    "sg:phone":"+34 937 10 20 05",
    "sg:postcode":"08204",
    "sg:province":"Barcelona",
    "wof:name":"Caixa D'estalvis I Pensions De Barcelona",
    "wof:placetype":"venue"
},
  "geometry": {"coordinates":[2.1181609631,41.5282821655],"type":"Point"}
}