{
  "type": "Feature",
  "properties": {
    "iso:country":"ES",
    "sg:address":"Calle de Santiago, 9",
    "sg:city":"Irun",
    "sg:orig_category":"Inform\u00c1tica (estudios, Servicios, Asesor\u00cda, Formaci\u00d3n)",
    "sg:phone":"+34 943 63 15 15",
    "sg:postcode":"20304",
    "sg:province":"Guip\u00f9zcoa",
    "wof:name":"Sistemas De Oficina Del Bidasoa, S.l.",
    "wof:placetype":"venue"
},
  "geometry": {"coordinates":[-1.7871290445,43.3405990601],"type":"Point"}
}