{
  "type": "Feature",
  "properties": {
    "addr:full":"Rua Capitan Bernal, 10 Estrada Pontevedra 36680",
    "addr:housenumber":"10",
    "addr:postcode":"36680",
    "addr:street":"Rua Capitan Bernal;Estrada Pontevedra",
    "iso:country":"ES",
    "sg:address":"Rua Capitan Bernal, 10",
    "sg:city":"Estrada",
    "sg:orig_category":"Sindicatos De Trabajadores",
    "sg:phone":"+34 986 57 32 32",
    "sg:postcode":"36680",
    "sg:province":"Pontevedra",
    "wof:name":"Sindicato Labrego Galego",
    "wof:placetype":"venue"
},
  "geometry": {"coordinates":[-8.4910736084,42.6887664795],"type":"Point"}
}