{
  "type": "Feature",
  "properties": {
    "iso:country":"ES",
    "sg:address":"Edificio Felgueroso, 10",
    "sg:city":"Llangreu",
    "sg:orig_category":"Talleres: Ropa A Medida",
    "sg:phone":"+34 985 69 26 84",
    "sg:postcode":"33930",
    "sg:province":"Asturias",
    "wof:name":"Alonso Gonzalez Angel Ramon",
    "wof:placetype":"venue"
},
  "geometry": {"coordinates":[-5.6918201447,43.3098716736],"type":"Point"}
}