{
  "type": "Feature",
  "properties": {
    "addr:full":"Grup San Matias, S/n Sevilla Sevilla 41008",
    "addr:housenumber":"s / n",
    "addr:postcode":"41008",
    "addr:street":"San Matias",
    "iso:country":"ES",
    "sg:address":"Grup San Matias, S/n",
    "sg:city":"Sevilla",
    "sg:orig_category":"Asesor\u00cda, Estudio Y Control Medioambiental",
    "sg:phone":"+34 954 35 82 72",
    "sg:postcode":"41008",
    "sg:province":"Sevilla",
    "wof:name":"Gamero Rodriguez Alberto",
    "wof:placetype":"venue"
},
  "geometry": {"coordinates":[-5.9776787758,37.3983459473],"type":"Point"}
}