{
  "type": "Feature",
  "properties": {
    "addr:full":"Psaj Cerro Del Toril, S/n Torremolinos M\u00e1laga 29620",
    "addr:housenumber":"/ n",
    "addr:postcode":"29620",
    "addr:street":"Toril S;Ma\u0301Laga",
    "iso:country":"ES",
    "sg:address":"Psaj Cerro Del Toril, S/n",
    "sg:city":"Torremolinos",
    "sg:orig_category":"Internados & Ense\u00d1anza Privada",
    "sg:phone":"+34 952 38 31 64",
    "sg:postcode":"29620",
    "sg:province":"M\u00e1laga",
    "wof:name":"Sunny View School S.l.",
    "wof:placetype":"venue"
},
  "geometry": {"coordinates":[-4.5139789581,36.6152000427],"type":"Point"}
}