{
  "type": "Feature",
  "properties": {
    "addr:full":"Carrer de Murcia, 30 S. Boi Llobregat Barcelona 08830",
    "addr:housenumber":"30",
    "addr:postcode":"08830",
    "addr:street":"Carrer De Murcia",
    "iso:country":"ES",
    "sg:address":"Carrer de Murcia, 30",
    "sg:city":"S. Boi Llobregat",
    "sg:orig_category":"Materias Pl\u00c1sticas: Art\u00cdculos Para La Industria",
    "sg:phone":"+34 936 40 66 44",
    "sg:postcode":"08830",
    "sg:province":"Barcelona",
    "wof:name":"Termo Forma S.l",
    "wof:placetype":"venue"
},
  "geometry": {"coordinates":[2.0417621136,41.3285369873],"type":"Point"}
}