{
  "type": "Feature",
  "properties": {
    "addr:full":"Pol Ind El Rubial, 110 Villena Alicante 03400",
    "addr:housenumber":"110",
    "addr:postcode":"03400",
    "iso:country":"ES",
    "sg:address":"Pol Ind El Rubial, 110",
    "sg:city":"Villena",
    "sg:orig_category":"Serigraf\u00cda (material Y Suministros)",
    "sg:phone":"+34 965 80 45 11",
    "sg:postcode":"03400",
    "sg:province":"Alicante",
    "wof:name":"Inser J. Pardo Y Gisbert S.l.",
    "wof:placetype":"venue"
},
  "geometry": {"coordinates":[-0.8688759804,38.6403198242],"type":"Point"}
}