{
  "type": "Feature",
  "properties": {
    "addr:full":"Avda Gran Via Tarrega Monteblanco, 5 Castellon Castell\u00f3n 12006",
    "addr:housenumber":"5",
    "addr:postcode":"12006",
    "addr:street":"Avda Gran Via Tarrega Monteblanco;Castello\u0301N",
    "iso:country":"ES",
    "sg:address":"Avda Gran Via Tarrega Monteblanco, 5",
    "sg:city":"Castellon",
    "sg:orig_category":"Molduras, Junquillos, Listones Y Molduras Perforadas",
    "sg:phone":"+34 964 21 16 78",
    "sg:postcode":"12006",
    "sg:province":"Castell\u00f3n",
    "wof:name":"Castillo Iba\u00f1ez Daniel",
    "wof:placetype":"venue"
},
  "geometry": {"coordinates":[-0.1292939931,40.0168533325],"type":"Point"}
}