{
  "type": "Feature",
  "properties": {
    "iso:country":"ES",
    "sg:address":"Urb C.r. Novo Sancti-petri, S/n",
    "sg:city":"Barrosa",
    "sg:orig_category":"Centros Comerciales Y Grandes Tiendas",
    "sg:phone":"+34 956 49 53 52",
    "sg:postcode":"11130",
    "sg:province":"C\u00e1diz",
    "wof:name":"Comunidad De Propietarios Centro Comercial Novo Center",
    "wof:placetype":"venue"
},
  "geometry": {"coordinates":[-6.1447038651,36.4212188721],"type":"Point"}
}