{
  "type": "Feature",
  "properties": {
    "iso:country":"ES",
    "sg:address":"Calle de Cercedilla, 14",
    "sg:city":"Estacion",
    "sg:orig_category":"Centros Empresariales",
    "sg:phone":"+34 918 51 33 36",
    "sg:postcode":"28400",
    "sg:province":"Madrid",
    "sg:website":"www.telefonica.net/web/smeraldo3000",
    "wof:name":"Smeraldo 3000 S.l.",
    "wof:placetype":"venue"
},
  "geometry": {"coordinates":[-3.9919650555,40.6455612183],"type":"Point"}
}