{
  "type": "Feature",
  "properties": {
    "iso:country":"ES",
    "sg:address":"Ctra Aznalcollar, Km. 0008,0",
    "sg:city":"Sanlucar Mayor",
    "sg:orig_category":"Vallados Y Barreras",
    "sg:phone":"+34 955 99 00 73",
    "sg:postcode":"41800",
    "sg:province":"Sevilla",
    "wof:name":"Cerramientos Y Transportes Olivares S.l.",
    "wof:placetype":"venue"
},
  "geometry": {"coordinates":[-6.1956338882,37.3855361938],"type":"Point"}
}