{
  "type": "Feature",
  "properties": {
    "iso:country":"ES",
    "sg:address":"Ametler(urb Sa Coma), 29",
    "sg:city":"Bunyola",
    "sg:orig_category":"Inversiones",
    "sg:phone":"+34 971 61 55 13",
    "sg:postcode":"07110",
    "sg:province":"Islas Baleares",
    "wof:name":"Homonovus S.l",
    "wof:placetype":"venue"
},
  "geometry": {"coordinates":[2.6937870979,39.6730461121],"type":"Point"}
}