{
  "type": "Feature",
  "properties": {
    "addr:full":"Ctra. Polan, Km. 0016,0 Puebla Montalban Toledo 45516",
    "addr:postcode":"45516",
    "addr:street":"Ctra. Polan Km. 0016,0",
    "iso:country":"ES",
    "sg:address":"Ctra. Polan, Km. 0016,0",
    "sg:city":"Puebla Montalban",
    "sg:orig_category":"Arenas, Guijarros Y Granulados",
    "sg:phone":"+34 925 78 91 57",
    "sg:postcode":"45516",
    "sg:province":"Toledo",
    "wof:name":"Aripad S.l.",
    "wof:placetype":"venue"
},
  "geometry": {"coordinates":[-4.3002505302,39.9002456665],"type":"Point"}
}