{
  "type": "Feature",
  "properties": {
    "addr:full":"Avda Constitucion, 96 Torrejon Ardoz Madrid 28850",
    "addr:housenumber":"96",
    "addr:postcode":"28850",
    "addr:street":"Avda Constitucion",
    "iso:country":"ES",
    "sg:address":"Avda Constitucion, 96",
    "sg:city":"Torrejon Ardoz",
    "sg:orig_category":"Promotores Constructores",
    "sg:phone":"+34 916 77 59 75",
    "sg:postcode":"28850",
    "sg:province":"Madrid",
    "wof:name":"Torrejon Hoteles S.l.",
    "wof:placetype":"venue"
},
  "geometry": {"coordinates":[-3.4714200497,40.4575576782],"type":"Point"}
}