{
  "type": "Feature",
  "properties": {
    "iso:country":"ES",
    "sg:address":"Calle de Antonio Lopez Del Oro, 18",
    "sg:city":"Hellin",
    "sg:orig_category":"Perfumer\u00cda (al Por Menor)",
    "sg:phone":"+34 967 30 63 11",
    "sg:postcode":"02400",
    "sg:province":"Albacete",
    "wof:name":"Medope S.a.",
    "wof:placetype":"venue"
},
  "geometry": {"coordinates":[-1.6989895105,38.5091018677],"type":"Point"}
}