{
  "type": "Feature",
  "properties": {
    "addr:full":"Av. Aragon, 34 Logro\u00f1o La Rioja 26006",
    "addr:housenumber":"34",
    "addr:postcode":"26006",
    "addr:street":"Av. Aragon;Rioja",
    "iso:country":"ES",
    "sg:address":"Av. Aragon, 34",
    "sg:city":"Logro\u00f1o",
    "sg:orig_category":"Colchones (fabricaci\u00d3n, Al Por Mayor, Al Por Menor)",
    "sg:phone":"+34 941 26 12 69",
    "sg:postcode":"26006",
    "sg:province":"La Rioja",
    "wof:name":"Nakhil  Hamid",
    "wof:placetype":"venue"
},
  "geometry": {"coordinates":[-2.4211890697,42.4611282349],"type":"Point"}
}