{
  "type": "Feature",
  "properties": {
    "addr:full":"Calle de Alloza, 163 Castellon Castell\u00f3n 12001",
    "addr:housenumber":"163",
    "addr:postcode":"12001",
    "addr:street":"Calle De Alloza;Castello\u0301N",
    "iso:country":"ES",
    "sg:address":"Calle de Alloza, 163",
    "sg:city":"Castellon",
    "sg:orig_category":"Centros Comerciales Y Grandes Tiendas",
    "sg:phone":"+34 964 25 49 47",
    "sg:postcode":"12001",
    "sg:province":"Castell\u00f3n",
    "wof:name":"Blanch Nicolau Maria Del Carmen",
    "wof:placetype":"venue"
},
  "geometry": {"coordinates":[-0.0385608003,39.9881248474],"type":"Point"}
}