{
  "type": "Feature",
  "properties": {
    "addr:full":"Iturrama, 11 Iru\u00f1a Navarra 31007",
    "addr:housenumber":"11",
    "addr:postcode":"31007",
    "addr:street":"Iturrama",
    "iso:country":"ES",
    "sg:address":"Iturrama, 11",
    "sg:city":"Iru\u00f1a",
    "sg:classifiers":[
        {
            "category":"Autos & Motor Vehicles",
            "subcategory":"Automobile Sales",
            "type":"Retail Goods"
        }
    ],
    "sg:phone":"+34 948 27 81 69",
    "sg:postcode":"31007",
    "sg:province":"Navarra",
    "wof:name":"Auto Escuela Mariezcurrena S.l.",
    "wof:placetype":"venue"
},
  "geometry": {"coordinates":[-1.6503597498,42.804019928],"type":"Point"}
}