{
  "type": "Feature",
  "properties": {
    "addr:full":"Calle de Ermita, 24 Burlada Navarra 31600",
    "addr:housenumber":"24",
    "addr:postcode":"31600",
    "addr:street":"Calle De Ermita",
    "iso:country":"ES",
    "sg:address":"Calle de Ermita, 24",
    "sg:city":"Burlada",
    "sg:orig_category":"Art\u00cdculos De Aluminio",
    "sg:phone":"+34 948 14 11 14",
    "sg:postcode":"31600",
    "sg:province":"Navarra",
    "wof:name":"Muro Garcia Heliodoro",
    "wof:placetype":"venue"
},
  "geometry": {"coordinates":[-1.6109880209,42.8275871277],"type":"Point"}
}