{
  "type": "Feature",
  "properties": {
    "addr:full":"Ctra Castell D'aro, 51 S. Feliu Guixols Girona 17220",
    "addr:housenumber":"51",
    "addr:postcode":"17220",
    "addr:street":"Ctra Castell D'Aro;S. Feliu Guixols",
    "iso:country":"ES",
    "sg:address":"Ctra Castell D'aro, 51",
    "sg:city":"S. Feliu Guixols",
    "sg:orig_category":"Panader\u00cdas, Panader\u00cdas",
    "sg:phone":"+34 972 32 42 21",
    "sg:postcode":"17220",
    "sg:province":"Girona",
    "wof:name":"Cortes Gonzalez Francisco",
    "wof:placetype":"venue"
},
  "geometry": {"coordinates":[2.8242149353,41.9879989624],"type":"Point"}
}