{
  "type": "Feature",
  "properties": {
    "iso:country":"ES",
    "sg:address":"Dormitaleria, 16",
    "sg:city":"Iru\u00f1a",
    "sg:orig_category":"Consultor\u00cdas Diversas",
    "sg:phone":"+34 948 22 32 02",
    "sg:postcode":"31001",
    "sg:province":"Navarra",
    "wof:name":"Argilur S. Cv.",
    "wof:placetype":"venue"
},
  "geometry": {"coordinates":[-1.6413121223,42.8191452026],"type":"Point"}
}