{
  "type": "Feature",
  "properties": {
    "iso:country":"ES",
    "sg:address":"Avda Madrid, 93",
    "sg:city":"Le\u00f3n",
    "sg:orig_category":"Agentes, Concesionarios Y Sucursales De Camiones Y Veh\u00cdculos Industriales",
    "sg:phone":"+34 987 21 57 20",
    "sg:postcode":"24005",
    "sg:province":"Le\u00f3n",
    "sg:website":"www.paginasamarillas.es",
    "wof:name":"Carolina Motor S.l.",
    "wof:placetype":"venue"
},
  "geometry": {"coordinates":[-5.5473408699,42.5787391663],"type":"Point"}
}