{
  "type": "Feature",
  "properties": {
    "addr:full":"Calle de Pintor Aparicio, 32 Alacant Alicante 03003",
    "addr:housenumber":"32",
    "addr:postcode":"03003",
    "addr:street":"Calle De Pintor Aparicio",
    "iso:country":"ES",
    "sg:address":"Calle de Pintor Aparicio, 32",
    "sg:city":"Alacant",
    "sg:orig_category":"Art\u00cdculos De Regalo (al Por Menor)",
    "sg:phone":"+34 965 12 38 46",
    "sg:postcode":"03003",
    "sg:province":"Alicante",
    "wof:name":"Sanchez De Rodriguez Alicia Beatriz",
    "wof:placetype":"venue"
},
  "geometry": {"coordinates":[-0.4916799963,38.3421707153],"type":"Point"}
}