{
  "type": "Feature",
  "properties": {
    "iso:country":"ES",
    "sg:address":"Felix Rguez. De La Fuente, 1",
    "sg:city":"Catadau",
    "sg:orig_category":"Cajas Y Embalajes De Madera",
    "sg:phone":"+34 962 99 00 72",
    "sg:postcode":"46196",
    "sg:province":"Valencia",
    "wof:name":"Testex S.l.",
    "wof:placetype":"venue"
},
  "geometry": {"coordinates":[-0.5759360194,39.2724914551],"type":"Point"}
}