{
  "type": "Feature",
  "properties": {
    "addr:full":"Calle de Noria, S/n Alhama De Almeria Almer\u00eda 04400",
    "addr:housenumber":"s",
    "addr:postcode":"04400",
    "addr:street":"Calle De Noria;/ N Alhama;Almeri\u0301A",
    "iso:country":"ES",
    "sg:address":"Calle de Noria, S/n",
    "sg:city":"Alhama De Almeria",
    "sg:orig_category":"Sanatorios M\u00c9dico",
    "sg:phone":"+34 950 64 10 77",
    "sg:postcode":"04400",
    "sg:province":"Almer\u00eda",
    "wof:name":"Servicio Andaluz De Salud",
    "wof:placetype":"venue"
},
  "geometry": {"coordinates":[-2.5680689812,36.9581642151],"type":"Point"}
}