{
  "type": "Feature",
  "properties": {
    "addr:full":"Peral(peral), 15 Cartagena Murcia 30300",
    "addr:housenumber":"15",
    "addr:postcode":"30300",
    "addr:street":"Peral",
    "iso:country":"ES",
    "sg:address":"Peral(peral), 15",
    "sg:city":"Cartagena",
    "sg:orig_category":"Bebidas",
    "sg:phone":"+34 968 53 69 62",
    "sg:postcode":"30300",
    "sg:province":"Murcia",
    "wof:name":"Centro Mediterranea De Bebidas Carbonicas Pepsico S.l.",
    "wof:placetype":"venue"
},
  "geometry": {"coordinates":[-0.9635059834,37.6914291382],"type":"Point"}
}