{
  "type": "Feature",
  "properties": {
    "iso:country":"ES",
    "sg:address":"Calle de Panueva, 38",
    "sg:city":"Tafalla",
    "sg:orig_category":"Art\u00cdculos Funerarios (al Por Menor)",
    "sg:phone":"+34 948 70 35 84",
    "sg:postcode":"31300",
    "sg:province":"Navarra",
    "wof:name":"Tanatorio Cipres S.l.",
    "wof:placetype":"venue"
},
  "geometry": {"coordinates":[-1.6720868349,42.534450531],"type":"Point"}
}