{
  "type": "Feature",
  "properties": {
    "addr:full":"Carrer de Napols, 319 Barcelona Barcelona 08025",
    "addr:housenumber":"319",
    "addr:postcode":"08025",
    "addr:street":"Carrer De Napols",
    "iso:country":"ES",
    "sg:address":"Carrer de Napols, 319",
    "sg:city":"Barcelona",
    "sg:orig_category":"Sociedades, Compa\u00d1\u00cdas Aseguradoras",
    "sg:phone":"+34 934 57 61 00",
    "sg:postcode":"08025",
    "sg:province":"Barcelona",
    "wof:name":"Fram Gabinete Correduria De Seguros S.l.",
    "wof:placetype":"venue"
},
  "geometry": {"coordinates":[2.1671180725,41.4044723511],"type":"Point"}
}