{
  "type": "Feature",
  "properties": {
    "iso:country":"ES",
    "sg:address":"Calle de Tenderina, S/n",
    "sg:city":"Oviedo",
    "sg:orig_category":"Carnicer\u00cdas, Carnicer\u00cdas",
    "sg:phone":"+34 985 28 86 51",
    "sg:postcode":"33010",
    "sg:province":"Asturias",
    "wof:name":"Lopez Menendez Pilar",
    "wof:placetype":"venue"
},
  "geometry": {"coordinates":[-5.8255238533,43.3676261902],"type":"Point"}
}