{
  "type": "Feature",
  "properties": {
    "iso:country":"ES",
    "sg:address":"Av Tarragona, 63",
    "sg:city":"Vilafranca Penedes",
    "sg:orig_category":"Asesor\u00cda Sobre Comunicaci\u00d3n De Empresas",
    "sg:phone":"+34 938 17 18 39",
    "sg:postcode":"08720",
    "sg:province":"Barcelona",
    "wof:name":"Safe Brocker S.l.",
    "wof:placetype":"venue"
},
  "geometry": {"coordinates":[1.6965290308,41.3428077698],"type":"Point"}
}