{
  "type": "Feature",
  "properties": {
    "addr:full":"Churruca, S/n Torredonjimeno Ja\u00e9n 23650",
    "addr:housenumber":"s / n",
    "addr:postcode":"23650",
    "addr:street":"Churruca",
    "iso:country":"ES",
    "sg:address":"Churruca, S/n",
    "sg:city":"Torredonjimeno",
    "sg:orig_category":"Centros De Educaci\u00d3n Especial",
    "sg:phone":"+34 953 57 18 83",
    "sg:postcode":"23650",
    "sg:province":"Ja\u00e9n",
    "wof:name":"Junta De Andalucia.delegacion Provincial De La Consejeria De Educacion Y Ciencia",
    "wof:placetype":"venue"
},
  "geometry": {"coordinates":[-4.0899910927,37.8016700745],"type":"Point"}
}