{
  "type": "Feature",
  "properties": {
    "iso:country":"ES",
    "sg:address":"Carr Vallcalent, 1",
    "sg:city":"Lleida",
    "sg:orig_category":"Producci\u00d3n, Distribuci\u00d3n De Electricidad",
    "sg:phone":"+34 973 26 47 95",
    "sg:postcode":"25006",
    "sg:province":"Lleida",
    "sg:website":"www.g3e.net",
    "wof:name":"Global 3 Energia Scpa",
    "wof:placetype":"venue"
},
  "geometry": {"coordinates":[0.6203600168,41.6168708801],"type":"Point"}
}