{
  "type": "Feature",
  "properties": {
    "addr:full":"Calle de Murillo, 8 Madrid Madrid 28010",
    "addr:housenumber":"8",
    "addr:postcode":"madrid;28010",
    "addr:street":"Calle De Murillo",
    "iso:country":"ES",
    "sg:address":"Calle de Murillo, 8",
    "sg:city":"Madrid",
    "sg:orig_category":"Cester\u00cda (fabricaci\u00d3n)",
    "sg:phone":"+34 914 46 34 28",
    "sg:postcode":"28010",
    "sg:province":"Madrid",
    "wof:name":"Boye Blas Julian",
    "wof:placetype":"venue"
},
  "geometry": {"coordinates":[-3.700480938,40.4334106445],"type":"Point"}
}