{
  "type": "Feature",
  "properties": {
    "addr:full":"Avda Universidad, 4 Santander Cantabria 39006",
    "addr:housenumber":"4",
    "addr:postcode":"39006",
    "addr:street":"Avda Universidad",
    "iso:country":"ES",
    "sg:address":"Avda Universidad, 4",
    "sg:city":"Santander",
    "sg:orig_category":"Costureras",
    "sg:phone":"+34 942 27 40 48",
    "sg:postcode":"39006",
    "sg:province":"Cantabria",
    "wof:name":"Gutierrez Abascal Luis",
    "wof:placetype":"venue"
},
  "geometry": {"coordinates":[-3.7963619232,43.4685287476],"type":"Point"}
}