{
  "type": "Feature",
  "properties": {
    "addr:full":"Calle de San Miguel, 57 Torremolinos M\u00e1laga 29620",
    "addr:housenumber":"57",
    "addr:postcode":"29620",
    "addr:street":"Calle De San Miguel;Ma\u0301Laga",
    "iso:country":"ES",
    "sg:address":"Calle de San Miguel, 57",
    "sg:city":"Torremolinos",
    "sg:orig_category":"Bisuter\u00cda, Joyer\u00cda, Relojer\u00cda (al Por Menor)",
    "sg:phone":"+34 952 37 49 09",
    "sg:postcode":"29620",
    "sg:province":"M\u00e1laga",
    "wof:name":"Aswani  Santumal",
    "wof:placetype":"venue"
},
  "geometry": {"coordinates":[-4.497777462,36.6226272583],"type":"Point"}
}