{
  "type": "Feature",
  "properties": {
    "addr:full":"Calle de Autonomia Aragonesa, 49 Sarrion Teruel 44460",
    "addr:housenumber":"49",
    "addr:postcode":"44460",
    "addr:street":"Calle De Autonomia Aragonesa",
    "iso:country":"ES",
    "sg:address":"Calle de Autonomia Aragonesa, 49",
    "sg:city":"Sarrion",
    "sg:orig_category":"Reposter\u00cdas",
    "sg:phone":"+34 978 78 04 56",
    "sg:postcode":"44460",
    "sg:province":"Teruel",
    "wof:name":"Martin Perez Carolina",
    "wof:placetype":"venue"
},
  "geometry": {"coordinates":[-0.8136128783,40.1398124695],"type":"Point"}
}