{
  "type": "Feature",
  "properties": {
    "addr:full":"Calle de Tarrasa, 20 Cordoba C\u00f3rdoba 14006",
    "addr:housenumber":"20",
    "addr:postcode":"14006",
    "addr:street":"Calle De Tarrasa;Co\u0301Rdoba",
    "iso:country":"ES",
    "sg:address":"Calle de Tarrasa, 20",
    "sg:city":"Cordoba",
    "sg:orig_category":"Asociaciones Y Clubs Deportivos",
    "sg:phone":"+34 957 27 47 26",
    "sg:postcode":"14006",
    "sg:province":"C\u00f3rdoba",
    "sg:website":"www.grupoprasa.es",
    "wof:name":"Romero Gonzalez Pablo",
    "wof:placetype":"venue"
},
  "geometry": {"coordinates":[-4.7873139381,37.8986625671],"type":"Point"}
}