{
  "type": "Feature",
  "properties": {
    "iso:country":"ES",
    "sg:address":"Av Goles De L'ebre, 144",
    "sg:city":"Deltebre",
    "sg:orig_category":"Reposter\u00cdas",
    "sg:phone":"+34 977 48 00 90",
    "sg:postcode":"43580",
    "sg:province":"Tarragona",
    "wof:name":"Fresquet Alvarado Ferran",
    "wof:placetype":"venue"
},
  "geometry": {"coordinates":[0.7328900099,40.7174568176],"type":"Point"}
}