{
  "type": "Feature",
  "properties": {
    "addr:full":"Calle de Estacion, 23 Miranda Ebro Burgos 09200",
    "addr:housenumber":"23",
    "addr:postcode":"09200",
    "addr:street":"Calle De Estacion",
    "iso:country":"ES",
    "sg:address":"Calle de Estacion, 23",
    "sg:city":"Miranda Ebro",
    "sg:orig_category":"Ropa Para Se\u00d1oras (al Por Menor)",
    "sg:phone":"+34 947 31 04 27",
    "sg:postcode":"09200",
    "sg:province":"Burgos",
    "wof:name":"Fernandez Uriarte Carmen",
    "wof:placetype":"venue"
},
  "geometry": {"coordinates":[-2.944467783,42.6875610352],"type":"Point"}
}