{
  "type": "Feature",
  "properties": {
    "iso:country":"ES",
    "sg:address":"Avda Juan De Ayolas, 15",
    "sg:city":"Briviesca",
    "sg:orig_category":"Electricidad: Instaladores",
    "sg:phone":"+34 947 59 03 33",
    "sg:postcode":"09240",
    "sg:province":"Burgos",
    "wof:name":"Gonzalez Calzada Ildefonso",
    "wof:placetype":"venue"
},
  "geometry": {"coordinates":[-3.322855711,42.5481719971],"type":"Point"}
}