{
  "type": "Feature",
  "properties": {
    "addr:full":"Av Polinya, 31 Poblenou Barcelona 08202",
    "addr:housenumber":"31",
    "addr:postcode":"08202",
    "addr:street":"Av Polinya",
    "iso:country":"ES",
    "sg:address":"Av Polinya, 31",
    "sg:city":"Poblenou",
    "sg:orig_category":"Iglesia Cat\u00d3lica",
    "sg:phone":"+34 937 47 83 59",
    "sg:postcode":"08202",
    "sg:province":"Barcelona",
    "wof:name":"Parroquia De San Jaime",
    "wof:placetype":"venue"
},
  "geometry": {"coordinates":[2.1277220249,41.5607795715],"type":"Point"}
}