{
  "type": "Feature",
  "properties": {
    "iso:country":"ES",
    "sg:address":"Calle de Ramon Llull, 7",
    "sg:city":"Valencia",
    "sg:orig_category":"Promotores Constructores",
    "sg:phone":"+34 963 89 13 86",
    "sg:postcode":"46021",
    "sg:province":"Valencia",
    "wof:name":"Unipres 40 S.l.",
    "wof:placetype":"venue"
},
  "geometry": {"coordinates":[-0.3475329876,39.4752464294],"type":"Point"}
}