{
  "type": "Feature",
  "properties": {
    "iso:country":"ES",
    "sg:address":"Calle de Pedro Orbea, 6",
    "sg:city":"Vitoria-gasteiz",
    "sg:orig_category":"Institutos De Belleza",
    "sg:phone":"+34 945 25 49 00",
    "sg:postcode":"01002",
    "sg:province":"\u00c1lava",
    "wof:name":"Palacios Perez Covadonga",
    "wof:placetype":"venue"
},
  "geometry": {"coordinates":[-2.6680459976,42.8510437012],"type":"Point"}
}