{
  "type": "Feature",
  "properties": {
    "addr:full":"Calle de Agricultura, 15 Salamanca Salamanca 37004",
    "addr:housenumber":"15",
    "addr:postcode":"37004",
    "addr:street":"Calle De Agricultura",
    "iso:country":"ES",
    "sg:address":"Calle de Agricultura, 15",
    "sg:city":"Salamanca",
    "sg:orig_category":"Ingenier\u00cda, Centros De Estudios (diversos)",
    "sg:phone":"+34 923 12 36 67",
    "sg:postcode":"37004",
    "sg:province":"Salamanca",
    "wof:name":"Inges Ceache S.l.",
    "wof:placetype":"venue"
},
  "geometry": {"coordinates":[-5.6531591415,40.9732589722],"type":"Point"}
}