{
  "type": "Feature",
  "properties": {
    "addr:full":"Calle de Zapateria, 81 Vitoria-gasteiz \u00c1lava 01001",
    "addr:housenumber":"81",
    "addr:postcode":"01001",
    "addr:street":"Calle De Zapateria",
    "iso:country":"ES",
    "sg:address":"Calle de Zapateria, 81",
    "sg:city":"Vitoria-gasteiz",
    "sg:orig_category":"Filatelia",
    "sg:phone":"+34 945 23 47 88",
    "sg:postcode":"01001",
    "sg:province":"\u00c1lava",
    "wof:name":"Asociacion Filatelica Y Numismatica Alavesa",
    "wof:placetype":"venue"
},
  "geometry": {"coordinates":[-2.6742506027,42.8492622375],"type":"Point"}
}