{
  "type": "Feature",
  "properties": {
    "addr:full":"Calle de Teniente Coronel Gautier, 33 Ceuta Ceuta 51002",
    "addr:housenumber":"33",
    "addr:postcode":"51002",
    "addr:street":"Calle De Teniente Coronel Gautier",
    "iso:country":"ES",
    "sg:address":"Calle de Teniente Coronel Gautier, 33",
    "sg:city":"Ceuta",
    "sg:orig_category":"Radiocomunicaciones, Telefon\u00cda M\u00d3vil, Radiomensajer\u00cda: Servicios, Comercializaci\u00d3n",
    "sg:phone":"+34 956 52 16 52",
    "sg:postcode":"51002",
    "sg:province":"Ceuta",
    "wof:name":"Kuber Mobil S.l.",
    "wof:placetype":"venue"
},
  "geometry": {"coordinates":[-5.3318591118,35.8850784302],"type":"Point"}
}