{
  "type": "Feature",
  "properties": {
    "addr:full":"Carr Jardi, 95 Vilanova I La Geltru Barcelona 08800",
    "addr:housenumber":"95",
    "addr:postcode":"08800",
    "addr:street":"Carr Jardi",
    "iso:country":"ES",
    "sg:address":"Carr Jardi, 95",
    "sg:city":"Vilanova I La Geltru",
    "sg:orig_category":"Promotores Constructores",
    "sg:phone":"+34 938 16 51 01",
    "sg:postcode":"08800",
    "sg:province":"Barcelona",
    "wof:name":"Via Inmobiliaria 2001 S.l.",
    "wof:placetype":"venue"
},
  "geometry": {"coordinates":[1.7187720537,41.2232437134],"type":"Point"}
}