{
  "type": "Feature",
  "properties": {
    "addr:full":"Carr Sant Crist, 12 Balaguer Lleida 25600",
    "addr:housenumber":"12",
    "addr:postcode":"25600",
    "addr:street":"Carr Sant Crist",
    "iso:country":"ES",
    "sg:address":"Carr Sant Crist, 12",
    "sg:city":"Balaguer",
    "sg:orig_category":"Electricidad: Instaladores",
    "sg:phone":"+34 973 44 60 84",
    "sg:postcode":"25600",
    "sg:province":"Lleida",
    "wof:name":"Vilalta Agusti Miguel",
    "wof:placetype":"venue"
},
  "geometry": {"coordinates":[0.8094570041,41.7929916382],"type":"Point"}
}