{
  "type": "Feature",
  "properties": {
    "iso:country":"ES",
    "sg:address":"Pg Sant Joan Bosco, 51",
    "sg:city":"Barcelona",
    "sg:orig_category":"Restaurantes",
    "sg:phone":"+34 932 05 24 08",
    "sg:postcode":"08017",
    "sg:province":"Barcelona",
    "wof:name":"Soler Fernandez Antonio",
    "wof:placetype":"venue"
},
  "geometry": {"coordinates":[2.1268420219,41.3947601318],"type":"Point"}
}