{
  "type": "Feature",
  "properties": {
    "iso:country":"ES",
    "sg:address":"Can Milans (pol Ind Can Milans), 22",
    "sg:city":"Masrampinyo",
    "sg:orig_category":"Delegados, Agentes De Tr\u00c1nsito, Auxiliares De Transporte Internacional",
    "sg:phone":"+34 935 65 01 98",
    "sg:postcode":"08110",
    "sg:province":"Barcelona",
    "wof:name":"Recaderos De Reus A Barcelona S. A.",
    "wof:placetype":"venue"
},
  "geometry": {"coordinates":[2.1817660332,41.4890899658],"type":"Point"}
}