{
  "type": "Feature",
  "properties": {
    "addr:full":"Carrer de Cardenal Casa\u00d1as, 1 Barcelona Barcelona 08002",
    "addr:housenumber":"1",
    "addr:postcode":"08002",
    "addr:street":"Carrer De Cardenal Casan\u0303As",
    "iso:country":"ES",
    "sg:address":"Carrer de Cardenal Casa\u00d1as, 1",
    "sg:city":"Barcelona",
    "sg:orig_category":"Administradores De Bienes Y Delegados De Comunidades De Propietarios",
    "sg:phone":"+34 933 01 33 86",
    "sg:postcode":"08002",
    "sg:province":"Barcelona",
    "wof:name":"Grup Assessor Finques Aparici S.cv.",
    "wof:placetype":"venue"
},
  "geometry": {"coordinates":[2.1734333038,41.3813705444],"type":"Point"}
}