{
  "type": "Feature",
  "properties": {
    "iso:country":"ES",
    "sg:address":"Avda Artesanos (de Los), 63",
    "sg:city":"Tres Cantos",
    "sg:orig_category":"Agencias Y Asesores De Publicidad",
    "sg:phone":"+34 918 04 27 57",
    "sg:postcode":"28760",
    "sg:province":"Madrid",
    "wof:name":"Departamento Creativo Sl",
    "wof:placetype":"venue"
},
  "geometry": {"coordinates":[-3.6980240345,40.5949363708],"type":"Point"}
}