{
  "type": "Feature",
  "properties": {
    "iso:country":"ES",
    "sg:address":"Calle de Virgen, 29",
    "sg:city":"Tarazona Mancha",
    "sg:orig_category":"Molduras, Junquillos, Listones Y Molduras Perforadas",
    "sg:phone":"+34 967 48 09 06",
    "sg:postcode":"02100",
    "sg:province":"Albacete",
    "wof:name":"Cordona Villena Alonso",
    "wof:placetype":"venue"
},
  "geometry": {"coordinates":[-1.9113910198,39.2630271912],"type":"Point"}
}