{
  "type": "Feature",
  "properties": {
    "iso:country":"ES",
    "sg:address":"Plaz Constitucion, 1",
    "sg:city":"Teulada",
    "sg:orig_category":"Institutos De Belleza",
    "sg:phone":"+34 965 74 02 96",
    "sg:postcode":"03725",
    "sg:province":"Alicante",
    "wof:name":"Ana Centro De Estetica S.l.",
    "wof:placetype":"venue"
},
  "geometry": {"coordinates":[0.1045835018,38.7288284302],"type":"Point"}
}