{
  "type": "Feature",
  "properties": {
    "addr:full":"Carrer de Mallorca, 410 Barcelona Barcelona 08013",
    "addr:housenumber":"410",
    "addr:postcode":"08013",
    "addr:street":"Carrer De Mallorca",
    "iso:country":"ES",
    "sg:address":"Carrer de Mallorca, 410",
    "sg:city":"Barcelona",
    "sg:orig_category":"Art\u00cdculos De Regalo (al Por Menor)",
    "sg:phone":"+34 932 31 27 65",
    "sg:postcode":"08013",
    "sg:province":"Barcelona",
    "wof:name":"Morwani Morwani Sanjiv",
    "wof:placetype":"venue"
},
  "geometry": {"coordinates":[2.1750199795,41.4030418396],"type":"Point"}
}