{
  "type": "Feature",
  "properties": {
    "addr:full":"Comercio(pol. Mijares), S/n Almassora Castell\u00f3n 12550",
    "addr:housenumber":"s / n",
    "addr:postcode":"12550",
    "addr:street":"Comercio Pol. Mijares;Almassora Castello\u0301N",
    "iso:country":"ES",
    "sg:address":"Comercio(pol. Mijares), S/n",
    "sg:city":"Almassora",
    "sg:orig_category":"Maquinaria Para Industrias Diversas",
    "sg:phone":"+34 964 50 31 46",
    "sg:postcode":"12550",
    "sg:province":"Castell\u00f3n",
    "wof:name":"Valser S.a.",
    "wof:placetype":"venue"
},
  "geometry": {"coordinates":[-0.0713789985,39.9571533203],"type":"Point"}
}