{
  "type": "Feature",
  "properties": {
    "addr:full":"Calle de Camino De Liria, 39 Sagunt Valencia 46500",
    "addr:housenumber":"39",
    "addr:postcode":"46500",
    "addr:street":"Calle De Camino De Liria",
    "iso:country":"ES",
    "sg:address":"Calle de Camino De Liria, 39",
    "sg:city":"Sagunt",
    "sg:orig_category":"Ense\u00d1anza, Formaci\u00d3n Profesional: Aprendizaje",
    "sg:phone":"+34 962 66 63 76",
    "sg:postcode":"46500",
    "sg:province":"Valencia",
    "wof:name":"Ayuntamiento De Sagunto-cementerio",
    "wof:placetype":"venue"
},
  "geometry": {"coordinates":[-0.2783089876,39.6799659729],"type":"Point"}
}