{
  "type": "Feature",
  "properties": {
    "addr:full":"Ctra. Segovia, 25 Portillo Valladolid 47160",
    "addr:housenumber":"25",
    "addr:postcode":"47160",
    "addr:street":"Ctra. Segovia",
    "iso:country":"ES",
    "sg:address":"Ctra. Segovia, 25",
    "sg:city":"Portillo",
    "sg:orig_category":"Peluqueros: De Se\u00d1oras",
    "sg:phone":"+34 983 55 62 14",
    "sg:postcode":"47160",
    "sg:province":"Valladolid",
    "wof:name":"Matesanz Frutos Maria Del Mar",
    "wof:placetype":"venue"
},
  "geometry": {"coordinates":[-4.5932068825,41.4750213623],"type":"Point"}
}