{
  "type": "Feature",
  "properties": {
    "addr:full":"Calle de Pintor Velazquez (del), 65 Mostoles Madrid 28935",
    "addr:housenumber":"65",
    "addr:postcode":"28935",
    "addr:street":"Calle De Pintor Velazquez Del",
    "iso:country":"ES",
    "sg:address":"Calle de Pintor Velazquez (del), 65",
    "sg:city":"Mostoles",
    "sg:orig_category":"Cajas De Ahorro",
    "sg:phone":"+34 916 13 85 61",
    "sg:postcode":"28935",
    "sg:province":"Madrid",
    "wof:name":"Caixa D'estalvis I Pensions De Barcelona",
    "wof:placetype":"venue"
},
  "geometry": {"coordinates":[-3.8808178902,40.3212623596],"type":"Point"}
}