{
  "type": "Feature",
  "properties": {
    "iso:country":"ES",
    "sg:address":"Calle de Don Sabino, 20",
    "sg:city":"Mota Cuervo",
    "sg:orig_category":"Electricidad: Instaladores",
    "sg:phone":"+34 967 18 03 44",
    "sg:postcode":"16630",
    "sg:province":"Cuenca",
    "wof:name":"Miguel Bascu\u00f1an Laguia S.l.",
    "wof:placetype":"venue"
},
  "geometry": {"coordinates":[-2.8721911907,39.5006065369],"type":"Point"}
}