{
  "type": "Feature",
  "properties": {
    "iso:country":"ES",
    "sg:address":"Calle de Bravo Murillo, 240",
    "sg:city":"Madrid",
    "sg:orig_category":"Institutos De Belleza",
    "sg:phone":"+34 915 71 66 23",
    "sg:postcode":"28020",
    "sg:province":"Madrid",
    "sg:website":"www.salondebellezacarmin.com",
    "wof:name":"Ivalgim S.l.",
    "wof:placetype":"venue"
},
  "geometry": {"coordinates":[-3.6997778416,40.459236145],"type":"Point"}
}