{
  "type": "Feature",
  "properties": {
    "iso:country":"ES",
    "sg:address":"Avda Carlos Iii, 324",
    "sg:city":"Aguadulce",
    "sg:orig_category":"Confecci\u00d3n De Trajes Para Se\u00d1oras",
    "sg:phone":"+34 950 34 97 23",
    "sg:postcode":"04720",
    "sg:province":"Almer\u00eda",
    "wof:name":"A Los Cuarenta Y Nueve S.l",
    "wof:placetype":"venue"
},
  "geometry": {"coordinates":[-2.5757730007,36.8133239746],"type":"Point"}
}