{
  "type": "Feature",
  "properties": {
    "iso:country":"ES",
    "sg:address":"Calle de Pintor Aurelio Vera-fajardo, 22",
    "sg:city":"Vitoria-gasteiz",
    "sg:orig_category":"Fabricaci\u00d3n De Enlosados, Soler\u00cdas",
    "sg:phone":"+34 945 22 31 51",
    "sg:postcode":"01008",
    "sg:province":"\u00c1lava",
    "sg:website":"www.construnet.net/empresa/berres",
    "wof:name":"Construcciones Berres, S.l.",
    "wof:placetype":"venue"
},
  "geometry": {"coordinates":[-2.6839640141,42.8501167297],"type":"Point"}
}