{
  "type": "Feature",
  "properties": {
    "addr:full":"Calle de Mayor, 9 Torres Cotillas Murcia 30565",
    "addr:housenumber":"9",
    "addr:postcode":"30565",
    "addr:street":"Calle De Mayor",
    "iso:country":"ES",
    "sg:address":"Calle de Mayor, 9",
    "sg:city":"Torres Cotillas",
    "sg:orig_category":"Bancos",
    "sg:phone":"+34 968 62 70 11",
    "sg:postcode":"30565",
    "sg:province":"Murcia",
    "wof:name":"Banco De Valencia S.a.",
    "wof:placetype":"venue"
},
  "geometry": {"coordinates":[-1.2410279512,38.0295562744],"type":"Point"}
}