{
  "type": "Feature",
  "properties": {
    "iso:country":"ES",
    "sg:address":"Calle de D (poligono Industrial), S/n",
    "sg:city":"Villarrobledo",
    "sg:orig_category":"Autob\u00das (explotaci\u00d3n Y Servicios De)",
    "sg:phone":"+34 967 14 39 49",
    "sg:postcode":"02600",
    "sg:province":"Albacete",
    "wof:name":"Roblebus S.l.",
    "wof:placetype":"venue"
},
  "geometry": {"coordinates":[-2.5873806477,39.275970459],"type":"Point"}
}