{
  "type": "Feature",
  "properties": {
    "iso:country":"ES",
    "sg:address":"Avda Eysines De, 2",
    "sg:city":"Piedras Blancas",
    "sg:orig_category":"Ropa Para Caballeros (al Por Menor)",
    "sg:phone":"+34 985 53 18 35",
    "sg:postcode":"33450",
    "sg:province":"Asturias",
    "wof:name":"Arnaldo Garcia Jesus",
    "wof:placetype":"venue"
},
  "geometry": {"coordinates":[-5.9748296738,43.5595436096],"type":"Point"}
}