{
  "type": "Feature",
  "properties": {
    "addr:full":"Calle de Leon Y Castillo, 106 Blanca Las Palmas 35110",
    "addr:housenumber":"106",
    "addr:postcode":"35110",
    "addr:street":"Calle De Leon Y Castillo;Blanca",
    "iso:country":"ES",
    "sg:address":"Calle de Leon Y Castillo, 106",
    "sg:city":"Blanca",
    "sg:orig_category":"Empresas De Carpinter\u00cda Met\u00c1lica",
    "sg:phone":"+34 928 75 85 61",
    "sg:postcode":"35110",
    "sg:province":"Las Palmas",
    "wof:name":"Sanchez Perez Ceferino",
    "wof:placetype":"venue"
},
  "geometry": {"coordinates":[-15.4485340118,27.8392906189],"type":"Point"}
}