{
  "type": "Feature",
  "properties": {
    "iso:country":"ES",
    "sg:address":"Cmno Hornera (la), 56",
    "sg:city":"Gracia",
    "sg:orig_category":"Quincaller\u00cda (al Por Menor)",
    "sg:phone":"+34 922 25 27 14",
    "sg:postcode":"38295",
    "sg:province":"Santa Cruz De Tenerife",
    "wof:name":"Amador Suarez Juan Manuel",
    "wof:placetype":"venue"
},
  "geometry": {"coordinates":[-16.2548561096,28.4698104858],"type":"Point"}
}