{
  "type": "Feature",
  "properties": {
    "iso:country":"ES",
    "sg:address":"Carrer de Ciutat De Balaguer, 27",
    "sg:city":"Barcelona",
    "sg:orig_category":"Mec\u00c1nico Del Autom\u00d3vil",
    "sg:phone":"+34 934 17 10 10",
    "sg:postcode":"08022",
    "sg:province":"Barcelona",
    "wof:name":"Iba\u00f1ez Tarrason Joaquin",
    "wof:placetype":"venue"
},
  "geometry": {"coordinates":[2.1353499889,41.4031448364],"type":"Point"}
}