{
  "type": "Feature",
  "properties": {
    "addr:full":"Francisco De Ayala, 6 Padul Granada 18640",
    "addr:housenumber":"6",
    "addr:postcode":"18640",
    "addr:street":"Francisco De Ayala",
    "iso:country":"ES",
    "sg:address":"Francisco De Ayala, 6",
    "sg:city":"Padul",
    "sg:orig_category":"Electromec\u00c1nica",
    "sg:phone":"+34 958 79 02 92",
    "sg:postcode":"18640",
    "sg:province":"Granada",
    "wof:name":"Alcala Fernandez Jose",
    "wof:placetype":"venue"
},
  "geometry": {"coordinates":[-3.634619236,37.0259552002],"type":"Point"}
}