{
  "type": "Feature",
  "properties": {
    "iso:country":"ES",
    "sg:address":"Calle de Sevilla, 40",
    "sg:city":"Ronda",
    "sg:orig_category":"Abogados",
    "sg:phone":"+34 952 87 88 57",
    "sg:postcode":"29400",
    "sg:province":"M\u00e1laga",
    "wof:name":"Becerra Serrato Antonio",
    "wof:placetype":"venue"
},
  "geometry": {"coordinates":[-5.1655430794,36.7446060181],"type":"Point"}
}