{
  "type": "Feature",
  "properties": {
    "iso:country":"ES",
    "sg:address":"Calle de Alosno, 11",
    "sg:city":"Huelva",
    "sg:orig_category":"Fabricaci\u00d3n De Distribuidores Autom\u00c1ticos",
    "sg:phone":"+34 959 22 52 94",
    "sg:postcode":"21006",
    "sg:province":"Huelva",
    "wof:name":"Modesto Navarro S.l.",
    "wof:placetype":"venue"
},
  "geometry": {"coordinates":[-6.9342541695,37.2605247498],"type":"Point"}
}