{
  "type": "Feature",
  "properties": {
    "iso:country":"ES",
    "sg:address":"Calle de Juan De La Cierva, 18",
    "sg:city":"San Jose Rinconada",
    "sg:orig_category":"Empresarios Y Productoras De Espect\u00c1culos",
    "sg:phone":"+34 954 79 33 21",
    "sg:postcode":"41300",
    "sg:province":"Sevilla",
    "wof:name":"Andaluza De Escenografia S.l.u.",
    "wof:placetype":"venue"
},
  "geometry": {"coordinates":[-5.9335622787,37.4900550842],"type":"Point"}
}