{
  "type": "Feature",
  "properties": {
    "addr:full":"Carrer de Ignasi Iglesias, 28 Reus Tarragona 43206",
    "addr:housenumber":"28",
    "addr:postcode":"43206",
    "addr:street":"Carrer De Ignasi Iglesias",
    "iso:country":"ES",
    "sg:address":"Carrer de Ignasi Iglesias, 28",
    "sg:city":"Reus",
    "sg:orig_category":"Eletrotecnica",
    "sg:phone":"+34 977 33 01 07",
    "sg:postcode":"43206",
    "sg:province":"Tarragona",
    "wof:name":"El Montaje Emasa S.l.",
    "wof:placetype":"venue"
},
  "geometry": {"coordinates":[1.1039400101,41.1745300293],"type":"Point"}
}