{
  "type": "Feature",
  "properties": {
    "addr:full":"Carrer de Benet Mateu, 49 Barcelona Barcelona 08034",
    "addr:housenumber":"49",
    "addr:postcode":"08034",
    "addr:street":"Carrer De Benet Mateu",
    "iso:country":"ES",
    "sg:address":"Carrer de Benet Mateu, 49",
    "sg:city":"Barcelona",
    "sg:orig_category":"Ropa Para Se\u00d1oras (al Por Menor)",
    "sg:phone":"+34 932 05 29 39",
    "sg:postcode":"08034",
    "sg:province":"Barcelona",
    "wof:name":"Crandon Mistral S.l.",
    "wof:placetype":"venue"
},
  "geometry": {"coordinates":[2.1260309219,41.3937606812],"type":"Point"}
}