{
  "type": "Feature",
  "properties": {
    "addr:full":"Carrer de Comte D'urgell, 113 Barcelona Barcelona 08011",
    "addr:housenumber":"113",
    "addr:postcode":"08011",
    "addr:street":"Carrer De Comte D'Urgell",
    "iso:country":"ES",
    "sg:address":"Carrer de Comte D'urgell, 113",
    "sg:city":"Barcelona",
    "sg:orig_category":"Caf\u00c9s, Bares, Cervecer\u00cdas",
    "sg:phone":"+34 934 51 34 35",
    "sg:postcode":"08011",
    "sg:province":"Barcelona",
    "sg:website":"www.bracafe.com",
    "wof:name":"Jove Cuchi Juan Sebastian",
    "wof:placetype":"venue"
},
  "geometry": {"coordinates":[2.1550121307,41.3848152161],"type":"Point"}
}