{
  "type": "Feature",
  "properties": {
    "addr:full":"Avda Filipinas, 63 Algar Murcia 30366",
    "addr:housenumber":"63",
    "addr:postcode":"30366",
    "addr:street":"Avda Filipinas",
    "iso:country":"ES",
    "sg:address":"Avda Filipinas, 63",
    "sg:city":"Algar",
    "sg:orig_category":"Cajas Para Embalar",
    "sg:phone":"+34 968 13 64 40",
    "sg:postcode":"30366",
    "sg:province":"Murcia",
    "sg:website":"www.cajamar.es",
    "wof:name":"Cajamar",
    "wof:placetype":"venue"
},
  "geometry": {"coordinates":[-0.8679890037,37.6475105286],"type":"Point"}
}