{
  "type": "Feature",
  "properties": {
    "addr:full":"Carrer de Jaume Roig, S/n Callosa D'en Sarria Alicante 03510",
    "addr:housenumber":"s / n",
    "addr:postcode":"03510",
    "addr:street":"Carrer De Jaume Roig",
    "iso:country":"ES",
    "sg:address":"Carrer de Jaume Roig, S/n",
    "sg:city":"Callosa D'en Sarria",
    "sg:orig_category":"Bisuter\u00cda, Joyer\u00cda, Relojer\u00cda (al Por Menor)",
    "sg:phone":"+34 965 88 17 43",
    "sg:postcode":"03510",
    "sg:province":"Alicante",
    "wof:name":"Climent Saval Juan Jose",
    "wof:placetype":"venue"
},
  "geometry": {"coordinates":[-0.1206507981,38.6514663696],"type":"Point"}
}