{
  "type": "Feature",
  "properties": {
    "addr:full":"Av Prat De La Riba, 16 Tarragona Tarragona 43001",
    "addr:housenumber":"16",
    "addr:postcode":"43001",
    "addr:street":"Av Prat De La Riba",
    "iso:country":"ES",
    "sg:address":"Av Prat De La Riba, 16",
    "sg:city":"Tarragona",
    "sg:orig_category":"Art\u00cdculos De Regalo (al Por Menor)",
    "sg:phone":"+34 977 23 02 54",
    "sg:postcode":"43001",
    "sg:province":"Tarragona",
    "wof:name":"Plat Preu S.l.",
    "wof:placetype":"venue"
},
  "geometry": {"coordinates":[1.2466210127,41.1159515381],"type":"Point"}
}