{
  "type": "Feature",
  "properties": {
    "iso:country":"ES",
    "sg:address":"Calle de Nuestra Se\u00d1ora Del Duero, 1",
    "sg:city":"Almazan",
    "sg:orig_category":"Art\u00cdculos De Madera (fabricaci\u00d3n Y Al Por Mayor)",
    "sg:phone":"+34 975 31 02 16",
    "sg:postcode":"42200",
    "sg:province":"Soria",
    "wof:name":"Rios Horno Joaquin De Los",
    "wof:placetype":"venue"
},
  "geometry": {"coordinates":[-2.5251090527,41.4922523499],"type":"Point"}
}