{
  "type": "Feature",
  "properties": {
    "iso:country":"ES",
    "sg:address":"Rua Berdillo, 1",
    "sg:city":"Carballo",
    "sg:orig_category":"Muebles, Minoristas",
    "sg:phone":"+34 981 70 13 61",
    "sg:postcode":"15100",
    "sg:province":"La Coru\u00f1a",
    "wof:name":"Collazo Taibo Carmen",
    "wof:placetype":"venue"
},
  "geometry": {"coordinates":[-8.6913089752,43.2121582031],"type":"Point"}
}