{
  "type": "Feature",
  "properties": {
    "iso:country":"ES",
    "sg:address":"Calle de General Mu\u00d1oz Arenillas, 4",
    "sg:city":"Cadiz",
    "sg:orig_category":"Caf\u00c9s, Bares, Cervecer\u00cdas",
    "sg:phone":"+34 956 25 00 53",
    "sg:postcode":"11010",
    "sg:province":"C\u00e1diz",
    "wof:name":"Macias Toledo Miguel",
    "wof:placetype":"venue"
},
  "geometry": {"coordinates":[-6.2779750824,36.5069732666],"type":"Point"}
}