{
  "type": "Feature",
  "properties": {
    "addr:full":"Calle de Serrate Felipe, 1 Bilbao Vizcaya 48013",
    "addr:housenumber":"1",
    "addr:postcode":"48013",
    "addr:street":"Calle De Serrate Felipe",
    "iso:country":"ES",
    "sg:address":"Calle de Serrate Felipe, 1",
    "sg:city":"Bilbao",
    "sg:orig_category":"Arquitectos",
    "sg:phone":"+34 944 42 42 69",
    "sg:postcode":"48013",
    "sg:province":"Vizcaya",
    "wof:name":"Javier San Sebastian Y Sergio De La Riva S.c.",
    "wof:placetype":"venue"
},
  "geometry": {"coordinates":[-2.9462809563,43.2637710571],"type":"Point"}
}