{
  "type": "Feature",
  "properties": {
    "iso:country":"ES",
    "sg:address":"Ctra (gi-2) Gijon-alto Infanzon Por La Providencia, 1146",
    "sg:city":"Gijon",
    "sg:orig_category":"Asesor\u00cda Fiscal Y Jur\u00cddica",
    "sg:phone":"+34 985 13 02 85",
    "sg:postcode":"33203",
    "sg:province":"Asturias",
    "wof:name":"Infoley S.l.",
    "wof:placetype":"venue"
},
  "geometry": {"coordinates":[-5.5962839127,43.5261116028],"type":"Point"}
}