{
  "type": "Feature",
  "properties": {
    "iso:country":"ES",
    "sg:address":"Carr Castellet, 5",
    "sg:city":"Cala Ratjada",
    "sg:orig_category":"Agencias De Viajes",
    "sg:phone":"+34 971 56 33 02",
    "sg:postcode":"07590",
    "sg:province":"Islas Baleares",
    "wof:name":"Iberoservice S.a.",
    "wof:placetype":"venue"
},
  "geometry": {"coordinates":[3.460848093,39.7106285095],"type":"Point"}
}