{
  "type": "Feature",
  "properties": {
    "addr:full":"Calle de Francisco Vitoria, 17 Zaragoza Zaragoza 50008",
    "addr:housenumber":"17",
    "addr:postcode":"50008",
    "addr:street":"Calle De Francisco Vitoria",
    "iso:country":"ES",
    "sg:address":"Calle de Francisco Vitoria, 17",
    "sg:city":"Zaragoza",
    "sg:orig_category":"Abogados",
    "sg:phone":"+34 976 21 53 88",
    "sg:postcode":"50008",
    "sg:province":"Zaragoza",
    "wof:name":"Prosa Sa",
    "wof:placetype":"venue"
},
  "geometry": {"coordinates":[-0.8802329898,41.6463279724],"type":"Point"}
}