{
  "type": "Feature",
  "properties": {
    "iso:country":"ES",
    "sg:address":"Avda Pais Valencia, 145",
    "sg:city":"Torrent",
    "sg:orig_category":"Servicios Gsm",
    "sg:phone":"+34 961 56 31 36",
    "sg:postcode":"46900",
    "sg:province":"Valencia",
    "wof:name":"Telecomunicaciones Soriano S.l.",
    "wof:placetype":"venue"
},
  "geometry": {"coordinates":[-0.4772900045,39.4293403625],"type":"Point"}
}