{
  "type": "Feature",
  "properties": {
    "iso:country":"ES",
    "sg:address":"Calle de Mariana Pineda, 16",
    "sg:city":"Zaragoza",
    "sg:orig_category":"Panader\u00cdas, Panader\u00cdas",
    "sg:phone":"+34 976 52 32 63",
    "sg:postcode":"50015",
    "sg:province":"Zaragoza",
    "wof:name":"Panificadora Castellana S.a.",
    "wof:placetype":"venue"
},
  "geometry": {"coordinates":[-0.888892591,41.6652832031],"type":"Point"}
}