{
  "type": "Feature",
  "properties": {
    "iso:country":"ES",
    "sg:address":"G.v. Lopez De Haro D. Diego, 51",
    "sg:city":"Bilbao",
    "sg:orig_category":"Ropa Para Se\u00d1oras (al Por Menor)",
    "sg:phone":"+34 944 39 70 81",
    "sg:postcode":"48011",
    "sg:province":"Vizcaya",
    "wof:name":"Hafril 91 S.l.",
    "wof:placetype":"venue"
},
  "geometry": {"coordinates":[-2.9383020401,43.2635879517],"type":"Point"}
}