{
  "type": "Feature",
  "properties": {
    "iso:country":"ES",
    "sg:address":"Calle de Delfin, 1",
    "sg:city":"Calpe",
    "sg:orig_category":"Inmobiliaria (agencias)",
    "sg:phone":"+34 965 83 33 87",
    "sg:postcode":"03710",
    "sg:province":"Alicante",
    "wof:name":"Calatayud Pizza Vicente",
    "wof:placetype":"venue"
},
  "geometry": {"coordinates":[0.0486271009,38.6427688599],"type":"Point"}
}