{
  "type": "Feature",
  "properties": {
    "addr:full":"Jose Luis I\u00d1arra Pasealekua, S/n Arrasate Guip\u00f9zcoa 20500",
    "addr:housenumber":"s / n",
    "addr:postcode":"20500",
    "addr:street":"Jose;In\u0303Arra Pasealekua;Guipu\u0300Zcoa",
    "iso:country":"ES",
    "sg:address":"Jose Luis I\u00d1arra Pasealekua, S/n",
    "sg:city":"Arrasate",
    "sg:orig_category":"Asociaciones, Organismos Culturales Y Socioeducativos",
    "sg:phone":"+34 943 79 06 38",
    "sg:postcode":"20500",
    "sg:province":"Guip\u00f9zcoa",
    "wof:name":"Sociedad Cultural Y Recreativa Herri-gain",
    "wof:placetype":"venue"
},
  "geometry": {"coordinates":[-2.4865810871,43.0680236816],"type":"Point"}
}