{
  "type": "Feature",
  "properties": {
    "addr:full":"Ctra. Ventas, S/n Cuerva Toledo 45126",
    "addr:housenumber":"s / n",
    "addr:postcode":"45126",
    "addr:street":"Ctra. Ventas",
    "iso:country":"ES",
    "sg:address":"Ctra. Ventas, S/n",
    "sg:city":"Cuerva",
    "sg:orig_category":"Cristaler\u00cdas",
    "sg:phone":"+34 925 42 43 93",
    "sg:postcode":"45126",
    "sg:province":"Toledo",
    "wof:name":"Alonso Sandoval Cipriano",
    "wof:placetype":"venue"
},
  "geometry": {"coordinates":[-4.2705383301,39.6342887878],"type":"Point"}
}