{
  "type": "Feature",
  "properties": {
    "iso:country":"ES",
    "sg:address":"Plaz Arenal, 2",
    "sg:city":"Dos Hermanas",
    "sg:orig_category":"Librer\u00cdas",
    "sg:phone":"+34 954 72 10 26",
    "sg:postcode":"41700",
    "sg:province":"Sevilla",
    "wof:name":"Espinosa Cardoso Antonio",
    "wof:placetype":"venue"
},
  "geometry": {"coordinates":[-5.9281339645,37.2829055786],"type":"Point"}
}