{
  "type": "Feature",
  "properties": {
    "iso:country":"ES",
    "sg:address":"Aeropuerto Tenerife Sur, S/n",
    "sg:city":"San Isidro",
    "sg:orig_category":"Aeropuertos Y Servicios Aeroportuarios",
    "sg:phone":"+34 922 39 31 04",
    "sg:postcode":"38611",
    "sg:province":"Santa Cruz De Tenerife",
    "wof:name":"Gb Airways Limited",
    "wof:placetype":"venue"
},
  "geometry": {"coordinates":[-16.5577411652,28.0779342651],"type":"Point"}
}