{
  "type": "Feature",
  "properties": {
    "addr:full":"Alam Areilza Doctor, 11 Bilbao Vizcaya 48011",
    "addr:housenumber":"11",
    "addr:postcode":"48011",
    "addr:street":"Alam;Doctor",
    "iso:country":"ES",
    "sg:address":"Alam Areilza Doctor, 11",
    "sg:city":"Bilbao",
    "sg:orig_category":"Fisioterapia",
    "sg:phone":"+34 944 41 05 10",
    "sg:postcode":"48011",
    "sg:province":"Vizcaya",
    "wof:name":"I\u00d1igo Gomez Castander-iker Gomez Castander S.c.p.",
    "wof:placetype":"venue"
},
  "geometry": {"coordinates":[-2.9416720867,43.2626113892],"type":"Point"}
}