{
  "type": "Feature",
  "properties": {
    "iso:country":"ES",
    "sg:address":"Avda Cantue\u00d1a (de La), 2",
    "sg:city":"Fuenlabrada",
    "sg:orig_category":"Ropa Y Accesorios",
    "sg:phone":"+34 916 42 20 18",
    "sg:postcode":"28947",
    "sg:province":"Madrid",
    "wof:name":"Roman Pelaez Javier",
    "wof:placetype":"venue"
},
  "geometry": {"coordinates":[-3.7629389763,40.2729682922],"type":"Point"}
}