{
  "type": "Feature",
  "properties": {
    "addr:full":"Calle de Martinez De La Riva, 72 Madrid Madrid 28053",
    "addr:housenumber":"72",
    "addr:postcode":"madrid;28053",
    "addr:street":"Calle De Martinez De La Riva",
    "iso:country":"ES",
    "sg:address":"Calle de Martinez De La Riva, 72",
    "sg:city":"Madrid",
    "sg:orig_category":"Muebles, Minoristas",
    "sg:phone":"+34 914 77 95 74",
    "sg:postcode":"28053",
    "sg:province":"Madrid",
    "sg:website":"www.granmuebleria.com",
    "wof:name":"Gran Muebleria S.l.",
    "wof:placetype":"venue"
},
  "geometry": {"coordinates":[-3.6651699543,40.3900337219],"type":"Point"}
}