{
  "type": "Feature",
  "properties": {
    "addr:full":"Calle de Nieremberg, 31 Madrid Madrid 28002",
    "addr:housenumber":"31",
    "addr:postcode":"madrid;28002",
    "addr:street":"Calle De Nieremberg",
    "iso:country":"ES",
    "sg:address":"Calle de Nieremberg, 31",
    "sg:city":"Madrid",
    "sg:orig_category":"Energ\u00cda Solar Y Nuevas Energ\u00cdas (equipo, Estudios)",
    "sg:phone":"+34 915 10 25 87",
    "sg:postcode":"28002",
    "sg:province":"Madrid",
    "wof:name":"Energysa S.l.",
    "wof:placetype":"venue"
},
  "geometry": {"coordinates":[-3.6730051041,40.4484519958],"type":"Point"}
}