{
  "type": "Feature",
  "properties": {
    "iso:country":"ES",
    "sg:address":"Avda Extremadura, 14",
    "sg:city":"Plasencia",
    "sg:orig_category":"Arreglo, Reparaci\u00d3n, Piezas Sueltas De Televisi\u00d3n, V\u00cddeo, Hi",
    "sg:phone":"+34 927 42 53 92",
    "sg:postcode":"10600",
    "sg:province":"C\u00e1ceres",
    "wof:name":"Teleservicio C.b.",
    "wof:placetype":"venue"
},
  "geometry": {"coordinates":[-6.0905828476,40.0387306213],"type":"Point"}
}