{
  "type": "Feature",
  "properties": {
    "addr:full":"Pje Leon, S/n Xativa Valencia 46800",
    "addr:postcode":"46800",
    "addr:street":"Pje Leon S / N",
    "iso:country":"ES",
    "sg:address":"Pje Leon, S/n",
    "sg:city":"Xativa",
    "sg:orig_category":"Ropa Para Se\u00d1oras Y Caballeros (al Por Menor)",
    "sg:phone":"+34 962 28 11 84",
    "sg:postcode":"46800",
    "sg:province":"Valencia",
    "wof:name":"Quiquet 2003, S.l.",
    "wof:placetype":"venue"
},
  "geometry": {"coordinates":[-0.5200830102,38.9934272766],"type":"Point"}
}