{
  "type": "Feature",
  "properties": {
    "addr:full":"P. I. Ciudad Blanca, 16 Dos Hermanas Sevilla 41700",
    "addr:housenumber":"16",
    "addr:postcode":"41700",
    "addr:street":"P. I. Ciudad Blanca",
    "iso:country":"ES",
    "sg:address":"P. I. Ciudad Blanca, 16",
    "sg:city":"Dos Hermanas",
    "sg:orig_category":"Chapister\u00cda",
    "sg:phone":"+34 955 66 37 14",
    "sg:postcode":"41700",
    "sg:province":"Sevilla",
    "wof:name":"Tecniauto Dos Hermanas S.l.",
    "wof:placetype":"venue"
},
  "geometry": {"coordinates":[-5.9281339645,37.2829055786],"type":"Point"}
}