{
  "type": "Feature",
  "properties": {
    "addr:full":"Plaz Capitan Boixareu Rivera, 21 Guadalajara Guadalajara 19001",
    "addr:housenumber":"21",
    "addr:postcode":"19001",
    "addr:street":"Plaz Capitan Boixareu Rivera",
    "iso:country":"ES",
    "sg:address":"Plaz Capitan Boixareu Rivera, 21",
    "sg:city":"Guadalajara",
    "sg:orig_category":"Asociaciones, Organismos Culturales Y Socioeducativos",
    "sg:phone":"+34 949 25 53 87",
    "sg:postcode":"19001",
    "sg:province":"Guadalajara",
    "wof:name":"Asociacion Cultural Anchara",
    "wof:placetype":"venue"
},
  "geometry": {"coordinates":[-3.162872076,40.6311454773],"type":"Point"}
}