{
  "type": "Feature",
  "properties": {
    "addr:full":"Cra. De Gironella, Km. 0000,8 Casserres Barcelona 08693",
    "addr:postcode":"08693",
    "addr:street":"Km. 0000,8",
    "iso:country":"ES",
    "sg:address":"Cra. De Gironella, Km. 0000,8",
    "sg:city":"Casserres",
    "sg:orig_category":"Mataderos Y Talleres De Despiezado",
    "sg:phone":"+34 938 23 40 33",
    "sg:postcode":"08693",
    "sg:province":"Barcelona",
    "wof:name":"Industria Avicola Del Bergueda S.l.",
    "wof:placetype":"venue"
},
  "geometry": {"coordinates":[1.8405050039,42.0134468079],"type":"Point"}
}