{
  "type": "Feature",
  "properties": {
    "addr:full":"Carrer de Sepulveda, 44 Barcelona Barcelona 08015",
    "addr:housenumber":"44",
    "addr:postcode":"08015",
    "addr:street":"Carrer De Sepulveda",
    "iso:country":"ES",
    "sg:address":"Carrer de Sepulveda, 44",
    "sg:city":"Barcelona",
    "sg:orig_category":"Quincaller\u00cda (al Por Menor)",
    "sg:phone":"+34 933 25 68 44",
    "sg:postcode":"08015",
    "sg:province":"Barcelona",
    "wof:name":"Segura Tejedor Miguel Angel",
    "wof:placetype":"venue"
},
  "geometry": {"coordinates":[2.1545479298,41.3770332336],"type":"Point"}
}