{
  "type": "Feature",
  "properties": {
    "iso:country":"ES",
    "sg:address":"Botos, 26",
    "sg:city":"Botos",
    "sg:orig_category":"Empresas De Hormig\u00d3n, Hormig\u00d3n Armado Y Pretensado",
    "sg:phone":"+34 986 78 05 24",
    "sg:postcode":"36519",
    "sg:province":"Pontevedra",
    "wof:name":"Garcia Lopez Manuel",
    "wof:placetype":"venue"
},
  "geometry": {"coordinates":[-8.1627492905,42.5798492432],"type":"Point"}
}