{
  "type": "Feature",
  "properties": {
    "iso:country":"ES",
    "sg:address":"G.v. Corts Catalanes, 608",
    "sg:city":"Barcelona",
    "sg:orig_category":"Asesor\u00cda Fiscal Y Jur\u00cddica",
    "sg:phone":"+34 933 01 08 41",
    "sg:postcode":"08007",
    "sg:province":"Barcelona",
    "wof:name":"Roman Barrero Francisco",
    "wof:placetype":"venue"
},
  "geometry": {"coordinates":[2.1659860611,41.3872871399],"type":"Point"}
}