{
  "type": "Feature",
  "properties": {
    "iso:country":"ES",
    "sg:address":"Carr Carme, 48",
    "sg:city":"Badalona",
    "sg:orig_category":"M\u00c1quinas De Escribir, M\u00c1quinas De Oficina (al Por Menor, Reparaci\u00d3n)",
    "sg:phone":"+34 933 84 32 53",
    "sg:postcode":"08911",
    "sg:province":"Barcelona",
    "wof:name":"Arias Gomez Jose",
    "wof:placetype":"venue"
},
  "geometry": {"coordinates":[2.2501249313,41.4504241943],"type":"Point"}
}