{
  "type": "Feature",
  "properties": {
    "iso:country":"ES",
    "sg:address":"Autopista A 17, Km. 0023,3",
    "sg:city":"Llinars Valles",
    "sg:orig_category":"Distribuci\u00d3n De Petr\u00d3leo Y Derivados",
    "sg:phone":"+34 938 41 25 07",
    "sg:postcode":"08450",
    "sg:province":"Barcelona",
    "wof:name":"Agip Espa\u00f1a S.a.",
    "wof:placetype":"venue"
},
  "geometry": {"coordinates":[2.171762228,41.5363464355],"type":"Point"}
}