{
  "type": "Feature",
  "properties": {
    "iso:country":"ES",
    "sg:address":"Carrer de Socrates, 44",
    "sg:city":"Sabadell",
    "sg:orig_category":"Mec\u00c1nico Del Autom\u00d3vil",
    "sg:phone":"+34 937 16 73 30",
    "sg:postcode":"08206",
    "sg:province":"Barcelona",
    "wof:name":"Martinez Alfonso Maria Encarnacion",
    "wof:placetype":"venue"
},
  "geometry": {"coordinates":[2.0839600563,41.556350708],"type":"Point"}
}