{
  "type": "Feature",
  "properties": {
    "iso:country":"ES",
    "sg:address":"Avda Xubia, 13",
    "sg:city":"Xubia-casadelos",
    "sg:orig_category":"Molduras, Junquillos, Listones Y Molduras Perforadas",
    "sg:phone":"+34 981 38 78 58",
    "sg:postcode":"15510",
    "sg:province":"La Coru\u00f1a",
    "wof:name":"Fernandez Lombao Eva",
    "wof:placetype":"venue"
},
  "geometry": {"coordinates":[-8.1510972977,43.5161895752],"type":"Point"}
}