{
  "type": "Feature",
  "properties": {
    "iso:country":"ES",
    "sg:address":"San Andres, S/n",
    "sg:city":"Zuasti",
    "sg:orig_category":"Clubes Y Asociaciones Deportivas Y De Actividades Invernales Y De Monta\u00d1a",
    "sg:phone":"+34 948 30 29 00",
    "sg:postcode":"31892",
    "sg:province":"Navarra",
    "wof:name":"Se\u00f1orio De Zuasti Golf Club S.a.",
    "wof:placetype":"venue"
},
  "geometry": {"coordinates":[-1.7668290138,42.8839645386],"type":"Point"}
}