{
  "type": "Feature",
  "properties": {
    "iso:country":"ES",
    "sg:address":"Calle de Rio Piedras, 8",
    "sg:city":"Puerto Rico",
    "sg:orig_category":"Alquiler De Veh\u00cdculos: Turismos Y Utilitarios",
    "sg:phone":"+34 928 56 23 34",
    "sg:postcode":"35130",
    "sg:province":"Las Palmas",
    "wof:name":"Vera Hernandez Carmen",
    "wof:placetype":"venue"
},
  "geometry": {"coordinates":[-15.7117671967,27.7879295349],"type":"Point"}
}