{
  "type": "Feature",
  "properties": {
    "addr:full":"Crt. Piedrabuena, Km. 0229,0 Valverde Ciudad Real 13195",
    "addr:postcode":"13195",
    "addr:street":"Piedrabuena Km. 0229,0",
    "iso:country":"ES",
    "sg:address":"Crt. Piedrabuena, Km. 0229,0",
    "sg:city":"Valverde",
    "sg:orig_category":"Productos L\u00c1cteos Y Av\u00cdcolas (al Por Mayor)",
    "sg:phone":"+34 926 21 98 44",
    "sg:postcode":"13195",
    "sg:province":"Ciudad Real",
    "wof:name":"Garin Cobian S.a.",
    "wof:placetype":"venue"
},
  "geometry": {"coordinates":[-4.0409832001,38.9636878967],"type":"Point"}
}