{
  "type": "Feature",
  "properties": {
    "addr:full":"Carretera, S/n Almodovar C\u00f3rdoba 14720",
    "addr:postcode":"14720",
    "addr:street":"Carretera S / N;Co\u0301Rdoba",
    "iso:country":"ES",
    "sg:address":"Carretera, S/n",
    "sg:city":"Almodovar",
    "sg:orig_category":"Asociaciones, Organismos Culturales Y Socioeducativos",
    "sg:phone":"+34 957 63 52 16",
    "sg:postcode":"14720",
    "sg:province":"C\u00f3rdoba",
    "wof:name":"Asociacion Cerro De La Pe\u00d1a Del Aguila",
    "wof:placetype":"venue"
},
  "geometry": {"coordinates":[-4.9974460602,37.8514900208],"type":"Point"}
}