{
  "type": "Feature",
  "properties": {
    "iso:country":"ES",
    "sg:address":"Avda Alcalde Manuel Platas Varela, 122",
    "sg:city":"Vilarrodis",
    "sg:orig_category":"Agentes, Concesionarios Y Sucursales De Veh\u00cdculos",
    "sg:phone":"+34 981 60 03 09",
    "sg:postcode":"15141",
    "sg:province":"A Coru\u00f1a",
    "wof:name":"Talleres Mosquera E Hijos S.l.",
    "wof:placetype":"venue"
},
  "geometry": {"coordinates":[-8.4788036346,43.3249664307],"type":"Point"}
}