{
  "type": "Feature",
  "properties": {
    "iso:country":"ES",
    "sg:address":"Rua Ronda Don Bosco, 28",
    "sg:city":"Vigo",
    "sg:orig_category":"Expertos Contables, Revisores De Cuentas",
    "sg:phone":"+34 986 22 48 81",
    "sg:postcode":"36202",
    "sg:province":"Pontevedra",
    "wof:name":"Castle Spain Auditores,s.l.",
    "wof:placetype":"venue"
},
  "geometry": {"coordinates":[-8.7225389481,42.2349014282],"type":"Point"}
}