{
  "type": "Feature",
  "properties": {
    "addr:full":"Calle de Raimundo Revilla, 2 Laredo Cantabria 39770",
    "addr:housenumber":"2",
    "addr:postcode":"39770",
    "addr:street":"Calle De Raimundo Revilla",
    "iso:country":"ES",
    "sg:address":"Calle de Raimundo Revilla, 2",
    "sg:city":"Laredo",
    "sg:orig_category":"Muebles Y Accesorios Para Cocinas Y Cuartos De Ba\u00d1o (al Por Menor)",
    "sg:phone":"+34 942 60 64 00",
    "sg:postcode":"39770",
    "sg:province":"Cantabria",
    "wof:name":"Santamaria Molinuevo Jose Antonio",
    "wof:placetype":"venue"
},
  "geometry": {"coordinates":[-3.4130868912,43.4123153687],"type":"Point"}
}