{
  "type": "Feature",
  "properties": {
    "iso:country":"ES",
    "sg:address":"Av Jaume Balmes, 32",
    "sg:city":"Vilanova I La Geltru",
    "sg:orig_category":"Caf\u00c9s, Bares, Cervecer\u00cdas",
    "sg:phone":"+34 938 15 74 21",
    "sg:postcode":"08800",
    "sg:province":"Barcelona",
    "wof:name":"Abasso Forcat Miguel",
    "wof:placetype":"venue"
},
  "geometry": {"coordinates":[1.722306,41.219776],"type":"Point"}
}