{
  "type": "Feature",
  "properties": {
    "iso:country":"ES",
    "sg:address":"Calle de Corredera, 8",
    "sg:city":"Alcazar S. Juan",
    "sg:orig_category":"Accesorios Para Tintorer\u00cdas, Limpieza En Seco",
    "sg:phone":"+34 926 58 84 49",
    "sg:postcode":"13600",
    "sg:province":"Ciudad Real",
    "wof:name":"Gonzalez Garcia-morato Maria Jose",
    "wof:placetype":"venue"
},
  "geometry": {"coordinates":[-3.2125895023,39.3911399841],"type":"Point"}
}