{
  "type": "Feature",
  "properties": {
    "iso:country":"ES",
    "sg:address":"Pase Chopera (de La), 124",
    "sg:city":"Alcobendas",
    "sg:orig_category":"Pintura, Barniz, Productos Asimilables (fabricaci\u00d3n, Al Por Mayor)",
    "sg:phone":"+34 916 62 02 19",
    "sg:postcode":"28100",
    "sg:province":"Madrid",
    "wof:name":"Perez Espada Jesus",
    "wof:placetype":"venue"
},
  "geometry": {"coordinates":[-3.6522829533,40.5450248718],"type":"Point"}
}