{
  "type": "Feature",
  "properties": {
    "addr:full":"Calle de Fernando Caston, 3 Badajoz Badajoz 06005",
    "addr:housenumber":"3",
    "addr:postcode":"06005",
    "addr:street":"Calle De Fernando Caston",
    "iso:country":"ES",
    "sg:address":"Calle de Fernando Caston, 3",
    "sg:city":"Badajoz",
    "sg:orig_category":"Institutos De Belleza",
    "sg:phone":"+34 924 24 19 59",
    "sg:postcode":"06005",
    "sg:province":"Badajoz",
    "wof:name":"Barroso Telesforo Emilia Maria",
    "wof:placetype":"venue"
},
  "geometry": {"coordinates":[-6.9766302109,38.873588562],"type":"Point"}
}