{
  "type": "Feature",
  "properties": {
    "iso:country":"ES",
    "sg:address":"Pase San Antonio (de), 12",
    "sg:city":"Cuenca",
    "sg:orig_category":"Plomeros",
    "sg:phone":"+34 969 24 03 90",
    "sg:postcode":"16003",
    "sg:province":"Cuenca",
    "wof:name":"Saneamientos San Antonio De Cuenca S. L.",
    "wof:placetype":"venue"
},
  "geometry": {"coordinates":[-2.1375660896,40.0677337646],"type":"Point"}
}