{
  "type": "Feature",
  "properties": {
    "addr:full":"Errementari Plaza, 2 O\u00f1ati Guip\u00f9zcoa 20560",
    "addr:housenumber":"2",
    "addr:postcode":"20560",
    "addr:street":"Errementari Plaza;Guipu\u0300Zcoa",
    "iso:country":"ES",
    "sg:address":"Errementari Plaza, 2",
    "sg:city":"O\u00f1ati",
    "sg:orig_category":"Asesor\u00cda Sobre Comunicaci\u00d3n De Empresas",
    "sg:phone":"+34 943 78 08 90",
    "sg:postcode":"20560",
    "sg:province":"Guip\u00f9zcoa",
    "wof:name":"Ignacio Erostarbe Garitano Y Ion Lizarra",
    "wof:placetype":"venue"
},
  "geometry": {"coordinates":[-2.4123806953,43.0305213928],"type":"Point"}
}