{
  "type": "Feature",
  "properties": {
    "iso:country":"ES",
    "sg:address":"Calle de Luis Vives, 2",
    "sg:city":"Alcala Henares",
    "sg:orig_category":"Pescader\u00cdas (al Por Menor)",
    "sg:phone":"+34 918 89 05 43",
    "sg:postcode":"28803",
    "sg:province":"Madrid",
    "wof:name":"Pescados German Criado S.l.",
    "wof:placetype":"venue"
},
  "geometry": {"coordinates":[-3.3688631058,40.4767913818],"type":"Point"}
}