{
  "type": "Feature",
  "properties": {
    "iso:country":"ES",
    "sg:address":"Barr Arnia (la), 9",
    "sg:city":"Liencres",
    "sg:orig_category":"Servicios De Telecomunicaciones",
    "sg:phone":"+34 942 57 86 00",
    "sg:postcode":"39120",
    "sg:province":"Cantabria",
    "wof:name":"Noditel S.l.",
    "wof:placetype":"venue"
},
  "geometry": {"coordinates":[-3.9269039631,43.4604797363],"type":"Point"}
}