{
  "type": "Feature",
  "properties": {
    "addr:full":"Avgd Alameda Jaume I, 42 Xativa Valencia 46800",
    "addr:housenumber":"42",
    "addr:postcode":"46800",
    "addr:street":"Alameda Jaume I",
    "iso:country":"ES",
    "sg:address":"Avgd Alameda Jaume I, 42",
    "sg:city":"Xativa",
    "sg:orig_category":"M\u00c9dicos: Pediatr\u00cda. Enfermedades De Los Ni\u00d1os",
    "sg:phone":"+34 962 27 38 90",
    "sg:postcode":"46800",
    "sg:province":"Valencia",
    "wof:name":"Baldo Cucarella Juan Bautista",
    "wof:placetype":"venue"
},
  "geometry": {"coordinates":[-0.5222234726,38.9897460938],"type":"Point"}
}