{
  "type": "Feature",
  "properties": {
    "iso:country":"ES",
    "sg:address":"Avda Marconi, 19",
    "sg:city":"Cadiz",
    "sg:orig_category":"Farmacias",
    "sg:phone":"+34 956 25 24 97",
    "sg:postcode":"11011",
    "sg:province":"C\u00e1diz",
    "wof:name":"Cuervas-mons Lazaga Milagrosa",
    "wof:placetype":"venue"
},
  "geometry": {"coordinates":[-6.2731628418,36.5078849792],"type":"Point"}
}