{
  "type": "Feature",
  "properties": {
    "addr:full":"Avda Rey Juan Carlos I, 50 Tarancon Cuenca 16400",
    "addr:housenumber":"50",
    "addr:postcode":"16400",
    "addr:street":"Avda Rey Juan Carlos I",
    "iso:country":"ES",
    "sg:address":"Avda Rey Juan Carlos I, 50",
    "sg:city":"Tarancon",
    "sg:orig_category":"Comercio, Reparaci\u00d3n De Bicicletas, De Motocicletas, De Accesorios",
    "sg:phone":"+34 969 32 10 28",
    "sg:postcode":"16400",
    "sg:province":"Cuenca",
    "wof:name":"Desarrollos Industriales Tarmotos S.l.",
    "wof:placetype":"venue"
},
  "geometry": {"coordinates":[-3.0054891109,40.0067214966],"type":"Point"}
}