{
  "type": "Feature",
  "properties": {
    "iso:country":"ES",
    "sg:address":"Rbla. P. Catalans, 1",
    "sg:city":"Vilanova Geltru",
    "sg:orig_category":"Promotores Constructores",
    "sg:phone":"+34 938 93 04 46",
    "sg:postcode":"08800",
    "sg:province":"Barcelona",
    "sg:website":"www.c2s.es",
    "wof:name":"Construccions 2 S S.l.",
    "wof:placetype":"venue"
},
  "geometry": {"coordinates":[1.7268999815,41.2211303711],"type":"Point"}
}