{
  "type": "Feature",
  "properties": {
    "addr:full":"Calle de Castellanos, 13 Valdepe\u00f1as Ciudad Real 13300",
    "addr:housenumber":"13",
    "addr:postcode":"13300",
    "addr:street":"Calle De Castellanos",
    "iso:country":"ES",
    "sg:address":"Calle de Castellanos, 13",
    "sg:city":"Valdepe\u00f1as",
    "sg:orig_category":"Ense\u00d1anza, Formaci\u00d3n Profesional: Aprendizaje",
    "sg:phone":"+34 926 31 00 95",
    "sg:postcode":"13300",
    "sg:province":"Ciudad Real",
    "sg:website":"www.mir.es}}",
    "wof:name":"Direccion General De La Policia D.n.i.",
    "wof:placetype":"venue"
},
  "geometry": {"coordinates":[-3.3843159676,38.7652168274],"type":"Point"}
}