{
  "type": "Feature",
  "properties": {
    "addr:full":"Ctra. General, 2 Chayofa Santa Cruz De Tenerife 38652",
    "addr:housenumber":"2",
    "addr:postcode":"38652",
    "addr:street":"Ctra. General",
    "iso:country":"ES",
    "sg:address":"Ctra. General, 2",
    "sg:city":"Chayofa",
    "sg:orig_category":"Transporte En General",
    "sg:phone":"+34 922 72 98 12",
    "sg:postcode":"38652",
    "sg:province":"Santa Cruz De Tenerife",
    "wof:name":"Cantabro Canaria De Logistica Integral S.l.",
    "wof:placetype":"venue"
},
  "geometry": {"coordinates":[-16.6932086945,28.07188797],"type":"Point"}
}