{
  "type": "Feature",
  "properties": {
    "iso:country":"ES",
    "sg:address":"Carrer de Mossen Joaquim Roca, 3",
    "sg:city":"Casc Antic",
    "sg:orig_category":"Caf\u00c9s (al Por Menor)",
    "sg:phone":"+34 936 45 03 07",
    "sg:postcode":"08690",
    "sg:province":"Barcelona",
    "wof:name":"Linares Afan Manuel",
    "wof:placetype":"venue"
},
  "geometry": {"coordinates":[2.0219130516,41.3697509766],"type":"Point"}
}