{
  "type": "Feature",
  "properties": {
    "iso:country":"ES",
    "sg:address":"Carrer de Sant Crist, 61",
    "sg:city":"Barcelona",
    "sg:orig_category":"Agricultores, Agricultores",
    "sg:phone":"+34 934 21 98 74",
    "sg:postcode":"08014",
    "sg:province":"Barcelona",
    "wof:name":"Corporacion Agropecuaria Persa Sl",
    "wof:placetype":"venue"
},
  "geometry": {"coordinates":[2.1375219822,41.3741722107],"type":"Point"}
}