{
  "type": "Feature",
  "properties": {
    "addr:full":"Avgd Llibertat (de La), 24 Almafra Alicante 03610",
    "addr:postcode":"03610",
    "iso:country":"ES",
    "sg:address":"Avgd Llibertat (de La), 24",
    "sg:city":"Almafra",
    "sg:orig_category":"Fabricaci\u00d3n De Sobres, Bolsas Y Fundas",
    "sg:phone":"+34 965 37 06 89",
    "sg:postcode":"03610",
    "sg:province":"Alicante",
    "sg:website":"www.robertpietri.com",
    "wof:name":"Robert Pietri S.l.",
    "wof:placetype":"venue"
},
  "geometry": {"coordinates":[-0.7859489918,38.489315033],"type":"Point"}
}