{
  "type": "Feature",
  "properties": {
    "iso:country":"ES",
    "sg:address":"Rua Conde (do), 51",
    "sg:city":"Lugo",
    "sg:classifiers":[
        {
            "category":"Personal",
            "subcategory":"Barber",
            "type":"Services"
        }
    ],
    "sg:phone":"+34 982 24 26 16",
    "sg:postcode":"27003",
    "sg:province":"Lugo",
    "sg:tags":[
        "caballeros",
        "de",
        "peluqueros"
    ],
    "wof:name":"Ferreiros Adrio Jose Angel",
    "wof:placetype":"venue"
},
  "geometry": {"coordinates":[-7.557612896,43.0164642334],"type":"Point"}
}