{
  "type": "Feature",
  "properties": {
    "addr:full":"Avda Pardo, 1 Matas-pinar-monte Rozas Madrid 28290",
    "addr:housenumber":"1",
    "addr:postcode":"28290",
    "addr:street":"Avda Pardo",
    "iso:country":"ES",
    "sg:address":"Avda Pardo, 1",
    "sg:city":"Matas-pinar-monte Rozas",
    "sg:orig_category":"Internados & Ense\u00d1anza Privada",
    "sg:phone":"+34 916 30 05 63",
    "sg:postcode":"28290",
    "sg:province":"Madrid",
    "wof:name":"Colegio Los Pe\u00f1ascales",
    "wof:placetype":"venue"
},
  "geometry": {"coordinates":[-3.8995120525,40.5642852783],"type":"Point"}
}