{
  "type": "Feature",
  "properties": {
    "iso:country":"ES",
    "sg:address":"Carrer de Tortosa, 6",
    "sg:city":"Rasquera",
    "sg:orig_category":"Administraciones Regionales, Departamentales Y Locales",
    "sg:phone":"+34 977 40 90 61",
    "sg:postcode":"43513",
    "sg:province":"Tarragona",
    "wof:name":"Ajuntament De Rasquera",
    "wof:placetype":"venue"
},
  "geometry": {"coordinates":[0.5966507792,41.0017662048],"type":"Point"}
}