{
  "type": "Feature",
  "properties": {
    "addr:full":"Avda Ana De Viya, 3 Cadiz C\u00e1diz 11009",
    "addr:housenumber":"3",
    "addr:postcode":"11009",
    "addr:street":"Avda Ana De Viya",
    "iso:country":"ES",
    "sg:address":"Avda Ana De Viya, 3",
    "sg:city":"Cadiz",
    "sg:orig_category":"Abogados",
    "sg:phone":"+34 956 27 65 54",
    "sg:postcode":"11009",
    "sg:province":"C\u00e1diz",
    "wof:name":"Perez Cordoba Ignacio",
    "wof:placetype":"venue"
},
  "geometry": {"coordinates":[-6.2802481651,36.5124397278],"type":"Point"}
}