{
  "type": "Feature",
  "properties": {
    "addr:full":"Cami Biniaraix, De, 17 Biniaraix Islas Baleares 07101",
    "addr:postcode":"07101",
    "addr:street":"Islas",
    "iso:country":"ES",
    "sg:address":"Cami Biniaraix, De, 17",
    "sg:city":"Biniaraix",
    "sg:orig_category":"Charcuter\u00cdas (al Por Mayor)",
    "sg:phone":"+34 971 63 05 91",
    "sg:postcode":"07101",
    "sg:province":"Islas Baleares",
    "wof:name":"Ca'n Matarino S.l.",
    "wof:placetype":"venue"
},
  "geometry": {"coordinates":[2.7354140282,39.771396637],"type":"Point"}
}