{
  "type": "Feature",
  "properties": {
    "iso:country":"ES",
    "sg:address":"Rua Paseo (do), 2",
    "sg:city":"Ourense",
    "sg:orig_category":"Oficinas: Suministros Para (fabricaci\u00d3n, Al Por Mayor)",
    "sg:phone":"+34 988 22 36 47",
    "sg:postcode":"32005",
    "sg:province":"Ourense",
    "wof:name":"Office Depot International Ltd Sucursal En Espana",
    "wof:placetype":"venue"
},
  "geometry": {"coordinates":[-7.8645019531,42.3379096985],"type":"Point"}
}