{
  "type": "Feature",
  "properties": {
    "iso:country":"ES",
    "sg:address":"Calle de Emilio Ferrari, 5",
    "sg:city":"Madrid",
    "sg:orig_category":"Administradores De Bienes Y Delegados De Comunidades De Propietarios",
    "sg:phone":"+34 914 07 57 83",
    "sg:postcode":"28017",
    "sg:province":"Madrid",
    "wof:name":"Garcia Liceras Maria Del Carmen",
    "wof:placetype":"venue"
},
  "geometry": {"coordinates":[-3.6436591148,40.4346466064],"type":"Point"}
}