{
  "type": "Feature",
  "properties": {
    "addr:full":"Calle de Jose Luis Caro, 25 Gines Sevilla 41960",
    "addr:housenumber":"25",
    "addr:postcode":"41960",
    "addr:street":"Calle De Jose Luis Caro;Sevilla",
    "iso:country":"ES",
    "sg:address":"Calle de Jose Luis Caro, 25",
    "sg:city":"Gines",
    "sg:orig_category":"Promotores Constructores",
    "sg:phone":"+34 954 71 30 62",
    "sg:postcode":"41960",
    "sg:province":"Sevilla",
    "wof:name":"Jurado Montiel Francisco Borja",
    "wof:placetype":"venue"
},
  "geometry": {"coordinates":[-6.0770978928,37.3855667114],"type":"Point"}
}