{
  "type": "Feature",
  "properties": {
    "addr:full":"Laubide Auzoa, 21 Legazpi Guip\u00f9zcoa 20230",
    "addr:housenumber":"21",
    "addr:postcode":"20230",
    "addr:street":"Laubide Auzoa;Guipu\u0300Zcoa",
    "iso:country":"ES",
    "sg:address":"Laubide Auzoa, 21",
    "sg:city":"Legazpi",
    "sg:orig_category":"Asistencia Social",
    "sg:phone":"+34 943 73 00 42",
    "sg:postcode":"20230",
    "sg:province":"Guip\u00f9zcoa",
    "wof:name":"Atzegi",
    "wof:placetype":"venue"
},
  "geometry": {"coordinates":[-2.3368880749,43.0568122864],"type":"Point"}
}