{
  "type": "Feature",
  "properties": {
    "addr:full":"Ctra. Picanya, Km. 0001,2 Torrent Valencia 46900",
    "addr:postcode":"46900",
    "addr:street":"Ctra. Picanya Km. 0001,2;Valencia",
    "iso:country":"ES",
    "sg:address":"Ctra. Picanya, Km. 0001,2",
    "sg:city":"Torrent",
    "sg:orig_category":"Distribuci\u00d3n De Petr\u00d3leo Y Derivados",
    "sg:phone":"+34 961 55 22 34",
    "sg:postcode":"46900",
    "sg:province":"Valencia",
    "wof:name":"Estacion De Servicio Nemesio S.l.",
    "wof:placetype":"venue"
},
  "geometry": {"coordinates":[-0.4621559978,39.4413108826],"type":"Point"}
}