{
  "type": "Feature",
  "properties": {
    "iso:country":"ES",
    "sg:address":"Pase Rosa, 132",
    "sg:city":"Toledo",
    "sg:orig_category":"Art\u00cdculos De Decoraci\u00d3n",
    "sg:phone":"+34 925 25 50 44",
    "sg:postcode":"45006",
    "sg:province":"Toledo",
    "sg:website":"www.paginasamarillas.es",
    "wof:name":"Garcia Mora San Jose Antonio",
    "wof:placetype":"venue"
},
  "geometry": {"coordinates":[-4.0053992271,39.860748291],"type":"Point"}
}