{
  "type": "Feature",
  "properties": {
    "iso:country":"ES",
    "sg:address":"Av Francesc Macia, 109",
    "sg:city":"Vilanova I La Geltru",
    "sg:orig_category":"Ropa Para Ni\u00d1os (al Por Menor)",
    "sg:phone":"+34 938 15 91 68",
    "sg:postcode":"08800",
    "sg:province":"Barcelona",
    "wof:name":"Linares Carrillo Carmen",
    "wof:placetype":"venue"
},
  "geometry": {"coordinates":[1.7184000015,41.2218017578],"type":"Point"}
}