{
  "type": "Feature",
  "properties": {
    "addr:full":"Carrer de Rossello, 446 Barcelona Barcelona 08025",
    "addr:housenumber":"446",
    "addr:postcode":"08025",
    "addr:street":"Carrer De Rossello",
    "iso:country":"ES",
    "sg:address":"Carrer de Rossello, 446",
    "sg:city":"Barcelona",
    "sg:orig_category":"Autob\u00das (explotaci\u00d3n Y Servicios De)",
    "sg:phone":"+34 934 12 23 93",
    "sg:postcode":"08025",
    "sg:province":"Barcelona",
    "wof:name":"Companyia Del Minibus S.a.",
    "wof:placetype":"venue"
},
  "geometry": {"coordinates":[2.176058054,41.4072113037],"type":"Point"}
}