{
  "type": "Feature",
  "properties": {
    "iso:country":"ES",
    "sg:address":"Carrer de Caldes, 18",
    "sg:city":"Castellar Valles",
    "sg:orig_category":"Fabricaci\u00d3n, Venta De Cuadros, Accesorios Para Enmarcar",
    "sg:phone":"+34 937 14 59 38",
    "sg:postcode":"08211",
    "sg:province":"Barcelona",
    "wof:name":"Santisteban Domingo Florencio",
    "wof:placetype":"venue"
},
  "geometry": {"coordinates":[2.0894310474,41.6177139282],"type":"Point"}
}