{
  "type": "Feature",
  "properties": {
    "iso:country":"ES",
    "sg:address":"Av Diagonal, 618",
    "sg:city":"Barcelona",
    "sg:orig_category":"Ense\u00d1anza: Comercio, Gesti\u00d3n, Inform\u00c1tica",
    "sg:phone":"+34 932 09 29 66",
    "sg:postcode":"08021",
    "sg:province":"Barcelona",
    "sg:website":"www.bit.es",
    "wof:name":"Bit S. A.",
    "wof:placetype":"venue"
},
  "geometry": {"coordinates":[2.1408720016,41.3922805786],"type":"Point"}
}