{
  "type": "Feature",
  "properties": {
    "addr:full":"Calle de Senda Mitjana, 41 Nules Castell\u00f3n 12520",
    "addr:housenumber":"41",
    "addr:postcode":"12520",
    "addr:street":"Calle De Senda Mitjana",
    "iso:country":"ES",
    "sg:address":"Calle de Senda Mitjana, 41",
    "sg:city":"Nules",
    "sg:orig_category":"Fabrica De Cer\u00c1micas",
    "sg:phone":"+34 964 69 05 67",
    "sg:postcode":"12520",
    "sg:province":"Castell\u00f3n",
    "wof:name":"Art Compakt S.l.",
    "wof:placetype":"venue"
},
  "geometry": {"coordinates":[-0.1470786035,39.8552818298],"type":"Point"}
}