{
  "type": "Feature",
  "properties": {
    "addr:full":"Avgd Valldigna, De La, 67 Casco Urbano Valencia 46760",
    "addr:postcode":"46760",
    "iso:country":"ES",
    "sg:address":"Avgd Valldigna, De La, 67",
    "sg:city":"Casco Urbano",
    "sg:orig_category":"Mec\u00c1nico Del Autom\u00d3vil",
    "sg:phone":"+34 962 82 15 84",
    "sg:postcode":"46760",
    "sg:province":"Valencia",
    "wof:name":"Jordi Motors S.c.l.v.",
    "wof:placetype":"venue"
},
  "geometry": {"coordinates":[-0.2594090104,39.0749702454],"type":"Point"}
}