{
  "type": "Feature",
  "properties": {
    "addr:full":"Calle de Duquesa, 8 Granada Granada 18001",
    "addr:housenumber":"8",
    "addr:postcode":"18001",
    "addr:street":"Calle De Duquesa",
    "iso:country":"ES",
    "sg:address":"Calle de Duquesa, 8",
    "sg:city":"Granada",
    "sg:orig_category":"Molduras, Junquillos, Listones Y Molduras Perforadas",
    "sg:phone":"+34 958 27 04 11",
    "sg:postcode":"18001",
    "sg:province":"Granada",
    "wof:name":"Aguilera Sanchez Gabriel",
    "wof:placetype":"venue"
},
  "geometry": {"coordinates":[-3.601973772,37.1770401001],"type":"Point"}
}