{
  "type": "Feature",
  "properties": {
    "addr:full":"Plaz Reloj (del), 9 Campos Del Rio Murcia 30191",
    "addr:housenumber":"9",
    "addr:postcode":"30191",
    "addr:street":"Plaz Reloj Del",
    "iso:country":"ES",
    "sg:address":"Plaz Reloj (del), 9",
    "sg:city":"Campos Del Rio",
    "sg:orig_category":"Aguas (distribuci\u00d3n, Servicios)",
    "sg:phone":"+34 968 65 05 55",
    "sg:postcode":"30191",
    "sg:province":"Murcia",
    "wof:name":"Aqualia Gestion Integral Del Agua S.a.",
    "wof:placetype":"venue"
},
  "geometry": {"coordinates":[-1.348490715,38.0388221741],"type":"Point"}
}