{
  "type": "Feature",
  "properties": {
    "addr:full":"Carr Tramuntana, (de), 14 Carlet Valencia 46240",
    "addr:housenumber":"14",
    "addr:postcode":"46240",
    "addr:street":"Carr Tramuntana De",
    "iso:country":"ES",
    "sg:address":"Carr Tramuntana, (de), 14",
    "sg:city":"Carlet",
    "sg:orig_category":"Comercio De Hierro",
    "sg:phone":"+34 962 53 80 25",
    "sg:postcode":"46240",
    "sg:province":"Valencia",
    "wof:name":"Hierros Garver S.l.",
    "wof:placetype":"venue"
},
  "geometry": {"coordinates":[-0.4901140034,39.2333297729],"type":"Point"}
}