{
  "type": "Feature",
  "properties": {
    "iso:country":"ES",
    "sg:address":"Lazo, 24",
    "sg:city":"Pozo Alcon",
    "sg:orig_category":"Electrodom\u00c9sticos (al Por Menor)",
    "sg:phone":"+34 953 73 86 74",
    "sg:postcode":"23485",
    "sg:province":"Ja\u00e9n",
    "wof:name":"Bautista Torres David",
    "wof:placetype":"venue"
},
  "geometry": {"coordinates":[-2.9353590012,37.7045326233],"type":"Point"}
}