{
  "type": "Feature",
  "properties": {
    "iso:country":"ES",
    "sg:address":"Plaz Espa\u00d1a, 8",
    "sg:city":"Lillo",
    "sg:orig_category":"Producci\u00d3n, Venta De Productos De Agricultura Biol\u00d3gica",
    "sg:phone":"+34 925 17 01 65",
    "sg:postcode":"45870",
    "sg:province":"Toledo",
    "wof:name":"Agropecuaria Esperanza S.l.",
    "wof:placetype":"venue"
},
  "geometry": {"coordinates":[-3.3187470436,39.7076759338],"type":"Point"}
}