{
  "type": "Feature",
  "properties": {
    "addr:full":"Av. Maritima, S/n Playa Americas Santa Cruz De Tenerife 38660",
    "addr:housenumber":"s / n",
    "addr:postcode":"38660",
    "addr:street":"Av. Maritima;Americas",
    "iso:country":"ES",
    "sg:address":"Av. Maritima, S/n",
    "sg:city":"Playa Americas",
    "sg:orig_category":"Supermercados Y Hipermercados",
    "sg:phone":"+34 922 79 16 58",
    "sg:postcode":"38660",
    "sg:province":"Santa Cruz De Tenerife",
    "wof:name":"Comares Amc S.l.",
    "wof:placetype":"venue"
},
  "geometry": {"coordinates":[-16.7362289429,28.0853347778],"type":"Point"}
}