{
  "type": "Feature",
  "properties": {
    "addr:full":"Avda Gasteiz, 28 Vitoria-gasteiz \u00c1lava 01008",
    "addr:housenumber":"28",
    "addr:postcode":"01008",
    "addr:street":"Avda Gasteiz",
    "iso:country":"ES",
    "sg:address":"Avda Gasteiz, 28",
    "sg:city":"Vitoria-gasteiz",
    "sg:orig_category":"Caf\u00c9s, Bares, Cervecer\u00cdas",
    "sg:phone":"+34 945 13 36 15",
    "sg:postcode":"01008",
    "sg:province":"\u00c1lava",
    "wof:name":"Irineo Lazaro Ordo\u00f1ez",
    "wof:placetype":"venue"
},
  "geometry": {"coordinates":[-2.6819090843,42.8457260132],"type":"Point"}
}