{
  "type": "Feature",
  "properties": {
    "addr:full":"Ctra Sevilla-malaga-granada, Km. 0013,0 Alcala Guadaira Sevilla 41500",
    "addr:postcode":"41500",
    "addr:street":"Ctra Sevilla-Malaga-Granada Km. 0013,0",
    "iso:country":"ES",
    "sg:address":"Ctra Sevilla-malaga-granada, Km. 0013,0",
    "sg:city":"Alcala Guadaira",
    "sg:orig_category":"Arenas, Guijarros Y Granulados",
    "sg:phone":"+34 955 61 32 41",
    "sg:postcode":"41500",
    "sg:province":"Sevilla",
    "wof:name":"Alvereda S.l.",
    "wof:placetype":"venue"
},
  "geometry": {"coordinates":[-5.8740124702,37.3626556396],"type":"Point"}
}