{
  "type": "Feature",
  "properties": {
    "iso:country":"ES",
    "sg:address":"Carrer de Major, 119",
    "sg:city":"Sabadell",
    "sg:orig_category":"Rectificaci\u00d3n, Mecanizado, Fresado",
    "sg:phone":"+34 937 16 06 99",
    "sg:postcode":"08208",
    "sg:province":"Barcelona",
    "wof:name":"Talleres Montalban S.c.p",
    "wof:placetype":"venue"
},
  "geometry": {"coordinates":[2.0983181,41.5567474365],"type":"Point"}
}