{
  "type": "Feature",
  "properties": {
    "iso:country":"ES",
    "sg:address":"Calle de Karmelo, 6",
    "sg:city":"Bilbao",
    "sg:orig_category":"Centros De Coordinaci\u00d3n",
    "sg:phone":"+34 944 33 81 41",
    "sg:postcode":"48004",
    "sg:province":"Vizcaya",
    "wof:name":"La Oficina Servicios Administrativos Integrales C.b.",
    "wof:placetype":"venue"
},
  "geometry": {"coordinates":[-2.9151830673,43.2535171509],"type":"Point"}
}