{
  "type": "Feature",
  "properties": {
    "iso:country":"ES",
    "sg:address":"Praz Fonte Dos Ranchos, 14",
    "sg:city":"Lugo",
    "sg:orig_category":"Peluquer\u00cdas, Peluquer\u00cda Mixta",
    "sg:phone":"+34 982 21 67 05",
    "sg:postcode":"27004",
    "sg:province":"Lugo",
    "wof:name":"Vazquez Roca Jaime",
    "wof:placetype":"venue"
},
  "geometry": {"coordinates":[-7.5650892258,43.0129585266],"type":"Point"}
}