{
  "type": "Feature",
  "properties": {
    "addr:full":"Calle de Murillo, 13 Alcazar S. Juan Ciudad Real 13600",
    "addr:housenumber":"13",
    "addr:postcode":"13600",
    "addr:street":"Calle De Murillo;Alcazar S. Juan Ciudad Real",
    "iso:country":"ES",
    "sg:address":"Calle de Murillo, 13",
    "sg:city":"Alcazar S. Juan",
    "sg:orig_category":"Abogados",
    "sg:phone":"+34 926 54 65 99",
    "sg:postcode":"13600",
    "sg:province":"Ciudad Real",
    "wof:name":"Martin-serrano Manzaneque Jose Maria",
    "wof:placetype":"venue"
},
  "geometry": {"coordinates":[-3.2018890381,39.3915290833],"type":"Point"}
}