{
  "type": "Feature",
  "properties": {
    "iso:country":"ES",
    "sg:address":"Calle de Real, 103",
    "sg:city":"S. Fernando",
    "sg:orig_category":"Tiendas De Grano, Frutas Y Legumbres Secas (al Por Menor)",
    "sg:phone":"+34 956 88 89 26",
    "sg:postcode":"11100",
    "sg:province":"C\u00e1diz",
    "wof:name":"Hermanos Toyos La Barraca",
    "wof:placetype":"venue"
},
  "geometry": {"coordinates":[-6.1954979897,36.466178894],"type":"Point"}
}