{
  "type": "Feature",
  "properties": {
    "iso:country":"ES",
    "sg:address":"Calle de Mayor, 88",
    "sg:city":"Madrid",
    "sg:orig_category":"Frutas Y Legumbres Secas (al Por Mayor)",
    "sg:phone":"+34 915 59 68 22",
    "sg:postcode":"28013",
    "sg:province":"Madrid",
    "wof:name":"Souvenirs Virgen De La Almudena",
    "wof:placetype":"venue"
},
  "geometry": {"coordinates":[-3.7131929398,40.4151000977],"type":"Point"}
}