{
  "type": "Feature",
  "properties": {
    "iso:country":"ES",
    "sg:address":"Calle de Manresa, 12",
    "sg:city":"Tudela",
    "sg:orig_category":"Promotores Constructores",
    "sg:phone":"+34 948 82 06 76",
    "sg:postcode":"31500",
    "sg:province":"Navarra",
    "wof:name":"Thebrocas S.l.",
    "wof:placetype":"venue"
},
  "geometry": {"coordinates":[-1.6022080183,42.0591239929],"type":"Point"}
}