{
  "type": "Feature",
  "properties": {
    "iso:country":"ES",
    "sg:address":"Avda Pocito De Las Nieves, 10",
    "sg:city":"Rozas De Madrid",
    "sg:orig_category":"Farmacias",
    "sg:phone":"+34 916 37 04 25",
    "sg:postcode":"28230",
    "sg:province":"Madrid",
    "wof:name":"Cubo Perez Raquel",
    "wof:placetype":"venue"
},
  "geometry": {"coordinates":[-3.8706109524,40.4935874939],"type":"Point"}
}