{
  "type": "Feature",
  "properties": {
    "addr:full":"Carrer de Merce Rodoreda, 1 Vic Barcelona 08500",
    "addr:housenumber":"1",
    "addr:postcode":"08500",
    "addr:street":"Carrer De Merce Rodoreda",
    "iso:country":"ES",
    "sg:address":"Carrer de Merce Rodoreda, 1",
    "sg:city":"Vic",
    "sg:orig_category":"Cueros Y Pieles (al Por Mayor)",
    "sg:phone":"+34 938 81 61 81",
    "sg:postcode":"08500",
    "sg:province":"Barcelona",
    "wof:name":"Sola Punti Merce",
    "wof:placetype":"venue"
},
  "geometry": {"coordinates":[2.2690639496,41.9267921448],"type":"Point"}
}