{
  "type": "Feature",
  "properties": {
    "iso:country":"ES",
    "sg:address":"Avda Doctor Galvez Ginachero, 25",
    "sg:city":"Malaga",
    "sg:orig_category":"Arquitectos",
    "sg:phone":"+34 952 28 40 11",
    "sg:postcode":"29009",
    "sg:province":"M\u00e1laga",
    "wof:name":"Morilla Sousa Fernando",
    "wof:placetype":"venue"
},
  "geometry": {"coordinates":[-4.4294872284,36.7268714905],"type":"Point"}
}