{
  "type": "Feature",
  "properties": {
    "addr:full":"Calle de Torrente, 42 Arnedo La Rioja 26580",
    "addr:housenumber":"42",
    "addr:postcode":"26580",
    "addr:street":"Calle De Torrente;Rioja",
    "iso:country":"ES",
    "sg:address":"Calle de Torrente, 42",
    "sg:city":"Arnedo",
    "sg:orig_category":"Tintorer\u00cdas, Limpieza En Seco",
    "sg:phone":"+34 941 38 47 59",
    "sg:postcode":"26580",
    "sg:province":"La Rioja",
    "wof:name":"Emplantillados Marin S.c.",
    "wof:placetype":"venue"
},
  "geometry": {"coordinates":[-2.1038029194,42.228717804],"type":"Point"}
}