{
  "type": "Feature",
  "properties": {
    "addr:full":"Pg Bonanova, 75 Barcelona Barcelona 08017",
    "addr:housenumber":"75",
    "addr:postcode":"08017",
    "addr:street":"Pg Bonanova",
    "iso:country":"ES",
    "sg:address":"Pg Bonanova, 75",
    "sg:city":"Barcelona",
    "sg:orig_category":"Institutos De Belleza",
    "sg:phone":"+34 934 18 25 11",
    "sg:postcode":"08017",
    "sg:province":"Barcelona",
    "wof:name":"Garcia Davila Ana",
    "wof:placetype":"venue"
},
  "geometry": {"coordinates":[2.1264879704,41.40259552],"type":"Point"}
}