{
  "type": "Feature",
  "properties": {
    "addr:full":"Rbla Badal, 156 Barcelona Barcelona 08028",
    "addr:housenumber":"156",
    "addr:postcode":"08028",
    "addr:street":"Rbla Badal",
    "iso:country":"ES",
    "sg:address":"Rbla Badal, 156",
    "sg:city":"Barcelona",
    "sg:orig_category":"Farmacias",
    "sg:phone":"+34 934 22 16 18",
    "sg:postcode":"08028",
    "sg:province":"Barcelona",
    "wof:name":"Estruch Rafa Joan",
    "wof:placetype":"venue"
},
  "geometry": {"coordinates":[2.1314949989,41.373298645],"type":"Point"}
}