{
  "type": "Feature",
  "properties": {
    "addr:full":"Avda Espa\u00d1a (de), 6 San Sebastian De Los Reyes Madrid 28700",
    "addr:postcode":"28700",
    "addr:street":"Avda Espan\u0303A De 6",
    "iso:country":"ES",
    "sg:address":"Avda Espa\u00d1a (de), 6",
    "sg:city":"San Sebastian De Los Reyes",
    "sg:orig_category":"Maquinaria Para Industrias Diversas",
    "sg:phone":"+34 916 52 46 65",
    "sg:postcode":"28700",
    "sg:province":"Madrid",
    "sg:website":"www.alquilalo.com",
    "wof:name":"Alquileres Alcobendas S.l.",
    "wof:placetype":"venue"
},
  "geometry": {"coordinates":[-3.6437852383,40.5441703796],"type":"Point"}
}