{
  "type": "Feature",
  "properties": {
    "iso:country":"ES",
    "sg:address":"Rbla Brasil, 53",
    "sg:city":"Barcelona",
    "sg:orig_category":"Agencias Y Agentes Comerciales, Representantes",
    "sg:phone":"+34 934 90 03 25",
    "sg:postcode":"08028",
    "sg:province":"Barcelona",
    "wof:name":"Forns Agullo Leandro",
    "wof:placetype":"venue"
},
  "geometry": {"coordinates":[2.1289670467,41.3786735535],"type":"Point"}
}