{
  "type": "Feature",
  "properties": {
    "iso:country":"ES",
    "sg:address":"Ctra. Valverde, Km. 0007,3",
    "sg:city":"Valverde Leganes",
    "sg:orig_category":"Cr\u00cda De Animales",
    "sg:phone":"+34 924 14 03 28",
    "sg:postcode":"06130",
    "sg:province":"Badajoz",
    "wof:name":"Terron Diaz Luis",
    "wof:placetype":"venue"
},
  "geometry": {"coordinates":[-6.9808440208,38.6714248657],"type":"Point"}
}