{
  "type": "Feature",
  "properties": {
    "iso:country":"ES",
    "sg:address":"Calle de Santa Ana, 51",
    "sg:city":"Campo Criptana",
    "sg:orig_category":"Agencias Y Agentes Comerciales, Representantes",
    "sg:phone":"+34 926 56 06 65",
    "sg:postcode":"13610",
    "sg:province":"Ciudad Real",
    "wof:name":"Arteaga Sanchez Guijaldo Maria Angeles",
    "wof:placetype":"venue"
},
  "geometry": {"coordinates":[-3.1223015785,39.406627655],"type":"Point"}
}