{
  "type": "Feature",
  "properties": {
    "addr:full":"Calle de Don Ramon De La Cruz, 70 Madrid Madrid 28006",
    "addr:housenumber":"70",
    "addr:postcode":"madrid;28006",
    "addr:street":"Calle De Don Ramon De La Cruz",
    "iso:country":"ES",
    "sg:address":"Calle de Don Ramon De La Cruz, 70",
    "sg:city":"Madrid",
    "sg:orig_category":"Sales (al Por Mayor)",
    "sg:phone":"+34 914 01 09 65",
    "sg:postcode":"28006",
    "sg:province":"Madrid",
    "wof:name":"Barrio Arregui Jose",
    "wof:placetype":"venue"
},
  "geometry": {"coordinates":[-3.6751580238,40.4285354614],"type":"Point"}
}