{
  "type": "Feature",
  "properties": {
    "iso:country":"ES",
    "sg:address":"Calle de Guardia Civil, La, 1",
    "sg:city":"Valencia",
    "sg:orig_category":"Platos Preparados Refrigerados (fabricaci\u00d3n, Al Por Mayor)",
    "sg:phone":"+34 963 69 24 06",
    "sg:postcode":"46020",
    "sg:province":"Valencia",
    "wof:name":"Alimentacion Eusebi S.l.",
    "wof:placetype":"venue"
},
  "geometry": {"coordinates":[-0.3605970144,39.4829292297],"type":"Point"}
}