{
  "type": "Feature",
  "properties": {
    "iso:country":"ES",
    "sg:address":"Avenida Fraga Iribarne, 7",
    "sg:city":"Cari\u00f1o",
    "sg:orig_category":"Asociaciones, Organismos Culturales Y Socioeducativos",
    "sg:phone":"+34 981 40 56 67",
    "sg:postcode":"15360",
    "sg:province":"La Coru\u00f1a",
    "wof:name":"Asociacion De Amas De Casa Consumidores",
    "wof:placetype":"venue"
},
  "geometry": {"coordinates":[-7.8678956032,43.7406730652],"type":"Point"}
}