{
  "type": "Feature",
  "properties": {
    "iso:country":"ES",
    "sg:address":"Herriko Enparantza, 5",
    "sg:city":"Lekunberri",
    "sg:orig_category":"Promotores Constructores",
    "sg:phone":"+34 948 60 46 40",
    "sg:postcode":"31870",
    "sg:province":"Navarra",
    "wof:name":"Construcciones Lansalot Hermanos S.l.",
    "wof:placetype":"venue"
},
  "geometry": {"coordinates":[-1.8958569765,43.0048027039],"type":"Point"}
}