{
  "type": "Feature",
  "properties": {
    "addr:full":"Calle de Moncasi, 11 Zaragoza Zaragoza 50006",
    "addr:housenumber":"11",
    "addr:postcode":"50006",
    "addr:street":"Calle De Moncasi",
    "iso:country":"ES",
    "sg:address":"Calle de Moncasi, 11",
    "sg:city":"Zaragoza",
    "sg:orig_category":"Dietistas",
    "sg:phone":"+34 976 38 19 55",
    "sg:postcode":"50006",
    "sg:province":"Zaragoza",
    "wof:name":"Jimenez Bermudez Maria Pilar",
    "wof:placetype":"venue"
},
  "geometry": {"coordinates":[-0.8876109719,41.6414070129],"type":"Point"}
}