{
  "type": "Feature",
  "properties": {
    "iso:country":"ES",
    "sg:address":"Carrer de Pau Font De Rubinat, 36",
    "sg:city":"Reus",
    "sg:orig_category":"Carnicer\u00cdas, Carnicer\u00cdas",
    "sg:phone":"+34 977 31 27 49",
    "sg:postcode":"43202",
    "sg:province":"Tarragona",
    "wof:name":"Ciurana Rimbau Antonio",
    "wof:placetype":"venue"
},
  "geometry": {"coordinates":[1.0998979807,41.1516914368],"type":"Point"}
}