{
  "type": "Feature",
  "properties": {
    "addr:full":"Calle de Aragon, 16 Castellon Castell\u00f3n 12004",
    "addr:housenumber":"16",
    "addr:postcode":"12004",
    "addr:street":"Calle De Aragon",
    "iso:country":"ES",
    "sg:address":"Calle de Aragon, 16",
    "sg:city":"Castellon",
    "sg:orig_category":"Electricidad: Instaladores",
    "sg:phone":"+34 964 24 01 72",
    "sg:postcode":"12004",
    "sg:province":"Castell\u00f3n",
    "wof:name":"Automatismos Electricos Castellon S.l.",
    "wof:placetype":"venue"
},
  "geometry": {"coordinates":[-0.0427778997,39.9891090393],"type":"Point"}
}