{
  "type": "Feature",
  "properties": {
    "iso:country":"ES",
    "sg:address":"Calle de Poeta Diez Gavi\u00d1o, 2",
    "sg:city":"Portugalete",
    "sg:orig_category":"Librer\u00cdas",
    "sg:phone":"+34 944 62 51 51",
    "sg:postcode":"48920",
    "sg:province":"Vizcaya",
    "wof:name":"Maria Luisa Diez Herandez",
    "wof:placetype":"venue"
},
  "geometry": {"coordinates":[-3.0228619576,43.3185272217],"type":"Point"}
}