{
  "type": "Feature",
  "properties": {
    "addr:full":"Calle de Caballero De Rodas, 6 Torrevieja Alicante 03180",
    "addr:housenumber":"6",
    "addr:postcode":"03180",
    "addr:street":"Calle De Caballero De Rodas",
    "iso:country":"ES",
    "sg:address":"Calle de Caballero De Rodas, 6",
    "sg:city":"Torrevieja",
    "sg:orig_category":"Confecci\u00d3n (fabricaci\u00d3n, Al Por Mayor)",
    "sg:phone":"+34 965 71 28 04",
    "sg:postcode":"03180",
    "sg:province":"Alicante",
    "wof:name":"Albaladejo Garcia Jose Luis",
    "wof:placetype":"venue"
},
  "geometry": {"coordinates":[-0.6846886873,37.9777030945],"type":"Point"}
}