{
  "type": "Feature",
  "properties": {
    "iso:country":"ES",
    "sg:address":"Carrer de Lleida, 16",
    "sg:city":"S. Boi Llobregat",
    "sg:orig_category":"Empresas De Limpieza",
    "sg:phone":"+34 936 54 10 76",
    "sg:postcode":"08830",
    "sg:province":"Barcelona",
    "wof:name":"Arroyo Marce Francesc Xavier",
    "wof:placetype":"venue"
},
  "geometry": {"coordinates":[2.0319387913,41.3513946533],"type":"Point"}
}