{
  "type": "Feature",
  "properties": {
    "addr:full":"Bda Pontillon, 22 Castreli\u00d1os Pontevedra 36210",
    "addr:housenumber":"22",
    "addr:postcode":"36210",
    "addr:street":"Pontillon",
    "iso:country":"ES",
    "sg:address":"Bda Pontillon, 22",
    "sg:city":"Castreli\u00d1os",
    "sg:orig_category":"Aislamiento El\u00c9ctrico",
    "sg:phone":"+34 986 48 28 88",
    "sg:postcode":"36210",
    "sg:province":"Pontevedra",
    "wof:name":"Gallega De Aislamientos S.l.",
    "wof:placetype":"venue"
},
  "geometry": {"coordinates":[-8.6428003311,42.4304618835],"type":"Point"}
}