{
  "type": "Feature",
  "properties": {
    "addr:full":"Calle de Bidebarrieta, 1 Bilbao Vizcaya 48005",
    "addr:housenumber":"1",
    "addr:postcode":"48005",
    "addr:street":"Calle De Bidebarrieta",
    "iso:country":"ES",
    "sg:address":"Calle de Bidebarrieta, 1",
    "sg:city":"Bilbao",
    "sg:orig_category":"Asesor\u00cdas Y Estudios Financieros",
    "sg:phone":"+34 944 79 02 36",
    "sg:postcode":"48005",
    "sg:province":"Vizcaya",
    "wof:name":"Mu\u00f1oz Gomez Alejandro",
    "wof:placetype":"venue"
},
  "geometry": {"coordinates":[-2.9245612621,43.2591094971],"type":"Point"}
}