{
  "type": "Feature",
  "properties": {
    "addr:full":"Calle de Principe, 95 Quintanar Rey Cuenca 16220",
    "addr:housenumber":"95",
    "addr:postcode":"16220",
    "addr:street":"Calle De Principe",
    "iso:country":"ES",
    "sg:address":"Calle de Principe, 95",
    "sg:city":"Quintanar Rey",
    "sg:orig_category":"Producci\u00d3n De Champi\u00d1ones",
    "sg:phone":"+34 967 49 52 95",
    "sg:postcode":"16220",
    "sg:province":"Cuenca",
    "wof:name":"Champi\u00f1ones Y Setas Hermar S.l.",
    "wof:placetype":"venue"
},
  "geometry": {"coordinates":[-1.9292500019,39.3375205994],"type":"Point"}
}