{
  "type": "Feature",
  "properties": {
    "addr:full":"Urb. Guadalmina Alta, 1 San Pedro Alcantara M\u00e1laga 29670",
    "addr:housenumber":"1",
    "addr:postcode":"29670",
    "addr:street":"Guadalmina Alta",
    "iso:country":"ES",
    "sg:address":"Urb. Guadalmina Alta, 1",
    "sg:city":"San Pedro Alcantara",
    "sg:orig_category":"Inmobiliaria (agencias)",
    "sg:phone":"+34 952 88 08 26",
    "sg:postcode":"29670",
    "sg:province":"M\u00e1laga",
    "wof:name":"Antonio Gascon Consultores Inmobiliarios S.l.",
    "wof:placetype":"venue"
},
  "geometry": {"coordinates":[-4.9894766808,36.4856033325],"type":"Point"}
}