{
  "type": "Feature",
  "properties": {
    "addr:full":"Calle de Cantos (los), 9 Galapagar Madrid 28260",
    "addr:housenumber":"9",
    "addr:postcode":"28260",
    "addr:street":"Calle De Cantos Los",
    "iso:country":"ES",
    "sg:address":"Calle de Cantos (los), 9",
    "sg:city":"Galapagar",
    "sg:orig_category":"Fisioterapia",
    "sg:phone":"+34 918 59 73 13",
    "sg:postcode":"28260",
    "sg:province":"Madrid",
    "wof:name":"Axis Clinica Fisiotrapia S. L.",
    "wof:placetype":"venue"
},
  "geometry": {"coordinates":[-4.0043034554,40.576084137],"type":"Point"}
}