{
  "type": "Feature",
  "properties": {
    "iso:country":"ES",
    "sg:address":"Calle de Molinos, 21",
    "sg:city":"Aguilar De La Frontera",
    "sg:orig_category":"Promotores Constructores",
    "sg:phone":"+34 957 68 94 86",
    "sg:postcode":"14920",
    "sg:province":"C\u00f3rdoba",
    "wof:name":"Promociones Hermanos Luque Molina",
    "wof:placetype":"venue"
},
  "geometry": {"coordinates":[-4.6588139534,37.5171699524],"type":"Point"}
}