{
  "type": "Feature",
  "properties": {
    "iso:country":"ES",
    "sg:address":"Carrer de Viladomat, 109",
    "sg:city":"Barcelona",
    "sg:orig_category":"Minerales (al Por Mayor)",
    "sg:phone":"+34 933 25 00 28",
    "sg:postcode":"08015",
    "sg:province":"Barcelona",
    "wof:name":"Lobelisc S.l.",
    "wof:placetype":"venue"
},
  "geometry": {"coordinates":[2.1569480896,41.3797836304],"type":"Point"}
}