{
  "type": "Feature",
  "properties": {
    "addr:full":"Calle de Tesoro, 1 Santa Cristina De La Polvorosa Zamora 49620",
    "addr:housenumber":"1",
    "addr:postcode":"49620",
    "addr:street":"Calle De Tesoro;Zamora",
    "iso:country":"ES",
    "sg:address":"Calle de Tesoro, 1",
    "sg:city":"Santa Cristina De La Polvorosa",
    "sg:orig_category":"Peluquer\u00cdas, Peluquer\u00cda Mixta",
    "sg:phone":"+34 980 63 47 42",
    "sg:postcode":"49620",
    "sg:province":"Zamora",
    "wof:name":"Fidalgo Brime Nieves",
    "wof:placetype":"venue"
},
  "geometry": {"coordinates":[-5.7143750191,41.9956245422],"type":"Point"}
}