{
  "type": "Feature",
  "properties": {
    "iso:country":"ES",
    "sg:address":"Avda Republica Argentina, 29",
    "sg:city":"Le\u00f3n",
    "sg:orig_category":"Transporte En General",
    "sg:phone":"+34 987 21 04 29",
    "sg:postcode":"24004",
    "sg:province":"Le\u00f3n",
    "wof:name":"Distribuidora Internacional De Alimentacion S.a.",
    "wof:placetype":"venue"
},
  "geometry": {"coordinates":[-5.5757331848,42.5955352783],"type":"Point"}
}