{
  "type": "Feature",
  "properties": {
    "addr:full":"Avda Jablillo (el), S/n Costa Teguise Las Palmas 35509",
    "addr:housenumber":"/ n",
    "addr:postcode":"35509",
    "addr:street":"Avda Jablillo El S",
    "iso:country":"ES",
    "sg:address":"Avda Jablillo (el), S/n",
    "sg:city":"Costa Teguise",
    "sg:orig_category":"Alquiler De Veh\u00cdculos: Turismos Y Utilitarios",
    "sg:phone":"+34 928 59 16 74",
    "sg:postcode":"35509",
    "sg:province":"Las Palmas",
    "wof:name":"Anibal Y German S.l.",
    "wof:placetype":"venue"
},
  "geometry": {"coordinates":[-13.4968519211,28.9993591309],"type":"Point"}
}