{
  "type": "Feature",
  "properties": {
    "addr:full":"Calle de Diego Salinas, 25 Alcuescar C\u00e1ceres 10160",
    "addr:housenumber":"25",
    "addr:postcode":"10160",
    "addr:street":"Calle De Diego Salinas;Ca\u0301Ceres",
    "iso:country":"ES",
    "sg:address":"Calle de Diego Salinas, 25",
    "sg:city":"Alcuescar",
    "sg:orig_category":"Muebles, Minoristas",
    "sg:phone":"+34 927 38 40 70",
    "sg:postcode":"10160",
    "sg:province":"C\u00e1ceres",
    "wof:name":"Electromuebles Mogollon S.l.",
    "wof:placetype":"venue"
},
  "geometry": {"coordinates":[-6.2288341522,39.1805534363],"type":"Point"}
}