{
  "type": "Feature",
  "properties": {
    "iso:country":"ES",
    "sg:address":"Calle de Cartagena, S/n",
    "sg:city":"Espinardo",
    "sg:orig_category":"Reposter\u00cdas",
    "sg:phone":"+34 968 21 38 76",
    "sg:postcode":"30002",
    "sg:province":"Murcia",
    "wof:name":"Pan Natura Parra S.l.",
    "wof:placetype":"venue"
},
  "geometry": {"coordinates":[-1.1327700615,37.9788322449],"type":"Point"}
}