{
  "type": "Feature",
  "properties": {
    "addr:full":"Avda Pablo Gargallo, 39 Zaragoza Zaragoza 50003",
    "addr:housenumber":"39",
    "addr:postcode":"50003",
    "addr:street":"Avda Pablo Gargallo",
    "iso:country":"ES",
    "sg:address":"Avda Pablo Gargallo, 39",
    "sg:city":"Zaragoza",
    "sg:orig_category":"Bisuter\u00cda, Joyer\u00cda, Relojer\u00cda (al Por Menor)",
    "sg:phone":"+34 976 45 67 85",
    "sg:postcode":"50003",
    "sg:province":"Zaragoza",
    "wof:name":"Oro Universal S.l",
    "wof:placetype":"venue"
},
  "geometry": {"coordinates":[-0.8974789977,41.6603317261],"type":"Point"}
}