{
  "type": "Feature",
  "properties": {
    "addr:full":"Carr Jaume I, 42 Girona Girona 17001",
    "addr:housenumber":"42",
    "addr:postcode":"17001",
    "addr:street":"Carr Jaume I",
    "iso:country":"ES",
    "sg:address":"Carr Jaume I, 42",
    "sg:city":"Girona",
    "sg:orig_category":"Traductores",
    "sg:phone":"+34 972 21 21 11",
    "sg:postcode":"17001",
    "sg:province":"Girona",
    "sg:website":"www.traduaction.com",
    "wof:name":"Hortal Fernandez Isabel",
    "wof:placetype":"venue"
},
  "geometry": {"coordinates":[2.8195309639,41.9835014343],"type":"Point"}
}