{
  "type": "Feature",
  "properties": {
    "addr:full":"Carr Castellar, 23 Casc Urba Girona 17490",
    "addr:housenumber":"23;urba",
    "addr:postcode":"17490",
    "addr:street":"Carr Castellar",
    "iso:country":"ES",
    "sg:address":"Carr Castellar, 23",
    "sg:city":"Casc Urba",
    "sg:orig_category":"Librer\u00cdas",
    "sg:phone":"+34 972 38 00 22",
    "sg:postcode":"17490",
    "sg:province":"Girona",
    "wof:name":"Gros Suri\u00f1ach Jose Maria",
    "wof:placetype":"venue"
},
  "geometry": {"coordinates":[3.1481759548,42.3640785217],"type":"Point"}
}