{
  "type": "Feature",
  "properties": {
    "iso:country":"ES",
    "sg:address":"Calle de Mozart, 1",
    "sg:city":"Carmen",
    "sg:orig_category":"Loter\u00cda Y T\u00d3mbola",
    "sg:phone":"+34 968 34 63 01",
    "sg:postcode":"30002",
    "sg:province":"Murcia",
    "wof:name":"Moreno Ortiz Antonia",
    "wof:placetype":"venue"
},
  "geometry": {"coordinates":[-1.1302499771,37.9829597473],"type":"Point"}
}