{
  "type": "Feature",
  "properties": {
    "addr:full":"Avda Pablo Picasso, 26 Granada Granada 18006",
    "addr:housenumber":"26",
    "addr:postcode":"18006",
    "addr:street":"Avda Pablo Picasso",
    "iso:country":"ES",
    "sg:address":"Avda Pablo Picasso, 26",
    "sg:city":"Granada",
    "sg:orig_category":"Cajas De Ahorro",
    "sg:phone":"+34 958 13 26 82",
    "sg:postcode":"18006",
    "sg:province":"Granada",
    "wof:name":"Caixa D'estalvis I Pensions De Barcelona",
    "wof:placetype":"venue"
},
  "geometry": {"coordinates":[-3.5945870876,37.1647377014],"type":"Point"}
}