{
  "type": "Feature",
  "properties": {
    "iso:country":"ES",
    "sg:address":"Carrer de Lloren\u00c7 Cerda, 2",
    "sg:city":"Palma",
    "sg:orig_category":"Doctores En Medicina",
    "sg:phone":"+34 971 29 01 34",
    "sg:postcode":"07012",
    "sg:province":"Islas Baleares",
    "wof:name":"Pons Vidal Salvador",
    "wof:placetype":"venue"
},
  "geometry": {"coordinates":[2.6470320225,39.5776329041],"type":"Point"}
}