{
  "type": "Feature",
  "properties": {
    "iso:country":"ES",
    "sg:address":"Calle de Pe\u00d1a, 1",
    "sg:city":"Malaga",
    "sg:orig_category":"Fabricaci\u00d3n, Venta De Productos Base Farmac\u00c9uticos",
    "sg:phone":"+34 952 21 21 21",
    "sg:postcode":"29012",
    "sg:province":"M\u00e1laga",
    "wof:name":"Cabiale Lecea Josefina",
    "wof:placetype":"venue"
},
  "geometry": {"coordinates":[-4.4197049141,36.7249946594],"type":"Point"}
}