{
  "type": "Feature",
  "properties": {
    "addr:full":"Barr Arriandi, 31 Arriandi Vizcaya 48215",
    "addr:housenumber":"31",
    "addr:postcode":"48215",
    "addr:street":"Arriandi",
    "iso:country":"ES",
    "sg:address":"Barr Arriandi, 31",
    "sg:city":"Arriandi",
    "sg:orig_category":"Delegados, Agentes De Tr\u00c1nsito, Auxiliares De Transporte Internacional",
    "sg:phone":"+34 946 81 00 87",
    "sg:postcode":"48215",
    "sg:province":"Vizcaya",
    "wof:name":"Aguirrezabal Maistegui Jose Julian",
    "wof:placetype":"venue"
},
  "geometry": {"coordinates":[-2.6607964039,43.1831130981],"type":"Point"}
}