{
  "type": "Feature",
  "properties": {
    "addr:full":"Calle de Camino De Malaga, S/n Humanes Guadalajara 19220",
    "addr:postcode":"19220",
    "addr:street":"Calle De Camino De Malaga S / N",
    "iso:country":"ES",
    "sg:address":"Calle de Camino De Malaga, S/n",
    "sg:city":"Humanes",
    "sg:orig_category":"Negocio De Materiales De Construcci\u00d3n",
    "sg:phone":"+34 949 85 11 49",
    "sg:postcode":"19220",
    "sg:province":"Guadalajara",
    "wof:name":"Coello Lopez Victor Manuel",
    "wof:placetype":"venue"
},
  "geometry": {"coordinates":[-3.1478514671,40.845161438],"type":"Point"}
}