{
  "type": "Feature",
  "properties": {
    "addr:full":"Calle de Saturno, 1 Cordoba C\u00f3rdoba 14014",
    "addr:housenumber":"1",
    "addr:postcode":"14014",
    "addr:street":"Calle De Saturno;Co\u0301Rdoba",
    "iso:country":"ES",
    "sg:address":"Calle de Saturno, 1",
    "sg:city":"Cordoba",
    "sg:classifiers":[
        {
            "category":"Autos & Motor Vehicles",
            "subcategory":"Automobile Sales",
            "type":"Retail Goods"
        }
    ],
    "sg:phone":"+34 957 44 21 47",
    "sg:postcode":"14014",
    "sg:province":"C\u00f3rdoba",
    "wof:name":"Autoescuela Gavilan S.l.",
    "wof:placetype":"venue"
},
  "geometry": {"coordinates":[-4.7526025772,37.8920021057],"type":"Point"}
}