{
  "type": "Feature",
  "properties": {
    "iso:country":"ES",
    "sg:address":"Pase Marques De Zafra, 64",
    "sg:city":"Madrid",
    "sg:orig_category":"M\u00c9dicos: Estomatolog\u00cda",
    "sg:phone":"+34 917 26 22 65",
    "sg:postcode":"28028",
    "sg:province":"Madrid",
    "wof:name":"Garcia Arribas Jesus",
    "wof:placetype":"venue"
},
  "geometry": {"coordinates":[-3.6617481709,40.4249572754],"type":"Point"}
}