{
  "type": "Feature",
  "properties": {
    "addr:full":"Carrer de Creu Roja, 25 Hospitalet Llobregat Barcelona 08904",
    "addr:housenumber":"25",
    "addr:postcode":"08904",
    "addr:street":"Carrer De Creu Roja",
    "iso:country":"ES",
    "sg:address":"Carrer de Creu Roja, 25",
    "sg:city":"Hospitalet Llobregat",
    "sg:orig_category":"Cl\u00cdnicas Dentales",
    "sg:phone":"+34 934 48 33 66",
    "sg:postcode":"08904",
    "sg:province":"Barcelona",
    "wof:name":"Asodent 2000 S.l.l.",
    "wof:placetype":"venue"
},
  "geometry": {"coordinates":[2.1161224842,41.3744430542],"type":"Point"}
}