{
  "type": "Feature",
  "properties": {
    "iso:country":"ES",
    "sg:address":"Calle de Cardenal Torquemada, 22",
    "sg:city":"Valladolid",
    "sg:orig_category":"Tiendas De Grano, Frutas Y Legumbres Secas (al Por Menor)",
    "sg:phone":"+34 983 25 13 99",
    "sg:postcode":"47010",
    "sg:province":"Valladolid",
    "wof:name":"Pe\u00f1a Gallego Agustin",
    "wof:placetype":"venue"
},
  "geometry": {"coordinates":[-4.7240934372,41.6610794067],"type":"Point"}
}