{
  "type": "Feature",
  "properties": {
    "addr:full":"Avda Madrid De, 11 Donostia-san Sebastian Guip\u00f9zcoa 20011",
    "addr:housenumber":"11",
    "addr:postcode":"20011",
    "addr:street":"Avda Madrid De",
    "iso:country":"ES",
    "sg:address":"Avda Madrid De, 11",
    "sg:city":"Donostia-san Sebastian",
    "sg:orig_category":"Laboratorios Y Trabajos De Fotograf\u00cda, V\u00cddeo Y Cine",
    "sg:phone":"+34 943 46 54 31",
    "sg:postcode":"20011",
    "sg:province":"Guip\u00f9zcoa",
    "wof:name":"Javier Maturana S.l.",
    "wof:placetype":"venue"
},
  "geometry": {"coordinates":[-1.9765770435,43.3045654297],"type":"Point"}
}