{
  "type": "Feature",
  "properties": {
    "addr:full":"Auditor Bohorquez, S/n Cortes De La Frontera M\u00e1laga 29380",
    "addr:housenumber":"s / n",
    "addr:postcode":"29380",
    "iso:country":"ES",
    "sg:address":"Auditor Bohorquez, S/n",
    "sg:city":"Cortes De La Frontera",
    "sg:orig_category":"Iglesia Cat\u00d3lica",
    "sg:phone":"+34 952 15 41 35",
    "sg:postcode":"29380",
    "sg:province":"M\u00e1laga",
    "wof:name":"Obispado De Malaga",
    "wof:placetype":"venue"
},
  "geometry": {"coordinates":[-5.342359066,36.6176948547],"type":"Point"}
}