{
  "type": "Feature",
  "properties": {
    "iso:country":"ES",
    "sg:address":"Avda Federico Garcia Lorca, 7",
    "sg:city":"Nijar",
    "sg:orig_category":"Molduras, Junquillos, Listones Y Molduras Perforadas",
    "sg:phone":"+34 950 36 02 93",
    "sg:postcode":"04100",
    "sg:province":"Almer\u00eda",
    "wof:name":"Hernandez Gongora Dolores",
    "wof:placetype":"venue"
},
  "geometry": {"coordinates":[-2.2073380947,36.9640731812],"type":"Point"}
}