{
  "type": "Feature",
  "properties": {
    "addr:full":"Carrer de Josep Domenech, 10 Cabrera Mar Barcelona 08349",
    "addr:housenumber":"10",
    "addr:postcode":"08349",
    "addr:street":"Carrer De Josep Domenech",
    "iso:country":"ES",
    "sg:address":"Carrer de Josep Domenech, 10",
    "sg:city":"Cabrera Mar",
    "sg:orig_category":"Restaurantes",
    "sg:phone":"+34 937 59 34 83",
    "sg:postcode":"08349",
    "sg:province":"Barcelona",
    "wof:name":"Catering Hepburn S.l.",
    "wof:placetype":"venue"
},
  "geometry": {"coordinates":[2.3928380013,41.5229263306],"type":"Point"}
}