{
  "type": "Feature",
  "properties": {
    "addr:full":"Calle de Azahar, 8 Alora M\u00e1laga 29500",
    "addr:housenumber":"8",
    "addr:postcode":"29500",
    "addr:street":"Calle De Azahar;Ma\u0301Laga",
    "iso:country":"ES",
    "sg:address":"Calle de Azahar, 8",
    "sg:city":"Alora",
    "sg:orig_category":"Agencias Y Agentes Comerciales, Representantes",
    "sg:phone":"+34 952 49 56 16",
    "sg:postcode":"29500",
    "sg:province":"M\u00e1laga",
    "wof:name":"Sanchez Martin Carmen",
    "wof:placetype":"venue"
},
  "geometry": {"coordinates":[-4.7045321465,36.8261642456],"type":"Point"}
}