{
  "type": "Feature",
  "properties": {
    "iso:country":"ES",
    "sg:address":"Plaz Espa\u00d1a (de), 5",
    "sg:city":"Cebreros",
    "sg:orig_category":"Inmobiliaria (agencias)",
    "sg:phone":"+34 918 63 06 67",
    "sg:postcode":"05260",
    "sg:province":"\u00c1vila",
    "wof:name":"Garcia Mu\u00f1oz Maria Belen",
    "wof:placetype":"venue"
},
  "geometry": {"coordinates":[-4.4182090759,40.4488563538],"type":"Point"}
}