{
  "type": "Feature",
  "properties": {
    "iso:country":"ES",
    "sg:address":"Calle de Gregorio Mendibil, 8",
    "sg:city":"Amorebieta",
    "sg:orig_category":"Restaurantes",
    "sg:phone":"+34 946 73 00 25",
    "sg:postcode":"48340",
    "sg:province":"Vizcaya",
    "wof:name":"Restaurante El Cojo S.l.",
    "wof:placetype":"venue"
},
  "geometry": {"coordinates":[-2.731112957,43.2193374634],"type":"Point"}
}