{
  "type": "Feature",
  "properties": {
    "iso:country":"ES",
    "sg:address":"Pla\u00c7 Joan Sansa, 13",
    "sg:city":"Seu D'urgell",
    "sg:orig_category":"M\u00c9dicos: Cirug\u00cda General",
    "sg:phone":"+34 973 35 39 39",
    "sg:postcode":"25700",
    "sg:province":"Lleida",
    "wof:name":"Aixas Obiols Joan",
    "wof:placetype":"venue"
},
  "geometry": {"coordinates":[1.4579695463,42.3600082397],"type":"Point"}
}