{
  "type": "Feature",
  "properties": {
    "iso:country":"ES",
    "sg:address":"Calle de Castelar, 13",
    "sg:city":"Zaragoza",
    "sg:orig_category":"Empresas De Carpinter\u00cda",
    "sg:phone":"+34 976 41 31 95",
    "sg:postcode":"50013",
    "sg:province":"Zaragoza",
    "wof:name":"Gimeno Lecha Manuel",
    "wof:placetype":"venue"
},
  "geometry": {"coordinates":[-0.8728426099,41.6407814026],"type":"Point"}
}