{
  "type": "Feature",
  "properties": {
    "addr:full":"Itturrin, 53 Lezo Guip\u00f9zcoa 20100",
    "addr:housenumber":"53",
    "addr:postcode":"20100",
    "addr:street":"Itturrin;Guipu\u0300Zcoa",
    "iso:country":"ES",
    "sg:address":"Itturrin, 53",
    "sg:city":"Lezo",
    "sg:orig_category":"Materias Pl\u00c1sticas: Productos Para Industria Y Agricultura (fabricaci\u00d3n, Al Por Mayor)",
    "sg:phone":"+34 943 49 33 60",
    "sg:postcode":"20100",
    "sg:province":"Guip\u00f9zcoa",
    "wof:name":"Plasticos Clossa S.l.",
    "wof:placetype":"venue"
},
  "geometry": {"coordinates":[-1.8681579828,43.3219070435],"type":"Point"}
}