{
  "type": "Feature",
  "properties": {
    "iso:country":"ES",
    "sg:address":"Calle de Do\u00d1a Mencia, 29",
    "sg:city":"Madrid",
    "sg:orig_category":"Fisioterapia",
    "sg:phone":"+34 914 64 59 48",
    "sg:postcode":"28011",
    "sg:province":"Madrid",
    "wof:name":"Up-r Masajes S.l.",
    "wof:placetype":"venue"
},
  "geometry": {"coordinates":[-3.7288970947,40.4102516174],"type":"Point"}
}