{
  "type": "Feature",
  "properties": {
    "addr:full":"Carr Santa Anna, 60 Estartit Girona 17258",
    "addr:housenumber":"60",
    "addr:postcode":"17258",
    "addr:street":"Carr Santa Anna",
    "iso:country":"ES",
    "sg:address":"Carr Santa Anna, 60",
    "sg:city":"Estartit",
    "sg:orig_category":"Asociaciones Y Clubs Deportivos",
    "sg:phone":"+34 972 75 18 15",
    "sg:postcode":"17258",
    "sg:province":"Girona",
    "wof:name":"Prats Massaguer Pelegri",
    "wof:placetype":"venue"
},
  "geometry": {"coordinates":[3.1878299713,42.0489959717],"type":"Point"}
}