{
  "type": "Feature",
  "properties": {
    "addr:full":"Calle de Eras, 1 Pinos-genil Granada 18191",
    "addr:housenumber":"1",
    "addr:postcode":"18191",
    "addr:street":"Calle De Eras",
    "iso:country":"ES",
    "sg:address":"Calle de Eras, 1",
    "sg:city":"Pinos-genil",
    "sg:orig_category":"Metalurgia",
    "sg:phone":"+34 958 48 88 16",
    "sg:postcode":"18191",
    "sg:province":"Granada",
    "wof:name":"Quiros Garcia Jorge",
    "wof:placetype":"venue"
},
  "geometry": {"coordinates":[-3.5016279221,37.1624717712],"type":"Point"}
}