{
  "type": "Feature",
  "properties": {
    "addr:full":"Carrer de Sant Miquel, 63 Palma Islas Baleares 07002",
    "addr:housenumber":"63",
    "addr:postcode":"07002",
    "addr:street":"Carrer De Sant Miquel",
    "iso:country":"ES",
    "sg:address":"Carrer de Sant Miquel, 63",
    "sg:city":"Palma",
    "sg:orig_category":"Ropa Para Se\u00d1oras Y Caballeros (al Por Menor)",
    "sg:phone":"+34 971 72 33 74",
    "sg:postcode":"07002",
    "sg:province":"Islas Baleares",
    "wof:name":"Passarel La Comunidad De Bienes",
    "wof:placetype":"venue"
},
  "geometry": {"coordinates":[2.652050972,39.5748977661],"type":"Point"}
}