{
  "type": "Feature",
  "properties": {
    "addr:full":"Carr Manuel Lopez Varela (de), 4 Lliria Valencia 46160",
    "addr:postcode":"46160",
    "addr:street":"Carr Manuel;Varela",
    "iso:country":"ES",
    "sg:address":"Carr Manuel Lopez Varela (de), 4",
    "sg:city":"Lliria",
    "sg:orig_category":"Carnicer\u00cdas, Carnicer\u00cdas",
    "sg:phone":"+34 962 79 24 74",
    "sg:postcode":"46160",
    "sg:province":"Valencia",
    "wof:name":"Porcar Merenciano Juan Bautista",
    "wof:placetype":"venue"
},
  "geometry": {"coordinates":[-0.59424299,39.6328430176],"type":"Point"}
}