{
  "type": "Feature",
  "properties": {
    "addr:full":"Calle de Vallehermoso, 50 Madrid Madrid 28015",
    "addr:housenumber":"50",
    "addr:postcode":"madrid;28015",
    "addr:street":"Calle De Vallehermoso",
    "iso:country":"ES",
    "sg:address":"Calle de Vallehermoso, 50",
    "sg:city":"Madrid",
    "sg:orig_category":"Institutos De Belleza",
    "sg:phone":"+34 914 45 40 86",
    "sg:postcode":"28015",
    "sg:province":"Madrid",
    "wof:name":"Muntion De La Rosa Margarita",
    "wof:placetype":"venue"
},
  "geometry": {"coordinates":[-3.708368063,40.4356307983],"type":"Point"}
}