{
  "type": "Feature",
  "properties": {
    "addr:full":"Calle de Carril De Cuenca, 4 Adra Almer\u00eda 04770",
    "addr:housenumber":"4",
    "addr:postcode":"04770",
    "addr:street":"Calle De Carril De Cuenca;Almeri\u0301A",
    "iso:country":"ES",
    "sg:address":"Calle de Carril De Cuenca, 4",
    "sg:city":"Adra",
    "sg:orig_category":"Ropa Para Se\u00d1oras (al Por Menor)",
    "sg:phone":"+34 950 60 41 64",
    "sg:postcode":"04770",
    "sg:province":"Almer\u00eda",
    "wof:name":"Payan Petaez Maria Trinidad",
    "wof:placetype":"venue"
},
  "geometry": {"coordinates":[-3.0181884766,36.7480049133],"type":"Point"}
}