{
  "type": "Feature",
  "properties": {
    "iso:country":"ES",
    "sg:address":"Avda Coria, 7",
    "sg:city":"Palomares Rio",
    "sg:orig_category":"Inmobiliaria (agencias)",
    "sg:phone":"+34 955 76 36 93",
    "sg:postcode":"41928",
    "sg:province":"Sevilla",
    "wof:name":"Sanchez Sanchez Maria Teresa",
    "wof:placetype":"venue"
},
  "geometry": {"coordinates":[-6.0594902039,37.3214569092],"type":"Point"}
}