{
  "type": "Feature",
  "properties": {
    "iso:country":"ES",
    "sg:address":"Calle de Molino De La Marquesa, 10",
    "sg:city":"Valencia",
    "sg:orig_category":"Ropa Y Accesorios",
    "sg:phone":"+34 963 47 26 01",
    "sg:postcode":"46015",
    "sg:province":"Valencia",
    "sg:website":"www.chescoxips.com",
    "wof:name":"Accesorios De Moda S. A.",
    "wof:placetype":"venue"
},
  "geometry": {"coordinates":[-0.3981209099,39.4838485718],"type":"Point"}
}