{
  "type": "Feature",
  "properties": {
    "iso:country":"ES",
    "sg:address":"Calle de Carlos Gangoiti, 19",
    "sg:city":"Gernika-lumo",
    "sg:orig_category":"Restaurantes",
    "sg:phone":"+34 946 25 42 20",
    "sg:postcode":"48300",
    "sg:province":"Vizcaya",
    "wof:name":"Lejarcegui Inunciaga Jesus",
    "wof:placetype":"venue"
},
  "geometry": {"coordinates":[-2.6795887947,43.318977356],"type":"Point"}
}