{
  "type": "Feature",
  "properties": {
    "addr:full":"Calle de Mula, 16 Torres Cotillas Murcia 30565",
    "addr:housenumber":"16",
    "addr:postcode":"30565",
    "addr:street":"Calle De Mula",
    "iso:country":"ES",
    "sg:address":"Calle de Mula, 16",
    "sg:city":"Torres Cotillas",
    "sg:orig_category":"Cadenas, Estaciones, Cableados Para Radio Y Televisi\u00d3n",
    "sg:phone":"+34 968 62 34 72",
    "sg:postcode":"30565",
    "sg:province":"Murcia",
    "wof:name":"Telecable Las Torres S.l.",
    "wof:placetype":"venue"
},
  "geometry": {"coordinates":[-1.2423969507,38.0321350098],"type":"Point"}
}