{
  "type": "Feature",
  "properties": {
    "iso:country":"ES",
    "sg:address":"Plaz San Francisco, 7",
    "sg:city":"Cartagena",
    "sg:orig_category":"Procuradores",
    "sg:phone":"+34 968 52 88 77",
    "sg:postcode":"30201",
    "sg:province":"Murcia",
    "wof:name":"Ortega Parra Joaquin",
    "wof:placetype":"venue"
},
  "geometry": {"coordinates":[-0.8610739708,37.719329834],"type":"Point"}
}