{
  "type": "Feature",
  "properties": {
    "addr:full":"Rua Quintian, 59 Ourense Ourense 32001",
    "addr:housenumber":"59",
    "addr:postcode":"32001",
    "addr:street":"Rua Quintian",
    "iso:country":"ES",
    "sg:address":"Rua Quintian, 59",
    "sg:city":"Ourense",
    "sg:orig_category":"Bastidores",
    "sg:phone":"+34 988 21 17 82",
    "sg:postcode":"32001",
    "sg:province":"Ourense",
    "sg:website":"www.remolquesaraujo.com",
    "wof:name":"Jose Martinez Araujo S.l.",
    "wof:placetype":"venue"
},
  "geometry": {"coordinates":[-7.8707761765,42.3525543213],"type":"Point"}
}