{
  "type": "Feature",
  "properties": {
    "addr:full":"Calle de Donantes De Sangre, 85 Coru\u00d1a La Coru\u00f1a 15...",
    "addr:housenumber":"85;15 ...",
    "addr:street":"Calle De Donantes De Sangre;Corun\u0303A",
    "iso:country":"ES",
    "sg:address":"Calle de Donantes De Sangre, 85",
    "sg:city":"Coru\u00d1a",
    "sg:classifiers":[
        {
            "category":"Professional",
            "subcategory":"Research",
            "type":"Services"
        }
    ],
    "sg:phone":"+34 981 16 73 00",
    "sg:postcode":"15...",
    "sg:province":"La Coru\u00f1a",
    "sg:tags":[
        "mercado",
        "de",
        "estudios"
    ],
    "wof:name":"Instituto Sondaxe S.l.",
    "wof:placetype":"venue"
},
  "geometry": {"coordinates":[-8.4097719193,43.3656082153],"type":"Point"}
}