{
  "type": "Feature",
  "properties": {
    "addr:full":"Pase Carlos Era\u00d1a, 38 Ciudad Real Ciudad Real 13004",
    "addr:housenumber":"38",
    "addr:postcode":"13004",
    "addr:street":"Eran\u0303A",
    "iso:country":"ES",
    "sg:address":"Pase Carlos Era\u00d1a, 38",
    "sg:city":"Ciudad Real",
    "sg:orig_category":"M\u00c9dicos: Cirug\u00cda Urol\u00d3gica",
    "sg:phone":"+34 926 25 28 28",
    "sg:postcode":"13004",
    "sg:province":"Ciudad Real",
    "wof:name":"Rodriguez Leal Diego Alberto",
    "wof:placetype":"venue"
},
  "geometry": {"coordinates":[-3.9301741123,38.9844093323],"type":"Point"}
}