{
  "type": "Feature",
  "properties": {
    "addr:full":"Calle de Mula, S/n Torres Cotillas Murcia 30565",
    "addr:housenumber":"s / n",
    "addr:postcode":"30565",
    "addr:street":"Calle De Mula",
    "iso:country":"ES",
    "sg:address":"Calle de Mula, S/n",
    "sg:city":"Torres Cotillas",
    "sg:orig_category":"Panader\u00cdas, Pasteler\u00cdas, Boller\u00cda Industriale (fabricaci\u00d3n, Al Por Mayor)",
    "sg:phone":"+34 968 62 63 64",
    "sg:postcode":"30565",
    "sg:province":"Murcia",
    "wof:name":"Confiletas S.l.",
    "wof:placetype":"venue"
},
  "geometry": {"coordinates":[-1.2483240366,38.0309638977],"type":"Point"}
}