{
  "type": "Feature",
  "properties": {
    "addr:full":"C/ Ntra. Sra. Dels Angels, 20 Ripollet Barcelona 08291",
    "addr:housenumber":"20",
    "addr:postcode":"08291",
    "addr:street":"C / Ntra. Sra. Dels Angels",
    "iso:country":"ES",
    "sg:address":"C/ Ntra. Sra. Dels Angels, 20",
    "sg:city":"Ripollet",
    "sg:orig_category":"Cr\u00cda De Animales",
    "sg:phone":"+34 935 94 00 44",
    "sg:postcode":"08291",
    "sg:province":"Barcelona",
    "wof:name":"Puerto Garcia Susana",
    "wof:placetype":"venue"
},
  "geometry": {"coordinates":[2.1504809856,41.4926795959],"type":"Point"}
}