{
  "type": "Feature",
  "properties": {
    "addr:full":"Zuaznabar Kalea, 49 Ugaldetxo Guip\u00f9zcoa 20180",
    "addr:housenumber":"49",
    "addr:postcode":"20180",
    "addr:street":"Zuaznabar Kalea;Guipu\u0300Zcoa",
    "iso:country":"ES",
    "sg:address":"Zuaznabar Kalea, 49",
    "sg:city":"Ugaldetxo",
    "sg:orig_category":"Torrefactado De Caf\u00c9",
    "sg:phone":"+34 943 49 16 42",
    "sg:postcode":"20180",
    "sg:province":"Guip\u00f9zcoa",
    "wof:name":"Juan Iriondo S.a.",
    "wof:placetype":"venue"
},
  "geometry": {"coordinates":[-1.8629590273,43.2992401123],"type":"Point"}
}