{
  "type": "Feature",
  "properties": {
    "addr:full":"Ctra Almazora/grao Cs A Termino Almazora, 97 Grao Castell\u00f3n 12100",
    "addr:housenumber":"97",
    "addr:postcode":"12100",
    "addr:street":"Ctra Almazora / Grao;Almazora",
    "iso:country":"ES",
    "sg:address":"Ctra Almazora/grao Cs A Termino Almazora, 97",
    "sg:city":"Grao",
    "sg:orig_category":"Reciclaje, Desguace De Veh\u00cdculos",
    "sg:phone":"+34 964 28 10 51",
    "sg:postcode":"12100",
    "sg:province":"Castell\u00f3n",
    "wof:name":"Fernandez Varela Jose Maria",
    "wof:placetype":"venue"
},
  "geometry": {"coordinates":[0.0176999997,39.9888801575],"type":"Point"}
}