{
  "type": "Feature",
  "properties": {
    "addr:full":"Calle de America, 1 Villanueva Arzobispo Ja\u00e9n 23330",
    "addr:housenumber":"1",
    "addr:postcode":"23330",
    "addr:street":"Calle De America",
    "iso:country":"ES",
    "sg:address":"Calle de America, 1",
    "sg:city":"Villanueva Arzobispo",
    "sg:orig_category":"Molduras, Junquillos, Listones Y Molduras Perforadas",
    "sg:phone":"+34 953 45 11 24",
    "sg:postcode":"23330",
    "sg:province":"Ja\u00e9n",
    "wof:name":"Carcelen Hurtado Agustin",
    "wof:placetype":"venue"
},
  "geometry": {"coordinates":[-3.0091657639,38.1712646484],"type":"Point"}
}