{
  "type": "Feature",
  "properties": {
    "iso:country":"ES",
    "sg:address":"Calle de San Francisco Javier, 6",
    "sg:city":"Obanos",
    "sg:orig_category":"Centros De Coordinaci\u00d3n",
    "sg:phone":"+34 948 34 44 24",
    "sg:postcode":"31151",
    "sg:province":"Navarra",
    "wof:name":"Mancomunidad De Servicios Administrativos Valdizarbe",
    "wof:placetype":"venue"
},
  "geometry": {"coordinates":[-1.7866710424,42.6785697937],"type":"Point"}
}