{
  "type": "Feature",
  "properties": {
    "iso:country":"ES",
    "sg:address":"Calle de Padre Fernando Casanova Benlloch, S.j., 8",
    "sg:city":"Valencia",
    "sg:orig_category":"Asesor\u00cda Fiscal Y Jur\u00cddica",
    "sg:phone":"+34 963 40 68 96",
    "sg:postcode":"46015",
    "sg:province":"Valencia",
    "wof:name":"Buenaventura-nicolau Abogados, C.b.",
    "wof:placetype":"venue"
},
  "geometry": {"coordinates":[-0.3959150016,39.4876098633],"type":"Point"}
}