{
  "type": "Feature",
  "properties": {
    "addr:full":"Carrer de Folch I Torres, 16 Tordera Barcelona 08490",
    "addr:housenumber":"16",
    "addr:postcode":"08490",
    "addr:street":"Carrer De Folch I Torres",
    "iso:country":"ES",
    "sg:address":"Carrer de Folch I Torres, 16",
    "sg:city":"Tordera",
    "sg:orig_category":"Cajas De Ahorro",
    "sg:phone":"+34 937 64 26 39",
    "sg:postcode":"08490",
    "sg:province":"Barcelona",
    "wof:name":"Caixa D'estalvis Sabadell",
    "wof:placetype":"venue"
},
  "geometry": {"coordinates":[2.7194650173,41.6988487244],"type":"Point"}
}