{
  "type": "Feature",
  "properties": {
    "iso:country":"ES",
    "sg:address":"Calle de Real, 25",
    "sg:city":"Iznajar",
    "sg:orig_category":"Mercer\u00cda, Lencer\u00cda (al Por Menor)",
    "sg:phone":"+34 957 53 40 05",
    "sg:postcode":"14970",
    "sg:province":"C\u00f3rdoba",
    "wof:name":"Villalba Rosua Clemente",
    "wof:placetype":"venue"
},
  "geometry": {"coordinates":[-4.3073248863,37.2566375732],"type":"Point"}
}