{
  "type": "Feature",
  "properties": {
    "iso:country":"ES",
    "sg:address":"Cmno Mitxine, 1",
    "sg:city":"Basozabal",
    "sg:orig_category":"Zapater\u00cds Y Cordeler\u00cda",
    "sg:phone":"+34 944 71 18 15",
    "sg:postcode":"48150",
    "sg:province":"Vizcaya",
    "wof:name":"Antillera Diez Jose Ramon",
    "wof:placetype":"venue"
},
  "geometry": {"coordinates":[-2.9270398617,43.2985038757],"type":"Point"}
}