{
  "type": "Feature",
  "properties": {
    "addr:full":"Avda Flores (las), S/n Algeciras C\u00e1diz 11204",
    "addr:postcode":"11204",
    "addr:street":"Avda Flores Las S / N;Ca\u0301Diz",
    "iso:country":"ES",
    "sg:address":"Avda Flores (las), S/n",
    "sg:city":"Algeciras",
    "sg:orig_category":"Centros De Educaci\u00d3n Especial",
    "sg:phone":"+34 956 65 23 01",
    "sg:postcode":"11204",
    "sg:province":"C\u00e1diz",
    "wof:name":"Junta De Andalucia-ceip Adalides",
    "wof:placetype":"venue"
},
  "geometry": {"coordinates":[-5.4604430199,36.1489028931],"type":"Point"}
}