{
  "type": "Feature",
  "properties": {
    "addr:full":"Calle de Pio Xii, S/n Churriana Vega Granada 18194",
    "addr:housenumber":"s / n",
    "addr:postcode":"18194",
    "addr:street":"Calle De Pio Xii",
    "iso:country":"ES",
    "sg:address":"Calle de Pio Xii, S/n",
    "sg:city":"Churriana Vega",
    "sg:orig_category":"Construcciones Met\u00c1licas",
    "sg:phone":"+34 958 57 84 67",
    "sg:postcode":"18194",
    "sg:province":"Granada",
    "wof:name":"Hinojosa Lopez Isidro",
    "wof:placetype":"venue"
},
  "geometry": {"coordinates":[-3.6437540054,37.1438140869],"type":"Point"}
}