{
  "type": "Feature",
  "properties": {
    "addr:full":"Av Maresme, 72 Almeda Mercader Barcelona 08940",
    "addr:housenumber":"72",
    "addr:postcode":"08940",
    "addr:street":"Av Maresme;Mercader Barcelona",
    "iso:country":"ES",
    "sg:address":"Av Maresme, 72",
    "sg:city":"Almeda Mercader",
    "sg:orig_category":"Agencias Y Agentes Comerciales, Representantes",
    "sg:phone":"+34 933 77 91 37",
    "sg:postcode":"08940",
    "sg:province":"Barcelona",
    "wof:name":"T.g. Promociones Representaciones S.a.",
    "wof:placetype":"venue"
},
  "geometry": {"coordinates":[2.0740599632,41.356880188],"type":"Point"}
}