{
  "type": "Feature",
  "properties": {
    "iso:country":"ES",
    "sg:address":"Calle de Reyes Magos, 18",
    "sg:city":"Madrid",
    "sg:orig_category":"Reparaci\u00d3n Y Restauraci\u00d3n De Objetos Diversos",
    "sg:phone":"+34 914 33 50 60",
    "sg:postcode":"28009",
    "sg:province":"Madrid",
    "wof:name":"Rember Iberica S. A.",
    "wof:placetype":"venue"
},
  "geometry": {"coordinates":[-3.6750690937,40.4109382629],"type":"Point"}
}