{
  "type": "Feature",
  "properties": {
    "iso:country":"ES",
    "sg:address":"Ctra. Almaden, Km. 0292,6",
    "sg:city":"Valdemanco Del Esteras",
    "sg:orig_category":"Agricultura: Abastecimiento Y Cosechado (negocio)",
    "sg:phone":"+34 926 69 20 02",
    "sg:postcode":"13411",
    "sg:province":"Ciudad Real",
    "wof:name":"Aliseda Blasco Maria Isabel",
    "wof:placetype":"venue"
},
  "geometry": {"coordinates":[-4.7928128242,38.8579368591],"type":"Point"}
}