{
  "type": "Feature",
  "properties": {
    "iso:country":"ES",
    "sg:address":"Calle de Gudari, 10",
    "sg:city":"Irun",
    "sg:orig_category":"Arquitectos",
    "sg:phone":"+34 943 62 63 42",
    "sg:postcode":"20302",
    "sg:province":"Guip\u00f9zcoa",
    "wof:name":"Jesus Gracenea Echegoyen Y Otro C.b.",
    "wof:placetype":"venue"
},
  "geometry": {"coordinates":[-1.7912800312,43.3419265747],"type":"Point"}
}