{
  "type": "Feature",
  "properties": {
    "addr:full":"Carretera De Almendralejo, S/n Aceuchal Badajoz 06207",
    "addr:housenumber":"s / n",
    "addr:postcode":"06207",
    "addr:street":"Carretera De Almendralejo",
    "iso:country":"ES",
    "sg:address":"Carretera De Almendralejo, S/n",
    "sg:city":"Aceuchal",
    "sg:orig_category":"Cooperativas Agr\u00cdcolas",
    "sg:phone":"+34 924 68 70 00",
    "sg:postcode":"06207",
    "sg:province":"Badajoz",
    "wof:name":"Sociedad Anonima Laboral San Isidro De Aceuchal",
    "wof:placetype":"venue"
},
  "geometry": {"coordinates":[-6.4863080978,38.6493225098],"type":"Point"}
}