{
  "type": "Feature",
  "properties": {
    "addr:full":"Calle de Dorado, 19 Langreo Asturias 33900",
    "addr:housenumber":"19",
    "addr:postcode":"33900",
    "addr:street":"Calle De Dorado",
    "iso:country":"ES",
    "sg:address":"Calle de Dorado, 19",
    "sg:city":"Langreo",
    "sg:orig_category":"Hielo Artificial (fabricaci\u00d3n, Distribuci\u00d3n)",
    "sg:phone":"+34 985 67 34 84",
    "sg:postcode":"33900",
    "sg:province":"Asturias",
    "wof:name":"Congelados Mieres S. L.",
    "wof:placetype":"venue"
},
  "geometry": {"coordinates":[-5.6821880341,43.2940216064],"type":"Point"}
}