{
  "type": "Feature",
  "properties": {
    "iso:country":"ES",
    "sg:address":"Calle de Alameda De Santa Eufemia, 34",
    "sg:city":"Tomares",
    "sg:orig_category":"Alquiler De V\u00cddeo",
    "sg:phone":"+34 954 15 16 69",
    "sg:postcode":"41940",
    "sg:province":"Sevilla",
    "wof:name":"Esteban Fari\u00f1as Fidel Angel",
    "wof:placetype":"venue"
},
  "geometry": {"coordinates":[-6.043419838,37.3758544922],"type":"Point"}
}