{
  "type": "Feature",
  "properties": {
    "addr:full":"Rond Sant Pau, 3 Barcelona Barcelona 08015",
    "addr:housenumber":"3",
    "addr:postcode":"08015",
    "iso:country":"ES",
    "sg:address":"Rond Sant Pau, 3",
    "sg:city":"Barcelona",
    "sg:orig_category":"Talleres: Ropa A Medida",
    "sg:phone":"+34 934 41 59 94",
    "sg:postcode":"08015",
    "sg:province":"Barcelona",
    "wof:name":"Rodriguez Penela Manuel",
    "wof:placetype":"venue"
},
  "geometry": {"coordinates":[2.1687450409,41.3855895996],"type":"Point"}
}