{
  "type": "Feature",
  "properties": {
    "iso:country":"ES",
    "sg:address":"Errosario Kalea, 34",
    "sg:city":"Elgoibar",
    "sg:orig_category":"Abogados",
    "sg:phone":"+34 943 53 12 98",
    "sg:postcode":"20870",
    "sg:province":"Guip\u00f9zcoa",
    "wof:name":"Berasaluze Lazkano Irune",
    "wof:placetype":"venue"
},
  "geometry": {"coordinates":[-2.4169158936,43.2149009705],"type":"Point"}
}