{
  "type": "Feature",
  "properties": {
    "iso:country":"ES",
    "sg:address":"Av Josep Tarradellas, 38",
    "sg:city":"Terrassa",
    "sg:orig_category":"Restaurantes",
    "sg:phone":"+34 937 88 50 48",
    "sg:postcode":"08225",
    "sg:province":"Barcelona",
    "wof:name":"Restaurant La Antorcha S.l.",
    "wof:placetype":"venue"
},
  "geometry": {"coordinates":[2.003289938,41.5715026855],"type":"Point"}
}