{
  "type": "Feature",
  "properties": {
    "addr:full":"Avda Conquistadores Bradenton, S/n Barcarrota Badajoz 06160",
    "addr:postcode":"06160",
    "addr:street":"Avda Conquistadores;S / N",
    "iso:country":"ES",
    "sg:address":"Avda Conquistadores Bradenton, S/n",
    "sg:city":"Barcarrota",
    "sg:orig_category":"Alimentaci\u00d3n General (al Por Mayor)",
    "sg:phone":"+34 924 73 68 13",
    "sg:postcode":"06160",
    "sg:province":"Badajoz",
    "wof:name":"Cocepiba S.l.",
    "wof:placetype":"venue"
},
  "geometry": {"coordinates":[-6.8501839638,38.5173149109],"type":"Point"}
}