{
  "type": "Feature",
  "properties": {
    "iso:country":"ES",
    "sg:address":"Plaz Bami, 6",
    "sg:city":"Madrid",
    "sg:orig_category":"Ingenier\u00cda, Centros De Estudios (diversos)",
    "sg:phone":"+34 913 26 05 89",
    "sg:postcode":"28017",
    "sg:province":"Madrid",
    "wof:name":"Auximasa S.l.",
    "wof:placetype":"venue"
},
  "geometry": {"coordinates":[-3.6541931629,40.4307518005],"type":"Point"}
}