{
  "type": "Feature",
  "properties": {
    "addr:full":"Calle de Gordoniz, 12 Bilbao Vizcaya 48010",
    "addr:housenumber":"12",
    "addr:postcode":"48010",
    "addr:street":"Calle De Gordoniz",
    "iso:country":"ES",
    "sg:address":"Calle de Gordoniz, 12",
    "sg:city":"Bilbao",
    "sg:orig_category":"M\u00c9dicos: Ginecolog\u00cda Y Obstetricia",
    "sg:phone":"+34 944 44 66 26",
    "sg:postcode":"48010",
    "sg:province":"Vizcaya",
    "wof:name":"Gorostiaga Ruiz Alvaro",
    "wof:placetype":"venue"
},
  "geometry": {"coordinates":[-2.9396259785,43.2591552734],"type":"Point"}
}