{
  "type": "Feature",
  "properties": {
    "iso:country":"ES",
    "sg:address":"Praz Martinez Anido, 5",
    "sg:city":"Estrada",
    "sg:orig_category":"Arquitectos",
    "sg:phone":"+34 986 57 25 52",
    "sg:postcode":"36680",
    "sg:province":"Pontevedra",
    "wof:name":"Trabe Estudio Tecnico S.c.",
    "wof:placetype":"venue"
},
  "geometry": {"coordinates":[-8.4923658371,42.6895828247],"type":"Point"}
}