{
  "type": "Feature",
  "properties": {
    "addr:full":"Leon-burgos, Km. 0049,0 Sahagun Le\u00f3n 24320",
    "addr:postcode":"24320",
    "addr:street":"Leon-Burgos Km. 0049,0 Sahagun Leo\u0301N",
    "iso:country":"ES",
    "sg:address":"Leon-burgos, Km. 0049,0",
    "sg:city":"Sahagun",
    "sg:orig_category":"Distribuci\u00d3n De Petr\u00d3leo Y Derivados",
    "sg:phone":"+34 987 78 11 47",
    "sg:postcode":"24320",
    "sg:province":"Le\u00f3n",
    "wof:name":"Cedipsa Compa\u00d1ia Espa\u00d1ola Distribuidora De Petroleos S.a.",
    "wof:placetype":"venue"
},
  "geometry": {"coordinates":[-5.026113987,42.3711051941],"type":"Point"}
}