{
  "type": "Feature",
  "properties": {
    "addr:full":"Calle de Principe De Asturias, 9 Madrid Madrid 28006",
    "addr:housenumber":"9",
    "addr:postcode":"madrid;28006",
    "addr:street":"Calle De Principe De Asturias",
    "iso:country":"ES",
    "sg:address":"Calle de Principe De Asturias, 9",
    "sg:city":"Madrid",
    "sg:orig_category":"Agentes, Concesionarios Y Sucursales De Camiones Y Veh\u00cdculos Industriales",
    "sg:phone":"+34 914 01 26 75",
    "sg:postcode":"28006",
    "sg:province":"Madrid",
    "wof:name":"Santamaria Hernan Carlos",
    "wof:placetype":"venue"
},
  "geometry": {"coordinates":[-3.6718940735,40.4281082153],"type":"Point"}
}