{
  "type": "Feature",
  "properties": {
    "iso:country":"ES",
    "sg:address":"Calle de Nu\u00d1ez De Balboa, 79",
    "sg:city":"Madrid",
    "sg:orig_category":"Producci\u00d3n, Venta De Productos De Agricultura Biol\u00d3gica",
    "sg:phone":"+34 917 81 29 92",
    "sg:postcode":"28006",
    "sg:province":"Madrid",
    "wof:name":"El Jaron C. De B.",
    "wof:placetype":"venue"
},
  "geometry": {"coordinates":[-3.6824409962,40.4312057495],"type":"Point"}
}