{
  "type": "Feature",
  "properties": {
    "iso:country":"ES",
    "sg:address":"Avda Almoradi, 3",
    "sg:city":"Daya Nueva",
    "sg:orig_category":"Arboricultura Y Producci\u00d3n De Frutas",
    "sg:phone":"+34 965 70 06 49",
    "sg:postcode":"03159",
    "sg:province":"Alicante",
    "wof:name":"Gregorio Ca\u00f1izares S.l.",
    "wof:placetype":"venue"
},
  "geometry": {"coordinates":[-0.762172997,38.1137428284],"type":"Point"}
}