{
  "type": "Feature",
  "properties": {
    "addr:full":"Calle de Mayor, 25 Ablitas Navarra 31523",
    "addr:housenumber":"25",
    "addr:postcode":"31523",
    "addr:street":"Calle De Mayor",
    "iso:country":"ES",
    "sg:address":"Calle de Mayor, 25",
    "sg:city":"Ablitas",
    "sg:orig_category":"Poller\u00cda Y Caza (al Por Menor)",
    "sg:phone":"+34 948 81 30 08",
    "sg:postcode":"31523",
    "sg:province":"Navarra",
    "wof:name":"Perez Gracia German",
    "wof:placetype":"venue"
},
  "geometry": {"coordinates":[-1.6411141157,41.9732017517],"type":"Point"}
}