{
  "type": "Feature",
  "properties": {
    "addr:full":"Calle de Tranvia, 2 Alcantarilla Murcia 30820",
    "addr:housenumber":"2",
    "addr:postcode":"30820",
    "addr:street":"Calle De Tranvia",
    "iso:country":"ES",
    "sg:address":"Calle de Tranvia, 2",
    "sg:city":"Alcantarilla",
    "sg:orig_category":"M\u00c9dicos: Estomatolog\u00cda",
    "sg:phone":"+34 968 80 83 61",
    "sg:postcode":"30820",
    "sg:province":"Murcia",
    "wof:name":"Fraile Camino Isaac",
    "wof:placetype":"venue"
},
  "geometry": {"coordinates":[-1.214269042,37.9697647095],"type":"Point"}
}