{
  "type": "Feature",
  "properties": {
    "iso:country":"ES",
    "sg:address":"Av Valencia, 8",
    "sg:city":"Benilloba",
    "sg:orig_category":"Hilaturas, Hilos Y Actividades Relacionadas",
    "sg:phone":"+34 966 50 40 00",
    "sg:postcode":"03810",
    "sg:province":"Alicante",
    "wof:name":"Textiles Fercom S.l.",
    "wof:placetype":"venue"
},
  "geometry": {"coordinates":[-0.3904339969,38.6987075806],"type":"Point"}
}