{
  "type": "Feature",
  "properties": {
    "iso:country":"ES",
    "sg:address":"Zancarron, 75",
    "sg:city":"Lebrija",
    "sg:orig_category":"Servicios Diversos",
    "sg:phone":"+34 902 14 40 44",
    "sg:postcode":"41740",
    "sg:province":"Sevilla",
    "wof:name":"Colefil S.l.",
    "wof:placetype":"venue"
},
  "geometry": {"coordinates":[-6.0854787827,36.9164466858],"type":"Point"}
}