{
  "type": "Feature",
  "properties": {
    "iso:country":"ES",
    "sg:address":"Calle de Rosa De Lima, 1",
    "sg:city":"Matas-pinar-monte Rozas",
    "sg:orig_category":"Ingeniero",
    "sg:phone":"+34 916 36 91 21",
    "sg:postcode":"28290",
    "sg:province":"Madrid",
    "sg:website":"www.aeat.com",
    "wof:name":"Aea Technology Global S.a.",
    "wof:placetype":"venue"
},
  "geometry": {"coordinates":[-3.8995010853,40.5538330078],"type":"Point"}
}