{
  "type": "Feature",
  "properties": {
    "addr:full":"Bidebarrieta Kalea, 6 Eibar Guip\u00f9zcoa 20600",
    "addr:housenumber":"6",
    "addr:postcode":"20600",
    "addr:street":"Bidebarrieta Kalea;Guipu\u0300Zcoa",
    "iso:country":"ES",
    "sg:address":"Bidebarrieta Kalea, 6",
    "sg:city":"Eibar",
    "sg:orig_category":"Art\u00cdculos De Decoraci\u00d3n",
    "sg:phone":"+34 943 20 13 14",
    "sg:postcode":"20600",
    "sg:province":"Guip\u00f9zcoa",
    "wof:name":"Yarza Aranzabal Eusebio",
    "wof:placetype":"venue"
},
  "geometry": {"coordinates":[-2.4700605869,43.185218811],"type":"Point"}
}