{
  "type": "Feature",
  "properties": {
    "addr:full":"Calle de Risco Viceche, 6 Chayofa Santa Cruz De Tenerife 38652",
    "addr:housenumber":"6",
    "addr:postcode":"38652",
    "addr:street":"Calle De Risco Viceche",
    "iso:country":"ES",
    "sg:address":"Calle de Risco Viceche, 6",
    "sg:city":"Chayofa",
    "sg:orig_category":"Agencias De Viajes",
    "sg:phone":"+34 922 72 96 51",
    "sg:postcode":"38652",
    "sg:province":"Santa Cruz De Tenerife",
    "wof:name":"Admiral Travel Agencia De Viajes",
    "wof:placetype":"venue"
},
  "geometry": {"coordinates":[-16.7012634277,28.0734519958],"type":"Point"}
}