{
  "type": "Feature",
  "properties": {
    "iso:country":"ES",
    "sg:address":"Calle de Doctor Gomez Ulla, 13",
    "sg:city":"Arrecife",
    "sg:orig_category":"Agencias Y Agentes Comerciales, Representantes",
    "sg:phone":"+34 928 80 50 13",
    "sg:postcode":"35500",
    "sg:province":"Las Palmas",
    "wof:name":"Vista Tomaren S.l.",
    "wof:placetype":"venue"
},
  "geometry": {"coordinates":[-13.5520935059,28.9629077911],"type":"Point"}
}