{
  "type": "Feature",
  "properties": {
    "iso:country":"ES",
    "sg:address":"Calle de Cruz Recia, 2",
    "sg:city":"Fernan Nu\u00e7ez",
    "sg:orig_category":"Fabricaci\u00d3n De Quesos",
    "sg:phone":"+34 957 37 36 02",
    "sg:postcode":"14520",
    "sg:province":"C\u00f3rdoba",
    "wof:name":"Quesos Galvez S.l.",
    "wof:placetype":"venue"
},
  "geometry": {"coordinates":[-4.7211456299,37.6646728516],"type":"Point"}
}