{
  "type": "Feature",
  "properties": {
    "iso:country":"ES",
    "sg:address":"Carr Major, 6",
    "sg:city":"Esterri D'aneu",
    "sg:orig_category":"Administraciones Regionales, Departamentales Y Locales",
    "sg:phone":"+34 973 62 60 05",
    "sg:postcode":"25580",
    "sg:province":"Lleida",
    "wof:name":"Ajuntament D'esterri D'aneu",
    "wof:placetype":"venue"
},
  "geometry": {"coordinates":[1.1232769489,42.625957489],"type":"Point"}
}