{
  "type": "Feature",
  "properties": {
    "iso:country":"ES",
    "sg:address":"Carrer de Aprestadora, 16",
    "sg:city":"Hospitalet Llobregat",
    "sg:orig_category":"Promotores Constructores",
    "sg:phone":"+34 934 21 23 71",
    "sg:postcode":"08902",
    "sg:province":"Barcelona",
    "wof:name":"Ute Ciutat De La Justicia",
    "wof:placetype":"venue"
},
  "geometry": {"coordinates":[2.1310191154,41.36561203],"type":"Point"}
}