{
  "type": "Feature",
  "properties": {
    "iso:country":"ES",
    "sg:address":"Ctra Nacional 111, Km. 0319,3",
    "sg:city":"Nalda",
    "sg:orig_category":"Distribuci\u00d3n De Petr\u00d3leo Y Derivados",
    "sg:phone":"+34 941 44 71 77",
    "sg:postcode":"26190",
    "sg:province":"La Rioja",
    "wof:name":"Las Gaunas S. A.",
    "wof:placetype":"venue"
},
  "geometry": {"coordinates":[-2.4869959354,42.3356437683],"type":"Point"}
}