{
  "type": "Feature",
  "properties": {
    "addr:full":"Calle de Federico Olmeda, 19 Burgos Burgos 09006",
    "addr:housenumber":"19",
    "addr:postcode":"09006",
    "addr:street":"Calle De Federico Olmeda",
    "iso:country":"ES",
    "sg:address":"Calle de Federico Olmeda, 19",
    "sg:city":"Burgos",
    "sg:orig_category":"Panader\u00cdas, Panader\u00cdas",
    "sg:phone":"+34 947 22 25 01",
    "sg:postcode":"09006",
    "sg:province":"Burgos",
    "wof:name":"Pinillos Abejon Fortunato",
    "wof:placetype":"venue"
},
  "geometry": {"coordinates":[-3.6916060448,42.3500518799],"type":"Point"}
}