{
  "type": "Feature",
  "properties": {
    "addr:full":"Rbla Nova, 18 Mollet Valles Barcelona 08100",
    "addr:housenumber":"18",
    "addr:postcode":"08100",
    "addr:street":"Rbla Nova",
    "iso:country":"ES",
    "sg:address":"Rbla Nova, 18",
    "sg:city":"Mollet Valles",
    "sg:orig_category":"Estancos",
    "sg:phone":"+34 935 93 07 48",
    "sg:postcode":"08100",
    "sg:province":"Barcelona",
    "wof:name":"Pe\u00f1a Pe\u00f1a Maria Elena",
    "wof:placetype":"venue"
},
  "geometry": {"coordinates":[2.2105789185,41.5387382507],"type":"Point"}
}