{
  "type": "Feature",
  "properties": {
    "addr:full":"Ctra Alicante, S/n Barrio Del Puente De La Muleta Murcia 30007",
    "addr:housenumber":"s / n",
    "addr:postcode":"30007",
    "addr:street":"Ctra Alicante;Del Puente De La",
    "iso:country":"ES",
    "sg:address":"Ctra Alicante, S/n",
    "sg:city":"Barrio Del Puente De La Muleta",
    "sg:orig_category":"Empresas De Pintura Y Revestimientos",
    "sg:phone":"+34 968 20 07 38",
    "sg:postcode":"30007",
    "sg:province":"Murcia",
    "wof:name":"Aragon Bravo Cristobal",
    "wof:placetype":"venue"
},
  "geometry": {"coordinates":[-1.1104143858,38.0169715881],"type":"Point"}
}