{
  "type": "Feature",
  "properties": {
    "iso:country":"ES",
    "sg:address":"Calle de Pirita, S/n",
    "sg:city":"Valladolid",
    "sg:orig_category":"Negocio De Materiales De Construcci\u00d3n",
    "sg:phone":"+34 983 30 51 14",
    "sg:postcode":"47012",
    "sg:province":"Valladolid",
    "wof:name":"Ruiz Ocariz Jose Ignacio",
    "wof:placetype":"venue"
},
  "geometry": {"coordinates":[-4.7090730667,41.6271095276],"type":"Point"}
}