{
  "type": "Feature",
  "properties": {
    "iso:country":"ES",
    "sg:address":"Rond Paisos Catalans (dels), 78",
    "sg:city":"Mataro",
    "sg:orig_category":"Mec\u00c1nico Del Autom\u00d3vil",
    "sg:phone":"+34 937 57 84 44",
    "sg:postcode":"08304",
    "sg:province":"Barcelona",
    "wof:name":"Morer Costa Salvador",
    "wof:placetype":"venue"
},
  "geometry": {"coordinates":[2.441847086,41.5545845032],"type":"Point"}
}