{
  "type": "Feature",
  "properties": {
    "iso:country":"ES",
    "sg:address":"Plaz Argel, 2",
    "sg:city":"Alacant",
    "sg:orig_category":"Droguer\u00cdas (al Por Menor)",
    "sg:phone":"+34 965 18 28 38",
    "sg:postcode":"03011",
    "sg:province":"Alicante",
    "wof:name":"Ferrer Escortell Pedro",
    "wof:placetype":"venue"
},
  "geometry": {"coordinates":[-0.491715014,38.3742446899],"type":"Point"}
}