{
  "type": "Feature",
  "properties": {
    "iso:country":"ES",
    "sg:address":"Crta De Martos, S/n",
    "sg:city":"Higuera Calatrava",
    "sg:orig_category":"Empresas De Desmonte",
    "sg:phone":"+34 953 52 91 88",
    "sg:postcode":"23611",
    "sg:province":"Ja\u00e9n",
    "wof:name":"Rueda Mesa Francisco",
    "wof:placetype":"venue"
},
  "geometry": {"coordinates":[-4.1551990509,37.7966156006],"type":"Point"}
}