{
  "type": "Feature",
  "properties": {
    "addr:full":"Avda Encarnacion, S/n Fuengirola M\u00e1laga 29640",
    "addr:housenumber":"s",
    "addr:postcode":"29640",
    "addr:street":"Avda Encarnacion;/ N;Ma\u0301Laga",
    "iso:country":"ES",
    "sg:address":"Avda Encarnacion, S/n",
    "sg:city":"Fuengirola",
    "sg:orig_category":"Tiendas De Grano, Frutas Y Legumbres Secas (al Por Menor)",
    "sg:phone":"+34 952 58 25 95",
    "sg:postcode":"29640",
    "sg:province":"M\u00e1laga",
    "wof:name":"Productos Alimenticios Belros S.a.",
    "wof:placetype":"venue"
},
  "geometry": {"coordinates":[-4.6306362152,36.5269432068],"type":"Point"}
}