{
  "type": "Feature",
  "properties": {
    "iso:country":"ES",
    "sg:address":"Carr Aeroclub, 3",
    "sg:city":"Empuriabrava",
    "sg:orig_category":"Fabricaci\u00d3n De Sobres, Bolsas Y Fundas",
    "sg:phone":"+34 972 45 00 48",
    "sg:postcode":"17487",
    "sg:province":"Girona",
    "wof:name":"Rivera Costal Salvador",
    "wof:placetype":"venue"
},
  "geometry": {"coordinates":[3.11282897,42.2576675415],"type":"Point"}
}