{
  "type": "Feature",
  "properties": {
    "addr:full":"Avda Valdes, 43 Ponferrada Le\u00f3n 24400",
    "addr:housenumber":"43",
    "addr:postcode":"24400",
    "addr:street":"Avda Valdes",
    "iso:country":"ES",
    "sg:address":"Avda Valdes, 43",
    "sg:city":"Ponferrada",
    "sg:orig_category":"Fabrica De Cer\u00c1micas",
    "sg:phone":"+34 987 40 43 11",
    "sg:postcode":"24400",
    "sg:province":"Le\u00f3n",
    "wof:name":"Arias Lopez Angel",
    "wof:placetype":"venue"
},
  "geometry": {"coordinates":[-6.601650238,42.5489768982],"type":"Point"}
}