{
  "type": "Feature",
  "properties": {
    "addr:full":"Estd Cedeira, Km. 0001,0 Freixeiro La Coru\u00f1a 15570",
    "addr:postcode":"15570",
    "addr:street":"Cedeira Km. 0001,0 Freixeiro La Corun\u0303A",
    "iso:country":"ES",
    "sg:address":"Estd Cedeira, Km. 0001,0",
    "sg:city":"Freixeiro",
    "sg:orig_category":"Frutas, Legumbres Frescas Y Tempranas (al Por Menor)",
    "sg:phone":"+34 981 38 32 20",
    "sg:postcode":"15570",
    "sg:province":"La Coru\u00f1a",
    "wof:name":"Alfre S.l.",
    "wof:placetype":"venue"
},
  "geometry": {"coordinates":[-8.1961069107,43.1968383789],"type":"Point"}
}