{
  "type": "Feature",
  "properties": {
    "iso:country":"ES",
    "sg:address":"Pl Mossen Jacint Verdaguer, 16",
    "sg:city":"Terrassa",
    "sg:orig_category":"Molduras, Junquillos, Listones Y Molduras Perforadas",
    "sg:phone":"+34 937 88 81 10",
    "sg:postcode":"08221",
    "sg:province":"Barcelona",
    "wof:name":"Aguilar Troya Juan",
    "wof:placetype":"venue"
},
  "geometry": {"coordinates":[2.02242589,41.6058998108],"type":"Point"}
}