{
  "type": "Feature",
  "properties": {
    "iso:country":"ES",
    "sg:address":"Ctra Granada, S/n",
    "sg:city":"Jaen",
    "sg:orig_category":"T\u00c9cnicos Veterinarios",
    "sg:phone":"+34 953 24 27 27",
    "sg:postcode":"23001",
    "sg:province":"Ja\u00e9n",
    "wof:name":"Aurgican Centro Canino",
    "wof:placetype":"venue"
},
  "geometry": {"coordinates":[-3.7661225796,37.7737426758],"type":"Point"}
}