{
  "type": "Feature",
  "properties": {
    "iso:country":"ES",
    "sg:address":"Calle de Sancho Iv El Bravo, 15",
    "sg:city":"Tarifa",
    "sg:orig_category":"Promotores Constructores",
    "sg:phone":"+34 956 68 49 67",
    "sg:postcode":"11380",
    "sg:province":"C\u00e1diz",
    "wof:name":"Alfonseca Santamaria Manuel",
    "wof:placetype":"venue"
},
  "geometry": {"coordinates":[-5.6030449867,36.0128974915],"type":"Point"}
}