{
  "type": "Feature",
  "properties": {
    "addr:full":"Calle de Deanes, 13 Cordoba C\u00f3rdoba 14003",
    "addr:housenumber":"13",
    "addr:postcode":"14003",
    "addr:street":"Calle De Deanes;Co\u0301Rdoba",
    "iso:country":"ES",
    "sg:address":"Calle de Deanes, 13",
    "sg:city":"Cordoba",
    "sg:orig_category":"Bisuter\u00cda, Joyer\u00cda, Relojer\u00cda (al Por Menor)",
    "sg:phone":"+34 957 47 97 02",
    "sg:postcode":"14003",
    "sg:province":"C\u00f3rdoba",
    "wof:name":"Rodriguez Exposito Inmaculada",
    "wof:placetype":"venue"
},
  "geometry": {"coordinates":[-4.7810277939,37.8796005249],"type":"Point"}
}