{
  "type": "Feature",
  "properties": {
    "iso:country":"ES",
    "sg:address":"Calle de Corredera De San Marcos, 24",
    "sg:city":"Linares",
    "sg:orig_category":"Parques De Atracciones Y Centros De Esparcimiento",
    "sg:phone":"+34 953 69 00 17",
    "sg:postcode":"23700",
    "sg:province":"Ja\u00e9n",
    "wof:name":"Recreativos Jocker S.l.",
    "wof:placetype":"venue"
},
  "geometry": {"coordinates":[-3.6342756748,38.0965805054],"type":"Point"}
}