{
  "type": "Feature",
  "properties": {
    "addr:full":"Avda Club Deportivo, 86 Logro\u00f1o La Rioja 26007",
    "addr:housenumber":"86",
    "addr:postcode":"26007",
    "addr:street":"Avda Club Deportivo;Rioja",
    "iso:country":"ES",
    "sg:address":"Avda Club Deportivo, 86",
    "sg:city":"Logro\u00f1o",
    "sg:orig_category":"Alimentaci\u00d3n General (al Por Menor)",
    "sg:phone":"+34 941 51 18 35",
    "sg:postcode":"26007",
    "sg:province":"La Rioja",
    "wof:name":"Agustin Y Angel Carmelo C.b.",
    "wof:placetype":"venue"
},
  "geometry": {"coordinates":[-2.4628212452,42.4583473206],"type":"Point"}
}