{
  "type": "Feature",
  "properties": {
    "addr:full":"Calle de Avila, 14 Madrid Madrid 28020",
    "addr:housenumber":"14",
    "addr:postcode":"madrid;28020",
    "addr:street":"Calle De Avila",
    "iso:country":"ES",
    "sg:address":"Calle de Avila, 14",
    "sg:city":"Madrid",
    "sg:orig_category":"Material Y Suministros Para Imprenta E Industrias Gr\u00c1ficas",
    "sg:phone":"+34 915 70 85 87",
    "sg:postcode":"28020",
    "sg:province":"Madrid",
    "wof:name":"A Priori Produccion & Publicidad S.l.",
    "wof:placetype":"venue"
},
  "geometry": {"coordinates":[-3.700592041,40.4526596069],"type":"Point"}
}