{
  "type": "Feature",
  "properties": {
    "iso:country":"ES",
    "sg:address":"Calle de Real, 29",
    "sg:city":"Armellada",
    "sg:orig_category":"Delegados, Agentes De Tr\u00c1nsito, Auxiliares De Transporte Internacional",
    "sg:phone":"+34 987 36 32 02",
    "sg:postcode":"24284",
    "sg:province":"Le\u00f3n",
    "wof:name":"Leonato Perez Ubaldo",
    "wof:placetype":"venue"
},
  "geometry": {"coordinates":[-5.8626818657,42.5522842407],"type":"Point"}
}