{
  "type": "Feature",
  "properties": {
    "iso:country":"ES",
    "sg:address":"Carrer de Enric Morera, 14",
    "sg:city":"Esplugues Llobregat",
    "sg:orig_category":"Filtros Y Elementos Filtradores",
    "sg:phone":"+34 933 71 39 48",
    "sg:postcode":"08950",
    "sg:province":"Barcelona",
    "sg:website":"www.siebec.es",
    "wof:name":"Siebec S.a.",
    "wof:placetype":"venue"
},
  "geometry": {"coordinates":[2.0801119804,41.371421814],"type":"Point"}
}