{
  "type": "Feature",
  "properties": {
    "addr:full":"Av Reus, 19 Alcover Tarragona 43460",
    "addr:housenumber":"19",
    "addr:postcode":"43460",
    "addr:street":"Av Reus",
    "iso:country":"ES",
    "sg:address":"Av Reus, 19",
    "sg:city":"Alcover",
    "sg:orig_category":"Reposter\u00cdas",
    "sg:phone":"+34 977 84 64 32",
    "sg:postcode":"43460",
    "sg:province":"Tarragona",
    "wof:name":"Forn Feijor S.l.",
    "wof:placetype":"venue"
},
  "geometry": {"coordinates":[1.1706830263,41.261844635],"type":"Point"}
}