{
  "type": "Feature",
  "properties": {
    "iso:country":"ES",
    "sg:address":"Estd Castela, 48",
    "sg:city":"Ferrol",
    "sg:orig_category":"Ambulancias",
    "sg:phone":"+34 981 37 10 53",
    "sg:postcode":"15404",
    "sg:province":"La Coru\u00f1a",
    "wof:name":"Lopez Diaz Jose",
    "wof:placetype":"venue"
},
  "geometry": {"coordinates":[-8.2144622803,43.4897613525],"type":"Point"}
}