{
  "type": "Feature",
  "properties": {
    "iso:country":"ES",
    "sg:address":"Los Artesanos, Km. 0082,0",
    "sg:city":"Tarancon",
    "sg:orig_category":"Sales (al Por Mayor)",
    "sg:phone":"+34 969 32 18 28",
    "sg:postcode":"16400",
    "sg:province":"Cuenca",
    "wof:name":"Delosal S.l.",
    "wof:placetype":"venue"
},
  "geometry": {"coordinates":[-3.0073239803,40.0039863586],"type":"Point"}
}