{
  "type": "Feature",
  "properties": {
    "addr:full":"Pase Canalejas, 83 Salamanca Salamanca 37001",
    "addr:housenumber":"83",
    "addr:postcode":"37001",
    "addr:street":"Canalejas",
    "iso:country":"ES",
    "sg:address":"Pase Canalejas, 83",
    "sg:city":"Salamanca",
    "sg:orig_category":"Transportes Por Carretera: Lotes Completos, Mercanc\u00cdas Diversas",
    "sg:phone":"+34 923 26 47 39",
    "sg:postcode":"37001",
    "sg:province":"Salamanca",
    "wof:name":"Distribuidora Internacional De Alimentacion S.a.",
    "wof:placetype":"venue"
},
  "geometry": {"coordinates":[-5.663848877,40.964225769],"type":"Point"}
}