{
  "type": "Feature",
  "properties": {
    "iso:country":"ES",
    "sg:address":"Calle de Isaac Peral, 10",
    "sg:city":"Albacete",
    "sg:orig_category":"Laboratorios De An\u00c1lisis Biom\u00c9dicos",
    "sg:phone":"+34 967 52 06 05",
    "sg:postcode":"02001",
    "sg:province":"Albacete",
    "wof:name":"Tecnyal Laboratorios S.l.",
    "wof:placetype":"venue"
},
  "geometry": {"coordinates":[-1.8546999693,38.9959411621],"type":"Point"}
}