{
  "type": "Feature",
  "properties": {
    "iso:country":"ES",
    "sg:address":"Calle de Goya, 55",
    "sg:city":"Madrid",
    "sg:orig_category":"Farmacias",
    "sg:phone":"+34 915 75 33 16",
    "sg:postcode":"28001",
    "sg:province":"Madrid",
    "sg:website":"www.farmaciadelglobo.com",
    "wof:name":"Nestares Lopez Marta",
    "wof:placetype":"venue"
},
  "geometry": {"coordinates":[-3.6812651157,40.425201416],"type":"Point"}
}