{
  "type": "Feature",
  "properties": {
    "addr:full":"Calle de Fuente Del Rio, S/n Arcos Frontera C\u00e1diz 11630",
    "addr:postcode":"11630",
    "addr:street":"Calle De Fuente Del Rio S / N Arcos;Ca\u0301Diz",
    "iso:country":"ES",
    "sg:address":"Calle de Fuente Del Rio, S/n",
    "sg:city":"Arcos Frontera",
    "sg:orig_category":"Molduras, Junquillos, Listones Y Molduras Perforadas",
    "sg:phone":"+34 956 70 07 34",
    "sg:postcode":"11630",
    "sg:province":"C\u00e1diz",
    "wof:name":"Pereira Barroso Antonio",
    "wof:placetype":"venue"
},
  "geometry": {"coordinates":[-6.29240942,36.5299415588],"type":"Point"}
}