{
  "type": "Feature",
  "properties": {
    "addr:full":"Plaz San Roque, 1 Jaen Ja\u00e9n 23008",
    "addr:postcode":"23008",
    "addr:street":"Plaz San",
    "iso:country":"ES",
    "sg:address":"Plaz San Roque, 1",
    "sg:city":"Jaen",
    "sg:orig_category":"Restaurantes",
    "sg:phone":"+34 953 27 26 55",
    "sg:postcode":"23008",
    "sg:province":"Ja\u00e9n",
    "wof:name":"Garcia Diaz Antonio",
    "wof:placetype":"venue"
},
  "geometry": {"coordinates":[-3.7906870842,37.7650947571],"type":"Point"}
}