{
  "type": "Feature",
  "properties": {
    "iso:country":"ES",
    "sg:address":"Calle de Allende Manuel, 24",
    "sg:city":"Bilbao",
    "sg:orig_category":"M\u00c9dicos: Oftalmolog\u00cda",
    "sg:phone":"+34 944 43 67 28",
    "sg:postcode":"48010",
    "sg:province":"Vizcaya",
    "wof:name":"Instituto Refractivo Bilbaino",
    "wof:placetype":"venue"
},
  "geometry": {"coordinates":[-2.9421422482,43.2588272095],"type":"Point"}
}