{
  "type": "Feature",
  "properties": {
    "iso:country":"ES",
    "sg:address":"Carrer de Lleida, 41",
    "sg:city":"Barcelona",
    "sg:orig_category":"Agencias Y Agentes Comerciales, Representantes",
    "sg:phone":"+34 934 26 94 12",
    "sg:postcode":"08004",
    "sg:province":"Barcelona",
    "wof:name":"Mir Nou Juan",
    "wof:placetype":"venue"
},
  "geometry": {"coordinates":[2.1556429863,41.3721427917],"type":"Point"}
}