{
  "type": "Feature",
  "properties": {
    "iso:country":"ES",
    "sg:address":"Calle de Benito Blanco Rajoy, 3",
    "sg:city":"Coru\u00d1a",
    "sg:orig_category":"Asesor\u00cda Fiscal Y Jur\u00cddica",
    "sg:phone":"+34 981 29 05 00",
    "sg:postcode":"15006",
    "sg:province":"La Coru\u00f1a",
    "wof:name":"Colaboradores Empresariales Asociados S.l.",
    "wof:placetype":"venue"
},
  "geometry": {"coordinates":[-8.403336525,43.3554420471],"type":"Point"}
}