{
  "type": "Feature",
  "properties": {
    "iso:country":"ES",
    "sg:address":"Plaz San Francisco, 13",
    "sg:city":"Le\u00f3n",
    "sg:orig_category":"Centros De Adelgazamiento Y De Est\u00c9tica",
    "sg:phone":"+34 987 20 92 11",
    "sg:postcode":"24004",
    "sg:province":"Le\u00f3n",
    "wof:name":"Peluqueria Marques S.l.",
    "wof:placetype":"venue"
},
  "geometry": {"coordinates":[-5.5722742081,42.5927619934],"type":"Point"}
}