{
  "type": "Feature",
  "properties": {
    "addr:full":"Calle de Puerto De Alazores, 16 Madrid Madrid 28031",
    "addr:housenumber":"16",
    "addr:postcode":"madrid;28031",
    "addr:street":"Calle De Puerto De Alazores",
    "iso:country":"ES",
    "sg:address":"Calle de Puerto De Alazores, 16",
    "sg:city":"Madrid",
    "sg:orig_category":"Arreglo, Reparaci\u00d3n, Piezas Sueltas De Televisi\u00d3n, V\u00cddeo, Hi",
    "sg:phone":"+34 913 03 73 95",
    "sg:postcode":"28031",
    "sg:province":"Madrid",
    "wof:name":"Lourenco Barrocales Joao",
    "wof:placetype":"venue"
},
  "geometry": {"coordinates":[-3.6254429817,40.3789863586],"type":"Point"}
}