{
  "type": "Feature",
  "properties": {
    "addr:full":"Calle de Barbate, S/n Cadiz C\u00e1diz 11012",
    "addr:housenumber":"s / n",
    "addr:postcode":"11012",
    "addr:street":"Calle De Barbate",
    "iso:country":"ES",
    "sg:address":"Calle de Barbate, S/n",
    "sg:city":"Cadiz",
    "sg:orig_category":"Asociaciones Y Clubs Deportivos",
    "sg:phone":"+34 956 25 05 85",
    "sg:postcode":"11012",
    "sg:province":"C\u00e1diz",
    "wof:name":"Asociacion De Clubes De Futbol Modesto",
    "wof:placetype":"venue"
},
  "geometry": {"coordinates":[-6.2738595009,36.5134048462],"type":"Point"}
}