{
  "type": "Feature",
  "properties": {
    "addr:full":"Navarra-nafarroa Ebde, 5 Iru\u00f1a Navarra 31012",
    "addr:housenumber":"5",
    "addr:postcode":"31012",
    "addr:street":"Ebde",
    "iso:country":"ES",
    "sg:address":"Navarra-nafarroa Ebde, 5",
    "sg:city":"Iru\u00f1a",
    "sg:orig_category":"Carnicer\u00cdas, Carnicer\u00cdas",
    "sg:phone":"+34 948 25 03 00",
    "sg:postcode":"31012",
    "sg:province":"Navarra",
    "wof:name":"Ariztia Mendiburu Emiliano",
    "wof:placetype":"venue"
},
  "geometry": {"coordinates":[-1.6809283495,42.8271217346],"type":"Point"}
}