{
  "type": "Feature",
  "properties": {
    "addr:full":"Calle de Fausto Garcia Tena, 53 Cordoba C\u00f3rdoba 14014",
    "addr:housenumber":"53",
    "addr:postcode":"14014",
    "addr:street":"Calle De Fausto Garcia Tena;Co\u0301Rdoba",
    "iso:country":"ES",
    "sg:address":"Calle de Fausto Garcia Tena, 53",
    "sg:city":"Cordoba",
    "sg:orig_category":"Alcoholes Y Aguardientes (fabricaci\u00d3n, Al Por Mayor)",
    "sg:phone":"+34 957 27 22 94",
    "sg:postcode":"14014",
    "sg:province":"C\u00f3rdoba",
    "wof:name":"Los Almogavares S.l.",
    "wof:placetype":"venue"
},
  "geometry": {"coordinates":[-4.7184691429,37.9011764526],"type":"Point"}
}