{
  "type": "Feature",
  "properties": {
    "iso:country":"ES",
    "sg:address":"Calle de Nueva Paz, 14",
    "sg:city":"Pegalajar",
    "sg:orig_category":"Plomeros",
    "sg:phone":"+34 953 36 10 59",
    "sg:postcode":"23110",
    "sg:province":"Ja\u00e9n",
    "wof:name":"Hermoso Ortega Ramon",
    "wof:placetype":"venue"
},
  "geometry": {"coordinates":[-3.6416809559,37.7398147583],"type":"Point"}
}