{
  "type": "Feature",
  "properties": {
    "addr:full":"Via Hispanidad, 85 Zaragoza Zaragoza 50012",
    "addr:housenumber":"85",
    "addr:postcode":"50012",
    "addr:street":"Via Hispanidad",
    "iso:country":"ES",
    "sg:address":"Via Hispanidad, 85",
    "sg:city":"Zaragoza",
    "sg:orig_category":"Distribuci\u00d3n De Petr\u00d3leo Y Derivados",
    "sg:phone":"+34 976 31 64 41",
    "sg:postcode":"50012",
    "sg:province":"Zaragoza",
    "sg:website":"www.cepsa.es",
    "wof:name":"Cedipsa Compa\u00d1ia Espa\u00d1ola Distribuidora De Petroleos S.a.",
    "wof:placetype":"venue"
},
  "geometry": {"coordinates":[-0.918325007,41.6480789185],"type":"Point"}
}