{
  "type": "Feature",
  "properties": {
    "addr:full":"Avda Playa Paraiso, S/n Playa Paraiso Santa Cruz De Tenerife 38678",
    "addr:postcode":"38678",
    "addr:street":"Avda Playa Paraiso S / N",
    "iso:country":"ES",
    "sg:address":"Avda Playa Paraiso, S/n",
    "sg:city":"Playa Paraiso",
    "sg:orig_category":"Cerrajer\u00cda, Ferrallista",
    "sg:phone":"+34 922 74 12 52",
    "sg:postcode":"38678",
    "sg:province":"Santa Cruz De Tenerife",
    "wof:name":"Gonzalez Mesa Maria Luisa",
    "wof:placetype":"venue"
},
  "geometry": {"coordinates":[-16.7669334412,28.1203994751],"type":"Point"}
}