{
  "type": "Feature",
  "properties": {
    "iso:country":"ES",
    "sg:address":"Rua Barroso, 8",
    "sg:city":"Barroso",
    "sg:orig_category":"Comercio, Reparaci\u00d3n De Motocicletas, Bicicletas Y Piezas Sueltas",
    "sg:phone":"+34 986 71 80 67",
    "sg:postcode":"36638",
    "sg:province":"Pontevedra",
    "wof:name":"Motos Pi\u00f1eiro S.l.",
    "wof:placetype":"venue"
},
  "geometry": {"coordinates":[-8.7815494537,42.4442214966],"type":"Point"}
}