{
  "type": "Feature",
  "properties": {
    "iso:country":"ES",
    "sg:address":"Av J V Foix, 74",
    "sg:city":"Barcelona",
    "sg:orig_category":"Veh\u00cdculos De Ocasi\u00d3n",
    "sg:phone":"+34 932 05 80 41",
    "sg:postcode":"08034",
    "sg:province":"Barcelona",
    "wof:name":"Pronatul Xxi S.l.",
    "wof:placetype":"venue"
},
  "geometry": {"coordinates":[2.1203188896,41.3964118958],"type":"Point"}
}