{
  "type": "Feature",
  "properties": {
    "addr:full":"Carretera De La Estacion, S/n Huetor-tajar Granada 18360",
    "addr:postcode":"18360",
    "addr:street":"Carretera De La Estacion S / N Huetor-Tajar",
    "iso:country":"ES",
    "sg:address":"Carretera De La Estacion, S/n",
    "sg:city":"Huetor-tajar",
    "sg:orig_category":"Material Y Herramientas Agr\u00cdcolas",
    "sg:phone":"+34 958 33 21 91",
    "sg:postcode":"18360",
    "sg:province":"Granada",
    "wof:name":"Moya Morales Francisco",
    "wof:placetype":"venue"
},
  "geometry": {"coordinates":[-4.0554189682,37.1983451843],"type":"Point"}
}