{
  "type": "Feature",
  "properties": {
    "addr:full":"Calle de Chiquinquira, S/n Madrid Madrid 28033",
    "addr:housenumber":"s / n",
    "addr:postcode":"28033",
    "addr:street":"Calle De Chiquinquira",
    "iso:country":"ES",
    "sg:address":"Calle de Chiquinquira, S/n",
    "sg:city":"Madrid",
    "sg:orig_category":"Parques De Atracciones Y Centros De Esparcimiento",
    "sg:phone":"+34 913 81 12 07",
    "sg:postcode":"28033",
    "sg:province":"Madrid",
    "wof:name":"Electronicos Colombia S.a.",
    "wof:placetype":"venue"
},
  "geometry": {"coordinates":[-3.6350889206,40.4715461731],"type":"Point"}
}