{
  "type": "Feature",
  "properties": {
    "addr:full":"Calle de Convalecientes, 7 Malaga M\u00e1laga 29008",
    "addr:housenumber":"7",
    "addr:postcode":"29008",
    "addr:street":"Calle De Convalecientes;Ma\u0301Laga",
    "iso:country":"ES",
    "sg:address":"Calle de Convalecientes, 7",
    "sg:city":"Malaga",
    "sg:orig_category":"Asociaciones, Organismos Culturales Y Socioeducativos",
    "sg:phone":"+34 952 21 84 60",
    "sg:postcode":"29008",
    "sg:province":"M\u00e1laga",
    "wof:name":"Ilustre Y Venerable Cofradia De Nuestro Padre Jesus De La Pasion Y Maria Santisima Amor Doloroso",
    "wof:placetype":"venue"
},
  "geometry": {"coordinates":[-4.4216842651,36.7223396301],"type":"Point"}
}