{
  "type": "Feature",
  "properties": {
    "iso:country":"ES",
    "sg:address":"Calle de Trafalgar (de), 1",
    "sg:city":"Coslada",
    "sg:orig_category":"Ropa Para Se\u00d1oras (al Por Menor)",
    "sg:phone":"+34 916 71 06 44",
    "sg:postcode":"28820",
    "sg:province":"Madrid",
    "wof:name":"Hernandez Del Viso Matilde",
    "wof:placetype":"venue"
},
  "geometry": {"coordinates":[-3.5639200211,40.424446106],"type":"Point"}
}