{
  "type": "Feature",
  "properties": {
    "addr:full":"Calle de Baltasar De Alcazar, 8 Sevilla Sevilla 41008",
    "addr:housenumber":"8",
    "addr:postcode":"41008",
    "addr:street":"Calle De Baltasar De Alcazar",
    "iso:country":"ES",
    "sg:address":"Calle de Baltasar De Alcazar, 8",
    "sg:city":"Sevilla",
    "sg:orig_category":"Mercer\u00cda, Lencer\u00cda (al Por Menor)",
    "sg:phone":"+34 954 35 67 67",
    "sg:postcode":"41008",
    "sg:province":"Sevilla",
    "wof:name":"Almacenes Sedasur S.l.",
    "wof:placetype":"venue"
},
  "geometry": {"coordinates":[-5.9680085182,37.4008789062],"type":"Point"}
}