{
  "type": "Feature",
  "properties": {
    "addr:full":"Carr Llebre, 3 Girona Girona 17004",
    "addr:housenumber":"3",
    "addr:postcode":"17004",
    "addr:street":"Carr Llebre",
    "iso:country":"ES",
    "sg:address":"Carr Llebre, 3",
    "sg:city":"Girona",
    "sg:orig_category":"Inmobiliaria (agencias)",
    "sg:phone":"+34 972 20 14 45",
    "sg:postcode":"17004",
    "sg:province":"Girona",
    "wof:name":"Torre De Raset S.l.",
    "wof:placetype":"venue"
},
  "geometry": {"coordinates":[2.8257930279,41.9841194153],"type":"Point"}
}