{
  "type": "Feature",
  "properties": {
    "iso:country":"ES",
    "sg:address":"Calle de Mayor, 4",
    "sg:city":"Sangonera La Verde O Ermita Nueva",
    "sg:orig_category":"Quincaller\u00cda (al Por Menor)",
    "sg:phone":"+34 968 86 67 58",
    "sg:postcode":"30833",
    "sg:province":"Murcia",
    "wof:name":"Mu\u00f1oz Noguera Concepcion",
    "wof:placetype":"venue"
},
  "geometry": {"coordinates":[-1.2084690332,37.9326210022],"type":"Point"}
}