{
  "type": "Feature",
  "properties": {
    "addr:full":"Ctra. Eivissa S. Antoni, Km. 0009,3 S. Rafel Creu Islas Baleares 07816",
    "addr:postcode":"07816",
    "addr:street":"Ctra. Eivissa S. Antoni Km. 0009,3 S. Rafel Creu Islas",
    "iso:country":"ES",
    "sg:address":"Ctra. Eivissa S. Antoni, Km. 0009,3",
    "sg:city":"S. Rafel Creu",
    "sg:orig_category":"Fabricaci\u00d3n De Juegos Y Juguetes",
    "sg:phone":"+34 971 19 84 49",
    "sg:postcode":"07816",
    "sg:province":"Islas Baleares",
    "sg:website":"www.luiscalle.com",
    "wof:name":"Juan Prats Alicia",
    "wof:placetype":"venue"
},
  "geometry": {"coordinates":[1.3828419447,39.0397987366],"type":"Point"}
}