{
  "type": "Feature",
  "properties": {
    "addr:full":"Calle de Aguilar Del Rio, 7 Madrid Madrid 28044",
    "addr:housenumber":"7",
    "addr:postcode":"madrid;28044",
    "addr:street":"Calle De Aguilar Del Rio",
    "iso:country":"ES",
    "sg:address":"Calle de Aguilar Del Rio, 7",
    "sg:city":"Madrid",
    "sg:orig_category":"Cl\u00cdnicas M\u00c9dicas",
    "sg:phone":"+34 915 08 95 79",
    "sg:postcode":"28044",
    "sg:province":"Madrid",
    "wof:name":"Hinojosa Lucena Rafael",
    "wof:placetype":"venue"
},
  "geometry": {"coordinates":[-3.758988142,40.3714408875],"type":"Point"}
}