{
  "type": "Feature",
  "properties": {
    "iso:country":"ES",
    "sg:address":"Ctra. Cuerva, Km. 0000,3",
    "sg:city":"Galvez",
    "sg:orig_category":"Negocio De Materiales De Construcci\u00d3n",
    "sg:phone":"+34 925 40 08 17",
    "sg:postcode":"45164",
    "sg:province":"Toledo",
    "wof:name":"Comercial Disama S.l.",
    "wof:placetype":"venue"
},
  "geometry": {"coordinates":[-4.2757091522,39.7027244568],"type":"Point"}
}