{
  "type": "Feature",
  "properties": {
    "addr:full":"Avda Madrid (de), 4 Xinzo De Limia Ourense 32630",
    "addr:housenumber":"4",
    "addr:postcode":"32630",
    "addr:street":"Avda Madrid De",
    "iso:country":"ES",
    "sg:address":"Avda Madrid (de), 4",
    "sg:city":"Xinzo De Limia",
    "sg:orig_category":"Telas Y Sedas (al Por Menor)",
    "sg:phone":"+34 988 46 25 82",
    "sg:postcode":"32630",
    "sg:province":"Ourense",
    "wof:name":"Almacenes Alfredo Romero S. A.",
    "wof:placetype":"venue"
},
  "geometry": {"coordinates":[-7.7101249695,42.0602836609],"type":"Point"}
}