{
  "type": "Feature",
  "properties": {
    "iso:country":"ES",
    "sg:address":"Calle de Zabaleta, 1",
    "sg:city":"Donostia-san Sebastian",
    "sg:orig_category":"Peluqueros: De Se\u00d1oras",
    "sg:phone":"+34 943 28 76 19",
    "sg:postcode":"20002",
    "sg:province":"Guip\u00f9zcoa",
    "wof:name":"Sesma Ochoa Maria Carmen",
    "wof:placetype":"venue"
},
  "geometry": {"coordinates":[-1.9769979715,43.3226737976],"type":"Point"}
}