{
  "type": "Feature",
  "properties": {
    "iso:country":"ES",
    "sg:address":"Calle de Almaraz, 2",
    "sg:city":"Zamora",
    "sg:orig_category":"Molduras, Junquillos, Listones Y Molduras Perforadas",
    "sg:phone":"+34 980 51 95 91",
    "sg:postcode":"49027",
    "sg:province":"Zamora",
    "wof:name":"Abad Vayre Cb",
    "wof:placetype":"venue"
},
  "geometry": {"coordinates":[-5.755739,41.501713],"type":"Point"}
}