{
  "type": "Feature",
  "properties": {
    "addr:full":"Campanar, S/n Castalla Alicante 03420",
    "addr:housenumber":"s / n",
    "addr:postcode":"03420",
    "iso:country":"ES",
    "sg:address":"Campanar, S/n",
    "sg:city":"Castalla",
    "sg:orig_category":"Tratamiento Y Transformaci\u00d3n De Tejidos",
    "sg:phone":"+34 966 54 30 70",
    "sg:postcode":"03420",
    "sg:province":"Alicante",
    "wof:name":"Gestion De Corte Industrrial De Tejidos S.l.",
    "wof:placetype":"venue"
},
  "geometry": {"coordinates":[-0.665948987,38.597328186],"type":"Point"}
}