{
  "type": "Feature",
  "properties": {
    "iso:country":"ES",
    "sg:address":"Calle de San Ignacio, 14",
    "sg:city":"Pilas",
    "sg:orig_category":"Supermercados Y Hipermercados",
    "sg:phone":"+34 954 75 14 49",
    "sg:postcode":"41840",
    "sg:province":"Sevilla",
    "wof:name":"Umbrete\u00f1a De Alimentacion S.l.",
    "wof:placetype":"venue"
},
  "geometry": {"coordinates":[-6.3005619049,37.304058075],"type":"Point"}
}