{
  "type": "Feature",
  "properties": {
    "addr:full":"Rua San Pedro, 62 Lugo Lugo 27001",
    "addr:housenumber":"62",
    "addr:postcode":"27001",
    "addr:street":"Rua San Pedro",
    "iso:country":"ES",
    "sg:address":"Rua San Pedro, 62",
    "sg:city":"Lugo",
    "sg:orig_category":"Electricidad (montaje, Ensamblaje De Componentes)",
    "sg:phone":"+34 982 22 40 04",
    "sg:postcode":"27001",
    "sg:province":"Lugo",
    "wof:name":"Ron Rodriguez Luis",
    "wof:placetype":"venue"
},
  "geometry": {"coordinates":[-7.5531749725,43.0103302002],"type":"Point"}
}