{
  "type": "Feature",
  "properties": {
    "iso:country":"ES",
    "sg:address":"Pol. Ind. San Fernando, 36",
    "sg:city":"Sevilla",
    "sg:orig_category":"Cojinetes De Bolas, Agujas Y Rodillos (fabricaci\u00d3n, Al Por Mayor)",
    "sg:phone":"+34 954 25 78 66",
    "sg:postcode":"41006",
    "sg:province":"Sevilla",
    "sg:website":"www.rodamientosbulnes.com",
    "wof:name":"Rodamientos Bulnes S.l.",
    "wof:placetype":"venue"
},
  "geometry": {"coordinates":[-5.9558591843,37.3783111572],"type":"Point"}
}