{
  "type": "Feature",
  "properties": {
    "addr:full":"Urbz Maestrazgo, S/n Valderrobres Teruel 44580",
    "addr:housenumber":"/ n",
    "addr:postcode":"44580",
    "addr:street":"Maestrazgo S",
    "iso:country":"ES",
    "sg:address":"Urbz Maestrazgo, S/n",
    "sg:city":"Valderrobres",
    "sg:orig_category":"Tintes (fabricaci\u00d3n, Al Por Mayor)",
    "sg:phone":"+34 978 85 07 21",
    "sg:postcode":"44580",
    "sg:province":"Teruel",
    "wof:name":"Estecha Celma Isaias",
    "wof:placetype":"venue"
},
  "geometry": {"coordinates":[0.1560399979,40.8723564148],"type":"Point"}
}