{
  "type": "Feature",
  "properties": {
    "addr:full":"Rond Nelle, 15 Coru\u00d1a La Coru\u00f1a 15007",
    "addr:housenumber":"15",
    "addr:postcode":"15007",
    "addr:street":"Rond Nelle;La Corun\u0303A",
    "iso:country":"ES",
    "sg:address":"Rond Nelle, 15",
    "sg:city":"Coru\u00d1a",
    "sg:orig_category":"Fabricaci\u00d3n, Importaci\u00d3n De Material Y Sistemas De Telecomunicaciones",
    "sg:phone":"+34 981 23 31 32",
    "sg:postcode":"15007",
    "sg:province":"La Coru\u00f1a",
    "wof:name":"Incotel S.l.",
    "wof:placetype":"venue"
},
  "geometry": {"coordinates":[-8.4115686417,43.3556938171],"type":"Point"}
}