{
  "type": "Feature",
  "properties": {
    "addr:full":"Calle de Mayor, 15 Torrijos Toledo 45500",
    "addr:housenumber":"15",
    "addr:postcode":"45500",
    "addr:street":"Calle De Mayor",
    "iso:country":"ES",
    "sg:address":"Calle de Mayor, 15",
    "sg:city":"Torrijos",
    "sg:orig_category":"Conservas De Carnes (fabricaci\u00d3n, Al Por Mayor)",
    "sg:phone":"+34 925 76 26 76",
    "sg:postcode":"45500",
    "sg:province":"Toledo",
    "wof:name":"Cooperativa Deshuese De Torrijos",
    "wof:placetype":"venue"
},
  "geometry": {"coordinates":[-4.2839951515,39.9813232422],"type":"Point"}
}