{
  "type": "Feature",
  "properties": {
    "addr:full":"Calle de Fuencarral, 132 Madrid Madrid 28010",
    "addr:housenumber":"132",
    "addr:postcode":"28010",
    "addr:street":"Calle De Fuencarral",
    "iso:country":"ES",
    "sg:address":"Calle de Fuencarral, 132",
    "sg:city":"Madrid",
    "sg:orig_category":"Lencer\u00cda Femenina, Corseter\u00cda, Trajes De Ba\u00d1o (al Por Menor)",
    "sg:phone":"+34 915 93 02 95",
    "sg:postcode":"28010",
    "sg:province":"Madrid",
    "sg:website":"www.womensecret.com",
    "wof:name":"Cortefiel S.a.",
    "wof:placetype":"venue"
},
  "geometry": {"coordinates":[-3.7029941082,40.4310417175],"type":"Point"}
}