{
  "type": "Feature",
  "properties": {
    "addr:full":"Calle de Pozo, 6 Pe\u00f1aparda Salamanca 37523",
    "addr:housenumber":"6",
    "addr:postcode":"37523",
    "addr:street":"Calle De Pozo",
    "iso:country":"ES",
    "sg:address":"Calle de Pozo, 6",
    "sg:city":"Pe\u00f1aparda",
    "sg:orig_category":"Iglesia Cat\u00d3lica",
    "sg:phone":"+34 923 48 64 02",
    "sg:postcode":"37523",
    "sg:province":"Salamanca",
    "wof:name":"Obispado De Ciudad Rodrigo",
    "wof:placetype":"venue"
},
  "geometry": {"coordinates":[-6.6694087982,40.32213974],"type":"Point"}
}