{
  "type": "Feature",
  "properties": {
    "addr:full":"Calle de San Pedro, 34 Lezaun Navarra 31177",
    "addr:housenumber":"34",
    "addr:postcode":"31177",
    "addr:street":"Calle De San Pedro",
    "iso:country":"ES",
    "sg:address":"Calle de San Pedro, 34",
    "sg:city":"Lezaun",
    "sg:orig_category":"Cr\u00cda De Animales",
    "sg:phone":"+34 948 54 20 42",
    "sg:postcode":"31177",
    "sg:province":"Navarra",
    "wof:name":"Diez De Ulzurrun Munarriz Y Ochandorena Nu\u00f1ez S.c.",
    "wof:placetype":"venue"
},
  "geometry": {"coordinates":[-1.9931089878,42.7772483826],"type":"Point"}
}