{
  "type": "Feature",
  "properties": {
    "iso:country":"ES",
    "sg:address":"Carr Sta Caterina, 9",
    "sg:city":"Igualada",
    "sg:orig_category":"Prendas Y Chalecos De Punto (al Por Menor)",
    "sg:phone":"+34 938 03 34 39",
    "sg:postcode":"08700",
    "sg:province":"Barcelona",
    "wof:name":"Guisado Vilapri\u00f1o Maria",
    "wof:placetype":"venue"
},
  "geometry": {"coordinates":[1.6149439812,41.5803108215],"type":"Point"}
}