{
  "type": "Feature",
  "properties": {
    "addr:full":"Ctra. Pozo Alcon, 3 Zujar Granada 18811",
    "addr:housenumber":"3",
    "addr:postcode":"18811",
    "addr:street":"Ctra. Pozo Alcon",
    "iso:country":"ES",
    "sg:address":"Ctra. Pozo Alcon, 3",
    "sg:city":"Zujar",
    "sg:orig_category":"Tiendas De Grano, Frutas Y Legumbres Secas (al Por Menor)",
    "sg:phone":"+34 958 71 65 42",
    "sg:postcode":"18811",
    "sg:province":"Granada",
    "wof:name":"Almendras Ferqui S.l.",
    "wof:placetype":"venue"
},
  "geometry": {"coordinates":[-2.8377656937,37.5407905579],"type":"Point"}
}