{
  "type": "Feature",
  "properties": {
    "addr:full":"Plaz Mayor, 6 Aspe Alicante 03680",
    "addr:housenumber":"6",
    "addr:postcode":"03680",
    "addr:street":"Plaz Mayor",
    "iso:country":"ES",
    "sg:address":"Plaz Mayor, 6",
    "sg:city":"Aspe",
    "sg:orig_category":"Iglesia Cat\u00d3lica",
    "sg:phone":"+34 965 49 21 88",
    "sg:postcode":"03680",
    "sg:province":"Alicante",
    "wof:name":"Parroquia Nuestra Se\u00f1ora Del Socorro",
    "wof:placetype":"venue"
},
  "geometry": {"coordinates":[-0.7684069872,38.3459281921],"type":"Point"}
}