{
  "type": "Feature",
  "properties": {
    "iso:country":"ES",
    "sg:address":"Calle de Silicio, 34",
    "sg:city":"Torrejon Ardoz",
    "sg:orig_category":"Panader\u00cdas, Panader\u00cdas",
    "sg:phone":"+34 916 76 95 46",
    "sg:postcode":"28850",
    "sg:province":"Madrid",
    "wof:name":"Hostelera Virgen Del Espino S.a.",
    "wof:placetype":"venue"
},
  "geometry": {"coordinates":[-3.4613699913,40.4473953247],"type":"Point"}
}