{
  "type": "Feature",
  "properties": {
    "addr:full":"Calle de Monte Aya, 4 Madrid Madrid 28031",
    "addr:housenumber":"4",
    "addr:postcode":"28031",
    "addr:street":"Calle De Monte Aya",
    "iso:country":"ES",
    "sg:address":"Calle de Monte Aya, 4",
    "sg:city":"Madrid",
    "sg:orig_category":"Telas Y Sedas (al Por Menor)",
    "sg:phone":"+34 913 03 41 59",
    "sg:postcode":"28031",
    "sg:province":"Madrid",
    "wof:name":"Marin Fortes Manuela",
    "wof:placetype":"venue"
},
  "geometry": {"coordinates":[-3.6229989529,40.3780632019],"type":"Point"}
}