{
  "type": "Feature",
  "properties": {
    "addr:full":"Calle de Argelete, 5 Fuentelespino De Haro Cuenca 16647",
    "addr:housenumber":"5",
    "addr:postcode":"16647",
    "addr:street":"Calle De Argelete",
    "iso:country":"ES",
    "sg:address":"Calle de Argelete, 5",
    "sg:city":"Fuentelespino De Haro",
    "sg:orig_category":"Centros De Educaci\u00d3n Especial",
    "sg:phone":"+34 967 18 78 48",
    "sg:postcode":"16647",
    "sg:province":"Cuenca",
    "wof:name":"Colegio Rural Agrupado-aula",
    "wof:placetype":"venue"
},
  "geometry": {"coordinates":[-2.6689198017,39.687713623],"type":"Point"}
}