{
  "type": "Feature",
  "properties": {
    "addr:full":"Ctra San Bartolome, Km. 0001,2 Argana Baja Las Palmas 35500",
    "addr:postcode":"35500",
    "addr:street":"Ctra San Bartolome Km. 0001,2",
    "iso:country":"ES",
    "sg:address":"Ctra San Bartolome, Km. 0001,2",
    "sg:city":"Argana Baja",
    "sg:orig_category":"Transportes Especiales",
    "sg:phone":"+34 928 81 01 20",
    "sg:postcode":"35500",
    "sg:province":"Las Palmas",
    "sg:website":"www.seur.es",
    "wof:name":"Valle Lopera S.l.",
    "wof:placetype":"venue"
},
  "geometry": {"coordinates":[-13.5490036011,28.9582099915],"type":"Point"}
}