{
  "type": "Feature",
  "properties": {
    "addr:full":"Calle de Juan De Olazabal, 2 Errenteria Guip\u00f9zcoa 20100",
    "addr:housenumber":"2",
    "addr:postcode":"20100",
    "addr:street":"Calle De Juan De Olazabal;Guipu\u0300Zcoa",
    "iso:country":"ES",
    "sg:address":"Calle de Juan De Olazabal, 2",
    "sg:city":"Errenteria",
    "sg:orig_category":"Peluqueros: De Se\u00d1oras",
    "sg:phone":"+34 943 52 91 68",
    "sg:postcode":"20100",
    "sg:province":"Guip\u00f9zcoa",
    "wof:name":"Ainhoa Errandonea Balda",
    "wof:placetype":"venue"
},
  "geometry": {"coordinates":[-1.9030708075,43.3140525818],"type":"Point"}
}