{
  "type": "Feature",
  "properties": {
    "iso:country":"ES",
    "sg:address":"Avda Domingo Bueno, 29",
    "sg:city":"Pontenova",
    "sg:orig_category":"Quincaller\u00cda (al Por Menor)",
    "sg:phone":"+34 986 33 51 11",
    "sg:postcode":"36400",
    "sg:province":"Pontevedra",
    "wof:name":"Ferreteria Pontenova",
    "wof:placetype":"venue"
},
  "geometry": {"coordinates":[-8.6179990768,42.1610298157],"type":"Point"}
}