{
  "type": "Feature",
  "properties": {
    "iso:country":"ES",
    "sg:address":"Calle de Lepanto, 49",
    "sg:city":"Palmas De Gran Canaria",
    "sg:orig_category":"Art\u00cdculos De Regalo (al Por Menor)",
    "sg:phone":"+34 928 27 54 23",
    "sg:postcode":"35010",
    "sg:province":"Las Palmas",
    "wof:name":"Perez Guerra Armando",
    "wof:placetype":"venue"
},
  "geometry": {"coordinates":[-15.4435405731,28.1283187866],"type":"Point"}
}