{
  "type": "Feature",
  "properties": {
    "addr:full":"Calle de Galicia, 12 Fuenlabrada Madrid 28942",
    "addr:housenumber":"12",
    "addr:postcode":"28942",
    "addr:street":"Calle De Galicia",
    "iso:country":"ES",
    "sg:address":"Calle de Galicia, 12",
    "sg:city":"Fuenlabrada",
    "sg:orig_category":"Mec\u00c1nico Del Autom\u00d3vil",
    "sg:phone":"+34 916 08 47 52",
    "sg:postcode":"28942",
    "sg:province":"Madrid",
    "wof:name":"Talleres Ij S.l",
    "wof:placetype":"venue"
},
  "geometry": {"coordinates":[-3.8098170757,40.2952346802],"type":"Point"}
}