{
  "type": "Feature",
  "properties": {
    "addr:full":"Calle de Tortola, 1 Valladolid Valladolid 47012",
    "addr:housenumber":"1",
    "addr:postcode":"47012",
    "addr:street":"Calle De Tortola",
    "iso:country":"ES",
    "sg:address":"Calle de Tortola, 1",
    "sg:city":"Valladolid",
    "sg:orig_category":"Carnicer\u00cdas, Carnicer\u00cdas",
    "sg:phone":"+34 983 39 58 62",
    "sg:postcode":"47012",
    "sg:province":"Valladolid",
    "wof:name":"Sanz Aguado Maria Del Carmen",
    "wof:placetype":"venue"
},
  "geometry": {"coordinates":[-4.7134690285,41.6467933655],"type":"Point"}
}