{
  "type": "Feature",
  "properties": {
    "iso:country":"ES",
    "sg:address":"Avda Raza (la), 22",
    "sg:city":"Sevilla",
    "sg:orig_category":"Congelados: Productos Alimentarios (fabricaci\u00d3n, Al Por Mayor)",
    "sg:phone":"+34 954 23 62 47",
    "sg:postcode":"41012",
    "sg:province":"Sevilla",
    "wof:name":"Nueva Congemar S.l.",
    "wof:placetype":"venue"
},
  "geometry": {"coordinates":[-5.9896430969,37.3662452698],"type":"Point"}
}