{
  "type": "Feature",
  "properties": {
    "iso:country":"ES",
    "sg:address":"Ctra Villamanrique (pi Ventolines), S/n",
    "sg:city":"Pilas",
    "sg:orig_category":"Lavado, Limpieza De Veh\u00cdculos",
    "sg:phone":"+34 954 75 02 32",
    "sg:postcode":"41840",
    "sg:province":"Sevilla",
    "wof:name":"Leonardo Ruiz Manuel",
    "wof:placetype":"venue"
},
  "geometry": {"coordinates":[-6.3119745255,37.3107185364],"type":"Point"}
}