{
  "type": "Feature",
  "properties": {
    "iso:country":"ES",
    "sg:address":"Poligono Industrial, 1",
    "sg:city":"Ascoy",
    "sg:orig_category":"Empresas De Carpinter\u00cda De Madera",
    "sg:phone":"+34 968 76 26 43",
    "sg:postcode":"30530",
    "sg:province":"Murcia",
    "wof:name":"Marin Aroga Jose",
    "wof:placetype":"venue"
},
  "geometry": {"coordinates":[-1.4241739511,38.2379302979],"type":"Point"}
}