{
  "type": "Feature",
  "properties": {
    "iso:country":"ES",
    "sg:address":"Urb La Fustera, S/n",
    "sg:city":"Benissa",
    "sg:orig_category":"Molduras, Junquillos, Listones Y Molduras Perforadas",
    "sg:phone":"+34 966 49 83 29",
    "sg:postcode":"03720",
    "sg:province":"Alicante",
    "wof:name":"Comidas Casa Manolo S.l.",
    "wof:placetype":"venue"
},
  "geometry": {"coordinates":[0.0762040019,38.6695137024],"type":"Point"}
}