{
  "type": "Feature",
  "properties": {
    "addr:full":"Av Cartagena, 16 El Altet Alicante 03195",
    "addr:housenumber":"16",
    "addr:postcode":"03195",
    "addr:street":"Av Cartagena;El Altet",
    "iso:country":"ES",
    "sg:address":"Av Cartagena, 16",
    "sg:city":"El Altet",
    "sg:orig_category":"Alquiler De Veh\u00cdculos: Turismos Y Utilitarios",
    "sg:phone":"+34 965 68 91 43",
    "sg:postcode":"03195",
    "sg:province":"Alicante",
    "wof:name":"De Diego Morera Francisco Javier",
    "wof:placetype":"venue"
},
  "geometry": {"coordinates":[-0.5206289887,38.2537002563],"type":"Point"}
}