{
  "type": "Feature",
  "properties": {
    "addr:full":"Av Estanislau Figueres (d'), 11 Tarragona Tarragona 43003",
    "addr:housenumber":"11",
    "addr:postcode":"43003",
    "addr:street":"Av Estanislau Figueres D '",
    "iso:country":"ES",
    "sg:address":"Av Estanislau Figueres (d'), 11",
    "sg:city":"Tarragona",
    "sg:orig_category":"Sexshops",
    "sg:phone":"+34 977 22 20 67",
    "sg:postcode":"43003",
    "sg:province":"Tarragona",
    "wof:name":"Lisboa S.c.p.",
    "wof:placetype":"venue"
},
  "geometry": {"coordinates":[1.2513560057,41.1178741455],"type":"Point"}
}