{
  "type": "Feature",
  "properties": {
    "iso:country":"ES",
    "sg:address":"Calle de Serafin Escalante, 10",
    "sg:city":"Torrelavega",
    "sg:orig_category":"Pod\u00d3logos: Pedicuros",
    "sg:phone":"+34 942 89 80 40",
    "sg:postcode":"39300",
    "sg:province":"Cantabria",
    "wof:name":"Cayon Michelena Isabel",
    "wof:placetype":"venue"
},
  "geometry": {"coordinates":[-4.0487370491,43.3493041992],"type":"Point"}
}