{
  "type": "Feature",
  "properties": {
    "iso:country":"ES",
    "sg:address":"Avda Dilar (de), 78",
    "sg:city":"Granada",
    "sg:orig_category":"Ropa Para Se\u00d1oras Y Caballeros (al Por Menor)",
    "sg:phone":"+34 958 81 25 77",
    "sg:postcode":"18007",
    "sg:province":"Granada",
    "wof:name":"Pe\u00f1a Garzon Carmen",
    "wof:placetype":"venue"
},
  "geometry": {"coordinates":[-3.6005420685,37.1548957825],"type":"Point"}
}