{
  "type": "Feature",
  "properties": {
    "addr:full":"Avda Ingenieros Del Ministerio Obras Publicas, 11 Haro La Rioja 26200",
    "addr:housenumber":"11",
    "addr:postcode":"26200",
    "addr:street":"Avda Ingenieros Del",
    "iso:country":"ES",
    "sg:address":"Avda Ingenieros Del Ministerio Obras Publicas, 11",
    "sg:city":"Haro",
    "sg:orig_category":"Contenedores (mercanc\u00cdas)",
    "sg:phone":"+34 941 31 06 12",
    "sg:postcode":"26200",
    "sg:province":"La Rioja",
    "wof:name":"Lumbreras Julian Jesus",
    "wof:placetype":"venue"
},
  "geometry": {"coordinates":[-2.8537869453,42.5761985779],"type":"Point"}
}