{
  "type": "Feature",
  "properties": {
    "iso:country":"ES",
    "sg:address":"Calle de Q, 6",
    "sg:city":"Mutiloabeiti",
    "sg:orig_category":"Cubiertas, Plomer\u00cda, Galvanizados",
    "sg:phone":"+34 948 23 42 16",
    "sg:postcode":"31192",
    "sg:province":"Navarra",
    "wof:name":"Fontaneria San Vicente Hermanos S.l.",
    "wof:placetype":"venue"
},
  "geometry": {"coordinates":[-1.6288410425,42.7864341736],"type":"Point"}
}