{
  "type": "Feature",
  "properties": {
    "iso:country":"ES",
    "sg:address":"Avda Perez Galdos, 43",
    "sg:city":"Logro\u00f1o",
    "sg:classifiers":[
        {
            "category":"Personal",
            "subcategory":"Barber",
            "type":"Services"
        }
    ],
    "sg:phone":"+34 941 22 02 96",
    "sg:postcode":"26002",
    "sg:province":"La Rioja",
    "sg:tags":[
        "caballeros",
        "de",
        "peluqueros"
    ],
    "wof:name":"Garcia Alvarez Juan",
    "wof:placetype":"venue"
},
  "geometry": {"coordinates":[-2.4525325298,42.4623947144],"type":"Point"}
}