{
  "type": "Feature",
  "properties": {
    "iso:country":"ES",
    "sg:address":"Rua Independencia, 6",
    "sg:city":"Portonovo",
    "sg:orig_category":"Asociaciones Y Clubs Deportivos",
    "sg:phone":"+34 986 72 04 27",
    "sg:postcode":"36970",
    "sg:province":"Pontevedra",
    "wof:name":"Deportes Maniotas S.l.",
    "wof:placetype":"venue"
},
  "geometry": {"coordinates":[-8.8260602951,42.3952865601],"type":"Point"}
}