{
  "type": "Feature",
  "properties": {
    "addr:full":"Carrer de Sant Gaieta, 115 Terrassa Barcelona 08221",
    "addr:housenumber":"115",
    "addr:postcode":"08221",
    "addr:street":"Carrer De Sant Gaieta",
    "iso:country":"ES",
    "sg:address":"Carrer de Sant Gaieta, 115",
    "sg:city":"Terrassa",
    "sg:orig_category":"Electricidad Veh\u00cdculo",
    "sg:phone":"+34 937 88 04 58",
    "sg:postcode":"08221",
    "sg:province":"Barcelona",
    "wof:name":"Electric Motor Valles S.l.",
    "wof:placetype":"venue"
},
  "geometry": {"coordinates":[2.0089030266,41.5690841675],"type":"Point"}
}