{
  "type": "Feature",
  "properties": {
    "addr:full":"Calle de Rambla Del Manjon, 16 Motril Granada 18600",
    "addr:housenumber":"16",
    "addr:postcode":"18600",
    "addr:street":"Calle De Rambla Del Manjon",
    "iso:country":"ES",
    "sg:address":"Calle de Rambla Del Manjon, 16",
    "sg:city":"Motril",
    "sg:orig_category":"Agencias Y Asesores De Publicidad",
    "sg:phone":"+34 958 83 36 57",
    "sg:postcode":"18600",
    "sg:province":"Granada",
    "wof:name":"Reguero Bustos Emilio",
    "wof:placetype":"venue"
},
  "geometry": {"coordinates":[-3.5152790546,36.7456130981],"type":"Point"}
}