{
  "type": "Feature",
  "properties": {
    "iso:country":"ES",
    "sg:address":"Cmno Borja, S/n",
    "sg:city":"Alacant",
    "sg:orig_category":"Molduras, Junquillos, Listones Y Molduras Perforadas",
    "sg:phone":"+34 965 11 26 13",
    "sg:postcode":"03006",
    "sg:province":"Alicante",
    "wof:name":"Gomez-lobo Guillen Angel",
    "wof:placetype":"venue"
},
  "geometry": {"coordinates":[-0.5227890015,38.3488197327],"type":"Point"}
}