{
  "type": "Feature",
  "properties": {
    "iso:country":"ES",
    "sg:address":"Calle de Hortaleza, 3",
    "sg:city":"Madrid",
    "sg:orig_category":"Fabricaci\u00d3n De Sobres, Bolsas Y Fundas",
    "sg:phone":"+34 915 22 61 37",
    "sg:postcode":"28004",
    "sg:province":"Madrid",
    "wof:name":"Tarin Garcia Esteban",
    "wof:placetype":"venue"
},
  "geometry": {"coordinates":[-3.7010715008,40.4202690125],"type":"Point"}
}