{
  "type": "Feature",
  "properties": {
    "addr:full":"Carr Ballesteries, 45 Girona Girona 17003",
    "addr:housenumber":"45",
    "addr:postcode":"17003",
    "addr:street":"Carr Ballesteries",
    "iso:country":"ES",
    "sg:address":"Carr Ballesteries, 45",
    "sg:city":"Girona",
    "sg:orig_category":"Molduras, Junquillos, Listones Y Molduras Perforadas",
    "sg:phone":"+34 972 20 29 11",
    "sg:postcode":"17003",
    "sg:province":"Girona",
    "wof:name":"Grabalosa Benet Carles",
    "wof:placetype":"venue"
},
  "geometry": {"coordinates":[2.8187448978,41.9808616638],"type":"Point"}
}