{
  "type": "Feature",
  "properties": {
    "addr:full":"Plaz Ayuntamiento Del, 3 Tineo Asturias 33870",
    "addr:postcode":"33870",
    "iso:country":"ES",
    "sg:address":"Plaz Ayuntamiento Del, 3",
    "sg:city":"Tineo",
    "sg:orig_category":"Bancos",
    "sg:phone":"+34 985 80 14 14",
    "sg:postcode":"33870",
    "sg:province":"Asturias",
    "sg:website":"www.bancoherrero.com",
    "wof:name":"Banc Sabadell S.a.",
    "wof:placetype":"venue"
},
  "geometry": {"coordinates":[-6.4165468216,43.3338775635],"type":"Point"}
}