{
  "type": "Feature",
  "properties": {
    "iso:country":"ES",
    "sg:address":"Barr Ferial (el), 142",
    "sg:city":"Saron",
    "sg:orig_category":"Equitaci\u00d3n: Guarnicioner\u00cda, Equipo (al Por Menor)",
    "sg:phone":"+34 942 56 37 29",
    "sg:postcode":"39620",
    "sg:province":"Cantabria",
    "wof:name":"Revuelta Ocejo Antonio",
    "wof:placetype":"venue"
},
  "geometry": {"coordinates":[-3.8524339199,43.3249206543],"type":"Point"}
}