{
  "type": "Feature",
  "properties": {
    "iso:country":"ES",
    "sg:address":"Calle de Cami Molino Nuevo, 4",
    "sg:city":"Alcora",
    "sg:orig_category":"Carnicer\u00cdas, Carnicer\u00cdas",
    "sg:phone":"+34 964 36 18 02",
    "sg:postcode":"12110",
    "sg:province":"Castell\u00f3n",
    "wof:name":"Gil Garcia Alejandro",
    "wof:placetype":"venue"
},
  "geometry": {"coordinates":[-0.2114306986,40.0798912048],"type":"Point"}
}