{
  "type": "Feature",
  "properties": {
    "iso:country":"ES",
    "sg:address":"Plaz Alcalde Agatangelo Soler, 7",
    "sg:city":"Alacant",
    "sg:orig_category":"Asesor\u00cdas",
    "sg:phone":"+34 965 91 70 80",
    "sg:postcode":"03012",
    "sg:province":"Alicante",
    "wof:name":"La Estrella S.a. De Seguros",
    "wof:placetype":"venue"
},
  "geometry": {"coordinates":[-0.4718280137,38.3657531738],"type":"Point"}
}