{
  "type": "Feature",
  "properties": {
    "iso:country":"ES",
    "sg:address":"Calle de Cebreros, 13",
    "sg:city":"Madrid",
    "sg:orig_category":"Molduras, Junquillos, Listones Y Molduras Perforadas",
    "sg:phone":"+34 914 70 15 64",
    "sg:postcode":"28011",
    "sg:province":"Madrid",
    "wof:name":"Hermanos Cid Hosteleria S.l.",
    "wof:placetype":"venue"
},
  "geometry": {"coordinates":[-3.7428014278,40.4048309326],"type":"Point"}
}