{
  "type": "Feature",
  "properties": {
    "iso:country":"ES",
    "sg:address":"Av Torrelles, 27",
    "sg:city":"Sant Vicen\u00c7 Dels Horts",
    "sg:orig_category":"Muebles Y Accesorios Para Cocinas Y Cuartos De Ba\u00d1o (al Por Menor)",
    "sg:phone":"+34 936 56 16 75",
    "sg:postcode":"08620",
    "sg:province":"Barcelona",
    "wof:name":"Muebles Roldan S.l.",
    "wof:placetype":"venue"
},
  "geometry": {"coordinates":[1.9929020405,41.3786888123],"type":"Point"}
}