{
  "type": "Feature",
  "properties": {
    "addr:full":"Calle de Villamartin, 30 Cascon Nava Palencia 34192",
    "addr:housenumber":"30",
    "addr:postcode":"34192",
    "addr:street":"Calle De Villamartin",
    "iso:country":"ES",
    "sg:address":"Calle de Villamartin, 30",
    "sg:city":"Cascon Nava",
    "sg:orig_category":"Contenedores (mercanc\u00cdas)",
    "sg:phone":"+34 979 83 31 06",
    "sg:postcode":"34192",
    "sg:province":"Palencia",
    "wof:name":"Fernandez Diez Jose Maria",
    "wof:placetype":"venue"
},
  "geometry": {"coordinates":[-4.5808391571,42.0539283752],"type":"Point"}
}