{
  "type": "Feature",
  "properties": {
    "addr:full":"Avda Andalucia, 13 Punta Umbria Huelva 21100",
    "addr:housenumber":"13",
    "addr:postcode":"21100",
    "addr:street":"Avda Andalucia",
    "iso:country":"ES",
    "sg:address":"Avda Andalucia, 13",
    "sg:city":"Punta Umbria",
    "sg:orig_category":"Ropa Para Ni\u00d1os (al Por Menor)",
    "sg:phone":"+34 959 31 25 95",
    "sg:postcode":"21100",
    "sg:province":"Huelva",
    "wof:name":"Vizcaino Gallego Angel Luis",
    "wof:placetype":"venue"
},
  "geometry": {"coordinates":[-6.9647898674,37.1842422485],"type":"Point"}
}