{
  "type": "Feature",
  "properties": {
    "iso:country":"ES",
    "sg:address":"Calle de Juan De Austria, 29",
    "sg:city":"Madrid",
    "sg:orig_category":"Bazares, Art\u00cdculos De Limpieza Y De Cocina (al Por Menor)",
    "sg:phone":"+34 915 93 94 66",
    "sg:postcode":"28010",
    "sg:province":"Madrid",
    "wof:name":"Zheng  Hai King",
    "wof:placetype":"venue"
},
  "geometry": {"coordinates":[-3.7000389099,40.4340553284],"type":"Point"}
}