{
  "type": "Feature",
  "properties": {
    "iso:country":"ES",
    "sg:address":"Huracan, 6",
    "sg:city":"Leganes",
    "sg:orig_category":"Transportes Por Carretera: Lotes Completos, Mercanc\u00cdas Diversas",
    "sg:phone":"+34 916 11 66 58",
    "sg:postcode":"28918",
    "sg:province":"Madrid",
    "wof:name":"Alotrans Servicio Directo S.l.",
    "wof:placetype":"venue"
},
  "geometry": {"coordinates":[-3.7999196053,40.3455200195],"type":"Point"}
}