{
  "type": "Feature",
  "properties": {
    "iso:country":"ES",
    "sg:address":"Calle de Manuel Gonzalez Longoria, 12",
    "sg:city":"Madrid",
    "sg:orig_category":"Traductores",
    "sg:phone":"+34 915 94 15 70",
    "sg:postcode":"28010",
    "sg:province":"Madrid",
    "wof:name":"Sartorius Alvargonzalez Javier",
    "wof:placetype":"venue"
},
  "geometry": {"coordinates":[-3.6964609623,40.4286270142],"type":"Point"}
}