{
  "type": "Feature",
  "properties": {
    "addr:full":"Carrer de Providencia, 19 Manresa Barcelona 08241",
    "addr:housenumber":"19",
    "addr:postcode":"08241",
    "addr:street":"Carrer De Providencia",
    "iso:country":"ES",
    "sg:address":"Carrer de Providencia, 19",
    "sg:city":"Manresa",
    "sg:orig_category":"Agencias De Viajes",
    "sg:phone":"+34 938 74 30 39",
    "sg:postcode":"08241",
    "sg:province":"Barcelona",
    "wof:name":"Pius Ponsa Viatges Sl",
    "wof:placetype":"venue"
},
  "geometry": {"coordinates":[1.8364540339,41.7255172729],"type":"Point"}
}