{
  "type": "Feature",
  "properties": {
    "addr:full":"Calle de Jose Pedraja, 12 Torrelavega Cantabria 39300",
    "addr:housenumber":"12",
    "addr:postcode":"39300",
    "addr:street":"Calle De Jose Pedraja",
    "iso:country":"ES",
    "sg:address":"Calle de Jose Pedraja, 12",
    "sg:city":"Torrelavega",
    "sg:orig_category":"Fabricaci\u00d3n De Jabones, Detergentes Y Lej\u00cdas",
    "sg:phone":"+34 942 88 18 57",
    "sg:postcode":"39300",
    "sg:province":"Cantabria",
    "wof:name":"Lesjul S.l.",
    "wof:placetype":"venue"
},
  "geometry": {"coordinates":[-4.0595889091,43.3505363464],"type":"Point"}
}