{
  "type": "Feature",
  "properties": {
    "iso:country":"ES",
    "sg:address":"Ctra De Salas Cenecero, Km. 0001,5",
    "sg:city":"Salas Infantes",
    "sg:orig_category":"Mataderos Y Talleres De Despiezado",
    "sg:phone":"+34 947 38 01 59",
    "sg:postcode":"09600",
    "sg:province":"Burgos",
    "wof:name":"Monpitenoro S.l.",
    "wof:placetype":"venue"
},
  "geometry": {"coordinates":[-3.2826690674,42.0228996277],"type":"Point"}
}