{
  "type": "Feature",
  "properties": {
    "iso:country":"ES",
    "sg:address":"Ctra Cuenca Alcazar, S/n",
    "sg:city":"Almarcha",
    "sg:orig_category":"Ense\u00d1anza, Formaci\u00d3n Profesional: Aprendizaje",
    "sg:phone":"+34 969 29 10 02",
    "sg:postcode":"16740",
    "sg:province":"Cuenca",
    "wof:name":"Direccion General De La Guardia Civil",
    "wof:placetype":"venue"
},
  "geometry": {"coordinates":[-2.3830111027,39.6885032654],"type":"Point"}
}