{
  "type": "Feature",
  "properties": {
    "addr:full":"Av. Aragon, 10 Logro\u00f1o La Rioja 26006",
    "addr:housenumber":"10",
    "addr:postcode":"26006",
    "addr:street":"Av. Aragon;Rioja",
    "iso:country":"ES",
    "sg:address":"Av. Aragon, 10",
    "sg:city":"Logro\u00f1o",
    "sg:orig_category":"Suministros Para Carrocer\u00cdas",
    "sg:phone":"+34 941 23 30 95",
    "sg:postcode":"26006",
    "sg:province":"La Rioja",
    "wof:name":"Carrocerias Viloria S. A.",
    "wof:placetype":"venue"
},
  "geometry": {"coordinates":[-2.4047880173,42.4600486755],"type":"Point"}
}