{
  "type": "Feature",
  "properties": {
    "addr:full":"Avda Lasalle, 31 Salamanca Salamanca 37008",
    "addr:housenumber":"31",
    "addr:postcode":"37008",
    "addr:street":"Avda Lasalle",
    "iso:country":"ES",
    "sg:address":"Avda Lasalle, 31",
    "sg:city":"Salamanca",
    "sg:orig_category":"Electromec\u00c1nica",
    "sg:phone":"+34 923 19 32 05",
    "sg:postcode":"37008",
    "sg:province":"Salamanca",
    "wof:name":"Perez Lugones Luis",
    "wof:placetype":"venue"
},
  "geometry": {"coordinates":[-5.6784558296,40.954864502],"type":"Point"}
}