{
  "type": "Feature",
  "properties": {
    "iso:country":"ES",
    "sg:address":"Calle de Cavanilles, 25",
    "sg:city":"Madrid",
    "sg:orig_category":"M\u00c1quinas De Coser Y De Hacer Punto (al Por Mayor)",
    "sg:phone":"+34 915 51 15 49",
    "sg:postcode":"28007",
    "sg:province":"Madrid",
    "wof:name":"Costura Y Hogar Sal",
    "wof:placetype":"venue"
},
  "geometry": {"coordinates":[-3.6753358841,40.4058685303],"type":"Point"}
}