{
  "type": "Feature",
  "properties": {
    "iso:country":"ES",
    "sg:address":"Rua Vinteun (do), Km. 0001,0",
    "sg:city":"Ourense",
    "sg:orig_category":"Sierras (fabricaci\u00d3n, Al Por Mayor)",
    "sg:phone":"+34 988 21 84 57",
    "sg:postcode":"32001",
    "sg:province":"Ourense",
    "wof:name":"Tecafil S.l.",
    "wof:placetype":"venue"
},
  "geometry": {"coordinates":[-7.8814702034,42.3738327026],"type":"Point"}
}