{
  "type": "Feature",
  "properties": {
    "iso:country":"ES",
    "sg:address":"Calle de La Legion, 1",
    "sg:city":"Valladolid",
    "sg:orig_category":"Cajas Para Embalar",
    "sg:phone":"+34 983 23 61 42",
    "sg:postcode":"47008",
    "sg:province":"Valladolid",
    "wof:name":"Caja Rural Del Duero",
    "wof:placetype":"venue"
},
  "geometry": {"coordinates":[-4.7416119576,41.6267929077],"type":"Point"}
}