{
  "type": "Feature",
  "properties": {
    "addr:full":"Carr Lasauca, 19 Figueres Girona 17600",
    "addr:housenumber":"19",
    "addr:postcode":"17600",
    "addr:street":"Carr Lasauca",
    "iso:country":"ES",
    "sg:address":"Carr Lasauca, 19",
    "sg:city":"Figueres",
    "sg:orig_category":"Inmobiliaria (agencias)",
    "sg:phone":"+34 972 51 43 60",
    "sg:postcode":"17600",
    "sg:province":"Girona",
    "sg:website":"www.expofinques.com",
    "wof:name":"Expofinques S.l.",
    "wof:placetype":"venue"
},
  "geometry": {"coordinates":[2.9586620331,42.2658119202],"type":"Point"}
}