{
  "type": "Feature",
  "properties": {
    "addr:full":"Calle de Zu\u00d1iga, 21 Malaga M\u00e1laga 29006",
    "addr:housenumber":"21",
    "addr:postcode":"29006",
    "addr:street":"Calle De Zun\u0303Iga;Ma\u0301Laga",
    "iso:country":"ES",
    "sg:address":"Calle de Zu\u00d1iga, 21",
    "sg:city":"Malaga",
    "sg:orig_category":"Ense\u00d1anza Variada",
    "sg:phone":"+34 952 31 00 15",
    "sg:postcode":"29006",
    "sg:province":"M\u00e1laga",
    "wof:name":"Llopis Rosado Alicia",
    "wof:placetype":"venue"
},
  "geometry": {"coordinates":[-4.4374661446,36.714805603],"type":"Point"}
}