{
  "type": "Feature",
  "properties": {
    "addr:full":"Calle de Fernando Madro\u00d1al, 18 Alacant Alicante 03007",
    "addr:housenumber":"18",
    "addr:postcode":"03007",
    "addr:street":"Calle De Fernando Madron\u0303Al",
    "iso:country":"ES",
    "sg:address":"Calle de Fernando Madro\u00d1al, 18",
    "sg:city":"Alacant",
    "sg:orig_category":"Farmacias",
    "sg:phone":"+34 965 10 42 07",
    "sg:postcode":"03007",
    "sg:province":"Alicante",
    "wof:name":"Bach Buendia Maria De La Asuncion",
    "wof:placetype":"venue"
},
  "geometry": {"coordinates":[-0.5098531842,38.3410491943],"type":"Point"}
}