{
  "type": "Feature",
  "properties": {
    "addr:full":"Calle de Castello, 32 Alcazar S. Juan Ciudad Real 13600",
    "addr:housenumber":"32",
    "addr:postcode":"13600",
    "addr:street":"Calle De Castello;Alcazar S. Juan Ciudad Real",
    "iso:country":"ES",
    "sg:address":"Calle de Castello, 32",
    "sg:city":"Alcazar S. Juan",
    "sg:orig_category":"Peluquer\u00cdas, Peluquer\u00cda Mixta",
    "sg:phone":"+34 926 55 00 09",
    "sg:postcode":"13600",
    "sg:province":"Ciudad Real",
    "wof:name":"Panadero Rebato Bego\u00f1a",
    "wof:placetype":"venue"
},
  "geometry": {"coordinates":[-3.215041399,39.3991508484],"type":"Point"}
}