{
  "type": "Feature",
  "properties": {
    "addr:full":"Carrer de Sant Domenech (de), 5 Pinell De Brai Tarragona 43594",
    "addr:housenumber":"5",
    "addr:postcode":"43594",
    "addr:street":"Carrer De Sant Domenech De",
    "iso:country":"ES",
    "sg:address":"Carrer de Sant Domenech (de), 5",
    "sg:city":"Pinell De Brai",
    "sg:orig_category":"Inform\u00c1tica, Ofim\u00c1tica (estudios, Asesor\u00cda, Ingenier\u00cda, Formaci\u00d3n)",
    "sg:phone":"+34 977 42 60 25",
    "sg:postcode":"43594",
    "sg:province":"Tarragona",
    "wof:name":"Ebresoft Informatica S.l.u.",
    "wof:placetype":"venue"
},
  "geometry": {"coordinates":[0.5153800249,41.0157585144],"type":"Point"}
}