{
  "type": "Feature",
  "properties": {
    "iso:country":"ES",
    "sg:address":"Calle de San Pedro, S/n",
    "sg:city":"Bembibre",
    "sg:orig_category":"Ferreter\u00cda (diversos)",
    "sg:phone":"+34 987 51 15 20",
    "sg:postcode":"24300",
    "sg:province":"Le\u00f3n",
    "wof:name":"Armafer Bierzo S.l.",
    "wof:placetype":"venue"
},
  "geometry": {"coordinates":[-6.4181585312,42.6057777405],"type":"Point"}
}