{
  "type": "Feature",
  "properties": {
    "iso:country":"ES",
    "sg:address":"Calle de Orense, 49",
    "sg:city":"Madrid",
    "sg:orig_category":"Promotores Constructores",
    "sg:phone":"+34 915 97 01 82",
    "sg:postcode":"28020",
    "sg:province":"Madrid",
    "wof:name":"Construcciones Consa S. L.",
    "wof:placetype":"venue"
},
  "geometry": {"coordinates":[-3.6948950291,40.4554901123],"type":"Point"}
}