{
  "type": "Feature",
  "properties": {
    "addr:full":"Calle de Suiza, 65 Carolina Ja\u00e9n 23200",
    "addr:housenumber":"65",
    "addr:postcode":"23200",
    "addr:street":"Calle De Suiza;Jae\u0301N",
    "iso:country":"ES",
    "sg:address":"Calle de Suiza, 65",
    "sg:city":"Carolina",
    "sg:orig_category":"Electricidad, Electr\u00d3nica: Material Y Suministros (al Por Mayor)",
    "sg:phone":"+34 953 66 07 85",
    "sg:postcode":"23200",
    "sg:province":"Ja\u00e9n",
    "wof:name":"Automaticos Isa S. L.",
    "wof:placetype":"venue"
},
  "geometry": {"coordinates":[-3.6033270359,38.2827377319],"type":"Point"}
}