{
  "type": "Feature",
  "properties": {
    "iso:country":"ES",
    "sg:address":"Calle de Salvador (el), 9",
    "sg:city":"Adra",
    "sg:orig_category":"Cooperativas Agr\u00cdcolas",
    "sg:phone":"+34 950 40 23 24",
    "sg:postcode":"04770",
    "sg:province":"Almer\u00eda",
    "wof:name":"Union De Agricultores Y Ganaderos De Alm",
    "wof:placetype":"venue"
},
  "geometry": {"coordinates":[-3.0110208988,36.7503738403],"type":"Point"}
}