{
  "type": "Feature",
  "properties": {
    "addr:full":"Avda. Finisterre, 286 A Coru\u00f1a La Coru\u00f1a 15010",
    "addr:housenumber":"286 a",
    "addr:postcode":"15010",
    "addr:street":"Avda. Finisterre;Corun\u0303A La Corun\u0303A",
    "iso:country":"ES",
    "sg:address":"Avda. Finisterre, 286",
    "sg:city":"A Coru\u00f1a",
    "sg:orig_category":"Reposter\u00cdas",
    "sg:phone":"+34 981 26 86 20",
    "sg:postcode":"15010",
    "sg:province":"La Coru\u00f1a",
    "wof:name":"Agra Panaderos Desde 1890 S.l.",
    "wof:placetype":"venue"
},
  "geometry": {"coordinates":[-8.4205970764,43.3588256836],"type":"Point"}
}