{
  "type": "Feature",
  "properties": {
    "addr:full":"Carrer de Vicente Aleixandre, 17 Deltebre Tarragona 43580",
    "addr:housenumber":"17",
    "addr:postcode":"43580",
    "addr:street":"Carrer De Vicente Aleixandre",
    "iso:country":"ES",
    "sg:address":"Carrer de Vicente Aleixandre, 17",
    "sg:city":"Deltebre",
    "sg:orig_category":"Distribuci\u00d3n De Petr\u00d3leo Y Derivados",
    "sg:phone":"+34 977 48 07 00",
    "sg:postcode":"43580",
    "sg:province":"Tarragona",
    "wof:name":"Jose Pi\u00f1ana Aliau S.l.",
    "wof:placetype":"venue"
},
  "geometry": {"coordinates":[0.7436559796,40.7173538208],"type":"Point"}
}