{
  "type": "Feature",
  "properties": {
    "addr:full":"Av Torre De La Vila, 1 S. Boi Llobregat Barcelona 08830",
    "addr:housenumber":"1",
    "addr:postcode":"08830",
    "addr:street":"Av Torre De La Vila",
    "iso:country":"ES",
    "sg:address":"Av Torre De La Vila, 1",
    "sg:city":"S. Boi Llobregat",
    "sg:orig_category":"Delegados, Agentes De Tr\u00c1nsito, Auxiliares De Transporte Internacional",
    "sg:phone":"+34 936 40 03 32",
    "sg:postcode":"08830",
    "sg:province":"Barcelona",
    "wof:name":"Logitrans S.l.",
    "wof:placetype":"venue"
},
  "geometry": {"coordinates":[2.0449779034,41.3480606079],"type":"Point"}
}