{
  "type": "Feature",
  "properties": {
    "addr:full":"Calle de Villacarlos, 10 Madrid Madrid 28032",
    "addr:housenumber":"10",
    "addr:postcode":"madrid;28032",
    "addr:street":"Calle De Villacarlos",
    "iso:country":"ES",
    "sg:address":"Calle de Villacarlos, 10",
    "sg:city":"Madrid",
    "sg:orig_category":"Molduras, Junquillos, Listones Y Molduras Perforadas",
    "sg:phone":"+34 917 76 02 26",
    "sg:postcode":"28032",
    "sg:province":"Madrid",
    "wof:name":"Castrillo De Sebastian Estrella",
    "wof:placetype":"venue"
},
  "geometry": {"coordinates":[-3.6068739891,40.406036377],"type":"Point"}
}