{
  "type": "Feature",
  "properties": {
    "iso:country":"ES",
    "sg:address":"Calle de Brasil, S/n",
    "sg:city":"Navahermosa",
    "sg:orig_category":"Electromec\u00c1nica",
    "sg:phone":"+34 925 42 84 19",
    "sg:postcode":"45150",
    "sg:province":"Toledo",
    "wof:name":"Talleres Cerezo Aceituno S.l.",
    "wof:placetype":"venue"
},
  "geometry": {"coordinates":[-4.46641922,39.6350212097],"type":"Point"}
}