{
  "type": "Feature",
  "properties": {
    "addr:full":"Calle de Francisco Chivite, 26 Cintruenigo Navarra 31592",
    "addr:housenumber":"26",
    "addr:postcode":"31592",
    "addr:street":"Calle De Francisco Chivite",
    "iso:country":"ES",
    "sg:address":"Calle de Francisco Chivite, 26",
    "sg:city":"Cintruenigo",
    "sg:orig_category":"Cr\u00cda De Cerdos",
    "sg:phone":"+34 948 81 15 18",
    "sg:postcode":"31592",
    "sg:province":"Navarra",
    "wof:name":"Agricola Ganadera Fedaser S.c.",
    "wof:placetype":"venue"
},
  "geometry": {"coordinates":[-1.8038398027,42.0809745789],"type":"Point"}
}