{
  "type": "Feature",
  "properties": {
    "iso:country":"ES",
    "sg:address":"Carrer de Jaume Casanovas, 192",
    "sg:city":"Prat Llobregat",
    "sg:orig_category":"Molduras, Junquillos, Listones Y Molduras Perforadas",
    "sg:phone":"+34 933 70 77 53",
    "sg:postcode":"08820",
    "sg:province":"Barcelona",
    "wof:name":"Avila Fuentes S.l.",
    "wof:placetype":"venue"
},
  "geometry": {"coordinates":[2.0938498974,41.323638916],"type":"Point"}
}