{
  "type": "Feature",
  "properties": {
    "addr:full":"Calle de Radio Sevilla, S/n Sevilla Sevilla 41001",
    "addr:housenumber":"s / n",
    "addr:postcode":"41001",
    "addr:street":"Calle De Radio Sevilla",
    "iso:country":"ES",
    "sg:address":"Calle de Radio Sevilla, S/n",
    "sg:city":"Sevilla",
    "sg:orig_category":"Arquitectos",
    "sg:phone":"+34 954 21 02 34",
    "sg:postcode":"41001",
    "sg:province":"Sevilla",
    "wof:name":"Martinez Millan Diego",
    "wof:placetype":"venue"
},
  "geometry": {"coordinates":[-6.0032739639,37.3884735107],"type":"Point"}
}