{
  "type": "Feature",
  "properties": {
    "iso:country":"ES",
    "sg:address":"Rua San Roque, 29",
    "sg:city":"Xinzo De Limia",
    "sg:orig_category":"Abogados",
    "sg:phone":"+34 988 46 11 29",
    "sg:postcode":"32630",
    "sg:province":"Ourense",
    "wof:name":"Peaguda Penin Pedro",
    "wof:placetype":"venue"
},
  "geometry": {"coordinates":[-7.7260389328,42.0627403259],"type":"Point"}
}