{
  "type": "Feature",
  "properties": {
    "iso:country":"ES",
    "sg:address":"Av. C. Sotelo, 45",
    "sg:city":"Muros",
    "sg:orig_category":"Quincaller\u00cda (al Por Menor)",
    "sg:phone":"+34 981 82 74 07",
    "sg:postcode":"15250",
    "sg:province":"La Coru\u00f1a",
    "wof:name":"Cama\u00f1o Paris Eugenio",
    "wof:placetype":"venue"
},
  "geometry": {"coordinates":[-9.0587692261,42.7760391235],"type":"Point"}
}