{
  "type": "Feature",
  "properties": {
    "iso:country":"ES",
    "sg:address":"Rond Oest, De L', 50",
    "sg:city":"Porto Cristo",
    "sg:orig_category":"T\u00c9cnicos Veterinarios",
    "sg:phone":"+34 971 82 23 85",
    "sg:postcode":"07680",
    "sg:province":"Islas Baleares",
    "wof:name":"Crende Casanegra Francisco Javier",
    "wof:placetype":"venue"
},
  "geometry": {"coordinates":[3.3338859081,39.5468101501],"type":"Point"}
}