{
  "type": "Feature",
  "properties": {
    "iso:country":"ES",
    "sg:address":"Carrer de Can Rabella, 2",
    "sg:city":"Molins Rei",
    "sg:orig_category":"Empresas De Desmonte",
    "sg:phone":"+34 936 80 10 55",
    "sg:postcode":"08750",
    "sg:province":"Barcelona",
    "wof:name":"Movimientos De Tierras Flatter S.l.",
    "wof:placetype":"venue"
},
  "geometry": {"coordinates":[2.0130450726,41.4200935364],"type":"Point"}
}