{
  "type": "Feature",
  "properties": {
    "addr:full":"Calle de Maria Tubau, 26 Malaga M\u00e1laga 29014",
    "addr:housenumber":"26",
    "addr:postcode":"29014",
    "addr:street":"Calle De Maria Tubau;Ma\u0301Laga",
    "iso:country":"ES",
    "sg:address":"Calle de Maria Tubau, 26",
    "sg:city":"Malaga",
    "sg:orig_category":"Asociaciones, Organismos Culturales Y Socioeducativos",
    "sg:phone":"+34 952 26 20 99",
    "sg:postcode":"29014",
    "sg:province":"M\u00e1laga",
    "wof:name":"Pe\u00f1a El Rosal",
    "wof:placetype":"venue"
},
  "geometry": {"coordinates":[-4.4222111702,36.741268158],"type":"Point"}
}