{
  "type": "Feature",
  "properties": {
    "addr:full":"Calle de Angelillo De Triana, 3 Malaga M\u00e1laga 29003",
    "addr:housenumber":"3",
    "addr:postcode":"29003",
    "addr:street":"Calle De Angelillo De Triana;Ma\u0301Laga",
    "iso:country":"ES",
    "sg:address":"Calle de Angelillo De Triana, 3",
    "sg:city":"Malaga",
    "sg:orig_category":"Papeler\u00cdas, Librer\u00cdas",
    "sg:phone":"+34 952 35 89 04",
    "sg:postcode":"29003",
    "sg:province":"M\u00e1laga",
    "wof:name":"Lopez Villalta Antonio",
    "wof:placetype":"venue"
},
  "geometry": {"coordinates":[-4.4504170418,36.6993026733],"type":"Point"}
}