{
  "type": "Feature",
  "properties": {
    "iso:country":"ES",
    "sg:address":"Calle de Alberche, 13",
    "sg:city":"Madrid",
    "sg:orig_category":"Tapicer\u00cdas",
    "sg:phone":"+34 914 67 01 34",
    "sg:postcode":"28045",
    "sg:province":"Madrid",
    "wof:name":"Perea Andreu Manuel",
    "wof:placetype":"venue"
},
  "geometry": {"coordinates":[-3.680398941,40.3977737427],"type":"Point"}
}