{
  "type": "Feature",
  "properties": {
    "addr:full":"Calle de Francisco Picazo, 9 Sanlucar De Barrameda C\u00e1diz 11540",
    "addr:housenumber":"9",
    "addr:postcode":"11540",
    "addr:street":"Calle De Francisco Picazo;Ca\u0301Diz",
    "iso:country":"ES",
    "sg:address":"Calle de Francisco Picazo, 9",
    "sg:city":"Sanlucar De Barrameda",
    "sg:orig_category":"Fabricaci\u00d3n De Juguetes Autom\u00c1ticos",
    "sg:phone":"+34 956 36 44 92",
    "sg:postcode":"11540",
    "sg:province":"C\u00e1diz",
    "wof:name":"Gallego Benitez S.l.",
    "wof:placetype":"venue"
},
  "geometry": {"coordinates":[-6.3551974297,36.782081604],"type":"Point"}
}