{
  "type": "Feature",
  "properties": {
    "iso:country":"ES",
    "sg:address":"Calle de Manuel Calero Calerito, 21",
    "sg:city":"Villaviciosa Cordoba",
    "sg:orig_category":"Empresas De Carpinter\u00cda De Madera",
    "sg:phone":"+34 957 36 11 32",
    "sg:postcode":"14300",
    "sg:province":"C\u00f3rdoba",
    "wof:name":"Due\u00f1as Mu\u00f1oz Luis",
    "wof:placetype":"venue"
},
  "geometry": {"coordinates":[-5.0158162117,38.0737609863],"type":"Point"}
}