{
  "type": "Feature",
  "properties": {
    "addr:full":"Los Rosales, 3 Coria C\u00e1ceres 10800",
    "addr:housenumber":"3",
    "addr:postcode":"10800",
    "addr:street":"Los Rosales;Ca\u0301Ceres",
    "iso:country":"ES",
    "sg:address":"Los Rosales, 3",
    "sg:city":"Coria",
    "sg:orig_category":"Empresas De Carpinter\u00cda De Madera",
    "sg:phone":"+34 927 50 34 80",
    "sg:postcode":"10800",
    "sg:province":"C\u00e1ceres",
    "wof:name":"Miguel Angel Asensio Martin",
    "wof:placetype":"venue"
},
  "geometry": {"coordinates":[-6.5036435127,39.9937400818],"type":"Point"}
}