{
  "type": "Feature",
  "properties": {
    "addr:full":"Calle de Salamanca, 11 Arganda Madrid 28500",
    "addr:housenumber":"11",
    "addr:postcode":"28500",
    "addr:street":"Calle De Salamanca",
    "iso:country":"ES",
    "sg:address":"Calle de Salamanca, 11",
    "sg:city":"Arganda",
    "sg:orig_category":"Cerrajer\u00cda, Ferrallista",
    "sg:phone":"+34 918 70 29 86",
    "sg:postcode":"28500",
    "sg:province":"Madrid",
    "wof:name":"Cerrajeria Barbosa S.l",
    "wof:placetype":"venue"
},
  "geometry": {"coordinates":[-3.4658839703,40.3077507019],"type":"Point"}
}