{
  "type": "Feature",
  "properties": {
    "addr:full":"Calle de Polvoranca, 44 Alcorcon Madrid 28921",
    "addr:housenumber":"44",
    "addr:postcode":"28921",
    "addr:street":"Calle De Polvoranca",
    "iso:country":"ES",
    "sg:address":"Calle de Polvoranca, 44",
    "sg:city":"Alcorcon",
    "sg:orig_category":"Peluquer\u00cdas, Peluquer\u00cda Mixta",
    "sg:phone":"+34 916 44 41 36",
    "sg:postcode":"28921",
    "sg:province":"Madrid",
    "wof:name":"Alvarez Peluqueros C.b.",
    "wof:placetype":"venue"
},
  "geometry": {"coordinates":[-3.8243603706,40.3460426331],"type":"Point"}
}