{
  "type": "Feature",
  "properties": {
    "addr:full":"Calle de Juan Xxiii, 1 Santurtzi Vizcaya 48980",
    "addr:housenumber":"1",
    "addr:postcode":"48980",
    "addr:street":"Calle De Juan Xxiii",
    "iso:country":"ES",
    "sg:address":"Calle de Juan Xxiii, 1",
    "sg:city":"Santurtzi",
    "sg:orig_category":"Carnicer\u00cdas, Carnicer\u00cdas",
    "sg:phone":"+34 944 61 87 39",
    "sg:postcode":"48980",
    "sg:province":"Vizcaya",
    "wof:name":"Ruiz Sainz Manuel",
    "wof:placetype":"venue"
},
  "geometry": {"coordinates":[-3.033976078,43.3300628662],"type":"Point"}
}