{
  "type": "Feature",
  "properties": {
    "addr:full":"Rua Bedoya, 18 Ourense Ourense 32004",
    "addr:housenumber":"18",
    "addr:postcode":"32004",
    "addr:street":"Rua Bedoya",
    "iso:country":"ES",
    "sg:address":"Rua Bedoya, 18",
    "sg:city":"Ourense",
    "sg:orig_category":"Mercer\u00cda, Lencer\u00cda (al Por Menor)",
    "sg:phone":"+34 988 23 98 07",
    "sg:postcode":"32004",
    "sg:province":"Ourense",
    "wof:name":"Gonzalez Castro Mercedes",
    "wof:placetype":"venue"
},
  "geometry": {"coordinates":[-7.8617730141,42.3401222229],"type":"Point"}
}