{
  "type": "Feature",
  "properties": {
    "iso:country":"ES",
    "sg:address":"Calle de Antonio Maura, 8",
    "sg:city":"Utiel",
    "sg:orig_category":"Herradores, Herreros, Carreteros",
    "sg:phone":"+34 962 17 00 66",
    "sg:postcode":"46300",
    "sg:province":"Valencia",
    "wof:name":"Ferreteria Gabaldon S.l",
    "wof:placetype":"venue"
},
  "geometry": {"coordinates":[-1.2074602842,39.5669784546],"type":"Point"}
}