{
  "type": "Feature",
  "properties": {
    "iso:country":"ES",
    "sg:address":"Avda Espa\u00d1a, 17",
    "sg:city":"Caceres",
    "sg:orig_category":"Financiaci\u00d3n Y Cr\u00c9ditos",
    "sg:phone":"+34 927 24 66 50",
    "sg:postcode":"10002",
    "sg:province":"C\u00e1ceres",
    "wof:name":"Bt Espa\u00f1a Compa\u00f1ia De Servicios Globales De Telecomunicaciones S.a.u.",
    "wof:placetype":"venue"
},
  "geometry": {"coordinates":[-6.3774561882,39.4704055786],"type":"Point"}
}