{
  "type": "Feature",
  "properties": {
    "addr:full":"Calle de Diputacion, 13 Villafranca De Los Barros Badajoz 06220",
    "addr:housenumber":"13",
    "addr:postcode":"06220",
    "addr:street":"Calle De Diputacion",
    "iso:country":"ES",
    "sg:address":"Calle de Diputacion, 13",
    "sg:city":"Villafranca De Los Barros",
    "sg:orig_category":"Negocio De Materiales De Construcci\u00d3n",
    "sg:phone":"+34 924 52 41 93",
    "sg:postcode":"06220",
    "sg:province":"Badajoz",
    "wof:name":"Suministros Perceiana S.l.",
    "wof:placetype":"venue"
},
  "geometry": {"coordinates":[-6.3314628601,38.555103302],"type":"Point"}
}