{
  "type": "Feature",
  "properties": {
    "addr:full":"Plaz Herrasti, 3 Ciudad Rodrigo Salamanca 37500",
    "addr:housenumber":"3",
    "addr:postcode":"37500",
    "addr:street":"Plaz Herrasti",
    "iso:country":"ES",
    "sg:address":"Plaz Herrasti, 3",
    "sg:city":"Ciudad Rodrigo",
    "sg:orig_category":"Centros Empresariales",
    "sg:phone":"+34 923 46 30 37",
    "sg:postcode":"37500",
    "sg:province":"Salamanca",
    "wof:name":"Afecir",
    "wof:placetype":"venue"
},
  "geometry": {"coordinates":[-6.5358633995,40.5997467041],"type":"Point"}
}