{
  "type": "Feature",
  "properties": {
    "addr:full":"Calle de Padre Jose Sebastian Bandaran, S/n Sevilla Sevilla 41013",
    "addr:housenumber":"s / n",
    "addr:postcode":"41013",
    "addr:street":"Calle De Padre Jose Sebastian Bandaran",
    "iso:country":"ES",
    "sg:address":"Calle de Padre Jose Sebastian Bandaran, S/n",
    "sg:city":"Sevilla",
    "sg:orig_category":"Mercer\u00cda, Lencer\u00cda (al Por Menor)",
    "sg:phone":"+34 954 62 00 16",
    "sg:postcode":"41013",
    "sg:province":"Sevilla",
    "wof:name":"Chaves Cadaval Maria Jose",
    "wof:placetype":"venue"
},
  "geometry": {"coordinates":[-5.9723939896,37.3599433899],"type":"Point"}
}