{
  "type": "Feature",
  "properties": {
    "iso:country":"ES",
    "sg:address":"Calle de Lucha Canaria (la), 54",
    "sg:city":"Pto. Rosario",
    "sg:orig_category":"Agricultores, Agricultores",
    "sg:phone":"+34 928 53 18 67",
    "sg:postcode":"35600",
    "sg:province":"Las Palmas",
    "wof:name":"Proganca Fuerteventura",
    "wof:placetype":"venue"
},
  "geometry": {"coordinates":[-13.8732376099,28.5055294037],"type":"Point"}
}