{
  "type": "Feature",
  "properties": {
    "addr:full":"C/ Cervantes, De, S/n S. Antoni Portmany Islas Baleares 07820",
    "addr:postcode":"07820",
    "addr:street":"C / Cervantes De S / N S. Antoni Portmany",
    "iso:country":"ES",
    "sg:address":"C/ Cervantes, De, S/n",
    "sg:city":"S. Antoni Portmany",
    "sg:orig_category":"Quincaller\u00cda (al Por Menor)",
    "sg:phone":"+34 971 34 04 64",
    "sg:postcode":"07820",
    "sg:province":"Islas Baleares",
    "wof:name":"Ferreteria Ferrbo S.a.",
    "wof:placetype":"venue"
},
  "geometry": {"coordinates":[1.5188339949,39.1094055176],"type":"Point"}
}