{
  "type": "Feature",
  "properties": {
    "iso:country":"ES",
    "sg:address":"Carrer de Vidiella, 21",
    "sg:city":"Barcelona",
    "sg:orig_category":"Mec\u00c1nico Del Autom\u00d3vil",
    "sg:phone":"+34 934 36 33 32",
    "sg:postcode":"08026",
    "sg:province":"Barcelona",
    "wof:name":"Franch Palau Juan",
    "wof:placetype":"venue"
},
  "geometry": {"coordinates":[2.1855840683,41.4124031067],"type":"Point"}
}