{
  "type": "Feature",
  "properties": {
    "iso:country":"ES",
    "sg:address":"Rua Illas Gabeiras, 9",
    "sg:city":"Ferrol",
    "sg:orig_category":"Autob\u00das (explotaci\u00d3n Y Servicios De)",
    "sg:phone":"+34 981 31 90 98",
    "sg:postcode":"15403",
    "sg:province":"La Coru\u00f1a",
    "wof:name":"Fernandez Barcia Camilo",
    "wof:placetype":"venue"
},
  "geometry": {"coordinates":[-8.2239084244,43.4917984009],"type":"Point"}
}