{
  "type": "Feature",
  "properties": {
    "addr:full":"Rua Rosalia De Castro, 9 Burela Lugo 27880",
    "addr:housenumber":"9",
    "addr:postcode":"27880",
    "addr:street":"Rua Rosalia De Castro",
    "iso:country":"ES",
    "sg:address":"Rua Rosalia De Castro, 9",
    "sg:city":"Burela",
    "sg:orig_category":"Caf\u00c9s, Bares, Cervecer\u00cdas",
    "sg:phone":"+34 982 58 07 53",
    "sg:postcode":"27880",
    "sg:province":"Lugo",
    "wof:name":"Fernandez Otero Eliseo",
    "wof:placetype":"venue"
},
  "geometry": {"coordinates":[-7.359336853,43.6600189209],"type":"Point"}
}