{
  "type": "Feature",
  "properties": {
    "addr:full":"La Orden, S/n Huelva Huelva 21005",
    "addr:housenumber":"s / n",
    "addr:postcode":"21005",
    "addr:street":"Orden",
    "iso:country":"ES",
    "sg:address":"La Orden, S/n",
    "sg:city":"Huelva",
    "sg:orig_category":"Ense\u00d1anza Secundaria: Colegios Y Escuelas Privadas",
    "sg:phone":"+34 959 15 18 39",
    "sg:postcode":"21005",
    "sg:province":"Huelva",
    "wof:name":"Junta De Andalucia",
    "wof:placetype":"venue"
},
  "geometry": {"coordinates":[-6.9384288788,37.2801246643],"type":"Point"}
}