{
  "type": "Feature",
  "properties": {
    "addr:full":"Rua Lopez Mora, 41 Vigo Pontevedra 36211",
    "addr:housenumber":"41",
    "addr:postcode":"36211",
    "addr:street":"Rua Lopez Mora",
    "iso:country":"ES",
    "sg:address":"Rua Lopez Mora, 41",
    "sg:city":"Vigo",
    "sg:orig_category":"M\u00c9dicos: An\u00c1lisis Cl\u00cdnicos",
    "sg:phone":"+34 986 20 53 54",
    "sg:postcode":"36211",
    "sg:province":"Pontevedra",
    "wof:name":"Sevillano Casta\u00f1o Joaquina",
    "wof:placetype":"venue"
},
  "geometry": {"coordinates":[-8.7319364548,42.2248001099],"type":"Point"}
}