{
  "type": "Feature",
  "properties": {
    "addr:full":"Carr Juneda, Km. 0000,2 Puigverd Lleida Lleida 25153",
    "addr:postcode":"25153",
    "addr:street":"Carr Juneda Km. 0000,2 Puigverd",
    "iso:country":"ES",
    "sg:address":"Carr Juneda, Km. 0000,2",
    "sg:city":"Puigverd Lleida",
    "sg:orig_category":"Dietistas",
    "sg:phone":"+34 973 16 72 69",
    "sg:postcode":"25153",
    "sg:province":"Lleida",
    "sg:website":"www.santiveri.es",
    "wof:name":"Casa Santiveri S.l.",
    "wof:placetype":"venue"
},
  "geometry": {"coordinates":[0.7342749834,41.5446853638],"type":"Point"}
}