{
  "type": "Feature",
  "properties": {
    "addr:full":"Calle de Jaen, 1 Bilbao Vizcaya 48012",
    "addr:housenumber":"1",
    "addr:postcode":"48012",
    "addr:street":"Calle De Jaen",
    "iso:country":"ES",
    "sg:address":"Calle de Jaen, 1",
    "sg:city":"Bilbao",
    "sg:orig_category":"Motocicletas (agentes, Concesionarios)",
    "sg:phone":"+34 944 43 81 36",
    "sg:postcode":"48012",
    "sg:province":"Vizcaya",
    "wof:name":"Gonzalez Rojas Alfredo",
    "wof:placetype":"venue"
},
  "geometry": {"coordinates":[-2.9438350201,43.253578186],"type":"Point"}
}