{
  "type": "Feature",
  "properties": {
    "addr:full":"Avda Mediterraneo, 50 Madrid Madrid 28007",
    "addr:housenumber":"50",
    "addr:postcode":"madrid;28007",
    "addr:street":"Avda Mediterraneo",
    "iso:country":"ES",
    "sg:address":"Avda Mediterraneo, 50",
    "sg:city":"Madrid",
    "sg:orig_category":"Tiendas De Grano, Frutas Y Legumbres Secas (al Por Menor)",
    "sg:phone":"+34 914 34 81 27",
    "sg:postcode":"28007",
    "sg:province":"Madrid",
    "wof:name":"Ye  Pinguang",
    "wof:placetype":"venue"
},
  "geometry": {"coordinates":[-3.671795845,40.4067649841],"type":"Point"}
}