{
  "type": "Feature",
  "properties": {
    "addr:full":"Calle de Siena, 28 Madrid Madrid 28027",
    "addr:housenumber":"28",
    "addr:postcode":"madrid;28027",
    "addr:street":"Calle De Siena",
    "iso:country":"ES",
    "sg:address":"Calle de Siena, 28",
    "sg:city":"Madrid",
    "sg:orig_category":"Inmobiliaria (agencias)",
    "sg:phone":"+34 914 04 61 55",
    "sg:postcode":"28027",
    "sg:province":"Madrid",
    "wof:name":"Cagigas Cespedes Moises",
    "wof:placetype":"venue"
},
  "geometry": {"coordinates":[-3.6541910172,40.4328041077],"type":"Point"}
}