{
  "type": "Feature",
  "properties": {
    "addr:full":"Calle de Almortas, 34 Madrid Madrid 28023",
    "addr:housenumber":"34",
    "addr:postcode":"madrid;28023",
    "addr:street":"Calle De Almortas",
    "iso:country":"ES",
    "sg:address":"Calle de Almortas, 34",
    "sg:city":"Madrid",
    "sg:orig_category":"Mec\u00c1nico Del Autom\u00d3vil",
    "sg:phone":"+34 913 14 87 11",
    "sg:postcode":"28023",
    "sg:province":"Madrid",
    "wof:name":"Talleres Jiser S.l.",
    "wof:placetype":"venue"
},
  "geometry": {"coordinates":[-3.7041759491,40.4661941528],"type":"Point"}
}