{
  "type": "Feature",
  "properties": {
    "addr:full":"Avda Reyes Catolicos De Los, 29 Fraga Huesca 22520",
    "addr:housenumber":"29",
    "addr:postcode":"22520",
    "addr:street":"Avda Reyes Catolicos De Los",
    "iso:country":"ES",
    "sg:address":"Avda Reyes Catolicos De Los, 29",
    "sg:city":"Fraga",
    "sg:orig_category":"Partidos Pol\u00cdticos",
    "sg:phone":"+34 974 47 33 77",
    "sg:postcode":"22520",
    "sg:province":"Huesca",
    "wof:name":"Partido Popular",
    "wof:placetype":"venue"
},
  "geometry": {"coordinates":[0.3473240137,41.5217819214],"type":"Point"}
}