{
  "type": "Feature",
  "properties": {
    "addr:full":"Av Artur Carbonell, 16 Sitges Barcelona 08870",
    "addr:housenumber":"16",
    "addr:postcode":"08870",
    "addr:street":"Av Artur Carbonell",
    "iso:country":"ES",
    "sg:address":"Av Artur Carbonell, 16",
    "sg:city":"Sitges",
    "sg:orig_category":"Compraventa De Antig\u00dcedades",
    "sg:phone":"+34 938 94 53 51",
    "sg:postcode":"08870",
    "sg:province":"Barcelona",
    "wof:name":"Arjomaldi Aghdasi Nasim",
    "wof:placetype":"venue"
},
  "geometry": {"coordinates":[1.8082369566,41.2385864258],"type":"Point"}
}