{
  "type": "Feature",
  "properties": {
    "addr:full":"Avda Santa Marina, 42 Badajoz Badajoz 06005",
    "addr:housenumber":"42",
    "addr:postcode":"06005",
    "addr:street":"Avda Santa Marina",
    "iso:country":"ES",
    "sg:address":"Avda Santa Marina, 42",
    "sg:city":"Badajoz",
    "sg:orig_category":"Peluquer\u00cdas, Peluquer\u00cda Mixta",
    "sg:phone":"+34 924 23 94 51",
    "sg:postcode":"06005",
    "sg:province":"Badajoz",
    "wof:name":"Rosa Acebedo Bego\u00f1a",
    "wof:placetype":"venue"
},
  "geometry": {"coordinates":[-6.9803781509,38.8764915466],"type":"Point"}
}