{
  "type": "Feature",
  "properties": {
    "addr:full":"Calle de Diputados, 25 Zaragoza Zaragoza 50004",
    "addr:housenumber":"25",
    "addr:postcode":"50004",
    "addr:street":"Calle De Diputados",
    "iso:country":"ES",
    "sg:address":"Calle de Diputados, 25",
    "sg:city":"Zaragoza",
    "sg:orig_category":"Molduras, Junquillos, Listones Y Molduras Perforadas",
    "sg:phone":"+34 976 43 19 00",
    "sg:postcode":"50004",
    "sg:province":"Zaragoza",
    "wof:name":"Escucha Rapida S.l.",
    "wof:placetype":"venue"
},
  "geometry": {"coordinates":[-0.8953409195,41.6563110352],"type":"Point"}
}