{
  "type": "Feature",
  "properties": {
    "iso:country":"ES",
    "sg:address":"Calle de Zumalakarregi Kalea, 6",
    "sg:city":"Durango",
    "sg:orig_category":"Asesor\u00cda Fiscal Y Jur\u00cddica",
    "sg:phone":"+34 946 03 01 27",
    "sg:postcode":"48200",
    "sg:province":"Vizcaya",
    "wof:name":"Jone Agurtzane Lekue Y Marta Pumarejo Cb",
    "wof:placetype":"venue"
},
  "geometry": {"coordinates":[-2.6325469017,43.169090271],"type":"Point"}
}