{
  "type": "Feature",
  "properties": {
    "iso:country":"ES",
    "sg:address":"Calle de Emilio Jimeno, 9",
    "sg:city":"Calatayud",
    "sg:orig_category":"Estancos",
    "sg:phone":"+34 976 88 26 36",
    "sg:postcode":"50300",
    "sg:province":"Zaragoza",
    "wof:name":"Oroz Mateo Maria Josefa",
    "wof:placetype":"venue"
},
  "geometry": {"coordinates":[-1.6414749622,41.3493728638],"type":"Point"}
}