{
  "type": "Feature",
  "properties": {
    "addr:full":"Avda Salinero (el), 8 Costa Teguise Las Palmas 35509",
    "addr:housenumber":"8",
    "addr:postcode":"35509",
    "addr:street":"Avda Salinero El",
    "iso:country":"ES",
    "sg:address":"Avda Salinero (el), 8",
    "sg:city":"Costa Teguise",
    "sg:orig_category":"Bazares, Art\u00cdculos De Limpieza Y De Cocina (al Por Menor)",
    "sg:phone":"+34 928 59 11 26",
    "sg:postcode":"35509",
    "sg:province":"Las Palmas",
    "wof:name":"Isla Negra S.l.",
    "wof:placetype":"venue"
},
  "geometry": {"coordinates":[-13.5071592331,28.986869812],"type":"Point"}
}