{
  "type": "Feature",
  "properties": {
    "addr:full":"Calle de Asuncion, S/n Moron Frontera Sevilla 41530",
    "addr:housenumber":"s",
    "addr:postcode":"41530",
    "addr:street":"Calle De Asuncion;/ N Moron",
    "iso:country":"ES",
    "sg:address":"Calle de Asuncion, S/n",
    "sg:city":"Moron Frontera",
    "sg:orig_category":"Supermercados Y Hipermercados",
    "sg:phone":"+34 955 85 47 42",
    "sg:postcode":"41530",
    "sg:province":"Sevilla",
    "wof:name":"Eroski Sociedad Cooperativa",
    "wof:placetype":"venue"
},
  "geometry": {"coordinates":[-5.4665727615,37.120513916],"type":"Point"}
}