{
  "type": "Feature",
  "properties": {
    "iso:country":"ES",
    "sg:address":"Carrer de Anselm Clave, 27",
    "sg:city":"Barbera Valles",
    "sg:orig_category":"Papeler\u00cdas, Librer\u00cdas",
    "sg:phone":"+34 937 29 08 77",
    "sg:postcode":"08210",
    "sg:province":"Barcelona",
    "wof:name":"Perez Calvo Josefa",
    "wof:placetype":"venue"
},
  "geometry": {"coordinates":[2.129983902,41.5184288025],"type":"Point"}
}