{
  "type": "Feature",
  "properties": {
    "addr:full":"Pg Sant Joan, 139 Barcelona Barcelona 08037",
    "addr:housenumber":"139",
    "addr:postcode":"08037",
    "addr:street":"Pg Sant Joan",
    "iso:country":"ES",
    "sg:address":"Pg Sant Joan, 139",
    "sg:city":"Barcelona",
    "sg:orig_category":"M\u00c9dicos: Cardiolog\u00cda Y Afecciones Cardiovasculares",
    "sg:phone":"+34 934 57 91 95",
    "sg:postcode":"08037",
    "sg:province":"Barcelona",
    "wof:name":"Periz Sague Alberto",
    "wof:placetype":"venue"
},
  "geometry": {"coordinates":[2.1667220592,41.4011497498],"type":"Point"}
}