{
  "type": "Feature",
  "properties": {
    "iso:country":"ES",
    "sg:address":"Calle de Princesa, 2",
    "sg:city":"Carmen",
    "sg:orig_category":"Institutos De Belleza",
    "sg:phone":"+34 968 21 38 62",
    "sg:postcode":"30002",
    "sg:province":"Murcia",
    "wof:name":"Gomez Salgero Margarita",
    "wof:placetype":"venue"
},
  "geometry": {"coordinates":[-1.127810955,37.9800643921],"type":"Point"}
}