{
  "type": "Feature",
  "properties": {
    "addr:full":"Avda Benito Perez Galdos, 49 Alacant Alicante 03005",
    "addr:housenumber":"49",
    "addr:postcode":"03005",
    "addr:street":"Avda Benito Perez Galdos",
    "iso:country":"ES",
    "sg:address":"Avda Benito Perez Galdos, 49",
    "sg:city":"Alacant",
    "sg:orig_category":"Transporte En General",
    "sg:phone":"+34 965 92 80 09",
    "sg:postcode":"03005",
    "sg:province":"Alicante",
    "wof:name":"Cerda Alemany Alfonso Manuel",
    "wof:placetype":"venue"
},
  "geometry": {"coordinates":[-0.4929090142,38.3474388123],"type":"Point"}
}