{
  "type": "Feature",
  "properties": {
    "iso:country":"ES",
    "sg:address":"Calle de Badajoz, 37",
    "sg:city":"Barriada Cuatro Santos",
    "sg:orig_category":"Mec\u00c1nico Del Autom\u00d3vil",
    "sg:phone":"+34 968 51 79 15",
    "sg:postcode":"30310",
    "sg:province":"Murcia",
    "wof:name":"Lorca Esteve Jose",
    "wof:placetype":"venue"
},
  "geometry": {"coordinates":[-1.1298867464,37.9834747314],"type":"Point"}
}