{
  "type": "Feature",
  "properties": {
    "addr:full":"Calle de Bosquecillo, 19 Velada Toledo 45612",
    "addr:housenumber":"19",
    "addr:postcode":"45612",
    "addr:street":"Calle De Bosquecillo",
    "iso:country":"ES",
    "sg:address":"Calle de Bosquecillo, 19",
    "sg:city":"Velada",
    "sg:orig_category":"Confecci\u00d3n (fabricaci\u00d3n, Al Por Mayor)",
    "sg:phone":"+34 925 89 24 19",
    "sg:postcode":"45612",
    "sg:province":"Toledo",
    "wof:name":"Cabo Gomez Maria Lourdes",
    "wof:placetype":"venue"
},
  "geometry": {"coordinates":[-4.9737315178,39.9784202576],"type":"Point"}
}