{
  "type": "Feature",
  "properties": {
    "iso:country":"ES",
    "sg:address":"C/ Empedrat, 5",
    "sg:city":"Elche",
    "sg:orig_category":"Electricidad: Instaladores",
    "sg:phone":"+34 965 45 10 29",
    "sg:postcode":"03203",
    "sg:province":"Alicante",
    "wof:name":"Nuevos Riegos El Progreso S. A.",
    "wof:placetype":"venue"
},
  "geometry": {"coordinates":[-0.6955929995,38.2660598755],"type":"Point"}
}