{
  "type": "Feature",
  "properties": {
    "addr:full":"Calle de Garcia De Toledo, S/n Playa De Arinaga Las Palmas 35118",
    "addr:housenumber":"/ n",
    "addr:postcode":"35118",
    "addr:street":"Calle De Garcia De Toledo S",
    "iso:country":"ES",
    "sg:address":"Calle de Garcia De Toledo, S/n",
    "sg:city":"Playa De Arinaga",
    "sg:orig_category":"Contenedores (mercanc\u00cdas)",
    "sg:phone":"+34 928 73 80 92",
    "sg:postcode":"35118",
    "sg:province":"Las Palmas",
    "wof:name":"Santana Muoz Jose",
    "wof:placetype":"venue"
},
  "geometry": {"coordinates":[-15.3899793625,27.856420517],"type":"Point"}
}