{
  "type": "Feature",
  "properties": {
    "addr:full":"Calle de Acera Del Darro, 2 Granada Granada 18005",
    "addr:housenumber":"2",
    "addr:postcode":"18005",
    "addr:street":"Calle De Acera Del Darro",
    "iso:country":"ES",
    "sg:address":"Calle de Acera Del Darro, 2",
    "sg:city":"Granada",
    "sg:orig_category":"Filatelia",
    "sg:phone":"+34 958 26 25 66",
    "sg:postcode":"18005",
    "sg:province":"Granada",
    "wof:name":"Vega Hermanos C.b.",
    "wof:placetype":"venue"
},
  "geometry": {"coordinates":[-3.5998361111,37.173286438],"type":"Point"}
}