{
  "type": "Feature",
  "properties": {
    "iso:country":"ES",
    "sg:address":"Avda Juan Carlos I, 62",
    "sg:city":"Torre-pacheco",
    "sg:orig_category":"Limpieza Industrial",
    "sg:phone":"+34 968 57 97 56",
    "sg:postcode":"30700",
    "sg:province":"Murcia",
    "wof:name":"Saex Tintorerias Y Lavanderias S.l",
    "wof:placetype":"venue"
},
  "geometry": {"coordinates":[-1.0747129917,37.8179244995],"type":"Point"}
}