{
  "type": "Feature",
  "properties": {
    "iso:country":"ES",
    "sg:address":"Barr Rons, 59",
    "sg:city":"Cantodorxo",
    "sg:orig_category":"Asociaciones Y Clubs Deportivos",
    "sg:phone":"+34 986 73 20 85",
    "sg:postcode":"36980",
    "sg:province":"Pontevedra",
    "wof:name":"Club De Remo Mecos",
    "wof:placetype":"venue"
},
  "geometry": {"coordinates":[-8.86282444,42.4956588745],"type":"Point"}
}