{
  "type": "Feature",
  "properties": {
    "addr:full":"Calle de Cuarteles, 19 Malaga M\u00e1laga 29002",
    "addr:housenumber":"19",
    "addr:postcode":"29002",
    "addr:street":"Calle De Cuarteles;Ma\u0301Laga",
    "iso:country":"ES",
    "sg:address":"Calle de Cuarteles, 19",
    "sg:city":"Malaga",
    "sg:orig_category":"Molduras, Junquillos, Listones Y Molduras Perforadas",
    "sg:phone":"+34 952 31 29 86",
    "sg:postcode":"29002",
    "sg:province":"M\u00e1laga",
    "wof:name":"Sanchez Civera Jose Luis",
    "wof:placetype":"venue"
},
  "geometry": {"coordinates":[-4.4276366234,36.7142295837],"type":"Point"}
}