{
  "type": "Feature",
  "properties": {
    "addr:full":"Calle de Cristobal Bordiu, 35 Madrid Madrid 28003",
    "addr:housenumber":"35",
    "addr:postcode":"madrid;28003",
    "addr:street":"Calle De Cristobal Bordiu",
    "iso:country":"ES",
    "sg:address":"Calle de Cristobal Bordiu, 35",
    "sg:city":"Madrid",
    "sg:orig_category":"Metalurgia",
    "sg:phone":"+34 915 98 60 90",
    "sg:postcode":"28003",
    "sg:province":"Madrid",
    "wof:name":"A Bianchini Ingeniero S.a.",
    "wof:placetype":"venue"
},
  "geometry": {"coordinates":[-3.698318,40.443024],"type":"Point"}
}