{
  "type": "Feature",
  "properties": {
    "iso:country":"ES",
    "sg:address":"Calle de Esperanza (la), 1",
    "sg:city":"Armilla",
    "sg:orig_category":"Ingeniero",
    "sg:phone":"+34 958 57 05 38",
    "sg:postcode":"18100",
    "sg:province":"Granada",
    "wof:name":"Gavilan Castro Joaquin",
    "wof:placetype":"venue"
},
  "geometry": {"coordinates":[-3.622838974,37.1451683044],"type":"Point"}
}