{
  "type": "Feature",
  "properties": {
    "iso:country":"ES",
    "sg:address":"Avgd Segre, 14",
    "sg:city":"Lleida",
    "sg:orig_category":"Carnicer\u00cdas, Carnicer\u00cdas",
    "sg:phone":"+34 973 24 60 83",
    "sg:postcode":"25007",
    "sg:province":"Lleida",
    "wof:name":"Al Ouadni  Ali",
    "wof:placetype":"venue"
},
  "geometry": {"coordinates":[0.6346874237,41.6175804138],"type":"Point"}
}