{
  "type": "Feature",
  "properties": {
    "addr:full":"Calle de Andra Mari Kalea, 24 Durango Vizcaya 48200",
    "addr:housenumber":"24",
    "addr:postcode":"48200",
    "addr:street":"Calle De Andra Mari Kalea",
    "iso:country":"ES",
    "sg:address":"Calle de Andra Mari Kalea, 24",
    "sg:city":"Durango",
    "sg:orig_category":"Quincaller\u00cda (al Por Menor)",
    "sg:phone":"+34 946 81 04 76",
    "sg:postcode":"48200",
    "sg:province":"Vizcaya",
    "wof:name":"Suministros Elcar S. A.",
    "wof:placetype":"venue"
},
  "geometry": {"coordinates":[-2.631385088,43.1677398682],"type":"Point"}
}