{
  "type": "Feature",
  "properties": {
    "iso:country":"ES",
    "sg:address":"C/ Gon\u00c7al Barrachina, 4",
    "sg:city":"Alcoi",
    "sg:orig_category":"Agentes Generales De Seguros",
    "sg:phone":"+34 965 54 15 08",
    "sg:postcode":"03801",
    "sg:province":"Alicante",
    "wof:name":"Gisbert Sansoli Jose",
    "wof:placetype":"venue"
},
  "geometry": {"coordinates":[-0.4725221097,38.6975440979],"type":"Point"}
}