{
  "type": "Feature",
  "properties": {
    "addr:full":"Calle de Bailen, 23 Alacant Alicante 03001",
    "addr:housenumber":"23",
    "addr:postcode":"03001",
    "addr:street":"Calle De Bailen",
    "iso:country":"ES",
    "sg:address":"Calle de Bailen, 23",
    "sg:city":"Alacant",
    "sg:orig_category":"Art\u00cdculos Funerarios (al Por Menor)",
    "sg:phone":"+34 965 20 54 44",
    "sg:postcode":"03001",
    "sg:province":"Alicante",
    "wof:name":"Funeraria La Santa Faz S. L.",
    "wof:placetype":"venue"
},
  "geometry": {"coordinates":[-0.4846169949,38.3453788757],"type":"Point"}
}