{
  "type": "Feature",
  "properties": {
    "iso:country":"ES",
    "sg:address":"Poli Mugitegi-b, 29",
    "sg:city":"Urretxu",
    "sg:orig_category":"Negocio De Materiales De Construcci\u00d3n",
    "sg:phone":"+34 943 72 39 08",
    "sg:postcode":"20700",
    "sg:province":"Guip\u00f9zcoa",
    "wof:name":"Izagirre Ceramicas Y Ba\u00f1os S.l.",
    "wof:placetype":"venue"
},
  "geometry": {"coordinates":[-2.3134770393,43.086730957],"type":"Point"}
}