{
  "type": "Feature",
  "properties": {
    "addr:full":"Ctra Orihuela (de), 7 Abanilla Murcia 30640",
    "addr:housenumber":"7",
    "addr:postcode":"30640",
    "addr:street":"Ctra Orihuela De",
    "iso:country":"ES",
    "sg:address":"Ctra Orihuela (de), 7",
    "sg:city":"Abanilla",
    "sg:orig_category":"Alimentaci\u00d3n General (al Por Menor)",
    "sg:phone":"+34 968 68 08 10",
    "sg:postcode":"30640",
    "sg:province":"Murcia",
    "wof:name":"Lloret Y Vallejo S.l.",
    "wof:placetype":"venue"
},
  "geometry": {"coordinates":[-1.0409530401,38.2055549622],"type":"Point"}
}