{
  "type": "Feature",
  "properties": {
    "iso:country":"ES",
    "sg:address":"Casa Canet, S/n",
    "sg:city":"Clariana Cardener",
    "sg:orig_category":"Agricultores, Agricultores",
    "sg:phone":"+34 973 29 92 23",
    "sg:postcode":"25290",
    "sg:province":"Lleida",
    "wof:name":"Sociedad Agraria De Transformacion La Concepcion",
    "wof:placetype":"venue"
},
  "geometry": {"coordinates":[1.5639150143,41.9418334961],"type":"Point"}
}