{
  "type": "Feature",
  "properties": {
    "iso:country":"ES",
    "sg:address":"Calle de Ave Maria, 3",
    "sg:city":"Ponferrada",
    "sg:orig_category":"Confecci\u00d3n De Trajes Para Se\u00d1oras",
    "sg:phone":"+34 987 42 74 43",
    "sg:postcode":"24400",
    "sg:province":"Le\u00f3n",
    "wof:name":"Lago Mendez Maria Teresa",
    "wof:placetype":"venue"
},
  "geometry": {"coordinates":[-6.5998239517,42.5482406616],"type":"Point"}
}