{
  "type": "Feature",
  "properties": {
    "iso:country":"ES",
    "sg:address":"Luga Jubias De Abajo, 24",
    "sg:city":"Jubias",
    "sg:orig_category":"Papeler\u00cdas: Art\u00cdculos (al Por Mayor)",
    "sg:phone":"+34 981 17 11 47",
    "sg:postcode":"15006",
    "sg:province":"La Coru\u00f1a",
    "wof:name":"Reprografia Galicia Y Suministros S.l.",
    "wof:placetype":"venue"
},
  "geometry": {"coordinates":[-8.3856277466,43.3446960449],"type":"Point"}
}