{
  "type": "Feature",
  "properties": {
    "addr:full":"G.v. Lopez De Haro D. Diego, 70 Bilbao Vizcaya 48011",
    "addr:housenumber":"70",
    "addr:postcode":"48011",
    "addr:street":"Lopez De Haro D. Diego",
    "iso:country":"ES",
    "sg:address":"G.v. Lopez De Haro D. Diego, 70",
    "sg:city":"Bilbao",
    "sg:orig_category":"Doctores En Medicina",
    "sg:phone":"+34 944 39 35 68",
    "sg:postcode":"48011",
    "sg:province":"Vizcaya",
    "wof:name":"Perez Llerandi Antonio",
    "wof:placetype":"venue"
},
  "geometry": {"coordinates":[-2.9420890808,43.2647209167],"type":"Point"}
}