{
  "type": "Feature",
  "properties": {
    "iso:country":"ES",
    "sg:address":"Carrer de Vall, 63",
    "sg:city":"Terrassa",
    "sg:orig_category":"Notarios",
    "sg:phone":"+34 937 88 87 54",
    "sg:postcode":"08221",
    "sg:province":"Barcelona",
    "wof:name":"Alvarez-cienfuegos Suarez Juan Manuel",
    "wof:placetype":"venue"
},
  "geometry": {"coordinates":[2.0093529224,41.5609130859],"type":"Point"}
}