{
  "type": "Feature",
  "properties": {
    "iso:country":"ES",
    "sg:address":"Pla\u00c7 Emporda, S/n",
    "sg:city":"Fortia",
    "sg:orig_category":"Insecticidas, Fumigaci\u00d3n",
    "sg:phone":"+34 972 53 40 23",
    "sg:postcode":"17469",
    "sg:province":"Girona",
    "wof:name":"Emporda Fitos S. L.",
    "wof:placetype":"venue"
},
  "geometry": {"coordinates":[3.0411279202,42.2441291809],"type":"Point"}
}