{
  "type": "Feature",
  "properties": {
    "iso:country":"ES",
    "sg:address":"Calle de Quero, 73",
    "sg:city":"Madrid",
    "sg:orig_category":"Bisuter\u00cda, Joyer\u00cda, Relojer\u00cda (al Por Menor)",
    "sg:phone":"+34 917 19 04 26",
    "sg:postcode":"28024",
    "sg:province":"Madrid",
    "wof:name":"Alvarez Busto Celina",
    "wof:placetype":"venue"
},
  "geometry": {"coordinates":[-3.7611522675,40.3900337219],"type":"Point"}
}