{
  "type": "Feature",
  "properties": {
    "iso:country":"ES",
    "sg:address":"Calle de Virgen De La Antigua, 13",
    "sg:city":"Sevilla",
    "sg:orig_category":"Abogados",
    "sg:phone":"+34 954 45 13 05",
    "sg:postcode":"41011",
    "sg:province":"Sevilla",
    "wof:name":"Osuna Fernandez Santiago",
    "wof:placetype":"venue"
},
  "geometry": {"coordinates":[-6.000975132,37.3728523254],"type":"Point"}
}