{
  "type": "Feature",
  "properties": {
    "addr:full":"Calle de General Pando, 3 Ciudad Rodrigo Salamanca 37500",
    "addr:housenumber":"3",
    "addr:postcode":"37500",
    "addr:street":"Calle De General Pando",
    "iso:country":"ES",
    "sg:address":"Calle de General Pando, 3",
    "sg:city":"Ciudad Rodrigo",
    "sg:orig_category":"Psic\u00d3logos",
    "sg:phone":"+34 923 46 02 31",
    "sg:postcode":"37500",
    "sg:province":"Salamanca",
    "wof:name":"Sanchez Arroyo Pilar",
    "wof:placetype":"venue"
},
  "geometry": {"coordinates":[-6.5352921486,40.5972557068],"type":"Point"}
}