{
  "type": "Feature",
  "properties": {
    "iso:country":"ES",
    "sg:address":"Calle de San Juan De La Cruz, 2",
    "sg:city":"Carolina",
    "sg:orig_category":"Loter\u00cda Y T\u00d3mbola",
    "sg:phone":"+34 953 66 01 09",
    "sg:postcode":"23200",
    "sg:province":"Ja\u00e9n",
    "wof:name":"Jimenez Barranco Carolina",
    "wof:placetype":"venue"
},
  "geometry": {"coordinates":[-3.6149001122,38.2748260498],"type":"Point"}
}