{
  "type": "Feature",
  "properties": {
    "iso:country":"ES",
    "sg:address":"Avda Doctor Federico Rubio Y Gali, 102",
    "sg:city":"Madrid",
    "sg:orig_category":"Asesor\u00cda Sobre Comunicaci\u00d3n De Empresas",
    "sg:phone":"+34 913 11 23 45",
    "sg:postcode":"28040",
    "sg:province":"Madrid",
    "wof:name":"Martinez Serrano Maria Carmen",
    "wof:placetype":"venue"
},
  "geometry": {"coordinates":[-3.713848114,40.455821991],"type":"Point"}
}