{
  "type": "Feature",
  "properties": {
    "iso:country":"ES",
    "sg:address":"Calle de Santander, 9",
    "sg:city":"Sabatera",
    "sg:orig_category":"Marketing Directo",
    "sg:phone":"+34 966 49 20 22",
    "sg:postcode":"03725",
    "sg:province":"Alicante",
    "wof:name":"Swirski Staniskawa Barbara",
    "wof:placetype":"venue"
},
  "geometry": {"coordinates":[0.1012500003,38.7296409607],"type":"Point"}
}