{
  "type": "Feature",
  "properties": {
    "iso:country":"ES",
    "sg:address":"Rond General Mitre, 163",
    "sg:city":"Barcelona",
    "sg:orig_category":"M\u00c9dicos: Alergolog\u00cda",
    "sg:phone":"+34 934 18 28 81",
    "sg:postcode":"08022",
    "sg:province":"Barcelona",
    "wof:name":"Buendia Gracia Enrique",
    "wof:placetype":"venue"
},
  "geometry": {"coordinates":[2.1392660141,41.4038124084],"type":"Point"}
}