{
  "type": "Feature",
  "properties": {
    "addr:full":"Ctra Madrid, Km. 0383,0 Molina Segura Murcia 30500",
    "addr:postcode":"30500",
    "addr:street":"Ctra Madrid Km. 0383,0 Molina",
    "iso:country":"ES",
    "sg:address":"Ctra Madrid, Km. 0383,0",
    "sg:city":"Molina Segura",
    "sg:orig_category":"Ropa Y Art\u00cdculos Pre",
    "sg:phone":"+34 968 61 25 12",
    "sg:postcode":"30500",
    "sg:province":"Murcia",
    "sg:website":"www.artemur.es",
    "wof:name":"Artemur S. A.",
    "wof:placetype":"venue"
},
  "geometry": {"coordinates":[-1.2257548571,38.0739707947],"type":"Point"}
}