{
  "type": "Feature",
  "properties": {
    "addr:full":"Pg Maritim De Los Delfines, 4 Delfines Islas Baleares 07769",
    "addr:housenumber":"4",
    "addr:postcode":"07769",
    "addr:street":"Pg Maritim De Los;Islas",
    "iso:country":"ES",
    "sg:address":"Pg Maritim De Los Delfines, 4",
    "sg:city":"Delfines",
    "sg:orig_category":"Restaurantes",
    "sg:phone":"+34 971 38 87 48",
    "sg:postcode":"07769",
    "sg:province":"Islas Baleares",
    "wof:name":"Paradasol S.l.",
    "wof:placetype":"venue"
},
  "geometry": {"coordinates":[3.8415720463,39.9769630432],"type":"Point"}
}