{
  "type": "Feature",
  "properties": {
    "iso:country":"ES",
    "sg:address":"Calle de Divino Maestro, 13",
    "sg:city":"Logro\u00f1o",
    "sg:orig_category":"Internados & Ense\u00d1anza Privada",
    "sg:phone":"+34 941 22 25 28",
    "sg:postcode":"26002",
    "sg:province":"La Rioja",
    "wof:name":"Misioneras Del Divino Maestro",
    "wof:placetype":"venue"
},
  "geometry": {"coordinates":[-2.4530172348,42.4568367004],"type":"Point"}
}