{
  "type": "Feature",
  "properties": {
    "iso:country":"ES",
    "sg:address":"Calle de Correria, 55",
    "sg:city":"Balmaseda",
    "sg:orig_category":"Perfumer\u00cda (al Por Menor)",
    "sg:phone":"+34 946 80 18 87",
    "sg:postcode":"48800",
    "sg:province":"Vizcaya",
    "wof:name":"Martin Alonso Maria Belen",
    "wof:placetype":"venue"
},
  "geometry": {"coordinates":[-3.1953129768,43.1942634583],"type":"Point"}
}