{
  "type": "Feature",
  "properties": {
    "addr:full":"Calle de Castelar, 18 Sevilla Sevilla 41001",
    "addr:housenumber":"18",
    "addr:postcode":"41001",
    "addr:street":"Calle De Castelar",
    "iso:country":"ES",
    "sg:address":"Calle de Castelar, 18",
    "sg:city":"Sevilla",
    "sg:orig_category":"Arquitectos",
    "sg:phone":"+34 954 50 20 79",
    "sg:postcode":"41001",
    "sg:province":"Sevilla",
    "wof:name":"Manchon Tejedor Francisco",
    "wof:placetype":"venue"
},
  "geometry": {"coordinates":[-5.997107029,37.3871002197],"type":"Point"}
}