{
  "type": "Feature",
  "properties": {
    "addr:full":"Calle de Toledo, 28 Getafe Madrid 28901",
    "addr:housenumber":"28",
    "addr:postcode":"28901",
    "addr:street":"Calle De Toledo",
    "iso:country":"ES",
    "sg:address":"Calle de Toledo, 28",
    "sg:city":"Getafe",
    "sg:orig_category":"Dietistas",
    "sg:phone":"+34 916 83 39 68",
    "sg:postcode":"28901",
    "sg:province":"Madrid",
    "wof:name":"Centro Optico Futurvision S.l.",
    "wof:placetype":"venue"
},
  "geometry": {"coordinates":[-3.7330338955,40.3032798767],"type":"Point"}
}