{
  "type": "Feature",
  "properties": {
    "addr:full":"Caragus, S/n Pedreguer Alicante 03750",
    "addr:postcode":"03750",
    "addr:street":"Caragus S / N",
    "iso:country":"ES",
    "sg:address":"Caragus, S/n",
    "sg:city":"Pedreguer",
    "sg:orig_category":"Aguas (distribuci\u00d3n, Servicios)",
    "sg:phone":"+34 966 45 70 00",
    "sg:postcode":"03750",
    "sg:province":"Alicante",
    "wof:name":"Oms-sacede S.a.",
    "wof:placetype":"venue"
},
  "geometry": {"coordinates":[0.0545369983,38.7801246643],"type":"Point"}
}