{
  "type": "Feature",
  "properties": {
    "addr:full":"Carrer de Adria, 6 Tarragona Tarragona 43004",
    "addr:housenumber":"6",
    "addr:postcode":"43004",
    "addr:street":"Carrer De Adria",
    "iso:country":"ES",
    "sg:address":"Carrer de Adria, 6",
    "sg:city":"Tarragona",
    "sg:orig_category":"Asesor\u00cdas Y Estudios Financieros",
    "sg:phone":"+34 977 23 98 02",
    "sg:postcode":"43004",
    "sg:province":"Tarragona",
    "wof:name":"Ballester Baiges Luis",
    "wof:placetype":"venue"
},
  "geometry": {"coordinates":[1.2534569502,41.1136054993],"type":"Point"}
}