{
  "type": "Feature",
  "properties": {
    "iso:country":"ES",
    "sg:address":"Carrer de Xalo (de), 16",
    "sg:city":"Gata Gorgos",
    "sg:orig_category":"Institutos De Belleza",
    "sg:phone":"+34 965 75 62 55",
    "sg:postcode":"03740",
    "sg:province":"Alicante",
    "wof:name":"Pedros Signes Julian",
    "wof:placetype":"venue"
},
  "geometry": {"coordinates":[0.0830949992,38.7749633789],"type":"Point"}
}