{
  "type": "Feature",
  "properties": {
    "addr:full":"Calle de Menor, S/n Colmenar Viejo Madrid 28770",
    "addr:housenumber":"s / n",
    "addr:postcode":"28770",
    "addr:street":"Calle De Menor",
    "iso:country":"ES",
    "sg:address":"Calle de Menor, S/n",
    "sg:city":"Colmenar Viejo",
    "sg:orig_category":"Electricidad: Equipos Industriales, Componentes (fabricaci\u00d3n)",
    "sg:phone":"+34 918 46 51 51",
    "sg:postcode":"28770",
    "sg:province":"Madrid",
    "wof:name":"Hyundai E.s., S.l.,",
    "wof:placetype":"venue"
},
  "geometry": {"coordinates":[-3.7544939518,40.6535758972],"type":"Point"}
}