{
  "type": "Feature",
  "properties": {
    "addr:full":"Calle de Evora, 34 Caceres C\u00e1ceres 10005",
    "addr:housenumber":"34",
    "addr:postcode":"10005",
    "addr:street":"Calle De Evora;Ca\u0301Ceres",
    "iso:country":"ES",
    "sg:address":"Calle de Evora, 34",
    "sg:city":"Caceres",
    "sg:orig_category":"Supermercados Y Hipermercados",
    "sg:phone":"+34 927 23 90 47",
    "sg:postcode":"10005",
    "sg:province":"C\u00e1ceres",
    "wof:name":"Hiper Tambo S. L.",
    "wof:placetype":"venue"
},
  "geometry": {"coordinates":[-6.3803434372,39.4557533264],"type":"Point"}
}