{
  "type": "Feature",
  "properties": {
    "addr:full":"Luga Poligono 11, S/n Llucmajor Islas Baleares 07620",
    "addr:housenumber":"s / n",
    "addr:postcode":"07620",
    "addr:street":"Poligono 11",
    "iso:country":"ES",
    "sg:address":"Luga Poligono 11, S/n",
    "sg:city":"Llucmajor",
    "sg:orig_category":"Ense\u00d1anza Variada",
    "sg:phone":"+34 971 12 05 79",
    "sg:postcode":"07620",
    "sg:province":"Islas Baleares",
    "sg:website":"www.easet.com",
    "wof:name":"Franke 2 Die Akademie S.l.",
    "wof:placetype":"venue"
},
  "geometry": {"coordinates":[2.8897550106,39.486114502],"type":"Point"}
}