{
  "type": "Feature",
  "properties": {
    "iso:country":"ES",
    "sg:address":"Aerodromo Son Bonet, S/n",
    "sg:city":"Pont Inca",
    "sg:orig_category":"Ense\u00d1anza, Formaci\u00d3n Profesional: Aprendizaje",
    "sg:phone":"+34 971 79 48 75",
    "sg:postcode":"07009",
    "sg:province":"Islas Baleares",
    "wof:name":"Aerojet Center S.l.",
    "wof:placetype":"venue"
},
  "geometry": {"coordinates":[2.7027778625,39.593334198],"type":"Point"}
}