{
  "type": "Feature",
  "properties": {
    "addr:full":"Avda Diputacion (de La), 36 Chipiona C\u00e1diz 11550",
    "addr:housenumber":"36",
    "addr:postcode":"11550",
    "addr:street":"Avda Diputacion De La",
    "iso:country":"ES",
    "sg:address":"Avda Diputacion (de La), 36",
    "sg:city":"Chipiona",
    "sg:orig_category":"Venta, Montaje De Neum\u00c1ticos",
    "sg:phone":"+34 956 37 17 06",
    "sg:postcode":"11550",
    "sg:province":"C\u00e1diz",
    "wof:name":"Dominguez Mu\u00f1oz Miguel",
    "wof:placetype":"venue"
},
  "geometry": {"coordinates":[-6.429628849,36.7402305603],"type":"Point"}
}