{
  "type": "Feature",
  "properties": {
    "iso:country":"ES",
    "sg:address":"Plaz Anibal E Himilce, 2",
    "sg:city":"Linares",
    "sg:orig_category":"Asilos De Ancianos. Centros Privados",
    "sg:phone":"+34 953 60 23 96",
    "sg:postcode":"23700",
    "sg:province":"Ja\u00e9n",
    "wof:name":"Vidal Gomar Miguel",
    "wof:placetype":"venue"
},
  "geometry": {"coordinates":[-3.6400930882,38.0928344727],"type":"Point"}
}