{
  "type": "Feature",
  "properties": {
    "iso:country":"ES",
    "sg:address":"Calle de Casta\u00d1er, 1",
    "sg:city":"Pozuelo De Alarcon",
    "sg:orig_category":"Marketing Directo",
    "sg:phone":"+34 913 51 35 38",
    "sg:postcode":"28224",
    "sg:province":"Madrid",
    "wof:name":"Value Marketing,s.l.",
    "wof:placetype":"venue"
},
  "geometry": {"coordinates":[-3.7938969135,40.4462242126],"type":"Point"}
}