{
  "type": "Feature",
  "properties": {
    "iso:country":"ES",
    "sg:address":"Calle de La Paloma, 4",
    "sg:city":"Vitoria-gasteiz",
    "sg:orig_category":"Centros Empresariales",
    "sg:phone":"+34 945 28 75 73",
    "sg:postcode":"01002",
    "sg:province":"\u00c1lava",
    "wof:name":"Asociacion Profesional De Carniceros Y Charcuteros Cadena 15",
    "wof:placetype":"venue"
},
  "geometry": {"coordinates":[-2.6667914391,42.8496322632],"type":"Point"}
}