{
  "type": "Feature",
  "properties": {
    "iso:country":"ES",
    "sg:address":"Carrer de Muntaner, 200",
    "sg:city":"Barcelona",
    "sg:orig_category":"Fabricaci\u00d3n, Instalaci\u00d3n Y Reparaci\u00d3n De Bombas",
    "sg:phone":"+34 932 01 74 66",
    "sg:postcode":"08036",
    "sg:province":"Barcelona",
    "sg:website":"www.itur.es",
    "wof:name":"Bombas Itur S.a.",
    "wof:placetype":"venue"
},
  "geometry": {"coordinates":[2.1511991024,41.3930168152],"type":"Point"}
}