{
  "type": "Feature",
  "properties": {
    "addr:full":"Carr Doctor Fleming, Del, 19 Casco Urbano Valencia 46760",
    "addr:housenumber":"19",
    "addr:postcode":"46760",
    "addr:street":"Carr Doctor Fleming Del",
    "iso:country":"ES",
    "sg:address":"Carr Doctor Fleming, Del, 19",
    "sg:city":"Casco Urbano",
    "sg:orig_category":"Servicios Gsm",
    "sg:phone":"+34 962 82 40 03",
    "sg:postcode":"46760",
    "sg:province":"Valencia",
    "sg:website":"www.comunicat.com",
    "wof:name":"Comunica't Valldigna, S.l.",
    "wof:placetype":"venue"
},
  "geometry": {"coordinates":[-0.2594090104,39.0749702454],"type":"Point"}
}