{
  "type": "Feature",
  "properties": {
    "iso:country":"ES",
    "sg:address":"Calle de Plazuela (la), 10",
    "sg:city":"Castro Urdiales",
    "sg:orig_category":"Librer\u00cdas",
    "sg:phone":"+34 942 86 04 44",
    "sg:postcode":"39700",
    "sg:province":"Cantabria",
    "wof:name":"Tueros Garcia Daniel",
    "wof:placetype":"venue"
},
  "geometry": {"coordinates":[-3.2178399563,43.3835334778],"type":"Point"}
}