{
  "type": "Feature",
  "properties": {
    "addr:full":"Calle de Mediabarba, 42 Lucena C\u00f3rdoba 14900",
    "addr:housenumber":"42",
    "addr:postcode":"14900",
    "addr:street":"Calle De Mediabarba",
    "iso:country":"ES",
    "sg:address":"Calle de Mediabarba, 42",
    "sg:city":"Lucena",
    "sg:orig_category":"Fabricaci\u00d3n De Juguetes Autom\u00c1ticos",
    "sg:phone":"+34 957 50 36 06",
    "sg:postcode":"14900",
    "sg:province":"C\u00f3rdoba",
    "wof:name":"Rasve S.l.",
    "wof:placetype":"venue"
},
  "geometry": {"coordinates":[-4.4884390831,37.4120788574],"type":"Point"}
}