{
  "type": "Feature",
  "properties": {
    "addr:full":"Calle de Joaquin Benlloch, 22 Valencia Valencia 46006",
    "addr:housenumber":"22",
    "addr:postcode":"46006",
    "addr:street":"Calle De Joaquin Benlloch",
    "iso:country":"ES",
    "sg:address":"Calle de Joaquin Benlloch, 22",
    "sg:city":"Valencia",
    "sg:orig_category":"Loter\u00cda Y T\u00d3mbola",
    "sg:phone":"+34 963 74 59 27",
    "sg:postcode":"46006",
    "sg:province":"Valencia",
    "wof:name":"Tatay Seresola Maria Mercedes",
    "wof:placetype":"venue"
},
  "geometry": {"coordinates":[-0.3761166036,39.4527931213],"type":"Point"}
}