{
  "type": "Feature",
  "properties": {
    "addr:full":"Calle de Polvoranca, 11 Leganes Madrid 28911",
    "addr:housenumber":"11",
    "addr:postcode":"28911",
    "addr:street":"Calle De Polvoranca",
    "iso:country":"ES",
    "sg:address":"Calle de Polvoranca, 11",
    "sg:city":"Leganes",
    "sg:orig_category":"Tapicer\u00cdas",
    "sg:phone":"+34 916 93 94 17",
    "sg:postcode":"28911",
    "sg:province":"Madrid",
    "wof:name":"Tapizados Muro S.l",
    "wof:placetype":"venue"
},
  "geometry": {"coordinates":[-3.7699398994,40.3266525269],"type":"Point"}
}