{
  "type": "Feature",
  "properties": {
    "iso:country":"ES",
    "sg:address":"Avda San Esteban, 7",
    "sg:city":"Etxebarri",
    "sg:orig_category":"Molduras, Junquillos, Listones Y Molduras Perforadas",
    "sg:phone":"+34 944 26 09 34",
    "sg:postcode":"48450",
    "sg:province":"Vizcaya",
    "wof:name":"Francisco Javier Bueno Hevia",
    "wof:placetype":"venue"
},
  "geometry": {"coordinates":[-2.8906469345,43.2461738586],"type":"Point"}
}