{
  "type": "Feature",
  "properties": {
    "iso:country":"ES",
    "sg:address":"Calle de Doctor Mateos Gago, 2",
    "sg:city":"Grazalema",
    "sg:orig_category":"Alimentaci\u00d3n General (al Por Menor)",
    "sg:phone":"+34 956 13 21 65",
    "sg:postcode":"11610",
    "sg:province":"C\u00e1diz",
    "wof:name":"Mateos Mu\u00f1oz Juan Luis",
    "wof:placetype":"venue"
},
  "geometry": {"coordinates":[-5.3730177879,36.7685394287],"type":"Point"}
}