{
  "type": "Feature",
  "properties": {
    "iso:country":"ES",
    "sg:address":"Av Pla Del Vinyet, 57",
    "sg:city":"S. Cugat Valles",
    "sg:orig_category":"Masajistas Kinesiterapeutas",
    "sg:phone":"+34 935 44 17 65",
    "sg:postcode":"08172",
    "sg:province":"Barcelona",
    "wof:name":"Lublimar Grup S.l",
    "wof:placetype":"venue"
},
  "geometry": {"coordinates":[2.0861420631,41.4693832397],"type":"Point"}
}