{
  "type": "Feature",
  "properties": {
    "addr:full":"Calle de Rebordelo, 49 Boiro La Coru\u00f1a 15930",
    "addr:housenumber":"49",
    "addr:postcode":"15930",
    "addr:street":"Calle De Rebordelo;La Corun\u0303A",
    "iso:country":"ES",
    "sg:address":"Calle de Rebordelo, 49",
    "sg:city":"Boiro",
    "sg:orig_category":"Promotores Constructores",
    "sg:phone":"+34 981 84 46 62",
    "sg:postcode":"15930",
    "sg:province":"La Coru\u00f1a",
    "wof:name":"Garcia Fernandez Jose",
    "wof:placetype":"venue"
},
  "geometry": {"coordinates":[-8.8847093582,42.6471214294],"type":"Point"}
}