{
  "type": "Feature",
  "properties": {
    "addr:full":"Avda Rafael Maroto, S/n San Cristobal Murcia 30800",
    "addr:housenumber":"s / n",
    "addr:postcode":"30800",
    "addr:street":"Avda Rafael Maroto",
    "iso:country":"ES",
    "sg:address":"Avda Rafael Maroto, S/n",
    "sg:city":"San Cristobal",
    "sg:orig_category":"Loter\u00cda Y T\u00d3mbola",
    "sg:phone":"+34 968 47 18 21",
    "sg:postcode":"30800",
    "sg:province":"Murcia",
    "wof:name":"Roldan Conesa Pedro Alberto",
    "wof:placetype":"venue"
},
  "geometry": {"coordinates":[-1.6905640364,37.680557251],"type":"Point"}
}