{
  "type": "Feature",
  "properties": {
    "iso:country":"ES",
    "sg:address":"Cmno Fuente Basilio, S/n",
    "sg:city":"Miranda Ebro",
    "sg:orig_category":"Material Y Herramientas Agr\u00cdcolas",
    "sg:phone":"+34 947 32 03 58",
    "sg:postcode":"09200",
    "sg:province":"Burgos",
    "wof:name":"Martinez Gomez Emilio",
    "wof:placetype":"venue"
},
  "geometry": {"coordinates":[-2.9524741173,42.6833839417],"type":"Point"}
}