{
  "type": "Feature",
  "properties": {
    "addr:full":"Avda Victoria, 2 Madrid Madrid 28023",
    "addr:housenumber":"2",
    "addr:postcode":"28023",
    "addr:street":"Avda Victoria",
    "iso:country":"ES",
    "sg:address":"Avda Victoria, 2",
    "sg:city":"Madrid",
    "sg:orig_category":"Ropa Para Se\u00d1oras Y Caballeros (al Por Menor)",
    "sg:phone":"+34 913 72 99 54",
    "sg:postcode":"28023",
    "sg:province":"Madrid",
    "sg:website":"www.adolfo-dominguez.com",
    "wof:name":"Adolfo Dominguez S.a.",
    "wof:placetype":"venue"
},
  "geometry": {"coordinates":[-3.817211628,40.4677658081],"type":"Point"}
}