{
  "type": "Feature",
  "properties": {
    "addr:full":"Carrer de Girona, 60 S. Feliu Guixols Girona 17220",
    "addr:housenumber":"60",
    "addr:postcode":"17220",
    "addr:street":"Carrer De Girona;S. Feliu Guixols",
    "iso:country":"ES",
    "sg:address":"Carrer de Girona, 60",
    "sg:city":"S. Feliu Guixols",
    "sg:orig_category":"Molduras, Junquillos, Listones Y Molduras Perforadas",
    "sg:phone":"+34 972 32 57 31",
    "sg:postcode":"17220",
    "sg:province":"Girona",
    "wof:name":"Alejo Lidiano Milagros Altagracia",
    "wof:placetype":"venue"
},
  "geometry": {"coordinates":[3.0306839943,41.7841262817],"type":"Point"}
}