{
  "type": "Feature",
  "properties": {
    "addr:full":"Calle de Principe De Asturias, 11 Javea Alicante 03730",
    "addr:housenumber":"11",
    "addr:postcode":"03730",
    "addr:street":"Calle De Principe De Asturias",
    "iso:country":"ES",
    "sg:address":"Calle de Principe De Asturias, 11",
    "sg:city":"Javea",
    "sg:orig_category":"Servicios De Telecomunicaciones",
    "sg:phone":"+34 966 46 24 65",
    "sg:postcode":"03730",
    "sg:province":"Alicante",
    "wof:name":"Teleconcept S.l.",
    "wof:placetype":"venue"
},
  "geometry": {"coordinates":[0.161721006,38.7891464233],"type":"Point"}
}