{
  "type": "Feature",
  "properties": {
    "iso:country":"ES",
    "sg:address":"Avda Aragon De, 7",
    "sg:city":"Fraga",
    "sg:orig_category":"Ense\u00d1anza: Profesiones Art\u00cdsticas",
    "sg:phone":"+34 974 47 13 37",
    "sg:postcode":"22520",
    "sg:province":"Huesca",
    "wof:name":"De Foto Fraga S.l.",
    "wof:placetype":"venue"
},
  "geometry": {"coordinates":[0.3427700102,41.5220603943],"type":"Point"}
}