{
  "type": "Feature",
  "properties": {
    "iso:country":"ES",
    "sg:address":"Carrer de Generalitat, 37",
    "sg:city":"Piera",
    "sg:orig_category":"Centros Empresariales",
    "sg:phone":"+34 937 78 96 47",
    "sg:postcode":"08784",
    "sg:province":"Barcelona",
    "sg:website":"www.bsm99servicios.com",
    "wof:name":"Apm 99 Promocions I Serveis S.l.",
    "wof:placetype":"venue"
},
  "geometry": {"coordinates":[1.7701265812,41.5045166016],"type":"Point"}
}