{
  "type": "Feature",
  "properties": {
    "iso:country":"ES",
    "sg:address":"Calle de Notario Salvador Montesinos Bonet, 7",
    "sg:city":"Sant Joan D'alacant",
    "sg:orig_category":"Transportes De Material De Construcci\u00d3n",
    "sg:phone":"+34 965 65 35 87",
    "sg:postcode":"03550",
    "sg:province":"Alicante",
    "wof:name":"Soler Espinos Rafael",
    "wof:placetype":"venue"
},
  "geometry": {"coordinates":[-0.4336934984,38.3961448669],"type":"Point"}
}