{
  "type": "Feature",
  "properties": {
    "iso:country":"ES",
    "sg:address":"Calle de Olmo, 1",
    "sg:city":"Baza",
    "sg:orig_category":"Empresas De Pintura Y Revestimientos",
    "sg:phone":"+34 958 70 11 54",
    "sg:postcode":"18800",
    "sg:province":"Granada",
    "wof:name":"Copibaza S.l.a.",
    "wof:placetype":"venue"
},
  "geometry": {"coordinates":[-2.7778201103,37.4850578308],"type":"Point"}
}