{
  "type": "Feature",
  "properties": {
    "iso:country":"ES",
    "sg:address":"Carrer de Gran De Sant Andreu, 352",
    "sg:city":"Barcelona",
    "sg:orig_category":"Talleres: Ropa A Medida",
    "sg:phone":"+34 933 45 72 62",
    "sg:postcode":"08030",
    "sg:province":"Barcelona",
    "wof:name":"Caritg Camp Miguel",
    "wof:placetype":"venue"
},
  "geometry": {"coordinates":[2.1891400814,41.4380187988],"type":"Point"}
}