{
  "type": "Feature",
  "properties": {
    "addr:full":"Carr Santa Barbara, 67 Palamos Girona 17230",
    "addr:housenumber":"67",
    "addr:postcode":"17230",
    "addr:street":"Carr Santa Barbara",
    "iso:country":"ES",
    "sg:address":"Carr Santa Barbara, 67",
    "sg:city":"Palamos",
    "sg:orig_category":"Venta, Instalaci\u00d3n, Reparaci\u00d3n De Antenas Para Televisi\u00d3n",
    "sg:phone":"+34 972 60 10 23",
    "sg:postcode":"17230",
    "sg:province":"Girona",
    "wof:name":"Figueras Figueras Andreu",
    "wof:placetype":"venue"
},
  "geometry": {"coordinates":[3.123718977,41.8496589661],"type":"Point"}
}