{
  "type": "Feature",
  "properties": {
    "iso:country":"ES",
    "sg:address":"Calle de Eduardo Dominguez Avila, 44",
    "sg:city":"Malaga",
    "sg:orig_category":"Caf\u00c9s, Bares, Cervecer\u00cdas",
    "sg:phone":"+34 952 26 22 63",
    "sg:postcode":"29014",
    "sg:province":"M\u00e1laga",
    "wof:name":"Macrotelefonia Division Andalucia S.l.",
    "wof:placetype":"venue"
},
  "geometry": {"coordinates":[-4.4215688705,36.7313423157],"type":"Point"}
}