{
  "type": "Feature",
  "properties": {
    "addr:full":"Calle de Comunidad De Madrid, S/n Rozas De Madrid Madrid 28230",
    "addr:housenumber":"s",
    "addr:postcode":"28230",
    "addr:street":"Calle De Comunidad;Madrid;/ N Rozas",
    "iso:country":"ES",
    "sg:address":"Calle de Comunidad De Madrid, S/n",
    "sg:city":"Rozas De Madrid",
    "sg:orig_category":"Ropa Para Se\u00d1oras (al Por Menor)",
    "sg:phone":"+34 916 36 00 22",
    "sg:postcode":"28230",
    "sg:province":"Madrid",
    "wof:name":"Tatut S.l.",
    "wof:placetype":"venue"
},
  "geometry": {"coordinates":[-3.8708488941,40.487865448],"type":"Point"}
}