{
  "type": "Feature",
  "properties": {
    "iso:country":"ES",
    "sg:address":"Calle de Arroyo, 113",
    "sg:city":"Sevilla",
    "sg:classifiers":[
        {
            "category":"Autos & Motor Vehicles",
            "subcategory":"Automobile Sales",
            "type":"Retail Goods"
        }
    ],
    "sg:phone":"+34 954 53 55 59",
    "sg:postcode":"41008",
    "sg:province":"Sevilla",
    "wof:name":"Autoescuela Maria Auxiliadora S.l.",
    "wof:placetype":"venue"
},
  "geometry": {"coordinates":[-5.9737591743,37.3985900879],"type":"Point"}
}