{
  "type": "Feature",
  "properties": {
    "addr:full":"Calle de Real, 17 Trevelez Granada 18417",
    "addr:housenumber":"17",
    "addr:postcode":"18417",
    "addr:street":"Calle De Real",
    "iso:country":"ES",
    "sg:address":"Calle de Real, 17",
    "sg:city":"Trevelez",
    "sg:orig_category":"Artesan\u00cda Y Trabajos Manuales: Suministros (al Por Menor)",
    "sg:phone":"+34 958 85 86 50",
    "sg:postcode":"18417",
    "sg:province":"Granada",
    "wof:name":"Moya Ortiz Rosa Maria",
    "wof:placetype":"venue"
},
  "geometry": {"coordinates":[-3.2648088932,36.9998016357],"type":"Point"}
}