{
  "type": "Feature",
  "properties": {
    "addr:full":"Trav De Gracia, 71 Barcelona Barcelona 08006",
    "addr:housenumber":"71",
    "addr:postcode":"08006",
    "addr:street":"Trav De Gracia",
    "iso:country":"ES",
    "sg:address":"Trav De Gracia, 71",
    "sg:city":"Barcelona",
    "sg:orig_category":"Abogados",
    "sg:phone":"+34 934 14 68 58",
    "sg:postcode":"08006",
    "sg:province":"Barcelona",
    "wof:name":"R.feliu & Bernabeu Advocats Associats",
    "wof:placetype":"venue"
},
  "geometry": {"coordinates":[2.150439024,41.3968353271],"type":"Point"}
}