{
  "type": "Feature",
  "properties": {
    "addr:full":"Plaz Tranvia (del), S/n Motril Granada 18600",
    "addr:postcode":"18600",
    "addr:street":"Plaz Tranvia Del S / N;Granada",
    "iso:country":"ES",
    "sg:address":"Plaz Tranvia (del), S/n",
    "sg:city":"Motril",
    "sg:orig_category":"Supermercados Y Hipermercados",
    "sg:phone":"+34 958 82 41 30",
    "sg:postcode":"18600",
    "sg:province":"Granada",
    "wof:name":"Manuel Castilla S.l",
    "wof:placetype":"venue"
},
  "geometry": {"coordinates":[-3.518476963,36.7440452576],"type":"Point"}
}