{
  "type": "Feature",
  "properties": {
    "iso:country":"ES",
    "sg:address":"Av Eduard Toldra, 40",
    "sg:city":"Vilanova I La Geltru",
    "sg:orig_category":"Muebles, Minoristas",
    "sg:phone":"+34 938 16 55 52",
    "sg:postcode":"08800",
    "sg:province":"Barcelona",
    "wof:name":"1951 Decoracio S.l.",
    "wof:placetype":"venue"
},
  "geometry": {"coordinates":[1.735011,41.226784],"type":"Point"}
}