{
  "type": "Feature",
  "properties": {
    "iso:country":"ES",
    "sg:address":"Plaz San Juan, 2",
    "sg:city":"Valladolid",
    "sg:orig_category":"Productos Alimentarios",
    "sg:phone":"+34 983 29 77 79",
    "sg:postcode":"47002",
    "sg:province":"Valladolid",
    "wof:name":"Granel Biologico C.b.",
    "wof:placetype":"venue"
},
  "geometry": {"coordinates":[-4.7179532051,41.6513328552],"type":"Point"}
}