{
  "type": "Feature",
  "properties": {
    "iso:country":"ES",
    "sg:address":"Calle de D(campollano), 45",
    "sg:city":"Albacete",
    "sg:orig_category":"Maquinaria Para Industrias Diversas",
    "sg:phone":"+34 967 24 87 27",
    "sg:postcode":"02006",
    "sg:province":"Albacete",
    "sg:website":"www.garcamps.com",
    "wof:name":"Suministros Garcamps S. A.",
    "wof:placetype":"venue"
},
  "geometry": {"coordinates":[-1.9363039732,39.0603866577],"type":"Point"}
}