{
  "type": "Feature",
  "properties": {
    "iso:country":"ES",
    "sg:address":"Calle de Callejonda, S/n",
    "sg:city":"Miranda Ebro",
    "sg:orig_category":"Explotaci\u00d3n De Canteras",
    "sg:phone":"+34 947 32 08 62",
    "sg:postcode":"09200",
    "sg:province":"Burgos",
    "wof:name":"Asfibu S.a.",
    "wof:placetype":"venue"
},
  "geometry": {"coordinates":[-2.9675571918,42.6790657043],"type":"Point"}
}