{
  "type": "Feature",
  "properties": {
    "iso:country":"ES",
    "sg:address":"C/ Bartolome Vicente Ramon, De, 10",
    "sg:city":"S. Antoni Portmany",
    "sg:orig_category":"Mercer\u00cda, Lencer\u00cda (al Por Menor)",
    "sg:phone":"+34 971 34 28 18",
    "sg:postcode":"07820",
    "sg:province":"Islas Baleares",
    "wof:name":"Ribas Tur Margarita",
    "wof:placetype":"venue"
},
  "geometry": {"coordinates":[1.5188339949,39.1094055176],"type":"Point"}
}