{
  "type": "Feature",
  "properties": {
    "iso:country":"ES",
    "sg:address":"C/ Alvado, 7",
    "sg:city":"Elche",
    "sg:orig_category":"M\u00c9dicos: Ginecolog\u00cda Y Obstetricia",
    "sg:phone":"+34 965 42 05 51",
    "sg:postcode":"03202",
    "sg:province":"Alicante",
    "wof:name":"Bermejo Fenoll Maria Dolores",
    "wof:placetype":"venue"
},
  "geometry": {"coordinates":[-0.698127985,38.2666282654],"type":"Point"}
}