{
  "type": "Feature",
  "properties": {
    "iso:country":"ES",
    "sg:address":"Calle de Manuel De Falla, 6",
    "sg:city":"San Jose Rinconada",
    "sg:orig_category":"Cervecer\u00cdas",
    "sg:phone":"+34 954 79 10 48",
    "sg:postcode":"41300",
    "sg:province":"Sevilla",
    "wof:name":"Pacheco Ba\u00f1egil Manuela",
    "wof:placetype":"venue"
},
  "geometry": {"coordinates":[-5.9463200569,37.4791221619],"type":"Point"}
}