{
  "type": "Feature",
  "properties": {
    "addr:full":"Calle de La Fabrica, 6 Alcora Castell\u00f3n 12110",
    "addr:housenumber":"6",
    "addr:postcode":"12110",
    "addr:street":"Calle De La Fabrica;Castello\u0301N",
    "iso:country":"ES",
    "sg:address":"Calle de La Fabrica, 6",
    "sg:city":"Alcora",
    "sg:orig_category":"Art\u00cdculos De Regalo (al Por Menor)",
    "sg:phone":"+34 964 36 10 04",
    "sg:postcode":"12110",
    "sg:province":"Castell\u00f3n",
    "wof:name":"Arlequin C.b.",
    "wof:placetype":"venue"
},
  "geometry": {"coordinates":[-0.2134560943,40.0731620789],"type":"Point"}
}