{
  "type": "Feature",
  "properties": {
    "addr:full":"Ctra. Guia, 3 Gijon Asturias 33203",
    "addr:housenumber":"3",
    "addr:postcode":"33203",
    "addr:street":"Ctra. Guia",
    "iso:country":"ES",
    "sg:address":"Ctra. Guia, 3",
    "sg:city":"Gijon",
    "sg:orig_category":"Art\u00cdculos De Decoraci\u00d3n",
    "sg:phone":"+34 985 36 53 07",
    "sg:postcode":"33203",
    "sg:province":"Asturias",
    "sg:website":"www.ceramicalaguia.com",
    "wof:name":"Ceramica Laguia S.l.",
    "wof:placetype":"venue"
},
  "geometry": {"coordinates":[-5.6319561005,43.5292129517],"type":"Point"}
}