{
  "type": "Feature",
  "properties": {
    "iso:country":"ES",
    "sg:address":"Calle de Torrelaguna, 64",
    "sg:city":"Madrid",
    "sg:orig_category":"Inmobiliaria (agencias)",
    "sg:phone":"+34 915 19 09 04",
    "sg:postcode":"28043",
    "sg:province":"Madrid",
    "wof:name":"Construcciones En Comunidad S.l.",
    "wof:placetype":"venue"
},
  "geometry": {"coordinates":[-3.6565430164,40.4477233887],"type":"Point"}
}