{
  "type": "Feature",
  "properties": {
    "iso:country":"ES",
    "sg:address":"Rbla Pompeu Fabra, 174",
    "sg:city":"Gava",
    "sg:classifiers":[
        {
            "category":"Personal",
            "subcategory":"Barber",
            "type":"Services"
        }
    ],
    "sg:phone":"+34 936 62 93 83",
    "sg:postcode":"08850",
    "sg:province":"Barcelona",
    "sg:tags":[
        "caballeros",
        "de",
        "peluqueros"
    ],
    "wof:name":"Garcia Montero Bartolome",
    "wof:placetype":"venue"
},
  "geometry": {"coordinates":[1.9948459864,41.3109397888],"type":"Point"}
}