{
  "type": "Feature",
  "properties": {
    "iso:country":"ES",
    "sg:address":"Luga Monserrat, 28",
    "sg:city":"Monserrat",
    "sg:orig_category":"Asesor\u00cda Sobre Comunicaci\u00d3n De Empresas",
    "sg:phone":"+34 981 13 48 02",
    "sg:postcode":"15009",
    "sg:province":"La Coru\u00f1a",
    "wof:name":"Judel Alcala Asesores S.l.",
    "wof:placetype":"venue"
},
  "geometry": {"coordinates":[-8.3964595795,43.3701095581],"type":"Point"}
}