{
  "type": "Feature",
  "properties": {
    "addr:full":"Escultor Estevez, 2 La Orotava Santa Cruz De Tenerife 38300",
    "addr:housenumber":"2",
    "addr:postcode":"38300",
    "addr:street":"Escultor Estevez",
    "iso:country":"ES",
    "sg:address":"Escultor Estevez, 2",
    "sg:city":"La Orotava",
    "sg:orig_category":"Abogados",
    "sg:phone":"+34 922 32 25 32",
    "sg:postcode":"38300",
    "sg:province":"Santa Cruz De Tenerife",
    "wof:name":"Diaz Mendez Gregorio",
    "wof:placetype":"venue"
},
  "geometry": {"coordinates":[-16.5189990997,28.3903846741],"type":"Point"}
}