{
  "type": "Feature",
  "properties": {
    "addr:full":"Ctra Sant Joan Les Abadesses, 6 Olot Girona 17800",
    "addr:housenumber":"6",
    "addr:postcode":"17800",
    "addr:street":"Ctra Sant Joan;Abadesses",
    "iso:country":"ES",
    "sg:address":"Ctra Sant Joan Les Abadesses, 6",
    "sg:city":"Olot",
    "sg:orig_category":"Alimentaci\u00d3n General (al Por Menor)",
    "sg:phone":"+34 972 26 12 65",
    "sg:postcode":"17800",
    "sg:province":"Girona",
    "wof:name":"Coma Curos Pilar",
    "wof:placetype":"venue"
},
  "geometry": {"coordinates":[2.4807839394,42.1850471497],"type":"Point"}
}