{
  "type": "Feature",
  "properties": {
    "iso:country":"ES",
    "sg:address":"Carrer de Guatemala, 17",
    "sg:city":"Barcelona",
    "sg:orig_category":"Peluquer\u00cdas",
    "sg:phone":"+34 933 07 06 24",
    "sg:postcode":"08018",
    "sg:province":"Barcelona",
    "wof:name":"Carbonell March Maria Angels",
    "wof:placetype":"venue"
},
  "geometry": {"coordinates":[2.1932449341,41.4089317322],"type":"Point"}
}