{
  "type": "Feature",
  "properties": {
    "iso:country":"ES",
    "sg:address":"Principe De Viana, 14",
    "sg:city":"Estella",
    "sg:orig_category":"Carnicer\u00cdas, Carnicer\u00cdas",
    "sg:phone":"+34 948 54 66 31",
    "sg:postcode":"31200",
    "sg:province":"Navarra",
    "wof:name":"Guinea Urra Miguel Angel",
    "wof:placetype":"venue"
},
  "geometry": {"coordinates":[-2.0335330963,42.6707420349],"type":"Point"}
}