{
  "type": "Feature",
  "properties": {
    "iso:country":"ES",
    "sg:address":"Avda Estacion Nueva, 55",
    "sg:city":"Calamocha",
    "sg:orig_category":"Material Y Herramientas Agr\u00cdcolas",
    "sg:phone":"+34 978 73 06 58",
    "sg:postcode":"44200",
    "sg:province":"Teruel",
    "wof:name":"Talleres Martin Maquinaria Agricola S.l.",
    "wof:placetype":"venue"
},
  "geometry": {"coordinates":[-1.2993890047,40.9128990173],"type":"Point"}
}