{
  "type": "Feature",
  "properties": {
    "iso:country":"ES",
    "sg:address":"Calle de Reyes, 3",
    "sg:city":"Madrid",
    "sg:orig_category":"Asesor\u00cda De Formaci\u00d3n Y Gesti\u00d3n De Personal",
    "sg:phone":"+34 915 23 91 10",
    "sg:postcode":"28015",
    "sg:province":"Madrid",
    "wof:name":"Unilaboral 10 S.l.",
    "wof:placetype":"venue"
},
  "geometry": {"coordinates":[-3.7080419064,40.4243125916],"type":"Point"}
}