{
  "type": "Feature",
  "properties": {
    "iso:country":"ES",
    "sg:address":"Calle de Poza Licenciado, 53",
    "sg:city":"Bilbao",
    "sg:orig_category":"Universidades",
    "sg:phone":"+34 944 42 37 71",
    "sg:postcode":"48011",
    "sg:province":"Vizcaya",
    "wof:name":"Iglesias Martinez Genaro",
    "wof:placetype":"venue"
},
  "geometry": {"coordinates":[-2.9419789314,43.2623214722],"type":"Point"}
}