{
  "type": "Feature",
  "properties": {
    "iso:country":"ES",
    "sg:address":"Carr Doctor Berenguer, 4",
    "sg:city":"Almenara",
    "sg:orig_category":"Cajas Para Embalar",
    "sg:phone":"+34 962 61 00 54",
    "sg:postcode":"12590",
    "sg:province":"Castell\u00f3n",
    "wof:name":"Caja Rural San Roque De Almenara",
    "wof:placetype":"venue"
},
  "geometry": {"coordinates":[-0.2243950069,39.7532844543],"type":"Point"}
}