{
  "type": "Feature",
  "properties": {
    "iso:country":"ES",
    "sg:address":"Avda Constitucion (de La), S/n",
    "sg:city":"S. Fernando",
    "sg:orig_category":"M\u00c9dicos: Estomatolog\u00cda",
    "sg:phone":"+34 956 48 69 69",
    "sg:postcode":"11100",
    "sg:province":"C\u00e1diz",
    "wof:name":"Martinez Vila Miguel Angel",
    "wof:placetype":"venue"
},
  "geometry": {"coordinates":[-6.2130050659,36.4521331787],"type":"Point"}
}