{
  "type": "Feature",
  "properties": {
    "addr:full":"Calle de Amelgares, 4 Miguelturra Ciudad Real 13170",
    "addr:housenumber":"4",
    "addr:postcode":"13170",
    "addr:street":"Calle De Amelgares",
    "iso:country":"ES",
    "sg:address":"Calle de Amelgares, 4",
    "sg:city":"Miguelturra",
    "sg:orig_category":"Comercio De Piezas De Recambio Y De Accesorios De Veh\u00cdculos, Veh\u00cdculos Industriales",
    "sg:phone":"+34 926 24 04 73",
    "sg:postcode":"13170",
    "sg:province":"Ciudad Real",
    "wof:name":"Aparicio Casero E Hijos S.l.",
    "wof:placetype":"venue"
},
  "geometry": {"coordinates":[-3.8974113464,38.9631958008],"type":"Point"}
}