{
  "type": "Feature",
  "properties": {
    "addr:full":"Avda Constitucion (de La), 30 Sanlucar De Barrameda C\u00e1diz 11540",
    "addr:housenumber":"30",
    "addr:postcode":"11540",
    "addr:street":"Avda Constitucion De La;Ca\u0301Diz",
    "iso:country":"ES",
    "sg:address":"Avda Constitucion (de La), 30",
    "sg:city":"Sanlucar De Barrameda",
    "sg:orig_category":"Supermercados Y Hipermercados",
    "sg:phone":"+34 956 38 52 77",
    "sg:postcode":"11540",
    "sg:province":"C\u00e1diz",
    "wof:name":"Distribuidora Internacional De Alimentacion S.a.",
    "wof:placetype":"venue"
},
  "geometry": {"coordinates":[-6.3469061852,36.76978302],"type":"Point"}
}