{
  "type": "Feature",
  "properties": {
    "iso:country":"ES",
    "sg:address":"Cra. Olot, 2",
    "sg:city":"Manlleu",
    "sg:orig_category":"Supermercados Y Hipermercados",
    "sg:phone":"+34 938 51 21 64",
    "sg:postcode":"08560",
    "sg:province":"Barcelona",
    "wof:name":"Bon Preu S. A.",
    "wof:placetype":"venue"
},
  "geometry": {"coordinates":[2.2860350609,42.0011787415],"type":"Point"}
}