{
  "type": "Feature",
  "properties": {
    "iso:country":"ES",
    "sg:address":"Calle de Clara Del Rey, 50",
    "sg:city":"Madrid",
    "sg:orig_category":"Retoques De Vestidos",
    "sg:phone":"+34 914 15 57 00",
    "sg:postcode":"28002",
    "sg:province":"Madrid",
    "wof:name":"Terreros Ojeda Carmita",
    "wof:placetype":"venue"
},
  "geometry": {"coordinates":[-3.668186903,40.44581604],"type":"Point"}
}