{
  "type": "Feature",
  "properties": {
    "addr:full":"Calle de Joaquin Salas, 1 Pe\u00d1acastillo Cantabria 39011",
    "addr:housenumber":"1",
    "addr:postcode":"39011",
    "addr:street":"Calle De Joaquin Salas",
    "iso:country":"ES",
    "sg:address":"Calle de Joaquin Salas, 1",
    "sg:city":"Pe\u00d1acastillo",
    "sg:orig_category":"Ense\u00d1anza, Formaci\u00d3n Profesional: Aprendizaje",
    "sg:phone":"+34 942 32 45 43",
    "sg:postcode":"39011",
    "sg:province":"Cantabria",
    "wof:name":"Ministerio De Fomento Demarcacion De Car",
    "wof:placetype":"venue"
},
  "geometry": {"coordinates":[-3.8739891052,43.4491386414],"type":"Point"}
}