{
  "type": "Feature",
  "properties": {
    "iso:country":"ES",
    "sg:address":"Ctra Villaverde, S/n",
    "sg:city":"Pedrajas S. Esteban",
    "sg:orig_category":"Barnizadores",
    "sg:phone":"+34 983 60 50 37",
    "sg:postcode":"47430",
    "sg:province":"Valladolid",
    "wof:name":"Decoracion Barnasa S.l.",
    "wof:placetype":"venue"
},
  "geometry": {"coordinates":[-4.5757808685,41.3409805298],"type":"Point"}
}