{
  "type": "Feature",
  "properties": {
    "iso:country":"ES",
    "sg:address":"Calle de Moscatel, 2",
    "sg:city":"Toledo",
    "sg:orig_category":"Guarder\u00cdas",
    "sg:phone":"+34 925 25 32 43",
    "sg:postcode":"45005",
    "sg:province":"Toledo",
    "wof:name":"Escuela Infantil De Nuestra Se\u00f1ora De Fatima S.l.l.",
    "wof:placetype":"venue"
},
  "geometry": {"coordinates":[-4.0518841743,39.8620529175],"type":"Point"}
}