{
  "type": "Feature",
  "properties": {
    "addr:full":"Calle de Restoy, 101 Almeria Almer\u00eda 04003",
    "addr:housenumber":"101",
    "addr:postcode":"04003",
    "addr:street":"Calle De Restoy",
    "iso:country":"ES",
    "sg:address":"Calle de Restoy, 101",
    "sg:city":"Almeria",
    "sg:orig_category":"Molduras, Junquillos, Listones Y Molduras Perforadas",
    "sg:phone":"+34 950 24 34 23",
    "sg:postcode":"04003",
    "sg:province":"Almer\u00eda",
    "wof:name":"Martil Valverde Maria Del Carmen",
    "wof:placetype":"venue"
},
  "geometry": {"coordinates":[-2.4626839161,36.8467445374],"type":"Point"}
}