{
  "type": "Feature",
  "properties": {
    "addr:full":"Pol. Ind. Barrio Gonzalin, 1 Seana Asturias 33618",
    "addr:housenumber":"1",
    "addr:postcode":"33618",
    "addr:street":"Gonzalin;Asturias",
    "iso:country":"ES",
    "sg:address":"Pol. Ind. Barrio Gonzalin, 1",
    "sg:city":"Seana",
    "sg:orig_category":"Muebles Y Accesorios Para Cocinas Y Cuartos De Ba\u00d1o (al Por Menor)",
    "sg:phone":"+34 985 46 27 00",
    "sg:postcode":"33618",
    "sg:province":"Asturias",
    "sg:website":"www.alonsoylopez.com",
    "wof:name":"Alonso Y Lopez S. L.",
    "wof:placetype":"venue"
},
  "geometry": {"coordinates":[-5.7806081772,43.2410583496],"type":"Point"}
}