{
  "type": "Feature",
  "properties": {
    "addr:full":"Calle de Santo Domingo, 17 G\u00fcimar Santa Cruz De Tenerife 38500",
    "addr:housenumber":"17",
    "addr:postcode":"38500",
    "addr:street":"Calle De Santo Domingo",
    "iso:country":"ES",
    "sg:address":"Calle de Santo Domingo, 17",
    "sg:city":"G\u00fcimar",
    "sg:orig_category":"Radiocomunicaciones, Telefon\u00cda M\u00d3vil, Radiomensajer\u00cda: Servicios, Comercializaci\u00d3n",
    "sg:phone":"+34 922 51 40 52",
    "sg:postcode":"38500",
    "sg:province":"Santa Cruz De Tenerife",
    "wof:name":"Union De Radioaficionados Del Valle De G",
    "wof:placetype":"venue"
},
  "geometry": {"coordinates":[-16.4114322662,28.3139057159],"type":"Point"}
}