{
  "type": "Feature",
  "properties": {
    "iso:country":"ES",
    "sg:address":"Plaz Serna (la), S/n",
    "sg:city":"Potes",
    "sg:orig_category":"Supermercados Y Hipermercados",
    "sg:phone":"+34 942 73 05 26",
    "sg:postcode":"39570",
    "sg:province":"Cantabria",
    "wof:name":"Grupo El Arbol Distribucion Y Supermercados S.a. Unipersonal",
    "wof:placetype":"venue"
},
  "geometry": {"coordinates":[-4.6248579025,43.1542053223],"type":"Point"}
}