{
  "type": "Feature",
  "properties": {
    "addr:full":"Carrer de Girona, 39 Roses Girona 17480",
    "addr:housenumber":"39",
    "addr:postcode":"17480",
    "addr:street":"Carrer De Girona",
    "iso:country":"ES",
    "sg:address":"Carrer de Girona, 39",
    "sg:city":"Roses",
    "sg:orig_category":"Sociedades, Compa\u00d1\u00cdas Aseguradoras",
    "sg:phone":"+34 972 15 07 39",
    "sg:postcode":"17480",
    "sg:province":"Girona",
    "wof:name":"Lloret Martinez Marc",
    "wof:placetype":"venue"
},
  "geometry": {"coordinates":[3.177063942,42.2631645203],"type":"Point"}
}