{
  "type": "Feature",
  "properties": {
    "iso:country":"ES",
    "sg:address":"Calle de Marques De Mondejar, 26",
    "sg:city":"Madrid",
    "sg:orig_category":"Pintores",
    "sg:phone":"+34 913 55 34 74",
    "sg:postcode":"28028",
    "sg:province":"Madrid",
    "wof:name":"Gracia Gomez-pintado Manuel De",
    "wof:placetype":"venue"
},
  "geometry": {"coordinates":[-3.6642289162,40.428188324],"type":"Point"}
}