{
  "type": "Feature",
  "properties": {
    "addr:full":"Calle de Canoniga, 6 Arrabal De Portillo Valladolid 47160",
    "addr:housenumber":"6",
    "addr:postcode":"47160",
    "addr:street":"Calle De Canoniga",
    "iso:country":"ES",
    "sg:address":"Calle de Canoniga, 6",
    "sg:city":"Arrabal De Portillo",
    "sg:orig_category":"Venta, Instalaci\u00d3n De Calefacci\u00d3n",
    "sg:phone":"+34 983 55 64 89",
    "sg:postcode":"47160",
    "sg:province":"Valladolid",
    "wof:name":"Hermanos Fernandez Rojo C.b.",
    "wof:placetype":"venue"
},
  "geometry": {"coordinates":[-4.5923318863,41.4722366333],"type":"Point"}
}