{
  "type": "Feature",
  "properties": {
    "iso:country":"ES",
    "sg:address":"Atamaria, 5",
    "sg:city":"La Manga Club",
    "sg:orig_category":"Alquiler De Veh\u00cdculos: Turismos Y Utilitarios",
    "sg:phone":"+34 968 17 51 99",
    "sg:postcode":"30385",
    "sg:province":"Murcia",
    "wof:name":"Sol-mar Alquiler De Vehiculos S.l.",
    "wof:placetype":"venue"
},
  "geometry": {"coordinates":[-0.8023809791,37.5983123779],"type":"Point"}
}