{
  "type": "Feature",
  "properties": {
    "addr:full":"Sabaters, 8 Ciutadella Menorca Islas Baleares 07760",
    "addr:housenumber":"8",
    "addr:postcode":"07760",
    "addr:street":"Sabaters",
    "iso:country":"ES",
    "sg:address":"Sabaters, 8",
    "sg:city":"Ciutadella Menorca",
    "sg:orig_category":"Bebidas",
    "sg:phone":"+34 971 48 40 19",
    "sg:postcode":"07760",
    "sg:province":"Islas Baleares",
    "wof:name":"Compa\u00d1ia De Bebidas Pepsico S.l.",
    "wof:placetype":"venue"
},
  "geometry": {"coordinates":[3.8416149616,40.0027542114],"type":"Point"}
}