{
  "type": "Feature",
  "properties": {
    "iso:country":"ES",
    "sg:address":"Calle de Infanta Do\u00d1a Maria, 69",
    "sg:city":"Cordoba",
    "sg:orig_category":"\u00d3ptica: Instrumentos (fabricaci\u00d3n)",
    "sg:phone":"+34 957 23 11 23",
    "sg:postcode":"14004",
    "sg:province":"C\u00f3rdoba",
    "wof:name":"Casa\u00f1o Salido Rafael",
    "wof:placetype":"venue"
},
  "geometry": {"coordinates":[-4.7912278175,37.8801040649],"type":"Point"}
}