{
  "type": "Feature",
  "properties": {
    "addr:full":"Calle de Manuel Anton, 2 Alacant Alicante 03004",
    "addr:housenumber":"2",
    "addr:postcode":"03004",
    "addr:street":"Calle De Manuel Anton",
    "iso:country":"ES",
    "sg:address":"Calle de Manuel Anton, 2",
    "sg:city":"Alacant",
    "sg:classifiers":[
        {
            "category":"Professional",
            "subcategory":"Management & Consulting",
            "type":"Services"
        }
    ],
    "sg:phone":"+34 965 20 66 68",
    "sg:postcode":"03004",
    "sg:province":"Alicante",
    "sg:tags":[
        "asesor\u00cda",
        "en",
        "marketing"
    ],
    "wof:name":"Garcia Lajarin Vicente",
    "wof:placetype":"venue"
},
  "geometry": {"coordinates":[-0.4849520028,38.3498268127],"type":"Point"}
}