{
  "type": "Feature",
  "properties": {
    "addr:full":"Calle de Rio Tajo, 7 Alcala Henares Madrid 28804",
    "addr:housenumber":"7",
    "addr:postcode":"28804",
    "addr:street":"Calle De Rio Tajo",
    "iso:country":"ES",
    "sg:address":"Calle de Rio Tajo, 7",
    "sg:city":"Alcala Henares",
    "sg:orig_category":"Empresas De Portes Y Mensajer\u00cda",
    "sg:phone":"+34 918 80 19 65",
    "sg:postcode":"28804",
    "sg:province":"Madrid",
    "wof:name":"Complu Courier S.l.",
    "wof:placetype":"venue"
},
  "geometry": {"coordinates":[-3.3620560169,40.478805542],"type":"Point"}
}