{
  "type": "Feature",
  "properties": {
    "addr:full":"Avda Andalucia, 1 Almu\u00f1ecar Granada 18690",
    "addr:housenumber":"1",
    "addr:postcode":"18690",
    "addr:street":"Avda Andalucia",
    "iso:country":"ES",
    "sg:address":"Avda Andalucia, 1",
    "sg:city":"Almu\u00f1ecar",
    "sg:orig_category":"Farmacias",
    "sg:phone":"+34 958 88 14 21",
    "sg:postcode":"18690",
    "sg:province":"Granada",
    "wof:name":"Barrera Codina Ana Teresa",
    "wof:placetype":"venue"
},
  "geometry": {"coordinates":[-3.6895589828,36.7353591919],"type":"Point"}
}