{
  "type": "Feature",
  "properties": {
    "addr:full":"Calle de E, 87 Pol. Malpica Zaragoza 50057",
    "addr:housenumber":"87",
    "addr:postcode":"50057",
    "addr:street":"Calle De E;Pol. Malpica",
    "iso:country":"ES",
    "sg:address":"Calle de E, 87",
    "sg:city":"Pol. Malpica",
    "sg:orig_category":"Metalurgia",
    "sg:phone":"+34 976 57 29 64",
    "sg:postcode":"50057",
    "sg:province":"Zaragoza",
    "wof:name":"Tratamientos Termicos Grama S.l.",
    "wof:placetype":"venue"
},
  "geometry": {"coordinates":[-0.7761809826,41.6513137817],"type":"Point"}
}