{
  "type": "Feature",
  "properties": {
    "addr:full":"Calle de Segovia, 14 Aldeavieja \u00c1vila 05193",
    "addr:housenumber":"14",
    "addr:postcode":"05193",
    "addr:street":"Calle De Segovia;A\u0301Vila",
    "iso:country":"ES",
    "sg:address":"Calle de Segovia, 14",
    "sg:city":"Aldeavieja",
    "sg:orig_category":"Transportes Por Carretera: Lotes Completos, Mercanc\u00cdas Diversas",
    "sg:phone":"+34 920 20 40 71",
    "sg:postcode":"05193",
    "sg:province":"\u00c1vila",
    "wof:name":"Transjujo S.l.",
    "wof:placetype":"venue"
},
  "geometry": {"coordinates":[-4.4700288773,40.7430496216],"type":"Point"}
}