{
  "type": "Feature",
  "properties": {
    "iso:country":"ES",
    "sg:address":"Tejero, 11",
    "sg:city":"Sobrado",
    "sg:orig_category":"Electrodom\u00c9sticos (al Por Menor)",
    "sg:phone":"+34 985 90 11 68",
    "sg:postcode":"33875",
    "sg:province":"Asturias",
    "wof:name":"Dema Iglesias Beningna",
    "wof:placetype":"venue"
},
  "geometry": {"coordinates":[-6.5462470055,43.2659797668],"type":"Point"}
}