{
  "type": "Feature",
  "properties": {
    "iso:country":"ES",
    "sg:address":"Carrer de Santa Maria, 3",
    "sg:city":"Vilafranca Penedes",
    "sg:orig_category":"Art\u00cdculos Funerarios (al Por Menor)",
    "sg:phone":"+34 938 92 01 05",
    "sg:postcode":"08720",
    "sg:province":"Barcelona",
    "wof:name":"Serveis Funeraris Del Penedes S.l.",
    "wof:placetype":"venue"
},
  "geometry": {"coordinates":[1.6977699995,41.3465843201],"type":"Point"}
}