{
  "type": "Feature",
  "properties": {
    "iso:country":"ES",
    "sg:address":"Praz Dona Agueda, 1",
    "sg:city":"Betanzos",
    "sg:orig_category":"Marketing Telef\u00d3nico",
    "sg:phone":"+34 981 77 11 47",
    "sg:postcode":"15300",
    "sg:province":"La Coru\u00f1a",
    "wof:name":"Call Center Brigatel S.l.",
    "wof:placetype":"venue"
},
  "geometry": {"coordinates":[-8.2119092941,43.279914856],"type":"Point"}
}