{
  "type": "Feature",
  "properties": {
    "addr:full":"Calle de Lentisco, 11 Cartaya Huelva 21450",
    "addr:housenumber":"11",
    "addr:postcode":"21450",
    "addr:street":"Calle De Lentisco",
    "iso:country":"ES",
    "sg:address":"Calle de Lentisco, 11",
    "sg:city":"Cartaya",
    "sg:orig_category":"Empresas De Desmonte",
    "sg:phone":"+34 959 39 10 51",
    "sg:postcode":"21450",
    "sg:province":"Huelva",
    "wof:name":"De Los Santos Maestre Juan Manuel",
    "wof:placetype":"venue"
},
  "geometry": {"coordinates":[-7.1533670425,37.2782974243],"type":"Point"}
}