{
  "type": "Feature",
  "properties": {
    "addr:full":"Avda Espa\u00d1a (de), 31 Priego Cordoba C\u00f3rdoba 14800",
    "addr:housenumber":"31",
    "addr:postcode":"14800",
    "addr:street":"Avda Espan\u0303A De;Cordoba Co\u0301Rdoba",
    "iso:country":"ES",
    "sg:address":"Avda Espa\u00d1a (de), 31",
    "sg:city":"Priego Cordoba",
    "sg:orig_category":"Plomeros",
    "sg:phone":"+34 957 54 13 52",
    "sg:postcode":"14800",
    "sg:province":"C\u00f3rdoba",
    "wof:name":"Campa\u00f1a Miranda Ana Maria",
    "wof:placetype":"venue"
},
  "geometry": {"coordinates":[-4.2043190002,37.4393424988],"type":"Point"}
}