{
  "type": "Feature",
  "properties": {
    "iso:country":"ES",
    "sg:address":"Calle de Andoain, 29",
    "sg:city":"Donostia-san Sebastian",
    "sg:orig_category":"Calefacci\u00d3n Central: Material (fabricaci\u00d3n, Al Por Mayor)",
    "sg:phone":"+34 943 31 15 91",
    "sg:postcode":"20009",
    "sg:province":"Guip\u00f9zcoa",
    "wof:name":"Termodis S.l.",
    "wof:placetype":"venue"
},
  "geometry": {"coordinates":[-1.9928879738,43.2997589111],"type":"Point"}
}