{
  "type": "Feature",
  "properties": {
    "iso:country":"ES",
    "sg:address":"Monasterio Zilbeti, 5",
    "sg:city":"Iru\u00f1a",
    "sg:orig_category":"Empresas De Limpieza",
    "sg:phone":"+34 948 17 24 51",
    "sg:postcode":"31011",
    "sg:province":"Navarra",
    "wof:name":"Boachie  Akosua",
    "wof:placetype":"venue"
},
  "geometry": {"coordinates":[-1.6565890312,42.8159942627],"type":"Point"}
}