{
  "type": "Feature",
  "properties": {
    "iso:country":"ES",
    "sg:address":"Calle de Atocha, 47",
    "sg:city":"Madrid",
    "sg:orig_category":"Caf\u00c9s, Bares, Cervecer\u00cdas",
    "sg:phone":"+34 913 69 43 39",
    "sg:postcode":"28012",
    "sg:province":"Madrid",
    "wof:name":"Manzanares Martinez Luis Jesus",
    "wof:placetype":"venue"
},
  "geometry": {"coordinates":[-3.7008273602,40.4131889343],"type":"Point"}
}