{
  "type": "Feature",
  "properties": {
    "iso:country":"ES",
    "sg:address":"Carrer de Corsega, 483",
    "sg:city":"Barcelona",
    "sg:orig_category":"Grabados",
    "sg:phone":"+34 934 57 19 37",
    "sg:postcode":"08025",
    "sg:province":"Barcelona",
    "wof:name":"Retolacio Gravada Monsan S.l.",
    "wof:placetype":"venue"
},
  "geometry": {"coordinates":[2.1682291031,41.4034385681],"type":"Point"}
}