{
  "type": "Feature",
  "properties": {
    "addr:full":"A. Verges, 10 S. Andreu Llavaneres Barcelona 08392",
    "addr:housenumber":"10",
    "addr:postcode":"08392",
    "addr:street":"Andreu",
    "iso:country":"ES",
    "sg:address":"A. Verges, 10",
    "sg:city":"S. Andreu Llavaneres",
    "sg:orig_category":"Caf\u00c9s, Bares, Cervecer\u00cdas",
    "sg:phone":"+34 937 92 87 27",
    "sg:postcode":"08392",
    "sg:province":"Barcelona",
    "wof:name":"La Trobada S.c.p.",
    "wof:placetype":"venue"
},
  "geometry": {"coordinates":[2.4849700928,41.5697517395],"type":"Point"}
}