{
  "type": "Feature",
  "properties": {
    "iso:country":"ES",
    "sg:address":"Rua Castro, 9",
    "sg:city":"Betanzos",
    "sg:orig_category":"Ropa Para Se\u00d1oras (al Por Menor)",
    "sg:phone":"+34 981 77 39 80",
    "sg:postcode":"15300",
    "sg:province":"La Coru\u00f1a",
    "wof:name":"Mi\u00f1ones Castro Balbina",
    "wof:placetype":"venue"
},
  "geometry": {"coordinates":[-8.2105913162,43.2806167603],"type":"Point"}
}