{
  "type": "Feature",
  "properties": {
    "iso:country":"ES",
    "sg:address":"Calle de Marcial Carlo Font, 2",
    "sg:city":"Malpartida Plasencia",
    "sg:orig_category":"Alimentaci\u00d3n General (al Por Menor)",
    "sg:phone":"+34 927 45 94 68",
    "sg:postcode":"10680",
    "sg:province":"C\u00e1ceres",
    "wof:name":"Palacios Fernandez Victor",
    "wof:placetype":"venue"
},
  "geometry": {"coordinates":[-6.0468177795,39.97681427],"type":"Point"}
}