{
  "type": "Feature",
  "properties": {
    "addr:full":"Via Augusta, 118 Barcelona Barcelona 08006",
    "addr:housenumber":"118",
    "addr:postcode":"08006",
    "addr:street":"Via Augusta",
    "iso:country":"ES",
    "sg:address":"Via Augusta, 118",
    "sg:city":"Barcelona",
    "sg:orig_category":"M\u00c9dicos: Pediatr\u00cda. Enfermedades De Los Ni\u00d1os",
    "sg:phone":"+34 932 17 82 48",
    "sg:postcode":"08006",
    "sg:province":"Barcelona",
    "wof:name":"Callis Bracons Luis Maria",
    "wof:placetype":"venue"
},
  "geometry": {"coordinates":[2.1479029655,41.4014053345],"type":"Point"}
}