{
  "type": "Feature",
  "properties": {
    "iso:country":"ES",
    "sg:address":"C/ Al\u00c7amora (els), S/n",
    "sg:city":"Alcoi",
    "sg:orig_category":"Ropa Para Se\u00d1oras (al Por Menor)",
    "sg:phone":"+34 965 33 16 23",
    "sg:postcode":"03802",
    "sg:province":"Alicante",
    "wof:name":"Punto Roma S.l.",
    "wof:placetype":"venue"
},
  "geometry": {"coordinates":[-0.4799140096,38.6952476501],"type":"Point"}
}