{
  "type": "Feature",
  "properties": {
    "iso:country":"ES",
    "sg:address":"Carrer de Espirall, 74",
    "sg:city":"Vilafranca Penedes",
    "sg:orig_category":"Ortopedia General",
    "sg:phone":"+34 938 18 17 49",
    "sg:postcode":"08720",
    "sg:province":"Barcelona",
    "wof:name":"Aparells Ortopedics Curto S. L.",
    "wof:placetype":"venue"
},
  "geometry": {"coordinates":[1.7041658163,41.3541488647],"type":"Point"}
}