{
  "type": "Feature",
  "properties": {
    "addr:full":"Calle de Salteras, 13 Sevilla Sevilla 41006",
    "addr:housenumber":"13",
    "addr:postcode":"41006",
    "addr:street":"Calle De Salteras",
    "iso:country":"ES",
    "sg:address":"Calle de Salteras, 13",
    "sg:city":"Sevilla",
    "sg:orig_category":"Mec\u00c1nico Del Autom\u00d3vil",
    "sg:phone":"+34 954 65 93 51",
    "sg:postcode":"41006",
    "sg:province":"Sevilla",
    "wof:name":"Talleres Junior S.l.",
    "wof:placetype":"venue"
},
  "geometry": {"coordinates":[-5.9516477585,37.3725547791],"type":"Point"}
}