{
  "type": "Feature",
  "properties": {
    "addr:full":"Carr Sant Pau, 129 Figueres Girona 17600",
    "addr:housenumber":"129",
    "addr:postcode":"17600",
    "addr:street":"Carr Sant Pau",
    "iso:country":"ES",
    "sg:address":"Carr Sant Pau, 129",
    "sg:city":"Figueres",
    "sg:orig_category":"Mec\u00c1nico Del Autom\u00d3vil",
    "sg:phone":"+34 972 50 16 79",
    "sg:postcode":"17600",
    "sg:province":"Girona",
    "wof:name":"Garaje Automecanic S.c.",
    "wof:placetype":"venue"
},
  "geometry": {"coordinates":[2.9632463455,42.2596893311],"type":"Point"}
}