{
  "type": "Feature",
  "properties": {
    "iso:country":"ES",
    "sg:address":"Calle de Torre De Abajo, 65",
    "sg:city":"Langreo",
    "sg:orig_category":"Animales (al Por Menor)",
    "sg:phone":"+34 985 67 64 39",
    "sg:postcode":"33900",
    "sg:province":"Asturias",
    "wof:name":"Bustelo Roda Jesus Manuel",
    "wof:placetype":"venue"
},
  "geometry": {"coordinates":[-5.6692090034,43.2883987427],"type":"Point"}
}