{
  "type": "Feature",
  "properties": {
    "iso:country":"ES",
    "sg:address":"Franco De Sena Cerdan, 1",
    "sg:city":"Torre-pacheco",
    "sg:orig_category":"Plomeros",
    "sg:phone":"+34 968 57 93 56",
    "sg:postcode":"30700",
    "sg:province":"Murcia",
    "wof:name":"Fontaneria Fabian Saura S.l",
    "wof:placetype":"venue"
},
  "geometry": {"coordinates":[-0.9551569819,37.7436637878],"type":"Point"}
}