{
  "type": "Feature",
  "properties": {
    "addr:full":"Calle de San Herculano, 6 Madrid Madrid 28022",
    "addr:housenumber":"6",
    "addr:postcode":"28022",
    "addr:street":"Calle De San Herculano",
    "iso:country":"ES",
    "sg:address":"Calle de San Herculano, 6",
    "sg:city":"Madrid",
    "sg:orig_category":"Asistencia Domiciliaria",
    "sg:phone":"+34 913 93 00 68",
    "sg:postcode":"28022",
    "sg:province":"Madrid",
    "wof:name":"Libercano S.l.",
    "wof:placetype":"venue"
},
  "geometry": {"coordinates":[-3.6107161045,40.4409065247],"type":"Point"}
}