{
  "type": "Feature",
  "properties": {
    "iso:country":"ES",
    "sg:address":"Calle de Isabel La Catolica, 8",
    "sg:city":"San Juan",
    "sg:orig_category":"Inmobiliaria (agencias)",
    "sg:phone":"+34 968 22 35 11",
    "sg:postcode":"30003",
    "sg:province":"Murcia",
    "wof:name":"Viviendas Y Locales S.l.",
    "wof:placetype":"venue"
},
  "geometry": {"coordinates":[-1.1249239445,37.9831848145],"type":"Point"}
}