{
  "type": "Feature",
  "properties": {
    "addr:full":"Calle de Arquitecto Rodriguez, 50 Valencia Valencia 46019",
    "addr:housenumber":"50",
    "addr:postcode":"46019",
    "addr:street":"Calle De Arquitecto Rodriguez",
    "iso:country":"ES",
    "sg:address":"Calle de Arquitecto Rodriguez, 50",
    "sg:city":"Valencia",
    "sg:orig_category":"Pintura Y Barniz (al Por Menor)",
    "sg:phone":"+34 963 66 46 36",
    "sg:postcode":"46019",
    "sg:province":"Valencia",
    "wof:name":"Castillo Martinez Elias",
    "wof:placetype":"venue"
},
  "geometry": {"coordinates":[-0.3681527078,39.4948654175],"type":"Point"}
}