{
  "type": "Feature",
  "properties": {
    "iso:country":"ES",
    "sg:address":"Carrer de Camelies, 19",
    "sg:city":"Barcelona",
    "sg:orig_category":"Mutuas De Seguros",
    "sg:phone":"+34 932 13 17 16",
    "sg:postcode":"08024",
    "sg:province":"Barcelona",
    "wof:name":"Mutualitat Evangelica De Previsio Social",
    "wof:placetype":"venue"
},
  "geometry": {"coordinates":[2.1593089104,41.4113197327],"type":"Point"}
}