{
  "type": "Feature",
  "properties": {
    "iso:country":"ES",
    "sg:address":"Lope De Isasti Plaza, 4",
    "sg:city":"Lezo",
    "sg:orig_category":"M\u00c1rmoles, Granitos Y Piedras Naturales",
    "sg:phone":"+34 943 52 38 22",
    "sg:postcode":"20100",
    "sg:province":"Guip\u00f9zcoa",
    "wof:name":"Gallardo Moreno Juan Francisco",
    "wof:placetype":"venue"
},
  "geometry": {"coordinates":[-1.893524766,43.3222885132],"type":"Point"}
}