{
  "type": "Feature",
  "properties": {
    "iso:country":"ES",
    "sg:address":"Calle de Monegros, 10",
    "sg:city":"Leganes",
    "sg:orig_category":"Poller\u00cda Y Caza (al Por Menor)",
    "sg:phone":"+34 916 88 47 26",
    "sg:postcode":"28915",
    "sg:province":"Madrid",
    "wof:name":"Ruiz Morejon Juan",
    "wof:placetype":"venue"
},
  "geometry": {"coordinates":[-3.7548029423,40.3364257812],"type":"Point"}
}