{
  "type": "Feature",
  "properties": {
    "addr:full":"Calle de Rafael Belderrain, 9 Langreo Asturias 33930",
    "addr:housenumber":"9",
    "addr:postcode":"33930",
    "addr:street":"Calle De Rafael Belderrain",
    "iso:country":"ES",
    "sg:address":"Calle de Rafael Belderrain, 9",
    "sg:city":"Langreo",
    "sg:orig_category":"Muebles, Minoristas",
    "sg:phone":"+34 985 69 06 67",
    "sg:postcode":"33930",
    "sg:province":"Asturias",
    "wof:name":"Garcia Vega Arsenio",
    "wof:placetype":"venue"
},
  "geometry": {"coordinates":[-5.7070870399,43.3195877075],"type":"Point"}
}