{
  "type": "Feature",
  "properties": {
    "iso:country":"ES",
    "sg:address":"Avda Espa\u00d1a, 19",
    "sg:city":"Linares",
    "sg:orig_category":"Muebles, Minoristas",
    "sg:phone":"+34 953 69 34 92",
    "sg:postcode":"23700",
    "sg:province":"Ja\u00e9n",
    "wof:name":"Muebles Rosa",
    "wof:placetype":"venue"
},
  "geometry": {"coordinates":[-3.6225390434,38.0869636536],"type":"Point"}
}