{
  "type": "Feature",
  "properties": {
    "iso:country":"ES",
    "sg:address":"Capelan-oca, 3",
    "sg:city":"Coristanco",
    "sg:orig_category":"Producci\u00d3n De Abonos Y De Fertilizantes",
    "sg:phone":"+34 981 73 30 04",
    "sg:postcode":"15147",
    "sg:province":"La Coru\u00f1a",
    "wof:name":"Naya Mato Manuel",
    "wof:placetype":"venue"
},
  "geometry": {"coordinates":[-8.7346086502,43.1884384155],"type":"Point"}
}