{
  "type": "Feature",
  "properties": {
    "addr:full":"Carrer de Joan Maragall, 55 Prat Llobregat Barcelona 08820",
    "addr:housenumber":"55",
    "addr:postcode":"08820",
    "addr:street":"Carrer De Joan Maragall;Llobregat",
    "iso:country":"ES",
    "sg:address":"Carrer de Joan Maragall, 55",
    "sg:city":"Prat Llobregat",
    "sg:orig_category":"Guarder\u00cdas",
    "sg:phone":"+34 933 70 13 51",
    "sg:postcode":"08820",
    "sg:province":"Barcelona",
    "wof:name":"Mestres Gonzalez Montserrat",
    "wof:placetype":"venue"
},
  "geometry": {"coordinates":[2.0980420113,41.3299827576],"type":"Point"}
}