{
  "type": "Feature",
  "properties": {
    "iso:country":"ES",
    "sg:address":"Pase Pago De La Perdiz (del), 4",
    "sg:city":"Berrocales Del Jarama",
    "sg:orig_category":"Suministros Para Exposiciones, Ferias, Salones",
    "sg:phone":"+34 916 77 88 74",
    "sg:postcode":"28861",
    "sg:province":"Madrid",
    "wof:name":"Troppo Uero S.l.",
    "wof:placetype":"venue"
},
  "geometry": {"coordinates":[-3.510406971,40.4735946655],"type":"Point"}
}