{
  "type": "Feature",
  "properties": {
    "iso:country":"ES",
    "sg:address":"Calle de Puente La Reina, 8",
    "sg:city":"Valladolid",
    "sg:orig_category":"Asociaciones, Organismos Culturales Y Socioeducativos",
    "sg:phone":"+34 983 22 60 33",
    "sg:postcode":"47011",
    "sg:province":"Valladolid",
    "wof:name":"Confederacion Regional De Jubilados Y Pensionistas De Castilla Y",
    "wof:placetype":"venue"
},
  "geometry": {"coordinates":[-4.7082967758,41.6519393921],"type":"Point"}
}