{
  "type": "Feature",
  "properties": {
    "iso:country":"ES",
    "sg:address":"Calle de Carlos Domingo, 10",
    "sg:city":"Madrid",
    "sg:orig_category":"Internados & Ense\u00d1anza Privada",
    "sg:phone":"+34 914 65 03 15",
    "sg:postcode":"28047",
    "sg:province":"Madrid",
    "wof:name":"Colegio Nebrija Rosales S. Coop. Ltda.",
    "wof:placetype":"venue"
},
  "geometry": {"coordinates":[-3.7445282936,40.390914917],"type":"Point"}
}