{
  "type": "Feature",
  "properties": {
    "iso:country":"ES",
    "sg:address":"Calle de Romancero, 10",
    "sg:city":"Burgos",
    "sg:orig_category":"Motocicletas (agentes, Concesionarios)",
    "sg:phone":"+34 947 27 90 89",
    "sg:postcode":"09002",
    "sg:province":"Burgos",
    "wof:name":"Citores Moral Cristina",
    "wof:placetype":"venue"
},
  "geometry": {"coordinates":[-3.6957368851,42.3342590332],"type":"Point"}
}