{
  "type": "Feature",
  "properties": {
    "addr:full":"Avda Concejal Alberto Jimenez-becerril, 22 Sevilla Sevilla 41009",
    "addr:housenumber":"22",
    "addr:postcode":"41009",
    "addr:street":"Avda Concejal Alberto Jimenez-Becerril",
    "iso:country":"ES",
    "sg:address":"Avda Concejal Alberto Jimenez-becerril, 22",
    "sg:city":"Sevilla",
    "sg:orig_category":"Cajas De Ahorro",
    "sg:phone":"+34 954 91 58 20",
    "sg:postcode":"41009",
    "sg:province":"Sevilla",
    "wof:name":"Caja De Ahorros De Valencia Castellon Y Alicante",
    "wof:placetype":"venue"
},
  "geometry": {"coordinates":[-5.9911842346,37.4094352722],"type":"Point"}
}