{
  "type": "Feature",
  "properties": {
    "iso:country":"ES",
    "sg:address":"Carrer de Marques De Bellet (del), 6",
    "sg:city":"Tortosa",
    "sg:orig_category":"Piscinas, Accesorios, Suministros (fabricaci\u00d3n, Al Por Mayor)",
    "sg:phone":"+34 977 44 23 64",
    "sg:postcode":"43500",
    "sg:province":"Tarragona",
    "wof:name":"Robres Gargallo Jose Miguel",
    "wof:placetype":"venue"
},
  "geometry": {"coordinates":[0.5208899975,40.8081893921],"type":"Point"}
}