{
  "type": "Feature",
  "properties": {
    "iso:country":"ES",
    "sg:address":"Calle de Moraza, 11",
    "sg:city":"Donostia-san Sebastian",
    "sg:orig_category":"Molduras, Junquillos, Listones Y Molduras Perforadas",
    "sg:phone":"+34 943 46 37 08",
    "sg:postcode":"20006",
    "sg:province":"Guip\u00f9zcoa",
    "wof:name":"Gonzalez Garcia Juliana",
    "wof:placetype":"venue"
},
  "geometry": {"coordinates":[-1.9812140465,43.3142204285],"type":"Point"}
}