{
  "type": "Feature",
  "properties": {
    "addr:full":"Calle de Lopez De Hoyos, 89 Madrid Madrid 28002",
    "addr:housenumber":"89",
    "addr:postcode":"madrid;28002",
    "addr:street":"Calle De Lopez De Hoyos",
    "iso:country":"ES",
    "sg:address":"Calle de Lopez De Hoyos, 89",
    "sg:city":"Madrid",
    "sg:orig_category":"Organismos Y Centros De Vacaciones Y Esparcimiento Para Ni\u00d1os Y Adolescentes",
    "sg:phone":"+34 914 15 11 44",
    "sg:postcode":"28002",
    "sg:province":"Madrid",
    "wof:name":"Droinsa S.l.",
    "wof:placetype":"venue"
},
  "geometry": {"coordinates":[-3.6734859943,40.4447288513],"type":"Point"}
}