{
  "type": "Feature",
  "properties": {
    "addr:full":"Av Pau (de La), 196 Deltebre Tarragona 43580",
    "addr:housenumber":"196",
    "addr:postcode":"43580",
    "addr:street":"Av Pau De La",
    "iso:country":"ES",
    "sg:address":"Av Pau (de La), 196",
    "sg:city":"Deltebre",
    "sg:classifiers":[
        {
            "category":"Taxi",
            "type":"Transportation"
        }
    ],
    "sg:phone":"+34 977 48 96 54",
    "sg:postcode":"43580",
    "sg:province":"Tarragona",
    "wof:name":"Tomas Noche Alvaro",
    "wof:placetype":"venue"
},
  "geometry": {"coordinates":[0.7073699832,40.7249298096],"type":"Point"}
}