{
  "type": "Feature",
  "properties": {
    "iso:country":"ES",
    "sg:address":"Calle de Chisperos, 16",
    "sg:city":"Madrid",
    "sg:orig_category":"Promotores Constructores",
    "sg:phone":"+34 914 63 46 99",
    "sg:postcode":"28047",
    "sg:province":"Madrid",
    "wof:name":"Promociones Casasana S.l.",
    "wof:placetype":"venue"
},
  "geometry": {"coordinates":[-3.7315516472,40.404209137],"type":"Point"}
}