{
  "type": "Feature",
  "properties": {
    "iso:country":"ES",
    "sg:address":"Carrer de Antoni De Bofarull, 8",
    "sg:city":"Reus",
    "sg:orig_category":"Centros P\u00dablicos De Formaci\u00d3n Profesional Y T\u00c9cnica",
    "sg:phone":"+34 977 31 79 53",
    "sg:postcode":"43202",
    "sg:province":"Tarragona",
    "wof:name":"Colegio Oficial De Medicos De La Provincia De Tarragona",
    "wof:placetype":"venue"
},
  "geometry": {"coordinates":[1.1029640436,41.150177002],"type":"Point"}
}