{
  "type": "Feature",
  "properties": {
    "addr:full":"Calle de Duque De Alba, 2 Avila \u00c1vila 05001",
    "addr:housenumber":"2",
    "addr:postcode":"05001",
    "addr:street":"Calle De Duque De Alba;A\u0301Vila",
    "iso:country":"ES",
    "sg:address":"Calle de Duque De Alba, 2",
    "sg:city":"Avila",
    "sg:orig_category":"Cajas Para Embalar",
    "sg:phone":"+34 920 25 67 94",
    "sg:postcode":"05001",
    "sg:province":"\u00c1vila",
    "sg:website":"www.ruraldia.com",
    "wof:name":"Caja Rural Del Duero",
    "wof:placetype":"venue"
},
  "geometry": {"coordinates":[-4.6940879822,40.6546821594],"type":"Point"}
}