{
  "type": "Feature",
  "properties": {
    "iso:country":"ES",
    "sg:address":"Bo. Nuevo, 1",
    "sg:city":"Villaflor",
    "sg:orig_category":"Cerrajer\u00cda, Ferrallista",
    "sg:phone":"+34 920 24 03 37",
    "sg:postcode":"05340",
    "sg:province":"\u00c1vila",
    "wof:name":"Resina Saez Florencio",
    "wof:placetype":"venue"
},
  "geometry": {"coordinates":[-4.8737778664,40.7586708069],"type":"Point"}
}