{
  "type": "Feature",
  "properties": {
    "iso:country":"ES",
    "sg:address":"Cmno Puesto Pallares, S/n",
    "sg:city":"Mojonera",
    "sg:orig_category":"Molduras, Junquillos, Listones Y Molduras Perforadas",
    "sg:phone":"+34 950 33 01 18",
    "sg:postcode":"04745",
    "sg:province":"Almer\u00eda",
    "wof:name":"Tarifa Romera Juan",
    "wof:placetype":"venue"
},
  "geometry": {"coordinates":[-2.6811990738,36.7550849915],"type":"Point"}
}