{
  "type": "Feature",
  "properties": {
    "iso:country":"ES",
    "sg:address":"Avda Salvador Allende, 7",
    "sg:city":"Fortuna",
    "sg:orig_category":"Muebles, Minoristas",
    "sg:phone":"+34 968 68 62 01",
    "sg:postcode":"30620",
    "sg:province":"Murcia",
    "wof:name":"Hernandez Navarro Joaquin Jesus",
    "wof:placetype":"venue"
},
  "geometry": {"coordinates":[-1.1244000196,38.177947998],"type":"Point"}
}