{
  "type": "Feature",
  "properties": {
    "addr:full":"Carrer de Sant Cugat, 72 Mataro Barcelona 08302",
    "addr:housenumber":"72",
    "addr:postcode":"08302",
    "addr:street":"Carrer De Sant Cugat",
    "iso:country":"ES",
    "sg:address":"Carrer de Sant Cugat, 72",
    "sg:city":"Mataro",
    "sg:orig_category":"Empresas De Carpinter\u00cda",
    "sg:phone":"+34 937 98 92 09",
    "sg:postcode":"08302",
    "sg:province":"Barcelona",
    "wof:name":"Notario Manche\u00f1o Manuel",
    "wof:placetype":"venue"
},
  "geometry": {"coordinates":[2.4382560253,41.5352134705],"type":"Point"}
}