{
  "type": "Feature",
  "properties": {
    "iso:country":"ES",
    "sg:address":"Pl Universitat, 2",
    "sg:city":"Barcelona",
    "sg:orig_category":"Internados & Ense\u00d1anza Privada",
    "sg:phone":"+34 933 23 69 31",
    "sg:postcode":"08007",
    "sg:province":"Barcelona",
    "wof:name":"Franciscanas Misioneras Inmaculada Concepcion",
    "wof:placetype":"venue"
},
  "geometry": {"coordinates":[2.1653530598,41.3860855103],"type":"Point"}
}