{
  "type": "Feature",
  "properties": {
    "iso:country":"ES",
    "sg:address":"Calle de Guzman El Bueno, 4",
    "sg:city":"Madrid",
    "sg:orig_category":"Pintura Y Barniz (al Por Menor)",
    "sg:phone":"+34 915 47 11 46",
    "sg:postcode":"28015",
    "sg:province":"Madrid",
    "sg:website":"www.dimactarimasflotantes.com",
    "wof:name":"Dimac S.l.",
    "wof:placetype":"venue"
},
  "geometry": {"coordinates":[-3.7133350372,40.4307289124],"type":"Point"}
}