{
  "type": "Feature",
  "properties": {
    "iso:country":"ES",
    "sg:address":"Pol Ind Campi\u00f1a, 2",
    "sg:city":"Ecija",
    "sg:orig_category":"Fabricaci\u00d3n De Muebles De Cocina",
    "sg:phone":"+34 955 90 53 07",
    "sg:postcode":"41400",
    "sg:province":"Sevilla",
    "wof:name":"Grucas De Ecija S.l.l.",
    "wof:placetype":"venue"
},
  "geometry": {"coordinates":[-5.0782690048,37.5395584106],"type":"Point"}
}