{
  "type": "Feature",
  "properties": {
    "addr:full":"Calle de Selva, 8 Valladolid Valladolid 47010",
    "addr:housenumber":"8",
    "addr:postcode":"47010",
    "addr:street":"Calle De Selva",
    "iso:country":"ES",
    "sg:address":"Calle de Selva, 8",
    "sg:city":"Valladolid",
    "sg:orig_category":"M\u00c1rmoles, Granitos Y Piedras Naturales",
    "sg:phone":"+34 983 25 74 08",
    "sg:postcode":"47010",
    "sg:province":"Valladolid",
    "wof:name":"Fuentes De La Serna Andres",
    "wof:placetype":"venue"
},
  "geometry": {"coordinates":[-4.7106909752,41.6672439575],"type":"Point"}
}