{
  "type": "Feature",
  "properties": {
    "iso:country":"ES",
    "sg:address":"Calle de Mayor, 60",
    "sg:city":"Briviesca",
    "sg:orig_category":"Electricidad: Instaladores",
    "sg:phone":"+34 947 59 06 30",
    "sg:postcode":"09240",
    "sg:province":"Burgos",
    "wof:name":"San Pedro Gutierrez Luis Ramon",
    "wof:placetype":"venue"
},
  "geometry": {"coordinates":[-3.3244590759,42.5477104187],"type":"Point"}
}