{
  "type": "Feature",
  "properties": {
    "addr:full":"Calle de Vicente Aleixandre, 36 Vitoria-gasteiz \u00c1lava 01003",
    "addr:housenumber":"36",
    "addr:postcode":"01003",
    "addr:street":"Calle De Vicente Aleixandre",
    "iso:country":"ES",
    "sg:address":"Calle de Vicente Aleixandre, 36",
    "sg:city":"Vitoria-gasteiz",
    "sg:orig_category":"Droguer\u00cdas (al Por Menor)",
    "sg:phone":"+34 945 25 63 69",
    "sg:postcode":"01003",
    "sg:province":"\u00c1lava",
    "wof:name":"Hernaez Alvarez Manuel",
    "wof:placetype":"venue"
},
  "geometry": {"coordinates":[-2.6566929817,42.8424453735],"type":"Point"}
}