{
  "type": "Feature",
  "properties": {
    "addr:full":"Gta Luis Braille, 6 Burgos Burgos 09007",
    "addr:housenumber":"6",
    "addr:postcode":"09007",
    "addr:street":"Gta Luis Braille",
    "iso:country":"ES",
    "sg:address":"Gta Luis Braille, 6",
    "sg:city":"Burgos",
    "sg:orig_category":"Charcuter\u00cdas (al Por Mayor)",
    "sg:phone":"+34 947 48 78 08",
    "sg:postcode":"09007",
    "sg:province":"Burgos",
    "wof:name":"Embutidos Rioseras S.l.",
    "wof:placetype":"venue"
},
  "geometry": {"coordinates":[-3.6643509865,42.3511924744],"type":"Point"}
}