{
  "type": "Feature",
  "properties": {
    "iso:country":"ES",
    "sg:address":"Calle de Benicarlo, 25",
    "sg:city":"Valencia",
    "sg:orig_category":"Mercer\u00cda, Lencer\u00cda (al Por Menor)",
    "sg:phone":"+34 963 60 69 47",
    "sg:postcode":"46020",
    "sg:province":"Valencia",
    "wof:name":"Palau Valle Maria",
    "wof:placetype":"venue"
},
  "geometry": {"coordinates":[-0.3655500114,39.4868965149],"type":"Point"}
}