{
  "type": "Feature",
  "properties": {
    "iso:country":"ES",
    "sg:address":"Ctra. Serranillos, Km. 0012,2",
    "sg:city":"Esquivias",
    "sg:orig_category":"Fabrica De Charcuter\u00cda",
    "sg:phone":"+34 925 54 65 66",
    "sg:postcode":"45221",
    "sg:province":"Toledo",
    "sg:website":"www.carnicaschamberi.com",
    "wof:name":"Carnicas Chamberi S.l.",
    "wof:placetype":"venue"
},
  "geometry": {"coordinates":[-3.7646589279,40.1034851074],"type":"Point"}
}