{
  "type": "Feature",
  "properties": {
    "addr:full":"Plaz Aurora (de La), 5 Montilla C\u00f3rdoba 14550",
    "addr:housenumber":"5",
    "addr:postcode":"14550",
    "addr:street":"Aurora De La;Co\u0301Rdoba",
    "iso:country":"ES",
    "sg:address":"Plaz Aurora (de La), 5",
    "sg:city":"Montilla",
    "sg:orig_category":"Electricidad Veh\u00cdculo",
    "sg:phone":"+34 957 65 53 14",
    "sg:postcode":"14550",
    "sg:province":"C\u00f3rdoba",
    "wof:name":"Martinez Repiso Rafael",
    "wof:placetype":"venue"
},
  "geometry": {"coordinates":[-4.6404590607,37.58177948],"type":"Point"}
}