{
  "type": "Feature",
  "properties": {
    "iso:country":"ES",
    "sg:address":"Calle de Real, 43",
    "sg:city":"Torredonjimeno",
    "sg:orig_category":"Marroquiner\u00cda (confecci\u00d3n)",
    "sg:phone":"+34 953 34 00 70",
    "sg:postcode":"23650",
    "sg:province":"Ja\u00e9n",
    "wof:name":"Mellado Jurado Monica",
    "wof:placetype":"venue"
},
  "geometry": {"coordinates":[-3.9549670219,37.7630271912],"type":"Point"}
}