{
  "type": "Feature",
  "properties": {
    "iso:country":"ES",
    "sg:address":"Calle de Nueva, 57",
    "sg:city":"Cabezas S. Juan",
    "sg:orig_category":"Alquiler De V\u00cddeo",
    "sg:phone":"+34 955 87 03 61",
    "sg:postcode":"41730",
    "sg:province":"Sevilla",
    "wof:name":"Todo Romero S.l.",
    "wof:placetype":"venue"
},
  "geometry": {"coordinates":[-5.938270092,36.9847106934],"type":"Point"}
}