{
  "type": "Feature",
  "properties": {
    "addr:full":"Ctra Plasencia, S/n Jarandilla Vera C\u00e1ceres 10450",
    "addr:housenumber":"s / n",
    "addr:postcode":"10450",
    "addr:street":"Ctra Plasencia;Ca\u0301Ceres",
    "iso:country":"ES",
    "sg:address":"Ctra Plasencia, S/n",
    "sg:city":"Jarandilla Vera",
    "sg:orig_category":"Distribuci\u00d3n De Petr\u00d3leo Y Derivados",
    "sg:phone":"+34 927 56 01 54",
    "sg:postcode":"10450",
    "sg:province":"C\u00e1ceres",
    "sg:website":"www.cepsa.es",
    "wof:name":"Monforte Y Nu\u00f1ez S.l.",
    "wof:placetype":"venue"
},
  "geometry": {"coordinates":[-5.659965992,40.1283340454],"type":"Point"}
}