{
  "type": "Feature",
  "properties": {
    "addr:full":"Av Pas D'arro, 22 Vielha Lleida 25530",
    "addr:housenumber":"22",
    "addr:postcode":"25530",
    "addr:street":"Av Pas D'Arro",
    "iso:country":"ES",
    "sg:address":"Av Pas D'arro, 22",
    "sg:city":"Vielha",
    "sg:orig_category":"Peluqueros: De Se\u00d1oras",
    "sg:phone":"+34 973 64 15 38",
    "sg:postcode":"25530",
    "sg:province":"Lleida",
    "wof:name":"Cabau Rimont Montserrat",
    "wof:placetype":"venue"
},
  "geometry": {"coordinates":[0.7991030216,42.6999740601],"type":"Point"}
}