{
  "type": "Feature",
  "properties": {
    "addr:full":"Monte, 161 Mos Pontevedra 36418",
    "addr:housenumber":"161",
    "addr:postcode":"36418",
    "addr:street":"Monte",
    "iso:country":"ES",
    "sg:address":"Monte, 161",
    "sg:city":"Mos",
    "sg:orig_category":"Masajistas Kinesiterapeutas",
    "sg:phone":"+34 986 33 57 75",
    "sg:postcode":"36418",
    "sg:province":"Pontevedra",
    "wof:name":"Varela Gonzalez Manuel",
    "wof:placetype":"venue"
},
  "geometry": {"coordinates":[-8.6259479523,42.1763916016],"type":"Point"}
}