{
  "type": "Feature",
  "properties": {
    "addr:full":"Avda Portugal, 68 Talavera Reina Toledo 45600",
    "addr:housenumber":"68",
    "addr:postcode":"45600",
    "addr:street":"Avda Portugal",
    "iso:country":"ES",
    "sg:address":"Avda Portugal, 68",
    "sg:city":"Talavera Reina",
    "sg:orig_category":"Agentes, Concesionarios Y Sucursales De Veh\u00cdculos",
    "sg:phone":"+34 925 82 38 39",
    "sg:postcode":"45600",
    "sg:province":"Toledo",
    "wof:name":"Jesus Mendez Motor S.a.",
    "wof:placetype":"venue"
},
  "geometry": {"coordinates":[-4.8485579491,39.958026886],"type":"Point"}
}