{
  "type": "Feature",
  "properties": {
    "iso:country":"ES",
    "sg:address":"Carrer de Ferran Puig, 84",
    "sg:city":"Prat Llobregat",
    "sg:orig_category":"Promotores Constructores",
    "sg:phone":"+34 933 70 29 01",
    "sg:postcode":"08820",
    "sg:province":"Barcelona",
    "sg:website":"www.cfeu.com",
    "wof:name":"Grupo Inversor Del Prat S.l.",
    "wof:placetype":"venue"
},
  "geometry": {"coordinates":[2.0945360661,41.3279953003],"type":"Point"}
}