{
  "type": "Feature",
  "properties": {
    "addr:full":"La Vegona, S/n La Robla Le\u00f3n 24640",
    "addr:housenumber":"/ n",
    "addr:postcode":"24640",
    "addr:street":"Vegona S",
    "iso:country":"ES",
    "sg:address":"La Vegona, S/n",
    "sg:city":"La Robla",
    "sg:orig_category":"Transportes Por V\u00cdas Navegables",
    "sg:phone":"+34 987 57 09 34",
    "sg:postcode":"24640",
    "sg:province":"Le\u00f3n",
    "wof:name":"Garcia Gutierrez Angel",
    "wof:placetype":"venue"
},
  "geometry": {"coordinates":[-5.6282129288,42.8004798889],"type":"Point"}
}