{
  "type": "Feature",
  "properties": {
    "addr:full":"Calle de Reyes Catolicos, 6 Avila \u00c1vila 05001",
    "addr:housenumber":"6",
    "addr:postcode":"05001",
    "addr:street":"Calle De Reyes Catolicos;A\u0301Vila",
    "iso:country":"ES",
    "sg:address":"Calle de Reyes Catolicos, 6",
    "sg:city":"Avila",
    "sg:orig_category":"Arquitectos",
    "sg:phone":"+34 920 22 20 04",
    "sg:postcode":"05001",
    "sg:province":"\u00c1vila",
    "wof:name":"Sanchez Caro Antonio",
    "wof:placetype":"venue"
},
  "geometry": {"coordinates":[-4.6996679306,40.6559066772],"type":"Point"}
}