{
  "type": "Feature",
  "properties": {
    "addr:full":"Plaz Ayuntamiento, S/n Linares Ja\u00e9n 23700",
    "addr:housenumber":"/ n",
    "addr:postcode":"23700",
    "addr:street":"S;Jae\u0301N",
    "iso:country":"ES",
    "sg:address":"Plaz Ayuntamiento, S/n",
    "sg:city":"Linares",
    "sg:orig_category":"Ense\u00d1anza, Formaci\u00d3n Profesional: Aprendizaje",
    "sg:phone":"+34 953 64 91 00",
    "sg:postcode":"23700",
    "sg:province":"Ja\u00e9n",
    "sg:website":"www.ayuntamientodelinares.org",
    "wof:name":"Ayuntamiento De Linares",
    "wof:placetype":"venue"
},
  "geometry": {"coordinates":[-3.6420478821,38.1125907898],"type":"Point"}
}