{
  "type": "Feature",
  "properties": {
    "addr:full":"Calle de Calvo Sotelo, 16 Santander Cantabria 39002",
    "addr:housenumber":"16",
    "addr:postcode":"39002",
    "addr:street":"Calle De Calvo Sotelo",
    "iso:country":"ES",
    "sg:address":"Calle de Calvo Sotelo, 16",
    "sg:city":"Santander",
    "sg:orig_category":"Cl\u00cdnicas Dentales",
    "sg:phone":"+34 942 31 36 53",
    "sg:postcode":"39002",
    "sg:province":"Cantabria",
    "wof:name":"Merino Rodrigo Ramon",
    "wof:placetype":"venue"
},
  "geometry": {"coordinates":[-3.8076548576,43.4614486694],"type":"Point"}
}