{
  "type": "Feature",
  "properties": {
    "addr:full":"Pl Mercat (del), 1 S. Carles Rapita Tarragona 43540",
    "addr:postcode":"43540",
    "addr:street":"Pl;S. Carles Rapita",
    "iso:country":"ES",
    "sg:address":"Pl Mercat (del), 1",
    "sg:city":"S. Carles Rapita",
    "sg:orig_category":"Cajas De Ahorro",
    "sg:phone":"+34 977 74 14 05",
    "sg:postcode":"43540",
    "sg:province":"Tarragona",
    "wof:name":"Caixa D'estalvis De Catalunya",
    "wof:placetype":"venue"
},
  "geometry": {"coordinates":[0.592598021,40.6186294556],"type":"Point"}
}