{
  "type": "Feature",
  "properties": {
    "iso:country":"ES",
    "sg:address":"Carrer de Barcelona, 183",
    "sg:city":"Sant Vicen\u00c7 Dels Horts",
    "sg:orig_category":"Electrodom\u00c9sticos (al Por Menor)",
    "sg:phone":"+34 936 76 96 75",
    "sg:postcode":"08620",
    "sg:province":"Barcelona",
    "wof:name":"Creixell Mitjans Josep",
    "wof:placetype":"venue"
},
  "geometry": {"coordinates":[2.0083079338,41.3977546692],"type":"Point"}
}