{
  "type": "Feature",
  "properties": {
    "addr:full":"Av. Generalisimo, 35 Alceda Cantabria 39680",
    "addr:housenumber":"35",
    "addr:postcode":"39680",
    "addr:street":"Av. Generalisimo",
    "iso:country":"ES",
    "sg:address":"Av. Generalisimo, 35",
    "sg:city":"Alceda",
    "sg:orig_category":"Carnicer\u00cdas, Carnicer\u00cdas",
    "sg:phone":"+34 942 59 40 26",
    "sg:postcode":"39680",
    "sg:province":"Cantabria",
    "wof:name":"Magaldi Gonzalez Casimiro",
    "wof:placetype":"venue"
},
  "geometry": {"coordinates":[-3.9219191074,43.1962852478],"type":"Point"}
}