{
  "type": "Feature",
  "properties": {
    "addr:full":"Avda Luis De Los Reyes, 33 Bullas Murcia 30180",
    "addr:housenumber":"33",
    "addr:postcode":"30180",
    "addr:street":"Avda Luis De Los Reyes",
    "iso:country":"ES",
    "sg:address":"Avda Luis De Los Reyes, 33",
    "sg:city":"Bullas",
    "sg:orig_category":"Agentes Generales De Seguros",
    "sg:phone":"+34 968 65 25 58",
    "sg:postcode":"30180",
    "sg:province":"Murcia",
    "wof:name":"Gomez Oliver Jose",
    "wof:placetype":"venue"
},
  "geometry": {"coordinates":[-1.6630699635,38.0464515686],"type":"Point"}
}