{
  "type": "Feature",
  "properties": {
    "addr:full":"Calle de Maceta (la), 10 Rambla C\u00f3rdoba 14540",
    "addr:housenumber":"10",
    "addr:postcode":"14540",
    "addr:street":"Calle De Maceta La;Co\u0301Rdoba",
    "iso:country":"ES",
    "sg:address":"Calle de Maceta (la), 10",
    "sg:city":"Rambla",
    "sg:orig_category":"Panader\u00cdas, Panader\u00cdas",
    "sg:phone":"+34 957 68 24 53",
    "sg:postcode":"14540",
    "sg:province":"C\u00f3rdoba",
    "wof:name":"Panificadora Los Alfares",
    "wof:placetype":"venue"
},
  "geometry": {"coordinates":[-4.7272529602,37.6122093201],"type":"Point"}
}