{
  "type": "Feature",
  "properties": {
    "addr:full":"Calle de Buenavista, 1 Villanueva De Los Castillejos Huelva 21540",
    "addr:housenumber":"1",
    "addr:postcode":"21540",
    "addr:street":"Calle De Buenavista",
    "iso:country":"ES",
    "sg:address":"Calle de Buenavista, 1",
    "sg:city":"Villanueva De Los Castillejos",
    "sg:orig_category":"Supermercados Y Hipermercados",
    "sg:phone":"+34 959 38 51 29",
    "sg:postcode":"21540",
    "sg:province":"Huelva",
    "wof:name":"Supermercados Hermanos Diaz S.l.",
    "wof:placetype":"venue"
},
  "geometry": {"coordinates":[-7.2696089745,37.4995040894],"type":"Point"}
}