{
  "type": "Feature",
  "properties": {
    "addr:full":"Ptge Princep De Viana, 6 Lleida Lleida 25008",
    "addr:housenumber":"6",
    "addr:postcode":"25008",
    "addr:street":"Ptge Princep De Viana",
    "iso:country":"ES",
    "sg:address":"Ptge Princep De Viana, 6",
    "sg:city":"Lleida",
    "sg:orig_category":"Chapa Y Pintura Veh\u00cdculos",
    "sg:phone":"+34 973 24 16 29",
    "sg:postcode":"25008",
    "sg:province":"Lleida",
    "wof:name":"Salvador Ropero Carlos",
    "wof:placetype":"venue"
},
  "geometry": {"coordinates":[0.6234369874,41.624370575],"type":"Point"}
}