{
  "type": "Feature",
  "properties": {
    "iso:country":"ES",
    "sg:address":"Jandilla, S/n",
    "sg:city":"Jandilla",
    "sg:orig_category":"Agricultores, Agricultores",
    "sg:phone":"+34 956 23 26 85",
    "sg:postcode":"11158",
    "sg:province":"C\u00e1diz",
    "wof:name":"Matilde Solis Atienza E Hijos Comunidad De Bienes",
    "wof:placetype":"venue"
},
  "geometry": {"coordinates":[-5.9772939682,36.3589744568],"type":"Point"}
}