{
  "type": "Feature",
  "properties": {
    "iso:country":"ES",
    "sg:address":"Trva Silgar, 26",
    "sg:city":"Sanxenxo",
    "sg:orig_category":"Bisuter\u00cda, Joyer\u00cda, Relojer\u00cda (al Por Menor)",
    "sg:phone":"+34 986 69 13 67",
    "sg:postcode":"36960",
    "sg:province":"Pontevedra",
    "wof:name":"Cervi\u00f1o Vazquez Lidia",
    "wof:placetype":"venue"
},
  "geometry": {"coordinates":[-8.8059329987,42.4015274048],"type":"Point"}
}