{
  "type": "Feature",
  "properties": {
    "iso:country":"ES",
    "sg:address":"Molinos, 1",
    "sg:city":"Baza",
    "sg:orig_category":"Centros Empresariales",
    "sg:phone":"+34 958 70 32 04",
    "sg:postcode":"18800",
    "sg:province":"Granada",
    "wof:name":"Martinez Magdaleno Antonia",
    "wof:placetype":"venue"
},
  "geometry": {"coordinates":[-2.7706050873,37.4726676941],"type":"Point"}
}