{
  "type": "Feature",
  "properties": {
    "iso:country":"ES",
    "sg:address":"Ctra General Adanero-gijon, S/n",
    "sg:city":"Becilla Valderaduey",
    "sg:orig_category":"Producci\u00d3n, Comercio De Cereales",
    "sg:phone":"+34 983 74 60 64",
    "sg:postcode":"47670",
    "sg:province":"Valladolid",
    "wof:name":"Cooperativa Regional De Comercializacion De Productos Agrarios",
    "wof:placetype":"venue"
},
  "geometry": {"coordinates":[-5.3267540932,42.0767936707],"type":"Point"}
}