{
  "type": "Feature",
  "properties": {
    "addr:full":"Carr Doctor Robert, 1 Santa Coloma De Farners Girona 17430",
    "addr:housenumber":"1",
    "addr:postcode":"17430",
    "addr:street":"Carr Doctor Robert",
    "iso:country":"ES",
    "sg:address":"Carr Doctor Robert, 1",
    "sg:city":"Santa Coloma De Farners",
    "sg:orig_category":"Agencias Y Agentes Comerciales, Representantes",
    "sg:phone":"+34 972 84 34 43",
    "sg:postcode":"17430",
    "sg:province":"Girona",
    "wof:name":"Bueno Pombero Sergi",
    "wof:placetype":"venue"
},
  "geometry": {"coordinates":[2.6624639034,41.8656349182],"type":"Point"}
}