{
  "type": "Feature",
  "properties": {
    "iso:country":"ES",
    "sg:address":"Avda Raza (la), S/n",
    "sg:city":"Sevilla",
    "sg:orig_category":"Cooperativas Agr\u00cdcolas",
    "sg:phone":"+34 954 62 32 01",
    "sg:postcode":"41012",
    "sg:province":"Sevilla",
    "wof:name":"Agencia Estatal De Administracion Tributaria",
    "wof:placetype":"venue"
},
  "geometry": {"coordinates":[-5.989836216,37.3565864563],"type":"Point"}
}