{
  "type": "Feature",
  "properties": {
    "iso:country":"ES",
    "sg:address":"Av Vila De Madrid, S/n",
    "sg:city":"Blanes",
    "sg:orig_category":"Art\u00cdculos De Regalo (al Por Menor)",
    "sg:phone":"+34 972 35 14 83",
    "sg:postcode":"17300",
    "sg:province":"Girona",
    "wof:name":"Mu\u00f1oz Malagarriga Juan",
    "wof:placetype":"venue"
},
  "geometry": {"coordinates":[2.7809998989,41.6619491577],"type":"Point"}
}