{
  "type": "Feature",
  "properties": {
    "iso:country":"ES",
    "sg:address":"Disseminat, S/n",
    "sg:city":"Gualba",
    "sg:orig_category":"Alfarer\u00cda",
    "sg:phone":"+34 938 47 22 33",
    "sg:postcode":"08474",
    "sg:province":"Barcelona",
    "wof:name":"Garriga Corts Enric",
    "wof:placetype":"venue"
},
  "geometry": {"coordinates":[2.5234498978,41.7172317505],"type":"Point"}
}