{
  "type": "Feature",
  "properties": {
    "addr:full":"Carrer de Girona, 161 Barcelona Barcelona 08037",
    "addr:housenumber":"161",
    "addr:postcode":"08037",
    "addr:street":"Carrer De Girona",
    "iso:country":"ES",
    "sg:address":"Carrer de Girona, 161",
    "sg:city":"Barcelona",
    "sg:orig_category":"Arquitectos",
    "sg:phone":"+34 932 07 43 85",
    "sg:postcode":"08037",
    "sg:province":"Barcelona",
    "wof:name":"Arnal Bigas Felix",
    "wof:placetype":"venue"
},
  "geometry": {"coordinates":[2.1654508114,41.3990898132],"type":"Point"}
}