{
  "type": "Feature",
  "properties": {
    "addr:full":"Calle de Cervantes, 22 Madrid Madrid 28014",
    "addr:housenumber":"22",
    "addr:postcode":"madrid;28014",
    "addr:street":"Calle De Cervantes",
    "iso:country":"ES",
    "sg:address":"Calle de Cervantes, 22",
    "sg:city":"Madrid",
    "sg:orig_category":"Agentes Generales De Seguros",
    "sg:phone":"+34 914 29 55 00",
    "sg:postcode":"28014",
    "sg:province":"Madrid",
    "wof:name":"Agencia General De Seguros Abc S.a.",
    "wof:placetype":"venue"
},
  "geometry": {"coordinates":[-3.6973104477,40.4143066406],"type":"Point"}
}