{
  "type": "Feature",
  "properties": {
    "addr:full":"Convento, 31 S. Martin Don Burgos 09212",
    "addr:housenumber":"31",
    "addr:postcode":"09212",
    "addr:street":"Convento;S. Martin Don Burgos",
    "iso:country":"ES",
    "sg:address":"Convento, 31",
    "sg:city":"S. Martin Don",
    "sg:orig_category":"Iglesia Cat\u00d3lica",
    "sg:phone":"+34 947 35 83 08",
    "sg:postcode":"09212",
    "sg:province":"Burgos",
    "wof:name":"Parroquia De San Martin",
    "wof:placetype":"venue"
},
  "geometry": {"coordinates":[-3.2203290462,42.7785606384],"type":"Point"}
}