{
  "type": "Feature",
  "properties": {
    "iso:country":"ES",
    "sg:address":"Calle de Aureliano Galarza, 3",
    "sg:city":"Mungia",
    "sg:orig_category":"Tintorer\u00cdas, Limpieza En Seco",
    "sg:phone":"+34 946 74 34 68",
    "sg:postcode":"48100",
    "sg:province":"Vizcaya",
    "wof:name":"Aitziber Olazar De La Concepcion",
    "wof:placetype":"venue"
},
  "geometry": {"coordinates":[-2.8460652828,43.3553733826],"type":"Point"}
}