{
  "type": "Feature",
  "properties": {
    "addr:full":"C/ Santiago, 2 Cerdanyola Valles Barcelona 08290",
    "addr:housenumber":"2",
    "addr:postcode":"08290",
    "addr:street":"C / Santiago;Valles Barcelona",
    "iso:country":"ES",
    "sg:address":"C/ Santiago, 2",
    "sg:city":"Cerdanyola Valles",
    "sg:orig_category":"Ropa Para Se\u00d1oras (al Por Menor)",
    "sg:phone":"+34 936 91 43 43",
    "sg:postcode":"08290",
    "sg:province":"Barcelona",
    "wof:name":"Falces Teixell Luisa",
    "wof:placetype":"venue"
},
  "geometry": {"coordinates":[2.1470150948,41.4924812317],"type":"Point"}
}