{
  "type": "Feature",
  "properties": {
    "iso:country":"ES",
    "sg:address":"Plaz Santa Maria, S/n",
    "sg:city":"Valencia De Don Juan",
    "sg:orig_category":"Carnicer\u00cdas, Carnicer\u00cdas",
    "sg:phone":"+34 987 75 09 12",
    "sg:postcode":"24200",
    "sg:province":"Le\u00f3n",
    "wof:name":"Gallego De Mata Aniano",
    "wof:placetype":"venue"
},
  "geometry": {"coordinates":[-5.5206189156,42.2921638489],"type":"Point"}
}