{
  "type": "Feature",
  "properties": {
    "addr:full":"Calle de Sarasate, 38 Zaragoza Zaragoza 50010",
    "addr:housenumber":"38",
    "addr:postcode":"50010",
    "addr:street":"Calle De Sarasate",
    "iso:country":"ES",
    "sg:address":"Calle de Sarasate, 38",
    "sg:city":"Zaragoza",
    "sg:orig_category":"Cristaler\u00cdas",
    "sg:phone":"+34 976 34 00 92",
    "sg:postcode":"50010",
    "sg:province":"Zaragoza",
    "wof:name":"Euroglass S.l.",
    "wof:placetype":"venue"
},
  "geometry": {"coordinates":[-0.9007179737,41.6526870728],"type":"Point"}
}