{
  "type": "Feature",
  "properties": {
    "iso:country":"ES",
    "sg:address":"Calle de Virgen Del Amparo, 6",
    "sg:city":"Marbella",
    "sg:orig_category":"Ebanister\u00cda",
    "sg:phone":"+34 952 86 62 31",
    "sg:postcode":"29600",
    "sg:province":"M\u00e1laga",
    "wof:name":"Marqueteria Dominguez Y Parra S.l.",
    "wof:placetype":"venue"
},
  "geometry": {"coordinates":[-4.8817520142,36.5109825134],"type":"Point"}
}