{
  "type": "Feature",
  "properties": {
    "addr:full":"Calle de Pedroche, 51 Adamuz C\u00f3rdoba 14430",
    "addr:housenumber":"51",
    "addr:postcode":"14430",
    "addr:street":"Calle De Pedroche",
    "iso:country":"ES",
    "sg:address":"Calle de Pedroche, 51",
    "sg:city":"Adamuz",
    "sg:orig_category":"Alimentaci\u00d3n General (al Por Menor)",
    "sg:phone":"+34 957 16 60 53",
    "sg:postcode":"14430",
    "sg:province":"C\u00f3rdoba",
    "wof:name":"Garcia Peralbo Inmaculada Concepcion",
    "wof:placetype":"venue"
},
  "geometry": {"coordinates":[-4.5230660439,38.0292930603],"type":"Point"}
}