{
  "type": "Feature",
  "properties": {
    "addr:full":"Calle de Metal, 2 Valladolid Valladolid 47008",
    "addr:housenumber":"2",
    "addr:postcode":"47008",
    "addr:street":"Calle De Metal",
    "iso:country":"ES",
    "sg:address":"Calle de Metal, 2",
    "sg:city":"Valladolid",
    "sg:orig_category":"Fabricaci\u00d3n De Juguetes Autom\u00c1ticos",
    "sg:phone":"+34 983 23 95 51",
    "sg:postcode":"47008",
    "sg:province":"Valladolid",
    "wof:name":"Electronicos Pisuerga S.a.",
    "wof:placetype":"venue"
},
  "geometry": {"coordinates":[-4.7346019745,41.6298446655],"type":"Point"}
}