{
  "type": "Feature",
  "properties": {
    "addr:full":"Av Baile Calbeto Barra, 1 Vielha Lleida 25530",
    "addr:housenumber":"1",
    "addr:postcode":"25530",
    "addr:street":"Av Baile;Barra",
    "iso:country":"ES",
    "sg:address":"Av Baile Calbeto Barra, 1",
    "sg:city":"Vielha",
    "sg:orig_category":"Molduras, Junquillos, Listones Y Molduras Perforadas",
    "sg:phone":"+34 973 64 04 49",
    "sg:postcode":"25530",
    "sg:province":"Lleida",
    "wof:name":"Espa\u00f1ol Leis Ramon",
    "wof:placetype":"venue"
},
  "geometry": {"coordinates":[0.7955200076,42.7055511475],"type":"Point"}
}