{
  "type": "Feature",
  "properties": {
    "iso:country":"ES",
    "sg:address":"Barriada De Cupillas, 1",
    "sg:city":"Cuevas Almanzora",
    "sg:orig_category":"Delegados, Agentes De Tr\u00c1nsito, Auxiliares De Transporte Internacional",
    "sg:phone":"+34 950 45 80 06",
    "sg:postcode":"04610",
    "sg:province":"Almer\u00eda",
    "wof:name":"Cargas Completas Logistic S.l.",
    "wof:placetype":"venue"
},
  "geometry": {"coordinates":[-1.8781139851,37.2911911011],"type":"Point"}
}