{
  "type": "Feature",
  "properties": {
    "addr:full":"Calle de Picasso, 24 Molina Segura Murcia 30500",
    "addr:housenumber":"24",
    "addr:postcode":"30500",
    "addr:street":"Calle De Picasso",
    "iso:country":"ES",
    "sg:address":"Calle de Picasso, 24",
    "sg:city":"Molina Segura",
    "sg:orig_category":"Sociedades, Compa\u00d1\u00cdas Aseguradoras",
    "sg:phone":"+34 968 64 22 70",
    "sg:postcode":"30500",
    "sg:province":"Murcia",
    "wof:name":"Seguros Piqueras Artero S.l.",
    "wof:placetype":"venue"
},
  "geometry": {"coordinates":[-1.2034100294,38.0560112],"type":"Point"}
}