{
  "type": "Feature",
  "properties": {
    "addr:full":"Calle de Katalina Eleizegi, 36 Donostia-san Sebastian Guip\u00f9zcoa 20009",
    "addr:housenumber":"36",
    "addr:postcode":"20009",
    "addr:street":"Calle De Katalina Eleizegi",
    "iso:country":"ES",
    "sg:address":"Calle de Katalina Eleizegi, 36",
    "sg:city":"Donostia-san Sebastian",
    "sg:orig_category":"Edici\u00d3n De Diarios, Revistas, Boletines",
    "sg:phone":"+34 943 46 71 81",
    "sg:postcode":"20009",
    "sg:province":"Guip\u00f9zcoa",
    "wof:name":"Donostiako Komunikabideak E.m.",
    "wof:placetype":"venue"
},
  "geometry": {"coordinates":[-1.988016963,43.3043212891],"type":"Point"}
}