{
  "type": "Feature",
  "properties": {
    "iso:country":"ES",
    "sg:address":"Pase Francia De, 1",
    "sg:city":"Donostia-san Sebastian",
    "sg:orig_category":"Caf\u00c9s, Bares, Cervecer\u00cdas",
    "sg:phone":"+34 943 28 72 33",
    "sg:postcode":"20012",
    "sg:province":"Guip\u00f9zcoa",
    "wof:name":"Rey Freyre Emilio",
    "wof:placetype":"venue"
},
  "geometry": {"coordinates":[-1.9768790007,43.3213195801],"type":"Point"}
}