{
  "type": "Feature",
  "properties": {
    "addr:full":"Calle de Camilo Jose Cela, 2 Redovan Alicante 03370",
    "addr:housenumber":"2",
    "addr:postcode":"03370",
    "addr:street":"Calle De Camilo Jose Cela;Alicante",
    "iso:country":"ES",
    "sg:address":"Calle de Camilo Jose Cela, 2",
    "sg:city":"Redovan",
    "sg:orig_category":"M\u00c9dicos: Dermatolog\u00cda Y Venereolog\u00cda",
    "sg:phone":"+34 966 75 42 47",
    "sg:postcode":"03370",
    "sg:province":"Alicante",
    "wof:name":"Juan Medina Joaquin",
    "wof:placetype":"venue"
},
  "geometry": {"coordinates":[-0.9075363278,38.1124801636],"type":"Point"}
}