{
  "type": "Feature",
  "properties": {
    "iso:country":"ES",
    "sg:address":"Calle de Loja, 21",
    "sg:city":"Cordoba",
    "sg:orig_category":"Peluqueros: De Se\u00d1oras",
    "sg:phone":"+34 957 20 29 81",
    "sg:postcode":"14013",
    "sg:province":"C\u00f3rdoba",
    "wof:name":"Roldan Leva Antonio",
    "wof:placetype":"venue"
},
  "geometry": {"coordinates":[-4.7778458595,37.8643188477],"type":"Point"}
}