{
  "type": "Feature",
  "properties": {
    "addr:full":"Cno. Carpesa A Moncada, 343 Pueblo Nuevo Valencia 46025",
    "addr:housenumber":"343",
    "addr:postcode":"46025",
    "addr:street":"Carpesa;Moncada",
    "iso:country":"ES",
    "sg:address":"Cno. Carpesa A Moncada, 343",
    "sg:city":"Pueblo Nuevo",
    "sg:orig_category":"Distribuci\u00d3n De Petr\u00d3leo Y Derivados",
    "sg:phone":"+34 963 66 84 68",
    "sg:postcode":"46025",
    "sg:province":"Valencia",
    "wof:name":"Soriano Soriano Jose",
    "wof:placetype":"venue"
},
  "geometry": {"coordinates":[-0.376819998,39.4691886902],"type":"Point"}
}