{
  "type": "Feature",
  "properties": {
    "addr:full":"Calle de Pio Milla Andres, 7 Angeles Madrid 28223",
    "addr:postcode":"28223",
    "addr:street":"Calle De Pio Milla Andres 7",
    "iso:country":"ES",
    "sg:address":"Calle de Pio Milla Andres, 7",
    "sg:city":"Angeles",
    "sg:orig_category":"Quincaller\u00cda (al Por Menor)",
    "sg:phone":"+34 917 11 42 74",
    "sg:postcode":"28223",
    "sg:province":"Madrid",
    "wof:name":"Gonzalez Cembellin Valeriano",
    "wof:placetype":"venue"
},
  "geometry": {"coordinates":[-3.7791190147,40.404460907],"type":"Point"}
}