{
  "type": "Feature",
  "properties": {
    "addr:full":"Calle de Union, 16 Binaced Huesca 22510",
    "addr:housenumber":"16",
    "addr:postcode":"22510",
    "addr:street":"Calle De;Binaced",
    "iso:country":"ES",
    "sg:address":"Calle de Union, 16",
    "sg:city":"Binaced",
    "sg:orig_category":"Peluquer\u00cdas, Peluquer\u00cda Mixta",
    "sg:phone":"+34 974 42 74 55",
    "sg:postcode":"22510",
    "sg:province":"Huesca",
    "wof:name":"Sorinas Delgado Sara",
    "wof:placetype":"venue"
},
  "geometry": {"coordinates":[0.201989904,41.8267631531],"type":"Point"}
}