{
  "type": "Feature",
  "properties": {
    "iso:country":"ES",
    "sg:address":"Calle de Spengler, 8",
    "sg:city":"Malaga",
    "sg:orig_category":"Importaci\u00d3n",
    "sg:phone":"+34 952 04 04 71",
    "sg:postcode":"29007",
    "sg:province":"M\u00e1laga",
    "wof:name":"Sanchez Pereda Alejandro",
    "wof:placetype":"venue"
},
  "geometry": {"coordinates":[-4.4556522369,36.7180252075],"type":"Point"}
}