{
  "type": "Feature",
  "properties": {
    "iso:country":"ES",
    "sg:address":"Calle de Malaga, S/n",
    "sg:city":"Ibi",
    "sg:orig_category":"Mec\u00c1nico Del Autom\u00d3vil",
    "sg:phone":"+34 966 55 41 27",
    "sg:postcode":"03440",
    "sg:province":"Alicante",
    "wof:name":"Maintenancar S. L.",
    "wof:placetype":"venue"
},
  "geometry": {"coordinates":[-0.5848590136,38.616065979],"type":"Point"}
}