{
  "type": "Feature",
  "properties": {
    "addr:full":"Calle de Malaspina, 20 S. Fernando C\u00e1diz 11100",
    "addr:housenumber":"20",
    "addr:postcode":"11100",
    "addr:street":"Calle De Malaspina;S. Fernando Ca\u0301Diz",
    "iso:country":"ES",
    "sg:address":"Calle de Malaspina, 20",
    "sg:city":"S. Fernando",
    "sg:orig_category":"Molduras, Junquillos, Listones Y Molduras Perforadas",
    "sg:phone":"+34 956 59 74 12",
    "sg:postcode":"11100",
    "sg:province":"C\u00e1diz",
    "wof:name":"Patron Reyes Luis",
    "wof:placetype":"venue"
},
  "geometry": {"coordinates":[-6.1991939545,36.4598617554],"type":"Point"}
}