{
  "type": "Feature",
  "properties": {
    "addr:full":"Calle de Conde De Altea, 29 Altea Alicante 03590",
    "addr:housenumber":"29",
    "addr:postcode":"03590",
    "addr:street":"Calle De Conde De Altea",
    "iso:country":"ES",
    "sg:address":"Calle de Conde De Altea, 29",
    "sg:city":"Altea",
    "sg:classifiers":[
        {
            "category":"Arts & Performance",
            "subcategory":"Art Gallery",
            "type":"Entertainment"
        }
    ],
    "sg:phone":"+34 966 88 09 92",
    "sg:postcode":"03590",
    "sg:province":"Alicante",
    "sg:tags":[
        "arte",
        "de",
        "galer\u00cdas"
    ],
    "wof:name":"Sahm Gallery S.l.",
    "wof:placetype":"venue"
},
  "geometry": {"coordinates":[-0.0465391017,38.6014900208],"type":"Point"}
}