{
  "type": "Feature",
  "properties": {
    "addr:full":"Rua Progreso (do), 36 Lugo Lugo 27001",
    "addr:housenumber":"36",
    "addr:postcode":"27001",
    "addr:street":"Rua Progreso Do",
    "iso:country":"ES",
    "sg:address":"Rua Progreso (do), 36",
    "sg:city":"Lugo",
    "sg:orig_category":"Venta, Instalaci\u00d3n De Cocinas",
    "sg:phone":"+34 982 22 60 05",
    "sg:postcode":"27001",
    "sg:province":"Lugo",
    "wof:name":"Rodriguez Gonzalez Jose Vidal",
    "wof:placetype":"venue"
},
  "geometry": {"coordinates":[-7.5552349091,43.0118255615],"type":"Point"}
}