{
  "type": "Feature",
  "properties": {
    "iso:country":"ES",
    "sg:address":"Traba, S/n",
    "sg:city":"Coristanco",
    "sg:orig_category":"Centros De Educaci\u00d3n Especial",
    "sg:phone":"+34 981 73 30 70",
    "sg:postcode":"15147",
    "sg:province":"La Coru\u00f1a",
    "wof:name":"Colegio Publico Infantil Alcalde Xose Pichel",
    "wof:placetype":"venue"
},
  "geometry": {"coordinates":[-8.7346086502,43.1884384155],"type":"Point"}
}