{
  "type": "Feature",
  "properties": {
    "iso:country":"ES",
    "sg:address":"Calle de Natero (el), 38",
    "sg:city":"Cruz Santa",
    "sg:orig_category":"Empresas De Carpinter\u00cda De Madera",
    "sg:phone":"+34 922 34 01 94",
    "sg:postcode":"38413",
    "sg:province":"Santa Cruz De Tenerife",
    "wof:name":"Sanabria Oliva Luis",
    "wof:placetype":"venue"
},
  "geometry": {"coordinates":[-16.5606460571,28.3570613861],"type":"Point"}
}