{
  "type": "Feature",
  "properties": {
    "addr:full":"Carrer de Concepcio, 13 Palma Islas Baleares 07012",
    "addr:housenumber":"13",
    "addr:postcode":"07012",
    "addr:street":"Carrer De Concepcio",
    "iso:country":"ES",
    "sg:address":"Carrer de Concepcio, 13",
    "sg:city":"Palma",
    "sg:orig_category":"Abogados",
    "sg:phone":"+34 971 71 60 45",
    "sg:postcode":"07012",
    "sg:province":"Islas Baleares",
    "wof:name":"De La Rosa Y Gual De Torrella Abogados C.b.",
    "wof:placetype":"venue"
},
  "geometry": {"coordinates":[2.6454699039,39.574005127],"type":"Point"}
}