{
  "type": "Feature",
  "properties": {
    "addr:full":"Avda San Sebastian, 51 Santa Cruz De Tenerife Santa Cruz De Tenerife 38003",
    "addr:housenumber":"51",
    "addr:postcode":"38003",
    "addr:street":"Avda San Sebastian",
    "iso:country":"ES",
    "sg:address":"Avda San Sebastian, 51",
    "sg:city":"Santa Cruz De Tenerife",
    "sg:orig_category":"Carnicer\u00cdas, Carnicer\u00cdas",
    "sg:phone":"+34 922 20 58 66",
    "sg:postcode":"38003",
    "sg:province":"Santa Cruz De Tenerife",
    "wof:name":"Borges Rivero Maria De Los Dolores",
    "wof:placetype":"venue"
},
  "geometry": {"coordinates":[-16.3326644897,28.4846744537],"type":"Point"}
}