{
  "type": "Feature",
  "properties": {
    "addr:full":"Calle de Capitan Luque, 23 Talavera Reina Toledo 45600",
    "addr:housenumber":"23",
    "addr:postcode":"45600",
    "addr:street":"Calle De Capitan Luque",
    "iso:country":"ES",
    "sg:address":"Calle de Capitan Luque, 23",
    "sg:city":"Talavera Reina",
    "sg:orig_category":"Alimentaci\u00d3n General (al Por Menor)",
    "sg:phone":"+34 925 80 64 18",
    "sg:postcode":"45600",
    "sg:province":"Toledo",
    "wof:name":"Herranz Santo-tomas Esteban",
    "wof:placetype":"venue"
},
  "geometry": {"coordinates":[-4.8330497742,39.9659805298],"type":"Point"}
}