{
  "type": "Feature",
  "properties": {
    "addr:full":"Plaz Iglesia (la), 2 Almensilla Sevilla 41111",
    "addr:housenumber":"2",
    "addr:postcode":"41111",
    "addr:street":"Almensilla Sevilla",
    "iso:country":"ES",
    "sg:address":"Plaz Iglesia (la), 2",
    "sg:city":"Almensilla",
    "sg:orig_category":"Administraciones Regionales, Departamentales Y Locales",
    "sg:phone":"+34 955 76 71 99",
    "sg:postcode":"41111",
    "sg:province":"Sevilla",
    "wof:name":"Ayuntamiento De Almensilla",
    "wof:placetype":"venue"
},
  "geometry": {"coordinates":[-6.1138339043,37.3091621399],"type":"Point"}
}