{
  "type": "Feature",
  "properties": {
    "addr:full":"Carrer de Pou, 38 Barcelona Barcelona 08016",
    "addr:housenumber":"38",
    "addr:postcode":"08016",
    "addr:street":"Carrer De Pou",
    "iso:country":"ES",
    "sg:address":"Carrer de Pou, 38",
    "sg:city":"Barcelona",
    "sg:orig_category":"Tintorer\u00cdas, Limpieza En Seco",
    "sg:phone":"+34 933 54 74 19",
    "sg:postcode":"08016",
    "sg:province":"Barcelona",
    "wof:name":"Ojeda Gimenez Antonio",
    "wof:placetype":"venue"
},
  "geometry": {"coordinates":[2.1814939976,41.4438743591],"type":"Point"}
}