{
  "type": "Feature",
  "properties": {
    "addr:full":"Doctor Ba\u00d1ez Kalea, 2 Arrasate Guip\u00f9zcoa 20500",
    "addr:housenumber":"2",
    "addr:postcode":"20500",
    "addr:street":"Doctor Ban\u0303Ez Kalea;Guipu\u0300Zcoa",
    "iso:country":"ES",
    "sg:address":"Doctor Ba\u00d1ez Kalea, 2",
    "sg:city":"Arrasate",
    "sg:orig_category":"Muebles Y Accesorios Para Cocinas Y Cuartos De Ba\u00d1o (al Por Menor)",
    "sg:phone":"+34 943 77 14 50",
    "sg:postcode":"20500",
    "sg:province":"Guip\u00f9zcoa",
    "wof:name":"Jose Aranzabal Sl",
    "wof:placetype":"venue"
},
  "geometry": {"coordinates":[-2.492634058,43.0625038147],"type":"Point"}
}