{
  "type": "Feature",
  "properties": {
    "iso:country":"ES",
    "sg:address":"Calle de Cea Bermudez, 6",
    "sg:city":"Madrid",
    "sg:orig_category":"Abogados",
    "sg:phone":"+34 915 33 87 87",
    "sg:postcode":"28003",
    "sg:province":"Madrid",
    "wof:name":"Gonzalez Ballesteros Pedro",
    "wof:placetype":"venue"
},
  "geometry": {"coordinates":[-3.7066254616,40.4387702942],"type":"Point"}
}