{
  "type": "Feature",
  "properties": {
    "iso:country":"ES",
    "sg:address":"Ctra. Francia, S/n",
    "sg:city":"Villanua",
    "sg:orig_category":"Venta, Instalaci\u00d3n De Cocinas",
    "sg:phone":"+34 974 37 82 56",
    "sg:postcode":"22870",
    "sg:province":"Huesca",
    "wof:name":"Compaire Izuel Marcos",
    "wof:placetype":"venue"
},
  "geometry": {"coordinates":[-0.5366939902,42.6808433533],"type":"Point"}
}