{
  "type": "Feature",
  "properties": {
    "iso:country":"ES",
    "sg:address":"Calle de Errementari Kalea, 8",
    "sg:city":"Tolosa",
    "sg:orig_category":"Ropa Para Ni\u00d1os (al Por Menor)",
    "sg:phone":"+34 943 67 49 81",
    "sg:postcode":"20400",
    "sg:province":"Guip\u00f9zcoa",
    "wof:name":"Amundarain Orrantia Miren Nekane",
    "wof:placetype":"venue"
},
  "geometry": {"coordinates":[-2.0735630989,43.1375007629],"type":"Point"}
}