{
  "type": "Feature",
  "properties": {
    "iso:country":"ES",
    "sg:address":"Tte Arturo Mu\u00f1oz, S/n",
    "sg:city":"Ejido",
    "sg:orig_category":"Guarder\u00cdas",
    "sg:phone":"+34 950 57 32 31",
    "sg:postcode":"04700",
    "sg:province":"Almer\u00eda",
    "wof:name":"Unicaja",
    "wof:placetype":"venue"
},
  "geometry": {"coordinates":[-2.8114540577,36.7724304199],"type":"Point"}
}