{
  "type": "Feature",
  "properties": {
    "iso:country":"ES",
    "sg:address":"Carrer de Mila I Fontanals, 68",
    "sg:city":"Santa Coloma De Gramenet",
    "sg:orig_category":"Centros Empresariales",
    "sg:phone":"+34 934 68 22 17",
    "sg:postcode":"08922",
    "sg:province":"Barcelona",
    "wof:name":"Alonso Montserrat Maria Del Carmen",
    "wof:placetype":"venue"
},
  "geometry": {"coordinates":[2.2158567905,41.4497680664],"type":"Point"}
}