{
  "type": "Feature",
  "properties": {
    "addr:full":"Calle de Valencia (de), 23 Humanes De Madrid Madrid 28970",
    "addr:housenumber":"23",
    "addr:postcode":"28970",
    "addr:street":"Calle De Valencia De",
    "iso:country":"ES",
    "sg:address":"Calle de Valencia (de), 23",
    "sg:city":"Humanes De Madrid",
    "sg:orig_category":"Negocio De Madera",
    "sg:phone":"+34 916 06 55 56",
    "sg:postcode":"28970",
    "sg:province":"Madrid",
    "wof:name":"Maderas Hermubasa S. L.",
    "wof:placetype":"venue"
},
  "geometry": {"coordinates":[-3.8178260326,40.2761993408],"type":"Point"}
}