{
  "type": "Feature",
  "properties": {
    "iso:country":"ES",
    "sg:address":"Avda Laredo, 29",
    "sg:city":"Fuenlabrada",
    "sg:orig_category":"Equipos De Marcado, Etiquetado",
    "sg:phone":"+34 916 85 62 05",
    "sg:postcode":"28946",
    "sg:province":"Madrid",
    "wof:name":"Roma Publicidad Y Decoracion S.l",
    "wof:placetype":"venue"
},
  "geometry": {"coordinates":[-3.7698791027,40.2767982483],"type":"Point"}
}