{
  "type": "Feature",
  "properties": {
    "iso:country":"ES",
    "sg:address":"Calle de Batalla De Brunete, 19",
    "sg:city":"Palmas De Gran Canaria",
    "sg:orig_category":"Mec\u00c1nico Del Autom\u00d3vil",
    "sg:phone":"+34 928 41 27 83",
    "sg:postcode":"35013",
    "sg:province":"Las Palmas",
    "wof:name":"Medina Hernandez Jose Luis",
    "wof:placetype":"venue"
},
  "geometry": {"coordinates":[-15.4479570389,28.0994853973],"type":"Point"}
}