{
  "type": "Feature",
  "properties": {
    "iso:country":"ES",
    "sg:address":"Ctra N-i (burgos), 19",
    "sg:city":"San Sebastian De Los Reyes",
    "sg:orig_category":"Retoques De Vestidos",
    "sg:phone":"+34 916 59 31 22",
    "sg:postcode":"28700",
    "sg:province":"Madrid",
    "wof:name":"Madrid Retouch S.l.",
    "wof:placetype":"venue"
},
  "geometry": {"coordinates":[-3.5937259197,40.5755310059],"type":"Point"}
}