{
  "type": "Feature",
  "properties": {
    "iso:country":"ES",
    "sg:address":"Calle de Hermanos Gomez, 1",
    "sg:city":"Madrid",
    "sg:orig_category":"Perfumer\u00cda, Art\u00cdculos De Ba\u00d1o (fabricaci\u00d3n, Al Por Mayor)",
    "sg:phone":"+34 914 08 06 07",
    "sg:postcode":"28017",
    "sg:province":"Madrid",
    "wof:name":"Sanchez Colomer Maria Estrella",
    "wof:placetype":"venue"
},
  "geometry": {"coordinates":[-3.6500809193,40.4326782227],"type":"Point"}
}