{
  "type": "Feature",
  "properties": {
    "iso:country":"ES",
    "sg:address":"Rua Pescadores, 1",
    "sg:city":"Vigo",
    "sg:orig_category":"Farmacias",
    "sg:phone":"+34 986 23 31 78",
    "sg:postcode":"36208",
    "sg:province":"Pontevedra",
    "wof:name":"Sueiro Justel Julia",
    "wof:placetype":"venue"
},
  "geometry": {"coordinates":[-8.7529888153,42.2246627808],"type":"Point"}
}