{
  "type": "Feature",
  "properties": {
    "addr:full":"Carrer de Hedilla, 104 Barcelona Barcelona 08031",
    "addr:housenumber":"104",
    "addr:postcode":"08031",
    "addr:street":"Carrer De Hedilla",
    "iso:country":"ES",
    "sg:address":"Carrer de Hedilla, 104",
    "sg:city":"Barcelona",
    "sg:orig_category":"Quincaller\u00cda (al Por Menor)",
    "sg:phone":"+34 934 27 19 70",
    "sg:postcode":"08031",
    "sg:province":"Barcelona",
    "wof:name":"Medina Cardoso Blas",
    "wof:placetype":"venue"
},
  "geometry": {"coordinates":[2.159334898,41.4371833801],"type":"Point"}
}