{
  "type": "Feature",
  "properties": {
    "iso:country":"ES",
    "sg:address":"Cra. Planes, 2",
    "sg:city":"S. Gregori",
    "sg:orig_category":"Colocaci\u00d3n, Mantenimiento De Canalizaciones",
    "sg:phone":"+34 972 21 38 18",
    "sg:postcode":"17150",
    "sg:province":"Girona",
    "wof:name":"Construccions Rebujent S.a.",
    "wof:placetype":"venue"
},
  "geometry": {"coordinates":[2.7533950806,41.9914512634],"type":"Point"}
}