{
  "type": "Feature",
  "properties": {
    "addr:full":"Calle de Luis Doreste Silva, 44 Palmas De Gran Canaria Las Palmas 35004",
    "addr:housenumber":"44",
    "addr:postcode":"35004",
    "addr:street":"Calle De Luis Doreste Silva",
    "iso:country":"ES",
    "sg:address":"Calle de Luis Doreste Silva, 44",
    "sg:city":"Palmas De Gran Canaria",
    "sg:orig_category":"Frutas, Legumbres Frescas Y Tempranas (al Por Menor)",
    "sg:phone":"+34 928 24 24 79",
    "sg:postcode":"35004",
    "sg:province":"Las Palmas",
    "wof:name":"Mateos Diaz Antonio",
    "wof:placetype":"venue"
},
  "geometry": {"coordinates":[-15.4222402573,28.1172294617],"type":"Point"}
}