{
  "type": "Feature",
  "properties": {
    "addr:full":"Carr Industria, 17 Bisbal D'emporda Girona 17100",
    "addr:housenumber":"17",
    "addr:postcode":"17100",
    "addr:street":"Carr Industria",
    "iso:country":"ES",
    "sg:address":"Carr Industria, 17",
    "sg:city":"Bisbal D'emporda",
    "sg:orig_category":"Alfarer\u00cda",
    "sg:phone":"+34 972 64 04 25",
    "sg:postcode":"17100",
    "sg:province":"Girona",
    "wof:name":"Puigdemont Sabater Jose",
    "wof:placetype":"venue"
},
  "geometry": {"coordinates":[2.8048899174,41.9639778137],"type":"Point"}
}