{
  "type": "Feature",
  "properties": {
    "addr:full":"Calle de Echevarrieta Cosme, 7 Bilbao Vizcaya 48009",
    "addr:housenumber":"7",
    "addr:postcode":"48009",
    "addr:street":"Calle De Echevarrieta Cosme",
    "iso:country":"ES",
    "sg:address":"Calle de Echevarrieta Cosme, 7",
    "sg:city":"Bilbao",
    "sg:orig_category":"Asesor\u00cda Sobre Comunicaci\u00d3n De Empresas",
    "sg:phone":"+34 944 23 02 71",
    "sg:postcode":"48009",
    "sg:province":"Vizcaya",
    "wof:name":"Bailen Asesores Consultores, S.l.",
    "wof:placetype":"venue"
},
  "geometry": {"coordinates":[-2.9311888218,43.2661705017],"type":"Point"}
}