{
  "type": "Feature",
  "properties": {
    "addr:full":"Carrer de Sas, 25 Barcelona Barcelona 08030",
    "addr:housenumber":"25",
    "addr:postcode":"08030",
    "addr:street":"Carrer De Sas",
    "iso:country":"ES",
    "sg:address":"Carrer de Sas, 25",
    "sg:city":"Barcelona",
    "sg:orig_category":"\u00d3ptica: Instrumentos (fabricaci\u00d3n)",
    "sg:phone":"+34 933 46 49 00",
    "sg:postcode":"08030",
    "sg:province":"Barcelona",
    "wof:name":"Cos Julian Juan Carlos",
    "wof:placetype":"venue"
},
  "geometry": {"coordinates":[2.2040979862,41.4372177124],"type":"Point"}
}