{
  "type": "Feature",
  "properties": {
    "addr:full":"Calle de Rosa Chacel, 8 Zaragoza Zaragoza 50015",
    "addr:housenumber":"8",
    "addr:postcode":"50015",
    "addr:street":"Calle De Rosa Chacel",
    "iso:country":"ES",
    "sg:address":"Calle de Rosa Chacel, 8",
    "sg:city":"Zaragoza",
    "sg:orig_category":"Dise\u00d1o Industrial",
    "sg:phone":"+34 976 52 92 79",
    "sg:postcode":"50015",
    "sg:province":"Zaragoza",
    "wof:name":"Moles Espadas Antonio",
    "wof:placetype":"venue"
},
  "geometry": {"coordinates":[-0.8926799893,41.6691589355],"type":"Point"}
}