{
  "type": "Feature",
  "properties": {
    "iso:country":"ES",
    "sg:address":"Trva Castro, 4",
    "sg:city":"Getafe",
    "sg:orig_category":"Empresarios",
    "sg:phone":"+34 916 42 56 43",
    "sg:postcode":"28903",
    "sg:province":"Madrid",
    "wof:name":"Inicia Obras Y Reformas S.l.",
    "wof:placetype":"venue"
},
  "geometry": {"coordinates":[-3.7251279354,40.3210029602],"type":"Point"}
}