{
  "type": "Feature",
  "properties": {
    "addr:full":"Avda Celanova (de), 78 Valenza Ourense 32002",
    "addr:housenumber":"78",
    "addr:postcode":"32002",
    "addr:street":"Avda Celanova De",
    "iso:country":"ES",
    "sg:address":"Avda Celanova (de), 78",
    "sg:city":"Valenza",
    "sg:orig_category":"Alimentaci\u00d3n General (al Por Menor)",
    "sg:phone":"+34 988 24 80 24",
    "sg:postcode":"32002",
    "sg:province":"Ourense",
    "wof:name":"Distribuciones Froiz S.a.",
    "wof:placetype":"venue"
},
  "geometry": {"coordinates":[-7.8810148239,42.3196105957],"type":"Point"}
}