{
  "type": "Feature",
  "properties": {
    "addr:full":"Ctra. Colloto-santander, 130 Colloto-oviedo Asturias 33010",
    "addr:housenumber":"130",
    "addr:postcode":"33010",
    "addr:street":"Ctra. Colloto-Santander;Asturias",
    "iso:country":"ES",
    "sg:address":"Ctra. Colloto-santander, 130",
    "sg:city":"Colloto-oviedo",
    "sg:orig_category":"Tapicer\u00cdas",
    "sg:phone":"+34 985 79 32 42",
    "sg:postcode":"33010",
    "sg:province":"Asturias",
    "wof:name":"Suarez Garcia Luis Daniel",
    "wof:placetype":"venue"
},
  "geometry": {"coordinates":[-5.7993540764,43.3772239685],"type":"Point"}
}