{
  "type": "Feature",
  "properties": {
    "iso:country":"ES",
    "sg:address":"Carrer de Enamorats, 81",
    "sg:city":"Barcelona",
    "sg:orig_category":"Camiser\u00cda Y Ropa Interior Masculina (al Por Menor)",
    "sg:phone":"+34 932 45 84 53",
    "sg:postcode":"08013",
    "sg:province":"Barcelona",
    "wof:name":"Camps Ferrando Concepcion",
    "wof:placetype":"venue"
},
  "geometry": {"coordinates":[2.1825809479,41.4059066772],"type":"Point"}
}