{
  "type": "Feature",
  "properties": {
    "addr:full":"Av S'agaro, S/n Platja D'aro Girona 17250",
    "addr:housenumber":"s / n",
    "addr:postcode":"17250",
    "addr:street":"Av S'Agaro",
    "iso:country":"ES",
    "sg:address":"Av S'agaro, S/n",
    "sg:city":"Platja D'aro",
    "sg:orig_category":"Venta, Instalaci\u00d3n De Calefacci\u00d3n",
    "sg:phone":"+34 972 81 98 39",
    "sg:postcode":"17250",
    "sg:province":"Girona",
    "wof:name":"Sitjes Hostench Jaime",
    "wof:placetype":"venue"
},
  "geometry": {"coordinates":[2.8163490295,41.9701499939],"type":"Point"}
}