{
  "type": "Feature",
  "properties": {
    "addr:full":"Avda Constitucion, S/n Jaraiz Vera C\u00e1ceres 10400",
    "addr:postcode":"10400",
    "addr:street":"Avda Constitucion S / N Jaraiz Vera Ca\u0301Ceres",
    "iso:country":"ES",
    "sg:address":"Avda Constitucion, S/n",
    "sg:city":"Jaraiz Vera",
    "sg:orig_category":"Tiendas De Grano, Frutas Y Legumbres Secas (al Por Menor)",
    "sg:phone":"+34 927 17 04 85",
    "sg:postcode":"10400",
    "sg:province":"C\u00e1ceres",
    "wof:name":"Labrador Santos Maximino",
    "wof:placetype":"venue"
},
  "geometry": {"coordinates":[-5.7529468536,40.0654678345],"type":"Point"}
}