{
  "type": "Feature",
  "properties": {
    "addr:full":"Calle de Marques De Valdecilla, 6 Laredo Cantabria 39770",
    "addr:housenumber":"6",
    "addr:postcode":"39770",
    "addr:street":"Calle De Marques De Valdecilla",
    "iso:country":"ES",
    "sg:address":"Calle de Marques De Valdecilla, 6",
    "sg:city":"Laredo",
    "sg:orig_category":"Agencias Y Agentes Comerciales, Representantes",
    "sg:phone":"+34 942 60 66 04",
    "sg:postcode":"39770",
    "sg:province":"Cantabria",
    "wof:name":"Bouras Trading S.l.",
    "wof:placetype":"venue"
},
  "geometry": {"coordinates":[-3.4181659222,43.4079971313],"type":"Point"}
}