{
  "type": "Feature",
  "properties": {
    "addr:full":"Calle de Malva, 1 Sevilla Sevilla 41008",
    "addr:housenumber":"1",
    "addr:postcode":"41008",
    "addr:street":"Calle De Malva",
    "iso:country":"ES",
    "sg:address":"Calle de Malva, 1",
    "sg:city":"Sevilla",
    "sg:orig_category":"Chapister\u00cda",
    "sg:phone":"+34 954 95 13 17",
    "sg:postcode":"41008",
    "sg:province":"Sevilla",
    "wof:name":"Acosta Acosta Jose Luis",
    "wof:placetype":"venue"
},
  "geometry": {"coordinates":[-5.9712543488,37.4083824158],"type":"Point"}
}