{
  "type": "Feature",
  "properties": {
    "iso:country":"ES",
    "sg:address":"Ctra Villagonzalo, S/n",
    "sg:city":"Santiuste De San Juan Bautista",
    "sg:orig_category":"Vinos Y Licores (venta Al Por Menor)",
    "sg:phone":"+34 921 59 63 26",
    "sg:postcode":"40460",
    "sg:province":"Segovia",
    "wof:name":"Bodegas Cerrosol S.a.",
    "wof:placetype":"venue"
},
  "geometry": {"coordinates":[-4.5701828003,41.1551170349],"type":"Point"}
}