{
  "type": "Feature",
  "properties": {
    "addr:full":"Avda Mario Spreafico, 23 Otro La'o Murcia 30600",
    "addr:housenumber":"23",
    "addr:postcode":"30600",
    "addr:street":"Avda Mario Spreafico",
    "iso:country":"ES",
    "sg:address":"Avda Mario Spreafico, 23",
    "sg:city":"Otro La'o",
    "sg:orig_category":"Comercio, Reparaci\u00d3n De Motocicletas, Bicicletas Y Piezas Sueltas",
    "sg:phone":"+34 968 67 08 43",
    "sg:postcode":"30600",
    "sg:province":"Murcia",
    "wof:name":"Marin Perea Jose Maria",
    "wof:placetype":"venue"
},
  "geometry": {"coordinates":[-1.1302499771,37.9829597473],"type":"Point"}
}