{
  "type": "Feature",
  "properties": {
    "iso:country":"ES",
    "sg:address":"Carrer de Doctor Trueta, 182",
    "sg:city":"Barcelona",
    "sg:orig_category":"Ebanister\u00cda",
    "sg:phone":"+34 932 25 08 00",
    "sg:postcode":"08005",
    "sg:province":"Barcelona",
    "wof:name":"Minguill\u00d3n Ram\u00d3n Jose Maria",
    "wof:placetype":"venue"
},
  "geometry": {"coordinates":[2.2016050816,41.3970298767],"type":"Point"}
}