{
  "type": "Feature",
  "properties": {
    "addr:full":"Avda Pueyo, 17 Monzon Huesca 22400",
    "addr:housenumber":"17",
    "addr:postcode":"22400",
    "addr:street":"Avda Pueyo",
    "iso:country":"ES",
    "sg:address":"Avda Pueyo, 17",
    "sg:city":"Monzon",
    "sg:orig_category":"Peluquer\u00cdas, Peluquer\u00cda Mixta",
    "sg:phone":"+34 974 40 32 46",
    "sg:postcode":"22400",
    "sg:province":"Huesca",
    "wof:name":"Hermanas Dominguez Zapater S.l.",
    "wof:placetype":"venue"
},
  "geometry": {"coordinates":[0.1862799972,41.9063301086],"type":"Point"}
}