{
  "type": "Feature",
  "properties": {
    "iso:country":"ES",
    "sg:address":"Calle de Alcalde Garcia Asensio, 6",
    "sg:city":"Malaga",
    "sg:orig_category":"Construcciones Met\u00c1licas",
    "sg:phone":"+34 952 34 43 37",
    "sg:postcode":"29006",
    "sg:province":"M\u00e1laga",
    "wof:name":"Cerrajeria Romo S. L.",
    "wof:placetype":"venue"
},
  "geometry": {"coordinates":[-4.4752850533,36.7087440491],"type":"Point"}
}