{
  "type": "Feature",
  "properties": {
    "addr:full":"Carr Pau Claris, 1 Lleida Lleida 25008",
    "addr:housenumber":"1",
    "addr:postcode":"25008",
    "addr:street":"Carr Pau Claris",
    "iso:country":"ES",
    "sg:address":"Carr Pau Claris, 1",
    "sg:city":"Lleida",
    "sg:orig_category":"Peluqueros: De Se\u00d1oras",
    "sg:phone":"+34 973 23 62 70",
    "sg:postcode":"25008",
    "sg:province":"Lleida",
    "wof:name":"Carrillo Navas Dolores",
    "wof:placetype":"venue"
},
  "geometry": {"coordinates":[0.6227300167,41.6222801208],"type":"Point"}
}