{
  "type": "Feature",
  "properties": {
    "addr:full":"Monasterio Zilbeti, 1 Iru\u00f1a Navarra 31011",
    "addr:housenumber":"1",
    "addr:postcode":"31011",
    "addr:street":"Zilbeti",
    "iso:country":"ES",
    "sg:address":"Monasterio Zilbeti, 1",
    "sg:city":"Iru\u00f1a",
    "sg:orig_category":"Arquitectos",
    "sg:phone":"+34 948 19 82 38",
    "sg:postcode":"31011",
    "sg:province":"Navarra",
    "wof:name":"Urquiza Echavarren Jose Maria",
    "wof:placetype":"venue"
},
  "geometry": {"coordinates":[-1.6555169821,42.8162498474],"type":"Point"}
}