{
  "type": "Feature",
  "properties": {
    "addr:full":"Ctra Sant Joan, 55 Centre Urba Girona 17500",
    "addr:housenumber":"55",
    "addr:postcode":"17500",
    "addr:street":"Ctra Sant Joan;Centre Urba",
    "iso:country":"ES",
    "sg:address":"Ctra Sant Joan, 55",
    "sg:city":"Centre Urba",
    "sg:orig_category":"Organizaciones Profesionales",
    "sg:phone":"+34 972 71 46 17",
    "sg:postcode":"17500",
    "sg:province":"Girona",
    "wof:name":"Perez Casas Miquel",
    "wof:placetype":"venue"
},
  "geometry": {"coordinates":[2.1959049702,42.1965866089],"type":"Point"}
}