{
  "type": "Feature",
  "properties": {
    "iso:country":"ES",
    "sg:address":"Plaz Jesus De La Pasion, 13",
    "sg:city":"Sevilla",
    "sg:orig_category":"Bisuter\u00cda, Joyer\u00cda, Relojer\u00cda (al Por Menor)",
    "sg:phone":"+34 954 21 44 85",
    "sg:postcode":"41004",
    "sg:province":"Sevilla",
    "wof:name":"Soto Sanchez Natalia",
    "wof:placetype":"venue"
},
  "geometry": {"coordinates":[-5.9923090935,37.3898696899],"type":"Point"}
}