{
  "type": "Feature",
  "properties": {
    "addr:full":"Plaz America, 1 Alacant Alicante 03010",
    "addr:housenumber":"1",
    "addr:postcode":"03010",
    "iso:country":"ES",
    "sg:address":"Plaz America, 1",
    "sg:city":"Alacant",
    "sg:orig_category":"M\u00c9dicos: Ginecolog\u00cda Y Obstetricia",
    "sg:phone":"+34 965 92 19 11",
    "sg:postcode":"03010",
    "sg:province":"Alicante",
    "wof:name":"Montoya Martinez Angela",
    "wof:placetype":"venue"
},
  "geometry": {"coordinates":[-0.4855979979,38.3595085144],"type":"Point"}
}