{
  "type": "Feature",
  "properties": {
    "iso:country":"ES",
    "sg:address":"Pase Casares De, 153",
    "sg:city":"Donostia-san Sebastian",
    "sg:orig_category":"Polideportivos",
    "sg:phone":"+34 943 35 24 57",
    "sg:postcode":"20017",
    "sg:province":"Guip\u00f9zcoa",
    "wof:name":"Patronato Municipal De Deportes",
    "wof:placetype":"venue"
},
  "geometry": {"coordinates":[-1.9272259474,43.318572998],"type":"Point"}
}