{
  "type": "Feature",
  "properties": {
    "iso:country":"ES",
    "sg:address":"Pg Rubi, 29",
    "sg:city":"Valldoreix",
    "sg:classifiers":[
        {
            "category":"Professional",
            "subcategory":"Research",
            "type":"Services"
        }
    ],
    "sg:phone":"+34 935 83 65 49",
    "sg:postcode":"08197",
    "sg:province":"Barcelona",
    "sg:tags":[
        "mercado",
        "de",
        "estudios"
    ],
    "wof:name":"Enviros Spain S.l.",
    "wof:placetype":"venue"
},
  "geometry": {"coordinates":[2.0633220673,41.4593009949],"type":"Point"}
}