{
  "type": "Feature",
  "properties": {
    "addr:full":"C/ Sant Pancra\u00c7, De, 2 Alaior Islas Baleares 07730",
    "addr:housenumber":"2",
    "addr:postcode":"07730",
    "addr:street":"C / Sant Pancrac\u0327 De",
    "iso:country":"ES",
    "sg:address":"C/ Sant Pancra\u00c7, De, 2",
    "sg:city":"Alaior",
    "sg:orig_category":"Promotores Constructores",
    "sg:phone":"+34 971 37 12 05",
    "sg:postcode":"07730",
    "sg:province":"Islas Baleares",
    "wof:name":"Inversiones Y Promociones Inmobiliarias Q.m.s.l.",
    "wof:placetype":"venue"
},
  "geometry": {"coordinates":[4.1400899887,39.9360466003],"type":"Point"}
}