{
  "type": "Feature",
  "properties": {
    "addr:full":"Rua Compostela, 1 Carballo La Coru\u00f1a 15100",
    "addr:housenumber":"1",
    "addr:postcode":"15100",
    "addr:street":"Rua Compostela;La Corun\u0303A",
    "iso:country":"ES",
    "sg:address":"Rua Compostela, 1",
    "sg:city":"Carballo",
    "sg:orig_category":"Reposter\u00cdas",
    "sg:phone":"+34 981 70 01 28",
    "sg:postcode":"15100",
    "sg:province":"La Coru\u00f1a",
    "wof:name":"Angeriz Riveiro Generoso",
    "wof:placetype":"venue"
},
  "geometry": {"coordinates":[-8.6854715347,43.2048835754],"type":"Point"}
}