{
  "type": "Feature",
  "properties": {
    "addr:full":"Avda Rosaleda, 1 Malaga M\u00e1laga 29008",
    "addr:housenumber":"1",
    "addr:postcode":"29008",
    "addr:street":"Avda Rosaleda;Ma\u0301Laga",
    "iso:country":"ES",
    "sg:address":"Avda Rosaleda, 1",
    "sg:city":"Malaga",
    "sg:orig_category":"M\u00c9dicos: Estomatolog\u00cda",
    "sg:phone":"+34 952 21 07 88",
    "sg:postcode":"29008",
    "sg:province":"M\u00e1laga",
    "wof:name":"Martinez Fernandez Gema",
    "wof:placetype":"venue"
},
  "geometry": {"coordinates":[-4.4251198769,36.7219238281],"type":"Point"}
}