{
  "type": "Feature",
  "properties": {
    "iso:country":"ES",
    "sg:address":"Ctra Fte Alamo, Km. 0013,0",
    "sg:city":"La Aljorra",
    "sg:orig_category":"Montaje (empresas De)",
    "sg:phone":"+34 968 16 17 07",
    "sg:postcode":"30390",
    "sg:province":"Murcia",
    "wof:name":"Espa\u00f1ola De Montajes Metalicos S.a.",
    "wof:placetype":"venue"
},
  "geometry": {"coordinates":[-1.0567389727,37.6922111511],"type":"Point"}
}