{
  "type": "Feature",
  "properties": {
    "iso:country":"ES",
    "sg:address":"Carrer de Roger De Lluria, 7",
    "sg:city":"Barcelona",
    "sg:orig_category":"Detectives, Agentes Investigadores Privados",
    "sg:phone":"+34 933 42 90 50",
    "sg:postcode":"08010",
    "sg:province":"Barcelona",
    "wof:name":"Pujadas Coscolla Juan",
    "wof:placetype":"venue"
},
  "geometry": {"coordinates":[2.1726360321,41.3900718689],"type":"Point"}
}