{
  "type": "Feature",
  "properties": {
    "addr:full":"Calle de Santa Engracia, 115 Madrid Madrid 28010",
    "addr:housenumber":"115",
    "addr:postcode":"28010",
    "addr:street":"Calle De Santa Engracia",
    "iso:country":"ES",
    "sg:address":"Calle de Santa Engracia, 115",
    "sg:city":"Madrid",
    "sg:orig_category":"Muebles Y Accesorios Para Cocinas Y Cuartos De Ba\u00d1o (al Por Menor)",
    "sg:phone":"+34 914 44 03 04",
    "sg:postcode":"28010",
    "sg:province":"Madrid",
    "sg:website":"www.bulthaup-se.com",
    "wof:name":"Dise\u00f1os Proyectos E Instalaciones Babia S.l.",
    "wof:placetype":"venue"
},
  "geometry": {"coordinates":[-3.7002470493,40.4379959106],"type":"Point"}
}