{
  "type": "Feature",
  "properties": {
    "iso:country":"ES",
    "sg:address":"Carrer de Francesc Bastos (de), 1",
    "sg:city":"Tarragona",
    "sg:orig_category":"Caf\u00c9s, Bares, Cervecer\u00cdas",
    "sg:phone":"+34 977 23 28 43",
    "sg:postcode":"43005",
    "sg:province":"Tarragona",
    "wof:name":"Cafe Del Barri S.l.",
    "wof:placetype":"venue"
},
  "geometry": {"coordinates":[1.2426600456,41.1160697937],"type":"Point"}
}