{
  "type": "Feature",
  "properties": {
    "iso:country":"ES",
    "sg:address":"Calle de Margaritas, 1",
    "sg:city":"Madrid",
    "sg:orig_category":"Mercer\u00cda, Lencer\u00cda (al Por Menor)",
    "sg:phone":"+34 913 11 37 72",
    "sg:postcode":"28039",
    "sg:province":"Madrid",
    "wof:name":"Peinado Martinez Gregoria",
    "wof:placetype":"venue"
},
  "geometry": {"coordinates":[-3.7066149712,40.4567184448],"type":"Point"}
}