{
  "type": "Feature",
  "properties": {
    "addr:full":"Carrer de Sant Antoni Abat, 48 Barcelona Barcelona 08001",
    "addr:housenumber":"48",
    "addr:postcode":"08001",
    "addr:street":"Carrer De Sant Antoni Abat",
    "iso:country":"ES",
    "sg:address":"Carrer de Sant Antoni Abat, 48",
    "sg:city":"Barcelona",
    "sg:orig_category":"Producci\u00d3n, Comercio De Cereales",
    "sg:phone":"+34 934 42 21 15",
    "sg:postcode":"08001",
    "sg:province":"Barcelona",
    "wof:name":"Lopez Juan Ricardo",
    "wof:placetype":"venue"
},
  "geometry": {"coordinates":[2.163902998,41.3789787292],"type":"Point"}
}