{
  "type": "Feature",
  "properties": {
    "addr:full":"Calle de Portichuelo, 10 Ronda M\u00e1laga 29400",
    "addr:housenumber":"10",
    "addr:postcode":"29400",
    "addr:street":"Calle De Portichuelo;Ronda Ma\u0301Laga",
    "iso:country":"ES",
    "sg:address":"Calle de Portichuelo, 10",
    "sg:city":"Ronda",
    "sg:orig_category":"Producci\u00d3n, Distribuci\u00d3n De Gas Butano Y Propano",
    "sg:phone":"+34 952 87 69 04",
    "sg:postcode":"29400",
    "sg:province":"M\u00e1laga",
    "wof:name":"Distribuidora De Gas Serrania De Ronda S.l.",
    "wof:placetype":"venue"
},
  "geometry": {"coordinates":[-5.1606287956,36.7447967529],"type":"Point"}
}