{
  "type": "Feature",
  "properties": {
    "addr:full":"Carrer de Jardi D'elx, S/n Barcelona Barcelona 08027",
    "addr:housenumber":"s / n",
    "addr:postcode":"08027",
    "addr:street":"Carrer De Jardi D'Elx",
    "iso:country":"ES",
    "sg:address":"Carrer de Jardi D'elx, S/n",
    "sg:city":"Barcelona",
    "sg:orig_category":"Iglesia Cat\u00d3lica",
    "sg:phone":"+34 934 08 13 63",
    "sg:postcode":"08027",
    "sg:province":"Barcelona",
    "wof:name":"Parroquia De Crist Rei",
    "wof:placetype":"venue"
},
  "geometry": {"coordinates":[2.1867861748,41.4230461121],"type":"Point"}
}