{
  "type": "Feature",
  "properties": {
    "addr:full":"Av Maria Fortuny, 1 Reus Tarragona 43204",
    "addr:housenumber":"1",
    "addr:postcode":"43204",
    "addr:street":"Av Maria Fortuny",
    "iso:country":"ES",
    "sg:address":"Av Maria Fortuny, 1",
    "sg:city":"Reus",
    "sg:orig_category":"Calefacci\u00d3n Central: Material (fabricaci\u00d3n, Al Por Mayor)",
    "sg:phone":"+34 977 77 43 99",
    "sg:postcode":"43204",
    "sg:province":"Tarragona",
    "wof:name":"Romero Cruz Antonio",
    "wof:placetype":"venue"
},
  "geometry": {"coordinates":[1.115811944,41.1528701782],"type":"Point"}
}