{
  "type": "Feature",
  "properties": {
    "addr:full":"Calle de Rodrigo Leon, 2 Jerez De La Frontera C\u00e1diz 11401",
    "addr:housenumber":"2",
    "addr:postcode":"11401",
    "addr:street":"Calle De Rodrigo Leon",
    "iso:country":"ES",
    "sg:address":"Calle de Rodrigo Leon, 2",
    "sg:city":"Jerez De La Frontera",
    "sg:orig_category":"Agentes Generales De Seguros",
    "sg:phone":"+34 956 34 97 01",
    "sg:postcode":"11401",
    "sg:province":"C\u00e1diz",
    "wof:name":"Seguxerez S.l.",
    "wof:placetype":"venue"
},
  "geometry": {"coordinates":[-6.1388349533,36.6792449951],"type":"Point"}
}