{
  "type": "Feature",
  "properties": {
    "addr:full":"Calle de Granada, 106 Ejido Almer\u00eda 04700",
    "addr:housenumber":"106",
    "addr:postcode":"04700",
    "addr:street":"Calle De Granada;Ejido Almeri\u0301A",
    "iso:country":"ES",
    "sg:address":"Calle de Granada, 106",
    "sg:city":"Ejido",
    "sg:orig_category":"Comercio De Piezas De Recambio Y De Accesorios De Veh\u00cdculos, Veh\u00cdculos Industriales",
    "sg:phone":"+34 950 48 02 63",
    "sg:postcode":"04700",
    "sg:province":"Almer\u00eda",
    "wof:name":"Villegas Enciso Jesus",
    "wof:placetype":"venue"
},
  "geometry": {"coordinates":[-2.8148789406,36.7720375061],"type":"Point"}
}