{
  "type": "Feature",
  "properties": {
    "addr:full":"Calle de Jesus Nazareno, 4 Santa Cruz De Tenerife Santa Cruz De Tenerife 38003",
    "addr:housenumber":"4",
    "addr:postcode":"38003",
    "addr:street":"Calle De Jesus Nazareno",
    "iso:country":"ES",
    "sg:address":"Calle de Jesus Nazareno, 4",
    "sg:city":"Santa Cruz De Tenerife",
    "sg:orig_category":"Abogados",
    "sg:phone":"+34 922 28 09 78",
    "sg:postcode":"38003",
    "sg:province":"Santa Cruz De Tenerife",
    "wof:name":"Olmos Aguilar Jose Maria",
    "wof:placetype":"venue"
},
  "geometry": {"coordinates":[-16.2548923492,28.4673538208],"type":"Point"}
}