{
  "type": "Feature",
  "properties": {
    "addr:full":"Ptda Alzabares Bajo, 7 Elche Alicante 03290",
    "addr:housenumber":"7",
    "addr:postcode":"03290",
    "addr:street":"Ptda Alzabares Bajo",
    "iso:country":"ES",
    "sg:address":"Ptda Alzabares Bajo, 7",
    "sg:city":"Elche",
    "sg:orig_category":"Aguas (distribuci\u00d3n, Servicios)",
    "sg:phone":"+34 965 42 00 61",
    "sg:postcode":"03290",
    "sg:province":"Alicante",
    "sg:website":"www.infotectii.com/dfeda",
    "wof:name":"Anip Piscinas S.l.",
    "wof:placetype":"venue"
},
  "geometry": {"coordinates":[-0.6915392876,38.2354507446],"type":"Point"}
}