{
  "type": "Feature",
  "properties": {
    "addr:full":"Calle de Mu\u00d1oz Y Pabon, 11 Sevilla Sevilla 41004",
    "addr:housenumber":"11",
    "addr:postcode":"41004",
    "addr:street":"Calle De Mun\u0303Oz Y Pabon",
    "iso:country":"ES",
    "sg:address":"Calle de Mu\u00d1oz Y Pabon, 11",
    "sg:city":"Sevilla",
    "sg:orig_category":"Centros De Coordinaci\u00d3n",
    "sg:phone":"+34 954 21 76 10",
    "sg:postcode":"41004",
    "sg:province":"Sevilla",
    "wof:name":"Roypro S.a.",
    "wof:placetype":"venue"
},
  "geometry": {"coordinates":[-5.9897289276,37.3889045715],"type":"Point"}
}