{
  "type": "Feature",
  "properties": {
    "addr:full":"Rua Severino Cobas, 65 Sabaxans Pontevedra 36214",
    "addr:housenumber":"65",
    "addr:postcode":"36214",
    "addr:street":"Rua Severino Cobas",
    "iso:country":"ES",
    "sg:address":"Rua Severino Cobas, 65",
    "sg:city":"Sabaxans",
    "sg:orig_category":"Mec\u00c1nico Del Autom\u00d3vil",
    "sg:phone":"+34 986 27 11 24",
    "sg:postcode":"36214",
    "sg:province":"Pontevedra",
    "wof:name":"Otebra S.l.",
    "wof:placetype":"venue"
},
  "geometry": {"coordinates":[-8.7059106827,42.2124443054],"type":"Point"}
}