{
  "type": "Feature",
  "properties": {
    "iso:country":"ES",
    "sg:address":"Calle de Unica, S/n",
    "sg:city":"Guaso",
    "sg:orig_category":"Agencias Y Agentes Comerciales, Representantes",
    "sg:phone":"+34 974 50 23 38",
    "sg:postcode":"22349",
    "sg:province":"Huesca",
    "wof:name":"Montal Mateu Jose Maria",
    "wof:placetype":"venue"
},
  "geometry": {"coordinates":[0.0985110998,42.4167709351],"type":"Point"}
}