{
  "type": "Feature",
  "properties": {
    "addr:full":"Barr Castanedo, 80 Rubayo Cantabria 39719",
    "addr:housenumber":"80",
    "addr:postcode":"39719",
    "addr:street":"Castanedo",
    "iso:country":"ES",
    "sg:address":"Barr Castanedo, 80",
    "sg:city":"Rubayo",
    "sg:orig_category":"Complementos De Vestir (al Por Menor)",
    "sg:phone":"+34 942 50 60 45",
    "sg:postcode":"39719",
    "sg:province":"Cantabria",
    "wof:name":"Vega De Seoane Azpilicueta Alvaro",
    "wof:placetype":"venue"
},
  "geometry": {"coordinates":[-3.7546238899,43.4222450256],"type":"Point"}
}