{
  "type": "Feature",
  "properties": {
    "iso:country":"ES",
    "sg:address":"Pg Torre Blanca, S/n",
    "sg:city":"S. Cugat Valles",
    "sg:orig_category":"Frutas, Legumbres Frescas Y Tempranas (al Por Menor)",
    "sg:phone":"+34 936 75 47 60",
    "sg:postcode":"08172",
    "sg:province":"Barcelona",
    "wof:name":"Gasull Ventura Isidro",
    "wof:placetype":"venue"
},
  "geometry": {"coordinates":[2.0842399597,41.4679336548],"type":"Point"}
}