{
  "type": "Feature",
  "properties": {
    "iso:country":"ES",
    "sg:address":"Carr Santa Maxima, 2",
    "sg:city":"Escala",
    "sg:orig_category":"Hielo Artificial (fabricaci\u00d3n, Distribuci\u00d3n)",
    "sg:phone":"+34 972 77 02 38",
    "sg:postcode":"17130",
    "sg:province":"Girona",
    "wof:name":"Candela Garcia Jose",
    "wof:placetype":"venue"
},
  "geometry": {"coordinates":[3.1321649551,42.1229934692],"type":"Point"}
}