{
  "type": "Feature",
  "properties": {
    "iso:country":"ES",
    "sg:address":"Avda Sierra De Yeguas, 1",
    "sg:city":"Campillos",
    "sg:orig_category":"Peleter\u00cdas",
    "sg:phone":"+34 952 72 40 82",
    "sg:postcode":"29320",
    "sg:province":"M\u00e1laga",
    "sg:website":"www.morgdoapiel.com",
    "wof:name":"Morgado Piel S.l.",
    "wof:placetype":"venue"
},
  "geometry": {"coordinates":[-4.8605089188,37.0521507263],"type":"Point"}
}