{
  "type": "Feature",
  "properties": {
    "addr:full":"Carrer de Mossen Jacint Verdaguer, 49 Sant Vicen\u00c7 Dels Horts Barcelona 08620",
    "addr:housenumber":"49",
    "addr:postcode":"08620",
    "addr:street":"Carrer De Mossen Jacint Verdaguer",
    "iso:country":"ES",
    "sg:address":"Carrer de Mossen Jacint Verdaguer, 49",
    "sg:city":"Sant Vicen\u00c7 Dels Horts",
    "sg:orig_category":"Laboratorios Y Trabajos De Fotograf\u00cda, V\u00cddeo Y Cine",
    "sg:phone":"+34 936 56 55 09",
    "sg:postcode":"08620",
    "sg:province":"Barcelona",
    "wof:name":"Vailet-foto",
    "wof:placetype":"venue"
},
  "geometry": {"coordinates":[2.0084431171,41.3953437805],"type":"Point"}
}