{
  "type": "Feature",
  "properties": {
    "iso:country":"ES",
    "sg:address":"Avda Costa Levante, S/n",
    "sg:city":"Garrucha",
    "sg:orig_category":"Art\u00cdculos De Regalo (al Por Menor)",
    "sg:phone":"+34 950 39 70 68",
    "sg:postcode":"04630",
    "sg:province":"Almer\u00eda",
    "wof:name":"Garcia Montoya Francisco",
    "wof:placetype":"venue"
},
  "geometry": {"coordinates":[-1.8280746937,37.1600532532],"type":"Point"}
}