{
  "type": "Feature",
  "properties": {
    "addr:full":"Calle de Logro\u00d1o, 26 Miranda Ebro Burgos 09200",
    "addr:housenumber":"26",
    "addr:postcode":"09200",
    "addr:street":"Calle De Logron\u0303O",
    "iso:country":"ES",
    "sg:address":"Calle de Logro\u00d1o, 26",
    "sg:city":"Miranda Ebro",
    "sg:orig_category":"Telas Y Sedas (al Por Menor)",
    "sg:phone":"+34 947 32 11 26",
    "sg:postcode":"09200",
    "sg:province":"Burgos",
    "wof:name":"Fernandez Garo\u00f1a Maria Elena",
    "wof:placetype":"venue"
},
  "geometry": {"coordinates":[-2.9388930798,42.6880378723],"type":"Point"}
}