{
  "type": "Feature",
  "properties": {
    "addr:full":"Avda Mediterraneo (del), 294 Almeria Almer\u00eda 04006",
    "addr:housenumber":"294",
    "addr:postcode":"04006",
    "addr:street":"Avda Mediterraneo Del",
    "iso:country":"ES",
    "sg:address":"Avda Mediterraneo (del), 294",
    "sg:city":"Almeria",
    "sg:orig_category":"Confecci\u00d3n (fabricaci\u00d3n, Al Por Mayor)",
    "sg:phone":"+34 950 22 80 25",
    "sg:postcode":"04006",
    "sg:province":"Almer\u00eda",
    "wof:name":"Estrada Garcia Gracia",
    "wof:placetype":"venue"
},
  "geometry": {"coordinates":[-2.4471490383,36.844165802],"type":"Point"}
}