{
  "type": "Feature",
  "properties": {
    "addr:full":"Rua Alfonso Senra, 117 Ordes La Coru\u00f1a 15680",
    "addr:housenumber":"117",
    "addr:postcode":"15680",
    "addr:street":"Rua Alfonso Senra;La Corun\u0303A",
    "iso:country":"ES",
    "sg:address":"Rua Alfonso Senra, 117",
    "sg:city":"Ordes",
    "sg:orig_category":"Ropa Para Se\u00d1oras Y Caballeros (al Por Menor)",
    "sg:phone":"+34 981 68 20 79",
    "sg:postcode":"15680",
    "sg:province":"La Coru\u00f1a",
    "wof:name":"Gonzalez Hernandez Aurelia",
    "wof:placetype":"venue"
},
  "geometry": {"coordinates":[-8.4072790146,43.0771408081],"type":"Point"}
}