{
  "type": "Feature",
  "properties": {
    "addr:full":"Carrer de Descartes, 2 Barcelona Barcelona 08006",
    "addr:housenumber":"2",
    "addr:postcode":"08006",
    "addr:street":"Carrer De Descartes",
    "iso:country":"ES",
    "sg:address":"Carrer de Descartes, 2",
    "sg:city":"Barcelona",
    "sg:orig_category":"Peluquer\u00cdas, Peluquer\u00cda Mixta",
    "sg:phone":"+34 932 09 01 28",
    "sg:postcode":"08006",
    "sg:province":"Barcelona",
    "wof:name":"Font Perramon Jose Maria",
    "wof:placetype":"venue"
},
  "geometry": {"coordinates":[2.1431269646,41.4004440308],"type":"Point"}
}