{
  "type": "Feature",
  "properties": {
    "iso:country":"ES",
    "sg:address":"Calle de Cantabria, 7",
    "sg:city":"Onda",
    "sg:orig_category":"Fabrica De Cer\u00c1micas",
    "sg:phone":"+34 964 60 26 43",
    "sg:postcode":"12200",
    "sg:province":"Castell\u00f3n",
    "wof:name":"I Relievi S.l.",
    "wof:placetype":"venue"
},
  "geometry": {"coordinates":[-0.2443726063,39.9661178589],"type":"Point"}
}