{
  "type": "Feature",
  "properties": {
    "addr:full":"Plaz Gracia (de), 2 Granada Granada 18002",
    "addr:housenumber":"2",
    "addr:postcode":"18002",
    "addr:street":"Plaz Gracia De",
    "iso:country":"ES",
    "sg:address":"Plaz Gracia (de), 2",
    "sg:city":"Granada",
    "sg:orig_category":"Ingeniero",
    "sg:phone":"+34 958 53 55 34",
    "sg:postcode":"18002",
    "sg:province":"Granada",
    "wof:name":"Uribe Contreras Ramon Fernando",
    "wof:placetype":"venue"
},
  "geometry": {"coordinates":[-3.6014740467,37.1748352051],"type":"Point"}
}