{
  "type": "Feature",
  "properties": {
    "iso:country":"ES",
    "sg:address":"A Pedra, S/n",
    "sg:city":"Nanton",
    "sg:orig_category":"Distribuci\u00d3n De Petr\u00d3leo Y Derivados",
    "sg:phone":"+34 981 71 82 25",
    "sg:postcode":"15149",
    "sg:province":"La Coru\u00f1a",
    "sg:website":"www.cepsa.es",
    "wof:name":"Gasuma S.l.",
    "wof:placetype":"venue"
},
  "geometry": {"coordinates":[-8.7374286652,42.9441757202],"type":"Point"}
}