{
  "type": "Feature",
  "properties": {
    "addr:full":"C/ Sant Antoni, 5 Cerdanyola Valles Barcelona 08290",
    "addr:housenumber":"5",
    "addr:postcode":"08290",
    "addr:street":"C / Sant Antoni;Valles Barcelona",
    "iso:country":"ES",
    "sg:address":"C/ Sant Antoni, 5",
    "sg:city":"Cerdanyola Valles",
    "sg:orig_category":"Mec\u00c1nico Del Autom\u00d3vil",
    "sg:phone":"+34 935 80 28 54",
    "sg:postcode":"08290",
    "sg:province":"Barcelona",
    "wof:name":"Priego Sanchez Rafael",
    "wof:placetype":"venue"
},
  "geometry": {"coordinates":[2.1379539967,41.491443634],"type":"Point"}
}