{
  "type": "Feature",
  "properties": {
    "addr:full":"Calle de Literato Gabriel Miro, 61 Valencia Valencia 46008",
    "addr:housenumber":"61",
    "addr:postcode":"46008",
    "addr:street":"Calle De Literato Gabriel Miro",
    "iso:country":"ES",
    "sg:address":"Calle de Literato Gabriel Miro, 61",
    "sg:city":"Valencia",
    "sg:orig_category":"Transportes Urbanos Y Regionales Para Personas",
    "sg:phone":"+34 963 85 16 69",
    "sg:postcode":"46008",
    "sg:province":"Valencia",
    "wof:name":"Ortega Martinez Pilar",
    "wof:placetype":"venue"
},
  "geometry": {"coordinates":[-0.392392993,39.4712028503],"type":"Point"}
}