{
  "type": "Feature",
  "properties": {
    "addr:full":"Calle de Titanio, 6 Torrejon Ardoz Madrid 28850",
    "addr:housenumber":"6",
    "addr:postcode":"28850",
    "addr:street":"Calle De Titanio",
    "iso:country":"ES",
    "sg:address":"Calle de Titanio, 6",
    "sg:city":"Torrejon Ardoz",
    "sg:orig_category":"Empresas De Pintura Y Revestimientos",
    "sg:phone":"+34 916 56 67 43",
    "sg:postcode":"28850",
    "sg:province":"Madrid",
    "wof:name":"Uceda Aplicaciones De Pintura",
    "wof:placetype":"venue"
},
  "geometry": {"coordinates":[-3.467443943,40.4460868835],"type":"Point"}
}