{
  "type": "Feature",
  "properties": {
    "iso:country":"ES",
    "sg:address":"Calle de Rio Jarama, 9",
    "sg:city":"Mostoles",
    "sg:orig_category":"M\u00c9dicos: Estomatolog\u00cda",
    "sg:phone":"+34 916 18 59 12",
    "sg:postcode":"28934",
    "sg:province":"Madrid",
    "wof:name":"Camargo Murillo Maria Luisa",
    "wof:placetype":"venue"
},
  "geometry": {"coordinates":[-3.8713099957,40.3174743652],"type":"Point"}
}