{
  "type": "Feature",
  "properties": {
    "iso:country":"ES",
    "sg:address":"Carretera Leon Collanzo, Km. 0026,0",
    "sg:city":"Matallana Torio",
    "sg:orig_category":"Distribuci\u00d3n De Petr\u00d3leo Y Derivados",
    "sg:phone":"+34 987 59 10 80",
    "sg:postcode":"24836",
    "sg:province":"Le\u00f3n",
    "sg:website":"www.cepsa.es",
    "wof:name":"Carbunor Torio S.l.",
    "wof:placetype":"venue"
},
  "geometry": {"coordinates":[-5.5344791412,42.8859596252],"type":"Point"}
}