{
  "type": "Feature",
  "properties": {
    "addr:full":"Calle de Navarra, 25 Castellon Castell\u00f3n 12002",
    "addr:housenumber":"25",
    "addr:postcode":"12002",
    "addr:street":"Calle De Navarra",
    "iso:country":"ES",
    "sg:address":"Calle de Navarra, 25",
    "sg:city":"Castellon",
    "sg:orig_category":"Ropa Para Ni\u00d1os (al Por Menor)",
    "sg:phone":"+34 964 21 27 68",
    "sg:postcode":"12002",
    "sg:province":"Castell\u00f3n",
    "wof:name":"Gil Leon Antonio",
    "wof:placetype":"venue"
},
  "geometry": {"coordinates":[-0.040031001,39.9842147827],"type":"Point"}
}