{
  "type": "Feature",
  "properties": {
    "iso:country":"ES",
    "sg:address":"Ctra Santiuste, S/n",
    "sg:city":"Nava Asuncion",
    "sg:orig_category":"Cr\u00cda De Animales",
    "sg:phone":"+34 921 58 05 17",
    "sg:postcode":"40450",
    "sg:province":"Segovia",
    "wof:name":"Ganadera El Cigue\u00f1al",
    "wof:placetype":"venue"
},
  "geometry": {"coordinates":[-4.4939489365,41.15599823],"type":"Point"}
}