{
  "type": "Feature",
  "properties": {
    "addr:full":"Ptge Autovia, 10 Prat Llobregat Barcelona 08820",
    "addr:housenumber":"10",
    "addr:postcode":"08820",
    "addr:street":"Ptge Autovia;Llobregat",
    "iso:country":"ES",
    "sg:address":"Ptge Autovia, 10",
    "sg:city":"Prat Llobregat",
    "sg:orig_category":"Negocio De Materiales De Construcci\u00d3n",
    "sg:phone":"+34 933 70 06 55",
    "sg:postcode":"08820",
    "sg:province":"Barcelona",
    "wof:name":"Materials De Construccio Pota Sud",
    "wof:placetype":"venue"
},
  "geometry": {"coordinates":[2.0931708813,41.3341522217],"type":"Point"}
}