{
  "type": "Feature",
  "properties": {
    "iso:country":"ES",
    "sg:address":"Armental, S/n",
    "sg:city":"Armental",
    "sg:orig_category":"Semiller\u00cdas",
    "sg:phone":"+34 985 47 34 50",
    "sg:postcode":"33719",
    "sg:province":"Asturias",
    "wof:name":"Norte Forestal S. A.",
    "wof:placetype":"venue"
},
  "geometry": {"coordinates":[-6.6598329544,43.5291023254],"type":"Point"}
}