{
  "type": "Feature",
  "properties": {
    "iso:country":"ES",
    "sg:address":"Carrer de Sant Pere, 23",
    "sg:city":"Olesa Montserrat",
    "sg:orig_category":"Inversiones",
    "sg:phone":"+34 937 78 97 97",
    "sg:postcode":"08640",
    "sg:province":"Barcelona",
    "wof:name":"Gonzalez Rodriguez Francesc Felix",
    "wof:placetype":"venue"
},
  "geometry": {"coordinates":[1.8980100155,41.5432815552],"type":"Point"}
}