{
  "type": "Feature",
  "properties": {
    "iso:country":"ES",
    "sg:address":"C/ Antonio Martinez Garcia, 9",
    "sg:city":"Elche",
    "sg:orig_category":"Maquinaria Para Industrias Diversas",
    "sg:phone":"+34 965 46 42 76",
    "sg:postcode":"03206",
    "sg:province":"Alicante",
    "wof:name":"Lledo Sanchez Antonio",
    "wof:placetype":"venue"
},
  "geometry": {"coordinates":[-0.7026879787,38.2713813782],"type":"Point"}
}