{
  "type": "Feature",
  "properties": {
    "addr:full":"Carrer de Flor De Nit, 1 Cornella Llobregat Barcelona 08940",
    "addr:housenumber":"1",
    "addr:postcode":"08940",
    "addr:street":"Carrer De Flor De Nit",
    "iso:country":"ES",
    "sg:address":"Carrer de Flor De Nit, 1",
    "sg:city":"Cornella Llobregat",
    "sg:orig_category":"Asesor\u00cda Fiscal Y Jur\u00cddica",
    "sg:phone":"+34 933 75 36 86",
    "sg:postcode":"08940",
    "sg:province":"Barcelona",
    "wof:name":"Miguel Briongos Jose Antonio",
    "wof:placetype":"venue"
},
  "geometry": {"coordinates":[2.0822238922,41.3590736389],"type":"Point"}
}