{
  "type": "Feature",
  "properties": {
    "iso:country":"ES",
    "sg:address":"Calle de Arriba, 43",
    "sg:city":"Puebla Sancho Perez",
    "sg:orig_category":"Productores Recolectores, Venta Directa De Vinos",
    "sg:phone":"+34 924 55 14 49",
    "sg:postcode":"06310",
    "sg:province":"Badajoz",
    "sg:website":"www.bodegastoribio.com",
    "wof:name":"Bodegas Toribio S.l.",
    "wof:placetype":"venue"
},
  "geometry": {"coordinates":[-6.3978981972,38.3967819214],"type":"Point"}
}