{
  "type": "Feature",
  "properties": {
    "iso:country":"ES",
    "sg:address":"Avda Cayetano Feu, S/n",
    "sg:city":"Ayamonte",
    "sg:orig_category":"Venta, Montaje De Neum\u00c1ticos",
    "sg:phone":"+34 959 32 17 31",
    "sg:postcode":"21400",
    "sg:province":"Huelva",
    "wof:name":"Rodriguez Romero Diego",
    "wof:placetype":"venue"
},
  "geometry": {"coordinates":[-7.394908905,37.2159500122],"type":"Point"}
}