{
  "type": "Feature",
  "properties": {
    "iso:country":"ES",
    "sg:address":"Calle de Horno, 12",
    "sg:city":"Albelda",
    "sg:orig_category":"Carnicer\u00cdas, Carnicer\u00cdas",
    "sg:phone":"+34 974 42 08 28",
    "sg:postcode":"22558",
    "sg:province":"Huesca",
    "wof:name":"Chicot Bria Vicente",
    "wof:placetype":"venue"
},
  "geometry": {"coordinates":[0.4587239921,41.8646087646],"type":"Point"}
}