{
  "type": "Feature",
  "properties": {
    "addr:full":"Calle de Fuente (la), S/n Erla Zaragoza 50611",
    "addr:postcode":"50611",
    "addr:street":"Calle De Fuente La S / N Erla",
    "iso:country":"ES",
    "sg:address":"Calle de Fuente (la), S/n",
    "sg:city":"Erla",
    "sg:orig_category":"Ba\u00d1os Y Duchas P\u00dablicos",
    "sg:phone":"+34 976 69 40 69",
    "sg:postcode":"50611",
    "sg:province":"Zaragoza",
    "wof:name":"Ayuntamiento De Erla",
    "wof:placetype":"venue"
},
  "geometry": {"coordinates":[-0.9477369785,42.1164321899],"type":"Point"}
}