{
  "type": "Feature",
  "properties": {
    "addr:full":"Pg Sant Joan, 127 Barcelona Barcelona 08037",
    "addr:housenumber":"127",
    "addr:postcode":"08037",
    "addr:street":"Pg Sant Joan",
    "iso:country":"ES",
    "sg:address":"Pg Sant Joan, 127",
    "sg:city":"Barcelona",
    "sg:orig_category":"Arquitectos",
    "sg:phone":"+34 932 07 16 05",
    "sg:postcode":"08037",
    "sg:province":"Barcelona",
    "wof:name":"Mascaro Zamora Maria Jose",
    "wof:placetype":"venue"
},
  "geometry": {"coordinates":[2.1673789024,41.400642395],"type":"Point"}
}