{
  "type": "Feature",
  "properties": {
    "iso:country":"ES",
    "sg:address":"Calle de Campoamor, 5",
    "sg:city":"Madrid",
    "sg:classifiers":[
        {
            "category":"Sports & Exercise",
            "subcategory":"Golf",
            "type":"Entertainment"
        }
    ],
    "sg:phone":"+34 913 08 27 79",
    "sg:postcode":"28004",
    "sg:province":"Madrid",
    "sg:tags":[
        "y",
        "de",
        "campos",
        "clases"
    ],
    "sg:website":"www.golfcampoamor.com",
    "wof:name":"Garciaestrada Garcia Juan Francisco",
    "wof:placetype":"venue"
},
  "geometry": {"coordinates":[-3.6960163116,40.4258041382],"type":"Point"}
}