{
  "type": "Feature",
  "properties": {
    "addr:full":"Ctra Nijar Alquian, 177 Alquian Almer\u00eda 04130",
    "addr:housenumber":"177",
    "addr:postcode":"04130",
    "addr:street":"Ctra Nijar Alquian;Almeri\u0301A",
    "iso:country":"ES",
    "sg:address":"Ctra Nijar Alquian, 177",
    "sg:city":"Alquian",
    "sg:orig_category":"Centros De Coordinaci\u00d3n",
    "sg:phone":"+34 950 60 03 06",
    "sg:postcode":"04130",
    "sg:province":"Almer\u00eda",
    "wof:name":"Infogest",
    "wof:placetype":"venue"
},
  "geometry": {"coordinates":[-2.3507189751,36.8520584106],"type":"Point"}
}