{
  "type": "Feature",
  "properties": {
    "iso:country":"ES",
    "sg:address":"Paris, 8",
    "sg:city":"Palmanova",
    "sg:orig_category":"Alquiler De V\u00cddeo",
    "sg:phone":"+34 971 68 00 30",
    "sg:postcode":"07181",
    "sg:province":"Islas Baleares",
    "wof:name":"Moore Moreno Sandra",
    "wof:placetype":"venue"
},
  "geometry": {"coordinates":[2.5309200287,39.5190963745],"type":"Point"}
}