{
  "type": "Feature",
  "properties": {
    "iso:country":"ES",
    "sg:address":"Ctra Villamarchante, 109",
    "sg:city":"Riba-roja Turia",
    "sg:orig_category":"Asesor\u00cda Fiscal Y Jur\u00cddica",
    "sg:phone":"+34 962 77 19 50",
    "sg:postcode":"46190",
    "sg:province":"Valencia",
    "sg:website":"www.qualitas.experience.com",
    "wof:name":"Qualitas Esperience S.l.",
    "wof:placetype":"venue"
},
  "geometry": {"coordinates":[-0.5716459751,39.5446052551],"type":"Point"}
}