{
  "type": "Feature",
  "properties": {
    "addr:full":"Carrer de Ausias Marc, 61 Barcelona Barcelona 08010",
    "addr:housenumber":"61",
    "addr:postcode":"08010",
    "addr:street":"Carrer De Ausias Marc",
    "iso:country":"ES",
    "sg:address":"Carrer de Ausias Marc, 61",
    "sg:city":"Barcelona",
    "sg:orig_category":"Administradores De Bienes Y Delegados De Comunidades De Propietarios",
    "sg:phone":"+34 932 32 60 61",
    "sg:postcode":"08010",
    "sg:province":"Barcelona",
    "wof:name":"Fraile Tor Javier",
    "wof:placetype":"venue"
},
  "geometry": {"coordinates":[2.1782100201,41.3934860229],"type":"Point"}
}