{
  "type": "Feature",
  "properties": {
    "iso:country":"ES",
    "sg:address":"Calle de Felix Rodriguez De La Fuente, 30",
    "sg:city":"Peligros",
    "sg:orig_category":"Alquiler De V\u00cddeo",
    "sg:phone":"+34 958 40 26 32",
    "sg:postcode":"18210",
    "sg:province":"Granada",
    "wof:name":"Entrena Gomez Francisco Javier",
    "wof:placetype":"venue"
},
  "geometry": {"coordinates":[-3.6289050579,37.2304954529],"type":"Point"}
}