{
  "type": "Feature",
  "properties": {
    "addr:full":"Pque Franchy Y Roca, 17 S.gregorio Las Palmas 35200",
    "addr:housenumber":"17",
    "addr:postcode":"35200",
    "addr:street":"S.Gregorio Las Palmas",
    "iso:country":"ES",
    "sg:address":"Pque Franchy Y Roca, 17",
    "sg:city":"S.gregorio",
    "sg:orig_category":"Promotores Constructores",
    "sg:phone":"+34 928 68 25 48",
    "sg:postcode":"35200",
    "sg:province":"Las Palmas",
    "wof:name":"Preconte S.l.",
    "wof:placetype":"venue"
},
  "geometry": {"coordinates":[-15.4144220352,28.0029888153],"type":"Point"}
}