{
  "type": "Feature",
  "properties": {
    "iso:country":"ES",
    "sg:address":"Calle de Mu\u00d1oz Cobos, 8",
    "sg:city":"Algeciras",
    "sg:orig_category":"Muebles, Minoristas",
    "sg:phone":"+34 956 66 49 77",
    "sg:postcode":"11201",
    "sg:province":"C\u00e1diz",
    "sg:website":"www.ka-international.com",
    "wof:name":"Rodriguez Allanegui S.l.",
    "wof:placetype":"venue"
},
  "geometry": {"coordinates":[-5.447824955,36.1308937073],"type":"Point"}
}