{
  "type": "Feature",
  "properties": {
    "addr:full":"Avda Rey Don Jaime, 80 Castellon Castell\u00f3n 12001",
    "addr:housenumber":"80",
    "addr:postcode":"12001",
    "addr:street":"Avda Rey Don Jaime",
    "iso:country":"ES",
    "sg:address":"Avda Rey Don Jaime, 80",
    "sg:city":"Castellon",
    "sg:orig_category":"Cajas De Ahorro",
    "sg:phone":"+34 964 25 26 24",
    "sg:postcode":"12001",
    "sg:province":"Castell\u00f3n",
    "sg:website":"www.lacaixa.es",
    "wof:name":"Caixa D'estalvis I Pensions De Barcelona",
    "wof:placetype":"venue"
},
  "geometry": {"coordinates":[-0.0390900001,39.9866714478],"type":"Point"}
}