{
  "type": "Feature",
  "properties": {
    "addr:full":"Calle de Rio Valdemarias, 21 Poligono Sta M. De Benquerencia Toledo 45007",
    "addr:housenumber":"21 poligono",
    "addr:postcode":"45007",
    "addr:street":"Calle De Rio Valdemarias;Sta M. De Benquerencia",
    "iso:country":"ES",
    "sg:address":"Calle de Rio Valdemarias, 21",
    "sg:city":"Poligono Sta M. De Benquerencia",
    "sg:orig_category":"Mudanzas",
    "sg:phone":"+34 925 23 17 13",
    "sg:postcode":"45007",
    "sg:province":"Toledo",
    "wof:name":"Sanchez-gabriel Aranda Felipe",
    "wof:placetype":"venue"
},
  "geometry": {"coordinates":[-3.9490039349,39.8686218262],"type":"Point"}
}