{
  "type": "Feature",
  "properties": {
    "iso:country":"ES",
    "sg:address":"Carr Emili Grahit, 63",
    "sg:city":"Girona",
    "sg:orig_category":"Venta, Alquiler De V\u00cddeo",
    "sg:phone":"+34 972 41 28 33",
    "sg:postcode":"17002",
    "sg:province":"Girona",
    "wof:name":"Engine Technology System S.l.",
    "wof:placetype":"venue"
},
  "geometry": {"coordinates":[2.8219189644,41.9747085571],"type":"Point"}
}