{
  "type": "Feature",
  "properties": {
    "iso:country":"ES",
    "sg:address":"Pg Rafael Soler, 42",
    "sg:city":"Vilafranca Penedes",
    "sg:orig_category":"Bordado, Marcado A Medida",
    "sg:phone":"+34 938 90 32 43",
    "sg:postcode":"08720",
    "sg:province":"Barcelona",
    "wof:name":"Miravalles Gonzalez Carlos Maria",
    "wof:placetype":"venue"
},
  "geometry": {"coordinates":[1.6973470449,41.3379631042],"type":"Point"}
}