{
  "type": "Feature",
  "properties": {
    "addr:full":"Pla\u00c7 Pou (del), 10 Agramunt Lleida 25310",
    "addr:postcode":"25310",
    "iso:country":"ES",
    "sg:address":"Pla\u00c7 Pou (del), 10",
    "sg:city":"Agramunt",
    "sg:orig_category":"Inform\u00c1tica: Material Y Suministros",
    "sg:phone":"+34 973 39 27 41",
    "sg:postcode":"25310",
    "sg:province":"Lleida",
    "wof:name":"Ona Gestio S.l.",
    "wof:placetype":"venue"
},
  "geometry": {"coordinates":[1.0938349962,41.7863693237],"type":"Point"}
}