{
  "type": "Feature",
  "properties": {
    "iso:country":"ES",
    "sg:address":"Calle de Gutierre De Cetina, 63",
    "sg:city":"Madrid",
    "sg:orig_category":"Molduras, Junquillos, Listones Y Molduras Perforadas",
    "sg:phone":"+34 913 68 14 86",
    "sg:postcode":"28017",
    "sg:province":"Madrid",
    "wof:name":"Cytasa Comunicaciones S.l.",
    "wof:placetype":"venue"
},
  "geometry": {"coordinates":[-3.6419930458,40.4311256409],"type":"Point"}
}