{
  "type": "Feature",
  "properties": {
    "iso:country":"ES",
    "sg:address":"Plaz Reloj, 6",
    "sg:city":"Nambroca",
    "sg:orig_category":"Quincaller\u00cda (al Por Menor)",
    "sg:phone":"+34 925 27 90 29",
    "sg:postcode":"45190",
    "sg:province":"Toledo",
    "wof:name":"Huertas Valencia Aniceta",
    "wof:placetype":"venue"
},
  "geometry": {"coordinates":[-3.9441618919,39.7990951538],"type":"Point"}
}