{
  "type": "Feature",
  "properties": {
    "iso:country":"ES",
    "sg:address":"Calle de Cueva De La Mora, 7",
    "sg:city":"Villaviciosa Odon",
    "sg:orig_category":"Cl\u00cdnicas Dentales",
    "sg:phone":"+34 916 65 91 01",
    "sg:postcode":"28670",
    "sg:province":"Madrid",
    "wof:name":"Luna Paredes Maria Jose",
    "wof:placetype":"venue"
},
  "geometry": {"coordinates":[-3.9075036049,40.3571128845],"type":"Point"}
}