{
  "type": "Feature",
  "properties": {
    "iso:country":"ES",
    "sg:address":"Calle de Colmillo, 6",
    "sg:city":"Cuenca",
    "sg:orig_category":"Ingeniero",
    "sg:phone":"+34 969 21 39 96",
    "sg:postcode":"16001",
    "sg:province":"Cuenca",
    "wof:name":"Cruz Garcia Eugenio",
    "wof:placetype":"venue"
},
  "geometry": {"coordinates":[-2.1295797825,40.0778961182],"type":"Point"}
}