{
  "type": "Feature",
  "properties": {
    "iso:country":"ES",
    "sg:address":"Calle de Coru\u00d1a (la), 19",
    "sg:city":"Alcala Henares",
    "sg:orig_category":"Molduras, Junquillos, Listones Y Molduras Perforadas",
    "sg:phone":"+34 918 81 62 89",
    "sg:postcode":"28804",
    "sg:province":"Madrid",
    "wof:name":"Lopez Alonso Julian",
    "wof:placetype":"venue"
},
  "geometry": {"coordinates":[-3.3538444042,40.4884223938],"type":"Point"}
}