{
  "type": "Feature",
  "properties": {
    "iso:country":"ES",
    "sg:address":"Carrer de Raspall, 4",
    "sg:city":"Altea",
    "sg:orig_category":"Ropa Para Se\u00d1oras Y Caballeros (al Por Menor)",
    "sg:phone":"+34 966 88 10 26",
    "sg:postcode":"03590",
    "sg:province":"Alicante",
    "wof:name":"Gomis Ponsoda S.l.",
    "wof:placetype":"venue"
},
  "geometry": {"coordinates":[-0.0455590002,38.6037750244],"type":"Point"}
}