{
  "type": "Feature",
  "properties": {
    "addr:full":"San Frantzisko Kalea, 9 Zarautz Guip\u00f9zcoa 20800",
    "addr:housenumber":"9",
    "addr:postcode":"20800",
    "addr:street":"San Frantzisko Kalea;Guipu\u0300Zcoa",
    "iso:country":"ES",
    "sg:address":"San Frantzisko Kalea, 9",
    "sg:city":"Zarautz",
    "sg:orig_category":"Agencias De Viajes",
    "sg:phone":"+34 943 83 29 53",
    "sg:postcode":"20800",
    "sg:province":"Guip\u00f9zcoa",
    "sg:website":"www.halconviajes.com",
    "wof:name":"Viajes Halcon S.a.",
    "wof:placetype":"venue"
},
  "geometry": {"coordinates":[-2.1738369465,43.2857780457],"type":"Point"}
}