{
  "type": "Feature",
  "properties": {
    "iso:country":"ES",
    "sg:address":"Calle de Jose Maria De Pereda, 43",
    "sg:city":"Sevilla",
    "sg:orig_category":"M\u00c1quinas De Coser Y De Hacer Punto (al Por Mayor)",
    "sg:phone":"+34 954 64 02 47",
    "sg:postcode":"41006",
    "sg:province":"Sevilla",
    "wof:name":"Singer Distribucion S.a.",
    "wof:placetype":"venue"
},
  "geometry": {"coordinates":[-5.9583201408,37.3722190857],"type":"Point"}
}