{
  "type": "Feature",
  "properties": {
    "addr:full":"Rua Cambre, 10 Gandara De Arriba A Coru\u00f1a 15407",
    "addr:housenumber":"10;corun\u0303a",
    "addr:postcode":"15407",
    "addr:street":"Rua Cambre;Arriba",
    "iso:country":"ES",
    "sg:address":"Rua Cambre, 10",
    "sg:city":"Gandara De Arriba",
    "sg:orig_category":"Molduras, Junquillos, Listones Y Molduras Perforadas",
    "sg:phone":"+34 981 38 02 91",
    "sg:postcode":"15407",
    "sg:province":"A Coru\u00f1a",
    "wof:name":"Suarez Diaz Carmen",
    "wof:placetype":"venue"
},
  "geometry": {"coordinates":[-8.1969175339,43.5052642822],"type":"Point"}
}