{
  "type": "Feature",
  "properties": {
    "addr:full":"Calle de Calderon De La Barca, 6 Alcala Henares Madrid 28805",
    "addr:housenumber":"6",
    "addr:postcode":"28805",
    "addr:street":"Calle De Calderon De La Barca",
    "iso:country":"ES",
    "sg:address":"Calle de Calderon De La Barca, 6",
    "sg:city":"Alcala Henares",
    "sg:orig_category":"Art\u00cdculos De Regalo (al Por Menor)",
    "sg:phone":"+34 918 82 87 91",
    "sg:postcode":"28805",
    "sg:province":"Madrid",
    "wof:name":"Serrano Serrano Pilar",
    "wof:placetype":"venue"
},
  "geometry": {"coordinates":[-3.3583528996,40.4891357422],"type":"Point"}
}