{
  "type": "Feature",
  "properties": {
    "iso:country":"ES",
    "sg:address":"Calle de Sierra Gorda, 36",
    "sg:city":"Madrid",
    "sg:orig_category":"Carnicer\u00cdas, Carnicer\u00cdas",
    "sg:phone":"+34 913 32 90 08",
    "sg:postcode":"28031",
    "sg:province":"Madrid",
    "wof:name":"Carnicas Sierra Gorda S.l.",
    "wof:placetype":"venue"
},
  "geometry": {"coordinates":[-3.618448019,40.3806343079],"type":"Point"}
}