{
  "type": "Feature",
  "properties": {
    "iso:country":"ES",
    "sg:address":"Carr Eres (de Les), 20",
    "sg:city":"Artesa Lleida",
    "sg:orig_category":"Refiner\u00cdas De Petr\u00d3leo",
    "sg:phone":"+34 973 16 72 92",
    "sg:postcode":"25150",
    "sg:province":"Lleida",
    "wof:name":"Distilde S.l.",
    "wof:placetype":"venue"
},
  "geometry": {"coordinates":[0.7057800293,41.5531044006],"type":"Point"}
}