{
  "type": "Feature",
  "properties": {
    "iso:country":"ES",
    "sg:address":"Afueras, S/n",
    "sg:city":"Cartaojal",
    "sg:orig_category":"Producci\u00d3n, Venta De Productos De Agricultura Biol\u00d3gica",
    "sg:phone":"+34 952 11 16 94",
    "sg:postcode":"29250",
    "sg:province":"M\u00e1laga",
    "wof:name":"Lora Sangran Hermanos S.cv.",
    "wof:placetype":"venue"
},
  "geometry": {"coordinates":[-4.5783290863,37.0727653503],"type":"Point"}
}