{
  "type": "Feature",
  "properties": {
    "iso:country":"ES",
    "sg:address":"Calle de Mudo, 1",
    "sg:city":"Torrecampo",
    "sg:orig_category":"Museos",
    "sg:phone":"+34 957 15 50 04",
    "sg:postcode":"14410",
    "sg:province":"C\u00f3rdoba",
    "wof:name":"Fundacion Prasa",
    "wof:placetype":"venue"
},
  "geometry": {"coordinates":[-4.6789832115,38.4751243591],"type":"Point"}
}