{
  "type": "Feature",
  "properties": {
    "addr:full":"Calle de Conchita Piquer, 8 Valencia Valencia 46015",
    "addr:postcode":"46015",
    "addr:street":"Calle De;Piquer;Valencia",
    "iso:country":"ES",
    "sg:address":"Calle de Conchita Piquer, 8",
    "sg:city":"Valencia",
    "sg:orig_category":"Librer\u00cdas",
    "sg:phone":"+34 963 49 23 30",
    "sg:postcode":"46015",
    "sg:province":"Valencia",
    "wof:name":"Valls Santos Jorge Juan",
    "wof:placetype":"venue"
},
  "geometry": {"coordinates":[-0.3915449977,39.4870643616],"type":"Point"}
}