{
  "type": "Feature",
  "properties": {
    "iso:country":"ES",
    "sg:address":"Calle de Angel Luis De La Herran, 7",
    "sg:city":"Madrid",
    "sg:orig_category":"Bisuter\u00cda, Joyer\u00cda, Relojer\u00cda (al Por Menor)",
    "sg:phone":"+34 913 82 15 90",
    "sg:postcode":"28043",
    "sg:province":"Madrid",
    "wof:name":"Garzon Montesinos Antonio",
    "wof:placetype":"venue"
},
  "geometry": {"coordinates":[-3.6503996849,40.4700088501],"type":"Point"}
}