{
  "type": "Feature",
  "properties": {
    "iso:country":"ES",
    "sg:address":"Calle de Torres, 18",
    "sg:city":"Archivel",
    "sg:orig_category":"Reposter\u00cdas",
    "sg:phone":"+34 968 72 51 08",
    "sg:postcode":"30195",
    "sg:province":"Murcia",
    "wof:name":"Lopez Torres Francisco",
    "wof:placetype":"venue"
},
  "geometry": {"coordinates":[-2.0067489147,38.0716896057],"type":"Point"}
}