{
  "type": "Feature",
  "properties": {
    "iso:country":"ES",
    "sg:address":"El Greco, 1",
    "sg:city":"Lebrija",
    "sg:orig_category":"Reposter\u00cdas",
    "sg:phone":"+34 955 97 43 04",
    "sg:postcode":"41740",
    "sg:province":"Sevilla",
    "wof:name":"Horno Nuestra Se\u00f1ora Del Rosario S.l.",
    "wof:placetype":"venue"
},
  "geometry": {"coordinates":[-6.0702381134,36.918712616],"type":"Point"}
}