{
  "type": "Feature",
  "properties": {
    "addr:full":"Calle de Husar Tiburcio, 8 Astorga Le\u00f3n 24700",
    "addr:housenumber":"8",
    "addr:postcode":"24700",
    "addr:street":"Calle De Husar Tiburcio;Leo\u0301N",
    "iso:country":"ES",
    "sg:address":"Calle de Husar Tiburcio, 8",
    "sg:city":"Astorga",
    "sg:orig_category":"Empresas De Carpinter\u00cda",
    "sg:phone":"+34 987 61 56 82",
    "sg:postcode":"24700",
    "sg:province":"Le\u00f3n",
    "wof:name":"Aluminios Toyde S.l",
    "wof:placetype":"venue"
},
  "geometry": {"coordinates":[-6.0599713326,42.4566040039],"type":"Point"}
}