{
  "type": "Feature",
  "properties": {
    "iso:country":"ES",
    "sg:address":"Calle de Rodriguez Marin, 54",
    "sg:city":"Madrid",
    "sg:orig_category":"Inmobiliaria (agencias)",
    "sg:phone":"+34 915 64 19 82",
    "sg:postcode":"28002",
    "sg:province":"Madrid",
    "wof:name":"Mar Y Casas Mediterraneas S.l.",
    "wof:placetype":"venue"
},
  "geometry": {"coordinates":[-3.6799631119,40.4471359253],"type":"Point"}
}