{
  "type": "Feature",
  "properties": {
    "iso:country":"ES",
    "sg:address":"Calle de Bachiller, El, 17",
    "sg:city":"Valencia",
    "sg:orig_category":"Agencias Y Agentes Comerciales, Representantes",
    "sg:phone":"+34 963 61 95 09",
    "sg:postcode":"46010",
    "sg:province":"Valencia",
    "wof:name":"Pouthier Pouthier Jackeline",
    "wof:placetype":"venue"
},
  "geometry": {"coordinates":[-0.3618843853,39.4820137024],"type":"Point"}
}