{
  "type": "Feature",
  "properties": {
    "addr:full":"C/ Cristobal Sanz, 78 Elche Alicante 03201",
    "addr:housenumber":"78",
    "addr:postcode":"03201",
    "addr:street":"C / Cristobal Sanz",
    "iso:country":"ES",
    "sg:address":"C/ Cristobal Sanz, 78",
    "sg:city":"Elche",
    "sg:orig_category":"Peluquer\u00cdas, Peluquer\u00cda Mixta",
    "sg:phone":"+34 965 44 79 08",
    "sg:postcode":"03201",
    "sg:province":"Alicante",
    "wof:name":"Conchi Jimenez S.l.",
    "wof:placetype":"venue"
},
  "geometry": {"coordinates":[-0.7033439875,38.2699050903],"type":"Point"}
}