{
  "type": "Feature",
  "properties": {
    "addr:full":"Carr Antoni Maura, 19 Lloseta Islas Baleares 07360",
    "addr:housenumber":"19",
    "addr:postcode":"07360",
    "addr:street":"Carr Antoni Maura",
    "iso:country":"ES",
    "sg:address":"Carr Antoni Maura, 19",
    "sg:city":"Lloseta",
    "sg:orig_category":"Ense\u00d1anza, Formaci\u00d3n Profesional: Aprendizaje",
    "sg:phone":"+34 971 51 94 82",
    "sg:postcode":"07360",
    "sg:province":"Islas Baleares",
    "wof:name":"Ib Salut",
    "wof:placetype":"venue"
},
  "geometry": {"coordinates":[2.8667809963,39.7176208496],"type":"Point"}
}