{
  "type": "Feature",
  "properties": {
    "iso:country":"ES",
    "sg:address":"Carrer de Bulnes, 7",
    "sg:city":"Palma",
    "sg:orig_category":"Centros De Educaci\u00d3n Especial",
    "sg:phone":"+34 971 47 57 91",
    "sg:postcode":"07008",
    "sg:province":"Islas Baleares",
    "wof:name":"Centro De Educacion Infantil Popeye Baby",
    "wof:placetype":"venue"
},
  "geometry": {"coordinates":[2.6865620613,39.5944290161],"type":"Point"}
}