{
  "type": "Feature",
  "properties": {
    "iso:country":"ES",
    "sg:address":"Carrer de Llobregat, 8",
    "sg:city":"Piera",
    "sg:orig_category":"Carnicer\u00cdas, Carnicer\u00cdas",
    "sg:phone":"+34 937 76 06 94",
    "sg:postcode":"08784",
    "sg:province":"Barcelona",
    "wof:name":"Ponnou Casanovas Josep",
    "wof:placetype":"venue"
},
  "geometry": {"coordinates":[1.751085043,41.5216064453],"type":"Point"}
}