{
  "type": "Feature",
  "properties": {
    "iso:country":"ES",
    "sg:address":"Avda Ciudad Jardin (la), 2",
    "sg:city":"Sevilla",
    "sg:orig_category":"Droguer\u00cdas (al Por Menor)",
    "sg:phone":"+34 954 93 33 92",
    "sg:postcode":"41005",
    "sg:province":"Sevilla",
    "wof:name":"Sevillana De Pinturas S.l.",
    "wof:placetype":"venue"
},
  "geometry": {"coordinates":[-5.965857029,37.3811569214],"type":"Point"}
}