{
  "type": "Feature",
  "properties": {
    "addr:full":"Carrer de Calabria, 69 Barcelona Barcelona 08015",
    "addr:housenumber":"69",
    "addr:postcode":"08015",
    "addr:street":"Carrer De Calabria",
    "iso:country":"ES",
    "sg:address":"Carrer de Calabria, 69",
    "sg:city":"Barcelona",
    "sg:orig_category":"Ortopedia General",
    "sg:phone":"+34 933 25 90 36",
    "sg:postcode":"08015",
    "sg:province":"Barcelona",
    "wof:name":"Garcia Lopez Daniel",
    "wof:placetype":"venue"
},
  "geometry": {"coordinates":[2.1569030285,41.378074646],"type":"Point"}
}