{
  "type": "Feature",
  "properties": {
    "iso:country":"ES",
    "sg:address":"Carrer de Nord, 32",
    "sg:city":"Viladecans",
    "sg:orig_category":"Electricidad: Instaladores",
    "sg:phone":"+34 936 47 40 02",
    "sg:postcode":"08840",
    "sg:province":"Barcelona",
    "wof:name":"Instalaciones Doguer S.l.",
    "wof:placetype":"venue"
},
  "geometry": {"coordinates":[2.0122048855,41.3210144043],"type":"Point"}
}