{
  "type": "Feature",
  "properties": {
    "iso:country":"ES",
    "sg:address":"Rua Sobran, S/n",
    "sg:city":"Vilaxoan",
    "sg:orig_category":"Suministros Para Exposiciones, Ferias, Salones",
    "sg:phone":"+34 986 51 02 87",
    "sg:postcode":"36611",
    "sg:province":"Pontevedra",
    "wof:name":"Galdrid Cv.",
    "wof:placetype":"venue"
},
  "geometry": {"coordinates":[-8.7828540802,42.5872116089],"type":"Point"}
}