{
  "type": "Feature",
  "properties": {
    "iso:country":"ES",
    "sg:address":"Calle de Inspector Luis Martin, 11",
    "sg:city":"Arrecife",
    "sg:orig_category":"Librer\u00cdas",
    "sg:phone":"+34 928 81 51 07",
    "sg:postcode":"35500",
    "sg:province":"Las Palmas",
    "wof:name":"Ruiz Gallego Norberto",
    "wof:placetype":"venue"
},
  "geometry": {"coordinates":[-13.5477304459,28.959154129],"type":"Point"}
}