{
  "type": "Feature",
  "properties": {
    "addr:full":"Calle de Soledad, 10 Puertollano Ciudad Real 13500",
    "addr:housenumber":"10",
    "addr:postcode":"13500",
    "addr:street":"Calle De Soledad",
    "iso:country":"ES",
    "sg:address":"Calle de Soledad, 10",
    "sg:city":"Puertollano",
    "sg:orig_category":"Asociaciones Humanitarias, De Cooperaci\u00d3n, De Acci\u00d3n Social",
    "sg:phone":"+34 926 41 50 10",
    "sg:postcode":"13500",
    "sg:province":"Ciudad Real",
    "wof:name":"Caritas Interparroquial",
    "wof:placetype":"venue"
},
  "geometry": {"coordinates":[-4.1096138954,38.6860275269],"type":"Point"}
}