{
  "type": "Feature",
  "properties": {
    "addr:full":"Plaz Serrano Berges (santa Isabel), 2 Zaragoza Zaragoza 50016",
    "addr:postcode":"50016",
    "addr:street":"Plaz Serrano Berges Santa Isabel",
    "iso:country":"ES",
    "sg:address":"Plaz Serrano Berges (santa Isabel), 2",
    "sg:city":"Zaragoza",
    "sg:orig_category":"Molduras, Junquillos, Listones Y Molduras Perforadas",
    "sg:phone":"+34 976 57 20 57",
    "sg:postcode":"50016",
    "sg:province":"Zaragoza",
    "wof:name":"Telefonos Publicos De Aragon S.l.",
    "wof:placetype":"venue"
},
  "geometry": {"coordinates":[-0.8317620158,41.6671485901],"type":"Point"}
}