{
  "type": "Feature",
  "properties": {
    "addr:full":"Carrer de Murcia, 54 S. Boi Llobregat Barcelona 08830",
    "addr:housenumber":"54",
    "addr:postcode":"08830",
    "addr:street":"Carrer De Murcia",
    "iso:country":"ES",
    "sg:address":"Carrer de Murcia, 54",
    "sg:city":"S. Boi Llobregat",
    "sg:orig_category":"Artes Gr\u00c1ficas, Artes Pl\u00c1sticas (curso)",
    "sg:phone":"+34 936 52 14 18",
    "sg:postcode":"08830",
    "sg:province":"Barcelona",
    "sg:website":"www.graficas-signo.com",
    "wof:name":"Signo Impressio Grafica S.a",
    "wof:placetype":"venue"
},
  "geometry": {"coordinates":[2.0402610302,41.3273925781],"type":"Point"}
}