{
  "type": "Feature",
  "properties": {
    "addr:full":"Urb Nueva Hacienda Dos Mares, S/n Manga Mar Menor Murcia 30380",
    "addr:housenumber":"s / n",
    "addr:postcode":"30380",
    "addr:street":"Urb;Hacienda Dos Mares",
    "iso:country":"ES",
    "sg:address":"Urb Nueva Hacienda Dos Mares, S/n",
    "sg:city":"Manga Mar Menor",
    "sg:orig_category":"Sanatorios M\u00c9dico",
    "sg:phone":"+34 968 14 20 60",
    "sg:postcode":"30380",
    "sg:province":"Murcia",
    "wof:name":"Servicio Murciano De Salud Centros Provinciales",
    "wof:placetype":"venue"
},
  "geometry": {"coordinates":[-0.7281540036,37.6686553955],"type":"Point"}
}