{
  "type": "Feature",
  "properties": {
    "addr:full":"C/ Pintor Marsa, 13 Tarrega Lleida 25300",
    "addr:housenumber":"13",
    "addr:postcode":"25300",
    "addr:street":"C / Pintor Marsa",
    "iso:country":"ES",
    "sg:address":"C/ Pintor Marsa, 13",
    "sg:city":"Tarrega",
    "sg:orig_category":"Agencias Y Agentes Comerciales, Representantes",
    "sg:phone":"+34 973 50 20 70",
    "sg:postcode":"25300",
    "sg:province":"Lleida",
    "wof:name":"Argiles Gomez S.l.",
    "wof:placetype":"venue"
},
  "geometry": {"coordinates":[1.1459368467,41.6428070068],"type":"Point"}
}