{
  "type": "Feature",
  "properties": {
    "addr:full":"Calle de Virgen Morena, 12 Almeria Almer\u00eda 04009",
    "addr:housenumber":"12",
    "addr:postcode":"04009",
    "addr:street":"Calle De Virgen Morena",
    "iso:country":"ES",
    "sg:address":"Calle de Virgen Morena, 12",
    "sg:city":"Almeria",
    "sg:orig_category":"Transporte En General",
    "sg:phone":"+34 950 22 22 42",
    "sg:postcode":"04009",
    "sg:province":"Almer\u00eda",
    "wof:name":"Martinez Lopez Isabel",
    "wof:placetype":"venue"
},
  "geometry": {"coordinates":[-2.431137085,36.8477210999],"type":"Point"}
}