{
  "type": "Feature",
  "properties": {
    "addr:full":"Carr Girona, 5 Figueres Girona 17600",
    "addr:housenumber":"5",
    "addr:postcode":"17600",
    "addr:street":"Carr Girona",
    "iso:country":"ES",
    "sg:address":"Carr Girona, 5",
    "sg:city":"Figueres",
    "sg:orig_category":"Ropa Para Se\u00d1oras Y Caballeros (al Por Menor)",
    "sg:phone":"+34 972 67 40 21",
    "sg:postcode":"17600",
    "sg:province":"Girona",
    "wof:name":"Tornassol S.c.",
    "wof:placetype":"venue"
},
  "geometry": {"coordinates":[2.9612760544,42.2671928406],"type":"Point"}
}