{
  "type": "Feature",
  "properties": {
    "iso:country":"ES",
    "sg:address":"Calle de Gerion, 31",
    "sg:city":"Chiclana De La Frontera",
    "sg:orig_category":"Procuradores",
    "sg:phone":"+34 956 40 33 95",
    "sg:postcode":"11130",
    "sg:province":"C\u00e1diz",
    "wof:name":"Romero Perez Maria De Los Santos",
    "wof:placetype":"venue"
},
  "geometry": {"coordinates":[-6.1579999924,36.4128761292],"type":"Point"}
}