{
  "type": "Feature",
  "properties": {
    "addr:full":"Carr Bajoli, 56 Poima Islas Baleares 07714",
    "addr:housenumber":"56",
    "addr:postcode":"07714",
    "addr:street":"Carr Bajoli",
    "iso:country":"ES",
    "sg:address":"Carr Bajoli, 56",
    "sg:city":"Poima",
    "sg:classifiers":[
        {
            "category":"Manufacturing",
            "subcategory":"Metals",
            "type":"Manufacturing & Wholesale Goods"
        }
    ],
    "sg:phone":"+34 971 36 27 30",
    "sg:postcode":"07714",
    "sg:province":"Islas Baleares",
    "sg:tags":[
        "en",
        "fundiciones"
    ],
    "wof:name":"Vanrell Olives Francisco",
    "wof:placetype":"venue"
},
  "geometry": {"coordinates":[2.9117100239,39.6136398315],"type":"Point"}
}