{
  "type": "Feature",
  "properties": {
    "iso:country":"ES",
    "sg:address":"Cami Ral, 526",
    "sg:city":"Mataro",
    "sg:orig_category":"Fabricaci\u00d3n, Importaci\u00d3n, Venta De Material De Telefon\u00cda, Peritelefon\u00cda",
    "sg:phone":"+34 937 41 52 47",
    "sg:postcode":"08302",
    "sg:province":"Barcelona",
    "sg:website":"www.amena.com",
    "wof:name":"Proactiva 3 G Telecom S.l.",
    "wof:placetype":"venue"
},
  "geometry": {"coordinates":[2.4408171177,41.5347328186],"type":"Point"}
}