{
  "type": "Feature",
  "properties": {
    "addr:full":"Carr Sant Vicent Ferrer, S/n Catarroja Valencia 46470",
    "addr:housenumber":"s / n",
    "addr:postcode":"46470",
    "addr:street":"Carr Sant Vicent Ferrer",
    "iso:country":"ES",
    "sg:address":"Carr Sant Vicent Ferrer, S/n",
    "sg:city":"Catarroja",
    "sg:orig_category":"Pintura, Barniz, Productos Asimilables (fabricaci\u00d3n, Al Por Mayor)",
    "sg:phone":"+34 961 26 21 07",
    "sg:postcode":"46470",
    "sg:province":"Valencia",
    "wof:name":"Barnices Rioja S.a.",
    "wof:placetype":"venue"
},
  "geometry": {"coordinates":[-0.4062890112,39.4088363647],"type":"Point"}
}