{
  "type": "Feature",
  "properties": {
    "addr:full":"Calle de Gallos, 22 Sevilla Sevilla 41003",
    "addr:housenumber":"22",
    "addr:postcode":"41003",
    "addr:street":"Calle De Gallos",
    "iso:country":"ES",
    "sg:address":"Calle de Gallos, 22",
    "sg:city":"Sevilla",
    "sg:orig_category":"M\u00c9dicos: Oftalmolog\u00cda",
    "sg:phone":"+34 954 21 81 50",
    "sg:postcode":"41003",
    "sg:province":"Sevilla",
    "wof:name":"Escolar Gonzalez Jose Antonio",
    "wof:placetype":"venue"
},
  "geometry": {"coordinates":[-5.9849891663,37.3941802979],"type":"Point"}
}