{
  "type": "Feature",
  "properties": {
    "addr:full":"Calle de Ecuador, 7 Toledo Toledo 45004",
    "addr:housenumber":"7",
    "addr:postcode":"45004",
    "addr:street":"Calle De Ecuador",
    "iso:country":"ES",
    "sg:address":"Calle de Ecuador, 7",
    "sg:city":"Toledo",
    "sg:orig_category":"Bosques (trabajos, Asesor\u00cda, Gesti\u00d3n)",
    "sg:phone":"+34 925 22 42 48",
    "sg:postcode":"45004",
    "sg:province":"Toledo",
    "wof:name":"Floranova S. L.",
    "wof:placetype":"venue"
},
  "geometry": {"coordinates":[-4.0300297737,39.8667564392],"type":"Point"}
}