{
  "type": "Feature",
  "properties": {
    "iso:country":"ES",
    "sg:address":"Calle de Meridiano, 20",
    "sg:city":"Torrejon Ardoz",
    "sg:orig_category":"Papel (al Por Mayor)",
    "sg:phone":"+34 916 75 45 06",
    "sg:postcode":"28850",
    "sg:province":"Madrid",
    "wof:name":"Manipulados Trebol S.a.",
    "wof:placetype":"venue"
},
  "geometry": {"coordinates":[-3.4799220562,40.4511528015],"type":"Point"}
}