{
  "type": "Feature",
  "properties": {
    "addr:full":"Avda Bondad (de La), 12 Caceres C\u00e1ceres 10002",
    "addr:housenumber":"12",
    "addr:postcode":"10002",
    "addr:street":"Avda Bondad De La;Ca\u0301Ceres",
    "iso:country":"ES",
    "sg:address":"Avda Bondad (de La), 12",
    "sg:city":"Caceres",
    "sg:orig_category":"Pescader\u00cdas (al Por Menor)",
    "sg:phone":"+34 927 24 14 46",
    "sg:postcode":"10002",
    "sg:province":"C\u00e1ceres",
    "wof:name":"Castellano Castela Fernando",
    "wof:placetype":"venue"
},
  "geometry": {"coordinates":[-6.3751940727,39.4620170593],"type":"Point"}
}