{
  "type": "Feature",
  "properties": {
    "iso:country":"ES",
    "sg:address":"Av Pau (de La), 30",
    "sg:city":"Calaf",
    "sg:orig_category":"Empresarios Y Productoras De Espect\u00c1culos",
    "sg:phone":"+34 938 69 87 90",
    "sg:postcode":"08280",
    "sg:province":"Barcelona",
    "wof:name":"Union Calafina",
    "wof:placetype":"venue"
},
  "geometry": {"coordinates":[1.5125449896,41.7326812744],"type":"Point"}
}