{
  "type": "Feature",
  "properties": {
    "addr:full":"Carr Major, 24 Felanitx Islas Baleares 07200",
    "addr:housenumber":"24",
    "addr:postcode":"07200",
    "addr:street":"Carr Major",
    "iso:country":"ES",
    "sg:address":"Carr Major, 24",
    "sg:city":"Felanitx",
    "sg:orig_category":"\u00d3ptica: Instrumentos (fabricaci\u00d3n)",
    "sg:phone":"+34 971 58 33 42",
    "sg:postcode":"07200",
    "sg:province":"Islas Baleares",
    "wof:name":"King Crimson S.l.",
    "wof:placetype":"venue"
},
  "geometry": {"coordinates":[3.1489768028,39.468585968],"type":"Point"}
}