{
  "type": "Feature",
  "properties": {
    "iso:country":"ES",
    "sg:address":"Carrer de Balmes, 228",
    "sg:city":"Barcelona",
    "sg:orig_category":"Abogados",
    "sg:phone":"+34 932 38 59 41",
    "sg:postcode":"08006",
    "sg:province":"Barcelona",
    "wof:name":"Bufete Rafael Castilla Scp",
    "wof:placetype":"venue"
},
  "geometry": {"coordinates":[2.1511011124,41.3988227844],"type":"Point"}
}