{
  "type": "Feature",
  "properties": {
    "addr:full":"Rbla Principal, 1 Vilanova I La Geltru Barcelona 08800",
    "addr:housenumber":"1",
    "addr:postcode":"08800",
    "addr:street":"Rbla Principal",
    "iso:country":"ES",
    "sg:address":"Rbla Principal, 1",
    "sg:city":"Vilanova I La Geltru",
    "sg:orig_category":"Laboratorios Y Trabajos De Fotograf\u00cda, V\u00cddeo Y Cine",
    "sg:phone":"+34 938 93 93 52",
    "sg:postcode":"08800",
    "sg:province":"Barcelona",
    "sg:website":"www.fotoprix.es",
    "wof:name":"Josep Maria Pallas S.l.",
    "wof:placetype":"venue"
},
  "geometry": {"coordinates":[1.7237850428,41.2257080078],"type":"Point"}
}