{
  "type": "Feature",
  "properties": {
    "addr:full":"Calle de Cruz De Piedra, 1 Alacant Alicante 03015",
    "addr:housenumber":"1",
    "addr:postcode":"03015",
    "addr:street":"Calle De Cruz De Piedra",
    "iso:country":"ES",
    "sg:address":"Calle de Cruz De Piedra, 1",
    "sg:city":"Alacant",
    "sg:orig_category":"Internados & Ense\u00d1anza Privada",
    "sg:phone":"+34 965 26 20 00",
    "sg:postcode":"03015",
    "sg:province":"Alicante",
    "wof:name":"Institucion Teresiana Asociacion Civil",
    "wof:placetype":"venue"
},
  "geometry": {"coordinates":[-0.4621149004,38.3639450073],"type":"Point"}
}