{
  "type": "Feature",
  "properties": {
    "addr:full":"Calle de Salvador Pechuan, 12 Catarroja Valencia 46470",
    "addr:housenumber":"12",
    "addr:postcode":"46470",
    "addr:street":"Calle De Salvador Pechuan",
    "iso:country":"ES",
    "sg:address":"Calle de Salvador Pechuan, 12",
    "sg:city":"Catarroja",
    "sg:orig_category":"Panader\u00cdas, Panader\u00cdas",
    "sg:phone":"+34 961 26 17 91",
    "sg:postcode":"46470",
    "sg:province":"Valencia",
    "wof:name":"Panet Sociedad Cooperativa Valenciana",
    "wof:placetype":"venue"
},
  "geometry": {"coordinates":[-0.4007419944,39.4021453857],"type":"Point"}
}