{
  "type": "Feature",
  "properties": {
    "iso:country":"ES",
    "sg:address":"Calle de Manuel Laguna, 6",
    "sg:city":"Madrid",
    "sg:orig_category":"Empresas De Carpinter\u00cda De Madera",
    "sg:phone":"+34 915 07 55 53",
    "sg:postcode":"28018",
    "sg:province":"Madrid",
    "wof:name":"Marin Perez Juan",
    "wof:placetype":"venue"
},
  "geometry": {"coordinates":[-3.6643259525,40.3826560974],"type":"Point"}
}