{
  "type": "Feature",
  "properties": {
    "addr:full":"Av Jaume I, 6 Sant Joan D'alacant Alicante 03550",
    "addr:housenumber":"6",
    "addr:postcode":"03550",
    "addr:street":"Av Jaume I",
    "iso:country":"ES",
    "sg:address":"Av Jaume I, 6",
    "sg:city":"Sant Joan D'alacant",
    "sg:orig_category":"Ropa Para Se\u00d1oras (al Por Menor)",
    "sg:phone":"+34 965 94 05 92",
    "sg:postcode":"03550",
    "sg:province":"Alicante",
    "wof:name":"Serna \u00d1iguez Maria De La Concepcion",
    "wof:placetype":"venue"
},
  "geometry": {"coordinates":[-0.4973970056,38.3658714294],"type":"Point"}
}