{
  "type": "Feature",
  "properties": {
    "iso:country":"ES",
    "sg:address":"Calle de Doctor Fleming, 7",
    "sg:city":"Pozoblanco",
    "sg:classifiers":[
        {
            "category":"Autos & Motor Vehicles",
            "subcategory":"Automobile Sales",
            "type":"Retail Goods"
        }
    ],
    "sg:phone":"+34 957 77 12 56",
    "sg:postcode":"14400",
    "sg:province":"C\u00f3rdoba",
    "wof:name":"Auto-escuela Virgen De Luna S.l.",
    "wof:placetype":"venue"
},
  "geometry": {"coordinates":[-4.8459701538,38.3778305054],"type":"Point"}
}