{
  "type": "Feature",
  "properties": {
    "addr:full":"Calle de San Luis, 20 Camas Sevilla 41900",
    "addr:housenumber":"20",
    "addr:postcode":"41900",
    "addr:street":"Calle De San Luis",
    "iso:country":"ES",
    "sg:address":"Calle de San Luis, 20",
    "sg:city":"Camas",
    "sg:orig_category":"Asociaciones, Organismos Culturales Y Socioeducativos",
    "sg:phone":"+34 954 39 18 05",
    "sg:postcode":"41900",
    "sg:province":"Sevilla",
    "wof:name":"Hermandad Del Gran Poder",
    "wof:placetype":"venue"
},
  "geometry": {"coordinates":[-6.0329642296,37.4021072388],"type":"Point"}
}