{
  "type": "Feature",
  "properties": {
    "addr:full":"Calle de Medico Manero Molla, 16 Alacant Alicante 03001",
    "addr:housenumber":"16",
    "addr:postcode":"03001",
    "addr:street":"Calle De Medico Manero Molla",
    "iso:country":"ES",
    "sg:address":"Calle de Medico Manero Molla, 16",
    "sg:city":"Alacant",
    "sg:orig_category":"Abogados",
    "sg:phone":"+34 965 20 65 47",
    "sg:postcode":"03001",
    "sg:province":"Alicante",
    "wof:name":"Collado Vives Luis Miguel",
    "wof:placetype":"venue"
},
  "geometry": {"coordinates":[-0.4845829904,38.3439407349],"type":"Point"}
}