{
  "type": "Feature",
  "properties": {
    "iso:country":"ES",
    "sg:address":"Avda Agirre Lehendakaria, 30",
    "sg:city":"Basauri",
    "sg:orig_category":"Reciclaje, Tratamiento De Tejidos",
    "sg:phone":"+34 944 40 03 14",
    "sg:postcode":"48970",
    "sg:province":"Vizcaya",
    "wof:name":"Bego\u00f1a Gonzalez  A\u00f1on (telas Bego)",
    "wof:placetype":"venue"
},
  "geometry": {"coordinates":[-2.8889539242,43.2372322083],"type":"Point"}
}