{
  "type": "Feature",
  "properties": {
    "iso:country":"ES",
    "sg:address":"Pje El Torico, 7",
    "sg:city":"Teruel",
    "sg:orig_category":"Laboratorios Y Trabajos De Fotograf\u00cda, V\u00cddeo Y Cine",
    "sg:phone":"+34 978 61 03 11",
    "sg:postcode":"44001",
    "sg:province":"Teruel",
    "wof:name":"Gimenez Y Mu\u00f1oz S.l.",
    "wof:placetype":"venue"
},
  "geometry": {"coordinates":[-1.1045490503,40.3420944214],"type":"Point"}
}