{
  "type": "Feature",
  "properties": {
    "iso:country":"ES",
    "sg:address":"Dism Isla Molino Pan, S/n",
    "sg:city":"Puebla Cazalla",
    "sg:orig_category":"F\u00c1bricas De Ladrillo Y Tejas",
    "sg:phone":"+34 954 84 62 00",
    "sg:postcode":"41540",
    "sg:province":"Sevilla",
    "wof:name":"Cooperativa Nuestra Se\u00f1ora Del Perpetuo Socorro",
    "wof:placetype":"venue"
},
  "geometry": {"coordinates":[-5.3132190704,37.2229957581],"type":"Point"}
}