{
  "type": "Feature",
  "properties": {
    "iso:country":"ES",
    "sg:address":"Carrer de Enamorats, 1",
    "sg:city":"Santa Coloma De Gramenet",
    "sg:orig_category":"Molduras, Junquillos, Listones Y Molduras Perforadas",
    "sg:phone":"+34 934 68 05 01",
    "sg:postcode":"08921",
    "sg:province":"Barcelona",
    "wof:name":"Rider Criado Maria Dolores",
    "wof:placetype":"venue"
},
  "geometry": {"coordinates":[2.2127900124,41.4540634155],"type":"Point"}
}