{
  "type": "Feature",
  "properties": {
    "iso:country":"ES",
    "sg:address":"Av Frederic Rahola, 42",
    "sg:city":"Barcelona",
    "sg:orig_category":"Centros De Salud",
    "sg:phone":"+34 933 58 17 07",
    "sg:postcode":"08032",
    "sg:province":"Barcelona",
    "wof:name":"Cooperativa Industrial De Promocion Obrera Barcanova",
    "wof:placetype":"venue"
},
  "geometry": {"coordinates":[2.1674480438,41.4250564575],"type":"Point"}
}