{
  "type": "Feature",
  "properties": {
    "addr:full":"Calle de Toledo, 41 Cabezas S. Juan Sevilla 41730",
    "addr:housenumber":"41",
    "addr:postcode":"41730",
    "addr:street":"Calle De Toledo;S.",
    "iso:country":"ES",
    "sg:address":"Calle de Toledo, 41",
    "sg:city":"Cabezas S. Juan",
    "sg:orig_category":"Promotores Constructores",
    "sg:phone":"+34 955 87 04 64",
    "sg:postcode":"41730",
    "sg:province":"Sevilla",
    "wof:name":"Sanjuan Puente Antonio",
    "wof:placetype":"venue"
},
  "geometry": {"coordinates":[-5.9310240746,36.9824943542],"type":"Point"}
}