{
  "type": "Feature",
  "properties": {
    "iso:country":"ES",
    "sg:address":"Urb Nueva Bellavista, 5",
    "sg:city":"Sevilla",
    "sg:orig_category":"Supermercados Y Hipermercados",
    "sg:phone":"+34 954 69 23 30",
    "sg:postcode":"41014",
    "sg:province":"Sevilla",
    "wof:name":"Auna Telecomunicaciones S.a.u.",
    "wof:placetype":"venue"
},
  "geometry": {"coordinates":[-5.9679789543,37.3165817261],"type":"Point"}
}