{
  "type": "Feature",
  "properties": {
    "iso:country":"ES",
    "sg:address":"Calle de San Jose, 12",
    "sg:city":"Pto Real",
    "sg:orig_category":"Agencias Y Agentes Comerciales, Representantes",
    "sg:phone":"+34 956 47 49 61",
    "sg:postcode":"11510",
    "sg:province":"C\u00e1diz",
    "wof:name":"Ramos Patron Jose",
    "wof:placetype":"venue"
},
  "geometry": {"coordinates":[-6.1885519028,36.5291175842],"type":"Point"}
}