{
  "type": "Feature",
  "properties": {
    "addr:full":"Calle de Padre Damian, 29 Madrid Madrid 28036",
    "addr:housenumber":"29",
    "addr:postcode":"madrid;28036",
    "addr:street":"Calle De Padre Damian",
    "iso:country":"ES",
    "sg:address":"Calle de Padre Damian, 29",
    "sg:city":"Madrid",
    "sg:orig_category":"M\u00c9dicos: Pediatr\u00cda. Enfermedades De Los Ni\u00d1os",
    "sg:phone":"+34 913 45 02 33",
    "sg:postcode":"28036",
    "sg:province":"Madrid",
    "wof:name":"Pazos Ruiz Mateos Federico",
    "wof:placetype":"venue"
},
  "geometry": {"coordinates":[-3.6855580807,40.4605026245],"type":"Point"}
}