{
  "type": "Feature",
  "properties": {
    "addr:full":"Calle de Doctor Jose-m.sarget, 27 Orihuela Alicante 03300",
    "addr:housenumber":"27",
    "addr:postcode":"03300",
    "addr:street":"Calle De Doctor Jose-M.Sarget",
    "iso:country":"ES",
    "sg:address":"Calle de Doctor Jose-m.sarget, 27",
    "sg:city":"Orihuela",
    "sg:orig_category":"Maquinaria Para Industrias Diversas",
    "sg:phone":"+34 965 30 31 72",
    "sg:postcode":"03300",
    "sg:province":"Alicante",
    "wof:name":"Tequifer S.l.",
    "wof:placetype":"venue"
},
  "geometry": {"coordinates":[-0.9533984065,38.0698738098],"type":"Point"}
}