{
  "type": "Feature",
  "properties": {
    "iso:country":"ES",
    "sg:address":"Plaz Escribano (del), S/n",
    "sg:city":"Torreguadiaro",
    "sg:orig_category":"Complementos De Vestir (al Por Menor)",
    "sg:phone":"+34 956 61 03 43",
    "sg:postcode":"11312",
    "sg:province":"C\u00e1diz",
    "wof:name":"Franquicias Blanco Sol Sl",
    "wof:placetype":"venue"
},
  "geometry": {"coordinates":[-5.2928490639,36.3059196472],"type":"Point"}
}