{
  "type": "Feature",
  "properties": {
    "iso:country":"ES",
    "sg:address":"Calle de Ca\u00d1ada Nueva, 34",
    "sg:city":"San Lorenzo De El Escorial",
    "sg:orig_category":"Inmobiliaria (agencias)",
    "sg:phone":"+34 918 90 90 33",
    "sg:postcode":"28200",
    "sg:province":"Madrid",
    "wof:name":"Administraciones De Fincas Lafico S.l.",
    "wof:placetype":"venue"
},
  "geometry": {"coordinates":[-4.1465725899,40.5944290161],"type":"Point"}
}