{
  "type": "Feature",
  "properties": {
    "addr:full":"Calle de Violante De Hungria, 7 Zaragoza Zaragoza 50009",
    "addr:housenumber":"7",
    "addr:postcode":"50009",
    "addr:street":"Calle De Violante De Hungria",
    "iso:country":"ES",
    "sg:address":"Calle de Violante De Hungria, 7",
    "sg:city":"Zaragoza",
    "sg:classifiers":[
        {
            "category":"Banks & Credit Unions",
            "subcategory":"Bureau De Change",
            "type":"Services"
        }
    ],
    "sg:phone":"+34 976 55 80 04",
    "sg:postcode":"50009",
    "sg:province":"Zaragoza",
    "sg:tags":[
        "organismos",
        "control"
    ],
    "wof:name":"Eurocontrol S.a.",
    "wof:placetype":"venue"
},
  "geometry": {"coordinates":[-0.9030039907,41.6397361755],"type":"Point"}
}