{
  "type": "Feature",
  "properties": {
    "addr:full":"Carr Sant Tomas, 117 Benicasim Castell\u00f3n 12560",
    "addr:housenumber":"117",
    "addr:postcode":"12560",
    "addr:street":"Carr Sant Tomas",
    "iso:country":"ES",
    "sg:address":"Carr Sant Tomas, 117",
    "sg:city":"Benicasim",
    "sg:orig_category":"Alquiler De Apartamentos",
    "sg:phone":"+34 964 30 11 13",
    "sg:postcode":"12560",
    "sg:province":"Castell\u00f3n",
    "wof:name":"Aleixandre Del Arco Francisca",
    "wof:placetype":"venue"
},
  "geometry": {"coordinates":[0.0466559008,40.0530471802],"type":"Point"}
}