{
  "type": "Feature",
  "properties": {
    "iso:country":"ES",
    "sg:address":"Carr Bisbe Ruano, 9",
    "sg:city":"Lleida",
    "sg:orig_category":"Reposter\u00cdas",
    "sg:phone":"+34 973 27 39 43",
    "sg:postcode":"25006",
    "sg:province":"Lleida",
    "wof:name":"Fleca Casals S.l.",
    "wof:placetype":"venue"
},
  "geometry": {"coordinates":[0.6182109714,41.6175842285],"type":"Point"}
}