{
  "type": "Feature",
  "properties": {
    "addr:full":"Avda Hispanidade, 84 Vigo Pontevedra 36203",
    "addr:housenumber":"84",
    "addr:postcode":"36203",
    "addr:street":"Avda Hispanidade",
    "iso:country":"ES",
    "sg:address":"Avda Hispanidade, 84",
    "sg:city":"Vigo",
    "sg:orig_category":"Ingeniero",
    "sg:phone":"+34 986 48 34 02",
    "sg:postcode":"36203",
    "sg:province":"Pontevedra",
    "wof:name":"Regueiro Blanco Pedro",
    "wof:placetype":"venue"
},
  "geometry": {"coordinates":[-8.7270364761,42.2265281677],"type":"Point"}
}