{
  "type": "Feature",
  "properties": {
    "iso:country":"ES",
    "sg:address":"Plaz Espa\u00d1a, 3",
    "sg:city":"Llerena",
    "sg:orig_category":"Restaurantes",
    "sg:phone":"+34 924 87 14 12",
    "sg:postcode":"06900",
    "sg:province":"Badajoz",
    "wof:name":"Hosteleria Zurbaran C.b.",
    "wof:placetype":"venue"
},
  "geometry": {"coordinates":[-6.0163578987,38.2378196716],"type":"Point"}
}