{
  "type": "Feature",
  "properties": {
    "iso:country":"ES",
    "sg:address":"Calle de Celestino Cabeza, 1",
    "sg:city":"Langreo",
    "sg:orig_category":"Librer\u00cdas",
    "sg:phone":"+34 985 69 17 43",
    "sg:postcode":"33900",
    "sg:province":"Asturias",
    "wof:name":"Villanueva Egocheaga Emma",
    "wof:placetype":"venue"
},
  "geometry": {"coordinates":[-5.6914820671,43.3087081909],"type":"Point"}
}