{
  "type": "Feature",
  "properties": {
    "iso:country":"ES",
    "sg:address":"Calle de Ramiro De Maeztu, S/n",
    "sg:city":"Madrid",
    "sg:orig_category":"Ense\u00d1anza Superior Privada",
    "sg:phone":"+34 915 54 01 04",
    "sg:postcode":"28040",
    "sg:province":"Madrid",
    "wof:name":"Fundacion Colegios Mayores Mae-aeci",
    "wof:placetype":"venue"
},
  "geometry": {"coordinates":[-3.719769001,40.4494667053],"type":"Point"}
}