{
  "type": "Feature",
  "properties": {
    "iso:country":"ES",
    "sg:address":"Avda Gaspar Aguilar, 99",
    "sg:city":"Valencia",
    "sg:orig_category":"Administradores De Bienes Y Delegados De Comunidades De Propietarios",
    "sg:phone":"+34 963 77 19 12",
    "sg:postcode":"46017",
    "sg:province":"Valencia",
    "wof:name":"Hernando Santafe Juan",
    "wof:placetype":"venue"
},
  "geometry": {"coordinates":[-0.392960012,39.4523162842],"type":"Point"}
}