{
  "type": "Feature",
  "properties": {
    "iso:country":"ES",
    "sg:address":"Calle de Juan Ramon Jimenez, 29",
    "sg:city":"Salteras",
    "sg:orig_category":"Caf\u00c9s, Bares, Cervecer\u00cdas",
    "sg:phone":"+34 955 70 76 80",
    "sg:postcode":"41909",
    "sg:province":"Sevilla",
    "wof:name":"Chicas De Oro Uno S.l.",
    "wof:placetype":"venue"
},
  "geometry": {"coordinates":[-6.10876894,37.4175491333],"type":"Point"}
}