{
  "type": "Feature",
  "properties": {
    "iso:country":"ES",
    "sg:address":"Avda Gasteiz, 75",
    "sg:city":"Vitoria-gasteiz",
    "sg:orig_category":"Caf\u00c9s, Bares, Cervecer\u00cdas",
    "sg:phone":"+34 945 22 26 25",
    "sg:postcode":"01009",
    "sg:province":"\u00c1lava",
    "wof:name":"Tato Vega Jose Luis",
    "wof:placetype":"venue"
},
  "geometry": {"coordinates":[-2.681180954,42.8506240845],"type":"Point"}
}