{
  "type": "Feature",
  "properties": {
    "addr:full":"Rbla Just Oliveras, 21 Hospitalet Llobregat Barcelona 08901",
    "addr:housenumber":"21",
    "addr:postcode":"08901",
    "addr:street":"Rbla Just Oliveras",
    "iso:country":"ES",
    "sg:address":"Rbla Just Oliveras, 21",
    "sg:city":"Hospitalet Llobregat",
    "sg:orig_category":"Promotores Constructores",
    "sg:phone":"+34 933 37 68 57",
    "sg:postcode":"08901",
    "sg:province":"Barcelona",
    "wof:name":"Construcciones De Obras E Interiorismo S.l.",
    "wof:placetype":"venue"
},
  "geometry": {"coordinates":[2.1010949612,41.3611793518],"type":"Point"}
}