{
  "type": "Feature",
  "properties": {
    "addr:full":"Avda Piscina (la), S/n Roda Andalucia Sevilla 41590",
    "addr:postcode":"41590",
    "addr:street":"Avda Piscina La S / N",
    "iso:country":"ES",
    "sg:address":"Avda Piscina (la), S/n",
    "sg:city":"Roda Andalucia",
    "sg:orig_category":"Centros De Educaci\u00d3n Especial",
    "sg:phone":"+34 954 01 64 03",
    "sg:postcode":"41590",
    "sg:province":"Sevilla",
    "wof:name":"Centro De Educacion De Adultos",
    "wof:placetype":"venue"
},
  "geometry": {"coordinates":[-4.7738838196,37.2011489868],"type":"Point"}
}