{
  "type": "Feature",
  "properties": {
    "addr:full":"Calle de Gallo, 1 Valladolid Valladolid 47012",
    "addr:housenumber":"1",
    "addr:postcode":"47012",
    "addr:street":"Calle De Gallo",
    "iso:country":"ES",
    "sg:address":"Calle de Gallo, 1",
    "sg:city":"Valladolid",
    "sg:orig_category":"Inversiones",
    "sg:phone":"+34 983 29 23 39",
    "sg:postcode":"47012",
    "sg:province":"Valladolid",
    "wof:name":"Acavi Inversiones S.l.",
    "wof:placetype":"venue"
},
  "geometry": {"coordinates":[-4.7096214294,41.645488739],"type":"Point"}
}