{
  "type": "Feature",
  "properties": {
    "addr:full":"Rond Fonti\u00d1as (das), 150 Lugo Lugo 27002",
    "addr:housenumber":"150",
    "addr:postcode":"27002",
    "iso:country":"ES",
    "sg:address":"Rond Fonti\u00d1as (das), 150",
    "sg:city":"Lugo",
    "sg:orig_category":"Empresas De Desmonte",
    "sg:phone":"+34 982 25 00 92",
    "sg:postcode":"27002",
    "sg:province":"Lugo",
    "wof:name":"Ansareu Bargos Domingo",
    "wof:placetype":"venue"
},
  "geometry": {"coordinates":[-7.5301399231,42.9997177124],"type":"Point"}
}