{
  "type": "Feature",
  "properties": {
    "iso:country":"ES",
    "sg:address":"Ctra Naquera, S/n",
    "sg:city":"Naquera",
    "sg:orig_category":"Ense\u00d1anza Agr\u00cdcola",
    "sg:phone":"+34 961 68 17 07",
    "sg:postcode":"46119",
    "sg:province":"Valencia",
    "sg:website":"www.proyectoadai.com",
    "wof:name":"Proyectos Adai S.l.",
    "wof:placetype":"venue"
},
  "geometry": {"coordinates":[-0.423819989,39.6582489014],"type":"Point"}
}