{
  "type": "Feature",
  "properties": {
    "iso:country":"ES",
    "sg:address":"Carrer de Tomas Rul.lan, 64",
    "sg:city":"Palma",
    "sg:orig_category":"M\u00c9dicos: Foniatr\u00cda Y Logopedia",
    "sg:phone":"+34 971 27 80 20",
    "sg:postcode":"07008",
    "sg:province":"Islas Baleares",
    "wof:name":"Centro Mater Misericordie",
    "wof:placetype":"venue"
},
  "geometry": {"coordinates":[2.6736929417,39.5770378113],"type":"Point"}
}