{
  "type": "Feature",
  "properties": {
    "addr:full":"Ctra Posadas, 33 Villaviciosa Cordoba C\u00f3rdoba 14300",
    "addr:housenumber":"33",
    "addr:postcode":"14300",
    "addr:street":"Ctra Posadas",
    "iso:country":"ES",
    "sg:address":"Ctra Posadas, 33",
    "sg:city":"Villaviciosa Cordoba",
    "sg:orig_category":"Carnicer\u00cdas, Carnicer\u00cdas",
    "sg:phone":"+34 957 36 07 79",
    "sg:postcode":"14300",
    "sg:province":"C\u00f3rdoba",
    "wof:name":"Productos De La Casa Y Del Cerdo Iberico El Canito Sl",
    "wof:placetype":"venue"
},
  "geometry": {"coordinates":[-5.0168352127,38.0728721619],"type":"Point"}
}