{
  "type": "Feature",
  "properties": {
    "addr:full":"Plaz Sandoval, 5 San Antolin Murcia 30004",
    "addr:postcode":"30004",
    "addr:street":"San",
    "iso:country":"ES",
    "sg:address":"Plaz Sandoval, 5",
    "sg:city":"San Antolin",
    "sg:orig_category":"Cristaler\u00cdas",
    "sg:phone":"+34 968 29 06 14",
    "sg:postcode":"30004",
    "sg:province":"Murcia",
    "wof:name":"Martinez Oliva Jesus",
    "wof:placetype":"venue"
},
  "geometry": {"coordinates":[-1.1361240149,37.98462677],"type":"Point"}
}