{
  "type": "Feature",
  "properties": {
    "addr:full":"Avda Aeropuerto (del), S/n Cordoba C\u00f3rdoba 14004",
    "addr:housenumber":"/ n",
    "addr:postcode":"14004",
    "addr:street":"Avda Aeropuerto Del S;Co\u0301Rdoba",
    "iso:country":"ES",
    "sg:address":"Avda Aeropuerto (del), S/n",
    "sg:city":"Cordoba",
    "sg:orig_category":"Cajas Para Embalar",
    "sg:phone":"+34 957 23 86 02",
    "sg:postcode":"14004",
    "sg:province":"C\u00f3rdoba",
    "sg:website":"www.cajarural.com",
    "wof:name":"Caja Rural De Cordoba",
    "wof:placetype":"venue"
},
  "geometry": {"coordinates":[-4.801902771,37.8714523315],"type":"Point"}
}