{
  "type": "Feature",
  "properties": {
    "iso:country":"ES",
    "sg:address":"Calle de Rio De Oro, 48",
    "sg:city":"Gijon",
    "sg:orig_category":"Farmacias",
    "sg:phone":"+34 985 16 45 71",
    "sg:postcode":"33209",
    "sg:province":"Asturias",
    "wof:name":"Fernandez Macias Manuela",
    "wof:placetype":"venue"
},
  "geometry": {"coordinates":[-5.6632871628,43.5283470154],"type":"Point"}
}