{
  "type": "Feature",
  "properties": {
    "addr:full":"Carrer de Ausias Marc, 65 Barcelona Barcelona 08010",
    "addr:housenumber":"65",
    "addr:postcode":"08010",
    "addr:street":"Carrer De Ausias Marc",
    "iso:country":"ES",
    "sg:address":"Carrer de Ausias Marc, 65",
    "sg:city":"Barcelona",
    "sg:orig_category":"Laboratorios Y Trabajos De Fotograf\u00cda, V\u00cddeo Y Cine",
    "sg:phone":"+34 932 46 66 61",
    "sg:postcode":"08010",
    "sg:province":"Barcelona",
    "wof:name":"Fotoprix S.a.",
    "wof:placetype":"venue"
},
  "geometry": {"coordinates":[2.1784420013,41.3936576843],"type":"Point"}
}