{
  "type": "Feature",
  "properties": {
    "iso:country":"ES",
    "sg:address":"Avda Manzanares, 40",
    "sg:city":"Madrid",
    "sg:orig_category":"Parques Para Contenedores",
    "sg:phone":"+34 913 66 67 21",
    "sg:postcode":"28011",
    "sg:province":"Madrid",
    "wof:name":"Moreno De Diezma Ignacio Jose",
    "wof:placetype":"venue"
},
  "geometry": {"coordinates":[-3.7234330177,40.4057197571],"type":"Point"}
}