{
  "type": "Feature",
  "properties": {
    "addr:full":"Calle de Bell, 8 Getafe Madrid 28906",
    "addr:housenumber":"8",
    "addr:postcode":"28906",
    "addr:street":"Calle De Bell",
    "iso:country":"ES",
    "sg:address":"Calle de Bell, 8",
    "sg:city":"Getafe",
    "sg:orig_category":"Electricidad: Instaladores",
    "sg:phone":"+34 916 83 48 60",
    "sg:postcode":"28906",
    "sg:province":"Madrid",
    "wof:name":"Elecnor S.a.",
    "wof:placetype":"venue"
},
  "geometry": {"coordinates":[-3.6997833252,40.2969245911],"type":"Point"}
}