{
  "type": "Feature",
  "properties": {
    "addr:full":"Calle de Azcona, 60 Madrid Madrid 28028",
    "addr:housenumber":"60",
    "addr:postcode":"madrid;28028",
    "addr:street":"Calle De Azcona",
    "iso:country":"ES",
    "sg:address":"Calle de Azcona, 60",
    "sg:city":"Madrid",
    "sg:orig_category":"Limpieza Industrial",
    "sg:phone":"+34 913 56 89 52",
    "sg:postcode":"28028",
    "sg:province":"Madrid",
    "wof:name":"Herpagon S.l.",
    "wof:placetype":"venue"
},
  "geometry": {"coordinates":[-3.6665401459,40.4356765747],"type":"Point"}
}