{
  "type": "Feature",
  "properties": {
    "iso:country":"ES",
    "sg:address":"Calle de Escorial, 6",
    "sg:city":"Rozas De Madrid",
    "sg:orig_category":"Audiovisuales: Material Y Accesorios (al Por Menor)",
    "sg:phone":"+34 916 03 00 97",
    "sg:postcode":"28230",
    "sg:province":"Madrid",
    "wof:name":"Orvaes Sound S.a.",
    "wof:placetype":"venue"
},
  "geometry": {"coordinates":[-3.8759460449,40.4927062988],"type":"Point"}
}