{
  "type": "Feature",
  "properties": {
    "addr:full":"Calle de Cuesta, 16 Talavera La Nueva Toledo 45694",
    "addr:housenumber":"16",
    "addr:postcode":"45694",
    "addr:street":"Calle De Cuesta",
    "iso:country":"ES",
    "sg:address":"Calle de Cuesta, 16",
    "sg:city":"Talavera La Nueva",
    "sg:orig_category":"Peluqueros: De Se\u00d1oras",
    "sg:phone":"+34 925 85 01 98",
    "sg:postcode":"45694",
    "sg:province":"Toledo",
    "wof:name":"Bernardo Gomez Jose Manuel",
    "wof:placetype":"venue"
},
  "geometry": {"coordinates":[-4.8928189278,39.9369010925],"type":"Point"}
}