{
  "type": "Feature",
  "properties": {
    "addr:full":"Avda Doctor Artero, S/n Huesca Huesca 22004",
    "addr:housenumber":"s / n",
    "addr:postcode":"22004",
    "addr:street":"Avda Doctor Artero",
    "iso:country":"ES",
    "sg:address":"Avda Doctor Artero, S/n",
    "sg:city":"Huesca",
    "sg:orig_category":"Supermercados Y Hipermercados",
    "sg:phone":"+34 974 23 13 57",
    "sg:postcode":"22004",
    "sg:province":"Huesca",
    "wof:name":"Erosmer Iberica S.a.",
    "wof:placetype":"venue"
},
  "geometry": {"coordinates":[-0.4132690132,42.1432266235],"type":"Point"}
}