{
  "type": "Feature",
  "properties": {
    "iso:country":"ES",
    "sg:address":"Rua Seco, 1",
    "sg:city":"Olite",
    "sg:orig_category":"Institutos De Belleza (productos Y Aparatos)",
    "sg:phone":"+34 948 71 22 31",
    "sg:postcode":"31390",
    "sg:province":"Navarra",
    "wof:name":"Echeverria Jaime Nuria",
    "wof:placetype":"venue"
},
  "geometry": {"coordinates":[-1.6518290043,42.4796409607],"type":"Point"}
}