{
  "type": "Feature",
  "properties": {
    "addr:full":"Rua Cobian Roffignac, 2 Pontevedra Pontevedra 36002",
    "addr:housenumber":"2",
    "addr:postcode":"36002",
    "addr:street":"Rua Cobian Roffignac",
    "iso:country":"ES",
    "sg:address":"Rua Cobian Roffignac, 2",
    "sg:city":"Pontevedra",
    "sg:orig_category":"Notarios",
    "sg:phone":"+34 986 86 66 02",
    "sg:postcode":"36002",
    "sg:province":"Pontevedra",
    "wof:name":"Darrieux De Ben Luis",
    "wof:placetype":"venue"
},
  "geometry": {"coordinates":[-8.6421489716,42.4314613342],"type":"Point"}
}