{
  "type": "Feature",
  "properties": {
    "addr:full":"Avda Encartaciones, 46 Balmaseda Vizcaya 48800",
    "addr:housenumber":"46",
    "addr:postcode":"48800",
    "addr:street":"Avda Encartaciones",
    "iso:country":"ES",
    "sg:address":"Avda Encartaciones, 46",
    "sg:city":"Balmaseda",
    "sg:orig_category":"Carnicer\u00cdas, Carnicer\u00cdas",
    "sg:phone":"+34 946 80 05 69",
    "sg:postcode":"48800",
    "sg:province":"Vizcaya",
    "wof:name":"Beraza Herrero Bego\u00f1a",
    "wof:placetype":"venue"
},
  "geometry": {"coordinates":[-3.2018930912,43.1887512207],"type":"Point"}
}