{
  "type": "Feature",
  "properties": {
    "iso:country":"ES",
    "sg:address":"Calle de Nazaret (de), 13",
    "sg:city":"Fuenlabrada",
    "sg:orig_category":"Farmacias",
    "sg:phone":"+34 916 15 68 33",
    "sg:postcode":"28941",
    "sg:province":"Madrid",
    "wof:name":"Alarcon Del Olmo Maria Del Rosario",
    "wof:placetype":"venue"
},
  "geometry": {"coordinates":[-3.798886776,40.2878036499],"type":"Point"}
}