{
  "type": "Feature",
  "properties": {
    "iso:country":"ES",
    "sg:address":"Calle de Rio Ebro, S/n",
    "sg:city":"Calatayud",
    "sg:orig_category":"Ense\u00d1anza, Formaci\u00d3n Profesional: Aprendizaje",
    "sg:phone":"+34 976 88 18 68",
    "sg:postcode":"50300",
    "sg:province":"Zaragoza",
    "wof:name":"Excelentisima Diputacion Provincial De Zaragoza",
    "wof:placetype":"venue"
},
  "geometry": {"coordinates":[-1.6406229734,41.3412361145],"type":"Point"}
}