{
  "type": "Feature",
  "properties": {
    "iso:country":"ES",
    "sg:address":"Calle de Italia, 8",
    "sg:city":"Torrijo Campo",
    "sg:orig_category":"Plomeros",
    "sg:phone":"+34 978 86 26 89",
    "sg:postcode":"44393",
    "sg:province":"Teruel",
    "wof:name":"Mateo Melendez Jose Luis",
    "wof:placetype":"venue"
},
  "geometry": {"coordinates":[-1.3355449438,40.8239860535],"type":"Point"}
}