{
  "type": "Feature",
  "properties": {
    "addr:full":"Carrer de Barcelona, 1 Gava Barcelona 08850",
    "addr:housenumber":"1",
    "addr:postcode":"08850",
    "addr:street":"Carrer De Barcelona",
    "iso:country":"ES",
    "sg:address":"Carrer de Barcelona, 1",
    "sg:city":"Gava",
    "sg:orig_category":"Fabricaci\u00d3n De Bebidas No Alcoh\u00d3licas",
    "sg:phone":"+34 936 38 93 05",
    "sg:postcode":"08850",
    "sg:province":"Barcelona",
    "wof:name":"Natural Juice 1 S.l.",
    "wof:placetype":"venue"
},
  "geometry": {"coordinates":[2.0098381042,41.3023605347],"type":"Point"}
}