{
  "type": "Feature",
  "properties": {
    "addr:full":"Calle de Cuba, 3 Aviles Asturias 33401",
    "addr:housenumber":"3",
    "addr:postcode":"33401",
    "addr:street":"Calle De Cuba",
    "iso:country":"ES",
    "sg:address":"Calle de Cuba, 3",
    "sg:city":"Aviles",
    "sg:orig_category":"Colchones (fabricaci\u00d3n, Al Por Mayor, Al Por Menor)",
    "sg:phone":"+34 985 52 14 83",
    "sg:postcode":"33401",
    "sg:province":"Asturias",
    "sg:website":"www.asturcolchon.com",
    "wof:name":"Asturiana De Colchones S.l.",
    "wof:placetype":"venue"
},
  "geometry": {"coordinates":[-5.9251894951,43.5575447083],"type":"Point"}
}