{
  "type": "Feature",
  "properties": {
    "iso:country":"ES",
    "sg:address":"Calle de Jesus Arambarri, 76",
    "sg:city":"Salamanca",
    "sg:orig_category":"Comercio De Piezas De Recambio Y De Accesorios De Veh\u00cdculos, Veh\u00cdculos Industriales",
    "sg:phone":"+34 923 22 97 27",
    "sg:postcode":"37003",
    "sg:province":"Salamanca",
    "wof:name":"Emilio Arenaz S.l.",
    "wof:placetype":"venue"
},
  "geometry": {"coordinates":[-5.6412291527,40.9710998535],"type":"Point"}
}