{
  "type": "Feature",
  "properties": {
    "iso:country":"ES",
    "sg:address":"Av Bartomeu Riutort, 33",
    "sg:city":"Can Pastilla",
    "sg:orig_category":"Art\u00cdculos De Regalo (al Por Menor)",
    "sg:phone":"+34 971 26 02 86",
    "sg:postcode":"07610",
    "sg:province":"Islas Baleares",
    "wof:name":"Serna Gascon Alberto",
    "wof:placetype":"venue"
},
  "geometry": {"coordinates":[2.7200241089,39.5354042053],"type":"Point"}
}