{
  "type": "Feature",
  "properties": {
    "iso:country":"ES",
    "sg:address":"Avda Alcalde Miguel Casta\u00d1o, 95",
    "sg:city":"Le\u00f3n",
    "sg:orig_category":"Juegos Y Juguetes (al Por Menor)",
    "sg:phone":"+34 987 26 29 00",
    "sg:postcode":"24005",
    "sg:province":"Le\u00f3n",
    "sg:website":"www.toysrus.es",
    "wof:name":"Toys R Us S.a.",
    "wof:placetype":"venue"
},
  "geometry": {"coordinates":[-5.5597901344,42.5866394043],"type":"Point"}
}