{
  "type": "Feature",
  "properties": {
    "addr:full":"Calle de Huertas (de Las), 12 Colmenar Viejo Madrid 28770",
    "addr:housenumber":"12",
    "addr:postcode":"28770",
    "addr:street":"Calle De Huertas De Las",
    "iso:country":"ES",
    "sg:address":"Calle de Huertas (de Las), 12",
    "sg:city":"Colmenar Viejo",
    "sg:orig_category":"Electricidad: Instaladores",
    "sg:phone":"+34 918 46 44 61",
    "sg:postcode":"28770",
    "sg:province":"Madrid",
    "wof:name":"Jesus Perrino S.l.",
    "wof:placetype":"venue"
},
  "geometry": {"coordinates":[-3.7653141022,40.6580429077],"type":"Point"}
}