{
  "type": "Feature",
  "properties": {
    "addr:full":"Calle de Padre Claret, 30 Madrid Madrid 28002",
    "addr:housenumber":"30",
    "addr:postcode":"madrid;28002",
    "addr:street":"Calle De Padre Claret",
    "iso:country":"ES",
    "sg:address":"Calle de Padre Claret, 30",
    "sg:city":"Madrid",
    "sg:orig_category":"Inform\u00c1tica (estudios, Servicios, Asesor\u00cda, Formaci\u00d3n)",
    "sg:phone":"+34 914 16 51 05",
    "sg:postcode":"28002",
    "sg:province":"Madrid",
    "wof:name":"Eopc S.l.",
    "wof:placetype":"venue"
},
  "geometry": {"coordinates":[-3.6647179127,40.4512710571],"type":"Point"}
}