{
  "type": "Feature",
  "properties": {
    "addr:full":"Carr Claro, De Sa, 6 Son Blanch Islas Baleares 07760",
    "addr:housenumber":"6",
    "addr:postcode":"07760",
    "addr:street":"Carr Claro De Sa",
    "iso:country":"ES",
    "sg:address":"Carr Claro, De Sa, 6",
    "sg:city":"Son Blanch",
    "sg:orig_category":"Arquitectos",
    "sg:phone":"+34 971 38 50 76",
    "sg:postcode":"07760",
    "sg:province":"Islas Baleares",
    "wof:name":"Camps Juaneda Juan",
    "wof:placetype":"venue"
},
  "geometry": {"coordinates":[3.8382499218,39.9930915833],"type":"Point"}
}