{
  "type": "Feature",
  "properties": {
    "addr:full":"Calle de Mayor, 9 Ferez Albacete 02436",
    "addr:housenumber":"9",
    "addr:postcode":"02436",
    "addr:street":"Calle De Mayor",
    "iso:country":"ES",
    "sg:address":"Calle de Mayor, 9",
    "sg:city":"Ferez",
    "sg:orig_category":"Sales (al Por Mayor)",
    "sg:phone":"+34 967 42 01 40",
    "sg:postcode":"02436",
    "sg:province":"Albacete",
    "wof:name":"Bautista Bautista Erotida",
    "wof:placetype":"venue"
},
  "geometry": {"coordinates":[-2.0105559826,38.3557472229],"type":"Point"}
}