{
  "type": "Feature",
  "properties": {
    "iso:country":"ES",
    "sg:address":"Plaz Calvo Sotelo, 3",
    "sg:city":"Horcajo De Las Torres",
    "sg:orig_category":"Carnicer\u00cdas, Carnicer\u00cdas",
    "sg:phone":"+34 920 32 71 32",
    "sg:postcode":"05210",
    "sg:province":"\u00c1vila",
    "wof:name":"Martin Diaz Francisco",
    "wof:placetype":"venue"
},
  "geometry": {"coordinates":[-5.0904479027,41.0654945374],"type":"Point"}
}