{
  "type": "Feature",
  "properties": {
    "addr:full":"Carrer de Mossen Jacint Verdaguer, S/n Cambrils Tarragona 43850",
    "addr:housenumber":"s / n",
    "addr:postcode":"43850",
    "addr:street":"Carrer De Mossen Jacint Verdaguer",
    "iso:country":"ES",
    "sg:address":"Carrer de Mossen Jacint Verdaguer, S/n",
    "sg:city":"Cambrils",
    "sg:orig_category":"Pescader\u00cdas (al Por Menor)",
    "sg:phone":"+34 977 36 58 87",
    "sg:postcode":"43850",
    "sg:province":"Tarragona",
    "wof:name":"Cofradia De Pescadores Cambrils",
    "wof:placetype":"venue"
},
  "geometry": {"coordinates":[1.0532009602,41.0722389221],"type":"Point"}
}