{
  "type": "Feature",
  "properties": {
    "addr:full":"Pase Glorieta, 32 Huelva Huelva 21002",
    "addr:postcode":"21002",
    "addr:street":"Glorieta",
    "iso:country":"ES",
    "sg:address":"Pase Glorieta, 32",
    "sg:city":"Huelva",
    "sg:classifiers":[
        {
            "category":"Recreation",
            "type":"Entertainment"
        }
    ],
    "sg:phone":"+34 959 26 29 52",
    "sg:postcode":"21002",
    "sg:province":"Huelva",
    "sg:tags":[
        "caza",
        "pr\u00c1ctica",
        "la",
        "de",
        "pesca",
        "y"
    ],
    "wof:name":"Mariscos Rodriguez S.a.",
    "wof:placetype":"venue"
},
  "geometry": {"coordinates":[-6.9582891464,37.2619285583],"type":"Point"}
}