{
  "type": "Feature",
  "properties": {
    "addr:full":"Calle de Lavapies, 37 Madrid Madrid 28012",
    "addr:housenumber":"37",
    "addr:postcode":"madrid;28012",
    "addr:street":"Calle De Lavapies",
    "iso:country":"ES",
    "sg:address":"Calle de Lavapies, 37",
    "sg:city":"Madrid",
    "sg:orig_category":"Bares, Piano",
    "sg:phone":"+34 915 28 43 81",
    "sg:postcode":"28012",
    "sg:province":"Madrid",
    "wof:name":"Nueva Armonia En La Mancha S.l./,",
    "wof:placetype":"venue"
},
  "geometry": {"coordinates":[-3.7021639347,40.4098777771],"type":"Point"}
}