{
  "type": "Feature",
  "properties": {
    "iso:country":"ES",
    "sg:address":"Carrer de Teresa Pamies I Bertran, 4",
    "sg:city":"Reus",
    "sg:orig_category":"Peluquer\u00cdas, Peluquer\u00cda Mixta",
    "sg:phone":"+34 977 77 08 58",
    "sg:postcode":"43202",
    "sg:province":"Tarragona",
    "wof:name":"Valera Arjona Cristina",
    "wof:placetype":"venue"
},
  "geometry": {"coordinates":[1.1186280251,41.1564064026],"type":"Point"}
}