{
  "type": "Feature",
  "properties": {
    "iso:country":"ES",
    "sg:address":"Calle de Torrelodones, 5",
    "sg:city":"Ventorro Del Cano",
    "sg:orig_category":"Centros Empresariales",
    "sg:phone":"+34 916 33 45 94",
    "sg:postcode":"28925",
    "sg:province":"Madrid",
    "wof:name":"Sociedad Espa\u00f1ola Inmuebles Y Locales S.l.",
    "wof:placetype":"venue"
},
  "geometry": {"coordinates":[-3.8350439072,40.3908004761],"type":"Point"}
}