{
  "type": "Feature",
  "properties": {
    "addr:full":"Pol Ind Casona De Lis, 5 Jerez C\u00e1diz 11405",
    "addr:postcode":"11405",
    "addr:street":"Lis",
    "iso:country":"ES",
    "sg:address":"Pol Ind Casona De Lis, 5",
    "sg:city":"Jerez",
    "sg:orig_category":"Fabricaci\u00d3n, Instalaci\u00d3n De Escaleras",
    "sg:phone":"+34 956 31 30 30",
    "sg:postcode":"11405",
    "sg:province":"C\u00e1diz",
    "wof:name":"Torneado Jerez S.l",
    "wof:placetype":"venue"
},
  "geometry": {"coordinates":[-6.1005191803,36.7067260742],"type":"Point"}
}