{
  "type": "Feature",
  "properties": {
    "addr:full":"Calle de Colon, 55 Cuenca Cuenca 16002",
    "addr:housenumber":"55",
    "addr:postcode":"16002",
    "addr:street":"Calle De Colon",
    "iso:country":"ES",
    "sg:address":"Calle de Colon, 55",
    "sg:city":"Cuenca",
    "sg:orig_category":"Centros P\u00dablicos De Formaci\u00d3n Profesional Y T\u00c9cnica",
    "sg:phone":"+34 969 21 23 33",
    "sg:postcode":"16002",
    "sg:province":"Cuenca",
    "wof:name":"Colegio Oficial De Medicos De Cuenca",
    "wof:placetype":"venue"
},
  "geometry": {"coordinates":[-2.1374742985,40.0732116699],"type":"Point"}
}