{
  "type": "Feature",
  "properties": {
    "iso:country":"ES",
    "sg:address":"Santa Marina Kalea, 28",
    "sg:city":"Zarautz",
    "sg:orig_category":"Peluqueros: De Se\u00d1oras",
    "sg:phone":"+34 943 13 01 33",
    "sg:postcode":"20800",
    "sg:province":"Guip\u00f9zcoa",
    "wof:name":"Aizpurua Aramburu Miren Arantxa",
    "wof:placetype":"venue"
},
  "geometry": {"coordinates":[-2.1767859459,43.2843208313],"type":"Point"}
}