{
  "type": "Feature",
  "properties": {
    "addr:full":"Calle de Arzobispo Perez Platero, 19 Burgos Burgos 09007",
    "addr:housenumber":"19",
    "addr:postcode":"09007",
    "addr:street":"Calle De Arzobispo Perez Platero",
    "iso:country":"ES",
    "sg:address":"Calle de Arzobispo Perez Platero, 19",
    "sg:city":"Burgos",
    "sg:orig_category":"Lencer\u00cda Femenina, Corseter\u00cda, Trajes De Ba\u00d1o (al Por Menor)",
    "sg:phone":"+34 947 21 03 27",
    "sg:postcode":"09007",
    "sg:province":"Burgos",
    "wof:name":"Espiga Gomez Monica",
    "wof:placetype":"venue"
},
  "geometry": {"coordinates":[-3.6673812866,42.3507461548],"type":"Point"}
}