{
  "type": "Feature",
  "properties": {
    "iso:country":"ES",
    "sg:address":"Carrer de Montsia, 83",
    "sg:city":"Poligono Industrial Can Carner",
    "sg:orig_category":"Maquinaria Para Industrias Diversas",
    "sg:phone":"+34 937 15 90 29",
    "sg:postcode":"08211",
    "sg:province":"Barcelona",
    "wof:name":"Ejetecdis Espa\u00f1a S.l.",
    "wof:placetype":"venue"
},
  "geometry": {"coordinates":[2.0824799538,41.6114387512],"type":"Point"}
}