{
  "type": "Feature",
  "properties": {
    "addr:full":"Avda Generalisimo, 116 Bola\u00e7os De Calatrava Ciudad Real 13260",
    "addr:housenumber":"116",
    "addr:postcode":"13260",
    "addr:street":"Avda Generalisimo",
    "iso:country":"ES",
    "sg:address":"Avda Generalisimo, 116",
    "sg:city":"Bola\u00e7os De Calatrava",
    "sg:orig_category":"Fabricaci\u00d3n De Quesos",
    "sg:phone":"+34 926 87 06 80",
    "sg:postcode":"13260",
    "sg:province":"Ciudad Real",
    "wof:name":"Rodrigo Ruiz Angel",
    "wof:placetype":"venue"
},
  "geometry": {"coordinates":[-3.6528038979,38.9070281982],"type":"Point"}
}