{
  "type": "Feature",
  "properties": {
    "addr:full":"Calle de Bailen (de), 1 Aranjuez Madrid 28300",
    "addr:housenumber":"1",
    "addr:postcode":"28300",
    "addr:street":"Calle De Bailen De",
    "iso:country":"ES",
    "sg:address":"Calle de Bailen (de), 1",
    "sg:city":"Aranjuez",
    "sg:orig_category":"Art\u00cdculos De Regalo (al Por Menor)",
    "sg:phone":"+34 918 91 28 81",
    "sg:postcode":"28300",
    "sg:province":"Madrid",
    "wof:name":"Megias Salmeron Ana Isabel",
    "wof:placetype":"venue"
},
  "geometry": {"coordinates":[-3.6058242321,40.028755188],"type":"Point"}
}