{
  "type": "Feature",
  "properties": {
    "iso:country":"ES",
    "sg:address":"Calle de San Blas, 4",
    "sg:city":"Almendralejo",
    "sg:orig_category":"Promotores Constructores",
    "sg:phone":"+34 924 67 12 26",
    "sg:postcode":"06200",
    "sg:province":"Badajoz",
    "wof:name":"Provial Construcciones Y Proyectos S.l.",
    "wof:placetype":"venue"
},
  "geometry": {"coordinates":[-6.4013438225,38.6846389771],"type":"Point"}
}