{
  "type": "Feature",
  "properties": {
    "iso:country":"ES",
    "sg:address":"Castanyers, 25",
    "sg:city":"S. Quirze Valles",
    "sg:orig_category":"Ingenier\u00cda, Centros De Estudios (diversos)",
    "sg:phone":"+34 937 21 02 47",
    "sg:postcode":"08192",
    "sg:province":"Barcelona",
    "wof:name":"Roca Vers Alberto",
    "wof:placetype":"venue"
},
  "geometry": {"coordinates":[2.0765779018,41.529384613],"type":"Point"}
}