{
  "type": "Feature",
  "properties": {
    "iso:country":"ES",
    "sg:address":"Pg Riera, 125",
    "sg:city":"Rubi",
    "sg:orig_category":"Reciclaje, Tratamiento De Tejidos",
    "sg:phone":"+34 935 86 25 00",
    "sg:postcode":"08191",
    "sg:province":"Barcelona",
    "wof:name":"Sedatex S.a.",
    "wof:placetype":"venue"
},
  "geometry": {"coordinates":[2.0282869339,41.4948501587],"type":"Point"}
}