{
  "type": "Feature",
  "properties": {
    "iso:country":"ES",
    "sg:address":"Calle de Pozo, 7",
    "sg:city":"Vilamarxant",
    "sg:orig_category":"Asesor\u00cda De Formaci\u00d3n Y Gesti\u00d3n De Personal",
    "sg:phone":"+34 962 71 51 03",
    "sg:postcode":"46191",
    "sg:province":"Valencia",
    "wof:name":"Finansegur Asesores S.l.",
    "wof:placetype":"venue"
},
  "geometry": {"coordinates":[-0.6210269928,39.5681266785],"type":"Point"}
}