{
  "type": "Feature",
  "properties": {
    "addr:full":"Calle de Flores Las, 2 Arroyo De La Miel-benalmadena Costa M\u00e1laga 29631",
    "addr:housenumber":"2",
    "addr:postcode":"29631",
    "addr:street":"Calle De Flores Las;Arroyo De La Miel-Benalmadena Costa Ma\u0301Laga",
    "iso:country":"ES",
    "sg:address":"Calle de Flores Las, 2",
    "sg:city":"Arroyo De La Miel-benalmadena Costa",
    "sg:orig_category":"Inform\u00c1tica (estudios, Servicios, Asesor\u00cda, Formaci\u00d3n)",
    "sg:phone":"+34 952 44 70 57",
    "sg:postcode":"29631",
    "sg:province":"M\u00e1laga",
    "wof:name":"Mapfre Servicios De Informatica",
    "wof:placetype":"venue"
},
  "geometry": {"coordinates":[-4.5482521057,36.6017608643],"type":"Point"}
}