{
  "type": "Feature",
  "properties": {
    "iso:country":"ES",
    "sg:address":"Avda Camilo Jose Cela, 12",
    "sg:city":"Triacastela",
    "sg:orig_category":"Carnicer\u00cdas, Carnicer\u00cdas",
    "sg:phone":"+34 982 54 80 67",
    "sg:postcode":"27630",
    "sg:province":"Lugo",
    "wof:name":"Rodriguez Castro Montserrat",
    "wof:placetype":"venue"
},
  "geometry": {"coordinates":[-7.2405390739,42.7565994263],"type":"Point"}
}