{
  "type": "Feature",
  "properties": {
    "iso:country":"ES",
    "sg:address":"Calle de Virgen De Fatima, 22",
    "sg:city":"San Jose Rinconada",
    "sg:orig_category":"Empresas De Carpinter\u00cda De Madera",
    "sg:phone":"+34 954 79 03 17",
    "sg:postcode":"41300",
    "sg:province":"Sevilla",
    "wof:name":"Carpilobo S.l.",
    "wof:placetype":"venue"
},
  "geometry": {"coordinates":[-5.9378390312,37.4828414917],"type":"Point"}
}