{
  "type": "Feature",
  "properties": {
    "addr:full":"Plaz Solobarria, 4 Arizgoiti Vizcaya 48970",
    "addr:housenumber":"4",
    "addr:postcode":"48970",
    "addr:street":"Plaz Solobarria",
    "iso:country":"ES",
    "sg:address":"Plaz Solobarria, 4",
    "sg:city":"Arizgoiti",
    "sg:orig_category":"Ense\u00d1anza: Idiomas",
    "sg:phone":"+34 944 40 82 64",
    "sg:postcode":"48970",
    "sg:province":"Vizcaya",
    "wof:name":"Euskaraz Koop. E.",
    "wof:placetype":"venue"
},
  "geometry": {"coordinates":[-2.8843719959,43.2383995056],"type":"Point"}
}