{
  "type": "Feature",
  "properties": {
    "iso:country":"ES",
    "sg:address":"Calle de Constitucion (de La), 55",
    "sg:city":"Alcobendas",
    "sg:orig_category":"Peluquer\u00cdas, Peluquer\u00cda Mixta",
    "sg:phone":"+34 916 53 56 40",
    "sg:postcode":"28100",
    "sg:province":"Madrid",
    "wof:name":"Moriche Parra Mercedes",
    "wof:placetype":"venue"
},
  "geometry": {"coordinates":[-3.6379685402,40.5431671143],"type":"Point"}
}