{
  "type": "Feature",
  "properties": {
    "addr:full":"Urbieta Kalea, 6 Hernani Guip\u00f9zcoa 20120",
    "addr:housenumber":"6",
    "addr:postcode":"20120",
    "addr:street":"Urbieta Kalea;Guipu\u0300Zcoa",
    "iso:country":"ES",
    "sg:address":"Urbieta Kalea, 6",
    "sg:city":"Hernani",
    "sg:orig_category":"Tintes (fabricaci\u00d3n, Al Por Mayor)",
    "sg:phone":"+34 943 55 00 84",
    "sg:postcode":"20120",
    "sg:province":"Guip\u00f9zcoa",
    "wof:name":"Garbi-berri Tintoreria, L.l.",
    "wof:placetype":"venue"
},
  "geometry": {"coordinates":[-1.975456953,43.2670516968],"type":"Point"}
}