{
  "type": "Feature",
  "properties": {
    "addr:full":"Rua Bernardo Sagasta, 31 Cuntis Pontevedra 36670",
    "addr:housenumber":"31",
    "addr:postcode":"36670",
    "addr:street":"Rua Bernardo Sagasta",
    "iso:country":"ES",
    "sg:address":"Rua Bernardo Sagasta, 31",
    "sg:city":"Cuntis",
    "sg:orig_category":"Quincaller\u00cda (al Por Menor)",
    "sg:phone":"+34 986 53 24 86",
    "sg:postcode":"36670",
    "sg:province":"Pontevedra",
    "wof:name":"Fergal Sociedad Cooperativa",
    "wof:placetype":"venue"
},
  "geometry": {"coordinates":[-8.5611791611,42.6424484253],"type":"Point"}
}