{
  "type": "Feature",
  "properties": {
    "iso:country":"ES",
    "sg:address":"Ctra Rellinars, 89",
    "sg:city":"Terrassa",
    "sg:orig_category":"Electricidad, Electr\u00d3nica: Material Y Suministros (al Por Mayor)",
    "sg:phone":"+34 937 89 40 52",
    "sg:postcode":"08225",
    "sg:province":"Barcelona",
    "wof:name":"Electronica Toni Torres S.l.i.",
    "wof:placetype":"venue"
},
  "geometry": {"coordinates":[2.0087630749,41.5725097656],"type":"Point"}
}