{
  "type": "Feature",
  "properties": {
    "iso:country":"ES",
    "sg:address":"Cristo Cedia, 7",
    "sg:city":"Carmona",
    "sg:orig_category":"Agricultura: Abastecimiento Y Cosechado (negocio)",
    "sg:phone":"+34 954 14 36 55",
    "sg:postcode":"41410",
    "sg:province":"Sevilla",
    "wof:name":"Justo Leon Mercedes",
    "wof:placetype":"venue"
},
  "geometry": {"coordinates":[-5.6414179802,37.4762840271],"type":"Point"}
}