{
  "type": "Feature",
  "properties": {
    "addr:full":"Estd A Portela, 84 Redondela Pontevedra 36800",
    "addr:housenumber":"84",
    "addr:postcode":"36800",
    "addr:street":"Estd;Portela",
    "iso:country":"ES",
    "sg:address":"Estd A Portela, 84",
    "sg:city":"Redondela",
    "sg:orig_category":"Materias Pl\u00c1sticas: Productos De Consumo Masivo (fabricaci\u00d3n, Al Por Mayor)",
    "sg:phone":"+34 986 40 80 32",
    "sg:postcode":"36800",
    "sg:province":"Pontevedra",
    "wof:name":"Peguform Iberica S.l.",
    "wof:placetype":"venue"
},
  "geometry": {"coordinates":[-8.6090641022,42.2820243835],"type":"Point"}
}