{
  "type": "Feature",
  "properties": {
    "iso:country":"ES",
    "sg:address":"Carrer de Jesus Pobre (de), 8",
    "sg:city":"Gata Gorgos",
    "sg:orig_category":"Mec\u00c1nico Del Autom\u00d3vil",
    "sg:phone":"+34 965 75 68 86",
    "sg:postcode":"03740",
    "sg:province":"Alicante",
    "wof:name":"David Font Jose",
    "wof:placetype":"venue"
},
  "geometry": {"coordinates":[0.0841569975,38.7779693604],"type":"Point"}
}