{
  "type": "Feature",
  "properties": {
    "addr:full":"Calle de Celso Amieva, S/n Llanes Asturias 33500",
    "addr:housenumber":"s / n",
    "addr:postcode":"33500",
    "addr:street":"Calle De Celso Amieva",
    "iso:country":"ES",
    "sg:address":"Calle de Celso Amieva, S/n",
    "sg:city":"Llanes",
    "sg:orig_category":"Partidos Pol\u00cdticos",
    "sg:phone":"+34 985 40 06 01",
    "sg:postcode":"33500",
    "sg:province":"Asturias",
    "wof:name":"Partido Popular",
    "wof:placetype":"venue"
},
  "geometry": {"coordinates":[-4.7591786385,43.4234352112],"type":"Point"}
}