{
  "type": "Feature",
  "properties": {
    "iso:country":"ES",
    "sg:address":"Plaz Espa\u00d1a, 13",
    "sg:city":"Herencia",
    "sg:orig_category":"Distribuci\u00d3n De Petr\u00d3leo Y Derivados",
    "sg:phone":"+34 926 57 10 41",
    "sg:postcode":"13640",
    "sg:province":"Ciudad Real",
    "wof:name":"Gomez Martinez Jose Luis",
    "wof:placetype":"venue"
},
  "geometry": {"coordinates":[-3.3544049263,39.3669013977],"type":"Point"}
}