{
  "type": "Feature",
  "properties": {
    "addr:full":"Pque Emp Areas, 25 Tui Pontevedra 36711",
    "addr:housenumber":"25",
    "addr:postcode":"36711",
    "iso:country":"ES",
    "sg:address":"Pque Emp Areas, 25",
    "sg:city":"Tui",
    "sg:orig_category":"Fabricaci\u00d3n De Bolsos Y Bolsos De Tela",
    "sg:phone":"+34 986 60 71 50",
    "sg:postcode":"36711",
    "sg:province":"Pontevedra",
    "wof:name":"Sacos Ibericos De Papel S.l.",
    "wof:placetype":"venue"
},
  "geometry": {"coordinates":[-8.6667318344,42.034992218],"type":"Point"}
}