{
  "type": "Feature",
  "properties": {
    "iso:country":"ES",
    "sg:address":"C/ Almassera, 11",
    "sg:city":"Elche",
    "sg:orig_category":"Promotores Constructores",
    "sg:phone":"+34 966 61 42 65",
    "sg:postcode":"03203",
    "sg:province":"Alicante",
    "wof:name":"Construcciones Y Estudios S.a.",
    "wof:placetype":"venue"
},
  "geometry": {"coordinates":[-0.6980199814,38.2646827698],"type":"Point"}
}