{
  "type": "Feature",
  "properties": {
    "iso:country":"ES",
    "sg:address":"Calle de Cercadillo (el), S/n",
    "sg:city":"Casas",
    "sg:orig_category":"Semiller\u00cdas",
    "sg:phone":"+34 928 57 13 37",
    "sg:postcode":"35217",
    "sg:province":"Las Palmas",
    "wof:name":"Ortega Sanchez Antonio",
    "wof:placetype":"venue"
},
  "geometry": {"coordinates":[-15.4922561646,27.9919910431],"type":"Point"}
}