{
  "type": "Feature",
  "properties": {
    "iso:country":"ES",
    "sg:address":"Carr Doctor Lleonart, 5",
    "sg:city":"Burjassot",
    "sg:orig_category":"Promotores Constructores",
    "sg:phone":"+34 963 90 00 87",
    "sg:postcode":"46100",
    "sg:province":"Valencia",
    "wof:name":"Valencia Urbana S. A.",
    "wof:placetype":"venue"
},
  "geometry": {"coordinates":[-0.4141789973,39.5069885254],"type":"Point"}
}