{
  "type": "Feature",
  "properties": {
    "iso:country":"ES",
    "sg:address":"Calle de Franchy Y Roca, 29",
    "sg:city":"Pto. Rosario",
    "sg:orig_category":"Chapister\u00cda",
    "sg:phone":"+34 928 53 00 54",
    "sg:postcode":"35600",
    "sg:province":"Las Palmas",
    "wof:name":"Cruz Monserrat Juan Jose De La",
    "wof:placetype":"venue"
},
  "geometry": {"coordinates":[-13.8664512634,28.5053501129],"type":"Point"}
}