{
  "type": "Feature",
  "properties": {
    "iso:country":"ES",
    "sg:address":"Calle de Ramon Y Cajal, 9",
    "sg:city":"Poligono Industrial Los Villares",
    "sg:orig_category":"Suministros Para Carrocer\u00cdas",
    "sg:phone":"+34 923 22 15 83",
    "sg:postcode":"37184",
    "sg:province":"Salamanca",
    "wof:name":"Torres Zamarre\u00f1o Emilio",
    "wof:placetype":"venue"
},
  "geometry": {"coordinates":[-5.6680355072,40.965385437],"type":"Point"}
}