{
  "type": "Feature",
  "properties": {
    "addr:full":"Calle de Ramon Y Cajal, 9 Poligono Industrial Los Villares Salamanca 37184",
    "addr:housenumber":"9 poligono",
    "addr:postcode":"37184",
    "addr:street":"Calle De Ramon Y Cajal;Industrial Los",
    "iso:country":"ES",
    "sg:address":"Calle de Ramon Y Cajal, 9",
    "sg:city":"Poligono Industrial Los Villares",
    "sg:orig_category":"Suministros Para Carrocer\u00cdas",
    "sg:phone":"+34 923 22 15 83",
    "sg:postcode":"37184",
    "sg:province":"Salamanca",
    "wof:name":"Torres Zamarre\u00f1o Emilio",
    "wof:placetype":"venue"
},
  "geometry": {"coordinates":[-5.6680355072,40.965385437],"type":"Point"}
}