{
  "type": "Feature",
  "properties": {
    "iso:country":"ES",
    "sg:address":"Calle de Camilo Jose Cela, 2",
    "sg:city":"Guadalajara",
    "sg:orig_category":"Centros Comerciales Y Grandes Tiendas",
    "sg:phone":"+34 949 21 26 47",
    "sg:postcode":"19004",
    "sg:province":"Guadalajara",
    "wof:name":"Olivares Del Valle Maria Dolores",
    "wof:placetype":"venue"
},
  "geometry": {"coordinates":[-3.1828503609,40.6389427185],"type":"Point"}
}