{
  "type": "Feature",
  "properties": {
    "addr:full":"Calle de Ricafort, 9 Huesca Huesca 22002",
    "addr:housenumber":"9",
    "addr:postcode":"22002",
    "addr:street":"Calle De Ricafort",
    "iso:country":"ES",
    "sg:address":"Calle de Ricafort, 9",
    "sg:city":"Huesca",
    "sg:orig_category":"M\u00c1quinas De Coser Y De Hacer Punto (al Por Mayor)",
    "sg:phone":"+34 974 24 67 60",
    "sg:postcode":"22002",
    "sg:province":"Huesca",
    "wof:name":"Casbas Gracia Fernando",
    "wof:placetype":"venue"
},
  "geometry": {"coordinates":[-0.4088590145,42.1401786804],"type":"Point"}
}