{
  "type": "Feature",
  "properties": {
    "iso:country":"ES",
    "sg:address":"Calle de Campo De Dalias, S/n",
    "sg:city":"Almeria",
    "sg:orig_category":"Trabajos De Soldaduras",
    "sg:phone":"+34 950 27 30 50",
    "sg:postcode":"04008",
    "sg:province":"Almer\u00eda",
    "wof:name":"Asensio Herrerias Jose",
    "wof:placetype":"venue"
},
  "geometry": {"coordinates":[-2.4950428009,36.8688850403],"type":"Point"}
}