{
  "type": "Feature",
  "properties": {
    "addr:full":"Calle de Tafetana, 19 G\u00fcimar Santa Cruz De Tenerife 38500",
    "addr:housenumber":"19",
    "addr:postcode":"38500",
    "addr:street":"Calle De Tafetana",
    "iso:country":"ES",
    "sg:address":"Calle de Tafetana, 19",
    "sg:city":"G\u00fcimar",
    "sg:orig_category":"M\u00c9dicos: Ginecolog\u00cda Y Obstetricia",
    "sg:phone":"+34 922 51 05 00",
    "sg:postcode":"38500",
    "sg:province":"Santa Cruz De Tenerife",
    "wof:name":"Fernandez Robayna Cristobal Francisco",
    "wof:placetype":"venue"
},
  "geometry": {"coordinates":[-16.4107131958,28.3140182495],"type":"Point"}
}