{
  "type": "Feature",
  "properties": {
    "iso:country":"ES",
    "sg:address":"Calle de Virgen De La Alegria, S/n",
    "sg:city":"Madrid",
    "sg:orig_category":"Iglesia Cat\u00d3lica",
    "sg:phone":"+34 914 04 53 91",
    "sg:postcode":"28027",
    "sg:province":"Madrid",
    "wof:name":"Parroquia Nuestra Se\u00f1ora Del Coro",
    "wof:placetype":"venue"
},
  "geometry": {"coordinates":[-3.6555991173,40.4351615906],"type":"Point"}
}