{
  "type": "Feature",
  "properties": {
    "addr:full":"Calle de Republica Argentina, 10 Badajoz Badajoz 06005",
    "addr:housenumber":"10",
    "addr:postcode":"06005",
    "addr:street":"Calle De Republica Argentina",
    "iso:country":"ES",
    "sg:address":"Calle de Republica Argentina, 10",
    "sg:city":"Badajoz",
    "sg:orig_category":"Ense\u00d1anza: Profesiones Art\u00cdsticas",
    "sg:phone":"+34 924 24 24 04",
    "sg:postcode":"06005",
    "sg:province":"Badajoz",
    "wof:name":"Lopez-lago Romero Manuel",
    "wof:placetype":"venue"
},
  "geometry": {"coordinates":[-6.9781861305,38.8735542297],"type":"Point"}
}