{
  "type": "Feature",
  "properties": {
    "iso:country":"ES",
    "sg:address":"Carcacia, S/n",
    "sg:city":"Padron",
    "sg:orig_category":"Plomeros",
    "sg:phone":"+34 981 19 21 76",
    "sg:postcode":"15900",
    "sg:province":"La Coru\u00f1a",
    "wof:name":"Penedo Mosquera Jose Manuel",
    "wof:placetype":"venue"
},
  "geometry": {"coordinates":[-8.6591444016,42.7387466431],"type":"Point"}
}