{
  "type": "Feature",
  "properties": {
    "iso:country":"ES",
    "sg:address":"Calle de Travessia, 26",
    "sg:city":"Novelda",
    "sg:orig_category":"Agencias Y Agentes Comerciales, Representantes",
    "sg:phone":"+34 965 60 12 70",
    "sg:postcode":"03660",
    "sg:province":"Alicante",
    "wof:name":"Carrillo Cobollo Raquel",
    "wof:placetype":"venue"
},
  "geometry": {"coordinates":[-0.7626670003,38.3857192993],"type":"Point"}
}