{
  "type": "Feature",
  "properties": {
    "addr:full":"Calle de Reales Alcazares, 41 Alhaurin Torre M\u00e1laga 29130",
    "addr:housenumber":"41",
    "addr:postcode":"29130",
    "addr:street":"Calle De Reales Alcazares",
    "iso:country":"ES",
    "sg:address":"Calle de Reales Alcazares, 41",
    "sg:city":"Alhaurin Torre",
    "sg:orig_category":"Droguer\u00cdas (al Por Mayor)",
    "sg:phone":"+34 952 96 38 23",
    "sg:postcode":"29130",
    "sg:province":"M\u00e1laga",
    "wof:name":"Marin Rios Claudia Patricxia",
    "wof:placetype":"venue"
},
  "geometry": {"coordinates":[-4.5589590073,36.6634407043],"type":"Point"}
}