{
  "type": "Feature",
  "properties": {
    "iso:country":"ES",
    "sg:address":"Pase Monica Plaza, 12",
    "sg:city":"Cervera Pisuerga",
    "sg:orig_category":"Veh\u00cdculos De Ocasi\u00d3n",
    "sg:phone":"+34 979 87 01 31",
    "sg:postcode":"34840",
    "sg:province":"Palencia",
    "wof:name":"Autos Avelino S.l.",
    "wof:placetype":"venue"
},
  "geometry": {"coordinates":[-4.5311746597,42.0124588013],"type":"Point"}
}