{
  "type": "Feature",
  "properties": {
    "iso:country":"ES",
    "sg:address":"Avgd Catalunya, 15",
    "sg:city":"Lleida",
    "sg:orig_category":"Bancos",
    "sg:phone":"+34 973 27 17 00",
    "sg:postcode":"25002",
    "sg:province":"Lleida",
    "wof:name":"Banco Popular Espa\u00f1ol S. A.",
    "wof:placetype":"venue"
},
  "geometry": {"coordinates":[0.6205109954,41.6114425659],"type":"Point"}
}