{
  "type": "Feature",
  "properties": {
    "addr:full":"Calle de Gran Via De Jose Antonio Agirre Y Lekube, 13 Sestao Vizcaya 48910",
    "addr:housenumber":"13",
    "addr:postcode":"48910",
    "addr:street":"Calle De Gran Via De Jose Antonio Agirre Y Lekube",
    "iso:country":"ES",
    "sg:address":"Calle de Gran Via De Jose Antonio Agirre Y Lekube, 13",
    "sg:city":"Sestao",
    "sg:orig_category":"Ense\u00d1anza, Formaci\u00d3n Profesional: Aprendizaje",
    "sg:phone":"+34 944 96 78 12",
    "sg:postcode":"48910",
    "sg:province":"Vizcaya",
    "wof:name":"Ayuntamiento De Sestao-escuela De Musica",
    "wof:placetype":"venue"
},
  "geometry": {"coordinates":[-3.0000603199,43.3071403503],"type":"Point"}
}