{
  "type": "Feature",
  "properties": {
    "iso:country":"ES",
    "sg:address":"Calle de Javier Echevarria, 6",
    "sg:city":"Castro Urdiales",
    "sg:orig_category":"Peluquer\u00cdas, Peluquer\u00cda Mixta",
    "sg:phone":"+34 942 87 09 60",
    "sg:postcode":"39700",
    "sg:province":"Cantabria",
    "wof:name":"Merino Gonzalez Maria Jose",
    "wof:placetype":"venue"
},
  "geometry": {"coordinates":[-3.219825983,43.3822784424],"type":"Point"}
}