{
  "type": "Feature",
  "properties": {
    "addr:full":"Carrer de L'alcalde De Mostoles, 33 Barcelona Barcelona 08025",
    "addr:housenumber":"33",
    "addr:postcode":"08025",
    "addr:street":"Carrer De L'Alcalde De Mostoles",
    "iso:country":"ES",
    "sg:address":"Carrer de L'alcalde De Mostoles, 33",
    "sg:city":"Barcelona",
    "sg:orig_category":"Farmacias",
    "sg:phone":"+34 934 55 30 36",
    "sg:postcode":"08025",
    "sg:province":"Barcelona",
    "wof:name":"Muzas Cucalon Maria",
    "wof:placetype":"venue"
},
  "geometry": {"coordinates":[2.1658856869,41.4110183716],"type":"Point"}
}