{
  "type": "Feature",
  "properties": {
    "iso:country":"ES",
    "sg:address":"Calle de Monsalves, 6",
    "sg:city":"Sevilla",
    "sg:orig_category":"Pod\u00d3logos: Pedicuros",
    "sg:phone":"+34 954 21 50 50",
    "sg:postcode":"41001",
    "sg:province":"Sevilla",
    "wof:name":"Toledo Lopez Anade",
    "wof:placetype":"venue"
},
  "geometry": {"coordinates":[-5.9976358414,37.3922653198],"type":"Point"}
}