{
  "type": "Feature",
  "properties": {
    "addr:full":"Carr Del Doctor Pons, 12 S. Rafael Rio Castell\u00f3n 12510",
    "addr:housenumber":"12",
    "addr:postcode":"12510",
    "addr:street":"Carr Del Doctor Pons;S. Rafael Rio Castello\u0301N",
    "iso:country":"ES",
    "sg:address":"Carr Del Doctor Pons, 12",
    "sg:city":"S. Rafael Rio",
    "sg:orig_category":"Art\u00cdculos De Regalo (al Por Menor)",
    "sg:phone":"+34 977 57 08 08",
    "sg:postcode":"12510",
    "sg:province":"Castell\u00f3n",
    "wof:name":"Verge Andres Rita",
    "wof:placetype":"venue"
},
  "geometry": {"coordinates":[0.3464699984,40.6063156128],"type":"Point"}
}