{
  "type": "Feature",
  "properties": {
    "addr:full":"Calle de Martin Mendia, 1 Balmaseda Vizcaya 48800",
    "addr:housenumber":"1",
    "addr:postcode":"48800",
    "addr:street":"Calle De Martin Mendia",
    "iso:country":"ES",
    "sg:address":"Calle de Martin Mendia, 1",
    "sg:city":"Balmaseda",
    "sg:orig_category":"Agentes Generales De Seguros",
    "sg:phone":"+34 946 80 02 56",
    "sg:postcode":"48800",
    "sg:province":"Vizcaya",
    "wof:name":"Mapfre Servicios De Informatica",
    "wof:placetype":"venue"
},
  "geometry": {"coordinates":[-3.1925780773,43.1950645447],"type":"Point"}
}