{
  "type": "Feature",
  "properties": {
    "addr:full":"Calle de Lopez De Hoyos, 124 Madrid Madrid 28002",
    "addr:housenumber":"124",
    "addr:postcode":"28002",
    "addr:street":"Calle De Lopez De Hoyos",
    "iso:country":"ES",
    "sg:address":"Calle de Lopez De Hoyos, 124",
    "sg:city":"Madrid",
    "sg:orig_category":"\u00d3ptica: Instrumentos (fabricaci\u00d3n)",
    "sg:phone":"+34 914 16 58 45",
    "sg:postcode":"28002",
    "sg:province":"Madrid",
    "wof:name":"Sanchez Galiano Fernandez Ernesto",
    "wof:placetype":"venue"
},
  "geometry": {"coordinates":[-3.6735219955,40.4444274902],"type":"Point"}
}