{
  "type": "Feature",
  "properties": {
    "iso:country":"ES",
    "sg:address":"Calle de Mercadillo, 2",
    "sg:city":"Coria",
    "sg:orig_category":"Carnicer\u00cdas, Carnicer\u00cdas",
    "sg:phone":"+34 927 50 39 53",
    "sg:postcode":"10800",
    "sg:province":"C\u00e1ceres",
    "wof:name":"Martin Bravo Maria Jose",
    "wof:placetype":"venue"
},
  "geometry": {"coordinates":[-6.5354070663,39.9847450256],"type":"Point"}
}