{
  "type": "Feature",
  "properties": {
    "addr:full":"Luga Marchena, S/n Marchena Murcia 30815",
    "addr:housenumber":"s",
    "addr:postcode":"30815",
    "addr:street":"Marchena;/ N",
    "iso:country":"ES",
    "sg:address":"Luga Marchena, S/n",
    "sg:city":"Marchena",
    "sg:orig_category":"Alimentaci\u00d3n General (al Por Mayor)",
    "sg:phone":"+34 968 44 10 51",
    "sg:postcode":"30815",
    "sg:province":"Murcia",
    "wof:name":"Vesol 2002 S.l.",
    "wof:placetype":"venue"
},
  "geometry": {"coordinates":[-1.5774840117,37.5886192322],"type":"Point"}
}