{
  "type": "Feature",
  "properties": {
    "addr:full":"Carrer de Valencia, 204 Barcelona Barcelona 08011",
    "addr:housenumber":"204",
    "addr:postcode":"08011",
    "addr:street":"Carrer De Valencia",
    "iso:country":"ES",
    "sg:address":"Carrer de Valencia, 204",
    "sg:city":"Barcelona",
    "sg:orig_category":"Restaurantes",
    "sg:phone":"+34 934 51 94 46",
    "sg:postcode":"08011",
    "sg:province":"Barcelona",
    "wof:name":"Yamashita S.a.",
    "wof:placetype":"venue"
},
  "geometry": {"coordinates":[2.1582787037,41.388885498],"type":"Point"}
}