{
  "type": "Feature",
  "properties": {
    "addr:full":"Pase Pocillo, 24 San Ildefonso O La Granja Segovia 40100",
    "addr:housenumber":"24",
    "addr:postcode":"40100",
    "addr:street":"Pocillo;O",
    "iso:country":"ES",
    "sg:address":"Pase Pocillo, 24",
    "sg:city":"San Ildefonso O La Granja",
    "sg:orig_category":"Empresarios Y Productoras De Espect\u00c1culos",
    "sg:phone":"+34 921 47 09 39",
    "sg:postcode":"40100",
    "sg:province":"Segovia",
    "wof:name":"Merlo Ornella Angelica",
    "wof:placetype":"venue"
},
  "geometry": {"coordinates":[-4.0079989433,40.8997459412],"type":"Point"}
}