{
  "type": "Feature",
  "properties": {
    "addr:full":"Vila-romana, 7 Sarria Ter Girona 17840",
    "addr:housenumber":"7",
    "addr:postcode":"17840",
    "addr:street":"Vila-Romana;Ter",
    "iso:country":"ES",
    "sg:address":"Vila-romana, 7",
    "sg:city":"Sarria Ter",
    "sg:orig_category":"Alimentaci\u00d3n General (al Por Menor)",
    "sg:phone":"+34 972 17 07 78",
    "sg:postcode":"17840",
    "sg:province":"Girona",
    "wof:name":"Vizcaino Martinez Ramona",
    "wof:placetype":"venue"
},
  "geometry": {"coordinates":[2.8155407906,42.0156593323],"type":"Point"}
}