{
  "type": "Feature",
  "properties": {
    "addr:full":"Calle de Huertas (las), 4 Algeciras C\u00e1diz 11201",
    "addr:housenumber":"4;ca\u0301diz",
    "addr:postcode":"11201",
    "addr:street":"Calle De Huertas Las",
    "iso:country":"ES",
    "sg:address":"Calle de Huertas (las), 4",
    "sg:city":"Algeciras",
    "sg:orig_category":"Bisuter\u00cda, Joyer\u00cda, Relojer\u00cda (al Por Menor)",
    "sg:phone":"+34 956 65 46 13",
    "sg:postcode":"11201",
    "sg:province":"C\u00e1diz",
    "wof:name":"Rios Olmedo Francisca",
    "wof:placetype":"venue"
},
  "geometry": {"coordinates":[-5.4465761185,36.1285362244],"type":"Point"}
}