{
  "type": "Feature",
  "properties": {
    "addr:full":"Calle de Juan De Las Vi\u00d1as, 3 Cartuja Baja Zaragoza 50720",
    "addr:housenumber":"3",
    "addr:postcode":"50720",
    "addr:street":"Calle De Juan De Las Vin\u0303As;Baja",
    "iso:country":"ES",
    "sg:address":"Calle de Juan De Las Vi\u00d1as, 3",
    "sg:city":"Cartuja Baja",
    "sg:orig_category":"Supermercados Y Hipermercados",
    "sg:phone":"+34 976 50 05 18",
    "sg:postcode":"50720",
    "sg:province":"Zaragoza",
    "wof:name":"Prades Alimentacion S.l.",
    "wof:placetype":"venue"
},
  "geometry": {"coordinates":[-0.8246139884,41.6071166992],"type":"Point"}
}