{
  "type": "Feature",
  "properties": {
    "iso:country":"ES",
    "sg:address":"Calle de Alferez Provisional, 8",
    "sg:city":"Oviedo",
    "sg:orig_category":"Bisuter\u00cda, Joyer\u00cda, Relojer\u00cda (al Por Menor)",
    "sg:phone":"+34 985 23 69 59",
    "sg:postcode":"33005",
    "sg:province":"Asturias",
    "wof:name":"Joyeria Opalo S.l.",
    "wof:placetype":"venue"
},
  "geometry": {"coordinates":[-5.8548746109,43.3607749939],"type":"Point"}
}