{
  "type": "Feature",
  "properties": {
    "addr:full":"Mercat Sant Antoni, 213 Barcelona Barcelona 08015",
    "addr:housenumber":"213",
    "addr:postcode":"08015",
    "iso:country":"ES",
    "sg:address":"Mercat Sant Antoni, 213",
    "sg:city":"Barcelona",
    "sg:orig_category":"Frutas, Legumbres Frescas Y Tempranas (al Por Menor)",
    "sg:phone":"+34 933 25 18 71",
    "sg:postcode":"08015",
    "sg:province":"Barcelona",
    "wof:name":"Fernandez Recio Jose",
    "wof:placetype":"venue"
},
  "geometry": {"coordinates":[2.1603300571,41.379108429],"type":"Point"}
}