{
  "type": "Feature",
  "properties": {
    "addr:full":"Calle de Eugenio Oneguin, S/n Malaga M\u00e1laga 29006",
    "addr:housenumber":"s",
    "addr:postcode":"29006",
    "addr:street":"Calle De Eugenio Oneguin;/ N;Ma\u0301Laga",
    "iso:country":"ES",
    "sg:address":"Calle de Eugenio Oneguin, S/n",
    "sg:city":"Malaga",
    "sg:orig_category":"Servicios De Telecomunicaciones",
    "sg:phone":"+34 952 04 05 28",
    "sg:postcode":"29006",
    "sg:province":"M\u00e1laga",
    "wof:name":"Sidecoan S.l.",
    "wof:placetype":"venue"
},
  "geometry": {"coordinates":[-4.4640240669,36.7114982605],"type":"Point"}
}