{
  "type": "Feature",
  "properties": {
    "addr:full":"Calle de Rector Benito Rodriguez Rios, 4 Tope Santa Cruz De Tenerife 38400",
    "addr:housenumber":"4",
    "addr:postcode":"38400",
    "addr:street":"Calle De Rector Benito Rodriguez Rios",
    "iso:country":"ES",
    "sg:address":"Calle de Rector Benito Rodriguez Rios, 4",
    "sg:city":"Tope",
    "sg:orig_category":"Farmacias",
    "sg:phone":"+34 922 37 19 27",
    "sg:postcode":"38400",
    "sg:province":"Santa Cruz De Tenerife",
    "wof:name":"Bello Toledo Blanca Rosa",
    "wof:placetype":"venue"
},
  "geometry": {"coordinates":[-16.5419540405,28.4112854004],"type":"Point"}
}