{
  "type": "Feature",
  "properties": {
    "addr:full":"Ctra Tarragona, Km. 0307,0 Vendrell Tarragona 43700",
    "addr:postcode":"43700",
    "addr:street":"Ctra Tarragona Km. 0307,0",
    "iso:country":"ES",
    "sg:address":"Ctra Tarragona, Km. 0307,0",
    "sg:city":"Vendrell",
    "sg:orig_category":"Agentes, Concesionarios Y Sucursales De Veh\u00cdculos",
    "sg:phone":"+34 977 66 15 00",
    "sg:postcode":"43700",
    "sg:province":"Tarragona",
    "wof:name":"Auto Garage Vendrell S.l.",
    "wof:placetype":"venue"
},
  "geometry": {"coordinates":[1.5381799936,41.2216491699],"type":"Point"}
}