{
  "type": "Feature",
  "properties": {
    "addr:full":"Calle de E, 28 Mutiloabeiti Navarra 31192",
    "addr:housenumber":"28",
    "addr:postcode":"31192",
    "addr:street":"Calle De E",
    "iso:country":"ES",
    "sg:address":"Calle de E, 28",
    "sg:city":"Mutiloabeiti",
    "sg:orig_category":"Fabricaci\u00d3n De Material Y Sistemas De Se\u00d1alizaci\u00d3n De Carreteras, Urbanos Y De Obras",
    "sg:phone":"+34 948 23 85 57",
    "sg:postcode":"31192",
    "sg:province":"Navarra",
    "wof:name":"Signos Viales S.l.",
    "wof:placetype":"venue"
},
  "geometry": {"coordinates":[-1.6230969429,42.7886924744],"type":"Point"}
}