{
  "type": "Feature",
  "properties": {
    "iso:country":"ES",
    "sg:address":"Rua Diego Pazos, 91",
    "sg:city":"Sarria",
    "sg:orig_category":"Peluquer\u00cdas, Peluquer\u00cda Mixta",
    "sg:phone":"+34 982 53 22 03",
    "sg:postcode":"27600",
    "sg:province":"Lugo",
    "wof:name":"Rubianes Bola\u00f1o Maria Luz",
    "wof:placetype":"venue"
},
  "geometry": {"coordinates":[-7.4095129967,42.781879425],"type":"Point"}
}