{
  "type": "Feature",
  "properties": {
    "addr:full":"Avda Deporte, 11 Villanueva Alcardete Toledo 45810",
    "addr:housenumber":"11",
    "addr:postcode":"45810",
    "addr:street":"Avda Deporte",
    "iso:country":"ES",
    "sg:address":"Avda Deporte, 11",
    "sg:city":"Villanueva Alcardete",
    "sg:orig_category":"Venta, Colocaci\u00d3n De Moquetas, Revestimiento De Suelos Y De Paredes",
    "sg:phone":"+34 925 16 61 80",
    "sg:postcode":"45810",
    "sg:province":"Toledo",
    "wof:name":"Roldan Garrido Juan De La Cruz",
    "wof:placetype":"venue"
},
  "geometry": {"coordinates":[-3.0230939388,39.6739006042],"type":"Point"}
}