{
  "type": "Feature",
  "properties": {
    "addr:full":"Calle de Doctor Manzanera, 14 Almansa Albacete 02640",
    "addr:housenumber":"14",
    "addr:postcode":"02640",
    "addr:street":"Calle De Doctor Manzanera",
    "iso:country":"ES",
    "sg:address":"Calle de Doctor Manzanera, 14",
    "sg:city":"Almansa",
    "sg:classifiers":[
        {
            "category":"Personal",
            "subcategory":"Barber",
            "type":"Services"
        }
    ],
    "sg:phone":"+34 967 34 42 19",
    "sg:postcode":"02640",
    "sg:province":"Albacete",
    "sg:tags":[
        "caballeros",
        "de",
        "peluqueros"
    ],
    "wof:name":"Navarro Alcaraz Miguel",
    "wof:placetype":"venue"
},
  "geometry": {"coordinates":[-1.0914423466,38.8653335571],"type":"Point"}
}