{
  "type": "Feature",
  "properties": {
    "addr:full":"Calle de Moreno Nieto, 15 Madrid Madrid 28005",
    "addr:housenumber":"15",
    "addr:postcode":"madrid;28005",
    "addr:street":"Calle De Moreno Nieto",
    "iso:country":"ES",
    "sg:address":"Calle de Moreno Nieto, 15",
    "sg:city":"Madrid",
    "sg:orig_category":"Perfumer\u00cda (al Por Menor)",
    "sg:phone":"+34 913 64 54 98",
    "sg:postcode":"28005",
    "sg:province":"Madrid",
    "wof:name":"Fresno Sanchez Manuel",
    "wof:placetype":"venue"
},
  "geometry": {"coordinates":[-3.7203109264,40.4119110107],"type":"Point"}
}