{
  "type": "Feature",
  "properties": {
    "addr:full":"Calle de Fernandez De Cordoba, 5 Cordoba C\u00f3rdoba 14009",
    "addr:housenumber":"5",
    "addr:postcode":"14009",
    "addr:street":"Calle De Fernandez De Cordoba;Co\u0301Rdoba",
    "iso:country":"ES",
    "sg:address":"Calle de Fernandez De Cordoba, 5",
    "sg:city":"Cordoba",
    "sg:orig_category":"Chapister\u00cda",
    "sg:phone":"+34 957 20 15 92",
    "sg:postcode":"14009",
    "sg:province":"C\u00f3rdoba",
    "wof:name":"Benito Raya Aranda S.l.",
    "wof:placetype":"venue"
},
  "geometry": {"coordinates":[-4.7734498978,37.8753967285],"type":"Point"}
}