{
  "type": "Feature",
  "properties": {
    "addr:full":"Afores, S/n Cabrianes Barcelona 08650",
    "addr:housenumber":"s / n",
    "addr:postcode":"08650",
    "addr:street":"Afores",
    "iso:country":"ES",
    "sg:address":"Afores, S/n",
    "sg:city":"Cabrianes",
    "sg:orig_category":"Empresas De Hormig\u00d3n, Hormig\u00d3n Armado Y Pretensado",
    "sg:phone":"+34 938 37 22 00",
    "sg:postcode":"08650",
    "sg:province":"Barcelona",
    "wof:name":"Norden S.a.",
    "wof:placetype":"venue"
},
  "geometry": {"coordinates":[1.8966200352,41.8131904602],"type":"Point"}
}