{
  "type": "Feature",
  "properties": {
    "addr:full":"Praz Mercedes (das), S/n Ourense Ourense 32004",
    "addr:postcode":"32004",
    "addr:street":"S / N",
    "iso:country":"ES",
    "sg:address":"Praz Mercedes (das), S/n",
    "sg:city":"Ourense",
    "sg:orig_category":"Centros De Educaci\u00d3n Especial",
    "sg:phone":"+34 988 24 35 81",
    "sg:postcode":"32004",
    "sg:province":"Ourense",
    "wof:name":"Colexio Educacion Infantil Y Primaria As Mercedes",
    "wof:placetype":"venue"
},
  "geometry": {"coordinates":[-7.8624958992,42.3383750916],"type":"Point"}
}