{
  "type": "Feature",
  "properties": {
    "addr:full":"Calle de Maria Cristina, S/n Nerva Huelva 21670",
    "addr:housenumber":"s / n",
    "addr:postcode":"21670",
    "addr:street":"Calle De Maria Cristina",
    "iso:country":"ES",
    "sg:address":"Calle de Maria Cristina, S/n",
    "sg:city":"Nerva",
    "sg:orig_category":"Naipes, Carteles, Artilugios",
    "sg:phone":"+34 959 58 14 40",
    "sg:postcode":"21670",
    "sg:province":"Huelva",
    "wof:name":"Herrera Rodriguez Alfonso",
    "wof:placetype":"venue"
},
  "geometry": {"coordinates":[-6.5506339073,37.6937408447],"type":"Point"}
}