{
  "type": "Feature",
  "properties": {
    "iso:country":"ES",
    "sg:address":"Avda Constitucion, 49",
    "sg:city":"Cebreros",
    "sg:orig_category":"Molduras, Junquillos, Listones Y Molduras Perforadas",
    "sg:phone":"+34 918 63 21 02",
    "sg:postcode":"05260",
    "sg:province":"\u00c1vila",
    "wof:name":"Diaz Garcia Jose Luis",
    "wof:placetype":"venue"
},
  "geometry": {"coordinates":[-4.4645190239,40.4591255188],"type":"Point"}
}