{
  "type": "Feature",
  "properties": {
    "iso:country":"ES",
    "sg:address":"Carrer de Joaquim Verdaguer, 1",
    "sg:city":"Arenal",
    "sg:orig_category":"Alquiler De Veh\u00cdculos: Turismos Y Utilitarios",
    "sg:phone":"+34 971 74 32 75",
    "sg:postcode":"07600",
    "sg:province":"Islas Baleares",
    "wof:name":"Overcar S.l.",
    "wof:placetype":"venue"
},
  "geometry": {"coordinates":[2.7505669594,39.5084686279],"type":"Point"}
}