{
  "type": "Feature",
  "properties": {
    "iso:country":"ES",
    "sg:address":"Calle de Obispo Soler, 14",
    "sg:city":"Valencia",
    "sg:orig_category":"Farmacias",
    "sg:phone":"+34 963 47 91 28",
    "sg:postcode":"46015",
    "sg:province":"Valencia",
    "wof:name":"Masia Samper Rosa Maria",
    "wof:placetype":"venue"
},
  "geometry": {"coordinates":[-0.3960539997,39.4822921753],"type":"Point"}
}