{
  "type": "Feature",
  "properties": {
    "addr:full":"Calle de General Oraa, 46 Madrid Madrid 28006",
    "addr:housenumber":"46",
    "addr:postcode":"madrid;28006",
    "addr:street":"Calle De General Oraa",
    "iso:country":"ES",
    "sg:address":"Calle de General Oraa, 46",
    "sg:city":"Madrid",
    "sg:orig_category":"Complementos De Vestir (al Por Menor)",
    "sg:phone":"+34 915 64 34 96",
    "sg:postcode":"28006",
    "sg:province":"Madrid",
    "wof:name":"Zamorano Tejero Victoria",
    "wof:placetype":"venue"
},
  "geometry": {"coordinates":[-3.6809108257,40.4360237122],"type":"Point"}
}