{
  "type": "Feature",
  "properties": {
    "iso:country":"ES",
    "sg:address":"Calle de Duquesa Villahermosa, 115",
    "sg:city":"Zaragoza",
    "sg:classifiers":[
        {
            "category":"Casinos & Gambling",
            "type":"Entertainment"
        }
    ],
    "sg:phone":"+34 976 35 10 66",
    "sg:postcode":"50009",
    "sg:province":"Zaragoza",
    "sg:tags":[
        "locale",
        "de",
        "juego"
    ],
    "wof:name":"Minicasino Villahermosa S.l.",
    "wof:placetype":"venue"
},
  "geometry": {"coordinates":[-0.908529222,41.6460952759],"type":"Point"}
}