{
  "type": "Feature",
  "properties": {
    "iso:country":"ES",
    "sg:address":"Av Rhode, S/n",
    "sg:city":"Roses",
    "sg:orig_category":"Inform\u00c1tica: Redes",
    "sg:phone":"+34 972 25 63 69",
    "sg:postcode":"17480",
    "sg:province":"Girona",
    "wof:name":"Llambrich Barbera Teresa",
    "wof:placetype":"venue"
},
  "geometry": {"coordinates":[3.1721999645,42.2647285461],"type":"Point"}
}