{
  "type": "Feature",
  "properties": {
    "iso:country":"ES",
    "sg:address":"Calle de Becerro De Bengoa, 5",
    "sg:city":"Palencia",
    "sg:orig_category":"Sindicatos De Trabajadores",
    "sg:phone":"+34 979 74 06 72",
    "sg:postcode":"34002",
    "sg:province":"Palencia",
    "wof:name":"Asociacion Nacional Del Profesorado Estatal De Palencia",
    "wof:placetype":"venue"
},
  "geometry": {"coordinates":[-4.5320696831,42.0087280273],"type":"Point"}
}