{
  "type": "Feature",
  "properties": {
    "iso:country":"ES",
    "sg:address":"Avda Libertad, 47",
    "sg:city":"Ubeda",
    "sg:orig_category":"Electrodom\u00c9sticos (fabricaci\u00d3n, Al Por Mayor)",
    "sg:phone":"+34 953 79 21 66",
    "sg:postcode":"23400",
    "sg:province":"Ja\u00e9n",
    "wof:name":"Alma Cocinas S.l.",
    "wof:placetype":"venue"
},
  "geometry": {"coordinates":[-3.3653802872,38.0167045593],"type":"Point"}
}