{
  "type": "Feature",
  "properties": {
    "addr:full":"Calle de Enrique Segura Ota\u00d1o, 4 Badajoz Badajoz 06004",
    "addr:housenumber":"4",
    "addr:postcode":"06004",
    "addr:street":"Calle De Enrique Segura Otan\u0303O",
    "iso:country":"ES",
    "sg:address":"Calle de Enrique Segura Ota\u00d1o, 4",
    "sg:city":"Badajoz",
    "sg:orig_category":"Sociedades, Compa\u00d1\u00cdas Aseguradoras",
    "sg:phone":"+34 924 22 71 61",
    "sg:postcode":"06004",
    "sg:province":"Badajoz",
    "wof:name":"La Alianza Espa\u00d1ola Sociedad Anonima De Seguros",
    "wof:placetype":"venue"
},
  "geometry": {"coordinates":[-6.9743256569,38.8731918335],"type":"Point"}
}