{
  "type": "Feature",
  "properties": {
    "iso:country":"ES",
    "sg:address":"Calle de Zaballa, 11",
    "sg:city":"San Vicente De Barakaldo",
    "sg:orig_category":"Agentes De Seguros",
    "sg:phone":"+34 944 38 08 97",
    "sg:postcode":"48901",
    "sg:province":"Vizcaya",
    "wof:name":"Rodriguez Zubiaur Emilio",
    "wof:placetype":"venue"
},
  "geometry": {"coordinates":[-2.9885270596,43.2966537476],"type":"Point"}
}