{
  "type": "Feature",
  "properties": {
    "addr:full":"Bda S. Francisco A, 3 Palma Rio C\u00f3rdoba 14700",
    "addr:housenumber":"3",
    "addr:postcode":"14700",
    "addr:street":"Bda;Francisco A;Rio Co\u0301Rdoba",
    "iso:country":"ES",
    "sg:address":"Bda S. Francisco A, 3",
    "sg:city":"Palma Rio",
    "sg:orig_category":"Delegados, Agentes De Tr\u00c1nsito, Auxiliares De Transporte Internacional",
    "sg:phone":"+34 957 64 44 27",
    "sg:postcode":"14700",
    "sg:province":"C\u00f3rdoba",
    "wof:name":"Mu\u00f1oz Almenara Jose",
    "wof:placetype":"venue"
},
  "geometry": {"coordinates":[-5.2795991898,37.7004241943],"type":"Point"}
}