{
  "type": "Feature",
  "properties": {
    "addr:full":"Avda Santa Eugenia, 27 Madrid Madrid 28031",
    "addr:housenumber":"27",
    "addr:postcode":"madrid;28031",
    "addr:street":"Avda Santa Eugenia",
    "iso:country":"ES",
    "sg:address":"Avda Santa Eugenia, 27",
    "sg:city":"Madrid",
    "sg:orig_category":"Peluqueros: De Se\u00d1oras",
    "sg:phone":"+34 913 32 39 18",
    "sg:postcode":"28031",
    "sg:province":"Madrid",
    "wof:name":"Arroba Mijarra Brigida",
    "wof:placetype":"venue"
},
  "geometry": {"coordinates":[-3.6115372181,40.3847808838],"type":"Point"}
}