{
  "type": "Feature",
  "properties": {
    "iso:country":"ES",
    "sg:address":"Calle de Postigo De San Martin, 9",
    "sg:city":"Madrid",
    "sg:orig_category":"Pintores",
    "sg:phone":"+34 915 31 22 24",
    "sg:postcode":"28013",
    "sg:province":"Madrid",
    "wof:name":"Calvin Fernandez Francisco",
    "wof:placetype":"venue"
},
  "geometry": {"coordinates":[-3.706195116,40.4194297791],"type":"Point"}
}