{
  "type": "Feature",
  "properties": {
    "addr:full":"Plaz Constitucion (la), 4 Carrion De Los Cespedes Sevilla 41820",
    "addr:housenumber":"4",
    "addr:postcode":"41820",
    "addr:street":"Constitucion La",
    "iso:country":"ES",
    "sg:address":"Plaz Constitucion (la), 4",
    "sg:city":"Carrion De Los Cespedes",
    "sg:orig_category":"Administraciones Regionales, Departamentales Y Locales",
    "sg:phone":"+34 954 75 56 08",
    "sg:postcode":"41820",
    "sg:province":"Sevilla",
    "wof:name":"Ayuntamiento De Carrion De Los Cespedes",
    "wof:placetype":"venue"
},
  "geometry": {"coordinates":[-6.3252658844,37.3659095764],"type":"Point"}
}