{
  "type": "Feature",
  "properties": {
    "addr:full":"Calle de Cordolin, S/n Maria Huerva Zaragoza 50430",
    "addr:housenumber":"s / n",
    "addr:postcode":"50430",
    "addr:street":"Calle De Cordolin;Huerva",
    "iso:country":"ES",
    "sg:address":"Calle de Cordolin, S/n",
    "sg:city":"Maria Huerva",
    "sg:orig_category":"Paletas",
    "sg:phone":"+34 976 13 12 85",
    "sg:postcode":"50430",
    "sg:province":"Zaragoza",
    "wof:name":"Arapal 3000 S. L.",
    "wof:placetype":"venue"
},
  "geometry": {"coordinates":[-1.0002454519,41.5413475037],"type":"Point"}
}