{
  "type": "Feature",
  "properties": {
    "iso:country":"ES",
    "sg:address":"Carrer de Santa Maria, 44",
    "sg:city":"S. Cugat Valles",
    "sg:orig_category":"Fabricaci\u00d3n De Sobres, Bolsas Y Fundas",
    "sg:phone":"+34 935 89 13 15",
    "sg:postcode":"08172",
    "sg:province":"Barcelona",
    "wof:name":"Tua Del Mas Maria",
    "wof:placetype":"venue"
},
  "geometry": {"coordinates":[2.0821130276,41.4717102051],"type":"Point"}
}