{
  "type": "Feature",
  "properties": {
    "addr:full":"Calle de Teodoro Calvache, 16 Jaen Ja\u00e9n 23001",
    "addr:housenumber":"16;jae\u0301n",
    "addr:postcode":"23001",
    "addr:street":"Calle De Teodoro Calvache",
    "iso:country":"ES",
    "sg:address":"Calle de Teodoro Calvache, 16",
    "sg:city":"Jaen",
    "sg:orig_category":"Reposter\u00cdas",
    "sg:phone":"+34 953 24 33 96",
    "sg:postcode":"23001",
    "sg:province":"Ja\u00e9n",
    "wof:name":"Sanchez Garcia Alfonso",
    "wof:placetype":"venue"
},
  "geometry": {"coordinates":[-3.7853360176,37.7676734924],"type":"Point"}
}