{
  "type": "Feature",
  "properties": {
    "iso:country":"ES",
    "sg:address":"Calle de Mayor, 3",
    "sg:city":"Binefar",
    "sg:orig_category":"Charcuter\u00cdas (al Por Mayor)",
    "sg:phone":"+34 974 42 80 94",
    "sg:postcode":"22500",
    "sg:province":"Huesca",
    "sg:website":"www.casateres.com",
    "wof:name":"Javier Echart S.l.",
    "wof:placetype":"venue"
},
  "geometry": {"coordinates":[0.2940219939,41.8520698547],"type":"Point"}
}