{
  "type": "Feature",
  "properties": {
    "iso:country":"ES",
    "sg:address":"Avda Francisco La Roche, 35",
    "sg:city":"Santa Cruz De Tenerife",
    "sg:classifiers":[
        {
            "category":"Communications",
            "type":"Services"
        }
    ],
    "sg:phone":"+34 922 27 04 00",
    "sg:postcode":"38001",
    "sg:province":"Santa Cruz De Tenerife",
    "sg:tags":[
        "televisiones",
        "y",
        "radio"
    ],
    "wof:name":"Radio Club De Canarias S. A.",
    "wof:placetype":"venue"
},
  "geometry": {"coordinates":[-16.2449493408,28.4773406982],"type":"Point"}
}