{
  "type": "Feature",
  "properties": {
    "addr:full":"Calle de Francisco Miranda, 14 Icod De Los Vinos Santa Cruz De Tenerife 38430",
    "addr:housenumber":"14",
    "addr:postcode":"38430",
    "addr:street":"Calle De Francisco Miranda",
    "iso:country":"ES",
    "sg:address":"Calle de Francisco Miranda, 14",
    "sg:city":"Icod De Los Vinos",
    "sg:orig_category":"Transporte En General",
    "sg:phone":"+34 922 81 46 38",
    "sg:postcode":"38430",
    "sg:province":"Santa Cruz De Tenerife",
    "wof:name":"Comercial Jesuman",
    "wof:placetype":"venue"
},
  "geometry": {"coordinates":[-16.7205123901,28.3694610596],"type":"Point"}
}