{
  "type": "Feature",
  "properties": {
    "iso:country":"ES",
    "sg:address":"Calle de Barrionuevo, 19",
    "sg:city":"Urda",
    "sg:orig_category":"Material Y Suministros Para Perforaciones, Sondeos",
    "sg:phone":"+34 925 47 23 76",
    "sg:postcode":"45480",
    "sg:province":"Toledo",
    "wof:name":"Alvarez Ruiz Antonio",
    "wof:placetype":"venue"
},
  "geometry": {"coordinates":[-3.7142794132,39.4135971069],"type":"Point"}
}