{
  "type": "Feature",
  "properties": {
    "iso:country":"ES",
    "sg:address":"Ptge Ciutadans, 4",
    "sg:city":"Barcelona",
    "sg:orig_category":"Perfumer\u00cda Y Cosm\u00c9tica (fabricaci\u00d3n, Al Por Mayor)",
    "sg:phone":"+34 933 08 36 56",
    "sg:postcode":"08005",
    "sg:province":"Barcelona",
    "wof:name":"Toskani S.l.",
    "wof:placetype":"venue"
},
  "geometry": {"coordinates":[2.2043290138,41.4049301147],"type":"Point"}
}