{
  "type": "Feature",
  "properties": {
    "iso:country":"ES",
    "sg:address":"Calle de Virgen Del Puig, 1",
    "sg:city":"Madrid",
    "sg:orig_category":"Serigraf\u00cda (material Y Suministros)",
    "sg:phone":"+34 914 05 21 85",
    "sg:postcode":"28027",
    "sg:province":"Madrid",
    "wof:name":"Gallego Garrido Maria Teresa",
    "wof:placetype":"venue"
},
  "geometry": {"coordinates":[-3.6586380005,40.4337654114],"type":"Point"}
}