{
  "type": "Feature",
  "properties": {
    "iso:country":"ES",
    "sg:address":"Calle de San Antonio, 14",
    "sg:city":"Villacedre",
    "sg:orig_category":"Material Y Herramientas Agr\u00cdcolas",
    "sg:phone":"+34 987 25 94 69",
    "sg:postcode":"24194",
    "sg:province":"Le\u00f3n",
    "wof:name":"Inganor S.l.",
    "wof:placetype":"venue"
},
  "geometry": {"coordinates":[-5.585714817,42.5637283325],"type":"Point"}
}