{
  "type": "Feature",
  "properties": {
    "iso:country":"ES",
    "sg:address":"Calle de Cano Y Cueto, 13",
    "sg:city":"Sevilla",
    "sg:orig_category":"Estancos",
    "sg:phone":"+34 954 41 78 43",
    "sg:postcode":"41004",
    "sg:province":"Sevilla",
    "wof:name":"Toro Rodriguez Antonia Del",
    "wof:placetype":"venue"
},
  "geometry": {"coordinates":[-5.9867320061,37.3861351013],"type":"Point"}
}