{
  "type": "Feature",
  "properties": {
    "iso:country":"ES",
    "sg:address":"Calle de Fragata, 1",
    "sg:city":"Palmones",
    "sg:orig_category":"Asesor\u00cda De Formaci\u00d3n Y Gesti\u00d3n De Personal",
    "sg:phone":"+34 956 67 74 18",
    "sg:postcode":"11379",
    "sg:province":"C\u00e1diz",
    "wof:name":"Prevencion Outsourcing S.l.",
    "wof:placetype":"venue"
},
  "geometry": {"coordinates":[-5.4427189827,36.1786231995],"type":"Point"}
}