{
  "type": "Feature",
  "properties": {
    "addr:full":"Avda Aixarte, 1 Arrigorriaga Vizcaya 48480",
    "addr:housenumber":"1",
    "addr:postcode":"48480",
    "addr:street":"Avda Aixarte",
    "iso:country":"ES",
    "sg:address":"Avda Aixarte, 1",
    "sg:city":"Arrigorriaga",
    "sg:orig_category":"Peluqueros: De Se\u00d1oras",
    "sg:phone":"+34 946 71 30 02",
    "sg:postcode":"48480",
    "sg:province":"Vizcaya",
    "wof:name":"Dieguez Vergara Maria Juncal",
    "wof:placetype":"venue"
},
  "geometry": {"coordinates":[-2.8894059658,43.205116272],"type":"Point"}
}