{
  "type": "Feature",
  "properties": {
    "addr:full":"Calle de Extremadura, 27 Isla Cristina Huelva 21410",
    "addr:housenumber":"27",
    "addr:postcode":"21410",
    "addr:street":"Calle De Extremadura",
    "iso:country":"ES",
    "sg:address":"Calle de Extremadura, 27",
    "sg:city":"Isla Cristina",
    "sg:orig_category":"Ense\u00d1anza: Profesiones Art\u00cdsticas",
    "sg:phone":"+34 959 33 00 33",
    "sg:postcode":"21410",
    "sg:province":"Huelva",
    "wof:name":"Tobarra Iglesias Francisco",
    "wof:placetype":"venue"
},
  "geometry": {"coordinates":[-7.3241791725,37.2008094788],"type":"Point"}
}