{
  "type": "Feature",
  "properties": {
    "addr:full":"Calle de D. Jose Lastiesas, 63 Sabi\u00f1anigo Huesca 22600",
    "addr:housenumber":"63",
    "addr:postcode":"22600",
    "addr:street":"Calle De D. Jose Lastiesas",
    "iso:country":"ES",
    "sg:address":"Calle de D. Jose Lastiesas, 63",
    "sg:city":"Sabi\u00f1anigo",
    "sg:orig_category":"Promotores Constructores",
    "sg:phone":"+34 974 48 22 04",
    "sg:postcode":"22600",
    "sg:province":"Huesca",
    "wof:name":"Moreno Marquez Francisco",
    "wof:placetype":"venue"
},
  "geometry": {"coordinates":[-0.3582144976,42.523891449],"type":"Point"}
}