{
  "type": "Feature",
  "properties": {
    "addr:full":"Calle de Risco (el), 13 Monta\u00d1eta Santa Cruz De Tenerife 38419",
    "addr:housenumber":"13",
    "addr:postcode":"38419",
    "addr:street":"Calle De Risco El",
    "iso:country":"ES",
    "sg:address":"Calle de Risco (el), 13",
    "sg:city":"Monta\u00d1eta",
    "sg:orig_category":"Congelados: Productos Alimentarios (al Por Menor)",
    "sg:phone":"+34 922 34 23 88",
    "sg:postcode":"38419",
    "sg:province":"Santa Cruz De Tenerife",
    "wof:name":"Frigorificos Del Norte De Tenerife S.l.",
    "wof:placetype":"venue"
},
  "geometry": {"coordinates":[-16.5830554962,28.3890552521],"type":"Point"}
}