{
  "type": "Feature",
  "properties": {
    "iso:country":"ES",
    "sg:address":"Calle de Angel Tarano, 10",
    "sg:city":"Cangas Onis",
    "sg:orig_category":"Abogados",
    "sg:phone":"+34 985 84 86 06",
    "sg:postcode":"33550",
    "sg:province":"Asturias",
    "wof:name":"Alonso Gonzalez Ricardo Santiago",
    "wof:placetype":"venue"
},
  "geometry": {"coordinates":[-5.1273398399,43.3515853882],"type":"Point"}
}