{
  "type": "Feature",
  "properties": {
    "iso:country":"ES",
    "sg:address":"Carrer de Porrera, 21",
    "sg:city":"Barcelona",
    "sg:orig_category":"Farmacias",
    "sg:phone":"+34 934 27 32 20",
    "sg:postcode":"08031",
    "sg:province":"Barcelona",
    "wof:name":"Espu\u00f1es Vendrell Miguel",
    "wof:placetype":"venue"
},
  "geometry": {"coordinates":[2.159637928,41.4381256104],"type":"Point"}
}