{
  "type": "Feature",
  "properties": {
    "addr:full":"Cno. Albadalejo, 109 Jerez C\u00e1diz 11406",
    "addr:housenumber":"109",
    "addr:postcode":"11406",
    "addr:street":"Cno. Albadalejo",
    "iso:country":"ES",
    "sg:address":"Cno. Albadalejo, 109",
    "sg:city":"Jerez",
    "sg:orig_category":"Panader\u00cdas, Panader\u00cdas",
    "sg:phone":"+34 956 33 65 29",
    "sg:postcode":"11406",
    "sg:province":"C\u00e1diz",
    "wof:name":"Romero Medina Isabel",
    "wof:placetype":"venue"
},
  "geometry": {"coordinates":[-6.1010842323,36.6589164734],"type":"Point"}
}