{
  "type": "Feature",
  "properties": {
    "iso:country":"ES",
    "sg:address":"Avda Maisonnave, 28",
    "sg:city":"Alacant",
    "sg:orig_category":"Ropa Y Art\u00cdculos Pre",
    "sg:phone":"+34 965 12 59 09",
    "sg:postcode":"03003",
    "sg:province":"Alicante",
    "wof:name":"Prenatal S.a.",
    "wof:placetype":"venue"
},
  "geometry": {"coordinates":[-0.4917060137,38.3435897827],"type":"Point"}
}