{
  "type": "Feature",
  "properties": {
    "addr:full":"Calle de Mayor Principal, 83 Palencia Palencia 34001",
    "addr:housenumber":"83",
    "addr:postcode":"34001",
    "addr:street":"Calle De Mayor Principal",
    "iso:country":"ES",
    "sg:address":"Calle de Mayor Principal, 83",
    "sg:city":"Palencia",
    "sg:orig_category":"Ropa Para Se\u00d1oras (al Por Menor)",
    "sg:phone":"+34 979 74 94 80",
    "sg:postcode":"34001",
    "sg:province":"Palencia",
    "wof:name":"Moni 2000 L.l.",
    "wof:placetype":"venue"
},
  "geometry": {"coordinates":[-4.5392618179,42.010433197],"type":"Point"}
}