{
  "type": "Feature",
  "properties": {
    "iso:country":"ES",
    "sg:address":"Carr Carles Iii, 10",
    "sg:city":"Castell",
    "sg:orig_category":"Urbanistas",
    "sg:phone":"+34 971 36 80 02",
    "sg:postcode":"07720",
    "sg:province":"Islas Baleares",
    "wof:name":"Junta De Consultores Reunidos Sl",
    "wof:placetype":"venue"
},
  "geometry": {"coordinates":[4.2888798714,39.8826599121],"type":"Point"}
}