{
  "type": "Feature",
  "properties": {
    "addr:full":"Calle de Santa Ana, 7 Campo Criptana Ciudad Real 13610",
    "addr:housenumber":"7",
    "addr:postcode":"13610",
    "addr:street":"Calle De Santa Ana;Criptana",
    "iso:country":"ES",
    "sg:address":"Calle de Santa Ana, 7",
    "sg:city":"Campo Criptana",
    "sg:orig_category":"Confecci\u00d3n De Trajes Para Se\u00d1oras",
    "sg:phone":"+34 926 56 24 01",
    "sg:postcode":"13610",
    "sg:province":"Ciudad Real",
    "wof:name":"Pasitos Cb",
    "wof:placetype":"venue"
},
  "geometry": {"coordinates":[-3.124778986,39.4059791565],"type":"Point"}
}