{
  "type": "Feature",
  "properties": {
    "iso:country":"ES",
    "sg:address":"Calle de Tulipanes, 4",
    "sg:city":"Benidorm",
    "sg:orig_category":"Electricidad, Electr\u00d3nica: Material Y Suministros (al Por Mayor)",
    "sg:phone":"+34 966 83 08 11",
    "sg:postcode":"03500",
    "sg:province":"Alicante",
    "wof:name":"Estrobel Azorin Carlos",
    "wof:placetype":"venue"
},
  "geometry": {"coordinates":[-0.1342010051,38.5392074585],"type":"Point"}
}