{
  "type": "Feature",
  "properties": {
    "addr:full":"Almajalejo, 25 Huercal-overa Almer\u00eda 04600",
    "addr:housenumber":"25",
    "addr:postcode":"04600",
    "addr:street":"Almajalejo;Almeri\u0301A",
    "iso:country":"ES",
    "sg:address":"Almajalejo, 25",
    "sg:city":"Huercal-overa",
    "sg:orig_category":"Artesan\u00cda",
    "sg:phone":"+34 950 13 56 03",
    "sg:postcode":"04600",
    "sg:province":"Almer\u00eda",
    "wof:name":"Ortega Sanchez Ambrosio",
    "wof:placetype":"venue"
},
  "geometry": {"coordinates":[-1.9444589615,37.392288208],"type":"Point"}
}