{
  "type": "Feature",
  "properties": {
    "iso:country":"ES",
    "sg:address":"Calle de General Moscardo, 9",
    "sg:city":"Madrid",
    "sg:orig_category":"Estancos",
    "sg:phone":"+34 915 54 23 35",
    "sg:postcode":"28020",
    "sg:province":"Madrid",
    "wof:name":"Bascones Calvo Carlos",
    "wof:placetype":"venue"
},
  "geometry": {"coordinates":[-3.697206974,40.4477577209],"type":"Point"}
}