{
  "type": "Feature",
  "properties": {
    "iso:country":"ES",
    "sg:address":"Ctra Alcantarilla, 20",
    "sg:city":"Sangonera La Verde O Ermita Nueva",
    "sg:orig_category":"Cr\u00cda De Perros Y De Gatos",
    "sg:phone":"+34 968 86 64 13",
    "sg:postcode":"30833",
    "sg:province":"Murcia",
    "wof:name":"Jesus Lopez Capitan S.l.",
    "wof:placetype":"venue"
},
  "geometry": {"coordinates":[-1.2056540251,37.9349632263],"type":"Point"}
}