{
  "type": "Feature",
  "properties": {
    "addr:full":"C/ Cerdanya, 7 Puigcerda Girona 17520",
    "addr:housenumber":"7",
    "addr:postcode":"17520",
    "addr:street":"C / Cerdanya",
    "iso:country":"ES",
    "sg:address":"C/ Cerdanya, 7",
    "sg:city":"Puigcerda",
    "sg:orig_category":"Agentes De Seguros",
    "sg:phone":"+34 972 88 05 11",
    "sg:postcode":"17520",
    "sg:province":"Girona",
    "wof:name":"Ruiz Labrador Manuel",
    "wof:placetype":"venue"
},
  "geometry": {"coordinates":[1.9264520407,42.4291763306],"type":"Point"}
}