{
  "type": "Feature",
  "properties": {
    "iso:country":"ES",
    "sg:address":"Calle de Boix Y Morer, 5",
    "sg:city":"Madrid",
    "sg:orig_category":"Bibliotecas, Mediatecas",
    "sg:phone":"+34 915 33 05 08",
    "sg:postcode":"28003",
    "sg:province":"Madrid",
    "wof:name":"Lopez Alonso Miguel Angel",
    "wof:placetype":"venue"
},
  "geometry": {"coordinates":[-3.7064948082,40.4395751953],"type":"Point"}
}