{
  "type": "Feature",
  "properties": {
    "iso:country":"ES",
    "sg:address":"Valtierra, 28",
    "sg:city":"Iru\u00f1a",
    "sg:orig_category":"Pescader\u00cdas (al Por Menor)",
    "sg:phone":"+34 948 12 20 83",
    "sg:postcode":"31015",
    "sg:province":"Navarra",
    "wof:name":"Pescados Y Mariscos Susimar S.l.",
    "wof:placetype":"venue"
},
  "geometry": {"coordinates":[-1.6289739609,42.8339958191],"type":"Point"}
}