{
  "type": "Feature",
  "properties": {
    "addr:full":"Vilardel, 18 Villardel La Coru\u00f1a 15318",
    "addr:housenumber":"18",
    "addr:postcode":"15318",
    "addr:street":"Vilardel;La Corun\u0303A",
    "iso:country":"ES",
    "sg:address":"Vilardel, 18",
    "sg:city":"Villardel",
    "sg:orig_category":"Reposter\u00cdas",
    "sg:phone":"+34 981 63 09 21",
    "sg:postcode":"15318",
    "sg:province":"La Coru\u00f1a",
    "wof:name":"Barros Bola\u00f1o Nicasio",
    "wof:placetype":"venue"
},
  "geometry": {"coordinates":[-8.2870817184,43.2287101746],"type":"Point"}
}