{
  "type": "Feature",
  "properties": {
    "iso:country":"ES",
    "sg:address":"Calle de Doctor Nicasio Benlloch, 1",
    "sg:city":"Valencia",
    "sg:orig_category":"Bisuter\u00cda, Joyer\u00cda, Relojer\u00cda (al Por Menor)",
    "sg:phone":"+34 963 48 78 63",
    "sg:postcode":"46009",
    "sg:province":"Valencia",
    "wof:name":"Perez Ruiz Jose Maria",
    "wof:placetype":"venue"
},
  "geometry": {"coordinates":[-0.3882234097,39.4870910645],"type":"Point"}
}