{
  "type": "Feature",
  "properties": {
    "iso:country":"ES",
    "sg:address":"Av Valencia, 14",
    "sg:city":"Oliva",
    "sg:orig_category":"Asesor\u00cda Sobre Comunicaci\u00d3n De Empresas",
    "sg:phone":"+34 962 85 24 99",
    "sg:postcode":"46780",
    "sg:province":"Valencia",
    "wof:name":"La Joiosa Guarda S.l.",
    "wof:placetype":"venue"
},
  "geometry": {"coordinates":[-0.1234709993,38.9238967896],"type":"Point"}
}