{
  "type": "Feature",
  "properties": {
    "addr:full":"Calle de Donantes De Sangre, S/n Algeciras C\u00e1diz 11207",
    "addr:housenumber":"s / n;ca\u0301diz",
    "addr:postcode":"11207",
    "addr:street":"Calle De Donantes De Sangre",
    "iso:country":"ES",
    "sg:address":"Calle de Donantes De Sangre, S/n",
    "sg:city":"Algeciras",
    "sg:orig_category":"Restaurantes",
    "sg:phone":"+34 956 60 44 88",
    "sg:postcode":"11207",
    "sg:province":"C\u00e1diz",
    "wof:name":"Restaurante Chino Ze Yun",
    "wof:placetype":"venue"
},
  "geometry": {"coordinates":[-5.4415621758,36.113658905],"type":"Point"}
}