{
  "type": "Feature",
  "properties": {
    "iso:country":"ES",
    "sg:address":"Polig. Pocomaco, S/n",
    "sg:city":"A Coru\u00f1a",
    "sg:orig_category":"Inform\u00c1tica: Mantenimiento Y Reparaci\u00d3n De Ordenadores",
    "sg:phone":"+34 981 28 61 59",
    "sg:postcode":"15190",
    "sg:province":"A Coru\u00f1a",
    "wof:name":"Suministros Importaciones Y Mantenimientos S. A.",
    "wof:placetype":"venue"
},
  "geometry": {"coordinates":[-8.4312744141,43.3228416443],"type":"Point"}
}