{
  "type": "Feature",
  "properties": {
    "iso:country":"ES",
    "sg:address":"Altzutzate, 13",
    "sg:city":"Huarte",
    "sg:orig_category":"Ferreter\u00cda (diversos)",
    "sg:phone":"+34 948 33 11 11",
    "sg:postcode":"31620",
    "sg:province":"Navarra",
    "wof:name":"Viguetas Navarras S.l.",
    "wof:placetype":"venue"
},
  "geometry": {"coordinates":[-1.6014139652,42.8249282837],"type":"Point"}
}