{
  "type": "Feature",
  "properties": {
    "addr:full":"Calle de Perojo, 33 Palmas De Gran Canaria Las Palmas 35003",
    "addr:housenumber":"33",
    "addr:postcode":"35003",
    "addr:street":"Calle De Perojo",
    "iso:country":"ES",
    "sg:address":"Calle de Perojo, 33",
    "sg:city":"Palmas De Gran Canaria",
    "sg:orig_category":"M\u00c9dicos: Estomatolog\u00cda",
    "sg:phone":"+34 928 37 07 07",
    "sg:postcode":"35003",
    "sg:province":"Las Palmas",
    "wof:name":"Perez Cabani Francisco Javier",
    "wof:placetype":"venue"
},
  "geometry": {"coordinates":[-15.4196243286,28.1106147766],"type":"Point"}
}