{
  "type": "Feature",
  "properties": {
    "iso:country":"ES",
    "sg:address":"Luga Darsena Pesquera, S/n",
    "sg:city":"San Andres",
    "sg:orig_category":"Construcciones Navales Y Fluviales",
    "sg:phone":"+34 922 59 10 11",
    "sg:postcode":"38120",
    "sg:province":"Santa Cruz De Tenerife",
    "sg:website":"www.varanaga.com",
    "wof:name":"Nautica Y Deportes Canarias S.l.",
    "wof:placetype":"venue"
},
  "geometry": {"coordinates":[-16.2060050964,28.4980163574],"type":"Point"}
}