{
  "type": "Feature",
  "properties": {
    "addr:full":"Carr S'auguer, 40 Blanes Girona 17300",
    "addr:housenumber":"40",
    "addr:postcode":"17300",
    "addr:street":"Carr S'Auguer",
    "iso:country":"ES",
    "sg:address":"Carr S'auguer, 40",
    "sg:city":"Blanes",
    "sg:orig_category":"Arquitectos",
    "sg:phone":"+34 972 33 13 57",
    "sg:postcode":"17300",
    "sg:province":"Girona",
    "wof:name":"Cornella I Oliu Arquitectes S.c.",
    "wof:placetype":"venue"
},
  "geometry": {"coordinates":[2.7900190353,41.6720695496],"type":"Point"}
}