{
  "type": "Feature",
  "properties": {
    "addr:full":"Barr Carbonaire Travesia 7, S/n Vall D'uixo Castell\u00f3n 12600",
    "addr:housenumber":"7 s / n",
    "addr:postcode":"12600",
    "addr:street":"Travesia",
    "iso:country":"ES",
    "sg:address":"Barr Carbonaire Travesia 7, S/n",
    "sg:city":"Vall D'uixo",
    "sg:orig_category":"Empresas De Carpinter\u00cda De Madera",
    "sg:phone":"+34 964 66 19 84",
    "sg:postcode":"12600",
    "sg:province":"Castell\u00f3n",
    "wof:name":"Carpinteria Tierraseca S.l.",
    "wof:placetype":"venue"
},
  "geometry": {"coordinates":[-0.0482099988,39.992477417],"type":"Point"}
}