{
  "type": "Feature",
  "properties": {
    "addr:full":"Avda La Libertad, 34 Barakaldo Vizcaya 48901",
    "addr:housenumber":"34",
    "addr:postcode":"48901",
    "addr:street":"Avda La Libertad",
    "iso:country":"ES",
    "sg:address":"Avda La Libertad, 34",
    "sg:city":"Barakaldo",
    "sg:orig_category":"Quincaller\u00cda (al Por Menor)",
    "sg:phone":"+34 944 38 33 23",
    "sg:postcode":"48901",
    "sg:province":"Vizcaya",
    "wof:name":"Ferreteria Rodriguez, C.b.",
    "wof:placetype":"venue"
},
  "geometry": {"coordinates":[-2.9922990799,43.29870224],"type":"Point"}
}