{
  "type": "Feature",
  "properties": {
    "addr:full":"Barr Salom, S/n Salom Girona 17246",
    "addr:housenumber":"s / n",
    "addr:postcode":"17246",
    "iso:country":"ES",
    "sg:address":"Barr Salom, S/n",
    "sg:city":"Salom",
    "sg:orig_category":"Servicios De Higiene Y Peluquer\u00cda Para Perros Y Gatos",
    "sg:phone":"+34 972 83 72 27",
    "sg:postcode":"17246",
    "sg:province":"Girona",
    "wof:name":"Schmidt-krieger  Denis",
    "wof:placetype":"venue"
},
  "geometry": {"coordinates":[2.9987950325,41.8115959167],"type":"Point"}
}