{
  "type": "Feature",
  "properties": {
    "iso:country":"ES",
    "sg:address":"Avda Fuente Alamo, 1",
    "sg:city":"Yecla",
    "sg:orig_category":"Caf\u00c9s, Bares, Cervecer\u00cdas",
    "sg:phone":"+34 968 79 52 99",
    "sg:postcode":"30510",
    "sg:province":"Murcia",
    "wof:name":"Val Fortes Cristobal",
    "wof:placetype":"venue"
},
  "geometry": {"coordinates":[-1.1281360388,38.6168403625],"type":"Point"}
}