{
  "type": "Feature",
  "properties": {
    "addr:full":"Carrer de Valencia, 351 Barcelona Barcelona 08009",
    "addr:housenumber":"351",
    "addr:postcode":"08009",
    "addr:street":"Carrer De Valencia",
    "iso:country":"ES",
    "sg:address":"Carrer de Valencia, 351",
    "sg:city":"Barcelona",
    "sg:orig_category":"Ingenier\u00cda, Centros De Estudios (diversos)",
    "sg:phone":"+34 932 07 02 58",
    "sg:postcode":"08009",
    "sg:province":"Barcelona",
    "wof:name":"Ribas & Asociados Grupo De Ingenieria Y Arquitectura S.l.",
    "wof:placetype":"venue"
},
  "geometry": {"coordinates":[2.1705009937,41.3982276917],"type":"Point"}
}