{
  "type": "Feature",
  "properties": {
    "iso:country":"ES",
    "sg:address":"Carrer de Barcelona, 6",
    "sg:city":"Gurb",
    "sg:orig_category":"Venta, Instalaci\u00d3n De Sistemas De Alarmas Y Vigilancia",
    "sg:phone":"+34 938 89 15 66",
    "sg:postcode":"08518",
    "sg:province":"Barcelona",
    "wof:name":"Serra Alarm S.l.",
    "wof:placetype":"venue"
},
  "geometry": {"coordinates":[2.2445719242,41.9426345825],"type":"Point"}
}