{
  "type": "Feature",
  "properties": {
    "iso:country":"ES",
    "sg:address":"Calle de Aldapeta, 1",
    "sg:city":"Irun",
    "sg:orig_category":"Perfumer\u00cda (al Por Menor)",
    "sg:phone":"+34 943 63 34 39",
    "sg:postcode":"20303",
    "sg:province":"Guip\u00f9zcoa",
    "wof:name":"Alonso Sistiaga Maria Soledad",
    "wof:placetype":"venue"
},
  "geometry": {"coordinates":[-1.7920205593,43.3391189575],"type":"Point"}
}