{
  "type": "Feature",
  "properties": {
    "addr:full":"Avda Rey Juan Carlos I, 23 Leganes Madrid 28915",
    "addr:housenumber":"23",
    "addr:postcode":"28915",
    "addr:street":"Avda Rey Juan Carlos I",
    "iso:country":"ES",
    "sg:address":"Avda Rey Juan Carlos I, 23",
    "sg:city":"Leganes",
    "sg:orig_category":"Talleres: Ropa A Medida",
    "sg:phone":"+34 916 88 13 16",
    "sg:postcode":"28915",
    "sg:province":"Madrid",
    "wof:name":"Martinez Ruiz Tomas",
    "wof:placetype":"venue"
},
  "geometry": {"coordinates":[-3.7526180744,40.3349914551],"type":"Point"}
}