{
  "type": "Feature",
  "properties": {
    "iso:country":"ES",
    "sg:address":"Calle de Fernando Vi, 2",
    "sg:city":"Madrid",
    "sg:orig_category":"Asesor\u00cda De Formaci\u00d3n Y Gesti\u00d3n De Personal",
    "sg:phone":"+34 913 08 41 97",
    "sg:postcode":"28004",
    "sg:province":"Madrid",
    "wof:name":"Lf Asesores S.l.",
    "wof:placetype":"venue"
},
  "geometry": {"coordinates":[-3.6971580982,40.4257583618],"type":"Point"}
}