{
  "type": "Feature",
  "properties": {
    "iso:country":"ES",
    "sg:address":"Calle de San Bernardo, 12",
    "sg:city":"Aviles",
    "sg:orig_category":"Monedas, Medallas",
    "sg:phone":"+34 985 52 31 53",
    "sg:postcode":"33402",
    "sg:province":"Asturias",
    "wof:name":"Sociedad Numismatica Avilesina",
    "wof:placetype":"venue"
},
  "geometry": {"coordinates":[-5.922852993,43.5567855835],"type":"Point"}
}