{
  "type": "Feature",
  "properties": {
    "addr:full":"Cruz De Rualla, 2 San Isidro De Benageber Valencia 46116",
    "addr:housenumber":"2",
    "addr:postcode":"46116",
    "addr:street":"Cruz;Rualla",
    "iso:country":"ES",
    "sg:address":"Cruz De Rualla, 2",
    "sg:city":"San Isidro De Benageber",
    "sg:orig_category":"Cooperativas Agr\u00cdcolas",
    "sg:phone":"+34 961 39 11 18",
    "sg:postcode":"46116",
    "sg:province":"Valencia",
    "wof:name":"Cooperativa Citrica San Isidro",
    "wof:placetype":"venue"
},
  "geometry": {"coordinates":[-0.4134680033,39.5645027161],"type":"Point"}
}