{
  "type": "Feature",
  "properties": {
    "iso:country":"ES",
    "sg:address":"Carrer de Diputacio, 183",
    "sg:city":"Barcelona",
    "sg:orig_category":"Empresarios Y Productoras De Espect\u00c1culos",
    "sg:phone":"+34 933 23 64 21",
    "sg:postcode":"08011",
    "sg:province":"Barcelona",
    "wof:name":"Serveis Actualizats De L'espectacle S.l.",
    "wof:placetype":"venue"
},
  "geometry": {"coordinates":[2.1601719856,41.3853683472],"type":"Point"}
}