{
  "type": "Feature",
  "properties": {
    "addr:full":"Avda Juan Carlos I, 5 Caravaca Cruz Murcia 30400",
    "addr:housenumber":"5",
    "addr:postcode":"30400",
    "addr:street":"Avda Juan Carlos I",
    "iso:country":"ES",
    "sg:address":"Avda Juan Carlos I, 5",
    "sg:city":"Caravaca Cruz",
    "sg:orig_category":"Perfumer\u00cda (al Por Menor)",
    "sg:phone":"+34 968 70 39 08",
    "sg:postcode":"30400",
    "sg:province":"Murcia",
    "wof:name":"Desarrollo Comercial Del Sureste S. L.",
    "wof:placetype":"venue"
},
  "geometry": {"coordinates":[-1.8623449802,38.1032791138],"type":"Point"}
}