{
  "type": "Feature",
  "properties": {
    "iso:country":"ES",
    "sg:address":"Carrer de Sant Jordi, 6",
    "sg:city":"Morell",
    "sg:orig_category":"Material Y Suministros Para Perforaciones, Sondeos",
    "sg:phone":"+34 977 84 29 18",
    "sg:postcode":"43760",
    "sg:province":"Tarragona",
    "wof:name":"Canel Alcalde Miguel",
    "wof:placetype":"venue"
},
  "geometry": {"coordinates":[1.2067849636,41.1900138855],"type":"Point"}
}