{
  "type": "Feature",
  "properties": {
    "addr:full":"Calle de Jurista Lopez Amo, 18 Alacant Alicante 03015",
    "addr:housenumber":"18",
    "addr:postcode":"03015",
    "addr:street":"Calle De Jurista Lopez Amo",
    "iso:country":"ES",
    "sg:address":"Calle de Jurista Lopez Amo, 18",
    "sg:city":"Alacant",
    "sg:orig_category":"Promotores Constructores",
    "sg:phone":"+34 965 26 56 19",
    "sg:postcode":"03015",
    "sg:province":"Alicante",
    "wof:name":"Tumayi S.l.",
    "wof:placetype":"venue"
},
  "geometry": {"coordinates":[-0.4625759125,38.3682327271],"type":"Point"}
}