{
  "type": "Feature",
  "properties": {
    "iso:country":"ES",
    "sg:address":"Calle de Estatuto, 15",
    "sg:city":"Castellon",
    "sg:orig_category":"Agencias Y Agentes Comerciales, Representantes",
    "sg:phone":"+34 964 22 76 98",
    "sg:postcode":"12004",
    "sg:province":"Castell\u00f3n",
    "wof:name":"Iba\u00f1ez Montolio Francisco",
    "wof:placetype":"venue"
},
  "geometry": {"coordinates":[-0.0346186012,39.9931755066],"type":"Point"}
}