{
  "type": "Feature",
  "properties": {
    "addr:full":"Carr Sant Lluc, 54 Badalona Barcelona 08918",
    "addr:housenumber":"54",
    "addr:postcode":"08918",
    "addr:street":"Carr Sant Lluc",
    "iso:country":"ES",
    "sg:address":"Carr Sant Lluc, 54",
    "sg:city":"Badalona",
    "sg:orig_category":"Agencias De Viajes",
    "sg:phone":"+34 934 60 56 03",
    "sg:postcode":"08918",
    "sg:province":"Barcelona",
    "wof:name":"Viajes Internacional Expreso S A",
    "wof:placetype":"venue"
},
  "geometry": {"coordinates":[2.2341558933,41.4362564087],"type":"Point"}
}