{
  "type": "Feature",
  "properties": {
    "addr:full":"Calle de Bilbao, 9 Salamanca Salamanca 37003",
    "addr:housenumber":"9",
    "addr:postcode":"37003",
    "addr:street":"Calle De Bilbao",
    "iso:country":"ES",
    "sg:address":"Calle de Bilbao, 9",
    "sg:city":"Salamanca",
    "sg:orig_category":"Promotores Constructores",
    "sg:phone":"+34 923 18 12 72",
    "sg:postcode":"37003",
    "sg:province":"Salamanca",
    "sg:website":"www.grupoprieto.com",
    "wof:name":"Hernan Cortes C.b",
    "wof:placetype":"venue"
},
  "geometry": {"coordinates":[-5.647046566,40.9703674316],"type":"Point"}
}