{
  "type": "Feature",
  "properties": {
    "iso:country":"ES",
    "sg:address":"Vred Chocolate, 71",
    "sg:city":"Huerta Y Campo De Los Ramos",
    "sg:orig_category":"Empresarios",
    "sg:phone":"+34 968 87 06 21",
    "sg:postcode":"30589",
    "sg:province":"Murcia",
    "wof:name":"Reformas Revicam S.l.",
    "wof:placetype":"venue"
},
  "geometry": {"coordinates":[-1.0358589888,37.992641449],"type":"Point"}
}