{
  "type": "Feature",
  "properties": {
    "addr:full":"Av Bisbe Llompart, 96 Inca Islas Baleares 07300",
    "addr:housenumber":"96",
    "addr:postcode":"07300",
    "addr:street":"Av Bisbe Llompart",
    "iso:country":"ES",
    "sg:address":"Av Bisbe Llompart, 96",
    "sg:city":"Inca",
    "sg:orig_category":"Estancos",
    "sg:phone":"+34 971 50 02 46",
    "sg:postcode":"07300",
    "sg:province":"Islas Baleares",
    "wof:name":"Bonnin Oliver Maria Antonia",
    "wof:placetype":"venue"
},
  "geometry": {"coordinates":[2.9071500301,39.7193717957],"type":"Point"}
}