{
  "type": "Feature",
  "properties": {
    "iso:country":"ES",
    "sg:address":"Calle de Alava, 8",
    "sg:city":"Fuenlabrada",
    "sg:orig_category":"Empresas De Pintura Y Revestimientos",
    "sg:phone":"+34 916 09 74 48",
    "sg:postcode":"28941",
    "sg:province":"Madrid",
    "wof:name":"Fernandez Carmona Angel",
    "wof:placetype":"venue"
},
  "geometry": {"coordinates":[-3.7992558479,40.2937240601],"type":"Point"}
}