{
  "type": "Feature",
  "properties": {
    "iso:country":"ES",
    "sg:address":"Avda Gustavo Adolfo Becquer, 10",
    "sg:city":"Nueva Andalucia",
    "sg:orig_category":"Molduras, Junquillos, Listones Y Molduras Perforadas",
    "sg:phone":"+34 952 81 88 39",
    "sg:postcode":"29660",
    "sg:province":"M\u00e1laga",
    "wof:name":"Telefonia Saltele Marbella S.l.",
    "wof:placetype":"venue"
},
  "geometry": {"coordinates":[-4.9783039093,36.5030136108],"type":"Point"}
}