{
  "type": "Feature",
  "properties": {
    "addr:full":"Calle de Divino Valles, 14 Madrid Madrid 28045",
    "addr:housenumber":"14",
    "addr:postcode":"madrid;28045",
    "addr:street":"Calle De Divino Valles",
    "iso:country":"ES",
    "sg:address":"Calle de Divino Valles, 14",
    "sg:city":"Madrid",
    "sg:orig_category":"Molduras, Junquillos, Listones Y Molduras Perforadas",
    "sg:phone":"+34 915 30 95 70",
    "sg:postcode":"28045",
    "sg:province":"Madrid",
    "wof:name":"Camacho Marco Engracia",
    "wof:placetype":"venue"
},
  "geometry": {"coordinates":[-3.6958930492,40.3964118958],"type":"Point"}
}