{
  "type": "Feature",
  "properties": {
    "addr:full":"Calle de Rudolf Diesel, 16 Zaragoza Zaragoza 50015",
    "addr:housenumber":"16",
    "addr:postcode":"50015",
    "addr:street":"Calle De Rudolf Diesel",
    "iso:country":"ES",
    "sg:address":"Calle de Rudolf Diesel, 16",
    "sg:city":"Zaragoza",
    "sg:orig_category":"Importaci\u00d3n",
    "sg:phone":"+34 976 10 60 64",
    "sg:postcode":"50015",
    "sg:province":"Zaragoza",
    "wof:name":"Importacion Galeria China S.l",
    "wof:placetype":"venue"
},
  "geometry": {"coordinates":[-0.8636890054,41.6791496277],"type":"Point"}
}