{
  "type": "Feature",
  "properties": {
    "addr:full":"Calle de Mariana Pineda, 19 Zaragoza Zaragoza 50015",
    "addr:housenumber":"19",
    "addr:postcode":"50015",
    "addr:street":"Calle De Mariana Pineda",
    "iso:country":"ES",
    "sg:address":"Calle de Mariana Pineda, 19",
    "sg:city":"Zaragoza",
    "sg:orig_category":"Arquitectos",
    "sg:phone":"+34 976 52 74 24",
    "sg:postcode":"50015",
    "sg:province":"Zaragoza",
    "wof:name":"Lopez Fernandez Gabriel",
    "wof:placetype":"venue"
},
  "geometry": {"coordinates":[-0.8885449767,41.6650772095],"type":"Point"}
}