{
  "type": "Feature",
  "properties": {
    "iso:country":"ES",
    "sg:address":"Carrer de Cementiri Nou, S/n",
    "sg:city":"Sentmenat",
    "sg:orig_category":"Cerrajer\u00cda, Ferrallista",
    "sg:phone":"+34 937 15 10 54",
    "sg:postcode":"08181",
    "sg:province":"Barcelona",
    "wof:name":"Asensio Morcillo Santiago",
    "wof:placetype":"venue"
},
  "geometry": {"coordinates":[2.1424987316,41.6157608032],"type":"Point"}
}