{
  "type": "Feature",
  "properties": {
    "iso:country":"ES",
    "sg:address":"Avda Portugal, 42",
    "sg:city":"Zamora",
    "sg:orig_category":"Fabricaci\u00d3n, Instalaci\u00d3n De Armarios",
    "sg:phone":"+34 980 53 63 10",
    "sg:postcode":"49016",
    "sg:province":"Zamora",
    "wof:name":"Remesal Gago Fernando",
    "wof:placetype":"venue"
},
  "geometry": {"coordinates":[-5.7399868965,41.5036735535],"type":"Point"}
}