{
  "type": "Feature",
  "properties": {
    "iso:country":"ES",
    "sg:address":"Ctra. Stgo-a Estrada, S/n",
    "sg:city":"Cacheiras",
    "sg:orig_category":"Asociaciones Y Clubs Deportivos",
    "sg:phone":"+34 981 80 76 29",
    "sg:postcode":"15883",
    "sg:province":"La Coru\u00f1a",
    "wof:name":"Fernandez Castro Bego\u00f1a",
    "wof:placetype":"venue"
},
  "geometry": {"coordinates":[-8.5463113785,42.8224372864],"type":"Point"}
}