{
  "type": "Feature",
  "properties": {
    "iso:country":"ES",
    "sg:address":"Calle de Entre Arroyos, 1",
    "sg:city":"Madrid",
    "sg:orig_category":"Agencias Y Agentes Comerciales, Representantes",
    "sg:phone":"+34 914 39 59 41",
    "sg:postcode":"28030",
    "sg:province":"Madrid",
    "wof:name":"Ruiz Garcia Jaime",
    "wof:placetype":"venue"
},
  "geometry": {"coordinates":[-3.6566879749,40.4089431763],"type":"Point"}
}