{
  "type": "Feature",
  "properties": {
    "addr:full":"Carrer de Sarda, 7 Reus Tarragona 43201",
    "addr:housenumber":"7",
    "addr:postcode":"43201",
    "addr:street":"Carrer De Sarda",
    "iso:country":"ES",
    "sg:address":"Carrer de Sarda, 7",
    "sg:city":"Reus",
    "sg:orig_category":"Molduras, Junquillos, Listones Y Molduras Perforadas",
    "sg:phone":"+34 977 34 37 00",
    "sg:postcode":"43201",
    "sg:province":"Tarragona",
    "wof:name":"Ferre Saludes Pere",
    "wof:placetype":"venue"
},
  "geometry": {"coordinates":[1.1118750572,41.1576843262],"type":"Point"}
}