{
  "type": "Feature",
  "properties": {
    "addr:full":"Calle de Amsterdam, 3 Madrid Madrid 28042",
    "addr:housenumber":"3",
    "addr:postcode":"28042",
    "addr:street":"Calle De Amsterdam",
    "iso:country":"ES",
    "sg:address":"Calle de Amsterdam, 3",
    "sg:city":"Madrid",
    "sg:orig_category":"Televisi\u00d3n, V\u00cddeo: Aparatos Y Accesorios (venta)",
    "sg:phone":"+34 917 21 12 94",
    "sg:postcode":"28042",
    "sg:province":"Madrid",
    "sg:website":"www.quadriga.com",
    "wof:name":"Quadriga Espa\u00f1a S.a.",
    "wof:placetype":"venue"
},
  "geometry": {"coordinates":[-3.6144545078,40.4625282288],"type":"Point"}
}