{
  "type": "Feature",
  "properties": {
    "iso:country":"ES",
    "sg:address":"Carr Pare Gari, 81",
    "sg:city":"Vilanova I La Geltru",
    "sg:orig_category":"M\u00c9dicos: Ginecolog\u00cda Y Obstetricia",
    "sg:phone":"+34 938 10 12 91",
    "sg:postcode":"08800",
    "sg:province":"Barcelona",
    "wof:name":"C.g.m. Valls S.l.",
    "wof:placetype":"venue"
},
  "geometry": {"coordinates":[1.7224340439,41.221408844],"type":"Point"}
}