{
  "type": "Feature",
  "properties": {
    "iso:country":"ES",
    "sg:address":"Durana Kalea, 11",
    "sg:city":"Aretxabaleta",
    "sg:orig_category":"Diarios, Revistas Y Boletines (distribuidores)",
    "sg:phone":"+34 943 79 86 21",
    "sg:postcode":"20550",
    "sg:province":"Guip\u00f9zcoa",
    "wof:name":"Aretxabaletako Komunikabideak Loramendi Elkarteaa",
    "wof:placetype":"venue"
},
  "geometry": {"coordinates":[-2.5039141178,43.0347595215],"type":"Point"}
}