{
  "type": "Feature",
  "properties": {
    "iso:country":"ES",
    "sg:address":"Carr Aeroclub, S/n",
    "sg:city":"Empuriabrava",
    "sg:orig_category":"Deportes Diversos",
    "sg:phone":"+34 972 45 08 54",
    "sg:postcode":"17487",
    "sg:province":"Girona",
    "wof:name":"Pages Laboria Enrique",
    "wof:placetype":"venue"
},
  "geometry": {"coordinates":[3.104929924,42.2619743347],"type":"Point"}
}