{
  "type": "Feature",
  "properties": {
    "addr:full":"Plaz Constitucion (la), 3 Astillero Cantabria 39610",
    "addr:housenumber":"3",
    "addr:postcode":"39610",
    "addr:street":"Constitucion La",
    "iso:country":"ES",
    "sg:address":"Plaz Constitucion (la), 3",
    "sg:city":"Astillero",
    "sg:orig_category":"Transporte En General",
    "sg:phone":"+34 942 54 33 74",
    "sg:postcode":"39610",
    "sg:province":"Cantabria",
    "wof:name":"Distribuidora Internacional De Alimentacion S.a.",
    "wof:placetype":"venue"
},
  "geometry": {"coordinates":[-3.821928978,43.4001655579],"type":"Point"}
}