{
  "type": "Feature",
  "properties": {
    "iso:country":"ES",
    "sg:address":"Vva Cordoba, 20",
    "sg:city":"Pozoblanco",
    "sg:orig_category":"Restaurantes Para Recepciones, Banquetes, Conferencias",
    "sg:phone":"+34 957 77 05 26",
    "sg:postcode":"14400",
    "sg:province":"C\u00f3rdoba",
    "wof:name":"Luna Mu\u00f1oz Marcial",
    "wof:placetype":"venue"
},
  "geometry": {"coordinates":[-4.8550338745,38.3794326782],"type":"Point"}
}