{
  "type": "Feature",
  "properties": {
    "iso:country":"ES",
    "sg:address":"Calle de General Bravo, 16",
    "sg:city":"Carrizal",
    "sg:orig_category":"Pescader\u00cdas (al Por Menor)",
    "sg:phone":"+34 928 78 11 05",
    "sg:postcode":"35240",
    "sg:province":"Las Palmas",
    "wof:name":"Garcia Perdomo Segundo",
    "wof:placetype":"venue"
},
  "geometry": {"coordinates":[-15.406586647,27.9128761292],"type":"Point"}
}