{
  "type": "Feature",
  "properties": {
    "addr:full":"Carrer de Comte Borrell, 328 Barcelona Barcelona 08029",
    "addr:housenumber":"328",
    "addr:postcode":"08029",
    "addr:street":"Carrer De Comte Borrell",
    "iso:country":"ES",
    "sg:address":"Carrer de Comte Borrell, 328",
    "sg:city":"Barcelona",
    "sg:orig_category":"Arquitectos",
    "sg:phone":"+34 934 30 99 88",
    "sg:postcode":"08029",
    "sg:province":"Barcelona",
    "wof:name":"Porta D Alella S.l.",
    "wof:placetype":"venue"
},
  "geometry": {"coordinates":[2.1447761059,41.3910064697],"type":"Point"}
}