{
  "type": "Feature",
  "properties": {
    "addr:full":"Calle de Cementerio (el), S/n Sartaguda Navarra 31589",
    "addr:housenumber":"s / n",
    "addr:postcode":"31589",
    "addr:street":"Calle De Cementerio El",
    "iso:country":"ES",
    "sg:address":"Calle de Cementerio (el), S/n",
    "sg:city":"Sartaguda",
    "sg:orig_category":"Producci\u00d3n De Champi\u00d1ones",
    "sg:phone":"+34 948 66 71 62",
    "sg:postcode":"31589",
    "sg:province":"Navarra",
    "wof:name":"Ruiz Fla\u00f1o Jesus Maria",
    "wof:placetype":"venue"
},
  "geometry": {"coordinates":[-2.0551893711,42.3801116943],"type":"Point"}
}