{
  "type": "Feature",
  "properties": {
    "addr:full":"Calle de Tomas Castellano, 1 Zaragoza Zaragoza 50001",
    "addr:housenumber":"1",
    "addr:postcode":"50001",
    "addr:street":"Calle De Tomas Castellano",
    "iso:country":"ES",
    "sg:address":"Calle de Tomas Castellano, 1",
    "sg:city":"Zaragoza",
    "sg:orig_category":"M\u00c9dicos: Estomatolog\u00cda",
    "sg:phone":"+34 976 23 22 09",
    "sg:postcode":"50001",
    "sg:province":"Zaragoza",
    "wof:name":"Garcia Castro Maria Teresa",
    "wof:placetype":"venue"
},
  "geometry": {"coordinates":[-0.8832240105,41.6488456726],"type":"Point"}
}