{
  "type": "Feature",
  "properties": {
    "addr:full":"Carrer de Miguel De Cervantes, 29 Mollet Valles Barcelona 08100",
    "addr:housenumber":"29",
    "addr:postcode":"08100",
    "addr:street":"Carrer De Miguel De Cervantes",
    "iso:country":"ES",
    "sg:address":"Carrer de Miguel De Cervantes, 29",
    "sg:city":"Mollet Valles",
    "sg:orig_category":"Farmacias",
    "sg:phone":"+34 935 93 15 35",
    "sg:postcode":"08100",
    "sg:province":"Barcelona",
    "wof:name":"Garnes Camarena Estruch Laura",
    "wof:placetype":"venue"
},
  "geometry": {"coordinates":[2.2089960575,41.5431098938],"type":"Point"}
}