{
  "type": "Feature",
  "properties": {
    "addr:full":"Ctra. Extremadura, Km. 0034,2 Navalcarnero Madrid 28600",
    "addr:postcode":"28600",
    "addr:street":"Ctra. Extremadura Km. 0034,2",
    "iso:country":"ES",
    "sg:address":"Ctra. Extremadura, Km. 0034,2",
    "sg:city":"Navalcarnero",
    "sg:orig_category":"Asociaciones, Organismos Culturales Y Socioeducativos",
    "sg:phone":"+34 918 11 03 57",
    "sg:postcode":"28600",
    "sg:province":"Madrid",
    "wof:name":"Centro Espa\u00f1ol De Solidaridad",
    "wof:placetype":"venue"
},
  "geometry": {"coordinates":[-3.977684021,40.2939796448],"type":"Point"}
}