{
  "type": "Feature",
  "properties": {
    "addr:full":"Avgd Comte Serrallo, 31 Alcudia Valencia 46250",
    "addr:housenumber":"31",
    "addr:postcode":"46250",
    "addr:street":"Serrallo",
    "iso:country":"ES",
    "sg:address":"Avgd Comte Serrallo, 31",
    "sg:city":"Alcudia",
    "sg:orig_category":"Electricidad: Instaladores",
    "sg:phone":"+34 962 99 63 35",
    "sg:postcode":"46250",
    "sg:province":"Valencia",
    "wof:name":"Automatizacion Electrica Y Neumatica S.l.",
    "wof:placetype":"venue"
},
  "geometry": {"coordinates":[-0.5031551123,39.2018508911],"type":"Point"}
}