{
  "type": "Feature",
  "properties": {
    "addr:full":"Calle de Juan Espa\u00d1ol, 18 Madrid Madrid 28026",
    "addr:housenumber":"18",
    "addr:postcode":"madrid;28026",
    "addr:street":"Calle De Juan Espan\u0303Ol",
    "iso:country":"ES",
    "sg:address":"Calle de Juan Espa\u00d1ol, 18",
    "sg:city":"Madrid",
    "sg:orig_category":"Electrodom\u00c9sticos (al Por Menor)",
    "sg:phone":"+34 914 76 50 46",
    "sg:postcode":"28026",
    "sg:province":"Madrid",
    "wof:name":"Alda Tecnic S.l.",
    "wof:placetype":"venue"
},
  "geometry": {"coordinates":[-3.7097499371,40.3865776062],"type":"Point"}
}