{
  "type": "Feature",
  "properties": {
    "addr:full":"Calle de Monederos, 26 Madrid Madrid 28026",
    "addr:housenumber":"26",
    "addr:postcode":"madrid;28026",
    "addr:street":"Calle De Monederos",
    "iso:country":"ES",
    "sg:address":"Calle de Monederos, 26",
    "sg:city":"Madrid",
    "sg:orig_category":"Delegados, Agentes De Tr\u00c1nsito, Auxiliares De Transporte Internacional",
    "sg:phone":"+34 914 76 60 09",
    "sg:postcode":"28026",
    "sg:province":"Madrid",
    "wof:name":"Villeta Fernandez Maria",
    "wof:placetype":"venue"
},
  "geometry": {"coordinates":[-3.7014930248,40.3874168396],"type":"Point"}
}