{
  "type": "Feature",
  "properties": {
    "addr:full":"Calle de Poeta Blas De Loma, 8 Alacant Alicante 03005",
    "addr:housenumber":"8",
    "addr:postcode":"03005",
    "addr:street":"Calle De Poeta Blas De Loma",
    "iso:country":"ES",
    "sg:address":"Calle de Poeta Blas De Loma, 8",
    "sg:city":"Alacant",
    "sg:orig_category":"Asociaciones Humanitarias, De Cooperaci\u00d3n, De Acci\u00d3n Social",
    "sg:phone":"+34 965 13 43 54",
    "sg:postcode":"03005",
    "sg:province":"Alicante",
    "wof:name":"Asociacion Esclerosis Multiple De Alicante",
    "wof:placetype":"venue"
},
  "geometry": {"coordinates":[-0.495244503,38.3495941162],"type":"Point"}
}