{
  "type": "Feature",
  "properties": {
    "addr:full":"Pl Sants Martirs (dels), 27 Vic Barcelona 08500",
    "addr:housenumber":"27",
    "addr:postcode":"08500",
    "addr:street":"Pl;Martirs Dels",
    "iso:country":"ES",
    "sg:address":"Pl Sants Martirs (dels), 27",
    "sg:city":"Vic",
    "sg:orig_category":"Material Y Suministros Para Perforaciones, Sondeos",
    "sg:phone":"+34 938 86 20 35",
    "sg:postcode":"08500",
    "sg:province":"Barcelona",
    "wof:name":"Tort Ta\u00f1a Ramon",
    "wof:placetype":"venue"
},
  "geometry": {"coordinates":[2.258161068,41.9304275513],"type":"Point"}
}