{
  "type": "Feature",
  "properties": {
    "iso:country":"ES",
    "sg:address":"Calle de Fuente (la), 33",
    "sg:city":"Andorra",
    "sg:classifiers":[
        {
            "category":"Tea Room",
            "subcategory":"None",
            "type":"Food & Drink"
        }
    ],
    "sg:phone":"+34 978 84 22 26",
    "sg:postcode":"44500",
    "sg:province":"Teruel",
    "sg:tags":[
        "snack"
    ],
    "wof:name":"La Parada 33 S.c.",
    "wof:placetype":"venue"
},
  "geometry": {"coordinates":[-0.4460450113,40.9762954712],"type":"Point"}
}