{
  "type": "Feature",
  "properties": {
    "iso:country":"ES",
    "sg:address":"Carrer de Llevant, 20",
    "sg:city":"Hospitalet Llobregat",
    "sg:orig_category":"Empresas De Carpinter\u00cda Met\u00c1lica",
    "sg:phone":"+34 934 48 04 66",
    "sg:postcode":"08905",
    "sg:province":"Barcelona",
    "wof:name":"Reyes Ponce Daniel",
    "wof:placetype":"venue"
},
  "geometry": {"coordinates":[2.1102609634,41.3738327026],"type":"Point"}
}