{
  "type": "Feature",
  "properties": {
    "iso:country":"ES",
    "sg:address":"Calle de Diputacion, 5",
    "sg:city":"Villafranca De Los Barros",
    "sg:orig_category":"Plomeros",
    "sg:phone":"+34 924 52 62 20",
    "sg:postcode":"06220",
    "sg:province":"Badajoz",
    "wof:name":"Ropero Mancera Pedro",
    "wof:placetype":"venue"
},
  "geometry": {"coordinates":[-6.334376812,38.5544090271],"type":"Point"}
}