{
  "type": "Feature",
  "properties": {
    "addr:full":"Urb Nueva Torrequebrada, S/n Benalmadena-costa M\u00e1laga 29630",
    "addr:postcode":"29630",
    "addr:street":"Urb;Torrequebrada S / N Benalmadena-Costa Ma\u0301Laga",
    "iso:country":"ES",
    "sg:address":"Urb Nueva Torrequebrada, S/n",
    "sg:city":"Benalmadena-costa",
    "sg:orig_category":"Cajas De Ahorro",
    "sg:phone":"+34 952 44 98 60",
    "sg:postcode":"29630",
    "sg:province":"M\u00e1laga",
    "wof:name":"Unicaja",
    "wof:placetype":"venue"
},
  "geometry": {"coordinates":[-4.521381855,36.5971374512],"type":"Point"}
}