{
  "type": "Feature",
  "properties": {
    "iso:country":"ES",
    "sg:address":"Avda Guadarrama (de), 15",
    "sg:city":"San Sebastian De Los Reyes",
    "sg:orig_category":"Promotores Constructores",
    "sg:phone":"+34 916 51 08 95",
    "sg:postcode":"28700",
    "sg:province":"Madrid",
    "wof:name":"Esteban Hierro Gregorio",
    "wof:placetype":"venue"
},
  "geometry": {"coordinates":[-3.6347429752,40.5492210388],"type":"Point"}
}