{
  "type": "Feature",
  "properties": {
    "iso:country":"ES",
    "sg:address":"Salvador Rueda, S/n",
    "sg:city":"San Pedro Alcantara",
    "sg:orig_category":"Cine (producci\u00d3n, Realizaci\u00d3n)",
    "sg:phone":"+34 952 78 61 66",
    "sg:postcode":"29670",
    "sg:province":"M\u00e1laga",
    "wof:name":"Luz Internacional Film S. A.",
    "wof:placetype":"venue"
},
  "geometry": {"coordinates":[-5.003718853,36.4735946655],"type":"Point"}
}