{
  "type": "Feature",
  "properties": {
    "addr:full":"Calle de Capuletti, 58 Valladolid Valladolid 47008",
    "addr:housenumber":"58",
    "addr:postcode":"47008",
    "addr:street":"Calle De Capuletti",
    "iso:country":"ES",
    "sg:address":"Calle de Capuletti, 58",
    "sg:city":"Valladolid",
    "sg:orig_category":"M\u00c9dicos: Neumolog\u00cda",
    "sg:phone":"+34 983 24 57 57",
    "sg:postcode":"47008",
    "sg:province":"Valladolid",
    "wof:name":"Aller Alvarez Jose Luis",
    "wof:placetype":"venue"
},
  "geometry": {"coordinates":[-4.7507977486,41.607963562],"type":"Point"}
}