{
  "type": "Feature",
  "properties": {
    "iso:country":"ES",
    "sg:address":"Calle de Aragon (de), 74",
    "sg:city":"Mejorada Campo",
    "sg:orig_category":"Quincaller\u00cda (al Por Menor)",
    "sg:phone":"+34 916 79 40 44",
    "sg:postcode":"28840",
    "sg:province":"Madrid",
    "sg:website":"www.suministrosaunon.com",
    "wof:name":"Suministros Au\u00f1on S.l.",
    "wof:placetype":"venue"
},
  "geometry": {"coordinates":[-3.4808473587,40.3854560852],"type":"Point"}
}