{
  "type": "Feature",
  "properties": {
    "iso:country":"ES",
    "sg:address":"Calle de Eduardo Julian Perez, 9",
    "sg:city":"Zamora",
    "sg:orig_category":"Arreglo, Reparaci\u00d3n, Piezas Sueltas De Televisi\u00d3n, V\u00cddeo, Hi",
    "sg:phone":"+34 980 67 00 99",
    "sg:postcode":"49018",
    "sg:province":"Zamora",
    "wof:name":"Blanco Gonzalez Antonio",
    "wof:placetype":"venue"
},
  "geometry": {"coordinates":[-5.7359957695,41.5050582886],"type":"Point"}
}