{
  "type": "Feature",
  "properties": {
    "iso:country":"ES",
    "sg:address":"Pl Catalunya, S/n",
    "sg:city":"S. Andreu Barca",
    "sg:orig_category":"Institutos De Belleza",
    "sg:phone":"+34 936 82 27 24",
    "sg:postcode":"08740",
    "sg:province":"Barcelona",
    "wof:name":"Bodysbel Scp",
    "wof:placetype":"venue"
},
  "geometry": {"coordinates":[1.9694449902,41.4472808838],"type":"Point"}
}