{
  "type": "Feature",
  "properties": {
    "iso:country":"ES",
    "sg:address":"Calle de Barrilero, 8",
    "sg:city":"Madrid",
    "sg:orig_category":"Productores Recolectores, Venta Directa De Vinos",
    "sg:phone":"+34 915 52 10 15",
    "sg:postcode":"28007",
    "sg:province":"Madrid",
    "wof:name":"Romera Benito Miguel",
    "wof:placetype":"venue"
},
  "geometry": {"coordinates":[-3.6730992794,40.3977088928],"type":"Point"}
}