{
  "type": "Feature",
  "properties": {
    "iso:country":"ES",
    "sg:address":"Calle de Muro, 9",
    "sg:city":"Valladolid",
    "sg:orig_category":"Abogados",
    "sg:phone":"+34 983 30 18 31",
    "sg:postcode":"47004",
    "sg:province":"Valladolid",
    "wof:name":"Lago San Jose Jesus",
    "wof:placetype":"venue"
},
  "geometry": {"coordinates":[-4.7248721123,41.6463737488],"type":"Point"}
}