{
  "type": "Feature",
  "properties": {
    "addr:full":"Carrer de Pardo, 6 Barcelona Barcelona 08027",
    "addr:housenumber":"6",
    "addr:postcode":"08027",
    "addr:street":"Carrer De Pardo",
    "iso:country":"ES",
    "sg:address":"Carrer de Pardo, 6",
    "sg:city":"Barcelona",
    "sg:orig_category":"Fabricaci\u00d3n, Importaci\u00d3n De Material Y Sistemas De Telecomunicaciones",
    "sg:phone":"+34 933 40 87 12",
    "sg:postcode":"08027",
    "sg:province":"Barcelona",
    "sg:website":"www.davantel.com",
    "wof:name":"Desarrollos Avanzados En Telecomunicaciones S.l.",
    "wof:placetype":"venue"
},
  "geometry": {"coordinates":[2.1826250553,41.425994873],"type":"Point"}
}