{
  "type": "Feature",
  "properties": {
    "addr:full":"Carrer de Doctor Pi I Molist, 101 Barcelona Barcelona 08031",
    "addr:housenumber":"101",
    "addr:postcode":"08031",
    "addr:street":"Carrer De Doctor Pi I Molist",
    "iso:country":"ES",
    "sg:address":"Carrer de Doctor Pi I Molist, 101",
    "sg:city":"Barcelona",
    "sg:orig_category":"Servicios Gsm",
    "sg:phone":"+34 933 54 28 81",
    "sg:postcode":"08031",
    "sg:province":"Barcelona",
    "wof:name":"Xxi Sokitel S.l.",
    "wof:placetype":"venue"
},
  "geometry": {"coordinates":[2.1724336147,41.4346542358],"type":"Point"}
}