{
  "type": "Feature",
  "properties": {
    "addr:full":"Calle de Hernan Cortes, 10 Guijo Galisteo C\u00e1ceres 10816",
    "addr:housenumber":"10",
    "addr:postcode":"10816",
    "addr:street":"Calle De Hernan Cortes;Ca\u0301Ceres",
    "iso:country":"ES",
    "sg:address":"Calle de Hernan Cortes, 10",
    "sg:city":"Guijo Galisteo",
    "sg:orig_category":"Iglesia Cat\u00d3lica",
    "sg:phone":"+34 927 44 91 64",
    "sg:postcode":"10816",
    "sg:province":"C\u00e1ceres",
    "wof:name":"Parroquia San Pedro Apostol",
    "wof:placetype":"venue"
},
  "geometry": {"coordinates":[-6.4124779701,40.0935897827],"type":"Point"}
}