{
  "type": "Feature",
  "properties": {
    "addr:full":"Calle de Santa Ana, 6 Plasencia C\u00e1ceres 10600",
    "addr:housenumber":"6",
    "addr:postcode":"10600",
    "addr:street":"Calle De Santa Ana;Ca\u0301Ceres",
    "iso:country":"ES",
    "sg:address":"Calle de Santa Ana, 6",
    "sg:city":"Plasencia",
    "sg:orig_category":"Droguer\u00cdas (al Por Menor)",
    "sg:phone":"+34 927 41 25 63",
    "sg:postcode":"10600",
    "sg:province":"C\u00e1ceres",
    "wof:name":"Sanchez Briz Antonio",
    "wof:placetype":"venue"
},
  "geometry": {"coordinates":[-6.0893549919,40.0310668945],"type":"Point"}
}