{
  "type": "Feature",
  "properties": {
    "iso:country":"ES",
    "sg:address":"Avda Goya, 96",
    "sg:city":"Zaragoza",
    "sg:orig_category":"Inform\u00c1tica, Ofim\u00c1tica (estudios, Asesor\u00cda, Ingenier\u00cda, Formaci\u00d3n)",
    "sg:phone":"+34 976 21 13 32",
    "sg:postcode":"50004",
    "sg:province":"Zaragoza",
    "wof:name":"Digital Europa S.l.",
    "wof:placetype":"venue"
},
  "geometry": {"coordinates":[-0.8813189864,41.6517295837],"type":"Point"}
}