{
  "type": "Feature",
  "properties": {
    "addr:full":"Calle de Santa Engracia, 122 Madrid Madrid 28003",
    "addr:housenumber":"122",
    "addr:postcode":"28003",
    "addr:street":"Calle De Santa Engracia",
    "iso:country":"ES",
    "sg:address":"Calle de Santa Engracia, 122",
    "sg:city":"Madrid",
    "sg:orig_category":"Artes Gr\u00c1ficas, Artes Pl\u00c1sticas (curso)",
    "sg:phone":"+34 913 99 13 07",
    "sg:postcode":"28003",
    "sg:province":"Madrid",
    "sg:website":"www.esdip.com",
    "wof:name":"Esdip Escuela De Arte S.l.",
    "wof:placetype":"venue"
},
  "geometry": {"coordinates":[-3.7012600899,40.4412155151],"type":"Point"}
}