{
  "type": "Feature",
  "properties": {
    "iso:country":"ES",
    "sg:address":"Carr Picapedrers, 25",
    "sg:city":"Vilanova I La Geltru",
    "sg:orig_category":"Locales Y Clases De Danza",
    "sg:phone":"+34 938 93 70 18",
    "sg:postcode":"08800",
    "sg:province":"Barcelona",
    "wof:name":"Estudi De Dan\u00e7a Rosa Mari Gonzalez S.c.p.",
    "wof:placetype":"venue"
},
  "geometry": {"coordinates":[1.7202270031,41.2254829407],"type":"Point"}
}