{
  "type": "Feature",
  "properties": {
    "iso:country":"ES",
    "sg:address":"Avda Juan Carlos I, 75",
    "sg:city":"Ibi",
    "sg:classifiers":[
        {
            "category":"Autos & Motor Vehicles",
            "subcategory":"Automobile Sales",
            "type":"Retail Goods"
        }
    ],
    "sg:phone":"+34 965 55 07 42",
    "sg:postcode":"03440",
    "sg:province":"Alicante",
    "wof:name":"Auto Escuela Monje",
    "wof:placetype":"venue"
},
  "geometry": {"coordinates":[-0.5801044703,38.6207084656],"type":"Point"}
}