{
  "type": "Feature",
  "properties": {
    "addr:full":"Calle de Flor (de La), 2 Alcobendas Madrid 28100",
    "addr:postcode":"28100",
    "addr:street":"Calle De Flor De La 2",
    "iso:country":"ES",
    "sg:address":"Calle de Flor (de La), 2",
    "sg:city":"Alcobendas",
    "sg:orig_category":"Farmacias",
    "sg:phone":"+34 916 51 35 35",
    "sg:postcode":"28100",
    "sg:province":"Madrid",
    "wof:name":"Serrano Diaz Maria Concepcion",
    "wof:placetype":"venue"
},
  "geometry": {"coordinates":[-3.6347429752,40.5401268005],"type":"Point"}
}