{
  "type": "Feature",
  "properties": {
    "addr:full":"Carrer de Josep Maria De Sagarra, 30 Malgrat Mar Barcelona 08380",
    "addr:housenumber":"30",
    "addr:postcode":"08380",
    "addr:street":"Carrer De Josep Maria De Sagarra",
    "iso:country":"ES",
    "sg:address":"Carrer de Josep Maria De Sagarra, 30",
    "sg:city":"Malgrat Mar",
    "sg:orig_category":"Remolques, Carretillas De Mano Para Operaciones Portuarias",
    "sg:phone":"+34 937 65 38 63",
    "sg:postcode":"08380",
    "sg:province":"Barcelona",
    "wof:name":"Auto Placido Malgrat S.l.",
    "wof:placetype":"venue"
},
  "geometry": {"coordinates":[2.7307300568,41.6456413269],"type":"Point"}
}