{
  "type": "Feature",
  "properties": {
    "iso:country":"ES",
    "sg:address":"Carrer de Bonsoms, 29",
    "sg:city":"Barcelona",
    "sg:orig_category":"Molduras, Junquillos, Listones Y Molduras Perforadas",
    "sg:phone":"+34 933 33 90 63",
    "sg:postcode":"08028",
    "sg:province":"Barcelona",
    "wof:name":"Jimenez Calleja Javier",
    "wof:placetype":"venue"
},
  "geometry": {"coordinates":[2.1258759499,41.3737602234],"type":"Point"}
}