{
  "type": "Feature",
  "properties": {
    "addr:full":"Avda Prudencio Gonzalez, 7 Posada Asturias 33424",
    "addr:housenumber":"7",
    "addr:postcode":"33424",
    "addr:street":"Avda Prudencio Gonzalez",
    "iso:country":"ES",
    "sg:address":"Avda Prudencio Gonzalez, 7",
    "sg:city":"Posada",
    "sg:orig_category":"Chapister\u00cda",
    "sg:phone":"+34 985 77 09 84",
    "sg:postcode":"33424",
    "sg:province":"Asturias",
    "wof:name":"Amores Menendez Manuel",
    "wof:placetype":"venue"
},
  "geometry": {"coordinates":[-5.8507771492,43.4391784668],"type":"Point"}
}