{
  "type": "Feature",
  "properties": {
    "addr:full":"Calle de San Francisco, 33 Cabra C\u00f3rdoba 14940",
    "addr:housenumber":"33",
    "addr:postcode":"14940",
    "addr:street":"Calle De San Francisco;Co\u0301Rdoba",
    "iso:country":"ES",
    "sg:address":"Calle de San Francisco, 33",
    "sg:city":"Cabra",
    "sg:orig_category":"Cristaler\u00cdas",
    "sg:phone":"+34 957 52 31 74",
    "sg:postcode":"14940",
    "sg:province":"C\u00f3rdoba",
    "wof:name":"Montes Santiago Antonio",
    "wof:placetype":"venue"
},
  "geometry": {"coordinates":[-4.4298658371,37.4757499695],"type":"Point"}
}