{
  "type": "Feature",
  "properties": {
    "addr:full":"Calle de Dos De Mayo, 41 Gijon Asturias 33212",
    "addr:housenumber":"41",
    "addr:postcode":"33212",
    "addr:street":"Calle De Dos;Mayo",
    "iso:country":"ES",
    "sg:address":"Calle de Dos De Mayo, 41",
    "sg:city":"Gijon",
    "sg:orig_category":"Librer\u00cdas",
    "sg:phone":"+34 985 32 99 77",
    "sg:postcode":"33212",
    "sg:province":"Asturias",
    "wof:name":"Principe Lopez Francisco Jose",
    "wof:placetype":"venue"
},
  "geometry": {"coordinates":[-5.685503006,43.537979126],"type":"Point"}
}