{
  "type": "Feature",
  "properties": {
    "addr:full":"Avda Madrid, 121 Zaragoza Zaragoza 50010",
    "addr:housenumber":"121",
    "addr:postcode":"50010",
    "addr:street":"Avda Madrid",
    "iso:country":"ES",
    "sg:address":"Avda Madrid, 121",
    "sg:city":"Zaragoza",
    "sg:orig_category":"Asesor\u00cda Sobre Comunicaci\u00d3n De Empresas",
    "sg:phone":"+34 976 34 79 44",
    "sg:postcode":"50010",
    "sg:province":"Zaragoza",
    "wof:name":"Pe\u00f1a Roy Ana",
    "wof:placetype":"venue"
},
  "geometry": {"coordinates":[-0.9019389749,41.6539649963],"type":"Point"}
}