{
  "type": "Feature",
  "properties": {
    "addr:full":"Rua Bola\u00d1o Rivadeneira, 21 Lugo Lugo 27001",
    "addr:housenumber":"21",
    "addr:postcode":"27001",
    "addr:street":"Rua Bolan\u0303O Rivadeneira",
    "iso:country":"ES",
    "sg:address":"Rua Bola\u00d1o Rivadeneira, 21",
    "sg:city":"Lugo",
    "sg:orig_category":"Procuradores",
    "sg:phone":"+34 982 24 51 01",
    "sg:postcode":"27001",
    "sg:province":"Lugo",
    "wof:name":"Lorenzana Teijeiro Jose Antonio",
    "wof:placetype":"venue"
},
  "geometry": {"coordinates":[-7.559346199,43.0125465393],"type":"Point"}
}