{
  "type": "Feature",
  "properties": {
    "addr:full":"Avda Padre Isla, 85 Le\u00f3n Le\u00f3n 24008",
    "addr:housenumber":"85",
    "addr:postcode":"24008",
    "addr:street":"Avda Padre Isla;Leo\u0301N",
    "iso:country":"ES",
    "sg:address":"Avda Padre Isla, 85",
    "sg:city":"Le\u00f3n",
    "sg:orig_category":"Mec\u00c1nico Del Autom\u00d3vil",
    "sg:phone":"+34 987 22 20 68",
    "sg:postcode":"24008",
    "sg:province":"Le\u00f3n",
    "wof:name":"Talleres Gilmon S.l.",
    "wof:placetype":"venue"
},
  "geometry": {"coordinates":[-5.5787949562,42.6057701111],"type":"Point"}
}