{
  "type": "Feature",
  "properties": {
    "addr:full":"Calle de Victor Pradera, 14 Mislata Valencia 46920",
    "addr:housenumber":"14",
    "addr:postcode":"46920",
    "addr:street":"Calle De Victor Pradera",
    "iso:country":"ES",
    "sg:address":"Calle de Victor Pradera, 14",
    "sg:city":"Mislata",
    "sg:orig_category":"Chapister\u00cda",
    "sg:phone":"+34 963 83 67 47",
    "sg:postcode":"46920",
    "sg:province":"Valencia",
    "wof:name":"Autos-pradera S.l.",
    "wof:placetype":"venue"
},
  "geometry": {"coordinates":[-0.416662991,39.4763641357],"type":"Point"}
}