{
  "type": "Feature",
  "properties": {
    "iso:country":"ES",
    "sg:address":"Calle de Arcos De La Frontera, 18",
    "sg:city":"Cordoba",
    "sg:orig_category":"Tapicer\u00cdas",
    "sg:phone":"+34 957 25 45 06",
    "sg:postcode":"14014",
    "sg:province":"C\u00f3rdoba",
    "wof:name":"Jimenez Delgado Enrique",
    "wof:placetype":"venue"
},
  "geometry": {"coordinates":[-4.7556967735,37.9003944397],"type":"Point"}
}