{
  "type": "Feature",
  "properties": {
    "addr:full":"Loramendi Kalea, 7 Arrasate Guip\u00f9zcoa 20500",
    "addr:housenumber":"7",
    "addr:postcode":"20500",
    "addr:street":"Loramendi Kalea;Guipu\u0300Zcoa",
    "iso:country":"ES",
    "sg:address":"Loramendi Kalea, 7",
    "sg:city":"Arrasate",
    "sg:orig_category":"Inform\u00c1tica, Ofim\u00c1tica (estudios, Asesor\u00cda, Ingenier\u00cda, Formaci\u00d3n)",
    "sg:phone":"+34 943 77 12 33",
    "sg:postcode":"20500",
    "sg:province":"Guip\u00f9zcoa",
    "wof:name":"Sortu Informatica S.l.",
    "wof:placetype":"venue"
},
  "geometry": {"coordinates":[-2.4959468842,43.0619125366],"type":"Point"}
}