{
  "type": "Feature",
  "properties": {
    "iso:country":"ES",
    "sg:address":"Avda Fatima, 25",
    "sg:city":"Malaga",
    "sg:orig_category":"Arreglo, Reparaci\u00d3n, Piezas Sueltas De Televisi\u00d3n, V\u00cddeo, Hi",
    "sg:phone":"+34 952 28 51 48",
    "sg:postcode":"29009",
    "sg:province":"M\u00e1laga",
    "wof:name":"Mu\u00f1oz Mu\u00f1oz Juan Antonio",
    "wof:placetype":"venue"
},
  "geometry": {"coordinates":[-4.4269480705,36.7265281677],"type":"Point"}
}