{
  "type": "Feature",
  "properties": {
    "iso:country":"ES",
    "sg:address":"Calle de Rios Rosas, 30",
    "sg:city":"Madrid",
    "sg:orig_category":"Agencias De Viajes",
    "sg:phone":"+34 914 51 42 55",
    "sg:postcode":"28003",
    "sg:province":"Madrid",
    "wof:name":"Open Viajes S.l.",
    "wof:placetype":"venue"
},
  "geometry": {"coordinates":[-3.6988039017,40.4417304993],"type":"Point"}
}