{
  "type": "Feature",
  "properties": {
    "iso:country":"ES",
    "sg:address":"Calle de Iglesia, S/n",
    "sg:city":"S. Francisco Olivenza",
    "sg:orig_category":"Asociaciones, Organismos Culturales Y Socioeducativos",
    "sg:phone":"+34 924 49 78 69",
    "sg:postcode":"06109",
    "sg:province":"Badajoz",
    "wof:name":"Ayuntamiento De Olivenza",
    "wof:placetype":"venue"
},
  "geometry": {"coordinates":[-7.1052761078,38.7465667725],"type":"Point"}
}