{
  "type": "Feature",
  "properties": {
    "addr:full":"Alam Ayuntamiento, S/n Colindres Cantabria 39750",
    "addr:housenumber":"/ n",
    "addr:postcode":"39750",
    "addr:street":"Alam Ayuntamiento S",
    "iso:country":"ES",
    "sg:address":"Alam Ayuntamiento, S/n",
    "sg:city":"Colindres",
    "sg:orig_category":"Molduras, Junquillos, Listones Y Molduras Perforadas",
    "sg:phone":"+34 942 67 47 55",
    "sg:postcode":"39750",
    "sg:province":"Cantabria",
    "wof:name":"Sociedad Regional De Informatica S.a.",
    "wof:placetype":"venue"
},
  "geometry": {"coordinates":[-3.4482440948,43.3958396912],"type":"Point"}
}