{
  "type": "Feature",
  "properties": {
    "addr:full":"Calle de Feria (de La), 1 Colmenar Viejo Madrid 28770",
    "addr:postcode":"28770",
    "addr:street":"Calle De",
    "iso:country":"ES",
    "sg:address":"Calle de Feria (de La), 1",
    "sg:city":"Colmenar Viejo",
    "sg:orig_category":"Bazares, Art\u00cdculos De Limpieza Y De Cocina (al Por Menor)",
    "sg:phone":"+34 918 45 46 36",
    "sg:postcode":"28770",
    "sg:province":"Madrid",
    "wof:name":"Galan Lopez Maria Pilar",
    "wof:placetype":"venue"
},
  "geometry": {"coordinates":[-3.7661039829,40.6589775085],"type":"Point"}
}