{
  "type": "Feature",
  "properties": {
    "addr:full":"Calle de Pintor Rosales, 3 Logro\u00f1o La Rioja 26005",
    "addr:housenumber":"3",
    "addr:postcode":"26005",
    "addr:street":"Calle De Pintor Rosales;Rioja",
    "iso:country":"ES",
    "sg:address":"Calle de Pintor Rosales, 3",
    "sg:city":"Logro\u00f1o",
    "sg:classifiers":[
        {
            "category":"Banks & Credit Unions",
            "subcategory":"Bureau De Change",
            "type":"Services"
        }
    ],
    "sg:phone":"+34 941 20 20 88",
    "sg:postcode":"26005",
    "sg:province":"La Rioja",
    "sg:tags":[
        "organismos",
        "control"
    ],
    "wof:name":"Entidad De Control Certificacion Y Servicios Agroalimentarios",
    "wof:placetype":"venue"
},
  "geometry": {"coordinates":[-2.4542911053,42.4576759338],"type":"Point"}
}