{
  "type": "Feature",
  "properties": {
    "iso:country":"ES",
    "sg:address":"Calle de Mirasierra, 3",
    "sg:city":"Moraleja Enmedio",
    "sg:orig_category":"Carnicer\u00cdas, Carnicer\u00cdas",
    "sg:phone":"+34 916 09 33 55",
    "sg:postcode":"28950",
    "sg:province":"Madrid",
    "wof:name":"Martin Arroyo Vicente Luis",
    "wof:placetype":"venue"
},
  "geometry": {"coordinates":[-3.8597300053,40.2622489929],"type":"Point"}
}