{
  "type": "Feature",
  "properties": {
    "iso:country":"ES",
    "sg:address":"Calle de Valdelarco, 10",
    "sg:city":"Sevilla",
    "sg:orig_category":"Telas Y Sedas (al Por Menor)",
    "sg:phone":"+34 954 43 06 92",
    "sg:postcode":"41008",
    "sg:province":"Sevilla",
    "wof:name":"Santana Feria Juan",
    "wof:placetype":"venue"
},
  "geometry": {"coordinates":[-5.9763021469,37.4092445374],"type":"Point"}
}