{
  "type": "Feature",
  "properties": {
    "addr:full":"Carrer de Horta, 56 Barcelona Barcelona 08032",
    "addr:housenumber":"56",
    "addr:postcode":"08032",
    "addr:street":"Carrer De Horta",
    "iso:country":"ES",
    "sg:address":"Carrer de Horta, 56",
    "sg:city":"Barcelona",
    "sg:orig_category":"Cajas De Ahorro",
    "sg:phone":"+34 933 57 39 62",
    "sg:postcode":"08032",
    "sg:province":"Barcelona",
    "wof:name":"Caixa D'estalvis De Catalunya",
    "wof:placetype":"venue"
},
  "geometry": {"coordinates":[2.1526939869,41.4219398499],"type":"Point"}
}