{
  "type": "Feature",
  "properties": {
    "addr:full":"Av Rivoli, 22 Mollet Valles Barcelona 08100",
    "addr:housenumber":"22",
    "addr:postcode":"08100",
    "addr:street":"Av Rivoli",
    "iso:country":"ES",
    "sg:address":"Av Rivoli, 22",
    "sg:city":"Mollet Valles",
    "sg:orig_category":"Reposter\u00cdas",
    "sg:phone":"+34 935 70 39 09",
    "sg:postcode":"08100",
    "sg:province":"Barcelona",
    "wof:name":"Arenas Pineda Juan Antonio",
    "wof:placetype":"venue"
},
  "geometry": {"coordinates":[2.2097730637,41.546913147],"type":"Point"}
}