{
  "type": "Feature",
  "properties": {
    "addr:full":"Calle de Doctor Garcia Y Garcia De Castro, 11 Granada Granada 18015",
    "addr:housenumber":"11",
    "addr:postcode":"18015",
    "addr:street":"Calle De Doctor Garcia Y Garcia De Castro",
    "iso:country":"ES",
    "sg:address":"Calle de Doctor Garcia Y Garcia De Castro, 11",
    "sg:city":"Granada",
    "sg:orig_category":"Caf\u00c9s, Bares, Cervecer\u00cdas",
    "sg:phone":"+34 958 80 02 07",
    "sg:postcode":"18015",
    "sg:province":"Granada",
    "wof:name":"Villegas Juegos S.l.",
    "wof:placetype":"venue"
},
  "geometry": {"coordinates":[-3.6572542191,37.1927947998],"type":"Point"}
}