{
  "type": "Feature",
  "properties": {
    "iso:country":"ES",
    "sg:address":"Calle de Corral De Los Olmos, 1",
    "sg:city":"Sevilla",
    "sg:orig_category":"Caf\u00c9s, Bares, Cervecer\u00cdas",
    "sg:phone":"+34 954 94 71 76",
    "sg:postcode":"41008",
    "sg:province":"Sevilla",
    "wof:name":"Sedano Gonzalez Andres",
    "wof:placetype":"venue"
},
  "geometry": {"coordinates":[-5.9696669579,37.4186248779],"type":"Point"}
}