{
  "type": "Feature",
  "properties": {
    "iso:country":"ES",
    "sg:address":"Calle de Arostegi, 10",
    "sg:city":"Donostia-san Sebastian",
    "sg:orig_category":"Internados & Ense\u00d1anza Privada",
    "sg:phone":"+34 943 21 88 11",
    "sg:postcode":"20009",
    "sg:province":"Guip\u00f9zcoa",
    "wof:name":"Axular Lizeoa Kooperatiba Elkartea",
    "wof:placetype":"venue"
},
  "geometry": {"coordinates":[-1.9874676466,43.2989845276],"type":"Point"}
}