{
  "type": "Feature",
  "properties": {
    "iso:country":"ES",
    "sg:address":"Calle de Venezuela, 18",
    "sg:city":"Vitoria-gasteiz",
    "sg:orig_category":"Ropa Para Ni\u00d1os (al Por Menor)",
    "sg:phone":"+34 945 28 49 76",
    "sg:postcode":"01012",
    "sg:province":"\u00c1lava",
    "wof:name":"Barchino Navarro Antonio",
    "wof:placetype":"venue"
},
  "geometry": {"coordinates":[-2.6785800457,42.8582229614],"type":"Point"}
}