{
  "type": "Feature",
  "properties": {
    "addr:full":"Pase Chopera, 51 Madrid Madrid 28045",
    "addr:housenumber":"51",
    "addr:postcode":"madrid;28045",
    "iso:country":"ES",
    "sg:address":"Pase Chopera, 51",
    "sg:city":"Madrid",
    "sg:orig_category":"Peluquer\u00cdas, Peluquer\u00cda Mixta",
    "sg:phone":"+34 914 73 21 55",
    "sg:postcode":"28045",
    "sg:province":"Madrid",
    "wof:name":"Cabezudo Gonzalez Santiago",
    "wof:placetype":"venue"
},
  "geometry": {"coordinates":[-3.6974000931,40.3929367065],"type":"Point"}
}