{
  "type": "Feature",
  "properties": {
    "addr:full":"Calle de Ortega Y Gasset, S/n Ponferrada Le\u00f3n 24400",
    "addr:housenumber":"s / n",
    "addr:postcode":"24400",
    "addr:street":"Calle De Ortega Y Gasset",
    "iso:country":"ES",
    "sg:address":"Calle de Ortega Y Gasset, S/n",
    "sg:city":"Ponferrada",
    "sg:orig_category":"Partidos Pol\u00cdticos",
    "sg:phone":"+34 987 41 19 50",
    "sg:postcode":"24400",
    "sg:province":"Le\u00f3n",
    "wof:name":"Partido Popular",
    "wof:placetype":"venue"
},
  "geometry": {"coordinates":[-6.5976438522,42.5442352295],"type":"Point"}
}