{
  "type": "Feature",
  "properties": {
    "addr:full":"Ctra. Alj. Cartaya, 1 Aljaraque Huelva 21110",
    "addr:housenumber":"1",
    "addr:postcode":"21110",
    "addr:street":"Ctra. Alj.",
    "iso:country":"ES",
    "sg:address":"Ctra. Alj. Cartaya, 1",
    "sg:city":"Aljaraque",
    "sg:orig_category":"Contenedores (mercanc\u00cdas)",
    "sg:phone":"+34 959 31 84 87",
    "sg:postcode":"21110",
    "sg:province":"Huelva",
    "wof:name":"Lazaro Esteban Amador",
    "wof:placetype":"venue"
},
  "geometry": {"coordinates":[-7.0241990089,37.2709159851],"type":"Point"}
}