{
  "type": "Feature",
  "properties": {
    "iso:country":"ES",
    "sg:address":"Calle de Palma (la), 24",
    "sg:city":"Andujar",
    "sg:orig_category":"Motocicletas (agentes, Concesionarios)",
    "sg:phone":"+34 953 50 65 66",
    "sg:postcode":"23740",
    "sg:province":"Ja\u00e9n",
    "wof:name":"Lopez Medina Miguel",
    "wof:placetype":"venue"
},
  "geometry": {"coordinates":[-4.0482068062,38.0418663025],"type":"Point"}
}