{
  "type": "Feature",
  "properties": {
    "addr:full":"Via Sant Ignasi, 40 Manresa Barcelona 08241",
    "addr:housenumber":"40",
    "addr:postcode":"08241",
    "addr:street":"Via Sant Ignasi",
    "iso:country":"ES",
    "sg:address":"Via Sant Ignasi, 40",
    "sg:city":"Manresa",
    "sg:orig_category":"Museos",
    "sg:phone":"+34 938 74 11 55",
    "sg:postcode":"08241",
    "sg:province":"Barcelona",
    "wof:name":"Ajuntament De Manresa",
    "wof:placetype":"venue"
},
  "geometry": {"coordinates":[1.82987535,41.7249183655],"type":"Point"}
}