{
  "type": "Feature",
  "properties": {
    "addr:full":"Carrer de Navarra, 27 Manresa Barcelona 08242",
    "addr:housenumber":"27",
    "addr:postcode":"08242",
    "addr:street":"Carrer De Navarra",
    "iso:country":"ES",
    "sg:address":"Carrer de Navarra, 27",
    "sg:city":"Manresa",
    "sg:orig_category":"Arquitectos",
    "sg:phone":"+34 938 75 12 24",
    "sg:postcode":"08242",
    "sg:province":"Barcelona",
    "wof:name":"Espinal Farre Jaime",
    "wof:placetype":"venue"
},
  "geometry": {"coordinates":[1.817710042,41.7281417847],"type":"Point"}
}