{
  "type": "Feature",
  "properties": {
    "iso:country":"ES",
    "sg:address":"Pg Sant Joan, 181",
    "sg:city":"Barcelona",
    "sg:orig_category":"Zapatos (al Por Menor)",
    "sg:phone":"+34 934 59 00 89",
    "sg:postcode":"08037",
    "sg:province":"Barcelona",
    "wof:name":"Gonzalez Martin Javier",
    "wof:placetype":"venue"
},
  "geometry": {"coordinates":[2.1640410423,41.4031829834],"type":"Point"}
}