{
  "type": "Feature",
  "properties": {
    "addr:full":"Calle de Ronda, 17 Villarta S. Juan Ciudad Real 13210",
    "addr:housenumber":"17",
    "addr:postcode":"13210",
    "addr:street":"Calle De Ronda;Villarta S. Juan Ciudad Real",
    "iso:country":"ES",
    "sg:address":"Calle de Ronda, 17",
    "sg:city":"Villarta S. Juan",
    "sg:classifiers":[
        {
            "category":"Taxi",
            "type":"Transportation"
        }
    ],
    "sg:phone":"+34 926 64 03 60",
    "sg:postcode":"13210",
    "sg:province":"Ciudad Real",
    "wof:name":"Martin Fernandez Jose",
    "wof:placetype":"venue"
},
  "geometry": {"coordinates":[-3.4263660908,39.2390289307],"type":"Point"}
}