{
  "type": "Feature",
  "properties": {
    "iso:country":"ES",
    "sg:address":"Calle de Conde De Salvatierra, 3",
    "sg:city":"Valencia",
    "sg:orig_category":"M\u00c9dicos: Dermatolog\u00cda Y Venereolog\u00cda",
    "sg:phone":"+34 963 51 35 93",
    "sg:postcode":"46004",
    "sg:province":"Valencia",
    "wof:name":"Cervera Genis Jose",
    "wof:placetype":"venue"
},
  "geometry": {"coordinates":[-0.3691542149,39.4711112976],"type":"Point"}
}