{
  "type": "Feature",
  "properties": {
    "addr:full":"Luga Ciudad Jardin Virgen Del Milagro, 13 Ciudad Jardin Virgen Del Milagro Palencia 34190",
    "addr:housenumber":"13",
    "addr:postcode":"34190",
    "addr:street":"Ciudad;Virgen",
    "iso:country":"ES",
    "sg:address":"Luga Ciudad Jardin Virgen Del Milagro, 13",
    "sg:city":"Ciudad Jardin Virgen Del Milagro",
    "sg:orig_category":"Molduras, Junquillos, Listones Y Molduras Perforadas",
    "sg:phone":"+34 979 77 72 72",
    "sg:postcode":"34190",
    "sg:province":"Palencia",
    "wof:name":"Casas Fontal Anibal",
    "wof:placetype":"venue"
},
  "geometry": {"coordinates":[-4.5164442062,41.9515914917],"type":"Point"}
}