{
  "type": "Feature",
  "properties": {
    "addr:full":"Calle de Chile, 10 Logro\u00f1o La Rioja 26005",
    "addr:housenumber":"10",
    "addr:postcode":"26005",
    "addr:street":"Calle De Chile;Rioja",
    "iso:country":"ES",
    "sg:address":"Calle de Chile, 10",
    "sg:city":"Logro\u00f1o",
    "sg:orig_category":"Zapatos (al Por Menor)",
    "sg:phone":"+34 941 21 14 62",
    "sg:postcode":"26005",
    "sg:province":"La Rioja",
    "wof:name":"Calzados Diez S.a.",
    "wof:placetype":"venue"
},
  "geometry": {"coordinates":[-2.453592062,42.4633331299],"type":"Point"}
}