{
  "type": "Feature",
  "properties": {
    "addr:full":"Ctra. Alcorcon-plasencia, S/n Poyales Del Hoyo \u00c1vila 05492",
    "addr:housenumber":"s",
    "addr:postcode":"05492",
    "addr:street":"Ctra. Alcorcon-Plasencia;/ N",
    "iso:country":"ES",
    "sg:address":"Ctra. Alcorcon-plasencia, S/n",
    "sg:city":"Poyales Del Hoyo",
    "sg:orig_category":"Producci\u00d3n, Venta De Productos De Agricultura Biol\u00d3gica",
    "sg:phone":"+34 920 39 01 00",
    "sg:postcode":"05492",
    "sg:province":"\u00c1vila",
    "wof:name":"Vega De Gredos Sociedad Cooperativa Limitada",
    "wof:placetype":"venue"
},
  "geometry": {"coordinates":[-5.1668691635,40.1736106873],"type":"Point"}
}