{
  "type": "Feature",
  "properties": {
    "addr:full":"Calle de Alcalde Pe\u00d1amaria De Llano, 3 Coru\u00d1a La Coru\u00f1a 15010",
    "addr:housenumber":"3",
    "addr:postcode":"15010",
    "addr:street":"Calle De Alcalde Pen\u0303Amaria De Llano;La Corun\u0303A",
    "iso:country":"ES",
    "sg:address":"Calle de Alcalde Pe\u00d1amaria De Llano, 3",
    "sg:city":"Coru\u00d1a",
    "sg:orig_category":"Asesor\u00cda De Formaci\u00d3n Y Gesti\u00d3n De Personal",
    "sg:phone":"+34 981 26 87 11",
    "sg:postcode":"15010",
    "sg:province":"La Coru\u00f1a",
    "wof:name":"Carricarte Gomez Eduardo Martin De",
    "wof:placetype":"venue"
},
  "geometry": {"coordinates":[-8.424703598,43.3610801697],"type":"Point"}
}