{
  "type": "Feature",
  "properties": {
    "addr:full":"Plaz Mayor, 21 Valladolid Valladolid 47001",
    "addr:housenumber":"21",
    "addr:postcode":"47001",
    "addr:street":"Plaz Mayor",
    "iso:country":"ES",
    "sg:address":"Plaz Mayor, 21",
    "sg:city":"Valladolid",
    "sg:orig_category":"Ense\u00d1anza, Formaci\u00d3n Profesional: Aprendizaje",
    "sg:phone":"+34 983 35 62 04",
    "sg:postcode":"47001",
    "sg:province":"Valladolid",
    "wof:name":"Coalicion Electoral Izquierda Unida",
    "wof:placetype":"venue"
},
  "geometry": {"coordinates":[-4.7291631699,41.6522636414],"type":"Point"}
}