{
  "type": "Feature",
  "properties": {
    "iso:country":"ES",
    "sg:address":"Calle de Ramon Albarran, 12",
    "sg:city":"Badajoz",
    "sg:orig_category":"Ingeniero",
    "sg:phone":"+34 924 23 37 88",
    "sg:postcode":"06002",
    "sg:province":"Badajoz",
    "wof:name":"Gabinete Morales Garcia Ingenieria S.l.u.",
    "wof:placetype":"venue"
},
  "geometry": {"coordinates":[-6.9697880745,38.8771438599],"type":"Point"}
}