{
  "type": "Feature",
  "properties": {
    "addr:full":"Avda Cambados, 36 Mosteiro Pontevedra 36637",
    "addr:housenumber":"36",
    "addr:postcode":"36637",
    "addr:street":"Avda Cambados",
    "iso:country":"ES",
    "sg:address":"Avda Cambados, 36",
    "sg:city":"Mosteiro",
    "sg:orig_category":"Reposter\u00cdas",
    "sg:phone":"+34 986 71 20 63",
    "sg:postcode":"36637",
    "sg:province":"Pontevedra",
    "wof:name":"Hermida Torres Elias",
    "wof:placetype":"venue"
},
  "geometry": {"coordinates":[-8.7026891708,42.5181312561],"type":"Point"}
}