{
  "type": "Feature",
  "properties": {
    "iso:country":"ES",
    "sg:address":"Carrer de Valencia, 70",
    "sg:city":"Barcelona",
    "sg:orig_category":"Asociaciones, Organismos Culturales Y Socioeducativos",
    "sg:phone":"+34 932 26 64 56",
    "sg:postcode":"08015",
    "sg:province":"Barcelona",
    "wof:name":"Matria Asociacion Cultural",
    "wof:placetype":"venue"
},
  "geometry": {"coordinates":[2.1488800049,41.3816375732],"type":"Point"}
}