{
  "type": "Feature",
  "properties": {
    "iso:country":"ES",
    "sg:address":"Plaz Fonsagrada, 5",
    "sg:city":"Madrid",
    "sg:orig_category":"M\u00c9dicos: Ortopedia Dento",
    "sg:phone":"+34 917 38 61 56",
    "sg:postcode":"28029",
    "sg:province":"Madrid",
    "sg:website":"www.centroaudicion.com",
    "wof:name":"Viedma 2003 S.l",
    "wof:placetype":"venue"
},
  "geometry": {"coordinates":[-3.7077250481,40.4780158997],"type":"Point"}
}