{
  "type": "Feature",
  "properties": {
    "iso:country":"ES",
    "sg:address":"Calle de Rafael Argeles, S/n",
    "sg:city":"Algeciras",
    "sg:orig_category":"Carnicer\u00cdas, Carnicer\u00cdas",
    "sg:phone":"+34 956 66 58 10",
    "sg:postcode":"11202",
    "sg:province":"C\u00e1diz",
    "wof:name":"Lopez Rodon Jose Antonio",
    "wof:placetype":"venue"
},
  "geometry": {"coordinates":[-5.4509439468,36.1355018616],"type":"Point"}
}