{
  "type": "Feature",
  "properties": {
    "iso:country":"ES",
    "sg:address":"Carr Martell, 2",
    "sg:city":"Pollen\u00e7a",
    "sg:orig_category":"Caf\u00c9s, Bares, Cervecer\u00cdas",
    "sg:phone":"+34 971 53 20 91",
    "sg:postcode":"07460",
    "sg:province":"Islas Baleares",
    "wof:name":"La Scalinata S.l.",
    "wof:placetype":"venue"
},
  "geometry": {"coordinates":[3.0190351009,39.8781204224],"type":"Point"}
}