{
  "type": "Feature",
  "properties": {
    "addr:full":"Carrer de Can Nualart, 5 Garriga Barcelona 08530",
    "addr:housenumber":"5",
    "addr:postcode":"08530",
    "addr:street":"Carrer De Can Nualart",
    "iso:country":"ES",
    "sg:address":"Carrer de Can Nualart, 5",
    "sg:city":"Garriga",
    "sg:orig_category":"Asesor\u00cdas Y Estudios Financieros",
    "sg:phone":"+34 938 41 81 33",
    "sg:postcode":"08530",
    "sg:province":"Barcelona",
    "wof:name":"Menta Textil S.l.",
    "wof:placetype":"venue"
},
  "geometry": {"coordinates":[2.2840359211,41.6830787659],"type":"Point"}
}