{
  "type": "Feature",
  "properties": {
    "addr:full":"Avda Rafaela Ybarra, 8 Madrid Madrid 28026",
    "addr:housenumber":"8",
    "addr:postcode":"madrid;28026",
    "addr:street":"Avda Rafaela Ybarra",
    "iso:country":"ES",
    "sg:address":"Avda Rafaela Ybarra, 8",
    "sg:city":"Madrid",
    "sg:orig_category":"Inmobiliaria (agencias)",
    "sg:phone":"+34 915 65 00 99",
    "sg:postcode":"28026",
    "sg:province":"Madrid",
    "sg:website":"www.habitasa.com",
    "wof:name":"Habitasa Usera Consulting Inmobiliario S.l.",
    "wof:placetype":"venue"
},
  "geometry": {"coordinates":[-3.7113130093,40.3826332092],"type":"Point"}
}