{
  "type": "Feature",
  "properties": {
    "addr:full":"Carrer de Bogatell, 4 S. Adria Besos Barcelona 08930",
    "addr:housenumber":"4",
    "addr:postcode":"08930",
    "addr:street":"Carrer De Bogatell;Barcelona",
    "iso:country":"ES",
    "sg:address":"Carrer de Bogatell, 4",
    "sg:city":"S. Adria Besos",
    "sg:orig_category":"Ropa Para Ni\u00d1os (al Por Menor)",
    "sg:phone":"+34 934 62 07 26",
    "sg:postcode":"08930",
    "sg:province":"Barcelona",
    "wof:name":"Golet Roset Francisco",
    "wof:placetype":"venue"
},
  "geometry": {"coordinates":[2.2164580822,41.4329872131],"type":"Point"}
}