{
  "type": "Feature",
  "properties": {
    "addr:full":"Calle de Nubla, 9 Cazorla Ja\u00e9n 23470",
    "addr:housenumber":"9",
    "addr:postcode":"23470",
    "addr:street":"Calle De Nubla",
    "iso:country":"ES",
    "sg:address":"Calle de Nubla, 9",
    "sg:city":"Cazorla",
    "sg:orig_category":"Art\u00cdculos De Regalo (al Por Menor)",
    "sg:phone":"+34 953 72 06 30",
    "sg:postcode":"23470",
    "sg:province":"Ja\u00e9n",
    "wof:name":"Garcia Galdon Javier",
    "wof:placetype":"venue"
},
  "geometry": {"coordinates":[-3.0025138855,37.9101104736],"type":"Point"}
}