{
  "type": "Feature",
  "properties": {
    "iso:country":"ES",
    "sg:address":"Carrer de Can Veri, 10",
    "sg:city":"Palma",
    "sg:classifiers":[
        {
            "category":"Arts & Performance",
            "subcategory":"Art Gallery",
            "type":"Entertainment"
        }
    ],
    "sg:phone":"+34 971 71 59 89",
    "sg:postcode":"07001",
    "sg:province":"Islas Baleares",
    "sg:tags":[
        "arte",
        "de",
        "galer\u00cdas"
    ],
    "wof:name":"Guaita Esteva Joan",
    "wof:placetype":"venue"
},
  "geometry": {"coordinates":[2.6480429173,39.5697631836],"type":"Point"}
}