{
  "type": "Feature",
  "properties": {
    "iso:country":"ES",
    "sg:address":"Calle de Orense, 28",
    "sg:city":"Madrid",
    "sg:orig_category":"Cuidado Del Cabello",
    "sg:phone":"+34 915 56 10 82",
    "sg:postcode":"28020",
    "sg:province":"Madrid",
    "sg:website":"www.svenson.es",
    "wof:name":"Svenson S.l.",
    "wof:placetype":"venue"
},
  "geometry": {"coordinates":[-3.6950078011,40.4521522522],"type":"Point"}
}