{
  "type": "Feature",
  "properties": {
    "iso:country":"ES",
    "sg:address":"Calle de Colon, 39",
    "sg:city":"Valencia",
    "sg:orig_category":"M\u00c9dicos: Neurocirug\u00cda",
    "sg:phone":"+34 963 50 90 31",
    "sg:postcode":"46004",
    "sg:province":"Valencia",
    "wof:name":"Sanchis Fargueta Jose",
    "wof:placetype":"venue"
},
  "geometry": {"coordinates":[-0.3699268997,39.4707984924],"type":"Point"}
}