{
  "type": "Feature",
  "properties": {
    "iso:country":"ES",
    "sg:address":"Calle de Juan Carlos I Rey De Espa\u00d1a, 2",
    "sg:city":"Badajoz",
    "sg:orig_category":"Tapiceros Y Tapiceros",
    "sg:phone":"+34 924 22 22 13",
    "sg:postcode":"06002",
    "sg:province":"Badajoz",
    "wof:name":"Room Decoracion De Interiores S.l.",
    "wof:placetype":"venue"
},
  "geometry": {"coordinates":[-6.9716691971,38.8768386841],"type":"Point"}
}