{
  "type": "Feature",
  "properties": {
    "addr:full":"Montechico, S/n Cumbres Mayores Huelva 21380",
    "addr:housenumber":"/ n",
    "addr:postcode":"21380",
    "addr:street":"Montechico S",
    "iso:country":"ES",
    "sg:address":"Montechico, S/n",
    "sg:city":"Cumbres Mayores",
    "sg:orig_category":"Charcuter\u00cdas (al Por Mayor)",
    "sg:phone":"+34 959 71 00 09",
    "sg:postcode":"21380",
    "sg:province":"Huelva",
    "wof:name":"Hijos De Narciso Vazquez Fernandez C.b.",
    "wof:placetype":"venue"
},
  "geometry": {"coordinates":[-6.6446328163,38.0636405945],"type":"Point"}
}