{
  "type": "Feature",
  "properties": {
    "addr:full":"Calle de San Vicente Martir, 33 Molina Segura Murcia 30500",
    "addr:housenumber":"33",
    "addr:postcode":"30500",
    "addr:street":"Calle De San Vicente Martir",
    "iso:country":"ES",
    "sg:address":"Calle de San Vicente Martir, 33",
    "sg:city":"Molina Segura",
    "sg:orig_category":"Agencias Y Agentes Comerciales, Representantes",
    "sg:phone":"+34 968 64 19 68",
    "sg:postcode":"30500",
    "sg:province":"Murcia",
    "wof:name":"Sabre S.l.",
    "wof:placetype":"venue"
},
  "geometry": {"coordinates":[-1.2103539705,38.0531539917],"type":"Point"}
}