{
  "type": "Feature",
  "properties": {
    "addr:full":"Calle de Valverde, 25 Madrid Madrid 28004",
    "addr:housenumber":"25",
    "addr:postcode":"madrid;28004",
    "addr:street":"Calle De Valverde",
    "iso:country":"ES",
    "sg:address":"Calle de Valverde, 25",
    "sg:city":"Madrid",
    "sg:orig_category":"Librer\u00cdas",
    "sg:phone":"+34 915 22 66 34",
    "sg:postcode":"28004",
    "sg:province":"Madrid",
    "sg:website":"www.murguialibros.com",
    "wof:name":"H. F. Martinez De Murguia S. A.",
    "wof:placetype":"venue"
},
  "geometry": {"coordinates":[-3.7018558979,40.4225349426],"type":"Point"}
}