{
  "type": "Feature",
  "properties": {
    "addr:full":"Ctra Taiala, 104 Girona Girona 17007",
    "addr:housenumber":"104",
    "addr:postcode":"17007",
    "addr:street":"Ctra Taiala",
    "iso:country":"ES",
    "sg:address":"Ctra Taiala, 104",
    "sg:city":"Girona",
    "sg:orig_category":"Instalaci\u00d3n De Aspiraci\u00d3n De Gases Y Humos",
    "sg:phone":"+34 972 20 69 44",
    "sg:postcode":"17007",
    "sg:province":"Girona",
    "wof:name":"Sala Carola Albert",
    "wof:placetype":"venue"
},
  "geometry": {"coordinates":[2.8014268875,41.9953193665],"type":"Point"}
}