{
  "type": "Feature",
  "properties": {
    "iso:country":"ES",
    "sg:address":"C/ Alvarez De Castro, 9",
    "sg:city":"Banyoles",
    "sg:orig_category":"Abogados",
    "sg:phone":"+34 972 57 59 04",
    "sg:postcode":"17820",
    "sg:province":"Girona",
    "wof:name":"Pages Heras Francesc Xavier",
    "wof:placetype":"venue"
},
  "geometry": {"coordinates":[2.7645499706,42.1171913147],"type":"Point"}
}