{
  "type": "Feature",
  "properties": {
    "iso:country":"ES",
    "sg:address":"Calle de Bolenga (la), 60",
    "sg:city":"Carrizo Ribera",
    "sg:orig_category":"Molduras, Junquillos, Listones Y Molduras Perforadas",
    "sg:phone":"+34 987 35 74 51",
    "sg:postcode":"24270",
    "sg:province":"Le\u00f3n",
    "wof:name":"Gonzalez Llamas Jose Manuel",
    "wof:placetype":"venue"
},
  "geometry": {"coordinates":[-5.8270010948,42.5826683044],"type":"Point"}
}