{
  "type": "Feature",
  "properties": {
    "iso:country":"ES",
    "sg:address":"Avda Santiago, 23",
    "sg:city":"Vitoria-gasteiz",
    "sg:orig_category":"Estancos",
    "sg:phone":"+34 945 28 69 52",
    "sg:postcode":"01003",
    "sg:province":"\u00c1lava",
    "wof:name":"Garcia Pe\u00f1os Maria Teresa",
    "wof:placetype":"venue"
},
  "geometry": {"coordinates":[-2.664223671,42.8472938538],"type":"Point"}
}