{
  "type": "Feature",
  "properties": {
    "iso:country":"ES",
    "sg:address":"Calle de Juan Llorens, 11",
    "sg:city":"Valencia",
    "sg:orig_category":"M\u00c9dicos: Ginecolog\u00cda Y Obstetricia",
    "sg:phone":"+34 963 85 75 51",
    "sg:postcode":"46008",
    "sg:province":"Valencia",
    "wof:name":"Mares Tejada Dolores",
    "wof:placetype":"venue"
},
  "geometry": {"coordinates":[-0.3909800053,39.4732551575],"type":"Point"}
}