{
  "type": "Feature",
  "properties": {
    "addr:full":"Avda Levante (de), 43 Jumilla Murcia 30520",
    "addr:housenumber":"43",
    "addr:postcode":"30520",
    "addr:street":"Avda Levante De",
    "iso:country":"ES",
    "sg:address":"Avda Levante (de), 43",
    "sg:city":"Jumilla",
    "sg:classifiers":[
        {
            "category":"Autos & Motor Vehicles",
            "subcategory":"Automobile Sales",
            "type":"Retail Goods"
        }
    ],
    "sg:phone":"+34 968 78 15 17",
    "sg:postcode":"30520",
    "sg:province":"Murcia",
    "wof:name":"Hernandez Nieto Antonio",
    "wof:placetype":"venue"
},
  "geometry": {"coordinates":[-1.3243249655,38.474521637],"type":"Point"}
}