{
  "type": "Feature",
  "properties": {
    "addr:full":"Calle de Ruben Dario, 1 San Vicente De Barakaldo Vizcaya 48901",
    "addr:housenumber":"1",
    "addr:postcode":"48901",
    "addr:street":"Calle De Ruben Dario",
    "iso:country":"ES",
    "sg:address":"Calle de Ruben Dario, 1",
    "sg:city":"San Vicente De Barakaldo",
    "sg:orig_category":"Aparcamientos (infraestructuras, Accesorios)",
    "sg:phone":"+34 944 37 98 39",
    "sg:postcode":"48901",
    "sg:province":"Vizcaya",
    "wof:name":"Echevarri Gonzalo Jose Ramon",
    "wof:placetype":"venue"
},
  "geometry": {"coordinates":[-2.9875841141,43.3001480103],"type":"Point"}
}