{
  "type": "Feature",
  "properties": {
    "iso:country":"ES",
    "sg:address":"Rua Carballeira, 6",
    "sg:city":"Cambados",
    "sg:orig_category":"Electricidad: Instaladores",
    "sg:phone":"+34 986 54 26 22",
    "sg:postcode":"36630",
    "sg:province":"Pontevedra",
    "wof:name":"Cardecid S.l.",
    "wof:placetype":"venue"
},
  "geometry": {"coordinates":[-8.8121595383,42.5154495239],"type":"Point"}
}