{
  "type": "Feature",
  "properties": {
    "iso:country":"ES",
    "sg:address":"Calle de Valverde, 32",
    "sg:city":"Madrid",
    "sg:orig_category":"Locales De Saunas, De Ba\u00d1os",
    "sg:phone":"+34 915 22 99 56",
    "sg:postcode":"28004",
    "sg:province":"Madrid",
    "wof:name":"Berjoquin S.a.",
    "wof:placetype":"venue"
},
  "geometry": {"coordinates":[-3.7014739513,40.4226951599],"type":"Point"}
}