{
  "type": "Feature",
  "properties": {
    "addr:full":"Carrer de Miquel Ricoma, 92 Granollers Barcelona 08401",
    "addr:housenumber":"92",
    "addr:postcode":"08401",
    "addr:street":"Carrer De Miquel Ricoma",
    "iso:country":"ES",
    "sg:address":"Carrer de Miquel Ricoma, 92",
    "sg:city":"Granollers",
    "sg:orig_category":"Molduras, Junquillos, Listones Y Molduras Perforadas",
    "sg:phone":"+34 938 61 32 67",
    "sg:postcode":"08401",
    "sg:province":"Barcelona",
    "wof:name":"Vasepu S.cp.",
    "wof:placetype":"venue"
},
  "geometry": {"coordinates":[2.2861459255,41.6051101685],"type":"Point"}
}