{
  "type": "Feature",
  "properties": {
    "iso:country":"ES",
    "sg:address":"Carrer de Floridablanca, 43",
    "sg:city":"Mataro",
    "sg:orig_category":"Guarder\u00cdas",
    "sg:phone":"+34 937 96 06 87",
    "sg:postcode":"08301",
    "sg:province":"Barcelona",
    "wof:name":"Anxaneta S.l.",
    "wof:placetype":"venue"
},
  "geometry": {"coordinates":[2.4523882866,41.5410346985],"type":"Point"}
}