{
  "type": "Feature",
  "properties": {
    "iso:country":"ES",
    "sg:address":"Plaz Espa\u00d1a, 5",
    "sg:city":"Ronda",
    "sg:orig_category":"Farmacias",
    "sg:phone":"+34 952 87 15 80",
    "sg:postcode":"29400",
    "sg:province":"M\u00e1laga",
    "wof:name":"Santos Zafra Fernanda",
    "wof:placetype":"venue"
},
  "geometry": {"coordinates":[-5.1662788391,36.7417945862],"type":"Point"}
}