{
  "type": "Feature",
  "properties": {
    "iso:country":"ES",
    "sg:address":"Ctra Sevilla-utrera, Km. 0007,0",
    "sg:city":"Alcala Guadaira",
    "sg:classifiers":[
        {
            "category":"Professional",
            "subcategory":"Business Services",
            "type":"Services"
        }
    ],
    "sg:phone":"+34 955 99 03 84",
    "sg:postcode":"41500",
    "sg:province":"Sevilla",
    "sg:tags":[
        "control",
        "asesor\u00cda",
        "organizaci\u00d3n",
        "la",
        "de",
        "gesti\u00d3n",
        "y"
    ],
    "wof:name":"Estacion De Servicio El Ancla S.l.",
    "wof:placetype":"venue"
},
  "geometry": {"coordinates":[-5.8398590088,37.3383140564],"type":"Point"}
}