{
  "type": "Feature",
  "properties": {
    "iso:country":"ES",
    "sg:address":"Plaz Cid, 9",
    "sg:city":"Melgar Fernamental",
    "sg:orig_category":"Alquiler De Veh\u00cdculos: Turismos Y Utilitarios",
    "sg:phone":"+34 947 37 21 35",
    "sg:postcode":"09100",
    "sg:province":"Burgos",
    "wof:name":"El Noroeste De Burgos S. R. C.",
    "wof:placetype":"venue"
},
  "geometry": {"coordinates":[-4.2453022003,42.4037704468],"type":"Point"}
}