{
  "type": "Feature",
  "properties": {
    "iso:country":"ES",
    "sg:address":"Avda Fisterra, 58",
    "sg:city":"Serra De Outes",
    "sg:orig_category":"Ingenier\u00cda, Centros De Estudios (diversos)",
    "sg:phone":"+34 981 85 08 52",
    "sg:postcode":"15230",
    "sg:province":"A Coru\u00f1a",
    "wof:name":"Transportes Outon E Hijos S.l.",
    "wof:placetype":"venue"
},
  "geometry": {"coordinates":[-8.9070386887,42.8427963257],"type":"Point"}
}