{
  "type": "Feature",
  "properties": {
    "iso:country":"ES",
    "sg:address":"Calle de Sierra Nevada, 9",
    "sg:city":"Gabia Grande",
    "sg:orig_category":"Reparaciones Y Remolcado De Veh\u00cdculos",
    "sg:phone":"+34 958 58 00 83",
    "sg:postcode":"18110",
    "sg:province":"Granada",
    "wof:name":"Jimenez Perti\u00f1ez Antonio Manuel",
    "wof:placetype":"venue"
},
  "geometry": {"coordinates":[-3.6720340252,37.1373825073],"type":"Point"}
}