{
  "type": "Feature",
  "properties": {
    "addr:full":"Calle de Padre Santonja, 49 Mislata Valencia 46920",
    "addr:housenumber":"49",
    "addr:postcode":"46920",
    "addr:street":"Calle De Padre Santonja",
    "iso:country":"ES",
    "sg:address":"Calle de Padre Santonja, 49",
    "sg:city":"Mislata",
    "sg:orig_category":"Mec\u00c1nico Del Autom\u00d3vil",
    "sg:phone":"+34 963 70 00 26",
    "sg:postcode":"46920",
    "sg:province":"Valencia",
    "wof:name":"Talleres Vera S. L.",
    "wof:placetype":"venue"
},
  "geometry": {"coordinates":[-0.4179047048,39.4706115723],"type":"Point"}
}