{
  "type": "Feature",
  "properties": {
    "iso:country":"ES",
    "sg:address":"Calle de Chile, 4",
    "sg:city":"Gijon",
    "sg:orig_category":"Flores Y Plantas Naturales (al Por Mayor)",
    "sg:phone":"+34 985 31 27 01",
    "sg:postcode":"33212",
    "sg:province":"Asturias",
    "wof:name":"Ivan De La Fuente Floristeria",
    "wof:placetype":"venue"
},
  "geometry": {"coordinates":[-5.6897153854,43.5378837585],"type":"Point"}
}