{
  "type": "Feature",
  "properties": {
    "addr:full":"Calle de Juan Xxiii, 12 Huercal-overa Almer\u00eda 04600",
    "addr:housenumber":"12",
    "addr:postcode":"04600",
    "addr:street":"Calle De Juan Xxiii;Almeri\u0301A",
    "iso:country":"ES",
    "sg:address":"Calle de Juan Xxiii, 12",
    "sg:city":"Huercal-overa",
    "sg:orig_category":"Alimentaci\u00d3n General (al Por Menor)",
    "sg:phone":"+34 950 47 09 85",
    "sg:postcode":"04600",
    "sg:province":"Almer\u00eda",
    "wof:name":"Garcia Garcia Tania",
    "wof:placetype":"venue"
},
  "geometry": {"coordinates":[-1.9454729557,37.3928260803],"type":"Point"}
}