{
  "type": "Feature",
  "properties": {
    "iso:country":"ES",
    "sg:address":"Pase Parques (de Los), 4",
    "sg:city":"Alcobendas",
    "sg:orig_category":"Inform\u00c1tica: Consultores",
    "sg:phone":"+34 916 50 72 46",
    "sg:postcode":"28109",
    "sg:province":"Madrid",
    "wof:name":"Astorga Hervas Carlos",
    "wof:placetype":"venue"
},
  "geometry": {"coordinates":[-3.6450707912,40.5105857849],"type":"Point"}
}