{
  "type": "Feature",
  "properties": {
    "addr:full":"Avda Joaquin Piqueras, S/n Montealegre Castillo Albacete 02650",
    "addr:housenumber":"s / n",
    "addr:postcode":"02650",
    "addr:street":"Avda Joaquin Piqueras",
    "iso:country":"ES",
    "sg:address":"Avda Joaquin Piqueras, S/n",
    "sg:city":"Montealegre Castillo",
    "sg:orig_category":"Ense\u00d1anza, Formaci\u00d3n Profesional: Aprendizaje",
    "sg:phone":"+34 967 33 65 05",
    "sg:postcode":"02650",
    "sg:province":"Albacete",
    "wof:name":"Ayuntamiento De Montealegre Del Castillo",
    "wof:placetype":"venue"
},
  "geometry": {"coordinates":[-1.3248440027,38.789768219],"type":"Point"}
}