{
  "type": "Feature",
  "properties": {
    "addr:full":"Plaz Juan Carlos I, 1 Policar Granada 18516",
    "addr:housenumber":"1",
    "addr:postcode":"18516",
    "addr:street":"Plaz Juan Carlos I",
    "iso:country":"ES",
    "sg:address":"Plaz Juan Carlos I, 1",
    "sg:city":"Policar",
    "sg:orig_category":"Administraciones Regionales, Departamentales Y Locales",
    "sg:phone":"+34 958 67 00 57",
    "sg:postcode":"18516",
    "sg:province":"Granada",
    "wof:name":"Ayuntamiento De Policar",
    "wof:placetype":"venue"
},
  "geometry": {"coordinates":[-3.2329969406,37.2576904297],"type":"Point"}
}