{
  "type": "Feature",
  "properties": {
    "addr:full":"Calle de Esteban Saez Alvarado, 17 Burgos Burgos 09007",
    "addr:housenumber":"17",
    "addr:postcode":"09007",
    "addr:street":"Calle De Esteban Saez Alvarado",
    "iso:country":"ES",
    "sg:address":"Calle de Esteban Saez Alvarado, 17",
    "sg:city":"Burgos",
    "sg:orig_category":"Inmobiliaria (agencias)",
    "sg:phone":"+34 947 47 02 76",
    "sg:postcode":"09007",
    "sg:province":"Burgos",
    "wof:name":"Inmolider Burgos Servicios Inmobiliarios S.l.",
    "wof:placetype":"venue"
},
  "geometry": {"coordinates":[-3.664429903,42.3569374084],"type":"Point"}
}