{
  "type": "Feature",
  "properties": {
    "addr:full":"Carrer de Major (sant Celoni), 43 S. Celoni Barcelona 08470",
    "addr:housenumber":"43",
    "addr:postcode":"08470",
    "addr:street":"Carrer De Major Sant Celoni;S. Celoni Barcelona",
    "iso:country":"ES",
    "sg:address":"Carrer de Major (sant Celoni), 43",
    "sg:city":"S. Celoni",
    "sg:orig_category":"Bisuter\u00cda, Joyer\u00cda, Relojer\u00cda (al Por Menor)",
    "sg:phone":"+34 938 67 54 76",
    "sg:postcode":"08470",
    "sg:province":"Barcelona",
    "wof:name":"Joan Pere Joier S.c.p.",
    "wof:placetype":"venue"
},
  "geometry": {"coordinates":[2.4887099266,41.6888389587],"type":"Point"}
}