{
  "type": "Feature",
  "properties": {
    "iso:country":"ES",
    "sg:address":"Calle de Maiquez, 36",
    "sg:city":"Madrid",
    "sg:orig_category":"Molduras, Junquillos, Listones Y Molduras Perforadas",
    "sg:phone":"+34 915 73 69 04",
    "sg:postcode":"28009",
    "sg:province":"Madrid",
    "wof:name":"Menendez Lopez Daniel",
    "wof:placetype":"venue"
},
  "geometry": {"coordinates":[-3.6732308865,40.4188537598],"type":"Point"}
}