{
  "type": "Feature",
  "properties": {
    "addr:full":"Calle de Villaba\u00d1ez, 91 Valladolid Valladolid 47012",
    "addr:housenumber":"91",
    "addr:postcode":"47012",
    "addr:street":"Calle De Villaban\u0303Ez",
    "iso:country":"ES",
    "sg:address":"Calle de Villaba\u00d1ez, 91",
    "sg:city":"Valladolid",
    "sg:orig_category":"Tapicer\u00cdas",
    "sg:phone":"+34 983 20 77 53",
    "sg:postcode":"47012",
    "sg:province":"Valladolid",
    "wof:name":"Jimenez Cuadrado Fernando",
    "wof:placetype":"venue"
},
  "geometry": {"coordinates":[-4.7035779953,41.6476860046],"type":"Point"}
}