{
  "type": "Feature",
  "properties": {
    "addr:full":"Ptge Santa Catalina Sen, S/n Palma Islas Baleares 07002",
    "addr:housenumber":"s",
    "addr:postcode":"07002",
    "addr:street":"Ptge Santa Catalina Sen;/ N",
    "iso:country":"ES",
    "sg:address":"Ptge Santa Catalina Sen, S/n",
    "sg:city":"Palma",
    "sg:orig_category":"Juegos Y Juguetes (al Por Menor)",
    "sg:phone":"+34 971 71 04 33",
    "sg:postcode":"07002",
    "sg:province":"Islas Baleares",
    "wof:name":"Mulet Roca Jaime",
    "wof:placetype":"venue"
},
  "geometry": {"coordinates":[2.65239501,39.5749702454],"type":"Point"}
}