{
  "type": "Feature",
  "properties": {
    "addr:full":"Calle de Ancha, 1 Sanlucar De Barrameda C\u00e1diz 11540",
    "addr:housenumber":"1",
    "addr:postcode":"11540",
    "addr:street":"Calle De Ancha;Ca\u0301Diz",
    "iso:country":"ES",
    "sg:address":"Calle de Ancha, 1",
    "sg:city":"Sanlucar De Barrameda",
    "sg:orig_category":"Ense\u00d1anza, Formaci\u00d3n Profesional: Aprendizaje",
    "sg:phone":"+34 956 38 15 17",
    "sg:postcode":"11540",
    "sg:province":"C\u00e1diz",
    "wof:name":"Junta De Andalucia-consejeria De Cultura",
    "wof:placetype":"venue"
},
  "geometry": {"coordinates":[-6.3538017273,36.7787055969],"type":"Point"}
}