{
  "type": "Feature",
  "properties": {
    "iso:country":"ES",
    "sg:address":"Calle de Seis De Junio, 66",
    "sg:city":"Valdepe\u00f1as",
    "sg:orig_category":"Cl\u00cdnicas Dentales",
    "sg:phone":"+34 926 34 71 96",
    "sg:postcode":"13300",
    "sg:province":"Ciudad Real",
    "wof:name":"Bellon Jimenez Rosalia",
    "wof:placetype":"venue"
},
  "geometry": {"coordinates":[-3.3870270252,38.7630195618],"type":"Point"}
}