{
  "type": "Feature",
  "properties": {
    "addr:full":"Carrer de Mossen Jacint Verdaguer, 1 Premia Mar Barcelona 08330",
    "addr:housenumber":"1",
    "addr:postcode":"08330",
    "addr:street":"Carrer De Mossen Jacint Verdaguer",
    "iso:country":"ES",
    "sg:address":"Carrer de Mossen Jacint Verdaguer, 1",
    "sg:city":"Premia Mar",
    "sg:orig_category":"Perfumer\u00cda (al Por Menor)",
    "sg:phone":"+34 937 51 39 50",
    "sg:postcode":"08330",
    "sg:province":"Barcelona",
    "wof:name":"Parias Cantero Eva",
    "wof:placetype":"venue"
},
  "geometry": {"coordinates":[2.3535859585,41.4915847778],"type":"Point"}
}