{
  "type": "Feature",
  "properties": {
    "iso:country":"ES",
    "sg:address":"Carrer de Aribau, 111",
    "sg:city":"Barcelona",
    "sg:orig_category":"Relojer\u00cda Industrial",
    "sg:phone":"+34 933 23 13 90",
    "sg:postcode":"08036",
    "sg:province":"Barcelona",
    "wof:name":"Jarque Moscardo Javier",
    "wof:placetype":"venue"
},
  "geometry": {"coordinates":[2.1559140682,41.3908042908],"type":"Point"}
}