{
  "type": "Feature",
  "properties": {
    "iso:country":"ES",
    "sg:address":"Carrer de Sant Joan, 5",
    "sg:city":"Esparreguera",
    "sg:orig_category":"Arquitectos",
    "sg:phone":"+34 937 70 99 80",
    "sg:postcode":"08292",
    "sg:province":"Barcelona",
    "wof:name":"Penalva Moreno Cristobal",
    "wof:placetype":"venue"
},
  "geometry": {"coordinates":[1.8710449934,41.5367546082],"type":"Point"}
}