{
  "type": "Feature",
  "properties": {
    "addr:full":"Calle de Torrelaguna, 127 Madrid Madrid 28043",
    "addr:housenumber":"127",
    "addr:postcode":"28043",
    "addr:street":"Calle De Torrelaguna",
    "iso:country":"ES",
    "sg:address":"Calle de Torrelaguna, 127",
    "sg:city":"Madrid",
    "sg:orig_category":"Agencias Y Asesores De Publicidad",
    "sg:phone":"+34 913 00 40 33",
    "sg:postcode":"28043",
    "sg:province":"Madrid",
    "sg:website":"www.arte-facto.com",
    "wof:name":"Artefacto De Ventas S.l.",
    "wof:placetype":"venue"
},
  "geometry": {"coordinates":[-3.6606380939,40.4548683167],"type":"Point"}
}