{
  "type": "Feature",
  "properties": {
    "addr:full":"Calle de Ramon Gomez De La Serna, 161 Madrid Madrid 28035",
    "addr:housenumber":"161",
    "addr:postcode":"28035",
    "addr:street":"Calle De Ramon Gomez De La Serna",
    "iso:country":"ES",
    "sg:address":"Calle de Ramon Gomez De La Serna, 161",
    "sg:city":"Madrid",
    "sg:orig_category":"Psic\u00d3logos",
    "sg:phone":"+34 913 73 65 07",
    "sg:postcode":"28035",
    "sg:province":"Madrid",
    "wof:name":"Garcia-arevalo Dorado Orestes",
    "wof:placetype":"venue"
},
  "geometry": {"coordinates":[-3.7240180969,40.480796814],"type":"Point"}
}