{
  "type": "Feature",
  "properties": {
    "addr:full":"Plaz Republica Dominicana, 8 Madrid Madrid 28016",
    "addr:housenumber":"8",
    "addr:postcode":"madrid;28016",
    "addr:street":"Dominicana",
    "iso:country":"ES",
    "sg:address":"Plaz Republica Dominicana, 8",
    "sg:city":"Madrid",
    "sg:orig_category":"Institutos De Belleza",
    "sg:phone":"+34 913 44 09 11",
    "sg:postcode":"28016",
    "sg:province":"Madrid",
    "wof:name":"Miranda Laso Maria Dolores",
    "wof:placetype":"venue"
},
  "geometry": {"coordinates":[-3.6766707897,40.4583854675],"type":"Point"}
}