{
  "type": "Feature",
  "properties": {
    "addr:full":"Av Roma, 119 Barcelona Barcelona 08011",
    "addr:housenumber":"119",
    "addr:postcode":"08011",
    "addr:street":"Av Roma",
    "iso:country":"ES",
    "sg:address":"Av Roma, 119",
    "sg:city":"Barcelona",
    "sg:orig_category":"Peritos En C\u00c1lculo Inmobiliario, Industrial Y De Fondos De Comercio",
    "sg:phone":"+34 934 52 55 55",
    "sg:postcode":"08011",
    "sg:province":"Barcelona",
    "sg:website":"www.grugesa.com",
    "wof:name":"Grugesa S. A.",
    "wof:placetype":"venue"
},
  "geometry": {"coordinates":[2.1558544636,41.3859024048],"type":"Point"}
}