{
  "type": "Feature",
  "properties": {
    "addr:full":"Calle de Jaen, 3 Bilbao Vizcaya 48012",
    "addr:housenumber":"3",
    "addr:postcode":"48012",
    "addr:street":"Calle De Jaen",
    "iso:country":"ES",
    "sg:address":"Calle de Jaen, 3",
    "sg:city":"Bilbao",
    "sg:orig_category":"Suministros Para Carrocer\u00cdas",
    "sg:phone":"+34 944 43 34 34",
    "sg:postcode":"48012",
    "sg:province":"Vizcaya",
    "wof:name":"Carrocerias Llaguno S.l.",
    "wof:placetype":"venue"
},
  "geometry": {"coordinates":[-2.9438350201,43.253578186],"type":"Point"}
}