{
  "type": "Feature",
  "properties": {
    "addr:full":"Rambleta Pare Alegre, 2 Terrassa Barcelona 08224",
    "addr:postcode":"08224",
    "iso:country":"ES",
    "sg:address":"Rambleta Pare Alegre, 2",
    "sg:city":"Terrassa",
    "sg:orig_category":"Reciclaje, Tratamiento De Tejidos",
    "sg:phone":"+34 937 36 89 80",
    "sg:postcode":"08224",
    "sg:province":"Barcelona",
    "sg:website":"www.hsegura.com",
    "wof:name":"Herederos De Salvador Segura S. A.",
    "wof:placetype":"venue"
},
  "geometry": {"coordinates":[1.9900530577,41.5446243286],"type":"Point"}
}