{
  "type": "Feature",
  "properties": {
    "addr:full":"Calle de Barrenkalea, 30 Durango Vizcaya 48200",
    "addr:housenumber":"30",
    "addr:postcode":"48200",
    "addr:street":"Calle De Barrenkalea",
    "iso:country":"ES",
    "sg:address":"Calle de Barrenkalea, 30",
    "sg:city":"Durango",
    "sg:orig_category":"Asesor\u00cda Sobre Comunicaci\u00d3n De Empresas",
    "sg:phone":"+34 946 21 78 90",
    "sg:postcode":"48200",
    "sg:province":"Vizcaya",
    "wof:name":"Asesoria Sagastizabal S.l.",
    "wof:placetype":"venue"
},
  "geometry": {"coordinates":[-2.6323137283,43.166809082],"type":"Point"}
}