{
  "type": "Feature",
  "properties": {
    "addr:full":"Carrer de Guardiola, 60 Calvet Barcelona 08253",
    "addr:housenumber":"60",
    "addr:postcode":"08253",
    "addr:street":"Carrer De Guardiola",
    "iso:country":"ES",
    "sg:address":"Carrer de Guardiola, 60",
    "sg:city":"Calvet",
    "sg:orig_category":"Desinfecci\u00d3n, Desinsectaci\u00d3n, Desratizaci\u00d3n",
    "sg:phone":"+34 938 35 80 13",
    "sg:postcode":"08253",
    "sg:province":"Barcelona",
    "wof:name":"Riera Melgosa Pedro",
    "wof:placetype":"venue"
},
  "geometry": {"coordinates":[1.7838430405,41.6824073792],"type":"Point"}
}