{
  "type": "Feature",
  "properties": {
    "iso:country":"ES",
    "sg:address":"Calle de Taberna, 5",
    "sg:city":"Rubielos Mora",
    "sg:orig_category":"Reposter\u00cdas",
    "sg:phone":"+34 978 80 40 37",
    "sg:postcode":"44415",
    "sg:province":"Teruel",
    "wof:name":"Horno De Rubielos S.l.",
    "wof:placetype":"venue"
},
  "geometry": {"coordinates":[-0.6515859962,40.1907081604],"type":"Point"}
}