{
  "type": "Feature",
  "properties": {
    "iso:country":"ES",
    "sg:address":"Montsec (urb Can Quisero), S/n",
    "sg:city":"Masquefa",
    "sg:orig_category":"Quincaller\u00cda (al Por Menor)",
    "sg:phone":"+34 937 72 51 60",
    "sg:postcode":"08783",
    "sg:province":"Barcelona",
    "wof:name":"Diaz Diaz Andrea",
    "wof:placetype":"venue"
},
  "geometry": {"coordinates":[1.7968449593,41.4790992737],"type":"Point"}
}