{
  "type": "Feature",
  "properties": {
    "iso:country":"ES",
    "sg:address":"Plaz Mar (del), 1",
    "sg:city":"Palmones",
    "sg:orig_category":"Molduras, Junquillos, Listones Y Molduras Perforadas",
    "sg:phone":"+34 956 67 52 49",
    "sg:postcode":"11379",
    "sg:province":"C\u00e1diz",
    "wof:name":"Mateo Benitez Salvador",
    "wof:placetype":"venue"
},
  "geometry": {"coordinates":[-5.4428992271,36.1843261719],"type":"Point"}
}