{
  "type": "Feature",
  "properties": {
    "addr:full":"Calle de Eraso, 6 Madrid Madrid 28028",
    "addr:housenumber":"6",
    "addr:postcode":"28028",
    "addr:street":"Calle De Eraso",
    "iso:country":"ES",
    "sg:address":"Calle de Eraso, 6",
    "sg:city":"Madrid",
    "sg:orig_category":"Electricidad: Equipos Industriales, Componentes (fabricaci\u00d3n)",
    "sg:phone":"+34 917 24 28 00",
    "sg:postcode":"28028",
    "sg:province":"Madrid",
    "sg:website":"www.sadepra.com",
    "wof:name":"Sadepra S.a.",
    "wof:placetype":"venue"
},
  "geometry": {"coordinates":[-3.6719129086,40.4335708618],"type":"Point"}
}