{
  "type": "Feature",
  "properties": {
    "iso:country":"ES",
    "sg:address":"Calle de Aragon, 5",
    "sg:city":"Utrillas",
    "sg:orig_category":"Florister\u00cdas",
    "sg:phone":"+34 978 75 81 14",
    "sg:postcode":"44760",
    "sg:province":"Teruel",
    "wof:name":"Elena Hijazo Muniesa Y Maria Jesus Abad Bellido Cdad",
    "wof:placetype":"venue"
},
  "geometry": {"coordinates":[-0.8474975228,40.8128166199],"type":"Point"}
}