{
  "type": "Feature",
  "properties": {
    "iso:country":"ES",
    "sg:address":"Barranco Hondo De Arriba, S/n",
    "sg:city":"Caideros",
    "sg:orig_category":"Asociaciones Ecologistas",
    "sg:phone":"+34 928 55 51 72",
    "sg:postcode":"35468",
    "sg:province":"Las Palmas",
    "wof:name":"Comunidad De Regantes Del Norte De Gran Canaria",
    "wof:placetype":"venue"
},
  "geometry": {"coordinates":[-15.6560087204,28.1299304962],"type":"Point"}
}