{
  "type": "Feature",
  "properties": {
    "iso:country":"ES",
    "sg:address":"Muel Pesquero, S/n",
    "sg:city":"Marin",
    "sg:orig_category":"Navegaci\u00d3n (equipos Fluviales)",
    "sg:phone":"+34 986 88 32 84",
    "sg:postcode":"36900",
    "sg:province":"Pontevedra",
    "wof:name":"Pesquera Estevez Lino S. A.",
    "wof:placetype":"venue"
},
  "geometry": {"coordinates":[-8.6881885529,42.391746521],"type":"Point"}
}