{
  "type": "Feature",
  "properties": {
    "addr:full":"Prol Arroyo Blanquillo, S/n Alhaurin Torre M\u00e1laga 29130",
    "addr:housenumber":"s",
    "addr:postcode":"29130",
    "addr:street":"Prol Arroyo Blanquillo;/ N Alhaurin Torre Ma\u0301Laga",
    "iso:country":"ES",
    "sg:address":"Prol Arroyo Blanquillo, S/n",
    "sg:city":"Alhaurin Torre",
    "sg:orig_category":"Asilos De Ancianos. Centros Privados",
    "sg:phone":"+34 952 41 38 38",
    "sg:postcode":"29130",
    "sg:province":"M\u00e1laga",
    "wof:name":"Residencia De Ancianos La Esperanza",
    "wof:placetype":"venue"
},
  "geometry": {"coordinates":[-4.5661988258,36.6517448425],"type":"Point"}
}