{
  "type": "Feature",
  "properties": {
    "iso:country":"ES",
    "sg:address":"Calle de Carretera, 16",
    "sg:city":"Cerro Muriano",
    "sg:orig_category":"Artesan\u00cda",
    "sg:phone":"+34 957 35 08 28",
    "sg:postcode":"14350",
    "sg:province":"C\u00f3rdoba",
    "wof:name":"Obrero Castro Jose Angel",
    "wof:placetype":"venue"
},
  "geometry": {"coordinates":[-4.7729697227,38.0026054382],"type":"Point"}
}