{
  "type": "Feature",
  "properties": {
    "iso:country":"ES",
    "sg:address":"Calle de Zuloaga Ignacio Pintor, 3",
    "sg:city":"Bilbao",
    "sg:orig_category":"Metales (labores, Pulido)",
    "sg:phone":"+34 944 47 05 00",
    "sg:postcode":"48014",
    "sg:province":"Vizcaya",
    "wof:name":"Estampaciones Y Caldereria S.a.l.",
    "wof:placetype":"venue"
},
  "geometry": {"coordinates":[-2.963572979,43.2713928223],"type":"Point"}
}