{
  "type": "Feature",
  "properties": {
    "iso:country":"ES",
    "sg:address":"Carrer de Esglesia, 22",
    "sg:city":"Vallgorguina",
    "sg:orig_category":"Cerrajer\u00cda, Ferrallista",
    "sg:phone":"+34 938 67 93 13",
    "sg:postcode":"08470",
    "sg:province":"Barcelona",
    "wof:name":"Tallers De Serralleria Vallgorguina S.c.p.",
    "wof:placetype":"venue"
},
  "geometry": {"coordinates":[2.489289999,41.6902389526],"type":"Point"}
}