{
  "type": "Feature",
  "properties": {
    "addr:full":"Calle de Manuel De Falla, 9 Motril Granada 18600",
    "addr:housenumber":"9",
    "addr:postcode":"18600",
    "addr:street":"Calle De Manuel De Falla",
    "iso:country":"ES",
    "sg:address":"Calle de Manuel De Falla, 9",
    "sg:city":"Motril",
    "sg:classifiers":[
        {
            "category":"Personal",
            "subcategory":"Barber",
            "type":"Services"
        }
    ],
    "sg:phone":"+34 958 82 13 62",
    "sg:postcode":"18600",
    "sg:province":"Granada",
    "sg:tags":[
        "caballeros",
        "de",
        "peluqueros"
    ],
    "wof:name":"Medina Lopez Antonio",
    "wof:placetype":"venue"
},
  "geometry": {"coordinates":[-3.5133941174,36.7454032898],"type":"Point"}
}