{
  "type": "Feature",
  "properties": {
    "iso:country":"ES",
    "sg:address":"Calle de Zurbano, 95",
    "sg:city":"Madrid",
    "sg:orig_category":"Cervecer\u00cdas",
    "sg:phone":"+34 915 34 64 79",
    "sg:postcode":"28003",
    "sg:province":"Madrid",
    "wof:name":"Kon-tiki S. A.",
    "wof:placetype":"venue"
},
  "geometry": {"coordinates":[-3.6928160191,40.4408378601],"type":"Point"}
}