{
  "type": "Feature",
  "properties": {
    "iso:country":"ES",
    "sg:address":"Arteaga Auzoa, 130",
    "sg:city":"Arteaga",
    "sg:orig_category":"Productos Qu\u00cdmicos (fabricaci\u00d3n, Al Por Mayor)",
    "sg:phone":"+34 944 52 50 50",
    "sg:postcode":"48170",
    "sg:province":"Vizcaya",
    "wof:name":"Fmc Foret",
    "wof:placetype":"venue"
},
  "geometry": {"coordinates":[-2.8657829762,43.2841300964],"type":"Point"}
}