{
  "type": "Feature",
  "properties": {
    "iso:country":"ES",
    "sg:address":"Calle de Iglesia (la), 5",
    "sg:city":"Villaverde De Iscar",
    "sg:orig_category":"Transportes Por V\u00cdas Navegables",
    "sg:phone":"+34 921 16 70 18",
    "sg:postcode":"40219",
    "sg:province":"Segovia",
    "wof:name":"Ca\u00f1o Garcia Tomas Del",
    "wof:placetype":"venue"
},
  "geometry": {"coordinates":[-4.5260472298,41.3079109192],"type":"Point"}
}