{
  "type": "Feature",
  "properties": {
    "addr:full":"Calle de Condor, 22 Valdelagua Salamanca 37900",
    "addr:housenumber":"22",
    "addr:postcode":"37900",
    "addr:street":"Calle De Condor",
    "iso:country":"ES",
    "sg:address":"Calle de Condor, 22",
    "sg:city":"Valdelagua",
    "sg:orig_category":"Agentes Generales De Seguros",
    "sg:phone":"+34 923 13 95 38",
    "sg:postcode":"37900",
    "sg:province":"Salamanca",
    "wof:name":"Gonzalez-orus Marcos Martin Jose",
    "wof:placetype":"venue"
},
  "geometry": {"coordinates":[-5.6175775528,40.9398765564],"type":"Point"}
}