{
  "type": "Feature",
  "properties": {
    "iso:country":"ES",
    "sg:address":"Praj Vinculo Alto, S/n",
    "sg:city":"Roquetas Mar",
    "sg:orig_category":"Promotores Constructores",
    "sg:phone":"+34 950 32 09 34",
    "sg:postcode":"04740",
    "sg:province":"Almer\u00eda",
    "wof:name":"Baeza Grancha Tomas",
    "wof:placetype":"venue"
},
  "geometry": {"coordinates":[-2.6124989986,36.7638435364],"type":"Point"}
}