{
  "type": "Feature",
  "properties": {
    "addr:full":"A Ri\u00f1a, 112 Oia Pontevedra 36794",
    "addr:housenumber":"112",
    "addr:postcode":"36794",
    "iso:country":"ES",
    "sg:address":"A Ri\u00f1a, 112",
    "sg:city":"Oia",
    "sg:orig_category":"Doctores En Medicina",
    "sg:phone":"+34 986 36 23 02",
    "sg:postcode":"36794",
    "sg:province":"Pontevedra",
    "wof:name":"Vallejo Polanco Jose Antonio",
    "wof:placetype":"venue"
},
  "geometry": {"coordinates":[-8.8784294128,42.0079994202],"type":"Point"}
}