{
  "type": "Feature",
  "properties": {
    "addr:full":"Cmno Purchil (de), 2 Granada Granada 18004",
    "addr:housenumber":"2",
    "addr:postcode":"18004",
    "addr:street":"Cmno Purchil De",
    "iso:country":"ES",
    "sg:address":"Cmno Purchil (de), 2",
    "sg:city":"Granada",
    "sg:orig_category":"Comercio De Piezas De Recambio Y De Accesorios De Veh\u00cdculos, Veh\u00cdculos Industriales",
    "sg:phone":"+34 958 52 16 66",
    "sg:postcode":"18004",
    "sg:province":"Granada",
    "wof:name":"Auto Recambios Granada S.l.",
    "wof:placetype":"venue"
},
  "geometry": {"coordinates":[-3.6083416939,37.1735115051],"type":"Point"}
}