{
  "type": "Feature",
  "properties": {
    "addr:full":"C/ Raval Del Carme, 40 Tarrega Lleida 25300",
    "addr:housenumber":"40",
    "addr:postcode":"25300",
    "addr:street":"C / Raval Del Carme",
    "iso:country":"ES",
    "sg:address":"C/ Raval Del Carme, 40",
    "sg:city":"Tarrega",
    "sg:orig_category":"Fabricaci\u00d3n De Distribuidores Autom\u00c1ticos",
    "sg:phone":"+34 973 50 06 98",
    "sg:postcode":"25300",
    "sg:province":"Lleida",
    "wof:name":"Albareda Sole Pedro",
    "wof:placetype":"venue"
},
  "geometry": {"coordinates":[1.141317606,41.6487159729],"type":"Point"}
}