{
  "type": "Feature",
  "properties": {
    "addr:full":"Calle de Castillo De Constantina, 8 Alcala Guadaira Sevilla 41500",
    "addr:housenumber":"8",
    "addr:postcode":"41500",
    "addr:street":"Calle De Castillo",
    "iso:country":"ES",
    "sg:address":"Calle de Castillo De Constantina, 8",
    "sg:city":"Alcala Guadaira",
    "sg:orig_category":"Contenedores (mercanc\u00cdas)",
    "sg:phone":"+34 955 68 52 42",
    "sg:postcode":"41500",
    "sg:province":"Sevilla",
    "wof:name":"Alanis Sanchez Manuel",
    "wof:placetype":"venue"
},
  "geometry": {"coordinates":[-5.8511457443,37.3403816223],"type":"Point"}
}