{
  "type": "Feature",
  "properties": {
    "addr:full":"Avda Golf (el), S/n Costa Teguise Las Palmas 35509",
    "addr:housenumber":"s / n",
    "addr:postcode":"35509",
    "iso:country":"ES",
    "sg:address":"Avda Golf (el), S/n",
    "sg:city":"Costa Teguise",
    "sg:orig_category":"Distribuci\u00d3n De Petr\u00d3leo Y Derivados",
    "sg:phone":"+34 928 82 60 99",
    "sg:postcode":"35509",
    "sg:province":"Las Palmas",
    "wof:name":"Hijos De Rafael Ramirez C.b.",
    "wof:placetype":"venue"
},
  "geometry": {"coordinates":[-13.4999437332,28.997089386],"type":"Point"}
}