{
  "type": "Feature",
  "properties": {
    "iso:country":"ES",
    "sg:address":"Calle de Juan De Urbieta, 40",
    "sg:city":"Madrid",
    "sg:orig_category":"Lencer\u00cda Femenina, Corseter\u00cda, Trajes De Ba\u00d1o (al Por Menor)",
    "sg:phone":"+34 915 01 82 06",
    "sg:postcode":"28007",
    "sg:province":"Madrid",
    "wof:name":"Lenceria Chalsa S.l.",
    "wof:placetype":"venue"
},
  "geometry": {"coordinates":[-3.675714016,40.4064369202],"type":"Point"}
}