{
  "type": "Feature",
  "properties": {
    "iso:country":"ES",
    "sg:address":"Calle de Mateo Errota, 11",
    "sg:city":"Donostia-san Sebastian",
    "sg:orig_category":"Artes Gr\u00c1ficas, Artes Pl\u00c1sticas: Material Y Suministros (al Por Menor)",
    "sg:phone":"+34 943 47 43 18",
    "sg:postcode":"20014",
    "sg:province":"Guip\u00f9zcoa",
    "sg:website":"www.litoandalus.com",
    "wof:name":"Litoandalus S.l.",
    "wof:placetype":"venue"
},
  "geometry": {"coordinates":[-1.9440640211,43.3023109436],"type":"Point"}
}