{
  "type": "Feature",
  "properties": {
    "addr:full":"Calle de Iturriza, 19 Bilbao Vizcaya 48003",
    "addr:housenumber":"19",
    "addr:postcode":"48003",
    "addr:street":"Calle De Iturriza",
    "iso:country":"ES",
    "sg:address":"Calle de Iturriza, 19",
    "sg:city":"Bilbao",
    "sg:orig_category":"Molduras, Junquillos, Listones Y Molduras Perforadas",
    "sg:phone":"+34 944 21 70 40",
    "sg:postcode":"48003",
    "sg:province":"Vizcaya",
    "wof:name":"Sobrado Varela Candido",
    "wof:placetype":"venue"
},
  "geometry": {"coordinates":[-2.9328289032,43.2571182251],"type":"Point"}
}