{
  "type": "Feature",
  "properties": {
    "addr:full":"Carrer de Esglesia (de L'), S/n Aldea Tarragona 43896",
    "addr:postcode":"43896",
    "addr:street":"Carrer De Esglesia De L ' S / N",
    "iso:country":"ES",
    "sg:address":"Carrer de Esglesia (de L'), S/n",
    "sg:city":"Aldea",
    "sg:orig_category":"Electricidad: Instaladores",
    "sg:phone":"+34 977 45 03 03",
    "sg:postcode":"43896",
    "sg:province":"Tarragona",
    "wof:name":"Lopez Najar Miguel",
    "wof:placetype":"venue"
},
  "geometry": {"coordinates":[0.6240699887,40.7481994629],"type":"Point"}
}