{
  "type": "Feature",
  "properties": {
    "addr:full":"Carrer de Burgos, S/n Amposta Tarragona 43870",
    "addr:housenumber":"s / n",
    "addr:postcode":"43870",
    "addr:street":"Carrer De Burgos",
    "iso:country":"ES",
    "sg:address":"Carrer de Burgos, S/n",
    "sg:city":"Amposta",
    "sg:orig_category":"Promotores Constructores",
    "sg:phone":"+34 977 70 39 65",
    "sg:postcode":"43870",
    "sg:province":"Tarragona",
    "wof:name":"Liteco S.l",
    "wof:placetype":"venue"
},
  "geometry": {"coordinates":[0.5808150172,40.7051734924],"type":"Point"}
}