{
  "type": "Feature",
  "properties": {
    "addr:full":"Rua Quintan, S/n Cambre La Coru\u00f1a 15660",
    "addr:housenumber":"s",
    "addr:postcode":"15660",
    "addr:street":"Rua Quintan;/ N;La Corun\u0303A",
    "iso:country":"ES",
    "sg:address":"Rua Quintan, S/n",
    "sg:city":"Cambre",
    "sg:orig_category":"Distribuci\u00d3n De Petr\u00d3leo Y Derivados",
    "sg:phone":"+34 981 67 55 37",
    "sg:postcode":"15660",
    "sg:province":"La Coru\u00f1a",
    "wof:name":"E.s.cecebre S.l.",
    "wof:placetype":"venue"
},
  "geometry": {"coordinates":[-8.3105812073,43.2944793701],"type":"Point"}
}