{
  "type": "Feature",
  "properties": {
    "iso:country":"ES",
    "sg:address":"Av Estacio, 22",
    "sg:city":"Pobla Segur",
    "sg:orig_category":"Carnicer\u00cdas, Carnicer\u00cdas",
    "sg:phone":"+34 973 68 04 84",
    "sg:postcode":"25500",
    "sg:province":"Lleida",
    "wof:name":"Supermercats Borrell Vila S.l.",
    "wof:placetype":"venue"
},
  "geometry": {"coordinates":[0.9653620124,42.2433319092],"type":"Point"}
}