{
  "type": "Feature",
  "properties": {
    "addr:full":"Pase Fernandez Vallejo, 315 Torrelavega Cantabria 39300",
    "addr:housenumber":"315",
    "addr:postcode":"39300",
    "addr:street":"Fernandez Vallejo",
    "iso:country":"ES",
    "sg:address":"Pase Fernandez Vallejo, 315",
    "sg:city":"Torrelavega",
    "sg:orig_category":"Delegados, Agentes De Tr\u00c1nsito, Auxiliares De Transporte Internacional",
    "sg:phone":"+34 942 80 16 93",
    "sg:postcode":"39300",
    "sg:province":"Cantabria",
    "wof:name":"Hergupe S.l.",
    "wof:placetype":"venue"
},
  "geometry": {"coordinates":[-4.0440292358,43.3278999329],"type":"Point"}
}