{
  "type": "Feature",
  "properties": {
    "addr:full":"Calle de Sola, 2 Ciudad Quesada Alicante 03170",
    "addr:housenumber":"2",
    "addr:postcode":"03170",
    "addr:street":"Calle De Sola",
    "iso:country":"ES",
    "sg:address":"Calle de Sola, 2",
    "sg:city":"Ciudad Quesada",
    "sg:orig_category":"Bazares, Art\u00cdculos De Limpieza Y De Cocina (al Por Menor)",
    "sg:phone":"+34 966 71 66 57",
    "sg:postcode":"03170",
    "sg:province":"Alicante",
    "wof:name":"La Marina-fashion Beach S.l.u.",
    "wof:placetype":"venue"
},
  "geometry": {"coordinates":[-0.726319015,38.0638084412],"type":"Point"}
}