{
  "type": "Feature",
  "properties": {
    "iso:country":"ES",
    "sg:address":"Avda Villamayor, 22",
    "sg:city":"Salamanca",
    "sg:orig_category":"Reposter\u00cdas",
    "sg:phone":"+34 923 26 22 25",
    "sg:postcode":"37007",
    "sg:province":"Salamanca",
    "wof:name":"Gonzalez Sanchez Francisco",
    "wof:placetype":"venue"
},
  "geometry": {"coordinates":[-5.6689791679,40.96900177],"type":"Point"}
}