{
  "type": "Feature",
  "properties": {
    "iso:country":"ES",
    "sg:address":"Calle de Primo De Rivera, S/n",
    "sg:city":"Pravia",
    "sg:orig_category":"Clubes Y Asociaciones Deportivas Y De Actividades Invernales Y De Monta\u00d1a",
    "sg:phone":"+34 985 82 20 01",
    "sg:postcode":"33120",
    "sg:province":"Asturias",
    "wof:name":"Escuderia Pravia Autocompeticion",
    "wof:placetype":"venue"
},
  "geometry": {"coordinates":[-6.1154088974,43.4901809692],"type":"Point"}
}