{
  "type": "Feature",
  "properties": {
    "addr:full":"Calle de Herrero, 18 Castellon Castell\u00f3n 12002",
    "addr:housenumber":"18",
    "addr:postcode":"12002",
    "addr:street":"Calle De Herrero",
    "iso:country":"ES",
    "sg:address":"Calle de Herrero, 18",
    "sg:city":"Castellon",
    "sg:orig_category":"Laboratorios Farmac\u00c9uticos",
    "sg:phone":"+34 964 22 93 89",
    "sg:postcode":"12002",
    "sg:province":"Castell\u00f3n",
    "wof:name":"Bagan Sanz Maria Jesus",
    "wof:placetype":"venue"
},
  "geometry": {"coordinates":[-0.0393129997,39.982006073],"type":"Point"}
}