{
  "type": "Feature",
  "properties": {
    "addr:full":"Plaz Mayor, 9 Alca\u00f1ices Zamora 49500",
    "addr:housenumber":"9",
    "addr:postcode":"49500",
    "addr:street":"Plaz Mayor;Zamora",
    "iso:country":"ES",
    "sg:address":"Plaz Mayor, 9",
    "sg:city":"Alca\u00f1ices",
    "sg:orig_category":"Peluqueros: De Se\u00d1oras",
    "sg:phone":"+34 980 68 02 09",
    "sg:postcode":"49500",
    "sg:province":"Zamora",
    "wof:name":"Bermudez Perez Francisca",
    "wof:placetype":"venue"
},
  "geometry": {"coordinates":[-6.3475852013,41.6988945007],"type":"Point"}
}