{
  "type": "Feature",
  "properties": {
    "iso:country":"ES",
    "sg:address":"Calle de Cartagena, 122",
    "sg:city":"Madrid",
    "sg:orig_category":"Bazares, Art\u00cdculos De Limpieza Y De Cocina (al Por Menor)",
    "sg:phone":"+34 914 16 75 89",
    "sg:postcode":"28002",
    "sg:province":"Madrid",
    "wof:name":"Jiang  Suping",
    "wof:placetype":"venue"
},
  "geometry": {"coordinates":[-3.6746313572,40.44090271],"type":"Point"}
}