{
  "type": "Feature",
  "properties": {
    "addr:full":"Plaz Espa\u00d1a, S/n Marcilla Navarra 31340",
    "addr:housenumber":"s / n",
    "addr:postcode":"31340",
    "addr:street":"Plaz Espan\u0303A;Navarra",
    "iso:country":"ES",
    "sg:address":"Plaz Espa\u00d1a, S/n",
    "sg:city":"Marcilla",
    "sg:orig_category":"Molduras, Junquillos, Listones Y Molduras Perforadas",
    "sg:phone":"+34 948 75 70 85",
    "sg:postcode":"31340",
    "sg:province":"Navarra",
    "wof:name":"Ruiz Caballero Blanca",
    "wof:placetype":"venue"
},
  "geometry": {"coordinates":[-1.7389639616,42.3262138367],"type":"Point"}
}