{
  "type": "Feature",
  "properties": {
    "addr:full":"Plaz Huerta Grande, S/n Sanlucar De Barrameda C\u00e1diz 11540",
    "addr:housenumber":"s / n",
    "addr:postcode":"11540",
    "addr:street":"Ca\u0301Diz",
    "iso:country":"ES",
    "sg:address":"Plaz Huerta Grande, S/n",
    "sg:city":"Sanlucar De Barrameda",
    "sg:orig_category":"Internados & Ense\u00d1anza Privada",
    "sg:phone":"+34 956 36 02 02",
    "sg:postcode":"11540",
    "sg:province":"C\u00e1diz",
    "wof:name":"Proyecto Educativo Jeyma S.a.",
    "wof:placetype":"venue"
},
  "geometry": {"coordinates":[-6.3576931953,36.7758522034],"type":"Point"}
}