{
  "type": "Feature",
  "properties": {
    "addr:full":"Carrer de Sant Marcel, 7 Falset Tarragona 43730",
    "addr:housenumber":"7",
    "addr:postcode":"43730",
    "addr:street":"Carrer De Sant Marcel",
    "iso:country":"ES",
    "sg:address":"Carrer de Sant Marcel, 7",
    "sg:city":"Falset",
    "sg:orig_category":"Inform\u00c1tica, Ofim\u00c1tica (estudios, Asesor\u00cda, Ingenier\u00cda, Formaci\u00d3n)",
    "sg:phone":"+34 977 83 10 16",
    "sg:postcode":"43730",
    "sg:province":"Tarragona",
    "wof:name":"Centre D'iniciatives Ocupacionals Del Priorat S.c.p.",
    "wof:placetype":"venue"
},
  "geometry": {"coordinates":[0.8208730221,41.1439476013],"type":"Point"}
}