{
  "type": "Feature",
  "properties": {
    "iso:country":"ES",
    "sg:address":"Plaz Espa\u00d1a, 2",
    "sg:city":"Turegano",
    "sg:orig_category":"Venta, Instalaci\u00d3n De Cocinas",
    "sg:phone":"+34 921 50 00 26",
    "sg:postcode":"40370",
    "sg:province":"Segovia",
    "wof:name":"Hnos Martin Gonzalez C.b.",
    "wof:placetype":"venue"
},
  "geometry": {"coordinates":[-4.0066370964,41.1536178589],"type":"Point"}
}