{
  "type": "Feature",
  "properties": {
    "iso:country":"ES",
    "sg:address":"Calle de Juan De Ribera, 33",
    "sg:city":"Ibi",
    "sg:orig_category":"Serigraf\u00cda (material Y Suministros)",
    "sg:phone":"+34 965 55 41 46",
    "sg:postcode":"03440",
    "sg:province":"Alicante",
    "wof:name":"Impresiones S.c.",
    "wof:placetype":"venue"
},
  "geometry": {"coordinates":[-0.5701990128,38.6322898865],"type":"Point"}
}