{
  "type": "Feature",
  "properties": {
    "iso:country":"ES",
    "sg:address":"Calle de Jose Antonio, 2",
    "sg:city":"Barrientos",
    "sg:orig_category":"Cooperativas Agr\u00cdcolas",
    "sg:phone":"+34 987 60 55 52",
    "sg:postcode":"24394",
    "sg:province":"Le\u00f3n",
    "wof:name":"Sociedad Cooperativa Textil",
    "wof:placetype":"venue"
},
  "geometry": {"coordinates":[-5.9707942009,42.4101066589],"type":"Point"}
}