{
  "type": "Feature",
  "properties": {
    "iso:country":"ES",
    "sg:address":"Cra Nal Trescientas Treinta Y Una, S/n",
    "sg:city":"Antequera",
    "sg:orig_category":"Fabricaci\u00d3n De Material Y Sistemas De Se\u00d1alizaci\u00d3n De Carreteras, Urbanos Y De Obras",
    "sg:phone":"+34 952 70 48 69",
    "sg:postcode":"29200",
    "sg:province":"M\u00e1laga",
    "wof:name":"Andaluza De Se\u00f1alizaciones S. A.",
    "wof:placetype":"venue"
},
  "geometry": {"coordinates":[-4.5211935043,36.9971008301],"type":"Point"}
}