{
  "type": "Feature",
  "properties": {
    "iso:country":"ES",
    "sg:address":"Carrer de Castillejos, 230",
    "sg:city":"Barcelona",
    "sg:orig_category":"Promotores Constructores",
    "sg:phone":"+34 932 31 35 89",
    "sg:postcode":"08013",
    "sg:province":"Barcelona",
    "wof:name":"Serogar S. A.",
    "wof:placetype":"venue"
},
  "geometry": {"coordinates":[2.1806280613,41.4049263],"type":"Point"}
}