{
  "type": "Feature",
  "properties": {
    "addr:full":"Carrer de Sant Felip Neri, 10 Palma Islas Baleares 07002",
    "addr:housenumber":"10",
    "addr:postcode":"07002",
    "addr:street":"Carrer De Sant Felip Neri",
    "iso:country":"ES",
    "sg:address":"Carrer de Sant Felip Neri, 10",
    "sg:city":"Palma",
    "sg:orig_category":"Ropa Y Art\u00cdculos Pre",
    "sg:phone":"+34 971 42 55 20",
    "sg:postcode":"07002",
    "sg:province":"Islas Baleares",
    "wof:name":"Valcris C.b",
    "wof:placetype":"venue"
},
  "geometry": {"coordinates":[2.6539199352,39.5732727051],"type":"Point"}
}