{
  "type": "Feature",
  "properties": {
    "addr:full":"Calle de Antonio Lasso, 17 Estacion Madrid 28250",
    "addr:housenumber":"17 estacion",
    "addr:postcode":"28250",
    "addr:street":"Calle De Antonio Lasso",
    "iso:country":"ES",
    "sg:address":"Calle de Antonio Lasso, 17",
    "sg:city":"Estacion",
    "sg:orig_category":"Limpieza Industrial",
    "sg:phone":"+34 918 54 90 41",
    "sg:postcode":"28250",
    "sg:province":"Madrid",
    "wof:name":"Chopard Castalia S.l.",
    "wof:placetype":"venue"
},
  "geometry": {"coordinates":[-3.7003455162,40.4166908264],"type":"Point"}
}