{
  "type": "Feature",
  "properties": {
    "iso:country":"ES",
    "sg:address":"Carrer de Arimon, 16",
    "sg:city":"Barcelona",
    "sg:orig_category":"Peleter\u00cdas",
    "sg:phone":"+34 932 11 89 99",
    "sg:postcode":"08022",
    "sg:province":"Barcelona",
    "wof:name":"Acosta Aznar Isabel Maria",
    "wof:placetype":"venue"
},
  "geometry": {"coordinates":[2.1371827126,41.4046401978],"type":"Point"}
}