{
  "type": "Feature",
  "properties": {
    "addr:full":"Avda Maisonnave, 43 Alacant Alicante 03003",
    "addr:housenumber":"43",
    "addr:postcode":"03003",
    "addr:street":"Avda Maisonnave",
    "iso:country":"ES",
    "sg:address":"Avda Maisonnave, 43",
    "sg:city":"Alacant",
    "sg:orig_category":"Cajas De Ahorro",
    "sg:phone":"+34 965 92 91 44",
    "sg:postcode":"03003",
    "sg:province":"Alicante",
    "wof:name":"Caja De Ahorros De Murcia",
    "wof:placetype":"venue"
},
  "geometry": {"coordinates":[-0.4923459888,38.3432846069],"type":"Point"}
}