{
  "type": "Feature",
  "properties": {
    "addr:full":"Calle de Florencio Llorente, 8 Madrid Madrid 28027",
    "addr:housenumber":"8",
    "addr:postcode":"madrid;28027",
    "addr:street":"Calle De Florencio Llorente",
    "iso:country":"ES",
    "sg:address":"Calle de Florencio Llorente, 8",
    "sg:city":"Madrid",
    "sg:orig_category":"Cine (producci\u00d3n, Realizaci\u00d3n)",
    "sg:phone":"+34 914 04 07 77",
    "sg:postcode":"28027",
    "sg:province":"Madrid",
    "wof:name":"Laya Producciones S.l.",
    "wof:placetype":"venue"
},
  "geometry": {"coordinates":[-3.6522450447,40.4334373474],"type":"Point"}
}