{
  "type": "Feature",
  "properties": {
    "iso:country":"ES",
    "sg:address":"Calle de Magallanes, 44",
    "sg:city":"Madrid",
    "sg:orig_category":"Imprenta",
    "sg:phone":"+34 914 46 97 13",
    "sg:postcode":"28015",
    "sg:province":"Madrid",
    "wof:name":"Reprografias Magallanes 44 S.l.",
    "wof:placetype":"venue"
},
  "geometry": {"coordinates":[-3.7054970264,40.436252594],"type":"Point"}
}