{
  "type": "Feature",
  "properties": {
    "iso:country":"ES",
    "sg:address":"Calle de Barraca La, 15",
    "sg:city":"Nava",
    "sg:orig_category":"Marroquiner\u00cda (confecci\u00d3n)",
    "sg:phone":"+34 985 71 80 34",
    "sg:postcode":"33529",
    "sg:province":"Asturias",
    "wof:name":"Corte Sanchez Benigno",
    "wof:placetype":"venue"
},
  "geometry": {"coordinates":[-5.5090918541,43.3606300354],"type":"Point"}
}