{
  "type": "Feature",
  "properties": {
    "iso:country":"ES",
    "sg:address":"Calle de Armando Palacio Valdes, 3",
    "sg:city":"Candas",
    "sg:orig_category":"Mercer\u00cda, Lencer\u00cda (al Por Menor)",
    "sg:phone":"+34 985 87 06 43",
    "sg:postcode":"33430",
    "sg:province":"Asturias",
    "wof:name":"Varela Varela Maria Del Carmen",
    "wof:placetype":"venue"
},
  "geometry": {"coordinates":[-5.767619133,43.5897827148],"type":"Point"}
}