{
  "type": "Feature",
  "properties": {
    "iso:country":"ES",
    "sg:address":"Pla\u00c7 Major, 8",
    "sg:city":"Sant Joan Les Fonts",
    "sg:orig_category":"Ense\u00d1anza: Profesiones Art\u00cdsticas",
    "sg:phone":"+34 972 29 01 78",
    "sg:postcode":"17857",
    "sg:province":"Girona",
    "wof:name":"Brunso Fageda Francisco Javier",
    "wof:placetype":"venue"
},
  "geometry": {"coordinates":[2.5107150078,42.2121162415],"type":"Point"}
}