{
  "type": "Feature",
  "properties": {
    "addr:full":"Pol Ind Pozo Concejo, 9 La Puebla Rio Sevilla 41130",
    "addr:housenumber":"9",
    "addr:postcode":"41130",
    "addr:street":"Concejo",
    "iso:country":"ES",
    "sg:address":"Pol Ind Pozo Concejo, 9",
    "sg:city":"La Puebla Rio",
    "sg:orig_category":"Escayola Y Productos De Escayola (fabricaci\u00d3n, Al Por Mayor)",
    "sg:phone":"+34 955 77 19 21",
    "sg:postcode":"41130",
    "sg:province":"Sevilla",
    "wof:name":"Escayolas Monte Alto S.l.",
    "wof:placetype":"venue"
},
  "geometry": {"coordinates":[-6.0651087761,37.2680435181],"type":"Point"}
}