{
  "type": "Feature",
  "properties": {
    "iso:country":"ES",
    "sg:address":"Calle de Madrid, 62",
    "sg:city":"Vitoria-gasteiz",
    "sg:orig_category":"Peluqueros: De Se\u00d1oras",
    "sg:phone":"+34 945 28 10 36",
    "sg:postcode":"01002",
    "sg:province":"\u00c1lava",
    "wof:name":"Maria Jesus Goicoechea Lecea",
    "wof:placetype":"venue"
},
  "geometry": {"coordinates":[-2.6573989391,42.8549499512],"type":"Point"}
}