{
  "type": "Feature",
  "properties": {
    "addr:full":"Carr Doctora Castells, 26 Lleida Lleida 25001",
    "addr:housenumber":"26",
    "addr:postcode":"25001",
    "addr:street":"Carr Doctora Castells",
    "iso:country":"ES",
    "sg:address":"Carr Doctora Castells, 26",
    "sg:city":"Lleida",
    "sg:orig_category":"Bebidas",
    "sg:phone":"+34 973 20 49 42",
    "sg:postcode":"25001",
    "sg:province":"Lleida",
    "wof:name":"Schweppes S.a.",
    "wof:placetype":"venue"
},
  "geometry": {"coordinates":[0.6281740069,41.6098937988],"type":"Point"}
}