{
  "type": "Feature",
  "properties": {
    "iso:country":"ES",
    "sg:address":"Calle de Veintitres De Abril, 14",
    "sg:city":"Zaragoza",
    "sg:orig_category":"Fabricaci\u00d3n De Moldes Y Modelos",
    "sg:phone":"+34 976 57 33 10",
    "sg:postcode":"50014",
    "sg:province":"Zaragoza",
    "wof:name":"Fabricados Industriales Aragoneses S.l.",
    "wof:placetype":"venue"
},
  "geometry": {"coordinates":[-0.8526390195,41.6683502197],"type":"Point"}
}