{
  "type": "Feature",
  "properties": {
    "iso:country":"ES",
    "sg:address":"Erdiko Kalea, 30",
    "sg:city":"Arrasate",
    "sg:orig_category":"Sociedades, Compa\u00d1\u00cdas Aseguradoras",
    "sg:phone":"+34 943 77 13 09",
    "sg:postcode":"20500",
    "sg:province":"Guip\u00f9zcoa",
    "wof:name":"Elorza Echevarria Miguel",
    "wof:placetype":"venue"
},
  "geometry": {"coordinates":[-2.4904060364,43.065612793],"type":"Point"}
}