{
  "type": "Feature",
  "properties": {
    "iso:country":"ES",
    "sg:address":"Mercat Guineueta, S/n",
    "sg:city":"Barcelona",
    "sg:orig_category":"Carnicer\u00cdas, Carnicer\u00cdas",
    "sg:phone":"+34 933 50 28 48",
    "sg:postcode":"08016",
    "sg:province":"Barcelona",
    "wof:name":"Alvarez Moriano Candido",
    "wof:placetype":"venue"
},
  "geometry": {"coordinates":[2.1806423664,41.436920166],"type":"Point"}
}