{
  "type": "Feature",
  "properties": {
    "iso:country":"ES",
    "sg:address":"Carrer de Gaia, 26",
    "sg:city":"Mas Rampinyo",
    "sg:orig_category":"Mec\u00c1nico Del Autom\u00d3vil",
    "sg:phone":"+34 935 64 79 19",
    "sg:postcode":"08110",
    "sg:province":"Barcelona",
    "wof:name":"Martinez Mu\u00f1oz Jose David",
    "wof:placetype":"venue"
},
  "geometry": {"coordinates":[2.1817660332,41.4890899658],"type":"Point"}
}