{
  "type": "Feature",
  "properties": {
    "iso:country":"ES",
    "sg:address":"Carrer de Prat De La Riba, 16",
    "sg:city":"Casco Urbano",
    "sg:orig_category":"Cl\u00cdnicas Dentales",
    "sg:phone":"+34 938 41 03 48",
    "sg:postcode":"08450",
    "sg:province":"Barcelona",
    "wof:name":"Dentalux Clinica Dental S.l.",
    "wof:placetype":"venue"
},
  "geometry": {"coordinates":[2.4019749165,41.6397705078],"type":"Point"}
}