{
  "type": "Feature",
  "properties": {
    "addr:full":"Calle de Carretera De Malaga, S/n Almu\u00f1ecar Granada 18690",
    "addr:postcode":"18690",
    "addr:street":"Calle De Carretera De Malaga S / N Almun\u0303Ecar",
    "iso:country":"ES",
    "sg:address":"Calle de Carretera De Malaga, S/n",
    "sg:city":"Almu\u00f1ecar",
    "sg:orig_category":"Venta, Instalaci\u00d3n De Cocinas",
    "sg:phone":"+34 958 63 21 62",
    "sg:postcode":"18690",
    "sg:province":"Granada",
    "wof:name":"Medina Cano Francisco",
    "wof:placetype":"venue"
},
  "geometry": {"coordinates":[-3.7373957634,36.738910675],"type":"Point"}
}