{
  "type": "Feature",
  "properties": {
    "addr:full":"Av Isidor Macabich, 2 Eivissa Islas Baleares 07800",
    "addr:housenumber":"2",
    "addr:postcode":"07800",
    "addr:street":"Av Isidor Macabich",
    "iso:country":"ES",
    "sg:address":"Av Isidor Macabich, 2",
    "sg:city":"Eivissa",
    "sg:orig_category":"Abogados",
    "sg:phone":"+34 971 31 14 87",
    "sg:postcode":"07800",
    "sg:province":"Islas Baleares",
    "wof:name":"Bufete A\u00d1o S.l.",
    "wof:placetype":"venue"
},
  "geometry": {"coordinates":[1.431120038,38.9106941223],"type":"Point"}
}