{
  "type": "Feature",
  "properties": {
    "addr:full":"Cno. C. Pastilla, S/n Can Pastilla Islas Baleares 07610",
    "addr:housenumber":"s",
    "addr:postcode":"07610",
    "addr:street":"Cno. C. Pastilla;/ N",
    "iso:country":"ES",
    "sg:address":"Cno. C. Pastilla, S/n",
    "sg:city":"Can Pastilla",
    "sg:orig_category":"Alquiler De Veh\u00cdculos: Turismos Y Utilitarios",
    "sg:phone":"+34 971 74 41 69",
    "sg:postcode":"07610",
    "sg:province":"Islas Baleares",
    "sg:website":"www.autosroig.com",
    "wof:name":"Autos D'or Rent A Car S.l.",
    "wof:placetype":"venue"
},
  "geometry": {"coordinates":[2.7114601135,39.5408096313],"type":"Point"}
}