{
  "type": "Feature",
  "properties": {
    "iso:country":"ES",
    "sg:address":"Calle de San Vicente, 4",
    "sg:city":"Chilches",
    "sg:orig_category":"Alimentaci\u00d3n General (al Por Mayor)",
    "sg:phone":"+34 964 59 00 29",
    "sg:postcode":"12592",
    "sg:province":"Castell\u00f3n",
    "wof:name":"Piensos Chilches S.l.",
    "wof:placetype":"venue"
},
  "geometry": {"coordinates":[-0.1879400015,39.7814178467],"type":"Point"}
}