{
  "type": "Feature",
  "properties": {
    "addr:full":"Calle de Matadero, 16 Talavera Reina Toledo 45600",
    "addr:housenumber":"16",
    "addr:postcode":"45600",
    "addr:street":"Calle De Matadero",
    "iso:country":"ES",
    "sg:address":"Calle de Matadero, 16",
    "sg:city":"Talavera Reina",
    "sg:orig_category":"Supermercados Y Hipermercados",
    "sg:phone":"+34 925 80 50 04",
    "sg:postcode":"45600",
    "sg:province":"Toledo",
    "sg:website":"www.mercadona.es",
    "wof:name":"Mercadona S.a.",
    "wof:placetype":"venue"
},
  "geometry": {"coordinates":[-4.8306951523,39.9636611938],"type":"Point"}
}