{
  "type": "Feature",
  "properties": {
    "addr:full":"Carrer de Bruc, 21 Barcelona Barcelona 08010",
    "addr:housenumber":"21",
    "addr:postcode":"08010",
    "addr:street":"Carrer De Bruc",
    "iso:country":"ES",
    "sg:address":"Carrer de Bruc, 21",
    "sg:city":"Barcelona",
    "sg:orig_category":"Aeropuertos Y Servicios Aeroportuarios",
    "sg:phone":"+34 933 01 23 65",
    "sg:postcode":"08010",
    "sg:province":"Barcelona",
    "sg:website":"www.ukraine-international.com",
    "wof:name":"Ukraine Internacional Airlines",
    "wof:placetype":"venue"
},
  "geometry": {"coordinates":[2.1739730835,41.3907775879],"type":"Point"}
}