{
  "type": "Feature",
  "properties": {
    "addr:full":"Escuela La, 28 Mecerreyes Burgos 09346",
    "addr:postcode":"09346",
    "iso:country":"ES",
    "sg:address":"Escuela La, 28",
    "sg:city":"Mecerreyes",
    "sg:orig_category":"Iglesia Cat\u00d3lica",
    "sg:phone":"+34 947 40 30 02",
    "sg:postcode":"09346",
    "sg:province":"Burgos",
    "wof:name":"Parroquia De San Martin",
    "wof:placetype":"venue"
},
  "geometry": {"coordinates":[-3.5733590126,42.095489502],"type":"Point"}
}