{
  "type": "Feature",
  "properties": {
    "addr:full":"Urb. La Monxina, S/n Oviedo Asturias 33010",
    "addr:housenumber":"s / n",
    "addr:postcode":"33010",
    "iso:country":"ES",
    "sg:address":"Urb. La Monxina, S/n",
    "sg:city":"Oviedo",
    "sg:orig_category":"Asociaciones Y Clubs Deportivos",
    "sg:phone":"+34 985 11 04 19",
    "sg:postcode":"33010",
    "sg:province":"Asturias",
    "wof:name":"Pe\u00f1a Ovidiedista Berto",
    "wof:placetype":"venue"
},
  "geometry": {"coordinates":[-5.7993540764,43.3772239685],"type":"Point"}
}