{
  "type": "Feature",
  "properties": {
    "addr:full":"Calle de Vega (la), S/n Matamorosa Cantabria 39200",
    "addr:postcode":"39200",
    "addr:street":"Calle De Vega La S / N",
    "iso:country":"ES",
    "sg:address":"Calle de Vega (la), S/n",
    "sg:city":"Matamorosa",
    "sg:orig_category":"Mec\u00c1nico Del Autom\u00d3vil",
    "sg:phone":"+34 942 75 05 04",
    "sg:postcode":"39200",
    "sg:province":"Cantabria",
    "wof:name":"Automoviles Suano S.l.",
    "wof:placetype":"venue"
},
  "geometry": {"coordinates":[-4.145111084,42.9852561951],"type":"Point"}
}