{
  "type": "Feature",
  "properties": {
    "iso:country":"ES",
    "sg:address":"Calle de Lain Calvo, 42",
    "sg:city":"Burgos",
    "sg:orig_category":"Ropa Para Ni\u00d1os (al Por Menor)",
    "sg:phone":"+34 947 26 08 24",
    "sg:postcode":"09003",
    "sg:province":"Burgos",
    "wof:name":"Garcia Pernas Vanesa",
    "wof:placetype":"venue"
},
  "geometry": {"coordinates":[-3.7014160156,42.3424797058],"type":"Point"}
}