{
  "type": "Feature",
  "properties": {
    "addr:full":"Avda Espa\u00d1a, 32 Ponferrada Le\u00f3n 24400",
    "addr:housenumber":"32",
    "addr:postcode":"24400",
    "addr:street":"Avda Espan\u0303A",
    "iso:country":"ES",
    "sg:address":"Avda Espa\u00d1a, 32",
    "sg:city":"Ponferrada",
    "sg:orig_category":"Arquitectos",
    "sg:phone":"+34 987 41 32 31",
    "sg:postcode":"24400",
    "sg:province":"Le\u00f3n",
    "wof:name":"Neitec Arquitectura S.l.",
    "wof:placetype":"venue"
},
  "geometry": {"coordinates":[-6.6001081467,42.5476951599],"type":"Point"}
}