{
  "type": "Feature",
  "properties": {
    "addr:full":"Calle de Ancora, 5 Madrid Madrid 28045",
    "addr:housenumber":"5",
    "addr:postcode":"28045",
    "addr:street":"Calle De Ancora",
    "iso:country":"ES",
    "sg:address":"Calle de Ancora, 5",
    "sg:city":"Madrid",
    "sg:orig_category":"Alimentaci\u00d3n General (al Por Menor)",
    "sg:phone":"+34 914 68 36 39",
    "sg:postcode":"28045",
    "sg:province":"Madrid",
    "wof:name":"Wang  Hai Feng",
    "wof:placetype":"venue"
},
  "geometry": {"coordinates":[-3.6930561066,40.4030952454],"type":"Point"}
}