{
  "type": "Feature",
  "properties": {
    "addr:full":"Carr Torrent D'en Grau, 17 Badalona Barcelona 08917",
    "addr:housenumber":"17",
    "addr:postcode":"08917",
    "addr:street":"Carr Torrent D'En Grau",
    "iso:country":"ES",
    "sg:address":"Carr Torrent D'en Grau, 17",
    "sg:city":"Badalona",
    "sg:orig_category":"Confecci\u00d3n De Trajes Para Se\u00d1oras",
    "sg:phone":"+34 934 60 27 85",
    "sg:postcode":"08917",
    "sg:province":"Barcelona",
    "wof:name":"Confecciones Pelia S.l.",
    "wof:placetype":"venue"
},
  "geometry": {"coordinates":[2.2285864353,41.4547653198],"type":"Point"}
}