{
  "type": "Feature",
  "properties": {
    "iso:country":"ES",
    "sg:address":"Calle de Puerto, 6",
    "sg:city":"Huelva",
    "sg:orig_category":"M\u00c9dicos: Gastroenterolog\u00cda Y Hepatolog\u00cda (aparato Digestivo)",
    "sg:phone":"+34 959 25 33 33",
    "sg:postcode":"21001",
    "sg:province":"Huelva",
    "wof:name":"Diaz Camacho Ricardo",
    "wof:placetype":"venue"
},
  "geometry": {"coordinates":[-6.951526165,37.258605957],"type":"Point"}
}