{
  "type": "Feature",
  "properties": {
    "iso:country":"ES",
    "sg:address":"Carr Sant Ermengol, 15",
    "sg:city":"Seu D'urgell",
    "sg:orig_category":"M\u00c9dicos: Reumatolog\u00cda",
    "sg:phone":"+34 973 35 46 03",
    "sg:postcode":"25700",
    "sg:province":"Lleida",
    "wof:name":"Ald-natural S.l.",
    "wof:placetype":"venue"
},
  "geometry": {"coordinates":[1.4579170942,42.3566627502],"type":"Point"}
}