{
  "type": "Feature",
  "properties": {
    "iso:country":"ES",
    "sg:address":"Calle de Mexico, 28",
    "sg:city":"Arrecife",
    "sg:orig_category":"M\u00c9dicos: An\u00c1lisis Cl\u00cdnicos",
    "sg:phone":"+34 928 80 18 88",
    "sg:postcode":"35500",
    "sg:province":"Las Palmas",
    "wof:name":"Laboratorio Dr.gonzalez Santiago S.l.",
    "wof:placetype":"venue"
},
  "geometry": {"coordinates":[-13.5565738678,28.9614715576],"type":"Point"}
}