{
  "type": "Feature",
  "properties": {
    "iso:country":"ES",
    "sg:address":"Parte Alta(felechosa), 65",
    "sg:city":"El Pino",
    "sg:orig_category":"Asociaciones Y Clubs Deportivos",
    "sg:phone":"+34 985 48 73 50",
    "sg:postcode":"33688",
    "sg:province":"Asturias",
    "wof:name":"Vidal Suarez Herminia",
    "wof:placetype":"venue"
},
  "geometry": {"coordinates":[-5.3874640465,43.0655136108],"type":"Point"}
}