{
  "type": "Feature",
  "properties": {
    "addr:full":"Calle de Granada, 84 Malaga M\u00e1laga 29015",
    "addr:housenumber":"84",
    "addr:postcode":"29015",
    "addr:street":"Calle De Granada;Ma\u0301Laga",
    "iso:country":"ES",
    "sg:address":"Calle de Granada, 84",
    "sg:city":"Malaga",
    "sg:orig_category":"Ropa Para Beb\u00c9s Y Ni\u00d1os (confecci\u00d3n, Al Por Mayor)",
    "sg:phone":"+34 952 21 61 94",
    "sg:postcode":"29015",
    "sg:province":"M\u00e1laga",
    "wof:name":"Diaz Brecia Esperanza",
    "wof:placetype":"venue"
},
  "geometry": {"coordinates":[-4.4174389839,36.7227287292],"type":"Point"}
}