{
  "type": "Feature",
  "properties": {
    "addr:full":"Poligono Industrial, 1 Guadasequies Valencia 46839",
    "addr:postcode":"46839",
    "addr:street":"Industrial",
    "iso:country":"ES",
    "sg:address":"Poligono Industrial, 1",
    "sg:city":"Guadasequies",
    "sg:orig_category":"Materias Pl\u00c1sticas: Productos De Consumo Masivo (fabricaci\u00d3n, Al Por Mayor)",
    "sg:phone":"+34 962 29 33 09",
    "sg:postcode":"46839",
    "sg:province":"Valencia",
    "wof:name":"Vit Plastic S.l.",
    "wof:placetype":"venue"
},
  "geometry": {"coordinates":[-0.4968676865,38.8979072571],"type":"Point"}
}