{
  "type": "Feature",
  "properties": {
    "addr:full":"Calle de Cerro Minguete, S/n Madrid Madrid 28035",
    "addr:housenumber":"s / n",
    "addr:postcode":"28035",
    "addr:street":"Calle De Cerro Minguete",
    "iso:country":"ES",
    "sg:address":"Calle de Cerro Minguete, S/n",
    "sg:city":"Madrid",
    "sg:orig_category":"Tintes (fabricaci\u00d3n, Al Por Mayor)",
    "sg:phone":"+34 913 76 57 42",
    "sg:postcode":"28035",
    "sg:province":"Madrid",
    "wof:name":"Mb Medioambiente Consulting",
    "wof:placetype":"venue"
},
  "geometry": {"coordinates":[-3.7212822437,40.4868354797],"type":"Point"}
}