{
  "type": "Feature",
  "properties": {
    "addr:full":"Calle de Maria Zambrano, 10 Zaragoza Zaragoza 50018",
    "addr:housenumber":"10",
    "addr:postcode":"50018",
    "addr:street":"Calle De Maria Zambrano",
    "iso:country":"ES",
    "sg:address":"Calle de Maria Zambrano, 10",
    "sg:city":"Zaragoza",
    "sg:orig_category":"Farmacias",
    "sg:phone":"+34 976 52 38 64",
    "sg:postcode":"50018",
    "sg:province":"Zaragoza",
    "wof:name":"Asensi Serrano Rosa Maria",
    "wof:placetype":"venue"
},
  "geometry": {"coordinates":[-0.8844752908,41.6649398804],"type":"Point"}
}