{
  "type": "Feature",
  "properties": {
    "addr:full":"C/ Cristobal Colon, 24 Porreres Islas Baleares 07260",
    "addr:housenumber":"24",
    "addr:postcode":"07260",
    "addr:street":"C / Cristobal Colon",
    "iso:country":"ES",
    "sg:address":"C/ Cristobal Colon, 24",
    "sg:city":"Porreres",
    "sg:orig_category":"Peluquer\u00cdas, Peluquer\u00cda Mixta",
    "sg:phone":"+34 971 64 76 10",
    "sg:postcode":"07260",
    "sg:province":"Islas Baleares",
    "wof:name":"Salon Antonia Cb",
    "wof:placetype":"venue"
},
  "geometry": {"coordinates":[3.0226650238,39.5170059204],"type":"Point"}
}