{
  "type": "Feature",
  "properties": {
    "addr:full":"Calle de Cervantes, 18 Merida Badajoz 06800",
    "addr:housenumber":"18",
    "addr:postcode":"06800",
    "addr:street":"Calle De Cervantes",
    "iso:country":"ES",
    "sg:address":"Calle de Cervantes, 18",
    "sg:city":"Merida",
    "sg:orig_category":"Inmobiliaria (agencias)",
    "sg:phone":"+34 924 31 71 65",
    "sg:postcode":"06800",
    "sg:province":"Badajoz",
    "wof:name":"Sierra Escobar Ismael",
    "wof:placetype":"venue"
},
  "geometry": {"coordinates":[-6.3430318832,38.9190063477],"type":"Point"}
}