{
  "type": "Feature",
  "properties": {
    "iso:country":"ES",
    "sg:address":"Avda Barcelona, 49",
    "sg:city":"Jaen",
    "sg:orig_category":"Reparaciones Y Remolcado De Veh\u00cdculos",
    "sg:phone":"+34 953 22 32 41",
    "sg:postcode":"23006",
    "sg:province":"Ja\u00e9n",
    "wof:name":"Juan Francisco Garrido Y Manuel Cortes C.b",
    "wof:placetype":"venue"
},
  "geometry": {"coordinates":[-3.8017780781,37.7804946899],"type":"Point"}
}