{
  "type": "Feature",
  "properties": {
    "addr:full":"Avda Primero De Junio, 46 Venta De Ba\u00e7os Palencia 34200",
    "addr:housenumber":"46",
    "addr:postcode":"34200",
    "addr:street":"Avda Primero De Junio",
    "iso:country":"ES",
    "sg:address":"Avda Primero De Junio, 46",
    "sg:city":"Venta De Ba\u00e7os",
    "sg:orig_category":"Contenedores (mercanc\u00cdas)",
    "sg:phone":"+34 979 77 02 98",
    "sg:postcode":"34200",
    "sg:province":"Palencia",
    "wof:name":"Nieto Perez Jose Maria",
    "wof:placetype":"venue"
},
  "geometry": {"coordinates":[-4.4944329262,41.9221725464],"type":"Point"}
}