{
  "type": "Feature",
  "properties": {
    "iso:country":"ES",
    "sg:address":"Calle de Aquitania, 31",
    "sg:city":"Madrid",
    "sg:orig_category":"Librer\u00cdas",
    "sg:phone":"+34 913 13 51 38",
    "sg:postcode":"28032",
    "sg:province":"Madrid",
    "wof:name":"Garcia Molero Alfonso",
    "wof:placetype":"venue"
},
  "geometry": {"coordinates":[-3.6167345047,40.4191818237],"type":"Point"}
}