{
  "type": "Feature",
  "properties": {
    "iso:country":"ES",
    "sg:address":"Calle de Virgen, 6",
    "sg:city":"Linares",
    "sg:orig_category":"Zapatos (al Por Menor)",
    "sg:phone":"+34 953 69 23 13",
    "sg:postcode":"23700",
    "sg:province":"Ja\u00e9n",
    "wof:name":"Gavilan Galiano Jose",
    "wof:placetype":"venue"
},
  "geometry": {"coordinates":[-3.6357250214,38.0961341858],"type":"Point"}
}