{
  "type": "Feature",
  "properties": {
    "iso:country":"ES",
    "sg:address":"Carrer de Chopin, 10",
    "sg:city":"Rubi",
    "sg:orig_category":"Lacadores",
    "sg:phone":"+34 935 86 17 68",
    "sg:postcode":"08191",
    "sg:province":"Barcelona",
    "wof:name":"Empresa Lacados Rubi Sl",
    "wof:placetype":"venue"
},
  "geometry": {"coordinates":[2.0235500336,41.469455719],"type":"Point"}
}