{
  "type": "Feature",
  "properties": {
    "addr:full":"Carrer de Duran I Bas, 16 Barcelona Barcelona 08002",
    "addr:housenumber":"16",
    "addr:postcode":"08002",
    "addr:street":"Carrer De Duran I Bas",
    "iso:country":"ES",
    "sg:address":"Carrer de Duran I Bas, 16",
    "sg:city":"Barcelona",
    "sg:orig_category":"Agencias Y Agentes Comerciales, Representantes",
    "sg:phone":"+34 933 17 23 84",
    "sg:postcode":"08002",
    "sg:province":"Barcelona",
    "wof:name":"Serrano Martin Araceli",
    "wof:placetype":"venue"
},
  "geometry": {"coordinates":[2.1747090816,41.3854942322],"type":"Point"}
}