{
  "type": "Feature",
  "properties": {
    "addr:full":"Calle de Artekale, 18 Berriozar Navarra 31013",
    "addr:housenumber":"18",
    "addr:postcode":"31013",
    "addr:street":"Calle De Artekale",
    "iso:country":"ES",
    "sg:address":"Calle de Artekale, 18",
    "sg:city":"Berriozar",
    "sg:orig_category":"Reposter\u00cdas",
    "sg:phone":"+34 948 30 10 22",
    "sg:postcode":"31013",
    "sg:province":"Navarra",
    "wof:name":"Panaderias Navarras S.a.",
    "wof:placetype":"venue"
},
  "geometry": {"coordinates":[-1.6767936945,42.8366928101],"type":"Point"}
}