{
  "type": "Feature",
  "properties": {
    "iso:country":"ES",
    "sg:address":"Rua Alcalde Hevia (do), 9",
    "sg:city":"Pontevedra",
    "sg:orig_category":"Piscinas, Accesorios, Suministros (fabricaci\u00d3n, Al Por Mayor)",
    "sg:phone":"+34 986 85 84 50",
    "sg:postcode":"36003",
    "sg:province":"Pontevedra",
    "wof:name":"Hisemar S. L.",
    "wof:placetype":"venue"
},
  "geometry": {"coordinates":[-8.6556968689,42.4145812988],"type":"Point"}
}