{
  "type": "Feature",
  "properties": {
    "iso:country":"ES",
    "sg:address":"Calle de Caridad (la), 3",
    "sg:city":"Le\u00f3n",
    "sg:orig_category":"Promotores Constructores",
    "sg:phone":"+34 987 24 47 68",
    "sg:postcode":"24007",
    "sg:province":"Le\u00f3n",
    "wof:name":"Miralgon Sl",
    "wof:placetype":"venue"
},
  "geometry": {"coordinates":[-5.5625071526,42.6014862061],"type":"Point"}
}