{
  "type": "Feature",
  "properties": {
    "addr:full":"Calle de Palo, 9 Madridejos Toledo 45710",
    "addr:housenumber":"9",
    "addr:postcode":"45710",
    "addr:street":"Calle De Palo",
    "iso:country":"ES",
    "sg:address":"Calle de Palo, 9",
    "sg:city":"Madridejos",
    "sg:orig_category":"Transporte En General",
    "sg:phone":"+34 925 46 10 79",
    "sg:postcode":"45710",
    "sg:province":"Toledo",
    "wof:name":"Lopez Infante Santiago",
    "wof:placetype":"venue"
},
  "geometry": {"coordinates":[-3.5330359936,39.4693984985],"type":"Point"}
}