{
  "type": "Feature",
  "properties": {
    "addr:full":"Calle de Santa Marina, 1 Etxebarri Vizcaya 48450",
    "addr:housenumber":"1",
    "addr:postcode":"48450",
    "addr:street":"Calle De Santa Marina",
    "iso:country":"ES",
    "sg:address":"Calle de Santa Marina, 1",
    "sg:city":"Etxebarri",
    "sg:orig_category":"Molduras, Junquillos, Listones Y Molduras Perforadas",
    "sg:phone":"+34 944 40 46 13",
    "sg:postcode":"48450",
    "sg:province":"Vizcaya",
    "wof:name":"Jagoba Valverde Blanca",
    "wof:placetype":"venue"
},
  "geometry": {"coordinates":[-2.8835148811,43.2549819946],"type":"Point"}
}