{
  "type": "Feature",
  "properties": {
    "addr:full":"Calle de Karl Raimund Popper, 11 Castellon Castell\u00f3n 12003",
    "addr:housenumber":"11",
    "addr:postcode":"12003",
    "addr:street":"Calle De Karl Raimund Popper",
    "iso:country":"ES",
    "sg:address":"Calle de Karl Raimund Popper, 11",
    "sg:city":"Castellon",
    "sg:orig_category":"Equitaci\u00d3n Y Centros De H\u00cdpica",
    "sg:phone":"+34 964 22 29 30",
    "sg:postcode":"12003",
    "sg:province":"Castell\u00f3n",
    "wof:name":"Gombau Valanzuela Emilio",
    "wof:placetype":"venue"
},
  "geometry": {"coordinates":[-0.0235459991,39.9905014038],"type":"Point"}
}