{
  "type": "Feature",
  "properties": {
    "addr:full":"Csta. Mentidero, S/n Valera Abajo Cuenca 16120",
    "addr:housenumber":"s / n",
    "addr:postcode":"16120",
    "addr:street":"Csta. Mentidero;Abajo",
    "iso:country":"ES",
    "sg:address":"Csta. Mentidero, S/n",
    "sg:city":"Valera Abajo",
    "sg:orig_category":"Distribuci\u00d3n De Petr\u00d3leo Y Derivados",
    "sg:phone":"+34 969 20 35 02",
    "sg:postcode":"16120",
    "sg:province":"Cuenca",
    "wof:name":"Valer-aparicio S.l.",
    "wof:placetype":"venue"
},
  "geometry": {"coordinates":[-2.1635560989,39.7696876526],"type":"Point"}
}