{
  "type": "Feature",
  "properties": {
    "iso:country":"ES",
    "sg:address":"Calle de Socuellamos, S/n",
    "sg:city":"Ciudad Real",
    "sg:orig_category":"Teatros Y Salas De Espect\u00c1culos",
    "sg:phone":"+34 926 21 25 98",
    "sg:postcode":"13005",
    "sg:province":"Ciudad Real",
    "wof:name":"Teatro Narea S.c.",
    "wof:placetype":"venue"
},
  "geometry": {"coordinates":[-3.9293160439,38.9767990112],"type":"Point"}
}