{
  "type": "Feature",
  "properties": {
    "addr:full":"Ctra Alfonso Xiii, 84 Melilla Melilla 52005",
    "addr:housenumber":"84",
    "addr:postcode":"52005",
    "addr:street":"Ctra Alfonso Xiii",
    "iso:country":"ES",
    "sg:address":"Ctra Alfonso Xiii, 84",
    "sg:city":"Melilla",
    "sg:orig_category":"Distribuci\u00d3n De Petr\u00d3leo Y Derivados",
    "sg:phone":"+34 952 67 38 21",
    "sg:postcode":"52005",
    "sg:province":"Melilla",
    "wof:name":"Explotacion Estacion De Servicio S.a.",
    "wof:placetype":"venue"
},
  "geometry": {"coordinates":[-2.9476480484,35.2811355591],"type":"Point"}
}