{
  "type": "Feature",
  "properties": {
    "addr:full":"Plaz Ramon Y Cajal, 1 Cari\u00f1ena Zaragoza 50400",
    "addr:housenumber":"1",
    "addr:postcode":"50400",
    "addr:street":"Ramon Y Cajal",
    "iso:country":"ES",
    "sg:address":"Plaz Ramon Y Cajal, 1",
    "sg:city":"Cari\u00f1ena",
    "sg:orig_category":"Albergues",
    "sg:phone":"+34 976 62 04 92",
    "sg:postcode":"50400",
    "sg:province":"Zaragoza",
    "wof:name":"Gil Lopez Francisco",
    "wof:placetype":"venue"
},
  "geometry": {"coordinates":[-1.2237490416,41.3375244141],"type":"Point"}
}