{
  "type": "Feature",
  "properties": {
    "iso:country":"ES",
    "sg:address":"Av Catalunya, 35",
    "sg:city":"Sant Valeria",
    "sg:orig_category":"Loter\u00cda Y T\u00d3mbola",
    "sg:phone":"+34 938 43 63 44",
    "sg:postcode":"08185",
    "sg:province":"Barcelona",
    "wof:name":"Clape Martinez Maria Teresa",
    "wof:placetype":"venue"
},
  "geometry": {"coordinates":[2.2373700142,41.5820808411],"type":"Point"}
}