{
  "type": "Feature",
  "properties": {
    "iso:country":"ES",
    "sg:address":"Calle de Mercaderes, S/n",
    "sg:city":"Llanes",
    "sg:orig_category":"Art\u00cdculos De Regalo (al Por Menor)",
    "sg:phone":"+34 985 40 09 53",
    "sg:postcode":"33500",
    "sg:province":"Asturias",
    "wof:name":"Rozas Garcia Francisco",
    "wof:placetype":"venue"
},
  "geometry": {"coordinates":[-4.7542738914,43.4195556641],"type":"Point"}
}