{
  "type": "Feature",
  "properties": {
    "addr:full":"Avda Galicia, 243 Fuentes Nuevas Le\u00f3n 24411",
    "addr:housenumber":"243",
    "addr:postcode":"24411",
    "addr:street":"Avda Galicia",
    "iso:country":"ES",
    "sg:address":"Avda Galicia, 243",
    "sg:city":"Fuentes Nuevas",
    "sg:orig_category":"Peleter\u00cdas",
    "sg:phone":"+34 987 45 50 19",
    "sg:postcode":"24411",
    "sg:province":"Le\u00f3n",
    "wof:name":"Bierzo Piel S. A.",
    "wof:placetype":"venue"
},
  "geometry": {"coordinates":[-6.6439290047,42.5685310364],"type":"Point"}
}