{
  "type": "Feature",
  "properties": {
    "addr:full":"Calle de Gutemberg, 12 Salamanca Salamanca 37007",
    "addr:housenumber":"12",
    "addr:postcode":"37007",
    "addr:street":"Calle De Gutemberg",
    "iso:country":"ES",
    "sg:address":"Calle de Gutemberg, 12",
    "sg:city":"Salamanca",
    "sg:orig_category":"Peluquer\u00cdas, Peluquer\u00cda Mixta",
    "sg:phone":"+34 923 24 04 12",
    "sg:postcode":"37007",
    "sg:province":"Salamanca",
    "wof:name":"Perez Vicente Claudina",
    "wof:placetype":"venue"
},
  "geometry": {"coordinates":[-5.6688051224,40.9720611572],"type":"Point"}
}