{
  "type": "Feature",
  "properties": {
    "iso:country":"ES",
    "sg:address":"Carrer de Sant Cugat, 2",
    "sg:city":"Mataro",
    "sg:orig_category":"Asesor\u00cda Fiscal Y Jur\u00cddica",
    "sg:phone":"+34 937 99 42 80",
    "sg:postcode":"08302",
    "sg:province":"Barcelona",
    "sg:website":"www.s-sorein.com",
    "wof:name":"Hermoso Sanchez Sergio",
    "wof:placetype":"venue"
},
  "geometry": {"coordinates":[2.4406630993,41.5370101929],"type":"Point"}
}