{
  "type": "Feature",
  "properties": {
    "addr:full":"Carrer de Francesc Armengol, 2 Sitges Barcelona 08870",
    "addr:housenumber":"2",
    "addr:postcode":"08870",
    "addr:street":"Carrer De Francesc Armengol",
    "iso:country":"ES",
    "sg:address":"Carrer de Francesc Armengol, 2",
    "sg:city":"Sitges",
    "sg:orig_category":"Promotores Constructores",
    "sg:phone":"+34 938 94 77 02",
    "sg:postcode":"08870",
    "sg:province":"Barcelona",
    "wof:name":"Vidal Llort Adela",
    "wof:placetype":"venue"
},
  "geometry": {"coordinates":[1.7998039722,41.2323951721],"type":"Point"}
}