{
  "type": "Feature",
  "properties": {
    "iso:country":"ES",
    "sg:address":"Carretera De Churriana-alhaurin, 3",
    "sg:city":"Churriana",
    "sg:orig_category":"Cultos Diversos",
    "sg:phone":"+34 952 62 10 38",
    "sg:postcode":"29140",
    "sg:province":"M\u00e1laga",
    "wof:name":"Asociacion Religiosa Conciencia De Krisna",
    "wof:placetype":"venue"
},
  "geometry": {"coordinates":[-4.4931116104,36.6576156616],"type":"Point"}
}