{
  "type": "Feature",
  "properties": {
    "addr:full":"Av Prat De La Riba, 152 Palleja Barcelona 08780",
    "addr:housenumber":"152",
    "addr:postcode":"08780",
    "addr:street":"Av Prat De La Riba",
    "iso:country":"ES",
    "sg:address":"Av Prat De La Riba, 152",
    "sg:city":"Palleja",
    "sg:orig_category":"Aparatos E Instalaci\u00d3n De Regad\u00cdos",
    "sg:phone":"+34 936 63 19 19",
    "sg:postcode":"08780",
    "sg:province":"Barcelona",
    "wof:name":"Campmany Canals Jorge",
    "wof:placetype":"venue"
},
  "geometry": {"coordinates":[1.9990420341,41.416053772],"type":"Point"}
}