{
  "type": "Feature",
  "properties": {
    "iso:country":"ES",
    "sg:address":"Calle de Maria Auxiliadora, 12",
    "sg:city":"Bollullos Par Condado",
    "sg:orig_category":"Delegados, Agentes De Tr\u00c1nsito, Auxiliares De Transporte Internacional",
    "sg:phone":"+34 959 41 33 10",
    "sg:postcode":"21710",
    "sg:province":"Huelva",
    "wof:name":"Carrasco Hernandez Sergio",
    "wof:placetype":"venue"
},
  "geometry": {"coordinates":[-6.5397648811,37.343082428],"type":"Point"}
}