{
  "type": "Feature",
  "properties": {
    "addr:full":"Alacant, 14 Cornella Llobregat Barcelona 08940",
    "addr:housenumber":"14",
    "addr:postcode":"08940",
    "addr:street":"Alacant",
    "iso:country":"ES",
    "sg:address":"Alacant, 14",
    "sg:city":"Cornella Llobregat",
    "sg:orig_category":"Garajes De Veh\u00cdculos",
    "sg:phone":"+34 932 74 02 83",
    "sg:postcode":"08940",
    "sg:province":"Barcelona",
    "wof:name":"Autotecno Industrial Trading Center S.l.",
    "wof:placetype":"venue"
},
  "geometry": {"coordinates":[2.1111176014,41.3722076416],"type":"Point"}
}