{
  "type": "Feature",
  "properties": {
    "addr:full":"Rua Concepcion Arenal, 39 Espirito Santo Pontevedra 36940",
    "addr:housenumber":"39",
    "addr:postcode":"36940",
    "addr:street":"Rua Concepcion Arenal",
    "iso:country":"ES",
    "sg:address":"Rua Concepcion Arenal, 39",
    "sg:city":"Espirito Santo",
    "sg:orig_category":"Centros Empresariales",
    "sg:phone":"+34 986 30 52 61",
    "sg:postcode":"36940",
    "sg:province":"Pontevedra",
    "wof:name":"Ferreteria Garmo S.l.",
    "wof:placetype":"venue"
},
  "geometry": {"coordinates":[-8.8184690475,42.2741928101],"type":"Point"}
}