{
  "type": "Feature",
  "properties": {
    "iso:country":"ES",
    "sg:address":"Indamendi Kalea, 12",
    "sg:city":"Zarautz",
    "sg:orig_category":"Carnicer\u00cdas, Carnicer\u00cdas",
    "sg:phone":"+34 943 83 36 64",
    "sg:postcode":"20800",
    "sg:province":"Guip\u00f9zcoa",
    "wof:name":"Amilibia Ecenarro, Jesus",
    "wof:placetype":"venue"
},
  "geometry": {"coordinates":[-2.1598849297,43.2807617188],"type":"Point"}
}