{
  "type": "Feature",
  "properties": {
    "iso:country":"ES",
    "sg:address":"Maricielo, S/n",
    "sg:city":"Garrucha",
    "sg:orig_category":"Supermercados Y Hipermercados",
    "sg:phone":"+34 950 46 03 53",
    "sg:postcode":"04630",
    "sg:province":"Almer\u00eda",
    "wof:name":"Beer Emporium S.l.",
    "wof:placetype":"venue"
},
  "geometry": {"coordinates":[-1.8186839819,37.1933898926],"type":"Point"}
}