{
  "type": "Feature",
  "properties": {
    "addr:full":"Avda Navarrondan (de), S/n San Sebastian De Los Reyes Madrid 28700",
    "addr:housenumber":"/ n",
    "addr:postcode":"28700",
    "addr:street":"Avda Navarrondan De S",
    "iso:country":"ES",
    "sg:address":"Avda Navarrondan (de), S/n",
    "sg:city":"San Sebastian De Los Reyes",
    "sg:orig_category":"Deportes Y Programas De Aventura",
    "sg:phone":"+34 916 52 92 11",
    "sg:postcode":"28700",
    "sg:province":"Madrid",
    "wof:name":"Club Baloncesto Zona Press S.l",
    "wof:placetype":"venue"
},
  "geometry": {"coordinates":[-3.6285541058,40.5513000488],"type":"Point"}
}