{
  "type": "Feature",
  "properties": {
    "addr:full":"Calle de Teniente Blanco Marin, 1 Santos De Maimona Badajoz 06230",
    "addr:housenumber":"1",
    "addr:postcode":"06230",
    "addr:street":"Calle De Teniente Blanco Marin",
    "iso:country":"ES",
    "sg:address":"Calle de Teniente Blanco Marin, 1",
    "sg:city":"Santos De Maimona",
    "sg:orig_category":"Bancos",
    "sg:phone":"+34 924 54 41 26",
    "sg:postcode":"06230",
    "sg:province":"Badajoz",
    "sg:website":"www.bancopopular.es",
    "wof:name":"Banco Popular Espa\u00f1ol",
    "wof:placetype":"venue"
},
  "geometry": {"coordinates":[-6.3829312325,38.4499206543],"type":"Point"}
}