{
  "type": "Feature",
  "properties": {
    "addr:full":"Calle de Cuchilleria, 51 Vitoria-gasteiz \u00c1lava 01001",
    "addr:housenumber":"51",
    "addr:postcode":"01001",
    "addr:street":"Calle De Cuchilleria",
    "iso:country":"ES",
    "sg:address":"Calle de Cuchilleria, 51",
    "sg:city":"Vitoria-gasteiz",
    "sg:orig_category":"Farmacias",
    "sg:phone":"+34 945 28 41 02",
    "sg:postcode":"01001",
    "sg:province":"\u00c1lava",
    "wof:name":"Sanz-diaz De Durana Sociedad Civil",
    "wof:placetype":"venue"
},
  "geometry": {"coordinates":[-2.6714110374,42.8493537903],"type":"Point"}
}