{
  "type": "Feature",
  "properties": {
    "addr:full":"Avda Miguel Delibes, 26 Moraleja C\u00e1ceres 10840",
    "addr:housenumber":"26",
    "addr:postcode":"10840",
    "addr:street":"Avda Miguel Delibes;Ca\u0301Ceres",
    "iso:country":"ES",
    "sg:address":"Avda Miguel Delibes, 26",
    "sg:city":"Moraleja",
    "sg:orig_category":"Ingeniero",
    "sg:phone":"+34 927 14 74 03",
    "sg:postcode":"10840",
    "sg:province":"C\u00e1ceres",
    "wof:name":"Roman Gomez Jeronimo",
    "wof:placetype":"venue"
},
  "geometry": {"coordinates":[-6.6528511047,40.0599784851],"type":"Point"}
}