{
  "type": "Feature",
  "properties": {
    "addr:full":"Carretera, 127 Arenas Igu\u00f1a Cantabria 39450",
    "addr:postcode":"39450",
    "addr:street":"Carretera 127",
    "iso:country":"ES",
    "sg:address":"Carretera, 127",
    "sg:city":"Arenas Igu\u00f1a",
    "sg:classifiers":[
        {
            "category":"Autos & Motor Vehicles",
            "subcategory":"Automobile Sales",
            "type":"Retail Goods"
        }
    ],
    "sg:phone":"+34 942 82 66 55",
    "sg:postcode":"39450",
    "sg:province":"Cantabria",
    "wof:name":"Ramona Zamanillo S.l.",
    "wof:placetype":"venue"
},
  "geometry": {"coordinates":[-4.0503439903,43.1874237061],"type":"Point"}
}