{
  "type": "Feature",
  "properties": {
    "addr:full":"Damaso Azkue Plaza, 9 Azpeitia Guip\u00f9zcoa 20730",
    "addr:housenumber":"9",
    "addr:postcode":"20730",
    "addr:street":"Damaso Azkue Plaza;Guipu\u0300Zcoa",
    "iso:country":"ES",
    "sg:address":"Damaso Azkue Plaza, 9",
    "sg:city":"Azpeitia",
    "sg:orig_category":"Plomeros",
    "sg:phone":"+34 943 02 60 28",
    "sg:postcode":"20730",
    "sg:province":"Guip\u00f9zcoa",
    "wof:name":"Bikendi Itugintza S.l..",
    "wof:placetype":"venue"
},
  "geometry": {"coordinates":[-2.2621059418,43.1872062683],"type":"Point"}
}