{
  "type": "Feature",
  "properties": {
    "addr:full":"Ctra., S/n Codesal Zamora 49594",
    "addr:postcode":"49594",
    "addr:street":"Ctra. S / N Codesal Zamora",
    "iso:country":"ES",
    "sg:address":"Ctra., S/n",
    "sg:city":"Codesal",
    "sg:orig_category":"Molduras, Junquillos, Listones Y Molduras Perforadas",
    "sg:phone":"+34 980 65 47 15",
    "sg:postcode":"49594",
    "sg:province":"Zamora",
    "wof:name":"Construcciones Carballeda Y Sanabria S.l.",
    "wof:placetype":"venue"
},
  "geometry": {"coordinates":[-6.4366240501,41.9904747009],"type":"Point"}
}