{
  "type": "Feature",
  "properties": {
    "iso:country":"ES",
    "sg:address":"Calle de Acera Recoletos, 20",
    "sg:city":"Valladolid",
    "sg:orig_category":"Laboratorios Y Cl\u00cdnicas Veterinarias",
    "sg:phone":"+34 983 30 37 58",
    "sg:postcode":"47004",
    "sg:province":"Valladolid",
    "wof:name":"Sam-co Zoosanitarios S.l.",
    "wof:placetype":"venue"
},
  "geometry": {"coordinates":[-4.727408886,41.6453208923],"type":"Point"}
}