{
  "type": "Feature",
  "properties": {
    "iso:country":"ES",
    "sg:address":"Carr Vassallo, 31",
    "sg:city":"Mao",
    "sg:orig_category":"Agencias De Viajes",
    "sg:phone":"+34 971 36 96 04",
    "sg:postcode":"07703",
    "sg:province":"Islas Baleares",
    "wof:name":"Viajes Iberia S.a:",
    "wof:placetype":"venue"
},
  "geometry": {"coordinates":[4.2570838928,39.8874053955],"type":"Point"}
}