{
  "type": "Feature",
  "properties": {
    "addr:full":"Avda Julian Saez, 38 Pedro Mu\u00e7oz Ciudad Real 13620",
    "addr:housenumber":"38",
    "addr:postcode":"13620",
    "addr:street":"Avda Julian Saez;Pedro Muc\u0327Oz",
    "iso:country":"ES",
    "sg:address":"Avda Julian Saez, 38",
    "sg:city":"Pedro Mu\u00e7oz",
    "sg:orig_category":"Escayola Y Productos De Escayola (fabricaci\u00d3n, Al Por Mayor)",
    "sg:phone":"+34 926 58 78 53",
    "sg:postcode":"13620",
    "sg:province":"Ciudad Real",
    "wof:name":"Escayolas Fabridis S.l.",
    "wof:placetype":"venue"
},
  "geometry": {"coordinates":[-2.944617033,39.3901367188],"type":"Point"}
}