{
  "type": "Feature",
  "properties": {
    "iso:country":"ES",
    "sg:address":"Vena Panedes, 45",
    "sg:city":"Veinat De Panedes",
    "sg:orig_category":"Edici\u00d3n De Diarios, Revistas, Boletines",
    "sg:phone":"+34 972 83 14 52",
    "sg:postcode":"17240",
    "sg:province":"Girona",
    "wof:name":"Gestio I Promocio Editorial S.l.",
    "wof:placetype":"venue"
},
  "geometry": {"coordinates":[2.892385006,41.8299255371],"type":"Point"}
}