{
  "type": "Feature",
  "properties": {
    "iso:country":"ES",
    "sg:address":"Calle de Antonio Machado, S/n",
    "sg:city":"Carmona",
    "sg:orig_category":"Asociaciones, Organismos Culturales Y Socioeducativos",
    "sg:phone":"+34 954 14 90 37",
    "sg:postcode":"41410",
    "sg:province":"Sevilla",
    "wof:name":"Casa De Cantabria",
    "wof:placetype":"venue"
},
  "geometry": {"coordinates":[-5.6462259293,37.4658851624],"type":"Point"}
}