{
  "type": "Feature",
  "properties": {
    "addr:full":"Calle de Severo Ochoa, S/n Gijon Asturias 33210",
    "addr:housenumber":"s",
    "addr:postcode":"33210",
    "addr:street":"Calle De Severo Ochoa;/ N",
    "iso:country":"ES",
    "sg:address":"Calle de Severo Ochoa, S/n",
    "sg:city":"Gijon",
    "sg:orig_category":"Asistencia Y Seguros De Automovilistas Y Turistas",
    "sg:phone":"+34 985 39 21 11",
    "sg:postcode":"33210",
    "sg:province":"Asturias",
    "wof:name":"Asistencia Automovilistica S.l.",
    "wof:placetype":"venue"
},
  "geometry": {"coordinates":[-5.6758341789,43.5271224976],"type":"Point"}
}