{
  "type": "Feature",
  "properties": {
    "iso:country":"ES",
    "sg:address":"Av Glories Catalanes (les), 100",
    "sg:city":"Terrassa",
    "sg:orig_category":"Porcelanas, Azulejos (fabricaci\u00d3n, Al Por Mayor)",
    "sg:phone":"+34 937 83 38 94",
    "sg:postcode":"08223",
    "sg:province":"Barcelona",
    "wof:name":"Azulejos Terrassa S.l",
    "wof:placetype":"venue"
},
  "geometry": {"coordinates":[2.0266098976,41.5540618896],"type":"Point"}
}