{
  "type": "Feature",
  "properties": {
    "addr:full":"Calle de Luis Braille, 55 Valencia Alcantara C\u00e1ceres 10500",
    "addr:housenumber":"55",
    "addr:postcode":"10500",
    "addr:street":"Calle De Luis Braille;Alcantara Ca\u0301Ceres",
    "iso:country":"ES",
    "sg:address":"Calle de Luis Braille, 55",
    "sg:city":"Valencia Alcantara",
    "sg:orig_category":"Laboratorios Farmac\u00c9uticos",
    "sg:phone":"+34 927 58 06 57",
    "sg:postcode":"10500",
    "sg:province":"C\u00e1ceres",
    "wof:name":"Navas Aranguren Guillermo",
    "wof:placetype":"venue"
},
  "geometry": {"coordinates":[-7.2480812073,39.4039306641],"type":"Point"}
}