{
  "type": "Feature",
  "properties": {
    "addr:full":"Ctra. Portugal, S/n Brozas C\u00e1ceres 10950",
    "addr:housenumber":"s / n",
    "addr:postcode":"10950",
    "addr:street":"Ctra. Portugal;Ca\u0301Ceres",
    "iso:country":"ES",
    "sg:address":"Ctra. Portugal, S/n",
    "sg:city":"Brozas",
    "sg:orig_category":"Muebles, Minoristas",
    "sg:phone":"+34 927 39 53 39",
    "sg:postcode":"10950",
    "sg:province":"C\u00e1ceres",
    "wof:name":"Fernandez Romero Joaquin",
    "wof:placetype":"venue"
},
  "geometry": {"coordinates":[-6.7763600349,39.6160469055],"type":"Point"}
}