{
  "type": "Feature",
  "properties": {
    "iso:country":"ES",
    "sg:address":"Virgen Refugio (pi Corredor Autovia), 9",
    "sg:city":"Dos Hermanas",
    "sg:orig_category":"Muebles Y Accesorios Para Cocinas Y Cuartos De Ba\u00d1o (al Por Menor)",
    "sg:phone":"+34 954 72 34 58",
    "sg:postcode":"41700",
    "sg:province":"Sevilla",
    "wof:name":"Cojo Alvarez Dativo",
    "wof:placetype":"venue"
},
  "geometry": {"coordinates":[-5.9321041107,37.2702026367],"type":"Point"}
}