{
  "type": "Feature",
  "properties": {
    "addr:full":"Calle de Charca, 48 Arroyo Luz C\u00e1ceres 10900",
    "addr:housenumber":"48",
    "addr:postcode":"10900",
    "addr:street":"Calle De Charca;Arroyo Luz Ca\u0301Ceres",
    "iso:country":"ES",
    "sg:address":"Calle de Charca, 48",
    "sg:city":"Arroyo Luz",
    "sg:orig_category":"Negocio De Materiales De Construcci\u00d3n",
    "sg:phone":"+34 927 27 16 88",
    "sg:postcode":"10900",
    "sg:province":"C\u00e1ceres",
    "wof:name":"Higuero Higuero Jeronimo",
    "wof:placetype":"venue"
},
  "geometry": {"coordinates":[-6.5849909782,39.4885635376],"type":"Point"}
}