{
  "type": "Feature",
  "properties": {
    "iso:country":"ES",
    "sg:address":"Rond Nelle, S/n",
    "sg:city":"Coru\u00d1a",
    "sg:orig_category":"Agencias Y Agentes Comerciales, Representantes",
    "sg:phone":"+34 981 26 55 88",
    "sg:postcode":"15010",
    "sg:province":"La Coru\u00f1a",
    "wof:name":"Nogueira Rodriguez Luis",
    "wof:placetype":"venue"
},
  "geometry": {"coordinates":[-8.4184589386,43.364654541],"type":"Point"}
}