{
  "type": "Feature",
  "properties": {
    "addr:full":"Olaso Kalea, 25 Elgoibar Guip\u00f9zcoa 20870",
    "addr:housenumber":"25",
    "addr:postcode":"20870",
    "addr:street":"Olaso Kalea;Guipu\u0300Zcoa",
    "iso:country":"ES",
    "sg:address":"Olaso Kalea, 25",
    "sg:city":"Elgoibar",
    "sg:orig_category":"Agentes, Concesionarios Y Sucursales De Veh\u00cdculos",
    "sg:phone":"+34 943 74 74 17",
    "sg:postcode":"20870",
    "sg:province":"Guip\u00f9zcoa",
    "wof:name":"Euskoauto 2003 S.l.",
    "wof:placetype":"venue"
},
  "geometry": {"coordinates":[-2.4240469933,43.2056159973],"type":"Point"}
}