{
  "type": "Feature",
  "properties": {
    "addr:full":"Calle de Norte, 7 Moraleja Enmedio Madrid 28950",
    "addr:housenumber":"7",
    "addr:postcode":"28950",
    "addr:street":"Calle De Norte",
    "iso:country":"ES",
    "sg:address":"Calle de Norte, 7",
    "sg:city":"Moraleja Enmedio",
    "sg:orig_category":"Molduras, Junquillos, Listones Y Molduras Perforadas",
    "sg:phone":"+34 916 09 43 64",
    "sg:postcode":"28950",
    "sg:province":"Madrid",
    "wof:name":"Andujar Aliaga Antonio",
    "wof:placetype":"venue"
},
  "geometry": {"coordinates":[-3.8498654366,40.2621383667],"type":"Point"}
}