{
  "type": "Feature",
  "properties": {
    "addr:full":"Carr Felip Ii, 31 Badalona Barcelona 08917",
    "addr:housenumber":"31",
    "addr:postcode":"08917",
    "addr:street":"Carr Felip Ii",
    "iso:country":"ES",
    "sg:address":"Carr Felip Ii, 31",
    "sg:city":"Badalona",
    "sg:classifiers":[
        {
            "category":"Personal",
            "subcategory":"Barber",
            "type":"Services"
        }
    ],
    "sg:phone":"+34 933 97 46 69",
    "sg:postcode":"08917",
    "sg:province":"Barcelona",
    "sg:tags":[
        "caballeros",
        "de",
        "peluqueros"
    ],
    "wof:name":"Del Moral Dominguez Eduardo",
    "wof:placetype":"venue"
},
  "geometry": {"coordinates":[2.2356081009,41.4526290894],"type":"Point"}
}