{
  "type": "Feature",
  "properties": {
    "addr:full":"Calle de Sollube, 9 Kurtzea Vizcaya 48960",
    "addr:housenumber":"9",
    "addr:postcode":"48960",
    "addr:street":"Calle De Sollube",
    "iso:country":"ES",
    "sg:address":"Calle de Sollube, 9",
    "sg:city":"Kurtzea",
    "sg:orig_category":"Contenedores (mercanc\u00cdas)",
    "sg:phone":"+34 944 56 52 09",
    "sg:postcode":"48960",
    "sg:province":"Vizcaya",
    "wof:name":"Uribe Ruesga Maria Teresa",
    "wof:placetype":"venue"
},
  "geometry": {"coordinates":[-2.8416860104,43.2316360474],"type":"Point"}
}