{
  "type": "Feature",
  "properties": {
    "iso:country":"ES",
    "sg:address":"Calle de Miguel Fluiters, 22",
    "sg:city":"Guadalajara",
    "sg:orig_category":"Ropa De Hogar (al Por Menor)",
    "sg:phone":"+34 949 21 33 53",
    "sg:postcode":"19001",
    "sg:province":"Guadalajara",
    "wof:name":"Tejidos Mayjo C.b.",
    "wof:placetype":"venue"
},
  "geometry": {"coordinates":[-3.1673638821,40.6349525452],"type":"Point"}
}