{
  "type": "Feature",
  "properties": {
    "iso:country":"ES",
    "sg:address":"O Telleiro, 8",
    "sg:city":"Telleiro",
    "sg:orig_category":"Alimentaci\u00d3n General (al Por Mayor)",
    "sg:phone":"+34 986 35 11 04",
    "sg:postcode":"36378",
    "sg:province":"Pontevedra",
    "wof:name":"Bugallo Lea Emilio",
    "wof:placetype":"venue"
},
  "geometry": {"coordinates":[-8.8027610779,42.109413147],"type":"Point"}
}