{
  "type": "Feature",
  "properties": {
    "iso:country":"ES",
    "sg:address":"Calle de Capitan Mendizabal, 16",
    "sg:city":"Santurtzi",
    "sg:orig_category":"Molduras, Junquillos, Listones Y Molduras Perforadas",
    "sg:phone":"+34 944 83 97 79",
    "sg:postcode":"48980",
    "sg:province":"Vizcaya",
    "wof:name":"Miren Nekane Martin Rekalde",
    "wof:placetype":"venue"
},
  "geometry": {"coordinates":[-3.034209013,43.3313941956],"type":"Point"}
}