{
  "type": "Feature",
  "properties": {
    "iso:country":"ES",
    "sg:address":"Calle de Do\u00d1a Clara, 81",
    "sg:city":"Ricla",
    "sg:orig_category":"Poller\u00cda Y Caza (al Por Menor)",
    "sg:phone":"+34 976 60 60 07",
    "sg:postcode":"50270",
    "sg:province":"Zaragoza",
    "wof:name":"Granja Bailon S.l.",
    "wof:placetype":"venue"
},
  "geometry": {"coordinates":[-1.4018906355,41.5079994202],"type":"Point"}
}