{
  "type": "Feature",
  "properties": {
    "iso:country":"ES",
    "sg:address":"Calle de Colon De Larreategui, 33",
    "sg:city":"Bilbao",
    "sg:orig_category":"Molduras, Junquillos, Listones Y Molduras Perforadas",
    "sg:phone":"+34 944 24 72 55",
    "sg:postcode":"48009",
    "sg:province":"Vizcaya",
    "wof:name":"Garcia Ausejo Javier",
    "wof:placetype":"venue"
},
  "geometry": {"coordinates":[-2.9323043823,43.2634925842],"type":"Point"}
}