{
  "type": "Feature",
  "properties": {
    "iso:country":"ES",
    "sg:address":"Jose Viudes Molla, S/n",
    "sg:city":"Huercal-overa",
    "sg:orig_category":"Rectificaci\u00d3n, Mecanizado, Fresado",
    "sg:phone":"+34 950 47 01 87",
    "sg:postcode":"04600",
    "sg:province":"Almer\u00eda",
    "wof:name":"Salvador Perez Marcos",
    "wof:placetype":"venue"
},
  "geometry": {"coordinates":[-1.9656490088,37.4148139954],"type":"Point"}
}