{
  "type": "Feature",
  "properties": {
    "iso:country":"ES",
    "sg:address":"Labeaga Kalea, 51",
    "sg:city":"Urretxu",
    "sg:orig_category":"Perfumer\u00cda (al Por Menor)",
    "sg:phone":"+34 943 53 48 56",
    "sg:postcode":"20700",
    "sg:province":"Guip\u00f9zcoa",
    "wof:name":"Ione Miren Igartua (igaro)",
    "wof:placetype":"venue"
},
  "geometry": {"coordinates":[-2.3200209141,43.0886154175],"type":"Point"}
}