{
  "type": "Feature",
  "properties": {
    "iso:country":"ES",
    "sg:address":"Plaz Moreal (el), 7",
    "sg:city":"Cordoba",
    "sg:classifiers":[
        {
            "category":"Personal",
            "subcategory":"Barber",
            "type":"Services"
        }
    ],
    "sg:phone":"+34 957 75 18 87",
    "sg:postcode":"14010",
    "sg:province":"C\u00f3rdoba",
    "sg:tags":[
        "caballeros",
        "de",
        "peluqueros"
    ],
    "wof:name":"Granados Garrido Jesus",
    "wof:placetype":"venue"
},
  "geometry": {"coordinates":[-4.6037230492,37.84633255],"type":"Point"}
}