{
  "type": "Feature",
  "properties": {
    "iso:country":"ES",
    "sg:address":"Calle de Maria De Molina, 3",
    "sg:city":"Palencia",
    "sg:orig_category":"Decoradores",
    "sg:phone":"+34 979 72 26 20",
    "sg:postcode":"34002",
    "sg:province":"Palencia",
    "wof:name":"Conde Martin Jose Luis",
    "wof:placetype":"venue"
},
  "geometry": {"coordinates":[-4.5264978409,42.0037574768],"type":"Point"}
}