{
  "type": "Feature",
  "properties": {
    "addr:full":"Calle de Pedralba, 1 Benaguasil Valencia 46180",
    "addr:housenumber":"1",
    "addr:postcode":"46180",
    "addr:street":"Calle De Pedralba",
    "iso:country":"ES",
    "sg:address":"Calle de Pedralba, 1",
    "sg:city":"Benaguasil",
    "sg:orig_category":"Deportes N\u00c1uticos, Acu\u00c1ticos Y Subacu\u00c1ticos: Art\u00cdculos Y Equipo (al Por Menor)",
    "sg:phone":"+34 962 73 04 91",
    "sg:postcode":"46180",
    "sg:province":"Valencia",
    "wof:name":"Nelan S. A.",
    "wof:placetype":"venue"
},
  "geometry": {"coordinates":[-0.5875390172,39.5956382751],"type":"Point"}
}