{
  "type": "Feature",
  "properties": {
    "iso:country":"ES",
    "sg:address":"Ru, 16",
    "sg:city":"Ru",
    "sg:orig_category":"Turismo: Lugares, Circuitos Y Curiosidades",
    "sg:phone":"+34 981 77 74 05",
    "sg:postcode":"15807",
    "sg:province":"La Coru\u00f1a",
    "wof:name":"Rutuser S.l.u.",
    "wof:placetype":"venue"
},
  "geometry": {"coordinates":[-8.0653038025,42.9738960266],"type":"Point"}
}