{
  "type": "Feature",
  "properties": {
    "addr:full":"Calle de Bomberos Voluntarios, S/n Lerma Burgos 09340",
    "addr:housenumber":"s / n",
    "addr:postcode":"09340",
    "addr:street":"Calle",
    "iso:country":"ES",
    "sg:address":"Calle de Bomberos Voluntarios, S/n",
    "sg:city":"Lerma",
    "sg:orig_category":"Productos Alimentarios",
    "sg:phone":"+34 947 17 00 76",
    "sg:postcode":"09340",
    "sg:province":"Burgos",
    "wof:name":"Ayuntamiento De Lerma",
    "wof:placetype":"venue"
},
  "geometry": {"coordinates":[-3.7333536148,42.0077514648],"type":"Point"}
}