{
  "type": "Feature",
  "properties": {
    "addr:full":"Calle de Manolito Franco, 9 Lucena C\u00f3rdoba 14900",
    "addr:housenumber":"9",
    "addr:postcode":"14900",
    "addr:street":"Calle De Manolito Franco",
    "iso:country":"ES",
    "sg:address":"Calle de Manolito Franco, 9",
    "sg:city":"Lucena",
    "sg:orig_category":"Muebles",
    "sg:phone":"+34 957 51 63 76",
    "sg:postcode":"14900",
    "sg:province":"C\u00f3rdoba",
    "wof:name":"Ibersofa S.l.",
    "wof:placetype":"venue"
},
  "geometry": {"coordinates":[-4.48624897,37.4152908325],"type":"Point"}
}