{
  "type": "Feature",
  "properties": {
    "addr:full":"Calle de Cervantes, 17 Villaralbo Zamora 49159",
    "addr:housenumber":"17",
    "addr:postcode":"49159",
    "addr:street":"Calle De Cervantes",
    "iso:country":"ES",
    "sg:address":"Calle de Cervantes, 17",
    "sg:city":"Villaralbo",
    "sg:orig_category":"Empresas De Carpinter\u00cda De Madera",
    "sg:phone":"+34 980 53 97 09",
    "sg:postcode":"49159",
    "sg:province":"Zamora",
    "wof:name":"Fabricados Villaralbo S Coop Ltda",
    "wof:placetype":"venue"
},
  "geometry": {"coordinates":[-5.6875314713,41.490776062],"type":"Point"}
}