{
  "type": "Feature",
  "properties": {
    "iso:country":"ES",
    "sg:address":"Rua San Bartolome, S/n",
    "sg:city":"Pobra Trives",
    "sg:orig_category":"Centros Empresariales",
    "sg:phone":"+34 988 33 08 84",
    "sg:postcode":"32780",
    "sg:province":"Ourense",
    "wof:name":"Asociacion De Empresarios De La Comarca De Trives",
    "wof:placetype":"venue"
},
  "geometry": {"coordinates":[-7.2539000511,42.3393058777],"type":"Point"}
}