{
  "type": "Feature",
  "properties": {
    "iso:country":"ES",
    "sg:address":"Carrer de Carme, 34",
    "sg:city":"Barcelona",
    "sg:orig_category":"Agencias De Viajes",
    "sg:phone":"+34 933 01 82 70",
    "sg:postcode":"08001",
    "sg:province":"Barcelona",
    "wof:name":"Huma Travel S.l.",
    "wof:placetype":"venue"
},
  "geometry": {"coordinates":[2.1698999405,41.382232666],"type":"Point"}
}