{
  "type": "Feature",
  "properties": {
    "iso:country":"ES",
    "sg:address":"Calle de Alberto Aguilera, 50",
    "sg:city":"Madrid",
    "sg:orig_category":"Ense\u00d1anza: Idiomas",
    "sg:phone":"+34 915 59 45 53",
    "sg:postcode":"28015",
    "sg:province":"Madrid",
    "wof:name":"Fyne Centro De Idiomas S.l.",
    "wof:placetype":"venue"
},
  "geometry": {"coordinates":[-3.7129273415,40.4303588867],"type":"Point"}
}