{
  "type": "Feature",
  "properties": {
    "addr:full":"Calle de Mugica Y Butron, 5 Bilbao Vizcaya 48007",
    "addr:housenumber":"5",
    "addr:postcode":"48007",
    "addr:street":"Calle De Mugica Y Butron",
    "iso:country":"ES",
    "sg:address":"Calle de Mugica Y Butron, 5",
    "sg:city":"Bilbao",
    "sg:orig_category":"Suministros Para Carrocer\u00cdas",
    "sg:phone":"+34 944 01 44 18",
    "sg:postcode":"48007",
    "sg:province":"Vizcaya",
    "wof:name":"Benito Feijoo Agregan",
    "wof:placetype":"venue"
},
  "geometry": {"coordinates":[-2.9271090031,43.2680931091],"type":"Point"}
}