{
  "type": "Feature",
  "properties": {
    "addr:full":"Avda Menendez Pelayo, 43 Sevilla Sevilla 41003",
    "addr:housenumber":"43",
    "addr:postcode":"41003",
    "addr:street":"Avda Menendez Pelayo",
    "iso:country":"ES",
    "sg:address":"Avda Menendez Pelayo, 43",
    "sg:city":"Sevilla",
    "sg:orig_category":"Asociaciones Y Clubs Deportivos",
    "sg:phone":"+34 954 53 16 46",
    "sg:postcode":"41003",
    "sg:province":"Sevilla",
    "wof:name":"Sevilla Surf S.l",
    "wof:placetype":"venue"
},
  "geometry": {"coordinates":[-5.9853987694,37.3869018555],"type":"Point"}
}