{
  "type": "Feature",
  "properties": {
    "addr:full":"Pg Sant Gervasi, 87 Barcelona Barcelona 08022",
    "addr:housenumber":"87",
    "addr:postcode":"08022",
    "addr:street":"Pg Sant Gervasi",
    "iso:country":"ES",
    "sg:address":"Pg Sant Gervasi, 87",
    "sg:city":"Barcelona",
    "sg:orig_category":"Electricidad: Instaladores",
    "sg:phone":"+34 934 18 56 74",
    "sg:postcode":"08022",
    "sg:province":"Barcelona",
    "wof:name":"Instalaciones Mei S.l.",
    "wof:placetype":"venue"
},
  "geometry": {"coordinates":[2.1375880241,41.4135093689],"type":"Point"}
}