{
  "type": "Feature",
  "properties": {
    "addr:full":"Av Roma, 113 Barcelona Barcelona 08011",
    "addr:housenumber":"113",
    "addr:postcode":"08011",
    "addr:street":"Av Roma",
    "iso:country":"ES",
    "sg:address":"Av Roma, 113",
    "sg:city":"Barcelona",
    "sg:orig_category":"Aparatos De Medida, Control, Regulaci\u00d3n Y Detecci\u00d3n",
    "sg:phone":"+34 934 53 83 69",
    "sg:postcode":"08011",
    "sg:province":"Barcelona",
    "wof:name":"Campmany Pascual Juan",
    "wof:placetype":"venue"
},
  "geometry": {"coordinates":[2.1543419361,41.3856163025],"type":"Point"}
}