{
  "type": "Feature",
  "properties": {
    "iso:country":"ES",
    "sg:address":"Ademuz, 14",
    "sg:city":"S. Francisco",
    "sg:orig_category":"Suministros Y Materiales Industriales",
    "sg:phone":"+34 961 54 12 86",
    "sg:postcode":"46940",
    "sg:province":"Valencia",
    "wof:name":"Ge Plastics Espa\u00d1a Sociedad Comanditaria Por Acciones",
    "wof:placetype":"venue"
},
  "geometry": {"coordinates":[-0.461488992,39.4922943115],"type":"Point"}
}