{
  "type": "Feature",
  "properties": {
    "iso:country":"ES",
    "sg:address":"Carr Ramon Ramia, 5",
    "sg:city":"Coves Vinroma",
    "sg:orig_category":"Artes Gr\u00c1ficas, Artes Pl\u00c1sticas (curso)",
    "sg:phone":"+34 964 42 62 83",
    "sg:postcode":"12185",
    "sg:province":"Castell\u00f3n",
    "wof:name":"Bernus Mujal Barbara",
    "wof:placetype":"venue"
},
  "geometry": {"coordinates":[-0.0456800014,39.9851417542],"type":"Point"}
}