{
  "type": "Feature",
  "properties": {
    "addr:full":"Carr Ter Vell, 22 Estartit Girona 17258",
    "addr:housenumber":"22",
    "addr:postcode":"17258",
    "addr:street":"Carr Ter Vell",
    "iso:country":"ES",
    "sg:address":"Carr Ter Vell, 22",
    "sg:city":"Estartit",
    "sg:classifiers":[
        {
            "category":"Recreation",
            "type":"Entertainment"
        }
    ],
    "sg:phone":"+34 972 75 01 25",
    "sg:postcode":"17258",
    "sg:province":"Girona",
    "sg:tags":[
        "caza",
        "pr\u00c1ctica",
        "la",
        "de",
        "pesca",
        "y"
    ],
    "wof:name":"Cofradia De Pescadores",
    "wof:placetype":"venue"
},
  "geometry": {"coordinates":[3.1995449066,42.053730011],"type":"Point"}
}