{
  "type": "Feature",
  "properties": {
    "addr:full":"Cmno Ronda (de), 30 Granada Granada 18004",
    "addr:housenumber":"30",
    "addr:postcode":"18004",
    "addr:street":"Cmno Ronda De",
    "iso:country":"ES",
    "sg:address":"Cmno Ronda (de), 30",
    "sg:city":"Granada",
    "sg:orig_category":"Art\u00cdculos Para Fumadores (al Por Menor)",
    "sg:phone":"+34 958 25 19 83",
    "sg:postcode":"18004",
    "sg:province":"Granada",
    "wof:name":"Sevilla Molina Maria Del Pilar",
    "wof:placetype":"venue"
},
  "geometry": {"coordinates":[-3.603153944,37.1660079956],"type":"Point"}
}