{
  "type": "Feature",
  "properties": {
    "addr:full":"Calle de Martin Belda, 56 Cabra C\u00f3rdoba 14940",
    "addr:housenumber":"56",
    "addr:postcode":"14940",
    "addr:street":"Calle De Martin Belda;Co\u0301Rdoba",
    "iso:country":"ES",
    "sg:address":"Calle de Martin Belda, 56",
    "sg:city":"Cabra",
    "sg:orig_category":"Ingeniero",
    "sg:phone":"+34 957 52 32 39",
    "sg:postcode":"14940",
    "sg:province":"C\u00f3rdoba",
    "wof:name":"Gallardo Jimenez Antonio",
    "wof:placetype":"venue"
},
  "geometry": {"coordinates":[-4.4410028458,37.4722518921],"type":"Point"}
}