{
  "type": "Feature",
  "properties": {
    "addr:full":"Calle de Doctor Calatayud, S/n Moraira Alicante 03724",
    "addr:housenumber":"s / n",
    "addr:postcode":"03724",
    "addr:street":"Calle De Doctor Calatayud",
    "iso:country":"ES",
    "sg:address":"Calle de Doctor Calatayud, S/n",
    "sg:city":"Moraira",
    "sg:orig_category":"Supermercados Y Hipermercados",
    "sg:phone":"+34 965 74 40 34",
    "sg:postcode":"03724",
    "sg:province":"Alicante",
    "wof:name":"Bertomeu Ferrer Jaime",
    "wof:placetype":"venue"
},
  "geometry": {"coordinates":[0.1348820031,38.6875991821],"type":"Point"}
}