{
  "type": "Feature",
  "properties": {
    "iso:country":"ES",
    "sg:address":"Avda Ejercito (del), 20",
    "sg:city":"Sabi\u00f1anigo",
    "sg:orig_category":"Reposter\u00cdas",
    "sg:phone":"+34 974 48 33 64",
    "sg:postcode":"22600",
    "sg:province":"Huesca",
    "wof:name":"Martinez Gonzalez Jose Luis",
    "wof:placetype":"venue"
},
  "geometry": {"coordinates":[-0.3569079936,42.5084495544],"type":"Point"}
}