{
  "type": "Feature",
  "properties": {
    "addr:full":"Calle de Guisasola Juan, 5 Bilbao Vizcaya 48004",
    "addr:housenumber":"5",
    "addr:postcode":"48004",
    "addr:street":"Calle De Guisasola Juan",
    "iso:country":"ES",
    "sg:address":"Calle de Guisasola Juan, 5",
    "sg:city":"Bilbao",
    "sg:orig_category":"Comercio De Piezas De Recambio Y De Accesorios De Veh\u00cdculos, Veh\u00cdculos Industriales",
    "sg:phone":"+34 944 11 19 03",
    "sg:postcode":"48004",
    "sg:province":"Vizcaya",
    "wof:name":"Autoexclusivas Bolueta, Juan Narbaiza Santamaria",
    "wof:placetype":"venue"
},
  "geometry": {"coordinates":[-2.9092381001,43.248134613],"type":"Point"}
}