{
  "type": "Feature",
  "properties": {
    "addr:full":"Carrer de Frederic Soler, 89 Cornella Llobregat Barcelona 08940",
    "addr:housenumber":"89",
    "addr:postcode":"08940",
    "addr:street":"Carrer De Frederic Soler",
    "iso:country":"ES",
    "sg:address":"Carrer de Frederic Soler, 89",
    "sg:city":"Cornella Llobregat",
    "sg:orig_category":"Guarder\u00cdas",
    "sg:phone":"+34 933 75 25 55",
    "sg:postcode":"08940",
    "sg:province":"Barcelona",
    "wof:name":"Medina Idalgo Lidia",
    "wof:placetype":"venue"
},
  "geometry": {"coordinates":[2.0777740479,41.3646621704],"type":"Point"}
}