{
  "type": "Feature",
  "properties": {
    "iso:country":"ES",
    "sg:address":"Calle de Valdesangil, 26",
    "sg:city":"Madrid",
    "sg:orig_category":"Estancos",
    "sg:phone":"+34 913 73 67 67",
    "sg:postcode":"28039",
    "sg:province":"Madrid",
    "wof:name":"Sanz Montero Bernabe",
    "wof:placetype":"venue"
},
  "geometry": {"coordinates":[-3.7170269489,40.468082428],"type":"Point"}
}