{
  "type": "Feature",
  "properties": {
    "addr:full":"Plaz Constitucion, 5 Almendralejo Badajoz 06200",
    "addr:housenumber":"5",
    "addr:postcode":"06200",
    "addr:street":"Constitucion",
    "iso:country":"ES",
    "sg:address":"Plaz Constitucion, 5",
    "sg:city":"Almendralejo",
    "sg:orig_category":"Inmobiliaria (agencias)",
    "sg:phone":"+34 924 67 00 98",
    "sg:postcode":"06200",
    "sg:province":"Badajoz",
    "wof:name":"Asuar Monge Julio",
    "wof:placetype":"venue"
},
  "geometry": {"coordinates":[-6.4086847305,38.6828994751],"type":"Point"}
}