{
  "type": "Feature",
  "properties": {
    "iso:country":"ES",
    "sg:address":"Avda San Miguel, 1",
    "sg:city":"Chinchilla Monte-aragon",
    "sg:orig_category":"Empresas De Carpinter\u00cda Met\u00c1lica",
    "sg:phone":"+34 967 26 10 75",
    "sg:postcode":"02520",
    "sg:province":"Albacete",
    "wof:name":"Piqueras Sanchez Antonio",
    "wof:placetype":"venue"
},
  "geometry": {"coordinates":[-1.7232949734,38.9209251404],"type":"Point"}
}