{
  "type": "Feature",
  "properties": {
    "addr:full":"Ctra Circunvalacion, 44 Villacarrillo Ja\u00e9n 23300",
    "addr:housenumber":"44",
    "addr:postcode":"23300",
    "addr:street":"Ctra Circunvalacion;Jae\u0301N",
    "iso:country":"ES",
    "sg:address":"Ctra Circunvalacion, 44",
    "sg:city":"Villacarrillo",
    "sg:orig_category":"Ense\u00d1anza: Comercio, Gesti\u00d3n, Inform\u00c1tica",
    "sg:phone":"+34 953 44 23 86",
    "sg:postcode":"23300",
    "sg:province":"Ja\u00e9n",
    "sg:website":"www.aserinfisco.com",
    "wof:name":"Aserincisco S.l.",
    "wof:placetype":"venue"
},
  "geometry": {"coordinates":[-3.0786762238,38.1193847656],"type":"Point"}
}