{
  "type": "Feature",
  "properties": {
    "addr:full":"Pg Sant Joan, 111 Barcelona Barcelona 08037",
    "addr:housenumber":"111",
    "addr:postcode":"08037",
    "addr:street":"Pg Sant Joan",
    "iso:country":"ES",
    "sg:address":"Pg Sant Joan, 111",
    "sg:city":"Barcelona",
    "sg:orig_category":"Agencias De Viajes",
    "sg:phone":"+34 934 59 05 58",
    "sg:postcode":"08037",
    "sg:province":"Barcelona",
    "sg:website":"www.marsans.es",
    "wof:name":"Viajes Marsans S.a.",
    "wof:placetype":"venue"
},
  "geometry": {"coordinates":[2.1684930325,41.3999671936],"type":"Point"}
}