{
  "type": "Feature",
  "properties": {
    "addr:full":"Calle de Alcalde Francisco Orejas, 2 Aviles Asturias 33401",
    "addr:housenumber":"2",
    "addr:postcode":"33401",
    "addr:street":"Calle De Alcalde Francisco Orejas",
    "iso:country":"ES",
    "sg:address":"Calle de Alcalde Francisco Orejas, 2",
    "sg:city":"Aviles",
    "sg:orig_category":"M\u00c9dicos: Endocrinolog\u00cda Y Metabolismo",
    "sg:phone":"+34 985 52 20 22",
    "sg:postcode":"33401",
    "sg:province":"Asturias",
    "wof:name":"Fau Cubero Carmen",
    "wof:placetype":"venue"
},
  "geometry": {"coordinates":[-5.9277076721,43.5577278137],"type":"Point"}
}