{
  "type": "Feature",
  "properties": {
    "iso:country":"ES",
    "sg:address":"Carrer de Verge Del Carme, 16",
    "sg:city":"Martorell",
    "sg:orig_category":"Ropa Para Ni\u00d1os (al Por Menor)",
    "sg:phone":"+34 937 76 50 50",
    "sg:postcode":"08760",
    "sg:province":"Barcelona",
    "wof:name":"Piratas Martorell S.c.p.",
    "wof:placetype":"venue"
},
  "geometry": {"coordinates":[1.918964982,41.4763412476],"type":"Point"}
}