{
  "type": "Feature",
  "properties": {
    "addr:full":"Calle de Centro, 14 Vencillon Huesca 22549",
    "addr:postcode":"22549",
    "addr:street":"Calle De Centro;Vencillon",
    "iso:country":"ES",
    "sg:address":"Calle de Centro, 14",
    "sg:city":"Vencillon",
    "sg:orig_category":"Alimentaci\u00d3n General (al Por Mayor)",
    "sg:phone":"+34 974 43 42 47",
    "sg:postcode":"22549",
    "sg:province":"Huesca",
    "wof:name":"Cooperativa Agricola Ganadera",
    "wof:placetype":"venue"
},
  "geometry": {"coordinates":[0.3230279982,41.7041931152],"type":"Point"}
}