{
  "type": "Feature",
  "properties": {
    "iso:country":"ES",
    "sg:address":"Calle de Cascante, 5",
    "sg:city":"Agreda",
    "sg:orig_category":"Confecci\u00d3n De Trajes Para Se\u00d1oras",
    "sg:phone":"+34 976 64 69 39",
    "sg:postcode":"42100",
    "sg:province":"Soria",
    "wof:name":"Ruiz Hernandez Lourdes",
    "wof:placetype":"venue"
},
  "geometry": {"coordinates":[-1.9222942591,41.8541412354],"type":"Point"}
}