{
  "type": "Feature",
  "properties": {
    "addr:full":"Carrer de Pineda, 28 Terrassa Barcelona 08226",
    "addr:housenumber":"28",
    "addr:postcode":"08226",
    "addr:street":"Carrer De Pineda",
    "iso:country":"ES",
    "sg:address":"Carrer de Pineda, 28",
    "sg:city":"Terrassa",
    "sg:orig_category":"M\u00c9dicos: Naturistas",
    "sg:phone":"+34 937 83 82 12",
    "sg:postcode":"08226",
    "sg:province":"Barcelona",
    "wof:name":"Escamilla Quintana Jose",
    "wof:placetype":"venue"
},
  "geometry": {"coordinates":[2.0352590084,41.5688743591],"type":"Point"}
}