{
  "type": "Feature",
  "properties": {
    "addr:full":"Calle de Paloma (de La), 17 Algete Madrid 28110",
    "addr:housenumber":"17",
    "addr:postcode":"28110",
    "addr:street":"Calle De Paloma De La",
    "iso:country":"ES",
    "sg:address":"Calle de Paloma (de La), 17",
    "sg:city":"Algete",
    "sg:orig_category":"Psic\u00d3logos",
    "sg:phone":"+34 916 29 09 10",
    "sg:postcode":"28110",
    "sg:province":"Madrid",
    "wof:name":"Alvaibaz S.l.",
    "wof:placetype":"venue"
},
  "geometry": {"coordinates":[-3.4980378151,40.5977592468],"type":"Point"}
}