{
  "type": "Feature",
  "properties": {
    "iso:country":"ES",
    "sg:address":"Calle de Amezti, 7",
    "sg:city":"Algorta",
    "sg:orig_category":"Mec\u00c1nico Del Autom\u00d3vil",
    "sg:phone":"+34 944 91 00 57",
    "sg:postcode":"48992",
    "sg:province":"Vizcaya",
    "wof:name":"Talleres Amesti S. A.",
    "wof:placetype":"venue"
},
  "geometry": {"coordinates":[-3.01040411,43.3494224548],"type":"Point"}
}