{
  "type": "Feature",
  "properties": {
    "addr:full":"Avda Doctor Federico Rubio Y Gali, 28 Madrid Madrid 28039",
    "addr:housenumber":"28",
    "addr:postcode":"madrid;28039",
    "addr:street":"Avda Doctor Federico Rubio Y Gali",
    "iso:country":"ES",
    "sg:address":"Avda Doctor Federico Rubio Y Gali, 28",
    "sg:city":"Madrid",
    "sg:orig_category":"Muebles Y Accesorios Para Cocinas Y Cuartos De Ba\u00d1o (al Por Menor)",
    "sg:phone":"+34 914 50 52 68",
    "sg:postcode":"28039",
    "sg:province":"Madrid",
    "wof:name":"Reimex Representaciones S.l.",
    "wof:placetype":"venue"
},
  "geometry": {"coordinates":[-3.7093520164,40.4506340027],"type":"Point"}
}