{
  "type": "Feature",
  "properties": {
    "addr:full":"Plaz Corazon De Jesus, 1 Villafranca De Los Barros Badajoz 06220",
    "addr:housenumber":"1",
    "addr:postcode":"06220",
    "addr:street":"Plaz Corazon;Jesus",
    "iso:country":"ES",
    "sg:address":"Plaz Corazon De Jesus, 1",
    "sg:city":"Villafranca De Los Barros",
    "sg:orig_category":"Cajas Para Embalar",
    "sg:phone":"+34 924 52 42 14",
    "sg:postcode":"06220",
    "sg:province":"Badajoz",
    "wof:name":"Caja Rural De Extremadura",
    "wof:placetype":"venue"
},
  "geometry": {"coordinates":[-6.3376989365,38.5625686646],"type":"Point"}
}