{
  "type": "Feature",
  "properties": {
    "addr:full":"Cm\u00d1o Romalla, 13 Vigo Pontevedra 36215",
    "addr:housenumber":"13",
    "addr:postcode":"36215",
    "addr:street":"Romalla",
    "iso:country":"ES",
    "sg:address":"Cm\u00d1o Romalla, 13",
    "sg:city":"Vigo",
    "sg:orig_category":"Molduras, Junquillos, Listones Y Molduras Perforadas",
    "sg:phone":"+34 986 37 51 55",
    "sg:postcode":"36215",
    "sg:province":"Pontevedra",
    "wof:name":"Garrido Dacu\u00f1a Enrique",
    "wof:placetype":"venue"
},
  "geometry": {"coordinates":[-8.6910247803,42.2370910645],"type":"Point"}
}