{
  "type": "Feature",
  "properties": {
    "addr:full":"Calle de Amanay, 22 Gran Tarajal Las Palmas 35620",
    "addr:housenumber":"22",
    "addr:postcode":"35620",
    "addr:street":"Calle De Amanay;Palmas",
    "iso:country":"ES",
    "sg:address":"Calle de Amanay, 22",
    "sg:city":"Gran Tarajal",
    "sg:orig_category":"Quincaller\u00cda (al Por Menor)",
    "sg:phone":"+34 928 16 50 09",
    "sg:postcode":"35620",
    "sg:province":"Las Palmas",
    "wof:name":"Rodriguez Galvan Olimpia",
    "wof:placetype":"venue"
},
  "geometry": {"coordinates":[-14.0203008652,28.2134685516],"type":"Point"}
}