{
  "type": "Feature",
  "properties": {
    "iso:country":"ES",
    "sg:address":"Calle de Pantxita Etxezarreta, 9",
    "sg:city":"Zumaia",
    "sg:orig_category":"Fabricaci\u00d3n De Art\u00cdculos Y Equipos Deportivos Y De Ocio",
    "sg:phone":"+34 943 14 34 13",
    "sg:postcode":"20750",
    "sg:province":"Guip\u00f9zcoa",
    "wof:name":"Maria Teresa Eizaguirre Uranga",
    "wof:placetype":"venue"
},
  "geometry": {"coordinates":[-2.2571640015,43.2947006226],"type":"Point"}
}