{
  "type": "Feature",
  "properties": {
    "iso:country":"ES",
    "sg:address":"Carrer de Closa De Mestres, 23",
    "sg:city":"Reus",
    "sg:orig_category":"Agentes, Concesionarios Y Sucursales De Veh\u00cdculos",
    "sg:phone":"+34 977 75 69 04",
    "sg:postcode":"43204",
    "sg:province":"Tarragona",
    "wof:name":"Vazquez Alejandre Antonio",
    "wof:placetype":"venue"
},
  "geometry": {"coordinates":[1.1112790108,41.1511497498],"type":"Point"}
}