{
  "type": "Feature",
  "properties": {
    "addr:full":"Calle de Aristoteles, 7 Madrid Madrid 28027",
    "addr:housenumber":"7",
    "addr:postcode":"madrid;28027",
    "addr:street":"Calle De Aristoteles",
    "iso:country":"ES",
    "sg:address":"Calle de Aristoteles, 7",
    "sg:city":"Madrid",
    "sg:orig_category":"Peluquer\u00cdas, Peluquer\u00cda Mixta",
    "sg:phone":"+34 914 05 20 42",
    "sg:postcode":"28027",
    "sg:province":"Madrid",
    "wof:name":"Martinez Toapanta Jorge Delfin",
    "wof:placetype":"venue"
},
  "geometry": {"coordinates":[-3.6516573429,40.4426841736],"type":"Point"}
}