{
  "type": "Feature",
  "properties": {
    "iso:country":"ES",
    "sg:address":"Calle de Juan De La Cosa, 14",
    "sg:city":"Castro Urdiales",
    "sg:orig_category":"Fabricaci\u00d3n De Art\u00cdculos Para Papeler\u00cdas",
    "sg:phone":"+34 942 86 33 48",
    "sg:postcode":"39700",
    "sg:province":"Cantabria",
    "wof:name":"Alcedo Alcedo Jose Maria",
    "wof:placetype":"venue"
},
  "geometry": {"coordinates":[-3.2206451893,43.3807411194],"type":"Point"}
}