{
  "type": "Feature",
  "properties": {
    "iso:country":"ES",
    "sg:address":"Ptge Puigmadrona, 1",
    "sg:city":"Barcelona",
    "sg:orig_category":"Agentes Generales De Seguros",
    "sg:phone":"+34 934 50 11 73",
    "sg:postcode":"08026",
    "sg:province":"Barcelona",
    "wof:name":"Miguel Batista Juan Carlos",
    "wof:placetype":"venue"
},
  "geometry": {"coordinates":[2.1854150295,41.4111671448],"type":"Point"}
}