{
  "type": "Feature",
  "properties": {
    "addr:full":"Mendelu Kalea, 25 Mugondo Guip\u00f9zcoa 20280",
    "addr:housenumber":"25",
    "addr:postcode":"20280",
    "addr:street":"Mendelu Kalea;Guipu\u0300Zcoa",
    "iso:country":"ES",
    "sg:address":"Mendelu Kalea, 25",
    "sg:city":"Mugondo",
    "sg:orig_category":"Alimentaci\u00d3n General (al Por Menor)",
    "sg:phone":"+34 943 64 33 99",
    "sg:postcode":"20280",
    "sg:province":"Guip\u00f9zcoa",
    "wof:name":"Gonzalez Martin Fernando",
    "wof:placetype":"venue"
},
  "geometry": {"coordinates":[-1.7936140299,43.3698997498],"type":"Point"}
}