{
  "type": "Feature",
  "properties": {
    "addr:full":"Avda. A. P. Maestre, 19 Cortegana Huelva 21230",
    "addr:housenumber":"19",
    "addr:postcode":"21230",
    "addr:street":"Avda. A. P. Maestre",
    "iso:country":"ES",
    "sg:address":"Avda. A. P. Maestre, 19",
    "sg:city":"Cortegana",
    "sg:orig_category":"Agricultores, Agricultores",
    "sg:phone":"+34 959 13 13 53",
    "sg:postcode":"21230",
    "sg:province":"Huelva",
    "wof:name":"Calidad Bellota S.cop.a.end.",
    "wof:placetype":"venue"
},
  "geometry": {"coordinates":[-6.8218269348,37.9156494141],"type":"Point"}
}