{
  "type": "Feature",
  "properties": {
    "addr:full":"Calle de Ezcurdia, 39 Gijon Asturias 33202",
    "addr:housenumber":"39",
    "addr:postcode":"33202",
    "addr:street":"Calle De Ezcurdia",
    "iso:country":"ES",
    "sg:address":"Calle de Ezcurdia, 39",
    "sg:city":"Gijon",
    "sg:orig_category":"M\u00c9dicos: Dermatolog\u00cda Y Venereolog\u00cda",
    "sg:phone":"+34 985 36 09 61",
    "sg:postcode":"33202",
    "sg:province":"Asturias",
    "wof:name":"San Martin Mu\u00f1iz Jose Carlos",
    "wof:placetype":"venue"
},
  "geometry": {"coordinates":[-5.6524682045,43.5391616821],"type":"Point"}
}