{
  "type": "Feature",
  "properties": {
    "addr:full":"Avda Escaleritas, 61 Palmas De Gran Canaria Las Palmas 35011",
    "addr:housenumber":"61",
    "addr:postcode":"35011",
    "addr:street":"Avda Escaleritas",
    "iso:country":"ES",
    "sg:address":"Avda Escaleritas, 61",
    "sg:city":"Palmas De Gran Canaria",
    "sg:orig_category":"Trabajos De Topograf\u00cda",
    "sg:phone":"+34 928 25 60 70",
    "sg:postcode":"35011",
    "sg:province":"Las Palmas",
    "wof:name":"Soto Paz Manuel",
    "wof:placetype":"venue"
},
  "geometry": {"coordinates":[-15.4386482239,28.1145210266],"type":"Point"}
}