{
  "type": "Feature",
  "properties": {
    "addr:full":"Carrer de Bogatell, 28 Montcada Centre Barcelona 08110",
    "addr:housenumber":"28",
    "addr:postcode":"08110",
    "addr:street":"Carrer De Bogatell",
    "iso:country":"ES",
    "sg:address":"Carrer de Bogatell, 28",
    "sg:city":"Montcada Centre",
    "sg:orig_category":"M\u00c9dicos: Medicina General Orientada A La Acupuntura",
    "sg:phone":"+34 935 75 35 53",
    "sg:postcode":"08110",
    "sg:province":"Barcelona",
    "wof:name":"Vera Parra Maria Rosa",
    "wof:placetype":"venue"
},
  "geometry": {"coordinates":[2.1817800999,41.4892234802],"type":"Point"}
}