{
  "type": "Feature",
  "properties": {
    "addr:full":"Martin Azpilcueta, 12 Iru\u00f1a Navarra 31011",
    "addr:housenumber":"12",
    "addr:postcode":"31011",
    "addr:street":"Azpilcueta",
    "iso:country":"ES",
    "sg:address":"Martin Azpilcueta, 12",
    "sg:city":"Iru\u00f1a",
    "sg:orig_category":"Periodistas Profesionales",
    "sg:phone":"+34 948 25 25 44",
    "sg:postcode":"31011",
    "sg:province":"Navarra",
    "wof:name":"Martinez De Zu\u00f1iga Sanchez Jose Javier",
    "wof:placetype":"venue"
},
  "geometry": {"coordinates":[-1.6629749537,42.8139305115],"type":"Point"}
}