{
  "type": "Feature",
  "properties": {
    "addr:full":"Carrer de Moreres (les), 27 Prat Llobregat Barcelona 08820",
    "addr:housenumber":"27",
    "addr:postcode":"08820",
    "addr:street":"Carrer De Moreres Les;Llobregat",
    "iso:country":"ES",
    "sg:address":"Carrer de Moreres (les), 27",
    "sg:city":"Prat Llobregat",
    "sg:orig_category":"Fabricaci\u00d3n De Cajas De Cart\u00d3n",
    "sg:phone":"+34 934 78 38 91",
    "sg:postcode":"08820",
    "sg:province":"Barcelona",
    "wof:name":"Manipulados Pahec S.l.",
    "wof:placetype":"venue"
},
  "geometry": {"coordinates":[2.101831913,41.3321228027],"type":"Point"}
}