{
  "type": "Feature",
  "properties": {
    "iso:country":"ES",
    "sg:address":"Calle de Francisco De Quevedo, 8",
    "sg:city":"Marbella",
    "sg:orig_category":"Molduras, Junquillos, Listones Y Molduras Perforadas",
    "sg:phone":"+34 952 86 72 46",
    "sg:postcode":"29600",
    "sg:province":"M\u00e1laga",
    "wof:name":"Telefonia Saltele Marbella S.l.",
    "wof:placetype":"venue"
},
  "geometry": {"coordinates":[-4.8868432045,36.5114097595],"type":"Point"}
}