{
  "type": "Feature",
  "properties": {
    "iso:country":"ES",
    "sg:address":"Calle de General Vives, 77",
    "sg:city":"Palmas De Gran Canaria",
    "sg:orig_category":"Juristas Extranjeros",
    "sg:phone":"+34 928 27 52 13",
    "sg:postcode":"35007",
    "sg:province":"Las Palmas",
    "wof:name":"Botello Menci Carmen",
    "wof:placetype":"venue"
},
  "geometry": {"coordinates":[-15.4312944412,28.1397132874],"type":"Point"}
}