{
  "type": "Feature",
  "properties": {
    "iso:country":"ES",
    "sg:address":"Calle de Goya, 2",
    "sg:city":"Alfaro",
    "sg:orig_category":"Oficinas: Suministros Para (fabricaci\u00d3n, Al Por Mayor)",
    "sg:phone":"+34 941 18 29 28",
    "sg:postcode":"26540",
    "sg:province":"La Rioja",
    "wof:name":"Comercial Aroz S.l.",
    "wof:placetype":"venue"
},
  "geometry": {"coordinates":[-1.7480200529,42.1759681702],"type":"Point"}
}