{
  "type": "Feature",
  "properties": {
    "addr:full":"Calle de Heroe De Sostoa, 73 Malaga M\u00e1laga 29002",
    "addr:housenumber":"73",
    "addr:postcode":"29002",
    "addr:street":"Calle De Heroe De Sostoa;Ma\u0301Laga",
    "iso:country":"ES",
    "sg:address":"Calle de Heroe De Sostoa, 73",
    "sg:city":"Malaga",
    "sg:orig_category":"Administradores De Bienes Y Delegados De Comunidades De Propietarios",
    "sg:phone":"+34 952 31 27 12",
    "sg:postcode":"29002",
    "sg:province":"M\u00e1laga",
    "wof:name":"Naranjo Ruiz Juan Ignacio",
    "wof:placetype":"venue"
},
  "geometry": {"coordinates":[-4.4373288155,36.7062454224],"type":"Point"}
}