{
  "type": "Feature",
  "properties": {
    "addr:full":"Calle de Bolenga (la), S/n Carrizo Ribera Le\u00f3n 24270",
    "addr:housenumber":"/ n",
    "addr:postcode":"24270",
    "addr:street":"Calle De Bolenga La S;Carrizo Ribera Leo\u0301N",
    "iso:country":"ES",
    "sg:address":"Calle de Bolenga (la), S/n",
    "sg:city":"Carrizo Ribera",
    "sg:orig_category":"Asilos De Ancianos. Centros Privados",
    "sg:phone":"+34 987 35 78 84",
    "sg:postcode":"24270",
    "sg:province":"Le\u00f3n",
    "wof:name":"Residencia Casa Hogar Santa Ana",
    "wof:placetype":"venue"
},
  "geometry": {"coordinates":[-5.8270010948,42.5826683044],"type":"Point"}
}