{
  "type": "Feature",
  "properties": {
    "iso:country":"ES",
    "sg:address":"Carrer de Cabrit I Bassa, 4",
    "sg:city":"Palma",
    "sg:orig_category":"Artes Gr\u00c1ficas, Artes Pl\u00c1sticas (curso)",
    "sg:phone":"+34 971 28 43 26",
    "sg:postcode":"07014",
    "sg:province":"Islas Baleares",
    "wof:name":"Industrias Graficas Venus S.l.",
    "wof:placetype":"venue"
},
  "geometry": {"coordinates":[2.6344020367,39.576171875],"type":"Point"}
}