{
  "type": "Feature",
  "properties": {
    "addr:full":"Carrer de Puerto Principe, 91 Barcelona Barcelona 08027",
    "addr:housenumber":"91",
    "addr:postcode":"08027",
    "addr:street":"Carrer De Puerto Principe",
    "iso:country":"ES",
    "sg:address":"Carrer de Puerto Principe, 91",
    "sg:city":"Barcelona",
    "sg:orig_category":"Laboratorios Y Trabajos De Fotograf\u00cda, V\u00cddeo Y Cine",
    "sg:phone":"+34 932 43 02 49",
    "sg:postcode":"08027",
    "sg:province":"Barcelona",
    "sg:website":"www.sinfo-digital.com",
    "wof:name":"Serveis Integrals De Fotografia S.l",
    "wof:placetype":"venue"
},
  "geometry": {"coordinates":[2.1818070412,41.4242134094],"type":"Point"}
}