{
  "type": "Feature",
  "properties": {
    "addr:full":"Arbidea, 16 Bilbao Vizcaya 48004",
    "addr:housenumber":"16",
    "addr:postcode":"48004",
    "addr:street":"Arbidea",
    "iso:country":"ES",
    "sg:address":"Arbidea, 16",
    "sg:city":"Bilbao",
    "sg:orig_category":"Lencer\u00cda Femenina, Corseter\u00cda, Trajes De Ba\u00d1o (al Por Menor)",
    "sg:phone":"+34 944 12 28 30",
    "sg:postcode":"48004",
    "sg:province":"Vizcaya",
    "wof:name":"Karmele Castresana (lenceria Nakar)",
    "wof:placetype":"venue"
},
  "geometry": {"coordinates":[-2.9096770287,43.2559661865],"type":"Point"}
}