{
  "type": "Feature",
  "properties": {
    "iso:country":"ES",
    "sg:address":"Avda Pinos, 15",
    "sg:city":"Santa Maria De Gracia",
    "sg:orig_category":"Cl\u00cdnicas Dentales",
    "sg:phone":"+34 968 28 36 18",
    "sg:postcode":"30009",
    "sg:province":"Murcia",
    "wof:name":"Vargas Guevara Dorys",
    "wof:placetype":"venue"
},
  "geometry": {"coordinates":[-1.1396720409,37.9974784851],"type":"Point"}
}