{
  "type": "Feature",
  "properties": {
    "iso:country":"ES",
    "sg:address":"Av. Cra. Rio, 511",
    "sg:city":"El Saler",
    "sg:orig_category":"Cristaler\u00cdas",
    "sg:phone":"+34 961 83 03 22",
    "sg:postcode":"46012",
    "sg:province":"Valencia",
    "wof:name":"Cristaleria Soler S.l.",
    "wof:placetype":"venue"
},
  "geometry": {"coordinates":[-0.2913190126,39.3012657166],"type":"Point"}
}