{
  "type": "Feature",
  "properties": {
    "iso:country":"ES",
    "sg:address":"Urb Villas De Aljamar Iv, 5",
    "sg:city":"Tomares",
    "sg:orig_category":"Creaci\u00d3n De Sitios, Hosting Internet",
    "sg:phone":"+34 954 15 02 54",
    "sg:postcode":"41940",
    "sg:province":"Sevilla",
    "wof:name":"Rodriguez Mendez Constantino",
    "wof:placetype":"venue"
},
  "geometry": {"coordinates":[-6.0511841774,37.3758506775],"type":"Point"}
}