{
  "type": "Feature",
  "properties": {
    "addr:full":"Calle de Retama, 4 Paz Santa Cruz De Tenerife 38400",
    "addr:housenumber":"4",
    "addr:postcode":"38400",
    "addr:street":"Calle De Retama",
    "iso:country":"ES",
    "sg:address":"Calle de Retama, 4",
    "sg:city":"Paz",
    "sg:orig_category":"Agencias Y Agentes Comerciales, Representantes",
    "sg:phone":"+34 922 38 88 71",
    "sg:postcode":"38400",
    "sg:province":"Santa Cruz De Tenerife",
    "wof:name":"Scherpe  Hans",
    "wof:placetype":"venue"
},
  "geometry": {"coordinates":[-16.5338745117,28.4120979309],"type":"Point"}
}