{
  "type": "Feature",
  "properties": {
    "addr:full":"Calle de Marques De Santillana (del), 12 Colmenar Viejo Madrid 28770",
    "addr:postcode":"28770",
    "addr:street":"Calle De Marques De Santillana Del",
    "iso:country":"ES",
    "sg:address":"Calle de Marques De Santillana (del), 12",
    "sg:city":"Colmenar Viejo",
    "sg:orig_category":"Cajas De Ahorro",
    "sg:phone":"+34 918 46 37 50",
    "sg:postcode":"28770",
    "sg:province":"Madrid",
    "sg:website":"www.ibercaja.es",
    "wof:name":"Caja De Ahorros Y Monte De Piedad De Zaragoza Aragon Y Rioja",
    "wof:placetype":"venue"
},
  "geometry": {"coordinates":[-3.7677130699,40.6593017578],"type":"Point"}
}