{
  "type": "Feature",
  "properties": {
    "iso:country":"ES",
    "sg:address":"Calle de Gante, 4",
    "sg:city":"Toledo",
    "sg:orig_category":"Telas Para Tapizar, Cortinas, Pasamaner\u00cda (fabricaci\u00d3n, Al Por Mayor)",
    "sg:phone":"+34 925 21 08 58",
    "sg:postcode":"45005",
    "sg:province":"Toledo",
    "wof:name":"Diaz Fernandez-salinero Julio",
    "wof:placetype":"venue"
},
  "geometry": {"coordinates":[-4.0301442146,39.8702468872],"type":"Point"}
}