{
  "type": "Feature",
  "properties": {
    "addr:full":"Avda Lerida (de), 39 Monzon Huesca 22400",
    "addr:housenumber":"39",
    "addr:postcode":"22400",
    "addr:street":"Avda Lerida De",
    "iso:country":"ES",
    "sg:address":"Avda Lerida (de), 39",
    "sg:city":"Monzon",
    "sg:orig_category":"Molduras, Junquillos, Listones Y Molduras Perforadas",
    "sg:phone":"+34 974 40 40 99",
    "sg:postcode":"22400",
    "sg:province":"Huesca",
    "wof:name":"Palacio Bestregui Manuel",
    "wof:placetype":"venue"
},
  "geometry": {"coordinates":[0.1971600056,41.9101982117],"type":"Point"}
}