{
  "type": "Feature",
  "properties": {
    "iso:country":"ES",
    "sg:address":"Calle de Doctor Fleming, 2",
    "sg:city":"Hellin",
    "sg:orig_category":"Autob\u00das (explotaci\u00d3n Y Servicios De)",
    "sg:phone":"+34 967 30 00 21",
    "sg:postcode":"02400",
    "sg:province":"Albacete",
    "wof:name":"Taxis Y Autobuses Alvarez S.l.",
    "wof:placetype":"venue"
},
  "geometry": {"coordinates":[-1.6938079596,38.5066070557],"type":"Point"}
}