{
  "type": "Feature",
  "properties": {
    "iso:country":"ES",
    "sg:address":"Calle de Pablo Casals, 2",
    "sg:city":"Zaragoza",
    "sg:orig_category":"Transporte En General",
    "sg:phone":"+34 976 73 74 03",
    "sg:postcode":"50015",
    "sg:province":"Zaragoza",
    "sg:website":"www.noctalia.es",
    "wof:name":"Noctalia",
    "wof:placetype":"venue"
},
  "geometry": {"coordinates":[-0.8884040117,41.6697883606],"type":"Point"}
}