{
  "type": "Feature",
  "properties": {
    "iso:country":"ES",
    "sg:address":"Carrer de Major, 71",
    "sg:city":"Ulldecona",
    "sg:orig_category":"Farmacias",
    "sg:phone":"+34 977 72 00 31",
    "sg:postcode":"43550",
    "sg:province":"Tarragona",
    "wof:name":"Viladot Arasa Antonio",
    "wof:placetype":"venue"
},
  "geometry": {"coordinates":[0.4478650093,40.597743988],"type":"Point"}
}