{
  "type": "Feature",
  "properties": {
    "iso:country":"ES",
    "sg:address":"Av Diputacio, 2",
    "sg:city":"Cambrils",
    "sg:orig_category":"Caf\u00c9s, Bares, Cervecer\u00cdas",
    "sg:phone":"+34 977 79 14 41",
    "sg:postcode":"43850",
    "sg:province":"Tarragona",
    "wof:name":"Monclan Cambrils S.l.",
    "wof:placetype":"venue"
},
  "geometry": {"coordinates":[1.0652470589,41.0659713745],"type":"Point"}
}