{
  "type": "Feature",
  "properties": {
    "iso:country":"ES",
    "sg:address":"Ctra Torres De Cotillas, S/n",
    "sg:city":"Javali Nuevo",
    "sg:orig_category":"Maquinaria Para Industrias Diversas",
    "sg:phone":"+34 968 80 26 88",
    "sg:postcode":"30832",
    "sg:province":"Murcia",
    "wof:name":"Talleres Nigomur S.l.",
    "wof:placetype":"venue"
},
  "geometry": {"coordinates":[-1.2194490433,37.9899787903],"type":"Point"}
}