{
  "type": "Feature",
  "properties": {
    "addr:full":"Calle de Ca\u00d1ete, 17 Madrid Madrid 28019",
    "addr:housenumber":"17",
    "addr:postcode":"madrid;28019",
    "addr:street":"Calle De Can\u0303Ete",
    "iso:country":"ES",
    "sg:address":"Calle de Ca\u00d1ete, 17",
    "sg:city":"Madrid",
    "sg:orig_category":"Imprenta",
    "sg:phone":"+34 914 71 11 33",
    "sg:postcode":"28019",
    "sg:province":"Madrid",
    "wof:name":"Etiquetas Rospil S.a.",
    "wof:placetype":"venue"
},
  "geometry": {"coordinates":[-3.7347290516,40.3921356201],"type":"Point"}
}