{
  "type": "Feature",
  "properties": {
    "addr:full":"Carrer de Vilaplana Del Camp, S/n Reus Tarragona 43203",
    "addr:housenumber":"s / n",
    "addr:postcode":"43203",
    "addr:street":"Carrer De Vilaplana Del Camp",
    "iso:country":"ES",
    "sg:address":"Carrer de Vilaplana Del Camp, S/n",
    "sg:city":"Reus",
    "sg:orig_category":"Arquitectos",
    "sg:phone":"+34 977 31 40 12",
    "sg:postcode":"43203",
    "sg:province":"Tarragona",
    "wof:name":"Prous Masdeu Juan",
    "wof:placetype":"venue"
},
  "geometry": {"coordinates":[1.107929945,41.1519889832],"type":"Point"}
}