{
  "type": "Feature",
  "properties": {
    "iso:country":"ES",
    "sg:address":"Entre Los Rios, S/n",
    "sg:city":"La Mata",
    "sg:orig_category":"T\u00c9cnicos Veterinarios",
    "sg:phone":"+34 985 75 17 21",
    "sg:postcode":"33825",
    "sg:province":"Asturias",
    "wof:name":"Sanchez Lopez Jose Maria",
    "wof:placetype":"venue"
},
  "geometry": {"coordinates":[-6.0492568016,43.3903999329],"type":"Point"}
}