{
  "type": "Feature",
  "properties": {
    "addr:full":"Calle de Porto Colon, 2 Alcorcon Madrid 28924",
    "addr:housenumber":"2",
    "addr:postcode":"28924",
    "addr:street":"Calle De Porto Colon",
    "iso:country":"ES",
    "sg:address":"Calle de Porto Colon, 2",
    "sg:city":"Alcorcon",
    "sg:orig_category":"Tintes (fabricaci\u00d3n, Al Por Mayor)",
    "sg:phone":"+34 916 19 14 13",
    "sg:postcode":"28924",
    "sg:province":"Madrid",
    "wof:name":"Peral Mu\u00d1oz Diego",
    "wof:placetype":"venue"
},
  "geometry": {"coordinates":[-3.8215308189,40.35181427],"type":"Point"}
}