{
  "type": "Feature",
  "properties": {
    "iso:country":"ES",
    "sg:address":"Calle de Letra B, 10",
    "sg:city":"Puebla Alfinden",
    "sg:orig_category":"Pescader\u00cdas (al Por Menor)",
    "sg:phone":"+34 976 10 98 41",
    "sg:postcode":"50171",
    "sg:province":"Zaragoza",
    "wof:name":"Toldos Arquitex Sl",
    "wof:placetype":"venue"
},
  "geometry": {"coordinates":[-0.7461140156,41.6334037781],"type":"Point"}
}