{
  "type": "Feature",
  "properties": {
    "iso:country":"ES",
    "sg:address":"Calle de Ancha, 49",
    "sg:city":"Montalban De Cordoba",
    "sg:orig_category":"Asociaciones, Organismos Culturales Y Socioeducativos",
    "sg:phone":"+34 957 31 05 73",
    "sg:postcode":"14548",
    "sg:province":"C\u00f3rdoba",
    "wof:name":"Pe\u00f1a Cultural Recreativa De Montalban De Cordoba",
    "wof:placetype":"venue"
},
  "geometry": {"coordinates":[-4.7498703003,37.582233429],"type":"Point"}
}