{
  "type": "Feature",
  "properties": {
    "addr:full":"Calle de Elisa Tomas Yusti, S/n Alacant Alicante 03540",
    "addr:housenumber":"s / n",
    "addr:postcode":"03540",
    "addr:street":"Calle De Elisa Tomas Yusti",
    "iso:country":"ES",
    "sg:address":"Calle de Elisa Tomas Yusti, S/n",
    "sg:city":"Alacant",
    "sg:orig_category":"Albergues",
    "sg:phone":"+34 965 16 00 37",
    "sg:postcode":"03540",
    "sg:province":"Alicante",
    "wof:name":"Namar Hosteleria S.l.",
    "wof:placetype":"venue"
},
  "geometry": {"coordinates":[-0.4178240001,38.3603591919],"type":"Point"}
}