{
  "type": "Feature",
  "properties": {
    "addr:full":"Carrer de Pere Iv, 530 Barcelona Barcelona 08019",
    "addr:housenumber":"530",
    "addr:postcode":"08019",
    "addr:street":"Carrer De Pere Iv",
    "iso:country":"ES",
    "sg:address":"Carrer de Pere Iv, 530",
    "sg:city":"Barcelona",
    "sg:orig_category":"Loter\u00cda Y T\u00d3mbola",
    "sg:phone":"+34 933 08 22 45",
    "sg:postcode":"08019",
    "sg:province":"Barcelona",
    "wof:name":"Maya Amador Julian",
    "wof:placetype":"venue"
},
  "geometry": {"coordinates":[2.2092719078,41.4175338745],"type":"Point"}
}