{
  "type": "Feature",
  "properties": {
    "addr:full":"Pol Ind Arriate, S/n Arriate M\u00e1laga 29350",
    "addr:postcode":"29350",
    "addr:street":"Arriate S / N Arriate Ma\u0301Laga",
    "iso:country":"ES",
    "sg:address":"Pol Ind Arriate, S/n",
    "sg:city":"Arriate",
    "sg:orig_category":"M\u00c1rmoles, Granitos Y Piedras Naturales",
    "sg:phone":"+34 952 16 56 95",
    "sg:postcode":"29350",
    "sg:province":"M\u00e1laga",
    "wof:name":"Garcia Gonzalez Jose Antonio",
    "wof:placetype":"venue"
},
  "geometry": {"coordinates":[-5.1353888512,36.7978210449],"type":"Point"}
}