{
  "type": "Feature",
  "properties": {
    "addr:full":"Calle de El Rompedizo, 9 Madrid Madrid 28044",
    "addr:housenumber":"9",
    "addr:postcode":"madrid;28044",
    "addr:street":"Calle De El Rompedizo",
    "iso:country":"ES",
    "sg:address":"Calle de El Rompedizo, 9",
    "sg:city":"Madrid",
    "sg:orig_category":"Inform\u00c1tica: Consultores",
    "sg:phone":"+34 917 05 48 28",
    "sg:postcode":"28044",
    "sg:province":"Madrid",
    "wof:name":"Distribucion Sistemas Y Consulting Informatico S.l.",
    "wof:placetype":"venue"
},
  "geometry": {"coordinates":[-3.7636940479,40.37657547],"type":"Point"}
}