{
  "type": "Feature",
  "properties": {
    "iso:country":"ES",
    "sg:address":"Av Jocs Olimpics (dels), S/n",
    "sg:city":"Reus",
    "sg:orig_category":"Agentes Generales De Seguros",
    "sg:phone":"+34 977 31 90 95",
    "sg:postcode":"43202",
    "sg:province":"Tarragona",
    "wof:name":"Gavalda Gisbert S.l.",
    "wof:placetype":"venue"
},
  "geometry": {"coordinates":[1.0970970392,41.1586723328],"type":"Point"}
}