{
  "type": "Feature",
  "properties": {
    "iso:country":"ES",
    "sg:address":"Ctra Norte Del, 219",
    "sg:city":"Palmas De Gran Canaria",
    "sg:orig_category":"Equipo De Refrigeraci\u00d3n Industrial",
    "sg:phone":"+34 928 41 44 08",
    "sg:postcode":"35013",
    "sg:province":"Las Palmas",
    "wof:name":"Arbelo Medina Agustin",
    "wof:placetype":"venue"
},
  "geometry": {"coordinates":[-15.4417381287,28.1009349823],"type":"Point"}
}