{
  "type": "Feature",
  "properties": {
    "addr:full":"Gral. Mola, 21 Villaverde De Iscar Segovia 40219",
    "addr:housenumber":"21",
    "addr:postcode":"40219",
    "addr:street":"Gral. Mola",
    "iso:country":"ES",
    "sg:address":"Gral. Mola, 21",
    "sg:city":"Villaverde De Iscar",
    "sg:orig_category":"Peluqueros: De Se\u00d1oras",
    "sg:phone":"+34 921 16 72 07",
    "sg:postcode":"40219",
    "sg:province":"Segovia",
    "wof:name":"Peluqueria Gen & Glo",
    "wof:placetype":"venue"
},
  "geometry": {"coordinates":[-4.5260257721,41.3066825867],"type":"Point"}
}