{
  "type": "Feature",
  "properties": {
    "iso:country":"ES",
    "sg:address":"Calle de Almendros Los, 3",
    "sg:city":"Arroyo De La Miel-benalmadena Costa",
    "sg:orig_category":"Discotecas Y Salas De Baile",
    "sg:phone":"+34 952 96 43 40",
    "sg:postcode":"29630",
    "sg:province":"M\u00e1laga",
    "wof:name":"Madson S.a.",
    "wof:placetype":"venue"
},
  "geometry": {"coordinates":[-4.5180735588,36.5991973877],"type":"Point"}
}