{
  "type": "Feature",
  "properties": {
    "addr:full":"Carrer de Fontanelles, 22 Fontanelles Barcelona 08510",
    "addr:housenumber":"22",
    "addr:postcode":"08510",
    "addr:street":"Carrer De Fontanelles",
    "iso:country":"ES",
    "sg:address":"Carrer de Fontanelles, 22",
    "sg:city":"Fontanelles",
    "sg:orig_category":"Distribuci\u00d3n De Petr\u00d3leo Y Derivados",
    "sg:phone":"+34 938 50 00 68",
    "sg:postcode":"08510",
    "sg:province":"Barcelona",
    "wof:name":"Feixas Aulet Distribucio S.a.",
    "wof:placetype":"venue"
},
  "geometry": {"coordinates":[2.3007199764,41.9688186646],"type":"Point"}
}