{
  "type": "Feature",
  "properties": {
    "addr:full":"Rua Santo Domingo, 82 Ourense Ourense 32003",
    "addr:housenumber":"82",
    "addr:postcode":"32003",
    "addr:street":"Rua Santo Domingo",
    "iso:country":"ES",
    "sg:address":"Rua Santo Domingo, 82",
    "sg:city":"Ourense",
    "sg:orig_category":"Confecci\u00d3n De Trajes Para Se\u00d1oras",
    "sg:phone":"+34 988 22 82 64",
    "sg:postcode":"32003",
    "sg:province":"Ourense",
    "wof:name":"Junco Gonzalez Orentino",
    "wof:placetype":"venue"
},
  "geometry": {"coordinates":[-7.8629989624,42.3407096863],"type":"Point"}
}