{
  "type": "Feature",
  "properties": {
    "iso:country":"ES",
    "sg:address":"Av Salvador Juan, 63",
    "sg:city":"Manacor",
    "sg:orig_category":"Ropa Para Se\u00d1oras Y Caballeros (al Por Menor)",
    "sg:phone":"+34 971 55 48 12",
    "sg:postcode":"07500",
    "sg:province":"Islas Baleares",
    "wof:name":"Modas Estelrich C.b.",
    "wof:placetype":"venue"
},
  "geometry": {"coordinates":[3.2053449154,39.5677108765],"type":"Point"}
}