{
  "type": "Feature",
  "properties": {
    "iso:country":"ES",
    "sg:address":"Fca. Piazos, S/n",
    "sg:city":"Boveda Del Rio Almar",
    "sg:orig_category":"Agricultores, Agricultores",
    "sg:phone":"+34 923 16 70 75",
    "sg:postcode":"37316",
    "sg:province":"Salamanca",
    "wof:name":"Sociedad Agraria De Transformacion Los Piazos",
    "wof:placetype":"venue"
},
  "geometry": {"coordinates":[-5.2086839676,40.8559417725],"type":"Point"}
}