{
  "type": "Feature",
  "properties": {
    "addr:full":"Puerta De Romeros, S/n Burgos Burgos 09...",
    "addr:housenumber":"s / n",
    "addr:street":"Burgos",
    "iso:country":"ES",
    "sg:address":"Puerta De Romeros, S/n",
    "sg:city":"Burgos",
    "sg:orig_category":"Universidades",
    "sg:phone":"+34 947 25 87 01",
    "sg:postcode":"09...",
    "sg:province":"Burgos",
    "sg:website":"www.ubu.es/investig/scai/imasd/imasd/index.htm",
    "wof:name":"Universidad De Burgos",
    "wof:placetype":"venue"
},
  "geometry": {"coordinates":[-3.6998100281,42.3410835266],"type":"Point"}
}