{
  "type": "Feature",
  "properties": {
    "iso:country":"ES",
    "sg:address":"Carr Musico Gomis, 5",
    "sg:city":"Burjassot",
    "sg:orig_category":"Aperitivos (fabricaci\u00d3n Y Al Por Mayor)",
    "sg:phone":"+34 963 90 60 44",
    "sg:postcode":"46100",
    "sg:province":"Valencia",
    "wof:name":"Cremades Guillen Silvestre",
    "wof:placetype":"venue"
},
  "geometry": {"coordinates":[-0.4154990017,39.5055046082],"type":"Point"}
}