{
  "type": "Feature",
  "properties": {
    "addr:full":"Calle de Ca\u00d1as (las), S/n Arenal \u00c1vila 05416",
    "addr:postcode":"05416",
    "addr:street":"Calle De Can\u0303As Las S / N Arenal A\u0301Vila",
    "iso:country":"ES",
    "sg:address":"Calle de Ca\u00d1as (las), S/n",
    "sg:city":"Arenal",
    "sg:orig_category":"Prot\u00c9sicos Dentales",
    "sg:phone":"+34 920 37 55 15",
    "sg:postcode":"05416",
    "sg:province":"\u00c1vila",
    "wof:name":"Vinuesa Mu\u00f1oz Lorenzo",
    "wof:placetype":"venue"
},
  "geometry": {"coordinates":[-5.087264061,40.2658081055],"type":"Point"}
}