{
  "type": "Feature",
  "properties": {
    "addr:full":"Calle de Cardenal Monescillo, 2 Nerva Huelva 21670",
    "addr:housenumber":"2",
    "addr:postcode":"21670",
    "addr:street":"Calle De Cardenal Monescillo",
    "iso:country":"ES",
    "sg:address":"Calle de Cardenal Monescillo, 2",
    "sg:city":"Nerva",
    "sg:orig_category":"Iglesia Cat\u00d3lica",
    "sg:phone":"+34 959 58 02 28",
    "sg:postcode":"21670",
    "sg:province":"Huelva",
    "wof:name":"Casa Rectoral",
    "wof:placetype":"venue"
},
  "geometry": {"coordinates":[-6.5249757767,37.702747345],"type":"Point"}
}