{
  "type": "Feature",
  "properties": {
    "addr:full":"Pase Pastrana (de), 37 Alcala Henares Madrid 28803",
    "addr:postcode":"28803",
    "iso:country":"ES",
    "sg:address":"Pase Pastrana (de), 37",
    "sg:city":"Alcala Henares",
    "sg:orig_category":"Mec\u00c1nico Del Autom\u00d3vil",
    "sg:phone":"+34 918 89 78 88",
    "sg:postcode":"28803",
    "sg:province":"Madrid",
    "wof:name":"Talleres Gallardo Sal",
    "wof:placetype":"venue"
},
  "geometry": {"coordinates":[-3.3661990166,40.4746208191],"type":"Point"}
}