{
  "type": "Feature",
  "properties": {
    "addr:full":"Carrer de Coto, 1 Colonia Sedo Barcelona 08292",
    "addr:housenumber":"1",
    "addr:postcode":"08292",
    "addr:street":"Carrer De Coto",
    "iso:country":"ES",
    "sg:address":"Carrer de Coto, 1",
    "sg:city":"Colonia Sedo",
    "sg:orig_category":"M\u00c1quinas Textiles, Accesorios Y Suministros (fabricaci\u00d3n)",
    "sg:phone":"+34 937 77 46 61",
    "sg:postcode":"08292",
    "sg:province":"Barcelona",
    "wof:name":"Comercial Catalana De Maquinaria Textil S. A.",
    "wof:placetype":"venue"
},
  "geometry": {"coordinates":[1.867759943,41.5371665955],"type":"Point"}
}