{
  "type": "Feature",
  "properties": {
    "iso:country":"ES",
    "sg:address":"Avda Alcalde Narciso Martin Navarro, S/n",
    "sg:city":"Ayamonte",
    "sg:classifiers":[
        {
            "category":"Recreation",
            "type":"Entertainment"
        }
    ],
    "sg:phone":"+34 959 32 16 45",
    "sg:postcode":"21400",
    "sg:province":"Huelva",
    "sg:tags":[
        "caza",
        "pr\u00c1ctica",
        "la",
        "de",
        "pesca",
        "y"
    ],
    "wof:name":"Pesca Espada S.l.",
    "wof:placetype":"venue"
},
  "geometry": {"coordinates":[-7.4044890404,37.2124862671],"type":"Point"}
}