{
  "type": "Feature",
  "properties": {
    "addr:full":"Calle de San Pancracio, 20 Valencia Valencia 46009",
    "addr:housenumber":"20",
    "addr:postcode":"46009",
    "addr:street":"Calle De San Pancracio",
    "iso:country":"ES",
    "sg:address":"Calle de San Pancracio, 20",
    "sg:city":"Valencia",
    "sg:orig_category":"Farmacias",
    "sg:phone":"+34 963 49 90 18",
    "sg:postcode":"46009",
    "sg:province":"Valencia",
    "wof:name":"Albors Rodrigo Maria Carmen",
    "wof:placetype":"venue"
},
  "geometry": {"coordinates":[-0.3861404955,39.4878463745],"type":"Point"}
}