{
  "type": "Feature",
  "properties": {
    "addr:full":"Calle de Serrano, 67 Madrid Madrid 28006",
    "addr:housenumber":"67",
    "addr:postcode":"madrid;28006",
    "addr:street":"Calle De Serrano",
    "iso:country":"ES",
    "sg:address":"Calle de Serrano, 67",
    "sg:city":"Madrid",
    "sg:orig_category":"Sociedades, Compa\u00d1\u00cdas Aseguradoras",
    "sg:phone":"+34 915 78 31 00",
    "sg:postcode":"28006",
    "sg:province":"Madrid",
    "wof:name":"Cahispa Recursos A.i.e.",
    "wof:placetype":"venue"
},
  "geometry": {"coordinates":[-3.6867690086,40.4330825806],"type":"Point"}
}