{
  "type": "Feature",
  "properties": {
    "addr:full":"Calle de Rio Segura, S/n Mostoles Madrid 28935",
    "addr:housenumber":"s / n",
    "addr:postcode":"28935",
    "addr:street":"Calle De Rio Segura",
    "iso:country":"ES",
    "sg:address":"Calle de Rio Segura, S/n",
    "sg:city":"Mostoles",
    "sg:orig_category":"Obras Y Organismos Sociales",
    "sg:phone":"+34 916 47 01 20",
    "sg:postcode":"28935",
    "sg:province":"Madrid",
    "wof:name":"Fundacion I\u00f1igo Alvarez De Toledo",
    "wof:placetype":"venue"
},
  "geometry": {"coordinates":[-3.8752889633,40.3137168884],"type":"Point"}
}