{
  "type": "Feature",
  "properties": {
    "addr:full":"Calle de Juan Carlos I, 9 Arnedo La Rioja 26580",
    "addr:housenumber":"9",
    "addr:postcode":"26580",
    "addr:street":"Calle De Juan Carlos I;Rioja",
    "iso:country":"ES",
    "sg:address":"Calle de Juan Carlos I, 9",
    "sg:city":"Arnedo",
    "sg:orig_category":"Molduras, Junquillos, Listones Y Molduras Perforadas",
    "sg:phone":"+34 941 38 34 70",
    "sg:postcode":"26580",
    "sg:province":"La Rioja",
    "wof:name":"Herrero Queija Mario",
    "wof:placetype":"venue"
},
  "geometry": {"coordinates":[-2.1002109051,42.2271118164],"type":"Point"}
}