{
  "type": "Feature",
  "properties": {
    "addr:full":"Calle de Marques Viudo De Pontejos, 3 Madrid Madrid 28012",
    "addr:housenumber":"3",
    "addr:postcode":"28012",
    "addr:street":"Calle De Marques Viudo De Pontejos",
    "iso:country":"ES",
    "sg:address":"Calle de Marques Viudo De Pontejos, 3",
    "sg:city":"Madrid",
    "sg:orig_category":"Papeler\u00cdas: Art\u00cdculos (al Por Mayor)",
    "sg:phone":"+34 915 21 21 09",
    "sg:postcode":"28012",
    "sg:province":"Madrid",
    "wof:name":"Velasco Ezquerro Julio",
    "wof:placetype":"venue"
},
  "geometry": {"coordinates":[-3.7043550014,40.4156723022],"type":"Point"}
}