{
  "type": "Feature",
  "properties": {
    "addr:full":"Plaz Espa\u00d1a, 18 Agost Alicante 03698",
    "addr:housenumber":"18",
    "addr:postcode":"03698",
    "addr:street":"Plaz Espan\u0303A",
    "iso:country":"ES",
    "sg:address":"Plaz Espa\u00d1a, 18",
    "sg:city":"Agost",
    "sg:orig_category":"Bancos",
    "sg:phone":"+34 965 69 13 76",
    "sg:postcode":"03698",
    "sg:province":"Alicante",
    "wof:name":"Banco Espa\u00f1ol De Credito S.a.",
    "wof:placetype":"venue"
},
  "geometry": {"coordinates":[-0.6349989772,38.4366798401],"type":"Point"}
}