{
  "type": "Feature",
  "properties": {
    "addr:full":"Avda Domingo Bueno, 54 Pontenova Pontevedra 36400",
    "addr:housenumber":"54",
    "addr:postcode":"36400",
    "addr:street":"Avda Domingo Bueno",
    "iso:country":"ES",
    "sg:address":"Avda Domingo Bueno, 54",
    "sg:city":"Pontenova",
    "sg:orig_category":"Molduras, Junquillos, Listones Y Molduras Perforadas",
    "sg:phone":"+34 986 33 09 10",
    "sg:postcode":"36400",
    "sg:province":"Pontevedra",
    "wof:name":"Gonzalez Lorenzo Ismael",
    "wof:placetype":"venue"
},
  "geometry": {"coordinates":[-8.6179990768,42.1610298157],"type":"Point"}
}