{
  "type": "Feature",
  "properties": {
    "iso:country":"ES",
    "sg:address":"Calle de Avda. Ntra. Sra. Del Carmen, S/n",
    "sg:city":"Ribaforada",
    "sg:orig_category":"Agricultores, Agricultores",
    "sg:phone":"+34 948 86 44 77",
    "sg:postcode":"31550",
    "sg:province":"Navarra",
    "wof:name":"Cobo Costa Manuel",
    "wof:placetype":"venue"
},
  "geometry": {"coordinates":[-1.5111806393,41.9791526794],"type":"Point"}
}