{
  "type": "Feature",
  "properties": {
    "iso:country":"ES",
    "sg:address":"Nueva, 18",
    "sg:city":"Gata",
    "sg:orig_category":"Discotecas Y Salas De Baile",
    "sg:phone":"+34 927 67 20 77",
    "sg:postcode":"10860",
    "sg:province":"C\u00e1ceres",
    "wof:name":"Torres Marin Jose Maria",
    "wof:placetype":"venue"
},
  "geometry": {"coordinates":[-6.5947389603,40.2371635437],"type":"Point"}
}