{
  "type": "Feature",
  "properties": {
    "addr:full":"Calle de Estrella, 21 Cantimpalos Segovia 40360",
    "addr:housenumber":"21",
    "addr:postcode":"40360",
    "addr:street":"Calle De Estrella;Segovia",
    "iso:country":"ES",
    "sg:address":"Calle de Estrella, 21",
    "sg:city":"Cantimpalos",
    "sg:orig_category":"Mec\u00c1nico Del Autom\u00d3vil",
    "sg:phone":"+34 921 49 63 64",
    "sg:postcode":"40360",
    "sg:province":"Segovia",
    "wof:name":"Talleres Rontoy S.l.",
    "wof:placetype":"venue"
},
  "geometry": {"coordinates":[-4.1631193161,41.0765075684],"type":"Point"}
}