{
  "type": "Feature",
  "properties": {
    "addr:full":"Rua Xeneral Franco, 20 Bande Ourense 32840",
    "addr:housenumber":"20",
    "addr:postcode":"32840",
    "addr:street":"Rua Xeneral Franco",
    "iso:country":"ES",
    "sg:address":"Rua Xeneral Franco, 20",
    "sg:city":"Bande",
    "sg:orig_category":"Librer\u00cdas",
    "sg:phone":"+34 988 44 30 57",
    "sg:postcode":"32840",
    "sg:province":"Ourense",
    "wof:name":"Valle Fernandez Alberto",
    "wof:placetype":"venue"
},
  "geometry": {"coordinates":[-7.9759888649,42.0309295654],"type":"Point"}
}