{
  "type": "Feature",
  "properties": {
    "addr:full":"Calle de Llana, 7 Cazalla Sierra Sevilla 41370",
    "addr:housenumber":"7",
    "addr:postcode":"41370",
    "addr:street":"Calle De Llana",
    "iso:country":"ES",
    "sg:address":"Calle de Llana, 7",
    "sg:city":"Cazalla Sierra",
    "sg:orig_category":"Granos Y Semillas (producci\u00d3n, Al Por Mayor)",
    "sg:phone":"+34 954 88 40 64",
    "sg:postcode":"41370",
    "sg:province":"Sevilla",
    "wof:name":"Ovelar Fernandez Alberto",
    "wof:placetype":"venue"
},
  "geometry": {"coordinates":[-5.7598829269,37.9325141907],"type":"Point"}
}