{
  "type": "Feature",
  "properties": {
    "addr:full":"Calle de Garay Juan De, 25 Bilbao Vizcaya 48003",
    "addr:housenumber":"25",
    "addr:postcode":"48003",
    "addr:street":"Calle De Garay Juan De",
    "iso:country":"ES",
    "sg:address":"Calle de Garay Juan De, 25",
    "sg:city":"Bilbao",
    "sg:orig_category":"Tapicer\u00cdas",
    "sg:phone":"+34 944 43 79 29",
    "sg:postcode":"48003",
    "sg:province":"Vizcaya",
    "wof:name":"Rodriguez Gimena Antonio",
    "wof:placetype":"venue"
},
  "geometry": {"coordinates":[-2.9337608814,43.2537574768],"type":"Point"}
}