{
  "type": "Feature",
  "properties": {
    "addr:full":"Calle de Molino De Viento (del), S/n Colmenar Viejo Madrid 28770",
    "addr:housenumber":"/ n",
    "addr:postcode":"28770",
    "addr:street":"Calle De Molino De Viento Del S",
    "iso:country":"ES",
    "sg:address":"Calle de Molino De Viento (del), S/n",
    "sg:city":"Colmenar Viejo",
    "sg:orig_category":"Poller\u00cda Y Caza (al Por Menor)",
    "sg:phone":"+34 918 46 16 06",
    "sg:postcode":"28770",
    "sg:province":"Madrid",
    "wof:name":"Fermobar S.l.",
    "wof:placetype":"venue"
},
  "geometry": {"coordinates":[-3.7731199265,40.6647148132],"type":"Point"}
}