{
  "type": "Feature",
  "properties": {
    "iso:country":"ES",
    "sg:address":"Maguxe, S/n",
    "sg:city":"Orto\u00f1o",
    "sg:orig_category":"Reciclaje, Desguace De Veh\u00cdculos",
    "sg:phone":"+34 981 89 13 42",
    "sg:postcode":"15228",
    "sg:province":"A Coru\u00f1a",
    "sg:website":"www.trameve.com",
    "wof:name":"Tratamiento Medioambiental De Vehiculos S.l.",
    "wof:placetype":"venue"
},
  "geometry": {"coordinates":[-8.6333398819,42.8469085693],"type":"Point"}
}