{
  "type": "Feature",
  "properties": {
    "addr:full":"Ctra. Andratx, 41 Costa Blanes Islas Baleares 07181",
    "addr:housenumber":"41",
    "addr:postcode":"07181",
    "addr:street":"Ctra. Andratx;Costa",
    "iso:country":"ES",
    "sg:address":"Ctra. Andratx, 41",
    "sg:city":"Costa Blanes",
    "sg:orig_category":"Abogados",
    "sg:phone":"+34 971 67 67 58",
    "sg:postcode":"07181",
    "sg:province":"Islas Baleares",
    "wof:name":"Agote Diez Elena",
    "wof:placetype":"venue"
},
  "geometry": {"coordinates":[2.5720164776,39.5351829529],"type":"Point"}
}