{
  "type": "Feature",
  "properties": {
    "addr:full":"Calle de Canonigo Pero Abat, S/n Osma Soria 42300",
    "addr:housenumber":"s / n",
    "addr:postcode":"42300",
    "addr:street":"Calle De Canonigo;Abat",
    "iso:country":"ES",
    "sg:address":"Calle de Canonigo Pero Abat, S/n",
    "sg:city":"Osma",
    "sg:orig_category":"Negocio De Materiales De Construcci\u00d3n",
    "sg:phone":"+34 975 34 13 00",
    "sg:postcode":"42300",
    "sg:province":"Soria",
    "wof:name":"Miguel Hernandez Juan Jose De",
    "wof:placetype":"venue"
},
  "geometry": {"coordinates":[-3.0776567459,41.619972229],"type":"Point"}
}