{
  "type": "Feature",
  "properties": {
    "addr:full":"Avgd Coma, Sa, 37 Son Moro Islas Baleares 07560",
    "addr:housenumber":"37",
    "addr:postcode":"07560",
    "iso:country":"ES",
    "sg:address":"Avgd Coma, Sa, 37",
    "sg:city":"Son Moro",
    "sg:orig_category":"Supermercados Y Hipermercados",
    "sg:phone":"+34 971 58 58 19",
    "sg:postcode":"07560",
    "sg:province":"Islas Baleares",
    "wof:name":"Ginart Soler Salvador",
    "wof:placetype":"venue"
},
  "geometry": {"coordinates":[3.3764801025,39.5764541626],"type":"Point"}
}