{
  "type": "Feature",
  "properties": {
    "iso:country":"ES",
    "sg:address":"Avda Luis De La Concha, 24",
    "sg:city":"Renedo",
    "sg:orig_category":"Librer\u00cdas",
    "sg:phone":"+34 942 57 01 18",
    "sg:postcode":"39470",
    "sg:province":"Cantabria",
    "wof:name":"Lisaso Real Luis",
    "wof:placetype":"venue"
},
  "geometry": {"coordinates":[-3.950553894,43.3535842896],"type":"Point"}
}