{
  "type": "Feature",
  "properties": {
    "iso:country":"ES",
    "sg:address":"Calle de Real, 11",
    "sg:city":"Santiponce",
    "sg:orig_category":"M\u00c9dicos: An\u00c1lisis Cl\u00cdnicos",
    "sg:phone":"+34 955 99 65 56",
    "sg:postcode":"41970",
    "sg:province":"Sevilla",
    "wof:name":"Algaba Moreno Jose",
    "wof:placetype":"venue"
},
  "geometry": {"coordinates":[-6.0386214256,37.4386444092],"type":"Point"}
}