{
  "type": "Feature",
  "properties": {
    "iso:country":"ES",
    "sg:address":"Calle de Rocinante, 9",
    "sg:city":"Socuellamos",
    "sg:orig_category":"Empresarios",
    "sg:phone":"+34 926 53 29 60",
    "sg:postcode":"13630",
    "sg:province":"Ciudad Real",
    "wof:name":"Cogodel 2005 S.l",
    "wof:placetype":"venue"
},
  "geometry": {"coordinates":[-2.7828888893,39.284450531],"type":"Point"}
}