{
  "type": "Feature",
  "properties": {
    "iso:country":"ES",
    "sg:address":"Avda Carmen, 35",
    "sg:city":"Cox",
    "sg:orig_category":"Caf\u00c9s, Bares, Cervecer\u00cdas",
    "sg:phone":"+34 966 75 01 08",
    "sg:postcode":"03350",
    "sg:province":"Alicante",
    "wof:name":"Sierra Morante Teresa",
    "wof:placetype":"venue"
},
  "geometry": {"coordinates":[-0.8881700039,38.1423721313],"type":"Point"}
}