{
  "type": "Feature",
  "properties": {
    "iso:country":"ES",
    "sg:address":"Avda Castejon De Valdejasa, 9",
    "sg:city":"Villanueva Gallego",
    "sg:orig_category":"Peluquer\u00cdas, Peluquer\u00cda Mixta",
    "sg:phone":"+34 976 18 69 56",
    "sg:postcode":"50830",
    "sg:province":"Zaragoza",
    "wof:name":"Peluqueria Tristras",
    "wof:placetype":"venue"
},
  "geometry": {"coordinates":[-0.8227289915,41.7713890076],"type":"Point"}
}