{
  "type": "Feature",
  "properties": {
    "addr:full":"Calle de Encomienda, 7 Madrid Madrid 28012",
    "addr:housenumber":"7",
    "addr:postcode":"madrid;28012",
    "addr:street":"Calle De Encomienda",
    "iso:country":"ES",
    "sg:address":"Calle de Encomienda, 7",
    "sg:city":"Madrid",
    "sg:orig_category":"Confecci\u00d3n (fabricaci\u00d3n, Al Por Mayor)",
    "sg:phone":"+34 914 67 44 22",
    "sg:postcode":"28012",
    "sg:province":"Madrid",
    "wof:name":"Calambola Import S.l.",
    "wof:placetype":"venue"
},
  "geometry": {"coordinates":[-3.7052218914,40.4107971191],"type":"Point"}
}