{
  "type": "Feature",
  "properties": {
    "iso:country":"ES",
    "sg:address":"Ctra. Es Migjorn Gran, 12",
    "sg:city":"Ferreries",
    "sg:orig_category":"Alimentaci\u00d3n General (al Por Mayor)",
    "sg:phone":"+34 971 37 34 22",
    "sg:postcode":"07750",
    "sg:province":"Islas Baleares",
    "wof:name":"Febrer Coll Bartolome",
    "wof:placetype":"venue"
},
  "geometry": {"coordinates":[4.012155056,39.9805412292],"type":"Point"}
}