{
  "type": "Feature",
  "properties": {
    "addr:full":"Carrer de Balmes, 237 Barcelona Barcelona 08006",
    "addr:housenumber":"237",
    "addr:postcode":"08006",
    "addr:street":"Carrer De Balmes",
    "iso:country":"ES",
    "sg:address":"Carrer de Balmes, 237",
    "sg:city":"Barcelona",
    "sg:orig_category":"Bisuter\u00cda, Joyer\u00cda, Relojer\u00cda (al Por Menor)",
    "sg:phone":"+34 934 16 16 94",
    "sg:postcode":"08006",
    "sg:province":"Barcelona",
    "wof:name":"Rotger Briones Carmina",
    "wof:placetype":"venue"
},
  "geometry": {"coordinates":[2.1501829624,41.3993186951],"type":"Point"}
}