{
  "type": "Feature",
  "properties": {
    "iso:country":"ES",
    "sg:address":"Calle de Ferrari, 3",
    "sg:city":"Valladolid",
    "sg:orig_category":"Marroquiner\u00cda Y Art\u00cdculos De Viaje (al Por Menor)",
    "sg:phone":"+34 983 33 82 52",
    "sg:postcode":"47001",
    "sg:province":"Valladolid",
    "wof:name":"Velasco Vega Teodoro",
    "wof:placetype":"venue"
},
  "geometry": {"coordinates":[-4.72727108,41.6519432068],"type":"Point"}
}