{
  "type": "Feature",
  "properties": {
    "iso:country":"ES",
    "sg:address":"Calle de Rodrigo De Triana, 40",
    "sg:city":"Santa Cruz De Tenerife",
    "sg:orig_category":"Contenedores (mercanc\u00cdas)",
    "sg:phone":"+34 922 65 68 09",
    "sg:postcode":"38010",
    "sg:province":"Santa Cruz De Tenerife",
    "wof:name":"Serma Marrero Monta\u00f1ez S.l.",
    "wof:placetype":"venue"
},
  "geometry": {"coordinates":[-16.2806415558,28.4514427185],"type":"Point"}
}