{
  "type": "Feature",
  "properties": {
    "addr:full":"Ptda Carrus, 259 Elche Alicante 03205",
    "addr:housenumber":"259",
    "addr:postcode":"03205",
    "addr:street":"Ptda Carrus",
    "iso:country":"ES",
    "sg:address":"Ptda Carrus, 259",
    "sg:city":"Elche",
    "sg:orig_category":"Chapister\u00cda",
    "sg:phone":"+34 965 43 60 12",
    "sg:postcode":"03205",
    "sg:province":"Alicante",
    "wof:name":"Berna Gamiz Jose Joaquin",
    "wof:placetype":"venue"
},
  "geometry": {"coordinates":[-0.6995239854,38.2634811401],"type":"Point"}
}