{
  "type": "Feature",
  "properties": {
    "iso:country":"ES",
    "sg:address":"Carrer de Amposta (d'), 42",
    "sg:city":"Tortosa",
    "sg:orig_category":"Bebidas",
    "sg:phone":"+34 977 58 87 87",
    "sg:postcode":"43500",
    "sg:province":"Tarragona",
    "wof:name":"Herraiz Sistemes S.a.",
    "wof:placetype":"venue"
},
  "geometry": {"coordinates":[0.5145260096,40.8099861145],"type":"Point"}
}