{
  "type": "Feature",
  "properties": {
    "iso:country":"ES",
    "sg:address":"Carr Major, 30",
    "sg:city":"Seu D'urgell",
    "sg:orig_category":"Panader\u00cdas, Panader\u00cdas",
    "sg:phone":"+34 973 35 00 69",
    "sg:postcode":"25700",
    "sg:province":"Lleida",
    "wof:name":"Sanchez Gimenez Angel",
    "wof:placetype":"venue"
},
  "geometry": {"coordinates":[0.6257429719,41.6143074036],"type":"Point"}
}