{
  "type": "Feature",
  "properties": {
    "addr:full":"Carr Baltasar Rull (de), 13 Betxi Castell\u00f3n 12549",
    "addr:housenumber":"13",
    "addr:postcode":"12549",
    "addr:street":"Carr Baltasar Rull De;Castello\u0301N",
    "iso:country":"ES",
    "sg:address":"Carr Baltasar Rull (de), 13",
    "sg:city":"Betxi",
    "sg:orig_category":"Plomeros",
    "sg:phone":"+34 964 62 21 63",
    "sg:postcode":"12549",
    "sg:province":"Castell\u00f3n",
    "wof:name":"Do\u00f1ate Salas Jose Vicente",
    "wof:placetype":"venue"
},
  "geometry": {"coordinates":[-0.2003850043,39.9275016785],"type":"Point"}
}