{
  "type": "Feature",
  "properties": {
    "iso:country":"ES",
    "sg:address":"Avda Casalduch, 98",
    "sg:city":"Castellon",
    "sg:orig_category":"Empresas De Pintura Y Revestimientos",
    "sg:phone":"+34 964 21 09 71",
    "sg:postcode":"12005",
    "sg:province":"Castell\u00f3n",
    "wof:name":"Cubillas Lopez Jose",
    "wof:placetype":"venue"
},
  "geometry": {"coordinates":[-0.044737,39.9754600525],"type":"Point"}
}