{
  "type": "Feature",
  "properties": {
    "addr:full":"Calle de Ayamosna, S/n Ayamosna Santa Cruz De Tenerife 38800",
    "addr:housenumber":"s",
    "addr:postcode":"38800",
    "addr:street":"Calle De Ayamosna;/ N Ayamosna",
    "iso:country":"ES",
    "sg:address":"Calle de Ayamosna, S/n",
    "sg:city":"Ayamosna",
    "sg:orig_category":"Ense\u00d1ante, Direcci\u00d3n",
    "sg:phone":"+34 922 87 03 16",
    "sg:postcode":"38800",
    "sg:province":"Santa Cruz De Tenerife",
    "wof:name":"Vera Sanchez Saturnino",
    "wof:placetype":"venue"
},
  "geometry": {"coordinates":[-17.1105136871,28.0907344818],"type":"Point"}
}