{
  "type": "Feature",
  "properties": {
    "addr:full":"Calle de Alango, 7 Getxo Vizcaya 48990",
    "addr:housenumber":"7",
    "addr:postcode":"48990",
    "addr:street":"Calle De Alango",
    "iso:country":"ES",
    "sg:address":"Calle de Alango, 7",
    "sg:city":"Getxo",
    "sg:orig_category":"Fabricaci\u00d3n De Ventanas",
    "sg:phone":"+34 944 60 58 56",
    "sg:postcode":"48990",
    "sg:province":"Vizcaya",
    "wof:name":"Karpesa 2000, S.l.",
    "wof:placetype":"venue"
},
  "geometry": {"coordinates":[-3.0087525845,43.347278595],"type":"Point"}
}