{
  "type": "Feature",
  "properties": {
    "addr:full":"Calle de Alcalde Martin De Alzaga, 6 Madrid Madrid 28039",
    "addr:housenumber":"6",
    "addr:postcode":"28039",
    "addr:street":"Calle De Alcalde Martin De Alzaga",
    "iso:country":"ES",
    "sg:address":"Calle de Alcalde Martin De Alzaga, 6",
    "sg:city":"Madrid",
    "sg:orig_category":"Aparcamientos (infraestructuras, Accesorios)",
    "sg:phone":"+34 914 50 08 31",
    "sg:postcode":"28039",
    "sg:province":"Madrid",
    "wof:name":"Comunidad De Usuarios Aparcamiento Alcalde Martin Alzaga",
    "wof:placetype":"venue"
},
  "geometry": {"coordinates":[-3.7166671753,40.4629974365],"type":"Point"}
}