{
  "type": "Feature",
  "properties": {
    "iso:country":"ES",
    "sg:address":"Calle de Ricardo Labaca, 18",
    "sg:city":"Coru\u00d1a",
    "sg:orig_category":"Restaurantes",
    "sg:phone":"+34 981 15 21 97",
    "sg:postcode":"15005",
    "sg:province":"La Coru\u00f1a",
    "wof:name":"Rodriguez Sande Antonio",
    "wof:placetype":"venue"
},
  "geometry": {"coordinates":[-8.4111433029,43.3580627441],"type":"Point"}
}