{
  "type": "Feature",
  "properties": {
    "iso:country":"ES",
    "sg:address":"Carrer de Ferrarons, 3",
    "sg:city":"Olot",
    "sg:orig_category":"Talleres: Ropa A Medida",
    "sg:phone":"+34 972 26 08 36",
    "sg:postcode":"17800",
    "sg:province":"Girona",
    "wof:name":"Verges Juanola Domingo",
    "wof:placetype":"venue"
},
  "geometry": {"coordinates":[2.4901940823,42.182434082],"type":"Point"}
}