{
  "type": "Feature",
  "properties": {
    "iso:country":"ES",
    "sg:address":"Calle de Mayor, 138",
    "sg:city":"Alcantarilla",
    "sg:orig_category":"M\u00c9dicos: An\u00c1lisis Cl\u00cdnicos",
    "sg:phone":"+34 968 80 37 62",
    "sg:postcode":"30820",
    "sg:province":"Murcia",
    "wof:name":"Perez Lopez Maria Luisa",
    "wof:placetype":"venue"
},
  "geometry": {"coordinates":[-1.2161749601,37.9682350159],"type":"Point"}
}