{
  "type": "Feature",
  "properties": {
    "addr:full":"Calle de San Roque, 9 Cinctorres Castell\u00f3n 12318",
    "addr:housenumber":"9",
    "addr:postcode":"12318",
    "addr:street":"Calle De San Roque;Castello\u0301N",
    "iso:country":"ES",
    "sg:address":"Calle de San Roque, 9",
    "sg:city":"Cinctorres",
    "sg:orig_category":"Cajas Para Embalar",
    "sg:phone":"+34 964 18 10 50",
    "sg:postcode":"12318",
    "sg:province":"Castell\u00f3n",
    "wof:name":"Caja Rural Del Mediterraneo Ruralcaja S Coop De Credito",
    "wof:placetype":"venue"
},
  "geometry": {"coordinates":[-0.2622190118,40.5332298279],"type":"Point"}
}