{
  "type": "Feature",
  "properties": {
    "addr:full":"Plaz Peru, 1 Madrid Madrid 28016",
    "addr:housenumber":"1",
    "addr:postcode":"28016",
    "addr:street":"Peru",
    "iso:country":"ES",
    "sg:address":"Plaz Peru, 1",
    "sg:city":"Madrid",
    "sg:orig_category":"Molduras, Junquillos, Listones Y Molduras Perforadas",
    "sg:phone":"+34 913 59 29 12",
    "sg:postcode":"28016",
    "sg:province":"Madrid",
    "wof:name":"Fernandez Rodriguez Jose Luis",
    "wof:placetype":"venue"
},
  "geometry": {"coordinates":[-3.7057740688,40.42029953],"type":"Point"}
}