{
  "type": "Feature",
  "properties": {
    "addr:full":"Gibeleta, S/n Hondarribia Guip\u00f9zcoa 20280",
    "addr:housenumber":"s / n",
    "addr:postcode":"20280",
    "addr:street":"Gibeleta;Guipu\u0300Zcoa",
    "iso:country":"ES",
    "sg:address":"Gibeleta, S/n",
    "sg:city":"Hondarribia",
    "sg:orig_category":"Diet\u00c9tica: Productos Biol\u00d3gicos, Naturales Y Diet\u00c9ticos (fabricaci\u00d3n, Al Por Mayor)",
    "sg:phone":"+34 943 64 59 21",
    "sg:postcode":"20280",
    "sg:province":"Guip\u00f9zcoa",
    "sg:website":"www.prohealth.es",
    "wof:name":"Oscoz Vazquez Manuel Maria",
    "wof:placetype":"venue"
},
  "geometry": {"coordinates":[-1.8062039614,43.3443984985],"type":"Point"}
}