{
  "type": "Feature",
  "properties": {
    "addr:full":"Carrer de Casp, 44 Barcelona Barcelona 08010",
    "addr:housenumber":"44",
    "addr:postcode":"08010",
    "addr:street":"Carrer De Casp",
    "iso:country":"ES",
    "sg:address":"Carrer de Casp, 44",
    "sg:city":"Barcelona",
    "sg:orig_category":"Asesor\u00cda Fiscal Y Jur\u00cddica",
    "sg:phone":"+34 934 12 34 57",
    "sg:postcode":"08010",
    "sg:province":"Barcelona",
    "wof:name":"Cartelache S.l.",
    "wof:placetype":"venue"
},
  "geometry": {"coordinates":[2.1727340221,41.3907012939],"type":"Point"}
}