{
  "type": "Feature",
  "properties": {
    "iso:country":"ES",
    "sg:address":"Rier Sant Andreu, 69",
    "sg:city":"Barcelona",
    "sg:orig_category":"Cer\u00c1micas: Material Y Suministros",
    "sg:phone":"+34 933 45 94 12",
    "sg:postcode":"08030",
    "sg:province":"Barcelona",
    "wof:name":"Espacio S.a.",
    "wof:placetype":"venue"
},
  "geometry": {"coordinates":[2.18699193,41.4340705872],"type":"Point"}
}