{
  "type": "Feature",
  "properties": {
    "addr:full":"Calle de San Eloy, 33 Sevilla Sevilla 41001",
    "addr:housenumber":"33",
    "addr:postcode":"41001",
    "addr:street":"Calle De San Eloy",
    "iso:country":"ES",
    "sg:address":"Calle de San Eloy, 33",
    "sg:city":"Sevilla",
    "sg:orig_category":"Ropa Para Caballeros (al Por Menor)",
    "sg:phone":"+34 954 21 86 76",
    "sg:postcode":"41001",
    "sg:province":"Sevilla",
    "wof:name":"Granada Hernandez Francisca Maria",
    "wof:placetype":"venue"
},
  "geometry": {"coordinates":[-5.9975299835,37.3914871216],"type":"Point"}
}