{
  "type": "Feature",
  "properties": {
    "iso:country":"ES",
    "sg:address":"Carrer de Merceria (de La), 18",
    "sg:city":"Tarragona",
    "sg:orig_category":"Molduras, Junquillos, Listones Y Molduras Perforadas",
    "sg:phone":"+34 977 23 95 27",
    "sg:postcode":"43003",
    "sg:province":"Tarragona",
    "wof:name":"Hermosilla Pinedo Maria Del Carmen",
    "wof:placetype":"venue"
},
  "geometry": {"coordinates":[1.2583509684,41.1180305481],"type":"Point"}
}