{
  "type": "Feature",
  "properties": {
    "addr:full":"Avda Argentina, S/n Gijon Asturias 33213",
    "addr:housenumber":"s / n",
    "addr:postcode":"33213",
    "addr:street":"Avda Argentina",
    "iso:country":"ES",
    "sg:address":"Avda Argentina, S/n",
    "sg:city":"Gijon",
    "sg:orig_category":"Promotores Constructores",
    "sg:phone":"+34 985 97 65 78",
    "sg:postcode":"33213",
    "sg:province":"Asturias",
    "wof:name":"Construcciones San Bernardo S.a.",
    "wof:placetype":"venue"
},
  "geometry": {"coordinates":[-5.7014889717,43.5386352539],"type":"Point"}
}