{
  "type": "Feature",
  "properties": {
    "iso:country":"ES",
    "sg:address":"Avda Happag Lloyd, 1",
    "sg:city":"Urbanizacion Ca\u00e7ada Del Rio",
    "sg:orig_category":"Audiovisuales (producci\u00d3n, Edici\u00d3n, Realizaci\u00d3n)",
    "sg:phone":"+34 928 87 55 87",
    "sg:postcode":"35627",
    "sg:province":"Las Palmas",
    "wof:name":"Vedado Vision S.l.",
    "wof:placetype":"venue"
},
  "geometry": {"coordinates":[-14.1530008316,28.1882152557],"type":"Point"}
}