{
  "type": "Feature",
  "properties": {
    "iso:country":"ES",
    "sg:address":"Carrer de Tres Creus, 104",
    "sg:city":"Sabadell",
    "sg:orig_category":"Decoraci\u00d3n: Instalaci\u00d3n Y Talleres",
    "sg:phone":"+34 937 27 61 32",
    "sg:postcode":"08202",
    "sg:province":"Barcelona",
    "wof:name":"Ferreres Carbonell Nuria",
    "wof:placetype":"venue"
},
  "geometry": {"coordinates":[2.1128048897,41.5460624695],"type":"Point"}
}