{
  "type": "Feature",
  "properties": {
    "iso:country":"ES",
    "sg:address":"Calle de Astorga, 47",
    "sg:city":"Ba\u00d1eza",
    "sg:orig_category":"Molduras, Junquillos, Listones Y Molduras Perforadas",
    "sg:phone":"+34 987 64 30 04",
    "sg:postcode":"24750",
    "sg:province":"Le\u00f3n",
    "wof:name":"Macias Vuelta Benigno",
    "wof:placetype":"venue"
},
  "geometry": {"coordinates":[-5.8997769356,42.3018455505],"type":"Point"}
}