{
  "type": "Feature",
  "properties": {
    "addr:full":"Calle de Juan Carlos I, 2 Santa Marta De Tormes Salamanca 37900",
    "addr:housenumber":"2",
    "addr:postcode":"37900",
    "addr:street":"Calle De Juan Carlos I",
    "iso:country":"ES",
    "sg:address":"Calle de Juan Carlos I, 2",
    "sg:city":"Santa Marta De Tormes",
    "sg:orig_category":"Molduras, Junquillos, Listones Y Molduras Perforadas",
    "sg:phone":"+34 923 20 10 61",
    "sg:postcode":"37900",
    "sg:province":"Salamanca",
    "wof:name":"Diaz De Geras Sastre Luciano",
    "wof:placetype":"venue"
},
  "geometry": {"coordinates":[-5.630833149,40.9496688843],"type":"Point"}
}