{
  "type": "Feature",
  "properties": {
    "addr:full":"Avda Marcelino Suarez, 19 Barco Ourense 32300",
    "addr:housenumber":"19",
    "addr:postcode":"32300",
    "addr:street":"Avda Marcelino Suarez",
    "iso:country":"ES",
    "sg:address":"Avda Marcelino Suarez, 19",
    "sg:city":"Barco",
    "sg:orig_category":"Farmacias",
    "sg:phone":"+34 988 32 51 05",
    "sg:postcode":"32300",
    "sg:province":"Ourense",
    "wof:name":"Farmacia Fernandez Martinez C.b.",
    "wof:placetype":"venue"
},
  "geometry": {"coordinates":[-6.9832191467,42.4160308838],"type":"Point"}
}