{
  "type": "Feature",
  "properties": {
    "iso:country":"ES",
    "sg:address":"Calle de San Francisco, 135",
    "sg:city":"Vinaros",
    "sg:orig_category":"Reposter\u00cdas",
    "sg:phone":"+34 964 45 25 43",
    "sg:postcode":"12500",
    "sg:province":"Castell\u00f3n",
    "wof:name":"F.cano-due\u00f1as Industrias Del Pan S.l.",
    "wof:placetype":"venue"
},
  "geometry": {"coordinates":[0.4749450088,40.4711990356],"type":"Point"}
}