{
  "type": "Feature",
  "properties": {
    "iso:country":"ES",
    "sg:address":"Avda Los Huetos, 20",
    "sg:city":"Vitoria-gasteiz",
    "sg:orig_category":"Agentes Generales De Seguros",
    "sg:phone":"+34 945 20 01 73",
    "sg:postcode":"01010",
    "sg:province":"\u00c1lava",
    "wof:name":"Alfredo Arnaiz S.l.",
    "wof:placetype":"venue"
},
  "geometry": {"coordinates":[-2.702370882,42.8543739319],"type":"Point"}
}