{
  "type": "Feature",
  "properties": {
    "iso:country":"ES",
    "sg:address":"Carrer de Villarroel, 65",
    "sg:city":"Barcelona",
    "sg:orig_category":"Ropa Y Art\u00cdculos Pre",
    "sg:phone":"+34 933 23 09 04",
    "sg:postcode":"08011",
    "sg:province":"Barcelona",
    "wof:name":"Puerimueble S.l.",
    "wof:placetype":"venue"
},
  "geometry": {"coordinates":[2.1587820053,41.3834991455],"type":"Point"}
}