{
  "type": "Feature",
  "properties": {
    "iso:country":"ES",
    "sg:address":"Bo Otsango, 28",
    "sg:city":"Lesaka",
    "sg:orig_category":"Imprenta",
    "sg:phone":"+34 948 62 76 35",
    "sg:postcode":"31770",
    "sg:province":"Navarra",
    "sg:website":"www.ekilur.com",
    "wof:name":"Ekilur",
    "wof:placetype":"venue"
},
  "geometry": {"coordinates":[-1.7035230398,43.2495765686],"type":"Point"}
}