{
  "type": "Feature",
  "properties": {
    "iso:country":"ES",
    "sg:address":"Calle de Don Juan De Austria, 11",
    "sg:city":"Malaga",
    "sg:orig_category":"Muebles, Minoristas",
    "sg:phone":"+34 952 61 58 46",
    "sg:postcode":"29009",
    "sg:province":"M\u00e1laga",
    "wof:name":"Asociacion Nueva Frontera",
    "wof:placetype":"venue"
},
  "geometry": {"coordinates":[-4.4288859367,36.7242927551],"type":"Point"}
}