{
  "type": "Feature",
  "properties": {
    "addr:full":"Carr Camp De Mart, 2 Lleida Lleida 25006",
    "addr:housenumber":"2",
    "addr:postcode":"25006",
    "addr:street":"Carr Camp De Mart",
    "iso:country":"ES",
    "sg:address":"Carr Camp De Mart, 2",
    "sg:city":"Lleida",
    "sg:orig_category":"Vestidos De Se\u00d1ora (tallas Grandes)",
    "sg:phone":"+34 973 26 66 20",
    "sg:postcode":"25006",
    "sg:province":"Lleida",
    "wof:name":"Citerea C.b",
    "wof:placetype":"venue"
},
  "geometry": {"coordinates":[0.5619999766,41.6497535706],"type":"Point"}
}