{
  "type": "Feature",
  "properties": {
    "addr:full":"Avda Estacion (la), 34 Astorga Le\u00f3n 24700",
    "addr:housenumber":"34",
    "addr:postcode":"24700",
    "addr:street":"Avda Estacion La;Leo\u0301N",
    "iso:country":"ES",
    "sg:address":"Avda Estacion (la), 34",
    "sg:city":"Astorga",
    "sg:orig_category":"Equitaci\u00d3n Y Centros De H\u00cdpica",
    "sg:phone":"+34 987 61 55 97",
    "sg:postcode":"24700",
    "sg:province":"Le\u00f3n",
    "wof:name":"Planeta Rural Sl",
    "wof:placetype":"venue"
},
  "geometry": {"coordinates":[-6.0504040718,42.458404541],"type":"Point"}
}