{
  "type": "Feature",
  "properties": {
    "addr:full":"Ctra Churra, 172 Churra Murcia 30110",
    "addr:housenumber":"172",
    "addr:postcode":"30110",
    "addr:street":"Ctra Churra",
    "iso:country":"ES",
    "sg:address":"Ctra Churra, 172",
    "sg:city":"Churra",
    "sg:orig_category":"Electricidad: Instaladores",
    "sg:phone":"+34 968 85 85 63",
    "sg:postcode":"30110",
    "sg:province":"Murcia",
    "wof:name":"Instalaciones Electricas Cabeluz S.l.",
    "wof:placetype":"venue"
},
  "geometry": {"coordinates":[-1.1360189915,38.0214653015],"type":"Point"}
}