{
  "type": "Feature",
  "properties": {
    "addr:full":"Calle de Felix Marti Alpera, 59 Cartagena Murcia 30204",
    "addr:housenumber":"59",
    "addr:postcode":"30204",
    "addr:street":"Calle De Felix Marti Alpera",
    "iso:country":"ES",
    "sg:address":"Calle de Felix Marti Alpera, 59",
    "sg:city":"Cartagena",
    "sg:orig_category":"Caf\u00c9s, Bares, Cervecer\u00cdas",
    "sg:phone":"+34 968 31 38 50",
    "sg:postcode":"30204",
    "sg:province":"Murcia",
    "wof:name":"Garcia Guillen Francisco",
    "wof:placetype":"venue"
},
  "geometry": {"coordinates":[-0.9923490286,37.6158485413],"type":"Point"}
}