{
  "type": "Feature",
  "properties": {
    "addr:full":"Las Ace\u00f1as, S/n Ace\u00d1as Asturias 33719",
    "addr:housenumber":"s",
    "addr:postcode":"33719",
    "addr:street":"/ N Acen\u0303As Asturias",
    "iso:country":"ES",
    "sg:address":"Las Ace\u00f1as, S/n",
    "sg:city":"Ace\u00d1as",
    "sg:orig_category":"Promotores Constructores",
    "sg:phone":"+34 985 47 34 91",
    "sg:postcode":"33719",
    "sg:province":"Asturias",
    "wof:name":"Rodriguez Mouriz Santiago",
    "wof:placetype":"venue"
},
  "geometry": {"coordinates":[-6.6598329544,43.5291023254],"type":"Point"}
}