{
  "type": "Feature",
  "properties": {
    "addr:full":"Avda Mare Nostrum, 10 Alacant Alicante 03007",
    "addr:housenumber":"10",
    "addr:postcode":"03007",
    "addr:street":"Avda Mare Nostrum",
    "iso:country":"ES",
    "sg:address":"Avda Mare Nostrum, 10",
    "sg:city":"Alacant",
    "sg:orig_category":"Suministros Y Materiales Industriales",
    "sg:phone":"+34 965 10 34 12",
    "sg:postcode":"03007",
    "sg:province":"Alicante",
    "wof:name":"Akra-se\u00d1al S.l.",
    "wof:placetype":"venue"
},
  "geometry": {"coordinates":[-0.5244321227,38.3419761658],"type":"Point"}
}