{
  "type": "Feature",
  "properties": {
    "addr:full":"Av Carrilet, 170 Hospitalet Llobregat Barcelona 08901",
    "addr:housenumber":"170",
    "addr:postcode":"08901",
    "addr:street":"Av Carrilet",
    "iso:country":"ES",
    "sg:address":"Av Carrilet, 170",
    "sg:city":"Hospitalet Llobregat",
    "sg:orig_category":"Mec\u00c1nico Del Autom\u00d3vil",
    "sg:phone":"+34 933 38 05 16",
    "sg:postcode":"08901",
    "sg:province":"Barcelona",
    "wof:name":"Mu\u00f1oz Mu\u00f1oz Meliton",
    "wof:placetype":"venue"
},
  "geometry": {"coordinates":[2.1147539616,41.3624763489],"type":"Point"}
}