{
  "type": "Feature",
  "properties": {
    "addr:full":"Praz San Antonio (de), 2 Ourense Ourense 32004",
    "addr:postcode":"32004",
    "addr:street":"Praz San Antonio De",
    "iso:country":"ES",
    "sg:address":"Praz San Antonio (de), 2",
    "sg:city":"Ourense",
    "sg:orig_category":"Zapatos (al Por Menor)",
    "sg:phone":"+34 988 22 09 88",
    "sg:postcode":"32004",
    "sg:province":"Ourense",
    "wof:name":"Gomez Guede Ana Maria",
    "wof:placetype":"venue"
},
  "geometry": {"coordinates":[-7.8511948586,42.3493232727],"type":"Point"}
}