{
  "type": "Feature",
  "properties": {
    "addr:full":"Avda Hermanos Maristas, 6 Valencia Valencia 46013",
    "addr:housenumber":"6",
    "addr:postcode":"46013",
    "addr:street":"Avda Hermanos Maristas",
    "iso:country":"ES",
    "sg:address":"Avda Hermanos Maristas, 6",
    "sg:city":"Valencia",
    "sg:orig_category":"Alimentaci\u00d3n General (al Por Menor)",
    "sg:phone":"+34 963 74 92 80",
    "sg:postcode":"46013",
    "sg:province":"Valencia",
    "wof:name":"Chetan Parqash Jain",
    "wof:placetype":"venue"
},
  "geometry": {"coordinates":[-0.3689019978,39.4508895874],"type":"Point"}
}