{
  "type": "Feature",
  "properties": {
    "addr:full":"Urb Molino De Viento, S/n Hinojosa Del Duque C\u00f3rdoba 14270",
    "addr:housenumber":"s / n",
    "addr:postcode":"14270",
    "addr:street":"Urb Molino De Viento;Co\u0301Rdoba",
    "iso:country":"ES",
    "sg:address":"Urb Molino De Viento, S/n",
    "sg:city":"Hinojosa Del Duque",
    "sg:orig_category":"Fabrica De Charcuter\u00cda",
    "sg:phone":"+34 957 14 20 56",
    "sg:postcode":"14270",
    "sg:province":"C\u00f3rdoba",
    "wof:name":"Jamones Y Embutidos La Hinojosa S.l.",
    "wof:placetype":"venue"
},
  "geometry": {"coordinates":[-5.1483325958,38.5009918213],"type":"Point"}
}