{
  "type": "Feature",
  "properties": {
    "addr:full":"Ctra. Nacional 340, Km. 0123,0 Sta. Magdalena Pulpis Castell\u00f3n 12597",
    "addr:postcode":"12597",
    "addr:street":"Ctra. Nacional 340 Km. 0123,0 Sta. Magdalena Pulpis Castello\u0301N",
    "iso:country":"ES",
    "sg:address":"Ctra. Nacional 340, Km. 0123,0",
    "sg:city":"Sta. Magdalena Pulpis",
    "sg:orig_category":"Distribuci\u00d3n De Petr\u00d3leo Y Derivados",
    "sg:phone":"+34 964 41 52 72",
    "sg:postcode":"12597",
    "sg:province":"Castell\u00f3n",
    "wof:name":"Zaragoza-puig E Hijos S.l.",
    "wof:placetype":"venue"
},
  "geometry": {"coordinates":[0.232050702,40.3102302551],"type":"Point"}
}