{
  "type": "Feature",
  "properties": {
    "iso:country":"ES",
    "sg:address":"Carrer de Mestre Serradesanferm, 1",
    "sg:city":"Barcelona",
    "sg:orig_category":"Papeler\u00cdas, Librer\u00cdas",
    "sg:phone":"+34 933 58 08 67",
    "sg:postcode":"08032",
    "sg:province":"Barcelona",
    "wof:name":"Andres Ruldua Francisco",
    "wof:placetype":"venue"
},
  "geometry": {"coordinates":[2.1604111195,41.4291801453],"type":"Point"}
}