{
  "type": "Feature",
  "properties": {
    "iso:country":"ES",
    "sg:address":"Pase Marques De Zafra, 41",
    "sg:city":"Madrid",
    "sg:orig_category":"Radiocomunicaciones, Telefon\u00cda M\u00d3vil, Radiomensajer\u00cda: Servicios, Comercializaci\u00d3n",
    "sg:phone":"+34 913 56 52 04",
    "sg:postcode":"28028",
    "sg:province":"Madrid",
    "wof:name":"Castillo Aguayo Flor",
    "wof:placetype":"venue"
},
  "geometry": {"coordinates":[-3.6635110378,40.4256401062],"type":"Point"}
}