{
  "type": "Feature",
  "properties": {
    "addr:full":"Calle de Valladolid, 30 Medina Campo Valladolid 47400",
    "addr:housenumber":"30",
    "addr:postcode":"47400",
    "addr:street":"Calle De Valladolid",
    "iso:country":"ES",
    "sg:address":"Calle de Valladolid, 30",
    "sg:city":"Medina Campo",
    "sg:orig_category":"Alimentaci\u00d3n General (al Por Menor)",
    "sg:phone":"+34 983 80 09 98",
    "sg:postcode":"47400",
    "sg:province":"Valladolid",
    "wof:name":"Valero Barrero Jose",
    "wof:placetype":"venue"
},
  "geometry": {"coordinates":[-4.9131889343,41.3154563904],"type":"Point"}
}