{
  "type": "Feature",
  "properties": {
    "addr:full":"Calle de Estartetxe, 10 Leioa Vizcaya 48940",
    "addr:housenumber":"10",
    "addr:postcode":"48940",
    "addr:street":"Calle De Estartetxe",
    "iso:country":"ES",
    "sg:address":"Calle de Estartetxe, 10",
    "sg:city":"Leioa",
    "sg:orig_category":"Bisuter\u00cda, Joyer\u00cda, Relojer\u00cda (al Por Menor)",
    "sg:phone":"+34 944 05 16 92",
    "sg:postcode":"48940",
    "sg:province":"Vizcaya",
    "wof:name":"Urbieta Y Perez, C.b.",
    "wof:placetype":"venue"
},
  "geometry": {"coordinates":[-2.9892458916,43.3275756836],"type":"Point"}
}