{
  "type": "Feature",
  "properties": {
    "iso:country":"ES",
    "sg:address":"Calle de Maria Uceda Diaz, 25",
    "sg:city":"Cenes Vega",
    "sg:orig_category":"Agencias Y Agentes Comerciales, Representantes",
    "sg:phone":"+34 958 48 62 63",
    "sg:postcode":"18190",
    "sg:province":"Granada",
    "wof:name":"Fernandez Fernandez Francisco Javier",
    "wof:placetype":"venue"
},
  "geometry": {"coordinates":[-3.5400190353,37.1605606079],"type":"Point"}
}