{
  "type": "Feature",
  "properties": {
    "addr:full":"Pol Ind Nevero, S/n Badajoz Badajoz 06006",
    "addr:housenumber":"s",
    "addr:postcode":"06006",
    "addr:street":"/ N",
    "iso:country":"ES",
    "sg:address":"Pol Ind Nevero, S/n",
    "sg:city":"Badajoz",
    "sg:orig_category":"Electricidad: Instaladores",
    "sg:phone":"+34 924 27 19 41",
    "sg:postcode":"06006",
    "sg:province":"Badajoz",
    "wof:name":"Instalaciones Y Montajes Electricos Y Saneamiento S.a.",
    "wof:placetype":"venue"
},
  "geometry": {"coordinates":[-7.0317192078,38.9165992737],"type":"Point"}
}