{
  "type": "Feature",
  "properties": {
    "addr:full":"Calle de Escosura, 67 Zaragoza Zaragoza 50005",
    "addr:housenumber":"67",
    "addr:postcode":"50005",
    "addr:street":"Calle De Escosura",
    "iso:country":"ES",
    "sg:address":"Calle de Escosura, 67",
    "sg:city":"Zaragoza",
    "sg:orig_category":"Asesor\u00cda Sobre Comunicaci\u00d3n De Empresas",
    "sg:phone":"+34 976 56 73 00",
    "sg:postcode":"50005",
    "sg:province":"Zaragoza",
    "wof:name":"Contabilidad Fiscalidad Y Gestion Empresarial S.l.",
    "wof:placetype":"venue"
},
  "geometry": {"coordinates":[-0.899254024,41.6490478516],"type":"Point"}
}