{
  "type": "Feature",
  "properties": {
    "iso:country":"ES",
    "sg:address":"Casa Esteve, S/n",
    "sg:city":"Espot",
    "sg:classifiers":[
        {
            "category":"Taxi",
            "type":"Transportation"
        }
    ],
    "sg:phone":"+34 973 62 40 19",
    "sg:postcode":"25597",
    "sg:province":"Lleida",
    "wof:name":"Castellarnau Carrera Antonio",
    "wof:placetype":"venue"
},
  "geometry": {"coordinates":[1.0894809961,42.575504303],"type":"Point"}
}