{
  "type": "Feature",
  "properties": {
    "iso:country":"ES",
    "sg:address":"Plaz Republica Del Ecuador, 6",
    "sg:city":"Madrid",
    "sg:orig_category":"Comercio De Cuadros, L\u00c1minas Y Reproducciones De Obras De Arte",
    "sg:phone":"+34 914 58 89 57",
    "sg:postcode":"28016",
    "sg:province":"Madrid",
    "wof:name":"Martinez-botas Gonzalez Jose Francisco",
    "wof:placetype":"venue"
},
  "geometry": {"coordinates":[-3.6777200699,40.4553718567],"type":"Point"}
}