{
  "type": "Feature",
  "properties": {
    "addr:full":"Calle de Santa Lucia, 15 Sevilla Sevilla 41003",
    "addr:housenumber":"15",
    "addr:postcode":"41003",
    "addr:street":"Calle De Santa Lucia",
    "iso:country":"ES",
    "sg:address":"Calle de Santa Lucia, 15",
    "sg:city":"Sevilla",
    "sg:orig_category":"Pintura, Barniz, Productos Asimilables (fabricaci\u00d3n, Al Por Mayor)",
    "sg:phone":"+34 954 41 08 41",
    "sg:postcode":"41003",
    "sg:province":"Sevilla",
    "wof:name":"Limpieza Torresol S.l",
    "wof:placetype":"venue"
},
  "geometry": {"coordinates":[-5.9828701019,37.3974494934],"type":"Point"}
}