{
  "type": "Feature",
  "properties": {
    "iso:country":"ES",
    "sg:address":"Carrer de Can Pantiquet, 47",
    "sg:city":"Mollet Valles",
    "sg:orig_category":"Papeler\u00cdas: Art\u00cdculos (al Por Mayor)",
    "sg:phone":"+34 935 70 66 33",
    "sg:postcode":"08100",
    "sg:province":"Barcelona",
    "wof:name":"Binney And Smith Europe L.t.d.",
    "wof:placetype":"venue"
},
  "geometry": {"coordinates":[2.2183699608,41.5445747375],"type":"Point"}
}