{
  "type": "Feature",
  "properties": {
    "iso:country":"ES",
    "sg:address":"Calle de Feria, 39",
    "sg:city":"Albacete",
    "sg:orig_category":"Veh\u00cdculos De Ocasi\u00d3n",
    "sg:phone":"+34 967 22 18 98",
    "sg:postcode":"02005",
    "sg:province":"Albacete",
    "wof:name":"Diaz Narro Joaquin",
    "wof:placetype":"venue"
},
  "geometry": {"coordinates":[-1.8616529703,38.9963569641],"type":"Point"}
}