{
  "type": "Feature",
  "properties": {
    "addr:full":"Carrer de Sant Joan, 61 Calella Barcelona 08370",
    "addr:housenumber":"61",
    "addr:postcode":"08370",
    "addr:street":"Carrer De Sant Joan",
    "iso:country":"ES",
    "sg:address":"Carrer de Sant Joan, 61",
    "sg:city":"Calella",
    "sg:orig_category":"Ropa De Hogar (al Por Menor)",
    "sg:phone":"+34 937 66 22 50",
    "sg:postcode":"08370",
    "sg:province":"Barcelona",
    "wof:name":"Pla Rovira Dolores",
    "wof:placetype":"venue"
},
  "geometry": {"coordinates":[2.6612520218,41.6149940491],"type":"Point"}
}