{
  "type": "Feature",
  "properties": {
    "addr:full":"Calle de Jose Luis De Arrese, 32 Madrid Madrid 28017",
    "addr:housenumber":"32",
    "addr:postcode":"madrid;28017",
    "addr:street":"Calle De Jose Luis De Arrese",
    "iso:country":"ES",
    "sg:address":"Calle de Jose Luis De Arrese, 32",
    "sg:city":"Madrid",
    "sg:orig_category":"Asesor\u00cdas",
    "sg:phone":"+34 914 05 01 01",
    "sg:postcode":"28017",
    "sg:province":"Madrid",
    "sg:website":"www.fortisegur.com",
    "wof:name":"Fortisegur S.l.",
    "wof:placetype":"venue"
},
  "geometry": {"coordinates":[-3.6519639492,40.4211997986],"type":"Point"}
}