{
  "type": "Feature",
  "properties": {
    "addr:full":"Carrer de Pintor Murillo, 53 Rubi Barcelona 08191",
    "addr:housenumber":"53",
    "addr:postcode":"08191",
    "addr:street":"Carrer De Pintor Murillo",
    "iso:country":"ES",
    "sg:address":"Carrer de Pintor Murillo, 53",
    "sg:city":"Rubi",
    "sg:orig_category":"Asesor\u00cda Fiscal Y Jur\u00cddica",
    "sg:phone":"+34 935 88 42 10",
    "sg:postcode":"08191",
    "sg:province":"Barcelona",
    "wof:name":"Assessoria I Gestio Ridao S.l.",
    "wof:placetype":"venue"
},
  "geometry": {"coordinates":[2.0315752029,41.4879951477],"type":"Point"}
}