{
  "type": "Feature",
  "properties": {
    "addr:full":"Calle de Jose Manuel Zaragoza, 2 Villaca\u00f1as Toledo 45860",
    "addr:housenumber":"2",
    "addr:postcode":"45860",
    "addr:street":"Calle De Jose Manuel Zaragoza",
    "iso:country":"ES",
    "sg:address":"Calle de Jose Manuel Zaragoza, 2",
    "sg:city":"Villaca\u00f1as",
    "sg:orig_category":"Confecci\u00d3n (fabricaci\u00d3n, Al Por Mayor)",
    "sg:phone":"+34 925 20 05 59",
    "sg:postcode":"45860",
    "sg:province":"Toledo",
    "wof:name":"Val Carrascosa Florentino Del",
    "wof:placetype":"venue"
},
  "geometry": {"coordinates":[-3.3346300125,39.6207313538],"type":"Point"}
}