{
  "type": "Feature",
  "properties": {
    "iso:country":"ES",
    "sg:address":"Calle de Alcalde Tarrega, 3",
    "sg:city":"Castellon",
    "sg:orig_category":"Peluqueros: De Se\u00d1oras",
    "sg:phone":"+34 964 23 05 31",
    "sg:postcode":"12004",
    "sg:province":"Castell\u00f3n",
    "wof:name":"Balaguer Altaba Rosa Ana",
    "wof:placetype":"venue"
},
  "geometry": {"coordinates":[-0.0346551985,39.9888916016],"type":"Point"}
}