{
  "type": "Feature",
  "properties": {
    "addr:full":"Moldes, 47 Moldes Pontevedra 36645",
    "addr:housenumber":"47",
    "addr:postcode":"36645",
    "addr:street":"Moldes",
    "iso:country":"ES",
    "sg:address":"Moldes, 47",
    "sg:city":"Moldes",
    "sg:orig_category":"Instalaci\u00d3n De Aspiraci\u00d3n De Gases Y Humos",
    "sg:phone":"+34 986 55 60 30",
    "sg:postcode":"36645",
    "sg:province":"Pontevedra",
    "wof:name":"Baleiron Gomez Francisco",
    "wof:placetype":"venue"
},
  "geometry": {"coordinates":[-8.6490335464,42.7007255554],"type":"Point"}
}