{
  "type": "Feature",
  "properties": {
    "addr:full":"Calle de Fueros De Leon, 1 Ponferrada Le\u00f3n 24400",
    "addr:housenumber":"1",
    "addr:postcode":"24400",
    "addr:street":"Calle De Fueros De Leon",
    "iso:country":"ES",
    "sg:address":"Calle de Fueros De Leon, 1",
    "sg:city":"Ponferrada",
    "sg:orig_category":"Laboratorios Y Trabajos De Fotograf\u00cda, V\u00cddeo Y Cine",
    "sg:phone":"+34 987 42 87 51",
    "sg:postcode":"24400",
    "sg:province":"Le\u00f3n",
    "wof:name":"Falf Biercolor S.l.",
    "wof:placetype":"venue"
},
  "geometry": {"coordinates":[-6.6008868217,42.5485687256],"type":"Point"}
}