{
  "type": "Feature",
  "properties": {
    "iso:country":"ES",
    "sg:address":"Calle de Graciano Atienza, 9",
    "sg:city":"Villarrobledo",
    "sg:orig_category":"Asesor\u00cda Fiscal Y Jur\u00cddica",
    "sg:phone":"+34 967 14 07 23",
    "sg:postcode":"02600",
    "sg:province":"Albacete",
    "wof:name":"Rosillo Hijo S.l.",
    "wof:placetype":"venue"
},
  "geometry": {"coordinates":[-2.6039090157,39.2646141052],"type":"Point"}
}