{
  "type": "Feature",
  "properties": {
    "addr:full":"Rua Castelao, 168 Grove Pontevedra 36980",
    "addr:housenumber":"168",
    "addr:postcode":"36980",
    "addr:street":"Rua Castelao;Grove Pontevedra",
    "iso:country":"ES",
    "sg:address":"Rua Castelao, 168",
    "sg:city":"Grove",
    "sg:orig_category":"Caf\u00c9s, Bares, Cervecer\u00cdas",
    "sg:phone":"+34 986 73 35 57",
    "sg:postcode":"36980",
    "sg:province":"Pontevedra",
    "wof:name":"Escalante Castro Antonio",
    "wof:placetype":"venue"
},
  "geometry": {"coordinates":[-8.858259201,42.4904518127],"type":"Point"}
}