{
  "type": "Feature",
  "properties": {
    "addr:full":"Calle de Poeta Querol, 11 Valencia Valencia 46002",
    "addr:housenumber":"11",
    "addr:postcode":"46002",
    "addr:street":"Calle De Poeta Querol",
    "iso:country":"ES",
    "sg:address":"Calle de Poeta Querol, 11",
    "sg:city":"Valencia",
    "sg:orig_category":"Promotores Constructores",
    "sg:phone":"+34 963 52 60 42",
    "sg:postcode":"46002",
    "sg:province":"Valencia",
    "wof:name":"Prietalba S.l.",
    "wof:placetype":"venue"
},
  "geometry": {"coordinates":[-0.3740809858,39.4713363647],"type":"Point"}
}