{
  "type": "Feature",
  "properties": {
    "iso:country":"ES",
    "sg:address":"Avda Alcalde Lorenzo Carbonell, 71",
    "sg:city":"Alacant",
    "sg:orig_category":"Distribuci\u00d3n De Petr\u00d3leo Y Derivados",
    "sg:phone":"+34 965 11 52 76",
    "sg:postcode":"03008",
    "sg:province":"Alicante",
    "wof:name":"Estacion De Servicio Llorca S.l.",
    "wof:placetype":"venue"
},
  "geometry": {"coordinates":[-0.5167890191,38.3390197754],"type":"Point"}
}