{
  "type": "Feature",
  "properties": {
    "iso:country":"ES",
    "sg:address":"Carr Progres (del), 34",
    "sg:city":"Betxi",
    "sg:orig_category":"Pintura Y Barniz (al Por Menor)",
    "sg:phone":"+34 964 62 22 89",
    "sg:postcode":"12549",
    "sg:province":"Castell\u00f3n",
    "wof:name":"Cabedo Vicent Manuel",
    "wof:placetype":"venue"
},
  "geometry": {"coordinates":[-0.1963589936,39.9285507202],"type":"Point"}
}