{
  "type": "Feature",
  "properties": {
    "iso:country":"ES",
    "sg:address":"Calle de Claudio Coello, 58",
    "sg:city":"Madrid",
    "sg:orig_category":"Molduras, Junquillos, Listones Y Molduras Perforadas",
    "sg:phone":"+34 915 75 06 95",
    "sg:postcode":"28001",
    "sg:province":"Madrid",
    "wof:name":"Pons Burgada Antonio",
    "wof:placetype":"venue"
},
  "geometry": {"coordinates":[-3.6861395836,40.4282150269],"type":"Point"}
}