{
  "type": "Feature",
  "properties": {
    "iso:country":"ES",
    "sg:address":"Avda Portugal (de), 2",
    "sg:city":"Barco",
    "sg:orig_category":"Distribuci\u00d3n De Petr\u00d3leo Y Derivados",
    "sg:phone":"+34 988 32 09 00",
    "sg:postcode":"32300",
    "sg:province":"Ourense",
    "wof:name":"Vegamolinos S.l.",
    "wof:placetype":"venue"
},
  "geometry": {"coordinates":[-6.9933590889,42.4203567505],"type":"Point"}
}