{
  "type": "Feature",
  "properties": {
    "addr:full":"Calle de Pio Xii, 2 \u00c1lava 01400",
    "addr:housenumber":"2",
    "addr:postcode":"01400",
    "addr:street":"Calle De Pio Xii;A\u0301Lava",
    "iso:country":"ES",
    "sg:address":"Calle de Pio Xii, 2",
    "sg:classifiers":[
        {
            "category":"Personal",
            "subcategory":"Barber",
            "type":"Services"
        }
    ],
    "sg:phone":"+34 946 72 11 88",
    "sg:postcode":"01400",
    "sg:province":"\u00c1lava",
    "sg:tags":[
        "caballeros",
        "de",
        "peluqueros"
    ],
    "wof:name":"Riti Ileapaindegia, Ricardo Jose Arza Ria\u00f1o",
    "wof:placetype":"venue"
},
  "geometry": {"coordinates":[-2.9647090435,43.1417808533],"type":"Point"}
}