{
  "type": "Feature",
  "properties": {
    "iso:country":"ES",
    "sg:address":"Calle de San Bartolome, 22",
    "sg:city":"Beas",
    "sg:orig_category":"Laboratorios Farmac\u00c9uticos",
    "sg:phone":"+34 959 30 90 33",
    "sg:postcode":"21630",
    "sg:province":"Huelva",
    "wof:name":"Romero Matias Manuel",
    "wof:placetype":"venue"
},
  "geometry": {"coordinates":[-6.7921390533,37.425037384],"type":"Point"}
}