{
  "type": "Feature",
  "properties": {
    "iso:country":"ES",
    "sg:address":"Avgd Doctor Fleming, 21",
    "sg:city":"Lleida",
    "sg:orig_category":"Inmobiliaria (agencias)",
    "sg:phone":"+34 973 27 14 16",
    "sg:postcode":"25006",
    "sg:province":"Lleida",
    "sg:website":"www.finques3cases.com",
    "wof:name":"Finques 3 Clases Fleming S.l.",
    "wof:placetype":"venue"
},
  "geometry": {"coordinates":[0.6157870293,41.6193847656],"type":"Point"}
}