{
  "type": "Feature",
  "properties": {
    "addr:full":"Avda Escritores (los), 42 Ponferrada Le\u00f3n 24400",
    "addr:housenumber":"42",
    "addr:postcode":"24400",
    "addr:street":"Avda Escritores Los",
    "iso:country":"ES",
    "sg:address":"Avda Escritores (los), 42",
    "sg:city":"Ponferrada",
    "sg:orig_category":"Centros Empresariales",
    "sg:phone":"+34 987 42 61 58",
    "sg:postcode":"24400",
    "sg:province":"Le\u00f3n",
    "wof:name":"Gardea De La Fuente Baldomero",
    "wof:placetype":"venue"
},
  "geometry": {"coordinates":[-6.6063342094,42.5488815308],"type":"Point"}
}