{
  "type": "Feature",
  "properties": {
    "iso:country":"ES",
    "sg:address":"G.v. Corts Catalanes, 433",
    "sg:city":"Barcelona",
    "sg:orig_category":"Ense\u00d1anza Variada",
    "sg:phone":"+34 934 25 44 40",
    "sg:postcode":"08015",
    "sg:province":"Barcelona",
    "sg:website":"www.kore.es",
    "wof:name":"Mulero Jimenez Isabel",
    "wof:placetype":"venue"
},
  "geometry": {"coordinates":[2.1529359818,41.378326416],"type":"Point"}
}