{
  "type": "Feature",
  "properties": {
    "iso:country":"ES",
    "sg:address":"Calle de Rivas De Neira, 5",
    "sg:city":"Vejer De La Frontera",
    "sg:orig_category":"Abogados",
    "sg:phone":"+34 956 44 72 56",
    "sg:postcode":"11150",
    "sg:province":"C\u00e1diz",
    "wof:name":"Vejeriega Consulting S.l.",
    "wof:placetype":"venue"
},
  "geometry": {"coordinates":[-5.9670090675,36.2526893616],"type":"Point"}
}