{
  "type": "Feature",
  "properties": {
    "addr:full":"Avda Virgen De Gracia, S/n Fresneda Teruel 44596",
    "addr:housenumber":"s / n",
    "addr:postcode":"44596",
    "addr:street":"Avda Virgen De Gracia",
    "iso:country":"ES",
    "sg:address":"Avda Virgen De Gracia, S/n",
    "sg:city":"Fresneda",
    "sg:orig_category":"Empresas De Carpinter\u00cda De Madera",
    "sg:phone":"+34 978 85 43 35",
    "sg:postcode":"44596",
    "sg:province":"Teruel",
    "wof:name":"Esteve Monserrat German",
    "wof:placetype":"venue"
},
  "geometry": {"coordinates":[0.0762450024,40.9296646118],"type":"Point"}
}