{
  "type": "Feature",
  "properties": {
    "iso:country":"ES",
    "sg:address":"Calle de Cristo, 5",
    "sg:city":"Almogia",
    "sg:orig_category":"Hilaturas, Hilos Y Actividades Relacionadas",
    "sg:phone":"+34 952 43 06 11",
    "sg:postcode":"29150",
    "sg:province":"M\u00e1laga",
    "wof:name":"Garcia Mayorga Maria Dolores",
    "wof:placetype":"venue"
},
  "geometry": {"coordinates":[-4.5402932167,36.8252410889],"type":"Point"}
}