{
  "type": "Feature",
  "properties": {
    "addr:full":"Calle de Enrique Ii, 2 Pola De Siero Asturias 33510",
    "addr:housenumber":"2",
    "addr:postcode":"33510",
    "addr:street":"Calle De Enrique Ii",
    "iso:country":"ES",
    "sg:address":"Calle de Enrique Ii, 2",
    "sg:city":"Pola De Siero",
    "sg:orig_category":"Electrodom\u00c9sticos (al Por Menor)",
    "sg:phone":"+34 985 72 15 96",
    "sg:postcode":"33510",
    "sg:province":"Asturias",
    "wof:name":"Gutierrez Diaz Avelino",
    "wof:placetype":"venue"
},
  "geometry": {"coordinates":[-5.6612091064,43.3928985596],"type":"Point"}
}