{
  "type": "Feature",
  "properties": {
    "iso:country":"ES",
    "sg:address":"Calle de San Roque, 2",
    "sg:city":"Alcorcon",
    "sg:orig_category":"Peluqueros: De Se\u00d1oras",
    "sg:phone":"+34 916 44 25 42",
    "sg:postcode":"28921",
    "sg:province":"Madrid",
    "wof:name":"Lopez Arranz Maximo",
    "wof:placetype":"venue"
},
  "geometry": {"coordinates":[-3.8248989582,40.3441390991],"type":"Point"}
}