{
  "type": "Feature",
  "properties": {
    "iso:country":"ES",
    "sg:address":"Calle de Santa Orosia, 2",
    "sg:city":"Zaragoza",
    "sg:orig_category":"Agencias Y Agentes Comerciales, Representantes",
    "sg:phone":"+34 976 33 97 10",
    "sg:postcode":"50010",
    "sg:province":"Zaragoza",
    "wof:name":"Jimenez Rodrigo Carlos",
    "wof:placetype":"venue"
},
  "geometry": {"coordinates":[-0.9015300274,41.6557197571],"type":"Point"}
}