{
  "type": "Feature",
  "properties": {
    "addr:full":"Calle de Menendez Pelayo, 1 Torres Cotillas Murcia 30565",
    "addr:housenumber":"1",
    "addr:postcode":"30565",
    "addr:street":"Calle De Menendez Pelayo",
    "iso:country":"ES",
    "sg:address":"Calle de Menendez Pelayo, 1",
    "sg:city":"Torres Cotillas",
    "sg:orig_category":"Peluquer\u00cdas, Peluquer\u00cda Mixta",
    "sg:phone":"+34 968 62 72 39",
    "sg:postcode":"30565",
    "sg:province":"Murcia",
    "wof:name":"Peluqueria Dotrix S.l.l.",
    "wof:placetype":"venue"
},
  "geometry": {"coordinates":[-1.2443300486,38.0245170593],"type":"Point"}
}