{
  "type": "Feature",
  "properties": {
    "addr:full":"Calle de Yague De Salas, 14 Teruel Teruel 44001",
    "addr:housenumber":"14",
    "addr:postcode":"44001",
    "addr:street":"Calle De Yague De Salas",
    "iso:country":"ES",
    "sg:address":"Calle de Yague De Salas, 14",
    "sg:city":"Teruel",
    "sg:orig_category":"Ropa Para Se\u00d1oras (al Por Menor)",
    "sg:phone":"+34 978 61 08 35",
    "sg:postcode":"44001",
    "sg:province":"Teruel",
    "sg:website":"www.benetton.com",
    "wof:name":"Franquicias Teruel S.l.",
    "wof:placetype":"venue"
},
  "geometry": {"coordinates":[-1.1084569693,40.3433609009],"type":"Point"}
}