{
  "type": "Feature",
  "properties": {
    "addr:full":"Av Manuel Carrasco I Formiguera, S/n Canonja Tarragona 43110",
    "addr:housenumber":"s / n",
    "addr:postcode":"43110",
    "addr:street":"Av Manuel Carrasco I Formiguera",
    "iso:country":"ES",
    "sg:address":"Av Manuel Carrasco I Formiguera, S/n",
    "sg:city":"Canonja",
    "sg:orig_category":"Empresarios",
    "sg:phone":"+34 977 54 82 86",
    "sg:postcode":"43110",
    "sg:province":"Tarragona",
    "wof:name":"Caixa D'estalvis De Tarragona",
    "wof:placetype":"venue"
},
  "geometry": {"coordinates":[1.1845550537,41.119758606],"type":"Point"}
}