{
  "type": "Feature",
  "properties": {
    "addr:full":"Calle de Fielato, 3 Espinosa De Los Monteros Burgos 09560",
    "addr:housenumber":"3",
    "addr:postcode":"09560",
    "addr:street":"Calle De Fielato",
    "iso:country":"ES",
    "sg:address":"Calle de Fielato, 3",
    "sg:city":"Espinosa De Los Monteros",
    "sg:orig_category":"Molduras, Junquillos, Listones Y Molduras Perforadas",
    "sg:phone":"+34 947 12 03 00",
    "sg:postcode":"09560",
    "sg:province":"Burgos",
    "wof:name":"Garcia Segura Jose Javier",
    "wof:placetype":"venue"
},
  "geometry": {"coordinates":[-3.5524101257,43.0772361755],"type":"Point"}
}