{
  "type": "Feature",
  "properties": {
    "addr:full":"Av Alexandre Rossello, 12 Palma Islas Baleares 07...",
    "addr:housenumber":"12;07 ...",
    "addr:street":"Av Alexandre Rossello;Islas Baleares",
    "iso:country":"ES",
    "sg:address":"Av Alexandre Rossello, 12",
    "sg:city":"Palma",
    "sg:orig_category":"Centros Comerciales Y Grandes Tiendas",
    "sg:phone":"+34 971 77 01 77",
    "sg:postcode":"07...",
    "sg:province":"Islas Baleares",
    "sg:website":"www.elcorteingles.es",
    "wof:name":"El Corte Ingles S.a.",
    "wof:placetype":"venue"
},
  "geometry": {"coordinates":[2.656692028,39.5731277466],"type":"Point"}
}