{
  "type": "Feature",
  "properties": {
    "iso:country":"ES",
    "sg:address":"Calle de San Buenaventura, 1",
    "sg:city":"Moraleja",
    "sg:orig_category":"Ambulancias",
    "sg:phone":"+34 927 14 74 23",
    "sg:postcode":"10840",
    "sg:province":"C\u00e1ceres",
    "wof:name":"Gomez Garcia Jose Manuel",
    "wof:placetype":"venue"
},
  "geometry": {"coordinates":[-6.6610617638,40.0685768127],"type":"Point"}
}