{
  "type": "Feature",
  "properties": {
    "iso:country":"ES",
    "sg:address":"Calle de Villar Y Villate, 6",
    "sg:city":"Sestao",
    "sg:orig_category":"Peluqueros: De Se\u00d1oras",
    "sg:phone":"+34 944 96 79 05",
    "sg:postcode":"48910",
    "sg:province":"Vizcaya",
    "wof:name":"Maria Teresa Jurado Seco",
    "wof:placetype":"venue"
},
  "geometry": {"coordinates":[-3.0070300102,43.3083648682],"type":"Point"}
}