{
  "type": "Feature",
  "properties": {
    "addr:full":"Trva San Ignacio, 55 Marchena Sevilla 41620",
    "addr:housenumber":"55",
    "addr:postcode":"41620",
    "addr:street":"Trva San Ignacio",
    "iso:country":"ES",
    "sg:address":"Trva San Ignacio, 55",
    "sg:city":"Marchena",
    "sg:orig_category":"Transporte En General",
    "sg:phone":"+34 954 84 34 70",
    "sg:postcode":"41620",
    "sg:province":"Sevilla",
    "wof:name":"Alvarez Vicente Jose",
    "wof:placetype":"venue"
},
  "geometry": {"coordinates":[-5.4174833298,37.322177887],"type":"Point"}
}