{
  "type": "Feature",
  "properties": {
    "iso:country":"ES",
    "sg:address":"Santo Estebo, 117",
    "sg:city":"Santo",
    "sg:orig_category":"Ingeniero",
    "sg:phone":"+34 982 50 21 08",
    "sg:postcode":"27818",
    "sg:province":"Lugo",
    "wof:name":"Lamela Suarez Jose Eulogio",
    "wof:placetype":"venue"
},
  "geometry": {"coordinates":[-7.6814470291,43.245716095],"type":"Point"}
}