{
  "type": "Feature",
  "properties": {
    "iso:country":"ES",
    "sg:address":"Ctra Martorell, Km. 0012,0",
    "sg:city":"Terrassa",
    "sg:orig_category":"Maquinaria Para Industrias Diversas",
    "sg:phone":"+34 937 88 07 05",
    "sg:postcode":"08224",
    "sg:province":"Barcelona",
    "wof:name":"Jimenez Cabrera Filomena",
    "wof:placetype":"venue"
},
  "geometry": {"coordinates":[2.0068631172,41.5569572449],"type":"Point"}
}