{
  "type": "Feature",
  "properties": {
    "iso:country":"ES",
    "sg:address":"Rua Velazquez Moreno, 3",
    "sg:city":"Vigo",
    "sg:orig_category":"Promotores Constructores",
    "sg:phone":"+34 986 43 46 06",
    "sg:postcode":"36201",
    "sg:province":"Pontevedra",
    "wof:name":"Opecen Inmobiliaria S.a.",
    "wof:placetype":"venue"
},
  "geometry": {"coordinates":[-8.7215709686,42.2387771606],"type":"Point"}
}