{
  "type": "Feature",
  "properties": {
    "addr:full":"Calle de Vida, 17 Sevilla Sevilla 41004",
    "addr:housenumber":"17",
    "addr:postcode":"41004",
    "addr:street":"Calle De Vida",
    "iso:country":"ES",
    "sg:address":"Calle de Vida, 17",
    "sg:city":"Sevilla",
    "sg:orig_category":"Fabrica De Cer\u00c1micas",
    "sg:phone":"+34 954 50 00 04",
    "sg:postcode":"41004",
    "sg:province":"Sevilla",
    "wof:name":"Fuentes De Fuentes Julio",
    "wof:placetype":"venue"
},
  "geometry": {"coordinates":[-5.990486145,37.3844566345],"type":"Point"}
}