{
  "type": "Feature",
  "properties": {
    "addr:full":"Carrer de Mossen Amadeu Oller, 11 Barcelona Barcelona 08014",
    "addr:housenumber":"11",
    "addr:postcode":"08014",
    "addr:street":"Carrer De Mossen Amadeu Oller",
    "iso:country":"ES",
    "sg:address":"Carrer de Mossen Amadeu Oller, 11",
    "sg:city":"Barcelona",
    "sg:orig_category":"Mec\u00c1nico Del Autom\u00d3vil",
    "sg:phone":"+34 934 22 30 70",
    "sg:postcode":"08014",
    "sg:province":"Barcelona",
    "wof:name":"Cables Y Controles Castillo S.l.l.",
    "wof:placetype":"venue"
},
  "geometry": {"coordinates":[2.1387178898,41.3682250977],"type":"Point"}
}