{
  "type": "Feature",
  "properties": {
    "addr:full":"Calle de Villamanin, 33 Madrid Madrid 28011",
    "addr:housenumber":"33",
    "addr:postcode":"madrid;28011",
    "addr:street":"Calle De Villamanin",
    "iso:country":"ES",
    "sg:address":"Calle de Villamanin, 33",
    "sg:city":"Madrid",
    "sg:orig_category":"Empresas De Pintura Y Revestimientos",
    "sg:phone":"+34 914 70 03 30",
    "sg:postcode":"28011",
    "sg:province":"Madrid",
    "wof:name":"Moreno Sandoval Ceferino",
    "wof:placetype":"venue"
},
  "geometry": {"coordinates":[-3.7528290749,40.4067573547],"type":"Point"}
}