{
  "type": "Feature",
  "properties": {
    "iso:country":"ES",
    "sg:address":"Calle de Sant Antoni, 43",
    "sg:city":"Rafelbunyol",
    "sg:orig_category":"Molduras, Junquillos, Listones Y Molduras Perforadas",
    "sg:phone":"+34 961 41 00 43",
    "sg:postcode":"46138",
    "sg:province":"Valencia",
    "wof:name":"Carranza Sanchez Espernza",
    "wof:placetype":"venue"
},
  "geometry": {"coordinates":[-0.3313530087,39.5885124207],"type":"Point"}
}