{
  "type": "Feature",
  "properties": {
    "addr:full":"Avda Valencia, 30 Requena Valencia 46340",
    "addr:housenumber":"30",
    "addr:postcode":"46340",
    "addr:street":"Avda Valencia",
    "iso:country":"ES",
    "sg:address":"Avda Valencia, 30",
    "sg:city":"Requena",
    "sg:orig_category":"Transportes De Material De Construcci\u00d3n",
    "sg:phone":"+34 962 30 10 44",
    "sg:postcode":"46340",
    "sg:province":"Valencia",
    "wof:name":"Torres Fernandez Angel",
    "wof:placetype":"venue"
},
  "geometry": {"coordinates":[-1.1047769785,39.4846153259],"type":"Point"}
}