{
  "type": "Feature",
  "properties": {
    "iso:country":"ES",
    "sg:address":"Carrer de Jaume Ferran, 54",
    "sg:city":"Palma",
    "sg:orig_category":"Empresas De Vigilancia, Guardia Y Protecci\u00d3n",
    "sg:phone":"+34 971 29 05 50",
    "sg:postcode":"07004",
    "sg:province":"Islas Baleares",
    "wof:name":"Porcel Reynes Juan Carlos",
    "wof:placetype":"venue"
},
  "geometry": {"coordinates":[2.659514904,39.5829353333],"type":"Point"}
}