{
  "type": "Feature",
  "properties": {
    "addr:full":"Avda Isabel De Farnesio (de), 16 Boadilla Del Monte Madrid 28660",
    "addr:housenumber":"16",
    "addr:postcode":"28660",
    "addr:street":"Avda Isabel De Farnesio De",
    "iso:country":"ES",
    "sg:address":"Avda Isabel De Farnesio (de), 16",
    "sg:city":"Boadilla Del Monte",
    "sg:orig_category":"Florister\u00cdas",
    "sg:phone":"+34 916 32 70 32",
    "sg:postcode":"28660",
    "sg:province":"Madrid",
    "wof:name":"Caixa D'estalvis De Catalunya",
    "wof:placetype":"venue"
},
  "geometry": {"coordinates":[-3.8867809772,40.4015617371],"type":"Point"}
}