{
  "type": "Feature",
  "properties": {
    "iso:country":"ES",
    "sg:address":"Carrer de Joaquim Ruyra, 11",
    "sg:city":"Sabadell",
    "sg:orig_category":"Empresas De Carpinter\u00cda De Madera",
    "sg:phone":"+34 937 11 46 00",
    "sg:postcode":"08205",
    "sg:province":"Barcelona",
    "wof:name":"Benito Soler Francisco",
    "wof:placetype":"venue"
},
  "geometry": {"coordinates":[2.1031808853,41.5352897644],"type":"Point"}
}