{
  "type": "Feature",
  "properties": {
    "iso:country":"ES",
    "sg:address":"Ctra Tries, Les, 48",
    "sg:city":"Olot",
    "sg:orig_category":"Ingeniero",
    "sg:phone":"+34 972 27 16 21",
    "sg:postcode":"17800",
    "sg:province":"Girona",
    "wof:name":"Sideco Enginyeria I Sistemes De Control S.l.",
    "wof:placetype":"venue"
},
  "geometry": {"coordinates":[2.5022599697,42.1893310547],"type":"Point"}
}