{
  "type": "Feature",
  "properties": {
    "addr:full":"Calle de Victor Pe\u00d1asco (don), 32 Tomelloso Ciudad Real 13700",
    "addr:housenumber":"32",
    "addr:postcode":"13700",
    "addr:street":"Calle De Victor Pen\u0303Asco Don",
    "iso:country":"ES",
    "sg:address":"Calle de Victor Pe\u00d1asco (don), 32",
    "sg:city":"Tomelloso",
    "sg:orig_category":"Papeler\u00cdas, Librer\u00cdas",
    "sg:phone":"+34 926 50 18 33",
    "sg:postcode":"13700",
    "sg:province":"Ciudad Real",
    "wof:name":"Tecnocopia Tomelloso S.l.",
    "wof:placetype":"venue"
},
  "geometry": {"coordinates":[-3.0225589275,39.1560211182],"type":"Point"}
}