{
  "type": "Feature",
  "properties": {
    "addr:full":"Calle de Manco De Lepanto, 8 Madrid Madrid 28038",
    "addr:housenumber":"8",
    "addr:postcode":"madrid;28038",
    "addr:street":"Calle De Manco De Lepanto",
    "iso:country":"ES",
    "sg:address":"Calle de Manco De Lepanto, 8",
    "sg:city":"Madrid",
    "sg:orig_category":"Escayola Y Productos De Escayola (fabricaci\u00d3n, Al Por Mayor)",
    "sg:phone":"+34 915 52 30 97",
    "sg:postcode":"28038",
    "sg:province":"Madrid",
    "wof:name":"Ruiz Redondo German",
    "wof:placetype":"venue"
},
  "geometry": {"coordinates":[-3.661303997,40.4026031494],"type":"Point"}
}