{
  "type": "Feature",
  "properties": {
    "iso:country":"ES",
    "sg:address":"Calle de Monsacro, 8",
    "sg:city":"Gijon",
    "sg:orig_category":"Carnicer\u00cdas, Carnicer\u00cdas",
    "sg:phone":"+34 985 14 75 91",
    "sg:postcode":"33211",
    "sg:province":"Asturias",
    "wof:name":"Martinez Tu\u00f1on Jose Manuel",
    "wof:placetype":"venue"
},
  "geometry": {"coordinates":[-5.6811952591,43.527721405],"type":"Point"}
}