{
  "type": "Feature",
  "properties": {
    "addr:full":"Calle de Santa Maria, 26 Pedrosillo El Ralo Salamanca 37427",
    "addr:housenumber":"26",
    "addr:postcode":"37427",
    "addr:street":"Calle De Santa Maria",
    "iso:country":"ES",
    "sg:address":"Calle de Santa Maria, 26",
    "sg:city":"Pedrosillo El Ralo",
    "sg:orig_category":"Centros De Educaci\u00d3n Especial",
    "sg:phone":"+34 923 35 43 85",
    "sg:postcode":"37427",
    "sg:province":"Salamanca",
    "wof:name":"Colegio Publico Comarcal",
    "wof:placetype":"venue"
},
  "geometry": {"coordinates":[-5.550547123,41.0635223389],"type":"Point"}
}