{
  "type": "Feature",
  "properties": {
    "iso:country":"ES",
    "sg:address":"Carrer de Lepant, 46",
    "sg:city":"Terrassa",
    "sg:orig_category":"Serigraf\u00cda (material Y Suministros)",
    "sg:phone":"+34 937 84 31 11",
    "sg:postcode":"08223",
    "sg:province":"Barcelona",
    "wof:name":"Cardila S.l.",
    "wof:placetype":"venue"
},
  "geometry": {"coordinates":[2.0161130428,41.55519104],"type":"Point"}
}