{
  "type": "Feature",
  "properties": {
    "addr:full":"Calle de Cueva Santa, 22 Vall D'uixo Castell\u00f3n 12600",
    "addr:housenumber":"22",
    "addr:postcode":"12600",
    "addr:street":"Calle De Cueva Santa",
    "iso:country":"ES",
    "sg:address":"Calle de Cueva Santa, 22",
    "sg:city":"Vall D'uixo",
    "sg:orig_category":"Institutos De Belleza",
    "sg:phone":"+34 964 69 03 83",
    "sg:postcode":"12600",
    "sg:province":"Castell\u00f3n",
    "wof:name":"Latorre Garcia Maria Jose",
    "wof:placetype":"venue"
},
  "geometry": {"coordinates":[-0.2371684015,39.8223114014],"type":"Point"}
}