{
  "type": "Feature",
  "properties": {
    "iso:country":"ES",
    "sg:address":"El Patronato, 3",
    "sg:city":"Tacoronte",
    "sg:orig_category":"Empresarios",
    "sg:phone":"+34 922 56 29 91",
    "sg:postcode":"38350",
    "sg:province":"Santa Cruz De Tenerife",
    "wof:name":"Fundacion Canaria Benefica Familia Quesada Sanchez",
    "wof:placetype":"venue"
},
  "geometry": {"coordinates":[-16.4174289703,28.4756546021],"type":"Point"}
}