{
  "type": "Feature",
  "properties": {
    "iso:country":"ES",
    "sg:address":"Calle de Almendro El, 4",
    "sg:city":"Huelva",
    "sg:orig_category":"Molduras, Junquillos, Listones Y Molduras Perforadas",
    "sg:phone":"+34 959 22 70 58",
    "sg:postcode":"21007",
    "sg:province":"Huelva",
    "wof:name":"Sistelcom-telemensaje S.a.",
    "wof:placetype":"venue"
},
  "geometry": {"coordinates":[-6.9251599312,37.2643356323],"type":"Point"}
}