{
  "type": "Feature",
  "properties": {
    "iso:country":"ES",
    "sg:address":"Calle de Obispo, 1",
    "sg:city":"Motril",
    "sg:classifiers":[
        {
            "category":"Autos & Motor Vehicles",
            "subcategory":"Automobile Sales",
            "type":"Retail Goods"
        }
    ],
    "sg:phone":"+34 958 60 12 73",
    "sg:postcode":"18600",
    "sg:province":"Granada",
    "wof:name":"Autoescuela Guillen S.l.",
    "wof:placetype":"venue"
},
  "geometry": {"coordinates":[-3.5165140629,36.7443809509],"type":"Point"}
}