{
  "type": "Feature",
  "properties": {
    "addr:full":"Calle de Jose Maria De Pereda, 28 Sevilla Sevilla 41006",
    "addr:housenumber":"28",
    "addr:postcode":"41006",
    "addr:street":"Calle De Jose Maria De Pereda",
    "iso:country":"ES",
    "sg:address":"Calle de Jose Maria De Pereda, 28",
    "sg:city":"Sevilla",
    "sg:orig_category":"Confecci\u00d3n (fabricaci\u00d3n, Al Por Mayor)",
    "sg:phone":"+34 954 63 52 85",
    "sg:postcode":"41006",
    "sg:province":"Sevilla",
    "wof:name":"Gordon Toro Lucia",
    "wof:placetype":"venue"
},
  "geometry": {"coordinates":[-5.9583082199,37.3718032837],"type":"Point"}
}