{
  "type": "Feature",
  "properties": {
    "iso:country":"ES",
    "sg:address":"Carrer de Calatrava, 10",
    "sg:city":"Barcelona",
    "sg:orig_category":"Iglesias Cristianas Diversas",
    "sg:phone":"+34 932 12 01 05",
    "sg:postcode":"08017",
    "sg:province":"Barcelona",
    "wof:name":"Iglesia De Jesucristo De Los Santos De Los Ultimos Dias",
    "wof:placetype":"venue"
},
  "geometry": {"coordinates":[2.1315340996,41.3984527588],"type":"Point"}
}