{
  "type": "Feature",
  "properties": {
    "addr:full":"Calle de San Jose De Calasanz, 3 Getafe Madrid 28902",
    "addr:housenumber":"3",
    "addr:postcode":"28902",
    "addr:street":"Calle De San;De Calasanz",
    "iso:country":"ES",
    "sg:address":"Calle de San Jose De Calasanz, 3",
    "sg:city":"Getafe",
    "sg:orig_category":"Sellos De Goma Y Met\u00c1licos",
    "sg:phone":"+34 916 95 79 07",
    "sg:postcode":"28902",
    "sg:province":"Madrid",
    "wof:name":"Marcajes Galan S.a.",
    "wof:placetype":"venue"
},
  "geometry": {"coordinates":[-3.7306170464,40.3099136353],"type":"Point"}
}