{
  "type": "Feature",
  "properties": {
    "addr:full":"Carrer de Carrero (el), 24 Mataro Barcelona 08301",
    "addr:postcode":"08301",
    "addr:street":"Carrer De Carrero El 24",
    "iso:country":"ES",
    "sg:address":"Carrer de Carrero (el), 24",
    "sg:city":"Mataro",
    "sg:orig_category":"Peluqueros: De Se\u00d1oras",
    "sg:phone":"+34 937 90 33 71",
    "sg:postcode":"08301",
    "sg:province":"Barcelona",
    "wof:name":"Cisterne Garcia Maria Dolores",
    "wof:placetype":"venue"
},
  "geometry": {"coordinates":[2.4454829693,41.5402297974],"type":"Point"}
}