{
  "type": "Feature",
  "properties": {
    "addr:full":"Miudes, S/n Miudes Asturias 33758",
    "addr:postcode":"33758",
    "addr:street":"Miudes S / N Miudes Asturias",
    "iso:country":"ES",
    "sg:address":"Miudes, S/n",
    "sg:city":"Miudes",
    "sg:orig_category":"Alimentaci\u00d3n General (al Por Mayor)",
    "sg:phone":"+34 985 47 82 97",
    "sg:postcode":"33758",
    "sg:province":"Asturias",
    "wof:name":"Iglesias Iglesias Jose Manuel",
    "wof:placetype":"venue"
},
  "geometry": {"coordinates":[-6.8051829338,43.5472984314],"type":"Point"}
}