{
  "type": "Feature",
  "properties": {
    "iso:country":"ES",
    "sg:address":"Avda Deportes, 3",
    "sg:city":"Alhama Murcia",
    "sg:orig_category":"Promotores Constructores",
    "sg:phone":"+34 968 63 12 11",
    "sg:postcode":"30840",
    "sg:province":"Murcia",
    "wof:name":"Construcciones Lorian S.l.",
    "wof:placetype":"venue"
},
  "geometry": {"coordinates":[-1.4157680273,37.8516426086],"type":"Point"}
}