{
  "type": "Feature",
  "properties": {
    "iso:country":"ES",
    "sg:address":"Calle de Agustina De Aragon, S/n",
    "sg:city":"Altorricon",
    "sg:orig_category":"Frutas Y Legumbres Secas (al Por Mayor)",
    "sg:phone":"+34 974 42 53 83",
    "sg:postcode":"22540",
    "sg:province":"Huesca",
    "wof:name":"Pociello Larregola Antonio",
    "wof:placetype":"venue"
},
  "geometry": {"coordinates":[0.4150558114,41.8028869629],"type":"Point"}
}