{
  "type": "Feature",
  "properties": {
    "addr:full":"Calle de Sauquillo, 1 Sevilla Sevilla 41020",
    "addr:housenumber":"1",
    "addr:postcode":"41020",
    "addr:street":"Calle De Sauquillo",
    "iso:country":"ES",
    "sg:address":"Calle de Sauquillo, 1",
    "sg:city":"Sevilla",
    "sg:orig_category":"Ingenier\u00cda, Centros De Estudios (diversos)",
    "sg:phone":"+34 954 99 90 26",
    "sg:postcode":"41020",
    "sg:province":"Sevilla",
    "wof:name":"Extraccion Baque S.l.",
    "wof:placetype":"venue"
},
  "geometry": {"coordinates":[-5.9411888123,37.4084892273],"type":"Point"}
}