{
  "type": "Feature",
  "properties": {
    "addr:full":"Calle de Jacinto Benavente (de), 1 Alcobendas Madrid 28100",
    "addr:postcode":"28100",
    "addr:street":"Calle De Jacinto Benavente De 1",
    "iso:country":"ES",
    "sg:address":"Calle de Jacinto Benavente (de), 1",
    "sg:city":"Alcobendas",
    "sg:orig_category":"Inmobiliaria (agencias)",
    "sg:phone":"+34 914 84 13 00",
    "sg:postcode":"28100",
    "sg:province":"Madrid",
    "wof:name":"Omnia Gestion Inmobiliaria S.l.",
    "wof:placetype":"venue"
},
  "geometry": {"coordinates":[-3.6465981007,40.5459976196],"type":"Point"}
}