{
  "type": "Feature",
  "properties": {
    "addr:full":"Ctra Olivenza, Km. 0005,0 Badajoz Badajoz 06011",
    "addr:postcode":"06011",
    "addr:street":"Ctra Olivenza Km. 0005,0",
    "iso:country":"ES",
    "sg:address":"Ctra Olivenza, Km. 0005,0",
    "sg:city":"Badajoz",
    "sg:orig_category":"Distribuci\u00d3n De Petr\u00d3leo Y Derivados",
    "sg:phone":"+34 924 25 34 07",
    "sg:postcode":"06011",
    "sg:province":"Badajoz",
    "wof:name":"Distribuciones Petroleras La Roca S.l.",
    "wof:placetype":"venue"
},
  "geometry": {"coordinates":[-6.9874491692,38.8595428467],"type":"Point"}
}