{
  "type": "Feature",
  "properties": {
    "addr:full":"Calle de Gutierrez Solana, 2 Madrid Madrid 28036",
    "addr:housenumber":"2",
    "addr:postcode":"28036",
    "addr:street":"Calle De Gutierrez Solana",
    "iso:country":"ES",
    "sg:address":"Calle de Gutierrez Solana, 2",
    "sg:city":"Madrid",
    "sg:orig_category":"Moda",
    "sg:phone":"+34 915 63 15 64",
    "sg:postcode":"28036",
    "sg:province":"Madrid",
    "sg:website":"www.jacadi.net",
    "wof:name":"Gonzalez Alcala S.l.",
    "wof:placetype":"venue"
},
  "geometry": {"coordinates":[-3.6890149117,40.4508323669],"type":"Point"}
}