{
  "type": "Feature",
  "properties": {
    "addr:full":"Urkizu Pasealekua, 18 Eibar Guip\u00f9zcoa 20600",
    "addr:housenumber":"18",
    "addr:postcode":"20600",
    "addr:street":"Urkizu Pasealekua;Guipu\u0300Zcoa",
    "iso:country":"ES",
    "sg:address":"Urkizu Pasealekua, 18",
    "sg:city":"Eibar",
    "sg:orig_category":"Electrodom\u00c9sticos (al Por Menor)",
    "sg:phone":"+34 943 12 10 33",
    "sg:postcode":"20600",
    "sg:province":"Guip\u00f9zcoa",
    "wof:name":"Ameki S.coop.ltda.",
    "wof:placetype":"venue"
},
  "geometry": {"coordinates":[-2.4632945061,43.1863937378],"type":"Point"}
}