{
  "type": "Feature",
  "properties": {
    "addr:full":"Poli Industrial Berriainz, 38 Berriozar Navarra 31013",
    "addr:housenumber":"38",
    "addr:postcode":"31013",
    "addr:street":"Berriainz",
    "iso:country":"ES",
    "sg:address":"Poli Industrial Berriainz, 38",
    "sg:city":"Berriozar",
    "sg:orig_category":"Textil",
    "sg:phone":"+34 948 30 26 67",
    "sg:postcode":"31013",
    "sg:province":"Navarra",
    "wof:name":"Gaseinco S.l.",
    "wof:placetype":"venue"
},
  "geometry": {"coordinates":[-97.78224945069999,45.7040786743],"type":"Point"}
}