{
  "type": "Feature",
  "properties": {
    "iso:country":"ES",
    "sg:address":"Rond Pilar, 20",
    "sg:city":"Badajoz",
    "sg:orig_category":"Ense\u00d1anza, Formaci\u00d3n Profesional: Aprendizaje",
    "sg:phone":"+34 924 21 14 00",
    "sg:postcode":"06...",
    "sg:province":"Badajoz",
    "wof:name":"Tesoreria General De La Seguridad Social-direccion Provincial De Badajoz",
    "wof:placetype":"venue"
},
  "geometry": {"coordinates":[-6.9726238251,38.874835968],"type":"Point"}
}