{
  "type": "Feature",
  "properties": {
    "addr:full":"Avda San Miguel, 43 Iscar Valladolid 47420",
    "addr:housenumber":"43",
    "addr:postcode":"47420",
    "addr:street":"Avda San Miguel",
    "iso:country":"ES",
    "sg:address":"Avda San Miguel, 43",
    "sg:city":"Iscar",
    "sg:orig_category":"Agentes, Concesionarios Y Sucursales De Veh\u00cdculos",
    "sg:phone":"+34 983 62 02 79",
    "sg:postcode":"47420",
    "sg:province":"Valladolid",
    "wof:name":"Otero Velazquez Julian",
    "wof:placetype":"venue"
},
  "geometry": {"coordinates":[-4.5376338959,41.3601837158],"type":"Point"}
}