{
  "type": "Feature",
  "properties": {
    "addr:full":"T R A C, S/n Hornachuelos C\u00f3rdoba 14740",
    "addr:postcode":"14740",
    "addr:street":"T R A C S / N;Co\u0301Rdoba",
    "iso:country":"ES",
    "sg:address":"T R A C, S/n",
    "sg:city":"Hornachuelos",
    "sg:orig_category":"Producci\u00d3n, Venta De Productos De Agricultura Biol\u00d3gica",
    "sg:phone":"+34 957 33 80 81",
    "sg:postcode":"14740",
    "sg:province":"C\u00f3rdoba",
    "wof:name":"La Mata S.l.",
    "wof:placetype":"venue"
},
  "geometry": {"coordinates":[-5.2428050041,37.8309288025],"type":"Point"}
}