{
  "type": "Feature",
  "properties": {
    "iso:country":"ES",
    "sg:address":"Avda Fragoso, 42",
    "sg:city":"Vigo",
    "sg:orig_category":"Pintura, Barniz, Productos Asimilables (fabricaci\u00d3n, Al Por Mayor)",
    "sg:phone":"+34 986 20 26 64",
    "sg:postcode":"36210",
    "sg:province":"Pontevedra",
    "sg:website":"www.juno.es",
    "wof:name":"Industrias Juno S. A.",
    "wof:placetype":"venue"
},
  "geometry": {"coordinates":[-8.7354440689,42.2163658142],"type":"Point"}
}