{
  "type": "Feature",
  "properties": {
    "addr:full":"El Canto, S/n Manzanedo Burgos 09558",
    "addr:housenumber":"s / n",
    "addr:postcode":"09558",
    "addr:street":"El Canto",
    "iso:country":"ES",
    "sg:address":"El Canto, S/n",
    "sg:city":"Manzanedo",
    "sg:orig_category":"Energ\u00cda Solar Y Nuevas Energ\u00cdas (equipo, Estudios)",
    "sg:phone":"+34 947 57 33 84",
    "sg:postcode":"09558",
    "sg:province":"Burgos",
    "wof:name":"Corporacion Eolica De Manzanedo S.l.",
    "wof:placetype":"venue"
},
  "geometry": {"coordinates":[-3.6922810078,42.8985595703],"type":"Point"}
}