{
  "type": "Feature",
  "properties": {
    "iso:country":"ES",
    "sg:address":"Polig Nueve, 9",
    "sg:city":"Selva",
    "sg:orig_category":"Confecci\u00d3n De Zapatos",
    "sg:phone":"+34 971 51 58 22",
    "sg:postcode":"07313",
    "sg:province":"Islas Baleares",
    "wof:name":"Martorel Planas Lorenzo",
    "wof:placetype":"venue"
},
  "geometry": {"coordinates":[2.9093449116,39.754650116],"type":"Point"}
}