{
  "type": "Feature",
  "properties": {
    "iso:country":"ES",
    "sg:address":"Avda Zaragoza, 17",
    "sg:city":"Alfajarin",
    "sg:orig_category":"Asilos De Ancianos. Centros Privados",
    "sg:phone":"+34 976 10 10 55",
    "sg:postcode":"50172",
    "sg:province":"Zaragoza",
    "wof:name":"Residencia De Ancianos Nuestra Se\u00f1ora De La Pe\u00f1a",
    "wof:placetype":"venue"
},
  "geometry": {"coordinates":[-0.7093380094,41.6155586243],"type":"Point"}
}