{
  "type": "Feature",
  "properties": {
    "addr:full":"Avda Machupichu, 16 Madrid Madrid 28043",
    "addr:housenumber":"16",
    "addr:postcode":"madrid;28043",
    "addr:street":"Avda Machupichu",
    "iso:country":"ES",
    "sg:address":"Avda Machupichu, 16",
    "sg:city":"Madrid",
    "sg:orig_category":"Art\u00cdculos De Decoraci\u00d3n",
    "sg:phone":"+34 913 88 04 19",
    "sg:postcode":"28043",
    "sg:province":"Madrid",
    "wof:name":"Nur House S.a.",
    "wof:placetype":"venue"
},
  "geometry": {"coordinates":[-3.624448061,40.4575042725],"type":"Point"}
}