{
  "type": "Feature",
  "properties": {
    "iso:country":"ES",
    "sg:address":"Avda Garcia Barbon, 108",
    "sg:city":"Vigo",
    "sg:orig_category":"Trajes Y Adornos De Boda (confecci\u00d3n, Al Por Menor)",
    "sg:phone":"+34 986 43 72 63",
    "sg:postcode":"36201",
    "sg:province":"Pontevedra",
    "wof:name":"Autismo Vigo",
    "wof:placetype":"venue"
},
  "geometry": {"coordinates":[-8.7074661255,42.2409172058],"type":"Point"}
}