{
  "type": "Feature",
  "properties": {
    "iso:country":"ES",
    "sg:address":"Av Meridiana, 326",
    "sg:city":"Barcelona",
    "sg:orig_category":"Ense\u00d1anza Variada",
    "sg:phone":"+34 933 40 03 58",
    "sg:postcode":"08027",
    "sg:province":"Barcelona",
    "sg:website":"www.mecarapid.pagina.de",
    "wof:name":"Vaque Sospedra Maria Teresa",
    "wof:placetype":"venue"
},
  "geometry": {"coordinates":[2.1869978905,41.4253349304],"type":"Point"}
}