{
  "type": "Feature",
  "properties": {
    "iso:country":"ES",
    "sg:address":"Calle de Pintor Emiliano Lozano, 12",
    "sg:city":"Tarancon",
    "sg:orig_category":"Arquitectos",
    "sg:phone":"+34 969 32 18 11",
    "sg:postcode":"16400",
    "sg:province":"Cuenca",
    "wof:name":"Martinez Parra Emilia",
    "wof:placetype":"venue"
},
  "geometry": {"coordinates":[-3.014300108,40.0097160339],"type":"Point"}
}