{
  "type": "Feature",
  "properties": {
    "addr:full":"Calle de Luxemburgo, 1 Toledo Toledo 45005",
    "addr:housenumber":"1",
    "addr:postcode":"45005",
    "addr:street":"Calle De Luxemburgo",
    "iso:country":"ES",
    "sg:address":"Calle de Luxemburgo, 1",
    "sg:city":"Toledo",
    "sg:orig_category":"M\u00c9dicos: Psiquiatr\u00cda",
    "sg:phone":"+34 925 25 50 68",
    "sg:postcode":"45005",
    "sg:province":"Toledo",
    "wof:name":"Goenechea Alcala-zamora Luis",
    "wof:placetype":"venue"
},
  "geometry": {"coordinates":[-4.0258469582,39.8709526062],"type":"Point"}
}