{
  "type": "Feature",
  "properties": {
    "iso:country":"ES",
    "sg:address":"Cra Cordoba-valencia-pi La Vicaria, S/n",
    "sg:city":"Puente Genave",
    "sg:orig_category":"Aceites Y Grasas Alimentarias (fabricaci\u00d3n, Al Por Mayor)",
    "sg:phone":"+34 953 43 54 00",
    "sg:postcode":"23350",
    "sg:province":"Ja\u00e9n",
    "sg:website":"www.olivardesegura.es",
    "wof:name":"Olivar De Segura S.c.a.",
    "wof:placetype":"venue"
},
  "geometry": {"coordinates":[-2.8030788898,38.3562431335],"type":"Point"}
}