{
  "type": "Feature",
  "properties": {
    "addr:full":"Calle de Cartuja, 2 Jerez De La Frontera C\u00e1diz 11401",
    "addr:housenumber":"2",
    "addr:postcode":"11401",
    "addr:street":"Calle De Cartuja",
    "iso:country":"ES",
    "sg:address":"Calle de Cartuja, 2",
    "sg:city":"Jerez De La Frontera",
    "sg:orig_category":"Albergues",
    "sg:phone":"+34 956 33 09 26",
    "sg:postcode":"11401",
    "sg:province":"C\u00e1diz",
    "wof:name":"Federacion Andalucia Acoge",
    "wof:placetype":"venue"
},
  "geometry": {"coordinates":[-6.1303377151,36.6810951233],"type":"Point"}
}