{
  "type": "Feature",
  "properties": {
    "addr:full":"Calle de Colon De Larreategui, 21 Bilbao Vizcaya 48001",
    "addr:housenumber":"21",
    "addr:postcode":"48001",
    "addr:street":"Calle De Colon De Larreategui",
    "iso:country":"ES",
    "sg:address":"Calle de Colon De Larreategui, 21",
    "sg:city":"Bilbao",
    "sg:orig_category":"Edici\u00d3n De Diarios, Revistas, Boletines",
    "sg:phone":"+34 944 23 09 26",
    "sg:postcode":"48001",
    "sg:province":"Vizcaya",
    "sg:website":"www.ibaizabal.biz",
    "wof:name":"Ibaizabal Denda, S.l",
    "wof:placetype":"venue"
},
  "geometry": {"coordinates":[-2.9301562309,43.2630195618],"type":"Point"}
}