{
  "type": "Feature",
  "properties": {
    "addr:full":"Plaza De Hospital, 12 Pontes Garcia Rodriguez La Coru\u00f1a 15320",
    "addr:housenumber":"12",
    "addr:postcode":"15320",
    "addr:street":"Pontes Garcia Rodriguez La Corun\u0303A",
    "iso:country":"ES",
    "sg:address":"Plaza De Hospital, 12",
    "sg:city":"Pontes Garcia Rodriguez",
    "sg:orig_category":"Quincaller\u00cda (al Por Menor)",
    "sg:phone":"+34 981 45 00 43",
    "sg:postcode":"15320",
    "sg:province":"La Coru\u00f1a",
    "wof:name":"Hermanos Gabeiras S.l.",
    "wof:placetype":"venue"
},
  "geometry": {"coordinates":[-7.8519802094,43.4437828064],"type":"Point"}
}