{
  "type": "Feature",
  "properties": {
    "addr:full":"Pase Pedro Simon Abril, 20 Albacete Albacete 02003",
    "addr:housenumber":"20",
    "addr:postcode":"02003",
    "addr:street":"Abril",
    "iso:country":"ES",
    "sg:address":"Pase Pedro Simon Abril, 20",
    "sg:city":"Albacete",
    "sg:orig_category":"Impuestos, Tesoro P\u00dablico",
    "sg:phone":"+34 967 23 79 06",
    "sg:postcode":"02003",
    "sg:province":"Albacete",
    "wof:name":"Bautista Gomez Jose",
    "wof:placetype":"venue"
},
  "geometry": {"coordinates":[-1.8590710163,38.9867858887],"type":"Point"}
}