{
  "type": "Feature",
  "properties": {
    "iso:country":"ES",
    "sg:address":"Plaz Azafranal, 1",
    "sg:city":"Membrilla",
    "sg:orig_category":"Molduras, Junquillos, Listones Y Molduras Perforadas",
    "sg:phone":"+34 926 63 68 30",
    "sg:postcode":"13230",
    "sg:province":"Ciudad Real",
    "wof:name":"Lozano Pacheco Juan Antonio",
    "wof:placetype":"venue"
},
  "geometry": {"coordinates":[-3.3460218906,38.9726791382],"type":"Point"}
}