{
  "type": "Feature",
  "properties": {
    "addr:full":"Calle de Martin Etxeberria, 12 Errenteria Guip\u00f9zcoa 20100",
    "addr:housenumber":"12",
    "addr:postcode":"20100",
    "addr:street":"Calle De Martin Etxeberria;Guipu\u0300Zcoa",
    "iso:country":"ES",
    "sg:address":"Calle de Martin Etxeberria, 12",
    "sg:city":"Errenteria",
    "sg:orig_category":"Transporte En General",
    "sg:phone":"+34 943 51 17 95",
    "sg:postcode":"20100",
    "sg:province":"Guip\u00f9zcoa",
    "wof:name":"Manuel Maria Bengoetxea Arbelaitz",
    "wof:placetype":"venue"
},
  "geometry": {"coordinates":[-1.9034719467,43.3134918213],"type":"Point"}
}