{
  "type": "Feature",
  "properties": {
    "iso:country":"ES",
    "sg:address":"Calle de Rafael Perez Del Alamo, 18",
    "sg:city":"Loja",
    "sg:orig_category":"Cl\u00cdnicas Dentales",
    "sg:phone":"+34 958 32 31 88",
    "sg:postcode":"18300",
    "sg:province":"Granada",
    "wof:name":"Lozano Arco Jose Antonio",
    "wof:placetype":"venue"
},
  "geometry": {"coordinates":[-4.1422739029,37.1645507812],"type":"Point"}
}