{
  "type": "Feature",
  "properties": {
    "addr:full":"Calle de San Pedro, 8 Puertollano Ciudad Real 13500",
    "addr:housenumber":"8",
    "addr:postcode":"13500",
    "addr:street":"Calle De San Pedro",
    "iso:country":"ES",
    "sg:address":"Calle de San Pedro, 8",
    "sg:city":"Puertollano",
    "sg:orig_category":"Bisuter\u00cda, Joyer\u00cda, Relojer\u00cda (al Por Menor)",
    "sg:phone":"+34 926 44 13 73",
    "sg:postcode":"13500",
    "sg:province":"Ciudad Real",
    "wof:name":"Rodriguez Nu\u00f1ez Jose Luis",
    "wof:placetype":"venue"
},
  "geometry": {"coordinates":[-4.1037807465,38.687286377],"type":"Point"}
}