{
  "type": "Feature",
  "properties": {
    "iso:country":"ES",
    "sg:address":"Avda Espa\u00d1a, 162",
    "sg:city":"Estepona",
    "sg:orig_category":"Cajas De Ahorro",
    "sg:phone":"+34 952 79 62 37",
    "sg:postcode":"29680",
    "sg:province":"M\u00e1laga",
    "sg:website":"www.cajasur.es",
    "wof:name":"Caja De Ahorros Y Monte De Piedad De Cordoba",
    "wof:placetype":"venue"
},
  "geometry": {"coordinates":[-5.1463518143,36.4234466553],"type":"Point"}
}