{
  "type": "Feature",
  "properties": {
    "addr:full":"Carrer de Antoni Rovira I Virgili (d'), 42 Tarragona Tarragona 43002",
    "addr:housenumber":"42",
    "addr:postcode":"43002",
    "addr:street":"Carrer De Antoni Rovira I Virgili D '",
    "iso:country":"ES",
    "sg:address":"Carrer de Antoni Rovira I Virgili (d'), 42",
    "sg:city":"Tarragona",
    "sg:orig_category":"Art\u00cdculos De Regalo (al Por Menor)",
    "sg:phone":"+34 977 22 82 54",
    "sg:postcode":"43002",
    "sg:province":"Tarragona",
    "wof:name":"Inma Objectes De Regal",
    "wof:placetype":"venue"
},
  "geometry": {"coordinates":[1.2516679764,41.1218948364],"type":"Point"}
}