{
  "type": "Feature",
  "properties": {
    "addr:full":"Calle de Teruel, 16 Madrid Madrid 28020",
    "addr:housenumber":"16",
    "addr:postcode":"madrid;28020",
    "addr:street":"Calle De Teruel",
    "iso:country":"ES",
    "sg:address":"Calle de Teruel, 16",
    "sg:city":"Madrid",
    "sg:orig_category":"Edici\u00d3n De Mapas, Gu\u00cdas Y Planos",
    "sg:phone":"+34 915 72 12 57",
    "sg:postcode":"28020",
    "sg:province":"Madrid",
    "sg:website":"www.revisatlas.com",
    "wof:name":"Revisatlas S. A.",
    "wof:placetype":"venue"
},
  "geometry": {"coordinates":[-3.7021939754,40.4514732361],"type":"Point"}
}