{
  "type": "Feature",
  "properties": {
    "iso:country":"ES",
    "sg:address":"Calle de Marques De Dosfuentes, 2",
    "sg:city":"Huelva",
    "sg:orig_category":"M\u00c9dicos: Alergolog\u00cda",
    "sg:phone":"+34 959 26 22 26",
    "sg:postcode":"21004",
    "sg:province":"Huelva",
    "wof:name":"Poch Marti Montserrat",
    "wof:placetype":"venue"
},
  "geometry": {"coordinates":[-6.9430761337,37.2671546936],"type":"Point"}
}