{
  "type": "Feature",
  "properties": {
    "iso:country":"ES",
    "sg:address":"Calle de General Yag\u00fce, 55",
    "sg:city":"Madrid",
    "sg:orig_category":"Ingenier\u00cda, Centros De Estudios (diversos)",
    "sg:phone":"+34 915 71 05 32",
    "sg:postcode":"28020",
    "sg:province":"Madrid",
    "wof:name":"Escobar Orosco Alberto",
    "wof:placetype":"venue"
},
  "geometry": {"coordinates":[-3.7010350227,40.4572563171],"type":"Point"}
}