{
  "type": "Feature",
  "properties": {
    "addr:full":"Pg Pins, 22 Sant Feliu Llobregat Barcelona 08980",
    "addr:housenumber":"22",
    "addr:postcode":"08980",
    "addr:street":"Pg Pins",
    "iso:country":"ES",
    "sg:address":"Pg Pins, 22",
    "sg:city":"Sant Feliu Llobregat",
    "sg:orig_category":"Peluquer\u00cdas, Peluquer\u00cda Mixta",
    "sg:phone":"+34 936 66 06 03",
    "sg:postcode":"08980",
    "sg:province":"Barcelona",
    "wof:name":"Sogarpin S.l.",
    "wof:placetype":"venue"
},
  "geometry": {"coordinates":[2.0436859131,41.3846054077],"type":"Point"}
}