{
  "type": "Feature",
  "properties": {
    "iso:country":"ES",
    "sg:address":"Avda Espa\u00d1a, S/n",
    "sg:city":"Getafe",
    "sg:orig_category":"Ense\u00d1anza, Formaci\u00d3n Profesional: Aprendizaje",
    "sg:phone":"+34 916 95 10 05",
    "sg:postcode":"28903",
    "sg:province":"Madrid",
    "wof:name":"Ayuntamiento De Getafe",
    "wof:placetype":"venue"
},
  "geometry": {"coordinates":[-3.722563982,40.3115997314],"type":"Point"}
}