{
  "type": "Feature",
  "properties": {
    "addr:full":"Ptda Alberca (l'), S/n Nucia Alicante 03530",
    "addr:housenumber":"s / n",
    "addr:postcode":"03530",
    "addr:street":"Ptda Alberca L '",
    "iso:country":"ES",
    "sg:address":"Ptda Alberca (l'), S/n",
    "sg:city":"Nucia",
    "sg:orig_category":"Empresas De Carpinter\u00cda Met\u00c1lica",
    "sg:phone":"+34 966 89 68 83",
    "sg:postcode":"03530",
    "sg:province":"Alicante",
    "wof:name":"Ruiz Martos Sebastian",
    "wof:placetype":"venue"
},
  "geometry": {"coordinates":[-0.1213990003,38.594619751],"type":"Point"}
}