{
  "type": "Feature",
  "properties": {
    "addr:full":"Calle de Uria, 44 Gijon Asturias 33202",
    "addr:housenumber":"44",
    "addr:postcode":"33202",
    "addr:street":"Calle De Uria",
    "iso:country":"ES",
    "sg:address":"Calle de Uria, 44",
    "sg:city":"Gijon",
    "sg:orig_category":"Importaci\u00d3n",
    "sg:phone":"+34 985 33 87 33",
    "sg:postcode":"33202",
    "sg:province":"Asturias",
    "wof:name":"Xinhua Importaciones Sl",
    "wof:placetype":"venue"
},
  "geometry": {"coordinates":[-5.6541361809,43.5379867554],"type":"Point"}
}