{
  "type": "Feature",
  "properties": {
    "addr:full":"Calle de Cuesta Del Ruedo, S/n Alcaudete Ja\u00e9n 23660",
    "addr:housenumber":"s / n",
    "addr:postcode":"23660",
    "addr:street":"Calle De Cuesta Del Ruedo;Jae\u0301N",
    "iso:country":"ES",
    "sg:address":"Calle de Cuesta Del Ruedo, S/n",
    "sg:city":"Alcaudete",
    "sg:orig_category":"Escayola Y Productos De Escayola (fabricaci\u00d3n, Al Por Mayor)",
    "sg:phone":"+34 953 56 08 50",
    "sg:postcode":"23660",
    "sg:province":"Ja\u00e9n",
    "wof:name":"Tapiador Pelaez Jose",
    "wof:placetype":"venue"
},
  "geometry": {"coordinates":[-4.0785541534,37.5891304016],"type":"Point"}
}