{
  "type": "Feature",
  "properties": {
    "addr:full":"Calle de Carlos De S Lamas, 38 Palmas De Gran Canaria Las Palmas 35015",
    "addr:housenumber":"38",
    "addr:postcode":"35015",
    "addr:street":"Calle De Carlos De S Lamas",
    "iso:country":"ES",
    "sg:address":"Calle de Carlos De S Lamas, 38",
    "sg:city":"Palmas De Gran Canaria",
    "sg:orig_category":"Doctores En Medicina",
    "sg:phone":"+34 928 31 71 10",
    "sg:postcode":"35015",
    "sg:province":"Las Palmas",
    "wof:name":"Gonzalez Blanco Ignacio",
    "wof:placetype":"venue"
},
  "geometry": {"coordinates":[-15.4310884476,28.0902309418],"type":"Point"}
}