{
  "type": "Feature",
  "properties": {
    "iso:country":"ES",
    "sg:address":"Calle de Lopez Gomez, 5",
    "sg:city":"Valladolid",
    "sg:orig_category":"Ingenier\u00cda, Centros De Estudios (diversos)",
    "sg:phone":"+34 983 30 58 71",
    "sg:postcode":"47002",
    "sg:province":"Valladolid",
    "wof:name":"Navarro San Roman Zoa",
    "wof:placetype":"venue"
},
  "geometry": {"coordinates":[-4.7239980698,41.6499938965],"type":"Point"}
}