{
  "type": "Feature",
  "properties": {
    "iso:country":"ES",
    "sg:address":"Plaz Tesillo (del), 11",
    "sg:city":"Fuenlabrada",
    "sg:orig_category":"Inmobiliaria (agencias)",
    "sg:phone":"+34 916 97 52 15",
    "sg:postcode":"28944",
    "sg:province":"Madrid",
    "wof:name":"Fernandez Rodriguez Ramona",
    "wof:placetype":"venue"
},
  "geometry": {"coordinates":[-3.7942330837,40.283870697],"type":"Point"}
}