{
  "type": "Feature",
  "properties": {
    "addr:full":"Carr Reina Fabiola, 3 Eliana Valencia 46183",
    "addr:housenumber":"3",
    "addr:postcode":"46183",
    "addr:street":"Carr Reina Fabiola",
    "iso:country":"ES",
    "sg:address":"Carr Reina Fabiola, 3",
    "sg:city":"Eliana",
    "sg:classifiers":[
        {
            "category":"Professional",
            "subcategory":"Management & Consulting",
            "type":"Services"
        }
    ],
    "sg:phone":"+34 962 74 17 55",
    "sg:postcode":"46183",
    "sg:province":"Valencia",
    "sg:tags":[
        "asesor\u00cda",
        "en",
        "marketing"
    ],
    "wof:name":"Gestion De Representadas Del Agua S.lu.",
    "wof:placetype":"venue"
},
  "geometry": {"coordinates":[-0.528208971,39.5667457581],"type":"Point"}
}