{
  "type": "Feature",
  "properties": {
    "iso:country":"ES",
    "sg:address":"Calle de Irurak, 4",
    "sg:city":"Donostia-san Sebastian",
    "sg:orig_category":"Transporte En General",
    "sg:phone":"+34 943 28 25 44",
    "sg:postcode":"20015",
    "sg:province":"Guip\u00f9zcoa",
    "wof:name":"Placeres Miranda Francisco",
    "wof:placetype":"venue"
},
  "geometry": {"coordinates":[-1.9525359869,43.3174285889],"type":"Point"}
}