{
  "type": "Feature",
  "properties": {
    "iso:country":"ES",
    "sg:address":"Carrer de Bailen, 43",
    "sg:city":"Barcelona",
    "sg:orig_category":"Abogados",
    "sg:phone":"+34 932 65 52 98",
    "sg:postcode":"08010",
    "sg:province":"Barcelona",
    "wof:name":"Fontsinera S.l.",
    "wof:placetype":"venue"
},
  "geometry": {"coordinates":[2.1747050285,41.3936271667],"type":"Point"}
}