{
  "type": "Feature",
  "properties": {
    "addr:full":"Calle de Lillo Juan, 49 San Vicente Del Raspeig-sant Vicent Del Raspeig Alicante 03690",
    "addr:housenumber":"49",
    "addr:postcode":"03690",
    "addr:street":"Calle De Lillo Juan",
    "iso:country":"ES",
    "sg:address":"Calle de Lillo Juan, 49",
    "sg:city":"San Vicente Del Raspeig-sant Vicent Del Raspeig",
    "sg:orig_category":"Alimentaci\u00d3n General (al Por Menor)",
    "sg:phone":"+34 965 66 70 40",
    "sg:postcode":"03690",
    "sg:province":"Alicante",
    "wof:name":"Torregrosa Gomis Esther",
    "wof:placetype":"venue"
},
  "geometry": {"coordinates":[-0.5262132287,38.3987617493],"type":"Point"}
}