{
  "type": "Feature",
  "properties": {
    "iso:country":"ES",
    "sg:address":"Calle de Rochapea, S/n",
    "sg:city":"Ezcaroz",
    "sg:orig_category":"Iglesia Cat\u00d3lica",
    "sg:phone":"+34 948 89 02 84",
    "sg:postcode":"31690",
    "sg:province":"Navarra",
    "wof:name":"Arzobispado De Pamplona",
    "wof:placetype":"venue"
},
  "geometry": {"coordinates":[-1.0971099138,42.8862609863],"type":"Point"}
}