{
  "type": "Feature",
  "properties": {
    "iso:country":"ES",
    "sg:address":"Avda Santa Ana, 45",
    "sg:city":"Palma Rio",
    "sg:orig_category":"Florister\u00cdas",
    "sg:phone":"+34 957 64 45 27",
    "sg:postcode":"14700",
    "sg:province":"C\u00f3rdoba",
    "wof:name":"Sotillo Lopez Ildefonso",
    "wof:placetype":"venue"
},
  "geometry": {"coordinates":[-5.2818989754,37.7028083801],"type":"Point"}
}