{
  "type": "Feature",
  "properties": {
    "iso:country":"ES",
    "sg:address":"La Plaza, S/n",
    "sg:city":"Pola Somiedo",
    "sg:orig_category":"Pensiones Familiares",
    "sg:phone":"+34 985 76 39 58",
    "sg:postcode":"33840",
    "sg:province":"Asturias",
    "wof:name":"Alvarez Alvarez Cesareo",
    "wof:placetype":"venue"
},
  "geometry": {"coordinates":[-6.2800865173,43.1187286377],"type":"Point"}
}