{
  "type": "Feature",
  "properties": {
    "addr:full":"Calle de Tiepolo, 7 Torremolinos M\u00e1laga 29620",
    "addr:housenumber":"7",
    "addr:postcode":"29620",
    "addr:street":"Calle De Tiepolo;Ma\u0301Laga",
    "iso:country":"ES",
    "sg:address":"Calle de Tiepolo, 7",
    "sg:city":"Torremolinos",
    "sg:orig_category":"Peluquer\u00cdas, Peluquer\u00cda Mixta",
    "sg:phone":"+34 952 05 81 56",
    "sg:postcode":"29620",
    "sg:province":"M\u00e1laga",
    "wof:name":"Valverde Ramirez Raquel",
    "wof:placetype":"venue"
},
  "geometry": {"coordinates":[-4.5006570816,36.6262817383],"type":"Point"}
}