{
  "type": "Feature",
  "properties": {
    "iso:country":"ES",
    "sg:address":"Calle de Torrijos, 39",
    "sg:city":"Fuente Palmera",
    "sg:orig_category":"Albergues",
    "sg:phone":"+34 957 71 27 82",
    "sg:postcode":"14120",
    "sg:province":"C\u00f3rdoba",
    "wof:name":"Vazquez Henz Francisco",
    "wof:placetype":"venue"
},
  "geometry": {"coordinates":[-5.100894928,37.7048187256],"type":"Point"}
}