{
  "type": "Feature",
  "properties": {
    "addr:full":"Rua Pi Y Margall, 27 Vigo Pontevedra 36202",
    "addr:housenumber":"27",
    "addr:postcode":"36202",
    "addr:street":"Rua Pi Y Margall",
    "iso:country":"ES",
    "sg:address":"Rua Pi Y Margall, 27",
    "sg:city":"Vigo",
    "sg:orig_category":"Carnicer\u00cdas, Carnicer\u00cdas",
    "sg:phone":"+34 986 43 90 43",
    "sg:postcode":"36202",
    "sg:province":"Pontevedra",
    "wof:name":"Rodriguez Garcia Maria Jose",
    "wof:placetype":"venue"
},
  "geometry": {"coordinates":[-8.7291631699,42.2345924377],"type":"Point"}
}