{
  "type": "Feature",
  "properties": {
    "addr:full":"Plaz Santa Ana, 7 Valladolid Valladolid 47001",
    "addr:housenumber":"7",
    "addr:postcode":"47001",
    "addr:street":"Santa Ana",
    "iso:country":"ES",
    "sg:address":"Plaz Santa Ana, 7",
    "sg:city":"Valladolid",
    "sg:orig_category":"Mutuas De Seguros",
    "sg:phone":"+34 983 37 35 36",
    "sg:postcode":"47001",
    "sg:province":"Valladolid",
    "sg:website":"www.divinapastora.com",
    "wof:name":"Mutualidad General De Prevision Del Hogar",
    "wof:placetype":"venue"
},
  "geometry": {"coordinates":[-4.7321238518,41.6541938782],"type":"Point"}
}