{
  "type": "Feature",
  "properties": {
    "addr:full":"Ctra. Murcia, Km. 0073,3 Alacant Alicante 03008",
    "addr:postcode":"03008",
    "addr:street":"Ctra. Murcia Km. 0073,3",
    "iso:country":"ES",
    "sg:address":"Ctra. Murcia, Km. 0073,3",
    "sg:city":"Alacant",
    "sg:orig_category":"Fabricaci\u00d3n De Juguetes Autom\u00c1ticos",
    "sg:phone":"+34 965 10 41 41",
    "sg:postcode":"03008",
    "sg:province":"Alicante",
    "wof:name":"Automaticos Orenes S.l.",
    "wof:placetype":"venue"
},
  "geometry": {"coordinates":[-0.498654604,38.349609375],"type":"Point"}
}