{
  "type": "Feature",
  "properties": {
    "addr:full":"Calle de Martires, 5 Torrelavega Cantabria 39300",
    "addr:housenumber":"5",
    "addr:postcode":"39300",
    "addr:street":"Calle De Martires",
    "iso:country":"ES",
    "sg:address":"Calle de Martires, 5",
    "sg:city":"Torrelavega",
    "sg:orig_category":"Telas Y Sedas (al Por Menor)",
    "sg:phone":"+34 942 88 33 22",
    "sg:postcode":"39300",
    "sg:province":"Cantabria",
    "wof:name":"Trueba Laso Gerardo",
    "wof:placetype":"venue"
},
  "geometry": {"coordinates":[-4.048500061,43.3513374329],"type":"Point"}
}