{
  "type": "Feature",
  "properties": {
    "addr:full":"Carr Bellprat, 18 Igualada Barcelona 08700",
    "addr:housenumber":"18",
    "addr:postcode":"08700",
    "addr:street":"Carr Bellprat",
    "iso:country":"ES",
    "sg:address":"Carr Bellprat, 18",
    "sg:city":"Igualada",
    "sg:orig_category":"Art\u00cdculos Reciclados",
    "sg:phone":"+34 938 04 73 98",
    "sg:postcode":"08700",
    "sg:province":"Barcelona",
    "sg:website":"wwwresyklincat.com",
    "wof:name":"Garrabou Perez Jaume",
    "wof:placetype":"venue"
},
  "geometry": {"coordinates":[1.6160438061,41.587474823],"type":"Point"}
}