{
  "type": "Feature",
  "properties": {
    "addr:full":"Calle de Camarin, S/n Torrijos Toledo 45500",
    "addr:housenumber":"s / n",
    "addr:postcode":"45500",
    "addr:street":"Calle De Camarin",
    "iso:country":"ES",
    "sg:address":"Calle de Camarin, S/n",
    "sg:city":"Torrijos",
    "sg:orig_category":"Arquitectos",
    "sg:phone":"+34 925 76 17 24",
    "sg:postcode":"45500",
    "sg:province":"Toledo",
    "wof:name":"Escobar Aguado Jose Luis",
    "wof:placetype":"venue"
},
  "geometry": {"coordinates":[-4.2830481529,39.9831581116],"type":"Point"}
}