{
  "type": "Feature",
  "properties": {
    "addr:full":"Calle de Colon, 50 Villamalea Albacete 02270",
    "addr:housenumber":"50",
    "addr:postcode":"02270",
    "addr:street":"Calle De Colon",
    "iso:country":"ES",
    "sg:address":"Calle de Colon, 50",
    "sg:city":"Villamalea",
    "sg:orig_category":"Confecci\u00d3n (fabricaci\u00d3n, Al Por Mayor)",
    "sg:phone":"+34 967 48 34 03",
    "sg:postcode":"02270",
    "sg:province":"Albacete",
    "wof:name":"Cambronero Fernandez Maria",
    "wof:placetype":"venue"
},
  "geometry": {"coordinates":[-1.5962789059,39.3595237732],"type":"Point"}
}