{
  "type": "Feature",
  "properties": {
    "iso:country":"ES",
    "sg:address":"Calle de General Ricardos, 158",
    "sg:city":"Madrid",
    "sg:orig_category":"Abogados",
    "sg:phone":"+34 914 71 83 93",
    "sg:postcode":"28019",
    "sg:province":"Madrid",
    "wof:name":"Abad Aguero Fernando",
    "wof:placetype":"venue"
},
  "geometry": {"coordinates":[-3.730815,40.38916],"type":"Point"}
}