{
  "type": "Feature",
  "properties": {
    "iso:country":"ES",
    "sg:address":"Calle de Valencia, 40",
    "sg:city":"Torres Cotillas",
    "sg:orig_category":"Psic\u00d3logos",
    "sg:phone":"+34 968 62 45 93",
    "sg:postcode":"30565",
    "sg:province":"Murcia",
    "wof:name":"Melgarejo Gonzalez-conde Francisca",
    "wof:placetype":"venue"
},
  "geometry": {"coordinates":[-1.2365390062,38.018371582],"type":"Point"}
}