{
  "type": "Feature",
  "properties": {
    "iso:country":"ES",
    "sg:address":"Av America, 89",
    "sg:city":"Mataro",
    "sg:orig_category":"Fabricaci\u00d3n De Distribuidores Autom\u00c1ticos",
    "sg:phone":"+34 937 90 85 57",
    "sg:postcode":"08304",
    "sg:province":"Barcelona",
    "wof:name":"Jomar-7 S.l.",
    "wof:placetype":"venue"
},
  "geometry": {"coordinates":[2.4526259899,41.5470962524],"type":"Point"}
}