{
  "type": "Feature",
  "properties": {
    "iso:country":"ES",
    "sg:address":"Reravalls, S/n",
    "sg:city":"Ventallo",
    "sg:orig_category":"Centros De Educaci\u00d3n Especial",
    "sg:phone":"+34 972 79 30 06",
    "sg:postcode":"17473",
    "sg:province":"Girona",
    "wof:name":"Ajuntament De Ventallo",
    "wof:placetype":"venue"
},
  "geometry": {"coordinates":[3.0261301994,42.1491508484],"type":"Point"}
}