{
  "type": "Feature",
  "properties": {
    "iso:country":"ES",
    "sg:address":"Plaz Magdalena (de La), S/n",
    "sg:city":"Zaragoza",
    "sg:orig_category":"Iglesia Cat\u00d3lica",
    "sg:phone":"+34 976 39 97 45",
    "sg:postcode":"50001",
    "sg:province":"Zaragoza",
    "wof:name":"Parroquia Santa Maria Magdalena",
    "wof:placetype":"venue"
},
  "geometry": {"coordinates":[-0.8735839725,41.6522216797],"type":"Point"}
}