{
  "type": "Feature",
  "properties": {
    "iso:country":"ES",
    "sg:address":"Carrer de Serrat Del Munt, 3",
    "sg:city":"Manlleu",
    "sg:orig_category":"Ingeniero",
    "sg:phone":"+34 938 51 34 86",
    "sg:postcode":"08560",
    "sg:province":"Barcelona",
    "wof:name":"Lopez Perez Jacinto",
    "wof:placetype":"venue"
},
  "geometry": {"coordinates":[2.2782080173,42.0004425049],"type":"Point"}
}