{
  "type": "Feature",
  "properties": {
    "iso:country":"ES",
    "sg:address":"Calle de Regina, 51",
    "sg:city":"Sanlucar De Barrameda",
    "sg:orig_category":"Bebidas",
    "sg:phone":"+34 956 38 02 21",
    "sg:postcode":"11540",
    "sg:province":"C\u00e1diz",
    "wof:name":"Yuste Distribucion S. A.",
    "wof:placetype":"venue"
},
  "geometry": {"coordinates":[-6.3510079384,36.779258728],"type":"Point"}
}