{
  "type": "Feature",
  "properties": {
    "addr:full":"Iribarren Kalea, 11 Lezo Guip\u00f9zcoa 20100",
    "addr:housenumber":"11",
    "addr:postcode":"20100",
    "addr:street":"Iribarren Kalea;Guipu\u0300Zcoa",
    "iso:country":"ES",
    "sg:address":"Iribarren Kalea, 11",
    "sg:city":"Lezo",
    "sg:orig_category":"Promotores Constructores",
    "sg:phone":"+34 943 34 11 37",
    "sg:postcode":"20100",
    "sg:province":"Guip\u00f9zcoa",
    "sg:website":"www.construccionesypromocionesalboka.com",
    "wof:name":"Construcciones Y Promociones Alboka S.l.",
    "wof:placetype":"venue"
},
  "geometry": {"coordinates":[-1.8762940168,43.3255691528],"type":"Point"}
}