{
  "type": "Feature",
  "properties": {
    "iso:country":"ES",
    "sg:address":"Carr Jardins, 26",
    "sg:city":"Sencelles",
    "sg:orig_category":"Maquinaria Para Industrias Diversas",
    "sg:phone":"+34 971 87 25 40",
    "sg:postcode":"07140",
    "sg:province":"Islas Baleares",
    "wof:name":"Firrel Ramis Pedro",
    "wof:placetype":"venue"
},
  "geometry": {"coordinates":[2.8999528885,39.647857666],"type":"Point"}
}