{
  "type": "Feature",
  "properties": {
    "iso:country":"ES",
    "sg:address":"Calle de Federico Pallardo, 5",
    "sg:city":"Alfafar",
    "sg:orig_category":"Laboratorios De An\u00c1lisis Agr\u00cdcolas Y De Biolog\u00cda Vegetal",
    "sg:phone":"+34 963 75 96 60",
    "sg:postcode":"46910",
    "sg:province":"Valencia",
    "wof:name":"Inca Laboratorios C.b.",
    "wof:placetype":"venue"
},
  "geometry": {"coordinates":[-0.3930940032,39.424407959],"type":"Point"}
}