{
  "type": "Feature",
  "properties": {
    "iso:country":"ES",
    "sg:address":"Calle de Infanta Mercedes, 62",
    "sg:city":"Madrid",
    "sg:orig_category":"Electricidad, Electr\u00d3nica: Material Y Suministros (al Por Mayor)",
    "sg:phone":"+34 915 71 30 92",
    "sg:postcode":"28020",
    "sg:province":"Madrid",
    "wof:name":"Novatronic Sistemas S.l.",
    "wof:placetype":"venue"
},
  "geometry": {"coordinates":[-3.6963200569,40.4602508545],"type":"Point"}
}