{
  "type": "Feature",
  "properties": {
    "addr:full":"Calle de Herencias, Las, S/n Talavera Reina Toledo 45600",
    "addr:postcode":"45600",
    "addr:street":"Calle De Herencias Las S / N",
    "iso:country":"ES",
    "sg:address":"Calle de Herencias, Las, S/n",
    "sg:city":"Talavera Reina",
    "sg:orig_category":"Cr\u00cda De Bovinos",
    "sg:phone":"+34 925 59 91 79",
    "sg:postcode":"45600",
    "sg:province":"Toledo",
    "wof:name":"Arenal Del Duque S.a.t.",
    "wof:placetype":"venue"
},
  "geometry": {"coordinates":[-4.8524017334,39.9482345581],"type":"Point"}
}