{
  "type": "Feature",
  "properties": {
    "iso:country":"ES",
    "sg:address":"Avda Europa (de), 13",
    "sg:city":"Alcobendas",
    "sg:orig_category":"Art\u00cdculos De Decoraci\u00d3n",
    "sg:phone":"+34 916 61 64 61",
    "sg:postcode":"28108",
    "sg:province":"Madrid",
    "sg:website":"www.nuevalinea.es",
    "wof:name":"Parkmale S.l.",
    "wof:placetype":"venue"
},
  "geometry": {"coordinates":[-3.6563339233,40.5191040039],"type":"Point"}
}