{
  "type": "Feature",
  "properties": {
    "iso:country":"ES",
    "sg:address":"Carrer de Panyo, 8",
    "sg:city":"Olot",
    "sg:orig_category":"Plomeros",
    "sg:phone":"+34 972 26 51 92",
    "sg:postcode":"17800",
    "sg:province":"Girona",
    "wof:name":"Germans Esparch S.l.l.",
    "wof:placetype":"venue"
},
  "geometry": {"coordinates":[2.4858369827,42.1799049377],"type":"Point"}
}