{
  "type": "Feature",
  "properties": {
    "addr:full":"Carrer de Llauder, 144 Mataro Barcelona 08302",
    "addr:housenumber":"144",
    "addr:postcode":"08302",
    "addr:street":"Carrer De Llauder",
    "iso:country":"ES",
    "sg:address":"Carrer de Llauder, 144",
    "sg:city":"Mataro",
    "sg:orig_category":"Inform\u00c1tica: Material Y Suministros",
    "sg:phone":"+34 937 98 71 16",
    "sg:postcode":"08302",
    "sg:province":"Barcelona",
    "wof:name":"Vila Vivet Pere",
    "wof:placetype":"venue"
},
  "geometry": {"coordinates":[2.4375989437,41.5330162048],"type":"Point"}
}