{
  "type": "Feature",
  "properties": {
    "iso:country":"ES",
    "sg:address":"Carrer de Sant Pere, 19",
    "sg:city":"Gava",
    "sg:orig_category":"Ropa Para Se\u00d1oras Y Caballeros (al Por Menor)",
    "sg:phone":"+34 936 38 40 99",
    "sg:postcode":"08850",
    "sg:province":"Barcelona",
    "wof:name":"Martinez Brau Jose Luis",
    "wof:placetype":"venue"
},
  "geometry": {"coordinates":[2.0046019554,41.3046684265],"type":"Point"}
}