{
  "type": "Feature",
  "properties": {
    "addr:full":"Ed Americas, S/n La Antilla Huelva 21449",
    "addr:postcode":"21449",
    "addr:street":"S / N",
    "iso:country":"ES",
    "sg:address":"Ed Americas, S/n",
    "sg:city":"La Antilla",
    "sg:orig_category":"Abogados",
    "sg:phone":"+34 959 48 66 33",
    "sg:postcode":"21449",
    "sg:province":"Huelva",
    "wof:name":"Sertrafic S.l.",
    "wof:placetype":"venue"
},
  "geometry": {"coordinates":[-7.2509040833,37.2072601318],"type":"Point"}
}