{
  "type": "Feature",
  "properties": {
    "addr:full":"Carrer de Pablo Iglesias, 5 Viladecans Barcelona 08840",
    "addr:housenumber":"5",
    "addr:postcode":"08840",
    "addr:street":"Carrer De Pablo Iglesias",
    "iso:country":"ES",
    "sg:address":"Carrer de Pablo Iglesias, 5",
    "sg:city":"Viladecans",
    "sg:orig_category":"Alquiler De Veh\u00cdculos: Turismos Y Utilitarios",
    "sg:phone":"+34 936 47 53 28",
    "sg:postcode":"08840",
    "sg:province":"Barcelona",
    "sg:website":"www.autofuler.com",
    "wof:name":"Fuler Services S.l",
    "wof:placetype":"venue"
},
  "geometry": {"coordinates":[2.0101509094,41.3144721985],"type":"Point"}
}