{
  "type": "Feature",
  "properties": {
    "iso:country":"ES",
    "sg:address":"Praz Manuel Escuris, 4",
    "sg:city":"Pobra Do Carami\u00e7al",
    "sg:orig_category":"Peluqueros: De Se\u00d1oras",
    "sg:phone":"+34 981 83 26 59",
    "sg:postcode":"15940",
    "sg:province":"La Coru\u00f1a",
    "wof:name":"Regades Villar Monica",
    "wof:placetype":"venue"
},
  "geometry": {"coordinates":[-8.938949585,42.6065750122],"type":"Point"}
}