{
  "type": "Feature",
  "properties": {
    "addr:full":"Av Sant Esteve, 75 Granollers Barcelona 08402",
    "addr:housenumber":"75",
    "addr:postcode":"08402",
    "addr:street":"Av Sant Esteve",
    "iso:country":"ES",
    "sg:address":"Av Sant Esteve, 75",
    "sg:city":"Granollers",
    "sg:orig_category":"Asociaciones Y Clubs Deportivos",
    "sg:phone":"+34 938 79 67 48",
    "sg:postcode":"08402",
    "sg:province":"Barcelona",
    "sg:website":"www.shermansurvival.com",
    "wof:name":"Sherman Survival S.c.",
    "wof:placetype":"venue"
},
  "geometry": {"coordinates":[2.2906351089,41.6013259888],"type":"Point"}
}