{
  "type": "Feature",
  "properties": {
    "iso:country":"ES",
    "sg:address":"Calle de Valentin Carderera, 3",
    "sg:city":"Huesca",
    "sg:orig_category":"Asesor\u00cda Fiscal Y Jur\u00cddica",
    "sg:phone":"+34 974 23 81 39",
    "sg:postcode":"22003",
    "sg:province":"Huesca",
    "wof:name":"Gescolvi Asesoria Fiscal S.l.l.",
    "wof:placetype":"venue"
},
  "geometry": {"coordinates":[-0.4108929932,42.1381950378],"type":"Point"}
}