{
  "type": "Feature",
  "properties": {
    "iso:country":"ES",
    "sg:address":"Calle de Zizeruena, 12",
    "sg:city":"Bilbao",
    "sg:orig_category":"Molduras, Junquillos, Listones Y Molduras Perforadas",
    "sg:phone":"+34 944 11 21 33",
    "sg:postcode":"48004",
    "sg:province":"Vizcaya",
    "wof:name":"Degustacion Etxegai",
    "wof:placetype":"venue"
},
  "geometry": {"coordinates":[-2.900603056,43.2613105774],"type":"Point"}
}