{
  "type": "Feature",
  "properties": {
    "addr:full":"Calle de Millan Astray, 1 Ceuta Ceuta 51001",
    "addr:housenumber":"1",
    "addr:postcode":"51001",
    "addr:street":"Calle De Millan Astray",
    "iso:country":"ES",
    "sg:address":"Calle de Millan Astray, 1",
    "sg:city":"Ceuta",
    "sg:orig_category":"M\u00c9dicos: An\u00c1lisis Cl\u00cdnicos",
    "sg:phone":"+34 956 51 14 35",
    "sg:postcode":"51001",
    "sg:province":"Ceuta",
    "wof:name":"Montero De San Miguel Joaquin",
    "wof:placetype":"venue"
},
  "geometry": {"coordinates":[-5.3086910248,35.8878288269],"type":"Point"}
}