{
  "type": "Feature",
  "properties": {
    "addr:full":"Calle de Alta, 59 Jarque Zaragoza 50258",
    "addr:housenumber":"59",
    "addr:postcode":"50258",
    "addr:street":"Calle De Alta",
    "iso:country":"ES",
    "sg:address":"Calle de Alta, 59",
    "sg:city":"Jarque",
    "sg:orig_category":"Empresas De Carpinter\u00cda De Madera",
    "sg:phone":"+34 976 82 24 38",
    "sg:postcode":"50258",
    "sg:province":"Zaragoza",
    "wof:name":"Mu\u00f1oz Jabal Luis Fernando",
    "wof:placetype":"venue"
},
  "geometry": {"coordinates":[-1.6757833958,41.5549163818],"type":"Point"}
}