{
  "type": "Feature",
  "properties": {
    "addr:full":"Calle de Rosa, 1 Dos Hermanas Sevilla 41700",
    "addr:housenumber":"1",
    "addr:postcode":"41700",
    "addr:street":"Calle De Rosa;Sevilla",
    "iso:country":"ES",
    "sg:address":"Calle de Rosa, 1",
    "sg:city":"Dos Hermanas",
    "sg:orig_category":"Alimentaci\u00d3n General (al Por Menor)",
    "sg:phone":"+34 955 66 03 63",
    "sg:postcode":"41700",
    "sg:province":"Sevilla",
    "wof:name":"Dominguez Blazquez Angel",
    "wof:placetype":"venue"
},
  "geometry": {"coordinates":[-5.9261932373,37.286781311],"type":"Point"}
}