{
  "type": "Feature",
  "properties": {
    "addr:full":"Carrer de L'hospital, 34 Barcelona Barcelona 08001",
    "addr:housenumber":"34",
    "addr:postcode":"08001",
    "addr:street":"Carrer De L'Hospital",
    "iso:country":"ES",
    "sg:address":"Carrer de L'hospital, 34",
    "sg:city":"Barcelona",
    "sg:orig_category":"Bisuter\u00cda, Joyer\u00cda, Relojer\u00cda (al Por Menor)",
    "sg:phone":"+34 933 01 57 29",
    "sg:postcode":"08001",
    "sg:province":"Barcelona",
    "wof:name":"Rossello Casula Pilar",
    "wof:placetype":"venue"
},
  "geometry": {"coordinates":[2.1718378067,41.3808898926],"type":"Point"}
}