{
  "type": "Feature",
  "properties": {
    "addr:full":"Carr Baldomer Sola, 156 Badalona Barcelona 08912",
    "addr:housenumber":"156",
    "addr:postcode":"08912",
    "addr:street":"Carr Baldomer Sola",
    "iso:country":"ES",
    "sg:address":"Carr Baldomer Sola, 156",
    "sg:city":"Badalona",
    "sg:orig_category":"Comercio De Piezas De Recambio Y De Accesorios De Veh\u00cdculos, Veh\u00cdculos Industriales",
    "sg:phone":"+34 934 60 14 12",
    "sg:postcode":"08912",
    "sg:province":"Barcelona",
    "wof:name":"Frapasa S.l.",
    "wof:placetype":"venue"
},
  "geometry": {"coordinates":[2.2350020409,41.4436798096],"type":"Point"}
}