{
  "type": "Feature",
  "properties": {
    "iso:country":"ES",
    "sg:address":"Calle de Gran Via, 40",
    "sg:city":"Madrid",
    "sg:orig_category":"Ayuda En Tareas Dom\u00c9sticas, Ayuda A Domicilio",
    "sg:phone":"+34 915 23 05 85",
    "sg:postcode":"28013",
    "sg:province":"Madrid",
    "sg:website":"www.euroserhogar.com",
    "wof:name":"Euroser Hogar 2000 S.l.",
    "wof:placetype":"venue"
},
  "geometry": {"coordinates":[-3.7049529552,40.4202156067],"type":"Point"}
}