{
  "type": "Feature",
  "properties": {
    "addr:full":"Calle de Ministro Benavides, 61 Villacarrillo Ja\u00e9n 23300",
    "addr:housenumber":"61",
    "addr:postcode":"23300",
    "addr:street":"Calle De Ministro Benavides;Jae\u0301N",
    "iso:country":"ES",
    "sg:address":"Calle de Ministro Benavides, 61",
    "sg:city":"Villacarrillo",
    "sg:orig_category":"Plomeros",
    "sg:phone":"+34 953 44 11 10",
    "sg:postcode":"23300",
    "sg:province":"Ja\u00e9n",
    "wof:name":"Mora Alfonso Jose Luis",
    "wof:placetype":"venue"
},
  "geometry": {"coordinates":[-3.0861129761,38.1163520813],"type":"Point"}
}