{
  "type": "Feature",
  "properties": {
    "addr:full":"Carrer de Gruta, 1 Palma Islas Baleares 07007",
    "addr:housenumber":"1",
    "addr:postcode":"07007",
    "addr:street":"Carrer De Gruta",
    "iso:country":"ES",
    "sg:address":"Carrer de Gruta, 1",
    "sg:city":"Palma",
    "sg:orig_category":"Estancos",
    "sg:phone":"+34 971 25 01 35",
    "sg:postcode":"07007",
    "sg:province":"Islas Baleares",
    "wof:name":"Consultoria De Comunicaciones Y Datos S.l.",
    "wof:placetype":"venue"
},
  "geometry": {"coordinates":[2.6850481033,39.5570068359],"type":"Point"}
}