{
  "type": "Feature",
  "properties": {
    "iso:country":"ES",
    "sg:address":"Pol Ind El Oliveral, S/n",
    "sg:city":"P. I. El Oliveral",
    "sg:orig_category":"Alumbrados",
    "sg:phone":"+34 961 66 85 30",
    "sg:postcode":"46190",
    "sg:province":"Valencia",
    "wof:name":"Pasarela Iluminacion S.l.",
    "wof:placetype":"venue"
},
  "geometry": {"coordinates":[-0.5698940158,39.5458450317],"type":"Point"}
}