{
  "type": "Feature",
  "properties": {
    "addr:full":"Calle de Embajadores, 16 Madrid Madrid 28012",
    "addr:housenumber":"16",
    "addr:postcode":"madrid;28012",
    "addr:street":"Calle De Embajadores",
    "iso:country":"ES",
    "sg:address":"Calle de Embajadores, 16",
    "sg:city":"Madrid",
    "sg:orig_category":"Quincaller\u00cda (al Por Menor)",
    "sg:phone":"+34 915 27 97 37",
    "sg:postcode":"28012",
    "sg:province":"Madrid",
    "wof:name":"Victorino Martin S. A.",
    "wof:placetype":"venue"
},
  "geometry": {"coordinates":[-3.7063748837,40.4098129272],"type":"Point"}
}