{
  "type": "Feature",
  "properties": {
    "iso:country":"ES",
    "sg:address":"Calle de Marroquina, 98",
    "sg:city":"Madrid",
    "sg:orig_category":"Asociaciones Y Clubs Deportivos",
    "sg:phone":"+34 914 37 01 65",
    "sg:postcode":"28030",
    "sg:province":"Madrid",
    "wof:name":"Jimenez Palacios Rosario",
    "wof:placetype":"venue"
},
  "geometry": {"coordinates":[-3.644867897,40.4110832214],"type":"Point"}
}