{
  "type": "Feature",
  "properties": {
    "iso:country":"ES",
    "sg:address":"Av. Zaragoza, 23",
    "sg:city":"Iru\u00f1a",
    "sg:orig_category":"Ense\u00d1anza, Formaci\u00d3n Profesional: Aprendizaje",
    "sg:phone":"+34 948 24 56 00",
    "sg:postcode":"31005",
    "sg:province":"Navarra",
    "wof:name":"Centro De Formacion Politecnica S.a.",
    "wof:placetype":"venue"
},
  "geometry": {"coordinates":[-1.6438440084,42.8089485168],"type":"Point"}
}