{
  "type": "Feature",
  "properties": {
    "iso:country":"ES",
    "sg:address":"Cami Can Suros, 17",
    "sg:city":"Besalu",
    "sg:orig_category":"Empresas De Electricidad En General",
    "sg:phone":"+34 972 59 09 71",
    "sg:postcode":"17850",
    "sg:province":"Girona",
    "wof:name":"Hurtos Costa Josep",
    "wof:placetype":"venue"
},
  "geometry": {"coordinates":[2.6925530434,42.1984481812],"type":"Point"}
}