{
  "type": "Feature",
  "properties": {
    "iso:country":"ES",
    "sg:address":"Calle de Lepanto, 22",
    "sg:city":"Teulada",
    "sg:orig_category":"Promotores Constructores",
    "sg:phone":"+34 965 74 00 29",
    "sg:postcode":"03725",
    "sg:province":"Alicante",
    "wof:name":"Maso Torres Pascual",
    "wof:placetype":"venue"
},
  "geometry": {"coordinates":[0.1061810032,38.7292442322],"type":"Point"}
}