{
  "type": "Feature",
  "properties": {
    "addr:full":"Barreiro, 11 Barreiro Lugo 27286",
    "addr:housenumber":"11",
    "addr:postcode":"27286",
    "addr:street":"Barreiro",
    "iso:country":"ES",
    "sg:address":"Barreiro, 11",
    "sg:city":"Barreiro",
    "sg:orig_category":"Alquiler De Veh\u00cdculos: Turismos Y Utilitarios",
    "sg:phone":"+34 982 34 93 40",
    "sg:postcode":"27286",
    "sg:province":"Lugo",
    "wof:name":"Autocares Ubeda S.l.",
    "wof:placetype":"venue"
},
  "geometry": {"coordinates":[-7.9184670448,42.8086204529],"type":"Point"}
}