{
  "type": "Feature",
  "properties": {
    "iso:country":"ES",
    "sg:address":"Calle de Carlos Vii, 9",
    "sg:city":"Socuellamos",
    "sg:orig_category":"Laboratorios",
    "sg:phone":"+34 926 53 26 28",
    "sg:postcode":"13630",
    "sg:province":"Ciudad Real",
    "wof:name":"Ecoagrocontrol S.l.",
    "wof:placetype":"venue"
},
  "geometry": {"coordinates":[-2.7860453129,39.2836761475],"type":"Point"}
}