{
  "type": "Feature",
  "properties": {
    "iso:country":"ES",
    "sg:address":"Pol. Ind Vidreres, 2",
    "sg:city":"Vidreres",
    "sg:orig_category":"Moda",
    "sg:phone":"+34 972 87 55 00",
    "sg:postcode":"17411",
    "sg:province":"Girona",
    "wof:name":"Davi Tailor S.l.",
    "wof:placetype":"venue"
},
  "geometry": {"coordinates":[2.7773220539,41.789768219],"type":"Point"}
}