{
  "type": "Feature",
  "properties": {
    "iso:country":"ES",
    "sg:address":"Calle de Colombia, 39",
    "sg:city":"Madrid",
    "sg:orig_category":"Inversiones",
    "sg:phone":"+34 913 45 29 88",
    "sg:postcode":"28016",
    "sg:province":"Madrid",
    "wof:name":"Garcia Izquierdo Jeronimo",
    "wof:placetype":"venue"
},
  "geometry": {"coordinates":[-3.6723034382,40.4569816589],"type":"Point"}
}