{
  "type": "Feature",
  "properties": {
    "addr:full":"Calle de Almaden, 3 Armilla Granada 18100",
    "addr:housenumber":"3",
    "addr:postcode":"18100",
    "addr:street":"Calle De Almaden",
    "iso:country":"ES",
    "sg:address":"Calle de Almaden, 3",
    "sg:city":"Armilla",
    "sg:orig_category":"Mec\u00c1nico Del Autom\u00d3vil",
    "sg:phone":"+34 958 55 21 62",
    "sg:postcode":"18100",
    "sg:province":"Granada",
    "wof:name":"Barcia Vargas Concepcion",
    "wof:placetype":"venue"
},
  "geometry": {"coordinates":[-3.6285481453,37.1414031982],"type":"Point"}
}