{
  "type": "Feature",
  "properties": {
    "addr:full":"Calle de Rosario, 109 Albacete Albacete 02003",
    "addr:housenumber":"109",
    "addr:postcode":"02003",
    "addr:street":"Calle De Rosario",
    "iso:country":"ES",
    "sg:address":"Calle de Rosario, 109",
    "sg:city":"Albacete",
    "sg:orig_category":"Locales Deportivos",
    "sg:phone":"+34 967 23 96 84",
    "sg:postcode":"02003",
    "sg:province":"Albacete",
    "wof:name":"Deporteco S.l.",
    "wof:placetype":"venue"
},
  "geometry": {"coordinates":[-1.8606309891,38.987663269],"type":"Point"}
}