{
  "type": "Feature",
  "properties": {
    "iso:country":"ES",
    "sg:address":"Calle de Jose Segura Torres, 8",
    "sg:city":"Corralejo",
    "sg:orig_category":"Asesor\u00cda Sobre Comunicaci\u00d3n De Empresas",
    "sg:phone":"+34 928 86 73 28",
    "sg:postcode":"35660",
    "sg:province":"Las Palmas",
    "wof:name":"Quesada Santana Yolanda",
    "wof:placetype":"venue"
},
  "geometry": {"coordinates":[-13.8680887222,28.7391204834],"type":"Point"}
}