{
  "type": "Feature",
  "properties": {
    "addr:full":"La Ronda, S/n Cuevas Bajas M\u00e1laga 29220",
    "addr:housenumber":"s",
    "addr:postcode":"29220",
    "addr:street":"/ N",
    "iso:country":"ES",
    "sg:address":"La Ronda, S/n",
    "sg:city":"Cuevas Bajas",
    "sg:orig_category":"Cooperativas Agr\u00cdcolas",
    "sg:phone":"+34 952 72 96 29",
    "sg:postcode":"29220",
    "sg:province":"M\u00e1laga",
    "wof:name":"Cooperativa De Corte Y Confeccion La Inmaculada",
    "wof:placetype":"venue"
},
  "geometry": {"coordinates":[-4.4852480888,37.2361106873],"type":"Point"}
}