{
  "type": "Feature",
  "properties": {
    "addr:full":"Calle de Agustina De Aragon, 3 Madrid Madrid 28006",
    "addr:housenumber":"3",
    "addr:postcode":"28006",
    "addr:street":"Calle De Agustina De Aragon",
    "iso:country":"ES",
    "sg:address":"Calle de Agustina De Aragon, 3",
    "sg:city":"Madrid",
    "sg:orig_category":"Inform\u00c1tica: Soportes De Informaci\u00d3n, Suministros & Accesorios",
    "sg:phone":"+34 914 01 50 99",
    "sg:postcode":"28006",
    "sg:province":"Madrid",
    "sg:website":"www.asemat.es",
    "wof:name":"Asemat S.a.",
    "wof:placetype":"venue"
},
  "geometry": {"coordinates":[-3.6726458073,40.4316520691],"type":"Point"}
}