{
  "type": "Feature",
  "properties": {
    "iso:country":"ES",
    "sg:address":"Rbla Marina, 68",
    "sg:city":"Hospitalet Llobregat",
    "sg:orig_category":"Farmacias",
    "sg:phone":"+34 933 35 04 35",
    "sg:postcode":"08907",
    "sg:province":"Barcelona",
    "wof:name":"Farmacia Rey-palau S.c.p.",
    "wof:placetype":"venue"
},
  "geometry": {"coordinates":[2.1115899086,41.3502502441],"type":"Point"}
}