{
  "type": "Feature",
  "properties": {
    "addr:full":"Calle de Padre Florez, 9 Burgos Burgos 09005",
    "addr:housenumber":"9",
    "addr:postcode":"09005",
    "addr:street":"Calle De Padre Florez",
    "iso:country":"ES",
    "sg:address":"Calle de Padre Florez, 9",
    "sg:city":"Burgos",
    "sg:orig_category":"Asociaciones, Organismos Culturales Y Socioeducativos",
    "sg:phone":"+34 947 23 47 69",
    "sg:postcode":"09005",
    "sg:province":"Burgos",
    "wof:name":"Caja De Ahorros Municipal De Burgos",
    "wof:placetype":"venue"
},
  "geometry": {"coordinates":[-3.697822094,42.3485031128],"type":"Point"}
}