{
  "type": "Feature",
  "properties": {
    "iso:country":"ES",
    "sg:address":"Calle de Jaen, 3",
    "sg:city":"Bilbao",
    "sg:orig_category":"Empresas De Carpinter\u00cda De Madera",
    "sg:phone":"+34 944 43 44 49",
    "sg:postcode":"48012",
    "sg:province":"Vizcaya",
    "wof:name":"Francisco Javier Lopez Redondo-gaizya Lopez Quiroga-olatz Lopez Quiroga,cdad",
    "wof:placetype":"venue"
},
  "geometry": {"coordinates":[-2.9438350201,43.253578186],"type":"Point"}
}