{
  "type": "Feature",
  "properties": {
    "addr:full":"Concejo De Ardanaz, 2 Iru\u00f1a Navarra 31016",
    "addr:housenumber":"2",
    "addr:postcode":"31016",
    "addr:street":"Irun\u0303A Navarra",
    "iso:country":"ES",
    "sg:address":"Concejo De Ardanaz, 2",
    "sg:city":"Iru\u00f1a",
    "sg:orig_category":"Inform\u00c1tica, Ofim\u00c1tica (estudios, Asesor\u00cda, Ingenier\u00cda, Formaci\u00d3n)",
    "sg:phone":"+34 948 16 40 50",
    "sg:postcode":"31016",
    "sg:province":"Navarra",
    "wof:name":"Matrix Informatica Sl.",
    "wof:placetype":"venue"
},
  "geometry": {"coordinates":[-1.6138800383,42.8127441406],"type":"Point"}
}