{
  "type": "Feature",
  "properties": {
    "addr:full":"Calle de General Fresneda, 80 Jodar Ja\u00e9n 23500",
    "addr:housenumber":"80",
    "addr:postcode":"23500",
    "addr:street":"Calle De General Fresneda;Jae\u0301N",
    "iso:country":"ES",
    "sg:address":"Calle de General Fresneda, 80",
    "sg:city":"Jodar",
    "sg:orig_category":"Ropa Para Se\u00d1oras Y Caballeros (al Por Menor)",
    "sg:phone":"+34 953 78 78 36",
    "sg:postcode":"23500",
    "sg:province":"Ja\u00e9n",
    "wof:name":"Alimentaria De Jodar S.l.",
    "wof:placetype":"venue"
},
  "geometry": {"coordinates":[-3.3525004387,37.8423728943],"type":"Point"}
}