{
  "type": "Feature",
  "properties": {
    "addr:full":"Bo. Areta, 45 Llodio \u00c1lava 01400",
    "addr:housenumber":"45",
    "addr:postcode":"01400",
    "addr:street":"Bo. Areta",
    "iso:country":"ES",
    "sg:address":"Bo. Areta, 45",
    "sg:city":"Llodio",
    "sg:orig_category":"Centros De Educaci\u00d3n Especial",
    "sg:phone":"+34 946 72 85 35",
    "sg:postcode":"01400",
    "sg:province":"\u00c1lava",
    "sg:website":"www.euskadi.net",
    "wof:name":"Gobierno Vasco-eusko Jaurlaritza",
    "wof:placetype":"venue"
},
  "geometry": {"coordinates":[-2.9429020882,43.1470718384],"type":"Point"}
}