{
  "type": "Feature",
  "properties": {
    "addr:full":"Rbla Pau Casals, 1 Palleja Barcelona 08780",
    "addr:housenumber":"1",
    "addr:postcode":"08780",
    "addr:street":"Rbla Pau Casals",
    "iso:country":"ES",
    "sg:address":"Rbla Pau Casals, 1",
    "sg:city":"Palleja",
    "sg:orig_category":"Bisuter\u00cda, Joyer\u00cda, Relojer\u00cda (al Por Menor)",
    "sg:phone":"+34 936 63 26 46",
    "sg:postcode":"08780",
    "sg:province":"Barcelona",
    "wof:name":"Molina Garcia Vanesa",
    "wof:placetype":"venue"
},
  "geometry": {"coordinates":[1.9983229637,41.4219474792],"type":"Point"}
}