{
  "type": "Feature",
  "properties": {
    "addr:full":"Calle de Ichaso, S/n Madrid Madrid 28041",
    "addr:housenumber":"s / n",
    "addr:postcode":"28041",
    "addr:street":"Calle De Ichaso",
    "iso:country":"ES",
    "sg:address":"Calle de Ichaso, S/n",
    "sg:city":"Madrid",
    "sg:orig_category":"Ense\u00d1anza Variada",
    "sg:phone":"+34 913 41 41 53",
    "sg:postcode":"28041",
    "sg:province":"Madrid",
    "wof:name":"Serrano Garcia Pedro Fernando",
    "wof:placetype":"venue"
},
  "geometry": {"coordinates":[-3.7162940502,40.3705215454],"type":"Point"}
}