{
  "type": "Feature",
  "properties": {
    "addr:full":"Carrer de Marquesos De Barbera, 79 Barbera Valles Barcelona 08210",
    "addr:housenumber":"79",
    "addr:postcode":"08210",
    "addr:street":"Carrer De Marquesos De Barbera",
    "iso:country":"ES",
    "sg:address":"Carrer de Marquesos De Barbera, 79",
    "sg:city":"Barbera Valles",
    "sg:orig_category":"M\u00c9dicos: Geriatr\u00cda, Gerontolog\u00cda (enfermedades De La Tercera Edad)",
    "sg:phone":"+34 937 29 29 22",
    "sg:postcode":"08210",
    "sg:province":"Barcelona",
    "wof:name":"Sophos Barbera S.l.",
    "wof:placetype":"venue"
},
  "geometry": {"coordinates":[2.11845994,41.5185089111],"type":"Point"}
}