{
  "type": "Feature",
  "properties": {
    "addr:full":"Carrer de Navas De Tolosa, 363 Barcelona Barcelona 08041",
    "addr:housenumber":"363",
    "addr:postcode":"08041",
    "addr:street":"Carrer De Navas De Tolosa",
    "iso:country":"ES",
    "sg:address":"Carrer de Navas De Tolosa, 363",
    "sg:city":"Barcelona",
    "sg:orig_category":"Frutas, Legumbres Frescas Y Tempranas (al Por Menor)",
    "sg:phone":"+34 933 52 65 00",
    "sg:postcode":"08041",
    "sg:province":"Barcelona",
    "wof:name":"Sedima Fruit S.l.",
    "wof:placetype":"venue"
},
  "geometry": {"coordinates":[2.182667017,41.4183044434],"type":"Point"}
}