{
  "type": "Feature",
  "properties": {
    "iso:country":"ES",
    "sg:address":"Turo Cavalls, 1",
    "sg:city":"Bescano",
    "sg:orig_category":"Deportes Y Ocio: Art\u00cdculos Y Equipos (al Por Mayor)",
    "sg:phone":"+34 972 44 29 40",
    "sg:postcode":"17162",
    "sg:province":"Girona",
    "sg:website":"www.hexared.com",
    "wof:name":"Hexared S.l.",
    "wof:placetype":"venue"
},
  "geometry": {"coordinates":[2.7393751144,41.9661865234],"type":"Point"}
}