{
  "type": "Feature",
  "properties": {
    "addr:full":"Calle de Francisco Legorburu De, 5 Aviles Asturias 33403",
    "addr:housenumber":"5",
    "addr:postcode":"33403",
    "addr:street":"Calle De Francisco Legorburu De",
    "iso:country":"ES",
    "sg:address":"Calle de Francisco Legorburu De, 5",
    "sg:city":"Aviles",
    "sg:orig_category":"Radiocomunicaciones, Telefon\u00cda M\u00d3vil, Radiomensajer\u00cda: Servicios, Comercializaci\u00d3n",
    "sg:phone":"+34 985 51 61 27",
    "sg:postcode":"33403",
    "sg:province":"Asturias",
    "wof:name":"Instalaciones Electricas Lazcano S.l.",
    "wof:placetype":"venue"
},
  "geometry": {"coordinates":[-5.9031162262,43.5378456116],"type":"Point"}
}