{
  "type": "Feature",
  "properties": {
    "addr:full":"Calle de Alcalde Marchesi, 14 Coru\u00d1a La Coru\u00f1a 15006",
    "addr:housenumber":"14",
    "addr:postcode":"15006",
    "addr:street":"Calle De Alcalde Marchesi;La Corun\u0303A",
    "iso:country":"ES",
    "sg:address":"Calle de Alcalde Marchesi, 14",
    "sg:city":"Coru\u00d1a",
    "sg:orig_category":"Estilistas Y Estudios De Estilo De Corte Y Confecci\u00d3n",
    "sg:phone":"+34 981 28 06 22",
    "sg:postcode":"15006",
    "sg:province":"La Coru\u00f1a",
    "wof:name":"Fernandez Vazquez Modesta",
    "wof:placetype":"venue"
},
  "geometry": {"coordinates":[-8.403626442,43.3559951782],"type":"Point"}
}