{
  "type": "Feature",
  "properties": {
    "iso:country":"ES",
    "sg:address":"Urb S Antonio, S/n",
    "sg:city":"Llombai",
    "sg:orig_category":"Ebanistas Y Talladores De Muebles Y Objetos De Arte",
    "sg:phone":"+34 962 99 06 98",
    "sg:postcode":"46195",
    "sg:province":"Valencia",
    "wof:name":"Gil Vidal Vicente",
    "wof:placetype":"venue"
},
  "geometry": {"coordinates":[-0.5720639825,39.2799758911],"type":"Point"}
}