{
  "type": "Feature",
  "properties": {
    "addr:full":"Avda Vera, 21 Plasencia C\u00e1ceres 10600",
    "addr:housenumber":"21",
    "addr:postcode":"10600",
    "addr:street":"Avda Vera;Ca\u0301Ceres",
    "iso:country":"ES",
    "sg:address":"Avda Vera, 21",
    "sg:city":"Plasencia",
    "sg:orig_category":"Papeler\u00cdas: Art\u00cdculos (al Por Mayor)",
    "sg:phone":"+34 927 42 64 20",
    "sg:postcode":"10600",
    "sg:province":"C\u00e1ceres",
    "wof:name":"Bermejo Martin Juan Angel",
    "wof:placetype":"venue"
},
  "geometry": {"coordinates":[-6.0832190514,40.0318908691],"type":"Point"}
}