{
  "type": "Feature",
  "properties": {
    "iso:country":"ES",
    "sg:address":"Avda Constitucion, S/n",
    "sg:city":"Cebreros",
    "sg:orig_category":"Centros De Educaci\u00d3n Especial",
    "sg:phone":"+34 918 63 02 89",
    "sg:postcode":"05260",
    "sg:province":"\u00c1vila",
    "wof:name":"Colegio Publico Moreno Espinosa",
    "wof:placetype":"venue"
},
  "geometry": {"coordinates":[-4.4641489983,40.4589500427],"type":"Point"}
}