{
  "type": "Feature",
  "properties": {
    "addr:full":"Plaz Arbol De Guernika (del), S/n Eskuernaga \u00c1lava 01307",
    "addr:postcode":"01307",
    "addr:street":"Plaz;S / N Eskuernaga A\u0301Lava",
    "iso:country":"ES",
    "sg:address":"Plaz Arbol De Guernika (del), S/n",
    "sg:city":"Eskuernaga",
    "sg:orig_category":"Farmacias",
    "sg:phone":"+34 945 60 93 07",
    "sg:postcode":"01307",
    "sg:province":"\u00c1lava",
    "wof:name":"Oregui Olaizola Maria Lourdes",
    "wof:placetype":"venue"
},
  "geometry": {"coordinates":[-2.6653320789,42.5489234924],"type":"Point"}
}