{
  "type": "Feature",
  "properties": {
    "addr:full":"Calle de San Bartolome / San Bartolome Kalea, S/n Ibero Navarra 31173",
    "addr:housenumber":"s / n",
    "addr:postcode":"31173",
    "addr:street":"Calle De San;/ San Bartolome Kalea",
    "iso:country":"ES",
    "sg:address":"Calle de San Bartolome / San Bartolome Kalea, S/n",
    "sg:city":"Ibero",
    "sg:orig_category":"Semiller\u00cdas",
    "sg:phone":"+34 948 39 00 85",
    "sg:postcode":"31173",
    "sg:province":"Navarra",
    "wof:name":"Nu\u00f1ez Perez Vicente",
    "wof:placetype":"venue"
},
  "geometry": {"coordinates":[-1.7800890207,42.812877655],"type":"Point"}
}