{
  "type": "Feature",
  "properties": {
    "addr:full":"Oriako Pasealekua, 28 Beasain Guip\u00f9zcoa 20200",
    "addr:housenumber":"28",
    "addr:postcode":"20200",
    "addr:street":"Oriako Pasealekua;Guipu\u0300Zcoa",
    "iso:country":"ES",
    "sg:address":"Oriako Pasealekua, 28",
    "sg:city":"Beasain",
    "sg:orig_category":"Plomeros",
    "sg:phone":"+34 943 08 55 94",
    "sg:postcode":"20200",
    "sg:province":"Guip\u00f9zcoa",
    "wof:name":"Juan Pe\u00f1a Gonzalez",
    "wof:placetype":"venue"
},
  "geometry": {"coordinates":[-2.1897447109,43.0534934998],"type":"Point"}
}