{
  "type": "Feature",
  "properties": {
    "addr:full":"Calle de Marques Del Duero, 76 San Pedro Alcantara M\u00e1laga 29670",
    "addr:housenumber":"76",
    "addr:postcode":"29670",
    "addr:street":"Calle De Marques Del Duero",
    "iso:country":"ES",
    "sg:address":"Calle de Marques Del Duero, 76",
    "sg:city":"San Pedro Alcantara",
    "sg:orig_category":"Centros De Coordinaci\u00d3n",
    "sg:phone":"+34 952 85 32 51",
    "sg:postcode":"29670",
    "sg:province":"M\u00e1laga",
    "wof:name":"Gestiones Gardia S.l.",
    "wof:placetype":"venue"
},
  "geometry": {"coordinates":[-4.9891791344,36.4841003418],"type":"Point"}
}