{
  "type": "Feature",
  "properties": {
    "iso:country":"ES",
    "sg:address":"Calle de Herreria, 10",
    "sg:city":"Eskuernaga",
    "sg:orig_category":"Ense\u00d1anza, Formaci\u00d3n Profesional: Aprendizaje",
    "sg:phone":"+34 945 62 33 81",
    "sg:postcode":"01307",
    "sg:province":"\u00c1lava",
    "wof:name":"Ayuntamiento De Villabuena De Alava",
    "wof:placetype":"venue"
},
  "geometry": {"coordinates":[-2.6644029617,42.5462036133],"type":"Point"}
}