{
  "type": "Feature",
  "properties": {
    "addr:full":"Carrer de Diputacio, 155 Barcelona Barcelona 08011",
    "addr:housenumber":"155",
    "addr:postcode":"08011",
    "addr:street":"Carrer De Diputacio",
    "iso:country":"ES",
    "sg:address":"Carrer de Diputacio, 155",
    "sg:city":"Barcelona",
    "sg:orig_category":"Triper\u00cdas",
    "sg:phone":"+34 934 54 49 30",
    "sg:postcode":"08011",
    "sg:province":"Barcelona",
    "wof:name":"Hijos De Jose Antonin S. A.",
    "wof:placetype":"venue"
},
  "geometry": {"coordinates":[2.1581840515,41.3839073181],"type":"Point"}
}