{
  "type": "Feature",
  "properties": {
    "iso:country":"ES",
    "sg:address":"Calle de Santa Ana, 20",
    "sg:city":"Campo Criptana",
    "sg:orig_category":"Laboratorios Y Cl\u00cdnicas Veterinarias",
    "sg:phone":"+34 926 56 35 36",
    "sg:postcode":"13610",
    "sg:province":"Ciudad Real",
    "wof:name":"Clinica Veterinaria La Mancha Centro S.l.",
    "wof:placetype":"venue"
},
  "geometry": {"coordinates":[-3.1228330135,39.4063339233],"type":"Point"}
}