{
  "type": "Feature",
  "properties": {
    "iso:country":"ES",
    "sg:address":"Rulador, 47",
    "sg:city":"Albox",
    "sg:orig_category":"Arquitectos",
    "sg:phone":"+34 950 43 15 17",
    "sg:postcode":"04800",
    "sg:province":"Almer\u00eda",
    "wof:name":"Sanchez Ollerr Pedro",
    "wof:placetype":"venue"
},
  "geometry": {"coordinates":[-2.1395559311,37.3870735168],"type":"Point"}
}