{
  "type": "Feature",
  "properties": {
    "iso:country":"ES",
    "sg:address":"C/ Pont Dels Ortissos, 7",
    "sg:city":"Elche",
    "sg:orig_category":"Promotores Constructores",
    "sg:phone":"+34 965 45 54 17",
    "sg:postcode":"03202",
    "sg:province":"Alicante",
    "wof:name":"Construcciones Y Reformas Jomahe S.l.",
    "wof:placetype":"venue"
},
  "geometry": {"coordinates":[-0.6953830123,38.2666168213],"type":"Point"}
}