{
  "type": "Feature",
  "properties": {
    "iso:country":"ES",
    "sg:address":"Barrio De Elzaurdia, S/n",
    "sg:city":"Elzaurdia",
    "sg:orig_category":"Supermercados Y Hipermercados",
    "sg:phone":"+34 948 63 13 19",
    "sg:postcode":"31780",
    "sg:province":"Navarra",
    "wof:name":"Venta Izarra S.a.",
    "wof:placetype":"venue"
},
  "geometry": {"coordinates":[-1.6813839674,43.2808914185],"type":"Point"}
}