{
  "type": "Feature",
  "properties": {
    "addr:full":"Poligon Planes Altes, S/n Ulldecona Tarragona 43550",
    "addr:postcode":"43550",
    "addr:street":"Altes S / N",
    "iso:country":"ES",
    "sg:address":"Poligon Planes Altes, S/n",
    "sg:city":"Ulldecona",
    "sg:orig_category":"Hormigonados",
    "sg:phone":"+34 977 26 11 41",
    "sg:postcode":"43550",
    "sg:province":"Tarragona",
    "wof:name":"Europea Del Formigo Sl",
    "wof:placetype":"venue"
},
  "geometry": {"coordinates":[0.4458549917,40.5956993103],"type":"Point"}
}