{
  "type": "Feature",
  "properties": {
    "iso:country":"ES",
    "sg:address":"Av Salou, Km. 0004,5",
    "sg:city":"Reus",
    "sg:orig_category":"Empresas De Vigilancia, Guardia Y Protecci\u00d3n",
    "sg:phone":"+34 977 30 10 36",
    "sg:postcode":"43205",
    "sg:province":"Tarragona",
    "sg:website":"www.prosegur.es",
    "wof:name":"Prosegur Compa\u00f1ia De Seguridad S.a.",
    "wof:placetype":"venue"
},
  "geometry": {"coordinates":[1.107929945,41.1519889832],"type":"Point"}
}