{
  "type": "Feature",
  "properties": {
    "iso:country":"ES",
    "sg:address":"Avda Estacion, 2",
    "sg:city":"Calahorra",
    "sg:orig_category":"Artes Gr\u00c1ficas, Artes Pl\u00c1sticas: Material Y Suministros (al Por Menor)",
    "sg:phone":"+34 941 13 42 63",
    "sg:postcode":"26500",
    "sg:province":"La Rioja",
    "sg:website":"www.microrioja.es",
    "wof:name":"Micro Rioja S.a.",
    "wof:placetype":"venue"
},
  "geometry": {"coordinates":[-1.9612360001,42.3053855896],"type":"Point"}
}