{
  "type": "Feature",
  "properties": {
    "iso:country":"ES",
    "sg:address":"Calle de Angel De Saavedra, 4",
    "sg:city":"Cordoba",
    "sg:orig_category":"Peluquer\u00cdas, Peluquer\u00cda Mixta",
    "sg:phone":"+34 957 49 10 92",
    "sg:postcode":"14003",
    "sg:province":"C\u00f3rdoba",
    "sg:website":"www.spejos.es",
    "wof:name":"Hernanz Color S.l.",
    "wof:placetype":"venue"
},
  "geometry": {"coordinates":[-4.7797679901,37.8826293945],"type":"Point"}
}