{
  "type": "Feature",
  "properties": {
    "addr:full":"Calle de Escorrata (la), 7 Redovan Alicante 03370",
    "addr:housenumber":"7",
    "addr:postcode":"03370",
    "addr:street":"Calle De Escorrata La;Alicante",
    "iso:country":"ES",
    "sg:address":"Calle de Escorrata (la), 7",
    "sg:city":"Redovan",
    "sg:orig_category":"Partidos Pol\u00cdticos",
    "sg:phone":"+34 966 75 55 25",
    "sg:postcode":"03370",
    "sg:province":"Alicante",
    "wof:name":"Partido Socialista Obrero Espa\u00f1ol",
    "wof:placetype":"venue"
},
  "geometry": {"coordinates":[-0.9081199765,38.1130256653],"type":"Point"}
}