{
  "type": "Feature",
  "properties": {
    "addr:full":"Calle de San Francisco, 56 Santa Cruz De Tenerife Santa Cruz De Tenerife 38001",
    "addr:housenumber":"56",
    "addr:postcode":"38001",
    "addr:street":"Calle De San Francisco",
    "iso:country":"ES",
    "sg:address":"Calle de San Francisco, 56",
    "sg:city":"Santa Cruz De Tenerife",
    "sg:orig_category":"Peluqueros: De Se\u00d1oras",
    "sg:phone":"+34 922 28 83 34",
    "sg:postcode":"38001",
    "sg:province":"Santa Cruz De Tenerife",
    "wof:name":"Basi Nieto S.l.u.",
    "wof:placetype":"venue"
},
  "geometry": {"coordinates":[-16.2538375854,28.4946174622],"type":"Point"}
}