{
  "type": "Feature",
  "properties": {
    "addr:full":"Calle de Segura (villarrubia), 39 Villarrubia C\u00f3rdoba 14710",
    "addr:housenumber":"39",
    "addr:postcode":"14710",
    "addr:street":"Calle De Segura Villarrubia",
    "iso:country":"ES",
    "sg:address":"Calle de Segura (villarrubia), 39",
    "sg:city":"Villarrubia",
    "sg:orig_category":"M\u00c9dicos: Estomatolog\u00cda",
    "sg:phone":"+34 957 45 88 53",
    "sg:postcode":"14710",
    "sg:province":"C\u00f3rdoba",
    "wof:name":"Gutierrez-rave Jimenez Bonifacio",
    "wof:placetype":"venue"
},
  "geometry": {"coordinates":[-4.9138088226,37.8484916687],"type":"Point"}
}