{
  "type": "Feature",
  "properties": {
    "iso:country":"ES",
    "sg:address":"Avda Campanar, 31",
    "sg:city":"Valencia",
    "sg:orig_category":"Peluqueros: De Se\u00d1oras",
    "sg:phone":"+34 963 48 59 77",
    "sg:postcode":"46009",
    "sg:province":"Valencia",
    "wof:name":"Vila Vila Desamparados",
    "wof:placetype":"venue"
},
  "geometry": {"coordinates":[-0.3934549987,39.4799804688],"type":"Point"}
}