{
  "type": "Feature",
  "properties": {
    "addr:full":"Ptge Cervantes, 1 Amposta Tarragona 43870",
    "addr:housenumber":"1",
    "addr:postcode":"43870",
    "addr:street":"Ptge Cervantes",
    "iso:country":"ES",
    "sg:address":"Ptge Cervantes, 1",
    "sg:city":"Amposta",
    "sg:orig_category":"Empresas De Pintura Y Revestimientos",
    "sg:phone":"+34 977 70 01 84",
    "sg:postcode":"43870",
    "sg:province":"Tarragona",
    "wof:name":"Garcia Cherta Pedro",
    "wof:placetype":"venue"
},
  "geometry": {"coordinates":[0.5771650076,40.709854126],"type":"Point"}
}