{
  "type": "Feature",
  "properties": {
    "iso:country":"ES",
    "sg:address":"Plaz Alfonso X El Sabio, 3",
    "sg:city":"Pola De Lena",
    "sg:orig_category":"M\u00c9dicos: Estomatolog\u00cda",
    "sg:phone":"+34 985 49 02 94",
    "sg:postcode":"33630",
    "sg:province":"Asturias",
    "wof:name":"Fernandez Garcia Paloma",
    "wof:placetype":"venue"
},
  "geometry": {"coordinates":[-5.8299732208,43.1590232849],"type":"Point"}
}