{
  "type": "Feature",
  "properties": {
    "iso:country":"ES",
    "sg:address":"Carr Didac Garrell I Tauler, 4",
    "sg:city":"Palamos",
    "sg:orig_category":"Agencias De Viajes",
    "sg:phone":"+34 972 31 42 88",
    "sg:postcode":"17230",
    "sg:province":"Girona",
    "wof:name":"Viajes Costa Brava S. L.",
    "wof:placetype":"venue"
},
  "geometry": {"coordinates":[3.1288340092,41.8485603333],"type":"Point"}
}