{
  "type": "Feature",
  "properties": {
    "iso:country":"ES",
    "sg:address":"Carrer de Dom Bosco, 1",
    "sg:city":"Palau-solita I Plegamans",
    "sg:orig_category":"Artes Gr\u00c1ficas, Artes Pl\u00c1sticas: Material Y Suministros (al Por Menor)",
    "sg:phone":"+34 938 64 54 53",
    "sg:postcode":"08184",
    "sg:province":"Barcelona",
    "wof:name":"Llansana Centelles Joaquina",
    "wof:placetype":"venue"
},
  "geometry": {"coordinates":[2.1764099598,41.5882339478],"type":"Point"}
}