{
  "type": "Feature",
  "properties": {
    "iso:country":"ES",
    "sg:address":"Calle de Jacinto Benavente, 2",
    "sg:city":"Mairena Alcor",
    "sg:orig_category":"Cristaler\u00cdas",
    "sg:phone":"+34 955 94 30 63",
    "sg:postcode":"41510",
    "sg:province":"Sevilla",
    "wof:name":"Navarro Sanchez Francisco",
    "wof:placetype":"venue"
},
  "geometry": {"coordinates":[-5.7569103241,37.3723716736],"type":"Point"}
}