{
  "type": "Feature",
  "properties": {
    "iso:country":"ES",
    "sg:address":"Calle de Cornisa, 13",
    "sg:city":"Rozas De Madrid",
    "sg:orig_category":"Camiser\u00cda Y Ropa Interior Masculina (al Por Menor)",
    "sg:phone":"+34 916 38 59 37",
    "sg:postcode":"28230",
    "sg:province":"Madrid",
    "wof:name":"Regordosa C.b.",
    "wof:placetype":"venue"
},
  "geometry": {"coordinates":[-3.8564887047,40.4806213379],"type":"Point"}
}