{
  "type": "Feature",
  "properties": {
    "iso:country":"ES",
    "sg:address":"Avda Santa Isabel, 20",
    "sg:city":"Movera",
    "sg:orig_category":"Perreras, Pensiones Para Perros, Gatos Y Otros Animales",
    "sg:phone":"+34 976 57 26 86",
    "sg:postcode":"50194",
    "sg:province":"Zaragoza",
    "wof:name":"Aragonesa De Animales De Compa\u00f1ia S.c.a.",
    "wof:placetype":"venue"
},
  "geometry": {"coordinates":[-0.8392593861,41.669834137],"type":"Point"}
}