{
  "type": "Feature",
  "properties": {
    "addr:full":"Via Augusta, 57 Tarragona Tarragona 43003",
    "addr:housenumber":"57",
    "addr:postcode":"43003",
    "addr:street":"Via Augusta",
    "iso:country":"ES",
    "sg:address":"Via Augusta, 57",
    "sg:city":"Tarragona",
    "sg:orig_category":"Empresas De Portes Y Mensajer\u00cda",
    "sg:phone":"+34 977 23 09 08",
    "sg:postcode":"43003",
    "sg:province":"Tarragona",
    "wof:name":"Logistic And Courrier Tarraco S.l.",
    "wof:placetype":"venue"
},
  "geometry": {"coordinates":[1.2625989914,41.1166038513],"type":"Point"}
}