{
  "type": "Feature",
  "properties": {
    "addr:full":"G.v. Corts Catalanes, 1040 Barcelona Barcelona 08020",
    "addr:postcode":"1040;08020",
    "addr:street":"Catalanes",
    "iso:country":"ES",
    "sg:address":"G.v. Corts Catalanes, 1040",
    "sg:city":"Barcelona",
    "sg:orig_category":"Confiter\u00cdas, Chocolater\u00cdas (al Por Menor)",
    "sg:phone":"+34 933 08 46 47",
    "sg:postcode":"08020",
    "sg:province":"Barcelona",
    "wof:name":"El Pergami 2006 S.l.",
    "wof:placetype":"venue"
},
  "geometry": {"coordinates":[2.2007329464,41.4131584167],"type":"Point"}
}