{
  "type": "Feature",
  "properties": {
    "iso:country":"ES",
    "sg:address":"Calle de Divino Valles, 4",
    "sg:city":"Alcala Henares",
    "sg:orig_category":"Guarder\u00cdas",
    "sg:phone":"+34 918 82 27 85",
    "sg:postcode":"28805",
    "sg:province":"Madrid",
    "sg:website":"www.pagina.amarilla.es",
    "wof:name":"Hergueta Sierra Teresa",
    "wof:placetype":"venue"
},
  "geometry": {"coordinates":[-3.3590192795,40.4854736328],"type":"Point"}
}