{
  "type": "Feature",
  "properties": {
    "iso:country":"ES",
    "sg:address":"Calle de Entre Arroyos, 11",
    "sg:city":"Madrid",
    "sg:orig_category":"Procuradores",
    "sg:phone":"+34 913 28 08 14",
    "sg:postcode":"28030",
    "sg:province":"Madrid",
    "wof:name":"Garcia Santos Gregorio",
    "wof:placetype":"venue"
},
  "geometry": {"coordinates":[-3.654872179,40.4078407288],"type":"Point"}
}