{
  "type": "Feature",
  "properties": {
    "iso:country":"ES",
    "sg:address":"Calle de Castillo, 3",
    "sg:city":"Santa Cruz De Tenerife",
    "sg:orig_category":"Bazares, Art\u00cdculos De Limpieza Y De Cocina (al Por Menor)",
    "sg:phone":"+34 922 24 11 04",
    "sg:postcode":"38002",
    "sg:province":"Santa Cruz De Tenerife",
    "sg:website":"www.orly.tf",
    "wof:name":"Orly Simplex S.l.",
    "wof:placetype":"venue"
},
  "geometry": {"coordinates":[-16.2493591309,28.4668712616],"type":"Point"}
}