{
  "type": "Feature",
  "properties": {
    "iso:country":"ES",
    "sg:address":"Calle de Pintor Clemente De Torres, 1",
    "sg:city":"Cadiz",
    "sg:orig_category":"Tiendas De Grano, Frutas Y Legumbres Secas (al Por Menor)",
    "sg:phone":"+34 956 28 36 28",
    "sg:postcode":"11010",
    "sg:province":"C\u00e1diz",
    "wof:name":"Hermanos Toyos La Barraca",
    "wof:placetype":"venue"
},
  "geometry": {"coordinates":[-6.2741789818,36.5041542053],"type":"Point"}
}