{
  "type": "Feature",
  "properties": {
    "iso:country":"ES",
    "sg:address":"Calle de Chiva, 107",
    "sg:city":"Cheste",
    "sg:orig_category":"Comerciantes Al Por Mayor De Vinos, Licores Y Alcoholes",
    "sg:phone":"+34 962 51 00 64",
    "sg:postcode":"46380",
    "sg:province":"Valencia",
    "wof:name":"Debon Viadel Ernesto",
    "wof:placetype":"venue"
},
  "geometry": {"coordinates":[-0.6874549985,39.4914588928],"type":"Point"}
}