{
  "type": "Feature",
  "properties": {
    "iso:country":"ES",
    "sg:address":"Calle de Academia, 8",
    "sg:city":"Madrid",
    "sg:orig_category":"Sociedades Y Organismos Burs\u00c1tiles",
    "sg:phone":"+34 914 20 00 25",
    "sg:postcode":"28014",
    "sg:province":"Madrid",
    "wof:name":"Ojalvo Manzanares Pedro Francisco",
    "wof:placetype":"venue"
},
  "geometry": {"coordinates":[-3.6898393631,40.4147529602],"type":"Point"}
}