{
  "type": "Feature",
  "properties": {
    "addr:full":"Calle de Monroy, 9 Salamanca Salamanca 37001",
    "addr:housenumber":"9",
    "addr:postcode":"37001",
    "addr:street":"Calle De Monroy",
    "iso:country":"ES",
    "sg:address":"Calle de Monroy, 9",
    "sg:city":"Salamanca",
    "sg:orig_category":"Supermercados Y Hipermercados",
    "sg:phone":"+34 923 21 95 05",
    "sg:postcode":"37001",
    "sg:province":"Salamanca",
    "wof:name":"Supermercados Champion S.a.",
    "wof:placetype":"venue"
},
  "geometry": {"coordinates":[-5.6607160568,40.9677848816],"type":"Point"}
}