{
  "type": "Feature",
  "properties": {
    "iso:country":"ES",
    "sg:address":"Calle de Cehegin, 11",
    "sg:city":"Calasparra",
    "sg:orig_category":"Congelados: Productos Alimentarios (al Por Menor)",
    "sg:phone":"+34 968 72 12 00",
    "sg:postcode":"30420",
    "sg:province":"Murcia",
    "wof:name":"Lopez Garcia Jose Francisco",
    "wof:placetype":"venue"
},
  "geometry": {"coordinates":[-1.7032014132,38.2271766663],"type":"Point"}
}