{
  "type": "Feature",
  "properties": {
    "iso:country":"ES",
    "sg:address":"Carrer de Alella, 4",
    "sg:city":"Barcelona",
    "sg:orig_category":"Abogados",
    "sg:phone":"+34 933 52 59 56",
    "sg:postcode":"08016",
    "sg:province":"Barcelona",
    "wof:name":"Palacio Giral Maria Carmen",
    "wof:placetype":"venue"
},
  "geometry": {"coordinates":[2.1806681156,41.4315643311],"type":"Point"}
}