{
  "type": "Feature",
  "properties": {
    "addr:full":"Readegos, S/n Vilamarin Ourense 32101",
    "addr:postcode":"32101",
    "addr:street":"Readegos S / N",
    "iso:country":"ES",
    "sg:address":"Readegos, S/n",
    "sg:city":"Vilamarin",
    "sg:orig_category":"Profesiones M\u00c9dicas, Param\u00c9dicas Y Otras",
    "sg:phone":"+34 988 28 60 29",
    "sg:postcode":"32101",
    "sg:province":"Ourense",
    "wof:name":"Gonzalez Puga Rosa",
    "wof:placetype":"venue"
},
  "geometry": {"coordinates":[-7.8583140373,42.435218811],"type":"Point"}
}