{
  "type": "Feature",
  "properties": {
    "iso:country":"ES",
    "sg:address":"Avda Espa\u00d1a, 3",
    "sg:city":"Estepona",
    "sg:orig_category":"Arquitectos",
    "sg:phone":"+34 952 80 71 43",
    "sg:postcode":"29680",
    "sg:province":"M\u00e1laga",
    "wof:name":"Lodavi Arqvitectura",
    "wof:placetype":"venue"
},
  "geometry": {"coordinates":[-5.1431665421,36.4256629944],"type":"Point"}
}