{
  "type": "Feature",
  "properties": {
    "iso:country":"ES",
    "sg:address":"Calle de Tomas Del Valle, S/n",
    "sg:city":"S. Fernando",
    "sg:orig_category":"Asilos De Ancianos. Centros Privados",
    "sg:phone":"+34 956 89 62 53",
    "sg:postcode":"11100",
    "sg:province":"C\u00e1diz",
    "wof:name":"Hermanas Carmelitas De La Caridad",
    "wof:placetype":"venue"
},
  "geometry": {"coordinates":[-6.1959939003,36.4625892639],"type":"Point"}
}