{
  "type": "Feature",
  "properties": {
    "iso:country":"ES",
    "sg:address":"Calle de Iglesia, 35",
    "sg:city":"Madrigueras",
    "sg:orig_category":"Contenedores (mercanc\u00cdas)",
    "sg:phone":"+34 967 48 44 54",
    "sg:postcode":"02230",
    "sg:province":"Albacete",
    "wof:name":"Alberca Valera Prisciliano",
    "wof:placetype":"venue"
},
  "geometry": {"coordinates":[-1.7998013496,39.2353096008],"type":"Point"}
}