{
  "type": "Feature",
  "properties": {
    "addr:full":"Calle de Rosario, 6 Sagunt Valencia 46500",
    "addr:housenumber":"6",
    "addr:postcode":"46500",
    "addr:street":"Calle De Rosario",
    "iso:country":"ES",
    "sg:address":"Calle de Rosario, 6",
    "sg:city":"Sagunt",
    "sg:orig_category":"Bazares, Art\u00cdculos De Limpieza Y De Cocina (al Por Menor)",
    "sg:phone":"+34 962 66 29 24",
    "sg:postcode":"46500",
    "sg:province":"Valencia",
    "wof:name":"Llopis Escriba Maria Dolores",
    "wof:placetype":"venue"
},
  "geometry": {"coordinates":[-0.271739006,39.6781959534],"type":"Point"}
}