{
  "type": "Feature",
  "properties": {
    "iso:country":"ES",
    "sg:address":"Calle de Copernico, 3",
    "sg:city":"Grela",
    "sg:orig_category":"Caf\u00c9s, Bares, Cervecer\u00cdas",
    "sg:phone":"+34 981 26 05 24",
    "sg:postcode":"15008",
    "sg:province":"A Coru\u00f1a",
    "wof:name":"Xestal Cafeterias S.l.",
    "wof:placetype":"venue"
},
  "geometry": {"coordinates":[-8.4512443542,43.3434753418],"type":"Point"}
}