{
  "type": "Feature",
  "properties": {
    "addr:full":"Plaz Constitucion (la), 12 Laredo Cantabria 39770",
    "addr:housenumber":"12",
    "addr:postcode":"39770",
    "addr:street":"Constitucion La",
    "iso:country":"ES",
    "sg:address":"Plaz Constitucion (la), 12",
    "sg:city":"Laredo",
    "sg:orig_category":"Asociaciones Y Clubs Deportivos",
    "sg:phone":"+34 942 60 59 08",
    "sg:postcode":"39770",
    "sg:province":"Cantabria",
    "wof:name":"Gomez Lopez Felipe",
    "wof:placetype":"venue"
},
  "geometry": {"coordinates":[-3.4082789421,43.4121055603],"type":"Point"}
}