{
  "type": "Feature",
  "properties": {
    "iso:country":"ES",
    "sg:address":"Calle de Cadiz, 1",
    "sg:city":"Jerez De La Frontera",
    "sg:orig_category":"Expertos Contables, Revisores De Cuentas",
    "sg:phone":"+34 956 34 56 13",
    "sg:postcode":"11402",
    "sg:province":"C\u00e1diz",
    "wof:name":"Gades Auditores Asociados S.l.",
    "wof:placetype":"venue"
},
  "geometry": {"coordinates":[-6.1314167976,36.6913528442],"type":"Point"}
}