{
  "type": "Feature",
  "properties": {
    "addr:full":"Calle de Periodista Justo Urrutia, S/n Cordoba C\u00f3rdoba 14010",
    "addr:housenumber":"s / n",
    "addr:postcode":"14010",
    "addr:street":"Calle De Periodista Justo Urrutia;Co\u0301Rdoba",
    "iso:country":"ES",
    "sg:address":"Calle de Periodista Justo Urrutia, S/n",
    "sg:city":"Cordoba",
    "sg:orig_category":"Molduras, Junquillos, Listones Y Molduras Perforadas",
    "sg:phone":"+34 957 75 16 94",
    "sg:postcode":"14010",
    "sg:province":"C\u00f3rdoba",
    "wof:name":"Morales Rodriguez Santiago",
    "wof:placetype":"venue"
},
  "geometry": {"coordinates":[-4.7622241974,37.8799781799],"type":"Point"}
}