{
  "type": "Feature",
  "properties": {
    "addr:full":"Muel Nardiz Tar Benanzio, 21 Bermeo Vizcaya 48370",
    "addr:housenumber":"21",
    "addr:postcode":"48370",
    "addr:street":"Benanzio",
    "iso:country":"ES",
    "sg:address":"Muel Nardiz Tar Benanzio, 21",
    "sg:city":"Bermeo",
    "sg:orig_category":"Molduras, Junquillos, Listones Y Molduras Perforadas",
    "sg:phone":"+34 946 88 32 71",
    "sg:postcode":"48370",
    "sg:province":"Vizcaya",
    "wof:name":"Sistelcom-telemensaje S.a.",
    "wof:placetype":"venue"
},
  "geometry": {"coordinates":[-2.7204699516,43.4205856323],"type":"Point"}
}