{
  "type": "Feature",
  "properties": {
    "iso:country":"ES",
    "sg:address":"Calle de Torrecerredo, 27",
    "sg:city":"Oviedo",
    "sg:orig_category":"Fabricaci\u00d3n De Productos Textiles Sin Tejer",
    "sg:phone":"+34 985 11 11 65",
    "sg:postcode":"33012",
    "sg:province":"Asturias",
    "wof:name":"Alvarez Torres Aniceto",
    "wof:placetype":"venue"
},
  "geometry": {"coordinates":[-5.8545489311,43.3706092834],"type":"Point"}
}