{
  "type": "Feature",
  "properties": {
    "addr:full":"Calle de Mayor, S/n Puente Tocinos Murcia 30006",
    "addr:housenumber":"s / n",
    "addr:postcode":"30006",
    "addr:street":"Calle De Mayor",
    "iso:country":"ES",
    "sg:address":"Calle de Mayor, S/n",
    "sg:city":"Puente Tocinos",
    "sg:orig_category":"Bancos",
    "sg:phone":"+34 968 30 40 41",
    "sg:postcode":"30006",
    "sg:province":"Murcia",
    "wof:name":"Auna Telecomunicaciones S.a.u.",
    "wof:placetype":"venue"
},
  "geometry": {"coordinates":[-1.102565527,37.9934158325],"type":"Point"}
}