{
  "type": "Feature",
  "properties": {
    "iso:country":"ES",
    "sg:address":"Calle de Virgen De Bego\u00d1a, 16",
    "sg:city":"Bilbao",
    "sg:orig_category":"Inform\u00c1tica (estudios, Servicios, Asesor\u00cda, Formaci\u00d3n)",
    "sg:phone":"+34 944 79 54 11",
    "sg:postcode":"48006",
    "sg:province":"Vizcaya",
    "wof:name":"Bizcaina-aplicaciones De Software De Sistemas S.l.",
    "wof:placetype":"venue"
},
  "geometry": {"coordinates":[-2.9174070358,43.2595176697],"type":"Point"}
}