{
  "type": "Feature",
  "properties": {
    "iso:country":"ES",
    "sg:address":"Pedro Pareja Morales, S/n",
    "sg:city":"Zamoranos",
    "sg:orig_category":"Tiendas De Grano, Frutas Y Legumbres Secas (al Por Menor)",
    "sg:phone":"+34 957 55 63 36",
    "sg:postcode":"14814",
    "sg:province":"C\u00f3rdoba",
    "wof:name":"Consorcio Exportador Andaluz",
    "wof:placetype":"venue"
},
  "geometry": {"coordinates":[-4.1640138626,37.5259399414],"type":"Point"}
}