{
  "type": "Feature",
  "properties": {
    "addr:full":"Av Collidors, 14 Pu\u00e7ol Valencia 46530",
    "addr:housenumber":"14",
    "addr:postcode":"46530",
    "addr:street":"Av Collidors",
    "iso:country":"ES",
    "sg:address":"Av Collidors, 14",
    "sg:city":"Pu\u00e7ol",
    "sg:orig_category":"Instalaci\u00d3n De Aspiraci\u00d3n De Gases Y Humos",
    "sg:phone":"+34 961 42 22 73",
    "sg:postcode":"46530",
    "sg:province":"Valencia",
    "wof:name":"Canalizaciones Instalaciones Y Servicios S.l.",
    "wof:placetype":"venue"
},
  "geometry": {"coordinates":[-0.3024829924,39.6232643127],"type":"Point"}
}