{
  "type": "Feature",
  "properties": {
    "iso:country":"ES",
    "sg:address":"Carrer de Balmes, 62",
    "sg:city":"Reus",
    "sg:orig_category":"Chapister\u00cda",
    "sg:phone":"+34 977 75 67 92",
    "sg:postcode":"43205",
    "sg:province":"Tarragona",
    "wof:name":"Manuel Camafort Redondo-carmen Luque Espadas C.b.",
    "wof:placetype":"venue"
},
  "geometry": {"coordinates":[1.1083749533,41.1511764526],"type":"Point"}
}