{
  "type": "Feature",
  "properties": {
    "iso:country":"ES",
    "sg:address":"Calle de Archidona, 11",
    "sg:city":"San Pedro Alcantara",
    "sg:orig_category":"Traductores",
    "sg:phone":"+34 952 79 93 83",
    "sg:postcode":"29670",
    "sg:province":"M\u00e1laga",
    "sg:website":"www.translationsteam.net",
    "wof:name":"Translationsteam S.l.",
    "wof:placetype":"venue"
},
  "geometry": {"coordinates":[-4.9931221008,36.4882698059],"type":"Point"}
}