{
  "type": "Feature",
  "properties": {
    "addr:full":"R Pez Acevedo, 4 Lepe Huelva 21440",
    "addr:housenumber":"4",
    "addr:postcode":"21440",
    "addr:street":"R Pez Acevedo",
    "iso:country":"ES",
    "sg:address":"R Pez Acevedo, 4",
    "sg:city":"Lepe",
    "sg:orig_category":"Ropa Para Ni\u00d1os (al Por Menor)",
    "sg:phone":"+34 959 38 20 09",
    "sg:postcode":"21440",
    "sg:province":"Huelva",
    "wof:name":"Leon Aguilar Maria",
    "wof:placetype":"venue"
},
  "geometry": {"coordinates":[-7.2030172348,37.254737854],"type":"Point"}
}