{
  "type": "Feature",
  "properties": {
    "iso:country":"ES",
    "sg:address":"Calle de Leganes (de), 14",
    "sg:city":"Fuenlabrada",
    "sg:orig_category":"Lencer\u00cda Femenina, Corseter\u00cda, Trajes De Ba\u00d1o (al Por Menor)",
    "sg:phone":"+34 916 06 58 50",
    "sg:postcode":"28945",
    "sg:province":"Madrid",
    "wof:name":"Jbari El Arabi Abdellah",
    "wof:placetype":"venue"
},
  "geometry": {"coordinates":[-3.792924881,40.2856254578],"type":"Point"}
}