{
  "type": "Feature",
  "properties": {
    "iso:country":"ES",
    "sg:address":"Avda Andalucia, 1",
    "sg:city":"Lebrija",
    "sg:orig_category":"Estudios, Instalaci\u00d3n De Climatizaci\u00d3n",
    "sg:phone":"+34 955 97 36 86",
    "sg:postcode":"41740",
    "sg:province":"Sevilla",
    "wof:name":"La Instaladora Lebrijana S.l",
    "wof:placetype":"venue"
},
  "geometry": {"coordinates":[-6.0804591179,36.9220657349],"type":"Point"}
}