{
  "type": "Feature",
  "properties": {
    "addr:full":"Calle de Conde De Altea, 31 Valencia Valencia 46005",
    "addr:housenumber":"31",
    "addr:postcode":"46005",
    "addr:street":"Calle De Conde De Altea",
    "iso:country":"ES",
    "sg:address":"Calle de Conde De Altea, 31",
    "sg:city":"Valencia",
    "sg:orig_category":"Restaurantes",
    "sg:phone":"+34 963 34 07 53",
    "sg:postcode":"46005",
    "sg:province":"Valencia",
    "wof:name":"La Ambrusqueria S.l.",
    "wof:placetype":"venue"
},
  "geometry": {"coordinates":[-0.3666033149,39.4666175842],"type":"Point"}
}