{
  "type": "Feature",
  "properties": {
    "iso:country":"ES",
    "sg:address":"Calle de Celia Vi\u00d1as, S/n",
    "sg:city":"Almeria",
    "sg:orig_category":"Ense\u00d1anza Secundaria: Colegios Y Escuelas Privadas",
    "sg:phone":"+34 950 24 35 66",
    "sg:postcode":"04007",
    "sg:province":"Almer\u00eda",
    "wof:name":"Instituto Nacional Bachillerato Nicolas Salmeron",
    "wof:placetype":"venue"
},
  "geometry": {"coordinates":[-2.4503276348,36.8327522278],"type":"Point"}
}