{
  "type": "Feature",
  "properties": {
    "iso:country":"ES",
    "sg:address":"Calle de Barquillo, 19",
    "sg:city":"Madrid",
    "sg:orig_category":"Fabricaci\u00d3n, Importaci\u00d3n De L\u00c1mparas Y Bombillas",
    "sg:phone":"+34 915 31 20 64",
    "sg:postcode":"28004",
    "sg:province":"Madrid",
    "wof:name":"Electricidad E Iluminacion Madrid S.l.",
    "wof:placetype":"venue"
},
  "geometry": {"coordinates":[-3.6956727505,40.4220161438],"type":"Point"}
}