{
  "type": "Feature",
  "properties": {
    "iso:country":"ES",
    "sg:address":"Calle de Saturnino Cachon, 34",
    "sg:city":"Ponferrada",
    "sg:orig_category":"Carnicer\u00cdas, Carnicer\u00cdas",
    "sg:phone":"+34 987 41 47 03",
    "sg:postcode":"24400",
    "sg:province":"Le\u00f3n",
    "wof:name":"Alvarez Vizcaino Agustin",
    "wof:placetype":"venue"
},
  "geometry": {"coordinates":[-6.5862669945,42.5475311279],"type":"Point"}
}