{
  "type": "Feature",
  "properties": {
    "addr:full":"Pase Romeral (del), 2 Puente-genil C\u00f3rdoba 14500",
    "addr:postcode":"14500",
    "addr:street":"Co\u0301Rdoba",
    "iso:country":"ES",
    "sg:address":"Pase Romeral (del), 2",
    "sg:city":"Puente-genil",
    "sg:orig_category":"Farmacias",
    "sg:phone":"+34 957 60 04 77",
    "sg:postcode":"14500",
    "sg:province":"C\u00f3rdoba",
    "wof:name":"Farmacia Villafranca Comunidad De Bienes",
    "wof:placetype":"venue"
},
  "geometry": {"coordinates":[-4.7779579163,37.3909187317],"type":"Point"}
}