{
  "type": "Feature",
  "properties": {
    "iso:country":"ES",
    "sg:address":"Calle de Cervantes, 13",
    "sg:city":"Santa Pola",
    "sg:orig_category":"Caf\u00c9s, Bares, Cervecer\u00cdas",
    "sg:phone":"+34 965 41 13 78",
    "sg:postcode":"03130",
    "sg:province":"Alicante",
    "wof:name":"Da Rosa Center S.l.",
    "wof:placetype":"venue"
},
  "geometry": {"coordinates":[-0.5549126267,38.1912879944],"type":"Point"}
}