{
  "type": "Feature",
  "properties": {
    "addr:full":"Calle de Ribera De Curtidores, 32 Madrid Madrid 28005",
    "addr:housenumber":"32",
    "addr:postcode":"madrid;28005",
    "addr:street":"Calle De Ribera De Curtidores",
    "iso:country":"ES",
    "sg:address":"Calle de Ribera De Curtidores, 32",
    "sg:city":"Madrid",
    "sg:orig_category":"Molduras, Junquillos, Listones Y Molduras Perforadas",
    "sg:phone":"+34 914 68 79 03",
    "sg:postcode":"28005",
    "sg:province":"Madrid",
    "wof:name":"Zhou Ruan Li Fei",
    "wof:placetype":"venue"
},
  "geometry": {"coordinates":[-3.7068772316,40.4046478271],"type":"Point"}
}