{
  "type": "Feature",
  "properties": {
    "addr:full":"Carrer de Magi Albert Cassanyes, S/n Sitges Barcelona 08870",
    "addr:housenumber":"s / n",
    "addr:postcode":"08870",
    "addr:street":"Carrer De Magi Albert Cassanyes",
    "iso:country":"ES",
    "sg:address":"Carrer de Magi Albert Cassanyes, S/n",
    "sg:city":"Sitges",
    "sg:orig_category":"Promotores Constructores",
    "sg:phone":"+34 938 10 24 48",
    "sg:postcode":"08870",
    "sg:province":"Barcelona",
    "wof:name":"R.p. Properties S.l.",
    "wof:placetype":"venue"
},
  "geometry": {"coordinates":[1.8035449982,41.2452392578],"type":"Point"}
}