{
  "type": "Feature",
  "properties": {
    "iso:country":"ES",
    "sg:address":"Cra Laurea Miro, 142",
    "sg:city":"Sant Feliu Llobregat",
    "sg:orig_category":"Estancos",
    "sg:phone":"+34 936 66 13 48",
    "sg:postcode":"08980",
    "sg:province":"Barcelona",
    "wof:name":"Pomar Grau Maria Rosa",
    "wof:placetype":"venue"
},
  "geometry": {"coordinates":[2.0457398891,41.3798675537],"type":"Point"}
}