{
  "type": "Feature",
  "properties": {
    "iso:country":"ES",
    "sg:address":"Calle de Zuatzu, 4",
    "sg:city":"Donostia-san Sebastian",
    "sg:orig_category":"Asesor\u00cda Sobre Comunicaci\u00d3n De Empresas",
    "sg:phone":"+34 943 31 61 15",
    "sg:postcode":"20009",
    "sg:province":"Guip\u00f9zcoa",
    "sg:website":"www.opeconsultores.es",
    "wof:name":"Ope Consultores S.l.",
    "wof:placetype":"venue"
},
  "geometry": {"coordinates":[-1.9794000387,43.3173789978],"type":"Point"}
}