{
  "type": "Feature",
  "properties": {
    "iso:country":"ES",
    "sg:address":"Calle de Mugakoa, 33",
    "sg:city":"Portugalete",
    "sg:orig_category":"Muebles, Minoristas",
    "sg:phone":"+34 944 83 69 81",
    "sg:postcode":"48920",
    "sg:province":"Vizcaya",
    "wof:name":"Solla Lafora Jose",
    "wof:placetype":"venue"
},
  "geometry": {"coordinates":[-3.0251235962,43.3234291077],"type":"Point"}
}