{
  "type": "Feature",
  "properties": {
    "iso:country":"ES",
    "sg:address":"Trva Vivero, 3",
    "sg:city":"Trillo",
    "sg:orig_category":"Energ\u00cda Solar Y Nuevas Energ\u00cdas (equipo, Estudios)",
    "sg:phone":"+34 949 81 55 30",
    "sg:postcode":"19450",
    "sg:province":"Guadalajara",
    "wof:name":"C.b.central Nuclear De Trillo",
    "wof:placetype":"venue"
},
  "geometry": {"coordinates":[-2.5927939415,40.6991767883],"type":"Point"}
}