{
  "type": "Feature",
  "properties": {
    "addr:full":"Rua Irmans Moreno, 2 Verin Ourense 32600",
    "addr:housenumber":"2",
    "addr:postcode":"32600",
    "addr:street":"Rua Irmans Moreno",
    "iso:country":"ES",
    "sg:address":"Rua Irmans Moreno, 2",
    "sg:city":"Verin",
    "sg:orig_category":"Fabricaci\u00d3n, Importaci\u00d3n, Venta De Material De Telefon\u00cda, Peritelefon\u00cda",
    "sg:phone":"+34 988 41 14 85",
    "sg:postcode":"32600",
    "sg:province":"Ourense",
    "wof:name":"Mobile Phone Galicia S.l.",
    "wof:placetype":"venue"
},
  "geometry": {"coordinates":[-7.4324841499,41.9374809265],"type":"Point"}
}