{
  "type": "Feature",
  "properties": {
    "addr:full":"Calle de Labayru, 27 Bilbao Vizcaya 48012",
    "addr:housenumber":"27",
    "addr:postcode":"48012",
    "addr:street":"Calle De Labayru",
    "iso:country":"ES",
    "sg:address":"Calle de Labayru, 27",
    "sg:city":"Bilbao",
    "sg:orig_category":"Fiesta: Art\u00cdculos De (al Por Menor)",
    "sg:phone":"+34 944 43 29 58",
    "sg:postcode":"48012",
    "sg:province":"Vizcaya",
    "wof:name":"Arechaga Lores Carlos Javier",
    "wof:placetype":"venue"
},
  "geometry": {"coordinates":[-2.9401686192,43.2566604614],"type":"Point"}
}