{
  "type": "Feature",
  "properties": {
    "iso:country":"ES",
    "sg:address":"Calle de Santa Maria Salome, 10",
    "sg:city":"Bonares",
    "sg:orig_category":"Centros Empresariales",
    "sg:phone":"+34 959 36 40 43",
    "sg:postcode":"21830",
    "sg:province":"Huelva",
    "wof:name":"Cooperacion Y Desarrollo De Bonares S.coop.and.",
    "wof:placetype":"venue"
},
  "geometry": {"coordinates":[-6.6808657646,37.3215026855],"type":"Point"}
}