{
  "type": "Feature",
  "properties": {
    "iso:country":"ES",
    "sg:address":"Ctra. Soria, Km. 0105,0",
    "sg:city":"Agreda",
    "sg:orig_category":"Reparaciones Y Remolcado De Veh\u00cdculos",
    "sg:phone":"+34 976 64 71 20",
    "sg:postcode":"42100",
    "sg:province":"Soria",
    "wof:name":"Talleres Vider S.l.",
    "wof:placetype":"venue"
},
  "geometry": {"coordinates":[-1.9239610434,41.8537368774],"type":"Point"}
}