{
  "type": "Feature",
  "properties": {
    "iso:country":"ES",
    "sg:address":"Calle de Ruise\u00d1or, 7",
    "sg:city":"Zaragoza",
    "sg:orig_category":"Asociaciones, Organismos Culturales Y Socioeducativos",
    "sg:phone":"+34 976 47 06 21",
    "sg:postcode":"50014",
    "sg:province":"Zaragoza",
    "wof:name":"Asociacion Ruise\u00f1or",
    "wof:placetype":"venue"
},
  "geometry": {"coordinates":[-0.8600865006,41.6633758545],"type":"Point"}
}