{
  "type": "Feature",
  "properties": {
    "iso:country":"ES",
    "sg:address":"Carr Triomf, 57",
    "sg:city":"Badalona",
    "sg:orig_category":"Mec\u00c1nico Del Autom\u00d3vil",
    "sg:phone":"+34 933 84 16 61",
    "sg:postcode":"08911",
    "sg:province":"Barcelona",
    "wof:name":"Barnich Gimenez Ignacio",
    "wof:placetype":"venue"
},
  "geometry": {"coordinates":[2.2551870346,41.4535903931],"type":"Point"}
}