{
  "type": "Feature",
  "properties": {
    "iso:country":"ES",
    "sg:address":"Calle de Alejandrina Moran, 19",
    "sg:city":"Madrid",
    "sg:orig_category":"Centros Empresariales",
    "sg:phone":"+34 914 79 71 14",
    "sg:postcode":"28047",
    "sg:province":"Madrid",
    "wof:name":"Asociacion Ser",
    "wof:placetype":"venue"
},
  "geometry": {"coordinates":[-3.7469627857,40.4024429321],"type":"Point"}
}