{
  "type": "Feature",
  "properties": {
    "addr:full":"Crta Isla Menor (p I Fuente Del Rey), S/n Dos Hermanas Sevilla 41700",
    "addr:postcode":"41700",
    "addr:street":"Crta Isla Menor P;Rey S / N Dos",
    "iso:country":"ES",
    "sg:address":"Crta Isla Menor (p I Fuente Del Rey), S/n",
    "sg:city":"Dos Hermanas",
    "sg:orig_category":"Ambulancias",
    "sg:phone":"+34 954 68 03 00",
    "sg:postcode":"41700",
    "sg:province":"Sevilla",
    "wof:name":"Servicios De Asistencia Medica De Urgencia S.a.",
    "wof:placetype":"venue"
},
  "geometry": {"coordinates":[-5.9378409386,37.2788009644],"type":"Point"}
}