{
  "type": "Feature",
  "properties": {
    "addr:full":"Calle de Puerto Alto, 36 Madrid Madrid 28053",
    "addr:housenumber":"36",
    "addr:postcode":"madrid;28053",
    "addr:street":"Calle De Puerto Alto",
    "iso:country":"ES",
    "sg:address":"Calle de Puerto Alto, 36",
    "sg:city":"Madrid",
    "sg:orig_category":"Plomeros",
    "sg:phone":"+34 914 77 98 02",
    "sg:postcode":"28053",
    "sg:province":"Madrid",
    "wof:name":"Eregas S.l.",
    "wof:placetype":"venue"
},
  "geometry": {"coordinates":[-3.6682229042,40.393371582],"type":"Point"}
}