{
  "type": "Feature",
  "properties": {
    "addr:full":"Avda Ch De Monover, S/n Xinorlet Alicante 03649",
    "addr:housenumber":"s",
    "addr:postcode":"03649",
    "addr:street":"Avda Ch De Monover;/ N Xinorlet",
    "iso:country":"ES",
    "sg:address":"Avda Ch De Monover, S/n",
    "sg:city":"Xinorlet",
    "sg:orig_category":"Fabricaci\u00d3n De Sobres, Bolsas Y Fundas",
    "sg:phone":"+34 966 97 95 04",
    "sg:postcode":"03649",
    "sg:province":"Alicante",
    "sg:website":"www.ferchi.com",
    "wof:name":"Ferran Monzo S.l.",
    "wof:placetype":"venue"
},
  "geometry": {"coordinates":[-0.9618210196,38.417804718],"type":"Point"}
}