{
  "type": "Feature",
  "properties": {
    "iso:country":"ES",
    "sg:address":"Calle de Jose Pellicer, 29",
    "sg:city":"Zaragoza",
    "sg:orig_category":"Agencias Y Agentes Comerciales, Representantes",
    "sg:phone":"+34 976 25 33 23",
    "sg:postcode":"50007",
    "sg:province":"Zaragoza",
    "wof:name":"Guallart Vieitez Joaquin",
    "wof:placetype":"venue"
},
  "geometry": {"coordinates":[-0.8800230026,41.6382064819],"type":"Point"}
}