{
  "type": "Feature",
  "properties": {
    "iso:country":"ES",
    "sg:address":"Carr Santa Eugenia, 7",
    "sg:city":"Girona",
    "sg:orig_category":"Abogados",
    "sg:phone":"+34 972 21 20 66",
    "sg:postcode":"17001",
    "sg:province":"Girona",
    "wof:name":"Tulsa Valenti Josep",
    "wof:placetype":"venue"
},
  "geometry": {"coordinates":[2.8183419704,41.9819831848],"type":"Point"}
}