{
  "type": "Feature",
  "properties": {
    "addr:full":"Carrer de Josep Prats, 16 Hospitalet Llobregat Barcelona 08901",
    "addr:housenumber":"16",
    "addr:postcode":"08901",
    "addr:street":"Carrer De Josep Prats",
    "iso:country":"ES",
    "sg:address":"Carrer de Josep Prats, 16",
    "sg:city":"Hospitalet Llobregat",
    "sg:orig_category":"Frutas, Legumbres Frescas Y Tempranas (al Por Menor)",
    "sg:phone":"+34 933 37 14 06",
    "sg:postcode":"08901",
    "sg:province":"Barcelona",
    "wof:name":"Jofre Giralt Josep",
    "wof:placetype":"venue"
},
  "geometry": {"coordinates":[2.0990109444,41.3588180542],"type":"Point"}
}