{
  "type": "Feature",
  "properties": {
    "iso:country":"ES",
    "sg:address":"Calle de San Rafael, 4",
    "sg:city":"Tijola",
    "sg:orig_category":"Venta, Instalaci\u00d3n De Calefacci\u00d3n",
    "sg:phone":"+34 950 42 06 93",
    "sg:postcode":"04880",
    "sg:province":"Almer\u00eda",
    "wof:name":"Concaguas S.l.",
    "wof:placetype":"venue"
},
  "geometry": {"coordinates":[-2.4330890179,37.3472862244],"type":"Point"}
}