{
  "type": "Feature",
  "properties": {
    "addr:full":"Calle de Tamarindo (del), 25 Parque Coimbra Madrid 28935",
    "addr:postcode":"28935",
    "addr:street":"Calle De Tamarindo Del;Parque",
    "iso:country":"ES",
    "sg:address":"Calle de Tamarindo (del), 25",
    "sg:city":"Parque Coimbra",
    "sg:orig_category":"Alquiler De V\u00cddeo",
    "sg:phone":"+34 916 47 87 93",
    "sg:postcode":"28935",
    "sg:province":"Madrid",
    "wof:name":"Casta\u00f1eda Y Romero Videos S.l.",
    "wof:placetype":"venue"
},
  "geometry": {"coordinates":[-3.9230549335,40.3128738403],"type":"Point"}
}