{
  "type": "Feature",
  "properties": {
    "addr:full":"Carrer de Mar, 19 Pego Alicante 03780",
    "addr:housenumber":"19",
    "addr:postcode":"03780",
    "addr:street":"Carrer De Mar",
    "iso:country":"ES",
    "sg:address":"Carrer de Mar, 19",
    "sg:city":"Pego",
    "sg:orig_category":"Carnicer\u00cdas, Carnicer\u00cdas",
    "sg:phone":"+34 965 57 04 66",
    "sg:postcode":"03780",
    "sg:province":"Alicante",
    "wof:name":"Guixot Saez Jose",
    "wof:placetype":"venue"
},
  "geometry": {"coordinates":[-0.1165879965,38.8387260437],"type":"Point"}
}