{
  "type": "Feature",
  "properties": {
    "iso:country":"ES",
    "sg:address":"Poli Trascueto, S/n",
    "sg:city":"Revilla",
    "sg:orig_category":"Mec\u00c1nica Y Herramientas De Precisi\u00d3n",
    "sg:phone":"+34 942 26 97 60",
    "sg:postcode":"39600",
    "sg:province":"Cantabria",
    "wof:name":"Industrias Cantabras De Torneado S.l.",
    "wof:placetype":"venue"
},
  "geometry": {"coordinates":[-3.8668148518,43.4065475464],"type":"Point"}
}