{
  "type": "Feature",
  "properties": {
    "addr:full":"Calle de Marques De Hinojares (del), 24 Mejorada Campo Madrid 28840",
    "addr:housenumber":"24",
    "addr:postcode":"28840",
    "addr:street":"Calle De Marques De Hinojares Del",
    "iso:country":"ES",
    "sg:address":"Calle de Marques De Hinojares (del), 24",
    "sg:city":"Mejorada Campo",
    "sg:orig_category":"Alimentaci\u00d3n General (al Por Menor)",
    "sg:phone":"+34 916 68 09 17",
    "sg:postcode":"28840",
    "sg:province":"Madrid",
    "wof:name":"Del Campo Villalvilla Angeles",
    "wof:placetype":"venue"
},
  "geometry": {"coordinates":[-3.4907979965,40.3981132507],"type":"Point"}
}