{
  "type": "Feature",
  "properties": {
    "addr:full":"Calle de Velluters, Dels, 4 Valencia Valencia 46014",
    "addr:housenumber":"4",
    "addr:postcode":"46014",
    "addr:street":"Calle De Velluters Dels",
    "iso:country":"ES",
    "sg:address":"Calle de Velluters, Dels, 4",
    "sg:city":"Valencia",
    "sg:orig_category":"Estudios, Instalaci\u00d3n De Climatizaci\u00d3n",
    "sg:phone":"+34 963 13 20 58",
    "sg:postcode":"46014",
    "sg:province":"Valencia",
    "wof:name":"Rochina Mantenimiento S.a.",
    "wof:placetype":"venue"
},
  "geometry": {"coordinates":[-0.4180090129,39.4682350159],"type":"Point"}
}