{
  "type": "Feature",
  "properties": {
    "iso:country":"ES",
    "sg:address":"Calle de Norte Del, 16",
    "sg:city":"Langreo",
    "sg:orig_category":"Zapatos (al Por Menor)",
    "sg:phone":"+34 985 67 42 87",
    "sg:postcode":"33930",
    "sg:province":"Asturias",
    "wof:name":"Fernandez Rodriguez Carmen",
    "wof:placetype":"venue"
},
  "geometry": {"coordinates":[-5.7070870399,43.3195877075],"type":"Point"}
}