{
  "type": "Feature",
  "properties": {
    "iso:country":"ES",
    "sg:address":"Ctra Santos, 14",
    "sg:city":"Zafra",
    "sg:orig_category":"Ense\u00d1anza, Formaci\u00d3n Profesional: Aprendizaje",
    "sg:phone":"+34 924 55 08 91",
    "sg:postcode":"06300",
    "sg:province":"Badajoz",
    "wof:name":"Consorcio Provincial De Prevencion Y Extincion De Incendios",
    "wof:placetype":"venue"
},
  "geometry": {"coordinates":[-6.410217762,38.4250602722],"type":"Point"}
}