{
  "type": "Feature",
  "properties": {
    "iso:country":"ES",
    "sg:address":"Rua Lopez Guntin (pintor), 9",
    "sg:city":"Lugo",
    "sg:orig_category":"Equipo De Refrigeraci\u00d3n Industrial",
    "sg:phone":"+34 982 21 81 27",
    "sg:postcode":"27004",
    "sg:province":"Lugo",
    "wof:name":"Lopez Casal Antonio",
    "wof:placetype":"venue"
},
  "geometry": {"coordinates":[-7.5678911209,43.0175895691],"type":"Point"}
}