{
  "type": "Feature",
  "properties": {
    "addr:full":"Plaz Mercado (del), 6 Logro\u00f1o La Rioja 26001",
    "addr:postcode":"26001",
    "addr:street":"Rioja",
    "iso:country":"ES",
    "sg:address":"Plaz Mercado (del), 6",
    "sg:city":"Logro\u00f1o",
    "sg:orig_category":"Comerciantes Al Por Mayor De Vinos, Licores Y Alcoholes",
    "sg:phone":"+34 941 23 12 85",
    "sg:postcode":"26001",
    "sg:province":"La Rioja",
    "wof:name":"Duarte Llorente Trifon",
    "wof:placetype":"venue"
},
  "geometry": {"coordinates":[-2.4464390278,42.466796875],"type":"Point"}
}