{
  "type": "Feature",
  "properties": {
    "iso:country":"ES",
    "sg:address":"Calle de Alf Martinez Vaque, 17",
    "sg:city":"Genova",
    "sg:orig_category":"Asilos De Ancianos. Centros Privados",
    "sg:phone":"+34 971 40 16 86",
    "sg:postcode":"07015",
    "sg:province":"Islas Baleares",
    "wof:name":"Asociacion Tercera Edad De Pensionistas Y Jubilados De Genova",
    "wof:placetype":"venue"
},
  "geometry": {"coordinates":[2.599634409,39.5611495972],"type":"Point"}
}