{
  "type": "Feature",
  "properties": {
    "iso:country":"ES",
    "sg:address":"Carrer de Sant Josep, 26",
    "sg:city":"Mataro",
    "sg:orig_category":"Complementos De Vestir (al Por Menor)",
    "sg:phone":"+34 937 41 00 55",
    "sg:postcode":"08302",
    "sg:province":"Barcelona",
    "wof:name":"La Moda Festa I Nuvies S.l.",
    "wof:placetype":"venue"
},
  "geometry": {"coordinates":[2.4434280396,41.5397453308],"type":"Point"}
}