{
  "type": "Feature",
  "properties": {
    "addr:full":"Foios, 8 Vinalesa Valencia 46114",
    "addr:housenumber":"8",
    "addr:postcode":"46114",
    "addr:street":"Foios",
    "iso:country":"ES",
    "sg:address":"Foios, 8",
    "sg:city":"Vinalesa",
    "sg:orig_category":"Congelados: Productos Alimentarios (fabricaci\u00d3n, Al Por Mayor)",
    "sg:phone":"+34 961 49 46 83",
    "sg:postcode":"46114",
    "sg:province":"Valencia",
    "wof:name":"Frinapa S.l.",
    "wof:placetype":"venue"
},
  "geometry": {"coordinates":[-0.3671450019,39.5390129089],"type":"Point"}
}