{
  "type": "Feature",
  "properties": {
    "addr:full":"Carrer de Sebastia Juan Arbo, 25 Amposta Tarragona 43870",
    "addr:housenumber":"25",
    "addr:postcode":"43870",
    "addr:street":"Carrer De Sebastia Juan Arbo",
    "iso:country":"ES",
    "sg:address":"Carrer de Sebastia Juan Arbo, 25",
    "sg:city":"Amposta",
    "sg:orig_category":"Inform\u00c1tica, Ofim\u00c1tica (estudios, Asesor\u00cda, Ingenier\u00cda, Formaci\u00d3n)",
    "sg:phone":"+34 977 70 51 31",
    "sg:postcode":"43870",
    "sg:province":"Tarragona",
    "wof:name":"Microdelta Sistemes Informatis S.c.",
    "wof:placetype":"venue"
},
  "geometry": {"coordinates":[0.5838099718,40.7057571411],"type":"Point"}
}