{
  "type": "Feature",
  "properties": {
    "iso:country":"ES",
    "sg:address":"Urb Ladera, 24",
    "sg:city":"Churra",
    "sg:orig_category":"Abogados",
    "sg:phone":"+34 968 85 62 35",
    "sg:postcode":"30110",
    "sg:province":"Murcia",
    "wof:name":"Aviles Perea Carmen",
    "wof:placetype":"venue"
},
  "geometry": {"coordinates":[-1.1356306076,38.0216903687],"type":"Point"}
}