{
  "type": "Feature",
  "properties": {
    "addr:full":"Calle de Victor Chavarri, 21 Portugalete Vizcaya 48920",
    "addr:housenumber":"21",
    "addr:postcode":"48920",
    "addr:street":"Calle De Victor Chavarri",
    "iso:country":"ES",
    "sg:address":"Calle de Victor Chavarri, 21",
    "sg:city":"Portugalete",
    "sg:orig_category":"\u00d3ptica: Instrumentos (fabricaci\u00d3n)",
    "sg:phone":"+34 944 95 57 53",
    "sg:postcode":"48920",
    "sg:province":"Vizcaya",
    "wof:name":"Espejo Etxeberria Cristina",
    "wof:placetype":"venue"
},
  "geometry": {"coordinates":[-3.0176930428,43.3202819824],"type":"Point"}
}