{
  "type": "Feature",
  "properties": {
    "addr:full":"Calle de Felipe Berge, 2 Alacant Alicante 03001",
    "addr:housenumber":"2",
    "addr:postcode":"03001",
    "addr:street":"Calle De Felipe Berge",
    "iso:country":"ES",
    "sg:address":"Calle de Felipe Berge, 2",
    "sg:city":"Alacant",
    "sg:orig_category":"Enfermeras: Consultas, Atenci\u00d3n A Domicilio",
    "sg:phone":"+34 965 21 49 42",
    "sg:postcode":"03001",
    "sg:province":"Alicante",
    "wof:name":"Rico Guirao Francisco",
    "wof:placetype":"venue"
},
  "geometry": {"coordinates":[-0.4869860113,38.3452835083],"type":"Point"}
}