{
  "type": "Feature",
  "properties": {
    "iso:country":"ES",
    "sg:address":"Rua Via Norte, 56",
    "sg:city":"Vigo",
    "sg:orig_category":"Fisioterapia",
    "sg:phone":"+34 986 47 31 42",
    "sg:postcode":"36204",
    "sg:province":"Pontevedra",
    "wof:name":"Clinica De Fisioterapia San Simon C.b.",
    "wof:placetype":"venue"
},
  "geometry": {"coordinates":[-8.7077436447,42.2344207764],"type":"Point"}
}