{
  "type": "Feature",
  "properties": {
    "addr:full":"Calle de Flores (de Las), 12 Aranjuez Madrid 28300",
    "addr:housenumber":"12",
    "addr:postcode":"28300",
    "addr:street":"Calle De Flores De Las",
    "iso:country":"ES",
    "sg:address":"Calle de Flores (de Las), 12",
    "sg:city":"Aranjuez",
    "sg:orig_category":"Herboristas (al Por Menor)",
    "sg:phone":"+34 918 92 63 01",
    "sg:postcode":"28300",
    "sg:province":"Madrid",
    "sg:website":"www.modusvivendi.es.caseta",
    "wof:name":"Modus Vivendi C.b.",
    "wof:placetype":"venue"
},
  "geometry": {"coordinates":[-3.5918529034,40.0315818787],"type":"Point"}
}