{
  "type": "Feature",
  "properties": {
    "addr:full":"Calle de Matachel, 8 Madrid Madrid 28021",
    "addr:housenumber":"8",
    "addr:postcode":"madrid;28021",
    "addr:street":"Calle De Matachel",
    "iso:country":"ES",
    "sg:address":"Calle de Matachel, 8",
    "sg:city":"Madrid",
    "sg:orig_category":"Publicidad (soportes Y Gesti\u00d3n)",
    "sg:phone":"+34 917 98 68 76",
    "sg:postcode":"28021",
    "sg:province":"Madrid",
    "wof:name":"Perez Martinez Gaspar",
    "wof:placetype":"venue"
},
  "geometry": {"coordinates":[-3.6817190647,40.3526077271],"type":"Point"}
}