{
  "type": "Feature",
  "properties": {
    "addr:full":"Pol Ind Cazorla, 10 Cazorla Ja\u00e9n 23470",
    "addr:housenumber":"10",
    "addr:postcode":"23470",
    "iso:country":"ES",
    "sg:address":"Pol Ind Cazorla, 10",
    "sg:city":"Cazorla",
    "sg:orig_category":"Mec\u00c1nico Del Autom\u00d3vil",
    "sg:phone":"+34 953 71 02 08",
    "sg:postcode":"23470",
    "sg:province":"Ja\u00e9n",
    "wof:name":"Guirado Garcia Juan Antonio",
    "wof:placetype":"venue"
},
  "geometry": {"coordinates":[-2.8776638508,37.8798332214],"type":"Point"}
}