{
  "type": "Feature",
  "properties": {
    "addr:full":"Carrer de Misser Rufet, 4 Vilafranca Penedes Barcelona 08720",
    "addr:housenumber":"4",
    "addr:postcode":"08720",
    "addr:street":"Carrer De Misser Rufet;Penedes Barcelona",
    "iso:country":"ES",
    "sg:address":"Carrer de Misser Rufet, 4",
    "sg:city":"Vilafranca Penedes",
    "sg:orig_category":"Ingenier\u00cda, Centros De Estudios (diversos)",
    "sg:phone":"+34 938 17 26 81",
    "sg:postcode":"08720",
    "sg:province":"Barcelona",
    "wof:name":"Accessibilitat Catalunya S.l:",
    "wof:placetype":"venue"
},
  "geometry": {"coordinates":[1.7027176619,41.3457298279],"type":"Point"}
}