{
  "type": "Feature",
  "properties": {
    "addr:full":"Calle de Fernando Iii El Santo, 6 Alcala De Los Gazules C\u00e1diz 11180",
    "addr:housenumber":"6",
    "addr:postcode":"11180",
    "addr:street":"Calle De Fernando Iii El Santo",
    "iso:country":"ES",
    "sg:address":"Calle de Fernando Iii El Santo, 6",
    "sg:city":"Alcala De Los Gazules",
    "sg:classifiers":[
        {
            "category":"Autos & Motor Vehicles",
            "subcategory":"Automobile Sales",
            "type":"Retail Goods"
        }
    ],
    "sg:phone":"+34 956 42 04 13",
    "sg:postcode":"11180",
    "sg:province":"C\u00e1diz",
    "wof:name":"Autoescuela 164 S.l.",
    "wof:placetype":"venue"
},
  "geometry": {"coordinates":[-5.7212004662,36.4605407715],"type":"Point"}
}