{
  "type": "Feature",
  "properties": {
    "iso:country":"ES",
    "sg:address":"Calle de Rey Don Jaime, 1",
    "sg:city":"Alginet",
    "sg:orig_category":"Venta, Instalaci\u00d3n De Calefacci\u00d3n",
    "sg:phone":"+34 961 75 25 64",
    "sg:postcode":"46230",
    "sg:province":"Valencia",
    "wof:name":"Salvador Escutia Carrasco S.l.",
    "wof:placetype":"venue"
},
  "geometry": {"coordinates":[-0.470043987,39.2614898682],"type":"Point"}
}