{
  "type": "Feature",
  "properties": {
    "addr:full":"Rond Est, 87 Barbera Valles Barcelona 08210",
    "addr:housenumber":"87",
    "addr:postcode":"08210",
    "addr:street":"Rond Est",
    "iso:country":"ES",
    "sg:address":"Rond Est, 87",
    "sg:city":"Barbera Valles",
    "sg:orig_category":"Panader\u00cdas, Panader\u00cdas",
    "sg:phone":"+34 937 19 03 54",
    "sg:postcode":"08210",
    "sg:province":"Barcelona",
    "wof:name":"Panificadora De Gallecs S.l.",
    "wof:placetype":"venue"
},
  "geometry": {"coordinates":[2.1271760464,41.5150566101],"type":"Point"}
}