{
  "type": "Feature",
  "properties": {
    "iso:country":"ES",
    "sg:address":"Calle de San Roque (de), 52",
    "sg:city":"Navalcarnero",
    "sg:orig_category":"Institutos De Belleza",
    "sg:phone":"+34 918 11 30 87",
    "sg:postcode":"28600",
    "sg:province":"Madrid",
    "wof:name":"Sampere Torres Susana",
    "wof:placetype":"venue"
},
  "geometry": {"coordinates":[-4.0128631592,40.2853813171],"type":"Point"}
}