{
  "type": "Feature",
  "properties": {
    "iso:country":"ES",
    "sg:address":"Calle de Jupiter, 5",
    "sg:city":"Ciudad Real",
    "sg:orig_category":"Psic\u00d3logos",
    "sg:phone":"+34 926 25 70 71",
    "sg:postcode":"13005",
    "sg:province":"Ciudad Real",
    "wof:name":"Gomez Cabezas Jose Ramon",
    "wof:placetype":"venue"
},
  "geometry": {"coordinates":[-3.9297389984,39.0009651184],"type":"Point"}
}