{
  "type": "Feature",
  "properties": {
    "iso:country":"ES",
    "sg:address":"Carr Peralta, De, 6",
    "sg:city":"Eivissa",
    "sg:orig_category":"Arquitectos",
    "sg:phone":"+34 971 31 77 75",
    "sg:postcode":"07800",
    "sg:province":"Islas Baleares",
    "wof:name":"Capitel Arquitectura Tecnica S.l.",
    "wof:placetype":"venue"
},
  "geometry": {"coordinates":[1.4106999636,38.9077644348],"type":"Point"}
}