{
  "type": "Feature",
  "properties": {
    "addr:full":"Calle de Cardenal Cisneros, 76 Coru\u00d1a A Coru\u00f1a 15007",
    "addr:housenumber":"76",
    "addr:postcode":"15007",
    "addr:street":"Calle De Cardenal Cisneros;Corun\u0303A",
    "iso:country":"ES",
    "sg:address":"Calle de Cardenal Cisneros, 76",
    "sg:city":"Coru\u00d1a",
    "sg:orig_category":"Molduras, Junquillos, Listones Y Molduras Perforadas",
    "sg:phone":"+34 981 24 62 46",
    "sg:postcode":"15007",
    "sg:province":"A Coru\u00f1a",
    "wof:name":"Villar Rodriguez Manuel",
    "wof:placetype":"venue"
},
  "geometry": {"coordinates":[-8.7951183319,42.9959411621],"type":"Point"}
}