{
  "type": "Feature",
  "properties": {
    "addr:full":"Carrer de Ribes, 63 Barcelona Barcelona 08013",
    "addr:housenumber":"63",
    "addr:postcode":"08013",
    "addr:street":"Carrer De Ribes",
    "iso:country":"ES",
    "sg:address":"Carrer de Ribes, 63",
    "sg:city":"Barcelona",
    "sg:orig_category":"Centros De Coordinaci\u00d3n",
    "sg:phone":"+34 932 65 82 93",
    "sg:postcode":"08013",
    "sg:province":"Barcelona",
    "wof:name":"Pardal March Cristina",
    "wof:placetype":"venue"
},
  "geometry": {"coordinates":[2.1836938858,41.3993988037],"type":"Point"}
}