{
  "type": "Feature",
  "properties": {
    "iso:country":"ES",
    "sg:address":"Coronel Obispo Cadena Y Eleta, 8",
    "sg:city":"Sta M. Real Nieva",
    "sg:orig_category":"Iglesia Cat\u00d3lica",
    "sg:phone":"+34 921 59 41 35",
    "sg:postcode":"40440",
    "sg:province":"Segovia",
    "wof:name":"Obispado Segovia",
    "wof:placetype":"venue"
},
  "geometry": {"coordinates":[-4.4072508812,41.0704154968],"type":"Point"}
}