{
  "type": "Feature",
  "properties": {
    "iso:country":"ES",
    "sg:address":"Cra. Girona, Km. 0021,8",
    "sg:city":"S. Celoni",
    "sg:orig_category":"Materiales De Aislamiento T\u00c9rmico Y Ac\u00dastico",
    "sg:phone":"+34 938 67 24 53",
    "sg:postcode":"08470",
    "sg:province":"Barcelona",
    "wof:name":"Aislamientos Rocal S.l.",
    "wof:placetype":"venue"
},
  "geometry": {"coordinates":[2.4931044579,41.6855506897],"type":"Point"}
}