{
  "type": "Feature",
  "properties": {
    "addr:full":"Carrer de Doctor Sastre, 12 Benifallet Tarragona 43512",
    "addr:housenumber":"12",
    "addr:postcode":"43512",
    "addr:street":"Carrer De Doctor Sastre",
    "iso:country":"ES",
    "sg:address":"Carrer de Doctor Sastre, 12",
    "sg:city":"Benifallet",
    "sg:orig_category":"Panader\u00cdas, Panader\u00cdas",
    "sg:phone":"+34 977 46 20 32",
    "sg:postcode":"43512",
    "sg:province":"Tarragona",
    "wof:name":"Pastisseria Casa La Campana S.l.",
    "wof:placetype":"venue"
},
  "geometry": {"coordinates":[0.5172259808,40.9743423462],"type":"Point"}
}