{
  "type": "Feature",
  "properties": {
    "iso:country":"ES",
    "sg:address":"Ptge Torrent De L'estadell, 47",
    "sg:city":"Barcelona",
    "sg:orig_category":"Cerrajer\u00cda, Ferrallista",
    "sg:phone":"+34 932 74 52 82",
    "sg:postcode":"08030",
    "sg:province":"Barcelona",
    "sg:website":"www.inoxfer.com",
    "wof:name":"Teyco Comercial S. L.",
    "wof:placetype":"venue"
},
  "geometry": {"coordinates":[2.1991620064,41.4341812134],"type":"Point"}
}