{
  "type": "Feature",
  "properties": {
    "iso:country":"ES",
    "sg:address":"Maliciosa, 14",
    "sg:city":"Tres Cantos",
    "sg:orig_category":"Guarder\u00cdas",
    "sg:phone":"+34 918 03 11 27",
    "sg:postcode":"28760",
    "sg:province":"Madrid",
    "wof:name":"Garcia Ojosnegros Maria Del Sagrario",
    "wof:placetype":"venue"
},
  "geometry": {"coordinates":[-3.7158522606,40.6118164062],"type":"Point"}
}