{
  "type": "Feature",
  "properties": {
    "addr:full":"Carrer de Ceravalls, 6 Hospitalet Llobregat Barcelona 08905",
    "addr:housenumber":"6",
    "addr:postcode":"08905",
    "addr:street":"Carrer De Ceravalls",
    "iso:country":"ES",
    "sg:address":"Carrer de Ceravalls, 6",
    "sg:city":"Hospitalet Llobregat",
    "sg:orig_category":"Trajes Y Adornos De Boda (confecci\u00d3n, Al Por Menor)",
    "sg:phone":"+34 934 49 43 81",
    "sg:postcode":"08905",
    "sg:province":"Barcelona",
    "wof:name":"Arjona Ramirez Ana Maria",
    "wof:placetype":"venue"
},
  "geometry": {"coordinates":[2.1087002754,41.3686752319],"type":"Point"}
}