{
  "type": "Feature",
  "properties": {
    "iso:country":"ES",
    "sg:address":"Ctra Arbucies, 125",
    "sg:city":"Breda",
    "sg:orig_category":"Alimentaci\u00d3n General (al Por Menor)",
    "sg:phone":"+34 972 87 02 64",
    "sg:postcode":"17400",
    "sg:province":"Girona",
    "wof:name":"Auladell Martori Francisca",
    "wof:placetype":"venue"
},
  "geometry": {"coordinates":[2.5585401058,41.7448234558],"type":"Point"}
}