{
  "type": "Feature",
  "properties": {
    "addr:full":"Calle de Rector Vives, 47 Genova Islas Baleares 07015",
    "addr:housenumber":"47",
    "addr:postcode":"07015",
    "addr:street":"Calle De Rector Vives",
    "iso:country":"ES",
    "sg:address":"Calle de Rector Vives, 47",
    "sg:city":"Genova",
    "sg:orig_category":"Arquitectos",
    "sg:phone":"+34 971 70 03 42",
    "sg:postcode":"07015",
    "sg:province":"Islas Baleares",
    "wof:name":"Spahni Generelli Aldo",
    "wof:placetype":"venue"
},
  "geometry": {"coordinates":[2.596821785,39.5632514954],"type":"Point"}
}