{
  "type": "Feature",
  "properties": {
    "iso:country":"ES",
    "sg:address":"Calle de Aguas Del Hospital, 1",
    "sg:city":"Motril",
    "sg:orig_category":"Inmobiliaria (agencias)",
    "sg:phone":"+34 958 60 04 58",
    "sg:postcode":"18600",
    "sg:province":"Granada",
    "wof:name":"Gnatek Alonso Cesareo",
    "wof:placetype":"venue"
},
  "geometry": {"coordinates":[-3.5218269825,36.7432479858],"type":"Point"}
}