{
  "type": "Feature",
  "properties": {
    "iso:country":"ES",
    "sg:address":"Carr Portella, 2",
    "sg:city":"Figueres",
    "sg:orig_category":"Zapatos (al Por Menor)",
    "sg:phone":"+34 972 51 34 56",
    "sg:postcode":"17600",
    "sg:province":"Girona",
    "wof:name":"Falgarona Sabaters Sl Unipersonal",
    "wof:placetype":"venue"
},
  "geometry": {"coordinates":[2.9607379436,42.2669410706],"type":"Point"}
}