{
  "type": "Feature",
  "properties": {
    "addr:full":"Calle de Segovia, 6 Espirdo Segovia 40191",
    "addr:housenumber":"6",
    "addr:postcode":"40191",
    "addr:street":"Calle De Segovia;Segovia",
    "iso:country":"ES",
    "sg:address":"Calle de Segovia, 6",
    "sg:city":"Espirdo",
    "sg:orig_category":"Asociaciones, Organismos Culturales Y Socioeducativos",
    "sg:phone":"+34 921 44 90 59",
    "sg:postcode":"40191",
    "sg:province":"Segovia",
    "wof:name":"Asociacion Para El Desarrollo Rural De Segovia Sur",
    "wof:placetype":"venue"
},
  "geometry": {"coordinates":[-4.0753235817,40.9974479675],"type":"Point"}
}