{
  "type": "Feature",
  "properties": {
    "addr:full":"Carrer de Tucuman, 6 Barcelona Barcelona 08030",
    "addr:housenumber":"6",
    "addr:postcode":"08030",
    "addr:street":"Carrer De Tucuman",
    "iso:country":"ES",
    "sg:address":"Carrer de Tucuman, 6",
    "sg:city":"Barcelona",
    "sg:orig_category":"Fabricaci\u00d3n De Moldes Y Modelos",
    "sg:phone":"+34 933 11 74 22",
    "sg:postcode":"08030",
    "sg:province":"Barcelona",
    "wof:name":"Lopez Diaz Manuel",
    "wof:placetype":"venue"
},
  "geometry": {"coordinates":[2.2001280785,41.4452896118],"type":"Point"}
}