{
  "type": "Feature",
  "properties": {
    "iso:country":"ES",
    "sg:address":"Calle de Tarragona, 7",
    "sg:city":"Castellon",
    "sg:orig_category":"Transportes Por Carretera: Lotes Completos, Mercanc\u00cdas Diversas",
    "sg:phone":"+34 964 22 89 23",
    "sg:postcode":"12003",
    "sg:province":"Castell\u00f3n",
    "wof:name":"Dialsur S.a.",
    "wof:placetype":"venue"
},
  "geometry": {"coordinates":[-0.0315140001,39.9867324829],"type":"Point"}
}