{
  "type": "Feature",
  "properties": {
    "addr:full":"Ctra Almenara, 68 Puente Botero Murcia 30813",
    "addr:housenumber":"68",
    "addr:postcode":"30813",
    "addr:street":"Ctra Almenara",
    "iso:country":"ES",
    "sg:address":"Ctra Almenara, 68",
    "sg:city":"Puente Botero",
    "sg:orig_category":"Quincaller\u00cda (al Por Menor)",
    "sg:phone":"+34 968 46 91 12",
    "sg:postcode":"30813",
    "sg:province":"Murcia",
    "wof:name":"Sanchez Sanchez Enrique",
    "wof:placetype":"venue"
},
  "geometry": {"coordinates":[-1.7215889692,37.491394043],"type":"Point"}
}