{
  "type": "Feature",
  "properties": {
    "iso:country":"ES",
    "sg:address":"Calle de Trigo (del), 33",
    "sg:city":"Leganes",
    "sg:orig_category":"Tapicer\u00cdas",
    "sg:phone":"+34 916 94 64 26",
    "sg:postcode":"28914",
    "sg:province":"Madrid",
    "wof:name":"Montes Guerrero Antonio",
    "wof:placetype":"venue"
},
  "geometry": {"coordinates":[-3.7840929031,40.327331543],"type":"Point"}
}