{
  "type": "Feature",
  "properties": {
    "addr:full":"Ctra Rocafort, 3 Godella Valencia 46110",
    "addr:housenumber":"3",
    "addr:postcode":"46110",
    "addr:street":"Ctra Rocafort",
    "iso:country":"ES",
    "sg:address":"Ctra Rocafort, 3",
    "sg:city":"Godella",
    "sg:orig_category":"Venta, Montaje De Neum\u00c1ticos",
    "sg:phone":"+34 963 64 04 04",
    "sg:postcode":"46110",
    "sg:province":"Valencia",
    "wof:name":"Clemente Bosch Oscar",
    "wof:placetype":"venue"
},
  "geometry": {"coordinates":[-0.4148899913,39.5239028931],"type":"Point"}
}