{
  "type": "Feature",
  "properties": {
    "addr:full":"Pla\u00c7 Espanya, 1 Lleida Lleida 25002",
    "addr:postcode":"1;25002",
    "iso:country":"ES",
    "sg:address":"Pla\u00c7 Espanya, 1",
    "sg:city":"Lleida",
    "sg:orig_category":"Promotores Constructores",
    "sg:phone":"+34 973 27 02 43",
    "sg:postcode":"25002",
    "sg:province":"Lleida",
    "wof:name":"Construcciones Industriales Y Edificaciones Leridanas",
    "wof:placetype":"venue"
},
  "geometry": {"coordinates":[0.627129972,41.6145210266],"type":"Point"}
}