{
  "type": "Feature",
  "properties": {
    "addr:full":"C/ Jose M Casta\u00d1o Martinez, 7 Elche Alicante 03202",
    "addr:housenumber":"7",
    "addr:postcode":"03202",
    "addr:street":"C / Jose M Castan\u0303O Martinez",
    "iso:country":"ES",
    "sg:address":"C/ Jose M Casta\u00d1o Martinez, 7",
    "sg:city":"Elche",
    "sg:orig_category":"Institutos De Belleza",
    "sg:phone":"+34 966 61 28 33",
    "sg:postcode":"03202",
    "sg:province":"Alicante",
    "wof:name":"Macia Roman Maria Vicenta",
    "wof:placetype":"venue"
},
  "geometry": {"coordinates":[-0.6863722205,38.271812439],"type":"Point"}
}