{
  "type": "Feature",
  "properties": {
    "iso:country":"ES",
    "sg:address":"Av Guadalhorce (zona Portuaria), S/n",
    "sg:city":"Sevilla",
    "sg:orig_category":"Agencias De Aduana",
    "sg:phone":"+34 954 62 41 55",
    "sg:postcode":"41012",
    "sg:province":"Sevilla",
    "wof:name":"Tejado Franco Francisco",
    "wof:placetype":"venue"
},
  "geometry": {"coordinates":[-5.9904341698,37.3659133911],"type":"Point"}
}