{
  "type": "Feature",
  "properties": {
    "addr:full":"Calle de Granero, 3 San Lorenzo Murcia 30001",
    "addr:housenumber":"3",
    "addr:postcode":"30001",
    "addr:street":"Calle De Granero",
    "iso:country":"ES",
    "sg:address":"Calle de Granero, 3",
    "sg:city":"San Lorenzo",
    "sg:orig_category":"Asociaciones, Instituciones De Consumidores Y Usuarios",
    "sg:phone":"+34 968 20 32 46",
    "sg:postcode":"30001",
    "sg:province":"Murcia",
    "wof:name":"Federacion Murciana De Asociaciones De Amas De Casa Consumidores Y Usuarios Thader",
    "wof:placetype":"venue"
},
  "geometry": {"coordinates":[-1.1276270151,37.9866104126],"type":"Point"}
}