{
  "type": "Feature",
  "properties": {
    "iso:country":"ES",
    "sg:address":"Calle de Oropesa, 14",
    "sg:city":"Puente Arzobispo",
    "sg:orig_category":"Mec\u00c1nico Del Autom\u00d3vil",
    "sg:phone":"+34 925 43 61 81",
    "sg:postcode":"45570",
    "sg:province":"Toledo",
    "wof:name":"Fernandez Fernandez Ana Maria",
    "wof:placetype":"venue"
},
  "geometry": {"coordinates":[-5.1719689369,39.8045387268],"type":"Point"}
}