{
  "type": "Feature",
  "properties": {
    "addr:full":"Avda Ronda (de), 110 Elda Alicante 03600",
    "addr:housenumber":"110",
    "addr:postcode":"03600",
    "addr:street":"Avda Ronda De",
    "iso:country":"ES",
    "sg:address":"Avda Ronda (de), 110",
    "sg:city":"Elda",
    "sg:orig_category":"Promotores Constructores",
    "sg:phone":"+34 965 38 08 75",
    "sg:postcode":"03600",
    "sg:province":"Alicante",
    "wof:name":"Protizor",
    "wof:placetype":"venue"
},
  "geometry": {"coordinates":[-0.8011289835,38.477809906],"type":"Point"}
}