{
  "type": "Feature",
  "properties": {
    "iso:country":"ES",
    "sg:address":"Calle de Peso, 6",
    "sg:city":"Oviedo",
    "sg:orig_category":"Asesor\u00cda Fiscal Y Jur\u00cddica",
    "sg:phone":"+34 985 21 82 90",
    "sg:postcode":"33009",
    "sg:province":"Asturias",
    "wof:name":"Arias Suarez Jose Antonio",
    "wof:placetype":"venue"
},
  "geometry": {"coordinates":[-5.8452715874,43.3608283997],"type":"Point"}
}