{
  "type": "Feature",
  "properties": {
    "addr:full":"Calle de Valle Inclan, 103 Madrid Madrid 28044",
    "addr:housenumber":"103",
    "addr:postcode":"28044",
    "addr:street":"Calle De Valle Inclan",
    "iso:country":"ES",
    "sg:address":"Calle de Valle Inclan, 103",
    "sg:city":"Madrid",
    "sg:orig_category":"Sociedades, Compa\u00d1\u00cdas Aseguradoras",
    "sg:phone":"+34 915 09 50 13",
    "sg:postcode":"28044",
    "sg:province":"Madrid",
    "wof:name":"L. Castejon Correduria De Seguros S.l.",
    "wof:placetype":"venue"
},
  "geometry": {"coordinates":[-3.7750239372,40.3753662109],"type":"Point"}
}