{
  "type": "Feature",
  "properties": {
    "addr:full":"Plaz Constitucion (navarredonda) (de La), 1 Navarredonda Madrid 28739",
    "addr:housenumber":"1",
    "addr:postcode":"28739",
    "addr:street":"Navarredonda",
    "iso:country":"ES",
    "sg:address":"Plaz Constitucion (navarredonda) (de La), 1",
    "sg:city":"Navarredonda",
    "sg:orig_category":"Administraciones Regionales, Departamentales Y Locales",
    "sg:phone":"+34 918 69 51 28",
    "sg:postcode":"28739",
    "sg:province":"Madrid",
    "wof:name":"Ayuntamiento De Navarredonda Y San Mames",
    "wof:placetype":"venue"
},
  "geometry": {"coordinates":[-3.7168691158,40.965473175],"type":"Point"}
}