{
  "type": "Feature",
  "properties": {
    "addr:full":"Calle de Carrizo, 15 Dalias Almer\u00eda 04750",
    "addr:housenumber":"15",
    "addr:postcode":"04750",
    "addr:street":"Calle De Carrizo;Almeri\u0301A",
    "iso:country":"ES",
    "sg:address":"Calle de Carrizo, 15",
    "sg:city":"Dalias",
    "sg:orig_category":"T\u00c9cnicos Veterinarios",
    "sg:phone":"+34 950 49 44 04",
    "sg:postcode":"04750",
    "sg:province":"Almer\u00eda",
    "wof:name":"Garnica Aberasturi Yolanda",
    "wof:placetype":"venue"
},
  "geometry": {"coordinates":[-2.874366045,36.8235092163],"type":"Point"}
}