{
  "type": "Feature",
  "properties": {
    "iso:country":"ES",
    "sg:address":"Calle de Calzada De Castro, 24",
    "sg:city":"Almeria",
    "sg:orig_category":"Importaci\u00d3n, Exportaci\u00d3n Y Comercios De Productos Textiles",
    "sg:phone":"+34 950 25 53 84",
    "sg:postcode":"04006",
    "sg:province":"Almer\u00eda",
    "wof:name":"Mendoza Jimenez Concepcion",
    "wof:placetype":"venue"
},
  "geometry": {"coordinates":[-2.4538350105,36.8378410339],"type":"Point"}
}