{
  "type": "Feature",
  "properties": {
    "addr:full":"Calle de Tintas, 4 Madrid Madrid 28025",
    "addr:housenumber":"4",
    "addr:postcode":"28025",
    "addr:street":"Calle De Tintas",
    "iso:country":"ES",
    "sg:address":"Calle de Tintas, 4",
    "sg:city":"Madrid",
    "sg:orig_category":"Ense\u00d1anza Variada",
    "sg:phone":"+34 914 62 41 11",
    "sg:postcode":"28025",
    "sg:province":"Madrid",
    "wof:name":"Segura Ossorio Santiago",
    "wof:placetype":"venue"
},
  "geometry": {"coordinates":[-3.740582943,40.3890190125],"type":"Point"}
}