{
  "type": "Feature",
  "properties": {
    "iso:country":"ES",
    "sg:address":"Nafarroa Etorbidea, 31",
    "sg:city":"Beasain",
    "sg:orig_category":"Carnicer\u00cdas, Carnicer\u00cdas",
    "sg:phone":"+34 943 08 52 09",
    "sg:postcode":"20200",
    "sg:province":"Guip\u00f9zcoa",
    "wof:name":"Juan Ignacio Mugica Lasa",
    "wof:placetype":"venue"
},
  "geometry": {"coordinates":[-2.2032821178,43.0467796326],"type":"Point"}
}