{
  "type": "Feature",
  "properties": {
    "iso:country":"ES",
    "sg:address":"Carrer de Gravina, 8",
    "sg:city":"Barcelona",
    "sg:orig_category":"Molduras, Junquillos, Listones Y Molduras Perforadas",
    "sg:phone":"+34 934 12 13 45",
    "sg:postcode":"08001",
    "sg:province":"Barcelona",
    "wof:name":"Guillen Pfitzmann Nicolas",
    "wof:placetype":"venue"
},
  "geometry": {"coordinates":[2.165858984,41.3851776123],"type":"Point"}
}