{
  "type": "Feature",
  "properties": {
    "addr:full":"Calle de Rafael Gonzalez Abreu, 1 Sevilla Sevilla 41001",
    "addr:housenumber":"1",
    "addr:postcode":"41001",
    "addr:street":"Calle De Rafael;Abreu",
    "iso:country":"ES",
    "sg:address":"Calle de Rafael Gonzalez Abreu, 1",
    "sg:city":"Sevilla",
    "sg:orig_category":"Abogados",
    "sg:phone":"+34 954 21 57 46",
    "sg:postcode":"41001",
    "sg:province":"Sevilla",
    "wof:name":"Velazquez Garcia Ramon",
    "wof:placetype":"venue"
},
  "geometry": {"coordinates":[-6.0002388954,37.3911056519],"type":"Point"}
}