{
  "type": "Feature",
  "properties": {
    "addr:full":"Carrer de Rossello, 53 Mataro Barcelona 08303",
    "addr:housenumber":"53",
    "addr:postcode":"08303",
    "addr:street":"Carrer De Rossello",
    "iso:country":"ES",
    "sg:address":"Carrer de Rossello, 53",
    "sg:city":"Mataro",
    "sg:orig_category":"Bazares, Art\u00cdculos De Limpieza Y De Cocina (al Por Menor)",
    "sg:phone":"+34 937 57 90 97",
    "sg:postcode":"08303",
    "sg:province":"Barcelona",
    "wof:name":"Wang  Yi",
    "wof:placetype":"venue"
},
  "geometry": {"coordinates":[2.4252734184,41.5385093689],"type":"Point"}
}