{
  "type": "Feature",
  "properties": {
    "iso:country":"ES",
    "sg:address":"Casanova, 15",
    "sg:city":"Casanova",
    "sg:orig_category":"Material Y Herramientas Agr\u00cdcolas",
    "sg:phone":"+34 982 33 03 52",
    "sg:postcode":"27240",
    "sg:province":"Lugo",
    "wof:name":"Folgueira Portela Jose",
    "wof:placetype":"venue"
},
  "geometry": {"coordinates":[-7.294479847,43.2133827209],"type":"Point"}
}