{
  "type": "Feature",
  "properties": {
    "iso:country":"ES",
    "sg:address":"Pg Jacint Verdaguer, 21",
    "sg:city":"Lloret Mar",
    "sg:orig_category":"Inmobiliaria (agencias)",
    "sg:phone":"+34 972 34 92 82",
    "sg:postcode":"17310",
    "sg:province":"Girona",
    "wof:name":"Alsina Pares Antonio",
    "wof:placetype":"venue"
},
  "geometry": {"coordinates":[2.7804713249,41.6826515198],"type":"Point"}
}