{
  "type": "Feature",
  "properties": {
    "iso:country":"ES",
    "sg:address":"Calle de Rosario, 80",
    "sg:city":"Albacete",
    "sg:orig_category":"Ingeniero",
    "sg:phone":"+34 967 22 43 16",
    "sg:postcode":"02003",
    "sg:province":"Albacete",
    "wof:name":"Garcia Rodriguez Juan Antonio",
    "wof:placetype":"venue"
},
  "geometry": {"coordinates":[-1.859801054,38.9890937805],"type":"Point"}
}