{
  "type": "Feature",
  "properties": {
    "addr:full":"Calle de Samuel Ros, 6 Valencia Valencia 46023",
    "addr:housenumber":"6",
    "addr:postcode":"46023",
    "addr:street":"Calle De Samuel Ros",
    "iso:country":"ES",
    "sg:address":"Calle de Samuel Ros, 6",
    "sg:city":"Valencia",
    "sg:orig_category":"Caf\u00c9s, Bares, Cervecer\u00cdas",
    "sg:phone":"+34 963 30 18 04",
    "sg:postcode":"46023",
    "sg:province":"Valencia",
    "wof:name":"Hernandez Romojaro Maria De Los Reyes",
    "wof:placetype":"venue"
},
  "geometry": {"coordinates":[-0.3458310068,39.4629898071],"type":"Point"}
}