{
  "type": "Feature",
  "properties": {
    "addr:full":"Calle de Diego Franco, 76 Hinojos Huelva 21740",
    "addr:housenumber":"76",
    "addr:postcode":"21740",
    "addr:street":"Calle De Diego Franco",
    "iso:country":"ES",
    "sg:address":"Calle de Diego Franco, 76",
    "sg:city":"Hinojos",
    "sg:orig_category":"Electricidad: Instaladores",
    "sg:phone":"+34 959 45 95 08",
    "sg:postcode":"21740",
    "sg:province":"Huelva",
    "wof:name":"Hidalgo Medina Antonio Luis",
    "wof:placetype":"venue"
},
  "geometry": {"coordinates":[-6.3864426613,37.146774292],"type":"Point"}
}