{
  "type": "Feature",
  "properties": {
    "addr:full":"Calle de Celanova, 2 Zaragoza Zaragoza 50017",
    "addr:housenumber":"2",
    "addr:postcode":"50017",
    "addr:street":"Calle De Celanova",
    "iso:country":"ES",
    "sg:address":"Calle de Celanova, 2",
    "sg:city":"Zaragoza",
    "sg:orig_category":"Venta Al Preg\u00d3n",
    "sg:phone":"+34 976 33 96 28",
    "sg:postcode":"50017",
    "sg:province":"Zaragoza",
    "wof:name":"Rubio Bello Manuel",
    "wof:placetype":"venue"
},
  "geometry": {"coordinates":[-0.9110352993,41.6540222168],"type":"Point"}
}