{
  "type": "Feature",
  "properties": {
    "addr:full":"Avda Monreal, 13 Huesca Huesca 22003",
    "addr:housenumber":"13",
    "addr:postcode":"22003",
    "addr:street":"Avda Monreal",
    "iso:country":"ES",
    "sg:address":"Avda Monreal, 13",
    "sg:city":"Huesca",
    "sg:orig_category":"Seguridad Social",
    "sg:phone":"+34 974 22 72 23",
    "sg:postcode":"22003",
    "sg:province":"Huesca",
    "wof:name":"Fraternidad-muprespa Mutua De Accidentes De Trabajo Y Enfermedades",
    "wof:placetype":"venue"
},
  "geometry": {"coordinates":[-0.4125739932,42.1422462463],"type":"Point"}
}