{
  "type": "Feature",
  "properties": {
    "addr:full":"Carr Josep Verdera, 1 Eivissa Islas Baleares 07800",
    "addr:housenumber":"1",
    "addr:postcode":"07800",
    "addr:street":"Carr Josep Verdera",
    "iso:country":"ES",
    "sg:address":"Carr Josep Verdera, 1",
    "sg:city":"Eivissa",
    "sg:orig_category":"Fotograf\u00cda Art\u00cdstica Y Retratos",
    "sg:phone":"+34 971 19 05 35",
    "sg:postcode":"07800",
    "sg:province":"Islas Baleares",
    "wof:name":"Ortega Martin Domiciano",
    "wof:placetype":"venue"
},
  "geometry": {"coordinates":[1.437443018,38.9093971252],"type":"Point"}
}