{
  "type": "Feature",
  "properties": {
    "iso:country":"ES",
    "sg:address":"Carrer de Almeria, 1",
    "sg:city":"Hospitalet Llobregat",
    "sg:orig_category":"Centros De Educaci\u00d3n Especial",
    "sg:phone":"+34 934 40 49 03",
    "sg:postcode":"08905",
    "sg:province":"Barcelona",
    "wof:name":"Ajuntament De L'hospitalet De Llobregat",
    "wof:placetype":"venue"
},
  "geometry": {"coordinates":[2.1156201363,41.3686790466],"type":"Point"}
}