{
  "type": "Feature",
  "properties": {
    "iso:country":"ES",
    "sg:address":"Errekatxu Kalea, 3",
    "sg:city":"Eibar",
    "sg:orig_category":"Ropa Y Art\u00cdculos Pre",
    "sg:phone":"+34 943 20 69 93",
    "sg:postcode":"20600",
    "sg:province":"Guip\u00f9zcoa",
    "wof:name":"Bartu S.l.",
    "wof:placetype":"venue"
},
  "geometry": {"coordinates":[-2.4690220356,43.1841163635],"type":"Point"}
}