{
  "type": "Feature",
  "properties": {
    "iso:country":"ES",
    "sg:address":"Calle de Iscar Peyra, 34",
    "sg:city":"Salamanca",
    "sg:orig_category":"Ropa Para Se\u00d1oras Y Caballeros (al Por Menor)",
    "sg:phone":"+34 923 27 06 21",
    "sg:postcode":"37002",
    "sg:province":"Salamanca",
    "wof:name":"Iscar Peyra 34 S.l.",
    "wof:placetype":"venue"
},
  "geometry": {"coordinates":[-5.6653752327,40.9667167664],"type":"Point"}
}