{
  "type": "Feature",
  "properties": {
    "addr:full":"Carrer de Mossen Jacint Verdaguer, 52 Santa Coloma De Gramenet Barcelona 08923",
    "addr:housenumber":"52",
    "addr:postcode":"08923",
    "addr:street":"Carrer De Mossen Jacint Verdaguer",
    "iso:country":"ES",
    "sg:address":"Carrer de Mossen Jacint Verdaguer, 52",
    "sg:city":"Santa Coloma De Gramenet",
    "sg:orig_category":"Mec\u00c1nica Y Herramientas De Precisi\u00d3n",
    "sg:phone":"+34 933 85 68 30",
    "sg:postcode":"08923",
    "sg:province":"Barcelona",
    "wof:name":"Sociedad Espa\u00d1ola De Microfiltracion",
    "wof:placetype":"venue"
},
  "geometry": {"coordinates":[2.2124950886,41.4473953247],"type":"Point"}
}