{
  "type": "Feature",
  "properties": {
    "addr:full":"Calle de Polibea, 8 Madrid Madrid 28027",
    "addr:housenumber":"8",
    "addr:postcode":"madrid;28027",
    "addr:street":"Calle De Polibea",
    "iso:country":"ES",
    "sg:address":"Calle de Polibea, 8",
    "sg:city":"Madrid",
    "sg:orig_category":"Molduras, Junquillos, Listones Y Molduras Perforadas",
    "sg:phone":"+34 914 07 89 81",
    "sg:postcode":"28027",
    "sg:province":"Madrid",
    "wof:name":"Otero Mateos Baltasar",
    "wof:placetype":"venue"
},
  "geometry": {"coordinates":[-3.6438760757,40.4409179688],"type":"Point"}
}