{
  "type": "Feature",
  "properties": {
    "addr:full":"Calle de Fernando El Santo, 15 Madrid Madrid 28010",
    "addr:housenumber":"15",
    "addr:postcode":"madrid;28010",
    "addr:street":"Calle De Fernando El Santo",
    "iso:country":"ES",
    "sg:address":"Calle de Fernando El Santo, 15",
    "sg:city":"Madrid",
    "sg:orig_category":"Asesor\u00cda Sobre Comunicaci\u00d3n De Empresas",
    "sg:phone":"+34 915 61 39 57",
    "sg:postcode":"28010",
    "sg:province":"Madrid",
    "sg:website":"www.auxadi.com",
    "wof:name":"Auxadi Contable S. A.",
    "wof:placetype":"venue"
},
  "geometry": {"coordinates":[-3.6926488876,40.4282722473],"type":"Point"}
}