{
  "type": "Feature",
  "properties": {
    "iso:country":"ES",
    "sg:address":"Avda Gipuzkoa, 48",
    "sg:city":"Ermua",
    "sg:orig_category":"Plomeros",
    "sg:phone":"+34 943 17 01 09",
    "sg:postcode":"48260",
    "sg:province":"Vizcaya",
    "wof:name":"Dios Gomez Bernardo De",
    "wof:placetype":"venue"
},
  "geometry": {"coordinates":[-2.4986290932,43.1806602478],"type":"Point"}
}