{
  "type": "Feature",
  "properties": {
    "addr:full":"Carrer de N Amargos, 15 Barcelona Barcelona 08002",
    "addr:housenumber":"15",
    "addr:postcode":"08002",
    "addr:street":"Carrer De N Amargos",
    "iso:country":"ES",
    "sg:address":"Carrer de N Amargos, 15",
    "sg:city":"Barcelona",
    "sg:orig_category":"Ropa Para Se\u00d1oras (al Por Menor)",
    "sg:phone":"+34 934 12 20 45",
    "sg:postcode":"08002",
    "sg:province":"Barcelona",
    "wof:name":"Almazul S.l.",
    "wof:placetype":"venue"
},
  "geometry": {"coordinates":[2.1740558147,41.3865242004],"type":"Point"}
}