{
  "type": "Feature",
  "properties": {
    "iso:country":"ES",
    "sg:address":"Ctra Soria, Km. 0265,5",
    "sg:city":"Aranda Duero",
    "sg:orig_category":"Transportes De Material De Construcci\u00d3n",
    "sg:phone":"+34 947 54 63 64",
    "sg:postcode":"09400",
    "sg:province":"Burgos",
    "wof:name":"Transportes Enrique Heredero S.a.",
    "wof:placetype":"venue"
},
  "geometry": {"coordinates":[-3.6889948845,41.6699256897],"type":"Point"}
}