{
  "type": "Feature",
  "properties": {
    "addr:full":"Calle de Cartagena, 17 Alcazares Murcia 30710",
    "addr:housenumber":"17",
    "addr:postcode":"30710",
    "addr:street":"Calle De Cartagena",
    "iso:country":"ES",
    "sg:address":"Calle de Cartagena, 17",
    "sg:city":"Alcazares",
    "sg:orig_category":"Hielo Artificial (fabricaci\u00d3n, Distribuci\u00d3n)",
    "sg:phone":"+34 968 57 58 51",
    "sg:postcode":"30710",
    "sg:province":"Murcia",
    "wof:name":"Montymer's S.l.",
    "wof:placetype":"venue"
},
  "geometry": {"coordinates":[-0.8500537276,37.7383384705],"type":"Point"}
}