{
  "type": "Feature",
  "properties": {
    "addr:full":"Carrer de Neopatria, 22 Barcelona Barcelona 08030",
    "addr:housenumber":"22",
    "addr:postcode":"08030",
    "addr:street":"Carrer De Neopatria",
    "iso:country":"ES",
    "sg:address":"Carrer de Neopatria, 22",
    "sg:city":"Barcelona",
    "sg:orig_category":"Agencias Y Agentes Comerciales, Representantes",
    "sg:phone":"+34 933 45 71 33",
    "sg:postcode":"08030",
    "sg:province":"Barcelona",
    "wof:name":"Moreno Villalon Ernestina",
    "wof:placetype":"venue"
},
  "geometry": {"coordinates":[2.1886529922,41.4321784973],"type":"Point"}
}