{
  "type": "Feature",
  "properties": {
    "iso:country":"ES",
    "sg:address":"Calle de Doctor Jimenez Encina, 16",
    "sg:city":"Torremolinos",
    "sg:orig_category":"Lavado, Limpieza De Veh\u00cdculos",
    "sg:phone":"+34 952 05 05 97",
    "sg:postcode":"29620",
    "sg:province":"M\u00e1laga",
    "wof:name":"Valverde Plaza Jose",
    "wof:placetype":"venue"
},
  "geometry": {"coordinates":[-4.504570961,36.6212158203],"type":"Point"}
}