{
  "type": "Feature",
  "properties": {
    "addr:full":"Cno. Campillo, S/n Campo Cuellar Segovia 40242",
    "addr:housenumber":"s / n",
    "addr:postcode":"40242",
    "addr:street":"Cno. Campillo",
    "iso:country":"ES",
    "sg:address":"Cno. Campillo, S/n",
    "sg:city":"Campo Cuellar",
    "sg:orig_category":"Agricultores, Agricultores",
    "sg:phone":"+34 921 12 30 53",
    "sg:postcode":"40242",
    "sg:province":"Segovia",
    "wof:name":"Ganadera El Cigue\u00f1al",
    "wof:placetype":"venue"
},
  "geometry": {"coordinates":[-4.368268013,41.3112411499],"type":"Point"}
}