{
  "type": "Feature",
  "properties": {
    "addr:full":"Av Pau (de La), 53 Mollerussa Lleida 25230",
    "addr:housenumber":"53",
    "addr:postcode":"25230",
    "addr:street":"Av Pau De La",
    "iso:country":"ES",
    "sg:address":"Av Pau (de La), 53",
    "sg:city":"Mollerussa",
    "sg:orig_category":"Cajas De Ahorro",
    "sg:phone":"+34 973 71 13 23",
    "sg:postcode":"25230",
    "sg:province":"Lleida",
    "wof:name":"Caixa D'estalvis I Pensions De Barcelona",
    "wof:placetype":"venue"
},
  "geometry": {"coordinates":[0.8980860114,41.6270637512],"type":"Point"}
}