{
  "type": "Feature",
  "properties": {
    "addr:full":"Avda Hilario Goyenechea, 13 Salamanca Salamanca 37008",
    "addr:housenumber":"13",
    "addr:postcode":"37008",
    "addr:street":"Avda Hilario Goyenechea",
    "iso:country":"ES",
    "sg:address":"Avda Hilario Goyenechea, 13",
    "sg:city":"Salamanca",
    "sg:orig_category":"Centros De Educaci\u00d3n Especial",
    "sg:phone":"+34 923 21 58 72",
    "sg:postcode":"37008",
    "sg:province":"Salamanca",
    "wof:name":"Colegio Publico Juan Del Enzina",
    "wof:placetype":"venue"
},
  "geometry": {"coordinates":[-5.6625051498,40.9491577148],"type":"Point"}
}