{
  "type": "Feature",
  "properties": {
    "addr:full":"Pol Ind Naviluz, 42 Huelva Huelva 21007",
    "addr:housenumber":"42",
    "addr:postcode":"21007",
    "addr:street":"Naviluz",
    "iso:country":"ES",
    "sg:address":"Pol Ind Naviluz, 42",
    "sg:city":"Huelva",
    "sg:orig_category":"Hormig\u00d3n (m\u00c1quinas E Instalaci\u00d3n)",
    "sg:phone":"+34 959 27 15 15",
    "sg:postcode":"21007",
    "sg:province":"Huelva",
    "wof:name":"Zarrias Aguilera Jose",
    "wof:placetype":"venue"
},
  "geometry": {"coordinates":[-6.8994493484,37.2885742188],"type":"Point"}
}