{
  "type": "Feature",
  "properties": {
    "addr:full":"Carrer de Vall, 25 Canet Mar Barcelona 08360",
    "addr:housenumber":"25",
    "addr:postcode":"08360",
    "addr:street":"Carrer De Vall",
    "iso:country":"ES",
    "sg:address":"Carrer de Vall, 25",
    "sg:city":"Canet Mar",
    "sg:orig_category":"Orquestas De Variedades",
    "sg:phone":"+34 937 94 20 70",
    "sg:postcode":"08360",
    "sg:province":"Barcelona",
    "sg:website":"www.orquestagirasol.com",
    "wof:name":"Orquestra Girasol S.l.",
    "wof:placetype":"venue"
},
  "geometry": {"coordinates":[2.5842061043,41.5882148743],"type":"Point"}
}