{
  "type": "Feature",
  "properties": {
    "addr:full":"Calle de Pez, 18 Madrid Madrid 28004",
    "addr:housenumber":"18",
    "addr:postcode":"madrid;28004",
    "addr:street":"Calle De Pez",
    "iso:country":"ES",
    "sg:address":"Calle de Pez, 18",
    "sg:city":"Madrid",
    "sg:orig_category":"Caf\u00c9s, Bares, Cervecer\u00cdas",
    "sg:phone":"+34 915 22 03 31",
    "sg:postcode":"28004",
    "sg:province":"Madrid",
    "wof:name":"Martinez Canepa Alvaro",
    "wof:placetype":"venue"
},
  "geometry": {"coordinates":[-3.7053458691,40.4237556458],"type":"Point"}
}