{
  "type": "Feature",
  "properties": {
    "addr:full":"Av Sant Ferran, 15 Palma Islas Baleares 07011",
    "addr:housenumber":"15",
    "addr:postcode":"07011",
    "addr:street":"Av Sant Ferran",
    "iso:country":"ES",
    "sg:address":"Av Sant Ferran, 15",
    "sg:city":"Palma",
    "sg:orig_category":"Agentes Generales De Seguros",
    "sg:phone":"+34 971 78 04 92",
    "sg:postcode":"07011",
    "sg:province":"Islas Baleares",
    "wof:name":"Cortes Ferrer S.c.",
    "wof:placetype":"venue"
},
  "geometry": {"coordinates":[2.6379261017,39.5799980164],"type":"Point"}
}