{
  "type": "Feature",
  "properties": {
    "iso:country":"ES",
    "sg:address":"Carrer de Josep Rodoreda, 44",
    "sg:city":"Esplugues Llobregat",
    "sg:orig_category":"Galvanizaci\u00d3n, Esta\u00d1ado, Emplomado",
    "sg:phone":"+34 933 71 07 97",
    "sg:postcode":"08950",
    "sg:province":"Barcelona",
    "wof:name":"Ruiz Bosom Juan Carlos",
    "wof:placetype":"venue"
},
  "geometry": {"coordinates":[2.0811100006,41.3722343445],"type":"Point"}
}