{
  "type": "Feature",
  "properties": {
    "iso:country":"ES",
    "sg:address":"Calle de Manuel Lasala, 40",
    "sg:city":"Zaragoza",
    "sg:orig_category":"M\u00c9dicos: Fisioterapia Y Rehabilitaci\u00d3n",
    "sg:phone":"+34 976 35 11 75",
    "sg:postcode":"50006",
    "sg:province":"Zaragoza",
    "wof:name":"Cardiel Gomez Estanislao",
    "wof:placetype":"venue"
},
  "geometry": {"coordinates":[-0.8964310288,41.6377906799],"type":"Point"}
}