{
  "type": "Feature",
  "properties": {
    "iso:country":"ES",
    "sg:address":"Cra. Empalme Bisbal, S/n",
    "sg:city":"Bisbal Del Penedes",
    "sg:orig_category":"Alimentaci\u00d3n General (al Por Mayor)",
    "sg:phone":"+34 977 68 81 86",
    "sg:postcode":"43717",
    "sg:province":"Tarragona",
    "wof:name":"Piensos Del Tietar S.l.",
    "wof:placetype":"venue"
},
  "geometry": {"coordinates":[1.4905450344,41.2773857117],"type":"Point"}
}