{
  "type": "Feature",
  "properties": {
    "addr:full":"Calle de Julian Ca\u00d1edo, 5 Oviedo Asturias 33008",
    "addr:housenumber":"5",
    "addr:postcode":"33008",
    "addr:street":"Calle De Julian Can\u0303Edo",
    "iso:country":"ES",
    "sg:address":"Calle de Julian Ca\u00d1edo, 5",
    "sg:city":"Oviedo",
    "sg:orig_category":"Agencias Y Agentes Comerciales, Representantes",
    "sg:phone":"+34 985 22 58 03",
    "sg:postcode":"33008",
    "sg:province":"Asturias",
    "wof:name":"Montes Fernandez Berta",
    "wof:placetype":"venue"
},
  "geometry": {"coordinates":[-5.8381319046,43.3548240662],"type":"Point"}
}