{
  "type": "Feature",
  "properties": {
    "addr:full":"Ctra. D'arta, S/n Platges Muro Islas Baleares 07440",
    "addr:housenumber":"s",
    "addr:postcode":"07440",
    "addr:street":"Ctra. D'Arta;/ N Platges",
    "iso:country":"ES",
    "sg:address":"Ctra. D'arta, S/n",
    "sg:city":"Platges Muro",
    "sg:orig_category":"Molduras, Junquillos, Listones Y Molduras Perforadas",
    "sg:phone":"+34 971 18 43 09",
    "sg:postcode":"07440",
    "sg:province":"Islas Baleares",
    "wof:name":"Perello Sastre Sebastian",
    "wof:placetype":"venue"
},
  "geometry": {"coordinates":[3.1140220165,39.8102416992],"type":"Point"}
}