{
  "type": "Feature",
  "properties": {
    "addr:full":"Carrer de Madrazo, 7 Sabadell Barcelona 08206",
    "addr:housenumber":"7",
    "addr:postcode":"08206",
    "addr:street":"Carrer De Madrazo",
    "iso:country":"ES",
    "sg:address":"Carrer de Madrazo, 7",
    "sg:city":"Sabadell",
    "sg:orig_category":"Confecci\u00d3n, Alquiler Y Venta De Maniqu\u00cdes De Escaparate",
    "sg:phone":"+34 937 45 16 66",
    "sg:postcode":"08206",
    "sg:province":"Barcelona",
    "wof:name":"Euro Ar 2002",
    "wof:placetype":"venue"
},
  "geometry": {"coordinates":[2.0882520676,41.5478744507],"type":"Point"}
}