{
  "type": "Feature",
  "properties": {
    "addr:full":"Calle de Maestro Zubeldia, 23 Portugalete Vizcaya 48920",
    "addr:housenumber":"23",
    "addr:postcode":"48920",
    "addr:street":"Calle De Maestro Zubeldia",
    "iso:country":"ES",
    "sg:address":"Calle de Maestro Zubeldia, 23",
    "sg:city":"Portugalete",
    "sg:orig_category":"Empresas De Carpinter\u00cda De Madera",
    "sg:phone":"+34 944 06 43 06",
    "sg:postcode":"48920",
    "sg:province":"Vizcaya",
    "wof:name":"Carpinteria Jose Agraso",
    "wof:placetype":"venue"
},
  "geometry": {"coordinates":[-3.0217769146,43.3158912659],"type":"Point"}
}