{
  "type": "Feature",
  "properties": {
    "iso:country":"ES",
    "sg:address":"Pase San Gregorio, 24",
    "sg:city":"Puertollano",
    "sg:orig_category":"Asociaciones, Organismos Culturales Y Socioeducativos",
    "sg:phone":"+34 926 42 00 44",
    "sg:postcode":"13500",
    "sg:province":"Ciudad Real",
    "wof:name":"Circulo De Recreo",
    "wof:placetype":"venue"
},
  "geometry": {"coordinates":[-4.1046910286,38.6888198853],"type":"Point"}
}