{
  "type": "Feature",
  "properties": {
    "addr:full":"Calle de Rosello, 10 Alacant Alicante 03010",
    "addr:housenumber":"10",
    "addr:postcode":"03010",
    "addr:street":"Calle De Rosello",
    "iso:country":"ES",
    "sg:address":"Calle de Rosello, 10",
    "sg:city":"Alacant",
    "sg:orig_category":"Laboratorios Y Trabajos De Fotograf\u00cda, V\u00cddeo Y Cine",
    "sg:phone":"+34 965 14 08 22",
    "sg:postcode":"03010",
    "sg:province":"Alicante",
    "wof:name":"Colormatic S. L.",
    "wof:placetype":"venue"
},
  "geometry": {"coordinates":[-0.4898009896,38.3601722717],"type":"Point"}
}