{
  "type": "Feature",
  "properties": {
    "iso:country":"ES",
    "sg:address":"Calle de Arquitecto Eduardo Esteve, 12",
    "sg:city":"Malaga",
    "sg:orig_category":"Proveedores De Acceso A Internet",
    "sg:phone":"+34 952 29 97 66",
    "sg:postcode":"29017",
    "sg:province":"M\u00e1laga",
    "sg:website":"www.centrored.com",
    "wof:name":"Centro Cibernetico De Servicios De Tecnologias De La Informacion S.l.",
    "wof:placetype":"venue"
},
  "geometry": {"coordinates":[-4.3631587029,36.7201385498],"type":"Point"}
}