{
  "type": "Feature",
  "properties": {
    "addr:full":"Bo. Peinador, 7 Peinador Pontevedra 36417",
    "addr:housenumber":"7",
    "addr:postcode":"36417",
    "addr:street":"Bo. Peinador",
    "iso:country":"ES",
    "sg:address":"Bo. Peinador, 7",
    "sg:city":"Peinador",
    "sg:orig_category":"Quincaller\u00cda (al Por Menor)",
    "sg:phone":"+34 986 48 75 63",
    "sg:postcode":"36417",
    "sg:province":"Pontevedra",
    "wof:name":"Lorenzo Comercial S. L.",
    "wof:placetype":"venue"
},
  "geometry": {"coordinates":[-8.6343994141,42.2206916809],"type":"Point"}
}