{
  "type": "Feature",
  "properties": {
    "iso:country":"ES",
    "sg:address":"Avda Nueve De Octubre, 78",
    "sg:city":"Puerto",
    "sg:orig_category":"Asilos De Ancianos. Centros Privados",
    "sg:phone":"+34 962 69 80 47",
    "sg:postcode":"46520",
    "sg:province":"Valencia",
    "wof:name":"Projecte Iaio S.a.",
    "wof:placetype":"venue"
},
  "geometry": {"coordinates":[-0.2244389951,39.6608085632],"type":"Point"}
}