{
  "type": "Feature",
  "properties": {
    "iso:country":"ES",
    "sg:address":"Calle de Campos De Montiel, S/n",
    "sg:city":"Tomelloso",
    "sg:orig_category":"Construcciones E Instalaciones Agr\u00cdcolas",
    "sg:phone":"+34 926 50 61 70",
    "sg:postcode":"13700",
    "sg:province":"Ciudad Real",
    "wof:name":"Inmegat Tomelloso S.l.",
    "wof:placetype":"venue"
},
  "geometry": {"coordinates":[-3.0340611935,39.1594276428],"type":"Point"}
}