{
  "type": "Feature",
  "properties": {
    "addr:full":"Avda Zurriola De, 44 Donostia-san Sebastian Guip\u00f9zcoa 20002",
    "addr:housenumber":"44",
    "addr:postcode":"20002",
    "addr:street":"Avda Zurriola De",
    "iso:country":"ES",
    "sg:address":"Avda Zurriola De, 44",
    "sg:city":"Donostia-san Sebastian",
    "sg:orig_category":"Inform\u00c1tica, Ofim\u00c1tica (estudios, Asesor\u00cda, Ingenier\u00cda, Formaci\u00d3n)",
    "sg:phone":"+34 943 29 80 50",
    "sg:postcode":"20002",
    "sg:province":"Guip\u00f9zcoa",
    "wof:name":"Willfred Micro S.l",
    "wof:placetype":"venue"
},
  "geometry": {"coordinates":[-1.9726926088,43.3261489868],"type":"Point"}
}