{
  "type": "Feature",
  "properties": {
    "iso:country":"ES",
    "sg:address":"Cmno Nuevo Del Cementerio, 6",
    "sg:city":"Granada",
    "sg:orig_category":"Doctores En Medicina",
    "sg:phone":"+34 958 22 72 60",
    "sg:postcode":"18009",
    "sg:province":"Granada",
    "wof:name":"Giron Irueste Fernando",
    "wof:placetype":"venue"
},
  "geometry": {"coordinates":[-3.5872659683,37.1710548401],"type":"Point"}
}