{
  "type": "Feature",
  "properties": {
    "addr:full":"Calle de Catedratico Francisco Bece\u00d1a, 14 Oviedo Asturias 33006",
    "addr:housenumber":"14",
    "addr:postcode":"33006",
    "addr:street":"Calle De Catedratico Francisco Becen\u0303A",
    "iso:country":"ES",
    "sg:address":"Calle de Catedratico Francisco Bece\u00d1a, 14",
    "sg:city":"Oviedo",
    "sg:orig_category":"Alimentaci\u00d3n General (al Por Menor)",
    "sg:phone":"+34 985 27 56 65",
    "sg:postcode":"33006",
    "sg:province":"Asturias",
    "wof:name":"Cadenas Cadenas Maria Soledad",
    "wof:placetype":"venue"
},
  "geometry": {"coordinates":[-5.8693890572,43.3572616577],"type":"Point"}
}