{
  "type": "Feature",
  "properties": {
    "iso:country":"ES",
    "sg:address":"Av Montseny, 12",
    "sg:city":"Can Nadal",
    "sg:orig_category":"Agricultores, Agricultores",
    "sg:phone":"+34 937 64 00 28",
    "sg:postcode":"08490",
    "sg:province":"Barcelona",
    "wof:name":"Carns Quintana S. L.",
    "wof:placetype":"venue"
},
  "geometry": {"coordinates":[2.7045679092,41.705078125],"type":"Point"}
}