{
  "type": "Feature",
  "properties": {
    "addr:full":"Ctra Villaverde A Vallecas, Km. 0005,0 Madrid Madrid 28053",
    "addr:postcode":"28053",
    "addr:street":"Ctra Villaverde A Vallecas Km. 0005,0",
    "iso:country":"ES",
    "sg:address":"Ctra Villaverde A Vallecas, Km. 0005,0",
    "sg:city":"Madrid",
    "sg:orig_category":"Trabajos De Soldaduras",
    "sg:phone":"+34 917 85 07 65",
    "sg:postcode":"28053",
    "sg:province":"Madrid",
    "wof:name":"Praxair Espa\u00f1a S.l.",
    "wof:placetype":"venue"
},
  "geometry": {"coordinates":[-3.6456971169,40.3697128296],"type":"Point"}
}