{
  "type": "Feature",
  "properties": {
    "addr:full":"Carrer de Ripolles, 46 Barcelona Barcelona 08026",
    "addr:housenumber":"46",
    "addr:postcode":"08026",
    "addr:street":"Carrer De Ripolles",
    "iso:country":"ES",
    "sg:address":"Carrer de Ripolles, 46",
    "sg:city":"Barcelona",
    "sg:orig_category":"Energ\u00cda Solar Y Nuevas Energ\u00cdas (equipo, Estudios)",
    "sg:phone":"+34 934 46 32 32",
    "sg:postcode":"08026",
    "sg:province":"Barcelona",
    "wof:name":"Associacio De Serveis Energetics Basics",
    "wof:placetype":"venue"
},
  "geometry": {"coordinates":[2.1848723888,41.4137153625],"type":"Point"}
}