{
  "type": "Feature",
  "properties": {
    "addr:full":"Calle de Armengual De La Mota, 43 Malaga M\u00e1laga 29007",
    "addr:housenumber":"43",
    "addr:postcode":"29007",
    "addr:street":"Calle De Armengual De La Mota;Ma\u0301Laga",
    "iso:country":"ES",
    "sg:address":"Calle de Armengual De La Mota, 43",
    "sg:city":"Malaga",
    "sg:orig_category":"Farmacias",
    "sg:phone":"+34 952 30 84 46",
    "sg:postcode":"29007",
    "sg:province":"M\u00e1laga",
    "wof:name":"Perez-piaya Y Garcia Eloisa",
    "wof:placetype":"venue"
},
  "geometry": {"coordinates":[-4.4290299416,36.7214508057],"type":"Point"}
}