{
  "type": "Feature",
  "properties": {
    "iso:country":"ES",
    "sg:address":"Calle de Laurel, 1",
    "sg:city":"Corella",
    "sg:orig_category":"Cajas De Ahorro",
    "sg:phone":"+34 948 78 12 06",
    "sg:postcode":"31591",
    "sg:province":"Navarra",
    "wof:name":"Fundacion Caja Navarra",
    "wof:placetype":"venue"
},
  "geometry": {"coordinates":[-1.7873959541,42.1161842346],"type":"Point"}
}