{
  "type": "Feature",
  "properties": {
    "iso:country":"ES",
    "sg:address":"Calle de Juan De Austria, 1",
    "sg:city":"Molina Segura",
    "sg:orig_category":"Inmobiliaria (agencias)",
    "sg:phone":"+34 968 64 18 31",
    "sg:postcode":"30500",
    "sg:province":"Murcia",
    "wof:name":"Infagarro S.l.",
    "wof:placetype":"venue"
},
  "geometry": {"coordinates":[-1.2070790529,38.0529594421],"type":"Point"}
}