{
  "type": "Feature",
  "properties": {
    "addr:full":"Carrer de Sant Josep, 11 Mataro Barcelona 08302",
    "addr:housenumber":"11",
    "addr:postcode":"08302",
    "addr:street":"Carrer De Sant Josep",
    "iso:country":"ES",
    "sg:address":"Carrer de Sant Josep, 11",
    "sg:city":"Mataro",
    "sg:orig_category":"Centros Empresariales",
    "sg:phone":"+34 937 90 75 43",
    "sg:postcode":"08302",
    "sg:province":"Barcelona",
    "wof:name":"Villa Boix Elena",
    "wof:placetype":"venue"
},
  "geometry": {"coordinates":[2.4432489872,41.5394554138],"type":"Point"}
}