{
  "type": "Feature",
  "properties": {
    "addr:full":"Ctra Cadiz Carretera A, 2 Algeciras C\u00e1diz 11207",
    "addr:housenumber":"2;ca\u0301diz",
    "addr:postcode":"11207",
    "addr:street":"Ctra Cadiz Carretera A",
    "iso:country":"ES",
    "sg:address":"Ctra Cadiz Carretera A, 2",
    "sg:city":"Algeciras",
    "sg:orig_category":"Cajas Y Embalajes Met\u00c1licos",
    "sg:phone":"+34 956 57 29 18",
    "sg:postcode":"11207",
    "sg:province":"C\u00e1diz",
    "wof:name":"Metalgrafica Malague\u00d1a S.a.",
    "wof:placetype":"venue"
},
  "geometry": {"coordinates":[-5.4324541092,36.0734519958],"type":"Point"}
}