{
  "type": "Feature",
  "properties": {
    "addr:full":"Carr Constitucio, 21 Vila Joiosa Alicante 03570",
    "addr:housenumber":"21",
    "addr:postcode":"03570",
    "addr:street":"Carr Constitucio",
    "iso:country":"ES",
    "sg:address":"Carr Constitucio, 21",
    "sg:city":"Vila Joiosa",
    "sg:orig_category":"Muebles Y Accesorios Para Cocinas Y Cuartos De Ba\u00d1o (al Por Menor)",
    "sg:phone":"+34 966 85 01 06",
    "sg:postcode":"03570",
    "sg:province":"Alicante",
    "wof:name":"Esquerdo Adrover Domingo",
    "wof:placetype":"venue"
},
  "geometry": {"coordinates":[-0.2327190042,38.505821228],"type":"Point"}
}