{
  "type": "Feature",
  "properties": {
    "addr:full":"Carr Estacio, 3 Cassa Selva Girona 17244",
    "addr:housenumber":"3",
    "addr:postcode":"17244",
    "addr:street":"Carr Estacio",
    "iso:country":"ES",
    "sg:address":"Carr Estacio, 3",
    "sg:city":"Cassa Selva",
    "sg:orig_category":"Grafistas",
    "sg:phone":"+34 972 46 33 25",
    "sg:postcode":"17244",
    "sg:province":"Girona",
    "wof:name":"Madria Roure Angel",
    "wof:placetype":"venue"
},
  "geometry": {"coordinates":[2.8780760765,41.8896598816],"type":"Point"}
}