{
  "type": "Feature",
  "properties": {
    "iso:country":"ES",
    "sg:address":"Calle de Sierra De Grazalema, 7",
    "sg:city":"Malaga",
    "sg:orig_category":"Promotores Constructores",
    "sg:phone":"+34 952 21 07 95",
    "sg:postcode":"29016",
    "sg:province":"M\u00e1laga",
    "wof:name":"Ruiz Gomez Juan Antonio",
    "wof:placetype":"venue"
},
  "geometry": {"coordinates":[-4.4024610519,36.7266311646],"type":"Point"}
}