{
  "type": "Feature",
  "properties": {
    "iso:country":"ES",
    "sg:address":"Entda. Casa Tota, 1",
    "sg:city":"Valencia",
    "sg:orig_category":"Inmobiliaria (agencias)",
    "sg:phone":"+34 963 65 06 26",
    "sg:postcode":"46019",
    "sg:province":"Valencia",
    "wof:name":"Manuel Y Ascension S.l.",
    "wof:placetype":"venue"
},
  "geometry": {"coordinates":[-0.3702349961,39.5000534058],"type":"Point"}
}