{
  "type": "Feature",
  "properties": {
    "addr:full":"Calle de Mazarambroz, 45 Sonseca Toledo 45100",
    "addr:housenumber":"45",
    "addr:postcode":"45100",
    "addr:street":"Calle De Mazarambroz",
    "iso:country":"ES",
    "sg:address":"Calle de Mazarambroz, 45",
    "sg:city":"Sonseca",
    "sg:orig_category":"Ropa Para Se\u00d1oras (al Por Menor)",
    "sg:phone":"+34 925 39 55 32",
    "sg:postcode":"45100",
    "sg:province":"Toledo",
    "wof:name":"Mora Delgado Cristina",
    "wof:placetype":"venue"
},
  "geometry": {"coordinates":[-3.9774990082,39.6769714355],"type":"Point"}
}