{
  "type": "Feature",
  "properties": {
    "addr:full":"Rua Santiago, 17 Amoeiro Ourense 32170",
    "addr:housenumber":"17",
    "addr:postcode":"32170",
    "addr:street":"Rua Santiago",
    "iso:country":"ES",
    "sg:address":"Rua Santiago, 17",
    "sg:city":"Amoeiro",
    "sg:orig_category":"Molduras, Junquillos, Listones Y Molduras Perforadas",
    "sg:phone":"+34 988 28 10 45",
    "sg:postcode":"32170",
    "sg:province":"Ourense",
    "wof:name":"Vazquez Gonzalez Isaac",
    "wof:placetype":"venue"
},
  "geometry": {"coordinates":[-7.9505810738,42.4126548767],"type":"Point"}
}