{
  "type": "Feature",
  "properties": {
    "iso:country":"ES",
    "sg:address":"Avda Porta Do Sol, 85",
    "sg:city":"Ribeira",
    "sg:orig_category":"Bazares, Art\u00cdculos De Limpieza Y De Cocina (al Por Menor)",
    "sg:phone":"+34 986 31 01 62",
    "sg:postcode":"36955",
    "sg:province":"Pontevedra",
    "wof:name":"Rodriguez Santiago Jose Orlando",
    "wof:placetype":"venue"
},
  "geometry": {"coordinates":[-8.7202234268,42.2883415222],"type":"Point"}
}