{
  "type": "Feature",
  "properties": {
    "iso:country":"ES",
    "sg:address":"Muel Santa Catalina, S/n",
    "sg:city":"Palmas De Gran Canaria",
    "sg:orig_category":"Ropa Para Se\u00d1oras (al Por Menor)",
    "sg:phone":"+34 928 22 13 23",
    "sg:postcode":"35008",
    "sg:province":"Las Palmas",
    "sg:website":"www.trucco.es",
    "wof:name":"Princesa 73 S.l.",
    "wof:placetype":"venue"
},
  "geometry": {"coordinates":[-15.4279222488,28.1409034729],"type":"Point"}
}