{
  "type": "Feature",
  "properties": {
    "addr:full":"Ctra Mataro A Granollers, Km. 0017,4 Roca Valles Barcelona 08430",
    "addr:postcode":"08430",
    "addr:street":"Ctra Mataro;Granollers Km. 0017,4 Roca",
    "iso:country":"ES",
    "sg:address":"Ctra Mataro A Granollers, Km. 0017,4",
    "sg:city":"Roca Valles",
    "sg:orig_category":"Agentes, Concesionarios Y Sucursales De Veh\u00cdculos",
    "sg:phone":"+34 938 70 76 56",
    "sg:postcode":"08430",
    "sg:province":"Barcelona",
    "sg:website":"www.pradesgrup.com",
    "wof:name":"Prades Granollers S.l.",
    "wof:placetype":"venue"
},
  "geometry": {"coordinates":[2.3770260811,41.6025276184],"type":"Point"}
}