{
  "type": "Feature",
  "properties": {
    "iso:country":"ES",
    "sg:address":"Calle de Ciudad De Paterna, 9",
    "sg:city":"Sevilla",
    "sg:orig_category":"Mec\u00c1nico Del Autom\u00d3vil",
    "sg:phone":"+34 954 67 52 20",
    "sg:postcode":"41019",
    "sg:province":"Sevilla",
    "wof:name":"Valverde Fernandez Jose",
    "wof:placetype":"venue"
},
  "geometry": {"coordinates":[-5.929169178,37.4106063843],"type":"Point"}
}