{
  "type": "Feature",
  "properties": {
    "iso:country":"ES",
    "sg:address":"C/ Esperidion Porta Requesens, 132",
    "sg:city":"Elche",
    "sg:orig_category":"Arreglo, Reparaci\u00d3n, Piezas Sueltas De Televisi\u00d3n, V\u00cddeo, Hi",
    "sg:phone":"+34 965 46 59 99",
    "sg:postcode":"03206",
    "sg:province":"Alicante",
    "wof:name":"Martinez Salinas Antonio",
    "wof:placetype":"venue"
},
  "geometry": {"coordinates":[-0.710431993,38.2725791931],"type":"Point"}
}