{
  "type": "Feature",
  "properties": {
    "iso:country":"ES",
    "sg:address":"Ctra Alicante, 73",
    "sg:city":"Flota",
    "sg:orig_category":"Comercio, Reparaci\u00d3n De Motocicletas, Bicicletas Y Piezas Sueltas",
    "sg:phone":"+34 968 23 52 22",
    "sg:postcode":"30007",
    "sg:province":"Murcia",
    "wof:name":"Gonzalez Clares Laureano",
    "wof:placetype":"venue"
},
  "geometry": {"coordinates":[-1.1142389774,37.9970092773],"type":"Point"}
}