{
  "type": "Feature",
  "properties": {
    "iso:country":"ES",
    "sg:address":"Avda Gregorio Gea, 32",
    "sg:city":"Mislata",
    "sg:orig_category":"Asesor\u00cda Fiscal Y Jur\u00cddica",
    "sg:phone":"+34 963 59 39 92",
    "sg:postcode":"46920",
    "sg:province":"Valencia",
    "wof:name":"Multigestiones Y Asesoramiento Dominguez S.l.",
    "wof:placetype":"venue"
},
  "geometry": {"coordinates":[-0.4165819883,39.4737281799],"type":"Point"}
}