{
  "type": "Feature",
  "properties": {
    "iso:country":"ES",
    "sg:address":"O Vilar De Calo, 1",
    "sg:city":"Vilar De Calo",
    "sg:orig_category":"Chapister\u00cda",
    "sg:phone":"+34 981 52 34 65",
    "sg:postcode":"15895",
    "sg:province":"La Coru\u00f1a",
    "wof:name":"Meimije De La Iglesia Alicia",
    "wof:placetype":"venue"
},
  "geometry": {"coordinates":[-9.1391420364,43.0312004089],"type":"Point"}
}