{
  "type": "Feature",
  "properties": {
    "addr:full":"Carrer de L'institut Quimic Sarria, 43 Barcelona Barcelona 08017",
    "addr:housenumber":"43",
    "addr:postcode":"08017",
    "addr:street":"Carrer De L'Institut;Sarria",
    "iso:country":"ES",
    "sg:address":"Carrer de L'institut Quimic Sarria, 43",
    "sg:city":"Barcelona",
    "sg:orig_category":"M\u00c9dicos: Geriatr\u00cda, Gerontolog\u00cda (enfermedades De La Tercera Edad)",
    "sg:phone":"+34 932 11 18 02",
    "sg:postcode":"08017",
    "sg:province":"Barcelona",
    "wof:name":"Mas D'angli Residencial S.l.",
    "wof:placetype":"venue"
},
  "geometry": {"coordinates":[2.1221940517,41.4042129517],"type":"Point"}
}