{
  "type": "Feature",
  "properties": {
    "iso:country":"ES",
    "sg:address":"Av Negrete, 20",
    "sg:city":"Ciutadella Menorca",
    "sg:orig_category":"Fabricaci\u00d3n De Mobiliario De Oficina",
    "sg:phone":"+34 971 48 25 65",
    "sg:postcode":"07760",
    "sg:province":"Islas Baleares",
    "wof:name":"Muebles De Oficina Mantolan S. L.",
    "wof:placetype":"venue"
},
  "geometry": {"coordinates":[3.8382809162,39.9991912842],"type":"Point"}
}