{
  "type": "Feature",
  "properties": {
    "iso:country":"ES",
    "sg:address":"San Pedro(campo), 1",
    "sg:city":"San Pedro",
    "sg:orig_category":"Cr\u00cda De Animales",
    "sg:phone":"+34 981 68 91 80",
    "sg:postcode":"15687",
    "sg:province":"La Coru\u00f1a",
    "wof:name":"Ganaderia Docampo S.a.t.",
    "wof:placetype":"venue"
},
  "geometry": {"coordinates":[-8.2927331924,43.3803634644],"type":"Point"}
}