{
  "type": "Feature",
  "properties": {
    "addr:full":"Col Molinou, 1 Sant Marti D'armancies Girona 17530",
    "addr:housenumber":"1",
    "addr:postcode":"17530",
    "addr:street":"Molinou",
    "iso:country":"ES",
    "sg:address":"Col Molinou, 1",
    "sg:city":"Sant Marti D'armancies",
    "sg:orig_category":"Inmobiliaria (agencias)",
    "sg:phone":"+34 972 73 02 69",
    "sg:postcode":"17530",
    "sg:province":"Girona",
    "wof:name":"Desarrollos Inmobiliarios Grupo Gaudir Ii S.l.",
    "wof:placetype":"venue"
},
  "geometry": {"coordinates":[2.8187398911,41.9808616638],"type":"Point"}
}