{
  "type": "Feature",
  "properties": {
    "iso:country":"ES",
    "sg:address":"Calle de San Ignacio, 2",
    "sg:city":"Valladolid",
    "sg:orig_category":"Doctores En Medicina",
    "sg:phone":"+34 983 34 20 64",
    "sg:postcode":"47003",
    "sg:province":"Valladolid",
    "wof:name":"Velasco Dominguez Emilio",
    "wof:placetype":"venue"
},
  "geometry": {"coordinates":[-4.7288970947,41.6550178528],"type":"Point"}
}