{
  "type": "Feature",
  "properties": {
    "iso:country":"ES",
    "sg:address":"Via Aurelia, 36",
    "sg:city":"Sabadell",
    "sg:classifiers":[
        {
            "category":"Personal",
            "subcategory":"Barber",
            "type":"Services"
        }
    ],
    "sg:phone":"+34 937 24 22 00",
    "sg:postcode":"08206",
    "sg:province":"Barcelona",
    "sg:tags":[
        "caballeros",
        "de",
        "peluqueros"
    ],
    "wof:name":"Hernandez Del Toro Alonso",
    "wof:placetype":"venue"
},
  "geometry": {"coordinates":[2.0941739082,41.5576934814],"type":"Point"}
}