{
  "type": "Feature",
  "properties": {
    "addr:full":"Avda Republica Argentina, 46 Miranda Ebro Burgos 09200",
    "addr:housenumber":"46",
    "addr:postcode":"09200",
    "addr:street":"Avda Republica Argentina",
    "iso:country":"ES",
    "sg:address":"Avda Republica Argentina, 46",
    "sg:city":"Miranda Ebro",
    "sg:orig_category":"Tiendas De Grano, Frutas Y Legumbres Secas (al Por Menor)",
    "sg:phone":"+34 947 33 61 28",
    "sg:postcode":"09200",
    "sg:province":"Burgos",
    "wof:name":"Caprichos Miranda S.l.",
    "wof:placetype":"venue"
},
  "geometry": {"coordinates":[-2.9401049614,42.685760498],"type":"Point"}
}