{
  "type": "Feature",
  "properties": {
    "iso:country":"ES",
    "sg:address":"Calle de San Juan, 72",
    "sg:city":"Sanlucar De Barrameda",
    "sg:orig_category":"Ropa Y Accesorios",
    "sg:phone":"+34 956 38 43 94",
    "sg:postcode":"11540",
    "sg:province":"C\u00e1diz",
    "wof:name":"Rodriguez Perez Juan Ramon",
    "wof:placetype":"venue"
},
  "geometry": {"coordinates":[-6.3569049835,36.7773666382],"type":"Point"}
}