{
  "type": "Feature",
  "properties": {
    "addr:full":"Carrer de Saclosa, 32 Manresa Barcelona 08241",
    "addr:housenumber":"32",
    "addr:postcode":"08241",
    "addr:street":"Carrer De Saclosa",
    "iso:country":"ES",
    "sg:address":"Carrer de Saclosa, 32",
    "sg:city":"Manresa",
    "sg:orig_category":"M\u00c1rmoles, Granitos Y Piedras Naturales",
    "sg:phone":"+34 938 72 87 32",
    "sg:postcode":"08241",
    "sg:province":"Barcelona",
    "wof:name":"Marbres Vall S.c.c.l.",
    "wof:placetype":"venue"
},
  "geometry": {"coordinates":[1.8204710484,41.728515625],"type":"Point"}
}