{
  "type": "Feature",
  "properties": {
    "addr:full":"C/ Rutlla, 5 Calonge Girona 17251",
    "addr:housenumber":"5",
    "addr:postcode":"17251",
    "addr:street":"C / Rutlla",
    "iso:country":"ES",
    "sg:address":"C/ Rutlla, 5",
    "sg:city":"Calonge",
    "sg:orig_category":"Farmacias",
    "sg:phone":"+34 972 65 17 19",
    "sg:postcode":"17251",
    "sg:province":"Girona",
    "wof:name":"Puigrefagut Serra Maria Cinta",
    "wof:placetype":"venue"
},
  "geometry": {"coordinates":[3.0745310783,41.8616409302],"type":"Point"}
}