{
  "type": "Feature",
  "properties": {
    "addr:full":"Calle de Mayor, 58 Leiva La Rioja 26213",
    "addr:housenumber":"58",
    "addr:postcode":"26213",
    "addr:street":"Calle De Mayor;Rioja",
    "iso:country":"ES",
    "sg:address":"Calle de Mayor, 58",
    "sg:city":"Leiva",
    "sg:orig_category":"Fabricaci\u00d3n De Harinas, S\u00c9molas, Productos De Elaboraci\u00d3n Del Grano",
    "sg:phone":"+34 941 32 75 68",
    "sg:postcode":"26213",
    "sg:province":"La Rioja",
    "wof:name":"Harinas La Esperanza S.l.",
    "wof:placetype":"venue"
},
  "geometry": {"coordinates":[-3.0480089188,42.502040863],"type":"Point"}
}