{
  "type": "Feature",
  "properties": {
    "addr:full":"Av Parc, 19 Cornella Llobregat Barcelona 08940",
    "addr:housenumber":"19",
    "addr:postcode":"08940",
    "addr:street":"Av Parc",
    "iso:country":"ES",
    "sg:address":"Av Parc, 19",
    "sg:city":"Cornella Llobregat",
    "sg:orig_category":"M\u00c9dicos: Geriatr\u00cda, Gerontolog\u00cda (enfermedades De La Tercera Edad)",
    "sg:phone":"+34 933 77 47 47",
    "sg:postcode":"08940",
    "sg:province":"Barcelona",
    "wof:name":"Clinica Sant Jordi De Cornella S.l.",
    "wof:placetype":"venue"
},
  "geometry": {"coordinates":[2.0730640888,41.3592796326],"type":"Point"}
}