{
  "type": "Feature",
  "properties": {
    "addr:full":"As Lamas, 25 Valenza Ourense 32920",
    "addr:housenumber":"25",
    "addr:postcode":"32920",
    "addr:street":"Lamas",
    "iso:country":"ES",
    "sg:address":"As Lamas, 25",
    "sg:city":"Valenza",
    "sg:orig_category":"Suministros Y Materiales Industriales",
    "sg:phone":"+34 988 22 73 29",
    "sg:postcode":"32920",
    "sg:province":"Ourense",
    "sg:website":"www.resortesgalicia.com",
    "wof:name":"Cid Castro Isolino",
    "wof:placetype":"venue"
},
  "geometry": {"coordinates":[-7.9207677841,42.30128479],"type":"Point"}
}