{
  "type": "Feature",
  "properties": {
    "iso:country":"ES",
    "sg:address":"Rond Buenavista, S/n",
    "sg:city":"Toledo",
    "sg:orig_category":"Papeler\u00cdas, Librer\u00cdas",
    "sg:phone":"+34 925 21 29 58",
    "sg:postcode":"45005",
    "sg:province":"Toledo",
    "wof:name":"Venin  Clara",
    "wof:placetype":"venue"
},
  "geometry": {"coordinates":[-4.0396938324,39.874370575],"type":"Point"}
}