{
  "type": "Feature",
  "properties": {
    "iso:country":"ES",
    "sg:address":"Calle de Ignacio De Soto, 6",
    "sg:city":"Ecija",
    "sg:orig_category":"Promotores Constructores",
    "sg:phone":"+34 955 90 33 74",
    "sg:postcode":"41400",
    "sg:province":"Sevilla",
    "wof:name":"Gestion De Contratas Y Promociones Gutierrez S.l.",
    "wof:placetype":"venue"
},
  "geometry": {"coordinates":[-5.0791668892,37.5388755798],"type":"Point"}
}