{
  "type": "Feature",
  "properties": {
    "iso:country":"ES",
    "sg:address":"Avda Mariano Andres, 184",
    "sg:city":"Le\u00f3n",
    "sg:orig_category":"Farmacias",
    "sg:phone":"+34 987 22 54 52",
    "sg:postcode":"24008",
    "sg:province":"Le\u00f3n",
    "wof:name":"Calleja Suarez Carmen",
    "wof:placetype":"venue"
},
  "geometry": {"coordinates":[-5.566988945,42.6181221008],"type":"Point"}
}