{
  "type": "Feature",
  "properties": {
    "addr:full":"Calle de Casiopea, 57 Alacant Alicante 03006",
    "addr:housenumber":"57",
    "addr:postcode":"03006",
    "addr:street":"Calle De Casiopea",
    "iso:country":"ES",
    "sg:address":"Calle de Casiopea, 57",
    "sg:city":"Alacant",
    "sg:orig_category":"Grafistas",
    "sg:phone":"+34 965 11 30 47",
    "sg:postcode":"03006",
    "sg:province":"Alicante",
    "wof:name":"Graficos Dueto Cooperativa Valenciana",
    "wof:placetype":"venue"
},
  "geometry": {"coordinates":[-0.5100699067,38.3472175598],"type":"Point"}
}