{
  "type": "Feature",
  "properties": {
    "iso:country":"ES",
    "sg:address":"Calle de Magacela, 28",
    "sg:city":"Villanueva Serena",
    "sg:orig_category":"Ropa Para Se\u00d1oras Y Caballeros (al Por Menor)",
    "sg:phone":"+34 924 84 55 51",
    "sg:postcode":"06700",
    "sg:province":"Badajoz",
    "wof:name":"Emilia Estilo S.l.",
    "wof:placetype":"venue"
},
  "geometry": {"coordinates":[-5.7984452248,38.9722595215],"type":"Point"}
}