{
  "type": "Feature",
  "properties": {
    "addr:full":"Calle de Francisco Garcia Pavon, 6 Tomelloso Ciudad Real 13700",
    "addr:housenumber":"6",
    "addr:postcode":"13700",
    "addr:street":"Calle De Francisco Garcia Pavon",
    "iso:country":"ES",
    "sg:address":"Calle de Francisco Garcia Pavon, 6",
    "sg:city":"Tomelloso",
    "sg:orig_category":"Peluqueros: De Se\u00d1oras",
    "sg:phone":"+34 926 51 17 06",
    "sg:postcode":"13700",
    "sg:province":"Ciudad Real",
    "wof:name":"Parra Onsurbe Isabel",
    "wof:placetype":"venue"
},
  "geometry": {"coordinates":[-3.00938797,39.1574363708],"type":"Point"}
}