{
  "type": "Feature",
  "properties": {
    "addr:full":"Calle de Valentu\u00d1ana, 2 Marbella M\u00e1laga 29600",
    "addr:housenumber":"2",
    "addr:postcode":"29600",
    "addr:street":"Calle De Valentun\u0303Ana;Ma\u0301Laga",
    "iso:country":"ES",
    "sg:address":"Calle de Valentu\u00d1ana, 2",
    "sg:city":"Marbella",
    "sg:orig_category":"M\u00c9dicos: Ginecolog\u00cda Y Obstetricia",
    "sg:phone":"+34 952 77 29 97",
    "sg:postcode":"29600",
    "sg:province":"M\u00e1laga",
    "wof:name":"Salcedo Lillo Antonio",
    "wof:placetype":"venue"
},
  "geometry": {"coordinates":[-4.8885512352,36.5102996826],"type":"Point"}
}