{
  "type": "Feature",
  "properties": {
    "iso:country":"ES",
    "sg:address":"Calle de Alfonso De Castro, 5",
    "sg:city":"Rute",
    "sg:orig_category":"M\u00c9dicos: Dermatolog\u00cda Y Venereolog\u00cda",
    "sg:phone":"+34 957 53 93 63",
    "sg:postcode":"14960",
    "sg:province":"C\u00f3rdoba",
    "wof:name":"Repiso Jimenez Juan Bosco",
    "wof:placetype":"venue"
},
  "geometry": {"coordinates":[-4.370071888,37.3255233765],"type":"Point"}
}