{
  "type": "Feature",
  "properties": {
    "iso:country":"ES",
    "sg:address":"Calle de Perez Galdos, S/n",
    "sg:city":"Santo\u00f1a",
    "sg:orig_category":"Carnicer\u00cdas, Carnicer\u00cdas",
    "sg:phone":"+34 942 66 22 51",
    "sg:postcode":"39740",
    "sg:province":"Cantabria",
    "wof:name":"Benavent Sainz Ramon",
    "wof:placetype":"venue"
},
  "geometry": {"coordinates":[-3.4593091011,43.4434738159],"type":"Point"}
}