{
  "type": "Feature",
  "properties": {
    "iso:country":"ES",
    "sg:address":"Carrer de Barcelona (de), 49",
    "sg:city":"Salou",
    "sg:orig_category":"Librer\u00cdas",
    "sg:phone":"+34 977 38 37 52",
    "sg:postcode":"43840",
    "sg:province":"Tarragona",
    "wof:name":"Anguera Monte Maria Elisa",
    "wof:placetype":"venue"
},
  "geometry": {"coordinates":[1.1309808493,41.0801315308],"type":"Point"}
}