{
  "type": "Feature",
  "properties": {
    "iso:country":"ES",
    "sg:address":"Vapor, 10",
    "sg:city":"Gava",
    "sg:orig_category":"Maquinaria Para Industrias Diversas",
    "sg:phone":"+34 936 62 72 45",
    "sg:postcode":"08850",
    "sg:province":"Barcelona",
    "wof:name":"Acabados Miranda E Hijos S. L.",
    "wof:placetype":"venue"
},
  "geometry": {"coordinates":[2.016383,41.299297],"type":"Point"}
}