{
  "type": "Feature",
  "properties": {
    "addr:full":"Calle de Higueras, 65 Madrid Madrid 28047",
    "addr:housenumber":"65",
    "addr:postcode":"madrid;28047",
    "addr:street":"Calle De Higueras",
    "iso:country":"ES",
    "sg:address":"Calle de Higueras, 65",
    "sg:city":"Madrid",
    "sg:orig_category":"Cl\u00cdnicas Dentales",
    "sg:phone":"+34 915 26 29 49",
    "sg:postcode":"28047",
    "sg:province":"Madrid",
    "wof:name":"Clinica Dental Lucero S.l.",
    "wof:placetype":"venue"
},
  "geometry": {"coordinates":[-3.7451798916,40.4027328491],"type":"Point"}
}