{
  "type": "Feature",
  "properties": {
    "iso:country":"ES",
    "sg:address":"Calle de Pedro Perez Fernandez, 11",
    "sg:city":"Sevilla",
    "sg:orig_category":"Pintura: M\u00c1quinas (instalaci\u00d3n)",
    "sg:phone":"+34 954 27 11 07",
    "sg:postcode":"41011",
    "sg:province":"Sevilla",
    "sg:website":"www.skm.es",
    "wof:name":"Exel Industrial Equipos Y Extrusion S.a.",
    "wof:placetype":"venue"
},
  "geometry": {"coordinates":[-6.001393795,37.3759994507],"type":"Point"}
}