{
  "type": "Feature",
  "properties": {
    "iso:country":"ES",
    "sg:address":"Carr Vallcalent, 1",
    "sg:city":"Lleida",
    "sg:orig_category":"M\u00c9dicos: Otorrinolaringolog\u00cda",
    "sg:phone":"+34 973 26 50 51",
    "sg:postcode":"25006",
    "sg:province":"Lleida",
    "wof:name":"Sarroca Capell Esteban",
    "wof:placetype":"venue"
},
  "geometry": {"coordinates":[0.6203600168,41.6168708801],"type":"Point"}
}