{
  "type": "Feature",
  "properties": {
    "iso:country":"ES",
    "sg:address":"Calle de Ramiro De Maeztu, 14",
    "sg:city":"Valencia",
    "sg:orig_category":"Ropa Para Beb\u00c9s Y Ni\u00d1os (confecci\u00d3n, Al Por Mayor)",
    "sg:phone":"+34 963 55 57 86",
    "sg:postcode":"46022",
    "sg:province":"Valencia",
    "wof:name":"Medina Fabra Maria Del Carmen",
    "wof:placetype":"venue"
},
  "geometry": {"coordinates":[-0.3489710093,39.4674606323],"type":"Point"}
}