{
  "type": "Feature",
  "properties": {
    "iso:country":"ES",
    "sg:address":"Avda Fuerzas Armadas (de Las), 19",
    "sg:city":"Granada",
    "sg:orig_category":"M\u00c9dicos: Ginecolog\u00cda Y Obstetricia",
    "sg:phone":"+34 958 28 72 09",
    "sg:postcode":"18014",
    "sg:province":"Granada",
    "wof:name":"Gallego Barros Jaime Rafael",
    "wof:placetype":"venue"
},
  "geometry": {"coordinates":[-3.612432003,37.1896133423],"type":"Point"}
}