{
  "type": "Feature",
  "properties": {
    "addr:full":"Calle de San Pedro Bautista, 35 Avila \u00c1vila 05005",
    "addr:housenumber":"35",
    "addr:postcode":"05005",
    "addr:street":"Calle De San;Bautista;A\u0301Vila",
    "iso:country":"ES",
    "sg:address":"Calle de San Pedro Bautista, 35",
    "sg:city":"Avila",
    "sg:orig_category":"Deportes Diversos",
    "sg:phone":"+34 920 25 34 93",
    "sg:postcode":"05005",
    "sg:province":"\u00c1vila",
    "wof:name":"Federacion De Castilla Y Leon De Futbol",
    "wof:placetype":"venue"
},
  "geometry": {"coordinates":[-4.6893820763,40.6584854126],"type":"Point"}
}