{
  "type": "Feature",
  "properties": {
    "iso:country":"ES",
    "sg:address":"Calle de Fuente (la), 8",
    "sg:city":"Leganes",
    "sg:orig_category":"Perfumer\u00cda (al Por Menor)",
    "sg:phone":"+34 916 94 88 77",
    "sg:postcode":"28911",
    "sg:province":"Madrid",
    "wof:name":"Eco Precio S.a.",
    "wof:placetype":"venue"
},
  "geometry": {"coordinates":[-3.7637319565,40.3284339905],"type":"Point"}
}