{
  "type": "Feature",
  "properties": {
    "addr:full":"Carr Guillem De Castro, 8 Oliva Valencia 46780",
    "addr:housenumber":"8",
    "addr:postcode":"46780",
    "addr:street":"Carr Guillem De Castro",
    "iso:country":"ES",
    "sg:address":"Carr Guillem De Castro, 8",
    "sg:city":"Oliva",
    "sg:orig_category":"Asesor\u00cda Fiscal Y Jur\u00cddica",
    "sg:phone":"+34 962 85 42 64",
    "sg:postcode":"46780",
    "sg:province":"Valencia",
    "wof:name":"Salom Asesores S.l.",
    "wof:placetype":"venue"
},
  "geometry": {"coordinates":[-0.1161210015,38.9224853516],"type":"Point"}
}