{
  "type": "Feature",
  "properties": {
    "addr:full":"Avda Extremadura, 70 Talavera Real Badajoz 06140",
    "addr:housenumber":"70",
    "addr:postcode":"06140",
    "addr:street":"Avda Extremadura",
    "iso:country":"ES",
    "sg:address":"Avda Extremadura, 70",
    "sg:city":"Talavera Real",
    "sg:orig_category":"Frutas, Legumbres Frescas Y Tempranas (al Por Menor)",
    "sg:phone":"+34 924 44 16 18",
    "sg:postcode":"06140",
    "sg:province":"Badajoz",
    "wof:name":"Laguna Sanchez Antonio",
    "wof:placetype":"venue"
},
  "geometry": {"coordinates":[-6.7684831619,38.8772773743],"type":"Point"}
}