{
  "type": "Feature",
  "properties": {
    "addr:full":"Avda Andalucia, 46 Cantillana Sevilla 41320",
    "addr:housenumber":"46",
    "addr:postcode":"41320",
    "addr:street":"Avda Andalucia",
    "iso:country":"ES",
    "sg:address":"Avda Andalucia, 46",
    "sg:city":"Cantillana",
    "sg:orig_category":"Molduras, Junquillos, Listones Y Molduras Perforadas",
    "sg:phone":"+34 955 73 20 71",
    "sg:postcode":"41320",
    "sg:province":"Sevilla",
    "wof:name":"Diaz Naranjos Maria Del Carmen",
    "wof:placetype":"venue"
},
  "geometry": {"coordinates":[-5.8254208565,37.6098709106],"type":"Point"}
}