{
  "type": "Feature",
  "properties": {
    "addr:full":"Calle de Moncada, 2 Castellon Castell\u00f3n 12005",
    "addr:housenumber":"2",
    "addr:postcode":"12005",
    "addr:street":"Calle De Moncada;Castello\u0301N",
    "iso:country":"ES",
    "sg:address":"Calle de Moncada, 2",
    "sg:city":"Castellon",
    "sg:orig_category":"Agencias Y Agentes Comerciales, Representantes",
    "sg:phone":"+34 964 23 60 13",
    "sg:postcode":"12005",
    "sg:province":"Castell\u00f3n",
    "wof:name":"Gozalbo Oliver Jose Joaquin",
    "wof:placetype":"venue"
},
  "geometry": {"coordinates":[-0.0368890017,39.9806594849],"type":"Point"}
}