{
  "type": "Feature",
  "properties": {
    "addr:full":"Calle de Severo Ochoa, 2 Gijon Asturias 33208",
    "addr:housenumber":"2",
    "addr:postcode":"33208",
    "addr:street":"Calle De Severo Ochoa",
    "iso:country":"ES",
    "sg:address":"Calle de Severo Ochoa, 2",
    "sg:city":"Gijon",
    "sg:orig_category":"Librer\u00cdas",
    "sg:phone":"+34 985 38 94 77",
    "sg:postcode":"33208",
    "sg:province":"Asturias",
    "wof:name":"Quintana Cabanas Sonia",
    "wof:placetype":"venue"
},
  "geometry": {"coordinates":[-5.6699399948,43.5321769714],"type":"Point"}
}