{
  "type": "Feature",
  "properties": {
    "addr:full":"Urb Julian Besteiro, S/n Linea De La Concepcion C\u00e1diz 11300",
    "addr:housenumber":"/ n",
    "addr:postcode":"11300",
    "addr:street":"Urb Julian Besteiro S;Ca\u0301Diz",
    "iso:country":"ES",
    "sg:address":"Urb Julian Besteiro, S/n",
    "sg:city":"Linea De La Concepcion",
    "sg:orig_category":"Peluquer\u00cdas, Peluquer\u00cda Mixta",
    "sg:phone":"+34 956 17 68 06",
    "sg:postcode":"11300",
    "sg:province":"C\u00e1diz",
    "wof:name":"Alvarez Beneroso Ricardo",
    "wof:placetype":"venue"
},
  "geometry": {"coordinates":[-6.29240942,36.5299415588],"type":"Point"}
}