{
  "type": "Feature",
  "properties": {
    "iso:country":"ES",
    "sg:address":"Josep Joaquin Landerer, 7",
    "sg:city":"Elche",
    "sg:orig_category":"Molduras, Junquillos, Listones Y Molduras Perforadas",
    "sg:phone":"+34 965 42 91 89",
    "sg:postcode":"03202",
    "sg:province":"Alicante",
    "wof:name":"Cafeteria Alejandria C.b.",
    "wof:placetype":"venue"
},
  "geometry": {"coordinates":[-0.5931239724,38.2568435669],"type":"Point"}
}