{
  "type": "Feature",
  "properties": {
    "addr:full":"Av Diagonal, 577 Barcelona Barcelona 08029",
    "addr:housenumber":"577",
    "addr:postcode":"08029",
    "addr:street":"Av Diagonal",
    "iso:country":"ES",
    "sg:address":"Av Diagonal, 577",
    "sg:city":"Barcelona",
    "sg:orig_category":"Florister\u00cdas",
    "sg:phone":"+34 934 39 02 09",
    "sg:postcode":"08029",
    "sg:province":"Barcelona",
    "wof:name":"Punt Flors Per Casa S.l.",
    "wof:placetype":"venue"
},
  "geometry": {"coordinates":[2.1327810287,41.389415741],"type":"Point"}
}