{
  "type": "Feature",
  "properties": {
    "addr:full":"Calle de Mercado Viejo, 7 Pe\u00f1afiel Valladolid 47300",
    "addr:housenumber":"7",
    "addr:postcode":"47300",
    "addr:street":"Calle De Mercado Viejo",
    "iso:country":"ES",
    "sg:address":"Calle de Mercado Viejo, 7",
    "sg:city":"Pe\u00f1afiel",
    "sg:orig_category":"Supermercados Y Hipermercados",
    "sg:phone":"+34 983 87 31 61",
    "sg:postcode":"47300",
    "sg:province":"Valladolid",
    "wof:name":"Zurro Plaza 98 S.l.",
    "wof:placetype":"venue"
},
  "geometry": {"coordinates":[-4.1230540276,41.5967330933],"type":"Point"}
}