{
  "type": "Feature",
  "properties": {
    "addr:full":"Fnc. Loma, S/n Bienvenida Ciudad Real 13596",
    "addr:housenumber":"/ n",
    "addr:postcode":"bienvenida;13596",
    "addr:street":"Loma S",
    "iso:country":"ES",
    "sg:address":"Fnc. Loma, S/n",
    "sg:city":"Bienvenida",
    "sg:orig_category":"Producci\u00d3n, Venta De Productos De Agricultura Biol\u00d3gica",
    "sg:phone":"+34 926 69 81 22",
    "sg:postcode":"13596",
    "sg:province":"Ciudad Real",
    "wof:name":"Campos De Alcudia S.a.",
    "wof:placetype":"venue"
},
  "geometry": {"coordinates":[-4.5712680817,38.6086883545],"type":"Point"}
}