{
  "type": "Feature",
  "properties": {
    "iso:country":"ES",
    "sg:address":"Carrer de Creueta, S/n",
    "sg:city":"Santa Perpetua De Mogoda",
    "sg:orig_category":"Parques Para Contenedores",
    "sg:phone":"+34 935 74 20 94",
    "sg:postcode":"08130",
    "sg:province":"Barcelona",
    "wof:name":"Wipak Iberica 2003 S.l.",
    "wof:placetype":"venue"
},
  "geometry": {"coordinates":[2.1786031723,41.5380477905],"type":"Point"}
}