{
  "type": "Feature",
  "properties": {
    "addr:full":"Trav Tte Gral Fdco Michavila, 8 Alcora Castell\u00f3n 12110",
    "addr:housenumber":"8",
    "addr:postcode":"12110",
    "addr:street":"Trav Tte Gral Fdco Michavila;Castello\u0301N",
    "iso:country":"ES",
    "sg:address":"Trav Tte Gral Fdco Michavila, 8",
    "sg:city":"Alcora",
    "sg:orig_category":"Art\u00cdculos Funerarios (al Por Menor)",
    "sg:phone":"+34 964 38 67 93",
    "sg:postcode":"12110",
    "sg:province":"Castell\u00f3n",
    "wof:name":"Funeraria La Magdalena S.l.",
    "wof:placetype":"venue"
},
  "geometry": {"coordinates":[-0.2178789973,40.0734786987],"type":"Point"}
}