{
  "type": "Feature",
  "properties": {
    "iso:country":"ES",
    "sg:address":"Pare Bartomeu Salva, 4",
    "sg:city":"Cadenas",
    "sg:orig_category":"Electrodom\u00c9sticos (al Por Menor)",
    "sg:phone":"+34 971 26 12 77",
    "sg:postcode":"07608",
    "sg:province":"Islas Baleares",
    "wof:name":"Pacual Bibiloni Miguel",
    "wof:placetype":"venue"
},
  "geometry": {"coordinates":[2.7556099892,39.5265617371],"type":"Point"}
}