{
  "type": "Feature",
  "properties": {
    "iso:country":"ES",
    "sg:address":"Av Finestrat, 22",
    "sg:city":"Torretes",
    "sg:orig_category":"Empresas De Carpinter\u00cda De Madera",
    "sg:phone":"+34 966 81 00 96",
    "sg:postcode":"03570",
    "sg:province":"Alicante",
    "wof:name":"Pe\u00f1a Garcia Emilio",
    "wof:placetype":"venue"
},
  "geometry": {"coordinates":[-0.2327190042,38.505821228],"type":"Point"}
}