{
  "type": "Feature",
  "properties": {
    "iso:country":"ES",
    "sg:address":"Rua Rueiro, 9",
    "sg:city":"Bertamirans",
    "sg:orig_category":"Agencias Y Agentes Comerciales, Representantes",
    "sg:phone":"+34 981 88 31 24",
    "sg:postcode":"15220",
    "sg:province":"La Coru\u00f1a",
    "wof:name":"Freire Romero Manuel",
    "wof:placetype":"venue"
},
  "geometry": {"coordinates":[-8.653008461,42.8609771729],"type":"Point"}
}