{
  "type": "Feature",
  "properties": {
    "iso:country":"ES",
    "sg:address":"Goribar Auzoa, 9",
    "sg:city":"Goribar",
    "sg:orig_category":"Suministros Para Carrocer\u00cdas",
    "sg:phone":"+34 943 78 13 50",
    "sg:postcode":"20560",
    "sg:province":"Guip\u00f9zcoa",
    "wof:name":"Garaje O\u00f1ati S.coop.ltda.",
    "wof:placetype":"venue"
},
  "geometry": {"coordinates":[-2.423648119,43.0449066162],"type":"Point"}
}