{
  "type": "Feature",
  "properties": {
    "addr:full":"Calle de Ca\u00d1as (las), 30 San Vicente Del Raspeig-sant Vicent Del Raspeig Alicante 03690",
    "addr:housenumber":"30",
    "addr:postcode":"03690",
    "addr:street":"Calle De Can\u0303As Las",
    "iso:country":"ES",
    "sg:address":"Calle de Ca\u00d1as (las), 30",
    "sg:city":"San Vicente Del Raspeig-sant Vicent Del Raspeig",
    "sg:orig_category":"Empresas De Carpinter\u00cda De Madera",
    "sg:phone":"+34 965 66 54 85",
    "sg:postcode":"03690",
    "sg:province":"Alicante",
    "wof:name":"Antonio Ordo\u00f1ez S.l.",
    "wof:placetype":"venue"
},
  "geometry": {"coordinates":[-0.53587991,38.3957443237],"type":"Point"}
}