{
  "type": "Feature",
  "properties": {
    "iso:country":"ES",
    "sg:address":"Trva Don Pedro, 2",
    "sg:city":"Villarrobledo",
    "sg:orig_category":"Frutas, Legumbres Frescas Y Tempranas (al Por Menor)",
    "sg:phone":"+34 967 14 53 65",
    "sg:postcode":"02600",
    "sg:province":"Albacete",
    "wof:name":"Fernandez Montesino Daniel",
    "wof:placetype":"venue"
},
  "geometry": {"coordinates":[-2.6038300991,39.2671928406],"type":"Point"}
}