{
  "type": "Feature",
  "properties": {
    "iso:country":"ES",
    "sg:address":"Calle de Postigos, 3",
    "sg:city":"Andujar",
    "sg:orig_category":"Empresas De Pintura Y Revestimientos",
    "sg:phone":"+34 953 50 23 10",
    "sg:postcode":"23740",
    "sg:province":"Ja\u00e9n",
    "wof:name":"Andujar Porcel Jesus",
    "wof:placetype":"venue"
},
  "geometry": {"coordinates":[-4.0547618866,38.0365943909],"type":"Point"}
}