{
  "type": "Feature",
  "properties": {
    "iso:country":"ES",
    "sg:address":"Calle de Pintor Mauro Ortiz De Urbina, 3",
    "sg:city":"Vitoria-gasteiz",
    "sg:orig_category":"Asesor\u00cda Sobre Comunicaci\u00d3n De Empresas",
    "sg:phone":"+34 945 21 30 04",
    "sg:postcode":"01008",
    "sg:province":"\u00c1lava",
    "wof:name":"Alegria Legarda Miguel Angel",
    "wof:placetype":"venue"
},
  "geometry": {"coordinates":[-2.685406208,42.8496856689],"type":"Point"}
}