{
  "type": "Feature",
  "properties": {
    "iso:country":"ES",
    "sg:address":"Carr Pere Alcantara Penya, 11",
    "sg:city":"Felanitx",
    "sg:orig_category":"Supermercados Y Hipermercados",
    "sg:phone":"+34 971 58 08 81",
    "sg:postcode":"07200",
    "sg:province":"Islas Baleares",
    "wof:name":"Rigo Vicens S.l.",
    "wof:placetype":"venue"
},
  "geometry": {"coordinates":[3.1423890591,39.4677581787],"type":"Point"}
}