{
  "type": "Feature",
  "properties": {
    "iso:country":"ES",
    "sg:address":"Calle de Miguel Villanueva, 37",
    "sg:city":"Casta\u00e7ares De Rioja",
    "sg:orig_category":"Ense\u00d1anza, Formaci\u00d3n Profesional: Aprendizaje",
    "sg:phone":"+34 941 30 02 00",
    "sg:postcode":"26240",
    "sg:province":"La Rioja",
    "wof:name":"Ayuntamiento De Casta\u00f1ares De Rioja",
    "wof:placetype":"venue"
},
  "geometry": {"coordinates":[-2.8806695938,42.5159606934],"type":"Point"}
}