{
  "type": "Feature",
  "properties": {
    "iso:country":"ES",
    "sg:address":"Plaz Llano De Las Coronadas, 5",
    "sg:city":"Aguilar De La Frontera",
    "sg:orig_category":"Ense\u00d1anza Variada",
    "sg:phone":"+34 957 68 95 64",
    "sg:postcode":"14920",
    "sg:province":"C\u00f3rdoba",
    "wof:name":"Perez Navarro Cristina",
    "wof:placetype":"venue"
},
  "geometry": {"coordinates":[-4.6575899124,37.5175857544],"type":"Point"}
}