{
  "type": "Feature",
  "properties": {
    "addr:full":"Calle de Aluminio, 23 Arganda Madrid 28500",
    "addr:housenumber":"23",
    "addr:postcode":"28500",
    "addr:street":"Calle De Aluminio",
    "iso:country":"ES",
    "sg:address":"Calle de Aluminio, 23",
    "sg:city":"Arganda",
    "sg:orig_category":"Rectificaci\u00d3n, Mecanizado, Fresado",
    "sg:phone":"+34 918 71 51 22",
    "sg:postcode":"28500",
    "sg:province":"Madrid",
    "wof:name":"Maycli Mecanizados S.l.",
    "wof:placetype":"venue"
},
  "geometry": {"coordinates":[-3.471165657,40.3006095886],"type":"Point"}
}