{
  "type": "Feature",
  "properties": {
    "iso:country":"ES",
    "sg:address":"Calle de Rocinante, 7",
    "sg:city":"Pto. Rosario",
    "sg:orig_category":"Peluqueros: De Se\u00d1oras",
    "sg:phone":"+34 928 53 05 92",
    "sg:postcode":"35600",
    "sg:province":"Las Palmas",
    "wof:name":"Quintana Ruiz Laura",
    "wof:placetype":"venue"
},
  "geometry": {"coordinates":[-13.8669300079,28.5001678467],"type":"Point"}
}