{
  "type": "Feature",
  "properties": {
    "iso:country":"ES",
    "sg:address":"Calle de Melilla, 2",
    "sg:city":"Begijar",
    "sg:orig_category":"Inform\u00c1tica (estudios, Servicios, Asesor\u00cda, Formaci\u00d3n)",
    "sg:phone":"+34 953 76 42 81",
    "sg:postcode":"23520",
    "sg:province":"Ja\u00e9n",
    "wof:name":"Rexus Informatica S.l.",
    "wof:placetype":"venue"
},
  "geometry": {"coordinates":[-3.528069973,37.9867286682],"type":"Point"}
}