{
  "type": "Feature",
  "properties": {
    "addr:full":"Cra. Arbucies, S/n Sta. Eugenia Berga Barcelona 08507",
    "addr:housenumber":"s / n",
    "addr:postcode":"08507",
    "addr:street":"Sta. Eugenia",
    "iso:country":"ES",
    "sg:address":"Cra. Arbucies, S/n",
    "sg:city":"Sta. Eugenia Berga",
    "sg:orig_category":"Alimentaci\u00d3n General (al Por Mayor)",
    "sg:phone":"+34 938 89 49 86",
    "sg:postcode":"08507",
    "sg:province":"Barcelona",
    "wof:name":"Cooperativa Agraria Comarcal Plana De Vich",
    "wof:placetype":"venue"
},
  "geometry": {"coordinates":[2.2816679478,41.9036827087],"type":"Point"}
}