{
  "type": "Feature",
  "properties": {
    "iso:country":"ES",
    "sg:address":"Pozo Blanco, 17",
    "sg:city":"Iru\u00f1a",
    "sg:orig_category":"Art\u00cdculos De Regalo (al Por Menor)",
    "sg:phone":"+34 948 22 14 32",
    "sg:postcode":"31001",
    "sg:province":"Navarra",
    "wof:name":"Aguinaga Roustan Margarita",
    "wof:placetype":"venue"
},
  "geometry": {"coordinates":[-1.6439201832,42.8167419434],"type":"Point"}
}