{
  "type": "Feature",
  "properties": {
    "iso:country":"ES",
    "sg:address":"Calle de Duquesa Villahermosa, 121",
    "sg:city":"Zaragoza",
    "sg:orig_category":"Promotores Constructores",
    "sg:phone":"+34 976 35 17 99",
    "sg:postcode":"50009",
    "sg:province":"Zaragoza",
    "wof:name":"Comercial Santos Semper S.l.",
    "wof:placetype":"venue"
},
  "geometry": {"coordinates":[-0.9089089036,41.6459999084],"type":"Point"}
}