{
  "type": "Feature",
  "properties": {
    "iso:country":"ES",
    "sg:address":"Calle de Padre Miguelez, 9",
    "sg:city":"Ba\u00d1eza",
    "sg:orig_category":"Lanas (al Por Mayor)",
    "sg:phone":"+34 987 64 10 52",
    "sg:postcode":"24750",
    "sg:province":"Le\u00f3n",
    "wof:name":"Amigo Esteban Yolanda",
    "wof:placetype":"venue"
},
  "geometry": {"coordinates":[-5.8977131844,42.2992515564],"type":"Point"}
}