{
  "type": "Feature",
  "properties": {
    "addr:full":"Calle de Ferrerias, 5 Donostia-san Sebastian Guip\u00f9zcoa 20011",
    "addr:housenumber":"5",
    "addr:postcode":"20011",
    "addr:street":"Calle De Ferrerias",
    "iso:country":"ES",
    "sg:address":"Calle de Ferrerias, 5",
    "sg:city":"Donostia-san Sebastian",
    "sg:orig_category":"Fabricaci\u00d3n De Ventanas",
    "sg:phone":"+34 943 46 56 58",
    "sg:postcode":"20011",
    "sg:province":"Guip\u00f9zcoa",
    "wof:name":"Amets Leihoak",
    "wof:placetype":"venue"
},
  "geometry": {"coordinates":[-1.9774495363,43.3021888733],"type":"Point"}
}