{
  "type": "Feature",
  "properties": {
    "addr:full":"Ctra Olivenza, 9 Badajoz Badajoz 06011",
    "addr:housenumber":"9",
    "addr:postcode":"06011",
    "addr:street":"Ctra Olivenza",
    "iso:country":"ES",
    "sg:address":"Ctra Olivenza, 9",
    "sg:city":"Badajoz",
    "sg:orig_category":"Construcci\u00d3n, Importaci\u00d3n De Veh\u00cdculos",
    "sg:phone":"+34 924 23 18 80",
    "sg:postcode":"06011",
    "sg:province":"Badajoz",
    "wof:name":"Cluny Merino Luis",
    "wof:placetype":"venue"
},
  "geometry": {"coordinates":[-6.9874491692,38.8595428467],"type":"Point"}
}