{
  "type": "Feature",
  "properties": {
    "iso:country":"ES",
    "sg:address":"Calle de Sevilla, 35",
    "sg:city":"Ronda",
    "sg:orig_category":"Camiser\u00cda Y Ropa Interior Masculina (al Por Menor)",
    "sg:phone":"+34 952 87 95 90",
    "sg:postcode":"29400",
    "sg:province":"M\u00e1laga",
    "wof:name":"Orozco Espinosa Vicenta",
    "wof:placetype":"venue"
},
  "geometry": {"coordinates":[-5.1658058167,36.7444343567],"type":"Point"}
}