{
  "type": "Feature",
  "properties": {
    "addr:full":"Ctra. Besalu-roses, Km. 0032,5 Vila-sacra Girona 17485",
    "addr:postcode":"17485",
    "addr:street":"Ctra. Besalu-Roses Km. 0032,5",
    "iso:country":"ES",
    "sg:address":"Ctra. Besalu-roses, Km. 0032,5",
    "sg:city":"Vila-sacra",
    "sg:orig_category":"Semiller\u00cdas",
    "sg:phone":"+34 972 51 04 52",
    "sg:postcode":"17485",
    "sg:province":"Girona",
    "wof:name":"Marti Palagos Juan",
    "wof:placetype":"venue"
},
  "geometry": {"coordinates":[3.0190849304,42.265460968],"type":"Point"}
}