{
  "type": "Feature",
  "properties": {
    "addr:full":"Rua Caldeireria (da), 5 Santiago De Compostela La Coru\u00f1a 15704",
    "addr:housenumber":"5",
    "addr:postcode":"15704",
    "addr:street":"Rua Caldeireria Da;Corun\u0303A",
    "iso:country":"ES",
    "sg:address":"Rua Caldeireria (da), 5",
    "sg:city":"Santiago De Compostela",
    "sg:orig_category":"Alimentaci\u00d3n General (al Por Menor)",
    "sg:phone":"+34 981 58 10 62",
    "sg:postcode":"15704",
    "sg:province":"La Coru\u00f1a",
    "wof:name":"Castro Crespo Alejandro",
    "wof:placetype":"venue"
},
  "geometry": {"coordinates":[-8.5421886444,42.8795051575],"type":"Point"}
}