{
  "type": "Feature",
  "properties": {
    "addr:full":"Carrer de Sedera (de La ), 28 Reus Tarragona 43205",
    "addr:housenumber":"28",
    "addr:postcode":"43205",
    "addr:street":"Carrer De Sedera De La",
    "iso:country":"ES",
    "sg:address":"Carrer de Sedera (de La ), 28",
    "sg:city":"Reus",
    "sg:orig_category":"Fabricaci\u00d3n De Productos L\u00c1cteos Y Derivados",
    "sg:phone":"+34 977 75 00 39",
    "sg:postcode":"43205",
    "sg:province":"Tarragona",
    "wof:name":"Derivados Carnicos Riudoms Sl",
    "wof:placetype":"venue"
},
  "geometry": {"coordinates":[1.1039379835,41.1456375122],"type":"Point"}
}