{
  "type": "Feature",
  "properties": {
    "iso:country":"ES",
    "sg:address":"Calle de Vega, 35",
    "sg:city":"Chiclana De La Frontera",
    "sg:orig_category":"Procuradores",
    "sg:phone":"+34 956 53 23 60",
    "sg:postcode":"11130",
    "sg:province":"C\u00e1diz",
    "wof:name":"Delgado Cabrera Jose Francisco",
    "wof:placetype":"venue"
},
  "geometry": {"coordinates":[-6.1492757797,36.4197387695],"type":"Point"}
}