{
  "type": "Feature",
  "properties": {
    "iso:country":"ES",
    "sg:address":"Avgd Primer De Maig, 101",
    "sg:city":"Paterna",
    "sg:orig_category":"Molduras, Junquillos, Listones Y Molduras Perforadas",
    "sg:phone":"+34 961 37 26 18",
    "sg:postcode":"46980",
    "sg:province":"Valencia",
    "wof:name":"Ortiz Martinez Ana",
    "wof:placetype":"venue"
},
  "geometry": {"coordinates":[-0.4428490102,39.5088386536],"type":"Point"}
}