{
  "type": "Feature",
  "properties": {
    "iso:country":"ES",
    "sg:address":"Camino De Coin, S/n",
    "sg:city":"Mijas Costa",
    "sg:orig_category":"Comercio De Piezas De Recambio Y De Accesorios De Veh\u00cdculos, Veh\u00cdculos Industriales",
    "sg:phone":"+34 952 58 87 56",
    "sg:postcode":"29649",
    "sg:province":"M\u00e1laga",
    "wof:name":"Autorrecambios Hermanos Gomez Pleguezuelos S.a.",
    "wof:placetype":"venue"
},
  "geometry": {"coordinates":[-4.7278642654,36.4931106567],"type":"Point"}
}