{
  "type": "Feature",
  "properties": {
    "iso:country":"ES",
    "sg:address":"Cami Vileta (la), 183",
    "sg:city":"Vileta",
    "sg:orig_category":"Iglesia Cat\u00d3lica",
    "sg:phone":"+34 971 79 34 26",
    "sg:postcode":"07011",
    "sg:province":"Islas Baleares",
    "wof:name":"Obispado De Mallorca",
    "wof:placetype":"venue"
},
  "geometry": {"coordinates":[2.6160879135,39.5949134827],"type":"Point"}
}