{
  "type": "Feature",
  "properties": {
    "iso:country":"ES",
    "sg:address":"Av. Rebullon, 42",
    "sg:city":"Mos",
    "sg:orig_category":"Adaptaciones, Acondicionamientos Especiales Para Veh\u00cdculos, Veh\u00cdculos Industriales",
    "sg:phone":"+34 986 48 68 80",
    "sg:postcode":"36416",
    "sg:province":"Pontevedra",
    "wof:name":"Soyfer S.l.",
    "wof:placetype":"venue"
},
  "geometry": {"coordinates":[-8.6643791199,42.2048416138],"type":"Point"}
}