{
  "type": "Feature",
  "properties": {
    "addr:full":"Calle de Galera, 2 Valladolid Valladolid 47002",
    "addr:housenumber":"2",
    "addr:postcode":"47002",
    "addr:street":"Calle De Galera",
    "iso:country":"ES",
    "sg:address":"Calle de Galera, 2",
    "sg:city":"Valladolid",
    "sg:orig_category":"Internados & Ense\u00d1anza Privada",
    "sg:phone":"+34 983 39 35 33",
    "sg:postcode":"47002",
    "sg:province":"Valladolid",
    "wof:name":"Institucion Teresiana Asociacion Civil",
    "wof:placetype":"venue"
},
  "geometry": {"coordinates":[-4.7242698669,41.6506462097],"type":"Point"}
}