{
  "type": "Feature",
  "properties": {
    "iso:country":"ES",
    "sg:address":"Pase Zorrilla, 91",
    "sg:city":"Valladolid",
    "sg:orig_category":"Bancos",
    "sg:phone":"+34 983 23 61 93",
    "sg:postcode":"47008",
    "sg:province":"Valladolid",
    "wof:name":"Banco De Castilla",
    "wof:placetype":"venue"
},
  "geometry": {"coordinates":[-4.7927489281,41.6193618774],"type":"Point"}
}