{
  "type": "Feature",
  "properties": {
    "addr:full":"Cami Coanegra, S/n Santa Maria Del Cami Islas Baleares 07320",
    "addr:postcode":"07320",
    "addr:street":"Coanegra S / N;Islas",
    "iso:country":"ES",
    "sg:address":"Cami Coanegra, S/n",
    "sg:city":"Santa Maria Del Cami",
    "sg:orig_category":"Productores Recolectores, Venta Directa De Vinos",
    "sg:phone":"+34 971 14 00 86",
    "sg:postcode":"07320",
    "sg:province":"Islas Baleares",
    "wof:name":"Bodegues Macia Batle S.l.",
    "wof:placetype":"venue"
},
  "geometry": {"coordinates":[2.7689518929,39.6631164551],"type":"Point"}
}