{
  "type": "Feature",
  "properties": {
    "iso:country":"ES",
    "sg:address":"Calle de Virgen (la), S/n",
    "sg:city":"Terriente",
    "sg:orig_category":"Plomeros",
    "sg:phone":"+34 978 70 51 77",
    "sg:postcode":"44120",
    "sg:province":"Teruel",
    "wof:name":"Manuel Martines Garcia Y Jose Luis Martinez Garcia Cdad.",
    "wof:placetype":"venue"
},
  "geometry": {"coordinates":[-1.5025789738,40.2971916199],"type":"Point"}
}