{
  "type": "Feature",
  "properties": {
    "iso:country":"ES",
    "sg:address":"Calle de Partera Leonorita, 13",
    "sg:city":"San Fernando",
    "sg:orig_category":"Chapister\u00cda",
    "sg:phone":"+34 928 76 72 26",
    "sg:postcode":"35100",
    "sg:province":"Las Palmas",
    "sg:website":"www.jjbeach.net",
    "wof:name":"Sarde\u00f1a De Negris Jose Roberto",
    "wof:placetype":"venue"
},
  "geometry": {"coordinates":[-15.5842504501,28.0904903412],"type":"Point"}
}