{
  "type": "Feature",
  "properties": {
    "iso:country":"ES",
    "sg:address":"Cmno Tximilarre, 5",
    "sg:city":"Kurtzea",
    "sg:orig_category":"Productos Qu\u00cdmicos (fabricaci\u00d3n, Al Por Mayor)",
    "sg:phone":"+34 944 56 77 15",
    "sg:postcode":"48960",
    "sg:province":"Vizcaya",
    "wof:name":"Oscar Ruben Calero De Diago-eunice Chinarro Lucas C.b.",
    "wof:placetype":"venue"
},
  "geometry": {"coordinates":[-2.8470389843,43.2298049927],"type":"Point"}
}