{
  "type": "Feature",
  "properties": {
    "addr:full":"Calle de Carmelo Gil Doctores, 4 Bilbao Vizcaya 48012",
    "addr:housenumber":"4",
    "addr:postcode":"48012",
    "addr:street":"Calle De Carmelo Gil Doctores",
    "iso:country":"ES",
    "sg:address":"Calle de Carmelo Gil Doctores, 4",
    "sg:city":"Bilbao",
    "sg:orig_category":"Comercio De Piezas De Recambio Y De Accesorios De Veh\u00cdculos, Veh\u00cdculos Industriales",
    "sg:phone":"+34 944 43 53 08",
    "sg:postcode":"48012",
    "sg:province":"Vizcaya",
    "wof:name":"Auto Industrial Basconia S.a.",
    "wof:placetype":"venue"
},
  "geometry": {"coordinates":[-2.9400260448,43.2570838928],"type":"Point"}
}