{
  "type": "Feature",
  "properties": {
    "addr:full":"Calle de Diego Cao, 11 Aljorra Murcia 30390",
    "addr:housenumber":"11",
    "addr:postcode":"30390",
    "addr:street":"Calle De Diego Cao",
    "iso:country":"ES",
    "sg:address":"Calle de Diego Cao, 11",
    "sg:city":"Aljorra",
    "sg:orig_category":"Promotores Constructores",
    "sg:phone":"+34 968 55 87 48",
    "sg:postcode":"30390",
    "sg:province":"Murcia",
    "wof:name":"Obras Caminer S.l.",
    "wof:placetype":"venue"
},
  "geometry": {"coordinates":[-1.0684921741,37.6929244995],"type":"Point"}
}