{
  "type": "Feature",
  "properties": {
    "addr:full":"Avda Entrepinos, 57 Eliana Valencia 46183",
    "addr:housenumber":"57",
    "addr:postcode":"46183",
    "addr:street":"Avda Entrepinos",
    "iso:country":"ES",
    "sg:address":"Avda Entrepinos, 57",
    "sg:city":"Eliana",
    "sg:orig_category":"Electricidad: Instaladores",
    "sg:phone":"+34 962 75 87 78",
    "sg:postcode":"46183",
    "sg:province":"Valencia",
    "wof:name":"Barbancho Murillo Juan Manuel",
    "wof:placetype":"venue"
},
  "geometry": {"coordinates":[-0.5123710036,39.5484657288],"type":"Point"}
}