{
  "type": "Feature",
  "properties": {
    "addr:full":"Calle de Caleros, 5 Luarca Asturias 33700",
    "addr:housenumber":"5",
    "addr:postcode":"33700",
    "addr:street":"Calle De Caleros",
    "iso:country":"ES",
    "sg:address":"Calle de Caleros, 5",
    "sg:city":"Luarca",
    "sg:orig_category":"Abogados",
    "sg:phone":"+34 985 47 07 40",
    "sg:postcode":"33700",
    "sg:province":"Asturias",
    "wof:name":"Saez Valdes Pablo",
    "wof:placetype":"venue"
},
  "geometry": {"coordinates":[-6.5363297462,43.5438613892],"type":"Point"}
}