{
  "type": "Feature",
  "properties": {
    "iso:country":"ES",
    "sg:address":"Carrer de Quatre De Novembre, 18",
    "sg:city":"Poligon Industrial De Can Valero",
    "sg:orig_category":"Fabricaci\u00d3n De Bibliotecas Y Estanter\u00cdas",
    "sg:phone":"+34 971 75 21 32",
    "sg:postcode":"07011",
    "sg:province":"Islas Baleares",
    "sg:website":"www.mecalux.com",
    "wof:name":"Domer S.a.",
    "wof:placetype":"venue"
},
  "geometry": {"coordinates":[2.6205170155,39.5930747986],"type":"Point"}
}