{
  "type": "Feature",
  "properties": {
    "iso:country":"ES",
    "sg:address":"Carrer de Llinars, 56",
    "sg:city":"Cornella Llobregat",
    "sg:orig_category":"Peluquer\u00cdas, Peluquer\u00cda Mixta",
    "sg:phone":"+34 933 76 22 49",
    "sg:postcode":"08940",
    "sg:province":"Barcelona",
    "wof:name":"Dolo Chillon Miriam",
    "wof:placetype":"venue"
},
  "geometry": {"coordinates":[2.0790300369,41.3625221252],"type":"Point"}
}