{
  "type": "Feature",
  "properties": {
    "addr:full":"Calle de Santiago, 42 Alcala Henares Madrid 28801",
    "addr:housenumber":"42",
    "addr:postcode":"28801",
    "addr:street":"Calle De Santiago",
    "iso:country":"ES",
    "sg:address":"Calle de Santiago, 42",
    "sg:city":"Alcala Henares",
    "sg:orig_category":"Barbacoas Y Accesorios",
    "sg:phone":"+34 918 89 00 22",
    "sg:postcode":"28801",
    "sg:province":"Madrid",
    "wof:name":"El Buen Paladar De Santiago S.l.",
    "wof:placetype":"venue"
},
  "geometry": {"coordinates":[-3.3648738861,40.4838523865],"type":"Point"}
}