{
  "type": "Feature",
  "properties": {
    "addr:full":"Calle de San Prudencio, 9 Vitoria-gasteiz \u00c1lava 01005",
    "addr:housenumber":"9",
    "addr:postcode":"01005",
    "addr:street":"Calle De San Prudencio",
    "iso:country":"ES",
    "sg:address":"Calle de San Prudencio, 9",
    "sg:city":"Vitoria-gasteiz",
    "sg:orig_category":"Juegos Y Juguetes (al Por Menor)",
    "sg:phone":"+34 945 13 19 13",
    "sg:postcode":"01005",
    "sg:province":"\u00c1lava",
    "wof:name":"Fernandez Delgado Antonio",
    "wof:placetype":"venue"
},
  "geometry": {"coordinates":[-2.672960043,42.8442382812],"type":"Point"}
}