{
  "type": "Feature",
  "properties": {
    "iso:country":"ES",
    "sg:address":"Calle de San Sebastian, 28",
    "sg:city":"Icod De Los Vinos",
    "sg:orig_category":"Muebles, Minoristas",
    "sg:phone":"+34 922 81 06 83",
    "sg:postcode":"38430",
    "sg:province":"Santa Cruz De Tenerife",
    "wof:name":"Almacenes Iris S.l.",
    "wof:placetype":"venue"
},
  "geometry": {"coordinates":[-16.7193984985,28.3672275543],"type":"Point"}
}