{
  "type": "Feature",
  "properties": {
    "addr:full":"Cmno Cementerio, 123 Valladolid Valladolid 47011",
    "addr:housenumber":"123",
    "addr:postcode":"47011",
    "addr:street":"Cmno Cementerio",
    "iso:country":"ES",
    "sg:address":"Cmno Cementerio, 123",
    "sg:city":"Valladolid",
    "sg:orig_category":"Acero: Productos Sider\u00dargicos Y Transformados (fabricaci\u00d3n, Negocio)",
    "sg:phone":"+34 983 25 08 19",
    "sg:postcode":"47011",
    "sg:province":"Valladolid",
    "wof:name":"Cebrian Perez Miguel Antonio",
    "wof:placetype":"venue"
},
  "geometry": {"coordinates":[-4.702393055,41.6672744751],"type":"Point"}
}