{
  "type": "Feature",
  "properties": {
    "iso:country":"ES",
    "sg:address":"Calle de Santa Teresa, 10",
    "sg:city":"San Nicolas",
    "sg:orig_category":"Centros Empresariales",
    "sg:phone":"+34 968 27 50 73",
    "sg:postcode":"30005",
    "sg:province":"Murcia",
    "wof:name":"Federacion De Empresarios De Comercio De La Region De Murcia",
    "wof:placetype":"venue"
},
  "geometry": {"coordinates":[-1.1351920366,37.9872627258],"type":"Point"}
}