{
  "type": "Feature",
  "properties": {
    "iso:country":"ES",
    "sg:address":"Calle de Salustiano Olozaga, 3",
    "sg:city":"Madrid",
    "sg:orig_category":"Arte, Cultura, Edici\u00d3n",
    "sg:phone":"+34 914 26 12 70",
    "sg:postcode":"28001",
    "sg:province":"Madrid",
    "wof:name":"Atalante Ars S.l.",
    "wof:placetype":"venue"
},
  "geometry": {"coordinates":[-3.6911680698,40.4209136963],"type":"Point"}
}