{
  "type": "Feature",
  "properties": {
    "iso:country":"ES",
    "sg:address":"Pl Ramon I Cajal, 1",
    "sg:city":"Masnou",
    "sg:orig_category":"Ropa Para Se\u00d1oras Y Caballeros (al Por Menor)",
    "sg:phone":"+34 935 40 29 23",
    "sg:postcode":"08320",
    "sg:province":"Barcelona",
    "wof:name":"Diestre Estebe Antonio",
    "wof:placetype":"venue"
},
  "geometry": {"coordinates":[2.3157000542,41.4831085205],"type":"Point"}
}