{
  "type": "Feature",
  "properties": {
    "addr:full":"Carrer de Cardenal Goma, 33 Ulldecona Tarragona 43550",
    "addr:postcode":"43550",
    "addr:street":"Carrer De Cardenal Goma 33",
    "iso:country":"ES",
    "sg:address":"Carrer de Cardenal Goma, 33",
    "sg:city":"Ulldecona",
    "sg:orig_category":"T\u00c9cnicos Veterinarios",
    "sg:phone":"+34 977 72 04 70",
    "sg:postcode":"43550",
    "sg:province":"Tarragona",
    "wof:name":"Vericat Forcadell Alejandro",
    "wof:placetype":"venue"
},
  "geometry": {"coordinates":[0.4436790049,40.5974121094],"type":"Point"}
}