{
  "type": "Feature",
  "properties": {
    "addr:full":"Calle de Pe\u00d1uelas, 36 Madrid Madrid 28005",
    "addr:housenumber":"36",
    "addr:postcode":"madrid;28005",
    "addr:street":"Calle De Pen\u0303Uelas",
    "iso:country":"ES",
    "sg:address":"Calle de Pe\u00d1uelas, 36",
    "sg:city":"Madrid",
    "sg:orig_category":"Abogados",
    "sg:phone":"+34 915 17 26 49",
    "sg:postcode":"28005",
    "sg:province":"Madrid",
    "wof:name":"Andres Alvez Rafael",
    "wof:placetype":"venue"
},
  "geometry": {"coordinates":[-3.7029128075,40.4015769958],"type":"Point"}
}