{
  "type": "Feature",
  "properties": {
    "iso:country":"ES",
    "sg:address":"Calle de Eugenia Del Pozo, 14",
    "sg:city":"Pozuelo De Alarcon",
    "sg:orig_category":"Multimedia: Servicios En L\u00cdnea, Acceso En L\u00cdnea, Cd",
    "sg:phone":"+34 917 99 09 13",
    "sg:postcode":"28224",
    "sg:province":"Madrid",
    "wof:name":"Personas Y Tecnicas Multimedia S.l.",
    "wof:placetype":"venue"
},
  "geometry": {"coordinates":[-3.7963666916,40.4569358826],"type":"Point"}
}