{
  "type": "Feature",
  "properties": {
    "addr:full":"Calle de Alberto Leon Peralta, 13 Madrid Madrid 28036",
    "addr:housenumber":"13",
    "addr:postcode":"madrid;28036",
    "addr:street":"Calle De Alberto Leon Peralta",
    "iso:country":"ES",
    "sg:address":"Calle de Alberto Leon Peralta, 13",
    "sg:city":"Madrid",
    "sg:orig_category":"Agencias De Modelos",
    "sg:phone":"+34 913 45 60 80",
    "sg:postcode":"28036",
    "sg:province":"Madrid",
    "wof:name":"Just Moda S.l.",
    "wof:placetype":"venue"
},
  "geometry": {"coordinates":[-3.6813931465,40.4694671631],"type":"Point"}
}