{
  "type": "Feature",
  "properties": {
    "iso:country":"ES",
    "sg:address":"Calle de Mayor, 15",
    "sg:city":"Pe\u00e7aflor De Hornija",
    "sg:orig_category":"Cajas Para Embalar",
    "sg:phone":"+34 983 56 50 48",
    "sg:postcode":"47640",
    "sg:province":"Valladolid",
    "wof:name":"Caja Rural Del Duero",
    "wof:placetype":"venue"
},
  "geometry": {"coordinates":[-4.9827528,41.7115364075],"type":"Point"}
}