{
  "type": "Feature",
  "properties": {
    "iso:country":"ES",
    "sg:address":"Calle de Antonio Lopez, 36",
    "sg:city":"Madrid",
    "sg:orig_category":"Fabricaci\u00d3n De Sobres, Bolsas Y Fundas",
    "sg:phone":"+34 915 65 21 81",
    "sg:postcode":"28019",
    "sg:province":"Madrid",
    "wof:name":"Leal Santos Maria Del Carmen",
    "wof:placetype":"venue"
},
  "geometry": {"coordinates":[-3.7121217251,40.3960037231],"type":"Point"}
}