{
  "type": "Feature",
  "properties": {
    "addr:full":"Carrer de Annibal, 28 Barcelona Barcelona 08004",
    "addr:housenumber":"28",
    "addr:postcode":"08004",
    "addr:street":"Carrer De Annibal",
    "iso:country":"ES",
    "sg:address":"Carrer de Annibal, 28",
    "sg:city":"Barcelona",
    "sg:orig_category":"Empresarios Y Productoras De Espect\u00c1culos",
    "sg:phone":"+34 934 41 78 65",
    "sg:postcode":"08004",
    "sg:province":"Barcelona",
    "sg:website":"www.perpoc.com",
    "wof:name":"Titelles Per Poc S.l",
    "wof:placetype":"venue"
},
  "geometry": {"coordinates":[2.1605420113,41.3721809387],"type":"Point"}
}