{
  "type": "Feature",
  "properties": {
    "addr:full":"Salitre, S/n Nijar Almer\u00eda 04100",
    "addr:housenumber":"s / n",
    "addr:postcode":"04100",
    "addr:street":"Salitre;Almeri\u0301A",
    "iso:country":"ES",
    "sg:address":"Salitre, S/n",
    "sg:city":"Nijar",
    "sg:orig_category":"Centros De Educaci\u00d3n Especial",
    "sg:phone":"+34 950 36 04 02",
    "sg:postcode":"04100",
    "sg:province":"Almer\u00eda",
    "wof:name":"Junta De Andalucia",
    "wof:placetype":"venue"
},
  "geometry": {"coordinates":[-2.2065095901,36.965763092],"type":"Point"}
}