{
  "type": "Feature",
  "properties": {
    "addr:full":"Pje Llano De La Sardina, S/n Genilla C\u00f3rdoba 14816",
    "addr:housenumber":"s",
    "addr:postcode":"14816",
    "addr:street":"Pje Llano De La Sardina;/ N Genilla Co\u0301Rdoba",
    "iso:country":"ES",
    "sg:address":"Pje Llano De La Sardina, S/n",
    "sg:city":"Genilla",
    "sg:orig_category":"Promotores Constructores",
    "sg:phone":"+34 957 54 31 19",
    "sg:postcode":"14816",
    "sg:province":"C\u00f3rdoba",
    "wof:name":"Hermanos Grande Torres S.l.",
    "wof:placetype":"venue"
},
  "geometry": {"coordinates":[-4.1533799171,37.4520111084],"type":"Point"}
}