{
  "type": "Feature",
  "properties": {
    "addr:full":"Refingoi, 14 Refingoi Lugo 27825",
    "addr:housenumber":"14",
    "addr:postcode":"27825",
    "addr:street":"Refingoi",
    "iso:country":"ES",
    "sg:address":"Refingoi, 14",
    "sg:city":"Refingoi",
    "sg:orig_category":"Bebidas",
    "sg:phone":"+34 982 51 14 76",
    "sg:postcode":"27825",
    "sg:province":"Lugo",
    "wof:name":"Distribuciones Villares Y Barro S.l.",
    "wof:placetype":"venue"
},
  "geometry": {"coordinates":[-7.5910038948,43.3122558594],"type":"Point"}
}