{
  "type": "Feature",
  "properties": {
    "iso:country":"ES",
    "sg:address":"Carr Santa Eugenia, 50",
    "sg:city":"Girona",
    "sg:orig_category":"Fabrica De Charcuter\u00cda",
    "sg:phone":"+34 972 21 96 30",
    "sg:postcode":"17005",
    "sg:province":"Girona",
    "wof:name":"Martin Gonzalez Julio",
    "wof:placetype":"venue"
},
  "geometry": {"coordinates":[2.8145470619,41.9806861877],"type":"Point"}
}