{
  "type": "Feature",
  "properties": {
    "iso:country":"ES",
    "sg:address":"Carrer de Valencia, 512",
    "sg:city":"Barcelona",
    "sg:orig_category":"Peluqueros: De Se\u00d1oras",
    "sg:phone":"+34 932 31 27 05",
    "sg:postcode":"08013",
    "sg:province":"Barcelona",
    "wof:name":"Lacambra Torres Maria Carmen",
    "wof:placetype":"venue"
},
  "geometry": {"coordinates":[2.1802229881,41.4052352905],"type":"Point"}
}