{
  "type": "Feature",
  "properties": {
    "iso:country":"ES",
    "sg:address":"Calle de Puente Tablas, 2",
    "sg:city":"Zaragoza",
    "sg:orig_category":"Molduras, Junquillos, Listones Y Molduras Perforadas",
    "sg:phone":"+34 976 29 39 21",
    "sg:postcode":"50014",
    "sg:province":"Zaragoza",
    "wof:name":"Garcia Garcia Carlos",
    "wof:placetype":"venue"
},
  "geometry": {"coordinates":[-0.8705360293,41.6579093933],"type":"Point"}
}