{
  "type": "Feature",
  "properties": {
    "iso:country":"ES",
    "sg:address":"Calle de Juan Arnela, 20",
    "sg:city":"Garrovilla",
    "sg:orig_category":"Aguas (distribuci\u00d3n, Servicios)",
    "sg:phone":"+34 924 33 51 34",
    "sg:postcode":"06870",
    "sg:province":"Badajoz",
    "wof:name":"Aquagest",
    "wof:placetype":"venue"
},
  "geometry": {"coordinates":[-6.4771504402,38.9212532043],"type":"Point"}
}