{
  "type": "Feature",
  "properties": {
    "iso:country":"ES",
    "sg:address":"Carrer de Valencia, 546",
    "sg:city":"Barcelona",
    "sg:orig_category":"Bisuter\u00cda, Joyer\u00cda, Relojer\u00cda (al Por Menor)",
    "sg:phone":"+34 932 31 80 36",
    "sg:postcode":"08013",
    "sg:province":"Barcelona",
    "wof:name":"Gonzalez Moragues Maria Mercedes",
    "wof:placetype":"venue"
},
  "geometry": {"coordinates":[2.1822190285,41.4067077637],"type":"Point"}
}