{
  "type": "Feature",
  "properties": {
    "iso:country":"ES",
    "sg:address":"Calle de Campanario, 3",
    "sg:city":"Cajar",
    "sg:orig_category":"Ense\u00d1anza, Formaci\u00d3n Profesional: Aprendizaje",
    "sg:phone":"+34 958 50 15 05",
    "sg:postcode":"18198",
    "sg:province":"Granada",
    "wof:name":"Ayuntamiento De Cajar",
    "wof:placetype":"venue"
},
  "geometry": {"coordinates":[-3.5700905323,37.1344261169],"type":"Point"}
}