{
  "type": "Feature",
  "properties": {
    "addr:full":"Avda Emilio Hurtado, S/n Le\u00f3n Le\u00f3n 24007",
    "addr:housenumber":"s",
    "addr:postcode":"24007",
    "addr:street":"Avda Emilio Hurtado;/ N Leo\u0301N Leo\u0301N",
    "iso:country":"ES",
    "sg:address":"Avda Emilio Hurtado, S/n",
    "sg:city":"Le\u00f3n",
    "sg:orig_category":"Internados & Ense\u00d1anza Privada",
    "sg:phone":"+34 987 22 34 34",
    "sg:postcode":"24007",
    "sg:province":"Le\u00f3n",
    "sg:website":"www.rehurtado.com",
    "wof:name":"A.i.e.cogefsa Y 1995 Adrima 2000",
    "wof:placetype":"venue"
},
  "geometry": {"coordinates":[-5.5607209206,42.6117172241],"type":"Point"}
}