{
  "type": "Feature",
  "properties": {
    "addr:full":"Po Enamorados, S/n Iru\u00f1a Navarra 31014",
    "addr:housenumber":"s / n",
    "addr:postcode":"31014",
    "addr:street":"Enamorados",
    "iso:country":"ES",
    "sg:address":"Po Enamorados, S/n",
    "sg:city":"Iru\u00f1a",
    "sg:orig_category":"Molduras, Junquillos, Listones Y Molduras Perforadas",
    "sg:phone":"+34 948 14 92 29",
    "sg:postcode":"31014",
    "sg:province":"Navarra",
    "wof:name":"Astiz Lekuona Cesar Manuel Oscar",
    "wof:placetype":"venue"
},
  "geometry": {"coordinates":[-1.6493531466,42.8251419067],"type":"Point"}
}