{
  "type": "Feature",
  "properties": {
    "addr:full":"Carrer de Casanova, 36 Barcelona Barcelona 08011",
    "addr:housenumber":"36",
    "addr:postcode":"08011",
    "addr:street":"Carrer De Casanova",
    "iso:country":"ES",
    "sg:address":"Carrer de Casanova, 36",
    "sg:city":"Barcelona",
    "sg:orig_category":"Asociaciones, Organismos Culturales Y Socioeducativos",
    "sg:phone":"+34 934 53 57 74",
    "sg:postcode":"08011",
    "sg:province":"Barcelona",
    "wof:name":"Agrupacio Formacio Permanent D'aules Gent Gran",
    "wof:placetype":"venue"
},
  "geometry": {"coordinates":[2.1610693932,41.3837127686],"type":"Point"}
}