{
  "type": "Feature",
  "properties": {
    "addr:full":"Anglada, 13 Vielha Lleida 25530",
    "addr:housenumber":"13",
    "addr:postcode":"25530",
    "addr:street":"Anglada",
    "iso:country":"ES",
    "sg:address":"Anglada, 13",
    "sg:city":"Vielha",
    "sg:orig_category":"Art\u00cdculos De Decoraci\u00d3n",
    "sg:phone":"+34 973 64 08 51",
    "sg:postcode":"25530",
    "sg:province":"Lleida",
    "wof:name":"Caubet Teresa Carmen",
    "wof:placetype":"venue"
},
  "geometry": {"coordinates":[0.7932230234,42.7046165466],"type":"Point"}
}