{
  "type": "Feature",
  "properties": {
    "iso:country":"ES",
    "sg:address":"Carrer de Trafalgar, 43",
    "sg:city":"Barcelona",
    "sg:orig_category":"Ropa Para Se\u00d1oras Y Caballeros (al Por Menor)",
    "sg:phone":"+34 933 10 06 48",
    "sg:postcode":"08010",
    "sg:province":"Barcelona",
    "wof:name":"Ang  Wenchuny",
    "wof:placetype":"venue"
},
  "geometry": {"coordinates":[2.1776835918,41.3902549744],"type":"Point"}
}