{
  "type": "Feature",
  "properties": {
    "addr:full":"Carr Molins, 40 Almenara Castell\u00f3n 12590",
    "addr:housenumber":"40",
    "addr:postcode":"12590",
    "addr:street":"Carr Molins",
    "iso:country":"ES",
    "sg:address":"Carr Molins, 40",
    "sg:city":"Almenara",
    "sg:orig_category":"Cl\u00cdnicas Dentales",
    "sg:phone":"+34 962 61 01 01",
    "sg:postcode":"12590",
    "sg:province":"Castell\u00f3n",
    "wof:name":"Gabinete Estomatologico Almenara S.l.",
    "wof:placetype":"venue"
},
  "geometry": {"coordinates":[-0.2252819985,39.7522544861],"type":"Point"}
}