{
  "type": "Feature",
  "properties": {
    "addr:full":"Cra. Cardona, 20 Callus Barcelona 08262",
    "addr:housenumber":"20",
    "addr:postcode":"08262",
    "addr:street":"Cardona;Barcelona",
    "iso:country":"ES",
    "sg:address":"Cra. Cardona, 20",
    "sg:city":"Callus",
    "sg:orig_category":"Material Y Suministros Para Perforaciones, Sondeos",
    "sg:phone":"+34 938 36 02 37",
    "sg:postcode":"08262",
    "sg:province":"Barcelona",
    "wof:name":"Esquius Selleres Moises",
    "wof:placetype":"venue"
},
  "geometry": {"coordinates":[1.783074975,41.7831039429],"type":"Point"}
}