{
  "type": "Feature",
  "properties": {
    "addr:full":"Penaporrin, S/n Loimil Pontevedra 36588",
    "addr:postcode":"36588",
    "addr:street":"Penaporrin S / N",
    "iso:country":"ES",
    "sg:address":"Penaporrin, S/n",
    "sg:city":"Loimil",
    "sg:orig_category":"Mudanzas",
    "sg:phone":"+34 986 58 78 19",
    "sg:postcode":"36588",
    "sg:province":"Pontevedra",
    "sg:website":"www.la-red.com/collazo",
    "wof:name":"Mudanzas Collazo S.l.",
    "wof:placetype":"venue"
},
  "geometry": {"coordinates":[-8.5255689621,42.6920852661],"type":"Point"}
}