{
  "type": "Feature",
  "properties": {
    "iso:country":"ES",
    "sg:address":"Calle de Esperanto, 8",
    "sg:city":"Malaga",
    "sg:orig_category":"Carnicer\u00cdas, Carnicer\u00cdas",
    "sg:phone":"+34 952 39 72 26",
    "sg:postcode":"29007",
    "sg:province":"M\u00e1laga",
    "wof:name":"Batista Del Rosario Juan Manuel",
    "wof:placetype":"venue"
},
  "geometry": {"coordinates":[-4.4325737953,36.7189483643],"type":"Point"}
}