{
  "type": "Feature",
  "properties": {
    "iso:country":"ES",
    "sg:address":"Calle de Cordonerias, 16",
    "sg:city":"Toledo",
    "sg:orig_category":"Sociedades, Compa\u00d1\u00cdas Aseguradoras",
    "sg:phone":"+34 925 21 07 47",
    "sg:postcode":"45001",
    "sg:province":"Toledo",
    "wof:name":"Patria Hispana S.a. De Seguros Y Reaseguros",
    "wof:placetype":"venue"
},
  "geometry": {"coordinates":[-4.0229215622,39.859161377],"type":"Point"}
}