{
  "type": "Feature",
  "properties": {
    "iso:country":"ES",
    "sg:address":"Calle de Ocho De Agosto, 14",
    "sg:city":"Pinoso",
    "sg:orig_category":"Confecci\u00d3n De Zapatos",
    "sg:phone":"+34 966 97 02 74",
    "sg:postcode":"03650",
    "sg:province":"Alicante",
    "wof:name":"Pinoso Sportshoes Sociedad Limitada",
    "wof:placetype":"venue"
},
  "geometry": {"coordinates":[-1.0409189463,38.3964805603],"type":"Point"}
}