{
  "type": "Feature",
  "properties": {
    "addr:full":"Luga Riofrio, S/n Angoren Pontevedra 36320",
    "addr:housenumber":"s / n",
    "addr:postcode":"36320",
    "addr:street":"Riofrio",
    "iso:country":"ES",
    "sg:address":"Luga Riofrio, S/n",
    "sg:city":"Angoren",
    "sg:orig_category":"Empresas De Electricidad En General",
    "sg:phone":"+34 986 45 26 89",
    "sg:postcode":"36320",
    "sg:province":"Pontevedra",
    "wof:name":"Estevez Montajes Electricos S.l",
    "wof:placetype":"venue"
},
  "geometry": {"coordinates":[-8.6428003311,42.4304618835],"type":"Point"}
}