{
  "type": "Feature",
  "properties": {
    "iso:country":"ES",
    "sg:address":"Calle de Convent, 37",
    "sg:city":"Paiporta",
    "sg:orig_category":"Arquitectos",
    "sg:phone":"+34 963 97 35 30",
    "sg:postcode":"46200",
    "sg:province":"Valencia",
    "wof:name":"Ag Arquitectura C.b.",
    "wof:placetype":"venue"
},
  "geometry": {"coordinates":[-0.4174582958,39.4267807007],"type":"Point"}
}