{
  "type": "Feature",
  "properties": {
    "addr:full":"Calle de Jardiel Poncela, 17 Alacant Alicante 03015",
    "addr:housenumber":"17",
    "addr:postcode":"03015",
    "addr:street":"Calle De Jardiel Poncela",
    "iso:country":"ES",
    "sg:address":"Calle de Jardiel Poncela, 17",
    "sg:city":"Alacant",
    "sg:orig_category":"Arquitectos",
    "sg:phone":"+34 965 15 17 15",
    "sg:postcode":"03015",
    "sg:province":"Alicante",
    "wof:name":"Garmendia Fernandez Joaquin",
    "wof:placetype":"venue"
},
  "geometry": {"coordinates":[-0.4667699933,38.3670387268],"type":"Point"}
}