{
  "type": "Feature",
  "properties": {
    "iso:country":"ES",
    "sg:address":"Calle de Mayor Principal, 21",
    "sg:city":"Palencia",
    "sg:orig_category":"\u00d3ptica: Instrumentos (fabricaci\u00d3n)",
    "sg:phone":"+34 979 74 17 80",
    "sg:postcode":"34001",
    "sg:province":"Palencia",
    "wof:name":"Ramos Opticos S. A.",
    "wof:placetype":"venue"
},
  "geometry": {"coordinates":[-4.5392618179,42.010433197],"type":"Point"}
}