{
  "type": "Feature",
  "properties": {
    "iso:country":"ES",
    "sg:address":"Calle de Lain Calvo, 27",
    "sg:city":"Burgos",
    "sg:orig_category":"Librer\u00cdas",
    "sg:phone":"+34 947 20 58 56",
    "sg:postcode":"09003",
    "sg:province":"Burgos",
    "wof:name":"Manso Urbano Javier",
    "wof:placetype":"venue"
},
  "geometry": {"coordinates":[-3.701613903,42.3425559998],"type":"Point"}
}