{
  "type": "Feature",
  "properties": {
    "addr:full":"Bo. San Antoi\u00f1o, 38 Mos Pontevedra 36415",
    "addr:housenumber":"38",
    "addr:postcode":"36415",
    "addr:street":"Bo. San Antoin\u0303O",
    "iso:country":"ES",
    "sg:address":"Bo. San Antoi\u00f1o, 38",
    "sg:city":"Mos",
    "sg:orig_category":"Servicios Gsm",
    "sg:phone":"+34 986 33 45 09",
    "sg:postcode":"36415",
    "sg:province":"Pontevedra",
    "wof:name":"Beatriz Gali\u00d1anes Ramos S.l",
    "wof:placetype":"venue"
},
  "geometry": {"coordinates":[-8.6081066132,42.201751709],"type":"Point"}
}