{
  "type": "Feature",
  "properties": {
    "iso:country":"ES",
    "sg:address":"Felechosa, S/n",
    "sg:city":"El Pino",
    "sg:orig_category":"Administradores De Bienes Y Delegados De Comunidades De Propietarios",
    "sg:phone":"+34 985 48 75 27",
    "sg:postcode":"33688",
    "sg:province":"Asturias",
    "wof:name":"Administraciones Valtrafer S.l.",
    "wof:placetype":"venue"
},
  "geometry": {"coordinates":[-5.5093975067,43.1042175293],"type":"Point"}
}