{
  "type": "Feature",
  "properties": {
    "iso:country":"ES",
    "sg:address":"Carrer de Torrent De L'olla, 23",
    "sg:city":"Barcelona",
    "sg:orig_category":"Tintorer\u00cdas, Limpieza En Seco",
    "sg:phone":"+34 932 17 17 14",
    "sg:postcode":"08012",
    "sg:province":"Barcelona",
    "wof:name":"Minit Spain S. A.",
    "wof:placetype":"venue"
},
  "geometry": {"coordinates":[2.160276413,41.3994483948],"type":"Point"}
}