{
  "type": "Feature",
  "properties": {
    "addr:full":"Calle de Amezti, 6 Algorta Vizcaya 48992",
    "addr:housenumber":"6",
    "addr:postcode":"48992",
    "addr:street":"Calle De Amezti",
    "iso:country":"ES",
    "sg:address":"Calle de Amezti, 6",
    "sg:city":"Algorta",
    "sg:orig_category":"Centros De Educaci\u00d3n Especial",
    "sg:phone":"+34 944 60 88 48",
    "sg:postcode":"48992",
    "sg:province":"Vizcaya",
    "wof:name":"Etxebarri Llaguno Nagore",
    "wof:placetype":"venue"
},
  "geometry": {"coordinates":[-3.0105071068,43.3492240906],"type":"Point"}
}