{
  "type": "Feature",
  "properties": {
    "addr:full":"Cmno Meatzeta, 5 Usansolo Vizcaya 48960",
    "addr:housenumber":"5",
    "addr:postcode":"48960",
    "addr:street":"Cmno Meatzeta",
    "iso:country":"ES",
    "sg:address":"Cmno Meatzeta, 5",
    "sg:city":"Usansolo",
    "sg:orig_category":"Empresas De Hormig\u00d3n, Hormig\u00d3n Armado Y Pretensado",
    "sg:phone":"+34 944 56 74 84",
    "sg:postcode":"48960",
    "sg:province":"Vizcaya",
    "wof:name":"Hermanos Ilardia S.l.",
    "wof:placetype":"venue"
},
  "geometry": {"coordinates":[-2.8232402802,43.2195625305],"type":"Point"}
}