{
  "type": "Feature",
  "properties": {
    "iso:country":"ES",
    "sg:address":"Alam Recalde, 34",
    "sg:city":"Bilbao",
    "sg:orig_category":"M\u00c9dicos: Cardiolog\u00cda Y Afecciones Cardiovasculares",
    "sg:phone":"+34 944 24 28 52",
    "sg:postcode":"48009",
    "sg:province":"Vizcaya",
    "wof:name":"Enrique Rodriguez Pardo Y Otros C.b.",
    "wof:placetype":"venue"
},
  "geometry": {"coordinates":[-2.9348239899,43.2638473511],"type":"Point"}
}