{
  "type": "Feature",
  "properties": {
    "iso:country":"ES",
    "sg:address":"Rebollada, S/n",
    "sg:city":"Cenero",
    "sg:orig_category":"Molduras, Junquillos, Listones Y Molduras Perforadas",
    "sg:phone":"+34 985 16 82 21",
    "sg:postcode":"33392",
    "sg:province":"Asturias",
    "wof:name":"Babio Del Valle Felipe",
    "wof:placetype":"venue"
},
  "geometry": {"coordinates":[-5.7301869392,43.493057251],"type":"Point"}
}