{
  "type": "Feature",
  "properties": {
    "addr:full":"Carr De Sant Isidre, 54 Benicarlo Castell\u00f3n 12580",
    "addr:housenumber":"54",
    "addr:postcode":"12580",
    "addr:street":"Carr De Sant Isidre",
    "iso:country":"ES",
    "sg:address":"Carr De Sant Isidre, 54",
    "sg:city":"Benicarlo",
    "sg:orig_category":"Tintorer\u00cdas, Limpieza En Seco",
    "sg:phone":"+34 964 46 02 73",
    "sg:postcode":"12580",
    "sg:province":"Castell\u00f3n",
    "wof:name":"Lluch Portoles Mari Carmen",
    "wof:placetype":"venue"
},
  "geometry": {"coordinates":[0.4042100012,40.4457893372],"type":"Point"}
}