{
  "type": "Feature",
  "properties": {
    "iso:country":"ES",
    "sg:address":"Calle de Calleja De La Fuente, 6",
    "sg:city":"Yebenes",
    "sg:orig_category":"Molduras, Junquillos, Listones Y Molduras Perforadas",
    "sg:phone":"+34 925 32 14 01",
    "sg:postcode":"45470",
    "sg:province":"Toledo",
    "wof:name":"Rodriguez Moreno Concepcion",
    "wof:placetype":"venue"
},
  "geometry": {"coordinates":[-3.8699805737,39.5817108154],"type":"Point"}
}