{
  "type": "Feature",
  "properties": {
    "iso:country":"ES",
    "sg:address":"Calle de Duque De Ahumada, 12",
    "sg:city":"Huelva",
    "sg:orig_category":"Asesor\u00cda Fiscal Y Jur\u00cddica",
    "sg:phone":"+34 959 24 75 53",
    "sg:postcode":"21004",
    "sg:province":"Huelva",
    "wof:name":"Garcia Perez Rafael Obdulio",
    "wof:placetype":"venue"
},
  "geometry": {"coordinates":[-6.9434833527,37.260925293],"type":"Point"}
}