{
  "type": "Feature",
  "properties": {
    "addr:full":"Carrer de Sor Damiana, S/n Pil.lari Islas Baleares 07608",
    "addr:housenumber":"s",
    "addr:postcode":"07608",
    "addr:street":"Carrer De Sor Damiana;/ N",
    "iso:country":"ES",
    "sg:address":"Carrer de Sor Damiana, S/n",
    "sg:city":"Pil.lari",
    "sg:orig_category":"Cajas De Ahorro",
    "sg:phone":"+34 971 74 59 56",
    "sg:postcode":"07608",
    "sg:province":"Islas Baleares",
    "wof:name":"Caixa D'estalvis I Pensions De Barcelona",
    "wof:placetype":"venue"
},
  "geometry": {"coordinates":[2.7546350956,39.5289802551],"type":"Point"}
}