{
  "type": "Feature",
  "properties": {
    "addr:full":"Calle de Lamparilla (la), 7 Pilas Sevilla 41840",
    "addr:housenumber":"7",
    "addr:postcode":"41840",
    "addr:street":"Calle De Lamparilla La",
    "iso:country":"ES",
    "sg:address":"Calle de Lamparilla (la), 7",
    "sg:city":"Pilas",
    "sg:orig_category":"Ense\u00d1anza Variada",
    "sg:phone":"+34 955 75 27 94",
    "sg:postcode":"41840",
    "sg:province":"Sevilla",
    "wof:name":"Academia La Tecla S.l.",
    "wof:placetype":"venue"
},
  "geometry": {"coordinates":[-6.2984743118,37.3047676086],"type":"Point"}
}