{
  "type": "Feature",
  "properties": {
    "iso:country":"ES",
    "sg:address":"Calle de Pintor Ribera, 4",
    "sg:city":"Madrid",
    "sg:orig_category":"Multimedia: Servicios En L\u00cdnea, Acceso En L\u00cdnea, Cd",
    "sg:phone":"+34 915 15 33 40",
    "sg:postcode":"28016",
    "sg:province":"Madrid",
    "sg:website":"www.tierradigital.es",
    "wof:name":"Tierra Digital S.l.",
    "wof:placetype":"venue"
},
  "geometry": {"coordinates":[-3.6707983017,40.4544448853],"type":"Point"}
}