{
  "type": "Feature",
  "properties": {
    "iso:country":"ES",
    "sg:address":"Polig. San Paio De Navia, 18",
    "sg:city":"Vigo",
    "sg:orig_category":"Agencias Y Agentes Comerciales, Representantes",
    "sg:phone":"+34 986 21 38 83",
    "sg:postcode":"36213",
    "sg:province":"Pontevedra",
    "wof:name":"U T Sampaio Xviii",
    "wof:placetype":"venue"
},
  "geometry": {"coordinates":[-8.7210121155,42.1948318481],"type":"Point"}
}