{
  "type": "Feature",
  "properties": {
    "iso:country":"ES",
    "sg:address":"Avda Jose Antonio Vaca De Osma, 9",
    "sg:city":"Barco De Avila",
    "sg:orig_category":"Transporte En General",
    "sg:phone":"+34 920 34 06 38",
    "sg:postcode":"05600",
    "sg:province":"\u00c1vila",
    "wof:name":"Mena Gonzalez Antonio Jose",
    "wof:placetype":"venue"
},
  "geometry": {"coordinates":[-5.5200119019,40.3586273193],"type":"Point"}
}