{
  "type": "Feature",
  "properties": {
    "addr:full":"Ctra Estacion, 9 Bejar Salamanca 37700",
    "addr:housenumber":"9",
    "addr:postcode":"37700",
    "addr:street":"Ctra Estacion",
    "iso:country":"ES",
    "sg:address":"Ctra Estacion, 9",
    "sg:city":"Bejar",
    "sg:orig_category":"Material Y Suministros Para Veterinarios",
    "sg:phone":"+34 923 40 00 42",
    "sg:postcode":"37700",
    "sg:province":"Salamanca",
    "wof:name":"Garcia Mateos Maria Soledad",
    "wof:placetype":"venue"
},
  "geometry": {"coordinates":[-5.7728161812,40.3881263733],"type":"Point"}
}