{
  "type": "Feature",
  "properties": {
    "addr:full":"Calle de Doctor Fleming, 5 Langreo Asturias 33930",
    "addr:housenumber":"5",
    "addr:postcode":"33930",
    "addr:street":"Calle De Doctor Fleming",
    "iso:country":"ES",
    "sg:address":"Calle de Doctor Fleming, 5",
    "sg:city":"Langreo",
    "sg:orig_category":"Loter\u00cda Y T\u00d3mbola",
    "sg:phone":"+34 985 69 02 57",
    "sg:postcode":"33930",
    "sg:province":"Asturias",
    "wof:name":"Suarez Miguel Jose Maria",
    "wof:placetype":"venue"
},
  "geometry": {"coordinates":[-5.693426609,43.3088874817],"type":"Point"}
}