{
  "type": "Feature",
  "properties": {
    "iso:country":"ES",
    "sg:address":"Calle de Poza Licenciado, 41",
    "sg:city":"Bilbao",
    "sg:orig_category":"Molduras, Junquillos, Listones Y Molduras Perforadas",
    "sg:phone":"+34 944 41 30 00",
    "sg:postcode":"48011",
    "sg:province":"Vizcaya",
    "wof:name":"Merino Uriona Patricio",
    "wof:placetype":"venue"
},
  "geometry": {"coordinates":[-2.9414379597,43.2620620728],"type":"Point"}
}