{
  "type": "Feature",
  "properties": {
    "addr:full":"Calle de Cerro San Cristobal, S/n Lucena C\u00f3rdoba 14900",
    "addr:postcode":"14900",
    "addr:street":"Calle De Cerro San Cristobal S / N",
    "iso:country":"ES",
    "sg:address":"Calle de Cerro San Cristobal, S/n",
    "sg:city":"Lucena",
    "sg:orig_category":"Contenedores (mercanc\u00cdas)",
    "sg:phone":"+34 957 59 02 39",
    "sg:postcode":"14900",
    "sg:province":"C\u00f3rdoba",
    "wof:name":"Baena Lopez Francisco",
    "wof:placetype":"venue"
},
  "geometry": {"coordinates":[-4.4832401276,37.404548645],"type":"Point"}
}