{
  "type": "Feature",
  "properties": {
    "iso:country":"ES",
    "sg:address":"Calle de Toril, S/n",
    "sg:city":"Cartama",
    "sg:orig_category":"Iglesia Cat\u00d3lica",
    "sg:phone":"+34 952 42 23 57",
    "sg:postcode":"29570",
    "sg:province":"M\u00e1laga",
    "wof:name":"Parroquia De San Pedro Apostol",
    "wof:placetype":"venue"
},
  "geometry": {"coordinates":[-4.6309437752,36.7100944519],"type":"Point"}
}