{
  "type": "Feature",
  "properties": {
    "addr:full":"Ctra Medellin, Km. 0095,0 Don Benito Badajoz 06400",
    "addr:postcode":"06400",
    "addr:street":"Ctra Medellin Km. 0095,0",
    "iso:country":"ES",
    "sg:address":"Ctra Medellin, Km. 0095,0",
    "sg:city":"Don Benito",
    "sg:orig_category":"Maquinaria Para Industrias Diversas",
    "sg:phone":"+34 924 81 09 22",
    "sg:postcode":"06400",
    "sg:province":"Badajoz",
    "wof:name":"Andujar Cerrato Pedro",
    "wof:placetype":"venue"
},
  "geometry": {"coordinates":[-5.8681616783,38.959400177],"type":"Point"}
}