{
  "type": "Feature",
  "properties": {
    "iso:country":"ES",
    "sg:address":"Calle de Jazmin, 41",
    "sg:city":"Pedrera",
    "sg:orig_category":"Electrodom\u00c9sticos (fabricaci\u00d3n, Al Por Mayor)",
    "sg:phone":"+34 955 82 72 22",
    "sg:postcode":"41566",
    "sg:province":"Sevilla",
    "wof:name":"Instalaciones Hnos. Pablo Y Manuel S.l.",
    "wof:placetype":"venue"
},
  "geometry": {"coordinates":[-4.8951888084,37.2268104553],"type":"Point"}
}