{
  "type": "Feature",
  "properties": {
    "addr:full":"Carrer de Santa Rosa, 49 S. Fost Campsentelles Barcelona 08105",
    "addr:housenumber":"49",
    "addr:postcode":"08105",
    "addr:street":"Carrer De Santa Rosa",
    "iso:country":"ES",
    "sg:address":"Carrer de Santa Rosa, 49",
    "sg:city":"S. Fost Campsentelles",
    "sg:orig_category":"Cojinetes De Bolas, Agujas Y Rodillos (fabricaci\u00d3n, Al Por Mayor)",
    "sg:phone":"+34 935 70 44 77",
    "sg:postcode":"08105",
    "sg:province":"Barcelona",
    "wof:name":"Rodamac S.l.",
    "wof:placetype":"venue"
},
  "geometry": {"coordinates":[2.2212250233,41.5285606384],"type":"Point"}
}