{
  "type": "Feature",
  "properties": {
    "iso:country":"ES",
    "sg:address":"Pase Francisco Mir Berlanga, Maritimo, S/n",
    "sg:city":"Melilla",
    "sg:orig_category":"Empresas De Carpinter\u00cda De Madera",
    "sg:phone":"+34 952 67 47 80",
    "sg:postcode":"52001",
    "sg:province":"Melilla",
    "wof:name":"Alpuente Mariscal Salvador",
    "wof:placetype":"venue"
},
  "geometry": {"coordinates":[-2.9388227463,35.2932281494],"type":"Point"}
}