{
  "type": "Feature",
  "properties": {
    "addr:full":"Ctra Sant Cugat, Km. 0006,0 Barcelona Barcelona 08035",
    "addr:postcode":"08035",
    "addr:street":"Ctra Sant Cugat Km. 0006,0",
    "iso:country":"ES",
    "sg:address":"Ctra Sant Cugat, Km. 0006,0",
    "sg:city":"Barcelona",
    "sg:orig_category":"Alquiler De Casas Y Habitaciones Amuebladas",
    "sg:phone":"+34 934 17 62 55",
    "sg:postcode":"08035",
    "sg:province":"Barcelona",
    "wof:name":"Patronat De Sant Medir",
    "wof:placetype":"venue"
},
  "geometry": {"coordinates":[2.1382980347,41.4181175232],"type":"Point"}
}