{
  "type": "Feature",
  "properties": {
    "addr:full":"Cmno Guincho (el), S/n Valle De Guerra Santa Cruz De Tenerife 38270",
    "addr:postcode":"38270",
    "addr:street":"Cmno Guincho El S / N",
    "iso:country":"ES",
    "sg:address":"Cmno Guincho (el), S/n",
    "sg:city":"Valle De Guerra",
    "sg:orig_category":"Invernaderos Y Semilleros",
    "sg:phone":"+34 922 15 03 11",
    "sg:postcode":"38270",
    "sg:province":"Santa Cruz De Tenerife",
    "wof:name":"Plantas El Guincho S.l.",
    "wof:placetype":"venue"
},
  "geometry": {"coordinates":[-16.3963832855,28.5111694336],"type":"Point"}
}