{
  "type": "Feature",
  "properties": {
    "iso:country":"ES",
    "sg:address":"Avda Estacion (la), 22",
    "sg:city":"Alacant",
    "sg:orig_category":"Electricidad: Instaladores",
    "sg:phone":"+34 965 92 12 28",
    "sg:postcode":"03005",
    "sg:province":"Alicante",
    "wof:name":"Terol Valls Vicente",
    "wof:placetype":"venue"
},
  "geometry": {"coordinates":[-0.4945909977,38.3446922302],"type":"Point"}
}