{
  "type": "Feature",
  "properties": {
    "iso:country":"ES",
    "sg:address":"Trva Fatima, 26",
    "sg:city":"Osuna",
    "sg:orig_category":"Panader\u00cdas, Panader\u00cdas",
    "sg:phone":"+34 954 81 25 98",
    "sg:postcode":"41640",
    "sg:province":"Sevilla",
    "wof:name":"Reina Garcia Pedro Jose",
    "wof:placetype":"venue"
},
  "geometry": {"coordinates":[-5.107172966,37.2334976196],"type":"Point"}
}