{
  "type": "Feature",
  "properties": {
    "addr:full":"Carrer de Raval Cortines, 44 Vic Barcelona 08500",
    "addr:housenumber":"44",
    "addr:postcode":"08500",
    "addr:street":"Carrer De Raval Cortines",
    "iso:country":"ES",
    "sg:address":"Carrer de Raval Cortines, 44",
    "sg:city":"Vic",
    "sg:orig_category":"Cueros Y Pieles (al Por Mayor)",
    "sg:phone":"+34 938 86 26 11",
    "sg:postcode":"08500",
    "sg:province":"Barcelona",
    "sg:website":"www.ictnet.es/salles",
    "wof:name":"Curtidos Salles S. A.",
    "wof:placetype":"venue"
},
  "geometry": {"coordinates":[2.2681028843,41.9311523438],"type":"Point"}
}