{
  "type": "Feature",
  "properties": {
    "iso:country":"ES",
    "sg:address":"Hipica, S/n",
    "sg:city":"Labiano",
    "sg:orig_category":"Equitaci\u00d3n Y Centros De H\u00cdpica",
    "sg:phone":"+34 948 39 00 06",
    "sg:postcode":"31192",
    "sg:province":"Navarra",
    "wof:name":"Vidal Aguilo Conchita",
    "wof:placetype":"venue"
},
  "geometry": {"coordinates":[-1.6151809692,42.7892303467],"type":"Point"}
}