{
  "type": "Feature",
  "properties": {
    "iso:country":"ES",
    "sg:address":"Calle de Real De Arriba, 71",
    "sg:city":"Valverde Camino",
    "sg:orig_category":"Cueros Y Pieles (al Por Mayor)",
    "sg:phone":"+34 959 55 00 22",
    "sg:postcode":"21600",
    "sg:province":"Huelva",
    "wof:name":"Becerro Ramirez Francisco",
    "wof:placetype":"venue"
},
  "geometry": {"coordinates":[-6.7535610199,37.5752372742],"type":"Point"}
}