{
  "type": "Feature",
  "properties": {
    "iso:country":"ES",
    "sg:address":"C/ Sant Nicolau, 39",
    "sg:city":"Alcoi",
    "sg:orig_category":"Compraventa De Antig\u00dcedades",
    "sg:phone":"+34 965 54 66 38",
    "sg:postcode":"03801",
    "sg:province":"Alicante",
    "wof:name":"Miro Vispo Juan Carlos",
    "wof:placetype":"venue"
},
  "geometry": {"coordinates":[-0.4729410112,38.6961555481],"type":"Point"}
}