{
  "type": "Feature",
  "properties": {
    "addr:full":"Carrer de Pintor Mir, 16 Barcelona Barcelona 08031",
    "addr:housenumber":"16",
    "addr:postcode":"08031",
    "addr:street":"Carrer De Pintor Mir",
    "iso:country":"ES",
    "sg:address":"Carrer de Pintor Mir, 16",
    "sg:city":"Barcelona",
    "sg:orig_category":"Asociaciones, Organismos Culturales Y Socioeducativos",
    "sg:phone":"+34 933 58 37 40",
    "sg:postcode":"08031",
    "sg:province":"Barcelona",
    "wof:name":"Unio Excursionista De Catalunya Horta",
    "wof:placetype":"venue"
},
  "geometry": {"coordinates":[2.1665179729,41.428478241],"type":"Point"}
}