{
  "type": "Feature",
  "properties": {
    "iso:country":"ES",
    "sg:address":"Calle de San Francisco, 12",
    "sg:city":"Cadiz",
    "sg:orig_category":"Complementos De Vestir (al Por Menor)",
    "sg:phone":"+34 956 21 10 10",
    "sg:postcode":"11004",
    "sg:province":"C\u00e1diz",
    "wof:name":"Cosano Garcia Francisco Javier",
    "wof:placetype":"venue"
},
  "geometry": {"coordinates":[-6.2948827744,36.5337791443],"type":"Point"}
}