{
  "type": "Feature",
  "properties": {
    "iso:country":"ES",
    "sg:address":"Calle de Pandorado, S/n",
    "sg:city":"Cogorderos",
    "sg:orig_category":"Poller\u00cda Y Caza (al Por Menor)",
    "sg:phone":"+34 987 60 51 89",
    "sg:postcode":"24712",
    "sg:province":"Le\u00f3n",
    "wof:name":"Alvarez Garcia Jesus",
    "wof:placetype":"venue"
},
  "geometry": {"coordinates":[-6.0302362442,42.542263031],"type":"Point"}
}