{
  "type": "Feature",
  "properties": {
    "iso:country":"ES",
    "sg:address":"Calle de Arboli, 1",
    "sg:city":"Cadiz",
    "sg:orig_category":"Ropa Para Se\u00d1oras (al Por Menor)",
    "sg:phone":"+34 956 21 34 32",
    "sg:postcode":"11005",
    "sg:province":"C\u00e1diz",
    "wof:name":"Infante Francisco Manuel",
    "wof:placetype":"venue"
},
  "geometry": {"coordinates":[-6.2963380814,36.5305137634],"type":"Point"}
}