{
  "type": "Feature",
  "properties": {
    "iso:country":"ES",
    "sg:address":"Calle de Don Tello, 10",
    "sg:city":"Elorrio",
    "sg:orig_category":"Asociaciones Y Clubs Deportivos",
    "sg:phone":"+34 946 58 20 66",
    "sg:postcode":"48230",
    "sg:province":"Vizcaya",
    "wof:name":"Francisco Javier Ortuzar Arabiorrutia Y Miguel Angel Oregui Herrera Cdad.",
    "wof:placetype":"venue"
},
  "geometry": {"coordinates":[-2.5440034866,43.1309394836],"type":"Point"}
}