{
  "type": "Feature",
  "properties": {
    "iso:country":"ES",
    "sg:address":"Calle de Jose Maria Peman, 15",
    "sg:city":"Elda",
    "sg:orig_category":"Molduras, Junquillos, Listones Y Molduras Perforadas",
    "sg:phone":"+34 965 39 10 52",
    "sg:postcode":"03600",
    "sg:province":"Alicante",
    "wof:name":"Fuentes Gambino Joel Pascal",
    "wof:placetype":"venue"
},
  "geometry": {"coordinates":[-0.7928979993,38.4767837524],"type":"Point"}
}