{
  "type": "Feature",
  "properties": {
    "iso:country":"ES",
    "sg:address":"Calle de Ramon Y Cajal, 32",
    "sg:city":"Aguilas",
    "sg:orig_category":"Comercio, Reparaci\u00d3n De Motocicletas, Bicicletas Y Piezas Sueltas",
    "sg:phone":"+34 968 44 85 53",
    "sg:postcode":"30880",
    "sg:province":"Murcia",
    "wof:name":"Lopez Gallego Jose",
    "wof:placetype":"venue"
},
  "geometry": {"coordinates":[-1.5867290497,37.4075317383],"type":"Point"}
}