{
  "type": "Feature",
  "properties": {
    "iso:country":"ES",
    "sg:address":"Avda Paz, 198",
    "sg:city":"Yecla",
    "sg:orig_category":"Albergues",
    "sg:phone":"+34 902 42 15 21",
    "sg:postcode":"30510",
    "sg:province":"Murcia",
    "sg:website":"www.bricoralia.com",
    "wof:name":"Alberto Mu\u00f1oz Mu\u00f1oz S.l.",
    "wof:placetype":"venue"
},
  "geometry": {"coordinates":[-1.1345796585,38.6128883362],"type":"Point"}
}