{
  "type": "Feature",
  "properties": {
    "iso:country":"ES",
    "sg:address":"Avda Regne De Valencia, 32",
    "sg:city":"Valencia",
    "sg:orig_category":"Arquitectos",
    "sg:phone":"+34 963 34 94 90",
    "sg:postcode":"46005",
    "sg:province":"Valencia",
    "wof:name":"Zanon Monfort Jose Luis",
    "wof:placetype":"venue"
},
  "geometry": {"coordinates":[-0.3704093099,39.4642066956],"type":"Point"}
}