{
  "type": "Feature",
  "properties": {
    "addr:full":"Nou D'octubre, 7 Sedavi Valencia 46910",
    "addr:housenumber":"7",
    "addr:postcode":"46910",
    "addr:street":"Nou D'Octubre",
    "iso:country":"ES",
    "sg:address":"Nou D'octubre, 7",
    "sg:city":"Sedavi",
    "sg:orig_category":"Distribuci\u00d3n De Petr\u00d3leo Y Derivados",
    "sg:phone":"+34 963 96 34 56",
    "sg:postcode":"46910",
    "sg:province":"Valencia",
    "wof:name":"Cosme Torres Pilar",
    "wof:placetype":"venue"
},
  "geometry": {"coordinates":[-0.3861579895,39.4215774536],"type":"Point"}
}