{
  "type": "Feature",
  "properties": {
    "iso:country":"ES",
    "sg:address":"Marne, S/n",
    "sg:city":"Marne",
    "sg:orig_category":"Serrer\u00cdas De Madera",
    "sg:phone":"+34 987 31 20 30",
    "sg:postcode":"24226",
    "sg:province":"Le\u00f3n",
    "wof:name":"Maderas Di\u00f1eiro S.l.",
    "wof:placetype":"venue"
},
  "geometry": {"coordinates":[-5.4851689339,42.5182266235],"type":"Point"}
}