{
  "type": "Feature",
  "properties": {
    "iso:country":"ES",
    "sg:address":"Calle de Damian Parras, 6",
    "sg:city":"Arjona",
    "sg:orig_category":"Agentes Generales De Seguros",
    "sg:phone":"+34 953 52 36 12",
    "sg:postcode":"23760",
    "sg:province":"Ja\u00e9n",
    "wof:name":"Ruiz Sanchez Bartolome",
    "wof:placetype":"venue"
},
  "geometry": {"coordinates":[-4.0565171242,37.936706543],"type":"Point"}
}