{
  "type": "Feature",
  "properties": {
    "iso:country":"ES",
    "sg:address":"Calle de Andalucia, 12",
    "sg:city":"Palencia",
    "sg:orig_category":"Empresas De Vigilancia, Guardia Y Protecci\u00d3n",
    "sg:phone":"+34 979 71 11 58",
    "sg:postcode":"34004",
    "sg:province":"Palencia",
    "wof:name":"Prosegur Compa\u00f1ia De Seguridad S.a.",
    "wof:placetype":"venue"
},
  "geometry": {"coordinates":[-4.5169711113,42.0075874329],"type":"Point"}
}