{
  "type": "Feature",
  "properties": {
    "iso:country":"ES",
    "sg:address":"Calle de Ruiz Tagle, 7",
    "sg:city":"Torrelavega",
    "sg:orig_category":"Poller\u00cda Y Caza (al Por Menor)",
    "sg:phone":"+34 942 80 23 51",
    "sg:postcode":"39300",
    "sg:province":"Cantabria",
    "wof:name":"Barquin Calderon Rosario Maria",
    "wof:placetype":"venue"
},
  "geometry": {"coordinates":[-4.0496001244,43.3491706848],"type":"Point"}
}