{
  "type": "Feature",
  "properties": {
    "iso:country":"ES",
    "sg:address":"Calle de Sendin, 35",
    "sg:city":"Aranda Duero",
    "sg:orig_category":"Armer\u00cdas",
    "sg:phone":"+34 947 50 06 53",
    "sg:postcode":"09400",
    "sg:province":"Burgos",
    "wof:name":"Ballestas De Aranda S.l.",
    "wof:placetype":"venue"
},
  "geometry": {"coordinates":[-3.7041618824,41.6711807251],"type":"Point"}
}