{
  "type": "Feature",
  "properties": {
    "addr:full":"Ctra Val/barna 340, Km. 0388,0 Castellon De La Plana Castell\u00f3n 12004",
    "addr:postcode":"12004",
    "addr:street":"Ctra Val / Barna 340 Km. 0388,0",
    "iso:country":"ES",
    "sg:address":"Ctra Val/barna 340, Km. 0388,0",
    "sg:city":"Castellon De La Plana",
    "sg:orig_category":"Semiller\u00cdas",
    "sg:phone":"+34 964 20 02 63",
    "sg:postcode":"12004",
    "sg:province":"Castell\u00f3n",
    "wof:name":"Horticultura Castellon S.l.",
    "wof:placetype":"venue"
},
  "geometry": {"coordinates":[0.0330299996,40.0113639832],"type":"Point"}
}