{
  "type": "Feature",
  "properties": {
    "addr:full":"Calle de Valle Del Corneja, 1 Avila \u00c1vila 05002",
    "addr:housenumber":"1",
    "addr:postcode":"05002",
    "addr:street":"Calle De Valle Del Corneja;A\u0301Vila",
    "iso:country":"ES",
    "sg:address":"Calle de Valle Del Corneja, 1",
    "sg:city":"Avila",
    "sg:orig_category":"Abogados",
    "sg:phone":"+34 920 25 59 44",
    "sg:postcode":"05002",
    "sg:province":"\u00c1vila",
    "wof:name":"Sanchez Gomez Alfredo",
    "wof:placetype":"venue"
},
  "geometry": {"coordinates":[-4.701417923,40.6502189636],"type":"Point"}
}