{
  "type": "Feature",
  "properties": {
    "addr:full":"Av Platja, 8 Santa Margarida-salatar Girona 17480",
    "addr:housenumber":"8",
    "addr:postcode":"17480",
    "addr:street":"Av Platja",
    "iso:country":"ES",
    "sg:address":"Av Platja, 8",
    "sg:city":"Santa Margarida-salatar",
    "sg:orig_category":"Bazares, Art\u00cdculos De Limpieza Y De Cocina (al Por Menor)",
    "sg:phone":"+34 972 15 21 78",
    "sg:postcode":"17480",
    "sg:province":"Girona",
    "wof:name":"Garcia Herruzo Carlos",
    "wof:placetype":"venue"
},
  "geometry": {"coordinates":[3.1522800922,42.2632293701],"type":"Point"}
}