{
  "type": "Feature",
  "properties": {
    "iso:country":"ES",
    "sg:address":"Carr Verge Del Carme, 4",
    "sg:city":"Casc Urba",
    "sg:orig_category":"Carnicer\u00cdas, Carnicer\u00cdas",
    "sg:phone":"+34 972 12 04 19",
    "sg:postcode":"17490",
    "sg:province":"Girona",
    "wof:name":"Ruzafa Gimeno Gustavo",
    "wof:placetype":"venue"
},
  "geometry": {"coordinates":[3.1481759548,42.3640785217],"type":"Point"}
}