{
  "type": "Feature",
  "properties": {
    "addr:full":"Carrer de Joan Prim, 67 Premia Mar Barcelona 08330",
    "addr:housenumber":"67",
    "addr:postcode":"08330",
    "addr:street":"Carrer De Joan Prim",
    "iso:country":"ES",
    "sg:address":"Carrer de Joan Prim, 67",
    "sg:city":"Premia Mar",
    "sg:orig_category":"Alquiler De V\u00cddeo",
    "sg:phone":"+34 937 54 70 00",
    "sg:postcode":"08330",
    "sg:province":"Barcelona",
    "wof:name":"Siensopte S.l.",
    "wof:placetype":"venue"
},
  "geometry": {"coordinates":[2.3578529358,41.4929962158],"type":"Point"}
}