{
  "type": "Feature",
  "properties": {
    "iso:country":"ES",
    "sg:address":"Calle de San Antonio, 32",
    "sg:city":"Marbella",
    "sg:orig_category":"Transportes De Material De Construcci\u00d3n",
    "sg:phone":"+34 952 90 22 47",
    "sg:postcode":"29600",
    "sg:province":"M\u00e1laga",
    "wof:name":"Emilio Fernandez Cruz S.l.",
    "wof:placetype":"venue"
},
  "geometry": {"coordinates":[-4.8819289207,36.5135688782],"type":"Point"}
}