{
  "type": "Feature",
  "properties": {
    "iso:country":"ES",
    "sg:address":"Plaz Carbayedo Del, 31",
    "sg:city":"Aviles",
    "sg:orig_category":"Fabricaci\u00d3n, Importaci\u00d3n, Venta De Material De Telefon\u00cda, Peritelefon\u00cda",
    "sg:phone":"+34 985 56 58 99",
    "sg:postcode":"33402",
    "sg:province":"Asturias",
    "wof:name":"Garcia Gutierrez Angel Maria",
    "wof:placetype":"venue"
},
  "geometry": {"coordinates":[-5.927008152,43.5536384583],"type":"Point"}
}