{
  "type": "Feature",
  "properties": {
    "iso:country":"ES",
    "sg:address":"Avda Castilla La Mancha, S/n",
    "sg:city":"Villarejo-periesteban",
    "sg:orig_category":"Administraciones Regionales, Departamentales Y Locales",
    "sg:phone":"+34 969 19 64 00",
    "sg:postcode":"16443",
    "sg:province":"Cuenca",
    "wof:name":"Ayuntamiento De Villarejo-periesteban",
    "wof:placetype":"venue"
},
  "geometry": {"coordinates":[-2.4445297718,39.8740310669],"type":"Point"}
}