{
  "type": "Feature",
  "properties": {
    "addr:full":"Av Cavall Bernat (del), 36 Platja D'aro Girona 17250",
    "addr:housenumber":"36",
    "addr:postcode":"17250",
    "addr:street":"Av Cavall Bernat Del",
    "iso:country":"ES",
    "sg:address":"Av Cavall Bernat (del), 36",
    "sg:city":"Platja D'aro",
    "sg:orig_category":"Inmobiliaria (agencias)",
    "sg:phone":"+34 972 81 74 14",
    "sg:postcode":"17250",
    "sg:province":"Girona",
    "wof:name":"Finques Borsa S.l.",
    "wof:placetype":"venue"
},
  "geometry": {"coordinates":[3.0726904869,41.8236846924],"type":"Point"}
}