{
  "type": "Feature",
  "properties": {
    "iso:country":"ES",
    "sg:address":"Carr Diposit, 8",
    "sg:city":"Vilanova Barca",
    "sg:orig_category":"Distribuci\u00d3n De Petr\u00d3leo Y Derivados",
    "sg:phone":"+34 973 19 06 92",
    "sg:postcode":"25690",
    "sg:province":"Lleida",
    "wof:name":"Blanch Romero Veronica",
    "wof:placetype":"venue"
},
  "geometry": {"coordinates":[0.7290250063,41.6892662048],"type":"Point"}
}