{
  "type": "Feature",
  "properties": {
    "iso:country":"ES",
    "sg:address":"Calle de Larrategi, 2",
    "sg:city":"Arbulo",
    "sg:orig_category":"Centros Empresariales",
    "sg:phone":"+34 945 29 33 98",
    "sg:postcode":"01192",
    "sg:province":"\u00c1lava",
    "wof:name":"Portela Del Rio Marta",
    "wof:placetype":"venue"
},
  "geometry": {"coordinates":[-2.5449340343,42.8497543335],"type":"Point"}
}