{
  "type": "Feature",
  "properties": {
    "addr:full":"Calle de Valencia, 23 Madrid Madrid 28012",
    "addr:housenumber":"23",
    "addr:postcode":"madrid;28012",
    "addr:street":"Calle De Valencia",
    "iso:country":"ES",
    "sg:address":"Calle de Valencia, 23",
    "sg:city":"Madrid",
    "sg:orig_category":"Agentes, Concesionarios Y Sucursales De Camiones Y Veh\u00cdculos Industriales",
    "sg:phone":"+34 915 27 39 76",
    "sg:postcode":"28012",
    "sg:province":"Madrid",
    "wof:name":"Martinez Garcia Luis",
    "wof:placetype":"venue"
},
  "geometry": {"coordinates":[-3.6994180679,40.4062919617],"type":"Point"}
}