{
  "type": "Feature",
  "properties": {
    "addr:full":"Av Joan Miro, 285 Sant Agusti Islas Baleares 07015",
    "addr:housenumber":"285",
    "addr:postcode":"07015",
    "addr:street":"Av Joan Miro;Sant Agusti",
    "iso:country":"ES",
    "sg:address":"Av Joan Miro, 285",
    "sg:city":"Sant Agusti",
    "sg:orig_category":"Iglesias Cristianas Diversas",
    "sg:phone":"+34 971 70 11 10",
    "sg:postcode":"07015",
    "sg:province":"Islas Baleares",
    "wof:name":"Iglesia Evangelica Ejercito Salvacion",
    "wof:placetype":"venue"
},
  "geometry": {"coordinates":[2.6040999889,39.5524291992],"type":"Point"}
}