{
  "type": "Feature",
  "properties": {
    "addr:full":"Calle de Carrera Del Genil, 1 Granada Granada 18009",
    "addr:housenumber":"1",
    "addr:postcode":"18009",
    "addr:street":"Calle De Carrera Del Genil",
    "iso:country":"ES",
    "sg:address":"Calle de Carrera Del Genil, 1",
    "sg:city":"Granada",
    "sg:orig_category":"M\u00c9dicos: Evaluaci\u00d3n Y Tratamiento Del Dolor",
    "sg:phone":"+34 958 22 83 03",
    "sg:postcode":"18009",
    "sg:province":"Granada",
    "wof:name":"Baca Garcia Arturo",
    "wof:placetype":"venue"
},
  "geometry": {"coordinates":[-3.5979888439,37.1717376709],"type":"Point"}
}