{
  "type": "Feature",
  "properties": {
    "iso:country":"ES",
    "sg:address":"Calle de Venta De Arriba, S/n",
    "sg:city":"Olias Rey",
    "sg:orig_category":"Marroquiner\u00cda (confecci\u00d3n)",
    "sg:phone":"+34 925 49 01 20",
    "sg:postcode":"45280",
    "sg:province":"Toledo",
    "wof:name":"Criado Navas Luis",
    "wof:placetype":"venue"
},
  "geometry": {"coordinates":[-3.9896929264,39.9465789795],"type":"Point"}
}