{
  "type": "Feature",
  "properties": {
    "addr:full":"Pl Non D'octubre, 1 Ondara Alicante 03760",
    "addr:housenumber":"1",
    "addr:postcode":"03760",
    "addr:street":"Pl;D'Octubre",
    "iso:country":"ES",
    "sg:address":"Pl Non D'octubre, 1",
    "sg:city":"Ondara",
    "sg:orig_category":"Panader\u00cdas, Panader\u00cdas",
    "sg:phone":"+34 965 76 63 07",
    "sg:postcode":"03760",
    "sg:province":"Alicante",
    "wof:name":"Dolcos Victoria S.l.",
    "wof:placetype":"venue"
},
  "geometry": {"coordinates":[0.0183889996,38.8248901367],"type":"Point"}
}