{
  "type": "Feature",
  "properties": {
    "iso:country":"ES",
    "sg:address":"Calle de Corrida, 14",
    "sg:city":"Gijon",
    "sg:orig_category":"Zapatos (al Por Menor)",
    "sg:phone":"+34 985 34 71 37",
    "sg:postcode":"33206",
    "sg:province":"Asturias",
    "wof:name":"Lorenzo Marquez Y Gloria Castellanos S.l.",
    "wof:placetype":"venue"
},
  "geometry": {"coordinates":[-5.6641449928,43.5421066284],"type":"Point"}
}