{
  "type": "Feature",
  "properties": {
    "addr:full":"Calle de Torres Quevedo, 5 Reinosa Cantabria 39200",
    "addr:housenumber":"5",
    "addr:postcode":"39200",
    "addr:street":"Calle De Torres Quevedo",
    "iso:country":"ES",
    "sg:address":"Calle de Torres Quevedo, 5",
    "sg:city":"Reinosa",
    "sg:orig_category":"Abogados",
    "sg:phone":"+34 942 75 10 54",
    "sg:postcode":"39200",
    "sg:province":"Cantabria",
    "wof:name":"Estevanez Abogados S.c.",
    "wof:placetype":"venue"
},
  "geometry": {"coordinates":[-4.1398601532,42.9977302551],"type":"Point"}
}