{
  "type": "Feature",
  "properties": {
    "iso:country":"ES",
    "sg:address":"Calle de Almirante Diaz Pimienta, 4",
    "sg:city":"Santa Cruz De Tenerife",
    "sg:orig_category":"Bazares, Art\u00cdculos De Limpieza Y De Cocina (al Por Menor)",
    "sg:phone":"+34 922 20 58 10",
    "sg:postcode":"38005",
    "sg:province":"Santa Cruz De Tenerife",
    "wof:name":"Barroso Rodriguez Jose",
    "wof:placetype":"venue"
},
  "geometry": {"coordinates":[-16.2608413696,28.4603366852],"type":"Point"}
}