{
  "type": "Feature",
  "properties": {
    "addr:full":"Calle de German Loperena, 10 Remolinos Zaragoza 50637",
    "addr:housenumber":"10",
    "addr:postcode":"50637",
    "addr:street":"Calle De German Loperena",
    "iso:country":"ES",
    "sg:address":"Calle de German Loperena, 10",
    "sg:city":"Remolinos",
    "sg:orig_category":"Grafistas",
    "sg:phone":"+34 976 61 82 04",
    "sg:postcode":"50637",
    "sg:province":"Zaragoza",
    "wof:name":"Alonso Gale Hector",
    "wof:placetype":"venue"
},
  "geometry": {"coordinates":[-1.1795247793,41.8398170471],"type":"Point"}
}