{
  "type": "Feature",
  "properties": {
    "addr:full":"Rua Marques De Valladares, 20 Vigo Pontevedra 36201",
    "addr:housenumber":"20",
    "addr:postcode":"36201",
    "addr:street":"Rua Marques De Valladares",
    "iso:country":"ES",
    "sg:address":"Rua Marques De Valladares, 20",
    "sg:city":"Vigo",
    "sg:orig_category":"Fabricaci\u00d3n De Peines Y De Accesorios De Peluquer\u00cda",
    "sg:phone":"+34 986 22 13 18",
    "sg:postcode":"36201",
    "sg:province":"Pontevedra",
    "wof:name":"Colomer Beauty And Profesional Products S.l.",
    "wof:placetype":"venue"
},
  "geometry": {"coordinates":[-8.720911026,42.2381210327],"type":"Point"}
}