{
  "type": "Feature",
  "properties": {
    "addr:full":"Ctra Murcia-alicante, Km. 0045,0 Crevillent Alicante 03330",
    "addr:postcode":"03330",
    "addr:street":"Ctra Murcia-Alicante Km. 0045,0",
    "iso:country":"ES",
    "sg:address":"Ctra Murcia-alicante, Km. 0045,0",
    "sg:city":"Crevillent",
    "sg:orig_category":"Confecci\u00d3n De Zapatos",
    "sg:phone":"+34 965 40 02 24",
    "sg:postcode":"03330",
    "sg:province":"Alicante",
    "sg:website":"www.artesa-sl.com",
    "wof:name":"Manufacturas Artesa S. L.",
    "wof:placetype":"venue"
},
  "geometry": {"coordinates":[-0.8139619827,38.2384681702],"type":"Point"}
}