{
  "type": "Feature",
  "properties": {
    "iso:country":"ES",
    "sg:address":"Carr De Madrid, 4",
    "sg:city":"Benicarlo",
    "sg:orig_category":"Fabricaci\u00d3n De Juguetes Autom\u00c1ticos",
    "sg:phone":"+34 964 47 17 46",
    "sg:postcode":"12580",
    "sg:province":"Castell\u00f3n",
    "wof:name":"Macrija S. A.",
    "wof:placetype":"venue"
},
  "geometry": {"coordinates":[0.4198122919,40.4194374084],"type":"Point"}
}