{
  "type": "Feature",
  "properties": {
    "iso:country":"ES",
    "sg:address":"Calle de Quintana, 17",
    "sg:city":"Campanario",
    "sg:orig_category":"Abogados",
    "sg:phone":"+34 924 83 14 63",
    "sg:postcode":"06460",
    "sg:province":"Badajoz",
    "wof:name":"Ruiz Murillo Juan",
    "wof:placetype":"venue"
},
  "geometry": {"coordinates":[-5.6177549362,38.8617935181],"type":"Point"}
}