{
  "type": "Feature",
  "properties": {
    "addr:full":"Calle de Rioja, 130 Leganes Madrid 28915",
    "addr:housenumber":"130",
    "addr:postcode":"28915",
    "addr:street":"Calle De Rioja",
    "iso:country":"ES",
    "sg:address":"Calle de Rioja, 130",
    "sg:city":"Leganes",
    "sg:orig_category":"Retoques De Vestidos",
    "sg:phone":"+34 916 80 18 13",
    "sg:postcode":"28915",
    "sg:province":"Madrid",
    "wof:name":"Emisa Complementos S.a.",
    "wof:placetype":"venue"
},
  "geometry": {"coordinates":[-3.7494699955,40.334312439],"type":"Point"}
}