{
  "type": "Feature",
  "properties": {
    "addr:full":"Urb Mariana Pineda, S/n Algeciras C\u00e1diz 11204",
    "addr:housenumber":"s / n;ca\u0301diz",
    "addr:postcode":"11204",
    "addr:street":"Urb Mariana Pineda",
    "iso:country":"ES",
    "sg:address":"Urb Mariana Pineda, S/n",
    "sg:city":"Algeciras",
    "sg:orig_category":"Laboratorios Y Cl\u00cdnicas Veterinarias",
    "sg:phone":"+34 956 63 24 85",
    "sg:postcode":"11204",
    "sg:province":"C\u00e1diz",
    "wof:name":"Clinica Veterinaria San Bernabe",
    "wof:placetype":"venue"
},
  "geometry": {"coordinates":[-5.4567308426,36.1387939453],"type":"Point"}
}