{
  "type": "Feature",
  "properties": {
    "iso:country":"ES",
    "sg:address":"Avda Porteli\u00d1a, 12",
    "sg:city":"Porteli\u00d1a",
    "sg:orig_category":"Peluqueros: De Se\u00d1oras",
    "sg:phone":"+34 986 87 34 95",
    "sg:postcode":"36163",
    "sg:province":"Pontevedra",
    "wof:name":"Angeles Belleza S.l.",
    "wof:placetype":"venue"
},
  "geometry": {"coordinates":[-8.4136533737,42.4107017517],"type":"Point"}
}