{
  "type": "Feature",
  "properties": {
    "addr:full":"Urb. Os Rueiros A (illa Toxa), 23 Grove Pontevedra 36991",
    "addr:housenumber":"23",
    "addr:postcode":"36991",
    "addr:street":"Toxa;Grove Pontevedra",
    "iso:country":"ES",
    "sg:address":"Urb. Os Rueiros A (illa Toxa), 23",
    "sg:city":"Grove",
    "sg:orig_category":"M\u00c9dicos: Ginecolog\u00cda Y Obstetricia",
    "sg:phone":"+34 986 73 06 72",
    "sg:postcode":"36991",
    "sg:province":"Pontevedra",
    "wof:name":"Servicios De Ginecologia S.l",
    "wof:placetype":"venue"
},
  "geometry": {"coordinates":[-8.8467092514,42.4828300476],"type":"Point"}
}