{
  "type": "Feature",
  "properties": {
    "addr:full":"Av Juan Gil - Albert, 2 Alcoi Alicante 03804",
    "addr:housenumber":"2",
    "addr:postcode":"03804",
    "addr:street":"Av Juan Gil Albert",
    "iso:country":"ES",
    "sg:address":"Av Juan Gil - Albert, 2",
    "sg:city":"Alcoi",
    "sg:orig_category":"M\u00c9dicos: Cirug\u00cda General",
    "sg:phone":"+34 965 52 28 68",
    "sg:postcode":"03804",
    "sg:province":"Alicante",
    "wof:name":"Rio Barcenilla Juan Del",
    "wof:placetype":"venue"
},
  "geometry": {"coordinates":[-0.4744189978,38.7042999268],"type":"Point"}
}