{
  "type": "Feature",
  "properties": {
    "iso:country":"ES",
    "sg:address":"Calle de Juan Agapito Y Revilla, 22",
    "sg:city":"Valladolid",
    "sg:orig_category":"Transporte En General",
    "sg:phone":"+34 983 30 21 76",
    "sg:postcode":"47004",
    "sg:province":"Valladolid",
    "wof:name":"Herrero Fernandez Jose Carlos",
    "wof:placetype":"venue"
},
  "geometry": {"coordinates":[-4.7216181755,41.6466293335],"type":"Point"}
}