{
  "type": "Feature",
  "properties": {
    "addr:full":"Carr Josep Segura Farre, S/n Lleida Lleida 25191",
    "addr:housenumber":"s / n",
    "addr:postcode":"25191",
    "addr:street":"Carr Josep Segura Farre",
    "iso:country":"ES",
    "sg:address":"Carr Josep Segura Farre, S/n",
    "sg:city":"Lleida",
    "sg:orig_category":"Negocio De Metales No Ferrosos",
    "sg:phone":"+34 973 20 02 12",
    "sg:postcode":"25191",
    "sg:province":"Lleida",
    "wof:name":"Alacer Mas S.a.",
    "wof:placetype":"venue"
},
  "geometry": {"coordinates":[0.6643906832,41.6246604919],"type":"Point"}
}