{
  "type": "Feature",
  "properties": {
    "addr:full":"Carrer de Sors, 29 Barcelona Barcelona 08024",
    "addr:housenumber":"29",
    "addr:postcode":"08024",
    "addr:street":"Carrer De Sors",
    "iso:country":"ES",
    "sg:address":"Carrer de Sors, 29",
    "sg:city":"Barcelona",
    "sg:orig_category":"Alumbrados",
    "sg:phone":"+34 932 84 95 66",
    "sg:postcode":"08024",
    "sg:province":"Barcelona",
    "wof:name":"Ma\u00f1e Vidal Fernando",
    "wof:placetype":"venue"
},
  "geometry": {"coordinates":[2.1580679417,41.4093437195],"type":"Point"}
}