{
  "type": "Feature",
  "properties": {
    "addr:full":"Carrer de Mayor, 10 Guardamar Segura Alicante 03140",
    "addr:housenumber":"10",
    "addr:postcode":"03140",
    "addr:street":"Carrer De Mayor",
    "iso:country":"ES",
    "sg:address":"Carrer de Mayor, 10",
    "sg:city":"Guardamar Segura",
    "sg:orig_category":"Asesor\u00cda Sobre Comunicaci\u00d3n De Empresas",
    "sg:phone":"+34 965 72 75 29",
    "sg:postcode":"03140",
    "sg:province":"Alicante",
    "wof:name":"G.a. Ros Asesores S.l.",
    "wof:placetype":"venue"
},
  "geometry": {"coordinates":[-0.6547287703,38.0907745361],"type":"Point"}
}