{
  "type": "Feature",
  "properties": {
    "addr:full":"San Miguel, 32 San Miguel Asturias 33188",
    "addr:housenumber":"32",
    "addr:postcode":"33188",
    "addr:street":"San Miguel",
    "iso:country":"ES",
    "sg:address":"San Miguel, 32",
    "sg:city":"San Miguel",
    "sg:orig_category":"Artes Gr\u00c1ficas, Artes Pl\u00c1sticas (curso)",
    "sg:phone":"+34 985 79 36 89",
    "sg:postcode":"33188",
    "sg:province":"Asturias",
    "wof:name":"Quifolith S. L.",
    "wof:placetype":"venue"
},
  "geometry": {"coordinates":[-5.7278189659,43.3858985901],"type":"Point"}
}