{
  "type": "Feature",
  "properties": {
    "addr:full":"Calle de Fairway Village, 116 Golf Sur Santa Cruz De Tenerife 38639",
    "addr:housenumber":"116",
    "addr:postcode":"38639",
    "addr:street":"Calle De Fairway Village;Golf Sur",
    "iso:country":"ES",
    "sg:address":"Calle de Fairway Village, 116",
    "sg:city":"Golf Sur",
    "sg:orig_category":"Inmobiliaria (agencias)",
    "sg:phone":"+34 922 70 82 51",
    "sg:postcode":"38639",
    "sg:province":"Santa Cruz De Tenerife",
    "wof:name":"B.i.c. Leisure S.l.",
    "wof:placetype":"venue"
},
  "geometry": {"coordinates":[-16.606760025,28.0324287415],"type":"Point"}
}