{
  "type": "Feature",
  "properties": {
    "iso:country":"ES",
    "sg:address":"Pl Garrigo, 11",
    "sg:city":"Barcelona",
    "sg:orig_category":"Zapatos (al Por Menor)",
    "sg:phone":"+34 933 11 67 01",
    "sg:postcode":"08016",
    "sg:province":"Barcelona",
    "wof:name":"Peregrina Rello Maria Carmen",
    "wof:placetype":"venue"
},
  "geometry": {"coordinates":[2.1813349724,41.4295883179],"type":"Point"}
}