{
  "type": "Feature",
  "properties": {
    "iso:country":"ES",
    "sg:address":"Calle de Nuestra Se\u00d1ora De Fatima, 1",
    "sg:city":"Pilas",
    "sg:orig_category":"Art\u00cdculos De Regalo (al Por Menor)",
    "sg:phone":"+34 954 75 13 55",
    "sg:postcode":"41840",
    "sg:province":"Sevilla",
    "wof:name":"Videos Todo Todo De Pilas S.l.",
    "wof:placetype":"venue"
},
  "geometry": {"coordinates":[-6.2985677719,37.3019332886],"type":"Point"}
}