{
  "type": "Feature",
  "properties": {
    "addr:full":"Calle de Muro De Puerta Nueva, 5 Malaga M\u00e1laga 29005",
    "addr:housenumber":"5",
    "addr:postcode":"29005",
    "addr:street":"Calle De Muro De Puerta Nueva;Ma\u0301Laga",
    "iso:country":"ES",
    "sg:address":"Calle de Muro De Puerta Nueva, 5",
    "sg:city":"Malaga",
    "sg:orig_category":"Confecci\u00d3n (fabricaci\u00d3n, Al Por Mayor)",
    "sg:phone":"+34 952 60 02 30",
    "sg:postcode":"29005",
    "sg:province":"M\u00e1laga",
    "wof:name":"Juana Quiles S.l.",
    "wof:placetype":"venue"
},
  "geometry": {"coordinates":[-4.4245772362,36.7211265564],"type":"Point"}
}