{
  "type": "Feature",
  "properties": {
    "iso:country":"ES",
    "sg:address":"Avda Berlin (de), 12",
    "sg:city":"Coslada",
    "sg:orig_category":"Poller\u00cda Y Caza (al Por Menor)",
    "sg:phone":"+34 916 73 61 02",
    "sg:postcode":"28820",
    "sg:province":"Madrid",
    "wof:name":"Andreu Moriano Luisa",
    "wof:placetype":"venue"
},
  "geometry": {"coordinates":[-3.5426828861,40.4178161621],"type":"Point"}
}