{
  "type": "Feature",
  "properties": {
    "iso:country":"ES",
    "sg:address":"Calle de Albareda, 1",
    "sg:city":"Sevilla",
    "sg:orig_category":"Camiser\u00cda Y Ropa Interior Masculina (al Por Menor)",
    "sg:phone":"+34 954 22 13 45",
    "sg:postcode":"41001",
    "sg:province":"Sevilla",
    "wof:name":"Porta Serrano Enrique",
    "wof:placetype":"venue"
},
  "geometry": {"coordinates":[-5.9946379662,37.3894958496],"type":"Point"}
}