{
  "type": "Feature",
  "properties": {
    "addr:full":"Lermandabidea, 8 Jundiz \u00c1lava 01015",
    "addr:housenumber":"8",
    "addr:postcode":"01015",
    "addr:street":"Lermandabidea;A\u0301Lava",
    "iso:country":"ES",
    "sg:address":"Lermandabidea, 8",
    "sg:city":"Jundiz",
    "sg:orig_category":"Transportes Internacionales",
    "sg:phone":"+34 945 29 08 78",
    "sg:postcode":"01015",
    "sg:province":"\u00c1lava",
    "sg:website":"www.ecutrans.com",
    "wof:name":"Ecutrans S.a.",
    "wof:placetype":"venue"
},
  "geometry": {"coordinates":[-6.1999697685,43.3617782593],"type":"Point"}
}