{
  "type": "Feature",
  "properties": {
    "iso:country":"ES",
    "sg:address":"Calle de San Juan, 60",
    "sg:city":"Alsasua",
    "sg:orig_category":"Tintes (fabricaci\u00d3n, Al Por Mayor)",
    "sg:phone":"+34 948 46 72 81",
    "sg:postcode":"31800",
    "sg:province":"Navarra",
    "wof:name":"Cobos De La Torre Juana",
    "wof:placetype":"venue"
},
  "geometry": {"coordinates":[-2.173607111,42.895362854],"type":"Point"}
}