{
  "type": "Feature",
  "properties": {
    "iso:country":"ES",
    "sg:address":"Pla\u00c7 Doctor Fleming, S/n",
    "sg:city":"Estartit",
    "sg:orig_category":"Artes Gr\u00c1ficas, Artes Pl\u00c1sticas (curso)",
    "sg:phone":"+34 972 75 19 31",
    "sg:postcode":"17258",
    "sg:province":"Girona",
    "wof:name":"Domenech Su\u00f1e Marisa",
    "wof:placetype":"venue"
},
  "geometry": {"coordinates":[3.1989750862,42.0541114807],"type":"Point"}
}