{
  "type": "Feature",
  "properties": {
    "addr:full":"Calle de Giner De Los Rios, 5 Fuentes Ebro Zaragoza 50740",
    "addr:housenumber":"5",
    "addr:postcode":"50740",
    "addr:street":"Calle De Giner De Los Rios",
    "iso:country":"ES",
    "sg:address":"Calle de Giner De Los Rios, 5",
    "sg:city":"Fuentes Ebro",
    "sg:orig_category":"Plomeros",
    "sg:phone":"+34 976 16 08 14",
    "sg:postcode":"50740",
    "sg:province":"Zaragoza",
    "wof:name":"Fontaneria Noni S.l.",
    "wof:placetype":"venue"
},
  "geometry": {"coordinates":[-0.6351622939,41.5117721558],"type":"Point"}
}