{
  "type": "Feature",
  "properties": {
    "addr:full":"Rbla Brasil, 24 Barcelona Barcelona 08028",
    "addr:housenumber":"24",
    "addr:postcode":"08028",
    "addr:street":"Rbla Brasil",
    "iso:country":"ES",
    "sg:address":"Rbla Brasil, 24",
    "sg:city":"Barcelona",
    "sg:orig_category":"Internados & Ense\u00d1anza Privada",
    "sg:phone":"+34 933 39 57 60",
    "sg:postcode":"08028",
    "sg:province":"Barcelona",
    "wof:name":"Comas Gual Angela",
    "wof:placetype":"venue"
},
  "geometry": {"coordinates":[2.1303989887,41.3769035339],"type":"Point"}
}