{
  "type": "Feature",
  "properties": {
    "iso:country":"ES",
    "sg:address":"Carrer de Sant Julia, 36",
    "sg:city":"Argentona",
    "sg:orig_category":"Muebles, Minoristas",
    "sg:phone":"+34 937 56 04 69",
    "sg:postcode":"08310",
    "sg:province":"Barcelona",
    "wof:name":"Mustaros Font Joaquin",
    "wof:placetype":"venue"
},
  "geometry": {"coordinates":[2.4023768902,41.5558776855],"type":"Point"}
}