{
  "type": "Feature",
  "properties": {
    "addr:full":"Calle de Alta, 3 Campillos M\u00e1laga 29320",
    "addr:housenumber":"3",
    "addr:postcode":"29320",
    "addr:street":"Calle De Alta",
    "iso:country":"ES",
    "sg:address":"Calle de Alta, 3",
    "sg:city":"Campillos",
    "sg:orig_category":"Molduras, Junquillos, Listones Y Molduras Perforadas",
    "sg:phone":"+34 952 72 23 23",
    "sg:postcode":"29320",
    "sg:province":"M\u00e1laga",
    "wof:name":"Luna Niebla Antonio",
    "wof:placetype":"venue"
},
  "geometry": {"coordinates":[-4.8653578758,37.0498085022],"type":"Point"}
}