{
  "type": "Feature",
  "properties": {
    "iso:country":"ES",
    "sg:address":"Calle de Estanislao Infanzon, S/n",
    "sg:city":"Sotrondio",
    "sg:classifiers":[
        {
            "category":"Taxi",
            "type":"Transportation"
        }
    ],
    "sg:phone":"+34 985 67 06 06",
    "sg:postcode":"33950",
    "sg:province":"Asturias",
    "wof:name":"Ayuntamiento De San Martin Del Rey Aurelio",
    "wof:placetype":"venue"
},
  "geometry": {"coordinates":[-5.6040740013,43.2756690979],"type":"Point"}
}