{
  "type": "Feature",
  "properties": {
    "addr:full":"Calle de General Marti, 10 Toledo Toledo 45005",
    "addr:housenumber":"10",
    "addr:postcode":"45005",
    "addr:street":"Calle De General Marti",
    "iso:country":"ES",
    "sg:address":"Calle de General Marti, 10",
    "sg:city":"Toledo",
    "sg:orig_category":"Agencias De Viajes",
    "sg:phone":"+34 925 28 54 34",
    "sg:postcode":"45005",
    "sg:province":"Toledo",
    "wof:name":"Viajes Happytour S.l.",
    "wof:placetype":"venue"
},
  "geometry": {"coordinates":[-4.0363268852,39.8721923828],"type":"Point"}
}