{
  "type": "Feature",
  "properties": {
    "addr:full":"Avda Generalisimo, 3 Puerto Cruz Santa Cruz De Tenerife 38...",
    "addr:housenumber":"3;38 ...",
    "addr:street":"Avda Generalisimo;Cruz Santa Cruz;Tenerife",
    "iso:country":"ES",
    "sg:address":"Avda Generalisimo, 3",
    "sg:city":"Puerto Cruz",
    "sg:orig_category":"Agencias De Viajes",
    "sg:phone":"+34 922 32 73 00",
    "sg:postcode":"38...",
    "sg:province":"Santa Cruz De Tenerife",
    "wof:name":"Travelplan S.a.",
    "wof:placetype":"venue"
},
  "geometry": {"coordinates":[-16.2645397186,28.4603805542],"type":"Point"}
}