{
  "type": "Feature",
  "properties": {
    "iso:country":"ES",
    "sg:address":"Pla\u00c7 Tres Moreres, 1",
    "sg:city":"Algemesi",
    "sg:orig_category":"Peluquer\u00cdas, Peluquer\u00cda Mixta",
    "sg:phone":"+34 962 48 13 45",
    "sg:postcode":"46680",
    "sg:province":"Valencia",
    "wof:name":"Bayona Jaime Juan",
    "wof:placetype":"venue"
},
  "geometry": {"coordinates":[-0.4353989959,39.1874694824],"type":"Point"}
}