{
  "type": "Feature",
  "properties": {
    "iso:country":"ES",
    "sg:address":"Av Diagonal, 319",
    "sg:city":"Barcelona",
    "sg:orig_category":"Encuadernaci\u00d3n E Impresi\u00d3n De Folletos",
    "sg:phone":"+34 934 58 33 54",
    "sg:postcode":"08009",
    "sg:province":"Barcelona",
    "wof:name":"Esclasans Hernandez Agustin",
    "wof:placetype":"venue"
},
  "geometry": {"coordinates":[2.1711819172,41.3991241455],"type":"Point"}
}