{
  "type": "Feature",
  "properties": {
    "addr:full":"Calle de Pedro Aleixandre, 57 Valencia Valencia 46006",
    "addr:housenumber":"57",
    "addr:postcode":"46006",
    "addr:street":"Calle De Pedro Aleixandre",
    "iso:country":"ES",
    "sg:address":"Calle de Pedro Aleixandre, 57",
    "sg:city":"Valencia",
    "sg:orig_category":"Sociedades, Compa\u00d1\u00cdas Aseguradoras",
    "sg:phone":"+34 963 34 22 20",
    "sg:postcode":"46006",
    "sg:province":"Valencia",
    "wof:name":"Gandia Y Torrano Agencia De Seguros S.l.",
    "wof:placetype":"venue"
},
  "geometry": {"coordinates":[-0.3600929976,39.4596252441],"type":"Point"}
}