{
  "type": "Feature",
  "properties": {
    "iso:country":"ES",
    "sg:address":"Pl Jaume Balmes, 5",
    "sg:city":"Gava",
    "sg:orig_category":"Electrodom\u00c9sticos (al Por Menor)",
    "sg:phone":"+34 936 62 16 08",
    "sg:postcode":"08850",
    "sg:province":"Barcelona",
    "wof:name":"Millan Salas Benito",
    "wof:placetype":"venue"
},
  "geometry": {"coordinates":[1.9994109869,41.3046264648],"type":"Point"}
}