{
  "type": "Feature",
  "properties": {
    "addr:full":"Carr Trafalgar, 1 Quart Poblet Valencia 46930",
    "addr:housenumber":"1",
    "addr:postcode":"46930",
    "addr:street":"Carr Trafalgar;Poblet",
    "iso:country":"ES",
    "sg:address":"Carr Trafalgar, 1",
    "sg:city":"Quart Poblet",
    "sg:orig_category":"Bancos",
    "sg:phone":"+34 961 53 74 91",
    "sg:postcode":"46930",
    "sg:province":"Valencia",
    "wof:name":"Banco Espa\u00f1ol De Credito S.a.",
    "wof:placetype":"venue"
},
  "geometry": {"coordinates":[-0.4419890046,39.482711792],"type":"Point"}
}