{
  "type": "Feature",
  "properties": {
    "iso:country":"ES",
    "sg:address":"Av Saragossa, 39",
    "sg:city":"S. Feliu Guixols",
    "sg:orig_category":"Venta Y Reparaci\u00d3n De Naves De Recreo, Accesorios",
    "sg:phone":"+34 972 82 08 02",
    "sg:postcode":"17220",
    "sg:province":"Girona",
    "wof:name":"Colls Bahi Lambert",
    "wof:placetype":"venue"
},
  "geometry": {"coordinates":[3.0262300968,41.7918205261],"type":"Point"}
}