{
  "type": "Feature",
  "properties": {
    "addr:full":"Ctra Palma Del Rio (villarrubia), Km. 0012,1 Villarrubia C\u00f3rdoba 14710",
    "addr:postcode":"14710",
    "addr:street":"Ctra Palma Del Rio Villarrubia Km. 0012,1 Villarrubia Co\u0301Rdoba",
    "iso:country":"ES",
    "sg:address":"Ctra Palma Del Rio (villarrubia), Km. 0012,1",
    "sg:city":"Villarrubia",
    "sg:orig_category":"M\u00c1rmoles, Granitos Y Piedras Naturales",
    "sg:phone":"+34 957 32 78 19",
    "sg:postcode":"14710",
    "sg:province":"C\u00f3rdoba",
    "wof:name":"El Marmol Creativo S.l",
    "wof:placetype":"venue"
},
  "geometry": {"coordinates":[-4.8645591736,37.8604507446],"type":"Point"}
}