{
  "type": "Feature",
  "properties": {
    "iso:country":"ES",
    "sg:address":"Ctra. V. Los Barrios, S/n",
    "sg:city":"Los Barrios",
    "sg:orig_category":"Construcciones E Instalaciones Agr\u00cdcolas",
    "sg:phone":"+34 956 62 22 03",
    "sg:postcode":"11370",
    "sg:province":"C\u00e1diz",
    "wof:name":"Alba Sanchez Sebastian",
    "wof:placetype":"venue"
},
  "geometry": {"coordinates":[-5.4983372688,36.1852531433],"type":"Point"}
}