{
  "type": "Feature",
  "properties": {
    "addr:full":"Avda Juan Carlos I, 50 Ibi Alicante 03440",
    "addr:housenumber":"50",
    "addr:postcode":"03440",
    "addr:street":"Avda Juan Carlos I",
    "iso:country":"ES",
    "sg:address":"Avda Juan Carlos I, 50",
    "sg:city":"Ibi",
    "sg:orig_category":"Inmobiliaria (agencias)",
    "sg:phone":"+34 966 55 18 23",
    "sg:postcode":"03440",
    "sg:province":"Alicante",
    "wof:name":"Vega Cervera Eduardo",
    "wof:placetype":"venue"
},
  "geometry": {"coordinates":[-0.5731660128,38.6238479614],"type":"Point"}
}