{
  "type": "Feature",
  "properties": {
    "addr:full":"Calle de Virgen De La Cabeza, 2 Jaen Ja\u00e9n 23008",
    "addr:housenumber":"2;jae\u0301n",
    "addr:postcode":"23008",
    "addr:street":"Calle De Virgen De La Cabeza",
    "iso:country":"ES",
    "sg:address":"Calle de Virgen De La Cabeza, 2",
    "sg:city":"Jaen",
    "sg:orig_category":"Ingenier\u00cda, Centros De Estudios (diversos)",
    "sg:phone":"+34 953 27 42 86",
    "sg:postcode":"23008",
    "sg:province":"Ja\u00e9n",
    "wof:name":"Rodriguez Navarro Leandro",
    "wof:placetype":"venue"
},
  "geometry": {"coordinates":[-3.7884058952,37.7759017944],"type":"Point"}
}