{
  "type": "Feature",
  "properties": {
    "addr:full":"Plaz Juan Benet, 9 Madrid Madrid 28032",
    "addr:housenumber":"9",
    "addr:postcode":"madrid;28032",
    "addr:street":"Plaz Juan Benet",
    "iso:country":"ES",
    "sg:address":"Plaz Juan Benet, 9",
    "sg:city":"Madrid",
    "sg:orig_category":"Peluquer\u00cdas, Peluquer\u00cda Mixta",
    "sg:phone":"+34 917 51 22 11",
    "sg:postcode":"28032",
    "sg:province":"Madrid",
    "wof:name":"Perea Lopez Marta",
    "wof:placetype":"venue"
},
  "geometry": {"coordinates":[-3.6234529018,40.4001846313],"type":"Point"}
}