{
  "type": "Feature",
  "properties": {
    "iso:country":"ES",
    "sg:address":"Ctra Circunvalacion, 18",
    "sg:city":"Villacarrillo",
    "sg:orig_category":"Arreglo, Reparaci\u00d3n, Piezas Sueltas De Televisi\u00d3n, V\u00cddeo, Hi",
    "sg:phone":"+34 953 44 01 72",
    "sg:postcode":"23300",
    "sg:province":"Ja\u00e9n",
    "wof:name":"Jimenez Mora Antonio",
    "wof:placetype":"venue"
},
  "geometry": {"coordinates":[-3.0803439617,38.1186408997],"type":"Point"}
}