{
  "type": "Feature",
  "properties": {
    "iso:country":"ES",
    "sg:address":"Calle de Felo Sanchez, 25",
    "sg:city":"Ingenio",
    "sg:orig_category":"Mec\u00c1nico Del Autom\u00d3vil",
    "sg:phone":"+34 928 78 56 30",
    "sg:postcode":"35250",
    "sg:province":"Las Palmas",
    "wof:name":"Hernandez Artiles Francisco Antonio",
    "wof:placetype":"venue"
},
  "geometry": {"coordinates":[-15.4287557602,27.917257309],"type":"Point"}
}