{
  "type": "Feature",
  "properties": {
    "iso:country":"ES",
    "sg:address":"Plaz Paradero, 4",
    "sg:city":"Casarrubios Monte",
    "sg:orig_category":"Mec\u00c1nico Del Autom\u00d3vil",
    "sg:phone":"+34 918 17 22 34",
    "sg:postcode":"45950",
    "sg:province":"Toledo",
    "wof:name":"Hierro Madrigal Vicente Del",
    "wof:placetype":"venue"
},
  "geometry": {"coordinates":[-4.0399508476,40.1880645752],"type":"Point"}
}