{
  "type": "Feature",
  "properties": {
    "addr:full":"Calle de Paraguay, 9 Leganes Madrid 28914",
    "addr:housenumber":"9",
    "addr:postcode":"28914",
    "addr:street":"Calle De Paraguay",
    "iso:country":"ES",
    "sg:address":"Calle de Paraguay, 9",
    "sg:city":"Leganes",
    "sg:orig_category":"Marketing Directo",
    "sg:phone":"+34 916 86 92 75",
    "sg:postcode":"28914",
    "sg:province":"Madrid",
    "wof:name":"Servimarket S.l.",
    "wof:placetype":"venue"
},
  "geometry": {"coordinates":[-3.767788887,40.3416099548],"type":"Point"}
}