{
  "type": "Feature",
  "properties": {
    "addr:full":"Calle de Estalajes, 5 Azuaga Badajoz 06920",
    "addr:housenumber":"5",
    "addr:postcode":"06920",
    "addr:street":"Calle De Estalajes",
    "iso:country":"ES",
    "sg:address":"Calle de Estalajes, 5",
    "sg:city":"Azuaga",
    "sg:orig_category":"Droguer\u00cdas (al Por Menor)",
    "sg:phone":"+34 924 89 27 52",
    "sg:postcode":"06920",
    "sg:province":"Badajoz",
    "wof:name":"Guerrero Y Duran Droguerias S.l.",
    "wof:placetype":"venue"
},
  "geometry": {"coordinates":[-5.677380085,38.2592010498],"type":"Point"}
}