{
  "type": "Feature",
  "properties": {
    "addr:full":"Calle de Leon Y Castillo, 244 Palmas De Gran Canaria Las Palmas 35005",
    "addr:housenumber":"244",
    "addr:postcode":"35005",
    "addr:street":"Calle De Leon Y Castillo",
    "iso:country":"ES",
    "sg:address":"Calle de Leon Y Castillo, 244",
    "sg:city":"Palmas De Gran Canaria",
    "sg:orig_category":"Inmobiliaria (agencias)",
    "sg:phone":"+34 928 29 64 02",
    "sg:postcode":"35005",
    "sg:province":"Las Palmas",
    "wof:name":"Santana Padron Maria Del Carmen",
    "wof:placetype":"venue"
},
  "geometry": {"coordinates":[-15.426358223,28.1210422516],"type":"Point"}
}