{
  "type": "Feature",
  "properties": {
    "addr:full":"Cmno Silo (del), 8 Barbastro Huesca 22300",
    "addr:housenumber":"8",
    "addr:postcode":"22300",
    "addr:street":"Cmno Silo Del",
    "iso:country":"ES",
    "sg:address":"Cmno Silo (del), 8",
    "sg:city":"Barbastro",
    "sg:orig_category":"Empresarios",
    "sg:phone":"+34 974 31 14 57",
    "sg:postcode":"22300",
    "sg:province":"Huesca",
    "wof:name":"Bruned Salamero Manuel",
    "wof:placetype":"venue"
},
  "geometry": {"coordinates":[0.1279940009,42.0360984802],"type":"Point"}
}