{
  "type": "Feature",
  "properties": {
    "addr:full":"Calle de Balmes, 12 Alberic Valencia 46260",
    "addr:housenumber":"12",
    "addr:postcode":"46260",
    "addr:street":"Calle De Balmes",
    "iso:country":"ES",
    "sg:address":"Calle de Balmes, 12",
    "sg:city":"Alberic",
    "sg:orig_category":"Electricidad Veh\u00cdculo",
    "sg:phone":"+34 962 44 14 64",
    "sg:postcode":"46260",
    "sg:province":"Valencia",
    "wof:name":"Mestre Esparza Francisco",
    "wof:placetype":"venue"
},
  "geometry": {"coordinates":[-0.5216577053,39.114982605],"type":"Point"}
}