{
  "type": "Feature",
  "properties": {
    "iso:country":"ES",
    "sg:address":"Avda Olimpica, 9",
    "sg:city":"Alcobendas",
    "sg:orig_category":"Servicios Gsm",
    "sg:phone":"+34 916 62 72 03",
    "sg:postcode":"28108",
    "sg:province":"Madrid",
    "sg:website":"www.tiendafutura.es",
    "wof:name":"Avenir Telecom S.a.",
    "wof:placetype":"venue"
},
  "geometry": {"coordinates":[-3.6371610165,40.5352287292],"type":"Point"}
}