{
  "type": "Feature",
  "properties": {
    "iso:country":"ES",
    "sg:address":"Carrer de Cultura, 2",
    "sg:city":"Hospitalet Llobregat",
    "sg:orig_category":"Cromado Y Niquelado",
    "sg:phone":"+34 934 22 08 20",
    "sg:postcode":"08902",
    "sg:province":"Barcelona",
    "wof:name":"Marin Aparicio Jose",
    "wof:placetype":"venue"
},
  "geometry": {"coordinates":[2.1201210022,41.3658638],"type":"Point"}
}