{
  "type": "Feature",
  "properties": {
    "addr:full":"Calle de Carretera De La Estacion, S/n Cantillana Sevilla 41320",
    "addr:postcode":"41320",
    "addr:street":"Calle De Carretera De La Estacion S / N",
    "iso:country":"ES",
    "sg:address":"Calle de Carretera De La Estacion, S/n",
    "sg:city":"Cantillana",
    "sg:orig_category":"Producci\u00d3n, Venta De Productos De Agricultura Biol\u00d3gica",
    "sg:phone":"+34 955 95 24 00",
    "sg:postcode":"41320",
    "sg:province":"Sevilla",
    "wof:name":"Ramio Espa\u00f1ol S. A.",
    "wof:placetype":"venue"
},
  "geometry": {"coordinates":[-5.8228302002,37.6077880859],"type":"Point"}
}