{
  "type": "Feature",
  "properties": {
    "iso:country":"ES",
    "sg:address":"Av Mossen Anton, 1",
    "sg:city":"Albi",
    "sg:orig_category":"Aceites Y Grasas Alimentarias (fabricaci\u00d3n, Al Por Mayor)",
    "sg:phone":"+34 973 17 50 09",
    "sg:postcode":"25450",
    "sg:province":"Lleida",
    "wof:name":"Cooperativa Del Campo",
    "wof:placetype":"venue"
},
  "geometry": {"coordinates":[0.9375669956,41.424533844],"type":"Point"}
}