{
  "type": "Feature",
  "properties": {
    "addr:full":"Ctra Zapateira, 13 Zapateira La Coru\u00f1a 15011",
    "addr:housenumber":"13",
    "addr:postcode":"15011",
    "addr:street":"Ctra Zapateira;La Corun\u0303A",
    "iso:country":"ES",
    "sg:address":"Ctra Zapateira, 13",
    "sg:city":"Zapateira",
    "sg:orig_category":"Inmobiliaria (agencias)",
    "sg:phone":"+34 981 13 30 95",
    "sg:postcode":"15011",
    "sg:province":"La Coru\u00f1a",
    "wof:name":"Inmobiliaria Tani,s.a.",
    "wof:placetype":"venue"
},
  "geometry": {"coordinates":[-8.3959693909,43.3714904785],"type":"Point"}
}