{
  "type": "Feature",
  "properties": {
    "iso:country":"ES",
    "sg:address":"Carrer de Santa Joaquima, 11",
    "sg:city":"S. Cugat Valles",
    "sg:orig_category":"Iglesias Cristianas Diversas",
    "sg:phone":"+34 935 89 76 42",
    "sg:postcode":"08172",
    "sg:province":"Barcelona",
    "wof:name":"Testigos Cristianos De Jehova",
    "wof:placetype":"venue"
},
  "geometry": {"coordinates":[2.0808889866,41.474067688],"type":"Point"}
}