{
  "type": "Feature",
  "properties": {
    "iso:country":"ES",
    "sg:address":"Calle de Compositor Ramon Medina, 8",
    "sg:city":"Cordoba",
    "sg:orig_category":"Cristaler\u00cdas",
    "sg:phone":"+34 957 25 68 61",
    "sg:postcode":"14010",
    "sg:province":"C\u00f3rdoba",
    "wof:name":"Leon Blancas Francisco",
    "wof:placetype":"venue"
},
  "geometry": {"coordinates":[-4.7622771263,37.8892250061],"type":"Point"}
}