{
  "type": "Feature",
  "properties": {
    "iso:country":"ES",
    "sg:address":"G.v. Corts Catalanes, 644",
    "sg:city":"Barcelona",
    "sg:classifiers":[
        {
            "category":"Home & Garden",
            "subcategory":"Household Appliances",
            "type":"Retail Goods"
        }
    ],
    "sg:phone":"+34 933 01 39 47",
    "sg:postcode":"08007",
    "sg:province":"Barcelona",
    "sg:tags":[
        "bodega",
        "de",
        "vino",
        "acondicionamiento"
    ],
    "sg:website":"www.codorniu.es",
    "wof:name":"Codorniu S.a.",
    "wof:placetype":"venue"
},
  "geometry": {"coordinates":[2.1696479321,41.3900184631],"type":"Point"}
}