{
  "type": "Feature",
  "properties": {
    "iso:country":"ES",
    "sg:address":"Calle de Castillo, 55",
    "sg:city":"Santa Cruz De Tenerife",
    "sg:orig_category":"Abogados",
    "sg:phone":"+34 922 28 00 18",
    "sg:postcode":"38003",
    "sg:province":"Santa Cruz De Tenerife",
    "wof:name":"Delgado Nu\u00f1ez Andres",
    "wof:placetype":"venue"
},
  "geometry": {"coordinates":[-16.253156662,28.4673786163],"type":"Point"}
}