{
  "type": "Feature",
  "properties": {
    "iso:country":"ES",
    "sg:address":"Calle de Hoya (la), 43",
    "sg:city":"Puerto Cruz",
    "sg:orig_category":"Inmobiliaria (agencias)",
    "sg:phone":"+34 922 38 41 13",
    "sg:postcode":"38400",
    "sg:province":"Santa Cruz De Tenerife",
    "wof:name":"Grupo Inmobiliario Internacional Del Puerto De La Cruz S.l.",
    "wof:placetype":"venue"
},
  "geometry": {"coordinates":[9.0760097504,52.7750091553],"type":"Point"}
}