{
  "type": "Feature",
  "properties": {
    "addr:full":"Calle de Gri\u00d1on, 4 Fuenlabrada Madrid 28944",
    "addr:housenumber":"4",
    "addr:postcode":"28944",
    "addr:street":"Calle De Grin\u0303On",
    "iso:country":"ES",
    "sg:address":"Calle de Gri\u00d1on, 4",
    "sg:city":"Fuenlabrada",
    "sg:orig_category":"Transportes En Volquetes Basculantes",
    "sg:phone":"+34 914 92 02 78",
    "sg:postcode":"28944",
    "sg:province":"Madrid",
    "wof:name":"Excavaciones Fuenlabrada S.l.",
    "wof:placetype":"venue"
},
  "geometry": {"coordinates":[-3.7895460129,40.2807235718],"type":"Point"}
}