{
  "type": "Feature",
  "properties": {
    "iso:country":"ES",
    "sg:address":"Calle de Mayor, 4",
    "sg:city":"Labastida",
    "sg:orig_category":"Peluquer\u00cdas, Peluquer\u00cda Mixta",
    "sg:phone":"+34 945 33 14 21",
    "sg:postcode":"01330",
    "sg:province":"\u00c1lava",
    "wof:name":"Canta Ibanez Candido",
    "wof:placetype":"venue"
},
  "geometry": {"coordinates":[-2.79449296,42.590713501],"type":"Point"}
}