{
  "type": "Feature",
  "properties": {
    "iso:country":"ES",
    "sg:address":"Calle de Jacometrezo, 4",
    "sg:city":"Madrid",
    "sg:orig_category":"Electricidad, Electr\u00d3nica: Suministros (al Por Menor)",
    "sg:phone":"+34 915 21 84 20",
    "sg:postcode":"28013",
    "sg:province":"Madrid",
    "wof:name":"Ingelectric Ingenieria De Sistemas S.a.",
    "wof:placetype":"venue"
},
  "geometry": {"coordinates":[-3.7068200111,40.4203147888],"type":"Point"}
}