{
  "type": "Feature",
  "properties": {
    "addr:full":"Calle de Churruca, 11 Madrid Madrid 28004",
    "addr:housenumber":"11",
    "addr:postcode":"madrid;28004",
    "addr:street":"Calle De Churruca",
    "iso:country":"ES",
    "sg:address":"Calle de Churruca, 11",
    "sg:city":"Madrid",
    "sg:orig_category":"Loter\u00cda Y T\u00d3mbola",
    "sg:phone":"+34 915 31 91 66",
    "sg:postcode":"28004",
    "sg:province":"Madrid",
    "wof:name":"Esteban Garcia Elena",
    "wof:placetype":"venue"
},
  "geometry": {"coordinates":[-3.7009439468,40.4275016785],"type":"Point"}
}