{
  "type": "Feature",
  "properties": {
    "addr:full":"Comedias, 3 Iru\u00f1a Navarra 31001",
    "addr:housenumber":"3",
    "addr:postcode":"31001",
    "addr:street":"Comedias",
    "iso:country":"ES",
    "sg:address":"Comedias, 3",
    "sg:city":"Iru\u00f1a",
    "sg:orig_category":"Carnicer\u00cdas, Carnicer\u00cdas",
    "sg:phone":"+34 948 22 02 01",
    "sg:postcode":"31001",
    "sg:province":"Navarra",
    "wof:name":"Solano Sadaba Julian",
    "wof:placetype":"venue"
},
  "geometry": {"coordinates":[-1.643576026,42.8164749146],"type":"Point"}
}