{
  "type": "Feature",
  "properties": {
    "iso:country":"ES",
    "sg:address":"P. Garcia De Najera, 13",
    "sg:city":"Iru\u00f1a",
    "sg:orig_category":"M\u00c9dicos: Estomatolog\u00cda",
    "sg:phone":"+34 948 17 46 57",
    "sg:postcode":"31008",
    "sg:province":"Navarra",
    "wof:name":"I\u00f1igo Noain Jesus",
    "wof:placetype":"venue"
},
  "geometry": {"coordinates":[-1.6611599922,42.8107948303],"type":"Point"}
}