{
  "type": "Feature",
  "properties": {
    "addr:full":"Carrer de Marques De Estella, 9 Verger Alicante 03770",
    "addr:housenumber":"9",
    "addr:postcode":"03770",
    "addr:street":"Carrer De Marques De Estella",
    "iso:country":"ES",
    "sg:address":"Carrer de Marques De Estella, 9",
    "sg:city":"Verger",
    "sg:orig_category":"Laboratorios Farmac\u00c9uticos",
    "sg:phone":"+34 965 75 01 66",
    "sg:postcode":"03770",
    "sg:province":"Alicante",
    "wof:name":"Infantes Costa Jose Maria",
    "wof:placetype":"venue"
},
  "geometry": {"coordinates":[0.0093130004,38.8456306458],"type":"Point"}
}