{
  "type": "Feature",
  "properties": {
    "addr:full":"Carrer de Proven\u00c7a, 493 Barcelona Barcelona 08025",
    "addr:housenumber":"493",
    "addr:postcode":"08025",
    "addr:street":"Carrer De Provenc\u0327A",
    "iso:country":"ES",
    "sg:address":"Carrer de Proven\u00c7a, 493",
    "sg:city":"Barcelona",
    "sg:orig_category":"Carnicer\u00cdas, Carnicer\u00cdas",
    "sg:phone":"+34 934 56 23 40",
    "sg:postcode":"08025",
    "sg:province":"Barcelona",
    "wof:name":"Felguera Garcia Jose",
    "wof:placetype":"venue"
},
  "geometry": {"coordinates":[2.1772100925,41.4067306519],"type":"Point"}
}