{
  "type": "Feature",
  "properties": {
    "iso:country":"ES",
    "sg:address":"Elkano Kalea, 11",
    "sg:city":"Hernani",
    "sg:orig_category":"Partidos Pol\u00cdticos",
    "sg:phone":"+34 943 55 04 29",
    "sg:postcode":"20120",
    "sg:province":"Guip\u00f9zcoa",
    "wof:name":"Partido Socialista Obrero Espa\u00f1ol",
    "wof:placetype":"venue"
},
  "geometry": {"coordinates":[-1.9767459631,43.2661437988],"type":"Point"}
}