{
  "type": "Feature",
  "properties": {
    "iso:country":"ES",
    "sg:address":"Calle de Navas De Tolosa, 74",
    "sg:city":"Zaragoza",
    "sg:classifiers":[
        {
            "category":"Autos & Motor Vehicles",
            "subcategory":"Automobile Sales",
            "type":"Retail Goods"
        }
    ],
    "sg:phone":"+34 976 32 46 99",
    "sg:postcode":"50010",
    "sg:province":"Zaragoza",
    "wof:name":"Autoescuela Pellicena S.l.",
    "wof:placetype":"venue"
},
  "geometry": {"coordinates":[-0.8984289169,41.6518287659],"type":"Point"}
}