{
  "type": "Feature",
  "properties": {
    "iso:country":"ES",
    "sg:address":"Av Onze De Setembre, 157",
    "sg:city":"Sabadell",
    "sg:orig_category":"Peluqueros: De Se\u00d1oras",
    "sg:phone":"+34 937 16 80 92",
    "sg:postcode":"08208",
    "sg:province":"Barcelona",
    "wof:name":"Sitjes Alsina Ricardo",
    "wof:placetype":"venue"
},
  "geometry": {"coordinates":[2.1026260853,41.5545196533],"type":"Point"}
}