{
  "type": "Feature",
  "properties": {
    "iso:country":"ES",
    "sg:address":"Carr Vinaroz, 13",
    "sg:city":"Sol De L'est",
    "sg:orig_category":"Abogados",
    "sg:phone":"+34 971 36 95 12",
    "sg:postcode":"07720",
    "sg:province":"Islas Baleares",
    "wof:name":"Espin Carreras Salvador",
    "wof:placetype":"venue"
},
  "geometry": {"coordinates":[2.9117100239,39.6136398315],"type":"Point"}
}