{
  "type": "Feature",
  "properties": {
    "iso:country":"ES",
    "sg:address":"Pl Maignon, 6",
    "sg:city":"Badalona",
    "sg:orig_category":"Molduras, Junquillos, Listones Y Molduras Perforadas",
    "sg:phone":"+34 933 89 30 42",
    "sg:postcode":"08911",
    "sg:province":"Barcelona",
    "wof:name":"Marcos Medina Francisco",
    "wof:placetype":"venue"
},
  "geometry": {"coordinates":[2.2472949028,41.4485282898],"type":"Point"}
}