{
  "type": "Feature",
  "properties": {
    "iso:country":"ES",
    "sg:address":"Calle de Canal De Bardenas, 33",
    "sg:city":"Ejea De Los Caballeros",
    "sg:orig_category":"Agricultores, Agricultores",
    "sg:phone":"+34 976 66 22 84",
    "sg:postcode":"50600",
    "sg:province":"Zaragoza",
    "wof:name":"Comunidad De Bienes Urbon",
    "wof:placetype":"venue"
},
  "geometry": {"coordinates":[-1.1268178225,42.1257019043],"type":"Point"}
}