{
  "type": "Feature",
  "properties": {
    "addr:full":"Calle de Camino De La Barca, 1 Barbastro Huesca 22300",
    "addr:housenumber":"1",
    "addr:postcode":"22300",
    "addr:street":"Calle De Camino De La Barca",
    "iso:country":"ES",
    "sg:address":"Calle de Camino De La Barca, 1",
    "sg:city":"Barbastro",
    "sg:orig_category":"Ebanister\u00cda",
    "sg:phone":"+34 974 31 19 28",
    "sg:postcode":"22300",
    "sg:province":"Huesca",
    "wof:name":"Millaruelo Rami S.l.",
    "wof:placetype":"venue"
},
  "geometry": {"coordinates":[0.130913794,42.0347480774],"type":"Point"}
}