{
  "type": "Feature",
  "properties": {
    "addr:full":"Calle de Tiziano, 45 Tafira Alta Las Palmas 35017",
    "addr:housenumber":"45",
    "addr:postcode":"35017",
    "addr:street":"Calle De Tiziano;Alta",
    "iso:country":"ES",
    "sg:address":"Calle de Tiziano, 45",
    "sg:city":"Tafira Alta",
    "sg:orig_category":"Quincaller\u00cda (al Por Menor)",
    "sg:phone":"+34 928 35 30 59",
    "sg:postcode":"35017",
    "sg:province":"Las Palmas",
    "wof:name":"Ferreteria Centro S.l.",
    "wof:placetype":"venue"
},
  "geometry": {"coordinates":[-15.4688825607,28.0524635315],"type":"Point"}
}