{
  "type": "Feature",
  "properties": {
    "addr:full":"Cra. Nacional 230, Km. 0126,5 Pont Suert Lleida 25520",
    "addr:postcode":"25520",
    "addr:street":"Nacional 230 Km. 0126,5 Pont Suert",
    "iso:country":"ES",
    "sg:address":"Cra. Nacional 230, Km. 0126,5",
    "sg:city":"Pont Suert",
    "sg:orig_category":"Agentes, Concesionarios Y Sucursales De Veh\u00cdculos",
    "sg:phone":"+34 973 69 01 09",
    "sg:postcode":"25520",
    "sg:province":"Lleida",
    "wof:name":"Automoviles Autoriutor S.l.",
    "wof:placetype":"venue"
},
  "geometry": {"coordinates":[0.7818089128,42.4010162354],"type":"Point"}
}