{
  "type": "Feature",
  "properties": {
    "addr:full":"Pg Gracia, 3 Barcelona Barcelona 08007",
    "addr:housenumber":"3",
    "addr:postcode":"08007",
    "addr:street":"Pg Gracia",
    "iso:country":"ES",
    "sg:address":"Pg Gracia, 3",
    "sg:city":"Barcelona",
    "sg:orig_category":"Distribuci\u00d3n De Petr\u00d3leo Y Derivados",
    "sg:phone":"+34 934 12 24 23",
    "sg:postcode":"08007",
    "sg:province":"Barcelona",
    "sg:website":"www.cepsa.es",
    "wof:name":"Gasolinera Matias Scp",
    "wof:placetype":"venue"
},
  "geometry": {"coordinates":[2.1694090366,41.3881492615],"type":"Point"}
}