{
  "type": "Feature",
  "properties": {
    "addr:full":"Calle de Amilcar Barca, 37 Cadiz C\u00e1diz 11009",
    "addr:housenumber":"37",
    "addr:postcode":"11009",
    "addr:street":"Calle De Amilcar Barca",
    "iso:country":"ES",
    "sg:address":"Calle de Amilcar Barca, 37",
    "sg:city":"Cadiz",
    "sg:orig_category":"Mec\u00c1nico Del Autom\u00d3vil",
    "sg:phone":"+34 956 26 10 28",
    "sg:postcode":"11009",
    "sg:province":"C\u00e1diz",
    "wof:name":"Recauto Express S.l.",
    "wof:placetype":"venue"
},
  "geometry": {"coordinates":[-6.2796492577,36.5078697205],"type":"Point"}
}