{
  "type": "Feature",
  "properties": {
    "addr:full":"Avda Toledo, 40 Ventas Con Pe\u00e7a Aguilera Toledo 45127",
    "addr:housenumber":"40",
    "addr:postcode":"45127",
    "addr:street":"Avda Toledo",
    "iso:country":"ES",
    "sg:address":"Avda Toledo, 40",
    "sg:city":"Ventas Con Pe\u00e7a Aguilera",
    "sg:orig_category":"Empresas De Carpinter\u00cda De Madera",
    "sg:phone":"+34 925 41 83 43",
    "sg:postcode":"45127",
    "sg:province":"Toledo",
    "wof:name":"Cid Cid Mariano",
    "wof:placetype":"venue"
},
  "geometry": {"coordinates":[-4.2269687653,39.617980957],"type":"Point"}
}