{
  "type": "Feature",
  "properties": {
    "iso:country":"ES",
    "sg:address":"Cno De Coin (p I La Vega), 51",
    "sg:city":"Mijas Costa",
    "sg:orig_category":"Ropa Para Ni\u00d1os (al Por Menor)",
    "sg:phone":"+34 952 47 93 26",
    "sg:postcode":"29649",
    "sg:province":"M\u00e1laga",
    "wof:name":"Jimenez Merino Francisca",
    "wof:placetype":"venue"
},
  "geometry": {"coordinates":[-4.6310629845,36.5238952637],"type":"Point"}
}