{
  "type": "Feature",
  "properties": {
    "iso:country":"ES",
    "sg:address":"Barr Urioste, 37",
    "sg:city":"Urioste",
    "sg:orig_category":"Pescader\u00cdas (al Por Menor)",
    "sg:phone":"+34 946 64 22 64",
    "sg:postcode":"48530",
    "sg:province":"Vizcaya",
    "wof:name":"Delgado Saenz Angel",
    "wof:placetype":"venue"
},
  "geometry": {"coordinates":[-3.0566248894,43.3107376099],"type":"Point"}
}