{
  "type": "Feature",
  "properties": {
    "iso:country":"ES",
    "sg:address":"Carrer de Ruben Dario, 2",
    "sg:city":"Barcelona",
    "sg:orig_category":"Decoraci\u00d3n: Instalaci\u00d3n Y Talleres",
    "sg:phone":"+34 933 45 55 47",
    "sg:postcode":"08030",
    "sg:province":"Barcelona",
    "wof:name":"Bason S.l.",
    "wof:placetype":"venue"
},
  "geometry": {"coordinates":[2.1893761158,41.4340782166],"type":"Point"}
}