{
  "type": "Feature",
  "properties": {
    "addr:full":"Calle de Sima, 1 Zujar Granada 18811",
    "addr:housenumber":"1",
    "addr:postcode":"18811",
    "addr:street":"Calle De Sima",
    "iso:country":"ES",
    "sg:address":"Calle de Sima, 1",
    "sg:city":"Zujar",
    "sg:orig_category":"Estancos",
    "sg:phone":"+34 958 71 67 58",
    "sg:postcode":"18811",
    "sg:province":"Granada",
    "wof:name":"Tamayo Arredondo Susana Pilar",
    "wof:placetype":"venue"
},
  "geometry": {"coordinates":[-2.8426940441,37.5390777588],"type":"Point"}
}