{
  "type": "Feature",
  "properties": {
    "iso:country":"ES",
    "sg:address":"Calle de Portal Del Rey, 2",
    "sg:city":"Vitoria-gasteiz",
    "sg:orig_category":"Molduras, Junquillos, Listones Y Molduras Perforadas",
    "sg:phone":"+34 945 26 46 02",
    "sg:postcode":"01001",
    "sg:province":"\u00c1lava",
    "wof:name":"Blanco Rodriguez Diego",
    "wof:placetype":"venue"
},
  "geometry": {"coordinates":[-2.6690530777,42.846950531],"type":"Point"}
}