{
  "type": "Feature",
  "properties": {
    "iso:country":"ES",
    "sg:address":"Plaz Portichuelo, 3",
    "sg:city":"Antequera",
    "sg:orig_category":"Molduras, Junquillos, Listones Y Molduras Perforadas",
    "sg:phone":"+34 952 84 13 62",
    "sg:postcode":"29200",
    "sg:province":"M\u00e1laga",
    "wof:name":"Hermanos Acedo Sanchez S.l.",
    "wof:placetype":"venue"
},
  "geometry": {"coordinates":[-4.5636138916,37.0203018188],"type":"Point"}
}