{
  "type": "Feature",
  "properties": {
    "iso:country":"ES",
    "sg:address":"Moll Barcelona, S/n",
    "sg:city":"Barcelona",
    "sg:orig_category":"Inform\u00c1tica (estudios, Servicios, Asesor\u00cda, Formaci\u00d3n)",
    "sg:phone":"+34 934 24 77 85",
    "sg:postcode":"08039",
    "sg:province":"Barcelona",
    "sg:website":"www.telynet.com",
    "wof:name":"Telynet Information Systems S.a.",
    "wof:placetype":"venue"
},
  "geometry": {"coordinates":[2.1776499748,41.3729553223],"type":"Point"}
}