{
  "type": "Feature",
  "properties": {
    "addr:full":"Carr S Magi, 28 Igualada Barcelona 08700",
    "addr:housenumber":"28",
    "addr:postcode":"08700",
    "addr:street":"Carr S Magi",
    "iso:country":"ES",
    "sg:address":"Carr S Magi, 28",
    "sg:city":"Igualada",
    "sg:orig_category":"Asociaciones, Organismos Culturales Y Socioeducativos",
    "sg:phone":"+34 938 03 20 47",
    "sg:postcode":"08700",
    "sg:province":"Barcelona",
    "wof:name":"Club Escursionista Eucanoia",
    "wof:placetype":"venue"
},
  "geometry": {"coordinates":[1.6167039871,41.5809020996],"type":"Point"}
}