{
  "type": "Feature",
  "properties": {
    "addr:full":"Calle de Cipriano Escudero, 4 Cisterniga Valladolid 47193",
    "addr:housenumber":"4",
    "addr:postcode":"47193",
    "addr:street":"Calle De Cipriano Escudero",
    "iso:country":"ES",
    "sg:address":"Calle de Cipriano Escudero, 4",
    "sg:city":"Cisterniga",
    "sg:orig_category":"Quiropr\u00c1cticos",
    "sg:phone":"+34 983 40 17 06",
    "sg:postcode":"47193",
    "sg:province":"Valladolid",
    "wof:name":"Sanz Rojo Juan Pablo",
    "wof:placetype":"venue"
},
  "geometry": {"coordinates":[-4.6852788925,41.6147003174],"type":"Point"}
}