{
  "type": "Feature",
  "properties": {
    "iso:country":"ES",
    "sg:address":"Carrer de Enginyer Moncunill, 57",
    "sg:city":"Hospitalet Llobregat",
    "sg:orig_category":"Restaurantes",
    "sg:phone":"+34 934 40 01 44",
    "sg:postcode":"08905",
    "sg:province":"Barcelona",
    "wof:name":"Ruiz Calero Francisco",
    "wof:placetype":"venue"
},
  "geometry": {"coordinates":[2.1082201004,41.369644165],"type":"Point"}
}