{
  "type": "Feature",
  "properties": {
    "iso:country":"ES",
    "sg:address":"Avda Pablo Picasso, 4",
    "sg:city":"Venta De Ba\u00e7os",
    "sg:orig_category":"Transporte En General",
    "sg:phone":"+34 979 77 13 30",
    "sg:postcode":"34200",
    "sg:province":"Palencia",
    "wof:name":"Distribuciones Froiz S.a.",
    "wof:placetype":"venue"
},
  "geometry": {"coordinates":[-4.4905219078,41.9189033508],"type":"Point"}
}