{
  "type": "Feature",
  "properties": {
    "iso:country":"ES",
    "sg:address":"Pg Sant Antoni, 14",
    "sg:city":"Barcelona",
    "sg:orig_category":"Inmobiliaria (agencias)",
    "sg:phone":"+34 933 32 14 11",
    "sg:postcode":"08014",
    "sg:province":"Barcelona",
    "wof:name":"Toran-l'habitatge S.l.",
    "wof:placetype":"venue"
},
  "geometry": {"coordinates":[2.1369869709,41.3765258789],"type":"Point"}
}