{
  "type": "Feature",
  "properties": {
    "iso:country":"ES",
    "sg:address":"Quinto Pino, 18",
    "sg:city":"Santander",
    "sg:orig_category":"Alimentaci\u00d3n General (al Por Menor)",
    "sg:phone":"+34 942 36 03 68",
    "sg:postcode":"39003",
    "sg:province":"Cantabria",
    "wof:name":"Fernandez Gonzalez Bego\u00f1a",
    "wof:placetype":"venue"
},
  "geometry": {"coordinates":[-3.8100090027,43.4614982605],"type":"Point"}
}