{
  "type": "Feature",
  "properties": {
    "iso:country":"ES",
    "sg:address":"Carrer de Santa Joaquima, 2",
    "sg:city":"Manresa",
    "sg:orig_category":"Internados & Ense\u00d1anza Privada",
    "sg:phone":"+34 938 73 99 47",
    "sg:postcode":"08002",
    "sg:province":"Barcelona",
    "wof:name":"Col Legi Sagrat Cor En Manresa Carmelitas De La Caridad Prov Tarragona",
    "wof:placetype":"venue"
},
  "geometry": {"coordinates":[1.8367960453,41.743434906],"type":"Point"}
}