{
  "type": "Feature",
  "properties": {
    "iso:country":"ES",
    "sg:address":"Zaragoza, 15",
    "sg:city":"Iglesuela Cid",
    "sg:orig_category":"Arquitectos",
    "sg:phone":"+34 964 44 34 79",
    "sg:postcode":"44142",
    "sg:province":"Teruel",
    "wof:name":"Tena Gazulla Jose Luis",
    "wof:placetype":"venue"
},
  "geometry": {"coordinates":[-0.318475008,40.4805984497],"type":"Point"}
}