{
  "type": "Feature",
  "properties": {
    "addr:full":"Avda Bele\u00d1a, S/n Guadalajara Guadalajara 19005",
    "addr:housenumber":"s",
    "addr:postcode":"19005",
    "addr:street":"Avda Belen\u0303A;/ N",
    "iso:country":"ES",
    "sg:address":"Avda Bele\u00d1a, S/n",
    "sg:city":"Guadalajara",
    "sg:orig_category":"Promotores Constructores",
    "sg:phone":"+34 949 82 00 60",
    "sg:postcode":"19005",
    "sg:province":"Guadalajara",
    "wof:name":"Rayet S.a.",
    "wof:placetype":"venue"
},
  "geometry": {"coordinates":[-3.1616559029,40.6382598877],"type":"Point"}
}