{
  "type": "Feature",
  "properties": {
    "iso:country":"ES",
    "sg:address":"Carr Esglesia, 28",
    "sg:city":"Sils",
    "sg:orig_category":"Animales (al Por Menor)",
    "sg:phone":"+34 972 85 32 53",
    "sg:postcode":"17410",
    "sg:province":"Girona",
    "wof:name":"Comercial D'aus Ca\u00f1et S.a.",
    "wof:placetype":"venue"
},
  "geometry": {"coordinates":[2.743710041,41.807144165],"type":"Point"}
}