{
  "type": "Feature",
  "properties": {
    "addr:full":"Santalaitz Kalea, 6 Bergara Guip\u00f9zcoa 20570",
    "addr:housenumber":"6",
    "addr:postcode":"20570",
    "addr:street":"Santalaitz Kalea;Guipu\u0300Zcoa",
    "iso:country":"ES",
    "sg:address":"Santalaitz Kalea, 6",
    "sg:city":"Bergara",
    "sg:orig_category":"Calderer\u00cda",
    "sg:phone":"+34 943 76 46 14",
    "sg:postcode":"20570",
    "sg:province":"Guip\u00f9zcoa",
    "wof:name":"Talleres Zubikua S.l.",
    "wof:placetype":"venue"
},
  "geometry": {"coordinates":[-2.4227828979,43.1242218018],"type":"Point"}
}