{
  "type": "Feature",
  "properties": {
    "iso:country":"ES",
    "sg:address":"Calle de Isaac Peral (de), 27",
    "sg:city":"Coslada",
    "sg:orig_category":"Maquinaria Para Industrias Diversas",
    "sg:phone":"+34 916 73 69 13",
    "sg:postcode":"28820",
    "sg:province":"Madrid",
    "wof:name":"Cater-kom Internacional S.l.",
    "wof:placetype":"venue"
},
  "geometry": {"coordinates":[-3.5357329845,40.4385948181],"type":"Point"}
}