{
  "type": "Feature",
  "properties": {
    "iso:country":"ES",
    "sg:address":"Calle de Juan Perez Albaladejo, 3",
    "sg:city":"Churra",
    "sg:orig_category":"Mec\u00c1nico Del Autom\u00d3vil",
    "sg:phone":"+34 968 83 15 81",
    "sg:postcode":"30110",
    "sg:province":"Murcia",
    "wof:name":"Cayetano Aranda Mu\u00f1oz S.l.",
    "wof:placetype":"venue"
},
  "geometry": {"coordinates":[-1.1340190172,38.0222167969],"type":"Point"}
}