{
  "type": "Feature",
  "properties": {
    "addr:full":"Calle de Alta Del Mar, 68 Valencia Valencia 46024",
    "addr:housenumber":"68",
    "addr:postcode":"46024",
    "addr:street":"Calle De Alta Del Mar",
    "iso:country":"ES",
    "sg:address":"Calle de Alta Del Mar, 68",
    "sg:city":"Valencia",
    "sg:orig_category":"Cajas De Ahorro",
    "sg:phone":"+34 963 67 52 61",
    "sg:postcode":"46024",
    "sg:province":"Valencia",
    "wof:name":"Caja De Ahorros De Valencia Castellon Y Alicante",
    "wof:placetype":"venue"
},
  "geometry": {"coordinates":[-0.3337942064,39.4494094849],"type":"Point"}
}