{
  "type": "Feature",
  "properties": {
    "addr:full":"Calle de Calvario, 26 Granadilla Abona Santa Cruz De Tenerife 38600",
    "addr:housenumber":"26",
    "addr:postcode":"38600",
    "addr:street":"Calle De Calvario",
    "iso:country":"ES",
    "sg:address":"Calle de Calvario, 26",
    "sg:city":"Granadilla Abona",
    "sg:orig_category":"Art\u00cdculos De Regalo (al Por Menor)",
    "sg:phone":"+34 922 77 29 97",
    "sg:postcode":"38600",
    "sg:province":"Santa Cruz De Tenerife",
    "wof:name":"Palgoya S.l.",
    "wof:placetype":"venue"
},
  "geometry": {"coordinates":[-16.5769100189,28.1201820374],"type":"Point"}
}