{
  "type": "Feature",
  "properties": {
    "addr:full":"Calle de Cristo De La Luz, 27 Toledo Toledo 45003",
    "addr:housenumber":"27",
    "addr:postcode":"45003",
    "addr:street":"Calle De Cristo De La Luz",
    "iso:country":"ES",
    "sg:address":"Calle de Cristo De La Luz, 27",
    "sg:city":"Toledo",
    "sg:orig_category":"Tapicer\u00cdas",
    "sg:phone":"+34 925 22 22 29",
    "sg:postcode":"45003",
    "sg:province":"Toledo",
    "wof:name":"Viso Garcia Domiciano Del",
    "wof:placetype":"venue"
},
  "geometry": {"coordinates":[-4.0249896049,39.861125946],"type":"Point"}
}