{
  "type": "Feature",
  "properties": {
    "addr:full":"Ctra Canet-los Valles, Km. 0002,5 Puerto Sagunto Valencia 46520",
    "addr:postcode":"46520",
    "addr:street":"Ctra Canet-Los Valles Km. 0002,5 Puerto",
    "iso:country":"ES",
    "sg:address":"Ctra Canet-los Valles, Km. 0002,5",
    "sg:city":"Puerto Sagunto",
    "sg:orig_category":"Negocio De Materiales De Construcci\u00d3n",
    "sg:phone":"+34 962 67 41 99",
    "sg:postcode":"46520",
    "sg:province":"Valencia",
    "wof:name":"Myvac S.l.",
    "wof:placetype":"venue"
},
  "geometry": {"coordinates":[-0.2025949955,39.7040786743],"type":"Point"}
}