{
  "type": "Feature",
  "properties": {
    "addr:full":"Iguarte, 3 Usurbil Guip\u00f9zcoa 20170",
    "addr:housenumber":"3",
    "addr:postcode":"20170",
    "addr:street":"Iguarte;Guipu\u0300Zcoa",
    "iso:country":"ES",
    "sg:address":"Iguarte, 3",
    "sg:city":"Usurbil",
    "sg:orig_category":"Ebanister\u00cda",
    "sg:phone":"+34 943 37 64 15",
    "sg:postcode":"20170",
    "sg:province":"Guip\u00f9zcoa",
    "wof:name":"Urruzola Vitoria Antonio",
    "wof:placetype":"venue"
},
  "geometry": {"coordinates":[-2.0539140701,43.2733459473],"type":"Point"}
}