{
  "type": "Feature",
  "properties": {
    "addr:full":"Calle de Echegaray, 13 Jaca Huesca 22700",
    "addr:housenumber":"13",
    "addr:postcode":"22700",
    "addr:street":"Calle De Echegaray",
    "iso:country":"ES",
    "sg:address":"Calle de Echegaray, 13",
    "sg:city":"Jaca",
    "sg:orig_category":"Fabricaci\u00d3n De Mantequilla (al Por Mayor)",
    "sg:phone":"+34 974 35 56 09",
    "sg:postcode":"22700",
    "sg:province":"Huesca",
    "wof:name":"Gallego Felices Cristina",
    "wof:placetype":"venue"
},
  "geometry": {"coordinates":[-0.5492563248,42.5702285767],"type":"Point"}
}