{
  "type": "Feature",
  "properties": {
    "iso:country":"ES",
    "sg:address":"Calle de Bailen, 14",
    "sg:city":"Alacant",
    "sg:orig_category":"Ortopedia General",
    "sg:phone":"+34 965 20 90 88",
    "sg:postcode":"03001",
    "sg:province":"Alicante",
    "wof:name":"Ortopedia Costablanca S. L.",
    "wof:placetype":"venue"
},
  "geometry": {"coordinates":[-0.4844602942,38.3451118469],"type":"Point"}
}