{
  "type": "Feature",
  "properties": {
    "addr:full":"Calle de Orilla De La Via, S/n Infante Juan Manuel Murcia 30012",
    "addr:postcode":"30012",
    "addr:street":"Calle De Orilla De La Via S / N Infante Juan",
    "iso:country":"ES",
    "sg:address":"Calle de Orilla De La Via, S/n",
    "sg:city":"Infante Juan Manuel",
    "sg:orig_category":"Poli\u00c9ster",
    "sg:phone":"+34 968 34 47 67",
    "sg:postcode":"30012",
    "sg:province":"Murcia",
    "wof:name":"Libalplas S.l.",
    "wof:placetype":"venue"
},
  "geometry": {"coordinates":[-1.1148940325,37.9730567932],"type":"Point"}
}