{
  "type": "Feature",
  "properties": {
    "iso:country":"ES",
    "sg:address":"Carrer de Fonollar, 4",
    "sg:city":"Barcelona",
    "sg:orig_category":"Molduras, Junquillos, Listones Y Molduras Perforadas",
    "sg:phone":"+34 933 19 45 91",
    "sg:postcode":"08003",
    "sg:province":"Barcelona",
    "wof:name":"Perez Mi\u00f1arro Javiera",
    "wof:placetype":"venue"
},
  "geometry": {"coordinates":[2.1800899506,41.3868026733],"type":"Point"}
}