{
  "type": "Feature",
  "properties": {
    "iso:country":"ES",
    "sg:address":"Calle de Eduardo Ibarra, 1",
    "sg:city":"Zaragoza",
    "sg:orig_category":"Tintorer\u00cdas, Limpieza En Seco",
    "sg:phone":"+34 976 55 80 98",
    "sg:postcode":"50009",
    "sg:province":"Zaragoza",
    "wof:name":"Lanuza Aznar S.c.",
    "wof:placetype":"venue"
},
  "geometry": {"coordinates":[-0.9015939832,41.638458252],"type":"Point"}
}