{
  "type": "Feature",
  "properties": {
    "addr:full":"Via Portugal, 24 Manacor Islas Baleares 07500",
    "addr:housenumber":"24",
    "addr:postcode":"07500",
    "addr:street":"Via Portugal",
    "iso:country":"ES",
    "sg:address":"Via Portugal, 24",
    "sg:city":"Manacor",
    "sg:orig_category":"Pintura, Barniz, Productos Asimilables (fabricaci\u00d3n, Al Por Mayor)",
    "sg:phone":"+34 971 55 45 15",
    "sg:postcode":"07500",
    "sg:province":"Islas Baleares",
    "wof:name":"Bruper S. A.",
    "wof:placetype":"venue"
},
  "geometry": {"coordinates":[3.2156839371,39.5668716431],"type":"Point"}
}