{
  "type": "Feature",
  "properties": {
    "iso:country":"ES",
    "sg:address":"Calle de Pablo Iglesias, 16",
    "sg:city":"Zaragoza",
    "sg:orig_category":"Panader\u00cdas, Panader\u00cdas",
    "sg:phone":"+34 976 52 82 32",
    "sg:postcode":"50018",
    "sg:province":"Zaragoza",
    "wof:name":"Herrero Castillo Francisco Antonio",
    "wof:placetype":"venue"
},
  "geometry": {"coordinates":[-0.8861029744,41.6772613525],"type":"Point"}
}