{
  "type": "Feature",
  "properties": {
    "addr:full":"Calle de Atocha, 108 Madrid Madrid 28012",
    "addr:housenumber":"108",
    "addr:postcode":"28012",
    "addr:street":"Calle De Atocha",
    "iso:country":"ES",
    "sg:address":"Calle de Atocha, 108",
    "sg:city":"Madrid",
    "sg:orig_category":"Librer\u00cdas",
    "sg:phone":"+34 915 30 13 48",
    "sg:postcode":"28012",
    "sg:province":"Madrid",
    "wof:name":"Aviles Garcia Jose",
    "wof:placetype":"venue"
},
  "geometry": {"coordinates":[-3.6939330101,40.4098320007],"type":"Point"}
}