{
  "type": "Feature",
  "properties": {
    "iso:country":"ES",
    "sg:address":"Carrer de Ramon Llull, 61",
    "sg:city":"Terrassa",
    "sg:orig_category":"Sociedades, Compa\u00d1\u00cdas Aseguradoras",
    "sg:phone":"+34 937 80 83 33",
    "sg:postcode":"08224",
    "sg:province":"Barcelona",
    "wof:name":"Prodegest S.l.",
    "wof:placetype":"venue"
},
  "geometry": {"coordinates":[2.002177,41.5572547913],"type":"Point"}
}