{
  "type": "Feature",
  "properties": {
    "addr:full":"Cllo Pitote, 1 Toledo Toledo 45002",
    "addr:housenumber":"1",
    "addr:postcode":"45002",
    "addr:street":"Pitote",
    "iso:country":"ES",
    "sg:address":"Cllo Pitote, 1",
    "sg:city":"Toledo",
    "sg:orig_category":"Centros Empresariales",
    "sg:phone":"+34 925 21 41 08",
    "sg:postcode":"45002",
    "sg:province":"Toledo",
    "wof:name":"Romero Taboada Margarita",
    "wof:placetype":"venue"
},
  "geometry": {"coordinates":[-4.0217690468,39.8536682129],"type":"Point"}
}