{
  "type": "Feature",
  "properties": {
    "addr:full":"Av Pais Valencia, 19 Elche Alicante 03201",
    "addr:housenumber":"19",
    "addr:postcode":"03201",
    "addr:street":"Av Pais Valencia",
    "iso:country":"ES",
    "sg:address":"Av Pais Valencia, 19",
    "sg:city":"Elche",
    "sg:orig_category":"Cajas Para Embalar",
    "sg:phone":"+34 965 46 66 30",
    "sg:postcode":"03201",
    "sg:province":"Alicante",
    "wof:name":"Caja Rural Central De Orihuela",
    "wof:placetype":"venue"
},
  "geometry": {"coordinates":[-0.7005890012,38.2671318054],"type":"Point"}
}