{
  "type": "Feature",
  "properties": {
    "addr:full":"Pase Matutino, 33 Ponteareas Pontevedra 36860",
    "addr:housenumber":"33",
    "addr:postcode":"36860",
    "addr:street":"Matutino",
    "iso:country":"ES",
    "sg:address":"Pase Matutino, 33",
    "sg:city":"Ponteareas",
    "sg:orig_category":"Caf\u00c9s, Bares, Cervecer\u00cdas",
    "sg:phone":"+34 986 64 22 49",
    "sg:postcode":"36860",
    "sg:province":"Pontevedra",
    "wof:name":"Rollick C.b.",
    "wof:placetype":"venue"
},
  "geometry": {"coordinates":[-8.5163888931,42.1783599854],"type":"Point"}
}