{
  "type": "Feature",
  "properties": {
    "addr:full":"Calle de Dep. Ramon Mendizabal, 25 Alacant Alicante 03006",
    "addr:housenumber":"25",
    "addr:postcode":"03006",
    "addr:street":"Calle De Dep. Ramon Mendizabal",
    "iso:country":"ES",
    "sg:address":"Calle de Dep. Ramon Mendizabal, 25",
    "sg:city":"Alacant",
    "sg:orig_category":"Electricidad: Instaladores",
    "sg:phone":"+34 965 28 68 14",
    "sg:postcode":"03006",
    "sg:province":"Alicante",
    "wof:name":"Ivorra Garcia Juan Jose",
    "wof:placetype":"venue"
},
  "geometry": {"coordinates":[-0.573071301,38.367855072],"type":"Point"}
}