{
  "type": "Feature",
  "properties": {
    "addr:full":"Calle de Virgen De Los Desamparados, 13 Torrent Valencia 46900",
    "addr:housenumber":"13",
    "addr:postcode":"46900",
    "addr:street":"Calle De Virgen De Los Desamparados;Valencia",
    "iso:country":"ES",
    "sg:address":"Calle de Virgen De Los Desamparados, 13",
    "sg:city":"Torrent",
    "sg:classifiers":[
        {
            "category":"Food & Beverages",
            "subcategory":"Candy",
            "type":"Retail Goods"
        }
    ],
    "sg:phone":"+34 961 55 12 13",
    "sg:postcode":"46900",
    "sg:province":"Valencia",
    "sg:tags":[
        "confiter\u00cdas",
        "y",
        "de",
        "fabricaci\u00d3n",
        "chocolate"
    ],
    "wof:name":"Comercial Yago S. L.",
    "wof:placetype":"venue"
},
  "geometry": {"coordinates":[-0.4656159878,39.4384918213],"type":"Point"}
}