{
  "type": "Feature",
  "properties": {
    "addr:full":"Calle de Cruz, 24 Navas San Juan Ja\u00e9n 23240",
    "addr:housenumber":"24",
    "addr:postcode":"23240",
    "addr:street":"Calle De Cruz",
    "iso:country":"ES",
    "sg:address":"Calle de Cruz, 24",
    "sg:city":"Navas San Juan",
    "sg:orig_category":"Peluquer\u00cdas, Peluquer\u00cda Mixta",
    "sg:phone":"+34 953 68 92 03",
    "sg:postcode":"23240",
    "sg:province":"Ja\u00e9n",
    "wof:name":"Belmonte Reyes Rosa Maria",
    "wof:placetype":"venue"
},
  "geometry": {"coordinates":[-3.3189020157,38.1818504333],"type":"Point"}
}