{
  "type": "Feature",
  "properties": {
    "addr:full":"Carrer de Rossello, 6 Granollers Barcelona 08401",
    "addr:housenumber":"6",
    "addr:postcode":"08401",
    "addr:street":"Carrer De Rossello",
    "iso:country":"ES",
    "sg:address":"Carrer de Rossello, 6",
    "sg:city":"Granollers",
    "sg:orig_category":"Mec\u00c1nico Del Autom\u00d3vil",
    "sg:phone":"+34 938 40 17 00",
    "sg:postcode":"08401",
    "sg:province":"Barcelona",
    "wof:name":"Automovils Alfred Fonseca S.l.",
    "wof:placetype":"venue"
},
  "geometry": {"coordinates":[2.2889740467,41.6142921448],"type":"Point"}
}