{
  "type": "Feature",
  "properties": {
    "iso:country":"ES",
    "sg:address":"Carrer de Reina Amalia, 20",
    "sg:city":"Barcelona",
    "sg:orig_category":"Librer\u00cdas",
    "sg:phone":"+34 934 41 27 80",
    "sg:postcode":"08001",
    "sg:province":"Barcelona",
    "wof:name":"Distribuciones De Enlace S. A.",
    "wof:placetype":"venue"
},
  "geometry": {"coordinates":[2.1663401127,41.3772697449],"type":"Point"}
}