{
  "type": "Feature",
  "properties": {
    "iso:country":"ES",
    "sg:address":"Calle de Marques De Comillas, 13",
    "sg:city":"Laredo",
    "sg:orig_category":"Abogados",
    "sg:phone":"+34 942 61 30 25",
    "sg:postcode":"39770",
    "sg:province":"Cantabria",
    "wof:name":"Perez Pi\u00f1ero Maria Teresa",
    "wof:placetype":"venue"
},
  "geometry": {"coordinates":[-3.417057991,43.4100532532],"type":"Point"}
}