{
  "type": "Feature",
  "properties": {
    "iso:country":"ES",
    "sg:address":"Calle de Progreso, 15",
    "sg:city":"Espinosa De Los Monteros",
    "sg:orig_category":"Molduras, Junquillos, Listones Y Molduras Perforadas",
    "sg:phone":"+34 947 12 00 43",
    "sg:postcode":"09560",
    "sg:province":"Burgos",
    "wof:name":"Lopez Hernandez Luis Maria",
    "wof:placetype":"venue"
},
  "geometry": {"coordinates":[-3.5501770973,43.0760421753],"type":"Point"}
}