{
  "type": "Feature",
  "properties": {
    "addr:full":"Carrer de Maladeta, 73 Barcelona Barcelona 08016",
    "addr:housenumber":"73",
    "addr:postcode":"08016",
    "addr:street":"Carrer De Maladeta",
    "iso:country":"ES",
    "sg:address":"Carrer de Maladeta, 73",
    "sg:city":"Barcelona",
    "sg:orig_category":"Mec\u00c1nico Del Autom\u00d3vil",
    "sg:phone":"+34 933 40 77 93",
    "sg:postcode":"08016",
    "sg:province":"Barcelona",
    "wof:name":"Talleres Escultor Ordo\u00f1ez S.c.p.",
    "wof:placetype":"venue"
},
  "geometry": {"coordinates":[2.1744499207,41.4332809448],"type":"Point"}
}