{
  "type": "Feature",
  "properties": {
    "addr:full":"Avda Menendez Y Pelayo, 1 Valencia Valencia 46010",
    "addr:housenumber":"1",
    "addr:postcode":"46010",
    "addr:street":"Avda Menendez Y Pelayo",
    "iso:country":"ES",
    "sg:address":"Avda Menendez Y Pelayo, 1",
    "sg:city":"Valencia",
    "sg:orig_category":"Promotores Constructores",
    "sg:phone":"+34 963 60 36 40",
    "sg:postcode":"46010",
    "sg:province":"Valencia",
    "wof:name":"Villas De Futuro S.l.",
    "wof:placetype":"venue"
},
  "geometry": {"coordinates":[-0.3641830087,39.4804725647],"type":"Point"}
}