{
  "type": "Feature",
  "properties": {
    "iso:country":"ES",
    "sg:address":"Plaz Escultor Pastor, 7",
    "sg:city":"Valencia",
    "sg:orig_category":"Zapatos (al Por Menor)",
    "sg:phone":"+34 963 33 61 60",
    "sg:postcode":"46013",
    "sg:province":"Valencia",
    "wof:name":"Navarro Rodriguez Marisol",
    "wof:placetype":"venue"
},
  "geometry": {"coordinates":[-0.3675320148,39.4437561035],"type":"Point"}
}