{
  "type": "Feature",
  "properties": {
    "addr:full":"Calle de Mayor, 4 Najera La Rioja 26300",
    "addr:housenumber":"4",
    "addr:postcode":"26300",
    "addr:street":"Calle De Mayor;Rioja",
    "iso:country":"ES",
    "sg:address":"Calle de Mayor, 4",
    "sg:city":"Najera",
    "sg:orig_category":"Ense\u00d1anza: Idiomas",
    "sg:phone":"+34 941 36 38 68",
    "sg:postcode":"26300",
    "sg:province":"La Rioja",
    "wof:name":"Centro De Ense\u00f1anza De La Rioja S.l.",
    "wof:placetype":"venue"
},
  "geometry": {"coordinates":[-2.7342190742,42.4165115356],"type":"Point"}
}