{
  "type": "Feature",
  "properties": {
    "addr:full":"Calle de Magallanes, 46 Madrid Madrid 28015",
    "addr:housenumber":"46",
    "addr:postcode":"madrid;28015",
    "addr:street":"Calle De Magallanes",
    "iso:country":"ES",
    "sg:address":"Calle de Magallanes, 46",
    "sg:city":"Madrid",
    "sg:orig_category":"Carnicer\u00cdas, Carnicer\u00cdas",
    "sg:phone":"+34 914 47 85 76",
    "sg:postcode":"28015",
    "sg:province":"Madrid",
    "wof:name":"Gomez Martinez Roque",
    "wof:placetype":"venue"
},
  "geometry": {"coordinates":[-3.7054688931,40.4364280701],"type":"Point"}
}