{
  "type": "Feature",
  "properties": {
    "iso:country":"ES",
    "sg:address":"Afores, S/n",
    "sg:city":"Colomers",
    "sg:orig_category":"Arenas, Guijarros Y Granulados",
    "sg:phone":"+34 972 76 83 86",
    "sg:postcode":"17144",
    "sg:province":"Girona",
    "wof:name":"Aridos Uniland S.a.",
    "wof:placetype":"venue"
},
  "geometry": {"coordinates":[2.9900569916,42.0863265991],"type":"Point"}
}