{
  "type": "Feature",
  "properties": {
    "addr:full":"Calle de General Pardi\u00d1as, 20 Madrid Madrid 28001",
    "addr:housenumber":"20",
    "addr:postcode":"madrid;28001",
    "addr:street":"Calle De General Pardin\u0303As",
    "iso:country":"ES",
    "sg:address":"Calle de General Pardi\u00d1as, 20",
    "sg:city":"Madrid",
    "sg:orig_category":"Asistencia Social",
    "sg:phone":"+34 914 35 65 43",
    "sg:postcode":"28001",
    "sg:province":"Madrid",
    "wof:name":"Asociacion Ab Padres Separados Divorciados",
    "wof:placetype":"venue"
},
  "geometry": {"coordinates":[-3.6786346436,40.4251594543],"type":"Point"}
}