{
  "type": "Feature",
  "properties": {
    "iso:country":"ES",
    "sg:address":"Ibarabarri Edificio F, 1",
    "sg:city":"Leioa",
    "sg:orig_category":"Arquitectos",
    "sg:phone":"+34 944 80 56 61",
    "sg:postcode":"48940",
    "sg:province":"Vizcaya",
    "wof:name":"Ricardo Gonzalez Vara",
    "wof:placetype":"venue"
},
  "geometry": {"coordinates":[-2.9860789776,43.3275489807],"type":"Point"}
}