{
  "type": "Feature",
  "properties": {
    "addr:full":"Panadero, 16 El Paso Santa Cruz De Tenerife 38750",
    "addr:housenumber":"16",
    "addr:postcode":"38750",
    "addr:street":"Panadero",
    "iso:country":"ES",
    "sg:address":"Panadero, 16",
    "sg:city":"El Paso",
    "sg:orig_category":"Arboricultura Y Producci\u00d3n De Frutas",
    "sg:phone":"+34 922 48 61 60",
    "sg:postcode":"38750",
    "sg:province":"Santa Cruz De Tenerife",
    "wof:name":"Zechmeister  Heinz",
    "wof:placetype":"venue"
},
  "geometry": {"coordinates":[-17.8883419037,28.6447601318],"type":"Point"}
}