{
  "type": "Feature",
  "properties": {
    "iso:country":"ES",
    "sg:address":"Calle de Nagusia, 11",
    "sg:city":"Arizgoiti",
    "sg:orig_category":"M\u00c9dicos: Medicina General Orientada A La Acupuntura",
    "sg:phone":"+34 944 49 65 38",
    "sg:postcode":"48970",
    "sg:province":"Vizcaya",
    "wof:name":"Acupuntura Su",
    "wof:placetype":"venue"
},
  "geometry": {"coordinates":[-2.8857843876,43.2364845276],"type":"Point"}
}