{
  "type": "Feature",
  "properties": {
    "iso:country":"ES",
    "sg:address":"Ctra Salamanca, 13",
    "sg:city":"Avila",
    "sg:orig_category":"Quincaller\u00cda (al Por Menor)",
    "sg:phone":"+34 920 21 28 80",
    "sg:postcode":"05002",
    "sg:province":"\u00c1vila",
    "wof:name":"Fragua Rodriguez Emilio",
    "wof:placetype":"venue"
},
  "geometry": {"coordinates":[-4.7107338905,40.6579284668],"type":"Point"}
}