{
  "type": "Feature",
  "properties": {
    "iso:country":"ES",
    "sg:address":"Calle de Enmedio, 5",
    "sg:city":"Castellon",
    "sg:orig_category":"Perfumer\u00cda (al Por Menor)",
    "sg:phone":"+34 964 24 80 89",
    "sg:postcode":"12001",
    "sg:province":"Castell\u00f3n",
    "wof:name":"Gocare S.l.",
    "wof:placetype":"venue"
},
  "geometry": {"coordinates":[-0.0387750007,39.9848632812],"type":"Point"}
}