{
  "type": "Feature",
  "properties": {
    "addr:full":"Calle de Santa Teresa, 28 Meliana Valencia 46133",
    "addr:housenumber":"28",
    "addr:postcode":"46133",
    "addr:street":"Calle De Santa Teresa",
    "iso:country":"ES",
    "sg:address":"Calle de Santa Teresa, 28",
    "sg:city":"Meliana",
    "sg:orig_category":"Electricidad: Instaladores",
    "sg:phone":"+34 961 49 54 95",
    "sg:postcode":"46133",
    "sg:province":"Valencia",
    "wof:name":"Granado Curiel Joaquin",
    "wof:placetype":"venue"
},
  "geometry": {"coordinates":[-0.3458679914,39.5301780701],"type":"Point"}
}