{
  "type": "Feature",
  "properties": {
    "iso:country":"ES",
    "sg:address":"Calle de General Iba\u00d1ez De Ibero, 5",
    "sg:city":"Madrid",
    "sg:orig_category":"Confecci\u00d3n De Trajes Para Se\u00d1oras",
    "sg:phone":"+34 915 33 11 33",
    "sg:postcode":"28003",
    "sg:province":"Madrid",
    "wof:name":"Rodriguez Garcia Maria Mercedes",
    "wof:placetype":"venue"
},
  "geometry": {"coordinates":[-3.7103381157,40.4450721741],"type":"Point"}
}