{
  "type": "Feature",
  "properties": {
    "iso:country":"ES",
    "sg:address":"Ctra Murcia (de), 25",
    "sg:city":"Caravaca Cruz",
    "sg:orig_category":"Mec\u00c1nico Del Autom\u00d3vil",
    "sg:phone":"+34 968 70 56 59",
    "sg:postcode":"30400",
    "sg:province":"Murcia",
    "wof:name":"Talleres Santa Cruz De Caravaca S.l.",
    "wof:placetype":"venue"
},
  "geometry": {"coordinates":[-1.852118969,38.1047477722],"type":"Point"}
}