{
  "type": "Feature",
  "properties": {
    "iso:country":"ES",
    "sg:address":"Carrer de Mata, 13",
    "sg:city":"Barcelona",
    "sg:orig_category":"Congelados: Productos Alimentarios (al Por Menor)",
    "sg:phone":"+34 934 43 10 18",
    "sg:postcode":"08004",
    "sg:province":"Barcelona",
    "wof:name":"C Lopez J Rojo Scp",
    "wof:placetype":"venue"
},
  "geometry": {"coordinates":[2.1708390713,41.3726119995],"type":"Point"}
}