{
  "type": "Feature",
  "properties": {
    "addr:full":"Calle de Santa Maria Kalea, S/n Tolosa Guip\u00f9zcoa 20400",
    "addr:housenumber":"s / n",
    "addr:postcode":"20400",
    "addr:street":"Calle De Santa Maria Kalea;Guipu\u0300Zcoa",
    "iso:country":"ES",
    "sg:address":"Calle de Santa Maria Kalea, S/n",
    "sg:city":"Tolosa",
    "sg:orig_category":"Asociaciones, Organismos Culturales Y Socioeducativos",
    "sg:phone":"+34 943 67 06 20",
    "sg:postcode":"20400",
    "sg:province":"Guip\u00f9zcoa",
    "wof:name":"Kabi Alai-sociedad Recreativa",
    "wof:placetype":"venue"
},
  "geometry": {"coordinates":[-2.0711290836,43.1387252808],"type":"Point"}
}