{
  "type": "Feature",
  "properties": {
    "iso:country":"ES",
    "sg:address":"Calle de Grande, 11",
    "sg:city":"Quintanar Orden",
    "sg:orig_category":"Ropa Para Se\u00d1oras (al Por Menor)",
    "sg:phone":"+34 925 18 09 80",
    "sg:postcode":"45800",
    "sg:province":"Toledo",
    "wof:name":"Boutique Abi S.l.",
    "wof:placetype":"venue"
},
  "geometry": {"coordinates":[-3.0432600975,39.592300415],"type":"Point"}
}