{
  "type": "Feature",
  "properties": {
    "iso:country":"ES",
    "sg:address":"Ptda Arnachares, S/n",
    "sg:city":"Alborache",
    "sg:orig_category":"Poli\u00c9ster",
    "sg:phone":"+34 962 12 74 98",
    "sg:postcode":"46369",
    "sg:province":"Valencia",
    "wof:name":"J.f.r.reparacion Y Fabricacion En Poliester S.l.",
    "wof:placetype":"venue"
},
  "geometry": {"coordinates":[-0.7721949816,39.392906189],"type":"Point"}
}