{
  "type": "Feature",
  "properties": {
    "iso:country":"ES",
    "sg:address":"Poli Industrial Pineda 'calle E', 8",
    "sg:city":"Sevilla",
    "sg:orig_category":"Gases Industriales",
    "sg:phone":"+34 954 68 90 99",
    "sg:postcode":"41013",
    "sg:province":"Sevilla",
    "wof:name":"Instalaciones Y Servicios Energeticos De Andalucia S.a.",
    "wof:placetype":"venue"
},
  "geometry": {"coordinates":[-5.9555873871,37.3235321045],"type":"Point"}
}