{
  "type": "Feature",
  "properties": {
    "iso:country":"ES",
    "sg:address":"Pol. Ind. Can Barri, 11",
    "sg:city":"Bigues",
    "sg:orig_category":"Adhesivos (fabricaci\u00d3n, Al Por Mayor)",
    "sg:phone":"+34 938 65 78 00",
    "sg:postcode":"08415",
    "sg:province":"Barcelona",
    "wof:name":"Distrex Iberica S. A.",
    "wof:placetype":"venue"
},
  "geometry": {"coordinates":[2.2144351006,41.67345047],"type":"Point"}
}