{
  "type": "Feature",
  "properties": {
    "addr:full":"Calle de D(campollano), 18 Albacete Albacete 02006",
    "addr:housenumber":"18",
    "addr:postcode":"02006",
    "addr:street":"Calle De D Campollano",
    "iso:country":"ES",
    "sg:address":"Calle de D(campollano), 18",
    "sg:city":"Albacete",
    "sg:orig_category":"Servicios Diversos",
    "sg:phone":"+34 967 52 20 76",
    "sg:postcode":"02006",
    "sg:province":"Albacete",
    "wof:name":"Kukers S.l.",
    "wof:placetype":"venue"
},
  "geometry": {"coordinates":[-1.9490209818,39.013168335],"type":"Point"}
}