{
  "type": "Feature",
  "properties": {
    "addr:full":"Calle de Escuelas, 12 Montilla C\u00f3rdoba 14550",
    "addr:housenumber":"12",
    "addr:postcode":"14550",
    "addr:street":"Calle De Escuelas;Co\u0301Rdoba",
    "iso:country":"ES",
    "sg:address":"Calle de Escuelas, 12",
    "sg:city":"Montilla",
    "sg:orig_category":"Laboratorios Y Cl\u00cdnicas Veterinarias",
    "sg:phone":"+34 957 65 37 02",
    "sg:postcode":"14550",
    "sg:province":"C\u00f3rdoba",
    "wof:name":"Lopez Rasero Jesus Carlos",
    "wof:placetype":"venue"
},
  "geometry": {"coordinates":[-4.6374530792,37.5888023376],"type":"Point"}
}