{
  "type": "Feature",
  "properties": {
    "iso:country":"ES",
    "sg:address":"Pase Fernandez Jara (de), 9",
    "sg:city":"Torres Cotillas",
    "sg:orig_category":"Asesor\u00cda Sobre Comunicaci\u00d3n De Empresas",
    "sg:phone":"+34 968 62 77 83",
    "sg:postcode":"30565",
    "sg:province":"Murcia",
    "wof:name":"Vicente Gelabert Antonio",
    "wof:placetype":"venue"
},
  "geometry": {"coordinates":[-1.2405740023,38.0286750793],"type":"Point"}
}