{
  "type": "Feature",
  "properties": {
    "iso:country":"ES",
    "sg:address":"Marques De Reinosa, 12",
    "sg:city":"Autol",
    "sg:orig_category":"Artes Gr\u00c1ficas, Artes Pl\u00c1sticas (curso)",
    "sg:phone":"+34 941 39 07 45",
    "sg:postcode":"26560",
    "sg:province":"La Rioja",
    "wof:name":"Disatex S.l.",
    "wof:placetype":"venue"
},
  "geometry": {"coordinates":[-2.004224062,42.2131233215],"type":"Point"}
}