{
  "type": "Feature",
  "properties": {
    "iso:country":"ES",
    "sg:address":"Plaz Principe De Asturias, 12",
    "sg:city":"Mislata",
    "sg:orig_category":"Asesor\u00cda Fiscal Y Jur\u00cddica",
    "sg:phone":"+34 963 83 50 70",
    "sg:postcode":"46920",
    "sg:province":"Valencia",
    "wof:name":"Jaro Hinarejos Emilia",
    "wof:placetype":"venue"
},
  "geometry": {"coordinates":[-0.4180189967,39.478099823],"type":"Point"}
}