{
  "type": "Feature",
  "properties": {
    "addr:full":"Carrer de Doctor Barri, 10 S. Celoni Barcelona 08470",
    "addr:housenumber":"10",
    "addr:postcode":"08470",
    "addr:street":"Carrer De Doctor Barri",
    "iso:country":"ES",
    "sg:address":"Carrer de Doctor Barri, 10",
    "sg:city":"S. Celoni",
    "sg:orig_category":"Centros M\u00c9dicos Y Sociales, Dispensarios",
    "sg:phone":"+34 938 67 29 42",
    "sg:postcode":"08470",
    "sg:province":"Barcelona",
    "wof:name":"Vicu\u00f1a Peri Ricardo",
    "wof:placetype":"venue"
},
  "geometry": {"coordinates":[2.4871780872,41.6843986511],"type":"Point"}
}