{
  "type": "Feature",
  "properties": {
    "iso:country":"ES",
    "sg:address":"Avda Peris Y Valero, 62",
    "sg:city":"Valencia",
    "sg:orig_category":"Reposter\u00cdas",
    "sg:phone":"+34 963 74 14 40",
    "sg:postcode":"46006",
    "sg:province":"Valencia",
    "wof:name":"Las Eras De Chiva S.l.",
    "wof:placetype":"venue"
},
  "geometry": {"coordinates":[-0.3723120093,39.4582214355],"type":"Point"}
}