{
  "type": "Feature",
  "properties": {
    "iso:country":"ES",
    "sg:address":"Calle de Capitan Garcia Gea, 13",
    "sg:city":"Torrevieja",
    "sg:orig_category":"Asesor\u00cda Sobre Comunicaci\u00d3n De Empresas",
    "sg:phone":"+34 966 70 77 35",
    "sg:postcode":"03180",
    "sg:province":"Alicante",
    "sg:website":"www.clubbravopeam.com",
    "wof:name":"Casablanca Properties Spain S.l.",
    "wof:placetype":"venue"
},
  "geometry": {"coordinates":[-0.66715312,37.9799537659],"type":"Point"}
}