{
  "type": "Feature",
  "properties": {
    "iso:country":"ES",
    "sg:address":"Avda Gaviotas, 227",
    "sg:city":"Perellonet",
    "sg:orig_category":"Caf\u00c9s, Bares, Cervecer\u00cdas",
    "sg:phone":"+34 961 77 80 81",
    "sg:postcode":"46012",
    "sg:province":"Valencia",
    "wof:name":"Urbanizacion Tres Carabelas",
    "wof:placetype":"venue"
},
  "geometry": {"coordinates":[-0.283318013,39.2877845764],"type":"Point"}
}