{
  "type": "Feature",
  "properties": {
    "iso:country":"ES",
    "sg:address":"Muel Primo De Rivera, S/n",
    "sg:city":"Palmas De Gran Canaria",
    "sg:orig_category":"Navegaci\u00d3n (equipos Fluviales)",
    "sg:phone":"+34 928 26 95 38",
    "sg:postcode":"35008",
    "sg:province":"Las Palmas",
    "wof:name":"Algarpesca S.a.",
    "wof:placetype":"venue"
},
  "geometry": {"coordinates":[-15.4126653671,28.1696929932],"type":"Point"}
}