{
  "type": "Feature",
  "properties": {
    "addr:full":"Calle de Muro, 33 Tudela Navarra 31500",
    "addr:housenumber":"33",
    "addr:postcode":"31500",
    "addr:street":"Calle De Muro",
    "iso:country":"ES",
    "sg:address":"Calle de Muro, 33",
    "sg:city":"Tudela",
    "sg:orig_category":"Institutos De Belleza",
    "sg:phone":"+34 948 41 06 40",
    "sg:postcode":"31500",
    "sg:province":"Navarra",
    "wof:name":"Cuidados Esteticos Malu S.l.",
    "wof:placetype":"venue"
},
  "geometry": {"coordinates":[-1.6051880121,42.0620574951],"type":"Point"}
}