{
  "type": "Feature",
  "properties": {
    "iso:country":"ES",
    "sg:address":"Carr Canonge Baranera, 44",
    "sg:city":"Badalona",
    "sg:orig_category":"Perfumer\u00cda (al Por Menor)",
    "sg:phone":"+34 933 84 62 35",
    "sg:postcode":"08911",
    "sg:province":"Barcelona",
    "wof:name":"Reguill Maresma Josefa",
    "wof:placetype":"venue"
},
  "geometry": {"coordinates":[2.2506608963,41.4499588013],"type":"Point"}
}