{
  "type": "Feature",
  "properties": {
    "iso:country":"ES",
    "sg:address":"Avda Pedro De Mendoza Y Lujan, 12",
    "sg:city":"Guadix",
    "sg:orig_category":"Pescader\u00cdas (al Por Menor)",
    "sg:phone":"+34 958 66 37 05",
    "sg:postcode":"18500",
    "sg:province":"Granada",
    "wof:name":"Puertas Tauste Pedro",
    "wof:placetype":"venue"
},
  "geometry": {"coordinates":[-3.1364529133,37.3039245605],"type":"Point"}
}