{
  "type": "Feature",
  "properties": {
    "addr:full":"Carr Bassa Bona, 16 Alcoletge Lleida 25660",
    "addr:housenumber":"16",
    "addr:postcode":"25660",
    "addr:street":"Carr Bassa Bona",
    "iso:country":"ES",
    "sg:address":"Carr Bassa Bona, 16",
    "sg:city":"Alcoletge",
    "sg:orig_category":"Ense\u00d1anza Variada",
    "sg:phone":"+34 973 19 66 03",
    "sg:postcode":"25660",
    "sg:province":"Lleida",
    "wof:name":"Centro De Estudios Ceac, S.l",
    "wof:placetype":"venue"
},
  "geometry": {"coordinates":[0.694765985,41.6466674805],"type":"Point"}
}