{
  "type": "Feature",
  "properties": {
    "addr:full":"Plaz Cervantes, 9 Palencia Palencia 34005",
    "addr:housenumber":"9",
    "addr:postcode":"34005",
    "addr:street":"Plaz Cervantes",
    "iso:country":"ES",
    "sg:address":"Plaz Cervantes, 9",
    "sg:city":"Palencia",
    "sg:orig_category":"Art\u00cdculos De Decoraci\u00d3n",
    "sg:phone":"+34 979 74 67 55",
    "sg:postcode":"34005",
    "sg:province":"Palencia",
    "wof:name":"Pepe Delgado S.l.",
    "wof:placetype":"venue"
},
  "geometry": {"coordinates":[-4.5378050804,42.0122413635],"type":"Point"}
}