{
  "type": "Feature",
  "properties": {
    "iso:country":"ES",
    "sg:address":"Calle de Prim, General, 16",
    "sg:city":"Melilla",
    "sg:orig_category":"Ense\u00d1anza: Profesiones Art\u00cdsticas",
    "sg:phone":"+34 952 68 29 53",
    "sg:postcode":"52004",
    "sg:province":"Melilla",
    "wof:name":"Soria Perez Miguel",
    "wof:placetype":"venue"
},
  "geometry": {"coordinates":[-2.9415655136,35.293598175],"type":"Point"}
}