{
  "type": "Feature",
  "properties": {
    "iso:country":"ES",
    "sg:address":"Lugar Arsenal Carraca, 45",
    "sg:city":"S. Fernando",
    "sg:orig_category":"Internados & Ense\u00d1anza Privada",
    "sg:phone":"+34 956 59 29 00",
    "sg:postcode":"11100",
    "sg:province":"C\u00e1diz",
    "wof:name":"Compa\u00d1ia De Maria La Bazan",
    "wof:placetype":"venue"
},
  "geometry": {"coordinates":[-6.1967391968,36.4654541016],"type":"Point"}
}