{
  "type": "Feature",
  "properties": {
    "iso:country":"ES",
    "sg:address":"Calle de Gran Via, 45",
    "sg:city":"Salamanca",
    "sg:orig_category":"M\u00c9dicos: Cirug\u00cda General",
    "sg:phone":"+34 923 27 05 86",
    "sg:postcode":"37001",
    "sg:province":"Salamanca",
    "wof:name":"Angoso Catalina Luis Fernando",
    "wof:placetype":"venue"
},
  "geometry": {"coordinates":[-5.6606125832,40.9651298523],"type":"Point"}
}