{
  "type": "Feature",
  "properties": {
    "iso:country":"ES",
    "sg:address":"Ctra Jarandilla, S/n",
    "sg:city":"Navalmoral Mata",
    "sg:orig_category":"Chapister\u00cda",
    "sg:phone":"+34 927 53 40 04",
    "sg:postcode":"10300",
    "sg:province":"C\u00e1ceres",
    "wof:name":"Navalauto Chapa Y Pintura S.l.",
    "wof:placetype":"venue"
},
  "geometry": {"coordinates":[-5.5438289642,39.896900177],"type":"Point"}
}