{
  "type": "Feature",
  "properties": {
    "iso:country":"ES",
    "sg:address":"Calle de Triana, 17",
    "sg:city":"Palmas De Gran Canaria",
    "sg:orig_category":"Fabricaci\u00d3n De Telas Y Sedas",
    "sg:phone":"+34 928 36 93 09",
    "sg:postcode":"35002",
    "sg:province":"Las Palmas",
    "wof:name":"Haddad Cabral Jorge",
    "wof:placetype":"venue"
},
  "geometry": {"coordinates":[-15.4152936935,28.1035404205],"type":"Point"}
}