{
  "type": "Feature",
  "properties": {
    "addr:full":"Calle de Jose Luis De Arrese, 34 Madrid Madrid 28017",
    "addr:housenumber":"34",
    "addr:postcode":"madrid;28017",
    "addr:street":"Calle De Jose Luis De Arrese",
    "iso:country":"ES",
    "sg:address":"Calle de Jose Luis De Arrese, 34",
    "sg:city":"Madrid",
    "sg:orig_category":"Mudanzas",
    "sg:phone":"+34 914 05 31 24",
    "sg:postcode":"28017",
    "sg:province":"Madrid",
    "wof:name":"Albanecich  Ivor",
    "wof:placetype":"venue"
},
  "geometry": {"coordinates":[-3.6518728733,40.4216499329],"type":"Point"}
}