{
  "type": "Feature",
  "properties": {
    "iso:country":"ES",
    "sg:address":"Mestral (urb. Pino Alto), 8",
    "sg:city":"Miami Platja",
    "sg:orig_category":"Agencias Y Asesores De Publicidad",
    "sg:phone":"+34 977 81 00 07",
    "sg:postcode":"43892",
    "sg:province":"Tarragona",
    "sg:website":"www.mediatica.net",
    "wof:name":"Aragones Sabater Marcel",
    "wof:placetype":"venue"
},
  "geometry": {"coordinates":[0.9366844893,41.0129203796],"type":"Point"}
}