{
  "type": "Feature",
  "properties": {
    "addr:full":"Iparragirre Avda Z Industrial, 98 Elexalde Vizcaya 48940",
    "addr:housenumber":"98",
    "addr:postcode":"48940",
    "addr:street":"Avda Z Industrial",
    "iso:country":"ES",
    "sg:address":"Iparragirre Avda Z Industrial, 98",
    "sg:city":"Elexalde",
    "sg:orig_category":"Negocio De Materiales De Construcci\u00d3n",
    "sg:phone":"+34 944 80 20 34",
    "sg:postcode":"48940",
    "sg:province":"Vizcaya",
    "wof:name":"Astola S.a.",
    "wof:placetype":"venue"
},
  "geometry": {"coordinates":[-2.8873260021,43.2208213806],"type":"Point"}
}