{
  "type": "Feature",
  "properties": {
    "addr:full":"Pol Eurocentro, Km. 0002,0 Eivissa Islas Baleares 07800",
    "addr:postcode":"07800",
    "addr:street":"Eurocentro Km. 0002,0",
    "iso:country":"ES",
    "sg:address":"Pol Eurocentro, Km. 0002,0",
    "sg:city":"Eivissa",
    "sg:orig_category":"Mec\u00c1nico Del Autom\u00d3vil",
    "sg:phone":"+34 971 31 36 69",
    "sg:postcode":"07800",
    "sg:province":"Islas Baleares",
    "wof:name":"Taller Ebusitano S.l.",
    "wof:placetype":"venue"
},
  "geometry": {"coordinates":[1.4188899994,38.9061164856],"type":"Point"}
}