{
  "type": "Feature",
  "properties": {
    "iso:country":"ES",
    "sg:address":"Carrer de Mare De Deu De Lorda, 3",
    "sg:city":"Vic",
    "sg:orig_category":"Molduras, Junquillos, Listones Y Molduras Perforadas",
    "sg:phone":"+34 938 85 31 66",
    "sg:postcode":"08500",
    "sg:province":"Barcelona",
    "wof:name":"Garzon Montoro Miguel",
    "wof:placetype":"venue"
},
  "geometry": {"coordinates":[2.2547109127,41.920249939],"type":"Point"}
}