{
  "type": "Feature",
  "properties": {
    "iso:country":"ES",
    "sg:address":"Calle de Nueva, 20",
    "sg:city":"Cartaya",
    "sg:orig_category":"Peluquer\u00cdas, Peluquer\u00cda Mixta",
    "sg:phone":"+34 959 39 12 67",
    "sg:postcode":"21450",
    "sg:province":"Huelva",
    "wof:name":"Perez Florencio Rosario",
    "wof:placetype":"venue"
},
  "geometry": {"coordinates":[-7.1536798477,37.2824859619],"type":"Point"}
}