{
  "type": "Feature",
  "properties": {
    "iso:country":"ES",
    "sg:address":"Gadoy, S/n",
    "sg:city":"Castro",
    "sg:orig_category":"Muebles Y Accesorios Para Cocinas Y Cuartos De Ba\u00d1o (al Por Menor)",
    "sg:phone":"+34 981 38 81 20",
    "sg:postcode":"15578",
    "sg:province":"A Coru\u00f1a",
    "wof:name":"Varela Vilaboi Jose Antonio",
    "wof:placetype":"venue"
},
  "geometry": {"coordinates":[-8.1806354523,43.5493278503],"type":"Point"}
}