{
  "type": "Feature",
  "properties": {
    "iso:country":"ES",
    "sg:address":"Calle de Hernan Cortes, 1",
    "sg:city":"Villafranca De Los Barros",
    "sg:orig_category":"Molduras, Junquillos, Listones Y Molduras Perforadas",
    "sg:phone":"+34 924 52 40 23",
    "sg:postcode":"06220",
    "sg:province":"Badajoz",
    "wof:name":"Sociedad La Pe\u00f1a",
    "wof:placetype":"venue"
},
  "geometry": {"coordinates":[-6.3413090706,38.5619735718],"type":"Point"}
}