{
  "type": "Feature",
  "properties": {
    "iso:country":"ES",
    "sg:address":"Avgd Madrid, 17",
    "sg:city":"Lleida",
    "sg:orig_category":"Asesor\u00cda Fiscal Y Jur\u00cddica",
    "sg:phone":"+34 973 26 97 87",
    "sg:postcode":"25002",
    "sg:province":"Lleida",
    "wof:name":"Centre Fiscal I De Serveis S.l.",
    "wof:placetype":"venue"
},
  "geometry": {"coordinates":[0.6192089915,41.6090354919],"type":"Point"}
}