{
  "type": "Feature",
  "properties": {
    "iso:country":"ES",
    "sg:address":"Ctra. General, S/n",
    "sg:city":"Buzanada",
    "sg:orig_category":"Pintura Y Barniz (al Por Menor)",
    "sg:phone":"+34 922 76 72 21",
    "sg:postcode":"38626",
    "sg:province":"Santa Cruz De Tenerife",
    "wof:name":"Arbolcolor Daute S.l.",
    "wof:placetype":"venue"
},
  "geometry": {"coordinates":[-16.6261119843,28.0959339142],"type":"Point"}
}