{
  "type": "Feature",
  "properties": {
    "iso:country":"ES",
    "sg:address":"Calle de Antonio Maura, 3",
    "sg:city":"Campo Criptana",
    "sg:orig_category":"Forjas Y Altos Hornos",
    "sg:phone":"+34 926 56 07 69",
    "sg:postcode":"13610",
    "sg:province":"Ciudad Real",
    "wof:name":"Sanchez Qui\u00f1ones Jeronimo Antonio",
    "wof:placetype":"venue"
},
  "geometry": {"coordinates":[-3.1223676205,39.3981437683],"type":"Point"}
}