{
  "type": "Feature",
  "properties": {
    "iso:country":"ES",
    "sg:address":"Calle de Gabriel Miro, 3",
    "sg:city":"Sax",
    "sg:orig_category":"Confecci\u00d3n De Trajes Para Se\u00d1oras",
    "sg:phone":"+34 966 96 70 80",
    "sg:postcode":"03630",
    "sg:province":"Alicante",
    "wof:name":"Ortin Gil Teresa",
    "wof:placetype":"venue"
},
  "geometry": {"coordinates":[-0.8208199739,38.5344619751],"type":"Point"}
}