{
  "type": "Feature",
  "properties": {
    "iso:country":"ES",
    "sg:address":"Carrer de Carrio, 19",
    "sg:city":"Manresa",
    "sg:orig_category":"Electrodom\u00c9sticos (al Por Menor)",
    "sg:phone":"+34 938 72 62 74",
    "sg:postcode":"08242",
    "sg:province":"Barcelona",
    "wof:name":"Comercial Juanola S. A.",
    "wof:placetype":"venue"
},
  "geometry": {"coordinates":[1.8225159645,41.7282829285],"type":"Point"}
}