{
  "type": "Feature",
  "properties": {
    "addr:full":"Avda Andalucia (de), 70 Montilla C\u00f3rdoba 14550",
    "addr:housenumber":"70",
    "addr:postcode":"14550",
    "addr:street":"Avda Andalucia De;Co\u0301Rdoba",
    "iso:country":"ES",
    "sg:address":"Avda Andalucia (de), 70",
    "sg:city":"Montilla",
    "sg:orig_category":"Comercio, Reparaci\u00d3n De Bicicletas, De Motocicletas, De Accesorios",
    "sg:phone":"+34 957 65 52 22",
    "sg:postcode":"14550",
    "sg:province":"C\u00f3rdoba",
    "wof:name":"Espejo Ruiz Antonio",
    "wof:placetype":"venue"
},
  "geometry": {"coordinates":[-4.6477999687,37.5805435181],"type":"Point"}
}