{
  "type": "Feature",
  "properties": {
    "iso:country":"ES",
    "sg:address":"Calle de Cristo, 4",
    "sg:city":"San Ildefonso O La Granja",
    "sg:orig_category":"Molduras, Junquillos, Listones Y Molduras Perforadas",
    "sg:phone":"+34 921 47 00 97",
    "sg:postcode":"40100",
    "sg:province":"Segovia",
    "wof:name":"Martin Vazquez Mariano",
    "wof:placetype":"venue"
},
  "geometry": {"coordinates":[-4.0062184334,40.900604248],"type":"Point"}
}