{
  "type": "Feature",
  "properties": {
    "iso:country":"ES",
    "sg:address":"Carr Hostal De La Bordeta, 30",
    "sg:city":"Lleida",
    "sg:orig_category":"Ebanister\u00cda",
    "sg:phone":"+34 973 20 10 94",
    "sg:postcode":"25001",
    "sg:province":"Lleida",
    "wof:name":"Alvarez Manzano Serafin",
    "wof:placetype":"venue"
},
  "geometry": {"coordinates":[0.6434130073,41.6036148071],"type":"Point"}
}