{
  "type": "Feature",
  "properties": {
    "addr:full":"Calle de Ruiz De Alda, 1 Valdemoro Madrid 28340",
    "addr:housenumber":"1",
    "addr:postcode":"28340",
    "addr:street":"Calle De Ruiz De Alda",
    "iso:country":"ES",
    "sg:address":"Calle de Ruiz De Alda, 1",
    "sg:city":"Valdemoro",
    "sg:orig_category":"Droguer\u00cdas (al Por Menor)",
    "sg:phone":"+34 918 95 25 53",
    "sg:postcode":"28340",
    "sg:province":"Madrid",
    "wof:name":"Gali Bermejo Luis",
    "wof:placetype":"venue"
},
  "geometry": {"coordinates":[-3.6796140671,40.1910667419],"type":"Point"}
}