{
  "type": "Feature",
  "properties": {
    "addr:full":"Calle de Luzarra, 20 Bilbao Vizcaya 48014",
    "addr:housenumber":"20",
    "addr:postcode":"48014",
    "addr:street":"Calle De Luzarra",
    "iso:country":"ES",
    "sg:address":"Calle de Luzarra, 20",
    "sg:city":"Bilbao",
    "sg:orig_category":"Automatizaci\u00d3n De Procesos Industriales Y De Edificaci\u00d3n (estudios, Instalaci\u00d3n)",
    "sg:phone":"+34 944 47 23 16",
    "sg:postcode":"48014",
    "sg:province":"Vizcaya",
    "wof:name":"Iberica De Automatismos S.a.",
    "wof:placetype":"venue"
},
  "geometry": {"coordinates":[-2.9474270344,43.272480011],"type":"Point"}
}