{
  "type": "Feature",
  "properties": {
    "addr:full":"Rbla Badal, 190 Barcelona Barcelona 08028",
    "addr:housenumber":"190",
    "addr:postcode":"08028",
    "addr:street":"Rbla Badal",
    "iso:country":"ES",
    "sg:address":"Rbla Badal, 190",
    "sg:city":"Barcelona",
    "sg:orig_category":"Agencias De Viajes",
    "sg:phone":"+34 934 32 37 89",
    "sg:postcode":"08028",
    "sg:province":"Barcelona",
    "wof:name":"Univertours S.a.",
    "wof:placetype":"venue"
},
  "geometry": {"coordinates":[2.131002903,41.3748435974],"type":"Point"}
}