{
  "type": "Feature",
  "properties": {
    "addr:full":"Pl Coc (del), 1 S. Carles Rapita Tarragona 43540",
    "addr:postcode":"43540",
    "addr:street":"Pl;Del 1 S. Carles Rapita",
    "iso:country":"ES",
    "sg:address":"Pl Coc (del), 1",
    "sg:city":"S. Carles Rapita",
    "sg:orig_category":"Heladeros",
    "sg:phone":"+34 977 74 52 17",
    "sg:postcode":"43540",
    "sg:province":"Tarragona",
    "wof:name":"Salmenart S.l.",
    "wof:placetype":"venue"
},
  "geometry": {"coordinates":[0.5930349827,40.6200485229],"type":"Point"}
}