{
  "type": "Feature",
  "properties": {
    "iso:country":"ES",
    "sg:address":"Calle de Ariza, 132",
    "sg:city":"Madrid",
    "sg:orig_category":"Panader\u00cdas, Panader\u00cdas",
    "sg:phone":"+34 914 66 29 31",
    "sg:postcode":"28047",
    "sg:province":"Madrid",
    "wof:name":"Del Toro Garcia Antonio Miguel",
    "wof:placetype":"venue"
},
  "geometry": {"coordinates":[-3.7389559746,40.3967857361],"type":"Point"}
}