{
  "type": "Feature",
  "properties": {
    "iso:country":"ES",
    "sg:address":"Gongora Plaza, 1",
    "sg:city":"Salobre\u00f1a",
    "sg:orig_category":"Pintura Y Barniz (al Por Menor)",
    "sg:phone":"+34 958 61 21 44",
    "sg:postcode":"18680",
    "sg:province":"Granada",
    "wof:name":"Pinturas Menape S.l.",
    "wof:placetype":"venue"
},
  "geometry": {"coordinates":[-3.5845439434,36.7455253601],"type":"Point"}
}