{
  "type": "Feature",
  "properties": {
    "iso:country":"ES",
    "sg:address":"Calle de Mariana Pineda, 18",
    "sg:city":"Zaragoza",
    "sg:orig_category":"Peluquer\u00cdas, Peluquer\u00cda Mixta",
    "sg:phone":"+34 976 73 11 54",
    "sg:postcode":"50015",
    "sg:province":"Zaragoza",
    "wof:name":"Alonso De Leon Raquel",
    "wof:placetype":"venue"
},
  "geometry": {"coordinates":[-0.8884437084,41.6654396057],"type":"Point"}
}