{
  "type": "Feature",
  "properties": {
    "addr:full":"Calle de Leonardo Da Vinci, 9 Vitoria-gasteiz \u00c1lava 01510",
    "addr:housenumber":"9",
    "addr:postcode":"01510",
    "addr:street":"Calle De Leonardo Da Vinci",
    "iso:country":"ES",
    "sg:address":"Calle de Leonardo Da Vinci, 9",
    "sg:city":"Vitoria-gasteiz",
    "sg:orig_category":"Fotocopias, Reprograf\u00cda",
    "sg:phone":"+34 945 29 69 91",
    "sg:postcode":"01510",
    "sg:province":"\u00c1lava",
    "wof:name":"Fotocopias Zalu",
    "wof:placetype":"venue"
},
  "geometry": {"coordinates":[-2.667607069,42.9104003906],"type":"Point"}
}