{
  "type": "Feature",
  "properties": {
    "addr:full":"Carr Rector Joanillo, Des, 11 Sant Elm Islas Baleares 07159",
    "addr:postcode":"07159",
    "addr:street":"Carr Rector Joanillo;Sant;Islas",
    "iso:country":"ES",
    "sg:address":"Carr Rector Joanillo, Des, 11",
    "sg:city":"Sant Elm",
    "sg:orig_category":"Inversiones",
    "sg:phone":"+34 971 23 93 14",
    "sg:postcode":"07159",
    "sg:province":"Islas Baleares",
    "wof:name":"Alemany Hormaeche Juan Ramon",
    "wof:placetype":"venue"
},
  "geometry": {"coordinates":[2.3502361774,39.5820922852],"type":"Point"}
}