{
  "type": "Feature",
  "properties": {
    "iso:country":"ES",
    "sg:address":"Ctra. Villacarrillo, 39",
    "sg:city":"Navas San Juan",
    "sg:orig_category":"Bebidas",
    "sg:phone":"+34 953 68 91 32",
    "sg:postcode":"23240",
    "sg:province":"Ja\u00e9n",
    "wof:name":"Morales Ruiz Juan Francisco",
    "wof:placetype":"venue"
},
  "geometry": {"coordinates":[-3.3123788834,38.1828651428],"type":"Point"}
}