{
  "type": "Feature",
  "properties": {
    "addr:full":"Calle de Covadonga, 10 Oviedo Asturias 33002",
    "addr:housenumber":"10",
    "addr:postcode":"33002",
    "addr:street":"Calle De Covadonga",
    "iso:country":"ES",
    "sg:address":"Calle de Covadonga, 10",
    "sg:city":"Oviedo",
    "sg:orig_category":"M\u00c9dicos: Estomatolog\u00cda",
    "sg:phone":"+34 985 22 22 14",
    "sg:postcode":"33002",
    "sg:province":"Asturias",
    "wof:name":"Alonso Del Vado Manuel",
    "wof:placetype":"venue"
},
  "geometry": {"coordinates":[-5.8479838371,43.3641586304],"type":"Point"}
}