{
  "type": "Feature",
  "properties": {
    "iso:country":"ES",
    "sg:address":"Avda De Los Alamos, 50",
    "sg:city":"Poligono Ind. La Mora",
    "sg:orig_category":"Mataderos De Poller\u00cda",
    "sg:phone":"+34 983 40 30 29",
    "sg:postcode":"47193",
    "sg:province":"Valladolid",
    "wof:name":"Matadero De Conejos Hermi S.l.",
    "wof:placetype":"venue"
},
  "geometry": {"coordinates":[-4.6859240532,41.6106681824],"type":"Point"}
}