{
  "type": "Feature",
  "properties": {
    "iso:country":"ES",
    "sg:address":"Real, 3",
    "sg:city":"S. Martin Porres",
    "sg:orig_category":"Ebanister\u00cda",
    "sg:phone":"+34 947 13 82 21",
    "sg:postcode":"09574",
    "sg:province":"Burgos",
    "wof:name":"Miras Lopez Bernabe",
    "wof:placetype":"venue"
},
  "geometry": {"coordinates":[-3.7391240597,43.006893158],"type":"Point"}
}