{
  "type": "Feature",
  "properties": {
    "addr:full":"Ctra Palacios, S/n Utrera Sevilla 41710",
    "addr:housenumber":"s",
    "addr:postcode":"41710",
    "addr:street":"Ctra Palacios;/ N",
    "iso:country":"ES",
    "sg:address":"Ctra Palacios, S/n",
    "sg:city":"Utrera",
    "sg:orig_category":"Cr\u00cda De Animales",
    "sg:phone":"+34 954 86 02 90",
    "sg:postcode":"41710",
    "sg:province":"Sevilla",
    "wof:name":"Pariente S. A.",
    "wof:placetype":"venue"
},
  "geometry": {"coordinates":[-5.786962986,37.1801872253],"type":"Point"}
}