{
  "type": "Feature",
  "properties": {
    "iso:country":"ES",
    "sg:address":"Carr Salada, 24",
    "sg:city":"Torres Segre",
    "sg:orig_category":"Cooperativas Agr\u00cdcolas",
    "sg:phone":"+34 973 79 60 40",
    "sg:postcode":"25170",
    "sg:province":"Lleida",
    "wof:name":"Cooperativa De Consum",
    "wof:placetype":"venue"
},
  "geometry": {"coordinates":[0.5142099857,41.5340461731],"type":"Point"}
}