{
  "type": "Feature",
  "properties": {
    "addr:full":"Calle de Jose Antonio, S/n Valdeltormo Teruel 44620",
    "addr:housenumber":"s / n",
    "addr:postcode":"44620",
    "addr:street":"Calle De Jose Antonio",
    "iso:country":"ES",
    "sg:address":"Calle de Jose Antonio, S/n",
    "sg:city":"Valdeltormo",
    "sg:orig_category":"Cajas De Ahorro",
    "sg:phone":"+34 978 85 82 52",
    "sg:postcode":"44620",
    "sg:province":"Teruel",
    "sg:website":"www.ibercaja.es",
    "wof:name":"Caja De Ahorros Y Monte De Piedad De Zaragoza Aragon Y Rioja",
    "wof:placetype":"venue"
},
  "geometry": {"coordinates":[0.0830530003,40.9864273071],"type":"Point"}
}