{
  "type": "Feature",
  "properties": {
    "addr:full":"Calle de Santa Cruz De Marcenado, 11 Madrid Madrid 28015",
    "addr:housenumber":"11",
    "addr:postcode":"madrid;28015",
    "addr:street":"Calle De Santa Cruz De Marcenado",
    "iso:country":"ES",
    "sg:address":"Calle de Santa Cruz De Marcenado, 11",
    "sg:city":"Madrid",
    "sg:orig_category":"Ingenier\u00cda, Centros De Estudios (diversos)",
    "sg:phone":"+34 915 41 87 85",
    "sg:postcode":"28015",
    "sg:province":"Madrid",
    "wof:name":"Espinosa Garcia Ramon",
    "wof:placetype":"venue"
},
  "geometry": {"coordinates":[-3.7071230412,40.4287757874],"type":"Point"}
}