{
  "type": "Feature",
  "properties": {
    "addr:full":"Calle de Real, 92 Brenes Sevilla 41310",
    "addr:housenumber":"92",
    "addr:postcode":"41310",
    "addr:street":"Calle De Real",
    "iso:country":"ES",
    "sg:address":"Calle de Real, 92",
    "sg:city":"Brenes",
    "sg:orig_category":"Reposter\u00cdas",
    "sg:phone":"+34 954 79 60 07",
    "sg:postcode":"41310",
    "sg:province":"Sevilla",
    "wof:name":"Perez Perez Antonio",
    "wof:placetype":"venue"
},
  "geometry": {"coordinates":[-5.8737897873,37.549911499],"type":"Point"}
}