{
  "type": "Feature",
  "properties": {
    "addr:full":"Calle de Cinco De Julio, 14 Carolina Ja\u00e9n 23200",
    "addr:housenumber":"14",
    "addr:postcode":"23200",
    "addr:street":"Calle De Cinco De Julio;Jae\u0301N",
    "iso:country":"ES",
    "sg:address":"Calle de Cinco De Julio, 14",
    "sg:city":"Carolina",
    "sg:orig_category":"Juegos Y Juguetes (al Por Menor)",
    "sg:phone":"+34 953 68 18 91",
    "sg:postcode":"23200",
    "sg:province":"Ja\u00e9n",
    "wof:name":"Pedrosa Artacho Juan Manuel",
    "wof:placetype":"venue"
},
  "geometry": {"coordinates":[-3.7895176411,37.7657394409],"type":"Point"}
}