{
  "type": "Feature",
  "properties": {
    "iso:country":"ES",
    "sg:address":"Barr Cardile, 3",
    "sg:city":"Hornedo",
    "sg:orig_category":"Arboricultura Y Producci\u00d3n De Frutas",
    "sg:phone":"+34 942 52 50 07",
    "sg:postcode":"39716",
    "sg:province":"Cantabria",
    "wof:name":"Candas Torre Gregorio",
    "wof:placetype":"venue"
},
  "geometry": {"coordinates":[-3.6326639652,43.3630180359],"type":"Point"}
}