{
  "type": "Feature",
  "properties": {
    "addr:full":"Rond Paisos Catalans (dels), 43 Mataro Barcelona 08304",
    "addr:housenumber":"43",
    "addr:postcode":"08304",
    "addr:street":"Catalans Dels",
    "iso:country":"ES",
    "sg:address":"Rond Paisos Catalans (dels), 43",
    "sg:city":"Mataro",
    "sg:orig_category":"Muebles Y Decoraci\u00d3n De Jardines (fabricaci\u00d3n, Venta)",
    "sg:phone":"+34 937 99 39 22",
    "sg:postcode":"08304",
    "sg:province":"Barcelona",
    "sg:website":"www.greendesign.es",
    "wof:name":"Green Design S.l.",
    "wof:placetype":"venue"
},
  "geometry": {"coordinates":[2.445581913,41.5602912903],"type":"Point"}
}