{
  "type": "Feature",
  "properties": {
    "addr:full":"Ctra Sagunto-burgos, Km. 0029,5 Segorbe Castell\u00f3n 12400",
    "addr:postcode":"12400",
    "addr:street":"Ctra Sagunto-Burgos Km. 0029,5;Castello\u0301N",
    "iso:country":"ES",
    "sg:address":"Ctra Sagunto-burgos, Km. 0029,5",
    "sg:city":"Segorbe",
    "sg:orig_category":"Confecci\u00d3n (fabricaci\u00d3n, Al Por Mayor)",
    "sg:phone":"+34 964 13 20 42",
    "sg:postcode":"12400",
    "sg:province":"Castell\u00f3n",
    "wof:name":"Saez Merino Textiles S.a.",
    "wof:placetype":"venue"
},
  "geometry": {"coordinates":[-0.4885739982,39.8518714905],"type":"Point"}
}