{
  "type": "Feature",
  "properties": {
    "iso:country":"ES",
    "sg:address":"Calle de Guzman El Bueno, 11",
    "sg:city":"Madrid",
    "sg:orig_category":"Arquitectos",
    "sg:phone":"+34 915 43 37 04",
    "sg:postcode":"28015",
    "sg:province":"Madrid",
    "wof:name":"Miranda Regojo Antonio",
    "wof:placetype":"venue"
},
  "geometry": {"coordinates":[-3.7135989666,40.4313583374],"type":"Point"}
}