{
  "type": "Feature",
  "properties": {
    "addr:full":"Calle de Matiko, 4 Bilbao Vizcaya 48007",
    "addr:housenumber":"4",
    "addr:postcode":"48007",
    "addr:street":"Calle De Matiko",
    "iso:country":"ES",
    "sg:address":"Calle de Matiko, 4",
    "sg:city":"Bilbao",
    "sg:orig_category":"Molduras, Junquillos, Listones Y Molduras Perforadas",
    "sg:phone":"+34 944 45 10 64",
    "sg:postcode":"48007",
    "sg:province":"Vizcaya",
    "wof:name":"Sociedad Regional De Informatica S.a.",
    "wof:placetype":"venue"
},
  "geometry": {"coordinates":[-2.9250864983,43.270450592],"type":"Point"}
}