{
  "type": "Feature",
  "properties": {
    "addr:full":"Calle de Virgen Del Puig, 20 Alacant Alicante 03009",
    "addr:housenumber":"20",
    "addr:postcode":"03009",
    "addr:street":"Calle De Virgen Del Puig",
    "iso:country":"ES",
    "sg:address":"Calle de Virgen Del Puig, 20",
    "sg:city":"Alacant",
    "sg:classifiers":[
        {
            "category":"Personal",
            "subcategory":"Barber",
            "type":"Services"
        }
    ],
    "sg:phone":"+34 965 17 35 42",
    "sg:postcode":"03009",
    "sg:province":"Alicante",
    "sg:tags":[
        "caballeros",
        "de",
        "peluqueros"
    ],
    "wof:name":"Mario Alex Y Jose S.c",
    "wof:placetype":"venue"
},
  "geometry": {"coordinates":[-0.4997520149,38.3706436157],"type":"Point"}
}