{
  "type": "Feature",
  "properties": {
    "iso:country":"ES",
    "sg:address":"Avda Generalisimo, 1",
    "sg:city":"Colunga",
    "sg:orig_category":"Frutas, Legumbres Frescas Y Tempranas (al Por Menor)",
    "sg:phone":"+34 985 85 62 84",
    "sg:postcode":"33320",
    "sg:province":"Asturias",
    "wof:name":"Fernandez Guzman Alberto",
    "wof:placetype":"venue"
},
  "geometry": {"coordinates":[-5.273832798,43.4849319458],"type":"Point"}
}