{
  "type": "Feature",
  "properties": {
    "iso:country":"ES",
    "sg:address":"Calle de Denia, 24",
    "sg:city":"Valencia",
    "sg:orig_category":"Asociaciones Y Clubs Deportivos",
    "sg:phone":"+34 963 41 49 48",
    "sg:postcode":"46006",
    "sg:province":"Valencia",
    "wof:name":"Garcia Navarrete Antonio",
    "wof:placetype":"venue"
},
  "geometry": {"coordinates":[-0.3743844926,39.4633102417],"type":"Point"}
}