{
  "type": "Feature",
  "properties": {
    "iso:country":"ES",
    "sg:address":"Rua Irmans Noia, S/n",
    "sg:city":"Guarda",
    "sg:orig_category":"Caf\u00c9s, Bares, Cervecer\u00cdas",
    "sg:phone":"+34 986 61 45 50",
    "sg:postcode":"36780",
    "sg:province":"Pontevedra",
    "wof:name":"Hosteleria Fala S.l.",
    "wof:placetype":"venue"
},
  "geometry": {"coordinates":[-8.8771743774,41.906414032],"type":"Point"}
}