{
  "type": "Feature",
  "properties": {
    "iso:country":"ES",
    "sg:address":"Calle de Alboraya, 57",
    "sg:city":"Valencia",
    "sg:orig_category":"Decoradores",
    "sg:phone":"+34 963 69 14 04",
    "sg:postcode":"46010",
    "sg:province":"Valencia",
    "wof:name":"Practic 3 S.l.",
    "wof:placetype":"venue"
},
  "geometry": {"coordinates":[-0.3687225878,39.4856300354],"type":"Point"}
}