{
  "type": "Feature",
  "properties": {
    "iso:country":"ES",
    "sg:address":"Avda Irun, S/n",
    "sg:city":"Arre",
    "sg:orig_category":"Promotores Constructores",
    "sg:phone":"+34 948 33 02 59",
    "sg:postcode":"31194",
    "sg:province":"Navarra",
    "wof:name":"Construcciones Rodriguez Viscarret S.l.",
    "wof:placetype":"venue"
},
  "geometry": {"coordinates":[-1.6132349968,42.8443031311],"type":"Point"}
}