{
  "type": "Feature",
  "properties": {
    "addr:full":"Avda America, 53 Ingenio Las Palmas 35250",
    "addr:housenumber":"53",
    "addr:postcode":"35250",
    "addr:street":"Avda America",
    "iso:country":"ES",
    "sg:address":"Avda America, 53",
    "sg:city":"Ingenio",
    "sg:orig_category":"Muebles, Minoristas",
    "sg:phone":"+34 928 78 07 89",
    "sg:postcode":"35250",
    "sg:province":"Las Palmas",
    "wof:name":"Espino Hernandez Jesus",
    "wof:placetype":"venue"
},
  "geometry": {"coordinates":[-15.4409389496,27.9181518555],"type":"Point"}
}