{
  "type": "Feature",
  "properties": {
    "addr:full":"Avda Juan Sebastian Elcano, 181 Malaga M\u00e1laga 29017",
    "addr:housenumber":"181",
    "addr:postcode":"29017",
    "addr:street":"Avda Juan Sebastian Elcano;Ma\u0301Laga",
    "iso:country":"ES",
    "sg:address":"Avda Juan Sebastian Elcano, 181",
    "sg:city":"Malaga",
    "sg:classifiers":[
        {
            "category":"Autos & Motor Vehicles",
            "subcategory":"Automobile Sales",
            "type":"Retail Goods"
        }
    ],
    "sg:phone":"+34 952 29 67 92",
    "sg:postcode":"29017",
    "sg:province":"M\u00e1laga",
    "wof:name":"Gavio Follana Manuel",
    "wof:placetype":"venue"
},
  "geometry": {"coordinates":[-4.3626790047,36.7213249207],"type":"Point"}
}