{
  "type": "Feature",
  "properties": {
    "addr:full":"Avda Jaca, 14 Madrid Madrid 28022",
    "addr:housenumber":"14",
    "addr:postcode":"madrid;28022",
    "addr:street":"Avda Jaca",
    "iso:country":"ES",
    "sg:address":"Avda Jaca, 14",
    "sg:city":"Madrid",
    "sg:orig_category":"Asilos De Ancianos. Centros Privados",
    "sg:phone":"+34 913 20 53 77",
    "sg:postcode":"28022",
    "sg:province":"Madrid",
    "wof:name":"Sanchez Fernandez-pintado Francisco Javier",
    "wof:placetype":"venue"
},
  "geometry": {"coordinates":[-3.6112909317,40.4493293762],"type":"Point"}
}