{
  "type": "Feature",
  "properties": {
    "iso:country":"ES",
    "sg:address":"Calle de Vega, 27",
    "sg:city":"Chiclana De La Frontera",
    "sg:orig_category":"Mercer\u00cda, Lencer\u00cda (al Por Menor)",
    "sg:phone":"+34 956 40 01 19",
    "sg:postcode":"11130",
    "sg:province":"C\u00e1diz",
    "wof:name":"Pedrero Cano Jose",
    "wof:placetype":"venue"
},
  "geometry": {"coordinates":[-6.1489601135,36.4198417664],"type":"Point"}
}