{
  "type": "Feature",
  "properties": {
    "addr:full":"Ctra Villaviciosa, 22 Gijon Asturias 33203",
    "addr:housenumber":"22",
    "addr:postcode":"33203",
    "addr:street":"Ctra Villaviciosa",
    "iso:country":"ES",
    "sg:address":"Ctra Villaviciosa, 22",
    "sg:city":"Gijon",
    "sg:orig_category":"Promotores Constructores",
    "sg:phone":"+34 985 13 43 58",
    "sg:postcode":"33203",
    "sg:province":"Asturias",
    "wof:name":"Promociones Villa San Lorenzo S.a.",
    "wof:placetype":"venue"
},
  "geometry": {"coordinates":[-5.6399488449,43.5339584351],"type":"Point"}
}