{
  "type": "Feature",
  "properties": {
    "addr:full":"Pla\u00c7 Vicent Ribes, 6 Turis Valencia 46389",
    "addr:housenumber":"6",
    "addr:postcode":"46389",
    "addr:street":"Vicent Ribes",
    "iso:country":"ES",
    "sg:address":"Pla\u00c7 Vicent Ribes, 6",
    "sg:city":"Turis",
    "sg:orig_category":"Art\u00cdculos Funerarios (al Por Menor)",
    "sg:phone":"+34 962 52 65 84",
    "sg:postcode":"46389",
    "sg:province":"Valencia",
    "wof:name":"Servicios Funerarios Turis S.l.l.",
    "wof:placetype":"venue"
},
  "geometry": {"coordinates":[-0.7127550244,39.3906974792],"type":"Point"}
}