{
  "type": "Feature",
  "properties": {
    "addr:full":"Calle de Archanda, 1 Madrid Madrid 28023",
    "addr:housenumber":"1",
    "addr:postcode":"28023",
    "addr:street":"Calle De Archanda",
    "iso:country":"ES",
    "sg:address":"Calle de Archanda, 1",
    "sg:city":"Madrid",
    "sg:orig_category":"Importaci\u00d3n",
    "sg:phone":"+34 913 07 68 32",
    "sg:postcode":"28023",
    "sg:province":"Madrid",
    "sg:website":"www.globax.org",
    "wof:name":"Bibcom S.l.",
    "wof:placetype":"venue"
},
  "geometry": {"coordinates":[-3.8079369068,40.4672737122],"type":"Point"}
}