{
  "type": "Feature",
  "properties": {
    "addr:full":"Plaz Mayor, S/n Tamames Salamanca 37600",
    "addr:housenumber":"s / n",
    "addr:postcode":"37600",
    "addr:street":"Plaz Mayor",
    "iso:country":"ES",
    "sg:address":"Plaz Mayor, S/n",
    "sg:city":"Tamames",
    "sg:orig_category":"Ense\u00d1anza, Formaci\u00d3n Profesional: Aprendizaje",
    "sg:phone":"+34 923 44 94 84",
    "sg:postcode":"37600",
    "sg:province":"Salamanca",
    "wof:name":"Ayuntamiento De Tamames",
    "wof:placetype":"venue"
},
  "geometry": {"coordinates":[-6.1053500175,40.6583099365],"type":"Point"}
}