{
  "type": "Feature",
  "properties": {
    "addr:full":"Calle de Gregorio Uzquiano, 20 Portugalete Vizcaya 48920",
    "addr:housenumber":"20",
    "addr:postcode":"48920",
    "addr:street":"Calle De Gregorio Uzquiano",
    "iso:country":"ES",
    "sg:address":"Calle de Gregorio Uzquiano, 20",
    "sg:city":"Portugalete",
    "sg:orig_category":"Telas Y Sedas (al Por Menor)",
    "sg:phone":"+34 944 62 43 48",
    "sg:postcode":"48920",
    "sg:province":"Vizcaya",
    "wof:name":"Bilbomoda S. L.",
    "wof:placetype":"venue"
},
  "geometry": {"coordinates":[-3.0209400654,43.318397522],"type":"Point"}
}