{
  "type": "Feature",
  "properties": {
    "iso:country":"ES",
    "sg:address":"Calle de Union, 11",
    "sg:city":"Valladolid",
    "sg:orig_category":"Inform\u00c1tica (estudios, Servicios, Asesor\u00cda, Formaci\u00d3n)",
    "sg:phone":"+34 983 21 93 94",
    "sg:postcode":"47005",
    "sg:province":"Valladolid",
    "wof:name":"Trevenque Sistemas De Informacion S.l.",
    "wof:placetype":"venue"
},
  "geometry": {"coordinates":[-4.713973999,41.6489486694],"type":"Point"}
}