{
  "type": "Feature",
  "properties": {
    "addr:full":"Carrer de Sant Pere, 10 Vilafranca Penedes Barcelona 08720",
    "addr:housenumber":"10",
    "addr:postcode":"08720",
    "addr:street":"Carrer De Sant Pere;Penedes Barcelona",
    "iso:country":"ES",
    "sg:address":"Carrer de Sant Pere, 10",
    "sg:city":"Vilafranca Penedes",
    "sg:orig_category":"Electrodom\u00c9sticos (al Por Menor)",
    "sg:phone":"+34 938 90 08 27",
    "sg:postcode":"08720",
    "sg:province":"Barcelona",
    "wof:name":"Vives Pons Juan",
    "wof:placetype":"venue"
},
  "geometry": {"coordinates":[1.6971181631,41.3451919556],"type":"Point"}
}