{
  "type": "Feature",
  "properties": {
    "addr:full":"Avgd Monaco, 92 Badalona Barcelona 08917",
    "addr:housenumber":"92",
    "addr:postcode":"08917",
    "iso:country":"ES",
    "sg:address":"Avgd Monaco, 92",
    "sg:city":"Badalona",
    "sg:orig_category":"Cajas De Ahorro",
    "sg:phone":"+34 934 60 34 80",
    "sg:postcode":"08917",
    "sg:province":"Barcelona",
    "wof:name":"Caixa D'estalvis De Catalunya",
    "wof:placetype":"venue"
},
  "geometry": {"coordinates":[2.2214200497,41.4528083801],"type":"Point"}
}