{
  "type": "Feature",
  "properties": {
    "addr:full":"Rua Doctor Loureiro Crespo, 83 Pontevedra Pontevedra 36004",
    "addr:housenumber":"83",
    "addr:postcode":"36004",
    "addr:street":"Rua Doctor Loureiro Crespo",
    "iso:country":"ES",
    "sg:address":"Rua Doctor Loureiro Crespo, 83",
    "sg:city":"Pontevedra",
    "sg:orig_category":"Pesca Y Caza: Art\u00cdculos (al Por Menor)",
    "sg:phone":"+34 986 84 60 94",
    "sg:postcode":"36004",
    "sg:province":"Pontevedra",
    "wof:name":"Manuel Santos Cao S. A.",
    "wof:placetype":"venue"
},
  "geometry": {"coordinates":[-8.6298656464,42.4285964966],"type":"Point"}
}