{
  "type": "Feature",
  "properties": {
    "addr:full":"Ctra. Alcudia-arta, Km. 0022,0 Can Picafort Islas Baleares 07458",
    "addr:postcode":"07458",
    "addr:street":"Ctra. Alcudia-Arta Km. 0022,0",
    "iso:country":"ES",
    "sg:address":"Ctra. Alcudia-arta, Km. 0022,0",
    "sg:city":"Can Picafort",
    "sg:orig_category":"Distribuci\u00d3n De Petr\u00d3leo Y Derivados",
    "sg:phone":"+34 971 85 15 95",
    "sg:postcode":"07458",
    "sg:province":"Islas Baleares",
    "wof:name":"Esterrich Alos Simon",
    "wof:placetype":"venue"
},
  "geometry": {"coordinates":[3.1486649513,39.7653236389],"type":"Point"}
}