{
  "type": "Feature",
  "properties": {
    "addr:full":"Carrer de Francesc Macia, 400 Granollers Barcelona 08400",
    "addr:housenumber":"400",
    "addr:postcode":"08400",
    "addr:street":"Carrer De Francesc Macia",
    "iso:country":"ES",
    "sg:address":"Carrer de Francesc Macia, 400",
    "sg:city":"Granollers",
    "sg:orig_category":"Embalajes",
    "sg:phone":"+34 935 10 69 39",
    "sg:postcode":"08400",
    "sg:province":"Barcelona",
    "wof:name":"Papers Robert Sl",
    "wof:placetype":"venue"
},
  "geometry": {"coordinates":[2.2889099121,41.6079521179],"type":"Point"}
}