{
  "type": "Feature",
  "properties": {
    "iso:country":"ES",
    "sg:address":"Calle de Poeta Cano Cervantes, 11",
    "sg:city":"Garrucha",
    "sg:orig_category":"Empresas De Carpinter\u00cda De Madera",
    "sg:phone":"+34 950 46 01 58",
    "sg:postcode":"04630",
    "sg:province":"Almer\u00eda",
    "wof:name":"Martin Cervantes E Hijos S.l.",
    "wof:placetype":"venue"
},
  "geometry": {"coordinates":[-1.8213640451,37.182964325],"type":"Point"}
}