{
  "type": "Feature",
  "properties": {
    "addr:full":"Rua Maria Pita, 91 Viana Do Bolo Ourense 32550",
    "addr:housenumber":"91",
    "addr:postcode":"32550",
    "addr:street":"Rua Maria Pita",
    "iso:country":"ES",
    "sg:address":"Rua Maria Pita, 91",
    "sg:city":"Viana Do Bolo",
    "sg:orig_category":"Molduras, Junquillos, Listones Y Molduras Perforadas",
    "sg:phone":"+34 988 34 02 37",
    "sg:postcode":"32550",
    "sg:province":"Ourense",
    "wof:name":"Alvarez Gomez Felipe",
    "wof:placetype":"venue"
},
  "geometry": {"coordinates":[-7.1124186516,42.1804161072],"type":"Point"}
}