{
  "type": "Feature",
  "properties": {
    "addr:full":"Calle de Barrio Nuevo Pozo, S/n Calasparra Murcia 30420",
    "addr:housenumber":"s / n",
    "addr:postcode":"30420",
    "addr:street":"Calle De Barrio Nuevo Pozo",
    "iso:country":"ES",
    "sg:address":"Calle de Barrio Nuevo Pozo, S/n",
    "sg:city":"Calasparra",
    "sg:orig_category":"Art\u00cdculos Funerarios (al Por Menor)",
    "sg:phone":"+34 968 72 07 12",
    "sg:postcode":"30420",
    "sg:province":"Murcia",
    "wof:name":"Servicios Y Gestion Funeraria",
    "wof:placetype":"venue"
},
  "geometry": {"coordinates":[-1.7075090408,38.2330513],"type":"Point"}
}