{
  "type": "Feature",
  "properties": {
    "addr:full":"Ctra Frailes, 3 Santa Ana Ja\u00e9n 23692",
    "addr:housenumber":"3",
    "addr:postcode":"23692",
    "addr:street":"Ctra Frailes",
    "iso:country":"ES",
    "sg:address":"Ctra Frailes, 3",
    "sg:city":"Santa Ana",
    "sg:orig_category":"Asociaciones Y Clubs Deportivos",
    "sg:phone":"+34 953 59 72 54",
    "sg:postcode":"23692",
    "sg:province":"Ja\u00e9n",
    "wof:name":"Club Fuente Del Rey",
    "wof:placetype":"venue"
},
  "geometry": {"coordinates":[-3.8869600296,37.4632034302],"type":"Point"}
}