{
  "type": "Feature",
  "properties": {
    "iso:country":"ES",
    "sg:address":"Pol Ind Munic Transv 4, 7",
    "sg:city":"Tudela",
    "sg:orig_category":"Comisarios",
    "sg:phone":"+34 948 82 79 39",
    "sg:postcode":"31500",
    "sg:province":"Navarra",
    "wof:name":"Alba Ultra Juan Manuel",
    "wof:placetype":"venue"
},
  "geometry": {"coordinates":[-1.4821481705,42.1872329712],"type":"Point"}
}