{
  "type": "Feature",
  "properties": {
    "iso:country":"ES",
    "sg:address":"Avda De Rosalia De Castro, 21",
    "sg:city":"Ponteareas",
    "sg:orig_category":"Herramientas Y Suministros Para Plomeros",
    "sg:phone":"+34 986 66 06 55",
    "sg:postcode":"36860",
    "sg:province":"Pontevedra",
    "wof:name":"Comercial Alvaro Y Rodriguez S.l.",
    "wof:placetype":"venue"
},
  "geometry": {"coordinates":[-8.5163888931,42.1783599854],"type":"Point"}
}