{
  "type": "Feature",
  "properties": {
    "iso:country":"ES",
    "sg:address":"Carr Calvario, 95",
    "sg:city":"Betera",
    "sg:orig_category":"Supermercados Y Hipermercados",
    "sg:phone":"+34 961 60 11 10",
    "sg:postcode":"46117",
    "sg:province":"Valencia",
    "wof:name":"Aloy Dasi Salvador Vicente",
    "wof:placetype":"venue"
},
  "geometry": {"coordinates":[-0.4560672045,39.5891151428],"type":"Point"}
}