{
  "type": "Feature",
  "properties": {
    "addr:full":"Avda Navarra De, 5 Donostia-san Sebastian Guip\u00f9zcoa 20013",
    "addr:housenumber":"5",
    "addr:postcode":"20013",
    "addr:street":"Avda Navarra De",
    "iso:country":"ES",
    "sg:address":"Avda Navarra De, 5",
    "sg:city":"Donostia-san Sebastian",
    "sg:orig_category":"Comercio De Piezas De Recambio Y De Accesorios De Veh\u00cdculos, Veh\u00cdculos Industriales",
    "sg:phone":"+34 943 27 92 11",
    "sg:postcode":"20013",
    "sg:province":"Guip\u00f9zcoa",
    "sg:website":"www.estaciondeserviciolarramendi.com",
    "wof:name":"Estacion Servicio Larramendi S. A.",
    "wof:placetype":"venue"
},
  "geometry": {"coordinates":[-1.9704589844,43.3257369995],"type":"Point"}
}