{
  "type": "Feature",
  "properties": {
    "addr:full":"Rond General Mitre, 196 Barcelona Barcelona 08006",
    "addr:housenumber":"196",
    "addr:postcode":"08006",
    "addr:street":"Mitre",
    "iso:country":"ES",
    "sg:address":"Rond General Mitre, 196",
    "sg:city":"Barcelona",
    "sg:orig_category":"Detectives, Agentes Investigadores Privados",
    "sg:phone":"+34 932 12 35 62",
    "sg:postcode":"08006",
    "sg:province":"Barcelona",
    "wof:name":"Heras Castellvi Ignacio De Las",
    "wof:placetype":"venue"
},
  "geometry": {"coordinates":[2.144423008,41.4053268433],"type":"Point"}
}