{
  "type": "Feature",
  "properties": {
    "iso:country":"ES",
    "sg:address":"Calle de Virgen De Lluc, 32",
    "sg:city":"Madrid",
    "sg:orig_category":"Molduras, Junquillos, Listones Y Molduras Perforadas",
    "sg:phone":"+34 914 03 62 59",
    "sg:postcode":"28027",
    "sg:province":"Madrid",
    "wof:name":"Cortes Martinez Carlos Felix",
    "wof:placetype":"venue"
},
  "geometry": {"coordinates":[-3.6525681019,40.4346885681],"type":"Point"}
}