{
  "type": "Feature",
  "properties": {
    "addr:full":"Ctra Leon, S/n Valdevimbre Le\u00f3n 24230",
    "addr:postcode":"24230",
    "addr:street":"Ctra Leon S / N Valdevimbre Leo\u0301N",
    "iso:country":"ES",
    "sg:address":"Ctra Leon, S/n",
    "sg:city":"Valdevimbre",
    "sg:orig_category":"Comerciantes Al Por Mayor De Vinos, Licores Y Alcoholes",
    "sg:phone":"+34 987 30 42 21",
    "sg:postcode":"24230",
    "sg:province":"Le\u00f3n",
    "sg:website":"www.paginasamarillas.es",
    "wof:name":"Los Prietos, C.b.",
    "wof:placetype":"venue"
},
  "geometry": {"coordinates":[-5.6176609993,42.4199371338],"type":"Point"}
}