{
  "type": "Feature",
  "properties": {
    "addr:full":"Calle de Basilon, 40 Quintanilla Onesimo Valladolid 47350",
    "addr:housenumber":"40",
    "addr:postcode":"47350",
    "addr:street":"Calle De Basilon",
    "iso:country":"ES",
    "sg:address":"Calle de Basilon, 40",
    "sg:city":"Quintanilla Onesimo",
    "sg:orig_category":"Transportes Por V\u00cdas Navegables",
    "sg:phone":"+34 983 68 02 54",
    "sg:postcode":"47350",
    "sg:province":"Valladolid",
    "wof:name":"Rodriguez Gomez Felix",
    "wof:placetype":"venue"
},
  "geometry": {"coordinates":[-4.3620896339,41.6236724854],"type":"Point"}
}