{
  "type": "Feature",
  "properties": {
    "addr:full":"Avda Juan Xxiii, 67 Cieza Murcia 30530",
    "addr:housenumber":"67",
    "addr:postcode":"30530",
    "addr:street":"Avda Juan Xxiii",
    "iso:country":"ES",
    "sg:address":"Avda Juan Xxiii, 67",
    "sg:city":"Cieza",
    "sg:orig_category":"Caf\u00c9s, Bares, Cervecer\u00cdas",
    "sg:phone":"+34 968 45 48 38",
    "sg:postcode":"30530",
    "sg:province":"Murcia",
    "wof:name":"Ortiz Real S.l.",
    "wof:placetype":"venue"
},
  "geometry": {"coordinates":[-1.4157639742,38.238986969],"type":"Point"}
}