{
  "type": "Feature",
  "properties": {
    "addr:full":"Av Bartomeu Riutort, 34 Can Pastilla Islas Baleares 07610",
    "addr:housenumber":"34",
    "addr:postcode":"07610",
    "addr:street":"Av Bartomeu Riutort",
    "iso:country":"ES",
    "sg:address":"Av Bartomeu Riutort, 34",
    "sg:city":"Can Pastilla",
    "sg:orig_category":"Art\u00cdculos De Regalo (al Por Menor)",
    "sg:phone":"+34 971 26 46 75",
    "sg:postcode":"07610",
    "sg:province":"Islas Baleares",
    "wof:name":"Llabres Ramis Francisco",
    "wof:placetype":"venue"
},
  "geometry": {"coordinates":[2.7243249416,39.5336914062],"type":"Point"}
}