{
  "type": "Feature",
  "properties": {
    "iso:country":"ES",
    "sg:address":"Plaz Moraleja (de La), 4",
    "sg:city":"Alcobendas",
    "sg:orig_category":"Fisioterapia",
    "sg:phone":"+34 916 50 46 19",
    "sg:postcode":"28109",
    "sg:province":"Madrid",
    "wof:name":"Kinefis S.l.",
    "wof:placetype":"venue"
},
  "geometry": {"coordinates":[-3.6215980053,40.5304718018],"type":"Point"}
}