{
  "type": "Feature",
  "properties": {
    "addr:full":"Calle de Hospicio, 17 Aranda Duero Burgos 09400",
    "addr:housenumber":"17",
    "addr:postcode":"09400",
    "addr:street":"Calle De Hospicio",
    "iso:country":"ES",
    "sg:address":"Calle de Hospicio, 17",
    "sg:city":"Aranda Duero",
    "sg:orig_category":"Molduras, Junquillos, Listones Y Molduras Perforadas",
    "sg:phone":"+34 947 51 15 31",
    "sg:postcode":"09400",
    "sg:province":"Burgos",
    "wof:name":"Rubio Andres Domingo",
    "wof:placetype":"venue"
},
  "geometry": {"coordinates":[-3.6817989349,41.670879364],"type":"Point"}
}