{
  "type": "Feature",
  "properties": {
    "addr:full":"Carrer de Boqueria, 42 Barcelona Barcelona 08002",
    "addr:housenumber":"42",
    "addr:postcode":"08002",
    "addr:street":"Carrer De Boqueria",
    "iso:country":"ES",
    "sg:address":"Carrer de Boqueria, 42",
    "sg:city":"Barcelona",
    "sg:orig_category":"Bisuteros (fabricaci\u00d3n, Al Por Mayor)",
    "sg:phone":"+34 933 17 23 49",
    "sg:postcode":"08002",
    "sg:province":"Barcelona",
    "wof:name":"Buni Dos S.a.",
    "wof:placetype":"venue"
},
  "geometry": {"coordinates":[2.1754570007,41.381778717],"type":"Point"}
}