{
  "type": "Feature",
  "properties": {
    "iso:country":"ES",
    "sg:address":"Santabaya, S/n",
    "sg:city":"Santa Baia",
    "sg:orig_category":"Iglesia Cat\u00d3lica",
    "sg:phone":"+34 988 45 85 21",
    "sg:postcode":"32858",
    "sg:province":"Ourense",
    "wof:name":"Obispado De Orense",
    "wof:placetype":"venue"
},
  "geometry": {"coordinates":[-8.0384159088,41.9874343872],"type":"Point"}
}