{
  "type": "Feature",
  "properties": {
    "iso:country":"ES",
    "sg:address":"Calle de Marcenado, 44",
    "sg:city":"Madrid",
    "sg:orig_category":"Ingenier\u00cda, Centros De Estudios (diversos)",
    "sg:phone":"+34 914 15 42 92",
    "sg:postcode":"28002",
    "sg:province":"Madrid",
    "wof:name":"Rubio Gonzalez Javier",
    "wof:placetype":"venue"
},
  "geometry": {"coordinates":[-3.6735610962,40.4483947754],"type":"Point"}
}