{
  "type": "Feature",
  "properties": {
    "addr:full":"Calle de Jesus, 14 Palma Islas Baleares 07003",
    "addr:housenumber":"14",
    "addr:postcode":"07003",
    "addr:street":"Calle De Jesus",
    "iso:country":"ES",
    "sg:address":"Calle de Jesus, 14",
    "sg:city":"Palma",
    "sg:orig_category":"Ense\u00d1anza, Formaci\u00d3n Profesional: Aprendizaje",
    "sg:phone":"+34 971 75 61 69",
    "sg:postcode":"07003",
    "sg:province":"Islas Baleares",
    "wof:name":"Tesoreria General De La Seguridad Social-direccion Provincial De Baleares",
    "wof:placetype":"venue"
},
  "geometry": {"coordinates":[2.646522522,39.5792007446],"type":"Point"}
}