{
  "type": "Feature",
  "properties": {
    "addr:full":"Avda Rodeiro, 25 Lalin De Arriba Pontevedra 36500",
    "addr:housenumber":"25",
    "addr:postcode":"36500",
    "addr:street":"Avda Rodeiro",
    "iso:country":"ES",
    "sg:address":"Avda Rodeiro, 25",
    "sg:city":"Lalin De Arriba",
    "sg:orig_category":"Molduras, Junquillos, Listones Y Molduras Perforadas",
    "sg:phone":"+34 986 79 01 39",
    "sg:postcode":"36500",
    "sg:province":"Pontevedra",
    "wof:name":"Moure Vazquez Rosa Maria",
    "wof:placetype":"venue"
},
  "geometry": {"coordinates":[-8.1024894714,42.6614494324],"type":"Point"}
}