{
  "type": "Feature",
  "properties": {
    "iso:country":"ES",
    "sg:address":"Calle de O\u00d1a, 43",
    "sg:city":"Madrid",
    "sg:orig_category":"M\u00c1quinas Textiles, Accesorios Y Suministros (fabricaci\u00d3n)",
    "sg:phone":"+34 913 83 37 97",
    "sg:postcode":"28050",
    "sg:province":"Madrid",
    "wof:name":"Mecos Madrid S.l.",
    "wof:placetype":"venue"
},
  "geometry": {"coordinates":[-3.6674420834,40.4890365601],"type":"Point"}
}