{
  "type": "Feature",
  "properties": {
    "addr:full":"Calle de Arriaza, 11 Madrid Madrid 28008",
    "addr:housenumber":"11",
    "addr:postcode":"madrid;28008",
    "addr:street":"Calle De Arriaza",
    "iso:country":"ES",
    "sg:address":"Calle de Arriaza, 11",
    "sg:city":"Madrid",
    "sg:orig_category":"Institutos De Belleza",
    "sg:phone":"+34 915 42 37 98",
    "sg:postcode":"28008",
    "sg:province":"Madrid",
    "wof:name":"El Balneario De Sonia S.l.",
    "wof:placetype":"venue"
},
  "geometry": {"coordinates":[-3.7162470818,40.4215507507],"type":"Point"}
}