{
  "type": "Feature",
  "properties": {
    "iso:country":"ES",
    "sg:address":"Carrer de Gasometre, 87",
    "sg:city":"Terrassa",
    "sg:orig_category":"Molduras, Junquillos, Listones Y Molduras Perforadas",
    "sg:phone":"+34 937 86 21 06",
    "sg:postcode":"08223",
    "sg:province":"Barcelona",
    "wof:name":"Ruiz Gonzalez Francisco",
    "wof:placetype":"venue"
},
  "geometry": {"coordinates":[2.0098869801,41.5556144714],"type":"Point"}
}