{
  "type": "Feature",
  "properties": {
    "addr:full":"Pias(san Miguel), S/n Rosal Pontevedra 36760",
    "addr:housenumber":"s / n",
    "addr:postcode":"36760",
    "addr:street":"San Miguel",
    "iso:country":"ES",
    "sg:address":"Pias(san Miguel), S/n",
    "sg:city":"Rosal",
    "sg:orig_category":"Empresas De Carpinter\u00cda",
    "sg:phone":"+34 986 62 51 64",
    "sg:postcode":"36760",
    "sg:province":"Pontevedra",
    "wof:name":"Sistemas Fametal S.l.",
    "wof:placetype":"venue"
},
  "geometry": {"coordinates":[-8.7972040176,41.930896759],"type":"Point"}
}