{
  "type": "Feature",
  "properties": {
    "addr:full":"Calle de San Juan, 37 Jadraque Guadalajara 19240",
    "addr:housenumber":"37",
    "addr:postcode":"19240",
    "addr:street":"Calle De San Juan",
    "iso:country":"ES",
    "sg:address":"Calle de San Juan, 37",
    "sg:city":"Jadraque",
    "sg:orig_category":"Reposter\u00cdas",
    "sg:phone":"+34 949 89 01 53",
    "sg:postcode":"19240",
    "sg:province":"Guadalajara",
    "wof:name":"Melado Gomez Florencio Del",
    "wof:placetype":"venue"
},
  "geometry": {"coordinates":[-2.9240028858,40.9259872437],"type":"Point"}
}