{
  "type": "Feature",
  "properties": {
    "addr:full":"Carrer de Anselm Clave, 28 Caldes Montbui Barcelona 08140",
    "addr:housenumber":"28",
    "addr:postcode":"08140",
    "addr:street":"Carrer De Anselm Clave;Montbui Barcelona",
    "iso:country":"ES",
    "sg:address":"Carrer de Anselm Clave, 28",
    "sg:city":"Caldes Montbui",
    "sg:orig_category":"Triper\u00cdas",
    "sg:phone":"+34 938 65 01 47",
    "sg:postcode":"08140",
    "sg:province":"Barcelona",
    "wof:name":"Jose Ors S.a.",
    "wof:placetype":"venue"
},
  "geometry": {"coordinates":[2.1683039665,41.6290779114],"type":"Point"}
}