{
  "type": "Feature",
  "properties": {
    "addr:full":"Carr Nauselva, 11 Canals Valencia 46650",
    "addr:housenumber":"11",
    "addr:postcode":"46650",
    "addr:street":"Carr Nauselva",
    "iso:country":"ES",
    "sg:address":"Carr Nauselva, 11",
    "sg:city":"Canals",
    "sg:orig_category":"Reposter\u00cdas",
    "sg:phone":"+34 962 24 09 75",
    "sg:postcode":"46650",
    "sg:province":"Valencia",
    "wof:name":"Panaderia Casa Mario S.l.",
    "wof:placetype":"venue"
},
  "geometry": {"coordinates":[-0.588168025,38.9644203186],"type":"Point"}
}