{
  "type": "Feature",
  "properties": {
    "addr:full":"Carrer de Peix (del), 4 Vilassar De Mar Barcelona 08340",
    "addr:housenumber":"4",
    "addr:postcode":"08340",
    "addr:street":"Carrer De Peix Del",
    "iso:country":"ES",
    "sg:address":"Carrer de Peix (del), 4",
    "sg:city":"Vilassar De Mar",
    "sg:orig_category":"Ropa Para Se\u00d1oras (al Por Menor)",
    "sg:phone":"+34 937 59 19 17",
    "sg:postcode":"08340",
    "sg:province":"Barcelona",
    "wof:name":"Lopez Mu\u00f1oz Josefa",
    "wof:placetype":"venue"
},
  "geometry": {"coordinates":[2.3907299042,41.5019264221],"type":"Point"}
}