{
  "type": "Feature",
  "properties": {
    "addr:full":"Poligono Mora-garay, S/n Gijon Asturias 33211",
    "addr:postcode":"33211",
    "addr:street":"Mora-Garay S / N",
    "iso:country":"ES",
    "sg:address":"Poligono Mora-garay, S/n",
    "sg:city":"Gijon",
    "sg:orig_category":"Transportes Por Carretera: Lotes Completos, Mercanc\u00cdas Diversas",
    "sg:phone":"+34 985 30 10 15",
    "sg:postcode":"33211",
    "sg:province":"Asturias",
    "wof:name":"Gregorio Bravo Exclusivas S.l.",
    "wof:placetype":"venue"
},
  "geometry": {"coordinates":[-5.6850991249,43.532913208],"type":"Point"}
}