{
  "type": "Feature",
  "properties": {
    "addr:full":"Calle de Otero Pedrayo, 13 Curtis-estacion La Coru\u00f1a 15379",
    "addr:housenumber":"13",
    "addr:postcode":"15379",
    "addr:street":"Calle De Otero Pedrayo;La Corun\u0303A",
    "iso:country":"ES",
    "sg:address":"Calle de Otero Pedrayo, 13",
    "sg:city":"Curtis-estacion",
    "sg:orig_category":"Negocio De Materiales De Construcci\u00d3n",
    "sg:phone":"+34 981 78 64 35",
    "sg:postcode":"15379",
    "sg:province":"La Coru\u00f1a",
    "wof:name":"Sanchez Garcia Fernando Jose",
    "wof:placetype":"venue"
},
  "geometry": {"coordinates":[-8.3964595795,43.3701095581],"type":"Point"}
}