{
  "type": "Feature",
  "properties": {
    "addr:full":"Mercat Sant Antoni, S/n Barcelona Barcelona 08015",
    "addr:housenumber":"s",
    "addr:postcode":"08015",
    "addr:street":"/ N",
    "iso:country":"ES",
    "sg:address":"Mercat Sant Antoni, S/n",
    "sg:city":"Barcelona",
    "sg:orig_category":"Carnicer\u00cdas, Carnicer\u00cdas",
    "sg:phone":"+34 934 26 89 66",
    "sg:postcode":"08015",
    "sg:province":"Barcelona",
    "wof:name":"Armengol Peiret Jorge",
    "wof:placetype":"venue"
},
  "geometry": {"coordinates":[2.1620833874,41.3786125183],"type":"Point"}
}