{
  "type": "Feature",
  "properties": {
    "iso:country":"ES",
    "sg:address":"Calle de Mariana Pineda, 5",
    "sg:city":"Sestao",
    "sg:orig_category":"Asociaciones Y Clubs Deportivos",
    "sg:phone":"+34 944 96 26 46",
    "sg:postcode":"48910",
    "sg:province":"Vizcaya",
    "wof:name":"Sestao River Club",
    "wof:placetype":"venue"
},
  "geometry": {"coordinates":[-3.0114150047,43.3096122742],"type":"Point"}
}