{
  "type": "Feature",
  "properties": {
    "addr:full":"Calle de Jesus Ferrer Jimeno, 8 Palmas De Gran Canaria Las Palmas 35010",
    "addr:housenumber":"8",
    "addr:postcode":"35010",
    "addr:street":"Calle De Jesus Ferrer Jimeno",
    "iso:country":"ES",
    "sg:address":"Calle de Jesus Ferrer Jimeno, 8",
    "sg:city":"Palmas De Gran Canaria",
    "sg:orig_category":"Doctores En Medicina",
    "sg:phone":"+34 928 22 15 12",
    "sg:postcode":"35010",
    "sg:province":"Las Palmas",
    "wof:name":"Ochoa Talavera Angeles",
    "wof:placetype":"venue"
},
  "geometry": {"coordinates":[-15.436255455,28.1328048706],"type":"Point"}
}