{
  "type": "Feature",
  "properties": {
    "iso:country":"ES",
    "sg:address":"C/ Vicente Blasco Iba\u00d1ez, 16",
    "sg:city":"Elche",
    "sg:orig_category":"Estancos",
    "sg:phone":"+34 965 44 24 96",
    "sg:postcode":"03201",
    "sg:province":"Alicante",
    "wof:name":"Marco Serrano Vicente",
    "wof:placetype":"venue"
},
  "geometry": {"coordinates":[-0.7017310262,38.2679672241],"type":"Point"}
}