{
  "type": "Feature",
  "properties": {
    "addr:full":"Pase Chopera (de La), 96 Alcobendas Madrid 28100",
    "addr:postcode":"28100",
    "iso:country":"ES",
    "sg:address":"Pase Chopera (de La), 96",
    "sg:city":"Alcobendas",
    "sg:orig_category":"Sociedades, Compa\u00d1\u00cdas Aseguradoras",
    "sg:phone":"+34 916 62 55 29",
    "sg:postcode":"28100",
    "sg:province":"Madrid",
    "wof:name":"La Union Madrile\u00d1a S.a.",
    "wof:placetype":"venue"
},
  "geometry": {"coordinates":[-3.6437749863,40.5435066223],"type":"Point"}
}