{
  "type": "Feature",
  "properties": {
    "addr:full":"Avda Fisterra, 163 Arteixo La Coru\u00f1a 15142",
    "addr:housenumber":"163",
    "addr:postcode":"15142",
    "addr:street":"Avda Fisterra;La Corun\u0303A",
    "iso:country":"ES",
    "sg:address":"Avda Fisterra, 163",
    "sg:city":"Arteixo",
    "sg:orig_category":"M\u00c9dicos: Estomatolog\u00cda",
    "sg:phone":"+34 981 60 27 58",
    "sg:postcode":"15142",
    "sg:province":"La Coru\u00f1a",
    "wof:name":"Centro Odontologico Integral",
    "wof:placetype":"venue"
},
  "geometry": {"coordinates":[-8.5084037781,43.305770874],"type":"Point"}
}