{
  "type": "Feature",
  "properties": {
    "addr:full":"Larin De Arriba, S/n Larin De Arriba La Coru\u00f1a 15144",
    "addr:housenumber":"s / n;corun\u0303a",
    "addr:postcode":"15144",
    "addr:street":"Larin;Arriba",
    "iso:country":"ES",
    "sg:address":"Larin De Arriba, S/n",
    "sg:city":"Larin De Arriba",
    "sg:classifiers":[
        {
            "category":"Sports & Exercise",
            "subcategory":"Golf",
            "type":"Entertainment"
        }
    ],
    "sg:phone":"+34 981 64 25 45",
    "sg:postcode":"15144",
    "sg:province":"La Coru\u00f1a",
    "sg:tags":[
        "y",
        "de",
        "campos",
        "clases"
    ],
    "sg:website":"www.herculesgolf.com",
    "wof:name":"Hercules Club De Golf",
    "wof:placetype":"venue"
},
  "geometry": {"coordinates":[-8.1520986557,43.4764251709],"type":"Point"}
}