{
  "type": "Feature",
  "properties": {
    "addr:full":"Plaz Nekazarien Plaza, 5 Elexalde Vizcaya 48970",
    "addr:housenumber":"5",
    "addr:postcode":"48970",
    "addr:street":"Plaz;Plaza",
    "iso:country":"ES",
    "sg:address":"Plaz Nekazarien Plaza, 5",
    "sg:city":"Elexalde",
    "sg:orig_category":"Iglesia Cat\u00d3lica",
    "sg:phone":"+34 944 49 14 97",
    "sg:postcode":"48970",
    "sg:province":"Vizcaya",
    "wof:name":"Obispado De Bilbao",
    "wof:placetype":"venue"
},
  "geometry": {"coordinates":[-2.8864479065,43.2193412781],"type":"Point"}
}