{
  "type": "Feature",
  "properties": {
    "iso:country":"ES",
    "sg:address":"Calle de Pablo Casals, S/n",
    "sg:city":"Parla",
    "sg:orig_category":"Institutos De Belleza",
    "sg:phone":"+34 916 05 06 47",
    "sg:postcode":"28980",
    "sg:province":"Madrid",
    "wof:name":"Varela Velasco Concepcion",
    "wof:placetype":"venue"
},
  "geometry": {"coordinates":[-3.7757165432,40.2273712158],"type":"Point"}
}