{
  "type": "Feature",
  "properties": {
    "addr:full":"Carrer de Salvador Dali, 36 Palma Islas Baleares 07011",
    "addr:housenumber":"36",
    "addr:postcode":"07011",
    "addr:street":"Carrer De Salvador Dali",
    "iso:country":"ES",
    "sg:address":"Carrer de Salvador Dali, 36",
    "sg:city":"Palma",
    "sg:orig_category":"Abogados",
    "sg:phone":"+34 971 73 25 82",
    "sg:postcode":"07011",
    "sg:province":"Islas Baleares",
    "wof:name":"Sicilia Merida Francisco Javier",
    "wof:placetype":"venue"
},
  "geometry": {"coordinates":[2.6336619854,39.5838279724],"type":"Point"}
}