{
  "type": "Feature",
  "properties": {
    "addr:full":"Calle de Pedro Gomez Meseguer, S/n Roldan Murcia 30709",
    "addr:housenumber":"s",
    "addr:postcode":"30709",
    "addr:street":"Calle De Pedro Gomez Meseguer;/ N",
    "iso:country":"ES",
    "sg:address":"Calle de Pedro Gomez Meseguer, S/n",
    "sg:city":"Roldan",
    "sg:orig_category":"Ense\u00d1anza Secundaria: Colegios Y Escuelas Privadas",
    "sg:phone":"+34 968 58 98 78",
    "sg:postcode":"30709",
    "sg:province":"Murcia",
    "wof:name":"Comunidad Autonoma De La Region De Murcia",
    "wof:placetype":"venue"
},
  "geometry": {"coordinates":[-1.0021890402,37.8021850586],"type":"Point"}
}