{
  "type": "Feature",
  "properties": {
    "iso:country":"ES",
    "sg:address":"Calle de Alfredo Calderon, 6",
    "sg:city":"Palmas De Gran Canaria",
    "sg:orig_category":"Electricidad Veh\u00cdculo",
    "sg:phone":"+34 928 23 25 34",
    "sg:postcode":"35006",
    "sg:province":"Las Palmas",
    "wof:name":"Hernandez Rodriguez Israel Arturo",
    "wof:placetype":"venue"
},
  "geometry": {"coordinates":[-15.4322118759,28.130531311],"type":"Point"}
}