{
  "type": "Feature",
  "properties": {
    "iso:country":"ES",
    "sg:address":"Calle de Trafalgar, 26",
    "sg:city":"Coll De'n Rabassa",
    "sg:orig_category":"Ropa Para Se\u00d1oras Y Caballeros (al Por Menor)",
    "sg:phone":"+34 971 26 15 89",
    "sg:postcode":"07007",
    "sg:province":"Islas Baleares",
    "wof:name":"Hermanos Cobos C.b.",
    "wof:placetype":"venue"
},
  "geometry": {"coordinates":[2.9117100239,39.6136398315],"type":"Point"}
}