{
  "type": "Feature",
  "properties": {
    "addr:full":"Ctra Sevilla-huelva, S/n Sanlucar Mayor Sevilla 41800",
    "addr:housenumber":"s / n",
    "addr:postcode":"41800",
    "addr:street":"Ctra Sevilla-Huelva",
    "iso:country":"ES",
    "sg:address":"Ctra Sevilla-huelva, S/n",
    "sg:city":"Sanlucar Mayor",
    "sg:orig_category":"Fabrica De Cer\u00c1micas",
    "sg:phone":"+34 955 70 02 13",
    "sg:postcode":"41800",
    "sg:province":"Sevilla",
    "wof:name":"Fuentes De Fuentes Julio",
    "wof:placetype":"venue"
},
  "geometry": {"coordinates":[-6.1956338882,37.3855361938],"type":"Point"}
}