{
  "type": "Feature",
  "properties": {
    "addr:full":"Calle de Stuart (de), 13 Aranjuez Madrid 28300",
    "addr:housenumber":"13",
    "addr:postcode":"28300",
    "addr:street":"Calle De Stuart De",
    "iso:country":"ES",
    "sg:address":"Calle de Stuart (de), 13",
    "sg:city":"Aranjuez",
    "sg:orig_category":"\u00d3ptica: Instrumentos (fabricaci\u00d3n)",
    "sg:phone":"+34 918 91 74 80",
    "sg:postcode":"28300",
    "sg:province":"Madrid",
    "wof:name":"Ribolen Ii S.l.",
    "wof:placetype":"venue"
},
  "geometry": {"coordinates":[-3.60323596,40.0352249146],"type":"Point"}
}