{
  "type": "Feature",
  "properties": {
    "addr:full":"Calle de San Andres, 126 Coru\u00d1a La Coru\u00f1a 15003",
    "addr:housenumber":"126",
    "addr:postcode":"15003",
    "addr:street":"Calle De San Andres;La Corun\u0303A",
    "iso:country":"ES",
    "sg:address":"Calle de San Andres, 126",
    "sg:city":"Coru\u00d1a",
    "sg:orig_category":"Trajes Y Adornos De Boda (confecci\u00d3n, Al Por Menor)",
    "sg:phone":"+34 981 22 31 17",
    "sg:postcode":"15003",
    "sg:province":"La Coru\u00f1a",
    "wof:name":"Lopez Rodriguez Maria Isabel",
    "wof:placetype":"venue"
},
  "geometry": {"coordinates":[-8.4048442841,43.3687705994],"type":"Point"}
}