{
  "type": "Feature",
  "properties": {
    "iso:country":"ES",
    "sg:address":"Carrer de Parellada (la), 53",
    "sg:city":"Vilafranca Penedes",
    "sg:orig_category":"Asociaciones Y Clubs Deportivos",
    "sg:phone":"+34 938 92 22 33",
    "sg:postcode":"08720",
    "sg:province":"Barcelona",
    "wof:name":"Puig Suria Ramon",
    "wof:placetype":"venue"
},
  "geometry": {"coordinates":[1.7006520033,41.346206665],"type":"Point"}
}