{
  "type": "Feature",
  "properties": {
    "addr:full":"Pase Ramon Y Cajal, S/n Huesca Huesca 22006",
    "addr:housenumber":"s",
    "addr:postcode":"22006",
    "addr:street":"Ramon Y Cajal;/ N",
    "iso:country":"ES",
    "sg:address":"Pase Ramon Y Cajal, S/n",
    "sg:city":"Huesca",
    "sg:orig_category":"Agentes, Concesionarios Y Sucursales De Veh\u00cdculos",
    "sg:phone":"+34 974 24 36 11",
    "sg:postcode":"22006",
    "sg:province":"Huesca",
    "wof:name":"Esteban Bandres S.a.",
    "wof:placetype":"venue"
},
  "geometry": {"coordinates":[-0.3877489865,42.1402511597],"type":"Point"}
}