{
  "type": "Feature",
  "properties": {
    "iso:country":"ES",
    "sg:address":"Kale Nagusia, 21",
    "sg:city":"Legazpi",
    "sg:orig_category":"Panader\u00cdas, Panader\u00cdas",
    "sg:phone":"+34 943 73 11 99",
    "sg:postcode":"20230",
    "sg:province":"Guip\u00f9zcoa",
    "wof:name":"Francisco Barandiaran Larrea",
    "wof:placetype":"venue"
},
  "geometry": {"coordinates":[-2.3315560818,43.0538253784],"type":"Point"}
}