{
  "type": "Feature",
  "properties": {
    "iso:country":"ES",
    "sg:address":"Crta De Peligros, S/n",
    "sg:city":"Pulianas",
    "sg:orig_category":"Reciclaje, Desguace De Veh\u00cdculos",
    "sg:phone":"+34 958 34 01 59",
    "sg:postcode":"18197",
    "sg:province":"Granada",
    "wof:name":"Marmol Ruiz Ismael",
    "wof:placetype":"venue"
},
  "geometry": {"coordinates":[-3.6097240448,37.2210998535],"type":"Point"}
}