{
  "type": "Feature",
  "properties": {
    "addr:full":"Calle de Real, 53 Parla Madrid 28980",
    "addr:housenumber":"53",
    "addr:postcode":"28980",
    "addr:street":"Calle De Real",
    "iso:country":"ES",
    "sg:address":"Calle de Real, 53",
    "sg:city":"Parla",
    "sg:orig_category":"Alquiler De V\u00cddeo",
    "sg:phone":"+34 916 98 29 98",
    "sg:postcode":"28980",
    "sg:province":"Madrid",
    "wof:name":"Alsu Vision S.l.",
    "wof:placetype":"venue"
},
  "geometry": {"coordinates":[-3.7701854706,40.2390403748],"type":"Point"}
}