{
  "type": "Feature",
  "properties": {
    "iso:country":"ES",
    "sg:address":"Carr Bartomeu Pasqual, S/n",
    "sg:city":"Santa Maria Del Cami",
    "sg:orig_category":"Cer\u00c1mica Art\u00cdstica Y Decorativa",
    "sg:phone":"+34 971 62 13 06",
    "sg:postcode":"07320",
    "sg:province":"Islas Baleares",
    "wof:name":"Vich Coll Catalina",
    "wof:placetype":"venue"
},
  "geometry": {"coordinates":[2.7762899399,39.6513633728],"type":"Point"}
}