{
  "type": "Feature",
  "properties": {
    "addr:full":"Avda Polonia, 474 Atalayas Castell\u00f3n 12598",
    "addr:housenumber":"474",
    "addr:postcode":"12598",
    "addr:street":"Avda Polonia;Castello\u0301N",
    "iso:country":"ES",
    "sg:address":"Avda Polonia, 474",
    "sg:city":"Atalayas",
    "sg:orig_category":"Inmobiliaria (agencias)",
    "sg:phone":"+34 964 48 06 79",
    "sg:postcode":"12598",
    "sg:province":"Castell\u00f3n",
    "wof:name":"Zonas Y Sistemas S.a.",
    "wof:placetype":"venue"
},
  "geometry": {"coordinates":[-0.0360242017,39.9860687256],"type":"Point"}
}