{
  "type": "Feature",
  "properties": {
    "iso:country":"ES",
    "sg:address":"Pg Antoni Maura, 61",
    "sg:city":"Manacor",
    "sg:orig_category":"Farmacias",
    "sg:phone":"+34 971 55 12 68",
    "sg:postcode":"07500",
    "sg:province":"Islas Baleares",
    "wof:name":"Llull Cabrer Andres",
    "wof:placetype":"venue"
},
  "geometry": {"coordinates":[3.2150170803,39.5717468262],"type":"Point"}
}