{
  "type": "Feature",
  "properties": {
    "addr:full":"Carr Princeps D'espanya, 17 Alfas Pi Alicante 03580",
    "addr:housenumber":"17",
    "addr:postcode":"03580",
    "addr:street":"Carr Princeps D'Espanya",
    "iso:country":"ES",
    "sg:address":"Carr Princeps D'espanya, 17",
    "sg:city":"Alfas Pi",
    "sg:orig_category":"\u00d3ptica: Instrumentos (fabricaci\u00d3n)",
    "sg:phone":"+34 965 88 78 72",
    "sg:postcode":"03580",
    "sg:province":"Alicante",
    "wof:name":"Optica Mediterranea Mare Nostrum S.l.",
    "wof:placetype":"venue"
},
  "geometry": {"coordinates":[-0.483141005,38.3732948303],"type":"Point"}
}