{
  "type": "Feature",
  "properties": {
    "iso:country":"ES",
    "sg:address":"Calle de Hermanos Falco, 35",
    "sg:city":"Albacete",
    "sg:orig_category":"Restaurantes",
    "sg:phone":"+34 967 24 48 14",
    "sg:postcode":"02006",
    "sg:province":"Albacete",
    "wof:name":"Sanchez Escobar Juan",
    "wof:placetype":"venue"
},
  "geometry": {"coordinates":[-1.8478269577,38.9849128723],"type":"Point"}
}