{
  "type": "Feature",
  "properties": {
    "iso:country":"ES",
    "sg:address":"Calle de Maria Rosa Alonso, 11",
    "sg:city":"Cuesta",
    "sg:orig_category":"Congelados: Productos Alimentarios (fabricaci\u00d3n, Al Por Mayor)",
    "sg:phone":"+34 922 64 54 08",
    "sg:postcode":"38320",
    "sg:province":"Santa Cruz De Tenerife",
    "wof:name":"Ramos Avero Juan",
    "wof:placetype":"venue"
},
  "geometry": {"coordinates":[-16.2934398651,28.4689979553],"type":"Point"}
}