{
  "type": "Feature",
  "properties": {
    "addr:full":"C/ Alexandre Rossello, 4 Manacor Islas Baleares 07500",
    "addr:housenumber":"4",
    "addr:postcode":"07500",
    "addr:street":"C / Alexandre Rossello",
    "iso:country":"ES",
    "sg:address":"C/ Alexandre Rossello, 4",
    "sg:city":"Manacor",
    "sg:orig_category":"Ropa Para Se\u00d1oras (al Por Menor)",
    "sg:phone":"+34 971 55 39 00",
    "sg:postcode":"07500",
    "sg:province":"Islas Baleares",
    "wof:name":"Puntsol S.l.",
    "wof:placetype":"venue"
},
  "geometry": {"coordinates":[3.227793932,39.5640945435],"type":"Point"}
}