{
  "type": "Feature",
  "properties": {
    "iso:country":"ES",
    "sg:address":"Avda Marin (de), 33",
    "sg:city":"Ourense",
    "sg:orig_category":"Bebidas",
    "sg:phone":"+34 988 21 55 54",
    "sg:postcode":"32001",
    "sg:province":"Ourense",
    "wof:name":"Begano S.a.",
    "wof:placetype":"venue"
},
  "geometry": {"coordinates":[-7.8707470894,42.349521637],"type":"Point"}
}