{
  "type": "Feature",
  "properties": {
    "iso:country":"ES",
    "sg:address":"Calle de Libertad, 64",
    "sg:city":"Tias",
    "sg:orig_category":"Inmobiliaria (agencias)",
    "sg:phone":"+34 928 52 43 88",
    "sg:postcode":"35572",
    "sg:province":"Las Palmas",
    "wof:name":"Vargas Pe\u00f1aranda Sonia",
    "wof:placetype":"venue"
},
  "geometry": {"coordinates":[-13.6536912918,28.9496021271],"type":"Point"}
}