{
  "type": "Feature",
  "properties": {
    "iso:country":"ES",
    "sg:address":"Avda Calvo Sotelo, 1",
    "sg:city":"Plasencia",
    "sg:orig_category":"Sociedades, Compa\u00d1\u00cdas Aseguradoras",
    "sg:phone":"+34 927 42 10 13",
    "sg:postcode":"10600",
    "sg:province":"C\u00e1ceres",
    "sg:website":"www.dkvseguros.com",
    "wof:name":"Dkv Seguros Y Reaseguros Sae",
    "wof:placetype":"venue"
},
  "geometry": {"coordinates":[-6.0928449631,40.0270462036],"type":"Point"}
}