{
  "type": "Feature",
  "properties": {
    "iso:country":"ES",
    "sg:address":"Calle de Gran Via, 10",
    "sg:city":"Madrid",
    "sg:orig_category":"Perfumer\u00cda (al Por Menor)",
    "sg:phone":"+34 915 31 32 32",
    "sg:postcode":"28013",
    "sg:province":"Madrid",
    "wof:name":"Garcia Perez Rosa Maria",
    "wof:placetype":"venue"
},
  "geometry": {"coordinates":[-3.6986117363,40.419418335],"type":"Point"}
}