{
  "type": "Feature",
  "properties": {
    "addr:full":"Calle de San Sisenando, 7 Badajoz Badajoz 06002",
    "addr:housenumber":"7",
    "addr:postcode":"06002",
    "addr:street":"Calle De San Sisenando",
    "iso:country":"ES",
    "sg:address":"Calle de San Sisenando, 7",
    "sg:city":"Badajoz",
    "sg:orig_category":"Pescader\u00cdas (al Por Menor)",
    "sg:phone":"+34 924 22 34 33",
    "sg:postcode":"06002",
    "sg:province":"Badajoz",
    "wof:name":"Monge Perez Maria Jose",
    "wof:placetype":"venue"
},
  "geometry": {"coordinates":[-6.9694542885,38.8763618469],"type":"Point"}
}