{
  "type": "Feature",
  "properties": {
    "addr:full":"Avda Playas (las), 103 Puerto Del Carmen Las Palmas 35510",
    "addr:housenumber":"103",
    "addr:postcode":"35510",
    "addr:street":"Avda Playas Las",
    "iso:country":"ES",
    "sg:address":"Avda Playas (las), 103",
    "sg:city":"Puerto Del Carmen",
    "sg:orig_category":"Alquiler De Veh\u00cdculos: Turismos Y Utilitarios",
    "sg:phone":"+34 928 51 08 92",
    "sg:postcode":"35510",
    "sg:province":"Las Palmas",
    "wof:name":"Felycar Canarias S.l.",
    "wof:placetype":"venue"
},
  "geometry": {"coordinates":[-13.6543092728,28.9192905426],"type":"Point"}
}