{
  "type": "Feature",
  "properties": {
    "iso:country":"ES",
    "sg:address":"Calle de Montevideo, 11",
    "sg:city":"Palmas De Gran Canaria",
    "sg:orig_category":"Ropa Para Se\u00d1oras Y Caballeros (al Por Menor)",
    "sg:phone":"+34 928 22 32 67",
    "sg:postcode":"35007",
    "sg:province":"Las Palmas",
    "wof:name":"Cool",
    "wof:placetype":"venue"
},
  "geometry": {"coordinates":[-15.4302892685,28.136220932],"type":"Point"}
}