{
  "type": "Feature",
  "properties": {
    "addr:full":"Calle de Gaspar Torrente (santa Isabel), 7 Zaragoza Zaragoza 50016",
    "addr:housenumber":"7",
    "addr:postcode":"50016",
    "addr:street":"Calle De Gaspar Torrente Santa Isabel",
    "iso:country":"ES",
    "sg:address":"Calle de Gaspar Torrente (santa Isabel), 7",
    "sg:city":"Zaragoza",
    "sg:orig_category":"Venta, Instalaci\u00d3n De Calefacci\u00d3n",
    "sg:phone":"+34 976 57 37 08",
    "sg:postcode":"50016",
    "sg:province":"Zaragoza",
    "wof:name":"Galvez Aguado Angel",
    "wof:placetype":"venue"
},
  "geometry": {"coordinates":[-0.8279839754,41.6687889099],"type":"Point"}
}