{
  "type": "Feature",
  "properties": {
    "iso:country":"ES",
    "sg:address":"Carrer de Doctor Aiguader, 2",
    "sg:city":"Barcelona",
    "sg:orig_category":"Cajas De Ahorro",
    "sg:phone":"+34 933 10 33 75",
    "sg:postcode":"08003",
    "sg:province":"Barcelona",
    "sg:website":"www.caixasabadell.es",
    "wof:name":"Caixa D'estalvis Sabadell",
    "wof:placetype":"venue"
},
  "geometry": {"coordinates":[2.1945290565,41.3858985901],"type":"Point"}
}