{
  "type": "Feature",
  "properties": {
    "iso:country":"ES",
    "sg:address":"Plaz Almu\u00d1ecar, 10",
    "sg:city":"Madrid",
    "sg:orig_category":"Panader\u00cdas, Panader\u00cdas",
    "sg:phone":"+34 915 47 27 32",
    "sg:postcode":"28008",
    "sg:province":"Madrid",
    "wof:name":"Cageao Villar Manuel",
    "wof:placetype":"venue"
},
  "geometry": {"coordinates":[-3.7294490337,40.4282875061],"type":"Point"}
}