{
  "type": "Feature",
  "properties": {
    "addr:full":"Calle de Francisco Perez Y Vacas, 25 Bollullos Par Condado Huelva 21710",
    "addr:housenumber":"25",
    "addr:postcode":"21710",
    "addr:street":"Calle De Francisco Perez Y Vacas",
    "iso:country":"ES",
    "sg:address":"Calle de Francisco Perez Y Vacas, 25",
    "sg:city":"Bollullos Par Condado",
    "sg:orig_category":"Caf\u00c9s, Bares, Cervecer\u00cdas",
    "sg:phone":"+34 959 40 85 98",
    "sg:postcode":"21710",
    "sg:province":"Huelva",
    "wof:name":"Arias Santos Manuel Jesus",
    "wof:placetype":"venue"
},
  "geometry": {"coordinates":[-6.5249757767,37.3204689026],"type":"Point"}
}