{
  "type": "Feature",
  "properties": {
    "iso:country":"ES",
    "sg:address":"Rbla Badal, 17",
    "sg:city":"Barcelona",
    "sg:orig_category":"Remolques, Carretillas De Mano Para Operaciones Portuarias",
    "sg:phone":"+34 934 21 20 21",
    "sg:postcode":"08014",
    "sg:province":"Barcelona",
    "wof:name":"Sedima S.a.",
    "wof:placetype":"venue"
},
  "geometry": {"coordinates":[2.1343040466,41.3661575317],"type":"Point"}
}