{
  "type": "Feature",
  "properties": {
    "addr:full":"Carrer de Rossello, 473 Barcelona Barcelona 08025",
    "addr:housenumber":"473",
    "addr:postcode":"08025",
    "addr:street":"Carrer De Rossello",
    "iso:country":"ES",
    "sg:address":"Carrer de Rossello, 473",
    "sg:city":"Barcelona",
    "sg:orig_category":"Peluqueros: De Se\u00d1oras",
    "sg:phone":"+34 934 36 43 23",
    "sg:postcode":"08025",
    "sg:province":"Barcelona",
    "wof:name":"Tugas Vilaltella Angela",
    "wof:placetype":"venue"
},
  "geometry": {"coordinates":[2.1752550602,41.4069709778],"type":"Point"}
}