{
  "type": "Feature",
  "properties": {
    "iso:country":"ES",
    "sg:address":"Avda Rio Guadarrama, 26",
    "sg:city":"Poligono Sta M. De Benquerencia",
    "sg:orig_category":"Alquiler De V\u00cddeo",
    "sg:phone":"+34 925 23 19 45",
    "sg:postcode":"45007",
    "sg:province":"Toledo",
    "wof:name":"Garcia Ramirez Alfonsa",
    "wof:placetype":"venue"
},
  "geometry": {"coordinates":[-3.9442191124,39.8644599915],"type":"Point"}
}