{
  "type": "Feature",
  "properties": {
    "iso:country":"ES",
    "sg:address":"Ctra Ronda (de), 11",
    "sg:city":"Almeria",
    "sg:orig_category":"Arquitectos",
    "sg:phone":"+34 950 25 18 88",
    "sg:postcode":"04004",
    "sg:province":"Almer\u00eda",
    "wof:name":"Ortiz Gacto Antonio",
    "wof:placetype":"venue"
},
  "geometry": {"coordinates":[-2.4612190723,36.8336257935],"type":"Point"}
}