{
  "type": "Feature",
  "properties": {
    "iso:country":"ES",
    "sg:address":"Calle de Estacion, 5",
    "sg:city":"San Juan De Muskiz",
    "sg:orig_category":"Carnicer\u00cdas, Carnicer\u00cdas",
    "sg:phone":"+34 946 70 78 75",
    "sg:postcode":"48550",
    "sg:province":"Vizcaya",
    "wof:name":"Ruiz Arostegui Julian",
    "wof:placetype":"venue"
},
  "geometry": {"coordinates":[-3.1134688854,43.3224449158],"type":"Point"}
}