{
  "type": "Feature",
  "properties": {
    "iso:country":"ES",
    "sg:address":"Avda Navarra, 6",
    "sg:city":"Aldeanueva Ebro",
    "sg:orig_category":"Reposter\u00cdas",
    "sg:phone":"+34 941 16 31 29",
    "sg:postcode":"26559",
    "sg:province":"La Rioja",
    "wof:name":"Siguenza Lopez Javier",
    "wof:placetype":"venue"
},
  "geometry": {"coordinates":[-1.8865339756,42.2291221619],"type":"Point"}
}