{
  "type": "Feature",
  "properties": {
    "iso:country":"ES",
    "sg:address":"Avda Primero De Mayo, 11",
    "sg:city":"Puertollano",
    "sg:orig_category":"Abogados",
    "sg:phone":"+34 926 43 01 55",
    "sg:postcode":"13500",
    "sg:province":"Ciudad Real",
    "wof:name":"Fernandez Gonzalez Miguel Angel",
    "wof:placetype":"venue"
},
  "geometry": {"coordinates":[-4.1057729721,38.686126709],"type":"Point"}
}