{
  "type": "Feature",
  "properties": {
    "addr:full":"Gta Jose Ramon Arana (santa Isabel), 11 Zaragoza Zaragoza 50016",
    "addr:housenumber":"11",
    "addr:postcode":"50016",
    "addr:street":"Jose Ramon Arana Santa Isabel",
    "iso:country":"ES",
    "sg:address":"Gta Jose Ramon Arana (santa Isabel), 11",
    "sg:city":"Zaragoza",
    "sg:orig_category":"Talleres De Corte Y Confecci\u00d3n",
    "sg:phone":"+34 976 57 10 05",
    "sg:postcode":"50016",
    "sg:province":"Zaragoza",
    "wof:name":"Marqueta Gimeno Francisco Javier",
    "wof:placetype":"venue"
},
  "geometry": {"coordinates":[-0.8234919906,41.6667442322],"type":"Point"}
}