{
  "type": "Feature",
  "properties": {
    "iso:country":"ES",
    "sg:address":"Calle de Infanta Cristina, 8",
    "sg:city":"Vista Alegre",
    "sg:orig_category":"Inform\u00c1tica Equipo Y Programas (al Por Mayor)",
    "sg:phone":"+34 968 20 07 42",
    "sg:postcode":"30007",
    "sg:province":"Murcia",
    "wof:name":"Inhis 3000 S.l.",
    "wof:placetype":"venue"
},
  "geometry": {"coordinates":[-1.1142389774,37.9970092773],"type":"Point"}
}