{
  "type": "Feature",
  "properties": {
    "addr:full":"Trujillo, 37 Miajadas C\u00e1ceres 10100",
    "addr:housenumber":"37",
    "addr:postcode":"10100",
    "addr:street":"Trujillo;Ca\u0301Ceres",
    "iso:country":"ES",
    "sg:address":"Trujillo, 37",
    "sg:city":"Miajadas",
    "sg:orig_category":"Asociaciones Y Clubs Deportivos",
    "sg:phone":"+34 927 16 03 74",
    "sg:postcode":"10100",
    "sg:province":"C\u00e1ceres",
    "wof:name":"Ucles Diaz Jose Luis",
    "wof:placetype":"venue"
},
  "geometry": {"coordinates":[-5.9057340622,39.1525726318],"type":"Point"}
}