{
  "type": "Feature",
  "properties": {
    "addr:full":"Avda Plutarco, 61 Malaga M\u00e1laga 29010",
    "addr:housenumber":"61",
    "addr:postcode":"29010",
    "addr:street":"Avda Plutarco;Ma\u0301Laga",
    "iso:country":"ES",
    "sg:address":"Avda Plutarco, 61",
    "sg:city":"Malaga",
    "sg:orig_category":"Asilos De Ancianos. Centros Privados",
    "sg:phone":"+34 952 62 99 40",
    "sg:postcode":"29010",
    "sg:province":"M\u00e1laga",
    "sg:website":"www.malaga.ballesol.es",
    "wof:name":"Intercentros Ballesol S.a.",
    "wof:placetype":"venue"
},
  "geometry": {"coordinates":[-4.4728488922,36.7208099365],"type":"Point"}
}