{
  "type": "Feature",
  "properties": {
    "addr:full":"Calle de Almagro, 11 Bola\u00e7os De Calatrava Ciudad Real 13260",
    "addr:housenumber":"11",
    "addr:postcode":"13260",
    "addr:street":"Calle De Almagro",
    "iso:country":"ES",
    "sg:address":"Calle de Almagro, 11",
    "sg:city":"Bola\u00e7os De Calatrava",
    "sg:orig_category":"Agencias De Viajes",
    "sg:phone":"+34 926 87 17 22",
    "sg:postcode":"13260",
    "sg:province":"Ciudad Real",
    "wof:name":"De Toro Gomez Maria Angeles",
    "wof:placetype":"venue"
},
  "geometry": {"coordinates":[-3.9272627831,38.9860954285],"type":"Point"}
}