{
  "type": "Feature",
  "properties": {
    "addr:full":"Carrer de Mairo, 28 Roses Girona 17480",
    "addr:housenumber":"28",
    "addr:postcode":"17480",
    "addr:street":"Carrer De Mairo",
    "iso:country":"ES",
    "sg:address":"Carrer de Mairo, 28",
    "sg:city":"Roses",
    "sg:orig_category":"Zapatos (al Por Menor)",
    "sg:phone":"+34 972 25 32 56",
    "sg:postcode":"17480",
    "sg:province":"Girona",
    "wof:name":"Font Moradell Maria Asuncion",
    "wof:placetype":"venue"
},
  "geometry": {"coordinates":[3.1770129204,42.2618980408],"type":"Point"}
}