{
  "type": "Feature",
  "properties": {
    "addr:full":"Circunvalacion, 2 Granada Granada 18...",
    "addr:housenumber":"2;18 ...",
    "addr:street":"Circunvalacion;Granada",
    "iso:country":"ES",
    "sg:address":"Circunvalacion, 2",
    "sg:city":"Granada",
    "sg:orig_category":"Bancos",
    "sg:phone":"+34 958 24 24 42",
    "sg:postcode":"18...",
    "sg:province":"Granada",
    "wof:name":"Caja Rural De Granada",
    "wof:placetype":"venue"
},
  "geometry": {"coordinates":[-3.6240649223,37.1825141907],"type":"Point"}
}