{
  "type": "Feature",
  "properties": {
    "addr:full":"Calle de Almaden, 12 Madrid Madrid 28014",
    "addr:housenumber":"12",
    "addr:postcode":"madrid;28014",
    "addr:street":"Calle De Almaden",
    "iso:country":"ES",
    "sg:address":"Calle de Almaden, 12",
    "sg:city":"Madrid",
    "sg:classifiers":[
        {
            "category":"Arts & Performance",
            "subcategory":"Art Gallery",
            "type":"Entertainment"
        }
    ],
    "sg:phone":"+34 915 30 72 37",
    "sg:postcode":"28014",
    "sg:province":"Madrid",
    "sg:tags":[
        "arte",
        "de",
        "galer\u00cdas"
    ],
    "sg:website":"www.mynameslolita.com",
    "wof:name":"Garcia Alcaraz Ramon",
    "wof:placetype":"venue"
},
  "geometry": {"coordinates":[-3.6948065758,40.4111022949],"type":"Point"}
}