{
  "type": "Feature",
  "properties": {
    "iso:country":"ES",
    "sg:address":"Trios Sobrado, S/n",
    "sg:city":"Trios",
    "sg:orig_category":"Asesor\u00cda Sobre Comunicaci\u00d3n De Empresas",
    "sg:phone":"+34 988 26 41 61",
    "sg:postcode":"32793",
    "sg:province":"Ourense",
    "wof:name":"Inter Correspondencia S.a.",
    "wof:placetype":"venue"
},
  "geometry": {"coordinates":[-7.734662056,42.3320808411],"type":"Point"}
}