{
  "type": "Feature",
  "properties": {
    "iso:country":"ES",
    "sg:address":"Calle de Coronel Lopez Pe\u00d1a, 21",
    "sg:city":"Santiago Ribera",
    "sg:orig_category":"Promotores Constructores",
    "sg:phone":"+34 968 57 00 21",
    "sg:postcode":"30720",
    "sg:province":"Murcia",
    "wof:name":"Canalizaciones Del Sureste S.l.",
    "wof:placetype":"venue"
},
  "geometry": {"coordinates":[-0.8096339703,37.7969436646],"type":"Point"}
}