{
  "type": "Feature",
  "properties": {
    "addr:full":"Cra. Vilanova, Km. 0004,7 S. Pere Ribes Barcelona 08810",
    "addr:postcode":"08810",
    "addr:street":"Vilanova Km. 0004,7 S. Pere Ribes Barcelona",
    "iso:country":"ES",
    "sg:address":"Cra. Vilanova, Km. 0004,7",
    "sg:city":"S. Pere Ribes",
    "sg:orig_category":"Promotores Constructores",
    "sg:phone":"+34 938 96 40 60",
    "sg:postcode":"08810",
    "sg:province":"Barcelona",
    "wof:name":"Mediaciones Y Adquisiciones S.l.",
    "wof:placetype":"venue"
},
  "geometry": {"coordinates":[1.7786979675,41.2564849854],"type":"Point"}
}