{
  "type": "Feature",
  "properties": {
    "iso:country":"ES",
    "sg:address":"Calle de Reyes, 3",
    "sg:city":"Valladolid",
    "sg:orig_category":"Internados & Ense\u00d1anza Privada",
    "sg:phone":"+34 983 39 24 56",
    "sg:postcode":"47002",
    "sg:province":"Valladolid",
    "wof:name":"Instituto Secular De Derecho Diocesano Cruzados De Santa Maria",
    "wof:placetype":"venue"
},
  "geometry": {"coordinates":[-4.7185578346,41.6515769958],"type":"Point"}
}