{
  "type": "Feature",
  "properties": {
    "iso:country":"ES",
    "sg:address":"Pase Real De La Feria, 35",
    "sg:city":"Alcazares",
    "sg:orig_category":"Controles De Edificaci\u00d3n (construcci\u00d3n, Seguridad)",
    "sg:phone":"+34 968 17 19 11",
    "sg:postcode":"30710",
    "sg:province":"Murcia",
    "sg:website":"www.habtibac.com",
    "wof:name":"Abity Inmuebles S.a.",
    "wof:placetype":"venue"
},
  "geometry": {"coordinates":[-1.129887,37.983475],"type":"Point"}
}