{
  "type": "Feature",
  "properties": {
    "addr:full":"Cmno Piedra (de La), 19 Alcantarilla Murcia 30820",
    "addr:housenumber":"19",
    "addr:postcode":"30820",
    "addr:street":"Cmno Piedra De La",
    "iso:country":"ES",
    "sg:address":"Cmno Piedra (de La), 19",
    "sg:city":"Alcantarilla",
    "sg:orig_category":"Mec\u00c1nico Del Autom\u00d3vil",
    "sg:phone":"+34 968 89 24 06",
    "sg:postcode":"30820",
    "sg:province":"Murcia",
    "wof:name":"Tormos Martinez Mateo",
    "wof:placetype":"venue"
},
  "geometry": {"coordinates":[-1.2159739733,37.9685440063],"type":"Point"}
}