{
  "type": "Feature",
  "properties": {
    "addr:full":"Plaz Primero De Mayo, 5 Melilla Melilla 52003",
    "addr:housenumber":"5",
    "addr:postcode":"52003",
    "addr:street":"Plaz Primero;Mayo",
    "iso:country":"ES",
    "sg:address":"Plaz Primero De Mayo, 5",
    "sg:city":"Melilla",
    "sg:orig_category":"Papeler\u00cdas, Librer\u00cdas",
    "sg:phone":"+34 952 68 10 60",
    "sg:postcode":"52003",
    "sg:province":"Melilla",
    "wof:name":"Papeleria Eva Y Otros Cdad",
    "wof:placetype":"venue"
},
  "geometry": {"coordinates":[-2.955919981,35.3033714294],"type":"Point"}
}