{
  "type": "Feature",
  "properties": {
    "addr:full":"Carrer de Bertran, 109 Barcelona Barcelona 08023",
    "addr:housenumber":"109",
    "addr:postcode":"08023",
    "addr:street":"Carrer De Bertran",
    "iso:country":"ES",
    "sg:address":"Carrer de Bertran, 109",
    "sg:city":"Barcelona",
    "sg:orig_category":"M\u00c9dicos: Neurolog\u00cda",
    "sg:phone":"+34 934 18 50 96",
    "sg:postcode":"08023",
    "sg:province":"Barcelona",
    "wof:name":"Marquez Sanchez Julian",
    "wof:placetype":"venue"
},
  "geometry": {"coordinates":[2.1395750046,41.4093589783],"type":"Point"}
}