{
  "type": "Feature",
  "properties": {
    "iso:country":"ES",
    "sg:address":"Calle de Esposos Curie, 13",
    "sg:city":"Poligono Industrial Los Villares",
    "sg:orig_category":"Quincaller\u00cda (al Por Menor)",
    "sg:phone":"+34 923 23 56 26",
    "sg:postcode":"37184",
    "sg:province":"Salamanca",
    "wof:name":"Servi Villares S.l",
    "wof:placetype":"venue"
},
  "geometry": {"coordinates":[-5.6323590279,40.9936599731],"type":"Point"}
}