{
  "type": "Feature",
  "properties": {
    "addr:full":"Avda Complutense, S/n Madrid Madrid 28040",
    "addr:housenumber":"s / n",
    "addr:postcode":"28040",
    "addr:street":"Avda Complutense",
    "iso:country":"ES",
    "sg:address":"Avda Complutense, S/n",
    "sg:city":"Madrid",
    "sg:orig_category":"Librer\u00cdas",
    "sg:phone":"+34 915 44 18 05",
    "sg:postcode":"28040",
    "sg:province":"Madrid",
    "wof:name":"Fragua Libros S.l.",
    "wof:placetype":"venue"
},
  "geometry": {"coordinates":[-3.7250890732,40.4496536255],"type":"Point"}
}