{
  "type": "Feature",
  "properties": {
    "addr:full":"Avda Mediterraneo, 134 Teulada Alicante 03725",
    "addr:housenumber":"134",
    "addr:postcode":"03725",
    "addr:street":"Avda Mediterraneo",
    "iso:country":"ES",
    "sg:address":"Avda Mediterraneo, 134",
    "sg:city":"Teulada",
    "sg:orig_category":"Loter\u00cda Y T\u00d3mbola",
    "sg:phone":"+34 965 74 12 62",
    "sg:postcode":"03725",
    "sg:province":"Alicante",
    "wof:name":"Puig Andres Vicente",
    "wof:placetype":"venue"
},
  "geometry": {"coordinates":[0.1045660004,38.7270011902],"type":"Point"}
}