{
  "type": "Feature",
  "properties": {
    "addr:full":"Calle de Garci-nu\u00d1o, 31 Madrid Madrid 28029",
    "addr:housenumber":"31",
    "addr:postcode":"madrid;28029",
    "addr:street":"Calle De Garci-Nun\u0303O",
    "iso:country":"ES",
    "sg:address":"Calle de Garci-nu\u00d1o, 31",
    "sg:city":"Madrid",
    "sg:orig_category":"Farmacias",
    "sg:phone":"+34 913 15 10 27",
    "sg:postcode":"28029",
    "sg:province":"Madrid",
    "wof:name":"Miguel Y Jesus Buisan Catevilla C.b.",
    "wof:placetype":"venue"
},
  "geometry": {"coordinates":[-3.7005815506,40.4670715332],"type":"Point"}
}