{
  "type": "Feature",
  "properties": {
    "addr:full":"Calle de Torremegia, 2 Almendralejo Badajoz 06200",
    "addr:housenumber":"2",
    "addr:postcode":"06200",
    "addr:street":"Calle De Torremegia",
    "iso:country":"ES",
    "sg:address":"Calle de Torremegia, 2",
    "sg:city":"Almendralejo",
    "sg:orig_category":"Alquiler De Camiones Y Veh\u00cdculos Industriales",
    "sg:phone":"+34 924 66 03 09",
    "sg:postcode":"06200",
    "sg:province":"Badajoz",
    "wof:name":"Rosado Ortiz Antonio",
    "wof:placetype":"venue"
},
  "geometry": {"coordinates":[-6.4124240875,38.6861152649],"type":"Point"}
}