{
  "type": "Feature",
  "properties": {
    "addr:full":"Pase Alfonso Xiii, S/n Palma Rio C\u00f3rdoba 14700",
    "addr:housenumber":"s",
    "addr:postcode":"14700",
    "addr:street":"Alfonso Xiii;/ N Palma Rio Co\u0301Rdoba",
    "iso:country":"ES",
    "sg:address":"Pase Alfonso Xiii, S/n",
    "sg:city":"Palma Rio",
    "sg:orig_category":"Equipo Y Material Deportivo Y De Actividades Invernales Y De Monta\u00d1a",
    "sg:phone":"+34 957 64 51 13",
    "sg:postcode":"14700",
    "sg:province":"C\u00f3rdoba",
    "wof:name":"Patronato Deportivo Municipal",
    "wof:placetype":"venue"
},
  "geometry": {"coordinates":[-5.2828588486,37.6935195923],"type":"Point"}
}