{
  "type": "Feature",
  "properties": {
    "iso:country":"ES",
    "sg:address":"Calle de Esquivel, 1",
    "sg:city":"Puerto Cruz",
    "sg:orig_category":"Ropa Para Ni\u00d1os (al Por Menor)",
    "sg:phone":"+34 922 36 86 10",
    "sg:postcode":"38400",
    "sg:province":"Santa Cruz De Tenerife",
    "wof:name":"Veguer Rumbeu Sara Maria",
    "wof:placetype":"venue"
},
  "geometry": {"coordinates":[-16.5481739044,28.4166507721],"type":"Point"}
}