{
  "type": "Feature",
  "properties": {
    "addr:full":"Calle de Arquitecto Reguera, 13 Oviedo Asturias 33004",
    "addr:housenumber":"13",
    "addr:postcode":"33004",
    "addr:street":"Calle De Arquitecto Reguera",
    "iso:country":"ES",
    "sg:address":"Calle de Arquitecto Reguera, 13",
    "sg:city":"Oviedo",
    "sg:orig_category":"Empresarios",
    "sg:phone":"+34 985 24 34 00",
    "sg:postcode":"33004",
    "sg:province":"Asturias",
    "wof:name":"Fundacion Baures",
    "wof:placetype":"venue"
},
  "geometry": {"coordinates":[-5.8555560112,43.3647041321],"type":"Point"}
}