{
  "type": "Feature",
  "properties": {
    "iso:country":"ES",
    "sg:address":"Ctra Cazalla, Km. 0014,0",
    "sg:city":"Constantina",
    "sg:orig_category":"Cr\u00cda De Bovinos",
    "sg:phone":"+34 955 95 42 77",
    "sg:postcode":"41450",
    "sg:province":"Sevilla",
    "wof:name":"Agropecuaria La Nava S.a.t.",
    "wof:placetype":"venue"
},
  "geometry": {"coordinates":[-5.7649755478,37.8377609253],"type":"Point"}
}