{
  "type": "Feature",
  "properties": {
    "iso:country":"ES",
    "sg:address":"Comerciants I Botiguers, S/n",
    "sg:city":"Ciutadella Menorca",
    "sg:orig_category":"Mec\u00c1nico Del Autom\u00d3vil",
    "sg:phone":"+34 971 38 05 33",
    "sg:postcode":"07760",
    "sg:province":"Islas Baleares",
    "wof:name":"Autos Benejam S.l.",
    "wof:placetype":"venue"
},
  "geometry": {"coordinates":[3.8858954906,39.9778633118],"type":"Point"}
}