{
  "type": "Feature",
  "properties": {
    "addr:full":"Calle de Sacerdote Isidro Albert, 6 Alacant Alicante 03010",
    "addr:housenumber":"6",
    "addr:postcode":"03010",
    "addr:street":"Calle De Sacerdote Isidro Albert",
    "iso:country":"ES",
    "sg:address":"Calle de Sacerdote Isidro Albert, 6",
    "sg:city":"Alacant",
    "sg:orig_category":"Electricidad: Instaladores",
    "sg:phone":"+34 965 25 43 31",
    "sg:postcode":"03010",
    "sg:province":"Alicante",
    "wof:name":"Fem Llun C.b.",
    "wof:placetype":"venue"
},
  "geometry": {"coordinates":[-0.4867689908,38.3663711548],"type":"Point"}
}