{
  "type": "Feature",
  "properties": {
    "addr:full":"Ctra Yecla, S/n Pinoso Alicante 03650",
    "addr:housenumber":"s / n",
    "addr:postcode":"03650",
    "addr:street":"Ctra Yecla",
    "iso:country":"ES",
    "sg:address":"Ctra Yecla, S/n",
    "sg:city":"Pinoso",
    "sg:orig_category":"Muebles, Minoristas",
    "sg:phone":"+34 966 97 00 27",
    "sg:postcode":"03650",
    "sg:province":"Alicante",
    "wof:name":"Mobiliario Yeclano S.l.",
    "wof:placetype":"venue"
},
  "geometry": {"coordinates":[-1.0420939922,38.4015884399],"type":"Point"}
}