{
  "type": "Feature",
  "properties": {
    "iso:country":"ES",
    "sg:address":"Carr Barraquetes, 46",
    "sg:city":"Cassa Selva",
    "sg:orig_category":"Pescader\u00cdas (al Por Menor)",
    "sg:phone":"+34 972 46 03 87",
    "sg:postcode":"17244",
    "sg:province":"Girona",
    "wof:name":"Bou Pons Asuncion",
    "wof:placetype":"venue"
},
  "geometry": {"coordinates":[2.8783109188,41.8882026672],"type":"Point"}
}