{
  "type": "Feature",
  "properties": {
    "addr:full":"Vred Yeguas (de Las), 1 Arganda Madrid 28500",
    "addr:postcode":"28500",
    "addr:street":"Las;Arganda",
    "iso:country":"ES",
    "sg:address":"Vred Yeguas (de Las), 1",
    "sg:city":"Arganda",
    "sg:orig_category":"Molduras, Junquillos, Listones Y Molduras Perforadas",
    "sg:phone":"+34 918 71 22 66",
    "sg:postcode":"28500",
    "sg:province":"Madrid",
    "wof:name":"Estrella De Oriente S.l.",
    "wof:placetype":"venue"
},
  "geometry": {"coordinates":[-3.4406979084,40.2999954224],"type":"Point"}
}