{
  "type": "Feature",
  "properties": {
    "addr:full":"Calle de Mencey Beneharo, 42 Santa Cruz De Tenerife Santa Cruz De Tenerife 38008",
    "addr:housenumber":"42",
    "addr:postcode":"38008",
    "addr:street":"Calle De Mencey Beneharo",
    "iso:country":"ES",
    "sg:address":"Calle de Mencey Beneharo, 42",
    "sg:city":"Santa Cruz De Tenerife",
    "sg:orig_category":"Art\u00cdculos Funerarios (al Por Menor)",
    "sg:phone":"+34 922 20 33 86",
    "sg:postcode":"38008",
    "sg:province":"Santa Cruz De Tenerife",
    "wof:name":"Hernandez Baute Julio",
    "wof:placetype":"venue"
},
  "geometry": {"coordinates":[-16.2716178894,28.4702224731],"type":"Point"}
}