{
  "type": "Feature",
  "properties": {
    "addr:full":"Ctra Barcelona, 152 Cerdanyola Valles Barcelona 08290",
    "addr:housenumber":"152",
    "addr:postcode":"08290",
    "addr:street":"Ctra Barcelona;Valles Barcelona",
    "iso:country":"ES",
    "sg:address":"Ctra Barcelona, 152",
    "sg:city":"Cerdanyola Valles",
    "sg:orig_category":"Fotocopias, Reprograf\u00cda",
    "sg:phone":"+34 935 80 43 08",
    "sg:postcode":"08290",
    "sg:province":"Barcelona",
    "wof:name":"Copisteria Esal S.l.",
    "wof:placetype":"venue"
},
  "geometry": {"coordinates":[2.1478829384,41.4936828613],"type":"Point"}
}