{
  "type": "Feature",
  "properties": {
    "iso:country":"ES",
    "sg:address":"Avda Primero De Mayo, 28",
    "sg:city":"Puertollano",
    "sg:orig_category":"Cl\u00cdnicas Dentales",
    "sg:phone":"+34 926 42 86 49",
    "sg:postcode":"13500",
    "sg:province":"Ciudad Real",
    "wof:name":"Sanchez Estevez Carlos",
    "wof:placetype":"venue"
},
  "geometry": {"coordinates":[-4.1049609184,38.6864242554],"type":"Point"}
}