{
  "type": "Feature",
  "properties": {
    "addr:full":"Calle de Santa Brigida, 17 Majadahonda Madrid 28220",
    "addr:housenumber":"17",
    "addr:postcode":"28220",
    "addr:street":"Calle De Santa Brigida",
    "iso:country":"ES",
    "sg:address":"Calle de Santa Brigida, 17",
    "sg:city":"Majadahonda",
    "sg:orig_category":"Importaci\u00d3n",
    "sg:phone":"+34 916 38 87 11",
    "sg:postcode":"28220",
    "sg:province":"Madrid",
    "sg:website":"www.sistemastdm.com",
    "wof:name":"Sistemas T.d.m. S.a.",
    "wof:placetype":"venue"
},
  "geometry": {"coordinates":[-3.8644769192,40.4729423523],"type":"Point"}
}