{
  "type": "Feature",
  "properties": {
    "iso:country":"ES",
    "sg:address":"Calle de Buenavista, 24",
    "sg:city":"Rota",
    "sg:orig_category":"Empresas De Carpinter\u00cda De Madera",
    "sg:phone":"+34 956 84 02 57",
    "sg:postcode":"11520",
    "sg:province":"C\u00e1diz",
    "wof:name":"Nu\u00f1ez Pizones Juan Antonio",
    "wof:placetype":"venue"
},
  "geometry": {"coordinates":[-6.3580260277,36.6230125427],"type":"Point"}
}