{
  "type": "Feature",
  "properties": {
    "iso:country":"ES",
    "sg:address":"Calle de Esperanto, 7",
    "sg:city":"Benidorm",
    "sg:orig_category":"Supermercados Y Hipermercados",
    "sg:phone":"+34 965 85 72 66",
    "sg:postcode":"03500",
    "sg:province":"Alicante",
    "wof:name":"Evangelio Martinez Juan Felix",
    "wof:placetype":"venue"
},
  "geometry": {"coordinates":[-0.1247458979,38.5383605957],"type":"Point"}
}