{
  "type": "Feature",
  "properties": {
    "addr:full":"Avda Llano Del, 28 Gijon Asturias 33209",
    "addr:housenumber":"28",
    "addr:postcode":"33209",
    "addr:street":"Avda Llano Del",
    "iso:country":"ES",
    "sg:address":"Avda Llano Del, 28",
    "sg:city":"Gijon",
    "sg:orig_category":"Fabricaci\u00d3n De Sobres, Bolsas Y Fundas",
    "sg:phone":"+34 985 38 07 99",
    "sg:postcode":"33209",
    "sg:province":"Asturias",
    "wof:name":"Ronderos Alvarez Carmen Rosa",
    "wof:placetype":"venue"
},
  "geometry": {"coordinates":[-5.6603651047,43.53332901],"type":"Point"}
}