{
  "type": "Feature",
  "properties": {
    "addr:full":"Poligono Industrial Camposol, S/n Puente Tocinos Murcia 30006",
    "addr:housenumber":"s / n",
    "addr:postcode":"30006",
    "iso:country":"ES",
    "sg:address":"Poligono Industrial Camposol, S/n",
    "sg:city":"Puente Tocinos",
    "sg:orig_category":"Productos Qu\u00cdmicos (fabricaci\u00d3n, Al Por Mayor)",
    "sg:phone":"+34 968 23 38 10",
    "sg:postcode":"30006",
    "sg:province":"Murcia",
    "wof:name":"Quimursa Garcia Cavada S.l.",
    "wof:placetype":"venue"
},
  "geometry": {"coordinates":[-1.1008939743,37.9940185547],"type":"Point"}
}