{
  "type": "Feature",
  "properties": {
    "iso:country":"ES",
    "sg:address":"Carrer de Campins, 13",
    "sg:city":"Barcelona",
    "sg:orig_category":"Carnicer\u00cdas, Carnicer\u00cdas",
    "sg:phone":"+34 933 11 86 30",
    "sg:postcode":"08030",
    "sg:province":"Barcelona",
    "wof:name":"Fernandez Torres Deogracias",
    "wof:placetype":"venue"
},
  "geometry": {"coordinates":[2.198513031,41.4471626282],"type":"Point"}
}