{
  "type": "Feature",
  "properties": {
    "iso:country":"ES",
    "sg:address":"Avda Rufo G Rendueles, 16",
    "sg:city":"Gijon",
    "sg:orig_category":"Papeler\u00cdas: Art\u00cdculos (al Por Mayor)",
    "sg:phone":"+34 985 33 68 08",
    "sg:postcode":"33203",
    "sg:province":"Asturias",
    "wof:name":"Industrias Envasa Y Exclusivas Marte S.a.",
    "wof:placetype":"venue"
},
  "geometry": {"coordinates":[-5.6475849152,43.5399932861],"type":"Point"}
}