{
  "type": "Feature",
  "properties": {
    "addr:full":"Avda Reina Sofia, 17 Leganes Madrid 28919",
    "addr:housenumber":"17",
    "addr:postcode":"28919",
    "addr:street":"Avda Reina Sofia",
    "iso:country":"ES",
    "sg:address":"Avda Reina Sofia, 17",
    "sg:city":"Leganes",
    "sg:orig_category":"Parafarmacias",
    "sg:phone":"+34 914 81 58 35",
    "sg:postcode":"28919",
    "sg:province":"Madrid",
    "wof:name":"Farmazul S.l.",
    "wof:placetype":"venue"
},
  "geometry": {"coordinates":[-3.7503890991,40.3428459167],"type":"Point"}
}