{
  "type": "Feature",
  "properties": {
    "iso:country":"ES",
    "sg:address":"Carr Manuel Fdez Marquez, S/n",
    "sg:city":"Badalona",
    "sg:orig_category":"Inform\u00c1tica: Mantenimiento Y Reparaci\u00d3n De Ordenadores",
    "sg:phone":"+34 934 62 87 00",
    "sg:postcode":"08...",
    "sg:province":"Barcelona",
    "wof:name":"Metrolico S.a.",
    "wof:placetype":"venue"
},
  "geometry": {"coordinates":[2.2450649738,41.4503440857],"type":"Point"}
}