{
  "type": "Feature",
  "properties": {
    "addr:full":"Pl San Agatangelo, 12 Elche Alicante 03201",
    "addr:housenumber":"12",
    "addr:postcode":"03201",
    "addr:street":"Pl San Agatangelo",
    "iso:country":"ES",
    "sg:address":"Pl San Agatangelo, 12",
    "sg:city":"Elche",
    "sg:orig_category":"Centros Comerciales Y Grandes Tiendas",
    "sg:phone":"+34 965 45 33 47",
    "sg:postcode":"03201",
    "sg:province":"Alicante",
    "wof:name":"Gesaltabix S.l.",
    "wof:placetype":"venue"
},
  "geometry": {"coordinates":[-0.6951389909,38.2685241699],"type":"Point"}
}