{
  "type": "Feature",
  "properties": {
    "iso:country":"ES",
    "sg:address":"Rua Observatorio, 6",
    "sg:city":"Lalin",
    "sg:orig_category":"Ropa Para Ni\u00d1os (al Por Menor)",
    "sg:phone":"+34 986 78 13 42",
    "sg:postcode":"36500",
    "sg:province":"Pontevedra",
    "wof:name":"Diaz Calvi\u00f1o Susana",
    "wof:placetype":"venue"
},
  "geometry": {"coordinates":[-8.1131038666,42.6610908508],"type":"Point"}
}