{
  "type": "Feature",
  "properties": {
    "addr:full":"Carr Costa I Llobera, 31 Felanitx Islas Baleares 07200",
    "addr:housenumber":"31",
    "addr:postcode":"07200",
    "addr:street":"Carr Costa I Llobera",
    "iso:country":"ES",
    "sg:address":"Carr Costa I Llobera, 31",
    "sg:city":"Felanitx",
    "sg:orig_category":"Contenedores (mercanc\u00cdas)",
    "sg:phone":"+34 971 58 04 95",
    "sg:postcode":"07200",
    "sg:province":"Islas Baleares",
    "wof:name":"Veny Obrador Colau",
    "wof:placetype":"venue"
},
  "geometry": {"coordinates":[3.1523449421,39.4752311707],"type":"Point"}
}