{
  "type": "Feature",
  "properties": {
    "addr:full":"Ctra Albacete, S/n Madrigueras Albacete 02230",
    "addr:housenumber":"s / n",
    "addr:postcode":"02230",
    "addr:street":"Ctra Albacete",
    "iso:country":"ES",
    "sg:address":"Ctra Albacete, S/n",
    "sg:city":"Madrigueras",
    "sg:orig_category":"Cuchiller\u00cda (al Por Menor)",
    "sg:phone":"+34 967 48 41 18",
    "sg:postcode":"02230",
    "sg:province":"Albacete",
    "wof:name":"Martinez Y Gascon S. A.",
    "wof:placetype":"venue"
},
  "geometry": {"coordinates":[-1.801164031,39.2306365967],"type":"Point"}
}