{
  "type": "Feature",
  "properties": {
    "addr:full":"Carrer de Bisbe Morgades, 14 Vic Barcelona 08500",
    "addr:housenumber":"14",
    "addr:postcode":"08500",
    "addr:street":"Carrer De Bisbe Morgades",
    "iso:country":"ES",
    "sg:address":"Carrer de Bisbe Morgades, 14",
    "sg:city":"Vic",
    "sg:orig_category":"Muebles Y Accesorios Para Cocinas Y Cuartos De Ba\u00d1o (al Por Menor)",
    "sg:phone":"+34 938 85 03 44",
    "sg:postcode":"08500",
    "sg:province":"Barcelona",
    "wof:name":"Alvic Fr. Mobiliario S.l.",
    "wof:placetype":"venue"
},
  "geometry": {"coordinates":[2.251121521,41.9297294617],"type":"Point"}
}