{
  "type": "Feature",
  "properties": {
    "addr:full":"Campi\u00f1uelas, 44 Coin M\u00e1laga 29100",
    "addr:housenumber":"44",
    "addr:postcode":"29100",
    "addr:street":"Campin\u0303Uelas;Ma\u0301Laga",
    "iso:country":"ES",
    "sg:address":"Campi\u00f1uelas, 44",
    "sg:city":"Coin",
    "sg:orig_category":"Carnicer\u00cdas, Carnicer\u00cdas",
    "sg:phone":"+34 952 45 21 21",
    "sg:postcode":"29100",
    "sg:province":"M\u00e1laga",
    "wof:name":"Martin Guerrero Salvador",
    "wof:placetype":"venue"
},
  "geometry": {"coordinates":[-4.7429227829,36.6691322327],"type":"Point"}
}