{
  "type": "Feature",
  "properties": {
    "iso:country":"ES",
    "sg:address":"Calle de La Iglesia, 28",
    "sg:city":"Palomero",
    "sg:orig_category":"Iglesia Cat\u00d3lica",
    "sg:phone":"+34 927 67 33 56",
    "sg:postcode":"10660",
    "sg:province":"C\u00e1ceres",
    "wof:name":"Parroquia San Miguel Arcangel",
    "wof:placetype":"venue"
},
  "geometry": {"coordinates":[-6.275698185,40.2471542358],"type":"Point"}
}