{
  "type": "Feature",
  "properties": {
    "iso:country":"ES",
    "sg:address":"Calle de Iglesia La, S/n",
    "sg:city":"Nore\u00f1a",
    "sg:orig_category":"Internados & Ense\u00d1anza Privada",
    "sg:phone":"+34 985 74 03 03",
    "sg:postcode":"33180",
    "sg:province":"Asturias",
    "wof:name":"Hijas De Maria Madre De La Iglesia",
    "wof:placetype":"venue"
},
  "geometry": {"coordinates":[-5.708384037,43.3936080933],"type":"Point"}
}