{
  "type": "Feature",
  "properties": {
    "iso:country":"ES",
    "sg:address":"Calle de Foncalada, 34",
    "sg:city":"Oviedo",
    "sg:orig_category":"Asociaciones, Instituciones De Consumidores Y Usuarios",
    "sg:phone":"+34 901 50 10 50",
    "sg:postcode":"33002",
    "sg:province":"Asturias",
    "wof:name":"Union De Consumidores De Asturias",
    "wof:placetype":"venue"
},
  "geometry": {"coordinates":[-5.8459281921,43.3661804199],"type":"Point"}
}