{
  "type": "Feature",
  "properties": {
    "addr:full":"Av Retor Emilio Bayarri, 9 Alfinach Valencia 46530",
    "addr:housenumber":"9",
    "addr:postcode":"46530",
    "addr:street":"Av Retor Emilio Bayarri",
    "iso:country":"ES",
    "sg:address":"Av Retor Emilio Bayarri, 9",
    "sg:city":"Alfinach",
    "sg:orig_category":"Confecci\u00d3n (fabricaci\u00d3n, Al Por Mayor)",
    "sg:phone":"+34 961 40 55 28",
    "sg:postcode":"46530",
    "sg:province":"Valencia",
    "wof:name":"Miguel Arajez S.l.",
    "wof:placetype":"venue"
},
  "geometry": {"coordinates":[-0.3432669938,39.6309509277],"type":"Point"}
}