{
  "type": "Feature",
  "properties": {
    "addr:full":"Avda Somosierra (de), 24 San Sebastian De Los Reyes Madrid 28700",
    "addr:housenumber":"24",
    "addr:postcode":"28700",
    "addr:street":"Avda Somosierra De",
    "iso:country":"ES",
    "sg:address":"Avda Somosierra (de), 24",
    "sg:city":"San Sebastian De Los Reyes",
    "sg:orig_category":"Comit\u00c9s De Organizaci\u00d3n De Exposiciones, Ferias, Salones",
    "sg:phone":"+34 916 58 65 57",
    "sg:postcode":"28700",
    "sg:province":"Madrid",
    "sg:website":"www.evenirsl.com",
    "wof:name":"Evenir S.l",
    "wof:placetype":"venue"
},
  "geometry": {"coordinates":[-3.6154589653,40.5547180176],"type":"Point"}
}