{
  "type": "Feature",
  "properties": {
    "addr:full":"Ctra. Miranda Puentelarra, S/n Leci\u00f1ana Camino \u00c1lava 01213",
    "addr:housenumber":"s",
    "addr:postcode":"01213",
    "addr:street":"Ctra. Miranda Puentelarra;/ N;Camino A\u0301Lava",
    "iso:country":"ES",
    "sg:address":"Ctra. Miranda Puentelarra, S/n",
    "sg:city":"Leci\u00f1ana Camino",
    "sg:orig_category":"Cooperativas Agr\u00cdcolas",
    "sg:phone":"+34 945 33 21 59",
    "sg:postcode":"01213",
    "sg:province":"\u00c1lava",
    "wof:name":"Cooperativa Agricola Lantaron",
    "wof:placetype":"venue"
},
  "geometry": {"coordinates":[-2.9184379578,42.7114753723],"type":"Point"}
}