{
  "type": "Feature",
  "properties": {
    "iso:country":"ES",
    "sg:address":"Avda Andalucia, 7",
    "sg:city":"Salar",
    "sg:orig_category":"Agentes Generales De Seguros",
    "sg:phone":"+34 958 31 63 19",
    "sg:postcode":"18310",
    "sg:province":"Granada",
    "wof:name":"Fernandez Lopez Jose",
    "wof:placetype":"venue"
},
  "geometry": {"coordinates":[-4.0675802231,37.1498908997],"type":"Point"}
}