{
  "type": "Feature",
  "properties": {
    "addr:full":"Calle de Azorin, 8 Santa Pola Alicante 03130",
    "addr:housenumber":"8",
    "addr:postcode":"03130",
    "addr:street":"Calle De Azorin",
    "iso:country":"ES",
    "sg:address":"Calle de Azorin, 8",
    "sg:city":"Santa Pola",
    "sg:orig_category":"Artesan\u00cda",
    "sg:phone":"+34 966 69 47 73",
    "sg:postcode":"03130",
    "sg:province":"Alicante",
    "wof:name":"Grupo Vilumasa S.l.",
    "wof:placetype":"venue"
},
  "geometry": {"coordinates":[-0.5596762896,38.1973190308],"type":"Point"}
}