{
  "type": "Feature",
  "properties": {
    "addr:full":"Calle de Villa De Foz, 1 Laredo Cantabria 39770",
    "addr:housenumber":"1",
    "addr:postcode":"39770",
    "addr:street":"Calle De Villa De Foz",
    "iso:country":"ES",
    "sg:address":"Calle de Villa De Foz, 1",
    "sg:city":"Laredo",
    "sg:orig_category":"Fabricaci\u00d3n, Importaci\u00d3n, Venta De Material De Telefon\u00cda, Peritelefon\u00cda",
    "sg:phone":"+34 942 60 81 05",
    "sg:postcode":"39770",
    "sg:province":"Cantabria",
    "wof:name":"Orbital Telefonia Y Equipos S.l.",
    "wof:placetype":"venue"
},
  "geometry": {"coordinates":[-3.4142839909,43.4100646973],"type":"Point"}
}