{
  "type": "Feature",
  "properties": {
    "addr:full":"Calle de Triana, 63 Palmas De Gran Canaria Las Palmas 35002",
    "addr:housenumber":"63",
    "addr:postcode":"35002",
    "addr:street":"Calle De Triana",
    "iso:country":"ES",
    "sg:address":"Calle de Triana, 63",
    "sg:city":"Palmas De Gran Canaria",
    "sg:orig_category":"Confecci\u00d3n De Zapatos",
    "sg:phone":"+34 928 37 25 37",
    "sg:postcode":"35002",
    "sg:province":"Las Palmas",
    "wof:name":"Calzados Lurue\u00f1a S.l.",
    "wof:placetype":"venue"
},
  "geometry": {"coordinates":[-15.4161939621,28.1056194305],"type":"Point"}
}