{
  "type": "Feature",
  "properties": {
    "addr:full":"Carrer de Treball, 24 Hospitalet Llobregat Barcelona 08901",
    "addr:housenumber":"24",
    "addr:postcode":"08901",
    "addr:street":"Carrer De Treball",
    "iso:country":"ES",
    "sg:address":"Carrer de Treball, 24",
    "sg:city":"Hospitalet Llobregat",
    "sg:orig_category":"Asociaciones Y Clubs Deportivos",
    "sg:phone":"+34 933 37 92 91",
    "sg:postcode":"08901",
    "sg:province":"Barcelona",
    "wof:name":"Aloy Sitjes Jose",
    "wof:placetype":"venue"
},
  "geometry": {"coordinates":[2.1170284748,41.3673210144],"type":"Point"}
}