{
  "type": "Feature",
  "properties": {
    "iso:country":"ES",
    "sg:address":"Av Goles De L'ebre, 163",
    "sg:city":"Deltebre",
    "sg:orig_category":"Servicios Gsm",
    "sg:phone":"+34 977 48 23 93",
    "sg:postcode":"43580",
    "sg:province":"Tarragona",
    "wof:name":"Cabimas Delta Park S.l",
    "wof:placetype":"venue"
},
  "geometry": {"coordinates":[0.7334120274,40.7176742554],"type":"Point"}
}