{
  "type": "Feature",
  "properties": {
    "iso:country":"ES",
    "sg:address":"C/ Major, 57",
    "sg:city":"Puigcerda",
    "sg:orig_category":"Juegos Y Juguetes (al Por Menor)",
    "sg:phone":"+34 972 14 04 77",
    "sg:postcode":"17520",
    "sg:province":"Girona",
    "wof:name":"Adell Barnola Genoveva",
    "wof:placetype":"venue"
},
  "geometry": {"coordinates":[1.9257926941,42.4334983826],"type":"Point"}
}