{
  "type": "Feature",
  "properties": {
    "addr:full":"Lavadero, S/n Casillas Ranera Cuenca 16321",
    "addr:housenumber":"s / n",
    "addr:postcode":"16321",
    "iso:country":"ES",
    "sg:address":"Lavadero, S/n",
    "sg:city":"Casillas Ranera",
    "sg:orig_category":"Alimentaci\u00d3n General (al Por Mayor)",
    "sg:phone":"+34 969 36 60 09",
    "sg:postcode":"16321",
    "sg:province":"Cuenca",
    "wof:name":"Licomo S.l.",
    "wof:placetype":"venue"
},
  "geometry": {"coordinates":[-1.2688939571,39.7801818848],"type":"Point"}
}