{
  "type": "Feature",
  "properties": {
    "addr:full":"Carrer de Muntaner, 24 Barcelona Barcelona 08011",
    "addr:housenumber":"24",
    "addr:postcode":"08011",
    "addr:street":"Carrer De Muntaner",
    "iso:country":"ES",
    "sg:address":"Carrer de Muntaner, 24",
    "sg:city":"Barcelona",
    "sg:orig_category":"Empresarios Y Productoras De Espect\u00c1culos",
    "sg:phone":"+34 934 53 38 21",
    "sg:postcode":"08011",
    "sg:province":"Barcelona",
    "wof:name":"Pedro Bala\u00f1a S. A.",
    "wof:placetype":"venue"
},
  "geometry": {"coordinates":[2.1615250111,41.3852272034],"type":"Point"}
}