{
  "type": "Feature",
  "properties": {
    "addr:full":"Calle de Infante Don Fernando, 43 Antequera M\u00e1laga 29200",
    "addr:housenumber":"43",
    "addr:postcode":"29200",
    "addr:street":"Calle De Infante Don Fernando",
    "iso:country":"ES",
    "sg:address":"Calle de Infante Don Fernando, 43",
    "sg:city":"Antequera",
    "sg:orig_category":"Asociaciones Humanitarias, De Cooperaci\u00d3n, De Acci\u00d3n Social",
    "sg:phone":"+34 952 70 24 25",
    "sg:postcode":"29200",
    "sg:province":"M\u00e1laga",
    "wof:name":"Asociacion Espa\u00f1ola Contra El Cancer",
    "wof:placetype":"venue"
},
  "geometry": {"coordinates":[-4.5625152588,37.0190353394],"type":"Point"}
}