{
  "type": "Feature",
  "properties": {
    "addr:full":"Carrer de Brusi, 82 Barcelona Barcelona 08006",
    "addr:housenumber":"82",
    "addr:postcode":"08006",
    "addr:street":"Carrer De Brusi",
    "iso:country":"ES",
    "sg:address":"Carrer de Brusi, 82",
    "sg:city":"Barcelona",
    "sg:orig_category":"Agencias Y Agentes Comerciales, Representantes",
    "sg:phone":"+34 932 01 37 24",
    "sg:postcode":"08006",
    "sg:province":"Barcelona",
    "wof:name":"Malagarriga Amigo Francisco",
    "wof:placetype":"venue"
},
  "geometry": {"coordinates":[2.1454200745,41.401424408],"type":"Point"}
}