{
  "type": "Feature",
  "properties": {
    "iso:country":"ES",
    "sg:address":"Pase Imperial, 14",
    "sg:city":"Madrid",
    "sg:orig_category":"Inform\u00c1tica: Mantenimiento Y Reparaci\u00d3n De Ordenadores",
    "sg:phone":"+34 914 23 88 70",
    "sg:postcode":"28...",
    "sg:province":"Madrid",
    "sg:website":"www.diasa.es",
    "wof:name":"Diasa Informatica S.a.",
    "wof:placetype":"venue"
},
  "geometry": {"coordinates":[-3.7071740627,40.4146842957],"type":"Point"}
}