{
  "type": "Feature",
  "properties": {
    "iso:country":"ES",
    "sg:address":"Ctra. Lorca-baza, Km. 0070,0",
    "sg:city":"Albox",
    "sg:orig_category":"Distribuci\u00d3n De Petr\u00d3leo Y Derivados",
    "sg:phone":"+34 950 12 13 67",
    "sg:postcode":"04800",
    "sg:province":"Almer\u00eda",
    "wof:name":"Teodoro Gonzalez Ruiz S.l.",
    "wof:placetype":"venue"
},
  "geometry": {"coordinates":[-2.1415529251,37.4031028748],"type":"Point"}
}