{
  "type": "Feature",
  "properties": {
    "addr:full":"Calle de Charca Chica, S/n Moriscos Salamanca 37430",
    "addr:housenumber":"s / n",
    "addr:postcode":"37430",
    "addr:street":"Calle De Charca Chica",
    "iso:country":"ES",
    "sg:address":"Calle de Charca Chica, S/n",
    "sg:city":"Moriscos",
    "sg:orig_category":"Ebanister\u00cda",
    "sg:phone":"+34 923 36 14 41",
    "sg:postcode":"37430",
    "sg:province":"Salamanca",
    "wof:name":"Dominguez Barre\u00f1a Francisco Javier",
    "wof:placetype":"venue"
},
  "geometry": {"coordinates":[-5.5812096596,41.0081787109],"type":"Point"}
}