{
  "type": "Feature",
  "properties": {
    "iso:country":"ES",
    "sg:address":"Calle de Capitan Fillol, 26",
    "sg:city":"Valdepe\u00f1as",
    "sg:orig_category":"Empresas De Desmonte",
    "sg:phone":"+34 926 32 33 33",
    "sg:postcode":"13300",
    "sg:province":"Ciudad Real",
    "sg:website":"www.excavacionesytransportes.com",
    "wof:name":"Gonzalez Hochstein Luis",
    "wof:placetype":"venue"
},
  "geometry": {"coordinates":[-3.3897402287,38.7618370056],"type":"Point"}
}