{
  "type": "Feature",
  "properties": {
    "iso:country":"ES",
    "sg:address":"Calle de Fray Jose Casanova, 5",
    "sg:city":"Zaragoza",
    "sg:orig_category":"Artes Gr\u00c1ficas, Artes Pl\u00c1sticas (curso)",
    "sg:phone":"+34 976 33 42 99",
    "sg:postcode":"50010",
    "sg:province":"Zaragoza",
    "wof:name":"Guirao Martinez Alfonso",
    "wof:placetype":"venue"
},
  "geometry": {"coordinates":[-0.9042670727,41.6562614441],"type":"Point"}
}