{
  "type": "Feature",
  "properties": {
    "addr:full":"Carr Sant Antoni Maria Claret, 59 Ciutadella Menorca Islas Baleares 07760",
    "addr:housenumber":"59",
    "addr:postcode":"07760",
    "addr:street":"Carr Sant Antoni Maria Claret",
    "iso:country":"ES",
    "sg:address":"Carr Sant Antoni Maria Claret, 59",
    "sg:city":"Ciutadella Menorca",
    "sg:orig_category":"Plomeros",
    "sg:phone":"+34 971 38 41 55",
    "sg:postcode":"07760",
    "sg:province":"Islas Baleares",
    "wof:name":"Capo Salord Jose",
    "wof:placetype":"venue"
},
  "geometry": {"coordinates":[3.8435540199,40.0057106018],"type":"Point"}
}