{
  "type": "Feature",
  "properties": {
    "iso:country":"ES",
    "sg:address":"Calle de Virgen De Guadalupe, 7",
    "sg:city":"Zafra",
    "sg:orig_category":"M\u00c9dicos: Estomatolog\u00cda",
    "sg:phone":"+34 924 55 09 38",
    "sg:postcode":"06300",
    "sg:province":"Badajoz",
    "wof:name":"Ruiz Fernandez Santos",
    "wof:placetype":"venue"
},
  "geometry": {"coordinates":[-6.4129519463,38.4225578308],"type":"Point"}
}