{
  "type": "Feature",
  "properties": {
    "addr:full":"Carrer de Napols, 352 Barcelona Barcelona 08025",
    "addr:housenumber":"352",
    "addr:postcode":"08025",
    "addr:street":"Carrer De Napols",
    "iso:country":"ES",
    "sg:address":"Carrer de Napols, 352",
    "sg:city":"Barcelona",
    "sg:orig_category":"Alquiler De Veh\u00cdculos: Turismos Y Utilitarios",
    "sg:phone":"+34 934 59 14 96",
    "sg:postcode":"08025",
    "sg:province":"Barcelona",
    "wof:name":"Barbal Iranzo Juan Luis",
    "wof:placetype":"venue"
},
  "geometry": {"coordinates":[2.1658449173,41.4058570862],"type":"Point"}
}