{
  "type": "Feature",
  "properties": {
    "addr:full":"Calle de Quart, 104 Valencia Valencia 46008",
    "addr:housenumber":"104",
    "addr:postcode":"46008",
    "addr:street":"Calle De Quart",
    "iso:country":"ES",
    "sg:address":"Calle de Quart, 104",
    "sg:city":"Valencia",
    "sg:orig_category":"Fabricaci\u00d3n De Telas Y Sedas",
    "sg:phone":"+34 963 92 48 22",
    "sg:postcode":"46008",
    "sg:province":"Valencia",
    "wof:name":"Jose Soria Valiente Y Otros C.b.",
    "wof:placetype":"venue"
},
  "geometry": {"coordinates":[-0.3877040148,39.475315094],"type":"Point"}
}