{
  "type": "Feature",
  "properties": {
    "iso:country":"ES",
    "sg:address":"Calle de Olmo, 27",
    "sg:city":"Madrid",
    "sg:orig_category":"Equitaci\u00d3n: Guarnicioner\u00cda, Equipo (al Por Menor)",
    "sg:phone":"+34 915 30 84 31",
    "sg:postcode":"28012",
    "sg:province":"Madrid",
    "wof:name":"Mas Rodriguez Angel",
    "wof:placetype":"venue"
},
  "geometry": {"coordinates":[-3.7001619339,40.4116363525],"type":"Point"}
}