{
  "type": "Feature",
  "properties": {
    "iso:country":"ES",
    "sg:address":"Ptda Macaroves, S/n",
    "sg:city":"Relleu",
    "sg:orig_category":"Empresarios",
    "sg:phone":"+34 966 85 61 18",
    "sg:postcode":"03578",
    "sg:province":"Alicante",
    "wof:name":"Fundacion Aap",
    "wof:placetype":"venue"
},
  "geometry": {"coordinates":[-0.3288230002,38.5698165894],"type":"Point"}
}