{
  "type": "Feature",
  "properties": {
    "iso:country":"ES",
    "sg:address":"Pol Ind Cuesta La Vi\u00f1a, S/n",
    "sg:city":"Cartaya",
    "sg:orig_category":"Empresas De Limpieza",
    "sg:phone":"+34 959 39 22 39",
    "sg:postcode":"21450",
    "sg:province":"Huelva",
    "wof:name":"Cespa Compa\u00d1ia De Servicios Publicos Auxiliares S.a.",
    "wof:placetype":"venue"
},
  "geometry": {"coordinates":[-7.1528987885,37.2844581604],"type":"Point"}
}