{
  "type": "Feature",
  "properties": {
    "iso:country":"ES",
    "sg:address":"Rbla Llibertat, 3",
    "sg:city":"Girona",
    "sg:orig_category":"Ropa Para Se\u00d1oras Y Caballeros (al Por Menor)",
    "sg:phone":"+34 972 22 29 60",
    "sg:postcode":"17004",
    "sg:province":"Girona",
    "sg:website":"www.massimodutti.com",
    "wof:name":"Grupo Massimo Dutti S.a.",
    "wof:placetype":"venue"
},
  "geometry": {"coordinates":[2.8237500191,41.9834671021],"type":"Point"}
}