{
  "type": "Feature",
  "properties": {
    "addr:full":"Calle de Benito De Castro, 10 Madrid Madrid 28028",
    "addr:housenumber":"10",
    "addr:postcode":"madrid;28028",
    "addr:street":"Calle De Benito De Castro",
    "iso:country":"ES",
    "sg:address":"Calle de Benito De Castro, 10",
    "sg:city":"Madrid",
    "sg:orig_category":"Trabajos De Fotocomposici\u00d3n",
    "sg:phone":"+34 917 13 15 10",
    "sg:postcode":"28028",
    "sg:province":"Madrid",
    "wof:name":"Castro Glass S.l.",
    "wof:placetype":"venue"
},
  "geometry": {"coordinates":[-3.6676914692,40.4261360168],"type":"Point"}
}