{
  "type": "Feature",
  "properties": {
    "addr:full":"Calle de Republica Dominicana, 13 Palmas De Gran Canaria Las Palmas 35010",
    "addr:housenumber":"13",
    "addr:postcode":"35010",
    "addr:street":"Calle De Republica Dominicana",
    "iso:country":"ES",
    "sg:address":"Calle de Republica Dominicana, 13",
    "sg:city":"Palmas De Gran Canaria",
    "sg:orig_category":"Agencias Y Agentes Comerciales, Representantes",
    "sg:phone":"+34 928 27 78 91",
    "sg:postcode":"35010",
    "sg:province":"Las Palmas",
    "wof:name":"Suarez Y Morales Representaciones S.l.",
    "wof:placetype":"venue"
},
  "geometry": {"coordinates":[-15.4386892319,28.1329650879],"type":"Point"}
}