{
  "type": "Feature",
  "properties": {
    "iso:country":"ES",
    "sg:address":"Calle de Juan Bautista Del Mazo, 2",
    "sg:city":"Zaragoza",
    "sg:orig_category":"Empresas De Pintura Y Revestimientos",
    "sg:phone":"+34 976 44 44 08",
    "sg:postcode":"50003",
    "sg:province":"Zaragoza",
    "wof:name":"Carcas Tramullas Francisco Javier",
    "wof:placetype":"venue"
},
  "geometry": {"coordinates":[-0.9004240036,41.6603851318],"type":"Point"}
}