{
  "type": "Feature",
  "properties": {
    "iso:country":"ES",
    "sg:address":"Ctra San Vicente, 3",
    "sg:city":"Elguero",
    "sg:orig_category":"Pintura, Barniz, Productos Asimilables (fabricaci\u00d3n, Al Por Mayor)",
    "sg:phone":"+34 944 72 24 33",
    "sg:postcode":"48510",
    "sg:province":"Vizcaya",
    "wof:name":"Max Color 97 S. L.",
    "wof:placetype":"venue"
},
  "geometry": {"coordinates":[-3.0369338989,43.3047294617],"type":"Point"}
}