{
  "type": "Feature",
  "properties": {
    "addr:full":"Calle de Capitan Velarde, 2 Talavera Reina Toledo 45600",
    "addr:housenumber":"2",
    "addr:postcode":"45600",
    "addr:street":"Calle De Capitan Velarde",
    "iso:country":"ES",
    "sg:address":"Calle de Capitan Velarde, 2",
    "sg:city":"Talavera Reina",
    "sg:orig_category":"Abogados",
    "sg:phone":"+34 925 80 46 28",
    "sg:postcode":"45600",
    "sg:province":"Toledo",
    "wof:name":"Rosado Gonzalez Francisco Javier",
    "wof:placetype":"venue"
},
  "geometry": {"coordinates":[-4.8265328407,39.9632835388],"type":"Point"}
}