{
  "type": "Feature",
  "properties": {
    "iso:country":"ES",
    "sg:address":"Calle de Ramon Gomez De La Serna, 2",
    "sg:city":"Marbella",
    "sg:orig_category":"Vinos Y Licores (venta Al Por Menor)",
    "sg:phone":"+34 952 77 00 24",
    "sg:postcode":"29600",
    "sg:province":"M\u00e1laga",
    "wof:name":"Casa Pablo Vinos Y Licores S.l.",
    "wof:placetype":"venue"
},
  "geometry": {"coordinates":[-4.8932509422,36.5099182129],"type":"Point"}
}