{
  "type": "Feature",
  "properties": {
    "iso:country":"ES",
    "sg:address":"Avda Francisco Gonzalez Rey, S/n",
    "sg:city":"Celanova",
    "sg:orig_category":"T\u00c9cnicos Veterinarios",
    "sg:phone":"+34 988 43 13 25",
    "sg:postcode":"32800",
    "sg:province":"Ourense",
    "wof:name":"Xunta De Galicia",
    "wof:placetype":"venue"
},
  "geometry": {"coordinates":[-7.9865350723,42.1502799988],"type":"Point"}
}