{
  "type": "Feature",
  "properties": {
    "addr:full":"Carrer de Alcalde Joan Bertran, 13 Reus Tarragona 43202",
    "addr:housenumber":"13",
    "addr:postcode":"43202",
    "addr:street":"Carrer De Alcalde Joan Bertran",
    "iso:country":"ES",
    "sg:address":"Carrer de Alcalde Joan Bertran, 13",
    "sg:city":"Reus",
    "sg:orig_category":"Centros Empresariales",
    "sg:phone":"+34 977 32 30 13",
    "sg:postcode":"43202",
    "sg:province":"Tarragona",
    "wof:name":"Gremi De La Construccio Del Baix Camp",
    "wof:placetype":"venue"
},
  "geometry": {"coordinates":[1.1017010212,41.1507110596],"type":"Point"}
}