{
  "type": "Feature",
  "properties": {
    "iso:country":"ES",
    "sg:address":"Calle de San Agustin, 74",
    "sg:city":"San Agustin",
    "sg:orig_category":"Frutas Y Legumbres Frescas (al Por Mayor)",
    "sg:phone":"+34 922 34 24 86",
    "sg:postcode":"38410",
    "sg:province":"Santa Cruz De Tenerife",
    "wof:name":"Frutas De Calidad S.l.",
    "wof:placetype":"venue"
},
  "geometry": {"coordinates":[-16.5807914734,28.3678131104],"type":"Point"}
}