{
  "type": "Feature",
  "properties": {
    "iso:country":"ES",
    "sg:address":"Ctra. Nal. Iii, Km. 0276,0",
    "sg:city":"Requena",
    "sg:orig_category":"Distribuci\u00d3n De Petr\u00d3leo Y Derivados",
    "sg:phone":"+34 962 30 25 52",
    "sg:postcode":"46340",
    "sg:province":"Valencia",
    "wof:name":"Navarro Lopez Isabel",
    "wof:placetype":"venue"
},
  "geometry": {"coordinates":[-1.0998990536,39.4906158447],"type":"Point"}
}