{
  "type": "Feature",
  "properties": {
    "addr:full":"Carrer de Cartagena, 206 Barcelona Barcelona 08013",
    "addr:housenumber":"206",
    "addr:postcode":"08013",
    "addr:street":"Carrer De Cartagena",
    "iso:country":"ES",
    "sg:address":"Carrer de Cartagena, 206",
    "sg:city":"Barcelona",
    "sg:orig_category":"Loter\u00cda Y T\u00d3mbola",
    "sg:phone":"+34 932 46 01 58",
    "sg:postcode":"08013",
    "sg:province":"Barcelona",
    "wof:name":"Ripolles Gamell Luis",
    "wof:placetype":"venue"
},
  "geometry": {"coordinates":[2.1814110279,41.4060173035],"type":"Point"}
}