{
  "type": "Feature",
  "properties": {
    "iso:country":"ES",
    "sg:address":"Calle de Fermin Lasuen, 15",
    "sg:city":"Vitoria-gasteiz",
    "sg:orig_category":"Mec\u00c1nico Del Autom\u00d3vil",
    "sg:phone":"+34 945 28 29 39",
    "sg:postcode":"01013",
    "sg:province":"\u00c1lava",
    "wof:name":"Fermin Trujillo Sanchez",
    "wof:placetype":"venue"
},
  "geometry": {"coordinates":[-2.6686034203,42.8564910889],"type":"Point"}
}