{
  "type": "Feature",
  "properties": {
    "iso:country":"ES",
    "sg:address":"Ctra Nacional Ciento Veinticinco, Km. 0001,6",
    "sg:city":"Garrapinillos",
    "sg:orig_category":"Controles De Edificaci\u00d3n (construcci\u00d3n, Seguridad)",
    "sg:phone":"+34 876 25 10 54",
    "sg:postcode":"50190",
    "sg:province":"Zaragoza",
    "wof:name":"U. T. E. Plaza 1 Fase",
    "wof:placetype":"venue"
},
  "geometry": {"coordinates":[-1.0269140005,41.6842803955],"type":"Point"}
}