{
  "type": "Feature",
  "properties": {
    "addr:full":"Calle de Leon Xiii, 10 Zaragoza Zaragoza 50008",
    "addr:housenumber":"10",
    "addr:postcode":"50008",
    "addr:street":"Calle De Leon Xiii",
    "iso:country":"ES",
    "sg:address":"Calle de Leon Xiii, 10",
    "sg:city":"Zaragoza",
    "sg:orig_category":"M\u00c9dicos: Estomatolog\u00cda",
    "sg:phone":"+34 976 23 16 31",
    "sg:postcode":"50008",
    "sg:province":"Zaragoza",
    "wof:name":"Polo Blasco Jaime",
    "wof:placetype":"venue"
},
  "geometry": {"coordinates":[-0.8815770149,41.6463546753],"type":"Point"}
}