{
  "type": "Feature",
  "properties": {
    "iso:country":"ES",
    "sg:address":"Avda Andalucia, 49",
    "sg:city":"Aracena",
    "sg:orig_category":"Centros Empresariales",
    "sg:phone":"+34 959 12 61 29",
    "sg:postcode":"21200",
    "sg:province":"Huelva",
    "wof:name":"Federacion Onubense De Empresarios",
    "wof:placetype":"venue"
},
  "geometry": {"coordinates":[-6.5569839478,37.8908996582],"type":"Point"}
}