{
  "type": "Feature",
  "properties": {
    "addr:full":"A Torre, S/n Torre La Coru\u00f1a 15883",
    "addr:housenumber":"s / n",
    "addr:postcode":"15883",
    "addr:street":"La Corun\u0303A",
    "iso:country":"ES",
    "sg:address":"A Torre, S/n",
    "sg:city":"Torre",
    "sg:orig_category":"Grafistas",
    "sg:phone":"+34 981 80 68 29",
    "sg:postcode":"15883",
    "sg:province":"La Coru\u00f1a",
    "wof:name":"Icono Servicios Integrales S.c.",
    "wof:placetype":"venue"
},
  "geometry": {"coordinates":[-8.5444011688,42.8382263184],"type":"Point"}
}