{
  "type": "Feature",
  "properties": {
    "addr:full":"Carrer de Doctor Balari, 139 Sabadell Barcelona 08203",
    "addr:housenumber":"139",
    "addr:postcode":"08203",
    "addr:street":"Carrer De Doctor Balari",
    "iso:country":"ES",
    "sg:address":"Carrer de Doctor Balari, 139",
    "sg:city":"Sabadell",
    "sg:orig_category":"Panader\u00cdas, Panader\u00cdas",
    "sg:phone":"+34 937 10 01 46",
    "sg:postcode":"08203",
    "sg:province":"Barcelona",
    "wof:name":"Guardia Angles Jose",
    "wof:placetype":"venue"
},
  "geometry": {"coordinates":[2.1076490879,41.5321578979],"type":"Point"}
}