{
  "type": "Feature",
  "properties": {
    "iso:country":"ES",
    "sg:address":"Carr Industria, 451",
    "sg:city":"Badalona",
    "sg:orig_category":"Encuadernaci\u00d3n E Impresi\u00d3n De Folletos",
    "sg:phone":"+34 934 60 80 66",
    "sg:postcode":"08918",
    "sg:province":"Barcelona",
    "wof:name":"Hendigraf Acabats Grafics S.l.",
    "wof:placetype":"venue"
},
  "geometry": {"coordinates":[2.2364630699,41.4352149963],"type":"Point"}
}