{
  "type": "Feature",
  "properties": {
    "addr:full":"Parada De Amoeiro, 33 Parada Ourense 32170",
    "addr:housenumber":"33",
    "addr:postcode":"32170",
    "addr:street":"Amoeiro",
    "iso:country":"ES",
    "sg:address":"Parada De Amoeiro, 33",
    "sg:city":"Parada",
    "sg:orig_category":"Peluquer\u00cdas, Peluquer\u00cda Mixta",
    "sg:phone":"+34 988 27 97 12",
    "sg:postcode":"32170",
    "sg:province":"Ourense",
    "wof:name":"Rodriguez Otero Clara Isabel",
    "wof:placetype":"venue"
},
  "geometry": {"coordinates":[-7.9451670647,42.4144706726],"type":"Point"}
}