{
  "type": "Feature",
  "properties": {
    "addr:full":"Carrer de Camp De Les Moreres, 4 Granollers Barcelona 08401",
    "addr:housenumber":"4",
    "addr:postcode":"08401",
    "addr:street":"Carrer De Camp De Les Moreres",
    "iso:country":"ES",
    "sg:address":"Carrer de Camp De Les Moreres, 4",
    "sg:city":"Granollers",
    "sg:orig_category":"Peluqueros: De Se\u00d1oras",
    "sg:phone":"+34 938 79 41 91",
    "sg:postcode":"08401",
    "sg:province":"Barcelona",
    "wof:name":"Ruiz Benitez Montserrat",
    "wof:placetype":"venue"
},
  "geometry": {"coordinates":[2.2842888832,41.6006622314],"type":"Point"}
}