{
  "type": "Feature",
  "properties": {
    "iso:country":"ES",
    "sg:address":"Calle de Natalio Rivas, 38",
    "sg:city":"Adra",
    "sg:orig_category":"Ropa Para Ni\u00d1os (al Por Menor)",
    "sg:phone":"+34 950 56 05 76",
    "sg:postcode":"04770",
    "sg:province":"Almer\u00eda",
    "sg:website":"www.karlettin.com",
    "wof:name":"Salmeron Perez Rosario",
    "wof:placetype":"venue"
},
  "geometry": {"coordinates":[-3.0163888931,36.7485809326],"type":"Point"}
}