{
  "type": "Feature",
  "properties": {
    "addr:full":"Calle de Marques De Mirasol, 7 Talavera Reina Toledo 45600",
    "addr:housenumber":"7",
    "addr:postcode":"45600",
    "addr:street":"Calle De Marques De Mirasol",
    "iso:country":"ES",
    "sg:address":"Calle de Marques De Mirasol, 7",
    "sg:city":"Talavera Reina",
    "sg:orig_category":"Mutuas De Seguros",
    "sg:phone":"+34 925 80 01 50",
    "sg:postcode":"45600",
    "sg:province":"Toledo",
    "wof:name":"Mutua General Seguros",
    "wof:placetype":"venue"
},
  "geometry": {"coordinates":[-4.8336439133,39.9625091553],"type":"Point"}
}