{
  "type": "Feature",
  "properties": {
    "iso:country":"ES",
    "sg:address":"Calle de Alcalde Pascual Sanchez, 12",
    "sg:city":"Torre-pacheco",
    "sg:orig_category":"Centros Empresariales",
    "sg:phone":"+34 968 57 70 38",
    "sg:postcode":"30700",
    "sg:province":"Murcia",
    "wof:name":"Cavas Garcia Jose",
    "wof:placetype":"venue"
},
  "geometry": {"coordinates":[-0.9511265159,37.7362365723],"type":"Point"}
}