{
  "type": "Feature",
  "properties": {
    "addr:full":"Calle de Padre Isla, 40 Cistierna Le\u00f3n 24800",
    "addr:housenumber":"40",
    "addr:postcode":"24800",
    "addr:street":"Calle De Padre Isla;Leo\u0301N",
    "iso:country":"ES",
    "sg:address":"Calle de Padre Isla, 40",
    "sg:city":"Cistierna",
    "sg:orig_category":"Farmacias",
    "sg:phone":"+34 987 70 10 21",
    "sg:postcode":"24800",
    "sg:province":"Le\u00f3n",
    "wof:name":"Alvarez Gonzalez Maria Victoria",
    "wof:placetype":"venue"
},
  "geometry": {"coordinates":[-5.1286230087,42.8041267395],"type":"Point"}
}