{
  "type": "Feature",
  "properties": {
    "iso:country":"ES",
    "sg:address":"C/ Alfons Xii, 143",
    "sg:city":"Banyoles",
    "sg:orig_category":"Empresas De Electricidad En General",
    "sg:phone":"+34 972 57 03 14",
    "sg:postcode":"17820",
    "sg:province":"Girona",
    "wof:name":"Bassols Energia S.a.",
    "wof:placetype":"venue"
},
  "geometry": {"coordinates":[2.7633700371,42.1228790283],"type":"Point"}
}