{
  "type": "Feature",
  "properties": {
    "iso:country":"ES",
    "sg:address":"C/ Bisbe Tormo, 2",
    "sg:city":"Elche",
    "sg:orig_category":"Diarios, Prensa, Revistas (al Por Menor)",
    "sg:phone":"+34 965 45 38 04",
    "sg:postcode":"03202",
    "sg:province":"Alicante",
    "wof:name":"Editorial Prensa Alicantina Sau",
    "wof:placetype":"venue"
},
  "geometry": {"coordinates":[-0.6966869831,38.2660903931],"type":"Point"}
}