{
  "type": "Feature",
  "properties": {
    "addr:full":"Calle de San Jeronimo Hermosilla, 33 Santo Domingo De La Calzada La Rioja 26250",
    "addr:housenumber":"33",
    "addr:postcode":"26250",
    "addr:street":"Calle De San;Hermosilla;Rioja",
    "iso:country":"ES",
    "sg:address":"Calle de San Jeronimo Hermosilla, 33",
    "sg:city":"Santo Domingo De La Calzada",
    "sg:orig_category":"Bancos",
    "sg:phone":"+34 941 34 21 11",
    "sg:postcode":"26250",
    "sg:province":"La Rioja",
    "wof:name":"Banc Sabadell S.a.",
    "wof:placetype":"venue"
},
  "geometry": {"coordinates":[-2.9535219669,42.4379997253],"type":"Point"}
}