{
  "type": "Feature",
  "properties": {
    "addr:full":"Carrer de Mossen Jacint Verdaguer, 156 S. Boi Llobregat Barcelona 08830",
    "addr:housenumber":"156",
    "addr:postcode":"08830",
    "addr:street":"Carrer De Mossen Jacint Verdaguer;S.",
    "iso:country":"ES",
    "sg:address":"Carrer de Mossen Jacint Verdaguer, 156",
    "sg:city":"S. Boi Llobregat",
    "sg:orig_category":"Mec\u00c1nico Del Autom\u00d3vil",
    "sg:phone":"+34 936 30 03 58",
    "sg:postcode":"08830",
    "sg:province":"Barcelona",
    "wof:name":"Garcia Semipiel Rafael",
    "wof:placetype":"venue"
},
  "geometry": {"coordinates":[2.043076992,41.3385047913],"type":"Point"}
}