{
  "type": "Feature",
  "properties": {
    "iso:country":"ES",
    "sg:address":"Sierra De Santa Ana, 5",
    "sg:city":"San Javier",
    "sg:orig_category":"Promotores Constructores",
    "sg:phone":"+34 968 19 22 97",
    "sg:postcode":"30730",
    "sg:province":"Murcia",
    "wof:name":"Construcciones Y Contratas S.l.",
    "wof:placetype":"venue"
},
  "geometry": {"coordinates":[-0.8444520235,37.8086967468],"type":"Point"}
}