{
  "type": "Feature",
  "properties": {
    "iso:country":"ES",
    "sg:address":"Bule Jose Prat, 9",
    "sg:city":"Madrid",
    "sg:orig_category":"Peluquer\u00cdas, Peluquer\u00cda Mixta",
    "sg:phone":"+34 917 51 05 43",
    "sg:postcode":"28032",
    "sg:province":"Madrid",
    "wof:name":"Coiff 1 De Hermanos Blanco S.l.",
    "wof:placetype":"venue"
},
  "geometry": {"coordinates":[-3.6240189075,40.3983955383],"type":"Point"}
}