{
  "type": "Feature",
  "properties": {
    "addr:full":"Fuente Risquillo, 1 Guadamur Toledo 45160",
    "addr:housenumber":"1",
    "addr:postcode":"45160",
    "addr:street":"Risquillo",
    "iso:country":"ES",
    "sg:address":"Fuente Risquillo, 1",
    "sg:city":"Guadamur",
    "sg:orig_category":"Cerrajer\u00cda, Ferrallista",
    "sg:phone":"+34 925 29 14 01",
    "sg:postcode":"45160",
    "sg:province":"Toledo",
    "wof:name":"Talleres Mabramar S.l.",
    "wof:placetype":"venue"
},
  "geometry": {"coordinates":[-4.1341891289,39.802986145],"type":"Point"}
}