{
  "type": "Feature",
  "properties": {
    "iso:country":"ES",
    "sg:address":"Carr De Gaspar Blai Arbuixec, 1",
    "sg:city":"Ontinyent",
    "sg:orig_category":"Iglesia Cat\u00d3lica",
    "sg:phone":"+34 962 38 21 78",
    "sg:postcode":"46870",
    "sg:province":"Valencia",
    "wof:name":"Parroquia San Rafael",
    "wof:placetype":"venue"
},
  "geometry": {"coordinates":[-0.6030989885,38.8258895874],"type":"Point"}
}