{
  "type": "Feature",
  "properties": {
    "iso:country":"ES",
    "sg:address":"Carrer de Lacy, 83",
    "sg:city":"Sabadell",
    "sg:orig_category":"Asociaciones Y Clubs Deportivos",
    "sg:phone":"+34 937 27 11 05",
    "sg:postcode":"08202",
    "sg:province":"Barcelona",
    "wof:name":"M. G. Bots S. L.",
    "wof:placetype":"venue"
},
  "geometry": {"coordinates":[2.1131811142,41.5447349548],"type":"Point"}
}