{
  "type": "Feature",
  "properties": {
    "iso:country":"ES",
    "sg:address":"Bulandegi Bidea, S/n",
    "sg:city":"Elbarrena",
    "sg:orig_category":"Suministros Para Carrocer\u00cdas",
    "sg:phone":"+34 943 69 05 70",
    "sg:postcode":"20159",
    "sg:province":"Guip\u00f9zcoa",
    "wof:name":"Zubelzu Chapartegui Ignacio",
    "wof:placetype":"venue"
},
  "geometry": {"coordinates":[-2.0570554733,43.1934623718],"type":"Point"}
}