{
  "type": "Feature",
  "properties": {
    "addr:full":"Urb San Luis, 15 San Pedro Alcantara M\u00e1laga 29670",
    "addr:housenumber":"15",
    "addr:postcode":"29670",
    "addr:street":"Luis",
    "iso:country":"ES",
    "sg:address":"Urb San Luis, 15",
    "sg:city":"San Pedro Alcantara",
    "sg:orig_category":"Asesor\u00cda Sobre Comunicaci\u00d3n De Empresas",
    "sg:phone":"+34 952 79 92 89",
    "sg:postcode":"29670",
    "sg:province":"M\u00e1laga",
    "wof:name":"Gestosan Asesores S.l.",
    "wof:placetype":"venue"
},
  "geometry": {"coordinates":[-4.9902391434,36.4866333008],"type":"Point"}
}