{
  "type": "Feature",
  "properties": {
    "addr:full":"Carrer de Ramon Casas, 12 Cunit Tarragona 43881",
    "addr:housenumber":"12",
    "addr:postcode":"43881",
    "addr:street":"Carrer De Ramon Casas",
    "iso:country":"ES",
    "sg:address":"Carrer de Ramon Casas, 12",
    "sg:city":"Cunit",
    "sg:orig_category":"Art\u00cdculos De Decoraci\u00d3n",
    "sg:phone":"+34 977 67 44 66",
    "sg:postcode":"43881",
    "sg:province":"Tarragona",
    "wof:name":"Pintura Y Decoracion Hermanos Lopez Molina S.a.",
    "wof:placetype":"venue"
},
  "geometry": {"coordinates":[1.6345239878,41.19688797],"type":"Point"}
}