{
  "type": "Feature",
  "properties": {
    "addr:full":"Cordoba, 22 Sta M Trassierra C\u00f3rdoba 14011",
    "addr:housenumber":"22",
    "addr:postcode":"14011",
    "addr:street":"Cordoba;M;Co\u0301Rdoba",
    "iso:country":"ES",
    "sg:address":"Cordoba, 22",
    "sg:city":"Sta M Trassierra",
    "sg:orig_category":"Quincaller\u00cda (al Por Menor)",
    "sg:phone":"+34 957 73 03 22",
    "sg:postcode":"14011",
    "sg:province":"C\u00f3rdoba",
    "wof:name":"Suministros Y Servicios Trassierra S.l.",
    "wof:placetype":"venue"
},
  "geometry": {"coordinates":[-4.8937740326,37.9224357605],"type":"Point"}
}