{
  "type": "Feature",
  "properties": {
    "iso:country":"ES",
    "sg:address":"Calle de Huerta (la), 10",
    "sg:city":"Petrer",
    "sg:orig_category":"Asociaciones, Organismos Culturales Y Socioeducativos",
    "sg:phone":"+34 966 95 02 57",
    "sg:postcode":"03610",
    "sg:province":"Alicante",
    "wof:name":"Asociacion Juvenil De Estudiantes Del Medio Vinalopo",
    "wof:placetype":"venue"
},
  "geometry": {"coordinates":[-0.7711241841,38.485496521],"type":"Point"}
}