{
  "type": "Feature",
  "properties": {
    "addr:full":"Calle de Jose Torres Martinez, 50 Mengibar Ja\u00e9n 23620",
    "addr:housenumber":"50",
    "addr:postcode":"23620",
    "addr:street":"Calle De Jose Torres Martinez;Jae\u0301N",
    "iso:country":"ES",
    "sg:address":"Calle de Jose Torres Martinez, 50",
    "sg:city":"Mengibar",
    "sg:orig_category":"Material Y Suministros Para Perforaciones, Sondeos",
    "sg:phone":"+34 953 37 13 76",
    "sg:postcode":"23620",
    "sg:province":"Ja\u00e9n",
    "wof:name":"Excavaciones Y Demoliciones Molina S.l.",
    "wof:placetype":"venue"
},
  "geometry": {"coordinates":[-3.813190937,37.9678268433],"type":"Point"}
}