{
  "type": "Feature",
  "properties": {
    "iso:country":"ES",
    "sg:address":"Av Costa Brava, 4",
    "sg:city":"Platja D'aro",
    "sg:orig_category":"Ropa De Hogar (al Por Menor)",
    "sg:phone":"+34 972 82 71 36",
    "sg:postcode":"17250",
    "sg:province":"Girona",
    "wof:name":"Uneideemoia  A",
    "wof:placetype":"venue"
},
  "geometry": {"coordinates":[2.8091239929,41.9675712585],"type":"Point"}
}