{
  "type": "Feature",
  "properties": {
    "addr:full":"Carrer de Blasco De Garay, 28 Barcelona Barcelona 08004",
    "addr:housenumber":"28",
    "addr:postcode":"08004",
    "addr:street":"Carrer De Blasco De Garay",
    "iso:country":"ES",
    "sg:address":"Carrer de Blasco De Garay, 28",
    "sg:city":"Barcelona",
    "sg:orig_category":"Reposter\u00cdas",
    "sg:phone":"+34 934 41 54 40",
    "sg:postcode":"08004",
    "sg:province":"Barcelona",
    "wof:name":"Gabriel Casimiro Jose",
    "wof:placetype":"venue"
},
  "geometry": {"coordinates":[2.1626720428,41.3735847473],"type":"Point"}
}