{
  "type": "Feature",
  "properties": {
    "addr:full":"Avda Bonaire, 12 Malaga M\u00e1laga 29004",
    "addr:housenumber":"12",
    "addr:postcode":"29004",
    "addr:street":"Avda Bonaire;Ma\u0301Laga",
    "iso:country":"ES",
    "sg:address":"Avda Bonaire, 12",
    "sg:city":"Malaga",
    "sg:orig_category":"Supermercados Y Hipermercados",
    "sg:phone":"+34 952 24 61 31",
    "sg:postcode":"29004",
    "sg:province":"M\u00e1laga",
    "wof:name":"Gongora Terron Antonio",
    "wof:placetype":"venue"
},
  "geometry": {"coordinates":[-4.4552941322,36.6953620911],"type":"Point"}
}