{
  "type": "Feature",
  "properties": {
    "iso:country":"ES",
    "sg:address":"Rua Benefica De Conxo (da), 23",
    "sg:city":"Santiago De Compostela",
    "sg:orig_category":"Electricidad: Instalaciones Industriales",
    "sg:phone":"+34 981 53 41 50",
    "sg:postcode":"15706",
    "sg:province":"La Coru\u00f1a",
    "wof:name":"Electricidad Rayosil S.l.",
    "wof:placetype":"venue"
},
  "geometry": {"coordinates":[-8.5581283569,42.862739563],"type":"Point"}
}