{
  "type": "Feature",
  "properties": {
    "addr:full":"Avda Galicia, S/n Tapia Casariego Asturias 33740",
    "addr:housenumber":"s / n",
    "addr:postcode":"33740",
    "addr:street":"Avda Galicia;Casariego",
    "iso:country":"ES",
    "sg:address":"Avda Galicia, S/n",
    "sg:city":"Tapia Casariego",
    "sg:orig_category":"Carnicer\u00cdas, Carnicer\u00cdas",
    "sg:phone":"+34 985 62 86 37",
    "sg:postcode":"33740",
    "sg:province":"Asturias",
    "wof:name":"Nieto Iglesias Luis",
    "wof:placetype":"venue"
},
  "geometry": {"coordinates":[-6.9432191849,43.5715408325],"type":"Point"}
}