{
  "type": "Feature",
  "properties": {
    "iso:country":"ES",
    "sg:address":"Pl Tetuan, 34",
    "sg:city":"Barcelona",
    "sg:orig_category":"Alcoholes Y Aguardientes (fabricaci\u00d3n, Al Por Mayor)",
    "sg:phone":"+34 932 45 00 85",
    "sg:postcode":"08010",
    "sg:province":"Barcelona",
    "wof:name":"Gualdo Porredon Maria Luisa",
    "wof:placetype":"venue"
},
  "geometry": {"coordinates":[2.1762080193,41.3955345154],"type":"Point"}
}