{
  "type": "Feature",
  "properties": {
    "iso:country":"ES",
    "sg:address":"Poli Can Font De La Parera, S/n",
    "sg:city":"Santa Agnes De Malanyanes",
    "sg:orig_category":"Fabricaci\u00d3n De Clavijas Y De Pistones",
    "sg:phone":"+34 938 42 23 50",
    "sg:postcode":"08430",
    "sg:province":"Barcelona",
    "sg:website":"www.bericap.com",
    "wof:name":"Bericap S. A.",
    "wof:placetype":"venue"
},
  "geometry": {"coordinates":[2.3271899223,41.5984611511],"type":"Point"}
}