{
  "type": "Feature",
  "properties": {
    "iso:country":"ES",
    "sg:address":"Avda Tomas Dominguez, 3",
    "sg:city":"Huelva",
    "sg:orig_category":"Centros Empresariales",
    "sg:phone":"+34 959 20 83 00",
    "sg:postcode":"21...",
    "sg:province":"Huelva",
    "sg:website":"www.foe.es",
    "wof:name":"Federacion Onubense De Empresarios",
    "wof:placetype":"venue"
},
  "geometry": {"coordinates":[-6.9495940208,37.256313324],"type":"Point"}
}