{
  "type": "Feature",
  "properties": {
    "iso:country":"ES",
    "sg:address":"Calle de Santa Clara, 4",
    "sg:city":"Oviedo",
    "sg:orig_category":"Arquitectos",
    "sg:phone":"+34 985 21 58 03",
    "sg:postcode":"33001",
    "sg:province":"Asturias",
    "wof:name":"Gonzalez Alvarez-luengo Jose Maria",
    "wof:placetype":"venue"
},
  "geometry": {"coordinates":[-5.8465909958,43.3640518188],"type":"Point"}
}