{
  "type": "Feature",
  "properties": {
    "addr:full":"Alto Do Couso, S/n Bustavalle Ourense 32703",
    "addr:housenumber":"s",
    "addr:postcode":"32703",
    "addr:street":"/ N",
    "iso:country":"ES",
    "sg:address":"Alto Do Couso, S/n",
    "sg:city":"Bustavalle",
    "sg:orig_category":"Aparcamientos (infraestructuras, Accesorios)",
    "sg:phone":"+34 988 46 34 80",
    "sg:postcode":"32703",
    "sg:province":"Ourense",
    "wof:name":"Alvarez Casado Antonio",
    "wof:placetype":"venue"
},
  "geometry": {"coordinates":[-7.6770486832,42.3012504578],"type":"Point"}
}