{
  "type": "Feature",
  "properties": {
    "iso:country":"ES",
    "sg:address":"Calle de General Vives, 54",
    "sg:city":"Palmas De Gran Canaria",
    "sg:orig_category":"Bisuter\u00cda, Joyer\u00cda, Relojer\u00cda (al Por Menor)",
    "sg:phone":"+34 928 22 06 19",
    "sg:postcode":"35007",
    "sg:province":"Las Palmas",
    "wof:name":"Sanz Esmoriz Andres",
    "wof:placetype":"venue"
},
  "geometry": {"coordinates":[-15.4315185547,28.1390781403],"type":"Point"}
}