{
  "type": "Feature",
  "properties": {
    "addr:full":"Ctra. Rueda, 36 Valladolid Valladolid 47008",
    "addr:housenumber":"36",
    "addr:postcode":"47008",
    "addr:street":"Ctra. Rueda",
    "iso:country":"ES",
    "sg:address":"Ctra. Rueda, 36",
    "sg:city":"Valladolid",
    "sg:orig_category":"Fabricaci\u00d3n, Venta De Cuadros, Accesorios Para Enmarcar",
    "sg:phone":"+34 983 22 34 53",
    "sg:postcode":"47008",
    "sg:province":"Valladolid",
    "wof:name":"Fernandez Posada Carmen",
    "wof:placetype":"venue"
},
  "geometry": {"coordinates":[-4.7420687675,41.6271781921],"type":"Point"}
}