{
  "type": "Feature",
  "properties": {
    "addr:full":"Calle de Manilva, S/n Angeles C\u00e1diz 11330",
    "addr:housenumber":"s / n",
    "addr:postcode":"11330",
    "addr:street":"Calle De Manilva",
    "iso:country":"ES",
    "sg:address":"Calle de Manilva, S/n",
    "sg:city":"Angeles",
    "sg:orig_category":"Tapones Y Art\u00cdculos De Corcho",
    "sg:phone":"+34 956 64 00 30",
    "sg:postcode":"11330",
    "sg:province":"C\u00e1diz",
    "wof:name":"Corchos Guerrero S.a.",
    "wof:placetype":"venue"
},
  "geometry": {"coordinates":[-5.4481987953,36.4326057434],"type":"Point"}
}