{
  "type": "Feature",
  "properties": {
    "addr:full":"Carr Quevedo, 9 Badalona Barcelona 08914",
    "addr:housenumber":"9",
    "addr:postcode":"08914",
    "addr:street":"Carr Quevedo",
    "iso:country":"ES",
    "sg:address":"Carr Quevedo, 9",
    "sg:city":"Badalona",
    "sg:orig_category":"Heladeros",
    "sg:phone":"+34 933 87 72 91",
    "sg:postcode":"08914",
    "sg:province":"Barcelona",
    "wof:name":"Casa Colomina,s.l.",
    "wof:placetype":"venue"
},
  "geometry": {"coordinates":[2.2263710499,41.4398384094],"type":"Point"}
}