{
  "type": "Feature",
  "properties": {
    "iso:country":"ES",
    "sg:address":"Calle de Tirma, 13",
    "sg:city":"Union",
    "sg:orig_category":"Empresas De Carpinter\u00cda",
    "sg:phone":"+34 928 75 59 80",
    "sg:postcode":"35110",
    "sg:province":"Las Palmas",
    "wof:name":"Santana Quintana Ezequiel Esteban",
    "wof:placetype":"venue"
},
  "geometry": {"coordinates":[-15.4485340118,27.8392906189],"type":"Point"}
}