{
  "type": "Feature",
  "properties": {
    "addr:full":"Carrer de Famadas, 98 Hospitalet Llobregat Barcelona 08907",
    "addr:housenumber":"98",
    "addr:postcode":"08907",
    "addr:street":"Carrer De Famadas",
    "iso:country":"ES",
    "sg:address":"Carrer de Famadas, 98",
    "sg:city":"Hospitalet Llobregat",
    "sg:orig_category":"Limpieza Con Chorro De Arena Y Con Granalla, Pulido",
    "sg:phone":"+34 933 38 35 93",
    "sg:postcode":"08907",
    "sg:province":"Barcelona",
    "sg:website":"www.esmepuli.com",
    "wof:name":"Esmepuli S. L.",
    "wof:placetype":"venue"
},
  "geometry": {"coordinates":[2.0980529785,41.3551177979],"type":"Point"}
}