{
  "type": "Feature",
  "properties": {
    "addr:full":"Calle de Victor Jara, S/n San Rafael Las Palmas 35110",
    "addr:housenumber":"s / n",
    "addr:postcode":"35110",
    "addr:street":"Calle De Victor Jara",
    "iso:country":"ES",
    "sg:address":"Calle de Victor Jara, S/n",
    "sg:city":"San Rafael",
    "sg:orig_category":"Ropa Para Caballeros (al Por Menor)",
    "sg:phone":"+34 928 75 28 71",
    "sg:postcode":"35110",
    "sg:province":"Las Palmas",
    "wof:name":"Garbor Modas S.l.",
    "wof:placetype":"venue"
},
  "geometry": {"coordinates":[-15.4485340118,27.8392906189],"type":"Point"}
}