{
  "type": "Feature",
  "properties": {
    "addr:full":"Calle de Cid (el), 6 Estepona M\u00e1laga 29680",
    "addr:housenumber":"6",
    "addr:postcode":"29680",
    "addr:street":"Calle De Cid El",
    "iso:country":"ES",
    "sg:address":"Calle de Cid (el), 6",
    "sg:city":"Estepona",
    "sg:orig_category":"Parques De Atracciones Y Centros De Esparcimiento",
    "sg:phone":"+34 952 79 23 72",
    "sg:postcode":"29680",
    "sg:province":"M\u00e1laga",
    "wof:name":"Telefonia Saltele Marbella S.l.",
    "wof:placetype":"venue"
},
  "geometry": {"coordinates":[-5.1452279091,36.4283256531],"type":"Point"}
}