{
  "type": "Feature",
  "properties": {
    "iso:country":"ES",
    "sg:address":"Plaz Doctor Cifuentes, 2",
    "sg:city":"Torrijos",
    "sg:orig_category":"Asociaciones Y Clubs Deportivos",
    "sg:phone":"+34 925 76 06 76",
    "sg:postcode":"45500",
    "sg:province":"Toledo",
    "wof:name":"Deportes Chanos Esport C.b.",
    "wof:placetype":"venue"
},
  "geometry": {"coordinates":[-4.2857499123,39.981754303],"type":"Point"}
}