{
  "type": "Feature",
  "properties": {
    "addr:full":"Carrer de L'encarnacio, 119 Barcelona Barcelona 08024",
    "addr:housenumber":"119",
    "addr:postcode":"08024",
    "addr:street":"Carrer De L'Encarnacio",
    "iso:country":"ES",
    "sg:address":"Carrer de L'encarnacio, 119",
    "sg:city":"Barcelona",
    "sg:orig_category":"Alquiler De V\u00cddeo",
    "sg:phone":"+34 932 13 02 85",
    "sg:postcode":"08024",
    "sg:province":"Barcelona",
    "wof:name":"Disapevi S.c.p.",
    "wof:placetype":"venue"
},
  "geometry": {"coordinates":[2.1633570194,41.4084625244],"type":"Point"}
}