{
  "type": "Feature",
  "properties": {
    "iso:country":"ES",
    "sg:address":"Calle de Cristobal Perez Pastor, 15",
    "sg:city":"Albacete",
    "sg:orig_category":"Laboratorios Dentales",
    "sg:phone":"+34 967 51 21 13",
    "sg:postcode":"02004",
    "sg:province":"Albacete",
    "wof:name":"Dentalab C.b.",
    "wof:placetype":"venue"
},
  "geometry": {"coordinates":[-1.8616412878,38.9949188232],"type":"Point"}
}