{
  "type": "Feature",
  "properties": {
    "iso:country":"ES",
    "sg:address":"Calle de Antequera, 4",
    "sg:city":"Cala",
    "sg:orig_category":"Asesor\u00cda Sobre Comunicaci\u00d3n De Empresas",
    "sg:phone":"+34 952 49 36 64",
    "sg:postcode":"29649",
    "sg:province":"M\u00e1laga",
    "wof:name":"La Cala Management Services S.l.",
    "wof:placetype":"venue"
},
  "geometry": {"coordinates":[-4.6794753075,36.5033607483],"type":"Point"}
}