{
  "type": "Feature",
  "properties": {
    "iso:country":"ES",
    "sg:address":"Calle de La Solana, 16",
    "sg:city":"Golf De Aldeamayor",
    "sg:orig_category":"Negocio De Materiales De Construcci\u00d3n",
    "sg:phone":"+34 983 54 90 97",
    "sg:postcode":"47162",
    "sg:province":"Valladolid",
    "wof:name":"Texsa Morteros S.a.",
    "wof:placetype":"venue"
},
  "geometry": {"coordinates":[-4.6361689568,41.515625],"type":"Point"}
}