{
  "type": "Feature",
  "properties": {
    "iso:country":"ES",
    "sg:address":"Calle de Camino Real, 24",
    "sg:city":"Colloto",
    "sg:orig_category":"Frutas, Legumbres Frescas Y Tempranas (al Por Menor)",
    "sg:phone":"+34 985 79 42 70",
    "sg:postcode":"33010",
    "sg:province":"Asturias",
    "wof:name":"Frutas Ayu S.l.",
    "wof:placetype":"venue"
},
  "geometry": {"coordinates":[-5.8007321358,43.3771629333],"type":"Point"}
}