{
  "type": "Feature",
  "properties": {
    "addr:full":"Calle de Portal De Gamarra, 2 Vitoria-gasteiz \u00c1lava 01013",
    "addr:housenumber":"2",
    "addr:postcode":"01013",
    "addr:street":"Calle De Portal De Gamarra",
    "iso:country":"ES",
    "sg:address":"Calle de Portal De Gamarra, 2",
    "sg:city":"Vitoria-gasteiz",
    "sg:orig_category":"Cristaler\u00cdas",
    "sg:phone":"+34 945 25 29 92",
    "sg:postcode":"01013",
    "sg:province":"\u00c1lava",
    "wof:name":"Ialvi S. L.",
    "wof:placetype":"venue"
},
  "geometry": {"coordinates":[-2.6530139446,42.8647193909],"type":"Point"}
}