{
  "type": "Feature",
  "properties": {
    "iso:country":"ES",
    "sg:address":"Calle de Ramon Gallud, 60",
    "sg:city":"Torrevieja",
    "sg:orig_category":"M\u00c9dicos: Estomatolog\u00cda",
    "sg:phone":"+34 965 71 73 19",
    "sg:postcode":"03180",
    "sg:province":"Alicante",
    "wof:name":"Instituto Inplatologico Periodontal S.l.",
    "wof:placetype":"venue"
},
  "geometry": {"coordinates":[-0.6815800071,37.9771499634],"type":"Point"}
}