{
  "type": "Feature",
  "properties": {
    "addr:full":"Calle de Aguilar De Mera, Teniente, 3 Melilla Melilla 52001",
    "addr:housenumber":"3",
    "addr:postcode":"52001",
    "addr:street":"Calle De Aguilar De Mera Teniente",
    "iso:country":"ES",
    "sg:address":"Calle de Aguilar De Mera, Teniente, 3",
    "sg:city":"Melilla",
    "sg:orig_category":"Bancos",
    "sg:phone":"+34 952 68 64 14",
    "sg:postcode":"52001",
    "sg:province":"Melilla",
    "wof:name":"Banco Bilbao Vizcaya Argentaria Sa",
    "wof:placetype":"venue"
},
  "geometry": {"coordinates":[-2.9388227463,35.2932281494],"type":"Point"}
}