{
  "type": "Feature",
  "properties": {
    "iso:country":"ES",
    "sg:address":"Calle de Malaga (de), 17",
    "sg:city":"Humanes De Madrid",
    "sg:orig_category":"Art\u00cdculos De Madera (fabricaci\u00d3n Y Al Por Mayor)",
    "sg:phone":"+34 916 15 90 62",
    "sg:postcode":"28970",
    "sg:province":"Madrid",
    "wof:name":"Estevez Fernandez Jesus",
    "wof:placetype":"venue"
},
  "geometry": {"coordinates":[-3.8207809925,40.2768211365],"type":"Point"}
}