{
  "type": "Feature",
  "properties": {
    "addr:full":"Calle de Fika, 50 Bilbao Vizcaya 48004",
    "addr:housenumber":"50",
    "addr:postcode":"48004",
    "addr:street":"Calle De Fika",
    "iso:country":"ES",
    "sg:address":"Calle de Fika, 50",
    "sg:city":"Bilbao",
    "sg:orig_category":"Clubes, Asociaciones De Ocio",
    "sg:phone":"+34 944 33 40 41",
    "sg:postcode":"48004",
    "sg:province":"Vizcaya",
    "wof:name":"Wolf Miniaturas S.l",
    "wof:placetype":"venue"
},
  "geometry": {"coordinates":[-2.9170880318,43.2529144287],"type":"Point"}
}