{
  "type": "Feature",
  "properties": {
    "iso:country":"ES",
    "sg:address":"Calle de General Pardi\u00d1as, 17",
    "sg:city":"Madrid",
    "sg:orig_category":"Arquitectos",
    "sg:phone":"+34 915 78 01 52",
    "sg:postcode":"28001",
    "sg:province":"Madrid",
    "wof:name":"Merino Garcia Francisco",
    "wof:placetype":"venue"
},
  "geometry": {"coordinates":[-3.6787741184,40.4256134033],"type":"Point"}
}