{
  "type": "Feature",
  "properties": {
    "addr:full":"Calle de Iglesia, 10 Majadahonda Madrid 28220",
    "addr:housenumber":"10",
    "addr:postcode":"28220",
    "addr:street":"Calle De Iglesia",
    "iso:country":"ES",
    "sg:address":"Calle de Iglesia, 10",
    "sg:city":"Majadahonda",
    "sg:orig_category":"Ense\u00d1anza: Profesiones Art\u00cdsticas",
    "sg:phone":"+34 916 39 73 71",
    "sg:postcode":"28220",
    "sg:province":"Madrid",
    "wof:name":"Imagen Telefonia Y Desarrollo S.l.",
    "wof:placetype":"venue"
},
  "geometry": {"coordinates":[-3.8726670742,40.4747200012],"type":"Point"}
}