{
  "type": "Feature",
  "properties": {
    "iso:country":"ES",
    "sg:address":"Calle de Santo Domingo, 18",
    "sg:city":"Marchena",
    "sg:orig_category":"Agencias De Viajes",
    "sg:phone":"+34 955 84 50 96",
    "sg:postcode":"41620",
    "sg:province":"Sevilla",
    "wof:name":"Viajes Marchena S.l.",
    "wof:placetype":"venue"
},
  "geometry": {"coordinates":[-5.4167709351,37.3286895752],"type":"Point"}
}