{
  "type": "Feature",
  "properties": {
    "addr:full":"Calle de Gavilanes (blq), 7 Madrid Madrid 28043",
    "addr:housenumber":"7",
    "addr:postcode":"madrid;28043",
    "addr:street":"Calle De Gavilanes Blq",
    "iso:country":"ES",
    "sg:address":"Calle de Gavilanes (blq), 7",
    "sg:city":"Madrid",
    "sg:orig_category":"M\u00c1quinas De Escribir, M\u00c1quinas De Oficina (al Por Menor, Reparaci\u00d3n)",
    "sg:phone":"+34 913 88 47 77",
    "sg:postcode":"28043",
    "sg:province":"Madrid",
    "sg:website":"www.canonm8sistemas.com",
    "wof:name":"M8 Sistemas De Comunicacion Y Reprografia S.a.",
    "wof:placetype":"venue"
},
  "geometry": {"coordinates":[-3.7407279015,40.4795074463],"type":"Point"}
}