{
  "type": "Feature",
  "properties": {
    "addr:full":"Avda Ana De Viya, 6 Cadiz C\u00e1diz 11008",
    "addr:housenumber":"6",
    "addr:postcode":"11008",
    "addr:street":"Avda Ana De Viya",
    "iso:country":"ES",
    "sg:address":"Avda Ana De Viya, 6",
    "sg:city":"Cadiz",
    "sg:orig_category":"Estancos",
    "sg:phone":"+34 956 25 19 53",
    "sg:postcode":"11008",
    "sg:province":"C\u00e1diz",
    "wof:name":"Sanchez Fernandez Felipe",
    "wof:placetype":"venue"
},
  "geometry": {"coordinates":[-6.2808580399,36.5129241943],"type":"Point"}
}