{
  "type": "Feature",
  "properties": {
    "addr:full":"Calle de Nestor De La Torre, 10 Palmas De Gran Canaria Las Palmas 35006",
    "addr:housenumber":"10",
    "addr:postcode":"35006",
    "addr:street":"Calle De Nestor De La Torre",
    "iso:country":"ES",
    "sg:address":"Calle de Nestor De La Torre, 10",
    "sg:city":"Palmas De Gran Canaria",
    "sg:orig_category":"Radiocomunicaciones, Telefon\u00cda M\u00d3vil, Radiomensajer\u00cda: Servicios, Comercializaci\u00d3n",
    "sg:phone":"+34 928 24 81 50",
    "sg:postcode":"35006",
    "sg:province":"Las Palmas",
    "sg:website":"www.servielectr.com",
    "wof:name":"Servicios Electronicos S.l.",
    "wof:placetype":"venue"
},
  "geometry": {"coordinates":[-15.4397087097,28.1302242279],"type":"Point"}
}