{
  "type": "Feature",
  "properties": {
    "iso:country":"ES",
    "sg:address":"Ctra. Francia, Km. 0038,0",
    "sg:city":"Murillo De Gallego",
    "sg:orig_category":"Deportes Y Programas De Aventura",
    "sg:phone":"+34 974 38 31 52",
    "sg:postcode":"50808",
    "sg:province":"Zaragoza",
    "sg:website":"www.carocaventura.com",
    "wof:name":"Alcorce Pirineos Aventura S.l.",
    "wof:placetype":"venue"
},
  "geometry": {"coordinates":[-0.754091382,42.3365058899],"type":"Point"}
}