{
  "type": "Feature",
  "properties": {
    "addr:full":"Avda Soto Palacios, S/n Madrid Madrid 28034",
    "addr:housenumber":"s / n",
    "addr:postcode":"28034",
    "addr:street":"Avda Soto Palacios",
    "iso:country":"ES",
    "sg:address":"Avda Soto Palacios, S/n",
    "sg:city":"Madrid",
    "sg:orig_category":"Iglesia Cat\u00d3lica",
    "sg:phone":"+34 917 29 12 49",
    "sg:postcode":"28034",
    "sg:province":"Madrid",
    "wof:name":"Parroquia De San Juan Maria Vianney",
    "wof:placetype":"venue"
},
  "geometry": {"coordinates":[-3.6847391129,40.4899291992],"type":"Point"}
}