{
  "type": "Feature",
  "properties": {
    "iso:country":"ES",
    "sg:address":"Poligono Industrial De Bayas, S/n",
    "sg:city":"Miranda Ebro",
    "sg:orig_category":"Juegos Y Juguetes (al Por Menor)",
    "sg:phone":"+34 947 33 09 52",
    "sg:postcode":"09200",
    "sg:province":"Burgos",
    "wof:name":"Dinova S.a.",
    "wof:placetype":"venue"
},
  "geometry": {"coordinates":[-2.916533947,42.6962852478],"type":"Point"}
}