{
  "type": "Feature",
  "properties": {
    "addr:full":"Carrer de Enric Granados, 11 Barbera Valles Barcelona 08210",
    "addr:housenumber":"11",
    "addr:postcode":"08210",
    "addr:street":"Carrer De Enric Granados",
    "iso:country":"ES",
    "sg:address":"Carrer de Enric Granados, 11",
    "sg:city":"Barbera Valles",
    "sg:orig_category":"Centros Empresariales",
    "sg:phone":"+34 937 29 34 59",
    "sg:postcode":"08210",
    "sg:province":"Barcelona",
    "wof:name":"Garcia Martin Maria Carmen",
    "wof:placetype":"venue"
},
  "geometry": {"coordinates":[2.1233100891,41.5158691406],"type":"Point"}
}