{
  "type": "Feature",
  "properties": {
    "addr:full":"Carrer de Maladeta, 58 Sabadell Barcelona 08207",
    "addr:housenumber":"58",
    "addr:postcode":"08207",
    "addr:street":"Carrer De Maladeta",
    "iso:country":"ES",
    "sg:address":"Carrer de Maladeta, 58",
    "sg:city":"Sabadell",
    "sg:orig_category":"Inversiones",
    "sg:phone":"+34 937 23 34 75",
    "sg:postcode":"08207",
    "sg:province":"Barcelona",
    "wof:name":"Ramirez Bocanegra Pedro",
    "wof:placetype":"venue"
},
  "geometry": {"coordinates":[2.0872879028,41.5690078735],"type":"Point"}
}