{
  "type": "Feature",
  "properties": {
    "iso:country":"ES",
    "sg:address":"Calle de Padre Santonja, 3",
    "sg:city":"Mislata",
    "sg:orig_category":"Asociaciones Y Clubs Deportivos",
    "sg:phone":"+34 963 70 78 48",
    "sg:postcode":"46920",
    "sg:province":"Valencia",
    "wof:name":"Nadal Serrano S.l.",
    "wof:placetype":"venue"
},
  "geometry": {"coordinates":[-0.4166190028,39.4729309082],"type":"Point"}
}