{
  "type": "Feature",
  "properties": {
    "iso:country":"ES",
    "sg:address":"Calle de Tilos, 2",
    "sg:city":"Salamanca",
    "sg:orig_category":"Carnicer\u00cdas, Carnicer\u00cdas",
    "sg:phone":"+34 923 22 89 50",
    "sg:postcode":"37004",
    "sg:province":"Salamanca",
    "wof:name":"Valdeval Agropecuaria S.l.",
    "wof:placetype":"venue"
},
  "geometry": {"coordinates":[-5.6545825005,40.9760246277],"type":"Point"}
}