{
  "type": "Feature",
  "properties": {
    "iso:country":"ES",
    "sg:address":"Ctra Vic, 147",
    "sg:city":"Manresa",
    "sg:orig_category":"Asesor\u00cda Fiscal Y Jur\u00cddica",
    "sg:phone":"+34 938 73 32 00",
    "sg:postcode":"08243",
    "sg:province":"Barcelona",
    "wof:name":"Sanchez Mora Associats S.l.",
    "wof:placetype":"venue"
},
  "geometry": {"coordinates":[1.8334840536,41.7306747437],"type":"Point"}
}