{
  "type": "Feature",
  "properties": {
    "addr:full":"Plaz Fernando Feijoo, 6 Villares Ja\u00e9n 23160",
    "addr:housenumber":"6",
    "addr:postcode":"23160",
    "addr:street":"Plaz Fernando Feijoo",
    "iso:country":"ES",
    "sg:address":"Plaz Fernando Feijoo, 6",
    "sg:city":"Villares",
    "sg:orig_category":"Molduras, Junquillos, Listones Y Molduras Perforadas",
    "sg:phone":"+34 953 32 12 72",
    "sg:postcode":"23160",
    "sg:province":"Ja\u00e9n",
    "wof:name":"Diaz Higueras Pedro",
    "wof:placetype":"venue"
},
  "geometry": {"coordinates":[-3.8161590099,37.6935958862],"type":"Point"}
}