{
  "type": "Feature",
  "properties": {
    "iso:country":"ES",
    "sg:address":"Pase Pechina, 28",
    "sg:city":"Valencia",
    "sg:orig_category":"Comercio, Reparaci\u00d3n De Motocicletas, Bicicletas Y Piezas Sueltas",
    "sg:phone":"+34 963 82 01 88",
    "sg:postcode":"46008",
    "sg:province":"Valencia",
    "wof:name":"Gracia Samper Manuel",
    "wof:placetype":"venue"
},
  "geometry": {"coordinates":[-0.3905990124,39.4771690369],"type":"Point"}
}