{
  "type": "Feature",
  "properties": {
    "iso:country":"ES",
    "sg:address":"Carrer de Joan Maragall, 1",
    "sg:city":"Sant Feliu Llobregat",
    "sg:orig_category":"Cl\u00cdnicas Dentales",
    "sg:phone":"+34 936 66 63 03",
    "sg:postcode":"08980",
    "sg:province":"Barcelona",
    "wof:name":"Obrador Giro Domingo",
    "wof:placetype":"venue"
},
  "geometry": {"coordinates":[2.0451140404,41.3803901672],"type":"Point"}
}