{
  "type": "Feature",
  "properties": {
    "addr:full":"Calle de Mayor, 24 Puebla Alfinden Zaragoza 50171",
    "addr:housenumber":"24",
    "addr:postcode":"50171",
    "addr:street":"Calle De Mayor;Alfinden",
    "iso:country":"ES",
    "sg:address":"Calle de Mayor, 24",
    "sg:city":"Puebla Alfinden",
    "sg:orig_category":"Sociedades, Compa\u00d1\u00cdas Aseguradoras",
    "sg:phone":"+34 976 10 88 53",
    "sg:postcode":"50171",
    "sg:province":"Zaragoza",
    "wof:name":"Sucursal Alfinden Aseguradores De Bienes S.l",
    "wof:placetype":"venue"
},
  "geometry": {"coordinates":[-0.7495775223,41.6309623718],"type":"Point"}
}