{
  "type": "Feature",
  "properties": {
    "iso:country":"ES",
    "sg:address":"Calle de Hornos (los), 44",
    "sg:city":"Andujar",
    "sg:orig_category":"Comit\u00c9s De Organizaci\u00d3n De Exposiciones, Ferias, Salones",
    "sg:phone":"+34 953 50 08 98",
    "sg:postcode":"23740",
    "sg:province":"Ja\u00e9n",
    "wof:name":"Garcia Garcia Antonio",
    "wof:placetype":"venue"
},
  "geometry": {"coordinates":[-4.0496811867,38.0384750366],"type":"Point"}
}