{
  "type": "Feature",
  "properties": {
    "addr:full":"Calle de Castillo, 81 Santa Cruz De Tenerife Santa Cruz De Tenerife 38003",
    "addr:housenumber":"81",
    "addr:postcode":"38003",
    "addr:street":"Calle De Castillo",
    "iso:country":"ES",
    "sg:address":"Calle de Castillo, 81",
    "sg:city":"Santa Cruz De Tenerife",
    "sg:orig_category":"Contables",
    "sg:phone":"+34 922 29 24 21",
    "sg:postcode":"38003",
    "sg:province":"Santa Cruz De Tenerife",
    "wof:name":"Armada Estevez Manuel",
    "wof:placetype":"venue"
},
  "geometry": {"coordinates":[-16.2521457672,28.4672431946],"type":"Point"}
}