{
  "type": "Feature",
  "properties": {
    "addr:full":"Calle de Miguel De Moncada, 4 Alcala Henares Madrid 28804",
    "addr:housenumber":"4",
    "addr:postcode":"28804",
    "addr:street":"Calle De Miguel De Moncada",
    "iso:country":"ES",
    "sg:address":"Calle de Miguel De Moncada, 4",
    "sg:city":"Alcala Henares",
    "sg:orig_category":"Comercio De Piezas De Recambio Y De Accesorios De Veh\u00cdculos, Veh\u00cdculos Industriales",
    "sg:phone":"+34 918 81 06 79",
    "sg:postcode":"28804",
    "sg:province":"Madrid",
    "wof:name":"Garcia De Marina Ruiz-valdepe\u00f1as Hilario",
    "wof:placetype":"venue"
},
  "geometry": {"coordinates":[-3.3550720215,40.4858703613],"type":"Point"}
}