{
  "type": "Feature",
  "properties": {
    "addr:full":"Plaz Soledad, 1 Huelva Huelva 21004",
    "addr:housenumber":"1",
    "addr:postcode":"21004",
    "addr:street":"Plaz Soledad",
    "iso:country":"ES",
    "sg:address":"Plaz Soledad, 1",
    "sg:city":"Huelva",
    "sg:orig_category":"Promotores Constructores",
    "sg:phone":"+34 959 24 00 22",
    "sg:postcode":"21004",
    "sg:province":"Huelva",
    "wof:name":"Veconsa S.a.",
    "wof:placetype":"venue"
},
  "geometry": {"coordinates":[-6.9495940208,37.256313324],"type":"Point"}
}