{
  "type": "Feature",
  "properties": {
    "iso:country":"ES",
    "sg:address":"Calle de Pilar, 42",
    "sg:city":"Zarza",
    "sg:orig_category":"Muebles, Minoristas",
    "sg:phone":"+34 924 36 65 20",
    "sg:postcode":"06830",
    "sg:province":"Badajoz",
    "wof:name":"Galan Gonzalez Antonio Manuel",
    "wof:placetype":"venue"
},
  "geometry": {"coordinates":[-6.21941185,38.8176765442],"type":"Point"}
}