{
  "type": "Feature",
  "properties": {
    "iso:country":"ES",
    "sg:address":"Calle de Huelva, 8",
    "sg:city":"S. Juan Puerto",
    "sg:orig_category":"Asilos De Ancianos. Centros Privados",
    "sg:phone":"+34 959 36 70 69",
    "sg:postcode":"21610",
    "sg:province":"Huelva",
    "wof:name":"Asociacion San Joaquin Y Santa Ana",
    "wof:placetype":"venue"
},
  "geometry": {"coordinates":[-6.8417096138,37.31508255],"type":"Point"}
}