{
  "type": "Feature",
  "properties": {
    "iso:country":"ES",
    "sg:address":"Calle de Maria Puga Cerdido, 8",
    "sg:city":"Coru\u00d1a",
    "sg:orig_category":"Agentes Generales De Seguros",
    "sg:phone":"+34 981 13 96 50",
    "sg:postcode":"15009",
    "sg:province":"A Coru\u00f1a",
    "wof:name":"Sociedad Setrimar S.l.",
    "wof:placetype":"venue"
},
  "geometry": {"coordinates":[-8.4034070969,43.3415412903],"type":"Point"}
}