{
  "type": "Feature",
  "properties": {
    "addr:full":"Carrer de Alcalde Comas, 5 Barbera Valles Barcelona 08210",
    "addr:housenumber":"5",
    "addr:postcode":"08210",
    "addr:street":"Carrer De Alcalde Comas",
    "iso:country":"ES",
    "sg:address":"Carrer de Alcalde Comas, 5",
    "sg:city":"Barbera Valles",
    "sg:orig_category":"Metales (labores, Pulido)",
    "sg:phone":"+34 937 29 31 93",
    "sg:postcode":"08210",
    "sg:province":"Barcelona",
    "wof:name":"Himedur S.l.",
    "wof:placetype":"venue"
},
  "geometry": {"coordinates":[2.1267659664,41.5173606873],"type":"Point"}
}