{
  "type": "Feature",
  "properties": {
    "addr:full":"C/ Doctor Sempere, 26 Alcoi Alicante 03803",
    "addr:housenumber":"26",
    "addr:postcode":"03803",
    "addr:street":"C / Doctor Sempere",
    "iso:country":"ES",
    "sg:address":"C/ Doctor Sempere, 26",
    "sg:city":"Alcoi",
    "sg:orig_category":"Promotores Constructores",
    "sg:phone":"+34 966 52 02 93",
    "sg:postcode":"03803",
    "sg:province":"Alicante",
    "wof:name":"Gestimat S.l.",
    "wof:placetype":"venue"
},
  "geometry": {"coordinates":[-0.4776110053,38.7006225586],"type":"Point"}
}