{
  "type": "Feature",
  "properties": {
    "iso:country":"ES",
    "sg:address":"La Fuente, S/n",
    "sg:city":"Fabero",
    "sg:orig_category":"Relojer\u00cda (al Por Menor, Reparaci\u00d3n)",
    "sg:phone":"+34 987 55 12 11",
    "sg:postcode":"24420",
    "sg:province":"Le\u00f3n",
    "wof:name":"Fernandez Prieto Manuel",
    "wof:placetype":"venue"
},
  "geometry": {"coordinates":[-6.6261639595,42.7667388916],"type":"Point"}
}