{
  "type": "Feature",
  "properties": {
    "addr:full":"Ctra Cordoba-malaga, S/n Tejar C\u00f3rdoba 14915",
    "addr:housenumber":"s / n",
    "addr:postcode":"14915",
    "addr:street":"Ctra Cordoba-Malaga;Tejar Co\u0301Rdoba",
    "iso:country":"ES",
    "sg:address":"Ctra Cordoba-malaga, S/n",
    "sg:city":"Tejar",
    "sg:orig_category":"Empresas De Desmonte",
    "sg:phone":"+34 957 53 06 49",
    "sg:postcode":"14915",
    "sg:province":"C\u00f3rdoba",
    "wof:name":"Excavaciones Y Transportes S.l",
    "wof:placetype":"venue"
},
  "geometry": {"coordinates":[-4.5449590683,37.2375450134],"type":"Point"}
}