{
  "type": "Feature",
  "properties": {
    "addr:full":"Carrer de Enric Granados, 151 Barcelona Barcelona 08008",
    "addr:housenumber":"151",
    "addr:postcode":"08008",
    "addr:street":"Carrer De Enric Granados",
    "iso:country":"ES",
    "sg:address":"Carrer de Enric Granados, 151",
    "sg:city":"Barcelona",
    "sg:orig_category":"Compraventa De Antig\u00dcedades",
    "sg:phone":"+34 934 14 32 89",
    "sg:postcode":"08008",
    "sg:province":"Barcelona",
    "wof:name":"Sabido Amatriain Francisco Javier",
    "wof:placetype":"venue"
},
  "geometry": {"coordinates":[2.1534569263,41.3943786621],"type":"Point"}
}