{
  "type": "Feature",
  "properties": {
    "addr:full":"Calle de Galena, 2 Valladolid Valladolid 47012",
    "addr:housenumber":"2",
    "addr:postcode":"47012",
    "addr:street":"Calle De Galena",
    "iso:country":"ES",
    "sg:address":"Calle de Galena, 2",
    "sg:city":"Valladolid",
    "sg:orig_category":"Fabricaci\u00d3n, Instalaci\u00d3n Y Reparaci\u00d3n De Bombas",
    "sg:phone":"+34 983 21 10 66",
    "sg:postcode":"47012",
    "sg:province":"Valladolid",
    "wof:name":"Airma Maquinaria Y Sistemas De Aire S. L.",
    "wof:placetype":"venue"
},
  "geometry": {"coordinates":[-4.7117786407,41.6237335205],"type":"Point"}
}