{
  "type": "Feature",
  "properties": {
    "iso:country":"ES",
    "sg:address":"C/ 13, 4",
    "sg:city":"Ca\u00d1ada",
    "sg:orig_category":"Cl\u00cdnicas M\u00c9dicas",
    "sg:phone":"+34 961 32 16 59",
    "sg:postcode":"46182",
    "sg:province":"Valencia",
    "wof:name":"Policlinica Ardit La Ca\u00f1ada S.l.",
    "wof:placetype":"venue"
},
  "geometry": {"coordinates":[-0.4852339923,39.5221443176],"type":"Point"}
}