{
  "type": "Feature",
  "properties": {
    "addr:full":"Avda Rabanales (de), 6 Cordoba C\u00f3rdoba 14007",
    "addr:housenumber":"6",
    "addr:postcode":"14007",
    "addr:street":"Avda Rabanales De;Co\u0301Rdoba",
    "iso:country":"ES",
    "sg:address":"Avda Rabanales (de), 6",
    "sg:city":"Cordoba",
    "sg:orig_category":"Bazares, Art\u00cdculos De Limpieza Y De Cocina (al Por Menor)",
    "sg:phone":"+34 957 25 02 66",
    "sg:postcode":"14007",
    "sg:province":"C\u00f3rdoba",
    "wof:name":"Cobija Lujan Rafael",
    "wof:placetype":"venue"
},
  "geometry": {"coordinates":[-4.7618541718,37.8920440674],"type":"Point"}
}