{
  "type": "Feature",
  "properties": {
    "iso:country":"ES",
    "sg:address":"Calle de Cerrajeros, 15",
    "sg:city":"Zafra",
    "sg:orig_category":"Ropa Para Se\u00d1oras (al Por Menor)",
    "sg:phone":"+34 924 55 29 62",
    "sg:postcode":"06300",
    "sg:province":"Badajoz",
    "wof:name":"Cillan Diaz Maria Isabel",
    "wof:placetype":"venue"
},
  "geometry": {"coordinates":[-6.4177508354,38.4249038696],"type":"Point"}
}