{
  "type": "Feature",
  "properties": {
    "addr:full":"Avda Fuensanta (la), 98 Pizarra M\u00e1laga 29560",
    "addr:housenumber":"98",
    "addr:postcode":"29560",
    "addr:street":"Fuensanta",
    "iso:country":"ES",
    "sg:address":"Avda Fuensanta (la), 98",
    "sg:city":"Pizarra",
    "sg:orig_category":"Cl\u00cdnicas Dentales",
    "sg:phone":"+34 952 48 35 36",
    "sg:postcode":"29560",
    "sg:province":"M\u00e1laga",
    "wof:name":"Borisonik  Maria Esther",
    "wof:placetype":"venue"
},
  "geometry": {"coordinates":[-4.7086939812,36.7709693909],"type":"Point"}
}