{
  "type": "Feature",
  "properties": {
    "addr:full":"Plaz Buen Jesus, 1 Chantada Lugo 27500",
    "addr:housenumber":"1",
    "addr:postcode":"27500",
    "addr:street":"Plaz Buen Jesus",
    "iso:country":"ES",
    "sg:address":"Plaz Buen Jesus, 1",
    "sg:city":"Chantada",
    "sg:orig_category":"Supermercados Y Hipermercados",
    "sg:phone":"+34 982 44 17 15",
    "sg:postcode":"27500",
    "sg:province":"Lugo",
    "wof:name":"Frutas Antonio S.l.",
    "wof:placetype":"venue"
},
  "geometry": {"coordinates":[-7.7607798576,42.6093711853],"type":"Point"}
}