{
  "type": "Feature",
  "properties": {
    "addr:full":"Calle de Madrid, 42 Humanes De Madrid Madrid 28970",
    "addr:housenumber":"42",
    "addr:postcode":"28970",
    "addr:street":"Calle De Madrid",
    "iso:country":"ES",
    "sg:address":"Calle de Madrid, 42",
    "sg:city":"Humanes De Madrid",
    "sg:orig_category":"Inmobiliaria (agencias)",
    "sg:phone":"+34 916 04 92 73",
    "sg:postcode":"28970",
    "sg:province":"Madrid",
    "sg:website":"www.doblempj.com",
    "wof:name":"Doble Mpj S.l.",
    "wof:placetype":"venue"
},
  "geometry": {"coordinates":[-3.82791996,40.2530021667],"type":"Point"}
}