{
  "type": "Feature",
  "properties": {
    "iso:country":"ES",
    "sg:address":"Calle de Melquiades Biencinto, 7",
    "sg:city":"Madrid",
    "sg:orig_category":"Teatro, Ballet, Danza (agrupaciones, Compa\u00d1\u00cdas)",
    "sg:phone":"+34 914 33 92 73",
    "sg:postcode":"28053",
    "sg:province":"Madrid",
    "wof:name":"Inaem Compa\u00f1ia Nacional De Teatro Clasico",
    "wof:placetype":"venue"
},
  "geometry": {"coordinates":[-3.6691439152,40.3971443176],"type":"Point"}
}