{
  "type": "Feature",
  "properties": {
    "addr:full":"Calle de Calvo Sotelo, 11 Logro\u00f1o La Rioja 26003",
    "addr:housenumber":"11",
    "addr:postcode":"26003",
    "addr:street":"Calle De Calvo Sotelo;Rioja",
    "iso:country":"ES",
    "sg:address":"Calle de Calvo Sotelo, 11",
    "sg:city":"Logro\u00f1o",
    "sg:orig_category":"Pintores",
    "sg:phone":"+34 941 25 24 52",
    "sg:postcode":"26003",
    "sg:province":"La Rioja",
    "wof:name":"Infante Perez De Pipaon Jesus",
    "wof:placetype":"venue"
},
  "geometry": {"coordinates":[-2.4426283836,42.4641075134],"type":"Point"}
}