{
  "type": "Feature",
  "properties": {
    "iso:country":"ES",
    "sg:address":"Psaj Isaac Albeniz, 3",
    "sg:city":"Burgos",
    "sg:orig_category":"Molduras, Junquillos, Listones Y Molduras Perforadas",
    "sg:phone":"+34 947 47 04 48",
    "sg:postcode":"09007",
    "sg:province":"Burgos",
    "wof:name":"Morena Ortiz Albertode La",
    "wof:placetype":"venue"
},
  "geometry": {"coordinates":[-3.664098978,42.3535003662],"type":"Point"}
}