{
  "type": "Feature",
  "properties": {
    "iso:country":"ES",
    "sg:address":"Av. Valladolid, 33",
    "sg:city":"Madrid",
    "sg:orig_category":"Ense\u00d1anza: Profesiones Art\u00cdsticas",
    "sg:phone":"+34 915 41 88 40",
    "sg:postcode":"28008",
    "sg:province":"Madrid",
    "wof:name":"Cartagena Lopez De Carrion Jose",
    "wof:placetype":"venue"
},
  "geometry": {"coordinates":[-3.7291219234,40.4272613525],"type":"Point"}
}