{
  "type": "Feature",
  "properties": {
    "addr:full":"Calle de Juan Xxiii, 9 Cacabelos Le\u00f3n 24540",
    "addr:housenumber":"9",
    "addr:postcode":"24540",
    "addr:street":"Calle De Juan Xxiii",
    "iso:country":"ES",
    "sg:address":"Calle de Juan Xxiii, 9",
    "sg:city":"Cacabelos",
    "sg:orig_category":"Centros Comerciales Y Grandes Tiendas",
    "sg:phone":"+34 987 54 60 86",
    "sg:postcode":"24540",
    "sg:province":"Le\u00f3n",
    "wof:name":"Lago Rodriguez Lucrecia",
    "wof:placetype":"venue"
},
  "geometry": {"coordinates":[-6.7236790657,42.5985565186],"type":"Point"}
}