{
  "type": "Feature",
  "properties": {
    "addr:full":"Calle de Juan Rejon, 3 Arrecife Las Palmas 35500",
    "addr:housenumber":"3",
    "addr:postcode":"35500",
    "addr:street":"Calle De Juan Rejon",
    "iso:country":"ES",
    "sg:address":"Calle de Juan Rejon, 3",
    "sg:city":"Arrecife",
    "sg:orig_category":"Abogados",
    "sg:phone":"+34 928 80 52 62",
    "sg:postcode":"35500",
    "sg:province":"Las Palmas",
    "wof:name":"Jusaes Gestion S.l.",
    "wof:placetype":"venue"
},
  "geometry": {"coordinates":[-13.5530662537,28.9593067169],"type":"Point"}
}