{
  "type": "Feature",
  "properties": {
    "iso:country":"ES",
    "sg:address":"Calle de Marti, 11",
    "sg:city":"Valencia",
    "sg:orig_category":"Costureras",
    "sg:phone":"+34 963 73 29 55",
    "sg:postcode":"46005",
    "sg:province":"Valencia",
    "wof:name":"Del Arbol Sanchez Jose Juan",
    "wof:placetype":"venue"
},
  "geometry": {"coordinates":[-0.3702139854,39.4649238586],"type":"Point"}
}