{
  "type": "Feature",
  "properties": {
    "addr:full":"Ctra. Cadiz-algeciras, Km. 0006,8 Chiclana C\u00e1diz 11130",
    "addr:postcode":"11130",
    "addr:street":"Ctra. Cadiz-Algeciras Km. 0006,8",
    "iso:country":"ES",
    "sg:address":"Ctra. Cadiz-algeciras, Km. 0006,8",
    "sg:city":"Chiclana",
    "sg:orig_category":"Mec\u00c1nico Del Autom\u00d3vil",
    "sg:phone":"+34 956 40 62 06",
    "sg:postcode":"11130",
    "sg:province":"C\u00e1diz",
    "wof:name":"Talleres Mota Y Butron S.l.",
    "wof:placetype":"venue"
},
  "geometry": {"coordinates":[-6.1447038651,36.4212188721],"type":"Point"}
}