{
  "type": "Feature",
  "properties": {
    "addr:full":"Gardenia (p I Los Girasoles), 14 Camas Sevilla 41900",
    "addr:housenumber":"14",
    "addr:postcode":"41900",
    "addr:street":"Los Girasoles",
    "iso:country":"ES",
    "sg:address":"Gardenia (p I Los Girasoles), 14",
    "sg:city":"Camas",
    "sg:orig_category":"Empresas De Carpinter\u00cda",
    "sg:phone":"+34 954 39 41 50",
    "sg:postcode":"41900",
    "sg:province":"Sevilla",
    "wof:name":"Parras Marin Fernando",
    "wof:placetype":"venue"
},
  "geometry": {"coordinates":[-6.0344491005,37.4007263184],"type":"Point"}
}