{
  "type": "Feature",
  "properties": {
    "addr:full":"Calle de Fuente Del Berro, 11 Madrid Madrid 28009",
    "addr:housenumber":"11",
    "addr:postcode":"madrid;28009",
    "addr:street":"Calle De Fuente Del Berro",
    "iso:country":"ES",
    "sg:address":"Calle de Fuente Del Berro, 11",
    "sg:city":"Madrid",
    "sg:orig_category":"Peluqueros: De Se\u00d1oras",
    "sg:phone":"+34 914 01 75 86",
    "sg:postcode":"28009",
    "sg:province":"Madrid",
    "wof:name":"Mu\u00f1oz Garcia Vicente",
    "wof:placetype":"venue"
},
  "geometry": {"coordinates":[-3.6707577705,40.4263839722],"type":"Point"}
}