{
  "type": "Feature",
  "properties": {
    "iso:country":"ES",
    "sg:address":"Avda Atlantico Del, S/n",
    "sg:city":"Vecindario",
    "sg:orig_category":"Ropa Para Ni\u00d1os (al Por Menor)",
    "sg:phone":"+34 928 79 30 86",
    "sg:postcode":"35110",
    "sg:province":"Las Palmas",
    "sg:website":"www.pimkie.com",
    "wof:name":"Summerfield S.a.",
    "wof:placetype":"venue"
},
  "geometry": {"coordinates":[-15.45058918,27.8365402222],"type":"Point"}
}