{
  "type": "Feature",
  "properties": {
    "addr:full":"Av Rapita (de La), 35 Amposta Tarragona 43870",
    "addr:housenumber":"35",
    "addr:postcode":"43870",
    "addr:street":"Av Rapita De La",
    "iso:country":"ES",
    "sg:address":"Av Rapita (de La), 35",
    "sg:city":"Amposta",
    "sg:orig_category":"Electrodom\u00c9sticos (al Por Menor)",
    "sg:phone":"+34 977 70 18 90",
    "sg:postcode":"43870",
    "sg:province":"Tarragona",
    "sg:website":"www.redelite.es",
    "wof:name":"Melich Moya S.l.",
    "wof:placetype":"venue"
},
  "geometry": {"coordinates":[0.5800380111,40.7110977173],"type":"Point"}
}