{
  "type": "Feature",
  "properties": {
    "iso:country":"ES",
    "sg:address":"Avda Fama, 8",
    "sg:city":"Paz",
    "sg:orig_category":"Arquitectos",
    "sg:phone":"+34 968 25 47 60",
    "sg:postcode":"30003",
    "sg:province":"Murcia",
    "wof:name":"Hurtado Contreras Antonio",
    "wof:placetype":"venue"
},
  "geometry": {"coordinates":[-1.119838953,37.9845466614],"type":"Point"}
}