{
  "type": "Feature",
  "properties": {
    "addr:full":"Calle de Ayora, 14 Valencia Valencia 46018",
    "addr:housenumber":"14",
    "addr:postcode":"46018",
    "addr:street":"Calle De Ayora",
    "iso:country":"ES",
    "sg:address":"Calle de Ayora, 14",
    "sg:city":"Valencia",
    "sg:orig_category":"Agencias De Viajes",
    "sg:phone":"+34 963 82 70 65",
    "sg:postcode":"46018",
    "sg:province":"Valencia",
    "sg:website":"www.viajesiberia.com",
    "wof:name":"Viajes Iberia S.a.",
    "wof:placetype":"venue"
},
  "geometry": {"coordinates":[-0.3921869993,39.466506958],"type":"Point"}
}