{
  "type": "Feature",
  "properties": {
    "iso:country":"ES",
    "sg:address":"Avda Buenos Aires, 2",
    "sg:city":"Palencia",
    "sg:orig_category":"Estudios, Instalaci\u00d3n De Climatizaci\u00d3n",
    "sg:phone":"+34 979 71 37 11",
    "sg:postcode":"34003",
    "sg:province":"Palencia",
    "wof:name":"J.d. Frio Palencia S.l.",
    "wof:placetype":"venue"
},
  "geometry": {"coordinates":[-4.5238018036,42.0120506287],"type":"Point"}
}