{
  "type": "Feature",
  "properties": {
    "iso:country":"ES",
    "sg:address":"Calle de Aguere, 2",
    "sg:city":"Santa Cruz De Tenerife",
    "sg:orig_category":"Sales (al Por Mayor)",
    "sg:phone":"+34 922 28 77 08",
    "sg:postcode":"38005",
    "sg:province":"Santa Cruz De Tenerife",
    "wof:name":"Facca Federacion De Alimentacion",
    "wof:placetype":"venue"
},
  "geometry": {"coordinates":[-16.2541065216,28.4648952484],"type":"Point"}
}