{
  "type": "Feature",
  "properties": {
    "iso:country":"ES",
    "sg:address":"Calle de German Perez Carrasco, 43",
    "sg:city":"Madrid",
    "sg:orig_category":"Panader\u00cdas, Panader\u00cdas",
    "sg:phone":"+34 913 67 46 36",
    "sg:postcode":"28027",
    "sg:province":"Madrid",
    "wof:name":"Martinez Caceres Maria De Los Angeles",
    "wof:placetype":"venue"
},
  "geometry": {"coordinates":[-3.6445610523,40.4358940125],"type":"Point"}
}