{
  "type": "Feature",
  "properties": {
    "iso:country":"ES",
    "sg:address":"Av Meridiana, 167",
    "sg:city":"Barcelona",
    "sg:orig_category":"Molduras, Junquillos, Listones Y Molduras Perforadas",
    "sg:phone":"+34 934 36 62 46",
    "sg:postcode":"08026",
    "sg:province":"Barcelona",
    "wof:name":"Picajavi S.c.p.",
    "wof:placetype":"venue"
},
  "geometry": {"coordinates":[2.1866080761,41.4127006531],"type":"Point"}
}