{
  "type": "Feature",
  "properties": {
    "iso:country":"ES",
    "sg:address":"Calle de Campo Real, 3",
    "sg:city":"Alcala Henares",
    "sg:orig_category":"Formaci\u00d3n Continuada (variada)",
    "sg:phone":"+34 918 89 32 62",
    "sg:postcode":"28806",
    "sg:province":"Madrid",
    "wof:name":"Garcia Rivas Alfonso",
    "wof:placetype":"venue"
},
  "geometry": {"coordinates":[-3.3787391186,40.495475769],"type":"Point"}
}