{
  "type": "Feature",
  "properties": {
    "addr:full":"Vena Gaia, 7 Veinat De Gaia Girona 17240",
    "addr:housenumber":"7",
    "addr:postcode":"17240",
    "addr:street":"Gaia",
    "iso:country":"ES",
    "sg:address":"Vena Gaia, 7",
    "sg:city":"Veinat De Gaia",
    "sg:orig_category":"Producci\u00d3n, Venta De Productos De Agricultura Biol\u00d3gica",
    "sg:phone":"+34 972 83 05 85",
    "sg:postcode":"17240",
    "sg:province":"Girona",
    "wof:name":"Bufi Artau Y Sanchez C.b.",
    "wof:placetype":"venue"
},
  "geometry": {"coordinates":[2.892385006,41.8299255371],"type":"Point"}
}