{
  "type": "Feature",
  "properties": {
    "iso:country":"ES",
    "sg:address":"Calle de Sierra De Tornavacas, 9",
    "sg:city":"Madrid",
    "sg:orig_category":"Arreglo, Reparaci\u00d3n, Piezas Sueltas De Televisi\u00d3n, V\u00cddeo, Hi",
    "sg:phone":"+34 913 31 58 69",
    "sg:postcode":"28031",
    "sg:province":"Madrid",
    "wof:name":"Diaz Bonache Jose Antonio",
    "wof:placetype":"venue"
},
  "geometry": {"coordinates":[-3.627532959,40.3781547546],"type":"Point"}
}