{
  "type": "Feature",
  "properties": {
    "iso:country":"ES",
    "sg:address":"Ctra Badajoz-valencia, S/n",
    "sg:city":"Manzanares",
    "sg:orig_category":"Asociaciones Y Clubs Deportivos",
    "sg:phone":"+34 926 61 30 29",
    "sg:postcode":"13200",
    "sg:province":"Ciudad Real",
    "wof:name":"Club Tenis Manzanares",
    "wof:placetype":"venue"
},
  "geometry": {"coordinates":[-3.373128891,38.994140625],"type":"Point"}
}