{
  "type": "Feature",
  "properties": {
    "iso:country":"ES",
    "sg:address":"Fontao(lobanes), S/n",
    "sg:city":"Fontao",
    "sg:orig_category":"Carnes De Carnicer\u00cda (al Por Mayor)",
    "sg:phone":"+34 988 27 32 19",
    "sg:postcode":"32510",
    "sg:province":"Ourense",
    "wof:name":"Casa Sanchez Santa Eugenia S.l.",
    "wof:placetype":"venue"
},
  "geometry": {"coordinates":[-7.8659892082,42.1830291748],"type":"Point"}
}