{
  "type": "Feature",
  "properties": {
    "addr:full":"Calle de Bucarel, 13 Logro\u00f1o La Rioja 26006",
    "addr:housenumber":"13",
    "addr:postcode":"26006",
    "addr:street":"Calle De Bucarel;Rioja",
    "iso:country":"ES",
    "sg:address":"Calle de Bucarel, 13",
    "sg:city":"Logro\u00f1o",
    "sg:orig_category":"Bebidas",
    "sg:phone":"+34 941 25 23 42",
    "sg:postcode":"26006",
    "sg:province":"La Rioja",
    "wof:name":"Bebinter S.a",
    "wof:placetype":"venue"
},
  "geometry": {"coordinates":[-2.4039011002,42.4575157166],"type":"Point"}
}