{
  "type": "Feature",
  "properties": {
    "iso:country":"ES",
    "sg:address":"C/ Formentor, S/n",
    "sg:city":"Cales Mallorca",
    "sg:orig_category":"Gas: Botellas Y Contenedores",
    "sg:phone":"+34 971 83 39 58",
    "sg:postcode":"07689",
    "sg:province":"Islas Baleares",
    "wof:name":"Mig C.b.",
    "wof:placetype":"venue"
},
  "geometry": {"coordinates":[3.2789549828,39.4605445862],"type":"Point"}
}