{
  "type": "Feature",
  "properties": {
    "iso:country":"ES",
    "sg:address":"Calle de Camino De Los Sastres, 1",
    "sg:city":"Cordoba",
    "sg:orig_category":"Iglesia Cat\u00d3lica",
    "sg:phone":"+34 957 23 94 99",
    "sg:postcode":"14004",
    "sg:province":"C\u00f3rdoba",
    "wof:name":"Parroquia Santa Cecilia",
    "wof:placetype":"venue"
},
  "geometry": {"coordinates":[-4.7871313095,37.8814620972],"type":"Point"}
}