{
  "type": "Feature",
  "properties": {
    "iso:country":"ES",
    "sg:address":"Calle de Ramon Y Cajal, 46",
    "sg:city":"Santa Cruz De Tenerife",
    "sg:orig_category":"Agentes, Concesionarios Y Sucursales De Veh\u00cdculos",
    "sg:phone":"+34 922 27 09 71",
    "sg:postcode":"38004",
    "sg:province":"Santa Cruz De Tenerife",
    "wof:name":"Materia Tunning S.a.l.",
    "wof:placetype":"venue"
},
  "geometry": {"coordinates":[-16.2522258759,28.4652347565],"type":"Point"}
}