{
  "type": "Feature",
  "properties": {
    "iso:country":"ES",
    "sg:address":"Calle de Hoya Del Molino, 8",
    "sg:city":"Lucena",
    "sg:orig_category":"Imprenta",
    "sg:phone":"+34 957 51 19 05",
    "sg:postcode":"14900",
    "sg:province":"C\u00f3rdoba",
    "wof:name":"Bit Print C.b Impresion Digital",
    "wof:placetype":"venue"
},
  "geometry": {"coordinates":[-4.4893488884,37.4063987732],"type":"Point"}
}