{
  "type": "Feature",
  "properties": {
    "addr:full":"Crta Viver-pto Burriana, 9 Vila-real Castell\u00f3n 12540",
    "addr:housenumber":"9;castello\u0301n",
    "addr:postcode":"12540",
    "addr:street":"Crta Viver-Pto Burriana",
    "iso:country":"ES",
    "sg:address":"Crta Viver-pto Burriana, 9",
    "sg:city":"Vila-real",
    "sg:orig_category":"Negocio De Madera",
    "sg:phone":"+34 964 52 08 00",
    "sg:postcode":"12540",
    "sg:province":"Castell\u00f3n",
    "wof:name":"Maderas Clemente S.a.",
    "wof:placetype":"venue"
},
  "geometry": {"coordinates":[-0.0952899978,39.9453010559],"type":"Point"}
}