{
  "type": "Feature",
  "properties": {
    "addr:full":"Calle de Santa Clotilde, 26 Granada Granada 18003",
    "addr:housenumber":"26",
    "addr:postcode":"18003",
    "addr:street":"Calle De Santa Clotilde",
    "iso:country":"ES",
    "sg:address":"Calle de Santa Clotilde, 26",
    "sg:city":"Granada",
    "sg:orig_category":"Ense\u00d1anza Variada",
    "sg:phone":"+34 958 80 42 11",
    "sg:postcode":"18003",
    "sg:province":"Granada",
    "wof:name":"Aula Didactica S.l.l",
    "wof:placetype":"venue"
},
  "geometry": {"coordinates":[-3.6127610207,37.1799087524],"type":"Point"}
}