{
  "type": "Feature",
  "properties": {
    "addr:full":"Pso. Maritimo, 10 Marbella M\u00e1laga 29600",
    "addr:housenumber":"10",
    "addr:postcode":"29600",
    "addr:street":"Maritimo;Ma\u0301Laga",
    "iso:country":"ES",
    "sg:address":"Pso. Maritimo, 10",
    "sg:city":"Marbella",
    "sg:orig_category":"Confecci\u00d3n (fabricaci\u00d3n, Al Por Mayor)",
    "sg:phone":"+34 952 86 71 27",
    "sg:postcode":"29600",
    "sg:province":"M\u00e1laga",
    "wof:name":"Andoni Nasr Company S.l.",
    "wof:placetype":"venue"
},
  "geometry": {"coordinates":[-4.9553346634,36.4858283997],"type":"Point"}
}