{
  "type": "Feature",
  "properties": {
    "addr:full":"Verdeal, 92 Verdeal Pontevedra 36957",
    "addr:housenumber":"92",
    "addr:postcode":"36957",
    "addr:street":"Verdeal",
    "iso:country":"ES",
    "sg:address":"Verdeal, 92",
    "sg:city":"Verdeal",
    "sg:orig_category":"Estudios Y Construcci\u00d3n De Acuarios Y Viveros",
    "sg:phone":"+34 986 32 61 94",
    "sg:postcode":"36957",
    "sg:province":"Pontevedra",
    "wof:name":"Marbopal C.b.",
    "wof:placetype":"venue"
},
  "geometry": {"coordinates":[-8.6878423691,42.282119751],"type":"Point"}
}