{
  "type": "Feature",
  "properties": {
    "iso:country":"ES",
    "sg:address":"Calle de Pinto, 30",
    "sg:city":"Argamasilla Calatrava",
    "sg:orig_category":"Reposter\u00cdas",
    "sg:phone":"+34 926 47 71 73",
    "sg:postcode":"13440",
    "sg:province":"Ciudad Real",
    "wof:name":"Mu\u00f1oz Lozano Antonio",
    "wof:placetype":"venue"
},
  "geometry": {"coordinates":[-4.083026886,38.7284202576],"type":"Point"}
}