{
  "type": "Feature",
  "properties": {
    "addr:full":"Cmno Aguas, S/n Salamanca Salamanca 37003",
    "addr:housenumber":"s / n",
    "addr:postcode":"37003",
    "addr:street":"Cmno Aguas",
    "iso:country":"ES",
    "sg:address":"Cmno Aguas, S/n",
    "sg:city":"Salamanca",
    "sg:orig_category":"Supermercados Y Hipermercados",
    "sg:phone":"+34 923 18 57 15",
    "sg:postcode":"37003",
    "sg:province":"Salamanca",
    "wof:name":"El Arbol Distribucion Y Supermercados S.a. Unipersonal",
    "wof:placetype":"venue"
},
  "geometry": {"coordinates":[-5.6536841393,40.9645957947],"type":"Point"}
}