{
  "type": "Feature",
  "properties": {
    "addr:full":"Carr Torreta (de La), 2 Gandia Valencia 46700",
    "addr:housenumber":"2",
    "addr:postcode":"46700",
    "addr:street":"Carr Torreta De La;Valencia",
    "iso:country":"ES",
    "sg:address":"Carr Torreta (de La), 2",
    "sg:city":"Gandia",
    "sg:orig_category":"Inmobiliaria (agencias)",
    "sg:phone":"+34 962 87 54 11",
    "sg:postcode":"46700",
    "sg:province":"Valencia",
    "wof:name":"Marques Perez Maria Desamparados",
    "wof:placetype":"venue"
},
  "geometry": {"coordinates":[-0.1913339943,38.960735321],"type":"Point"}
}