{
  "type": "Feature",
  "properties": {
    "iso:country":"ES",
    "sg:address":"Calle de Fuerte, 38",
    "sg:city":"Badajoz",
    "sg:orig_category":"\u00d3ptica: Instrumentos (fabricaci\u00d3n)",
    "sg:phone":"+34 924 23 27 72",
    "sg:postcode":"06010",
    "sg:province":"Badajoz",
    "wof:name":"Optica Badajoz S. A.",
    "wof:placetype":"venue"
},
  "geometry": {"coordinates":[-6.9715919495,38.8688354492],"type":"Point"}
}