{
  "type": "Feature",
  "properties": {
    "iso:country":"ES",
    "sg:address":"Calle de Doctor Josep Gonzalez, 99",
    "sg:city":"Alzira",
    "sg:orig_category":"Edici\u00d3n De Diarios, Revistas, Boletines",
    "sg:phone":"+34 962 41 98 54",
    "sg:postcode":"46600",
    "sg:province":"Valencia",
    "wof:name":"Editorial Germania S.l.",
    "wof:placetype":"venue"
},
  "geometry": {"coordinates":[-0.4030939937,39.1432685852],"type":"Point"}
}