{
  "type": "Feature",
  "properties": {
    "addr:full":"Calle de Xativa, 4 Benaguasil Valencia 46180",
    "addr:housenumber":"4",
    "addr:postcode":"46180",
    "addr:street":"Calle De Xativa",
    "iso:country":"ES",
    "sg:address":"Calle de Xativa, 4",
    "sg:city":"Benaguasil",
    "sg:orig_category":"Promotores Constructores",
    "sg:phone":"+34 962 73 02 51",
    "sg:postcode":"46180",
    "sg:province":"Valencia",
    "wof:name":"Construcciones Serde\u00f1ano",
    "wof:placetype":"venue"
},
  "geometry": {"coordinates":[-0.587421,39.5965538025],"type":"Point"}
}