{
  "type": "Feature",
  "properties": {
    "iso:country":"ES",
    "sg:address":"Calle de Aquilon, 2",
    "sg:city":"Humera-somosaguas-prado Del Rey",
    "sg:orig_category":"Papeler\u00cdas, Librer\u00cdas",
    "sg:phone":"+34 917 11 74 94",
    "sg:postcode":"28223",
    "sg:province":"Madrid",
    "wof:name":"Sacapuntas Somosaguas S.l",
    "wof:placetype":"venue"
},
  "geometry": {"coordinates":[-3.7003455162,40.4166908264],"type":"Point"}
}