{
  "type": "Feature",
  "properties": {
    "iso:country":"ES",
    "sg:address":"Ba\u00f1o, 26",
    "sg:city":"Ba\u00d1o",
    "sg:classifiers":[
        {
            "category":"Taxi",
            "type":"Transportation"
        }
    ],
    "sg:phone":"+34 981 82 71 20",
    "sg:postcode":"15250",
    "sg:province":"La Coru\u00f1a",
    "wof:name":"Leston Martinez Zoilo",
    "wof:placetype":"venue"
},
  "geometry": {"coordinates":[-9.0576505661,42.7748222351],"type":"Point"}
}