{
  "type": "Feature",
  "properties": {
    "iso:country":"ES",
    "sg:address":"Mercat Mare Deu Merce, S/n",
    "sg:city":"Barcelona",
    "sg:orig_category":"Carnicer\u00cdas, Carnicer\u00cdas",
    "sg:phone":"+34 934 29 66 41",
    "sg:postcode":"08031",
    "sg:province":"Barcelona",
    "wof:name":"Torregrosa Giro Jose",
    "wof:placetype":"venue"
},
  "geometry": {"coordinates":[2.1706500053,41.4288063049],"type":"Point"}
}