{
  "type": "Feature",
  "properties": {
    "iso:country":"ES",
    "sg:address":"Av Paisos Catalans, 50",
    "sg:city":"Esplugues Llobregat",
    "sg:orig_category":"Productos Qu\u00cdmicos (fabricaci\u00d3n, Al Por Mayor)",
    "sg:phone":"+34 933 71 05 16",
    "sg:postcode":"08950",
    "sg:province":"Barcelona",
    "wof:name":"Ferrer Rovira Juan",
    "wof:placetype":"venue"
},
  "geometry": {"coordinates":[2.0966749191,41.3805618286],"type":"Point"}
}