{
  "type": "Feature",
  "properties": {
    "iso:country":"ES",
    "sg:address":"Calle de Cruz, 6",
    "sg:city":"Osuna",
    "sg:orig_category":"Reposter\u00cdas",
    "sg:phone":"+34 954 81 17 31",
    "sg:postcode":"41640",
    "sg:province":"Sevilla",
    "wof:name":"Productos Aguisan Sociedad Cooperativa Andaluza",
    "wof:placetype":"venue"
},
  "geometry": {"coordinates":[-5.1075072289,37.2348747253],"type":"Point"}
}