{
  "type": "Feature",
  "properties": {
    "addr:full":"Ctra Mora, S/n Falset Tarragona 43730",
    "addr:housenumber":"s / n",
    "addr:postcode":"43730",
    "addr:street":"Ctra Mora",
    "iso:country":"ES",
    "sg:address":"Ctra Mora, S/n",
    "sg:city":"Falset",
    "sg:orig_category":"Mec\u00c1nico Del Autom\u00d3vil",
    "sg:phone":"+34 977 83 03 85",
    "sg:postcode":"43730",
    "sg:province":"Tarragona",
    "wof:name":"Just Turon Maria Dels Angels",
    "wof:placetype":"venue"
},
  "geometry": {"coordinates":[0.8157259822,41.1412239075],"type":"Point"}
}