{
  "type": "Feature",
  "properties": {
    "addr:full":"Calle de Churruca, 2 Castellar Ja\u00e9n 23260",
    "addr:housenumber":"2",
    "addr:postcode":"23260",
    "addr:street":"Calle De Churruca",
    "iso:country":"ES",
    "sg:address":"Calle de Churruca, 2",
    "sg:city":"Castellar",
    "sg:orig_category":"Transportes Por Carretera: Lotes Completos, Mercanc\u00cdas Diversas",
    "sg:phone":"+34 953 40 04 58",
    "sg:postcode":"23260",
    "sg:province":"Ja\u00e9n",
    "wof:name":"Gilabert Villarroya Maria Antonia",
    "wof:placetype":"venue"
},
  "geometry": {"coordinates":[-3.1329193115,38.2524681091],"type":"Point"}
}