{
  "type": "Feature",
  "properties": {
    "addr:full":"Carrer de Pobla (la), 48 Sant Vicen\u00c7 Dels Horts Barcelona 08620",
    "addr:housenumber":"48",
    "addr:postcode":"08620",
    "addr:street":"Carrer De Pobla La",
    "iso:country":"ES",
    "sg:address":"Carrer de Pobla (la), 48",
    "sg:city":"Sant Vicen\u00c7 Dels Horts",
    "sg:orig_category":"Peluqueros: De Se\u00d1oras",
    "sg:phone":"+34 936 56 11 04",
    "sg:postcode":"08620",
    "sg:province":"Barcelona",
    "wof:name":"Vilaplana Via Montserrat",
    "wof:placetype":"venue"
},
  "geometry": {"coordinates":[2.010283947,41.3912315369],"type":"Point"}
}