{
  "type": "Feature",
  "properties": {
    "addr:full":"Carr Campcardos, 44 Girona Girona 17006",
    "addr:housenumber":"44",
    "addr:postcode":"17006",
    "addr:street":"Carr Campcardos",
    "iso:country":"ES",
    "sg:address":"Carr Campcardos, 44",
    "sg:city":"Girona",
    "sg:orig_category":"Caf\u00c9s, Bares, Cervecer\u00cdas",
    "sg:phone":"+34 972 23 50 34",
    "sg:postcode":"17006",
    "sg:province":"Girona",
    "wof:name":"Qui\u00f1ones Lopez Catalina",
    "wof:placetype":"venue"
},
  "geometry": {"coordinates":[2.8057079315,41.9740066528],"type":"Point"}
}