{
  "type": "Feature",
  "properties": {
    "iso:country":"ES",
    "sg:address":"Positos, 4",
    "sg:city":"Tiedra",
    "sg:orig_category":"Panader\u00cdas, Pasteler\u00cdas, Boller\u00cda Industriale (fabricaci\u00d3n, Al Por Mayor)",
    "sg:phone":"+34 983 79 14 06",
    "sg:postcode":"47870",
    "sg:province":"Valladolid",
    "wof:name":"Confiteria Viuda De Lisardo Bragado E Hijos S.l.",
    "wof:placetype":"venue"
},
  "geometry": {"coordinates":[-5.2652468681,41.6520233154],"type":"Point"}
}