{
  "type": "Feature",
  "properties": {
    "iso:country":"ES",
    "sg:address":"Calle de Maria De Rozas, 4",
    "sg:city":"Plasencia",
    "sg:orig_category":"Ense\u00d1anza Variada",
    "sg:phone":"+34 927 41 61 55",
    "sg:postcode":"10600",
    "sg:province":"C\u00e1ceres",
    "wof:name":"A La Vera Del Jerte Formacion S.l.",
    "wof:placetype":"venue"
},
  "geometry": {"coordinates":[-6.089407444,40.0272254944],"type":"Point"}
}