{
  "type": "Feature",
  "properties": {
    "iso:country":"ES",
    "sg:address":"Carrer de Ferrocarrils Catalans, S/n",
    "sg:city":"Barcelona",
    "sg:orig_category":"Molduras, Junquillos, Listones Y Molduras Perforadas",
    "sg:phone":"+34 934 23 03 85",
    "sg:postcode":"08038",
    "sg:province":"Barcelona",
    "wof:name":"Trabajadores De Hosteleria De Ferrocarriles S.c.c.l.",
    "wof:placetype":"venue"
},
  "geometry": {"coordinates":[2.1421740055,41.3606300354],"type":"Point"}
}