{
  "type": "Feature",
  "properties": {
    "iso:country":"ES",
    "sg:address":"Via Augusta, 31",
    "sg:city":"Tarragona",
    "sg:orig_category":"Oficinas Y Gesti\u00d3n De Inmuebles",
    "sg:phone":"+34 977 23 55 06",
    "sg:postcode":"43003",
    "sg:province":"Tarragona",
    "wof:name":"Proycom Quality S.l.",
    "wof:placetype":"venue"
},
  "geometry": {"coordinates":[1.2603620291,41.1160202026],"type":"Point"}
}