{
  "type": "Feature",
  "properties": {
    "addr:full":"Carr Emilia Pardo Bazan, 5 Palafrugell Girona 17200",
    "addr:housenumber":"5",
    "addr:postcode":"17200",
    "addr:street":"Carr Emilia Pardo Bazan",
    "iso:country":"ES",
    "sg:address":"Carr Emilia Pardo Bazan, 5",
    "sg:city":"Palafrugell",
    "sg:orig_category":"Cervecer\u00cdas",
    "sg:phone":"+34 972 30 04 34",
    "sg:postcode":"17200",
    "sg:province":"Girona",
    "wof:name":"Mantenimiento Y Servicios Bernal S. L.",
    "wof:placetype":"venue"
},
  "geometry": {"coordinates":[3.1630868912,41.9116210938],"type":"Point"}
}