{
  "type": "Feature",
  "properties": {
    "addr:full":"Cuesta-taco, S/n La Cuesta Santa Cruz De Tenerife 38320",
    "addr:housenumber":"/ n",
    "addr:postcode":"38320",
    "addr:street":"Cuesta-Taco S",
    "iso:country":"ES",
    "sg:address":"Cuesta-taco, S/n",
    "sg:city":"La Cuesta",
    "sg:orig_category":"Quincaller\u00cda (al Por Menor)",
    "sg:phone":"+34 922 65 07 09",
    "sg:postcode":"38320",
    "sg:province":"Santa Cruz De Tenerife",
    "wof:name":"Bolsa De Aguas De Tenerife S.a.",
    "wof:placetype":"venue"
},
  "geometry": {"coordinates":[-16.2880134583,28.468454361],"type":"Point"}
}