{
  "type": "Feature",
  "properties": {
    "addr:full":"Pl Arago, S/n Cambrils Tarragona 43850",
    "addr:housenumber":"s / n",
    "addr:postcode":"43850",
    "addr:street":"Pl Arago",
    "iso:country":"ES",
    "sg:address":"Pl Arago, S/n",
    "sg:city":"Cambrils",
    "sg:orig_category":"Cl\u00cdnicas M\u00c9dicas",
    "sg:phone":"+34 977 36 01 75",
    "sg:postcode":"43850",
    "sg:province":"Tarragona",
    "wof:name":"Fundacio Privada Fass Fundacio Assistenc",
    "wof:placetype":"venue"
},
  "geometry": {"coordinates":[1.0615270138,41.0673980713],"type":"Point"}
}