{
  "type": "Feature",
  "properties": {
    "addr:full":"Calle de Assumpta Glez. Cubertorer, 2 Burriana Castell\u00f3n 12530",
    "addr:housenumber":"2",
    "addr:postcode":"12530",
    "addr:street":"Calle De Assumpta Glez. Cubertorer",
    "iso:country":"ES",
    "sg:address":"Calle de Assumpta Glez. Cubertorer, 2",
    "sg:city":"Burriana",
    "sg:orig_category":"Perfumer\u00cda (al Por Menor)",
    "sg:phone":"+34 964 51 65 75",
    "sg:postcode":"12530",
    "sg:province":"Castell\u00f3n",
    "wof:name":"Fandos Montoro Gloria",
    "wof:placetype":"venue"
},
  "geometry": {"coordinates":[-0.0840215012,39.8887367249],"type":"Point"}
}