{
  "type": "Feature",
  "properties": {
    "iso:country":"ES",
    "sg:address":"Parque De Roma, S/n",
    "sg:city":"Zaragoza",
    "sg:orig_category":"Inmobiliaria (agencias)",
    "sg:phone":"+34 976 46 03 46",
    "sg:postcode":"50010",
    "sg:province":"Zaragoza",
    "wof:name":"Intermediacion De Fincas Aragonesa Rei S.l.",
    "wof:placetype":"venue"
},
  "geometry": {"coordinates":[-0.8985379934,41.6495132446],"type":"Point"}
}