{
  "type": "Feature",
  "properties": {
    "iso:country":"ES",
    "sg:address":"Carr Conradors, 46",
    "sg:city":"Cabaneta",
    "sg:orig_category":"Transportes Mar\u00cdtimos",
    "sg:phone":"+34 971 60 50 97",
    "sg:postcode":"07141",
    "sg:province":"Islas Baleares",
    "wof:name":"Compa\u00f1ia Balear De Cargas S.l.",
    "wof:placetype":"venue"
},
  "geometry": {"coordinates":[2.7445349693,39.6195487976],"type":"Point"}
}