{
  "type": "Feature",
  "properties": {
    "addr:full":"Rua Tomas Maria Mosquera, 6 Carballi\u00f1o Ourense 32500",
    "addr:housenumber":"6",
    "addr:postcode":"32500",
    "addr:street":"Rua Tomas Maria Mosquera",
    "iso:country":"ES",
    "sg:address":"Rua Tomas Maria Mosquera, 6",
    "sg:city":"Carballi\u00f1o",
    "sg:orig_category":"\u00d3ptica: Instrumentos (fabricaci\u00d3n)",
    "sg:phone":"+34 988 27 01 81",
    "sg:postcode":"32500",
    "sg:province":"Ourense",
    "wof:name":"Casino De Carballi\u00f1o",
    "wof:placetype":"venue"
},
  "geometry": {"coordinates":[-8.0793066025,42.4286499023],"type":"Point"}
}