{
  "type": "Feature",
  "properties": {
    "iso:country":"ES",
    "sg:address":"Calle de Enrique Villar, 12",
    "sg:city":"San Lorenzo",
    "sg:orig_category":"Bares, Piano",
    "sg:phone":"+34 968 23 89 62",
    "sg:postcode":"30008",
    "sg:province":"Murcia",
    "wof:name":"Piscis Hosteleria S.l.",
    "wof:placetype":"venue"
},
  "geometry": {"coordinates":[-1.1281189919,37.9876861572],"type":"Point"}
}