{
  "type": "Feature",
  "properties": {
    "iso:country":"ES",
    "sg:address":"Cronista L Polaino, 4",
    "sg:city":"Cazorla",
    "sg:orig_category":"Agentes Generales De Seguros",
    "sg:phone":"+34 953 72 06 24",
    "sg:postcode":"23470",
    "sg:province":"Ja\u00e9n",
    "wof:name":"Navarrete Moreno Francisco",
    "wof:placetype":"venue"
},
  "geometry": {"coordinates":[-3.0030300617,37.9129638672],"type":"Point"}
}