{
  "type": "Feature",
  "properties": {
    "iso:country":"ES",
    "sg:address":"Avda Andalucia (de), 59",
    "sg:city":"Estepa",
    "sg:orig_category":"Suministros Y Materiales Industriales",
    "sg:phone":"+34 955 91 39 13",
    "sg:postcode":"41560",
    "sg:province":"Sevilla",
    "wof:name":"Suministros Industriales Y Agricolas Gonver S.l.",
    "wof:placetype":"venue"
},
  "geometry": {"coordinates":[-4.8797922134,37.2951927185],"type":"Point"}
}