{
  "type": "Feature",
  "properties": {
    "iso:country":"ES",
    "sg:address":"Avda Comuneros, 108",
    "sg:city":"Morales Toro",
    "sg:orig_category":"Material Y Herramientas Agr\u00cdcolas",
    "sg:phone":"+34 980 69 83 23",
    "sg:postcode":"49810",
    "sg:province":"Zamora",
    "wof:name":"Talleres Gil Aranda S.l.",
    "wof:placetype":"venue"
},
  "geometry": {"coordinates":[-5.3064441681,41.5372848511],"type":"Point"}
}