{
  "type": "Feature",
  "properties": {
    "addr:full":"Avda Rioja De (la), 19 Quel La Rioja 26570",
    "addr:housenumber":"19",
    "addr:postcode":"26570",
    "addr:street":"Avda Rioja De La;Rioja",
    "iso:country":"ES",
    "sg:address":"Avda Rioja De (la), 19",
    "sg:city":"Quel",
    "sg:orig_category":"Panader\u00cdas, Panader\u00cdas",
    "sg:phone":"+34 941 40 31 00",
    "sg:postcode":"26570",
    "sg:province":"La Rioja",
    "wof:name":"Blas Alguacil Maria Angeles De",
    "wof:placetype":"venue"
},
  "geometry": {"coordinates":[-2.0563650131,42.233341217],"type":"Point"}
}