{
  "type": "Feature",
  "properties": {
    "addr:full":"Calle de Francisco Silvela, 19 Madrid Madrid 28028",
    "addr:housenumber":"19",
    "addr:postcode":"madrid;28028",
    "addr:street":"Calle De Francisco Silvela",
    "iso:country":"ES",
    "sg:address":"Calle de Francisco Silvela, 19",
    "sg:city":"Madrid",
    "sg:orig_category":"Procuradores",
    "sg:phone":"+34 914 01 04 36",
    "sg:postcode":"28028",
    "sg:province":"Madrid",
    "wof:name":"Montes Agusti Rosina",
    "wof:placetype":"venue"
},
  "geometry": {"coordinates":[-3.6711809635,40.4304962158],"type":"Point"}
}