{
  "type": "Feature",
  "properties": {
    "addr:full":"Av Joaquim De Sagrera, 106 Terrassa Barcelona 08224",
    "addr:housenumber":"106",
    "addr:postcode":"08224",
    "addr:street":"Av Joaquim De Sagrera",
    "iso:country":"ES",
    "sg:address":"Av Joaquim De Sagrera, 106",
    "sg:city":"Terrassa",
    "sg:orig_category":"Puertas Y Portales",
    "sg:phone":"+34 937 80 86 18",
    "sg:postcode":"08224",
    "sg:province":"Barcelona",
    "wof:name":"Rincon Romero Dionisio",
    "wof:placetype":"venue"
},
  "geometry": {"coordinates":[2.0038499832,41.553314209],"type":"Point"}
}