{
  "type": "Feature",
  "properties": {
    "iso:country":"ES",
    "sg:address":"Calle de Rosas, 8",
    "sg:city":"Fuengirola",
    "sg:orig_category":"Piscinas, Accesorios, Suministros (fabricaci\u00d3n, Al Por Mayor)",
    "sg:phone":"+34 952 47 61 17",
    "sg:postcode":"29640",
    "sg:province":"M\u00e1laga",
    "wof:name":"Espa\u00f1a Rondon Matias",
    "wof:placetype":"venue"
},
  "geometry": {"coordinates":[-4.6239790916,36.5414886475],"type":"Point"}
}