{
  "type": "Feature",
  "properties": {
    "iso:country":"ES",
    "sg:address":"Abejeras, 45",
    "sg:city":"Iru\u00f1a",
    "sg:orig_category":"Promotores Constructores",
    "sg:phone":"+34 948 15 22 28",
    "sg:postcode":"31007",
    "sg:province":"Navarra",
    "wof:name":"Construcciones Eceolaza S.a.",
    "wof:placetype":"venue"
},
  "geometry": {"coordinates":[-1.6472920179,42.8041343689],"type":"Point"}
}