{
  "type": "Feature",
  "properties": {
    "iso:country":"ES",
    "sg:address":"Avda Carlos Francisco Lorenzo Navarro, 10",
    "sg:city":"Monta\u00e7a Tenisca",
    "sg:orig_category":"Servicios De Telecomunicaciones",
    "sg:phone":"+34 922 46 21 04",
    "sg:postcode":"38760",
    "sg:province":"Santa Cruz De Tenerife",
    "wof:name":"Instalaciones Electricas Alcorac S.l.",
    "wof:placetype":"venue"
},
  "geometry": {"coordinates":[-17.9153308868,28.658033371],"type":"Point"}
}