{
  "type": "Feature",
  "properties": {
    "addr:full":"Calle de Doctor Vila, 12 Rua De Valdeorras Ourense 32350",
    "addr:housenumber":"12",
    "addr:postcode":"32350",
    "addr:street":"Calle De Doctor Vila;Rua De",
    "iso:country":"ES",
    "sg:address":"Calle de Doctor Vila, 12",
    "sg:city":"Rua De Valdeorras",
    "sg:orig_category":"Quincaller\u00cda (al Por Menor)",
    "sg:phone":"+34 988 31 06 18",
    "sg:postcode":"32350",
    "sg:province":"Ourense",
    "wof:name":"Garcia Abeledo Angel",
    "wof:placetype":"venue"
},
  "geometry": {"coordinates":[-7.114481926,42.3937339783],"type":"Point"}
}