{
  "type": "Feature",
  "properties": {
    "iso:country":"ES",
    "sg:address":"Calle de Alfredo Corrochano, 67",
    "sg:city":"Malaga",
    "sg:orig_category":"Fabricaci\u00d3n De Enlosados, Soler\u00cdas",
    "sg:phone":"+34 952 33 70 97",
    "sg:postcode":"29006",
    "sg:province":"M\u00e1laga",
    "wof:name":"Azulejos Y Pavimentos San Juan S.l.",
    "wof:placetype":"venue"
},
  "geometry": {"coordinates":[-4.4803547859,36.7136497498],"type":"Point"}
}