{
  "type": "Feature",
  "properties": {
    "addr:full":"Avda 28 De Febrero, 77 Benahadux Almer\u00eda 04410",
    "addr:housenumber":"77",
    "addr:postcode":"04410",
    "addr:street":"Avda 28 De Febrero",
    "iso:country":"ES",
    "sg:address":"Avda 28 De Febrero, 77",
    "sg:city":"Benahadux",
    "sg:orig_category":"Inmobiliaria (agencias)",
    "sg:phone":"+34 950 31 12 78",
    "sg:postcode":"04410",
    "sg:province":"Almer\u00eda",
    "wof:name":"Inversiones Y Promociones Urbasol Sl",
    "wof:placetype":"venue"
},
  "geometry": {"coordinates":[-2.4606389999,36.9262466431],"type":"Point"}
}