{
  "type": "Feature",
  "properties": {
    "addr:full":"Carr Juan De Austria, 6 Godella Valencia 46110",
    "addr:housenumber":"6",
    "addr:postcode":"46110",
    "addr:street":"Carr Juan De Austria",
    "iso:country":"ES",
    "sg:address":"Carr Juan De Austria, 6",
    "sg:city":"Godella",
    "sg:orig_category":"Mec\u00c1nico Del Autom\u00d3vil",
    "sg:phone":"+34 963 90 24 36",
    "sg:postcode":"46110",
    "sg:province":"Valencia",
    "wof:name":"Enguix Alca\u00f1iz Vicente",
    "wof:placetype":"venue"
},
  "geometry": {"coordinates":[-0.4154840112,39.5255889893],"type":"Point"}
}