{
  "type": "Feature",
  "properties": {
    "addr:full":"Avda Alcalde Federico Molina, 28 Huelva Huelva 21006",
    "addr:housenumber":"28",
    "addr:postcode":"21006",
    "addr:street":"Avda Alcalde Federico Molina",
    "iso:country":"ES",
    "sg:address":"Avda Alcalde Federico Molina, 28",
    "sg:city":"Huelva",
    "sg:orig_category":"Hielo Artificial (fabricaci\u00d3n, Distribuci\u00d3n)",
    "sg:phone":"+34 959 23 37 74",
    "sg:postcode":"21006",
    "sg:province":"Huelva",
    "wof:name":"Hernandez Vilaplana Leonardo",
    "wof:placetype":"venue"
},
  "geometry": {"coordinates":[-6.9350662231,37.2577590942],"type":"Point"}
}