{
  "type": "Feature",
  "properties": {
    "iso:country":"ES",
    "sg:address":"Calle de Los Fueros, 11",
    "sg:city":"Algorta",
    "sg:orig_category":"Procuradores",
    "sg:phone":"+34 944 91 03 35",
    "sg:postcode":"48992",
    "sg:province":"Vizcaya",
    "wof:name":"Gonzalez Yacob Gabriela",
    "wof:placetype":"venue"
},
  "geometry": {"coordinates":[-3.0060620308,43.3447799683],"type":"Point"}
}