{
  "type": "Feature",
  "properties": {
    "addr:full":"Calle de Eduardo Morales, 31 Madrid Madrid 28025",
    "addr:housenumber":"31",
    "addr:postcode":"madrid;28025",
    "addr:street":"Calle De Eduardo Morales",
    "iso:country":"ES",
    "sg:address":"Calle de Eduardo Morales, 31",
    "sg:city":"Madrid",
    "sg:orig_category":"Molduras, Junquillos, Listones Y Molduras Perforadas",
    "sg:phone":"+34 914 66 68 75",
    "sg:postcode":"28025",
    "sg:province":"Madrid",
    "wof:name":"Mera Crespo Maria Bego\u00f1a",
    "wof:placetype":"venue"
},
  "geometry": {"coordinates":[-3.7373440266,40.3872566223],"type":"Point"}
}