{
  "type": "Feature",
  "properties": {
    "addr:full":"Carr Napols, 28 Badalona Barcelona 08914",
    "addr:housenumber":"28",
    "addr:postcode":"08914",
    "addr:street":"Carr Napols",
    "iso:country":"ES",
    "sg:address":"Carr Napols, 28",
    "sg:city":"Badalona",
    "sg:orig_category":"Alimentaci\u00d3n General (al Por Menor)",
    "sg:phone":"+34 934 60 51 39",
    "sg:postcode":"08914",
    "sg:province":"Barcelona",
    "wof:name":"Jose Gracia Monzon E Hijos S.l.",
    "wof:placetype":"venue"
},
  "geometry": {"coordinates":[2.2251229286,41.4400177002],"type":"Point"}
}