{
  "type": "Feature",
  "properties": {
    "iso:country":"ES",
    "sg:address":"Carrer de Sant Pere, S/n",
    "sg:city":"Pla Del Penedes",
    "sg:orig_category":"Fabricaci\u00d3n, Distribuci\u00d3n De Material Para La Climatizaci\u00d3n, Aireaci\u00d3n Y Ventilaci\u00d3n",
    "sg:phone":"+34 938 98 85 88",
    "sg:postcode":"08733",
    "sg:province":"Barcelona",
    "wof:name":"Mochisa S.l.",
    "wof:placetype":"venue"
},
  "geometry": {"coordinates":[1.7134590149,41.4179534912],"type":"Point"}
}