{
  "type": "Feature",
  "properties": {
    "iso:country":"ES",
    "sg:address":"Calle de Explorador Andres, 36",
    "sg:city":"Valencia",
    "sg:orig_category":"Ropa Para Se\u00d1oras (al Por Menor)",
    "sg:phone":"+34 963 71 61 87",
    "sg:postcode":"46022",
    "sg:province":"Valencia",
    "wof:name":"Roberto De Darro S.l",
    "wof:placetype":"venue"
},
  "geometry": {"coordinates":[-0.345077008,39.4714584351],"type":"Point"}
}