{
  "type": "Feature",
  "properties": {
    "addr:full":"Calle de Cardona, 20 Gijon Asturias 33213",
    "addr:housenumber":"20",
    "addr:postcode":"33213",
    "addr:street":"Calle De Cardona",
    "iso:country":"ES",
    "sg:address":"Calle de Cardona, 20",
    "sg:city":"Gijon",
    "sg:orig_category":"Electricidad: Equipos Industriales, Componentes (fabricaci\u00d3n)",
    "sg:phone":"+34 985 31 19 17",
    "sg:postcode":"33213",
    "sg:province":"Asturias",
    "wof:name":"Tecnicas Electricas Mayra S.l.",
    "wof:placetype":"venue"
},
  "geometry": {"coordinates":[-5.7047290802,43.5408668518],"type":"Point"}
}