{
  "type": "Feature",
  "properties": {
    "iso:country":"ES",
    "sg:address":"Via Julia, 140",
    "sg:city":"Barcelona",
    "sg:orig_category":"Electrodom\u00c9sticos (fabricaci\u00d3n, Al Por Mayor)",
    "sg:phone":"+34 933 50 25 00",
    "sg:postcode":"08016",
    "sg:province":"Barcelona",
    "sg:website":"www.miro.es",
    "wof:name":"Establecimientos Miro S.l.",
    "wof:placetype":"venue"
},
  "geometry": {"coordinates":[2.1791319847,41.444065094],"type":"Point"}
}