{
  "type": "Feature",
  "properties": {
    "addr:full":"Calle de Rio Vello, S/n Arzua A Coru\u00f1a 15810",
    "addr:housenumber":"s",
    "addr:postcode":"15810",
    "addr:street":"Calle De Rio Vello;/ N;Corun\u0303A",
    "iso:country":"ES",
    "sg:address":"Calle de Rio Vello, S/n",
    "sg:city":"Arzua",
    "sg:orig_category":"Plomeros",
    "sg:phone":"+34 981 50 04 55",
    "sg:postcode":"15810",
    "sg:province":"A Coru\u00f1a",
    "wof:name":"Vaamonde Martinez Francisco",
    "wof:placetype":"venue"
},
  "geometry": {"coordinates":[-8.1634550095,42.9267272949],"type":"Point"}
}