{
  "type": "Feature",
  "properties": {
    "addr:full":"Calle de Calzadilla Del Valle, 12 Lucena C\u00f3rdoba 14900",
    "addr:housenumber":"12",
    "addr:postcode":"14900",
    "addr:street":"Calle De Calzadilla Del Valle",
    "iso:country":"ES",
    "sg:address":"Calle de Calzadilla Del Valle, 12",
    "sg:city":"Lucena",
    "sg:orig_category":"Mec\u00c1nico Del Autom\u00d3vil",
    "sg:phone":"+34 957 50 23 19",
    "sg:postcode":"14900",
    "sg:province":"C\u00f3rdoba",
    "wof:name":"Serrano Bartolesis Antonio",
    "wof:placetype":"venue"
},
  "geometry": {"coordinates":[-4.4947638512,37.4069061279],"type":"Point"}
}