{
  "type": "Feature",
  "properties": {
    "iso:country":"ES",
    "sg:address":"Calle de Arquitecto Segura De Lago, 40",
    "sg:city":"Valencia",
    "sg:orig_category":"Venta, Instalaci\u00d3n, Reparaci\u00d3n De Antenas Para Televisi\u00d3n",
    "sg:phone":"+34 963 78 62 60",
    "sg:postcode":"46014",
    "sg:province":"Valencia",
    "wof:name":"Banacloche Garcia Jose Vicente",
    "wof:placetype":"venue"
},
  "geometry": {"coordinates":[-0.4024339914,39.4524879456],"type":"Point"}
}