{
  "type": "Feature",
  "properties": {
    "addr:full":"Ctra Chorro, S/n Navafria Segovia 40161",
    "addr:housenumber":"s / n",
    "addr:postcode":"40161",
    "addr:street":"Ctra Chorro",
    "iso:country":"ES",
    "sg:address":"Ctra Chorro, S/n",
    "sg:city":"Navafria",
    "sg:orig_category":"Promotores Constructores",
    "sg:phone":"+34 921 50 62 81",
    "sg:postcode":"40161",
    "sg:province":"Segovia",
    "wof:name":"Dragados S.a.",
    "wof:placetype":"venue"
},
  "geometry": {"coordinates":[-3.8183839321,41.0548782349],"type":"Point"}
}