{
  "type": "Feature",
  "properties": {
    "iso:country":"ES",
    "sg:address":"Rua Luis Calvo, 29",
    "sg:city":"Carballo",
    "sg:orig_category":"Inform\u00c1tica, Ofim\u00c1tica (estudios, Asesor\u00cda, Ingenier\u00cda, Formaci\u00d3n)",
    "sg:phone":"+34 981 70 40 85",
    "sg:postcode":"15100",
    "sg:province":"A Coru\u00f1a",
    "wof:name":"Teijeira Y Carballo Sll",
    "wof:placetype":"venue"
},
  "geometry": {"coordinates":[-8.6935043335,43.2123985291],"type":"Point"}
}