{
  "type": "Feature",
  "properties": {
    "iso:country":"ES",
    "sg:address":"Calle de Alboraya, 50",
    "sg:city":"Valencia",
    "sg:orig_category":"Inmobiliaria (agencias)",
    "sg:phone":"+34 963 93 77 33",
    "sg:postcode":"46010",
    "sg:province":"Valencia",
    "wof:name":"Expofinques 2000 S.a.",
    "wof:placetype":"venue"
},
  "geometry": {"coordinates":[-0.3691470921,39.4847412109],"type":"Point"}
}