{
  "type": "Feature",
  "properties": {
    "addr:full":"Calle de Mayorazgo, 24 Leganes Madrid 28915",
    "addr:housenumber":"24",
    "addr:postcode":"28915",
    "addr:street":"Calle De Mayorazgo",
    "iso:country":"ES",
    "sg:address":"Calle de Mayorazgo, 24",
    "sg:city":"Leganes",
    "sg:orig_category":"Herboristas (al Por Menor)",
    "sg:phone":"+34 916 80 78 12",
    "sg:postcode":"28915",
    "sg:province":"Madrid",
    "wof:name":"Salvador Sampedro Maria Eulalia",
    "wof:placetype":"venue"
},
  "geometry": {"coordinates":[-3.7511880398,40.3374176025],"type":"Point"}
}