{
  "type": "Feature",
  "properties": {
    "addr:full":"Calle de Valverde, 1 Torredelcampo Ja\u00e9n 23640",
    "addr:housenumber":"1",
    "addr:postcode":"23640",
    "addr:street":"Calle De Valverde;Jae\u0301N",
    "iso:country":"ES",
    "sg:address":"Calle de Valverde, 1",
    "sg:city":"Torredelcampo",
    "sg:orig_category":"Cajas Para Embalar",
    "sg:phone":"+34 953 56 70 11",
    "sg:postcode":"23640",
    "sg:province":"Ja\u00e9n",
    "sg:website":"www.ruralvia.com",
    "wof:name":"Caja Rural De Jaen",
    "wof:placetype":"venue"
},
  "geometry": {"coordinates":[-3.8971810341,37.7706489563],"type":"Point"}
}