{
  "type": "Feature",
  "properties": {
    "iso:country":"ES",
    "sg:address":"Calle de Timanfaya, 1",
    "sg:city":"Puerto Del Carmen",
    "sg:orig_category":"Marroquiner\u00cda (confecci\u00d3n)",
    "sg:phone":"+34 928 51 02 17",
    "sg:postcode":"35510",
    "sg:province":"Las Palmas",
    "wof:name":"Garcia Prieto Maria",
    "wof:placetype":"venue"
},
  "geometry": {"coordinates":[-13.6669988632,28.9206790924],"type":"Point"}
}