{
  "type": "Feature",
  "properties": {
    "iso:country":"ES",
    "sg:address":"Calle de Cirilo Amoros, 28",
    "sg:city":"Valencia",
    "sg:orig_category":"Muebles Y Accesorios Para Cocinas Y Cuartos De Ba\u00d1o (al Por Menor)",
    "sg:phone":"+34 963 51 01 65",
    "sg:postcode":"46004",
    "sg:province":"Valencia",
    "wof:name":"Ares Decor S.l.",
    "wof:placetype":"venue"
},
  "geometry": {"coordinates":[-0.3721981943,39.4670066833],"type":"Point"}
}