{
  "type": "Feature",
  "properties": {
    "addr:full":"Escultor Juan De Juni, 3 Alcala Guadaira Sevilla 41500",
    "addr:housenumber":"3",
    "addr:postcode":"41500",
    "addr:street":"Escultor Juan De Juni",
    "iso:country":"ES",
    "sg:address":"Escultor Juan De Juni, 3",
    "sg:city":"Alcala Guadaira",
    "sg:orig_category":"Cl\u00cdnicas Dentales",
    "sg:phone":"+34 954 10 12 13",
    "sg:postcode":"41500",
    "sg:province":"Sevilla",
    "wof:name":"Velez Morales Jorge",
    "wof:placetype":"venue"
},
  "geometry": {"coordinates":[-5.8247032166,37.3409080505],"type":"Point"}
}