{
  "type": "Feature",
  "properties": {
    "addr:full":"Calle de Trujillo, 12 Sierra Fuentes C\u00e1ceres 10181",
    "addr:housenumber":"12",
    "addr:postcode":"10181",
    "addr:street":"Calle De Trujillo;Sierra Fuentes Ca\u0301Ceres",
    "iso:country":"ES",
    "sg:address":"Calle de Trujillo, 12",
    "sg:city":"Sierra Fuentes",
    "sg:orig_category":"Negocio De Materiales De Construcci\u00d3n",
    "sg:phone":"+34 927 20 11 77",
    "sg:postcode":"10181",
    "sg:province":"C\u00e1ceres",
    "wof:name":"Martin Lopez Facundo",
    "wof:placetype":"venue"
},
  "geometry": {"coordinates":[-6.2737979889,39.4374198914],"type":"Point"}
}