{
  "type": "Feature",
  "properties": {
    "iso:country":"ES",
    "sg:address":"Calle de Caudal, 58",
    "sg:city":"Malaga",
    "sg:orig_category":"Fabricaci\u00d3n, Distribuci\u00d3n De Material Para La Climatizaci\u00d3n, Aireaci\u00d3n Y Ventilaci\u00d3n",
    "sg:phone":"+34 952 34 11 04",
    "sg:postcode":"29006",
    "sg:province":"M\u00e1laga",
    "wof:name":"Maquinaria De Lavado Andaluza S.l.",
    "wof:placetype":"venue"
},
  "geometry": {"coordinates":[-4.4852714539,36.7124481201],"type":"Point"}
}