{
  "type": "Feature",
  "properties": {
    "iso:country":"ES",
    "sg:address":"Carrer de Lloma (la), 12",
    "sg:city":"Muro Alcoy",
    "sg:orig_category":"Caf\u00c9s, Bares, Cervecer\u00cdas",
    "sg:phone":"+34 965 53 22 54",
    "sg:postcode":"03830",
    "sg:province":"Alicante",
    "wof:name":"Lescala Caffe Cb",
    "wof:placetype":"venue"
},
  "geometry": {"coordinates":[-0.4414289892,38.7812538147],"type":"Point"}
}