{
  "type": "Feature",
  "properties": {
    "addr:full":"Carr Major, S/n Benifaio Valencia 46450",
    "addr:housenumber":"s",
    "addr:postcode":"46450",
    "addr:street":"Carr Major;/ N",
    "iso:country":"ES",
    "sg:address":"Carr Major, S/n",
    "sg:city":"Benifaio",
    "sg:orig_category":"Dietistas",
    "sg:phone":"+34 961 79 46 10",
    "sg:postcode":"46450",
    "sg:province":"Valencia",
    "wof:name":"Jare\u00f1o Polo Carmen",
    "wof:placetype":"venue"
},
  "geometry": {"coordinates":[-0.427139014,39.2845306396],"type":"Point"}
}