{
  "type": "Feature",
  "properties": {
    "addr:full":"Calle de San Carlos Borromeo, 2 Segovia Segovia 40002",
    "addr:housenumber":"2",
    "addr:postcode":"40002",
    "addr:street":"Calle De",
    "iso:country":"ES",
    "sg:address":"Calle de San Carlos Borromeo, 2",
    "sg:city":"Segovia",
    "sg:orig_category":"Cooperativas Agr\u00cdcolas",
    "sg:phone":"+34 921 43 11 51",
    "sg:postcode":"40002",
    "sg:province":"Segovia",
    "wof:name":"Cooperativa Empleados De Banca",
    "wof:placetype":"venue"
},
  "geometry": {"coordinates":[-4.118118763,40.9414215088],"type":"Point"}
}