{
  "type": "Feature",
  "properties": {
    "addr:full":"Avda Mediterraneo, 238 Bahia De Javea Alicante 03730",
    "addr:housenumber":"238",
    "addr:postcode":"03730",
    "addr:street":"Avda Mediterraneo;Bahia De Javea Alicante",
    "iso:country":"ES",
    "sg:address":"Avda Mediterraneo, 238",
    "sg:city":"Bahia De Javea",
    "sg:orig_category":"Administradores De Bienes Y Delegados De Comunidades De Propietarios",
    "sg:phone":"+34 966 46 18 10",
    "sg:postcode":"03730",
    "sg:province":"Alicante",
    "sg:website":"www.juansoler.net",
    "wof:name":"Soler Pardo Juan",
    "wof:placetype":"venue"
},
  "geometry": {"coordinates":[0.1570300013,38.7885093689],"type":"Point"}
}