{
  "type": "Feature",
  "properties": {
    "addr:full":"Avda Vazquez Diaz, 18 Palma Rio C\u00f3rdoba 14700",
    "addr:housenumber":"18",
    "addr:postcode":"14700",
    "addr:street":"Avda Vazquez Diaz;Rio Co\u0301Rdoba",
    "iso:country":"ES",
    "sg:address":"Avda Vazquez Diaz, 18",
    "sg:city":"Palma Rio",
    "sg:orig_category":"Comercio, Reparaci\u00d3n De Motocicletas, Bicicletas Y Piezas Sueltas",
    "sg:phone":"+34 957 64 33 16",
    "sg:postcode":"14700",
    "sg:province":"C\u00f3rdoba",
    "wof:name":"Caro Fuentes Francisco",
    "wof:placetype":"venue"
},
  "geometry": {"coordinates":[-5.2778191566,37.6997756958],"type":"Point"}
}