{
  "type": "Feature",
  "properties": {
    "addr:full":"Bloc La Mussara, 13 Sant Pere I Sant Pau Tarragona 43007",
    "addr:housenumber":"13",
    "addr:postcode":"43007",
    "iso:country":"ES",
    "sg:address":"Bloc La Mussara, 13",
    "sg:city":"Sant Pere I Sant Pau",
    "sg:orig_category":"Inmobiliaria (agencias)",
    "sg:phone":"+34 977 24 94 24",
    "sg:postcode":"43007",
    "sg:province":"Tarragona",
    "wof:name":"Tarraco Inmobiliaria Del Hogar S.l.",
    "wof:placetype":"venue"
},
  "geometry": {"coordinates":[1.2959779501,41.1377334595],"type":"Point"}
}