{
  "type": "Feature",
  "properties": {
    "addr:full":"Calle de Pez Espada, 54 Sevilla Sevilla 41015",
    "addr:housenumber":"54",
    "addr:postcode":"41015",
    "addr:street":"Calle De Pez Espada",
    "iso:country":"ES",
    "sg:address":"Calle de Pez Espada, 54",
    "sg:city":"Sevilla",
    "sg:orig_category":"Importaci\u00d3n",
    "sg:phone":"+34 954 91 54 70",
    "sg:postcode":"41015",
    "sg:province":"Sevilla",
    "wof:name":"Lerida Ojeda Jose",
    "wof:placetype":"venue"
},
  "geometry": {"coordinates":[-5.9825630188,37.4319877625],"type":"Point"}
}