{
  "type": "Feature",
  "properties": {
    "iso:country":"ES",
    "sg:address":"Mayor, 15",
    "sg:city":"Atarrabia",
    "sg:orig_category":"Inmobiliaria (agencias)",
    "sg:phone":"+34 948 38 46 05",
    "sg:postcode":"31610",
    "sg:province":"Navarra",
    "wof:name":"Naranjo Gonzalez Manuel De Jesus",
    "wof:placetype":"venue"
},
  "geometry": {"coordinates":[-1.6083749533,42.83152771],"type":"Point"}
}