{
  "type": "Feature",
  "properties": {
    "addr:full":"Calle de Susana Gonzalez, 40 Bembibre Le\u00f3n 24300",
    "addr:housenumber":"40",
    "addr:postcode":"24300",
    "addr:street":"Calle De Susana Gonzalez;Leo\u0301N",
    "iso:country":"ES",
    "sg:address":"Calle de Susana Gonzalez, 40",
    "sg:city":"Bembibre",
    "sg:orig_category":"Peluqueros: De Se\u00d1oras",
    "sg:phone":"+34 987 51 14 53",
    "sg:postcode":"24300",
    "sg:province":"Le\u00f3n",
    "wof:name":"Alija Bernardo Victor Vicente",
    "wof:placetype":"venue"
},
  "geometry": {"coordinates":[-6.4212756157,42.6110649109],"type":"Point"}
}