{
  "type": "Feature",
  "properties": {
    "addr:full":"Avda Concepcion Arenal, 54 Praia Pontevedra 36950",
    "addr:housenumber":"54",
    "addr:postcode":"36950",
    "addr:street":"Avda Concepcion Arenal",
    "iso:country":"ES",
    "sg:address":"Avda Concepcion Arenal, 54",
    "sg:city":"Praia",
    "sg:orig_category":"Mercer\u00cda, Lencer\u00cda (al Por Menor)",
    "sg:phone":"+34 986 31 40 77",
    "sg:postcode":"36950",
    "sg:province":"Pontevedra",
    "wof:name":"Rua Gayo Francisco Javier",
    "wof:placetype":"venue"
},
  "geometry": {"coordinates":[-8.738442421,42.2772254944],"type":"Point"}
}