{
  "type": "Feature",
  "properties": {
    "iso:country":"ES",
    "sg:address":"Avda Mancha, 24",
    "sg:city":"Villaca\u00f1as",
    "sg:orig_category":"Agentes Generales De Seguros",
    "sg:phone":"+34 925 16 03 06",
    "sg:postcode":"45860",
    "sg:province":"Toledo",
    "wof:name":"Mapfre Servicios De Informatica",
    "wof:placetype":"venue"
},
  "geometry": {"coordinates":[-3.3319368362,39.6236000061],"type":"Point"}
}