{
  "type": "Feature",
  "properties": {
    "iso:country":"ES",
    "sg:address":"Calle de Comercio, 2",
    "sg:city":"Tahal",
    "sg:orig_category":"Cajas De Ahorro",
    "sg:phone":"+34 950 43 48 19",
    "sg:postcode":"04275",
    "sg:province":"Almer\u00eda",
    "sg:website":"www.unicaja.es",
    "wof:name":"Unicaja",
    "wof:placetype":"venue"
},
  "geometry": {"coordinates":[-2.2841949463,37.2279090881],"type":"Point"}
}