{
  "type": "Feature",
  "properties": {
    "iso:country":"ES",
    "sg:address":"Calle de Temprado, 2",
    "sg:city":"Teruel",
    "sg:orig_category":"Asociaciones Y Clubs Deportivos",
    "sg:phone":"+34 978 60 23 09",
    "sg:postcode":"44001",
    "sg:province":"Teruel",
    "wof:name":"Asociacion Deportiva Cazadores El Torico",
    "wof:placetype":"venue"
},
  "geometry": {"coordinates":[-1.1078423262,40.343547821],"type":"Point"}
}