{
  "type": "Feature",
  "properties": {
    "addr:full":"Calle de San Millan, 20 Logro\u00f1o La Rioja 26004",
    "addr:housenumber":"20",
    "addr:postcode":"26004",
    "addr:street":"Calle De San Millan;Rioja",
    "iso:country":"ES",
    "sg:address":"Calle de San Millan, 20",
    "sg:city":"Logro\u00f1o",
    "sg:orig_category":"Peluqueros: De Se\u00d1oras",
    "sg:phone":"+34 941 24 39 53",
    "sg:postcode":"26004",
    "sg:province":"La Rioja",
    "wof:name":"Saenz Barron Susana",
    "wof:placetype":"venue"
},
  "geometry": {"coordinates":[-2.432092905,42.4665565491],"type":"Point"}
}