{
  "type": "Feature",
  "properties": {
    "addr:full":"Cno Fuentes, S/n Aspe Alicante 03680",
    "addr:housenumber":"s",
    "addr:postcode":"03680",
    "addr:street":"Cno Fuentes;/ N",
    "iso:country":"ES",
    "sg:address":"Cno Fuentes, S/n",
    "sg:city":"Aspe",
    "sg:orig_category":"Ba\u00d1os Y Duchas P\u00dablicos",
    "sg:phone":"+34 965 49 54 30",
    "sg:postcode":"03680",
    "sg:province":"Alicante",
    "wof:name":"Eurotel Sur S.l.",
    "wof:placetype":"venue"
},
  "geometry": {"coordinates":[-0.7689840198,38.3471984863],"type":"Point"}
}