{
  "type": "Feature",
  "properties": {
    "iso:country":"ES",
    "sg:address":"Calle de Antonio De Leyva, 83",
    "sg:city":"Zaragoza",
    "sg:orig_category":"Molduras, Junquillos, Listones Y Molduras Perforadas",
    "sg:phone":"+34 976 33 49 08",
    "sg:postcode":"50011",
    "sg:province":"Zaragoza",
    "wof:name":"Felipe Diez Alejandra",
    "wof:placetype":"venue"
},
  "geometry": {"coordinates":[-0.9290465117,41.6515350342],"type":"Point"}
}