{
  "type": "Feature",
  "properties": {
    "iso:country":"ES",
    "sg:address":"Granadillos, S/n",
    "sg:city":"Baeza",
    "sg:orig_category":"Producci\u00d3n De Abonos Y De Fertilizantes",
    "sg:phone":"+34 953 74 07 63",
    "sg:postcode":"23440",
    "sg:province":"Ja\u00e9n",
    "wof:name":"Aniceto Aladarios E Hijo S.l.",
    "wof:placetype":"venue"
},
  "geometry": {"coordinates":[-3.4693629742,37.9995994568],"type":"Point"}
}