{
  "type": "Feature",
  "properties": {
    "iso:country":"ES",
    "sg:address":"Calle de Maestro Mu\u00d1oz Molleda, 23",
    "sg:city":"Linea De La Concepcion",
    "sg:orig_category":"Sociedades, Compa\u00d1\u00cdas Aseguradoras",
    "sg:phone":"+34 956 76 04 05",
    "sg:postcode":"11300",
    "sg:province":"C\u00e1diz",
    "wof:name":"Camacho Real Rosa Maria",
    "wof:placetype":"venue"
},
  "geometry": {"coordinates":[-5.3464407921,36.1629676819],"type":"Point"}
}