{
  "type": "Feature",
  "properties": {
    "addr:full":"Pl Esglesia, 3 Vallmoll Tarragona 43144",
    "addr:housenumber":"3",
    "addr:postcode":"43144",
    "addr:street":"Pl Esglesia",
    "iso:country":"ES",
    "sg:address":"Pl Esglesia, 3",
    "sg:city":"Vallmoll",
    "sg:orig_category":"Iglesia Cat\u00d3lica",
    "sg:phone":"+34 977 63 71 95",
    "sg:postcode":"43144",
    "sg:province":"Tarragona",
    "wof:name":"Arquebisbat De Tarragona",
    "wof:placetype":"venue"
},
  "geometry": {"coordinates":[1.2231955528,41.2349815369],"type":"Point"}
}