{
  "type": "Feature",
  "properties": {
    "iso:country":"ES",
    "sg:address":"Avda Hernan Cortes, 52",
    "sg:city":"Caceres",
    "sg:orig_category":"Motocicletas (agentes, Concesionarios)",
    "sg:phone":"+34 927 22 42 70",
    "sg:postcode":"10004",
    "sg:province":"C\u00e1ceres",
    "wof:name":"Pelin S.l.",
    "wof:placetype":"venue"
},
  "geometry": {"coordinates":[-6.3791899681,39.4770736694],"type":"Point"}
}