{
  "type": "Feature",
  "properties": {
    "iso:country":"ES",
    "sg:address":"Calle de Bolea, 100",
    "sg:city":"Elche Sierra",
    "sg:orig_category":"Lavado, Limpieza De Veh\u00cdculos",
    "sg:phone":"+34 967 41 04 12",
    "sg:postcode":"02430",
    "sg:province":"Albacete",
    "wof:name":"Alarcon Garcia Antonio",
    "wof:placetype":"venue"
},
  "geometry": {"coordinates":[-1.6613692045,38.5615997314],"type":"Point"}
}