{
  "type": "Feature",
  "properties": {
    "addr:full":"Rbla Doctor Perez, 32 Santa Ursula Santa Cruz De Tenerife 38390",
    "addr:housenumber":"32",
    "addr:postcode":"38390",
    "addr:street":"Rbla Doctor Perez",
    "iso:country":"ES",
    "sg:address":"Rbla Doctor Perez, 32",
    "sg:city":"Santa Ursula",
    "sg:orig_category":"Reposter\u00cdas",
    "sg:phone":"+34 922 30 17 14",
    "sg:postcode":"38390",
    "sg:province":"Santa Cruz De Tenerife",
    "wof:name":"Toledo Garcia Pedro",
    "wof:placetype":"venue"
},
  "geometry": {"coordinates":[-16.4917697906,28.425359726],"type":"Point"}
}