{
  "type": "Feature",
  "properties": {
    "iso:country":"ES",
    "sg:address":"Cmno Mesa (de La), S/n",
    "sg:city":"Campo Real",
    "sg:orig_category":"Aceites Y Grasas Alimentarias (fabricaci\u00d3n, Al Por Mayor)",
    "sg:phone":"+34 918 73 33 17",
    "sg:postcode":"28510",
    "sg:province":"Madrid",
    "sg:website":"www.aceitecamporreal.com",
    "wof:name":"Aceite De Oliva Campo Real S.l.",
    "wof:placetype":"venue"
},
  "geometry": {"coordinates":[-3.3750386238,40.3428535461],"type":"Point"}
}