{
  "type": "Feature",
  "properties": {
    "iso:country":"ES",
    "sg:address":"Carrer de L'equador, 27",
    "sg:city":"Barcelona",
    "sg:orig_category":"Frutas, Legumbres Frescas Y Tempranas (al Por Menor)",
    "sg:phone":"+34 933 22 36 64",
    "sg:postcode":"08029",
    "sg:province":"Barcelona",
    "wof:name":"Aznar Martorell Francisco",
    "wof:placetype":"venue"
},
  "geometry": {"coordinates":[2.1409029961,41.3851737976],"type":"Point"}
}