{
  "type": "Feature",
  "properties": {
    "addr:full":"Calle de Capitan Troncoso, 10 Coru\u00d1a La Coru\u00f1a 15001",
    "addr:housenumber":"10",
    "addr:postcode":"15001",
    "addr:street":"Calle De Capitan Troncoso;La Corun\u0303A",
    "iso:country":"ES",
    "sg:address":"Calle de Capitan Troncoso, 10",
    "sg:city":"Coru\u00d1a",
    "sg:orig_category":"Parques De Atracciones Y Centros De Esparcimiento",
    "sg:phone":"+34 981 22 23 95",
    "sg:postcode":"15001",
    "sg:province":"La Coru\u00f1a",
    "wof:name":"Canguro Park S.l.",
    "wof:placetype":"venue"
},
  "geometry": {"coordinates":[-8.394821167,43.3707847595],"type":"Point"}
}