{
  "type": "Feature",
  "properties": {
    "addr:full":"Calle de Violeta, 36 Palmas De Gran Canaria Las Palmas 35010",
    "addr:postcode":"35010",
    "addr:street":"Calle De Violeta 36",
    "iso:country":"ES",
    "sg:address":"Calle de Violeta, 36",
    "sg:city":"Palmas De Gran Canaria",
    "sg:orig_category":"Molduras, Junquillos, Listones Y Molduras Perforadas",
    "sg:phone":"+34 928 48 02 77",
    "sg:postcode":"35010",
    "sg:province":"Las Palmas",
    "wof:name":"Perez Gonzalez Lorenzo Daniel",
    "wof:placetype":"venue"
},
  "geometry": {"coordinates":[-15.4504613876,28.1145591736],"type":"Point"}
}