{
  "type": "Feature",
  "properties": {
    "addr:full":"Calle de Francos Rodriguez, 58 Madrid Madrid 28039",
    "addr:housenumber":"58",
    "addr:postcode":"madrid;28039",
    "addr:street":"Calle De Francos Rodriguez",
    "iso:country":"ES",
    "sg:address":"Calle de Francos Rodriguez, 58",
    "sg:city":"Madrid",
    "sg:orig_category":"Muebles Y Accesorios Para Cocinas Y Cuartos De Ba\u00d1o (al Por Menor)",
    "sg:phone":"+34 913 11 21 00",
    "sg:postcode":"28039",
    "sg:province":"Madrid",
    "wof:name":"Velasco Clemente Felix",
    "wof:placetype":"venue"
},
  "geometry": {"coordinates":[-3.7073009014,40.4567832947],"type":"Point"}
}