{
  "type": "Feature",
  "properties": {
    "addr:full":"Calle de Estigia, 3 Madrid Madrid 28037",
    "addr:housenumber":"3",
    "addr:postcode":"28037",
    "addr:street":"Calle De Estigia",
    "iso:country":"ES",
    "sg:address":"Calle de Estigia, 3",
    "sg:city":"Madrid",
    "sg:orig_category":"Goma: Materias Primas (producci\u00d3n, Distribuci\u00d3n)",
    "sg:phone":"+34 913 04 83 63",
    "sg:postcode":"28037",
    "sg:province":"Madrid",
    "sg:website":"www.crmsistemas.com",
    "wof:name":"C.r.m.sistemas De Fidelizacion S.a.",
    "wof:placetype":"venue"
},
  "geometry": {"coordinates":[-3.6285591125,40.4400138855],"type":"Point"}
}