{
  "type": "Feature",
  "properties": {
    "addr:full":"Av Puig I Cadafalch, 256 Mataro Barcelona 08303",
    "addr:housenumber":"256",
    "addr:postcode":"08303",
    "addr:street":"Av Puig;Cadafalch",
    "iso:country":"ES",
    "sg:address":"Av Puig I Cadafalch, 256",
    "sg:city":"Mataro",
    "sg:orig_category":"Farmacias",
    "sg:phone":"+34 937 98 25 50",
    "sg:postcode":"08303",
    "sg:province":"Barcelona",
    "wof:name":"Vilardell Garriga Andres Luis",
    "wof:placetype":"venue"
},
  "geometry": {"coordinates":[2.4228789806,41.5407562256],"type":"Point"}
}