{
  "type": "Feature",
  "properties": {
    "iso:country":"ES",
    "sg:address":"Avda Portugal, 39",
    "sg:city":"Ramallosa",
    "sg:orig_category":"Asesor\u00cda Sobre Comunicaci\u00d3n De Empresas",
    "sg:phone":"+34 986 35 05 34",
    "sg:postcode":"36379",
    "sg:province":"Pontevedra",
    "wof:name":"Asesoria Savi S.l.",
    "wof:placetype":"venue"
},
  "geometry": {"coordinates":[-8.8043117523,42.1149749756],"type":"Point"}
}