{
  "type": "Feature",
  "properties": {
    "addr:full":"Calle de Antonio Blazquez, 84 Almaden Ciudad Real 13400",
    "addr:housenumber":"84",
    "addr:postcode":"13400",
    "addr:street":"Calle De Antonio Blazquez;Real",
    "iso:country":"ES",
    "sg:address":"Calle de Antonio Blazquez, 84",
    "sg:city":"Almaden",
    "sg:orig_category":"Asociaciones Humanitarias, De Cooperaci\u00d3n, De Acci\u00d3n Social",
    "sg:phone":"+34 926 71 11 56",
    "sg:postcode":"13400",
    "sg:province":"Ciudad Real",
    "wof:name":"Caritas Diocesanas",
    "wof:placetype":"venue"
},
  "geometry": {"coordinates":[-4.8327178955,38.7753219604],"type":"Point"}
}