{
  "type": "Feature",
  "properties": {
    "iso:country":"ES",
    "sg:address":"Calle de Jesus Arambarri, 100",
    "sg:city":"Salamanca",
    "sg:orig_category":"Contenedores Para Transporte De Mercanc\u00cdas",
    "sg:phone":"+34 923 18 28 56",
    "sg:postcode":"37003",
    "sg:province":"Salamanca",
    "wof:name":"Guinaldo Alvarez Jose Antonio",
    "wof:placetype":"venue"
},
  "geometry": {"coordinates":[-5.6377391815,40.9722976685],"type":"Point"}
}