{
  "type": "Feature",
  "properties": {
    "iso:country":"ES",
    "sg:address":"Cmno Camino De Sancho Rey, S/n",
    "sg:city":"Ciudad Real",
    "sg:orig_category":"Reciclaje Y Tratamiento De Desechos Varios",
    "sg:phone":"+34 926 69 02 43",
    "sg:postcode":"13002",
    "sg:province":"Ciudad Real",
    "wof:name":"Residuos Solidos Urbanos De Castilla La Mancha S.a.",
    "wof:placetype":"venue"
},
  "geometry": {"coordinates":[-3.9361619949,38.9884681702],"type":"Point"}
}