{
  "type": "Feature",
  "properties": {
    "iso:country":"ES",
    "sg:address":"Avda Andalucia, 248",
    "sg:city":"Dos Hermanas",
    "sg:orig_category":"Muebles Y Accesorios Para Cocinas Y Cuartos De Ba\u00d1o (al Por Menor)",
    "sg:phone":"+34 955 66 15 87",
    "sg:postcode":"41700",
    "sg:province":"Sevilla",
    "wof:name":"Interdeco S.l.",
    "wof:placetype":"venue"
},
  "geometry": {"coordinates":[-5.9206929207,37.2642478943],"type":"Point"}
}