{
  "type": "Feature",
  "properties": {
    "iso:country":"ES",
    "sg:address":"Calle de Israel, 1",
    "sg:city":"Cordoba",
    "sg:orig_category":"Agencias De Viajes",
    "sg:phone":"+34 957 29 70 03",
    "sg:postcode":"14009",
    "sg:province":"C\u00f3rdoba",
    "wof:name":"Viajes Escolares Sinta's Espa\u00f1ola S.l.",
    "wof:placetype":"venue"
},
  "geometry": {"coordinates":[-4.7789821625,37.8717727661],"type":"Point"}
}