{
  "type": "Feature",
  "properties": {
    "iso:country":"ES",
    "sg:address":"Avda Albufera, 95",
    "sg:city":"Madrid",
    "sg:orig_category":"Ropa Para Se\u00d1oras Y Caballeros (al Por Menor)",
    "sg:phone":"+34 914 37 23 83",
    "sg:postcode":"28038",
    "sg:province":"Madrid",
    "wof:name":"Moreno Ruiz Alfredo",
    "wof:placetype":"venue"
},
  "geometry": {"coordinates":[-3.661206007,40.3942642212],"type":"Point"}
}