{
  "type": "Feature",
  "properties": {
    "iso:country":"ES",
    "sg:address":"Calle de Pelota, 4",
    "sg:city":"Valladolid",
    "sg:orig_category":"Venta, Colocaci\u00d3n, Reparaci\u00d3n De Parabrisas, Techos Descapotables",
    "sg:phone":"+34 983 34 50 70",
    "sg:postcode":"47003",
    "sg:province":"Valladolid",
    "wof:name":"Autovidrio Castilla S.l.",
    "wof:placetype":"venue"
},
  "geometry": {"coordinates":[-4.7282018661,41.6583557129],"type":"Point"}
}