{
  "type": "Feature",
  "properties": {
    "iso:country":"ES",
    "sg:address":"Carr Mestre Alberti, 24",
    "sg:city":"Puerto De Pollen\u00c7a",
    "sg:orig_category":"Centros Empresariales",
    "sg:phone":"+34 971 86 48 06",
    "sg:postcode":"07470",
    "sg:province":"Islas Baleares",
    "wof:name":"Manteniments I Serveis Pollen\u00e7a S.l",
    "wof:placetype":"venue"
},
  "geometry": {"coordinates":[3.0790278912,39.9084663391],"type":"Point"}
}