{
  "type": "Feature",
  "properties": {
    "addr:full":"Rua Ramon Pi\u00d1eiro, 1 Ourense Ourense 32001",
    "addr:housenumber":"1",
    "addr:postcode":"32001",
    "addr:street":"Rua Ramon Pin\u0303Eiro",
    "iso:country":"ES",
    "sg:address":"Rua Ramon Pi\u00d1eiro, 1",
    "sg:city":"Ourense",
    "sg:orig_category":"Peluquer\u00cdas, Peluquer\u00cda Mixta",
    "sg:phone":"+34 988 21 93 70",
    "sg:postcode":"32001",
    "sg:province":"Ourense",
    "wof:name":"Silva Barbeito Rosa Maria",
    "wof:placetype":"venue"
},
  "geometry": {"coordinates":[-7.8692917824,42.3518104553],"type":"Point"}
}