{
  "type": "Feature",
  "properties": {
    "addr:full":"Calle de Mayor, 19 Quintanadue\u00f1as Burgos 09197",
    "addr:housenumber":"19",
    "addr:postcode":"09197",
    "addr:street":"Calle De Mayor",
    "iso:country":"ES",
    "sg:address":"Calle de Mayor, 19",
    "sg:city":"Quintanadue\u00f1as",
    "sg:orig_category":"Institutos De Belleza",
    "sg:phone":"+34 947 29 26 17",
    "sg:postcode":"09197",
    "sg:province":"Burgos",
    "wof:name":"Juez Diez Tania",
    "wof:placetype":"venue"
},
  "geometry": {"coordinates":[-3.7342090607,42.3852081299],"type":"Point"}
}