{
  "type": "Feature",
  "properties": {
    "addr:full":"Carrer de Major, 36 Terrassa Barcelona 08221",
    "addr:housenumber":"36",
    "addr:postcode":"08221",
    "addr:street":"Carrer De Major",
    "iso:country":"ES",
    "sg:address":"Carrer de Major, 36",
    "sg:city":"Terrassa",
    "sg:orig_category":"Zapatos (al Por Menor)",
    "sg:phone":"+34 937 88 10 50",
    "sg:postcode":"08221",
    "sg:province":"Barcelona",
    "wof:name":"Calzados Moya S.l.",
    "wof:placetype":"venue"
},
  "geometry": {"coordinates":[2.0096099377,41.5614585876],"type":"Point"}
}