{
  "type": "Feature",
  "properties": {
    "iso:country":"ES",
    "sg:address":"Ctra. Perrina, S/n",
    "sg:city":"Valencia",
    "sg:orig_category":"Reparaci\u00d3n Y Restauraci\u00d3n De Objetos Diversos",
    "sg:phone":"+34 963 97 66 17",
    "sg:postcode":"46017",
    "sg:province":"Valencia",
    "wof:name":"Verdeguer Gimeno Fernando",
    "wof:placetype":"venue"
},
  "geometry": {"coordinates":[-0.3909240067,39.4433784485],"type":"Point"}
}