{
  "type": "Feature",
  "properties": {
    "addr:full":"Calle de Agustin Blazquez, S/n Chiclana De La Frontera C\u00e1diz 11130",
    "addr:housenumber":"s",
    "addr:postcode":"11130",
    "addr:street":"Calle De Agustin Blazquez;/ N",
    "iso:country":"ES",
    "sg:address":"Calle de Agustin Blazquez, S/n",
    "sg:city":"Chiclana De La Frontera",
    "sg:orig_category":"Polideportivos",
    "sg:phone":"+34 956 53 82 20",
    "sg:postcode":"11130",
    "sg:province":"C\u00e1diz",
    "wof:name":"Ayuntamiento De Chiclana Fra.",
    "wof:placetype":"venue"
},
  "geometry": {"coordinates":[-6.1529350281,36.4161567688],"type":"Point"}
}