{
  "type": "Feature",
  "properties": {
    "addr:full":"Avda Salamanca, S/n Alacant Alicante 03005",
    "addr:housenumber":"s / n",
    "addr:postcode":"03005",
    "addr:street":"Avda Salamanca",
    "iso:country":"ES",
    "sg:address":"Avda Salamanca, S/n",
    "sg:city":"Alacant",
    "sg:orig_category":"Artesan\u00cda",
    "sg:phone":"+34 965 12 61 93",
    "sg:postcode":"03005",
    "sg:province":"Alicante",
    "wof:name":"Artesania Alicantina Agrupacion Interes Economico",
    "wof:placetype":"venue"
},
  "geometry": {"coordinates":[-0.4944423139,38.3458175659],"type":"Point"}
}