{
  "type": "Feature",
  "properties": {
    "iso:country":"ES",
    "sg:address":"Calle de Pico Almanzor, 36",
    "sg:city":"Arganda",
    "sg:orig_category":"Papel (al Por Mayor)",
    "sg:phone":"+34 918 71 03 95",
    "sg:postcode":"28500",
    "sg:province":"Madrid",
    "wof:name":"Mayen Seren S.l.",
    "wof:placetype":"venue"
},
  "geometry": {"coordinates":[-3.4838480949,40.3068466187],"type":"Point"}
}