{
  "type": "Feature",
  "properties": {
    "addr:full":"Calle de Ribera De Navarra, 33 Cortes Navarra 31530",
    "addr:housenumber":"33",
    "addr:postcode":"31530",
    "addr:street":"Calle De Ribera De Navarra",
    "iso:country":"ES",
    "sg:address":"Calle de Ribera De Navarra, 33",
    "sg:city":"Cortes",
    "sg:orig_category":"Empresas De Pintura Y Revestimientos",
    "sg:phone":"+34 948 81 07 71",
    "sg:postcode":"31530",
    "sg:province":"Navarra",
    "wof:name":"Carlos Y Lucio Sebastian Roig",
    "wof:placetype":"venue"
},
  "geometry": {"coordinates":[-1.4164550304,41.9222373962],"type":"Point"}
}