{
  "type": "Feature",
  "properties": {
    "addr:full":"Poli Mugitegi-e, 4 Urretxu Guip\u00f9zcoa 20700",
    "addr:housenumber":"4",
    "addr:postcode":"20700",
    "addr:street":"Mugitegi-E;Guipu\u0300Zcoa",
    "iso:country":"ES",
    "sg:address":"Poli Mugitegi-e, 4",
    "sg:city":"Urretxu",
    "sg:orig_category":"Escayola Y Productos De Escayola (fabricaci\u00d3n, Al Por Mayor)",
    "sg:phone":"+34 943 72 90 48",
    "sg:postcode":"20700",
    "sg:province":"Guip\u00f9zcoa",
    "wof:name":"Decoracion Y Aislamientos Nu\u00f1ez S.l.",
    "wof:placetype":"venue"
},
  "geometry": {"coordinates":[-2.3134770393,43.086730957],"type":"Point"}
}