{
  "type": "Feature",
  "properties": {
    "iso:country":"ES",
    "sg:address":"Plaz Alfonso X El Sabio, 1",
    "sg:city":"Pola De Lena",
    "sg:orig_category":"Abogados",
    "sg:phone":"+34 985 49 33 33",
    "sg:postcode":"33630",
    "sg:province":"Asturias",
    "wof:name":"Tomillo Urbina Maria Del Mar",
    "wof:placetype":"venue"
},
  "geometry": {"coordinates":[-5.8293747902,43.1589202881],"type":"Point"}
}