{
  "type": "Feature",
  "properties": {
    "iso:country":"ES",
    "sg:address":"Plaz San Martin, 3",
    "sg:city":"Zaldibar",
    "sg:orig_category":"Contenedores (mercanc\u00cdas)",
    "sg:phone":"+34 946 82 68 01",
    "sg:postcode":"48250",
    "sg:province":"Vizcaya",
    "wof:name":"Madariaga Moyua Roberto",
    "wof:placetype":"venue"
},
  "geometry": {"coordinates":[-2.5471470356,43.1717758179],"type":"Point"}
}