{
  "type": "Feature",
  "properties": {
    "iso:country":"ES",
    "sg:address":"Calle de Mariano Fernandez, 30",
    "sg:city":"Nava Asuncion",
    "sg:orig_category":"Cerrajer\u00cda, Ferrallista",
    "sg:phone":"+34 921 58 03 38",
    "sg:postcode":"40450",
    "sg:province":"Segovia",
    "wof:name":"Gonzalez Garcia Pablo",
    "wof:placetype":"venue"
},
  "geometry": {"coordinates":[-4.4862399101,41.1567726135],"type":"Point"}
}