{
  "type": "Feature",
  "properties": {
    "iso:country":"ES",
    "sg:address":"Avda Manuel De Falla, 4",
    "sg:city":"Ubrique",
    "sg:orig_category":"Sindicatos Y Colegios Profesionales",
    "sg:phone":"+34 956 46 02 11",
    "sg:postcode":"11600",
    "sg:province":"C\u00e1diz",
    "wof:name":"Administradora De La Marca Y Denominacion Del Articulo De Piel De Ubrique",
    "wof:placetype":"venue"
},
  "geometry": {"coordinates":[-5.4472641945,36.6795501709],"type":"Point"}
}