{
  "type": "Feature",
  "properties": {
    "addr:full":"Portal De Sant Roc, 48 Terrassa Barcelona 08221",
    "addr:postcode":"08221",
    "iso:country":"ES",
    "sg:address":"Portal De Sant Roc, 48",
    "sg:city":"Terrassa",
    "sg:orig_category":"Cajas De Ahorro",
    "sg:phone":"+34 937 33 90 11",
    "sg:postcode":"08221",
    "sg:province":"Barcelona",
    "sg:website":"www.caixagirona.es",
    "wof:name":"Caixa De Girona",
    "wof:placetype":"venue"
},
  "geometry": {"coordinates":[2.0086290836,41.5611000061],"type":"Point"}
}