{
  "type": "Feature",
  "properties": {
    "addr:full":"Calle de Nueva De San Bernardo, 60 Salamanca Salamanca 37007",
    "addr:housenumber":"60",
    "addr:postcode":"37007",
    "addr:street":"Calle De Nueva De San Bernardo",
    "iso:country":"ES",
    "sg:address":"Calle de Nueva De San Bernardo, 60",
    "sg:city":"Salamanca",
    "sg:orig_category":"Carnicer\u00cdas, Carnicer\u00cdas",
    "sg:phone":"+34 923 26 40 69",
    "sg:postcode":"37007",
    "sg:province":"Salamanca",
    "wof:name":"Agudo Sanchez Vicente",
    "wof:placetype":"venue"
},
  "geometry": {"coordinates":[-5.6714406013,40.9691925049],"type":"Point"}
}