{
  "type": "Feature",
  "properties": {
    "addr:full":"Avda Generalisimo, 9 S. Vicente Barquera Cantabria 39540",
    "addr:housenumber":"9",
    "addr:postcode":"39540",
    "addr:street":"Avda Generalisimo;S. Vicente",
    "iso:country":"ES",
    "sg:address":"Avda Generalisimo, 9",
    "sg:city":"S. Vicente Barquera",
    "sg:orig_category":"\u00d3ptica: Instrumentos (fabricaci\u00d3n)",
    "sg:phone":"+34 942 71 23 89",
    "sg:postcode":"39540",
    "sg:province":"Cantabria",
    "wof:name":"Centro Optico Bulevar S.l.",
    "wof:placetype":"venue"
},
  "geometry": {"coordinates":[-4.3991708755,43.3849525452],"type":"Point"}
}