{
  "type": "Feature",
  "properties": {
    "addr:full":"Calle de Rosalia De Castro, 1 Chantada Lugo 27500",
    "addr:housenumber":"1",
    "addr:postcode":"27500",
    "addr:street":"Calle De Rosalia De Castro",
    "iso:country":"ES",
    "sg:address":"Calle de Rosalia De Castro, 1",
    "sg:city":"Chantada",
    "sg:orig_category":"Peluqueros: De Se\u00d1oras",
    "sg:phone":"+34 982 44 11 13",
    "sg:postcode":"27500",
    "sg:province":"Lugo",
    "wof:name":"Lopez Abad Monserrat",
    "wof:placetype":"venue"
},
  "geometry": {"coordinates":[-7.7773208618,42.6094818115],"type":"Point"}
}