{
  "type": "Feature",
  "properties": {
    "addr:full":"Pl. Abastos, S/n Palencia Palencia 34001",
    "addr:housenumber":"s / n",
    "addr:postcode":"34001",
    "addr:street":"Abastos",
    "iso:country":"ES",
    "sg:address":"Pl. Abastos, S/n",
    "sg:city":"Palencia",
    "sg:orig_category":"Carnicer\u00cdas, Carnicer\u00cdas",
    "sg:phone":"+34 979 74 61 50",
    "sg:postcode":"34001",
    "sg:province":"Palencia",
    "wof:name":"Emperador Muslares Lino",
    "wof:placetype":"venue"
},
  "geometry": {"coordinates":[-4.5392618179,42.010433197],"type":"Point"}
}