{
  "type": "Feature",
  "properties": {
    "iso:country":"ES",
    "sg:address":"Av Dr. Fleming, De, 6",
    "sg:city":"S. Antoni Portmany",
    "sg:orig_category":"Molduras, Junquillos, Listones Y Molduras Perforadas",
    "sg:phone":"+34 971 34 66 65",
    "sg:postcode":"07820",
    "sg:province":"Islas Baleares",
    "wof:name":"Crichton Claveras Guillermo",
    "wof:placetype":"venue"
},
  "geometry": {"coordinates":[1.3105829954,38.968006134],"type":"Point"}
}