{
  "type": "Feature",
  "properties": {
    "addr:full":"Calle de Marin, S/n Salamanca Salamanca 37007",
    "addr:housenumber":"s / n",
    "addr:postcode":"37007",
    "addr:street":"Calle De Marin",
    "iso:country":"ES",
    "sg:address":"Calle de Marin, S/n",
    "sg:city":"Salamanca",
    "sg:orig_category":"Aguas (distribuci\u00d3n, Servicios)",
    "sg:phone":"+34 923 24 21 99",
    "sg:postcode":"37007",
    "sg:province":"Salamanca",
    "wof:name":"Sociedad Anonima Industrial La Platina",
    "wof:placetype":"venue"
},
  "geometry": {"coordinates":[-5.6573338509,40.9641113281],"type":"Point"}
}