{
  "type": "Feature",
  "properties": {
    "iso:country":"ES",
    "sg:address":"Calle de Paloma, 8",
    "sg:city":"Ciudad Real",
    "sg:orig_category":"Institutos De Belleza",
    "sg:phone":"+34 926 22 36 69",
    "sg:postcode":"13001",
    "sg:province":"Ciudad Real",
    "wof:name":"Sanz Sanchez Celia",
    "wof:placetype":"venue"
},
  "geometry": {"coordinates":[-3.9269618988,38.9857521057],"type":"Point"}
}