{
  "type": "Feature",
  "properties": {
    "addr:full":"Calle de Ramon Y Cajal, 6 Mazaleon Teruel 44621",
    "addr:housenumber":"6",
    "addr:postcode":"44621",
    "addr:street":"Calle De Ramon Y Cajal",
    "iso:country":"ES",
    "sg:address":"Calle de Ramon Y Cajal, 6",
    "sg:city":"Mazaleon",
    "sg:orig_category":"Carnicer\u00cdas, Carnicer\u00cdas",
    "sg:phone":"+34 978 89 87 87",
    "sg:postcode":"44621",
    "sg:province":"Teruel",
    "wof:name":"Pe Angosto Nieves De",
    "wof:placetype":"venue"
},
  "geometry": {"coordinates":[0.1016839966,41.0489997864],"type":"Point"}
}