{
  "type": "Feature",
  "properties": {
    "addr:full":"Rond General Mitre, 144 Barcelona Barcelona 08006",
    "addr:housenumber":"144",
    "addr:postcode":"08006",
    "addr:street":"Mitre",
    "iso:country":"ES",
    "sg:address":"Rond General Mitre, 144",
    "sg:city":"Barcelona",
    "sg:orig_category":"Ense\u00d1ante, Direcci\u00d3n",
    "sg:phone":"+34 932 01 89 41",
    "sg:postcode":"08006",
    "sg:province":"Barcelona",
    "wof:name":"Contreras Ramos Jose Miguel",
    "wof:placetype":"venue"
},
  "geometry": {"coordinates":[2.1389870644,41.4032897949],"type":"Point"}
}