{
  "type": "Feature",
  "properties": {
    "iso:country":"ES",
    "sg:address":"Calle de San Sebastian, 58",
    "sg:city":"Brenes",
    "sg:orig_category":"Negocio De Enlosados, Soler\u00cdas",
    "sg:phone":"+34 954 79 63 10",
    "sg:postcode":"41310",
    "sg:province":"Sevilla",
    "wof:name":"Olmos Arias Francisco",
    "wof:placetype":"venue"
},
  "geometry": {"coordinates":[-5.8756141663,37.5462989807],"type":"Point"}
}