{
  "type": "Feature",
  "properties": {
    "iso:country":"ES",
    "sg:address":"Calle de Alcala, 187",
    "sg:city":"Madrid",
    "sg:orig_category":"Agentes, Concesionarios Y Sucursales De Veh\u00cdculos",
    "sg:phone":"+34 914 01 05 49",
    "sg:postcode":"28009",
    "sg:province":"Madrid",
    "wof:name":"Jose Jurado S.a.",
    "wof:placetype":"venue"
},
  "geometry": {"coordinates":[-3.67029953,40.4273681641],"type":"Point"}
}