{
  "type": "Feature",
  "properties": {
    "iso:country":"ES",
    "sg:address":"Calle de Alcorcon, 11",
    "sg:city":"Torrejon Ardoz",
    "sg:orig_category":"Telas Para Tapizar, Cortinas, Pasamaner\u00cda (fabricaci\u00d3n, Al Por Mayor)",
    "sg:phone":"+34 913 58 52 95",
    "sg:postcode":"28850",
    "sg:province":"Madrid",
    "sg:website":"www.maisondecor.info",
    "wof:name":"Intextil S.l.",
    "wof:placetype":"venue"
},
  "geometry": {"coordinates":[-3.4888932705,40.4589729309],"type":"Point"}
}