{
  "type": "Feature",
  "properties": {
    "iso:country":"ES",
    "sg:address":"Ctra Ciudad Real-murcia, Km. 0057,8",
    "sg:city":"Valdepe\u00f1as",
    "sg:orig_category":"Distribuci\u00d3n De Petr\u00d3leo Y Derivados",
    "sg:phone":"+34 926 32 46 76",
    "sg:postcode":"13300",
    "sg:province":"Ciudad Real",
    "wof:name":"Gasolinera Obregon C.b.",
    "wof:placetype":"venue"
},
  "geometry": {"coordinates":[-3.3877990246,38.7597694397],"type":"Point"}
}