{
  "type": "Feature",
  "properties": {
    "iso:country":"ES",
    "sg:address":"Calle de Carre\u00d1o Miranda, 2",
    "sg:city":"Mieres",
    "sg:orig_category":"Bazares, Art\u00cdculos De Limpieza Y De Cocina (al Por Menor)",
    "sg:phone":"+34 985 46 55 48",
    "sg:postcode":"33600",
    "sg:province":"Asturias",
    "wof:name":"Arg\u00fcelles Suarez Maria",
    "wof:placetype":"venue"
},
  "geometry": {"coordinates":[-5.7724785805,43.2523002625],"type":"Point"}
}