{
  "type": "Feature",
  "properties": {
    "addr:full":"Calle de Monte De Montjuich, 14 Madrid Madrid 28031",
    "addr:housenumber":"14",
    "addr:postcode":"madrid;28031",
    "addr:street":"Calle De Monte De Montjuich",
    "iso:country":"ES",
    "sg:address":"Calle de Monte De Montjuich, 14",
    "sg:city":"Madrid",
    "sg:orig_category":"Ferreter\u00cda (diversos)",
    "sg:phone":"+34 913 31 50 78",
    "sg:postcode":"28031",
    "sg:province":"Madrid",
    "wof:name":"Vazquez Barroso Carmen",
    "wof:placetype":"venue"
},
  "geometry": {"coordinates":[-3.6179690361,40.379989624],"type":"Point"}
}