{
  "type": "Feature",
  "properties": {
    "iso:country":"ES",
    "sg:address":"Calle de Proclamacion, 3",
    "sg:city":"Carmen",
    "sg:orig_category":"M\u00c9dicos: Estomatolog\u00cda",
    "sg:phone":"+34 968 21 36 07",
    "sg:postcode":"30002",
    "sg:province":"Murcia",
    "wof:name":"Sandoval Vazquez Enrique",
    "wof:placetype":"venue"
},
  "geometry": {"coordinates":[-1.129776001,37.9811248779],"type":"Point"}
}