{
  "type": "Feature",
  "properties": {
    "iso:country":"ES",
    "sg:address":"Carr Compositor Baro, 5",
    "sg:city":"Figueres",
    "sg:orig_category":"Iglesia Cat\u00d3lica",
    "sg:phone":"+34 972 50 47 81",
    "sg:postcode":"17600",
    "sg:province":"Girona",
    "wof:name":"Bisbat De Girona",
    "wof:placetype":"venue"
},
  "geometry": {"coordinates":[2.9672460556,42.2714385986],"type":"Point"}
}