{
  "type": "Feature",
  "properties": {
    "addr:full":"Calle de Menendez Y Pelayo, 18 Entrego Asturias 33940",
    "addr:housenumber":"18",
    "addr:postcode":"33940",
    "addr:street":"Calle De Menendez Y Pelayo",
    "iso:country":"ES",
    "sg:address":"Calle de Menendez Y Pelayo, 18",
    "sg:city":"Entrego",
    "sg:orig_category":"Fisioterapia",
    "sg:phone":"+34 985 66 06 66",
    "sg:postcode":"33940",
    "sg:province":"Asturias",
    "wof:name":"Alvarez Suarez Rocio",
    "wof:placetype":"venue"
},
  "geometry": {"coordinates":[-5.6389436722,43.2871398926],"type":"Point"}
}