{
  "type": "Feature",
  "properties": {
    "iso:country":"ES",
    "sg:address":"Calle de Vazquez De Mella, 65",
    "sg:city":"Oviedo",
    "sg:orig_category":"Carnicer\u00cdas, Carnicer\u00cdas",
    "sg:phone":"+34 985 27 36 30",
    "sg:postcode":"33012",
    "sg:province":"Asturias",
    "wof:name":"Alonso Garcia Jose Luis",
    "wof:placetype":"venue"
},
  "geometry": {"coordinates":[-5.8644318581,43.3659744263],"type":"Point"}
}