{
  "type": "Feature",
  "properties": {
    "addr:full":"Calle de Mediterraneo, 3 Xirivella Valencia 46950",
    "addr:housenumber":"3",
    "addr:postcode":"46950",
    "addr:street":"Calle De Mediterraneo",
    "iso:country":"ES",
    "sg:address":"Calle de Mediterraneo, 3",
    "sg:city":"Xirivella",
    "sg:orig_category":"Mec\u00c1nico Del Autom\u00d3vil",
    "sg:phone":"+34 963 59 12 11",
    "sg:postcode":"46950",
    "sg:province":"Valencia",
    "wof:name":"Bonet Perez Jose Luis",
    "wof:placetype":"venue"
},
  "geometry": {"coordinates":[-0.4348860085,39.4647483826],"type":"Point"}
}