{
  "type": "Feature",
  "properties": {
    "iso:country":"ES",
    "sg:address":"Carrer de Unio, 10",
    "sg:city":"Mataro",
    "sg:orig_category":"Maquinaria Para Industrias Diversas",
    "sg:phone":"+34 937 98 34 96",
    "sg:postcode":"08302",
    "sg:province":"Barcelona",
    "wof:name":"Ca\u00f1ete Ca\u00f1ete Francisco",
    "wof:placetype":"venue"
},
  "geometry": {"coordinates":[2.4398920536,41.5372543335],"type":"Point"}
}