{
  "type": "Feature",
  "properties": {
    "iso:country":"ES",
    "sg:address":"Avda Pasaje, 55",
    "sg:city":"Coru\u00d1a",
    "sg:orig_category":"Importaci\u00d3n",
    "sg:phone":"+34 981 17 33 58",
    "sg:postcode":"15006",
    "sg:province":"La Coru\u00f1a",
    "wof:name":"Linetach S.l",
    "wof:placetype":"venue"
},
  "geometry": {"coordinates":[-8.3873319626,43.3426742554],"type":"Point"}
}