{
  "type": "Feature",
  "properties": {
    "addr:full":"Carrer de Melcior De Palau, 69 Barcelona Barcelona 08028",
    "addr:housenumber":"69",
    "addr:postcode":"08028",
    "addr:street":"Carrer De Melcior De Palau",
    "iso:country":"ES",
    "sg:address":"Carrer de Melcior De Palau, 69",
    "sg:city":"Barcelona",
    "sg:orig_category":"Empresas De Impermeabilizaci\u00d3n",
    "sg:phone":"+34 934 09 77 93",
    "sg:postcode":"08028",
    "sg:province":"Barcelona",
    "wof:name":"Rosblan S.l.",
    "wof:placetype":"venue"
},
  "geometry": {"coordinates":[2.1335699558,41.3795013428],"type":"Point"}
}