{
  "type": "Feature",
  "properties": {
    "iso:country":"ES",
    "sg:address":"Mcdo Central, 25",
    "sg:city":"Castello Plana",
    "sg:orig_category":"Carnicer\u00cdas, Carnicer\u00cdas",
    "sg:phone":"+34 964 23 01 58",
    "sg:postcode":"12001",
    "sg:province":"Castell\u00f3n",
    "wof:name":"Besalduch Mi\u00f1ana David",
    "wof:placetype":"venue"
},
  "geometry": {"coordinates":[-0.0456800014,39.9851417542],"type":"Point"}
}