{
  "type": "Feature",
  "properties": {
    "iso:country":"ES",
    "sg:address":"Ctra Ourense (soutelo), 17",
    "sg:city":"Soutelo",
    "sg:orig_category":"Centros De Reservas Hoteleras",
    "sg:phone":"+34 986 75 63 11",
    "sg:postcode":"36560",
    "sg:province":"Pontevedra",
    "wof:name":"Pan De Soutelo C.b.",
    "wof:placetype":"venue"
},
  "geometry": {"coordinates":[-8.3186740875,42.5127601624],"type":"Point"}
}