{
  "type": "Feature",
  "properties": {
    "addr:full":"Ctra Cambrils, 11 Riudoms Tarragona 43330",
    "addr:housenumber":"11",
    "addr:postcode":"43330",
    "addr:street":"Ctra Cambrils",
    "iso:country":"ES",
    "sg:address":"Ctra Cambrils, 11",
    "sg:city":"Riudoms",
    "sg:classifiers":[
        {
            "category":"Food & Beverages",
            "subcategory":"Candy",
            "type":"Retail Goods"
        }
    ],
    "sg:phone":"+34 977 85 02 19",
    "sg:postcode":"43330",
    "sg:province":"Tarragona",
    "sg:tags":[
        "confiter\u00cdas",
        "y",
        "de",
        "fabricaci\u00d3n",
        "chocolate"
    ],
    "wof:name":"Exclusives Dol\u00e7a S.l.",
    "wof:placetype":"venue"
},
  "geometry": {"coordinates":[1.0588480234,41.1380767822],"type":"Point"}
}