{
  "type": "Feature",
  "properties": {
    "iso:country":"ES",
    "sg:address":"Carrer de Proven\u00c7a, 556",
    "sg:city":"Barcelona",
    "sg:orig_category":"Venta, Instalaci\u00d3n De Calefacci\u00d3n",
    "sg:phone":"+34 933 47 06 95",
    "sg:postcode":"08026",
    "sg:province":"Barcelona",
    "wof:name":"Luz Lopez Francisco",
    "wof:placetype":"venue"
},
  "geometry": {"coordinates":[2.1805911064,41.4088249207],"type":"Point"}
}