{
  "type": "Feature",
  "properties": {
    "iso:country":"ES",
    "sg:address":"Calle de Mariano Gil, 3",
    "sg:city":"Arevalo",
    "sg:orig_category":"Artesan\u00cda Y Trabajos Manuales: Suministros (al Por Menor)",
    "sg:phone":"+34 920 30 14 71",
    "sg:postcode":"05200",
    "sg:province":"\u00c1vila",
    "wof:name":"Serrano Collado Mariano",
    "wof:placetype":"venue"
},
  "geometry": {"coordinates":[-4.7181301117,41.0564994812],"type":"Point"}
}