{
  "type": "Feature",
  "properties": {
    "addr:full":"Ctra Barcelona, 81 Sabadell Barcelona 08201",
    "addr:housenumber":"81",
    "addr:postcode":"08201",
    "addr:street":"Ctra Barcelona",
    "iso:country":"ES",
    "sg:address":"Ctra Barcelona, 81",
    "sg:city":"Sabadell",
    "sg:orig_category":"Comercio, Reparaci\u00d3n De Bicicletas, De Motocicletas, De Accesorios",
    "sg:phone":"+34 937 45 10 74",
    "sg:postcode":"08201",
    "sg:province":"Barcelona",
    "sg:website":"www.biciscapa.com",
    "wof:name":"Escapa Carulla Ramon",
    "wof:placetype":"venue"
},
  "geometry": {"coordinates":[2.1047370434,41.5419692993],"type":"Point"}
}