{
  "type": "Feature",
  "properties": {
    "addr:full":"Carrer de Finestrat, 3 Benidorm Alicante 03500",
    "addr:housenumber":"3",
    "addr:postcode":"03500",
    "addr:street":"Carrer De Finestrat",
    "iso:country":"ES",
    "sg:address":"Carrer de Finestrat, 3",
    "sg:city":"Benidorm",
    "sg:orig_category":"Asesor\u00cda Fiscal Y Jur\u00cddica",
    "sg:phone":"+34 966 80 55 06",
    "sg:postcode":"03500",
    "sg:province":"Alicante",
    "wof:name":"Renta Asesoria S.l.",
    "wof:placetype":"venue"
},
  "geometry": {"coordinates":[-0.1254149973,38.5385055542],"type":"Point"}
}