{
  "type": "Feature",
  "properties": {
    "iso:country":"ES",
    "sg:address":"Carr Pintor Calbo, 73",
    "sg:city":"Mao",
    "sg:orig_category":"Comunidades Religiosas",
    "sg:phone":"+34 971 36 12 05",
    "sg:postcode":"07703",
    "sg:province":"Islas Baleares",
    "wof:name":"Compania Hijas De La Caridad De San Vicente De Paul Provincia De Barcelona Curia Provincial",
    "wof:placetype":"venue"
},
  "geometry": {"coordinates":[4.2582998276,39.8840103149],"type":"Point"}
}