{
  "type": "Feature",
  "properties": {
    "addr:full":"Calle de General Aldave, 38 Alacant Alicante 03012",
    "addr:housenumber":"38",
    "addr:postcode":"03012",
    "addr:street":"Calle De General Aldave",
    "iso:country":"ES",
    "sg:address":"Calle de General Aldave, 38",
    "sg:city":"Alacant",
    "sg:orig_category":"M\u00c1quinas De Escribir, M\u00c1quinas De Oficina (al Por Menor, Reparaci\u00d3n)",
    "sg:phone":"+34 965 25 56 41",
    "sg:postcode":"03012",
    "sg:province":"Alicante",
    "wof:name":"Vargas Olivares Guillermo",
    "wof:placetype":"venue"
},
  "geometry": {"coordinates":[-0.4845910072,38.3552513123],"type":"Point"}
}