{
  "type": "Feature",
  "properties": {
    "iso:country":"ES",
    "sg:address":"Rua Dr. Carracido, 44",
    "sg:city":"Vigo",
    "sg:orig_category":"Peluqueros: De Se\u00d1oras",
    "sg:phone":"+34 986 37 32 56",
    "sg:postcode":"36205",
    "sg:province":"Pontevedra",
    "wof:name":"Marta Estevez Gonzalez Y Maria Del Carmen Estevez Gonzalez Cdad",
    "wof:placetype":"venue"
},
  "geometry": {"coordinates":[-8.7050018311,42.2294006348],"type":"Point"}
}