{
  "type": "Feature",
  "properties": {
    "addr:full":"Calle de Yerma, 7 Huetor-vega Granada 18198",
    "addr:housenumber":"7",
    "addr:postcode":"18198",
    "addr:street":"Calle De Yerma",
    "iso:country":"ES",
    "sg:address":"Calle de Yerma, 7",
    "sg:city":"Huetor-vega",
    "sg:orig_category":"Alquiler De V\u00cddeo",
    "sg:phone":"+34 958 30 12 91",
    "sg:postcode":"18198",
    "sg:province":"Granada",
    "wof:name":"Martin Del Rio Leticia",
    "wof:placetype":"venue"
},
  "geometry": {"coordinates":[-3.5665619373,37.15076828],"type":"Point"}
}