{
  "type": "Feature",
  "properties": {
    "addr:full":"P. Esc. Viejas, S/n Pitres Granada 18414",
    "addr:housenumber":"s",
    "addr:postcode":"18414",
    "addr:street":"/ N Pitres",
    "iso:country":"ES",
    "sg:address":"P. Esc. Viejas, S/n",
    "sg:city":"Pitres",
    "sg:orig_category":"Ense\u00d1anza Secundaria: Colegios Y Escuelas Privadas",
    "sg:phone":"+34 958 85 74 04",
    "sg:postcode":"18414",
    "sg:province":"Granada",
    "wof:name":"Junta De Andalucia",
    "wof:placetype":"venue"
},
  "geometry": {"coordinates":[-3.3241889477,36.9365768433],"type":"Point"}
}