{
  "type": "Feature",
  "properties": {
    "addr:full":"Nueve De Agosto, 7 Ribeira-santa Uxia La Coru\u00f1a 15960",
    "addr:housenumber":"7",
    "addr:postcode":"15960",
    "addr:street":"Nueve De Agosto;Uxia;Corun\u0303A",
    "iso:country":"ES",
    "sg:address":"Nueve De Agosto, 7",
    "sg:city":"Ribeira-santa Uxia",
    "sg:orig_category":"Fabricaci\u00d3n, Venta De Cuadros, Accesorios Para Enmarcar",
    "sg:phone":"+34 981 87 52 95",
    "sg:postcode":"15960",
    "sg:province":"La Coru\u00f1a",
    "wof:name":"Rincon-benzala Fernandez Ester",
    "wof:placetype":"venue"
},
  "geometry": {"coordinates":[-8.9939661026,42.5549201965],"type":"Point"}
}