{
  "type": "Feature",
  "properties": {
    "addr:full":"Pl Merce, 4 Palma Islas Baleares 07002",
    "addr:housenumber":"4",
    "addr:postcode":"07002",
    "addr:street":"Pl Merce",
    "iso:country":"ES",
    "sg:address":"Pl Merce, 4",
    "sg:city":"Palma",
    "sg:orig_category":"Bordado, Marcado A Medida",
    "sg:phone":"+34 971 71 14 66",
    "sg:postcode":"07002",
    "sg:province":"Islas Baleares",
    "wof:name":"Brodats De Mallorca S.c.",
    "wof:placetype":"venue"
},
  "geometry": {"coordinates":[2.6541140079,39.572517395],"type":"Point"}
}