{
  "type": "Feature",
  "properties": {
    "iso:country":"ES",
    "sg:address":"Carr Joan Regla, 1",
    "sg:city":"Figueres",
    "sg:orig_category":"Servicios De Telecomunicaciones",
    "sg:phone":"+34 972 51 30 99",
    "sg:postcode":"17600",
    "sg:province":"Girona",
    "wof:name":"Tele Haddi S.l.",
    "wof:placetype":"venue"
},
  "geometry": {"coordinates":[2.9678099155,42.2648658752],"type":"Point"}
}