{
  "type": "Feature",
  "properties": {
    "addr:full":"Ctra Tarragona-lerida, Km. 0014,5 Vallmoll Tarragona 43144",
    "addr:postcode":"43144",
    "addr:street":"Ctra Tarragona-Lerida Km. 0014,5",
    "iso:country":"ES",
    "sg:address":"Ctra Tarragona-lerida, Km. 0014,5",
    "sg:city":"Vallmoll",
    "sg:orig_category":"Fabricaci\u00d3n De Ventanas",
    "sg:phone":"+34 977 63 70 01",
    "sg:postcode":"43144",
    "sg:province":"Tarragona",
    "sg:website":"www.finstral.com",
    "wof:name":"Finstral S.a.",
    "wof:placetype":"venue"
},
  "geometry": {"coordinates":[1.249235034,41.2438163757],"type":"Point"}
}