{
  "type": "Feature",
  "properties": {
    "addr:full":"Carr Torres I Jonama, 35 Palafrugell Girona 17200",
    "addr:housenumber":"35",
    "addr:postcode":"17200",
    "addr:street":"Carr Torres I Jonama",
    "iso:country":"ES",
    "sg:address":"Carr Torres I Jonama, 35",
    "sg:city":"Palafrugell",
    "sg:orig_category":"Cajas De Ahorro",
    "sg:phone":"+34 972 30 81 03",
    "sg:postcode":"17200",
    "sg:province":"Girona",
    "wof:name":"Caixa Deestalvis De Manresa",
    "wof:placetype":"venue"
},
  "geometry": {"coordinates":[3.1616649628,41.9183731079],"type":"Point"}
}