{
  "type": "Feature",
  "properties": {
    "iso:country":"ES",
    "sg:address":"Calle de Rafael Alberti, 9",
    "sg:city":"Almeria",
    "sg:orig_category":"Caf\u00c9s, Bares, Cervecer\u00cdas",
    "sg:phone":"+34 950 26 30 38",
    "sg:postcode":"04004",
    "sg:province":"Almer\u00eda",
    "wof:name":"Alcarria S.c.",
    "wof:placetype":"venue"
},
  "geometry": {"coordinates":[-2.4603168964,36.8348121643],"type":"Point"}
}