{
  "type": "Feature",
  "properties": {
    "iso:country":"ES",
    "sg:address":"Plaz Pais Valenciano, 5",
    "sg:city":"Mislata",
    "sg:orig_category":"M\u00c9dicos: Estomatolog\u00cda",
    "sg:phone":"+34 963 83 20 84",
    "sg:postcode":"46920",
    "sg:province":"Valencia",
    "wof:name":"Ribas Sanz Julian",
    "wof:placetype":"venue"
},
  "geometry": {"coordinates":[-0.4225980043,39.478729248],"type":"Point"}
}