{
  "type": "Feature",
  "properties": {
    "iso:country":"ES",
    "sg:address":"Calle de Estacion De Basurtu, 2",
    "sg:city":"Bilbao",
    "sg:orig_category":"Molduras, Junquillos, Listones Y Molduras Perforadas",
    "sg:phone":"+34 944 27 29 94",
    "sg:postcode":"48002",
    "sg:province":"Vizcaya",
    "wof:name":"Bayon Manrique Jose Luis",
    "wof:placetype":"venue"
},
  "geometry": {"coordinates":[-2.9512319565,43.2579956055],"type":"Point"}
}