{
  "type": "Feature",
  "properties": {
    "iso:country":"ES",
    "sg:address":"Avda Cristobal Colon, 26",
    "sg:city":"Dos Hermanas",
    "sg:classifiers":[
        {
            "category":"Autos & Motor Vehicles",
            "subcategory":"Automobile Sales",
            "type":"Retail Goods"
        }
    ],
    "sg:phone":"+34 955 66 49 20",
    "sg:postcode":"41700",
    "sg:province":"Sevilla",
    "wof:name":"Begines Acebedo Carlos Javier",
    "wof:placetype":"venue"
},
  "geometry": {"coordinates":[-5.9298682213,37.2819976807],"type":"Point"}
}