{
  "type": "Feature",
  "properties": {
    "iso:country":"ES",
    "sg:address":"Calle de Ce, 1",
    "sg:city":"Puebla Montalban",
    "sg:orig_category":"Pescader\u00cdas (al Por Menor)",
    "sg:phone":"+34 925 75 08 91",
    "sg:postcode":"45516",
    "sg:province":"Toledo",
    "wof:name":"Diaz De La Rosa Felix",
    "wof:placetype":"venue"
},
  "geometry": {"coordinates":[-4.3593964577,39.8607597351],"type":"Point"}
}