{
  "type": "Feature",
  "properties": {
    "iso:country":"ES",
    "sg:address":"Avda Pablo Ruiz Picasso, S/n",
    "sg:city":"Alora",
    "sg:orig_category":"Centros De Educaci\u00d3n Especial",
    "sg:phone":"+34 952 49 60 16",
    "sg:postcode":"29500",
    "sg:province":"M\u00e1laga",
    "wof:name":"Junta De Andalucia",
    "wof:placetype":"venue"
},
  "geometry": {"coordinates":[-4.7043218613,36.8296852112],"type":"Point"}
}