{
  "type": "Feature",
  "properties": {
    "addr:full":"Av. Jose Antonio, 10 Avila \u00c1vila 05001",
    "addr:housenumber":"10",
    "addr:postcode":"05001",
    "addr:street":"Av. Jose Antonio;A\u0301Vila",
    "iso:country":"ES",
    "sg:address":"Av. Jose Antonio, 10",
    "sg:city":"Avila",
    "sg:orig_category":"Abogados",
    "sg:phone":"+34 920 25 12 50",
    "sg:postcode":"05001",
    "sg:province":"\u00c1vila",
    "wof:name":"Martin Martin Victoriano",
    "wof:placetype":"venue"
},
  "geometry": {"coordinates":[-4.6878609657,40.6562232971],"type":"Point"}
}