{
  "type": "Feature",
  "properties": {
    "addr:full":"Calle de Clemente Velasco, 43 Ciudad Rodrigo Salamanca 37500",
    "addr:housenumber":"43",
    "addr:postcode":"37500",
    "addr:street":"Calle De Clemente Velasco",
    "iso:country":"ES",
    "sg:address":"Calle de Clemente Velasco, 43",
    "sg:city":"Ciudad Rodrigo",
    "sg:orig_category":"Cajas Para Embalar",
    "sg:phone":"+34 923 46 27 69",
    "sg:postcode":"37500",
    "sg:province":"Salamanca",
    "wof:name":"Caja Rural Provincial De Salamanca",
    "wof:placetype":"venue"
},
  "geometry": {"coordinates":[-6.5377287865,40.5910987854],"type":"Point"}
}