{
  "type": "Feature",
  "properties": {
    "iso:country":"ES",
    "sg:address":"Calle de Alvarez Quintero, 23",
    "sg:city":"Sevilla",
    "sg:orig_category":"Fabricaci\u00d3n De Banderas Y De Banderines",
    "sg:phone":"+34 954 22 02 47",
    "sg:postcode":"41004",
    "sg:province":"Sevilla",
    "wof:name":"Ramirez Garcia De Gomariz Angel",
    "wof:placetype":"venue"
},
  "geometry": {"coordinates":[-5.9932537079,37.3886833191],"type":"Point"}
}