{
  "type": "Feature",
  "properties": {
    "addr:full":"Calle de Virgen Maria, 3 Avila \u00c1vila 05003",
    "addr:housenumber":"3",
    "addr:postcode":"05003",
    "addr:street":"Calle De Virgen Maria;A\u0301Vila",
    "iso:country":"ES",
    "sg:address":"Calle de Virgen Maria, 3",
    "sg:city":"Avila",
    "sg:orig_category":"Asilos De Ancianos. Centros Privados",
    "sg:phone":"+34 920 25 70 73",
    "sg:postcode":"05003",
    "sg:province":"\u00c1vila",
    "wof:name":"Hijas Del Buen Pastor Y De Maria Inmaculada",
    "wof:placetype":"venue"
},
  "geometry": {"coordinates":[-4.6870961189,40.6529541016],"type":"Point"}
}