{
  "type": "Feature",
  "properties": {
    "iso:country":"ES",
    "sg:address":"La Victoria, 2",
    "sg:city":"El Rinconcillo",
    "sg:orig_category":"Molduras, Junquillos, Listones Y Molduras Perforadas",
    "sg:phone":"+34 957 30 14 20",
    "sg:postcode":"14100",
    "sg:province":"C\u00f3rdoba",
    "wof:name":"Alcantara Alcantara Ana",
    "wof:placetype":"venue"
},
  "geometry": {"coordinates":[-4.8525218964,37.6810379028],"type":"Point"}
}