{
  "type": "Feature",
  "properties": {
    "iso:country":"ES",
    "sg:address":"Calle de Ciruela, 4",
    "sg:city":"Ciudad Real",
    "sg:orig_category":"Ropa Para Ni\u00d1os (al Por Menor)",
    "sg:phone":"+34 926 25 24 66",
    "sg:postcode":"13001",
    "sg:province":"Ciudad Real",
    "wof:name":"Chayla Cdad",
    "wof:placetype":"venue"
},
  "geometry": {"coordinates":[-3.9282972813,38.982635498],"type":"Point"}
}