{
  "type": "Feature",
  "properties": {
    "iso:country":"ES",
    "sg:address":"Ctra. Sta. Cruz Salceda, Km. 0000,1",
    "sg:city":"Vadocondes",
    "sg:orig_category":"Centros Empresariales",
    "sg:phone":"+34 947 52 81 35",
    "sg:postcode":"09491",
    "sg:province":"Burgos",
    "wof:name":"Comunidad De Regantes San Cosme Y San Damian",
    "wof:placetype":"venue"
},
  "geometry": {"coordinates":[-3.6059188843,41.6375999451],"type":"Point"}
}