{
  "type": "Feature",
  "properties": {
    "addr:full":"Rua Paz, 33 Pobra Do Carami\u00e7al La Coru\u00f1a 15940",
    "addr:housenumber":"33",
    "addr:postcode":"15940",
    "addr:street":"Rua Paz;Corun\u0303A",
    "iso:country":"ES",
    "sg:address":"Rua Paz, 33",
    "sg:city":"Pobra Do Carami\u00e7al",
    "sg:orig_category":"Librer\u00cdas",
    "sg:phone":"+34 981 83 04 09",
    "sg:postcode":"15940",
    "sg:province":"La Coru\u00f1a",
    "wof:name":"Brey Mera Jose",
    "wof:placetype":"venue"
},
  "geometry": {"coordinates":[-8.9382886887,42.6055793762],"type":"Point"}
}