{
  "type": "Feature",
  "properties": {
    "iso:country":"ES",
    "sg:address":"Av. Albufera, 7",
    "sg:city":"Sedavi",
    "sg:orig_category":"Droguer\u00cdas (al Por Menor)",
    "sg:phone":"+34 963 75 00 87",
    "sg:postcode":"46910",
    "sg:province":"Valencia",
    "wof:name":"Maria Alabau Roig S.l.",
    "wof:placetype":"venue"
},
  "geometry": {"coordinates":[-0.3816620111,39.422416687],"type":"Point"}
}