{
  "type": "Feature",
  "properties": {
    "addr:full":"Calle de Sagrada Familia, 25 Granada Granada 18015",
    "addr:housenumber":"25",
    "addr:postcode":"18015",
    "addr:street":"Calle De Sagrada Familia",
    "iso:country":"ES",
    "sg:address":"Calle de Sagrada Familia, 25",
    "sg:city":"Granada",
    "sg:orig_category":"Carnicer\u00cdas, Carnicer\u00cdas",
    "sg:phone":"+34 958 27 01 23",
    "sg:postcode":"18015",
    "sg:province":"Granada",
    "wof:name":"Garcia Hernandez Florentino",
    "wof:placetype":"venue"
},
  "geometry": {"coordinates":[-3.6250889301,37.190448761],"type":"Point"}
}