{
  "type": "Feature",
  "properties": {
    "addr:full":"C/ Abeurador, 2 Banyoles Girona 17820",
    "addr:housenumber":"2",
    "addr:postcode":"17820",
    "addr:street":"C / Abeurador",
    "iso:country":"ES",
    "sg:address":"C/ Abeurador, 2",
    "sg:city":"Banyoles",
    "sg:orig_category":"Ropa Para Se\u00d1oras (al Por Menor)",
    "sg:phone":"+34 972 57 60 58",
    "sg:postcode":"17820",
    "sg:province":"Girona",
    "wof:name":"Frigola Duran S.c.",
    "wof:placetype":"venue"
},
  "geometry": {"coordinates":[2.7642500401,42.1182823181],"type":"Point"}
}