{
  "type": "Feature",
  "properties": {
    "addr:full":"Pte. Universidad, 2 Badajoz Badajoz 06004",
    "addr:housenumber":"2",
    "addr:postcode":"06004",
    "addr:street":"Pte. Universidad",
    "iso:country":"ES",
    "sg:address":"Pte. Universidad, 2",
    "sg:city":"Badajoz",
    "sg:orig_category":"Reposter\u00cdas",
    "sg:phone":"+34 924 27 42 36",
    "sg:postcode":"06004",
    "sg:province":"Badajoz",
    "wof:name":"Murillo Gutierrez Vicenta",
    "wof:placetype":"venue"
},
  "geometry": {"coordinates":[-6.9726238251,38.874835968],"type":"Point"}
}