{
  "type": "Feature",
  "properties": {
    "iso:country":"ES",
    "sg:address":"Calle de Soldados (los), 14",
    "sg:city":"Palencia",
    "sg:orig_category":"Agencias Y Asesores De Publicidad",
    "sg:phone":"+34 979 70 30 43",
    "sg:postcode":"34001",
    "sg:province":"Palencia",
    "wof:name":"Badiola Y Anderez S.l.",
    "wof:placetype":"venue"
},
  "geometry": {"coordinates":[-4.5327649117,42.0126190186],"type":"Point"}
}