{
  "type": "Feature",
  "properties": {
    "addr:full":"Calle de Polea (de La), 13 Partija-santa Monica Madrid 28529",
    "addr:housenumber":"13",
    "addr:postcode":"28529",
    "addr:street":"Calle De Polea De La",
    "iso:country":"ES",
    "sg:address":"Calle de Polea (de La), 13",
    "sg:city":"Partija-santa Monica",
    "sg:orig_category":"Escultores, Estatuarios E Imagineros",
    "sg:phone":"+34 916 66 54 90",
    "sg:postcode":"28529",
    "sg:province":"Madrid",
    "sg:website":"www.capaesculturas.com",
    "wof:name":"Capaser S.l.",
    "wof:placetype":"venue"
},
  "geometry": {"coordinates":[-3.5102670193,40.314289093],"type":"Point"}
}