{
  "type": "Feature",
  "properties": {
    "addr:full":"Calle de Ramon Gil Roldan, 22 Santa Cruz De Tenerife Santa Cruz De Tenerife 38006",
    "addr:housenumber":"22",
    "addr:postcode":"38006",
    "addr:street":"Calle De Ramon Gil Roldan",
    "iso:country":"ES",
    "sg:address":"Calle de Ramon Gil Roldan, 22",
    "sg:city":"Santa Cruz De Tenerife",
    "sg:orig_category":"Motocicletas (agentes, Concesionarios)",
    "sg:phone":"+34 922 27 18 07",
    "sg:postcode":"38006",
    "sg:province":"Santa Cruz De Tenerife",
    "wof:name":"Joima Motos S.l.",
    "wof:placetype":"venue"
},
  "geometry": {"coordinates":[-16.2652893066,28.4761505127],"type":"Point"}
}