{
  "type": "Feature",
  "properties": {
    "addr:full":"Ctra Santo Domingo, Km. 0011,8 Villar De Torre La Rioja 26225",
    "addr:housenumber":"26225",
    "addr:street":"Ctra Santo Domingo Km. 0011,8 Villar;Torre;Rioja",
    "iso:country":"ES",
    "sg:address":"Ctra Santo Domingo, Km. 0011,8",
    "sg:city":"Villar De Torre",
    "sg:orig_category":"Producci\u00d3n De Abonos Y De Fertilizantes",
    "sg:phone":"+34 941 36 61 18",
    "sg:postcode":"26225",
    "sg:province":"La Rioja",
    "wof:name":"Amando Martinez S.l.",
    "wof:placetype":"venue"
},
  "geometry": {"coordinates":[-2.8962244987,42.41173172],"type":"Point"}
}