{
  "type": "Feature",
  "properties": {
    "iso:country":"ES",
    "sg:address":"Calle de Zaldivar, 4",
    "sg:city":"Villaviciosa",
    "sg:orig_category":"Asociaciones Y Clubs Deportivos",
    "sg:phone":"+34 985 89 25 32",
    "sg:postcode":"33300",
    "sg:province":"Asturias",
    "wof:name":"Bembribe Sport S.l.",
    "wof:placetype":"venue"
},
  "geometry": {"coordinates":[-5.4332141876,43.4804763794],"type":"Point"}
}