{
  "type": "Feature",
  "properties": {
    "iso:country":"ES",
    "sg:address":"Calle de San Anton, 17",
    "sg:city":"Logro\u00f1o",
    "sg:orig_category":"Retoques De Vestidos",
    "sg:phone":"+34 941 25 75 15",
    "sg:postcode":"26002",
    "sg:province":"La Rioja",
    "sg:website":"www.retoucherie.com",
    "wof:name":"Calvo Azpeitia Carla",
    "wof:placetype":"venue"
},
  "geometry": {"coordinates":[-2.4464230537,42.4616241455],"type":"Point"}
}