{
  "type": "Feature",
  "properties": {
    "iso:country":"ES",
    "sg:address":"Carrer de Repartidor, 38",
    "sg:city":"Barcelona",
    "sg:orig_category":"Servicios De Telecomunicaciones",
    "sg:phone":"+34 932 84 49 56",
    "sg:postcode":"08023",
    "sg:province":"Barcelona",
    "wof:name":"Ovagacom S.l.l.",
    "wof:placetype":"venue"
},
  "geometry": {"coordinates":[2.1483058929,41.4119644165],"type":"Point"}
}