{
  "type": "Feature",
  "properties": {
    "addr:full":"Avda Ciudades (de Las), 94 Getafe Madrid 28903",
    "addr:housenumber":"94",
    "addr:postcode":"28903",
    "addr:street":"Avda Ciudades De Las",
    "iso:country":"ES",
    "sg:address":"Avda Ciudades (de Las), 94",
    "sg:city":"Getafe",
    "sg:orig_category":"Cristaler\u00cdas",
    "sg:phone":"+34 916 83 69 83",
    "sg:postcode":"28903",
    "sg:province":"Madrid",
    "wof:name":"Aparicio Ojeda Marcos",
    "wof:placetype":"venue"
},
  "geometry": {"coordinates":[-3.7150967121,40.3133087158],"type":"Point"}
}