{
  "type": "Feature",
  "properties": {
    "addr:full":"Calle de Ariznabarra, S/n Vitoria-gasteiz \u00c1lava 01007",
    "addr:housenumber":"s",
    "addr:postcode":"01007",
    "addr:street":"Calle De Ariznabarra;/ N",
    "iso:country":"ES",
    "sg:address":"Calle de Ariznabarra, S/n",
    "sg:city":"Vitoria-gasteiz",
    "sg:orig_category":"Centros De Educaci\u00d3n Especial",
    "sg:phone":"+34 945 13 21 13",
    "sg:postcode":"01007",
    "sg:province":"\u00c1lava",
    "wof:name":"Colegio Miguel De Cervantes-ayuntamiento",
    "wof:placetype":"venue"
},
  "geometry": {"coordinates":[-2.690931797,42.8395767212],"type":"Point"}
}