{
  "type": "Feature",
  "properties": {
    "iso:country":"ES",
    "sg:address":"Calle de Catalu\u00d1a, 13",
    "sg:city":"Gijon",
    "sg:orig_category":"Fabricaci\u00d3n, Instalaci\u00d3n De Armarios",
    "sg:phone":"+34 985 14 14 28",
    "sg:postcode":"33208",
    "sg:province":"Asturias",
    "wof:name":"Sistemas Buk S. A.",
    "wof:placetype":"venue"
},
  "geometry": {"coordinates":[-5.6714320183,43.5292320251],"type":"Point"}
}