{
  "type": "Feature",
  "properties": {
    "iso:country":"ES",
    "sg:address":"Calle de Aragon, 7",
    "sg:city":"Mancha Real",
    "sg:orig_category":"Carnicer\u00cdas, Carnicer\u00cdas",
    "sg:phone":"+34 953 35 28 88",
    "sg:postcode":"23100",
    "sg:province":"Ja\u00e9n",
    "wof:name":"Almagro Ortiz Antonio",
    "wof:placetype":"venue"
},
  "geometry": {"coordinates":[-3.6060838699,37.7841682434],"type":"Point"}
}