{
  "type": "Feature",
  "properties": {
    "iso:country":"ES",
    "sg:address":"Po. Tilos, 3",
    "sg:city":"Monteprincipe",
    "sg:orig_category":"Agentes Y Bufetes De Negocio",
    "sg:phone":"+34 913 52 55 05",
    "sg:postcode":"28668",
    "sg:province":"Madrid",
    "wof:name":"Coinsa Inmuebles S.l.",
    "wof:placetype":"venue"
},
  "geometry": {"coordinates":[-3.8439650536,40.4083824158],"type":"Point"}
}