{
  "type": "Feature",
  "properties": {
    "iso:country":"ES",
    "sg:address":"Carrer de Cartagena, 191",
    "sg:city":"Barcelona",
    "sg:orig_category":"C\u00c1maras De Comercio E Industria, Oficios, Agricultura",
    "sg:phone":"+34 932 65 37 67",
    "sg:postcode":"08013",
    "sg:province":"Barcelona",
    "wof:name":"Informes De Riesgo S.l.",
    "wof:placetype":"venue"
},
  "geometry": {"coordinates":[2.1823680401,41.4049415588],"type":"Point"}
}