{
  "type": "Feature",
  "properties": {
    "addr:full":"Calle de Tauste, 1 Remolinos Zaragoza 50637",
    "addr:housenumber":"1",
    "addr:postcode":"50637",
    "addr:street":"Calle De Tauste",
    "iso:country":"ES",
    "sg:address":"Calle de Tauste, 1",
    "sg:city":"Remolinos",
    "sg:orig_category":"Explotaci\u00d3n De Canteras",
    "sg:phone":"+34 976 61 81 70",
    "sg:postcode":"50637",
    "sg:province":"Zaragoza",
    "wof:name":"Ugarit Aragon S.l.",
    "wof:placetype":"venue"
},
  "geometry": {"coordinates":[-1.1787090302,41.8365440369],"type":"Point"}
}