{
  "type": "Feature",
  "properties": {
    "addr:full":"Carrer de Doctor Ferran, 11 Vilassar Dalt Barcelona 08339",
    "addr:housenumber":"11",
    "addr:postcode":"08339",
    "addr:street":"Carrer De Doctor Ferran",
    "iso:country":"ES",
    "sg:address":"Carrer de Doctor Ferran, 11",
    "sg:city":"Vilassar Dalt",
    "sg:orig_category":"Fabricaci\u00d3n De Material Y Sistemas De Se\u00d1alizaci\u00d3n De Carreteras, Urbanos Y De Obras",
    "sg:phone":"+34 937 53 15 62",
    "sg:postcode":"08339",
    "sg:province":"Barcelona",
    "wof:name":"Ecoyma S.a.",
    "wof:placetype":"venue"
},
  "geometry": {"coordinates":[2.3633460999,41.5165863037],"type":"Point"}
}