{
  "type": "Feature",
  "properties": {
    "addr:full":"Calle de Jabonerias, 2 San Bartolome Murcia 30001",
    "addr:housenumber":"2",
    "addr:postcode":"30001",
    "addr:street":"Calle De Jabonerias",
    "iso:country":"ES",
    "sg:address":"Calle de Jabonerias, 2",
    "sg:city":"San Bartolome",
    "sg:orig_category":"M\u00c9dicos: Oftalmolog\u00cda",
    "sg:phone":"+34 968 21 20 46",
    "sg:postcode":"30001",
    "sg:province":"Murcia",
    "wof:name":"Trigueros Mateos Pablo",
    "wof:placetype":"venue"
},
  "geometry": {"coordinates":[-1.1309529543,37.9858322144],"type":"Point"}
}