{
  "type": "Feature",
  "properties": {
    "addr:full":"Calle de Veronica (la), 49 Cuevas Almanzora Almer\u00eda 04610",
    "addr:housenumber":"49",
    "addr:postcode":"04610",
    "addr:street":"Calle De Veronica La;Almeri\u0301A",
    "iso:country":"ES",
    "sg:address":"Calle de Veronica (la), 49",
    "sg:city":"Cuevas Almanzora",
    "sg:orig_category":"Carnicer\u00cdas, Carnicer\u00cdas",
    "sg:phone":"+34 950 45 65 36",
    "sg:postcode":"04610",
    "sg:province":"Almer\u00eda",
    "wof:name":"Valero Torres Tomas",
    "wof:placetype":"venue"
},
  "geometry": {"coordinates":[-1.8799489737,37.294921875],"type":"Point"}
}