{
  "type": "Feature",
  "properties": {
    "addr:full":"Avda Jaca, 2 Madrid Madrid 28022",
    "addr:housenumber":"2",
    "addr:postcode":"28022",
    "addr:street":"Avda Jaca",
    "iso:country":"ES",
    "sg:address":"Avda Jaca, 2",
    "sg:city":"Madrid",
    "sg:orig_category":"Centros Empresariales",
    "sg:phone":"+34 913 20 50 04",
    "sg:postcode":"28022",
    "sg:province":"Madrid",
    "wof:name":"J Gervas Asesores S.l.",
    "wof:placetype":"venue"
},
  "geometry": {"coordinates":[-3.6104810238,40.447971344],"type":"Point"}
}