{
  "type": "Feature",
  "properties": {
    "iso:country":"ES",
    "sg:address":"Poligono, S/n",
    "sg:city":"Beniparrell",
    "sg:orig_category":"Empresas De Carpinter\u00cda Met\u00c1lica",
    "sg:phone":"+34 961 21 80 95",
    "sg:postcode":"46469",
    "sg:province":"Valencia",
    "wof:name":"Aluminios Cerratosa S.l.",
    "wof:placetype":"venue"
},
  "geometry": {"coordinates":[-0.3801681995,39.4218101501],"type":"Point"}
}