{
  "type": "Feature",
  "properties": {
    "addr:full":"Martieta Etxadia, 11 Arragua Guip\u00f9zcoa 20180",
    "addr:housenumber":"11",
    "addr:postcode":"20180",
    "addr:street":"Martieta Etxadia;Guipu\u0300Zcoa",
    "iso:country":"ES",
    "sg:address":"Martieta Etxadia, 11",
    "sg:city":"Arragua",
    "sg:orig_category":"Venta, Alquiler De Toldos",
    "sg:phone":"+34 943 26 02 82",
    "sg:postcode":"20180",
    "sg:province":"Guip\u00f9zcoa",
    "wof:name":"Gutierrez Serrano Antonio",
    "wof:placetype":"venue"
},
  "geometry": {"coordinates":[-1.8629590273,43.2992401123],"type":"Point"}
}