{
  "type": "Feature",
  "properties": {
    "addr:full":"Calle de Modesto Lafuente, 5 Madrid Madrid 28010",
    "addr:housenumber":"5",
    "addr:postcode":"28010",
    "addr:street":"Calle De Modesto Lafuente",
    "iso:country":"ES",
    "sg:address":"Calle de Modesto Lafuente, 5",
    "sg:city":"Madrid",
    "sg:orig_category":"Agentes Generales De Seguros",
    "sg:phone":"+34 914 45 39 28",
    "sg:postcode":"28010",
    "sg:province":"Madrid",
    "wof:name":"Panizo Lopez Angel",
    "wof:placetype":"venue"
},
  "geometry": {"coordinates":[-3.6964728832,40.4360351562],"type":"Point"}
}