{
  "type": "Feature",
  "properties": {
    "addr:full":"Estacion, S/n Iru\u00f1a Navarra 31012",
    "addr:postcode":"31012",
    "addr:street":"S / N Irun\u0303A Navarra",
    "iso:country":"ES",
    "sg:address":"Estacion, S/n",
    "sg:city":"Iru\u00f1a",
    "sg:orig_category":"Caf\u00c9s, Bares, Cervecer\u00cdas",
    "sg:phone":"+34 948 13 04 66",
    "sg:postcode":"31012",
    "sg:province":"Navarra",
    "wof:name":"Jimenez Alfaro Vicente",
    "wof:placetype":"venue"
},
  "geometry": {"coordinates":[-1.6606440544,42.82421875],"type":"Point"}
}