{
  "type": "Feature",
  "properties": {
    "iso:country":"ES",
    "sg:address":"Carr Francesc Moragas, 3",
    "sg:city":"Vilanova I La Geltru",
    "sg:orig_category":"Empresas De Vigilancia, Guardia Y Protecci\u00d3n",
    "sg:phone":"+34 938 15 88 26",
    "sg:postcode":"08800",
    "sg:province":"Barcelona",
    "wof:name":"Rueda Lopez Jose",
    "wof:placetype":"venue"
},
  "geometry": {"coordinates":[1.7142499685,41.2211952209],"type":"Point"}
}