{
  "type": "Feature",
  "properties": {
    "addr:full":"Avda Salvador Allende, 39 Zaragoza Zaragoza 50015",
    "addr:housenumber":"39",
    "addr:postcode":"50015",
    "addr:street":"Avda Salvador Allende",
    "iso:country":"ES",
    "sg:address":"Avda Salvador Allende, 39",
    "sg:city":"Zaragoza",
    "sg:classifiers":[
        {
            "category":"Personal",
            "subcategory":"Barber",
            "type":"Services"
        }
    ],
    "sg:phone":"+34 976 52 94 49",
    "sg:postcode":"50015",
    "sg:province":"Zaragoza",
    "sg:tags":[
        "caballeros",
        "de",
        "peluqueros"
    ],
    "wof:name":"Lafuente Carazo Victor Manuel",
    "wof:placetype":"venue"
},
  "geometry": {"coordinates":[-0.8771589994,41.67162323],"type":"Point"}
}