{
  "type": "Feature",
  "properties": {
    "iso:country":"ES",
    "sg:address":"Avda San Miguel, 5",
    "sg:city":"Chinchilla Monte-aragon",
    "sg:orig_category":"Reposter\u00cdas",
    "sg:phone":"+34 967 26 03 20",
    "sg:postcode":"02520",
    "sg:province":"Albacete",
    "wof:name":"Castillo Ballesteros Mariana",
    "wof:placetype":"venue"
},
  "geometry": {"coordinates":[-1.7232949734,38.9209251404],"type":"Point"}
}