{
  "type": "Feature",
  "properties": {
    "iso:country":"ES",
    "sg:address":"Calle de Azorin, 11",
    "sg:city":"Almeria",
    "sg:orig_category":"Abogados",
    "sg:phone":"+34 950 22 76 23",
    "sg:postcode":"04005",
    "sg:province":"Almer\u00eda",
    "wof:name":"Rodriguez Peon Maria Del Pilar",
    "wof:placetype":"venue"
},
  "geometry": {"coordinates":[-2.4571812153,36.8389701843],"type":"Point"}
}