{
  "type": "Feature",
  "properties": {
    "iso:country":"ES",
    "sg:address":"Carrer de Enten\u00c7a, 106",
    "sg:city":"Barcelona",
    "sg:orig_category":"Enfermeras: Consultas, Atenci\u00d3n A Domicilio",
    "sg:phone":"+34 933 25 90 46",
    "sg:postcode":"08015",
    "sg:province":"Barcelona",
    "wof:name":"Bernal Alonso Monica",
    "wof:placetype":"venue"
},
  "geometry": {"coordinates":[2.1497819424,41.3804397583],"type":"Point"}
}