{
  "type": "Feature",
  "properties": {
    "addr:full":"Avda Rosalia Castro, 8 Milladoiro La Coru\u00f1a 15895",
    "addr:housenumber":"8",
    "addr:postcode":"15895",
    "addr:street":"Avda Rosalia Castro;La Corun\u0303A",
    "iso:country":"ES",
    "sg:address":"Avda Rosalia Castro, 8",
    "sg:city":"Milladoiro",
    "sg:orig_category":"Muebles, Minoristas",
    "sg:phone":"+34 981 52 52 92",
    "sg:postcode":"15895",
    "sg:province":"La Coru\u00f1a",
    "wof:name":"Mondi Muebles Canarias S.l.",
    "wof:placetype":"venue"
},
  "geometry": {"coordinates":[-8.5750617981,42.8469314575],"type":"Point"}
}