{
  "type": "Feature",
  "properties": {
    "iso:country":"ES",
    "sg:address":"Calle de Pedro Antonio De Alarcon, 34",
    "sg:city":"Granada",
    "sg:orig_category":"Asesor\u00cda, Estudio Y Control Medioambiental",
    "sg:phone":"+34 958 53 56 25",
    "sg:postcode":"18002",
    "sg:province":"Granada",
    "wof:name":"Tecnologia De La Naturaleza S.l.",
    "wof:placetype":"venue"
},
  "geometry": {"coordinates":[-3.6057419777,37.1721382141],"type":"Point"}
}