{
  "type": "Feature",
  "properties": {
    "addr:full":"Calle de Carmen Perez Pascual, 34 Puerto De Santa Maria C\u00e1diz 11500",
    "addr:housenumber":"34",
    "addr:postcode":"11500",
    "addr:street":"Calle De Carmen Perez Pascual;Ca\u0301Diz",
    "iso:country":"ES",
    "sg:address":"Calle de Carmen Perez Pascual, 34",
    "sg:city":"Puerto De Santa Maria",
    "sg:orig_category":"Negocio De Materiales De Construcci\u00d3n",
    "sg:phone":"+34 956 85 79 19",
    "sg:postcode":"11500",
    "sg:province":"C\u00e1diz",
    "wof:name":"Caballero Conejo Antonio",
    "wof:placetype":"venue"
},
  "geometry": {"coordinates":[-6.2260379791,36.6034088135],"type":"Point"}
}