{
  "type": "Feature",
  "properties": {
    "addr:full":"Calle de Sierra De Cazorla, 1 Torremolinos M\u00e1laga 29620",
    "addr:housenumber":"1",
    "addr:postcode":"29620",
    "addr:street":"Calle De Sierra De Cazorla;Ma\u0301Laga",
    "iso:country":"ES",
    "sg:address":"Calle de Sierra De Cazorla, 1",
    "sg:city":"Torremolinos",
    "sg:orig_category":"Cer\u00c1mica Art\u00cdstica Y Decorativa",
    "sg:phone":"+34 952 37 04 62",
    "sg:postcode":"29620",
    "sg:province":"M\u00e1laga",
    "wof:name":"Vallejo Ruiz Irene",
    "wof:placetype":"venue"
},
  "geometry": {"coordinates":[-4.4964561462,36.6222381592],"type":"Point"}
}