{
  "type": "Feature",
  "properties": {
    "addr:full":"Carrer de Bac De Roda, 49 Vic Barcelona 08500",
    "addr:housenumber":"49",
    "addr:postcode":"08500",
    "addr:street":"Carrer De Bac De Roda",
    "iso:country":"ES",
    "sg:address":"Carrer de Bac De Roda, 49",
    "sg:city":"Vic",
    "sg:orig_category":"Reciclaje, Tratamiento De Tejidos",
    "sg:phone":"+34 938 85 08 77",
    "sg:postcode":"08500",
    "sg:province":"Barcelona",
    "wof:name":"Casanpere Vall Jaume",
    "wof:placetype":"venue"
},
  "geometry": {"coordinates":[2.262706995,41.9241256714],"type":"Point"}
}