{
  "type": "Feature",
  "properties": {
    "addr:full":"Ctra. General, S/n Guia Isora Santa Cruz De Tenerife 38680",
    "addr:postcode":"38680",
    "addr:street":"Ctra. General S / N Guia",
    "iso:country":"ES",
    "sg:address":"Ctra. General, S/n",
    "sg:city":"Guia Isora",
    "sg:orig_category":"Ense\u00d1anza, Formaci\u00d3n Profesional: Aprendizaje",
    "sg:phone":"+34 922 85 13 20",
    "sg:postcode":"38680",
    "sg:province":"Santa Cruz De Tenerife",
    "wof:name":"Ayuntamiento De Guia De Isora",
    "wof:placetype":"venue"
},
  "geometry": {"coordinates":[-16.7657680511,28.1890926361],"type":"Point"}
}