{
  "type": "Feature",
  "properties": {
    "iso:country":"ES",
    "sg:address":"Calle de Felipe Ii, 7",
    "sg:city":"Sevilla",
    "sg:orig_category":"Contenedores (mercanc\u00cdas)",
    "sg:phone":"+34 954 23 19 60",
    "sg:postcode":"41013",
    "sg:province":"Sevilla",
    "wof:name":"J. Tavallo S.l.",
    "wof:placetype":"venue"
},
  "geometry": {"coordinates":[-5.9839658737,37.3720436096],"type":"Point"}
}