{
  "type": "Feature",
  "properties": {
    "addr:full":"Avda Espa\u00d1a (de), 18 San Sebastian De Los Reyes Madrid 28700",
    "addr:housenumber":"18",
    "addr:postcode":"28700",
    "addr:street":"Avda Espan\u0303A De",
    "iso:country":"ES",
    "sg:address":"Avda Espa\u00d1a (de), 18",
    "sg:city":"San Sebastian De Los Reyes",
    "sg:orig_category":"Agencias De Viajes",
    "sg:phone":"+34 916 58 60 50",
    "sg:postcode":"28700",
    "sg:province":"Madrid",
    "sg:website":"www.viajesiberia.com",
    "wof:name":"Viajes Iberia S.a.",
    "wof:placetype":"venue"
},
  "geometry": {"coordinates":[-3.6315460205,40.5448722839],"type":"Point"}
}