{
  "type": "Feature",
  "properties": {
    "addr:full":"Calle de Doctor Sventenius, 14 Palmas De Gran Canaria Las Palmas 35016",
    "addr:housenumber":"14",
    "addr:postcode":"35016",
    "addr:street":"Calle De Doctor Sventenius",
    "iso:country":"ES",
    "sg:address":"Calle de Doctor Sventenius, 14",
    "sg:city":"Palmas De Gran Canaria",
    "sg:orig_category":"Ense\u00d1ante, Direcci\u00d3n",
    "sg:phone":"+34 928 31 50 70",
    "sg:postcode":"35016",
    "sg:province":"Las Palmas",
    "wof:name":"Gonzalez Monzon Josefa",
    "wof:placetype":"venue"
},
  "geometry": {"coordinates":[-15.419757843,28.0836048126],"type":"Point"}
}