{
  "type": "Feature",
  "properties": {
    "iso:country":"ES",
    "sg:address":"Rond General Mitre, 179",
    "sg:city":"Barcelona",
    "sg:orig_category":"Artes Gr\u00c1ficas, Artes Pl\u00c1sticas: Material Y Suministros (al Por Menor)",
    "sg:phone":"+34 934 17 09 06",
    "sg:postcode":"08023",
    "sg:province":"Barcelona",
    "wof:name":"Ecoimpres Xxi Sl",
    "wof:placetype":"venue"
},
  "geometry": {"coordinates":[2.1410839558,41.404712677],"type":"Point"}
}