{
  "type": "Feature",
  "properties": {
    "addr:full":"Calle de Senegal, S/n Jerez De La Frontera C\u00e1diz 11408",
    "addr:housenumber":"s / n",
    "addr:postcode":"11408",
    "addr:street":"Calle De Senegal",
    "iso:country":"ES",
    "sg:address":"Calle de Senegal, S/n",
    "sg:city":"Jerez De La Frontera",
    "sg:orig_category":"Transporte En General",
    "sg:phone":"+34 956 14 16 82",
    "sg:postcode":"11408",
    "sg:province":"C\u00e1diz",
    "wof:name":"Delta Logistics Solucions S.l.",
    "wof:placetype":"venue"
},
  "geometry": {"coordinates":[-6.1592831612,36.6686592102],"type":"Point"}
}