{
  "type": "Feature",
  "properties": {
    "iso:country":"ES",
    "sg:address":"Calle de Andres Arbiol, 58",
    "sg:city":"Albal",
    "sg:orig_category":"Pescader\u00cdas (al Por Menor)",
    "sg:phone":"+34 961 27 01 57",
    "sg:postcode":"46470",
    "sg:province":"Valencia",
    "wof:name":"Cebrian Fernandez Amparo",
    "wof:placetype":"venue"
},
  "geometry": {"coordinates":[-0.4088861942,39.3955459595],"type":"Point"}
}