{
  "type": "Feature",
  "properties": {
    "addr:full":"Av J.m.quadrado, 43 Mao Islas Baleares 07703",
    "addr:housenumber":"43",
    "addr:postcode":"07703",
    "addr:street":"Av J.M.Quadrado",
    "iso:country":"ES",
    "sg:address":"Av J.m.quadrado, 43",
    "sg:city":"Mao",
    "sg:orig_category":"Deportes Diversos",
    "sg:phone":"+34 971 35 46 54",
    "sg:postcode":"07703",
    "sg:province":"Islas Baleares",
    "wof:name":"Jose Maria Pons Y Monserrat Grandio S.l.",
    "wof:placetype":"venue"
},
  "geometry": {"coordinates":[4.2567400932,39.8892440796],"type":"Point"}
}