{
  "type": "Feature",
  "properties": {
    "iso:country":"ES",
    "sg:address":"Calle de Dionisio Casa\u00d1al, 1",
    "sg:city":"Zaragoza",
    "sg:orig_category":"Fabricaci\u00d3n De Bolsos Y Bolsos De Tela",
    "sg:phone":"+34 976 43 20 78",
    "sg:postcode":"50003",
    "sg:province":"Zaragoza",
    "wof:name":"Sacos Ambroj S.c.",
    "wof:placetype":"venue"
},
  "geometry": {"coordinates":[-0.8930004835,41.660572052],"type":"Point"}
}