{
  "type": "Feature",
  "properties": {
    "addr:full":"Calle de Hoya (la), 46 Puerto Cruz Santa Cruz De Tenerife 38400",
    "addr:housenumber":"46",
    "addr:postcode":"38400",
    "addr:street":"Calle De Hoya La;Puerto Cruz",
    "iso:country":"ES",
    "sg:address":"Calle de Hoya (la), 46",
    "sg:city":"Puerto Cruz",
    "sg:orig_category":"Camiser\u00cda Y Ropa Interior Masculina (al Por Menor)",
    "sg:phone":"+34 922 37 13 75",
    "sg:postcode":"38400",
    "sg:province":"Santa Cruz De Tenerife",
    "wof:name":"Namaste Dial S.l.",
    "wof:placetype":"venue"
},
  "geometry": {"coordinates":[9.0760097504,52.7750091553],"type":"Point"}
}