{
  "type": "Feature",
  "properties": {
    "iso:country":"ES",
    "sg:address":"Calle de Renteria, 13",
    "sg:city":"Donostia-san Sebastian",
    "sg:orig_category":"Inmobiliaria (agencias)",
    "sg:phone":"+34 943 32 20 15",
    "sg:postcode":"20013",
    "sg:province":"Guip\u00f9zcoa",
    "wof:name":"Delgado Riezu Juan Jesus",
    "wof:placetype":"venue"
},
  "geometry": {"coordinates":[-1.9684089422,43.3232002258],"type":"Point"}
}