{
  "type": "Feature",
  "properties": {
    "addr:full":"Carrer de Miguel De Cervantes, 5 Ametlla Mar Tarragona 43860",
    "addr:housenumber":"5",
    "addr:postcode":"43860",
    "addr:street":"Carrer De Miguel De Cervantes",
    "iso:country":"ES",
    "sg:address":"Carrer de Miguel De Cervantes, 5",
    "sg:city":"Ametlla Mar",
    "sg:orig_category":"Florister\u00cdas",
    "sg:phone":"+34 977 45 70 93",
    "sg:postcode":"43860",
    "sg:province":"Tarragona",
    "wof:name":"Mora Romero Jose Maria",
    "wof:placetype":"venue"
},
  "geometry": {"coordinates":[0.8034030199,40.8843574524],"type":"Point"}
}