{
  "type": "Feature",
  "properties": {
    "iso:country":"ES",
    "sg:address":"Rua Doutor Xerman Alonso Hortas, 25",
    "sg:city":"Lugo",
    "sg:orig_category":"Material Y Suministros Para Peluquer\u00cda",
    "sg:phone":"+34 982 20 33 08",
    "sg:postcode":"27004",
    "sg:province":"Lugo",
    "wof:name":"Prodube S.l.",
    "wof:placetype":"venue"
},
  "geometry": {"coordinates":[-7.5641818047,43.012096405],"type":"Point"}
}