{
  "type": "Feature",
  "properties": {
    "iso:country":"ES",
    "sg:address":"Carrer de Mallorca, 328",
    "sg:city":"Barcelona",
    "sg:orig_category":"Ingenier\u00cda, Centros De Estudios (diversos)",
    "sg:phone":"+34 934 59 44 06",
    "sg:postcode":"08037",
    "sg:province":"Barcelona",
    "wof:name":"Imogep S.a.",
    "wof:placetype":"venue"
},
  "geometry": {"coordinates":[2.1685130596,41.3981246948],"type":"Point"}
}