{
  "type": "Feature",
  "properties": {
    "addr:full":"Calle de Almendros (de Los), S/n Arganda Madrid 28500",
    "addr:postcode":"28500",
    "addr:street":"Calle De Almendros De Los S / N",
    "iso:country":"ES",
    "sg:address":"Calle de Almendros (de Los), S/n",
    "sg:city":"Arganda",
    "sg:orig_category":"Molduras, Junquillos, Listones Y Molduras Perforadas",
    "sg:phone":"+34 918 70 02 13",
    "sg:postcode":"28500",
    "sg:province":"Madrid",
    "wof:name":"Cerveceria Rangel C.b.",
    "wof:placetype":"venue"
},
  "geometry": {"coordinates":[-3.4358210564,40.2991333008],"type":"Point"}
}