{
  "type": "Feature",
  "properties": {
    "iso:country":"ES",
    "sg:address":"Carrer de Sant Cugat, 42",
    "sg:city":"Sabadell",
    "sg:orig_category":"Centros Empresariales",
    "sg:phone":"+34 937 25 25 91",
    "sg:postcode":"08201",
    "sg:province":"Barcelona",
    "wof:name":"Control Guar Sabadell S.l.",
    "wof:placetype":"venue"
},
  "geometry": {"coordinates":[2.1048300266,41.5454826355],"type":"Point"}
}