{
  "type": "Feature",
  "properties": {
    "iso:country":"ES",
    "sg:address":"Carrer de Major, 11",
    "sg:city":"Santa Barbara",
    "sg:orig_category":"Producci\u00d3n De Abonos Y De Fertilizantes",
    "sg:phone":"+34 977 71 80 61",
    "sg:postcode":"43570",
    "sg:province":"Tarragona",
    "wof:name":"Torres Monllau Jose",
    "wof:placetype":"venue"
},
  "geometry": {"coordinates":[0.4914380014,40.714427948],"type":"Point"}
}