{
  "type": "Feature",
  "properties": {
    "iso:country":"ES",
    "sg:address":"Avda Rey Don Jaime, 1",
    "sg:city":"Castellon",
    "sg:orig_category":"Inmobiliaria (agencias)",
    "sg:phone":"+34 964 24 29 33",
    "sg:postcode":"12001",
    "sg:province":"Castell\u00f3n",
    "sg:website":"www.zhanetdifference.com",
    "wof:name":"Antersa Castellon S.l.",
    "wof:placetype":"venue"
},
  "geometry": {"coordinates":[-0.0408436991,39.9853630066],"type":"Point"}
}