{
  "type": "Feature",
  "properties": {
    "addr:full":"Ctra Sevilla, 113 Algaba Sevilla 41980",
    "addr:housenumber":"113",
    "addr:postcode":"41980",
    "addr:street":"Ctra Sevilla",
    "iso:country":"ES",
    "sg:address":"Ctra Sevilla, 113",
    "sg:city":"Algaba",
    "sg:orig_category":"Promotores Constructores",
    "sg:phone":"+34 954 11 98 80",
    "sg:postcode":"41980",
    "sg:province":"Sevilla",
    "sg:website":"www.fadesa.es",
    "wof:name":"Fadesa Inmobiliaria S.a.",
    "wof:placetype":"venue"
},
  "geometry": {"coordinates":[-6.0153942108,37.4607162476],"type":"Point"}
}