{
  "type": "Feature",
  "properties": {
    "iso:country":"ES",
    "sg:address":"Carrer de Orso, 41",
    "sg:city":"Rubi",
    "sg:orig_category":"Artes Gr\u00c1ficas, Artes Pl\u00c1sticas (curso)",
    "sg:phone":"+34 936 97 07 55",
    "sg:postcode":"08191",
    "sg:province":"Barcelona",
    "wof:name":"Garcia Estepa Juan Carlos",
    "wof:placetype":"venue"
},
  "geometry": {"coordinates":[2.0332129002,41.4949264526],"type":"Point"}
}