{
  "type": "Feature",
  "properties": {
    "iso:country":"ES",
    "sg:address":"Calle de Emiliano Barral, 6",
    "sg:city":"Madrid",
    "sg:orig_category":"Fotograf\u00cda Art\u00cdstica Y Retratos",
    "sg:phone":"+34 915 19 81 32",
    "sg:postcode":"28043",
    "sg:province":"Madrid",
    "wof:name":"Porrua Rosa Jose Luis",
    "wof:placetype":"venue"
},
  "geometry": {"coordinates":[-3.6601369381,40.4493141174],"type":"Point"}
}