{
  "type": "Feature",
  "properties": {
    "addr:full":"Calle de Serapio Mugica, 10 Irun Guip\u00f9zcoa 20302",
    "addr:housenumber":"10",
    "addr:postcode":"20302",
    "addr:street":"Calle De Serapio Mugica;Guipu\u0300Zcoa",
    "iso:country":"ES",
    "sg:address":"Calle de Serapio Mugica, 10",
    "sg:city":"Irun",
    "sg:orig_category":"Complementos De Vestir (al Por Menor)",
    "sg:phone":"+34 943 61 74 39",
    "sg:postcode":"20302",
    "sg:province":"Guip\u00f9zcoa",
    "wof:name":"Irastorza Michelena Manuela",
    "wof:placetype":"venue"
},
  "geometry": {"coordinates":[-1.7959649563,43.339176178],"type":"Point"}
}