{
  "type": "Feature",
  "properties": {
    "iso:country":"ES",
    "sg:address":"Calle de Poeta Manuel Alcantara, 6",
    "sg:city":"Rincon Victoria",
    "sg:orig_category":"Laboratorios Y Cl\u00cdnicas Veterinarias",
    "sg:phone":"+34 952 97 23 02",
    "sg:postcode":"29730",
    "sg:province":"M\u00e1laga",
    "wof:name":"Diez Posse Maria Dolores",
    "wof:placetype":"venue"
},
  "geometry": {"coordinates":[-4.2795829773,36.7158584595],"type":"Point"}
}