{
  "type": "Feature",
  "properties": {
    "iso:country":"ES",
    "sg:address":"Calle de Azahar, 9",
    "sg:city":"Costa Oeste",
    "sg:orig_category":"Arquitectos",
    "sg:phone":"+34 956 85 07 08",
    "sg:postcode":"11500",
    "sg:province":"C\u00e1diz",
    "wof:name":"Cuvillo Jimenez Antonio",
    "wof:placetype":"venue"
},
  "geometry": {"coordinates":[-6.2197542191,36.6056632996],"type":"Point"}
}