{
  "type": "Feature",
  "properties": {
    "iso:country":"ES",
    "sg:address":"Pase Eduardo Chillida, 9",
    "sg:city":"Donostia-san Sebastian",
    "sg:orig_category":"Pistas Y Clases De Tenis",
    "sg:phone":"+34 943 21 51 61",
    "sg:postcode":"20008",
    "sg:province":"Guip\u00f9zcoa",
    "sg:website":"www.rctss.com",
    "wof:name":"Real Club De Tenis De San Sebastian",
    "wof:placetype":"venue"
},
  "geometry": {"coordinates":[-2.0402700901,43.3095817566],"type":"Point"}
}