{
  "type": "Feature",
  "properties": {
    "iso:country":"ES",
    "sg:address":"Calle de Rio Guadalquivir, 7",
    "sg:city":"Torrejon Ardoz",
    "sg:orig_category":"Metales (labores, Pulido)",
    "sg:phone":"+34 916 75 09 43",
    "sg:postcode":"28850",
    "sg:province":"Madrid",
    "wof:name":"Talleres Norma S. A.",
    "wof:placetype":"venue"
},
  "geometry": {"coordinates":[-3.4647209644,40.4602241516],"type":"Point"}
}