{
  "type": "Feature",
  "properties": {
    "addr:full":"Calle de Doctor Miguel Rosas, 37 Palmas De Gran Canaria Las Palmas 35007",
    "addr:postcode":"35007",
    "addr:street":"Calle De Doctor Miguel Rosas 37",
    "iso:country":"ES",
    "sg:address":"Calle de Doctor Miguel Rosas, 37",
    "sg:city":"Palmas De Gran Canaria",
    "sg:orig_category":"Agencias Y Agentes Comerciales, Representantes",
    "sg:phone":"+34 928 22 44 11",
    "sg:postcode":"35007",
    "sg:province":"Las Palmas",
    "wof:name":"Szlosek  Josefina",
    "wof:placetype":"venue"
},
  "geometry": {"coordinates":[-15.4332084656,28.1405162811],"type":"Point"}
}