{
  "type": "Feature",
  "properties": {
    "iso:country":"ES",
    "sg:address":"Calle de Sangenjo, 13",
    "sg:city":"Madrid",
    "sg:orig_category":"Limpieza Industrial",
    "sg:phone":"+34 917 30 69 30",
    "sg:postcode":"28034",
    "sg:province":"Madrid",
    "wof:name":"Couso Blanco Manuel",
    "wof:placetype":"venue"
},
  "geometry": {"coordinates":[-3.7014670372,40.484500885],"type":"Point"}
}