{
  "type": "Feature",
  "properties": {
    "iso:country":"ES",
    "sg:address":"Pla\u00c7 La Sal, 11",
    "sg:city":"Lleida",
    "sg:orig_category":"Ropa Para Se\u00d1oras (al Por Menor)",
    "sg:phone":"+34 973 24 70 25",
    "sg:postcode":"25007",
    "sg:province":"Lleida",
    "wof:name":"Casalilla Puertolas Inmaculada",
    "wof:placetype":"venue"
},
  "geometry": {"coordinates":[0.627129972,41.6145210266],"type":"Point"}
}