{
  "type": "Feature",
  "properties": {
    "addr:full":"Calle de Tras De Las Casas, S/n Zuheros C\u00f3rdoba 14870",
    "addr:housenumber":"s",
    "addr:postcode":"14870",
    "addr:street":"Calle De Tras De Las Casas;/ N;Co\u0301Rdoba",
    "iso:country":"ES",
    "sg:address":"Calle de Tras De Las Casas, S/n",
    "sg:city":"Zuheros",
    "sg:orig_category":"Alquiler De Casas Y Habitaciones Amuebladas",
    "sg:phone":"+34 957 69 46 42",
    "sg:postcode":"14870",
    "sg:province":"C\u00f3rdoba",
    "wof:name":"Ortiz Exposito Jose",
    "wof:placetype":"venue"
},
  "geometry": {"coordinates":[-4.3147788048,37.5447998047],"type":"Point"}
}