{
  "type": "Feature",
  "properties": {
    "addr:full":"Los Limoneros, 196 Elviria M\u00e1laga 29604",
    "addr:housenumber":"196",
    "addr:postcode":"29604",
    "addr:street":"Los Limoneros;Ma\u0301Laga",
    "iso:country":"ES",
    "sg:address":"Los Limoneros, 196",
    "sg:city":"Elviria",
    "sg:orig_category":"Financiaci\u00d3n Y Cr\u00c9ditos",
    "sg:phone":"+34 952 83 13 97",
    "sg:postcode":"29604",
    "sg:province":"M\u00e1laga",
    "wof:name":"Mapex Establishment",
    "wof:placetype":"venue"
},
  "geometry": {"coordinates":[-4.8104672432,36.5068321228],"type":"Point"}
}