{
  "type": "Feature",
  "properties": {
    "iso:country":"ES",
    "sg:address":"Calle de Fermin Canella, S/n",
    "sg:city":"Gijon",
    "sg:orig_category":"Peluqueros: De Se\u00d1oras",
    "sg:phone":"+34 985 34 34 58",
    "sg:postcode":"33207",
    "sg:province":"Asturias",
    "wof:name":"Garcia Hernando Maria Pilar",
    "wof:placetype":"venue"
},
  "geometry": {"coordinates":[-5.6686205864,43.5397453308],"type":"Point"}
}