{
  "type": "Feature",
  "properties": {
    "addr:full":"Calle de Real, 75 Villanueva Vera C\u00e1ceres 10470",
    "addr:housenumber":"75",
    "addr:postcode":"10470",
    "addr:street":"Calle De Real;Ca\u0301Ceres",
    "iso:country":"ES",
    "sg:address":"Calle de Real, 75",
    "sg:city":"Villanueva Vera",
    "sg:orig_category":"Alimentaci\u00d3n General (al Por Menor)",
    "sg:phone":"+34 927 56 60 28",
    "sg:postcode":"10470",
    "sg:province":"C\u00e1ceres",
    "wof:name":"Caset Timon Tomas",
    "wof:placetype":"venue"
},
  "geometry": {"coordinates":[-5.4632191658,40.128868103],"type":"Point"}
}