{
  "type": "Feature",
  "properties": {
    "addr:full":"Calle de Salamanca, 18 Albacete Albacete 02001",
    "addr:housenumber":"18",
    "addr:postcode":"02001",
    "addr:street":"Calle De Salamanca",
    "iso:country":"ES",
    "sg:address":"Calle de Salamanca, 18",
    "sg:city":"Albacete",
    "sg:orig_category":"Internados & Ense\u00d1anza Privada",
    "sg:phone":"+34 967 52 26 97",
    "sg:postcode":"02001",
    "sg:province":"Albacete",
    "wof:name":"Religiosas Dominicas De La Anunciata",
    "wof:placetype":"venue"
},
  "geometry": {"coordinates":[-1.8519090414,38.9962692261],"type":"Point"}
}