{
  "type": "Feature",
  "properties": {
    "addr:full":"Rbla Sant Jordi (de), 58 Ripollet Barcelona 08291",
    "addr:housenumber":"58",
    "addr:postcode":"08291",
    "addr:street":"Rbla Sant Jordi De",
    "iso:country":"ES",
    "sg:address":"Rbla Sant Jordi (de), 58",
    "sg:city":"Ripollet",
    "sg:orig_category":"Laboratorios Y Trabajos De Fotograf\u00cda, V\u00cddeo Y Cine",
    "sg:phone":"+34 936 91 25 65",
    "sg:postcode":"08291",
    "sg:province":"Barcelona",
    "sg:website":"www.fotoprix.es",
    "wof:name":"Fotoprix Sa.",
    "wof:placetype":"venue"
},
  "geometry": {"coordinates":[2.1614480019,41.4967079163],"type":"Point"}
}