{
  "type": "Feature",
  "properties": {
    "addr:full":"Pagoaldea Poligonoa, 2 Ergoien Guip\u00f9zcoa 20180",
    "addr:housenumber":"2",
    "addr:postcode":"20180",
    "addr:street":"Pagoaldea Poligonoa;Guipu\u0300Zcoa",
    "iso:country":"ES",
    "sg:address":"Pagoaldea Poligonoa, 2",
    "sg:city":"Ergoien",
    "sg:orig_category":"Empresas De Carpinter\u00cda",
    "sg:phone":"+34 943 49 08 25",
    "sg:postcode":"20180",
    "sg:province":"Guip\u00f9zcoa",
    "wof:name":"Crespo Roman Luciano",
    "wof:placetype":"venue"
},
  "geometry": {"coordinates":[-1.8629590273,43.2992401123],"type":"Point"}
}