{
  "type": "Feature",
  "properties": {
    "addr:full":"Calle de Guitarra, 8 Madrid Madrid 28044",
    "addr:housenumber":"8",
    "addr:postcode":"madrid;28044",
    "addr:street":"Calle De Guitarra",
    "iso:country":"ES",
    "sg:address":"Calle de Guitarra, 8",
    "sg:city":"Madrid",
    "sg:orig_category":"Tratamientos De Conversi\u00d3n Qu\u00cdmica O Electrol\u00cdtica De Metales",
    "sg:phone":"+34 915 11 16 97",
    "sg:postcode":"28044",
    "sg:province":"Madrid",
    "wof:name":"Olympus Optical Espa\u00d1a S.a.",
    "wof:placetype":"venue"
},
  "geometry": {"coordinates":[-3.7530360222,40.3713264465],"type":"Point"}
}