{
  "type": "Feature",
  "properties": {
    "iso:country":"ES",
    "sg:address":"Calle de Alabarderos, 2",
    "sg:city":"Membrilla",
    "sg:orig_category":"Florister\u00cdas",
    "sg:phone":"+34 926 63 69 14",
    "sg:postcode":"13230",
    "sg:province":"Ciudad Real",
    "wof:name":"Jimenez Mu\u00f1oz Antonio",
    "wof:placetype":"venue"
},
  "geometry": {"coordinates":[-3.3465828896,38.9685897827],"type":"Point"}
}