{
  "type": "Feature",
  "properties": {
    "addr:full":"Calle de Real, 22 Viator Almer\u00eda 04240",
    "addr:housenumber":"22",
    "addr:postcode":"04240",
    "addr:street":"Calle De Real;Almeri\u0301A",
    "iso:country":"ES",
    "sg:address":"Calle de Real, 22",
    "sg:city":"Viator",
    "sg:orig_category":"Inmobiliaria (alquileres Por Temporada Y Temporales)",
    "sg:phone":"+34 950 30 45 04",
    "sg:postcode":"04240",
    "sg:province":"Almer\u00eda",
    "wof:name":"Inmobiliaria Musan S.l.",
    "wof:placetype":"venue"
},
  "geometry": {"coordinates":[-2.4264431,36.8884277344],"type":"Point"}
}