{
  "type": "Feature",
  "properties": {
    "iso:country":"ES",
    "sg:address":"Calle de San Juan, 6",
    "sg:city":"Segovia",
    "sg:orig_category":"M\u00c1rmoles, Granitos Y Piedras Naturales",
    "sg:phone":"+34 921 46 33 40",
    "sg:postcode":"40001",
    "sg:province":"Segovia",
    "wof:name":"Martin Viniegra Valentin",
    "wof:placetype":"venue"
},
  "geometry": {"coordinates":[-4.1174998283,40.9490242004],"type":"Point"}
}