{
  "type": "Feature",
  "properties": {
    "addr:full":"Calle de Lope De Irigoyen, 9 Irun Guip\u00f9zcoa 20301",
    "addr:housenumber":"9",
    "addr:postcode":"20301",
    "addr:street":"Calle De Lope De Irigoyen;Guipu\u0300Zcoa",
    "iso:country":"ES",
    "sg:address":"Calle de Lope De Irigoyen, 9",
    "sg:city":"Irun",
    "sg:orig_category":"Alquiler De Veh\u00cdculos: Turismos Y Utilitarios",
    "sg:phone":"+34 943 61 28 66",
    "sg:postcode":"20301",
    "sg:province":"Guip\u00f9zcoa",
    "wof:name":"Construcciones Legasa S. A.",
    "wof:placetype":"venue"
},
  "geometry": {"coordinates":[7.5249300003,51.0156097412],"type":"Point"}
}