{
  "type": "Feature",
  "properties": {
    "addr:full":"Calle de Capitan Cortes, 6 Logro\u00f1o La Rioja 26003",
    "addr:housenumber":"6",
    "addr:postcode":"26003",
    "addr:street":"Calle De Capitan Cortes;Rioja",
    "iso:country":"ES",
    "sg:address":"Calle de Capitan Cortes, 6",
    "sg:city":"Logro\u00f1o",
    "sg:orig_category":"Ropa Para Se\u00d1oras Y Caballeros (al Por Menor)",
    "sg:phone":"+34 941 23 19 58",
    "sg:postcode":"26003",
    "sg:province":"La Rioja",
    "sg:website":"www.adolfo-dominguez.com",
    "wof:name":"Las Telas De Conchi S.l",
    "wof:placetype":"venue"
},
  "geometry": {"coordinates":[-2.4424417019,42.4642753601],"type":"Point"}
}