{
  "type": "Feature",
  "properties": {
    "addr:full":"Calle de Rocafort, 129 Madrid Madrid 28021",
    "addr:housenumber":"129",
    "addr:postcode":"28021",
    "addr:street":"Calle De Rocafort",
    "iso:country":"ES",
    "sg:address":"Calle de Rocafort, 129",
    "sg:city":"Madrid",
    "sg:classifiers":[
        {
            "category":"Personal",
            "subcategory":"Barber",
            "type":"Services"
        }
    ],
    "sg:phone":"+34 917 98 39 25",
    "sg:postcode":"28021",
    "sg:province":"Madrid",
    "sg:tags":[
        "caballeros",
        "de",
        "peluqueros"
    ],
    "wof:name":"Prieto Arrabal Gonzalo",
    "wof:placetype":"venue"
},
  "geometry": {"coordinates":[-3.6855449677,40.3430633545],"type":"Point"}
}