{
  "type": "Feature",
  "properties": {
    "iso:country":"ES",
    "sg:address":"Calle de Poeta Francisco Antonio Jimenez, 33",
    "sg:city":"Yecla",
    "sg:orig_category":"Tapicer\u00cdas",
    "sg:phone":"+34 968 71 91 11",
    "sg:postcode":"30510",
    "sg:province":"Murcia",
    "sg:website":"www.frajumar.com",
    "wof:name":"Tapizados Frajumar Sl",
    "wof:placetype":"venue"
},
  "geometry": {"coordinates":[-1.173699379,38.6051635742],"type":"Point"}
}