{
  "type": "Feature",
  "properties": {
    "addr:full":"Calle de Ca\u00d1averal, 39 Villaverde Rio Sevilla 41318",
    "addr:housenumber":"39",
    "addr:postcode":"41318",
    "addr:street":"Calle De Can\u0303Averal",
    "iso:country":"ES",
    "sg:address":"Calle de Ca\u00d1averal, 39",
    "sg:city":"Villaverde Rio",
    "sg:orig_category":"Autob\u00das (explotaci\u00d3n Y Servicios De)",
    "sg:phone":"+34 955 73 63 79",
    "sg:postcode":"41318",
    "sg:province":"Sevilla",
    "wof:name":"Autocares Villaverde Haro S.l.",
    "wof:placetype":"venue"
},
  "geometry": {"coordinates":[-5.869222641,37.5862808228],"type":"Point"}
}