{
  "type": "Feature",
  "properties": {
    "iso:country":"ES",
    "sg:address":"Pago Humo (del), Km. 0003,0",
    "sg:city":"Pago Humo",
    "sg:orig_category":"Ingenier\u00cda, Centros De Estudios (diversos)",
    "sg:phone":"+34 956 40 62 32",
    "sg:postcode":"11130",
    "sg:province":"C\u00e1diz",
    "wof:name":"Modus Hispanica S.l.",
    "wof:placetype":"venue"
},
  "geometry": {"coordinates":[-6.1447038651,36.4212188721],"type":"Point"}
}