{
  "type": "Feature",
  "properties": {
    "addr:full":"Carr Sant Vicent De Paul, 1 Quart Poblet Valencia 46930",
    "addr:housenumber":"1",
    "addr:postcode":"46930",
    "addr:street":"Carr Sant Vicent De Paul;Poblet",
    "iso:country":"ES",
    "sg:address":"Carr Sant Vicent De Paul, 1",
    "sg:city":"Quart Poblet",
    "sg:orig_category":"Empresas De Carpinter\u00cda De Madera",
    "sg:phone":"+34 961 52 41 69",
    "sg:postcode":"46930",
    "sg:province":"Valencia",
    "wof:name":"Ferrer Duran Emilio Tomas",
    "wof:placetype":"venue"
},
  "geometry": {"coordinates":[-0.4384920001,39.481388092],"type":"Point"}
}