{
  "type": "Feature",
  "properties": {
    "iso:country":"ES",
    "sg:address":"Calle de Castillo, 8",
    "sg:city":"Zaragoza",
    "sg:orig_category":"Transportes Por V\u00cdas Navegables",
    "sg:phone":"+34 976 44 25 63",
    "sg:postcode":"50004",
    "sg:province":"Zaragoza",
    "wof:name":"Transportes Alfa S.l.",
    "wof:placetype":"venue"
},
  "geometry": {"coordinates":[-0.8947979808,41.6563568115],"type":"Point"}
}