{
  "type": "Feature",
  "properties": {
    "addr:full":"Pl. Vila, 3 Vilavella Castell\u00f3n 12526",
    "addr:housenumber":"3",
    "addr:postcode":"12526",
    "addr:street":"Vila;Castello\u0301N",
    "iso:country":"ES",
    "sg:address":"Pl. Vila, 3",
    "sg:city":"Vilavella",
    "sg:orig_category":"Molduras, Junquillos, Listones Y Molduras Perforadas",
    "sg:phone":"+34 964 67 77 69",
    "sg:postcode":"12526",
    "sg:province":"Castell\u00f3n",
    "wof:name":"Marquez Puertolas Margarita",
    "wof:placetype":"venue"
},
  "geometry": {"coordinates":[-0.1848009974,39.8590774536],"type":"Point"}
}