{
  "type": "Feature",
  "properties": {
    "addr:full":"Antonio Meiras, S/n Viveiro Lugo 27850",
    "addr:housenumber":"s / n",
    "addr:postcode":"27850",
    "iso:country":"ES",
    "sg:address":"Antonio Meiras, S/n",
    "sg:city":"Viveiro",
    "sg:orig_category":"Ense\u00d1anza, Formaci\u00d3n Profesional: Aprendizaje",
    "sg:phone":"+34 982 56 21 12",
    "sg:postcode":"27850",
    "sg:province":"Lugo",
    "wof:name":"Concello De Viveiro-pavillon Municipal Dos Deportes",
    "wof:placetype":"venue"
},
  "geometry": {"coordinates":[-7.5911931992,43.6644439697],"type":"Point"}
}