{
  "type": "Feature",
  "properties": {
    "iso:country":"ES",
    "sg:address":"Rond Outeiro, 208",
    "sg:city":"Coru\u00d1a",
    "sg:orig_category":"Colchones (fabricaci\u00d3n, Al Por Mayor, Al Por Menor)",
    "sg:phone":"+34 981 23 67 56",
    "sg:postcode":"15007",
    "sg:province":"La Coru\u00f1a",
    "wof:name":"Conde Mosteiro Carmen",
    "wof:placetype":"venue"
},
  "geometry": {"coordinates":[-8.7951183319,42.9959411621],"type":"Point"}
}