{
  "type": "Feature",
  "properties": {
    "addr:full":"Calle de Pajaritos, 11 Sevilla Sevilla 41004",
    "addr:housenumber":"11",
    "addr:postcode":"41004",
    "addr:street":"Calle De Pajaritos",
    "iso:country":"ES",
    "sg:address":"Calle de Pajaritos, 11",
    "sg:city":"Sevilla",
    "sg:orig_category":"Vinos Y Licores (venta Al Por Menor)",
    "sg:phone":"+34 954 22 00 90",
    "sg:postcode":"41004",
    "sg:province":"Sevilla",
    "wof:name":"Mendez-benegassi De Tena-davila Carmen Antonia",
    "wof:placetype":"venue"
},
  "geometry": {"coordinates":[-5.991795063,37.388584137],"type":"Point"}
}