{
  "type": "Feature",
  "properties": {
    "iso:country":"ES",
    "sg:address":"Calle de Alberto Palacios, 2",
    "sg:city":"Madrid",
    "sg:orig_category":"Molduras, Junquillos, Listones Y Molduras Perforadas",
    "sg:phone":"+34 917 96 03 25",
    "sg:postcode":"28021",
    "sg:province":"Madrid",
    "wof:name":"Oreja Morcilla Bravo S.l.",
    "wof:placetype":"venue"
},
  "geometry": {"coordinates":[-3.7127480507,40.3446617126],"type":"Point"}
}