{
  "type": "Feature",
  "properties": {
    "addr:full":"Calle de Masquefa, 18 Valencia Valencia 46020",
    "addr:housenumber":"18",
    "addr:postcode":"46020",
    "addr:street":"Calle De Masquefa",
    "iso:country":"ES",
    "sg:address":"Calle de Masquefa, 18",
    "sg:city":"Valencia",
    "sg:orig_category":"Guarder\u00cdas",
    "sg:phone":"+34 963 62 45 59",
    "sg:postcode":"46020",
    "sg:province":"Valencia",
    "wof:name":"Escuela Infantil Campanilla C.b.",
    "wof:placetype":"venue"
},
  "geometry": {"coordinates":[-0.3590460122,39.4879493713],"type":"Point"}
}