{
  "type": "Feature",
  "properties": {
    "addr:full":"Ptda Monta\u00f1a Grande, 15 Pedreguer Alicante 03750",
    "addr:housenumber":"15",
    "addr:postcode":"03750",
    "addr:street":"Ptda Montan\u0303A Grande",
    "iso:country":"ES",
    "sg:address":"Ptda Monta\u00f1a Grande, 15",
    "sg:city":"Pedreguer",
    "sg:orig_category":"Contenedores Para Transporte De Mercanc\u00cdas",
    "sg:phone":"+34 965 76 11 01",
    "sg:postcode":"03750",
    "sg:province":"Alicante",
    "wof:name":"Hermanos Segui Montaner S.l.",
    "wof:placetype":"venue"
},
  "geometry": {"coordinates":[0.0279866997,38.7891578674],"type":"Point"}
}