{
  "type": "Feature",
  "properties": {
    "addr:full":"Pablo Hern\u00e1ndez, 32 Cieza Murcia 30530",
    "addr:housenumber":"32",
    "addr:postcode":"30530",
    "addr:street":"Herna\u0301Ndez",
    "iso:country":"ES",
    "sg:address":"Pablo Hern\u00e1ndez, 32",
    "sg:city":"Cieza",
    "sg:orig_category":"Quincaller\u00cda (al Por Menor)",
    "sg:phone":"+34 968 45 61 50",
    "sg:postcode":"30530",
    "sg:province":"Murcia",
    "wof:name":"Valcarcel Guardiola Santiago",
    "wof:placetype":"venue"
},
  "geometry": {"coordinates":[-1.4211740494,38.235824585],"type":"Point"}
}