{
  "type": "Feature",
  "properties": {
    "addr:full":"Calle de Carretera, Km. 0025,5 Arganda Madrid 28500",
    "addr:postcode":"28500",
    "addr:street":"Calle De Carretera Km. 0025,5",
    "iso:country":"ES",
    "sg:address":"Calle de Carretera, Km. 0025,5",
    "sg:city":"Arganda",
    "sg:orig_category":"Muebles, Minoristas",
    "sg:phone":"+34 918 70 38 03",
    "sg:postcode":"28500",
    "sg:province":"Madrid",
    "wof:name":"Gil Campillo Benito",
    "wof:placetype":"venue"
},
  "geometry": {"coordinates":[-3.4353477955,40.3003158569],"type":"Point"}
}