{
  "type": "Feature",
  "properties": {
    "addr:full":"Carrer de Sant Julia, 5 Mas Mates Girona 17480",
    "addr:housenumber":"5",
    "addr:postcode":"17480",
    "addr:street":"Carrer De Sant Julia;Mates",
    "iso:country":"ES",
    "sg:address":"Carrer de Sant Julia, 5",
    "sg:city":"Mas Mates",
    "sg:orig_category":"Porcelanas, Azulejos (fabricaci\u00d3n, Al Por Mayor)",
    "sg:phone":"+34 972 15 23 68",
    "sg:postcode":"17480",
    "sg:province":"Girona",
    "wof:name":"Geli Pons Carlos",
    "wof:placetype":"venue"
},
  "geometry": {"coordinates":[3.1663351059,42.2661399841],"type":"Point"}
}