{
  "type": "Feature",
  "properties": {
    "addr:full":"Plaz Teniente Linares, 2 Orihuela Alicante 03300",
    "addr:housenumber":"2",
    "addr:postcode":"03300",
    "addr:street":"Plaz Teniente Linares",
    "iso:country":"ES",
    "sg:address":"Plaz Teniente Linares, 2",
    "sg:city":"Orihuela",
    "sg:orig_category":"Ropa Para Se\u00d1oras (al Por Menor)",
    "sg:phone":"+34 965 30 42 07",
    "sg:postcode":"03300",
    "sg:province":"Alicante",
    "wof:name":"Vegatoys S.l.",
    "wof:placetype":"venue"
},
  "geometry": {"coordinates":[-0.9454029799,38.0859832764],"type":"Point"}
}