{
  "type": "Feature",
  "properties": {
    "iso:country":"ES",
    "sg:address":"Avda Juan Xxiii, 23",
    "sg:city":"Huesca",
    "sg:orig_category":"Ropa Para Ni\u00d1os (al Por Menor)",
    "sg:phone":"+34 974 24 07 63",
    "sg:postcode":"22003",
    "sg:province":"Huesca",
    "wof:name":"Buisan Inglan Ana Belen",
    "wof:placetype":"venue"
},
  "geometry": {"coordinates":[-0.4083139896,42.1365661621],"type":"Point"}
}