{
  "type": "Feature",
  "properties": {
    "addr:full":"Dsmdo Pago Rodalabota, 1 Cuervo Sevilla 41749",
    "addr:housenumber":"1",
    "addr:postcode":"41749",
    "addr:street":"Rodalabota",
    "iso:country":"ES",
    "sg:address":"Dsmdo Pago Rodalabota, 1",
    "sg:city":"Cuervo",
    "sg:orig_category":"Explotaci\u00d3n De Canteras",
    "sg:phone":"+34 955 97 82 48",
    "sg:postcode":"41749",
    "sg:province":"Sevilla",
    "wof:name":"Canteras Y Suministros S.a.",
    "wof:placetype":"venue"
},
  "geometry": {"coordinates":[-6.0345978737,36.8576164246],"type":"Point"}
}