{
  "type": "Feature",
  "properties": {
    "iso:country":"ES",
    "sg:address":"Calle de Almonacid, 25",
    "sg:city":"Madrid",
    "sg:orig_category":"Peluqueros: De Se\u00d1oras",
    "sg:phone":"+34 914 39 61 01",
    "sg:postcode":"28038",
    "sg:province":"Madrid",
    "wof:name":"Romero Caballero Rosalia",
    "wof:placetype":"venue"
},
  "geometry": {"coordinates":[-3.6599769592,40.3966255188],"type":"Point"}
}