{
  "type": "Feature",
  "properties": {
    "addr:full":"Ctra Torrelaguna (de), S/n Azuqueca Henares Guadalajara 19200",
    "addr:housenumber":"/ n",
    "addr:postcode":"19200",
    "addr:street":"Ctra Torrelaguna De S",
    "iso:country":"ES",
    "sg:address":"Ctra Torrelaguna (de), S/n",
    "sg:city":"Azuqueca Henares",
    "sg:orig_category":"Fabricaci\u00d3n De Juegos Y Juguetes",
    "sg:phone":"+34 949 26 31 67",
    "sg:postcode":"19200",
    "sg:province":"Guadalajara",
    "sg:website":"www.bandai.com",
    "wof:name":"Bandai Espa\u00f1a S.a.",
    "wof:placetype":"venue"
},
  "geometry": {"coordinates":[-3.2661209106,40.5673294067],"type":"Point"}
}