{
  "type": "Feature",
  "properties": {
    "iso:country":"ES",
    "sg:address":"Calle de Fuente Nueva, S/n",
    "sg:city":"Yebenes",
    "sg:orig_category":"Refiner\u00cdas De Petr\u00d3leo",
    "sg:phone":"+34 925 34 82 52",
    "sg:postcode":"45470",
    "sg:province":"Toledo",
    "wof:name":"Bravo Gomez Jose",
    "wof:placetype":"venue"
},
  "geometry": {"coordinates":[-3.8673810959,39.5804481506],"type":"Point"}
}