{
  "type": "Feature",
  "properties": {
    "addr:full":"Calle de Colon, 27 Valverde Camino Huelva 21600",
    "addr:housenumber":"27",
    "addr:postcode":"21600",
    "addr:street":"Calle De Colon;Camino Huelva",
    "iso:country":"ES",
    "sg:address":"Calle de Colon, 27",
    "sg:city":"Valverde Camino",
    "sg:orig_category":"Molduras, Junquillos, Listones Y Molduras Perforadas",
    "sg:phone":"+34 959 55 27 15",
    "sg:postcode":"21600",
    "sg:province":"Huelva",
    "wof:name":"Becerro Y Macias Gregoria",
    "wof:placetype":"venue"
},
  "geometry": {"coordinates":[-6.7510390282,37.575378418],"type":"Point"}
}