{
  "type": "Feature",
  "properties": {
    "addr:full":"Avda Juan De Austria, 30 Alcala Henares Madrid 28804",
    "addr:housenumber":"30",
    "addr:postcode":"28804",
    "addr:street":"Avda Juan De Austria",
    "iso:country":"ES",
    "sg:address":"Avda Juan De Austria, 30",
    "sg:city":"Alcala Henares",
    "sg:orig_category":"Institutos De Belleza",
    "sg:phone":"+34 918 88 63 93",
    "sg:postcode":"28804",
    "sg:province":"Madrid",
    "wof:name":"Planeta Sol C.b",
    "wof:placetype":"venue"
},
  "geometry": {"coordinates":[-3.3514668941,40.487071991],"type":"Point"}
}