{
  "type": "Feature",
  "properties": {
    "addr:full":"Cm\u00d1o Monte Da Serra, 15 Viloura Pontevedra 36213",
    "addr:housenumber":"15",
    "addr:postcode":"36213",
    "addr:street":"Viloura Pontevedra",
    "iso:country":"ES",
    "sg:address":"Cm\u00d1o Monte Da Serra, 15",
    "sg:city":"Viloura",
    "sg:orig_category":"Asesor\u00cda, Estudio Y Control Medioambiental",
    "sg:phone":"+34 986 47 26 60",
    "sg:postcode":"36213",
    "sg:province":"Pontevedra",
    "wof:name":"Tecnicas Medioambientales Hospitalarias S.a.",
    "wof:placetype":"venue"
},
  "geometry": {"coordinates":[-8.7210121155,42.1948318481],"type":"Point"}
}