{
  "type": "Feature",
  "properties": {
    "addr:full":"Calle de Alemania, 72 Linea De La Concepcion C\u00e1diz 11300",
    "addr:housenumber":"72",
    "addr:postcode":"11300",
    "addr:street":"Calle De Alemania;Ca\u0301Diz",
    "iso:country":"ES",
    "sg:address":"Calle de Alemania, 72",
    "sg:city":"Linea De La Concepcion",
    "sg:orig_category":"Zootecnia",
    "sg:phone":"+34 956 17 40 80",
    "sg:postcode":"11300",
    "sg:province":"C\u00e1diz",
    "wof:name":"Orni-tour S.l.",
    "wof:placetype":"venue"
},
  "geometry": {"coordinates":[-5.3503484726,36.167766571],"type":"Point"}
}