{
  "type": "Feature",
  "properties": {
    "addr:full":"Calle de Agapito Marazuela, 40 Segovia Segovia 40005",
    "addr:housenumber":"40",
    "addr:postcode":"40005",
    "addr:street":"Calle De Agapito Marazuela",
    "iso:country":"ES",
    "sg:address":"Calle de Agapito Marazuela, 40",
    "sg:city":"Segovia",
    "sg:orig_category":"Inform\u00c1tica (estudios, Servicios, Asesor\u00cda, Formaci\u00d3n)",
    "sg:phone":"+34 921 43 02 09",
    "sg:postcode":"40005",
    "sg:province":"Segovia",
    "wof:name":"De La Fuente Soluciones Integrales S.l.",
    "wof:placetype":"venue"
},
  "geometry": {"coordinates":[-4.1128587723,40.9384307861],"type":"Point"}
}