{
  "type": "Feature",
  "properties": {
    "addr:full":"Italia (pol Industrial), S/n Constanti Tarragona 43120",
    "addr:housenumber":"/ n",
    "addr:postcode":"43120",
    "addr:street":"Industrial",
    "iso:country":"ES",
    "sg:address":"Italia (pol Industrial), S/n",
    "sg:city":"Constanti",
    "sg:orig_category":"Art\u00cdculos De Limpieza Y De Cocina (fabricaci\u00d3n, Al Por Mayor)",
    "sg:phone":"+34 977 52 30 59",
    "sg:postcode":"43120",
    "sg:province":"Tarragona",
    "sg:website":"www.ecobrill.com",
    "wof:name":"Ecobrill S.l.",
    "wof:placetype":"venue"
},
  "geometry": {"coordinates":[1.1712549925,41.1604385376],"type":"Point"}
}