{
  "type": "Feature",
  "properties": {
    "iso:country":"ES",
    "sg:address":"Calle de Eulogio Fernandez Barros, 2",
    "sg:city":"Muriedas",
    "sg:orig_category":"Fabricaci\u00d3n, Venta De Cuadros, Accesorios Para Enmarcar",
    "sg:phone":"+34 942 25 00 09",
    "sg:postcode":"39600",
    "sg:province":"Cantabria",
    "wof:name":"Enmarcaciones Acuarela S.l.",
    "wof:placetype":"venue"
},
  "geometry": {"coordinates":[-3.8558828831,43.4274368286],"type":"Point"}
}