{
  "type": "Feature",
  "properties": {
    "iso:country":"ES",
    "sg:address":"Carrer de Aribau, 13",
    "sg:city":"Rubi",
    "sg:orig_category":"Promotores Constructores",
    "sg:phone":"+34 935 88 84 83",
    "sg:postcode":"08191",
    "sg:province":"Barcelona",
    "wof:name":"Contratas Y Edificaciones Eurinter S.l.",
    "wof:placetype":"venue"
},
  "geometry": {"coordinates":[2.0281500816,41.4989509583],"type":"Point"}
}