{
  "type": "Feature",
  "properties": {
    "addr:full":"Calle de Salamanca, 46 Zamora Zamora 49028",
    "addr:housenumber":"46",
    "addr:postcode":"49028",
    "addr:street":"Calle De Salamanca",
    "iso:country":"ES",
    "sg:address":"Calle de Salamanca, 46",
    "sg:city":"Zamora",
    "sg:orig_category":"Distribuci\u00d3n De Petr\u00d3leo Y Derivados",
    "sg:phone":"+34 980 53 18 00",
    "sg:postcode":"49028",
    "sg:province":"Zamora",
    "sg:website":"www.cepsa.es",
    "wof:name":"Raigada S.l.",
    "wof:placetype":"venue"
},
  "geometry": {"coordinates":[-5.7414388657,41.4947319031],"type":"Point"}
}