{
  "type": "Feature",
  "properties": {
    "addr:full":"Calle de Carcelen, 24 Alatoz Albacete 02152",
    "addr:housenumber":"24",
    "addr:postcode":"02152",
    "addr:street":"Calle De Carcelen",
    "iso:country":"ES",
    "sg:address":"Calle de Carcelen, 24",
    "sg:city":"Alatoz",
    "sg:orig_category":"Empresas De Carpinter\u00cda De Madera",
    "sg:phone":"+34 967 40 20 36",
    "sg:postcode":"02152",
    "sg:province":"Albacete",
    "wof:name":"Piqueras Martinez Andres",
    "wof:placetype":"venue"
},
  "geometry": {"coordinates":[-1.3617062569,39.0956077576],"type":"Point"}
}