{
  "type": "Feature",
  "properties": {
    "iso:country":"ES",
    "sg:address":"Carrer de Mont-ras, 3",
    "sg:city":"Hospitalet Llobregat",
    "sg:orig_category":"Electrodom\u00c9sticos (al Por Menor)",
    "sg:phone":"+34 933 34 29 00",
    "sg:postcode":"08906",
    "sg:province":"Barcelona",
    "wof:name":"Corbetres S. A.",
    "wof:placetype":"venue"
},
  "geometry": {"coordinates":[2.1054809093,41.3743934631],"type":"Point"}
}