{
  "type": "Feature",
  "properties": {
    "addr:full":"Manuel Carrera D\u00edez, 15 Agreda Soria 42100",
    "addr:housenumber":"15",
    "addr:postcode":"42100",
    "addr:street":"Carrera Di\u0301Ez",
    "iso:country":"ES",
    "sg:address":"Manuel Carrera D\u00edez, 15",
    "sg:city":"Agreda",
    "sg:orig_category":"Contenedores (mercanc\u00cdas)",
    "sg:phone":"+34 976 64 74 19",
    "sg:postcode":"42100",
    "sg:province":"Soria",
    "wof:name":"Jimenez Cilla S.l.",
    "wof:placetype":"venue"
},
  "geometry": {"coordinates":[-1.9281818867,41.8503227234],"type":"Point"}
}