{
  "type": "Feature",
  "properties": {
    "addr:full":"Calle de San Pedro Y San Felices, 27 Burgos Burgos 09001",
    "addr:housenumber":"27",
    "addr:postcode":"09001",
    "addr:street":"Calle De San;Felices",
    "iso:country":"ES",
    "sg:address":"Calle de San Pedro Y San Felices, 27",
    "sg:city":"Burgos",
    "sg:orig_category":"Carnicer\u00cdas, Carnicer\u00cdas",
    "sg:phone":"+34 947 27 37 90",
    "sg:postcode":"09001",
    "sg:province":"Burgos",
    "wof:name":"Arcecarne S.l.",
    "wof:placetype":"venue"
},
  "geometry": {"coordinates":[-3.7051708698,42.332824707],"type":"Point"}
}