{
  "type": "Feature",
  "properties": {
    "iso:country":"ES",
    "sg:address":"Calle de Alonso De Bazan, 3",
    "sg:city":"Marbella",
    "sg:orig_category":"Caf\u00c9s, Bares, Cervecer\u00cdas",
    "sg:phone":"+34 952 77 66 42",
    "sg:postcode":"29600",
    "sg:province":"M\u00e1laga",
    "wof:name":"Goyo S.l.",
    "wof:placetype":"venue"
},
  "geometry": {"coordinates":[-4.889380455,36.5096664429],"type":"Point"}
}