{
  "type": "Feature",
  "properties": {
    "iso:country":"ES",
    "sg:address":"Av. Esparteros, 25",
    "sg:city":"Leganes",
    "sg:orig_category":"Gr\u00daas, Montacargas Y Elevadores Para Astilleros",
    "sg:phone":"+34 916 41 08 12",
    "sg:postcode":"28918",
    "sg:province":"Madrid",
    "sg:website":"www.gondolasmerino.com",
    "wof:name":"Gondolas Merino S. A.",
    "wof:placetype":"venue"
},
  "geometry": {"coordinates":[-3.801347971,40.3453407288],"type":"Point"}
}