{
  "type": "Feature",
  "properties": {
    "addr:full":"Luga Rematacaudales, 3 Miraflores C\u00e1diz 11540",
    "addr:housenumber":"3",
    "addr:postcode":"11540",
    "addr:street":"Rematacaudales",
    "iso:country":"ES",
    "sg:address":"Luga Rematacaudales, 3",
    "sg:city":"Miraflores",
    "sg:orig_category":"Negocio De Materiales De Construcci\u00d3n",
    "sg:phone":"+34 956 36 71 35",
    "sg:postcode":"11540",
    "sg:province":"C\u00e1diz",
    "wof:name":"Hormigones N-b S.a.",
    "wof:placetype":"venue"
},
  "geometry": {"coordinates":[-6.3575987816,36.777721405],"type":"Point"}
}