{
  "type": "Feature",
  "properties": {
    "iso:country":"ES",
    "sg:address":"Calle de Antonio Pirala, 33",
    "sg:city":"Madrid",
    "sg:orig_category":"Venta, Colocaci\u00d3n, Reparaci\u00d3n De Radiadores Para Veh\u00cdculos",
    "sg:phone":"+34 913 56 10 78",
    "sg:postcode":"28017",
    "sg:province":"Madrid",
    "wof:name":"Pinilla Hermanos S.l.",
    "wof:placetype":"venue"
},
  "geometry": {"coordinates":[-3.6595687866,40.4276008606],"type":"Point"}
}