{
  "type": "Feature",
  "properties": {
    "iso:country":"ES",
    "sg:address":"Carrer de Torrent De L'olla, 191",
    "sg:city":"Barcelona",
    "sg:orig_category":"Centros Empresariales",
    "sg:phone":"+34 932 17 09 31",
    "sg:postcode":"08012",
    "sg:province":"Barcelona",
    "wof:name":"Marin Ruiz Marisol",
    "wof:placetype":"venue"
},
  "geometry": {"coordinates":[2.1530125141,41.405834198],"type":"Point"}
}