{
  "type": "Feature",
  "properties": {
    "iso:country":"ES",
    "sg:address":"Calle de Celanova, 1",
    "sg:city":"Zaragoza",
    "sg:orig_category":"Ropa Para Beb\u00c9s Y Ni\u00d1os (confecci\u00d3n, Al Por Mayor)",
    "sg:phone":"+34 976 33 60 83",
    "sg:postcode":"50017",
    "sg:province":"Zaragoza",
    "wof:name":"Baby Crevica S.l.",
    "wof:placetype":"venue"
},
  "geometry": {"coordinates":[-0.9109963775,41.6540222168],"type":"Point"}
}