{
  "type": "Feature",
  "properties": {
    "iso:country":"ES",
    "sg:address":"Caselas, 32",
    "sg:city":"Caselas",
    "sg:orig_category":"Charcuter\u00cdas (al Por Mayor)",
    "sg:phone":"+34 986 62 61 58",
    "sg:postcode":"36770",
    "sg:province":"Pontevedra",
    "wof:name":"Carnes Y Embutidos Alvarez Giraldez S.l.",
    "wof:placetype":"venue"
},
  "geometry": {"coordinates":[-8.8362493515,41.9370346069],"type":"Point"}
}