{
  "type": "Feature",
  "properties": {
    "addr:full":"Carrer de Sant Gervasi De Cassoles, 88 Barcelona Barcelona 08022",
    "addr:housenumber":"88",
    "addr:postcode":"08022",
    "addr:street":"Carrer De Sant Gervasi De Cassoles",
    "iso:country":"ES",
    "sg:address":"Carrer de Sant Gervasi De Cassoles, 88",
    "sg:city":"Barcelona",
    "sg:orig_category":"M\u00c9dicos: Psiquiatr\u00cda",
    "sg:phone":"+34 932 12 02 12",
    "sg:postcode":"08022",
    "sg:province":"Barcelona",
    "sg:website":"www.fundaciovidalbarraquer.com",
    "wof:name":"Fundacion Cardenal Vidal Y Barraquer",
    "wof:placetype":"venue"
},
  "geometry": {"coordinates":[2.1354539394,41.406288147],"type":"Point"}
}