{
  "type": "Feature",
  "properties": {
    "addr:full":"Calle de Jose Doval, 37 Alcantarilla Murcia 30820",
    "addr:housenumber":"37",
    "addr:postcode":"30820",
    "addr:street":"Calle De Jose Doval",
    "iso:country":"ES",
    "sg:address":"Calle de Jose Doval, 37",
    "sg:city":"Alcantarilla",
    "sg:orig_category":"Aparatos, Material Y Suministros Para Laboratorios",
    "sg:phone":"+34 968 80 44 84",
    "sg:postcode":"30820",
    "sg:province":"Murcia",
    "wof:name":"Radiometer Iberica S.a.",
    "wof:placetype":"venue"
},
  "geometry": {"coordinates":[-1.2207709551,37.9726219177],"type":"Point"}
}