{
  "type": "Feature",
  "properties": {
    "iso:country":"ES",
    "sg:address":"Carr Santa Barbara, 11",
    "sg:city":"Santa Coloma De Farners",
    "sg:orig_category":"Ropa Para Se\u00d1oras Y Caballeros (al Por Menor)",
    "sg:phone":"+34 972 84 24 86",
    "sg:postcode":"17430",
    "sg:province":"Girona",
    "wof:name":"Serarols Serra Monserrat",
    "wof:placetype":"venue"
},
  "geometry": {"coordinates":[2.659676075,41.8650779724],"type":"Point"}
}