{
  "type": "Feature",
  "properties": {
    "iso:country":"ES",
    "sg:address":"Avda Fray Luis Amigo, 12",
    "sg:city":"Segorbe",
    "sg:orig_category":"Asociaciones Y Clubs Deportivos",
    "sg:phone":"+34 964 71 10 47",
    "sg:postcode":"12400",
    "sg:province":"Castell\u00f3n",
    "wof:name":"Armeria Y Deportes Macario S.l.",
    "wof:placetype":"venue"
},
  "geometry": {"coordinates":[-0.4887405038,39.8485488892],"type":"Point"}
}