{
  "type": "Feature",
  "properties": {
    "iso:country":"ES",
    "sg:address":"Ctra. Navas Oro, 5",
    "sg:city":"Turegano",
    "sg:orig_category":"Empresas De Carpinter\u00cda De Madera",
    "sg:phone":"+34 921 50 06 12",
    "sg:postcode":"40370",
    "sg:province":"Segovia",
    "wof:name":"Carpinteria Montes Gonzalez S.l.",
    "wof:placetype":"venue"
},
  "geometry": {"coordinates":[-4.00664711,41.1553382874],"type":"Point"}
}