{
  "type": "Feature",
  "properties": {
    "iso:country":"ES",
    "sg:address":"Calle de Larga, 27",
    "sg:city":"Trebujena",
    "sg:orig_category":"Restaurantes",
    "sg:phone":"+34 956 39 51 34",
    "sg:postcode":"11560",
    "sg:province":"C\u00e1diz",
    "wof:name":"Romero Bustillos Antonio",
    "wof:placetype":"venue"
},
  "geometry": {"coordinates":[-6.1754050255,36.8696556091],"type":"Point"}
}