{
  "type": "Feature",
  "properties": {
    "iso:country":"ES",
    "sg:address":"Carrer de Barcelona, 33",
    "sg:city":"Rubi",
    "sg:orig_category":"Agencias Y Agentes Comerciales, Representantes",
    "sg:phone":"+34 936 99 93 54",
    "sg:postcode":"08191",
    "sg:province":"Barcelona",
    "wof:name":"Diez Alonso Esther",
    "wof:placetype":"venue"
},
  "geometry": {"coordinates":[2.0312991142,41.4883804321],"type":"Point"}
}