{
  "type": "Feature",
  "properties": {
    "iso:country":"ES",
    "sg:address":"Carrer de Fra Antoni Cardona I Grau, 3",
    "sg:city":"Tarragona",
    "sg:orig_category":"Empresarios",
    "sg:phone":"+34 977 21 40 32",
    "sg:postcode":"43002",
    "sg:province":"Tarragona",
    "wof:name":"Construccions I Manteniments J.bonfill S.l",
    "wof:placetype":"venue"
},
  "geometry": {"coordinates":[1.2541329861,41.1221885681],"type":"Point"}
}