{
  "type": "Feature",
  "properties": {
    "addr:full":"Calle de Estacion, 90 Miranda Ebro Burgos 09200",
    "addr:housenumber":"90",
    "addr:postcode":"09200",
    "addr:street":"Calle De Estacion",
    "iso:country":"ES",
    "sg:address":"Calle de Estacion, 90",
    "sg:city":"Miranda Ebro",
    "sg:classifiers":[
        {
            "category":"Taxi",
            "type":"Transportation"
        }
    ],
    "sg:phone":"+34 947 31 09 74",
    "sg:postcode":"09200",
    "sg:province":"Burgos",
    "wof:name":"Gonzalez Renedo Alfredo",
    "wof:placetype":"venue"
},
  "geometry": {"coordinates":[-2.9441018105,42.6877479553],"type":"Point"}
}