{
  "type": "Feature",
  "properties": {
    "addr:full":"Calle de Gil Velez, 19 Nerva Huelva 21670",
    "addr:housenumber":"19",
    "addr:postcode":"21670",
    "addr:street":"Calle De Gil Velez",
    "iso:country":"ES",
    "sg:address":"Calle de Gil Velez, 19",
    "sg:city":"Nerva",
    "sg:orig_category":"Loter\u00cda Y T\u00d3mbola",
    "sg:phone":"+34 959 58 08 34",
    "sg:postcode":"21670",
    "sg:province":"Huelva",
    "wof:name":"Fernandez Vaquero Dolores",
    "wof:placetype":"venue"
},
  "geometry": {"coordinates":[-6.5494914055,37.6951446533],"type":"Point"}
}