{
  "type": "Feature",
  "properties": {
    "addr:full":"Mlle Levante, 6 Alacant Alicante 03001",
    "addr:housenumber":"6",
    "addr:postcode":"03001",
    "addr:street":"Levante",
    "iso:country":"ES",
    "sg:address":"Mlle Levante, 6",
    "sg:city":"Alacant",
    "sg:orig_category":"Cervecer\u00cdas",
    "sg:phone":"+34 965 20 97 36",
    "sg:postcode":"03001",
    "sg:province":"Alicante",
    "wof:name":"Directo 96 S.l.",
    "wof:placetype":"venue"
},
  "geometry": {"coordinates":[-0.4804739952,38.3440856934],"type":"Point"}
}