{
  "type": "Feature",
  "properties": {
    "iso:country":"ES",
    "sg:address":"Puente La Pista, 2",
    "sg:city":"Cabezas S. Juan",
    "sg:orig_category":"Fabricaci\u00d3n, Venta, Instalaci\u00d3n De R\u00d3tulos, De R\u00d3tulos Luminosos",
    "sg:phone":"+34 955 87 21 09",
    "sg:postcode":"41730",
    "sg:province":"Sevilla",
    "wof:name":"Montajes Y Electrificaciones Caygust S.c.a.",
    "wof:placetype":"venue"
},
  "geometry": {"coordinates":[-5.9365491867,36.9817962646],"type":"Point"}
}