{
  "type": "Feature",
  "properties": {
    "iso:country":"ES",
    "sg:address":"Calle de Fuente De Los Molinos (la), 65",
    "sg:city":"Almeria",
    "sg:orig_category":"Arreglo, Reparaci\u00d3n, Piezas Sueltas De Televisi\u00d3n, V\u00cddeo, Hi",
    "sg:phone":"+34 950 25 16 96",
    "sg:postcode":"04009",
    "sg:province":"Almer\u00eda",
    "wof:name":"Gonzalez Andujar Cayetano",
    "wof:placetype":"venue"
},
  "geometry": {"coordinates":[-2.437278986,36.8505706787],"type":"Point"}
}