{
  "type": "Feature",
  "properties": {
    "iso:country":"ES",
    "sg:address":"Calle de Real, 251",
    "sg:city":"Calzada Calatrava",
    "sg:orig_category":"Molduras, Junquillos, Listones Y Molduras Perforadas",
    "sg:phone":"+34 926 87 68 60",
    "sg:postcode":"13370",
    "sg:province":"Ciudad Real",
    "wof:name":"Cubero Medran Ramon",
    "wof:placetype":"venue"
},
  "geometry": {"coordinates":[-3.7789990902,38.7063713074],"type":"Point"}
}