{
  "type": "Feature",
  "properties": {
    "iso:country":"ES",
    "sg:address":"Carr Vilanova, 15",
    "sg:city":"Monells",
    "sg:orig_category":"Adhesivos (fabricaci\u00d3n, Al Por Mayor)",
    "sg:phone":"+34 972 63 01 48",
    "sg:postcode":"17121",
    "sg:province":"Girona",
    "wof:name":"Marti Pages Lluis",
    "wof:placetype":"venue"
},
  "geometry": {"coordinates":[3.0000998974,41.97473526],"type":"Point"}
}