{
  "type": "Feature",
  "properties": {
    "addr:full":"Calle de Obra Pia, 10 Miajadas C\u00e1ceres 10100",
    "addr:housenumber":"10",
    "addr:postcode":"10100",
    "addr:street":"Calle De Obra Pia;Ca\u0301Ceres",
    "iso:country":"ES",
    "sg:address":"Calle de Obra Pia, 10",
    "sg:city":"Miajadas",
    "sg:orig_category":"Plomeros",
    "sg:phone":"+34 927 34 71 36",
    "sg:postcode":"10100",
    "sg:province":"C\u00e1ceres",
    "wof:name":"Barbero Redondo Juan",
    "wof:placetype":"venue"
},
  "geometry": {"coordinates":[-5.9082989693,39.1555213928],"type":"Point"}
}