{
  "type": "Feature",
  "properties": {
    "iso:country":"ES",
    "sg:address":"Bo. La Casona-enfistiella, 29",
    "sg:city":"Nembra",
    "sg:orig_category":"Chapister\u00cda",
    "sg:phone":"+34 985 48 50 60",
    "sg:postcode":"33677",
    "sg:province":"Asturias",
    "wof:name":"Casta\u00f1on Fernandez Roberto",
    "wof:placetype":"venue"
},
  "geometry": {"coordinates":[-5.7153201103,43.1499519348],"type":"Point"}
}