{
  "type": "Feature",
  "properties": {
    "addr:full":"Carr Guipuscoa, 11 Girona Girona 17003",
    "addr:housenumber":"11",
    "addr:postcode":"17003",
    "addr:street":"Carr Guipuscoa",
    "iso:country":"ES",
    "sg:address":"Carr Guipuscoa, 11",
    "sg:city":"Girona",
    "sg:orig_category":"Empresas De Carpinter\u00cda De Madera",
    "sg:phone":"+34 972 21 32 13",
    "sg:postcode":"17003",
    "sg:province":"Girona",
    "wof:name":"Romero Sau Jaime",
    "wof:placetype":"venue"
},
  "geometry": {"coordinates":[2.8080599308,41.9508743286],"type":"Point"}
}