{
  "type": "Feature",
  "properties": {
    "iso:country":"ES",
    "sg:address":"Carr Muralla, 30",
    "sg:city":"Castello D'empuries",
    "sg:orig_category":"Herboristas (al Por Menor)",
    "sg:phone":"+34 972 15 60 71",
    "sg:postcode":"17486",
    "sg:province":"Girona",
    "wof:name":"Bardes Lopez Maria Rosa",
    "wof:placetype":"venue"
},
  "geometry": {"coordinates":[3.117882967,42.1298103333],"type":"Point"}
}