{
  "type": "Feature",
  "properties": {
    "addr:full":"Ctra. Ogijares-la Riola, S/n Ogijares Granada 18151",
    "addr:housenumber":"s / n",
    "addr:postcode":"18151",
    "addr:street":"Ctra. Ogijares-La Riola",
    "iso:country":"ES",
    "sg:address":"Ctra. Ogijares-la Riola, S/n",
    "sg:city":"Ogijares",
    "sg:orig_category":"Trabajos De Asfalto, De Alquitr\u00c1n Y Asfalto",
    "sg:phone":"+34 958 50 68 52",
    "sg:postcode":"18151",
    "sg:province":"Granada",
    "wof:name":"Asfaltos Luis Fernandez S.l.",
    "wof:placetype":"venue"
},
  "geometry": {"coordinates":[-3.616714716,37.1191101074],"type":"Point"}
}