{
  "type": "Feature",
  "properties": {
    "addr:full":"Calle de Padre Angel De Novele, 8 Totana Murcia 30850",
    "addr:housenumber":"8",
    "addr:postcode":"30850",
    "addr:street":"Calle De Padre Angel De Novele",
    "iso:country":"ES",
    "sg:address":"Calle de Padre Angel De Novele, 8",
    "sg:city":"Totana",
    "sg:orig_category":"Zapatos (al Por Menor)",
    "sg:phone":"+34 968 42 30 96",
    "sg:postcode":"30850",
    "sg:province":"Murcia",
    "wof:name":"Cazorla Romero Ana",
    "wof:placetype":"venue"
},
  "geometry": {"coordinates":[-1.4986679554,37.7708358765],"type":"Point"}
}