{
  "type": "Feature",
  "properties": {
    "addr:full":"Calle de Prior, 8 Salamanca Salamanca 37002",
    "addr:housenumber":"8",
    "addr:postcode":"37002",
    "addr:street":"Calle De Prior",
    "iso:country":"ES",
    "sg:address":"Calle de Prior, 8",
    "sg:city":"Salamanca",
    "sg:orig_category":"Perfumer\u00cda (al Por Menor)",
    "sg:phone":"+34 923 21 40 46",
    "sg:postcode":"37002",
    "sg:province":"Salamanca",
    "wof:name":"Lurue\u00f1a Barbero Oscar",
    "wof:placetype":"venue"
},
  "geometry": {"coordinates":[-5.6649541855,40.9650115967],"type":"Point"}
}