{
  "type": "Feature",
  "properties": {
    "iso:country":"ES",
    "sg:address":"Calle de Zubiaurre, 29",
    "sg:city":"Donostia-san Sebastian",
    "sg:orig_category":"Venta, Localizaci\u00d3n, Reparaci\u00d3n De Material E Instrumental M\u00c9dico",
    "sg:phone":"+34 943 28 41 00",
    "sg:postcode":"20013",
    "sg:province":"Guip\u00f9zcoa",
    "wof:name":"Indumed S.a.",
    "wof:placetype":"venue"
},
  "geometry": {"coordinates":[-1.9622089863,43.3204689026],"type":"Point"}
}