{
  "type": "Feature",
  "properties": {
    "addr:full":"Calle de Mariano Garcia Abril, 6 Valladolid Valladolid 47014",
    "addr:housenumber":"6",
    "addr:postcode":"47014",
    "addr:street":"Calle De Mariano Garcia Abril",
    "iso:country":"ES",
    "sg:address":"Calle de Mariano Garcia Abril, 6",
    "sg:city":"Valladolid",
    "sg:orig_category":"Agencias Y Agentes Comerciales, Representantes",
    "sg:phone":"+34 983 36 06 31",
    "sg:postcode":"47014",
    "sg:province":"Valladolid",
    "wof:name":"Representaciones Lanora S.l.",
    "wof:placetype":"venue"
},
  "geometry": {"coordinates":[-4.7355360985,41.6559066772],"type":"Point"}
}