{
  "type": "Feature",
  "properties": {
    "iso:country":"ES",
    "sg:address":"Calle de Miguel Artigas, 17",
    "sg:city":"Zaragoza",
    "sg:orig_category":"Alimentaci\u00d3n General (al Por Menor)",
    "sg:phone":"+34 976 53 55 36",
    "sg:postcode":"50011",
    "sg:province":"Zaragoza",
    "wof:name":"Porcar Guio Carmen",
    "wof:placetype":"venue"
},
  "geometry": {"coordinates":[-0.9258720279,41.6521873474],"type":"Point"}
}