{
  "type": "Feature",
  "properties": {
    "addr:full":"Calle de Cruz Dorada, S/n Trujillo C\u00e1ceres 10200",
    "addr:housenumber":"s",
    "addr:postcode":"10200",
    "addr:street":"Calle De Cruz Dorada;/ N;Ca\u0301Ceres",
    "iso:country":"ES",
    "sg:address":"Calle de Cruz Dorada, S/n",
    "sg:city":"Trujillo",
    "sg:orig_category":"T\u00c9cnicos Veterinarios",
    "sg:phone":"+34 927 32 02 09",
    "sg:postcode":"10200",
    "sg:province":"C\u00e1ceres",
    "wof:name":"Murillo Gutierrez Manuel",
    "wof:placetype":"venue"
},
  "geometry": {"coordinates":[-5.872633934,39.4598884583],"type":"Point"}
}