{
  "type": "Feature",
  "properties": {
    "addr:full":"Calle de Santa Engracia, 41 Madrid Madrid 28010",
    "addr:housenumber":"41",
    "addr:postcode":"madrid;28010",
    "addr:street":"Calle De Santa Engracia",
    "iso:country":"ES",
    "sg:address":"Calle de Santa Engracia, 41",
    "sg:city":"Madrid",
    "sg:orig_category":"Droguer\u00cdas (al Por Menor)",
    "sg:phone":"+34 915 94 31 84",
    "sg:postcode":"28010",
    "sg:province":"Madrid",
    "wof:name":"Montero Delgado Luis",
    "wof:placetype":"venue"
},
  "geometry": {"coordinates":[-3.6975939274,40.4319610596],"type":"Point"}
}