{
  "type": "Feature",
  "properties": {
    "addr:full":"Ctra Torrelaguna (de), S/n Casar Guadalajara 19170",
    "addr:housenumber":"/ n",
    "addr:postcode":"19170",
    "addr:street":"Ctra Torrelaguna De S",
    "iso:country":"ES",
    "sg:address":"Ctra Torrelaguna (de), S/n",
    "sg:city":"Casar",
    "sg:orig_category":"Empresas De Hormig\u00d3n, Hormig\u00d3n Armado Y Pretensado",
    "sg:phone":"+34 949 33 67 75",
    "sg:postcode":"19170",
    "sg:province":"Guadalajara",
    "wof:name":"Indagsa",
    "wof:placetype":"venue"
},
  "geometry": {"coordinates":[-3.4308691025,40.7028961182],"type":"Point"}
}