{
  "type": "Feature",
  "properties": {
    "iso:country":"ES",
    "sg:address":"Calle de Calvo Sotelo, 19",
    "sg:city":"Naquera",
    "sg:orig_category":"Pescader\u00cdas (al Por Menor)",
    "sg:phone":"+34 961 68 01 28",
    "sg:postcode":"46119",
    "sg:province":"Valencia",
    "wof:name":"Ferrando Ruiz Francisco",
    "wof:placetype":"venue"
},
  "geometry": {"coordinates":[-0.4219444096,39.6407318115],"type":"Point"}
}