{
  "type": "Feature",
  "properties": {
    "iso:country":"ES",
    "sg:address":"Calle de Parroco Juan Gonzalez, 18",
    "sg:city":"Teror",
    "sg:classifiers":[
        {
            "category":"Personal",
            "subcategory":"Barber",
            "type":"Services"
        }
    ],
    "sg:phone":"+34 928 63 16 52",
    "sg:postcode":"35330",
    "sg:province":"Las Palmas",
    "sg:tags":[
        "caballeros",
        "de",
        "peluqueros"
    ],
    "wof:name":"Estevez Moreno Pedro",
    "wof:placetype":"venue"
},
  "geometry": {"coordinates":[-15.5468168259,28.0618782043],"type":"Point"}
}