{
  "type": "Feature",
  "properties": {
    "iso:country":"ES",
    "sg:address":"Av Alcudia, 9",
    "sg:city":"Inca",
    "sg:orig_category":"Procuradores",
    "sg:phone":"+34 971 50 04 96",
    "sg:postcode":"07300",
    "sg:province":"Islas Baleares",
    "wof:name":"Serra Llull Antonio",
    "wof:placetype":"venue"
},
  "geometry": {"coordinates":[2.9134259224,39.7225456238],"type":"Point"}
}