{
  "type": "Feature",
  "properties": {
    "iso:country":"ES",
    "sg:address":"Calle de Sancho Panza, 44",
    "sg:city":"Cordoba",
    "sg:orig_category":"Bisuteros (fabricaci\u00d3n, Al Por Mayor)",
    "sg:phone":"+34 957 25 02 41",
    "sg:postcode":"14014",
    "sg:province":"C\u00f3rdoba",
    "wof:name":"Bea Espinosa Jose Antonio",
    "wof:placetype":"venue"
},
  "geometry": {"coordinates":[-4.7543458939,37.887752533],"type":"Point"}
}