{
  "type": "Feature",
  "properties": {
    "iso:country":"ES",
    "sg:address":"Carrer de Bellvei, 27",
    "sg:city":"Barbera Valles",
    "sg:orig_category":"Transportes Por V\u00cdas Navegables",
    "sg:phone":"+34 937 19 38 90",
    "sg:postcode":"08210",
    "sg:province":"Barcelona",
    "sg:website":"www.norbet-dentressangle.sr",
    "wof:name":"Norbert Dentressangle S.l.",
    "wof:placetype":"venue"
},
  "geometry": {"coordinates":[2.1513879299,41.5132217407],"type":"Point"}
}