{
  "type": "Feature",
  "properties": {
    "addr:full":"De La Mona, 11 Ventas Pe\u00f1a Aguilera Toledo 45127",
    "addr:housenumber":"11",
    "addr:postcode":"45127",
    "iso:country":"ES",
    "sg:address":"De La Mona, 11",
    "sg:city":"Ventas Pe\u00f1a Aguilera",
    "sg:orig_category":"Cr\u00cda De Animales",
    "sg:phone":"+34 925 41 80 40",
    "sg:postcode":"45127",
    "sg:province":"Toledo",
    "wof:name":"Hermanos Isabel Mora C.b.",
    "wof:placetype":"venue"
},
  "geometry": {"coordinates":[-4.2286472321,39.6132736206],"type":"Point"}
}