{
  "type": "Feature",
  "properties": {
    "iso:country":"ES",
    "sg:address":"Calle de Colon, 3",
    "sg:city":"Villarrobledo",
    "sg:orig_category":"Fabricaci\u00d3n De Enlosados, Soler\u00cdas",
    "sg:phone":"+34 967 14 25 49",
    "sg:postcode":"02600",
    "sg:province":"Albacete",
    "wof:name":"Azulejos Aroca S.l.",
    "wof:placetype":"venue"
},
  "geometry": {"coordinates":[-2.5964279175,39.2671546936],"type":"Point"}
}