{
  "type": "Feature",
  "properties": {
    "addr:full":"Rua Hio (de), 22 Cangas Pontevedra 36940",
    "addr:housenumber":"22",
    "addr:postcode":"36940",
    "addr:street":"Rua Hio De",
    "iso:country":"ES",
    "sg:address":"Rua Hio (de), 22",
    "sg:city":"Cangas",
    "sg:orig_category":"Alimentaci\u00d3n General (al Por Menor)",
    "sg:phone":"+34 986 30 04 28",
    "sg:postcode":"36940",
    "sg:province":"Pontevedra",
    "wof:name":"Guardado Gonzalez Manuel",
    "wof:placetype":"venue"
},
  "geometry": {"coordinates":[-8.786072731,42.2635536194],"type":"Point"}
}