{
  "type": "Feature",
  "properties": {
    "iso:country":"ES",
    "sg:address":"Avda Filipinas, 3",
    "sg:city":"Madrid",
    "sg:orig_category":"Caf\u00c9s, Bares, Cervecer\u00cdas",
    "sg:phone":"+34 915 54 21 45",
    "sg:postcode":"28003",
    "sg:province":"Madrid",
    "wof:name":"Mirodano S.l",
    "wof:placetype":"venue"
},
  "geometry": {"coordinates":[-3.7115819454,40.4397392273],"type":"Point"}
}