{
  "type": "Feature",
  "properties": {
    "addr:full":"Calle de Roman Romano, 1 Llanes Asturias 33500",
    "addr:housenumber":"1",
    "addr:postcode":"33500",
    "addr:street":"Calle De Roman Romano",
    "iso:country":"ES",
    "sg:address":"Calle de Roman Romano, 1",
    "sg:city":"Llanes",
    "sg:orig_category":"Transportes Por V\u00cdas Navegables",
    "sg:phone":"+34 985 40 17 65",
    "sg:postcode":"33500",
    "sg:province":"Asturias",
    "wof:name":"Balmori Gutierrez Jose Antonio",
    "wof:placetype":"venue"
},
  "geometry": {"coordinates":[-4.7567338943,43.4207077026],"type":"Point"}
}