{
  "type": "Feature",
  "properties": {
    "addr:full":"Avgd Alcalde Pujol, 15 Lleida Lleida 25006",
    "addr:housenumber":"15",
    "addr:postcode":"25006",
    "addr:street":"Alcalde Pujol",
    "iso:country":"ES",
    "sg:address":"Avgd Alcalde Pujol, 15",
    "sg:city":"Lleida",
    "sg:orig_category":"Veh\u00cdculos De Ocasi\u00d3n",
    "sg:phone":"+34 902 36 50 54",
    "sg:postcode":"25006",
    "sg:province":"Lleida",
    "wof:name":"Coa Trucks S.l.",
    "wof:placetype":"venue"
},
  "geometry": {"coordinates":[0.6111879945,41.6192207336],"type":"Point"}
}