{
  "type": "Feature",
  "properties": {
    "addr:full":"Calle de Aaiun (el), 16 Teruel Teruel 44003",
    "addr:housenumber":"16",
    "addr:postcode":"44003",
    "addr:street":"Calle De Aaiun El",
    "iso:country":"ES",
    "sg:address":"Calle de Aaiun (el), 16",
    "sg:city":"Teruel",
    "sg:orig_category":"Transportes Por V\u00cdas Navegables",
    "sg:phone":"+34 978 60 92 99",
    "sg:postcode":"44003",
    "sg:province":"Teruel",
    "wof:name":"Guillen Hoyo Vicente",
    "wof:placetype":"venue"
},
  "geometry": {"coordinates":[-1.1015205383,40.3432502747],"type":"Point"}
}