{
  "type": "Feature",
  "properties": {
    "iso:country":"ES",
    "sg:address":"Unic, S/n",
    "sg:city":"Puigcercos",
    "sg:orig_category":"Producci\u00d3n, Comercio De Cereales",
    "sg:phone":"+34 973 65 23 05",
    "sg:postcode":"25633",
    "sg:province":"Lleida",
    "wof:name":"Janot Farre Jose",
    "wof:placetype":"venue"
},
  "geometry": {"coordinates":[0.8918750286,42.1315002441],"type":"Point"}
}