{
  "type": "Feature",
  "properties": {
    "addr:full":"Carrer de Miquel Crevea, 9 Cocentaina Alicante 03820",
    "addr:housenumber":"9",
    "addr:postcode":"03820",
    "addr:street":"Carrer De Miquel Crevea",
    "iso:country":"ES",
    "sg:address":"Carrer de Miquel Crevea, 9",
    "sg:city":"Cocentaina",
    "sg:orig_category":"Cajas De Ahorro",
    "sg:phone":"+34 966 50 00 62",
    "sg:postcode":"03820",
    "sg:province":"Alicante",
    "sg:website":"www.bancaja.es",
    "wof:name":"Caja De Ahorros De Valencia Castellon Y Alicante",
    "wof:placetype":"venue"
},
  "geometry": {"coordinates":[-0.4402129948,38.741771698],"type":"Point"}
}