{
  "type": "Feature",
  "properties": {
    "iso:country":"ES",
    "sg:address":"Carr Corralot, 40",
    "sg:city":"Albalat De La Ribera",
    "sg:orig_category":"Producci\u00d3n De Abonos Y De Fertilizantes",
    "sg:phone":"+34 962 49 00 14",
    "sg:postcode":"46687",
    "sg:province":"Valencia",
    "wof:name":"Carrascosa Florit Carlos",
    "wof:placetype":"venue"
},
  "geometry": {"coordinates":[-0.3883180022,39.2014541626],"type":"Point"}
}