{
  "type": "Feature",
  "properties": {
    "addr:full":"Ctra Estacio (de L'), 20 Ripollet Barcelona 08291",
    "addr:housenumber":"20",
    "addr:postcode":"08291",
    "addr:street":"Ctra Estacio De L '",
    "iso:country":"ES",
    "sg:address":"Ctra Estacio (de L'), 20",
    "sg:city":"Ripollet",
    "sg:orig_category":"Abogados",
    "sg:phone":"+34 936 91 94 32",
    "sg:postcode":"08291",
    "sg:province":"Barcelona",
    "wof:name":"Exposito Aranega Pedro Maria",
    "wof:placetype":"venue"
},
  "geometry": {"coordinates":[2.1530649662,41.4968643188],"type":"Point"}
}