{
  "type": "Feature",
  "properties": {
    "iso:country":"ES",
    "sg:address":"Grup Arriberri, 1",
    "sg:city":"Donostia-san Sebastian",
    "sg:orig_category":"Iglesia Cat\u00d3lica",
    "sg:phone":"+34 943 35 11 39",
    "sg:postcode":"20017",
    "sg:province":"Guip\u00f9zcoa",
    "wof:name":"Parroquia De San Pablo",
    "wof:placetype":"venue"
},
  "geometry": {"coordinates":[-1.9285449982,43.3176231384],"type":"Point"}
}