{
  "type": "Feature",
  "properties": {
    "iso:country":"ES",
    "sg:address":"C/ Ciutat, 14",
    "sg:city":"Llucmajor",
    "sg:orig_category":"Plomeros",
    "sg:phone":"+34 971 66 00 53",
    "sg:postcode":"07620",
    "sg:province":"Islas Baleares",
    "wof:name":"Fontaneria Llucmajor S L",
    "wof:placetype":"venue"
},
  "geometry": {"coordinates":[2.8881030083,39.4922370911],"type":"Point"}
}