{
  "type": "Feature",
  "properties": {
    "addr:full":"Calle de Cuchilleria, 34 Vitoria-gasteiz \u00c1lava 01001",
    "addr:housenumber":"34",
    "addr:postcode":"01001",
    "addr:street":"Calle De Cuchilleria",
    "iso:country":"ES",
    "sg:address":"Calle de Cuchilleria, 34",
    "sg:city":"Vitoria-gasteiz",
    "sg:orig_category":"Bares, Piano",
    "sg:phone":"+34 945 28 67 46",
    "sg:postcode":"01001",
    "sg:province":"\u00c1lava",
    "wof:name":"Martinez Fernandezdeleceta I\u00f1aki",
    "wof:placetype":"venue"
},
  "geometry": {"coordinates":[-2.6709954739,42.8487052917],"type":"Point"}
}