{
  "type": "Feature",
  "properties": {
    "addr:full":"Calle de Lezo-bide, 51 Pasai Donibane Guip\u00f9zcoa 20110",
    "addr:housenumber":"51",
    "addr:postcode":"20110",
    "addr:street":"Calle De Lezo-Bide;Guipu\u0300Zcoa",
    "iso:country":"ES",
    "sg:address":"Calle de Lezo-bide, 51",
    "sg:city":"Pasai Donibane",
    "sg:orig_category":"Suministros Para Carrocer\u00cdas",
    "sg:phone":"+34 943 51 85 83",
    "sg:postcode":"20110",
    "sg:province":"Guip\u00f9zcoa",
    "wof:name":"Ormazabal Otegui Juan Jose",
    "wof:placetype":"venue"
},
  "geometry": {"coordinates":[-1.9109840393,43.3241386414],"type":"Point"}
}