{
  "type": "Feature",
  "properties": {
    "addr:full":"Calle de Gelasio Aramburu, 13 Pasai Antxo Guip\u00f9zcoa 20110",
    "addr:housenumber":"13",
    "addr:postcode":"20110",
    "addr:street":"Calle De Gelasio Aramburu;Guipu\u0300Zcoa",
    "iso:country":"ES",
    "sg:address":"Calle de Gelasio Aramburu, 13",
    "sg:city":"Pasai Antxo",
    "sg:orig_category":"Artes Gr\u00c1ficas, Artes Pl\u00c1sticas (curso)",
    "sg:phone":"+34 943 51 05 94",
    "sg:postcode":"20110",
    "sg:province":"Guip\u00f9zcoa",
    "wof:name":"Arrillaga Guere\u00f1o Maricarmen",
    "wof:placetype":"venue"
},
  "geometry": {"coordinates":[-1.9165780544,43.317527771],"type":"Point"}
}