{
  "type": "Feature",
  "properties": {
    "addr:full":"Avda San Mames, 35 Le\u00f3n Le\u00f3n 24007",
    "addr:housenumber":"35",
    "addr:postcode":"24007",
    "addr:street":"Avda San Mames;Leo\u0301N",
    "iso:country":"ES",
    "sg:address":"Avda San Mames, 35",
    "sg:city":"Le\u00f3n",
    "sg:orig_category":"Zapatos (al Por Menor)",
    "sg:phone":"+34 987 24 27 00",
    "sg:postcode":"24007",
    "sg:province":"Le\u00f3n",
    "wof:name":"Ma\u00f1anes Garcia Eduardo",
    "wof:placetype":"venue"
},
  "geometry": {"coordinates":[-5.5710139275,42.6052017212],"type":"Point"}
}