{
  "type": "Feature",
  "properties": {
    "addr:full":"Calle de Padre Xifre, 3 Madrid Madrid 28002",
    "addr:housenumber":"3",
    "addr:postcode":"28002",
    "addr:street":"Calle De Padre Xifre",
    "iso:country":"ES",
    "sg:address":"Calle de Padre Xifre, 3",
    "sg:city":"Madrid",
    "sg:orig_category":"Labores Dom\u00c9sticas",
    "sg:phone":"+34 914 13 09 17",
    "sg:postcode":"28002",
    "sg:province":"Madrid",
    "wof:name":"V.m. Arquitectura Y Construccion S.l.",
    "wof:placetype":"venue"
},
  "geometry": {"coordinates":[-3.6729900837,40.4400672913],"type":"Point"}
}