{
  "type": "Feature",
  "properties": {
    "iso:country":"ES",
    "sg:address":"Barr San Roman La Gloria, 79",
    "sg:city":"San Roman",
    "sg:orig_category":"Muebles, Minoristas",
    "sg:phone":"+34 942 32 02 89",
    "sg:postcode":"39012",
    "sg:province":"Cantabria",
    "wof:name":"La Gubia Muebles Y Complementos S.c.",
    "wof:placetype":"venue"
},
  "geometry": {"coordinates":[-3.8422091007,43.4637527466],"type":"Point"}
}