{
  "type": "Feature",
  "properties": {
    "addr:full":"Calle de Bilbao, 45 Valencia Valencia 46009",
    "addr:housenumber":"45",
    "addr:postcode":"46009",
    "addr:street":"Calle De Bilbao",
    "iso:country":"ES",
    "sg:address":"Calle de Bilbao, 45",
    "sg:city":"Valencia",
    "sg:orig_category":"Laboratorios Y Trabajos De Fotograf\u00cda, V\u00cddeo Y Cine",
    "sg:phone":"+34 963 66 17 98",
    "sg:postcode":"46009",
    "sg:province":"Valencia",
    "wof:name":"Gonzalez Gimenez Enrique",
    "wof:placetype":"venue"
},
  "geometry": {"coordinates":[-0.3716445863,39.489200592],"type":"Point"}
}