{
  "type": "Feature",
  "properties": {
    "addr:full":"Rua Pedroso, 69 Casal Pontevedra 36618",
    "addr:housenumber":"69",
    "addr:postcode":"36618",
    "addr:street":"Rua Pedroso",
    "iso:country":"ES",
    "sg:address":"Rua Pedroso, 69",
    "sg:city":"Casal",
    "sg:orig_category":"Suministros Para Carrocer\u00cdas",
    "sg:phone":"+34 986 56 59 24",
    "sg:postcode":"36618",
    "sg:province":"Pontevedra",
    "wof:name":"Castro Carrocera S.a.",
    "wof:placetype":"venue"
},
  "geometry": {"coordinates":[-8.7647190094,42.5881881714],"type":"Point"}
}