{
  "type": "Feature",
  "properties": {
    "iso:country":"ES",
    "sg:address":"Calle de Iturralde Kalea, 4",
    "sg:city":"Amurrio",
    "sg:orig_category":"Alquiler De V\u00cddeo",
    "sg:phone":"+34 945 39 36 02",
    "sg:postcode":"01470",
    "sg:province":"\u00c1lava",
    "wof:name":"Gonzalez Barquero Ana Maria",
    "wof:placetype":"venue"
},
  "geometry": {"coordinates":[-3.0019950867,43.0526161194],"type":"Point"}
}