{
  "type": "Feature",
  "properties": {
    "addr:full":"Calle de San Gines, 1 Cehegin Murcia 30430",
    "addr:housenumber":"1",
    "addr:postcode":"30430",
    "addr:street":"Calle De San Gines",
    "iso:country":"ES",
    "sg:address":"Calle de San Gines, 1",
    "sg:city":"Cehegin",
    "sg:orig_category":"Panader\u00cdas, Panader\u00cdas",
    "sg:phone":"+34 968 74 00 11",
    "sg:postcode":"30430",
    "sg:province":"Murcia",
    "wof:name":"Abril Fernandez Juan",
    "wof:placetype":"venue"
},
  "geometry": {"coordinates":[-1.791607,38.092239],"type":"Point"}
}