{
  "type": "Feature",
  "properties": {
    "iso:country":"ES",
    "sg:address":"Ctra Carrion, Km. 0313,0",
    "sg:city":"Ciudad Real",
    "sg:orig_category":"Centros De Coordinaci\u00d3n",
    "sg:phone":"+34 926 25 61 34",
    "sg:postcode":"13005",
    "sg:province":"Ciudad Real",
    "wof:name":"Centro De Asesoria Hipotecaria S.l.",
    "wof:placetype":"venue"
},
  "geometry": {"coordinates":[-3.9038190842,38.9907417297],"type":"Point"}
}