{
  "type": "Feature",
  "properties": {
    "iso:country":"ES",
    "sg:address":"Via Augusta, 236",
    "sg:city":"Barcelona",
    "sg:orig_category":"Metalurgia",
    "sg:phone":"+34 932 00 56 73",
    "sg:postcode":"08021",
    "sg:province":"Barcelona",
    "wof:name":"Cisa Cedaceria Industrial Sl",
    "wof:placetype":"venue"
},
  "geometry": {"coordinates":[2.1376531124,41.3979148865],"type":"Point"}
}