{
  "type": "Feature",
  "properties": {
    "addr:full":"Calle de Salvador, 8 Tirgo La Rioja 26211",
    "addr:housenumber":"8",
    "addr:postcode":"26211",
    "addr:street":"Calle De Salvador;Rioja",
    "iso:country":"ES",
    "sg:address":"Calle de Salvador, 8",
    "sg:city":"Tirgo",
    "sg:orig_category":"Restaurantes",
    "sg:phone":"+34 941 30 17 77",
    "sg:postcode":"26211",
    "sg:province":"La Rioja",
    "wof:name":"Porres Diaz Pablo U Otro C.b.",
    "wof:placetype":"venue"
},
  "geometry": {"coordinates":[-3.0136179924,42.582233429],"type":"Point"}
}