{
  "type": "Feature",
  "properties": {
    "addr:full":"Calle de Cobalto, S/n Valladolid Valladolid 47012",
    "addr:housenumber":"s / n",
    "addr:postcode":"47012",
    "addr:street":"Calle De Cobalto",
    "iso:country":"ES",
    "sg:address":"Calle de Cobalto, S/n",
    "sg:city":"Valladolid",
    "sg:orig_category":"M\u00c1quinas Para Recortar Y Pegar",
    "sg:phone":"+34 983 20 83 31",
    "sg:postcode":"47012",
    "sg:province":"Valladolid",
    "wof:name":"Matricerias Matro S.l.",
    "wof:placetype":"venue"
},
  "geometry": {"coordinates":[-4.7044382095,41.6211166382],"type":"Point"}
}