{
  "type": "Feature",
  "properties": {
    "addr:full":"Calle de Almirante Bonifaz, 3 Burgos Burgos 09003",
    "addr:housenumber":"3",
    "addr:postcode":"09003",
    "addr:street":"Calle De Almirante Bonifaz",
    "iso:country":"ES",
    "sg:address":"Calle de Almirante Bonifaz, 3",
    "sg:city":"Burgos",
    "sg:orig_category":"Abogados",
    "sg:phone":"+34 947 20 88 10",
    "sg:postcode":"09003",
    "sg:province":"Burgos",
    "wof:name":"Jve Asesoria Juridica S.c.",
    "wof:placetype":"venue"
},
  "geometry": {"coordinates":[-3.7010667324,42.3414802551],"type":"Point"}
}