{
  "type": "Feature",
  "properties": {
    "iso:country":"ES",
    "sg:address":"Rua Juan Bautista Andrade, 112",
    "sg:city":"Pontevedra",
    "sg:orig_category":"Agencias Y Agentes Comerciales, Representantes",
    "sg:phone":"+34 986 87 05 30",
    "sg:postcode":"36005",
    "sg:province":"Pontevedra",
    "wof:name":"Carballo Cons Aurelio",
    "wof:placetype":"venue"
},
  "geometry": {"coordinates":[-8.6382904053,42.4445800781],"type":"Point"}
}