{
  "type": "Feature",
  "properties": {
    "iso:country":"ES",
    "sg:address":"Calle de Velazquez, 5",
    "sg:city":"Santa Lucia",
    "sg:orig_category":"Centros De Educaci\u00d3n Especial",
    "sg:phone":"+34 987 58 61 71",
    "sg:postcode":"24650",
    "sg:province":"Le\u00f3n",
    "wof:name":"Colegio Santa Lucia",
    "wof:placetype":"venue"
},
  "geometry": {"coordinates":[-5.6359148026,42.8743476868],"type":"Point"}
}