{
  "type": "Feature",
  "properties": {
    "addr:full":"Carr Primitiu Artigas, 18 Torroella Montgri Girona 17257",
    "addr:housenumber":"18",
    "addr:postcode":"17257",
    "addr:street":"Carr Primitiu Artigas",
    "iso:country":"ES",
    "sg:address":"Carr Primitiu Artigas, 18",
    "sg:city":"Torroella Montgri",
    "sg:orig_category":"Ropa Para Caballeros (al Por Menor)",
    "sg:phone":"+34 972 75 73 97",
    "sg:postcode":"17257",
    "sg:province":"Girona",
    "wof:name":"Pou Casademont Maria Teresa",
    "wof:placetype":"venue"
},
  "geometry": {"coordinates":[3.1277420521,42.042766571],"type":"Point"}
}