{
  "type": "Feature",
  "properties": {
    "addr:full":"Avda Iparralde, 1 Irun Guip\u00f9zcoa 20304",
    "addr:housenumber":"1",
    "addr:postcode":"20304",
    "addr:street":"Avda Iparralde;Guipu\u0300Zcoa",
    "iso:country":"ES",
    "sg:address":"Avda Iparralde, 1",
    "sg:city":"Irun",
    "sg:orig_category":"Empleado Administrativo",
    "sg:phone":"+34 943 62 18 72",
    "sg:postcode":"20304",
    "sg:province":"Guip\u00f9zcoa",
    "wof:name":"Rey Yanguas Juan Alberto Del",
    "wof:placetype":"venue"
},
  "geometry": {"coordinates":[-1.7885489464,43.3441581726],"type":"Point"}
}