{
  "type": "Feature",
  "properties": {
    "iso:country":"ES",
    "sg:address":"Barcia, 105",
    "sg:city":"Barcia",
    "sg:orig_category":"M\u00c1rmoles, Granitos Y Piedras Naturales",
    "sg:phone":"+34 988 47 19 50",
    "sg:postcode":"32411",
    "sg:province":"Ourense",
    "wof:name":"Rodriguez Duran Manuel",
    "wof:placetype":"venue"
},
  "geometry": {"coordinates":[-8.1786737442,42.2871932983],"type":"Point"}
}