{
  "type": "Feature",
  "properties": {
    "iso:country":"ES",
    "sg:address":"Calle de Jose Miguel Barandiaran, 16",
    "sg:city":"Santurtzi",
    "sg:orig_category":"Venta, Instalaci\u00d3n De Calefacci\u00d3n",
    "sg:phone":"+34 944 06 00 98",
    "sg:postcode":"48980",
    "sg:province":"Vizcaya",
    "wof:name":"Serpogas, S.l.",
    "wof:placetype":"venue"
},
  "geometry": {"coordinates":[-3.0343809128,43.3268318176],"type":"Point"}
}