{
  "type": "Feature",
  "properties": {
    "addr:full":"Plaz Provincia, 16 Vitoria-gasteiz \u00c1lava 01001",
    "addr:housenumber":"16",
    "addr:postcode":"01001",
    "addr:street":"Provincia",
    "iso:country":"ES",
    "sg:address":"Plaz Provincia, 16",
    "sg:city":"Vitoria-gasteiz",
    "sg:orig_category":"Bisuter\u00cda, Joyer\u00cda, Relojer\u00cda (al Por Menor)",
    "sg:phone":"+34 945 25 91 37",
    "sg:postcode":"01001",
    "sg:province":"\u00c1lava",
    "wof:name":"Joyeria La Giralda",
    "wof:placetype":"venue"
},
  "geometry": {"coordinates":[-2.675784111,42.8475723267],"type":"Point"}
}