{
  "type": "Feature",
  "properties": {
    "addr:full":"Calle de Maestro Gozalbo, 20 Valencia Valencia 46005",
    "addr:housenumber":"20",
    "addr:postcode":"46005",
    "addr:street":"Calle De Maestro Gozalbo",
    "iso:country":"ES",
    "sg:address":"Calle de Maestro Gozalbo, 20",
    "sg:city":"Valencia",
    "sg:orig_category":"Asesor\u00cda De Formaci\u00d3n Y Gesti\u00d3n De Personal",
    "sg:phone":"+34 963 95 24 65",
    "sg:postcode":"46005",
    "sg:province":"Valencia",
    "wof:name":"Salom Carrillo Juana Francisca",
    "wof:placetype":"venue"
},
  "geometry": {"coordinates":[-0.3692150116,39.4648475647],"type":"Point"}
}