{
  "type": "Feature",
  "properties": {
    "addr:full":"Carrer de Rambla (la), 9 Vendrell Tarragona 43700",
    "addr:housenumber":"9",
    "addr:postcode":"43700",
    "addr:street":"Carrer De Rambla La",
    "iso:country":"ES",
    "sg:address":"Carrer de Rambla (la), 9",
    "sg:city":"Vendrell",
    "sg:orig_category":"Formaci\u00d3n Continuada (variada)",
    "sg:phone":"+34 977 66 01 36",
    "sg:postcode":"43700",
    "sg:province":"Tarragona",
    "wof:name":"Fontanals Nin Josep",
    "wof:placetype":"venue"
},
  "geometry": {"coordinates":[1.5363639593,41.2208404541],"type":"Point"}
}