{
  "type": "Feature",
  "properties": {
    "addr:full":"Calle de Roa De La Vega, 23 Le\u00f3n Le\u00f3n 24001",
    "addr:housenumber":"23",
    "addr:postcode":"24001",
    "addr:street":"Calle De Roa De La Vega;Leo\u0301N",
    "iso:country":"ES",
    "sg:address":"Calle de Roa De La Vega, 23",
    "sg:city":"Le\u00f3n",
    "sg:orig_category":"Hoteles",
    "sg:phone":"+34 987 24 77 60",
    "sg:postcode":"24001",
    "sg:province":"Le\u00f3n",
    "wof:name":"Dominguez Dominguez Miguel",
    "wof:placetype":"venue"
},
  "geometry": {"coordinates":[-5.5771379471,42.5996246338],"type":"Point"}
}