{
  "type": "Feature",
  "properties": {
    "iso:country":"ES",
    "sg:address":"Calle de Donoso Cortes, 27",
    "sg:city":"Caceres",
    "sg:orig_category":"Contables",
    "sg:phone":"+34 927 24 72 47",
    "sg:postcode":"10003",
    "sg:province":"C\u00e1ceres",
    "wof:name":"Guillen Zancas Jose",
    "wof:placetype":"venue"
},
  "geometry": {"coordinates":[-6.3747820854,39.4732208252],"type":"Point"}
}