{
  "type": "Feature",
  "properties": {
    "iso:country":"ES",
    "sg:address":"Calle de Ribera De San Javier, 12",
    "sg:city":"Cartagena",
    "sg:orig_category":"Caf\u00c9s, Bares, Cervecer\u00cdas",
    "sg:phone":"+34 968 52 85 81",
    "sg:postcode":"30203",
    "sg:province":"Murcia",
    "wof:name":"Eurotel Sur",
    "wof:placetype":"venue"
},
  "geometry": {"coordinates":[-0.9837890267,37.6121101379],"type":"Point"}
}