{
  "type": "Feature",
  "properties": {
    "addr:full":"Calle de Londres, 11 Parla Madrid 28980",
    "addr:housenumber":"11",
    "addr:postcode":"28980",
    "addr:street":"Calle De Londres",
    "iso:country":"ES",
    "sg:address":"Calle de Londres, 11",
    "sg:city":"Parla",
    "sg:orig_category":"Fabricaci\u00d3n De Juguetes Autom\u00c1ticos",
    "sg:phone":"+34 916 05 05 84",
    "sg:postcode":"28980",
    "sg:province":"Madrid",
    "wof:name":"Nova-xpender S.l.",
    "wof:placetype":"venue"
},
  "geometry": {"coordinates":[-3.7734539509,40.237449646],"type":"Point"}
}