{
  "type": "Feature",
  "properties": {
    "addr:full":"Carrer de Mila I Fontanals, 93 Sabadell Barcelona 08205",
    "addr:housenumber":"93",
    "addr:postcode":"08205",
    "addr:street":"Carrer De Mila I Fontanals",
    "iso:country":"ES",
    "sg:address":"Carrer de Mila I Fontanals, 93",
    "sg:city":"Sabadell",
    "sg:orig_category":"Fabricaci\u00d3n De Juguetes Autom\u00c1ticos",
    "sg:phone":"+34 937 11 37 47",
    "sg:postcode":"08205",
    "sg:province":"Barcelona",
    "wof:name":"K.l. Manipulados S.l.",
    "wof:placetype":"venue"
},
  "geometry": {"coordinates":[2.1021940708,41.5355415344],"type":"Point"}
}