{
  "type": "Feature",
  "properties": {
    "addr:full":"Plaz Andalucia, 15 Manzanilla Huelva 21890",
    "addr:housenumber":"15",
    "addr:postcode":"21890",
    "addr:street":"Plaz Andalucia",
    "iso:country":"ES",
    "sg:address":"Plaz Andalucia, 15",
    "sg:city":"Manzanilla",
    "sg:orig_category":"Cajas Para Embalar",
    "sg:phone":"+34 959 41 50 70",
    "sg:postcode":"21890",
    "sg:province":"Huelva",
    "wof:name":"Caja Rural Del Sur Sociedad Cooperativa",
    "wof:placetype":"venue"
},
  "geometry": {"coordinates":[-6.4390740395,37.3908004761],"type":"Point"}
}