{
  "type": "Feature",
  "properties": {
    "iso:country":"ES",
    "sg:address":"Carr Nou De Juliol, 18",
    "sg:city":"Ciutadella Menorca",
    "sg:orig_category":"Semiller\u00cdas",
    "sg:phone":"+34 971 38 21 16",
    "sg:postcode":"07760",
    "sg:province":"Islas Baleares",
    "wof:name":"Segui Moll Juan",
    "wof:placetype":"venue"
},
  "geometry": {"coordinates":[3.8416149616,40.0027542114],"type":"Point"}
}