{
  "type": "Feature",
  "properties": {
    "addr:full":"Carrer de Santiago Rusi\u00d1ol, 2 Casco Urbano Barcelona 08450",
    "addr:housenumber":"2",
    "addr:postcode":"08450",
    "addr:street":"Carrer De Santiago Rusin\u0303Ol",
    "iso:country":"ES",
    "sg:address":"Carrer de Santiago Rusi\u00d1ol, 2",
    "sg:city":"Casco Urbano",
    "sg:orig_category":"Confecci\u00d3n De Trajes Para Se\u00d1oras",
    "sg:phone":"+34 938 41 02 81",
    "sg:postcode":"08450",
    "sg:province":"Barcelona",
    "wof:name":"Basart Albi Jose",
    "wof:placetype":"venue"
},
  "geometry": {"coordinates":[2.4019749165,41.6397705078],"type":"Point"}
}