{
  "type": "Feature",
  "properties": {
    "addr:full":"Carr Maluquer Salvador, 1 Girona Girona 17002",
    "addr:housenumber":"1",
    "addr:postcode":"17002",
    "addr:street":"Carr Maluquer Salvador",
    "iso:country":"ES",
    "sg:address":"Carr Maluquer Salvador, 1",
    "sg:city":"Girona",
    "sg:orig_category":"Lencer\u00cda Femenina, Corseter\u00cda, Trajes De Ba\u00d1o (al Por Menor)",
    "sg:phone":"+34 972 21 31 74",
    "sg:postcode":"17002",
    "sg:province":"Girona",
    "wof:name":"Bancells Viladomat Maria Angels",
    "wof:placetype":"venue"
},
  "geometry": {"coordinates":[2.8199210167,41.9771652222],"type":"Point"}
}