{
  "type": "Feature",
  "properties": {
    "iso:country":"ES",
    "sg:address":"Calle de Paseo Del Rio Guadarrama, 2",
    "sg:city":"Estacion",
    "sg:orig_category":"Psic\u00d3logos",
    "sg:phone":"+34 918 49 13 45",
    "sg:postcode":"28400",
    "sg:province":"Madrid",
    "wof:name":"Canales Molina Juan",
    "wof:placetype":"venue"
},
  "geometry": {"coordinates":[-3.9919650555,40.6455612183],"type":"Point"}
}