{
  "type": "Feature",
  "properties": {
    "addr:full":"Calle de Vera, S/n Berlanga Badajoz 06930",
    "addr:housenumber":"s / n",
    "addr:postcode":"06930",
    "addr:street":"Calle De Vera",
    "iso:country":"ES",
    "sg:address":"Calle de Vera, S/n",
    "sg:city":"Berlanga",
    "sg:orig_category":"Empresas De Desmonte",
    "sg:phone":"+34 924 89 41 03",
    "sg:postcode":"06930",
    "sg:province":"Badajoz",
    "wof:name":"Suministros Tema Gres S.l.",
    "wof:placetype":"venue"
},
  "geometry": {"coordinates":[-5.8316521645,38.2804794312],"type":"Point"}
}