{
  "type": "Feature",
  "properties": {
    "iso:country":"ES",
    "sg:address":"Calle de Carretera Zaragoza, 54",
    "sg:city":"Caparroso",
    "sg:orig_category":"Molduras, Junquillos, Listones Y Molduras Perforadas",
    "sg:phone":"+34 948 71 09 53",
    "sg:postcode":"31380",
    "sg:province":"Navarra",
    "wof:name":"Alvarez Martinez Gracia",
    "wof:placetype":"venue"
},
  "geometry": {"coordinates":[-1.6566376686,42.3228721619],"type":"Point"}
}