{
  "type": "Feature",
  "properties": {
    "iso:country":"ES",
    "sg:address":"Carrer de Ramon Llull, 29",
    "sg:city":"S. Boi Llobregat",
    "sg:orig_category":"Fabricaci\u00d3n De Moldes Y Modelos",
    "sg:phone":"+34 936 40 93 88",
    "sg:postcode":"08830",
    "sg:province":"Barcelona",
    "wof:name":"Nicalizados Rivas S.l.",
    "wof:placetype":"venue"
},
  "geometry": {"coordinates":[2.0335259438,41.3563232422],"type":"Point"}
}