{
  "type": "Feature",
  "properties": {
    "iso:country":"ES",
    "sg:address":"Carr Lleida, 8",
    "sg:city":"Palafrugell",
    "sg:orig_category":"Mec\u00c1nico Del Autom\u00d3vil",
    "sg:phone":"+34 972 30 17 65",
    "sg:postcode":"17200",
    "sg:province":"Girona",
    "wof:name":"Quibus Prats Joaquin",
    "wof:placetype":"venue"
},
  "geometry": {"coordinates":[3.1549320221,41.9136619568],"type":"Point"}
}