{
  "type": "Feature",
  "properties": {
    "iso:country":"ES",
    "sg:address":"Carrer de Mare De Deu De La Llum, 110",
    "sg:city":"Terrassa",
    "sg:orig_category":"Promotores Constructores",
    "sg:phone":"+34 937 83 91 90",
    "sg:postcode":"08222",
    "sg:province":"Barcelona",
    "wof:name":"Construcciones Egar-noysa S.l.",
    "wof:placetype":"venue"
},
  "geometry": {"coordinates":[2.0324718952,41.56042099],"type":"Point"}
}