{
  "type": "Feature",
  "properties": {
    "addr:full":"Zumea Kalea, 1 Andoain Guip\u00f9zcoa 20140",
    "addr:housenumber":"1",
    "addr:postcode":"20140",
    "addr:street":"Zumea Kalea;Guipu\u0300Zcoa",
    "iso:country":"ES",
    "sg:address":"Zumea Kalea, 1",
    "sg:city":"Andoain",
    "sg:orig_category":"Iglesia Cat\u00d3lica",
    "sg:phone":"+34 943 59 08 57",
    "sg:postcode":"20140",
    "sg:province":"Guip\u00f9zcoa",
    "wof:name":"Parroquia De La Santa Cruz",
    "wof:placetype":"venue"
},
  "geometry": {"coordinates":[-2.0220050812,43.2150917053],"type":"Point"}
}