{
  "type": "Feature",
  "properties": {
    "addr:full":"Calle de Bravo Murillo, 75 Madrid Madrid 28003",
    "addr:housenumber":"75",
    "addr:postcode":"madrid;28003",
    "addr:street":"Calle De Bravo Murillo",
    "iso:country":"ES",
    "sg:address":"Calle de Bravo Murillo, 75",
    "sg:city":"Madrid",
    "sg:orig_category":"Farmacias",
    "sg:phone":"+34 915 54 58 38",
    "sg:postcode":"28003",
    "sg:province":"Madrid",
    "wof:name":"Ramirez Canovas Carmen Maria",
    "wof:placetype":"venue"
},
  "geometry": {"coordinates":[-3.7041320801,40.4431266785],"type":"Point"}
}