{
  "type": "Feature",
  "properties": {
    "iso:country":"ES",
    "sg:address":"Ancha, S/n",
    "sg:city":"Alomartes",
    "sg:orig_category":"Iglesia Cat\u00d3lica",
    "sg:phone":"+34 958 45 61 82",
    "sg:postcode":"18350",
    "sg:province":"Granada",
    "wof:name":"Parroquia Nuestra Se\u00f1ora De Los Dolores",
    "wof:placetype":"venue"
},
  "geometry": {"coordinates":[-3.9091091156,37.2651290894],"type":"Point"}
}