{
  "type": "Feature",
  "properties": {
    "addr:full":"Calle de Garibai, 6 Donostia-san Sebastian Guip\u00f9zcoa 20004",
    "addr:housenumber":"6",
    "addr:postcode":"20004",
    "addr:street":"Calle De Garibai",
    "iso:country":"ES",
    "sg:address":"Calle de Garibai, 6",
    "sg:city":"Donostia-san Sebastian",
    "sg:orig_category":"Institutos De Belleza (productos Y Aparatos)",
    "sg:phone":"+34 943 43 00 61",
    "sg:postcode":"20004",
    "sg:province":"Guip\u00f9zcoa",
    "wof:name":"Centro De  Estetica Idoia Ugarte",
    "wof:placetype":"venue"
},
  "geometry": {"coordinates":[-1.9841899872,43.321434021],"type":"Point"}
}