{
  "type": "Feature",
  "properties": {
    "addr:full":"Rua Florentino Lopez Cuevillas, 17 Lugo Lugo 27004",
    "addr:housenumber":"17",
    "addr:postcode":"27004",
    "addr:street":"Rua Florentino;Cuevillas",
    "iso:country":"ES",
    "sg:address":"Rua Florentino Lopez Cuevillas, 17",
    "sg:city":"Lugo",
    "sg:orig_category":"Mec\u00c1nico Del Autom\u00d3vil",
    "sg:phone":"+34 982 20 31 32",
    "sg:postcode":"27004",
    "sg:province":"Lugo",
    "wof:name":"Vazquez Perez David",
    "wof:placetype":"venue"
},
  "geometry": {"coordinates":[-7.5680370331,43.0085754395],"type":"Point"}
}