{
  "type": "Feature",
  "properties": {
    "addr:full":"Calle de Alfonso Ix, 1 Zamora Zamora 49014",
    "addr:housenumber":"1",
    "addr:postcode":"49014",
    "addr:street":"Calle De Alfonso Ix",
    "iso:country":"ES",
    "sg:address":"Calle de Alfonso Ix, 1",
    "sg:city":"Zamora",
    "sg:orig_category":"Agentes Generales De Seguros",
    "sg:phone":"+34 980 53 32 16",
    "sg:postcode":"49014",
    "sg:province":"Zamora",
    "wof:name":"Lopez Fernandez Francisco",
    "wof:placetype":"venue"
},
  "geometry": {"coordinates":[-5.7418675423,41.5073890686],"type":"Point"}
}