{
  "type": "Feature",
  "properties": {
    "iso:country":"ES",
    "sg:address":"Mayor-nagusia Kalea, 36",
    "sg:city":"Iru\u00f1a",
    "sg:orig_category":"Organizaciones Profesionales",
    "sg:phone":"+34 948 20 76 69",
    "sg:postcode":"31001",
    "sg:province":"Navarra",
    "wof:name":"Casanellas Luri Aiona",
    "wof:placetype":"venue"
},
  "geometry": {"coordinates":[-1.6473759413,42.8177680969],"type":"Point"}
}