{
  "type": "Feature",
  "properties": {
    "addr:full":"Avda Jerez, Km. 0547,0 Sevilla Sevilla 41014",
    "addr:postcode":"41014",
    "addr:street":"Avda Jerez Km. 0547,0",
    "iso:country":"ES",
    "sg:address":"Avda Jerez, Km. 0547,0",
    "sg:city":"Sevilla",
    "sg:orig_category":"Agentes, Concesionarios Y Sucursales De Veh\u00cdculos",
    "sg:phone":"+34 954 69 39 57",
    "sg:postcode":"41014",
    "sg:province":"Sevilla",
    "wof:name":"Rafarca S. A.",
    "wof:placetype":"venue"
},
  "geometry": {"coordinates":[-5.9596791267,37.3278617859],"type":"Point"}
}