{
  "type": "Feature",
  "properties": {
    "iso:country":"ES",
    "sg:address":"Av Sant Jordi, 23",
    "sg:city":"Reus",
    "sg:orig_category":"Asociaciones Y Clubs Deportivos",
    "sg:phone":"+34 977 34 08 43",
    "sg:postcode":"43201",
    "sg:province":"Tarragona",
    "wof:name":"Penya Barcelonista Baix Camp",
    "wof:placetype":"venue"
},
  "geometry": {"coordinates":[1.1098480225,41.1608009338],"type":"Point"}
}