{
  "type": "Feature",
  "properties": {
    "addr:full":"Carrer de Dante Alighieri, 99 Barcelona Barcelona 08032",
    "addr:housenumber":"99",
    "addr:postcode":"08032",
    "addr:street":"Carrer De Dante Alighieri",
    "iso:country":"ES",
    "sg:address":"Carrer de Dante Alighieri, 99",
    "sg:city":"Barcelona",
    "sg:orig_category":"Ropa Para Se\u00d1oras Y Caballeros (al Por Menor)",
    "sg:phone":"+34 934 20 04 62",
    "sg:postcode":"08032",
    "sg:province":"Barcelona",
    "wof:name":"Garcia Romero Maria Isabel",
    "wof:placetype":"venue"
},
  "geometry": {"coordinates":[2.1563439369,41.4272232056],"type":"Point"}
}