{
  "type": "Feature",
  "properties": {
    "iso:country":"ES",
    "sg:address":"Carrer de Doctor Ferran, 45",
    "sg:city":"Reus",
    "sg:orig_category":"Promotores Constructores",
    "sg:phone":"+34 977 31 43 12",
    "sg:postcode":"43202",
    "sg:province":"Tarragona",
    "wof:name":"Construcciones Y Obras Reus S.l.",
    "wof:placetype":"venue"
},
  "geometry": {"coordinates":[1.0983090401,41.1544837952],"type":"Point"}
}