{
  "type": "Feature",
  "properties": {
    "iso:country":"ES",
    "sg:address":"Avda Nuestra Se\u00d1ora De La Soledad, 32",
    "sg:city":"Cantillana",
    "sg:orig_category":"Papeler\u00cdas, Librer\u00cdas",
    "sg:phone":"+34 955 73 21 77",
    "sg:postcode":"41320",
    "sg:province":"Sevilla",
    "wof:name":"Lopez Romero Cayetano",
    "wof:placetype":"venue"
},
  "geometry": {"coordinates":[-5.8230857849,37.6109008789],"type":"Point"}
}