{
  "type": "Feature",
  "properties": {
    "iso:country":"ES",
    "sg:address":"Calle de Espiritu Santo, 8",
    "sg:city":"Madrid",
    "sg:orig_category":"Inform\u00c1tica, Ofim\u00c1tica (estudios, Asesor\u00cda, Ingenier\u00cda, Formaci\u00d3n)",
    "sg:phone":"+34 915 31 22 70",
    "sg:postcode":"28004",
    "sg:province":"Madrid",
    "sg:website":"www.upi.es",
    "wof:name":"Perez Rodriguez Alejandro",
    "wof:placetype":"venue"
},
  "geometry": {"coordinates":[-3.7024691105,40.4252090454],"type":"Point"}
}