{
  "type": "Feature",
  "properties": {
    "addr:full":"Calle de Garcia Arista, 1 Zaragoza Zaragoza 50015",
    "addr:housenumber":"1",
    "addr:postcode":"50015",
    "addr:street":"Calle De Garcia Arista",
    "iso:country":"ES",
    "sg:address":"Calle de Garcia Arista, 1",
    "sg:city":"Zaragoza",
    "sg:orig_category":"Cajas De Ahorro",
    "sg:phone":"+34 976 73 70 01",
    "sg:postcode":"50015",
    "sg:province":"Zaragoza",
    "sg:website":"www.lacaixa.es",
    "wof:name":"Caixa D'estalvis I Pensions De Barcelona",
    "wof:placetype":"venue"
},
  "geometry": {"coordinates":[-0.8756229877,41.6589889526],"type":"Point"}
}