{
  "type": "Feature",
  "properties": {
    "addr:full":"Calle de Garcia Lorca, 16 Carmona Sevilla 41410",
    "addr:housenumber":"16",
    "addr:postcode":"41410",
    "addr:street":"Calle De Garcia Lorca",
    "iso:country":"ES",
    "sg:address":"Calle de Garcia Lorca, 16",
    "sg:city":"Carmona",
    "sg:orig_category":"M\u00c9dicos: Dermatolog\u00cda Y Venereolog\u00cda",
    "sg:phone":"+34 954 19 20 21",
    "sg:postcode":"41410",
    "sg:province":"Sevilla",
    "wof:name":"Buzon Cobano Eduardo",
    "wof:placetype":"venue"
},
  "geometry": {"coordinates":[-5.6451377869,37.4667778015],"type":"Point"}
}