{
  "type": "Feature",
  "properties": {
    "addr:full":"Av Esglesia (l'), 2 Nucia Alicante 03530",
    "addr:housenumber":"2",
    "addr:postcode":"03530",
    "addr:street":"Av Esglesia L '",
    "iso:country":"ES",
    "sg:address":"Av Esglesia (l'), 2",
    "sg:city":"Nucia",
    "sg:orig_category":"Iglesia Cat\u00d3lica",
    "sg:phone":"+34 965 87 07 29",
    "sg:postcode":"03530",
    "sg:province":"Alicante",
    "wof:name":"Parroquia De La Purisima Concepcion",
    "wof:placetype":"venue"
},
  "geometry": {"coordinates":[-0.1234040037,38.6174201965],"type":"Point"}
}