{
  "type": "Feature",
  "properties": {
    "iso:country":"ES",
    "sg:address":"Ctra. Bollullos, S/n",
    "sg:city":"Bormujos",
    "sg:orig_category":"Chapister\u00cda",
    "sg:phone":"+34 955 72 42 60",
    "sg:postcode":"41930",
    "sg:province":"Sevilla",
    "wof:name":"Gavi\u00f1o Romero Juan",
    "wof:placetype":"venue"
},
  "geometry": {"coordinates":[-6.0711288452,37.3726081848],"type":"Point"}
}