{
  "type": "Feature",
  "properties": {
    "addr:full":"Avda Principe De Asturias, 129 Villaviciosa Odon Madrid 28670",
    "addr:housenumber":"129",
    "addr:postcode":"28670",
    "addr:street":"Avda Principe De Asturias;Odon",
    "iso:country":"ES",
    "sg:address":"Avda Principe De Asturias, 129",
    "sg:city":"Villaviciosa Odon",
    "sg:orig_category":"Servicios Gsm",
    "sg:phone":"+34 916 85 50 42",
    "sg:postcode":"28670",
    "sg:province":"Madrid",
    "wof:name":"Fonocenter S.l.",
    "wof:placetype":"venue"
},
  "geometry": {"coordinates":[-3.8669540882,40.3543052673],"type":"Point"}
}