{
  "type": "Feature",
  "properties": {
    "addr:full":"Calle de Reyes, 11 Madrid Madrid 28015",
    "addr:housenumber":"11",
    "addr:postcode":"madrid;28015",
    "addr:street":"Calle De Reyes",
    "iso:country":"ES",
    "sg:address":"Calle de Reyes, 11",
    "sg:city":"Madrid",
    "sg:orig_category":"Procuradores",
    "sg:phone":"+34 915 41 00 76",
    "sg:postcode":"28015",
    "sg:province":"Madrid",
    "wof:name":"Noriega Arquer Jose Ignacio De",
    "wof:placetype":"venue"
},
  "geometry": {"coordinates":[-3.7092730999,40.4240837097],"type":"Point"}
}