{
  "type": "Feature",
  "properties": {
    "addr:full":"Avda Juan Xxiii, S/n Pedro\u00d1eras Cuenca 16660",
    "addr:housenumber":"s",
    "addr:postcode":"16660",
    "addr:street":"Avda Juan Xxiii;/ N Pedron\u0303Eras",
    "iso:country":"ES",
    "sg:address":"Avda Juan Xxiii, S/n",
    "sg:city":"Pedro\u00d1eras",
    "sg:orig_category":"Distribuci\u00d3n De Petr\u00d3leo Y Derivados",
    "sg:phone":"+34 967 16 20 02",
    "sg:postcode":"16660",
    "sg:province":"Cuenca",
    "sg:website":"www.cepsa.es",
    "wof:name":"Pedrogas S.l.",
    "wof:placetype":"venue"
},
  "geometry": {"coordinates":[-2.67918396,39.4532318115],"type":"Point"}
}