{
  "type": "Feature",
  "properties": {
    "addr:full":"Pg Mediterrani, 1 Altea Alicante 03590",
    "addr:housenumber":"1",
    "addr:postcode":"03590",
    "addr:street":"Pg Mediterrani",
    "iso:country":"ES",
    "sg:address":"Pg Mediterrani, 1",
    "sg:city":"Altea",
    "sg:orig_category":"Asesores De Gesti\u00d3n Del Patrimonio",
    "sg:phone":"+34 966 88 25 53",
    "sg:postcode":"03590",
    "sg:province":"Alicante",
    "wof:name":"Alteana De Patrimonios S.l.",
    "wof:placetype":"venue"
},
  "geometry": {"coordinates":[-0.0279866997,38.6424942017],"type":"Point"}
}