{
  "type": "Feature",
  "properties": {
    "iso:country":"ES",
    "sg:address":"Ctra. Palomar-adzaneta, S/n",
    "sg:city":"Atzeneta Albaida",
    "sg:orig_category":"Velas Y Cirios (fabricaci\u00d3n, Al Por Menor)",
    "sg:phone":"+34 962 35 65 64",
    "sg:postcode":"46869",
    "sg:province":"Valencia",
    "sg:website":"www.vilahermanoscereria.com",
    "wof:name":"Vila Hermanos Cereria S.a.",
    "wof:placetype":"venue"
},
  "geometry": {"coordinates":[-0.5286989808,38.8338088989],"type":"Point"}
}