{
  "type": "Feature",
  "properties": {
    "addr:full":"Calle de Juan Mu\u00d1oz, 10 Leganes Madrid 28911",
    "addr:housenumber":"10",
    "addr:postcode":"28911",
    "addr:street":"Calle De Juan Mun\u0303Oz",
    "iso:country":"ES",
    "sg:address":"Calle de Juan Mu\u00d1oz, 10",
    "sg:city":"Leganes",
    "sg:orig_category":"Bazares, Art\u00cdculos De Limpieza Y De Cocina (al Por Menor)",
    "sg:phone":"+34 916 94 81 21",
    "sg:postcode":"28911",
    "sg:province":"Madrid",
    "wof:name":"Lopez Fernandez Roberto Jose",
    "wof:placetype":"venue"
},
  "geometry": {"coordinates":[-3.7659850121,40.3293113708],"type":"Point"}
}