{
  "type": "Feature",
  "properties": {
    "iso:country":"ES",
    "sg:address":"Pase Marques De Zafra, 28",
    "sg:city":"Madrid",
    "sg:orig_category":"Frutas, Legumbres Frescas Y Tempranas (al Por Menor)",
    "sg:phone":"+34 917 25 51 12",
    "sg:postcode":"28028",
    "sg:province":"Madrid",
    "wof:name":"Velazquez Choes Dorly Alexandra",
    "wof:placetype":"venue"
},
  "geometry": {"coordinates":[-3.6650750637,40.4258651733],"type":"Point"}
}