{
  "type": "Feature",
  "properties": {
    "iso:country":"ES",
    "sg:address":"Carrer de Venteta (la), 6",
    "sg:city":"Aig\u00fces",
    "sg:orig_category":"Pescader\u00cdas (al Por Menor)",
    "sg:phone":"+34 965 69 00 12",
    "sg:postcode":"03569",
    "sg:province":"Alicante",
    "wof:name":"Pescados Fuentes S.l.",
    "wof:placetype":"venue"
},
  "geometry": {"coordinates":[-0.3620690107,38.500629425],"type":"Point"}
}