{
  "type": "Feature",
  "properties": {
    "iso:country":"ES",
    "sg:address":"Cerco Viejo, S/n",
    "sg:city":"Gares",
    "sg:orig_category":"Carnicer\u00cdas, Carnicer\u00cdas",
    "sg:phone":"+34 948 34 03 44",
    "sg:postcode":"31100",
    "sg:province":"Navarra",
    "wof:name":"Unciti Castillo Marcelo",
    "wof:placetype":"venue"
},
  "geometry": {"coordinates":[-1.8171390295,42.672580719],"type":"Point"}
}