{
  "type": "Feature",
  "properties": {
    "iso:country":"ES",
    "sg:address":"A Laxa, S/n",
    "sg:city":"Laxa",
    "sg:orig_category":"Alimentaci\u00d3n General (al Por Menor)",
    "sg:phone":"+34 988 49 28 17",
    "sg:postcode":"32417",
    "sg:province":"Ourense",
    "wof:name":"Perez Fernandez Manuela",
    "wof:placetype":"venue"
},
  "geometry": {"coordinates":[-8.1362161636,42.2448577881],"type":"Point"}
}