{
  "type": "Feature",
  "properties": {
    "iso:country":"ES",
    "sg:address":"Calle de Dolores Barranco, 88",
    "sg:city":"Madrid",
    "sg:orig_category":"Barbacoas Y Accesorios",
    "sg:phone":"+34 915 60 54 07",
    "sg:postcode":"28026",
    "sg:province":"Madrid",
    "wof:name":"Pozo Ucles Juan Carlos Del",
    "wof:placetype":"venue"
},
  "geometry": {"coordinates":[-3.71083951,40.3826751709],"type":"Point"}
}