{
  "type": "Feature",
  "properties": {
    "iso:country":"ES",
    "sg:address":"Carrer de Consell De Cent, 332",
    "sg:city":"Barcelona",
    "sg:orig_category":"Encuadernaci\u00d3n E Impresi\u00d3n De Folletos",
    "sg:phone":"+34 934 88 04 90",
    "sg:postcode":"08009",
    "sg:province":"Barcelona",
    "wof:name":"Centgraf S. A.",
    "wof:placetype":"venue"
},
  "geometry": {"coordinates":[2.1680190563,41.3926811218],"type":"Point"}
}