{
  "type": "Feature",
  "properties": {
    "iso:country":"ES",
    "sg:address":"Calle de Alfredo Marquerie, 14",
    "sg:city":"Madrid",
    "sg:orig_category":"Confecci\u00d3n De Trajes Para Se\u00d1oras",
    "sg:phone":"+34 913 78 44 31",
    "sg:postcode":"28034",
    "sg:province":"Madrid",
    "wof:name":"Cobo Garcia Maria Del Carmen",
    "wof:placetype":"venue"
},
  "geometry": {"coordinates":[-3.7066011429,40.4861450195],"type":"Point"}
}