{
  "type": "Feature",
  "properties": {
    "addr:full":"Trva Canicouva, 3 Pereiro Pontevedra 36213",
    "addr:housenumber":"3",
    "addr:postcode":"36213",
    "addr:street":"Trva Canicouva",
    "iso:country":"ES",
    "sg:address":"Trva Canicouva, 3",
    "sg:city":"Pereiro",
    "sg:orig_category":"Agencias Y Agentes Comerciales, Representantes",
    "sg:phone":"+34 986 29 52 88",
    "sg:postcode":"36213",
    "sg:province":"Pontevedra",
    "wof:name":"Rey Dominguez Manuel Victoriano",
    "wof:placetype":"venue"
},
  "geometry": {"coordinates":[-8.7210121155,42.1948318481],"type":"Point"}
}