{
  "type": "Feature",
  "properties": {
    "addr:full":"Calle de Zaratan, 1 Madrid Madrid 28037",
    "addr:housenumber":"1",
    "addr:postcode":"28037",
    "addr:street":"Calle De Zaratan",
    "iso:country":"ES",
    "sg:address":"Calle de Zaratan, 1",
    "sg:city":"Madrid",
    "sg:orig_category":"Frutas, Legumbres Frescas Y Tempranas (al Por Menor)",
    "sg:phone":"+34 917 54 41 55",
    "sg:postcode":"28037",
    "sg:province":"Madrid",
    "wof:name":"Lucas De La Torre Manuel",
    "wof:placetype":"venue"
},
  "geometry": {"coordinates":[-3.6258649826,40.4282951355],"type":"Point"}
}