{
  "type": "Feature",
  "properties": {
    "iso:country":"ES",
    "sg:address":"Calle de Doctor Grai\u00d1o Del, 3",
    "sg:city":"Aviles",
    "sg:orig_category":"Ropa Para Se\u00d1oras (al Por Menor)",
    "sg:phone":"+34 985 56 26 20",
    "sg:postcode":"33401",
    "sg:province":"Asturias",
    "sg:website":"www.induyco.es/sintesis",
    "wof:name":"Bernardo Garcia Aurelio",
    "wof:placetype":"venue"
},
  "geometry": {"coordinates":[-5.9256691933,43.5565490723],"type":"Point"}
}