{
  "type": "Feature",
  "properties": {
    "iso:country":"ES",
    "sg:address":"Calle de Puerto De Cerredo, 20",
    "sg:city":"Gijon",
    "sg:orig_category":"Transportes Por Carretera: Lotes Completos, Mercanc\u00cdas Diversas",
    "sg:phone":"+34 985 14 33 01",
    "sg:postcode":"33207",
    "sg:province":"Asturias",
    "wof:name":"Menendez Huerta Maria Del Rosario",
    "wof:placetype":"venue"
},
  "geometry": {"coordinates":[-5.677532196,43.53358078],"type":"Point"}
}