{
  "type": "Feature",
  "properties": {
    "iso:country":"ES",
    "sg:address":"Calle de Malaga, 26",
    "sg:city":"Alcala Henares",
    "sg:orig_category":"Cajas Y Embalajes De Pl\u00c1stico",
    "sg:phone":"+34 918 83 36 27",
    "sg:postcode":"28804",
    "sg:province":"Madrid",
    "wof:name":"J.carmona S.a.",
    "wof:placetype":"venue"
},
  "geometry": {"coordinates":[-3.3466069698,40.4885520935],"type":"Point"}
}