{
  "type": "Feature",
  "properties": {
    "addr:full":"Mugertza, 7 Bergara Guip\u00f9zcoa 20570",
    "addr:housenumber":"7",
    "addr:postcode":"20570",
    "addr:street":"Mugertza;Guipu\u0300Zcoa",
    "iso:country":"ES",
    "sg:address":"Mugertza, 7",
    "sg:city":"Bergara",
    "sg:orig_category":"Electricidad: Instaladores",
    "sg:phone":"+34 943 76 25 94",
    "sg:postcode":"20570",
    "sg:province":"Guip\u00f9zcoa",
    "wof:name":"Guisasola Barandiaran Basilio",
    "wof:placetype":"venue"
},
  "geometry": {"coordinates":[-2.4186589718,43.1220397949],"type":"Point"}
}