{
  "type": "Feature",
  "properties": {
    "iso:country":"ES",
    "sg:address":"Kontzezino Kalea, 18",
    "sg:city":"Arrasate",
    "sg:orig_category":"Cristaler\u00cdas",
    "sg:phone":"+34 943 08 28 91",
    "sg:postcode":"20500",
    "sg:province":"Guip\u00f9zcoa",
    "wof:name":"Arrasate Kristaldegia, S.l.",
    "wof:placetype":"venue"
},
  "geometry": {"coordinates":[-2.4910161495,43.0640525818],"type":"Point"}
}