{
  "type": "Feature",
  "properties": {
    "iso:country":"ES",
    "sg:address":"Trav Corts, 375",
    "sg:city":"Barcelona",
    "sg:orig_category":"Asesor\u00cda Fiscal Y Jur\u00cddica",
    "sg:phone":"+34 934 30 69 61",
    "sg:postcode":"08029",
    "sg:province":"Barcelona",
    "wof:name":"Garcia Mallor Jose Antonio",
    "wof:placetype":"venue"
},
  "geometry": {"coordinates":[2.1406400204,41.3901748657],"type":"Point"}
}