{
  "type": "Feature",
  "properties": {
    "addr:full":"Calle de Azucarera, S/n Torre Mar M\u00e1laga 29740",
    "addr:housenumber":"s / n",
    "addr:postcode":"29740",
    "addr:street":"Calle De Azucarera;Ma\u0301Laga",
    "iso:country":"ES",
    "sg:address":"Calle de Azucarera, S/n",
    "sg:city":"Torre Mar",
    "sg:orig_category":"Alquiler De Veh\u00cdculos: Turismos Y Utilitarios",
    "sg:phone":"+34 952 54 40 29",
    "sg:postcode":"29740",
    "sg:province":"M\u00e1laga",
    "wof:name":"Adrescotur S.l.",
    "wof:placetype":"venue"
},
  "geometry": {"coordinates":[-4.0907936096,36.745639801],"type":"Point"}
}