{
  "type": "Feature",
  "properties": {
    "addr:full":"Carrer de Fontcuberta, 5 Manlleu Barcelona 08560",
    "addr:housenumber":"5",
    "addr:postcode":"08560",
    "addr:street":"Carrer De Fontcuberta",
    "iso:country":"ES",
    "sg:address":"Carrer de Fontcuberta, 5",
    "sg:city":"Manlleu",
    "sg:orig_category":"Alimentaci\u00d3n General (al Por Menor)",
    "sg:phone":"+34 938 51 26 58",
    "sg:postcode":"08560",
    "sg:province":"Barcelona",
    "wof:name":"Eina Manteniment Integral S",
    "wof:placetype":"venue"
},
  "geometry": {"coordinates":[2.2922980785,42.0085716248],"type":"Point"}
}