{
  "type": "Feature",
  "properties": {
    "iso:country":"ES",
    "sg:address":"Cilla, 2",
    "sg:city":"Aroche",
    "sg:orig_category":"Arte, Cultura, Edici\u00d3n",
    "sg:phone":"+34 959 14 02 61",
    "sg:postcode":"21240",
    "sg:province":"Huelva",
    "wof:name":"Amigo Garcia Manuel",
    "wof:placetype":"venue"
},
  "geometry": {"coordinates":[-6.9540963173,37.9443855286],"type":"Point"}
}