{
  "type": "Feature",
  "properties": {
    "iso:country":"ES",
    "sg:address":"Calle de Carlos Aurioles, 11",
    "sg:city":"Madrid",
    "sg:orig_category":"Quincaller\u00cda (al Por Menor)",
    "sg:phone":"+34 917 85 54 19",
    "sg:postcode":"28018",
    "sg:province":"Madrid",
    "wof:name":"Fefruca S.l.",
    "wof:placetype":"venue"
},
  "geometry": {"coordinates":[-3.6658341885,40.3832435608],"type":"Point"}
}