{
  "type": "Feature",
  "properties": {
    "iso:country":"ES",
    "sg:address":"Calle de Santiago, 9",
    "sg:city":"Calahorra",
    "sg:orig_category":"Peluquer\u00cdas, Peluquer\u00cda Mixta",
    "sg:phone":"+34 941 13 44 68",
    "sg:postcode":"26500",
    "sg:province":"La Rioja",
    "wof:name":"Gallardo Lozano Rosario",
    "wof:placetype":"venue"
},
  "geometry": {"coordinates":[-1.9605180025,42.3020057678],"type":"Point"}
}