{
  "type": "Feature",
  "properties": {
    "addr:full":"Calle de Brigadas Internacionales, 8 Alcala Henares Madrid 28805",
    "addr:housenumber":"8",
    "addr:postcode":"28805",
    "addr:street":"Calle De Brigadas Internacionales",
    "iso:country":"ES",
    "sg:address":"Calle de Brigadas Internacionales, 8",
    "sg:city":"Alcala Henares",
    "sg:orig_category":"Promotores Constructores",
    "sg:phone":"+34 918 30 08 61",
    "sg:postcode":"28805",
    "sg:province":"Madrid",
    "wof:name":"Comunidad De Propietarios Brigadas Internacionales",
    "wof:placetype":"venue"
},
  "geometry": {"coordinates":[-3.3547523022,40.510925293],"type":"Point"}
}