{
  "type": "Feature",
  "properties": {
    "addr:full":"Calle de Mar Bonita, 7 Costa Ayala Las Palmas 35010",
    "addr:housenumber":"7",
    "addr:postcode":"35010",
    "addr:street":"Calle De Mar Bonita;Ayala Las Palmas",
    "iso:country":"ES",
    "sg:address":"Calle de Mar Bonita, 7",
    "sg:city":"Costa Ayala",
    "sg:orig_category":"Inmobiliaria (agencias)",
    "sg:phone":"+34 928 60 99 15",
    "sg:postcode":"35010",
    "sg:province":"Las Palmas",
    "wof:name":"Tierra De Gran Canaria Gestion Inmobiliaria S.l.",
    "wof:placetype":"venue"
},
  "geometry": {"coordinates":[-15.4397087097,28.1302242279],"type":"Point"}
}