{
  "type": "Feature",
  "properties": {
    "iso:country":"ES",
    "sg:address":"Carr Sant Lloren\u00c7, 39",
    "sg:city":"Lloseta",
    "sg:orig_category":"Reposter\u00cdas",
    "sg:phone":"+34 971 51 94 65",
    "sg:postcode":"07360",
    "sg:province":"Islas Baleares",
    "wof:name":"Ferrer Mayol Magdalena",
    "wof:placetype":"venue"
},
  "geometry": {"coordinates":[2.8673810959,39.719455719],"type":"Point"}
}