{
  "type": "Feature",
  "properties": {
    "iso:country":"ES",
    "sg:address":"Avda Benito Galceran, 8",
    "sg:city":"Viveiro",
    "sg:orig_category":"Farmacias",
    "sg:phone":"+34 982 56 01 38",
    "sg:postcode":"27850",
    "sg:province":"Lugo",
    "wof:name":"Miranda Alfonso Adelina",
    "wof:placetype":"venue"
},
  "geometry": {"coordinates":[-7.5952091217,43.6636695862],"type":"Point"}
}