{
  "type": "Feature",
  "properties": {
    "addr:full":"Pase Mercadal (del), 40 Calahorra La Rioja 26500",
    "addr:postcode":"26500",
    "iso:country":"ES",
    "sg:address":"Pase Mercadal (del), 40",
    "sg:city":"Calahorra",
    "sg:orig_category":"Agencias Y Asesores De Publicidad",
    "sg:phone":"+34 941 13 34 41",
    "sg:postcode":"26500",
    "sg:province":"La Rioja",
    "wof:name":"Objetivo Publicitario S.l.",
    "wof:placetype":"venue"
},
  "geometry": {"coordinates":[-1.9626489878,42.3045158386],"type":"Point"}
}