{
  "type": "Feature",
  "properties": {
    "addr:full":"Calle de Sierra De La Estrella, 1 Arganda Madrid 28500",
    "addr:housenumber":"1",
    "addr:postcode":"28500",
    "addr:street":"Calle De Sierra De La Estrella",
    "iso:country":"ES",
    "sg:address":"Calle de Sierra De La Estrella, 1",
    "sg:city":"Arganda",
    "sg:orig_category":"Oficinas: Suministros Para (fabricaci\u00d3n, Al Por Mayor)",
    "sg:phone":"+34 918 72 01 85",
    "sg:postcode":"28500",
    "sg:province":"Madrid",
    "wof:name":"Comercial Arge S.a.",
    "wof:placetype":"venue"
},
  "geometry": {"coordinates":[-3.479391098,40.3078689575],"type":"Point"}
}