{
  "type": "Feature",
  "properties": {
    "iso:country":"ES",
    "sg:address":"Avda Maisonnave, 46",
    "sg:city":"Alacant",
    "sg:orig_category":"Cl\u00cdnicas M\u00c9dicas",
    "sg:phone":"+34 965 92 69 52",
    "sg:postcode":"03003",
    "sg:province":"Alicante",
    "wof:name":"De Anta Y De Barrio Jesus",
    "wof:placetype":"venue"
},
  "geometry": {"coordinates":[-0.4942199886,38.3434791565],"type":"Point"}
}