{
  "type": "Feature",
  "properties": {
    "addr:full":"Calle de Gran Via De Colon, 51 Granada Granada 18001",
    "addr:housenumber":"51",
    "addr:postcode":"18001",
    "addr:street":"Calle De Gran Via De Colon",
    "iso:country":"ES",
    "sg:address":"Calle de Gran Via De Colon, 51",
    "sg:city":"Granada",
    "sg:orig_category":"Doctores En Medicina",
    "sg:phone":"+34 958 20 34 70",
    "sg:postcode":"18001",
    "sg:province":"Granada",
    "wof:name":"Pe\u00f1atoro Girela Braulio",
    "wof:placetype":"venue"
},
  "geometry": {"coordinates":[-3.6006989479,37.1812515259],"type":"Point"}
}