{
  "type": "Feature",
  "properties": {
    "iso:country":"ES",
    "sg:address":"Calle de Madre Del Buen Consejo, 1",
    "sg:city":"Torremolinos",
    "sg:orig_category":"Electricidad, Electr\u00d3nica: Material Y Suministros (al Por Mayor)",
    "sg:phone":"+34 952 05 35 38",
    "sg:postcode":"29620",
    "sg:province":"M\u00e1laga",
    "wof:name":"Juegomatic S. A.",
    "wof:placetype":"venue"
},
  "geometry": {"coordinates":[-4.5004448891,36.6247634888],"type":"Point"}
}