{
  "type": "Feature",
  "properties": {
    "addr:full":"Calle de Iglesia Vieja, 2 Olula Rio Almer\u00eda 04860",
    "addr:housenumber":"2",
    "addr:postcode":"04860",
    "addr:street":"Calle De Iglesia Vieja;Almeri\u0301A",
    "iso:country":"ES",
    "sg:address":"Calle de Iglesia Vieja, 2",
    "sg:city":"Olula Rio",
    "sg:orig_category":"Asociaciones Humanitarias, De Cooperaci\u00d3n, De Acci\u00d3n Social",
    "sg:phone":"+34 950 44 03 37",
    "sg:postcode":"04860",
    "sg:province":"Almer\u00eda",
    "wof:name":"Asarcom",
    "wof:placetype":"venue"
},
  "geometry": {"coordinates":[-2.2982857227,37.3520393372],"type":"Point"}
}