{
  "type": "Feature",
  "properties": {
    "addr:full":"Avda Sorolla De, 35 Torremolinos M\u00e1laga 29620",
    "addr:housenumber":"35",
    "addr:postcode":"29620",
    "addr:street":"Avda Sorolla De;Ma\u0301Laga",
    "iso:country":"ES",
    "sg:address":"Avda Sorolla De, 35",
    "sg:city":"Torremolinos",
    "sg:orig_category":"Importaci\u00d3n",
    "sg:phone":"+34 952 38 74 30",
    "sg:postcode":"29620",
    "sg:province":"M\u00e1laga",
    "wof:name":"Opincariu  Petru",
    "wof:placetype":"venue"
},
  "geometry": {"coordinates":[-4.5040969849,36.627040863],"type":"Point"}
}