{
  "type": "Feature",
  "properties": {
    "addr:full":"Carrer de Valencia, 437 Barcelona Barcelona 08013",
    "addr:housenumber":"437",
    "addr:postcode":"08013",
    "addr:street":"Carrer De Valencia",
    "iso:country":"ES",
    "sg:address":"Carrer de Valencia, 437",
    "sg:city":"Barcelona",
    "sg:orig_category":"Agencias De Viajes",
    "sg:phone":"+34 932 31 71 13",
    "sg:postcode":"08013",
    "sg:province":"Barcelona",
    "wof:name":"Viajes Barcelona Internacional S. A.",
    "wof:placetype":"venue"
},
  "geometry": {"coordinates":[2.176279068,41.4026298523],"type":"Point"}
}