{
  "type": "Feature",
  "properties": {
    "addr:full":"Calle de San Agustin, 8 Algorfa Alicante 03169",
    "addr:housenumber":"8",
    "addr:postcode":"03169",
    "addr:street":"Calle De San Agustin",
    "iso:country":"ES",
    "sg:address":"Calle de San Agustin, 8",
    "sg:city":"Algorfa",
    "sg:orig_category":"Art\u00cdculos De Decoraci\u00d3n",
    "sg:phone":"+34 966 78 20 86",
    "sg:postcode":"03169",
    "sg:province":"Alicante",
    "wof:name":"Senerio Garcia Trinidad",
    "wof:placetype":"venue"
},
  "geometry": {"coordinates":[-0.7971609831,38.0869522095],"type":"Point"}
}