{
  "type": "Feature",
  "properties": {
    "iso:country":"ES",
    "sg:address":"Rond General Mitre, 115",
    "sg:city":"Barcelona",
    "sg:orig_category":"Panader\u00cdas, Panader\u00cdas",
    "sg:phone":"+34 934 17 91 99",
    "sg:postcode":"08022",
    "sg:province":"Barcelona",
    "wof:name":"Font Juve Jose Maria",
    "wof:placetype":"venue"
},
  "geometry": {"coordinates":[2.1363780499,41.4014015198],"type":"Point"}
}