{
  "type": "Feature",
  "properties": {
    "iso:country":"ES",
    "sg:address":"Calle de Bruno Solano, 8",
    "sg:city":"Zaragoza",
    "sg:orig_category":"Fotocopias, Reprograf\u00cda",
    "sg:phone":"+34 976 35 05 56",
    "sg:postcode":"50006",
    "sg:province":"Zaragoza",
    "wof:name":"Gomez Rivas Maria Gloria",
    "wof:placetype":"venue"
},
  "geometry": {"coordinates":[-0.8940424919,41.6390533447],"type":"Point"}
}