{
  "type": "Feature",
  "properties": {
    "addr:full":"Carrer de Feliu, 28 Barcelona Barcelona 08041",
    "addr:housenumber":"28",
    "addr:postcode":"08041",
    "addr:street":"Carrer De Feliu",
    "iso:country":"ES",
    "sg:address":"Carrer de Feliu, 28",
    "sg:city":"Barcelona",
    "sg:orig_category":"Cables Y Hilos El\u00c9ctricos (fabricaci\u00d3n, Al Por Mayor)",
    "sg:phone":"+34 934 36 90 72",
    "sg:postcode":"08041",
    "sg:province":"Barcelona",
    "wof:name":"Aisbar S.l.",
    "wof:placetype":"venue"
},
  "geometry": {"coordinates":[2.1750752926,41.4180412292],"type":"Point"}
}