{
  "type": "Feature",
  "properties": {
    "addr:full":"Avda Coru\u00d1a (a), 2 Sada La Coru\u00f1a 15160",
    "addr:housenumber":"2",
    "addr:postcode":"15160",
    "addr:street":"Avda Corun\u0303A A;La",
    "iso:country":"ES",
    "sg:address":"Avda Coru\u00d1a (a), 2",
    "sg:city":"Sada",
    "sg:orig_category":"Art\u00cdculos Funerarios (al Por Menor)",
    "sg:phone":"+34 981 61 90 85",
    "sg:postcode":"15160",
    "sg:province":"La Coru\u00f1a",
    "wof:name":"Pompas Funebres De La Coru\u00f1a S.a.",
    "wof:placetype":"venue"
},
  "geometry": {"coordinates":[-8.2558240891,43.3478431702],"type":"Point"}
}