{
  "type": "Feature",
  "properties": {
    "addr:full":"Calle de Albatros (de), 26 Pinto Madrid 28320",
    "addr:housenumber":"26",
    "addr:postcode":"28320",
    "addr:street":"Calle De Albatros De",
    "iso:country":"ES",
    "sg:address":"Calle de Albatros (de), 26",
    "sg:city":"Pinto",
    "sg:orig_category":"Metalurgia",
    "sg:phone":"+34 916 91 63 11",
    "sg:postcode":"28320",
    "sg:province":"Madrid",
    "sg:website":"www.lonasa.es",
    "wof:name":"Lonasa Pinto S.a.",
    "wof:placetype":"venue"
},
  "geometry": {"coordinates":[-3.709225893,40.2522659302],"type":"Point"}
}