{
  "type": "Feature",
  "properties": {
    "iso:country":"ES",
    "sg:address":"Plaz Rafael Salazar, 23",
    "sg:city":"Villanueva Ariscal",
    "sg:orig_category":"Instalaci\u00d3n De Aspiraci\u00d3n De Gases Y Humos",
    "sg:phone":"+34 954 11 44 36",
    "sg:postcode":"41808",
    "sg:province":"Sevilla",
    "wof:name":"Gas Region Aplicaciones Energeticas S.l.",
    "wof:placetype":"venue"
},
  "geometry": {"coordinates":[-6.1437211037,37.395149231],"type":"Point"}
}