{
  "type": "Feature",
  "properties": {
    "addr:full":"Avda Juan Xxiii, 22 Huesca Huesca 22003",
    "addr:housenumber":"22",
    "addr:postcode":"22003",
    "addr:street":"Avda Juan Xxiii",
    "iso:country":"ES",
    "sg:address":"Avda Juan Xxiii, 22",
    "sg:city":"Huesca",
    "sg:orig_category":"Ense\u00d1anza: Costura",
    "sg:phone":"+34 974 22 32 21",
    "sg:postcode":"22003",
    "sg:province":"Huesca",
    "wof:name":"Granero Bernabe Maria Luisa",
    "wof:placetype":"venue"
},
  "geometry": {"coordinates":[-0.4083139896,42.1365661621],"type":"Point"}
}