{
  "type": "Feature",
  "properties": {
    "addr:full":"G (pol Ind Brenes), S/n Carmona Sevilla 41410",
    "addr:housenumber":"s / n",
    "addr:postcode":"41410",
    "iso:country":"ES",
    "sg:address":"G (pol Ind Brenes), S/n",
    "sg:city":"Carmona",
    "sg:orig_category":"Pescader\u00cdas (al Por Menor)",
    "sg:phone":"+34 954 14 15 94",
    "sg:postcode":"41410",
    "sg:province":"Sevilla",
    "wof:name":"Exclusivas Alcore S.l.",
    "wof:placetype":"venue"
},
  "geometry": {"coordinates":[-5.6573390961,37.4602203369],"type":"Point"}
}