{
  "type": "Feature",
  "properties": {
    "addr:full":"Calle de Almirante Martin De Vallecilla, 17 Portugalete Vizcaya 48920",
    "addr:housenumber":"17",
    "addr:postcode":"48920",
    "addr:street":"Calle De Almirante Martin De Vallecilla",
    "iso:country":"ES",
    "sg:address":"Calle de Almirante Martin De Vallecilla, 17",
    "sg:city":"Portugalete",
    "sg:classifiers":[
        {
            "category":"Personal",
            "subcategory":"Barber",
            "type":"Services"
        }
    ],
    "sg:phone":"+34 944 83 50 30",
    "sg:postcode":"48920",
    "sg:province":"Vizcaya",
    "sg:tags":[
        "caballeros",
        "de",
        "peluqueros"
    ],
    "wof:name":"Placido Fernandez Salgado",
    "wof:placetype":"venue"
},
  "geometry": {"coordinates":[-3.0206880569,43.3167724609],"type":"Point"}
}