{
  "type": "Feature",
  "properties": {
    "addr:full":"Calle de Serrablo (de), 60 Sabi\u00f1anigo Huesca 22600",
    "addr:housenumber":"60",
    "addr:postcode":"22600",
    "addr:street":"Calle De Serrablo De",
    "iso:country":"ES",
    "sg:address":"Calle de Serrablo (de), 60",
    "sg:city":"Sabi\u00f1anigo",
    "sg:classifiers":[
        {
            "category":"Taxi",
            "type":"Transportation"
        }
    ],
    "sg:phone":"+34 974 48 28 81",
    "sg:postcode":"22600",
    "sg:province":"Huesca",
    "wof:name":"Muro Gonzalez Jose",
    "wof:placetype":"venue"
},
  "geometry": {"coordinates":[-0.3672319949,42.5181274414],"type":"Point"}
}