{
  "type": "Feature",
  "properties": {
    "iso:country":"ES",
    "sg:address":"Cmno Miraflores, 2",
    "sg:city":"Zaragoza",
    "sg:orig_category":"Alimentaci\u00d3n General (al Por Menor)",
    "sg:phone":"+34 976 37 61 17",
    "sg:postcode":"50007",
    "sg:province":"Zaragoza",
    "wof:name":"Gracia Gracia Inmaculada",
    "wof:placetype":"venue"
},
  "geometry": {"coordinates":[-0.8750690222,41.6339683533],"type":"Point"}
}