{
  "type": "Feature",
  "properties": {
    "addr:full":"Calle de Roque (el), 5 Corralejo Playa Las Palmas 35660",
    "addr:housenumber":"5",
    "addr:postcode":"35660",
    "addr:street":"Calle De Roque El;Playa Las Palmas",
    "iso:country":"ES",
    "sg:address":"Calle de Roque (el), 5",
    "sg:city":"Corralejo Playa",
    "sg:orig_category":"Inmobiliaria (agencias)",
    "sg:phone":"+34 928 53 56 23",
    "sg:postcode":"35660",
    "sg:province":"Las Palmas",
    "wof:name":"Lurogada S.l.",
    "wof:placetype":"venue"
},
  "geometry": {"coordinates":[-13.8664989471,28.7248458862],"type":"Point"}
}