{
  "type": "Feature",
  "properties": {
    "iso:country":"ES",
    "sg:address":"Calle de Magallanes, 21",
    "sg:city":"Fuente Cantos",
    "sg:orig_category":"Negocio De Materiales De Construcci\u00d3n",
    "sg:phone":"+34 924 50 07 28",
    "sg:postcode":"06240",
    "sg:province":"Badajoz",
    "wof:name":"Suministros De Fuentede Cantos S.l.",
    "wof:placetype":"venue"
},
  "geometry": {"coordinates":[-6.3085460663,38.2491798401],"type":"Point"}
}