{
  "type": "Feature",
  "properties": {
    "iso:country":"ES",
    "sg:address":"Carrer de Santiago Rusi\u00d1ol, 4",
    "sg:city":"Palma",
    "sg:orig_category":"Expertos Contables",
    "sg:phone":"+34 971 72 18 21",
    "sg:postcode":"07012",
    "sg:province":"Islas Baleares",
    "wof:name":"Buffete Fiscal Roca S.l.",
    "wof:placetype":"venue"
},
  "geometry": {"coordinates":[2.6478600502,39.575969696],"type":"Point"}
}