{
  "type": "Feature",
  "properties": {
    "iso:country":"ES",
    "sg:address":"Calle de Miguel Molino, 6",
    "sg:city":"Zaragoza",
    "sg:orig_category":"Compraventa De Antig\u00dcedades",
    "sg:phone":"+34 976 39 33 01",
    "sg:postcode":"50003",
    "sg:province":"Zaragoza",
    "wof:name":"El Quinque Antiguedades S.c.",
    "wof:placetype":"venue"
},
  "geometry": {"coordinates":[-0.8798509836,41.6547088623],"type":"Point"}
}