{
  "type": "Feature",
  "properties": {
    "iso:country":"ES",
    "sg:address":"Carrer de Doctor Lluis Gaya, S/n",
    "sg:city":"Martorell",
    "sg:classifiers":[
        {
            "category":"Personal",
            "subcategory":"Barber",
            "type":"Services"
        }
    ],
    "sg:phone":"+34 937 75 38 90",
    "sg:postcode":"08760",
    "sg:province":"Barcelona",
    "sg:tags":[
        "caballeros",
        "de",
        "peluqueros"
    ],
    "wof:name":"Grup Julio S.c.p.",
    "wof:placetype":"venue"
},
  "geometry": {"coordinates":[1.9185049534,41.4760017395],"type":"Point"}
}