{
  "type": "Feature",
  "properties": {
    "iso:country":"ES",
    "sg:address":"Carrer de Sallares I Pla, 91",
    "sg:city":"Sabadell",
    "sg:orig_category":"Agencias Y Agentes Comerciales, Representantes",
    "sg:phone":"+34 937 25 98 87",
    "sg:postcode":"08202",
    "sg:province":"Barcelona",
    "wof:name":"Comercial Camilo S.c.p.",
    "wof:placetype":"venue"
},
  "geometry": {"coordinates":[2.1139330864,41.5430908203],"type":"Point"}
}