{
  "type": "Feature",
  "properties": {
    "iso:country":"ES",
    "sg:address":"Calle de Mayor De Nazaret, 94",
    "sg:city":"Valencia",
    "sg:orig_category":"Farmacias",
    "sg:phone":"+34 963 67 06 35",
    "sg:postcode":"46024",
    "sg:province":"Valencia",
    "wof:name":"Lahoz Garcia Ana",
    "wof:placetype":"venue"
},
  "geometry": {"coordinates":[-0.3341378868,39.4501876831],"type":"Point"}
}