{
  "type": "Feature",
  "properties": {
    "iso:country":"ES",
    "sg:address":"Carrer de Mare Deu Pilar (casc Antic), 16",
    "sg:city":"Barcelona",
    "sg:orig_category":"Asociaciones, Organismos Culturales Y Socioeducativos",
    "sg:phone":"+34 932 68 91 10",
    "sg:postcode":"08003",
    "sg:province":"Barcelona",
    "wof:name":"Fundacio Josep Carol",
    "wof:placetype":"venue"
},
  "geometry": {"coordinates":[2.1765120029,41.3874664307],"type":"Point"}
}