{
  "type": "Feature",
  "properties": {
    "iso:country":"ES",
    "sg:address":"Avda Menendez Pelayo, 55",
    "sg:city":"Sevilla",
    "sg:orig_category":"Agentes Generales De Seguros",
    "sg:phone":"+34 954 42 25 63",
    "sg:postcode":"41003",
    "sg:province":"Sevilla",
    "wof:name":"Martin Cerrudo Maria Esther",
    "wof:placetype":"venue"
},
  "geometry": {"coordinates":[-5.9849891663,37.3876686096],"type":"Point"}
}