{
  "type": "Feature",
  "properties": {
    "iso:country":"ES",
    "sg:address":"Calle de San Miguel, 43",
    "sg:city":"Zaragoza",
    "sg:orig_category":"Restaurantes",
    "sg:phone":"+34 976 23 10 48",
    "sg:postcode":"50001",
    "sg:province":"Zaragoza",
    "wof:name":"Marnos 97 S.l.",
    "wof:placetype":"venue"
},
  "geometry": {"coordinates":[-0.87717098,41.6499176025],"type":"Point"}
}