{
  "type": "Feature",
  "properties": {
    "addr:full":"Pase Carmelitas, 35 Salamanca Salamanca 37002",
    "addr:housenumber":"35",
    "addr:postcode":"37002",
    "addr:street":"Carmelitas",
    "iso:country":"ES",
    "sg:address":"Pase Carmelitas, 35",
    "sg:city":"Salamanca",
    "sg:orig_category":"Peluquer\u00cdas, Peluquer\u00cda Mixta",
    "sg:phone":"+34 923 21 56 74",
    "sg:postcode":"37002",
    "sg:province":"Salamanca",
    "wof:name":"Sevillano Martin Maria Jesus",
    "wof:placetype":"venue"
},
  "geometry": {"coordinates":[-5.6655359268,40.9691390991],"type":"Point"}
}