{
  "type": "Feature",
  "properties": {
    "iso:country":"ES",
    "sg:address":"Avda Paz, 132",
    "sg:city":"Yecla",
    "sg:orig_category":"Bebidas",
    "sg:phone":"+34 968 79 42 24",
    "sg:postcode":"30510",
    "sg:province":"Murcia",
    "wof:name":"Distribuciones De Montoya Y Susesores S.",
    "wof:placetype":"venue"
},
  "geometry": {"coordinates":[-1.1300820112,38.6149902344],"type":"Point"}
}