{
  "type": "Feature",
  "properties": {
    "addr:full":"Pla\u00c7 Soler I Carbonell, S/n Vilanova I La Geltru Barcelona 08800",
    "addr:housenumber":"s / n",
    "addr:postcode":"08800",
    "addr:street":"Carbonell",
    "iso:country":"ES",
    "sg:address":"Pla\u00c7 Soler I Carbonell, S/n",
    "sg:city":"Vilanova I La Geltru",
    "sg:orig_category":"Herboristas (al Por Menor)",
    "sg:phone":"+34 938 14 41 69",
    "sg:postcode":"08800",
    "sg:province":"Barcelona",
    "wof:name":"Caama\u00f1o Escorihuela Adela",
    "wof:placetype":"venue"
},
  "geometry": {"coordinates":[1.7230750322,41.2225646973],"type":"Point"}
}