{
  "type": "Feature",
  "properties": {
    "iso:country":"ES",
    "sg:address":"Calle de Molino De Las Monjas, 38",
    "sg:city":"Estepa",
    "sg:orig_category":"Empresas De Carpinter\u00cda",
    "sg:phone":"+34 955 91 22 37",
    "sg:postcode":"41560",
    "sg:province":"Sevilla",
    "wof:name":"Aluminio Enrique Y Ayala S.c",
    "wof:placetype":"venue"
},
  "geometry": {"coordinates":[-4.8714380264,37.2938423157],"type":"Point"}
}