{
  "type": "Feature",
  "properties": {
    "iso:country":"ES",
    "sg:address":"Artesanos, 10",
    "sg:city":"Vecindario",
    "sg:classifiers":[
        {
            "category":"Autos & Motor Vehicles",
            "subcategory":"Automobile Sales",
            "type":"Retail Goods"
        }
    ],
    "sg:phone":"+34 928 75 30 68",
    "sg:postcode":"35110",
    "sg:province":"Las Palmas",
    "wof:name":"Auto Escuela Vecindario S. L.",
    "wof:placetype":"venue"
},
  "geometry": {"coordinates":[-15.4401330948,27.8509902954],"type":"Point"}
}