{
  "type": "Feature",
  "properties": {
    "addr:full":"Cllo Siete Revueltas, 1 Toledo Toledo 45002",
    "addr:housenumber":"1",
    "addr:postcode":"45002",
    "iso:country":"ES",
    "sg:address":"Cllo Siete Revueltas, 1",
    "sg:city":"Toledo",
    "sg:orig_category":"Peluqueros: De Se\u00d1oras",
    "sg:phone":"+34 925 22 43 74",
    "sg:postcode":"45002",
    "sg:province":"Toledo",
    "wof:name":"Pinedo Ramirez Pilar",
    "wof:placetype":"venue"
},
  "geometry": {"coordinates":[-4.0290222168,39.8574905396],"type":"Point"}
}