{
  "type": "Feature",
  "properties": {
    "iso:country":"ES",
    "sg:address":"Calle de Pirotecnia, 33",
    "sg:city":"Madrid",
    "sg:orig_category":"Frutas Y Legumbres Frescas (al Por Mayor)",
    "sg:phone":"+34 917 76 42 03",
    "sg:postcode":"28052",
    "sg:province":"Madrid",
    "wof:name":"Aceitunas Guerra S.l.",
    "wof:placetype":"venue"
},
  "geometry": {"coordinates":[-3.5931854248,40.3963623047],"type":"Point"}
}