{
  "type": "Feature",
  "properties": {
    "iso:country":"ES",
    "sg:address":"Calle de Patalon, 18",
    "sg:city":"Plasencia",
    "sg:classifiers":[
        {
            "category":"Personal",
            "subcategory":"Barber",
            "type":"Services"
        }
    ],
    "sg:phone":"+34 927 41 49 55",
    "sg:postcode":"10600",
    "sg:province":"C\u00e1ceres",
    "sg:tags":[
        "caballeros",
        "de",
        "peluqueros"
    ],
    "wof:name":"Mu\u00f1oz Garcia Demetrio",
    "wof:placetype":"venue"
},
  "geometry": {"coordinates":[-6.0895991325,40.0293006897],"type":"Point"}
}