{
  "type": "Feature",
  "properties": {
    "addr:full":"Calle de Vazquez Lara, 13 Encinas Reales C\u00f3rdoba 14913",
    "addr:housenumber":"13",
    "addr:postcode":"14913",
    "addr:street":"Calle De Vazquez Lara",
    "iso:country":"ES",
    "sg:address":"Calle de Vazquez Lara, 13",
    "sg:city":"Encinas Reales",
    "sg:orig_category":"Empresas De Demolici\u00d3n",
    "sg:phone":"+34 957 59 82 20",
    "sg:postcode":"14913",
    "sg:province":"C\u00f3rdoba",
    "wof:name":"Gines Moreno,s.l.",
    "wof:placetype":"venue"
},
  "geometry": {"coordinates":[-4.4871687889,37.2763328552],"type":"Point"}
}