{
  "type": "Feature",
  "properties": {
    "addr:full":"Plaz Constitucion (la), 1 S. Miguel Salinas Alicante 03193",
    "addr:postcode":"03193",
    "addr:street":"Constitucion La 1 S. Miguel Salinas Alicante",
    "iso:country":"ES",
    "sg:address":"Plaz Constitucion (la), 1",
    "sg:city":"S. Miguel Salinas",
    "sg:orig_category":"Iglesia Cat\u00d3lica",
    "sg:phone":"+34 965 72 00 70",
    "sg:postcode":"03193",
    "sg:province":"Alicante",
    "wof:name":"Parroquia De San Miguel Arcangel",
    "wof:placetype":"venue"
},
  "geometry": {"coordinates":[-0.7697899938,37.9393119812],"type":"Point"}
}