{
  "type": "Feature",
  "properties": {
    "iso:country":"ES",
    "sg:address":"Calle de Luis Oliver, 2",
    "sg:city":"Marbella",
    "sg:orig_category":"Sociedades, Compa\u00d1\u00cdas Aseguradoras",
    "sg:phone":"+34 952 76 51 50",
    "sg:postcode":"29600",
    "sg:province":"M\u00e1laga",
    "wof:name":"La Estrella S.a. De Seguros",
    "wof:placetype":"venue"
},
  "geometry": {"coordinates":[-4.8888669014,36.5099906921],"type":"Point"}
}