{
  "type": "Feature",
  "properties": {
    "iso:country":"ES",
    "sg:address":"Carr De Vinar S, 48",
    "sg:city":"Benicarlo",
    "sg:orig_category":"Chapister\u00cda",
    "sg:phone":"+34 964 47 00 86",
    "sg:postcode":"12580",
    "sg:province":"Castell\u00f3n",
    "wof:name":"Salinas Perez Carlos",
    "wof:placetype":"venue"
},
  "geometry": {"coordinates":[0.4042100012,40.4457893372],"type":"Point"}
}