{
  "type": "Feature",
  "properties": {
    "iso:country":"ES",
    "sg:address":"Pl Angel Guimera, 7",
    "sg:city":"Cornella Llobregat",
    "sg:classifiers":[
        {
            "category":"Personal",
            "subcategory":"Barber",
            "type":"Services"
        }
    ],
    "sg:phone":"+34 933 75 65 13",
    "sg:postcode":"08940",
    "sg:province":"Barcelona",
    "sg:tags":[
        "caballeros",
        "de",
        "peluqueros"
    ],
    "wof:name":"Bravo Perez Javier",
    "wof:placetype":"venue"
},
  "geometry": {"coordinates":[2.0742108822,41.3647727966],"type":"Point"}
}