{
  "type": "Feature",
  "properties": {
    "iso:country":"ES",
    "sg:address":"Avgd Pere Mas I Reus, 16",
    "sg:city":"Platja D'alcudia",
    "sg:orig_category":"Perfumer\u00cda, Art\u00cdculos De Ba\u00d1o (fabricaci\u00d3n, Al Por Mayor)",
    "sg:phone":"+34 971 89 20 30",
    "sg:postcode":"07408",
    "sg:province":"Islas Baleares",
    "wof:name":"Artperfum S.l.",
    "wof:placetype":"venue"
},
  "geometry": {"coordinates":[3.1220273972,39.8523139954],"type":"Point"}
}