{
  "type": "Feature",
  "properties": {
    "addr:full":"Calle de Pitagoras, 1 Getafe Madrid 28906",
    "addr:housenumber":"1",
    "addr:postcode":"28906",
    "addr:street":"Calle De Pitagoras",
    "iso:country":"ES",
    "sg:address":"Calle de Pitagoras, 1",
    "sg:city":"Getafe",
    "sg:orig_category":"Distribuci\u00d3n De Petr\u00d3leo Y Derivados",
    "sg:phone":"+34 916 83 13 62",
    "sg:postcode":"28906",
    "sg:province":"Madrid",
    "wof:name":"Gasoleos Getafe S.l.",
    "wof:placetype":"venue"
},
  "geometry": {"coordinates":[-3.7045650482,40.2969970703],"type":"Point"}
}