{
  "type": "Feature",
  "properties": {
    "addr:full":"Calle de Doctor Fleming, 5 Ponferrada Le\u00f3n 24400",
    "addr:housenumber":"5",
    "addr:postcode":"24400",
    "addr:street":"Calle De Doctor Fleming",
    "iso:country":"ES",
    "sg:address":"Calle de Doctor Fleming, 5",
    "sg:city":"Ponferrada",
    "sg:orig_category":"Ropa Para Ni\u00d1os (al Por Menor)",
    "sg:phone":"+34 987 41 58 12",
    "sg:postcode":"24400",
    "sg:province":"Le\u00f3n",
    "wof:name":"Monpica Bierzo S.l.",
    "wof:placetype":"venue"
},
  "geometry": {"coordinates":[-6.5998821259,42.5490112305],"type":"Point"}
}