{
  "type": "Feature",
  "properties": {
    "iso:country":"ES",
    "sg:address":"Ctra Stgo-a Estrada, Km. 0008,0",
    "sg:city":"Reis",
    "sg:orig_category":"Agencias Y Agentes Comerciales, Representantes",
    "sg:phone":"+34 981 81 57 22",
    "sg:postcode":"15883",
    "sg:province":"La Coru\u00f1a",
    "wof:name":"Residencial Valle De La Ramallosa S.l.",
    "wof:placetype":"venue"
},
  "geometry": {"coordinates":[-8.5444011688,42.8382263184],"type":"Point"}
}