{
  "type": "Feature",
  "properties": {
    "addr:full":"Calle de Juan Antonio Untzueta, 2 Tra\u00e7a-matiena Vizcaya 48220",
    "addr:housenumber":"2",
    "addr:postcode":"48220",
    "addr:street":"Calle De Juan Antonio Untzueta",
    "iso:country":"ES",
    "sg:address":"Calle de Juan Antonio Untzueta, 2",
    "sg:city":"Tra\u00e7a-matiena",
    "sg:orig_category":"Reposter\u00cdas",
    "sg:phone":"+34 946 20 36 45",
    "sg:postcode":"48220",
    "sg:province":"Vizcaya",
    "wof:name":"Bilbao Iturriagaetxeberria Felix",
    "wof:placetype":"venue"
},
  "geometry": {"coordinates":[-2.6079039574,43.1692581177],"type":"Point"}
}