{
  "type": "Feature",
  "properties": {
    "addr:full":"Csta San Pedro, 1 Madrid Madrid 28005",
    "addr:housenumber":"1",
    "addr:postcode":"28005",
    "addr:street":"San Pedro",
    "iso:country":"ES",
    "sg:address":"Csta San Pedro, 1",
    "sg:city":"Madrid",
    "sg:orig_category":"Iglesia Cat\u00d3lica",
    "sg:phone":"+34 913 65 12 84",
    "sg:postcode":"28005",
    "sg:province":"Madrid",
    "wof:name":"Iglesia De San Pedro",
    "wof:placetype":"venue"
},
  "geometry": {"coordinates":[-3.7104899883,40.4132003784],"type":"Point"}
}