{
  "type": "Feature",
  "properties": {
    "iso:country":"ES",
    "sg:address":"Calle de Maestro Alonso, 5",
    "sg:city":"Madrid",
    "sg:orig_category":"Tintes (fabricaci\u00d3n, Al Por Mayor)",
    "sg:phone":"+34 917 26 00 68",
    "sg:postcode":"28028",
    "sg:province":"Madrid",
    "wof:name":"Vizcaya Dominguez Vicente",
    "wof:placetype":"venue"
},
  "geometry": {"coordinates":[-3.6646239758,40.4294624329],"type":"Point"}
}