{
  "type": "Feature",
  "properties": {
    "iso:country":"ES",
    "sg:address":"Avda Torcuato Fernandez Miranda, 42",
    "sg:city":"Gijon",
    "sg:orig_category":"Venta, Instalaci\u00d3n De Cocinas",
    "sg:phone":"+34 985 37 24 97",
    "sg:postcode":"33203",
    "sg:province":"Asturias",
    "wof:name":"Restaurante La Casa Del Parque C.b.",
    "wof:placetype":"venue"
},
  "geometry": {"coordinates":[-5.6402292252,43.5356864929],"type":"Point"}
}