{
  "type": "Feature",
  "properties": {
    "iso:country":"ES",
    "sg:address":"Pl Jacint Verdaguer (d'en), 4",
    "sg:city":"Tarragona",
    "sg:orig_category":"Ropa Para Se\u00d1oras (al Por Menor)",
    "sg:phone":"+34 977 23 77 26",
    "sg:postcode":"43003",
    "sg:province":"Tarragona",
    "wof:name":"Ochoa Calvo Carmen",
    "wof:placetype":"venue"
},
  "geometry": {"coordinates":[1.2558410168,41.1152763367],"type":"Point"}
}