{
  "type": "Feature",
  "properties": {
    "addr:full":"Calle de Periodista Jose Maria Carulla, 5 Granada Granada 18014",
    "addr:housenumber":"5",
    "addr:postcode":"18014",
    "addr:street":"Calle De Periodista Jose Maria Carulla",
    "iso:country":"ES",
    "sg:address":"Calle de Periodista Jose Maria Carulla, 5",
    "sg:city":"Granada",
    "sg:orig_category":"Inmobiliaria (agencias)",
    "sg:phone":"+34 958 15 99 46",
    "sg:postcode":"18014",
    "sg:province":"Granada",
    "sg:website":"www.eligeinmobiliaria.com",
    "wof:name":"Aguilar Granados Juan",
    "wof:placetype":"venue"
},
  "geometry": {"coordinates":[-3.6221444607,37.1955375671],"type":"Point"}
}