{
  "type": "Feature",
  "properties": {
    "addr:full":"Calle de Seis De Junio, 77 Valdepe\u00f1as Ciudad Real 13300",
    "addr:housenumber":"77",
    "addr:postcode":"13300",
    "addr:street":"Calle De Seis De Junio",
    "iso:country":"ES",
    "sg:address":"Calle de Seis De Junio, 77",
    "sg:city":"Valdepe\u00f1as",
    "sg:orig_category":"Bancos",
    "sg:phone":"+34 926 34 80 48",
    "sg:postcode":"13300",
    "sg:province":"Ciudad Real",
    "sg:website":"www.barclays.es",
    "wof:name":"Barclays Bank S.a.e.",
    "wof:placetype":"venue"
},
  "geometry": {"coordinates":[-3.3875091076,38.7611045837],"type":"Point"}
}