{
  "type": "Feature",
  "properties": {
    "iso:country":"ES",
    "sg:address":"Monasterio De La Oliva, 37",
    "sg:city":"Iru\u00f1a",
    "sg:orig_category":"Venta, Reparaci\u00d3n De M\u00c1quinas De Coser, Planchadoras Y M\u00c1quinas De Tricotar",
    "sg:phone":"+34 948 25 11 48",
    "sg:postcode":"31011",
    "sg:province":"Navarra",
    "wof:name":"Ainaga Salaberri Maria Esperanza",
    "wof:placetype":"venue"
},
  "geometry": {"coordinates":[-1.6613218784,42.8153076172],"type":"Point"}
}