{
  "type": "Feature",
  "properties": {
    "addr:full":"Calle de Santa Engracia, 52 Madrid Madrid 28010",
    "addr:housenumber":"52",
    "addr:postcode":"madrid;28010",
    "addr:street":"Calle De Santa Engracia",
    "iso:country":"ES",
    "sg:address":"Calle de Santa Engracia, 52",
    "sg:city":"Madrid",
    "sg:orig_category":"Cajas De Ahorro",
    "sg:phone":"+34 915 94 37 72",
    "sg:postcode":"28010",
    "sg:province":"Madrid",
    "sg:website":"www.lacaixa.es",
    "wof:name":"Caixa D'estalvis I Pensions De Barcelona",
    "wof:placetype":"venue"
},
  "geometry": {"coordinates":[-3.6982688904,40.4342918396],"type":"Point"}
}