{
  "type": "Feature",
  "properties": {
    "iso:country":"ES",
    "sg:address":"Avda Simon Nieto, 8",
    "sg:city":"Palencia",
    "sg:orig_category":"Servicios Y Funcionarios De Polic\u00cda",
    "sg:phone":"+34 979 16 74 00",
    "sg:postcode":"34...",
    "sg:province":"Palencia",
    "wof:name":"Direccion General De La Policia",
    "wof:placetype":"venue"
},
  "geometry": {"coordinates":[-4.538394928,42.0163650513],"type":"Point"}
}