{
  "type": "Feature",
  "properties": {
    "addr:full":"Calle de Romero Cordoba, 12 Ceuta Ceuta 51002",
    "addr:housenumber":"12",
    "addr:postcode":"51002",
    "addr:street":"Calle De Romero Cordoba",
    "iso:country":"ES",
    "sg:address":"Calle de Romero Cordoba, 12",
    "sg:city":"Ceuta",
    "sg:orig_category":"Zapater\u00cdas",
    "sg:phone":"+34 956 50 64 66",
    "sg:postcode":"51002",
    "sg:province":"Ceuta",
    "wof:name":"Roman Orozco Jesus Maria",
    "wof:placetype":"venue"
},
  "geometry": {"coordinates":[-5.3314437866,35.8856964111],"type":"Point"}
}