{
  "type": "Feature",
  "properties": {
    "iso:country":"ES",
    "sg:address":"Pto. Deportivo Las Fuentes, S/n",
    "sg:city":"Alcoceber",
    "sg:orig_category":"Deportes N\u00c1uticos, Acu\u00c1ticos Y Subacu\u00c1ticos: Art\u00cdculos Y Equipo (al Por Menor)",
    "sg:phone":"+34 964 41 46 88",
    "sg:postcode":"12579",
    "sg:province":"Castell\u00f3n",
    "wof:name":"Zaragoza Pitarch Ramon Adrian",
    "wof:placetype":"venue"
},
  "geometry": {"coordinates":[0.2761178017,40.2457504272],"type":"Point"}
}