{
  "type": "Feature",
  "properties": {
    "addr:full":"Av Portal De L'angel, 40 Barcelona Barcelona 08002",
    "addr:housenumber":"40",
    "addr:postcode":"08002",
    "addr:street":"Av Portal De L'Angel",
    "iso:country":"ES",
    "sg:address":"Av Portal De L'angel, 40",
    "sg:city":"Barcelona",
    "sg:orig_category":"Abogados",
    "sg:phone":"+34 933 18 10 36",
    "sg:postcode":"08002",
    "sg:province":"Barcelona",
    "wof:name":"Varela Castro Fernando Primo",
    "wof:placetype":"venue"
},
  "geometry": {"coordinates":[2.1718034744,41.3865890503],"type":"Point"}
}