{
  "type": "Feature",
  "properties": {
    "iso:country":"ES",
    "sg:address":"Calle de Doctor Moreno, 26",
    "sg:city":"Valladolid",
    "sg:orig_category":"Empresarios",
    "sg:phone":"+34 983 23 55 27",
    "sg:postcode":"47008",
    "sg:province":"Valladolid",
    "wof:name":"Martin Martin Isidoro",
    "wof:placetype":"venue"
},
  "geometry": {"coordinates":[-4.7408971786,41.6245193481],"type":"Point"}
}