{
  "type": "Feature",
  "properties": {
    "addr:full":"Calle de Alicante, 9 Castellon Castell\u00f3n 12004",
    "addr:housenumber":"9",
    "addr:postcode":"12004",
    "addr:street":"Calle De Alicante;Castello\u0301N",
    "iso:country":"ES",
    "sg:address":"Calle de Alicante, 9",
    "sg:city":"Castellon",
    "sg:orig_category":"Material Y Herramientas Agr\u00cdcolas",
    "sg:phone":"+34 964 22 55 12",
    "sg:postcode":"12004",
    "sg:province":"Castell\u00f3n",
    "wof:name":"Archiles Escorihuela Joaquin",
    "wof:placetype":"venue"
},
  "geometry": {"coordinates":[-0.0360953994,39.9939727783],"type":"Point"}
}