{
  "type": "Feature",
  "properties": {
    "addr:full":"Calle de Virgen De Los Lirios, 7 Ibi Alicante 03440",
    "addr:housenumber":"7",
    "addr:postcode":"03440",
    "addr:street":"Calle De Virgen De Los Lirios",
    "iso:country":"ES",
    "sg:address":"Calle de Virgen De Los Lirios, 7",
    "sg:city":"Ibi",
    "sg:orig_category":"Juegos Y Juguetes (al Por Menor)",
    "sg:phone":"+34 965 55 12 58",
    "sg:postcode":"03440",
    "sg:province":"Alicante",
    "sg:website":"www.juguetesvercor.com",
    "wof:name":"Juguetes Vercor S.a.",
    "wof:placetype":"venue"
},
  "geometry": {"coordinates":[-0.5789369941,38.6192512512],"type":"Point"}
}