{
  "type": "Feature",
  "properties": {
    "addr:full":"C/ Pintor Casanova, 8 Alcoi Alicante 03801",
    "addr:housenumber":"8",
    "addr:postcode":"03801",
    "addr:street":"C / Pintor Casanova",
    "iso:country":"ES",
    "sg:address":"C/ Pintor Casanova, 8",
    "sg:city":"Alcoi",
    "sg:orig_category":"M\u00c9dicos: An\u00c1lisis Cl\u00cdnicos",
    "sg:phone":"+34 965 54 31 30",
    "sg:postcode":"03801",
    "sg:province":"Alicante",
    "wof:name":"Boronat Martinez Miguel",
    "wof:placetype":"venue"
},
  "geometry": {"coordinates":[-0.4728370011,38.6986236572],"type":"Point"}
}