{
  "type": "Feature",
  "properties": {
    "iso:country":"ES",
    "sg:address":"C/ Artur Mundet, S/n",
    "sg:city":"S. Antoni Calonge",
    "sg:orig_category":"Doctores En Medicina",
    "sg:phone":"+34 972 65 05 83",
    "sg:postcode":"17252",
    "sg:province":"Girona",
    "wof:name":"Cabarrocas Gafarot Enrique",
    "wof:placetype":"venue"
},
  "geometry": {"coordinates":[3.1094601154,41.8569297791],"type":"Point"}
}