{
  "type": "Feature",
  "properties": {
    "addr:full":"Pol Ind Can Massaguer, 49 Sta. Agnes Malanyanes Barcelona 08430",
    "addr:housenumber":"49",
    "addr:postcode":"08430",
    "addr:street":"Ind;Massaguer",
    "iso:country":"ES",
    "sg:address":"Pol Ind Can Massaguer, 49",
    "sg:city":"Sta. Agnes Malanyanes",
    "sg:orig_category":"Zapatos (al Por Menor)",
    "sg:phone":"+34 938 42 30 19",
    "sg:postcode":"08430",
    "sg:province":"Barcelona",
    "sg:website":"www.yanko.com",
    "wof:name":"Yanko S.a.",
    "wof:placetype":"venue"
},
  "geometry": {"coordinates":[2.1699187756,41.3879165649],"type":"Point"}
}