{
  "type": "Feature",
  "properties": {
    "addr:full":"Barro Elexalde, 26 Leioa Vizcaya 48940",
    "addr:housenumber":"26",
    "addr:postcode":"48940",
    "addr:street":"Barro Elexalde",
    "iso:country":"ES",
    "sg:address":"Barro Elexalde, 26",
    "sg:city":"Leioa",
    "sg:orig_category":"Comercio De Cuadros, L\u00c1minas Y Reproducciones De Obras De Arte",
    "sg:phone":"+34 944 02 23 64",
    "sg:postcode":"48940",
    "sg:province":"Vizcaya",
    "wof:name":"Oscar Sanchez (arte Leioa)",
    "wof:placetype":"venue"
},
  "geometry": {"coordinates":[-2.9860789776,43.3275489807],"type":"Point"}
}