{
  "type": "Feature",
  "properties": {
    "addr:full":"Calle de Monte Llosorio, 7 Mieres Asturias 33600",
    "addr:housenumber":"7",
    "addr:postcode":"33600",
    "addr:street":"Calle De Monte Llosorio",
    "iso:country":"ES",
    "sg:address":"Calle de Monte Llosorio, 7",
    "sg:city":"Mieres",
    "sg:classifiers":[
        {
            "category":"Taxi",
            "type":"Transportation"
        }
    ],
    "sg:phone":"+34 985 45 11 45",
    "sg:postcode":"33600",
    "sg:province":"Asturias",
    "wof:name":"Gonzalez Fernandez Jose Ramon",
    "wof:placetype":"venue"
},
  "geometry": {"coordinates":[-5.775976181,43.2484130859],"type":"Point"}
}