{
  "type": "Feature",
  "properties": {
    "iso:country":"ES",
    "sg:address":"Cno Algaba, S/n",
    "sg:city":"Alcala Rio",
    "sg:orig_category":"Material Y Suministros Para Horticultura, Arboricultura",
    "sg:phone":"+34 954 78 00 96",
    "sg:postcode":"41200",
    "sg:province":"Sevilla",
    "wof:name":"Pastor Abonos S.l.",
    "wof:placetype":"venue"
},
  "geometry": {"coordinates":[-5.9833860397,37.521987915],"type":"Point"}
}