{
  "type": "Feature",
  "properties": {
    "addr:full":"Calle de San Roque, S/n Santa Olalla Toledo 45530",
    "addr:housenumber":"s / n",
    "addr:postcode":"45530",
    "addr:street":"Calle De San Roque",
    "iso:country":"ES",
    "sg:address":"Calle de San Roque, S/n",
    "sg:city":"Santa Olalla",
    "sg:orig_category":"Promotores Constructores",
    "sg:phone":"+34 925 74 41 88",
    "sg:postcode":"45530",
    "sg:province":"Toledo",
    "wof:name":"Construcciones Frando S.a.",
    "wof:placetype":"venue"
},
  "geometry": {"coordinates":[-4.4223690033,40.0246124268],"type":"Point"}
}