{
  "type": "Feature",
  "properties": {
    "iso:country":"ES",
    "sg:address":"Plaz Juan Naya, 1",
    "sg:city":"Coru\u00d1a",
    "sg:orig_category":"Reposter\u00cdas",
    "sg:phone":"+34 981 20 88 80",
    "sg:postcode":"15003",
    "sg:province":"La Coru\u00f1a",
    "wof:name":"Panaderia Antonio Lozano S.l.",
    "wof:placetype":"venue"
},
  "geometry": {"coordinates":[-8.4012622833,43.3724060059],"type":"Point"}
}