{
  "type": "Feature",
  "properties": {
    "addr:full":"Trva Llebre, 10 Cassa Selva Girona 17244",
    "addr:housenumber":"10",
    "addr:postcode":"17244",
    "addr:street":"Trva Llebre",
    "iso:country":"ES",
    "sg:address":"Trva Llebre, 10",
    "sg:city":"Cassa Selva",
    "sg:orig_category":"Soportes L\u00d3gicos, Programas Integradores De Aplicaciones (progiciels)",
    "sg:phone":"+34 972 46 30 25",
    "sg:postcode":"17244",
    "sg:province":"Girona",
    "sg:website":"www.subprof.com",
    "wof:name":"Subprof S.l.",
    "wof:placetype":"venue"
},
  "geometry": {"coordinates":[2.8820290565,41.8855857849],"type":"Point"}
}