{
  "type": "Feature",
  "properties": {
    "iso:country":"ES",
    "sg:address":"Del Desarrollo-pque Empresarial, S/n",
    "sg:city":"Jerez",
    "sg:orig_category":"Servicio De Salud",
    "sg:phone":"+34 956 18 30 00",
    "sg:postcode":"11407",
    "sg:province":"C\u00e1diz",
    "wof:name":"Aramburu Guzman S.l.",
    "wof:placetype":"venue"
},
  "geometry": {"coordinates":[-6.1367936134,36.7047843933],"type":"Point"}
}