{
  "type": "Feature",
  "properties": {
    "addr:full":"Carrer de Esquirol, 17 S. Feliu Codines Barcelona 08182",
    "addr:housenumber":"17",
    "addr:postcode":"08182",
    "addr:street":"Carrer De Esquirol;S. Feliu",
    "iso:country":"ES",
    "sg:address":"Carrer de Esquirol, 17",
    "sg:city":"S. Feliu Codines",
    "sg:orig_category":"Armaduras De Hormig\u00d3n",
    "sg:phone":"+34 938 66 20 24",
    "sg:postcode":"08182",
    "sg:province":"Barcelona",
    "wof:name":"Menfis 2000 S.l.",
    "wof:placetype":"venue"
},
  "geometry": {"coordinates":[2.1627700329,41.6903305054],"type":"Point"}
}