{
  "type": "Feature",
  "properties": {
    "addr:full":"Calle de Artabide, 26 Ondarroa Vizcaya 48700",
    "addr:housenumber":"26",
    "addr:postcode":"48700",
    "addr:street":"Calle De Artabide",
    "iso:country":"ES",
    "sg:address":"Calle de Artabide, 26",
    "sg:city":"Ondarroa",
    "sg:orig_category":"Peluqueros: De Se\u00d1oras",
    "sg:phone":"+34 946 83 34 07",
    "sg:postcode":"48700",
    "sg:province":"Vizcaya",
    "wof:name":"Badiola Badiola Maria Victoria",
    "wof:placetype":"venue"
},
  "geometry": {"coordinates":[-2.4235548973,43.3238830566],"type":"Point"}
}