{
  "type": "Feature",
  "properties": {
    "iso:country":"ES",
    "sg:address":"Calle de Jeronimo Hernandez, 4",
    "sg:city":"Sevilla",
    "sg:orig_category":"Confecci\u00d3n De Zapatos",
    "sg:phone":"+34 954 22 61 14",
    "sg:postcode":"41003",
    "sg:province":"Sevilla",
    "wof:name":"Compite S.l.",
    "wof:placetype":"venue"
},
  "geometry": {"coordinates":[-5.9919939041,37.3943557739],"type":"Point"}
}