{
  "type": "Feature",
  "properties": {
    "addr:full":"Av Generalitat De Catalunya, 45 Sort Lleida 25560",
    "addr:housenumber":"45",
    "addr:postcode":"25560",
    "addr:street":"Av Generalitat De Catalunya",
    "iso:country":"ES",
    "sg:address":"Av Generalitat De Catalunya, 45",
    "sg:city":"Sort",
    "sg:orig_category":"Restaurantes",
    "sg:phone":"+34 973 62 12 25",
    "sg:postcode":"25560",
    "sg:province":"Lleida",
    "wof:name":"Rodriguez Pelegrina Jose Antonio",
    "wof:placetype":"venue"
},
  "geometry": {"coordinates":[1.132349968,42.416809082],"type":"Point"}
}