{
  "type": "Feature",
  "properties": {
    "iso:country":"ES",
    "sg:address":"Carr Sant Domenec, 39",
    "sg:city":"Badalona",
    "sg:orig_category":"Asesor\u00cda Fiscal Y Jur\u00cddica",
    "sg:phone":"+34 934 64 62 10",
    "sg:postcode":"08911",
    "sg:province":"Barcelona",
    "sg:website":"www.lladogrup.com",
    "wof:name":"Llado Advocats Grup Consultor S.a.",
    "wof:placetype":"venue"
},
  "geometry": {"coordinates":[2.2525229454,41.4500694275],"type":"Point"}
}