{
  "type": "Feature",
  "properties": {
    "iso:country":"ES",
    "sg:address":"G.v. Manuel Lopez Carre\u00d1o, 11",
    "sg:city":"Bullas",
    "sg:orig_category":"Electrodom\u00c9sticos (al Por Menor)",
    "sg:phone":"+34 968 65 47 17",
    "sg:postcode":"30180",
    "sg:province":"Murcia",
    "wof:name":"Palacios Sanchez Sebastian",
    "wof:placetype":"venue"
},
  "geometry": {"coordinates":[-1.666893959,38.0503196716],"type":"Point"}
}