{
  "type": "Feature",
  "properties": {
    "iso:country":"ES",
    "sg:address":"Calle de Pozo Amarillo, 7",
    "sg:city":"Salamanca",
    "sg:orig_category":"Ingeniero",
    "sg:phone":"+34 923 27 11 52",
    "sg:postcode":"37001",
    "sg:province":"Salamanca",
    "wof:name":"Sanchez Patrocinio Alberto",
    "wof:placetype":"venue"
},
  "geometry": {"coordinates":[-5.6628260612,40.9652137756],"type":"Point"}
}