{
  "type": "Feature",
  "properties": {
    "iso:country":"ES",
    "sg:address":"Avda Juan Carlos I, 2",
    "sg:city":"Campo Abajo",
    "sg:orig_category":"Tapicer\u00cdas",
    "sg:phone":"+34 968 71 80 41",
    "sg:postcode":"30510",
    "sg:province":"Murcia",
    "sg:website":"www.dinatapizados.com",
    "wof:name":"Tapizados Dina S.l.",
    "wof:placetype":"venue"
},
  "geometry": {"coordinates":[-1.1149940491,38.6145591736],"type":"Point"}
}