{
  "type": "Feature",
  "properties": {
    "addr:full":"Calle de Porto Lagos, 5 Alcorcon Madrid 28924",
    "addr:housenumber":"5",
    "addr:postcode":"28924",
    "addr:street":"Calle De Porto Lagos",
    "iso:country":"ES",
    "sg:address":"Calle de Porto Lagos, 5",
    "sg:city":"Alcorcon",
    "sg:orig_category":"Venta, Instalaci\u00d3n De Calefacci\u00d3n",
    "sg:phone":"+34 916 11 81 66",
    "sg:postcode":"28924",
    "sg:province":"Madrid",
    "wof:name":"Instalaciones Penaza S.l.",
    "wof:placetype":"venue"
},
  "geometry": {"coordinates":[-3.8211519718,40.3499526978],"type":"Point"}
}