{
  "type": "Feature",
  "properties": {
    "addr:full":"Calle de Isaac Peral, 32 Dos Hermanas Sevilla 41700",
    "addr:housenumber":"32",
    "addr:postcode":"41700",
    "addr:street":"Calle De Isaac Peral",
    "iso:country":"ES",
    "sg:address":"Calle de Isaac Peral, 32",
    "sg:city":"Dos Hermanas",
    "sg:orig_category":"Carnicer\u00cdas, Carnicer\u00cdas",
    "sg:phone":"+34 955 66 92 81",
    "sg:postcode":"41700",
    "sg:province":"Sevilla",
    "wof:name":"Mo\u00f1ino Garcia Jose Manuel",
    "wof:placetype":"venue"
},
  "geometry": {"coordinates":[-5.9290828705,37.2867050171],"type":"Point"}
}