{
  "type": "Feature",
  "properties": {
    "addr:full":"Calle de Ancha, 15 Yepes Toledo 45313",
    "addr:housenumber":"15",
    "addr:postcode":"45313",
    "addr:street":"Calle De Ancha",
    "iso:country":"ES",
    "sg:address":"Calle de Ancha, 15",
    "sg:city":"Yepes",
    "sg:orig_category":"Art\u00cdculos De Decoraci\u00d3n",
    "sg:phone":"+34 925 15 44 41",
    "sg:postcode":"45313",
    "sg:province":"Toledo",
    "wof:name":"Ruiz Ugena Maria Del Sagrario",
    "wof:placetype":"venue"
},
  "geometry": {"coordinates":[-3.6245369911,39.900302887],"type":"Point"}
}