{
  "type": "Feature",
  "properties": {
    "addr:full":"Paradisia, 51 Entremontes Madrid 28230",
    "addr:housenumber":"51",
    "addr:postcode":"28230",
    "addr:street":"Paradisia",
    "iso:country":"ES",
    "sg:address":"Paradisia, 51",
    "sg:city":"Entremontes",
    "sg:orig_category":"Ense\u00d1anza: Profesiones Art\u00cdsticas",
    "sg:phone":"+34 916 31 73 55",
    "sg:postcode":"28230",
    "sg:province":"Madrid",
    "wof:name":"Dorda Pastrana Eduardo",
    "wof:placetype":"venue"
},
  "geometry": {"coordinates":[-3.7057700157,40.42029953],"type":"Point"}
}