{
  "type": "Feature",
  "properties": {
    "addr:full":"Carrer de Forn Nou Del, 28 Valls Tarragona 43800",
    "addr:housenumber":"28",
    "addr:postcode":"43800",
    "addr:street":"Carrer De Forn Nou Del",
    "iso:country":"ES",
    "sg:address":"Carrer de Forn Nou Del, 28",
    "sg:city":"Valls",
    "sg:orig_category":"Librer\u00cdas",
    "sg:phone":"+34 977 60 24 78",
    "sg:postcode":"43800",
    "sg:province":"Tarragona",
    "wof:name":"Plassa Benet Ramon",
    "wof:placetype":"venue"
},
  "geometry": {"coordinates":[1.2500280142,41.2847633362],"type":"Point"}
}