{
  "type": "Feature",
  "properties": {
    "iso:country":"ES",
    "sg:address":"Rua Varsovia (de), 4",
    "sg:city":"Santiago De Compostela",
    "sg:orig_category":"Administradores De Bienes Y Delegados De Comunidades De Propietarios",
    "sg:phone":"+34 981 57 61 04",
    "sg:postcode":"15707",
    "sg:province":"La Coru\u00f1a",
    "wof:name":"Guzman Crespo Antonio",
    "wof:placetype":"venue"
},
  "geometry": {"coordinates":[-8.5274839401,42.8833847046],"type":"Point"}
}