{
  "type": "Feature",
  "properties": {
    "iso:country":"ES",
    "sg:address":"Pla\u00c7 Forgas, 2",
    "sg:city":"Begur",
    "sg:orig_category":"Deportes N\u00c1uticos, Acu\u00c1ticos Y Subacu\u00c1ticos: Art\u00cdculos Y Equipo (al Por Menor)",
    "sg:phone":"+34 972 62 41 97",
    "sg:postcode":"17255",
    "sg:province":"Girona",
    "wof:name":"Palserveis 2000 S.l.l.",
    "wof:placetype":"venue"
},
  "geometry": {"coordinates":[3.2061150074,41.9516716003],"type":"Point"}
}