{
  "type": "Feature",
  "properties": {
    "addr:full":"Carrer de Pons I Gallarza, 26 Barcelona Barcelona 08030",
    "addr:housenumber":"26",
    "addr:postcode":"08030",
    "addr:street":"Carrer De Pons;Gallarza",
    "iso:country":"ES",
    "sg:address":"Carrer de Pons I Gallarza, 26",
    "sg:city":"Barcelona",
    "sg:orig_category":"Fabricaci\u00d3n, Venta De Cuadros, Accesorios Para Enmarcar",
    "sg:phone":"+34 933 46 67 07",
    "sg:postcode":"08030",
    "sg:province":"Barcelona",
    "wof:name":"Reluy  Maria Teresa",
    "wof:placetype":"venue"
},
  "geometry": {"coordinates":[2.1882069111,41.4355926514],"type":"Point"}
}