{
  "type": "Feature",
  "properties": {
    "addr:full":"Calle de Vidrio, 5 Castril Granada 18816",
    "addr:housenumber":"5",
    "addr:postcode":"18816",
    "addr:street":"Calle De Vidrio",
    "iso:country":"ES",
    "sg:address":"Calle de Vidrio, 5",
    "sg:city":"Castril",
    "sg:orig_category":"Armas Y Municiones (fabricaci\u00d3n, Al Por Mayor)",
    "sg:phone":"+34 958 72 02 01",
    "sg:postcode":"18816",
    "sg:province":"Granada",
    "wof:name":"Sanchez Perez Eva",
    "wof:placetype":"venue"
},
  "geometry": {"coordinates":[-2.7793879509,37.795753479],"type":"Point"}
}