{
  "type": "Feature",
  "properties": {
    "addr:full":"Ctra. S. Juan Puerto, Km. 0004,8 Moguer Huelva 21800",
    "addr:postcode":"21800",
    "addr:street":"Ctra. S. Juan Puerto Km. 0004,8",
    "iso:country":"ES",
    "sg:address":"Ctra. S. Juan Puerto, Km. 0004,8",
    "sg:city":"Moguer",
    "sg:orig_category":"Combustibles: Fuel",
    "sg:phone":"+34 959 37 23 95",
    "sg:postcode":"21800",
    "sg:province":"Huelva",
    "wof:name":"Estacion De Servicio Platero S. A.",
    "wof:placetype":"venue"
},
  "geometry": {"coordinates":[-6.8296589851,37.2830352783],"type":"Point"}
}