{
  "type": "Feature",
  "properties": {
    "addr:full":"Carr Jardi, 65 Vilanova I La Geltru Barcelona 08800",
    "addr:housenumber":"65",
    "addr:postcode":"08800",
    "addr:street":"Carr Jardi",
    "iso:country":"ES",
    "sg:address":"Carr Jardi, 65",
    "sg:city":"Vilanova I La Geltru",
    "sg:orig_category":"Mercer\u00cda, Lencer\u00cda (al Por Menor)",
    "sg:phone":"+34 938 14 18 90",
    "sg:postcode":"08800",
    "sg:province":"Barcelona",
    "wof:name":"Mu\u00f1oz Navarro Leonor",
    "wof:placetype":"venue"
},
  "geometry": {"coordinates":[1.7204699516,41.2238044739],"type":"Point"}
}