{
  "type": "Feature",
  "properties": {
    "iso:country":"ES",
    "sg:address":"Poli Pol.indust. Cami Dels Frares, S/n",
    "sg:city":"Lleida",
    "sg:orig_category":"Delegados, Agentes De Tr\u00c1nsito, Auxiliares De Transporte Internacional",
    "sg:phone":"+34 973 20 80 30",
    "sg:postcode":"25191",
    "sg:province":"Lleida",
    "wof:name":"Comercial Terrestre Maritima De Lerida-tarragona S. L.",
    "wof:placetype":"venue"
},
  "geometry": {"coordinates":[0.6831650138,41.5832138062],"type":"Point"}
}