{
  "type": "Feature",
  "properties": {
    "iso:country":"ES",
    "sg:address":"Calle de Tejar, 7",
    "sg:city":"Quismondo",
    "sg:orig_category":"Empresas De Carpinter\u00cda De Madera",
    "sg:phone":"+34 925 79 01 36",
    "sg:postcode":"45514",
    "sg:province":"Toledo",
    "wof:name":"Carpinteria Valverde Del Castillo S.l.",
    "wof:placetype":"venue"
},
  "geometry": {"coordinates":[-4.3221969604,40.1065864563],"type":"Point"}
}