{
  "type": "Feature",
  "properties": {
    "iso:country":"ES",
    "sg:address":"Calle de Huelva, 22",
    "sg:city":"Palmas De Gran Canaria",
    "sg:orig_category":"Impermeabilizantes",
    "sg:phone":"+34 928 33 23 55",
    "sg:postcode":"35016",
    "sg:province":"Las Palmas",
    "wof:name":"Delgado Perez Honorio",
    "wof:placetype":"venue"
},
  "geometry": {"coordinates":[-15.4343700409,28.0745296478],"type":"Point"}
}