{
  "type": "Feature",
  "properties": {
    "iso:country":"ES",
    "sg:address":"Calle de Torres (de Las), 21",
    "sg:city":"Cuenca",
    "sg:orig_category":"Farmacias",
    "sg:phone":"+34 969 23 45 29",
    "sg:postcode":"16001",
    "sg:province":"Cuenca",
    "wof:name":"Alfaro Gonzalez Maria Paz",
    "wof:placetype":"venue"
},
  "geometry": {"coordinates":[-2.1333050728,40.0725708008],"type":"Point"}
}