{
  "type": "Feature",
  "properties": {
    "iso:country":"ES",
    "sg:address":"Calle de Bernabe Cantos, 7",
    "sg:city":"Albacete",
    "sg:orig_category":"Laboratorios Y Cl\u00cdnicas Veterinarias",
    "sg:phone":"+34 967 66 58 35",
    "sg:postcode":"02003",
    "sg:province":"Albacete",
    "wof:name":"Cabot Lerma Antonio",
    "wof:placetype":"venue"
},
  "geometry": {"coordinates":[-1.8594279289,38.9905509949],"type":"Point"}
}