{
  "type": "Feature",
  "properties": {
    "addr:full":"Calle de Erreka Bazterrak, 1 Urbi Vizcaya 48970",
    "addr:housenumber":"1",
    "addr:postcode":"48970",
    "addr:street":"Calle De Erreka Bazterrak",
    "iso:country":"ES",
    "sg:address":"Calle de Erreka Bazterrak, 1",
    "sg:city":"Urbi",
    "sg:orig_category":"Fabricaci\u00d3n De Muebles De Cocina",
    "sg:phone":"+34 944 40 02 47",
    "sg:postcode":"48970",
    "sg:province":"Vizcaya",
    "wof:name":"Accesorios Y Herrajes Jiro S.l.",
    "wof:placetype":"venue"
},
  "geometry": {"coordinates":[-2.881862402,43.2284431458],"type":"Point"}
}