{
  "type": "Feature",
  "properties": {
    "addr:full":"Rbla Sant Jordi (de), 119 Ripollet Barcelona 08291",
    "addr:housenumber":"119",
    "addr:postcode":"08291",
    "addr:street":"Rbla Sant Jordi De",
    "iso:country":"ES",
    "sg:address":"Rbla Sant Jordi (de), 119",
    "sg:city":"Ripollet",
    "sg:orig_category":"Droguer\u00cdas (al Por Menor)",
    "sg:phone":"+34 936 91 17 49",
    "sg:postcode":"08291",
    "sg:province":"Barcelona",
    "wof:name":"Arenas Conejo Montserrat",
    "wof:placetype":"venue"
},
  "geometry": {"coordinates":[2.1674113274,41.4946632385],"type":"Point"}
}