{
  "type": "Feature",
  "properties": {
    "iso:country":"ES",
    "sg:address":"Calle de Pelicano, 3",
    "sg:city":"Madrid",
    "sg:orig_category":"Empresarios",
    "sg:phone":"+34 914 69 25 51",
    "sg:postcode":"28025",
    "sg:province":"Madrid",
    "wof:name":"Hervas Diaz Manuel",
    "wof:placetype":"venue"
},
  "geometry": {"coordinates":[-3.7253389359,40.3834190369],"type":"Point"}
}