{
  "type": "Feature",
  "properties": {
    "iso:country":"ES",
    "sg:address":"Mallorquines, 2",
    "sg:city":"Riudarenes",
    "sg:orig_category":"Fabrica De Charcuter\u00cda",
    "sg:phone":"+34 972 85 63 13",
    "sg:postcode":"17421",
    "sg:province":"Girona",
    "sg:website":"www.quintanaifills.com",
    "wof:name":"A. Quintana I Fills S.l.",
    "wof:placetype":"venue"
},
  "geometry": {"coordinates":[2.7326929569,41.8180885315],"type":"Point"}
}