{
  "type": "Feature",
  "properties": {
    "iso:country":"ES",
    "sg:address":"Calle de Doctor Galindez, 8",
    "sg:city":"Cuenca",
    "sg:orig_category":"Caf\u00c9s, Bares, Cervecer\u00cdas",
    "sg:phone":"+34 969 21 31 25",
    "sg:postcode":"16001",
    "sg:province":"Cuenca",
    "wof:name":"Ace\u00f1ero Morillas Felix",
    "wof:placetype":"venue"
},
  "geometry": {"coordinates":[-2.136392355,40.0749168396],"type":"Point"}
}