{
  "type": "Feature",
  "properties": {
    "addr:full":"Arry Infierno (del), S/n Ceuta Ceuta 51004",
    "addr:postcode":"51004",
    "addr:street":"S / N",
    "iso:country":"ES",
    "sg:address":"Arry Infierno (del), S/n",
    "sg:city":"Ceuta",
    "sg:orig_category":"Ense\u00d1anza Variada",
    "sg:phone":"+34 956 50 05 83",
    "sg:postcode":"51004",
    "sg:province":"Ceuta",
    "wof:name":"Merki  Martin",
    "wof:placetype":"venue"
},
  "geometry": {"coordinates":[-5.3568201065,35.9010009766],"type":"Point"}
}