{
  "type": "Feature",
  "properties": {
    "iso:country":"ES",
    "sg:address":"Calle de Regimiento Toledo, 15",
    "sg:city":"Tabara",
    "sg:orig_category":"Cooperativas Agr\u00cdcolas",
    "sg:phone":"+34 980 59 00 67",
    "sg:postcode":"49140",
    "sg:province":"Zamora",
    "wof:name":"Ende Sociedad Cooperativa Textil De Castilla Leon",
    "wof:placetype":"venue"
},
  "geometry": {"coordinates":[-5.9588150978,41.8262939453],"type":"Point"}
}