{
  "type": "Feature",
  "properties": {
    "addr:full":"Ctra Armilla Parque Comercial Alban, S/n Armilla Granada 18100",
    "addr:postcode":"18100",
    "addr:street":"Ctra Armilla Parque;S / N",
    "iso:country":"ES",
    "sg:address":"Ctra Armilla Parque Comercial Alban, S/n",
    "sg:city":"Armilla",
    "sg:orig_category":"Jardiner\u00cdas, Vegetales, Art\u00cdculos De Jardiner\u00cda (al Por Menor)",
    "sg:phone":"+34 958 13 61 86",
    "sg:postcode":"18100",
    "sg:province":"Granada",
    "sg:website":"www.aki.es",
    "wof:name":"Aki Bricolage Espa\u00d1a S.l.",
    "wof:placetype":"venue"
},
  "geometry": {"coordinates":[-3.6192471981,37.148475647],"type":"Point"}
}