{
  "type": "Feature",
  "properties": {
    "iso:country":"ES",
    "sg:address":"Zalain Auzoa, S/n",
    "sg:city":"Bera",
    "sg:orig_category":"Materias Pl\u00c1sticas: Art\u00cdculos Para La Industria",
    "sg:phone":"+34 948 63 14 55",
    "sg:postcode":"31780",
    "sg:province":"Navarra",
    "wof:name":"Burgui Aramburu Martin",
    "wof:placetype":"venue"
},
  "geometry": {"coordinates":[-1.7002589703,43.278465271],"type":"Point"}
}