{
  "type": "Feature",
  "properties": {
    "addr:full":"Avda San Miguel, 1 San Miguel De Meruelo Cantabria 39192",
    "addr:housenumber":"1",
    "addr:postcode":"39192",
    "addr:street":"Avda San Miguel",
    "iso:country":"ES",
    "sg:address":"Avda San Miguel, 1",
    "sg:city":"San Miguel De Meruelo",
    "sg:orig_category":"Carnicer\u00cdas, Carnicer\u00cdas",
    "sg:phone":"+34 942 63 70 93",
    "sg:postcode":"39192",
    "sg:province":"Cantabria",
    "wof:name":"Casanueva San Emeterio Andres",
    "wof:placetype":"venue"
},
  "geometry": {"coordinates":[-3.5726869106,43.4560775757],"type":"Point"}
}