{
  "type": "Feature",
  "properties": {
    "addr:full":"Calle de Morcillo, 1 Durcal Granada 18650",
    "addr:housenumber":"1",
    "addr:postcode":"18650",
    "addr:street":"Calle De Morcillo",
    "iso:country":"ES",
    "sg:address":"Calle de Morcillo, 1",
    "sg:city":"Durcal",
    "sg:orig_category":"Supermercados Y Hipermercados",
    "sg:phone":"+34 958 78 13 39",
    "sg:postcode":"18650",
    "sg:province":"Granada",
    "wof:name":"Gutierrez Padial Antonio Jesus",
    "wof:placetype":"venue"
},
  "geometry": {"coordinates":[-3.565928936,36.988658905],"type":"Point"}
}