{
  "type": "Feature",
  "properties": {
    "iso:country":"ES",
    "sg:address":"Ctra. B-granada, Km. 0276,5",
    "sg:city":"Cordoba",
    "sg:orig_category":"Distribuci\u00d3n De Petr\u00d3leo Y Derivados",
    "sg:phone":"+34 957 42 20 89",
    "sg:postcode":"14013",
    "sg:province":"C\u00f3rdoba",
    "wof:name":"Guadaloil S.l.",
    "wof:placetype":"venue"
},
  "geometry": {"coordinates":[-4.7774405479,37.8692169189],"type":"Point"}
}