{
  "type": "Feature",
  "properties": {
    "iso:country":"ES",
    "sg:address":"Calle de Costa Brava, 45",
    "sg:city":"Madrid",
    "sg:orig_category":"Impuestos, Tesoro P\u00dablico",
    "sg:phone":"+34 917 35 37 20",
    "sg:postcode":"28034",
    "sg:province":"Madrid",
    "wof:name":"Medina Davila-ponce De Leon Emilio",
    "wof:placetype":"venue"
},
  "geometry": {"coordinates":[-3.7113842964,40.4972763062],"type":"Point"}
}