{
  "type": "Feature",
  "properties": {
    "addr:full":"Calle de Navales, 24 Alcorcon Madrid 28925",
    "addr:housenumber":"24",
    "addr:postcode":"28925",
    "addr:street":"Calle De Navales",
    "iso:country":"ES",
    "sg:address":"Calle de Navales, 24",
    "sg:city":"Alcorcon",
    "sg:orig_category":"Mayoristas E Intermediarios En Alcoholes",
    "sg:phone":"+34 914 86 16 32",
    "sg:postcode":"28925",
    "sg:province":"Madrid",
    "wof:name":"Comercial Microdisc S.l.u.",
    "wof:placetype":"venue"
},
  "geometry": {"coordinates":[-3.8142340183,40.3379631042],"type":"Point"}
}