{
  "type": "Feature",
  "properties": {
    "iso:country":"ES",
    "sg:address":"Monasterio Aberin, 5",
    "sg:city":"Iru\u00f1a",
    "sg:orig_category":"Arquitectos",
    "sg:phone":"+34 948 17 28 04",
    "sg:postcode":"31011",
    "sg:province":"Navarra",
    "wof:name":"Salda\u00f1a Fernandez Ana",
    "wof:placetype":"venue"
},
  "geometry": {"coordinates":[-1.6572760344,42.8168029785],"type":"Point"}
}