{
  "type": "Feature",
  "properties": {
    "iso:country":"ES",
    "sg:address":"Calle de Convento, 4",
    "sg:city":"Puebla Montalban",
    "sg:orig_category":"Asociaciones Y Clubs Deportivos",
    "sg:phone":"+34 925 75 00 90",
    "sg:postcode":"45516",
    "sg:province":"Toledo",
    "wof:name":"Flores Ramirez Maria",
    "wof:placetype":"venue"
},
  "geometry": {"coordinates":[-4.3600420952,39.8674850464],"type":"Point"}
}