{
  "type": "Feature",
  "properties": {
    "iso:country":"ES",
    "sg:address":"Calle de Medio, 40",
    "sg:city":"Bretocino",
    "sg:orig_category":"Molduras, Junquillos, Listones Y Molduras Perforadas",
    "sg:phone":"+34 980 64 02 66",
    "sg:postcode":"49698",
    "sg:province":"Zamora",
    "wof:name":"Garcia Lopez Filomena",
    "wof:placetype":"venue"
},
  "geometry": {"coordinates":[-5.7530488968,41.8827705383],"type":"Point"}
}