{
  "type": "Feature",
  "properties": {
    "iso:country":"ES",
    "sg:address":"Rond Santo Domingo, 29",
    "sg:city":"Almagro",
    "sg:orig_category":"Relojer\u00cda (al Por Menor, Reparaci\u00d3n)",
    "sg:phone":"+34 926 88 26 50",
    "sg:postcode":"13270",
    "sg:province":"Ciudad Real",
    "wof:name":"Abellan Pedrero Beatriz",
    "wof:placetype":"venue"
},
  "geometry": {"coordinates":[-3.712682,38.89159],"type":"Point"}
}