{
  "type": "Feature",
  "properties": {
    "iso:country":"ES",
    "sg:address":"Rua Noria, 4",
    "sg:city":"Reboredo",
    "sg:orig_category":"Producci\u00d3n, Comercio De Cereales",
    "sg:phone":"+34 986 30 57 20",
    "sg:postcode":"36940",
    "sg:province":"Pontevedra",
    "wof:name":"Docagro C.b.",
    "wof:placetype":"venue"
},
  "geometry": {"coordinates":[-8.8184690475,42.2742500305],"type":"Point"}
}