{
  "type": "Feature",
  "properties": {
    "iso:country":"ES",
    "sg:address":"Amunaga Industrialdea, S/n",
    "sg:city":"Gernika",
    "sg:orig_category":"Empresarios",
    "sg:phone":"+34 946 25 09 92",
    "sg:postcode":"48300",
    "sg:province":"Vizcaya",
    "wof:name":"Zabala Calzada Francisco",
    "wof:placetype":"venue"
},
  "geometry": {"coordinates":[-2.6871831417,43.2972602844],"type":"Point"}
}