{
  "type": "Feature",
  "properties": {
    "iso:country":"ES",
    "sg:address":"Calle de Pozos, 26",
    "sg:city":"Santa Cruz De La Zarza",
    "sg:orig_category":"Electricidad, Electr\u00d3nica: Material Y Suministros (al Por Mayor)",
    "sg:phone":"+34 925 14 34 10",
    "sg:postcode":"45370",
    "sg:province":"Toledo",
    "wof:name":"Instalaciones Uninsa S.l.",
    "wof:placetype":"venue"
},
  "geometry": {"coordinates":[-3.1842160225,39.9783859253],"type":"Point"}
}