{
  "type": "Feature",
  "properties": {
    "iso:country":"ES",
    "sg:address":"Calle de Brujula, 5",
    "sg:city":"Torrejon Ardoz",
    "sg:orig_category":"Electrodom\u00c9sticos (al Por Menor)",
    "sg:phone":"+34 916 56 33 62",
    "sg:postcode":"28850",
    "sg:province":"Madrid",
    "wof:name":"Cafeteria Daos S.l.",
    "wof:placetype":"venue"
},
  "geometry": {"coordinates":[-3.4593391418,40.4491004944],"type":"Point"}
}