{
  "type": "Feature",
  "properties": {
    "addr:full":"Carrer de Sant Rafael, 20 Barcelona Barcelona 08001",
    "addr:housenumber":"20",
    "addr:postcode":"08001",
    "addr:street":"Carrer De Sant Rafael",
    "iso:country":"ES",
    "sg:address":"Carrer de Sant Rafael, 20",
    "sg:city":"Barcelona",
    "sg:orig_category":"Supermercados Y Hipermercados",
    "sg:phone":"+34 934 43 13 89",
    "sg:postcode":"08001",
    "sg:province":"Barcelona",
    "wof:name":"Javed  Iqbal",
    "wof:placetype":"venue"
},
  "geometry": {"coordinates":[2.1695849895,41.3793334961],"type":"Point"}
}