{
  "type": "Feature",
  "properties": {
    "iso:country":"ES",
    "sg:address":"Calle de Achuri, 15",
    "sg:city":"Madrid",
    "sg:orig_category":"Artes Gr\u00c1ficas, Artes Pl\u00c1sticas: Material Y Suministros (al Por Menor)",
    "sg:phone":"+34 914 07 34 99",
    "sg:postcode":"28017",
    "sg:province":"Madrid",
    "wof:name":"Yosan S.a.",
    "wof:placetype":"venue"
},
  "geometry": {"coordinates":[-3.6419730186,40.4285888672],"type":"Point"}
}