{
  "type": "Feature",
  "properties": {
    "iso:country":"ES",
    "sg:address":"Carrer de Riera Blanca, 156",
    "sg:city":"Hospitalet Llobregat",
    "sg:orig_category":"Fabricaci\u00d3n De Sobres, Bolsas Y Fundas",
    "sg:phone":"+34 934 21 13 97",
    "sg:postcode":"08903",
    "sg:province":"Barcelona",
    "wof:name":"Benedicto Font Teresa",
    "wof:placetype":"venue"
},
  "geometry": {"coordinates":[2.1294510365,41.3703346252],"type":"Point"}
}