{
  "type": "Feature",
  "properties": {
    "addr:full":"Ctra Villafames, Km. 0001,3 Pobla Tornesa Castell\u00f3n 12191",
    "addr:postcode":"12191",
    "addr:street":"Ctra Villafames Km. 0001,3",
    "iso:country":"ES",
    "sg:address":"Ctra Villafames, Km. 0001,3",
    "sg:city":"Pobla Tornesa",
    "sg:orig_category":"Cerrajer\u00cda, Ferrallista",
    "sg:phone":"+34 964 33 80 81",
    "sg:postcode":"12191",
    "sg:province":"Castell\u00f3n",
    "wof:name":"Eulogio Iba\u00f1ez S.l.",
    "wof:placetype":"venue"
},
  "geometry": {"coordinates":[-0.00097,40.1001205444],"type":"Point"}
}