{
  "type": "Feature",
  "properties": {
    "addr:full":"Calle de Archiduque Carlos, 1 Valencia Valencia 46018",
    "addr:housenumber":"1",
    "addr:postcode":"46018",
    "addr:street":"Calle De Archiduque Carlos",
    "iso:country":"ES",
    "sg:address":"Calle de Archiduque Carlos, 1",
    "sg:city":"Valencia",
    "sg:orig_category":"Loter\u00cda Y T\u00d3mbola",
    "sg:phone":"+34 963 82 42 52",
    "sg:postcode":"46018",
    "sg:province":"Valencia",
    "wof:name":"Saez Perez Maria De Los Angeles",
    "wof:placetype":"venue"
},
  "geometry": {"coordinates":[-0.392798394,39.4674186707],"type":"Point"}
}