{
  "type": "Feature",
  "properties": {
    "addr:full":"Pase Doctor Torres Villarroel, 13 Salamanca Salamanca 37006",
    "addr:housenumber":"13",
    "addr:postcode":"37006",
    "addr:street":"Doctor Torres Villarroel",
    "iso:country":"ES",
    "sg:address":"Pase Doctor Torres Villarroel, 13",
    "sg:city":"Salamanca",
    "sg:orig_category":"Asesor\u00cdas Y Estudios Financieros",
    "sg:phone":"+34 923 25 82 62",
    "sg:postcode":"37006",
    "sg:province":"Salamanca",
    "wof:name":"Moya Espejo Josefa",
    "wof:placetype":"venue"
},
  "geometry": {"coordinates":[-5.6635217667,40.9714775085],"type":"Point"}
}