{
  "type": "Feature",
  "properties": {
    "addr:full":"Calle de Becquer, 1 Cehegin Murcia 30430",
    "addr:housenumber":"1",
    "addr:postcode":"30430",
    "addr:street":"Calle De Becquer",
    "iso:country":"ES",
    "sg:address":"Calle de Becquer, 1",
    "sg:city":"Cehegin",
    "sg:orig_category":"Mec\u00c1nico Del Autom\u00d3vil",
    "sg:phone":"+34 968 74 01 79",
    "sg:postcode":"30430",
    "sg:province":"Murcia",
    "wof:name":"Talleres Amancio Gonzalez Duran S.l.",
    "wof:placetype":"venue"
},
  "geometry": {"coordinates":[-1.7954180241,38.0955162048],"type":"Point"}
}