{
  "type": "Feature",
  "properties": {
    "iso:country":"ES",
    "sg:address":"San Andres, 5",
    "sg:city":"Estella",
    "sg:orig_category":"Fotograf\u00cda Art\u00cdstica Y Retratos",
    "sg:phone":"+34 948 55 09 44",
    "sg:postcode":"31200",
    "sg:province":"Navarra",
    "wof:name":"Chasco Martinez Jesus Maria",
    "wof:placetype":"venue"
},
  "geometry": {"coordinates":[-2.0326290131,42.670791626],"type":"Point"}
}