{
  "type": "Feature",
  "properties": {
    "addr:full":"Calle de Virgen De Los Desamparados, 25 Valencia Valencia 46020",
    "addr:housenumber":"25",
    "addr:postcode":"46020",
    "addr:street":"Calle De Virgen De Los Desamparados",
    "iso:country":"ES",
    "sg:address":"Calle de Virgen De Los Desamparados, 25",
    "sg:city":"Valencia",
    "sg:orig_category":"Bisuter\u00cda, Joyer\u00cda, Relojer\u00cda (al Por Menor)",
    "sg:phone":"+34 963 60 38 00",
    "sg:postcode":"46020",
    "sg:province":"Valencia",
    "wof:name":"Tatay Herranz Ramon",
    "wof:placetype":"venue"
},
  "geometry": {"coordinates":[-0.3616657853,39.4860725403],"type":"Point"}
}