{
  "type": "Feature",
  "properties": {
    "addr:full":"Ctra. Valencia, S/n Mira Cuenca 16393",
    "addr:housenumber":"s / n",
    "addr:postcode":"16393",
    "addr:street":"Ctra. Valencia",
    "iso:country":"ES",
    "sg:address":"Ctra. Valencia, S/n",
    "sg:city":"Mira",
    "sg:orig_category":"Poller\u00cda Y Caza (al Por Menor)",
    "sg:phone":"+34 969 14 20 17",
    "sg:postcode":"16393",
    "sg:province":"Cuenca",
    "wof:name":"Llanos De La Cabezuela S.l.",
    "wof:placetype":"venue"
},
  "geometry": {"coordinates":[-1.4388190508,39.7186737061],"type":"Point"}
}