{
  "type": "Feature",
  "properties": {
    "iso:country":"ES",
    "sg:address":"Calle de America, S/n",
    "sg:city":"Alguazas",
    "sg:orig_category":"Ense\u00d1anza Secundaria: Colegios Y Escuelas Privadas",
    "sg:phone":"+34 968 62 23 05",
    "sg:postcode":"30560",
    "sg:province":"Murcia",
    "wof:name":"I.e.s Villa De Alguazas",
    "wof:placetype":"venue"
},
  "geometry": {"coordinates":[-1.2524391413,38.0552825928],"type":"Point"}
}