{
  "type": "Feature",
  "properties": {
    "addr:full":"San Cristobal, 20 Jaraiz Vera C\u00e1ceres 10400",
    "addr:housenumber":"20",
    "addr:postcode":"10400",
    "addr:street":"San Cristobal",
    "iso:country":"ES",
    "sg:address":"San Cristobal, 20",
    "sg:city":"Jaraiz Vera",
    "sg:orig_category":"Empresas De Carpinter\u00cda Met\u00c1lica",
    "sg:phone":"+34 927 46 11 23",
    "sg:postcode":"10400",
    "sg:province":"C\u00e1ceres",
    "wof:name":"Avila Nu\u00f1ez Jose",
    "wof:placetype":"venue"
},
  "geometry": {"coordinates":[-5.7516927719,40.0606231689],"type":"Point"}
}