{
  "type": "Feature",
  "properties": {
    "addr:full":"Calle de San Jose, 71 San Jose Rinconada Sevilla 41300",
    "addr:postcode":"41300",
    "addr:street":"Calle De San;71",
    "iso:country":"ES",
    "sg:address":"Calle de San Jose, 71",
    "sg:city":"San Jose Rinconada",
    "sg:orig_category":"Dietistas",
    "sg:phone":"+34 954 79 30 18",
    "sg:postcode":"41300",
    "sg:province":"Sevilla",
    "sg:website":"www.ynsadiet.com",
    "wof:name":"Ynsadiet S.a.",
    "wof:placetype":"venue"
},
  "geometry": {"coordinates":[-5.9437208176,37.48179245],"type":"Point"}
}