{
  "type": "Feature",
  "properties": {
    "addr:full":"Calle de Majuelo, 7 Monreal Campo Teruel 44300",
    "addr:housenumber":"7",
    "addr:postcode":"44300",
    "addr:street":"Calle De Majuelo",
    "iso:country":"ES",
    "sg:address":"Calle de Majuelo, 7",
    "sg:city":"Monreal Campo",
    "sg:orig_category":"Cooperativas Agr\u00cdcolas",
    "sg:phone":"+34 978 86 34 28",
    "sg:postcode":"44300",
    "sg:province":"Teruel",
    "wof:name":"Cereales Teruel Sociedad Cooperativa",
    "wof:placetype":"venue"
},
  "geometry": {"coordinates":[-1.3582240343,40.7870941162],"type":"Point"}
}