{
  "type": "Feature",
  "properties": {
    "iso:country":"ES",
    "sg:address":"Calle de Laguna, 54",
    "sg:city":"Madrid",
    "sg:orig_category":"Molduras, Junquillos, Listones Y Molduras Perforadas",
    "sg:phone":"+34 914 61 18 93",
    "sg:postcode":"28025",
    "sg:province":"Madrid",
    "wof:name":"Los Cu\u00f1ados C.b.",
    "wof:placetype":"venue"
},
  "geometry": {"coordinates":[-3.742007494,40.3887519836],"type":"Point"}
}