{
  "type": "Feature",
  "properties": {
    "iso:country":"ES",
    "sg:address":"Pase Sixto Celorrio, 8",
    "sg:city":"Calatayud",
    "sg:orig_category":"Contenedores (mercanc\u00cdas)",
    "sg:phone":"+34 976 88 61 92",
    "sg:postcode":"50300",
    "sg:province":"Zaragoza",
    "wof:name":"Transportes Jesus Mora Lopez E Hijo S.l.",
    "wof:placetype":"venue"
},
  "geometry": {"coordinates":[-1.6406979561,41.3473777771],"type":"Point"}
}