{
  "type": "Feature",
  "properties": {
    "addr:full":"Avda Manolete, 2 Cordoba C\u00f3rdoba 14005",
    "addr:housenumber":"2",
    "addr:postcode":"14005",
    "addr:street":"Avda Manolete;Co\u0301Rdoba",
    "iso:country":"ES",
    "sg:address":"Avda Manolete, 2",
    "sg:city":"Cordoba",
    "sg:orig_category":"Caf\u00c9s, Bares, Cervecer\u00cdas",
    "sg:phone":"+34 957 41 28 28",
    "sg:postcode":"14005",
    "sg:province":"C\u00f3rdoba",
    "wof:name":"Jurado Cabrera Antonio",
    "wof:placetype":"venue"
},
  "geometry": {"coordinates":[-4.7938799858,37.8808403015],"type":"Point"}
}