{
  "type": "Feature",
  "properties": {
    "iso:country":"ES",
    "sg:address":"Avda Juan Carlos I, S/n",
    "sg:city":"Cristianos",
    "sg:orig_category":"Florister\u00cdas",
    "sg:phone":"+34 922 75 18 51",
    "sg:postcode":"38650",
    "sg:province":"Santa Cruz De Tenerife",
    "wof:name":"Campos Oramas Carmen Gloria",
    "wof:placetype":"venue"
},
  "geometry": {"coordinates":[-16.7118148804,28.0564250946],"type":"Point"}
}