{
  "type": "Feature",
  "properties": {
    "iso:country":"ES",
    "sg:address":"Rua General Franco, 42",
    "sg:city":"Lalin",
    "sg:orig_category":"Cajas De Ahorro",
    "sg:phone":"+34 986 78 00 58",
    "sg:postcode":"36500",
    "sg:province":"Pontevedra",
    "wof:name":"Caixa De Aforros De Vigo Ourense E Pontevedra",
    "wof:placetype":"venue"
},
  "geometry": {"coordinates":[-8.1120891571,42.6614303589],"type":"Point"}
}