{
  "type": "Feature",
  "properties": {
    "addr:full":"Avda Jose Maria Moreno Galvan, 1 Puebla Cazalla Sevilla 41540",
    "addr:housenumber":"1",
    "addr:postcode":"41540",
    "addr:street":"Avda Jose Maria Moreno Galvan",
    "iso:country":"ES",
    "sg:address":"Avda Jose Maria Moreno Galvan, 1",
    "sg:city":"Puebla Cazalla",
    "sg:orig_category":"Sociedades, Compa\u00d1\u00cdas Aseguradoras",
    "sg:phone":"+34 955 84 37 51",
    "sg:postcode":"41540",
    "sg:province":"Sevilla",
    "wof:name":"Seguros Catalana Occidente S.a. De Seguros Y Reaseguros",
    "wof:placetype":"venue"
},
  "geometry": {"coordinates":[-5.3129739761,37.2229118347],"type":"Point"}
}