{
  "type": "Feature",
  "properties": {
    "addr:full":"Carrer de Pare Sallares, 6 Sabadell Barcelona 08201",
    "addr:housenumber":"6",
    "addr:postcode":"08201",
    "addr:street":"Carrer De Pare Sallares",
    "iso:country":"ES",
    "sg:address":"Carrer de Pare Sallares, 6",
    "sg:city":"Sabadell",
    "sg:orig_category":"M\u00c9dicos: Gastroenterolog\u00cda Y Hepatolog\u00cda (aparato Digestivo)",
    "sg:phone":"+34 937 26 19 37",
    "sg:postcode":"08201",
    "sg:province":"Barcelona",
    "wof:name":"Bedos Casals Gabriel",
    "wof:placetype":"venue"
},
  "geometry": {"coordinates":[2.105340004,41.5488395691],"type":"Point"}
}