{
  "type": "Feature",
  "properties": {
    "addr:full":"Calle de Doctor Gomez Ulla, 8 Almeria Almer\u00eda 04001",
    "addr:housenumber":"8",
    "addr:postcode":"04001",
    "addr:street":"Calle De Doctor Gomez Ulla",
    "iso:country":"ES",
    "sg:address":"Calle de Doctor Gomez Ulla, 8",
    "sg:city":"Almeria",
    "sg:orig_category":"Radiocomunicaciones, Telefon\u00cda M\u00d3vil, Radiomensajer\u00cda: Servicios, Comercializaci\u00d3n",
    "sg:phone":"+34 950 25 35 50",
    "sg:postcode":"04001",
    "sg:province":"Almer\u00eda",
    "sg:website":"www.telyco.es",
    "wof:name":"Teleinformatica Y Comunicaciones S.a.",
    "wof:placetype":"venue"
},
  "geometry": {"coordinates":[-2.4640109539,36.8389205933],"type":"Point"}
}