{
  "type": "Feature",
  "properties": {
    "addr:full":"Carr Carles Iii, 4 Cervera Lleida 25200",
    "addr:housenumber":"4",
    "addr:postcode":"25200",
    "addr:street":"Carr Carles Iii",
    "iso:country":"ES",
    "sg:address":"Carr Carles Iii, 4",
    "sg:city":"Cervera",
    "sg:orig_category":"Electricidad: Instaladores",
    "sg:phone":"+34 973 53 01 33",
    "sg:postcode":"25200",
    "sg:province":"Lleida",
    "wof:name":"Esteve Sole Francisco",
    "wof:placetype":"venue"
},
  "geometry": {"coordinates":[1.2714600563,41.6712989807],"type":"Point"}
}