{
  "type": "Feature",
  "properties": {
    "iso:country":"ES",
    "sg:address":"Calle de Antonio Sacramento (escultor), 7",
    "sg:city":"Valencia",
    "sg:orig_category":"Promotores Constructores",
    "sg:phone":"+34 963 73 18 16",
    "sg:postcode":"46013",
    "sg:province":"Valencia",
    "wof:name":"Promociones Y Construcciones Proluma S.l.",
    "wof:placetype":"venue"
},
  "geometry": {"coordinates":[-0.3588694036,39.4535369873],"type":"Point"}
}