{
  "type": "Feature",
  "properties": {
    "addr:full":"Calle de Portada, 10 Palma Rio C\u00f3rdoba 14700",
    "addr:housenumber":"10",
    "addr:postcode":"14700",
    "addr:street":"Calle De Portada;Rio Co\u0301Rdoba",
    "iso:country":"ES",
    "sg:address":"Calle de Portada, 10",
    "sg:city":"Palma Rio",
    "sg:orig_category":"Caf\u00c9s, Bares, Cervecer\u00cdas",
    "sg:phone":"+34 957 64 43 01",
    "sg:postcode":"14700",
    "sg:province":"C\u00f3rdoba",
    "wof:name":"Viajes Cercosta S.l.",
    "wof:placetype":"venue"
},
  "geometry": {"coordinates":[-5.2822041512,37.6965560913],"type":"Point"}
}