{
  "type": "Feature",
  "properties": {
    "iso:country":"ES",
    "sg:address":"Calle de Canarias, 12",
    "sg:city":"Ajalvir",
    "sg:orig_category":"Rectificaci\u00d3n, Mecanizado, Fresado",
    "sg:phone":"+34 918 84 43 21",
    "sg:postcode":"28864",
    "sg:province":"Madrid",
    "wof:name":"Indechapa S.a.l.",
    "wof:placetype":"venue"
},
  "geometry": {"coordinates":[-3.4903638363,40.5309371948],"type":"Point"}
}