{
  "type": "Feature",
  "properties": {
    "iso:country":"ES",
    "sg:address":"Calle de Lope De Vega, 5",
    "sg:city":"Oviedo",
    "sg:orig_category":"Ense\u00d1anza Variada",
    "sg:phone":"+34 985 20 23 69",
    "sg:postcode":"33010",
    "sg:province":"Asturias",
    "wof:name":"Diaz Garcia Antonio",
    "wof:placetype":"venue"
},
  "geometry": {"coordinates":[-5.8379120827,43.3631134033],"type":"Point"}
}