{
  "type": "Feature",
  "properties": {
    "iso:country":"ES",
    "sg:address":"Calle de Principe De Vergara, 94",
    "sg:city":"Madrid",
    "sg:orig_category":"Doctores En Medicina",
    "sg:phone":"+34 915 62 18 40",
    "sg:postcode":"28006",
    "sg:province":"Madrid",
    "wof:name":"Diaz Gomez Manuel",
    "wof:placetype":"venue"
},
  "geometry": {"coordinates":[-3.6789770126,40.4369316101],"type":"Point"}
}