{
  "type": "Feature",
  "properties": {
    "addr:full":"Avda Andalucia, 85 Ayamonte Huelva 21400",
    "addr:housenumber":"85",
    "addr:postcode":"21400",
    "addr:street":"Avda Andalucia",
    "iso:country":"ES",
    "sg:address":"Avda Andalucia, 85",
    "sg:city":"Ayamonte",
    "sg:orig_category":"Alimentaci\u00d3n General (al Por Menor)",
    "sg:phone":"+34 959 32 12 17",
    "sg:postcode":"21400",
    "sg:province":"Huelva",
    "wof:name":"Lopez Ortiz Antonio",
    "wof:placetype":"venue"
},
  "geometry": {"coordinates":[-7.4004788399,37.2147102356],"type":"Point"}
}