{
  "type": "Feature",
  "properties": {
    "iso:country":"ES",
    "sg:address":"Avda Florida, 149",
    "sg:city":"Vigo",
    "sg:orig_category":"Ense\u00d1anza Variada",
    "sg:phone":"+34 986 20 59 87",
    "sg:postcode":"36210",
    "sg:province":"Pontevedra",
    "wof:name":"Valverde Villar Maria Belen",
    "wof:placetype":"venue"
},
  "geometry": {"coordinates":[-8.7440252304,42.2128334045],"type":"Point"}
}