{
  "type": "Feature",
  "properties": {
    "addr:full":"Carr Major Sant Domenec, 27 Villarreal Castell\u00f3n 12540",
    "addr:housenumber":"27",
    "addr:postcode":"12540",
    "addr:street":"Carr Major Sant Domenec",
    "iso:country":"ES",
    "sg:address":"Carr Major Sant Domenec, 27",
    "sg:city":"Villarreal",
    "sg:orig_category":"Construcci\u00d3n De Edificios Residenciales Y No Residenciales",
    "sg:phone":"+34 964 52 17 36",
    "sg:postcode":"12540",
    "sg:province":"Castell\u00f3n",
    "wof:name":"Constructora Broch Iii S.l.",
    "wof:placetype":"venue"
},
  "geometry": {"coordinates":[-0.102173999,39.9361763],"type":"Point"}
}