{
  "type": "Feature",
  "properties": {
    "iso:country":"ES",
    "sg:address":"Plaz Concepcion Garcia Redondo, 2",
    "sg:city":"Ronda",
    "sg:orig_category":"Librer\u00cdas",
    "sg:phone":"+34 952 87 85 62",
    "sg:postcode":"29400",
    "sg:province":"M\u00e1laga",
    "wof:name":"Orozco Moreno Isabel",
    "wof:placetype":"venue"
},
  "geometry": {"coordinates":[-5.1651239395,36.7464065552],"type":"Point"}
}