{
  "type": "Feature",
  "properties": {
    "addr:full":"Carrer de Cedre, 30 Viladecans Barcelona 08840",
    "addr:housenumber":"30",
    "addr:postcode":"08840",
    "addr:street":"Carrer De Cedre",
    "iso:country":"ES",
    "sg:address":"Carrer de Cedre, 30",
    "sg:city":"Viladecans",
    "sg:orig_category":"Confecci\u00d3n De Zapatos",
    "sg:phone":"+34 936 37 93 44",
    "sg:postcode":"08840",
    "sg:province":"Barcelona",
    "wof:name":"Mudarra Moya Emilio",
    "wof:placetype":"venue"
},
  "geometry": {"coordinates":[2.0085520744,41.3233451843],"type":"Point"}
}