{
  "type": "Feature",
  "properties": {
    "addr:full":"Calle de Ramon Y Cajal, 31 Lantejuela Sevilla 41630",
    "addr:housenumber":"31",
    "addr:postcode":"41630",
    "addr:street":"Calle De Ramon Y Cajal",
    "iso:country":"ES",
    "sg:address":"Calle de Ramon Y Cajal, 31",
    "sg:city":"Lantejuela",
    "sg:orig_category":"Empresas De Hormig\u00d3n, Hormig\u00d3n Armado Y Pretensado",
    "sg:phone":"+34 954 82 85 99",
    "sg:postcode":"41630",
    "sg:province":"Sevilla",
    "wof:name":"Garrido Martin Jesus Rafael",
    "wof:placetype":"venue"
},
  "geometry": {"coordinates":[-5.2206377983,37.3533668518],"type":"Point"}
}