{
  "type": "Feature",
  "properties": {
    "addr:full":"Calle de Puerto Del Escudo, 4 Sevilla Sevilla 41006",
    "addr:housenumber":"4",
    "addr:postcode":"41006",
    "addr:street":"Calle De Puerto Del Escudo",
    "iso:country":"ES",
    "sg:address":"Calle de Puerto Del Escudo, 4",
    "sg:city":"Sevilla",
    "sg:orig_category":"Bancos",
    "sg:phone":"+34 954 64 69 50",
    "sg:postcode":"41006",
    "sg:province":"Sevilla",
    "wof:name":"Banco De Andalucia",
    "wof:placetype":"venue"
},
  "geometry": {"coordinates":[-5.9539852142,37.3756141663],"type":"Point"}
}