{
  "type": "Feature",
  "properties": {
    "iso:country":"ES",
    "sg:address":"Av Angels, 12",
    "sg:city":"Miami Platja",
    "sg:orig_category":"Reposter\u00cdas",
    "sg:phone":"+34 977 81 12 05",
    "sg:postcode":"43892",
    "sg:province":"Tarragona",
    "wof:name":"Escote Mute Gloria",
    "wof:placetype":"venue"
},
  "geometry": {"coordinates":[0.9359700084,41.0051307678],"type":"Point"}
}