{
  "type": "Feature",
  "properties": {
    "addr:full":"Plaz Felipe Alvarez Gadea (de), 1 Alcobendas Madrid 28100",
    "addr:postcode":"28100",
    "addr:street":"Plaz;Alvarez Gadea De 1",
    "iso:country":"ES",
    "sg:address":"Plaz Felipe Alvarez Gadea (de), 1",
    "sg:city":"Alcobendas",
    "sg:orig_category":"Guarder\u00cdas",
    "sg:phone":"+34 916 53 57 21",
    "sg:postcode":"28100",
    "sg:province":"Madrid",
    "wof:name":"Parroquia San Pedro Apostol",
    "wof:placetype":"venue"
},
  "geometry": {"coordinates":[-3.6325139999,40.5411376953],"type":"Point"}
}