{
  "type": "Feature",
  "properties": {
    "iso:country":"ES",
    "sg:address":"Calle de Doctor Jimenez Encina, 3",
    "sg:city":"Torremolinos",
    "sg:orig_category":"Transportes Urbanos Y Regionales Para Personas",
    "sg:phone":"+34 952 38 81 64",
    "sg:postcode":"29620",
    "sg:province":"M\u00e1laga",
    "wof:name":"Empresa Municipal De Transportes De Madrid S. A.",
    "wof:placetype":"venue"
},
  "geometry": {"coordinates":[-4.5034952164,36.6216812134],"type":"Point"}
}