{
  "type": "Feature",
  "properties": {
    "iso:country":"ES",
    "sg:address":"Calle de Gran Via, 59",
    "sg:city":"Madrid",
    "sg:orig_category":"Albergues",
    "sg:phone":"+34 915 47 56 13",
    "sg:postcode":"28013",
    "sg:province":"Madrid",
    "sg:website":"www.flamencoexport.com",
    "wof:name":"Flamenco Export S.l.",
    "wof:placetype":"venue"
},
  "geometry": {"coordinates":[-3.7090520859,40.4220581055],"type":"Point"}
}