{
  "type": "Feature",
  "properties": {
    "addr:full":"Calle de Doctor Bruno Alegria, 6 Santurtzi Vizcaya 48980",
    "addr:housenumber":"6",
    "addr:postcode":"48980",
    "addr:street":"Calle De Doctor Bruno Alegria",
    "iso:country":"ES",
    "sg:address":"Calle de Doctor Bruno Alegria, 6",
    "sg:city":"Santurtzi",
    "sg:orig_category":"Agencias Y Asesores De Publicidad",
    "sg:phone":"+34 944 96 63 97",
    "sg:postcode":"48980",
    "sg:province":"Vizcaya",
    "wof:name":"Nefher-medic,s.l",
    "wof:placetype":"venue"
},
  "geometry": {"coordinates":[-3.039305687,43.3303565979],"type":"Point"}
}