{
  "type": "Feature",
  "properties": {
    "addr:full":"Acacia, 34 Elviria M\u00e1laga 29604",
    "addr:housenumber":"34",
    "addr:postcode":"29604",
    "addr:street":"Acacia;Ma\u0301Laga",
    "iso:country":"ES",
    "sg:address":"Acacia, 34",
    "sg:city":"Elviria",
    "sg:orig_category":"Agencias Y Agentes Comerciales, Representantes",
    "sg:phone":"+34 952 83 50 76",
    "sg:postcode":"29604",
    "sg:province":"M\u00e1laga",
    "wof:name":"Grundell  Lars",
    "wof:placetype":"venue"
},
  "geometry": {"coordinates":[-4.7839570045,36.4972267151],"type":"Point"}
}