{
  "type": "Feature",
  "properties": {
    "iso:country":"ES",
    "sg:address":"Calle de Asistente Arjona, 19",
    "sg:city":"Osuna",
    "sg:orig_category":"Zapatos (al Por Menor)",
    "sg:phone":"+34 954 81 06 90",
    "sg:postcode":"41640",
    "sg:province":"Sevilla",
    "wof:name":"Selva Pi\u00f1ar Concepcion",
    "wof:placetype":"venue"
},
  "geometry": {"coordinates":[-5.1023488045,37.2366027832],"type":"Point"}
}