{
  "type": "Feature",
  "properties": {
    "addr:full":"Mayor, 1 Mohernando Guadalajara 19291",
    "addr:housenumber":"1",
    "addr:postcode":"19291",
    "addr:street":"Mayor",
    "iso:country":"ES",
    "sg:address":"Mayor, 1",
    "sg:city":"Mohernando",
    "sg:orig_category":"Producci\u00d3n, Venta De Productos De Agricultura Biol\u00d3gica",
    "sg:phone":"+34 949 85 00 12",
    "sg:postcode":"19291",
    "sg:province":"Guadalajara",
    "wof:name":"Explotaciones Agrarias Montero S.l.",
    "wof:placetype":"venue"
},
  "geometry": {"coordinates":[-3.1760630608,40.8039588928],"type":"Point"}
}