{
  "type": "Feature",
  "properties": {
    "addr:full":"Carr Pont De La Barca, 1 Girona Girona 17007",
    "addr:housenumber":"1",
    "addr:postcode":"17007",
    "addr:street":"Carr Pont De La Barca",
    "iso:country":"ES",
    "sg:address":"Carr Pont De La Barca, 1",
    "sg:city":"Girona",
    "sg:classifiers":[
        {
            "category":"Casinos & Gambling",
            "type":"Entertainment"
        }
    ],
    "sg:phone":"+34 972 21 14 05",
    "sg:postcode":"17007",
    "sg:province":"Girona",
    "sg:tags":[
        "locale",
        "de",
        "juego"
    ],
    "wof:name":"Rank Catalunya S.a.",
    "wof:placetype":"venue"
},
  "geometry": {"coordinates":[2.8187479973,41.9907035828],"type":"Point"}
}