{
  "type": "Feature",
  "properties": {
    "addr:full":"Carr Josep Pers I Ricart, 8 Vilanova I La Geltru Barcelona 08800",
    "addr:housenumber":"8",
    "addr:postcode":"08800",
    "addr:street":"Carr Josep Pers I Ricart",
    "iso:country":"ES",
    "sg:address":"Carr Josep Pers I Ricart, 8",
    "sg:city":"Vilanova I La Geltru",
    "sg:orig_category":"Promotores Constructores",
    "sg:phone":"+34 938 16 50 73",
    "sg:postcode":"08800",
    "sg:province":"Barcelona",
    "wof:name":"Miguel Perona S L",
    "wof:placetype":"venue"
},
  "geometry": {"coordinates":[1.7304580212,41.2246856689],"type":"Point"}
}