{
  "type": "Feature",
  "properties": {
    "addr:full":"Plaz Ayuntamiento, 1 Cebolla Toledo 45550",
    "addr:housenumber":"1",
    "addr:postcode":"45550",
    "addr:street":"Ayuntamiento",
    "iso:country":"ES",
    "sg:address":"Plaz Ayuntamiento, 1",
    "sg:city":"Cebolla",
    "sg:orig_category":"Servicios Diversos",
    "sg:phone":"+34 925 86 64 78",
    "sg:postcode":"45550",
    "sg:province":"Toledo",
    "wof:name":"Hogar Del Pensionista Nuestra Se\u00f1ora De La Antigua",
    "wof:placetype":"venue"
},
  "geometry": {"coordinates":[-4.5676598549,39.9334411621],"type":"Point"}
}