{
  "type": "Feature",
  "properties": {
    "iso:country":"ES",
    "sg:address":"Calle de Calidon, 7",
    "sg:city":"Madrid",
    "sg:orig_category":"Asesor\u00cda Sobre Comunicaci\u00d3n De Empresas",
    "sg:phone":"+34 915 15 00 11",
    "sg:postcode":"28043",
    "sg:province":"Madrid",
    "wof:name":"Eurogest Y Asociados S.l.",
    "wof:placetype":"venue"
},
  "geometry": {"coordinates":[-3.6512255669,40.4483642578],"type":"Point"}
}