{
  "type": "Feature",
  "properties": {
    "iso:country":"ES",
    "sg:address":"Calle de Abajo (de), 26",
    "sg:city":"Albares",
    "sg:orig_category":"Promotores Constructores",
    "sg:phone":"+34 949 38 06 37",
    "sg:postcode":"19112",
    "sg:province":"Guadalajara",
    "wof:name":"Inversiones Castilla La Mancha S.a.",
    "wof:placetype":"venue"
},
  "geometry": {"coordinates":[-3.0122609138,40.3075141907],"type":"Point"}
}