{
  "type": "Feature",
  "properties": {
    "iso:country":"ES",
    "sg:address":"Don Jose Mora, 17",
    "sg:city":"Miguelturra",
    "sg:orig_category":"Asesor\u00cda Fiscal Y Jur\u00cddica",
    "sg:phone":"+34 926 24 09 38",
    "sg:postcode":"13170",
    "sg:province":"Ciudad Real",
    "wof:name":"Rala Contabilidad S.l.",
    "wof:placetype":"venue"
},
  "geometry": {"coordinates":[-3.8881509304,38.966583252],"type":"Point"}
}