{
  "type": "Feature",
  "properties": {
    "addr:full":"Pase Duque De Mandas, 8 Donostia-san Sebastian Guip\u00f9zcoa 20012",
    "addr:housenumber":"8",
    "addr:postcode":"20012",
    "addr:street":"Mandas",
    "iso:country":"ES",
    "sg:address":"Pase Duque De Mandas, 8",
    "sg:city":"Donostia-san Sebastian",
    "sg:orig_category":"Agencias De Viajes",
    "sg:phone":"+34 943 32 09 19",
    "sg:postcode":"20012",
    "sg:province":"Guip\u00f9zcoa",
    "wof:name":"Savia Amadeus S.a.",
    "wof:placetype":"venue"
},
  "geometry": {"coordinates":[-1.9741970301,43.3206367493],"type":"Point"}
}