{
  "type": "Feature",
  "properties": {
    "addr:full":"Rbla Onze De Setembre, 7 Barcelona Barcelona 08030",
    "addr:housenumber":"7",
    "addr:postcode":"08030",
    "addr:street":"Rbla Onze De Setembre",
    "iso:country":"ES",
    "sg:address":"Rbla Onze De Setembre, 7",
    "sg:city":"Barcelona",
    "sg:orig_category":"Venta, Montaje De Neum\u00c1ticos",
    "sg:phone":"+34 933 46 44 10",
    "sg:postcode":"08030",
    "sg:province":"Barcelona",
    "wof:name":"Segundo Payan Ramon",
    "wof:placetype":"venue"
},
  "geometry": {"coordinates":[2.1947588921,41.4297828674],"type":"Point"}
}