{
  "type": "Feature",
  "properties": {
    "addr:full":"Curros Enriquez(o Graxal), 25 O Temple La Coru\u00f1a 15679",
    "addr:housenumber":"25 o",
    "addr:postcode":"15679",
    "addr:street":"Curros Enriquez O Graxal;La Corun\u0303A",
    "iso:country":"ES",
    "sg:address":"Curros Enriquez(o Graxal), 25",
    "sg:city":"O Temple",
    "sg:orig_category":"Muebles, Minoristas",
    "sg:phone":"+34 981 63 56 16",
    "sg:postcode":"15679",
    "sg:province":"La Coru\u00f1a",
    "wof:name":"Industrial Del Mueble Mubasa S.l.",
    "wof:placetype":"venue"
},
  "geometry": {"coordinates":[-8.3581409454,43.3161239624],"type":"Point"}
}