{
  "type": "Feature",
  "properties": {
    "iso:country":"ES",
    "sg:address":"Calle de Siroco Del, 10",
    "sg:city":"Arroyo De La Miel-benalmadena Costa",
    "sg:orig_category":"Asesor\u00cda Sobre Comunicaci\u00d3n De Empresas",
    "sg:phone":"+34 952 56 24 19",
    "sg:postcode":"29630",
    "sg:province":"M\u00e1laga",
    "wof:name":"Gonzalez Sanchez Francisco",
    "wof:placetype":"venue"
},
  "geometry": {"coordinates":[-4.5382881165,36.581993103],"type":"Point"}
}