{
  "type": "Feature",
  "properties": {
    "iso:country":"ES",
    "sg:address":"Ptge Xavier Montsalvatge, S/n",
    "sg:city":"Tarragona",
    "sg:orig_category":"Guarder\u00cdas",
    "sg:phone":"+34 977 24 85 92",
    "sg:postcode":"43005",
    "sg:province":"Tarragona",
    "wof:name":"Fundacio Pia Autonoma Institut Pere Tarr",
    "wof:placetype":"venue"
},
  "geometry": {"coordinates":[1.240825057,41.1113586426],"type":"Point"}
}