{
  "type": "Feature",
  "properties": {
    "iso:country":"ES",
    "sg:address":"Avda Jose Rodriguez Ruano, 23",
    "sg:city":"Almansa",
    "sg:orig_category":"Inform\u00c1tica, Ofim\u00c1tica (estudios, Asesor\u00cda, Ingenier\u00cda, Formaci\u00d3n)",
    "sg:phone":"+34 967 34 58 79",
    "sg:postcode":"02640",
    "sg:province":"Albacete",
    "wof:name":"Indepro Audiovisual S.l.",
    "wof:placetype":"venue"
},
  "geometry": {"coordinates":[-1.0924229622,38.8664932251],"type":"Point"}
}