{
  "type": "Feature",
  "properties": {
    "addr:full":"Carrer de F. Pi I Margall, 101 Gava Barcelona 08850",
    "addr:housenumber":"101",
    "addr:postcode":"08850",
    "addr:street":"Carrer De F. Pi;Margall",
    "iso:country":"ES",
    "sg:address":"Carrer de F. Pi I Margall, 101",
    "sg:city":"Gava",
    "sg:orig_category":"Reposter\u00cdas",
    "sg:phone":"+34 936 38 82 78",
    "sg:postcode":"08850",
    "sg:province":"Barcelona",
    "wof:name":"La Deliciosa Del Llobregat Sl",
    "wof:placetype":"venue"
},
  "geometry": {"coordinates":[1.9996210337,41.2960395813],"type":"Point"}
}