{
  "type": "Feature",
  "properties": {
    "addr:full":"Plaz Constitucion, 12 Villacarrillo Ja\u00e9n 23300",
    "addr:postcode":"23300",
    "addr:street":"Constitucion 12;Jae\u0301N",
    "iso:country":"ES",
    "sg:address":"Plaz Constitucion, 12",
    "sg:city":"Villacarrillo",
    "sg:orig_category":"Centros Empresariales",
    "sg:phone":"+34 953 44 11 47",
    "sg:postcode":"23300",
    "sg:province":"Ja\u00e9n",
    "wof:name":"Comunidad De Propietarios Plaza De La Constitucion 12",
    "wof:placetype":"venue"
},
  "geometry": {"coordinates":[-3.0877261162,38.115322113],"type":"Point"}
}