{
  "type": "Feature",
  "properties": {
    "iso:country":"ES",
    "sg:address":"Calle de Alondra, 52",
    "sg:city":"Madrid",
    "sg:orig_category":"Electrodom\u00c9sticos (fabricaci\u00d3n, Al Por Mayor)",
    "sg:phone":"+34 914 66 55 15",
    "sg:postcode":"28025",
    "sg:province":"Madrid",
    "wof:name":"Tv Casado S.l.",
    "wof:placetype":"venue"
},
  "geometry": {"coordinates":[-3.7394089699,40.3881797791],"type":"Point"}
}