{
  "type": "Feature",
  "properties": {
    "iso:country":"ES",
    "sg:address":"Avda Concordia (de La), S/n",
    "sg:city":"Pozo Ca\u00e7ada",
    "sg:orig_category":"Serrer\u00cdas De Madera",
    "sg:phone":"+34 967 25 00 41",
    "sg:postcode":"02510",
    "sg:province":"Albacete",
    "wof:name":"Tecnologicas Del Medio Ambiente S.a.",
    "wof:placetype":"venue"
},
  "geometry": {"coordinates":[-1.7302010059,38.8003730774],"type":"Point"}
}