{
  "type": "Feature",
  "properties": {
    "iso:country":"ES",
    "sg:address":"Calle de Cordoba, 4",
    "sg:city":"Rute",
    "sg:orig_category":"Servicios Gsm",
    "sg:phone":"+34 957 53 25 07",
    "sg:postcode":"14960",
    "sg:province":"C\u00f3rdoba",
    "sg:website":"www.maximovilplus.com",
    "wof:name":"Maximovil Plus S.l.",
    "wof:placetype":"venue"
},
  "geometry": {"coordinates":[-4.3746390343,37.3298912048],"type":"Point"}
}