{
  "type": "Feature",
  "properties": {
    "iso:country":"ES",
    "sg:address":"Carr Ciutat De Valencia, 1",
    "sg:city":"Cullera",
    "sg:orig_category":"Molduras, Junquillos, Listones Y Molduras Perforadas",
    "sg:phone":"+34 961 73 23 10",
    "sg:postcode":"46400",
    "sg:province":"Valencia",
    "wof:name":"Alvarez Martinez Jesus",
    "wof:placetype":"venue"
},
  "geometry": {"coordinates":[-0.2416996062,39.1648788452],"type":"Point"}
}