{
  "type": "Feature",
  "properties": {
    "iso:country":"ES",
    "sg:address":"Av. Valladolid, 47",
    "sg:city":"Madrid",
    "sg:orig_category":"Asesor\u00cda, Estudio Y Control Medioambiental",
    "sg:phone":"+34 915 47 50 71",
    "sg:postcode":"28008",
    "sg:province":"Madrid",
    "wof:name":"Fonotest S.l.",
    "wof:placetype":"venue"
},
  "geometry": {"coordinates":[-3.7312049866,40.4295310974],"type":"Point"}
}