{
  "type": "Feature",
  "properties": {
    "addr:full":"Zona Ind. Ergoien, 635 Urnieta Guip\u00f9zcoa 20130",
    "addr:housenumber":"635",
    "addr:postcode":"20130",
    "addr:street":"Ergoien;Guipu\u0300Zcoa",
    "iso:country":"ES",
    "sg:address":"Zona Ind. Ergoien, 635",
    "sg:city":"Urnieta",
    "sg:orig_category":"Negocio De Materiales De Construcci\u00d3n",
    "sg:phone":"+34 943 33 66 15",
    "sg:postcode":"20130",
    "sg:province":"Guip\u00f9zcoa",
    "wof:name":"S.zaldua Y Cia S.l.",
    "wof:placetype":"venue"
},
  "geometry": {"coordinates":[-1.992429018,43.248588562],"type":"Point"}
}