{
  "type": "Feature",
  "properties": {
    "addr:full":"Calle de Elcano, 25 San Vicente De Barakaldo Vizcaya 48901",
    "addr:housenumber":"25",
    "addr:postcode":"48901",
    "addr:street":"Calle De Elcano",
    "iso:country":"ES",
    "sg:address":"Calle de Elcano, 25",
    "sg:city":"San Vicente De Barakaldo",
    "sg:orig_category":"Agentes Generales De Seguros",
    "sg:phone":"+34 944 37 38 23",
    "sg:postcode":"48901",
    "sg:province":"Vizcaya",
    "wof:name":"Garcia Ribera Roberto",
    "wof:placetype":"venue"
},
  "geometry": {"coordinates":[-2.9899230003,43.2958297729],"type":"Point"}
}