{
  "type": "Feature",
  "properties": {
    "iso:country":"ES",
    "sg:address":"Calle de Pe\u00d1a Gorbea, 26",
    "sg:city":"Madrid",
    "sg:orig_category":"Arreglo, Reparaci\u00d3n, Piezas Sueltas De Televisi\u00d3n, V\u00cddeo, Hi",
    "sg:phone":"+34 914 78 73 36",
    "sg:postcode":"28053",
    "sg:province":"Madrid",
    "wof:name":"Matilla Juarez Maria Isabel",
    "wof:placetype":"venue"
},
  "geometry": {"coordinates":[-3.6659519672,40.3950233459],"type":"Point"}
}