{
  "type": "Feature",
  "properties": {
    "iso:country":"ES",
    "sg:address":"Calle de Murcia, 70",
    "sg:city":"Almeria",
    "sg:orig_category":"Peluquer\u00cdas, Peluquer\u00cda Mixta",
    "sg:phone":"+34 950 25 06 55",
    "sg:postcode":"04004",
    "sg:province":"Almer\u00eda",
    "wof:name":"Soler Martin Jose Agustin",
    "wof:placetype":"venue"
},
  "geometry": {"coordinates":[-2.4595160484,36.8437843323],"type":"Point"}
}