{
  "type": "Feature",
  "properties": {
    "addr:full":"Ctra Circunvalacion, S/n Guarda Pontevedra 36780",
    "addr:postcode":"36780",
    "addr:street":"Ctra Circunvalacion S / N",
    "iso:country":"ES",
    "sg:address":"Ctra Circunvalacion, S/n",
    "sg:city":"Guarda",
    "sg:orig_category":"Negocio De Materiales De Construcci\u00d3n",
    "sg:phone":"+34 986 61 05 76",
    "sg:postcode":"36780",
    "sg:province":"Pontevedra",
    "wof:name":"Cividanes Martinez Materiales De Construccion S. L.",
    "wof:placetype":"venue"
},
  "geometry": {"coordinates":[-8.8713140488,41.9025039673],"type":"Point"}
}