{
  "type": "Feature",
  "properties": {
    "addr:full":"Carrer de Vapor (del), S/n Terra Nostra Barcelona 08110",
    "addr:housenumber":"/ n",
    "addr:postcode":"08110",
    "addr:street":"Carrer De Vapor Del S",
    "iso:country":"ES",
    "sg:address":"Carrer de Vapor (del), S/n",
    "sg:city":"Terra Nostra",
    "sg:orig_category":"Fabricaci\u00d3n De Moldes Y Modelos",
    "sg:phone":"+34 935 75 07 89",
    "sg:postcode":"08110",
    "sg:province":"Barcelona",
    "wof:name":"Intrael S.a.",
    "wof:placetype":"venue"
},
  "geometry": {"coordinates":[2.1696550846,41.4881515503],"type":"Point"}
}