{
  "type": "Feature",
  "properties": {
    "addr:full":"Calle de Italia, 53 Zaragoza Zaragoza 50010",
    "addr:housenumber":"53",
    "addr:postcode":"50010",
    "addr:street":"Calle De Italia",
    "iso:country":"ES",
    "sg:address":"Calle de Italia, 53",
    "sg:city":"Zaragoza",
    "sg:orig_category":"Frutas, Legumbres Frescas Y Tempranas (al Por Menor)",
    "sg:phone":"+34 976 33 87 86",
    "sg:postcode":"50010",
    "sg:province":"Zaragoza",
    "wof:name":"Martin Martinez Alfredo",
    "wof:placetype":"venue"
},
  "geometry": {"coordinates":[-0.8996480107,41.6504821777],"type":"Point"}
}