{
  "type": "Feature",
  "properties": {
    "addr:full":"Calle de Plus Ultra, 7 Huelva Huelva 21001",
    "addr:housenumber":"7",
    "addr:postcode":"21001",
    "addr:street":"Calle De Plus Ultra",
    "iso:country":"ES",
    "sg:address":"Calle de Plus Ultra, 7",
    "sg:city":"Huelva",
    "sg:orig_category":"Ropa Para Ni\u00d1os (al Por Menor)",
    "sg:phone":"+34 959 25 54 56",
    "sg:postcode":"21001",
    "sg:province":"Huelva",
    "sg:website":"www.torero.com",
    "wof:name":"Villegas Lopez Pilar",
    "wof:placetype":"venue"
},
  "geometry": {"coordinates":[-6.9537467957,37.2574462891],"type":"Point"}
}