{
  "type": "Feature",
  "properties": {
    "addr:full":"Carrer de Sugranyes, 117 Barcelona Barcelona 08028",
    "addr:housenumber":"117",
    "addr:postcode":"08028",
    "addr:street":"Carrer De Sugranyes",
    "iso:country":"ES",
    "sg:address":"Carrer de Sugranyes, 117",
    "sg:city":"Barcelona",
    "sg:orig_category":"Instalaci\u00d3n, Reparaci\u00d3n De Ascensores Y Montacargas",
    "sg:phone":"+34 934 22 78 11",
    "sg:postcode":"08028",
    "sg:province":"Barcelona",
    "sg:website":"www.asfortascensores.com",
    "wof:name":"Ascensores Asfort S.l.",
    "wof:placetype":"venue"
},
  "geometry": {"coordinates":[2.1309549809,41.3709602356],"type":"Point"}
}