{
  "type": "Feature",
  "properties": {
    "addr:full":"Calle de Principal, 79 Boiro La Coru\u00f1a 15930",
    "addr:housenumber":"79",
    "addr:postcode":"15930",
    "addr:street":"Calle De Principal;La Corun\u0303A",
    "iso:country":"ES",
    "sg:address":"Calle de Principal, 79",
    "sg:city":"Boiro",
    "sg:orig_category":"Confecci\u00d3n (fabricaci\u00d3n, Al Por Mayor)",
    "sg:phone":"+34 981 84 41 41",
    "sg:postcode":"15930",
    "sg:province":"La Coru\u00f1a",
    "wof:name":"Cortes Sanchez Joaquin",
    "wof:placetype":"venue"
},
  "geometry": {"coordinates":[-8.8847093582,42.6471214294],"type":"Point"}
}