{
  "type": "Feature",
  "properties": {
    "iso:country":"ES",
    "sg:address":"Avda Marques De Lacy, 62",
    "sg:city":"Murada",
    "sg:orig_category":"Empresas De Impermeabilizaci\u00d3n",
    "sg:phone":"+34 966 77 92 05",
    "sg:postcode":"03315",
    "sg:province":"Alicante",
    "wof:name":"Impemur S.l.",
    "wof:placetype":"venue"
},
  "geometry": {"coordinates":[-0.9639940262,38.1715431213],"type":"Point"}
}