{
  "type": "Feature",
  "properties": {
    "addr:full":"Carrer de Diputacio, 426 Barcelona Barcelona 08013",
    "addr:housenumber":"426",
    "addr:postcode":"08013",
    "addr:street":"Carrer De Diputacio",
    "iso:country":"ES",
    "sg:address":"Carrer de Diputacio, 426",
    "sg:city":"Barcelona",
    "sg:orig_category":"Herboristas (al Por Menor)",
    "sg:phone":"+34 932 45 03 09",
    "sg:postcode":"08013",
    "sg:province":"Barcelona",
    "wof:name":"Vickyari Dietetica S.l.",
    "wof:placetype":"venue"
},
  "geometry": {"coordinates":[2.1797959805,41.3997612],"type":"Point"}
}