{
  "type": "Feature",
  "properties": {
    "addr:full":"Calle de Elvira, 10 Madrid Madrid 28028",
    "addr:housenumber":"10",
    "addr:postcode":"madrid;28028",
    "addr:street":"Calle De Elvira",
    "iso:country":"ES",
    "sg:address":"Calle de Elvira, 10",
    "sg:city":"Madrid",
    "sg:orig_category":"Complementos De Vestir (al Por Menor)",
    "sg:phone":"+34 915 74 49 14",
    "sg:postcode":"28028",
    "sg:province":"Madrid",
    "wof:name":"Del Pozo Castro Vanesa",
    "wof:placetype":"venue"
},
  "geometry": {"coordinates":[-3.6656229496,40.4233398438],"type":"Point"}
}