{
  "type": "Feature",
  "properties": {
    "iso:country":"ES",
    "sg:address":"Calle de Constitucion (la), 14",
    "sg:city":"Palanquinos",
    "sg:orig_category":"Empresarios",
    "sg:phone":"+34 987 31 50 41",
    "sg:postcode":"24225",
    "sg:province":"Le\u00f3n",
    "wof:name":"Calzada Gonzalez Nicanor",
    "wof:placetype":"venue"
},
  "geometry": {"coordinates":[-5.4807291031,42.4700965881],"type":"Point"}
}