{
  "type": "Feature",
  "properties": {
    "addr:full":"Calle de Cabo San Vicente, 14 Alcorcon Madrid 28924",
    "addr:housenumber":"14",
    "addr:postcode":"28924",
    "addr:street":"Calle De Cabo San Vicente",
    "iso:country":"ES",
    "sg:address":"Calle de Cabo San Vicente, 14",
    "sg:city":"Alcorcon",
    "sg:orig_category":"Poller\u00cda Y Caza (al Por Menor)",
    "sg:phone":"+34 916 42 58 18",
    "sg:postcode":"28924",
    "sg:province":"Madrid",
    "wof:name":"Avescastilla S.l.",
    "wof:placetype":"venue"
},
  "geometry": {"coordinates":[-3.8148009777,40.3521499634],"type":"Point"}
}