{
  "type": "Feature",
  "properties": {
    "iso:country":"ES",
    "sg:address":"Calle de Salou, 1",
    "sg:city":"Bilbao",
    "sg:orig_category":"Molduras, Junquillos, Listones Y Molduras Perforadas",
    "sg:phone":"+34 944 43 50 70",
    "sg:postcode":"48002",
    "sg:province":"Vizcaya",
    "wof:name":"Alonso Del Amo Jesus Maria",
    "wof:placetype":"venue"
},
  "geometry": {"coordinates":[-2.9441158772,43.2520675659],"type":"Point"}
}