{
  "type": "Feature",
  "properties": {
    "addr:full":"Avda Benidorm, 6 Arnedo La Rioja 26580",
    "addr:housenumber":"6",
    "addr:postcode":"26580",
    "addr:street":"Avda Benidorm;Rioja",
    "iso:country":"ES",
    "sg:address":"Avda Benidorm, 6",
    "sg:city":"Arnedo",
    "sg:orig_category":"Transportes Por V\u00cdas Navegables",
    "sg:phone":"+34 941 38 09 16",
    "sg:postcode":"26580",
    "sg:province":"La Rioja",
    "wof:name":"Valenciano Gonzalez Orestes",
    "wof:placetype":"venue"
},
  "geometry": {"coordinates":[-2.0992290974,42.2252616882],"type":"Point"}
}