{
  "type": "Feature",
  "properties": {
    "addr:full":"Calle de Colina Blanca, S/n Fuengirola M\u00e1laga 29640",
    "addr:housenumber":"s / n",
    "addr:postcode":"29640",
    "addr:street":"Calle De Colina Blanca;Ma\u0301Laga",
    "iso:country":"ES",
    "sg:address":"Calle de Colina Blanca, S/n",
    "sg:city":"Fuengirola",
    "sg:orig_category":"Promotores Constructores",
    "sg:phone":"+34 952 49 93 50",
    "sg:postcode":"29640",
    "sg:province":"M\u00e1laga",
    "wof:name":"Inares Promociones,s.l",
    "wof:placetype":"venue"
},
  "geometry": {"coordinates":[-4.6088852882,36.5691261292],"type":"Point"}
}