{
  "type": "Feature",
  "properties": {
    "iso:country":"ES",
    "sg:address":"Plg Ind Tobares, S/n",
    "sg:city":"Molina",
    "sg:orig_category":"Mec\u00c1nico Del Autom\u00d3vil",
    "sg:phone":"+34 949 83 20 19",
    "sg:postcode":"19300",
    "sg:province":"Guadalajara",
    "wof:name":"Marco Llorente Angel",
    "wof:placetype":"venue"
},
  "geometry": {"coordinates":[-1.8168599606,40.8542098999],"type":"Point"}
}