{
  "type": "Feature",
  "properties": {
    "iso:country":"ES",
    "sg:address":"Calle de Francisco Navacerrada, 29",
    "sg:city":"Madrid",
    "sg:orig_category":"Postigos, Persianas Y Celos\u00cdas",
    "sg:phone":"+34 913 55 51 50",
    "sg:postcode":"28028",
    "sg:province":"Madrid",
    "wof:name":"Gomez Arellano Dolores",
    "wof:placetype":"venue"
},
  "geometry": {"coordinates":[-3.6685988903,40.4312553406],"type":"Point"}
}