{
  "type": "Feature",
  "properties": {
    "addr:full":"Calle de Montesa, 20 Madrid Madrid 28006",
    "addr:housenumber":"20",
    "addr:postcode":"madrid;28006",
    "addr:street":"Calle De Montesa",
    "iso:country":"ES",
    "sg:address":"Calle de Montesa, 20",
    "sg:city":"Madrid",
    "sg:orig_category":"Gastronom\u00cda: Especialidades Regionales Y Extranjeras (producci\u00d3n, Al Por Mayor)",
    "sg:phone":"+34 914 01 17 40",
    "sg:postcode":"28006",
    "sg:province":"Madrid",
    "wof:name":"Olmedillo Pascuas Azucena",
    "wof:placetype":"venue"
},
  "geometry": {"coordinates":[-3.6723053455,40.4284362793],"type":"Point"}
}