{
  "type": "Feature",
  "properties": {
    "addr:full":"Carr Josep Verdera, 12 Eivissa Islas Baleares 07800",
    "addr:housenumber":"12",
    "addr:postcode":"07800",
    "addr:street":"Carr Josep Verdera",
    "iso:country":"ES",
    "sg:address":"Carr Josep Verdera, 12",
    "sg:city":"Eivissa",
    "sg:orig_category":"Confecci\u00d3n De Guantes",
    "sg:phone":"+34 971 19 15 67",
    "sg:postcode":"07800",
    "sg:province":"Islas Baleares",
    "sg:website":"www.us-motos-ibiza.net",
    "wof:name":"U.s. Motos Ibiza Icyhot Ibiza S.l.",
    "wof:placetype":"venue"
},
  "geometry": {"coordinates":[1.4188899994,38.9061164856],"type":"Point"}
}