{
  "type": "Feature",
  "properties": {
    "addr:full":"Calle de Isaac Peral, S/n Estacion De Benacazon Sevilla 41800",
    "addr:housenumber":"s",
    "addr:postcode":"41800",
    "addr:street":"Calle De Isaac Peral;/ N Estacion De Benacazon",
    "iso:country":"ES",
    "sg:address":"Calle de Isaac Peral, S/n",
    "sg:city":"Estacion De Benacazon",
    "sg:orig_category":"Comercio De Piezas De Recambio Y De Accesorios De Veh\u00cdculos, Veh\u00cdculos Industriales",
    "sg:phone":"+34 955 70 33 36",
    "sg:postcode":"41800",
    "sg:province":"Sevilla",
    "wof:name":"Grupo M. Jimenez Ma\u00f1a S.l.",
    "wof:placetype":"venue"
},
  "geometry": {"coordinates":[-6.1956338882,37.3855361938],"type":"Point"}
}