{
  "type": "Feature",
  "properties": {
    "addr:full":"Calle de Berriobide, 24 Ansoain Navarra 31013",
    "addr:housenumber":"24",
    "addr:postcode":"31013",
    "addr:street":"Calle De Berriobide",
    "iso:country":"ES",
    "sg:address":"Calle de Berriobide, 24",
    "sg:city":"Ansoain",
    "sg:orig_category":"Venta, Instalaci\u00d3n De Quemadores",
    "sg:phone":"+34 948 14 32 01",
    "sg:postcode":"31013",
    "sg:province":"Navarra",
    "wof:name":"Zu\u00f1iga Azcarate Joseba Xabier",
    "wof:placetype":"venue"
},
  "geometry": {"coordinates":[-1.6431988478,42.8338470459],"type":"Point"}
}