{
  "type": "Feature",
  "properties": {
    "iso:country":"ES",
    "sg:address":"Carrer de Vapor (d'el), 9",
    "sg:city":"Tarragona",
    "sg:orig_category":"Suministros Para Hoteles",
    "sg:phone":"+34 977 23 09 55",
    "sg:postcode":"43004",
    "sg:province":"Tarragona",
    "wof:name":"Llorens Monguio Domingo",
    "wof:placetype":"venue"
},
  "geometry": {"coordinates":[1.2452720404,41.1122627258],"type":"Point"}
}