{
  "type": "Feature",
  "properties": {
    "addr:full":"Calle de Valdepe\u00d1as, 10 Requena Valencia 46340",
    "addr:housenumber":"10",
    "addr:postcode":"46340",
    "addr:street":"Calle De Valdepen\u0303As",
    "iso:country":"ES",
    "sg:address":"Calle de Valdepe\u00d1as, 10",
    "sg:city":"Requena",
    "sg:orig_category":"Escayola Y Productos De Escayola (fabricaci\u00d3n, Al Por Mayor)",
    "sg:phone":"+34 962 30 12 74",
    "sg:postcode":"46340",
    "sg:province":"Valencia",
    "wof:name":"Ortiz Pedron Piedad",
    "wof:placetype":"venue"
},
  "geometry": {"coordinates":[-1.0967680216,39.4903717041],"type":"Point"}
}