{
  "type": "Feature",
  "properties": {
    "iso:country":"ES",
    "sg:address":"Cno. De La Fuente, S/n",
    "sg:city":"Tiena",
    "sg:orig_category":"Negocio De Materiales De Construcci\u00d3n",
    "sg:phone":"+34 958 34 00 71",
    "sg:postcode":"18248",
    "sg:province":"Granada",
    "wof:name":"El Mimbre E Hijos S.l.",
    "wof:placetype":"venue"
},
  "geometry": {"coordinates":[-3.7883729935,37.320476532],"type":"Point"}
}