{
  "type": "Feature",
  "properties": {
    "addr:full":"Carrer de Freixa, 46 Barcelona Barcelona 08021",
    "addr:housenumber":"46",
    "addr:postcode":"08021",
    "addr:street":"Carrer De Freixa",
    "iso:country":"ES",
    "sg:address":"Carrer de Freixa, 46",
    "sg:city":"Barcelona",
    "sg:classifiers":[
        {
            "category":"Professional",
            "subcategory":"Management & Consulting",
            "type":"Services"
        }
    ],
    "sg:phone":"+34 932 09 67 38",
    "sg:postcode":"08021",
    "sg:province":"Barcelona",
    "sg:tags":[
        "asesor\u00cda",
        "en",
        "marketing"
    ],
    "wof:name":"Maplaco S.l.",
    "wof:placetype":"venue"
},
  "geometry": {"coordinates":[2.1393370628,41.3991584778],"type":"Point"}
}