{
  "type": "Feature",
  "properties": {
    "addr:full":"Carrer de Rabassaires, 16 Vendrell Tarragona 43700",
    "addr:housenumber":"16",
    "addr:postcode":"43700",
    "addr:street":"Carrer De Rabassaires",
    "iso:country":"ES",
    "sg:address":"Carrer de Rabassaires, 16",
    "sg:city":"Vendrell",
    "sg:orig_category":"Asociaciones Y Clubs Deportivos",
    "sg:phone":"+34 977 15 71 86",
    "sg:postcode":"43700",
    "sg:province":"Tarragona",
    "wof:name":"Oscar Serrano Santos",
    "wof:placetype":"venue"
},
  "geometry": {"coordinates":[1.5350110531,41.2240867615],"type":"Point"}
}