{
  "type": "Feature",
  "properties": {
    "iso:country":"ES",
    "sg:address":"Carrer de Baro De Pinopar, 4",
    "sg:city":"Palma",
    "sg:orig_category":"Asesor\u00cdas Y Estudios Financieros",
    "sg:phone":"+34 971 71 70 59",
    "sg:postcode":"07012",
    "sg:province":"Islas Baleares",
    "wof:name":"Sanchez Salgado Jose Manuel",
    "wof:placetype":"venue"
},
  "geometry": {"coordinates":[2.6478600502,39.575969696],"type":"Point"}
}