{
  "type": "Feature",
  "properties": {
    "iso:country":"ES",
    "sg:address":"Calle de Postigo, 36",
    "sg:city":"Astorga",
    "sg:orig_category":"Alimentaci\u00d3n General (al Por Menor)",
    "sg:phone":"+34 987 61 58 84",
    "sg:postcode":"24700",
    "sg:province":"Le\u00f3n",
    "wof:name":"Pedrosa Garcia Isabel",
    "wof:placetype":"venue"
},
  "geometry": {"coordinates":[-6.0513281822,42.451877594],"type":"Point"}
}