{
  "type": "Feature",
  "properties": {
    "iso:country":"ES",
    "sg:address":"Carr Gabriel Roca, 73",
    "sg:city":"Colonia S. Jordi",
    "sg:orig_category":"Cervecer\u00cdas",
    "sg:phone":"+34 971 65 51 83",
    "sg:postcode":"07638",
    "sg:province":"Islas Baleares",
    "wof:name":"Ferrer Salva Jaime",
    "wof:placetype":"venue"
},
  "geometry": {"coordinates":[2.9928250313,39.3186759949],"type":"Point"}
}