{
  "type": "Feature",
  "properties": {
    "iso:country":"ES",
    "sg:address":"C. C. Cala Del Sol, S/n",
    "sg:city":"Mijas Costa",
    "sg:orig_category":"Inmobiliaria (agencias)",
    "sg:phone":"+34 952 49 43 68",
    "sg:postcode":"29649",
    "sg:province":"M\u00e1laga",
    "wof:name":"Vitania Residencial S.a.",
    "wof:placetype":"venue"
},
  "geometry": {"coordinates":[-4.6802053452,36.5034294128],"type":"Point"}
}