{
  "type": "Feature",
  "properties": {
    "iso:country":"ES",
    "sg:address":"Alba, S/n",
    "sg:city":"Alba",
    "sg:orig_category":"Mantequer\u00cdas, Queser\u00cdas (al Por Menor)",
    "sg:phone":"+34 982 38 02 51",
    "sg:postcode":"27207",
    "sg:province":"Lugo",
    "wof:name":"Carrera Valin Xose Luis",
    "wof:placetype":"venue"
},
  "geometry": {"coordinates":[-7.8872327805,42.8478088379],"type":"Point"}
}