{
  "type": "Feature",
  "properties": {
    "iso:country":"ES",
    "sg:address":"Carrer de Sant Joaquim, 84",
    "sg:city":"Santa Coloma De Gramenet",
    "sg:orig_category":"Molduras, Junquillos, Listones Y Molduras Perforadas",
    "sg:phone":"+34 933 86 27 29",
    "sg:postcode":"08922",
    "sg:province":"Barcelona",
    "wof:name":"Alvarez Mu\u00f1oz Romualdo",
    "wof:placetype":"venue"
},
  "geometry": {"coordinates":[2.2063961029,41.447971344],"type":"Point"}
}