{
  "type": "Feature",
  "properties": {
    "addr:full":"Calle de Alfonso Xii, 13 Mostoles Madrid 28934",
    "addr:housenumber":"13",
    "addr:postcode":"28934",
    "addr:street":"Calle De Alfonso Xii",
    "iso:country":"ES",
    "sg:address":"Calle de Alfonso Xii, 13",
    "sg:city":"Mostoles",
    "sg:orig_category":"Molduras, Junquillos, Listones Y Molduras Perforadas",
    "sg:phone":"+34 916 64 31 04",
    "sg:postcode":"28934",
    "sg:province":"Madrid",
    "wof:name":"Navarro Jurado Manuel",
    "wof:placetype":"venue"
},
  "geometry": {"coordinates":[-3.8752837181,40.3182945251],"type":"Point"}
}