{
  "type": "Feature",
  "properties": {
    "addr:full":"Avda Marinas (las), 14 Marinas Almer\u00eda 04740",
    "addr:housenumber":"14",
    "addr:postcode":"04740",
    "addr:street":"Avda Marinas Las;Almeri\u0301A",
    "iso:country":"ES",
    "sg:address":"Avda Marinas (las), 14",
    "sg:city":"Marinas",
    "sg:orig_category":"Molduras, Junquillos, Listones Y Molduras Perforadas",
    "sg:phone":"+34 950 33 33 13",
    "sg:postcode":"04740",
    "sg:province":"Almer\u00eda",
    "wof:name":"Garcia Martinez Rafael",
    "wof:placetype":"venue"
},
  "geometry": {"coordinates":[-1.8177318573,37.1918640137],"type":"Point"}
}