{
  "type": "Feature",
  "properties": {
    "iso:country":"ES",
    "sg:address":"Calle de Pablo Gargallo, 3",
    "sg:city":"Alca\u00f1iz",
    "sg:orig_category":"Negocio De Enlosados, Soler\u00cdas",
    "sg:phone":"+34 978 87 07 62",
    "sg:postcode":"44600",
    "sg:province":"Teruel",
    "wof:name":"Tafalla Zapater Maria Teresa",
    "wof:placetype":"venue"
},
  "geometry": {"coordinates":[-0.1262789965,41.0484809875],"type":"Point"}
}