{
  "type": "Feature",
  "properties": {
    "addr:full":"G.v. Corts Catalanes, 1129 Barcelona Barcelona 08020",
    "addr:postcode":"1129;08020",
    "addr:street":"Catalanes",
    "iso:country":"ES",
    "sg:address":"G.v. Corts Catalanes, 1129",
    "sg:city":"Barcelona",
    "sg:orig_category":"Molduras, Junquillos, Listones Y Molduras Perforadas",
    "sg:phone":"+34 933 14 41 48",
    "sg:postcode":"08020",
    "sg:province":"Barcelona",
    "wof:name":"Alvarez Martin Mercedes",
    "wof:placetype":"venue"
},
  "geometry": {"coordinates":[2.2058339119,41.4181938171],"type":"Point"}
}