{
  "type": "Feature",
  "properties": {
    "iso:country":"ES",
    "sg:address":"Calle de Alcalde Martin Cobos, S/n",
    "sg:city":"Burgos",
    "sg:orig_category":"Agricultura: Abastecimiento Y Cosechado (negocio)",
    "sg:phone":"+34 947 48 37 91",
    "sg:postcode":"09007",
    "sg:province":"Burgos",
    "wof:name":"Nuevocampo S. L.",
    "wof:placetype":"venue"
},
  "geometry": {"coordinates":[-3.6492722034,42.3622016907],"type":"Point"}
}