{
  "type": "Feature",
  "properties": {
    "iso:country":"ES",
    "sg:address":"Psaj Ventos Mir, 24",
    "sg:city":"Badalona",
    "sg:orig_category":"Iglesia Cat\u00d3lica",
    "sg:phone":"+34 933 84 37 15",
    "sg:postcode":"08912",
    "sg:province":"Barcelona",
    "wof:name":"Parroquia De San Jose",
    "wof:placetype":"venue"
},
  "geometry": {"coordinates":[2.2394599915,41.4451293945],"type":"Point"}
}