{
  "type": "Feature",
  "properties": {
    "addr:full":"Avda Antonio Machado, 10 Arroyo De La Miel-benalmadena Costa M\u00e1laga 29630",
    "addr:housenumber":"10",
    "addr:postcode":"29630",
    "addr:street":"Avda Antonio Machado;Ma\u0301Laga",
    "iso:country":"ES",
    "sg:address":"Avda Antonio Machado, 10",
    "sg:city":"Arroyo De La Miel-benalmadena Costa",
    "sg:orig_category":"Ense\u00d1anza, Formaci\u00d3n Profesional: Aprendizaje",
    "sg:phone":"+34 952 44 24 94",
    "sg:postcode":"29630",
    "sg:province":"M\u00e1laga",
    "sg:website":"www.benalmadena.com",
    "wof:name":"Ayuntamiento De Benalmadena Tenenc Alc Benalmadena Costa",
    "wof:placetype":"venue"
},
  "geometry": {"coordinates":[-4.5364460945,36.5824203491],"type":"Point"}
}