{
  "type": "Feature",
  "properties": {
    "addr:full":"Calle de Caridad, 48 Estepona M\u00e1laga 29680",
    "addr:housenumber":"48",
    "addr:postcode":"29680",
    "addr:street":"Calle De Caridad",
    "iso:country":"ES",
    "sg:address":"Calle de Caridad, 48",
    "sg:city":"Estepona",
    "sg:orig_category":"Asociaciones, Organismos Culturales Y Socioeducativos",
    "sg:phone":"+34 952 79 44 45",
    "sg:postcode":"29680",
    "sg:province":"M\u00e1laga",
    "wof:name":"Asociacion De Mujeres Pe\u00f1as Blancas",
    "wof:placetype":"venue"
},
  "geometry": {"coordinates":[-5.1418604851,36.4270324707],"type":"Point"}
}