{
  "type": "Feature",
  "properties": {
    "addr:full":"Ctra. Madrid, S/n Encinas De Abajo Salamanca 37182",
    "addr:housenumber":"s / n",
    "addr:postcode":"37182",
    "addr:street":"Ctra. Madrid",
    "iso:country":"ES",
    "sg:address":"Ctra. Madrid, S/n",
    "sg:city":"Encinas De Abajo",
    "sg:orig_category":"Agricultores, Agricultores",
    "sg:phone":"+34 923 36 20 05",
    "sg:postcode":"37182",
    "sg:province":"Salamanca",
    "wof:name":"Santa Ana Del Gamo Soc. Coop. Ltda.",
    "wof:placetype":"venue"
},
  "geometry": {"coordinates":[-5.4662699699,40.9334983826],"type":"Point"}
}