{
  "type": "Feature",
  "properties": {
    "addr:full":"Carrer de Hospital, 5 Tivissa Tarragona 43746",
    "addr:housenumber":"5",
    "addr:postcode":"43746",
    "addr:street":"Carrer De Hospital",
    "iso:country":"ES",
    "sg:address":"Carrer de Hospital, 5",
    "sg:city":"Tivissa",
    "sg:orig_category":"Bares, Piano",
    "sg:phone":"+34 977 41 74 05",
    "sg:postcode":"43746",
    "sg:province":"Tarragona",
    "wof:name":"Quintana Margalef Antonio",
    "wof:placetype":"venue"
},
  "geometry": {"coordinates":[0.7326850295,41.0425605774],"type":"Point"}
}