{
  "type": "Feature",
  "properties": {
    "addr:full":"Calle de Rodriguez Arias, 26 Bilbao Vizcaya 48011",
    "addr:housenumber":"26",
    "addr:postcode":"48011",
    "addr:street":"Calle De Rodriguez Arias",
    "iso:country":"ES",
    "sg:address":"Calle de Rodriguez Arias, 26",
    "sg:city":"Bilbao",
    "sg:orig_category":"M\u00c9dicos: Medicina Interna",
    "sg:phone":"+34 944 42 09 34",
    "sg:postcode":"48011",
    "sg:province":"Vizcaya",
    "wof:name":"Aguirre Errasti Ciriaco",
    "wof:placetype":"venue"
},
  "geometry": {"coordinates":[-2.9391283989,43.2627677917],"type":"Point"}
}