{
  "type": "Feature",
  "properties": {
    "addr:full":"Carrer de Turo Blau, 12 Barcelona Barcelona 08016",
    "addr:housenumber":"12",
    "addr:postcode":"08016",
    "addr:street":"Carrer De Turo Blau",
    "iso:country":"ES",
    "sg:address":"Carrer de Turo Blau, 12",
    "sg:city":"Barcelona",
    "sg:orig_category":"Estudios Y Construcci\u00d3n De Acuarios Y Viveros",
    "sg:phone":"+34 932 76 28 24",
    "sg:postcode":"08016",
    "sg:province":"Barcelona",
    "wof:name":"Torello Baldrich Gines",
    "wof:placetype":"venue"
},
  "geometry": {"coordinates":[2.1764690876,41.4393539429],"type":"Point"}
}