{
  "type": "Feature",
  "properties": {
    "iso:country":"ES",
    "sg:address":"Pto. Punta Portals, S/n",
    "sg:city":"Portals Nous",
    "sg:orig_category":"Molduras, Junquillos, Listones Y Molduras Perforadas",
    "sg:phone":"+34 971 67 75 22",
    "sg:postcode":"07181",
    "sg:province":"Islas Baleares",
    "wof:name":"El Caribe\u00f1o S.l.",
    "wof:placetype":"venue"
},
  "geometry": {"coordinates":[2.5657799244,39.5388221741],"type":"Point"}
}