{
  "type": "Feature",
  "properties": {
    "addr:full":"Calle de Pitillas, Km. 0000,8 Santacara Navarra 31314",
    "addr:postcode":"31314",
    "addr:street":"Calle De Pitillas Km. 0000,8",
    "iso:country":"ES",
    "sg:address":"Calle de Pitillas, Km. 0000,8",
    "sg:city":"Santacara",
    "sg:orig_category":"Distribuci\u00d3n De Petr\u00d3leo Y Derivados",
    "sg:phone":"+34 948 74 65 82",
    "sg:postcode":"31314",
    "sg:province":"Navarra",
    "wof:name":"Estacion De Servicio Beriain S.a.",
    "wof:placetype":"venue"
},
  "geometry": {"coordinates":[-1.5525000095,42.3754615784],"type":"Point"}
}