{
  "type": "Feature",
  "properties": {
    "addr:full":"Carrer de Doctor Tarres, 30 Sant Pau Barcelona 08241",
    "addr:housenumber":"30",
    "addr:postcode":"08241",
    "addr:street":"Carrer De Doctor Tarres",
    "iso:country":"ES",
    "sg:address":"Carrer de Doctor Tarres, 30",
    "sg:city":"Sant Pau",
    "sg:orig_category":"Autob\u00das (explotaci\u00d3n Y Servicios De)",
    "sg:phone":"+34 938 72 33 98",
    "sg:postcode":"08241",
    "sg:province":"Barcelona",
    "wof:name":"Pe\u00f1a Corral Jose",
    "wof:placetype":"venue"
},
  "geometry": {"coordinates":[1.8238949776,41.7253952026],"type":"Point"}
}