{
  "type": "Feature",
  "properties": {
    "addr:full":"Av Nord, 12 Santa Margarida-salatar Girona 17480",
    "addr:housenumber":"12",
    "addr:postcode":"17480",
    "addr:street":"Av Nord",
    "iso:country":"ES",
    "sg:address":"Av Nord, 12",
    "sg:city":"Santa Margarida-salatar",
    "sg:orig_category":"Administradores De Bienes Y Delegados De Comunidades De Propietarios",
    "sg:phone":"+34 972 15 09 12",
    "sg:postcode":"17480",
    "sg:province":"Girona",
    "wof:name":"Immoserveis J.company S.l.",
    "wof:placetype":"venue"
},
  "geometry": {"coordinates":[3.1537342072,42.2646446228],"type":"Point"}
}