{
  "type": "Feature",
  "properties": {
    "addr:full":"Caba\u00f1ares, S/n Covaleda Soria 42157",
    "addr:housenumber":"/ n",
    "addr:postcode":"42157",
    "addr:street":"Caban\u0303Ares S",
    "iso:country":"ES",
    "sg:address":"Caba\u00f1ares, S/n",
    "sg:city":"Covaleda",
    "sg:orig_category":"Paletas",
    "sg:phone":"+34 975 37 06 98",
    "sg:postcode":"42157",
    "sg:province":"Soria",
    "wof:name":"Industria Maderera La Nava S. C. L.",
    "wof:placetype":"venue"
},
  "geometry": {"coordinates":[-2.8883941174,41.936756134],"type":"Point"}
}