{
  "type": "Feature",
  "properties": {
    "addr:full":"Rua C, S/n Barreiros Ourense 32910",
    "addr:housenumber":"/ n",
    "addr:postcode":"32910",
    "addr:street":"C S",
    "iso:country":"ES",
    "sg:address":"Rua C, S/n",
    "sg:city":"Barreiros",
    "sg:orig_category":"Contenedores (mercanc\u00cdas)",
    "sg:phone":"+34 988 36 40 94",
    "sg:postcode":"32910",
    "sg:province":"Ourense",
    "wof:name":"Congalle S.l.",
    "wof:placetype":"venue"
},
  "geometry": {"coordinates":[-7.8773641586,42.2747917175],"type":"Point"}
}