{
  "type": "Feature",
  "properties": {
    "iso:country":"ES",
    "sg:address":"Calle de Arabial, 54",
    "sg:city":"Granada",
    "sg:orig_category":"Centros De Coordinaci\u00d3n",
    "sg:phone":"+34 958 53 60 51",
    "sg:postcode":"18004",
    "sg:province":"Granada",
    "wof:name":"Gestion De Inversiones Y Patrimonio Clemente Y Huertas S.l.",
    "wof:placetype":"venue"
},
  "geometry": {"coordinates":[-3.6094489098,37.1735153198],"type":"Point"}
}