{
  "type": "Feature",
  "properties": {
    "addr:full":"Poli Poligono Industrial 5, 5 Collado Villalba Madrid 28400",
    "addr:housenumber":"5 5",
    "addr:postcode":"28400",
    "addr:street":"Poligono Industrial",
    "iso:country":"ES",
    "sg:address":"Poli Poligono Industrial 5, 5",
    "sg:city":"Collado Villalba",
    "sg:orig_category":"Empresas De Carpinter\u00cda De Madera",
    "sg:phone":"+34 918 50 64 01",
    "sg:postcode":"28400",
    "sg:province":"Madrid",
    "wof:name":"Mad-sierra S.l.",
    "wof:placetype":"venue"
},
  "geometry": {"coordinates":[-4.0045962334,40.6371269226],"type":"Point"}
}