{
  "type": "Feature",
  "properties": {
    "iso:country":"ES",
    "sg:address":"Calle de Estartetxe, 7",
    "sg:city":"Estartetxe",
    "sg:orig_category":"Venta, Instalaci\u00d3n De Calefacci\u00d3n",
    "sg:phone":"+34 944 31 67 90",
    "sg:postcode":"48940",
    "sg:province":"Vizcaya",
    "sg:website":"www.temperclima.es",
    "wof:name":"Temper Clima S. A.",
    "wof:placetype":"venue"
},
  "geometry": {"coordinates":[-2.9860789776,43.3275489807],"type":"Point"}
}