{
  "type": "Feature",
  "properties": {
    "iso:country":"ES",
    "sg:address":"Calle de Fatiga, 62",
    "sg:city":"Sotogrande",
    "sg:orig_category":"Restaurantes",
    "sg:phone":"+34 956 69 52 49",
    "sg:postcode":"11310",
    "sg:province":"C\u00e1diz",
    "wof:name":"Bowerman  David Harold",
    "wof:placetype":"venue"
},
  "geometry": {"coordinates":[-5.331715107,36.2784576416],"type":"Point"}
}