{
  "type": "Feature",
  "properties": {
    "addr:full":"Calle de Gallo, 11 Madrid Madrid 28032",
    "addr:housenumber":"11",
    "addr:postcode":"madrid;28032",
    "addr:street":"Calle De Gallo",
    "iso:country":"ES",
    "sg:address":"Calle de Gallo, 11",
    "sg:city":"Madrid",
    "sg:orig_category":"Peluquer\u00cdas, Peluquer\u00cda Mixta",
    "sg:phone":"+34 917 75 13 78",
    "sg:postcode":"28032",
    "sg:province":"Madrid",
    "wof:name":"Marco Perez Engracia",
    "wof:placetype":"venue"
},
  "geometry": {"coordinates":[-3.6148691177,40.4062156677],"type":"Point"}
}