{
  "type": "Feature",
  "properties": {
    "iso:country":"ES",
    "sg:address":"Carr Segon Pati, (del), 52",
    "sg:city":"Carlet",
    "sg:orig_category":"Cl\u00cdnicas Dentales",
    "sg:phone":"+34 962 53 06 01",
    "sg:postcode":"46240",
    "sg:province":"Valencia",
    "wof:name":"Pla Y Candel C.b",
    "wof:placetype":"venue"
},
  "geometry": {"coordinates":[-0.5232869983,39.2299232483],"type":"Point"}
}