{
  "type": "Feature",
  "properties": {
    "addr:full":"Avda General Mola, 18 Pobra Parga Lugo 27380",
    "addr:housenumber":"18",
    "addr:postcode":"27380",
    "addr:street":"Avda General Mola;Parga",
    "iso:country":"ES",
    "sg:address":"Avda General Mola, 18",
    "sg:city":"Pobra Parga",
    "sg:orig_category":"Art\u00cdculos De Madera (fabricaci\u00d3n Y Al Por Mayor)",
    "sg:phone":"+34 982 37 31 35",
    "sg:postcode":"27380",
    "sg:province":"Lugo",
    "wof:name":"Muebles Florentino S.coop.",
    "wof:placetype":"venue"
},
  "geometry": {"coordinates":[-7.8388590813,43.1623191833],"type":"Point"}
}