{
  "type": "Feature",
  "properties": {
    "iso:country":"ES",
    "sg:address":"Calle de Tenerias, 4",
    "sg:city":"Vitoria-gasteiz",
    "sg:orig_category":"Promotores Constructores",
    "sg:phone":"+34 945 24 34 36",
    "sg:postcode":"01012",
    "sg:province":"\u00c1lava",
    "wof:name":"Construcciones Rico Fernandez S.l.",
    "wof:placetype":"venue"
},
  "geometry": {"coordinates":[-2.6756789684,42.8534698486],"type":"Point"}
}