{
  "type": "Feature",
  "properties": {
    "iso:country":"ES",
    "sg:address":"Rua Castelao, 28",
    "sg:city":"Fonte Diaz",
    "sg:orig_category":"Loter\u00cda Y T\u00d3mbola",
    "sg:phone":"+34 981 50 41 29",
    "sg:postcode":"15822",
    "sg:province":"La Coru\u00f1a",
    "wof:name":"Mejuto Miguelez Amelia",
    "wof:placetype":"venue"
},
  "geometry": {"coordinates":[-8.3075380325,42.8657684326],"type":"Point"}
}