{
  "type": "Feature",
  "properties": {
    "iso:country":"ES",
    "sg:address":"O Outeiro, 9",
    "sg:city":"Mos",
    "sg:orig_category":"Empresas De Carpinter\u00cda De Madera",
    "sg:phone":"+34 986 34 44 26",
    "sg:postcode":"36417",
    "sg:province":"Pontevedra",
    "wof:name":"Alfa Y Omega S.c.",
    "wof:placetype":"venue"
},
  "geometry": {"coordinates":[-8.6499872208,42.1766281128],"type":"Point"}
}