{
  "type": "Feature",
  "properties": {
    "iso:country":"ES",
    "sg:address":"Calle de Arritugane, 5",
    "sg:city":"Berreagamendi",
    "sg:orig_category":"Promotores Constructores",
    "sg:phone":"+34 946 74 60 17",
    "sg:postcode":"48100",
    "sg:province":"Vizcaya",
    "wof:name":"Etxeak Egin 1 S.l.",
    "wof:placetype":"venue"
},
  "geometry": {"coordinates":[-2.853774786,43.3220024109],"type":"Point"}
}