{
  "type": "Feature",
  "properties": {
    "iso:country":"ES",
    "sg:address":"Calle de Mesones, 10",
    "sg:city":"Estepa",
    "sg:orig_category":"Farmacias",
    "sg:phone":"+34 955 91 30 08",
    "sg:postcode":"41560",
    "sg:province":"Sevilla",
    "wof:name":"Moyano Hortal Maria Teresa",
    "wof:placetype":"venue"
},
  "geometry": {"coordinates":[-4.8783397675,37.2911911011],"type":"Point"}
}