{
  "type": "Feature",
  "properties": {
    "addr:full":"Calle de Canalejas, 92 Palmas De Gran Canaria Las Palmas 35003",
    "addr:housenumber":"92",
    "addr:postcode":"35003",
    "addr:street":"Calle De Canalejas",
    "iso:country":"ES",
    "sg:address":"Calle de Canalejas, 92",
    "sg:city":"Palmas De Gran Canaria",
    "sg:orig_category":"Centros De Coordinaci\u00d3n",
    "sg:phone":"+34 928 36 41 33",
    "sg:postcode":"35003",
    "sg:province":"Las Palmas",
    "wof:name":"Gestoria Hernandez Tristan E Hijos S.l.",
    "wof:placetype":"venue"
},
  "geometry": {"coordinates":[-15.4214105606,28.1127338409],"type":"Point"}
}