{
  "type": "Feature",
  "properties": {
    "iso:country":"ES",
    "sg:address":"Avda Esteiro, 1",
    "sg:city":"Ferrol",
    "sg:orig_category":"Caf\u00c9s, Bares, Cervecer\u00cdas",
    "sg:phone":"+34 981 35 27 13",
    "sg:postcode":"15403",
    "sg:province":"A Coru\u00f1a",
    "wof:name":"Sertel Atlantico S.l.",
    "wof:placetype":"venue"
},
  "geometry": {"coordinates":[-8.2274856567,43.4831237793],"type":"Point"}
}