{
  "type": "Feature",
  "properties": {
    "iso:country":"ES",
    "sg:address":"Carrer de Amadeu Torner, 105",
    "sg:city":"Hospitalet Llobregat",
    "sg:orig_category":"Empresas De Demolici\u00d3n",
    "sg:phone":"+34 934 21 01 42",
    "sg:postcode":"08902",
    "sg:province":"Barcelona",
    "sg:website":"www.hierrosdelta.com",
    "wof:name":"Escribano Curado Rafael",
    "wof:placetype":"venue"
},
  "geometry": {"coordinates":[2.1216869354,41.3628959656],"type":"Point"}
}