{
  "type": "Feature",
  "properties": {
    "addr:full":"Carrer de Sant Pere, 45 Lloret Mar Girona 17310",
    "addr:housenumber":"45",
    "addr:postcode":"17310",
    "addr:street":"Carrer De Sant Pere",
    "iso:country":"ES",
    "sg:address":"Carrer de Sant Pere, 45",
    "sg:city":"Lloret Mar",
    "sg:orig_category":"Art\u00cdculos De Regalo (al Por Menor)",
    "sg:phone":"+34 972 36 75 74",
    "sg:postcode":"17310",
    "sg:province":"Girona",
    "wof:name":"Mayani  Asha",
    "wof:placetype":"venue"
},
  "geometry": {"coordinates":[2.8457889557,41.7008628845],"type":"Point"}
}