{
  "type": "Feature",
  "properties": {
    "addr:full":"Calle de Quijote (don), 81 Socuellamos Ciudad Real 13630",
    "addr:housenumber":"81",
    "addr:postcode":"13630",
    "addr:street":"Calle De Quijote Don",
    "iso:country":"ES",
    "sg:address":"Calle de Quijote (don), 81",
    "sg:city":"Socuellamos",
    "sg:orig_category":"Agentes Generales De Seguros",
    "sg:phone":"+34 926 53 05 51",
    "sg:postcode":"13630",
    "sg:province":"Ciudad Real",
    "wof:name":"Tortosa Fernandez Honorato Jose",
    "wof:placetype":"venue"
},
  "geometry": {"coordinates":[-2.7975790501,39.2844467163],"type":"Point"}
}