{
  "type": "Feature",
  "properties": {
    "iso:country":"ES",
    "sg:address":"Calle de Pintor Lorenzo Casanova, 18",
    "sg:city":"Alacant",
    "sg:classifiers":[
        {
            "category":"Food & Beverages",
            "subcategory":"Candy",
            "type":"Retail Goods"
        }
    ],
    "sg:phone":"+34 965 92 79 65",
    "sg:postcode":"03003",
    "sg:province":"Alicante",
    "sg:tags":[
        "confiter\u00cdas",
        "y",
        "de",
        "fabricaci\u00d3n",
        "chocolate"
    ],
    "wof:name":"Pico Sanchis Ismael",
    "wof:placetype":"venue"
},
  "geometry": {"coordinates":[-0.4898340106,38.3421211243],"type":"Point"}
}