{
  "type": "Feature",
  "properties": {
    "iso:country":"ES",
    "sg:address":"Carrer de Raval (de), 22",
    "sg:city":"Canonja",
    "sg:orig_category":"Alimentaci\u00d3n General (al Por Menor)",
    "sg:phone":"+34 977 54 42 09",
    "sg:postcode":"43110",
    "sg:province":"Tarragona",
    "wof:name":"Espasa Pelegri Maria Lourdes",
    "wof:placetype":"venue"
},
  "geometry": {"coordinates":[1.1791989803,41.1224060059],"type":"Point"}
}