{
  "type": "Feature",
  "properties": {
    "iso:country":"ES",
    "sg:address":"Carr Antoni Sole, 14",
    "sg:city":"Lleida",
    "sg:orig_category":"Peluqueros: De Se\u00d1oras",
    "sg:phone":"+34 973 20 15 09",
    "sg:postcode":"25001",
    "sg:province":"Lleida",
    "wof:name":"Oca\u00f1a Perez Enriqueta",
    "wof:placetype":"venue"
},
  "geometry": {"coordinates":[0.6442909837,41.6020812988],"type":"Point"}
}