{
  "type": "Feature",
  "properties": {
    "iso:country":"ES",
    "sg:address":"Avda Estacion De El Palo, S/n",
    "sg:city":"Malaga",
    "sg:orig_category":"Universidades",
    "sg:phone":"+34 952 29 03 54",
    "sg:postcode":"29017",
    "sg:province":"M\u00e1laga",
    "wof:name":"Universidad De Malaga",
    "wof:placetype":"venue"
},
  "geometry": {"coordinates":[-4.3612341881,36.7206459045],"type":"Point"}
}