{
  "type": "Feature",
  "properties": {
    "iso:country":"ES",
    "sg:address":"Carr S Josep, 57",
    "sg:city":"Igualada",
    "sg:orig_category":"Bazares, Art\u00cdculos De Limpieza Y De Cocina (al Por Menor)",
    "sg:phone":"+34 938 03 51 58",
    "sg:postcode":"08700",
    "sg:province":"Barcelona",
    "wof:name":"Pablo Mu\u00f1io Mercedes",
    "wof:placetype":"venue"
},
  "geometry": {"coordinates":[1.6232609749,41.5828742981],"type":"Point"}
}