{
  "type": "Feature",
  "properties": {
    "iso:country":"ES",
    "sg:address":"Carrer de Puig Novell, 53",
    "sg:city":"Terrassa",
    "sg:orig_category":"Formaci\u00d3n A Distancia, Por Correspondencia",
    "sg:phone":"+34 937 83 69 07",
    "sg:postcode":"08221",
    "sg:province":"Barcelona",
    "wof:name":"Alavedra Miro Mariona",
    "wof:placetype":"venue"
},
  "geometry": {"coordinates":[2.0145199299,41.5614700317],"type":"Point"}
}