{
  "type": "Feature",
  "properties": {
    "iso:country":"ES",
    "sg:address":"Calle de Pare Presentat, 1",
    "sg:city":"Valencia",
    "sg:orig_category":"Promotores Constructores",
    "sg:phone":"+34 963 16 15 13",
    "sg:postcode":"46013",
    "sg:province":"Valencia",
    "wof:name":"Desco Desco Salvador",
    "wof:placetype":"venue"
},
  "geometry": {"coordinates":[-0.3675389886,39.4419631958],"type":"Point"}
}