{
  "type": "Feature",
  "properties": {
    "iso:country":"ES",
    "sg:address":"Calle de Padre Isla, 13",
    "sg:city":"Valderas",
    "sg:orig_category":"Pescader\u00cdas (al Por Menor)",
    "sg:phone":"+34 987 76 32 78",
    "sg:postcode":"24220",
    "sg:province":"Le\u00f3n",
    "wof:name":"Pescaderia Rabanal C.b.",
    "wof:placetype":"venue"
},
  "geometry": {"coordinates":[-5.4418740273,42.0796890259],"type":"Point"}
}