{
  "type": "Feature",
  "properties": {
    "iso:country":"ES",
    "sg:address":"Veigas (baldranes), 5",
    "sg:city":"Veigas",
    "sg:orig_category":"Chapister\u00cda",
    "sg:phone":"+34 986 62 91 28",
    "sg:postcode":"36460",
    "sg:province":"Pontevedra",
    "wof:name":"Nu\u00f1ez Valenzuela Ramon",
    "wof:placetype":"venue"
},
  "geometry": {"coordinates":[-8.5616960526,42.057220459],"type":"Point"}
}