{
  "type": "Feature",
  "properties": {
    "iso:country":"ES",
    "sg:address":"Avda Veintiocho De Febrero, 99",
    "sg:city":"Bollullos Par Condado",
    "sg:orig_category":"Restaurantes",
    "sg:phone":"+34 959 41 13 49",
    "sg:postcode":"21710",
    "sg:province":"Huelva",
    "wof:name":"Roldan Camacho Francisco",
    "wof:placetype":"venue"
},
  "geometry": {"coordinates":[-6.539495945,37.3441963196],"type":"Point"}
}