{
  "type": "Feature",
  "properties": {
    "addr:full":"Pol. Veintiseis, 6 Vallelado Segovia 40213",
    "addr:housenumber":"6",
    "addr:postcode":"40213",
    "addr:street":"Veintiseis;Segovia",
    "iso:country":"ES",
    "sg:address":"Pol. Veintiseis, 6",
    "sg:city":"Vallelado",
    "sg:orig_category":"Cerrajer\u00cda, Ferrallista",
    "sg:phone":"+34 921 15 03 11",
    "sg:postcode":"40213",
    "sg:province":"Segovia",
    "wof:name":"Talleres Govi S.l.",
    "wof:placetype":"venue"
},
  "geometry": {"coordinates":[-4.4269690514,41.4046897888],"type":"Point"}
}