{
  "type": "Feature",
  "properties": {
    "addr:full":"Tarambana, 393 Tarambana Almer\u00eda 04713",
    "addr:housenumber":"393",
    "addr:postcode":"04713",
    "addr:street":"Tarambana;Almeri\u0301A",
    "iso:country":"ES",
    "sg:address":"Tarambana, 393",
    "sg:city":"Tarambana",
    "sg:orig_category":"Empresas De Carpinter\u00cda Met\u00c1lica",
    "sg:phone":"+34 950 40 62 54",
    "sg:postcode":"04713",
    "sg:province":"Almer\u00eda",
    "wof:name":"Acosta Moron Miguel Angel",
    "wof:placetype":"venue"
},
  "geometry": {"coordinates":[-2.8603508472,36.7653617859],"type":"Point"}
}