{
  "type": "Feature",
  "properties": {
    "addr:full":"Calle de Sigfrido, 7 Malaga M\u00e1laga 29006",
    "addr:housenumber":"7",
    "addr:postcode":"29006",
    "addr:street":"Calle De Sigfrido;Ma\u0301Laga",
    "iso:country":"ES",
    "sg:address":"Calle de Sigfrido, 7",
    "sg:city":"Malaga",
    "sg:orig_category":"Comercio De Cuadros, L\u00c1minas Y Reproducciones De Obras De Arte",
    "sg:phone":"+34 952 35 15 06",
    "sg:postcode":"29006",
    "sg:province":"M\u00e1laga",
    "wof:name":"Idea Cuadros S.l.",
    "wof:placetype":"venue"
},
  "geometry": {"coordinates":[-4.469329834,36.7080039978],"type":"Point"}
}