{
  "type": "Feature",
  "properties": {
    "addr:full":"Rua Ervedelo, 47 Ourense Ourense 32002",
    "addr:housenumber":"47",
    "addr:postcode":"32002",
    "addr:street":"Rua Ervedelo",
    "iso:country":"ES",
    "sg:address":"Rua Ervedelo, 47",
    "sg:city":"Ourense",
    "sg:orig_category":"Molduras, Junquillos, Listones Y Molduras Perforadas",
    "sg:phone":"+34 988 22 00 65",
    "sg:postcode":"32002",
    "sg:province":"Ourense",
    "wof:name":"Gomez Perez Eloy",
    "wof:placetype":"venue"
},
  "geometry": {"coordinates":[-7.8723812103,42.3402824402],"type":"Point"}
}