{
  "type": "Feature",
  "properties": {
    "addr:full":"Avda Cervantes, 27 Baena C\u00f3rdoba 14850",
    "addr:housenumber":"27",
    "addr:postcode":"14850",
    "addr:street":"Avda Cervantes",
    "iso:country":"ES",
    "sg:address":"Avda Cervantes, 27",
    "sg:city":"Baena",
    "sg:orig_category":"Transportes Por V\u00cdas Navegables",
    "sg:phone":"+34 957 67 07 86",
    "sg:postcode":"14850",
    "sg:province":"C\u00f3rdoba",
    "wof:name":"Villareal Lucena Rafael",
    "wof:placetype":"venue"
},
  "geometry": {"coordinates":[-4.3224191666,37.6166610718],"type":"Point"}
}