{
  "type": "Feature",
  "properties": {
    "iso:country":"ES",
    "sg:address":"Calle de Real, 7",
    "sg:city":"Toledo",
    "sg:orig_category":"Perfumer\u00cda, Art\u00cdculos De Ba\u00d1o (fabricaci\u00d3n, Al Por Mayor)",
    "sg:phone":"+34 925 22 86 38",
    "sg:postcode":"45002",
    "sg:province":"Toledo",
    "wof:name":"Sanchez Mu\u00f1oz Jesus",
    "wof:placetype":"venue"
},
  "geometry": {"coordinates":[-4.0291318893,39.8599472046],"type":"Point"}
}