{
  "type": "Feature",
  "properties": {
    "iso:country":"ES",
    "sg:address":"Av Canaletes, 61",
    "sg:city":"Cerdanyola Valles",
    "sg:orig_category":"Fotograf\u00cda Art\u00cdstica Y Retratos",
    "sg:phone":"+34 935 86 39 76",
    "sg:postcode":"08290",
    "sg:province":"Barcelona",
    "sg:website":"www.visiondigital.org",
    "wof:name":"Monje Martinez Juan Carlos",
    "wof:placetype":"venue"
},
  "geometry": {"coordinates":[2.1523439884,41.483631134],"type":"Point"}
}