{
  "type": "Feature",
  "properties": {
    "addr:full":"Los Riegos, S/n Nore\u00f1a Asturias 33180",
    "addr:housenumber":"s",
    "addr:postcode":"33180",
    "addr:street":"Los Riegos;/ N Noren\u0303A Asturias",
    "iso:country":"ES",
    "sg:address":"Los Riegos, S/n",
    "sg:city":"Nore\u00f1a",
    "sg:orig_category":"Asociaciones Y Clubs Deportivos",
    "sg:phone":"+34 985 74 37 03",
    "sg:postcode":"33180",
    "sg:province":"Asturias",
    "sg:website":"www.condalcf.com",
    "wof:name":"Condal Club De Futbol",
    "wof:placetype":"venue"
},
  "geometry": {"coordinates":[-5.7020292282,43.4001083374],"type":"Point"}
}