{
  "type": "Feature",
  "properties": {
    "addr:full":"Pl Gal.la Placidia, 4 Barcelona Barcelona 08006",
    "addr:housenumber":"4",
    "addr:postcode":"08006",
    "addr:street":"Pl Gal.La Placidia",
    "iso:country":"ES",
    "sg:address":"Pl Gal.la Placidia, 4",
    "sg:city":"Barcelona",
    "sg:orig_category":"Bisuter\u00cda, Joyer\u00cda, Relojer\u00cda (al Por Menor)",
    "sg:phone":"+34 932 37 70 52",
    "sg:postcode":"08006",
    "sg:province":"Barcelona",
    "wof:name":"Bofill Planas Mercedes",
    "wof:placetype":"venue"
},
  "geometry": {"coordinates":[2.153678894,41.3989982605],"type":"Point"}
}