{
  "type": "Feature",
  "properties": {
    "addr:full":"Ipintza Kalea, 11 Lezo Guip\u00f9zcoa 20100",
    "addr:housenumber":"11",
    "addr:postcode":"20100",
    "addr:street":"Ipintza Kalea;Guipu\u0300Zcoa",
    "iso:country":"ES",
    "sg:address":"Ipintza Kalea, 11",
    "sg:city":"Lezo",
    "sg:orig_category":"Guarda",
    "sg:phone":"+34 943 34 17 20",
    "sg:postcode":"20100",
    "sg:province":"Guip\u00f9zcoa",
    "wof:name":"Oliva Iglesias Rogelio",
    "wof:placetype":"venue"
},
  "geometry": {"coordinates":[-1.8758490086,43.3249435425],"type":"Point"}
}