{
  "type": "Feature",
  "properties": {
    "iso:country":"ES",
    "sg:address":"Avgd Port, 10",
    "sg:city":"Vila Joiosa",
    "sg:orig_category":"Molduras, Junquillos, Listones Y Molduras Perforadas",
    "sg:phone":"+34 966 85 35 72",
    "sg:postcode":"03570",
    "sg:province":"Alicante",
    "wof:name":"Wrigt  Cristopher John",
    "wof:placetype":"venue"
},
  "geometry": {"coordinates":[-0.2279119045,38.5064811707],"type":"Point"}
}