{
  "type": "Feature",
  "properties": {
    "iso:country":"ES",
    "sg:address":"Calle de Papin, 6",
    "sg:city":"Salamanca",
    "sg:orig_category":"Mercer\u00cda (fabricaci\u00d3n, Al Por Mayor)",
    "sg:phone":"+34 923 25 87 65",
    "sg:postcode":"37007",
    "sg:province":"Salamanca",
    "wof:name":"Mediero Hernandez Fernando Pablo",
    "wof:placetype":"venue"
},
  "geometry": {"coordinates":[-5.6678361893,40.9703941345],"type":"Point"}
}