{
  "type": "Feature",
  "properties": {
    "addr:full":"Calle de Lope De Vega, 5 Bembibre Le\u00f3n 24300",
    "addr:housenumber":"5",
    "addr:postcode":"24300",
    "addr:street":"Calle De Lope De Vega;Leo\u0301N",
    "iso:country":"ES",
    "sg:address":"Calle de Lope De Vega, 5",
    "sg:city":"Bembibre",
    "sg:orig_category":"Sindicatos De Trabajadores",
    "sg:phone":"+34 987 51 09 20",
    "sg:postcode":"24300",
    "sg:province":"Le\u00f3n",
    "wof:name":"Union Regional De Comisiones Obreras De Castilla Y Leon De Vall",
    "wof:placetype":"venue"
},
  "geometry": {"coordinates":[-6.4158229828,42.6178741455],"type":"Point"}
}