{
  "type": "Feature",
  "properties": {
    "addr:full":"Plaz Quinto Centenario, 2 Valladolid Valladolid 47008",
    "addr:housenumber":"2",
    "addr:postcode":"47008",
    "addr:street":"Centenario",
    "iso:country":"ES",
    "sg:address":"Plaz Quinto Centenario, 2",
    "sg:city":"Valladolid",
    "sg:orig_category":"Promotores Constructores",
    "sg:phone":"+34 983 27 76 04",
    "sg:postcode":"47008",
    "sg:province":"Valladolid",
    "wof:name":"Francisco Ruiz Cano S.l.",
    "wof:placetype":"venue"
},
  "geometry": {"coordinates":[-4.7532539368,41.6252288818],"type":"Point"}
}