{
  "type": "Feature",
  "properties": {
    "iso:country":"ES",
    "sg:address":"Avda Galan Bergua, 21",
    "sg:city":"Alca\u00f1iz",
    "sg:orig_category":"Lencer\u00cda Femenina, Corseter\u00cda, Trajes De Ba\u00d1o (al Por Menor)",
    "sg:phone":"+34 978 83 33 62",
    "sg:postcode":"44600",
    "sg:province":"Teruel",
    "wof:name":"Asensio Paricio Fidencia",
    "wof:placetype":"venue"
},
  "geometry": {"coordinates":[-0.1294558048,41.0509796143],"type":"Point"}
}