{
  "type": "Feature",
  "properties": {
    "addr:full":"Plaz San Nicolas, 19 Avila \u00c1vila 05002",
    "addr:housenumber":"19",
    "addr:postcode":"05002",
    "addr:street":"Plaz San Nicolas;A\u0301Vila",
    "iso:country":"ES",
    "sg:address":"Plaz San Nicolas, 19",
    "sg:city":"Avila",
    "sg:orig_category":"Molduras, Junquillos, Listones Y Molduras Perforadas",
    "sg:phone":"+34 920 22 69 68",
    "sg:postcode":"05002",
    "sg:province":"\u00c1vila",
    "wof:name":"Carrera Lopez Vitoriano",
    "wof:placetype":"venue"
},
  "geometry": {"coordinates":[-4.7004771233,40.6519355774],"type":"Point"}
}