{
  "type": "Feature",
  "properties": {
    "addr:full":"Carrer de Amadeu Vives, 6 Manresa Barcelona 08243",
    "addr:housenumber":"6",
    "addr:postcode":"08243",
    "addr:street":"Carrer De Amadeu Vives",
    "iso:country":"ES",
    "sg:address":"Carrer de Amadeu Vives, 6",
    "sg:city":"Manresa",
    "sg:orig_category":"Panader\u00cdas, Panader\u00cdas",
    "sg:phone":"+34 938 74 48 54",
    "sg:postcode":"08243",
    "sg:province":"Barcelona",
    "wof:name":"Manrepans S.l",
    "wof:placetype":"venue"
},
  "geometry": {"coordinates":[1.8358620405,41.7406616211],"type":"Point"}
}