{
  "type": "Feature",
  "properties": {
    "iso:country":"ES",
    "sg:address":"Pl. Catalunya, 3",
    "sg:city":"Palamos",
    "sg:orig_category":"Inmobiliaria (agencias)",
    "sg:phone":"+34 972 31 66 19",
    "sg:postcode":"17230",
    "sg:province":"Girona",
    "wof:name":"Finques Torre Mar S.l.",
    "wof:placetype":"venue"
},
  "geometry": {"coordinates":[3.1282498837,41.8509292603],"type":"Point"}
}