{
  "type": "Feature",
  "properties": {
    "iso:country":"ES",
    "sg:address":"Pol Ind Urbayecla, 54",
    "sg:city":"Yecla",
    "sg:orig_category":"Sales (al Por Mayor)",
    "sg:phone":"+34 968 75 07 27",
    "sg:postcode":"30510",
    "sg:province":"Murcia",
    "wof:name":"Alameda Reposteria Sl",
    "wof:placetype":"venue"
},
  "geometry": {"coordinates":[-1.173699379,38.6051635742],"type":"Point"}
}