{
  "type": "Feature",
  "properties": {
    "addr:full":"Carrer de L'harmonia, 6 Barcelona Barcelona 08035",
    "addr:housenumber":"6",
    "addr:postcode":"08035",
    "addr:street":"Carrer De L'Harmonia",
    "iso:country":"ES",
    "sg:address":"Carrer de L'harmonia, 6",
    "sg:city":"Barcelona",
    "sg:orig_category":"Escultores, Estatuarios E Imagineros",
    "sg:phone":"+34 934 28 22 92",
    "sg:postcode":"08035",
    "sg:province":"Barcelona",
    "wof:name":"Capelo Siso Alvaro",
    "wof:placetype":"venue"
},
  "geometry": {"coordinates":[2.1429970264,41.4343070984],"type":"Point"}
}