{
  "type": "Feature",
  "properties": {
    "addr:full":"Calle de Navarro Rodrigo, 15 Almeria Almer\u00eda 04001",
    "addr:housenumber":"15",
    "addr:postcode":"04001",
    "addr:street":"Calle De Navarro Rodrigo",
    "iso:country":"ES",
    "sg:address":"Calle de Navarro Rodrigo, 15",
    "sg:city":"Almeria",
    "sg:orig_category":"Laboratorios Y Trabajos De Fotograf\u00cda, V\u00cddeo Y Cine",
    "sg:phone":"+34 950 27 75 30",
    "sg:postcode":"04001",
    "sg:province":"Almer\u00eda",
    "wof:name":"Enmarcaciones Asthon S.l.",
    "wof:placetype":"venue"
},
  "geometry": {"coordinates":[-2.4622659683,36.8398246765],"type":"Point"}
}