{
  "type": "Feature",
  "properties": {
    "iso:country":"ES",
    "sg:address":"Carrer de Berlin (de), 5",
    "sg:city":"Salou",
    "sg:orig_category":"Inmobiliaria (alquileres Por Temporada Y Temporales)",
    "sg:phone":"+34 977 38 12 45",
    "sg:postcode":"43840",
    "sg:province":"Tarragona",
    "wof:name":"Clubotel La Dorada S.l.",
    "wof:placetype":"venue"
},
  "geometry": {"coordinates":[1.1371029615,41.0755805969],"type":"Point"}
}