{
  "type": "Feature",
  "properties": {
    "iso:country":"ES",
    "sg:address":"Calle de Ceuta, 28",
    "sg:city":"Madrid",
    "sg:orig_category":"Molduras, Junquillos, Listones Y Molduras Perforadas",
    "sg:phone":"+34 915 79 08 68",
    "sg:postcode":"28039",
    "sg:province":"Madrid",
    "wof:name":"Lopez Arribas Jose Antonio",
    "wof:placetype":"venue"
},
  "geometry": {"coordinates":[-3.6983327866,40.4629402161],"type":"Point"}
}