{
  "type": "Feature",
  "properties": {
    "iso:country":"ES",
    "sg:address":"Carr Ferrocarril D'alcoi, 22",
    "sg:city":"Gandia",
    "sg:orig_category":"Asesor\u00cda Sobre Comunicaci\u00d3n De Empresas",
    "sg:phone":"+34 902 44 45 48",
    "sg:postcode":"46700",
    "sg:province":"Valencia",
    "sg:website":"www.multigestion-gecp.com",
    "wof:name":"Grupo Gegp Europeo De Gestion S.l.",
    "wof:placetype":"venue"
},
  "geometry": {"coordinates":[-0.1857710034,38.9646873474],"type":"Point"}
}