{
  "type": "Feature",
  "properties": {
    "iso:country":"ES",
    "sg:address":"Calle de Angel, 17",
    "sg:city":"Granada",
    "sg:orig_category":"Poller\u00cda Y Caza (al Por Menor)",
    "sg:phone":"+34 958 12 90 02",
    "sg:postcode":"18006",
    "sg:province":"Granada",
    "wof:name":"Chaves Velasco Manuel",
    "wof:placetype":"venue"
},
  "geometry": {"coordinates":[-3.6020982265,37.1727828979],"type":"Point"}
}