{
  "type": "Feature",
  "properties": {
    "iso:country":"ES",
    "sg:address":"Pg Born, 16",
    "sg:city":"Palma",
    "sg:orig_category":"Art\u00cdculos De Decoraci\u00d3n",
    "sg:phone":"+34 971 72 28 40",
    "sg:postcode":"07012",
    "sg:province":"Islas Baleares",
    "wof:name":"Karmentxu Sl",
    "wof:placetype":"venue"
},
  "geometry": {"coordinates":[2.6470069885,39.5703964233],"type":"Point"}
}