{
  "type": "Feature",
  "properties": {
    "iso:country":"ES",
    "sg:address":"Carr Pedro, 31",
    "sg:city":"Bisbal D'emporda",
    "sg:orig_category":"Contenedores (mercanc\u00cdas)",
    "sg:phone":"+34 972 64 03 42",
    "sg:postcode":"17100",
    "sg:province":"Girona",
    "wof:name":"Font Ventura Jordi",
    "wof:placetype":"venue"
},
  "geometry": {"coordinates":[2.813131094,41.9749221802],"type":"Point"}
}