{
  "type": "Feature",
  "properties": {
    "addr:full":"Ctra Almatriche De, 12 Almatriche Alto Las Palmas 35018",
    "addr:housenumber":"12",
    "addr:postcode":"35018",
    "addr:street":"Ctra Almatriche De",
    "iso:country":"ES",
    "sg:address":"Ctra Almatriche De, 12",
    "sg:city":"Almatriche Alto",
    "sg:orig_category":"Electricidad: Instaladores",
    "sg:phone":"+34 928 67 34 88",
    "sg:postcode":"35018",
    "sg:province":"Las Palmas",
    "sg:website":"www.grupopage.com",
    "wof:name":"Page Iberica",
    "wof:placetype":"venue"
},
  "geometry": {"coordinates":[-15.4614219666,28.0847301483],"type":"Point"}
}