{
  "type": "Feature",
  "properties": {
    "iso:country":"ES",
    "sg:address":"Calle de Herradura, 7",
    "sg:city":"Alca\u00f1ices",
    "sg:orig_category":"Librer\u00cdas",
    "sg:phone":"+34 980 68 03 28",
    "sg:postcode":"49500",
    "sg:province":"Zamora",
    "wof:name":"Arguello Prieto Francisca",
    "wof:placetype":"venue"
},
  "geometry": {"coordinates":[-6.3502788544,41.7001647949],"type":"Point"}
}