{
  "type": "Feature",
  "properties": {
    "iso:country":"ES",
    "sg:address":"Calle de General Alava, 30",
    "sg:city":"Vitoria-gasteiz",
    "sg:orig_category":"Grafistas",
    "sg:phone":"+34 945 13 85 46",
    "sg:postcode":"01005",
    "sg:province":"\u00c1lava",
    "sg:website":"www.theorica.es",
    "wof:name":"Theorica De La Pintura S.l.",
    "wof:placetype":"venue"
},
  "geometry": {"coordinates":[-2.670265913,42.8446807861],"type":"Point"}
}