{
  "type": "Feature",
  "properties": {
    "addr:full":"Avda Torrelaguna (de), 2 Azuqueca Henares Guadalajara 19200",
    "addr:housenumber":"2",
    "addr:postcode":"19200",
    "addr:street":"Avda Torrelaguna De",
    "iso:country":"ES",
    "sg:address":"Avda Torrelaguna (de), 2",
    "sg:city":"Azuqueca Henares",
    "sg:orig_category":"Centros Empresariales",
    "sg:phone":"+34 949 26 48 39",
    "sg:postcode":"19200",
    "sg:province":"Guadalajara",
    "wof:name":"Tierno Ropero Rosa",
    "wof:placetype":"venue"
},
  "geometry": {"coordinates":[-3.2656440735,40.5634231567],"type":"Point"}
}