{
  "type": "Feature",
  "properties": {
    "iso:country":"ES",
    "sg:address":"Gijun, 7",
    "sg:city":"La Carrera",
    "sg:orig_category":"Alimentaci\u00d3n General (al Por Mayor)",
    "sg:phone":"+34 985 74 36 27",
    "sg:postcode":"33187",
    "sg:province":"Asturias",
    "wof:name":"Adpan Europa S.l.",
    "wof:placetype":"venue"
},
  "geometry": {"coordinates":[-5.6871051788,43.3447799683],"type":"Point"}
}