{
  "type": "Feature",
  "properties": {
    "iso:country":"ES",
    "sg:address":"Avda Zumalakarregi, 30",
    "sg:city":"Llodio",
    "sg:orig_category":"Perfumer\u00cda (al Por Menor)",
    "sg:phone":"+34 946 72 42 65",
    "sg:postcode":"01400",
    "sg:province":"\u00c1lava",
    "wof:name":"Molinillo Silvia Maria Cristina",
    "wof:placetype":"venue"
},
  "geometry": {"coordinates":[-2.9610130787,43.1451950073],"type":"Point"}
}