{
  "type": "Feature",
  "properties": {
    "addr:full":"Rua Alcalde Electo Carballo, 19 Acea De Ama La Coru\u00f1a 15174",
    "addr:housenumber":"19",
    "addr:postcode":"15174",
    "addr:street":"Rua Alcalde Electo Carballo;Corun\u0303A",
    "iso:country":"ES",
    "sg:address":"Rua Alcalde Electo Carballo, 19",
    "sg:city":"Acea De Ama",
    "sg:orig_category":"Electricidad, Electr\u00d3nica: Material Y Suministros (al Por Mayor)",
    "sg:phone":"+34 981 66 10 37",
    "sg:postcode":"15174",
    "sg:province":"La Coru\u00f1a",
    "wof:name":"Electronica Informatica Y Control S.l.",
    "wof:placetype":"venue"
},
  "geometry": {"coordinates":[-8.3826389313,43.3110656738],"type":"Point"}
}