{
  "type": "Feature",
  "properties": {
    "iso:country":"ES",
    "sg:address":"Calle de Condes De Crespo Rascon, 22",
    "sg:city":"Salamanca",
    "sg:orig_category":"Caf\u00c9s, Bares, Cervecer\u00cdas",
    "sg:phone":"+34 923 26 73 42",
    "sg:postcode":"37002",
    "sg:province":"Salamanca",
    "wof:name":"Teldespa\u00d1a S.l.",
    "wof:placetype":"venue"
},
  "geometry": {"coordinates":[-5.6655087471,40.9674682617],"type":"Point"}
}