{
  "type": "Feature",
  "properties": {
    "addr:full":"Plaz San Pedro De Alcantara, 3 Arenas San Pedro \u00c1vila 05400",
    "addr:housenumber":"3",
    "addr:postcode":"05400",
    "addr:street":"Plaz;Alcantara;A\u0301Vila",
    "iso:country":"ES",
    "sg:address":"Plaz San Pedro De Alcantara, 3",
    "sg:city":"Arenas San Pedro",
    "sg:orig_category":"Inmobiliaria (agencias)",
    "sg:phone":"+34 920 37 27 96",
    "sg:postcode":"05400",
    "sg:province":"\u00c1vila",
    "wof:name":"Estudios Y Estructuras Gredos S.l.",
    "wof:placetype":"venue"
},
  "geometry": {"coordinates":[-5.0866141319,40.210231781],"type":"Point"}
}