{
  "type": "Feature",
  "properties": {
    "iso:country":"ES",
    "sg:address":"Calle de Vicente Aleixandre, 7",
    "sg:city":"Burgos",
    "sg:orig_category":"Caf\u00c9s, Bares, Cervecer\u00cdas",
    "sg:phone":"+34 947 22 10 05",
    "sg:postcode":"09006",
    "sg:province":"Burgos",
    "wof:name":"Merino Castilla S.l.",
    "wof:placetype":"venue"
},
  "geometry": {"coordinates":[-3.6770486832,42.3548355103],"type":"Point"}
}