{
  "type": "Feature",
  "properties": {
    "iso:country":"ES",
    "sg:address":"Calle de Doctor Esquerdo, 105",
    "sg:city":"Madrid",
    "sg:orig_category":"Farmacias",
    "sg:phone":"+34 915 73 41 70",
    "sg:postcode":"28007",
    "sg:province":"Madrid",
    "wof:name":"Pancorbo Vicente Gloria",
    "wof:placetype":"venue"
},
  "geometry": {"coordinates":[-3.669383049,40.4151306152],"type":"Point"}
}