{
  "type": "Feature",
  "properties": {
    "addr:full":"Av Sant Esteve, 37 Granollers Barcelona 08402",
    "addr:housenumber":"37",
    "addr:postcode":"08402",
    "addr:street":"Av Sant Esteve",
    "iso:country":"ES",
    "sg:address":"Av Sant Esteve, 37",
    "sg:city":"Granollers",
    "sg:orig_category":"Asesor\u00cda De Formaci\u00d3n Y Gesti\u00d3n De Personal",
    "sg:phone":"+34 938 70 42 78",
    "sg:postcode":"08402",
    "sg:province":"Barcelona",
    "wof:name":"Asesoria Laboral Gregori S.l.",
    "wof:placetype":"venue"
},
  "geometry": {"coordinates":[2.2904708385,41.6030311584],"type":"Point"}
}