{
  "type": "Feature",
  "properties": {
    "iso:country":"ES",
    "sg:address":"Pist Queidores, 10",
    "sg:city":"Cachadas",
    "sg:orig_category":"Serrer\u00cdas De Madera",
    "sg:phone":"+34 986 64 16 74",
    "sg:postcode":"36869",
    "sg:province":"Pontevedra",
    "wof:name":"Maderas Hermanos Castro S.l.",
    "wof:placetype":"venue"
},
  "geometry": {"coordinates":[-8.6480531693,42.4336204529],"type":"Point"}
}