{
  "type": "Feature",
  "properties": {
    "iso:country":"ES",
    "sg:address":"Carrer de L'encarnacio, 104",
    "sg:city":"Barcelona",
    "sg:orig_category":"Arreglo, Reparaci\u00d3n, Piezas Sueltas De Televisi\u00d3n, V\u00cddeo, Hi",
    "sg:phone":"+34 932 13 27 09",
    "sg:postcode":"08024",
    "sg:province":"Barcelona",
    "wof:name":"Serra Lecina Juan",
    "wof:placetype":"venue"
},
  "geometry": {"coordinates":[2.1625497341,41.4079322815],"type":"Point"}
}