{
  "type": "Feature",
  "properties": {
    "addr:full":"Diseminado Partida Cahuets, S/n Albal Valencia 46470",
    "addr:housenumber":"s / n",
    "addr:postcode":"46470",
    "addr:street":"Diseminado Partida Cahuets",
    "iso:country":"ES",
    "sg:address":"Diseminado Partida Cahuets, S/n",
    "sg:city":"Albal",
    "sg:orig_category":"Art\u00cdculos De Madera (fabricaci\u00d3n Y Al Por Mayor)",
    "sg:phone":"+34 961 26 06 04",
    "sg:postcode":"46470",
    "sg:province":"Valencia",
    "wof:name":"Mueble Auxiliar Grupo Dos S.l.",
    "wof:placetype":"venue"
},
  "geometry": {"coordinates":[-0.4032689929,39.4032859802],"type":"Point"}
}