{
  "type": "Feature",
  "properties": {
    "addr:full":"Calle de Rodriguez Arias, 62 Bilbao Vizcaya 48013",
    "addr:housenumber":"62",
    "addr:postcode":"48013",
    "addr:street":"Calle De Rodriguez Arias",
    "iso:country":"ES",
    "sg:address":"Calle de Rodriguez Arias, 62",
    "sg:city":"Bilbao",
    "sg:orig_category":"Arquitectos",
    "sg:phone":"+34 944 27 75 84",
    "sg:postcode":"48013",
    "sg:province":"Vizcaya",
    "wof:name":"Gorostiza Montero Gerardo",
    "wof:placetype":"venue"
},
  "geometry": {"coordinates":[-2.943969965,43.2639579773],"type":"Point"}
}