{
  "type": "Feature",
  "properties": {
    "addr:full":"Avda Juan Carlos I, 14 Espinardo Murcia 30008",
    "addr:housenumber":"14",
    "addr:postcode":"30008",
    "addr:street":"Avda Juan Carlos I",
    "iso:country":"ES",
    "sg:address":"Avda Juan Carlos I, 14",
    "sg:city":"Espinardo",
    "sg:orig_category":"Laboratorios Y Cl\u00cdnicas Veterinarias",
    "sg:phone":"+34 968 24 51 91",
    "sg:postcode":"30008",
    "sg:province":"Murcia",
    "wof:name":"Albaladejo Serrano Antonio",
    "wof:placetype":"venue"
},
  "geometry": {"coordinates":[-1.1428675652,38.0043716431],"type":"Point"}
}