{
  "type": "Feature",
  "properties": {
    "addr:full":"Plaz Mercado, 1 Fuente S. Esteban Salamanca 37200",
    "addr:housenumber":"1",
    "addr:postcode":"37200",
    "addr:street":"Mercado;S.",
    "iso:country":"ES",
    "sg:address":"Plaz Mercado, 1",
    "sg:city":"Fuente S. Esteban",
    "sg:orig_category":"Laboratorios Y Cl\u00cdnicas Veterinarias",
    "sg:phone":"+34 923 44 00 71",
    "sg:postcode":"37200",
    "sg:province":"Salamanca",
    "wof:name":"Centro Veterinario De La Fuente De San Esteban S.l.",
    "wof:placetype":"venue"
},
  "geometry": {"coordinates":[-6.1650328636,40.826171875],"type":"Point"}
}