{
  "type": "Feature",
  "properties": {
    "iso:country":"ES",
    "sg:address":"Carrer de Demostenes, 13",
    "sg:city":"Sabadell",
    "sg:orig_category":"Ropa De Hogar (al Por Menor)",
    "sg:phone":"+34 937 24 22 49",
    "sg:postcode":"08206",
    "sg:province":"Barcelona",
    "wof:name":"Gonzalez Martos Florian",
    "wof:placetype":"venue"
},
  "geometry": {"coordinates":[2.0863039494,41.5548210144],"type":"Point"}
}