{
  "type": "Feature",
  "properties": {
    "addr:full":"Calle de Jacobo Camarero, 3 Albolote Granada 18220",
    "addr:housenumber":"3",
    "addr:postcode":"18220",
    "addr:street":"Calle De Jacobo Camarero",
    "iso:country":"ES",
    "sg:address":"Calle de Jacobo Camarero, 3",
    "sg:city":"Albolote",
    "sg:orig_category":"Internados & Ense\u00d1anza Privada",
    "sg:phone":"+34 958 46 61 54",
    "sg:postcode":"18220",
    "sg:province":"Granada",
    "wof:name":"Fundacion Patronato Avemariano De Granada",
    "wof:placetype":"venue"
},
  "geometry": {"coordinates":[-3.6530690193,37.2281188965],"type":"Point"}
}