{
  "type": "Feature",
  "properties": {
    "iso:country":"ES",
    "sg:address":"Ctra Olesa, S/n",
    "sg:city":"Terrassa",
    "sg:orig_category":"Inmobiliaria (agencias)",
    "sg:phone":"+34 937 88 13 74",
    "sg:postcode":"08221",
    "sg:province":"Barcelona",
    "wof:name":"Promociones Can Poal S.l.",
    "wof:placetype":"venue"
},
  "geometry": {"coordinates":[1.9886850119,41.5562858582],"type":"Point"}
}