{
  "type": "Feature",
  "properties": {
    "addr:full":"Calle de Isaac Albeniz, 2 Jaen Ja\u00e9n 23009",
    "addr:housenumber":"2;jae\u0301n",
    "addr:postcode":"23009",
    "addr:street":"Calle De Isaac Albeniz",
    "iso:country":"ES",
    "sg:address":"Calle de Isaac Albeniz, 2",
    "sg:city":"Jaen",
    "sg:orig_category":"Mutuas De Seguros",
    "sg:phone":"+34 953 26 37 91",
    "sg:postcode":"23009",
    "sg:province":"Ja\u00e9n",
    "wof:name":"Fraternidad-muprespa Mutua De Accidentes De Trabajo Y Enfermedades Profesionales",
    "wof:placetype":"venue"
},
  "geometry": {"coordinates":[-3.785036087,37.7764167786],"type":"Point"}
}