{
  "type": "Feature",
  "properties": {
    "iso:country":"ES",
    "sg:address":"Calle de Palacio El, S/n",
    "sg:city":"Vegadeo",
    "sg:orig_category":"Promotores Constructores",
    "sg:phone":"+34 985 47 64 78",
    "sg:postcode":"33770",
    "sg:province":"Asturias",
    "wof:name":"Comunidad El Paseo",
    "wof:placetype":"venue"
},
  "geometry": {"coordinates":[-7.0480041504,43.4645385742],"type":"Point"}
}