{
  "type": "Feature",
  "properties": {
    "addr:full":"Pl Llibertat, 8 Barcelona Barcelona 08012",
    "addr:housenumber":"8",
    "addr:postcode":"08012",
    "addr:street":"Pl Llibertat",
    "iso:country":"ES",
    "sg:address":"Pl Llibertat, 8",
    "sg:city":"Barcelona",
    "sg:orig_category":"Reposter\u00cdas",
    "sg:phone":"+34 932 17 15 92",
    "sg:postcode":"08012",
    "sg:province":"Barcelona",
    "wof:name":"El Pa De Sempre S.l.",
    "wof:placetype":"venue"
},
  "geometry": {"coordinates":[2.1535980701,41.4002304077],"type":"Point"}
}