{
  "type": "Feature",
  "properties": {
    "addr:full":"Carrer de Ramoneda, 21 Cornella Llobregat Barcelona 08940",
    "addr:housenumber":"21",
    "addr:postcode":"08940",
    "addr:street":"Carrer De Ramoneda",
    "iso:country":"ES",
    "sg:address":"Carrer de Ramoneda, 21",
    "sg:city":"Cornella Llobregat",
    "sg:orig_category":"Reposter\u00cdas",
    "sg:phone":"+34 933 76 50 10",
    "sg:postcode":"08940",
    "sg:province":"Barcelona",
    "wof:name":"Peralta Rodriguez Jose",
    "wof:placetype":"venue"
},
  "geometry": {"coordinates":[2.0772631168,41.3611068726],"type":"Point"}
}