{
  "type": "Feature",
  "properties": {
    "iso:country":"ES",
    "sg:address":"Carrer de Esteve Terradas, S/n",
    "sg:city":"Manresa",
    "sg:orig_category":"Negocio De Madera",
    "sg:phone":"+34 938 77 38 40",
    "sg:postcode":"08243",
    "sg:province":"Barcelona",
    "wof:name":"Maderas Martinez Hermanos S.l.",
    "wof:placetype":"venue"
},
  "geometry": {"coordinates":[1.8502459526,41.7129402161],"type":"Point"}
}