{
  "type": "Feature",
  "properties": {
    "addr:full":"Carrer de Barca, 3 S. Adria Besos Barcelona 08930",
    "addr:housenumber":"3",
    "addr:postcode":"08930",
    "addr:street":"Carrer De Barca;Barcelona",
    "iso:country":"ES",
    "sg:address":"Carrer de Barca, 3",
    "sg:city":"S. Adria Besos",
    "sg:orig_category":"Chapister\u00cda",
    "sg:phone":"+34 933 81 97 04",
    "sg:postcode":"08930",
    "sg:province":"Barcelona",
    "wof:name":"Mur Calvo Ricardo",
    "wof:placetype":"venue"
},
  "geometry": {"coordinates":[2.2254860401,41.4270362854],"type":"Point"}
}