{
  "type": "Feature",
  "properties": {
    "iso:country":"ES",
    "sg:address":"Calle de San Nicolas, 4",
    "sg:city":"Portugalete",
    "sg:orig_category":"Pescader\u00cdas (al Por Menor)",
    "sg:phone":"+34 944 06 93 63",
    "sg:postcode":"48920",
    "sg:province":"Vizcaya",
    "wof:name":"Maite Teijido Castro Y Romualdo Lopez",
    "wof:placetype":"venue"
},
  "geometry": {"coordinates":[-3.0171000957,43.3164787292],"type":"Point"}
}