{
  "type": "Feature",
  "properties": {
    "addr:full":"Psaj Rio Ribota, 2 Torremolinos M\u00e1laga 29620",
    "addr:housenumber":"2",
    "addr:postcode":"29620",
    "addr:street":"Ribota;Ma\u0301Laga",
    "iso:country":"ES",
    "sg:address":"Psaj Rio Ribota, 2",
    "sg:city":"Torremolinos",
    "sg:orig_category":"Carnicer\u00cdas, Carnicer\u00cdas",
    "sg:phone":"+34 952 38 49 83",
    "sg:postcode":"29620",
    "sg:province":"M\u00e1laga",
    "wof:name":"Carnicerias Selectas S.l.",
    "wof:placetype":"venue"
},
  "geometry": {"coordinates":[-4.5001220703,36.626701355],"type":"Point"}
}