{
  "type": "Feature",
  "properties": {
    "iso:country":"ES",
    "sg:address":"Calle de Islas Baleares, 40",
    "sg:city":"Pozuelo De Alarcon",
    "sg:orig_category":"Inmobiliaria (agencias)",
    "sg:phone":"+34 913 51 44 27",
    "sg:postcode":"28223",
    "sg:province":"Madrid",
    "wof:name":"La Gaveta S.l.",
    "wof:placetype":"venue"
},
  "geometry": {"coordinates":[-3.8205471039,40.4401855469],"type":"Point"}
}