{
  "type": "Feature",
  "properties": {
    "addr:full":"Calle de Arquitecto Morell, 10 Alacant Alicante 03003",
    "addr:housenumber":"10",
    "addr:postcode":"03003",
    "addr:street":"Calle De Arquitecto Morell",
    "iso:country":"ES",
    "sg:address":"Calle de Arquitecto Morell, 10",
    "sg:city":"Alacant",
    "sg:orig_category":"Organizaciones Internacionales",
    "sg:phone":"+34 965 92 22 98",
    "sg:postcode":"03003",
    "sg:province":"Alicante",
    "sg:website":"www.manosunidas.org",
    "wof:name":"Manos Unidas Campa\u00f1a Contra El Hambre",
    "wof:placetype":"venue"
},
  "geometry": {"coordinates":[-0.4926199913,38.3420524597],"type":"Point"}
}