{
  "type": "Feature",
  "properties": {
    "iso:country":"ES",
    "sg:address":"Carrer de Sant Ferran, 14",
    "sg:city":"Pego",
    "sg:orig_category":"Peluquer\u00cdas, Peluquer\u00cda Mixta",
    "sg:phone":"+34 965 57 20 21",
    "sg:postcode":"03780",
    "sg:province":"Alicante",
    "wof:name":"Vicente Sendra Perruquer S.l.",
    "wof:placetype":"venue"
},
  "geometry": {"coordinates":[-0.116042003,38.8409156799],"type":"Point"}
}