{
  "type": "Feature",
  "properties": {
    "addr:full":"Calle de Poeta Llorente, 139 Pobla Vallbona Valencia 46185",
    "addr:housenumber":"139",
    "addr:postcode":"46185",
    "addr:street":"Calle De Poeta Llorente",
    "iso:country":"ES",
    "sg:address":"Calle de Poeta Llorente, 139",
    "sg:city":"Pobla Vallbona",
    "sg:orig_category":"Empresas De Carpinter\u00cda",
    "sg:phone":"+34 961 66 24 22",
    "sg:postcode":"46185",
    "sg:province":"Valencia",
    "wof:name":"Hernandez Giner Santiago",
    "wof:placetype":"venue"
},
  "geometry": {"coordinates":[-0.547977984,39.5904846191],"type":"Point"}
}