{
  "type": "Feature",
  "properties": {
    "iso:country":"ES",
    "sg:address":"Calle de Marquesa De Pinares, 11",
    "sg:city":"Merida",
    "sg:orig_category":"Bordado, Marcado A Medida",
    "sg:phone":"+34 924 31 86 03",
    "sg:postcode":"06800",
    "sg:province":"Badajoz",
    "wof:name":"Tovar Gomez Luis",
    "wof:placetype":"venue"
},
  "geometry": {"coordinates":[-6.3451495171,38.9206733704],"type":"Point"}
}