{
  "type": "Feature",
  "properties": {
    "addr:full":"Ctra Lorca (de), S/n Aguilas Murcia 30880",
    "addr:postcode":"30880",
    "addr:street":"Ctra Lorca De S / N",
    "iso:country":"ES",
    "sg:address":"Ctra Lorca (de), S/n",
    "sg:city":"Aguilas",
    "sg:orig_category":"Frutas Y Legumbres Frescas (al Por Mayor)",
    "sg:phone":"+34 968 43 64 05",
    "sg:postcode":"30880",
    "sg:province":"Murcia",
    "wof:name":"Sociedad Agraria De Transformacion Agricultores Del Sureste",
    "wof:placetype":"venue"
},
  "geometry": {"coordinates":[-1.588408947,37.4092941284],"type":"Point"}
}