{
  "type": "Feature",
  "properties": {
    "addr:full":"Calle de Vereda, 29 Herencia Ciudad Real 13640",
    "addr:housenumber":"29",
    "addr:postcode":"13640",
    "addr:street":"Calle De Vereda",
    "iso:country":"ES",
    "sg:address":"Calle de Vereda, 29",
    "sg:city":"Herencia",
    "sg:orig_category":"Transportes Por Carretera: Lotes Completos, Mercanc\u00cdas Diversas",
    "sg:phone":"+34 926 57 13 42",
    "sg:postcode":"13640",
    "sg:province":"Ciudad Real",
    "wof:name":"Transsafer S.l.",
    "wof:placetype":"venue"
},
  "geometry": {"coordinates":[-3.3571062088,39.3652496338],"type":"Point"}
}