{
  "type": "Feature",
  "properties": {
    "addr:full":"Calle de Nieves, 29 Bola\u00e7os De Calatrava Ciudad Real 13260",
    "addr:housenumber":"29",
    "addr:postcode":"13260",
    "addr:street":"Calle De Nieves",
    "iso:country":"ES",
    "sg:address":"Calle de Nieves, 29",
    "sg:city":"Bola\u00e7os De Calatrava",
    "sg:orig_category":"Molduras, Junquillos, Listones Y Molduras Perforadas",
    "sg:phone":"+34 926 87 00 87",
    "sg:postcode":"13260",
    "sg:province":"Ciudad Real",
    "wof:name":"Chacon Garcia Antonio",
    "wof:placetype":"venue"
},
  "geometry": {"coordinates":[-3.6663589478,38.906791687],"type":"Point"}
}