{
  "type": "Feature",
  "properties": {
    "iso:country":"ES",
    "sg:address":"Pago Moralico, S/n",
    "sg:city":"Vera",
    "sg:orig_category":"Formaci\u00d3n Continuada (variada)",
    "sg:phone":"+34 950 39 07 45",
    "sg:postcode":"04620",
    "sg:province":"Almer\u00eda",
    "wof:name":"Centro Ocupacional Asprodalba",
    "wof:placetype":"venue"
},
  "geometry": {"coordinates":[-1.8724600077,37.2477874756],"type":"Point"}
}