{
  "type": "Feature",
  "properties": {
    "addr:full":"Pol Ind Cipreses, 10 Castello Plana Castell\u00f3n 12006",
    "addr:housenumber":"10",
    "addr:postcode":"12006",
    "addr:street":"Castello\u0301N",
    "iso:country":"ES",
    "sg:address":"Pol Ind Cipreses, 10",
    "sg:city":"Castello Plana",
    "sg:orig_category":"Cerrajer\u00cda, Ferrallista",
    "sg:phone":"+34 964 25 32 41",
    "sg:postcode":"12006",
    "sg:province":"Castell\u00f3n",
    "wof:name":"Javier Garcia Garriga S.l.",
    "wof:placetype":"venue"
},
  "geometry": {"coordinates":[-0.1292939931,40.0168533325],"type":"Point"}
}