{
  "type": "Feature",
  "properties": {
    "iso:country":"ES",
    "sg:address":"Carrer de Rectoria, 1",
    "sg:city":"Sant Feliu Llobregat",
    "sg:orig_category":"M\u00c9dicos: Pediatr\u00cda. Enfermedades De Los Ni\u00d1os",
    "sg:phone":"+34 936 66 08 94",
    "sg:postcode":"08980",
    "sg:province":"Barcelona",
    "wof:name":"Camarasa Piquer Federico",
    "wof:placetype":"venue"
},
  "geometry": {"coordinates":[2.045101881,41.3810844421],"type":"Point"}
}