{
  "type": "Feature",
  "properties": {
    "addr:full":"Calle de Jose Abascal, 61 Madrid Madrid 28003",
    "addr:housenumber":"61",
    "addr:postcode":"madrid;28003",
    "addr:street":"Calle De Jose Abascal",
    "iso:country":"ES",
    "sg:address":"Calle de Jose Abascal, 61",
    "sg:city":"Madrid",
    "sg:orig_category":"Promotores Constructores",
    "sg:phone":"+34 914 41 02 21",
    "sg:postcode":"28003",
    "sg:province":"Madrid",
    "wof:name":"Promociones Pe\u00f1a Grau S.a.",
    "wof:placetype":"venue"
},
  "geometry": {"coordinates":[-3.6922490597,40.4382362366],"type":"Point"}
}