{
  "type": "Feature",
  "properties": {
    "addr:full":"Avda Ciudad De Barcelona, 55 Madrid Madrid 28007",
    "addr:housenumber":"55",
    "addr:postcode":"madrid;28007",
    "addr:street":"Avda Ciudad De Barcelona",
    "iso:country":"ES",
    "sg:address":"Avda Ciudad De Barcelona, 55",
    "sg:city":"Madrid",
    "sg:orig_category":"\u00d3ptica: Instrumentos (fabricaci\u00d3n)",
    "sg:phone":"+34 914 33 58 51",
    "sg:postcode":"28007",
    "sg:province":"Madrid",
    "wof:name":"Guillo Sanchez S.l.",
    "wof:placetype":"venue"
},
  "geometry": {"coordinates":[-3.6771469116,40.4026412964],"type":"Point"}
}