{
  "type": "Feature",
  "properties": {
    "iso:country":"ES",
    "sg:address":"Calle de General Vives, 16",
    "sg:city":"Ponferrada",
    "sg:orig_category":"Ingeniero",
    "sg:phone":"+34 987 41 93 57",
    "sg:postcode":"24400",
    "sg:province":"Le\u00f3n",
    "wof:name":"Garcia Osorio Luis",
    "wof:placetype":"venue"
},
  "geometry": {"coordinates":[-6.5914788246,42.5467567444],"type":"Point"}
}