{
  "type": "Feature",
  "properties": {
    "iso:country":"ES",
    "sg:address":"Ctra. Torrijos, S/n",
    "sg:city":"S. Martin Montalban",
    "sg:orig_category":"Agricultores, Agricultores",
    "sg:phone":"+34 925 41 72 51",
    "sg:postcode":"45165",
    "sg:province":"Toledo",
    "wof:name":"Promociones Industriales Y Laborales Proinsa S.a.",
    "wof:placetype":"venue"
},
  "geometry": {"coordinates":[-4.3876738548,39.7027740479],"type":"Point"}
}