{
  "type": "Feature",
  "properties": {
    "addr:full":"Carr Victor Concas, 8 Estartit Girona 17258",
    "addr:housenumber":"8",
    "addr:postcode":"17258",
    "addr:street":"Carr Victor Concas",
    "iso:country":"ES",
    "sg:address":"Carr Victor Concas, 8",
    "sg:city":"Estartit",
    "sg:orig_category":"Bazares, Art\u00cdculos De Limpieza Y De Cocina (al Por Menor)",
    "sg:phone":"+34 972 75 13 77",
    "sg:postcode":"17258",
    "sg:province":"Girona",
    "wof:name":"Santamaria Arisso Jaime",
    "wof:placetype":"venue"
},
  "geometry": {"coordinates":[3.1878299713,42.0489959717],"type":"Point"}
}