{
  "type": "Feature",
  "properties": {
    "iso:country":"ES",
    "sg:address":"Ctra Cardona, 31",
    "sg:city":"Manresa",
    "sg:classifiers":[
        {
            "category":"Autos & Motor Vehicles",
            "subcategory":"Automobile Sales",
            "type":"Retail Goods"
        }
    ],
    "sg:phone":"+34 938 75 01 09",
    "sg:postcode":"08241",
    "sg:province":"Barcelona",
    "wof:name":"Autoescola Font S.l.",
    "wof:placetype":"venue"
},
  "geometry": {"coordinates":[1.8333090544,41.71434021],"type":"Point"}
}