{
  "type": "Feature",
  "properties": {
    "addr:full":"Calle de San Blas, 8 Alcorcon Madrid 28921",
    "addr:housenumber":"8",
    "addr:postcode":"28921",
    "addr:street":"Calle De San Blas",
    "iso:country":"ES",
    "sg:address":"Calle de San Blas, 8",
    "sg:city":"Alcorcon",
    "sg:orig_category":"Muebles, Minoristas",
    "sg:phone":"+34 916 43 22 75",
    "sg:postcode":"28921",
    "sg:province":"Madrid",
    "wof:name":"Decorbel Mobiliario S.l.",
    "wof:placetype":"venue"
},
  "geometry": {"coordinates":[-3.8249099255,40.3444023132],"type":"Point"}
}