{
  "type": "Feature",
  "properties": {
    "addr:full":"Ctr Santa Cruz, Km. 0007,0 Torrenueva Ciudad Real 13740",
    "addr:postcode":"13740",
    "addr:street":"Santa Cruz Km. 0007,0",
    "iso:country":"ES",
    "sg:address":"Ctr Santa Cruz, Km. 0007,0",
    "sg:city":"Torrenueva",
    "sg:orig_category":"Empresas De Carpinter\u00cda Met\u00c1lica",
    "sg:phone":"+34 926 34 15 29",
    "sg:postcode":"13740",
    "sg:province":"Ciudad Real",
    "wof:name":"Taller Laguna Prada S.l",
    "wof:placetype":"venue"
},
  "geometry": {"coordinates":[-3.3627440929,38.6430053711],"type":"Point"}
}