{
  "type": "Feature",
  "properties": {
    "addr:full":"Barr San Ramon, 12 Corrales Cantabria 39400",
    "addr:housenumber":"12",
    "addr:postcode":"39400",
    "addr:street":"San Ramon",
    "iso:country":"ES",
    "sg:address":"Barr San Ramon, 12",
    "sg:city":"Corrales",
    "sg:orig_category":"Alimentaci\u00d3n General (al Por Menor)",
    "sg:phone":"+34 942 83 13 92",
    "sg:postcode":"39400",
    "sg:province":"Cantabria",
    "wof:name":"Gonzalez Santandres Paulino",
    "wof:placetype":"venue"
},
  "geometry": {"coordinates":[-4.0666542053,43.2560577393],"type":"Point"}
}