{
  "type": "Feature",
  "properties": {
    "iso:country":"ES",
    "sg:address":"Carrer de Bonaire, 2",
    "sg:city":"Arenys Mar",
    "sg:orig_category":"Bibliotecas, Mediatecas",
    "sg:phone":"+34 937 92 32 53",
    "sg:postcode":"08350",
    "sg:province":"Barcelona",
    "wof:name":"Ajuntament D'arenys De Mar",
    "wof:placetype":"venue"
},
  "geometry": {"coordinates":[2.5491406918,41.5802116394],"type":"Point"}
}