{
  "type": "Feature",
  "properties": {
    "iso:country":"ES",
    "sg:address":"Calle de Alfonso X El Sabio, 3",
    "sg:city":"Parla",
    "sg:orig_category":"Asociaciones Humanitarias, De Cooperaci\u00d3n, De Acci\u00d3n Social",
    "sg:phone":"+34 916 98 43 57",
    "sg:postcode":"28980",
    "sg:province":"Madrid",
    "wof:name":"Asociacion Reto A La Esperanza",
    "wof:placetype":"venue"
},
  "geometry": {"coordinates":[-3.7694284916,40.2360305786],"type":"Point"}
}