{
  "type": "Feature",
  "properties": {
    "addr:full":"Av Jaume Iii, 4 Palma Islas Baleares 07012",
    "addr:housenumber":"4",
    "addr:postcode":"07012",
    "addr:street":"Av Jaume Iii",
    "iso:country":"ES",
    "sg:address":"Av Jaume Iii, 4",
    "sg:city":"Palma",
    "sg:orig_category":"Ropa Para Se\u00d1oras Y Caballeros (al Por Menor)",
    "sg:phone":"+34 971 71 20 43",
    "sg:postcode":"07012",
    "sg:province":"Islas Baleares",
    "wof:name":"Difusioni Turzi International S.l.",
    "wof:placetype":"venue"
},
  "geometry": {"coordinates":[2.6464118958,39.5717010498],"type":"Point"}
}