{
  "type": "Feature",
  "properties": {
    "addr:full":"Avda Aizpuru, General, 4 Melilla Melilla 52004",
    "addr:housenumber":"4",
    "addr:postcode":"52004",
    "addr:street":"Avda Aizpuru General",
    "iso:country":"ES",
    "sg:address":"Avda Aizpuru, General, 4",
    "sg:city":"Melilla",
    "sg:orig_category":"Formaci\u00d3n Continuada (variada)",
    "sg:phone":"+34 952 67 97 83",
    "sg:postcode":"52004",
    "sg:province":"Melilla",
    "wof:name":"Alonso Sanchez Jose",
    "wof:placetype":"venue"
},
  "geometry": {"coordinates":[-2.9436631203,35.2901420593],"type":"Point"}
}