{
  "type": "Feature",
  "properties": {
    "iso:country":"ES",
    "sg:address":"Calle de Pedro Laborde, 49",
    "sg:city":"Madrid",
    "sg:orig_category":"Electrodom\u00c9sticos (al Por Menor)",
    "sg:phone":"+34 913 03 94 67",
    "sg:postcode":"28018",
    "sg:province":"Madrid",
    "wof:name":"Reimar Disa S.l.",
    "wof:placetype":"venue"
},
  "geometry": {"coordinates":[-3.6490740776,40.3870315552],"type":"Point"}
}