{
  "type": "Feature",
  "properties": {
    "addr:full":"Calle de Ancha, 22 Vera Almer\u00eda 04620",
    "addr:housenumber":"22;almeri\u0301a",
    "addr:postcode":"04620",
    "addr:street":"Calle De Ancha",
    "iso:country":"ES",
    "sg:address":"Calle de Ancha, 22",
    "sg:city":"Vera",
    "sg:orig_category":"Fabricaci\u00d3n De Juguetes Autom\u00c1ticos",
    "sg:phone":"+34 950 39 16 58",
    "sg:postcode":"04620",
    "sg:province":"Almer\u00eda",
    "wof:name":"Veramatic S.l.",
    "wof:placetype":"venue"
},
  "geometry": {"coordinates":[-1.8727940321,37.249546051],"type":"Point"}
}