{
  "type": "Feature",
  "properties": {
    "iso:country":"ES",
    "sg:address":"Calle de Santander, 8",
    "sg:city":"Castro Urdiales",
    "sg:orig_category":"Herboristas (al Por Menor)",
    "sg:phone":"+34 942 86 33 47",
    "sg:postcode":"39700",
    "sg:province":"Cantabria",
    "wof:name":"Cobo Pinto Ernesto",
    "wof:placetype":"venue"
},
  "geometry": {"coordinates":[-3.2193350792,43.3832435608],"type":"Point"}
}