{
  "type": "Feature",
  "properties": {
    "iso:country":"ES",
    "sg:address":"Avda Lepanto, 15",
    "sg:city":"Albox",
    "sg:orig_category":"Maquinaria Para Industrias Diversas",
    "sg:phone":"+34 950 12 19 12",
    "sg:postcode":"04800",
    "sg:province":"Almer\u00eda",
    "wof:name":"Taller Los Berbeles S.l.",
    "wof:placetype":"venue"
},
  "geometry": {"coordinates":[-2.1385769844,37.3846206665],"type":"Point"}
}