{
  "type": "Feature",
  "properties": {
    "addr:full":"Calle de Salvador Allende, S/n Vall D'uixo Castell\u00f3n 12600",
    "addr:postcode":"12600",
    "addr:street":"Calle De Salvador Allende S / N",
    "iso:country":"ES",
    "sg:address":"Calle de Salvador Allende, S/n",
    "sg:city":"Vall D'uixo",
    "sg:orig_category":"Caf\u00c9s, Bares, Cervecer\u00cdas",
    "sg:phone":"+34 964 66 30 14",
    "sg:postcode":"12600",
    "sg:province":"Castell\u00f3n",
    "wof:name":"Aguilar Tido Jose Vicente",
    "wof:placetype":"venue"
},
  "geometry": {"coordinates":[-0.2313933969,39.8212165833],"type":"Point"}
}