{
  "type": "Feature",
  "properties": {
    "iso:country":"ES",
    "sg:address":"Avda Barrie De La Maza, 13",
    "sg:city":"Sada",
    "sg:orig_category":"Bisuter\u00cda, Joyer\u00cda, Relojer\u00cda (al Por Menor)",
    "sg:phone":"+34 981 62 08 65",
    "sg:postcode":"15160",
    "sg:province":"La Coru\u00f1a",
    "wof:name":"Sadajoya S.l.",
    "wof:placetype":"venue"
},
  "geometry": {"coordinates":[-8.2546482086,43.3509254456],"type":"Point"}
}