{
  "type": "Feature",
  "properties": {
    "addr:full":"Praz Eugenio Fadrique, 8 Vigo Pontevedra 36208",
    "addr:housenumber":"8",
    "addr:postcode":"36208",
    "addr:street":"Praz Eugenio Fadrique",
    "iso:country":"ES",
    "sg:address":"Praz Eugenio Fadrique, 8",
    "sg:city":"Vigo",
    "sg:orig_category":"Arquitectos",
    "sg:phone":"+34 986 20 82 78",
    "sg:postcode":"36208",
    "sg:province":"Pontevedra",
    "wof:name":"Fernandez Fernandez Juan Antonio",
    "wof:placetype":"venue"
},
  "geometry": {"coordinates":[-8.7359342575,42.224395752],"type":"Point"}
}