{
  "type": "Feature",
  "properties": {
    "iso:country":"ES",
    "sg:address":"Calle de Carreras, 6",
    "sg:city":"Montijo",
    "sg:orig_category":"Ense\u00d1anza: Comercio, Gesti\u00d3n, Inform\u00c1tica",
    "sg:phone":"+34 924 45 25 75",
    "sg:postcode":"06480",
    "sg:province":"Badajoz",
    "wof:name":"Abc Formacion Montijo S.l.",
    "wof:placetype":"venue"
},
  "geometry": {"coordinates":[-6.61601,38.907475],"type":"Point"}
}