{
  "type": "Feature",
  "properties": {
    "addr:full":"Calle de Garcia De Qui\u00d1ones, 2 Salamanca Salamanca 37005",
    "addr:housenumber":"2",
    "addr:postcode":"37005",
    "addr:street":"Calle De Garcia De Quin\u0303Ones",
    "iso:country":"ES",
    "sg:address":"Calle de Garcia De Qui\u00d1ones, 2",
    "sg:city":"Salamanca",
    "sg:orig_category":"Producci\u00d3n, Distribuci\u00d3n De Gas Butano Y Propano",
    "sg:phone":"+34 923 22 22 00",
    "sg:postcode":"37005",
    "sg:province":"Salamanca",
    "wof:name":"Butano Salamanca S.l",
    "wof:placetype":"venue"
},
  "geometry": {"coordinates":[-5.6619157791,40.9704971313],"type":"Point"}
}