{
  "type": "Feature",
  "properties": {
    "iso:country":"ES",
    "sg:address":"Plaz Mercado, 2",
    "sg:city":"Salamanca",
    "sg:orig_category":"Lencer\u00cda Femenina, Corseter\u00cda, Trajes De Ba\u00d1o (al Por Menor)",
    "sg:phone":"+34 923 21 61 13",
    "sg:postcode":"37001",
    "sg:province":"Salamanca",
    "wof:name":"Feldy S. A.",
    "wof:placetype":"venue"
},
  "geometry": {"coordinates":[-5.6632199287,40.9650001526],"type":"Point"}
}