{
  "type": "Feature",
  "properties": {
    "addr:full":"Matodoso, S/n Triaba Lugo 27267",
    "addr:postcode":"27267",
    "addr:street":"Matodoso S / N",
    "iso:country":"ES",
    "sg:address":"Matodoso, S/n",
    "sg:city":"Triaba",
    "sg:orig_category":"Agricultura: Abastecimiento Y Cosechado (negocio)",
    "sg:phone":"+34 982 31 02 54",
    "sg:postcode":"27267",
    "sg:province":"Lugo",
    "wof:name":"Cooperativa Del Campo Tierra Llana",
    "wof:placetype":"venue"
},
  "geometry": {"coordinates":[-7.5376391411,43.1623458862],"type":"Point"}
}