{
  "type": "Feature",
  "properties": {
    "addr:full":"Poligono Industrial Boch, 249 Poligono Industrial Boch Alicante 03330",
    "addr:housenumber":"249",
    "addr:postcode":"03330",
    "addr:street":"Industrial Boch;Industrial;Alicante",
    "iso:country":"ES",
    "sg:address":"Poligono Industrial Boch, 249",
    "sg:city":"Poligono Industrial Boch",
    "sg:orig_category":"Confecci\u00d3n De Zapatos",
    "sg:phone":"+34 965 40 32 38",
    "sg:postcode":"03330",
    "sg:province":"Alicante",
    "wof:name":"Marna Shoes 2000 S.l.",
    "wof:placetype":"venue"
},
  "geometry": {"coordinates":[-0.8056010008,38.241355896],"type":"Point"}
}