{
  "type": "Feature",
  "properties": {
    "addr:full":"Calle de Rodriguez Acosta, 31 Port D'andratx Islas Baleares 07157",
    "addr:housenumber":"31",
    "addr:postcode":"07157",
    "addr:street":"Calle De Rodriguez Acosta",
    "iso:country":"ES",
    "sg:address":"Calle de Rodriguez Acosta, 31",
    "sg:city":"Port D'andratx",
    "sg:orig_category":"Quincaller\u00cda (al Por Menor)",
    "sg:phone":"+34 971 67 24 90",
    "sg:postcode":"07157",
    "sg:province":"Islas Baleares",
    "wof:name":"Ferreteria Seguina C.b.",
    "wof:placetype":"venue"
},
  "geometry": {"coordinates":[2.9117100239,39.6136398315],"type":"Point"}
}