{
  "type": "Feature",
  "properties": {
    "iso:country":"ES",
    "sg:address":"Rua Irida, 9",
    "sg:city":"Estrada",
    "sg:orig_category":"Asesor\u00cda Fiscal Y Jur\u00cddica",
    "sg:phone":"+34 986 57 37 31",
    "sg:postcode":"36680",
    "sg:province":"Pontevedra",
    "wof:name":"Blanco Rivadulla Maria Elvira",
    "wof:placetype":"venue"
},
  "geometry": {"coordinates":[-8.4910736084,42.6887664795],"type":"Point"}
}