{
  "type": "Feature",
  "properties": {
    "iso:country":"ES",
    "sg:address":"Calle de Lobero, 36",
    "sg:city":"Ejido",
    "sg:orig_category":"Papeler\u00cdas, Librer\u00cdas",
    "sg:phone":"+34 950 48 11 38",
    "sg:postcode":"04700",
    "sg:province":"Almer\u00eda",
    "wof:name":"Olvera Fuentes Florencio",
    "wof:placetype":"venue"
},
  "geometry": {"coordinates":[-2.8133790493,36.7746658325],"type":"Point"}
}