{
  "type": "Feature",
  "properties": {
    "iso:country":"ES",
    "sg:address":"Calle de Kale Nagusia, 36",
    "sg:city":"Segura",
    "sg:orig_category":"Hospitales",
    "sg:phone":"+34 943 80 10 08",
    "sg:postcode":"20214",
    "sg:province":"Guip\u00f9zcoa",
    "wof:name":"Gestion Servicios Residenciales S.c.l.",
    "wof:placetype":"venue"
},
  "geometry": {"coordinates":[-2.2536559105,43.0088729858],"type":"Point"}
}