{
  "type": "Feature",
  "properties": {
    "addr:full":"Rond Buganvilla Del Rey, 130 Madrid Madrid 28023",
    "addr:housenumber":"130",
    "addr:postcode":"28023",
    "addr:street":"Rey",
    "iso:country":"ES",
    "sg:address":"Rond Buganvilla Del Rey, 130",
    "sg:city":"Madrid",
    "sg:orig_category":"Financiaci\u00d3n Y Cr\u00c9ditos",
    "sg:phone":"+34 917 40 02 80",
    "sg:postcode":"28023",
    "sg:province":"Madrid",
    "wof:name":"R2 Financial Services S.l.",
    "wof:placetype":"venue"
},
  "geometry": {"coordinates":[-3.7664880753,40.4557609558],"type":"Point"}
}