{
  "type": "Feature",
  "properties": {
    "iso:country":"ES",
    "sg:address":"Calle de Poeta Miguel Hernandez, 1",
    "sg:city":"Puente Tocinos",
    "sg:orig_category":"Panader\u00cdas, Panader\u00cdas",
    "sg:phone":"+34 968 30 30 16",
    "sg:postcode":"30006",
    "sg:province":"Murcia",
    "wof:name":"Sanchez Bueno Eva Maria",
    "wof:placetype":"venue"
},
  "geometry": {"coordinates":[-1.1013799906,37.9940109253],"type":"Point"}
}