{
  "type": "Feature",
  "properties": {
    "iso:country":"ES",
    "sg:address":"Calle de Higueras, 63",
    "sg:city":"Madrid",
    "sg:orig_category":"Caf\u00c9s, Bares, Cervecer\u00cdas",
    "sg:phone":"+34 914 63 44 85",
    "sg:postcode":"28047",
    "sg:province":"Madrid",
    "wof:name":"Perez Robles Narciso",
    "wof:placetype":"venue"
},
  "geometry": {"coordinates":[-3.7454164028,40.4028892517],"type":"Point"}
}