{
  "type": "Feature",
  "properties": {
    "addr:full":"Cno. Morales, S/n Brunete Madrid 28690",
    "addr:housenumber":"s / n",
    "addr:postcode":"28690",
    "addr:street":"Cno. Morales",
    "iso:country":"ES",
    "sg:address":"Cno. Morales, S/n",
    "sg:city":"Brunete",
    "sg:orig_category":"Ense\u00d1anza, Formaci\u00d3n Profesional: Aprendizaje",
    "sg:phone":"+34 918 15 83 96",
    "sg:postcode":"28690",
    "sg:province":"Madrid",
    "wof:name":"T.p. Servicios Integrales De Proteccion Civil S.a.",
    "wof:placetype":"venue"
},
  "geometry": {"coordinates":[-4.0294880867,40.4102516174],"type":"Point"}
}