{
  "type": "Feature",
  "properties": {
    "iso:country":"ES",
    "sg:address":"Carrer de Sant Pere (de), 8",
    "sg:city":"Tortosa",
    "sg:orig_category":"Molduras, Junquillos, Listones Y Molduras Perforadas",
    "sg:phone":"+34 977 44 10 44",
    "sg:postcode":"43500",
    "sg:province":"Tarragona",
    "wof:name":"Lozano Martin Florencio",
    "wof:placetype":"venue"
},
  "geometry": {"coordinates":[0.5203099847,40.8104133606],"type":"Point"}
}