{
  "type": "Feature",
  "properties": {
    "iso:country":"ES",
    "sg:address":"Calle de Almirante Ferrandiz, 29",
    "sg:city":"Nerja",
    "sg:orig_category":"Abogados",
    "sg:phone":"+34 952 52 18 12",
    "sg:postcode":"29780",
    "sg:province":"M\u00e1laga",
    "wof:name":"Olmedo Hurtado Jose Luis",
    "wof:placetype":"venue"
},
  "geometry": {"coordinates":[-3.8755540848,36.7468299866],"type":"Point"}
}