{
  "type": "Feature",
  "properties": {
    "addr:full":"Ctra Cadiz-barcelona Cn-340, Km. 0027,3 Sagunt Valencia 46500",
    "addr:postcode":"46500",
    "addr:street":"Ctra Cadiz-Barcelona Cn-340 Km. 0027,3",
    "iso:country":"ES",
    "sg:address":"Ctra Cadiz-barcelona Cn-340, Km. 0027,3",
    "sg:city":"Sagunt",
    "sg:orig_category":"Agentes, Concesionarios Y Sucursales De Veh\u00cdculos",
    "sg:phone":"+34 962 65 57 45",
    "sg:postcode":"46500",
    "sg:province":"Valencia",
    "sg:website":"www.autoval.es",
    "wof:name":"Autoval S.a.",
    "wof:placetype":"venue"
},
  "geometry": {"coordinates":[-0.2713944018,39.6824607849],"type":"Point"}
}