{
  "type": "Feature",
  "properties": {
    "iso:country":"ES",
    "sg:address":"Pg Maritim, 619",
    "sg:city":"Castelldefels",
    "sg:orig_category":"Asesor\u00cda De Comercio Exterior",
    "sg:phone":"+34 936 64 75 00",
    "sg:postcode":"08860",
    "sg:province":"Barcelona",
    "wof:name":"Maciblanc S.l.",
    "wof:placetype":"venue"
},
  "geometry": {"coordinates":[1.9576510191,41.2654495239],"type":"Point"}
}