{
  "type": "Feature",
  "properties": {
    "addr:full":"Calle de Francisco Amado, 12 Guadiaro C\u00e1diz 11311",
    "addr:housenumber":"12",
    "addr:postcode":"11311",
    "addr:street":"Calle De Francisco Amado;Ca\u0301Diz",
    "iso:country":"ES",
    "sg:address":"Calle de Francisco Amado, 12",
    "sg:city":"Guadiaro",
    "sg:orig_category":"Bebidas",
    "sg:phone":"+34 956 61 41 83",
    "sg:postcode":"11311",
    "sg:province":"C\u00e1diz",
    "wof:name":"Ciro Cb.",
    "wof:placetype":"venue"
},
  "geometry": {"coordinates":[-5.3023438454,36.299911499],"type":"Point"}
}