{
  "type": "Feature",
  "properties": {
    "iso:country":"ES",
    "sg:address":"Portal De Gamarra Carrer de Carrer de Boulevard, 21",
    "sg:city":"Vitoria-gasteiz",
    "sg:orig_category":"Serigraf\u00cda (material Y Suministros)",
    "sg:phone":"+34 945 25 17 04",
    "sg:postcode":"01013",
    "sg:province":"\u00c1lava",
    "wof:name":"Forjas Y Estampaciones Indar, S,a,",
    "wof:placetype":"venue"
},
  "geometry": {"coordinates":[-2.6840889454,42.8761367798],"type":"Point"}
}