{
  "type": "Feature",
  "properties": {
    "iso:country":"ES",
    "sg:address":"Campo, 10",
    "sg:city":"Campo",
    "sg:orig_category":"Ingeniero",
    "sg:phone":"+34 986 54 83 09",
    "sg:postcode":"36679",
    "sg:province":"Pontevedra",
    "wof:name":"Constenla Pego Jose",
    "wof:placetype":"venue"
},
  "geometry": {"coordinates":[-8.5949983597,42.6398010254],"type":"Point"}
}