{
  "type": "Feature",
  "properties": {
    "addr:full":"Calle de David Herrero, 16 Avila \u00c1vila 05005",
    "addr:housenumber":"16",
    "addr:postcode":"05005",
    "addr:street":"Calle De David Herrero;A\u0301Vila",
    "iso:country":"ES",
    "sg:address":"Calle de David Herrero, 16",
    "sg:city":"Avila",
    "sg:orig_category":"Centros De Educaci\u00d3n Especial",
    "sg:phone":"+34 920 22 21 37",
    "sg:postcode":"05005",
    "sg:province":"\u00c1vila",
    "wof:name":"Colegio Publico Reina Fabiola-m Educacion Ciencia",
    "wof:placetype":"venue"
},
  "geometry": {"coordinates":[-4.6903691292,40.6597747803],"type":"Point"}
}