{
  "type": "Feature",
  "properties": {
    "addr:full":"Ctra. Valmojado, 22 Cedillo Condado Toledo 45214",
    "addr:housenumber":"22",
    "addr:postcode":"45214",
    "addr:street":"Ctra. Valmojado",
    "iso:country":"ES",
    "sg:address":"Ctra. Valmojado, 22",
    "sg:city":"Cedillo Condado",
    "sg:orig_category":"Fabricaci\u00d3n, Importaci\u00d3n, Venta De Material De Telefon\u00cda, Peritelefon\u00cda",
    "sg:phone":"+34 925 50 85 60",
    "sg:postcode":"45214",
    "sg:province":"Toledo",
    "wof:name":"J R V Navaltelecom S.l.",
    "wof:placetype":"venue"
},
  "geometry": {"coordinates":[-3.9311089516,40.1178207397],"type":"Point"}
}