{
  "type": "Feature",
  "properties": {
    "iso:country":"ES",
    "sg:address":"Calle de Nuestro Padre Jesus, 27",
    "sg:city":"Cantillana",
    "sg:orig_category":"Cajas De Ahorro",
    "sg:phone":"+34 955 73 29 20",
    "sg:postcode":"41320",
    "sg:province":"Sevilla",
    "sg:website":"www.elmonte.es",
    "wof:name":"Monte De Piedad Y Caja De Ahorros De Huelva Y Sevilla",
    "wof:placetype":"venue"
},
  "geometry": {"coordinates":[-5.8256821632,37.6096000671],"type":"Point"}
}