{
  "type": "Feature",
  "properties": {
    "iso:country":"ES",
    "sg:address":"Carrer de Aribau, 160",
    "sg:city":"Barcelona",
    "sg:classifiers":[
        {
            "category":"Personal",
            "subcategory":"Barber",
            "type":"Services"
        }
    ],
    "sg:phone":"+34 932 18 07 31",
    "sg:postcode":"08036",
    "sg:province":"Barcelona",
    "sg:tags":[
        "caballeros",
        "de",
        "peluqueros"
    ],
    "wof:name":"Palos Domingo Jaime",
    "wof:placetype":"venue"
},
  "geometry": {"coordinates":[2.1542370319,41.39245224],"type":"Point"}
}