{
  "type": "Feature",
  "properties": {
    "iso:country":"ES",
    "sg:address":"Calle de Real, 78",
    "sg:city":"Valdepe\u00f1as",
    "sg:orig_category":"Productores Recolectores, Venta Directa De Vinos",
    "sg:phone":"+34 926 32 33 54",
    "sg:postcode":"13300",
    "sg:province":"Ciudad Real",
    "wof:name":"Hermanos Navarro Racimo De Oro",
    "wof:placetype":"venue"
},
  "geometry": {"coordinates":[-3.3830590248,38.7638626099],"type":"Point"}
}