{
  "type": "Feature",
  "properties": {
    "addr:full":"Pl Tortosa, S/n Camarles Tarragona 43894",
    "addr:housenumber":"s",
    "addr:postcode":"43894",
    "addr:street":"Pl Tortosa;/ N",
    "iso:country":"ES",
    "sg:address":"Pl Tortosa, S/n",
    "sg:city":"Camarles",
    "sg:orig_category":"Iglesia Cat\u00d3lica",
    "sg:phone":"+34 977 47 00 41",
    "sg:postcode":"43894",
    "sg:province":"Tarragona",
    "wof:name":"Bisbat De Tortosa",
    "wof:placetype":"venue"
},
  "geometry": {"coordinates":[0.669475019,40.7720489502],"type":"Point"}
}