{
  "type": "Feature",
  "properties": {
    "addr:full":"Carrer de Ramon Y Cajal, 8 Barcelona Barcelona 08012",
    "addr:housenumber":"8",
    "addr:postcode":"08012",
    "addr:street":"Carrer De Ramon Y Cajal",
    "iso:country":"ES",
    "sg:address":"Carrer de Ramon Y Cajal, 8",
    "sg:city":"Barcelona",
    "sg:orig_category":"Compraventa De Antig\u00dcedades",
    "sg:phone":"+34 932 10 67 91",
    "sg:postcode":"08012",
    "sg:province":"Barcelona",
    "wof:name":"Rouse Valls Benet",
    "wof:placetype":"venue"
},
  "geometry": {"coordinates":[2.1579120159,41.4019851685],"type":"Point"}
}