{
  "type": "Feature",
  "properties": {
    "iso:country":"ES",
    "sg:address":"Calle de Real, 69",
    "sg:city":"Tamaimo",
    "sg:orig_category":"Organizaciones Internacionales",
    "sg:phone":"+34 922 86 36 87",
    "sg:postcode":"38684",
    "sg:province":"Santa Cruz De Tenerife",
    "wof:name":"Cruz Roja Espa\u00f1ola",
    "wof:placetype":"venue"
},
  "geometry": {"coordinates":[-16.8193664551,28.2707901001],"type":"Point"}
}