{
  "type": "Feature",
  "properties": {
    "iso:country":"ES",
    "sg:address":"Pla\u00c7 Palmera, 8",
    "sg:city":"Figueres",
    "sg:orig_category":"Cajas De Ahorro",
    "sg:phone":"+34 972 51 39 07",
    "sg:postcode":"17600",
    "sg:province":"Girona",
    "wof:name":"Caja De Ahorros De Valencia Castellon Y Alicante",
    "wof:placetype":"venue"
},
  "geometry": {"coordinates":[2.9641590118,42.2671051025],"type":"Point"}
}