{
  "type": "Feature",
  "properties": {
    "iso:country":"ES",
    "sg:address":"Cra. Coll De Nargo, 65",
    "sg:city":"Isona",
    "sg:orig_category":"Supermercados Y Hipermercados",
    "sg:phone":"+34 973 66 43 77",
    "sg:postcode":"25650",
    "sg:province":"Lleida",
    "wof:name":"Amoa Scp",
    "wof:placetype":"venue"
},
  "geometry": {"coordinates":[1.0298918486,42.1230201721],"type":"Point"}
}