{
  "type": "Feature",
  "properties": {
    "iso:country":"ES",
    "sg:address":"Bard Marchena, S/n",
    "sg:city":"Marchena",
    "sg:orig_category":"Mec\u00c1nico Del Autom\u00d3vil",
    "sg:phone":"+34 958 78 02 67",
    "sg:postcode":"18650",
    "sg:province":"Granada",
    "wof:name":"Auto Famelsa S.l.",
    "wof:placetype":"venue"
},
  "geometry": {"coordinates":[-3.5833339691,37.0051193237],"type":"Point"}
}