{
  "type": "Feature",
  "properties": {
    "iso:country":"ES",
    "sg:address":"Avda Nuestra Se\u00d1ora Del Pilar, 7",
    "sg:city":"Binefar",
    "sg:orig_category":"Molduras, Junquillos, Listones Y Molduras Perforadas",
    "sg:phone":"+34 974 42 80 04",
    "sg:postcode":"22500",
    "sg:province":"Huesca",
    "wof:name":"Cierco Castan Cesar",
    "wof:placetype":"venue"
},
  "geometry": {"coordinates":[0.2923989892,41.8516235352],"type":"Point"}
}