{
  "type": "Feature",
  "properties": {
    "addr:full":"Bo Reocin, S/n Reocin Cantabria 39538",
    "addr:housenumber":"s",
    "addr:postcode":"39538",
    "addr:street":"/ N",
    "iso:country":"ES",
    "sg:address":"Bo Reocin, S/n",
    "sg:city":"Reocin",
    "sg:orig_category":"Explotaci\u00d3n De Minas",
    "sg:phone":"+34 942 83 83 67",
    "sg:postcode":"39538",
    "sg:province":"Cantabria",
    "wof:name":"Asturiana De Zinc S.a.",
    "wof:placetype":"venue"
},
  "geometry": {"coordinates":[-4.1002168655,43.3430023193],"type":"Point"}
}