{
  "type": "Feature",
  "properties": {
    "iso:country":"ES",
    "sg:address":"Calle de Merida, 7",
    "sg:city":"Burgos",
    "sg:orig_category":"Quincaller\u00cda (al Por Menor)",
    "sg:phone":"+34 947 48 64 94",
    "sg:postcode":"09007",
    "sg:province":"Burgos",
    "wof:name":"Gonzalez Delgado Gregorio",
    "wof:placetype":"venue"
},
  "geometry": {"coordinates":[-3.6542019844,42.3630447388],"type":"Point"}
}