{
  "type": "Feature",
  "properties": {
    "addr:full":"Calle de Mayor, 71 Alcorcon Madrid 28922",
    "addr:housenumber":"71",
    "addr:postcode":"28922",
    "addr:street":"Calle De Mayor",
    "iso:country":"ES",
    "sg:address":"Calle de Mayor, 71",
    "sg:city":"Alcorcon",
    "sg:orig_category":"Frutas, Legumbres Frescas Y Tempranas (al Por Menor)",
    "sg:phone":"+34 916 43 21 49",
    "sg:postcode":"28922",
    "sg:province":"Madrid",
    "wof:name":"Gimenez Velardiez Miguel Agustin",
    "wof:placetype":"venue"
},
  "geometry": {"coordinates":[-3.8274230957,40.3448829651],"type":"Point"}
}