{
  "type": "Feature",
  "properties": {
    "iso:country":"ES",
    "sg:address":"Severo Ochoa, 3",
    "sg:city":"Parque Empresarial",
    "sg:orig_category":"Fabricaci\u00d3n De Sobres, Bolsas Y Fundas",
    "sg:phone":"+34 916 30 93 51",
    "sg:postcode":"28232",
    "sg:province":"Madrid",
    "wof:name":"Sistemas Kern S.a.",
    "wof:placetype":"venue"
},
  "geometry": {"coordinates":[-3.8983619213,40.5216598511],"type":"Point"}
}