{
  "type": "Feature",
  "properties": {
    "iso:country":"ES",
    "sg:address":"Calle de Luchana, 17",
    "sg:city":"Palmas De Gran Canaria",
    "sg:orig_category":"Material Y Suministros Para Veterinarios",
    "sg:phone":"+34 928 27 74 06",
    "sg:postcode":"35010",
    "sg:province":"Las Palmas",
    "wof:name":"Arvi S.c.p.",
    "wof:placetype":"venue"
},
  "geometry": {"coordinates":[-15.4431266785,28.1279201508],"type":"Point"}
}