{
  "type": "Feature",
  "properties": {
    "addr:full":"Calle de Vega (la), 2 Martiherrero \u00c1vila 05140",
    "addr:housenumber":"2",
    "addr:postcode":"05140",
    "addr:street":"Calle De Vega La;A\u0301Vila",
    "iso:country":"ES",
    "sg:address":"Calle de Vega (la), 2",
    "sg:city":"Martiherrero",
    "sg:orig_category":"Restaurantes",
    "sg:phone":"+34 920 26 94 03",
    "sg:postcode":"05140",
    "sg:province":"\u00c1vila",
    "wof:name":"Casillas Herraez Agustin",
    "wof:placetype":"venue"
},
  "geometry": {"coordinates":[-4.7780070305,40.6733398438],"type":"Point"}
}