{
  "type": "Feature",
  "properties": {
    "iso:country":"ES",
    "sg:address":"Calle de Feria, 9",
    "sg:city":"Solana",
    "sg:orig_category":"T\u00c9cnicos Veterinarios",
    "sg:phone":"+34 926 63 11 48",
    "sg:postcode":"13240",
    "sg:province":"Ciudad Real",
    "wof:name":"Velasco Morales Silvestre",
    "wof:placetype":"venue"
},
  "geometry": {"coordinates":[-3.2379970551,38.9428787231],"type":"Point"}
}