{
  "type": "Feature",
  "properties": {
    "addr:full":"Carrer de Valencia, 460 Barcelona Barcelona 08013",
    "addr:housenumber":"460",
    "addr:postcode":"08013",
    "addr:street":"Carrer De Valencia",
    "iso:country":"ES",
    "sg:address":"Carrer de Valencia, 460",
    "sg:city":"Barcelona",
    "sg:orig_category":"Asesor\u00cda, Estudio Y Control Medioambiental",
    "sg:phone":"+34 932 45 04 72",
    "sg:postcode":"08013",
    "sg:province":"Barcelona",
    "wof:name":"Adedma Consulturia I Serveis S.l.",
    "wof:placetype":"venue"
},
  "geometry": {"coordinates":[2.1772685051,41.4031639099],"type":"Point"}
}