{
  "type": "Feature",
  "properties": {
    "iso:country":"ES",
    "sg:address":"Carrer de Cala Tuent, 5",
    "sg:city":"Palma",
    "sg:orig_category":"Ense\u00d1anza: Profesiones Art\u00cdsticas",
    "sg:phone":"+34 971 47 48 28",
    "sg:postcode":"07009",
    "sg:province":"Islas Baleares",
    "wof:name":"Recursos Didacticos, S.l.",
    "wof:placetype":"venue"
},
  "geometry": {"coordinates":[2.6767120361,39.5975074768],"type":"Point"}
}