{
  "type": "Feature",
  "properties": {
    "addr:full":"Calle de Lago Constanza, 90 Madrid Madrid 28017",
    "addr:housenumber":"90",
    "addr:postcode":"madrid;28017",
    "addr:street":"Calle De Lago Constanza",
    "iso:country":"ES",
    "sg:address":"Calle de Lago Constanza, 90",
    "sg:city":"Madrid",
    "sg:orig_category":"Promotores Constructores",
    "sg:phone":"+34 914 07 87 57",
    "sg:postcode":"28017",
    "sg:province":"Madrid",
    "wof:name":"Gonzalez Ayuso Valeriana",
    "wof:placetype":"venue"
},
  "geometry": {"coordinates":[-3.6458721161,40.4282417297],"type":"Point"}
}