{
  "type": "Feature",
  "properties": {
    "addr:full":"Ctra. Burgos Portugal, Km. 0005,7 Villagonzalo-pedernales Burgos 09195",
    "addr:postcode":"09195",
    "addr:street":"Ctra. Burgos Portugal Km. 0005,7 Villagonzalo-Pedernales",
    "iso:country":"ES",
    "sg:address":"Ctra. Burgos Portugal, Km. 0005,7",
    "sg:city":"Villagonzalo-pedernales",
    "sg:orig_category":"Distribuci\u00d3n De Petr\u00d3leo Y Derivados",
    "sg:phone":"+34 947 29 42 57",
    "sg:postcode":"09195",
    "sg:province":"Burgos",
    "wof:name":"Hermela S.a.",
    "wof:placetype":"venue"
},
  "geometry": {"coordinates":[-3.7549920082,42.2654838562],"type":"Point"}
}