{
  "type": "Feature",
  "properties": {
    "addr:full":"Calle de Granados, 19 Almoradi Alicante 03160",
    "addr:housenumber":"19",
    "addr:postcode":"03160",
    "addr:street":"Calle De Granados",
    "iso:country":"ES",
    "sg:address":"Calle de Granados, 19",
    "sg:city":"Almoradi",
    "sg:orig_category":"Promotores Constructores",
    "sg:phone":"+34 965 70 26 44",
    "sg:postcode":"03160",
    "sg:province":"Alicante",
    "wof:name":"Promociones Algo-sol Mediterraneo S.l.",
    "wof:placetype":"venue"
},
  "geometry": {"coordinates":[-0.7951490283,38.1133499146],"type":"Point"}
}