{
  "type": "Feature",
  "properties": {
    "addr:full":"Calle de Antonio Zamora, 14 Madrid Madrid 28011",
    "addr:housenumber":"14",
    "addr:postcode":"madrid;28011",
    "addr:street":"Calle De Antonio Zamora",
    "iso:country":"ES",
    "sg:address":"Calle de Antonio Zamora, 14",
    "sg:city":"Madrid",
    "sg:orig_category":"Peluqueros: De Se\u00d1oras",
    "sg:phone":"+34 914 64 10 25",
    "sg:postcode":"28011",
    "sg:province":"Madrid",
    "wof:name":"Ferruelo Del Hierro Tomas",
    "wof:placetype":"venue"
},
  "geometry": {"coordinates":[-3.7265958786,40.4133338928],"type":"Point"}
}