{
  "type": "Feature",
  "properties": {
    "addr:full":"Pase Calanda, 23 Zaragoza Zaragoza 50010",
    "addr:housenumber":"23",
    "addr:postcode":"50010",
    "addr:street":"Calanda",
    "iso:country":"ES",
    "sg:address":"Pase Calanda, 23",
    "sg:city":"Zaragoza",
    "sg:orig_category":"Molduras, Junquillos, Listones Y Molduras Perforadas",
    "sg:phone":"+34 976 31 12 63",
    "sg:postcode":"50010",
    "sg:province":"Zaragoza",
    "wof:name":"Telefonos Publicos De Aragon S.l.",
    "wof:placetype":"venue"
},
  "geometry": {"coordinates":[-0.9035400152,41.6520042419],"type":"Point"}
}