{
  "type": "Feature",
  "properties": {
    "iso:country":"ES",
    "sg:address":"Av. Pio Xii, 9",
    "sg:city":"Iru\u00f1a",
    "sg:orig_category":"Muebles Y Accesorios Para Cocinas Y Cuartos De Ba\u00d1o (al Por Menor)",
    "sg:phone":"+34 948 25 35 00",
    "sg:postcode":"31008",
    "sg:province":"Navarra",
    "wof:name":"Dobayco S. L.",
    "wof:placetype":"venue"
},
  "geometry": {"coordinates":[-1.6558359861,42.8115234375],"type":"Point"}
}