{
  "type": "Feature",
  "properties": {
    "addr:full":"Calle de Alcalde Juan Sanchez Mesa, 8 Castilleja Cuesta Sevilla 41950",
    "addr:housenumber":"8",
    "addr:postcode":"41950",
    "addr:street":"Calle De Alcalde Juan Sanchez Mesa;Cuesta Sevilla",
    "iso:country":"ES",
    "sg:address":"Calle de Alcalde Juan Sanchez Mesa, 8",
    "sg:city":"Castilleja Cuesta",
    "sg:orig_category":"Molduras, Junquillos, Listones Y Molduras Perforadas",
    "sg:phone":"+34 954 16 27 52",
    "sg:postcode":"41950",
    "sg:province":"Sevilla",
    "wof:name":"Gutierrez Tallafet Juan Jose",
    "wof:placetype":"venue"
},
  "geometry": {"coordinates":[-6.0559473038,37.3834915161],"type":"Point"}
}