{
  "type": "Feature",
  "properties": {
    "addr:full":"Calle de Cerro Santiago, S/n Autol La Rioja 26560",
    "addr:housenumber":"s",
    "addr:postcode":"26560",
    "addr:street":"Calle De Cerro Santiago;/ N Autol;Rioja",
    "iso:country":"ES",
    "sg:address":"Calle de Cerro Santiago, S/n",
    "sg:city":"Autol",
    "sg:orig_category":"Fotograf\u00cda Publicitaria E Industrial",
    "sg:phone":"+34 941 39 09 00",
    "sg:postcode":"26560",
    "sg:province":"La Rioja",
    "wof:name":"Marin Estudio S.c.",
    "wof:placetype":"venue"
},
  "geometry": {"coordinates":[-2.0090575218,42.2162017822],"type":"Point"}
}