{
  "type": "Feature",
  "properties": {
    "addr:full":"C/ Sant Pelegri, 76 Tarrega Lleida 25300",
    "addr:housenumber":"76",
    "addr:postcode":"25300",
    "addr:street":"C / Sant Pelegri",
    "iso:country":"ES",
    "sg:address":"C/ Sant Pelegri, 76",
    "sg:city":"Tarrega",
    "sg:orig_category":"Ense\u00d1anza, Formaci\u00d3n Profesional: Aprendizaje",
    "sg:phone":"+34 973 31 37 48",
    "sg:postcode":"25300",
    "sg:province":"Lleida",
    "wof:name":"Centre De Telecomunicaciones De Catalunya",
    "wof:placetype":"venue"
},
  "geometry": {"coordinates":[1.1397999525,41.6504211426],"type":"Point"}
}