{
  "type": "Feature",
  "properties": {
    "addr:full":"Poli Industrial Francoli, 19 Campsa Tarragona 43006",
    "addr:housenumber":"19",
    "addr:postcode":"43006",
    "addr:street":"Francoli",
    "iso:country":"ES",
    "sg:address":"Poli Industrial Francoli, 19",
    "sg:city":"Campsa",
    "sg:orig_category":"Ebanister\u00cda",
    "sg:phone":"+34 977 54 30 80",
    "sg:postcode":"43006",
    "sg:province":"Tarragona",
    "sg:website":"paginasamarilla.es",
    "wof:name":"Bonancia Gandia Luis",
    "wof:placetype":"venue"
},
  "geometry": {"coordinates":[1.2209249735,41.1154441833],"type":"Point"}
}