{
  "type": "Feature",
  "properties": {
    "iso:country":"ES",
    "sg:address":"Avda Severo Ochoa, 28",
    "sg:city":"Marbella",
    "sg:orig_category":"Barcos",
    "sg:phone":"+34 952 76 51 77",
    "sg:postcode":"29600",
    "sg:province":"M\u00e1laga",
    "wof:name":"Eitzen Chemical Spain S.a.",
    "wof:placetype":"venue"
},
  "geometry": {"coordinates":[-4.8738360405,36.5092658997],"type":"Point"}
}