{
  "type": "Feature",
  "properties": {
    "addr:full":"Calle de Galvanes, 24 Jerez De Los Caballeros Badajoz 06380",
    "addr:housenumber":"24",
    "addr:postcode":"06380",
    "addr:street":"Calle De Galvanes",
    "iso:country":"ES",
    "sg:address":"Calle de Galvanes, 24",
    "sg:city":"Jerez De Los Caballeros",
    "sg:orig_category":"Negocio De Materiales De Construcci\u00d3n",
    "sg:phone":"+34 924 73 12 10",
    "sg:postcode":"06380",
    "sg:province":"Badajoz",
    "wof:name":"Camilo Y Serafin S.l.",
    "wof:placetype":"venue"
},
  "geometry": {"coordinates":[-6.7757987976,38.3197212219],"type":"Point"}
}