{
  "type": "Feature",
  "properties": {
    "addr:full":"Calle de Eduardo Soler Y Perez, 10 Valencia Valencia 46015",
    "addr:housenumber":"10",
    "addr:postcode":"46015",
    "addr:street":"Calle De Eduardo Soler Y Perez",
    "iso:country":"ES",
    "sg:address":"Calle de Eduardo Soler Y Perez, 10",
    "sg:city":"Valencia",
    "sg:orig_category":"Procuradores",
    "sg:phone":"+34 963 49 86 62",
    "sg:postcode":"46015",
    "sg:province":"Valencia",
    "wof:name":"Andres Lalaguna Carmen",
    "wof:placetype":"venue"
},
  "geometry": {"coordinates":[-0.3994233012,39.4768409729],"type":"Point"}
}