{
  "type": "Feature",
  "properties": {
    "iso:country":"ES",
    "sg:address":"Calle de Mayor, 86",
    "sg:city":"Palmar  O Lugar De Don Juan",
    "sg:orig_category":"\u00d3ptica: Instrumentos (fabricaci\u00d3n)",
    "sg:phone":"+34 968 88 64 02",
    "sg:postcode":"30120",
    "sg:province":"Murcia",
    "wof:name":"Opticas Omega S.l.",
    "wof:placetype":"venue"
},
  "geometry": {"coordinates":[-1.1302490234,37.9829597473],"type":"Point"}
}