{
  "type": "Feature",
  "properties": {
    "addr:full":"Calle de Granada (de), 7 Humanes De Madrid Madrid 28970",
    "addr:postcode":"28970",
    "addr:street":"Calle De Granada De 7",
    "iso:country":"ES",
    "sg:address":"Calle de Granada (de), 7",
    "sg:city":"Humanes De Madrid",
    "sg:orig_category":"Imprenta",
    "sg:phone":"+34 914 92 12 63",
    "sg:postcode":"28970",
    "sg:province":"Madrid",
    "wof:name":"Impriarte S.l.",
    "wof:placetype":"venue"
},
  "geometry": {"coordinates":[-3.8228759766,40.2764358521],"type":"Point"}
}