{
  "type": "Feature",
  "properties": {
    "addr:full":"Calle de Cervantes, 11 Adra Almer\u00eda 04770",
    "addr:housenumber":"11",
    "addr:postcode":"04770",
    "addr:street":"Calle De Cervantes;Almeri\u0301A",
    "iso:country":"ES",
    "sg:address":"Calle de Cervantes, 11",
    "sg:city":"Adra",
    "sg:orig_category":"Ropa Para Beb\u00c9s Y Ni\u00d1os (confecci\u00d3n, Al Por Mayor)",
    "sg:phone":"+34 950 40 31 60",
    "sg:postcode":"04770",
    "sg:province":"Almer\u00eda",
    "wof:name":"Oliver Vargas Jesus",
    "wof:placetype":"venue"
},
  "geometry": {"coordinates":[-3.0205190182,36.7473640442],"type":"Point"}
}