{
  "type": "Feature",
  "properties": {
    "addr:full":"Avda Concepcion Arenal, 1 Praia Pontevedra 36950",
    "addr:housenumber":"1",
    "addr:postcode":"36950",
    "addr:street":"Avda Concepcion Arenal",
    "iso:country":"ES",
    "sg:address":"Avda Concepcion Arenal, 1",
    "sg:city":"Praia",
    "sg:orig_category":"Complementos De Vestir (al Por Menor)",
    "sg:phone":"+34 986 31 23 35",
    "sg:postcode":"36950",
    "sg:province":"Pontevedra",
    "wof:name":"Santome Gestido Jorge",
    "wof:placetype":"venue"
},
  "geometry": {"coordinates":[-8.738442421,42.2772254944],"type":"Point"}
}