{
  "type": "Feature",
  "properties": {
    "iso:country":"ES",
    "sg:address":"Plaz Luis Obispo Galarza, 3",
    "sg:city":"Caceres",
    "sg:orig_category":"Inmobiliaria (agencias)",
    "sg:phone":"+34 927 21 19 37",
    "sg:postcode":"10004",
    "sg:province":"C\u00e1ceres",
    "wof:name":"Urvipexsa Sau",
    "wof:placetype":"venue"
},
  "geometry": {"coordinates":[-6.3583831787,39.5027656555],"type":"Point"}
}