{
  "type": "Feature",
  "properties": {
    "iso:country":"ES",
    "sg:address":"Calle de Cantillana, 3",
    "sg:city":"Alcala Guadaira",
    "sg:orig_category":"Mec\u00c1nico Del Autom\u00d3vil",
    "sg:phone":"+34 955 61 46 62",
    "sg:postcode":"41500",
    "sg:province":"Sevilla",
    "wof:name":"Zarza E Hijos S.l.",
    "wof:placetype":"venue"
},
  "geometry": {"coordinates":[-5.8422942162,37.3429298401],"type":"Point"}
}