{
  "type": "Feature",
  "properties": {
    "iso:country":"ES",
    "sg:address":"Carrer de Major, 3",
    "sg:city":"Palafolls",
    "sg:orig_category":"Bancos",
    "sg:phone":"+34 937 62 01 31",
    "sg:postcode":"08389",
    "sg:province":"Barcelona",
    "wof:name":"Banco Popular Espa\u00f1ol",
    "wof:placetype":"venue"
},
  "geometry": {"coordinates":[2.7488811016,41.6672706604],"type":"Point"}
}