{
  "type": "Feature",
  "properties": {
    "iso:country":"ES",
    "sg:address":"Calle de Bielsa, 19",
    "sg:city":"Zaragoza",
    "sg:orig_category":"Centros De Coordinaci\u00d3n",
    "sg:phone":"+34 976 18 93 36",
    "sg:postcode":"50014",
    "sg:province":"Zaragoza",
    "wof:name":"Tomas Lazaro Ana",
    "wof:placetype":"venue"
},
  "geometry": {"coordinates":[-0.8693293929,41.661945343],"type":"Point"}
}