{
  "type": "Feature",
  "properties": {
    "addr:full":"Avda Concordia, 96 Tui Pontevedra 36700",
    "addr:housenumber":"96",
    "addr:postcode":"36700",
    "addr:street":"Avda Concordia",
    "iso:country":"ES",
    "sg:address":"Avda Concordia, 96",
    "sg:city":"Tui",
    "sg:orig_category":"Panader\u00cdas, Panader\u00cdas",
    "sg:phone":"+34 986 60 41 81",
    "sg:postcode":"36700",
    "sg:province":"Pontevedra",
    "wof:name":"Dulces Tui S.l.",
    "wof:placetype":"venue"
},
  "geometry": {"coordinates":[-8.6448440552,42.0485496521],"type":"Point"}
}