{
  "type": "Feature",
  "properties": {
    "addr:full":"Ctra General Del Sur, 130 San Miguel Santa Cruz De Tenerife 38620",
    "addr:housenumber":"130",
    "addr:postcode":"38620",
    "addr:street":"Ctra General Del Sur",
    "iso:country":"ES",
    "sg:address":"Ctra General Del Sur, 130",
    "sg:city":"San Miguel",
    "sg:orig_category":"Institutos De Belleza",
    "sg:phone":"+34 922 70 09 45",
    "sg:postcode":"38620",
    "sg:province":"Santa Cruz De Tenerife",
    "wof:name":"Panaderia Tamaide S.l.",
    "wof:placetype":"venue"
},
  "geometry": {"coordinates":[-16.6175785065,28.0993404388],"type":"Point"}
}