{
  "type": "Feature",
  "properties": {
    "addr:full":"Av Cornella, 57 Esplugues Llobregat Barcelona 08950",
    "addr:housenumber":"57",
    "addr:postcode":"08950",
    "addr:street":"Av Cornella",
    "iso:country":"ES",
    "sg:address":"Av Cornella, 57",
    "sg:city":"Esplugues Llobregat",
    "sg:orig_category":"Promotores Constructores",
    "sg:phone":"+34 933 71 37 66",
    "sg:postcode":"08950",
    "sg:province":"Barcelona",
    "wof:name":"Promociones Inmobiliarias Pastor Y Jimenez",
    "wof:placetype":"venue"
},
  "geometry": {"coordinates":[2.0859808922,41.3744812012],"type":"Point"}
}