{
  "type": "Feature",
  "properties": {
    "iso:country":"ES",
    "sg:address":"Calle de Antonio Buero Vallejo, 11",
    "sg:city":"Sevilla",
    "sg:orig_category":"Centros M\u00c9dicos Y Sociales, Dispensarios",
    "sg:phone":"+34 954 90 35 77",
    "sg:postcode":"41009",
    "sg:province":"Sevilla",
    "wof:name":"Paz Aguilar Luis De",
    "wof:placetype":"venue"
},
  "geometry": {"coordinates":[-5.9894528389,37.4081420898],"type":"Point"}
}