{
  "type": "Feature",
  "properties": {
    "addr:full":"Av Catalunya, 75 S. Adria Besos Barcelona 08930",
    "addr:housenumber":"75",
    "addr:postcode":"08930",
    "addr:street":"Av Catalunya;S. Adria Besos Barcelona",
    "iso:country":"ES",
    "sg:address":"Av Catalunya, 75",
    "sg:city":"S. Adria Besos",
    "sg:orig_category":"Inmobiliaria (agencias)",
    "sg:phone":"+34 933 81 54 50",
    "sg:postcode":"08930",
    "sg:province":"Barcelona",
    "sg:website":"www.santadriaconsulting.com",
    "wof:name":"Gestion Inmobiliaria Afisa S.l",
    "wof:placetype":"venue"
},
  "geometry": {"coordinates":[2.2200529575,41.4302635193],"type":"Point"}
}