{
  "type": "Feature",
  "properties": {
    "addr:full":"Carr Major Sant Jaume, 8 Villarreal Castell\u00f3n 12540",
    "addr:housenumber":"8",
    "addr:postcode":"12540",
    "addr:street":"Carr Major Sant Jaume",
    "iso:country":"ES",
    "sg:address":"Carr Major Sant Jaume, 8",
    "sg:city":"Villarreal",
    "sg:orig_category":"Bisuter\u00cda, Joyer\u00cda, Relojer\u00cda (al Por Menor)",
    "sg:phone":"+34 964 53 74 01",
    "sg:postcode":"12540",
    "sg:province":"Castell\u00f3n",
    "sg:website":"www.alejandrojoyas.com",
    "wof:name":"Cerda Hidalgo Alejandro Jose",
    "wof:placetype":"venue"
},
  "geometry": {"coordinates":[-0.1005280018,39.9375228882],"type":"Point"}
}