{
  "type": "Feature",
  "properties": {
    "iso:country":"ES",
    "sg:address":"Calle de Aguilas, 18",
    "sg:city":"Sevilla",
    "sg:orig_category":"Asociaciones Humanitarias, De Cooperaci\u00d3n, De Acci\u00d3n Social",
    "sg:phone":"+34 954 63 33 11",
    "sg:postcode":"41003",
    "sg:province":"Sevilla",
    "wof:name":"Asociacion Seu",
    "wof:placetype":"venue"
},
  "geometry": {"coordinates":[-5.9883384705,37.3899116516],"type":"Point"}
}