{
  "type": "Feature",
  "properties": {
    "iso:country":"ES",
    "sg:address":"C/ Alfons El Magnanim, 15",
    "sg:city":"Alcoi",
    "sg:orig_category":"Materiales De Construcci\u00d3n (en General)",
    "sg:phone":"+34 966 52 20 23",
    "sg:postcode":"03802",
    "sg:province":"Alicante",
    "wof:name":"Ruiz Pedraza Rafael",
    "wof:placetype":"venue"
},
  "geometry": {"coordinates":[-0.4848169982,38.6972961426],"type":"Point"}
}