{
  "type": "Feature",
  "properties": {
    "addr:full":"Avda Ricardo Soriano, 63 Marbella M\u00e1laga 29600",
    "addr:housenumber":"63",
    "addr:postcode":"29600",
    "addr:street":"Avda Ricardo Soriano;Ma\u0301Laga",
    "iso:country":"ES",
    "sg:address":"Avda Ricardo Soriano, 63",
    "sg:city":"Marbella",
    "sg:orig_category":"Ropa Para Se\u00d1oras Y Caballeros (al Por Menor)",
    "sg:phone":"+34 952 82 74 68",
    "sg:postcode":"29600",
    "sg:province":"M\u00e1laga",
    "wof:name":"Don Miguel S.a.",
    "wof:placetype":"venue"
},
  "geometry": {"coordinates":[-4.9007239342,36.5101966858],"type":"Point"}
}