{
  "type": "Feature",
  "properties": {
    "iso:country":"ES",
    "sg:address":"Avda Rey Juan Carlos I, 1",
    "sg:city":"Vejer De La Frontera",
    "sg:orig_category":"Edici\u00d3n De Diarios, Revistas, Boletines",
    "sg:phone":"+34 956 44 74 67",
    "sg:postcode":"11150",
    "sg:province":"C\u00e1diz",
    "wof:name":"Diario De Cadiz S.l.",
    "wof:placetype":"venue"
},
  "geometry": {"coordinates":[-5.9699988365,36.2530517578],"type":"Point"}
}