{
  "type": "Feature",
  "properties": {
    "addr:full":"Calle de Carpinteria, 2 Navaconcejo C\u00e1ceres 10613",
    "addr:housenumber":"2",
    "addr:postcode":"10613",
    "addr:street":"Calle De Carpinteria;Ca\u0301Ceres",
    "iso:country":"ES",
    "sg:address":"Calle de Carpinteria, 2",
    "sg:city":"Navaconcejo",
    "sg:orig_category":"Frutas Y Legumbres Frescas (al Por Mayor)",
    "sg:phone":"+34 927 17 35 83",
    "sg:postcode":"10613",
    "sg:province":"C\u00e1ceres",
    "wof:name":"Hurcerez S.l.",
    "wof:placetype":"venue"
},
  "geometry": {"coordinates":[-5.8324337006,40.1760864258],"type":"Point"}
}