{
  "type": "Feature",
  "properties": {
    "addr:full":"Ctra Barcelona, 436 Sabadell Barcelona 08203",
    "addr:housenumber":"436",
    "addr:postcode":"08203",
    "addr:street":"Ctra Barcelona",
    "iso:country":"ES",
    "sg:address":"Ctra Barcelona, 436",
    "sg:city":"Sabadell",
    "sg:orig_category":"Peluquer\u00cdas, Peluquer\u00cda Mixta",
    "sg:phone":"+34 937 12 41 43",
    "sg:postcode":"08203",
    "sg:province":"Barcelona",
    "wof:name":"Otero Barragan Ana Clara",
    "wof:placetype":"venue"
},
  "geometry": {"coordinates":[2.1137340069,41.5322494507],"type":"Point"}
}