{
  "type": "Feature",
  "properties": {
    "addr:full":"Calle de Historias De La Radio, 3 Madrid Madrid 28018",
    "addr:housenumber":"3",
    "addr:postcode":"28018",
    "addr:street":"Calle De Historias De La Radio",
    "iso:country":"ES",
    "sg:address":"Calle de Historias De La Radio, 3",
    "sg:city":"Madrid",
    "sg:orig_category":"Ense\u00d1anza: Idiomas",
    "sg:phone":"+34 915 07 16 29",
    "sg:postcode":"28018",
    "sg:province":"Madrid",
    "wof:name":"Rodriguez Martin Jose Luis",
    "wof:placetype":"venue"
},
  "geometry": {"coordinates":[-3.6556549072,40.380191803],"type":"Point"}
}