{
  "type": "Feature",
  "properties": {
    "addr:full":"Calle de Empleo (del), 35 Adaro Madrid 28906",
    "addr:housenumber":"35",
    "addr:postcode":"28906",
    "addr:street":"Calle De Empleo Del",
    "iso:country":"ES",
    "sg:address":"Calle de Empleo (del), 35",
    "sg:city":"Adaro",
    "sg:orig_category":"Adaptaciones, Acondicionamientos Especiales Para Veh\u00cdculos, Veh\u00cdculos Industriales",
    "sg:phone":"+34 916 83 04 09",
    "sg:postcode":"28906",
    "sg:province":"Madrid",
    "wof:name":"Talleres Vaquero Crespo S.l.",
    "wof:placetype":"venue"
},
  "geometry": {"coordinates":[-3.7057700157,40.42029953],"type":"Point"}
}