{
  "type": "Feature",
  "properties": {
    "addr:full":"Ctra Abrigos (a Los), 15 San Miguel Santa Cruz De Tenerife 38620",
    "addr:postcode":"38620",
    "addr:street":"Ctra Abrigos;Los",
    "iso:country":"ES",
    "sg:address":"Ctra Abrigos (a Los), 15",
    "sg:city":"San Miguel",
    "sg:orig_category":"Inmobiliaria (agencias)",
    "sg:phone":"+34 922 70 12 00",
    "sg:postcode":"38620",
    "sg:province":"Santa Cruz De Tenerife",
    "wof:name":"Central De Gestiones Inmobiliarias Olimar S.l.",
    "wof:placetype":"venue"
},
  "geometry": {"coordinates":[-16.6123085022,28.0977592468],"type":"Point"}
}