{
  "type": "Feature",
  "properties": {
    "iso:country":"ES",
    "sg:address":"Plaz Nueva De La Iglesia, 5",
    "sg:city":"Valencia",
    "sg:orig_category":"Plomeros",
    "sg:phone":"+34 963 49 10 96",
    "sg:postcode":"46025",
    "sg:province":"Valencia",
    "wof:name":"Camps Romero Jose Antonio",
    "wof:placetype":"venue"
},
  "geometry": {"coordinates":[-0.3916609883,39.4921646118],"type":"Point"}
}