{
  "type": "Feature",
  "properties": {
    "iso:country":"ES",
    "sg:address":"Pla\u00c7 Marques De Camps, 9",
    "sg:city":"Girona",
    "sg:orig_category":"M\u00c9dicos: Naturistas",
    "sg:phone":"+34 972 22 16 32",
    "sg:postcode":"17001",
    "sg:province":"Girona",
    "wof:name":"Aguilella Ribot Joan Manuel",
    "wof:placetype":"venue"
},
  "geometry": {"coordinates":[2.8215665817,41.9854621887],"type":"Point"}
}