{
  "type": "Feature",
  "properties": {
    "iso:country":"ES",
    "sg:address":"Calle de General Diaz Porlier, 23",
    "sg:city":"Madrid",
    "sg:orig_category":"Institutos De Belleza",
    "sg:phone":"+34 914 35 60 82",
    "sg:postcode":"28001",
    "sg:province":"Madrid",
    "wof:name":"Montero Gomez Rocio",
    "wof:placetype":"venue"
},
  "geometry": {"coordinates":[-3.677259922,40.4266967773],"type":"Point"}
}