{
  "type": "Feature",
  "properties": {
    "iso:country":"ES",
    "sg:address":"Calle de Antonia Rodriguez Sacristan, 10",
    "sg:city":"Madrid",
    "sg:orig_category":"Asilos De Ancianos. Centros Privados",
    "sg:phone":"+34 915 08 11 10",
    "sg:postcode":"28044",
    "sg:province":"Madrid",
    "wof:name":"Valdeluz S.a.",
    "wof:placetype":"venue"
},
  "geometry": {"coordinates":[-3.7449367046,40.372756958],"type":"Point"}
}