{
  "type": "Feature",
  "properties": {
    "iso:country":"ES",
    "sg:address":"Calle de Mayor, 12",
    "sg:city":"Rivero De Posadas",
    "sg:orig_category":"Limpieza Industrial",
    "sg:phone":"+34 957 63 12 75",
    "sg:postcode":"14739",
    "sg:province":"C\u00f3rdoba",
    "wof:name":"Diaz Marina Pilar",
    "wof:placetype":"venue"
},
  "geometry": {"coordinates":[-5.1439638138,37.792755127],"type":"Point"}
}