{
  "type": "Feature",
  "properties": {
    "addr:full":"Calle de Uruguay, 15 Valencia Valencia 46007",
    "addr:housenumber":"15",
    "addr:postcode":"46007",
    "addr:street":"Calle De Uruguay",
    "iso:country":"ES",
    "sg:address":"Calle de Uruguay, 15",
    "sg:city":"Valencia",
    "sg:orig_category":"Venta, Montaje De Neum\u00c1ticos",
    "sg:phone":"+34 963 41 76 27",
    "sg:postcode":"46007",
    "sg:province":"Valencia",
    "wof:name":"Jovellar Tecnirueda S.l.",
    "wof:placetype":"venue"
},
  "geometry": {"coordinates":[-0.3867279887,39.458770752],"type":"Point"}
}