{
  "type": "Feature",
  "properties": {
    "addr:full":"Avda Iparraguirre(ed Cantabrico), 59 Santurtzi Vizcaya 48980",
    "addr:housenumber":"59",
    "addr:postcode":"48980",
    "addr:street":"Avda Iparraguirre Ed Cantabrico",
    "iso:country":"ES",
    "sg:address":"Avda Iparraguirre(ed Cantabrico), 59",
    "sg:city":"Santurtzi",
    "sg:orig_category":"Organizaciones Profesionales",
    "sg:phone":"+34 944 62 64 44",
    "sg:postcode":"48980",
    "sg:province":"Vizcaya",
    "wof:name":"Global Caontainer Agency S.a.",
    "wof:placetype":"venue"
},
  "geometry": {"coordinates":[-3.0526120663,43.3322906494],"type":"Point"}
}