{
  "type": "Feature",
  "properties": {
    "iso:country":"ES",
    "sg:address":"Avda Cristo De Las Cadenas, 5",
    "sg:city":"Oviedo",
    "sg:orig_category":"Quincaller\u00cda (al Por Menor)",
    "sg:phone":"+34 985 23 96 28",
    "sg:postcode":"33006",
    "sg:province":"Asturias",
    "wof:name":"Garcia Fernandez Manuel",
    "wof:placetype":"venue"
},
  "geometry": {"coordinates":[-5.8580360413,43.3562965393],"type":"Point"}
}