{
  "type": "Feature",
  "properties": {
    "addr:full":"Calle de Escolta Real, 49 Donostia-san Sebastian Guip\u00f9zcoa 20008",
    "addr:housenumber":"49",
    "addr:postcode":"20008",
    "addr:street":"Calle De Escolta Real",
    "iso:country":"ES",
    "sg:address":"Calle de Escolta Real, 49",
    "sg:city":"Donostia-san Sebastian",
    "sg:orig_category":"Poller\u00cda Y Caza (al Por Menor)",
    "sg:phone":"+34 943 21 02 43",
    "sg:postcode":"20008",
    "sg:province":"Guip\u00f9zcoa",
    "wof:name":"Bernas Andueza Alfonso",
    "wof:placetype":"venue"
},
  "geometry": {"coordinates":[-2.0000538826,43.3116073608],"type":"Point"}
}