{
  "type": "Feature",
  "properties": {
    "addr:full":"Barr Barinaga, 2 Barinaga Vizcaya 48277",
    "addr:housenumber":"2",
    "addr:postcode":"48277",
    "addr:street":"Barinaga",
    "iso:country":"ES",
    "sg:address":"Barr Barinaga, 2",
    "sg:city":"Barinaga",
    "sg:orig_category":"Molduras, Junquillos, Listones Y Molduras Perforadas",
    "sg:phone":"+34 946 16 65 34",
    "sg:postcode":"48277",
    "sg:province":"Vizcaya",
    "wof:name":"Gandiaga Arriola Fausto",
    "wof:placetype":"venue"
},
  "geometry": {"coordinates":[-2.4781939983,43.2544898987],"type":"Point"}
}