{
  "type": "Feature",
  "properties": {
    "iso:country":"ES",
    "sg:address":"Carrer de Josep Tapiolas, 98",
    "sg:city":"Terrassa",
    "sg:orig_category":"Electricidad, Electr\u00d3nica: Suministros (al Por Menor)",
    "sg:phone":"+34 937 31 88 01",
    "sg:postcode":"08226",
    "sg:province":"Barcelona",
    "wof:name":"Comercial De Productos De Ocasion S.l.",
    "wof:placetype":"venue"
},
  "geometry": {"coordinates":[2.0292921066,41.570526123],"type":"Point"}
}