{
  "type": "Feature",
  "properties": {
    "addr:full":"Avda Rafael Onieva Ariza, S/n Baena C\u00f3rdoba 14850",
    "addr:housenumber":"s",
    "addr:postcode":"14850",
    "addr:street":"Avda Rafael Onieva Ariza;/ N;Co\u0301Rdoba",
    "iso:country":"ES",
    "sg:address":"Avda Rafael Onieva Ariza, S/n",
    "sg:city":"Baena",
    "sg:orig_category":"Barnizadores",
    "sg:phone":"+34 957 69 17 45",
    "sg:postcode":"14850",
    "sg:province":"C\u00f3rdoba",
    "wof:name":"Pinturas Y Acabados Del Sur S.l.",
    "wof:placetype":"venue"
},
  "geometry": {"coordinates":[-4.3144578934,37.6238059998],"type":"Point"}
}