{
  "type": "Feature",
  "properties": {
    "addr:full":"Calle de Ramon Y Cajal, 7 Calanda Teruel 44570",
    "addr:housenumber":"7",
    "addr:postcode":"44570",
    "addr:street":"Calle De Ramon Y Cajal",
    "iso:country":"ES",
    "sg:address":"Calle de Ramon Y Cajal, 7",
    "sg:city":"Calanda",
    "sg:orig_category":"Electrodom\u00c9sticos (al Por Menor)",
    "sg:phone":"+34 978 84 62 31",
    "sg:postcode":"44570",
    "sg:province":"Teruel",
    "wof:name":"Electrodomestico Bielsa S.l.",
    "wof:placetype":"venue"
},
  "geometry": {"coordinates":[-0.2331169993,40.9393844604],"type":"Point"}
}