{
  "type": "Feature",
  "properties": {
    "iso:country":"ES",
    "sg:address":"Cmno Losa (la), Km. 0034,0",
    "sg:city":"Madrona",
    "sg:orig_category":"Carb\u00d3n, Carb\u00d3n De Madera (al Por Mayor)",
    "sg:phone":"+34 921 48 50 40",
    "sg:postcode":"40154",
    "sg:province":"Segovia",
    "wof:name":"Soldado Lomillos Rafael",
    "wof:placetype":"venue"
},
  "geometry": {"coordinates":[-4.1714987755,40.8973388672],"type":"Point"}
}