{
  "type": "Feature",
  "properties": {
    "addr:full":"Valdegrillo, 19 Olivares Sevilla 41804",
    "addr:housenumber":"19",
    "addr:postcode":"41804",
    "addr:street":"Valdegrillo;Sevilla",
    "iso:country":"ES",
    "sg:address":"Valdegrillo, 19",
    "sg:city":"Olivares",
    "sg:orig_category":"Escayola Y Productos De Escayola (fabricaci\u00d3n, Al Por Mayor)",
    "sg:phone":"+34 955 71 85 28",
    "sg:postcode":"41804",
    "sg:province":"Sevilla",
    "wof:name":"Servi Escayeso S.l.",
    "wof:placetype":"venue"
},
  "geometry": {"coordinates":[-6.153439045,37.4184074402],"type":"Point"}
}