{
  "type": "Feature",
  "properties": {
    "iso:country":"ES",
    "sg:address":"Calle de Jorge Luis Borges, 5",
    "sg:city":"Guadalajara",
    "sg:orig_category":"Arquitectos",
    "sg:phone":"+34 949 20 11 29",
    "sg:postcode":"19004",
    "sg:province":"Guadalajara",
    "wof:name":"Mu\u00f1oz Benegas Juana",
    "wof:placetype":"venue"
},
  "geometry": {"coordinates":[-3.1805992126,40.6304855347],"type":"Point"}
}