{
  "type": "Feature",
  "properties": {
    "addr:full":"Calle de Minerva, 159 Madrid Madrid 28032",
    "addr:housenumber":"159",
    "addr:postcode":"28032",
    "addr:street":"Calle De Minerva",
    "iso:country":"ES",
    "sg:address":"Calle de Minerva, 159",
    "sg:city":"Madrid",
    "sg:orig_category":"Agencias Y Agentes Comerciales, Representantes",
    "sg:phone":"+34 917 76 46 50",
    "sg:postcode":"28032",
    "sg:province":"Madrid",
    "wof:name":"Calculo Y Tratamiento De La Informacion",
    "wof:placetype":"venue"
},
  "geometry": {"coordinates":[-3.6079719067,40.3946151733],"type":"Point"}
}