{
  "type": "Feature",
  "properties": {
    "addr:full":"Calle de General Almirante, 8 Valladolid Valladolid 47003",
    "addr:housenumber":"8",
    "addr:postcode":"47003",
    "addr:street":"Calle De General Almirante",
    "iso:country":"ES",
    "sg:address":"Calle de General Almirante, 8",
    "sg:city":"Valladolid",
    "sg:orig_category":"Arquitectos",
    "sg:phone":"+34 983 35 29 14",
    "sg:postcode":"47003",
    "sg:province":"Valladolid",
    "wof:name":"Llanos Gato Jose Maria",
    "wof:placetype":"venue"
},
  "geometry": {"coordinates":[-4.7280359268,41.6540794373],"type":"Point"}
}