{
  "type": "Feature",
  "properties": {
    "iso:country":"ES",
    "sg:address":"Calle de Poeta Sanchez Bautista, 1",
    "sg:city":"Llano De Brujas",
    "sg:orig_category":"Caf\u00c9s, Bares, Cervecer\u00cdas",
    "sg:phone":"+34 968 81 27 29",
    "sg:postcode":"30161",
    "sg:province":"Murcia",
    "wof:name":"Cordoba Mu\u00f1oz Pedro",
    "wof:placetype":"venue"
},
  "geometry": {"coordinates":[-1.0711450577,38.0052986145],"type":"Point"}
}