{
  "type": "Feature",
  "properties": {
    "iso:country":"ES",
    "sg:address":"Lugar Cepo Venta, S/n",
    "sg:city":"Torrecera",
    "sg:orig_category":"Alimentaci\u00d3n General (al Por Mayor)",
    "sg:phone":"+34 956 16 18 02",
    "sg:postcode":"11595",
    "sg:province":"C\u00e1diz",
    "wof:name":"Suara Ganadera S.c.a",
    "wof:placetype":"venue"
},
  "geometry": {"coordinates":[-5.9430441856,36.6100997925],"type":"Point"}
}