{
  "type": "Feature",
  "properties": {
    "iso:country":"ES",
    "sg:address":"Carrer de Antoni Rovira I Virgili (d'), 11",
    "sg:city":"Tarragona",
    "sg:orig_category":"Agencias De Trabajo Temporal",
    "sg:phone":"+34 977 22 60 46",
    "sg:postcode":"43002",
    "sg:province":"Tarragona",
    "wof:name":"Creyf's Trabajo Temporal Ett S.a.",
    "wof:placetype":"venue"
},
  "geometry": {"coordinates":[1.2503069639,41.1181983948],"type":"Point"}
}