{
  "type": "Feature",
  "properties": {
    "addr:full":"Ctra Madrid, Km. 0058,4 Olias Rey Toledo 45280",
    "addr:postcode":"45280",
    "addr:street":"Ctra Madrid Km. 0058,4 Olias Rey",
    "iso:country":"ES",
    "sg:address":"Ctra Madrid, Km. 0058,4",
    "sg:city":"Olias Rey",
    "sg:orig_category":"Bebidas",
    "sg:phone":"+34 925 49 19 17",
    "sg:postcode":"45280",
    "sg:province":"Toledo",
    "wof:name":"Distribuciones Orgaba S.l.",
    "wof:placetype":"venue"
},
  "geometry": {"coordinates":[-3.9885389805,39.9435043335],"type":"Point"}
}