{
  "type": "Feature",
  "properties": {
    "iso:country":"ES",
    "sg:address":"Avda Asturias, S/n",
    "sg:city":"Boal",
    "sg:orig_category":"Transportes Por Carretera: Lotes Completos, Mercanc\u00cdas Diversas",
    "sg:phone":"+34 985 62 00 40",
    "sg:postcode":"33720",
    "sg:province":"Asturias",
    "wof:name":"Ron Castrillon Rosa Maria",
    "wof:placetype":"venue"
},
  "geometry": {"coordinates":[-6.81873703,43.4276847839],"type":"Point"}
}