{
  "type": "Feature",
  "properties": {
    "addr:full":"Rua Serra, 3 Pontevedra Pontevedra 36002",
    "addr:housenumber":"3",
    "addr:postcode":"36002",
    "addr:street":"Rua Serra",
    "iso:country":"ES",
    "sg:address":"Rua Serra, 3",
    "sg:city":"Pontevedra",
    "sg:orig_category":"Bisuter\u00cda, Joyer\u00cda, Relojer\u00cda (al Por Menor)",
    "sg:phone":"+34 986 84 32 57",
    "sg:postcode":"36002",
    "sg:province":"Pontevedra",
    "wof:name":"Paisa Gil Luis Antonio",
    "wof:placetype":"venue"
},
  "geometry": {"coordinates":[-8.6439599991,42.4342460632],"type":"Point"}
}