{
  "type": "Feature",
  "properties": {
    "iso:country":"ES",
    "sg:address":"Pase San Illan, 5",
    "sg:city":"Madrid",
    "sg:orig_category":"Molduras, Junquillos, Listones Y Molduras Perforadas",
    "sg:phone":"+34 915 60 10 32",
    "sg:postcode":"28019",
    "sg:province":"Madrid",
    "wof:name":"Vidal Fari\u00f1as Joaquin",
    "wof:placetype":"venue"
},
  "geometry": {"coordinates":[-3.7244210243,40.4023323059],"type":"Point"}
}