{
  "type": "Feature",
  "properties": {
    "addr:full":"Carr De Ferreres Breto, S/n Benicarlo Castell\u00f3n 12580",
    "addr:housenumber":"s",
    "addr:postcode":"12580",
    "addr:street":"Carr De Ferreres Breto;/ N;Castello\u0301N",
    "iso:country":"ES",
    "sg:address":"Carr De Ferreres Breto, S/n",
    "sg:city":"Benicarlo",
    "sg:orig_category":"Quincaller\u00cda (al Por Menor)",
    "sg:phone":"+34 964 47 55 44",
    "sg:postcode":"12580",
    "sg:province":"Castell\u00f3n",
    "wof:name":"Alvarez Sotelo Francisco",
    "wof:placetype":"venue"
},
  "geometry": {"coordinates":[0.4237649143,40.4179801941],"type":"Point"}
}