{
  "type": "Feature",
  "properties": {
    "iso:country":"ES",
    "sg:address":"Calle de Cisterna, 10",
    "sg:city":"Riba-roja Turia",
    "sg:orig_category":"Delegados, Agentes De Tr\u00c1nsito, Auxiliares De Transporte Internacional",
    "sg:phone":"+34 962 77 11 15",
    "sg:postcode":"46190",
    "sg:province":"Valencia",
    "wof:name":"Garcia Enguix Felipe",
    "wof:placetype":"venue"
},
  "geometry": {"coordinates":[-0.5664340258,39.5477867126],"type":"Point"}
}