{
  "type": "Feature",
  "properties": {
    "addr:full":"Carrer de Margarida Xirgu, 14 Rubi Barcelona 08191",
    "addr:housenumber":"14",
    "addr:postcode":"08191",
    "addr:street":"Carrer De Margarida Xirgu",
    "iso:country":"ES",
    "sg:address":"Carrer de Margarida Xirgu, 14",
    "sg:city":"Rubi",
    "sg:orig_category":"Inmobiliaria (agencias)",
    "sg:phone":"+34 935 86 12 15",
    "sg:postcode":"08191",
    "sg:province":"Barcelona",
    "wof:name":"Fincas Riarre S.l.l.",
    "wof:placetype":"venue"
},
  "geometry": {"coordinates":[2.0313448906,41.4952125549],"type":"Point"}
}