{
  "type": "Feature",
  "properties": {
    "iso:country":"ES",
    "sg:address":"Calle de Barria, 3",
    "sg:city":"Getxo",
    "sg:orig_category":"M\u00c9dicos: Estomatolog\u00cda",
    "sg:phone":"+34 944 63 03 94",
    "sg:postcode":"48930",
    "sg:province":"Vizcaya",
    "wof:name":"Ruben Marin Pico (clinica Dental)",
    "wof:placetype":"venue"
},
  "geometry": {"coordinates":[-3.0149815083,43.3242454529],"type":"Point"}
}