{
  "type": "Feature",
  "properties": {
    "addr:full":"Rbla Catalunya, 16 Barcelona Barcelona 08007",
    "addr:housenumber":"16",
    "addr:postcode":"08007",
    "addr:street":"Rbla Catalunya",
    "iso:country":"ES",
    "sg:address":"Rbla Catalunya, 16",
    "sg:city":"Barcelona",
    "sg:orig_category":"Grafistas",
    "sg:phone":"+34 933 43 54 80",
    "sg:postcode":"08007",
    "sg:province":"Barcelona",
    "wof:name":"Subira I Associats S.l.",
    "wof:placetype":"venue"
},
  "geometry": {"coordinates":[2.1674480438,41.388256073],"type":"Point"}
}