{
  "type": "Feature",
  "properties": {
    "iso:country":"ES",
    "sg:address":"Jose Lasa Etorbidea, 4",
    "sg:city":"Lazkao",
    "sg:orig_category":"Inmobiliaria (agencias)",
    "sg:phone":"+34 943 16 02 98",
    "sg:postcode":"20210",
    "sg:province":"Guip\u00f9zcoa",
    "wof:name":"Lamy Insausti Gorka",
    "wof:placetype":"venue"
},
  "geometry": {"coordinates":[-2.1873590946,43.0314903259],"type":"Point"}
}