{
  "type": "Feature",
  "properties": {
    "iso:country":"ES",
    "sg:address":"Pase Calzada (da), S/n",
    "sg:city":"Cambados",
    "sg:orig_category":"Empresarios",
    "sg:phone":"+34 986 52 10 08",
    "sg:postcode":"36630",
    "sg:province":"Pontevedra",
    "wof:name":"Fundacion Para O Desenvolvemento Comarcal Do Salnes",
    "wof:placetype":"venue"
},
  "geometry": {"coordinates":[-8.8148622513,42.5161514282],"type":"Point"}
}