{
  "type": "Feature",
  "properties": {
    "iso:country":"ES",
    "sg:address":"Calle de Santo Domingo, 2",
    "sg:city":"Novallas",
    "sg:orig_category":"Empresas De Carpinter\u00cda De Madera",
    "sg:phone":"+34 976 19 84 80",
    "sg:postcode":"50510",
    "sg:province":"Zaragoza",
    "wof:name":"Ullate Crespo Antonio",
    "wof:placetype":"venue"
},
  "geometry": {"coordinates":[-1.6931329966,41.947517395],"type":"Point"}
}