{
  "type": "Feature",
  "properties": {
    "iso:country":"ES",
    "sg:address":"Habana, 25",
    "sg:city":"Ribeira-santa Uxia",
    "sg:classifiers":[
        {
            "category":"Taxi",
            "type":"Transportation"
        }
    ],
    "sg:phone":"+34 981 87 04 63",
    "sg:postcode":"15960",
    "sg:province":"La Coru\u00f1a",
    "wof:name":"Perez Vidal Manuel",
    "wof:placetype":"venue"
},
  "geometry": {"coordinates":[-8.9958591461,42.5591392517],"type":"Point"}
}