{
  "type": "Feature",
  "properties": {
    "addr:full":"Afores, S/n Vilamari Girona 17468",
    "addr:housenumber":"s / n",
    "addr:postcode":"17468",
    "addr:street":"Afores",
    "iso:country":"ES",
    "sg:address":"Afores, S/n",
    "sg:city":"Vilamari",
    "sg:orig_category":"Cr\u00cda De Animales",
    "sg:phone":"+34 972 56 10 22",
    "sg:postcode":"17468",
    "sg:province":"Girona",
    "wof:name":"Riera Illa Ramon",
    "wof:placetype":"venue"
},
  "geometry": {"coordinates":[2.8884160519,42.1389427185],"type":"Point"}
}