{
  "type": "Feature",
  "properties": {
    "addr:full":"Urb Carmelo (el), 144 Ogijares Granada 18151",
    "addr:housenumber":"144",
    "addr:postcode":"18151",
    "addr:street":"Urb Carmelo El",
    "iso:country":"ES",
    "sg:address":"Urb Carmelo (el), 144",
    "sg:city":"Ogijares",
    "sg:orig_category":"Delegados, Agentes De Tr\u00c1nsito, Auxiliares De Transporte Internacional",
    "sg:phone":"+34 958 59 75 77",
    "sg:postcode":"18151",
    "sg:province":"Granada",
    "wof:name":"Jaldo Pinel Jose",
    "wof:placetype":"venue"
},
  "geometry": {"coordinates":[-3.6051189899,37.1205368042],"type":"Point"}
}