{
  "type": "Feature",
  "properties": {
    "iso:country":"ES",
    "sg:address":"Calle de Mayor, 22",
    "sg:city":"Garrucha",
    "sg:orig_category":"Muebles, Minoristas",
    "sg:phone":"+34 950 46 00 83",
    "sg:postcode":"04630",
    "sg:province":"Almer\u00eda",
    "wof:name":"Soler Caparros Diego",
    "wof:placetype":"venue"
},
  "geometry": {"coordinates":[-1.8203779459,37.1858024597],"type":"Point"}
}