{
  "type": "Feature",
  "properties": {
    "iso:country":"ES",
    "sg:address":"Calle de Santa Ines, S/n",
    "sg:city":"Cadiz",
    "sg:orig_category":"Museos",
    "sg:phone":"+34 956 22 17 88",
    "sg:postcode":"11003",
    "sg:province":"C\u00e1diz",
    "wof:name":"Ayuntamiento De Cadiz",
    "wof:placetype":"venue"
},
  "geometry": {"coordinates":[-6.2998290062,36.5333099365],"type":"Point"}
}