{
  "type": "Feature",
  "properties": {
    "iso:country":"ES",
    "sg:address":"Calle de Buenos Aires, 56",
    "sg:city":"Sotogrande",
    "sg:orig_category":"Promotores Constructores",
    "sg:phone":"+34 956 79 41 36",
    "sg:postcode":"11310",
    "sg:province":"C\u00e1diz",
    "wof:name":"Bright Development Construction S.l.",
    "wof:placetype":"venue"
},
  "geometry": {"coordinates":[-5.3094129562,36.2786369324],"type":"Point"}
}