{
  "type": "Feature",
  "properties": {
    "addr:full":"Calle de Arte, 13 Madrid Madrid 28033",
    "addr:housenumber":"13",
    "addr:postcode":"madrid;28033",
    "addr:street":"Calle De Arte",
    "iso:country":"ES",
    "sg:address":"Calle de Arte, 13",
    "sg:city":"Madrid",
    "sg:orig_category":"Restaurantes De Empresas Y Colectivos",
    "sg:phone":"+34 913 02 93 45",
    "sg:postcode":"28033",
    "sg:province":"Madrid",
    "wof:name":"Hosteleria Y Colectividades S.a.",
    "wof:placetype":"venue"
},
  "geometry": {"coordinates":[-3.6724083424,40.4823188782],"type":"Point"}
}