{
  "type": "Feature",
  "properties": {
    "addr:full":"Calle de Pizarro, 2 Aranda Duero Burgos 09400",
    "addr:housenumber":"2",
    "addr:postcode":"09400",
    "addr:street":"Calle De Pizarro",
    "iso:country":"ES",
    "sg:address":"Calle de Pizarro, 2",
    "sg:city":"Aranda Duero",
    "sg:orig_category":"Quincaller\u00cda (al Por Menor)",
    "sg:phone":"+34 947 50 57 90",
    "sg:postcode":"09400",
    "sg:province":"Burgos",
    "wof:name":"Arroyo Esgueva Emilio",
    "wof:placetype":"venue"
},
  "geometry": {"coordinates":[-3.6811385155,41.6713523865],"type":"Point"}
}