{
  "type": "Feature",
  "properties": {
    "addr:full":"Calle de Renedo, 13 Valladolid Valladolid 47005",
    "addr:housenumber":"13",
    "addr:postcode":"47005",
    "addr:street":"Calle De Renedo",
    "iso:country":"ES",
    "sg:address":"Calle de Renedo, 13",
    "sg:city":"Valladolid",
    "sg:orig_category":"Embalajes",
    "sg:phone":"+34 983 29 02 04",
    "sg:postcode":"47005",
    "sg:province":"Valladolid",
    "wof:name":"Trigueros Herrero Adoracion",
    "wof:placetype":"venue"
},
  "geometry": {"coordinates":[-4.7156448364,41.6522331238],"type":"Point"}
}