{
  "type": "Feature",
  "properties": {
    "iso:country":"ES",
    "sg:address":"Calle de General Ricardos, 202",
    "sg:city":"Madrid",
    "sg:orig_category":"Molduras, Junquillos, Listones Y Molduras Perforadas",
    "sg:phone":"+34 914 65 31 95",
    "sg:postcode":"28025",
    "sg:province":"Madrid",
    "wof:name":"Solis Navarro Domingo",
    "wof:placetype":"venue"
},
  "geometry": {"coordinates":[-3.7365942001,40.3853034973],"type":"Point"}
}