{
  "type": "Feature",
  "properties": {
    "addr:full":"Calle de Amor De Dios, 33 Valladolid Valladolid 47010",
    "addr:housenumber":"33",
    "addr:postcode":"47010",
    "addr:street":"Calle De Amor De Dios",
    "iso:country":"ES",
    "sg:address":"Calle de Amor De Dios, 33",
    "sg:city":"Valladolid",
    "sg:orig_category":"Centros Empresariales",
    "sg:phone":"+34 983 26 45 65",
    "sg:postcode":"47010",
    "sg:province":"Valladolid",
    "sg:website":"www.clarosol.es",
    "wof:name":"Claro Sol Limpiezas De Suelos Y Ventanas S.a.",
    "wof:placetype":"venue"
},
  "geometry": {"coordinates":[-4.7180509567,41.6628952026],"type":"Point"}
}