{
  "type": "Feature",
  "properties": {
    "addr:full":"Avda San Sebastian, 152 Santa Cruz De Tenerife Santa Cruz De Tenerife 38005",
    "addr:housenumber":"152",
    "addr:postcode":"38005",
    "addr:street":"Avda San Sebastian",
    "iso:country":"ES",
    "sg:address":"Avda San Sebastian, 152",
    "sg:city":"Santa Cruz De Tenerife",
    "sg:orig_category":"Organismos De Turismo",
    "sg:phone":"+34 922 22 21 71",
    "sg:postcode":"38005",
    "sg:province":"Santa Cruz De Tenerife",
    "wof:name":"Asociacion Empresarial Hotelera Y Extrahotelera De Tenerife",
    "wof:placetype":"venue"
},
  "geometry": {"coordinates":[-16.2607765198,28.4639205933],"type":"Point"}
}