{
  "type": "Feature",
  "properties": {
    "iso:country":"ES",
    "sg:address":"Calle de Pintor Stolz, 31",
    "sg:city":"Valencia",
    "sg:orig_category":"Diarios, Revistas Y Boletines (distribuidores)",
    "sg:phone":"+34 963 59 33 49",
    "sg:postcode":"46018",
    "sg:province":"Valencia",
    "wof:name":"Rios Serrano Serafina",
    "wof:placetype":"venue"
},
  "geometry": {"coordinates":[-0.3997150064,39.4694213867],"type":"Point"}
}