{
  "type": "Feature",
  "properties": {
    "iso:country":"ES",
    "sg:address":"Rua Santiago, S/n",
    "sg:city":"Amoeiro",
    "sg:orig_category":"Mec\u00c1nico Del Autom\u00d3vil",
    "sg:phone":"+34 988 28 10 55",
    "sg:postcode":"32170",
    "sg:province":"Ourense",
    "wof:name":"Talleres Pereiro S.c.",
    "wof:placetype":"venue"
},
  "geometry": {"coordinates":[-7.9537248611,42.4104118347],"type":"Point"}
}