{
  "type": "Feature",
  "properties": {
    "iso:country":"ES",
    "sg:address":"Calle de Embajadores, 147",
    "sg:city":"Madrid",
    "sg:orig_category":"Agentes, Concesionarios Y Sucursales De Veh\u00cdculos",
    "sg:phone":"+34 915 27 36 74",
    "sg:postcode":"28045",
    "sg:province":"Madrid",
    "wof:name":"Pemauto S.l.",
    "wof:placetype":"venue"
},
  "geometry": {"coordinates":[-3.6961743832,40.3963851929],"type":"Point"}
}