{
  "type": "Feature",
  "properties": {
    "addr:full":"Praz Irmans Garcia Naveira, 26 Betanzos La Coru\u00f1a 15300",
    "addr:housenumber":"26",
    "addr:postcode":"15300",
    "addr:street":"Praz Irmans Garcia Naveira;La",
    "iso:country":"ES",
    "sg:address":"Praz Irmans Garcia Naveira, 26",
    "sg:city":"Betanzos",
    "sg:orig_category":"Carnicer\u00cdas, Carnicer\u00cdas",
    "sg:phone":"+34 981 77 13 10",
    "sg:postcode":"15300",
    "sg:province":"La Coru\u00f1a",
    "wof:name":"Lopez Regueira Jose",
    "wof:placetype":"venue"
},
  "geometry": {"coordinates":[-8.2098836899,43.2795906067],"type":"Point"}
}