{
  "type": "Feature",
  "properties": {
    "addr:full":"Calle de Nogueras (las), 7 Utiel Valencia 46300",
    "addr:housenumber":"7",
    "addr:postcode":"46300",
    "addr:street":"Calle De Nogueras Las",
    "iso:country":"ES",
    "sg:address":"Calle de Nogueras (las), 7",
    "sg:city":"Utiel",
    "sg:orig_category":"Reposter\u00cdas",
    "sg:phone":"+34 962 17 40 46",
    "sg:postcode":"46300",
    "sg:province":"Valencia",
    "wof:name":"Gallego Palacios Jose",
    "wof:placetype":"venue"
},
  "geometry": {"coordinates":[-1.2008789778,39.5656051636],"type":"Point"}
}