{
  "type": "Feature",
  "properties": {
    "iso:country":"ES",
    "sg:address":"Calle de Melchor Fernandez Almagro, 86",
    "sg:city":"Madrid",
    "sg:orig_category":"Ropa Para Se\u00d1oras (al Por Menor)",
    "sg:phone":"+34 917 38 15 05",
    "sg:postcode":"28029",
    "sg:province":"Madrid",
    "wof:name":"Consulting Melchor -86 Sl",
    "wof:placetype":"venue"
},
  "geometry": {"coordinates":[-3.7110168934,40.4754371643],"type":"Point"}
}