{
  "type": "Feature",
  "properties": {
    "addr:full":"Pl. Pi\u00f1a, 4 Bollullos Par Condado Huelva 21710",
    "addr:housenumber":"4",
    "addr:postcode":"21710",
    "addr:street":"Pl. Pin\u0303A",
    "iso:country":"ES",
    "sg:address":"Pl. Pi\u00f1a, 4",
    "sg:city":"Bollullos Par Condado",
    "sg:orig_category":"Molduras, Junquillos, Listones Y Molduras Perforadas",
    "sg:phone":"+34 959 41 06 55",
    "sg:postcode":"21710",
    "sg:province":"Huelva",
    "wof:name":"Iglesias Garcia Jose Joaquin",
    "wof:placetype":"venue"
},
  "geometry": {"coordinates":[-6.5419440269,37.3377761841],"type":"Point"}
}