{
  "type": "Feature",
  "properties": {
    "addr:full":"Calle de Alcarria (de La), 7 Coslada Madrid 28820",
    "addr:housenumber":"7",
    "addr:postcode":"28820",
    "addr:street":"Calle De Alcarria De La",
    "iso:country":"ES",
    "sg:address":"Calle de Alcarria (de La), 7",
    "sg:city":"Coslada",
    "sg:orig_category":"Pintura, Barniz, Productos Asimilables (fabricaci\u00d3n, Al Por Mayor)",
    "sg:phone":"+34 916 73 86 93",
    "sg:postcode":"28820",
    "sg:province":"Madrid",
    "wof:name":"Xylazel S.a.",
    "wof:placetype":"venue"
},
  "geometry": {"coordinates":[-3.5493149757,40.4309844971],"type":"Point"}
}