{
  "type": "Feature",
  "properties": {
    "addr:full":"Avda Peru (del), 12 Cadiz C\u00e1diz 11007",
    "addr:housenumber":"12",
    "addr:postcode":"11007",
    "addr:street":"Avda Peru Del",
    "iso:country":"ES",
    "sg:address":"Avda Peru (del), 12",
    "sg:city":"Cadiz",
    "sg:orig_category":"Estancos",
    "sg:phone":"+34 956 25 87 58",
    "sg:postcode":"11007",
    "sg:province":"C\u00e1diz",
    "wof:name":"Cerezo Hormigo Manuel",
    "wof:placetype":"venue"
},
  "geometry": {"coordinates":[-6.2766900063,36.518196106],"type":"Point"}
}