{
  "type": "Feature",
  "properties": {
    "addr:full":"Calle de Corredera Del Cristo, 27 Talavera Reina Toledo 45600",
    "addr:housenumber":"27",
    "addr:postcode":"45600",
    "addr:street":"Calle De Corredera Del Cristo",
    "iso:country":"ES",
    "sg:address":"Calle de Corredera Del Cristo, 27",
    "sg:city":"Talavera Reina",
    "sg:orig_category":"Ense\u00d1anza: Profesiones Art\u00cdsticas",
    "sg:phone":"+34 925 82 14 74",
    "sg:postcode":"45600",
    "sg:province":"Toledo",
    "wof:name":"Cid Fernandez David",
    "wof:placetype":"venue"
},
  "geometry": {"coordinates":[-4.8325662613,39.9601669312],"type":"Point"}
}