{
  "type": "Feature",
  "properties": {
    "iso:country":"ES",
    "sg:address":"Carrer de Passeig, 160",
    "sg:city":"Castellar Valles",
    "sg:orig_category":"Asociaciones Y Clubs Deportivos",
    "sg:phone":"+34 937 15 92 48",
    "sg:postcode":"08211",
    "sg:province":"Barcelona",
    "wof:name":"Martin Esteban Jose Manuel",
    "wof:placetype":"venue"
},
  "geometry": {"coordinates":[2.0857300758,41.6151885986],"type":"Point"}
}