{
  "type": "Feature",
  "properties": {
    "addr:full":"Calle de Mariano Mu\u00d1oz Nogues, 3 Teruel Teruel 44001",
    "addr:housenumber":"3",
    "addr:postcode":"44001",
    "addr:street":"Calle De Mariano;Nogues",
    "iso:country":"ES",
    "sg:address":"Calle de Mariano Mu\u00d1oz Nogues, 3",
    "sg:city":"Teruel",
    "sg:classifiers":[
        {
            "category":"Personal",
            "subcategory":"Barber",
            "type":"Services"
        }
    ],
    "sg:phone":"+34 978 60 10 89",
    "sg:postcode":"44001",
    "sg:province":"Teruel",
    "sg:tags":[
        "caballeros",
        "de",
        "peluqueros"
    ],
    "wof:name":"Cuesta Calvo Isidro",
    "wof:placetype":"venue"
},
  "geometry": {"coordinates":[-1.1072499752,40.3430671692],"type":"Point"}
}