{
  "type": "Feature",
  "properties": {
    "addr:full":"Calle de San Ramon, 24 Churriana Vega Granada 18194",
    "addr:housenumber":"24",
    "addr:postcode":"18194",
    "addr:street":"Calle De San Ramon",
    "iso:country":"ES",
    "sg:address":"Calle de San Ramon, 24",
    "sg:city":"Churriana Vega",
    "sg:orig_category":"Fabrica, Negocio De Vidrieras, Productos Vidriados Y Espejos",
    "sg:phone":"+34 958 55 33 50",
    "sg:postcode":"18194",
    "sg:province":"Granada",
    "wof:name":"Villalta De La Torre Alfonso",
    "wof:placetype":"venue"
},
  "geometry": {"coordinates":[-3.6773679256,37.1503562927],"type":"Point"}
}