{
  "type": "Feature",
  "properties": {
    "iso:country":"ES",
    "sg:address":"Avda J. G. Walker, 12",
    "sg:city":"Fuente Palmera",
    "sg:orig_category":"Hoteles",
    "sg:phone":"+34 957 63 86 81",
    "sg:postcode":"14120",
    "sg:province":"C\u00f3rdoba",
    "wof:name":"Macrotelefonia Division Andalucia S.l.",
    "wof:placetype":"venue"
},
  "geometry": {"coordinates":[-5.100399971,37.706325531],"type":"Point"}
}