{
  "type": "Feature",
  "properties": {
    "addr:full":"Calle de Dr. Fleming, 1 Paiporta Valencia 46200",
    "addr:housenumber":"1",
    "addr:postcode":"46200",
    "addr:street":"Calle De Dr. Fleming",
    "iso:country":"ES",
    "sg:address":"Calle de Dr. Fleming, 1",
    "sg:city":"Paiporta",
    "sg:orig_category":"Ropa Para Caballeros (al Por Menor)",
    "sg:phone":"+34 963 97 31 99",
    "sg:postcode":"46200",
    "sg:province":"Valencia",
    "wof:name":"Moreno Serrano Amalia",
    "wof:placetype":"venue"
},
  "geometry": {"coordinates":[-0.4157415032,39.4317932129],"type":"Point"}
}