{
  "type": "Feature",
  "properties": {
    "iso:country":"ES",
    "sg:address":"Calle de Rosario, 63",
    "sg:city":"Albacete",
    "sg:orig_category":"Impresiones Sobre Tela",
    "sg:phone":"+34 967 50 23 16",
    "sg:postcode":"02003",
    "sg:province":"Albacete",
    "wof:name":"Encarnacion Plasencia Barbera Y Ana Cebrian Herraiz Cdad",
    "wof:placetype":"venue"
},
  "geometry": {"coordinates":[-1.8582949638,38.9912071228],"type":"Point"}
}