{
  "type": "Feature",
  "properties": {
    "iso:country":"ES",
    "sg:address":"Carr Alba, 17",
    "sg:city":"Palamos",
    "sg:orig_category":"Muebles, Minoristas",
    "sg:phone":"+34 972 31 88 37",
    "sg:postcode":"17230",
    "sg:province":"Girona",
    "wof:name":"Mobles Alba Interiors S.l.",
    "wof:placetype":"venue"
},
  "geometry": {"coordinates":[3.1279499531,41.8473548889],"type":"Point"}
}