{
  "type": "Feature",
  "properties": {
    "addr:full":"Avda Monteazahar, 8 Beniajan Murcia 30570",
    "addr:housenumber":"8",
    "addr:postcode":"30570",
    "addr:street":"Avda Monteazahar",
    "iso:country":"ES",
    "sg:address":"Avda Monteazahar, 8",
    "sg:city":"Beniajan",
    "sg:orig_category":"Ropa Para Se\u00d1oras (al Por Menor)",
    "sg:phone":"+34 968 87 34 81",
    "sg:postcode":"30570",
    "sg:province":"Murcia",
    "wof:name":"Nicolas Olmos Concepcion",
    "wof:placetype":"venue"
},
  "geometry": {"coordinates":[-1.0696400404,37.973690033],"type":"Point"}
}