{
  "type": "Feature",
  "properties": {
    "addr:full":"Calle de Astorga, 57 Salamanca Salamanca 37005",
    "addr:housenumber":"57",
    "addr:postcode":"37005",
    "addr:street":"Calle De Astorga",
    "iso:country":"ES",
    "sg:address":"Calle de Astorga, 57",
    "sg:city":"Salamanca",
    "sg:orig_category":"Alquiler De Casas Y Habitaciones Amuebladas",
    "sg:phone":"+34 923 22 26 15",
    "sg:postcode":"37005",
    "sg:province":"Salamanca",
    "wof:name":"Hermandad Operarias Evangelicas",
    "wof:placetype":"venue"
},
  "geometry": {"coordinates":[-5.6677160263,40.9810791016],"type":"Point"}
}