{
  "type": "Feature",
  "properties": {
    "iso:country":"ES",
    "sg:address":"Calle de Juan Verdeguer, 59",
    "sg:city":"Valencia",
    "sg:orig_category":"Chapister\u00cda",
    "sg:phone":"+34 963 30 45 25",
    "sg:postcode":"46024",
    "sg:province":"Valencia",
    "wof:name":"Ariza Peralta Manuel",
    "wof:placetype":"venue"
},
  "geometry": {"coordinates":[-0.3346059024,39.4588890076],"type":"Point"}
}