{
  "type": "Feature",
  "properties": {
    "iso:country":"ES",
    "sg:address":"Avda Portugal, 18",
    "sg:city":"Logro\u00f1o",
    "sg:orig_category":"Sex\u00d3logos",
    "sg:phone":"+34 941 21 31 74",
    "sg:postcode":"26001",
    "sg:province":"La Rioja",
    "wof:name":"Oraa Baroja Roberto",
    "wof:placetype":"venue"
},
  "geometry": {"coordinates":[-2.4491090775,42.4647216797],"type":"Point"}
}