{
  "type": "Feature",
  "properties": {
    "addr:full":"Calle de Moises De Leon, S/n Le\u00f3n Le\u00f3n 24006",
    "addr:postcode":"24006",
    "addr:street":"Calle De Moises De Leon S / N Leo\u0301N Leo\u0301N",
    "iso:country":"ES",
    "sg:address":"Calle de Moises De Leon, S/n",
    "sg:city":"Le\u00f3n",
    "sg:orig_category":"Delegados, Agentes De Tr\u00c1nsito, Auxiliares De Transporte Internacional",
    "sg:phone":"+34 987 20 66 55",
    "sg:postcode":"24006",
    "sg:province":"Le\u00f3n",
    "wof:name":"Agrupacion Sindical De Transportistas Autonomos De Leon",
    "wof:placetype":"venue"
},
  "geometry": {"coordinates":[-5.5594391823,42.5903739929],"type":"Point"}
}