{
  "type": "Feature",
  "properties": {
    "addr:full":"Calle de Francisco Silvela, 30 Madrid Madrid 28028",
    "addr:housenumber":"30",
    "addr:postcode":"madrid;28028",
    "addr:street":"Calle De Francisco Silvela",
    "iso:country":"ES",
    "sg:address":"Calle de Francisco Silvela, 30",
    "sg:city":"Madrid",
    "sg:orig_category":"Centros M\u00c9dicos Y Sociales, Dispensarios",
    "sg:phone":"+34 913 61 44 13",
    "sg:postcode":"28028",
    "sg:province":"Madrid",
    "wof:name":"Rodriguez Garcia Carlos Manuel",
    "wof:placetype":"venue"
},
  "geometry": {"coordinates":[-3.6718969345,40.4319877625],"type":"Point"}
}