{
  "type": "Feature",
  "properties": {
    "iso:country":"ES",
    "sg:address":"Calle de Cipres, S/n",
    "sg:city":"Zaragoza",
    "sg:classifiers":[
        {
            "category":"Arts & Performance",
            "subcategory":"Art Gallery",
            "type":"Entertainment"
        }
    ],
    "sg:phone":"+34 976 29 63 66",
    "sg:postcode":"50003",
    "sg:province":"Zaragoza",
    "sg:tags":[
        "arte",
        "de",
        "galer\u00cdas"
    ],
    "wof:name":"Difusion Y Promocion De Actividades Plasticas S. A.",
    "wof:placetype":"venue"
},
  "geometry": {"coordinates":[-0.882707715,41.6552848816],"type":"Point"}
}