{
  "type": "Feature",
  "properties": {
    "iso:country":"ES",
    "sg:address":"Calle de Agustin De Bethencourt, 23",
    "sg:city":"Puerto Cruz",
    "sg:orig_category":"Dietistas",
    "sg:phone":"+34 922 38 58 19",
    "sg:postcode":"38400",
    "sg:province":"Santa Cruz De Tenerife",
    "wof:name":"Cc.bb. El Almut",
    "wof:placetype":"venue"
},
  "geometry": {"coordinates":[-16.5488834381,28.415719986],"type":"Point"}
}