{
  "type": "Feature",
  "properties": {
    "addr:full":"Avda Marbella, 21 Coripe Sevilla 41780",
    "addr:housenumber":"21",
    "addr:postcode":"41780",
    "addr:street":"Avda Marbella",
    "iso:country":"ES",
    "sg:address":"Avda Marbella, 21",
    "sg:city":"Coripe",
    "sg:orig_category":"Reciclaje Y Tratamiento De Desechos Varios",
    "sg:phone":"+34 955 85 85 41",
    "sg:postcode":"41780",
    "sg:province":"Sevilla",
    "wof:name":"Pedro Jimenez Luna S.l.",
    "wof:placetype":"venue"
},
  "geometry": {"coordinates":[-5.439912796,36.9734992981],"type":"Point"}
}