{
  "type": "Feature",
  "properties": {
    "addr:full":"Ptge Clave, 2 Sabadell Barcelona 08201",
    "addr:housenumber":"2",
    "addr:postcode":"08201",
    "addr:street":"Ptge Clave",
    "iso:country":"ES",
    "sg:address":"Ptge Clave, 2",
    "sg:city":"Sabadell",
    "sg:orig_category":"Construcci\u00d3n Mec\u00c1nica",
    "sg:phone":"+34 937 25 97 74",
    "sg:postcode":"08201",
    "sg:province":"Barcelona",
    "sg:website":"www.conformetal.com",
    "wof:name":"Conformados Metalicos S.l. Comesa",
    "wof:placetype":"venue"
},
  "geometry": {"coordinates":[2.1023089886,41.5446205139],"type":"Point"}
}