{
  "type": "Feature",
  "properties": {
    "iso:country":"ES",
    "sg:address":"Avda Maria Auxiliadora, 21",
    "sg:city":"Badajoz",
    "sg:orig_category":"Administradores De Bienes Y Delegados De Comunidades De Propietarios",
    "sg:phone":"+34 924 26 18 67",
    "sg:postcode":"06011",
    "sg:province":"Badajoz",
    "wof:name":"Gamcor 13 S.l.",
    "wof:placetype":"venue"
},
  "geometry": {"coordinates":[-6.9799890518,38.868560791],"type":"Point"}
}