{
  "type": "Feature",
  "properties": {
    "iso:country":"ES",
    "sg:address":"Bard Francisco De Quevedo, 18",
    "sg:city":"Arahal",
    "sg:orig_category":"Carnicer\u00cdas, Carnicer\u00cdas",
    "sg:phone":"+34 955 84 10 23",
    "sg:postcode":"41600",
    "sg:province":"Sevilla",
    "wof:name":"Hermoso Sanchez Daniel",
    "wof:placetype":"venue"
},
  "geometry": {"coordinates":[-5.5384907722,37.2617416382],"type":"Point"}
}