{
  "type": "Feature",
  "properties": {
    "iso:country":"ES",
    "sg:address":"Calle de Diego De Leon, 11",
    "sg:city":"Madrid",
    "sg:orig_category":"M\u00c9dicos: Cirug\u00cda Pl\u00c1stica, Reconstructiva Y Est\u00c9tica",
    "sg:phone":"+34 915 62 16 70",
    "sg:postcode":"28006",
    "sg:province":"Madrid",
    "wof:name":"Cuadrado De Vicente Luis",
    "wof:placetype":"venue"
},
  "geometry": {"coordinates":[-3.6842558384,40.4350128174],"type":"Point"}
}