{
  "type": "Feature",
  "properties": {
    "addr:full":"Avda San Jose, 29 Zaragoza Zaragoza 50013",
    "addr:housenumber":"29",
    "addr:postcode":"50013",
    "addr:street":"Avda San Jose",
    "iso:country":"ES",
    "sg:address":"Avda San Jose, 29",
    "sg:city":"Zaragoza",
    "sg:classifiers":[
        {
            "category":"Personal",
            "subcategory":"Barber",
            "type":"Services"
        }
    ],
    "sg:phone":"+34 976 59 26 51",
    "sg:postcode":"50013",
    "sg:province":"Zaragoza",
    "sg:tags":[
        "caballeros",
        "de",
        "peluqueros"
    ],
    "wof:name":"Ferrer Villuendas Cesar",
    "wof:placetype":"venue"
},
  "geometry": {"coordinates":[-0.8725939989,41.6439590454],"type":"Point"}
}