{
  "type": "Feature",
  "properties": {
    "iso:country":"ES",
    "sg:address":"Calle de Calasparra, 9",
    "sg:city":"Canteras",
    "sg:orig_category":"Peluquer\u00cdas, Peluquer\u00cda Mixta",
    "sg:phone":"+34 968 53 82 56",
    "sg:postcode":"30394",
    "sg:province":"Murcia",
    "wof:name":"Surtel S. L.",
    "wof:placetype":"venue"
},
  "geometry": {"coordinates":[-1.0425169468,37.6118011475],"type":"Point"}
}