{
  "type": "Feature",
  "properties": {
    "iso:country":"ES",
    "sg:address":"Avda Sudamerica (de), S/n",
    "sg:city":"Jerez De La Frontera",
    "sg:orig_category":"Papeler\u00cdas: Art\u00cdculos (al Por Mayor)",
    "sg:phone":"+34 956 31 15 39",
    "sg:postcode":"11407",
    "sg:province":"C\u00e1diz",
    "wof:name":"Medina Rios Manuel",
    "wof:placetype":"venue"
},
  "geometry": {"coordinates":[-6.1240200996,36.7033081055],"type":"Point"}
}