{
  "type": "Feature",
  "properties": {
    "iso:country":"ES",
    "sg:address":"Carrer de Nadal, 49",
    "sg:city":"Sabadell",
    "sg:orig_category":"Iglesias Cristianas Diversas",
    "sg:phone":"+34 937 12 44 60",
    "sg:postcode":"08204",
    "sg:province":"Barcelona",
    "wof:name":"Testigos Cristianos De Jehova",
    "wof:placetype":"venue"
},
  "geometry": {"coordinates":[2.1157848835,41.5255584717],"type":"Point"}
}