{
  "type": "Feature",
  "properties": {
    "addr:full":"Plaz Posada De San Antonio, 1 Leganes Madrid 28912",
    "addr:housenumber":"1",
    "addr:postcode":"28912",
    "addr:street":"Antonio",
    "iso:country":"ES",
    "sg:address":"Plaz Posada De San Antonio, 1",
    "sg:city":"Leganes",
    "sg:orig_category":"Oficinas Y Gesti\u00d3n De Inmuebles",
    "sg:phone":"+34 916 93 27 51",
    "sg:postcode":"28912",
    "sg:province":"Madrid",
    "sg:website":"www.larcovi.es",
    "wof:name":"Larcovi S.a.l.",
    "wof:placetype":"venue"
},
  "geometry": {"coordinates":[-3.7630169392,40.3278083801],"type":"Point"}
}