{
  "type": "Feature",
  "properties": {
    "iso:country":"ES",
    "sg:address":"Crri Manresa, S/n",
    "sg:city":"Torre De La Manresa",
    "sg:orig_category":"Artes Gr\u00c1ficas, Artes Pl\u00c1sticas (curso)",
    "sg:phone":"+34 968 30 25 77",
    "sg:postcode":"30006",
    "sg:province":"Murcia",
    "wof:name":"Murciagraf S.a.l.",
    "wof:placetype":"venue"
},
  "geometry": {"coordinates":[-1.1302490234,37.9829597473],"type":"Point"}
}