{
  "type": "Feature",
  "properties": {
    "iso:country":"ES",
    "sg:address":"Calle de Hiedra, 12",
    "sg:city":"Villarrobledo",
    "sg:orig_category":"Productores Recolectores, Venta Directa De Vinos",
    "sg:phone":"+34 967 14 04 82",
    "sg:postcode":"02600",
    "sg:province":"Albacete",
    "wof:name":"Velasco Martinez Cesar",
    "wof:placetype":"venue"
},
  "geometry": {"coordinates":[-2.6077480316,39.2641983032],"type":"Point"}
}