{
  "type": "Feature",
  "properties": {
    "iso:country":"ES",
    "sg:address":"Calle de Parroco Perez Mu\u00d1oz, S/n",
    "sg:city":"Deifontes",
    "sg:orig_category":"Chapister\u00cda",
    "sg:phone":"+34 958 40 71 34",
    "sg:postcode":"18570",
    "sg:province":"Granada",
    "wof:name":"Ca\u00f1adas Lopez Antonio",
    "wof:placetype":"venue"
},
  "geometry": {"coordinates":[-3.595181942,37.3277053833],"type":"Point"}
}