{
  "type": "Feature",
  "properties": {
    "addr:full":"C/ Bons Aires, 6 Llucmajor Islas Baleares 07620",
    "addr:housenumber":"6",
    "addr:postcode":"07620",
    "addr:street":"C / Bons Aires",
    "iso:country":"ES",
    "sg:address":"C/ Bons Aires, 6",
    "sg:city":"Llucmajor",
    "sg:orig_category":"Empresas De Pintura Y Revestimientos",
    "sg:phone":"+34 971 66 09 06",
    "sg:postcode":"07620",
    "sg:province":"Islas Baleares",
    "wof:name":"Bezares Tirado Jesus",
    "wof:placetype":"venue"
},
  "geometry": {"coordinates":[2.8911540508,39.4899711609],"type":"Point"}
}