{
  "type": "Feature",
  "properties": {
    "iso:country":"ES",
    "sg:address":"Calle de Ferial (del), 7",
    "sg:city":"Calamocha",
    "sg:orig_category":"Chapister\u00cda",
    "sg:phone":"+34 978 73 22 21",
    "sg:postcode":"44200",
    "sg:province":"Teruel",
    "wof:name":"Gruas Y Talleres San Blas S.l.",
    "wof:placetype":"venue"
},
  "geometry": {"coordinates":[-1.295877099,40.920124054],"type":"Point"}
}