{
  "type": "Feature",
  "properties": {
    "iso:country":"ES",
    "sg:address":"Azkoitiko Industrialdea, 51",
    "sg:city":"Azkoitia",
    "sg:orig_category":"Rectificaci\u00d3n, Mecanizado, Fresado",
    "sg:phone":"+34 943 85 22 27",
    "sg:postcode":"20720",
    "sg:province":"Guip\u00f9zcoa",
    "wof:name":"Aldalur Oruezagasti Didaka Andoni",
    "wof:placetype":"venue"
},
  "geometry": {"coordinates":[-2.3218460083,43.1737327576],"type":"Point"}
}