{
  "type": "Feature",
  "properties": {
    "addr:full":"Carretera Orriols-la Escala, Km. 0007,0 Saus Girona 17467",
    "addr:postcode":"17467",
    "addr:street":"Carretera Orriols-La Escala Km. 0007,0",
    "iso:country":"ES",
    "sg:address":"Carretera Orriols-la Escala, Km. 0007,0",
    "sg:city":"Saus",
    "sg:orig_category":"Distribuci\u00d3n De Petr\u00d3leo Y Derivados",
    "sg:phone":"+34 972 79 41 20",
    "sg:postcode":"17467",
    "sg:province":"Girona",
    "wof:name":"E.s.saus S.a.",
    "wof:placetype":"venue"
},
  "geometry": {"coordinates":[2.9903941154,42.155254364],"type":"Point"}
}