{
  "type": "Feature",
  "properties": {
    "addr:full":"Carrer de Canigo, 84 Barcelona Barcelona 08031",
    "addr:housenumber":"84",
    "addr:postcode":"08031",
    "addr:street":"Carrer De Canigo",
    "iso:country":"ES",
    "sg:address":"Carrer de Canigo, 84",
    "sg:city":"Barcelona",
    "sg:orig_category":"Ingenier\u00cda, Centros De Estudios (diversos)",
    "sg:phone":"+34 934 27 54 55",
    "sg:postcode":"08031",
    "sg:province":"Barcelona",
    "wof:name":"Mosegui Gimenez Agusti",
    "wof:placetype":"venue"
},
  "geometry": {"coordinates":[2.1581289768,41.4369850159],"type":"Point"}
}