{
  "type": "Feature",
  "properties": {
    "iso:country":"ES",
    "sg:address":"Carrer de Pont (el), 37",
    "sg:city":"Torello",
    "sg:orig_category":"Confiter\u00cdas, Chocolater\u00cdas (al Por Menor)",
    "sg:phone":"+34 938 59 36 14",
    "sg:postcode":"08570",
    "sg:province":"Barcelona",
    "wof:name":"Farran Autet Mireya",
    "wof:placetype":"venue"
},
  "geometry": {"coordinates":[2.2625749111,42.048374176],"type":"Point"}
}