{
  "type": "Feature",
  "properties": {
    "iso:country":"ES",
    "sg:address":"Calle de Bernart Etxepare, 5",
    "sg:city":"Galdakao",
    "sg:orig_category":"Molduras, Junquillos, Listones Y Molduras Perforadas",
    "sg:phone":"+34 944 57 15 15",
    "sg:postcode":"48960",
    "sg:province":"Vizcaya",
    "wof:name":"Alberto Bezos Soto",
    "wof:placetype":"venue"
},
  "geometry": {"coordinates":[-2.8436613083,43.2324180603],"type":"Point"}
}