{
  "type": "Feature",
  "properties": {
    "addr:full":"Calle de Iba\u00d1ez Marin, 9 Madrid Madrid 28019",
    "addr:housenumber":"9",
    "addr:postcode":"madrid;28019",
    "addr:street":"Calle De Iban\u0303Ez Marin",
    "iso:country":"ES",
    "sg:address":"Calle de Iba\u00d1ez Marin, 9",
    "sg:city":"Madrid",
    "sg:orig_category":"Bisuter\u00cda, Joyer\u00cda, Relojer\u00cda (al Por Menor)",
    "sg:phone":"+34 914 72 08 32",
    "sg:postcode":"28019",
    "sg:province":"Madrid",
    "wof:name":"Luyjo S.l.",
    "wof:placetype":"venue"
},
  "geometry": {"coordinates":[-3.7309510708,40.3958511353],"type":"Point"}
}