{
  "type": "Feature",
  "properties": {
    "addr:full":"Calle de San Roque, 1 Santos Salamanca 37768",
    "addr:housenumber":"1",
    "addr:postcode":"37768",
    "addr:street":"Calle De San Roque",
    "iso:country":"ES",
    "sg:address":"Calle de San Roque, 1",
    "sg:city":"Santos",
    "sg:orig_category":"M\u00c1rmoles, Granitos Y Piedras Naturales",
    "sg:phone":"+34 923 59 21 46",
    "sg:postcode":"37768",
    "sg:province":"Salamanca",
    "wof:name":"Sociedad Cooperativa Limitada El Cubillo",
    "wof:placetype":"venue"
},
  "geometry": {"coordinates":[-5.7980899811,40.5422821045],"type":"Point"}
}