{
  "type": "Feature",
  "properties": {
    "iso:country":"ES",
    "sg:address":"Calle de Bolos (los), 1",
    "sg:city":"San Cristobal De La Laguna",
    "sg:orig_category":"Supermercados Y Hipermercados",
    "sg:phone":"+34 922 26 49 01",
    "sg:postcode":"38201",
    "sg:province":"Santa Cruz De Tenerife",
    "wof:name":"Comercial Jesuman",
    "wof:placetype":"venue"
},
  "geometry": {"coordinates":[-16.320526123,28.4908733368],"type":"Point"}
}