{
  "type": "Feature",
  "properties": {
    "addr:full":"Carrer de Sant Miquel, 19 Reus Tarragona 43201",
    "addr:housenumber":"19",
    "addr:postcode":"43201",
    "addr:street":"Carrer De Sant Miquel",
    "iso:country":"ES",
    "sg:address":"Carrer de Sant Miquel, 19",
    "sg:city":"Reus",
    "sg:orig_category":"Alimentaci\u00d3n General (al Por Mayor)",
    "sg:phone":"+34 977 34 11 03",
    "sg:postcode":"43201",
    "sg:province":"Tarragona",
    "wof:name":"P.j.gene Comercial S.l.",
    "wof:placetype":"venue"
},
  "geometry": {"coordinates":[1.1080009937,41.1579666138],"type":"Point"}
}