{
  "type": "Feature",
  "properties": {
    "iso:country":"ES",
    "sg:address":"Rbla Davallades, 8",
    "sg:city":"Vic",
    "sg:orig_category":"Bisuter\u00cda, Joyer\u00cda, Relojer\u00cda (al Por Menor)",
    "sg:phone":"+34 938 86 34 43",
    "sg:postcode":"08500",
    "sg:province":"Barcelona",
    "wof:name":"Salas De Los Ojos Ramon",
    "wof:placetype":"venue"
},
  "geometry": {"coordinates":[2.2534000874,41.9307327271],"type":"Point"}
}