{
  "type": "Feature",
  "properties": {
    "addr:full":"Calle de Procesiones (de Las), 8 Mejorada Campo Madrid 28840",
    "addr:housenumber":"8",
    "addr:postcode":"28840",
    "addr:street":"Calle De Procesiones De Las",
    "iso:country":"ES",
    "sg:address":"Calle de Procesiones (de Las), 8",
    "sg:city":"Mejorada Campo",
    "sg:orig_category":"Textiles: Suministros Y Accesorios Para Industrias (fabricaci\u00d3n, Negocio)",
    "sg:phone":"+34 916 79 30 19",
    "sg:postcode":"28840",
    "sg:province":"Madrid",
    "wof:name":"Tecnicos Analisis De Laboratorio",
    "wof:placetype":"venue"
},
  "geometry": {"coordinates":[-3.4886903763,40.3975028992],"type":"Point"}
}