{
  "type": "Feature",
  "properties": {
    "iso:country":"ES",
    "sg:address":"Bo. Gardea, S/n",
    "sg:city":"Llodio",
    "sg:orig_category":"Calderer\u00cda",
    "sg:phone":"+34 946 72 85 05",
    "sg:postcode":"01400",
    "sg:province":"\u00c1lava",
    "sg:website":"www.gometegui.com",
    "wof:name":"Talleres Gometegui S. A.",
    "wof:placetype":"venue"
},
  "geometry": {"coordinates":[-2.97853899,43.1305541992],"type":"Point"}
}