{
  "type": "Feature",
  "properties": {
    "iso:country":"ES",
    "sg:address":"Zona Aldura, 60",
    "sg:city":"Errenteria",
    "sg:orig_category":"Equitaci\u00d3n Y Centros De H\u00cdpica",
    "sg:phone":"+34 943 51 03 99",
    "sg:postcode":"20100",
    "sg:province":"Guip\u00f9zcoa",
    "wof:name":"Club Hipico Listorreta S.l.",
    "wof:placetype":"venue"
},
  "geometry": {"coordinates":[-1.8970370293,43.3210067749],"type":"Point"}
}