{
  "type": "Feature",
  "properties": {
    "iso:country":"ES",
    "sg:address":"Calle de Velazquez, 17",
    "sg:city":"Elda",
    "sg:orig_category":"Herboristas (al Por Menor)",
    "sg:phone":"+34 965 39 38 40",
    "sg:postcode":"03600",
    "sg:province":"Alicante",
    "wof:name":"Almendros Martinez Maria Ventura",
    "wof:placetype":"venue"
},
  "geometry": {"coordinates":[-0.7968543172,38.4708175659],"type":"Point"}
}