{
  "type": "Feature",
  "properties": {
    "iso:country":"ES",
    "sg:address":"Carrer de Lluis Pascual Roca, 59",
    "sg:city":"S. Boi Llobregat",
    "sg:orig_category":"Loter\u00cda Y T\u00d3mbola",
    "sg:phone":"+34 936 40 75 39",
    "sg:postcode":"08830",
    "sg:province":"Barcelona",
    "wof:name":"Romano Espinosa Guillermo",
    "wof:placetype":"venue"
},
  "geometry": {"coordinates":[2.036730051,41.3448295593],"type":"Point"}
}