{
  "type": "Feature",
  "properties": {
    "addr:full":"Calle de Valdeon, 16 Fuenlabrada Madrid 28947",
    "addr:housenumber":"16",
    "addr:postcode":"28947",
    "addr:street":"Calle De Valdeon",
    "iso:country":"ES",
    "sg:address":"Calle de Valdeon, 16",
    "sg:city":"Fuenlabrada",
    "sg:orig_category":"Fabricaci\u00d3n De Sobres, Bolsas Y Fundas",
    "sg:phone":"+34 916 42 20 44",
    "sg:postcode":"28947",
    "sg:province":"Madrid",
    "wof:name":"Xinglong Moda 2000 S.l.",
    "wof:placetype":"venue"
},
  "geometry": {"coordinates":[-3.7499227524,40.2709999084],"type":"Point"}
}