{
  "type": "Feature",
  "properties": {
    "addr:full":"Calle de Cruz Blanca, 4 Vitoria-gasteiz \u00c1lava 01012",
    "addr:housenumber":"4",
    "addr:postcode":"01012",
    "addr:street":"Calle De Cruz Blanca",
    "iso:country":"ES",
    "sg:address":"Calle de Cruz Blanca, 4",
    "sg:city":"Vitoria-gasteiz",
    "sg:orig_category":"Internados & Ense\u00d1anza Privada",
    "sg:phone":"+34 945 21 73 94",
    "sg:postcode":"01012",
    "sg:province":"\u00c1lava",
    "wof:name":"Colegio Presentacion De Maria",
    "wof:placetype":"venue"
},
  "geometry": {"coordinates":[-2.6774439812,42.852394104],"type":"Point"}
}