{
  "type": "Feature",
  "properties": {
    "iso:country":"ES",
    "sg:address":"Carr Major, 70",
    "sg:city":"Jonquera",
    "sg:orig_category":"Bisuter\u00cda, Joyer\u00cda, Relojer\u00cda (al Por Menor)",
    "sg:phone":"+34 972 55 60 41",
    "sg:postcode":"17700",
    "sg:province":"Girona",
    "wof:name":"Artigas Arbat Bea",
    "wof:placetype":"venue"
},
  "geometry": {"coordinates":[2.8730316162,42.4181747437],"type":"Point"}
}