{
  "type": "Feature",
  "properties": {
    "addr:full":"Calle de Graciano Atienza, 31 Villarrobledo Albacete 02600",
    "addr:housenumber":"31",
    "addr:postcode":"02600",
    "addr:street":"Calle De Graciano Atienza",
    "iso:country":"ES",
    "sg:address":"Calle de Graciano Atienza, 31",
    "sg:city":"Villarrobledo",
    "sg:orig_category":"Calzados Ortop\u00c9dicos",
    "sg:phone":"+34 967 14 01 37",
    "sg:postcode":"02600",
    "sg:province":"Albacete",
    "wof:name":"Ruescas Marquez Enrique",
    "wof:placetype":"venue"
},
  "geometry": {"coordinates":[-2.6040520668,39.2663917542],"type":"Point"}
}