{
  "type": "Feature",
  "properties": {
    "addr:full":"Carrer de Ausias March, 43 Mutxamel Alicante 03110",
    "addr:housenumber":"43",
    "addr:postcode":"03110",
    "addr:street":"Carrer De Ausias March",
    "iso:country":"ES",
    "sg:address":"Carrer de Ausias March, 43",
    "sg:city":"Mutxamel",
    "sg:orig_category":"Reparaciones Y Remolcado De Veh\u00cdculos",
    "sg:phone":"+34 965 95 14 74",
    "sg:postcode":"03110",
    "sg:province":"Alicante",
    "wof:name":"Egea Sanchez Emilia",
    "wof:placetype":"venue"
},
  "geometry": {"coordinates":[-0.4443649948,38.4194831848],"type":"Point"}
}