{
  "type": "Feature",
  "properties": {
    "iso:country":"ES",
    "sg:address":"Carrer de Sinies (de Les), 7",
    "sg:city":"Salou",
    "sg:orig_category":"Empresas De Limpieza",
    "sg:phone":"+34 977 38 32 33",
    "sg:postcode":"43840",
    "sg:province":"Tarragona",
    "wof:name":"Salou Net.s.l.",
    "wof:placetype":"venue"
},
  "geometry": {"coordinates":[1.1307079792,41.0821495056],"type":"Point"}
}