{
  "type": "Feature",
  "properties": {
    "iso:country":"ES",
    "sg:address":"Calle de Francisco Cano, 3",
    "sg:city":"Fuengirola",
    "sg:orig_category":"Suministros Para Hoteles",
    "sg:phone":"+34 952 47 35 13",
    "sg:postcode":"29640",
    "sg:province":"M\u00e1laga",
    "wof:name":"Moreno Morales Francisco",
    "wof:placetype":"venue"
},
  "geometry": {"coordinates":[-4.6138358116,36.5538787842],"type":"Point"}
}