{
  "type": "Feature",
  "properties": {
    "iso:country":"ES",
    "sg:address":"Ctra Hondon Nieves, S/n",
    "sg:city":"Hondon Frailes",
    "sg:orig_category":"Explotaci\u00d3n De Canteras",
    "sg:phone":"+34 966 67 77 22",
    "sg:postcode":"03689",
    "sg:province":"Alicante",
    "wof:name":"Extraccion De Aridos Sierra Negra S.l.",
    "wof:placetype":"venue"
},
  "geometry": {"coordinates":[-0.9337959886,38.3050117493],"type":"Point"}
}