{
  "type": "Feature",
  "properties": {
    "iso:country":"ES",
    "sg:address":"Calle de Faustino Garralda, 4",
    "sg:city":"Burlada",
    "sg:orig_category":"Tiendas De Grano, Frutas Y Legumbres Secas (al Por Menor)",
    "sg:phone":"+34 948 24 26 19",
    "sg:postcode":"31600",
    "sg:province":"Navarra",
    "wof:name":"Perez De Ciriza Oficialdegui Maria",
    "wof:placetype":"venue"
},
  "geometry": {"coordinates":[-1.6151499748,42.8240661621],"type":"Point"}
}