{
  "type": "Feature",
  "properties": {
    "iso:country":"ES",
    "sg:address":"Avda Cantabria, 1",
    "sg:city":"Reinosa",
    "sg:orig_category":"Comercio De Piezas De Recambio Y De Accesorios De Veh\u00cdculos, Veh\u00cdculos Industriales",
    "sg:phone":"+34 942 75 19 30",
    "sg:postcode":"39200",
    "sg:province":"Cantabria",
    "wof:name":"Movilla Quintano Jose",
    "wof:placetype":"venue"
},
  "geometry": {"coordinates":[-4.1353478432,43.0022315979],"type":"Point"}
}