{
  "type": "Feature",
  "properties": {
    "iso:country":"ES",
    "sg:address":"Carrer de Pla De Fornells, 8",
    "sg:city":"Barcelona",
    "sg:orig_category":"Reposter\u00cdas",
    "sg:phone":"+34 932 76 00 58",
    "sg:postcode":"08042",
    "sg:province":"Barcelona",
    "wof:name":"Aixela Rente Antonio",
    "wof:placetype":"venue"
},
  "geometry": {"coordinates":[2.1766676903,41.4461898804],"type":"Point"}
}