{
  "type": "Feature",
  "properties": {
    "addr:full":"Calle de Gran Via De Colon, 54 Granada Granada 18010",
    "addr:housenumber":"54",
    "addr:postcode":"18010",
    "addr:street":"Calle De Gran Via De Colon",
    "iso:country":"ES",
    "sg:address":"Calle de Gran Via De Colon, 54",
    "sg:city":"Granada",
    "sg:orig_category":"Farmacias",
    "sg:phone":"+34 958 20 28 16",
    "sg:postcode":"18010",
    "sg:province":"Granada",
    "wof:name":"Lopez Lopez Jose Maria",
    "wof:placetype":"venue"
},
  "geometry": {"coordinates":[-3.6009290218,37.182346344],"type":"Point"}
}