{
  "type": "Feature",
  "properties": {
    "iso:country":"ES",
    "sg:address":"Avda Plaza De Toros, 44",
    "sg:city":"Benavente",
    "sg:orig_category":"Ferreter\u00cda (diversos)",
    "sg:phone":"+34 980 63 04 90",
    "sg:postcode":"49600",
    "sg:province":"Zamora",
    "wof:name":"Tosal Garcia Gregorio",
    "wof:placetype":"venue"
},
  "geometry": {"coordinates":[-5.6732468605,42.0078887939],"type":"Point"}
}