{
  "type": "Feature",
  "properties": {
    "addr:full":"Avda Malaga (de), S/n Yunquera Henares Guadalajara 19210",
    "addr:postcode":"19210",
    "addr:street":"Avda Malaga De S / N",
    "iso:country":"ES",
    "sg:address":"Avda Malaga (de), S/n",
    "sg:city":"Yunquera Henares",
    "sg:orig_category":"Cr\u00cda De Animales",
    "sg:phone":"+34 949 33 04 17",
    "sg:postcode":"19210",
    "sg:province":"Guadalajara",
    "wof:name":"Fraile Corral Francisco",
    "wof:placetype":"venue"
},
  "geometry": {"coordinates":[-3.1713290215,40.7567939758],"type":"Point"}
}