{
  "type": "Feature",
  "properties": {
    "addr:full":"Plaz Espa\u00d1a, 6 Calzada Calatrava Ciudad Real 13370",
    "addr:housenumber":"6",
    "addr:postcode":"13370",
    "addr:street":"Plaz Espan\u0303A",
    "iso:country":"ES",
    "sg:address":"Plaz Espa\u00d1a, 6",
    "sg:city":"Calzada Calatrava",
    "sg:orig_category":"Bares, Piano",
    "sg:phone":"+34 926 87 50 32",
    "sg:postcode":"13370",
    "sg:province":"Ciudad Real",
    "wof:name":"Garcia Garcia Santos",
    "wof:placetype":"venue"
},
  "geometry": {"coordinates":[-3.7771589756,38.7046661377],"type":"Point"}
}