{
  "type": "Feature",
  "properties": {
    "iso:country":"ES",
    "sg:address":"Calle de Santa Ines, 2",
    "sg:city":"Gijon",
    "sg:orig_category":"Abogados",
    "sg:phone":"+34 985 17 07 14",
    "sg:postcode":"33207",
    "sg:province":"Asturias",
    "wof:name":"Caso Roiz Soledad",
    "wof:placetype":"venue"
},
  "geometry": {"coordinates":[-5.6674761772,43.5376205444],"type":"Point"}
}