{
  "type": "Feature",
  "properties": {
    "iso:country":"ES",
    "sg:address":"Mayor, 16",
    "sg:city":"Monovar",
    "sg:orig_category":"Electricidad: Equipos Industriales, Componentes (fabricaci\u00d3n)",
    "sg:phone":"+34 965 47 24 03",
    "sg:postcode":"03640",
    "sg:province":"Alicante",
    "wof:name":"Perez Cambra S.l.",
    "wof:placetype":"venue"
},
  "geometry": {"coordinates":[-0.8483089805,38.4369010925],"type":"Point"}
}