{
  "type": "Feature",
  "properties": {
    "iso:country":"ES",
    "sg:address":"Rbla Can Mora, 17",
    "sg:city":"S. Cugat Valles",
    "sg:orig_category":"Doctores En Medicina",
    "sg:phone":"+34 936 75 19 69",
    "sg:postcode":"08172",
    "sg:province":"Barcelona",
    "wof:name":"Conillera Plana Cristina",
    "wof:placetype":"venue"
},
  "geometry": {"coordinates":[2.081610918,41.4685020447],"type":"Point"}
}