{
  "type": "Feature",
  "properties": {
    "iso:country":"ES",
    "sg:address":"Calle de Bilbao, 12",
    "sg:city":"Zaragoza",
    "sg:orig_category":"Agencias Y Agentes Comerciales, Representantes",
    "sg:phone":"+34 976 21 24 36",
    "sg:postcode":"50004",
    "sg:province":"Zaragoza",
    "wof:name":"Lapuerta Perez Jose",
    "wof:placetype":"venue"
},
  "geometry": {"coordinates":[-0.8863415122,41.6487197876],"type":"Point"}
}