{
  "type": "Feature",
  "properties": {
    "addr:full":"Calle de Catedratico D.j.cisneros, 27 Alacant Alicante 03012",
    "addr:housenumber":"27",
    "addr:postcode":"03012",
    "addr:street":"Calle De Catedratico D.J.Cisneros",
    "iso:country":"ES",
    "sg:address":"Calle de Catedratico D.j.cisneros, 27",
    "sg:city":"Alacant",
    "sg:orig_category":"Supermercados Y Hipermercados",
    "sg:phone":"+34 965 25 07 19",
    "sg:postcode":"03012",
    "sg:province":"Alicante",
    "wof:name":"Consum Sociedad Cooperativa Limitada",
    "wof:placetype":"venue"
},
  "geometry": {"coordinates":[-0.4778910875,38.3603363037],"type":"Point"}
}