{
  "type": "Feature",
  "properties": {
    "addr:full":"Pla\u00c7 Agermanament, 8 Vilanova I La Geltru Barcelona 08800",
    "addr:housenumber":"8",
    "addr:postcode":"08800",
    "addr:street":"Agermanament",
    "iso:country":"ES",
    "sg:address":"Pla\u00c7 Agermanament, 8",
    "sg:city":"Vilanova I La Geltru",
    "sg:orig_category":"Peluquer\u00cdas, Peluquer\u00cda Mixta",
    "sg:phone":"+34 938 14 22 94",
    "sg:postcode":"08800",
    "sg:province":"Barcelona",
    "wof:name":"Agermanament S.l.",
    "wof:placetype":"venue"
},
  "geometry": {"coordinates":[1.705232501,41.2381515503],"type":"Point"}
}