{
  "type": "Feature",
  "properties": {
    "addr:full":"Avda Zaragoza, 7 Jaca Huesca 22700",
    "addr:housenumber":"7",
    "addr:postcode":"22700",
    "addr:street":"Avda Zaragoza",
    "iso:country":"ES",
    "sg:address":"Avda Zaragoza, 7",
    "sg:city":"Jaca",
    "sg:orig_category":"Reparaciones Y Remolcado De Veh\u00cdculos",
    "sg:phone":"+34 974 36 07 44",
    "sg:postcode":"22700",
    "sg:province":"Huesca",
    "wof:name":"Hermanos Dominguez S. L.",
    "wof:placetype":"venue"
},
  "geometry": {"coordinates":[-0.5484470129,42.5729484558],"type":"Point"}
}