{
  "type": "Feature",
  "properties": {
    "iso:country":"ES",
    "sg:address":"Llobregat, 12",
    "sg:city":"Peralada",
    "sg:orig_category":"Agricultura: Abastecimiento Y Cosechado (negocio)",
    "sg:phone":"+34 972 53 81 75",
    "sg:postcode":"17491",
    "sg:province":"Girona",
    "wof:name":"Centelles Bech Jose",
    "wof:placetype":"venue"
},
  "geometry": {"coordinates":[3.0114369392,42.3083000183],"type":"Point"}
}