{
  "type": "Feature",
  "properties": {
    "addr:full":"Avda Jose Mesa Y Lopez, 50 Palmas De Gran Canaria Las Palmas 35007",
    "addr:postcode":"35007",
    "addr:street":"Avda Jose Mesa Y Lopez 50",
    "iso:country":"ES",
    "sg:address":"Avda Jose Mesa Y Lopez, 50",
    "sg:city":"Palmas De Gran Canaria",
    "sg:orig_category":"Peluquer\u00cdas",
    "sg:phone":"+34 928 27 93 02",
    "sg:postcode":"35007",
    "sg:province":"Las Palmas",
    "wof:name":"Sunao Las Palmas S.l.",
    "wof:placetype":"venue"
},
  "geometry": {"coordinates":[-15.4346532822,28.1347122192],"type":"Point"}
}