{
  "type": "Feature",
  "properties": {
    "addr:full":"Masos, 403 Pals Girona 17256",
    "addr:housenumber":"403",
    "addr:postcode":"17256",
    "addr:street":"Masos",
    "iso:country":"ES",
    "sg:address":"Masos, 403",
    "sg:city":"Pals",
    "sg:orig_category":"Discapacitados",
    "sg:phone":"+34 972 66 74 89",
    "sg:postcode":"17256",
    "sg:province":"Girona",
    "wof:name":"Asociacion El Trampoli",
    "wof:placetype":"venue"
},
  "geometry": {"coordinates":[3.198182106,41.9823188782],"type":"Point"}
}