{
  "type": "Feature",
  "properties": {
    "iso:country":"ES",
    "sg:address":"Rua Areal (do), 57",
    "sg:city":"Lalin",
    "sg:orig_category":"Material Y Herramientas Agr\u00cdcolas",
    "sg:phone":"+34 986 78 16 35",
    "sg:postcode":"36500",
    "sg:province":"Pontevedra",
    "wof:name":"Riadigos Gonzalez Maria Luz",
    "wof:placetype":"venue"
},
  "geometry": {"coordinates":[-8.1106138229,42.6577606201],"type":"Point"}
}