{
  "type": "Feature",
  "properties": {
    "addr:full":"Avda Derechos Humanos (los), 18 Laredo Cantabria 39770",
    "addr:housenumber":"18",
    "addr:postcode":"39770",
    "addr:street":"Avda Derechos Humanos Los",
    "iso:country":"ES",
    "sg:address":"Avda Derechos Humanos (los), 18",
    "sg:city":"Laredo",
    "sg:orig_category":"Asilos De Ancianos. Centros Privados",
    "sg:phone":"+34 942 60 71 50",
    "sg:postcode":"39770",
    "sg:province":"Cantabria",
    "wof:name":"Gobierno De Cantabria",
    "wof:placetype":"venue"
},
  "geometry": {"coordinates":[-3.4347751141,43.4104270935],"type":"Point"}
}