{
  "type": "Feature",
  "properties": {
    "iso:country":"ES",
    "sg:address":"Pl Marques Del Palmer, 5",
    "sg:city":"Palma",
    "sg:orig_category":"Bisuter\u00cda, Joyer\u00cda, Relojer\u00cda (al Por Menor)",
    "sg:phone":"+34 971 72 15 11",
    "sg:postcode":"07001",
    "sg:province":"Islas Baleares",
    "wof:name":"De La Cruz Gonzalez Azucena",
    "wof:placetype":"venue"
},
  "geometry": {"coordinates":[2.6511969566,39.5709228516],"type":"Point"}
}