{
  "type": "Feature",
  "properties": {
    "iso:country":"ES",
    "sg:address":"Calle de Hermanos Sanchez Del Rio, 16",
    "sg:city":"Haro",
    "sg:orig_category":"Panader\u00cdas, Panader\u00cdas",
    "sg:phone":"+34 941 31 14 39",
    "sg:postcode":"26200",
    "sg:province":"La Rioja",
    "wof:name":"Saez Lopez Manuel",
    "wof:placetype":"venue"
},
  "geometry": {"coordinates":[-2.8502631187,42.5774803162],"type":"Point"}
}