{
  "type": "Feature",
  "properties": {
    "addr:full":"Calle de Gaztambide, 9 Madrid Madrid 28015",
    "addr:housenumber":"9",
    "addr:postcode":"madrid;28015",
    "addr:street":"Calle De Gaztambide",
    "iso:country":"ES",
    "sg:address":"Calle de Gaztambide, 9",
    "sg:city":"Madrid",
    "sg:orig_category":"Ropa Para Se\u00d1oras Y Caballeros (al Por Menor)",
    "sg:phone":"+34 915 43 27 15",
    "sg:postcode":"28015",
    "sg:province":"Madrid",
    "wof:name":"Banco Echeverria S.a",
    "wof:placetype":"venue"
},
  "geometry": {"coordinates":[-3.7159221172,40.4313087463],"type":"Point"}
}