{
  "type": "Feature",
  "properties": {
    "addr:full":"Carrer de Regas, 14 Barcelona Barcelona 08006",
    "addr:housenumber":"14",
    "addr:postcode":"08006",
    "addr:street":"Carrer De Regas",
    "iso:country":"ES",
    "sg:address":"Carrer de Regas, 14",
    "sg:city":"Barcelona",
    "sg:orig_category":"Inform\u00c1tica (estudios, Servicios, Asesor\u00cda, Formaci\u00d3n)",
    "sg:phone":"+34 932 18 44 70",
    "sg:postcode":"08006",
    "sg:province":"Barcelona",
    "wof:name":"Vern Serveis Informatics S.l.",
    "wof:placetype":"venue"
},
  "geometry": {"coordinates":[2.1520240307,41.3988647461],"type":"Point"}
}