{
  "type": "Feature",
  "properties": {
    "iso:country":"ES",
    "sg:address":"Carrer de Compte (d'en), 4",
    "sg:city":"Tarragona",
    "sg:orig_category":"Tapicer\u00cdas",
    "sg:phone":"+34 977 23 68 03",
    "sg:postcode":"43003",
    "sg:province":"Tarragona",
    "wof:name":"Ferrez Bujaldon Pedro",
    "wof:placetype":"venue"
},
  "geometry": {"coordinates":[1.2553889751,41.1181373596],"type":"Point"}
}