{
  "type": "Feature",
  "properties": {
    "iso:country":"ES",
    "sg:address":"Calle de San Vicente, 11",
    "sg:city":"Campillos",
    "sg:orig_category":"Alquiler De V\u00cddeo",
    "sg:phone":"+34 952 72 25 47",
    "sg:postcode":"29320",
    "sg:province":"M\u00e1laga",
    "wof:name":"Porras Montes Francisco",
    "wof:placetype":"venue"
},
  "geometry": {"coordinates":[-4.8654198647,37.0447349548],"type":"Point"}
}