{
  "type": "Feature",
  "properties": {
    "iso:country":"ES",
    "sg:address":"Calle de Carlos Mauricio Blandy, 37",
    "sg:city":"Palmas De Gran Canaria",
    "sg:orig_category":"Promotores Constructores",
    "sg:phone":"+34 928 28 11 27",
    "sg:postcode":"35011",
    "sg:province":"Las Palmas",
    "wof:name":"Fernandez Torres Candelaria",
    "wof:placetype":"venue"
},
  "geometry": {"coordinates":[-15.4336061478,28.1165485382],"type":"Point"}
}