{
  "type": "Feature",
  "properties": {
    "iso:country":"ES",
    "sg:address":"Carr Pau, 4",
    "sg:city":"Sencelles",
    "sg:orig_category":"Asilos De Ancianos. Centros Privados",
    "sg:phone":"+34 971 87 26 36",
    "sg:postcode":"07140",
    "sg:province":"Islas Baleares",
    "wof:name":"Fundacion Hospital Sant Francesc D'asis",
    "wof:placetype":"venue"
},
  "geometry": {"coordinates":[2.8979299068,39.6459465027],"type":"Point"}
}