{
  "type": "Feature",
  "properties": {
    "iso:country":"ES",
    "sg:address":"Plaz Cruz Verde, 2",
    "sg:city":"Valladolid",
    "sg:orig_category":"Florister\u00cdas",
    "sg:phone":"+34 983 30 56 79",
    "sg:postcode":"47002",
    "sg:province":"Valladolid",
    "wof:name":"Fadrique Y Rojo S.l.",
    "wof:placetype":"venue"
},
  "geometry": {"coordinates":[-4.7199659348,41.6482696533],"type":"Point"}
}