{
  "type": "Feature",
  "properties": {
    "addr:full":"Montoyas, S/n Aljucer Murcia 30152",
    "addr:housenumber":"/ n",
    "addr:postcode":"30152",
    "addr:street":"Montoyas S",
    "iso:country":"ES",
    "sg:address":"Montoyas, S/n",
    "sg:city":"Aljucer",
    "sg:orig_category":"Alimentaci\u00d3n General (al Por Menor)",
    "sg:phone":"+34 968 25 40 29",
    "sg:postcode":"30152",
    "sg:province":"Murcia",
    "wof:name":"Gomez Martin Ricardo",
    "wof:placetype":"venue"
},
  "geometry": {"coordinates":[-1.1475520134,37.9626274109],"type":"Point"}
}