{
  "type": "Feature",
  "properties": {
    "iso:country":"ES",
    "sg:address":"Calle de Marina Vega, 32",
    "sg:city":"Madrid",
    "sg:orig_category":"Rectificaci\u00d3n, Mecanizado, Fresado",
    "sg:phone":"+34 915 69 59 34",
    "sg:postcode":"28026",
    "sg:province":"Madrid",
    "wof:name":"Rama Ruiz Juan",
    "wof:placetype":"venue"
},
  "geometry": {"coordinates":[-3.7139689922,40.3800315857],"type":"Point"}
}