{
  "type": "Feature",
  "properties": {
    "iso:country":"ES",
    "sg:address":"Calle de Nu\u00d1ez De Balboa, 23",
    "sg:city":"Alcala",
    "sg:orig_category":"Agencias Y Agentes Comerciales, Representantes",
    "sg:phone":"+34 922 86 64 01",
    "sg:postcode":"38686",
    "sg:province":"Santa Cruz De Tenerife",
    "wof:name":"Rayco Batista Santos",
    "wof:placetype":"venue"
},
  "geometry": {"coordinates":[-16.8283786774,28.2016677856],"type":"Point"}
}