{
  "type": "Feature",
  "properties": {
    "iso:country":"ES",
    "sg:address":"Avda Santiago Madrigal, 1",
    "sg:city":"Salamanca",
    "sg:orig_category":"Agencias Y Agentes Comerciales, Representantes",
    "sg:phone":"+34 923 18 63 74",
    "sg:postcode":"37003",
    "sg:province":"Salamanca",
    "wof:name":"Sanchez Bertoli Carlos",
    "wof:placetype":"venue"
},
  "geometry": {"coordinates":[-5.6390151978,40.9708633423],"type":"Point"}
}