{
  "type": "Feature",
  "properties": {
    "iso:country":"ES",
    "sg:address":"Sbid Cemiterio Puxeiros, 11",
    "sg:city":"Fonti\u00d1as",
    "sg:orig_category":"Puertas Autom\u00c1ticas, Puertas De Garaje",
    "sg:phone":"+34 986 27 29 04",
    "sg:postcode":"36318",
    "sg:province":"Pontevedra",
    "wof:name":"Gallega De Herrajes S.l",
    "wof:placetype":"venue"
},
  "geometry": {"coordinates":[-8.6480531693,42.4336204529],"type":"Point"}
}