{
  "type": "Feature",
  "properties": {
    "addr:full":"Calle de Prensa (la), 2 San Sebastian De Los Reyes Madrid 28700",
    "addr:postcode":"28700",
    "addr:street":"Calle De Prensa La 2",
    "iso:country":"ES",
    "sg:address":"Calle de Prensa (la), 2",
    "sg:city":"San Sebastian De Los Reyes",
    "sg:classifiers":[
        {
            "category":"Autos & Motor Vehicles",
            "subcategory":"Automobile Sales",
            "type":"Retail Goods"
        }
    ],
    "sg:phone":"+34 916 52 20 27",
    "sg:postcode":"28700",
    "sg:province":"Madrid",
    "wof:name":"Autoescula Prensa Sl",
    "wof:placetype":"venue"
},
  "geometry": {"coordinates":[-3.6280379295,40.5443344116],"type":"Point"}
}