{
  "type": "Feature",
  "properties": {
    "addr:full":"Ctra Espa\u00d1a, 50 Vera Santa Cruz De Tenerife 38390",
    "addr:housenumber":"50",
    "addr:postcode":"38390",
    "addr:street":"Ctra Espan\u0303A",
    "iso:country":"ES",
    "sg:address":"Ctra Espa\u00d1a, 50",
    "sg:city":"Vera",
    "sg:orig_category":"Confecci\u00d3n (fabricaci\u00d3n, Al Por Mayor)",
    "sg:phone":"+34 922 30 24 95",
    "sg:postcode":"38390",
    "sg:province":"Santa Cruz De Tenerife",
    "wof:name":"Representaciones Acentejo S.l.",
    "wof:placetype":"venue"
},
  "geometry": {"coordinates":[-16.4917697906,28.425359726],"type":"Point"}
}