{
  "type": "Feature",
  "properties": {
    "iso:country":"ES",
    "sg:address":"Calle de Calderon De La Barca, 8",
    "sg:city":"Alacant",
    "sg:orig_category":"Sociedades Y Organismos Burs\u00c1tiles",
    "sg:phone":"+34 965 23 07 67",
    "sg:postcode":"03004",
    "sg:province":"Alicante",
    "wof:name":"Gaesco Bolsa S.a.",
    "wof:placetype":"venue"
},
  "geometry": {"coordinates":[-0.4859854877,38.3486480713],"type":"Point"}
}