{
  "type": "Feature",
  "properties": {
    "addr:full":"Calle de Zorrilla, 2 Barakaldo Vizcaya 48902",
    "addr:housenumber":"2",
    "addr:postcode":"48902",
    "addr:street":"Calle De Zorrilla",
    "iso:country":"ES",
    "sg:address":"Calle de Zorrilla, 2",
    "sg:city":"Barakaldo",
    "sg:orig_category":"Suministros Para Carrocer\u00cdas",
    "sg:phone":"+34 944 38 46 77",
    "sg:postcode":"48902",
    "sg:province":"Vizcaya",
    "wof:name":"Talleres Pedrin, S.l.",
    "wof:placetype":"venue"
},
  "geometry": {"coordinates":[-2.9929189682,43.3015899658],"type":"Point"}
}