{
  "type": "Feature",
  "properties": {
    "iso:country":"ES",
    "sg:address":"Carrer de Claret, 6",
    "sg:city":"Hospitalet Llobregat",
    "sg:orig_category":"Venta, Instalaci\u00d3n De Calefacci\u00d3n",
    "sg:phone":"+34 934 48 17 64",
    "sg:postcode":"08903",
    "sg:province":"Barcelona",
    "wof:name":"Instalaciones Y Rehabilitaciones S.l",
    "wof:placetype":"venue"
},
  "geometry": {"coordinates":[2.1214110851,41.3720970154],"type":"Point"}
}