{
  "type": "Feature",
  "properties": {
    "addr:full":"Cra. Caldes, Km. 0002,0 Cassa Selva Girona 17244",
    "addr:postcode":"17244",
    "addr:street":"Km. 0002,0 Cassa Selva Girona",
    "iso:country":"ES",
    "sg:address":"Cra. Caldes, Km. 0002,0",
    "sg:city":"Cassa Selva",
    "sg:orig_category":"Empresas De Pintura Y Revestimientos",
    "sg:phone":"+34 972 46 08 70",
    "sg:postcode":"17244",
    "sg:province":"Girona",
    "wof:name":"Pintures Fornells S.l",
    "wof:placetype":"venue"
},
  "geometry": {"coordinates":[2.8780760765,41.8896598816],"type":"Point"}
}