{
  "type": "Feature",
  "properties": {
    "addr:full":"Carr Gaspar Puig, 10 Eivissa Islas Baleares 07800",
    "addr:housenumber":"10",
    "addr:postcode":"07800",
    "addr:street":"Carr Gaspar Puig",
    "iso:country":"ES",
    "sg:address":"Carr Gaspar Puig, 10",
    "sg:city":"Eivissa",
    "sg:orig_category":"Reposter\u00cdas",
    "sg:phone":"+34 971 31 34 72",
    "sg:postcode":"07800",
    "sg:province":"Islas Baleares",
    "wof:name":"Torres Costa Antonio",
    "wof:placetype":"venue"
},
  "geometry": {"coordinates":[1.4323600531,38.9105911255],"type":"Point"}
}