{
  "type": "Feature",
  "properties": {
    "addr:full":"San Lorenzo, 33 Cea Ourense 32130",
    "addr:housenumber":"33",
    "addr:postcode":"32130",
    "addr:street":"San Lorenzo",
    "iso:country":"ES",
    "sg:address":"San Lorenzo, 33",
    "sg:city":"Cea",
    "sg:orig_category":"Alimentaci\u00d3n General (al Por Menor)",
    "sg:phone":"+34 988 28 20 50",
    "sg:postcode":"32130",
    "sg:province":"Ourense",
    "wof:name":"Vazquez Docampo Jose Vicente",
    "wof:placetype":"venue"
},
  "geometry": {"coordinates":[-7.9879989624,42.4770317078],"type":"Point"}
}