{
  "type": "Feature",
  "properties": {
    "addr:full":"Plaz Padre Vallet, S/n Pozuelo De Alarcon Madrid 28223",
    "addr:housenumber":"s / n",
    "addr:postcode":"28223",
    "addr:street":"Vallet",
    "iso:country":"ES",
    "sg:address":"Plaz Padre Vallet, S/n",
    "sg:city":"Pozuelo De Alarcon",
    "sg:orig_category":"Librer\u00cdas",
    "sg:phone":"+34 917 15 82 45",
    "sg:postcode":"28223",
    "sg:province":"Madrid",
    "wof:name":"Lopez Fradejas Jose",
    "wof:placetype":"venue"
},
  "geometry": {"coordinates":[-3.8143138885,40.4354133606],"type":"Point"}
}