{
  "type": "Feature",
  "properties": {
    "addr:full":"Calle de Reig Genoves, 13 Valencia Valencia 46019",
    "addr:housenumber":"13",
    "addr:postcode":"46019",
    "addr:street":"Calle De Reig Genoves",
    "iso:country":"ES",
    "sg:address":"Calle de Reig Genoves, 13",
    "sg:city":"Valencia",
    "sg:orig_category":"Droguer\u00cdas (al Por Menor)",
    "sg:phone":"+34 963 65 54 46",
    "sg:postcode":"46019",
    "sg:province":"Valencia",
    "wof:name":"Pamblanco Valero Ramon",
    "wof:placetype":"venue"
},
  "geometry": {"coordinates":[-0.3716169894,39.4926681519],"type":"Point"}
}