{
  "type": "Feature",
  "properties": {
    "addr:full":"Pase Mu\u00d1oz Grandes, 22 Madrid Madrid 28025",
    "addr:housenumber":"22",
    "addr:postcode":"madrid;28025",
    "iso:country":"ES",
    "sg:address":"Pase Mu\u00d1oz Grandes, 22",
    "sg:city":"Madrid",
    "sg:orig_category":"Material Y Suministros Para Imprenta E Industrias Gr\u00c1ficas",
    "sg:phone":"+34 914 65 00 05",
    "sg:postcode":"28025",
    "sg:province":"Madrid",
    "wof:name":"Graficas Garme S.l.",
    "wof:placetype":"venue"
},
  "geometry": {"coordinates":[-3.728276968,40.3764381409],"type":"Point"}
}