{
  "type": "Feature",
  "properties": {
    "iso:country":"ES",
    "sg:address":"Avda Vilagarcia, S/n",
    "sg:city":"Cabana",
    "sg:orig_category":"Agentes, Concesionarios Y Sucursales De Veh\u00cdculos",
    "sg:phone":"+34 986 54 20 00",
    "sg:postcode":"36634",
    "sg:province":"Pontevedra",
    "wof:name":"Automocion Cangas S.l.",
    "wof:placetype":"venue"
},
  "geometry": {"coordinates":[-8.6480531693,42.4336204529],"type":"Point"}
}