{
  "type": "Feature",
  "properties": {
    "iso:country":"ES",
    "sg:address":"C/ Santa Rosa, 32",
    "sg:city":"Alcoi",
    "sg:orig_category":"Telefon\u00cda: Instaladores Varios",
    "sg:phone":"+34 966 52 32 62",
    "sg:postcode":"03802",
    "sg:province":"Alicante",
    "sg:website":"www.alfayomegaonline.com",
    "wof:name":"Alcalay  Henrique Asher",
    "wof:placetype":"venue"
},
  "geometry": {"coordinates":[-0.4845368862,38.6954040527],"type":"Point"}
}