{
  "type": "Feature",
  "properties": {
    "addr:full":"Rua Luis Taboada, 28 Vigo Pontevedra 36201",
    "addr:housenumber":"28",
    "addr:postcode":"36201",
    "addr:street":"Rua Luis Taboada",
    "iso:country":"ES",
    "sg:address":"Rua Luis Taboada, 28",
    "sg:city":"Vigo",
    "sg:orig_category":"Restaurantes",
    "sg:phone":"+34 986 22 86 15",
    "sg:postcode":"36201",
    "sg:province":"Pontevedra",
    "wof:name":"Araujo Viso Leonardo",
    "wof:placetype":"venue"
},
  "geometry": {"coordinates":[-8.7224969864,42.240032196],"type":"Point"}
}