{
  "type": "Feature",
  "properties": {
    "addr:full":"Calle de Doctor Don Luis Bilbao Libano, 58 Elexalde Vizcaya 48940",
    "addr:housenumber":"58",
    "addr:postcode":"48940",
    "addr:street":"Calle De Doctor Don;Libano",
    "iso:country":"ES",
    "sg:address":"Calle de Doctor Don Luis Bilbao Libano, 58",
    "sg:city":"Elexalde",
    "sg:orig_category":"Ense\u00d1anza: Idiomas",
    "sg:phone":"+34 944 64 60 63",
    "sg:postcode":"48940",
    "sg:province":"Vizcaya",
    "wof:name":"Euskaraz Koop. E.",
    "wof:placetype":"venue"
},
  "geometry": {"coordinates":[-2.8873260021,43.2208213806],"type":"Point"}
}