{
  "type": "Feature",
  "properties": {
    "addr:full":"Av Castelldefels, Km. 0016,4 Castelldefels Barcelona 08860",
    "addr:postcode":"08860",
    "addr:street":"Av Castelldefels Km. 0016,4",
    "iso:country":"ES",
    "sg:address":"Av Castelldefels, Km. 0016,4",
    "sg:city":"Castelldefels",
    "sg:orig_category":"M\u00c9dicos: Nefrolog\u00cda",
    "sg:phone":"+34 936 33 07 36",
    "sg:postcode":"08860",
    "sg:province":"Barcelona",
    "wof:name":"Lopez Pedret Jose",
    "wof:placetype":"venue"
},
  "geometry": {"coordinates":[1.9896689653,41.269821167],"type":"Point"}
}