{
  "type": "Feature",
  "properties": {
    "addr:full":"Pg Pare Manyanet, 26 Tremp Lleida 25620",
    "addr:housenumber":"26",
    "addr:postcode":"25620",
    "addr:street":"Pg Pare Manyanet",
    "iso:country":"ES",
    "sg:address":"Pg Pare Manyanet, 26",
    "sg:city":"Tremp",
    "sg:orig_category":"Confecci\u00d3n (fabricaci\u00d3n, Al Por Mayor)",
    "sg:phone":"+34 973 65 01 28",
    "sg:postcode":"25620",
    "sg:province":"Lleida",
    "wof:name":"Dominguez Goye Teresa",
    "wof:placetype":"venue"
},
  "geometry": {"coordinates":[0.8940600157,42.1672172546],"type":"Point"}
}