{
  "type": "Feature",
  "properties": {
    "iso:country":"ES",
    "sg:address":"Calle de San Ignacio, 4",
    "sg:city":"Valladolid",
    "sg:orig_category":"Art\u00cdculos De Regalo (al Por Menor)",
    "sg:phone":"+34 983 37 55 77",
    "sg:postcode":"47003",
    "sg:province":"Valladolid",
    "wof:name":"Detalle De Tu Vida S.l.",
    "wof:placetype":"venue"
},
  "geometry": {"coordinates":[-4.7288122177,41.6552085876],"type":"Point"}
}