{
  "type": "Feature",
  "properties": {
    "addr:full":"Pl Sant Antoni, 6 Palma Islas Baleares 07002",
    "addr:housenumber":"6",
    "addr:postcode":"07002",
    "addr:street":"Pl Sant Antoni",
    "iso:country":"ES",
    "sg:address":"Pl Sant Antoni, 6",
    "sg:city":"Palma",
    "sg:orig_category":"Abogados",
    "sg:phone":"+34 971 72 50 75",
    "sg:postcode":"07002",
    "sg:province":"Islas Baleares",
    "wof:name":"Pujol Porcel Onofre",
    "wof:placetype":"venue"
},
  "geometry": {"coordinates":[2.6555359364,39.5716018677],"type":"Point"}
}