{
  "type": "Feature",
  "properties": {
    "iso:country":"ES",
    "sg:address":"Calle de Jose De Echegaray, 2",
    "sg:city":"Merida",
    "sg:orig_category":"Droguer\u00cdas (al Por Menor)",
    "sg:phone":"+34 924 30 35 02",
    "sg:postcode":"06800",
    "sg:province":"Badajoz",
    "wof:name":"Guisado Jimenez Elena",
    "wof:placetype":"venue"
},
  "geometry": {"coordinates":[-6.3421988487,38.913105011],"type":"Point"}
}