{
  "type": "Feature",
  "properties": {
    "addr:full":"Plaz San Antonio, 4 Santo\u00f1a Cantabria 39740",
    "addr:housenumber":"4",
    "addr:postcode":"39740",
    "addr:street":"Plaz San Antonio",
    "iso:country":"ES",
    "sg:address":"Plaz San Antonio, 4",
    "sg:city":"Santo\u00f1a",
    "sg:orig_category":"Electrodom\u00c9sticos (al Por Menor)",
    "sg:phone":"+34 942 66 09 16",
    "sg:postcode":"39740",
    "sg:province":"Cantabria",
    "wof:name":"Sainz-rozas Fernandez Luisa",
    "wof:placetype":"venue"
},
  "geometry": {"coordinates":[-3.4559640884,43.4430236816],"type":"Point"}
}