{
  "type": "Feature",
  "properties": {
    "addr:full":"Calle de Santo Tomas De Villanueva, 10 Granada Granada 18004",
    "addr:housenumber":"10",
    "addr:postcode":"18004",
    "addr:street":"Calle De Santo;Villanueva",
    "iso:country":"ES",
    "sg:address":"Calle de Santo Tomas De Villanueva, 10",
    "sg:city":"Granada",
    "sg:orig_category":"Formaci\u00d3n Continuada (variada)",
    "sg:phone":"+34 958 20 12 99",
    "sg:postcode":"18004",
    "sg:province":"Granada",
    "wof:name":"Enrique De Luna Fernandez Emilio",
    "wof:placetype":"venue"
},
  "geometry": {"coordinates":[-3.6138720512,37.1800804138],"type":"Point"}
}