{
  "type": "Feature",
  "properties": {
    "addr:full":"Plaz Aligustres (de Los), 5 Cazorla Ja\u00e9n 23470",
    "addr:postcode":"23470",
    "addr:street":"Plaz",
    "iso:country":"ES",
    "sg:address":"Plaz Aligustres (de Los), 5",
    "sg:city":"Cazorla",
    "sg:orig_category":"Limpieza Industrial",
    "sg:phone":"+34 953 71 04 50",
    "sg:postcode":"23470",
    "sg:province":"Ja\u00e9n",
    "wof:name":"Lavanderia Industrial Cazorla S.c.a.",
    "wof:placetype":"venue"
},
  "geometry": {"coordinates":[-3.0002439022,38.0034065247],"type":"Point"}
}