{
  "type": "Feature",
  "properties": {
    "addr:full":"Carrer de Salvador, 16 Barcelona Barcelona 08001",
    "addr:housenumber":"16",
    "addr:postcode":"08001",
    "addr:street":"Carrer De Salvador",
    "iso:country":"ES",
    "sg:address":"Carrer de Salvador, 16",
    "sg:city":"Barcelona",
    "sg:orig_category":"Encuadernaci\u00d3n E Impresi\u00d3n De Folletos",
    "sg:phone":"+34 934 41 47 02",
    "sg:postcode":"08001",
    "sg:province":"Barcelona",
    "sg:website":"www.muns-bcn.com",
    "wof:name":"Muns Prats Miguel",
    "wof:placetype":"venue"
},
  "geometry": {"coordinates":[2.1646609306,41.3783416748],"type":"Point"}
}