{
  "type": "Feature",
  "properties": {
    "addr:full":"Calle de Duquesa Villahermosa, 42 Zaragoza Zaragoza 50010",
    "addr:housenumber":"42",
    "addr:postcode":"50010",
    "addr:street":"Calle De Duquesa Villahermosa",
    "iso:country":"ES",
    "sg:address":"Calle de Duquesa Villahermosa, 42",
    "sg:city":"Zaragoza",
    "sg:orig_category":"Bisuter\u00cda, Joyer\u00cda, Relojer\u00cda (al Por Menor)",
    "sg:phone":"+34 976 31 41 99",
    "sg:postcode":"50010",
    "sg:province":"Zaragoza",
    "wof:name":"Marques Bazataqui Jesus",
    "wof:placetype":"venue"
},
  "geometry": {"coordinates":[-0.9035243988,41.6478538513],"type":"Point"}
}