{
  "type": "Feature",
  "properties": {
    "iso:country":"ES",
    "sg:address":"Calle de Periodista Azzati, 28",
    "sg:city":"Puerto",
    "sg:orig_category":"Chapister\u00cda",
    "sg:phone":"+34 962 67 96 50",
    "sg:postcode":"46520",
    "sg:province":"Valencia",
    "wof:name":"Autotaller Colorauto S.l.",
    "wof:placetype":"venue"
},
  "geometry": {"coordinates":[-0.2261369973,39.6657829285],"type":"Point"}
}