{
  "type": "Feature",
  "properties": {
    "iso:country":"ES",
    "sg:address":"Cmno Santovenia, S/n",
    "sg:city":"Villafafila",
    "sg:orig_category":"Lecher\u00cdas",
    "sg:phone":"+34 980 59 17 23",
    "sg:postcode":"49136",
    "sg:province":"Zamora",
    "wof:name":"Sociedad Cooperativa Limitada Campo De Las Abutardas",
    "wof:placetype":"venue"
},
  "geometry": {"coordinates":[-5.6153688431,41.8469963074],"type":"Point"}
}