{
  "type": "Feature",
  "properties": {
    "addr:full":"Calle de Andre Gide, 37 Malaga M\u00e1laga 29004",
    "addr:housenumber":"37",
    "addr:postcode":"29004",
    "addr:street":"Calle De Andre Gide;Ma\u0301Laga",
    "iso:country":"ES",
    "sg:address":"Calle de Andre Gide, 37",
    "sg:city":"Malaga",
    "sg:orig_category":"Importaci\u00d3n",
    "sg:phone":"+34 952 23 52 60",
    "sg:postcode":"29004",
    "sg:province":"M\u00e1laga",
    "wof:name":"Weng  Rong Rong",
    "wof:placetype":"venue"
},
  "geometry": {"coordinates":[-4.4750022888,36.6909141541],"type":"Point"}
}