{
  "type": "Feature",
  "properties": {
    "addr:full":"Plaz Valentin Ortigosa, 1 Malaga M\u00e1laga 29004",
    "addr:housenumber":"1",
    "addr:postcode":"29004",
    "addr:street":"Ortigosa;Ma\u0301Laga",
    "iso:country":"ES",
    "sg:address":"Plaz Valentin Ortigosa, 1",
    "sg:city":"Malaga",
    "sg:orig_category":"Bibliotecas, Mediatecas",
    "sg:phone":"+34 952 17 60 05",
    "sg:postcode":"29004",
    "sg:province":"M\u00e1laga",
    "wof:name":"Ayuntamiento De Malaga",
    "wof:placetype":"venue"
},
  "geometry": {"coordinates":[-4.4452571869,36.6906890869],"type":"Point"}
}