{
  "type": "Feature",
  "properties": {
    "iso:country":"ES",
    "sg:address":"Av Africa, 89",
    "sg:city":"Terrassa",
    "sg:orig_category":"Promotores Constructores",
    "sg:phone":"+34 937 85 13 17",
    "sg:postcode":"08228",
    "sg:province":"Barcelona",
    "wof:name":"Almodovar Sanchez Domingo",
    "wof:placetype":"venue"
},
  "geometry": {"coordinates":[2.0484101772,41.5330314636],"type":"Point"}
}