{
  "type": "Feature",
  "properties": {
    "iso:country":"ES",
    "sg:address":"Calle de Arriaza, 4",
    "sg:city":"Madrid",
    "sg:orig_category":"Centros De Adelgazamiento Y De Est\u00c9tica",
    "sg:phone":"+34 915 48 47 06",
    "sg:postcode":"28008",
    "sg:province":"Madrid",
    "wof:name":"Ruiz Prieto Julian",
    "wof:placetype":"venue"
},
  "geometry": {"coordinates":[-3.7157170773,40.4206848145],"type":"Point"}
}