{
  "type": "Feature",
  "properties": {
    "iso:country":"ES",
    "sg:address":"Av Meridiana, 498",
    "sg:city":"Barcelona",
    "sg:orig_category":"Trabajos De Aislamiento T\u00c9rmico Y Ac\u00dastico",
    "sg:phone":"+34 933 11 89 18",
    "sg:postcode":"08030",
    "sg:province":"Barcelona",
    "wof:name":"Insonorizaciones Catalanas S.l.",
    "wof:placetype":"venue"
},
  "geometry": {"coordinates":[2.1849749088,41.4369812012],"type":"Point"}
}