{
  "type": "Feature",
  "properties": {
    "addr:full":"Ctra Mar\u00c7a, S/n Falset Tarragona 43730",
    "addr:housenumber":"s / n",
    "addr:postcode":"43730",
    "addr:street":"Ctra Marc\u0327A",
    "iso:country":"ES",
    "sg:address":"Ctra Mar\u00c7a, S/n",
    "sg:city":"Falset",
    "sg:orig_category":"Inmobiliaria (agencias)",
    "sg:phone":"+34 977 83 09 93",
    "sg:postcode":"43730",
    "sg:province":"Tarragona",
    "wof:name":"Celler Joan Simo Scp",
    "wof:placetype":"venue"
},
  "geometry": {"coordinates":[0.8157259822,41.1412239075],"type":"Point"}
}