{
  "type": "Feature",
  "properties": {
    "addr:full":"Calle de Eugenio De Usandizaga, S/n Monzon Huesca 22400",
    "addr:housenumber":"s / n",
    "addr:postcode":"22400",
    "addr:street":"Calle De Eugenio De Usandizaga",
    "iso:country":"ES",
    "sg:address":"Calle de Eugenio De Usandizaga, S/n",
    "sg:city":"Monzon",
    "sg:orig_category":"Aeropuertos Y Servicios Aeroportuarios",
    "sg:phone":"+34 974 40 44 80",
    "sg:postcode":"22400",
    "sg:province":"Huesca",
    "wof:name":"Aireuropa Lineas Aereas S.a.",
    "wof:placetype":"venue"
},
  "geometry": {"coordinates":[0.1682271063,41.8996734619],"type":"Point"}
}