{
  "type": "Feature",
  "properties": {
    "addr:full":"Calle de Simon Del Mazo, S/n Calvario Pontevedra 36770",
    "addr:housenumber":"s / n",
    "addr:postcode":"36770",
    "addr:street":"Calle De Simon Del Mazo",
    "iso:country":"ES",
    "sg:address":"Calle de Simon Del Mazo, S/n",
    "sg:city":"Calvario",
    "sg:orig_category":"Clases De M\u00dasica Y Canto",
    "sg:phone":"+34 986 62 63 11",
    "sg:postcode":"36770",
    "sg:province":"Pontevedra",
    "wof:name":"Agrupacion Musical O Rosal",
    "wof:placetype":"venue"
},
  "geometry": {"coordinates":[-8.8371391296,41.9378623962],"type":"Point"}
}