{
  "type": "Feature",
  "properties": {
    "iso:country":"ES",
    "sg:address":"C/ Tia De Sa Real, 21",
    "sg:city":"Manacor",
    "sg:orig_category":"Promotores Constructores",
    "sg:phone":"+34 971 84 64 73",
    "sg:postcode":"07500",
    "sg:province":"Islas Baleares",
    "wof:name":"Industrial Voltor 44 Ib S.l.",
    "wof:placetype":"venue"
},
  "geometry": {"coordinates":[3.2047450542,39.568649292],"type":"Point"}
}