{
  "type": "Feature",
  "properties": {
    "addr:full":"Plaz Santa Eulalia, 12 Santa Eulalia Murcia 30003",
    "addr:housenumber":"12",
    "addr:postcode":"30003",
    "addr:street":"Eulalia",
    "iso:country":"ES",
    "sg:address":"Plaz Santa Eulalia, 12",
    "sg:city":"Santa Eulalia",
    "sg:orig_category":"Iglesia Cat\u00d3lica",
    "sg:phone":"+34 968 21 10 99",
    "sg:postcode":"30003",
    "sg:province":"Murcia",
    "wof:name":"Obispado De Cartagena",
    "wof:placetype":"venue"
},
  "geometry": {"coordinates":[-1.1250590086,37.9850616455],"type":"Point"}
}