{
  "type": "Feature",
  "properties": {
    "addr:full":"Carrer de Pou De Neu, 1 Ibi Alicante 03440",
    "addr:housenumber":"1",
    "addr:postcode":"03440",
    "addr:street":"Carrer De Pou De Neu",
    "iso:country":"ES",
    "sg:address":"Carrer de Pou De Neu, 1",
    "sg:city":"Ibi",
    "sg:orig_category":"Molduras, Junquillos, Listones Y Molduras Perforadas",
    "sg:phone":"+34 966 55 03 41",
    "sg:postcode":"03440",
    "sg:province":"Alicante",
    "wof:name":"Rico Agullo Rocio",
    "wof:placetype":"venue"
},
  "geometry": {"coordinates":[-0.572404027,38.6254348755],"type":"Point"}
}