{
  "type": "Feature",
  "properties": {
    "iso:country":"ES",
    "sg:address":"Avda. Maritima, 39",
    "sg:city":"Las Caletillas",
    "sg:orig_category":"Frutas Y Legumbres Frescas (al Por Mayor)",
    "sg:phone":"+34 922 50 63 20",
    "sg:postcode":"38520",
    "sg:province":"Santa Cruz De Tenerife",
    "wof:name":"Frutas Champi S.l.",
    "wof:placetype":"venue"
},
  "geometry": {"coordinates":[-16.3749637604,28.3827953339],"type":"Point"}
}