{
  "type": "Feature",
  "properties": {
    "addr:full":"Calle de Manolo Caracol, 5 Jerez De La Frontera C\u00e1diz 11408",
    "addr:housenumber":"5",
    "addr:postcode":"11408",
    "addr:street":"Calle De;Caracol",
    "iso:country":"ES",
    "sg:address":"Calle de Manolo Caracol, 5",
    "sg:city":"Jerez De La Frontera",
    "sg:orig_category":"Art\u00cdculos De Madera (fabricaci\u00d3n Y Al Por Mayor)",
    "sg:phone":"+34 956 30 14 88",
    "sg:postcode":"11408",
    "sg:province":"C\u00e1diz",
    "wof:name":"Valencia Oca Diego",
    "wof:placetype":"venue"
},
  "geometry": {"coordinates":[-6.1592831612,36.6686592102],"type":"Point"}
}