{
  "type": "Feature",
  "properties": {
    "iso:country":"ES",
    "sg:address":"Calle de Cruz, 25",
    "sg:city":"Santa Pola",
    "sg:orig_category":"Molduras, Junquillos, Listones Y Molduras Perforadas",
    "sg:phone":"+34 965 41 10 46",
    "sg:postcode":"03130",
    "sg:province":"Alicante",
    "wof:name":"Eurotel Sur S.l.",
    "wof:placetype":"venue"
},
  "geometry": {"coordinates":[-0.5542246103,38.1938438416],"type":"Point"}
}