{
  "type": "Feature",
  "properties": {
    "addr:full":"Rua Concepcion Arenal, 15 Lugo Lugo 27004",
    "addr:housenumber":"15",
    "addr:postcode":"27004",
    "addr:street":"Rua Concepcion Arenal",
    "iso:country":"ES",
    "sg:address":"Rua Concepcion Arenal, 15",
    "sg:city":"Lugo",
    "sg:orig_category":"Asesor\u00cda De Formaci\u00d3n Y Gesti\u00d3n De Personal",
    "sg:phone":"+34 982 25 10 64",
    "sg:postcode":"27004",
    "sg:province":"Lugo",
    "wof:name":"Gabinete Asesor Lucense S.l.",
    "wof:placetype":"venue"
},
  "geometry": {"coordinates":[-7.5602278709,43.0152587891],"type":"Point"}
}