{
  "type": "Feature",
  "properties": {
    "addr:full":"Calle de Lardero, 18 Logro\u00f1o La Rioja 26002",
    "addr:housenumber":"18",
    "addr:postcode":"26002",
    "addr:street":"Calle De Lardero;Rioja",
    "iso:country":"ES",
    "sg:address":"Calle de Lardero, 18",
    "sg:city":"Logro\u00f1o",
    "sg:orig_category":"Ropa Para Se\u00d1oras (al Por Menor)",
    "sg:phone":"+34 941 22 25 08",
    "sg:postcode":"26002",
    "sg:province":"La Rioja",
    "wof:name":"Maria Angeles Ruete Ortega Y Uno S.cv.",
    "wof:placetype":"venue"
},
  "geometry": {"coordinates":[-2.4516088963,42.4623260498],"type":"Point"}
}