{
  "type": "Feature",
  "properties": {
    "iso:country":"ES",
    "sg:address":"Carr Ramon Argiles, 55",
    "sg:city":"Lleida",
    "sg:orig_category":"Empresas De Carpinter\u00cda Met\u00c1lica",
    "sg:phone":"+34 973 22 56 98",
    "sg:postcode":"25005",
    "sg:province":"Lleida",
    "wof:name":"Sistemes Y Proyectes Del Alumini Y Vidre S.l.",
    "wof:placetype":"venue"
},
  "geometry": {"coordinates":[0.640707016,41.6275024414],"type":"Point"}
}