{
  "type": "Feature",
  "properties": {
    "addr:full":"Avgd Alcalde Pujol, 13 Lleida Lleida 25006",
    "addr:housenumber":"13",
    "addr:postcode":"25006",
    "addr:street":"Alcalde Pujol",
    "iso:country":"ES",
    "sg:address":"Avgd Alcalde Pujol, 13",
    "sg:city":"Lleida",
    "sg:orig_category":"Peluquer\u00cdas, Peluquer\u00cda Mixta",
    "sg:phone":"+34 973 26 53 30",
    "sg:postcode":"25006",
    "sg:province":"Lleida",
    "wof:name":"Calzada Estrada Lloren\u00e7",
    "wof:placetype":"venue"
},
  "geometry": {"coordinates":[0.6114360094,41.6195831299],"type":"Point"}
}