{
  "type": "Feature",
  "properties": {
    "iso:country":"ES",
    "sg:address":"Plaz Mayor, 34",
    "sg:city":"Burgos",
    "sg:orig_category":"Panader\u00cdas, Panader\u00cdas",
    "sg:phone":"+34 947 20 10 65",
    "sg:postcode":"09003",
    "sg:province":"Burgos",
    "wof:name":"Alonso De Linaje S.l.",
    "wof:placetype":"venue"
},
  "geometry": {"coordinates":[-3.7012963295,42.341632843],"type":"Point"}
}