{
  "type": "Feature",
  "properties": {
    "addr:full":"Ctra Tacoronte Tejina, 25 Tacoronte Santa Cruz De Tenerife 38350",
    "addr:housenumber":"25",
    "addr:postcode":"38350",
    "addr:street":"Ctra Tacoronte Tejina",
    "iso:country":"ES",
    "sg:address":"Ctra Tacoronte Tejina, 25",
    "sg:city":"Tacoronte",
    "sg:orig_category":"M\u00c9dicos: An\u00c1lisis Cl\u00cdnicos",
    "sg:phone":"+34 922 56 11 52",
    "sg:postcode":"38350",
    "sg:province":"Santa Cruz De Tenerife",
    "wof:name":"Galan Gonzalez Jose Maximino",
    "wof:placetype":"venue"
},
  "geometry": {"coordinates":[-16.4124031067,28.4793319702],"type":"Point"}
}