{
  "type": "Feature",
  "properties": {
    "iso:country":"ES",
    "sg:address":"Plaz San Sebastian, 5",
    "sg:city":"Buenavista Norte",
    "sg:orig_category":"Ropa Para Ni\u00d1os (al Por Menor)",
    "sg:phone":"+34 922 12 80 66",
    "sg:postcode":"38480",
    "sg:province":"Santa Cruz De Tenerife",
    "wof:name":"Romeral Tenerife S.l.",
    "wof:placetype":"venue"
},
  "geometry": {"coordinates":[-16.8514194489,28.3723888397],"type":"Point"}
}