{
  "type": "Feature",
  "properties": {
    "addr:full":"Grup Font Dels Capellans, S/n Manresa Barcelona 08243",
    "addr:housenumber":"s / n",
    "addr:postcode":"08243",
    "iso:country":"ES",
    "sg:address":"Grup Font Dels Capellans, S/n",
    "sg:city":"Manresa",
    "sg:orig_category":"Reposter\u00cdas",
    "sg:phone":"+34 938 74 43 54",
    "sg:postcode":"08243",
    "sg:province":"Barcelona",
    "wof:name":"Forn De Cabrianes S.l.",
    "wof:placetype":"venue"
},
  "geometry": {"coordinates":[1.8407640457,41.7305107117],"type":"Point"}
}