{
  "type": "Feature",
  "properties": {
    "addr:full":"Carrer de Fulton, 8 Barcelona Barcelona 08031",
    "addr:housenumber":"8",
    "addr:postcode":"08031",
    "addr:street":"Carrer De Fulton",
    "iso:country":"ES",
    "sg:address":"Carrer de Fulton, 8",
    "sg:city":"Barcelona",
    "sg:orig_category":"Partidos Pol\u00cdticos",
    "sg:phone":"+34 933 57 61 47",
    "sg:postcode":"08031",
    "sg:province":"Barcelona",
    "wof:name":"Convergencia Democratica De Catalu\u00f1a",
    "wof:placetype":"venue"
},
  "geometry": {"coordinates":[2.1619150639,41.4299087524],"type":"Point"}
}