{
  "type": "Feature",
  "properties": {
    "iso:country":"ES",
    "sg:address":"Barro Elexalde, 24",
    "sg:city":"Leioa",
    "sg:orig_category":"Fabricaci\u00d3n, Instalaci\u00d3n De Armarios",
    "sg:phone":"+34 944 80 21 75",
    "sg:postcode":"48940",
    "sg:province":"Vizcaya",
    "wof:name":"Maria Asuncion Ramos Gonzalez",
    "wof:placetype":"venue"
},
  "geometry": {"coordinates":[-2.9860789776,43.3275489807],"type":"Point"}
}