{
  "type": "Feature",
  "properties": {
    "addr:full":"Avda Rey, 3 Martiago Salamanca 37510",
    "addr:housenumber":"3",
    "addr:postcode":"37510",
    "addr:street":"Avda Rey",
    "iso:country":"ES",
    "sg:address":"Avda Rey, 3",
    "sg:city":"Martiago",
    "sg:orig_category":"Transportes Por Carretera: Lotes Completos, Mercanc\u00cdas Diversas",
    "sg:phone":"+34 923 48 70 35",
    "sg:postcode":"37510",
    "sg:province":"Salamanca",
    "wof:name":"Saez Moneo Esther",
    "wof:placetype":"venue"
},
  "geometry": {"coordinates":[-6.4898247719,40.4558753967],"type":"Point"}
}