{
  "type": "Feature",
  "properties": {
    "addr:full":"Calle de Antonio Ruiz, 1 Alhabia Almer\u00eda 04567",
    "addr:housenumber":"1",
    "addr:postcode":"04567",
    "addr:street":"Calle De Antonio Ruiz;Almeri\u0301A",
    "iso:country":"ES",
    "sg:address":"Calle de Antonio Ruiz, 1",
    "sg:city":"Alhabia",
    "sg:orig_category":"Cajas De Ahorro",
    "sg:phone":"+34 950 64 30 91",
    "sg:postcode":"04567",
    "sg:province":"Almer\u00eda",
    "wof:name":"Unicaja",
    "wof:placetype":"venue"
},
  "geometry": {"coordinates":[-2.5868890285,36.9894638062],"type":"Point"}
}