{
  "type": "Feature",
  "properties": {
    "addr:full":"Avda Compostela, 24 Boiro La Coru\u00f1a 15930",
    "addr:housenumber":"24",
    "addr:postcode":"15930",
    "addr:street":"Avda Compostela;La Corun\u0303A",
    "iso:country":"ES",
    "sg:address":"Avda Compostela, 24",
    "sg:city":"Boiro",
    "sg:orig_category":"Producci\u00d3n, Distribuci\u00d3n De Electricidad",
    "sg:phone":"+34 981 84 26 42",
    "sg:postcode":"15930",
    "sg:province":"La Coru\u00f1a",
    "wof:name":"Lijo Instalaciones Y Servicios Del Barbanza S.l.",
    "wof:placetype":"venue"
},
  "geometry": {"coordinates":[-8.8907709122,42.6447105408],"type":"Point"}
}