{
  "type": "Feature",
  "properties": {
    "iso:country":"ES",
    "sg:address":"Calle de Maestro Miguel Chicote, 2",
    "sg:city":"Arganda",
    "sg:orig_category":"Abogados",
    "sg:phone":"+34 918 71 63 06",
    "sg:postcode":"28500",
    "sg:province":"Madrid",
    "wof:name":"Parrales Vidal Maria Jesus",
    "wof:placetype":"venue"
},
  "geometry": {"coordinates":[-3.4480400085,40.3023796082],"type":"Point"}
}