{
  "type": "Feature",
  "properties": {
    "iso:country":"ES",
    "sg:address":"Ptda Figueral, 7",
    "sg:city":"Lliber",
    "sg:orig_category":"M\u00c9dicos: Cardiolog\u00cda Y Afecciones Cardiovasculares",
    "sg:phone":"+34 965 73 11 57",
    "sg:postcode":"03729",
    "sg:province":"Alicante",
    "wof:name":"Vandentoren  Enoch Wolter",
    "wof:placetype":"venue"
},
  "geometry": {"coordinates":[0.0188100003,38.7338752747],"type":"Point"}
}