{
  "type": "Feature",
  "properties": {
    "addr:full":"Calle de Puentezuelas, 26 Granada Granada 18002",
    "addr:housenumber":"26",
    "addr:postcode":"18002",
    "addr:street":"Calle De Puentezuelas",
    "iso:country":"ES",
    "sg:address":"Calle de Puentezuelas, 26",
    "sg:city":"Granada",
    "sg:classifiers":[
        {
            "category":"Professional",
            "subcategory":"Research",
            "type":"Services"
        }
    ],
    "sg:phone":"+34 958 26 63 16",
    "sg:postcode":"18002",
    "sg:province":"Granada",
    "sg:tags":[
        "mercado",
        "de",
        "estudios"
    ],
    "sg:website":"www.grupoitems.com",
    "wof:name":"Grupo Item Investigaciones",
    "wof:placetype":"venue"
},
  "geometry": {"coordinates":[-3.6022789478,37.1742973328],"type":"Point"}
}