{
  "type": "Feature",
  "properties": {
    "addr:full":"Calle de Sagasta, 32 Palmas De Gran Canaria Las Palmas 35008",
    "addr:housenumber":"32",
    "addr:postcode":"35008",
    "addr:street":"Calle De Sagasta",
    "iso:country":"ES",
    "sg:address":"Calle de Sagasta, 32",
    "sg:city":"Palmas De Gran Canaria",
    "sg:orig_category":"Carnicer\u00cdas, Carnicer\u00cdas",
    "sg:phone":"+34 928 26 67 67",
    "sg:postcode":"35008",
    "sg:province":"Las Palmas",
    "wof:name":"Martin Burgos Maria Soledad",
    "wof:placetype":"venue"
},
  "geometry": {"coordinates":[-15.4309015274,28.1443729401],"type":"Point"}
}