{
  "type": "Feature",
  "properties": {
    "iso:country":"ES",
    "sg:address":"Av Igualada, 1",
    "sg:city":"Cervera",
    "sg:orig_category":"Suministros Para Carrocer\u00cdas",
    "sg:phone":"+34 973 53 04 60",
    "sg:postcode":"25200",
    "sg:province":"Lleida",
    "wof:name":"Carrosseries Sucarrats S.l.",
    "wof:placetype":"venue"
},
  "geometry": {"coordinates":[1.2714600563,41.6712989807],"type":"Point"}
}