{
  "type": "Feature",
  "properties": {
    "addr:full":"Calle de Maqueda, 136 Madrid Madrid 28024",
    "addr:housenumber":"136",
    "addr:postcode":"28024",
    "addr:street":"Calle De Maqueda",
    "iso:country":"ES",
    "sg:address":"Calle de Maqueda, 136",
    "sg:city":"Madrid",
    "sg:orig_category":"Filatelia",
    "sg:phone":"+34 915 09 86 59",
    "sg:postcode":"28024",
    "sg:province":"Madrid",
    "wof:name":"Europea De Filatelia 2000 S.l.",
    "wof:placetype":"venue"
},
  "geometry": {"coordinates":[-3.7621030807,40.3879241943],"type":"Point"}
}