{
  "type": "Feature",
  "properties": {
    "addr:full":"Carrer de Berenguer Iii, 18 Mollet Valles Barcelona 08100",
    "addr:housenumber":"18",
    "addr:postcode":"08100",
    "addr:street":"Carrer De Berenguer Iii",
    "iso:country":"ES",
    "sg:address":"Carrer de Berenguer Iii, 18",
    "sg:city":"Mollet Valles",
    "sg:orig_category":"Ropa Para Caballeros (al Por Menor)",
    "sg:phone":"+34 935 70 40 10",
    "sg:postcode":"08100",
    "sg:province":"Barcelona",
    "wof:name":"Distribuciones Textiles Lintejo S.l.",
    "wof:placetype":"venue"
},
  "geometry": {"coordinates":[2.2124540806,41.5378684998],"type":"Point"}
}