{
  "type": "Feature",
  "properties": {
    "iso:country":"ES",
    "sg:address":"Moli De La Sal, 23",
    "sg:city":"Canovelles",
    "sg:orig_category":"\u00d3ptica: Instrumentos (fabricaci\u00d3n)",
    "sg:phone":"+34 938 49 74 49",
    "sg:postcode":"08420",
    "sg:province":"Barcelona",
    "wof:name":"Puigvert Barnils S.c.p.centro Optometrico Barnils",
    "wof:placetype":"venue"
},
  "geometry": {"coordinates":[2.2798349857,41.615688324],"type":"Point"}
}