{
  "type": "Feature",
  "properties": {
    "addr:full":"Ctra Tarragona, 21 Lleida Lleida 25005",
    "addr:housenumber":"21",
    "addr:postcode":"25005",
    "addr:street":"Ctra Tarragona",
    "iso:country":"ES",
    "sg:address":"Ctra Tarragona, 21",
    "sg:city":"Lleida",
    "sg:orig_category":"Comercio De Piezas De Recambio Y De Accesorios De Veh\u00cdculos, Veh\u00cdculos Industriales",
    "sg:phone":"+34 973 24 51 54",
    "sg:postcode":"25005",
    "sg:province":"Lleida",
    "wof:name":"Krahmer S. L.",
    "wof:placetype":"venue"
},
  "geometry": {"coordinates":[0.6379719973,41.624004364],"type":"Point"}
}