{
  "type": "Feature",
  "properties": {
    "addr:full":"Carrer de Bigai, 11 Barcelona Barcelona 08022",
    "addr:housenumber":"11",
    "addr:postcode":"08022",
    "addr:street":"Carrer De Bigai",
    "iso:country":"ES",
    "sg:address":"Carrer de Bigai, 11",
    "sg:city":"Barcelona",
    "sg:orig_category":"Agencias De Relaciones P\u00dablicas",
    "sg:phone":"+34 934 94 84 60",
    "sg:postcode":"08022",
    "sg:province":"Barcelona",
    "sg:website":"www.gcom.com",
    "wof:name":"Gene Asociados S.l.",
    "wof:placetype":"venue"
},
  "geometry": {"coordinates":[2.1330850124,41.4055099487],"type":"Point"}
}