{
  "type": "Feature",
  "properties": {
    "iso:country":"ES",
    "sg:address":"Avda Constitucion, 3",
    "sg:city":"San Miguel",
    "sg:orig_category":"M\u00c9dicos: Cirug\u00cda Ortop\u00c9dica Y Traumatolog\u00cda",
    "sg:phone":"+34 968 24 49 56",
    "sg:postcode":"30008",
    "sg:province":"Murcia",
    "wof:name":"Martinez Herrada Jesus",
    "wof:placetype":"venue"
},
  "geometry": {"coordinates":[-1.1315530539,37.9898033142],"type":"Point"}
}