{
  "type": "Feature",
  "properties": {
    "iso:country":"ES",
    "sg:address":"Carrer de Hospital (de L'), 27",
    "sg:city":"Reus",
    "sg:orig_category":"Transportes Por Carretera: Lotes Completos, Mercanc\u00cdas Diversas",
    "sg:phone":"+34 977 34 51 06",
    "sg:postcode":"43201",
    "sg:province":"Tarragona",
    "wof:name":"Sendra Claraso Jose",
    "wof:placetype":"venue"
},
  "geometry": {"coordinates":[1.1110030413,41.1550216675],"type":"Point"}
}