{
  "type": "Feature",
  "properties": {
    "iso:country":"ES",
    "sg:address":"Azeri Kalea, 7",
    "sg:city":"Arrasate",
    "sg:orig_category":"Bebidas",
    "sg:phone":"+34 943 79 70 33",
    "sg:postcode":"20500",
    "sg:province":"Guip\u00f9zcoa",
    "wof:name":"Hernandez Nieto Jose Antonio",
    "wof:placetype":"venue"
},
  "geometry": {"coordinates":[-2.494328022,43.0583953857],"type":"Point"}
}