{
  "type": "Feature",
  "properties": {
    "iso:country":"ES",
    "sg:address":"Calle de Copenhague, 12",
    "sg:city":"Torrejon Ardoz",
    "sg:orig_category":"Herboristas (al Por Menor)",
    "sg:phone":"+34 916 76 78 19",
    "sg:postcode":"28850",
    "sg:province":"Madrid",
    "wof:name":"Herraez De La Fuente Miguel",
    "wof:placetype":"venue"
},
  "geometry": {"coordinates":[-3.4724640846,40.461353302],"type":"Point"}
}