{
  "type": "Feature",
  "properties": {
    "iso:country":"ES",
    "sg:address":"Calle de Ramon Y Cajal, 6",
    "sg:city":"Mieres",
    "sg:orig_category":"Centros De Coordinaci\u00d3n",
    "sg:phone":"+34 985 45 26 57",
    "sg:postcode":"33600",
    "sg:province":"Asturias",
    "wof:name":"Sierra Alvarez Ana Cristina",
    "wof:placetype":"venue"
},
  "geometry": {"coordinates":[-5.7731890678,43.2444152832],"type":"Point"}
}