{
  "type": "Feature",
  "properties": {
    "iso:country":"ES",
    "sg:address":"Calle de Abad Banzo, 1",
    "sg:city":"Sabi\u00f1anigo",
    "sg:orig_category":"Empresas De Pintura Y Revestimientos",
    "sg:phone":"+34 974 48 06 52",
    "sg:postcode":"22600",
    "sg:province":"Huesca",
    "wof:name":"Granada Lanaspa Jesus",
    "wof:placetype":"venue"
},
  "geometry": {"coordinates":[-0.3619607985,42.5200691223],"type":"Point"}
}