{
  "type": "Feature",
  "properties": {
    "addr:full":"Emilio Arrieta, 11 Iru\u00f1a Navarra 31002",
    "addr:housenumber":"11",
    "addr:postcode":"31002",
    "addr:street":"Emilio Arrieta",
    "iso:country":"ES",
    "sg:address":"Emilio Arrieta, 11",
    "sg:city":"Iru\u00f1a",
    "sg:classifiers":[
        {
            "category":"Professional",
            "subcategory":"Business Services",
            "type":"Services"
        }
    ],
    "sg:phone":"+34 948 20 39 60",
    "sg:postcode":"31002",
    "sg:province":"Navarra",
    "sg:tags":[
        "control",
        "asesor\u00cda",
        "organizaci\u00d3n",
        "la",
        "de",
        "gesti\u00d3n",
        "y"
    ],
    "wof:name":"Clave Mayor Sa Sgecr",
    "wof:placetype":"venue"
},
  "geometry": {"coordinates":[-1.6393450499,42.8147964478],"type":"Point"}
}