{
  "type": "Feature",
  "properties": {
    "addr:full":"Calle de Campos Crespo, 54 Valencia Valencia 46014",
    "addr:housenumber":"54",
    "addr:postcode":"46014",
    "addr:street":"Calle De Campos Crespo",
    "iso:country":"ES",
    "sg:address":"Calle de Campos Crespo, 54",
    "sg:city":"Valencia",
    "sg:orig_category":"Engranajes Y Elementos De Transmisi\u00d3n",
    "sg:phone":"+34 963 77 87 00",
    "sg:postcode":"46014",
    "sg:province":"Valencia",
    "wof:name":"Industrias Mecantex S.a.",
    "wof:placetype":"venue"
},
  "geometry": {"coordinates":[-0.3984884024,39.4544944763],"type":"Point"}
}