{
  "type": "Feature",
  "properties": {
    "addr:full":"Luga Trema\u00d1es (juveria), S/n Gijon Asturias 33211",
    "addr:housenumber":"s",
    "addr:postcode":"33211",
    "addr:street":"/ N",
    "iso:country":"ES",
    "sg:address":"Luga Trema\u00d1es (juveria), S/n",
    "sg:city":"Gijon",
    "sg:orig_category":"Comercio De Mobiliario De Oficina",
    "sg:phone":"+34 985 32 48 57",
    "sg:postcode":"33211",
    "sg:province":"Asturias",
    "wof:name":"Urmobile S.a.",
    "wof:placetype":"venue"
},
  "geometry": {"coordinates":[-5.7112731934,43.5316085815],"type":"Point"}
}