{
  "type": "Feature",
  "properties": {
    "iso:country":"ES",
    "sg:address":"Avda General Mola (del), 20",
    "sg:city":"Santa Cruz De Tenerife",
    "sg:orig_category":"Bazares, Art\u00cdculos De Limpieza Y De Cocina (al Por Menor)",
    "sg:phone":"+34 922 28 62 80",
    "sg:postcode":"38006",
    "sg:province":"Santa Cruz De Tenerife",
    "wof:name":"Encuentro 24 Horas",
    "wof:placetype":"venue"
},
  "geometry": {"coordinates":[-16.2629814148,28.4678287506],"type":"Point"}
}