{
  "type": "Feature",
  "properties": {
    "addr:full":"Carrer de Major, 57 Roquetes Tarragona 43520",
    "addr:housenumber":"57",
    "addr:postcode":"43520",
    "addr:street":"Carrer De Major",
    "iso:country":"ES",
    "sg:address":"Carrer de Major, 57",
    "sg:city":"Roquetes",
    "sg:orig_category":"Electrodom\u00c9sticos (al Por Menor)",
    "sg:phone":"+34 977 50 15 60",
    "sg:postcode":"43520",
    "sg:province":"Tarragona",
    "wof:name":"Fava Barbera Daniel",
    "wof:placetype":"venue"
},
  "geometry": {"coordinates":[0.5021899939,40.8207893372],"type":"Point"}
}