{
  "type": "Feature",
  "properties": {
    "iso:country":"ES",
    "sg:address":"Mcdo Mayoristas, 26",
    "sg:city":"Alhaurin Grande",
    "sg:orig_category":"Promotores Constructores",
    "sg:phone":"+34 952 59 70 03",
    "sg:postcode":"29120",
    "sg:province":"M\u00e1laga",
    "sg:website":"www.agesa.com",
    "wof:name":"Construcciones Agaesa S.l",
    "wof:placetype":"venue"
},
  "geometry": {"coordinates":[-4.6911292076,36.6420783997],"type":"Point"}
}