{
  "type": "Feature",
  "properties": {
    "iso:country":"ES",
    "sg:address":"Aranda(p I Sepes), 2",
    "sg:city":"Puerto Sagunto",
    "sg:orig_category":"Limpieza Industrial",
    "sg:phone":"+34 962 65 04 07",
    "sg:postcode":"46520",
    "sg:province":"Valencia",
    "wof:name":"Litramed S.l.",
    "wof:placetype":"venue"
},
  "geometry": {"coordinates":[-0.2782787979,39.6801376343],"type":"Point"}
}