{
  "type": "Feature",
  "properties": {
    "addr:full":"Ctra Palamos, 99 Celra Girona 17460",
    "addr:housenumber":"99",
    "addr:postcode":"17460",
    "addr:street":"Ctra Palamos",
    "iso:country":"ES",
    "sg:address":"Ctra Palamos, 99",
    "sg:city":"Celra",
    "sg:orig_category":"\u00c1rboles Frutales",
    "sg:phone":"+34 972 49 22 23",
    "sg:postcode":"17460",
    "sg:province":"Girona",
    "wof:name":"Vivers Planas S. L.",
    "wof:placetype":"venue"
},
  "geometry": {"coordinates":[2.8869140148,42.0308227539],"type":"Point"}
}