{
  "type": "Feature",
  "properties": {
    "addr:full":"Rua Cornubia, 15 Lugo Lugo 27002",
    "addr:housenumber":"15",
    "addr:postcode":"27002",
    "addr:street":"Rua Cornubia",
    "iso:country":"ES",
    "sg:address":"Rua Cornubia, 15",
    "sg:city":"Lugo",
    "sg:orig_category":"Empresas De Pintura Y Revestimientos",
    "sg:phone":"+34 982 24 06 78",
    "sg:postcode":"27002",
    "sg:province":"Lugo",
    "wof:name":"Estevez Rodriguez Luisa",
    "wof:placetype":"venue"
},
  "geometry": {"coordinates":[-7.551776886,43.0016479492],"type":"Point"}
}