{
  "type": "Feature",
  "properties": {
    "iso:country":"ES",
    "sg:address":"Ctra Madrid-cadiz, Km. 0567,5",
    "sg:city":"Palacios Y Villafranca",
    "sg:classifiers":[
        {
            "category":"Banks & Credit Unions",
            "subcategory":"Bureau De Change",
            "type":"Services"
        }
    ],
    "sg:phone":"+34 955 81 12 45",
    "sg:postcode":"41720",
    "sg:province":"Sevilla",
    "sg:tags":[
        "organismos",
        "control"
    ],
    "wof:name":"Centro De Investigacion De Carretera De Andalucia S.a.",
    "wof:placetype":"venue"
},
  "geometry": {"coordinates":[-5.9241790771,37.1630935669],"type":"Point"}
}