{
  "type": "Feature",
  "properties": {
    "iso:country":"ES",
    "sg:address":"Cost Can Muntaner, 6",
    "sg:city":"Palma",
    "sg:orig_category":"Abogados",
    "sg:phone":"+34 971 72 22 50",
    "sg:postcode":"07003",
    "sg:province":"Islas Baleares",
    "wof:name":"Cortes Segura Maria Elisa",
    "wof:placetype":"venue"
},
  "geometry": {"coordinates":[2.6517651081,39.5742073059],"type":"Point"}
}