{
  "type": "Feature",
  "properties": {
    "iso:country":"ES",
    "sg:address":"Ctra. Guijuelo, S/n",
    "sg:city":"Macotera",
    "sg:orig_category":"Textil",
    "sg:phone":"+34 923 55 51 52",
    "sg:postcode":"37310",
    "sg:province":"Salamanca",
    "wof:name":"Ramon Cuesta S.l.",
    "wof:placetype":"venue"
},
  "geometry": {"coordinates":[-5.2848639488,40.8340301514],"type":"Point"}
}