{
  "type": "Feature",
  "properties": {
    "addr:full":"Via Roma, 4 Salou Tarragona 43840",
    "addr:housenumber":"4",
    "addr:postcode":"43840",
    "addr:street":"Via Roma",
    "iso:country":"ES",
    "sg:address":"Via Roma, 4",
    "sg:city":"Salou",
    "sg:orig_category":"Bazares, Art\u00cdculos De Limpieza Y De Cocina (al Por Menor)",
    "sg:phone":"+34 977 35 00 96",
    "sg:postcode":"43840",
    "sg:province":"Tarragona",
    "wof:name":"Diop  Thierno",
    "wof:placetype":"venue"
},
  "geometry": {"coordinates":[1.1306660175,41.0786857605],"type":"Point"}
}