{
  "type": "Feature",
  "properties": {
    "addr:full":"Carr Magdalena, 3 Lleida Lleida 25007",
    "addr:housenumber":"3",
    "addr:postcode":"25007",
    "addr:street":"Carr Magdalena",
    "iso:country":"ES",
    "sg:address":"Carr Magdalena, 3",
    "sg:city":"Lleida",
    "sg:orig_category":"Ropa Para Se\u00d1oras (al Por Menor)",
    "sg:phone":"+34 973 22 18 66",
    "sg:postcode":"25007",
    "sg:province":"Lleida",
    "wof:name":"Maria Pilar I Maria Elena Felip Abascal C.b.",
    "wof:placetype":"venue"
},
  "geometry": {"coordinates":[0.6290770173,41.6181106567],"type":"Point"}
}