{
  "type": "Feature",
  "properties": {
    "iso:country":"ES",
    "sg:address":"Calle de Bernardo De La Torre, 74",
    "sg:city":"Palmas De Gran Canaria",
    "sg:orig_category":"Agencias De Viajes",
    "sg:phone":"+34 928 47 23 70",
    "sg:postcode":"35007",
    "sg:province":"Las Palmas",
    "wof:name":"Alda Saya S.c.p.",
    "wof:placetype":"venue"
},
  "geometry": {"coordinates":[-15.4345712662,28.1392269135],"type":"Point"}
}