{
  "type": "Feature",
  "properties": {
    "iso:country":"ES",
    "sg:address":"Carrer de Sant Quirze, 15",
    "sg:city":"Sabadell",
    "sg:orig_category":"Inmobiliaria (agencias)",
    "sg:phone":"+34 937 26 00 35",
    "sg:postcode":"08201",
    "sg:province":"Barcelona",
    "wof:name":"Finsa Punt Immobiliari De Sabadell S.l.",
    "wof:placetype":"venue"
},
  "geometry": {"coordinates":[2.1073520184,41.5465164185],"type":"Point"}
}