{
  "type": "Feature",
  "properties": {
    "iso:country":"ES",
    "sg:address":"Carrer de Gran De Gracia, 236",
    "sg:city":"Barcelona",
    "sg:orig_category":"Internados & Ense\u00d1anza Privada",
    "sg:phone":"+34 932 18 82 69",
    "sg:postcode":"08012",
    "sg:province":"Barcelona",
    "wof:name":"Congregacion De Hermanas Carmelitas De La Caridad",
    "wof:placetype":"venue"
},
  "geometry": {"coordinates":[2.1514079571,41.4048461914],"type":"Point"}
}