{
  "type": "Feature",
  "properties": {
    "addr:full":"Calle de Miguel Hernandez Febles, 49 Palmas De Gran Canaria Las Palmas 35009",
    "addr:housenumber":"49",
    "addr:postcode":"35009",
    "addr:street":"Calle De Miguel Hernandez Febles",
    "iso:country":"ES",
    "sg:address":"Calle de Miguel Hernandez Febles, 49",
    "sg:city":"Palmas De Gran Canaria",
    "sg:orig_category":"Lencer\u00cda Femenina, Corseter\u00cda, Trajes De Ba\u00d1o (al Por Menor)",
    "sg:phone":"+34 928 46 69 46",
    "sg:postcode":"35009",
    "sg:province":"Las Palmas",
    "wof:name":"Abou-medlej Padron Carmelo",
    "wof:placetype":"venue"
},
  "geometry": {"coordinates":[-15.433453,28.166534],"type":"Point"}
}