{
  "type": "Feature",
  "properties": {
    "iso:country":"ES",
    "sg:address":"Avda Gijon, 24",
    "sg:city":"Lugones",
    "sg:orig_category":"Transporte En General",
    "sg:phone":"+34 985 26 55 96",
    "sg:postcode":"33420",
    "sg:province":"Asturias",
    "wof:name":"Dislonor S.l.",
    "wof:placetype":"venue"
},
  "geometry": {"coordinates":[-5.8073620796,43.4049911499],"type":"Point"}
}