{
  "type": "Feature",
  "properties": {
    "iso:country":"ES",
    "sg:address":"Carrer de Schumann, S/n",
    "sg:city":"Rubi",
    "sg:orig_category":"Escotaduras, Torneados",
    "sg:phone":"+34 936 99 54 64",
    "sg:postcode":"08191",
    "sg:province":"Barcelona",
    "wof:name":"Decolletage Llobregat S.a.",
    "wof:placetype":"venue"
},
  "geometry": {"coordinates":[2.0183899403,41.4720802307],"type":"Point"}
}