{
  "type": "Feature",
  "properties": {
    "iso:country":"ES",
    "sg:address":"Avda Calvo Sotelo, S/n",
    "sg:city":"Solares",
    "sg:orig_category":"Relojer\u00cda (al Por Menor, Reparaci\u00d3n)",
    "sg:phone":"+34 942 52 07 50",
    "sg:postcode":"39710",
    "sg:province":"Cantabria",
    "wof:name":"Palacio Cuesta Jesus",
    "wof:placetype":"venue"
},
  "geometry": {"coordinates":[-3.7327589989,43.3855285645],"type":"Point"}
}