{
  "type": "Feature",
  "properties": {
    "addr:full":"Carr Barca, De La, 41 Casco Urbano Valencia 46760",
    "addr:housenumber":"41",
    "addr:postcode":"46760",
    "addr:street":"Carr Barca De La",
    "iso:country":"ES",
    "sg:address":"Carr Barca, De La, 41",
    "sg:city":"Casco Urbano",
    "sg:orig_category":"Abogados",
    "sg:phone":"+34 962 82 20 10",
    "sg:postcode":"46760",
    "sg:province":"Valencia",
    "wof:name":"Ayuntamiento De Tavernes De La Valldigna",
    "wof:placetype":"venue"
},
  "geometry": {"coordinates":[-0.3768048882,39.4702377319],"type":"Point"}
}