{
  "type": "Feature",
  "properties": {
    "iso:country":"ES",
    "sg:address":"Carr Republica Del Paraguai, 29",
    "sg:city":"Lleida",
    "sg:orig_category":"Ense\u00d1anza: Comercio, Gesti\u00d3n, Inform\u00c1tica",
    "sg:phone":"+34 973 28 28 22",
    "sg:postcode":"25002",
    "sg:province":"Lleida",
    "sg:website":"www.noumon.com",
    "wof:name":"Noumon Informatica S.l.",
    "wof:placetype":"venue"
},
  "geometry": {"coordinates":[0.6181139946,41.6106681824],"type":"Point"}
}