{
  "type": "Feature",
  "properties": {
    "addr:full":"Crta. Madrid-cadiz (p I Coto La Isleta), S/n Pto Sta Maria C\u00e1diz 11500",
    "addr:housenumber":"s / n",
    "addr:postcode":"11500",
    "addr:street":"Crta. Madrid-Cadiz P;Isleta;Pto Sta;Ca\u0301Diz",
    "iso:country":"ES",
    "sg:address":"Crta. Madrid-cadiz (p I Coto La Isleta), S/n",
    "sg:city":"Pto Sta Maria",
    "sg:orig_category":"Alimentaci\u00d3n General (al Por Mayor)",
    "sg:phone":"+34 956 56 20 48",
    "sg:postcode":"11500",
    "sg:province":"C\u00e1diz",
    "sg:website":"www.makro.es",
    "wof:name":"Makro Autoservicio Mayorista S.a.",
    "wof:placetype":"venue"
},
  "geometry": {"coordinates":[-6.29240942,36.5299415588],"type":"Point"}
}