{
  "type": "Feature",
  "properties": {
    "iso:country":"ES",
    "sg:address":"Calle de Miguel De Cervantes Saavedra, 2",
    "sg:city":"Jerez De Los Caballeros",
    "sg:orig_category":"Tintes (fabricaci\u00d3n, Al Por Mayor)",
    "sg:phone":"+34 924 73 16 22",
    "sg:postcode":"06380",
    "sg:province":"Badajoz",
    "wof:name":"Salgado Campos Margarita",
    "wof:placetype":"venue"
},
  "geometry": {"coordinates":[-6.7721290588,38.3237304688],"type":"Point"}
}