{
  "type": "Feature",
  "properties": {
    "iso:country":"ES",
    "sg:address":"Carrer de Vall Palau, 1",
    "sg:city":"S. Andreu Barca",
    "sg:orig_category":"Alimentaci\u00d3n General (al Por Menor)",
    "sg:phone":"+34 936 82 34 07",
    "sg:postcode":"08740",
    "sg:province":"Barcelona",
    "wof:name":"Montero Espinar Mercedes",
    "wof:placetype":"venue"
},
  "geometry": {"coordinates":[1.9695199728,41.4477882385],"type":"Point"}
}