{
  "type": "Feature",
  "properties": {
    "iso:country":"ES",
    "sg:address":"Carr Llum, S/n",
    "sg:city":"Son Moro",
    "sg:orig_category":"Supermercados Y Hipermercados",
    "sg:phone":"+34 971 58 62 69",
    "sg:postcode":"07560",
    "sg:province":"Islas Baleares",
    "wof:name":"Hiper Manacor S. A.",
    "wof:placetype":"venue"
},
  "geometry": {"coordinates":[3.3764801025,39.5764541626],"type":"Point"}
}