{
  "type": "Feature",
  "properties": {
    "addr:full":"Ctra Almagro-valenzuela, Km. 0000,5 Almagro Ciudad Real 13270",
    "addr:postcode":"13270",
    "addr:street":"Ctra Almagro-Valenzuela Km. 0000,5",
    "iso:country":"ES",
    "sg:address":"Ctra Almagro-valenzuela, Km. 0000,5",
    "sg:city":"Almagro",
    "sg:orig_category":"Productores Recolectores, Venta Directa De Vinos",
    "sg:phone":"+34 926 86 03 44",
    "sg:postcode":"13270",
    "sg:province":"Ciudad Real",
    "wof:name":"Cooperativa Del Campo Nuestra Se\u00f1ora De Las Nieves",
    "wof:placetype":"venue"
},
  "geometry": {"coordinates":[-3.7093889713,38.8842353821],"type":"Point"}
}