{
  "type": "Feature",
  "properties": {
    "iso:country":"ES",
    "sg:address":"C/ Reina Victoria, 129",
    "sg:city":"Elche",
    "sg:orig_category":"M\u00c1quinas De Coser Y De Hacer Punto (al Por Mayor)",
    "sg:phone":"+34 965 46 26 63",
    "sg:postcode":"03201",
    "sg:province":"Alicante",
    "wof:name":"Kurt-kauf S. A.",
    "wof:placetype":"venue"
},
  "geometry": {"coordinates":[-0.710062027,38.265537262],"type":"Point"}
}