{
  "type": "Feature",
  "properties": {
    "addr:full":"J. M. Y Glez Hoyuel, 19 Lora Rio Sevilla 41440",
    "addr:housenumber":"19",
    "addr:postcode":"41440",
    "addr:street":"J. M. Y Glez Hoyuel;Rio Sevilla",
    "iso:country":"ES",
    "sg:address":"J. M. Y Glez Hoyuel, 19",
    "sg:city":"Lora Rio",
    "sg:orig_category":"Art\u00cdculos De Regalo (al Por Menor)",
    "sg:phone":"+34 955 80 43 12",
    "sg:postcode":"41440",
    "sg:province":"Sevilla",
    "wof:name":"Roman Gil Margarita",
    "wof:placetype":"venue"
},
  "geometry": {"coordinates":[-5.5281839371,37.659828186],"type":"Point"}
}