{
  "type": "Feature",
  "properties": {
    "iso:country":"ES",
    "sg:address":"Luga Bens, S/n",
    "sg:city":"Bens",
    "sg:orig_category":"Frutas Y Legumbres Frescas (al Por Mayor)",
    "sg:phone":"+34 981 13 12 78",
    "sg:postcode":"15010",
    "sg:province":"La Coru\u00f1a",
    "wof:name":"Frutas Prado S.l.",
    "wof:placetype":"venue"
},
  "geometry": {"coordinates":[-8.4468679428,43.3595733643],"type":"Point"}
}