{
  "type": "Feature",
  "properties": {
    "addr:full":"Pozo Blanco, 1 Iru\u00f1a Navarra 31001",
    "addr:housenumber":"1",
    "addr:postcode":"31001",
    "addr:street":"Pozo Blanco",
    "iso:country":"ES",
    "sg:address":"Pozo Blanco, 1",
    "sg:city":"Iru\u00f1a",
    "sg:orig_category":"Ropa Para Caballeros (al Por Menor)",
    "sg:phone":"+34 948 22 02 45",
    "sg:postcode":"31001",
    "sg:province":"Navarra",
    "wof:name":"Eraso Perurena Sagrario",
    "wof:placetype":"venue"
},
  "geometry": {"coordinates":[-1.6441789865,42.8173217773],"type":"Point"}
}