{
  "type": "Feature",
  "properties": {
    "iso:country":"ES",
    "sg:address":"Carregal De Arriba, S/n",
    "sg:city":"Amorin",
    "sg:orig_category":"Producci\u00d3n, Venta De Productos De Agricultura Biol\u00d3gica",
    "sg:phone":"+34 986 63 33 87",
    "sg:postcode":"36730",
    "sg:province":"Pontevedra",
    "wof:name":"Urbano Perez E Hijos S.l.",
    "wof:placetype":"venue"
},
  "geometry": {"coordinates":[-8.7277517319,41.9853744507],"type":"Point"}
}