{
  "type": "Feature",
  "properties": {
    "addr:full":"Calle de Nu\u00d1ez De Arce, 31 Valladolid Valladolid 47002",
    "addr:housenumber":"31",
    "addr:postcode":"47002",
    "addr:street":"Calle De Nun\u0303Ez De Arce",
    "iso:country":"ES",
    "sg:address":"Calle de Nu\u00d1ez De Arce, 31",
    "sg:city":"Valladolid",
    "sg:orig_category":"Enfermeras: Consultas, Atenci\u00d3n A Domicilio",
    "sg:phone":"+34 983 30 73 02",
    "sg:postcode":"47002",
    "sg:province":"Valladolid",
    "wof:name":"Pascual Garcia Tomas",
    "wof:placetype":"venue"
},
  "geometry": {"coordinates":[-4.7210960388,41.6510353088],"type":"Point"}
}