{
  "type": "Feature",
  "properties": {
    "addr:full":"Calle de Buenavista, 36 Adra Almer\u00eda 04770",
    "addr:housenumber":"36",
    "addr:postcode":"04770",
    "addr:street":"Calle De Buenavista;Almeri\u0301A",
    "iso:country":"ES",
    "sg:address":"Calle de Buenavista, 36",
    "sg:city":"Adra",
    "sg:orig_category":"Complementos De Vestir (al Por Menor)",
    "sg:phone":"+34 950 56 00 65",
    "sg:postcode":"04770",
    "sg:province":"Almer\u00eda",
    "wof:name":"Martin Valls Antonio",
    "wof:placetype":"venue"
},
  "geometry": {"coordinates":[-3.0175509453,36.7489128113],"type":"Point"}
}