{
  "type": "Feature",
  "properties": {
    "iso:country":"ES",
    "sg:address":"Poligono Industrial, 3",
    "sg:city":"Pola Gordon",
    "sg:orig_category":"Mec\u00c1nico Del Autom\u00d3vil",
    "sg:phone":"+34 987 58 81 44",
    "sg:postcode":"24600",
    "sg:province":"Le\u00f3n",
    "wof:name":"Leon Martin Margarita",
    "wof:placetype":"venue"
},
  "geometry": {"coordinates":[-5.6757760048,42.8608665466],"type":"Point"}
}