{
  "type": "Feature",
  "properties": {
    "iso:country":"ES",
    "sg:address":"Carrer de Consell De Cent, 173",
    "sg:city":"Barcelona",
    "sg:orig_category":"Cl\u00cdnicas Dentales",
    "sg:phone":"+34 934 53 63 42",
    "sg:postcode":"08015",
    "sg:province":"Barcelona",
    "sg:website":"www.vitaldent.com",
    "wof:name":"Somife Dental S.l.",
    "wof:placetype":"venue"
},
  "geometry": {"coordinates":[2.1551818848,41.3833732605],"type":"Point"}
}