{
  "type": "Feature",
  "properties": {
    "iso:country":"ES",
    "sg:address":"F. Padua Rissech Samada, 2",
    "sg:city":"Tossa Mar",
    "sg:orig_category":"Inmobiliaria (agencias)",
    "sg:phone":"+34 972 34 18 65",
    "sg:postcode":"17320",
    "sg:province":"Girona",
    "wof:name":"Inmobiliaria Soms S.l.",
    "wof:placetype":"venue"
},
  "geometry": {"coordinates":[2.9298949242,41.7226753235],"type":"Point"}
}