{
  "type": "Feature",
  "properties": {
    "addr:full":"Calle de Capitan Cortes, 31 Talavera Reina Toledo 45600",
    "addr:housenumber":"31",
    "addr:postcode":"45600",
    "addr:street":"Calle De Capitan Cortes",
    "iso:country":"ES",
    "sg:address":"Calle de Capitan Cortes, 31",
    "sg:city":"Talavera Reina",
    "sg:orig_category":"Supermercados Y Hipermercados",
    "sg:phone":"+34 925 81 66 01",
    "sg:postcode":"45600",
    "sg:province":"Toledo",
    "wof:name":"Promociones De Talavera Proyecto 2000",
    "wof:placetype":"venue"
},
  "geometry": {"coordinates":[-4.823662281,39.9655418396],"type":"Point"}
}