{
  "type": "Feature",
  "properties": {
    "addr:full":"Calle de Valle Plan, 36 Monzon Huesca 22400",
    "addr:housenumber":"36",
    "addr:postcode":"22400",
    "addr:street":"Calle De Valle Plan",
    "iso:country":"ES",
    "sg:address":"Calle de Valle Plan, 36",
    "sg:city":"Monzon",
    "sg:orig_category":"M\u00c1rmoles, Granitos Y Piedras Naturales",
    "sg:phone":"+34 974 40 18 07",
    "sg:postcode":"22400",
    "sg:province":"Huesca",
    "wof:name":"Marmoles Barranco S.l.",
    "wof:placetype":"venue"
},
  "geometry": {"coordinates":[0.1915819943,41.9130134583],"type":"Point"}
}