{
  "type": "Feature",
  "properties": {
    "iso:country":"ES",
    "sg:address":"Carrer de Carrasco I Formiguera, 25",
    "sg:city":"Barcelona",
    "sg:orig_category":"Restaurantes",
    "sg:phone":"+34 932 03 15 88",
    "sg:postcode":"08017",
    "sg:province":"Barcelona",
    "wof:name":"La Torre De Sarria S.l.",
    "wof:placetype":"venue"
},
  "geometry": {"coordinates":[2.1218409538,41.4024505615],"type":"Point"}
}