{
  "type": "Feature",
  "properties": {
    "iso:country":"ES",
    "sg:address":"Avda Oviedo, 17",
    "sg:city":"Posada",
    "sg:orig_category":"Mec\u00c1nica Y Herramientas De Precisi\u00d3n",
    "sg:phone":"+34 985 77 20 54",
    "sg:postcode":"33424",
    "sg:province":"Asturias",
    "wof:name":"Industrial Termometrica Sociedad De Asturias S.l.",
    "wof:placetype":"venue"
},
  "geometry": {"coordinates":[-5.8474154472,43.4366569519],"type":"Point"}
}