{
  "type": "Feature",
  "properties": {
    "addr:full":"Plaz Madrid, 3 Valladolid Valladolid 47001",
    "addr:housenumber":"3",
    "addr:postcode":"47001",
    "addr:street":"Madrid",
    "iso:country":"ES",
    "sg:address":"Plaz Madrid, 3",
    "sg:city":"Valladolid",
    "sg:orig_category":"Psic\u00d3logos",
    "sg:phone":"+34 983 29 01 54",
    "sg:postcode":"47001",
    "sg:province":"Valladolid",
    "wof:name":"Blanco Ja\u00f1ez Maria Del Mar",
    "wof:placetype":"venue"
},
  "geometry": {"coordinates":[-4.725317955,41.6482009888],"type":"Point"}
}