{
  "type": "Feature",
  "properties": {
    "iso:country":"ES",
    "sg:address":"Calle de Gregorio Mara\u00d1on, 12",
    "sg:city":"Leganes",
    "sg:orig_category":"Materias Pl\u00c1sticas: Productos De Consumo Masivo (fabricaci\u00d3n, Al Por Mayor)",
    "sg:phone":"+34 916 88 10 10",
    "sg:postcode":"28914",
    "sg:province":"Madrid",
    "wof:name":"Silcotech S.l.",
    "wof:placetype":"venue"
},
  "geometry": {"coordinates":[-3.7504210472,40.3231391907],"type":"Point"}
}