{
  "type": "Feature",
  "properties": {
    "iso:country":"ES",
    "sg:address":"Calle de Merineros (los), 20",
    "sg:city":"Soria",
    "sg:orig_category":"Peluquer\u00cdas, Peluquer\u00cda Mixta",
    "sg:phone":"+34 975 23 03 95",
    "sg:postcode":"42001",
    "sg:province":"Soria",
    "wof:name":"Martinez Martin Pilar",
    "wof:placetype":"venue"
},
  "geometry": {"coordinates":[-2.4745090008,41.7670402527],"type":"Point"}
}