{
  "type": "Feature",
  "properties": {
    "addr:full":"Carrer de Bonestar, 24 Cornella Llobregat Barcelona 08940",
    "addr:housenumber":"24",
    "addr:postcode":"08940",
    "addr:street":"Carrer De Bonestar",
    "iso:country":"ES",
    "sg:address":"Carrer de Bonestar, 24",
    "sg:city":"Cornella Llobregat",
    "sg:orig_category":"Transportes Por Carretera: Lotes Completos, Mercanc\u00cdas Diversas",
    "sg:phone":"+34 933 75 71 55",
    "sg:postcode":"08940",
    "sg:province":"Barcelona",
    "wof:name":"Comercial Alimentaria Artesana S.a.",
    "wof:placetype":"venue"
},
  "geometry": {"coordinates":[2.0766088963,41.3582267761],"type":"Point"}
}