{
  "type": "Feature",
  "properties": {
    "addr:full":"Calle de Caracas, 17 Madrid Madrid 28010",
    "addr:housenumber":"17",
    "addr:postcode":"madrid;28010",
    "addr:street":"Calle De Caracas",
    "iso:country":"ES",
    "sg:address":"Calle de Caracas, 17",
    "sg:city":"Madrid",
    "sg:orig_category":"Alquiler De Casas Y Habitaciones Amuebladas",
    "sg:phone":"+34 913 10 16 00",
    "sg:postcode":"28010",
    "sg:province":"Madrid",
    "wof:name":"Residencia Del Sagrado Corazon",
    "wof:placetype":"venue"
},
  "geometry": {"coordinates":[-3.6947848797,40.4307365417],"type":"Point"}
}