{
  "type": "Feature",
  "properties": {
    "addr:full":"Ezkaba, 36 Iru\u00f1a Navarra 31015",
    "addr:housenumber":"36",
    "addr:postcode":"31015",
    "addr:street":"Ezkaba",
    "iso:country":"ES",
    "sg:address":"Ezkaba, 36",
    "sg:city":"Iru\u00f1a",
    "sg:orig_category":"Ense\u00d1anza Secundaria: Colegios Y Escuelas Privadas",
    "sg:phone":"+34 948 13 66 10",
    "sg:postcode":"31015",
    "sg:province":"Navarra",
    "wof:name":"Gobierno De Navarra",
    "wof:placetype":"venue"
},
  "geometry": {"coordinates":[-1.6263209581,42.8289413452],"type":"Point"}
}