{
  "type": "Feature",
  "properties": {
    "iso:country":"ES",
    "sg:address":"Calle de Ruzafa, 10",
    "sg:city":"Valencia",
    "sg:orig_category":"Ense\u00d1anza Variada",
    "sg:phone":"+34 963 94 28 92",
    "sg:postcode":"46004",
    "sg:province":"Valencia",
    "wof:name":"Instituto De Orientacion J.m. S.l.",
    "wof:placetype":"venue"
},
  "geometry": {"coordinates":[-0.3748289943,39.4664955139],"type":"Point"}
}