{
  "type": "Feature",
  "properties": {
    "iso:country":"ES",
    "sg:address":"Lago, 13",
    "sg:city":"Iru\u00f1a",
    "sg:orig_category":"Farmacias",
    "sg:phone":"+34 948 16 37 33",
    "sg:postcode":"31016",
    "sg:province":"Navarra",
    "wof:name":"Celdran Lazaro Carmen",
    "wof:placetype":"venue"
},
  "geometry": {"coordinates":[-1.6157410145,42.8086357117],"type":"Point"}
}