{
  "type": "Feature",
  "properties": {
    "addr:full":"Calle de Alhondiga, 6 Baza Granada 18800",
    "addr:housenumber":"6",
    "addr:postcode":"18800",
    "addr:street":"Calle De Alhondiga",
    "iso:country":"ES",
    "sg:address":"Calle de Alhondiga, 6",
    "sg:city":"Baza",
    "sg:orig_category":"Heladeros",
    "sg:phone":"+34 958 70 11 47",
    "sg:postcode":"18800",
    "sg:province":"Granada",
    "wof:name":"Heladerias Reunidas S.l.",
    "wof:placetype":"venue"
},
  "geometry": {"coordinates":[-2.7745006084,37.4898681641],"type":"Point"}
}