{
  "type": "Feature",
  "properties": {
    "iso:country":"ES",
    "sg:address":"Calle de Alberto Aguilera, 12",
    "sg:city":"Madrid",
    "sg:orig_category":"Parques De Atracciones Y Centros De Esparcimiento",
    "sg:phone":"+34 914 46 45 02",
    "sg:postcode":"28015",
    "sg:province":"Madrid",
    "wof:name":"Arranz Alaez Pablo",
    "wof:placetype":"venue"
},
  "geometry": {"coordinates":[-3.7077658176,40.4298400879],"type":"Point"}
}