{
  "type": "Feature",
  "properties": {
    "addr:full":"Calle de Tamadaba, 2 Cala Moral M\u00e1laga 29720",
    "addr:housenumber":"2",
    "addr:postcode":"29720",
    "addr:street":"Calle De Tamadaba;Ma\u0301Laga",
    "iso:country":"ES",
    "sg:address":"Calle de Tamadaba, 2",
    "sg:city":"Cala Moral",
    "sg:orig_category":"Alimentaci\u00d3n General (al Por Menor)",
    "sg:phone":"+34 952 03 23 20",
    "sg:postcode":"29720",
    "sg:province":"M\u00e1laga",
    "wof:name":"Moya Medina Antonio",
    "wof:placetype":"venue"
},
  "geometry": {"coordinates":[-4.325949192,36.7128982544],"type":"Point"}
}