{
  "type": "Feature",
  "properties": {
    "addr:full":"Avda Salobrar, 2 Jaraiz Vera C\u00e1ceres 10400",
    "addr:housenumber":"2",
    "addr:postcode":"10400",
    "addr:street":"Avda Salobrar",
    "iso:country":"ES",
    "sg:address":"Avda Salobrar, 2",
    "sg:city":"Jaraiz Vera",
    "sg:orig_category":"Panader\u00cdas, Panader\u00cdas",
    "sg:phone":"+34 927 46 13 18",
    "sg:postcode":"10400",
    "sg:province":"C\u00e1ceres",
    "wof:name":"Jimenez Cruz Maria Del Pilar",
    "wof:placetype":"venue"
},
  "geometry": {"coordinates":[-5.7519369125,40.0603370667],"type":"Point"}
}