{
  "type": "Feature",
  "properties": {
    "addr:full":"Calle de Vitoria, 23 Burgos Burgos 09004",
    "addr:housenumber":"23",
    "addr:postcode":"09004",
    "addr:street":"Calle De Vitoria",
    "iso:country":"ES",
    "sg:address":"Calle de Vitoria, 23",
    "sg:city":"Burgos",
    "sg:orig_category":"Cl\u00cdnicas Dentales",
    "sg:phone":"+34 947 20 25 69",
    "sg:postcode":"09004",
    "sg:province":"Burgos",
    "wof:name":"Pallares Bartolome Carlos",
    "wof:placetype":"venue"
},
  "geometry": {"coordinates":[-3.6962850094,42.3416290283],"type":"Point"}
}