{
  "type": "Feature",
  "properties": {
    "addr:full":"Calle de Pesquera, 12 Torrejon Ardoz Madrid 28850",
    "addr:housenumber":"12",
    "addr:postcode":"28850",
    "addr:street":"Calle De Pesquera",
    "iso:country":"ES",
    "sg:address":"Calle de Pesquera, 12",
    "sg:city":"Torrejon Ardoz",
    "sg:orig_category":"Zapatos (al Por Menor)",
    "sg:phone":"+34 916 76 60 37",
    "sg:postcode":"28850",
    "sg:province":"Madrid",
    "wof:name":"Calzados Los Guerrilleros S.a.",
    "wof:placetype":"venue"
},
  "geometry": {"coordinates":[-3.4787271023,40.4573287964],"type":"Point"}
}