{
  "type": "Feature",
  "properties": {
    "addr:full":"Cmno Avellanos (somio), 677 Gijon Asturias 33203",
    "addr:housenumber":"677",
    "addr:postcode":"33203",
    "addr:street":"Cmno Avellanos Somio",
    "iso:country":"ES",
    "sg:address":"Cmno Avellanos (somio), 677",
    "sg:city":"Gijon",
    "sg:orig_category":"Prot\u00c9sicos Dentales",
    "sg:phone":"+34 985 33 01 41",
    "sg:postcode":"33203",
    "sg:province":"Asturias",
    "wof:name":"Rodriguez Montes Maria Del Pilar",
    "wof:placetype":"venue"
},
  "geometry": {"coordinates":[-5.5962839127,43.5261116028],"type":"Point"}
}