{
  "type": "Feature",
  "properties": {
    "iso:country":"ES",
    "sg:address":"Plaza Zabalgane, 6",
    "sg:city":"Galdakao",
    "sg:orig_category":"Ingeniero",
    "sg:phone":"+34 944 57 02 95",
    "sg:postcode":"48960",
    "sg:province":"Vizcaya",
    "wof:name":"Proyectos Electronicos Zabalgane, S.l.",
    "wof:placetype":"venue"
},
  "geometry": {"coordinates":[-2.8380200863,43.2308654785],"type":"Point"}
}