{
  "type": "Feature",
  "properties": {
    "iso:country":"ES",
    "sg:address":"Calle de Guenia, 5",
    "sg:city":"Arrecife",
    "sg:orig_category":"Asociaciones Y Clubs Deportivos",
    "sg:phone":"+34 928 81 53 72",
    "sg:postcode":"35500",
    "sg:province":"Las Palmas",
    "wof:name":"Club Deportivo Orientacion Maritima",
    "wof:placetype":"venue"
},
  "geometry": {"coordinates":[-13.5580320358,28.9605407715],"type":"Point"}
}