{
  "type": "Feature",
  "properties": {
    "addr:full":"Carrer de Valencia, 619 Barcelona Barcelona 08026",
    "addr:housenumber":"619",
    "addr:postcode":"08026",
    "addr:street":"Carrer De Valencia",
    "iso:country":"ES",
    "sg:address":"Carrer de Valencia, 619",
    "sg:city":"Barcelona",
    "sg:orig_category":"Estudios, Instalaci\u00d3n De Climatizaci\u00d3n",
    "sg:phone":"+34 932 46 63 70",
    "sg:postcode":"08026",
    "sg:province":"Barcelona",
    "wof:name":"Ingenieria Y Mantenimiento S.l.",
    "wof:placetype":"venue"
},
  "geometry": {"coordinates":[2.186508894,41.4102745056],"type":"Point"}
}