{
  "type": "Feature",
  "properties": {
    "addr:full":"Rua Pepe Apenela, 24 Vilalba Lugo 27800",
    "addr:housenumber":"24",
    "addr:postcode":"27800",
    "addr:street":"Pepe Apenela",
    "iso:country":"ES",
    "sg:address":"Rua Pepe Apenela, 24",
    "sg:city":"Vilalba",
    "sg:orig_category":"Mec\u00c1nico Del Autom\u00d3vil",
    "sg:phone":"+34 982 51 02 22",
    "sg:postcode":"27800",
    "sg:province":"Lugo",
    "wof:name":"Otero Hermida Jose Tomas",
    "wof:placetype":"venue"
},
  "geometry": {"coordinates":[-7.6806411743,43.3037109375],"type":"Point"}
}