{
  "type": "Feature",
  "properties": {
    "addr:full":"Ctra Murcia (de), S/n Granada Granada 18012",
    "addr:housenumber":"/ n",
    "addr:postcode":"18012",
    "addr:street":"Ctra Murcia De S",
    "iso:country":"ES",
    "sg:address":"Ctra Murcia (de), S/n",
    "sg:city":"Granada",
    "sg:orig_category":"M\u00c9dicos: Cirug\u00cda Cardiovascular Y Tor\u00c1cica",
    "sg:phone":"+34 958 29 16 08",
    "sg:postcode":"18012",
    "sg:province":"Granada",
    "wof:name":"Lara Torrano Juan",
    "wof:placetype":"venue"
},
  "geometry": {"coordinates":[-3.6001610756,37.1879768372],"type":"Point"}
}