{
  "type": "Feature",
  "properties": {
    "iso:country":"ES",
    "sg:address":"Calle de Santa Virgilia, 29",
    "sg:city":"Madrid",
    "sg:orig_category":"Suministros Y Materiales Industriales",
    "sg:phone":"+34 917 64 21 00",
    "sg:postcode":"28033",
    "sg:province":"Madrid",
    "sg:website":"www.guemisa.com",
    "wof:name":"Electronica Guerra Y Miro S. A.",
    "wof:placetype":"venue"
},
  "geometry": {"coordinates":[-3.6396009922,40.4763069153],"type":"Point"}
}