{
  "type": "Feature",
  "properties": {
    "iso:country":"ES",
    "sg:address":"Calle de Abastos (de), 98",
    "sg:city":"Aranjuez",
    "sg:orig_category":"Ropa Para Ni\u00d1os (al Por Menor)",
    "sg:phone":"+34 918 92 20 15",
    "sg:postcode":"28300",
    "sg:province":"Madrid",
    "wof:name":"Confecciones Le\u00f1o S.l.",
    "wof:placetype":"venue"
},
  "geometry": {"coordinates":[-3.6002306938,40.0317649841],"type":"Point"}
}