{
  "type": "Feature",
  "properties": {
    "iso:country":"ES",
    "sg:address":"Calle de Corredera (la), 13",
    "sg:city":"Villena",
    "sg:orig_category":"Electrodom\u00c9sticos (al Por Menor)",
    "sg:phone":"+34 965 80 03 94",
    "sg:postcode":"03400",
    "sg:province":"Alicante",
    "wof:name":"Riesma S. A.",
    "wof:placetype":"venue"
},
  "geometry": {"coordinates":[-0.8639224768,38.6304206848],"type":"Point"}
}