{
  "type": "Feature",
  "properties": {
    "addr:full":"Avda Virgen De La Monta\u00d1a, 8 Caceres C\u00e1ceres 10004",
    "addr:housenumber":"8",
    "addr:postcode":"10004",
    "addr:street":"Avda Virgen De La Montan\u0303A;Ca\u0301Ceres",
    "iso:country":"ES",
    "sg:address":"Avda Virgen De La Monta\u00d1a, 8",
    "sg:city":"Caceres",
    "sg:classifiers":[
        {
            "category":"Shopping",
            "subcategory":"Clothing, Apparel, & Fashions",
            "type":"Retail Goods"
        }
    ],
    "sg:phone":"+34 927 26 00 17",
    "sg:postcode":"10004",
    "sg:province":"C\u00e1ceres",
    "sg:tags":[
        "boutique"
    ],
    "wof:name":"Bache Surf C.b",
    "wof:placetype":"venue"
},
  "geometry": {"coordinates":[-6.376390934,39.4710617065],"type":"Point"}
}