{
  "type": "Feature",
  "properties": {
    "addr:full":"Plaz Axular, 4 Pasai Antxo Guip\u00f9zcoa 20110",
    "addr:housenumber":"4",
    "addr:postcode":"20110",
    "addr:street":"Plaz Axular;Guipu\u0300Zcoa",
    "iso:country":"ES",
    "sg:address":"Plaz Axular, 4",
    "sg:city":"Pasai Antxo",
    "sg:orig_category":"Molduras, Junquillos, Listones Y Molduras Perforadas",
    "sg:phone":"+34 943 52 42 66",
    "sg:postcode":"20110",
    "sg:province":"Guip\u00f9zcoa",
    "wof:name":"Teciruna S.l.",
    "wof:placetype":"venue"
},
  "geometry": {"coordinates":[-1.9172699451,43.3158798218],"type":"Point"}
}