{
  "type": "Feature",
  "properties": {
    "addr:full":"Ctra Torrelodones (de), 52 Estacion Madrid 28250",
    "addr:housenumber":"52",
    "addr:postcode":"28250",
    "addr:street":"Ctra Torrelodones De",
    "iso:country":"ES",
    "sg:address":"Ctra Torrelodones (de), 52",
    "sg:city":"Estacion",
    "sg:orig_category":"Pescader\u00cdas (al Por Menor)",
    "sg:phone":"+34 918 59 00 81",
    "sg:postcode":"28250",
    "sg:province":"Madrid",
    "wof:name":"Garcia Lazaro Valentin",
    "wof:placetype":"venue"
},
  "geometry": {"coordinates":[-3.9539730549,40.5730285645],"type":"Point"}
}