{
  "type": "Feature",
  "properties": {
    "iso:country":"ES",
    "sg:address":"Calle de Ginzo De Limia, 52",
    "sg:city":"Madrid",
    "sg:orig_category":"Material Y Suministros Para Peluquer\u00cda",
    "sg:phone":"+34 917 30 33 31",
    "sg:postcode":"28029",
    "sg:province":"Madrid",
    "wof:name":"Martinez Ruiz Maria Rosa",
    "wof:placetype":"venue"
},
  "geometry": {"coordinates":[-3.703943491,40.4788818359],"type":"Point"}
}