{
  "type": "Feature",
  "properties": {
    "iso:country":"ES",
    "sg:address":"Calle de Avellaneda, Teniente Coronel, 10",
    "sg:city":"Melilla",
    "sg:orig_category":"Imprenta",
    "sg:phone":"+34 952 68 57 72",
    "sg:postcode":"52003",
    "sg:province":"Melilla",
    "wof:name":"Publigrafic Melilla S.l",
    "wof:placetype":"venue"
},
  "geometry": {"coordinates":[-2.9467103481,35.2929077148],"type":"Point"}
}