{
  "type": "Feature",
  "properties": {
    "iso:country":"ES",
    "sg:address":"Avda Cedros, 32",
    "sg:city":"Salamanca",
    "sg:orig_category":"Sociedades, Compa\u00d1\u00cdas Aseguradoras",
    "sg:phone":"+34 923 12 26 50",
    "sg:postcode":"37004",
    "sg:province":"Salamanca",
    "wof:name":"Valle Soria Jesus",
    "wof:placetype":"venue"
},
  "geometry": {"coordinates":[-5.6509070396,40.9753112793],"type":"Point"}
}