{
  "type": "Feature",
  "properties": {
    "addr:full":"Carrer de Banys, 7 Garriga Barcelona 08530",
    "addr:housenumber":"7",
    "addr:postcode":"08530",
    "addr:street":"Carrer De Banys",
    "iso:country":"ES",
    "sg:address":"Carrer de Banys, 7",
    "sg:city":"Garriga",
    "sg:orig_category":"Ropa Para Se\u00d1oras (al Por Menor)",
    "sg:phone":"+34 938 71 45 80",
    "sg:postcode":"08530",
    "sg:province":"Barcelona",
    "wof:name":"Fortuny Mallol Montserrat",
    "wof:placetype":"venue"
},
  "geometry": {"coordinates":[2.2858710289,41.6841888428],"type":"Point"}
}