{
  "type": "Feature",
  "properties": {
    "addr:full":"Calle de Ibarra, 15 Gernika-lumo Vizcaya 48300",
    "addr:housenumber":"15",
    "addr:postcode":"48300",
    "addr:street":"Calle De Ibarra",
    "iso:country":"ES",
    "sg:address":"Calle de Ibarra, 15",
    "sg:city":"Gernika-lumo",
    "sg:orig_category":"Artes Gr\u00c1ficas, Artes Pl\u00c1sticas (curso)",
    "sg:phone":"+34 946 25 02 74",
    "sg:postcode":"48300",
    "sg:province":"Vizcaya",
    "wof:name":"Graficas Gaubeca S.l.",
    "wof:placetype":"venue"
},
  "geometry": {"coordinates":[-2.6755759716,43.3112182617],"type":"Point"}
}