{
  "type": "Feature",
  "properties": {
    "iso:country":"ES",
    "sg:address":"Calle de San Juan De Dios, 32",
    "sg:city":"Badajoz",
    "sg:orig_category":"Institutos De Belleza",
    "sg:phone":"+34 924 26 22 00",
    "sg:postcode":"06003",
    "sg:province":"Badajoz",
    "wof:name":"Santano Plaza Purificacion",
    "wof:placetype":"venue"
},
  "geometry": {"coordinates":[-6.968334198,38.8721656799],"type":"Point"}
}