{
  "type": "Feature",
  "properties": {
    "iso:country":"ES",
    "sg:address":"Reco Els Hospitals, 5",
    "sg:city":"Hospitalet Infant",
    "sg:orig_category":"M\u00c9dicos: Estomatolog\u00cda",
    "sg:phone":"+34 977 82 00 49",
    "sg:postcode":"43890",
    "sg:province":"Tarragona",
    "wof:name":"Gazze  Edgardo Jorge",
    "wof:placetype":"venue"
},
  "geometry": {"coordinates":[0.9221500158,40.9912948608],"type":"Point"}
}