{
  "type": "Feature",
  "properties": {
    "addr:full":"Calle de Villamanin, 14 Madrid Madrid 28011",
    "addr:housenumber":"14",
    "addr:postcode":"madrid;28011",
    "addr:street":"Calle De Villamanin",
    "iso:country":"ES",
    "sg:address":"Calle de Villamanin, 14",
    "sg:city":"Madrid",
    "sg:orig_category":"Edici\u00d3n, Venta De Partituras Musicales",
    "sg:phone":"+34 917 55 02 50",
    "sg:postcode":"28011",
    "sg:province":"Madrid",
    "wof:name":"Vazquez Sanjurjo Dolores",
    "wof:placetype":"venue"
},
  "geometry": {"coordinates":[-3.7492907047,40.4077377319],"type":"Point"}
}