{
  "type": "Feature",
  "properties": {
    "iso:country":"ES",
    "sg:address":"Carrer de Hipolito Lazaro, 4",
    "sg:city":"Sitges",
    "sg:orig_category":"Empresas De Limpieza",
    "sg:phone":"+34 938 94 61 18",
    "sg:postcode":"08870",
    "sg:province":"Barcelona",
    "sg:website":"www.hidrotec.tv",
    "wof:name":"Hidrotec Sanejament S.l.",
    "wof:placetype":"venue"
},
  "geometry": {"coordinates":[1.8080999851,41.2403526306],"type":"Point"}
}