{
  "type": "Feature",
  "properties": {
    "iso:country":"ES",
    "sg:address":"Calle de Sepulveda, 13",
    "sg:city":"Binefar",
    "sg:orig_category":"Transportes De Animales Vivos",
    "sg:phone":"+34 974 42 87 57",
    "sg:postcode":"22500",
    "sg:province":"Huesca",
    "wof:name":"Solans Gistau Juan",
    "wof:placetype":"venue"
},
  "geometry": {"coordinates":[0.2912733853,41.8533935547],"type":"Point"}
}