{
  "type": "Feature",
  "properties": {
    "iso:country":"ES",
    "sg:address":"Calle de Antequera, 61",
    "sg:city":"Herrera",
    "sg:orig_category":"Molduras, Junquillos, Listones Y Molduras Perforadas",
    "sg:phone":"+34 954 01 33 36",
    "sg:postcode":"41567",
    "sg:province":"Sevilla",
    "wof:name":"Jimenez Benjumea Manuel",
    "wof:placetype":"venue"
},
  "geometry": {"coordinates":[-4.8492488861,37.3626785278],"type":"Point"}
}