{
  "type": "Feature",
  "properties": {
    "iso:country":"ES",
    "sg:address":"Carrer de Sant Pere Martir, 20",
    "sg:city":"Olot",
    "sg:orig_category":"Inmobiliaria (agencias)",
    "sg:phone":"+34 972 26 39 66",
    "sg:postcode":"17800",
    "sg:province":"Girona",
    "wof:name":"Vector Serveis Immobiliaris S.a.",
    "wof:placetype":"venue"
},
  "geometry": {"coordinates":[2.4852890968,42.1821174622],"type":"Point"}
}