{
  "type": "Feature",
  "properties": {
    "addr:full":"Carrer de Salva, 13 Barcelona Barcelona 08004",
    "addr:housenumber":"13",
    "addr:postcode":"08004",
    "addr:street":"Carrer De Salva",
    "iso:country":"ES",
    "sg:address":"Carrer de Salva, 13",
    "sg:city":"Barcelona",
    "sg:orig_category":"Muebles",
    "sg:phone":"+34 933 29 85 39",
    "sg:postcode":"08004",
    "sg:province":"Barcelona",
    "wof:name":"Eisi Escenarios S.l.",
    "wof:placetype":"venue"
},
  "geometry": {"coordinates":[2.1665680408,41.3740921021],"type":"Point"}
}