{
  "type": "Feature",
  "properties": {
    "iso:country":"ES",
    "sg:address":"Carrer de Eduard Rifa, 73",
    "sg:city":"Manlleu",
    "sg:orig_category":"Empresas De Pintura Y Revestimientos",
    "sg:phone":"+34 938 51 21 70",
    "sg:postcode":"08560",
    "sg:province":"Barcelona",
    "wof:name":"Carrasco Gomezgodayol Francisco Javier",
    "wof:placetype":"venue"
},
  "geometry": {"coordinates":[2.294490099,42.0063858032],"type":"Point"}
}