{
  "type": "Feature",
  "properties": {
    "addr:full":"Rbla Martir Santa Eulalia, 63 Merida Badajoz 06800",
    "addr:housenumber":"63",
    "addr:postcode":"06800",
    "addr:street":"Rbla Martir Santa Eulalia",
    "iso:country":"ES",
    "sg:address":"Rbla Martir Santa Eulalia, 63",
    "sg:city":"Merida",
    "sg:orig_category":"Laboratorios Y Cl\u00cdnicas Veterinarias",
    "sg:phone":"+34 924 31 80 57",
    "sg:postcode":"06800",
    "sg:province":"Badajoz",
    "wof:name":"Mendoza Sanzano Felix",
    "wof:placetype":"venue"
},
  "geometry": {"coordinates":[-6.3417038918,38.9192848206],"type":"Point"}
}