{
  "type": "Feature",
  "properties": {
    "iso:country":"ES",
    "sg:address":"Calle de Ferraz, 18",
    "sg:city":"Madrid",
    "sg:orig_category":"Estancos",
    "sg:phone":"+34 915 41 91 94",
    "sg:postcode":"28008",
    "sg:province":"Madrid",
    "wof:name":"Guill Guillem Agustin Carlos",
    "wof:placetype":"venue"
},
  "geometry": {"coordinates":[-3.7157380581,40.424659729],"type":"Point"}
}