{
  "type": "Feature",
  "properties": {
    "addr:full":"Carrer de Pare Font, 74 Terrassa Barcelona 08223",
    "addr:housenumber":"74",
    "addr:postcode":"08223",
    "addr:street":"Carrer De Pare Font",
    "iso:country":"ES",
    "sg:address":"Carrer de Pare Font, 74",
    "sg:city":"Terrassa",
    "sg:orig_category":"Agencias Y Agentes Comerciales, Representantes",
    "sg:phone":"+34 937 84 39 50",
    "sg:postcode":"08223",
    "sg:province":"Barcelona",
    "wof:name":"Violeta Beltran Vicente",
    "wof:placetype":"venue"
},
  "geometry": {"coordinates":[2.0144789219,41.5554924011],"type":"Point"}
}