{
  "type": "Feature",
  "properties": {
    "addr:full":"Calle de Santo\u00d1a, 41 Madrid Madrid 28026",
    "addr:housenumber":"41",
    "addr:postcode":"madrid;28026",
    "addr:street":"Calle De Santon\u0303A",
    "iso:country":"ES",
    "sg:address":"Calle de Santo\u00d1a, 41",
    "sg:city":"Madrid",
    "sg:orig_category":"Herramientas Manuales (fabricaci\u00d3n, Al Por Mayor)",
    "sg:phone":"+34 914 69 73 05",
    "sg:postcode":"28026",
    "sg:province":"Madrid",
    "wof:name":"Vela Ruperez Antonio",
    "wof:placetype":"venue"
},
  "geometry": {"coordinates":[-3.7131679058,40.3819198608],"type":"Point"}
}