{
  "type": "Feature",
  "properties": {
    "addr:full":"Calle de Aguilon, 3 Madrid Madrid 28045",
    "addr:housenumber":"3",
    "addr:postcode":"28045",
    "addr:street":"Calle De Aguilon",
    "iso:country":"ES",
    "sg:address":"Calle de Aguilon, 3",
    "sg:city":"Madrid",
    "sg:orig_category":"Asesor\u00cda Sobre Comunicaci\u00d3n De Empresas",
    "sg:phone":"+34 914 74 77 99",
    "sg:postcode":"28045",
    "sg:province":"Madrid",
    "wof:name":"Gutierrez Yuste Maria Luisa",
    "wof:placetype":"venue"
},
  "geometry": {"coordinates":[-3.701649189,40.3978233337],"type":"Point"}
}