{
  "type": "Feature",
  "properties": {
    "addr:full":"Calle de Cruz Del Guanche, 52 Cruz Del Guanche Santa Cruz De Tenerife 38626",
    "addr:housenumber":"52",
    "addr:postcode":"38626",
    "addr:street":"Calle De Cruz Del Guanche;Cruz Del Guanche",
    "iso:country":"ES",
    "sg:address":"Calle de Cruz Del Guanche, 52",
    "sg:city":"Cruz Del Guanche",
    "sg:orig_category":"Maquinaria Para Industrias Diversas",
    "sg:phone":"+34 922 76 53 29",
    "sg:postcode":"38626",
    "sg:province":"Santa Cruz De Tenerife",
    "wof:name":"Alquiler Y Transportes Pedro Trujillo S.l.",
    "wof:placetype":"venue"
},
  "geometry": {"coordinates":[-16.2548561096,28.4698104858],"type":"Point"}
}