{
  "type": "Feature",
  "properties": {
    "addr:full":"Bda Overa, S/n Huercal-overa Almer\u00eda 04600",
    "addr:housenumber":"s / n",
    "addr:postcode":"04600",
    "addr:street":"Almeri\u0301A",
    "iso:country":"ES",
    "sg:address":"Bda Overa, S/n",
    "sg:city":"Huercal-overa",
    "sg:orig_category":"Arboricultura Y Producci\u00d3n De Frutas",
    "sg:phone":"+34 950 13 56 98",
    "sg:postcode":"04600",
    "sg:province":"Almer\u00eda",
    "wof:name":"S.a.t. Frutas El Botas",
    "wof:placetype":"venue"
},
  "geometry": {"coordinates":[-1.9177479744,37.4068946838],"type":"Point"}
}