{
  "type": "Feature",
  "properties": {
    "iso:country":"ES",
    "sg:address":"Calle de Trinidad, 12",
    "sg:city":"Talavera Reina",
    "sg:orig_category":"Carnicer\u00cdas, Carnicer\u00cdas",
    "sg:phone":"+34 925 80 07 75",
    "sg:postcode":"45600",
    "sg:province":"Toledo",
    "wof:name":"Mu\u00f1oz Sanchez Julian",
    "wof:placetype":"venue"
},
  "geometry": {"coordinates":[-4.8268928528,39.9633407593],"type":"Point"}
}