{
  "type": "Feature",
  "properties": {
    "iso:country":"ES",
    "sg:address":"Calle de Tahona, 4",
    "sg:city":"Pozuelo De Alarcon",
    "sg:orig_category":"Electrodom\u00c9sticos (al Por Menor)",
    "sg:phone":"+34 917 15 60 52",
    "sg:postcode":"28223",
    "sg:province":"Madrid",
    "wof:name":"Vicente Bravo Josefa",
    "wof:placetype":"venue"
},
  "geometry": {"coordinates":[-3.8161768913,40.436870575],"type":"Point"}
}