{
  "type": "Feature",
  "properties": {
    "addr:full":"Calle de Encomienda De Palacios, 124 Madrid Madrid 28030",
    "addr:housenumber":"124",
    "addr:postcode":"28030",
    "addr:street":"Calle De Encomienda De Palacios",
    "iso:country":"ES",
    "sg:address":"Calle de Encomienda De Palacios, 124",
    "sg:city":"Madrid",
    "sg:orig_category":"Arreglo, Reparaci\u00d3n, Piezas Sueltas De Televisi\u00d3n, V\u00cddeo, Hi",
    "sg:phone":"+34 917 72 78 66",
    "sg:postcode":"28030",
    "sg:province":"Madrid",
    "wof:name":"Garcia Ortega Ramon",
    "wof:placetype":"venue"
},
  "geometry": {"coordinates":[-3.6437749863,40.4005889893],"type":"Point"}
}