{
  "type": "Feature",
  "properties": {
    "addr:full":"Calle de General Manuel Saavedra Palmeiro, 12 Badajoz Badajoz 06004",
    "addr:housenumber":"12",
    "addr:postcode":"06004",
    "addr:street":"Calle De General Manuel Saavedra Palmeiro",
    "iso:country":"ES",
    "sg:address":"Calle de General Manuel Saavedra Palmeiro, 12",
    "sg:city":"Badajoz",
    "sg:orig_category":"Asesor\u00cda Fiscal Y Jur\u00cddica",
    "sg:phone":"+34 924 22 92 22",
    "sg:postcode":"06004",
    "sg:province":"Badajoz",
    "wof:name":"Duran Martinez Felipe",
    "wof:placetype":"venue"
},
  "geometry": {"coordinates":[-6.9756770134,38.8721733093],"type":"Point"}
}