{
  "type": "Feature",
  "properties": {
    "addr:full":"Avda Mateo Bosch, 30 Port D'andratx Islas Baleares 07157",
    "addr:housenumber":"30",
    "addr:postcode":"07157",
    "addr:street":"Avda Mateo Bosch",
    "iso:country":"ES",
    "sg:address":"Avda Mateo Bosch, 30",
    "sg:city":"Port D'andratx",
    "sg:orig_category":"Molduras, Junquillos, Listones Y Molduras Perforadas",
    "sg:phone":"+34 971 67 36 92",
    "sg:postcode":"07157",
    "sg:province":"Islas Baleares",
    "wof:name":"Porcel Amengual Juan",
    "wof:placetype":"venue"
},
  "geometry": {"coordinates":[2.3878479004,39.5442962646],"type":"Point"}
}