{
  "type": "Feature",
  "properties": {
    "iso:country":"ES",
    "sg:address":"Ctra Alca\u00d1iz, S/n",
    "sg:city":"Hijar",
    "sg:orig_category":"Empresas De Carpinter\u00cda Met\u00c1lica",
    "sg:phone":"+34 978 82 17 25",
    "sg:postcode":"44530",
    "sg:province":"Teruel",
    "wof:name":"Lasala Lasala Isaac",
    "wof:placetype":"venue"
},
  "geometry": {"coordinates":[-0.4462690055,41.1748580933],"type":"Point"}
}