{
  "type": "Feature",
  "properties": {
    "iso:country":"ES",
    "sg:address":"Calle de Navas (las), 14",
    "sg:city":"Elda",
    "sg:orig_category":"Grabados, Pintura Y Decoraci\u00d3n De Vidrio Y Cristal",
    "sg:phone":"+34 965 38 19 09",
    "sg:postcode":"03600",
    "sg:province":"Alicante",
    "wof:name":"Logas Cdad",
    "wof:placetype":"venue"
},
  "geometry": {"coordinates":[-0.7886689901,38.4819984436],"type":"Point"}
}