{
  "type": "Feature",
  "properties": {
    "iso:country":"ES",
    "sg:address":"Carrer de Campo Florido, 48",
    "sg:city":"Barcelona",
    "sg:orig_category":"Empresas De Carpinter\u00cda",
    "sg:phone":"+34 933 40 33 57",
    "sg:postcode":"08027",
    "sg:province":"Barcelona",
    "wof:name":"Godinez Toledo Rafael",
    "wof:placetype":"venue"
},
  "geometry": {"coordinates":[2.1812839508,41.4216842651],"type":"Point"}
}