{
  "type": "Feature",
  "properties": {
    "iso:country":"ES",
    "sg:address":"Av J Ortega Y Gasset (p I San Luis), 335",
    "sg:city":"Malaga",
    "sg:orig_category":"Promotores Constructores",
    "sg:phone":"+34 952 31 06 25",
    "sg:postcode":"29006",
    "sg:province":"M\u00e1laga",
    "wof:name":"Reconsur S.l.",
    "wof:placetype":"venue"
},
  "geometry": {"coordinates":[-4.4770750999,36.7074890137],"type":"Point"}
}