{
  "type": "Feature",
  "properties": {
    "iso:country":"ES",
    "sg:address":"Calle de Cristo De La Epidemia, 31",
    "sg:city":"Malaga",
    "sg:orig_category":"Laboratorios Y Trabajos De Fotograf\u00cda, V\u00cddeo Y Cine",
    "sg:phone":"+34 952 26 73 48",
    "sg:postcode":"29013",
    "sg:province":"M\u00e1laga",
    "wof:name":"Garcia Mi\u00f1ana Jose Carlos",
    "wof:placetype":"venue"
},
  "geometry": {"coordinates":[-4.4144001007,36.7284431458],"type":"Point"}
}