{
  "type": "Feature",
  "properties": {
    "iso:country":"ES",
    "sg:address":"Calle de Mugica Y Butron, 1 Bis",
    "sg:city":"Bilbao",
    "sg:classifiers":[
        {
            "category":"Personal",
            "subcategory":"Barber",
            "type":"Services"
        }
    ],
    "sg:phone":"+34 944 45 56 54",
    "sg:postcode":"48007",
    "sg:province":"Vizcaya",
    "sg:tags":[
        "caballeros",
        "de",
        "peluqueros"
    ],
    "wof:name":"Yolanda Sainz Gonzalez",
    "wof:placetype":"venue"
},
  "geometry": {"coordinates":[-2.9250864983,43.270450592],"type":"Point"}
}