{
  "type": "Feature",
  "properties": {
    "addr:full":"Calle de San Andres (de), 5 Fuenlabrada Madrid 28945",
    "addr:housenumber":"5",
    "addr:postcode":"28945",
    "addr:street":"Calle De San Andres De",
    "iso:country":"ES",
    "sg:address":"Calle de San Andres (de), 5",
    "sg:city":"Fuenlabrada",
    "sg:orig_category":"Molduras, Junquillos, Listones Y Molduras Perforadas",
    "sg:phone":"+34 916 15 95 72",
    "sg:postcode":"28945",
    "sg:province":"Madrid",
    "wof:name":"Duran Sanchez Francisco Javier",
    "wof:placetype":"venue"
},
  "geometry": {"coordinates":[-3.7952690125,40.2854385376],"type":"Point"}
}