{
  "type": "Feature",
  "properties": {
    "addr:full":"Calle de Maria Zambrano, 4 Zaragoza Zaragoza 50018",
    "addr:housenumber":"4",
    "addr:postcode":"50018",
    "addr:street":"Calle De Maria Zambrano",
    "iso:country":"ES",
    "sg:address":"Calle de Maria Zambrano, 4",
    "sg:city":"Zaragoza",
    "sg:orig_category":"Cajas De Ahorro",
    "sg:phone":"+34 976 52 12 26",
    "sg:postcode":"50018",
    "sg:province":"Zaragoza",
    "wof:name":"Caja De Ahorros De La Inmaculada",
    "wof:placetype":"venue"
},
  "geometry": {"coordinates":[-0.8838260174,41.6644706726],"type":"Point"}
}