{
  "type": "Feature",
  "properties": {
    "iso:country":"ES",
    "sg:address":"Carrer de Concepcion Arenal, 272",
    "sg:city":"Barcelona",
    "sg:orig_category":"Material Did\u00c1ctico",
    "sg:phone":"+34 933 46 46 29",
    "sg:postcode":"08030",
    "sg:province":"Barcelona",
    "sg:website":"www.cienciaactiva.com",
    "wof:name":"Ciencia Activa S.l.",
    "wof:placetype":"venue"
},
  "geometry": {"coordinates":[2.1843950748,41.4325294495],"type":"Point"}
}