{
  "type": "Feature",
  "properties": {
    "iso:country":"ES",
    "sg:address":"Calle de Rafael Alberti, 9",
    "sg:city":"Coru\u00d1a",
    "sg:classifiers":[
        {
            "category":"Banks & Credit Unions",
            "subcategory":"Bureau De Change",
            "type":"Services"
        }
    ],
    "sg:phone":"+34 981 28 29 28",
    "sg:postcode":"15008",
    "sg:province":"La Coru\u00f1a",
    "sg:tags":[
        "organismos",
        "control"
    ],
    "wof:name":"Lodge Service Specialist S.a.",
    "wof:placetype":"venue"
},
  "geometry": {"coordinates":[-8.4065093994,43.3491706848],"type":"Point"}
}