{
  "type": "Feature",
  "properties": {
    "addr:full":"Calle de Rincon Del Mediodia (del), 1 Rozas De Puerto Real Madrid 28649",
    "addr:housenumber":"1",
    "addr:postcode":"28649",
    "addr:street":"Calle De Rincon Del Mediodia Del;Puerto",
    "iso:country":"ES",
    "sg:address":"Calle de Rincon Del Mediodia (del), 1",
    "sg:city":"Rozas De Puerto Real",
    "sg:orig_category":"Iglesia Cat\u00d3lica",
    "sg:phone":"+34 918 64 86 49",
    "sg:postcode":"28649",
    "sg:province":"Madrid",
    "wof:name":"Parroquia De San Juan Bautista",
    "wof:placetype":"venue"
},
  "geometry": {"coordinates":[-4.4917750359,40.3102798462],"type":"Point"}
}