{
  "type": "Feature",
  "properties": {
    "iso:country":"ES",
    "sg:address":"Carrer de Manuel Sanchis I Guarner, 16",
    "sg:city":"Barcelona",
    "sg:classifiers":[
        {
            "category":"Taxi",
            "type":"Transportation"
        }
    ],
    "sg:phone":"+34 933 54 66 39",
    "sg:postcode":"08016",
    "sg:province":"Barcelona",
    "wof:name":"Martos Hidalgo Francisco",
    "wof:placetype":"venue"
},
  "geometry": {"coordinates":[2.18227911,41.4385147095],"type":"Point"}
}