{
  "type": "Feature",
  "properties": {
    "iso:country":"ES",
    "sg:address":"Calle de Francisco Garcia De Sola, 36",
    "sg:city":"Cadiz",
    "sg:orig_category":"Supermercados Y Hipermercados",
    "sg:phone":"+34 956 26 31 41",
    "sg:postcode":"11008",
    "sg:province":"C\u00e1diz",
    "wof:name":"Supermercados Cadiz S.l.",
    "wof:placetype":"venue"
},
  "geometry": {"coordinates":[-6.2796401978,36.5170173645],"type":"Point"}
}