{
  "type": "Feature",
  "properties": {
    "addr:full":"Calle de San Agustin, 16 Benabarre Huesca 22580",
    "addr:housenumber":"16",
    "addr:postcode":"22580",
    "addr:street":"Calle De San Agustin",
    "iso:country":"ES",
    "sg:address":"Calle de San Agustin, 16",
    "sg:city":"Benabarre",
    "sg:orig_category":"Producci\u00d3n, Distribuci\u00d3n De Gas Butano Y Propano",
    "sg:phone":"+34 974 54 33 23",
    "sg:postcode":"22580",
    "sg:province":"Huesca",
    "wof:name":"Sopena Y Asociados S.cv.",
    "wof:placetype":"venue"
},
  "geometry": {"coordinates":[0.4805530012,42.1083106995],"type":"Point"}
}