{
  "type": "Feature",
  "properties": {
    "iso:country":"ES",
    "sg:address":"Ctra De Malaga (zi Huerta Ardila), Km. 0440,0",
    "sg:city":"Santa Fe",
    "sg:orig_category":"Empresas De Carpinter\u00cda Met\u00c1lica",
    "sg:phone":"+34 958 44 00 90",
    "sg:postcode":"18320",
    "sg:province":"Granada",
    "wof:name":"Metal Bramon Slol",
    "wof:placetype":"venue"
},
  "geometry": {"coordinates":[-3.715419054,37.1926345825],"type":"Point"}
}