{
  "type": "Feature",
  "properties": {
    "addr:full":"Rua Cami\u00d1o Real (do), 31 Lugo Lugo 27004",
    "addr:postcode":"27004",
    "addr:street":"Rua Camin\u0303O",
    "iso:country":"ES",
    "sg:address":"Rua Cami\u00d1o Real (do), 31",
    "sg:city":"Lugo",
    "sg:orig_category":"Ropa Para Ni\u00d1os (al Por Menor)",
    "sg:phone":"+34 982 24 05 36",
    "sg:postcode":"27004",
    "sg:province":"Lugo",
    "wof:name":"Confecciones Faraldo S.l.",
    "wof:placetype":"venue"
},
  "geometry": {"coordinates":[-7.56127882,43.0153007507],"type":"Point"}
}