{
  "type": "Feature",
  "properties": {
    "iso:country":"ES",
    "sg:address":"Calle de Aluminio, 209",
    "sg:city":"Valladolid",
    "sg:orig_category":"Negocio De Madera",
    "sg:phone":"+34 983 30 46 22",
    "sg:postcode":"47012",
    "sg:province":"Valladolid",
    "sg:website":"www.marinodelafuente.net",
    "wof:name":"Marino De La Fuente S.a.",
    "wof:placetype":"venue"
},
  "geometry": {"coordinates":[-4.7075033188,41.6232261658],"type":"Point"}
}