{
  "type": "Feature",
  "properties": {
    "iso:country":"ES",
    "sg:address":"Rua Vila Real, 17",
    "sg:city":"Ourense",
    "sg:orig_category":"Buzones De Correos",
    "sg:phone":"+34 988 22 16 83",
    "sg:postcode":"32002",
    "sg:province":"Ourense",
    "wof:name":"Ucha Y Novoa S.l.",
    "wof:placetype":"venue"
},
  "geometry": {"coordinates":[-7.8717579842,42.3398323059],"type":"Point"}
}