{
  "type": "Feature",
  "properties": {
    "iso:country":"ES",
    "sg:address":"Calle de Garcia Morato, 14",
    "sg:city":"Valladolid",
    "sg:orig_category":"Material Y Suministros Para Dentistas, Cirujanos",
    "sg:phone":"+34 983 47 11 00",
    "sg:postcode":"47007",
    "sg:province":"Valladolid",
    "wof:name":"Casa Schmidt S.a.",
    "wof:placetype":"venue"
},
  "geometry": {"coordinates":[-4.7304778099,41.6424484253],"type":"Point"}
}