{
  "type": "Feature",
  "properties": {
    "addr:full":"Calle de Solana, 11 Torrejon Ardoz Madrid 28850",
    "addr:housenumber":"11",
    "addr:postcode":"28850",
    "addr:street":"Calle De Solana",
    "iso:country":"ES",
    "sg:address":"Calle de Solana, 11",
    "sg:city":"Torrejon Ardoz",
    "sg:orig_category":"Chapister\u00cda",
    "sg:phone":"+34 916 76 38 13",
    "sg:postcode":"28850",
    "sg:province":"Madrid",
    "wof:name":"Polcar Torrejon S.l.l.",
    "wof:placetype":"venue"
},
  "geometry": {"coordinates":[-3.4704010487,40.4541702271],"type":"Point"}
}