{
  "type": "Feature",
  "properties": {
    "iso:country":"ES",
    "sg:address":"Calle de Puerto De Pozazal, 4",
    "sg:city":"Madrid",
    "sg:orig_category":"Charcuter\u00cdas (al Por Mayor)",
    "sg:phone":"+34 917 77 78 08",
    "sg:postcode":"28031",
    "sg:province":"Madrid",
    "wof:name":"Comercial Hermanos Magro S.a.",
    "wof:placetype":"venue"
},
  "geometry": {"coordinates":[-3.6281449795,40.3794746399],"type":"Point"}
}