{
  "type": "Feature",
  "properties": {
    "iso:country":"ES",
    "sg:address":"Av Bon Pastor, 142",
    "sg:city":"S. Adria Besos",
    "sg:orig_category":"Agentes, Concesionarios Y Sucursales De Veh\u00cdculos",
    "sg:phone":"+34 934 62 64 31",
    "sg:postcode":"08930",
    "sg:province":"Barcelona",
    "wof:name":"Hispanomocion S.a.",
    "wof:placetype":"venue"
},
  "geometry": {"coordinates":[2.2100300789,41.431186676],"type":"Point"}
}