{
  "type": "Feature",
  "properties": {
    "addr:full":"Calle de Clavel, 2 Alora M\u00e1laga 29500",
    "addr:housenumber":"2",
    "addr:postcode":"29500",
    "addr:street":"Calle De Clavel;Ma\u0301Laga",
    "iso:country":"ES",
    "sg:address":"Calle de Clavel, 2",
    "sg:city":"Alora",
    "sg:orig_category":"Comercio, Reparaci\u00d3n De Motocicletas, Bicicletas Y Piezas Sueltas",
    "sg:phone":"+34 952 49 60 08",
    "sg:postcode":"29500",
    "sg:province":"M\u00e1laga",
    "wof:name":"Merino Baena Inmaculada",
    "wof:placetype":"venue"
},
  "geometry": {"coordinates":[-4.7049407959,36.8260421753],"type":"Point"}
}