{
  "type": "Feature",
  "properties": {
    "iso:country":"ES",
    "sg:address":"Avda Federico Mayo, 23",
    "sg:city":"Huelva",
    "sg:orig_category":"Farmacias",
    "sg:phone":"+34 959 25 24 91",
    "sg:postcode":"21004",
    "sg:province":"Huelva",
    "wof:name":"Martin Fernandez Mercedes",
    "wof:placetype":"venue"
},
  "geometry": {"coordinates":[-6.9427847862,37.2571105957],"type":"Point"}
}