{
  "type": "Feature",
  "properties": {
    "addr:full":"Carrer de Cobalt, 156 Hospitalet Llobregat Barcelona 08907",
    "addr:housenumber":"156",
    "addr:postcode":"08907",
    "addr:street":"Carrer De Cobalt",
    "iso:country":"ES",
    "sg:address":"Carrer de Cobalt, 156",
    "sg:city":"Hospitalet Llobregat",
    "sg:orig_category":"Maquinaria Para Industrias Diversas",
    "sg:phone":"+34 933 37 51 50",
    "sg:postcode":"08907",
    "sg:province":"Barcelona",
    "wof:name":"J.j.electromecanica S.c.p.",
    "wof:placetype":"venue"
},
  "geometry": {"coordinates":[2.1016380787,41.3556671143],"type":"Point"}
}