{
  "type": "Feature",
  "properties": {
    "addr:full":"Rond Buenavista, S/n Toledo Toledo 45005",
    "addr:housenumber":"s / n",
    "addr:postcode":"45005",
    "addr:street":"Buenavista",
    "iso:country":"ES",
    "sg:address":"Rond Buenavista, S/n",
    "sg:city":"Toledo",
    "sg:orig_category":"Agencias Y Agentes Comerciales, Representantes",
    "sg:phone":"+34 925 22 08 92",
    "sg:postcode":"45005",
    "sg:province":"Toledo",
    "wof:name":"Representaciones F.j. De La Iglesia S.l.",
    "wof:placetype":"venue"
},
  "geometry": {"coordinates":[-4.0396938324,39.874370575],"type":"Point"}
}