{
  "type": "Feature",
  "properties": {
    "iso:country":"ES",
    "sg:address":"Calle de Valencia, 18",
    "sg:city":"Segorbe",
    "sg:orig_category":"Bancos",
    "sg:phone":"+34 964 71 06 45",
    "sg:postcode":"12400",
    "sg:province":"Castell\u00f3n",
    "wof:name":"Banco Espa\u00f1ol De Credito S.a.",
    "wof:placetype":"venue"
},
  "geometry": {"coordinates":[-0.4879640043,39.8511199951],"type":"Point"}
}