{
  "type": "Feature",
  "properties": {
    "iso:country":"ES",
    "sg:address":"Calle de Ferrero, 15",
    "sg:city":"Almansa",
    "sg:orig_category":"Fabricaci\u00d3n De Juegos Y Juguetes",
    "sg:phone":"+34 967 34 50 81",
    "sg:postcode":"02640",
    "sg:province":"Albacete",
    "wof:name":"Casa Mancebo S.l.",
    "wof:placetype":"venue"
},
  "geometry": {"coordinates":[-1.095739007,38.8680000305],"type":"Point"}
}