{
  "type": "Feature",
  "properties": {
    "iso:country":"ES",
    "sg:address":"Calle de Pedroches, 18",
    "sg:city":"Leganes",
    "sg:orig_category":"Zapatos (al Por Menor)",
    "sg:phone":"+34 916 88 04 22",
    "sg:postcode":"28915",
    "sg:province":"Madrid",
    "wof:name":"Vazquez Diaz Angel",
    "wof:placetype":"venue"
},
  "geometry": {"coordinates":[-3.7544059753,40.3358268738],"type":"Point"}
}