{
  "type": "Feature",
  "properties": {
    "iso:country":"ES",
    "sg:address":"Calle de Fernando El Catolico, 54",
    "sg:city":"Malaga",
    "sg:orig_category":"Centros Empresariales",
    "sg:phone":"+34 952 25 35 14",
    "sg:postcode":"29013",
    "sg:province":"M\u00e1laga",
    "wof:name":"Viajes Amor Tour S. A.",
    "wof:placetype":"venue"
},
  "geometry": {"coordinates":[-4.414276123,36.731300354],"type":"Point"}
}