{
  "type": "Feature",
  "properties": {
    "addr:full":"Calle de Colon, S/n S. Fernando C\u00e1diz 11100",
    "addr:postcode":"11100",
    "addr:street":"Calle De Colon S / N S. Fernando Ca\u0301Diz",
    "iso:country":"ES",
    "sg:address":"Calle de Colon, S/n",
    "sg:city":"S. Fernando",
    "sg:orig_category":"Promotores Constructores",
    "sg:phone":"+34 956 59 34 43",
    "sg:postcode":"11100",
    "sg:province":"C\u00e1diz",
    "sg:website":"www.gabrielrojas.com",
    "wof:name":"Promotora Social San Fernando S.a.",
    "wof:placetype":"venue"
},
  "geometry": {"coordinates":[-6.1967434883,36.4687042236],"type":"Point"}
}