{
  "type": "Feature",
  "properties": {
    "iso:country":"ES",
    "sg:address":"Avda Cid, 3",
    "sg:city":"Valencia",
    "sg:orig_category":"Distribuci\u00d3n De Petr\u00d3leo Y Derivados",
    "sg:phone":"+34 963 85 63 97",
    "sg:postcode":"46018",
    "sg:province":"Valencia",
    "sg:website":"www.cepsa.es",
    "wof:name":"Herederos De Bernardo Ferrer Mu\u00f1oz S. R. C.",
    "wof:placetype":"venue"
},
  "geometry": {"coordinates":[-0.3904600143,39.4669914246],"type":"Point"}
}