{
  "type": "Feature",
  "properties": {
    "addr:full":"Avda San Juan De Sahagun, 9 Le\u00f3n Le\u00f3n 24007",
    "addr:housenumber":"9",
    "addr:postcode":"24007",
    "addr:street":"Avda San Juan De Sahagun;Leo\u0301N",
    "iso:country":"ES",
    "sg:address":"Avda San Juan De Sahagun, 9",
    "sg:city":"Le\u00f3n",
    "sg:orig_category":"Peluqueros: De Se\u00d1oras",
    "sg:phone":"+34 987 23 84 50",
    "sg:postcode":"24007",
    "sg:province":"Le\u00f3n",
    "wof:name":"Blanco Quijada Daniel",
    "wof:placetype":"venue"
},
  "geometry": {"coordinates":[-5.566988945,42.6063308716],"type":"Point"}
}