{
  "type": "Feature",
  "properties": {
    "iso:country":"ES",
    "sg:address":"Calle de Rioja, 108",
    "sg:city":"Leganes",
    "sg:orig_category":"Suministros Y Materiales Industriales",
    "sg:phone":"+34 916 80 10 67",
    "sg:postcode":"28915",
    "sg:province":"Madrid",
    "wof:name":"Suministros Electricos Mingo S.l.",
    "wof:placetype":"venue"
},
  "geometry": {"coordinates":[-3.7484810352,40.3338317871],"type":"Point"}
}