{
  "type": "Feature",
  "properties": {
    "iso:country":"ES",
    "sg:address":"Carr Ausias March, 17",
    "sg:city":"Benetusser",
    "sg:orig_category":"Madera Para Chapado",
    "sg:phone":"+34 963 76 17 28",
    "sg:postcode":"46910",
    "sg:province":"Valencia",
    "wof:name":"Quiros Lopez Miguel Angel",
    "wof:placetype":"venue"
},
  "geometry": {"coordinates":[-0.3976509869,39.42162323],"type":"Point"}
}