{
  "type": "Feature",
  "properties": {
    "iso:country":"ES",
    "sg:address":"Calle de Martin De Los Heros, 21",
    "sg:city":"Madrid",
    "sg:orig_category":"Comercio, Reparaci\u00d3n De Motocicletas, Bicicletas Y Piezas Sueltas",
    "sg:phone":"+34 915 47 56 12",
    "sg:postcode":"28008",
    "sg:province":"Madrid",
    "sg:website":"www.velardmotorsport.com",
    "wof:name":"Tecnica Del Motor Roman Infante S.l.",
    "wof:placetype":"venue"
},
  "geometry": {"coordinates":[-3.714414835,40.4253883362],"type":"Point"}
}