{
  "type": "Feature",
  "properties": {
    "addr:full":"Calle de Toledo, S/n Sonseca Toledo 45100",
    "addr:postcode":"45100",
    "addr:street":"Calle De Toledo S / N",
    "iso:country":"ES",
    "sg:address":"Calle de Toledo, S/n",
    "sg:city":"Sonseca",
    "sg:orig_category":"Hilaturas, Hilos Y Actividades Relacionadas",
    "sg:phone":"+34 925 38 06 95",
    "sg:postcode":"45100",
    "sg:province":"Toledo",
    "wof:name":"Hilados De Castilla S.l.",
    "wof:placetype":"venue"
},
  "geometry": {"coordinates":[-3.977658987,39.6890830994],"type":"Point"}
}