{
  "type": "Feature",
  "properties": {
    "iso:country":"ES",
    "sg:address":"Calle de Mayor, 1",
    "sg:city":"Huete",
    "sg:orig_category":"Transporte En General",
    "sg:phone":"+34 969 37 10 94",
    "sg:postcode":"16500",
    "sg:province":"Cuenca",
    "wof:name":"Salmeron Lopez Agustin",
    "wof:placetype":"venue"
},
  "geometry": {"coordinates":[-2.6912279129,40.1445236206],"type":"Point"}
}