{
  "type": "Feature",
  "properties": {
    "addr:full":"Calle de Ines Chemida, S/n Palmas De Gran Canaria Las Palmas 35009",
    "addr:housenumber":"s",
    "addr:postcode":"35009",
    "addr:street":"Calle De;/ N",
    "iso:country":"ES",
    "sg:address":"Calle de Ines Chemida, S/n",
    "sg:city":"Palmas De Gran Canaria",
    "sg:orig_category":"Promotores Constructores",
    "sg:phone":"+34 928 46 03 60",
    "sg:postcode":"35009",
    "sg:province":"Las Palmas",
    "wof:name":"Lopesan Asfaltos Y Construcciones S.a.",
    "wof:placetype":"venue"
},
  "geometry": {"coordinates":[-15.4297990799,28.1522598267],"type":"Point"}
}