{
  "type": "Feature",
  "properties": {
    "iso:country":"ES",
    "sg:address":"Carrer de Sadet, 25",
    "sg:city":"S. Just Desvern",
    "sg:orig_category":"Peluqueros: De Se\u00d1oras",
    "sg:phone":"+34 933 71 71 44",
    "sg:postcode":"08960",
    "sg:province":"Barcelona",
    "wof:name":"Lopez Jurado Ana",
    "wof:placetype":"venue"
},
  "geometry": {"coordinates":[2.0716819763,41.3807373047],"type":"Point"}
}