{
  "type": "Feature",
  "properties": {
    "iso:country":"ES",
    "sg:address":"Ctra Nacional Ii, 18",
    "sg:city":"Limits",
    "sg:orig_category":"Estancos",
    "sg:phone":"+34 972 55 42 67",
    "sg:postcode":"17709",
    "sg:province":"Girona",
    "wof:name":"Serra Santalo Maria Pilar",
    "wof:placetype":"venue"
},
  "geometry": {"coordinates":[2.8407700062,42.4389533997],"type":"Point"}
}