{
  "type": "Feature",
  "properties": {
    "iso:country":"ES",
    "sg:address":"Avda Carlota Alessandri, 186",
    "sg:city":"Torremolinos",
    "sg:orig_category":"Mec\u00c1nico Del Autom\u00d3vil",
    "sg:phone":"+34 952 37 30 74",
    "sg:postcode":"29620",
    "sg:province":"M\u00e1laga",
    "wof:name":"Talleres Goman S.l.",
    "wof:placetype":"venue"
},
  "geometry": {"coordinates":[-4.5085668564,36.6085472107],"type":"Point"}
}