{
  "type": "Feature",
  "properties": {
    "addr:full":"Afueras, S/n Albero Bajo Huesca 22255",
    "addr:postcode":"22255",
    "addr:street":"Afueras S / N",
    "iso:country":"ES",
    "sg:address":"Afueras, S/n",
    "sg:city":"Albero Bajo",
    "sg:orig_category":"Aparatos E Instalaci\u00d3n De Regad\u00cdos",
    "sg:phone":"+34 974 34 02 23",
    "sg:postcode":"22255",
    "sg:province":"Huesca",
    "wof:name":"Comunidad De Regantes La Corona",
    "wof:placetype":"venue"
},
  "geometry": {"coordinates":[-0.4344089925,41.9588890076],"type":"Point"}
}