{
  "type": "Feature",
  "properties": {
    "addr:full":"Calle de Antonio Machado, 44 Torrevieja Alicante 03180",
    "addr:housenumber":"44",
    "addr:postcode":"03180",
    "addr:street":"Calle De Antonio Machado",
    "iso:country":"ES",
    "sg:address":"Calle de Antonio Machado, 44",
    "sg:city":"Torrevieja",
    "sg:orig_category":"Contenedores (mercanc\u00cdas)",
    "sg:phone":"+34 965 71 32 80",
    "sg:postcode":"03180",
    "sg:province":"Alicante",
    "wof:name":"Martinez Martinez Antonio",
    "wof:placetype":"venue"
},
  "geometry": {"coordinates":[-0.6790809035,37.9792900085],"type":"Point"}
}