{
  "type": "Feature",
  "properties": {
    "iso:country":"ES",
    "sg:address":"Carrer de Abat Oliva, 10",
    "sg:city":"S. Celoni",
    "sg:orig_category":"Art\u00cdculos De Decoraci\u00d3n",
    "sg:phone":"+34 938 67 51 94",
    "sg:postcode":"08470",
    "sg:province":"Barcelona",
    "wof:name":"Via Del Corso",
    "wof:placetype":"venue"
},
  "geometry": {"coordinates":[2.4902939796,41.6901397705],"type":"Point"}
}