{
  "type": "Feature",
  "properties": {
    "iso:country":"ES",
    "sg:address":"Carr Mar, De Sa, 17",
    "sg:city":"Soller",
    "sg:orig_category":"Tintes (fabricaci\u00d3n, Al Por Mayor)",
    "sg:phone":"+34 971 63 05 06",
    "sg:postcode":"07100",
    "sg:province":"Islas Baleares",
    "wof:name":"Bugaderia La Vall S.a.",
    "wof:placetype":"venue"
},
  "geometry": {"coordinates":[2.7147779465,39.7659072876],"type":"Point"}
}