{
  "type": "Feature",
  "properties": {
    "addr:full":"Calle de Montemar, Marques De, 20 Melilla Melilla 52006",
    "addr:housenumber":"20",
    "addr:postcode":"52006",
    "addr:street":"Calle De Montemar Marques De",
    "iso:country":"ES",
    "sg:address":"Calle de Montemar, Marques De, 20",
    "sg:city":"Melilla",
    "sg:orig_category":"Inform\u00c1tica, Ofim\u00c1tica (estudios, Asesor\u00cda, Ingenier\u00cda, Formaci\u00d3n)",
    "sg:phone":"+34 952 67 15 84",
    "sg:postcode":"52006",
    "sg:province":"Melilla",
    "wof:name":"Fundacion Empresas-universidad De Granada",
    "wof:placetype":"venue"
},
  "geometry": {"coordinates":[-2.9397099018,35.2832260132],"type":"Point"}
}