{
  "type": "Feature",
  "properties": {
    "addr:full":"Ctra. Casas Iba\u00f1ez, Km. 0003,7 Albacete Albacete 02006",
    "addr:postcode":"02006",
    "addr:street":"Ctra. Casas Iban\u0303Ez Km. 0003,7",
    "iso:country":"ES",
    "sg:address":"Ctra. Casas Iba\u00f1ez, Km. 0003,7",
    "sg:city":"Albacete",
    "sg:orig_category":"Fabricaci\u00d3n De Mobiliario De Oficina",
    "sg:phone":"+34 967 21 13 17",
    "sg:postcode":"02006",
    "sg:province":"Albacete",
    "sg:website":"www.piquerasycrespo.com",
    "wof:name":"Piqueras Y Crespo S.l.",
    "wof:placetype":"venue"
},
  "geometry": {"coordinates":[-1.8574210405,39.0163497925],"type":"Point"}
}