{
  "type": "Feature",
  "properties": {
    "addr:full":"Yumbo, S/n S. Agustin-playa Ingles Las Palmas 35100",
    "addr:housenumber":"s",
    "addr:postcode":"35100",
    "addr:street":"/ N S. Agustin-Playa",
    "iso:country":"ES",
    "sg:address":"Yumbo, S/n",
    "sg:city":"S. Agustin-playa Ingles",
    "sg:orig_category":"Cl\u00cdnicas M\u00c9dicas",
    "sg:phone":"+34 928 76 11 72",
    "sg:postcode":"35100",
    "sg:province":"Las Palmas",
    "wof:name":"Al Shubbak Shubbak Mahmud",
    "wof:placetype":"venue"
},
  "geometry": {"coordinates":[-15.4300060272,28.1248226166],"type":"Point"}
}