{
  "type": "Feature",
  "properties": {
    "iso:country":"ES",
    "sg:address":"Carrer de Bacardi, 26",
    "sg:city":"Hospitalet Llobregat",
    "sg:orig_category":"Fisioterapia",
    "sg:phone":"+34 932 96 77 04",
    "sg:postcode":"08902",
    "sg:province":"Barcelona",
    "wof:name":"Crespo Palomo Oscar",
    "wof:placetype":"venue"
},
  "geometry": {"coordinates":[2.1288890839,41.3623504639],"type":"Point"}
}