{
  "type": "Feature",
  "properties": {
    "iso:country":"ES",
    "sg:address":"Trva Entrala, 8",
    "sg:city":"Morales Vino",
    "sg:orig_category":"Aparatos De Iluminaci\u00d3n (al Por Menor)",
    "sg:phone":"+34 980 57 02 43",
    "sg:postcode":"49190",
    "sg:province":"Zamora",
    "wof:name":"Portos Merino Manuel Angel",
    "wof:placetype":"venue"
},
  "geometry": {"coordinates":[-5.7337379456,41.4451713562],"type":"Point"}
}