{
  "type": "Feature",
  "properties": {
    "addr:full":"Calle de Arrasate, 26 Donostia-san Sebastian Guip\u00f9zcoa 20005",
    "addr:housenumber":"26",
    "addr:postcode":"20005",
    "addr:street":"Calle De Arrasate",
    "iso:country":"ES",
    "sg:address":"Calle de Arrasate, 26",
    "sg:city":"Donostia-san Sebastian",
    "sg:orig_category":"Carnicer\u00cdas, Carnicer\u00cdas",
    "sg:phone":"+34 943 42 17 36",
    "sg:postcode":"20005",
    "sg:province":"Guip\u00f9zcoa",
    "wof:name":"Alzuri Goya Mari Jose",
    "wof:placetype":"venue"
},
  "geometry": {"coordinates":[-1.9822202921,43.318031311],"type":"Point"}
}