{
  "type": "Feature",
  "properties": {
    "iso:country":"ES",
    "sg:address":"Calle de San Francisco, 4",
    "sg:city":"Tarifa",
    "sg:orig_category":"Agricultores, Agricultores",
    "sg:phone":"+34 956 68 46 34",
    "sg:postcode":"11380",
    "sg:province":"C\u00e1diz",
    "wof:name":"Sanchez-ybarguen Salcedo Elvira",
    "wof:placetype":"venue"
},
  "geometry": {"coordinates":[-5.6030550003,36.0130844116],"type":"Point"}
}