{
  "type": "Feature",
  "properties": {
    "iso:country":"ES",
    "sg:address":"Calle de Pablo Picasso, 1",
    "sg:city":"Alcala Real",
    "sg:orig_category":"M\u00c9dicos: Otorrinolaringolog\u00cda",
    "sg:phone":"+34 953 58 47 84",
    "sg:postcode":"23680",
    "sg:province":"Ja\u00e9n",
    "wof:name":"Carmona Marinetto Asuncion",
    "wof:placetype":"venue"
},
  "geometry": {"coordinates":[-3.9221661091,37.4593200684],"type":"Point"}
}