{
  "type": "Feature",
  "properties": {
    "addr:full":"Avda Jose Mu\u00d1oz De Vargas, 9 Huelva Huelva 21006",
    "addr:housenumber":"9",
    "addr:postcode":"21006",
    "addr:street":"Avda Jose",
    "iso:country":"ES",
    "sg:address":"Avda Jose Mu\u00d1oz De Vargas, 9",
    "sg:city":"Huelva",
    "sg:orig_category":"Mec\u00c1nico Del Autom\u00d3vil",
    "sg:phone":"+34 959 22 23 45",
    "sg:postcode":"21006",
    "sg:province":"Huelva",
    "wof:name":"Ruiz Walls S.l.",
    "wof:placetype":"venue"
},
  "geometry": {"coordinates":[-6.937707901,37.260219574],"type":"Point"}
}