{
  "type": "Feature",
  "properties": {
    "addr:full":"Calle de Acacia, S/n Puebla Alfinden Zaragoza 50171",
    "addr:housenumber":"s / n",
    "addr:postcode":"50171",
    "addr:street":"Calle De Acacia;Alfinden",
    "iso:country":"ES",
    "sg:address":"Calle de Acacia, S/n",
    "sg:city":"Puebla Alfinden",
    "sg:orig_category":"Construcciones Met\u00c1licas",
    "sg:phone":"+34 976 10 80 51",
    "sg:postcode":"50171",
    "sg:province":"Zaragoza",
    "wof:name":"Menaje Y Confort Centro De Produccion S.l.",
    "wof:placetype":"venue"
},
  "geometry": {"coordinates":[-0.7632855177,41.6416625977],"type":"Point"}
}