{
  "type": "Feature",
  "properties": {
    "addr:full":"Avda Valencia, 3 Utrillas Teruel 44760",
    "addr:housenumber":"3",
    "addr:postcode":"44760",
    "addr:street":"Avda Valencia",
    "iso:country":"ES",
    "sg:address":"Avda Valencia, 3",
    "sg:city":"Utrillas",
    "sg:orig_category":"Loter\u00cda Y T\u00d3mbola",
    "sg:phone":"+34 978 75 68 16",
    "sg:postcode":"44760",
    "sg:province":"Teruel",
    "wof:name":"Espada Aguilar Carmen",
    "wof:placetype":"venue"
},
  "geometry": {"coordinates":[-0.847743988,40.8096466064],"type":"Point"}
}