{
  "type": "Feature",
  "properties": {
    "addr:full":"Ptda Les Cloches, 10 Vilafames Castell\u00f3n 12192",
    "addr:housenumber":"10",
    "addr:postcode":"12192",
    "addr:street":"Ptda Les Cloches;Castello\u0301N",
    "iso:country":"ES",
    "sg:address":"Ptda Les Cloches, 10",
    "sg:city":"Vilafames",
    "sg:orig_category":"Maquinaria Para Industrias Diversas",
    "sg:phone":"+34 964 76 03 25",
    "sg:postcode":"12192",
    "sg:province":"Castell\u00f3n",
    "wof:name":"Clausell Brisach Jose",
    "wof:placetype":"venue"
},
  "geometry": {"coordinates":[-0.0640499964,40.1220092773],"type":"Point"}
}