{
  "type": "Feature",
  "properties": {
    "iso:country":"ES",
    "sg:address":"Pla\u00c7 Vayreda, 5",
    "sg:city":"Olot",
    "sg:orig_category":"Inmobiliaria (agencias)",
    "sg:phone":"+34 972 26 95 61",
    "sg:postcode":"17800",
    "sg:province":"Girona",
    "wof:name":"Inmobiliaria Puigsacalm S.a.",
    "wof:placetype":"venue"
},
  "geometry": {"coordinates":[2.4859399796,42.1788101196],"type":"Point"}
}