{
  "type": "Feature",
  "properties": {
    "addr:full":"Calle de Coli Escalona, Leonardo, 24 Sabi\u00f1anigo Huesca 22600",
    "addr:housenumber":"24",
    "addr:postcode":"22600",
    "addr:street":"Calle De Coli Escalona Leonardo",
    "iso:country":"ES",
    "sg:address":"Calle de Coli Escalona, Leonardo, 24",
    "sg:city":"Sabi\u00f1anigo",
    "sg:orig_category":"Pintura Y Barniz (al Por Menor)",
    "sg:phone":"+34 974 48 12 17",
    "sg:postcode":"22600",
    "sg:province":"Huesca",
    "wof:name":"Comercial Joaquin Y Maribel S.l",
    "wof:placetype":"venue"
},
  "geometry": {"coordinates":[-0.3639279902,42.5188331604],"type":"Point"}
}