{
  "type": "Feature",
  "properties": {
    "addr:full":"Calle de Baiona, 3 Cangas Pontevedra 36940",
    "addr:housenumber":"3",
    "addr:postcode":"36940",
    "addr:street":"Calle De Baiona",
    "iso:country":"ES",
    "sg:address":"Calle de Baiona, 3",
    "sg:city":"Cangas",
    "sg:orig_category":"Mercer\u00cda, Lencer\u00cda (al Por Menor)",
    "sg:phone":"+34 986 30 42 70",
    "sg:postcode":"36940",
    "sg:province":"Pontevedra",
    "wof:name":"Sotelo Pena Carmen",
    "wof:placetype":"venue"
},
  "geometry": {"coordinates":[-8.7798376083,42.2648887634],"type":"Point"}
}