{
  "type": "Feature",
  "properties": {
    "iso:country":"ES",
    "sg:address":"Carrer de Rafael De Casanova, 63",
    "sg:city":"Molins Rei",
    "sg:orig_category":"Promotores Constructores",
    "sg:phone":"+34 936 68 74 39",
    "sg:postcode":"08750",
    "sg:province":"Barcelona",
    "wof:name":"Sanchez Mayor Juan",
    "wof:placetype":"venue"
},
  "geometry": {"coordinates":[2.0156259537,41.4127349854],"type":"Point"}
}