{
  "type": "Feature",
  "properties": {
    "iso:country":"ES",
    "sg:address":"Carrer de Rossello, 76",
    "sg:city":"Hospitalet Llobregat",
    "sg:orig_category":"Maquinaria Para Industrias Diversas",
    "sg:phone":"+34 934 22 39 58",
    "sg:postcode":"08903",
    "sg:province":"Barcelona",
    "wof:name":"Dalmau Nadal Ramon",
    "wof:placetype":"venue"
},
  "geometry": {"coordinates":[2.1267800331,41.3707618713],"type":"Point"}
}