{
  "type": "Feature",
  "properties": {
    "iso:country":"ES",
    "sg:address":"Calle de Tales De Mileto, 15",
    "sg:city":"Marbella",
    "sg:orig_category":"Porcelana Decorativa",
    "sg:phone":"+34 952 76 51 29",
    "sg:postcode":"29600",
    "sg:province":"M\u00e1laga",
    "sg:website":"www.cder.com",
    "wof:name":"Rueda Escardo Cristina",
    "wof:placetype":"venue"
},
  "geometry": {"coordinates":[-4.8666601181,36.5084342957],"type":"Point"}
}