{
  "type": "Feature",
  "properties": {
    "addr:full":"Calle de Carlos Iii El Noble, 6 Tudela Navarra 31500",
    "addr:housenumber":"6",
    "addr:postcode":"31500",
    "addr:street":"Calle De Carlos Iii El Noble",
    "iso:country":"ES",
    "sg:address":"Calle de Carlos Iii El Noble, 6",
    "sg:city":"Tudela",
    "sg:orig_category":"Empresarios",
    "sg:phone":"+34 948 82 24 91",
    "sg:postcode":"31500",
    "sg:province":"Navarra",
    "wof:name":"Milagro Marzal Cesar",
    "wof:placetype":"venue"
},
  "geometry": {"coordinates":[-1.5968892574,42.0549888611],"type":"Point"}
}