{
  "type": "Feature",
  "properties": {
    "addr:full":"Bakardadeko Ama Kalea, 2 O\u00f1ati Guip\u00f9zcoa 20560",
    "addr:housenumber":"2",
    "addr:postcode":"20560",
    "addr:street":"Ama Kalea;Guipu\u0300Zcoa",
    "iso:country":"ES",
    "sg:address":"Bakardadeko Ama Kalea, 2",
    "sg:city":"O\u00f1ati",
    "sg:orig_category":"M\u00c9dicos: Cirug\u00cda Ortop\u00c9dica Y Traumatolog\u00cda",
    "sg:phone":"+34 943 78 29 60",
    "sg:postcode":"20560",
    "sg:province":"Guip\u00f9zcoa",
    "wof:name":"Galarza Arrazola Jose Ramon",
    "wof:placetype":"venue"
},
  "geometry": {"coordinates":[-2.4127719402,43.0335235596],"type":"Point"}
}