{
  "type": "Feature",
  "properties": {
    "iso:country":"ES",
    "sg:address":"Avda Burgos, 13",
    "sg:city":"Aguilar Campoo",
    "sg:orig_category":"Contenedores (mercanc\u00cdas)",
    "sg:phone":"+34 979 12 25 39",
    "sg:postcode":"34800",
    "sg:province":"Palencia",
    "wof:name":"Ogensa-ascan U.t.e.",
    "wof:placetype":"venue"
},
  "geometry": {"coordinates":[-4.2532968521,42.7927284241],"type":"Point"}
}