{
  "type": "Feature",
  "properties": {
    "iso:country":"ES",
    "sg:address":"Tamon, S/n",
    "sg:city":"Tamon",
    "sg:orig_category":"Materiales De Aislamiento T\u00c9rmico Y Ac\u00dastico",
    "sg:phone":"+34 985 51 80 89",
    "sg:postcode":"33469",
    "sg:province":"Asturias",
    "sg:website":"www.wanneryvinyas.com",
    "wof:name":"Wanner Y Vinyas S.a.",
    "wof:placetype":"venue"
},
  "geometry": {"coordinates":[-5.9832577705,43.2504386902],"type":"Point"}
}