{
  "type": "Feature",
  "properties": {
    "iso:country":"ES",
    "sg:address":"Carr Costa Brava, 28",
    "sg:city":"Girona",
    "sg:orig_category":"Peluqueros: De Se\u00d1oras",
    "sg:phone":"+34 972 23 06 94",
    "sg:postcode":"17005",
    "sg:province":"Girona",
    "wof:name":"Madrenas Grau Maria Dolores",
    "wof:placetype":"venue"
},
  "geometry": {"coordinates":[2.8087930679,41.9692687988],"type":"Point"}
}