{
  "type": "Feature",
  "properties": {
    "iso:country":"ES",
    "sg:address":"Calle de Galizia, 2",
    "sg:city":"Basauri",
    "sg:orig_category":"Bisuter\u00cda, Joyer\u00cda, Relojer\u00cda (al Por Menor)",
    "sg:phone":"+34 944 00 58 96",
    "sg:postcode":"48970",
    "sg:province":"Vizcaya",
    "wof:name":"Alberto Santos Garcia",
    "wof:placetype":"venue"
},
  "geometry": {"coordinates":[-2.8822143078,43.2356948853],"type":"Point"}
}