{
  "type": "Feature",
  "properties": {
    "iso:country":"ES",
    "sg:address":"Carrer de Pare Rodes, 4",
    "sg:city":"Barcelona",
    "sg:orig_category":"Molduras, Junquillos, Listones Y Molduras Perforadas",
    "sg:phone":"+34 933 53 49 51",
    "sg:postcode":"08042",
    "sg:province":"Barcelona",
    "wof:name":"Acu\u00f1a Hermosilla Jose Ricardo",
    "wof:placetype":"venue"
},
  "geometry": {"coordinates":[2.1744353771,41.4399032593],"type":"Point"}
}