{
  "type": "Feature",
  "properties": {
    "iso:country":"ES",
    "sg:address":"Cno Cementerio, S/n",
    "sg:city":"Real Montroi",
    "sg:orig_category":"Fabricaci\u00d3n, Importaci\u00d3n De L\u00c1mparas Y Bombillas",
    "sg:phone":"+34 962 55 61 85",
    "sg:postcode":"46194",
    "sg:province":"Valencia",
    "wof:name":"Jucalamp S. L.",
    "wof:placetype":"venue"
},
  "geometry": {"coordinates":[-0.6092489958,39.3363342285],"type":"Point"}
}