{
  "type": "Feature",
  "properties": {
    "iso:country":"ES",
    "sg:address":"Calle de Islas Cies, 7",
    "sg:city":"Alcorcon",
    "sg:orig_category":"Cervecer\u00cdas",
    "sg:phone":"+34 916 10 12 04",
    "sg:postcode":"28924",
    "sg:province":"Madrid",
    "wof:name":"Garcia Arevalo Eulalio",
    "wof:placetype":"venue"
},
  "geometry": {"coordinates":[-3.8093891144,40.3447685242],"type":"Point"}
}