{
  "type": "Feature",
  "properties": {
    "iso:country":"ES",
    "sg:address":"Calle de Manuel Viola, 11",
    "sg:city":"Zaragoza",
    "sg:orig_category":"Agencias Y Agentes Comerciales, Representantes",
    "sg:phone":"+34 976 47 60 19",
    "sg:postcode":"50014",
    "sg:province":"Zaragoza",
    "wof:name":"Velazquez Toro Luis Gonzaga",
    "wof:placetype":"venue"
},
  "geometry": {"coordinates":[-0.8578490019,41.6593589783],"type":"Point"}
}