{
  "type": "Feature",
  "properties": {
    "addr:full":"Cmno San Martin De La Vega, 23 Arganda Madrid 28500",
    "addr:housenumber":"23",
    "addr:postcode":"28500",
    "addr:street":"Cmno San Martin De La Vega",
    "iso:country":"ES",
    "sg:address":"Cmno San Martin De La Vega, 23",
    "sg:city":"Arganda",
    "sg:orig_category":"Alquiler De Gr\u00daas",
    "sg:phone":"+34 918 71 18 16",
    "sg:postcode":"28500",
    "sg:province":"Madrid",
    "sg:website":"www.gruasaguilar.com",
    "wof:name":"Gruas Aguilar S.l.",
    "wof:placetype":"venue"
},
  "geometry": {"coordinates":[-3.4607820511,40.3018684387],"type":"Point"}
}