{
  "type": "Feature",
  "properties": {
    "iso:country":"ES",
    "sg:address":"Carrer de Joan Maragall, 83",
    "sg:city":"Mataro",
    "sg:orig_category":"Hilaturas, Hilos Y Actividades Relacionadas",
    "sg:phone":"+34 937 99 48 92",
    "sg:postcode":"08303",
    "sg:province":"Barcelona",
    "wof:name":"Bueno Garcia Juan",
    "wof:placetype":"venue"
},
  "geometry": {"coordinates":[2.4289700985,41.5426330566],"type":"Point"}
}