{
  "type": "Feature",
  "properties": {
    "addr:full":"Calle de Asturias, 4 Gijon Asturias 33206",
    "addr:housenumber":"4",
    "addr:postcode":"33206",
    "addr:street":"Calle De Asturias",
    "iso:country":"ES",
    "sg:address":"Calle de Asturias, 4",
    "sg:city":"Gijon",
    "sg:orig_category":"Abogados",
    "sg:phone":"+34 985 34 56 86",
    "sg:postcode":"33206",
    "sg:province":"Asturias",
    "wof:name":"Adoracion Rosaenz Lopez Y Otros Cdad.",
    "wof:placetype":"venue"
},
  "geometry": {"coordinates":[-5.6642546654,43.5401649475],"type":"Point"}
}