{
  "type": "Feature",
  "properties": {
    "addr:full":"Calle de Labati, S/n Arag\u00fces Puerto Huesca 22730",
    "addr:housenumber":"s",
    "addr:postcode":"22730",
    "addr:street":"Calle De Labati;/ N Araguees Puerto",
    "iso:country":"ES",
    "sg:address":"Calle de Labati, S/n",
    "sg:city":"Arag\u00fces Puerto",
    "sg:orig_category":"Comunidades Religiosas",
    "sg:phone":"+34 974 37 14 57",
    "sg:postcode":"22730",
    "sg:province":"Huesca",
    "wof:name":"Curia Provincial Compa\u00f1ia De Jesus",
    "wof:placetype":"venue"
},
  "geometry": {"coordinates":[-0.6719059944,42.7061195374],"type":"Point"}
}