{
  "type": "Feature",
  "properties": {
    "addr:full":"Calle de Andres Segovia, 38 Granada Granada 18006",
    "addr:housenumber":"38",
    "addr:postcode":"18006",
    "addr:street":"Calle De Andres Segovia",
    "iso:country":"ES",
    "sg:address":"Calle de Andres Segovia, 38",
    "sg:city":"Granada",
    "sg:orig_category":"Farmacias",
    "sg:phone":"+34 958 81 15 51",
    "sg:postcode":"18006",
    "sg:province":"Granada",
    "wof:name":"Garach Galan Manuel",
    "wof:placetype":"venue"
},
  "geometry": {"coordinates":[-3.5946030617,37.1626930237],"type":"Point"}
}