{
  "type": "Feature",
  "properties": {
    "addr:full":"Calle de Mendez Nu\u00d1ez, 12 Carolina Ja\u00e9n 23200",
    "addr:housenumber":"12",
    "addr:postcode":"23200",
    "addr:street":"Calle De Mendez Nun\u0303Ez;Jae\u0301N",
    "iso:country":"ES",
    "sg:address":"Calle de Mendez Nu\u00d1ez, 12",
    "sg:city":"Carolina",
    "sg:orig_category":"Cr\u00cda De Animales",
    "sg:phone":"+34 953 66 02 94",
    "sg:postcode":"23200",
    "sg:province":"Ja\u00e9n",
    "wof:name":"Valero Perez Ignacio",
    "wof:placetype":"venue"
},
  "geometry": {"coordinates":[-3.6138958931,38.2738418579],"type":"Point"}
}