{
  "type": "Feature",
  "properties": {
    "addr:full":"Calle de Carvajal, 2 Palmas De Gran Canaria Las Palmas 35004",
    "addr:housenumber":"2",
    "addr:postcode":"35004",
    "addr:street":"Calle De Carvajal",
    "iso:country":"ES",
    "sg:address":"Calle de Carvajal, 2",
    "sg:city":"Palmas De Gran Canaria",
    "sg:orig_category":"Ense\u00d1anza, Formaci\u00d3n Profesional: Aprendizaje",
    "sg:phone":"+34 928 24 89 79",
    "sg:postcode":"35004",
    "sg:province":"Las Palmas",
    "wof:name":"Gobierno De Canarias",
    "wof:placetype":"venue"
},
  "geometry": {"coordinates":[-15.4211082458,28.1180114746],"type":"Point"}
}