{
  "type": "Feature",
  "properties": {
    "addr:full":"Calle de Rodriguez Arias, 10 Bilbao Vizcaya 48011",
    "addr:housenumber":"10",
    "addr:postcode":"48011",
    "addr:street":"Calle De Rodriguez Arias",
    "iso:country":"ES",
    "sg:address":"Calle de Rodriguez Arias, 10",
    "sg:city":"Bilbao",
    "sg:orig_category":"Art\u00cdculos De Regalo (al Por Menor)",
    "sg:phone":"+34 944 16 98 00",
    "sg:postcode":"48011",
    "sg:province":"Vizcaya",
    "wof:name":"Guerra San Martin S. A.",
    "wof:placetype":"venue"
},
  "geometry": {"coordinates":[-2.935997963,43.2621955872],"type":"Point"}
}