{
  "type": "Feature",
  "properties": {
    "iso:country":"ES",
    "sg:address":"Mola, S/n",
    "sg:city":"Salardu",
    "sg:classifiers":[
        {
            "category":"Sports & Exercise",
            "subcategory":"Golf",
            "type":"Entertainment"
        }
    ],
    "sg:phone":"+34 973 64 45 72",
    "sg:postcode":"25598",
    "sg:province":"Lleida",
    "sg:tags":[
        "y",
        "de",
        "campos",
        "clases"
    ],
    "sg:website":"www.golfsalardu.com",
    "wof:name":"Navarro Pozo Bartolome",
    "wof:placetype":"venue"
},
  "geometry": {"coordinates":[0.9039779902,42.7065010071],"type":"Point"}
}