{
  "type": "Feature",
  "properties": {
    "iso:country":"ES",
    "sg:address":"Calle de Olimpico Francisco Fernandez Ochoa, S/n",
    "sg:city":"Alcorcon",
    "sg:orig_category":"Centros De Educaci\u00d3n Especial",
    "sg:phone":"+34 916 41 03 62",
    "sg:postcode":"28923",
    "sg:province":"Madrid",
    "wof:name":"Colegio Publico Federico Garcia Lorca",
    "wof:placetype":"venue"
},
  "geometry": {"coordinates":[-3.8128941059,40.3445053101],"type":"Point"}
}