{
  "type": "Feature",
  "properties": {
    "iso:country":"ES",
    "sg:address":"Ctra. Valencia-ademuz, Km. 0013,0",
    "sg:city":"S. Antonio Benageber",
    "sg:orig_category":"Semiller\u00cdas",
    "sg:phone":"+34 961 35 09 25",
    "sg:postcode":"46184",
    "sg:province":"Valencia",
    "wof:name":"Madrid Conesa Juan",
    "wof:placetype":"venue"
},
  "geometry": {"coordinates":[-0.5012540221,39.5620651245],"type":"Point"}
}