{
  "type": "Feature",
  "properties": {
    "iso:country":"ES",
    "sg:address":"Calle de Mayor, 19",
    "sg:city":"Alcolea Cinca",
    "sg:orig_category":"Cr\u00cda De Corderos Y De Cabras",
    "sg:phone":"+34 974 46 95 84",
    "sg:postcode":"22410",
    "sg:province":"Huesca",
    "wof:name":"Ovired Calidad S.l.",
    "wof:placetype":"venue"
},
  "geometry": {"coordinates":[0.1182579994,41.7180862427],"type":"Point"}
}