{
  "type": "Feature",
  "properties": {
    "iso:country":"ES",
    "sg:address":"Avda Agustin Plana, 11",
    "sg:city":"Calanda",
    "sg:orig_category":"Alimentaci\u00d3n General (al Por Menor)",
    "sg:phone":"+34 978 84 61 78",
    "sg:postcode":"44570",
    "sg:province":"Teruel",
    "wof:name":"Maria Del Carmen Gasque S.l.",
    "wof:placetype":"venue"
},
  "geometry": {"coordinates":[-0.2335779965,40.9394493103],"type":"Point"}
}