{
  "type": "Feature",
  "properties": {
    "addr:full":"Plaz Sagrado Corazon De Jesus, 2 Fontiveros \u00c1vila 05310",
    "addr:housenumber":"2",
    "addr:postcode":"05310",
    "addr:street":"Jesus;A\u0301Vila",
    "iso:country":"ES",
    "sg:address":"Plaz Sagrado Corazon De Jesus, 2",
    "sg:city":"Fontiveros",
    "sg:orig_category":"Centros De Coordinaci\u00d3n",
    "sg:phone":"+34 920 24 51 76",
    "sg:postcode":"05310",
    "sg:province":"\u00c1vila",
    "wof:name":"Adanero Martin Florencio",
    "wof:placetype":"venue"
},
  "geometry": {"coordinates":[-4.96626091,40.9226303101],"type":"Point"}
}