{
  "type": "Feature",
  "properties": {
    "addr:full":"Calle de San Pedro, 57 Antequera M\u00e1laga 29200",
    "addr:housenumber":"57",
    "addr:postcode":"29200",
    "addr:street":"Calle De San Pedro",
    "iso:country":"ES",
    "sg:address":"Calle de San Pedro, 57",
    "sg:city":"Antequera",
    "sg:orig_category":"Formaci\u00d3n Continuada (variada)",
    "sg:phone":"+34 952 84 47 60",
    "sg:postcode":"29200",
    "sg:province":"M\u00e1laga",
    "wof:name":"Garcia De La Vega Manuel",
    "wof:placetype":"venue"
},
  "geometry": {"coordinates":[-4.5555357933,37.0203895569],"type":"Point"}
}