{
  "type": "Feature",
  "properties": {
    "iso:country":"ES",
    "sg:address":"Carretera Mas Del Jutge, 12",
    "sg:city":"Torrent",
    "sg:orig_category":"Inform\u00c1tica, Ofim\u00c1tica (estudios, Asesor\u00cda, Ingenier\u00cda, Formaci\u00d3n)",
    "sg:phone":"+34 961 55 96 67",
    "sg:postcode":"46900",
    "sg:province":"Valencia",
    "wof:name":"Tecnologias Y Comunicaciones Integrales Levante, S.l.",
    "wof:placetype":"venue"
},
  "geometry": {"coordinates":[-0.4805260003,39.4386978149],"type":"Point"}
}