{
  "type": "Feature",
  "properties": {
    "addr:full":"C/ Pere Joan Perpinya, 17 Elche Alicante 03204",
    "addr:housenumber":"17",
    "addr:postcode":"03204",
    "addr:street":"C / Pere Joan Perpinya",
    "iso:country":"ES",
    "sg:address":"C/ Pere Joan Perpinya, 17",
    "sg:city":"Elche",
    "sg:orig_category":"Peluquer\u00cdas, Peluquer\u00cda Mixta",
    "sg:phone":"+34 966 63 13 62",
    "sg:postcode":"03204",
    "sg:province":"Alicante",
    "wof:name":"Miralles Anton Mariana",
    "wof:placetype":"venue"
},
  "geometry": {"coordinates":[-0.7046579719,38.2585372925],"type":"Point"}
}