{
  "type": "Feature",
  "properties": {
    "iso:country":"ES",
    "sg:address":"Rond General Mitre, 261",
    "sg:city":"Barcelona",
    "sg:orig_category":"Promotores Constructores",
    "sg:phone":"+34 934 15 98 27",
    "sg:postcode":"08023",
    "sg:province":"Barcelona",
    "wof:name":"Bt Espa\u00d1a Compa\u00d1ia De Servicios Globales De Telecomunicaciones S.a.u.",
    "wof:placetype":"venue"
},
  "geometry": {"coordinates":[2.1487390995,41.4063148499],"type":"Point"}
}