{
  "type": "Feature",
  "properties": {
    "addr:full":"Avda Menendez Pelayo, 250 Linea De La Concepcion C\u00e1diz 11300",
    "addr:housenumber":"250",
    "addr:postcode":"11300",
    "addr:street":"Avda Menendez Pelayo;Ca\u0301Diz",
    "iso:country":"ES",
    "sg:address":"Avda Menendez Pelayo, 250",
    "sg:city":"Linea De La Concepcion",
    "sg:orig_category":"Farmacias",
    "sg:phone":"+34 956 17 29 38",
    "sg:postcode":"11300",
    "sg:province":"C\u00e1diz",
    "wof:name":"Cadenas Beltran Agustin",
    "wof:placetype":"venue"
},
  "geometry": {"coordinates":[-5.3379712105,36.1723213196],"type":"Point"}
}