{
  "type": "Feature",
  "properties": {
    "iso:country":"ES",
    "sg:address":"Plaz De Santa Maria, 10",
    "sg:city":"Benavente",
    "sg:orig_category":"Art\u00cdculos De Decoraci\u00d3n",
    "sg:phone":"+34 980 63 02 39",
    "sg:postcode":"49600",
    "sg:province":"Zamora",
    "wof:name":"Manuel Cubo E Hijo S. L.",
    "wof:placetype":"venue"
},
  "geometry": {"coordinates":[-5.6867961884,42.0085144043],"type":"Point"}
}