{
  "type": "Feature",
  "properties": {
    "iso:country":"ES",
    "sg:address":"Calle de Jose Abascal, 44",
    "sg:city":"Madrid",
    "sg:orig_category":"Ingeniero",
    "sg:phone":"+34 913 95 22 17",
    "sg:postcode":"28003",
    "sg:province":"Madrid",
    "sg:website":"www.analysys.com",
    "wof:name":"Analysys Limited S.l.",
    "wof:placetype":"venue"
},
  "geometry": {"coordinates":[-3.694362402,40.4381980896],"type":"Point"}
}