{
  "type": "Feature",
  "properties": {
    "addr:full":"Calle de Tres De Abril, 1 Bollullos Par Condado Huelva 21710",
    "addr:housenumber":"1",
    "addr:postcode":"21710",
    "addr:street":"Calle De Tres De Abril",
    "iso:country":"ES",
    "sg:address":"Calle de Tres De Abril, 1",
    "sg:city":"Bollullos Par Condado",
    "sg:orig_category":"Aceites Y Grasas Alimentarias (fabricaci\u00d3n, Al Por Mayor)",
    "sg:phone":"+34 959 41 07 02",
    "sg:postcode":"21710",
    "sg:province":"Huelva",
    "wof:name":"Almazara Cooperativa San Isidro",
    "wof:placetype":"venue"
},
  "geometry": {"coordinates":[-6.5249757767,37.3204689026],"type":"Point"}
}