{
  "type": "Feature",
  "properties": {
    "iso:country":"ES",
    "sg:address":"Pl Coronacion, 1",
    "sg:city":"Estella",
    "sg:orig_category":"Conservatorios",
    "sg:phone":"+34 948 55 44 08",
    "sg:postcode":"31200",
    "sg:province":"Navarra",
    "wof:name":"Ayuntamiento De Estella",
    "wof:placetype":"venue"
},
  "geometry": {"coordinates":[-2.0326929092,42.6698875427],"type":"Point"}
}