{
  "type": "Feature",
  "properties": {
    "addr:full":"Carrer de Amigo, 69 Barcelona Barcelona 08021",
    "addr:housenumber":"69",
    "addr:postcode":"08021",
    "addr:street":"Carrer De Amigo",
    "iso:country":"ES",
    "sg:address":"Carrer de Amigo, 69",
    "sg:city":"Barcelona",
    "sg:orig_category":"Mec\u00c1nico Del Autom\u00d3vil",
    "sg:phone":"+34 932 09 13 20",
    "sg:postcode":"08021",
    "sg:province":"Barcelona",
    "wof:name":"Taller Amigo 2002 S.l.",
    "wof:placetype":"venue"
},
  "geometry": {"coordinates":[2.1423211098,41.3967933655],"type":"Point"}
}