{
  "type": "Feature",
  "properties": {
    "addr:full":"Ctra Madrid N-iv (extrarradio), 102 Alcolea C\u00f3rdoba 14610",
    "addr:housenumber":"102",
    "addr:postcode":"14610",
    "addr:street":"Ctra Madrid N-Iv Extrarradio;Co\u0301Rdoba",
    "iso:country":"ES",
    "sg:address":"Ctra Madrid N-iv (extrarradio), 102",
    "sg:city":"Alcolea",
    "sg:orig_category":"Cajas De Ahorro",
    "sg:phone":"+34 957 32 00 93",
    "sg:postcode":"14610",
    "sg:province":"C\u00f3rdoba",
    "wof:name":"Caja De Ahorros Y Monte De Piedad De Cordoba",
    "wof:placetype":"venue"
},
  "geometry": {"coordinates":[-4.6694087982,37.9339485168],"type":"Point"}
}