{
  "type": "Feature",
  "properties": {
    "addr:full":"Calle de Carasol, 8 Autol La Rioja 26560",
    "addr:housenumber":"8",
    "addr:postcode":"26560",
    "addr:street":"Calle De Carasol;Autol;Rioja",
    "iso:country":"ES",
    "sg:address":"Calle de Carasol, 8",
    "sg:city":"Autol",
    "sg:orig_category":"Asociaciones, Organismos Culturales Y Socioeducativos",
    "sg:phone":"+34 941 39 05 49",
    "sg:postcode":"26560",
    "sg:province":"La Rioja",
    "wof:name":"Ayuntamiento De Autol",
    "wof:placetype":"venue"
},
  "geometry": {"coordinates":[-2.0065379143,42.2134208679],"type":"Point"}
}