{
  "type": "Feature",
  "properties": {
    "iso:country":"ES",
    "sg:address":"Calle de Talco, 33",
    "sg:city":"Madrid",
    "sg:orig_category":"Farmacias",
    "sg:phone":"+34 917 97 13 49",
    "sg:postcode":"28021",
    "sg:province":"Madrid",
    "wof:name":"Arnaud Lopez-cepero Rosario",
    "wof:placetype":"venue"
},
  "geometry": {"coordinates":[-3.714640379,40.3469543457],"type":"Point"}
}