{
  "type": "Feature",
  "properties": {
    "addr:full":"Calle de Vendimia (de La), 28 Velilla S.antonio Madrid 28891",
    "addr:housenumber":"28",
    "addr:postcode":"28891",
    "addr:street":"Calle De Vendimia De La",
    "iso:country":"ES",
    "sg:address":"Calle de Vendimia (de La), 28",
    "sg:city":"Velilla S.antonio",
    "sg:orig_category":"Almacenes Frigor\u00cdficos",
    "sg:phone":"+34 916 55 13 57",
    "sg:postcode":"28891",
    "sg:province":"Madrid",
    "wof:name":"Difusion Y Climatizacion Y Refrigeracion S.l.",
    "wof:placetype":"venue"
},
  "geometry": {"coordinates":[-3.4822289944,40.3739624023],"type":"Point"}
}