{
  "type": "Feature",
  "properties": {
    "iso:country":"ES",
    "sg:address":"Poli Poliviso, 1",
    "sg:city":"Viso Del Alcor",
    "sg:orig_category":"Fabricaci\u00d3n De Muebles",
    "sg:phone":"+34 955 74 08 70",
    "sg:postcode":"41520",
    "sg:province":"Sevilla",
    "wof:name":"Carpinteria De Madera Reami S.l",
    "wof:placetype":"venue"
},
  "geometry": {"coordinates":[-5.7224740982,37.3872108459],"type":"Point"}
}