{
  "type": "Feature",
  "properties": {
    "iso:country":"ES",
    "sg:address":"Calle de Bolivia, 5",
    "sg:city":"Coslada",
    "sg:orig_category":"Molduras, Junquillos, Listones Y Molduras Perforadas",
    "sg:phone":"+34 916 73 44 44",
    "sg:postcode":"28820",
    "sg:province":"Madrid",
    "wof:name":"Pulido Lopez Angel",
    "wof:placetype":"venue"
},
  "geometry": {"coordinates":[-3.5538744926,40.4250793457],"type":"Point"}
}