{
  "type": "Feature",
  "properties": {
    "addr:full":"Pla\u00c7 Castell, 3 Alcasser Valencia 46290",
    "addr:housenumber":"3",
    "addr:postcode":"46290",
    "addr:street":"Castell",
    "iso:country":"ES",
    "sg:address":"Pla\u00c7 Castell, 3",
    "sg:city":"Alcasser",
    "sg:orig_category":"Clases De M\u00dasica Y Canto",
    "sg:phone":"+34 961 23 09 28",
    "sg:postcode":"46290",
    "sg:province":"Valencia",
    "wof:name":"Sociedad Musical Santa Cecilia",
    "wof:placetype":"venue"
},
  "geometry": {"coordinates":[-0.4453490078,39.3651695251],"type":"Point"}
}