{
  "type": "Feature",
  "properties": {
    "addr:full":"Calle de Zanja, S/n Vera Almer\u00eda 04620",
    "addr:housenumber":"s / n;almeri\u0301a",
    "addr:postcode":"04620",
    "addr:street":"Calle De Zanja",
    "iso:country":"ES",
    "sg:address":"Calle de Zanja, S/n",
    "sg:city":"Vera",
    "sg:orig_category":"Supermercados Y Hipermercados",
    "sg:phone":"+34 950 39 14 63",
    "sg:postcode":"04620",
    "sg:province":"Almer\u00eda",
    "wof:name":"Jose Espinosa Pomares S. A.",
    "wof:placetype":"venue"
},
  "geometry": {"coordinates":[-1.8710540533,37.2487602234],"type":"Point"}
}