{
  "type": "Feature",
  "properties": {
    "addr:full":"Calle de San Martin, 29 Getxo Vizcaya 48990",
    "addr:housenumber":"29",
    "addr:postcode":"48990",
    "addr:street":"Calle De San Martin",
    "iso:country":"ES",
    "sg:address":"Calle de San Martin, 29",
    "sg:city":"Getxo",
    "sg:orig_category":"Fabricaci\u00d3n, Venta De Cuadros, Accesorios Para Enmarcar",
    "sg:phone":"+34 944 60 65 49",
    "sg:postcode":"48990",
    "sg:province":"Vizcaya",
    "wof:name":"Eloy Perez Ramos",
    "wof:placetype":"venue"
},
  "geometry": {"coordinates":[-3.0124499798,43.3553085327],"type":"Point"}
}