{
  "type": "Feature",
  "properties": {
    "addr:full":"Rua Coru\u00d1a, 17 Solana La Coru\u00f1a 15407",
    "addr:housenumber":"17",
    "addr:postcode":"15407",
    "addr:street":"Rua Corun\u0303A;Corun\u0303A",
    "iso:country":"ES",
    "sg:address":"Rua Coru\u00d1a, 17",
    "sg:city":"Solana",
    "sg:orig_category":"Pescader\u00cdas (al Por Menor)",
    "sg:phone":"+34 981 38 25 33",
    "sg:postcode":"15407",
    "sg:province":"La Coru\u00f1a",
    "wof:name":"Perez Perez Vicente",
    "wof:placetype":"venue"
},
  "geometry": {"coordinates":[-8.1969175339,43.5052642822],"type":"Point"}
}