{
  "type": "Feature",
  "properties": {
    "addr:full":"Calle de Olivon, 19 Durcal Granada 18650",
    "addr:housenumber":"19",
    "addr:postcode":"18650",
    "addr:street":"Calle De Olivon",
    "iso:country":"ES",
    "sg:address":"Calle de Olivon, 19",
    "sg:city":"Durcal",
    "sg:orig_category":"Ense\u00d1anza: Comercio, Gesti\u00d3n, Inform\u00c1tica",
    "sg:phone":"+34 958 79 70 04",
    "sg:postcode":"18650",
    "sg:province":"Granada",
    "sg:website":"www.cemahina.com",
    "wof:name":"Centro De Estudios Mahina C.b.",
    "wof:placetype":"venue"
},
  "geometry": {"coordinates":[-3.5697960854,36.9874153137],"type":"Point"}
}