{
  "type": "Feature",
  "properties": {
    "addr:full":"Ctra Juncal (el), S/n Ugarte Vizcaya 48510",
    "addr:postcode":"48510",
    "addr:street":"Ctra Juncal El S / N Ugarte",
    "iso:country":"ES",
    "sg:address":"Ctra Juncal (el), S/n",
    "sg:city":"Ugarte",
    "sg:orig_category":"Restaurantes",
    "sg:phone":"+34 944 78 12 29",
    "sg:postcode":"48510",
    "sg:province":"Vizcaya",
    "wof:name":"Janindu S.l.",
    "wof:placetype":"venue"
},
  "geometry": {"coordinates":[-3.0369338989,43.3047294617],"type":"Point"}
}