{
  "type": "Feature",
  "properties": {
    "iso:country":"ES",
    "sg:address":"C/ Muralla, 28",
    "sg:city":"Banyoles",
    "sg:orig_category":"Organizaciones Internacionales",
    "sg:phone":"+34 972 58 30 55",
    "sg:postcode":"17820",
    "sg:province":"Girona",
    "wof:name":"Caritas Arxiprestat De Banyoles",
    "wof:placetype":"venue"
},
  "geometry": {"coordinates":[2.7678050995,42.1181602478],"type":"Point"}
}