{
  "type": "Feature",
  "properties": {
    "addr:full":"Cruceiro De Seira, 2 Antequeira La Coru\u00f1a 15911",
    "addr:housenumber":"2",
    "addr:postcode":"15911",
    "addr:street":"Seira;La Corun\u0303A",
    "iso:country":"ES",
    "sg:address":"Cruceiro De Seira, 2",
    "sg:city":"Antequeira",
    "sg:orig_category":"Material Y Suministros Para Fabricar Y Transformar El Papel Y El Cart\u00d3n",
    "sg:phone":"+34 981 80 42 16",
    "sg:postcode":"15911",
    "sg:province":"La Coru\u00f1a",
    "wof:name":"Majuve S.l.",
    "wof:placetype":"venue"
},
  "geometry": {"coordinates":[-8.6919794083,42.7621002197],"type":"Point"}
}