{
  "type": "Feature",
  "properties": {
    "iso:country":"ES",
    "sg:address":"Calle de Cartaya, 49",
    "sg:city":"S. Bartolome Torre",
    "sg:orig_category":"Confecci\u00d3n De Trajes Para Se\u00d1oras",
    "sg:phone":"+34 959 38 62 05",
    "sg:postcode":"21510",
    "sg:province":"Huelva",
    "wof:name":"Limon Carrasco Alonso",
    "wof:placetype":"venue"
},
  "geometry": {"coordinates":[-7.1068372726,37.4440994263],"type":"Point"}
}