{
  "type": "Feature",
  "properties": {
    "iso:country":"ES",
    "sg:address":"Carrer de Comte D'urgell, 272",
    "sg:city":"Barcelona",
    "sg:orig_category":"Ingenier\u00cda, Centros De Estudios (diversos)",
    "sg:phone":"+34 933 21 11 29",
    "sg:postcode":"08036",
    "sg:province":"Barcelona",
    "wof:name":"Rahola Casagran Luis",
    "wof:placetype":"venue"
},
  "geometry": {"coordinates":[2.1465158463,41.391242981],"type":"Point"}
}