{
  "type": "Feature",
  "properties": {
    "addr:full":"Av. Fisterra, 85 Laracha La Coru\u00f1a 15145",
    "addr:housenumber":"85",
    "addr:postcode":"15145",
    "addr:street":"Av. Fisterra;La Corun\u0303A",
    "iso:country":"ES",
    "sg:address":"Av. Fisterra, 85",
    "sg:city":"Laracha",
    "sg:orig_category":"Parafarmacias",
    "sg:phone":"+34 981 64 30 51",
    "sg:postcode":"15145",
    "sg:province":"La Coru\u00f1a",
    "wof:name":"Dubra Suarez Maria Del Carmen",
    "wof:placetype":"venue"
},
  "geometry": {"coordinates":[-8.5799293518,43.247959137],"type":"Point"}
}