{
  "type": "Feature",
  "properties": {
    "addr:full":"Rua Hospitali\u00d1o (do), 2 Santiago De Compostela A Coru\u00f1a 15704",
    "addr:housenumber":"2",
    "addr:postcode":"15704",
    "addr:street":"Rua Hospitalin\u0303O Do;Corun\u0303A",
    "iso:country":"ES",
    "sg:address":"Rua Hospitali\u00d1o (do), 2",
    "sg:city":"Santiago De Compostela",
    "sg:orig_category":"M\u00c9dicos: Pediatr\u00cda. Enfermedades De Los Ni\u00d1os",
    "sg:phone":"+34 981 58 12 30",
    "sg:postcode":"15704",
    "sg:province":"A Coru\u00f1a",
    "wof:name":"Suarez Camino Jesus",
    "wof:placetype":"venue"
},
  "geometry": {"coordinates":[-8.5422449112,42.8832130432],"type":"Point"}
}