{
  "type": "Feature",
  "properties": {
    "addr:full":"Pl Bonanova, 6 Barcelona Barcelona 08022",
    "addr:housenumber":"6",
    "addr:postcode":"08022",
    "addr:street":"Pl Bonanova",
    "iso:country":"ES",
    "sg:address":"Pl Bonanova, 6",
    "sg:city":"Barcelona",
    "sg:orig_category":"Caf\u00c9s, Bares, Cervecer\u00cdas",
    "sg:phone":"+34 934 17 11 31",
    "sg:postcode":"08022",
    "sg:province":"Barcelona",
    "wof:name":"Martinez Puig Juan",
    "wof:placetype":"venue"
},
  "geometry": {"coordinates":[2.1342020035,41.4066200256],"type":"Point"}
}