{
  "type": "Feature",
  "properties": {
    "addr:full":"Cmno Bajo De Huetor, 49 Granada Granada 18008",
    "addr:housenumber":"49",
    "addr:postcode":"18008",
    "addr:street":"Cmno Bajo De Huetor",
    "iso:country":"ES",
    "sg:address":"Cmno Bajo De Huetor, 49",
    "sg:city":"Granada",
    "sg:orig_category":"Internados & Ense\u00d1anza Privada",
    "sg:phone":"+34 958 81 02 63",
    "sg:postcode":"18008",
    "sg:province":"Granada",
    "wof:name":"Esclavas Divina Infantita",
    "wof:placetype":"venue"
},
  "geometry": {"coordinates":[-3.5863919258,37.1569747925],"type":"Point"}
}