{
  "type": "Feature",
  "properties": {
    "iso:country":"ES",
    "sg:address":"Av Joan Carles I, 4",
    "sg:city":"Blanes",
    "sg:orig_category":"Farmacias",
    "sg:phone":"+34 972 33 19 78",
    "sg:postcode":"17300",
    "sg:province":"Girona",
    "wof:name":"Falguera Sacrest Rafael",
    "wof:placetype":"venue"
},
  "geometry": {"coordinates":[2.7920899391,41.6800422668],"type":"Point"}
}