{
  "type": "Feature",
  "properties": {
    "iso:country":"ES",
    "sg:address":"Calle de Lepanto, 22",
    "sg:city":"Benidorm",
    "sg:orig_category":"Electrodom\u00c9sticos (al Por Menor)",
    "sg:phone":"+34 966 80 32 21",
    "sg:postcode":"03500",
    "sg:province":"Alicante",
    "wof:name":"Devesa-sol S.l.",
    "wof:placetype":"venue"
},
  "geometry": {"coordinates":[-0.1152350008,38.5382766724],"type":"Point"}
}