{
  "type": "Feature",
  "properties": {
    "iso:country":"ES",
    "sg:address":"Calle de San Norberto, 18",
    "sg:city":"Madrid",
    "sg:orig_category":"Maquinaria Para Industrias Diversas",
    "sg:phone":"+34 917 23 04 13",
    "sg:postcode":"28021",
    "sg:province":"Madrid",
    "wof:name":"Nueva Azar S.l.",
    "wof:placetype":"venue"
},
  "geometry": {"coordinates":[-3.6963729858,40.3408088684],"type":"Point"}
}