{
  "type": "Feature",
  "properties": {
    "iso:country":"ES",
    "sg:address":"Calle de Eras Altas, S/n",
    "sg:city":"Ejea De Los Caballeros",
    "sg:orig_category":"Empresarios",
    "sg:phone":"+34 976 66 06 37",
    "sg:postcode":"50600",
    "sg:province":"Zaragoza",
    "wof:name":"Gallego Villanua Carlos",
    "wof:placetype":"venue"
},
  "geometry": {"coordinates":[-1.13539505,42.1300735474],"type":"Point"}
}