{
  "type": "Feature",
  "properties": {
    "addr:full":"Nueva, 11 Agoitz Navarra 31430",
    "addr:housenumber":"11",
    "addr:postcode":"31430",
    "addr:street":"Nueva",
    "iso:country":"ES",
    "sg:address":"Nueva, 11",
    "sg:city":"Agoitz",
    "sg:orig_category":"Farmacias",
    "sg:phone":"+34 948 33 40 67",
    "sg:postcode":"31430",
    "sg:province":"Navarra",
    "wof:name":"Farmacia Bados-calahorra C.b.",
    "wof:placetype":"venue"
},
  "geometry": {"coordinates":[-1.3681540489,42.785533905],"type":"Point"}
}