{
  "type": "Feature",
  "properties": {
    "iso:country":"ES",
    "sg:address":"Calle de Rio Sil, 6",
    "sg:city":"Villablino",
    "sg:orig_category":"Albergues",
    "sg:phone":"+34 987 47 00 76",
    "sg:postcode":"24100",
    "sg:province":"Le\u00f3n",
    "wof:name":"Oltra Soler Maria Jose",
    "wof:placetype":"venue"
},
  "geometry": {"coordinates":[-6.3170537949,42.9384651184],"type":"Point"}
}