{
  "type": "Feature",
  "properties": {
    "iso:country":"ES",
    "sg:address":"Calle de San Francisco, 49",
    "sg:city":"Carmona",
    "sg:orig_category":"Molduras, Junquillos, Listones Y Molduras Perforadas",
    "sg:phone":"+34 954 14 09 54",
    "sg:postcode":"41410",
    "sg:province":"Sevilla",
    "wof:name":"Aroca Jimenez Juan",
    "wof:placetype":"venue"
},
  "geometry": {"coordinates":[-5.6507444382,37.472366333],"type":"Point"}
}