{
  "type": "Feature",
  "properties": {
    "addr:full":"Cra. Olot, 6 Manlleu Barcelona 08560",
    "addr:housenumber":"6",
    "addr:postcode":"08560",
    "addr:street":"Cra. Olot",
    "iso:country":"ES",
    "sg:address":"Cra. Olot, 6",
    "sg:city":"Manlleu",
    "sg:orig_category":"Alimentaci\u00d3n General (al Por Mayor)",
    "sg:phone":"+34 938 51 08 54",
    "sg:postcode":"08560",
    "sg:province":"Barcelona",
    "wof:name":"Cooperativa Agraria Comarcal Plana De Vic",
    "wof:placetype":"venue"
},
  "geometry": {"coordinates":[2.2861039639,42.0011444092],"type":"Point"}
}