{
  "type": "Feature",
  "properties": {
    "iso:country":"ES",
    "sg:address":"Calle de Granada, 6",
    "sg:city":"Rute",
    "sg:orig_category":"Iglesia Cat\u00d3lica",
    "sg:phone":"+34 957 53 86 91",
    "sg:postcode":"14960",
    "sg:province":"C\u00f3rdoba",
    "wof:name":"Parroquia De San Francisco",
    "wof:placetype":"venue"
},
  "geometry": {"coordinates":[-4.3706541061,37.3248138428],"type":"Point"}
}