{
  "type": "Feature",
  "properties": {
    "addr:full":"Calle de Iparraguirre, 15 Bilbao Vizcaya 48009",
    "addr:housenumber":"15",
    "addr:postcode":"48009",
    "addr:street":"Calle De Iparraguirre",
    "iso:country":"ES",
    "sg:address":"Calle de Iparraguirre, 15",
    "sg:city":"Bilbao",
    "sg:orig_category":"Florister\u00cdas",
    "sg:phone":"+34 944 24 40 66",
    "sg:postcode":"48009",
    "sg:province":"Vizcaya",
    "wof:name":"Saez Krais Maria Pilar",
    "wof:placetype":"venue"
},
  "geometry": {"coordinates":[-2.9354200363,43.2652015686],"type":"Point"}
}