{
  "type": "Feature",
  "properties": {
    "addr:full":"Ctra. N. 432, Km. 0432,0 Atarfe Granada 18230",
    "addr:postcode":"18230",
    "addr:street":"Ctra. N. 432 Km. 0432,0",
    "iso:country":"ES",
    "sg:address":"Ctra. N. 432, Km. 0432,0",
    "sg:city":"Atarfe",
    "sg:orig_category":"Fabrica De Charcuter\u00cda",
    "sg:phone":"+34 958 43 45 13",
    "sg:postcode":"18230",
    "sg:province":"Granada",
    "wof:name":"Carnes Granada Faig S.l.l.",
    "wof:placetype":"venue"
},
  "geometry": {"coordinates":[-3.6903159618,37.2228775024],"type":"Point"}
}