{
  "type": "Feature",
  "properties": {
    "addr:full":"Calle de Reyes Catolicos, 4 Ejido Almer\u00eda 04700",
    "addr:housenumber":"4",
    "addr:postcode":"04700",
    "addr:street":"Calle De Reyes Catolicos;Almeri\u0301A",
    "iso:country":"ES",
    "sg:address":"Calle de Reyes Catolicos, 4",
    "sg:city":"Ejido",
    "sg:orig_category":"Ense\u00d1anza Variada",
    "sg:phone":"+34 950 48 66 25",
    "sg:postcode":"04700",
    "sg:province":"Almer\u00eda",
    "sg:website":"www.iespana.es/c-e-acme",
    "wof:name":"Villegas Delgado Maria Elena",
    "wof:placetype":"venue"
},
  "geometry": {"coordinates":[-2.8135170937,36.7730979919],"type":"Point"}
}