{
  "type": "Feature",
  "properties": {
    "iso:country":"ES",
    "sg:address":"Calle de Medico Almagro, 6",
    "sg:city":"Almedinilla",
    "sg:orig_category":"Pescader\u00cdas (al Por Menor)",
    "sg:phone":"+34 957 70 31 37",
    "sg:postcode":"14812",
    "sg:province":"C\u00f3rdoba",
    "wof:name":"Calmaestra Castillo Antonio",
    "wof:placetype":"venue"
},
  "geometry": {"coordinates":[-4.0906209946,37.4389533997],"type":"Point"}
}