{
  "type": "Feature",
  "properties": {
    "iso:country":"ES",
    "sg:address":"Calle de Francisco Legorburu De, 2",
    "sg:city":"Aviles",
    "sg:orig_category":"Electrodom\u00c9sticos (al Por Menor)",
    "sg:phone":"+34 985 57 09 53",
    "sg:postcode":"33403",
    "sg:province":"Asturias",
    "wof:name":"Fernandez Fernandez Jose Carlos",
    "wof:placetype":"venue"
},
  "geometry": {"coordinates":[-5.9032578468,43.5381584167],"type":"Point"}
}