{
  "type": "Feature",
  "properties": {
    "iso:country":"ES",
    "sg:address":"Carrer de Joventut, 50",
    "sg:city":"Hospitalet Llobregat",
    "sg:orig_category":"Fabricaci\u00d3n De Muebles",
    "sg:phone":"+34 934 40 06 75",
    "sg:postcode":"08904",
    "sg:province":"Barcelona",
    "wof:name":"Martinez Angosto Marc",
    "wof:placetype":"venue"
},
  "geometry": {"coordinates":[2.1188180447,41.3713111877],"type":"Point"}
}