{
  "type": "Feature",
  "properties": {
    "iso:country":"ES",
    "sg:address":"Calle de Arrabal, 26",
    "sg:city":"Laguna Duero",
    "sg:orig_category":"Reposter\u00cdas",
    "sg:phone":"+34 983 54 24 06",
    "sg:postcode":"47140",
    "sg:province":"Valladolid",
    "wof:name":"Arribas Doncel S.l",
    "wof:placetype":"venue"
},
  "geometry": {"coordinates":[-4.7236909866,41.5813369751],"type":"Point"}
}