{
  "type": "Feature",
  "properties": {
    "iso:country":"ES",
    "sg:address":"Calle de Pintor Velazquez, 2",
    "sg:city":"Do\u00e7a Mencia",
    "sg:orig_category":"Molduras, Junquillos, Listones Y Molduras Perforadas",
    "sg:phone":"+34 957 67 64 98",
    "sg:postcode":"14860",
    "sg:province":"C\u00f3rdoba",
    "wof:name":"Ruiz Flores Juliana",
    "wof:placetype":"venue"
},
  "geometry": {"coordinates":[-4.3576889038,37.5531234741],"type":"Point"}
}