{
  "type": "Feature",
  "properties": {
    "iso:country":"ES",
    "sg:address":"Calle de Moratina La, 20",
    "sg:city":"Grado",
    "sg:orig_category":"Doctores En Medicina",
    "sg:phone":"+34 985 75 19 35",
    "sg:postcode":"33820",
    "sg:province":"Asturias",
    "wof:name":"Arechaga Fernandez Juan Manuel",
    "wof:placetype":"venue"
},
  "geometry": {"coordinates":[-6.0685868263,43.3924751282],"type":"Point"}
}