{
  "type": "Feature",
  "properties": {
    "iso:country":"ES",
    "sg:address":"Carrer de Santander, 30",
    "sg:city":"Barcelona",
    "sg:orig_category":"Mec\u00c1nico Del Autom\u00d3vil",
    "sg:phone":"+34 933 05 28 53",
    "sg:postcode":"08020",
    "sg:province":"Barcelona",
    "wof:name":"Poveda Ruiz Manuel",
    "wof:placetype":"venue"
},
  "geometry": {"coordinates":[2.2011730671,41.426071167],"type":"Point"}
}