{
  "type": "Feature",
  "properties": {
    "addr:full":"Plaz Conde De Elda (del), 13 Aranjuez Madrid 28300",
    "addr:postcode":"28300",
    "iso:country":"ES",
    "sg:address":"Plaz Conde De Elda (del), 13",
    "sg:city":"Aranjuez",
    "sg:orig_category":"\u00d3ptica: Instrumentos (fabricaci\u00d3n)",
    "sg:phone":"+34 918 01 18 49",
    "sg:postcode":"28300",
    "sg:province":"Madrid",
    "wof:name":"Papaseit Sanchez-pascuala Jesus Maria",
    "wof:placetype":"venue"
},
  "geometry": {"coordinates":[-3.5972490311,40.0350074768],"type":"Point"}
}