{
  "type": "Feature",
  "properties": {
    "addr:full":"Avda Roquetas, 94 Roquetas Mar Almer\u00eda 04740",
    "addr:housenumber":"94",
    "addr:postcode":"04740",
    "addr:street":"Avda Roquetas;Mar Almeri\u0301A",
    "iso:country":"ES",
    "sg:address":"Avda Roquetas, 94",
    "sg:city":"Roquetas Mar",
    "sg:orig_category":"Muebles, Minoristas",
    "sg:phone":"+34 950 32 14 39",
    "sg:postcode":"04740",
    "sg:province":"Almer\u00eda",
    "wof:name":"Muebles Pedro Carvajal S.a.",
    "wof:placetype":"venue"
},
  "geometry": {"coordinates":[-2.6124989986,36.7638435364],"type":"Point"}
}