{
  "type": "Feature",
  "properties": {
    "addr:full":"Calle de Flor De Albahaca, 5 Sevilla Sevilla 41020",
    "addr:housenumber":"5",
    "addr:postcode":"41020",
    "addr:street":"Calle De Flor De Albahaca",
    "iso:country":"ES",
    "sg:address":"Calle de Flor De Albahaca, 5",
    "sg:city":"Sevilla",
    "sg:orig_category":"Ropa Para Se\u00d1oras (al Por Menor)",
    "sg:phone":"+34 954 44 26 57",
    "sg:postcode":"41020",
    "sg:province":"Sevilla",
    "wof:name":"Neyra Garcia Julio",
    "wof:placetype":"venue"
},
  "geometry": {"coordinates":[-5.9218392372,37.3967857361],"type":"Point"}
}