{
  "type": "Feature",
  "properties": {
    "addr:full":"Avda Pio Xii, 9 Logro\u00f1o La Rioja 26003",
    "addr:housenumber":"9",
    "addr:postcode":"26003",
    "addr:street":"Avda Pio Xii;Rioja",
    "iso:country":"ES",
    "sg:address":"Avda Pio Xii, 9",
    "sg:city":"Logro\u00f1o",
    "sg:orig_category":"Alimentaci\u00d3n General (al Por Menor)",
    "sg:phone":"+34 941 23 08 89",
    "sg:postcode":"26003",
    "sg:province":"La Rioja",
    "wof:name":"Productos Frescos La Sierra S.a.l.",
    "wof:placetype":"venue"
},
  "geometry": {"coordinates":[-2.4445679188,42.4606208801],"type":"Point"}
}