{
  "type": "Feature",
  "properties": {
    "iso:country":"ES",
    "sg:address":"Plaz Luceros (los), 7",
    "sg:city":"Sevilla",
    "sg:orig_category":"Peluqueros: De Se\u00d1oras",
    "sg:phone":"+34 954 25 56 80",
    "sg:postcode":"41019",
    "sg:province":"Sevilla",
    "wof:name":"Moreno Parrado Cristina",
    "wof:placetype":"venue"
},
  "geometry": {"coordinates":[-5.9262390137,37.4087562561],"type":"Point"}
}