{
  "type": "Feature",
  "properties": {
    "addr:full":"Calle de Canales, 27 Cartagena Murcia 30201",
    "addr:housenumber":"27",
    "addr:postcode":"30201",
    "addr:street":"Calle De Canales",
    "iso:country":"ES",
    "sg:address":"Calle de Canales, 27",
    "sg:city":"Cartagena",
    "sg:orig_category":"Florister\u00cdas",
    "sg:phone":"+34 968 52 53 52",
    "sg:postcode":"30201",
    "sg:province":"Murcia",
    "wof:name":"Aznar Oton Maria Jose",
    "wof:placetype":"venue"
},
  "geometry": {"coordinates":[-0.9877709746,37.6046562195],"type":"Point"}
}