{
  "type": "Feature",
  "properties": {
    "iso:country":"ES",
    "sg:address":"Calle de Trinidad, 122",
    "sg:city":"Castellon",
    "sg:orig_category":"Aparcamientos (infraestructuras, Accesorios)",
    "sg:phone":"+34 964 25 37 79",
    "sg:postcode":"12002",
    "sg:province":"Castell\u00f3n",
    "wof:name":"Sequiol S.a.",
    "wof:placetype":"venue"
},
  "geometry": {"coordinates":[-0.0417400002,39.9835395813],"type":"Point"}
}