{
  "type": "Feature",
  "properties": {
    "addr:full":"Calle de Pamplona, 48 Sevilla Sevilla 41014",
    "addr:housenumber":"48",
    "addr:postcode":"41014",
    "addr:street":"Calle De Pamplona",
    "iso:country":"ES",
    "sg:address":"Calle de Pamplona, 48",
    "sg:city":"Sevilla",
    "sg:orig_category":"Lencer\u00cda Femenina, Corseter\u00cda, Trajes De Ba\u00d1o (al Por Menor)",
    "sg:phone":"+34 954 69 13 42",
    "sg:postcode":"41014",
    "sg:province":"Sevilla",
    "wof:name":"Ruiz Nu\u00f1ez Mercedes",
    "wof:placetype":"venue"
},
  "geometry": {"coordinates":[-5.9668331146,37.3218078613],"type":"Point"}
}