{
  "type": "Feature",
  "properties": {
    "iso:country":"ES",
    "sg:address":"Luga Muelle Ribera, S/n",
    "sg:city":"Santa Cruz De Tenerife",
    "sg:orig_category":"Frutas Y Legumbres Frescas (al Por Mayor)",
    "sg:phone":"+34 922 28 02 00",
    "sg:postcode":"38001",
    "sg:province":"Santa Cruz De Tenerife",
    "wof:name":"Asociacion Provincial De Cosecheros Exportadores De Tomates De Tenerife",
    "wof:placetype":"venue"
},
  "geometry": {"coordinates":[-16.2345638275,28.538942337],"type":"Point"}
}