{
  "type": "Feature",
  "properties": {
    "addr:full":"Calle de Mendez Nu\u00d1ez, 106 Santa Cruz De Tenerife Santa Cruz De Tenerife 38001",
    "addr:housenumber":"106",
    "addr:postcode":"38001",
    "addr:street":"Calle De Mendez Nun\u0303Ez",
    "iso:country":"ES",
    "sg:address":"Calle de Mendez Nu\u00d1ez, 106",
    "sg:city":"Santa Cruz De Tenerife",
    "sg:orig_category":"Arquitectos",
    "sg:phone":"+34 922 29 09 65",
    "sg:postcode":"38001",
    "sg:province":"Santa Cruz De Tenerife",
    "wof:name":"Arricivita Calvet Miguel",
    "wof:placetype":"venue"
},
  "geometry": {"coordinates":[-16.2499465942,28.4745616913],"type":"Point"}
}