{
  "type": "Feature",
  "properties": {
    "iso:country":"ES",
    "sg:address":"Carrer de D'amadeu Paltor, 20",
    "sg:city":"Olesa Montserrat",
    "sg:orig_category":"Platos Preparados Refrigerados (fabricaci\u00d3n, Al Por Mayor)",
    "sg:phone":"+34 937 78 08 56",
    "sg:postcode":"08640",
    "sg:province":"Barcelona",
    "wof:name":"Sola Salinas Yolanda",
    "wof:placetype":"venue"
},
  "geometry": {"coordinates":[1.8365827799,41.5926704407],"type":"Point"}
}