{
  "type": "Feature",
  "properties": {
    "iso:country":"ES",
    "sg:address":"Carrer de Pujada, 28",
    "sg:city":"Can Falguera-turons",
    "sg:orig_category":"Cerrajer\u00cda, Ferrallista",
    "sg:phone":"+34 938 64 53 67",
    "sg:postcode":"08184",
    "sg:province":"Barcelona",
    "wof:name":"Buquets Ferrer Joaquin",
    "wof:placetype":"venue"
},
  "geometry": {"coordinates":[2.1843969822,41.5935897827],"type":"Point"}
}