{
  "type": "Feature",
  "properties": {
    "iso:country":"ES",
    "sg:address":"Carr Dos De Maig, 6",
    "sg:city":"Almenara",
    "sg:orig_category":"Congelados: Productos Alimentarios (al Por Menor)",
    "sg:phone":"+34 962 62 33 09",
    "sg:postcode":"12590",
    "sg:province":"Castell\u00f3n",
    "wof:name":"Josefa Garcia-miguel Y Vicenta Saez Bueso C.b.",
    "wof:placetype":"venue"
},
  "geometry": {"coordinates":[-0.2252819985,39.7522544861],"type":"Point"}
}