{
  "type": "Feature",
  "properties": {
    "iso:country":"ES",
    "sg:address":"Barr Hoya (la), S/n",
    "sg:city":"Lia\u00f1o",
    "sg:orig_category":"Distribuci\u00d3n De Petr\u00d3leo Y Derivados",
    "sg:phone":"+34 942 54 23 79",
    "sg:postcode":"39692",
    "sg:province":"Cantabria",
    "wof:name":"Ferman-lia\u00f1o S.l.",
    "wof:placetype":"venue"
},
  "geometry": {"coordinates":[-3.8402040005,43.3819007874],"type":"Point"}
}