{
  "type": "Feature",
  "properties": {
    "addr:full":"Carrer de Galvani, 120 Terrassa Barcelona 08224",
    "addr:housenumber":"120",
    "addr:postcode":"08224",
    "addr:street":"Carrer De Galvani",
    "iso:country":"ES",
    "sg:address":"Carrer de Galvani, 120",
    "sg:city":"Terrassa",
    "sg:orig_category":"Bisuter\u00cda, Joyer\u00cda, Relojer\u00cda (al Por Menor)",
    "sg:phone":"+34 937 80 99 13",
    "sg:postcode":"08224",
    "sg:province":"Barcelona",
    "wof:name":"Javier Garcia S.l.",
    "wof:placetype":"venue"
},
  "geometry": {"coordinates":[2.0019218922,41.5608863831],"type":"Point"}
}