{
  "type": "Feature",
  "properties": {
    "iso:country":"ES",
    "sg:address":"Calle de Hermanos Moroy, 17",
    "sg:city":"Logro\u00f1o",
    "sg:orig_category":"Lencer\u00cda Femenina, Corseter\u00cda, Trajes De Ba\u00d1o (al Por Menor)",
    "sg:phone":"+34 941 20 70 47",
    "sg:postcode":"26001",
    "sg:province":"La Rioja",
    "wof:name":"Peso  Clara Isabel",
    "wof:placetype":"venue"
},
  "geometry": {"coordinates":[-2.4468259811,42.4659996033],"type":"Point"}
}