{
  "type": "Feature",
  "properties": {
    "addr:full":"Calle de Diego Mu\u00d1oz Torrero, S/n Merida Badajoz 06800",
    "addr:housenumber":"s",
    "addr:postcode":"06800",
    "addr:street":"Calle De Diego Mun\u0303Oz Torrero;/ N",
    "iso:country":"ES",
    "sg:address":"Calle de Diego Mu\u00d1oz Torrero, S/n",
    "sg:city":"Merida",
    "sg:orig_category":"Inmobiliaria (agencias)",
    "sg:phone":"+34 924 38 74 02",
    "sg:postcode":"06800",
    "sg:province":"Badajoz",
    "wof:name":"Comeravi Promociones S.a.",
    "wof:placetype":"venue"
},
  "geometry": {"coordinates":[-6.3336191177,38.9122962952],"type":"Point"}
}