{
  "type": "Feature",
  "properties": {
    "addr:full":"Calle de Especeria, 18 Malaga M\u00e1laga 29005",
    "addr:housenumber":"18",
    "addr:postcode":"29005",
    "addr:street":"Calle De Especeria;Ma\u0301Laga",
    "iso:country":"ES",
    "sg:address":"Calle de Especeria, 18",
    "sg:city":"Malaga",
    "sg:orig_category":"Confecci\u00d3n De Sombreros Y Tocados",
    "sg:phone":"+34 952 21 29 51",
    "sg:postcode":"29005",
    "sg:province":"M\u00e1laga",
    "wof:name":"Lopez Garcia Miguel",
    "wof:placetype":"venue"
},
  "geometry": {"coordinates":[-4.4233493805,36.720916748],"type":"Point"}
}