{
  "type": "Feature",
  "properties": {
    "iso:country":"ES",
    "sg:address":"Cmno Estacion, 8",
    "sg:city":"Utebo",
    "sg:orig_category":"Confecci\u00d3n De Cinturones Y De Tirantes",
    "sg:phone":"+34 976 77 05 53",
    "sg:postcode":"50180",
    "sg:province":"Zaragoza",
    "wof:name":"Aragonesa Del Cinturon S.l.",
    "wof:placetype":"venue"
},
  "geometry": {"coordinates":[-0.9847406745,41.7028388977],"type":"Point"}
}