{
  "type": "Feature",
  "properties": {
    "addr:full":"Plaz Alfonso Xiii De, 2 Donostia-san Sebastian Guip\u00f9zcoa 20008",
    "addr:housenumber":"2",
    "addr:postcode":"20008",
    "addr:street":"Plaz Alfonso Xiii De",
    "iso:country":"ES",
    "sg:address":"Plaz Alfonso Xiii De, 2",
    "sg:city":"Donostia-san Sebastian",
    "sg:orig_category":"Carnicer\u00cdas, Carnicer\u00cdas",
    "sg:phone":"+34 943 31 31 15",
    "sg:postcode":"20008",
    "sg:province":"Guip\u00f9zcoa",
    "wof:name":"Arregi Ostolaza Carlos",
    "wof:placetype":"venue"
},
  "geometry": {"coordinates":[-2.0402700901,43.3095817566],"type":"Point"}
}