{
  "type": "Feature",
  "properties": {
    "iso:country":"ES",
    "sg:address":"Calle de Rio Duero, 8",
    "sg:city":"Mostoles",
    "sg:orig_category":"Poller\u00cda Y Caza (al Por Menor)",
    "sg:phone":"+34 916 45 51 28",
    "sg:postcode":"28935",
    "sg:province":"Madrid",
    "wof:name":"Parra Bravo Victor",
    "wof:placetype":"venue"
},
  "geometry": {"coordinates":[-3.8759739399,40.3153114319],"type":"Point"}
}