{
  "type": "Feature",
  "properties": {
    "iso:country":"ES",
    "sg:address":"Calle de Puerta De Granada, 8",
    "sg:city":"Ubeda",
    "sg:orig_category":"Afilado",
    "sg:phone":"+34 953 75 62 44",
    "sg:postcode":"23400",
    "sg:province":"Ja\u00e9n",
    "wof:name":"Mendoza Cruz Miguel",
    "wof:placetype":"venue"
},
  "geometry": {"coordinates":[-3.3713989258,38.0069198608],"type":"Point"}
}