{
  "type": "Feature",
  "properties": {
    "iso:country":"ES",
    "sg:address":"Plaz Apostoles, 2",
    "sg:city":"Catedral",
    "sg:orig_category":"Locales Y Clases De Danza",
    "sg:phone":"+34 968 21 76 36",
    "sg:postcode":"30001",
    "sg:province":"Murcia",
    "wof:name":"Escuela Superior De Arte Dramatico Y Danza",
    "wof:placetype":"venue"
},
  "geometry": {"coordinates":[-1.1302490234,37.9829597473],"type":"Point"}
}