{
  "type": "Feature",
  "properties": {
    "addr:full":"Calle de Iparragirre, 2 Donostia-san Sebastian Guip\u00f9zcoa 20001",
    "addr:housenumber":"2",
    "addr:postcode":"20001",
    "addr:street":"Calle De Iparragirre",
    "iso:country":"ES",
    "sg:address":"Calle de Iparragirre, 2",
    "sg:city":"Donostia-san Sebastian",
    "sg:orig_category":"Molduras, Junquillos, Listones Y Molduras Perforadas",
    "sg:phone":"+34 943 27 64 70",
    "sg:postcode":"20001",
    "sg:province":"Guip\u00f9zcoa",
    "wof:name":"Medina Domingo Jose Antonio",
    "wof:placetype":"venue"
},
  "geometry": {"coordinates":[-1.9749399424,43.3213577271],"type":"Point"}
}