{
  "type": "Feature",
  "properties": {
    "addr:full":"Puntes (pol Ind), 1 Constanti Tarragona 43120",
    "addr:housenumber":"1",
    "addr:postcode":"43120",
    "addr:street":"Ind",
    "iso:country":"ES",
    "sg:address":"Puntes (pol Ind), 1",
    "sg:city":"Constanti",
    "sg:orig_category":"Mortero Y Material Para Jardines",
    "sg:phone":"+34 977 52 40 05",
    "sg:postcode":"43120",
    "sg:province":"Tarragona",
    "wof:name":"Morteros Tarraco 2001 S.l.",
    "wof:placetype":"venue"
},
  "geometry": {"coordinates":[1.1677199602,41.1648902893],"type":"Point"}
}