{
  "type": "Feature",
  "properties": {
    "addr:full":"Ptge Prim, 30 Barcelona Barcelona 08019",
    "addr:housenumber":"30",
    "addr:postcode":"08019",
    "addr:street":"Ptge Prim",
    "iso:country":"ES",
    "sg:address":"Ptge Prim, 30",
    "sg:city":"Barcelona",
    "sg:orig_category":"Alimentaci\u00d3n General (al Por Menor)",
    "sg:phone":"+34 933 05 52 52",
    "sg:postcode":"08019",
    "sg:province":"Barcelona",
    "wof:name":"Martin Izquierdo Vicente",
    "wof:placetype":"venue"
},
  "geometry": {"coordinates":[2.2161018848,41.4140586853],"type":"Point"}
}