{
  "type": "Feature",
  "properties": {
    "addr:full":"V. Molinos, S/n Navaconcejo C\u00e1ceres 10613",
    "addr:housenumber":"s / n",
    "addr:postcode":"10613",
    "addr:street":"V. Molinos;Ca\u0301Ceres",
    "iso:country":"ES",
    "sg:address":"V. Molinos, S/n",
    "sg:city":"Navaconcejo",
    "sg:orig_category":"Frutas Y Legumbres Frescas (al Por Mayor)",
    "sg:phone":"+34 927 17 31 68",
    "sg:postcode":"10613",
    "sg:province":"C\u00e1ceres",
    "wof:name":"Coop Del Campo De Navaconcejo Scl",
    "wof:placetype":"venue"
},
  "geometry": {"coordinates":[-5.8300590515,40.1774253845],"type":"Point"}
}