{
  "type": "Feature",
  "properties": {
    "iso:country":"ES",
    "sg:address":"Calle de Iglesia, 1",
    "sg:city":"Mozoncillo",
    "sg:orig_category":"Iglesia Cat\u00d3lica",
    "sg:phone":"+34 921 57 72 11",
    "sg:postcode":"40250",
    "sg:province":"Segovia",
    "wof:name":"Obispado Segovia",
    "wof:placetype":"venue"
},
  "geometry": {"coordinates":[-4.1867079735,41.1476974487],"type":"Point"}
}