{
  "type": "Feature",
  "properties": {
    "addr:full":"Sauce, 6 Ponteareas Pontevedra 36860",
    "addr:housenumber":"6",
    "addr:postcode":"36860",
    "addr:street":"Sauce",
    "iso:country":"ES",
    "sg:address":"Sauce, 6",
    "sg:city":"Ponteareas",
    "sg:orig_category":"Porcelana Decorativa",
    "sg:phone":"+34 986 66 02 25",
    "sg:postcode":"36860",
    "sg:province":"Pontevedra",
    "wof:name":"Creaciones Bautista C.b.",
    "wof:placetype":"venue"
},
  "geometry": {"coordinates":[-8.5012226105,42.1726989746],"type":"Point"}
}