{
  "type": "Feature",
  "properties": {
    "addr:full":"Calle de Blanco, 37 Villanueva Alcardete Toledo 45810",
    "addr:housenumber":"37",
    "addr:postcode":"45810",
    "addr:street":"Calle De Blanco",
    "iso:country":"ES",
    "sg:address":"Calle de Blanco, 37",
    "sg:city":"Villanueva Alcardete",
    "sg:orig_category":"Centros Empresariales",
    "sg:phone":"+34 925 16 64 37",
    "sg:postcode":"45810",
    "sg:province":"Toledo",
    "wof:name":"Empregilser S.l.",
    "wof:placetype":"venue"
},
  "geometry": {"coordinates":[-3.0097641945,39.6724433899],"type":"Point"}
}