{
  "type": "Feature",
  "properties": {
    "iso:country":"ES",
    "sg:address":"Avda Gonzalez Besada, 33",
    "sg:city":"Vilanova Arousa",
    "sg:orig_category":"T\u00c9cnicos Veterinarios",
    "sg:phone":"+34 986 56 10 33",
    "sg:postcode":"36620",
    "sg:province":"Pontevedra",
    "wof:name":"Machicote Goth Gustavo",
    "wof:placetype":"venue"
},
  "geometry": {"coordinates":[-8.8267803192,42.5619697571],"type":"Point"}
}