{
  "type": "Feature",
  "properties": {
    "addr:full":"Pol. Industrial, 3 Agramunt Lleida 25310",
    "addr:housenumber":"3",
    "addr:postcode":"25310",
    "addr:street":"Pol. Industrial",
    "iso:country":"ES",
    "sg:address":"Pol. Industrial, 3",
    "sg:city":"Agramunt",
    "sg:orig_category":"Transporte En General",
    "sg:phone":"+34 973 39 25 66",
    "sg:postcode":"25310",
    "sg:province":"Lleida",
    "wof:name":"Ai4 Plataforma Logistica S.l.",
    "wof:placetype":"venue"
},
  "geometry": {"coordinates":[1.0873551369,41.785369873],"type":"Point"}
}