{
  "type": "Feature",
  "properties": {
    "iso:country":"ES",
    "sg:address":"Calle de Bergara, 20",
    "sg:city":"Donostia-san Sebastian",
    "sg:orig_category":"Abogados",
    "sg:phone":"+34 943 42 26 34",
    "sg:postcode":"20005",
    "sg:province":"Guip\u00f9zcoa",
    "wof:name":"I\u00f1igo Abad Etxaniz",
    "wof:placetype":"venue"
},
  "geometry": {"coordinates":[-1.979870677,43.3182907104],"type":"Point"}
}