{
  "type": "Feature",
  "properties": {
    "addr:full":"Avda Alonso Martin, 10 Don Benito Badajoz 06400",
    "addr:housenumber":"10",
    "addr:postcode":"06400",
    "addr:street":"Avda Alonso Martin",
    "iso:country":"ES",
    "sg:address":"Avda Alonso Martin, 10",
    "sg:city":"Don Benito",
    "sg:orig_category":"Molduras, Junquillos, Listones Y Molduras Perforadas",
    "sg:phone":"+34 924 80 12 00",
    "sg:postcode":"06400",
    "sg:province":"Badajoz",
    "wof:name":"Macrotelefonia Division Andalucia S.l.",
    "wof:placetype":"venue"
},
  "geometry": {"coordinates":[-5.8643789291,38.9613304138],"type":"Point"}
}