{
  "type": "Feature",
  "properties": {
    "addr:full":"Calle de Tellez, 27 Madrid Madrid 28007",
    "addr:housenumber":"27",
    "addr:postcode":"madrid;28007",
    "addr:street":"Calle De Tellez",
    "iso:country":"ES",
    "sg:address":"Calle de Tellez, 27",
    "sg:city":"Madrid",
    "sg:orig_category":"Empresas De Carpinter\u00cda",
    "sg:phone":"+34 914 34 10 50",
    "sg:postcode":"28007",
    "sg:province":"Madrid",
    "sg:website":"www.jorkon.com",
    "wof:name":"Jorkon S.l.",
    "wof:placetype":"venue"
},
  "geometry": {"coordinates":[-3.6793990135,40.4023017883],"type":"Point"}
}