{
  "type": "Feature",
  "properties": {
    "addr:full":"Arragua Nuc., S/n Oiartzun Guip\u00f9zcoa 20180",
    "addr:housenumber":"s",
    "addr:postcode":"20180",
    "addr:street":"/ N;Guipu\u0300Zcoa",
    "iso:country":"ES",
    "sg:address":"Arragua Nuc., S/n",
    "sg:city":"Oiartzun",
    "sg:orig_category":"Empresas De Carpinter\u00cda De Madera",
    "sg:phone":"+34 943 49 19 66",
    "sg:postcode":"20180",
    "sg:province":"Guip\u00f9zcoa",
    "wof:name":"Urbieta Hermanos S.l.",
    "wof:placetype":"venue"
},
  "geometry": {"coordinates":[-1.8729389906,43.3085098267],"type":"Point"}
}