{
  "type": "Feature",
  "properties": {
    "addr:full":"Alam Boulevard Del, 14 Donostia-san Sebastian Guip\u00f9zcoa 20003",
    "addr:housenumber":"14",
    "addr:postcode":"20003",
    "addr:street":"Alam Boulevard Del",
    "iso:country":"ES",
    "sg:address":"Alam Boulevard Del, 14",
    "sg:city":"Donostia-san Sebastian",
    "sg:orig_category":"Ense\u00d1anza Variada",
    "sg:phone":"+34 943 42 01 54",
    "sg:postcode":"20003",
    "sg:province":"Guip\u00f9zcoa",
    "wof:name":"Masaje Y Formacion S.l.",
    "wof:placetype":"venue"
},
  "geometry": {"coordinates":[-1.9842859507,43.3224754333],"type":"Point"}
}