{
  "type": "Feature",
  "properties": {
    "iso:country":"ES",
    "sg:address":"Ctra La Magdalena, 31",
    "sg:city":"Guardo",
    "sg:orig_category":"Imprenta",
    "sg:phone":"+34 979 85 06 84",
    "sg:postcode":"34880",
    "sg:province":"Palencia",
    "wof:name":"Graficas Guardo 98 S.l.",
    "wof:placetype":"venue"
},
  "geometry": {"coordinates":[-4.8589601517,42.7856674194],"type":"Point"}
}