{
  "type": "Feature",
  "properties": {
    "addr:full":"Ctra. Calonge, S/n Cala D'or Islas Baleares 07660",
    "addr:housenumber":"s / n",
    "addr:postcode":"07660",
    "addr:street":"Ctra. Calonge",
    "iso:country":"ES",
    "sg:address":"Ctra. Calonge, S/n",
    "sg:city":"Cala D'or",
    "sg:orig_category":"Encuadernaci\u00d3n E Impresi\u00d3n De Folletos",
    "sg:phone":"+34 971 18 10 09",
    "sg:postcode":"07660",
    "sg:province":"Islas Baleares",
    "wof:name":"Goldberger  Kurt",
    "wof:placetype":"venue"
},
  "geometry": {"coordinates":[2.9117100239,39.6136398315],"type":"Point"}
}