{
  "type": "Feature",
  "properties": {
    "iso:country":"ES",
    "sg:address":"Av Diagonal, 354",
    "sg:city":"Barcelona",
    "sg:orig_category":"Centros M\u00c9dicos Y Sociales, Dispensarios",
    "sg:phone":"+34 934 57 17 30",
    "sg:postcode":"08013",
    "sg:province":"Barcelona",
    "wof:name":"Centre Medic Mayo S.l.",
    "wof:placetype":"venue"
},
  "geometry": {"coordinates":[2.1721270084,41.4000205994],"type":"Point"}
}