{
  "type": "Feature",
  "properties": {
    "iso:country":"ES",
    "sg:address":"Plaz Andalucia, 16",
    "sg:city":"Pozo Alcon",
    "sg:orig_category":"Sales (al Por Mayor)",
    "sg:phone":"+34 953 73 86 85",
    "sg:postcode":"23485",
    "sg:province":"Ja\u00e9n",
    "wof:name":"Garcia Sanchez Juan Francisco",
    "wof:placetype":"venue"
},
  "geometry": {"coordinates":[-2.9475662708,37.7189407349],"type":"Point"}
}