{
  "type": "Feature",
  "properties": {
    "iso:country":"ES",
    "sg:address":"Gta Logro\u00d1o, 1",
    "sg:city":"Burgos",
    "sg:orig_category":"Distribuci\u00d3n De Petr\u00d3leo Y Derivados",
    "sg:phone":"+34 947 22 03 55",
    "sg:postcode":"09007",
    "sg:province":"Burgos",
    "wof:name":"Villarce S.l.",
    "wof:placetype":"venue"
},
  "geometry": {"coordinates":[-3.6774671078,42.3487052917],"type":"Point"}
}