{
  "type": "Feature",
  "properties": {
    "iso:country":"ES",
    "sg:address":"Av Puig I Cadafalch, 154",
    "sg:city":"Mataro",
    "sg:orig_category":"Supermercados Y Hipermercados",
    "sg:phone":"+34 937 99 59 54",
    "sg:postcode":"08303",
    "sg:province":"Barcelona",
    "sg:website":"www.capraboacasa.com",
    "wof:name":"Caprabo S.a.",
    "wof:placetype":"venue"
},
  "geometry": {"coordinates":[2.4276649952,41.5403671265],"type":"Point"}
}