{
  "type": "Feature",
  "properties": {
    "iso:country":"ES",
    "sg:address":"Playa Los Alicates, S/n",
    "sg:city":"Elviria",
    "sg:orig_category":"Asilos De Ancianos. Centros Privados",
    "sg:phone":"+34 952 83 34 30",
    "sg:postcode":"29604",
    "sg:province":"M\u00e1laga",
    "wof:name":"Residencia Familiar Para Mayores S.l.",
    "wof:placetype":"venue"
},
  "geometry": {"coordinates":[-4.7747840881,36.4966812134],"type":"Point"}
}