{
  "type": "Feature",
  "properties": {
    "addr:full":"Ctra. Barbate-vejer, S/n Barbate Franco C\u00e1diz 11160",
    "addr:housenumber":"s / n",
    "addr:postcode":"11160",
    "addr:street":"Ctra. Barbate-Vejer",
    "iso:country":"ES",
    "sg:address":"Ctra. Barbate-vejer, S/n",
    "sg:city":"Barbate Franco",
    "sg:orig_category":"Ense\u00d1anza, Formaci\u00d3n Profesional: Aprendizaje",
    "sg:phone":"+34 956 43 14 32",
    "sg:postcode":"11160",
    "sg:province":"C\u00e1diz",
    "wof:name":"Ayuntamiento",
    "wof:placetype":"venue"
},
  "geometry": {"coordinates":[-5.9262189865,36.1924819946],"type":"Point"}
}