{
  "type": "Feature",
  "properties": {
    "iso:country":"ES",
    "sg:address":"Rua Conde De Vallellano, 11",
    "sg:city":"Carballi\u00f1o",
    "sg:orig_category":"Molduras, Junquillos, Listones Y Molduras Perforadas",
    "sg:phone":"+34 988 27 02 23",
    "sg:postcode":"32500",
    "sg:province":"Ourense",
    "wof:name":"Baamonde Viador Jose Benito",
    "wof:placetype":"venue"
},
  "geometry": {"coordinates":[-8.0628862381,42.4484519958],"type":"Point"}
}