{
  "type": "Feature",
  "properties": {
    "iso:country":"ES",
    "sg:address":"Tiendas, 1",
    "sg:city":"Lucena",
    "sg:orig_category":"Ropa Para Ni\u00d1os (al Por Menor)",
    "sg:phone":"+34 957 50 18 63",
    "sg:postcode":"14900",
    "sg:province":"C\u00f3rdoba",
    "wof:name":"Campa\u00f1a Garcia Maria Del Pilar",
    "wof:placetype":"venue"
},
  "geometry": {"coordinates":[-4.4845428467,37.4098014832],"type":"Point"}
}