{
  "type": "Feature",
  "properties": {
    "iso:country":"ES",
    "sg:address":"Calle de Cea Bermudez, 70",
    "sg:city":"Madrid",
    "sg:orig_category":"Asesor\u00cda Fiscal Y Jur\u00cddica",
    "sg:phone":"+34 915 43 73 47",
    "sg:postcode":"28003",
    "sg:province":"Madrid",
    "wof:name":"Garcia Fernandez Gumersindo Luis",
    "wof:placetype":"venue"
},
  "geometry": {"coordinates":[-3.7164416313,40.4392814636],"type":"Point"}
}