{
  "type": "Feature",
  "properties": {
    "addr:full":"Calle de Francisco Catoira, 10 Coru\u00d1a A Coru\u00f1a 15007",
    "addr:housenumber":"10",
    "addr:postcode":"15007",
    "addr:street":"Calle De Francisco Catoira;Corun\u0303A",
    "iso:country":"ES",
    "sg:address":"Calle de Francisco Catoira, 10",
    "sg:city":"Coru\u00d1a",
    "sg:orig_category":"Prot\u00c9sicos Dentales",
    "sg:phone":"+34 981 23 82 58",
    "sg:postcode":"15007",
    "sg:province":"A Coru\u00f1a",
    "wof:name":"Veira Leiras David",
    "wof:placetype":"venue"
},
  "geometry": {"coordinates":[-8.4094600677,43.3545417786],"type":"Point"}
}