{
  "type": "Feature",
  "properties": {
    "iso:country":"ES",
    "sg:address":"Rua Vilar (do), 1",
    "sg:city":"Santiago De Compostela",
    "sg:orig_category":"Bazares, Art\u00cdculos De Limpieza Y De Cocina (al Por Menor)",
    "sg:phone":"+34 981 58 11 64",
    "sg:postcode":"15705",
    "sg:province":"La Coru\u00f1a",
    "wof:name":"Bazar De Villar S.l.",
    "wof:placetype":"venue"
},
  "geometry": {"coordinates":[-8.5440940857,42.8796844482],"type":"Point"}
}