{
  "type": "Feature",
  "properties": {
    "iso:country":"ES",
    "sg:address":"Luga Club Nautico De Sa Rapita, S/n",
    "sg:city":"Rapita",
    "sg:orig_category":"Pr\u00c1ctica De Vela, Navegaci\u00d3n Y Deportes N\u00c1uticos Y Acu\u00c1ticos",
    "sg:phone":"+34 971 64 00 01",
    "sg:postcode":"07639",
    "sg:province":"Islas Baleares",
    "wof:name":"Club Nautico La Rapita",
    "wof:placetype":"venue"
},
  "geometry": {"coordinates":[2.8558709621,39.3647956848],"type":"Point"}
}