{
  "type": "Feature",
  "properties": {
    "addr:full":"Avda Estacion, 2 Albacete Albacete 02001",
    "addr:housenumber":"2",
    "addr:postcode":"02001",
    "addr:street":"Avda Estacion",
    "iso:country":"ES",
    "sg:address":"Avda Estacion, 2",
    "sg:city":"Albacete",
    "sg:orig_category":"Administraciones Regionales, Departamentales Y Locales",
    "sg:phone":"+34 967 24 56 19",
    "sg:postcode":"02001",
    "sg:province":"Albacete",
    "sg:website":"www.viviendajovenclm.com",
    "wof:name":"Junta De Comunidades Castilla-la Mancha",
    "wof:placetype":"venue"
},
  "geometry": {"coordinates":[-1.8511739969,38.9975547791],"type":"Point"}
}