{
  "type": "Feature",
  "properties": {
    "addr:full":"Pl Angels (dels), 1 Montblanc Tarragona 43400",
    "addr:housenumber":"1",
    "addr:postcode":"43400",
    "addr:street":"Dels",
    "iso:country":"ES",
    "sg:address":"Pl Angels (dels), 1",
    "sg:city":"Montblanc",
    "sg:orig_category":"Pensiones Familiares",
    "sg:phone":"+34 977 86 01 73",
    "sg:postcode":"43400",
    "sg:province":"Tarragona",
    "wof:name":"Sanahuja Armengol Pau",
    "wof:placetype":"venue"
},
  "geometry": {"coordinates":[1.1626199484,41.3765945435],"type":"Point"}
}