{
  "type": "Feature",
  "properties": {
    "addr:full":"Calle de Doctor Esquerdo, 6 Madrid Madrid 28028",
    "addr:housenumber":"6",
    "addr:postcode":"28028",
    "addr:street":"Calle De Doctor Esquerdo",
    "iso:country":"ES",
    "sg:address":"Calle de Doctor Esquerdo, 6",
    "sg:city":"Madrid",
    "sg:orig_category":"Juegos Y Juguetes (al Por Menor)",
    "sg:phone":"+34 914 02 96 08",
    "sg:postcode":"28028",
    "sg:province":"Madrid",
    "wof:name":"Arte Nueve S.l.",
    "wof:placetype":"venue"
},
  "geometry": {"coordinates":[-3.6686866283,40.4268531799],"type":"Point"}
}