{
  "type": "Feature",
  "properties": {
    "iso:country":"ES",
    "sg:address":"Calle de Marquesa De Canillejas, 6",
    "sg:city":"Pola De Siero",
    "sg:orig_category":"Partidos Pol\u00cdticos",
    "sg:phone":"+34 985 72 19 08",
    "sg:postcode":"33510",
    "sg:province":"Asturias",
    "wof:name":"Grupo Municipal Partido Popular De Siero",
    "wof:placetype":"venue"
},
  "geometry": {"coordinates":[-5.662279129,43.3923797607],"type":"Point"}
}