{
  "type": "Feature",
  "properties": {
    "iso:country":"ES",
    "sg:address":"Rua Nova, 113",
    "sg:city":"Lugo",
    "sg:orig_category":"Zapatos (al Por Menor)",
    "sg:phone":"+34 982 22 31 41",
    "sg:postcode":"27001",
    "sg:province":"Lugo",
    "wof:name":"Carrelli C.b.",
    "wof:placetype":"venue"
},
  "geometry": {"coordinates":[-7.5603141785,43.0132446289],"type":"Point"}
}