{
  "type": "Feature",
  "properties": {
    "addr:full":"Plaz Paraiso, S/n Laluenga Huesca 22125",
    "addr:postcode":"22125",
    "addr:street":"Plaz Paraiso S / N Laluenga",
    "iso:country":"ES",
    "sg:address":"Plaz Paraiso, S/n",
    "sg:city":"Laluenga",
    "sg:orig_category":"Cajas De Ahorro",
    "sg:phone":"+34 974 30 15 84",
    "sg:postcode":"22125",
    "sg:province":"Huesca",
    "sg:website":"www.ibercaja.es",
    "wof:name":"Caja De Ahorros Y Monte De Piedad De Zaragoza Aragon Y Rioja",
    "wof:placetype":"venue"
},
  "geometry": {"coordinates":[-0.0473840013,42.0053405762],"type":"Point"}
}