{
  "type": "Feature",
  "properties": {
    "iso:country":"ES",
    "sg:address":"Calle de Josefa Valcarcel, 30",
    "sg:city":"Madrid",
    "sg:orig_category":"Ense\u00d1anza, Formaci\u00d3n Profesional: Aprendizaje",
    "sg:phone":"+34 913 20 00 21",
    "sg:postcode":"28027",
    "sg:province":"Madrid",
    "wof:name":"Aeropuertos Espa\u00d1oles Y Navegacion Aerea",
    "wof:placetype":"venue"
},
  "geometry": {"coordinates":[-3.6440870762,40.4492797852],"type":"Point"}
}