{
  "type": "Feature",
  "properties": {
    "iso:country":"ES",
    "sg:address":"Calle de Moreno Nieto, 8",
    "sg:city":"Madrid",
    "sg:orig_category":"Loter\u00cda Y T\u00d3mbola",
    "sg:phone":"+34 913 65 85 74",
    "sg:postcode":"28005",
    "sg:province":"Madrid",
    "wof:name":"Pereda Villasante Jose Luis",
    "wof:placetype":"venue"
},
  "geometry": {"coordinates":[-3.7193069458,40.4121818542],"type":"Point"}
}