{
  "type": "Feature",
  "properties": {
    "addr:full":"Calle de Carmona, S/n Alora M\u00e1laga 29500",
    "addr:postcode":"29500",
    "addr:street":"Calle De Carmona S / N Alora Ma\u0301Laga",
    "iso:country":"ES",
    "sg:address":"Calle de Carmona, S/n",
    "sg:city":"Alora",
    "sg:orig_category":"Empresas De Desmonte",
    "sg:phone":"+34 952 49 72 98",
    "sg:postcode":"29500",
    "sg:province":"M\u00e1laga",
    "wof:name":"Benitez Mancera Antonio",
    "wof:placetype":"venue"
},
  "geometry": {"coordinates":[-4.7067542076,36.8233985901],"type":"Point"}
}