{
  "type": "Feature",
  "properties": {
    "iso:country":"ES",
    "sg:address":"Calle de Carnerillo, 6",
    "sg:city":"Galvez",
    "sg:orig_category":"Agricultores, Agricultores",
    "sg:phone":"+34 925 40 07 87",
    "sg:postcode":"45164",
    "sg:province":"Toledo",
    "sg:website":"www.nugato.com",
    "wof:name":"Grupo De Empresas Hermanos Linares S.l.",
    "wof:placetype":"venue"
},
  "geometry": {"coordinates":[-4.2727718353,39.7009925842],"type":"Point"}
}