{
  "type": "Feature",
  "properties": {
    "iso:country":"ES",
    "sg:address":"Rua Aduana (da), S/n",
    "sg:city":"San Cibrao",
    "sg:orig_category":"Talleres De Corte Y Confecci\u00d3n",
    "sg:phone":"+34 982 59 40 81",
    "sg:postcode":"27890",
    "sg:province":"Lugo",
    "wof:name":"Establecimientos Mosquera S.l.",
    "wof:placetype":"venue"
},
  "geometry": {"coordinates":[-7.4412088394,43.6955184937],"type":"Point"}
}