{
  "type": "Feature",
  "properties": {
    "addr:full":"Calle de Capitan Haya, 50 Madrid Madrid 28020",
    "addr:housenumber":"50",
    "addr:postcode":"madrid;28020",
    "addr:street":"Calle De Capitan Haya",
    "iso:country":"ES",
    "sg:address":"Calle de Capitan Haya, 50",
    "sg:city":"Madrid",
    "sg:orig_category":"Ense\u00d1anza: Comercio, Gesti\u00d3n, Inform\u00c1tica",
    "sg:phone":"+34 915 71 95 55",
    "sg:postcode":"28020",
    "sg:province":"Madrid",
    "wof:name":"Limpiezas Prisa S.l.",
    "wof:placetype":"venue"
},
  "geometry": {"coordinates":[-3.6917755604,40.4615974426],"type":"Point"}
}