{
  "type": "Feature",
  "properties": {
    "addr:full":"Foruen Kalea, 4 Zarautz Guip\u00f9zcoa 20800",
    "addr:housenumber":"4",
    "addr:postcode":"20800",
    "addr:street":"Foruen Kalea;Guipu\u0300Zcoa",
    "iso:country":"ES",
    "sg:address":"Foruen Kalea, 4",
    "sg:city":"Zarautz",
    "sg:orig_category":"Asesor\u00cda Fiscal Y Jur\u00cddica",
    "sg:phone":"+34 943 13 01 04",
    "sg:postcode":"20800",
    "sg:province":"Guip\u00f9zcoa",
    "sg:website":"www.laguntza.com",
    "wof:name":"Gabinete Laguntza, S.l.",
    "wof:placetype":"venue"
},
  "geometry": {"coordinates":[-2.1755940914,43.2847213745],"type":"Point"}
}