{
  "type": "Feature",
  "properties": {
    "iso:country":"ES",
    "sg:address":"Calle de Pizarro, 1",
    "sg:city":"Corralejo",
    "sg:orig_category":"Ropa Para Caballeros (al Por Menor)",
    "sg:phone":"+34 928 86 66 00",
    "sg:postcode":"35660",
    "sg:province":"Las Palmas",
    "wof:name":"Figueroa Padron Juan Francisco",
    "wof:placetype":"venue"
},
  "geometry": {"coordinates":[-13.8697490692,28.7385501862],"type":"Point"}
}