{
  "type": "Feature",
  "properties": {
    "iso:country":"ES",
    "sg:address":"Plaz Sal, S/n",
    "sg:city":"Aldeamayor S. Martin",
    "sg:orig_category":"Maquinaria Para Industrias Diversas",
    "sg:phone":"+34 983 55 80 64",
    "sg:postcode":"47162",
    "sg:province":"Valladolid",
    "wof:name":"Alberto Prieto Fernandez Y Carlos Prieto Salvador Cdad",
    "wof:placetype":"venue"
},
  "geometry": {"coordinates":[-4.7283878326,41.6529464722],"type":"Point"}
}