{
  "type": "Feature",
  "properties": {
    "iso:country":"ES",
    "sg:address":"Calle de General Bravo, 60",
    "sg:city":"Jinamar",
    "sg:orig_category":"Colchones (fabricaci\u00d3n, Al Por Mayor, Al Por Menor)",
    "sg:phone":"+34 928 71 21 73",
    "sg:postcode":"35220",
    "sg:province":"Las Palmas",
    "sg:website":"www.incapol.com",
    "wof:name":"Incapol S.a.",
    "wof:placetype":"venue"
},
  "geometry": {"coordinates":[-15.4140691757,28.0225143433],"type":"Point"}
}