{
  "type": "Feature",
  "properties": {
    "addr:full":"Carrer de Mare De Deu Del Turo, S/n Mas Rampinyo Barcelona 08110",
    "addr:housenumber":"s / n",
    "addr:postcode":"08110",
    "addr:street":"Carrer De Mare De Deu Del Turo",
    "iso:country":"ES",
    "sg:address":"Carrer de Mare De Deu Del Turo, S/n",
    "sg:city":"Mas Rampinyo",
    "sg:orig_category":"Tratamiento De Metales",
    "sg:phone":"+34 935 75 39 94",
    "sg:postcode":"08110",
    "sg:province":"Barcelona",
    "wof:name":"Pulidos Quinto S.cv.",
    "wof:placetype":"venue"
},
  "geometry": {"coordinates":[2.1821498871,41.491985321],"type":"Point"}
}