{
  "type": "Feature",
  "properties": {
    "addr:full":"Barr Camarreal, 52 Pe\u00d1acastillo Cantabria 39011",
    "addr:housenumber":"52",
    "addr:postcode":"39011",
    "addr:street":"Barr Camarreal",
    "iso:country":"ES",
    "sg:address":"Barr Camarreal, 52",
    "sg:city":"Pe\u00d1acastillo",
    "sg:orig_category":"Molduras, Junquillos, Listones Y Molduras Perforadas",
    "sg:phone":"+34 942 33 11 95",
    "sg:postcode":"39011",
    "sg:province":"Cantabria",
    "wof:name":"Ordo\u00f1ez Martinez Manuel",
    "wof:placetype":"venue"
},
  "geometry": {"coordinates":[-3.8599019051,43.445690155],"type":"Point"}
}