{
  "type": "Feature",
  "properties": {
    "iso:country":"ES",
    "sg:address":"Calle de Coso, 66",
    "sg:city":"Zaragoza",
    "sg:orig_category":"M\u00c9dicos: Psiquiatr\u00cda",
    "sg:phone":"+34 976 22 58 47",
    "sg:postcode":"50001",
    "sg:province":"Zaragoza",
    "wof:name":"Perez Camo Valero",
    "wof:placetype":"venue"
},
  "geometry": {"coordinates":[-0.8793470263,41.6516304016],"type":"Point"}
}