{
  "type": "Feature",
  "properties": {
    "iso:country":"ES",
    "sg:address":"Calle de Zabalbide, 26",
    "sg:city":"Bilbao",
    "sg:orig_category":"Ense\u00d1anza Variada",
    "sg:phone":"+34 944 32 04 45",
    "sg:postcode":"48006",
    "sg:province":"Vizcaya",
    "sg:website":"www.urtsintxa.com",
    "wof:name":"Urtxintxa Eskola",
    "wof:placetype":"venue"
},
  "geometry": {"coordinates":[-2.9200539589,43.2551002502],"type":"Point"}
}