{
  "type": "Feature",
  "properties": {
    "addr:full":"Pl Pati Del Castell, 5 Valls Tarragona 43800",
    "addr:postcode":"43800",
    "addr:street":"Pl",
    "iso:country":"ES",
    "sg:address":"Pl Pati Del Castell, 5",
    "sg:city":"Valls",
    "sg:orig_category":"Heladeros",
    "sg:phone":"+34 977 60 05 46",
    "sg:postcode":"43800",
    "sg:province":"Tarragona",
    "wof:name":"Garcia Sirvent David",
    "wof:placetype":"venue"
},
  "geometry": {"coordinates":[1.2506849766,41.2858657837],"type":"Point"}
}