{
  "type": "Feature",
  "properties": {
    "iso:country":"ES",
    "sg:address":"Calle de Jose Ortega Y Gasset, 65",
    "sg:city":"Madrid",
    "sg:orig_category":"Art\u00cdculos De Regalo (al Por Menor)",
    "sg:phone":"+34 914 01 50 53",
    "sg:postcode":"28006",
    "sg:province":"Madrid",
    "wof:name":"Aracil Hernandez David",
    "wof:placetype":"venue"
},
  "geometry": {"coordinates":[-3.6740810871,40.4298706055],"type":"Point"}
}