{
  "type": "Feature",
  "properties": {
    "iso:country":"ES",
    "sg:address":"Calle de Retama (de La), 16",
    "sg:city":"Colmenar Viejo",
    "sg:orig_category":"Inmobiliaria (agencias)",
    "sg:phone":"+34 918 46 12 83",
    "sg:postcode":"28770",
    "sg:province":"Madrid",
    "wof:name":"Alfa Colmenar S.l",
    "wof:placetype":"venue"
},
  "geometry": {"coordinates":[-3.7673778534,40.6610031128],"type":"Point"}
}