{
  "type": "Feature",
  "properties": {
    "addr:full":"C/ Alferez Cosido, 23 Elche Alicante 03201",
    "addr:housenumber":"23",
    "addr:postcode":"03201",
    "addr:street":"C / Alferez Cosido",
    "iso:country":"ES",
    "sg:address":"C/ Alferez Cosido, 23",
    "sg:city":"Elche",
    "sg:orig_category":"Promotores Constructores",
    "sg:phone":"+34 966 66 14 23",
    "sg:postcode":"03201",
    "sg:province":"Alicante",
    "wof:name":"Construcciones Larafa S.l.",
    "wof:placetype":"venue"
},
  "geometry": {"coordinates":[-0.7069299817,38.2656364441],"type":"Point"}
}