{
  "type": "Feature",
  "properties": {
    "addr:full":"Calle de San Juan, 11 Lodosa Navarra 31580",
    "addr:housenumber":"11",
    "addr:postcode":"31580",
    "addr:street":"Calle De San Juan",
    "iso:country":"ES",
    "sg:address":"Calle de San Juan, 11",
    "sg:city":"Lodosa",
    "sg:classifiers":[
        {
            "category":"Autos & Motor Vehicles",
            "subcategory":"Automobile Sales",
            "type":"Retail Goods"
        }
    ],
    "sg:phone":"+34 948 69 36 43",
    "sg:postcode":"31580",
    "sg:province":"Navarra",
    "wof:name":"Auto Escuela Marrodan Ontoria S.l.",
    "wof:placetype":"venue"
},
  "geometry": {"coordinates":[-2.0779519081,42.4230804443],"type":"Point"}
}