{
  "type": "Feature",
  "properties": {
    "addr:full":"Calle de Miraflores (de), 48 Alcobendas Madrid 28100",
    "addr:housenumber":"48",
    "addr:postcode":"28100",
    "addr:street":"Calle De Miraflores De",
    "iso:country":"ES",
    "sg:address":"Calle de Miraflores (de), 48",
    "sg:city":"Alcobendas",
    "sg:orig_category":"Carnicer\u00cdas, Carnicer\u00cdas",
    "sg:phone":"+34 916 53 67 05",
    "sg:postcode":"28100",
    "sg:province":"Madrid",
    "wof:name":"Rivas Gonzalez Juan Antonio",
    "wof:placetype":"venue"
},
  "geometry": {"coordinates":[-3.6386520863,40.5456085205],"type":"Point"}
}