{
  "type": "Feature",
  "properties": {
    "addr:full":"Avgd Serra, 2 Massamagrell Valencia 46130",
    "addr:housenumber":"2",
    "addr:postcode":"46130",
    "addr:street":"Serra",
    "iso:country":"ES",
    "sg:address":"Avgd Serra, 2",
    "sg:city":"Massamagrell",
    "sg:orig_category":"Panader\u00cdas, Panader\u00cdas",
    "sg:phone":"+34 961 44 00 72",
    "sg:postcode":"46130",
    "sg:province":"Valencia",
    "wof:name":"Pa I Dol\u00c7os Valero C.b.",
    "wof:placetype":"venue"
},
  "geometry": {"coordinates":[-0.3422729969,39.5775718689],"type":"Point"}
}