{
  "type": "Feature",
  "properties": {
    "iso:country":"ES",
    "sg:address":"Calle de Toledo, 53",
    "sg:city":"Ciudad Real",
    "sg:orig_category":"Promotores Constructores",
    "sg:phone":"+34 926 25 65 89",
    "sg:postcode":"13003",
    "sg:province":"Ciudad Real",
    "wof:name":"Promociones E Inversiones Inmobiliariarias Del Mediterraneo C.b.",
    "wof:placetype":"venue"
},
  "geometry": {"coordinates":[-3.9280719757,38.9924087524],"type":"Point"}
}