{
  "type": "Feature",
  "properties": {
    "addr:full":"Calle de Cruz Dorada, S/n Dos-torres C\u00f3rdoba 14460",
    "addr:housenumber":"s",
    "addr:postcode":"14460",
    "addr:street":"Calle De Cruz Dorada;/ N Dos-Torres Co\u0301Rdoba",
    "iso:country":"ES",
    "sg:address":"Calle de Cruz Dorada, S/n",
    "sg:city":"Dos-torres",
    "sg:orig_category":"Lecher\u00cdas",
    "sg:phone":"+34 957 13 46 36",
    "sg:postcode":"14460",
    "sg:province":"C\u00f3rdoba",
    "wof:name":"Hoyo Misas Jose",
    "wof:placetype":"venue"
},
  "geometry": {"coordinates":[-4.8993721008,38.4455032349],"type":"Point"}
}