{
  "type": "Feature",
  "properties": {
    "addr:full":"Calle de Carrera, 75 Herrera Duque Badajoz 06670",
    "addr:postcode":"06670",
    "addr:street":"Calle De Carrera 75 Herrera;Badajoz",
    "iso:country":"ES",
    "sg:address":"Calle de Carrera, 75",
    "sg:city":"Herrera Duque",
    "sg:orig_category":"Farmacias",
    "sg:phone":"+34 924 65 03 06",
    "sg:postcode":"06670",
    "sg:province":"Badajoz",
    "wof:name":"Navarrete Perez Remedios",
    "wof:placetype":"venue"
},
  "geometry": {"coordinates":[-5.0507254601,39.1681480408],"type":"Point"}
}