{
  "type": "Feature",
  "properties": {
    "iso:country":"ES",
    "sg:address":"Calle de Corindon, 20",
    "sg:city":"Madrid",
    "sg:orig_category":"Ense\u00d1ante, Direcci\u00d3n",
    "sg:phone":"+34 915 00 15 71",
    "sg:postcode":"28041",
    "sg:province":"Madrid",
    "wof:name":"Actua Eduacion S.l.",
    "wof:placetype":"venue"
},
  "geometry": {"coordinates":[-3.6880948544,40.3676147461],"type":"Point"}
}