{
  "type": "Feature",
  "properties": {
    "iso:country":"ES",
    "sg:address":"Pol Ind La Salina, S/n",
    "sg:city":"Rute",
    "sg:orig_category":"Arenas, Guijarros Y Granulados",
    "sg:phone":"+34 957 53 26 26",
    "sg:postcode":"14960",
    "sg:province":"C\u00f3rdoba",
    "wof:name":"Antonio Matas S.l.",
    "wof:placetype":"venue"
},
  "geometry": {"coordinates":[-4.3770704269,37.3233642578],"type":"Point"}
}