{
  "type": "Feature",
  "properties": {
    "addr:full":"Carrer de Sant Pau, 39 Sabadell Barcelona 08201",
    "addr:housenumber":"39",
    "addr:postcode":"08201",
    "addr:street":"Carrer De Sant Pau",
    "iso:country":"ES",
    "sg:address":"Carrer de Sant Pau, 39",
    "sg:city":"Sabadell",
    "sg:orig_category":"Sales (al Por Mayor)",
    "sg:phone":"+34 937 27 07 94",
    "sg:postcode":"08201",
    "sg:province":"Barcelona",
    "wof:name":"Reynes San Nicolas Isaac",
    "wof:placetype":"venue"
},
  "geometry": {"coordinates":[2.1082549095,41.5448150635],"type":"Point"}
}