{
  "type": "Feature",
  "properties": {
    "iso:country":"ES",
    "sg:address":"Calle de Montpellier, 1",
    "sg:city":"Madrid",
    "sg:orig_category":"Inmobiliaria (agencias)",
    "sg:phone":"+34 913 71 09 03",
    "sg:postcode":"28030",
    "sg:province":"Madrid",
    "wof:name":"Lizard Point And Company S.l.",
    "wof:placetype":"venue"
},
  "geometry": {"coordinates":[-3.6305520535,40.404964447],"type":"Point"}
}