{
  "type": "Feature",
  "properties": {
    "addr:full":"Calle de Gran Via, 47 Salamanca Salamanca 37001",
    "addr:housenumber":"47",
    "addr:postcode":"37001",
    "addr:street":"Calle De Gran Via",
    "iso:country":"ES",
    "sg:address":"Calle de Gran Via, 47",
    "sg:city":"Salamanca",
    "sg:orig_category":"M\u00c9dicos: Psiquiatr\u00cda",
    "sg:phone":"+34 923 27 08 06",
    "sg:postcode":"37001",
    "sg:province":"Salamanca",
    "wof:name":"Ledesma Jimeno Alfonso",
    "wof:placetype":"venue"
},
  "geometry": {"coordinates":[-5.6605191231,40.9651031494],"type":"Point"}
}