{
  "type": "Feature",
  "properties": {
    "addr:full":"Rua Blanco Amor, 19 Vilagarcia Pontevedra 36600",
    "addr:housenumber":"19",
    "addr:postcode":"36600",
    "addr:street":"Rua Blanco Amor",
    "iso:country":"ES",
    "sg:address":"Rua Blanco Amor, 19",
    "sg:city":"Vilagarcia",
    "sg:orig_category":"Asesor\u00cda Sobre Comunicaci\u00d3n De Empresas",
    "sg:phone":"+34 986 50 06 39",
    "sg:postcode":"36600",
    "sg:province":"Pontevedra",
    "wof:name":"Iglesias Rodriguez Eliseo",
    "wof:placetype":"venue"
},
  "geometry": {"coordinates":[-8.7524690628,42.5958480835],"type":"Point"}
}