{
  "type": "Feature",
  "properties": {
    "iso:country":"ES",
    "sg:address":"Carr Sant Antoni, 9",
    "sg:city":"Lleida",
    "sg:orig_category":"Ropa Para Se\u00d1oras (al Por Menor)",
    "sg:phone":"+34 973 26 01 74",
    "sg:postcode":"25002",
    "sg:province":"Lleida",
    "wof:name":"Carmona Sthone S.l.",
    "wof:placetype":"venue"
},
  "geometry": {"coordinates":[0.6230250001,41.6124649048],"type":"Point"}
}