{
  "type": "Feature",
  "properties": {
    "iso:country":"ES",
    "sg:address":"Ctra. Almaden, S/n",
    "sg:city":"Cerro Muriano",
    "sg:orig_category":"Maquinaria Para Industrias Diversas",
    "sg:phone":"+34 957 35 03 42",
    "sg:postcode":"14350",
    "sg:province":"C\u00f3rdoba",
    "wof:name":"Sociedad Metalurgica Hp S.l.",
    "wof:placetype":"venue"
},
  "geometry": {"coordinates":[-4.7704291344,38.0036849976],"type":"Point"}
}