{
  "type": "Feature",
  "properties": {
    "addr:full":"Avda Cabo De Gata, 148 Almeria Almer\u00eda 04007",
    "addr:housenumber":"148",
    "addr:postcode":"04007",
    "addr:street":"Avda Cabo De Gata",
    "iso:country":"ES",
    "sg:address":"Avda Cabo De Gata, 148",
    "sg:city":"Almeria",
    "sg:orig_category":"Carnicer\u00cdas, Carnicer\u00cdas",
    "sg:phone":"+34 950 26 57 52",
    "sg:postcode":"04007",
    "sg:province":"Almer\u00eda",
    "wof:name":"Godoy Molina Antonio",
    "wof:placetype":"venue"
},
  "geometry": {"coordinates":[-2.4501590729,36.8274497986],"type":"Point"}
}