{
  "type": "Feature",
  "properties": {
    "iso:country":"ES",
    "sg:address":"Ctra. La Corta-las Pedreras, S/n",
    "sg:city":"Jerez",
    "sg:orig_category":"Servicios De Telecomunicaciones",
    "sg:phone":"+34 956 23 70 74",
    "sg:postcode":"11406",
    "sg:province":"C\u00e1diz",
    "wof:name":"Jesytel Jerez Sistemas Y Telecomunicaciones S.a.",
    "wof:placetype":"venue"
},
  "geometry": {"coordinates":[-6.1049957275,36.6741828918],"type":"Point"}
}