{
  "type": "Feature",
  "properties": {
    "addr:full":"Avgd Jaume I, 18 Olleria Valencia 46850",
    "addr:housenumber":"18",
    "addr:postcode":"46850",
    "addr:street":"Olleria",
    "iso:country":"ES",
    "sg:address":"Avgd Jaume I, 18",
    "sg:city":"Olleria",
    "sg:orig_category":"Heladeros",
    "sg:phone":"+34 962 20 00 28",
    "sg:postcode":"46850",
    "sg:province":"Valencia",
    "wof:name":"Gelat's L'olleria S.l.",
    "wof:placetype":"venue"
},
  "geometry": {"coordinates":[-0.5478360057,38.9096603394],"type":"Point"}
}