{
  "type": "Feature",
  "properties": {
    "iso:country":"ES",
    "sg:address":"Carrer de Varsovia, 70",
    "sg:city":"Barcelona",
    "sg:orig_category":"Ingenier\u00cda, Centros De Estudios (diversos)",
    "sg:phone":"+34 934 35 73 17",
    "sg:postcode":"08041",
    "sg:province":"Barcelona",
    "wof:name":"Gestion Desarrollo Calidad Y Auditoria S.l.",
    "wof:placetype":"venue"
},
  "geometry": {"coordinates":[2.1748399734,41.4217834473],"type":"Point"}
}