{
  "type": "Feature",
  "properties": {
    "addr:full":"Calle de Cruz Verde, 44 Velez-malaga M\u00e1laga 29700",
    "addr:housenumber":"44",
    "addr:postcode":"29700",
    "addr:street":"Calle De Cruz Verde",
    "iso:country":"ES",
    "sg:address":"Calle de Cruz Verde, 44",
    "sg:city":"Velez-malaga",
    "sg:orig_category":"Agencias Y Agentes Comerciales, Representantes",
    "sg:phone":"+34 952 50 84 03",
    "sg:postcode":"29700",
    "sg:province":"M\u00e1laga",
    "wof:name":"Comunidad De Propietarios Edi. Villaverde",
    "wof:placetype":"venue"
},
  "geometry": {"coordinates":[-4.107653141,36.7859191895],"type":"Point"}
}