{
  "type": "Feature",
  "properties": {
    "iso:country":"ES",
    "sg:address":"Metal, 6",
    "sg:city":"Pepino",
    "sg:orig_category":"Confecci\u00d3n De Trajes Para Se\u00d1oras",
    "sg:phone":"+34 925 70 94 70",
    "sg:postcode":"45638",
    "sg:province":"Toledo",
    "wof:name":"Confecciones Dialjuma S.l.",
    "wof:placetype":"venue"
},
  "geometry": {"coordinates":[-4.8243589401,40.0013694763],"type":"Point"}
}