{
  "type": "Feature",
  "properties": {
    "iso:country":"ES",
    "sg:address":"Pol Ind S Antonio, S/n",
    "sg:city":"Belmez",
    "sg:orig_category":"Chapister\u00cda",
    "sg:phone":"+34 957 57 31 84",
    "sg:postcode":"14240",
    "sg:province":"C\u00f3rdoba",
    "wof:name":"Calvo Gomez Jose Manuel",
    "wof:placetype":"venue"
},
  "geometry": {"coordinates":[-5.2100291252,38.2716331482],"type":"Point"}
}