{
  "type": "Feature",
  "properties": {
    "addr:full":"Calle de Jacinto Anglada, 58 Vera Almer\u00eda 04620",
    "addr:housenumber":"58;almeri\u0301a",
    "addr:postcode":"04620",
    "addr:street":"Calle De Jacinto Anglada",
    "iso:country":"ES",
    "sg:address":"Calle de Jacinto Anglada, 58",
    "sg:city":"Vera",
    "sg:orig_category":"Molinos",
    "sg:phone":"+34 950 39 07 54",
    "sg:postcode":"04620",
    "sg:province":"Almer\u00eda",
    "wof:name":"Gimenez Alonso Ana",
    "wof:placetype":"venue"
},
  "geometry": {"coordinates":[-1.8709340096,37.2502861023],"type":"Point"}
}