{
  "type": "Feature",
  "properties": {
    "iso:country":"ES",
    "sg:address":"Carrer de Llevant, 2",
    "sg:city":"S. Lloren\u00e7 Savall",
    "sg:orig_category":"Producci\u00d3n, Comercio De Cereales",
    "sg:phone":"+34 937 14 00 23",
    "sg:postcode":"08212",
    "sg:province":"Barcelona",
    "wof:name":"Caba Camprubi Josep",
    "wof:placetype":"venue"
},
  "geometry": {"coordinates":[2.058934927,41.6792907715],"type":"Point"}
}