{
  "type": "Feature",
  "properties": {
    "addr:full":"Bo Carbonaire-tres, 4 Vall Uixo Castell\u00f3n 12600",
    "addr:housenumber":"4",
    "addr:postcode":"12600",
    "addr:street":"Carbonaire-Tres;Castello\u0301N",
    "iso:country":"ES",
    "sg:address":"Bo Carbonaire-tres, 4",
    "sg:city":"Vall Uixo",
    "sg:orig_category":"Zapatos: Material, Suministros, Accesorios (fabricaci\u00d3n, Al Por Mayor)",
    "sg:phone":"+34 964 69 09 32",
    "sg:postcode":"12600",
    "sg:province":"Castell\u00f3n",
    "wof:name":"Guarnecidos Elecort S.l.",
    "wof:placetype":"venue"
},
  "geometry": {"coordinates":[-0.0360242017,39.9860687256],"type":"Point"}
}