{
  "type": "Feature",
  "properties": {
    "iso:country":"ES",
    "sg:address":"Plaz Alfonso El Magnanimo, 7",
    "sg:city":"Valencia",
    "sg:orig_category":"Centros Empresariales",
    "sg:phone":"+34 963 51 73 88",
    "sg:postcode":"46003",
    "sg:province":"Valencia",
    "wof:name":"Creperie Bretonne S.l.",
    "wof:placetype":"venue"
},
  "geometry": {"coordinates":[-0.3706910014,39.4712333679],"type":"Point"}
}