{
  "type": "Feature",
  "properties": {
    "iso:country":"ES",
    "sg:address":"Poli Industrial 1 De Mayo, 5",
    "sg:city":"Miajadas",
    "sg:orig_category":"Frutas Y Legumbres Frescas (al Por Mayor)",
    "sg:phone":"+34 927 34 73 64",
    "sg:postcode":"10100",
    "sg:province":"C\u00e1ceres",
    "wof:name":"Frutas Luisi S.l.",
    "wof:placetype":"venue"
},
  "geometry": {"coordinates":[-5.9082989693,39.1555213928],"type":"Point"}
}