{
  "type": "Feature",
  "properties": {
    "addr:full":"Federico Garcia Lorca, 20 Baena C\u00f3rdoba 14850",
    "addr:housenumber":"20",
    "addr:postcode":"14850",
    "addr:street":"Federico Garcia Lorca",
    "iso:country":"ES",
    "sg:address":"Federico Garcia Lorca, 20",
    "sg:city":"Baena",
    "sg:orig_category":"Aceites Y Grasas Alimentarias (fabricaci\u00d3n, Al Por Mayor)",
    "sg:phone":"+34 957 69 05 30",
    "sg:postcode":"14850",
    "sg:province":"C\u00f3rdoba",
    "wof:name":"Francisco Calero S.l.",
    "wof:placetype":"venue"
},
  "geometry": {"coordinates":[-4.3223562241,37.6149787903],"type":"Point"}
}