{
  "type": "Feature",
  "properties": {
    "iso:country":"ES",
    "sg:address":"Avda Antonio Alzaga, 68",
    "sg:city":"Santurtzi",
    "sg:orig_category":"Panader\u00cdas, Panader\u00cdas",
    "sg:phone":"+34 944 62 30 43",
    "sg:postcode":"48980",
    "sg:province":"Vizcaya",
    "wof:name":"Pasteleria Kai-alde, S.a.",
    "wof:placetype":"venue"
},
  "geometry": {"coordinates":[-3.0371119976,43.3222885132],"type":"Point"}
}