{
  "type": "Feature",
  "properties": {
    "addr:full":"Ctra Sur, Km. 0053,0 S. Agustin-playa Ingles Las Palmas 35100",
    "addr:postcode":"35100",
    "addr:street":"Ctra Sur Km. 0053,0 S. Agustin-Playa",
    "iso:country":"ES",
    "sg:address":"Ctra Sur, Km. 0053,0",
    "sg:city":"S. Agustin-playa Ingles",
    "sg:orig_category":"Imprenta",
    "sg:phone":"+34 928 77 16 98",
    "sg:postcode":"35100",
    "sg:province":"Las Palmas",
    "wof:name":"Grafic World Design",
    "wof:placetype":"venue"
},
  "geometry": {"coordinates":[-15.4397096634,28.1302204132],"type":"Point"}
}