{
  "type": "Feature",
  "properties": {
    "addr:full":"Carrer de Fran\u00c7a, 26 Terrassa Barcelona 08228",
    "addr:housenumber":"26",
    "addr:postcode":"08228",
    "addr:street":"Carrer De Franc\u0327A",
    "iso:country":"ES",
    "sg:address":"Carrer de Fran\u00c7a, 26",
    "sg:city":"Terrassa",
    "sg:orig_category":"Frutas, Legumbres Frescas Y Tempranas (al Por Menor)",
    "sg:phone":"+34 937 83 96 43",
    "sg:postcode":"08228",
    "sg:province":"Barcelona",
    "wof:name":"Frutas Nu\u00f1o S.l.",
    "wof:placetype":"venue"
},
  "geometry": {"coordinates":[2.0444290638,41.5385360718],"type":"Point"}
}