{
  "type": "Feature",
  "properties": {
    "addr:full":"Amillaga Kalea, 1 Bergara Guip\u00f9zcoa 20570",
    "addr:housenumber":"1",
    "addr:postcode":"20570",
    "addr:street":"Amillaga Kalea;Guipu\u0300Zcoa",
    "iso:country":"ES",
    "sg:address":"Amillaga Kalea, 1",
    "sg:city":"Bergara",
    "sg:orig_category":"Plomeros",
    "sg:phone":"+34 943 76 28 04",
    "sg:postcode":"20570",
    "sg:province":"Guip\u00f9zcoa",
    "wof:name":"Unanue Olaizola Jose Maria",
    "wof:placetype":"venue"
},
  "geometry": {"coordinates":[-2.4217479229,43.1228294373],"type":"Point"}
}