{
  "type": "Feature",
  "properties": {
    "iso:country":"ES",
    "sg:address":"Carrer de Prosper De Bofarull, 5",
    "sg:city":"Reus",
    "sg:orig_category":"Asesor\u00cda Sobre Comunicaci\u00d3n De Empresas",
    "sg:phone":"+34 977 34 14 34",
    "sg:postcode":"43202",
    "sg:province":"Tarragona",
    "wof:name":"Clatovall Associats S.l.",
    "wof:placetype":"venue"
},
  "geometry": {"coordinates":[1.1023509502,41.1580657959],"type":"Point"}
}