{
  "type": "Feature",
  "properties": {
    "iso:country":"ES",
    "sg:address":"Carrer de Francoli, 25",
    "sg:city":"Barcelona",
    "sg:orig_category":"Mensajer\u00cda Express, Portes Internacionales",
    "sg:phone":"+34 932 17 15 54",
    "sg:postcode":"08006",
    "sg:province":"Barcelona",
    "sg:website":"www.halcourier.es",
    "wof:name":"Hrm Catalu\u00f1a S.l.",
    "wof:placetype":"venue"
},
  "geometry": {"coordinates":[2.1473639011,41.4041671753],"type":"Point"}
}