{
  "type": "Feature",
  "properties": {
    "iso:country":"ES",
    "sg:address":"Fca. Tornajon, S/n",
    "sg:city":"Linares Riofrio",
    "sg:orig_category":"Ense\u00d1anza, Formaci\u00d3n Profesional: Aprendizaje",
    "sg:phone":"+34 923 41 61 47",
    "sg:postcode":"37760",
    "sg:province":"Salamanca",
    "wof:name":"Colegio Rural Agrupado Alto Alagon",
    "wof:placetype":"venue"
},
  "geometry": {"coordinates":[-5.9210190773,40.5825767517],"type":"Point"}
}