{
  "type": "Feature",
  "properties": {
    "addr:full":"Calle de Pio Xi, 13 Valencia Valencia 46007",
    "addr:housenumber":"13",
    "addr:postcode":"46007",
    "addr:street":"Calle De Pio Xi",
    "iso:country":"ES",
    "sg:address":"Calle de Pio Xi, 13",
    "sg:city":"Valencia",
    "sg:classifiers":[
        {
            "category":"Autos & Motor Vehicles",
            "subcategory":"Automobile Sales",
            "type":"Retail Goods"
        }
    ],
    "sg:phone":"+34 963 57 28 23",
    "sg:postcode":"46007",
    "sg:province":"Valencia",
    "wof:name":"Fernando Guillem E Hijos S.l.",
    "wof:placetype":"venue"
},
  "geometry": {"coordinates":[-0.3929030001,39.4590759277],"type":"Point"}
}