{
  "type": "Feature",
  "properties": {
    "addr:full":"Calle de Santiago Ramon Y Cajal (de), 2 Colmenar Viejo Madrid 28770",
    "addr:postcode":"28770",
    "addr:street":"Calle De Santiago Ramon Y Cajal De",
    "iso:country":"ES",
    "sg:address":"Calle de Santiago Ramon Y Cajal (de), 2",
    "sg:city":"Colmenar Viejo",
    "sg:orig_category":"Cl\u00cdnicas Dentales",
    "sg:phone":"+34 918 45 78 79",
    "sg:postcode":"28770",
    "sg:province":"Madrid",
    "wof:name":"Perez Herrero Carlos",
    "wof:placetype":"venue"
},
  "geometry": {"coordinates":[-3.769990921,40.6627616882],"type":"Point"}
}