{
  "type": "Feature",
  "properties": {
    "addr:full":"Concepcion Arenal, 135 Naron La Coru\u00f1a 15570",
    "addr:housenumber":"135",
    "addr:postcode":"15570",
    "addr:street":"Concepcion Arenal;La Corun\u0303A",
    "iso:country":"ES",
    "sg:address":"Concepcion Arenal, 135",
    "sg:city":"Naron",
    "sg:orig_category":"Promotores Constructores",
    "sg:phone":"+34 981 38 64 82",
    "sg:postcode":"15570",
    "sg:province":"La Coru\u00f1a",
    "wof:name":"Caruncho Pena Manuel",
    "wof:placetype":"venue"
},
  "geometry": {"coordinates":[-8.1647539139,43.5165405273],"type":"Point"}
}