{
  "type": "Feature",
  "properties": {
    "addr:full":"Carrer de Sardenya, 256 Barcelona Barcelona 08013",
    "addr:housenumber":"256",
    "addr:postcode":"08013",
    "addr:street":"Carrer De Sardenya",
    "iso:country":"ES",
    "sg:address":"Carrer de Sardenya, 256",
    "sg:city":"Barcelona",
    "sg:orig_category":"Grafistas",
    "sg:phone":"+34 932 44 44 02",
    "sg:postcode":"08013",
    "sg:province":"Barcelona",
    "wof:name":"Tintaxina S.c.p.",
    "wof:placetype":"venue"
},
  "geometry": {"coordinates":[2.1781699657,41.3999328613],"type":"Point"}
}