{
  "type": "Feature",
  "properties": {
    "iso:country":"ES",
    "sg:address":"Calle de Pinar De Do\u00d1a Consuelo, 11",
    "sg:city":"Majadahonda",
    "sg:orig_category":"Expertos Contables, Revisores De Cuentas",
    "sg:phone":"+34 916 34 45 94",
    "sg:postcode":"28220",
    "sg:province":"Madrid",
    "sg:website":"www.auditores-consultores.com",
    "wof:name":"De Diego Y Cortes Auditoria Y Asesoramiento S.l.",
    "wof:placetype":"venue"
},
  "geometry": {"coordinates":[-3.8763210773,40.4820480347],"type":"Point"}
}