{
  "type": "Feature",
  "properties": {
    "iso:country":"ES",
    "sg:address":"Pase Extremadura, 288",
    "sg:city":"Monesterio",
    "sg:orig_category":"Mec\u00c1nico Del Autom\u00d3vil",
    "sg:phone":"+34 924 51 60 52",
    "sg:postcode":"06260",
    "sg:province":"Badajoz",
    "wof:name":"Taller Mecanico Antonio Moya S.l.",
    "wof:placetype":"venue"
},
  "geometry": {"coordinates":[-6.2714591026,38.0864181519],"type":"Point"}
}