{
  "type": "Feature",
  "properties": {
    "addr:full":"Avda Virgen De Guadalupe, 29 Caceres C\u00e1ceres 10001",
    "addr:housenumber":"29",
    "addr:postcode":"10001",
    "addr:street":"Avda Virgen De Guadalupe;Ca\u0301Ceres",
    "iso:country":"ES",
    "sg:address":"Avda Virgen De Guadalupe, 29",
    "sg:city":"Caceres",
    "sg:orig_category":"Arquitectos",
    "sg:phone":"+34 927 62 60 60",
    "sg:postcode":"10001",
    "sg:province":"C\u00e1ceres",
    "wof:name":"Alonso Martinez Consulting Legal S.l.",
    "wof:placetype":"venue"
},
  "geometry": {"coordinates":[-6.3823695183,39.4700698853],"type":"Point"}
}