{
  "type": "Feature",
  "properties": {
    "addr:full":"Carrer de Avinyo, 25 Barcelona Barcelona 08002",
    "addr:housenumber":"25",
    "addr:postcode":"08002",
    "addr:street":"Carrer De Avinyo",
    "iso:country":"ES",
    "sg:address":"Carrer de Avinyo, 25",
    "sg:city":"Barcelona",
    "sg:orig_category":"Bisuteros (fabricaci\u00d3n, Al Por Mayor)",
    "sg:phone":"+34 933 01 41 94",
    "sg:postcode":"08002",
    "sg:province":"Barcelona",
    "wof:name":"Alvarez Gomez Robert",
    "wof:placetype":"venue"
},
  "geometry": {"coordinates":[2.1780223846,41.3806495667],"type":"Point"}
}