{
  "type": "Feature",
  "properties": {
    "iso:country":"ES",
    "sg:address":"Carrer de Joan Maragall, 4",
    "sg:city":"Valls",
    "sg:orig_category":"Electricidad: Instaladores",
    "sg:phone":"+34 977 60 01 66",
    "sg:postcode":"43800",
    "sg:province":"Tarragona",
    "wof:name":"Gatell Saperas Francisco",
    "wof:placetype":"venue"
},
  "geometry": {"coordinates":[1.248617053,41.2921218872],"type":"Point"}
}