{
  "type": "Feature",
  "properties": {
    "iso:country":"ES",
    "sg:address":"Calle de Colombia, 29",
    "sg:city":"Coslada",
    "sg:orig_category":"Procuradores",
    "sg:phone":"+34 916 71 10 18",
    "sg:postcode":"28820",
    "sg:province":"Madrid",
    "wof:name":"Ilustre Colegio De Procuradores De Madrid",
    "wof:placetype":"venue"
},
  "geometry": {"coordinates":[-3.5429811478,40.4274139404],"type":"Point"}
}