{
  "type": "Feature",
  "properties": {
    "iso:country":"ES",
    "sg:address":"Carrer de Josep Recort, 10",
    "sg:city":"Cornella Llobregat",
    "sg:orig_category":"Promotores Constructores",
    "sg:phone":"+34 934 74 49 47",
    "sg:postcode":"08940",
    "sg:province":"Barcelona",
    "wof:name":"Construcciones Y Derivados En General S.l",
    "wof:placetype":"venue"
},
  "geometry": {"coordinates":[2.0672140121,41.3531646729],"type":"Point"}
}