{
  "type": "Feature",
  "properties": {
    "addr:full":"Calle de Ramon Y Cajal, 23 Lahiguera Ja\u00e9n 23146",
    "addr:housenumber":"23",
    "addr:postcode":"23146",
    "addr:street":"Calle De Ramon Y Cajal",
    "iso:country":"ES",
    "sg:address":"Calle de Ramon Y Cajal, 23",
    "sg:city":"Lahiguera",
    "sg:orig_category":"Fabricaci\u00d3n, Venta De Productos Base Farmac\u00c9uticos",
    "sg:phone":"+34 953 53 01 27",
    "sg:postcode":"23146",
    "sg:province":"Ja\u00e9n",
    "wof:name":"Arrazola Moreno Tomas",
    "wof:placetype":"venue"
},
  "geometry": {"coordinates":[-3.9919774532,37.9700050354],"type":"Point"}
}