{
  "type": "Feature",
  "properties": {
    "addr:full":"Plaz Herriko Plaza, 8 San Vicente De Barakaldo Vizcaya 48901",
    "addr:housenumber":"8",
    "addr:postcode":"48901",
    "addr:street":"Herriko Plaza",
    "iso:country":"ES",
    "sg:address":"Plaz Herriko Plaza, 8",
    "sg:city":"San Vicente De Barakaldo",
    "sg:orig_category":"Ropa Para Se\u00d1oras (al Por Menor)",
    "sg:phone":"+34 944 37 20 52",
    "sg:postcode":"48901",
    "sg:province":"Vizcaya",
    "wof:name":"Mansoa Y Algarra S.l",
    "wof:placetype":"venue"
},
  "geometry": {"coordinates":[-2.9859509468,43.2966003418],"type":"Point"}
}