{
  "type": "Feature",
  "properties": {
    "addr:full":"Calle de Sierra De Gata (de La), 6 Poligono De San Fernando De Henares Madrid 28830",
    "addr:housenumber":"6",
    "addr:postcode":"28830",
    "addr:street":"Calle De Sierra De Gata De La",
    "iso:country":"ES",
    "sg:address":"Calle de Sierra De Gata (de La), 6",
    "sg:city":"Poligono De San Fernando De Henares",
    "sg:orig_category":"Material Did\u00c1ctico",
    "sg:phone":"+34 916 77 95 70",
    "sg:postcode":"28830",
    "sg:province":"Madrid",
    "wof:name":"Simuplast S.l.",
    "wof:placetype":"venue"
},
  "geometry": {"coordinates":[-3.5070490837,40.4509315491],"type":"Point"}
}