{
  "type": "Feature",
  "properties": {
    "iso:country":"ES",
    "sg:address":"Calle de Triunfo, 6",
    "sg:city":"Pe\u00e7arroya-pueblonuevo",
    "sg:orig_category":"Transportes Por V\u00cdas Navegables",
    "sg:phone":"+34 957 56 03 88",
    "sg:postcode":"14200",
    "sg:province":"C\u00f3rdoba",
    "wof:name":"Lopez Bejarano Eugenio",
    "wof:placetype":"venue"
},
  "geometry": {"coordinates":[-5.2626171112,38.2987594604],"type":"Point"}
}