{
  "type": "Feature",
  "properties": {
    "iso:country":"ES",
    "sg:address":"Calle de Henry De Boulogne, S/n",
    "sg:city":"Sabi\u00f1anigo",
    "sg:orig_category":"Asociaciones, Organismos Culturales Y Socioeducativos",
    "sg:phone":"+34 974 48 20 61",
    "sg:postcode":"22600",
    "sg:province":"Huesca",
    "wof:name":"Grupo Folclorico Santiago",
    "wof:placetype":"venue"
},
  "geometry": {"coordinates":[-0.3585410118,42.5077705383],"type":"Point"}
}