{
  "type": "Feature",
  "properties": {
    "iso:country":"ES",
    "sg:address":"Calle de Ca\u00d1averal, 75",
    "sg:city":"Madrid",
    "sg:orig_category":"Molduras, Junquillos, Listones Y Molduras Perforadas",
    "sg:phone":"+34 913 14 99 40",
    "sg:postcode":"28029",
    "sg:province":"Madrid",
    "wof:name":"Qu  Dong Dong",
    "wof:placetype":"venue"
},
  "geometry": {"coordinates":[-3.6927754879,40.4698448181],"type":"Point"}
}