{
  "type": "Feature",
  "properties": {
    "addr:full":"Calle de Ezequiel Aguirre, 5 Getxo Vizcaya 48930",
    "addr:housenumber":"5",
    "addr:postcode":"48930",
    "addr:street":"Calle De Ezequiel Aguirre",
    "iso:country":"ES",
    "sg:address":"Calle de Ezequiel Aguirre, 5",
    "sg:city":"Getxo",
    "sg:orig_category":"Electricidad: Instaladores",
    "sg:phone":"+34 944 63 19 33",
    "sg:postcode":"48930",
    "sg:province":"Vizcaya",
    "wof:name":"Gabino Yague",
    "wof:placetype":"venue"
},
  "geometry": {"coordinates":[-3.0075201988,43.3273696899],"type":"Point"}
}