{
  "type": "Feature",
  "properties": {
    "iso:country":"ES",
    "sg:address":"Avda Castilla La Mancha, 14",
    "sg:city":"Cobisa",
    "sg:orig_category":"Molduras, Junquillos, Listones Y Molduras Perforadas",
    "sg:phone":"+34 925 37 67 82",
    "sg:postcode":"45111",
    "sg:province":"Toledo",
    "wof:name":"Maestro Collado Tomas",
    "wof:placetype":"venue"
},
  "geometry": {"coordinates":[-4.0229740143,39.8063735962],"type":"Point"}
}