{
  "type": "Feature",
  "properties": {
    "addr:full":"Calle de Huelva, 40 Arrecife Las Palmas 35500",
    "addr:housenumber":"40",
    "addr:postcode":"35500",
    "addr:street":"Calle De Huelva",
    "iso:country":"ES",
    "sg:address":"Calle de Huelva, 40",
    "sg:city":"Arrecife",
    "sg:orig_category":"Deportes N\u00c1uticos, Acu\u00c1ticos Y Subacu\u00c1ticos: Art\u00cdculos Y Equipo (al Por Menor)",
    "sg:phone":"+34 928 80 72 49",
    "sg:postcode":"35500",
    "sg:province":"Las Palmas",
    "wof:name":"J.h.sport Lanzarote S.l",
    "wof:placetype":"venue"
},
  "geometry": {"coordinates":[-13.5489902496,28.9692420959],"type":"Point"}
}