{
  "type": "Feature",
  "properties": {
    "iso:country":"ES",
    "sg:address":"Carrer de Muntaner, 401",
    "sg:city":"Barcelona",
    "sg:orig_category":"Administraci\u00d3n En Agricultura",
    "sg:phone":"+34 934 14 47 74",
    "sg:postcode":"08021",
    "sg:province":"Barcelona",
    "wof:name":"Financament I Tecnica S.l.",
    "wof:placetype":"venue"
},
  "geometry": {"coordinates":[2.1416509151,41.3998451233],"type":"Point"}
}