{
  "type": "Feature",
  "properties": {
    "addr:full":"Ctra Cabezo De Torres, S/n Laderas Del Campillo Murcia 30163",
    "addr:postcode":"30163",
    "addr:street":"Ctra Cabezo De Torres S / N Laderas",
    "iso:country":"ES",
    "sg:address":"Ctra Cabezo De Torres, S/n",
    "sg:city":"Laderas Del Campillo",
    "sg:orig_category":"Suministros Para Carrocer\u00cdas",
    "sg:phone":"+34 968 83 44 44",
    "sg:postcode":"30163",
    "sg:province":"Murcia",
    "wof:name":"Basculantes Bademur S.l.",
    "wof:placetype":"venue"
},
  "geometry": {"coordinates":[-1.0736939907,38.0533943176],"type":"Point"}
}