{
  "type": "Feature",
  "properties": {
    "addr:full":"Carrer de Sant Josep, 60 Calella Barcelona 08370",
    "addr:housenumber":"60",
    "addr:postcode":"08370",
    "addr:street":"Carrer De Sant Josep",
    "iso:country":"ES",
    "sg:address":"Carrer de Sant Josep, 60",
    "sg:city":"Calella",
    "sg:orig_category":"Molduras, Junquillos, Listones Y Molduras Perforadas",
    "sg:phone":"+34 937 66 17 78",
    "sg:postcode":"08370",
    "sg:province":"Barcelona",
    "wof:name":"Escandell Ribas Josep Antoni",
    "wof:placetype":"venue"
},
  "geometry": {"coordinates":[2.6605761051,41.6146659851],"type":"Point"}
}