{
  "type": "Feature",
  "properties": {
    "iso:country":"ES",
    "sg:address":"Calle de Acacias, 9",
    "sg:city":"Salamanca",
    "sg:orig_category":"Producci\u00d3n, Distribuci\u00d3n De Electricidad",
    "sg:phone":"+34 923 22 31 59",
    "sg:postcode":"37004",
    "sg:province":"Salamanca",
    "wof:name":"Iglesias Ullan Bego\u00f1a",
    "wof:placetype":"venue"
},
  "geometry": {"coordinates":[-5.653222084,40.9762763977],"type":"Point"}
}