{
  "type": "Feature",
  "properties": {
    "addr:full":"Praz Maior, 20 Viana Do Bolo Ourense 32550",
    "addr:housenumber":"20",
    "addr:postcode":"32550",
    "addr:street":"Praz Maior",
    "iso:country":"ES",
    "sg:address":"Praz Maior, 20",
    "sg:city":"Viana Do Bolo",
    "sg:orig_category":"Peluqueros: De Se\u00d1oras",
    "sg:phone":"+34 988 34 02 44",
    "sg:postcode":"32550",
    "sg:province":"Ourense",
    "wof:name":"Sanchez Sanchez Mercedes",
    "wof:placetype":"venue"
},
  "geometry": {"coordinates":[-7.1098628044,42.1833190918],"type":"Point"}
}