{
  "type": "Feature",
  "properties": {
    "iso:country":"ES",
    "sg:address":"Carrer de Menendez I Pelayo, 25",
    "sg:city":"Vic",
    "sg:orig_category":"Electrodom\u00c9sticos (al Por Menor)",
    "sg:phone":"+34 938 89 41 03",
    "sg:postcode":"08500",
    "sg:province":"Barcelona",
    "wof:name":"Mayans Casas Joan",
    "wof:placetype":"venue"
},
  "geometry": {"coordinates":[2.2600460052,41.9237823486],"type":"Point"}
}