{
  "type": "Feature",
  "properties": {
    "addr:full":"Calle de Zurbaran, 2 Bilbao Vizcaya 48007",
    "addr:housenumber":"2",
    "addr:postcode":"48007",
    "addr:street":"Calle De Zurbaran",
    "iso:country":"ES",
    "sg:address":"Calle de Zurbaran, 2",
    "sg:city":"Bilbao",
    "sg:orig_category":"Artes Gr\u00c1ficas, Artes Pl\u00c1sticas (curso)",
    "sg:phone":"+34 944 45 01 00",
    "sg:postcode":"48007",
    "sg:province":"Vizcaya",
    "wof:name":"Fotocomposicion Ipar S. C. L.",
    "wof:placetype":"venue"
},
  "geometry": {"coordinates":[-2.9165639877,43.2640533447],"type":"Point"}
}