{
  "type": "Feature",
  "properties": {
    "iso:country":"ES",
    "sg:address":"Calle de Imagen, 32",
    "sg:city":"Madrid",
    "sg:orig_category":"Inmobiliaria (agencias)",
    "sg:phone":"+34 917 85 32 57",
    "sg:postcode":"28018",
    "sg:province":"Madrid",
    "wof:name":"Proyect Imanking S.l.",
    "wof:placetype":"venue"
},
  "geometry": {"coordinates":[-3.6682479382,40.3831634521],"type":"Point"}
}