{
  "type": "Feature",
  "properties": {
    "addr:full":"Carr Colon, 121 Vila Joiosa Alicante 03570",
    "addr:housenumber":"121",
    "addr:postcode":"03570",
    "addr:street":"Carr Colon",
    "iso:country":"ES",
    "sg:address":"Carr Colon, 121",
    "sg:city":"Vila Joiosa",
    "sg:orig_category":"Carnicer\u00cdas, Carnicer\u00cdas",
    "sg:phone":"+34 965 89 14 67",
    "sg:postcode":"03570",
    "sg:province":"Alicante",
    "wof:name":"Lloret Selles Francisco",
    "wof:placetype":"venue"
},
  "geometry": {"coordinates":[-0.7466139793,38.3102035522],"type":"Point"}
}