{
  "type": "Feature",
  "properties": {
    "iso:country":"ES",
    "sg:address":"Rond Can Rabada, 5",
    "sg:city":"Castelldefels",
    "sg:orig_category":"Fabricaci\u00d3n De Motores El\u00c9ctricos",
    "sg:phone":"+34 936 33 35 35",
    "sg:postcode":"08860",
    "sg:province":"Barcelona",
    "sg:website":"www.ememotor.com",
    "wof:name":"Eme-motor Loher Distribucion S.a.",
    "wof:placetype":"venue"
},
  "geometry": {"coordinates":[1.9278570414,41.2629699707],"type":"Point"}
}