{
  "type": "Feature",
  "properties": {
    "iso:country":"ES",
    "sg:address":"Carrer de Sant Magi, 8",
    "sg:city":"Palma",
    "sg:orig_category":"Estancos",
    "sg:phone":"+34 971 73 35 54",
    "sg:postcode":"07013",
    "sg:province":"Islas Baleares",
    "wof:name":"Vicens Vidal Francisco",
    "wof:placetype":"venue"
},
  "geometry": {"coordinates":[2.6390359402,39.5704689026],"type":"Point"}
}