{
  "type": "Feature",
  "properties": {
    "addr:full":"Carrer de Galicia, 83 Terrassa Barcelona 08223",
    "addr:housenumber":"83",
    "addr:postcode":"08223",
    "addr:street":"Carrer De Galicia",
    "iso:country":"ES",
    "sg:address":"Carrer de Galicia, 83",
    "sg:city":"Terrassa",
    "sg:orig_category":"Tapicer\u00cdas",
    "sg:phone":"+34 937 31 27 42",
    "sg:postcode":"08223",
    "sg:province":"Barcelona",
    "wof:name":"Tendenza.it S.l.",
    "wof:placetype":"venue"
},
  "geometry": {"coordinates":[2.0131011009,41.550945282],"type":"Point"}
}