{
  "type": "Feature",
  "properties": {
    "iso:country":"ES",
    "sg:address":"Calle de Isaac De Vega, 32",
    "sg:city":"Granadilla Abona",
    "sg:orig_category":"Bazares, Art\u00cdculos De Limpieza Y De Cocina (al Por Menor)",
    "sg:phone":"+34 922 77 02 53",
    "sg:postcode":"38600",
    "sg:province":"Santa Cruz De Tenerife",
    "wof:name":"Torres Garcia Marisol",
    "wof:placetype":"venue"
},
  "geometry": {"coordinates":[-16.5761947632,28.1261081696],"type":"Point"}
}