{
  "type": "Feature",
  "properties": {
    "iso:country":"ES",
    "sg:address":"Plaz Ayuntamiento, 19",
    "sg:city":"Valencia",
    "sg:orig_category":"Inmobiliaria (agencias)",
    "sg:phone":"+34 963 10 61 15",
    "sg:postcode":"46002",
    "sg:province":"Valencia",
    "wof:name":"Yotu",
    "wof:placetype":"venue"
},
  "geometry": {"coordinates":[-0.3761447072,39.4705543518],"type":"Point"}
}