{
  "type": "Feature",
  "properties": {
    "addr:full":"Rua De Amado Garra, 13 Ponteareas Pontevedra 36860",
    "addr:housenumber":"13",
    "addr:postcode":"36860",
    "addr:street":"Rua De Amado Garra",
    "iso:country":"ES",
    "sg:address":"Rua De Amado Garra, 13",
    "sg:city":"Ponteareas",
    "sg:orig_category":"Ense\u00d1anza: Profesiones Art\u00cdsticas",
    "sg:phone":"+34 986 64 41 16",
    "sg:postcode":"36860",
    "sg:province":"Pontevedra",
    "wof:name":"Ledo & Garcia S.l.l.",
    "wof:placetype":"venue"
},
  "geometry": {"coordinates":[-8.5053443909,42.1726799011],"type":"Point"}
}