{
  "type": "Feature",
  "properties": {
    "iso:country":"ES",
    "sg:address":"Calle de Cavas, 16",
    "sg:city":"Calahorra",
    "sg:orig_category":"Peluquer\u00cdas, Peluquer\u00cda Mixta",
    "sg:phone":"+34 941 14 60 47",
    "sg:postcode":"26500",
    "sg:province":"La Rioja",
    "wof:name":"Irisarri Ucar Oscar",
    "wof:placetype":"venue"
},
  "geometry": {"coordinates":[-1.9623895884,42.3027458191],"type":"Point"}
}