{
  "type": "Feature",
  "properties": {
    "addr:full":"Escoles, S/n Freixinet Lleida 25290",
    "addr:housenumber":"s",
    "addr:postcode":"25290",
    "addr:street":"/ N Freixinet",
    "iso:country":"ES",
    "sg:address":"Escoles, S/n",
    "sg:city":"Freixinet",
    "sg:orig_category":"Centros De Educaci\u00d3n Especial",
    "sg:phone":"+34 973 48 18 77",
    "sg:postcode":"25290",
    "sg:province":"Lleida",
    "wof:name":"Ajuntament De Riner",
    "wof:placetype":"venue"
},
  "geometry": {"coordinates":[1.4181294441,41.6557579041],"type":"Point"}
}