{
  "type": "Feature",
  "properties": {
    "iso:country":"ES",
    "sg:address":"Ctra Segorbe, 91",
    "sg:city":"Vall D'uixo",
    "sg:orig_category":"Reposter\u00cdas",
    "sg:phone":"+34 964 66 07 83",
    "sg:postcode":"12600",
    "sg:province":"Castell\u00f3n",
    "wof:name":"Sanz Moliner Maria Dolores",
    "wof:placetype":"venue"
},
  "geometry": {"coordinates":[-0.0400759988,39.9915237427],"type":"Point"}
}