{
  "type": "Feature",
  "properties": {
    "addr:full":"C/ Poeta Joan Valls, 42 Alcoi Alicante 03803",
    "addr:housenumber":"42",
    "addr:postcode":"03803",
    "addr:street":"C / Poeta Joan Valls",
    "iso:country":"ES",
    "sg:address":"C/ Poeta Joan Valls, 42",
    "sg:city":"Alcoi",
    "sg:orig_category":"Carnicer\u00cdas, Carnicer\u00cdas",
    "sg:phone":"+34 965 33 26 21",
    "sg:postcode":"03803",
    "sg:province":"Alicante",
    "wof:name":"Industrias Carnicas Luis Ripoll S.a.",
    "wof:placetype":"venue"
},
  "geometry": {"coordinates":[-0.4785589874,38.7040672302],"type":"Point"}
}