{
  "type": "Feature",
  "properties": {
    "iso:country":"ES",
    "sg:address":"Alfarero Salvador Hernandez, 12",
    "sg:city":"Vera",
    "sg:orig_category":"Notarios",
    "sg:phone":"+34 950 39 01 52",
    "sg:postcode":"04620",
    "sg:province":"Almer\u00eda",
    "wof:name":"Diaz Cadorniga Jorge",
    "wof:placetype":"venue"
},
  "geometry": {"coordinates":[-1.8645819426,37.2478141785],"type":"Point"}
}