{
  "type": "Feature",
  "properties": {
    "iso:country":"ES",
    "sg:address":"Avgd Pintor Gomar, S/n",
    "sg:city":"Beniganim",
    "sg:orig_category":"Ebanister\u00cda",
    "sg:phone":"+34 962 21 51 98",
    "sg:postcode":"46830",
    "sg:province":"Valencia",
    "wof:name":"Ebanisteria Jormi, Sl",
    "wof:placetype":"venue"
},
  "geometry": {"coordinates":[-0.447863996,38.9413452148],"type":"Point"}
}