{
  "type": "Feature",
  "properties": {
    "iso:country":"ES",
    "sg:address":"Calle de Domingo Fresnedo, 15",
    "sg:city":"Arriondas",
    "sg:orig_category":"Producci\u00d3n De Sidra",
    "sg:phone":"+34 985 84 02 27",
    "sg:postcode":"33540",
    "sg:province":"Asturias",
    "wof:name":"Aramburo Melero Benigno",
    "wof:placetype":"venue"
},
  "geometry": {"coordinates":[-5.1843686104,43.3908042908],"type":"Point"}
}