{
  "type": "Feature",
  "properties": {
    "iso:country":"ES",
    "sg:address":"Calle de Estacion, 9",
    "sg:city":"Irun",
    "sg:orig_category":"Discotecas Y Salas De Baile",
    "sg:phone":"+34 943 66 60 91",
    "sg:postcode":"20301",
    "sg:province":"Guip\u00f9zcoa",
    "wof:name":"Ruiz Perez Valentin",
    "wof:placetype":"venue"
},
  "geometry": {"coordinates":[-1.798879981,43.3408317566],"type":"Point"}
}