{
  "type": "Feature",
  "properties": {
    "addr:full":"Carrer de Antiquaris, 6 Reus Tarragona 43205",
    "addr:housenumber":"6",
    "addr:postcode":"43205",
    "addr:street":"Carrer De Antiquaris",
    "iso:country":"ES",
    "sg:address":"Carrer de Antiquaris, 6",
    "sg:city":"Reus",
    "sg:orig_category":"Ense\u00d1anza: Profesiones Art\u00cdsticas",
    "sg:phone":"+34 977 75 67 59",
    "sg:postcode":"43205",
    "sg:province":"Tarragona",
    "wof:name":"Febrer Riba Ana Maria De La Piedad",
    "wof:placetype":"venue"
},
  "geometry": {"coordinates":[1.1129180193,41.1443977356],"type":"Point"}
}