{
  "type": "Feature",
  "properties": {
    "iso:country":"ES",
    "sg:address":"Calle de Siria, 4",
    "sg:city":"Archena",
    "sg:orig_category":"Bares, Piano",
    "sg:phone":"+34 968 67 23 44",
    "sg:postcode":"30600",
    "sg:province":"Murcia",
    "wof:name":"Salar Garcia Jose Javier",
    "wof:placetype":"venue"
},
  "geometry": {"coordinates":[-1.3012850285,38.1199378967],"type":"Point"}
}