{
  "type": "Feature",
  "properties": {
    "addr:full":"Calle de Caveda, 4 Oviedo Asturias 33002",
    "addr:housenumber":"4",
    "addr:postcode":"33002",
    "addr:street":"Calle De Caveda",
    "iso:country":"ES",
    "sg:address":"Calle de Caveda, 4",
    "sg:city":"Oviedo",
    "sg:orig_category":"Promotores Constructores",
    "sg:phone":"+34 985 21 90 40",
    "sg:postcode":"33002",
    "sg:province":"Asturias",
    "wof:name":"Promotora Carbayon S.a.",
    "wof:placetype":"venue"
},
  "geometry": {"coordinates":[-5.8476052284,43.3645248413],"type":"Point"}
}