{
  "type": "Feature",
  "properties": {
    "iso:country":"ES",
    "sg:address":"Calle de Soria, 14",
    "sg:city":"San Fernando De Henares",
    "sg:orig_category":"Clubes, Asociaciones De Ocio",
    "sg:phone":"+34 916 73 45 11",
    "sg:postcode":"28830",
    "sg:province":"Madrid",
    "sg:website":"www.conresa.com",
    "wof:name":"Fabricados Textiles Sayma S.l.",
    "wof:placetype":"venue"
},
  "geometry": {"coordinates":[-3.5319969654,40.4316978455],"type":"Point"}
}