{
  "type": "Feature",
  "properties": {
    "addr:full":"Carr Industria, 11 Angles Girona 17160",
    "addr:housenumber":"11",
    "addr:postcode":"17160",
    "addr:street":"Carr Industria",
    "iso:country":"ES",
    "sg:address":"Carr Industria, 11",
    "sg:city":"Angles",
    "sg:orig_category":"Juegos Y Juguetes (al Por Menor)",
    "sg:phone":"+34 972 42 01 53",
    "sg:postcode":"17160",
    "sg:province":"Girona",
    "wof:name":"Familia Vila Morera S.l.",
    "wof:placetype":"venue"
},
  "geometry": {"coordinates":[2.6347820759,41.9582252502],"type":"Point"}
}