{
  "type": "Feature",
  "properties": {
    "iso:country":"ES",
    "sg:address":"Carrer de Santa Teresa, 40",
    "sg:city":"S. Cugat Valles",
    "sg:orig_category":"Farmacias",
    "sg:phone":"+34 936 75 33 44",
    "sg:postcode":"08172",
    "sg:province":"Barcelona",
    "wof:name":"Moral Ajado Montserrat",
    "wof:placetype":"venue"
},
  "geometry": {"coordinates":[2.0868558884,41.467464447],"type":"Point"}
}