{
  "type": "Feature",
  "properties": {
    "addr:full":"Pol. Indust. Pont Princep, S/n Vilamalla Girona 17469",
    "addr:housenumber":"s / n",
    "addr:postcode":"17469",
    "addr:street":"Pol.;Pont Princep",
    "iso:country":"ES",
    "sg:address":"Pol. Indust. Pont Princep, S/n",
    "sg:city":"Vilamalla",
    "sg:orig_category":"Poli\u00c9ster",
    "sg:phone":"+34 972 52 50 48",
    "sg:postcode":"17469",
    "sg:province":"Girona",
    "wof:name":"Turro Hipolit Pedro",
    "wof:placetype":"venue"
},
  "geometry": {"coordinates":[3.0403180122,42.2426719666],"type":"Point"}
}