{
  "type": "Feature",
  "properties": {
    "iso:country":"ES",
    "sg:address":"Calle de Diego De Ria\u00d1o, 7",
    "sg:city":"Sevilla",
    "sg:orig_category":"M\u00c9dicos: Estomatolog\u00cda",
    "sg:phone":"+34 954 42 51 09",
    "sg:postcode":"41004",
    "sg:province":"Sevilla",
    "wof:name":"Aznar Martin Teresa",
    "wof:placetype":"venue"
},
  "geometry": {"coordinates":[-5.9848761559,37.3794364929],"type":"Point"}
}