{
  "type": "Feature",
  "properties": {
    "addr:full":"Rua Bispo Aguirre, 5 Lugo Lugo 27002",
    "addr:housenumber":"5",
    "addr:postcode":"27002",
    "addr:street":"Rua Bispo Aguirre",
    "iso:country":"ES",
    "sg:address":"Rua Bispo Aguirre, 5",
    "sg:city":"Lugo",
    "sg:orig_category":"Equipo Y Material Deportivo Y De Actividades Invernales Y De Monta\u00d1a",
    "sg:phone":"+34 982 23 15 58",
    "sg:postcode":"27002",
    "sg:province":"Lugo",
    "wof:name":"Miguel Sport S.l.",
    "wof:placetype":"venue"
},
  "geometry": {"coordinates":[-7.556333065,43.0080680847],"type":"Point"}
}