{
  "type": "Feature",
  "properties": {
    "addr:full":"Carrer de Salvador Espriu, 4 Casc Antic Barcelona 08150",
    "addr:housenumber":"4",
    "addr:postcode":"08150",
    "addr:street":"Carrer De Salvador Espriu",
    "iso:country":"ES",
    "sg:address":"Carrer de Salvador Espriu, 4",
    "sg:city":"Casc Antic",
    "sg:orig_category":"Ambulancias",
    "sg:phone":"+34 935 73 12 04",
    "sg:postcode":"08150",
    "sg:province":"Barcelona",
    "wof:name":"Transports Sanitaris Parets S.l.",
    "wof:placetype":"venue"
},
  "geometry": {"coordinates":[2.2293000221,41.5678787231],"type":"Point"}
}