{
  "type": "Feature",
  "properties": {
    "iso:country":"ES",
    "sg:address":"Calle de Mozanaque (de), 8",
    "sg:city":"Nogal",
    "sg:orig_category":"Empresas De Carpinter\u00cda De Madera",
    "sg:phone":"+34 916 29 01 57",
    "sg:postcode":"28110",
    "sg:province":"Madrid",
    "wof:name":"Carpinteria-evanisteria Industrial Aranda S.l.",
    "wof:placetype":"venue"
},
  "geometry": {"coordinates":[-3.4999940395,40.5979003906],"type":"Point"}
}