{
  "type": "Feature",
  "properties": {
    "addr:full":"Polig. Ind. A Granxa, S/n Porri\u00f1o Pontevedra 36475",
    "addr:housenumber":"s",
    "addr:postcode":"36475",
    "addr:street":"Polig. Ind. A Granxa;/ N",
    "iso:country":"ES",
    "sg:address":"Polig. Ind. A Granxa, S/n",
    "sg:city":"Porri\u00f1o",
    "sg:orig_category":"Triper\u00cdas",
    "sg:phone":"+34 986 34 21 68",
    "sg:postcode":"36475",
    "sg:province":"Pontevedra",
    "wof:name":"Industrial Tripera Gallega S.l.",
    "wof:placetype":"venue"
},
  "geometry": {"coordinates":[-8.606926918,42.1053466797],"type":"Point"}
}