{
  "type": "Feature",
  "properties": {
    "addr:full":"Avda Sinforiano Madro\u00d1ero, 15 Badajoz Badajoz 06011",
    "addr:housenumber":"15",
    "addr:postcode":"06011",
    "addr:street":"Avda Sinforiano Madron\u0303Ero",
    "iso:country":"ES",
    "sg:address":"Avda Sinforiano Madro\u00d1ero, 15",
    "sg:city":"Badajoz",
    "sg:orig_category":"M\u00c9dicos: Estomatolog\u00cda",
    "sg:phone":"+34 924 26 02 64",
    "sg:postcode":"06011",
    "sg:province":"Badajoz",
    "wof:name":"Martinez-berna Garcia Monica",
    "wof:placetype":"venue"
},
  "geometry": {"coordinates":[-6.9877858162,38.868686676],"type":"Point"}
}