{
  "type": "Feature",
  "properties": {
    "addr:full":"Calle de Real, 61 Estacion Madrid 28400",
    "addr:housenumber":"61",
    "addr:postcode":"28400",
    "addr:street":"Calle De Real",
    "iso:country":"ES",
    "sg:address":"Calle de Real, 61",
    "sg:city":"Estacion",
    "sg:orig_category":"Fisioterapia",
    "sg:phone":"+34 918 49 37 16",
    "sg:postcode":"28400",
    "sg:province":"Madrid",
    "wof:name":"Fisiovitally S.l.",
    "wof:placetype":"venue"
},
  "geometry": {"coordinates":[-3.9919650555,40.6455612183],"type":"Point"}
}