{
  "type": "Feature",
  "properties": {
    "iso:country":"ES",
    "sg:address":"Avda Atlantida, 86",
    "sg:city":"Vigo",
    "sg:orig_category":"Impuestos, Tesoro P\u00dablico",
    "sg:phone":"+34 986 20 04 24",
    "sg:postcode":"36208",
    "sg:province":"Pontevedra",
    "wof:name":"Rial Fernandez Jacinto",
    "wof:placetype":"venue"
},
  "geometry": {"coordinates":[-8.760058403,42.2218971252],"type":"Point"}
}