{
  "type": "Feature",
  "properties": {
    "iso:country":"ES",
    "sg:address":"Calle de Alfonso El Sabio, 44",
    "sg:city":"Caudete",
    "sg:orig_category":"Agencias De Viajes",
    "sg:phone":"+34 965 82 59 49",
    "sg:postcode":"02660",
    "sg:province":"Albacete",
    "wof:name":"Gandia Navarro Mari Angeles",
    "wof:placetype":"venue"
},
  "geometry": {"coordinates":[-0.9879457951,38.7083892822],"type":"Point"}
}