{
  "type": "Feature",
  "properties": {
    "addr:full":"Calle de Garcia Mas, 32 Albacete Albacete 02005",
    "addr:housenumber":"32",
    "addr:postcode":"02005",
    "addr:street":"Calle De Garcia Mas",
    "iso:country":"ES",
    "sg:address":"Calle de Garcia Mas, 32",
    "sg:city":"Albacete",
    "sg:orig_category":"Molduras, Junquillos, Listones Y Molduras Perforadas",
    "sg:phone":"+34 967 22 26 50",
    "sg:postcode":"02005",
    "sg:province":"Albacete",
    "wof:name":"Bleda Alarcon Juan Jose",
    "wof:placetype":"venue"
},
  "geometry": {"coordinates":[-1.8623859882,38.9986114502],"type":"Point"}
}