{
  "type": "Feature",
  "properties": {
    "addr:full":"Carrer de Doctor Fleming, S/n Premia Mar Barcelona 08330",
    "addr:housenumber":"s",
    "addr:postcode":"08330",
    "addr:street":"Carrer De Doctor Fleming;/ N",
    "iso:country":"ES",
    "sg:address":"Carrer de Doctor Fleming, S/n",
    "sg:city":"Premia Mar",
    "sg:orig_category":"Zapatos (al Por Menor)",
    "sg:phone":"+34 937 51 24 14",
    "sg:postcode":"08330",
    "sg:province":"Barcelona",
    "wof:name":"Navarro Aparicio Maria Gracia",
    "wof:placetype":"venue"
},
  "geometry": {"coordinates":[2.3569750786,41.4931755066],"type":"Point"}
}