{
  "type": "Feature",
  "properties": {
    "addr:full":"Calle de Rasca\u00d1a, 12 Valencia Valencia 46015",
    "addr:housenumber":"12",
    "addr:postcode":"46015",
    "addr:street":"Calle De Rascan\u0303A",
    "iso:country":"ES",
    "sg:address":"Calle de Rasca\u00d1a, 12",
    "sg:city":"Valencia",
    "sg:orig_category":"Tapiceros Y Tapiceros",
    "sg:phone":"+34 963 47 86 37",
    "sg:postcode":"46015",
    "sg:province":"Valencia",
    "wof:name":"Ros Subiela Manuel",
    "wof:placetype":"venue"
},
  "geometry": {"coordinates":[-0.3959420025,39.4820175171],"type":"Point"}
}