{
  "type": "Feature",
  "properties": {
    "iso:country":"ES",
    "sg:address":"Calle de Nu\u00d1ez De Balboa, 31",
    "sg:city":"Madrid",
    "sg:orig_category":"Propiedad Industrial: Patentes De Inventos, Marcas, Modelos, Dise\u00d1os",
    "sg:phone":"+34 915 76 33 34",
    "sg:postcode":"28001",
    "sg:province":"Madrid",
    "sg:website":"www.alvamark.com",
    "wof:name":"Alvarez Lopez Fernando",
    "wof:placetype":"venue"
},
  "geometry": {"coordinates":[-3.6828308105,40.4247741699],"type":"Point"}
}