{
  "type": "Feature",
  "properties": {
    "iso:country":"ES",
    "sg:address":"Ctra. Valencia, Km. 0015,0",
    "sg:city":"Rivas Urbanizaciones",
    "sg:orig_category":"Supermercados Y Hipermercados",
    "sg:phone":"+34 916 66 16 83",
    "sg:postcode":"28529",
    "sg:province":"Madrid",
    "wof:name":"Coalve S.l.",
    "wof:placetype":"venue"
},
  "geometry": {"coordinates":[-3.5102670193,40.314289093],"type":"Point"}
}