{
  "type": "Feature",
  "properties": {
    "addr:full":"Av Tren, 54 Inca Islas Baleares 07300",
    "addr:housenumber":"54",
    "addr:postcode":"07300",
    "addr:street":"Av Tren",
    "iso:country":"ES",
    "sg:address":"Av Tren, 54",
    "sg:city":"Inca",
    "sg:orig_category":"Imprenta",
    "sg:phone":"+34 971 50 02 44",
    "sg:postcode":"07300",
    "sg:province":"Islas Baleares",
    "wof:name":"Imprenta Molinos S.l.",
    "wof:placetype":"venue"
},
  "geometry": {"coordinates":[2.905962944,39.7184448242],"type":"Point"}
}