{
  "type": "Feature",
  "properties": {
    "addr:full":"Pl. Espanya, 7 Pals Girona 17256",
    "addr:housenumber":"7",
    "addr:postcode":"17256",
    "addr:street":"Pl. Espanya",
    "iso:country":"ES",
    "sg:address":"Pl. Espanya, 7",
    "sg:city":"Pals",
    "sg:orig_category":"Ense\u00d1anza, Formaci\u00d3n Profesional: Aprendizaje",
    "sg:phone":"+34 972 63 61 61",
    "sg:postcode":"17256",
    "sg:province":"Girona",
    "wof:name":"Ajuntament De Pals",
    "wof:placetype":"venue"
},
  "geometry": {"coordinates":[3.1488764286,41.9712142944],"type":"Point"}
}