{
  "type": "Feature",
  "properties": {
    "addr:full":"Rua Michelena, 2 Pontevedra Pontevedra 36002",
    "addr:housenumber":"2",
    "addr:postcode":"36002",
    "addr:street":"Rua Michelena",
    "iso:country":"ES",
    "sg:address":"Rua Michelena, 2",
    "sg:city":"Pontevedra",
    "sg:orig_category":"Estilistas Y Estudios De Estilo De Corte Y Confecci\u00d3n",
    "sg:phone":"+34 986 86 19 54",
    "sg:postcode":"36002",
    "sg:province":"Pontevedra",
    "wof:name":"Martinez Lema Armenio",
    "wof:placetype":"venue"
},
  "geometry": {"coordinates":[-8.6455793381,42.4312782288],"type":"Point"}
}