{
  "type": "Feature",
  "properties": {
    "iso:country":"ES",
    "sg:address":"Calle de Carlos Cano, 1",
    "sg:city":"Tarancon",
    "sg:orig_category":"Fabricaci\u00d3n De Sobres, Bolsas Y Fundas",
    "sg:phone":"+34 969 32 28 57",
    "sg:postcode":"16400",
    "sg:province":"Cuenca",
    "wof:name":"Figueroa De La Osada Maria Del Pilar",
    "wof:placetype":"venue"
},
  "geometry": {"coordinates":[-3.0079572201,40.0077667236],"type":"Point"}
}