{
  "type": "Feature",
  "properties": {
    "addr:full":"Ctra Guardias Viejas, S/n Matagorda Almer\u00eda 04715",
    "addr:housenumber":"s / n",
    "addr:postcode":"04715",
    "addr:street":"Ctra Guardias Viejas;Matagorda Almeri\u0301A",
    "iso:country":"ES",
    "sg:address":"Ctra Guardias Viejas, S/n",
    "sg:city":"Matagorda",
    "sg:orig_category":"Empresas De Desmonte",
    "sg:phone":"+34 950 49 85 00",
    "sg:postcode":"04715",
    "sg:province":"Almer\u00eda",
    "wof:name":"Aridos Manuel Figueredo E Hijos S.l.",
    "wof:placetype":"venue"
},
  "geometry": {"coordinates":[-2.8420639038,36.7215385437],"type":"Point"}
}