{
  "type": "Feature",
  "properties": {
    "addr:full":"Carrer de Moline, 3 Barcelona Barcelona 08006",
    "addr:housenumber":"3",
    "addr:postcode":"08006",
    "addr:street":"Carrer De Moline",
    "iso:country":"ES",
    "sg:address":"Carrer de Moline, 3",
    "sg:city":"Barcelona",
    "sg:orig_category":"Agencias Y Agentes Comerciales, Representantes",
    "sg:phone":"+34 932 00 61 31",
    "sg:postcode":"08006",
    "sg:province":"Barcelona",
    "wof:name":"Bono Illa Jorge",
    "wof:placetype":"venue"
},
  "geometry": {"coordinates":[2.1478409767,41.398235321],"type":"Point"}
}