{
  "type": "Feature",
  "properties": {
    "addr:full":"Calle de Ortega Y Gasset, 1 Luanco Asturias 33440",
    "addr:housenumber":"1",
    "addr:postcode":"33440",
    "addr:street":"Calle De Ortega Y Gasset;Luanco Asturias",
    "iso:country":"ES",
    "sg:address":"Calle de Ortega Y Gasset, 1",
    "sg:city":"Luanco",
    "sg:orig_category":"Heladeros",
    "sg:phone":"+34 985 88 00 14",
    "sg:postcode":"33440",
    "sg:province":"Asturias",
    "wof:name":"Helados Helio Hermanos S. L.",
    "wof:placetype":"venue"
},
  "geometry": {"coordinates":[-5.7910199165,43.6160736084],"type":"Point"}
}