{
  "type": "Feature",
  "properties": {
    "iso:country":"ES",
    "sg:address":"Rua Santo Domingo, S/n",
    "sg:city":"Ourense",
    "sg:orig_category":"Inform\u00c1tica (estudios, Servicios, Asesor\u00cda, Formaci\u00d3n)",
    "sg:phone":"+34 988 24 23 78",
    "sg:postcode":"32003",
    "sg:province":"Ourense",
    "wof:name":"Publimuz Informatica S.l.",
    "wof:placetype":"venue"
},
  "geometry": {"coordinates":[-7.8631229401,42.3377761841],"type":"Point"}
}