{
  "type": "Feature",
  "properties": {
    "iso:country":"ES",
    "sg:address":"Ctra Alanis-san Nicolas, Km. 0001,2",
    "sg:city":"Constantina",
    "sg:orig_category":"Guarder\u00cdas",
    "sg:phone":"+34 955 88 20 30",
    "sg:postcode":"41450",
    "sg:province":"Sevilla",
    "wof:name":"Asociacion Los Cerezos",
    "wof:placetype":"venue"
},
  "geometry": {"coordinates":[-5.6037464142,37.8877105713],"type":"Point"}
}