{
  "type": "Feature",
  "properties": {
    "iso:country":"ES",
    "sg:address":"Ctra. Rueda, 85",
    "sg:city":"Valladolid",
    "sg:orig_category":"Servicios De Telecomunicaciones",
    "sg:phone":"+34 983 24 46 61",
    "sg:postcode":"47008",
    "sg:province":"Valladolid",
    "wof:name":"Commovile Consulting S.a.",
    "wof:placetype":"venue"
},
  "geometry": {"coordinates":[-4.741768837,41.6221694946],"type":"Point"}
}