{
  "type": "Feature",
  "properties": {
    "addr:full":"Carrer de Taronges, 2 Lloret Mar Girona 17310",
    "addr:housenumber":"2",
    "addr:postcode":"17310",
    "addr:street":"Carrer De Taronges",
    "iso:country":"ES",
    "sg:address":"Carrer de Taronges, 2",
    "sg:city":"Lloret Mar",
    "sg:orig_category":"Ense\u00d1anza: Profesiones Art\u00cdsticas",
    "sg:phone":"+34 972 37 25 05",
    "sg:postcode":"17310",
    "sg:province":"Girona",
    "wof:name":"S.a.l. , S. L.",
    "wof:placetype":"venue"
},
  "geometry": {"coordinates":[2.8497009277,41.6995735168],"type":"Point"}
}