{
  "type": "Feature",
  "properties": {
    "addr:full":"C/ Poeta Miguel Hernandez, 80 Elche Alicante 03201",
    "addr:housenumber":"80",
    "addr:postcode":"03201",
    "addr:street":"C / Poeta Miguel Hernandez",
    "iso:country":"ES",
    "sg:address":"C/ Poeta Miguel Hernandez, 80",
    "sg:city":"Elche",
    "sg:orig_category":"Ingeniero",
    "sg:phone":"+34 966 66 12 00",
    "sg:postcode":"03201",
    "sg:province":"Alicante",
    "wof:name":"Sinatelcom S.l.",
    "wof:placetype":"venue"
},
  "geometry": {"coordinates":[-0.7084900141,38.2646484375],"type":"Point"}
}