{
  "type": "Feature",
  "properties": {
    "iso:country":"ES",
    "sg:address":"Calle de Juan Ramon Jimenez, 7",
    "sg:city":"Martos",
    "sg:orig_category":"Centros Empresariales",
    "sg:phone":"+34 953 55 36 80",
    "sg:postcode":"23600",
    "sg:province":"Ja\u00e9n",
    "wof:name":"Ballesteros Y Perez Consulting S.l.",
    "wof:placetype":"venue"
},
  "geometry": {"coordinates":[-3.9716489315,37.7223052979],"type":"Point"}
}