{
  "type": "Feature",
  "properties": {
    "iso:country":"ES",
    "sg:address":"Calle de Monasterio De Bergondo, 10",
    "sg:city":"Coru\u00d1a",
    "sg:orig_category":"Tiendas De Grano, Frutas Y Legumbres Secas (al Por Menor)",
    "sg:phone":"+34 981 26 29 93",
    "sg:postcode":"15010",
    "sg:province":"La Coru\u00f1a",
    "wof:name":"Pedrosa Vidal Agustina",
    "wof:placetype":"venue"
},
  "geometry": {"coordinates":[-8.4236297607,43.3623466492],"type":"Point"}
}