{
  "type": "Feature",
  "properties": {
    "iso:country":"ES",
    "sg:address":"Jaen, 1",
    "sg:city":"Mijas Costa",
    "sg:orig_category":"Centros Empresariales",
    "sg:phone":"+34 952 93 18 68",
    "sg:postcode":"29649",
    "sg:province":"M\u00e1laga",
    "wof:name":"European Mortages S.l.",
    "wof:placetype":"venue"
},
  "geometry": {"coordinates":[-4.7281570435,36.4979743958],"type":"Point"}
}