{
  "type": "Feature",
  "properties": {
    "addr:full":"P Pol Noain-esquiroz, 13 Noain Navarra 31110",
    "addr:housenumber":"13",
    "addr:postcode":"31110",
    "addr:street":"Noain-Esquiroz",
    "iso:country":"ES",
    "sg:address":"P Pol Noain-esquiroz, 13",
    "sg:city":"Noain",
    "sg:orig_category":"Freidur\u00cdas: Equipos Y Suministros",
    "sg:phone":"+34 948 31 22 71",
    "sg:postcode":"31110",
    "sg:province":"Navarra",
    "wof:name":"Snack Ventures S.a.",
    "wof:placetype":"venue"
},
  "geometry": {"coordinates":[-1.6338239908,42.7598800659],"type":"Point"}
}