{
  "type": "Feature",
  "properties": {
    "addr:full":"Pla\u00c7 Pare Antoni Llinas, Del, 1 Arta Islas Baleares 07570",
    "addr:postcode":"07570",
    "addr:street":"Islas Baleares",
    "iso:country":"ES",
    "sg:address":"Pla\u00c7 Pare Antoni Llinas, Del, 1",
    "sg:city":"Arta",
    "sg:orig_category":"Electrodom\u00c9sticos (al Por Menor)",
    "sg:phone":"+34 971 83 62 98",
    "sg:postcode":"07570",
    "sg:province":"Islas Baleares",
    "wof:name":"Electronica Ayala S.l.",
    "wof:placetype":"venue"
},
  "geometry": {"coordinates":[3.3529589176,39.6940078735],"type":"Point"}
}