{
  "type": "Feature",
  "properties": {
    "addr:full":"Rua Calzada, S/n Cee La Coru\u00f1a 15270",
    "addr:postcode":"15270",
    "addr:street":"Rua Calzada S / N;La",
    "iso:country":"ES",
    "sg:address":"Rua Calzada, S/n",
    "sg:city":"Cee",
    "sg:orig_category":"Asesor\u00cda Sobre Comunicaci\u00d3n De Empresas",
    "sg:phone":"+34 981 74 76 30",
    "sg:postcode":"15270",
    "sg:province":"La Coru\u00f1a",
    "wof:name":"Ceegestion S.c.",
    "wof:placetype":"venue"
},
  "geometry": {"coordinates":[-9.1893787384,42.9575042725],"type":"Point"}
}