{
  "type": "Feature",
  "properties": {
    "addr:full":"Calle de Pozo Amarguillo, 10 Sanlucar De Barrameda C\u00e1diz 11540",
    "addr:housenumber":"10",
    "addr:postcode":"11540",
    "addr:street":"Calle De Pozo Amarguillo;Ca\u0301Diz",
    "iso:country":"ES",
    "sg:address":"Calle de Pozo Amarguillo, 10",
    "sg:city":"Sanlucar De Barrameda",
    "sg:orig_category":"Muebles Y Accesorios Para Cocinas Y Cuartos De Ba\u00d1o (al Por Menor)",
    "sg:phone":"+34 956 36 26 58",
    "sg:postcode":"11540",
    "sg:province":"C\u00e1diz",
    "wof:name":"Radiotelevision Y Muebles Oliva S.l.l",
    "wof:placetype":"venue"
},
  "geometry": {"coordinates":[-6.353181839,36.7733306885],"type":"Point"}
}