{
  "type": "Feature",
  "properties": {
    "iso:country":"ES",
    "sg:address":"Calle de Arco De Avila, 1",
    "sg:city":"Arevalo",
    "sg:orig_category":"Molduras, Junquillos, Listones Y Molduras Perforadas",
    "sg:phone":"+34 920 30 19 05",
    "sg:postcode":"05200",
    "sg:province":"\u00c1vila",
    "wof:name":"Roldan Cisneros Luis Alfonso",
    "wof:placetype":"venue"
},
  "geometry": {"coordinates":[-4.7187261581,41.0610961914],"type":"Point"}
}