{
  "type": "Feature",
  "properties": {
    "iso:country":"ES",
    "sg:address":"Calle de Rodriguez Del Valle, 22",
    "sg:city":"Le\u00f3n",
    "sg:orig_category":"Doctores En Medicina",
    "sg:phone":"+34 987 22 32 52",
    "sg:postcode":"24002",
    "sg:province":"Le\u00f3n",
    "wof:name":"Urdiales Urdiales Javier",
    "wof:placetype":"venue"
},
  "geometry": {"coordinates":[-5.5785431862,42.6009368896],"type":"Point"}
}