{
  "type": "Feature",
  "properties": {
    "iso:country":"ES",
    "sg:address":"Carr Major, 43",
    "sg:city":"Cervera",
    "sg:orig_category":"M\u00c9dicos: Ginecolog\u00cda Y Obstetricia",
    "sg:phone":"+34 973 53 19 22",
    "sg:postcode":"25200",
    "sg:province":"Lleida",
    "wof:name":"Pique Canal Pilar",
    "wof:placetype":"venue"
},
  "geometry": {"coordinates":[1.2716120481,41.6667556763],"type":"Point"}
}