{
  "type": "Feature",
  "properties": {
    "iso:country":"ES",
    "sg:address":"Calle de Gran Via De Jose Antonio Agirre Y Lekube, 43",
    "sg:city":"Sestao",
    "sg:orig_category":"Cajas De Ahorro",
    "sg:phone":"+34 944 72 04 95",
    "sg:postcode":"48910",
    "sg:province":"Vizcaya",
    "wof:name":"Caja Laboral Popular",
    "wof:placetype":"venue"
},
  "geometry": {"coordinates":[-3.007666111,43.3094024658],"type":"Point"}
}