{
  "type": "Feature",
  "properties": {
    "addr:full":"Calle de Molinell, 4 Valencia Valencia 46010",
    "addr:housenumber":"4",
    "addr:postcode":"46010",
    "addr:street":"Calle De Molinell",
    "iso:country":"ES",
    "sg:address":"Calle de Molinell, 4",
    "sg:city":"Valencia",
    "sg:orig_category":"Artes Gr\u00c1ficas, Artes Pl\u00c1sticas (curso)",
    "sg:phone":"+34 963 89 17 48",
    "sg:postcode":"46010",
    "sg:province":"Valencia",
    "wof:name":"Redon Bastida Jose Maria",
    "wof:placetype":"venue"
},
  "geometry": {"coordinates":[-0.3700250089,39.4849586487],"type":"Point"}
}