{
  "type": "Feature",
  "properties": {
    "addr:full":"Epidauro, 26 Entremontes Madrid 28230",
    "addr:housenumber":"26",
    "addr:postcode":"28230",
    "addr:street":"Epidauro",
    "iso:country":"ES",
    "sg:address":"Epidauro, 26",
    "sg:city":"Entremontes",
    "sg:orig_category":"Inform\u00c1tica: Consultores",
    "sg:phone":"+34 916 03 21 57",
    "sg:postcode":"28230",
    "sg:province":"Madrid",
    "wof:name":"Ingeninsa;s.a.",
    "wof:placetype":"venue"
},
  "geometry": {"coordinates":[-3.7057700157,40.42029953],"type":"Point"}
}