{
  "type": "Feature",
  "properties": {
    "iso:country":"ES",
    "sg:address":"Calle de Genil, 7",
    "sg:city":"Fuentes De Andalucia",
    "sg:orig_category":"Bosques (trabajos, Asesor\u00cda, Gesti\u00d3n)",
    "sg:phone":"+34 954 83 78 06",
    "sg:postcode":"41420",
    "sg:province":"Sevilla",
    "wof:name":"Garcia Toro Siglo Xxi Sl",
    "wof:placetype":"venue"
},
  "geometry": {"coordinates":[-5.3472161293,37.4580726624],"type":"Point"}
}