{
  "type": "Feature",
  "properties": {
    "addr:full":"Calle de Parras Baja, 15 Torredonjimeno Ja\u00e9n 23650",
    "addr:housenumber":"15",
    "addr:postcode":"23650",
    "addr:street":"Calle De Parras Baja",
    "iso:country":"ES",
    "sg:address":"Calle de Parras Baja, 15",
    "sg:city":"Torredonjimeno",
    "sg:orig_category":"Institutos De Belleza",
    "sg:phone":"+34 953 57 21 26",
    "sg:postcode":"23650",
    "sg:province":"Ja\u00e9n",
    "wof:name":"Arrabal Sanchez Maria Josefa",
    "wof:placetype":"venue"
},
  "geometry": {"coordinates":[-4.0899910927,37.8016700745],"type":"Point"}
}