{
  "type": "Feature",
  "properties": {
    "addr:full":"Pl Polvoron, S/n Moron Frontera Sevilla 41530",
    "addr:housenumber":"s",
    "addr:postcode":"41530",
    "addr:street":"Pl Polvoron;/ N Moron",
    "iso:country":"ES",
    "sg:address":"Pl Polvoron, S/n",
    "sg:city":"Moron Frontera",
    "sg:orig_category":"Polideportivos",
    "sg:phone":"+34 954 85 22 36",
    "sg:postcode":"41530",
    "sg:province":"Sevilla",
    "wof:name":"Patronato Municipal De Deportes De Moron De La Frontera",
    "wof:placetype":"venue"
},
  "geometry": {"coordinates":[-5.4528231621,37.1294212341],"type":"Point"}
}