{
  "type": "Feature",
  "properties": {
    "addr:full":"Carrer de 31 De Desembre, 21 Palma Islas Baleares 07003",
    "addr:housenumber":"31;21",
    "addr:postcode":"07003",
    "addr:street":"Carrer De;Desembre",
    "iso:country":"ES",
    "sg:address":"Carrer de 31 De Desembre, 21",
    "sg:city":"Palma",
    "sg:orig_category":"Agencias De Viajes",
    "sg:phone":"+34 971 20 27 11",
    "sg:postcode":"07003",
    "sg:province":"Islas Baleares",
    "sg:website":"www.halconviajes.com",
    "wof:name":"Viajes Halcon S.a.",
    "wof:placetype":"venue"
},
  "geometry": {"coordinates":[2.6522250175,39.5796661377],"type":"Point"}
}