{
  "type": "Feature",
  "properties": {
    "addr:full":"Pol Ind Nevero, S/n Badajoz Badajoz 06006",
    "addr:housenumber":"s",
    "addr:postcode":"06006",
    "addr:street":"/ N",
    "iso:country":"ES",
    "sg:address":"Pol Ind Nevero, S/n",
    "sg:city":"Badajoz",
    "sg:orig_category":"Fabricaci\u00d3n De Material Y Sistemas De Se\u00d1alizaci\u00d3n De Carreteras, Urbanos Y De Obras",
    "sg:phone":"+34 924 27 37 09",
    "sg:postcode":"06006",
    "sg:province":"Badajoz",
    "wof:name":"Se\u00f1alizaciones Extreme\u00f1as S. A.",
    "wof:placetype":"venue"
},
  "geometry": {"coordinates":[-7.0317192078,38.9165992737],"type":"Point"}
}