{
  "type": "Feature",
  "properties": {
    "addr:full":"Carrer de Valldonzella, 7 Barcelona Barcelona 08001",
    "addr:housenumber":"7",
    "addr:postcode":"08001",
    "addr:street":"Carrer De Valldonzella",
    "iso:country":"ES",
    "sg:address":"Carrer de Valldonzella, 7",
    "sg:city":"Barcelona",
    "sg:orig_category":"Librer\u00cdas",
    "sg:phone":"+34 934 12 33 88",
    "sg:postcode":"08001",
    "sg:province":"Barcelona",
    "wof:name":"Libreria Medios S.c.c.ltda.",
    "wof:placetype":"venue"
},
  "geometry": {"coordinates":[2.1665871143,41.3846168518],"type":"Point"}
}