{
  "type": "Feature",
  "properties": {
    "iso:country":"ES",
    "sg:address":"Pase Maria Droc, 13",
    "sg:city":"Madrid",
    "sg:orig_category":"Ense\u00d1anza, Formaci\u00d3n Profesional: Aprendizaje",
    "sg:phone":"+34 915 05 09 71",
    "sg:postcode":"28021",
    "sg:province":"Madrid",
    "wof:name":"Empresa Municipal De La Vivienda De Madr",
    "wof:placetype":"venue"
},
  "geometry": {"coordinates":[-3.6923298836,40.3445396423],"type":"Point"}
}