{
  "type": "Feature",
  "properties": {
    "addr:full":"Cmno Pesqueruela, Km. 0001,5 Simancas Valladolid 47130",
    "addr:postcode":"47130",
    "addr:street":"Cmno Pesqueruela Km. 0001,5",
    "iso:country":"ES",
    "sg:address":"Cmno Pesqueruela, Km. 0001,5",
    "sg:city":"Simancas",
    "sg:classifiers":[
        {
            "category":"Sports & Exercise",
            "subcategory":"Golf",
            "type":"Entertainment"
        }
    ],
    "sg:phone":"+34 983 59 05 11",
    "sg:postcode":"47130",
    "sg:province":"Valladolid",
    "sg:tags":[
        "y",
        "de",
        "campos",
        "clases"
    ],
    "wof:name":"Golf Entrepinos S.a.",
    "wof:placetype":"venue"
},
  "geometry": {"coordinates":[-4.8235812187,41.5907974243],"type":"Point"}
}