{
  "type": "Feature",
  "properties": {
    "addr:full":"Calle de Jose De Echegaray, 7 Puerto De Sardina Las Palmas 35469",
    "addr:housenumber":"7",
    "addr:postcode":"35469",
    "addr:street":"Calle De Jose De Echegaray",
    "iso:country":"ES",
    "sg:address":"Calle de Jose De Echegaray, 7",
    "sg:city":"Puerto De Sardina",
    "sg:orig_category":"Mudanzas",
    "sg:phone":"+34 928 55 02 50",
    "sg:postcode":"35469",
    "sg:province":"Las Palmas",
    "sg:website":"www.mudanzasmoreno.com",
    "wof:name":"Mudanzas Moreno Hernandez S.l.",
    "wof:placetype":"venue"
},
  "geometry": {"coordinates":[-15.4663276672,27.8457489014],"type":"Point"}
}