{
  "type": "Feature",
  "properties": {
    "iso:country":"ES",
    "sg:address":"Carrer de Trullols, 13",
    "sg:city":"Barcelona",
    "sg:orig_category":"Cajas Y Embalajes De Pl\u00c1stico",
    "sg:phone":"+34 932 54 06 09",
    "sg:postcode":"08035",
    "sg:province":"Barcelona",
    "wof:name":"J Y E Castella Llorca S.l.",
    "wof:placetype":"venue"
},
  "geometry": {"coordinates":[2.1376230717,41.4203491211],"type":"Point"}
}