{
  "type": "Feature",
  "properties": {
    "iso:country":"ES",
    "sg:address":"Luga Parada (a), S/n",
    "sg:city":"Parada",
    "sg:orig_category":"Promotores Constructores",
    "sg:phone":"+34 988 38 21 84",
    "sg:postcode":"32930",
    "sg:province":"Ourense",
    "wof:name":"Munobras S.l.",
    "wof:placetype":"venue"
},
  "geometry": {"coordinates":[-7.9522171021,42.3144187927],"type":"Point"}
}