{
  "type": "Feature",
  "properties": {
    "addr:full":"Plaz San Francisco, 2 Jaen Ja\u00e9n 23003",
    "addr:housenumber":"2;jae\u0301n",
    "addr:postcode":"23003",
    "addr:street":"Plaz San Francisco",
    "iso:country":"ES",
    "sg:address":"Plaz San Francisco, 2",
    "sg:city":"Jaen",
    "sg:orig_category":"Fachadas",
    "sg:phone":"+34 953 27 45 84",
    "sg:postcode":"23003",
    "sg:province":"Ja\u00e9n",
    "wof:name":"Alta Tecnologia En Control Solar S.l.",
    "wof:placetype":"venue"
},
  "geometry": {"coordinates":[-3.7485873699,37.7440452576],"type":"Point"}
}