{
  "type": "Feature",
  "properties": {
    "addr:full":"Poli Mugitegi-a, 24 Urretxu Guip\u00f9zcoa 20700",
    "addr:housenumber":"24",
    "addr:postcode":"20700",
    "addr:street":"Mugitegi-A;Guipu\u0300Zcoa",
    "iso:country":"ES",
    "sg:address":"Poli Mugitegi-a, 24",
    "sg:city":"Urretxu",
    "sg:orig_category":"Delegados, Agentes De Tr\u00c1nsito, Auxiliares De Transporte Internacional",
    "sg:phone":"+34 943 72 41 16",
    "sg:postcode":"20700",
    "sg:province":"Guip\u00f9zcoa",
    "wof:name":"Transportes Goiherri, S.l.",
    "wof:placetype":"venue"
},
  "geometry": {"coordinates":[-2.3134770393,43.086730957],"type":"Point"}
}