{
  "type": "Feature",
  "properties": {
    "iso:country":"ES",
    "sg:address":"Calle de Ataulfo Argenta, 9",
    "sg:city":"Castro Urdiales",
    "sg:orig_category":"Centros Empresariales",
    "sg:phone":"+34 942 87 13 88",
    "sg:postcode":"39700",
    "sg:province":"Cantabria",
    "wof:name":"Gestion Integral De Servicios Comunitarios S.l.",
    "wof:placetype":"venue"
},
  "geometry": {"coordinates":[-3.2079179287,43.3721466064],"type":"Point"}
}