{
  "type": "Feature",
  "properties": {
    "addr:full":"Carrer de Comte D'urgell, 41 Barcelona Barcelona 08011",
    "addr:housenumber":"41",
    "addr:postcode":"08011",
    "addr:street":"Carrer De Comte D'Urgell",
    "iso:country":"ES",
    "sg:address":"Carrer de Comte D'urgell, 41",
    "sg:city":"Barcelona",
    "sg:orig_category":"Muebles, Minoristas",
    "sg:phone":"+34 933 25 09 74",
    "sg:postcode":"08011",
    "sg:province":"Barcelona",
    "sg:website":"www.masterpiel.com",
    "wof:name":"Master Piel Confort S.a.",
    "wof:placetype":"venue"
},
  "geometry": {"coordinates":[2.1598653793,41.3811378479],"type":"Point"}
}