{
  "type": "Feature",
  "properties": {
    "addr:full":"Potri\u00f1a, S/n Pepino Toledo 45638",
    "addr:housenumber":"/ n",
    "addr:postcode":"45638",
    "addr:street":"Potrin\u0303A S",
    "iso:country":"ES",
    "sg:address":"Potri\u00f1a, S/n",
    "sg:city":"Pepino",
    "sg:orig_category":"Ebanister\u00cda",
    "sg:phone":"+34 925 70 97 02",
    "sg:postcode":"45638",
    "sg:province":"Toledo",
    "sg:website":"www.virgendelprado.com",
    "wof:name":"Fabrica De Muebles Virgen Del Prado S.l.",
    "wof:placetype":"venue"
},
  "geometry": {"coordinates":[-4.803000927,40.0316200256],"type":"Point"}
}