{
  "type": "Feature",
  "properties": {
    "addr:full":"Camino De Roturas, S/n Robledollano C\u00e1ceres 10371",
    "addr:housenumber":"s / n",
    "addr:postcode":"10371",
    "addr:street":"Camino De Roturas;Ca\u0301Ceres",
    "iso:country":"ES",
    "sg:address":"Camino De Roturas, S/n",
    "sg:city":"Robledollano",
    "sg:orig_category":"Producci\u00d3n, Venta De Productos De Agricultura Biol\u00d3gica",
    "sg:phone":"+34 927 19 50 31",
    "sg:postcode":"10371",
    "sg:province":"C\u00e1ceres",
    "wof:name":"Ciste Extremadura S.l.",
    "wof:placetype":"venue"
},
  "geometry": {"coordinates":[-5.5090088844,39.6091308594],"type":"Point"}
}