{
  "type": "Feature",
  "properties": {
    "iso:country":"ES",
    "sg:address":"Calle de Villegas, 5",
    "sg:city":"Melilla",
    "sg:orig_category":"Sociedades, Compa\u00d1\u00cdas Aseguradoras",
    "sg:phone":"+34 952 67 58 55",
    "sg:postcode":"52004",
    "sg:province":"Melilla",
    "wof:name":"Ocaso S.a. Compa\u00d1ia De Seguros Y Reaseguros",
    "wof:placetype":"venue"
},
  "geometry": {"coordinates":[-2.9406208992,35.2907676697],"type":"Point"}
}