{
  "type": "Feature",
  "properties": {
    "addr:full":"Calle de Don Jaime I, 19 Zaragoza Zaragoza 50003",
    "addr:housenumber":"19",
    "addr:postcode":"50003",
    "addr:street":"Calle De Don Jaime I",
    "iso:country":"ES",
    "sg:address":"Calle de Don Jaime I, 19",
    "sg:city":"Zaragoza",
    "sg:orig_category":"Abogados",
    "sg:phone":"+34 976 29 99 66",
    "sg:postcode":"50003",
    "sg:province":"Zaragoza",
    "wof:name":"Parra Navarro Alvaro",
    "wof:placetype":"venue"
},
  "geometry": {"coordinates":[-0.8787640929,41.6529350281],"type":"Point"}
}