{
  "type": "Feature",
  "properties": {
    "iso:country":"ES",
    "sg:address":"Calle de Alamos (los), S/n",
    "sg:city":"Sese\u00f1a",
    "sg:orig_category":"Mec\u00c1nico Del Autom\u00d3vil",
    "sg:phone":"+34 918 95 78 86",
    "sg:postcode":"45223",
    "sg:province":"Toledo",
    "wof:name":"Autos Sese\u00f1a S.l.",
    "wof:placetype":"venue"
},
  "geometry": {"coordinates":[-3.6947510242,40.1014251709],"type":"Point"}
}