{
  "type": "Feature",
  "properties": {
    "iso:country":"ES",
    "sg:address":"Avda Espa\u00d1a, 41",
    "sg:city":"Majadahonda",
    "sg:orig_category":"Ingenier\u00cda, Centros De Estudios (diversos)",
    "sg:phone":"+34 916 38 68 04",
    "sg:postcode":"28220",
    "sg:province":"Madrid",
    "wof:name":"Interprofessional Project Consulting S.l.",
    "wof:placetype":"venue"
},
  "geometry": {"coordinates":[-3.8673520088,40.4688034058],"type":"Point"}
}