{
  "type": "Feature",
  "properties": {
    "addr:full":"Av. C. Sotelo, 127 Muros A Coru\u00f1a 15250",
    "addr:housenumber":"127",
    "addr:postcode":"15250",
    "addr:street":"Av. C. Sotelo;A Corun\u0303A",
    "iso:country":"ES",
    "sg:address":"Av. C. Sotelo, 127",
    "sg:city":"Muros",
    "sg:classifiers":[
        {
            "category":"Taxi",
            "type":"Transportation"
        }
    ],
    "sg:phone":"+34 981 82 60 35",
    "sg:postcode":"15250",
    "sg:province":"A Coru\u00f1a",
    "wof:name":"Santiago Formoso Domingo Antonio",
    "wof:placetype":"venue"
},
  "geometry": {"coordinates":[-9.0596790314,42.7772331238],"type":"Point"}
}