{
  "type": "Feature",
  "properties": {
    "addr:full":"Arroyo Del Moro, 1 Cordoba C\u00f3rdoba 14011",
    "addr:housenumber":"1",
    "addr:postcode":"14011",
    "addr:street":"Arroyo Del Moro;Co\u0301Rdoba",
    "iso:country":"ES",
    "sg:address":"Arroyo Del Moro, 1",
    "sg:city":"Cordoba",
    "sg:orig_category":"Cajas De Ahorro",
    "sg:phone":"+34 957 01 41 20",
    "sg:postcode":"14011",
    "sg:province":"C\u00f3rdoba",
    "sg:website":"www.elmonte.es",
    "wof:name":"Monte De Piedad Y Caja De Ahorros De Huelva Y Sevilla",
    "wof:placetype":"venue"
},
  "geometry": {"coordinates":[-4.8999910355,37.9277877808],"type":"Point"}
}