{
  "type": "Feature",
  "properties": {
    "addr:full":"Avda Navarra, 15 Coru\u00d1a La Coru\u00f1a 15002",
    "addr:housenumber":"15",
    "addr:postcode":"15002",
    "addr:street":"Avda Navarra;La Corun\u0303A",
    "iso:country":"ES",
    "sg:address":"Avda Navarra, 15",
    "sg:city":"Coru\u00d1a",
    "sg:orig_category":"Agencias Y Agentes Comerciales, Representantes",
    "sg:phone":"+34 981 20 17 55",
    "sg:postcode":"15002",
    "sg:province":"La Coru\u00f1a",
    "wof:name":"Garrido Eiranova Maria Luisa",
    "wof:placetype":"venue"
},
  "geometry": {"coordinates":[-8.3990364075,43.379940033],"type":"Point"}
}