{
  "type": "Feature",
  "properties": {
    "addr:full":"Carrer de Prat De La Riba, 4 Rubi Barcelona 08191",
    "addr:housenumber":"4",
    "addr:postcode":"08191",
    "addr:street":"Carrer De Prat De La Riba",
    "iso:country":"ES",
    "sg:address":"Carrer de Prat De La Riba, 4",
    "sg:city":"Rubi",
    "sg:orig_category":"Seguridad Social",
    "sg:phone":"+34 935 86 00 88",
    "sg:postcode":"08191",
    "sg:province":"Barcelona",
    "wof:name":"Sat Mutua De Accidentes",
    "wof:placetype":"venue"
},
  "geometry": {"coordinates":[2.0314970016,41.4941673279],"type":"Point"}
}