{
  "type": "Feature",
  "properties": {
    "addr:full":"C/ Sagrada Familia, 6 Alcoi Alicante 03804",
    "addr:housenumber":"6",
    "addr:postcode":"03804",
    "addr:street":"C / Sagrada Familia",
    "iso:country":"ES",
    "sg:address":"C/ Sagrada Familia, 6",
    "sg:city":"Alcoi",
    "sg:orig_category":"Tapicer\u00cdas",
    "sg:phone":"+34 966 52 12 16",
    "sg:postcode":"03804",
    "sg:province":"Alicante",
    "wof:name":"La Tapiceria C.b.",
    "wof:placetype":"venue"
},
  "geometry": {"coordinates":[-0.4716329873,38.7079963684],"type":"Point"}
}