{
  "type": "Feature",
  "properties": {
    "addr:full":"Avda Tirajana (de), 15 Playa Del Ingles Las Palmas 35100",
    "addr:housenumber":"15",
    "addr:postcode":"35100",
    "addr:street":"Avda Tirajana De",
    "iso:country":"ES",
    "sg:address":"Avda Tirajana (de), 15",
    "sg:city":"Playa Del Ingles",
    "sg:orig_category":"Molduras, Junquillos, Listones Y Molduras Perforadas",
    "sg:phone":"+34 928 76 49 18",
    "sg:postcode":"35100",
    "sg:province":"Las Palmas",
    "wof:name":"Benitez Perdomo Nicolas",
    "wof:placetype":"venue"
},
  "geometry": {"coordinates":[-15.5787067413,27.7560749054],"type":"Point"}
}