{
  "type": "Feature",
  "properties": {
    "iso:country":"ES",
    "sg:address":"Raval Del Castell, 4",
    "sg:city":"Valls",
    "sg:orig_category":"Perfumer\u00cda, Art\u00cdculos De Ba\u00d1o (fabricaci\u00d3n, Al Por Mayor)",
    "sg:phone":"+34 977 60 54 50",
    "sg:postcode":"43800",
    "sg:province":"Tarragona",
    "wof:name":"Muntala Rofes Joan Maria",
    "wof:placetype":"venue"
},
  "geometry": {"coordinates":[1.2600419521,41.2991676331],"type":"Point"}
}