{
  "type": "Feature",
  "properties": {
    "addr:full":"Calle de Sor Angela De La Cruz, 13 Coria Rio Sevilla 41100",
    "addr:housenumber":"13",
    "addr:postcode":"41100",
    "addr:street":"Calle De Sor Angela De La Cruz;Rio Sevilla",
    "iso:country":"ES",
    "sg:address":"Calle de Sor Angela De La Cruz, 13",
    "sg:city":"Coria Rio",
    "sg:orig_category":"Quincaller\u00cda (al Por Menor)",
    "sg:phone":"+34 954 77 34 80",
    "sg:postcode":"41100",
    "sg:province":"Sevilla",
    "wof:name":"Ferreteria El Mirador, S.l.",
    "wof:placetype":"venue"
},
  "geometry": {"coordinates":[-6.0545802116,37.2869949341],"type":"Point"}
}