{
  "type": "Feature",
  "properties": {
    "iso:country":"ES",
    "sg:address":"Jose Antonio Plaza De, 4",
    "sg:city":"Motril",
    "sg:orig_category":"Asesor\u00cda De Formaci\u00d3n Y Gesti\u00d3n De Personal",
    "sg:phone":"+34 958 60 18 19",
    "sg:postcode":"18600",
    "sg:province":"Granada",
    "wof:name":"Lopez-puertas Ruiz-coello Jose Manuel",
    "wof:placetype":"venue"
},
  "geometry": {"coordinates":[-3.5183711052,36.7548027039],"type":"Point"}
}