{
  "type": "Feature",
  "properties": {
    "addr:full":"Calle de Eguiluz Antonio Medico, 19 Bilbao Vizcaya 48004",
    "addr:housenumber":"19",
    "addr:postcode":"48004",
    "addr:street":"Calle De Eguiluz Antonio Medico",
    "iso:country":"ES",
    "sg:address":"Calle de Eguiluz Antonio Medico, 19",
    "sg:city":"Bilbao",
    "sg:orig_category":"Art\u00cdculos De Limpieza Y De Cocina (fabricaci\u00d3n, Al Por Mayor)",
    "sg:phone":"+34 944 12 55 88",
    "sg:postcode":"48004",
    "sg:province":"Vizcaya",
    "sg:website":"www.grupocrisol.com",
    "wof:name":"Suministros Hogar Hotel S.a.",
    "wof:placetype":"venue"
},
  "geometry": {"coordinates":[-2.9118030071,43.2507362366],"type":"Point"}
}