{
  "type": "Feature",
  "properties": {
    "addr:full":"Avda Monforte De Lemos, 133 Madrid Madrid 28029",
    "addr:housenumber":"133",
    "addr:postcode":"28029",
    "addr:street":"Avda Monforte De Lemos",
    "iso:country":"ES",
    "sg:address":"Avda Monforte De Lemos, 133",
    "sg:city":"Madrid",
    "sg:orig_category":"Postigos, Persianas Y Celos\u00cdas",
    "sg:phone":"+34 917 39 40 13",
    "sg:postcode":"28029",
    "sg:province":"Madrid",
    "wof:name":"Delbal Y Rodrigo S.l.",
    "wof:placetype":"venue"
},
  "geometry": {"coordinates":[-3.7117760181,40.4776153564],"type":"Point"}
}