{
  "type": "Feature",
  "properties": {
    "addr:full":"Calle de Tornadizos, 45 Avila \u00c1vila 05005",
    "addr:housenumber":"45",
    "addr:postcode":"05005",
    "addr:street":"Calle De Tornadizos;A\u0301Vila",
    "iso:country":"ES",
    "sg:address":"Calle de Tornadizos, 45",
    "sg:city":"Avila",
    "sg:orig_category":"Pescader\u00cdas (al Por Menor)",
    "sg:phone":"+34 920 22 83 17",
    "sg:postcode":"05005",
    "sg:province":"\u00c1vila",
    "wof:name":"Arevalo Hernandez Luis",
    "wof:placetype":"venue"
},
  "geometry": {"coordinates":[-4.6939234734,40.6625328064],"type":"Point"}
}