{
  "type": "Feature",
  "properties": {
    "addr:full":"Calle de Virgen De La Victoria, 11 Sevilla Sevilla 41011",
    "addr:housenumber":"11",
    "addr:postcode":"41011",
    "addr:street":"Calle De Virgen De La Victoria",
    "iso:country":"ES",
    "sg:address":"Calle de Virgen De La Victoria, 11",
    "sg:city":"Sevilla",
    "sg:orig_category":"Lencer\u00cda Femenina, Corseter\u00cda, Trajes De Ba\u00d1o (al Por Menor)",
    "sg:phone":"+34 954 27 47 25",
    "sg:postcode":"41011",
    "sg:province":"Sevilla",
    "wof:name":"Riba Bassons Monserrat",
    "wof:placetype":"venue"
},
  "geometry": {"coordinates":[-5.9967122078,37.3724327087],"type":"Point"}
}