{
  "type": "Feature",
  "properties": {
    "iso:country":"ES",
    "sg:address":"Avda Carmen Morcillo, 61",
    "sg:city":"Gojar",
    "sg:orig_category":"Mec\u00c1nico Del Autom\u00d3vil",
    "sg:phone":"+34 958 50 78 32",
    "sg:postcode":"18150",
    "sg:province":"Granada",
    "wof:name":"Fernandez Fernandez Francisco Javier",
    "wof:placetype":"venue"
},
  "geometry": {"coordinates":[-3.6034760475,37.0999298096],"type":"Point"}
}