{
  "type": "Feature",
  "properties": {
    "iso:country":"ES",
    "sg:address":"Avda Federico Anaya, 12",
    "sg:city":"Salamanca",
    "sg:orig_category":"Mercer\u00cda, Lencer\u00cda (al Por Menor)",
    "sg:phone":"+34 923 22 36 37",
    "sg:postcode":"37004",
    "sg:province":"Salamanca",
    "wof:name":"Cuadrado Revesado Purificacion",
    "wof:placetype":"venue"
},
  "geometry": {"coordinates":[-5.6574010849,40.9721298218],"type":"Point"}
}