{
  "type": "Feature",
  "properties": {
    "addr:full":"Sant Mart\u00ed, 5 Carme Barcelona 08787",
    "addr:housenumber":"5",
    "addr:postcode":"08787",
    "addr:street":"Sant Marti\u0301",
    "iso:country":"ES",
    "sg:address":"Sant Mart\u00ed, 5",
    "sg:city":"Carme",
    "sg:orig_category":"\u00c1rboles Frutales",
    "sg:phone":"+34 938 08 02 35",
    "sg:postcode":"08787",
    "sg:province":"Barcelona",
    "wof:name":"Tree Surgeons S.l.",
    "wof:placetype":"venue"
},
  "geometry": {"coordinates":[1.6210589409,41.5309181213],"type":"Point"}
}