{
  "type": "Feature",
  "properties": {
    "addr:full":"Polig.industrial Azitain, 3 Eibar Guip\u00f9zcoa 20600",
    "addr:housenumber":"3",
    "addr:postcode":"20600",
    "addr:street":"Azitain;Guipu\u0300Zcoa",
    "iso:country":"ES",
    "sg:address":"Polig.industrial Azitain, 3",
    "sg:city":"Eibar",
    "sg:orig_category":"Ingeniero",
    "sg:phone":"+34 943 12 08 78",
    "sg:postcode":"20600",
    "sg:province":"Guip\u00f9zcoa",
    "sg:website":"www.inprone.com",
    "wof:name":"Alfonso Goy S. L.",
    "wof:placetype":"venue"
},
  "geometry": {"coordinates":[-2.4884390831,43.1800117493],"type":"Point"}
}