{
  "type": "Feature",
  "properties": {
    "addr:full":"Calle de Viriato, 3 Madrid Madrid 28010",
    "addr:housenumber":"3",
    "addr:postcode":"28010",
    "addr:street":"Calle De Viriato",
    "iso:country":"ES",
    "sg:address":"Calle de Viriato, 3",
    "sg:city":"Madrid",
    "sg:orig_category":"Loter\u00cda Y T\u00d3mbola",
    "sg:phone":"+34 914 45 51 24",
    "sg:postcode":"28010",
    "sg:province":"Madrid",
    "wof:name":"Escobar Gonzalez Antonia",
    "wof:placetype":"venue"
},
  "geometry": {"coordinates":[-3.7039399147,40.4361495972],"type":"Point"}
}