{
  "type": "Feature",
  "properties": {
    "iso:country":"ES",
    "sg:address":"Avda Paular (del), 11",
    "sg:city":"Rascafria",
    "sg:orig_category":"Bazares, Art\u00cdculos De Limpieza Y De Cocina (al Por Menor)",
    "sg:phone":"+34 918 69 12 98",
    "sg:postcode":"28740",
    "sg:province":"Madrid",
    "wof:name":"Martin De Prados Maria Isabel",
    "wof:placetype":"venue"
},
  "geometry": {"coordinates":[-3.8791060448,40.9034423828],"type":"Point"}
}