{
  "type": "Feature",
  "properties": {
    "iso:country":"ES",
    "sg:address":"Calle de Sp Virgen De Loreto, 3",
    "sg:city":"San Pedro Alcantara",
    "sg:orig_category":"Supermercados Y Hipermercados",
    "sg:phone":"+34 952 78 30 68",
    "sg:postcode":"29670",
    "sg:province":"M\u00e1laga",
    "wof:name":"Ecoserca S.l.",
    "wof:placetype":"venue"
},
  "geometry": {"coordinates":[-4.9922981262,36.4890136719],"type":"Point"}
}