{
  "type": "Feature",
  "properties": {
    "addr:full":"Pol. Macua, 12 Aviles Asturias 33490",
    "addr:housenumber":"12",
    "addr:postcode":"33490",
    "iso:country":"ES",
    "sg:address":"Pol. Macua, 12",
    "sg:city":"Aviles",
    "sg:orig_category":"Ingenier\u00cda, Centros De Estudios (diversos)",
    "sg:phone":"+34 985 54 76 10",
    "sg:postcode":"33490",
    "sg:province":"Asturias",
    "wof:name":"Construcciones Icma S.a.u.",
    "wof:placetype":"venue"
},
  "geometry": {"coordinates":[-5.894133091,43.5974273682],"type":"Point"}
}