{
  "type": "Feature",
  "properties": {
    "iso:country":"ES",
    "sg:address":"Calle de Salvador Ferrandis Luna, 60",
    "sg:city":"Valencia",
    "sg:orig_category":"Peluqueros: De Se\u00d1oras",
    "sg:phone":"+34 963 50 27 70",
    "sg:postcode":"46018",
    "sg:province":"Valencia",
    "wof:name":"Pizarro Perez Florentina",
    "wof:placetype":"venue"
},
  "geometry": {"coordinates":[-0.3982880116,39.4709320068],"type":"Point"}
}