{
  "type": "Feature",
  "properties": {
    "iso:country":"ES",
    "sg:address":"Avda Estacion, 71",
    "sg:city":"Torrijos",
    "sg:orig_category":"Farmacias",
    "sg:phone":"+34 925 77 14 47",
    "sg:postcode":"45500",
    "sg:province":"Toledo",
    "wof:name":"Gomez Lopez Maria Soledad",
    "wof:placetype":"venue"
},
  "geometry": {"coordinates":[-4.2824549675,39.9808998108],"type":"Point"}
}