{
  "type": "Feature",
  "properties": {
    "addr:full":"Calle de Legion Vii, 3 Le\u00f3n Le\u00f3n 24003",
    "addr:housenumber":"3",
    "addr:postcode":"24003",
    "addr:street":"Calle De Legion Vii;Leo\u0301N",
    "iso:country":"ES",
    "sg:address":"Calle de Legion Vii, 3",
    "sg:city":"Le\u00f3n",
    "sg:orig_category":"M\u00c1quinas De Coser Y De Hacer Punto (al Por Mayor)",
    "sg:phone":"+34 987 23 32 60",
    "sg:postcode":"24003",
    "sg:province":"Le\u00f3n",
    "wof:name":"Martinez Lopez Gaspar",
    "wof:placetype":"venue"
},
  "geometry": {"coordinates":[-5.5710940361,42.5977592468],"type":"Point"}
}