{
  "type": "Feature",
  "properties": {
    "iso:country":"ES",
    "sg:address":"Plaza Ronda Sur, 131",
    "sg:city":"Losar Vera",
    "sg:orig_category":"Bazares, Art\u00cdculos De Limpieza Y De Cocina (al Por Menor)",
    "sg:phone":"+34 927 57 01 23",
    "sg:postcode":"10460",
    "sg:province":"C\u00e1ceres",
    "wof:name":"Diaz Sanchez Monserrat",
    "wof:placetype":"venue"
},
  "geometry": {"coordinates":[-5.6094250679,40.1218147278],"type":"Point"}
}