{
  "type": "Feature",
  "properties": {
    "iso:country":"ES",
    "sg:address":"Calle de Adolfo Diaz Ambrona, 17",
    "sg:city":"Villanueva Serena",
    "sg:orig_category":"Ropa De Hogar (al Por Menor)",
    "sg:phone":"+34 924 84 06 46",
    "sg:postcode":"06700",
    "sg:province":"Badajoz",
    "wof:name":"Bermejo Barco Francisco",
    "wof:placetype":"venue"
},
  "geometry": {"coordinates":[-5.797791481,38.9728927612],"type":"Point"}
}