{
  "type": "Feature",
  "properties": {
    "addr:full":"Calle de Maria Auxiliadora, 5 Cordoba C\u00f3rdoba 14002",
    "addr:housenumber":"5",
    "addr:postcode":"14002",
    "addr:street":"Calle De Maria Auxiliadora;Co\u0301Rdoba",
    "iso:country":"ES",
    "sg:address":"Calle de Maria Auxiliadora, 5",
    "sg:city":"Cordoba",
    "sg:orig_category":"Agencias Y Asesores De Publicidad",
    "sg:phone":"+34 957 48 37 96",
    "sg:postcode":"14002",
    "sg:province":"C\u00f3rdoba",
    "wof:name":"Publicidad Fd Studio C.b.",
    "wof:placetype":"venue"
},
  "geometry": {"coordinates":[-4.7683272362,37.8888092041],"type":"Point"}
}