{
  "type": "Feature",
  "properties": {
    "iso:country":"ES",
    "sg:address":"Avda Castilla (de), 19",
    "sg:city":"Alcala Henares",
    "sg:orig_category":"Tiendas De Grano, Frutas Y Legumbres Secas (al Por Menor)",
    "sg:phone":"+34 918 89 37 44",
    "sg:postcode":"28804",
    "sg:province":"Madrid",
    "wof:name":"Inspeccion Tecnica De Edificios Alcala S.l.l",
    "wof:placetype":"venue"
},
  "geometry": {"coordinates":[-3.3509159088,40.4842948914],"type":"Point"}
}