{
  "type": "Feature",
  "properties": {
    "iso:country":"ES",
    "sg:address":"Carrer de Maria Sanjuan Cuchi, 7",
    "sg:city":"Viladecans",
    "sg:orig_category":"Ense\u00d1anza Variada",
    "sg:phone":"+34 936 37 21 94",
    "sg:postcode":"08840",
    "sg:province":"Barcelona",
    "wof:name":"Asociacion Catalana De Servicios Empresariales Act-so S.l.",
    "wof:placetype":"venue"
},
  "geometry": {"coordinates":[2.0322172642,41.2981071472],"type":"Point"}
}