{
  "type": "Feature",
  "properties": {
    "addr:full":"Carrer de Unio (de La), 9 Tarragona Tarragona 43001",
    "addr:housenumber":"9",
    "addr:postcode":"43001",
    "addr:street":"Carrer De Unio De La",
    "iso:country":"ES",
    "sg:address":"Carrer de Unio (de La), 9",
    "sg:city":"Tarragona",
    "sg:classifiers":[
        {
            "category":"Personal",
            "subcategory":"Barber",
            "type":"Services"
        }
    ],
    "sg:phone":"+34 977 23 40 50",
    "sg:postcode":"43001",
    "sg:province":"Tarragona",
    "sg:tags":[
        "caballeros",
        "de",
        "peluqueros"
    ],
    "wof:name":"Abenbon S.l.",
    "wof:placetype":"venue"
},
  "geometry": {"coordinates":[1.252166,41.115173],"type":"Point"}
}