{
  "type": "Feature",
  "properties": {
    "addr:full":"Avda Historiador Bernardo Herrero, S/n Sax Alicante 03630",
    "addr:housenumber":"s / n",
    "addr:postcode":"03630",
    "addr:street":"Avda Historiador Bernardo Herrero",
    "iso:country":"ES",
    "sg:address":"Avda Historiador Bernardo Herrero, S/n",
    "sg:city":"Sax",
    "sg:classifiers":[
        {
            "category":"Professional",
            "subcategory":"Research",
            "type":"Services"
        }
    ],
    "sg:phone":"+34 965 47 50 04",
    "sg:postcode":"03630",
    "sg:province":"Alicante",
    "sg:tags":[
        "mercado",
        "de",
        "estudios"
    ],
    "wof:name":"Pasquin Studio, Sl",
    "wof:placetype":"venue"
},
  "geometry": {"coordinates":[-0.825173974,38.5343055725],"type":"Point"}
}