{
  "type": "Feature",
  "properties": {
    "iso:country":"ES",
    "sg:address":"Carrer de Edison, 15",
    "sg:city":"Terrassa",
    "sg:orig_category":"Asociaciones Humanitarias, De Cooperaci\u00d3n, De Acci\u00d3n Social",
    "sg:phone":"+34 937 33 62 53",
    "sg:postcode":"08224",
    "sg:province":"Barcelona",
    "wof:name":"Consorci Sanitari De Terrassa",
    "wof:placetype":"venue"
},
  "geometry": {"coordinates":[2.0041129589,41.5553588867],"type":"Point"}
}