{
  "type": "Feature",
  "properties": {
    "iso:country":"ES",
    "sg:address":"Avda Juan Carlos I, 4",
    "sg:city":"Tobarra",
    "sg:orig_category":"Producci\u00d3n De Abonos Y De Fertilizantes",
    "sg:phone":"+34 967 32 56 26",
    "sg:postcode":"02500",
    "sg:province":"Albacete",
    "wof:name":"Jimenez Claramonte Fernando",
    "wof:placetype":"venue"
},
  "geometry": {"coordinates":[-1.6885620356,38.5899429321],"type":"Point"}
}