{
  "type": "Feature",
  "properties": {
    "iso:country":"ES",
    "sg:address":"Ctra General C-820, S/n",
    "sg:city":"Buen Paso",
    "sg:orig_category":"Supermercados Y Hipermercados",
    "sg:phone":"+34 922 81 55 45",
    "sg:postcode":"38430",
    "sg:province":"Santa Cruz De Tenerife",
    "wof:name":"Dinosol Supermercados S.l.",
    "wof:placetype":"venue"
},
  "geometry": {"coordinates":[-16.7204761505,28.3677654266],"type":"Point"}
}