{
  "type": "Feature",
  "properties": {
    "iso:country":"ES",
    "sg:address":"Calle de Poeta Bodria, 10",
    "sg:city":"Valencia",
    "sg:orig_category":"Institutos De Belleza",
    "sg:phone":"+34 963 60 69 66",
    "sg:postcode":"46010",
    "sg:province":"Valencia",
    "wof:name":"Mu\u00f1oz Bujalance Natalia",
    "wof:placetype":"venue"
},
  "geometry": {"coordinates":[-0.3726668954,39.4813957214],"type":"Point"}
}