{
  "type": "Feature",
  "properties": {
    "addr:full":"Carretera De Carcabuey, S/n Rute C\u00f3rdoba 14960",
    "addr:housenumber":"s / n",
    "addr:postcode":"14960",
    "addr:street":"Carretera De Carcabuey;Co\u0301Rdoba",
    "iso:country":"ES",
    "sg:address":"Carretera De Carcabuey, S/n",
    "sg:city":"Rute",
    "sg:orig_category":"Guarder\u00cdas",
    "sg:phone":"+34 957 53 35 46",
    "sg:postcode":"14960",
    "sg:province":"C\u00f3rdoba",
    "wof:name":"Centro Educacion Infantil Bambi",
    "wof:placetype":"venue"
},
  "geometry": {"coordinates":[-4.36434412,37.3276290894],"type":"Point"}
}