{
  "type": "Feature",
  "properties": {
    "iso:country":"ES",
    "sg:address":"Carrer de Lleo Xiii, 25",
    "sg:city":"Barcelona",
    "sg:orig_category":"Abogados",
    "sg:phone":"+34 932 11 26 45",
    "sg:postcode":"08022",
    "sg:province":"Barcelona",
    "wof:name":"Perea Lanchares Lourdes",
    "wof:placetype":"venue"
},
  "geometry": {"coordinates":[2.1366899014,41.4128036499],"type":"Point"}
}