{
  "type": "Feature",
  "properties": {
    "iso:country":"ES",
    "sg:address":"Rava Santa Anna, 6",
    "sg:city":"Reus",
    "sg:orig_category":"Confiter\u00cdas, Chocolater\u00cdas (al Por Menor)",
    "sg:phone":"+34 977 34 30 13",
    "sg:postcode":"43201",
    "sg:province":"Tarragona",
    "wof:name":"Del Cacho Mira Saturio",
    "wof:placetype":"venue"
},
  "geometry": {"coordinates":[1.1094739437,41.1558036804],"type":"Point"}
}