{
  "type": "Feature",
  "properties": {
    "addr:full":"Avda Burjasot, 180 Valencia Valencia 46025",
    "addr:housenumber":"180",
    "addr:postcode":"46025",
    "addr:street":"Avda Burjasot",
    "iso:country":"ES",
    "sg:address":"Avda Burjasot, 180",
    "sg:city":"Valencia",
    "sg:orig_category":"Empresas De Carpinter\u00cda De Madera",
    "sg:phone":"+34 963 40 65 10",
    "sg:postcode":"46025",
    "sg:province":"Valencia",
    "wof:name":"Sahuquillo Ruescas Ricardo",
    "wof:placetype":"venue"
},
  "geometry": {"coordinates":[-0.3928380013,39.4921035767],"type":"Point"}
}