{
  "type": "Feature",
  "properties": {
    "addr:full":"Avda Valdefierro, 38 Zaragoza Zaragoza 50012",
    "addr:housenumber":"38",
    "addr:postcode":"50012",
    "addr:street":"Avda Valdefierro",
    "iso:country":"ES",
    "sg:address":"Avda Valdefierro, 38",
    "sg:city":"Zaragoza",
    "sg:classifiers":[
        {
            "category":"Autos & Motor Vehicles",
            "subcategory":"Automobile Sales",
            "type":"Retail Goods"
        }
    ],
    "sg:phone":"+34 976 53 31 14",
    "sg:postcode":"50012",
    "sg:province":"Zaragoza",
    "wof:name":"Esteban Delgado Jesus",
    "wof:placetype":"venue"
},
  "geometry": {"coordinates":[-0.9287329912,41.6408309937],"type":"Point"}
}