{
  "type": "Feature",
  "properties": {
    "iso:country":"ES",
    "sg:address":"Carr Guifre, 170",
    "sg:city":"Badalona",
    "sg:orig_category":"Cl\u00cdnicas Dentales",
    "sg:phone":"+34 934 60 33 40",
    "sg:postcode":"08912",
    "sg:province":"Barcelona",
    "wof:name":"Pijuan Calonge Antonio",
    "wof:placetype":"venue"
},
  "geometry": {"coordinates":[2.2426350117,41.4447822571],"type":"Point"}
}