{
  "type": "Feature",
  "properties": {
    "iso:country":"ES",
    "sg:address":"Galeon, 10",
    "sg:city":"Los Narejos",
    "sg:orig_category":"Empresarios",
    "sg:phone":"+34 968 57 56 33",
    "sg:postcode":"30710",
    "sg:province":"Murcia",
    "wof:name":"Murtagh  Jarlatz",
    "wof:placetype":"venue"
},
  "geometry": {"coordinates":[-0.8323720098,37.7604904175],"type":"Point"}
}