{
  "type": "Feature",
  "properties": {
    "iso:country":"ES",
    "sg:address":"Carr Sant Pere Martir, 46",
    "sg:city":"Blanes",
    "sg:orig_category":"Transportes De Material De Construcci\u00d3n",
    "sg:phone":"+34 972 35 15 14",
    "sg:postcode":"17300",
    "sg:province":"Girona",
    "wof:name":"Morillo Trans S.l.",
    "wof:placetype":"venue"
},
  "geometry": {"coordinates":[2.7871170044,41.6731796265],"type":"Point"}
}