{
  "type": "Feature",
  "properties": {
    "iso:country":"ES",
    "sg:address":"Calle de Teniente Borges, 8",
    "sg:city":"Sevilla",
    "sg:orig_category":"Molduras, Junquillos, Listones Y Molduras Perforadas",
    "sg:phone":"+34 954 56 12 85",
    "sg:postcode":"41002",
    "sg:province":"Sevilla",
    "wof:name":"La Flor De Los Ni\u00f1os S.l.",
    "wof:placetype":"venue"
},
  "geometry": {"coordinates":[-5.9969434738,37.3937721252],"type":"Point"}
}