{
  "type": "Feature",
  "properties": {
    "iso:country":"ES",
    "sg:address":"Calle de Torrejon, 18",
    "sg:city":"Parla",
    "sg:orig_category":"Bares, Piano",
    "sg:phone":"+34 916 99 91 26",
    "sg:postcode":"28980",
    "sg:province":"Madrid",
    "wof:name":"Horquillo S.l.",
    "wof:placetype":"venue"
},
  "geometry": {"coordinates":[-3.7668728828,40.2381782532],"type":"Point"}
}