{
  "type": "Feature",
  "properties": {
    "addr:full":"Polig. Indust. Chacon, S/n Fuente Palmera C\u00f3rdoba 14120",
    "addr:postcode":"14120",
    "addr:street":"Polig. Indust. Chacon S / N",
    "iso:country":"ES",
    "sg:address":"Polig. Indust. Chacon, S/n",
    "sg:city":"Fuente Palmera",
    "sg:orig_category":"Mec\u00c1nico Del Autom\u00d3vil",
    "sg:phone":"+34 957 63 83 20",
    "sg:postcode":"14120",
    "sg:province":"C\u00f3rdoba",
    "wof:name":"Rodriguez Martin Lazaro",
    "wof:placetype":"venue"
},
  "geometry": {"coordinates":[-5.0964288712,37.7094764709],"type":"Point"}
}