{
  "type": "Feature",
  "properties": {
    "addr:full":"Calle de Salvador, El, 29 Torrent Valencia 46900",
    "addr:housenumber":"29",
    "addr:postcode":"46900",
    "addr:street":"Calle De Salvador El;Valencia",
    "iso:country":"ES",
    "sg:address":"Calle de Salvador, El, 29",
    "sg:city":"Torrent",
    "sg:orig_category":"Mec\u00c1nico Del Autom\u00d3vil",
    "sg:phone":"+34 961 57 29 73",
    "sg:postcode":"46900",
    "sg:province":"Valencia",
    "wof:name":"March Montoro Luis Manuel",
    "wof:placetype":"venue"
},
  "geometry": {"coordinates":[-0.4713810086,39.4348297119],"type":"Point"}
}