{
  "type": "Feature",
  "properties": {
    "iso:country":"ES",
    "sg:address":"Crt. Madrid, 21",
    "sg:city":"Motilla Palancar",
    "sg:orig_category":"Insecticidas, Fumigaci\u00d3n",
    "sg:phone":"+34 969 33 33 79",
    "sg:postcode":"16200",
    "sg:province":"Cuenca",
    "wof:name":"Martinez Gomez Miguel Enrique",
    "wof:placetype":"venue"
},
  "geometry": {"coordinates":[-1.905823946,39.5647583008],"type":"Point"}
}