{
  "type": "Feature",
  "properties": {
    "iso:country":"ES",
    "sg:address":"Carrer de Tarragona, 9",
    "sg:city":"S. Joan Despi",
    "sg:orig_category":"Empresarios",
    "sg:phone":"+34 933 73 28 03",
    "sg:postcode":"08970",
    "sg:province":"Barcelona",
    "wof:name":"Gonzasa S.l.",
    "wof:placetype":"venue"
},
  "geometry": {"coordinates":[2.0717880726,41.3680992126],"type":"Point"}
}