{
  "type": "Feature",
  "properties": {
    "iso:country":"ES",
    "sg:address":"Pl Marquilles, 1",
    "sg:city":"Sabadell",
    "sg:orig_category":"Quincaller\u00cda (al Por Menor)",
    "sg:phone":"+34 937 26 02 82",
    "sg:postcode":"08201",
    "sg:province":"Barcelona",
    "wof:name":"Marles Tortosa Carles",
    "wof:placetype":"venue"
},
  "geometry": {"coordinates":[2.1058530807,41.5461997986],"type":"Point"}
}