{
  "type": "Feature",
  "properties": {
    "addr:full":"Carr Doctor Combelles, 44 Lleida Lleida 25003",
    "addr:housenumber":"44",
    "addr:postcode":"25003",
    "addr:street":"Carr Doctor Combelles",
    "iso:country":"ES",
    "sg:address":"Carr Doctor Combelles, 44",
    "sg:city":"Lleida",
    "sg:orig_category":"Mec\u00c1nico Del Autom\u00d3vil",
    "sg:phone":"+34 973 26 29 63",
    "sg:postcode":"25003",
    "sg:province":"Lleida",
    "wof:name":"Soligue Carulla Jaume",
    "wof:placetype":"venue"
},
  "geometry": {"coordinates":[0.616411984,41.6140823364],"type":"Point"}
}