{
  "type": "Feature",
  "properties": {
    "iso:country":"ES",
    "sg:address":"Carrer de Mare De Deu Dels Desemparats, 30",
    "sg:city":"Hospitalet Llobregat",
    "sg:orig_category":"Ense\u00d1anza: Profesiones Art\u00cdsticas",
    "sg:phone":"+34 934 48 05 38",
    "sg:postcode":"08903",
    "sg:province":"Barcelona",
    "wof:name":"Calvo Dolz Carlos",
    "wof:placetype":"venue"
},
  "geometry": {"coordinates":[2.1243948936,41.3721504211],"type":"Point"}
}