{
  "type": "Feature",
  "properties": {
    "addr:full":"Cm\u00d1o Laxes (das), 11 Laxes Pontevedra 36163",
    "addr:postcode":"36163",
    "iso:country":"ES",
    "sg:address":"Cm\u00d1o Laxes (das), 11",
    "sg:city":"Laxes",
    "sg:orig_category":"Autob\u00das (explotaci\u00d3n Y Servicios De)",
    "sg:phone":"+34 986 87 30 56",
    "sg:postcode":"36163",
    "sg:province":"Pontevedra",
    "wof:name":"Esperon Gonzalez Manuel",
    "wof:placetype":"venue"
},
  "geometry": {"coordinates":[-8.6428003311,42.4304618835],"type":"Point"}
}