{
  "type": "Feature",
  "properties": {
    "iso:country":"ES",
    "sg:address":"Calle de San Isidro, 12",
    "sg:city":"Malagon",
    "sg:orig_category":"Muebles Y Accesorios Para Cocinas Y Cuartos De Ba\u00d1o (al Por Menor)",
    "sg:phone":"+34 926 80 25 06",
    "sg:postcode":"13420",
    "sg:province":"Ciudad Real",
    "wof:name":"Rodriguez Madrid Jacinto",
    "wof:placetype":"venue"
},
  "geometry": {"coordinates":[-3.8578948975,39.1617088318],"type":"Point"}
}