{
  "type": "Feature",
  "properties": {
    "addr:full":"Calle de Padre Guillem, 24 Alaquas Valencia 46970",
    "addr:housenumber":"24",
    "addr:postcode":"46970",
    "addr:street":"Calle De Padre Guillem",
    "iso:country":"ES",
    "sg:address":"Calle de Padre Guillem, 24",
    "sg:city":"Alaquas",
    "sg:orig_category":"Postigos, Persianas Y Celos\u00cdas",
    "sg:phone":"+34 961 50 63 06",
    "sg:postcode":"46970",
    "sg:province":"Valencia",
    "wof:name":"Teruel Anaya Mariano",
    "wof:placetype":"venue"
},
  "geometry": {"coordinates":[-0.4563170075,39.4566230774],"type":"Point"}
}