{
  "type": "Feature",
  "properties": {
    "iso:country":"ES",
    "sg:address":"Calle de Juan Xxiii (de), 14",
    "sg:city":"Mostoles",
    "sg:orig_category":"Farmacias",
    "sg:phone":"+34 916 17 50 05",
    "sg:postcode":"28938",
    "sg:province":"Madrid",
    "wof:name":"Fernandez Sanchez Angel",
    "wof:placetype":"venue"
},
  "geometry": {"coordinates":[-3.8641149998,40.3198127747],"type":"Point"}
}