{
  "type": "Feature",
  "properties": {
    "addr:full":"Ctra Villalpando, Km. 0002,0 Zamora Zamora 49023",
    "addr:postcode":"49023",
    "addr:street":"Ctra Villalpando Km. 0002,0",
    "iso:country":"ES",
    "sg:address":"Ctra Villalpando, Km. 0002,0",
    "sg:city":"Zamora",
    "sg:orig_category":"Escotaduras, Torneados",
    "sg:phone":"+34 980 52 11 85",
    "sg:postcode":"49023",
    "sg:province":"Zamora",
    "wof:name":"Mecanizaciones Guerrero S. A.",
    "wof:placetype":"venue"
},
  "geometry": {"coordinates":[-5.7432451248,41.5151977539],"type":"Point"}
}