{
  "type": "Feature",
  "properties": {
    "addr:full":"Monasterio Urdax, 15 Iru\u00f1a Navarra 31011",
    "addr:housenumber":"15",
    "addr:postcode":"31011",
    "addr:street":"Urdax",
    "iso:country":"ES",
    "sg:address":"Monasterio Urdax, 15",
    "sg:city":"Iru\u00f1a",
    "sg:orig_category":"Abogados",
    "sg:phone":"+34 948 25 53 44",
    "sg:postcode":"31011",
    "sg:province":"Navarra",
    "wof:name":"Potestad Menendez Luis",
    "wof:placetype":"venue"
},
  "geometry": {"coordinates":[-1.6576410532,42.8134155273],"type":"Point"}
}