{
  "type": "Feature",
  "properties": {
    "iso:country":"ES",
    "sg:address":"Carrer de Sant Ramon, 55",
    "sg:city":"Campello",
    "sg:orig_category":"Peleter\u00cdas",
    "sg:phone":"+34 965 63 58 72",
    "sg:postcode":"03560",
    "sg:province":"Alicante",
    "wof:name":"La Piel De Aqui S.l.",
    "wof:placetype":"venue"
},
  "geometry": {"coordinates":[-0.4026570022,38.4279327393],"type":"Point"}
}