{
  "type": "Feature",
  "properties": {
    "addr:full":"Fnc. Llano Cojo, S/n Barajas Melo Cuenca 16460",
    "addr:housenumber":"s / n",
    "addr:postcode":"16460",
    "addr:street":"Cojo",
    "iso:country":"ES",
    "sg:address":"Fnc. Llano Cojo, S/n",
    "sg:city":"Barajas Melo",
    "sg:orig_category":"Inmobiliaria (agencias)",
    "sg:phone":"+34 969 14 82 13",
    "sg:postcode":"16460",
    "sg:province":"Cuenca",
    "wof:name":"Halfer Actividades Y Rentas S.l.",
    "wof:placetype":"venue"
},
  "geometry": {"coordinates":[-2.9168190956,40.1228599548],"type":"Point"}
}