{
  "type": "Feature",
  "properties": {
    "addr:full":"Carrer de Roquetes (de Les), 5 Gata Gorgos Alicante 03740",
    "addr:housenumber":"5",
    "addr:postcode":"03740",
    "addr:street":"Carrer De Roquetes De Les",
    "iso:country":"ES",
    "sg:address":"Carrer de Roquetes (de Les), 5",
    "sg:city":"Gata Gorgos",
    "sg:orig_category":"Armas Y Municiones (fabricaci\u00d3n, Al Por Mayor)",
    "sg:phone":"+34 965 75 61 65",
    "sg:postcode":"03740",
    "sg:province":"Alicante",
    "wof:name":"Pons Gil Vicente",
    "wof:placetype":"venue"
},
  "geometry": {"coordinates":[0.0818749964,38.7738418579],"type":"Point"}
}