{
  "type": "Feature",
  "properties": {
    "addr:full":"Avda Montes De Oca (de Los), 20 San Sebastian De Los Reyes Madrid 28700",
    "addr:housenumber":"20",
    "addr:postcode":"28700",
    "addr:street":"Avda Montes De Oca De Los",
    "iso:country":"ES",
    "sg:address":"Avda Montes De Oca (de Los), 20",
    "sg:city":"San Sebastian De Los Reyes",
    "sg:orig_category":"Compraventa De Antig\u00dcedades",
    "sg:phone":"+34 916 63 70 64",
    "sg:postcode":"28700",
    "sg:province":"Madrid",
    "wof:name":"Santafe Arroyo Pilar",
    "wof:placetype":"venue"
},
  "geometry": {"coordinates":[-3.6127269268,40.5511322021],"type":"Point"}
}