{
  "type": "Feature",
  "properties": {
    "addr:full":"Plaz Espa\u00d1a, 15 Hornachos Badajoz 06228",
    "addr:housenumber":"15",
    "addr:postcode":"06228",
    "addr:street":"Plaz Espan\u0303A",
    "iso:country":"ES",
    "sg:address":"Plaz Espa\u00d1a, 15",
    "sg:city":"Hornachos",
    "sg:orig_category":"Electrodom\u00c9sticos (al Por Menor)",
    "sg:phone":"+34 924 53 33 36",
    "sg:postcode":"06228",
    "sg:province":"Badajoz",
    "wof:name":"Casa Nanin S.l.",
    "wof:placetype":"venue"
},
  "geometry": {"coordinates":[-6.0721697807,38.5533332825],"type":"Point"}
}