{
  "type": "Feature",
  "properties": {
    "addr:full":"Avda Fuente Nueva (de La), 12 San Sebastian De Los Reyes Madrid 28700",
    "addr:housenumber":"12",
    "addr:postcode":"28700",
    "addr:street":"Avda Fuente Nueva De La",
    "iso:country":"ES",
    "sg:address":"Avda Fuente Nueva (de La), 12",
    "sg:city":"San Sebastian De Los Reyes",
    "sg:orig_category":"Suministros Y Materiales Industriales",
    "sg:phone":"+34 916 58 60 48",
    "sg:postcode":"28700",
    "sg:province":"Madrid",
    "wof:name":"Metal Work Iberica S.a.",
    "wof:placetype":"venue"
},
  "geometry": {"coordinates":[-3.6123359203,40.547668457],"type":"Point"}
}