{
  "type": "Feature",
  "properties": {
    "iso:country":"ES",
    "sg:address":"Calle de San Sebastian, 45",
    "sg:city":"Vinaros",
    "sg:orig_category":"Ingeniero",
    "sg:phone":"+34 964 45 08 57",
    "sg:postcode":"12500",
    "sg:province":"Castell\u00f3n",
    "wof:name":"Vidal Ferrer Miguel",
    "wof:placetype":"venue"
},
  "geometry": {"coordinates":[0.4749450088,40.4711990356],"type":"Point"}
}