{
  "type": "Feature",
  "properties": {
    "addr:full":"Calle de Cadiz, 6 Baza Granada 18800",
    "addr:housenumber":"6",
    "addr:postcode":"18800",
    "addr:street":"Calle De Cadiz",
    "iso:country":"ES",
    "sg:address":"Calle de Cadiz, 6",
    "sg:city":"Baza",
    "sg:orig_category":"Asesor\u00cda Fiscal Y Jur\u00cddica",
    "sg:phone":"+34 958 70 31 50",
    "sg:postcode":"18800",
    "sg:province":"Granada",
    "wof:name":"Asesoria Moreno Weidmann C.b.",
    "wof:placetype":"venue"
},
  "geometry": {"coordinates":[-2.7689535618,37.4866676331],"type":"Point"}
}