{
  "type": "Feature",
  "properties": {
    "addr:full":"Carrer de Carders, 18 Barcelona Barcelona 08003",
    "addr:housenumber":"18",
    "addr:postcode":"08003",
    "addr:street":"Carrer De Carders",
    "iso:country":"ES",
    "sg:address":"Carrer de Carders, 18",
    "sg:city":"Barcelona",
    "sg:orig_category":"Inmobiliaria (agencias)",
    "sg:phone":"+34 932 68 70 28",
    "sg:postcode":"08003",
    "sg:province":"Barcelona",
    "wof:name":"Casc Antic Bcn S.l.",
    "wof:placetype":"venue"
},
  "geometry": {"coordinates":[2.1801860332,41.386428833],"type":"Point"}
}