{
  "type": "Feature",
  "properties": {
    "addr:full":"Calle de Hospital, 11 Vinaros Castell\u00f3n 12500",
    "addr:housenumber":"11",
    "addr:postcode":"12500",
    "addr:street":"Calle De Hospital",
    "iso:country":"ES",
    "sg:address":"Calle de Hospital, 11",
    "sg:city":"Vinaros",
    "sg:orig_category":"Abogados",
    "sg:phone":"+34 964 40 08 05",
    "sg:postcode":"12500",
    "sg:province":"Castell\u00f3n",
    "wof:name":"Garcia Gil Daniel",
    "wof:placetype":"venue"
},
  "geometry": {"coordinates":[0.4714510143,40.4695396423],"type":"Point"}
}