{
  "type": "Feature",
  "properties": {
    "iso:country":"ES",
    "sg:address":"Calle de Ancha, 18",
    "sg:city":"Torredelcampo",
    "sg:orig_category":"Electrodom\u00c9sticos (al Por Menor)",
    "sg:phone":"+34 953 56 75 95",
    "sg:postcode":"23640",
    "sg:province":"Ja\u00e9n",
    "wof:name":"Electronica Pancorbo S.l.",
    "wof:placetype":"venue"
},
  "geometry": {"coordinates":[-3.8994801044,37.7710838318],"type":"Point"}
}