{
  "type": "Feature",
  "properties": {
    "addr:full":"Calle de Ballobar, 8 Huesca Huesca 22004",
    "addr:housenumber":"8",
    "addr:postcode":"22004",
    "addr:street":"Calle De Ballobar",
    "iso:country":"ES",
    "sg:address":"Calle de Ballobar, 8",
    "sg:city":"Huesca",
    "sg:orig_category":"Reparaciones Y Remolcado De Veh\u00cdculos",
    "sg:phone":"+34 974 21 12 52",
    "sg:postcode":"22004",
    "sg:province":"Huesca",
    "sg:website":"www.maycar.com",
    "wof:name":"Chapisteria Maycar S.l.",
    "wof:placetype":"venue"
},
  "geometry": {"coordinates":[-0.4158670008,42.1289291382],"type":"Point"}
}