{
  "type": "Feature",
  "properties": {
    "iso:country":"ES",
    "sg:address":"Ctra Estacion (de La), S/n",
    "sg:city":"Meco",
    "sg:orig_category":"Transportes De Autom\u00d3viles Y Otros Veh\u00cdculos",
    "sg:phone":"+34 918 87 70 31",
    "sg:postcode":"28880",
    "sg:province":"Madrid",
    "wof:name":"Walon Iberia S.l.",
    "wof:placetype":"venue"
},
  "geometry": {"coordinates":[-3.3236618042,40.5527992249],"type":"Point"}
}