{
  "type": "Feature",
  "properties": {
    "addr:full":"Calle de Illescas, 67 Madrid Madrid 28024",
    "addr:housenumber":"67",
    "addr:postcode":"madrid;28024",
    "addr:street":"Calle De Illescas",
    "iso:country":"ES",
    "sg:address":"Calle de Illescas, 67",
    "sg:city":"Madrid",
    "sg:orig_category":"Ropa Para Se\u00d1oras (al Por Menor)",
    "sg:phone":"+34 917 11 25 14",
    "sg:postcode":"28024",
    "sg:province":"Madrid",
    "wof:name":"Garcia Magari\u00f1os Jorge",
    "wof:placetype":"venue"
},
  "geometry": {"coordinates":[-3.7633650303,40.3950500488],"type":"Point"}
}