{
  "type": "Feature",
  "properties": {
    "addr:full":"Avda Zaragoza, 10 Borriol Castell\u00f3n 12190",
    "addr:housenumber":"10",
    "addr:postcode":"12190",
    "addr:street":"Avda Zaragoza",
    "iso:country":"ES",
    "sg:address":"Avda Zaragoza, 10",
    "sg:city":"Borriol",
    "sg:orig_category":"Mec\u00c1nico Del Autom\u00d3vil",
    "sg:phone":"+34 964 32 11 45",
    "sg:postcode":"12190",
    "sg:province":"Castell\u00f3n",
    "wof:name":"J.l.andres S.l.",
    "wof:placetype":"venue"
},
  "geometry": {"coordinates":[-0.073725,40.039932251],"type":"Point"}
}