{
  "type": "Feature",
  "properties": {
    "addr:full":"La Ventilla, 4 Aguadulce Almer\u00eda 04720",
    "addr:housenumber":"4",
    "addr:postcode":"04720",
    "addr:street":"Ventilla;Almeri\u0301A",
    "iso:country":"ES",
    "sg:address":"La Ventilla, 4",
    "sg:city":"Aguadulce",
    "sg:orig_category":"Arboricultura Y Producci\u00d3n De Frutas",
    "sg:phone":"+34 950 55 04 10",
    "sg:postcode":"04720",
    "sg:province":"Almer\u00eda",
    "wof:name":"Solduce S.l.",
    "wof:placetype":"venue"
},
  "geometry": {"coordinates":[-2.5974500179,36.801410675],"type":"Point"}
}