{
  "type": "Feature",
  "properties": {
    "iso:country":"ES",
    "sg:address":"Av Espanya, 10",
    "sg:city":"Eivissa",
    "sg:orig_category":"M\u00c9dicos: Pediatr\u00cda. Enfermedades De Los Ni\u00d1os",
    "sg:phone":"+34 971 39 04 61",
    "sg:postcode":"07800",
    "sg:province":"Islas Baleares",
    "wof:name":"Ferrer Pons Juan",
    "wof:placetype":"venue"
},
  "geometry": {"coordinates":[1.4312249422,38.9087524414],"type":"Point"}
}