{
  "type": "Feature",
  "properties": {
    "addr:full":"C. Tietar-barquilla, S/n Tietar Caudillo C\u00e1ceres 10319",
    "addr:housenumber":"s",
    "addr:postcode":"10319",
    "addr:street":"/ N",
    "iso:country":"ES",
    "sg:address":"C. Tietar-barquilla, S/n",
    "sg:city":"Tietar Caudillo",
    "sg:orig_category":"Caf\u00c9s, Bares, Cervecer\u00cdas",
    "sg:phone":"+34 927 55 06 50",
    "sg:postcode":"10319",
    "sg:province":"C\u00e1ceres",
    "wof:name":"Monroy Jimenez Jose Luis",
    "wof:placetype":"venue"
},
  "geometry": {"coordinates":[-5.484058857,40.0295753479],"type":"Point"}
}