{
  "type": "Feature",
  "properties": {
    "addr:full":"Calle de San Francisco, 33 Loja Granada 18300",
    "addr:housenumber":"33 loja",
    "addr:postcode":"18300",
    "addr:street":"Calle De San Francisco",
    "iso:country":"ES",
    "sg:address":"Calle de San Francisco, 33",
    "sg:city":"Loja",
    "sg:orig_category":"Empresas De Carpinter\u00cda Met\u00c1lica",
    "sg:phone":"+34 958 32 07 13",
    "sg:postcode":"18300",
    "sg:province":"Granada",
    "wof:name":"Mu\u00f1oz Sanchez Emilio",
    "wof:placetype":"venue"
},
  "geometry": {"coordinates":[-4.1533203125,37.1736297607],"type":"Point"}
}