{
  "type": "Feature",
  "properties": {
    "iso:country":"ES",
    "sg:address":"Barr Vallejas, S/n",
    "sg:city":"Ace\u00d1a",
    "sg:orig_category":"Apicultura",
    "sg:phone":"+34 946 10 00 10",
    "sg:postcode":"48191",
    "sg:province":"Vizcaya",
    "wof:name":"Sat Eztikidetza",
    "wof:placetype":"venue"
},
  "geometry": {"coordinates":[-3.0992720127,43.2543907166],"type":"Point"}
}