{
  "type": "Feature",
  "properties": {
    "iso:country":"ES",
    "sg:address":"Calle de Natalio Rivas, 59",
    "sg:city":"Adra",
    "sg:orig_category":"Inform\u00c1tica (estudios, Servicios, Asesor\u00cda, Formaci\u00d3n)",
    "sg:phone":"+34 950 60 40 24",
    "sg:postcode":"04770",
    "sg:province":"Almer\u00eda",
    "wof:name":"Promolico S.l.",
    "wof:placetype":"venue"
},
  "geometry": {"coordinates":[-3.0056390762,36.7545166016],"type":"Point"}
}