{
  "type": "Feature",
  "properties": {
    "iso:country":"ES",
    "sg:address":"Av Carrilet, 74",
    "sg:city":"Hospitalet Llobregat",
    "sg:orig_category":"Cajas De Ahorro",
    "sg:phone":"+34 934 21 27 37",
    "sg:postcode":"08902",
    "sg:province":"Barcelona",
    "sg:website":"www.lacaixa.es",
    "wof:name":"Caixa D'estalvis I Pensions De Barcelona",
    "wof:placetype":"venue"
},
  "geometry": {"coordinates":[2.1262459755,41.364818573],"type":"Point"}
}