{
  "type": "Feature",
  "properties": {
    "iso:country":"ES",
    "sg:address":"Calle de Gran Via, 30",
    "sg:city":"Almazan",
    "sg:orig_category":"Producci\u00d3n, Venta De Productos De Agricultura Biol\u00d3gica",
    "sg:phone":"+34 975 30 11 94",
    "sg:postcode":"42200",
    "sg:province":"Soria",
    "wof:name":"Andres Pascual Alfredo",
    "wof:placetype":"venue"
},
  "geometry": {"coordinates":[-2.5270080566,41.4885406494],"type":"Point"}
}