{
  "type": "Feature",
  "properties": {
    "addr:full":"Carrer de Barcelona, 33 Calella Barcelona 08370",
    "addr:housenumber":"33",
    "addr:postcode":"08370",
    "addr:street":"Carrer De Barcelona",
    "iso:country":"ES",
    "sg:address":"Carrer de Barcelona, 33",
    "sg:city":"Calella",
    "sg:orig_category":"Institutos De Belleza",
    "sg:phone":"+34 937 66 12 36",
    "sg:postcode":"08370",
    "sg:province":"Barcelona",
    "wof:name":"Boada Herrero Marta",
    "wof:placetype":"venue"
},
  "geometry": {"coordinates":[2.6558790207,41.6126594543],"type":"Point"}
}