{
  "type": "Feature",
  "properties": {
    "addr:full":"Avda Leganes, 9 Alcorcon Madrid 28924",
    "addr:housenumber":"9",
    "addr:postcode":"28924",
    "addr:street":"Avda Leganes",
    "iso:country":"ES",
    "sg:address":"Avda Leganes, 9",
    "sg:city":"Alcorcon",
    "sg:orig_category":"Guarder\u00cdas",
    "sg:phone":"+34 916 11 65 85",
    "sg:postcode":"28924",
    "sg:province":"Madrid",
    "wof:name":"Piccolo Noventa S.l.",
    "wof:placetype":"venue"
},
  "geometry": {"coordinates":[-3.8159999847,40.346912384],"type":"Point"}
}