{
  "type": "Feature",
  "properties": {
    "iso:country":"ES",
    "sg:address":"Avda Federico Garcia Lorca, S/n",
    "sg:city":"Arroyo De La Miel-benalmadena Costa",
    "sg:orig_category":"Papeler\u00cdas, Librer\u00cdas",
    "sg:phone":"+34 952 56 04 75",
    "sg:postcode":"29631",
    "sg:province":"M\u00e1laga",
    "wof:name":"Downie  Andrew George Ernest",
    "wof:placetype":"venue"
},
  "geometry": {"coordinates":[-4.5315542221,36.5993232727],"type":"Point"}
}