{
  "type": "Feature",
  "properties": {
    "iso:country":"ES",
    "sg:address":"Calle de General Diaz Porlier, 22",
    "sg:city":"Madrid",
    "sg:orig_category":"Inmobiliaria (agencias)",
    "sg:phone":"+34 915 75 74 15",
    "sg:postcode":"28001",
    "sg:province":"Madrid",
    "sg:website":"www.alfainmo.com",
    "wof:name":"Inmomar Gestion E Inversiones Inmobilarias S.l.",
    "wof:placetype":"venue"
},
  "geometry": {"coordinates":[-3.6770582199,40.4268989563],"type":"Point"}
}