{
  "type": "Feature",
  "properties": {
    "iso:country":"ES",
    "sg:address":"C/ Gambi, Del, 4",
    "sg:city":"Porto Cristo",
    "sg:orig_category":"Art\u00cdculos De Regalo (al Por Menor)",
    "sg:phone":"+34 971 82 09 67",
    "sg:postcode":"07680",
    "sg:province":"Islas Baleares",
    "wof:name":"Mascaro Cerda Guillermo",
    "wof:placetype":"venue"
},
  "geometry": {"coordinates":[3.3309600353,39.5396690369],"type":"Point"}
}