{
  "type": "Feature",
  "properties": {
    "iso:country":"ES",
    "sg:address":"Partida L'olla, S/n",
    "sg:city":"Olla",
    "sg:orig_category":"Molduras, Junquillos, Listones Y Molduras Perforadas",
    "sg:phone":"+34 965 84 15 63",
    "sg:postcode":"03590",
    "sg:province":"Alicante",
    "wof:name":"Cendra Orozco Magdalena",
    "wof:placetype":"venue"
},
  "geometry": {"coordinates":[-0.0314770006,38.6189727783],"type":"Point"}
}