{
  "type": "Feature",
  "properties": {
    "iso:country":"ES",
    "sg:address":"Calle de Pablo Picasso (de), 14",
    "sg:city":"Mejorada Campo",
    "sg:orig_category":"Partidos Pol\u00cdticos",
    "sg:phone":"+34 916 79 36 19",
    "sg:postcode":"28840",
    "sg:province":"Madrid",
    "wof:name":"Partido Comunista De Espa\u00f1a",
    "wof:placetype":"venue"
},
  "geometry": {"coordinates":[-3.4880859852,40.3978691101],"type":"Point"}
}