{
  "type": "Feature",
  "properties": {
    "iso:country":"ES",
    "sg:address":"Tv M Azpilcueta, 4",
    "sg:city":"Iru\u00f1a",
    "sg:orig_category":"Material Y Suministros Para Imprenta E Industrias Gr\u00c1ficas",
    "sg:phone":"+34 948 27 48 07",
    "sg:postcode":"31011",
    "sg:province":"Navarra",
    "wof:name":"Bardeak S.l.",
    "wof:placetype":"venue"
},
  "geometry": {"coordinates":[-1.663251996,42.8147277832],"type":"Point"}
}