{
  "type": "Feature",
  "properties": {
    "addr:full":"Carretera, S/n Urbiola Navarra 31243",
    "addr:postcode":"31243",
    "addr:street":"Carretera S / N Urbiola Navarra",
    "iso:country":"ES",
    "sg:address":"Carretera, S/n",
    "sg:city":"Urbiola",
    "sg:orig_category":"Ferreter\u00cda Artesanal",
    "sg:phone":"+34 948 53 70 05",
    "sg:postcode":"31243",
    "sg:province":"Navarra",
    "wof:name":"Alcoz San Martin Jose Cruz Santiago Francisco Javier Cesar Maria",
    "wof:placetype":"venue"
},
  "geometry": {"coordinates":[-2.0839898586,42.6447525024],"type":"Point"}
}