{
  "type": "Feature",
  "properties": {
    "addr:full":"Carr Maset, 12 Silla Valencia 46460",
    "addr:housenumber":"12",
    "addr:postcode":"46460",
    "addr:street":"Carr Maset",
    "iso:country":"ES",
    "sg:address":"Carr Maset, 12",
    "sg:city":"Silla",
    "sg:orig_category":"Cajas Y Embalajes De Cart\u00d3n Y Papel",
    "sg:phone":"+34 961 21 05 76",
    "sg:postcode":"46460",
    "sg:province":"Valencia",
    "wof:name":"Cartonajes Obrador Sl",
    "wof:placetype":"venue"
},
  "geometry": {"coordinates":[-0.4175449908,39.374294281],"type":"Point"}
}