{
  "type": "Feature",
  "properties": {
    "iso:country":"ES",
    "sg:address":"Plaza De Serrano, 4",
    "sg:city":"Baza",
    "sg:orig_category":"Arquitectos",
    "sg:phone":"+34 958 71 28 35",
    "sg:postcode":"18800",
    "sg:province":"Granada",
    "wof:name":"Ca\u00f1ada Rodriguez Jose Andres",
    "wof:placetype":"venue"
},
  "geometry": {"coordinates":[-2.7736890316,37.4896812439],"type":"Point"}
}