{
  "type": "Feature",
  "properties": {
    "addr:full":"Avgd Born, Des, 4 Soller Islas Baleares 07100",
    "addr:postcode":"07100",
    "iso:country":"ES",
    "sg:address":"Avgd Born, Des, 4",
    "sg:city":"Soller",
    "sg:orig_category":"Bazares, Art\u00cdculos De Limpieza Y De Cocina (al Por Menor)",
    "sg:phone":"+34 971 63 03 02",
    "sg:postcode":"07100",
    "sg:province":"Islas Baleares",
    "wof:name":"Rullan Gual Ramon Victor",
    "wof:placetype":"venue"
},
  "geometry": {"coordinates":[2.7147779465,39.7659072876],"type":"Point"}
}