{
  "type": "Feature",
  "properties": {
    "iso:country":"ES",
    "sg:address":"Cami\u00f1o Do Rio, 2",
    "sg:city":"Malpica Berganti\u00f1os",
    "sg:orig_category":"Alquiler De V\u00cddeo",
    "sg:phone":"+34 981 72 11 43",
    "sg:postcode":"15113",
    "sg:province":"La Coru\u00f1a",
    "wof:name":"Pose Porto Juan Luis",
    "wof:placetype":"venue"
},
  "geometry": {"coordinates":[-8.8103790283,43.3228607178],"type":"Point"}
}