{
  "type": "Feature",
  "properties": {
    "iso:country":"ES",
    "sg:address":"Calle de Antonio Zamora, 5",
    "sg:city":"Madrid",
    "sg:orig_category":"Empresarios",
    "sg:phone":"+34 914 64 35 42",
    "sg:postcode":"28011",
    "sg:province":"Madrid",
    "wof:name":"Fundacion Balia",
    "wof:placetype":"venue"
},
  "geometry": {"coordinates":[-3.7256791592,40.4134101868],"type":"Point"}
}