{
  "type": "Feature",
  "properties": {
    "iso:country":"ES",
    "sg:address":"Carrer de Major De Sarria, 6",
    "sg:city":"Barcelona",
    "sg:orig_category":"Papeler\u00cdas, Librer\u00cdas",
    "sg:phone":"+34 932 05 66 64",
    "sg:postcode":"08017",
    "sg:province":"Barcelona",
    "wof:name":"Gomez Hernandez Andres",
    "wof:placetype":"venue"
},
  "geometry": {"coordinates":[2.1250920296,41.396194458],"type":"Point"}
}