{
  "type": "Feature",
  "properties": {
    "addr:full":"Calle de Plateria, 3 San Bartolome Murcia 30004",
    "addr:housenumber":"3",
    "addr:postcode":"30004",
    "addr:street":"Calle De Plateria",
    "iso:country":"ES",
    "sg:address":"Calle de Plateria, 3",
    "sg:city":"San Bartolome",
    "sg:orig_category":"Asesor\u00cda De Comercio Exterior",
    "sg:phone":"+34 968 22 54 10",
    "sg:postcode":"30004",
    "sg:province":"Murcia",
    "wof:name":"Asesores Taso Internacional S.l.",
    "wof:placetype":"venue"
},
  "geometry": {"coordinates":[-1.1298867464,37.9834747314],"type":"Point"}
}