{
  "type": "Feature",
  "properties": {
    "addr:full":"Calle de Doctor Barraquer, S/n Ogijares Granada 18151",
    "addr:housenumber":"s / n",
    "addr:postcode":"18151",
    "addr:street":"Calle De Doctor Barraquer",
    "iso:country":"ES",
    "sg:address":"Calle de Doctor Barraquer, S/n",
    "sg:city":"Ogijares",
    "sg:orig_category":"Caf\u00c9s, Bares, Cervecer\u00cdas",
    "sg:phone":"+34 958 50 93 25",
    "sg:postcode":"18151",
    "sg:province":"Granada",
    "wof:name":"Robles Alcala Antonia",
    "wof:placetype":"venue"
},
  "geometry": {"coordinates":[-3.6196699142,37.1156845093],"type":"Point"}
}