{
  "type": "Feature",
  "properties": {
    "iso:country":"ES",
    "sg:address":"Carrer de Mare De Deu De Nuria, 11",
    "sg:city":"Granollers",
    "sg:orig_category":"Zapatos (al Por Menor)",
    "sg:phone":"+34 938 79 11 67",
    "sg:postcode":"08401",
    "sg:province":"Barcelona",
    "wof:name":"Serra Masferrer Maria Teresa",
    "wof:placetype":"venue"
},
  "geometry": {"coordinates":[2.2848050594,41.6087913513],"type":"Point"}
}