{
  "type": "Feature",
  "properties": {
    "addr:full":"Calle de Santa Engracia, 98 Madrid Madrid 28010",
    "addr:housenumber":"98",
    "addr:postcode":"madrid;28010",
    "addr:street":"Calle De Santa Engracia",
    "iso:country":"ES",
    "sg:address":"Calle de Santa Engracia, 98",
    "sg:city":"Madrid",
    "sg:orig_category":"Molduras, Junquillos, Listones Y Molduras Perforadas",
    "sg:phone":"+34 914 46 67 61",
    "sg:postcode":"28010",
    "sg:province":"Madrid",
    "wof:name":"Simon Martin Asuncion Elena",
    "wof:placetype":"venue"
},
  "geometry": {"coordinates":[-3.6999719143,40.4382247925],"type":"Point"}
}