{
  "type": "Feature",
  "properties": {
    "addr:full":"Cllo Moro, 12 Olias Rey Toledo 45280",
    "addr:housenumber":"12",
    "addr:postcode":"45280",
    "addr:street":"Moro",
    "iso:country":"ES",
    "sg:address":"Cllo Moro, 12",
    "sg:city":"Olias Rey",
    "sg:orig_category":"Puertas Y Portales",
    "sg:phone":"+34 925 49 08 95",
    "sg:postcode":"45280",
    "sg:province":"Toledo",
    "wof:name":"Tordesillas Mu\u00f1iz Ramon",
    "wof:placetype":"venue"
},
  "geometry": {"coordinates":[-3.9885389805,39.9435043335],"type":"Point"}
}