{
  "type": "Feature",
  "properties": {
    "iso:country":"ES",
    "sg:address":"Carrer de Paris, 16",
    "sg:city":"Hospitalet Llobregat",
    "sg:orig_category":"Molduras, Junquillos, Listones Y Molduras Perforadas",
    "sg:phone":"+34 933 34 28 54",
    "sg:postcode":"08903",
    "sg:province":"Barcelona",
    "wof:name":"Parrado Gonzalez Francisco",
    "wof:placetype":"venue"
},
  "geometry": {"coordinates":[2.120898962,41.3729820251],"type":"Point"}
}