{
  "type": "Feature",
  "properties": {
    "addr:full":"Plaz Mayor, 21 Meira Lugo 27240",
    "addr:housenumber":"21",
    "addr:postcode":"27240",
    "addr:street":"Plaz Mayor",
    "iso:country":"ES",
    "sg:address":"Plaz Mayor, 21",
    "sg:city":"Meira",
    "sg:orig_category":"Material Y Suministros Para Veterinarios",
    "sg:phone":"+34 982 35 67 07",
    "sg:postcode":"27240",
    "sg:province":"Lugo",
    "wof:name":"Zoonort S.l.",
    "wof:placetype":"venue"
},
  "geometry": {"coordinates":[-7.2934885025,43.2136116028],"type":"Point"}
}