{
  "type": "Feature",
  "properties": {
    "addr:full":"Rond Outeiro, S/n Coru\u00d1a La Coru\u00f1a 15011",
    "addr:housenumber":"s",
    "addr:postcode":"15011",
    "addr:street":"Outeiro;/ N Corun\u0303A La Corun\u0303A",
    "iso:country":"ES",
    "sg:address":"Rond Outeiro, S/n",
    "sg:city":"Coru\u00d1a",
    "sg:orig_category":"Centros De Educaci\u00d3n Especial",
    "sg:phone":"+34 981 17 59 68",
    "sg:postcode":"15011",
    "sg:province":"La Coru\u00f1a",
    "wof:name":"Colegio Publico San Francisco Javier",
    "wof:placetype":"venue"
},
  "geometry": {"coordinates":[-8.4252109528,43.3728866577],"type":"Point"}
}