{
  "type": "Feature",
  "properties": {
    "addr:full":"Calle de Picasso Pablo, 17 Bilbao Vizcaya 48012",
    "addr:housenumber":"17",
    "addr:postcode":"48012",
    "addr:street":"Calle De Picasso Pablo",
    "iso:country":"ES",
    "sg:address":"Calle de Picasso Pablo, 17",
    "sg:city":"Bilbao",
    "sg:orig_category":"Electricidad, Electr\u00d3nica: Material Y Suministros (al Por Mayor)",
    "sg:phone":"+34 944 44 62 35",
    "sg:postcode":"48012",
    "sg:province":"Vizcaya",
    "wof:name":"Comercial De Desarrollos Electronicos S.a.",
    "wof:placetype":"venue"
},
  "geometry": {"coordinates":[-2.9363648891,43.255695343],"type":"Point"}
}