{
  "type": "Feature",
  "properties": {
    "iso:country":"ES",
    "sg:address":"Perellonet, 9",
    "sg:city":"Torrent",
    "sg:orig_category":"Estilistas Y Estudios De Estilo De Corte Y Confecci\u00d3n",
    "sg:phone":"+34 961 58 85 90",
    "sg:postcode":"46900",
    "sg:province":"Valencia",
    "wof:name":"Ferraltex S.l.",
    "wof:placetype":"venue"
},
  "geometry": {"coordinates":[-0.4792639911,39.4371337891],"type":"Point"}
}