{
  "type": "Feature",
  "properties": {
    "addr:full":"Calle de Alferez Baanante, 5 Chantada Lugo 27500",
    "addr:housenumber":"5",
    "addr:postcode":"27500",
    "addr:street":"Calle De Alferez Baanante",
    "iso:country":"ES",
    "sg:address":"Calle de Alferez Baanante, 5",
    "sg:city":"Chantada",
    "sg:orig_category":"Molduras, Junquillos, Listones Y Molduras Perforadas",
    "sg:phone":"+34 982 44 10 87",
    "sg:postcode":"27500",
    "sg:province":"Lugo",
    "wof:name":"Galtelcom",
    "wof:placetype":"venue"
},
  "geometry": {"coordinates":[-7.7960119247,42.6083450317],"type":"Point"}
}