{
  "type": "Feature",
  "properties": {
    "addr:full":"Calle de Urquiza, 30 Madrid Madrid 28017",
    "addr:housenumber":"30",
    "addr:postcode":"madrid;28017",
    "addr:street":"Calle De Urquiza",
    "iso:country":"ES",
    "sg:address":"Calle de Urquiza, 30",
    "sg:city":"Madrid",
    "sg:orig_category":"Chapister\u00cda",
    "sg:phone":"+34 913 67 34 15",
    "sg:postcode":"28017",
    "sg:province":"Madrid",
    "sg:website":"www.lunasarevalillo.com",
    "wof:name":"Talleres Arevalillo S.a.",
    "wof:placetype":"venue"
},
  "geometry": {"coordinates":[-3.6451222897,40.4323883057],"type":"Point"}
}