{
  "type": "Feature",
  "properties": {
    "addr:full":"Carrer de Torrent De L'olla, 67 Barcelona Barcelona 08012",
    "addr:housenumber":"67",
    "addr:postcode":"08012",
    "addr:street":"Carrer De Torrent De L'Olla",
    "iso:country":"ES",
    "sg:address":"Carrer de Torrent De L'olla, 67",
    "sg:city":"Barcelona",
    "sg:orig_category":"Farmacias",
    "sg:phone":"+34 932 18 79 21",
    "sg:postcode":"08012",
    "sg:province":"Barcelona",
    "wof:name":"Vall Garriga Montserrat",
    "wof:placetype":"venue"
},
  "geometry": {"coordinates":[2.1587209702,41.400932312],"type":"Point"}
}