{
  "type": "Feature",
  "properties": {
    "addr:full":"La Constitucion, 4 Espinosa Monteros Burgos 09560",
    "addr:housenumber":"4",
    "addr:postcode":"09560",
    "addr:street":"Constitucion",
    "iso:country":"ES",
    "sg:address":"La Constitucion, 4",
    "sg:city":"Espinosa Monteros",
    "sg:orig_category":"Material Y Suministros Para Veterinarios",
    "sg:phone":"+34 947 12 04 95",
    "sg:postcode":"09560",
    "sg:province":"Burgos",
    "wof:name":"Distribuidora De Productos Veterinarios S. A.",
    "wof:placetype":"venue"
},
  "geometry": {"coordinates":[-3.5528199673,43.0758666992],"type":"Point"}
}