{
  "type": "Feature",
  "properties": {
    "addr:full":"Avda Tenor Fleta, 122 Zaragoza Zaragoza 50007",
    "addr:housenumber":"122",
    "addr:postcode":"50007",
    "addr:street":"Avda Tenor Fleta",
    "iso:country":"ES",
    "sg:address":"Avda Tenor Fleta, 122",
    "sg:city":"Zaragoza",
    "sg:orig_category":"Papeler\u00cdas, Librer\u00cdas",
    "sg:phone":"+34 976 37 58 52",
    "sg:postcode":"50007",
    "sg:province":"Zaragoza",
    "wof:name":"Bermudez Galan Jesus Maria",
    "wof:placetype":"venue"
},
  "geometry": {"coordinates":[-0.8778820038,41.6379203796],"type":"Point"}
}