{
  "type": "Feature",
  "properties": {
    "iso:country":"ES",
    "sg:address":"Calle de O\u00d1a, 41",
    "sg:city":"Madrid",
    "sg:orig_category":"Agencias Y Agentes Comerciales, Representantes",
    "sg:phone":"+34 915 72 14 85",
    "sg:postcode":"28050",
    "sg:province":"Madrid",
    "wof:name":"Intermediacion Soja Cereales S.l.",
    "wof:placetype":"venue"
},
  "geometry": {"coordinates":[-3.6675589085,40.4890441895],"type":"Point"}
}