{
  "type": "Feature",
  "properties": {
    "iso:country":"ES",
    "sg:address":"Calle de Arriaga, 2",
    "sg:city":"Barakaldo",
    "sg:orig_category":"Empresas De Pintura Y Revestimientos",
    "sg:phone":"+34 944 04 45 81",
    "sg:postcode":"48903",
    "sg:province":"Vizcaya",
    "wof:name":"Pinturas Barakolor",
    "wof:placetype":"venue"
},
  "geometry": {"coordinates":[-2.9799699783,43.2868041992],"type":"Point"}
}