{
  "type": "Feature",
  "properties": {
    "iso:country":"ES",
    "sg:address":"Calle de Cuesta De Las Caballeras, 11",
    "sg:city":"Montilla",
    "sg:orig_category":"Enfermeras: Consultas, Atenci\u00d3n A Domicilio",
    "sg:phone":"+34 957 65 56 64",
    "sg:postcode":"14550",
    "sg:province":"C\u00f3rdoba",
    "wof:name":"Ponferrada Panadero Manuel",
    "wof:placetype":"venue"
},
  "geometry": {"coordinates":[-4.6376051903,37.5869178772],"type":"Point"}
}