{
  "type": "Feature",
  "properties": {
    "iso:country":"ES",
    "sg:address":"Calle de San Bernardo, 2",
    "sg:city":"Peal Becerro",
    "sg:orig_category":"Abogados",
    "sg:phone":"+34 953 73 01 20",
    "sg:postcode":"23460",
    "sg:province":"Ja\u00e9n",
    "wof:name":"Pelegrin Carrillo Bernardo",
    "wof:placetype":"venue"
},
  "geometry": {"coordinates":[-3.1177790165,37.9137382507],"type":"Point"}
}