{
  "type": "Feature",
  "properties": {
    "addr:full":"Carrer de Tarragona, 2 Playa Muchavista Alicante 03560",
    "addr:housenumber":"2",
    "addr:postcode":"03560",
    "addr:street":"Carrer De Tarragona;Muchavista",
    "iso:country":"ES",
    "sg:address":"Carrer de Tarragona, 2",
    "sg:city":"Playa Muchavista",
    "sg:orig_category":"Empresas De Limpieza",
    "sg:phone":"+34 965 94 02 81",
    "sg:postcode":"03560",
    "sg:province":"Alicante",
    "wof:name":"Genser S.l.",
    "wof:placetype":"venue"
},
  "geometry": {"coordinates":[-0.4081090093,38.3975982666],"type":"Point"}
}