{
  "type": "Feature",
  "properties": {
    "iso:country":"ES",
    "sg:address":"Ctra Juncal (el), S/n",
    "sg:city":"Ugarte",
    "sg:orig_category":"Empresas De Carpinter\u00cda De Madera",
    "sg:phone":"+34 944 37 45 46",
    "sg:postcode":"48510",
    "sg:province":"Vizcaya",
    "wof:name":"Juan Jesus E Ignacio Hernandez Gonzalez C.b.",
    "wof:placetype":"venue"
},
  "geometry": {"coordinates":[-3.0369338989,43.3047294617],"type":"Point"}
}