{
  "type": "Feature",
  "properties": {
    "addr:full":"Cmno Camino De La Soledad, 19 Chiclana De La Frontera C\u00e1diz 11130",
    "addr:housenumber":"19",
    "addr:postcode":"11130",
    "addr:street":"Cmno Camino De La Soledad",
    "iso:country":"ES",
    "sg:address":"Cmno Camino De La Soledad, 19",
    "sg:city":"Chiclana De La Frontera",
    "sg:orig_category":"Administradores De Bienes Y Delegados De Comunidades De Propietarios",
    "sg:phone":"+34 956 40 20 59",
    "sg:postcode":"11130",
    "sg:province":"C\u00e1diz",
    "wof:name":"Zafra Casas Esther",
    "wof:placetype":"venue"
},
  "geometry": {"coordinates":[-6.1479110718,36.42137146],"type":"Point"}
}