{
  "type": "Feature",
  "properties": {
    "addr:full":"Rbla Jaume Sabat, 10 S. Cugat Valles Barcelona 08172",
    "addr:housenumber":"10",
    "addr:postcode":"08172",
    "addr:street":"Rbla Jaume Sabat;Barcelona",
    "iso:country":"ES",
    "sg:address":"Rbla Jaume Sabat, 10",
    "sg:city":"S. Cugat Valles",
    "sg:orig_category":"Sociedades, Compa\u00d1\u00cdas Aseguradoras",
    "sg:phone":"+34 935 89 50 48",
    "sg:postcode":"08172",
    "sg:province":"Barcelona",
    "wof:name":"Asistencia Sanitaria Colegial S.a.",
    "wof:placetype":"venue"
},
  "geometry": {"coordinates":[2.0831677914,41.4705085754],"type":"Point"}
}