{
  "type": "Feature",
  "properties": {
    "iso:country":"ES",
    "sg:address":"Cno Cascante, S/n",
    "sg:city":"Cintruenigo",
    "sg:orig_category":"Construcciones Met\u00c1licas",
    "sg:phone":"+34 948 81 11 64",
    "sg:postcode":"31592",
    "sg:province":"Navarra",
    "wof:name":"Navascues Garbayo Fermin",
    "wof:placetype":"venue"
},
  "geometry": {"coordinates":[-1.7964639664,42.0835533142],"type":"Point"}
}