{
  "type": "Feature",
  "properties": {
    "addr:full":"Ctra Alicante (de), Km. 0750,0 Santomera Murcia 30140",
    "addr:postcode":"30140",
    "addr:street":"Ctra Alicante De Km. 0750,0",
    "iso:country":"ES",
    "sg:address":"Ctra Alicante (de), Km. 0750,0",
    "sg:city":"Santomera",
    "sg:orig_category":"Promotores Constructores",
    "sg:phone":"+34 968 86 32 94",
    "sg:postcode":"30140",
    "sg:province":"Murcia",
    "wof:name":"Repsol Ypf S.a.",
    "wof:placetype":"venue"
},
  "geometry": {"coordinates":[-1.0543140173,38.0592765808],"type":"Point"}
}