{
  "type": "Feature",
  "properties": {
    "addr:full":"Calle de San Miguel, 12 Bocairent Valencia 46880",
    "addr:housenumber":"12",
    "addr:postcode":"46880",
    "addr:street":"Calle De San Miguel",
    "iso:country":"ES",
    "sg:address":"Calle de San Miguel, 12",
    "sg:city":"Bocairent",
    "sg:orig_category":"Hilaturas, Hilos Y Actividades Relacionadas",
    "sg:phone":"+34 962 35 01 83",
    "sg:postcode":"46880",
    "sg:province":"Valencia",
    "wof:name":"Herbeva S. L.",
    "wof:placetype":"venue"
},
  "geometry": {"coordinates":[-0.6148200035,38.7652854919],"type":"Point"}
}