{
  "type": "Feature",
  "properties": {
    "iso:country":"ES",
    "sg:address":"Ctra Porzuna, S/n",
    "sg:city":"Ciudad Real",
    "sg:orig_category":"Molduras, Junquillos, Listones Y Molduras Perforadas",
    "sg:phone":"+34 926 22 45 82",
    "sg:postcode":"13002",
    "sg:province":"Ciudad Real",
    "wof:name":"Maldonado Ortiz Manuel",
    "wof:placetype":"venue"
},
  "geometry": {"coordinates":[-3.9350841045,38.990234375],"type":"Point"}
}