{
  "type": "Feature",
  "properties": {
    "iso:country":"ES",
    "sg:address":"Calle de Molares, 27",
    "sg:city":"Utrera",
    "sg:orig_category":"Bisuter\u00cda, Joyer\u00cda, Relojer\u00cda (al Por Menor)",
    "sg:phone":"+34 954 86 28 85",
    "sg:postcode":"41710",
    "sg:province":"Sevilla",
    "wof:name":"Coronilla Morilla Juana",
    "wof:placetype":"venue"
},
  "geometry": {"coordinates":[-5.7749547958,37.1788825989],"type":"Point"}
}