{
  "type": "Feature",
  "properties": {
    "iso:country":"ES",
    "sg:address":"Carrer de L'encuny, 24",
    "sg:city":"Barcelona",
    "sg:orig_category":"Chapas Y Flejes De Acero",
    "sg:phone":"+34 932 23 32 00",
    "sg:postcode":"08038",
    "sg:province":"Barcelona",
    "wof:name":"Hijos De Juan Vacarisas S. A.",
    "wof:placetype":"venue"
},
  "geometry": {"coordinates":[2.145252943,41.3546714783],"type":"Point"}
}