{
  "type": "Feature",
  "properties": {
    "addr:full":"Calle de San Juan, 6 Alsasua Navarra 31800",
    "addr:housenumber":"6",
    "addr:postcode":"31800",
    "addr:street":"Calle De San Juan",
    "iso:country":"ES",
    "sg:address":"Calle de San Juan, 6",
    "sg:city":"Alsasua",
    "sg:orig_category":"Electricidad, Electr\u00d3nica: Suministros (al Por Menor)",
    "sg:phone":"+34 948 46 80 12",
    "sg:postcode":"31800",
    "sg:province":"Navarra",
    "wof:name":"Beraiz Lizarraga Julia",
    "wof:placetype":"venue"
},
  "geometry": {"coordinates":[-2.1698460579,42.8956794739],"type":"Point"}
}