{
  "type": "Feature",
  "properties": {
    "iso:country":"ES",
    "sg:address":"Av Valencia, 1",
    "sg:city":"Benidorm",
    "sg:orig_category":"Ropa Para Se\u00d1oras Y Caballeros (al Por Menor)",
    "sg:phone":"+34 966 80 17 13",
    "sg:postcode":"03500",
    "sg:province":"Alicante",
    "wof:name":"Bustins Frigola Rosa",
    "wof:placetype":"venue"
},
  "geometry": {"coordinates":[-0.1267360002,38.5362167358],"type":"Point"}
}