{
  "type": "Feature",
  "properties": {
    "addr:full":"Calle de Puerto De Arlaban, 49 Madrid Madrid 28053",
    "addr:housenumber":"49",
    "addr:postcode":"madrid;28053",
    "addr:street":"Calle De Puerto De Arlaban",
    "iso:country":"ES",
    "sg:address":"Calle de Puerto De Arlaban, 49",
    "sg:city":"Madrid",
    "sg:orig_category":"Confecci\u00d3n De Trajes Para Se\u00d1oras",
    "sg:phone":"+34 914 78 43 66",
    "sg:postcode":"28053",
    "sg:province":"Madrid",
    "wof:name":"Yera Olmedo Juan",
    "wof:placetype":"venue"
},
  "geometry": {"coordinates":[-3.6663177013,40.3873748779],"type":"Point"}
}