{
  "type": "Feature",
  "properties": {
    "iso:country":"ES",
    "sg:address":"Calle de Beko Benta, 10",
    "sg:city":"Markina-xemein",
    "sg:orig_category":"Electricidad: Instaladores",
    "sg:phone":"+34 946 16 75 74",
    "sg:postcode":"48270",
    "sg:province":"Vizcaya",
    "wof:name":"Ekin Electricidad",
    "wof:placetype":"venue"
},
  "geometry": {"coordinates":[-2.4973361492,43.2714385986],"type":"Point"}
}