{
  "type": "Feature",
  "properties": {
    "iso:country":"ES",
    "sg:address":"Ctra Reus-cambrils, S/n",
    "sg:city":"Vinyols I Els Arcs",
    "sg:orig_category":"Reciclaje, Desguace De Veh\u00cdculos",
    "sg:phone":"+34 977 26 93 13",
    "sg:postcode":"43391",
    "sg:province":"Tarragona",
    "wof:name":"Perez Quero Francisco",
    "wof:placetype":"venue"
},
  "geometry": {"coordinates":[1.042050004,41.1135597229],"type":"Point"}
}