{
  "type": "Feature",
  "properties": {
    "iso:country":"ES",
    "sg:address":"Carrer de Guifre El Pelos, 26",
    "sg:city":"Viladecans",
    "sg:orig_category":"Acero: Productos Sider\u00dargicos Y Transformados (fabricaci\u00d3n, Negocio)",
    "sg:phone":"+34 936 59 18 60",
    "sg:postcode":"08840",
    "sg:province":"Barcelona",
    "sg:website":"www.inoxparareda.net",
    "wof:name":"Inox Parareda S.l.",
    "wof:placetype":"venue"
},
  "geometry": {"coordinates":[2.025357008,41.316696167],"type":"Point"}
}