{
  "type": "Feature",
  "properties": {
    "addr:full":"Calle de Colquide, 6 Rozas De Madrid Madrid 28230",
    "addr:housenumber":"6",
    "addr:postcode":"28230",
    "addr:street":"Calle De Colquide",
    "iso:country":"ES",
    "sg:address":"Calle de Colquide, 6",
    "sg:city":"Rozas De Madrid",
    "sg:orig_category":"Asesor\u00cda Fiscal Y Jur\u00cddica",
    "sg:phone":"+34 917 10 50 55",
    "sg:postcode":"28230",
    "sg:province":"Madrid",
    "sg:website":"www.aduldacio.com",
    "wof:name":"Adul-dacio S.l.",
    "wof:placetype":"venue"
},
  "geometry": {"coordinates":[-3.875235796,40.5000686646],"type":"Point"}
}