{
  "type": "Feature",
  "properties": {
    "iso:country":"ES",
    "sg:address":"Calle de Josue Lillo, 7",
    "sg:city":"Madrid",
    "sg:orig_category":"Escultores, Estatuarios E Imagineros",
    "sg:phone":"+34 914 78 79 56",
    "sg:postcode":"28053",
    "sg:province":"Madrid",
    "wof:name":"Gonzalez Romo Mariano",
    "wof:placetype":"venue"
},
  "geometry": {"coordinates":[-3.6681320667,40.3861656189],"type":"Point"}
}