{
  "type": "Feature",
  "properties": {
    "iso:country":"ES",
    "sg:address":"Carrer de Esglesia, 61",
    "sg:city":"Castelldefels",
    "sg:orig_category":"Tintorer\u00cdas, Limpieza En Seco",
    "sg:phone":"+34 936 65 02 45",
    "sg:postcode":"08860",
    "sg:province":"Barcelona",
    "wof:name":"Cano Jover Luis",
    "wof:placetype":"venue"
},
  "geometry": {"coordinates":[1.9813530445,41.2842559814],"type":"Point"}
}