{
  "type": "Feature",
  "properties": {
    "iso:country":"ES",
    "sg:address":"Rua Garcia Lorca, 3",
    "sg:city":"Vigo",
    "sg:orig_category":"Frutas, Legumbres Frescas Y Tempranas (al Por Menor)",
    "sg:phone":"+34 986 23 67 38",
    "sg:postcode":"36209",
    "sg:province":"Pontevedra",
    "wof:name":"Lemos Alvarez Gerardo",
    "wof:placetype":"venue"
},
  "geometry": {"coordinates":[-8.7358179092,42.2191047668],"type":"Point"}
}