{
  "type": "Feature",
  "properties": {
    "addr:full":"Calle de Portada, 11 Palma Rio C\u00f3rdoba 14700",
    "addr:housenumber":"11",
    "addr:postcode":"14700",
    "addr:street":"Calle De Portada;Rio Co\u0301Rdoba",
    "iso:country":"ES",
    "sg:address":"Calle de Portada, 11",
    "sg:city":"Palma Rio",
    "sg:orig_category":"Agentes Generales De Seguros",
    "sg:phone":"+34 957 64 51 45",
    "sg:postcode":"14700",
    "sg:province":"C\u00f3rdoba",
    "wof:name":"Dominguez Alcaraz Pablo",
    "wof:placetype":"venue"
},
  "geometry": {"coordinates":[-5.2820219994,37.6965255737],"type":"Point"}
}