{
  "type": "Feature",
  "properties": {
    "iso:country":"ES",
    "sg:address":"Calle de Doctor Ramon Y Cajal, 32",
    "sg:city":"Atarfe",
    "sg:orig_category":"Cristaler\u00cdas",
    "sg:phone":"+34 958 43 86 53",
    "sg:postcode":"18230",
    "sg:province":"Granada",
    "wof:name":"Trujillo Ramos Antonio",
    "wof:placetype":"venue"
},
  "geometry": {"coordinates":[-3.6873469353,37.2244720459],"type":"Point"}
}