{
  "type": "Feature",
  "properties": {
    "addr:full":"Calle de Olas (las), S/n Costa Teguise Las Palmas 35509",
    "addr:postcode":"35509",
    "addr:street":"Calle De Olas Las S / N",
    "iso:country":"ES",
    "sg:address":"Calle de Olas (las), S/n",
    "sg:city":"Costa Teguise",
    "sg:orig_category":"Complementos De Vestir (al Por Menor)",
    "sg:phone":"+34 928 59 03 87",
    "sg:postcode":"35509",
    "sg:province":"Las Palmas",
    "wof:name":"Barrios Peraza Maria De Las Nieves",
    "wof:placetype":"venue"
},
  "geometry": {"coordinates":[-13.5916891098,28.955160141],"type":"Point"}
}