{
  "type": "Feature",
  "properties": {
    "addr:full":"Carrer de Parellades, 37 Sitges Barcelona 08870",
    "addr:housenumber":"37",
    "addr:postcode":"08870",
    "addr:street":"Carrer De Parellades",
    "iso:country":"ES",
    "sg:address":"Carrer de Parellades, 37",
    "sg:city":"Sitges",
    "sg:orig_category":"Camiser\u00cda Y Ropa Interior Masculina (al Por Menor)",
    "sg:phone":"+34 938 94 14 20",
    "sg:postcode":"08870",
    "sg:province":"Barcelona",
    "sg:website":"www.intimissimi.com",
    "wof:name":"Calzintimi S.l.",
    "wof:placetype":"venue"
},
  "geometry": {"coordinates":[1.80727005,41.2363166809],"type":"Point"}
}