{
  "type": "Feature",
  "properties": {
    "iso:country":"ES",
    "sg:address":"Av Diagonal, 3",
    "sg:city":"Torredembarra",
    "sg:classifiers":[
        {
            "category":"Taxi",
            "type":"Transportation"
        }
    ],
    "sg:phone":"+34 977 64 37 75",
    "sg:postcode":"43830",
    "sg:province":"Tarragona",
    "wof:name":"Moreno Reche Jose Antonio",
    "wof:placetype":"venue"
},
  "geometry": {"coordinates":[1.4024349451,41.1467857361],"type":"Point"}
}