{
  "type": "Feature",
  "properties": {
    "addr:full":"Avenida Del Parroco Villanueva, 21 Sada A Coru\u00f1a 15160",
    "addr:housenumber":"21",
    "addr:postcode":"15160",
    "addr:street":"Avenida Del Parroco Villanueva",
    "iso:country":"ES",
    "sg:address":"Avenida Del Parroco Villanueva, 21",
    "sg:city":"Sada",
    "sg:orig_category":"Asociaciones, Organismos Culturales Y Socioeducativos",
    "sg:phone":"+34 981 62 01 07",
    "sg:postcode":"15160",
    "sg:province":"A Coru\u00f1a",
    "wof:name":"Sociedad Recreativa Cultural Deportiva",
    "wof:placetype":"venue"
},
  "geometry": {"coordinates":[-8.2563991547,43.3526611328],"type":"Point"}
}