{
  "type": "Feature",
  "properties": {
    "iso:country":"ES",
    "sg:address":"Ptda Cremats, S/n",
    "sg:city":"Benaguasil",
    "sg:orig_category":"Materias Pl\u00c1sticas: Art\u00cdculos Para La Industria",
    "sg:phone":"+34 962 73 75 00",
    "sg:postcode":"46180",
    "sg:province":"Valencia",
    "wof:name":"Plasben S.l.",
    "wof:placetype":"venue"
},
  "geometry": {"coordinates":[-0.6052240133,39.5940246582],"type":"Point"}
}