{
  "type": "Feature",
  "properties": {
    "iso:country":"ES",
    "sg:address":"Avda Jaime I, 65",
    "sg:city":"Vall D'uixo",
    "sg:orig_category":"Reposter\u00cdas",
    "sg:phone":"+34 964 66 15 95",
    "sg:postcode":"12600",
    "sg:province":"Castell\u00f3n",
    "wof:name":"Miralles Langa Jose Javier",
    "wof:placetype":"venue"
},
  "geometry": {"coordinates":[-0.2328158021,39.8183822632],"type":"Point"}
}