{
  "type": "Feature",
  "properties": {
    "iso:country":"ES",
    "sg:address":"Calle de Libreros, 6",
    "sg:city":"Madrid",
    "sg:orig_category":"Empresarios",
    "sg:phone":"+34 915 32 91 92",
    "sg:postcode":"28004",
    "sg:province":"Madrid",
    "sg:website":"www.matercristi.es",
    "wof:name":"Fundacion Mater Cristi",
    "wof:placetype":"venue"
},
  "geometry": {"coordinates":[-3.7065210342,40.4216117859],"type":"Point"}
}