{
  "type": "Feature",
  "properties": {
    "iso:country":"ES",
    "sg:address":"Avda Martinez De Velasco, 83",
    "sg:city":"Huesca",
    "sg:orig_category":"Supermercados Y Hipermercados",
    "sg:phone":"+34 974 21 50 54",
    "sg:postcode":"22004",
    "sg:province":"Huesca",
    "wof:name":"Samper Florian Maria Susana",
    "wof:placetype":"venue"
},
  "geometry": {"coordinates":[-0.4207220078,42.1303863525],"type":"Point"}
}