{
  "type": "Feature",
  "properties": {
    "addr:full":"Rua Sanjurjo Badia, 132 Vigo Pontevedra 36207",
    "addr:housenumber":"132",
    "addr:postcode":"36207",
    "addr:street":"Rua Sanjurjo Badia",
    "iso:country":"ES",
    "sg:address":"Rua Sanjurjo Badia, 132",
    "sg:city":"Vigo",
    "sg:orig_category":"Asistencia Y Consejos",
    "sg:phone":"+34 986 37 34 33",
    "sg:postcode":"36207",
    "sg:province":"Pontevedra",
    "wof:name":"Asesoria Y Gestiones Mallo S.l.",
    "wof:placetype":"venue"
},
  "geometry": {"coordinates":[-8.7019166946,42.2458953857],"type":"Point"}
}