{
  "type": "Feature",
  "properties": {
    "iso:country":"ES",
    "sg:address":"Carrer de Pompeu Fabra, 23",
    "sg:city":"Ametlla Valles",
    "sg:orig_category":"Cajas De Ahorro",
    "sg:phone":"+34 938 43 17 32",
    "sg:postcode":"08480",
    "sg:province":"Barcelona",
    "wof:name":"Caixa De Manlleu",
    "wof:placetype":"venue"
},
  "geometry": {"coordinates":[2.262773037,41.6667060852],"type":"Point"}
}