{
  "type": "Feature",
  "properties": {
    "iso:country":"ES",
    "sg:address":"Carrer de Major, 25",
    "sg:city":"Selva Del Camp",
    "sg:orig_category":"Electrodom\u00c9sticos (al Por Menor)",
    "sg:phone":"+34 977 84 51 25",
    "sg:postcode":"43470",
    "sg:province":"Tarragona",
    "wof:name":"Mestre Ferre Jose Maria",
    "wof:placetype":"venue"
},
  "geometry": {"coordinates":[1.1383240223,41.2147636414],"type":"Point"}
}