{
  "type": "Feature",
  "properties": {
    "iso:country":"ES",
    "sg:address":"Plaz Carmen (del), 3",
    "sg:city":"Velez-malaga",
    "sg:orig_category":"Abogados",
    "sg:phone":"+34 952 50 74 47",
    "sg:postcode":"29700",
    "sg:province":"M\u00e1laga",
    "sg:website":"www.aretesabogados.es",
    "wof:name":"Aretes Abogados S.c.",
    "wof:placetype":"venue"
},
  "geometry": {"coordinates":[-4.141140461,36.7639465332],"type":"Point"}
}