{
  "type": "Feature",
  "properties": {
    "addr:full":"Nueva-kale Berria, 30 Iru\u00f1a Navarra 31001",
    "addr:housenumber":"30",
    "addr:postcode":"31001",
    "addr:street":"Berria",
    "iso:country":"ES",
    "sg:address":"Nueva-kale Berria, 30",
    "sg:city":"Iru\u00f1a",
    "sg:orig_category":"Psic\u00d3logos",
    "sg:phone":"+34 948 22 98 90",
    "sg:postcode":"31001",
    "sg:province":"Navarra",
    "wof:name":"Ros Morencos Ricardo",
    "wof:placetype":"venue"
},
  "geometry": {"coordinates":[-1.6437540054,42.81275177],"type":"Point"}
}