{
  "type": "Feature",
  "properties": {
    "addr:full":"Plaz Beltran Martinez, 1 Zaragoza Zaragoza 50001",
    "addr:housenumber":"1",
    "addr:postcode":"50001",
    "addr:street":"Martinez",
    "iso:country":"ES",
    "sg:address":"Plaz Beltran Martinez, 1",
    "sg:city":"Zaragoza",
    "sg:orig_category":"Agentes Generales De Seguros",
    "sg:phone":"+34 976 39 12 35",
    "sg:postcode":"50001",
    "sg:province":"Zaragoza",
    "sg:website":"www.aviva.es",
    "wof:name":"Comunitel Global S.a.",
    "wof:placetype":"venue"
},
  "geometry": {"coordinates":[-0.8813189864,41.6517295837],"type":"Point"}
}