{
  "type": "Feature",
  "properties": {
    "addr:full":"Calle de Fueros, 26 Vitoria-gasteiz \u00c1lava 01005",
    "addr:housenumber":"26",
    "addr:postcode":"01005",
    "addr:street":"Calle De Fueros",
    "iso:country":"ES",
    "sg:address":"Calle de Fueros, 26",
    "sg:city":"Vitoria-gasteiz",
    "sg:orig_category":"M\u00c9dicos: Otorrinolaringolog\u00cda",
    "sg:phone":"+34 945 23 00 33",
    "sg:postcode":"01005",
    "sg:province":"\u00c1lava",
    "wof:name":"Rodriguez Gomez Enrique",
    "wof:placetype":"venue"
},
  "geometry": {"coordinates":[-2.6704330444,42.8422584534],"type":"Point"}
}