{
  "type": "Feature",
  "properties": {
    "addr:full":"Ctra Gral, 250 Santiago Cantabria 39311",
    "addr:housenumber":"250",
    "addr:postcode":"39311",
    "addr:street":"Ctra Gral",
    "iso:country":"ES",
    "sg:address":"Ctra Gral, 250",
    "sg:city":"Santiago",
    "sg:orig_category":"Art\u00cdculos De Aluminio",
    "sg:phone":"+34 942 88 28 41",
    "sg:postcode":"39311",
    "sg:province":"Cantabria",
    "wof:name":"Umecan S.l.",
    "wof:placetype":"venue"
},
  "geometry": {"coordinates":[-4.0702290535,43.3219108582],"type":"Point"}
}