{
  "type": "Feature",
  "properties": {
    "addr:full":"Calle de Esparteros, 16 Madrid Madrid 28012",
    "addr:housenumber":"16",
    "addr:postcode":"madrid;28012",
    "addr:street":"Calle De Esparteros",
    "iso:country":"ES",
    "sg:address":"Calle de Esparteros, 16",
    "sg:city":"Madrid",
    "sg:orig_category":"Filatelia",
    "sg:phone":"+34 915 22 80 39",
    "sg:postcode":"28012",
    "sg:province":"Madrid",
    "wof:name":"Pariente Correal Raquel",
    "wof:placetype":"venue"
},
  "geometry": {"coordinates":[-3.7055559158,40.4155235291],"type":"Point"}
}