{
  "type": "Feature",
  "properties": {
    "iso:country":"ES",
    "sg:address":"A Oliveira, 13",
    "sg:city":"Ponteareas",
    "sg:orig_category":"Puertas Autom\u00c1ticas, Puertas De Garaje",
    "sg:phone":"+34 986 66 16 28",
    "sg:postcode":"36892",
    "sg:province":"Pontevedra",
    "wof:name":"Barchetta  Haroldo Daniel",
    "wof:placetype":"venue"
},
  "geometry": {"coordinates":[-8.4606618881,42.1719589233],"type":"Point"}
}