{
  "type": "Feature",
  "properties": {
    "iso:country":"ES",
    "sg:address":"Calle de San Pascual, 16",
    "sg:city":"Burriana",
    "sg:orig_category":"Ense\u00d1ante, Direcci\u00d3n",
    "sg:phone":"+34 964 51 12 16",
    "sg:postcode":"12530",
    "sg:province":"Castell\u00f3n",
    "wof:name":"Carda Isach Susana",
    "wof:placetype":"venue"
},
  "geometry": {"coordinates":[-0.0839819983,39.8911132812],"type":"Point"}
}