{
  "type": "Feature",
  "properties": {
    "iso:country":"ES",
    "sg:address":"Calle de Pontevedra, 7",
    "sg:city":"Armilla",
    "sg:orig_category":"Art\u00cdculos Funerarios (al Por Menor)",
    "sg:phone":"+34 958 57 14 31",
    "sg:postcode":"18100",
    "sg:province":"Granada",
    "wof:name":"Toro Siles Angeles",
    "wof:placetype":"venue"
},
  "geometry": {"coordinates":[-3.6235392094,37.1429901123],"type":"Point"}
}