{
  "type": "Feature",
  "properties": {
    "addr:full":"G.v. Corts Catalanes, 1003 Barcelona Barcelona 08020",
    "addr:postcode":"1003;08020",
    "addr:street":"Catalanes",
    "iso:country":"ES",
    "sg:address":"G.v. Corts Catalanes, 1003",
    "sg:city":"Barcelona",
    "sg:orig_category":"Herboristas (al Por Menor)",
    "sg:phone":"+34 932 66 18 13",
    "sg:postcode":"08020",
    "sg:province":"Barcelona",
    "wof:name":"Herbocat S.l.",
    "wof:placetype":"venue"
},
  "geometry": {"coordinates":[2.199062109,41.4130973816],"type":"Point"}
}