{
  "type": "Feature",
  "properties": {
    "addr:full":"Calle de Carolina Paino, 4 Madrid Madrid 28025",
    "addr:housenumber":"4",
    "addr:postcode":"28025",
    "addr:street":"Calle De Carolina Paino",
    "iso:country":"ES",
    "sg:address":"Calle de Carolina Paino, 4",
    "sg:city":"Madrid",
    "sg:orig_category":"Construcciones Met\u00c1licas",
    "sg:phone":"+34 914 61 12 56",
    "sg:postcode":"28025",
    "sg:province":"Madrid",
    "wof:name":"Mu\u00f1oz Montajes Industriales S.a.",
    "wof:placetype":"venue"
},
  "geometry": {"coordinates":[-3.7411792278,40.3844261169],"type":"Point"}
}