{
  "type": "Feature",
  "properties": {
    "addr:full":"Rua Alfonso R Castelao, 3 Estrada Pontevedra 36680",
    "addr:housenumber":"3",
    "addr:postcode":"36680",
    "addr:street":"Rua Alfonso R Castelao;Estrada Pontevedra",
    "iso:country":"ES",
    "sg:address":"Rua Alfonso R Castelao, 3",
    "sg:city":"Estrada",
    "sg:orig_category":"Asesor\u00cda Sobre Comunicaci\u00d3n De Empresas",
    "sg:phone":"+34 986 59 00 78",
    "sg:postcode":"36680",
    "sg:province":"Pontevedra",
    "wof:name":"Parque 7 La Estrada S.l.",
    "wof:placetype":"venue"
},
  "geometry": {"coordinates":[-8.4864387512,42.6871681213],"type":"Point"}
}