{
  "type": "Feature",
  "properties": {
    "iso:country":"ES",
    "sg:address":"Calle de Alcalde Lopez Mulero, 8",
    "sg:city":"Oviedo",
    "sg:orig_category":"Peluqueros: De Se\u00d1oras",
    "sg:phone":"+34 985 29 06 60",
    "sg:postcode":"33011",
    "sg:province":"Asturias",
    "wof:name":"Covadonga Lopez Fraga",
    "wof:placetype":"venue"
},
  "geometry": {"coordinates":[-5.8199725151,43.3755836487],"type":"Point"}
}