{
  "type": "Feature",
  "properties": {
    "iso:country":"ES",
    "sg:address":"Daimuz Bajo, 3",
    "sg:city":"Lachar",
    "sg:orig_category":"Cr\u00cda De Animales",
    "sg:phone":"+34 958 45 71 90",
    "sg:postcode":"18327",
    "sg:province":"Granada",
    "wof:name":"Lodaisa S.c.a.",
    "wof:placetype":"venue"
},
  "geometry": {"coordinates":[-3.8345489502,37.1960754395],"type":"Point"}
}