{
  "type": "Feature",
  "properties": {
    "iso:country":"ES",
    "sg:address":"Carrer de Camp, 29",
    "sg:city":"Barcelona",
    "sg:orig_category":"Edici\u00d3n, Venta De Partituras Musicales",
    "sg:phone":"+34 934 18 61 44",
    "sg:postcode":"08022",
    "sg:province":"Barcelona",
    "sg:website":"www.tanitmusic.com",
    "wof:name":"Tanit Music S.l.",
    "wof:placetype":"venue"
},
  "geometry": {"coordinates":[2.1368749142,41.4026222229],"type":"Point"}
}