{
  "type": "Feature",
  "properties": {
    "iso:country":"ES",
    "sg:address":"Avda Doctor Gomez Ferrer, 5",
    "sg:city":"Alfafar",
    "sg:orig_category":"Empresas De Carpinter\u00cda De Madera",
    "sg:phone":"+34 963 75 47 91",
    "sg:postcode":"46910",
    "sg:province":"Valencia",
    "wof:name":"Felipe Ferrer Tejedor S. L.",
    "wof:placetype":"venue"
},
  "geometry": {"coordinates":[-0.3895890117,39.4208602905],"type":"Point"}
}