{
  "type": "Feature",
  "properties": {
    "addr:full":"Carr Sant Miquel (de), 30 Lliria Valencia 46160",
    "addr:housenumber":"30",
    "addr:postcode":"46160",
    "addr:street":"Carr Sant Miquel De",
    "iso:country":"ES",
    "sg:address":"Carr Sant Miquel (de), 30",
    "sg:city":"Lliria",
    "sg:orig_category":"Metales (labores, Pulido)",
    "sg:phone":"+34 962 79 23 22",
    "sg:postcode":"46160",
    "sg:province":"Valencia",
    "wof:name":"Vivo Fernandez Cesar Jesus",
    "wof:placetype":"venue"
},
  "geometry": {"coordinates":[-0.5971363187,39.6270942688],"type":"Point"}
}