{
  "type": "Feature",
  "properties": {
    "iso:country":"ES",
    "sg:address":"Calle de F(campollano), 15",
    "sg:city":"Albacete",
    "sg:orig_category":"Negocio De Madera",
    "sg:phone":"+34 967 52 20 31",
    "sg:postcode":"02006",
    "sg:province":"Albacete",
    "wof:name":"Tableman S.a.",
    "wof:placetype":"venue"
},
  "geometry": {"coordinates":[-1.9490209818,39.013168335],"type":"Point"}
}