{
  "type": "Feature",
  "properties": {
    "addr:full":"Calle de Alfredo Tella, 11 Coru\u00d1a La Coru\u00f1a 15010",
    "addr:housenumber":"11",
    "addr:postcode":"15010",
    "addr:street":"Calle De Alfredo Tella;La Corun\u0303A",
    "iso:country":"ES",
    "sg:address":"Calle de Alfredo Tella, 11",
    "sg:city":"Coru\u00d1a",
    "sg:orig_category":"Reposter\u00cdas",
    "sg:phone":"+34 981 14 04 24",
    "sg:postcode":"15010",
    "sg:province":"La Coru\u00f1a",
    "wof:name":"Rozamontes Deus Angeles",
    "wof:placetype":"venue"
},
  "geometry": {"coordinates":[-8.4224643707,43.3604698181],"type":"Point"}
}