{
  "type": "Feature",
  "properties": {
    "addr:full":"Avda Cardenal Cisneros, S/n Zamora Zamora 49023",
    "addr:postcode":"49023",
    "addr:street":"Avda Cardenal Cisneros S / N",
    "iso:country":"ES",
    "sg:address":"Avda Cardenal Cisneros, S/n",
    "sg:city":"Zamora",
    "sg:orig_category":"Asociaciones Y Clubs Deportivos",
    "sg:phone":"+34 980 51 83 89",
    "sg:postcode":"49023",
    "sg:province":"Zamora",
    "wof:name":"Hernandez Asensio S.l.",
    "wof:placetype":"venue"
},
  "geometry": {"coordinates":[-5.7447137833,41.5148506165],"type":"Point"}
}