{
  "type": "Feature",
  "properties": {
    "addr:full":"Calle de Maestro Serrano, 9 Antella Valencia 46266",
    "addr:housenumber":"9",
    "addr:postcode":"46266",
    "addr:street":"Calle De Maestro Serrano",
    "iso:country":"ES",
    "sg:address":"Calle de Maestro Serrano, 9",
    "sg:city":"Antella",
    "sg:orig_category":"Comercio, Reparaci\u00d3n De Motocicletas, Bicicletas Y Piezas Sueltas",
    "sg:phone":"+34 962 97 40 44",
    "sg:postcode":"46266",
    "sg:province":"Valencia",
    "wof:name":"Cuenca Esparza Francisco",
    "wof:placetype":"venue"
},
  "geometry": {"coordinates":[-0.5892649889,39.08070755],"type":"Point"}
}