{
  "type": "Feature",
  "properties": {
    "addr:full":"Calle de Hidalgo Cabanillas, 40 Navalvillar Pela Badajoz 06760",
    "addr:housenumber":"40",
    "addr:postcode":"06760",
    "addr:street":"Calle De Hidalgo Cabanillas",
    "iso:country":"ES",
    "sg:address":"Calle de Hidalgo Cabanillas, 40",
    "sg:city":"Navalvillar Pela",
    "sg:orig_category":"Negocio De Materiales De Construcci\u00d3n",
    "sg:phone":"+34 924 86 07 26",
    "sg:postcode":"06760",
    "sg:province":"Badajoz",
    "wof:name":"Rios Sierra Antonio",
    "wof:placetype":"venue"
},
  "geometry": {"coordinates":[-5.4675078392,39.0939788818],"type":"Point"}
}