{
  "type": "Feature",
  "properties": {
    "addr:full":"Calle de Portada, 2 Palma Rio C\u00f3rdoba 14700",
    "addr:housenumber":"2",
    "addr:postcode":"14700",
    "addr:street":"Calle De Portada;Rio Co\u0301Rdoba",
    "iso:country":"ES",
    "sg:address":"Calle de Portada, 2",
    "sg:city":"Palma Rio",
    "sg:orig_category":"Confecci\u00d3n (fabricaci\u00d3n, Al Por Mayor)",
    "sg:phone":"+34 957 64 34 77",
    "sg:postcode":"14700",
    "sg:province":"C\u00f3rdoba",
    "wof:name":"Rivera Rodriguez Candida",
    "wof:placetype":"venue"
},
  "geometry": {"coordinates":[-5.2821240425,37.6971092224],"type":"Point"}
}