{
  "type": "Feature",
  "properties": {
    "addr:full":"Avda Arganza, 61 Cacabelos Le\u00f3n 24540",
    "addr:housenumber":"61",
    "addr:postcode":"24540",
    "addr:street":"Avda Arganza",
    "iso:country":"ES",
    "sg:address":"Avda Arganza, 61",
    "sg:city":"Cacabelos",
    "sg:orig_category":"Negocio De Materiales De Construcci\u00d3n",
    "sg:phone":"+34 987 54 71 95",
    "sg:postcode":"24540",
    "sg:province":"Le\u00f3n",
    "wof:name":"Luis Fernandez Gallego S.a.",
    "wof:placetype":"venue"
},
  "geometry": {"coordinates":[-6.7274041176,42.6011161804],"type":"Point"}
}