{
  "type": "Feature",
  "properties": {
    "addr:full":"Algas, 19 Batea Tarragona 43786",
    "addr:housenumber":"19",
    "addr:postcode":"43786",
    "addr:street":"Algas",
    "iso:country":"ES",
    "sg:address":"Algas, 19",
    "sg:city":"Batea",
    "sg:orig_category":"Cerrajer\u00cda, Ferrallista",
    "sg:phone":"+34 977 43 00 66",
    "sg:postcode":"43786",
    "sg:province":"Tarragona",
    "wof:name":"Aguilo Vaquer Manuel",
    "wof:placetype":"venue"
},
  "geometry": {"coordinates":[0.2807868123,41.099521637],"type":"Point"}
}