{
  "type": "Feature",
  "properties": {
    "iso:country":"ES",
    "sg:address":"Ctra. De Madrid Barcelona, Km. 0263,0",
    "sg:city":"Almunia D. Godina",
    "sg:orig_category":"Distribuci\u00d3n De Petr\u00d3leo Y Derivados",
    "sg:phone":"+34 976 60 10 87",
    "sg:postcode":"50100",
    "sg:province":"Zaragoza",
    "sg:website":"www.cepsa.es",
    "wof:name":"Cedipsa Compa\u00d1ia Espa\u00d1ola Distribuidora De Petroleos S.a.",
    "wof:placetype":"venue"
},
  "geometry": {"coordinates":[-1.3779189587,41.4772033691],"type":"Point"}
}