{
  "type": "Feature",
  "properties": {
    "addr:full":"Riodolas, S/n Riodolas Ourense 32336",
    "addr:postcode":"32336",
    "addr:street":"Riodolas S / N",
    "iso:country":"ES",
    "sg:address":"Riodolas, S/n",
    "sg:city":"Riodolas",
    "sg:orig_category":"Pizzer\u00cdas",
    "sg:phone":"+34 988 29 43 93",
    "sg:postcode":"32336",
    "sg:province":"Ourense",
    "wof:name":"Industrias De Rocas Ornamentales S. A.",
    "wof:placetype":"venue"
},
  "geometry": {"coordinates":[-6.8777217865,42.376335144],"type":"Point"}
}