{
  "type": "Feature",
  "properties": {
    "addr:full":"Calle de Mastil, S/n Playa Honda Las Palmas 35509",
    "addr:housenumber":"s / n",
    "addr:postcode":"35509",
    "addr:street":"Calle De Mastil",
    "iso:country":"ES",
    "sg:address":"Calle de Mastil, S/n",
    "sg:city":"Playa Honda",
    "sg:orig_category":"Ense\u00d1anza: Comercio, Gesti\u00d3n, Inform\u00c1tica",
    "sg:phone":"+34 928 82 11 53",
    "sg:postcode":"35509",
    "sg:province":"Las Palmas",
    "wof:name":"Lizarraga Feringan Gabriela",
    "wof:placetype":"venue"
},
  "geometry": {"coordinates":[-13.5971240997,28.9523906708],"type":"Point"}
}