{
  "type": "Feature",
  "properties": {
    "iso:country":"ES",
    "sg:address":"Calle de Moncalvos, S/n",
    "sg:city":"Sari\u00f1ena",
    "sg:orig_category":"Mec\u00c1nico Del Autom\u00d3vil",
    "sg:phone":"+34 974 57 04 87",
    "sg:postcode":"22200",
    "sg:province":"Huesca",
    "wof:name":"Huerva Grustan Juan",
    "wof:placetype":"venue"
},
  "geometry": {"coordinates":[-0.1628039926,41.7908210754],"type":"Point"}
}