{
  "type": "Feature",
  "properties": {
    "addr:full":"Carr La Palma, 9 Lleida Lleida 25002",
    "addr:housenumber":"9",
    "addr:postcode":"25002",
    "addr:street":"Carr La Palma",
    "iso:country":"ES",
    "sg:address":"Carr La Palma, 9",
    "sg:city":"Lleida",
    "sg:orig_category":"Agencias Y Asesores De Publicidad",
    "sg:phone":"+34 973 28 24 23",
    "sg:postcode":"25002",
    "sg:province":"Lleida",
    "wof:name":"Llibreria Ramon Llull S.l.l.",
    "wof:placetype":"venue"
},
  "geometry": {"coordinates":[0.627129972,41.6145210266],"type":"Point"}
}