{
  "type": "Feature",
  "properties": {
    "addr:full":"Pla\u00c7 Petita, 8 Cassa Selva Girona 17244",
    "addr:housenumber":"8",
    "addr:postcode":"17244",
    "addr:street":"Petita",
    "iso:country":"ES",
    "sg:address":"Pla\u00c7 Petita, 8",
    "sg:city":"Cassa Selva",
    "sg:orig_category":"Carnicer\u00cdas, Carnicer\u00cdas",
    "sg:phone":"+34 972 46 01 83",
    "sg:postcode":"17244",
    "sg:province":"Girona",
    "wof:name":"Pibernat Deulofeu Lluis",
    "wof:placetype":"venue"
},
  "geometry": {"coordinates":[2.8780760765,41.8896598816],"type":"Point"}
}