{
  "type": "Feature",
  "properties": {
    "addr:full":"Rua Praia (da), 27 Cambados Pontevedra 36630",
    "addr:housenumber":"27",
    "addr:postcode":"36630",
    "addr:street":"Rua Praia Da",
    "iso:country":"ES",
    "sg:address":"Rua Praia (da), 27",
    "sg:city":"Cambados",
    "sg:orig_category":"Empresas De Carpinter\u00cda De Madera",
    "sg:phone":"+34 986 54 30 95",
    "sg:postcode":"36630",
    "sg:province":"Pontevedra",
    "wof:name":"Nu\u00f1ez Bugallo Luis",
    "wof:placetype":"venue"
},
  "geometry": {"coordinates":[-8.8169527054,42.5115509033],"type":"Point"}
}