{
  "type": "Feature",
  "properties": {
    "addr:full":"Rua Navegantes, 12 Ferrol La Coru\u00f1a 15401",
    "addr:housenumber":"12",
    "addr:postcode":"15401",
    "addr:street":"Rua Navegantes;La Corun\u0303A",
    "iso:country":"ES",
    "sg:address":"Rua Navegantes, 12",
    "sg:city":"Ferrol",
    "sg:orig_category":"Peluquer\u00cdas, Peluquer\u00cda Mixta",
    "sg:phone":"+34 981 30 03 15",
    "sg:postcode":"15401",
    "sg:province":"La Coru\u00f1a",
    "wof:name":"Miraz Sanmartin Anunciacion",
    "wof:placetype":"venue"
},
  "geometry": {"coordinates":[-8.239192009,43.4876937866],"type":"Point"}
}