{
  "type": "Feature",
  "properties": {
    "iso:country":"ES",
    "sg:address":"Calle de Chiva, 10",
    "sg:city":"Valencia",
    "sg:orig_category":"Asociaciones Humanitarias, De Cooperaci\u00d3n, De Acci\u00d3n Social",
    "sg:phone":"+34 963 82 46 14",
    "sg:postcode":"46018",
    "sg:province":"Valencia",
    "wof:name":"Asociacion Parkinson Valencia",
    "wof:placetype":"venue"
},
  "geometry": {"coordinates":[-0.3900307119,39.464717865],"type":"Point"}
}