{
  "type": "Feature",
  "properties": {
    "iso:country":"ES",
    "sg:address":"Pase Cortes De Aragon, 11",
    "sg:city":"Calatayud",
    "sg:orig_category":"Cervecer\u00cdas",
    "sg:phone":"+34 976 88 25 34",
    "sg:postcode":"50300",
    "sg:province":"Zaragoza",
    "wof:name":"San Julian Romanos Fernando",
    "wof:placetype":"venue"
},
  "geometry": {"coordinates":[-1.6420789957,41.3516197205],"type":"Point"}
}