{
  "type": "Feature",
  "properties": {
    "iso:country":"ES",
    "sg:address":"Calle de Raya Real, 5",
    "sg:city":"Bormujos",
    "sg:orig_category":"Fotocopias, Reprograf\u00cda",
    "sg:phone":"+34 955 72 65 02",
    "sg:postcode":"41930",
    "sg:province":"Sevilla",
    "wof:name":"Hermanos Ruiz-ruiz S.c.",
    "wof:placetype":"venue"
},
  "geometry": {"coordinates":[-6.0701298714,37.3743782043],"type":"Point"}
}