{
  "type": "Feature",
  "properties": {
    "addr:full":"Calle de Cruz, 27 Albacete Albacete 02001",
    "addr:housenumber":"27",
    "addr:postcode":"02001",
    "addr:street":"Calle De Cruz",
    "iso:country":"ES",
    "sg:address":"Calle de Cruz, 27",
    "sg:city":"Albacete",
    "sg:orig_category":"Mec\u00c1nico Del Autom\u00d3vil",
    "sg:phone":"+34 967 21 37 13",
    "sg:postcode":"02001",
    "sg:province":"Albacete",
    "wof:name":"Talleres Rafael Montero S.l.",
    "wof:placetype":"venue"
},
  "geometry": {"coordinates":[-1.8499430418,38.9932823181],"type":"Point"}
}