{
  "type": "Feature",
  "properties": {
    "addr:full":"Calle de Teodoro Golfin, 33 Palmas De Gran Canaria Las Palmas 35012",
    "addr:housenumber":"33",
    "addr:postcode":"35012",
    "addr:street":"Calle De Teodoro Golfin",
    "iso:country":"ES",
    "sg:address":"Calle de Teodoro Golfin, 33",
    "sg:city":"Palmas De Gran Canaria",
    "sg:orig_category":"Molduras, Junquillos, Listones Y Molduras Perforadas",
    "sg:phone":"+34 928 25 58 97",
    "sg:postcode":"35012",
    "sg:province":"Las Palmas",
    "wof:name":"Espino Sanchez Manuel",
    "wof:placetype":"venue"
},
  "geometry": {"coordinates":[-15.4305706024,28.1146411896],"type":"Point"}
}