{
  "type": "Feature",
  "properties": {
    "iso:country":"ES",
    "sg:address":"Calle de Hernando De Perona, 4",
    "sg:city":"Roda",
    "sg:orig_category":"Bares, Piano",
    "sg:phone":"+34 967 44 14 79",
    "sg:postcode":"02630",
    "sg:province":"Albacete",
    "wof:name":"Peces De Ciudad C.b.",
    "wof:placetype":"venue"
},
  "geometry": {"coordinates":[-2.1574180126,39.204536438],"type":"Point"}
}