{
  "type": "Feature",
  "properties": {
    "addr:full":"Pase Comuneros De Castilla, S/n Burgos Burgos 09006",
    "addr:housenumber":"s / n",
    "addr:postcode":"09006",
    "iso:country":"ES",
    "sg:address":"Pase Comuneros De Castilla, S/n",
    "sg:city":"Burgos",
    "sg:orig_category":"Asociaciones Y Clubs Deportivos",
    "sg:phone":"+34 947 22 43 00",
    "sg:postcode":"09006",
    "sg:province":"Burgos",
    "wof:name":"Union Deportiva Grupo Rio Vena",
    "wof:placetype":"venue"
},
  "geometry": {"coordinates":[-3.6850469112,42.3502349854],"type":"Point"}
}