{
  "type": "Feature",
  "properties": {
    "iso:country":"ES",
    "sg:address":"Pl Om (de L'), 3",
    "sg:city":"Riudoms",
    "sg:orig_category":"Reposter\u00cdas",
    "sg:phone":"+34 977 85 00 08",
    "sg:postcode":"43330",
    "sg:province":"Tarragona",
    "wof:name":"Rovira Guinjoan Josep Maria",
    "wof:placetype":"venue"
},
  "geometry": {"coordinates":[1.0511800051,41.1377182007],"type":"Point"}
}