{
  "type": "Feature",
  "properties": {
    "addr:full":"Praz Europa (de), S/n Santiago De Compostela La Coru\u00f1a 15703",
    "addr:postcode":"15703",
    "addr:street":"Praz Europa De S / N;Corun\u0303A",
    "iso:country":"ES",
    "sg:address":"Praz Europa (de), S/n",
    "sg:city":"Santiago De Compostela",
    "sg:orig_category":"Fabricaci\u00d3n De Sobres, Bolsas Y Fundas",
    "sg:phone":"+34 981 56 27 51",
    "sg:postcode":"15703",
    "sg:province":"La Coru\u00f1a",
    "wof:name":"Quintans Val Francisco",
    "wof:placetype":"venue"
},
  "geometry": {"coordinates":[-8.4892587662,42.892364502],"type":"Point"}
}