{
  "type": "Feature",
  "properties": {
    "iso:country":"ES",
    "sg:address":"Calle de Pino, 3",
    "sg:city":"Costa Oeste",
    "sg:orig_category":"M\u00c9dicos: Cardiolog\u00cda Y Afecciones Cardiovasculares",
    "sg:phone":"+34 956 54 30 84",
    "sg:postcode":"11500",
    "sg:province":"C\u00e1diz",
    "wof:name":"Cruz Fernandez Jose Maria",
    "wof:placetype":"venue"
},
  "geometry": {"coordinates":[-6.2197542191,36.6056632996],"type":"Point"}
}