{
  "type": "Feature",
  "properties": {
    "addr:full":"Urb. Roca Brava, 55 Palamos Girona 17230",
    "addr:housenumber":"55",
    "addr:postcode":"17230",
    "addr:street":"Palamos Girona",
    "iso:country":"ES",
    "sg:address":"Urb. Roca Brava, 55",
    "sg:city":"Palamos",
    "sg:orig_category":"Fabricaci\u00d3n De Pastas Alimentarias",
    "sg:phone":"+34 972 31 82 29",
    "sg:postcode":"17230",
    "sg:province":"Girona",
    "wof:name":"Alimentos Naturales S.a.",
    "wof:placetype":"venue"
},
  "geometry": {"coordinates":[3.1328010559,41.8621673584],"type":"Point"}
}