{
  "type": "Feature",
  "properties": {
    "iso:country":"ES",
    "sg:address":"Rua Garcia Ferreiro, 3",
    "sg:city":"Ourense",
    "sg:orig_category":"Maquinaria Para Industrias Diversas",
    "sg:phone":"+34 988 23 91 97",
    "sg:postcode":"32005",
    "sg:province":"Ourense",
    "wof:name":"Cui\u00f1as Iglesias Anselmo",
    "wof:placetype":"venue"
},
  "geometry": {"coordinates":[-7.8616518974,42.3227844238],"type":"Point"}
}