{
  "type": "Feature",
  "properties": {
    "addr:full":"Calle de Palacio Valdes, 12 Oviedo Asturias 33002",
    "addr:housenumber":"12",
    "addr:postcode":"33002",
    "addr:street":"Calle De Palacio Valdes",
    "iso:country":"ES",
    "sg:address":"Calle de Palacio Valdes, 12",
    "sg:city":"Oviedo",
    "sg:orig_category":"Abogados",
    "sg:phone":"+34 985 21 74 88",
    "sg:postcode":"33002",
    "sg:province":"Asturias",
    "wof:name":"Albo Abogados C.b.",
    "wof:placetype":"venue"
},
  "geometry": {"coordinates":[-5.8490190506,43.3637390137],"type":"Point"}
}