{
  "type": "Feature",
  "properties": {
    "iso:country":"ES",
    "sg:address":"Calle de Tejeria, 10",
    "sg:city":"Donostia-san Sebastian",
    "sg:orig_category":"Ense\u00d1anza Agr\u00cdcola",
    "sg:phone":"+34 943 27 98 14",
    "sg:postcode":"20012",
    "sg:province":"Guip\u00f9zcoa",
    "wof:name":"Fundacion Social Y Cultural Kutxa",
    "wof:placetype":"venue"
},
  "geometry": {"coordinates":[-1.9722980261,43.3169441223],"type":"Point"}
}