{
  "type": "Feature",
  "properties": {
    "iso:country":"ES",
    "sg:address":"C/ Espanya, 31",
    "sg:city":"Puigcerda",
    "sg:orig_category":"Carnicer\u00cdas, Carnicer\u00cdas",
    "sg:phone":"+34 972 88 02 06",
    "sg:postcode":"17520",
    "sg:province":"Girona",
    "wof:name":"Esteve Bennasar Domingo",
    "wof:placetype":"venue"
},
  "geometry": {"coordinates":[1.9275499582,42.4323654175],"type":"Point"}
}