{
  "type": "Feature",
  "properties": {
    "iso:country":"ES",
    "sg:address":"Avda Constitucion, 6",
    "sg:city":"Valencia",
    "sg:orig_category":"Agencias Y Agentes Comerciales, Representantes",
    "sg:phone":"+34 963 47 92 80",
    "sg:postcode":"46009",
    "sg:province":"Valencia",
    "wof:name":"Gimenez Marti Jose",
    "wof:placetype":"venue"
},
  "geometry": {"coordinates":[-0.3787150085,39.4837303162],"type":"Point"}
}