{
  "type": "Feature",
  "properties": {
    "addr:full":"Calle de Greco, 2 Talavera Reina Toledo 45600",
    "addr:housenumber":"2",
    "addr:postcode":"45600",
    "addr:street":"Calle De Greco",
    "iso:country":"ES",
    "sg:address":"Calle de Greco, 2",
    "sg:city":"Talavera Reina",
    "sg:orig_category":"Aguas (distribuci\u00d3n, Servicios)",
    "sg:phone":"+34 925 80 24 39",
    "sg:postcode":"45600",
    "sg:province":"Toledo",
    "wof:name":"Sanchez Garcia Isabel",
    "wof:placetype":"venue"
},
  "geometry": {"coordinates":[-4.8277249336,39.9624252319],"type":"Point"}
}