{
  "type": "Feature",
  "properties": {
    "addr:full":"Carr Sant Roc, 10 Torregrossa Lleida 25141",
    "addr:housenumber":"10",
    "addr:postcode":"25141",
    "addr:street":"Carr Sant Roc",
    "iso:country":"ES",
    "sg:address":"Carr Sant Roc, 10",
    "sg:city":"Torregrossa",
    "sg:orig_category":"Mataderos Y Talleres De Despiezado",
    "sg:phone":"+34 973 17 00 09",
    "sg:postcode":"25141",
    "sg:province":"Lleida",
    "wof:name":"Carnicas Capell S.a.",
    "wof:placetype":"venue"
},
  "geometry": {"coordinates":[0.8324049711,41.5803718567],"type":"Point"}
}