{
  "type": "Feature",
  "properties": {
    "addr:full":"Calle de Molino (el), 59 Caudete Albacete 02660",
    "addr:postcode":"02660",
    "addr:street":"Calle De Molino El",
    "iso:country":"ES",
    "sg:address":"Calle de Molino (el), 59",
    "sg:city":"Caudete",
    "sg:orig_category":"Electricidad: Instaladores",
    "sg:phone":"+34 965 82 57 60",
    "sg:postcode":"02660",
    "sg:province":"Albacete",
    "wof:name":"Albeluz S.l.",
    "wof:placetype":"venue"
},
  "geometry": {"coordinates":[-0.9862089753,38.7064704895],"type":"Point"}
}