{
  "type": "Feature",
  "properties": {
    "addr:full":"Av Manel Ribe, 18 Montblanc Tarragona 43400",
    "addr:housenumber":"18",
    "addr:postcode":"43400",
    "addr:street":"Av Manel Ribe",
    "iso:country":"ES",
    "sg:address":"Av Manel Ribe, 18",
    "sg:city":"Montblanc",
    "sg:orig_category":"Peluqueros: De Se\u00d1oras",
    "sg:phone":"+34 977 86 08 36",
    "sg:postcode":"43400",
    "sg:province":"Tarragona",
    "wof:name":"Domingo Torres Juan",
    "wof:placetype":"venue"
},
  "geometry": {"coordinates":[1.1614060402,41.3734207153],"type":"Point"}
}