{
  "type": "Feature",
  "properties": {
    "iso:country":"ES",
    "sg:address":"Avda Coru\u00d1a (da), 464",
    "sg:city":"Lugo",
    "sg:orig_category":"Contenedores (mercanc\u00cdas)",
    "sg:phone":"+34 982 21 25 13",
    "sg:postcode":"27003",
    "sg:province":"Lugo",
    "wof:name":"Nu\u00f1ez Cabado Edelmiro",
    "wof:placetype":"venue"
},
  "geometry": {"coordinates":[-7.5710291862,43.0305213928],"type":"Point"}
}