{
  "type": "Feature",
  "properties": {
    "addr:full":"Calle de Pedro Bocanegra, 5 Vera Almer\u00eda 04620",
    "addr:housenumber":"5;almeri\u0301a",
    "addr:postcode":"04620",
    "addr:street":"Calle De Pedro Bocanegra",
    "iso:country":"ES",
    "sg:address":"Calle de Pedro Bocanegra, 5",
    "sg:city":"Vera",
    "sg:orig_category":"Servicios Gsm",
    "sg:phone":"+34 950 39 12 59",
    "sg:postcode":"04620",
    "sg:province":"Almer\u00eda",
    "wof:name":"Mobyme S.l.",
    "wof:placetype":"venue"
},
  "geometry": {"coordinates":[-1.8575940132,37.240776062],"type":"Point"}
}