{
  "type": "Feature",
  "properties": {
    "addr:full":"Calle de Huescar, 12 Castillejar Granada 18818",
    "addr:housenumber":"12",
    "addr:postcode":"18818",
    "addr:street":"Calle De Huescar",
    "iso:country":"ES",
    "sg:address":"Calle de Huescar, 12",
    "sg:city":"Castillejar",
    "sg:orig_category":"Fabrica De Charcuter\u00cda",
    "sg:phone":"+34 958 73 70 88",
    "sg:postcode":"18818",
    "sg:province":"Granada",
    "wof:name":"Hermanos Canillo S.c.p.",
    "wof:placetype":"venue"
},
  "geometry": {"coordinates":[-2.6422169209,37.715171814],"type":"Point"}
}