{
  "type": "Feature",
  "properties": {
    "iso:country":"ES",
    "sg:address":"Carr Industria, 16",
    "sg:city":"Igualada",
    "sg:orig_category":"Cueros Y Pieles (al Por Mayor)",
    "sg:phone":"+34 938 03 14 65",
    "sg:postcode":"08700",
    "sg:province":"Barcelona",
    "wof:name":"Curtidos Lancina S. A.",
    "wof:placetype":"venue"
},
  "geometry": {"coordinates":[1.6129959822,41.5811958313],"type":"Point"}
}