{
  "type": "Feature",
  "properties": {
    "addr:full":"Calle de Uruguay, 14 Caceres C\u00e1ceres 10005",
    "addr:housenumber":"14",
    "addr:postcode":"10005",
    "addr:street":"Calle De Uruguay;Ca\u0301Ceres",
    "iso:country":"ES",
    "sg:address":"Calle de Uruguay, 14",
    "sg:city":"Caceres",
    "sg:classifiers":[
        {
            "category":"Banks & Credit Unions",
            "subcategory":"Bureau De Change",
            "type":"Services"
        }
    ],
    "sg:phone":"+34 927 21 60 16",
    "sg:postcode":"10005",
    "sg:province":"C\u00e1ceres",
    "sg:tags":[
        "organismos",
        "control"
    ],
    "wof:name":"Calidad Alimentaria Del Oeste S.l.",
    "wof:placetype":"venue"
},
  "geometry": {"coordinates":[-6.3739519119,39.4598045349],"type":"Point"}
}