{
  "type": "Feature",
  "properties": {
    "addr:full":"Plaz Aita San Migel Plaza, 10 Aita San Migel Vizcaya 48215",
    "addr:housenumber":"10",
    "addr:postcode":"48215",
    "addr:street":"Plaz Aita San;Aita San",
    "iso:country":"ES",
    "sg:address":"Plaz Aita San Migel Plaza, 10",
    "sg:city":"Aita San Migel",
    "sg:orig_category":"Iglesia Cat\u00d3lica",
    "sg:phone":"+34 946 81 87 63",
    "sg:postcode":"48215",
    "sg:province":"Vizcaya",
    "wof:name":"Obispado De Bilbao",
    "wof:placetype":"venue"
},
  "geometry": {"coordinates":[-2.631608963,43.1760597229],"type":"Point"}
}