{
  "type": "Feature",
  "properties": {
    "addr:full":"Bahia Dorada Tres, S/n Estepona M\u00e1laga 29680",
    "addr:housenumber":"/ n",
    "addr:postcode":"29680",
    "addr:street":"Tres S",
    "iso:country":"ES",
    "sg:address":"Bahia Dorada Tres, S/n",
    "sg:city":"Estepona",
    "sg:orig_category":"Alquiler De Veh\u00cdculos: Turismos Y Utilitarios",
    "sg:phone":"+34 952 79 25 80",
    "sg:postcode":"29680",
    "sg:province":"M\u00e1laga",
    "wof:name":"Solcars Rent A Car S.l.",
    "wof:placetype":"venue"
},
  "geometry": {"coordinates":[-5.194794178,36.4006004333],"type":"Point"}
}