{
  "type": "Feature",
  "properties": {
    "iso:country":"ES",
    "sg:address":"Calle de Julian Fernandez Ollero, 4",
    "sg:city":"Haro",
    "sg:orig_category":"Freidur\u00cdas: Equipos Y Suministros",
    "sg:phone":"+34 941 31 28 16",
    "sg:postcode":"26200",
    "sg:province":"La Rioja",
    "wof:name":"Santamaria Santos Luis",
    "wof:placetype":"venue"
},
  "geometry": {"coordinates":[-2.8502631187,42.5774803162],"type":"Point"}
}