{
  "type": "Feature",
  "properties": {
    "addr:full":"Calle de Virgen De Lujan, 44 Sevilla Sevilla 41011",
    "addr:housenumber":"44",
    "addr:postcode":"41011",
    "addr:street":"Calle De Virgen De Lujan",
    "iso:country":"ES",
    "sg:address":"Calle de Virgen De Lujan, 44",
    "sg:city":"Sevilla",
    "sg:orig_category":"Institutos De Belleza",
    "sg:phone":"+34 954 27 94 59",
    "sg:postcode":"41011",
    "sg:province":"Sevilla",
    "wof:name":"Sevillasol Bronceados S.l.",
    "wof:placetype":"venue"
},
  "geometry": {"coordinates":[-6.0016379356,37.3749008179],"type":"Point"}
}