{
  "type": "Feature",
  "properties": {
    "iso:country":"ES",
    "sg:address":"Plaz Mostenses, 7",
    "sg:city":"Madrid",
    "sg:orig_category":"M\u00c9dicos: Naturistas",
    "sg:phone":"+34 915 59 42 59",
    "sg:postcode":"28015",
    "sg:province":"Madrid",
    "wof:name":"Fernandez Hervella Juan",
    "wof:placetype":"venue"
},
  "geometry": {"coordinates":[-3.7086451054,40.4235534668],"type":"Point"}
}