{
  "type": "Feature",
  "properties": {
    "addr:full":"Calle de Arroyo, 6 Marmolejo Ja\u00e9n 23770",
    "addr:housenumber":"6",
    "addr:postcode":"23770",
    "addr:street":"Calle De Arroyo;Jae\u0301N",
    "iso:country":"ES",
    "sg:address":"Calle de Arroyo, 6",
    "sg:city":"Marmolejo",
    "sg:orig_category":"Asociaciones Y Clubs Deportivos",
    "sg:phone":"+34 953 54 09 43",
    "sg:postcode":"23770",
    "sg:province":"Ja\u00e9n",
    "wof:name":"Javier Y Aurora C.b.",
    "wof:placetype":"venue"
},
  "geometry": {"coordinates":[-4.171020031,38.0458106995],"type":"Point"}
}