{
  "type": "Feature",
  "properties": {
    "addr:full":"Carrer de Angli, 46 Barcelona Barcelona 08017",
    "addr:housenumber":"46",
    "addr:postcode":"08017",
    "addr:street":"Carrer De Angli",
    "iso:country":"ES",
    "sg:address":"Carrer de Angli, 46",
    "sg:city":"Barcelona",
    "sg:orig_category":"Empresarios",
    "sg:phone":"+34 932 04 09 18",
    "sg:postcode":"08017",
    "sg:province":"Barcelona",
    "wof:name":"Etg. Cimentaciones S.l.",
    "wof:placetype":"venue"
},
  "geometry": {"coordinates":[2.1236009598,41.4027175903],"type":"Point"}
}