{
  "type": "Feature",
  "properties": {
    "addr:full":"Calle de Alfonso Iii El Magno, 2 Zamora Zamora 49003",
    "addr:housenumber":"2",
    "addr:postcode":"49003",
    "addr:street":"Calle De Alfonso Iii El Magno",
    "iso:country":"ES",
    "sg:address":"Calle de Alfonso Iii El Magno, 2",
    "sg:city":"Zamora",
    "sg:orig_category":"Asesor\u00cda Fiscal Y Jur\u00cddica",
    "sg:phone":"+34 980 51 98 73",
    "sg:postcode":"49003",
    "sg:province":"Zamora",
    "wof:name":"Asesoria Zamora S.l",
    "wof:placetype":"venue"
},
  "geometry": {"coordinates":[-5.7438526154,41.5041160583],"type":"Point"}
}