{
  "type": "Feature",
  "properties": {
    "addr:full":"Urb. Pe\u00f1asolana, 1 Carrascal Barregas Salamanca 37129",
    "addr:housenumber":"1",
    "addr:postcode":"37129",
    "addr:street":"Pen\u0303Asolana",
    "iso:country":"ES",
    "sg:address":"Urb. Pe\u00f1asolana, 1",
    "sg:city":"Carrascal Barregas",
    "sg:orig_category":"Trabajos De Perforaciones, Sondeos, Construcci\u00d3n De Pozos",
    "sg:phone":"+34 923 33 03 48",
    "sg:postcode":"37129",
    "sg:province":"Salamanca",
    "wof:name":"Jose Manuel Balboa S.l.",
    "wof:placetype":"venue"
},
  "geometry": {"coordinates":[-5.761329174,40.9782981873],"type":"Point"}
}