{
  "type": "Feature",
  "properties": {
    "addr:full":"Plza Rio Mayor, 4 Mendavia Navarra 31587",
    "addr:housenumber":"4",
    "addr:postcode":"31587",
    "addr:street":"Mayor",
    "iso:country":"ES",
    "sg:address":"Plza Rio Mayor, 4",
    "sg:city":"Mendavia",
    "sg:orig_category":"Administradores De Bienes Y Delegados De Comunidades De Propietarios",
    "sg:phone":"+34 948 69 51 27",
    "sg:postcode":"31587",
    "sg:province":"Navarra",
    "wof:name":"Copropietarios Augusto Echevarria, Rio M",
    "wof:placetype":"venue"
},
  "geometry": {"coordinates":[-2.1981918812,42.4444274902],"type":"Point"}
}