{
  "type": "Feature",
  "properties": {
    "addr:full":"Avda Colonia (de La), 9 Linea De La Concepcion C\u00e1diz 11300",
    "addr:housenumber":"9",
    "addr:postcode":"11300",
    "addr:street":"Avda Colonia De La;Ca\u0301Diz",
    "iso:country":"ES",
    "sg:address":"Avda Colonia (de La), 9",
    "sg:city":"Linea De La Concepcion",
    "sg:orig_category":"Centros Comerciales Y Grandes Tiendas",
    "sg:phone":"+34 956 17 48 06",
    "sg:postcode":"11300",
    "sg:province":"C\u00e1diz",
    "wof:name":"Comunidad De Propietarios Centro Comercial Gran Sur",
    "wof:placetype":"venue"
},
  "geometry": {"coordinates":[-5.3622441292,36.1733894348],"type":"Point"}
}