{
  "type": "Feature",
  "properties": {
    "addr:full":"Antziola Auzoa, 46 Hernani Guip\u00f9zcoa 20120",
    "addr:housenumber":"46",
    "addr:postcode":"20120",
    "addr:street":"Antziola Auzoa;Guipu\u0300Zcoa",
    "iso:country":"ES",
    "sg:address":"Antziola Auzoa, 46",
    "sg:city":"Hernani",
    "sg:orig_category":"Plomeros",
    "sg:phone":"+34 943 33 05 19",
    "sg:postcode":"20120",
    "sg:province":"Guip\u00f9zcoa",
    "wof:name":"Ocariz Ardanui Aihert",
    "wof:placetype":"venue"
},
  "geometry": {"coordinates":[-1.9776359797,43.2734985352],"type":"Point"}
}