{
  "type": "Feature",
  "properties": {
    "addr:full":"Generalisimo Franco, 38 Padron La Coru\u00f1a 15900",
    "addr:housenumber":"38",
    "addr:postcode":"15900",
    "addr:street":"Padron La Corun\u0303A",
    "iso:country":"ES",
    "sg:address":"Generalisimo Franco, 38",
    "sg:city":"Padron",
    "sg:orig_category":"Caf\u00c9s, Bares, Cervecer\u00cdas",
    "sg:phone":"+34 981 81 05 59",
    "sg:postcode":"15900",
    "sg:province":"La Coru\u00f1a",
    "wof:name":"Martinez Lopez Severino",
    "wof:placetype":"venue"
},
  "geometry": {"coordinates":[-8.6603002548,42.7378578186],"type":"Point"}
}