{
  "type": "Feature",
  "properties": {
    "addr:full":"Calle de Colombia, 2 Arrecife Las Palmas 35500",
    "addr:housenumber":"2",
    "addr:postcode":"35500",
    "addr:street":"Calle De Colombia",
    "iso:country":"ES",
    "sg:address":"Calle de Colombia, 2",
    "sg:city":"Arrecife",
    "sg:orig_category":"Venta, Reparaci\u00d3n De M\u00c1quinas De Coser, Planchadoras Y M\u00c1quinas De Tricotar",
    "sg:phone":"+34 928 80 51 40",
    "sg:postcode":"35500",
    "sg:province":"Las Palmas",
    "wof:name":"Rodriguez Socorro Eliseo Antonio",
    "wof:placetype":"venue"
},
  "geometry": {"coordinates":[-13.5574998856,28.9618415833],"type":"Point"}
}