{
  "type": "Feature",
  "properties": {
    "addr:full":"Carr Academia, 1 Lleida Lleida 25002",
    "addr:housenumber":"1",
    "addr:postcode":"25002",
    "addr:street":"Carr Academia",
    "iso:country":"ES",
    "sg:address":"Carr Academia, 1",
    "sg:city":"Lleida",
    "sg:orig_category":"M\u00c9dicos: Estomatolog\u00cda",
    "sg:phone":"+34 973 26 44 28",
    "sg:postcode":"25002",
    "sg:province":"Lleida",
    "wof:name":"Anadon Sole Enrique",
    "wof:placetype":"venue"
},
  "geometry": {"coordinates":[0.6201431155,41.6116104126],"type":"Point"}
}