{
  "type": "Feature",
  "properties": {
    "iso:country":"ES",
    "sg:address":"Calle de Bono Guarner, 17",
    "sg:city":"Alacant",
    "sg:orig_category":"Reposter\u00cdas",
    "sg:phone":"+34 965 22 80 83",
    "sg:postcode":"03005",
    "sg:province":"Alicante",
    "wof:name":"Rojas Aliaga Jose Vicente",
    "wof:placetype":"venue"
},
  "geometry": {"coordinates":[-0.4982691109,38.3464736938],"type":"Point"}
}