{
  "type": "Feature",
  "properties": {
    "addr:full":"Urb. Gale, 157 Palos Frontera Huelva 21810",
    "addr:housenumber":"157",
    "addr:postcode":"21810",
    "addr:street":"Urb.;Palos Frontera",
    "iso:country":"ES",
    "sg:address":"Urb. Gale, 157",
    "sg:city":"Palos Frontera",
    "sg:orig_category":"Arreglo, Reparaci\u00d3n, Piezas Sueltas De Televisi\u00d3n, V\u00cddeo, Hi",
    "sg:phone":"+34 959 35 08 46",
    "sg:postcode":"21810",
    "sg:province":"Huelva",
    "wof:name":"Rofa Lozano Manuel",
    "wof:placetype":"venue"
},
  "geometry": {"coordinates":[-6.8923411369,37.2240829468],"type":"Point"}
}