{
  "type": "Feature",
  "properties": {
    "addr:full":"Avda Barzola (la), 14 Sevilla Sevilla 41008",
    "addr:housenumber":"14",
    "addr:postcode":"41008",
    "addr:street":"Avda Barzola La",
    "iso:country":"ES",
    "sg:address":"Avda Barzola (la), 14",
    "sg:city":"Sevilla",
    "sg:classifiers":[
        {
            "category":"Personal",
            "subcategory":"Barber",
            "type":"Services"
        }
    ],
    "sg:phone":"+34 954 36 14 72",
    "sg:postcode":"41008",
    "sg:province":"Sevilla",
    "sg:tags":[
        "caballeros",
        "de",
        "peluqueros"
    ],
    "wof:name":"Master Peluqueros S.l.",
    "wof:placetype":"venue"
},
  "geometry": {"coordinates":[-5.9768180847,37.41173172],"type":"Point"}
}