{
  "type": "Feature",
  "properties": {
    "addr:full":"Calle de Perez Oliva, 6 Salamanca Salamanca 37005",
    "addr:housenumber":"6",
    "addr:postcode":"37005",
    "addr:street":"Calle De Perez Oliva",
    "iso:country":"ES",
    "sg:address":"Calle de Perez Oliva, 6",
    "sg:city":"Salamanca",
    "sg:orig_category":"Frutas Y Legumbres Frescas (al Por Mayor)",
    "sg:phone":"+34 923 22 63 32",
    "sg:postcode":"37005",
    "sg:province":"Salamanca",
    "wof:name":"Distribuidora De Soja S.a.",
    "wof:placetype":"venue"
},
  "geometry": {"coordinates":[-5.6606612206,40.969745636],"type":"Point"}
}