{
  "type": "Feature",
  "properties": {
    "iso:country":"ES",
    "sg:address":"Calle de Iglesia, 4",
    "sg:city":"Menasalbas",
    "sg:orig_category":"Cr\u00cda De Animales",
    "sg:phone":"+34 925 41 32 48",
    "sg:postcode":"45128",
    "sg:province":"Toledo",
    "wof:name":"Campochotos S.l.",
    "wof:placetype":"venue"
},
  "geometry": {"coordinates":[-4.2843570709,39.6395797729],"type":"Point"}
}