{
  "type": "Feature",
  "properties": {
    "addr:full":"Calle de Victorio, 20 San Lorenzo Murcia 30003",
    "addr:housenumber":"20",
    "addr:postcode":"30003",
    "addr:street":"Calle De Victorio",
    "iso:country":"ES",
    "sg:address":"Calle de Victorio, 20",
    "sg:city":"San Lorenzo",
    "sg:orig_category":"Peluqueros: De Se\u00d1oras",
    "sg:phone":"+34 968 21 97 63",
    "sg:postcode":"30003",
    "sg:province":"Murcia",
    "wof:name":"Martinez Amante Maria Carmen",
    "wof:placetype":"venue"
},
  "geometry": {"coordinates":[-1.1249599457,37.9862823486],"type":"Point"}
}