{
  "type": "Feature",
  "properties": {
    "addr:full":"Calle de Tetuan, 33 Santander Cantabria 39004",
    "addr:housenumber":"33",
    "addr:postcode":"39004",
    "addr:street":"Calle De Tetuan",
    "iso:country":"ES",
    "sg:address":"Calle de Tetuan, 33",
    "sg:city":"Santander",
    "sg:orig_category":"Molduras, Junquillos, Listones Y Molduras Perforadas",
    "sg:phone":"+34 942 21 12 60",
    "sg:postcode":"39004",
    "sg:province":"Cantabria",
    "wof:name":"Sociedad Regional De Informatica S.a.",
    "wof:placetype":"venue"
},
  "geometry": {"coordinates":[-3.7943165302,43.4658622742],"type":"Point"}
}