{
  "type": "Feature",
  "properties": {
    "iso:country":"ES",
    "sg:address":"Pase Extremadura, 222",
    "sg:city":"Monesterio",
    "sg:orig_category":"Cajas Para Embalar",
    "sg:phone":"+34 924 51 80 41",
    "sg:postcode":"06260",
    "sg:province":"Badajoz",
    "wof:name":"Caja Rural De Almendralejo",
    "wof:placetype":"venue"
},
  "geometry": {"coordinates":[-6.2717652321,38.0865287781],"type":"Point"}
}