{
  "type": "Feature",
  "properties": {
    "iso:country":"ES",
    "sg:address":"Calle de San Marcos, 45",
    "sg:city":"Manzanares",
    "sg:classifiers":[
        {
            "category":"Autos & Motor Vehicles",
            "subcategory":"Automobile Sales",
            "type":"Retail Goods"
        }
    ],
    "sg:phone":"+34 926 61 22 69",
    "sg:postcode":"13200",
    "sg:province":"Ciudad Real",
    "wof:name":"Gomez Mu\u00f1oz Jose Luis",
    "wof:placetype":"venue"
},
  "geometry": {"coordinates":[-3.3643889427,38.9994506836],"type":"Point"}
}