{
  "type": "Feature",
  "properties": {
    "addr:full":"Calle de Toro, 30 Salamanca Salamanca 37002",
    "addr:housenumber":"30",
    "addr:postcode":"37002",
    "addr:street":"Calle De Toro",
    "iso:country":"ES",
    "sg:address":"Calle de Toro, 30",
    "sg:city":"Salamanca",
    "sg:orig_category":"Estancos",
    "sg:phone":"+34 923 21 70 97",
    "sg:postcode":"37002",
    "sg:province":"Salamanca",
    "wof:name":"Mu\u00f1oz Marcos Luis",
    "wof:placetype":"venue"
},
  "geometry": {"coordinates":[-5.6628251076,40.9662590027],"type":"Point"}
}