{
  "type": "Feature",
  "properties": {
    "addr:full":"Calle de Ataulfo Argenta, 2 Castro Urdiales Cantabria 39700",
    "addr:housenumber":"2",
    "addr:postcode":"39700",
    "addr:street":"Calle De Ataulfo Argenta",
    "iso:country":"ES",
    "sg:address":"Calle de Ataulfo Argenta, 2",
    "sg:city":"Castro Urdiales",
    "sg:orig_category":"Florister\u00cdas",
    "sg:phone":"+34 942 86 76 15",
    "sg:postcode":"39700",
    "sg:province":"Cantabria",
    "wof:name":"Cerro Martinez Juan Valentin Del",
    "wof:placetype":"venue"
},
  "geometry": {"coordinates":[-3.2079179287,43.3721466064],"type":"Point"}
}