{
  "type": "Feature",
  "properties": {
    "addr:full":"Av Sant Maurici, 4 Caldes Malavella Girona 17455",
    "addr:housenumber":"4",
    "addr:postcode":"17455",
    "addr:street":"Av Sant Maurici",
    "iso:country":"ES",
    "sg:address":"Av Sant Maurici, 4",
    "sg:city":"Caldes Malavella",
    "sg:orig_category":"Bancos",
    "sg:phone":"+34 972 47 03 03",
    "sg:postcode":"17455",
    "sg:province":"Girona",
    "wof:name":"Banco Espa\u00f1ol De Credito S.a.",
    "wof:placetype":"venue"
},
  "geometry": {"coordinates":[2.8080890179,41.8365097046],"type":"Point"}
}