{
  "type": "Feature",
  "properties": {
    "iso:country":"ES",
    "sg:address":"Carrer de Joan Coromines, 9",
    "sg:city":"Terrassa",
    "sg:orig_category":"Art\u00cdculos De Decoraci\u00d3n",
    "sg:phone":"+34 937 88 87 81",
    "sg:postcode":"08221",
    "sg:province":"Barcelona",
    "wof:name":"Najar Gomez Maria Isabel",
    "wof:placetype":"venue"
},
  "geometry": {"coordinates":[2.0097010136,41.5623207092],"type":"Point"}
}