{
  "type": "Feature",
  "properties": {
    "addr:full":"Carrer de Pau Casals, 22 Montblanc Tarragona 43400",
    "addr:housenumber":"22",
    "addr:postcode":"43400",
    "addr:street":"Carrer De Pau Casals",
    "iso:country":"ES",
    "sg:address":"Carrer de Pau Casals, 22",
    "sg:city":"Montblanc",
    "sg:orig_category":"Partidos Pol\u00cdticos",
    "sg:phone":"+34 977 86 02 77",
    "sg:postcode":"43400",
    "sg:province":"Tarragona",
    "wof:name":"Convergencia Democratica De Catalunya",
    "wof:placetype":"venue"
},
  "geometry": {"coordinates":[1.165199995,41.373790741],"type":"Point"}
}