{
  "type": "Feature",
  "properties": {
    "addr:full":"Calle de Santiago, 34 Irun Guip\u00f9zcoa 20304",
    "addr:housenumber":"34",
    "addr:postcode":"20304",
    "addr:street":"Calle De Santiago;Guipu\u0300Zcoa",
    "iso:country":"ES",
    "sg:address":"Calle de Santiago, 34",
    "sg:city":"Irun",
    "sg:orig_category":"Barbacoas Y Accesorios",
    "sg:phone":"+34 943 63 09 93",
    "sg:postcode":"20304",
    "sg:province":"Guip\u00f9zcoa",
    "wof:name":"Fermin Martinez Pascual E Hijos S.l.",
    "wof:placetype":"venue"
},
  "geometry": {"coordinates":[-1.7863329649,43.3416786194],"type":"Point"}
}