{
  "type": "Feature",
  "properties": {
    "iso:country":"ES",
    "sg:address":"Calle de Oca\u00d1a, 24",
    "sg:city":"Madrid",
    "sg:orig_category":"Mec\u00c1nico Del Autom\u00d3vil",
    "sg:phone":"+34 915 25 66 70",
    "sg:postcode":"28047",
    "sg:province":"Madrid",
    "wof:name":"Talleres Jarau S.l.",
    "wof:placetype":"venue"
},
  "geometry": {"coordinates":[-3.7540800571,40.384437561],"type":"Point"}
}