{
  "type": "Feature",
  "properties": {
    "addr:full":"Carr Moll De Ponent, 15 Mao Islas Baleares 07703",
    "addr:housenumber":"15",
    "addr:postcode":"07703",
    "addr:street":"Carr Moll De Ponent",
    "iso:country":"ES",
    "sg:address":"Carr Moll De Ponent, 15",
    "sg:city":"Mao",
    "sg:orig_category":"Restaurantes",
    "sg:phone":"+34 971 35 41 69",
    "sg:postcode":"07703",
    "sg:province":"Islas Baleares",
    "wof:name":"Puglia Ranieri S.c.p.",
    "wof:placetype":"venue"
},
  "geometry": {"coordinates":[4.265625,39.8903694153],"type":"Point"}
}