{
  "type": "Feature",
  "properties": {
    "iso:country":"ES",
    "sg:address":"Calle de Jose Zorrilla, 111",
    "sg:city":"Segovia",
    "sg:orig_category":"Zapater\u00cdas",
    "sg:phone":"+34 921 43 53 50",
    "sg:postcode":"40002",
    "sg:province":"Segovia",
    "wof:name":"Higuera Gomez Maria Esther",
    "wof:placetype":"venue"
},
  "geometry": {"coordinates":[-4.1137771606,40.9382553101],"type":"Point"}
}