{
  "type": "Feature",
  "properties": {
    "addr:full":"Calle de Zeus, 90 Almeria Almer\u00eda 04009",
    "addr:housenumber":"90",
    "addr:postcode":"04009",
    "addr:street":"Calle De Zeus",
    "iso:country":"ES",
    "sg:address":"Calle de Zeus, 90",
    "sg:city":"Almeria",
    "sg:classifiers":[
        {
            "category":"Communications",
            "type":"Services"
        }
    ],
    "sg:phone":"+34 950 14 34 27",
    "sg:postcode":"04009",
    "sg:province":"Almer\u00eda",
    "sg:tags":[
        "televisiones",
        "y",
        "radio"
    ],
    "wof:name":"Fernandez Lopez Jose",
    "wof:placetype":"venue"
},
  "geometry": {"coordinates":[-2.4353690147,36.8497314453],"type":"Point"}
}