{
  "type": "Feature",
  "properties": {
    "iso:country":"ES",
    "sg:address":"Biku\u00d1a Enea Enparantza, 9",
    "sg:city":"Legazpi",
    "sg:orig_category":"Quincaller\u00cda (al Por Menor)",
    "sg:phone":"+34 943 73 43 62",
    "sg:postcode":"20230",
    "sg:province":"Guip\u00f9zcoa",
    "wof:name":"Alfonso Mahamud Gonzalez",
    "wof:placetype":"venue"
},
  "geometry": {"coordinates":[-2.3353939056,43.0490493774],"type":"Point"}
}