{
  "type": "Feature",
  "properties": {
    "addr:full":"Poli Menestrales (los) -polig.ind.-, Km. 0003,0 Posadas C\u00f3rdoba 14730",
    "addr:housenumber":"co\u0301rdoba",
    "addr:postcode":"14730",
    "addr:street":"Polig.Ind. Km. 0003,0",
    "iso:country":"ES",
    "sg:address":"Poli Menestrales (los) -polig.ind.-, Km. 0003,0",
    "sg:city":"Posadas",
    "sg:orig_category":"Mec\u00c1nico Del Autom\u00d3vil",
    "sg:phone":"+34 957 63 07 27",
    "sg:postcode":"14730",
    "sg:province":"C\u00f3rdoba",
    "wof:name":"Automoviles Posadas S.l.",
    "wof:placetype":"venue"
},
  "geometry": {"coordinates":[-97.78224945069999,45.7040786743],"type":"Point"}
}