{
  "type": "Feature",
  "properties": {
    "iso:country":"ES",
    "sg:address":"Avda San Rogelio, S/n",
    "sg:city":"Illora",
    "sg:orig_category":"Heladeros",
    "sg:phone":"+34 958 46 35 57",
    "sg:postcode":"18260",
    "sg:province":"Granada",
    "wof:name":"Cordero Gutierrez Jose Angel",
    "wof:placetype":"venue"
},
  "geometry": {"coordinates":[-3.8776741028,37.2880897522],"type":"Point"}
}