{
  "type": "Feature",
  "properties": {
    "addr:full":"Cmno Hortensias (somio), S/n Gijon Asturias 33203",
    "addr:housenumber":"s",
    "addr:postcode":"33203",
    "addr:street":"Cmno Hortensias Somio;/ N",
    "iso:country":"ES",
    "sg:address":"Cmno Hortensias (somio), S/n",
    "sg:city":"Gijon",
    "sg:orig_category":"M\u00c9dicos: Reumatolog\u00cda",
    "sg:phone":"+34 985 37 28 92",
    "sg:postcode":"33203",
    "sg:province":"Asturias",
    "wof:name":"Fuentes Blanco Maria Covadonga",
    "wof:placetype":"venue"
},
  "geometry": {"coordinates":[-5.6244301796,43.537311554],"type":"Point"}
}