{
  "type": "Feature",
  "properties": {
    "addr:full":"Avda Constitucion, 15 Roda Albacete 02630",
    "addr:housenumber":"15",
    "addr:postcode":"02630",
    "addr:street":"Avda Constitucion",
    "iso:country":"ES",
    "sg:address":"Avda Constitucion, 15",
    "sg:city":"Roda",
    "sg:orig_category":"Tapicer\u00cdas",
    "sg:phone":"+34 967 44 09 90",
    "sg:postcode":"02630",
    "sg:province":"Albacete",
    "wof:name":"Segovia Arcas Antonio",
    "wof:placetype":"venue"
},
  "geometry": {"coordinates":[-2.1613628864,39.210521698],"type":"Point"}
}