{
  "type": "Feature",
  "properties": {
    "iso:country":"ES",
    "sg:address":"Rua Rio Xubia, 157",
    "sg:city":"Ferrol",
    "sg:orig_category":"Empresarios",
    "sg:phone":"+34 981 32 28 34",
    "sg:postcode":"15403",
    "sg:province":"La Coru\u00f1a",
    "wof:name":"Alvarez Pacios Serafin",
    "wof:placetype":"venue"
},
  "geometry": {"coordinates":[-8.2246322632,43.4903907776],"type":"Point"}
}