{
  "type": "Feature",
  "properties": {
    "iso:country":"ES",
    "sg:address":"Rbla Doctor Pearson, 27",
    "sg:city":"Tremp",
    "sg:orig_category":"Electrodom\u00c9sticos (al Por Menor)",
    "sg:phone":"+34 973 65 25 52",
    "sg:postcode":"25620",
    "sg:province":"Lleida",
    "wof:name":"Electro Confort Rambla S.l.",
    "wof:placetype":"venue"
},
  "geometry": {"coordinates":[0.8943499923,42.1646270752],"type":"Point"}
}