{
  "type": "Feature",
  "properties": {
    "addr:full":"Calle de Blas Tello, 70 Manzanares Ciudad Real 13200",
    "addr:housenumber":"70",
    "addr:postcode":"13200",
    "addr:street":"Calle De Blas Tello",
    "iso:country":"ES",
    "sg:address":"Calle de Blas Tello, 70",
    "sg:city":"Manzanares",
    "sg:orig_category":"Molduras, Junquillos, Listones Y Molduras Perforadas",
    "sg:phone":"+34 926 61 27 91",
    "sg:postcode":"13200",
    "sg:province":"Ciudad Real",
    "wof:name":"Fernandez-cuadrado Arroyo Maria Isabel",
    "wof:placetype":"venue"
},
  "geometry": {"coordinates":[-3.3657801151,38.9978675842],"type":"Point"}
}