{
  "type": "Feature",
  "properties": {
    "iso:country":"ES",
    "sg:address":"Calle de Postas, 33",
    "sg:city":"Vitoria-gasteiz",
    "sg:orig_category":"Estilistas Y Estudios De Estilo De Corte Y Confecci\u00d3n",
    "sg:phone":"+34 945 25 90 78",
    "sg:postcode":"01004",
    "sg:province":"\u00c1lava",
    "wof:name":"Alvarez Gomez Claudio",
    "wof:placetype":"venue"
},
  "geometry": {"coordinates":[-2.6682012081,42.8456039429],"type":"Point"}
}