{
  "type": "Feature",
  "properties": {
    "iso:country":"ES",
    "sg:address":"Calle de General Diaz Porlier, 19",
    "sg:city":"Madrid",
    "sg:orig_category":"Molduras, Junquillos, Listones Y Molduras Perforadas",
    "sg:phone":"+34 914 35 39 80",
    "sg:postcode":"28001",
    "sg:province":"Madrid",
    "wof:name":"Ostos Garcia Marina",
    "wof:placetype":"venue"
},
  "geometry": {"coordinates":[-3.6773018837,40.4262542725],"type":"Point"}
}