{
  "type": "Feature",
  "properties": {
    "addr:full":"Pla\u00c7 Joc De La Pilota, 4 Castello D'empuries Girona 17486",
    "addr:housenumber":"4",
    "addr:postcode":"17486",
    "addr:street":"Pilota",
    "iso:country":"ES",
    "sg:address":"Pla\u00c7 Joc De La Pilota, 4",
    "sg:city":"Castello D'empuries",
    "sg:orig_category":"Ense\u00d1anza, Formaci\u00d3n Profesional: Aprendizaje",
    "sg:phone":"+34 972 25 04 26",
    "sg:postcode":"17486",
    "sg:province":"Girona",
    "wof:name":"Ajuntament De Castello D'empuries",
    "wof:placetype":"venue"
},
  "geometry": {"coordinates":[3.092689991,42.2390518188],"type":"Point"}
}