{
  "type": "Feature",
  "properties": {
    "iso:country":"ES",
    "sg:address":"Avda Primero De Mayo, 28",
    "sg:city":"Puertollano",
    "sg:orig_category":"Abogados",
    "sg:phone":"+34 926 41 14 02",
    "sg:postcode":"13500",
    "sg:province":"Ciudad Real",
    "wof:name":"Espigares Diaz Maria Del Pilar",
    "wof:placetype":"venue"
},
  "geometry": {"coordinates":[-4.1049609184,38.6864242554],"type":"Point"}
}