{
  "type": "Feature",
  "properties": {
    "iso:country":"ES",
    "sg:address":"Calle de Arraez, 7",
    "sg:city":"Almeria",
    "sg:orig_category":"Art\u00cdculos De Decoraci\u00d3n",
    "sg:phone":"+34 950 26 55 77",
    "sg:postcode":"04002",
    "sg:province":"Almer\u00eda",
    "wof:name":"Palmira Colacios Decoracion",
    "wof:placetype":"venue"
},
  "geometry": {"coordinates":[-2.4681742191,36.839553833],"type":"Point"}
}