{
  "type": "Feature",
  "properties": {
    "addr:full":"Avda Santa Amalia, 28 Fuengirola M\u00e1laga 29640",
    "addr:housenumber":"28",
    "addr:postcode":"29640",
    "addr:street":"Avda Santa Amalia;Ma\u0301Laga",
    "iso:country":"ES",
    "sg:address":"Avda Santa Amalia, 28",
    "sg:city":"Fuengirola",
    "sg:orig_category":"Muebles Y Accesorios Para Cocinas Y Cuartos De Ba\u00d1o (al Por Menor)",
    "sg:phone":"+34 952 46 56 85",
    "sg:postcode":"29640",
    "sg:province":"M\u00e1laga",
    "wof:name":"De Olague Garcia Juan Carlos",
    "wof:placetype":"venue"
},
  "geometry": {"coordinates":[-4.6273927689,36.5316123962],"type":"Point"}
}