{
  "type": "Feature",
  "properties": {
    "iso:country":"ES",
    "sg:address":"Avda Portugal, S/n",
    "sg:city":"Villalcampo",
    "sg:orig_category":"Farmacias",
    "sg:phone":"+34 980 55 47 84",
    "sg:postcode":"49166",
    "sg:province":"Zamora",
    "wof:name":"Prieto Corpas Juan",
    "wof:placetype":"venue"
},
  "geometry": {"coordinates":[-6.0505809784,41.5212364197],"type":"Point"}
}