{
  "type": "Feature",
  "properties": {
    "iso:country":"ES",
    "sg:address":"Carr Bisbe Guitart, 29",
    "sg:city":"Seu D'urgell",
    "sg:orig_category":"Fotocopias, Reprograf\u00cda",
    "sg:phone":"+34 973 35 46 45",
    "sg:postcode":"25700",
    "sg:province":"Lleida",
    "wof:name":"Molina Cano Josep Maria",
    "wof:placetype":"venue"
},
  "geometry": {"coordinates":[0.6119109988,41.6164245605],"type":"Point"}
}