{
  "type": "Feature",
  "properties": {
    "addr:full":"Calle de Nuestra Se\u00d1ora Del Rosario, 3 Rota C\u00e1diz 11520",
    "addr:housenumber":"3",
    "addr:postcode":"11520",
    "addr:street":"Calle De Nuestra Sen\u0303Ora Del Rosario;Ca\u0301Diz",
    "iso:country":"ES",
    "sg:address":"Calle de Nuestra Se\u00d1ora Del Rosario, 3",
    "sg:city":"Rota",
    "sg:orig_category":"Florister\u00cdas",
    "sg:phone":"+34 956 81 16 68",
    "sg:postcode":"11520",
    "sg:province":"C\u00e1diz",
    "wof:name":"Viveros Hnos. Olmedo S. L.",
    "wof:placetype":"venue"
},
  "geometry": {"coordinates":[-6.3582220078,36.6187362671],"type":"Point"}
}