{
  "type": "Feature",
  "properties": {
    "iso:country":"ES",
    "sg:address":"Calle de Angelita Cavero, 11",
    "sg:city":"Madrid",
    "sg:orig_category":"Molduras, Junquillos, Listones Y Molduras Perforadas",
    "sg:phone":"+34 917 42 51 89",
    "sg:postcode":"28027",
    "sg:province":"Madrid",
    "wof:name":"Parejo Diaz Gabriel",
    "wof:placetype":"venue"
},
  "geometry": {"coordinates":[-3.6467738152,40.4473190308],"type":"Point"}
}