{
  "type": "Feature",
  "properties": {
    "iso:country":"ES",
    "sg:address":"Hondartza Kalea, 8",
    "sg:city":"Deba",
    "sg:orig_category":"Florister\u00cdas",
    "sg:phone":"+34 943 19 11 67",
    "sg:postcode":"20820",
    "sg:province":"Guip\u00f9zcoa",
    "wof:name":"Burga\u00f1a Rubio Pedro",
    "wof:placetype":"venue"
},
  "geometry": {"coordinates":[-2.3541989326,43.2953186035],"type":"Point"}
}