{
  "type": "Feature",
  "properties": {
    "addr:full":"Calle de Burbia, S/n Barrio De Pinilla Le\u00f3n 24010",
    "addr:housenumber":"s / n",
    "addr:postcode":"24010",
    "addr:street":"Calle De Burbia",
    "iso:country":"ES",
    "sg:address":"Calle de Burbia, S/n",
    "sg:city":"Barrio De Pinilla",
    "sg:orig_category":"Panader\u00cdas, Panader\u00cdas",
    "sg:phone":"+34 987 22 17 77",
    "sg:postcode":"24010",
    "sg:province":"Le\u00f3n",
    "wof:name":"Riesco Lozano Iluminada",
    "wof:placetype":"venue"
},
  "geometry": {"coordinates":[-5.5686106682,42.6233596802],"type":"Point"}
}