{
  "type": "Feature",
  "properties": {
    "iso:country":"ES",
    "sg:address":"Avda Nuestro Padre Jesus, 6",
    "sg:city":"Aznalcazar",
    "sg:orig_category":"Farmacias",
    "sg:phone":"+34 955 75 00 91",
    "sg:postcode":"41849",
    "sg:province":"Sevilla",
    "wof:name":"Vazquez Rosso Alberto",
    "wof:placetype":"venue"
},
  "geometry": {"coordinates":[-6.2495188713,37.3036460876],"type":"Point"}
}