{
  "type": "Feature",
  "properties": {
    "iso:country":"ES",
    "sg:address":"Pase Canalejas, 76",
    "sg:city":"Santander",
    "sg:orig_category":"Zapater\u00cdas",
    "sg:phone":"+34 942 27 56 41",
    "sg:postcode":"39004",
    "sg:province":"Cantabria",
    "wof:name":"Gomez Somarriba Luis Fernando",
    "wof:placetype":"venue"
},
  "geometry": {"coordinates":[-3.7872130871,43.4658622742],"type":"Point"}
}