{
  "type": "Feature",
  "properties": {
    "iso:country":"ES",
    "sg:address":"Avda Murcia (de), 63",
    "sg:city":"Bullas",
    "sg:orig_category":"Centros M\u00c9dicos Y Sociales, Dispensarios",
    "sg:phone":"+34 968 65 47 44",
    "sg:postcode":"30180",
    "sg:province":"Murcia",
    "wof:name":"Centro Medico Castellar S.l.",
    "wof:placetype":"venue"
},
  "geometry": {"coordinates":[-1.667296052,38.0504684448],"type":"Point"}
}