{
  "type": "Feature",
  "properties": {
    "addr:full":"Calle de Zubiaurre, 47 Donostia-san Sebastian Guip\u00f9zcoa 20015",
    "addr:housenumber":"47",
    "addr:postcode":"20015",
    "addr:street":"Calle De Zubiaurre",
    "iso:country":"ES",
    "sg:address":"Calle de Zubiaurre, 47",
    "sg:city":"Donostia-san Sebastian",
    "sg:orig_category":"Cuchiller\u00cda (al Por Menor)",
    "sg:phone":"+34 943 27 34 93",
    "sg:postcode":"20015",
    "sg:province":"Guip\u00f9zcoa",
    "wof:name":"Vazquez Barba Milagros",
    "wof:placetype":"venue"
},
  "geometry": {"coordinates":[-1.9558360577,43.319984436],"type":"Point"}
}