{
  "type": "Feature",
  "properties": {
    "iso:country":"ES",
    "sg:address":"Calle de Rio (san Juan De Mozarrifar), 30",
    "sg:city":"San Juan De Mozarrifar",
    "sg:classifiers":[
        {
            "category":"Manufacturing",
            "subcategory":"Metals",
            "type":"Manufacturing & Wholesale Goods"
        }
    ],
    "sg:phone":"+34 976 15 01 43",
    "sg:postcode":"50820",
    "sg:province":"Zaragoza",
    "sg:tags":[
        "en",
        "fundiciones"
    ],
    "wof:name":"Torres Aznar Francisco",
    "wof:placetype":"venue"
},
  "geometry": {"coordinates":[-0.8331980109,41.713722229],"type":"Point"}
}