{
  "type": "Feature",
  "properties": {
    "iso:country":"ES",
    "sg:address":"Av. Rebullon, S/n",
    "sg:city":"Mos",
    "sg:orig_category":"Papeler\u00cdas: Art\u00cdculos (al Por Mayor)",
    "sg:phone":"+34 986 48 88 82",
    "sg:postcode":"36416",
    "sg:province":"Pontevedra",
    "wof:name":"Distrisantiago Papeleria Vigo S.l.",
    "wof:placetype":"venue"
},
  "geometry": {"coordinates":[-8.6641283035,42.2043952942],"type":"Point"}
}