{
  "type": "Feature",
  "properties": {
    "iso:country":"ES",
    "sg:address":"Ctra Moraira A Calpe, 3",
    "sg:city":"Moraira",
    "sg:orig_category":"Peluquer\u00cdas, Peluquer\u00cda Mixta",
    "sg:phone":"+34 965 74 49 99",
    "sg:postcode":"03724",
    "sg:province":"Alicante",
    "wof:name":"Peluqueria Unisex Montemar S.r.l.",
    "wof:placetype":"venue"
},
  "geometry": {"coordinates":[0.1333699971,38.6890983582],"type":"Point"}
}