{
  "type": "Feature",
  "properties": {
    "iso:country":"ES",
    "sg:address":"Mendigorritxu Kalea, 59",
    "sg:city":"Jundiz",
    "sg:orig_category":"Comercio De Hierro",
    "sg:phone":"+34 945 29 24 24",
    "sg:postcode":"01015",
    "sg:province":"\u00c1lava",
    "sg:website":"www.rosacares.es",
    "wof:name":"Abal Transformados S.l.",
    "wof:placetype":"venue"
},
  "geometry": {"coordinates":[-2.746437,42.83876],"type":"Point"}
}