{
  "type": "Feature",
  "properties": {
    "iso:country":"ES",
    "sg:address":"Calle de Obispo Rey Redondo, 22",
    "sg:city":"San Cristobal De La Laguna",
    "sg:orig_category":"Moda",
    "sg:phone":"+34 922 25 85 22",
    "sg:postcode":"38201",
    "sg:province":"Santa Cruz De Tenerife",
    "wof:name":"Ledesma Dominguez Felix Juan",
    "wof:placetype":"venue"
},
  "geometry": {"coordinates":[-16.3162479401,28.4884376526],"type":"Point"}
}