{
  "type": "Feature",
  "properties": {
    "iso:country":"ES",
    "sg:address":"Calle de Secorun, 2",
    "sg:city":"Sabi\u00f1anigo",
    "sg:orig_category":"Jardiner\u00cdas, Vegetales, Art\u00cdculos De Jardiner\u00cda (al Por Menor)",
    "sg:phone":"+34 974 48 23 96",
    "sg:postcode":"22600",
    "sg:province":"Huesca",
    "wof:name":"Cajal Bosque Y Jardin S.l.",
    "wof:placetype":"venue"
},
  "geometry": {"coordinates":[-0.3601740003,42.5245132446],"type":"Point"}
}