{
  "type": "Feature",
  "properties": {
    "iso:country":"ES",
    "sg:address":"Calle de Rio Viejo, 30",
    "sg:city":"Fuente Del Rey",
    "sg:orig_category":"Electrodom\u00c9sticos (fabricaci\u00d3n, Al Por Mayor)",
    "sg:phone":"+34 954 93 00 76",
    "sg:postcode":"41700",
    "sg:province":"Sevilla",
    "wof:name":"Activa Hogar Sur S.a.",
    "wof:placetype":"venue"
},
  "geometry": {"coordinates":[-5.9939994812,37.2816772461],"type":"Point"}
}