{
  "type": "Feature",
  "properties": {
    "iso:country":"ES",
    "sg:address":"Carrer de Pirineus, 133",
    "sg:city":"Sant Salvador",
    "sg:orig_category":"Promotores Constructores",
    "sg:phone":"+34 977 52 17 89",
    "sg:postcode":"43130",
    "sg:province":"Tarragona",
    "wof:name":"Reformas Rocio 3133 S.l.",
    "wof:placetype":"venue"
},
  "geometry": {"coordinates":[1.240702033,41.160697937],"type":"Point"}
}