{
  "type": "Feature",
  "properties": {
    "iso:country":"ES",
    "sg:address":"Calle de Palmar, 12",
    "sg:city":"Borriol",
    "sg:orig_category":"Cintas, Balduques Y Cierres De Tela (fabricaci\u00d3n, Al Por Mayor)",
    "sg:phone":"+34 964 32 10 34",
    "sg:postcode":"12190",
    "sg:province":"Castell\u00f3n",
    "wof:name":"Novitex C.b.",
    "wof:placetype":"venue"
},
  "geometry": {"coordinates":[-0.0672520027,40.0406150818],"type":"Point"}
}