{
  "type": "Feature",
  "properties": {
    "iso:country":"ES",
    "sg:address":"Perez De Abajo, S/n",
    "sg:city":"La Palma",
    "sg:orig_category":"Cl\u00cdnicas M\u00c9dicas",
    "sg:phone":"+34 968 55 48 83",
    "sg:postcode":"30593",
    "sg:province":"Murcia",
    "wof:name":"Cruz Verde Servicios Socio-sanitarios S.l.",
    "wof:placetype":"venue"
},
  "geometry": {"coordinates":[-0.9635639787,37.689781189],"type":"Point"}
}