{
  "type": "Feature",
  "properties": {
    "iso:country":"ES",
    "sg:address":"Calle de Caballero De Rodas, 136",
    "sg:city":"Torrevieja",
    "sg:orig_category":"Promotores Constructores",
    "sg:phone":"+34 965 71 46 14",
    "sg:postcode":"03180",
    "sg:province":"Alicante",
    "wof:name":"Torre-cox S.l.",
    "wof:placetype":"venue"
},
  "geometry": {"coordinates":[-0.6723849773,37.978225708],"type":"Point"}
}