{
  "type": "Feature",
  "properties": {
    "addr:full":"Carrer de Vint-i-dos, 62 Bonavista Tarragona 43100",
    "addr:housenumber":"62",
    "addr:postcode":"43100",
    "addr:street":"Carrer De Vint-I-Dos",
    "iso:country":"ES",
    "sg:address":"Carrer de Vint-i-dos, 62",
    "sg:city":"Bonavista",
    "sg:orig_category":"Molduras, Junquillos, Listones Y Molduras Perforadas",
    "sg:phone":"+34 977 54 92 56",
    "sg:postcode":"43100",
    "sg:province":"Tarragona",
    "wof:name":"Garcia Martinez David",
    "wof:placetype":"venue"
},
  "geometry": {"coordinates":[1.1934130192,41.1214027405],"type":"Point"}
}