{
  "type": "Feature",
  "properties": {
    "addr:full":"Ctra Mota, Km. 0030,0 Zaratan Valladolid 47610",
    "addr:housenumber":"km.",
    "addr:postcode":"47610",
    "addr:street":"Ctra Mota;0030,0 Zaratan",
    "iso:country":"ES",
    "sg:address":"Ctra Mota, Km. 0030,0",
    "sg:city":"Zaratan",
    "sg:orig_category":"Fabricaci\u00d3n, Importaci\u00d3n De L\u00c1mparas Y Bombillas",
    "sg:phone":"+34 983 36 02 89",
    "sg:postcode":"47610",
    "sg:province":"Valladolid",
    "sg:website":"www.luminus.es",
    "wof:name":"Luz Luminus S.a.",
    "wof:placetype":"venue"
},
  "geometry": {"coordinates":[-4.7839388847,41.6605911255],"type":"Point"}
}