{
  "type": "Feature",
  "properties": {
    "addr:full":"Avda Burguillos, S/n Guillena Sevilla 41210",
    "addr:housenumber":"s / n",
    "addr:postcode":"41210",
    "addr:street":"Avda Burguillos",
    "iso:country":"ES",
    "sg:address":"Avda Burguillos, S/n",
    "sg:city":"Guillena",
    "sg:orig_category":"Molduras, Junquillos, Listones Y Molduras Perforadas",
    "sg:phone":"+34 955 78 46 87",
    "sg:postcode":"41210",
    "sg:province":"Sevilla",
    "wof:name":"Venta El Palmarillo S.l.",
    "wof:placetype":"venue"
},
  "geometry": {"coordinates":[-6.0542788506,37.5486984253],"type":"Point"}
}