{
  "type": "Feature",
  "properties": {
    "addr:full":"Calle de Rio Mi\u00d1o, S/n Valencia Valencia 46017",
    "addr:housenumber":"s / n",
    "addr:postcode":"46017",
    "addr:street":"Calle De Rio Min\u0303O",
    "iso:country":"ES",
    "sg:address":"Calle de Rio Mi\u00d1o, S/n",
    "sg:city":"Valencia",
    "sg:orig_category":"Negocio De Materiales De Construcci\u00d3n",
    "sg:phone":"+34 963 78 79 71",
    "sg:postcode":"46017",
    "sg:province":"Valencia",
    "wof:name":"Camarasa Sabater Joaquin",
    "wof:placetype":"venue"
},
  "geometry": {"coordinates":[-0.3858639896,39.4534835815],"type":"Point"}
}