{
  "type": "Feature",
  "properties": {
    "addr:full":"Arquillo, 9 Teruel Teruel 44003",
    "addr:housenumber":"9",
    "addr:postcode":"44003",
    "addr:street":"Arquillo",
    "iso:country":"ES",
    "sg:address":"Arquillo, 9",
    "sg:city":"Teruel",
    "sg:orig_category":"Bricolaje, Herramientas (al Por Menor)",
    "sg:phone":"+34 978 60 24 42",
    "sg:postcode":"44003",
    "sg:province":"Teruel",
    "wof:name":"L.d. Bricolage S.l.",
    "wof:placetype":"venue"
},
  "geometry": {"coordinates":[-1.1077599525,40.3506164551],"type":"Point"}
}