{
  "type": "Feature",
  "properties": {
    "iso:country":"ES",
    "sg:address":"Calle de Santiago, 14",
    "sg:city":"Cabeza Buey",
    "sg:orig_category":"Empresas De Carpinter\u00cda De Madera",
    "sg:phone":"+34 924 63 22 02",
    "sg:postcode":"06600",
    "sg:province":"Badajoz",
    "wof:name":"Moreno Maya Miguel",
    "wof:placetype":"venue"
},
  "geometry": {"coordinates":[-5.2172760963,38.7211074829],"type":"Point"}
}