{
  "type": "Feature",
  "properties": {
    "addr:full":"Carr Migdia, 12 Figueres Girona 17600",
    "addr:housenumber":"12",
    "addr:postcode":"17600",
    "addr:street":"Carr Migdia",
    "iso:country":"ES",
    "sg:address":"Carr Migdia, 12",
    "sg:city":"Figueres",
    "sg:orig_category":"Fabricaci\u00d3n, Venta De Cuadros, Accesorios Para Enmarcar",
    "sg:phone":"+34 972 50 43 44",
    "sg:postcode":"17600",
    "sg:province":"Girona",
    "wof:name":"Dalmau Nuren S.c.",
    "wof:placetype":"venue"
},
  "geometry": {"coordinates":[2.9673159122,42.2631988525],"type":"Point"}
}