{
  "type": "Feature",
  "properties": {
    "iso:country":"ES",
    "sg:address":"Ctra Abrera, Km. 0024,9",
    "sg:city":"Sant Pau",
    "sg:orig_category":"Trabajos De Soldaduras",
    "sg:phone":"+34 938 75 07 35",
    "sg:postcode":"08241",
    "sg:province":"Barcelona",
    "wof:name":"Talleres Bande S.l.",
    "wof:placetype":"venue"
},
  "geometry": {"coordinates":[1.8238949776,41.7253952026],"type":"Point"}
}