{
  "type": "Feature",
  "properties": {
    "addr:full":"Calle de Carmen (del), 10 Jaca Huesca 22700",
    "addr:housenumber":"10",
    "addr:postcode":"22700",
    "addr:street":"Calle De Carmen Del",
    "iso:country":"ES",
    "sg:address":"Calle de Carmen (del), 10",
    "sg:city":"Jaca",
    "sg:orig_category":"Ropa Para Ni\u00d1os (al Por Menor)",
    "sg:phone":"+34 974 36 02 30",
    "sg:postcode":"22700",
    "sg:province":"Huesca",
    "wof:name":"Sarasa Bailo Amparo",
    "wof:placetype":"venue"
},
  "geometry": {"coordinates":[-0.5503140092,42.5690803528],"type":"Point"}
}