{
  "type": "Feature",
  "properties": {
    "addr:full":"Calle de Angel Del Alcazar, 7 Talavera Reina Toledo 45600",
    "addr:housenumber":"7",
    "addr:postcode":"45600",
    "addr:street":"Calle De Angel Del Alcazar",
    "iso:country":"ES",
    "sg:address":"Calle de Angel Del Alcazar, 7",
    "sg:city":"Talavera Reina",
    "sg:orig_category":"Bancos",
    "sg:phone":"+34 925 81 92 50",
    "sg:postcode":"45600",
    "sg:province":"Toledo",
    "wof:name":"Bankinter S.a.",
    "wof:placetype":"venue"
},
  "geometry": {"coordinates":[-4.8238220215,39.9635124207],"type":"Point"}
}