{
  "type": "Feature",
  "properties": {
    "iso:country":"ES",
    "sg:address":"Plaz Rollo (del), 27",
    "sg:city":"Avila",
    "sg:orig_category":"Electrodom\u00c9sticos (al Por Menor)",
    "sg:phone":"+34 920 22 79 36",
    "sg:postcode":"05002",
    "sg:province":"\u00c1vila",
    "wof:name":"Martin Sanchez Mariano",
    "wof:placetype":"venue"
},
  "geometry": {"coordinates":[-4.6997718811,40.650718689],"type":"Point"}
}