{
  "type": "Feature",
  "properties": {
    "addr:full":"Avda Ramon Y Cajal, 8 Yuncos Toledo 45210",
    "addr:housenumber":"8",
    "addr:postcode":"45210",
    "addr:street":"Avda Ramon Y Cajal",
    "iso:country":"ES",
    "sg:address":"Avda Ramon Y Cajal, 8",
    "sg:city":"Yuncos",
    "sg:orig_category":"Molduras, Junquillos, Listones Y Molduras Perforadas",
    "sg:phone":"+34 925 55 79 71",
    "sg:postcode":"45210",
    "sg:province":"Toledo",
    "wof:name":"Diaz Lopez Esperanza",
    "wof:placetype":"venue"
},
  "geometry": {"coordinates":[-3.871516943,40.0863723755],"type":"Point"}
}