{
  "type": "Feature",
  "properties": {
    "iso:country":"ES",
    "sg:address":"Calle de San Jose, 2",
    "sg:city":"Le\u00f3n",
    "sg:orig_category":"Internados & Ense\u00d1anza Privada",
    "sg:phone":"+34 987 22 11 79",
    "sg:postcode":"24010",
    "sg:province":"Le\u00f3n",
    "wof:name":"Franciscanas Misioneras De La Madre Del Divino Pastor Provincia De Leon Colegio Divina Pastora De Le",
    "wof:placetype":"venue"
},
  "geometry": {"coordinates":[-5.5904688835,42.6043167114],"type":"Point"}
}