{
  "type": "Feature",
  "properties": {
    "addr:full":"Avda Balaidos, S/n Vigo Pontevedra 36210",
    "addr:housenumber":"s",
    "addr:postcode":"36210",
    "addr:street":"Avda Balaidos;/ N",
    "iso:country":"ES",
    "sg:address":"Avda Balaidos, S/n",
    "sg:city":"Vigo",
    "sg:orig_category":"Asociaciones Y Clubs Deportivos",
    "sg:phone":"+34 986 21 32 30",
    "sg:postcode":"36210",
    "sg:province":"Pontevedra",
    "sg:website":"www.celtavigo.net",
    "wof:name":"Real Club Celta",
    "wof:placetype":"venue"
},
  "geometry": {"coordinates":[-8.7372894287,42.2128791809],"type":"Point"}
}