{
  "type": "Feature",
  "properties": {
    "iso:country":"ES",
    "sg:address":"Plaz Concordia (de La), 5",
    "sg:city":"San Mateo",
    "sg:orig_category":"Ropa Para Ni\u00d1os (al Por Menor)",
    "sg:phone":"+34 968 44 20 05",
    "sg:postcode":"30800",
    "sg:province":"Murcia",
    "wof:name":"Roldan Navarro Angela",
    "wof:placetype":"venue"
},
  "geometry": {"coordinates":[-1.6905640364,37.680557251],"type":"Point"}
}