{
  "type": "Feature",
  "properties": {
    "addr:full":"Carrer de Joan Fuster, 9 Ibi Alicante 03440",
    "addr:housenumber":"9",
    "addr:postcode":"03440",
    "addr:street":"Carrer De Joan Fuster",
    "iso:country":"ES",
    "sg:address":"Carrer de Joan Fuster, 9",
    "sg:city":"Ibi",
    "sg:orig_category":"Electricidad: Instaladores",
    "sg:phone":"+34 965 55 35 56",
    "sg:postcode":"03440",
    "sg:province":"Alicante",
    "wof:name":"Campoy Electricidad S.l.",
    "wof:placetype":"venue"
},
  "geometry": {"coordinates":[-0.5721780062,38.6229820251],"type":"Point"}
}