{
  "type": "Feature",
  "properties": {
    "iso:country":"ES",
    "sg:address":"Rond Port, Del, S/n",
    "sg:city":"Manacor",
    "sg:orig_category":"Centros De Educaci\u00d3n Especial",
    "sg:phone":"+34 971 55 41 16",
    "sg:postcode":"07500",
    "sg:province":"Islas Baleares",
    "wof:name":"Aproscom",
    "wof:placetype":"venue"
},
  "geometry": {"coordinates":[3.2382509708,39.5448951721],"type":"Point"}
}