{
  "type": "Feature",
  "properties": {
    "iso:country":"ES",
    "sg:address":"Calle de Marques De Zenete, 6",
    "sg:city":"Valencia",
    "sg:orig_category":"Mec\u00c1nico Del Autom\u00d3vil",
    "sg:phone":"+34 963 85 24 15",
    "sg:postcode":"46007",
    "sg:province":"Valencia",
    "wof:name":"Pascual Gimeno Miguel",
    "wof:placetype":"venue"
},
  "geometry": {"coordinates":[-0.3847368062,39.4655151367],"type":"Point"}
}