{
  "type": "Feature",
  "properties": {
    "addr:full":"Carrer de Drago, 45 Masies Catalanes Tarragona 43479",
    "addr:housenumber":"45",
    "addr:postcode":"43479",
    "addr:street":"Carrer De Drago",
    "iso:country":"ES",
    "sg:address":"Carrer de Drago, 45",
    "sg:city":"Masies Catalanes",
    "sg:orig_category":"Expertos Contables, Revisores De Cuentas",
    "sg:phone":"+34 977 84 64 46",
    "sg:postcode":"43479",
    "sg:province":"Tarragona",
    "sg:website":"www.sagardoyauditores.com",
    "wof:name":"Sagardoy Auditores S L",
    "wof:placetype":"venue"
},
  "geometry": {"coordinates":[1.0893199444,41.25207901],"type":"Point"}
}