{
  "type": "Feature",
  "properties": {
    "addr:full":"Calle de Maestro Amado Moran, S/n Gijon Asturias 33213",
    "addr:housenumber":"s",
    "addr:postcode":"33213",
    "addr:street":"Calle De Maestro Amado Moran;/ N",
    "iso:country":"ES",
    "sg:address":"Calle de Maestro Amado Moran, S/n",
    "sg:city":"Gijon",
    "sg:orig_category":"Ropa Para Se\u00d1oras (al Por Menor)",
    "sg:phone":"+34 985 31 62 78",
    "sg:postcode":"33213",
    "sg:province":"Asturias",
    "wof:name":"Modas Queen S.l.",
    "wof:placetype":"venue"
},
  "geometry": {"coordinates":[-5.6962928772,43.5371437073],"type":"Point"}
}