{
  "type": "Feature",
  "properties": {
    "iso:country":"ES",
    "sg:address":"Calle de Ernio, 3",
    "sg:city":"Errenteria",
    "sg:orig_category":"Empresas De Limpieza",
    "sg:phone":"+34 943 01 69 02",
    "sg:postcode":"20100",
    "sg:province":"Guip\u00f9zcoa",
    "wof:name":"Limpiezas Spray , S.l",
    "wof:placetype":"venue"
},
  "geometry": {"coordinates":[-1.9103939533,43.3131446838],"type":"Point"}
}