{
  "type": "Feature",
  "properties": {
    "iso:country":"ES",
    "sg:address":"Avda De La Reu, 17",
    "sg:city":"Nerva",
    "sg:orig_category":"\u00d3ptica: Instrumentos (fabricaci\u00d3n)",
    "sg:phone":"+34 959 58 21 94",
    "sg:postcode":"21670",
    "sg:province":"Huelva",
    "wof:name":"Visual Optica Nerva S.l.",
    "wof:placetype":"venue"
},
  "geometry": {"coordinates":[-6.5501041412,37.6965942383],"type":"Point"}
}