{
  "type": "Feature",
  "properties": {
    "iso:country":"ES",
    "sg:address":"Carrer de Bergueda, 36",
    "sg:city":"Vendrell",
    "sg:orig_category":"Reposter\u00cdas",
    "sg:phone":"+34 977 66 21 50",
    "sg:postcode":"43700",
    "sg:province":"Tarragona",
    "wof:name":"Merchan Platero Policarpo",
    "wof:placetype":"venue"
},
  "geometry": {"coordinates":[1.5243569613,41.2202606201],"type":"Point"}
}