{
  "type": "Feature",
  "properties": {
    "addr:full":"Calle de Serrato, 2 Ronda M\u00e1laga 29400",
    "addr:housenumber":"2",
    "addr:postcode":"29400",
    "addr:street":"Calle De Serrato;Ronda Ma\u0301Laga",
    "iso:country":"ES",
    "sg:address":"Calle de Serrato, 2",
    "sg:city":"Ronda",
    "sg:orig_category":"Centros M\u00c9dicos Y Sociales, Dispensarios",
    "sg:phone":"+34 952 87 56 31",
    "sg:postcode":"29400",
    "sg:province":"M\u00e1laga",
    "wof:name":"Centro Medico Del Conductor Al Andalus S.cv",
    "wof:placetype":"venue"
},
  "geometry": {"coordinates":[-5.1603808403,36.745803833],"type":"Point"}
}