{
  "type": "Feature",
  "properties": {
    "iso:country":"ES",
    "sg:address":"Ctra San Javier, Km. 0007,0",
    "sg:city":"Secano",
    "sg:orig_category":"Alquiler De Material Y De Programas Audiovisuales",
    "sg:phone":"+34 968 83 70 25",
    "sg:postcode":"30579",
    "sg:province":"Murcia",
    "sg:website":"www.discosurbano.com",
    "wof:name":"Discos Urbano S.l.",
    "wof:placetype":"venue"
},
  "geometry": {"coordinates":[-1.0529290438,37.9830245972],"type":"Point"}
}