{
  "type": "Feature",
  "properties": {
    "iso:country":"ES",
    "sg:address":"San Marco, 15",
    "sg:city":"San Marcos",
    "sg:orig_category":"Talleres: Ropa A Medida",
    "sg:phone":"+34 981 67 36 47",
    "sg:postcode":"15318",
    "sg:province":"La Coru\u00f1a",
    "wof:name":"Regueiro Cacheiro Tomas",
    "wof:placetype":"venue"
},
  "geometry": {"coordinates":[-8.4912586212,42.8925590515],"type":"Point"}
}