{
  "type": "Feature",
  "properties": {
    "iso:country":"ES",
    "sg:address":"Calle de Muro De Los Navarros, 24",
    "sg:city":"Sevilla",
    "sg:orig_category":"Arquitectos",
    "sg:phone":"+34 954 54 09 41",
    "sg:postcode":"41003",
    "sg:province":"Sevilla",
    "wof:name":"Del Pozo Rodriguez Daniel",
    "wof:placetype":"venue"
},
  "geometry": {"coordinates":[-5.9824252129,37.3899536133],"type":"Point"}
}