{
  "type": "Feature",
  "properties": {
    "addr:full":"Calle de Pozo De Las Nieves, 24 Torrejon Ardoz Madrid 28850",
    "addr:housenumber":"24",
    "addr:postcode":"28850",
    "addr:street":"Calle De Pozo De Las Nieves",
    "iso:country":"ES",
    "sg:address":"Calle de Pozo De Las Nieves, 24",
    "sg:city":"Torrejon Ardoz",
    "sg:orig_category":"Pescader\u00cdas (al Por Menor)",
    "sg:phone":"+34 916 56 85 30",
    "sg:postcode":"28850",
    "sg:province":"Madrid",
    "wof:name":"La Trucha De Oro Comunidad De Bienes",
    "wof:placetype":"venue"
},
  "geometry": {"coordinates":[-3.4630169868,40.4457626343],"type":"Point"}
}