{
  "type": "Feature",
  "properties": {
    "addr:full":"Carr Gran, S/n Castell Islas Baleares 07720",
    "addr:housenumber":"s / n",
    "addr:postcode":"07720",
    "addr:street":"Carr Gran",
    "iso:country":"ES",
    "sg:address":"Carr Gran, S/n",
    "sg:city":"Castell",
    "sg:classifiers":[
        {
            "category":"Taxi",
            "type":"Transportation"
        }
    ],
    "sg:phone":"+34 971 36 27 79",
    "sg:postcode":"07720",
    "sg:province":"Islas Baleares",
    "wof:name":"Ajuntament D'es Castell",
    "wof:placetype":"venue"
},
  "geometry": {"coordinates":[4.2890400887,39.8797645569],"type":"Point"}
}