{
  "type": "Feature",
  "properties": {
    "addr:full":"Calle de Mayor, 65 Cari\u00f1ena Zaragoza 50400",
    "addr:housenumber":"65",
    "addr:postcode":"50400",
    "addr:street":"Calle De Mayor",
    "iso:country":"ES",
    "sg:address":"Calle de Mayor, 65",
    "sg:city":"Cari\u00f1ena",
    "sg:orig_category":"Cajas De Ahorro",
    "sg:phone":"+34 976 62 20 18",
    "sg:postcode":"50400",
    "sg:province":"Zaragoza",
    "wof:name":"Caja De Ahorros De La Inmaculada",
    "wof:placetype":"venue"
},
  "geometry": {"coordinates":[-1.2246450186,41.3390388489],"type":"Point"}
}