{
  "type": "Feature",
  "properties": {
    "addr:full":"Calle de Poeta Luis Cernuda, 10 Cordoba C\u00f3rdoba 14012",
    "addr:housenumber":"10",
    "addr:postcode":"14012",
    "addr:street":"Calle De Poeta Luis Cernuda;Co\u0301Rdoba",
    "iso:country":"ES",
    "sg:address":"Calle de Poeta Luis Cernuda, 10",
    "sg:city":"Cordoba",
    "sg:orig_category":"Inmobiliaria (agencias)",
    "sg:phone":"+34 957 27 68 74",
    "sg:postcode":"14012",
    "sg:province":"C\u00f3rdoba",
    "wof:name":"Silap S.a.",
    "wof:placetype":"venue"
},
  "geometry": {"coordinates":[-4.7984490395,37.903968811],"type":"Point"}
}