{
  "type": "Feature",
  "properties": {
    "addr:full":"Calle de Ba\u00d1os, 2 Albacete Albacete 02004",
    "addr:housenumber":"2",
    "addr:postcode":"02004",
    "addr:street":"Calle De Ban\u0303Os",
    "iso:country":"ES",
    "sg:address":"Calle de Ba\u00d1os, 2",
    "sg:city":"Albacete",
    "sg:orig_category":"Carnicer\u00cdas, Carnicer\u00cdas",
    "sg:phone":"+34 967 22 89 10",
    "sg:postcode":"02004",
    "sg:province":"Albacete",
    "wof:name":"Rubio Martinez Jose Luis",
    "wof:placetype":"venue"
},
  "geometry": {"coordinates":[-1.8601125479,38.9944801331],"type":"Point"}
}