{
  "type": "Feature",
  "properties": {
    "iso:country":"ES",
    "sg:address":"Av Catalunya, 76",
    "sg:city":"Vila-sana",
    "sg:orig_category":"Arboricultura Y Producci\u00d3n De Frutas",
    "sg:phone":"+34 973 71 12 96",
    "sg:postcode":"25245",
    "sg:province":"Lleida",
    "wof:name":"Frucavi S.coop.c.l.",
    "wof:placetype":"venue"
},
  "geometry": {"coordinates":[0.9312530756,41.6611976624],"type":"Point"}
}