{
  "type": "Feature",
  "properties": {
    "iso:country":"ES",
    "sg:address":"Calle de Sebastian Elcano, 10",
    "sg:city":"Zamora",
    "sg:orig_category":"Alimentaci\u00d3n General (al Por Menor)",
    "sg:phone":"+34 980 51 02 22",
    "sg:postcode":"49020",
    "sg:province":"Zamora",
    "wof:name":"Agustina Juan Fernandez Y Maria Sonia Esteban Juan Cdad",
    "wof:placetype":"venue"
},
  "geometry": {"coordinates":[-5.7309541702,41.5072441101],"type":"Point"}
}