{
  "type": "Feature",
  "properties": {
    "addr:full":"Calle de Ferrandiz, 20 Malaga M\u00e1laga 29012",
    "addr:housenumber":"20",
    "addr:postcode":"29012",
    "addr:street":"Calle De Ferrandiz;Ma\u0301Laga",
    "iso:country":"ES",
    "sg:address":"Calle de Ferrandiz, 20",
    "sg:city":"Malaga",
    "sg:orig_category":"Loter\u00cda Y T\u00d3mbola",
    "sg:phone":"+34 952 26 48 31",
    "sg:postcode":"29012",
    "sg:province":"M\u00e1laga",
    "wof:name":"Sanchez Aguilera Maria Teresa",
    "wof:placetype":"venue"
},
  "geometry": {"coordinates":[-4.412197113,36.7271385193],"type":"Point"}
}