{
  "type": "Feature",
  "properties": {
    "addr:full":"Carrer de Manacor, 27 Palma Islas Baleares 07006",
    "addr:housenumber":"27",
    "addr:postcode":"07006",
    "addr:street":"Carrer De Manacor",
    "iso:country":"ES",
    "sg:address":"Carrer de Manacor, 27",
    "sg:city":"Palma",
    "sg:orig_category":"Restaurantes",
    "sg:phone":"+34 971 46 23 59",
    "sg:postcode":"07006",
    "sg:province":"Islas Baleares",
    "wof:name":"Restaurante Ca'n Nofre C.b.",
    "wof:placetype":"venue"
},
  "geometry": {"coordinates":[2.6595470905,39.5715904236],"type":"Point"}
}