{
  "type": "Feature",
  "properties": {
    "addr:full":"C/ Sant Antoni, 8 S. Antoni Calonge Girona 17252",
    "addr:housenumber":"8",
    "addr:postcode":"17252",
    "addr:street":"C / Sant Antoni",
    "iso:country":"ES",
    "sg:address":"C/ Sant Antoni, 8",
    "sg:city":"S. Antoni Calonge",
    "sg:orig_category":"Agencias Y Agentes Comerciales, Representantes",
    "sg:phone":"+34 972 65 13 29",
    "sg:postcode":"17252",
    "sg:province":"Girona",
    "wof:name":"Pablo Lizaur Beatriz",
    "wof:placetype":"venue"
},
  "geometry": {"coordinates":[3.1094601154,41.8569297791],"type":"Point"}
}