{
  "type": "Feature",
  "properties": {
    "iso:country":"ES",
    "sg:address":"Calle de Luz, 5",
    "sg:city":"Ciudad Real",
    "sg:orig_category":"Abogados",
    "sg:phone":"+34 926 25 22 25",
    "sg:postcode":"13003",
    "sg:province":"Ciudad Real",
    "wof:name":"Lucendo Carretero Manuel",
    "wof:placetype":"venue"
},
  "geometry": {"coordinates":[-3.9270560741,38.989402771],"type":"Point"}
}