{
  "type": "Feature",
  "properties": {
    "addr:full":"Calle de Karmen, 1 Amorebieta Vizcaya 48340",
    "addr:housenumber":"1",
    "addr:postcode":"48340",
    "addr:street":"Calle De Karmen",
    "iso:country":"ES",
    "sg:address":"Calle de Karmen, 1",
    "sg:city":"Amorebieta",
    "sg:orig_category":"Loter\u00cda Y T\u00d3mbola",
    "sg:phone":"+34 946 73 00 67",
    "sg:postcode":"48340",
    "sg:province":"Vizcaya",
    "wof:name":"Martin Jaureguibeitia Santiago",
    "wof:placetype":"venue"
},
  "geometry": {"coordinates":[-2.7330861092,43.2206115723],"type":"Point"}
}