{
  "type": "Feature",
  "properties": {
    "iso:country":"ES",
    "sg:address":"Calle de Jesus Del Perdon, 64",
    "sg:city":"Manzanares",
    "sg:orig_category":"Molduras, Junquillos, Listones Y Molduras Perforadas",
    "sg:phone":"+34 926 61 47 05",
    "sg:postcode":"13200",
    "sg:province":"Ciudad Real",
    "wof:name":"Lopez Callejas Vicente",
    "wof:placetype":"venue"
},
  "geometry": {"coordinates":[-3.3756277561,39.0005607605],"type":"Point"}
}