{
  "type": "Feature",
  "properties": {
    "iso:country":"ES",
    "sg:address":"Ctra Moron-pruna, Km. 0061,0",
    "sg:city":"Moron Frontera",
    "sg:orig_category":"Cr\u00cda De Bovinos",
    "sg:phone":"+34 955 95 73 49",
    "sg:postcode":"41530",
    "sg:province":"Sevilla",
    "wof:name":"Agreyra S.l.",
    "wof:placetype":"venue"
},
  "geometry": {"coordinates":[-5.1962108612,37.041721344],"type":"Point"}
}