{
  "type": "Feature",
  "properties": {
    "addr:full":"Avda Ricardo Carapeto Zambrano, 91 Badajoz Badajoz 06008",
    "addr:housenumber":"91",
    "addr:postcode":"06008",
    "addr:street":"Avda Ricardo Carapeto Zambrano",
    "iso:country":"ES",
    "sg:address":"Avda Ricardo Carapeto Zambrano, 91",
    "sg:city":"Badajoz",
    "sg:orig_category":"Comercio De Piezas De Recambio Y De Accesorios De Veh\u00cdculos, Veh\u00cdculos Industriales",
    "sg:phone":"+34 924 24 54 24",
    "sg:postcode":"06008",
    "sg:province":"Badajoz",
    "wof:name":"Tirado Mendoza Valentin",
    "wof:placetype":"venue"
},
  "geometry": {"coordinates":[-6.9506688118,38.8783416748],"type":"Point"}
}