{
  "type": "Feature",
  "properties": {
    "iso:country":"ES",
    "sg:address":"Calle de Pina, 6",
    "sg:city":"Puente Tocinos",
    "sg:orig_category":"Estudios, Instalaci\u00d3n De Climatizaci\u00d3n",
    "sg:phone":"+34 968 30 17 19",
    "sg:postcode":"30006",
    "sg:province":"Murcia",
    "wof:name":"Sotomayor Ortigosa Juan Antonio",
    "wof:placetype":"venue"
},
  "geometry": {"coordinates":[-1.1018440723,37.9959983826],"type":"Point"}
}