{
  "type": "Feature",
  "properties": {
    "iso:country":"ES",
    "sg:address":"Calle de Canillas, 5",
    "sg:city":"Madrid",
    "sg:orig_category":"Abogados",
    "sg:phone":"+34 915 64 16 55",
    "sg:postcode":"28002",
    "sg:province":"Madrid",
    "wof:name":"Ruiz Martin Enrique",
    "wof:placetype":"venue"
},
  "geometry": {"coordinates":[-3.6773729324,40.4405517578],"type":"Point"}
}