{
  "type": "Feature",
  "properties": {
    "iso:country":"ES",
    "sg:address":"Carrer de Mall, 13",
    "sg:city":"S. Feliu Guixols",
    "sg:orig_category":"Ropa Para Caballeros (al Por Menor)",
    "sg:phone":"+34 972 32 07 28",
    "sg:postcode":"17220",
    "sg:province":"Girona",
    "wof:name":"L'aula, Formacio I Serveis Integrals I A Distancia Sll",
    "wof:placetype":"venue"
},
  "geometry": {"coordinates":[3.0272989273,41.7821655273],"type":"Point"}
}