{
  "type": "Feature",
  "properties": {
    "addr:full":"Pol. Ind. Barrio Gonzalin, 1 Seana Asturias 33618",
    "addr:housenumber":"1",
    "addr:postcode":"33618",
    "addr:street":"Gonzalin;Asturias",
    "iso:country":"ES",
    "sg:address":"Pol. Ind. Barrio Gonzalin, 1",
    "sg:city":"Seana",
    "sg:orig_category":"Transportes Ferroviarios",
    "sg:phone":"+34 985 45 29 11",
    "sg:postcode":"33618",
    "sg:province":"Asturias",
    "wof:name":"Gonzalez Cardo Miguel Angel",
    "wof:placetype":"venue"
},
  "geometry": {"coordinates":[-5.7806081772,43.2410583496],"type":"Point"}
}