{
  "type": "Feature",
  "properties": {
    "iso:country":"ES",
    "sg:address":"Pol. Indus. Campana, S/n",
    "sg:city":"Nueva Andalucia",
    "sg:orig_category":"Mec\u00c1nico Del Autom\u00d3vil",
    "sg:phone":"+34 952 81 41 69",
    "sg:postcode":"29660",
    "sg:province":"M\u00e1laga",
    "wof:name":"Talleres Espada S.l.",
    "wof:placetype":"venue"
},
  "geometry": {"coordinates":[-4.9540901184,36.4891586304],"type":"Point"}
}