{
  "type": "Feature",
  "properties": {
    "addr:full":"Carrer de Cartagena, 273 Barcelona Barcelona 08025",
    "addr:housenumber":"273",
    "addr:postcode":"08025",
    "addr:street":"Carrer De Cartagena",
    "iso:country":"ES",
    "sg:address":"Carrer de Cartagena, 273",
    "sg:city":"Barcelona",
    "sg:orig_category":"Arquitectos",
    "sg:phone":"+34 934 33 17 38",
    "sg:postcode":"08025",
    "sg:province":"Barcelona",
    "wof:name":"I.d. Interiorismo S.l.",
    "wof:placetype":"venue"
},
  "geometry": {"coordinates":[2.1769220829,41.4090042114],"type":"Point"}
}