{
  "type": "Feature",
  "properties": {
    "addr:full":"Calle de Castellon, 35 Rozas De Madrid Madrid 28230",
    "addr:housenumber":"35",
    "addr:postcode":"28230",
    "addr:street":"Calle De Castellon",
    "iso:country":"ES",
    "sg:address":"Calle de Castellon, 35",
    "sg:city":"Rozas De Madrid",
    "sg:orig_category":"Fabricaci\u00d3n, Importaci\u00d3n De Material Y Sistemas De Telecomunicaciones",
    "sg:phone":"+34 916 38 24 26",
    "sg:postcode":"28230",
    "sg:province":"Madrid",
    "wof:name":"Cordoba Sanchez Jose Gabriel",
    "wof:placetype":"venue"
},
  "geometry": {"coordinates":[-3.8806619644,40.4864616394],"type":"Point"}
}