{
  "type": "Feature",
  "properties": {
    "addr:full":"Plaz Sancho Vii El Fuerte, 10 Tudela Navarra 31500",
    "addr:housenumber":"10",
    "addr:postcode":"31500",
    "addr:street":"Plaz;El Fuerte",
    "iso:country":"ES",
    "sg:address":"Plaz Sancho Vii El Fuerte, 10",
    "sg:city":"Tudela",
    "sg:orig_category":"Cl\u00cdnicas Dentales",
    "sg:phone":"+34 948 41 06 90",
    "sg:postcode":"31500",
    "sg:province":"Navarra",
    "wof:name":"Sachica Bernal Mario",
    "wof:placetype":"venue"
},
  "geometry": {"coordinates":[-1.6036169529,42.0611343384],"type":"Point"}
}