{
  "type": "Feature",
  "properties": {
    "iso:country":"ES",
    "sg:address":"Carr Cristofor Colom, 25",
    "sg:city":"Blanes",
    "sg:orig_category":"Discotecas Y Salas De Baile",
    "sg:phone":"+34 972 33 15 36",
    "sg:postcode":"17300",
    "sg:province":"Girona",
    "wof:name":"Heredia Avalo Sl",
    "wof:placetype":"venue"
},
  "geometry": {"coordinates":[2.7823491096,41.6652069092],"type":"Point"}
}