{
  "type": "Feature",
  "properties": {
    "addr:full":"Pase Virgen Del Puerto, 5 Madrid Madrid 28005",
    "addr:housenumber":"5",
    "addr:postcode":"28005",
    "iso:country":"ES",
    "sg:address":"Pase Virgen Del Puerto, 5",
    "sg:city":"Madrid",
    "sg:orig_category":"Peritos Diversos",
    "sg:phone":"+34 913 65 47 19",
    "sg:postcode":"28005",
    "sg:province":"Madrid",
    "wof:name":"Lorenzo Mac Lean Manuel",
    "wof:placetype":"venue"
},
  "geometry": {"coordinates":[-3.7208719254,40.4135055542],"type":"Point"}
}