{
  "type": "Feature",
  "properties": {
    "iso:country":"ES",
    "sg:address":"Rua Coru\u00d1a, 1",
    "sg:city":"Vigo",
    "sg:orig_category":"Congelados: Productos Alimentarios (al Por Menor)",
    "sg:phone":"+34 986 29 26 99",
    "sg:postcode":"36208",
    "sg:province":"Pontevedra",
    "wof:name":"Hiper Xel S. L.",
    "wof:placetype":"venue"
},
  "geometry": {"coordinates":[-8.7332515717,42.221031189],"type":"Point"}
}