{
  "type": "Feature",
  "properties": {
    "addr:full":"Calle de Pizarro, 16 Madrid Madrid 28004",
    "addr:housenumber":"16",
    "addr:postcode":"madrid;28004",
    "addr:street":"Calle De Pizarro",
    "iso:country":"ES",
    "sg:address":"Calle de Pizarro, 16",
    "sg:city":"Madrid",
    "sg:orig_category":"Aparcamientos (infraestructuras, Accesorios)",
    "sg:phone":"+34 915 21 88 75",
    "sg:postcode":"28004",
    "sg:province":"Madrid",
    "wof:name":"Gestion Patrimonio Peinado S.l.",
    "wof:placetype":"venue"
},
  "geometry": {"coordinates":[-3.7056620121,40.4231643677],"type":"Point"}
}