{
  "type": "Feature",
  "properties": {
    "addr:full":"Bo Billela, 18 Billela Vizcaya 48100",
    "addr:housenumber":"18",
    "addr:postcode":"48100",
    "addr:street":"Billela",
    "iso:country":"ES",
    "sg:address":"Bo Billela, 18",
    "sg:city":"Billela",
    "sg:orig_category":"Caf\u00c9s, Bares, Cervecer\u00cdas",
    "sg:phone":"+34 946 74 42 65",
    "sg:postcode":"48100",
    "sg:province":"Vizcaya",
    "wof:name":"Aranda Cano Francisco Javier",
    "wof:placetype":"venue"
},
  "geometry": {"coordinates":[-2.8568511009,43.3709068298],"type":"Point"}
}