{
  "type": "Feature",
  "properties": {
    "iso:country":"ES",
    "sg:address":"Avda Ciudad De Barcelona, 9",
    "sg:city":"Madrid",
    "sg:orig_category":"Abogados",
    "sg:phone":"+34 915 52 46 69",
    "sg:postcode":"28007",
    "sg:province":"Madrid",
    "wof:name":"Bayona Beriso Sofia",
    "wof:placetype":"venue"
},
  "geometry": {"coordinates":[-3.6823530197,40.4049186707],"type":"Point"}
}