{
  "type": "Feature",
  "properties": {
    "addr:full":"Carrer de Joan Obiols, 15 Barcelona Barcelona 08034",
    "addr:housenumber":"15",
    "addr:postcode":"08034",
    "addr:street":"Carrer De Joan Obiols",
    "iso:country":"ES",
    "sg:address":"Carrer de Joan Obiols, 15",
    "sg:city":"Barcelona",
    "sg:orig_category":"Inmobiliaria (agencias)",
    "sg:phone":"+34 932 80 16 42",
    "sg:postcode":"08034",
    "sg:province":"Barcelona",
    "wof:name":"Cearch Asesores Inmobiliarios S.l:",
    "wof:placetype":"venue"
},
  "geometry": {"coordinates":[2.1139519215,41.3873100281],"type":"Point"}
}