{
  "type": "Feature",
  "properties": {
    "iso:country":"ES",
    "sg:address":"Carrer de Balmes, 245",
    "sg:city":"Barcelona",
    "sg:orig_category":"Agencias De Viajes",
    "sg:phone":"+34 932 18 08 56",
    "sg:postcode":"08006",
    "sg:province":"Barcelona",
    "wof:name":"Savia Amadeus S.a.",
    "wof:placetype":"venue"
},
  "geometry": {"coordinates":[2.149586916,41.3996505737],"type":"Point"}
}