{
  "type": "Feature",
  "properties": {
    "iso:country":"ES",
    "sg:address":"Carrer de Narcis Giralt, 3",
    "sg:city":"Sabadell",
    "sg:orig_category":"Inversiones",
    "sg:phone":"+34 937 47 85 12",
    "sg:postcode":"08202",
    "sg:province":"Barcelona",
    "wof:name":"Inversions Familiars Arrahona S.l.",
    "wof:placetype":"venue"
},
  "geometry": {"coordinates":[2.1101629734,41.5467185974],"type":"Point"}
}