{
  "type": "Feature",
  "properties": {
    "iso:country":"ES",
    "sg:address":"Pl Emili Sala, 1",
    "sg:city":"Alcoi",
    "sg:orig_category":"Asesor\u00cda Sobre Comunicaci\u00d3n De Empresas",
    "sg:phone":"+34 965 54 16 66",
    "sg:postcode":"03801",
    "sg:province":"Alicante",
    "wof:name":"Centro De Empresas E Innovacion De Alcoy",
    "wof:placetype":"venue"
},
  "geometry": {"coordinates":[-0.4769090116,38.6973648071],"type":"Point"}
}