{
  "type": "Feature",
  "properties": {
    "addr:full":"Carrer de Manuel Sancho, 3 Barcelona Barcelona 08016",
    "addr:housenumber":"3",
    "addr:postcode":"08016",
    "addr:street":"Carrer De Manuel Sancho",
    "iso:country":"ES",
    "sg:address":"Carrer de Manuel Sancho, 3",
    "sg:city":"Barcelona",
    "sg:orig_category":"Disfraces",
    "sg:phone":"+34 933 52 72 81",
    "sg:postcode":"08016",
    "sg:province":"Barcelona",
    "wof:name":"Sanz Gonzalez Iris",
    "wof:placetype":"venue"
},
  "geometry": {"coordinates":[2.1815829277,41.4304542542],"type":"Point"}
}