{
  "type": "Feature",
  "properties": {
    "iso:country":"ES",
    "sg:address":"Avda Luis Chamizo, 4",
    "sg:city":"Entrin Bajo",
    "sg:orig_category":"Cr\u00cda De Animales",
    "sg:phone":"+34 924 48 10 80",
    "sg:postcode":"06197",
    "sg:province":"Badajoz",
    "wof:name":"Sociedad Agraria De Transformacion Caballo Alto",
    "wof:placetype":"venue"
},
  "geometry": {"coordinates":[-6.7136030197,38.7172775269],"type":"Point"}
}