{
  "type": "Feature",
  "properties": {
    "addr:full":"Carrer de Vic, 19 Barcelona Barcelona 08006",
    "addr:housenumber":"19",
    "addr:postcode":"08006",
    "addr:street":"Carrer De Vic",
    "iso:country":"ES",
    "sg:address":"Carrer de Vic, 19",
    "sg:city":"Barcelona",
    "sg:orig_category":"Caf\u00c9s, Bares, Cervecer\u00cdas",
    "sg:phone":"+34 934 15 29 56",
    "sg:postcode":"08006",
    "sg:province":"Barcelona",
    "wof:name":"Duacastilla Soler Sandra",
    "wof:placetype":"venue"
},
  "geometry": {"coordinates":[2.1547589302,41.398979187],"type":"Point"}
}