{
  "type": "Feature",
  "properties": {
    "addr:full":"Carrer de Albinyana, 6 Terrassa Barcelona 08223",
    "addr:housenumber":"6",
    "addr:postcode":"08223",
    "addr:street":"Carrer De Albinyana",
    "iso:country":"ES",
    "sg:address":"Carrer de Albinyana, 6",
    "sg:city":"Terrassa",
    "sg:classifiers":[
        {
            "category":"Personal",
            "subcategory":"Barber",
            "type":"Services"
        }
    ],
    "sg:phone":"+34 937 83 71 87",
    "sg:postcode":"08223",
    "sg:province":"Barcelona",
    "sg:tags":[
        "caballeros",
        "de",
        "peluqueros"
    ],
    "wof:name":"Rodelas Guerrero David",
    "wof:placetype":"venue"
},
  "geometry": {"coordinates":[2.0215070248,41.5558013916],"type":"Point"}
}