{
  "type": "Feature",
  "properties": {
    "iso:country":"ES",
    "sg:address":"Ctra Calatayud, S/n",
    "sg:city":"Villalba De Perejil",
    "sg:orig_category":"Empresas De Carpinter\u00cda De Madera",
    "sg:phone":"+34 976 89 27 26",
    "sg:postcode":"50333",
    "sg:province":"Zaragoza",
    "wof:name":"Condon Gormaz Eduardo",
    "wof:placetype":"venue"
},
  "geometry": {"coordinates":[-1.5496640205,41.3286781311],"type":"Point"}
}