{
  "type": "Feature",
  "properties": {
    "addr:full":"Calle de Arrabal (liesa), S/n Liesa Huesca 22122",
    "addr:housenumber":"s / n",
    "addr:postcode":"22122",
    "addr:street":"Calle De Arrabal Liesa",
    "iso:country":"ES",
    "sg:address":"Calle de Arrabal (liesa), S/n",
    "sg:city":"Liesa",
    "sg:orig_category":"Agricultores, Agricultores",
    "sg:phone":"+34 974 26 04 89",
    "sg:postcode":"22122",
    "sg:province":"Huesca",
    "wof:name":"Hermanos Burgase S.l.",
    "wof:placetype":"venue"
},
  "geometry": {"coordinates":[-0.2200948,42.1368598938],"type":"Point"}
}