{
  "type": "Feature",
  "properties": {
    "addr:full":"Ctra Ledesma, 91 Salamanca Salamanca 37006",
    "addr:housenumber":"91",
    "addr:postcode":"37006",
    "addr:street":"Ctra Ledesma",
    "iso:country":"ES",
    "sg:address":"Ctra Ledesma, 91",
    "sg:city":"Salamanca",
    "sg:orig_category":"\u00d3ptica: Instrumentos (fabricaci\u00d3n)",
    "sg:phone":"+34 923 12 35 66",
    "sg:postcode":"37006",
    "sg:province":"Salamanca",
    "sg:website":"www.nuevavision.net",
    "wof:name":"Nueva Vision 2002 S.l.",
    "wof:placetype":"venue"
},
  "geometry": {"coordinates":[-5.6762280464,40.9775543213],"type":"Point"}
}