{
  "type": "Feature",
  "properties": {
    "iso:country":"ES",
    "sg:address":"Calle de Palomar, 3",
    "sg:city":"Villalba Alcor",
    "sg:orig_category":"Negocio De Materiales De Construcci\u00d3n",
    "sg:phone":"+34 959 42 12 28",
    "sg:postcode":"21860",
    "sg:province":"Huelva",
    "wof:name":"Garcia Fernandez Juan",
    "wof:placetype":"venue"
},
  "geometry": {"coordinates":[-6.4749450684,37.3978233337],"type":"Point"}
}