{
  "type": "Feature",
  "properties": {
    "iso:country":"ES",
    "sg:address":"Carr Enric Granados, 78",
    "sg:city":"Alpicat",
    "sg:orig_category":"Empresas De Carpinter\u00cda De Madera",
    "sg:phone":"+34 973 73 60 82",
    "sg:postcode":"25110",
    "sg:province":"Lleida",
    "wof:name":"Jostore S.l.",
    "wof:placetype":"venue"
},
  "geometry": {"coordinates":[0.5569967031,41.6664237976],"type":"Point"}
}