{
  "type": "Feature",
  "properties": {
    "iso:country":"ES",
    "sg:address":"Carrer de Francesc Macia, 18",
    "sg:city":"S. Boi Llobregat",
    "sg:orig_category":"Art\u00cdculos De Regalo (al Por Menor)",
    "sg:phone":"+34 936 30 94 34",
    "sg:postcode":"08830",
    "sg:province":"Barcelona",
    "wof:name":"Splash St. Boi S.l,",
    "wof:placetype":"venue"
},
  "geometry": {"coordinates":[2.0403308868,41.3427238464],"type":"Point"}
}