{
  "type": "Feature",
  "properties": {
    "iso:country":"ES",
    "sg:address":"Carrer de Sol I Padris, 36",
    "sg:city":"Sabadell",
    "sg:classifiers":[
        {
            "category":"Autos & Motor Vehicles",
            "subcategory":"Automobile Sales",
            "type":"Retail Goods"
        }
    ],
    "sg:phone":"+34 937 25 61 06",
    "sg:postcode":"08203",
    "sg:province":"Barcelona",
    "wof:name":"Sanchez Celma Luis",
    "wof:placetype":"venue"
},
  "geometry": {"coordinates":[2.117650032,41.5395698547],"type":"Point"}
}