{
  "type": "Feature",
  "properties": {
    "iso:country":"ES",
    "sg:address":"Calle de Roble (del), 13",
    "sg:city":"Segovia",
    "sg:orig_category":"Peluqueros: De Se\u00d1oras",
    "sg:phone":"+34 921 42 09 28",
    "sg:postcode":"40002",
    "sg:province":"Segovia",
    "wof:name":"Casado Sastre Paloma",
    "wof:placetype":"venue"
},
  "geometry": {"coordinates":[-4.1182022095,40.9441986084],"type":"Point"}
}