{
  "type": "Feature",
  "properties": {
    "iso:country":"ES",
    "sg:address":"Rua Pizarro, 29",
    "sg:city":"Vigo",
    "sg:orig_category":"Molduras, Junquillos, Listones Y Molduras Perforadas",
    "sg:phone":"+34 986 41 51 67",
    "sg:postcode":"36204",
    "sg:province":"Pontevedra",
    "wof:name":"Gonzalez Gonzalez Manuel",
    "wof:placetype":"venue"
},
  "geometry": {"coordinates":[-8.715423584,42.2306747437],"type":"Point"}
}