{
  "type": "Feature",
  "properties": {
    "iso:country":"ES",
    "sg:address":"Calle de Postigo Bajo, 48",
    "sg:city":"Oviedo",
    "sg:orig_category":"Asociaciones Humanitarias, De Cooperaci\u00d3n, De Acci\u00d3n Social",
    "sg:phone":"+34 985 20 55 00",
    "sg:postcode":"33009",
    "sg:province":"Asturias",
    "wof:name":"Asociacion De Familias Y Amigos Proyecto Hombre",
    "wof:placetype":"venue"
},
  "geometry": {"coordinates":[-5.8395552635,43.3625450134],"type":"Point"}
}