{
  "type": "Feature",
  "properties": {
    "iso:country":"ES",
    "sg:address":"Ptda Cachapet, S/n",
    "sg:city":"Crevillente",
    "sg:orig_category":"Hilaturas, Hilos Y Actividades Relacionadas",
    "sg:phone":"+34 966 68 04 55",
    "sg:postcode":"03330",
    "sg:province":"Alicante",
    "wof:name":"Yute Distribucion S.l.",
    "wof:placetype":"venue"
},
  "geometry": {"coordinates":[-0.8079771996,38.2478981018],"type":"Point"}
}