{
  "type": "Feature",
  "properties": {
    "addr:full":"Carrer de Llata (de La), S/n Pedreguer Alicante 03750",
    "addr:postcode":"03750",
    "addr:street":"Carrer De Llata De La S / N",
    "iso:country":"ES",
    "sg:address":"Carrer de Llata (de La), S/n",
    "sg:city":"Pedreguer",
    "sg:orig_category":"Delegados, Agentes De Tr\u00c1nsito, Auxiliares De Transporte Internacional",
    "sg:phone":"+34 965 76 16 98",
    "sg:postcode":"03750",
    "sg:province":"Alicante",
    "wof:name":"Transportes Garcia Costa S.l.",
    "wof:placetype":"venue"
},
  "geometry": {"coordinates":[0.0424799994,38.8002548218],"type":"Point"}
}