{
  "type": "Feature",
  "properties": {
    "iso:country":"ES",
    "sg:address":"Calle de Merced, 11",
    "sg:city":"Calasparra",
    "sg:orig_category":"Peluqueros: De Se\u00d1oras",
    "sg:phone":"+34 968 72 05 92",
    "sg:postcode":"30420",
    "sg:province":"Murcia",
    "wof:name":"Villena Alvarez Victoria",
    "wof:placetype":"venue"
},
  "geometry": {"coordinates":[-1.7006349564,38.2302894592],"type":"Point"}
}