{
  "type": "Feature",
  "properties": {
    "addr:full":"Calle de Rosario Pino, 16 Madrid Madrid 28020",
    "addr:housenumber":"16",
    "addr:postcode":"madrid;28020",
    "addr:street":"Calle De Rosario Pino",
    "iso:country":"ES",
    "sg:address":"Calle de Rosario Pino, 16",
    "sg:city":"Madrid",
    "sg:orig_category":"Inmobiliaria (agencias)",
    "sg:phone":"+34 915 71 06 75",
    "sg:postcode":"28020",
    "sg:province":"Madrid",
    "wof:name":"Torre Rioja-madrid S.a.",
    "wof:placetype":"venue"
},
  "geometry": {"coordinates":[-3.6930179596,40.4623031616],"type":"Point"}
}