{
  "type": "Feature",
  "properties": {
    "iso:country":"ES",
    "sg:address":"Calle de Prim, 40",
    "sg:city":"Linea De La Concepcion",
    "sg:orig_category":"M\u00c1rmoles, Granitos Y Piedras Naturales",
    "sg:phone":"+34 956 17 49 22",
    "sg:postcode":"11300",
    "sg:province":"C\u00e1diz",
    "wof:name":"Rodriguez Granado Francisco",
    "wof:placetype":"venue"
},
  "geometry": {"coordinates":[-5.3501849174,36.1719818115],"type":"Point"}
}