{
  "type": "Feature",
  "properties": {
    "addr:full":"Carrer de Andreu De Bofarull, S/n Reus Tarragona 43205",
    "addr:housenumber":"s / n",
    "addr:postcode":"43205",
    "addr:street":"Carrer De Andreu De Bofarull",
    "iso:country":"ES",
    "sg:address":"Carrer de Andreu De Bofarull, S/n",
    "sg:city":"Reus",
    "sg:orig_category":"Peluquer\u00cdas, Peluquer\u00cda Mixta",
    "sg:phone":"+34 977 31 71 98",
    "sg:postcode":"43205",
    "sg:province":"Tarragona",
    "wof:name":"Berzosa Martinez Antonio",
    "wof:placetype":"venue"
},
  "geometry": {"coordinates":[1.1058750153,41.1508903503],"type":"Point"}
}