{
  "type": "Feature",
  "properties": {
    "addr:full":"Calle de Jorge Juan, 163 Madrid Madrid 28028",
    "addr:housenumber":"163",
    "addr:postcode":"28028",
    "addr:street":"Calle De Jorge Juan",
    "iso:country":"ES",
    "sg:address":"Calle de Jorge Juan, 163",
    "sg:city":"Madrid",
    "sg:orig_category":"Internados & Ense\u00d1anza Privada",
    "sg:phone":"+34 913 55 90 02",
    "sg:postcode":"28028",
    "sg:province":"Madrid",
    "wof:name":"Colegio Sagrada Familia En Cl Jorge Juan 165 Caridad Del Sgdo Coraz",
    "wof:placetype":"venue"
},
  "geometry": {"coordinates":[-3.6651880741,40.4228668213],"type":"Point"}
}