{
  "type": "Feature",
  "properties": {
    "iso:country":"ES",
    "sg:address":"Ctra Cubla, S/n",
    "sg:city":"Villaspesa",
    "sg:orig_category":"Venta De Caravanas, Casas M\u00d3viles, Camping",
    "sg:phone":"+34 978 60 82 07",
    "sg:postcode":"44190",
    "sg:province":"Teruel",
    "wof:name":"Gomez Perez Antonio",
    "wof:placetype":"venue"
},
  "geometry": {"coordinates":[-1.1260390282,40.2955207825],"type":"Point"}
}