{
  "type": "Feature",
  "properties": {
    "iso:country":"ES",
    "sg:address":"Bo. Estacion, S/n",
    "sg:city":"Etxarri-aranatz",
    "sg:orig_category":"Muebles, Minoristas",
    "sg:phone":"+34 948 46 00 21",
    "sg:postcode":"31820",
    "sg:province":"Navarra",
    "wof:name":"Comerial Etxarri S.a.",
    "wof:placetype":"venue"
},
  "geometry": {"coordinates":[-2.0638840199,42.9061965942],"type":"Point"}
}