{
  "type": "Feature",
  "properties": {
    "addr:full":"Avda Fernandez Ladreda, 16 Le\u00f3n Le\u00f3n 24005",
    "addr:housenumber":"16",
    "addr:postcode":"24005",
    "addr:street":"Avda Fernandez Ladreda;Leo\u0301N",
    "iso:country":"ES",
    "sg:address":"Avda Fernandez Ladreda, 16",
    "sg:city":"Le\u00f3n",
    "sg:orig_category":"Arquitectos",
    "sg:phone":"+34 987 26 22 40",
    "sg:postcode":"24005",
    "sg:province":"Le\u00f3n",
    "wof:name":"Fernandez Carnerero Santiago",
    "wof:placetype":"venue"
},
  "geometry": {"coordinates":[-5.5632157326,42.587223053],"type":"Point"}
}