{
  "type": "Feature",
  "properties": {
    "addr:full":"O Pazo, 7 Nigoi Pontevedra 36684",
    "addr:housenumber":"7",
    "addr:postcode":"36684",
    "addr:street":"Nigoi Pontevedra",
    "iso:country":"ES",
    "sg:address":"O Pazo, 7",
    "sg:city":"Nigoi",
    "sg:orig_category":"Alquiler De Casas Y Habitaciones Amuebladas",
    "sg:phone":"+34 986 57 32 53",
    "sg:postcode":"36684",
    "sg:province":"Pontevedra",
    "wof:name":"Pazo Nigoi S.l.",
    "wof:placetype":"venue"
},
  "geometry": {"coordinates":[-8.4635591507,42.6137084961],"type":"Point"}
}