{
  "type": "Feature",
  "properties": {
    "addr:full":"Calle de San Jose De Calasanz, 7 Rubio Sevilla 41568",
    "addr:housenumber":"7",
    "addr:postcode":"41568",
    "addr:street":"Calle De San;De Calasanz",
    "iso:country":"ES",
    "sg:address":"Calle de San Jose De Calasanz, 7",
    "sg:city":"Rubio",
    "sg:orig_category":"Droguer\u00cdas (al Por Menor)",
    "sg:phone":"+34 955 82 88 93",
    "sg:postcode":"41568",
    "sg:province":"Sevilla",
    "wof:name":"Paez Perez Consuelo",
    "wof:placetype":"venue"
},
  "geometry": {"coordinates":[-4.9920988083,37.3519897461],"type":"Point"}
}