{
  "type": "Feature",
  "properties": {
    "addr:full":"Calle de Real, 14 Torrelodones Madrid 28250",
    "addr:housenumber":"14",
    "addr:postcode":"28250",
    "addr:street":"Calle De Real",
    "iso:country":"ES",
    "sg:address":"Calle de Real, 14",
    "sg:city":"Torrelodones",
    "sg:orig_category":"Herboristas (al Por Menor)",
    "sg:phone":"+34 918 59 54 96",
    "sg:postcode":"28250",
    "sg:province":"Madrid",
    "wof:name":"Sanfrutos Arroyo Julia",
    "wof:placetype":"venue"
},
  "geometry": {"coordinates":[-3.927957058,40.5754699707],"type":"Point"}
}