{
  "type": "Feature",
  "properties": {
    "iso:country":"ES",
    "sg:address":"Calle de Maestro Alonso, 24",
    "sg:city":"Madrid",
    "sg:orig_category":"Estudios, Instalaci\u00d3n De Climatizaci\u00d3n",
    "sg:phone":"+34 917 25 18 02",
    "sg:postcode":"28028",
    "sg:province":"Madrid",
    "wof:name":"Insserco S. A.",
    "wof:placetype":"venue"
},
  "geometry": {"coordinates":[-3.6637680531,40.4271392822],"type":"Point"}
}