{
  "type": "Feature",
  "properties": {
    "iso:country":"ES",
    "sg:address":"Calle de Buendia, 12",
    "sg:city":"Marchena",
    "sg:orig_category":"Alimentaci\u00d3n General (al Por Menor)",
    "sg:phone":"+34 954 84 40 56",
    "sg:postcode":"41620",
    "sg:province":"Sevilla",
    "wof:name":"Carrillo Lebron Antonio",
    "wof:placetype":"venue"
},
  "geometry": {"coordinates":[-5.4199151993,37.3295516968],"type":"Point"}
}