{
  "type": "Feature",
  "properties": {
    "iso:country":"ES",
    "sg:address":"Carrer de Gaiter Del Llobregat (lo), 133",
    "sg:city":"Prat Llobregat",
    "sg:orig_category":"Publicidad (soportes Y Gesti\u00d3n)",
    "sg:phone":"+34 934 78 64 49",
    "sg:postcode":"08820",
    "sg:province":"Barcelona",
    "sg:website":"www.creacionesolimpia.es",
    "wof:name":"Creaciones Olimpia S.a.",
    "wof:placetype":"venue"
},
  "geometry": {"coordinates":[2.1029961109,41.3317985535],"type":"Point"}
}