{
  "type": "Feature",
  "properties": {
    "addr:full":"Pg Zona Franca, 157 Barcelona Barcelona 08038",
    "addr:housenumber":"157",
    "addr:postcode":"08038",
    "addr:street":"Pg Zona Franca",
    "iso:country":"ES",
    "sg:address":"Pg Zona Franca, 157",
    "sg:city":"Barcelona",
    "sg:orig_category":"Agencias De Trabajo Temporal",
    "sg:phone":"+34 932 98 16 50",
    "sg:postcode":"08038",
    "sg:province":"Barcelona",
    "sg:website":"www.adecco.es",
    "wof:name":"Adecco E.t.t. S.a.",
    "wof:placetype":"venue"
},
  "geometry": {"coordinates":[2.1390166283,41.3600120544],"type":"Point"}
}