{
  "type": "Feature",
  "properties": {
    "addr:full":"O Pazo, S/n Pazo Pontevedra 36446",
    "addr:housenumber":"s / n",
    "addr:postcode":"36446",
    "iso:country":"ES",
    "sg:address":"O Pazo, S/n",
    "sg:city":"Pazo",
    "sg:orig_category":"Arenas, Guijarros Y Granulados",
    "sg:phone":"+34 986 69 76 74",
    "sg:postcode":"36446",
    "sg:province":"Pontevedra",
    "wof:name":"Minas Del Condado S.l.",
    "wof:placetype":"venue"
},
  "geometry": {"coordinates":[-8.3823709488,42.10987854],"type":"Point"}
}