{
  "type": "Feature",
  "properties": {
    "addr:full":"Calle de Mayor, 26 Mondejar Guadalajara 19110",
    "addr:housenumber":"26",
    "addr:postcode":"19110",
    "addr:street":"Calle De Mayor",
    "iso:country":"ES",
    "sg:address":"Calle de Mayor, 26",
    "sg:city":"Mondejar",
    "sg:orig_category":"Reposter\u00cdas",
    "sg:phone":"+34 949 38 50 18",
    "sg:postcode":"19110",
    "sg:province":"Guadalajara",
    "wof:name":"Olivares Jimenez Inocente",
    "wof:placetype":"venue"
},
  "geometry": {"coordinates":[-3.1081669331,40.323261261],"type":"Point"}
}