{
  "type": "Feature",
  "properties": {
    "iso:country":"ES",
    "sg:address":"Calle de Xativa, 18",
    "sg:city":"Valencia",
    "sg:orig_category":"Panader\u00cdas, Panader\u00cdas",
    "sg:phone":"+34 963 51 08 09",
    "sg:postcode":"46002",
    "sg:province":"Valencia",
    "wof:name":"Martin Maicas Francisca",
    "wof:placetype":"venue"
},
  "geometry": {"coordinates":[-0.3781389892,39.4677581787],"type":"Point"}
}