{
  "type": "Feature",
  "properties": {
    "addr:full":"Calle de Ramon Y Cajal, 12 Teruel Teruel 44001",
    "addr:housenumber":"12",
    "addr:postcode":"44001",
    "addr:street":"Calle De Ramon Y Cajal",
    "iso:country":"ES",
    "sg:address":"Calle de Ramon Y Cajal, 12",
    "sg:city":"Teruel",
    "sg:orig_category":"Arquitectos",
    "sg:phone":"+34 978 60 18 43",
    "sg:postcode":"44001",
    "sg:province":"Teruel",
    "wof:name":"Andres Galindo Antonio",
    "wof:placetype":"venue"
},
  "geometry": {"coordinates":[-1.1072949171,40.3418083191],"type":"Point"}
}