{
  "type": "Feature",
  "properties": {
    "iso:country":"ES",
    "sg:address":"Urb. Tamaide, 9",
    "sg:city":"Costa Del Silencio",
    "sg:orig_category":"Delegados, Agentes De Tr\u00c1nsito, Auxiliares De Transporte Internacional",
    "sg:phone":"+34 922 73 28 89",
    "sg:postcode":"38630",
    "sg:province":"Santa Cruz De Tenerife",
    "wof:name":"Sierra Dominguez Ramiro Jose Antonio",
    "wof:placetype":"venue"
},
  "geometry": {"coordinates":[-16.6466293335,28.0117092133],"type":"Point"}
}