{
  "type": "Feature",
  "properties": {
    "iso:country":"ES",
    "sg:address":"Av Meridiana, 384",
    "sg:city":"Barcelona",
    "sg:orig_category":"Fabricaci\u00d3n De Muebles",
    "sg:phone":"+34 933 11 72 52",
    "sg:postcode":"08030",
    "sg:province":"Barcelona",
    "wof:name":"Lujan Cazalilla Javier",
    "wof:placetype":"venue"
},
  "geometry": {"coordinates":[2.1836290359,41.4297218323],"type":"Point"}
}