{
  "type": "Feature",
  "properties": {
    "iso:country":"ES",
    "sg:address":"Avda Union Murense, 12",
    "sg:city":"Muras",
    "sg:orig_category":"Doctores En Medicina",
    "sg:phone":"+34 982 50 00 75",
    "sg:postcode":"27836",
    "sg:province":"Lugo",
    "wof:name":"Lopez Diaz Tarsila",
    "wof:placetype":"venue"
},
  "geometry": {"coordinates":[-7.7227787971,43.466835022],"type":"Point"}
}