{
  "type": "Feature",
  "properties": {
    "iso:country":"ES",
    "sg:address":"Carr Sant Pere, 1",
    "sg:city":"Figueres",
    "sg:orig_category":"Museos",
    "sg:phone":"+34 972 50 45 85",
    "sg:postcode":"17600",
    "sg:province":"Girona",
    "wof:name":"Fundacio Museu Del Joguet",
    "wof:placetype":"venue"
},
  "geometry": {"coordinates":[2.9607069492,42.2667121887],"type":"Point"}
}