{
  "type": "Feature",
  "properties": {
    "addr:full":"Calle de Alferez Baanante, S/n Chantada Lugo 27500",
    "addr:housenumber":"s",
    "addr:postcode":"27500",
    "addr:street":"Calle De Alferez Baanante;/ N",
    "iso:country":"ES",
    "sg:address":"Calle de Alferez Baanante, S/n",
    "sg:city":"Chantada",
    "sg:orig_category":"Ense\u00d1anza Secundaria: Colegios Y Escuelas Privadas",
    "sg:phone":"+34 982 44 05 51",
    "sg:postcode":"27500",
    "sg:province":"Lugo",
    "wof:name":"Instituto Lama Das Quendas",
    "wof:placetype":"venue"
},
  "geometry": {"coordinates":[-7.7960119247,42.6083450317],"type":"Point"}
}