{
  "type": "Feature",
  "properties": {
    "iso:country":"ES",
    "sg:address":"Cmno Camaras (las), 9",
    "sg:city":"Mojonera",
    "sg:orig_category":"Semiller\u00cdas",
    "sg:phone":"+34 950 33 04 86",
    "sg:postcode":"04745",
    "sg:province":"Almer\u00eda",
    "wof:name":"Viveros Gonzalvez S.l.",
    "wof:placetype":"venue"
},
  "geometry": {"coordinates":[-2.6919989586,36.80235672],"type":"Point"}
}