{
  "type": "Feature",
  "properties": {
    "iso:country":"ES",
    "sg:address":"Calle de Gran Capitan, 14",
    "sg:city":"Gijon",
    "sg:orig_category":"Ropa Y Accesorios",
    "sg:phone":"+34 985 32 26 59",
    "sg:postcode":"33213",
    "sg:province":"Asturias",
    "wof:name":"Armesto Alvarez Jose Antonio",
    "wof:placetype":"venue"
},
  "geometry": {"coordinates":[-5.7024469376,43.5398368835],"type":"Point"}
}