{
  "type": "Feature",
  "properties": {
    "iso:country":"ES",
    "sg:address":"Calle de Do\u00d1ana (de), 36",
    "sg:city":"Humanes De Madrid",
    "sg:orig_category":"Panader\u00cdas, Pasteler\u00cdas, Boller\u00cda Industriale (fabricaci\u00d3n, Al Por Mayor)",
    "sg:phone":"+34 916 97 29 63",
    "sg:postcode":"28970",
    "sg:province":"Madrid",
    "wof:name":"Hermaja S.l.",
    "wof:placetype":"venue"
},
  "geometry": {"coordinates":[-3.8182508945,40.2699584961],"type":"Point"}
}