{
  "type": "Feature",
  "properties": {
    "iso:country":"ES",
    "sg:address":"Calle de Real, S/n",
    "sg:city":"Sancedo",
    "sg:orig_category":"Empresarios",
    "sg:phone":"+34 987 56 53 35",
    "sg:postcode":"24439",
    "sg:province":"Le\u00f3n",
    "wof:name":"Gonzalez Gonzalez Pedro Jesus",
    "wof:placetype":"venue"
},
  "geometry": {"coordinates":[-6.6401791573,42.6618118286],"type":"Point"}
}