{
  "type": "Feature",
  "properties": {
    "addr:full":"Calle de Virgen Del Rosario, 26 Pobla Vallbona Valencia 46185",
    "addr:housenumber":"26",
    "addr:postcode":"46185",
    "addr:street":"Calle De Virgen Del Rosario",
    "iso:country":"ES",
    "sg:address":"Calle de Virgen Del Rosario, 26",
    "sg:city":"Pobla Vallbona",
    "sg:orig_category":"Peluqueros: De Se\u00d1oras",
    "sg:phone":"+34 961 66 24 28",
    "sg:postcode":"46185",
    "sg:province":"Valencia",
    "wof:name":"Medollos S.l.",
    "wof:placetype":"venue"
},
  "geometry": {"coordinates":[-0.5513759851,39.5933303833],"type":"Point"}
}