{
  "type": "Feature",
  "properties": {
    "iso:country":"ES",
    "sg:address":"Calle de Codornices (de Las), 10",
    "sg:city":"Jardin De Serracines",
    "sg:orig_category":"Desinfecci\u00d3n, Desinsectaci\u00d3n, Desratizaci\u00d3n",
    "sg:phone":"+34 918 79 16 91",
    "sg:postcode":"28815",
    "sg:province":"Madrid",
    "wof:name":"Deslim Siglo Xxi S.l.",
    "wof:placetype":"venue"
},
  "geometry": {"coordinates":[-3.4000759125,40.6362800598],"type":"Point"}
}