{
  "type": "Feature",
  "properties": {
    "iso:country":"ES",
    "sg:address":"Calle de Alonso Castrillo, 29",
    "sg:city":"Valencia De Don Juan",
    "sg:orig_category":"Productores Recolectores, Venta Directa De Vinos",
    "sg:phone":"+34 987 75 10 89",
    "sg:postcode":"24200",
    "sg:province":"Le\u00f3n",
    "wof:name":"Aso.vinos Tierra Valdevimbre Los Oteros",
    "wof:placetype":"venue"
},
  "geometry": {"coordinates":[-5.5164175034,42.2932167053],"type":"Point"}
}