{
  "type": "Feature",
  "properties": {
    "addr:full":"Calle de Reyes Catolicos, S/n Madro\u00f1era C\u00e1ceres 10210",
    "addr:housenumber":"s / n",
    "addr:postcode":"10210",
    "addr:street":"Calle De Reyes Catolicos;Ca\u0301Ceres",
    "iso:country":"ES",
    "sg:address":"Calle de Reyes Catolicos, S/n",
    "sg:city":"Madro\u00f1era",
    "sg:orig_category":"Peluquer\u00cdas, Peluquer\u00cda Mixta",
    "sg:phone":"+34 927 31 91 14",
    "sg:postcode":"10210",
    "sg:province":"C\u00e1ceres",
    "wof:name":"Gonzalez Sanchez Mercedes",
    "wof:placetype":"venue"
},
  "geometry": {"coordinates":[-5.7537660599,39.4242515564],"type":"Point"}
}