{
  "type": "Feature",
  "properties": {
    "iso:country":"ES",
    "sg:address":"Calle de San Francisco, S/n",
    "sg:city":"Baza",
    "sg:orig_category":"Ingeniero",
    "sg:phone":"+34 958 70 13 50",
    "sg:postcode":"18800",
    "sg:province":"Granada",
    "wof:name":"Martinez Martinez Jose Maria",
    "wof:placetype":"venue"
},
  "geometry": {"coordinates":[-2.7724940777,37.4887046814],"type":"Point"}
}