{
  "type": "Feature",
  "properties": {
    "addr:full":"Calle de Getaria, 7 Vitoria-gasteiz \u00c1lava 01010",
    "addr:housenumber":"7",
    "addr:postcode":"01010",
    "addr:street":"Calle De Getaria",
    "iso:country":"ES",
    "sg:address":"Calle de Getaria, 7",
    "sg:city":"Vitoria-gasteiz",
    "sg:orig_category":"Confiter\u00cdas, Chocolater\u00cdas (al Por Menor)",
    "sg:phone":"+34 945 19 12 04",
    "sg:postcode":"01010",
    "sg:province":"\u00c1lava",
    "wof:name":"Liberal Rosado Marca",
    "wof:placetype":"venue"
},
  "geometry": {"coordinates":[-2.6928281784,42.8663291931],"type":"Point"}
}