{
  "type": "Feature",
  "properties": {
    "iso:country":"ES",
    "sg:address":"Calle de Pintor Ribera, 3",
    "sg:city":"Cadiz",
    "sg:orig_category":"Estudios De Grabaci\u00d3n Sonora",
    "sg:phone":"+34 956 20 07 28",
    "sg:postcode":"11010",
    "sg:province":"C\u00e1diz",
    "wof:name":"Garcia Alberni Mario",
    "wof:placetype":"venue"
},
  "geometry": {"coordinates":[-6.2754530907,36.5070991516],"type":"Point"}
}