{
  "type": "Feature",
  "properties": {
    "addr:full":"Calle de Barrera, 5 Cuellar Segovia 40200",
    "addr:housenumber":"5",
    "addr:postcode":"40200",
    "addr:street":"Calle De Barrera",
    "iso:country":"ES",
    "sg:address":"Calle de Barrera, 5",
    "sg:city":"Cuellar",
    "sg:orig_category":"Carnicer\u00cdas, Carnicer\u00cdas",
    "sg:phone":"+34 921 14 02 82",
    "sg:postcode":"40200",
    "sg:province":"Segovia",
    "wof:name":"Embutidos Y Jamones Cuellar, S.l.",
    "wof:placetype":"venue"
},
  "geometry": {"coordinates":[-4.3166356087,41.4022674561],"type":"Point"}
}