{
  "type": "Feature",
  "properties": {
    "iso:country":"ES",
    "sg:address":"Calle de Lago Constanza, 72",
    "sg:city":"Madrid",
    "sg:orig_category":"Serigraf\u00cda (material Y Suministros)",
    "sg:phone":"+34 914 07 52 58",
    "sg:postcode":"28017",
    "sg:province":"Madrid",
    "wof:name":"Pavon Jimenez Enrique",
    "wof:placetype":"venue"
},
  "geometry": {"coordinates":[-3.6459829807,40.4289283752],"type":"Point"}
}