{
  "type": "Feature",
  "properties": {
    "addr:full":"Av Maresme (del), 63 Mataro Barcelona 08302",
    "addr:postcode":"08302",
    "addr:street":"Av;Del 63",
    "iso:country":"ES",
    "sg:address":"Av Maresme (del), 63",
    "sg:city":"Mataro",
    "sg:orig_category":"Alquiler De Veh\u00cdculos: Turismos Y Utilitarios",
    "sg:phone":"+34 937 57 87 86",
    "sg:postcode":"08302",
    "sg:province":"Barcelona",
    "sg:website":"www.atesa.es",
    "wof:name":"Atesa",
    "wof:placetype":"venue"
},
  "geometry": {"coordinates":[2.4399621487,41.5309410095],"type":"Point"}
}