{
  "type": "Feature",
  "properties": {
    "addr:full":"Carrer de Torrento, 20 Lloret Mar Girona 17310",
    "addr:housenumber":"20",
    "addr:postcode":"17310",
    "addr:street":"Carrer De Torrento",
    "iso:country":"ES",
    "sg:address":"Carrer de Torrento, 20",
    "sg:city":"Lloret Mar",
    "sg:orig_category":"Inmobiliaria (agencias)",
    "sg:phone":"+34 972 36 32 61",
    "sg:postcode":"17310",
    "sg:province":"Girona",
    "wof:name":"Promocions Garangou S.l.",
    "wof:placetype":"venue"
},
  "geometry": {"coordinates":[2.8471090794,41.7015266418],"type":"Point"}
}