{
  "type": "Feature",
  "properties": {
    "addr:full":"Plaz Salvador, 2 Valencia De Don Juan Le\u00f3n 24200",
    "addr:housenumber":"2",
    "addr:postcode":"24200",
    "addr:street":"Salvador",
    "iso:country":"ES",
    "sg:address":"Plaz Salvador, 2",
    "sg:city":"Valencia De Don Juan",
    "sg:classifiers":[
        {
            "category":"Casinos & Gambling",
            "type":"Entertainment"
        }
    ],
    "sg:phone":"+34 987 75 01 52",
    "sg:postcode":"24200",
    "sg:province":"Le\u00f3n",
    "sg:tags":[
        "locale",
        "de",
        "juego"
    ],
    "wof:name":"El Rincon De Los Duendes C.b.",
    "wof:placetype":"venue"
},
  "geometry": {"coordinates":[-5.5147738457,42.293170929],"type":"Point"}
}