{
  "type": "Feature",
  "properties": {
    "addr:full":"Plaz Espa\u00d1a, 14 Piedrahita \u00c1vila 05500",
    "addr:housenumber":"14",
    "addr:postcode":"05500",
    "addr:street":"Plaz Espan\u0303A",
    "iso:country":"ES",
    "sg:address":"Plaz Espa\u00d1a, 14",
    "sg:city":"Piedrahita",
    "sg:orig_category":"Bancos",
    "sg:phone":"+34 920 36 01 59",
    "sg:postcode":"05500",
    "sg:province":"\u00c1vila",
    "wof:name":"Banco De Castilla",
    "wof:placetype":"venue"
},
  "geometry": {"coordinates":[-5.3263239861,40.4657211304],"type":"Point"}
}