{
  "type": "Feature",
  "properties": {
    "iso:country":"ES",
    "sg:address":"G.v. Corts Catalanes, 399",
    "sg:city":"Barcelona",
    "sg:orig_category":"Agencias Y Asesores De Publicidad",
    "sg:phone":"+34 934 23 16 59",
    "sg:postcode":"08015",
    "sg:province":"Barcelona",
    "wof:name":"Eskokat S.l.",
    "wof:placetype":"venue"
},
  "geometry": {"coordinates":[2.1511180401,41.3769645691],"type":"Point"}
}