{
  "type": "Feature",
  "properties": {
    "addr:full":"Calle de Larga, 55 Puebla Del Rio Sevilla 41130",
    "addr:housenumber":"55",
    "addr:postcode":"41130",
    "addr:street":"Calle De Larga",
    "iso:country":"ES",
    "sg:address":"Calle de Larga, 55",
    "sg:city":"Puebla Del Rio",
    "sg:orig_category":"Farmacias",
    "sg:phone":"+34 955 77 02 23",
    "sg:postcode":"41130",
    "sg:province":"Sevilla",
    "wof:name":"Atienza Mendez Miguel",
    "wof:placetype":"venue"
},
  "geometry": {"coordinates":[-6.0616087914,37.2688713074],"type":"Point"}
}