{
  "type": "Feature",
  "properties": {
    "addr:full":"Calle de Calvo Sotelo, S/n Ampuero Cantabria 39840",
    "addr:housenumber":"s / n",
    "addr:postcode":"39840",
    "addr:street":"Calle De Calvo Sotelo",
    "iso:country":"ES",
    "sg:address":"Calle de Calvo Sotelo, S/n",
    "sg:city":"Ampuero",
    "sg:orig_category":"Molduras, Junquillos, Listones Y Molduras Perforadas",
    "sg:phone":"+34 942 62 20 26",
    "sg:postcode":"39840",
    "sg:province":"Cantabria",
    "wof:name":"Irastorza Escajadillo Antonio",
    "wof:placetype":"venue"
},
  "geometry": {"coordinates":[-3.4146502018,43.3423271179],"type":"Point"}
}