{
  "type": "Feature",
  "properties": {
    "iso:country":"ES",
    "sg:address":"Villarroa\u00f1e, Km. 0027,0",
    "sg:city":"Sta Olaja Ribera",
    "sg:orig_category":"Negocio De Materiales De Construcci\u00d3n",
    "sg:phone":"+34 987 25 41 22",
    "sg:postcode":"24199",
    "sg:province":"Le\u00f3n",
    "wof:name":"Macys S. A.",
    "wof:placetype":"venue"
},
  "geometry": {"coordinates":[-5.5717520714,42.5998764038],"type":"Point"}
}