{
  "type": "Feature",
  "properties": {
    "addr:full":"Uxio Souto, 3 Cuntis Pontevedra 36670",
    "addr:housenumber":"3",
    "addr:postcode":"36670",
    "addr:street":"Souto",
    "iso:country":"ES",
    "sg:address":"Uxio Souto, 3",
    "sg:city":"Cuntis",
    "sg:orig_category":"Electricidad: Instaladores",
    "sg:phone":"+34 986 54 86 67",
    "sg:postcode":"36670",
    "sg:province":"Pontevedra",
    "wof:name":"Ags Galicia Instalaciones Electricas S.l.",
    "wof:placetype":"venue"
},
  "geometry": {"coordinates":[-8.5618896484,42.6350326538],"type":"Point"}
}