{
  "type": "Feature",
  "properties": {
    "iso:country":"ES",
    "sg:address":"Calle de Tejar, 37",
    "sg:city":"Torrijos",
    "sg:orig_category":"Contables",
    "sg:phone":"+34 925 77 50 09",
    "sg:postcode":"45500",
    "sg:province":"Toledo",
    "wof:name":"Romar S.c.",
    "wof:placetype":"venue"
},
  "geometry": {"coordinates":[-4.2815589905,39.9855117798],"type":"Point"}
}