{
  "type": "Feature",
  "properties": {
    "addr:full":"Calle de Maestro Fernando Sierra, 9 Jerez De La Frontera C\u00e1diz 11401",
    "addr:housenumber":"9",
    "addr:postcode":"11401",
    "addr:street":"Calle De Maestro Fernando Sierra",
    "iso:country":"ES",
    "sg:address":"Calle de Maestro Fernando Sierra, 9",
    "sg:city":"Jerez De La Frontera",
    "sg:orig_category":"Vallados Y Barreras",
    "sg:phone":"+34 956 32 12 98",
    "sg:postcode":"11401",
    "sg:province":"C\u00e1diz",
    "wof:name":"Pe\u00f1a Navarro Emilio",
    "wof:placetype":"venue"
},
  "geometry": {"coordinates":[-6.1262087822,36.6759796143],"type":"Point"}
}