{
  "type": "Feature",
  "properties": {
    "addr:full":"Florida Auzoa, 144 Hernani Guip\u00f9zcoa 20120",
    "addr:housenumber":"144",
    "addr:postcode":"20120",
    "addr:street":"Florida Auzoa;Guipu\u0300Zcoa",
    "iso:country":"ES",
    "sg:address":"Florida Auzoa, 144",
    "sg:city":"Hernani",
    "sg:orig_category":"Metalizados",
    "sg:phone":"+34 943 55 46 54",
    "sg:postcode":"20120",
    "sg:province":"Guip\u00f9zcoa",
    "sg:website":"www.mecanizadosaisper.com",
    "wof:name":"Mecanizados Aisper S.l.",
    "wof:placetype":"venue"
},
  "geometry": {"coordinates":[-1.9651839733,43.270904541],"type":"Point"}
}