{
  "type": "Feature",
  "properties": {
    "iso:country":"ES",
    "sg:address":"Avda Sierra (de La), 23",
    "sg:city":"San Sebastian De Los Reyes",
    "sg:orig_category":"Ense\u00d1anza: Peluquer\u00cda Est\u00c9tica",
    "sg:phone":"+34 916 52 14 20",
    "sg:postcode":"28700",
    "sg:province":"Madrid",
    "wof:name":"Nem Sangar S.l.",
    "wof:placetype":"venue"
},
  "geometry": {"coordinates":[-3.6325280666,40.5502510071],"type":"Point"}
}