{
  "type": "Feature",
  "properties": {
    "addr:full":"C/ Cristobal Sanz, 27 Elche Alicante 03201",
    "addr:housenumber":"27",
    "addr:postcode":"03201",
    "addr:street":"C / Cristobal Sanz",
    "iso:country":"ES",
    "sg:address":"C/ Cristobal Sanz, 27",
    "sg:city":"Elche",
    "sg:orig_category":"Cajas De Ahorro",
    "sg:phone":"+34 966 66 72 50",
    "sg:postcode":"03201",
    "sg:province":"Alicante",
    "wof:name":"Caja De Ahorros De Valencia Castellon Y Alicante",
    "wof:placetype":"venue"
},
  "geometry": {"coordinates":[-0.7038499713,38.2672576904],"type":"Point"}
}