{
  "type": "Feature",
  "properties": {
    "addr:full":"Calle de San Sebastian, 5 Nanclares De La Oca \u00c1lava 01230",
    "addr:housenumber":"5",
    "addr:postcode":"01230",
    "addr:street":"Calle De San Sebastian;A\u0301Lava",
    "iso:country":"ES",
    "sg:address":"Calle de San Sebastian, 5",
    "sg:city":"Nanclares De La Oca",
    "sg:orig_category":"Molduras, Junquillos, Listones Y Molduras Perforadas",
    "sg:phone":"+34 945 37 12 66",
    "sg:postcode":"01230",
    "sg:province":"\u00c1lava",
    "wof:name":"Romero Ruiz Antonio",
    "wof:placetype":"venue"
},
  "geometry": {"coordinates":[-2.8155388832,42.8174514771],"type":"Point"}
}