{
  "type": "Feature",
  "properties": {
    "iso:country":"ES",
    "sg:address":"Carrer de Pallars, 262",
    "sg:city":"Barcelona",
    "sg:orig_category":"Construcci\u00d3n Mec\u00c1nica",
    "sg:phone":"+34 933 08 49 83",
    "sg:postcode":"08005",
    "sg:province":"Barcelona",
    "wof:name":"Fillol Trimer S.l.",
    "wof:placetype":"venue"
},
  "geometry": {"coordinates":[2.2016499043,41.4040107727],"type":"Point"}
}