{
  "type": "Feature",
  "properties": {
    "iso:country":"ES",
    "sg:address":"Calle de Real, 17",
    "sg:city":"Adra",
    "sg:orig_category":"Tapicer\u00cdas",
    "sg:phone":"+34 950 40 15 07",
    "sg:postcode":"04770",
    "sg:province":"Almer\u00eda",
    "wof:name":"Torres Rodriguez Francisco",
    "wof:placetype":"venue"
},
  "geometry": {"coordinates":[-3.0147049427,36.7497940063],"type":"Point"}
}