{
  "type": "Feature",
  "properties": {
    "addr:full":"Teuler\u00eda, 13 Olot Girona 17800",
    "addr:housenumber":"13",
    "addr:postcode":"17800",
    "addr:street":"Teuleri\u0301A",
    "iso:country":"ES",
    "sg:address":"Teuler\u00eda, 13",
    "sg:city":"Olot",
    "sg:orig_category":"Tintes (fabricaci\u00d3n, Al Por Mayor)",
    "sg:phone":"+34 972 26 96 79",
    "sg:postcode":"17800",
    "sg:province":"Girona",
    "wof:name":"La Bugada S.l.",
    "wof:placetype":"venue"
},
  "geometry": {"coordinates":[2.4780170918,42.173324585],"type":"Point"}
}