{
  "type": "Feature",
  "properties": {
    "addr:full":"Calle de Alfonso Xiii, 26 Orihuela Alicante 03300",
    "addr:housenumber":"26",
    "addr:postcode":"03300",
    "addr:street":"Calle De Alfonso Xiii",
    "iso:country":"ES",
    "sg:address":"Calle de Alfonso Xiii, 26",
    "sg:city":"Orihuela",
    "sg:orig_category":"Centros Empresariales",
    "sg:phone":"+34 966 34 08 78",
    "sg:postcode":"03300",
    "sg:province":"Alicante",
    "wof:name":"Sociedad Agraria De Transformacion Virgen Del Camino",
    "wof:placetype":"venue"
},
  "geometry": {"coordinates":[-0.9441710114,38.0857696533],"type":"Point"}
}