{
  "type": "Feature",
  "properties": {
    "iso:country":"ES",
    "sg:address":"Rond Sant Antoni, 26",
    "sg:city":"Barcelona",
    "sg:orig_category":"Lencer\u00cda Femenina, Corseter\u00cda, Trajes De Ba\u00d1o (al Por Menor)",
    "sg:phone":"+34 934 42 22 44",
    "sg:postcode":"08001",
    "sg:province":"Barcelona",
    "wof:name":"Belma C.b.",
    "wof:placetype":"venue"
},
  "geometry": {"coordinates":[2.1646640301,41.3791732788],"type":"Point"}
}