{
  "type": "Feature",
  "properties": {
    "iso:country":"ES",
    "sg:address":"Las Bateas, S/n",
    "sg:city":"Manzanera",
    "sg:orig_category":"Carnicer\u00cdas, Carnicer\u00cdas",
    "sg:phone":"+34 978 78 29 06",
    "sg:postcode":"44420",
    "sg:province":"Teruel",
    "wof:name":"Javalambre Ocio, S.l.",
    "wof:placetype":"venue"
},
  "geometry": {"coordinates":[-0.857981801,40.0293807983],"type":"Point"}
}