{
  "type": "Feature",
  "properties": {
    "iso:country":"ES",
    "sg:address":"Pl Mossen Josep, 1",
    "sg:city":"Alcoi",
    "sg:orig_category":"Internados & Ense\u00d1anza Privada",
    "sg:phone":"+34 965 54 08 66",
    "sg:postcode":"03801",
    "sg:province":"Alicante",
    "wof:name":"Colegio Salesiano San Vicente Ferrer",
    "wof:placetype":"venue"
},
  "geometry": {"coordinates":[-0.4759739935,38.6942443848],"type":"Point"}
}