{
  "type": "Feature",
  "properties": {
    "addr:full":"Plaz Fernandez Viaga, 11 Antequera M\u00e1laga 29200",
    "addr:housenumber":"11",
    "addr:postcode":"29200",
    "addr:street":"Plaz;Viaga",
    "iso:country":"ES",
    "sg:address":"Plaz Fernandez Viaga, 11",
    "sg:city":"Antequera",
    "sg:orig_category":"Autob\u00das (explotaci\u00d3n Y Servicios De)",
    "sg:phone":"+34 952 84 24 92",
    "sg:postcode":"29200",
    "sg:province":"M\u00e1laga",
    "wof:name":"Automoviles Torres S.l.",
    "wof:placetype":"venue"
},
  "geometry": {"coordinates":[-4.5211935043,36.9971008301],"type":"Point"}
}