{
  "type": "Feature",
  "properties": {
    "iso:country":"ES",
    "sg:address":"Calle de Castillo (del), 59",
    "sg:city":"Barbastro",
    "sg:orig_category":"Mec\u00c1nico Del Autom\u00d3vil",
    "sg:phone":"+34 974 31 42 82",
    "sg:postcode":"22300",
    "sg:province":"Huesca",
    "wof:name":"Felipe Samper Maria Luisa",
    "wof:placetype":"venue"
},
  "geometry": {"coordinates":[0.124665603,42.0338478088],"type":"Point"}
}