{
  "type": "Feature",
  "properties": {
    "iso:country":"ES",
    "sg:address":"Calle de Iglesia, 15",
    "sg:city":"Granja Torrehermosa",
    "sg:orig_category":"Supermercados Y Hipermercados",
    "sg:phone":"+34 924 89 54 26",
    "sg:postcode":"06910",
    "sg:province":"Badajoz",
    "wof:name":"Calero Santiago Jose",
    "wof:placetype":"venue"
},
  "geometry": {"coordinates":[-5.5952420235,38.3100967407],"type":"Point"}
}