{
  "type": "Feature",
  "properties": {
    "addr:full":"Cami Ca Na Gabriela, 25 Arenal Islas Baleares 07600",
    "addr:housenumber":"25",
    "addr:postcode":"07600",
    "addr:street":"Ca Na Gabriela",
    "iso:country":"ES",
    "sg:address":"Cami Ca Na Gabriela, 25",
    "sg:city":"Arenal",
    "sg:orig_category":"Distribuci\u00d3n De Petr\u00d3leo Y Derivados",
    "sg:phone":"+34 971 49 10 08",
    "sg:postcode":"07600",
    "sg:province":"Islas Baleares",
    "wof:name":"Matas Y Campins Suministros S.l.u.",
    "wof:placetype":"venue"
},
  "geometry": {"coordinates":[2.7530798912,39.5117263794],"type":"Point"}
}