{
  "type": "Feature",
  "properties": {
    "iso:country":"ES",
    "sg:address":"Calle de Real, 46",
    "sg:city":"Coronada",
    "sg:orig_category":"Asociaciones, Organismos Culturales Y Socioeducativos",
    "sg:phone":"+34 924 82 60 48",
    "sg:postcode":"06469",
    "sg:province":"Badajoz",
    "wof:name":"Ayuntamiento De La Coronada",
    "wof:placetype":"venue"
},
  "geometry": {"coordinates":[-5.6697950363,38.9177932739],"type":"Point"}
}