{
  "type": "Feature",
  "properties": {
    "addr:full":"Calle de Valdemorillo, 6 Getafe Madrid 28901",
    "addr:housenumber":"6",
    "addr:postcode":"28901",
    "addr:street":"Calle De Valdemorillo",
    "iso:country":"ES",
    "sg:address":"Calle de Valdemorillo, 6",
    "sg:city":"Getafe",
    "sg:orig_category":"Plomeros",
    "sg:phone":"+34 916 96 82 58",
    "sg:postcode":"28901",
    "sg:province":"Madrid",
    "wof:name":"Instalaciones Pardal Olivares Y Lopez S.l.",
    "wof:placetype":"venue"
},
  "geometry": {"coordinates":[-3.7342510223,40.3050308228],"type":"Point"}
}