{
  "type": "Feature",
  "properties": {
    "iso:country":"ES",
    "sg:address":"Coop Nuestra Se\u00f1ora Del Carmen, 102",
    "sg:city":"Caleta Velez",
    "sg:orig_category":"Piscinas, Accesorios, Suministros (fabricaci\u00d3n, Al Por Mayor)",
    "sg:phone":"+34 952 55 09 25",
    "sg:postcode":"29751",
    "sg:province":"M\u00e1laga",
    "wof:name":"Ruiz Garcia Remedios",
    "wof:placetype":"venue"
},
  "geometry": {"coordinates":[-4.0726838112,36.7514686584],"type":"Point"}
}