{
  "type": "Feature",
  "properties": {
    "addr:full":"Plaz Espa\u00d1a, 6 Villafranca De Los Barros Badajoz 06220",
    "addr:housenumber":"6",
    "addr:postcode":"06220",
    "addr:street":"Plaz Espan\u0303A",
    "iso:country":"ES",
    "sg:address":"Plaz Espa\u00d1a, 6",
    "sg:city":"Villafranca De Los Barros",
    "sg:orig_category":"Deportes Y Ocio: Art\u00cdculos Y Ropas (al Por Menor Y Accesorios)",
    "sg:phone":"+34 924 52 59 03",
    "sg:postcode":"06220",
    "sg:province":"Badajoz",
    "wof:name":"Bazo Crespo Amalia",
    "wof:placetype":"venue"
},
  "geometry": {"coordinates":[-6.3426737785,38.5613861084],"type":"Point"}
}