{
  "type": "Feature",
  "properties": {
    "iso:country":"ES",
    "sg:address":"Calle de Alfaro, 9",
    "sg:city":"Santa Cruz De Tenerife",
    "sg:orig_category":"Confecci\u00d3n De Uniformes",
    "sg:phone":"+34 922 28 32 79",
    "sg:postcode":"38003",
    "sg:province":"Santa Cruz De Tenerife",
    "wof:name":"Perez Almazan Francisco J.",
    "wof:placetype":"venue"
},
  "geometry": {"coordinates":[-16.2547092438,28.4666500092],"type":"Point"}
}