{
  "type": "Feature",
  "properties": {
    "iso:country":"ES",
    "sg:address":"Calle de Olivos (de Los), 1",
    "sg:city":"Gri\u00f1on",
    "sg:orig_category":"Organismos Y Centros De Vacaciones Y Esparcimiento Para Ni\u00d1os Y Adolescentes",
    "sg:phone":"+34 918 14 04 97",
    "sg:postcode":"28971",
    "sg:province":"Madrid",
    "wof:name":"Arribas Rodriguez Carlos",
    "wof:placetype":"venue"
},
  "geometry": {"coordinates":[-3.8494553566,40.2129402161],"type":"Point"}
}