{
  "type": "Feature",
  "properties": {
    "addr:full":"Calle de Eusebio Revilla, 13 Arevalo \u00c1vila 05200",
    "addr:housenumber":"13",
    "addr:postcode":"05200",
    "addr:street":"Calle De Eusebio Revilla",
    "iso:country":"ES",
    "sg:address":"Calle de Eusebio Revilla, 13",
    "sg:city":"Arevalo",
    "sg:orig_category":"Molduras, Junquillos, Listones Y Molduras Perforadas",
    "sg:phone":"+34 920 30 36 66",
    "sg:postcode":"05200",
    "sg:province":"\u00c1vila",
    "wof:name":"Gonzalez Hernandez Angel",
    "wof:placetype":"venue"
},
  "geometry": {"coordinates":[-4.7187147141,41.0620040894],"type":"Point"}
}