{
  "type": "Feature",
  "properties": {
    "addr:full":"La Laguna, 309 Los Llanos Aridane Santa Cruz De Tenerife 38760",
    "addr:housenumber":"309",
    "addr:postcode":"38760",
    "addr:street":"La Laguna",
    "iso:country":"ES",
    "sg:address":"La Laguna, 309",
    "sg:city":"Los Llanos Aridane",
    "sg:orig_category":"Iglesia Cat\u00d3lica",
    "sg:phone":"+34 922 46 20 51",
    "sg:postcode":"38760",
    "sg:province":"Santa Cruz De Tenerife",
    "wof:name":"Parroquia San Isidro Labrador",
    "wof:placetype":"venue"
},
  "geometry": {"coordinates":[-17.9085597992,28.6563796997],"type":"Point"}
}