{
  "type": "Feature",
  "properties": {
    "addr:full":"Atv Madrid-toledo, Km. 0003,0 Illescas Toledo 45200",
    "addr:postcode":"45200",
    "addr:street":"Madrid-Toledo Km. 0003,0",
    "iso:country":"ES",
    "sg:address":"Atv Madrid-toledo, Km. 0003,0",
    "sg:city":"Illescas",
    "sg:orig_category":"Tapicer\u00cdas",
    "sg:phone":"+34 925 54 15 22",
    "sg:postcode":"45200",
    "sg:province":"Toledo",
    "wof:name":"Solo Sofas S.l.",
    "wof:placetype":"venue"
},
  "geometry": {"coordinates":[-3.8458640575,40.1230163574],"type":"Point"}
}