{
  "type": "Feature",
  "properties": {
    "addr:full":"Artegieta Kalea, 6 Eibar Guip\u00f9zcoa 20600",
    "addr:housenumber":"6",
    "addr:postcode":"20600",
    "addr:street":"Artegieta Kalea;Guipu\u0300Zcoa",
    "iso:country":"ES",
    "sg:address":"Artegieta Kalea, 6",
    "sg:city":"Eibar",
    "sg:orig_category":"Centros De Educaci\u00d3n Especial",
    "sg:phone":"+34 943 20 72 50",
    "sg:postcode":"20600",
    "sg:province":"Guip\u00f9zcoa",
    "wof:name":"Gobierno Vasco-eusko Jaurlaritza",
    "wof:placetype":"venue"
},
  "geometry": {"coordinates":[-2.4831390381,43.1839103699],"type":"Point"}
}