{
  "type": "Feature",
  "properties": {
    "iso:country":"ES",
    "sg:address":"Avda Colon, 89",
    "sg:city":"Pobla Vallbona",
    "sg:orig_category":"Peluqueros: De Se\u00d1oras",
    "sg:phone":"+34 962 76 18 28",
    "sg:postcode":"46185",
    "sg:province":"Valencia",
    "wof:name":"Perfil C.b.",
    "wof:placetype":"venue"
},
  "geometry": {"coordinates":[-0.5547459722,39.5907058716],"type":"Point"}
}