{
  "type": "Feature",
  "properties": {
    "iso:country":"ES",
    "sg:address":"Calle de Glories Valencianes, 5",
    "sg:city":"Meliana",
    "sg:orig_category":"Promotores Constructores",
    "sg:phone":"+34 961 49 38 44",
    "sg:postcode":"46133",
    "sg:province":"Valencia",
    "wof:name":"Construcciones Garrigues Morales S.a.",
    "wof:placetype":"venue"
},
  "geometry": {"coordinates":[-0.3483639956,39.5253562927],"type":"Point"}
}