{
  "type": "Feature",
  "properties": {
    "addr:full":"Av Lluis Companys, 40 S. Cugat Valles Barcelona 08172",
    "addr:housenumber":"40",
    "addr:postcode":"08172",
    "addr:street":"Av Lluis Companys;S. Cugat Valles Barcelona",
    "iso:country":"ES",
    "sg:address":"Av Lluis Companys, 40",
    "sg:city":"S. Cugat Valles",
    "sg:orig_category":"Art\u00cdculos De Decoraci\u00d3n",
    "sg:phone":"+34 935 89 50 50",
    "sg:postcode":"08172",
    "sg:province":"Barcelona",
    "sg:website":"www.grupolober.com",
    "wof:name":"Domusdecor S.l.",
    "wof:placetype":"venue"
},
  "geometry": {"coordinates":[2.0793600082,41.4715118408],"type":"Point"}
}