{
  "type": "Feature",
  "properties": {
    "addr:full":"Calle de Alcala, 584 Madrid Madrid 28022",
    "addr:housenumber":"584",
    "addr:postcode":"28022",
    "addr:street":"Calle De Alcala",
    "iso:country":"ES",
    "sg:address":"Calle de Alcala, 584",
    "sg:city":"Madrid",
    "sg:orig_category":"Centros De Coordinaci\u00d3n",
    "sg:phone":"+34 917 41 16 10",
    "sg:postcode":"28022",
    "sg:province":"Madrid",
    "sg:website":"www.glezvilla.com",
    "wof:name":"Glezvilla Asesores S.l.",
    "wof:placetype":"venue"
},
  "geometry": {"coordinates":[-3.6128268242,40.4462547302],"type":"Point"}
}