{
  "type": "Feature",
  "properties": {
    "addr:full":"Carrer de Enamorats, 89 Barcelona Barcelona 08013",
    "addr:housenumber":"89",
    "addr:postcode":"08013",
    "addr:street":"Carrer De Enamorats",
    "iso:country":"ES",
    "sg:address":"Carrer de Enamorats, 89",
    "sg:city":"Barcelona",
    "sg:orig_category":"Inform\u00c1tica, Ofim\u00c1tica (estudios, Asesor\u00cda, Ingenier\u00cda, Formaci\u00d3n)",
    "sg:phone":"+34 932 65 12 38",
    "sg:postcode":"08013",
    "sg:province":"Barcelona",
    "wof:name":"Jove Teixits S.cv.",
    "wof:placetype":"venue"
},
  "geometry": {"coordinates":[2.1827731133,41.4061317444],"type":"Point"}
}