{
  "type": "Feature",
  "properties": {
    "iso:country":"ES",
    "sg:address":"Calle de Pablo Casals, S/n",
    "sg:city":"Parla",
    "sg:orig_category":"Carnicer\u00cdas, Carnicer\u00cdas",
    "sg:phone":"+34 916 05 40 04",
    "sg:postcode":"28980",
    "sg:province":"Madrid",
    "wof:name":"Garcia Vallejo Antonio",
    "wof:placetype":"venue"
},
  "geometry": {"coordinates":[-3.7728939056,40.2308883667],"type":"Point"}
}