{
  "type": "Feature",
  "properties": {
    "iso:country":"ES",
    "sg:address":"Bijuters, 88",
    "sg:city":"Ciutadella Menorca",
    "sg:orig_category":"Maquinaria Para Industrias Diversas",
    "sg:phone":"+34 971 38 41 96",
    "sg:postcode":"07760",
    "sg:province":"Islas Baleares",
    "wof:name":"Camps Coll Francisco",
    "wof:placetype":"venue"
},
  "geometry": {"coordinates":[3.8534700871,40.0113601685],"type":"Point"}
}