{
  "type": "Feature",
  "properties": {
    "addr:full":"C/ Fatxo, 5 Elche Alicante 03202",
    "addr:housenumber":"5",
    "addr:postcode":"03202",
    "addr:street":"C / Fatxo",
    "iso:country":"ES",
    "sg:address":"C/ Fatxo, 5",
    "sg:city":"Elche",
    "sg:orig_category":"Asesor\u00cda De Formaci\u00d3n Y Gesti\u00d3n De Personal",
    "sg:phone":"+34 965 42 14 22",
    "sg:postcode":"03202",
    "sg:province":"Alicante",
    "wof:name":"1980 Consultors Legals S.l.",
    "wof:placetype":"venue"
},
  "geometry": {"coordinates":[-0.697072,38.267696],"type":"Point"}
}