{
  "type": "Feature",
  "properties": {
    "addr:full":"Calle de Sevilla, 59 Rociana Condado Huelva 21720",
    "addr:housenumber":"59",
    "addr:postcode":"21720",
    "addr:street":"Calle De Sevilla",
    "iso:country":"ES",
    "sg:address":"Calle de Sevilla, 59",
    "sg:city":"Rociana Condado",
    "sg:orig_category":"Promotores Constructores",
    "sg:phone":"+34 959 41 67 96",
    "sg:postcode":"21720",
    "sg:province":"Huelva",
    "wof:name":"Multiservicios Sevillanos S.l.",
    "wof:placetype":"venue"
},
  "geometry": {"coordinates":[-6.5961894989,37.3092269897],"type":"Point"}
}