{
  "type": "Feature",
  "properties": {
    "addr:full":"Calle de Santa Apolonia, 135 Aviles Asturias 33403",
    "addr:housenumber":"135",
    "addr:postcode":"33403",
    "addr:street":"Calle De Santa Apolonia",
    "iso:country":"ES",
    "sg:address":"Calle de Santa Apolonia, 135",
    "sg:city":"Aviles",
    "sg:orig_category":"Abogados",
    "sg:phone":"+34 985 57 54 02",
    "sg:postcode":"33403",
    "sg:province":"Asturias",
    "wof:name":"Hernando Acero Ignacio",
    "wof:placetype":"venue"
},
  "geometry": {"coordinates":[-5.9033970833,43.5393867493],"type":"Point"}
}