{
  "type": "Feature",
  "properties": {
    "addr:full":"Calle de Ramon Gallud, 74 Torrevieja Alicante 03180",
    "addr:housenumber":"74",
    "addr:postcode":"03180",
    "addr:street":"Calle De Ramon Gallud",
    "iso:country":"ES",
    "sg:address":"Calle de Ramon Gallud, 74",
    "sg:city":"Torrevieja",
    "sg:orig_category":"Abogados",
    "sg:phone":"+34 965 71 19 47",
    "sg:postcode":"03180",
    "sg:province":"Alicante",
    "wof:name":"Sanchez Pardines Manuel",
    "wof:placetype":"venue"
},
  "geometry": {"coordinates":[-0.6797339916,37.9772071838],"type":"Point"}
}