{
  "type": "Feature",
  "properties": {
    "addr:full":"Calle de Solarillo De Gracia, 8 Granada Granada 18002",
    "addr:housenumber":"8",
    "addr:postcode":"18002",
    "addr:street":"Calle De Solarillo De Gracia",
    "iso:country":"ES",
    "sg:address":"Calle de Solarillo De Gracia, 8",
    "sg:city":"Granada",
    "sg:orig_category":"Complementos De Vestir (al Por Menor)",
    "sg:phone":"+34 958 26 17 17",
    "sg:postcode":"18002",
    "sg:province":"Granada",
    "wof:name":"Arribas Wriedt Juan Mariano",
    "wof:placetype":"venue"
},
  "geometry": {"coordinates":[-3.6036632061,37.1726989746],"type":"Point"}
}