{
  "type": "Feature",
  "properties": {
    "addr:full":"Carr Miranda De Cala Corb, 1 Castell Islas Baleares 07720",
    "addr:housenumber":"1",
    "addr:postcode":"07720",
    "addr:street":"Carr Miranda De Cala Corb",
    "iso:country":"ES",
    "sg:address":"Carr Miranda De Cala Corb, 1",
    "sg:city":"Castell",
    "sg:orig_category":"Ense\u00d1anza, Formaci\u00d3n Profesional: Aprendizaje",
    "sg:phone":"+34 971 36 45 12",
    "sg:postcode":"07720",
    "sg:province":"Islas Baleares",
    "wof:name":"Govern Balear",
    "wof:placetype":"venue"
},
  "geometry": {"coordinates":[4.2858448029,39.879650116],"type":"Point"}
}