{
  "type": "Feature",
  "properties": {
    "addr:full":"Rua Subride, 134 Fonte Escura Pontevedra 36215",
    "addr:housenumber":"134",
    "addr:postcode":"36215",
    "addr:street":"Rua Subride",
    "iso:country":"ES",
    "sg:address":"Rua Subride, 134",
    "sg:city":"Fonte Escura",
    "sg:orig_category":"Molduras, Junquillos, Listones Y Molduras Perforadas",
    "sg:phone":"+34 986 26 48 02",
    "sg:postcode":"36215",
    "sg:province":"Pontevedra",
    "wof:name":"Martinez Comesa\u00f1a Maria Eugenia",
    "wof:placetype":"venue"
},
  "geometry": {"coordinates":[-8.663274765,42.2263412476],"type":"Point"}
}