{
  "type": "Feature",
  "properties": {
    "addr:full":"Calle de San Antonio, 70 Mislata Valencia 46920",
    "addr:housenumber":"70",
    "addr:postcode":"46920",
    "addr:street":"Calle De San Antonio",
    "iso:country":"ES",
    "sg:address":"Calle de San Antonio, 70",
    "sg:city":"Mislata",
    "sg:orig_category":"Empresas De Carpinter\u00cda",
    "sg:phone":"+34 963 83 33 19",
    "sg:postcode":"46920",
    "sg:province":"Valencia",
    "wof:name":"Alumigon S.l.",
    "wof:placetype":"venue"
},
  "geometry": {"coordinates":[-0.4173446,39.4759750366],"type":"Point"}
}