{
  "type": "Feature",
  "properties": {
    "addr:full":"Calle de Rey Baltasar, 20 Cabra C\u00f3rdoba 14940",
    "addr:housenumber":"20",
    "addr:postcode":"14940",
    "addr:street":"Calle De Rey Baltasar;Co\u0301Rdoba",
    "iso:country":"ES",
    "sg:address":"Calle de Rey Baltasar, 20",
    "sg:city":"Cabra",
    "sg:orig_category":"Empresas De Carpinter\u00cda De Madera",
    "sg:phone":"+34 957 52 33 61",
    "sg:postcode":"14940",
    "sg:province":"C\u00f3rdoba",
    "wof:name":"Leon Rodriguez Francisco",
    "wof:placetype":"venue"
},
  "geometry": {"coordinates":[-4.4428877831,37.4786987305],"type":"Point"}
}