{
  "type": "Feature",
  "properties": {
    "addr:full":"Calle de Principal, 55 Boiro La Coru\u00f1a 15930",
    "addr:housenumber":"55",
    "addr:postcode":"15930",
    "addr:street":"Calle De Principal;La Corun\u0303A",
    "iso:country":"ES",
    "sg:address":"Calle de Principal, 55",
    "sg:city":"Boiro",
    "sg:orig_category":"Organizaciones Profesionales",
    "sg:phone":"+34 981 84 55 32",
    "sg:postcode":"15930",
    "sg:province":"La Coru\u00f1a",
    "wof:name":"Multinave Ship'agent S.l.",
    "wof:placetype":"venue"
},
  "geometry": {"coordinates":[-8.8817510605,42.64818573],"type":"Point"}
}