{
  "type": "Feature",
  "properties": {
    "iso:country":"ES",
    "sg:address":"Calle de Atlantico, S/n",
    "sg:city":"Ajalvir",
    "sg:orig_category":"Centros De Reservas Hoteleras",
    "sg:phone":"+34 918 84 37 28",
    "sg:postcode":"28864",
    "sg:province":"Madrid",
    "sg:website":"www.ribs.es",
    "wof:name":"Ribs Casa De Las Costillas S.a.",
    "wof:placetype":"venue"
},
  "geometry": {"coordinates":[-3.4828419685,40.5281143188],"type":"Point"}
}