{
  "type": "Feature",
  "properties": {
    "addr:full":"Pase Acacias (de Las), 45 Azuqueca Henares Guadalajara 19200",
    "addr:housenumber":"45",
    "addr:postcode":"19200",
    "addr:street":"Las",
    "iso:country":"ES",
    "sg:address":"Pase Acacias (de Las), 45",
    "sg:city":"Azuqueca Henares",
    "sg:orig_category":"Peluquer\u00cdas, Peluquer\u00cda Mixta",
    "sg:phone":"+34 949 26 06 62",
    "sg:postcode":"19200",
    "sg:province":"Guadalajara",
    "wof:name":"Burgos Iglesias Sonia",
    "wof:placetype":"venue"
},
  "geometry": {"coordinates":[-3.2677440643,40.5646400452],"type":"Point"}
}