{
  "type": "Feature",
  "properties": {
    "iso:country":"ES",
    "sg:address":"Calle de Belgica, De, 137",
    "sg:city":"Castellon De La Plana",
    "sg:orig_category":"Art\u00cdculos De Aluminio",
    "sg:phone":"+34 964 20 02 49",
    "sg:postcode":"12006",
    "sg:province":"Castell\u00f3n",
    "sg:website":"www. paginasamarillas . es",
    "wof:name":"Aluminio Castellon S. A.",
    "wof:placetype":"venue"
},
  "geometry": {"coordinates":[-0.0753272027,39.9718284607],"type":"Point"}
}