{
  "type": "Feature",
  "properties": {
    "iso:country":"ES",
    "sg:address":"Calle de Juan De Garai, 1",
    "sg:city":"Donostia-san Sebastian",
    "sg:orig_category":"Carnicer\u00cdas, Carnicer\u00cdas",
    "sg:phone":"+34 943 21 29 63",
    "sg:postcode":"20008",
    "sg:province":"Guip\u00f9zcoa",
    "wof:name":"Miguel Angel Arrillaga Saizar",
    "wof:placetype":"venue"
},
  "geometry": {"coordinates":[-2.0037639141,43.3130187988],"type":"Point"}
}