{
  "type": "Feature",
  "properties": {
    "iso:country":"ES",
    "sg:address":"Plaz Daoiz Y Velarde, 1",
    "sg:city":"Melilla",
    "sg:orig_category":"Carnicer\u00cdas, Carnicer\u00cdas",
    "sg:phone":"+34 952 67 24 79",
    "sg:postcode":"52005",
    "sg:province":"Melilla",
    "wof:name":"Azouaghe  Driss",
    "wof:placetype":"venue"
},
  "geometry": {"coordinates":[-2.9460968971,35.2877807617],"type":"Point"}
}