{
  "type": "Feature",
  "properties": {
    "addr:full":"Carrer de Espanya, 6 Sitges Barcelona 08870",
    "addr:housenumber":"6",
    "addr:postcode":"08870",
    "addr:street":"Carrer De Espanya",
    "iso:country":"ES",
    "sg:address":"Carrer de Espanya, 6",
    "sg:city":"Sitges",
    "sg:orig_category":"Vinos Y Licores (venta Al Por Menor)",
    "sg:phone":"+34 938 94 00 00",
    "sg:postcode":"08870",
    "sg:province":"Barcelona",
    "sg:website":"www.elcellerdesitges.com",
    "wof:name":"El Arte De Beber S.l.l.",
    "wof:placetype":"venue"
},
  "geometry": {"coordinates":[1.8066010475,41.2350082397],"type":"Point"}
}