{
  "type": "Feature",
  "properties": {
    "addr:full":"Polig Industrial, S/n Lorqui Murcia 30564",
    "addr:housenumber":"/ n",
    "addr:postcode":"30564",
    "addr:street":"Polig Industrial S",
    "iso:country":"ES",
    "sg:address":"Polig Industrial, S/n",
    "sg:city":"Lorqui",
    "sg:orig_category":"Construcciones Met\u00c1licas",
    "sg:phone":"+34 968 68 75 41",
    "sg:postcode":"30564",
    "sg:province":"Murcia",
    "wof:name":"Proyectos Estrucon S.l.",
    "wof:placetype":"venue"
},
  "geometry": {"coordinates":[-1.2350000143,38.1045875549],"type":"Point"}
}