{
  "type": "Feature",
  "properties": {
    "addr:full":"G.v. Corts Catalanes, 759 Barcelona Barcelona 08013",
    "addr:housenumber":"759",
    "addr:postcode":"08013",
    "addr:street":"Catalanes",
    "iso:country":"ES",
    "sg:address":"G.v. Corts Catalanes, 759",
    "sg:city":"Barcelona",
    "sg:orig_category":"Mec\u00c1nico Del Autom\u00d3vil",
    "sg:phone":"+34 932 45 58 43",
    "sg:postcode":"08013",
    "sg:province":"Barcelona",
    "wof:name":"Beetle Speedster S.l.",
    "wof:placetype":"venue"
},
  "geometry": {"coordinates":[2.1838750839,41.4015197754],"type":"Point"}
}