{
  "type": "Feature",
  "properties": {
    "addr:full":"Avda Asturias, 149 Columbrianos Le\u00f3n 24490",
    "addr:housenumber":"149",
    "addr:postcode":"24490",
    "addr:street":"Avda Asturias;Leo\u0301N",
    "iso:country":"ES",
    "sg:address":"Avda Asturias, 149",
    "sg:city":"Columbrianos",
    "sg:orig_category":"Chapister\u00cda",
    "sg:phone":"+34 987 40 31 60",
    "sg:postcode":"24490",
    "sg:province":"Le\u00f3n",
    "wof:name":"Talleres Santalla Y Sampron S.l.",
    "wof:placetype":"venue"
},
  "geometry": {"coordinates":[-6.604572773,42.5627288818],"type":"Point"}
}