{
  "type": "Feature",
  "properties": {
    "addr:full":"Urb Santa Maria, S/n Alca\u00f1iz Teruel 44600",
    "addr:postcode":"44600",
    "addr:street":"Urb Santa Maria S / N",
    "iso:country":"ES",
    "sg:address":"Urb Santa Maria, S/n",
    "sg:city":"Alca\u00f1iz",
    "sg:orig_category":"Imprenta",
    "sg:phone":"+34 978 83 00 85",
    "sg:postcode":"44600",
    "sg:province":"Teruel",
    "wof:name":"Imprenta Ferrando S.c.",
    "wof:placetype":"venue"
},
  "geometry": {"coordinates":[-0.1332339942,41.052898407],"type":"Point"}
}