{
  "type": "Feature",
  "properties": {
    "addr:full":"Pase Salut, 6 Badalona Barcelona 08914",
    "addr:postcode":"08914",
    "iso:country":"ES",
    "sg:address":"Pase Salut, 6",
    "sg:city":"Badalona",
    "sg:orig_category":"Reposter\u00cdas",
    "sg:phone":"+34 933 83 09 62",
    "sg:postcode":"08914",
    "sg:province":"Barcelona",
    "wof:name":"Horno La Salud S. L.",
    "wof:placetype":"venue"
},
  "geometry": {"coordinates":[2.227686882,41.4402885437],"type":"Point"}
}