{
  "type": "Feature",
  "properties": {
    "iso:country":"ES",
    "sg:address":"Poli Industrial Alces, 83",
    "sg:city":"Alcazar S. Juan",
    "sg:orig_category":"Confecci\u00d3n De Trajes Para Se\u00d1oras",
    "sg:phone":"+34 926 54 36 50",
    "sg:postcode":"13600",
    "sg:province":"Ciudad Real",
    "wof:name":"Missouri S. A.",
    "wof:placetype":"venue"
},
  "geometry": {"coordinates":[-3.210203886,39.3900718689],"type":"Point"}
}