{
  "type": "Feature",
  "properties": {
    "iso:country":"ES",
    "sg:address":"Avda Salamanca, 43",
    "sg:city":"Ciudad Rodrigo",
    "sg:orig_category":"Empresarios",
    "sg:phone":"+34 923 48 20 79",
    "sg:postcode":"37500",
    "sg:province":"Salamanca",
    "wof:name":"Garcia Rivero Perfecto",
    "wof:placetype":"venue"
},
  "geometry": {"coordinates":[-6.5288610458,40.6042861938],"type":"Point"}
}