{
  "type": "Feature",
  "properties": {
    "iso:country":"ES",
    "sg:address":"Pseo. Constitucion, 28",
    "sg:city":"Almaraz",
    "sg:orig_category":"Estancos",
    "sg:phone":"+34 927 54 40 31",
    "sg:postcode":"10350",
    "sg:province":"C\u00e1ceres",
    "wof:name":"Arjona Izquierdo Fatima",
    "wof:placetype":"venue"
},
  "geometry": {"coordinates":[-5.6773509979,39.7912712097],"type":"Point"}
}