{
  "type": "Feature",
  "properties": {
    "addr:full":"Poli Industrial Las Casas, S/n Soria Soria 42005",
    "addr:housenumber":"s / n",
    "addr:postcode":"42005",
    "iso:country":"ES",
    "sg:address":"Poli Industrial Las Casas, S/n",
    "sg:city":"Soria",
    "sg:orig_category":"Ferreter\u00cda Artesanal",
    "sg:phone":"+34 975 22 97 65",
    "sg:postcode":"42005",
    "sg:province":"Soria",
    "wof:name":"Garcia Cabrerizo Luis",
    "wof:placetype":"venue"
},
  "geometry": {"coordinates":[-2.4691669941,41.7646598816],"type":"Point"}
}