{
  "type": "Feature",
  "properties": {
    "addr:full":"Damaso Alonso(las Lumbreras), S/n Monteagudo Murcia 30160",
    "addr:housenumber":"s / n",
    "addr:postcode":"30160",
    "addr:street":"Damaso Alonso Las Lumbreras",
    "iso:country":"ES",
    "sg:address":"Damaso Alonso(las Lumbreras), S/n",
    "sg:city":"Monteagudo",
    "sg:orig_category":"Centros De Educaci\u00d3n Especial",
    "sg:phone":"+34 968 85 04 48",
    "sg:postcode":"30160",
    "sg:province":"Murcia",
    "wof:name":"Colegio Publico Juan Xxiii",
    "wof:placetype":"venue"
},
  "geometry": {"coordinates":[-1.0898009539,38.0297737122],"type":"Point"}
}