{
  "type": "Feature",
  "properties": {
    "addr:full":"Calle de Pablo Serrano, 17 Madrid Madrid 28043",
    "addr:housenumber":"17",
    "addr:postcode":"madrid;28043",
    "addr:street":"Calle De Pablo Serrano",
    "iso:country":"ES",
    "sg:address":"Calle de Pablo Serrano, 17",
    "sg:city":"Madrid",
    "sg:orig_category":"Farmacias",
    "sg:phone":"+34 913 81 05 10",
    "sg:postcode":"28043",
    "sg:province":"Madrid",
    "wof:name":"Fonseca Herrero Maria Del Carmen",
    "wof:placetype":"venue"
},
  "geometry": {"coordinates":[-3.6476728916,40.4691696167],"type":"Point"}
}