{
  "type": "Feature",
  "properties": {
    "iso:country":"ES",
    "sg:address":"Calle de Milagros, 1",
    "sg:city":"Coria Rio",
    "sg:orig_category":"Promotores Constructores",
    "sg:phone":"+34 954 77 07 10",
    "sg:postcode":"41100",
    "sg:province":"Sevilla",
    "wof:name":"Construcciones De La Rosa-lama S.l.",
    "wof:placetype":"venue"
},
  "geometry": {"coordinates":[-6.0598921776,37.2878417969],"type":"Point"}
}