{
  "type": "Feature",
  "properties": {
    "addr:full":"Avda El Ferial, 144 Benavente Zamora 49600",
    "addr:housenumber":"144",
    "addr:postcode":"49600",
    "addr:street":"Avda El Ferial",
    "iso:country":"ES",
    "sg:address":"Avda El Ferial, 144",
    "sg:city":"Benavente",
    "sg:orig_category":"Armas Y Municiones (fabricaci\u00d3n, Al Por Mayor)",
    "sg:phone":"+34 980 63 05 07",
    "sg:postcode":"49600",
    "sg:province":"Zamora",
    "wof:name":"Sanchez Garcia Luciano",
    "wof:placetype":"venue"
},
  "geometry": {"coordinates":[-5.6804051399,41.993686676],"type":"Point"}
}