{
  "type": "Feature",
  "properties": {
    "iso:country":"ES",
    "sg:address":"Carr Angel Guimera, 37",
    "sg:city":"Palafrugell",
    "sg:orig_category":"Reposter\u00cdas",
    "sg:phone":"+34 972 30 56 37",
    "sg:postcode":"17200",
    "sg:province":"Girona",
    "wof:name":"Fleca I Pastisseria L'artesa S.l.",
    "wof:placetype":"venue"
},
  "geometry": {"coordinates":[3.1654100418,41.9124641418],"type":"Point"}
}