{
  "type": "Feature",
  "properties": {
    "iso:country":"ES",
    "sg:address":"Barr Okin-zuri, 3",
    "sg:city":"Ermua",
    "sg:orig_category":"Molduras, Junquillos, Listones Y Molduras Perforadas",
    "sg:phone":"+34 943 17 10 09",
    "sg:postcode":"48260",
    "sg:province":"Vizcaya",
    "wof:name":"Mellado Carnero Dolores",
    "wof:placetype":"venue"
},
  "geometry": {"coordinates":[-2.5020270348,43.1915359497],"type":"Point"}
}