{
  "type": "Feature",
  "properties": {
    "iso:country":"ES",
    "sg:address":"Rua Vilar (do), 36",
    "sg:city":"Santiago De Compostela",
    "sg:orig_category":"Ropa Para Se\u00d1oras (al Por Menor)",
    "sg:phone":"+34 981 58 13 43",
    "sg:postcode":"15705",
    "sg:province":"La Coru\u00f1a",
    "wof:name":"Pedrouso Montero Maria Luisa",
    "wof:placetype":"venue"
},
  "geometry": {"coordinates":[-8.544667244,42.8787155151],"type":"Point"}
}