{
  "type": "Feature",
  "properties": {
    "addr:full":"Carr Estrella, 6 Mao Islas Baleares 07702",
    "addr:housenumber":"6",
    "addr:postcode":"07702",
    "addr:street":"Carr Estrella",
    "iso:country":"ES",
    "sg:address":"Carr Estrella, 6",
    "sg:city":"Mao",
    "sg:orig_category":"Mec\u00c1nica General",
    "sg:phone":"+34 971 35 32 37",
    "sg:postcode":"07702",
    "sg:province":"Islas Baleares",
    "wof:name":"Menorca Equipamientos S.l.",
    "wof:placetype":"venue"
},
  "geometry": {"coordinates":[4.2644000053,39.8840751648],"type":"Point"}
}