{
  "type": "Feature",
  "properties": {
    "addr:full":"Calle de Diaz Crespo, 44 Algodonales C\u00e1diz 11680",
    "addr:housenumber":"44",
    "addr:postcode":"11680",
    "addr:street":"Calle De Diaz Crespo",
    "iso:country":"ES",
    "sg:address":"Calle de Diaz Crespo, 44",
    "sg:city":"Algodonales",
    "sg:orig_category":"Reposter\u00cdas",
    "sg:phone":"+34 956 13 71 58",
    "sg:postcode":"11680",
    "sg:province":"C\u00e1diz",
    "wof:name":"Rios Rosado Manuel",
    "wof:placetype":"venue"
},
  "geometry": {"coordinates":[-5.4077224731,36.8820304871],"type":"Point"}
}