{
  "type": "Feature",
  "properties": {
    "iso:country":"ES",
    "sg:address":"Calle de Malaga, 46",
    "sg:city":"Linea De La Concepcion",
    "sg:orig_category":"Reposter\u00cdas",
    "sg:phone":"+34 956 76 64 51",
    "sg:postcode":"11300",
    "sg:province":"C\u00e1diz",
    "wof:name":"Vega Sanchez Sebastian",
    "wof:placetype":"venue"
},
  "geometry": {"coordinates":[-5.3452010155,36.171913147],"type":"Point"}
}