{
  "type": "Feature",
  "properties": {
    "iso:country":"ES",
    "sg:address":"Barakaldo Kalea, 13",
    "sg:city":"Eibar",
    "sg:orig_category":"Fabricaci\u00d3n De Peines Y De Accesorios De Peluquer\u00cda",
    "sg:phone":"+34 943 20 06 54",
    "sg:postcode":"20600",
    "sg:province":"Guip\u00f9zcoa",
    "wof:name":"Exclusivas Javi Sl",
    "wof:placetype":"venue"
},
  "geometry": {"coordinates":[-2.4621419907,43.1878051758],"type":"Point"}
}