{
  "type": "Feature",
  "properties": {
    "iso:country":"ES",
    "sg:address":"Calle de Carolina Paino, 12",
    "sg:city":"Madrid",
    "sg:orig_category":"Negocio De Materiales De Construcci\u00d3n",
    "sg:phone":"+34 914 62 83 88",
    "sg:postcode":"28025",
    "sg:province":"Madrid",
    "wof:name":"Mu\u00f1oz De La Cruz Hipolito",
    "wof:placetype":"venue"
},
  "geometry": {"coordinates":[-3.7417111397,40.3846473694],"type":"Point"}
}