{
  "type": "Feature",
  "properties": {
    "addr:full":"Avda Pintor Xavier Soler, 1 Alacant Alicante 03015",
    "addr:housenumber":"1",
    "addr:postcode":"03015",
    "addr:street":"Avda Pintor Xavier Soler",
    "iso:country":"ES",
    "sg:address":"Avda Pintor Xavier Soler, 1",
    "sg:city":"Alacant",
    "sg:orig_category":"Ropa Para Se\u00d1oras (al Por Menor)",
    "sg:phone":"+34 965 25 80 63",
    "sg:postcode":"03015",
    "sg:province":"Alicante",
    "wof:name":"Oportunidades Pemar S.l.",
    "wof:placetype":"venue"
},
  "geometry": {"coordinates":[-0.4702189863,38.365776062],"type":"Point"}
}