{
  "type": "Feature",
  "properties": {
    "iso:country":"ES",
    "sg:address":"Calle de Jose Antonio Giron, 6",
    "sg:city":"Carrion De Los Condes",
    "sg:orig_category":"Empresas De Pintura Y Revestimientos",
    "sg:phone":"+34 979 88 11 86",
    "sg:postcode":"34120",
    "sg:province":"Palencia",
    "wof:name":"Garea Llorente Jose Carlos",
    "wof:placetype":"venue"
},
  "geometry": {"coordinates":[-4.6057457924,42.3386230469],"type":"Point"}
}