{
  "type": "Feature",
  "properties": {
    "iso:country":"ES",
    "sg:address":"Calle de Coronel Reig, 1",
    "sg:city":"Casetas",
    "sg:orig_category":"Cl\u00cdnicas Psiqui\u00c1tricas",
    "sg:phone":"+34 976 77 42 25",
    "sg:postcode":"50620",
    "sg:province":"Zaragoza",
    "wof:name":"Hermanas Hospitalarias Del Sagrado Corazon",
    "wof:placetype":"venue"
},
  "geometry": {"coordinates":[-1.0269263983,41.7183494568],"type":"Point"}
}