{
  "type": "Feature",
  "properties": {
    "addr:full":"Calle de Virgen Del Val, 52 Madrid Madrid 28027",
    "addr:housenumber":"52",
    "addr:postcode":"madrid;28027",
    "addr:street":"Calle De Virgen Del Val",
    "iso:country":"ES",
    "sg:address":"Calle de Virgen Del Val, 52",
    "sg:city":"Madrid",
    "sg:orig_category":"Alimentaci\u00d3n General (al Por Menor)",
    "sg:phone":"+34 914 04 30 51",
    "sg:postcode":"28027",
    "sg:province":"Madrid",
    "wof:name":"De Blas Garces Pedro",
    "wof:placetype":"venue"
},
  "geometry": {"coordinates":[-3.6499910355,40.4398345947],"type":"Point"}
}