{
  "type": "Feature",
  "properties": {
    "addr:full":"Carrer de Catalunya, 118 Prat Llobregat Barcelona 08820",
    "addr:housenumber":"118",
    "addr:postcode":"08820",
    "addr:street":"Carrer De Catalunya;Llobregat",
    "iso:country":"ES",
    "sg:address":"Carrer de Catalunya, 118",
    "sg:city":"Prat Llobregat",
    "sg:orig_category":"Empresas De Carpinter\u00cda De Madera",
    "sg:phone":"+34 933 79 64 78",
    "sg:postcode":"08820",
    "sg:province":"Barcelona",
    "wof:name":"Carpinteria Jo Pa Alvarez Scp",
    "wof:placetype":"venue"
},
  "geometry": {"coordinates":[2.1006250381,41.3253288269],"type":"Point"}
}