{
  "type": "Feature",
  "properties": {
    "iso:country":"ES",
    "sg:address":"Avda Constitucion, 3",
    "sg:city":"Mas Matas",
    "sg:orig_category":"Electrodom\u00c9sticos (al Por Menor)",
    "sg:phone":"+34 978 84 89 80",
    "sg:postcode":"44564",
    "sg:province":"Teruel",
    "wof:name":"Pastor Giner Jose Luis",
    "wof:placetype":"venue"
},
  "geometry": {"coordinates":[-0.2411209941,40.8345336914],"type":"Point"}
}