{
  "type": "Feature",
  "properties": {
    "addr:full":"Carr Anselm Pujol, 25 Ciutadella Menorca Islas Baleares 07760",
    "addr:housenumber":"25",
    "addr:postcode":"07760",
    "addr:street":"Carr Anselm Pujol",
    "iso:country":"ES",
    "sg:address":"Carr Anselm Pujol, 25",
    "sg:city":"Ciutadella Menorca",
    "sg:orig_category":"Electricidad: Instaladores",
    "sg:phone":"+34 971 38 20 76",
    "sg:postcode":"07760",
    "sg:province":"Islas Baleares",
    "wof:name":"Gener Femenias Juan",
    "wof:placetype":"venue"
},
  "geometry": {"coordinates":[3.8411920071,39.998966217],"type":"Point"}
}