{
  "type": "Feature",
  "properties": {
    "addr:full":"Los Naranjos (p I Los Arroyos), 5 Moguer Huelva 21800",
    "addr:housenumber":"5",
    "addr:postcode":"21800",
    "addr:street":"P I Los Arroyos",
    "iso:country":"ES",
    "sg:address":"Los Naranjos (p I Los Arroyos), 5",
    "sg:city":"Moguer",
    "sg:orig_category":"Electricidad: Instaladores",
    "sg:phone":"+34 959 37 13 93",
    "sg:postcode":"21800",
    "sg:province":"Huelva",
    "wof:name":"Electrimoguer S.l.",
    "wof:placetype":"venue"
},
  "geometry": {"coordinates":[-6.8297739029,37.2719993591],"type":"Point"}
}