{
  "type": "Feature",
  "properties": {
    "addr:full":"Avda. Joaquin Planells Riera, 35 A Coru\u00f1a La Coru\u00f1a 15008",
    "addr:housenumber":"35 a",
    "addr:postcode":"15008",
    "addr:street":"Avda. Joaquin Planells Riera;Corun\u0303A La Corun\u0303A",
    "iso:country":"ES",
    "sg:address":"Avda. Joaquin Planells Riera, 35",
    "sg:city":"A Coru\u00f1a",
    "sg:orig_category":"Asesor\u00cda Fiscal Y Jur\u00cddica",
    "sg:phone":"+34 981 24 32 34",
    "sg:postcode":"15008",
    "sg:province":"La Coru\u00f1a",
    "wof:name":"Brais Miron Y Asociados S.l.",
    "wof:placetype":"venue"
},
  "geometry": {"coordinates":[-8.4149894714,43.3471984863],"type":"Point"}
}