{
  "type": "Feature",
  "properties": {
    "addr:full":"Rua Horreo (do), 104 Santiago De Compostela A Coru\u00f1a 15702",
    "addr:housenumber":"104",
    "addr:postcode":"15702",
    "addr:street":"Rua Horreo;Corun\u0303A",
    "iso:country":"ES",
    "sg:address":"Rua Horreo (do), 104",
    "sg:city":"Santiago De Compostela",
    "sg:orig_category":"Cooperativas Agr\u00cdcolas",
    "sg:phone":"+34 981 57 55 78",
    "sg:postcode":"15702",
    "sg:province":"A Coru\u00f1a",
    "wof:name":"Union De Cooperativas De Trabajo Asociado Ugacota",
    "wof:placetype":"venue"
},
  "geometry": {"coordinates":[-8.5448389053,42.8728637695],"type":"Point"}
}