{
  "type": "Feature",
  "properties": {
    "iso:country":"ES",
    "sg:address":"Carrer de Batista I Roca, 4",
    "sg:city":"Barcelona",
    "sg:orig_category":"Inmobiliaria (agencias)",
    "sg:phone":"+34 934 30 60 53",
    "sg:postcode":"08029",
    "sg:province":"Barcelona",
    "wof:name":"Coorporacion Lurben Xxi S.l.",
    "wof:placetype":"venue"
},
  "geometry": {"coordinates":[2.1366500854,41.3871498108],"type":"Point"}
}