{
  "type": "Feature",
  "properties": {
    "iso:country":"ES",
    "sg:address":"Eras, S/n",
    "sg:city":"Sta. M. Llanos",
    "sg:orig_category":"Productores Recolectores, Venta Directa De Vinos",
    "sg:phone":"+34 967 18 72 04",
    "sg:postcode":"16639",
    "sg:province":"Cuenca",
    "wof:name":"Sociedad Agraria De Transformacion Virgen De Los Llanos",
    "wof:placetype":"venue"
},
  "geometry": {"coordinates":[-2.8063969612,39.4899902344],"type":"Point"}
}