{
  "type": "Feature",
  "properties": {
    "addr:full":"Calle de Marmoles, 28 Almeria Almer\u00eda 04006",
    "addr:housenumber":"28",
    "addr:postcode":"04006",
    "addr:street":"Calle De Marmoles",
    "iso:country":"ES",
    "sg:address":"Calle de Marmoles, 28",
    "sg:city":"Almeria",
    "sg:orig_category":"Delegados, Agentes De Tr\u00c1nsito, Auxiliares De Transporte Internacional",
    "sg:phone":"+34 950 22 55 82",
    "sg:postcode":"04006",
    "sg:province":"Almer\u00eda",
    "sg:website":"www.seur.es",
    "wof:name":"Redtrans Almeria S.l.",
    "wof:placetype":"venue"
},
  "geometry": {"coordinates":[-2.4371659756,36.841709137],"type":"Point"}
}