{
  "type": "Feature",
  "properties": {
    "addr:full":"Ctra. San Pedro De Visma, S/n A Coru\u00f1a La Coru\u00f1a 15191",
    "addr:housenumber":"s / n",
    "addr:postcode":"15191",
    "addr:street":"Ctra. San Pedro De Visma;A Corun\u0303A La Corun\u0303A",
    "iso:country":"ES",
    "sg:address":"Ctra. San Pedro De Visma, S/n",
    "sg:city":"A Coru\u00f1a",
    "sg:orig_category":"Empresas De Impermeabilizaci\u00d3n",
    "sg:phone":"+34 981 14 54 72",
    "sg:postcode":"15191",
    "sg:province":"La Coru\u00f1a",
    "wof:name":"Impergal S.l.",
    "wof:placetype":"venue"
},
  "geometry": {"coordinates":[-8.4424257278,43.3293380737],"type":"Point"}
}