{
  "type": "Feature",
  "properties": {
    "iso:country":"ES",
    "sg:address":"Carr Mar, 17",
    "sg:city":"Port Selva",
    "sg:orig_category":"Alimentaci\u00d3n General (al Por Menor)",
    "sg:phone":"+34 972 38 71 57",
    "sg:postcode":"17489",
    "sg:province":"Girona",
    "wof:name":"Cervera Tamborero Julia",
    "wof:placetype":"venue"
},
  "geometry": {"coordinates":[3.1865150928,42.3239517212],"type":"Point"}
}