{
  "type": "Feature",
  "properties": {
    "iso:country":"ES",
    "sg:address":"Calle de Vandergoten, 4",
    "sg:city":"Madrid",
    "sg:orig_category":"Comercio, Reparaci\u00d3n De Motocicletas, Bicicletas Y Piezas Sueltas",
    "sg:phone":"+34 915 02 14 03",
    "sg:postcode":"28014",
    "sg:province":"Madrid",
    "wof:name":"Terremotos Nr S.%.",
    "wof:placetype":"venue"
},
  "geometry": {"coordinates":[-3.6825461388,40.4053421021],"type":"Point"}
}