{
  "type": "Feature",
  "properties": {
    "addr:full":"Calle de Muller, 77 Madrid Madrid 28029",
    "addr:housenumber":"77",
    "addr:postcode":"madrid;28029",
    "addr:street":"Calle De Muller",
    "iso:country":"ES",
    "sg:address":"Calle de Muller, 77",
    "sg:city":"Madrid",
    "sg:orig_category":"Cajas De Ahorro",
    "sg:phone":"+34 913 15 50 90",
    "sg:postcode":"28029",
    "sg:province":"Madrid",
    "wof:name":"Caixa D'estalvis I Pensions De Barcelona",
    "wof:placetype":"venue"
},
  "geometry": {"coordinates":[-3.6973590851,40.4670791626],"type":"Point"}
}