{
  "type": "Feature",
  "properties": {
    "iso:country":"ES",
    "sg:address":"Calle de Arrue Pintores, 16",
    "sg:city":"Bilbao",
    "sg:orig_category":"Fabricaci\u00d3n, Instalaci\u00d3n De Escaleras",
    "sg:phone":"+34 944 75 94 69",
    "sg:postcode":"48015",
    "sg:province":"Vizcaya",
    "wof:name":"Maquiber S. A.",
    "wof:placetype":"venue"
},
  "geometry": {"coordinates":[-2.9500646591,43.2794685364],"type":"Point"}
}