{
  "type": "Feature",
  "properties": {
    "iso:country":"ES",
    "sg:address":"Veigadecabo, 50",
    "sg:city":"Barco De Valdeorras",
    "sg:orig_category":"Guarder\u00cdas",
    "sg:phone":"+34 988 32 18 45",
    "sg:postcode":"32300",
    "sg:province":"Ourense",
    "wof:name":"Perez Perez Maria Gloria",
    "wof:placetype":"venue"
},
  "geometry": {"coordinates":[-6.9837059975,42.4104614258],"type":"Point"}
}