{
  "type": "Feature",
  "properties": {
    "addr:full":"Rua Alberto Vilanova (de), 8 Carballi\u00f1o Ourense 32500",
    "addr:postcode":"32500",
    "addr:street":"Rua Alberto",
    "iso:country":"ES",
    "sg:address":"Rua Alberto Vilanova (de), 8",
    "sg:city":"Carballi\u00f1o",
    "sg:orig_category":"Sociedades, Compa\u00d1\u00cdas Aseguradoras",
    "sg:phone":"+34 988 27 30 55",
    "sg:postcode":"32500",
    "sg:province":"Ourense",
    "wof:name":"Mapfre Servicios De Informatica",
    "wof:placetype":"venue"
},
  "geometry": {"coordinates":[-8.0723085403,42.4294700623],"type":"Point"}
}