{
  "type": "Feature",
  "properties": {
    "addr:full":"Calle de Antonio Hernandez, 12 Mostoles Madrid 28931",
    "addr:housenumber":"12",
    "addr:postcode":"28931",
    "addr:street":"Calle De Antonio Hernandez",
    "iso:country":"ES",
    "sg:address":"Calle de Antonio Hernandez, 12",
    "sg:city":"Mostoles",
    "sg:orig_category":"Tiendas De Grano, Frutas Y Legumbres Secas (al Por Menor)",
    "sg:phone":"+34 916 13 61 10",
    "sg:postcode":"28931",
    "sg:province":"Madrid",
    "wof:name":"Guan Min Wu",
    "wof:placetype":"venue"
},
  "geometry": {"coordinates":[-3.8655221462,40.322933197],"type":"Point"}
}