{
  "type": "Feature",
  "properties": {
    "addr:full":"Mdo Ctral Abastos, S/n Alacant Alicante 03004",
    "addr:housenumber":"s / n",
    "addr:postcode":"03004",
    "iso:country":"ES",
    "sg:address":"Mdo Ctral Abastos, S/n",
    "sg:city":"Alacant",
    "sg:orig_category":"Carnicer\u00cdas, Carnicer\u00cdas",
    "sg:phone":"+34 965 20 62 50",
    "sg:postcode":"03004",
    "sg:province":"Alicante",
    "wof:name":"Lopez Real Juan",
    "wof:placetype":"venue"
},
  "geometry": {"coordinates":[-0.4804739952,38.3440856934],"type":"Point"}
}