{
  "type": "Feature",
  "properties": {
    "iso:country":"ES",
    "sg:address":"Carrer de Cristofor Colom, 33",
    "sg:city":"Tarragona",
    "sg:orig_category":"Peluqueros: De Se\u00d1oras",
    "sg:phone":"+34 977 21 10 53",
    "sg:postcode":"43001",
    "sg:province":"Tarragona",
    "wof:name":"Aranega Carmona Ana Maria",
    "wof:placetype":"venue"
},
  "geometry": {"coordinates":[1.2474825382,41.1151390076],"type":"Point"}
}