{
  "type": "Feature",
  "properties": {
    "addr:full":"Carr Ample, 17 Bisbal D'emporda Girona 17100",
    "addr:housenumber":"17",
    "addr:postcode":"17100",
    "addr:street":"Carr Ample",
    "iso:country":"ES",
    "sg:address":"Carr Ample, 17",
    "sg:city":"Bisbal D'emporda",
    "sg:orig_category":"Molduras, Junquillos, Listones Y Molduras Perforadas",
    "sg:phone":"+34 972 64 07 95",
    "sg:postcode":"17100",
    "sg:province":"Girona",
    "wof:name":"Martinez Arres Antonio",
    "wof:placetype":"venue"
},
  "geometry": {"coordinates":[2.813131094,41.9749221802],"type":"Point"}
}