{
  "type": "Feature",
  "properties": {
    "iso:country":"ES",
    "sg:address":"Carrer de Velazquez, 9",
    "sg:city":"Caldes Montbui",
    "sg:orig_category":"Cueros Y Pieles (al Por Mayor)",
    "sg:phone":"+34 938 65 47 65",
    "sg:postcode":"08140",
    "sg:province":"Barcelona",
    "wof:name":"Tous Pell S.l.",
    "wof:placetype":"venue"
},
  "geometry": {"coordinates":[2.1721699238,41.6315765381],"type":"Point"}
}