{
  "type": "Feature",
  "properties": {
    "addr:full":"Carrer de Sant Pere Mes Baix, 47 Barcelona Barcelona 08003",
    "addr:housenumber":"47",
    "addr:postcode":"08003",
    "addr:street":"Carrer De Sant",
    "iso:country":"ES",
    "sg:address":"Carrer de Sant Pere Mes Baix, 47",
    "sg:city":"Barcelona",
    "sg:orig_category":"Reposter\u00cdas",
    "sg:phone":"+34 933 19 20 25",
    "sg:postcode":"08003",
    "sg:province":"Barcelona",
    "wof:name":"Camps Aibar S.l.",
    "wof:placetype":"venue"
},
  "geometry": {"coordinates":[2.1780059338,41.3879470825],"type":"Point"}
}