{
  "type": "Feature",
  "properties": {
    "addr:full":"Carr Arbres, 8 Badalona Barcelona 08912",
    "addr:housenumber":"8",
    "addr:postcode":"08912",
    "addr:street":"Carr Arbres",
    "iso:country":"ES",
    "sg:address":"Carr Arbres, 8",
    "sg:city":"Badalona",
    "sg:orig_category":"Bisuter\u00cda, Joyer\u00cda, Relojer\u00cda (al Por Menor)",
    "sg:phone":"+34 933 89 23 15",
    "sg:postcode":"08912",
    "sg:province":"Barcelona",
    "wof:name":"Pardo Garcia Emilio",
    "wof:placetype":"venue"
},
  "geometry": {"coordinates":[2.2463190556,41.44789505],"type":"Point"}
}