{
  "type": "Feature",
  "properties": {
    "iso:country":"ES",
    "sg:address":"Carrer de Mina, 12",
    "sg:city":"Hospitalet Llobregat",
    "sg:orig_category":"Promotores Constructores",
    "sg:phone":"+34 934 38 97 55",
    "sg:postcode":"08906",
    "sg:province":"Barcelona",
    "wof:name":"Suleman S.l.",
    "wof:placetype":"venue"
},
  "geometry": {"coordinates":[2.1009459496,41.3721885681],"type":"Point"}
}