{
  "type": "Feature",
  "properties": {
    "iso:country":"ES",
    "sg:address":"Calle de Pi\u00d1a Delgado, 3",
    "sg:city":"Marbella",
    "sg:orig_category":"Administradores De Bienes Y Delegados De Comunidades De Propietarios",
    "sg:phone":"+34 952 82 04 54",
    "sg:postcode":"29600",
    "sg:province":"M\u00e1laga",
    "wof:name":"Administraciones Y Servicios Oasis S.c.",
    "wof:placetype":"venue"
},
  "geometry": {"coordinates":[-4.8881444931,36.5141067505],"type":"Point"}
}