{
  "type": "Feature",
  "properties": {
    "iso:country":"ES",
    "sg:address":"Touring Etorbidea, S/n",
    "sg:city":"Errenteria",
    "sg:orig_category":"Asociaciones Y Clubs Deportivos",
    "sg:phone":"+34 943 52 43 81",
    "sg:postcode":"20100",
    "sg:province":"Guip\u00f9zcoa",
    "wof:name":"Club Deportivo Union Txiki",
    "wof:placetype":"venue"
},
  "geometry": {"coordinates":[-1.8938230276,43.3094978333],"type":"Point"}
}