{
  "type": "Feature",
  "properties": {
    "iso:country":"ES",
    "sg:address":"Calle de Almenara, 7",
    "sg:city":"Vall D'uixo",
    "sg:orig_category":"Promotores Constructores",
    "sg:phone":"+34 964 69 68 41",
    "sg:postcode":"12600",
    "sg:province":"Castell\u00f3n",
    "wof:name":"Construcciones Talante S.l.",
    "wof:placetype":"venue"
},
  "geometry": {"coordinates":[-0.2341658026,39.8215255737],"type":"Point"}
}