{
  "type": "Feature",
  "properties": {
    "addr:full":"Calle de Artagan, 11 Getxo Vizcaya 48990",
    "addr:housenumber":"11",
    "addr:postcode":"48990",
    "addr:street":"Calle De Artagan",
    "iso:country":"ES",
    "sg:address":"Calle de Artagan, 11",
    "sg:city":"Getxo",
    "sg:orig_category":"Inform\u00c1tica: Consultores",
    "sg:phone":"+34 944 60 26 67",
    "sg:postcode":"48990",
    "sg:province":"Vizcaya",
    "wof:name":"Servicios Empresariales Deiga, S.c.",
    "wof:placetype":"venue"
},
  "geometry": {"coordinates":[-3.0166959763,43.3545913696],"type":"Point"}
}