{
  "type": "Feature",
  "properties": {
    "addr:full":"Calle de Cid, 6 Miranda Ebro Burgos 09200",
    "addr:housenumber":"6",
    "addr:postcode":"09200",
    "addr:street":"Calle De Cid",
    "iso:country":"ES",
    "sg:address":"Calle de Cid, 6",
    "sg:city":"Miranda Ebro",
    "sg:orig_category":"Cajas De Ahorro",
    "sg:phone":"+34 947 33 06 43",
    "sg:postcode":"09200",
    "sg:province":"Burgos",
    "sg:website":"www.cajanavarra.es",
    "wof:name":"Caja De Ahorros Y Monte De Piedad De Navarra",
    "wof:placetype":"venue"
},
  "geometry": {"coordinates":[-2.9447746277,42.686630249],"type":"Point"}
}