{
  "type": "Feature",
  "properties": {
    "addr:full":"Calle de Trinidad, 15 Urroz Navarra 31420",
    "addr:housenumber":"15",
    "addr:postcode":"31420",
    "addr:street":"Calle De Trinidad",
    "iso:country":"ES",
    "sg:address":"Calle de Trinidad, 15",
    "sg:city":"Urroz",
    "sg:orig_category":"Material Y Herramientas Agr\u00cdcolas",
    "sg:phone":"+34 948 33 81 03",
    "sg:postcode":"31420",
    "sg:province":"Navarra",
    "wof:name":"Hernandez Larramendi Jose Maria Y Juan Luis S.cv.",
    "wof:placetype":"venue"
},
  "geometry": {"coordinates":[-1.4608000517,42.7779083252],"type":"Point"}
}