{
  "type": "Feature",
  "properties": {
    "addr:full":"Plaz Manises, 4 Valencia Valencia 46...",
    "addr:housenumber":"4",
    "addr:street":"Plaz Manises;Valencia",
    "iso:country":"ES",
    "sg:address":"Plaz Manises, 4",
    "sg:city":"Valencia",
    "sg:orig_category":"Ense\u00d1anza, Formaci\u00d3n Profesional: Aprendizaje",
    "sg:phone":"+34 963 88 25 00",
    "sg:postcode":"46...",
    "sg:province":"Valencia",
    "sg:website":"www.dva.gva.es",
    "wof:name":"Diputacio Provincial De Valencia",
    "wof:placetype":"venue"
},
  "geometry": {"coordinates":[-0.3766799867,39.4768714905],"type":"Point"}
}