{
  "type": "Feature",
  "properties": {
    "addr:full":"Barr San Roman Virgen Del Mar, 31 San Roman Cantabria 39012",
    "addr:housenumber":"31",
    "addr:postcode":"39012",
    "addr:street":"Del Mar;San Roman",
    "iso:country":"ES",
    "sg:address":"Barr San Roman Virgen Del Mar, 31",
    "sg:city":"San Roman",
    "sg:orig_category":"Venta, Instalaci\u00d3n De Calefacci\u00d3n",
    "sg:phone":"+34 942 33 35 63",
    "sg:postcode":"39012",
    "sg:province":"Cantabria",
    "wof:name":"Fontaneria Y Calefaccion Agustin S.l.",
    "wof:placetype":"venue"
},
  "geometry": {"coordinates":[-3.8701729774,43.4666824341],"type":"Point"}
}