{
  "type": "Feature",
  "properties": {
    "iso:country":"ES",
    "sg:address":"Estacion Ferrocarril, 3",
    "sg:city":"Denia",
    "sg:orig_category":"Ortopedia General",
    "sg:phone":"+34 965 78 47 51",
    "sg:postcode":"03700",
    "sg:province":"Alicante",
    "wof:name":"Ortopedia Paris S.l.",
    "wof:placetype":"venue"
},
  "geometry": {"coordinates":[0.1114400029,38.8428153992],"type":"Point"}
}