{
  "type": "Feature",
  "properties": {
    "iso:country":"ES",
    "sg:address":"Calle de Manuel De Falla, 3",
    "sg:city":"Villa Don Fadrique",
    "sg:orig_category":"Mec\u00c1nico Del Autom\u00d3vil",
    "sg:phone":"+34 925 19 56 85",
    "sg:postcode":"45850",
    "sg:province":"Toledo",
    "wof:name":"Nieto Manzanero Santiago",
    "wof:placetype":"venue"
},
  "geometry": {"coordinates":[-3.2137889862,39.6137313843],"type":"Point"}
}