{
  "type": "Feature",
  "properties": {
    "iso:country":"ES",
    "sg:address":"Calle de Doctor Mara\u00d1on, 6",
    "sg:city":"Cartagena",
    "sg:orig_category":"Ingeniero",
    "sg:phone":"+34 968 52 90 75",
    "sg:postcode":"30204",
    "sg:province":"Murcia",
    "wof:name":"Conesa Tejerina Alfredo",
    "wof:placetype":"venue"
},
  "geometry": {"coordinates":[-0.9919490218,37.6061210632],"type":"Point"}
}