{
  "type": "Feature",
  "properties": {
    "addr:full":"Calle de Anochecer, 2 Pozuelo De Alarcon Madrid 28223",
    "addr:housenumber":"2",
    "addr:postcode":"28223",
    "addr:street":"Calle De Anochecer",
    "iso:country":"ES",
    "sg:address":"Calle de Anochecer, 2",
    "sg:city":"Pozuelo De Alarcon",
    "sg:orig_category":"Audiovisuales (producci\u00d3n, Edici\u00d3n, Realizaci\u00d3n)",
    "sg:phone":"+34 913 51 35 51",
    "sg:postcode":"28223",
    "sg:province":"Madrid",
    "sg:website":"www.spika.es",
    "wof:name":"Spika Films S.a.",
    "wof:placetype":"venue"
},
  "geometry": {"coordinates":[-3.8126926422,40.4435768127],"type":"Point"}
}