{
  "type": "Feature",
  "properties": {
    "iso:country":"ES",
    "sg:address":"Calle de Gregorio Benitez, 16",
    "sg:city":"Madrid",
    "sg:orig_category":"Farmacias",
    "sg:phone":"+34 917 59 10 42",
    "sg:postcode":"28043",
    "sg:province":"Madrid",
    "wof:name":"Uguina Zamorano Maria Pilar",
    "wof:placetype":"venue"
},
  "geometry": {"coordinates":[-3.6487369537,40.4502677917],"type":"Point"}
}