{
  "type": "Feature",
  "properties": {
    "addr:full":"Calle de Maestro Aguilar, 29 Valencia Valencia 46006",
    "addr:housenumber":"29",
    "addr:postcode":"46006",
    "addr:street":"Calle De Maestro Aguilar",
    "iso:country":"ES",
    "sg:address":"Calle de Maestro Aguilar, 29",
    "sg:city":"Valencia",
    "sg:orig_category":"Sociedades, Compa\u00d1\u00cdas Aseguradoras",
    "sg:phone":"+34 963 16 31 10",
    "sg:postcode":"46006",
    "sg:province":"Valencia",
    "wof:name":"Iba\u00f1ez Furio Carmen",
    "wof:placetype":"venue"
},
  "geometry": {"coordinates":[-0.3693029881,39.4600601196],"type":"Point"}
}