{
  "type": "Feature",
  "properties": {
    "addr:full":"Carrer de Pensaments, 25 Vilafortuny Tarragona 43850",
    "addr:housenumber":"25",
    "addr:postcode":"43850",
    "addr:street":"Carrer De Pensaments",
    "iso:country":"ES",
    "sg:address":"Carrer de Pensaments, 25",
    "sg:city":"Vilafortuny",
    "sg:orig_category":"Arquitectos",
    "sg:phone":"+34 977 36 26 37",
    "sg:postcode":"43850",
    "sg:province":"Tarragona",
    "wof:name":"Nu\u00f1ez Lopez Ulises",
    "wof:placetype":"venue"
},
  "geometry": {"coordinates":[1.0909949541,41.074798584],"type":"Point"}
}