{
  "type": "Feature",
  "properties": {
    "addr:full":"Calle de Mikel Zarate, 2 Mallabia Vizcaya 48269",
    "addr:housenumber":"2",
    "addr:postcode":"48269",
    "addr:street":"Calle De Mikel Zarate",
    "iso:country":"ES",
    "sg:address":"Calle de Mikel Zarate, 2",
    "sg:city":"Mallabia",
    "sg:orig_category":"Aparcamientos (infraestructuras, Accesorios)",
    "sg:phone":"+34 943 17 05 39",
    "sg:postcode":"48269",
    "sg:province":"Vizcaya",
    "wof:name":"Garitaonandia Alcibar Jose Luis",
    "wof:placetype":"venue"
},
  "geometry": {"coordinates":[-2.5289518833,43.1894378662],"type":"Point"}
}