{
  "type": "Feature",
  "properties": {
    "addr:full":"Carrer de Constancia, 11 Esplugues Llobregat Barcelona 08950",
    "addr:housenumber":"11",
    "addr:postcode":"08950",
    "addr:street":"Carrer De Constancia",
    "iso:country":"ES",
    "sg:address":"Carrer de Constancia, 11",
    "sg:city":"Esplugues Llobregat",
    "sg:orig_category":"Electricidad: Instaladores",
    "sg:phone":"+34 934 73 97 94",
    "sg:postcode":"08950",
    "sg:province":"Barcelona",
    "wof:name":"Batista Manzano Alex",
    "wof:placetype":"venue"
},
  "geometry": {"coordinates":[2.0924859047,41.3747024536],"type":"Point"}
}