{
  "type": "Feature",
  "properties": {
    "addr:full":"Carr Sant Antoni, 112 Figueres Girona 17600",
    "addr:housenumber":"112",
    "addr:postcode":"17600",
    "addr:street":"Carr Sant Antoni",
    "iso:country":"ES",
    "sg:address":"Carr Sant Antoni, 112",
    "sg:city":"Figueres",
    "sg:orig_category":"Centros Empresariales",
    "sg:phone":"+34 972 50 22 60",
    "sg:postcode":"17600",
    "sg:province":"Girona",
    "wof:name":"Serveis De Neteja Trip-trap S.l.",
    "wof:placetype":"venue"
},
  "geometry": {"coordinates":[2.9658069611,42.2622413635],"type":"Point"}
}