{
  "type": "Feature",
  "properties": {
    "iso:country":"ES",
    "sg:address":"Av Pau Casals, 32",
    "sg:city":"Jonquera",
    "sg:orig_category":"Mec\u00c1nico Del Autom\u00d3vil",
    "sg:phone":"+34 972 55 54 14",
    "sg:postcode":"17700",
    "sg:province":"Girona",
    "wof:name":"Garatge Pirineus C.b.",
    "wof:placetype":"venue"
},
  "geometry": {"coordinates":[2.8704330921,42.4247436523],"type":"Point"}
}