{
  "type": "Feature",
  "properties": {
    "iso:country":"ES",
    "sg:address":"Calle de Muralla Del Mar, 19",
    "sg:city":"Cartagena",
    "sg:orig_category":"Ingeniero",
    "sg:phone":"+34 968 52 23 66",
    "sg:postcode":"30202",
    "sg:province":"Murcia",
    "wof:name":"Navarro Paredes Juan Jose",
    "wof:placetype":"venue"
},
  "geometry": {"coordinates":[-0.9810565114,37.5987586975],"type":"Point"}
}