{
  "type": "Feature",
  "properties": {
    "addr:full":"Avda Enrique Tierno Galvan, 5 San Fernando De Henares Madrid 28830",
    "addr:housenumber":"5",
    "addr:postcode":"28830",
    "addr:street":"Avda Enrique Tierno Galvan",
    "iso:country":"ES",
    "sg:address":"Avda Enrique Tierno Galvan, 5",
    "sg:city":"San Fernando De Henares",
    "sg:orig_category":"Molduras, Junquillos, Listones Y Molduras Perforadas",
    "sg:phone":"+34 916 73 20 74",
    "sg:postcode":"28830",
    "sg:province":"Madrid",
    "wof:name":"Cytasa Comunicaciones S.l.",
    "wof:placetype":"venue"
},
  "geometry": {"coordinates":[-3.5333089828,40.4223709106],"type":"Point"}
}