{
  "type": "Feature",
  "properties": {
    "addr:full":"Carrer de Marina, 313 Barcelona Barcelona 08025",
    "addr:housenumber":"313",
    "addr:postcode":"08025",
    "addr:street":"Carrer De Marina",
    "iso:country":"ES",
    "sg:address":"Carrer de Marina, 313",
    "sg:city":"Barcelona",
    "sg:orig_category":"Centros Empresariales",
    "sg:phone":"+34 932 65 53 20",
    "sg:postcode":"08025",
    "sg:province":"Barcelona",
    "wof:name":"Asesoria Garcia Fuentes S.a.",
    "wof:placetype":"venue"
},
  "geometry": {"coordinates":[2.1708846092,41.4071807861],"type":"Point"}
}