{
  "type": "Feature",
  "properties": {
    "iso:country":"ES",
    "sg:address":"Serna, 35",
    "sg:city":"Salamanca",
    "sg:orig_category":"Bebidas",
    "sg:phone":"+34 923 21 55 47",
    "sg:postcode":"37008",
    "sg:province":"Salamanca",
    "wof:name":"Casbega S.a.",
    "wof:placetype":"venue"
},
  "geometry": {"coordinates":[-5.6957888603,40.9548416138],"type":"Point"}
}