{
  "type": "Feature",
  "properties": {
    "iso:country":"ES",
    "sg:address":"Carrer de Mediodia, 70",
    "sg:city":"Vilanova Cami",
    "sg:orig_category":"Equipos De Extracci\u00d3n Centralizada",
    "sg:phone":"+34 938 03 14 44",
    "sg:postcode":"08788",
    "sg:province":"Barcelona",
    "wof:name":"Sistemac S.l.l.",
    "wof:placetype":"venue"
},
  "geometry": {"coordinates":[1.6405899525,41.5763664246],"type":"Point"}
}