{
  "type": "Feature",
  "properties": {
    "iso:country":"ES",
    "sg:address":"Calle de Salbatierrabide, 77",
    "sg:city":"Vitoria-gasteiz",
    "sg:orig_category":"Ingenier\u00cda, Centros De Estudios (diversos)",
    "sg:phone":"+34 945 13 48 83",
    "sg:postcode":"01007",
    "sg:province":"\u00c1lava",
    "wof:name":"Martinez De Marigorta Api\u00f1aniz Blanca",
    "wof:placetype":"venue"
},
  "geometry": {"coordinates":[-2.6830790043,42.8377723694],"type":"Point"}
}