{
  "type": "Feature",
  "properties": {
    "addr:full":"Calle de Camino Viejo De Malaga, S/n Velez-malaga M\u00e1laga 29700",
    "addr:postcode":"29700",
    "addr:street":"Calle De Camino Viejo De Malaga S / N Velez-Malaga Ma\u0301Laga",
    "iso:country":"ES",
    "sg:address":"Calle de Camino Viejo De Malaga, S/n",
    "sg:city":"Velez-malaga",
    "sg:orig_category":"F\u00c1bricas De Ladrillo Y Tejas",
    "sg:phone":"+34 952 50 25 79",
    "sg:postcode":"29700",
    "sg:province":"M\u00e1laga",
    "wof:name":"Nuestra Se\u00f1ora De Fatima S. A.",
    "wof:placetype":"venue"
},
  "geometry": {"coordinates":[-4.103509903,36.7748603821],"type":"Point"}
}