{
  "type": "Feature",
  "properties": {
    "iso:country":"ES",
    "sg:address":"Av Generalitat, 27",
    "sg:city":"Horta S. Joan",
    "sg:orig_category":"Albergues",
    "sg:phone":"+34 977 43 53 53",
    "sg:postcode":"43596",
    "sg:province":"Tarragona",
    "wof:name":"Sancho Grau Eva",
    "wof:placetype":"venue"
},
  "geometry": {"coordinates":[0.3155300021,40.9561080933],"type":"Point"}
}