{
  "type": "Feature",
  "properties": {
    "iso:country":"ES",
    "sg:address":"Calle de Concepcion, 9",
    "sg:city":"Albacete",
    "sg:orig_category":"Cl\u00cdnicas Dentales",
    "sg:phone":"+34 967 52 02 29",
    "sg:postcode":"02002",
    "sg:province":"Albacete",
    "wof:name":"Olaya Iniesta Joaquin",
    "wof:placetype":"venue"
},
  "geometry": {"coordinates":[-1.8547251225,38.9939956665],"type":"Point"}
}