{
  "type": "Feature",
  "properties": {
    "iso:country":"ES",
    "sg:address":"Calle de San Antonio, 9",
    "sg:city":"Villacedre",
    "sg:orig_category":"Materias Pl\u00c1sticas: Art\u00cdculos Para La Industria",
    "sg:phone":"+34 987 21 31 10",
    "sg:postcode":"24194",
    "sg:province":"Le\u00f3n",
    "wof:name":"Bolsas Y Papel Semar S.l.",
    "wof:placetype":"venue"
},
  "geometry": {"coordinates":[-5.585714817,42.5637283325],"type":"Point"}
}