{
  "type": "Feature",
  "properties": {
    "iso:country":"ES",
    "sg:address":"Calle de Manuel Mas, 14",
    "sg:city":"Talayuela",
    "sg:orig_category":"Loter\u00cda Y T\u00d3mbola",
    "sg:phone":"+34 927 55 12 79",
    "sg:postcode":"10310",
    "sg:province":"C\u00e1ceres",
    "wof:name":"Perez Perez Patro",
    "wof:placetype":"venue"
},
  "geometry": {"coordinates":[-5.6099610329,39.9903488159],"type":"Point"}
}