{
  "type": "Feature",
  "properties": {
    "iso:country":"ES",
    "sg:address":"Ctra Moral, Km. 0002,8",
    "sg:city":"Bola\u00e7os De Calatrava",
    "sg:orig_category":"Fabricaci\u00d3n De Muebles",
    "sg:phone":"+34 926 69 31 93",
    "sg:postcode":"13260",
    "sg:province":"Ciudad Real",
    "wof:name":"Hermanos Arreaza Almansa S.l.",
    "wof:placetype":"venue"
},
  "geometry": {"coordinates":[-3.6656041145,38.9035949707],"type":"Point"}
}