{
  "type": "Feature",
  "properties": {
    "iso:country":"ES",
    "sg:address":"Avgd De L'almaig, 85",
    "sg:city":"Ontinyent",
    "sg:orig_category":"Abogados",
    "sg:phone":"+34 962 91 42 25",
    "sg:postcode":"46870",
    "sg:province":"Valencia",
    "wof:name":"Cerda Gandia Maria Rosario",
    "wof:placetype":"venue"
},
  "geometry": {"coordinates":[-0.6036059856,38.8186798096],"type":"Point"}
}