{
  "type": "Feature",
  "properties": {
    "iso:country":"ES",
    "sg:address":"Avda Marques De Los Velez, 28",
    "sg:city":"Vista Alegre",
    "sg:orig_category":"Electrodom\u00c9sticos (al Por Menor)",
    "sg:phone":"+34 968 23 75 29",
    "sg:postcode":"30008",
    "sg:province":"Murcia",
    "wof:name":"Remle S.a.",
    "wof:placetype":"venue"
},
  "geometry": {"coordinates":[-1.129603982,37.9940490723],"type":"Point"}
}