{
  "type": "Feature",
  "properties": {
    "addr:full":"Avda Modesto Lafuente, 25 Palencia Palencia 34002",
    "addr:housenumber":"25",
    "addr:postcode":"34002",
    "addr:street":"Avda Modesto Lafuente",
    "iso:country":"ES",
    "sg:address":"Avda Modesto Lafuente, 25",
    "sg:city":"Palencia",
    "sg:orig_category":"Droguer\u00cdas (al Por Menor)",
    "sg:phone":"+34 979 72 01 47",
    "sg:postcode":"34002",
    "sg:province":"Palencia",
    "wof:name":"Bernado Alvarez Mercedes",
    "wof:placetype":"venue"
},
  "geometry": {"coordinates":[-4.5272121429,42.0044059753],"type":"Point"}
}