{
  "type": "Feature",
  "properties": {
    "addr:full":"Garagartza Auzoa, 52 Garagartza Guip\u00f9zcoa 20509",
    "addr:housenumber":"52",
    "addr:postcode":"20509",
    "addr:street":"Garagartza Auzoa;Guipu\u0300Zcoa",
    "iso:country":"ES",
    "sg:address":"Garagartza Auzoa, 52",
    "sg:city":"Garagartza",
    "sg:orig_category":"Explotaci\u00d3n De Canteras",
    "sg:phone":"+34 943 71 24 03",
    "sg:postcode":"20509",
    "sg:province":"Guip\u00f9zcoa",
    "wof:name":"Cantera Y Calera De Cobate S. L.",
    "wof:placetype":"venue"
},
  "geometry": {"coordinates":[-2.5292959213,43.0634117126],"type":"Point"}
}