{
  "type": "Feature",
  "properties": {
    "addr:full":"Pais Vasco, 90 Villarcayo Burgos 09550",
    "addr:housenumber":"90",
    "addr:postcode":"09550",
    "addr:street":"Pais Vasco",
    "iso:country":"ES",
    "sg:address":"Pais Vasco, 90",
    "sg:city":"Villarcayo",
    "sg:orig_category":"Empresas De Carpinter\u00cda De Madera",
    "sg:phone":"+34 947 13 04 75",
    "sg:postcode":"09550",
    "sg:province":"Burgos",
    "wof:name":"Gomez Pereda Roberto",
    "wof:placetype":"venue"
},
  "geometry": {"coordinates":[-3.5783491135,42.9255943298],"type":"Point"}
}