{
  "type": "Feature",
  "properties": {
    "iso:country":"ES",
    "sg:address":"Ptda Altabix, S/n",
    "sg:city":"Elche",
    "sg:orig_category":"Empresas De Carpinter\u00cda",
    "sg:phone":"+34 965 45 37 05",
    "sg:postcode":"03291",
    "sg:province":"Alicante",
    "wof:name":"Iba\u00f1ez Garcia Carlos",
    "wof:placetype":"venue"
},
  "geometry": {"coordinates":[-0.6765189767,38.2994346619],"type":"Point"}
}