{
  "type": "Feature",
  "properties": {
    "addr:full":"Rond Llevant, 42 Turo Del Mar Barcelona 08390",
    "addr:housenumber":"42",
    "addr:postcode":"08390",
    "addr:street":"Rond Llevant",
    "iso:country":"ES",
    "sg:address":"Rond Llevant, 42",
    "sg:city":"Turo Del Mar",
    "sg:orig_category":"Seguridad En El Trabajo Y Prevenci\u00d3n De Riesgos Laborales",
    "sg:phone":"+34 934 69 32 91",
    "sg:postcode":"08390",
    "sg:province":"Barcelona",
    "wof:name":"Calderon Prevencion De Riesgos Laborales",
    "wof:placetype":"venue"
},
  "geometry": {"coordinates":[2.2786700726,41.4704208374],"type":"Point"}
}