{
  "type": "Feature",
  "properties": {
    "iso:country":"ES",
    "sg:address":"Calle de Barrenkale, 1",
    "sg:city":"Mutriku",
    "sg:orig_category":"Herboristas (al Por Menor)",
    "sg:phone":"+34 943 60 41 24",
    "sg:postcode":"20830",
    "sg:province":"Guip\u00f9zcoa",
    "wof:name":"Azcarate Calzacorta Sagrario",
    "wof:placetype":"venue"
},
  "geometry": {"coordinates":[-2.3852889538,43.3069992065],"type":"Point"}
}