{
  "type": "Feature",
  "properties": {
    "addr:full":"Ptda La Marquesa, S/n Alberic Valencia 46260",
    "addr:housenumber":"s / n",
    "addr:postcode":"46260",
    "addr:street":"Ptda La Marquesa",
    "iso:country":"ES",
    "sg:address":"Ptda La Marquesa, S/n",
    "sg:city":"Alberic",
    "sg:orig_category":"Explotaci\u00d3n De Canteras",
    "sg:phone":"+34 962 44 29 77",
    "sg:postcode":"46260",
    "sg:province":"Valencia",
    "wof:name":"Aricar S.a.",
    "wof:placetype":"venue"
},
  "geometry": {"coordinates":[-0.5352355838,39.1219215393],"type":"Point"}
}