{
  "type": "Feature",
  "properties": {
    "addr:full":"Rua Galicia (de), 3 Vilalba Lugo 27800",
    "addr:housenumber":"3",
    "addr:postcode":"27800",
    "addr:street":"Rua Galicia De",
    "iso:country":"ES",
    "sg:address":"Rua Galicia (de), 3",
    "sg:city":"Vilalba",
    "sg:orig_category":"Confecci\u00d3n (fabricaci\u00d3n, Al Por Mayor)",
    "sg:phone":"+34 982 51 00 59",
    "sg:postcode":"27800",
    "sg:province":"Lugo",
    "wof:name":"Castro Ferreiro Luis",
    "wof:placetype":"venue"
},
  "geometry": {"coordinates":[-7.6814641953,43.2966461182],"type":"Point"}
}