{
  "type": "Feature",
  "properties": {
    "iso:country":"ES",
    "sg:address":"Calle de Iparraguirre, 19",
    "sg:city":"Bilbao",
    "sg:orig_category":"Suministros Y Materiales Industriales",
    "sg:phone":"+34 944 23 57 65",
    "sg:postcode":"48009",
    "sg:province":"Vizcaya",
    "wof:name":"Suministros De Golf Sl",
    "wof:placetype":"venue"
},
  "geometry": {"coordinates":[-2.9356884956,43.264995575],"type":"Point"}
}