{
  "type": "Feature",
  "properties": {
    "iso:country":"ES",
    "sg:address":"Virgen Del Puy, 6",
    "sg:city":"Iru\u00f1a",
    "sg:orig_category":"Lencer\u00cda Femenina, Corseter\u00cda, Trajes De Ba\u00d1o (al Por Menor)",
    "sg:phone":"+34 948 17 38 21",
    "sg:postcode":"31011",
    "sg:province":"Navarra",
    "wof:name":"Gomez Martin Encarnacion Y Fernandez Vaquero Marcelino S.cv.",
    "wof:placetype":"venue"
},
  "geometry": {"coordinates":[-1.6597859859,42.8163108826],"type":"Point"}
}