{
  "type": "Feature",
  "properties": {
    "addr:full":"Carrer de Panta De Tremp, 63 Barcelona Barcelona 08032",
    "addr:housenumber":"63",
    "addr:postcode":"08032",
    "addr:street":"Carrer De Panta;Tremp",
    "iso:country":"ES",
    "sg:address":"Carrer de Panta De Tremp, 63",
    "sg:city":"Barcelona",
    "sg:orig_category":"Farmacias",
    "sg:phone":"+34 934 20 80 35",
    "sg:postcode":"08032",
    "sg:province":"Barcelona",
    "wof:name":"Bosch De Basea Cusco Maria Dolors",
    "wof:placetype":"venue"
},
  "geometry": {"coordinates":[2.1511189938,41.4259338379],"type":"Point"}
}