{
  "type": "Feature",
  "properties": {
    "addr:full":"Calle de Ramon Y Cajal, 2 Donostia-san Sebastian Guip\u00f9zcoa 20002",
    "addr:housenumber":"2",
    "addr:postcode":"20002",
    "addr:street":"Calle De Ramon Y Cajal",
    "iso:country":"ES",
    "sg:address":"Calle de Ramon Y Cajal, 2",
    "sg:city":"Donostia-san Sebastian",
    "sg:orig_category":"Agencias De Viajes",
    "sg:phone":"+34 943 29 70 71",
    "sg:postcode":"20002",
    "sg:province":"Guip\u00f9zcoa",
    "wof:name":"Viajes Zurriola S.l.l",
    "wof:placetype":"venue"
},
  "geometry": {"coordinates":[-1.97615695,43.3247032166],"type":"Point"}
}