{
  "type": "Feature",
  "properties": {
    "addr:full":"Pasarell, 2 S. Antonio Benageber Valencia 46184",
    "addr:housenumber":"2",
    "addr:postcode":"46184",
    "addr:street":"Pasarell;S. Antonio Benageber",
    "iso:country":"ES",
    "sg:address":"Pasarell, 2",
    "sg:city":"S. Antonio Benageber",
    "sg:orig_category":"Muebles Y Accesorios Para Cocinas Y Cuartos De Ba\u00d1o (al Por Menor)",
    "sg:phone":"+34 961 35 08 91",
    "sg:postcode":"46184",
    "sg:province":"Valencia",
    "wof:name":"Pgm Cuines En Kit S.l.",
    "wof:placetype":"venue"
},
  "geometry": {"coordinates":[-0.5012540221,39.5620651245],"type":"Point"}
}