{
  "type": "Feature",
  "properties": {
    "iso:country":"ES",
    "sg:address":"Avda Madrid De, 14",
    "sg:city":"Donostia-san Sebastian",
    "sg:orig_category":"M\u00c9dicos: Evaluaci\u00d3n Y Tratamiento Del Dolor",
    "sg:phone":"+34 943 45 10 07",
    "sg:postcode":"20011",
    "sg:province":"Guip\u00f9zcoa",
    "wof:name":"Clinica Dental C.b.",
    "wof:placetype":"venue"
},
  "geometry": {"coordinates":[-1.9768630266,43.3043937683],"type":"Point"}
}