{
  "type": "Feature",
  "properties": {
    "addr:full":"Av Diagonal, 612 Barcelona Barcelona 08021",
    "addr:housenumber":"612",
    "addr:postcode":"08021",
    "addr:street":"Av Diagonal",
    "iso:country":"ES",
    "sg:address":"Av Diagonal, 612",
    "sg:city":"Barcelona",
    "sg:orig_category":"Promotores Constructores",
    "sg:phone":"+34 932 41 20 88",
    "sg:postcode":"08021",
    "sg:province":"Barcelona",
    "wof:name":"Profel S. A.",
    "wof:placetype":"venue"
},
  "geometry": {"coordinates":[2.1421809196,41.3926086426],"type":"Point"}
}