{
  "type": "Feature",
  "properties": {
    "addr:full":"Calle de Avila, 8 Bilbao Vizcaya 48012",
    "addr:housenumber":"8",
    "addr:postcode":"48012",
    "addr:street":"Calle De Avila",
    "iso:country":"ES",
    "sg:address":"Calle de Avila, 8",
    "sg:city":"Bilbao",
    "sg:orig_category":"Asociaciones Y Clubs Deportivos",
    "sg:phone":"+34 944 10 29 00",
    "sg:postcode":"48012",
    "sg:province":"Vizcaya",
    "wof:name":"Urtabi",
    "wof:placetype":"venue"
},
  "geometry": {"coordinates":[-2.9395740032,43.2567558289],"type":"Point"}
}