{
  "type": "Feature",
  "properties": {
    "iso:country":"ES",
    "sg:address":"Avda Constitucion, S/n",
    "sg:city":"Torneros Del Bernesga",
    "sg:orig_category":"Empresas De Carpinter\u00cda",
    "sg:phone":"+34 987 28 96 32",
    "sg:postcode":"24347",
    "sg:province":"Le\u00f3n",
    "sg:website":"www.paginasamarillas.es",
    "wof:name":"Oficios Varios Ofiplus S.l.",
    "wof:placetype":"venue"
},
  "geometry": {"coordinates":[-5.557161808,42.5250663757],"type":"Point"}
}