{
  "type": "Feature",
  "properties": {
    "iso:country":"ES",
    "sg:address":"Carrer de Jocs Florals, 66",
    "sg:city":"Barcelona",
    "sg:orig_category":"Agencias Y Agentes Comerciales, Representantes",
    "sg:phone":"+34 932 98 88 90",
    "sg:postcode":"08014",
    "sg:province":"Barcelona",
    "wof:name":"Oikos Tecnics S.l.",
    "wof:placetype":"venue"
},
  "geometry": {"coordinates":[2.1346719265,41.373462677],"type":"Point"}
}