{
  "type": "Feature",
  "properties": {
    "addr:full":"Calle de Bego\u00d1a, 46 Gijon Asturias 33206",
    "addr:housenumber":"46",
    "addr:postcode":"33206",
    "addr:street":"Calle De Begon\u0303A",
    "iso:country":"ES",
    "sg:address":"Calle de Bego\u00d1a, 46",
    "sg:city":"Gijon",
    "sg:orig_category":"Arquitectos",
    "sg:phone":"+34 985 17 04 32",
    "sg:postcode":"33206",
    "sg:province":"Asturias",
    "wof:name":"Diaz-moro Cuesta Ceferino Luis",
    "wof:placetype":"venue"
},
  "geometry": {"coordinates":[-5.6619591713,43.5401496887],"type":"Point"}
}