{
  "type": "Feature",
  "properties": {
    "addr:full":"Calle de Juan Hurtado De Mendoza, 9 Madrid Madrid 28036",
    "addr:housenumber":"9",
    "addr:postcode":"madrid;28036",
    "addr:street":"Calle De Juan Hurtado De Mendoza",
    "iso:country":"ES",
    "sg:address":"Calle de Juan Hurtado De Mendoza, 9",
    "sg:city":"Madrid",
    "sg:orig_category":"Masajes",
    "sg:phone":"+34 913 45 36 99",
    "sg:postcode":"28036",
    "sg:province":"Madrid",
    "sg:website":"www.fdg.es/usr/shiatsu\u00a7\u00a7",
    "wof:name":"Escuela Japonesa De Shiatsu Do S.l.",
    "wof:placetype":"venue"
},
  "geometry": {"coordinates":[-3.6876070499,40.4605751038],"type":"Point"}
}