{
  "type": "Feature",
  "properties": {
    "addr:full":"Calle de Cruz, 31 Alhaurin El Grande M\u00e1laga 29120",
    "addr:housenumber":"31",
    "addr:postcode":"29120",
    "addr:street":"Calle De Cruz",
    "iso:country":"ES",
    "sg:address":"Calle de Cruz, 31",
    "sg:city":"Alhaurin El Grande",
    "sg:orig_category":"Electrodom\u00c9sticos (al Por Menor)",
    "sg:phone":"+34 952 49 01 71",
    "sg:postcode":"29120",
    "sg:province":"M\u00e1laga",
    "wof:name":"Electro Imangen Hermanos Bravo S.l.",
    "wof:placetype":"venue"
},
  "geometry": {"coordinates":[-4.6878781319,36.6428756714],"type":"Point"}
}