{
  "type": "Feature",
  "properties": {
    "addr:full":"Avda Sant Agusti, 205 Cala De Bou Islas Baleares 07839",
    "addr:housenumber":"205",
    "addr:postcode":"07839",
    "addr:street":"Avda Sant Agusti;Baleares",
    "iso:country":"ES",
    "sg:address":"Avda Sant Agusti, 205",
    "sg:city":"Cala De Bou",
    "sg:orig_category":"Alquiler De Veh\u00cdculos: Turismos Y Utilitarios",
    "sg:phone":"+34 971 34 50 78",
    "sg:postcode":"07839",
    "sg:province":"Islas Baleares",
    "wof:name":"Management Turistico Balear S.l.",
    "wof:placetype":"venue"
},
  "geometry": {"coordinates":[1.3025970459,38.8642692566],"type":"Point"}
}