{
  "type": "Feature",
  "properties": {
    "addr:full":"Avda Galo Ponte, 12 S. Mateo Gallego Zaragoza 50840",
    "addr:housenumber":"12",
    "addr:postcode":"50840",
    "addr:street":"Avda Galo Ponte;S. Mateo Gallego",
    "iso:country":"ES",
    "sg:address":"Avda Galo Ponte, 12",
    "sg:city":"S. Mateo Gallego",
    "sg:orig_category":"Reposter\u00cdas",
    "sg:phone":"+34 976 68 40 16",
    "sg:postcode":"50840",
    "sg:province":"Zaragoza",
    "wof:name":"Rodriguez Gascon Luis",
    "wof:placetype":"venue"
},
  "geometry": {"coordinates":[-0.7655969858,41.8334236145],"type":"Point"}
}