{
  "type": "Feature",
  "properties": {
    "iso:country":"ES",
    "sg:address":"Carrer de Fran\u00c7a, 27",
    "sg:city":"Hospitalet Llobregat",
    "sg:orig_category":"Loter\u00cda Y T\u00d3mbola",
    "sg:phone":"+34 932 63 19 57",
    "sg:postcode":"08907",
    "sg:province":"Barcelona",
    "wof:name":"Jimenez Martinez Sergio",
    "wof:placetype":"venue"
},
  "geometry": {"coordinates":[2.1119699478,41.3554954529],"type":"Point"}
}