{
  "type": "Feature",
  "properties": {
    "iso:country":"ES",
    "sg:address":"Carr Francesc Layret, 135",
    "sg:city":"Badalona",
    "sg:orig_category":"Sociedades, Compa\u00d1\u00cdas Aseguradoras",
    "sg:phone":"+34 933 84 63 13",
    "sg:postcode":"08911",
    "sg:province":"Barcelona",
    "wof:name":"Tomeu Deulofeu Miquel",
    "wof:placetype":"venue"
},
  "geometry": {"coordinates":[2.2485899925,41.4512939453],"type":"Point"}
}