{
  "type": "Feature",
  "properties": {
    "addr:full":"Calle de Merindad De Sanguesa, 3 Burlada Navarra 31600",
    "addr:housenumber":"3",
    "addr:postcode":"31600",
    "addr:street":"Calle De Merindad;Sanguesa",
    "iso:country":"ES",
    "sg:address":"Calle de Merindad De Sanguesa, 3",
    "sg:city":"Burlada",
    "sg:orig_category":"Administrativo",
    "sg:phone":"+34 948 13 47 35",
    "sg:postcode":"31600",
    "sg:province":"Navarra",
    "wof:name":"Urbiola Saenz Martin Angel",
    "wof:placetype":"venue"
},
  "geometry": {"coordinates":[-1.6159720421,42.826461792],"type":"Point"}
}