{
  "type": "Feature",
  "properties": {
    "iso:country":"ES",
    "sg:address":"Calle de Flores Las, 12",
    "sg:city":"Arroyo De La Miel-benalmadena Costa",
    "sg:orig_category":"Reposter\u00cdas",
    "sg:phone":"+34 952 57 66 29",
    "sg:postcode":"29631",
    "sg:province":"M\u00e1laga",
    "wof:name":"Panificadora Migas S.l.",
    "wof:placetype":"venue"
},
  "geometry": {"coordinates":[-4.5337204933,36.6007881165],"type":"Point"}
}