{
  "type": "Feature",
  "properties": {
    "iso:country":"ES",
    "sg:address":"Carrer de Mossen Jacint Verdaguer, 33",
    "sg:city":"Masnou",
    "sg:orig_category":"Bebidas",
    "sg:phone":"+34 935 40 40 00",
    "sg:postcode":"08320",
    "sg:province":"Barcelona",
    "wof:name":"Piera Badia Francisco",
    "wof:placetype":"venue"
},
  "geometry": {"coordinates":[2.3103759289,41.4773635864],"type":"Point"}
}