{
  "type": "Feature",
  "properties": {
    "addr:full":"Calle de Villaamil, 5 Mostoles Madrid 28934",
    "addr:housenumber":"5",
    "addr:postcode":"28934",
    "addr:street":"Calle De Villaamil",
    "iso:country":"ES",
    "sg:address":"Calle de Villaamil, 5",
    "sg:city":"Mostoles",
    "sg:orig_category":"Fotocopias, Reprograf\u00cda",
    "sg:phone":"+34 916 17 37 57",
    "sg:postcode":"28934",
    "sg:province":"Madrid",
    "wof:name":"Heras Arellano Jesus Pablo",
    "wof:placetype":"venue"
},
  "geometry": {"coordinates":[-3.8673899174,40.3218307495],"type":"Point"}
}