{
  "type": "Feature",
  "properties": {
    "iso:country":"ES",
    "sg:address":"Avda Jesus Rescatado (de), 21",
    "sg:city":"Cordoba",
    "sg:orig_category":"Ropa Para Se\u00d1oras Y Caballeros (al Por Menor)",
    "sg:phone":"+34 957 25 08 28",
    "sg:postcode":"14007",
    "sg:province":"C\u00f3rdoba",
    "wof:name":"Garcia Torrico Eulalio",
    "wof:placetype":"venue"
},
  "geometry": {"coordinates":[-4.7597560883,37.8906364441],"type":"Point"}
}