{
  "type": "Feature",
  "properties": {
    "iso:country":"ES",
    "sg:address":"Calle de Ruiz De Alda, 26",
    "sg:city":"Moraleja",
    "sg:orig_category":"Transportes Por V\u00cdas Navegables",
    "sg:phone":"+34 927 51 58 79",
    "sg:postcode":"10840",
    "sg:province":"C\u00e1ceres",
    "wof:name":"Salvado Rodriguez Angel",
    "wof:placetype":"venue"
},
  "geometry": {"coordinates":[-6.6567220688,40.0661392212],"type":"Point"}
}