{
  "type": "Feature",
  "properties": {
    "iso:country":"ES",
    "sg:address":"Calle de Cirilo Santos, 44",
    "sg:city":"Santa Maria Del Paramo",
    "sg:orig_category":"Centros De Coordinaci\u00d3n",
    "sg:phone":"+34 987 35 01 26",
    "sg:postcode":"24240",
    "sg:province":"Le\u00f3n",
    "wof:name":"Perez Rodriguez Amelia",
    "wof:placetype":"venue"
},
  "geometry": {"coordinates":[-5.7498998642,42.3542861938],"type":"Point"}
}