{
  "type": "Feature",
  "properties": {
    "addr:full":"Avda Valencia, S/n Ibi Alicante 03440",
    "addr:housenumber":"s / n",
    "addr:postcode":"03440",
    "addr:street":"Avda Valencia",
    "iso:country":"ES",
    "sg:address":"Avda Valencia, S/n",
    "sg:city":"Ibi",
    "sg:orig_category":"Artes Gr\u00c1ficas, Artes Pl\u00c1sticas (curso)",
    "sg:phone":"+34 965 55 46 00",
    "sg:postcode":"03440",
    "sg:province":"Alicante",
    "wof:name":"Graficas Torres S. A.",
    "wof:placetype":"venue"
},
  "geometry": {"coordinates":[-0.5980730057,38.6172943115],"type":"Point"}
}