{
  "type": "Feature",
  "properties": {
    "iso:country":"ES",
    "sg:address":"Luga Poligono 16, S/n",
    "sg:city":"Llucmajor",
    "sg:orig_category":"Arquitectos",
    "sg:phone":"+34 971 66 91 76",
    "sg:postcode":"07620",
    "sg:province":"Islas Baleares",
    "wof:name":"Scheldors  Kirsa",
    "wof:placetype":"venue"
},
  "geometry": {"coordinates":[2.8897550106,39.486114502],"type":"Point"}
}