{
  "type": "Feature",
  "properties": {
    "addr:full":"Carr Mossen Ferran, 38 Seros Lleida 25183",
    "addr:housenumber":"38",
    "addr:postcode":"25183",
    "addr:street":"Carr Mossen Ferran",
    "iso:country":"ES",
    "sg:address":"Carr Mossen Ferran, 38",
    "sg:city":"Seros",
    "sg:orig_category":"Agentes Generales De Seguros",
    "sg:phone":"+34 973 78 02 97",
    "sg:postcode":"25183",
    "sg:province":"Lleida",
    "sg:website":"www.romiapujol.com",
    "wof:name":"Romia Pujol S.l.",
    "wof:placetype":"venue"
},
  "geometry": {"coordinates":[0.4143359959,41.4656867981],"type":"Point"}
}