{
  "type": "Feature",
  "properties": {
    "addr:full":"Calle de Padre Mozota, 19 Maria Huerva Zaragoza 50430",
    "addr:housenumber":"19",
    "addr:postcode":"50430",
    "addr:street":"Calle De Padre Mozota;Huerva",
    "iso:country":"ES",
    "sg:address":"Calle de Padre Mozota, 19",
    "sg:city":"Maria Huerva",
    "sg:orig_category":"Iglesia Cat\u00d3lica",
    "sg:phone":"+34 976 12 40 23",
    "sg:postcode":"50430",
    "sg:province":"Zaragoza",
    "wof:name":"Parroquia Ntra Sra De La Asuncion",
    "wof:placetype":"venue"
},
  "geometry": {"coordinates":[-0.9964290261,41.5375785828],"type":"Point"}
}