{
  "type": "Feature",
  "properties": {
    "addr:full":"Ctra Antigua De El Pardo A Fuencarral, Km. 0001,4 Madrid Madrid 28034",
    "addr:postcode":"28034",
    "addr:street":"Ctra Antigua De El;Km. 0001,4",
    "iso:country":"ES",
    "sg:address":"Ctra Antigua De El Pardo A Fuencarral, Km. 0001,4",
    "sg:city":"Madrid",
    "sg:orig_category":"Reciclaje, Desguace De Veh\u00cdculos",
    "sg:phone":"+34 917 34 01 09",
    "sg:postcode":"28034",
    "sg:province":"Madrid",
    "wof:name":"Azabal Desguaces S.l.",
    "wof:placetype":"venue"
},
  "geometry": {"coordinates":[-3.6978263855,40.4995040894],"type":"Point"}
}