{
  "type": "Feature",
  "properties": {
    "iso:country":"ES",
    "sg:address":"Avda Comuneros, 10",
    "sg:city":"Salamanca",
    "sg:orig_category":"Delegados, Agentes De Tr\u00c1nsito, Auxiliares De Transporte Internacional",
    "sg:phone":"+34 923 18 77 97",
    "sg:postcode":"37003",
    "sg:province":"Salamanca",
    "wof:name":"Vicente Rodriguez Vicente",
    "wof:placetype":"venue"
},
  "geometry": {"coordinates":[-5.6519980431,40.9684944153],"type":"Point"}
}