{
  "type": "Feature",
  "properties": {
    "iso:country":"ES",
    "sg:address":"Plaz Espa\u00d1a, 11",
    "sg:city":"Cantalejo",
    "sg:orig_category":"Bazares, Art\u00cdculos De Limpieza Y De Cocina (al Por Menor)",
    "sg:phone":"+34 921 52 02 35",
    "sg:postcode":"40320",
    "sg:province":"Segovia",
    "wof:name":"Calvo Matesanz Maria",
    "wof:placetype":"venue"
},
  "geometry": {"coordinates":[-3.9275488853,41.2580032349],"type":"Point"}
}