{
  "type": "Feature",
  "properties": {
    "addr:full":"Calle de Juan Ramon Jimenez, 30 Valencia Valencia 46006",
    "addr:housenumber":"30",
    "addr:postcode":"46006",
    "addr:street":"Calle De Juan Ramon Jimenez",
    "iso:country":"ES",
    "sg:address":"Calle de Juan Ramon Jimenez, 30",
    "sg:city":"Valencia",
    "sg:orig_category":"Panader\u00cdas, Panader\u00cdas",
    "sg:phone":"+34 963 33 94 61",
    "sg:postcode":"46006",
    "sg:province":"Valencia",
    "wof:name":"Puchol Garrigos Antonio",
    "wof:placetype":"venue"
},
  "geometry": {"coordinates":[-0.3752090037,39.4535140991],"type":"Point"}
}