{
  "type": "Feature",
  "properties": {
    "addr:full":"Av Duran I Sanpere, 3 Cervera Lleida 25200",
    "addr:housenumber":"3",
    "addr:postcode":"25200",
    "addr:street":"Av Duran I Sanpere",
    "iso:country":"ES",
    "sg:address":"Av Duran I Sanpere, 3",
    "sg:city":"Cervera",
    "sg:orig_category":"Agencias De Prensa E Informaci\u00d3n",
    "sg:phone":"+34 973 53 12 66",
    "sg:postcode":"25200",
    "sg:province":"Lleida",
    "wof:name":"Produccions Lleidatanes De Comunicacio S.l.",
    "wof:placetype":"venue"
},
  "geometry": {"coordinates":[1.2706270218,41.6673240662],"type":"Point"}
}