{
  "type": "Feature",
  "properties": {
    "addr:full":"Calle de Carmenes, 2 Zafra Badajoz 06300",
    "addr:housenumber":"2",
    "addr:postcode":"06300",
    "addr:street":"Calle De Carmenes",
    "iso:country":"ES",
    "sg:address":"Calle de Carmenes, 2",
    "sg:city":"Zafra",
    "sg:orig_category":"Asesor\u00cda Fiscal Y Jur\u00cddica",
    "sg:phone":"+34 924 55 04 80",
    "sg:postcode":"06300",
    "sg:province":"Badajoz",
    "wof:name":"Bru Bonilla S.l.",
    "wof:placetype":"venue"
},
  "geometry": {"coordinates":[-6.4118099213,38.41796875],"type":"Point"}
}