{
  "type": "Feature",
  "properties": {
    "addr:full":"Puerto, 4 Sada La Coru\u00f1a 15160",
    "addr:housenumber":"4",
    "addr:postcode":"15160",
    "addr:street":"Puerto;La",
    "iso:country":"ES",
    "sg:address":"Puerto, 4",
    "sg:city":"Sada",
    "sg:orig_category":"Transporte En General",
    "sg:phone":"+34 981 62 42 53",
    "sg:postcode":"15160",
    "sg:province":"La Coru\u00f1a",
    "wof:name":"Mercedes Montero Ascariz Y Otros S.c.",
    "wof:placetype":"venue"
},
  "geometry": {"coordinates":[-8.250453949,43.3578033447],"type":"Point"}
}