{
  "type": "Feature",
  "properties": {
    "iso:country":"ES",
    "sg:address":"Carrer de Tres Torres, 20",
    "sg:city":"Barcelona",
    "sg:orig_category":"Agencias Y Agentes Comerciales, Representantes",
    "sg:phone":"+34 932 04 01 57",
    "sg:postcode":"08017",
    "sg:province":"Barcelona",
    "sg:website":"www.caverin.com",
    "wof:name":"Caverin Solutions S.a.",
    "wof:placetype":"venue"
},
  "geometry": {"coordinates":[2.1322650909,41.3952522278],"type":"Point"}
}