{
  "type": "Feature",
  "properties": {
    "iso:country":"ES",
    "sg:address":"Carrer de Floridablanca, 121",
    "sg:city":"Barcelona",
    "sg:orig_category":"M\u00c9dicos: Estomatolog\u00cda",
    "sg:phone":"+34 934 24 02 56",
    "sg:postcode":"08011",
    "sg:province":"Barcelona",
    "wof:name":"Camargo Arizaga Hugo Javier",
    "wof:placetype":"venue"
},
  "geometry": {"coordinates":[2.1613409519,41.380821228],"type":"Point"}
}