{
  "type": "Feature",
  "properties": {
    "iso:country":"ES",
    "sg:address":"Av Hispamica, 7",
    "sg:city":"Lepe",
    "sg:orig_category":"Fabricaci\u00d3n, Venta, Instalaci\u00d3n De R\u00d3tulos, De R\u00d3tulos Luminosos",
    "sg:phone":"+34 959 38 32 77",
    "sg:postcode":"21440",
    "sg:province":"Huelva",
    "wof:name":"Fumador Jaime Rafael",
    "wof:placetype":"venue"
},
  "geometry": {"coordinates":[-7.2029190063,37.255241394],"type":"Point"}
}