{
  "type": "Feature",
  "properties": {
    "iso:country":"ES",
    "sg:address":"Calle de Evaristo Valle, 3",
    "sg:city":"Oviedo",
    "sg:orig_category":"Bisuter\u00cda, Joyer\u00cda, Relojer\u00cda (al Por Menor)",
    "sg:phone":"+34 985 11 86 81",
    "sg:postcode":"33011",
    "sg:province":"Asturias",
    "wof:name":"Rodriguez Martinez Jose Luis",
    "wof:placetype":"venue"
},
  "geometry": {"coordinates":[-5.8447151184,43.3692321777],"type":"Point"}
}