{
  "type": "Feature",
  "properties": {
    "addr:full":"Plaz Manuel Sanchis Guarner, 1 Valencia Valencia 46006",
    "addr:housenumber":"1",
    "addr:postcode":"46006",
    "addr:street":"Guarner",
    "iso:country":"ES",
    "sg:address":"Plaz Manuel Sanchis Guarner, 1",
    "sg:city":"Valencia",
    "sg:orig_category":"Inmobiliaria (agencias)",
    "sg:phone":"+34 963 33 45 29",
    "sg:postcode":"46006",
    "sg:province":"Valencia",
    "wof:name":"Construjesa 2000 S.a.",
    "wof:placetype":"venue"
},
  "geometry": {"coordinates":[-0.3751919866,39.456943512],"type":"Point"}
}