{
  "type": "Feature",
  "properties": {
    "addr:full":"Rua Angelo Colocci, 4 Lugo Lugo 27003",
    "addr:housenumber":"4",
    "addr:postcode":"27003",
    "addr:street":"Rua Angelo Colocci",
    "iso:country":"ES",
    "sg:address":"Rua Angelo Colocci, 4",
    "sg:city":"Lugo",
    "sg:orig_category":"Caf\u00c9s, Bares, Cervecer\u00cdas",
    "sg:phone":"+34 982 20 06 02",
    "sg:postcode":"27003",
    "sg:province":"Lugo",
    "wof:name":"Automaticos Vending Palace S.l.",
    "wof:placetype":"venue"
},
  "geometry": {"coordinates":[-7.5713210106,43.0234031677],"type":"Point"}
}