{
  "type": "Feature",
  "properties": {
    "addr:full":"Calle de Meira, 1 Coru\u00d1a La Coru\u00f1a 15010",
    "addr:housenumber":"1",
    "addr:postcode":"15010",
    "addr:street":"Calle De Meira;La Corun\u0303A",
    "iso:country":"ES",
    "sg:address":"Calle de Meira, 1",
    "sg:city":"Coru\u00d1a",
    "sg:orig_category":"Bisuter\u00cda, Joyer\u00cda, Relojer\u00cda (al Por Menor)",
    "sg:phone":"+34 981 26 76 38",
    "sg:postcode":"15010",
    "sg:province":"La Coru\u00f1a",
    "wof:name":"Casas Lopez Francisco",
    "wof:placetype":"venue"
},
  "geometry": {"coordinates":[-8.4196214676,43.3617744446],"type":"Point"}
}