{
  "type": "Feature",
  "properties": {
    "iso:country":"ES",
    "sg:address":"Calle de Velazquez, 8",
    "sg:city":"Oviedo",
    "sg:orig_category":"Mec\u00c1nico Del Autom\u00d3vil",
    "sg:phone":"+34 985 29 03 73",
    "sg:postcode":"33011",
    "sg:province":"Asturias",
    "wof:name":"Borrego Huergo Alejandro Jesus",
    "wof:placetype":"venue"
},
  "geometry": {"coordinates":[-5.8376951218,43.3687973022],"type":"Point"}
}