{
  "type": "Feature",
  "properties": {
    "iso:country":"ES",
    "sg:address":"Calle de San Prudencio, 7",
    "sg:city":"Vitoria-gasteiz",
    "sg:orig_category":"Abogados",
    "sg:phone":"+34 945 14 60 62",
    "sg:postcode":"01005",
    "sg:province":"\u00c1lava",
    "wof:name":"Villegas Merino Jesus Maria",
    "wof:placetype":"venue"
},
  "geometry": {"coordinates":[-2.6732070446,42.8442611694],"type":"Point"}
}