{
  "type": "Feature",
  "properties": {
    "iso:country":"ES",
    "sg:address":"Rbla Rambla, 109",
    "sg:city":"Sabadell",
    "sg:orig_category":"Doctores En Medicina",
    "sg:phone":"+34 937 26 59 58",
    "sg:postcode":"08202",
    "sg:province":"Barcelona",
    "wof:name":"Griera Alvares-castrillon Ignacio",
    "wof:placetype":"venue"
},
  "geometry": {"coordinates":[2.1108059883,41.5432624817],"type":"Point"}
}