{
  "type": "Feature",
  "properties": {
    "addr:full":"Plaz Profesor Tamarit Olmos, 16 Valencia Valencia 46010",
    "addr:housenumber":"16",
    "addr:postcode":"46010",
    "addr:street":"Plaz Profesor Tamarit Olmos",
    "iso:country":"ES",
    "sg:address":"Plaz Profesor Tamarit Olmos, 16",
    "sg:city":"Valencia",
    "sg:orig_category":"Centros Empresariales",
    "sg:phone":"+34 963 93 42 03",
    "sg:postcode":"46010",
    "sg:province":"Valencia",
    "wof:name":"Ytapwana S.l.",
    "wof:placetype":"venue"
},
  "geometry": {"coordinates":[-0.3628847003,39.4802703857],"type":"Point"}
}