{
  "type": "Feature",
  "properties": {
    "iso:country":"ES",
    "sg:address":"Calle de Jaen, 23",
    "sg:city":"Pozoblanco",
    "sg:orig_category":"Empresarios",
    "sg:phone":"+34 957 77 05 41",
    "sg:postcode":"14400",
    "sg:province":"C\u00f3rdoba",
    "wof:name":"Amor Castillo Francisco",
    "wof:placetype":"venue"
},
  "geometry": {"coordinates":[-4.8537101746,38.3783378601],"type":"Point"}
}