{
  "type": "Feature",
  "properties": {
    "iso:country":"ES",
    "sg:address":"Calle de Andaquilla, S/n",
    "sg:city":"Santa Eulalia",
    "sg:orig_category":"Peluquer\u00cdas, Peluquer\u00cda Mixta",
    "sg:phone":"+34 978 86 01 56",
    "sg:postcode":"44360",
    "sg:province":"Teruel",
    "wof:name":"Ubeda Abril Maria Isabel",
    "wof:placetype":"venue"
},
  "geometry": {"coordinates":[-1.3140772581,40.5689125061],"type":"Point"}
}