{
  "type": "Feature",
  "properties": {
    "addr:full":"Calle de Progreso, 13 Ayerbe Huesca 22800",
    "addr:housenumber":"13",
    "addr:postcode":"22800",
    "addr:street":"Calle De Progreso",
    "iso:country":"ES",
    "sg:address":"Calle de Progreso, 13",
    "sg:city":"Ayerbe",
    "sg:orig_category":"Delegados, Agentes De Tr\u00c1nsito, Auxiliares De Transporte Internacional",
    "sg:phone":"+34 974 38 01 24",
    "sg:postcode":"22800",
    "sg:province":"Huesca",
    "wof:name":"Sarasa Hermanos S. L.",
    "wof:placetype":"venue"
},
  "geometry": {"coordinates":[-0.6870099902,42.2755775452],"type":"Point"}
}