{
  "type": "Feature",
  "properties": {
    "addr:full":"Via Massague, 105 Sabadell Barcelona 08201",
    "addr:housenumber":"105",
    "addr:postcode":"08201",
    "addr:street":"Via Massague",
    "iso:country":"ES",
    "sg:address":"Via Massague, 105",
    "sg:city":"Sabadell",
    "sg:orig_category":"Bancos",
    "sg:phone":"+34 937 26 34 22",
    "sg:postcode":"08201",
    "sg:province":"Barcelona",
    "sg:website":"www.grupobancosabadell.com",
    "wof:name":"Banc Sabadell S.a.",
    "wof:placetype":"venue"
},
  "geometry": {"coordinates":[2.1062591076,41.5519142151],"type":"Point"}
}