{
  "type": "Feature",
  "properties": {
    "addr:full":"Avda Carmen Martin Gaite, 64 Leganes Madrid 28919",
    "addr:housenumber":"64",
    "addr:postcode":"28919",
    "addr:street":"Avda Carmen Martin Gaite",
    "iso:country":"ES",
    "sg:address":"Avda Carmen Martin Gaite, 64",
    "sg:city":"Leganes",
    "sg:orig_category":"Papeler\u00cdas, Librer\u00cdas",
    "sg:phone":"+34 916 88 71 81",
    "sg:postcode":"28919",
    "sg:province":"Madrid",
    "wof:name":"Comercial Chocolin S.l.",
    "wof:placetype":"venue"
},
  "geometry": {"coordinates":[-3.7416889668,40.3452110291],"type":"Point"}
}