{
  "type": "Feature",
  "properties": {
    "addr:full":"Calle de Dr Santiago Ramon Y Cajal, 16 Guadalajara Guadalajara 19001",
    "addr:housenumber":"16",
    "addr:postcode":"19001",
    "addr:street":"Calle De Dr Santiago Ramon Y Cajal",
    "iso:country":"ES",
    "sg:address":"Calle de Dr Santiago Ramon Y Cajal, 16",
    "sg:city":"Guadalajara",
    "sg:orig_category":"Muebles, Minoristas",
    "sg:phone":"+34 949 21 14 40",
    "sg:postcode":"19001",
    "sg:province":"Guadalajara",
    "wof:name":"Tudecora Cb",
    "wof:placetype":"venue"
},
  "geometry": {"coordinates":[-3.162266016,40.6335525513],"type":"Point"}
}