{
  "type": "Feature",
  "properties": {
    "iso:country":"ES",
    "sg:address":"Calle de Ferroviarios, 57",
    "sg:city":"Madrid",
    "sg:orig_category":"Autom\u00d3viles Y Camiones",
    "sg:phone":"+34 914 75 76 27",
    "sg:postcode":"28026",
    "sg:province":"Madrid",
    "wof:name":"Taller 57 C.b.",
    "wof:placetype":"venue"
},
  "geometry": {"coordinates":[-3.7046599388,40.3841743469],"type":"Point"}
}