{
  "type": "Feature",
  "properties": {
    "addr:full":"Avda Alcalde Manuel Platas Varela, 215 Vilarrodis La Coru\u00f1a 15141",
    "addr:housenumber":"215",
    "addr:postcode":"15141",
    "addr:street":"Avda Alcalde Manuel Platas Varela;La Corun\u0303A",
    "iso:country":"ES",
    "sg:address":"Avda Alcalde Manuel Platas Varela, 215",
    "sg:city":"Vilarrodis",
    "sg:orig_category":"Montaje (empresas De)",
    "sg:phone":"+34 981 64 18 31",
    "sg:postcode":"15141",
    "sg:province":"La Coru\u00f1a",
    "wof:name":"Log Y Marp S.l.",
    "wof:placetype":"venue"
},
  "geometry": {"coordinates":[-8.4752206802,43.323600769],"type":"Point"}
}