{
  "type": "Feature",
  "properties": {
    "addr:full":"Calle de Arzobispo Guerrero, 15 Granada Granada 18015",
    "addr:housenumber":"15",
    "addr:postcode":"18015",
    "addr:street":"Calle De Arzobispo Guerrero",
    "iso:country":"ES",
    "sg:address":"Calle de Arzobispo Guerrero, 15",
    "sg:city":"Granada",
    "sg:orig_category":"Librer\u00cdas",
    "sg:phone":"+34 958 20 45 32",
    "sg:postcode":"18015",
    "sg:province":"Granada",
    "wof:name":"Domingo Aguila Jose Miguel",
    "wof:placetype":"venue"
},
  "geometry": {"coordinates":[-3.6244792938,37.1921195984],"type":"Point"}
}