{
  "type": "Feature",
  "properties": {
    "addr:full":"Calle de Ansite, 14 Cruce De Arinaga Las Palmas 35118",
    "addr:housenumber":"14",
    "addr:postcode":"35118",
    "addr:street":"Calle De Ansite",
    "iso:country":"ES",
    "sg:address":"Calle de Ansite, 14",
    "sg:city":"Cruce De Arinaga",
    "sg:orig_category":"Asociaciones Y Clubs Deportivos",
    "sg:phone":"+34 928 18 82 33",
    "sg:postcode":"35118",
    "sg:province":"Las Palmas",
    "wof:name":"Abian Gim S.l.",
    "wof:placetype":"venue"
},
  "geometry": {"coordinates":[-15.430639,27.879852],"type":"Point"}
}