{
  "type": "Feature",
  "properties": {
    "iso:country":"ES",
    "sg:address":"Calle de Cuesta Estacion, 8",
    "sg:city":"Tudela",
    "sg:orig_category":"Telefon\u00cda M\u00d3vil, Radiomensajer\u00cda, Radiocomunicaciones (servicios, Comercializaci\u00d3n)",
    "sg:phone":"+34 948 40 29 60",
    "sg:postcode":"31500",
    "sg:province":"Navarra",
    "wof:name":"Umts Navarra",
    "wof:placetype":"venue"
},
  "geometry": {"coordinates":[-1.4821481705,42.1872329712],"type":"Point"}
}