{
  "type": "Feature",
  "properties": {
    "addr:full":"Poli San Crispin, 1 Illueca Zaragoza 50250",
    "addr:housenumber":"1",
    "addr:postcode":"50250",
    "addr:street":"Crispin",
    "iso:country":"ES",
    "sg:address":"Poli San Crispin, 1",
    "sg:city":"Illueca",
    "sg:orig_category":"Confecci\u00d3n De Zapatos",
    "sg:phone":"+34 976 82 02 00",
    "sg:postcode":"50250",
    "sg:province":"Zaragoza",
    "wof:name":"Daniel Perez Velilla S. A.",
    "wof:placetype":"venue"
},
  "geometry": {"coordinates":[-1.6259119511,41.5391235352],"type":"Point"}
}