{
  "type": "Feature",
  "properties": {
    "iso:country":"ES",
    "sg:address":"Avda Burjasot, 181",
    "sg:city":"Valencia",
    "sg:orig_category":"Bisuter\u00cda, Joyer\u00cda, Relojer\u00cda (al Por Menor)",
    "sg:phone":"+34 963 49 84 50",
    "sg:postcode":"46015",
    "sg:province":"Valencia",
    "wof:name":"Enrique Tarrasa S.l.",
    "wof:placetype":"venue"
},
  "geometry": {"coordinates":[-0.393768996,39.4928398132],"type":"Point"}
}