{
  "type": "Feature",
  "properties": {
    "iso:country":"ES",
    "sg:address":"Plaz Puerto, 5",
    "sg:city":"Tarazona",
    "sg:orig_category":"Molduras, Junquillos, Listones Y Molduras Perforadas",
    "sg:phone":"+34 976 64 25 46",
    "sg:postcode":"50500",
    "sg:province":"Zaragoza",
    "wof:name":"Lancis Vallejo Jose Javier",
    "wof:placetype":"venue"
},
  "geometry": {"coordinates":[-1.7312710285,41.9042778015],"type":"Point"}
}