{
  "type": "Feature",
  "properties": {
    "iso:country":"ES",
    "sg:address":"Calle de Santiago Lope, 22",
    "sg:city":"Benimamet-beniferri",
    "sg:orig_category":"Empresas De Limpieza",
    "sg:phone":"+34 963 63 85 17",
    "sg:postcode":"46035",
    "sg:province":"Valencia",
    "wof:name":"Valbuena Ochoa Astrid",
    "wof:placetype":"venue"
},
  "geometry": {"coordinates":[-0.4185830057,39.5035018921],"type":"Point"}
}