{
  "type": "Feature",
  "properties": {
    "addr:full":"Avda Pueyo, S/n Monzon Huesca 22400",
    "addr:housenumber":"s / n",
    "addr:postcode":"22400",
    "addr:street":"Avda Pueyo",
    "iso:country":"ES",
    "sg:address":"Avda Pueyo, S/n",
    "sg:city":"Monzon",
    "sg:orig_category":"Cr\u00cda De Animales",
    "sg:phone":"+34 974 40 06 36",
    "sg:postcode":"22400",
    "sg:province":"Huesca",
    "wof:name":"Betela S.a.",
    "wof:placetype":"venue"
},
  "geometry": {"coordinates":[0.1864700019,41.9066047668],"type":"Point"}
}