{
  "type": "Feature",
  "properties": {
    "addr:full":"Calle de Puerto, 16 Barbate C\u00e1diz 11160",
    "addr:housenumber":"16",
    "addr:postcode":"11160",
    "addr:street":"Calle De Puerto",
    "iso:country":"ES",
    "sg:address":"Calle de Puerto, 16",
    "sg:city":"Barbate",
    "sg:orig_category":"Fabricaci\u00d3n, Venta, Instalaci\u00d3n De R\u00d3tulos, De R\u00d3tulos Luminosos",
    "sg:phone":"+34 956 43 02 79",
    "sg:postcode":"11160",
    "sg:province":"C\u00e1diz",
    "wof:name":"Fernandez Benitez Juan",
    "wof:placetype":"venue"
},
  "geometry": {"coordinates":[-5.9229769707,36.1933288574],"type":"Point"}
}