{
  "type": "Feature",
  "properties": {
    "iso:country":"ES",
    "sg:address":"Cami Ral, 500",
    "sg:city":"Mataro",
    "sg:orig_category":"Abogados",
    "sg:phone":"+34 937 57 68 18",
    "sg:postcode":"08302",
    "sg:province":"Barcelona",
    "wof:name":"Bufet Casas-de Doria S.c.p.",
    "wof:placetype":"venue"
},
  "geometry": {"coordinates":[2.4415280819,41.5353012085],"type":"Point"}
}