{
  "type": "Feature",
  "properties": {
    "iso:country":"ES",
    "sg:address":"Urbanizacion Las Fuentes, S/n",
    "sg:city":"Mojados",
    "sg:orig_category":"Distribuci\u00d3n De Petr\u00d3leo Y Derivados",
    "sg:phone":"+34 983 60 72 81",
    "sg:postcode":"47250",
    "sg:province":"Valladolid",
    "wof:name":"Arroyo Alvarez Maria Luz",
    "wof:placetype":"venue"
},
  "geometry": {"coordinates":[-4.6921277046,41.5138664246],"type":"Point"}
}