{
  "type": "Feature",
  "properties": {
    "addr:full":"Calle de Reina, 48 Valencia Valencia 46011",
    "addr:housenumber":"48",
    "addr:postcode":"46011",
    "addr:street":"Calle De Reina",
    "iso:country":"ES",
    "sg:address":"Calle de Reina, 48",
    "sg:city":"Valencia",
    "sg:orig_category":"Reposter\u00cdas",
    "sg:phone":"+34 963 56 12 03",
    "sg:postcode":"46011",
    "sg:province":"Valencia",
    "wof:name":"Segrera Alcaliz Maria",
    "wof:placetype":"venue"
},
  "geometry": {"coordinates":[-0.3289349973,39.4657096863],"type":"Point"}
}