{
  "type": "Feature",
  "properties": {
    "iso:country":"ES",
    "sg:address":"Av Isidor Macabich, 15",
    "sg:city":"S. Antoni Portmany",
    "sg:orig_category":"Caf\u00c9s, Bares, Cervecer\u00cdas",
    "sg:phone":"+34 971 34 07 17",
    "sg:postcode":"07820",
    "sg:province":"Islas Baleares",
    "wof:name":"Riera Costa Antonio",
    "wof:placetype":"venue"
},
  "geometry": {"coordinates":[1.5188339949,39.1094055176],"type":"Point"}
}