{
  "type": "Feature",
  "properties": {
    "addr:full":"Calle de Balejo, 12 San Vicente De Barakaldo Vizcaya 48903",
    "addr:housenumber":"12",
    "addr:postcode":"48903",
    "addr:street":"Calle De Balejo",
    "iso:country":"ES",
    "sg:address":"Calle de Balejo, 12",
    "sg:city":"San Vicente De Barakaldo",
    "sg:orig_category":"Zapatos (al Por Menor)",
    "sg:phone":"+34 944 99 73 45",
    "sg:postcode":"48903",
    "sg:province":"Vizcaya",
    "wof:name":"Izquierdo Garcia Esperanza",
    "wof:placetype":"venue"
},
  "geometry": {"coordinates":[-2.9839498997,43.2854652405],"type":"Point"}
}