{
  "type": "Feature",
  "properties": {
    "addr:full":"Calle de Veredilla, 13 Pueblanueva Toledo 45690",
    "addr:housenumber":"13",
    "addr:postcode":"45690",
    "addr:street":"Calle De Veredilla",
    "iso:country":"ES",
    "sg:address":"Calle de Veredilla, 13",
    "sg:city":"Pueblanueva",
    "sg:orig_category":"Sindicatos Y Colegios Profesionales",
    "sg:phone":"+34 925 86 06 41",
    "sg:postcode":"45690",
    "sg:province":"Toledo",
    "wof:name":"Asociacion Profesional De Ganaderos De Porcino Nuestra Se\u00f1ora De La Paz S.a.",
    "wof:placetype":"venue"
},
  "geometry": {"coordinates":[-4.6814250946,39.9099197388],"type":"Point"}
}