{
  "type": "Feature",
  "properties": {
    "addr:full":"Plaz Iglesia, 4 Guarda Pontevedra 36780",
    "addr:housenumber":"4",
    "addr:postcode":"36780",
    "addr:street":"Iglesia",
    "iso:country":"ES",
    "sg:address":"Plaz Iglesia, 4",
    "sg:city":"Guarda",
    "sg:orig_category":"Centros Empresariales",
    "sg:phone":"+34 986 60 90 25",
    "sg:postcode":"36780",
    "sg:province":"Pontevedra",
    "wof:name":"Asociacion De Comerciantes E Industriales De La Guardia A.c.i.g.u",
    "wof:placetype":"venue"
},
  "geometry": {"coordinates":[-8.8739538193,41.9020233154],"type":"Point"}
}