{
  "type": "Feature",
  "properties": {
    "addr:full":"Carrer de Marques D'espanya, 20 Esplugues Llobregat Barcelona 08950",
    "addr:housenumber":"20",
    "addr:postcode":"08950",
    "addr:street":"Carrer De Marques D'Espanya",
    "iso:country":"ES",
    "sg:address":"Carrer de Marques D'espanya, 20",
    "sg:city":"Esplugues Llobregat",
    "sg:orig_category":"Promotores Constructores",
    "sg:phone":"+34 934 99 07 16",
    "sg:postcode":"08950",
    "sg:province":"Barcelona",
    "wof:name":"Construcciones Romero Granado S.l.",
    "wof:placetype":"venue"
},
  "geometry": {"coordinates":[2.0869719982,41.3709793091],"type":"Point"}
}