{
  "type": "Feature",
  "properties": {
    "iso:country":"ES",
    "sg:address":"Carr Alfons Xiii, 18",
    "sg:city":"Castello D'empuries",
    "sg:orig_category":"Fotograf\u00cda Art\u00cdstica Y Retratos",
    "sg:phone":"+34 972 25 03 48",
    "sg:postcode":"17486",
    "sg:province":"Girona",
    "wof:name":"Casamitjana Causa Carlos",
    "wof:placetype":"venue"
},
  "geometry": {"coordinates":[3.1170799732,42.139251709],"type":"Point"}
}