{
  "type": "Feature",
  "properties": {
    "addr:full":"Pla\u00c7 Mercadal, 7 Balaguer Lleida 25600",
    "addr:housenumber":"7",
    "addr:postcode":"25600",
    "addr:street":"Mercadal",
    "iso:country":"ES",
    "sg:address":"Pla\u00c7 Mercadal, 7",
    "sg:city":"Balaguer",
    "sg:orig_category":"Animales (al Por Menor)",
    "sg:phone":"+34 973 44 74 41",
    "sg:postcode":"25600",
    "sg:province":"Lleida",
    "wof:name":"Colilles Rubio Magdalena",
    "wof:placetype":"venue"
},
  "geometry": {"coordinates":[0.8046129942,41.7899436951],"type":"Point"}
}