{
  "type": "Feature",
  "properties": {
    "iso:country":"ES",
    "sg:address":"Calle de San Jose Obrero, S/n",
    "sg:city":"Pozuelo De Alarcon",
    "sg:orig_category":"Centros De Educaci\u00d3n Especial",
    "sg:phone":"+34 913 51 38 62",
    "sg:postcode":"28224",
    "sg:province":"Madrid",
    "wof:name":"Colegio Publico San Jose Obrero",
    "wof:placetype":"venue"
},
  "geometry": {"coordinates":[-3.7961740494,40.4434585571],"type":"Point"}
}