{
  "type": "Feature",
  "properties": {
    "iso:country":"ES",
    "sg:address":"Polig. Lalin Dos Mil, 15",
    "sg:city":"Donsion",
    "sg:orig_category":"Productos Qu\u00cdmicos (fabricaci\u00d3n, Al Por Mayor)",
    "sg:phone":"+34 986 79 42 50",
    "sg:postcode":"36519",
    "sg:province":"Pontevedra",
    "wof:name":"Laboratorios Minea S.l.u.",
    "wof:placetype":"venue"
},
  "geometry": {"coordinates":[-8.1627492905,42.5798492432],"type":"Point"}
}