{
  "type": "Feature",
  "properties": {
    "iso:country":"ES",
    "sg:address":"Ctra Torrelles, 60",
    "sg:city":"Sant Vicen\u00c7 Dels Horts",
    "sg:orig_category":"Decoraci\u00d3n: Instalaci\u00d3n Y Talleres",
    "sg:phone":"+34 936 72 45 00",
    "sg:postcode":"08620",
    "sg:province":"Barcelona",
    "wof:name":"Fidec Associats S.a.",
    "wof:placetype":"venue"
},
  "geometry": {"coordinates":[2.0097641945,41.3854255676],"type":"Point"}
}