{
  "type": "Feature",
  "properties": {
    "addr:full":"Carrer de Rossello, 372 Barcelona Barcelona 08025",
    "addr:housenumber":"372",
    "addr:postcode":"08025",
    "addr:street":"Carrer De Rossello",
    "iso:country":"ES",
    "sg:address":"Carrer de Rossello, 372",
    "sg:city":"Barcelona",
    "sg:orig_category":"Inform\u00c1tica (estudios, Servicios, Asesor\u00cda, Formaci\u00d3n)",
    "sg:phone":"+34 932 07 60 67",
    "sg:postcode":"08025",
    "sg:province":"Barcelona",
    "wof:name":"Rnd Sistemas S.l.",
    "wof:placetype":"venue"
},
  "geometry": {"coordinates":[2.1718809605,41.4040603638],"type":"Point"}
}