{
  "type": "Feature",
  "properties": {
    "iso:country":"ES",
    "sg:address":"Ctra Zaragoza (de), S/n",
    "sg:city":"Cari\u00f1ena",
    "sg:orig_category":"Alcoholes Y Aguardientes (fabricaci\u00d3n, Al Por Mayor)",
    "sg:phone":"+34 976 62 04 00",
    "sg:postcode":"50400",
    "sg:province":"Zaragoza",
    "wof:name":"Bodegas San Valero Sociedad Cooperativa",
    "wof:placetype":"venue"
},
  "geometry": {"coordinates":[-1.2234489918,41.340675354],"type":"Point"}
}