{
  "type": "Feature",
  "properties": {
    "addr:full":"Calle de Castillo, 8 Campo Criptana Ciudad Real 13610",
    "addr:housenumber":"8",
    "addr:postcode":"13610",
    "addr:street":"Calle De Castillo;Criptana",
    "iso:country":"ES",
    "sg:address":"Calle de Castillo, 8",
    "sg:city":"Campo Criptana",
    "sg:orig_category":"Material Y Suministros Para Imprenta E Industrias Gr\u00c1ficas",
    "sg:phone":"+34 926 56 06 53",
    "sg:postcode":"13610",
    "sg:province":"Ciudad Real",
    "wof:name":"Imprenta Flores S.l.",
    "wof:placetype":"venue"
},
  "geometry": {"coordinates":[-3.1237847805,39.4051322937],"type":"Point"}
}