{
  "type": "Feature",
  "properties": {
    "addr:full":"Calle de Blasco, 26 Alca\u00f1iz Teruel 44600",
    "addr:housenumber":"26",
    "addr:postcode":"44600",
    "addr:street":"Calle De Blasco",
    "iso:country":"ES",
    "sg:address":"Calle de Blasco, 26",
    "sg:city":"Alca\u00f1iz",
    "sg:orig_category":"Institutos De Belleza",
    "sg:phone":"+34 978 83 36 10",
    "sg:postcode":"44600",
    "sg:province":"Teruel",
    "wof:name":"Riba Ulldemolins Aranzazu",
    "wof:placetype":"venue"
},
  "geometry": {"coordinates":[-0.1310787052,41.050945282],"type":"Point"}
}