{
  "type": "Feature",
  "properties": {
    "iso:country":"ES",
    "sg:address":"Avda Vi\u00d1uela (de La), 16",
    "sg:city":"Cordoba",
    "sg:orig_category":"Fabricaci\u00d3n De Productos Textiles Sin Tejer",
    "sg:phone":"+34 957 25 35 67",
    "sg:postcode":"14010",
    "sg:province":"C\u00f3rdoba",
    "wof:name":"Ballester Ruiz Pilar",
    "wof:placetype":"venue"
},
  "geometry": {"coordinates":[-4.7629780769,37.8893165588],"type":"Point"}
}