{
  "type": "Feature",
  "properties": {
    "iso:country":"ES",
    "sg:address":"Pol Ind El Puente Del Rio, Km. 0064,0",
    "sg:city":"Puente Del Rio",
    "sg:orig_category":"Electricidad Veh\u00cdculo",
    "sg:phone":"+34 950 56 80 38",
    "sg:postcode":"04779",
    "sg:province":"Almer\u00eda",
    "wof:name":"Autocolor Cram S.l.",
    "wof:placetype":"venue"
},
  "geometry": {"coordinates":[-3.0038468838,36.7787475586],"type":"Point"}
}