{
  "type": "Feature",
  "properties": {
    "iso:country":"ES",
    "sg:address":"Calle de Juan Antonio Bravo, 18",
    "sg:city":"Cudillero",
    "sg:orig_category":"Supermercados Y Hipermercados",
    "sg:phone":"+34 985 59 17 01",
    "sg:postcode":"33150",
    "sg:province":"Asturias",
    "wof:name":"Merkaprecio S.a.",
    "wof:placetype":"venue"
},
  "geometry": {"coordinates":[-6.1496601105,43.5588111877],"type":"Point"}
}