{
  "type": "Feature",
  "properties": {
    "addr:full":"Carrer de Mendez Nu\u00d1ez, 11 Tarragona Tarragona 43004",
    "addr:housenumber":"11",
    "addr:postcode":"43004",
    "addr:street":"Carrer De Mendez Nun\u0303Ez",
    "iso:country":"ES",
    "sg:address":"Carrer de Mendez Nu\u00d1ez, 11",
    "sg:city":"Tarragona",
    "sg:orig_category":"Abogados",
    "sg:phone":"+34 977 25 20 40",
    "sg:postcode":"43004",
    "sg:province":"Tarragona",
    "wof:name":"Gabinet Salva Advocats Associats S.c.p.",
    "wof:placetype":"venue"
},
  "geometry": {"coordinates":[1.2526420355,41.1147003174],"type":"Point"}
}