{
  "type": "Feature",
  "properties": {
    "addr:full":"Carr For\u00c7a, 9 Girona Girona 17004",
    "addr:housenumber":"9",
    "addr:postcode":"17004",
    "addr:street":"Carr Forc\u0327A",
    "iso:country":"ES",
    "sg:address":"Carr For\u00c7a, 9",
    "sg:city":"Girona",
    "sg:orig_category":"Caf\u00c9s, Bares, Cervecer\u00cdas",
    "sg:phone":"+34 872 08 15 76",
    "sg:postcode":"17004",
    "sg:province":"Girona",
    "wof:name":"Cafes Toscana S.l.",
    "wof:placetype":"venue"
},
  "geometry": {"coordinates":[2.825122118,41.9857826233],"type":"Point"}
}