{
  "type": "Feature",
  "properties": {
    "iso:country":"ES",
    "sg:address":"Avda Kansas City, 11",
    "sg:city":"Sevilla",
    "sg:orig_category":"Panader\u00cdas, Panader\u00cdas",
    "sg:phone":"+34 954 54 20 22",
    "sg:postcode":"41007",
    "sg:province":"Sevilla",
    "wof:name":"Parrilla Maes Antonino",
    "wof:placetype":"venue"
},
  "geometry": {"coordinates":[-5.9727392197,37.3882408142],"type":"Point"}
}