{
  "type": "Feature",
  "properties": {
    "addr:full":"Av Font De Mora, 6 Pu\u00e7ol Valencia 46530",
    "addr:housenumber":"6",
    "addr:postcode":"46530",
    "addr:street":"Av Font De Mora",
    "iso:country":"ES",
    "sg:address":"Av Font De Mora, 6",
    "sg:city":"Pu\u00e7ol",
    "sg:orig_category":"Electrodom\u00c9sticos (al Por Menor)",
    "sg:phone":"+34 961 42 08 00",
    "sg:postcode":"46530",
    "sg:province":"Valencia",
    "wof:name":"Puzol Industrial S. A.",
    "wof:placetype":"venue"
},
  "geometry": {"coordinates":[-0.3031480014,39.6208229065],"type":"Point"}
}