{
  "type": "Feature",
  "properties": {
    "iso:country":"ES",
    "sg:address":"Calle de Espejo, 62",
    "sg:city":"Villanueva De La Ca\u00e7ada",
    "sg:orig_category":"Empresarios",
    "sg:phone":"+34 918 12 52 07",
    "sg:postcode":"28691",
    "sg:province":"Madrid",
    "wof:name":"Medio Punto Vivienda Y Paisaje.",
    "wof:placetype":"venue"
},
  "geometry": {"coordinates":[-4.0020289421,40.4459114075],"type":"Point"}
}