{
  "type": "Feature",
  "properties": {
    "addr:full":"Calle de Eduardo Carre\u00d1o Valdes, 1 Aviles Asturias 33401",
    "addr:housenumber":"1",
    "addr:postcode":"33401",
    "addr:street":"Calle De Eduardo Carren\u0303O Valdes",
    "iso:country":"ES",
    "sg:address":"Calle de Eduardo Carre\u00d1o Valdes, 1",
    "sg:city":"Aviles",
    "sg:orig_category":"Ense\u00d1anza Secundaria: Colegios Y Escuelas Privadas",
    "sg:phone":"+34 985 56 59 05",
    "sg:postcode":"33401",
    "sg:province":"Asturias",
    "wof:name":"Vega Vi\u00f1uela Flor De",
    "wof:placetype":"venue"
},
  "geometry": {"coordinates":[-5.9322490692,43.5587005615],"type":"Point"}
}