{
  "type": "Feature",
  "properties": {
    "iso:country":"ES",
    "sg:address":"Carr Constitucio, 16",
    "sg:city":"Vila Joiosa",
    "sg:orig_category":"Asociaciones Y Clubs Deportivos",
    "sg:phone":"+34 965 89 48 35",
    "sg:postcode":"03570",
    "sg:province":"Alicante",
    "wof:name":"Sociedad Deportiva De Pesca Con Ca\u00f1a",
    "wof:placetype":"venue"
},
  "geometry": {"coordinates":[-0.2327190042,38.505821228],"type":"Point"}
}