{
  "type": "Feature",
  "properties": {
    "iso:country":"ES",
    "sg:address":"Carrer de Jaume Isern, 3",
    "sg:city":"Mataro",
    "sg:orig_category":"Locales Y Clases De Danza",
    "sg:phone":"+34 937 99 08 23",
    "sg:postcode":"08302",
    "sg:province":"Barcelona",
    "wof:name":"Roig Camps Dunia",
    "wof:placetype":"venue"
},
  "geometry": {"coordinates":[2.4399390221,41.5404815674],"type":"Point"}
}