{
  "type": "Feature",
  "properties": {
    "addr:full":"Cra. Castelldans, S/n Juneda Lleida 25430",
    "addr:housenumber":"s / n",
    "addr:postcode":"25430",
    "iso:country":"ES",
    "sg:address":"Cra. Castelldans, S/n",
    "sg:city":"Juneda",
    "sg:orig_category":"Producci\u00d3n, Venta De Productos De Agricultura Biol\u00d3gica",
    "sg:phone":"+34 973 15 06 11",
    "sg:postcode":"25430",
    "sg:province":"Lleida",
    "wof:name":"Fabregat Capell Margarita",
    "wof:placetype":"venue"
},
  "geometry": {"coordinates":[0.8210999966,41.5490760803],"type":"Point"}
}