{
  "type": "Feature",
  "properties": {
    "addr:full":"Calle de Pastores, 3 Javea Alicante 03730",
    "addr:housenumber":"3",
    "addr:postcode":"03730",
    "addr:street":"Calle De Pastores",
    "iso:country":"ES",
    "sg:address":"Calle de Pastores, 3",
    "sg:city":"Javea",
    "sg:orig_category":"Ropa Para Se\u00d1oras (al Por Menor)",
    "sg:phone":"+34 965 79 29 41",
    "sg:postcode":"03730",
    "sg:province":"Alicante",
    "wof:name":"Ferrer Soler Josefa",
    "wof:placetype":"venue"
},
  "geometry": {"coordinates":[0.1624130011,38.7877883911],"type":"Point"}
}