{
  "type": "Feature",
  "properties": {
    "iso:country":"ES",
    "sg:address":"Calle de Amparo, 42",
    "sg:city":"Madrid",
    "sg:orig_category":"Ropa Para Se\u00d1oras (al Por Menor)",
    "sg:phone":"+34 915 27 38 22",
    "sg:postcode":"28012",
    "sg:province":"Madrid",
    "wof:name":"Rubi Fashion S.l.",
    "wof:placetype":"venue"
},
  "geometry": {"coordinates":[-3.7027313709,40.4091529846],"type":"Point"}
}