{
  "type": "Feature",
  "properties": {
    "addr:full":"Calle de Luis De Vargas, 1 Huelva Huelva 21001",
    "addr:housenumber":"1",
    "addr:postcode":"21001",
    "addr:street":"Calle De Luis De Vargas",
    "iso:country":"ES",
    "sg:address":"Calle de Luis De Vargas, 1",
    "sg:city":"Huelva",
    "sg:orig_category":"Inform\u00c1tica, Ofim\u00c1tica (estudios, Asesor\u00cda, Ingenier\u00cda, Formaci\u00d3n)",
    "sg:phone":"+34 959 25 07 67",
    "sg:postcode":"21001",
    "sg:province":"Huelva",
    "sg:website":"www.estoeshuelva.com",
    "wof:name":"Gallego Martin Francisco",
    "wof:placetype":"venue"
},
  "geometry": {"coordinates":[-6.9531130791,37.2537651062],"type":"Point"}
}