{
  "type": "Feature",
  "properties": {
    "iso:country":"ES",
    "sg:address":"Calle de Estudios, 9",
    "sg:city":"Madrid",
    "sg:orig_category":"Peritos En Seguros",
    "sg:phone":"+34 913 65 42 76",
    "sg:postcode":"28012",
    "sg:province":"Madrid",
    "wof:name":"Garcia & Bermello Correduria De Seguros",
    "wof:placetype":"venue"
},
  "geometry": {"coordinates":[-3.7072520256,40.4116516113],"type":"Point"}
}