{
  "type": "Feature",
  "properties": {
    "addr:full":"Crta De La Parrilla, Km. 0001,5 Andujar Ja\u00e9n 23740",
    "addr:postcode":"23740",
    "addr:street":"Crta De La Parrilla Km. 0001,5;Jae\u0301N",
    "iso:country":"ES",
    "sg:address":"Crta De La Parrilla, Km. 0001,5",
    "sg:city":"Andujar",
    "sg:orig_category":"Promotores Constructores",
    "sg:phone":"+34 953 12 22 42",
    "sg:postcode":"23740",
    "sg:province":"Ja\u00e9n",
    "wof:name":"De La Pe\u00d1a Asociados S.a.",
    "wof:placetype":"venue"
},
  "geometry": {"coordinates":[-4.057518959,38.0386962891],"type":"Point"}
}