{
  "type": "Feature",
  "properties": {
    "iso:country":"ES",
    "sg:address":"Ptda. Hrta. Alta, S/n",
    "sg:city":"Xirivella",
    "sg:orig_category":"Polideportivos",
    "sg:phone":"+34 963 59 54 17",
    "sg:postcode":"46950",
    "sg:province":"Valencia",
    "wof:name":"Ayuntamiento De Xirivella",
    "wof:placetype":"venue"
},
  "geometry": {"coordinates":[-0.426658392,39.4597816467],"type":"Point"}
}