{
  "type": "Feature",
  "properties": {
    "addr:full":"Calle de Castelar, 3 Sevilla Sevilla 41001",
    "addr:housenumber":"3",
    "addr:postcode":"41001",
    "addr:street":"Calle De Castelar",
    "iso:country":"ES",
    "sg:address":"Calle de Castelar, 3",
    "sg:city":"Sevilla",
    "sg:orig_category":"Cristaler\u00cdas",
    "sg:phone":"+34 954 22 23 73",
    "sg:postcode":"41001",
    "sg:province":"Sevilla",
    "wof:name":"Giraldez Macias Manuel",
    "wof:placetype":"venue"
},
  "geometry": {"coordinates":[-5.9967370033,37.3867874146],"type":"Point"}
}