{
  "type": "Feature",
  "properties": {
    "addr:full":"Carrer de Muntaner, 49 Barcelona Barcelona 08011",
    "addr:housenumber":"49",
    "addr:postcode":"08011",
    "addr:street":"Carrer De Muntaner",
    "iso:country":"ES",
    "sg:address":"Carrer de Muntaner, 49",
    "sg:city":"Barcelona",
    "sg:orig_category":"Electricidad: Equipos Industriales, Componentes (fabricaci\u00d3n)",
    "sg:phone":"+34 933 23 28 08",
    "sg:postcode":"08011",
    "sg:province":"Barcelona",
    "sg:website":"www.diotronic.com",
    "wof:name":"Diotronic S. A.",
    "wof:placetype":"venue"
},
  "geometry": {"coordinates":[2.1600248814,41.3859786987],"type":"Point"}
}