{
  "type": "Feature",
  "properties": {
    "iso:country":"ES",
    "sg:address":"Estacio, S/n",
    "sg:city":"Blanes",
    "sg:orig_category":"Maquinaria Para Industrias Diversas",
    "sg:phone":"+34 972 33 05 49",
    "sg:postcode":"17300",
    "sg:province":"Girona",
    "wof:name":"Talleres Mecanicos Somac S. A.",
    "wof:placetype":"venue"
},
  "geometry": {"coordinates":[2.7755870819,41.6759109497],"type":"Point"}
}