{
  "type": "Feature",
  "properties": {
    "iso:country":"ES",
    "sg:address":"Calle de Encarnacion Del Pino, 3",
    "sg:city":"Madrid",
    "sg:orig_category":"Librer\u00cdas",
    "sg:phone":"+34 915 05 19 58",
    "sg:postcode":"28021",
    "sg:province":"Madrid",
    "wof:name":"Salas Diaz Manuel",
    "wof:placetype":"venue"
},
  "geometry": {"coordinates":[-3.7128551006,40.346031189],"type":"Point"}
}