{
  "type": "Feature",
  "properties": {
    "addr:full":"Calle de Alcala, 380 Madrid Madrid 28027",
    "addr:housenumber":"380",
    "addr:postcode":"28027",
    "addr:street":"Calle De Alcala",
    "iso:country":"ES",
    "sg:address":"Calle de Alcala, 380",
    "sg:city":"Madrid",
    "sg:orig_category":"Asesor\u00cda Sobre Comunicaci\u00d3n De Empresas",
    "sg:phone":"+34 913 68 06 02",
    "sg:postcode":"28027",
    "sg:province":"Madrid",
    "wof:name":"Alcala Asesores S.a.",
    "wof:placetype":"venue"
},
  "geometry": {"coordinates":[-3.6419887543,40.4360389709],"type":"Point"}
}