{
  "type": "Feature",
  "properties": {
    "iso:country":"ES",
    "sg:address":"Calle de Chimidas, 20",
    "sg:city":"Playa Honda",
    "sg:orig_category":"Cr\u00cda De Animales",
    "sg:phone":"+34 928 82 10 91",
    "sg:postcode":"35509",
    "sg:province":"Las Palmas",
    "wof:name":"El Arca De Noe S.l.",
    "wof:placetype":"venue"
},
  "geometry": {"coordinates":[-13.5917158127,28.9558792114],"type":"Point"}
}