{
  "type": "Feature",
  "properties": {
    "addr:full":"Plaz San Cristobal, 22 San Cristobal De La Laguna Santa Cruz De Tenerife 38204",
    "addr:housenumber":"22",
    "addr:postcode":"38204",
    "addr:street":"Plaz San Cristobal",
    "iso:country":"ES",
    "sg:address":"Plaz San Cristobal, 22",
    "sg:city":"San Cristobal De La Laguna",
    "sg:classifiers":[
        {
            "category":"Personal",
            "subcategory":"Barber",
            "type":"Services"
        }
    ],
    "sg:phone":"+34 922 63 24 81",
    "sg:postcode":"38204",
    "sg:province":"Santa Cruz De Tenerife",
    "sg:tags":[
        "caballeros",
        "de",
        "peluqueros"
    ],
    "wof:name":"Gonzalez Gutierrez Sigfredo",
    "wof:placetype":"venue"
},
  "geometry": {"coordinates":[-16.3138256073,28.4839363098],"type":"Point"}
}