{
  "type": "Feature",
  "properties": {
    "iso:country":"ES",
    "sg:address":"Calle de San Antonio, 30",
    "sg:city":"Valverde Leganes",
    "sg:orig_category":"Contenedores (mercanc\u00cdas)",
    "sg:phone":"+34 924 49 65 32",
    "sg:postcode":"06130",
    "sg:province":"Badajoz",
    "wof:name":"Jimeno Rodriguez Julio",
    "wof:placetype":"venue"
},
  "geometry": {"coordinates":[-6.978178978,38.6722488403],"type":"Point"}
}