{
  "type": "Feature",
  "properties": {
    "addr:full":"Azkoitiko Industrialdea, 50 Azkoitia Guip\u00f9zcoa 20720",
    "addr:housenumber":"50",
    "addr:postcode":"20720",
    "addr:street":"Industrialdea;Guipu\u0300Zcoa",
    "iso:country":"ES",
    "sg:address":"Azkoitiko Industrialdea, 50",
    "sg:city":"Azkoitia",
    "sg:orig_category":"Madera Para Construcci\u00d3n E Industria",
    "sg:phone":"+34 943 85 05 06",
    "sg:postcode":"20720",
    "sg:province":"Guip\u00f9zcoa",
    "wof:name":"Sheitek Automatizacion Industrial S.a.l.",
    "wof:placetype":"venue"
},
  "geometry": {"coordinates":[-2.3221380711,43.1730728149],"type":"Point"}
}