{
  "type": "Feature",
  "properties": {
    "addr:full":"Calle de San Quintin, 15 Malaga M\u00e1laga 29009",
    "addr:housenumber":"15",
    "addr:postcode":"29009",
    "addr:street":"Calle De San Quintin;Ma\u0301Laga",
    "iso:country":"ES",
    "sg:address":"Calle de San Quintin, 15",
    "sg:city":"Malaga",
    "sg:orig_category":"Artes Gr\u00c1ficas, Artes Pl\u00c1sticas: Material Y Suministros (al Por Menor)",
    "sg:phone":"+34 952 61 85 68",
    "sg:postcode":"29009",
    "sg:province":"M\u00e1laga",
    "wof:name":"Ilasa Graphic S.a.",
    "wof:placetype":"venue"
},
  "geometry": {"coordinates":[-4.427670002,36.7244720459],"type":"Point"}
}