{
  "type": "Feature",
  "properties": {
    "iso:country":"ES",
    "sg:address":"Av Joan Xxiii, 13",
    "sg:city":"Masnou",
    "sg:orig_category":"Discapacitados",
    "sg:phone":"+34 935 40 29 59",
    "sg:postcode":"08320",
    "sg:province":"Barcelona",
    "wof:name":"Asociacion Pro-disminuidos Psiquicos Del Masnou",
    "wof:placetype":"venue"
},
  "geometry": {"coordinates":[2.3106665611,41.4838600159],"type":"Point"}
}