{
  "type": "Feature",
  "properties": {
    "addr:full":"Pol. Ind. La Central, 7 Central Asturias 33940",
    "addr:postcode":"33940",
    "addr:street":"Central Asturias",
    "iso:country":"ES",
    "sg:address":"Pol. Ind. La Central, 7",
    "sg:city":"Central",
    "sg:orig_category":"Electricidad (montaje, Ensamblaje De Componentes)",
    "sg:phone":"+34 985 66 04 38",
    "sg:postcode":"33940",
    "sg:province":"Asturias",
    "wof:name":"Taller Electromecanico Joprar S.l.",
    "wof:placetype":"venue"
},
  "geometry": {"coordinates":[-5.6435742378,43.2864112854],"type":"Point"}
}