{
  "type": "Feature",
  "properties": {
    "addr:full":"Callejon Del Cura, 4 La Rabita Granada 18760",
    "addr:housenumber":"4",
    "addr:postcode":"18760",
    "addr:street":"Callejon Del Cura;La Rabita",
    "iso:country":"ES",
    "sg:address":"Callejon Del Cura, 4",
    "sg:city":"La Rabita",
    "sg:orig_category":"Iglesia Cat\u00d3lica",
    "sg:phone":"+34 958 82 94 50",
    "sg:postcode":"18760",
    "sg:province":"Granada",
    "wof:name":"Parroquia De La Natividad De Nuestra Se\u00f1ora",
    "wof:placetype":"venue"
},
  "geometry": {"coordinates":[-3.1724073887,36.748664856],"type":"Point"}
}