{
  "type": "Feature",
  "properties": {
    "addr:full":"Carrer de Ciutadans, 10 Pineda Mar Barcelona 08397",
    "addr:housenumber":"10",
    "addr:postcode":"08397",
    "addr:street":"Carrer De Ciutadans;Barcelona",
    "iso:country":"ES",
    "sg:address":"Carrer de Ciutadans, 10",
    "sg:city":"Pineda Mar",
    "sg:orig_category":"Empresas De Carpinter\u00cda",
    "sg:phone":"+34 937 62 14 50",
    "sg:postcode":"08397",
    "sg:province":"Barcelona",
    "wof:name":"Molina Olias Maria Jesus",
    "wof:placetype":"venue"
},
  "geometry": {"coordinates":[2.6897039413,41.6277656555],"type":"Point"}
}