{
  "type": "Feature",
  "properties": {
    "iso:country":"ES",
    "sg:address":"Plaz Mencey Bencomo, 2",
    "sg:city":"Carrera",
    "sg:orig_category":"Ingeniero",
    "sg:phone":"+34 922 35 52 54",
    "sg:postcode":"38410",
    "sg:province":"Santa Cruz De Tenerife",
    "wof:name":"Hello Tenerife Norte S.l.",
    "wof:placetype":"venue"
},
  "geometry": {"coordinates":[-16.5807914734,28.3678131104],"type":"Point"}
}