{
  "type": "Feature",
  "properties": {
    "addr:full":"Avda Padre Isla, 7 Le\u00f3n Le\u00f3n 24002",
    "addr:housenumber":"7",
    "addr:postcode":"24002",
    "addr:street":"Avda Padre Isla;Leo\u0301N",
    "iso:country":"ES",
    "sg:address":"Avda Padre Isla, 7",
    "sg:city":"Le\u00f3n",
    "sg:orig_category":"Venta, Instalaci\u00d3n De Calefacci\u00d3n",
    "sg:phone":"+34 987 23 46 00",
    "sg:postcode":"24002",
    "sg:province":"Le\u00f3n",
    "wof:name":"Eurocivil S.l.",
    "wof:placetype":"venue"
},
  "geometry": {"coordinates":[-5.5728750229,42.5992393494],"type":"Point"}
}