{
  "type": "Feature",
  "properties": {
    "addr:full":"Carrer de Vila I Vila, 101 Barcelona Barcelona 08004",
    "addr:housenumber":"101",
    "addr:postcode":"08004",
    "addr:street":"Carrer De Vila I Vila",
    "iso:country":"ES",
    "sg:address":"Carrer de Vila I Vila, 101",
    "sg:city":"Barcelona",
    "sg:orig_category":"Cursos Particulares, Asistencia Escolar",
    "sg:phone":"+34 934 41 61 32",
    "sg:postcode":"08004",
    "sg:province":"Barcelona",
    "sg:website":"www.idiomachino.com",
    "wof:name":"Bou Vazquez Vidal",
    "wof:placetype":"venue"
},
  "geometry": {"coordinates":[2.1670689583,41.3745765686],"type":"Point"}
}