{
  "type": "Feature",
  "properties": {
    "iso:country":"ES",
    "sg:address":"Avda Andalucia, 69",
    "sg:city":"Estepona",
    "sg:orig_category":"Arreglo, Reparaci\u00d3n, Piezas Sueltas De Televisi\u00d3n, V\u00cddeo, Hi",
    "sg:phone":"+34 952 80 33 01",
    "sg:postcode":"29680",
    "sg:province":"M\u00e1laga",
    "wof:name":"Reyes Garcia Juan",
    "wof:placetype":"venue"
},
  "geometry": {"coordinates":[-5.1431670189,36.4305267334],"type":"Point"}
}