{
  "type": "Feature",
  "properties": {
    "addr:full":"Calle de Larga, 52 Tamames Salamanca 37600",
    "addr:housenumber":"52",
    "addr:postcode":"37600",
    "addr:street":"Calle De Larga",
    "iso:country":"ES",
    "sg:address":"Calle de Larga, 52",
    "sg:city":"Tamames",
    "sg:orig_category":"Cooperativas Agr\u00cdcolas",
    "sg:phone":"+34 923 44 91 51",
    "sg:postcode":"37600",
    "sg:province":"Salamanca",
    "wof:name":"Union De Peque\u00f1os Agricultores De Salamanca",
    "wof:placetype":"venue"
},
  "geometry": {"coordinates":[-6.1027779579,40.656578064],"type":"Point"}
}