{
  "type": "Feature",
  "properties": {
    "addr:full":"Ses Coves, 8 Son Vilar Islas Baleares 07713",
    "addr:housenumber":"8",
    "addr:postcode":"07713",
    "addr:street":"Coves",
    "iso:country":"ES",
    "sg:address":"Ses Coves, 8",
    "sg:city":"Son Vilar",
    "sg:orig_category":"Empresas De Pintura Y Revestimientos",
    "sg:phone":"+34 971 36 68 97",
    "sg:postcode":"07713",
    "sg:province":"Islas Baleares",
    "wof:name":"Delgado Perez Manuel",
    "wof:placetype":"venue"
},
  "geometry": {"coordinates":[4.2635698318,39.8131599426],"type":"Point"}
}