{
  "type": "Feature",
  "properties": {
    "addr:full":"Barr Meson (el), 19 Beranga Cantabria 39730",
    "addr:postcode":"39730",
    "iso:country":"ES",
    "sg:address":"Barr Meson (el), 19",
    "sg:city":"Beranga",
    "sg:orig_category":"M\u00c9dicos: Estomatolog\u00cda",
    "sg:phone":"+34 942 63 52 12",
    "sg:postcode":"39730",
    "sg:province":"Cantabria",
    "wof:name":"Trueba Martinez Carmen",
    "wof:placetype":"venue"
},
  "geometry": {"coordinates":[-3.5771279335,43.4150924683],"type":"Point"}
}