{
  "type": "Feature",
  "properties": {
    "addr:full":"Avda Montevideo, 121 Bilbao Vizcaya 48013",
    "addr:housenumber":"121",
    "addr:postcode":"48013",
    "addr:street":"Avda Montevideo",
    "iso:country":"ES",
    "sg:address":"Avda Montevideo, 121",
    "sg:city":"Bilbao",
    "sg:orig_category":"Asilos De Ancianos. Centros Privados",
    "sg:phone":"+34 944 41 50 09",
    "sg:postcode":"48013",
    "sg:province":"Vizcaya",
    "wof:name":"Bilbao Bizkaia Kutxa",
    "wof:placetype":"venue"
},
  "geometry": {"coordinates":[-2.9609279633,43.2650375366],"type":"Point"}
}