{
  "type": "Feature",
  "properties": {
    "iso:country":"ES",
    "sg:address":"Avda Padre Piquer, 16",
    "sg:city":"Madrid",
    "sg:orig_category":"Peluquer\u00cdas, Peluquer\u00cda Mixta",
    "sg:phone":"+34 915 18 59 61",
    "sg:postcode":"28024",
    "sg:province":"Madrid",
    "wof:name":"Ocurrele Villar Eva",
    "wof:placetype":"venue"
},
  "geometry": {"coordinates":[-3.7684600353,40.3931274414],"type":"Point"}
}