{
  "type": "Feature",
  "properties": {
    "addr:full":"Calle de Vallejo, 15 Santurtzi Vizcaya 48980",
    "addr:housenumber":"15",
    "addr:postcode":"48980",
    "addr:street":"Calle De Vallejo",
    "iso:country":"ES",
    "sg:address":"Calle de Vallejo, 15",
    "sg:city":"Santurtzi",
    "sg:orig_category":"Fabricaci\u00d3n, Reparaci\u00d3n Y Mantenimiento De Construcciones Navales Y Fluviales",
    "sg:phone":"+34 944 62 85 77",
    "sg:postcode":"48980",
    "sg:province":"Vizcaya",
    "wof:name":"Arco Barquin Jose Luis Barriocanal Gastiasoro Antonio S.cv.",
    "wof:placetype":"venue"
},
  "geometry": {"coordinates":[-3.0402495861,43.3315124512],"type":"Point"}
}