{
  "type": "Feature",
  "properties": {
    "iso:country":"ES",
    "sg:address":"Calle de Juan Carlos I, 9",
    "sg:city":"Pe\u00e7arroya-pueblonuevo",
    "sg:orig_category":"Quincaller\u00cda (al Por Menor)",
    "sg:phone":"+34 957 56 03 87",
    "sg:postcode":"14200",
    "sg:province":"C\u00f3rdoba",
    "wof:name":"Balsera Galan Consuelo",
    "wof:placetype":"venue"
},
  "geometry": {"coordinates":[-5.2653450966,38.2983398438],"type":"Point"}
}