{
  "type": "Feature",
  "properties": {
    "addr:full":"Avda Valencia, 53 Requena Valencia 46340",
    "addr:housenumber":"53",
    "addr:postcode":"46340",
    "addr:street":"Avda Valencia",
    "iso:country":"ES",
    "sg:address":"Avda Valencia, 53",
    "sg:city":"Requena",
    "sg:orig_category":"Aparatos E Instalaci\u00d3n De Regad\u00cdos",
    "sg:phone":"+34 962 30 31 12",
    "sg:postcode":"46340",
    "sg:province":"Valencia",
    "wof:name":"Sistema Feri S.l.",
    "wof:placetype":"venue"
},
  "geometry": {"coordinates":[-1.1055150032,39.484577179],"type":"Point"}
}