{
  "type": "Feature",
  "properties": {
    "addr:full":"Trav Dalt, 109 Barcelona Barcelona 08024",
    "addr:housenumber":"109",
    "addr:postcode":"08024",
    "addr:street":"Trav Dalt",
    "iso:country":"ES",
    "sg:address":"Trav Dalt, 109",
    "sg:city":"Barcelona",
    "sg:orig_category":"Asesor\u00cda Sobre Comunicaci\u00d3n De Empresas",
    "sg:phone":"+34 932 10 54 57",
    "sg:postcode":"08024",
    "sg:province":"Barcelona",
    "wof:name":"Asesoria Taidys S. R. L.",
    "wof:placetype":"venue"
},
  "geometry": {"coordinates":[2.1580038071,41.4116325378],"type":"Point"}
}