{
  "type": "Feature",
  "properties": {
    "addr:full":"Pg Progres, S/n Olesa Montserrat Barcelona 08640",
    "addr:housenumber":"s / n",
    "addr:postcode":"08640",
    "addr:street":"Pg Progres",
    "iso:country":"ES",
    "sg:address":"Pg Progres, S/n",
    "sg:city":"Olesa Montserrat",
    "sg:orig_category":"Piedras Artificiales",
    "sg:phone":"+34 937 77 33 77",
    "sg:postcode":"08640",
    "sg:province":"Barcelona",
    "sg:website":"hj@hispanojardin.com",
    "wof:name":"Creaciones En Piedra Artificial Hispano Jardin S.l.",
    "wof:placetype":"venue"
},
  "geometry": {"coordinates":[1.8927350044,41.5391960144],"type":"Point"}
}