{
  "type": "Feature",
  "properties": {
    "iso:country":"ES",
    "sg:address":"Pase General Davila, 324",
    "sg:city":"Santander",
    "sg:orig_category":"Confecci\u00d3n De Guantes",
    "sg:phone":"+34 942 34 53 80",
    "sg:postcode":"39007",
    "sg:province":"Cantabria",
    "wof:name":"Manufacturas Altamira S. A.",
    "wof:placetype":"venue"
},
  "geometry": {"coordinates":[-3.8299589157,43.4615211487],"type":"Point"}
}