{
  "type": "Feature",
  "properties": {
    "addr:full":"Calle de Benelux, 5 Elda Alicante 03600",
    "addr:housenumber":"5",
    "addr:postcode":"03600",
    "addr:street":"Calle De Benelux",
    "iso:country":"ES",
    "sg:address":"Calle de Benelux, 5",
    "sg:city":"Elda",
    "sg:orig_category":"Importaci\u00d3n",
    "sg:phone":"+34 965 39 02 99",
    "sg:postcode":"03600",
    "sg:province":"Alicante",
    "wof:name":"Ralph Cohen S.l.",
    "wof:placetype":"venue"
},
  "geometry": {"coordinates":[-0.8158627748,38.4646492004],"type":"Point"}
}