{
  "type": "Feature",
  "properties": {
    "iso:country":"ES",
    "sg:address":"Carrer de Muntanya, 53",
    "sg:city":"Viladecans",
    "sg:orig_category":"Ense\u00d1anza Agr\u00cdcola",
    "sg:phone":"+34 936 37 35 67",
    "sg:postcode":"08840",
    "sg:province":"Barcelona",
    "wof:name":"Agrupament Escolta Sant Joan",
    "wof:placetype":"venue"
},
  "geometry": {"coordinates":[2.0164060593,41.3194656372],"type":"Point"}
}