{
  "type": "Feature",
  "properties": {
    "addr:full":"Calle de Urbieta, 60 Donostia-san Sebastian Guip\u00f9zcoa 20006",
    "addr:housenumber":"60",
    "addr:postcode":"20006",
    "addr:street":"Calle De Urbieta",
    "iso:country":"ES",
    "sg:address":"Calle de Urbieta, 60",
    "sg:city":"Donostia-san Sebastian",
    "sg:orig_category":"Abogados",
    "sg:phone":"+34 943 46 29 00",
    "sg:postcode":"20006",
    "sg:province":"Guip\u00f9zcoa",
    "wof:name":"Llorente Lopez Josefa",
    "wof:placetype":"venue"
},
  "geometry": {"coordinates":[-1.9808419943,43.3139572144],"type":"Point"}
}