{
  "type": "Feature",
  "properties": {
    "addr:full":"Calle de Eria Del Hospital, 10 Pola De Siero Asturias 33510",
    "addr:housenumber":"10",
    "addr:postcode":"33510",
    "addr:street":"Calle De Eria Del Hospital",
    "iso:country":"ES",
    "sg:address":"Calle de Eria Del Hospital, 10",
    "sg:city":"Pola De Siero",
    "sg:orig_category":"Procuradores",
    "sg:phone":"+34 985 72 30 26",
    "sg:postcode":"33510",
    "sg:province":"Asturias",
    "wof:name":"Blanco Perez Maria Ines",
    "wof:placetype":"venue"
},
  "geometry": {"coordinates":[-5.6630549431,43.3911628723],"type":"Point"}
}