{
  "type": "Feature",
  "properties": {
    "iso:country":"ES",
    "sg:address":"Pr. Victoria Cadaval, 13",
    "sg:city":"A Ramallosa",
    "sg:orig_category":"Molduras, Junquillos, Listones Y Molduras Perforadas",
    "sg:phone":"+34 986 35 00 08",
    "sg:postcode":"36393",
    "sg:province":"Pontevedra",
    "wof:name":"Perez Sousa Rosa Maria",
    "wof:placetype":"venue"
},
  "geometry": {"coordinates":[-8.8274269104,42.1040344238],"type":"Point"}
}