{
  "type": "Feature",
  "properties": {
    "addr:full":"Calle de Manuel Caballero Venzala, 9 Jaen Ja\u00e9n 23009",
    "addr:housenumber":"9;jae\u0301n",
    "addr:postcode":"23009",
    "addr:street":"Calle De Manuel Caballero Venzala",
    "iso:country":"ES",
    "sg:address":"Calle de Manuel Caballero Venzala, 9",
    "sg:city":"Jaen",
    "sg:orig_category":"Estancos",
    "sg:phone":"+34 953 22 47 01",
    "sg:postcode":"23009",
    "sg:province":"Ja\u00e9n",
    "wof:name":"Rosell Anton Asuncion",
    "wof:placetype":"venue"
},
  "geometry": {"coordinates":[-3.7881689072,37.7815055847],"type":"Point"}
}