{
  "type": "Feature",
  "properties": {
    "addr:full":"Calle de La Paz, S/n Vitoria-gasteiz \u00c1lava 01004",
    "addr:housenumber":"s / n",
    "addr:postcode":"01004",
    "addr:street":"Calle De La Paz",
    "iso:country":"ES",
    "sg:address":"Calle de La Paz, S/n",
    "sg:city":"Vitoria-gasteiz",
    "sg:orig_category":"Juegos Y Juguetes (al Por Menor)",
    "sg:phone":"+34 945 14 79 48",
    "sg:postcode":"01004",
    "sg:province":"\u00c1lava",
    "wof:name":"Sanchez Garcia Amaia",
    "wof:placetype":"venue"
},
  "geometry": {"coordinates":[-2.6682140827,42.8448562622],"type":"Point"}
}