{
  "type": "Feature",
  "properties": {
    "addr:full":"Avda Cabildo Insular, 27 Rincon Las Palmas 35330",
    "addr:housenumber":"27",
    "addr:postcode":"35330",
    "addr:street":"Avda Cabildo Insular",
    "iso:country":"ES",
    "sg:address":"Avda Cabildo Insular, 27",
    "sg:city":"Rincon",
    "sg:orig_category":"Electricidad Veh\u00cdculo",
    "sg:phone":"+34 928 63 12 43",
    "sg:postcode":"35330",
    "sg:province":"Las Palmas",
    "wof:name":"Rivero Ramirez Magdalena",
    "wof:placetype":"venue"
},
  "geometry": {"coordinates":[-15.5451288223,28.0638542175],"type":"Point"}
}