{
  "type": "Feature",
  "properties": {
    "iso:country":"ES",
    "sg:address":"Carr Ciutat, De, 51",
    "sg:city":"Arta",
    "sg:orig_category":"Inform\u00c1tica (estudios, Servicios, Asesor\u00cda, Formaci\u00d3n)",
    "sg:phone":"+34 971 83 59 69",
    "sg:postcode":"07570",
    "sg:province":"Islas Baleares",
    "wof:name":"Colinas Jauregui Maria Del Pilar",
    "wof:placetype":"venue"
},
  "geometry": {"coordinates":[3.3499960899,39.6910057068],"type":"Point"}
}