{
  "type": "Feature",
  "properties": {
    "addr:full":"Praz Santo Domingo, 11 Lugo Lugo 27001",
    "addr:housenumber":"11",
    "addr:postcode":"27001",
    "addr:street":"Praz Santo Domingo",
    "iso:country":"ES",
    "sg:address":"Praz Santo Domingo, 11",
    "sg:city":"Lugo",
    "sg:orig_category":"Aud\u00cdfonos",
    "sg:phone":"+34 982 25 57 37",
    "sg:postcode":"27001",
    "sg:province":"Lugo",
    "sg:website":"www.bioacustica.com",
    "wof:name":"Bioacustica Espa\u00f1ola Am S.l.",
    "wof:placetype":"venue"
},
  "geometry": {"coordinates":[-7.5566220284,43.0119743347],"type":"Point"}
}