{
  "type": "Feature",
  "properties": {
    "iso:country":"ES",
    "sg:address":"Pg Verneda, 111",
    "sg:city":"Barcelona",
    "sg:orig_category":"Empresarios",
    "sg:phone":"+34 933 13 19 91",
    "sg:postcode":"08020",
    "sg:province":"Barcelona",
    "wof:name":"Fundacion Engrunes",
    "wof:placetype":"venue"
},
  "geometry": {"coordinates":[2.2075600624,41.4252052307],"type":"Point"}
}