{
  "type": "Feature",
  "properties": {
    "addr:full":"Calle de Maestro Serrano, 3 Zaragoza Zaragoza 50005",
    "addr:housenumber":"3",
    "addr:postcode":"50005",
    "addr:street":"Calle De Maestro Serrano",
    "iso:country":"ES",
    "sg:address":"Calle de Maestro Serrano, 3",
    "sg:city":"Zaragoza",
    "sg:orig_category":"Venta, Alquiler De Instrumentos Y Accesorios De M\u00dasica",
    "sg:phone":"+34 976 56 83 93",
    "sg:postcode":"50005",
    "sg:province":"Zaragoza",
    "wof:name":"Bosco Zaragoza S.a.",
    "wof:placetype":"venue"
},
  "geometry": {"coordinates":[-0.8983240128,41.6450996399],"type":"Point"}
}