{
  "type": "Feature",
  "properties": {
    "iso:country":"ES",
    "sg:address":"Carr De Josep Melcior Gomis, 38",
    "sg:city":"Ontinyent",
    "sg:orig_category":"Estancos",
    "sg:phone":"+34 962 38 39 12",
    "sg:postcode":"46870",
    "sg:province":"Valencia",
    "wof:name":"Mico Mico Milagros De La Concepcion",
    "wof:placetype":"venue"
},
  "geometry": {"coordinates":[-0.6030989885,38.8258895874],"type":"Point"}
}