{
  "type": "Feature",
  "properties": {
    "addr:full":"Ctra Alicante-murcia, Km. 0681,9 La Aparecida Alicante 03311",
    "addr:postcode":"03311",
    "addr:street":"Ctra Alicante-Murcia Km. 0681,9",
    "iso:country":"ES",
    "sg:address":"Ctra Alicante-murcia, Km. 0681,9",
    "sg:city":"La Aparecida",
    "sg:orig_category":"Rectificaci\u00d3n, Mecanizado, Fresado",
    "sg:phone":"+34 966 73 73 07",
    "sg:postcode":"03311",
    "sg:province":"Alicante",
    "wof:name":"Rodriguez Cordoba Mecanizados S.l.l.",
    "wof:placetype":"venue"
},
  "geometry": {"coordinates":[-1.0089440346,38.0803642273],"type":"Point"}
}