{
  "type": "Feature",
  "properties": {
    "addr:full":"Calle de Feria, 16 Sevilla Sevilla 41003",
    "addr:housenumber":"16",
    "addr:postcode":"41003",
    "addr:street":"Calle De Feria",
    "iso:country":"ES",
    "sg:address":"Calle de Feria, 16",
    "sg:city":"Sevilla",
    "sg:orig_category":"Ferreter\u00cda (diversos)",
    "sg:phone":"+34 954 38 58 15",
    "sg:postcode":"41003",
    "sg:province":"Sevilla",
    "wof:name":"Rubio Alvarez Manuel",
    "wof:placetype":"venue"
},
  "geometry": {"coordinates":[-5.9915690422,37.398059845],"type":"Point"}
}