{
  "type": "Feature",
  "properties": {
    "addr:full":"Ctra Madrid Toledo (1-3), Km. 0032,0 Illescas Toledo 45200",
    "addr:housenumber":"1-3",
    "addr:postcode":"45200",
    "addr:street":"Ctra Madrid Toledo;Km. 0032,0",
    "iso:country":"ES",
    "sg:address":"Ctra Madrid Toledo (1-3), Km. 0032,0",
    "sg:city":"Illescas",
    "sg:orig_category":"Quincaller\u00cda (fabricaci\u00d3n)",
    "sg:phone":"+34 925 51 17 52",
    "sg:postcode":"45200",
    "sg:province":"Toledo",
    "wof:name":"Motorsport-a42 S.l",
    "wof:placetype":"venue"
},
  "geometry": {"coordinates":[-3.8594288826,40.1091804504],"type":"Point"}
}