{
  "type": "Feature",
  "properties": {
    "addr:full":"Avda Madrid (de), 28 Molina Segura Murcia 30500",
    "addr:housenumber":"28",
    "addr:postcode":"30500",
    "addr:street":"Avda Madrid De",
    "iso:country":"ES",
    "sg:address":"Avda Madrid (de), 28",
    "sg:city":"Molina Segura",
    "sg:orig_category":"Asesor\u00cda De Formaci\u00d3n Y Gesti\u00d3n De Personal",
    "sg:phone":"+34 968 61 63 15",
    "sg:postcode":"30500",
    "sg:province":"Murcia",
    "wof:name":"Enrique Espinosa Jaen Y Otros C.b.",
    "wof:placetype":"venue"
},
  "geometry": {"coordinates":[-1.2137479782,38.0559692383],"type":"Point"}
}