{
  "type": "Feature",
  "properties": {
    "addr:full":"C/ Amnistia Internacional, 24 Salt Girona 17190",
    "addr:housenumber":"24",
    "addr:postcode":"17190",
    "addr:street":"C / Amnistia Internacional",
    "iso:country":"ES",
    "sg:address":"C/ Amnistia Internacional, 24",
    "sg:city":"Salt",
    "sg:orig_category":"Suministros Y Materiales Industriales",
    "sg:phone":"+34 972 40 09 70",
    "sg:postcode":"17190",
    "sg:province":"Girona",
    "wof:name":"Suministros Siderurgicos De Catalu\u00f1a S.a.",
    "wof:placetype":"venue"
},
  "geometry": {"coordinates":[2.7740550041,41.9681739807],"type":"Point"}
}