{
  "type": "Feature",
  "properties": {
    "addr:full":"Calle de Castelar, 1 Santander Cantabria 39004",
    "addr:housenumber":"1",
    "addr:postcode":"39004",
    "addr:street":"Calle De Castelar",
    "iso:country":"ES",
    "sg:address":"Calle de Castelar, 1",
    "sg:city":"Santander",
    "sg:orig_category":"Arquitectos",
    "sg:phone":"+34 942 36 25 18",
    "sg:postcode":"39004",
    "sg:province":"Cantabria",
    "wof:name":"Salceda Y Quintana S.l.",
    "wof:placetype":"venue"
},
  "geometry": {"coordinates":[-3.79616189,43.4631347656],"type":"Point"}
}