{
  "type": "Feature",
  "properties": {
    "iso:country":"ES",
    "sg:address":"Calle de Rincon De San Nicolas, 4",
    "sg:city":"Plasencia",
    "sg:orig_category":"Arquitectos",
    "sg:phone":"+34 927 42 19 91",
    "sg:postcode":"10600",
    "sg:province":"C\u00e1ceres",
    "wof:name":"Serrano San Pedro Fernando Tomas",
    "wof:placetype":"venue"
},
  "geometry": {"coordinates":[-6.0930981636,40.0286216736],"type":"Point"}
}