{
  "type": "Feature",
  "properties": {
    "iso:country":"ES",
    "sg:address":"Carrer de Mossen Bellpuig (de), 2",
    "sg:city":"Tortosa",
    "sg:orig_category":"M\u00dasicos Int\u00c9rpretes",
    "sg:phone":"+34 977 44 35 94",
    "sg:postcode":"43500",
    "sg:province":"Tarragona",
    "wof:name":"Curto Pedrola Rafael",
    "wof:placetype":"venue"
},
  "geometry": {"coordinates":[0.5200610161,40.8029403687],"type":"Point"}
}