{
  "type": "Feature",
  "properties": {
    "addr:full":"Cami Serra, 11 Castell Bendinat Islas Baleares 07181",
    "addr:housenumber":"11",
    "addr:postcode":"07181",
    "addr:street":"Serra;Islas",
    "iso:country":"ES",
    "sg:address":"Cami Serra, 11",
    "sg:city":"Castell Bendinat",
    "sg:orig_category":"Andamiajes Y Escaleras De Mano (fabricaci\u00d3n, Al Por Mayor)",
    "sg:phone":"+34 971 70 00 73",
    "sg:postcode":"07181",
    "sg:province":"Islas Baleares",
    "wof:name":"Weald Estates L.t.d.",
    "wof:placetype":"venue"
},
  "geometry": {"coordinates":[2.8577105999,39.5341796875],"type":"Point"}
}