{
  "type": "Feature",
  "properties": {
    "addr:full":"Pl. Iglesia, 9 Sevilla Sevilla 41016",
    "addr:housenumber":"9",
    "addr:postcode":"41016",
    "addr:street":"Pl. Iglesia",
    "iso:country":"ES",
    "sg:address":"Pl. Iglesia, 9",
    "sg:city":"Sevilla",
    "sg:orig_category":"Transportes Por V\u00cdas Navegables",
    "sg:phone":"+34 954 40 35 13",
    "sg:postcode":"41016",
    "sg:province":"Sevilla",
    "wof:name":"Infantes Reyes Luis",
    "wof:placetype":"venue"
},
  "geometry": {"coordinates":[-5.9115209579,37.3838844299],"type":"Point"}
}