{
  "type": "Feature",
  "properties": {
    "addr:full":"El Jardincillo, S/n Cartama M\u00e1laga 29580",
    "addr:housenumber":"s",
    "addr:postcode":"29580",
    "addr:street":"/ N;Ma\u0301Laga",
    "iso:country":"ES",
    "sg:address":"El Jardincillo, S/n",
    "sg:city":"Cartama",
    "sg:orig_category":"Fabricaci\u00d3n De Productos L\u00c1cteos Y Derivados",
    "sg:phone":"+34 952 42 05 75",
    "sg:postcode":"29580",
    "sg:province":"M\u00e1laga",
    "wof:name":"Sociedad Agraria De Transformacion Ganaderos Malague\u00f1os",
    "wof:placetype":"venue"
},
  "geometry": {"coordinates":[-4.6276788712,36.71301651],"type":"Point"}
}