{
  "type": "Feature",
  "properties": {
    "addr:full":"Calle de Benito Perez Galdos, S/n Cadiz C\u00e1diz 11002",
    "addr:housenumber":"s / n",
    "addr:postcode":"11002",
    "addr:street":"Calle De Benito Perez Galdos",
    "iso:country":"ES",
    "sg:address":"Calle de Benito Perez Galdos, S/n",
    "sg:city":"Cadiz",
    "sg:orig_category":"Servidores Y Editores De Bases De Datos",
    "sg:phone":"+34 956 22 00 08",
    "sg:postcode":"11002",
    "sg:province":"C\u00e1diz",
    "sg:website":"www.codenet.es",
    "wof:name":"Codenet S.l.",
    "wof:placetype":"venue"
},
  "geometry": {"coordinates":[-6.3046088219,36.5342254639],"type":"Point"}
}