{
  "type": "Feature",
  "properties": {
    "addr:full":"Plg. Las Nieves, S/n Almaden Ciudad Real 13400",
    "addr:housenumber":"s / n",
    "addr:postcode":"almaden;13400",
    "addr:street":"Nieves;Real",
    "iso:country":"ES",
    "sg:address":"Plg. Las Nieves, S/n",
    "sg:city":"Almaden",
    "sg:orig_category":"Frutas Y Legumbres Secas (al Por Mayor)",
    "sg:phone":"+34 926 71 09 44",
    "sg:postcode":"13400",
    "sg:province":"Ciudad Real",
    "wof:name":"Santillana C.b.",
    "wof:placetype":"venue"
},
  "geometry": {"coordinates":[-4.8230538368,38.787563324],"type":"Point"}
}