{
  "type": "Feature",
  "properties": {
    "addr:full":"Avda Virgen Del Carmen, 53 Madrid Madrid 28033",
    "addr:housenumber":"53",
    "addr:postcode":"madrid;28033",
    "addr:street":"Avda Virgen Del Carmen",
    "iso:country":"ES",
    "sg:address":"Avda Virgen Del Carmen, 53",
    "sg:city":"Madrid",
    "sg:orig_category":"Agentes, Concesionarios Y Sucursales De Veh\u00cdculos",
    "sg:phone":"+34 913 81 02 73",
    "sg:postcode":"28033",
    "sg:province":"Madrid",
    "wof:name":"Talleres Perez E Hijos S.l.",
    "wof:placetype":"venue"
},
  "geometry": {"coordinates":[-3.6489980221,40.4753799438],"type":"Point"}
}