{
  "type": "Feature",
  "properties": {
    "iso:country":"ES",
    "sg:address":"Calle de Antonio Martinez De Pinillos, 39",
    "sg:city":"Almendralejo",
    "sg:orig_category":"Ingeniero",
    "sg:phone":"+34 924 66 62 71",
    "sg:postcode":"06200",
    "sg:province":"Badajoz",
    "wof:name":"J C Del Alamo Ortiz S.l.",
    "wof:placetype":"venue"
},
  "geometry": {"coordinates":[-6.4028253555,38.6827926636],"type":"Point"}
}