{
  "type": "Feature",
  "properties": {
    "iso:country":"ES",
    "sg:address":"Carrer de Zurbano, 5",
    "sg:city":"Sabadell",
    "sg:orig_category":"Internados & Ense\u00d1anza Privada",
    "sg:phone":"+34 937 25 95 06",
    "sg:postcode":"08201",
    "sg:province":"Barcelona",
    "wof:name":"Hermanas Capuchinas De La Madre Del Divino Pastor",
    "wof:placetype":"venue"
},
  "geometry": {"coordinates":[2.1110060215,41.5407867432],"type":"Point"}
}