{
  "type": "Feature",
  "properties": {
    "iso:country":"ES",
    "sg:address":"Calle de Cal (de La), 12",
    "sg:city":"Arganda",
    "sg:orig_category":"Fabricaci\u00d3n De Motores El\u00c9ctricos",
    "sg:phone":"+34 918 71 57 45",
    "sg:postcode":"28500",
    "sg:province":"Madrid",
    "wof:name":"Corral Zarapuz Julio",
    "wof:placetype":"venue"
},
  "geometry": {"coordinates":[-3.4580271244,40.3041419983],"type":"Point"}
}