{
  "type": "Feature",
  "properties": {
    "addr:full":"Calle de Medio, 12 Santander Cantabria 39...",
    "addr:housenumber":"12;39 ...",
    "addr:street":"Calle De Medio;Cantabria",
    "iso:country":"ES",
    "sg:address":"Calle de Medio, 12",
    "sg:city":"Santander",
    "sg:orig_category":"Empresas De Electricidad En General",
    "sg:phone":"+34 942 24 60 00",
    "sg:postcode":"39...",
    "sg:province":"Cantabria",
    "wof:name":"Enel Viesgo Servicios S.l.",
    "wof:placetype":"venue"
},
  "geometry": {"coordinates":[-3.8037700653,43.4628829956],"type":"Point"}
}