{
  "type": "Feature",
  "properties": {
    "addr:full":"Calle de Juan Bravo, 66 Madrid Madrid 28006",
    "addr:housenumber":"66",
    "addr:postcode":"madrid;28006",
    "addr:street":"Calle De Juan Bravo",
    "iso:country":"ES",
    "sg:address":"Calle de Juan Bravo, 66",
    "sg:city":"Madrid",
    "sg:orig_category":"Empleado Administrativo",
    "sg:phone":"+34 914 02 97 35",
    "sg:postcode":"28006",
    "sg:province":"Madrid",
    "wof:name":"Gestoria Luis Moreno S.l.",
    "wof:placetype":"venue"
},
  "geometry": {"coordinates":[-3.6730289459,40.4321365356],"type":"Point"}
}