{
  "type": "Feature",
  "properties": {
    "iso:country":"ES",
    "sg:address":"Calle de Pescadores, 2",
    "sg:city":"Logro\u00f1o",
    "sg:orig_category":"Cajas Y Embalajes Met\u00c1licos",
    "sg:phone":"+34 941 27 13 00",
    "sg:postcode":"26006",
    "sg:province":"La Rioja",
    "sg:website":"www.fedinsa.com",
    "wof:name":"Fedinsa Envases S.a.",
    "wof:placetype":"venue"
},
  "geometry": {"coordinates":[-2.4036989212,42.46043396],"type":"Point"}
}