{
  "type": "Feature",
  "properties": {
    "iso:country":"ES",
    "sg:address":"Calle de San Pedro De Mestallon, 16",
    "sg:city":"Oviedo",
    "sg:orig_category":"Ropa De Hogar (al Por Menor)",
    "sg:phone":"+34 985 21 05 36",
    "sg:postcode":"33009",
    "sg:province":"Asturias",
    "wof:name":"Diez Blanco Antonio",
    "wof:placetype":"venue"
},
  "geometry": {"coordinates":[-5.8402481079,43.3577537537],"type":"Point"}
}