{
  "type": "Feature",
  "properties": {
    "iso:country":"ES",
    "sg:address":"Av Madrid, 90",
    "sg:city":"Barcelona",
    "sg:orig_category":"Asesor\u00cda Sobre Comunicaci\u00d3n De Empresas",
    "sg:phone":"+34 934 90 07 70",
    "sg:postcode":"08028",
    "sg:province":"Barcelona",
    "wof:name":"Jimenez Mendoza Luis",
    "wof:placetype":"venue"
},
  "geometry": {"coordinates":[2.1274631023,41.3783416748],"type":"Point"}
}