{
  "type": "Feature",
  "properties": {
    "iso:country":"ES",
    "sg:address":"Pase Mirasierra, 6",
    "sg:city":"Collado Villalba",
    "sg:orig_category":"Perfumer\u00cda Y Cosm\u00c9tica (fabricaci\u00d3n, Al Por Mayor)",
    "sg:phone":"+34 918 51 78 02",
    "sg:postcode":"28400",
    "sg:province":"Madrid",
    "sg:website":"www.finderspa.com",
    "wof:name":"Spa Find Spain S.l.",
    "wof:placetype":"venue"
},
  "geometry": {"coordinates":[-3.9918398857,40.6406784058],"type":"Point"}
}