{
  "type": "Feature",
  "properties": {
    "addr:full":"Calle de Ercilla, 11 Bilbao Vizcaya 48009",
    "addr:housenumber":"11",
    "addr:postcode":"48009",
    "addr:street":"Calle De Ercilla",
    "iso:country":"ES",
    "sg:address":"Calle de Ercilla, 11",
    "sg:city":"Bilbao",
    "sg:orig_category":"Locales Y Clases De Danza",
    "sg:phone":"+34 944 24 22 43",
    "sg:postcode":"48009",
    "sg:province":"Vizcaya",
    "wof:name":"Victor Olaeta Torrezuri",
    "wof:placetype":"venue"
},
  "geometry": {"coordinates":[-2.9322419167,43.2641296387],"type":"Point"}
}