{
  "type": "Feature",
  "properties": {
    "iso:country":"ES",
    "sg:address":"Calle de Gonzalo De Berceo, 5",
    "sg:city":"Cartagena",
    "sg:orig_category":"Organismos De Reclutamiento",
    "sg:phone":"+34 968 50 67 17",
    "sg:postcode":"30203",
    "sg:province":"Murcia",
    "wof:name":"Sinac S.l.l. Riesgos Laborales",
    "wof:placetype":"venue"
},
  "geometry": {"coordinates":[-0.984022975,37.6074447632],"type":"Point"}
}