{
  "type": "Feature",
  "properties": {
    "iso:country":"ES",
    "sg:address":"Calle de Erronkari, 7",
    "sg:city":"Bilbao",
    "sg:orig_category":"Molduras, Junquillos, Listones Y Molduras Perforadas",
    "sg:phone":"+34 944 47 31 75",
    "sg:postcode":"48015",
    "sg:province":"Vizcaya",
    "wof:name":"Sdad. Recreativa San Ignacio",
    "wof:placetype":"venue"
},
  "geometry": {"coordinates":[-2.9591760635,43.2780723572],"type":"Point"}
}