{
  "type": "Feature",
  "properties": {
    "iso:country":"ES",
    "sg:address":"Calle de Cap Martinet, Des, 68",
    "sg:city":"Nuestra Se\u00e7ora De Jesus",
    "sg:orig_category":"Calcoman\u00cda, Impresi\u00d3n, Transferencia (transfert)",
    "sg:phone":"+34 971 31 21 46",
    "sg:postcode":"07819",
    "sg:province":"Islas Baleares",
    "wof:name":"De Todo Ibiza S.l",
    "wof:placetype":"venue"
},
  "geometry": {"coordinates":[1.444257021,38.934135437],"type":"Point"}
}