{
  "type": "Feature",
  "properties": {
    "iso:country":"ES",
    "sg:address":"Pl La Cruz, 4",
    "sg:city":"Molina Segura",
    "sg:orig_category":"Art\u00cdculos De Regalo (al Por Menor)",
    "sg:phone":"+34 968 61 28 68",
    "sg:postcode":"30500",
    "sg:province":"Murcia",
    "wof:name":"Miansus S.l.",
    "wof:placetype":"venue"
},
  "geometry": {"coordinates":[-1.2056479454,38.0565223694],"type":"Point"}
}