{
  "type": "Feature",
  "properties": {
    "iso:country":"ES",
    "sg:address":"Barr Bia\u00d1ez, 30",
    "sg:city":"Bia\u00d1ez",
    "sg:orig_category":"Obras Y Organismos Sociales",
    "sg:phone":"+34 946 80 60 03",
    "sg:postcode":"48890",
    "sg:province":"Vizcaya",
    "wof:name":"Misioneras Cruzadas De La Igle",
    "wof:placetype":"venue"
},
  "geometry": {"coordinates":[-3.3572499752,43.2380752563],"type":"Point"}
}