{
  "type": "Feature",
  "properties": {
    "addr:full":"Calle de Sierra Alhamilla, 12 Viator Almer\u00eda 04240",
    "addr:housenumber":"12",
    "addr:postcode":"04240",
    "addr:street":"Calle De Sierra Alhamilla;Almeri\u0301A",
    "iso:country":"ES",
    "sg:address":"Calle de Sierra Alhamilla, 12",
    "sg:city":"Viator",
    "sg:orig_category":"Transporte En General",
    "sg:phone":"+34 950 30 42 79",
    "sg:postcode":"04240",
    "sg:province":"Almer\u00eda",
    "wof:name":"Centroservi Pulpi S.l.",
    "wof:placetype":"venue"
},
  "geometry": {"coordinates":[-2.420799017,36.8813095093],"type":"Point"}
}