{
  "type": "Feature",
  "properties": {
    "iso:country":"ES",
    "sg:address":"Pje Merinos, 62",
    "sg:city":"Ecija",
    "sg:orig_category":"Arreglo, Reparaci\u00d3n, Piezas Sueltas De Televisi\u00d3n, V\u00cddeo, Hi",
    "sg:phone":"+34 954 83 33 93",
    "sg:postcode":"41400",
    "sg:province":"Sevilla",
    "wof:name":"Bersabe Sanchez Jose Luis",
    "wof:placetype":"venue"
},
  "geometry": {"coordinates":[-5.0779690742,37.5446205139],"type":"Point"}
}