{
  "type": "Feature",
  "properties": {
    "iso:country":"ES",
    "sg:address":"Calle de Lira, 5",
    "sg:city":"Alacant",
    "sg:orig_category":"Electrodom\u00c9sticos (al Por Menor)",
    "sg:phone":"+34 965 10 32 50",
    "sg:postcode":"03006",
    "sg:province":"Alicante",
    "wof:name":"Alberto Lira 5 S.l.",
    "wof:placetype":"venue"
},
  "geometry": {"coordinates":[-0.5086255074,38.3451805115],"type":"Point"}
}