{
  "type": "Feature",
  "properties": {
    "iso:country":"ES",
    "sg:address":"Carrer de Calderon De La Barca, 89",
    "sg:city":"Barcelona",
    "sg:orig_category":"Molduras, Junquillos, Listones Y Molduras Perforadas",
    "sg:phone":"+34 933 57 30 49",
    "sg:postcode":"08032",
    "sg:province":"Barcelona",
    "wof:name":"Ramirez Gonzalez Jose",
    "wof:placetype":"venue"
},
  "geometry": {"coordinates":[2.1569440365,41.4206237793],"type":"Point"}
}