{
  "type": "Feature",
  "properties": {
    "addr:full":"Avda San Jose, 205 Zaragoza Zaragoza 50007",
    "addr:housenumber":"205",
    "addr:postcode":"50007",
    "addr:street":"Avda San Jose",
    "iso:country":"ES",
    "sg:address":"Avda San Jose, 205",
    "sg:city":"Zaragoza",
    "sg:orig_category":"Elementos Para Suelos Prefabricados",
    "sg:phone":"+34 976 27 11 32",
    "sg:postcode":"50007",
    "sg:province":"Zaragoza",
    "wof:name":"Perruca Artigas Salvador",
    "wof:placetype":"venue"
},
  "geometry": {"coordinates":[-0.879471004,41.6357040405],"type":"Point"}
}