{
  "type": "Feature",
  "properties": {
    "addr:full":"Calle de Ave Maria, 2 Granada Granada 18009",
    "addr:housenumber":"2",
    "addr:postcode":"18009",
    "addr:street":"Calle De Ave Maria",
    "iso:country":"ES",
    "sg:address":"Calle de Ave Maria, 2",
    "sg:city":"Granada",
    "sg:orig_category":"Aparcamientos (infraestructuras, Accesorios)",
    "sg:phone":"+34 958 22 40 21",
    "sg:postcode":"18009",
    "sg:province":"Granada",
    "wof:name":"Garcia Cabrerizo Antonio",
    "wof:placetype":"venue"
},
  "geometry": {"coordinates":[-3.5908460617,37.1706581116],"type":"Point"}
}