{
  "type": "Feature",
  "properties": {
    "addr:full":"Ctra. S. Infantes, 10 Covarrubias Burgos 09346",
    "addr:housenumber":"10",
    "addr:postcode":"09346",
    "addr:street":"Ctra. S. Infantes",
    "iso:country":"ES",
    "sg:address":"Ctra. S. Infantes, 10",
    "sg:city":"Covarrubias",
    "sg:orig_category":"Plomeros",
    "sg:phone":"+34 947 40 65 28",
    "sg:postcode":"09346",
    "sg:province":"Burgos",
    "wof:name":"Jorge Moneo Juan Luis",
    "wof:placetype":"venue"
},
  "geometry": {"coordinates":[-3.5233221054,42.0590133667],"type":"Point"}
}