{
  "type": "Feature",
  "properties": {
    "addr:full":"Calle de Alicante, 24 Ojos De Garza Las Palmas 35219",
    "addr:housenumber":"24",
    "addr:postcode":"35219",
    "addr:street":"Calle De Alicante;Las Palmas",
    "iso:country":"ES",
    "sg:address":"Calle de Alicante, 24",
    "sg:city":"Ojos De Garza",
    "sg:orig_category":"Centros De Educaci\u00d3n Especial",
    "sg:phone":"+34 928 57 46 78",
    "sg:postcode":"35219",
    "sg:province":"Las Palmas",
    "wof:name":"Gobierno De Canarias",
    "wof:placetype":"venue"
},
  "geometry": {"coordinates":[-15.3957204819,27.9442920685],"type":"Point"}
}