{
  "type": "Feature",
  "properties": {
    "addr:full":"Calle de Cardenal Cisneros, 21 Madrid Madrid 28010",
    "addr:housenumber":"21",
    "addr:postcode":"madrid;28010",
    "addr:street":"Calle De Cardenal Cisneros",
    "iso:country":"ES",
    "sg:address":"Calle de Cardenal Cisneros, 21",
    "sg:city":"Madrid",
    "sg:orig_category":"Panader\u00cdas, Panader\u00cdas",
    "sg:phone":"+34 914 48 97 22",
    "sg:postcode":"28010",
    "sg:province":"Madrid",
    "wof:name":"Dycarta S.l.",
    "wof:placetype":"venue"
},
  "geometry": {"coordinates":[-3.7018749714,40.4307518005],"type":"Point"}
}