{
  "type": "Feature",
  "properties": {
    "addr:full":"Carr Almogavers, 4 Badalona Barcelona 08915",
    "addr:housenumber":"4",
    "addr:postcode":"08915",
    "addr:street":"Carr Almogavers",
    "iso:country":"ES",
    "sg:address":"Carr Almogavers, 4",
    "sg:city":"Badalona",
    "sg:orig_category":"Fabricaci\u00d3n De Correas De Transmisi\u00d3n",
    "sg:phone":"+34 934 65 03 74",
    "sg:postcode":"08915",
    "sg:province":"Barcelona",
    "wof:name":"Sociedad Industrial De Transmisiones S.a.",
    "wof:placetype":"venue"
},
  "geometry": {"coordinates":[2.2502970695,41.4582519531],"type":"Point"}
}