{
  "type": "Feature",
  "properties": {
    "addr:full":"Carrer de Sicilia, 29 Sabadell Barcelona 08205",
    "addr:housenumber":"29",
    "addr:postcode":"08205",
    "addr:street":"Carrer De Sicilia",
    "iso:country":"ES",
    "sg:address":"Carrer de Sicilia, 29",
    "sg:city":"Sabadell",
    "sg:orig_category":"Empresas De Limpieza",
    "sg:phone":"+34 937 25 45 53",
    "sg:postcode":"08205",
    "sg:province":"Barcelona",
    "wof:name":"Caprisa Neteges S.l.",
    "wof:placetype":"venue"
},
  "geometry": {"coordinates":[2.0857748985,41.5477867126],"type":"Point"}
}