{
  "type": "Feature",
  "properties": {
    "iso:country":"ES",
    "sg:address":"Pase Villa Esperanza, S/n",
    "sg:city":"Torre-pacheco",
    "sg:orig_category":"Zapatos (al Por Menor)",
    "sg:phone":"+34 968 57 90 53",
    "sg:postcode":"30700",
    "sg:province":"Murcia",
    "wof:name":"Mero\u00f1o Domenech Mari Carmen",
    "wof:placetype":"venue"
},
  "geometry": {"coordinates":[-0.9550200105,37.7395248413],"type":"Point"}
}