{
  "type": "Feature",
  "properties": {
    "iso:country":"ES",
    "sg:address":"Rua Lopez De Neira, 22",
    "sg:city":"Vigo",
    "sg:orig_category":"Abogados",
    "sg:phone":"+34 986 22 29 65",
    "sg:postcode":"36202",
    "sg:province":"Pontevedra",
    "wof:name":"Tinoco Lavado Luis Maria",
    "wof:placetype":"venue"
},
  "geometry": {"coordinates":[-8.7244968414,42.2363395691],"type":"Point"}
}