{
  "type": "Feature",
  "properties": {
    "addr:full":"Barr Barrondo, S/n Moyordin-barrondo Vizcaya 48480",
    "addr:housenumber":"s",
    "addr:postcode":"48480",
    "addr:street":"/ N",
    "iso:country":"ES",
    "sg:address":"Barr Barrondo, S/n",
    "sg:city":"Moyordin-barrondo",
    "sg:orig_category":"Electricidad: Equipos Industriales, Componentes (fabricaci\u00d3n)",
    "sg:phone":"+34 946 71 32 67",
    "sg:postcode":"48480",
    "sg:province":"Vizcaya",
    "wof:name":"Goizbelan S.l.",
    "wof:placetype":"venue"
},
  "geometry": {"coordinates":[-2.8896090984,43.2052345276],"type":"Point"}
}