{
  "type": "Feature",
  "properties": {
    "iso:country":"ES",
    "sg:address":"Calle de Cruces (las), S/n",
    "sg:city":"Santander",
    "sg:orig_category":"Instalaci\u00d3n De Sanitarios",
    "sg:phone":"+34 942 27 10 74",
    "sg:postcode":"39005",
    "sg:province":"Cantabria",
    "wof:name":"Ayuntamiento De Santander",
    "wof:placetype":"venue"
},
  "geometry": {"coordinates":[-3.7859082222,43.472694397],"type":"Point"}
}