{
  "type": "Feature",
  "properties": {
    "addr:full":"Pg Cementiri, S/n Figueres Girona 17600",
    "addr:housenumber":"s / n",
    "addr:postcode":"17600",
    "addr:street":"Pg Cementiri",
    "iso:country":"ES",
    "sg:address":"Pg Cementiri, S/n",
    "sg:city":"Figueres",
    "sg:orig_category":"Venta, Colocaci\u00d3n, Reparaci\u00d3n De Radiadores Para Veh\u00cdculos",
    "sg:phone":"+34 972 67 86 26",
    "sg:postcode":"17600",
    "sg:province":"Girona",
    "wof:name":"Giro Clotas Jose Maria",
    "wof:placetype":"venue"
},
  "geometry": {"coordinates":[2.9722499847,42.2642860413],"type":"Point"}
}