{
  "type": "Feature",
  "properties": {
    "addr:full":"Calle de Leon Y Castillo, 4 Arrecife Las Palmas 35500",
    "addr:housenumber":"4",
    "addr:postcode":"35500",
    "addr:street":"Calle De Leon Y Castillo",
    "iso:country":"ES",
    "sg:address":"Calle de Leon Y Castillo, 4",
    "sg:city":"Arrecife",
    "sg:orig_category":"Fabricaci\u00d3n De Productos Textiles Sin Tejer",
    "sg:phone":"+34 928 81 31 86",
    "sg:postcode":"35500",
    "sg:province":"Las Palmas",
    "wof:name":"Vallesiete S.a.",
    "wof:placetype":"venue"
},
  "geometry": {"coordinates":[-13.5482988358,28.9586372375],"type":"Point"}
}