{
  "type": "Feature",
  "properties": {
    "addr:full":"Calle de San Blas, 8 Maella Zaragoza 50710",
    "addr:housenumber":"8",
    "addr:postcode":"50710",
    "addr:street":"Calle De San Blas",
    "iso:country":"ES",
    "sg:address":"Calle de San Blas, 8",
    "sg:city":"Maella",
    "sg:orig_category":"Fabricaci\u00d3n De Art\u00cdculos Y Equipos Deportivos Y De Ocio",
    "sg:phone":"+34 976 63 80 58",
    "sg:postcode":"50710",
    "sg:province":"Zaragoza",
    "wof:name":"Antonio Gargallo Guimera",
    "wof:placetype":"venue"
},
  "geometry": {"coordinates":[0.1418502927,41.1242446899],"type":"Point"}
}