{
  "type": "Feature",
  "properties": {
    "addr:full":"Plaz Feria De La, 19 Palmas De Gran Canaria Las Palmas 35003",
    "addr:postcode":"35003",
    "iso:country":"ES",
    "sg:address":"Plaz Feria De La, 19",
    "sg:city":"Palmas De Gran Canaria",
    "sg:orig_category":"Expertos Contables",
    "sg:phone":"+34 928 37 31 64",
    "sg:postcode":"35003",
    "sg:province":"Las Palmas",
    "wof:name":"Consulting Finaco Sl",
    "wof:placetype":"venue"
},
  "geometry": {"coordinates":[-15.4196901321,28.1116905212],"type":"Point"}
}