{
  "type": "Feature",
  "properties": {
    "iso:country":"ES",
    "sg:address":"Pl. F. Huarte, 2",
    "sg:city":"Iru\u00f1a",
    "sg:orig_category":"Marketing Telef\u00d3nico",
    "sg:phone":"+34 948 19 67 18",
    "sg:postcode":"31007",
    "sg:province":"Navarra",
    "wof:name":"Blanco Martin Jose Angel",
    "wof:placetype":"venue"
},
  "geometry": {"coordinates":[-1.6539260149,42.8043479919],"type":"Point"}
}