{
  "type": "Feature",
  "properties": {
    "addr:full":"Calle de Concordia (de La), 6 Mostoles Madrid 28931",
    "addr:postcode":"28931",
    "addr:street":"Calle De Concordia De La 6 Mostoles",
    "iso:country":"ES",
    "sg:address":"Calle de Concordia (de La), 6",
    "sg:city":"Mostoles",
    "sg:orig_category":"Colchones (fabricaci\u00d3n, Al Por Mayor, Al Por Menor)",
    "sg:phone":"+34 916 14 82 36",
    "sg:postcode":"28931",
    "sg:province":"Madrid",
    "wof:name":"Ruiz Negro Serafin",
    "wof:placetype":"venue"
},
  "geometry": {"coordinates":[-3.8602368832,40.3250732422],"type":"Point"}
}