{
  "type": "Feature",
  "properties": {
    "iso:country":"ES",
    "sg:address":"Calle de Virgen De La Cinta, 7",
    "sg:city":"Sevilla",
    "sg:orig_category":"Abogados",
    "sg:phone":"+34 954 27 51 02",
    "sg:postcode":"41011",
    "sg:province":"Sevilla",
    "wof:name":"Pozo Solis Juana Maria",
    "wof:placetype":"venue"
},
  "geometry": {"coordinates":[-5.9961118698,37.3724403381],"type":"Point"}
}