{
  "type": "Feature",
  "properties": {
    "iso:country":"ES",
    "sg:address":"Calle de Rios Rosas, 39",
    "sg:city":"Madrid",
    "sg:orig_category":"Lencer\u00cda Femenina, Corseter\u00cda, Trajes De Ba\u00d1o (al Por Menor)",
    "sg:phone":"+34 914 41 08 41",
    "sg:postcode":"28003",
    "sg:province":"Madrid",
    "wof:name":"Rizos, S.l.",
    "wof:placetype":"venue"
},
  "geometry": {"coordinates":[-3.6979150772,40.4419555664],"type":"Point"}
}