{
  "type": "Feature",
  "properties": {
    "iso:country":"ES",
    "sg:address":"Lonja Pescado, S/n",
    "sg:city":"Malpica Berganti\u00f1os",
    "sg:orig_category":"Empresas Portuarias",
    "sg:phone":"+34 981 72 00 76",
    "sg:postcode":"15113",
    "sg:province":"La Coru\u00f1a",
    "wof:name":"Portos De Galicia-grupo De Portos De Galicia",
    "wof:placetype":"venue"
},
  "geometry": {"coordinates":[-8.8115386963,43.3227500916],"type":"Point"}
}