{
  "type": "Feature",
  "properties": {
    "iso:country":"ES",
    "sg:address":"Calle de Calderas, 6",
    "sg:city":"Torrejon Ardoz",
    "sg:orig_category":"Mercer\u00cda, Lencer\u00cda (al Por Menor)",
    "sg:phone":"+34 916 75 34 30",
    "sg:postcode":"28850",
    "sg:province":"Madrid",
    "wof:name":"Hernandez Garcia Manuel",
    "wof:placetype":"venue"
},
  "geometry": {"coordinates":[-3.4773964882,40.4570198059],"type":"Point"}
}