{
  "type": "Feature",
  "properties": {
    "iso:country":"ES",
    "sg:address":"C/ Sant Tomas, 9",
    "sg:city":"Alcoi",
    "sg:orig_category":"Muebles, Minoristas",
    "sg:phone":"+34 965 54 28 84",
    "sg:postcode":"03801",
    "sg:province":"Alicante",
    "wof:name":"Mobleimport S.l.",
    "wof:placetype":"venue"
},
  "geometry": {"coordinates":[-0.4744989872,38.6992912292],"type":"Point"}
}