{
  "type": "Feature",
  "properties": {
    "iso:country":"ES",
    "sg:address":"Calle de Monta\u00d1a Chica, S/n",
    "sg:city":"Cristianos",
    "sg:orig_category":"Radiocomunicaciones, Telefon\u00cda M\u00d3vil, Radiomensajer\u00cda: Servicios, Comercializaci\u00d3n",
    "sg:phone":"+34 922 75 19 96",
    "sg:postcode":"38650",
    "sg:province":"Santa Cruz De Tenerife",
    "wof:name":"Tecnisur Tenerife S.l.",
    "wof:placetype":"venue"
},
  "geometry": {"coordinates":[-16.7171134949,28.0532512665],"type":"Point"}
}