{
  "type": "Feature",
  "properties": {
    "iso:country":"ES",
    "sg:address":"Pase Circunvalacion (de), 80",
    "sg:city":"Albacete",
    "sg:orig_category":"Aceites Y Grasas Alimentarias (fabricaci\u00d3n, Al Por Mayor)",
    "sg:phone":"+34 967 22 09 91",
    "sg:postcode":"02006",
    "sg:province":"Albacete",
    "wof:name":"Servicios Oleicolas Navarro Sl",
    "wof:placetype":"venue"
},
  "geometry": {"coordinates":[-1.8678070307,38.9888534546],"type":"Point"}
}