{
  "type": "Feature",
  "properties": {
    "iso:country":"ES",
    "sg:address":"Urb Sierra Mijas, 4",
    "sg:city":"Fuengirola",
    "sg:orig_category":"Molduras, Junquillos, Listones Y Molduras Perforadas",
    "sg:phone":"+34 952 46 23 82",
    "sg:postcode":"29640",
    "sg:province":"M\u00e1laga",
    "wof:name":"Calvo Berlanga Isabel Maria",
    "wof:placetype":"venue"
},
  "geometry": {"coordinates":[-4.6330537796,36.5426368713],"type":"Point"}
}