{
  "type": "Feature",
  "properties": {
    "iso:country":"ES",
    "sg:address":"Ctra Canillas, 35",
    "sg:city":"Madrid",
    "sg:orig_category":"Bazares, Art\u00cdculos De Limpieza Y De Cocina (al Por Menor)",
    "sg:phone":"+34 913 88 55 68",
    "sg:postcode":"28043",
    "sg:province":"Madrid",
    "wof:name":"Zhu  Nika",
    "wof:placetype":"venue"
},
  "geometry": {"coordinates":[-3.6483919621,40.4630966187],"type":"Point"}
}