{
  "type": "Feature",
  "properties": {
    "addr:full":"C/ Angel Guimera, 93 Salt Girona 17190",
    "addr:housenumber":"93",
    "addr:postcode":"17190",
    "addr:street":"C / Angel Guimera",
    "iso:country":"ES",
    "sg:address":"C/ Angel Guimera, 93",
    "sg:city":"Salt",
    "sg:orig_category":"Ropa Y Art\u00cdculos Pre",
    "sg:phone":"+34 972 23 09 03",
    "sg:postcode":"17190",
    "sg:province":"Girona",
    "wof:name":"Alcalde Pe\u00f1a Blanca",
    "wof:placetype":"venue"
},
  "geometry": {"coordinates":[2.7904956341,41.9741516113],"type":"Point"}
}