{
  "type": "Feature",
  "properties": {
    "iso:country":"ES",
    "sg:address":"Calle de Abogado Andres Charques, 7",
    "sg:city":"Alacant",
    "sg:orig_category":"Servicios De Telecomunicaciones",
    "sg:phone":"+34 965 10 59 99",
    "sg:postcode":"03006",
    "sg:province":"Alicante",
    "wof:name":"Dajiva Comunica S.l.",
    "wof:placetype":"venue"
},
  "geometry": {"coordinates":[-0.5207591057,38.3481712341],"type":"Point"}
}