{
  "type": "Feature",
  "properties": {
    "iso:country":"ES",
    "sg:address":"Ctra Canya, La, S/n",
    "sg:city":"Olot",
    "sg:orig_category":"Asesor\u00cda Sobre Comunicaci\u00d3n De Empresas",
    "sg:phone":"+34 972 26 54 99",
    "sg:postcode":"17800",
    "sg:province":"Girona",
    "wof:name":"Proyectos Asesoria Y Servicios S.a.",
    "wof:placetype":"venue"
},
  "geometry": {"coordinates":[2.4992148876,42.189994812],"type":"Point"}
}