{
  "type": "Feature",
  "properties": {
    "iso:country":"ES",
    "sg:address":"Carr Primer De Maig, 15",
    "sg:city":"Gandia",
    "sg:orig_category":"Peluquer\u00cdas, Peluquer\u00cda Mixta",
    "sg:phone":"+34 962 86 03 40",
    "sg:postcode":"46700",
    "sg:province":"Valencia",
    "wof:name":"Orengo Peiro Juan",
    "wof:placetype":"venue"
},
  "geometry": {"coordinates":[-0.1882440001,38.9670944214],"type":"Point"}
}