{
  "type": "Feature",
  "properties": {
    "iso:country":"ES",
    "sg:address":"Kale Nagusia, 25",
    "sg:city":"Beasain",
    "sg:orig_category":"Bazares, Art\u00cdculos De Limpieza Y De Cocina (al Por Menor)",
    "sg:phone":"+34 943 16 18 32",
    "sg:postcode":"20200",
    "sg:province":"Guip\u00f9zcoa",
    "wof:name":"Gorrochategui Orue Maider",
    "wof:placetype":"venue"
},
  "geometry": {"coordinates":[-2.1944589615,43.0469207764],"type":"Point"}
}