{
  "type": "Feature",
  "properties": {
    "addr:full":"Calle de Pablo Casals, 17 Alhama Murcia Murcia 30840",
    "addr:housenumber":"17",
    "addr:postcode":"30840",
    "addr:street":"Calle De Pablo Casals",
    "iso:country":"ES",
    "sg:address":"Calle de Pablo Casals, 17",
    "sg:city":"Alhama Murcia",
    "sg:orig_category":"Electrodom\u00c9sticos (al Por Menor)",
    "sg:phone":"+34 968 63 93 85",
    "sg:postcode":"30840",
    "sg:province":"Murcia",
    "wof:name":"Espadas Lopez Jose",
    "wof:placetype":"venue"
},
  "geometry": {"coordinates":[-1.4317090511,37.8521385193],"type":"Point"}
}