{
  "type": "Feature",
  "properties": {
    "addr:full":"Avda Zamora (de), 50 Ourense Ourense 32005",
    "addr:housenumber":"50",
    "addr:postcode":"32005",
    "addr:street":"Avda Zamora De",
    "iso:country":"ES",
    "sg:address":"Avda Zamora (de), 50",
    "sg:city":"Ourense",
    "sg:orig_category":"Contenedores (mercanc\u00cdas)",
    "sg:phone":"+34 988 22 72 76",
    "sg:postcode":"32005",
    "sg:province":"Ourense",
    "wof:name":"Campos Gabriel Manuel",
    "wof:placetype":"venue"
},
  "geometry": {"coordinates":[-7.8637719154,42.3273887634],"type":"Point"}
}