{
  "type": "Feature",
  "properties": {
    "addr:full":"Plaz Nueva, 4 Bilbao Vizcaya 48005",
    "addr:housenumber":"4",
    "addr:postcode":"48005",
    "addr:street":"Plaz Nueva",
    "iso:country":"ES",
    "sg:address":"Plaz Nueva, 4",
    "sg:city":"Bilbao",
    "sg:orig_category":"Farmacias",
    "sg:phone":"+34 944 15 46 27",
    "sg:postcode":"48005",
    "sg:province":"Vizcaya",
    "wof:name":"Fuldain Iturri Miren Itziar",
    "wof:placetype":"venue"
},
  "geometry": {"coordinates":[-2.9253809452,43.2584495544],"type":"Point"}
}