{
  "type": "Feature",
  "properties": {
    "iso:country":"ES",
    "sg:address":"Calle de Joaquin Blume (de), 3",
    "sg:city":"Mostoles",
    "sg:orig_category":"Reposter\u00cdas",
    "sg:phone":"+34 916 13 45 62",
    "sg:postcode":"28935",
    "sg:province":"Madrid",
    "wof:name":"Segovia De La Vega Benita",
    "wof:placetype":"venue"
},
  "geometry": {"coordinates":[-3.8856489658,40.3267364502],"type":"Point"}
}