{
  "type": "Feature",
  "properties": {
    "iso:country":"ES",
    "sg:address":"Calle de Papin, 10",
    "sg:city":"Salamanca",
    "sg:orig_category":"Centros Empresariales",
    "sg:phone":"+34 923 25 33 96",
    "sg:postcode":"37007",
    "sg:province":"Salamanca",
    "wof:name":"Recreativos Goywer S.l.",
    "wof:placetype":"venue"
},
  "geometry": {"coordinates":[-5.6680779457,40.9703483582],"type":"Point"}
}