{
  "type": "Feature",
  "properties": {
    "addr:full":"Av Sant Miquel Del Pui, 16 Pobla Segur Lleida 25500",
    "addr:housenumber":"16",
    "addr:postcode":"25500",
    "addr:street":"Av Sant Miquel Del Pui",
    "iso:country":"ES",
    "sg:address":"Av Sant Miquel Del Pui, 16",
    "sg:city":"Pobla Segur",
    "sg:orig_category":"Droguer\u00cdas (al Por Menor)",
    "sg:phone":"+34 973 68 13 32",
    "sg:postcode":"25500",
    "sg:province":"Lleida",
    "wof:name":"Miquel,s S.c.p.",
    "wof:placetype":"venue"
},
  "geometry": {"coordinates":[0.9670779705,42.2480583191],"type":"Point"}
}