{
  "type": "Feature",
  "properties": {
    "addr:full":"Avda Madrid, 2 Valdecaballeros Badajoz 06689",
    "addr:housenumber":"2",
    "addr:postcode":"06689",
    "addr:street":"Avda Madrid",
    "iso:country":"ES",
    "sg:address":"Avda Madrid, 2",
    "sg:city":"Valdecaballeros",
    "sg:orig_category":"Autob\u00das (explotaci\u00d3n Y Servicios De)",
    "sg:phone":"+34 924 64 32 61",
    "sg:postcode":"06689",
    "sg:province":"Badajoz",
    "wof:name":"Autocares Valdecaballeros",
    "wof:placetype":"venue"
},
  "geometry": {"coordinates":[-5.1853508949,39.2418289185],"type":"Point"}
}