{
  "type": "Feature",
  "properties": {
    "addr:full":"Avda Euzkadi, 8 Barakaldo Vizcaya 48902",
    "addr:housenumber":"8",
    "addr:postcode":"48902",
    "addr:street":"Avda Euzkadi",
    "iso:country":"ES",
    "sg:address":"Avda Euzkadi, 8",
    "sg:city":"Barakaldo",
    "sg:orig_category":"Papel Pintado (al Por Menor)",
    "sg:phone":"+34 944 99 07 09",
    "sg:postcode":"48902",
    "sg:province":"Vizcaya",
    "wof:name":"Decoraciones Sonia, S.a.",
    "wof:placetype":"venue"
},
  "geometry": {"coordinates":[-2.9896380901,43.2937202454],"type":"Point"}
}