{
  "type": "Feature",
  "properties": {
    "addr:full":"Avda Euskadi Etorbidea, 7 Pasaia Guip\u00f9zcoa 20110",
    "addr:housenumber":"7",
    "addr:postcode":"20110",
    "addr:street":"Avda Euskadi Etorbidea;Guipu\u0300Zcoa",
    "iso:country":"ES",
    "sg:address":"Avda Euskadi Etorbidea, 7",
    "sg:city":"Pasaia",
    "sg:orig_category":"Estilistas Y Estudios De Estilo De Corte Y Confecci\u00d3n",
    "sg:phone":"+34 943 39 08 12",
    "sg:postcode":"20110",
    "sg:province":"Guip\u00f9zcoa",
    "wof:name":"Confecciones Ubeda S.l.",
    "wof:placetype":"venue"
},
  "geometry": {"coordinates":[-1.9217879772,43.3260040283],"type":"Point"}
}