{
  "type": "Feature",
  "properties": {
    "iso:country":"ES",
    "sg:address":"Calle de Doctor Rojas Ballesteros, 2",
    "sg:city":"Granada",
    "sg:orig_category":"Ense\u00d1anza: Peluquer\u00cda Est\u00c9tica",
    "sg:phone":"+34 958 15 48 10",
    "sg:postcode":"18012",
    "sg:province":"Granada",
    "wof:name":"Romero Rodriguez Enrique",
    "wof:placetype":"venue"
},
  "geometry": {"coordinates":[-3.6069800854,37.1903762817],"type":"Point"}
}