{
  "type": "Feature",
  "properties": {
    "addr:full":"Ctra Nacional V Madrid-lisboa, Km. 0402,0 Badajoz Badajoz 06008",
    "addr:postcode":"06008",
    "addr:street":"Ctra Nacional V Madrid-Lisboa Km. 0402,0",
    "iso:country":"ES",
    "sg:address":"Ctra Nacional V Madrid-lisboa, Km. 0402,0",
    "sg:city":"Badajoz",
    "sg:orig_category":"Venta, Montaje De Neum\u00c1ticos",
    "sg:phone":"+34 924 25 32 11",
    "sg:postcode":"06008",
    "sg:province":"Badajoz",
    "wof:name":"Autodisco S. A.",
    "wof:placetype":"venue"
},
  "geometry": {"coordinates":[-6.6745042801,38.9741096497],"type":"Point"}
}