{
  "type": "Feature",
  "properties": {
    "iso:country":"ES",
    "sg:address":"Rua Jesus Soria, 10",
    "sg:city":"Ourense",
    "sg:orig_category":"Instalaci\u00d3n, Reparaci\u00d3n De Ascensores Y Montacargas",
    "sg:phone":"+34 988 24 34 24",
    "sg:postcode":"32002",
    "sg:province":"Ourense",
    "wof:name":"Thyssenkrupp Elevadores S.l.",
    "wof:placetype":"venue"
},
  "geometry": {"coordinates":[-7.8692350388,42.3401031494],"type":"Point"}
}