{
  "type": "Feature",
  "properties": {
    "iso:country":"ES",
    "sg:address":"Calle de Damaso Alonso, 16",
    "sg:city":"Alcala Henares",
    "sg:orig_category":"Promotores Constructores",
    "sg:phone":"+34 918 02 21 69",
    "sg:postcode":"28806",
    "sg:province":"Madrid",
    "wof:name":"Promociones Y Construcciones Granmansion S.l.",
    "wof:placetype":"venue"
},
  "geometry": {"coordinates":[-3.3753614426,40.4958114624],"type":"Point"}
}