{
  "type": "Feature",
  "properties": {
    "iso:country":"ES",
    "sg:address":"Calle de San Cristobal, 6",
    "sg:city":"Huescar",
    "sg:orig_category":"Art\u00cdculos De Regalo (al Por Menor)",
    "sg:phone":"+34 958 74 03 84",
    "sg:postcode":"18830",
    "sg:province":"Granada",
    "wof:name":"Rodriguez Sanchez Marcela",
    "wof:placetype":"venue"
},
  "geometry": {"coordinates":[-2.5404129028,37.808467865],"type":"Point"}
}