{
  "type": "Feature",
  "properties": {
    "addr:full":"Calle de San Pascual, 9 Orihuela Alicante 03300",
    "addr:housenumber":"9",
    "addr:postcode":"03300",
    "addr:street":"Calle De San Pascual",
    "iso:country":"ES",
    "sg:address":"Calle de San Pascual, 9",
    "sg:city":"Orihuela",
    "sg:orig_category":"Trajes Y Adornos De Boda (confecci\u00d3n, Al Por Menor)",
    "sg:phone":"+34 965 30 56 53",
    "sg:postcode":"03300",
    "sg:province":"Alicante",
    "wof:name":"Ruiz Vegara Dolores",
    "wof:placetype":"venue"
},
  "geometry": {"coordinates":[-0.9468960166,38.0846862793],"type":"Point"}
}