{
  "type": "Feature",
  "properties": {
    "addr:full":"Plaz San Antonio, 13 Vinaros Castell\u00f3n 12500",
    "addr:housenumber":"13",
    "addr:postcode":"12500",
    "addr:street":"Plaz San Antonio",
    "iso:country":"ES",
    "sg:address":"Plaz San Antonio, 13",
    "sg:city":"Vinaros",
    "sg:orig_category":"Molduras, Junquillos, Listones Y Molduras Perforadas",
    "sg:phone":"+34 964 45 14 86",
    "sg:postcode":"12500",
    "sg:province":"Castell\u00f3n",
    "wof:name":"Iba\u00f1ez Clausich Manuel",
    "wof:placetype":"venue"
},
  "geometry": {"coordinates":[0.4749450088,40.4711990356],"type":"Point"}
}