{
  "type": "Feature",
  "properties": {
    "iso:country":"ES",
    "sg:address":"Av Peguera, 62",
    "sg:city":"Peguera",
    "sg:orig_category":"Transportes Por Carretera: Lotes Completos, Mercanc\u00cdas Diversas",
    "sg:phone":"+34 971 68 60 99",
    "sg:postcode":"07160",
    "sg:province":"Islas Baleares",
    "wof:name":"Torrens Esteve Sebastian",
    "wof:placetype":"venue"
},
  "geometry": {"coordinates":[2.4519529343,39.5377426147],"type":"Point"}
}