{
  "type": "Feature",
  "properties": {
    "addr:full":"Calle de Pintor Francisco Domingo, 23 Monte Vedat Valencia 46901",
    "addr:housenumber":"23",
    "addr:postcode":"46901",
    "addr:street":"Calle De Pintor Francisco Domingo;Vedat",
    "iso:country":"ES",
    "sg:address":"Calle de Pintor Francisco Domingo, 23",
    "sg:city":"Monte Vedat",
    "sg:orig_category":"Empresas De Escayolas",
    "sg:phone":"+34 961 55 18 16",
    "sg:postcode":"46901",
    "sg:province":"Valencia",
    "wof:name":"Rubio Jerez Crispulo",
    "wof:placetype":"venue"
},
  "geometry": {"coordinates":[-0.490485996,39.426109314],"type":"Point"}
}