{
  "type": "Feature",
  "properties": {
    "addr:full":"Carr Unio, 3 Albi Lleida 25450",
    "addr:housenumber":"3",
    "addr:postcode":"25450",
    "addr:street":"Carr Unio",
    "iso:country":"ES",
    "sg:address":"Carr Unio, 3",
    "sg:city":"Albi",
    "sg:orig_category":"Cr\u00cda De Cerdos",
    "sg:phone":"+34 973 17 50 78",
    "sg:postcode":"25450",
    "sg:province":"Lleida",
    "wof:name":"Bergcuni S.l.",
    "wof:placetype":"venue"
},
  "geometry": {"coordinates":[0.9390789866,41.4253921509],"type":"Point"}
}