{
  "type": "Feature",
  "properties": {
    "iso:country":"ES",
    "sg:address":"Barr Estacion, S/n",
    "sg:city":"Ciempozuelos",
    "sg:orig_category":"Aceites Y Grasas Alimentarias (fabricaci\u00d3n, Al Por Mayor)",
    "sg:phone":"+34 918 93 21 51",
    "sg:postcode":"28350",
    "sg:province":"Madrid",
    "wof:name":"Grasas Del Centro S.a.",
    "wof:placetype":"venue"
},
  "geometry": {"coordinates":[-3.6104741096,40.1590614319],"type":"Point"}
}