{
  "type": "Feature",
  "properties": {
    "iso:country":"ES",
    "sg:address":"Calle de Generalisimo, 57",
    "sg:city":"Socuellamos",
    "sg:orig_category":"Asociaciones Humanitarias, De Cooperaci\u00d3n, De Acci\u00d3n Social",
    "sg:phone":"+34 926 50 06 47",
    "sg:postcode":"13630",
    "sg:province":"Ciudad Real",
    "wof:name":"Caritas Interparroquial",
    "wof:placetype":"venue"
},
  "geometry": {"coordinates":[-2.7926149368,39.2835197449],"type":"Point"}
}