{
  "type": "Feature",
  "properties": {
    "addr:full":"Calle de Andalucia, 1 Linea De La Concepcion C\u00e1diz 11300",
    "addr:housenumber":"1",
    "addr:postcode":"11300",
    "addr:street":"Calle De Andalucia;Ca\u0301Diz",
    "iso:country":"ES",
    "sg:address":"Calle de Andalucia, 1",
    "sg:city":"Linea De La Concepcion",
    "sg:orig_category":"Fotograf\u00cda Y Cine: Aparatos, Pel\u00cdculas Y Accesorios (al Por Menor)",
    "sg:phone":"+34 956 17 45 78",
    "sg:postcode":"11300",
    "sg:province":"C\u00e1diz",
    "wof:name":"Aragon Cazalla Juan",
    "wof:placetype":"venue"
},
  "geometry": {"coordinates":[-5.3558006287,36.166229248],"type":"Point"}
}