{
  "type": "Feature",
  "properties": {
    "iso:country":"ES",
    "sg:address":"Calle de Pintada, 35",
    "sg:city":"Nerja",
    "sg:orig_category":"Inmobiliaria (agencias)",
    "sg:phone":"+34 952 52 66 26",
    "sg:postcode":"29780",
    "sg:province":"M\u00e1laga",
    "sg:website":"www.nerjaone.com",
    "wof:name":"Ruiz Montero Javier Vicente",
    "wof:placetype":"venue"
},
  "geometry": {"coordinates":[-3.8764090538,36.7472724915],"type":"Point"}
}