{
  "type": "Feature",
  "properties": {
    "addr:full":"Calle de Isidoro Bodson, 2 Ba\u00e7os De La Encina Ja\u00e9n 23711",
    "addr:housenumber":"2",
    "addr:postcode":"23711",
    "addr:street":"Calle De Isidoro Bodson;Jae\u0301N",
    "iso:country":"ES",
    "sg:address":"Calle de Isidoro Bodson, 2",
    "sg:city":"Ba\u00e7os De La Encina",
    "sg:orig_category":"Cajas De Ahorro",
    "sg:phone":"+34 953 61 30 50",
    "sg:postcode":"23711",
    "sg:province":"Ja\u00e9n",
    "sg:website":"www.unicaja.es",
    "wof:name":"Unicaja",
    "wof:placetype":"venue"
},
  "geometry": {"coordinates":[-3.7711639404,38.172328949],"type":"Point"}
}