{
  "type": "Feature",
  "properties": {
    "addr:full":"Carrer de Valles, 40 Sabadell Barcelona 08201",
    "addr:housenumber":"40",
    "addr:postcode":"08201",
    "addr:street":"Carrer De Valles",
    "iso:country":"ES",
    "sg:address":"Carrer de Valles, 40",
    "sg:city":"Sabadell",
    "sg:orig_category":"Peluquer\u00cdas, Peluquer\u00cda Mixta",
    "sg:phone":"+34 937 27 26 78",
    "sg:postcode":"08201",
    "sg:province":"Barcelona",
    "wof:name":"Cid Caridad Irene",
    "wof:placetype":"venue"
},
  "geometry": {"coordinates":[2.1009449959,41.5471191406],"type":"Point"}
}