{
  "type": "Feature",
  "properties": {
    "addr:full":"Calle de Dos De Mayo, 15 Ponferrada Le\u00f3n 24400",
    "addr:postcode":"24400",
    "addr:street":"Calle De Dos;Mayo 15;Leo\u0301N",
    "iso:country":"ES",
    "sg:address":"Calle de Dos De Mayo, 15",
    "sg:city":"Ponferrada",
    "sg:orig_category":"Abogados",
    "sg:phone":"+34 987 40 52 80",
    "sg:postcode":"24400",
    "sg:province":"Le\u00f3n",
    "sg:website":"www.paginasamarillas.es",
    "wof:name":"Asesoria Dos De Mayo S.l.",
    "wof:placetype":"venue"
},
  "geometry": {"coordinates":[-6.5993237495,42.5468063354],"type":"Point"}
}