{
  "type": "Feature",
  "properties": {
    "iso:country":"ES",
    "sg:address":"Escuela, 8",
    "sg:city":"Zaragoza",
    "sg:orig_category":"Chapister\u00cda",
    "sg:phone":"+34 976 56 28 38",
    "sg:postcode":"50009",
    "sg:province":"Zaragoza",
    "wof:name":"Sanchez Lausin Jose",
    "wof:placetype":"venue"
},
  "geometry": {"coordinates":[-0.907087028,41.6299781799],"type":"Point"}
}