{
  "type": "Feature",
  "properties": {
    "addr:full":"Calle de Alfonso De Armas Ayala, 3 S.gregorio Las Palmas 35200",
    "addr:housenumber":"3",
    "addr:postcode":"35200",
    "addr:street":"Calle De Alfonso De Armas Ayala;Las Palmas",
    "iso:country":"ES",
    "sg:address":"Calle de Alfonso De Armas Ayala, 3",
    "sg:city":"S.gregorio",
    "sg:orig_category":"Caf\u00c9s, Bares, Cervecer\u00cdas",
    "sg:phone":"+34 928 69 10 07",
    "sg:postcode":"35200",
    "sg:province":"Las Palmas",
    "wof:name":"Hernandez Ramirez Jose Miguel",
    "wof:placetype":"venue"
},
  "geometry": {"coordinates":[-15.4300060272,28.1248226166],"type":"Point"}
}