{
  "type": "Feature",
  "properties": {
    "iso:country":"ES",
    "sg:address":"Calle de Segovia, 22",
    "sg:city":"Cantalejo",
    "sg:orig_category":"Art\u00cdculos Funerarios (al Por Menor)",
    "sg:phone":"+34 921 52 21 08",
    "sg:postcode":"40320",
    "sg:province":"Segovia",
    "wof:name":"Lapidas Y Funerarias El Carmen S.l.",
    "wof:placetype":"venue"
},
  "geometry": {"coordinates":[-3.9290831089,41.2543487549],"type":"Point"}
}