{
  "type": "Feature",
  "properties": {
    "addr:full":"Calle de Pozos Dulces, 8 Malaga M\u00e1laga 29008",
    "addr:housenumber":"8",
    "addr:postcode":"29008",
    "addr:street":"Calle De Pozos Dulces;Ma\u0301Laga",
    "iso:country":"ES",
    "sg:address":"Calle de Pozos Dulces, 8",
    "sg:city":"Malaga",
    "sg:orig_category":"Inmobiliaria (agencias)",
    "sg:phone":"+34 952 21 07 60",
    "sg:postcode":"29008",
    "sg:province":"M\u00e1laga",
    "wof:name":"Bchbanif Fondo Inmobiliario F.i.i.",
    "wof:placetype":"venue"
},
  "geometry": {"coordinates":[-4.423874855,36.7216300964],"type":"Point"}
}