{
  "type": "Feature",
  "properties": {
    "addr:full":"Plaz Belen, 3 Jaen Ja\u00e9n 23001",
    "addr:housenumber":"3;jae\u0301n",
    "addr:postcode":"23001",
    "addr:street":"Belen",
    "iso:country":"ES",
    "sg:address":"Plaz Belen, 3",
    "sg:city":"Jaen",
    "sg:orig_category":"Centros Empresariales",
    "sg:phone":"+34 953 27 07 76",
    "sg:postcode":"23001",
    "sg:province":"Ja\u00e9n",
    "wof:name":"Jaenera De Multiservicios S L",
    "wof:placetype":"venue"
},
  "geometry": {"coordinates":[-3.7906870842,37.7650947571],"type":"Point"}
}