{
  "type": "Feature",
  "properties": {
    "addr:full":"Carrer de Trinquet, 28 Deltebre Tarragona 43580",
    "addr:housenumber":"28",
    "addr:postcode":"43580",
    "addr:street":"Carrer De Trinquet",
    "iso:country":"ES",
    "sg:address":"Carrer de Trinquet, 28",
    "sg:city":"Deltebre",
    "sg:orig_category":"Sociedades, Compa\u00d1\u00cdas Aseguradoras",
    "sg:phone":"+34 977 48 01 16",
    "sg:postcode":"43580",
    "sg:province":"Tarragona",
    "wof:name":"Venturabrockers Societat D'agencia D'assegurances S.l.l.",
    "wof:placetype":"venue"
},
  "geometry": {"coordinates":[0.737424016,40.7157363892],"type":"Point"}
}