{
  "type": "Feature",
  "properties": {
    "addr:full":"Calle de Astura, 5 Valencia De Don Juan Le\u00f3n 24200",
    "addr:housenumber":"5",
    "addr:postcode":"24200",
    "addr:street":"Calle De Astura",
    "iso:country":"ES",
    "sg:address":"Calle de Astura, 5",
    "sg:city":"Valencia De Don Juan",
    "sg:orig_category":"Peluqueros: De Se\u00d1oras",
    "sg:phone":"+34 987 75 08 15",
    "sg:postcode":"24200",
    "sg:province":"Le\u00f3n",
    "wof:name":"Peluqueria Unisex Ysa",
    "wof:placetype":"venue"
},
  "geometry": {"coordinates":[-5.518693924,42.2928009033],"type":"Point"}
}