{
  "type": "Feature",
  "properties": {
    "addr:full":"Carrer de Independencia, 95 Terrassa Barcelona 08225",
    "addr:housenumber":"95",
    "addr:postcode":"08225",
    "addr:street":"Carrer De Independencia",
    "iso:country":"ES",
    "sg:address":"Carrer de Independencia, 95",
    "sg:city":"Terrassa",
    "sg:orig_category":"Contenedores (mercanc\u00cdas)",
    "sg:phone":"+34 937 35 04 40",
    "sg:postcode":"08225",
    "sg:province":"Barcelona",
    "wof:name":"Empresa Tarrasense De Comercio Exterior S.l.",
    "wof:placetype":"venue"
},
  "geometry": {"coordinates":[2.01394701,41.5739784241],"type":"Point"}
}