{
  "type": "Feature",
  "properties": {
    "iso:country":"ES",
    "sg:address":"Calle de Gran Via, 20",
    "sg:city":"Donostia-san Sebastian",
    "sg:orig_category":"Sociedades, Compa\u00d1\u00cdas Aseguradoras",
    "sg:phone":"+34 943 27 10 11",
    "sg:postcode":"20001",
    "sg:province":"Guip\u00f9zcoa",
    "wof:name":"Seguros Lagun Aro S.a.",
    "wof:placetype":"venue"
},
  "geometry": {"coordinates":[-1.9729989767,43.3233642578],"type":"Point"}
}