{
  "type": "Feature",
  "properties": {
    "addr:full":"Calle de Carolina (la), 1 Linares Ja\u00e9n 23700",
    "addr:housenumber":"1",
    "addr:postcode":"23700",
    "addr:street":"Calle De Carolina La;Jae\u0301N",
    "iso:country":"ES",
    "sg:address":"Calle de Carolina (la), 1",
    "sg:city":"Linares",
    "sg:orig_category":"Aceites Y Grasas Alimentarias (fabricaci\u00d3n, Al Por Mayor)",
    "sg:phone":"+34 953 65 69 91",
    "sg:postcode":"23700",
    "sg:province":"Ja\u00e9n",
    "wof:name":"Productos Aceiteros Eduardo Caro Eismann S.l.",
    "wof:placetype":"venue"
},
  "geometry": {"coordinates":[-3.6323018074,38.0980567932],"type":"Point"}
}