{
  "type": "Feature",
  "properties": {
    "iso:country":"ES",
    "sg:address":"C/ Sant Josep, 20",
    "sg:city":"Alcoi",
    "sg:orig_category":"Abogados",
    "sg:phone":"+34 965 54 67 10",
    "sg:postcode":"03801",
    "sg:province":"Alicante",
    "wof:name":"Garcia Llorens Roberto",
    "wof:placetype":"venue"
},
  "geometry": {"coordinates":[-0.4750509858,38.696937561],"type":"Point"}
}