{
  "type": "Feature",
  "properties": {
    "iso:country":"ES",
    "sg:address":"Calle de Molinos (los), S/n",
    "sg:city":"Astorga",
    "sg:orig_category":"Fabricaci\u00d3n De Papel Para Embalar",
    "sg:phone":"+34 987 61 53 66",
    "sg:postcode":"24700",
    "sg:province":"Le\u00f3n",
    "wof:name":"Papelera Astorgana S. A.",
    "wof:placetype":"venue"
},
  "geometry": {"coordinates":[-6.0442900658,42.4553108215],"type":"Point"}
}