{
  "type": "Feature",
  "properties": {
    "iso:country":"ES",
    "sg:address":"Avda Constitucion, 337",
    "sg:city":"Valencia",
    "sg:orig_category":"Comercio, Reparaci\u00d3n De Motocicletas, Bicicletas Y Piezas Sueltas",
    "sg:phone":"+34 961 85 30 73",
    "sg:postcode":"46019",
    "sg:province":"Valencia",
    "wof:name":"Motomas Valencia Sl",
    "wof:placetype":"venue"
},
  "geometry": {"coordinates":[-0.3681870103,39.5034866333],"type":"Point"}
}