{
  "type": "Feature",
  "properties": {
    "addr:full":"El Gobernador, S/n Gobernador Asturias 33315",
    "addr:housenumber":"s",
    "addr:postcode":"33315",
    "addr:street":"El Gobernador;/ N Gobernador Asturias",
    "iso:country":"ES",
    "sg:address":"El Gobernador, S/n",
    "sg:city":"Gobernador",
    "sg:orig_category":"Deportes N\u00c1uticos, Acu\u00c1ticos Y Subacu\u00c1ticos: Art\u00cdculos Y Equipo (al Por Menor)",
    "sg:phone":"+34 985 89 18 16",
    "sg:postcode":"33315",
    "sg:province":"Asturias",
    "wof:name":"Ramos Rodriguez Marco Antonio 000402043h S.l.n.e",
    "wof:placetype":"venue"
},
  "geometry": {"coordinates":[-5.4002161026,43.5276565552],"type":"Point"}
}