{
  "type": "Feature",
  "properties": {
    "iso:country":"ES",
    "sg:address":"Calle de Jose Payan, 60",
    "sg:city":"Camas",
    "sg:orig_category":"Arreglo, Reparaci\u00d3n, Piezas Sueltas De Televisi\u00d3n, V\u00cddeo, Hi",
    "sg:phone":"+34 954 39 32 92",
    "sg:postcode":"41900",
    "sg:province":"Sevilla",
    "wof:name":"Linde Romero Francisco",
    "wof:placetype":"venue"
},
  "geometry": {"coordinates":[-6.0345139503,37.3990287781],"type":"Point"}
}