{
  "type": "Feature",
  "properties": {
    "addr:full":"Carrer de Dinamarca, 9 Urbanitzacio El Mirador Del Penedes Tarragona 43718",
    "addr:housenumber":"9",
    "addr:postcode":"43718",
    "addr:street":"Carrer De Dinamarca",
    "iso:country":"ES",
    "sg:address":"Carrer de Dinamarca, 9",
    "sg:city":"Urbanitzacio El Mirador Del Penedes",
    "sg:orig_category":"Ingenier\u00cda, Centros De Estudios (diversos)",
    "sg:phone":"+34 977 68 96 20",
    "sg:postcode":"43718",
    "sg:province":"Tarragona",
    "wof:name":"Art Isor,s.c.p",
    "wof:placetype":"venue"
},
  "geometry": {"coordinates":[1.4224021435,41.2934265137],"type":"Point"}
}