{
  "type": "Feature",
  "properties": {
    "iso:country":"ES",
    "sg:address":"Ctra Cabezo Torres-autovia, S/n",
    "sg:city":"Cabezo Torres",
    "sg:orig_category":"M\u00c1rmoles, Granitos Y Piedras Naturales",
    "sg:phone":"+34 968 83 04 08",
    "sg:postcode":"30110",
    "sg:province":"Murcia",
    "wof:name":"Gramarsi S.l",
    "wof:placetype":"venue"
},
  "geometry": {"coordinates":[-1.2403124571,38.0278625488],"type":"Point"}
}