{
  "type": "Feature",
  "properties": {
    "addr:full":"Calle de Ibiza, 31 Alovera Guadalajara 19208",
    "addr:housenumber":"31",
    "addr:postcode":"19208",
    "addr:street":"Calle De Ibiza",
    "iso:country":"ES",
    "sg:address":"Calle de Ibiza, 31",
    "sg:city":"Alovera",
    "sg:orig_category":"El Hogar: Amueblado, Acondicionamiento, Decoraci\u00d3n Y Mantenimiento",
    "sg:phone":"+34 949 29 72 82",
    "sg:postcode":"19208",
    "sg:province":"Guadalajara",
    "wof:name":"Inreda S.l.",
    "wof:placetype":"venue"
},
  "geometry": {"coordinates":[-3.243735075,40.5974273682],"type":"Point"}
}