{
  "type": "Feature",
  "properties": {
    "addr:full":"Plaz Alameda De Hercules, 57 Sevilla Sevilla 41002",
    "addr:housenumber":"57",
    "addr:postcode":"41002",
    "addr:street":"Alameda De Hercules",
    "iso:country":"ES",
    "sg:address":"Plaz Alameda De Hercules, 57",
    "sg:city":"Sevilla",
    "sg:orig_category":"Electrodom\u00c9sticos (al Por Menor)",
    "sg:phone":"+34 954 37 71 91",
    "sg:postcode":"41002",
    "sg:province":"Sevilla",
    "wof:name":"Flores Marquez Juan",
    "wof:placetype":"venue"
},
  "geometry": {"coordinates":[-5.9942588806,37.3967475891],"type":"Point"}
}