{
  "type": "Feature",
  "properties": {
    "iso:country":"ES",
    "sg:address":"Av America, 101",
    "sg:city":"Mataro",
    "sg:orig_category":"Hilaturas, Hilos Y Actividades Relacionadas",
    "sg:phone":"+34 937 90 64 90",
    "sg:postcode":"08304",
    "sg:province":"Barcelona",
    "wof:name":"Esbento S.l",
    "wof:placetype":"venue"
},
  "geometry": {"coordinates":[2.4532380104,41.5470199585],"type":"Point"}
}