{
  "type": "Feature",
  "properties": {
    "addr:full":"Avda Ramon Llido, 27 Javea Alicante 03730",
    "addr:housenumber":"27",
    "addr:postcode":"03730",
    "addr:street":"Avda Ramon Llido",
    "iso:country":"ES",
    "sg:address":"Avda Ramon Llido, 27",
    "sg:city":"Javea",
    "sg:orig_category":"Empresas De Carpinter\u00cda De Madera",
    "sg:phone":"+34 965 79 08 88",
    "sg:postcode":"03730",
    "sg:province":"Alicante",
    "wof:name":"Guijarro Ortega Francisco Daniel",
    "wof:placetype":"venue"
},
  "geometry": {"coordinates":[0.1638280004,38.7842063904],"type":"Point"}
}