{
  "type": "Feature",
  "properties": {
    "addr:full":"Cra. Riu, Km. 0002,0 Estartit Girona 17258",
    "addr:postcode":"17258",
    "iso:country":"ES",
    "sg:address":"Cra. Riu, Km. 0002,0",
    "sg:city":"Estartit",
    "sg:orig_category":"Poller\u00cda Y Caza (al Por Menor)",
    "sg:phone":"+34 972 75 06 15",
    "sg:postcode":"17258",
    "sg:province":"Girona",
    "wof:name":"Mu\u00f1oz Martinez Nicolas",
    "wof:placetype":"venue"
},
  "geometry": {"coordinates":[3.1995449066,42.053730011],"type":"Point"}
}