{
  "type": "Feature",
  "properties": {
    "iso:country":"ES",
    "sg:address":"Calle de Aire, 70",
    "sg:city":"Aguilas",
    "sg:orig_category":"Fabricaci\u00d3n, Reparaci\u00d3n Y Mantenimiento De Construcciones Navales Y Fluviales",
    "sg:phone":"+34 968 44 73 84",
    "sg:postcode":"30880",
    "sg:province":"Murcia",
    "wof:name":"Nautica Pedro Franco S.l.",
    "wof:placetype":"venue"
},
  "geometry": {"coordinates":[-1.5740468502,37.4080657959],"type":"Point"}
}