{
  "type": "Feature",
  "properties": {
    "iso:country":"ES",
    "sg:address":"Calle de Joaquin Turina, 15",
    "sg:city":"Brenes",
    "sg:orig_category":"Quincaller\u00cda (al Por Menor)",
    "sg:phone":"+34 954 79 70 26",
    "sg:postcode":"41310",
    "sg:province":"Sevilla",
    "wof:name":"Ferresereno Sl",
    "wof:placetype":"venue"
},
  "geometry": {"coordinates":[-5.8741998672,37.5467605591],"type":"Point"}
}