{
  "type": "Feature",
  "properties": {
    "addr:full":"Calle de Antonio De Nebrija, 10 Merida Badajoz 06800",
    "addr:housenumber":"10",
    "addr:postcode":"06800",
    "addr:street":"Calle De Antonio De Nebrija",
    "iso:country":"ES",
    "sg:address":"Calle de Antonio De Nebrija, 10",
    "sg:city":"Merida",
    "sg:orig_category":"Cervecer\u00cdas",
    "sg:phone":"+34 924 37 07 66",
    "sg:postcode":"06800",
    "sg:province":"Badajoz",
    "wof:name":"Lucas Berdonce Francisco",
    "wof:placetype":"venue"
},
  "geometry": {"coordinates":[-6.361664772,38.9129600525],"type":"Point"}
}