{
  "type": "Feature",
  "properties": {
    "addr:full":"Ctra. Estacion, 2 Puerto Lumbreras Murcia 30890",
    "addr:housenumber":"2",
    "addr:postcode":"30890",
    "addr:street":"Ctra. Estacion",
    "iso:country":"ES",
    "sg:address":"Ctra. Estacion, 2",
    "sg:city":"Puerto Lumbreras",
    "sg:orig_category":"Centros De Educaci\u00d3n Especial",
    "sg:phone":"+34 968 40 23 86",
    "sg:postcode":"30890",
    "sg:province":"Murcia",
    "wof:name":"Colegio Nacional Comarcal",
    "wof:placetype":"venue"
},
  "geometry": {"coordinates":[-1.7345819473,37.5820960999],"type":"Point"}
}