{
  "type": "Feature",
  "properties": {
    "addr:full":"Kondeko Aldapa, 5 San Blas Guip\u00f9zcoa 20400",
    "addr:housenumber":"5",
    "addr:postcode":"20400",
    "addr:street":"Aldapa",
    "iso:country":"ES",
    "sg:address":"Kondeko Aldapa, 5",
    "sg:city":"San Blas",
    "sg:orig_category":"Internados & Ense\u00d1anza Privada",
    "sg:phone":"+34 943 67 36 29",
    "sg:postcode":"20400",
    "sg:province":"Guip\u00f9zcoa",
    "wof:name":"Inmaculada Concepcion S.coop.",
    "wof:placetype":"venue"
},
  "geometry": {"coordinates":[-2.0789339542,43.1339912415],"type":"Point"}
}