{
  "type": "Feature",
  "properties": {
    "addr:full":"Calle de Matarrosa, 30 Fuenlabrada Madrid 28947",
    "addr:housenumber":"30",
    "addr:postcode":"28947",
    "addr:street":"Calle De Matarrosa",
    "iso:country":"ES",
    "sg:address":"Calle de Matarrosa, 30",
    "sg:city":"Fuenlabrada",
    "sg:orig_category":"Empresas De Limpieza",
    "sg:phone":"+34 916 21 42 53",
    "sg:postcode":"28947",
    "sg:province":"Madrid",
    "wof:name":"Eulen S.a.",
    "wof:placetype":"venue"
},
  "geometry": {"coordinates":[-3.753166914,40.2645759583],"type":"Point"}
}