{
  "type": "Feature",
  "properties": {
    "iso:country":"ES",
    "sg:address":"Calle de Cura Aguilar, 4",
    "sg:city":"Benifaraig",
    "sg:orig_category":"Promotores Constructores",
    "sg:phone":"+34 963 63 51 68",
    "sg:postcode":"46016",
    "sg:province":"Valencia",
    "wof:name":"Proesca S.l.",
    "wof:placetype":"venue"
},
  "geometry": {"coordinates":[-0.3853861988,39.5277862549],"type":"Point"}
}