{
  "type": "Feature",
  "properties": {
    "iso:country":"ES",
    "sg:address":"Plaz Cervantes, 3",
    "sg:city":"Ciudad Real",
    "sg:orig_category":"Lencer\u00cda Femenina, Corseter\u00cda, Trajes De Ba\u00d1o (al Por Menor)",
    "sg:phone":"+34 926 21 11 80",
    "sg:postcode":"13001",
    "sg:province":"Ciudad Real",
    "wof:name":"Lenceria Yedra S.l.",
    "wof:placetype":"venue"
},
  "geometry": {"coordinates":[-3.9301741123,38.9844093323],"type":"Point"}
}