{
  "type": "Feature",
  "properties": {
    "iso:country":"ES",
    "sg:address":"Nuevas, S/n",
    "sg:city":"Balsicas",
    "sg:orig_category":"Electricidad: Instaladores",
    "sg:phone":"+34 968 58 01 27",
    "sg:postcode":"30591",
    "sg:province":"Murcia",
    "wof:name":"Raimundo Garceran S.l.",
    "wof:placetype":"venue"
},
  "geometry": {"coordinates":[-0.9609609842,37.8191490173],"type":"Point"}
}