{
  "type": "Feature",
  "properties": {
    "addr:full":"Plaz Lugo (de), S/n Viveiro Lugo 27850",
    "addr:housenumber":"/ n",
    "addr:postcode":"27850",
    "addr:street":"Plaz;De S",
    "iso:country":"ES",
    "sg:address":"Plaz Lugo (de), S/n",
    "sg:city":"Viveiro",
    "sg:orig_category":"Aparcamientos (infraestructuras, Accesorios)",
    "sg:phone":"+34 982 55 19 70",
    "sg:postcode":"27850",
    "sg:province":"Lugo",
    "wof:name":"Aparcamientos A Mari\u00f1a S.l.",
    "wof:placetype":"venue"
},
  "geometry": {"coordinates":[-7.6018390656,43.637096405],"type":"Point"}
}