{
  "type": "Feature",
  "properties": {
    "iso:country":"ES",
    "sg:address":"Ctra Valverde, Km. 0002,0",
    "sg:city":"Badajoz",
    "sg:classifiers":[
        {
            "category":"Casinos & Gambling",
            "type":"Entertainment"
        }
    ],
    "sg:phone":"+34 924 26 83 08",
    "sg:postcode":"06010",
    "sg:province":"Badajoz",
    "sg:tags":[
        "locale",
        "de",
        "juego"
    ],
    "wof:name":"Casino De Badajoz",
    "wof:placetype":"venue"
},
  "geometry": {"coordinates":[-6.9726390839,38.8646392822],"type":"Point"}
}