{
  "type": "Feature",
  "properties": {
    "addr:full":"Av Mare De Deu De Bellvitge, 326 Hospitalet Llobregat Barcelona 08907",
    "addr:housenumber":"326",
    "addr:postcode":"08907",
    "addr:street":"Av Mare De Deu De Bellvitge",
    "iso:country":"ES",
    "sg:address":"Av Mare De Deu De Bellvitge, 326",
    "sg:city":"Hospitalet Llobregat",
    "sg:orig_category":"Mec\u00c1nico Del Autom\u00d3vil",
    "sg:phone":"+34 933 37 81 63",
    "sg:postcode":"08907",
    "sg:province":"Barcelona",
    "wof:name":"Cortes Y Plegados G.c. C.b.",
    "wof:placetype":"venue"
},
  "geometry": {"coordinates":[2.1055400372,41.3509292603],"type":"Point"}
}