{
  "type": "Feature",
  "properties": {
    "addr:full":"Calle de Juan Lorenzo Segura, 3 Le\u00f3n Le\u00f3n 24001",
    "addr:housenumber":"3",
    "addr:postcode":"24001",
    "addr:street":"Calle De Juan;Segura;Leo\u0301N",
    "iso:country":"ES",
    "sg:address":"Calle de Juan Lorenzo Segura, 3",
    "sg:city":"Le\u00f3n",
    "sg:orig_category":"Inmobiliaria (agencias)",
    "sg:phone":"+34 987 24 36 97",
    "sg:postcode":"24001",
    "sg:province":"Le\u00f3n",
    "wof:name":"Prohogares Leon 2001 S.l",
    "wof:placetype":"venue"
},
  "geometry": {"coordinates":[-5.5765180588,42.5978012085],"type":"Point"}
}