{
  "type": "Feature",
  "properties": {
    "iso:country":"ES",
    "sg:address":"Calle de Arboledas, 2",
    "sg:city":"Illescas",
    "sg:orig_category":"Acero: Productos Sider\u00dargicos Y Transformados (fabricaci\u00d3n, Negocio)",
    "sg:phone":"+34 925 51 19 01",
    "sg:postcode":"45200",
    "sg:province":"Toledo",
    "sg:website":"www.acerosgrinon.com",
    "wof:name":"Aceros Gri\u00f1on S.l.",
    "wof:placetype":"venue"
},
  "geometry": {"coordinates":[-3.8326075077,40.1314048767],"type":"Point"}
}