{
  "type": "Feature",
  "properties": {
    "iso:country":"ES",
    "sg:address":"Rua Benito Corbal, 17",
    "sg:city":"Pontevedra",
    "sg:orig_category":"Ense\u00d1anza: Comercio, Gesti\u00d3n, Inform\u00c1tica",
    "sg:phone":"+34 986 84 58 06",
    "sg:postcode":"36001",
    "sg:province":"Pontevedra",
    "wof:name":"Aula Informatica Gallega S.l.",
    "wof:placetype":"venue"
},
  "geometry": {"coordinates":[-8.6420564651,42.4305725098],"type":"Point"}
}