{
  "type": "Feature",
  "properties": {
    "iso:country":"ES",
    "sg:address":"Carrer de Major, 40",
    "sg:city":"Castellar Valles",
    "sg:orig_category":"Perfumer\u00cda, Art\u00cdculos De Ba\u00d1o (fabricaci\u00d3n, Al Por Mayor)",
    "sg:phone":"+34 937 14 69 58",
    "sg:postcode":"08211",
    "sg:province":"Barcelona",
    "wof:name":"Rovira Salles Rosario",
    "wof:placetype":"venue"
},
  "geometry": {"coordinates":[2.0868029594,41.616973877],"type":"Point"}
}