{
  "type": "Feature",
  "properties": {
    "iso:country":"ES",
    "sg:address":"Calle de Sevilla, S/n",
    "sg:city":"Fuente Piedra",
    "sg:orig_category":"Productores Recolectores, Venta Directa De Vinos",
    "sg:phone":"+34 952 11 16 81",
    "sg:postcode":"29520",
    "sg:province":"M\u00e1laga",
    "wof:name":"Inversiones Santa Ana S.a.",
    "wof:placetype":"venue"
},
  "geometry": {"coordinates":[-4.7294130325,37.1387214661],"type":"Point"}
}