{
  "type": "Feature",
  "properties": {
    "iso:country":"ES",
    "sg:address":"Calle de Flora Florez, 22",
    "sg:city":"Sahagun",
    "sg:orig_category":"Arreglo, Reparaci\u00d3n, Piezas Sueltas De Televisi\u00d3n, V\u00cddeo, Hi",
    "sg:phone":"+34 987 78 07 94",
    "sg:postcode":"24320",
    "sg:province":"Le\u00f3n",
    "wof:name":"Herrero Azuara Jose Antolin",
    "wof:placetype":"venue"
},
  "geometry": {"coordinates":[-5.0315499306,42.3711395264],"type":"Point"}
}