{
  "type": "Feature",
  "properties": {
    "addr:full":"Carr Riu, 2 Sarria Ter Girona 17840",
    "addr:housenumber":"2",
    "addr:postcode":"17840",
    "addr:street":"Carr Riu;Ter",
    "iso:country":"ES",
    "sg:address":"Carr Riu, 2",
    "sg:city":"Sarria Ter",
    "sg:orig_category":"Asociaciones Y Clubs Deportivos",
    "sg:phone":"+34 972 17 25 09",
    "sg:postcode":"17840",
    "sg:province":"Girona",
    "sg:website":"www.dartsgimnas.com",
    "wof:name":"X-type Gym S.c.p.",
    "wof:placetype":"venue"
},
  "geometry": {"coordinates":[2.8196923733,41.9860992432],"type":"Point"}
}