{
  "type": "Feature",
  "properties": {
    "iso:country":"ES",
    "sg:address":"Calle de Caidos De La Division Azul, 1",
    "sg:city":"Madrid",
    "sg:orig_category":"Promotores Constructores",
    "sg:phone":"+34 913 50 04 86",
    "sg:postcode":"28016",
    "sg:province":"Madrid",
    "wof:name":"Abside, Construccion Y Rehabilitacion S.l.",
    "wof:placetype":"venue"
},
  "geometry": {"coordinates":[-3.677304,40.467884],"type":"Point"}
}