{
  "type": "Feature",
  "properties": {
    "iso:country":"ES",
    "sg:address":"Avda Mar, Avda. (del), 12",
    "sg:city":"Marbella",
    "sg:orig_category":"Asesor\u00cda Fiscal Y Jur\u00cddica",
    "sg:phone":"+34 952 77 80 19",
    "sg:postcode":"29600",
    "sg:province":"M\u00e1laga",
    "wof:name":"Santos Diaz Santiago",
    "wof:placetype":"venue"
},
  "geometry": {"coordinates":[-4.8833007812,36.5079956055],"type":"Point"}
}