{
  "type": "Feature",
  "properties": {
    "iso:country":"ES",
    "sg:address":"Calle de Coso Bajo, 7",
    "sg:city":"Huesca",
    "sg:orig_category":"Partidos Pol\u00cdticos",
    "sg:phone":"+34 974 22 68 22",
    "sg:postcode":"22001",
    "sg:province":"Huesca",
    "wof:name":"Coalicion Electoral Izquierda Unida",
    "wof:placetype":"venue"
},
  "geometry": {"coordinates":[-0.4076231122,42.1372299194],"type":"Point"}
}