{
  "type": "Feature",
  "properties": {
    "iso:country":"ES",
    "sg:address":"Plaz Constitucion (la), 11",
    "sg:city":"Villanueva Reina",
    "sg:orig_category":"Iglesia Cat\u00d3lica",
    "sg:phone":"+34 953 53 71 27",
    "sg:postcode":"23730",
    "sg:province":"Ja\u00e9n",
    "wof:name":"Parroquia Nuestra Se\u00f1ora De La Natividad",
    "wof:placetype":"venue"
},
  "geometry": {"coordinates":[-3.9147191048,38.0040740967],"type":"Point"}
}