{
  "type": "Feature",
  "properties": {
    "addr:full":"Carr Teatre, 3 Vilanova I La Geltru Barcelona 08800",
    "addr:housenumber":"3",
    "addr:postcode":"08800",
    "addr:street":"Carr Teatre",
    "iso:country":"ES",
    "sg:address":"Carr Teatre, 3",
    "sg:city":"Vilanova I La Geltru",
    "sg:orig_category":"Reposter\u00cdas",
    "sg:phone":"+34 938 93 26 53",
    "sg:postcode":"08800",
    "sg:province":"Barcelona",
    "wof:name":"Ripoll Planas Jose",
    "wof:placetype":"venue"
},
  "geometry": {"coordinates":[1.7230869532,41.2252311707],"type":"Point"}
}