{
  "type": "Feature",
  "properties": {
    "addr:full":"Calle de Flor De Salvia, S/n Sevilla Sevilla 41020",
    "addr:housenumber":"s / n",
    "addr:postcode":"41020",
    "addr:street":"Calle De Flor De Salvia",
    "iso:country":"ES",
    "sg:address":"Calle de Flor De Salvia, S/n",
    "sg:city":"Sevilla",
    "sg:orig_category":"Farmacias",
    "sg:phone":"+34 954 40 71 17",
    "sg:postcode":"41020",
    "sg:province":"Sevilla",
    "wof:name":"Garcia Ayuso Cristina",
    "wof:placetype":"venue"
},
  "geometry": {"coordinates":[-5.9178676605,37.3957901001],"type":"Point"}
}