{
  "type": "Feature",
  "properties": {
    "iso:country":"ES",
    "sg:address":"Ctra. Granada, 62",
    "sg:city":"Puerto Lumbreras",
    "sg:orig_category":"Escayola Y Productos De Escayola (fabricaci\u00d3n, Al Por Mayor)",
    "sg:phone":"+34 968 40 22 20",
    "sg:postcode":"30890",
    "sg:province":"Murcia",
    "wof:name":"Yesos Millan S.l.",
    "wof:placetype":"venue"
},
  "geometry": {"coordinates":[-1.8130376339,37.5632362366],"type":"Point"}
}