{
  "type": "Feature",
  "properties": {
    "addr:full":"Calle de Corona De Aragon, 34 Barbastro Huesca 22300",
    "addr:housenumber":"34",
    "addr:postcode":"22300",
    "addr:street":"Calle De Corona De Aragon",
    "iso:country":"ES",
    "sg:address":"Calle de Corona De Aragon, 34",
    "sg:city":"Barbastro",
    "sg:orig_category":"\u00d3ptica: Instrumentos (fabricaci\u00d3n)",
    "sg:phone":"+34 974 31 52 06",
    "sg:postcode":"22300",
    "sg:province":"Huesca",
    "wof:name":"Centros Opticos Osca S.l.",
    "wof:placetype":"venue"
},
  "geometry": {"coordinates":[0.128322795,42.0359230042],"type":"Point"}
}