{
  "type": "Feature",
  "properties": {
    "addr:full":"Calle de Orixe, 54 Bilbao Vizcaya 48015",
    "addr:housenumber":"54",
    "addr:postcode":"48015",
    "addr:street":"Calle De Orixe",
    "iso:country":"ES",
    "sg:address":"Calle de Orixe, 54",
    "sg:city":"Bilbao",
    "sg:orig_category":"Venta, Instalaci\u00d3n De Calefacci\u00d3n",
    "sg:phone":"+34 944 75 89 47",
    "sg:postcode":"48015",
    "sg:province":"Vizcaya",
    "wof:name":"Servicio Tecnico Urue\u00f1a S.l.",
    "wof:placetype":"venue"
},
  "geometry": {"coordinates":[-2.9641840458,43.2845993042],"type":"Point"}
}