{
  "type": "Feature",
  "properties": {
    "addr:full":"Calle de Doctor Pedrajas Suardiaz, 6 Priego Cordoba C\u00f3rdoba 14800",
    "addr:housenumber":"6",
    "addr:postcode":"14800",
    "addr:street":"Calle De Doctor Pedrajas Suardiaz;Cordoba Co\u0301Rdoba",
    "iso:country":"ES",
    "sg:address":"Calle de Doctor Pedrajas Suardiaz, 6",
    "sg:city":"Priego Cordoba",
    "sg:orig_category":"Frutas, Legumbres Frescas Y Tempranas (al Por Menor)",
    "sg:phone":"+34 957 54 21 43",
    "sg:postcode":"14800",
    "sg:province":"C\u00f3rdoba",
    "wof:name":"Fruteria Durcal S.l.",
    "wof:placetype":"venue"
},
  "geometry": {"coordinates":[-4.1933269501,37.4395179749],"type":"Point"}
}