{
  "type": "Feature",
  "properties": {
    "iso:country":"ES",
    "sg:address":"Calle de Mendez Nu\u00d1ez, 5",
    "sg:city":"Almeria",
    "sg:orig_category":"Ingeniero",
    "sg:phone":"+34 950 23 15 93",
    "sg:postcode":"04001",
    "sg:province":"Almer\u00eda",
    "wof:name":"Soriano Garcia Matilde",
    "wof:placetype":"venue"
},
  "geometry": {"coordinates":[-2.463176012,36.8386802673],"type":"Point"}
}