{
  "type": "Feature",
  "properties": {
    "addr:full":"C/ Sant Eloi, 1 Alcoi Alicante 03804",
    "addr:housenumber":"1",
    "addr:postcode":"03804",
    "addr:street":"C / Sant Eloi",
    "iso:country":"ES",
    "sg:address":"C/ Sant Eloi, 1",
    "sg:city":"Alcoi",
    "sg:orig_category":"Fotograf\u00cda Art\u00cdstica Y Retratos",
    "sg:phone":"+34 965 52 00 53",
    "sg:postcode":"03804",
    "sg:province":"Alicante",
    "wof:name":"Juan Solroca Jose Luis",
    "wof:placetype":"venue"
},
  "geometry": {"coordinates":[-0.4664739966,38.7086181641],"type":"Point"}
}