{
  "type": "Feature",
  "properties": {
    "iso:country":"ES",
    "sg:address":"Calle de Taliarte, 42",
    "sg:city":"Palmas De Gran Canaria",
    "sg:orig_category":"Herboristas (al Por Menor)",
    "sg:phone":"+34 928 46 28 15",
    "sg:postcode":"35009",
    "sg:province":"Las Palmas",
    "wof:name":"Hernandez Betancor Santiago",
    "wof:placetype":"venue"
},
  "geometry": {"coordinates":[-15.4286823273,28.1503582001],"type":"Point"}
}