{
  "type": "Feature",
  "properties": {
    "addr:full":"Carr Leonor Servera, 12 Cala Ratjada Islas Baleares 07590",
    "addr:housenumber":"12",
    "addr:postcode":"07590",
    "addr:street":"Carr Leonor Servera",
    "iso:country":"ES",
    "sg:address":"Carr Leonor Servera, 12",
    "sg:city":"Cala Ratjada",
    "sg:orig_category":"Ropa Para Ni\u00d1os (al Por Menor)",
    "sg:phone":"+34 971 81 82 45",
    "sg:postcode":"07590",
    "sg:province":"Islas Baleares",
    "wof:name":"Nandu Culeco S.l.",
    "wof:placetype":"venue"
},
  "geometry": {"coordinates":[3.4606449604,39.7145996094],"type":"Point"}
}