{
  "type": "Feature",
  "properties": {
    "addr:full":"Pla\u00c7 Catalunya, 6 S. Pere Pescador Girona 17470",
    "addr:housenumber":"6",
    "addr:postcode":"17470",
    "addr:street":"S. Pere Pescador",
    "iso:country":"ES",
    "sg:address":"Pla\u00c7 Catalunya, 6",
    "sg:city":"S. Pere Pescador",
    "sg:orig_category":"Carnicer\u00cdas, Carnicer\u00cdas",
    "sg:phone":"+34 972 52 03 57",
    "sg:postcode":"17470",
    "sg:province":"Girona",
    "wof:name":"Sanchez Marchante Pere",
    "wof:placetype":"venue"
},
  "geometry": {"coordinates":[3.0805599689,42.1881332397],"type":"Point"}
}