{
  "type": "Feature",
  "properties": {
    "iso:country":"ES",
    "sg:address":"Calle de Hernan Cortes, 66",
    "sg:city":"Villanueva Serena",
    "sg:orig_category":"Tractores Agr\u00cdcolas Y Remolques",
    "sg:phone":"+34 924 84 60 66",
    "sg:postcode":"06700",
    "sg:province":"Badajoz",
    "sg:website":"www.automocionvillanovense.com",
    "wof:name":"Automocion Villanovense S. A.",
    "wof:placetype":"venue"
},
  "geometry": {"coordinates":[-5.7929587364,38.9727134705],"type":"Point"}
}