{
  "type": "Feature",
  "properties": {
    "iso:country":"ES",
    "sg:address":"Rincon, 6",
    "sg:city":"Sta Cruz Tenerife",
    "sg:orig_category":"Escotaduras, Torneados",
    "sg:phone":"+34 922 61 89 03",
    "sg:postcode":"38108",
    "sg:province":"Santa Cruz De Tenerife",
    "wof:name":"Acosta Rodriguez Carmelo",
    "wof:placetype":"venue"
},
  "geometry": {"coordinates":[-16.3021869659,28.4425296783],"type":"Point"}
}