{
  "type": "Feature",
  "properties": {
    "addr:full":"Calle de Motilla Del Palancar, 28 Madrid Madrid 28043",
    "addr:housenumber":"28",
    "addr:postcode":"madrid;28043",
    "addr:street":"Calle De Motilla Del Palancar",
    "iso:country":"ES",
    "sg:address":"Calle de Motilla Del Palancar, 28",
    "sg:city":"Madrid",
    "sg:orig_category":"Electricidad: Equipos Industriales, Componentes (fabricaci\u00d3n)",
    "sg:phone":"+34 917 59 50 75",
    "sg:postcode":"28043",
    "sg:province":"Madrid",
    "wof:name":"Saez 94 S.l.",
    "wof:placetype":"venue"
},
  "geometry": {"coordinates":[-3.6323940754,40.4655227661],"type":"Point"}
}