{
  "type": "Feature",
  "properties": {
    "iso:country":"ES",
    "sg:address":"Avda Cabo De Gata, 191",
    "sg:city":"Almeria",
    "sg:orig_category":"Auditores De Empresas",
    "sg:phone":"+34 950 27 30 02",
    "sg:postcode":"04007",
    "sg:province":"Almer\u00eda",
    "wof:name":"Ayuntamiento De Almeria",
    "wof:placetype":"venue"
},
  "geometry": {"coordinates":[-2.4462666512,36.8242111206],"type":"Point"}
}