{
  "type": "Feature",
  "properties": {
    "addr:full":"Trav Dalt, 100 Barcelona Barcelona 08024",
    "addr:housenumber":"100",
    "addr:postcode":"08024",
    "addr:street":"Trav Dalt",
    "iso:country":"ES",
    "sg:address":"Trav Dalt, 100",
    "sg:city":"Barcelona",
    "sg:orig_category":"Empresarios",
    "sg:phone":"+34 932 19 24 95",
    "sg:postcode":"08024",
    "sg:province":"Barcelona",
    "wof:name":"Fundacion Para La Clinica Psicoanalitica De Orientacion Lacaniana",
    "wof:placetype":"venue"
},
  "geometry": {"coordinates":[2.1578450203,41.4111175537],"type":"Point"}
}