{
  "type": "Feature",
  "properties": {
    "iso:country":"ES",
    "sg:address":"Calle de San Agustin, 15",
    "sg:city":"Madrid",
    "sg:orig_category":"Sindicatos Y Colegios Profesionales",
    "sg:phone":"+34 913 69 21 34",
    "sg:postcode":"28014",
    "sg:province":"Madrid",
    "wof:name":"Veterindustria",
    "wof:placetype":"venue"
},
  "geometry": {"coordinates":[-3.696778059,40.4140739441],"type":"Point"}
}