{
  "type": "Feature",
  "properties": {
    "addr:full":"Carrer de Doctor Trueta, 195 Barcelona Barcelona 08005",
    "addr:housenumber":"195",
    "addr:postcode":"08005",
    "addr:street":"Carrer De Doctor Trueta",
    "iso:country":"ES",
    "sg:address":"Carrer de Doctor Trueta, 195",
    "sg:city":"Barcelona",
    "sg:orig_category":"Asociaciones, Organismos Culturales Y Socioeducativos",
    "sg:phone":"+34 932 25 00 29",
    "sg:postcode":"08005",
    "sg:province":"Barcelona",
    "wof:name":"Ateneu Popular La Flor De Maig De Barcelona",
    "wof:placetype":"venue"
},
  "geometry": {"coordinates":[2.2023925781,41.3977966309],"type":"Point"}
}