{
  "type": "Feature",
  "properties": {
    "addr:full":"Calle de Doce Ligero De Artilleria, 1 Logro\u00f1o La Rioja 26004",
    "addr:housenumber":"1",
    "addr:postcode":"26004",
    "addr:street":"Calle De Doce;Logron\u0303O;Rioja",
    "iso:country":"ES",
    "sg:address":"Calle de Doce Ligero De Artilleria, 1",
    "sg:city":"Logro\u00f1o",
    "sg:orig_category":"Inmobiliaria (alquileres Por Temporada Y Temporales)",
    "sg:phone":"+34 941 27 23 00",
    "sg:postcode":"26004",
    "sg:province":"La Rioja",
    "wof:name":"Ceigroup S.l.",
    "wof:placetype":"venue"
},
  "geometry": {"coordinates":[-2.4382610321,42.4667358398],"type":"Point"}
}