{
  "type": "Feature",
  "properties": {
    "iso:country":"ES",
    "sg:address":"Mitxelena Kalea, 4",
    "sg:city":"Zarautz",
    "sg:orig_category":"Ebanister\u00cda",
    "sg:phone":"+34 943 13 06 55",
    "sg:postcode":"20800",
    "sg:province":"Guip\u00f9zcoa",
    "wof:name":"I\u00f1aki Lizaso Osa Y Marino Valentin Cdad.",
    "wof:placetype":"venue"
},
  "geometry": {"coordinates":[-2.1674389839,43.283164978],"type":"Point"}
}