{
  "type": "Feature",
  "properties": {
    "addr:full":"Calle de Alpujarras, 52 Leganes Madrid 28915",
    "addr:housenumber":"52",
    "addr:postcode":"28915",
    "addr:street":"Calle De Alpujarras",
    "iso:country":"ES",
    "sg:address":"Calle de Alpujarras, 52",
    "sg:city":"Leganes",
    "sg:orig_category":"Ense\u00d1anza Secundaria: Colegios Y Escuelas Privadas",
    "sg:phone":"+34 916 88 02 22",
    "sg:postcode":"28915",
    "sg:province":"Madrid",
    "sg:website":"www.madrid.org",
    "wof:name":"Comunidad Autonoma De Madrid -ies Maria Zambrano",
    "wof:placetype":"venue"
},
  "geometry": {"coordinates":[-3.7487440109,40.3309249878],"type":"Point"}
}