{
  "type": "Feature",
  "properties": {
    "addr:full":"Carrer de Recs, 13 Reus Tarragona 43201",
    "addr:housenumber":"13",
    "addr:postcode":"43201",
    "addr:street":"Carrer De Recs",
    "iso:country":"ES",
    "sg:address":"Carrer de Recs, 13",
    "sg:city":"Reus",
    "sg:classifiers":[
        {
            "category":"Personal",
            "subcategory":"Barber",
            "type":"Services"
        }
    ],
    "sg:phone":"+34 977 32 27 06",
    "sg:postcode":"43201",
    "sg:province":"Tarragona",
    "sg:tags":[
        "caballeros",
        "de",
        "peluqueros"
    ],
    "wof:name":"Pedret Fontgivell Juan",
    "wof:placetype":"venue"
},
  "geometry": {"coordinates":[1.1056879759,41.1562538147],"type":"Point"}
}