{
  "type": "Feature",
  "properties": {
    "addr:full":"Calle de Toledo, 34 Oca\u00f1a Toledo 45300",
    "addr:housenumber":"34",
    "addr:postcode":"45300",
    "addr:street":"Calle De Toledo",
    "iso:country":"ES",
    "sg:address":"Calle de Toledo, 34",
    "sg:city":"Oca\u00f1a",
    "sg:orig_category":"Mec\u00c1nico Del Autom\u00d3vil",
    "sg:phone":"+34 925 13 16 86",
    "sg:postcode":"45300",
    "sg:province":"Toledo",
    "wof:name":"Talleres Rico Y Hervas S.l.",
    "wof:placetype":"venue"
},
  "geometry": {"coordinates":[-3.502393961,39.9576835632],"type":"Point"}
}