{
  "type": "Feature",
  "properties": {
    "iso:country":"ES",
    "sg:address":"Plaz Juez De Paz Jose M Guillen, 2",
    "sg:city":"Aguilas",
    "sg:orig_category":"Reposter\u00cdas",
    "sg:phone":"+34 968 41 13 74",
    "sg:postcode":"30880",
    "sg:province":"Murcia",
    "wof:name":"Fernandez Mengual Antonio",
    "wof:placetype":"venue"
},
  "geometry": {"coordinates":[-1.5839740038,37.4077987671],"type":"Point"}
}