{
  "type": "Feature",
  "properties": {
    "addr:full":"Avda Andalucia, 230 Dos Hermanas Sevilla 41700",
    "addr:housenumber":"230",
    "addr:postcode":"41700",
    "addr:street":"Avda Andalucia;Sevilla",
    "iso:country":"ES",
    "sg:address":"Avda Andalucia, 230",
    "sg:city":"Dos Hermanas",
    "sg:orig_category":"Distribuci\u00d3n De Petr\u00d3leo Y Derivados",
    "sg:phone":"+34 955 66 10 64",
    "sg:postcode":"41700",
    "sg:province":"Sevilla",
    "wof:name":"Pastorgas S.l.",
    "wof:placetype":"venue"
},
  "geometry": {"coordinates":[-5.920486927,37.2705078125],"type":"Point"}
}