{
  "type": "Feature",
  "properties": {
    "addr:full":"Ptda L'horteta, S/n Alcacer Valencia 46290",
    "addr:housenumber":"s / n",
    "addr:postcode":"46290",
    "addr:street":"Ptda L'Horteta",
    "iso:country":"ES",
    "sg:address":"Ptda L'horteta, S/n",
    "sg:city":"Alcacer",
    "sg:orig_category":"Limpieza Con Chorro De Arena Y Con Granalla, Pulido",
    "sg:phone":"+34 961 23 45 12",
    "sg:postcode":"46290",
    "sg:province":"Valencia",
    "wof:name":"Gascon Iborra Damaso",
    "wof:placetype":"venue"
},
  "geometry": {"coordinates":[-0.4490849972,39.3658752441],"type":"Point"}
}