{
  "type": "Feature",
  "properties": {
    "iso:country":"ES",
    "sg:address":"Calle de Dinamarca, 9",
    "sg:city":"Alcala Henares",
    "sg:orig_category":"Panader\u00cdas, Panader\u00cdas",
    "sg:phone":"+34 918 81 64 41",
    "sg:postcode":"28802",
    "sg:province":"Madrid",
    "wof:name":"Hijos De Gonzalez Y Correa S.l.",
    "wof:placetype":"venue"
},
  "geometry": {"coordinates":[-3.3857924938,40.4820098877],"type":"Point"}
}