{
  "type": "Feature",
  "properties": {
    "iso:country":"ES",
    "sg:address":"Calle de Iberia, 19",
    "sg:city":"Carolina",
    "sg:orig_category":"Carnicer\u00cdas, Carnicer\u00cdas",
    "sg:phone":"+34 953 68 09 06",
    "sg:postcode":"23200",
    "sg:province":"Ja\u00e9n",
    "wof:name":"Jose L Martin Hernandez Y Tres Mas C.b.",
    "wof:placetype":"venue"
},
  "geometry": {"coordinates":[-3.6138420105,38.2778625488],"type":"Point"}
}