{
  "type": "Feature",
  "properties": {
    "iso:country":"ES",
    "sg:address":"Carrer de Escultor Figueras (de L'), 35",
    "sg:city":"Canonja",
    "sg:orig_category":"Promotores Constructores",
    "sg:phone":"+34 977 54 69 20",
    "sg:postcode":"43110",
    "sg:province":"Tarragona",
    "wof:name":"Miami Momar M3",
    "wof:placetype":"venue"
},
  "geometry": {"coordinates":[1.1847059727,41.1201858521],"type":"Point"}
}