{
  "type": "Feature",
  "properties": {
    "iso:country":"ES",
    "sg:address":"Calle de San Gil, 3",
    "sg:city":"S. Fernando",
    "sg:orig_category":"Asociaciones Y Clubs Deportivos",
    "sg:phone":"+34 956 88 08 09",
    "sg:postcode":"11100",
    "sg:province":"C\u00e1diz",
    "wof:name":"Gurria Romero Luis",
    "wof:placetype":"venue"
},
  "geometry": {"coordinates":[-6.2069759369,36.4565544128],"type":"Point"}
}