{
  "type": "Feature",
  "properties": {
    "iso:country":"ES",
    "sg:address":"Calle de Isabel La Catolica, 14",
    "sg:city":"Santander",
    "sg:orig_category":"Confecci\u00d3n (fabricaci\u00d3n, Al Por Mayor)",
    "sg:phone":"+34 942 23 40 80",
    "sg:postcode":"39007",
    "sg:province":"Cantabria",
    "wof:name":"Alonso Ramirez Luis",
    "wof:placetype":"venue"
},
  "geometry": {"coordinates":[-3.8143186569,43.4628181458],"type":"Point"}
}