{
  "type": "Feature",
  "properties": {
    "addr:full":"Pase Huerta De Guadian (de La), 3 Palencia Palencia 34002",
    "addr:postcode":"34002",
    "iso:country":"ES",
    "sg:address":"Pase Huerta De Guadian (de La), 3",
    "sg:city":"Palencia",
    "sg:orig_category":"M\u00c9dicos: Alergolog\u00cda",
    "sg:phone":"+34 979 71 29 77",
    "sg:postcode":"34002",
    "sg:province":"Palencia",
    "wof:name":"Alonso Gomez Alicia",
    "wof:placetype":"venue"
},
  "geometry": {"coordinates":[-4.527636528,42.0076599121],"type":"Point"}
}