{
  "type": "Feature",
  "properties": {
    "iso:country":"ES",
    "sg:address":"Carrer de Baquer, 7",
    "sg:city":"Hospitalet Llobregat",
    "sg:orig_category":"Art\u00cdculos De Regalo (al Por Menor)",
    "sg:phone":"+34 934 49 65 68",
    "sg:postcode":"08903",
    "sg:province":"Barcelona",
    "wof:name":"Oliveras Gui\u00f1on Segundo",
    "wof:placetype":"venue"
},
  "geometry": {"coordinates":[2.1209499836,41.3748054504],"type":"Point"}
}