{
  "type": "Feature",
  "properties": {
    "addr:full":"Calle de Jerusalen, 63 Lomo Los Frailes Las Palmas 35018",
    "addr:housenumber":"63",
    "addr:postcode":"35018",
    "addr:street":"Calle De Jerusalen;Frailes Las",
    "iso:country":"ES",
    "sg:address":"Calle de Jerusalen, 63",
    "sg:city":"Lomo Los Frailes",
    "sg:orig_category":"Plomeros",
    "sg:phone":"+34 928 43 90 40",
    "sg:postcode":"35018",
    "sg:province":"Las Palmas",
    "wof:name":"Fontaneria Josan Sl",
    "wof:placetype":"venue"
},
  "geometry": {"coordinates":[-15.4784650803,28.0919818878],"type":"Point"}
}