{
  "type": "Feature",
  "properties": {
    "iso:country":"ES",
    "sg:address":"Calle de Navegante Juan Morcillo, 84",
    "sg:city":"Villanueva Serena",
    "sg:orig_category":"Asociaciones Y Clubs Deportivos",
    "sg:phone":"+34 924 84 06 36",
    "sg:postcode":"06700",
    "sg:province":"Badajoz",
    "wof:name":"Gomez Chouvet Lorenzo Antonio",
    "wof:placetype":"venue"
},
  "geometry": {"coordinates":[-5.7897391319,38.9721183777],"type":"Point"}
}