{
  "type": "Feature",
  "properties": {
    "addr:full":"Pol Ind Usila, S/n Ugao-miraballes Vizcaya 48490",
    "addr:housenumber":"s / n",
    "addr:postcode":"48490",
    "iso:country":"ES",
    "sg:address":"Pol Ind Usila, S/n",
    "sg:city":"Ugao-miraballes",
    "sg:orig_category":"Metales (labores, Pulido)",
    "sg:phone":"+34 946 32 22 02",
    "sg:postcode":"48490",
    "sg:province":"Vizcaya",
    "sg:website":"www.asebal.com",
    "wof:name":"Auxiliar De Se\u00f1alizaciones Y Balizamientos S.l.",
    "wof:placetype":"venue"
},
  "geometry": {"coordinates":[-2.900121212,43.1792259216],"type":"Point"}
}