{
  "type": "Feature",
  "properties": {
    "iso:country":"ES",
    "sg:address":"Pla\u00c7 Joan Carreras Dagas, 2",
    "sg:city":"Bisbal D'emporda",
    "sg:orig_category":"Electricidad: Instaladores",
    "sg:phone":"+34 972 64 22 18",
    "sg:postcode":"17100",
    "sg:province":"Girona",
    "wof:name":"Insta%acions Coll-bonet S.l.",
    "wof:placetype":"venue"
},
  "geometry": {"coordinates":[3.0425977707,41.9439201355],"type":"Point"}
}