{
  "type": "Feature",
  "properties": {
    "iso:country":"ES",
    "sg:address":"Carr Conradors, 37",
    "sg:city":"Cabaneta",
    "sg:orig_category":"Art\u00cdculos De Aluminio",
    "sg:phone":"+34 971 60 54 29",
    "sg:postcode":"07141",
    "sg:province":"Islas Baleares",
    "wof:name":"Cerrajeria Santandreu",
    "wof:placetype":"venue"
},
  "geometry": {"coordinates":[2.741590023,39.6156005859],"type":"Point"}
}