{
  "type": "Feature",
  "properties": {
    "addr:full":"C/ Ruiz I Pablo, 23 Alaior Islas Baleares 07730",
    "addr:housenumber":"23",
    "addr:postcode":"07730",
    "addr:street":"C / Ruiz I Pablo",
    "iso:country":"ES",
    "sg:address":"C/ Ruiz I Pablo, 23",
    "sg:city":"Alaior",
    "sg:orig_category":"Partidos Pol\u00cdticos",
    "sg:phone":"+34 971 37 28 48",
    "sg:postcode":"07730",
    "sg:province":"Islas Baleares",
    "wof:name":"Partido Socialista Obrero Espa\u00f1ol",
    "wof:placetype":"venue"
},
  "geometry": {"coordinates":[4.1381030083,39.9316329956],"type":"Point"}
}