{
  "type": "Feature",
  "properties": {
    "addr:full":"Plaz Escultor Ruiz Olmos (del), 11 Cordoba C\u00f3rdoba 14014",
    "addr:postcode":"14014",
    "addr:street":"Co\u0301Rdoba",
    "iso:country":"ES",
    "sg:address":"Plaz Escultor Ruiz Olmos (del), 11",
    "sg:city":"Cordoba",
    "sg:orig_category":"Delegados, Agentes De Tr\u00c1nsito, Auxiliares De Transporte Internacional",
    "sg:phone":"+34 957 44 02 44",
    "sg:postcode":"14014",
    "sg:province":"C\u00f3rdoba",
    "wof:name":"Gonzalez Rodriguez Manuel Felipe",
    "wof:placetype":"venue"
},
  "geometry": {"coordinates":[-4.7634887695,37.8994750977],"type":"Point"}
}