{
  "type": "Feature",
  "properties": {
    "addr:full":"Calle de Poema La Maleta, 14 Vecindario Las Palmas 35110",
    "addr:housenumber":"14",
    "addr:postcode":"35110",
    "addr:street":"Calle De Poema La Maleta;Palmas",
    "iso:country":"ES",
    "sg:address":"Calle de Poema La Maleta, 14",
    "sg:city":"Vecindario",
    "sg:orig_category":"Estudios, Instalaci\u00d3n De Climatizaci\u00d3n",
    "sg:phone":"+34 928 75 29 39",
    "sg:postcode":"35110",
    "sg:province":"Las Palmas",
    "wof:name":"Lopez Calvo Francisco",
    "wof:placetype":"venue"
},
  "geometry": {"coordinates":[-15.4400901794,27.8505973816],"type":"Point"}
}