{
  "type": "Feature",
  "properties": {
    "addr:full":"Valdriz, 56 Pobra De San Xiao Lugo 27360",
    "addr:housenumber":"56",
    "addr:postcode":"27360",
    "addr:street":"Valdriz",
    "iso:country":"ES",
    "sg:address":"Valdriz, 56",
    "sg:city":"Pobra De San Xiao",
    "sg:orig_category":"Electrodom\u00c9sticos (fabricaci\u00d3n, Al Por Mayor)",
    "sg:phone":"+34 982 54 31 13",
    "sg:postcode":"27360",
    "sg:province":"Lugo",
    "wof:name":"Vazquez Ferreiro S.l.",
    "wof:placetype":"venue"
},
  "geometry": {"coordinates":[-7.446434021,42.8657264709],"type":"Point"}
}