{
  "type": "Feature",
  "properties": {
    "iso:country":"ES",
    "sg:address":"Calle de Castellon De La Plana, 31",
    "sg:city":"Ibi",
    "sg:orig_category":"Fabricaci\u00d3n De Moldes Y Modelos",
    "sg:phone":"+34 966 55 05 14",
    "sg:postcode":"03440",
    "sg:province":"Alicante",
    "wof:name":"Peygran Cdad.",
    "wof:placetype":"venue"
},
  "geometry": {"coordinates":[-0.5959789157,38.6104469299],"type":"Point"}
}