{
  "type": "Feature",
  "properties": {
    "addr:full":"Calle de Almunia, 5 Zaragoza Zaragoza 50003",
    "addr:housenumber":"5",
    "addr:postcode":"50003",
    "addr:street":"Calle De Almunia",
    "iso:country":"ES",
    "sg:address":"Calle de Almunia, 5",
    "sg:city":"Zaragoza",
    "sg:orig_category":"Abogados",
    "sg:phone":"+34 976 44 40 63",
    "sg:postcode":"50003",
    "sg:province":"Zaragoza",
    "wof:name":"Soria Carrillo Jose Maria",
    "wof:placetype":"venue"
},
  "geometry": {"coordinates":[-0.8992366791,41.6608085632],"type":"Point"}
}