{
  "type": "Feature",
  "properties": {
    "addr:full":"Carrer de Manresa, 4 Barcelona Barcelona 08003",
    "addr:housenumber":"4",
    "addr:postcode":"08003",
    "addr:street":"Carrer De Manresa",
    "iso:country":"ES",
    "sg:address":"Carrer de Manresa, 4",
    "sg:city":"Barcelona",
    "sg:orig_category":"Ense\u00d1anza: Profesiones Art\u00cdsticas",
    "sg:phone":"+34 933 19 55 84",
    "sg:postcode":"08003",
    "sg:province":"Barcelona",
    "wof:name":"Godo Costa Antonio",
    "wof:placetype":"venue"
},
  "geometry": {"coordinates":[2.1803328991,41.3833084106],"type":"Point"}
}