{
  "type": "Feature",
  "properties": {
    "addr:full":"Valme, 62 Dos Hermanas Sevilla 41700",
    "addr:housenumber":"62",
    "addr:postcode":"41700",
    "addr:street":"Valme",
    "iso:country":"ES",
    "sg:address":"Valme, 62",
    "sg:city":"Dos Hermanas",
    "sg:orig_category":"Bancos",
    "sg:phone":"+34 954 72 10 58",
    "sg:postcode":"41700",
    "sg:province":"Sevilla",
    "sg:website":"www.deutsche-bank.es",
    "wof:name":"Deutsche Bank S.a.e.",
    "wof:placetype":"venue"
},
  "geometry": {"coordinates":[-5.9281339645,37.2829055786],"type":"Point"}
}