{
  "type": "Feature",
  "properties": {
    "iso:country":"ES",
    "sg:address":"Carr Bartomeu Vicent Ramon, 15",
    "sg:city":"Eivissa",
    "sg:orig_category":"Centros Empresariales",
    "sg:phone":"+34 971 31 84 28",
    "sg:postcode":"07800",
    "sg:province":"Islas Baleares",
    "wof:name":"Latimar Ibiza,s.l.",
    "wof:placetype":"venue"
},
  "geometry": {"coordinates":[1.4334824085,38.9098548889],"type":"Point"}
}