{
  "type": "Feature",
  "properties": {
    "addr:full":"Calle de Vitoria, 6 Burgos Burgos 09004",
    "addr:housenumber":"6",
    "addr:postcode":"09004",
    "addr:street":"Calle De Vitoria",
    "iso:country":"ES",
    "sg:address":"Calle de Vitoria, 6",
    "sg:city":"Burgos",
    "sg:orig_category":"Bancos",
    "sg:phone":"+34 947 25 75 32",
    "sg:postcode":"09004",
    "sg:province":"Burgos",
    "wof:name":"Auna Telecomunicaciones S.a.u.",
    "wof:placetype":"venue"
},
  "geometry": {"coordinates":[-3.6986989975,42.341178894],"type":"Point"}
}