{
  "type": "Feature",
  "properties": {
    "iso:country":"ES",
    "sg:address":"Calle de Pascual Amat, 4",
    "sg:city":"Yecla",
    "sg:orig_category":"Arquitectos",
    "sg:phone":"+34 968 79 31 17",
    "sg:postcode":"30510",
    "sg:province":"Murcia",
    "wof:name":"Superficie 3 S.l.",
    "wof:placetype":"venue"
},
  "geometry": {"coordinates":[-1.115478158,38.6143722534],"type":"Point"}
}