{
  "type": "Feature",
  "properties": {
    "iso:country":"ES",
    "sg:address":"Calle de Se\u00d1or De Bembibre, 1",
    "sg:city":"Le\u00f3n",
    "sg:orig_category":"Librer\u00cdas",
    "sg:phone":"+34 987 25 74 04",
    "sg:postcode":"24005",
    "sg:province":"Le\u00f3n",
    "wof:name":"Ferro Ferro Jose Luis",
    "wof:placetype":"venue"
},
  "geometry": {"coordinates":[-5.5672068596,42.5871047974],"type":"Point"}
}