{
  "type": "Feature",
  "properties": {
    "iso:country":"ES",
    "sg:address":"San Andres, S/n",
    "sg:city":"San Andres",
    "sg:orig_category":"Mec\u00c1nico Del Autom\u00d3vil",
    "sg:phone":"+34 922 59 12 94",
    "sg:postcode":"38120",
    "sg:province":"Santa Cruz De Tenerife",
    "wof:name":"Arecio De La Rosa Y Sucesores De Juan Cabrera S.l.",
    "wof:placetype":"venue"
},
  "geometry": {"coordinates":[-16.1960868835,28.5078105927],"type":"Point"}
}