{
  "type": "Feature",
  "properties": {
    "iso:country":"ES",
    "sg:address":"Calle de Derecha, 28",
    "sg:city":"Mayorga",
    "sg:orig_category":"Reposter\u00cdas",
    "sg:phone":"+34 983 75 10 33",
    "sg:postcode":"47680",
    "sg:province":"Valladolid",
    "wof:name":"Blanco Perez Dolores",
    "wof:placetype":"venue"
},
  "geometry": {"coordinates":[-5.2643241882,42.1666564941],"type":"Point"}
}