{
  "type": "Feature",
  "properties": {
    "addr:full":"Calle de Descalzos, 4 Sevilla Sevilla 41003",
    "addr:housenumber":"4",
    "addr:postcode":"41003",
    "addr:street":"Calle De Descalzos",
    "iso:country":"ES",
    "sg:address":"Calle de Descalzos, 4",
    "sg:city":"Sevilla",
    "sg:orig_category":"Promotores Constructores",
    "sg:phone":"+34 954 21 08 44",
    "sg:postcode":"41003",
    "sg:province":"Sevilla",
    "wof:name":"Zapoteca Del Mar S.a.",
    "wof:placetype":"venue"
},
  "geometry": {"coordinates":[-5.9894442558,37.391242981],"type":"Point"}
}