{
  "type": "Feature",
  "properties": {
    "iso:country":"ES",
    "sg:address":"Carr Gracia, 57",
    "sg:city":"Mao",
    "sg:orig_category":"Ense\u00d1anza, Formaci\u00d3n Profesional: Aprendizaje",
    "sg:phone":"+34 971 35 24 30",
    "sg:postcode":"07702",
    "sg:province":"Islas Baleares",
    "wof:name":"Obispado De Menorca",
    "wof:placetype":"venue"
},
  "geometry": {"coordinates":[4.2627558708,39.8867454529],"type":"Point"}
}