{
  "type": "Feature",
  "properties": {
    "addr:full":"Ctra Sta Creu Calafell-barcelona, 149 Segur Calafell Tarragona 43882",
    "addr:housenumber":"149",
    "addr:postcode":"43882",
    "addr:street":"Ctra Sta Creu Calafell-Barcelona",
    "iso:country":"ES",
    "sg:address":"Ctra Sta Creu Calafell-barcelona, 149",
    "sg:city":"Segur Calafell",
    "sg:orig_category":"Cristaler\u00cdas",
    "sg:phone":"+34 977 16 49 37",
    "sg:postcode":"43882",
    "sg:province":"Tarragona",
    "wof:name":"Cristaleria Alumar 94 Del Baix Penedes S.l.",
    "wof:placetype":"venue"
},
  "geometry": {"coordinates":[1.6017500162,41.1933441162],"type":"Point"}
}