{
  "type": "Feature",
  "properties": {
    "addr:full":"Sis Quarts, 49 Onda Castell\u00f3n 12200",
    "addr:housenumber":"49",
    "addr:postcode":"12200",
    "addr:street":"Quarts;Castello\u0301N",
    "iso:country":"ES",
    "sg:address":"Sis Quarts, 49",
    "sg:city":"Onda",
    "sg:orig_category":"Porcelanas, Azulejos (fabricaci\u00d3n, Al Por Mayor)",
    "sg:phone":"+34 964 53 48 07",
    "sg:postcode":"12200",
    "sg:province":"Castell\u00f3n",
    "wof:name":"Cera Bronce S.l.",
    "wof:placetype":"venue"
},
  "geometry": {"coordinates":[-0.1923789978,39.9507102966],"type":"Point"}
}