{
  "type": "Feature",
  "properties": {
    "iso:country":"ES",
    "sg:address":"Calle de Serrano, 164",
    "sg:city":"Madrid",
    "sg:orig_category":"Alimentaci\u00d3n General (al Por Menor)",
    "sg:phone":"+34 915 61 68 59",
    "sg:postcode":"28002",
    "sg:province":"Madrid",
    "wof:name":"Santos Moral Francisco",
    "wof:placetype":"venue"
},
  "geometry": {"coordinates":[-3.6845560074,40.4463882446],"type":"Point"}
}