{
  "type": "Feature",
  "properties": {
    "iso:country":"ES",
    "sg:address":"Avda Marcelino Suarez, 25",
    "sg:city":"Barco",
    "sg:orig_category":"Ropa Para Ni\u00d1os (al Por Menor)",
    "sg:phone":"+34 988 32 70 32",
    "sg:postcode":"32300",
    "sg:province":"Ourense",
    "wof:name":"Copermoda S.l.",
    "wof:placetype":"venue"
},
  "geometry": {"coordinates":[-6.9840540886,42.4161911011],"type":"Point"}
}