{
  "type": "Feature",
  "properties": {
    "iso:country":"ES",
    "sg:address":"Calle de Principe De Vergara, 13",
    "sg:city":"Madrid",
    "sg:orig_category":"Asesor\u00cda Sobre Comunicaci\u00d3n De Empresas",
    "sg:phone":"+34 914 31 77 69",
    "sg:postcode":"28001",
    "sg:province":"Madrid",
    "sg:website":"www.consultayseleccion.com",
    "wof:name":"Consulta Y Seleccion S. A.",
    "wof:placetype":"venue"
},
  "geometry": {"coordinates":[-3.6804330349,40.4241027832],"type":"Point"}
}