{
  "type": "Feature",
  "properties": {
    "iso:country":"ES",
    "sg:address":"Pla\u00c7 Salvador Giner, (de), 4",
    "sg:city":"Carlet",
    "sg:orig_category":"Venta, Montaje De Neum\u00c1ticos",
    "sg:phone":"+34 962 53 10 82",
    "sg:postcode":"46240",
    "sg:province":"Valencia",
    "wof:name":"Hermanos Ortiz Peris S.l.",
    "wof:placetype":"venue"
},
  "geometry": {"coordinates":[-0.518148005,39.2266273499],"type":"Point"}
}