{
  "type": "Feature",
  "properties": {
    "iso:country":"ES",
    "sg:address":"Avda Pedro Barrie De La Maza, 10",
    "sg:city":"Coru\u00d1a",
    "sg:orig_category":"Arquitectos",
    "sg:phone":"+34 981 21 11 79",
    "sg:postcode":"15002",
    "sg:province":"La Coru\u00f1a",
    "wof:name":"Garcia Agudin Jose Luis",
    "wof:placetype":"venue"
},
  "geometry": {"coordinates":[-8.4028501511,43.3743400574],"type":"Point"}
}