{
  "type": "Feature",
  "properties": {
    "iso:country":"ES",
    "sg:address":"Calle de Fuente La, 24",
    "sg:city":"Cangas Narcea",
    "sg:orig_category":"Artesan\u00cda Y Trabajos Manuales: Suministros (al Por Menor)",
    "sg:phone":"+34 985 81 33 27",
    "sg:postcode":"33800",
    "sg:province":"Asturias",
    "wof:name":"Agustin Rodriguez Maria Luisa",
    "wof:placetype":"venue"
},
  "geometry": {"coordinates":[-6.5504236221,43.176612854],"type":"Point"}
}