{
  "type": "Feature",
  "properties": {
    "addr:full":"Calle de Tenderina, 167 Oviedo Asturias 33010",
    "addr:housenumber":"167",
    "addr:postcode":"33010",
    "addr:street":"Calle De Tenderina",
    "iso:country":"ES",
    "sg:address":"Calle de Tenderina, 167",
    "sg:city":"Oviedo",
    "sg:orig_category":"Promotores Constructores",
    "sg:phone":"+34 985 23 51 75",
    "sg:postcode":"33010",
    "sg:province":"Asturias",
    "wof:name":"Bango Y Fernandez S.l.",
    "wof:placetype":"venue"
},
  "geometry": {"coordinates":[-5.8255548477,43.3677635193],"type":"Point"}
}