{
  "type": "Feature",
  "properties": {
    "addr:full":"Calle de Santa Barbara, 46 Corella Navarra 31591",
    "addr:housenumber":"46",
    "addr:postcode":"31591",
    "addr:street":"Calle De Santa Barbara",
    "iso:country":"ES",
    "sg:address":"Calle de Santa Barbara, 46",
    "sg:city":"Corella",
    "sg:orig_category":"Farmacias",
    "sg:phone":"+34 948 78 10 04",
    "sg:postcode":"31591",
    "sg:province":"Navarra",
    "wof:name":"Elena Morales Jimenez Y Maria Del Carmen Poyales Morales S.i.",
    "wof:placetype":"venue"
},
  "geometry": {"coordinates":[-1.7912219763,42.1154136658],"type":"Point"}
}