{
  "type": "Feature",
  "properties": {
    "addr:full":"Calle de Jose Maria Usandizaga, 8 Errenteria Guip\u00f9zcoa 20100",
    "addr:housenumber":"8",
    "addr:postcode":"20100",
    "addr:street":"Calle De Jose Maria Usandizaga;Guipu\u0300Zcoa",
    "iso:country":"ES",
    "sg:address":"Calle de Jose Maria Usandizaga, 8",
    "sg:city":"Errenteria",
    "sg:orig_category":"Alimentaci\u00d3n General (al Por Menor)",
    "sg:phone":"+34 943 51 37 75",
    "sg:postcode":"20100",
    "sg:province":"Guip\u00f9zcoa",
    "wof:name":"Maria Asuncion Polo Escudero",
    "wof:placetype":"venue"
},
  "geometry": {"coordinates":[-1.9133620262,43.3100357056],"type":"Point"}
}