{
  "type": "Feature",
  "properties": {
    "iso:country":"ES",
    "sg:address":"Calle de Cronista Matias De Haro, 6",
    "sg:city":"Bailen",
    "sg:orig_category":"Abogados",
    "sg:phone":"+34 953 67 67 05",
    "sg:postcode":"23710",
    "sg:province":"Ja\u00e9n",
    "wof:name":"Villarejo Rusillo Mariana",
    "wof:placetype":"venue"
},
  "geometry": {"coordinates":[-3.7787439823,38.0943717957],"type":"Point"}
}