{
  "type": "Feature",
  "properties": {
    "addr:full":"Calle de Alboran, 3 Jerez De La Frontera C\u00e1diz 11406",
    "addr:housenumber":"3",
    "addr:postcode":"11406",
    "addr:street":"Calle De Alboran",
    "iso:country":"ES",
    "sg:address":"Calle de Alboran, 3",
    "sg:city":"Jerez De La Frontera",
    "sg:orig_category":"Ingeniero",
    "sg:phone":"+34 956 32 43 86",
    "sg:postcode":"11406",
    "sg:province":"C\u00e1diz",
    "wof:name":"Canalizaciones Guadalete S.l.",
    "wof:placetype":"venue"
},
  "geometry": {"coordinates":[-6.1179795265,36.6798553467],"type":"Point"}
}