{
  "type": "Feature",
  "properties": {
    "iso:country":"ES",
    "sg:address":"Carrer de Esteve Terradas, 51",
    "sg:city":"Barcelona",
    "sg:orig_category":"M\u00c9dicos: Medicina General",
    "sg:phone":"+34 934 34 22 40",
    "sg:postcode":"08023",
    "sg:province":"Barcelona",
    "wof:name":"Dextro Medica S.l.",
    "wof:placetype":"venue"
},
  "geometry": {"coordinates":[2.1400129795,41.4141120911],"type":"Point"}
}