{
  "type": "Feature",
  "properties": {
    "addr:full":"Salamanca 17 madrid 28020",
    "addr:housenumber":"17",
    "addr:postcode":"28020",
    "addr:street":"Salamanca",
    "iso:country":"ES",
    "sg:address":"Salamanca 17",
    "sg:city":"madrid",
    "sg:classifiers":[
        {
            "category":"Professional",
            "subcategory":"Computer Services",
            "type":"Services"
        }
    ],
    "sg:postcode":"28020",
    "sg:tags":[
        "travel",
        "trip",
        "share"
    ],
    "sg:website":"http://iwannagothere.com",
    "wof:name":"iwannagothere",
    "wof:placetype":"venue"
},
  "geometry": {"coordinates":[-3.7003565,40.4539547],"type":"Point"}
}