{
  "type": "Feature",
  "properties": {
    "iso:country":"ES",
    "sg:address":"Calle de Independencia (de La), 21",
    "sg:city":"Mostoles",
    "sg:orig_category":"Farmacias",
    "sg:phone":"+34 916 18 73 11",
    "sg:postcode":"28931",
    "sg:province":"Madrid",
    "wof:name":"Sanchez Moreno Valentin",
    "wof:placetype":"venue"
},
  "geometry": {"coordinates":[-3.8628339767,40.3234786987],"type":"Point"}
}