{
  "type": "Feature",
  "properties": {
    "addr:full":"Avda Espa\u00d1a, 8 Algeciras C\u00e1diz 11205",
    "addr:housenumber":"8;ca\u0301diz",
    "addr:postcode":"11205",
    "addr:street":"Avda Espan\u0303A",
    "iso:country":"ES",
    "sg:address":"Avda Espa\u00d1a, 8",
    "sg:city":"Algeciras",
    "sg:orig_category":"Soportes L\u00d3gicos, Programas Integradores De Aplicaciones (progiciels)",
    "sg:phone":"+34 956 66 91 78",
    "sg:postcode":"11205",
    "sg:province":"C\u00e1diz",
    "wof:name":"Lerena Panao Alejandro",
    "wof:placetype":"venue"
},
  "geometry": {"coordinates":[-5.4505028725,36.1456718445],"type":"Point"}
}