{
  "type": "Feature",
  "properties": {
    "iso:country":"ES",
    "sg:address":"Pase Conde De Sepulveda (del), 41",
    "sg:city":"Segovia",
    "sg:orig_category":"Cristaler\u00cdas",
    "sg:phone":"+34 921 44 49 46",
    "sg:postcode":"40006",
    "sg:province":"Segovia",
    "wof:name":"Aluminios Y Cristaleria Roma S.l.",
    "wof:placetype":"venue"
},
  "geometry": {"coordinates":[-4.2025856972,40.8924293518],"type":"Point"}
}