{
  "type": "Feature",
  "properties": {
    "iso:country":"ES",
    "sg:address":"Calle de Doctor Salcedo, 36",
    "sg:city":"Olvega",
    "sg:orig_category":"Ense\u00d1anza, Formaci\u00d3n Profesional: Aprendizaje",
    "sg:phone":"+34 976 64 56 93",
    "sg:postcode":"42110",
    "sg:province":"Soria",
    "wof:name":"Servicios Sociales De La Junta De Castilla Y Leon",
    "wof:placetype":"venue"
},
  "geometry": {"coordinates":[-1.9851540327,41.7794876099],"type":"Point"}
}