{
  "type": "Feature",
  "properties": {
    "iso:country":"ES",
    "sg:address":"Calle de Juan Ramon Jimenez (de), 2",
    "sg:city":"Alcobendas",
    "sg:orig_category":"Inmobiliaria (agencias)",
    "sg:phone":"+34 916 62 58 98",
    "sg:postcode":"28100",
    "sg:province":"Madrid",
    "wof:name":"Zerbo Timm Douglas Alexander",
    "wof:placetype":"venue"
},
  "geometry": {"coordinates":[-3.6573498249,40.5463371277],"type":"Point"}
}