{
  "type": "Feature",
  "properties": {
    "iso:country":"ES",
    "sg:address":"F. Malpartida Alta, S/n",
    "sg:city":"S. Roman Montes",
    "sg:orig_category":"Cr\u00cda De Animales",
    "sg:phone":"+34 925 59 72 36",
    "sg:postcode":"45646",
    "sg:province":"Toledo",
    "wof:name":"Compa\u00f1ia Agropecuaria Guadmora",
    "wof:placetype":"venue"
},
  "geometry": {"coordinates":[-4.7319440842,40.0716743469],"type":"Point"}
}