{
  "type": "Feature",
  "properties": {
    "addr:full":"Carrer de Can Peric, 20 Sentmenat Barcelona 08181",
    "addr:housenumber":"20",
    "addr:postcode":"08181",
    "addr:street":"Carrer De Can Peric",
    "iso:country":"ES",
    "sg:address":"Carrer de Can Peric, 20",
    "sg:city":"Sentmenat",
    "sg:orig_category":"Maquinaria Para Industrias Diversas",
    "sg:phone":"+34 937 15 14 42",
    "sg:postcode":"08181",
    "sg:province":"Barcelona",
    "wof:name":"As Cuatro S.a.",
    "wof:placetype":"venue"
},
  "geometry": {"coordinates":[2.1425876617,41.6091003418],"type":"Point"}
}