{
  "type": "Feature",
  "properties": {
    "iso:country":"ES",
    "sg:address":"Av Pere Matutes Noguera, 59",
    "sg:city":"Eivissa",
    "sg:orig_category":"Desinfecci\u00d3n, Desinsectaci\u00d3n, Desratizaci\u00d3n",
    "sg:phone":"+34 971 39 08 25",
    "sg:postcode":"07800",
    "sg:province":"Islas Baleares",
    "wof:name":"Rodriguez Quesada Isabel",
    "wof:placetype":"venue"
},
  "geometry": {"coordinates":[1.4180099964,38.9004707336],"type":"Point"}
}