{
  "type": "Feature",
  "properties": {
    "addr:full":"Raco D'ademuz, S/n P. I. La Cova Valencia 46940",
    "addr:housenumber":"s / n",
    "addr:postcode":"46940",
    "addr:street":"P. I. La Cova",
    "iso:country":"ES",
    "sg:address":"Raco D'ademuz, S/n",
    "sg:city":"P. I. La Cova",
    "sg:orig_category":"Tratamientos De Conversi\u00d3n Qu\u00cdmica O Electrol\u00cdtica De Metales",
    "sg:phone":"+34 961 52 11 63",
    "sg:postcode":"46940",
    "sg:province":"Valencia",
    "wof:name":"Peguimar S.a.",
    "wof:placetype":"venue"
},
  "geometry": {"coordinates":[-0.4839648902,39.4986114502],"type":"Point"}
}