{
  "type": "Feature",
  "properties": {
    "iso:country":"ES",
    "sg:address":"Avda Federico Silva, 32",
    "sg:city":"Benavente",
    "sg:orig_category":"Lavado, Limpieza De Veh\u00cdculos",
    "sg:phone":"+34 980 63 47 58",
    "sg:postcode":"49600",
    "sg:province":"Zamora",
    "wof:name":"Lavauto Benavente S.l.",
    "wof:placetype":"venue"
},
  "geometry": {"coordinates":[-5.6711888313,42.0019874573],"type":"Point"}
}