{
  "type": "Feature",
  "properties": {
    "addr:full":"Pg Tramuntana, 73 Castelldefels Barcelona 08860",
    "addr:housenumber":"73",
    "addr:postcode":"08860",
    "addr:street":"Pg Tramuntana",
    "iso:country":"ES",
    "sg:address":"Pg Tramuntana, 73",
    "sg:city":"Castelldefels",
    "sg:orig_category":"Carnicer\u00cdas, Carnicer\u00cdas",
    "sg:phone":"+34 936 65 25 64",
    "sg:postcode":"08860",
    "sg:province":"Barcelona",
    "wof:name":"Martos Gimenez Angel",
    "wof:placetype":"venue"
},
  "geometry": {"coordinates":[1.9883990288,41.268535614],"type":"Point"}
}