{
  "type": "Feature",
  "properties": {
    "addr:full":"Calle de Castelar, 1 Algar Murcia 30366",
    "addr:housenumber":"1",
    "addr:postcode":"30366",
    "addr:street":"Calle De Castelar",
    "iso:country":"ES",
    "sg:address":"Calle de Castelar, 1",
    "sg:city":"Algar",
    "sg:orig_category":"Supermercados Y Hipermercados",
    "sg:phone":"+34 968 13 56 81",
    "sg:postcode":"30366",
    "sg:province":"Murcia",
    "wof:name":"Supermercado Ramon Nieto S.l.",
    "wof:placetype":"venue"
},
  "geometry": {"coordinates":[-0.8667320013,37.6485366821],"type":"Point"}
}