{
  "type": "Feature",
  "properties": {
    "iso:country":"ES",
    "sg:address":"Calle de San Juan, 28",
    "sg:city":"Sonseca",
    "sg:orig_category":"Molduras, Junquillos, Listones Y Molduras Perforadas",
    "sg:phone":"+34 925 38 32 65",
    "sg:postcode":"45100",
    "sg:province":"Toledo",
    "wof:name":"Lemans C.b.",
    "wof:placetype":"venue"
},
  "geometry": {"coordinates":[-3.9683480263,39.6759643555],"type":"Point"}
}