{
  "type": "Feature",
  "properties": {
    "addr:full":"Avda Ricardo Carapeto Zambrano, 100 Badajoz Badajoz 06008",
    "addr:housenumber":"100",
    "addr:postcode":"06008",
    "addr:street":"Avda Ricardo Carapeto Zambrano",
    "iso:country":"ES",
    "sg:address":"Avda Ricardo Carapeto Zambrano, 100",
    "sg:city":"Badajoz",
    "sg:orig_category":"Cajas Para Embalar",
    "sg:phone":"+34 924 26 26 07",
    "sg:postcode":"06008",
    "sg:province":"Badajoz",
    "wof:name":"Caja Rural De Extremadura",
    "wof:placetype":"venue"
},
  "geometry": {"coordinates":[-6.9473338127,38.8786468506],"type":"Point"}
}