{
  "type": "Feature",
  "properties": {
    "addr:full":"Calle de Antequera, 4 Nerja M\u00e1laga 29780",
    "addr:housenumber":"4",
    "addr:postcode":"29780",
    "addr:street":"Calle De Antequera",
    "iso:country":"ES",
    "sg:address":"Calle de Antequera, 4",
    "sg:city":"Nerja",
    "sg:orig_category":"Agencias Y Agentes Comerciales, Representantes",
    "sg:phone":"+34 952 52 73 38",
    "sg:postcode":"29780",
    "sg:province":"M\u00e1laga",
    "wof:name":"Drain  Michael Robert",
    "wof:placetype":"venue"
},
  "geometry": {"coordinates":[-3.8665430546,36.7566871643],"type":"Point"}
}