{
  "type": "Feature",
  "properties": {
    "iso:country":"ES",
    "sg:address":"Ctra Toledo-alcazar, Km. 0070,8",
    "sg:city":"Madridejos",
    "sg:orig_category":"Veh\u00cdculos De Ocasi\u00d3n",
    "sg:phone":"+34 925 46 38 97",
    "sg:postcode":"45710",
    "sg:province":"Toledo",
    "wof:name":"Autos Sebas S.l.",
    "wof:placetype":"venue"
},
  "geometry": {"coordinates":[-3.5426566601,39.4668922424],"type":"Point"}
}