{
  "type": "Feature",
  "properties": {
    "iso:country":"ES",
    "sg:address":"Calle de Orotava La, 26",
    "sg:city":"Malaga",
    "sg:orig_category":"Carnes De Carnicer\u00cda (al Por Mayor)",
    "sg:phone":"+34 952 32 00 63",
    "sg:postcode":"29006",
    "sg:province":"M\u00e1laga",
    "wof:name":"Amador Y Aranda S.l.l.",
    "wof:placetype":"venue"
},
  "geometry": {"coordinates":[-4.4765663147,36.7048721313],"type":"Point"}
}