{
  "type": "Feature",
  "properties": {
    "addr:full":"Calle de Modistas, 21 Madrid Madrid 28037",
    "addr:housenumber":"21",
    "addr:postcode":"madrid;28037",
    "addr:street":"Calle De Modistas",
    "iso:country":"ES",
    "sg:address":"Calle de Modistas, 21",
    "sg:city":"Madrid",
    "sg:orig_category":"Plomeros",
    "sg:phone":"+34 913 06 58 78",
    "sg:postcode":"28037",
    "sg:province":"Madrid",
    "wof:name":"Martin Rojo Cristina",
    "wof:placetype":"venue"
},
  "geometry": {"coordinates":[-3.6193037033,40.4273490906],"type":"Point"}
}