{
  "type": "Feature",
  "properties": {
    "addr:full":"Carrer de Pau Claris, 4 Santa Perpetua De Mogoda Barcelona 08130",
    "addr:housenumber":"4",
    "addr:postcode":"08130",
    "addr:street":"Carrer De Pau Claris",
    "iso:country":"ES",
    "sg:address":"Carrer de Pau Claris, 4",
    "sg:city":"Santa Perpetua De Mogoda",
    "sg:orig_category":"Ense\u00d1anza: Idiomas",
    "sg:phone":"+34 935 60 77 72",
    "sg:postcode":"08130",
    "sg:province":"Barcelona",
    "wof:name":"English Havest Sct",
    "wof:placetype":"venue"
},
  "geometry": {"coordinates":[2.1835141182,41.534160614],"type":"Point"}
}