{
  "type": "Feature",
  "properties": {
    "addr:full":"Calle de Joaquin Lorenzo, 68 Madrid Madrid 28035",
    "addr:housenumber":"68",
    "addr:postcode":"madrid;28035",
    "addr:street":"Calle De Joaquin Lorenzo",
    "iso:country":"ES",
    "sg:address":"Calle de Joaquin Lorenzo, 68",
    "sg:city":"Madrid",
    "sg:orig_category":"Plomeros",
    "sg:phone":"+34 913 16 25 89",
    "sg:postcode":"28035",
    "sg:province":"Madrid",
    "wof:name":"Frutos Garcia Maria Luisa De",
    "wof:placetype":"venue"
},
  "geometry": {"coordinates":[-3.7314729691,40.475063324],"type":"Point"}
}