{
  "type": "Feature",
  "properties": {
    "iso:country":"ES",
    "sg:address":"Calle de Perez Medina, 42",
    "sg:city":"Alacant",
    "sg:orig_category":"Comercio De Piezas De Recambio Y De Accesorios De Veh\u00cdculos, Veh\u00cdculos Industriales",
    "sg:phone":"+34 965 22 85 68",
    "sg:postcode":"03007",
    "sg:province":"Alicante",
    "wof:name":"Hernandez Cano Jesus",
    "wof:placetype":"venue"
},
  "geometry": {"coordinates":[-0.4978129864,38.3398742676],"type":"Point"}
}