{
  "type": "Feature",
  "properties": {
    "addr:full":"Calle de Conde Orgaz, 3 Cruz Del Portillo Toledo 45593",
    "addr:housenumber":"3",
    "addr:postcode":"45593",
    "addr:street":"Calle De Conde Orgaz;Cruz Del Portillo",
    "iso:country":"ES",
    "sg:address":"Calle de Conde Orgaz, 3",
    "sg:city":"Cruz Del Portillo",
    "sg:orig_category":"Contenedores (mercanc\u00cdas)",
    "sg:phone":"+34 925 39 50 18",
    "sg:postcode":"45593",
    "sg:province":"Toledo",
    "wof:name":"Trans Nostrum S.l.",
    "wof:placetype":"venue"
},
  "geometry": {"coordinates":[-4.0194129944,39.9406776428],"type":"Point"}
}