{
  "type": "Feature",
  "properties": {
    "addr:full":"Calle de Casariche, 1 Herrera Sevilla 41567",
    "addr:housenumber":"1",
    "addr:postcode":"41567",
    "addr:street":"Calle De Casariche",
    "iso:country":"ES",
    "sg:address":"Calle de Casariche, 1",
    "sg:city":"Herrera",
    "sg:orig_category":"Electricidad: Instaladores",
    "sg:phone":"+34 954 01 37 81",
    "sg:postcode":"41567",
    "sg:province":"Sevilla",
    "wof:name":"Promitel S.c.a.",
    "wof:placetype":"venue"
},
  "geometry": {"coordinates":[-4.8479042053,37.3637199402],"type":"Point"}
}