{
  "type": "Feature",
  "properties": {
    "iso:country":"ES",
    "sg:address":"Calle de Carretera, S/n",
    "sg:city":"Tierrantona",
    "sg:orig_category":"Distribuci\u00d3n De Petr\u00d3leo Y Derivados",
    "sg:phone":"+34 974 50 70 12",
    "sg:postcode":"22336",
    "sg:province":"Huesca",
    "wof:name":"Gracia Solano Angel",
    "wof:placetype":"venue"
},
  "geometry": {"coordinates":[0.2827011049,42.3494987488],"type":"Point"}
}