{
  "type": "Feature",
  "properties": {
    "addr:full":"Ptda Costa-mitjana, 23 Penaguila Alicante 03815",
    "addr:housenumber":"23",
    "addr:postcode":"03815",
    "addr:street":"Ptda Costa-Mitjana",
    "iso:country":"ES",
    "sg:address":"Ptda Costa-mitjana, 23",
    "sg:city":"Penaguila",
    "sg:orig_category":"Albergues",
    "sg:phone":"+34 965 51 31 11",
    "sg:postcode":"03815",
    "sg:province":"Alicante",
    "wof:name":"Hostal Mas Del Pau S.l.",
    "wof:placetype":"venue"
},
  "geometry": {"coordinates":[-0.3598060012,38.6786804199],"type":"Point"}
}