{
  "type": "Feature",
  "properties": {
    "addr:full":"Carrer de Bruguera, 205 Calella Barcelona 08370",
    "addr:housenumber":"205",
    "addr:postcode":"08370",
    "addr:street":"Carrer De Bruguera",
    "iso:country":"ES",
    "sg:address":"Carrer de Bruguera, 205",
    "sg:city":"Calella",
    "sg:orig_category":"Inversiones",
    "sg:phone":"+34 937 66 50 10",
    "sg:postcode":"08370",
    "sg:province":"Barcelona",
    "wof:name":"Inversiones Multisectoriales S.l",
    "wof:placetype":"venue"
},
  "geometry": {"coordinates":[2.6639111042,41.6162071228],"type":"Point"}
}