{
  "type": "Feature",
  "properties": {
    "iso:country":"ES",
    "sg:address":"Poligono Industrial, S/n",
    "sg:city":"Avila",
    "sg:orig_category":"Diarios, Revistas Y Boletines (suscripciones)",
    "sg:phone":"+34 920 22 63 79",
    "sg:postcode":"05004",
    "sg:province":"\u00c1vila",
    "wof:name":"Prensa Distribucion Abulense S.l.",
    "wof:placetype":"venue"
},
  "geometry": {"coordinates":[-4.6828289032,40.6613960266],"type":"Point"}
}