{
  "type": "Feature",
  "properties": {
    "iso:country":"ES",
    "sg:address":"Carrer de Puig-agut, 23",
    "sg:city":"Torello",
    "sg:orig_category":"Fabricaci\u00d3n De Moldes Y Modelos",
    "sg:phone":"+34 938 59 01 81",
    "sg:postcode":"08570",
    "sg:province":"Barcelona",
    "wof:name":"Freixa Bofill Tesem S.l.",
    "wof:placetype":"venue"
},
  "geometry": {"coordinates":[2.2683360577,42.0454483032],"type":"Point"}
}