{
  "type": "Feature",
  "properties": {
    "iso:country":"ES",
    "sg:address":"Avda Miguel De Cervantes, 43",
    "sg:city":"Tarancon",
    "sg:orig_category":"Ropa Para Se\u00d1oras Y Caballeros (al Por Menor)",
    "sg:phone":"+34 969 32 05 50",
    "sg:postcode":"16400",
    "sg:province":"Cuenca",
    "wof:name":"Gomez Sanchez Luis",
    "wof:placetype":"venue"
},
  "geometry": {"coordinates":[-3.0095231533,40.0102500916],"type":"Point"}
}