{
  "type": "Feature",
  "properties": {
    "addr:full":"Calle de Olmos (de Los), 50 Partija-santa Monica Madrid 28529",
    "addr:housenumber":"50",
    "addr:postcode":"28529",
    "addr:street":"Calle De Olmos De Los",
    "iso:country":"ES",
    "sg:address":"Calle de Olmos (de Los), 50",
    "sg:city":"Partija-santa Monica",
    "sg:orig_category":"Suministros Y Colocaci\u00d3n De Canalones Para Aguas Pluviales",
    "sg:phone":"+34 913 01 14 59",
    "sg:postcode":"28529",
    "sg:province":"Madrid",
    "wof:name":"Canalon 2000 S.l.",
    "wof:placetype":"venue"
},
  "geometry": {"coordinates":[-3.5102670193,40.314289093],"type":"Point"}
}