{
  "type": "Feature",
  "properties": {
    "addr:full":"Calle de Nuestra Se\u00d1ora De Fatima, S/n Pilas Sevilla 41840",
    "addr:postcode":"41840",
    "addr:street":"Calle De Nuestra Sen\u0303Ora De;S / N",
    "iso:country":"ES",
    "sg:address":"Calle de Nuestra Se\u00d1ora De Fatima, S/n",
    "sg:city":"Pilas",
    "sg:orig_category":"Supermercados Y Hipermercados",
    "sg:phone":"+34 954 75 05 24",
    "sg:postcode":"41840",
    "sg:province":"Sevilla",
    "wof:name":"Udama S.a.",
    "wof:placetype":"venue"
},
  "geometry": {"coordinates":[-6.2976489067,37.3020095825],"type":"Point"}
}