{
  "type": "Feature",
  "properties": {
    "addr:full":"Calle de San Pelayo, 24 Cangas Onis Asturias 33550",
    "addr:housenumber":"24",
    "addr:postcode":"33550",
    "addr:street":"Calle De San;Onis Asturias",
    "iso:country":"ES",
    "sg:address":"Calle de San Pelayo, 24",
    "sg:city":"Cangas Onis",
    "sg:orig_category":"Peluqueros: De Se\u00d1oras",
    "sg:phone":"+34 985 84 84 98",
    "sg:postcode":"33550",
    "sg:province":"Asturias",
    "wof:name":"Fernandez Diaz Josefina",
    "wof:placetype":"venue"
},
  "geometry": {"coordinates":[-5.1300587654,43.3499717712],"type":"Point"}
}