{
  "type": "Feature",
  "properties": {
    "addr:full":"Carrer de Sant Francesc, 24 Sitges Barcelona 08870",
    "addr:housenumber":"24",
    "addr:postcode":"08870",
    "addr:street":"Carrer De Sant Francesc",
    "iso:country":"ES",
    "sg:address":"Carrer de Sant Francesc, 24",
    "sg:city":"Sitges",
    "sg:orig_category":"Ropa Para Se\u00d1oras (al Por Menor)",
    "sg:phone":"+34 938 94 49 75",
    "sg:postcode":"08870",
    "sg:province":"Barcelona",
    "wof:name":"Ramirez Morcillo Carmen",
    "wof:placetype":"venue"
},
  "geometry": {"coordinates":[1.8084330559,41.237613678],"type":"Point"}
}