{
  "type": "Feature",
  "properties": {
    "iso:country":"ES",
    "sg:address":"Calle de Juan De Garay, 2",
    "sg:city":"Almeria",
    "sg:orig_category":"Peluqueros: De Se\u00d1oras",
    "sg:phone":"+34 950 22 47 99",
    "sg:postcode":"04005",
    "sg:province":"Almer\u00eda",
    "wof:name":"Rueda Soriano Torcuato",
    "wof:placetype":"venue"
},
  "geometry": {"coordinates":[-2.4553239346,36.8398628235],"type":"Point"}
}