{
  "type": "Feature",
  "properties": {
    "addr:full":"Carrer de Rafael Casanova, S/n Gava Barcelona 08850",
    "addr:housenumber":"s / n",
    "addr:postcode":"08850",
    "addr:street":"Carrer De Rafael Casanova",
    "iso:country":"ES",
    "sg:address":"Carrer de Rafael Casanova, S/n",
    "sg:city":"Gava",
    "sg:orig_category":"Iglesia Cat\u00d3lica",
    "sg:phone":"+34 936 62 29 76",
    "sg:postcode":"08850",
    "sg:province":"Barcelona",
    "wof:name":"Parroquia Sant Nicasi De Gava",
    "wof:placetype":"venue"
},
  "geometry": {"coordinates":[1.9994449615,41.3097610474],"type":"Point"}
}