{
  "type": "Feature",
  "properties": {
    "iso:country":"ES",
    "sg:address":"Calle de Fernandez Ladreda, S/n",
    "sg:city":"Oviedo",
    "sg:orig_category":"Ropa Para Ni\u00d1os (al Por Menor)",
    "sg:phone":"+34 985 29 93 08",
    "sg:postcode":"33011",
    "sg:province":"Asturias",
    "sg:website":"www.inditex.es",
    "wof:name":"Stradivarius Espa\u00d1a S.a",
    "wof:placetype":"venue"
},
  "geometry": {"coordinates":[-5.8351025581,43.370765686],"type":"Point"}
}