{
  "type": "Feature",
  "properties": {
    "iso:country":"ES",
    "sg:address":"Calle de Miguel Martinez, 17",
    "sg:city":"Caudete",
    "sg:orig_category":"Promotores Constructores",
    "sg:phone":"+34 965 82 56 50",
    "sg:postcode":"02660",
    "sg:province":"Albacete",
    "wof:name":"Jubelcom Constrocciones S.l:",
    "wof:placetype":"venue"
},
  "geometry": {"coordinates":[-0.9904590249,38.7027816772],"type":"Point"}
}