{
  "type": "Feature",
  "properties": {
    "addr:full":"Calle de Lujan Perez, 5 Villa De Moya Las Palmas 35420",
    "addr:housenumber":"5",
    "addr:postcode":"35420",
    "addr:street":"Calle De Lujan Perez",
    "iso:country":"ES",
    "sg:address":"Calle de Lujan Perez, 5",
    "sg:city":"Villa De Moya",
    "sg:orig_category":"Fabricaci\u00d3n, Venta De Productos Base Farmac\u00c9uticos",
    "sg:phone":"+34 928 62 00 09",
    "sg:postcode":"35420",
    "sg:province":"Las Palmas",
    "wof:name":"Marrero Hernandez Victoria Maria",
    "wof:placetype":"venue"
},
  "geometry": {"coordinates":[-15.5827293396,28.1089496613],"type":"Point"}
}