{
  "type": "Feature",
  "properties": {
    "addr:full":"Pol Siete(walaig), 11 Monforte Cid Alicante 03670",
    "addr:housenumber":"11",
    "addr:postcode":"03670",
    "iso:country":"ES",
    "sg:address":"Pol Siete(walaig), 11",
    "sg:city":"Monforte Cid",
    "sg:orig_category":"M\u00c1rmoles, Granitos Y Piedras Naturales",
    "sg:phone":"+34 965 62 17 94",
    "sg:postcode":"03670",
    "sg:province":"Alicante",
    "wof:name":"Dura Granitos Y Marmoles S.l.",
    "wof:placetype":"venue"
},
  "geometry": {"coordinates":[-0.7296299934,38.3807296753],"type":"Point"}
}