{
  "type": "Feature",
  "properties": {
    "iso:country":"ES",
    "sg:address":"Calle de Escuelas, S/n",
    "sg:city":"Belvis Monroy",
    "sg:orig_category":"Administraciones Regionales, Departamentales Y Locales",
    "sg:phone":"+34 927 57 58 23",
    "sg:postcode":"10394",
    "sg:province":"C\u00e1ceres",
    "wof:name":"Ayuntamiento De Belvis De Monroy",
    "wof:placetype":"venue"
},
  "geometry": {"coordinates":[-5.6104049683,39.8195610046],"type":"Point"}
}