{
  "type": "Feature",
  "properties": {
    "iso:country":"ES",
    "sg:address":"Ctra Salamanca, 15",
    "sg:city":"Avila",
    "sg:orig_category":"Sales (al Por Mayor)",
    "sg:phone":"+34 920 22 10 12",
    "sg:postcode":"05002",
    "sg:province":"\u00c1vila",
    "wof:name":"Jimenez Ahijado Rodrigo",
    "wof:placetype":"venue"
},
  "geometry": {"coordinates":[-4.7109651566,40.658039093],"type":"Point"}
}