{
  "type": "Feature",
  "properties": {
    "iso:country":"ES",
    "sg:address":"Pg Verdaguer, 138",
    "sg:city":"Igualada",
    "sg:orig_category":"Transportes Por V\u00cdas Navegables",
    "sg:phone":"+34 938 03 64 13",
    "sg:postcode":"08700",
    "sg:province":"Barcelona",
    "wof:name":"Martos Lopez Fernando",
    "wof:placetype":"venue"
},
  "geometry": {"coordinates":[1.6269739866,41.5787200928],"type":"Point"}
}