{
  "type": "Feature",
  "properties": {
    "addr:full":"Avda Doctor Ramon Y Cajal, 10 Alacant Alicante 03003",
    "addr:housenumber":"10",
    "addr:postcode":"03003",
    "addr:street":"Avda Doctor Ramon Y Cajal",
    "iso:country":"ES",
    "sg:address":"Avda Doctor Ramon Y Cajal, 10",
    "sg:city":"Alacant",
    "sg:orig_category":"M\u00c1rmoles, Granitos Y Piedras Naturales",
    "sg:phone":"+34 965 92 62 42",
    "sg:postcode":"03003",
    "sg:province":"Alicante",
    "wof:name":"Incom S.l.",
    "wof:placetype":"venue"
},
  "geometry": {"coordinates":[-0.4888069928,38.3396072388],"type":"Point"}
}