{
  "type": "Feature",
  "properties": {
    "addr:full":"Carrer de L'argenteria, 66 Barcelona Barcelona 08003",
    "addr:housenumber":"66",
    "addr:postcode":"08003",
    "addr:street":"Carrer De L'Argenteria",
    "iso:country":"ES",
    "sg:address":"Carrer de L'argenteria, 66",
    "sg:city":"Barcelona",
    "sg:orig_category":"Bisuter\u00cda, Joyer\u00cda, Relojer\u00cda (al Por Menor)",
    "sg:phone":"+34 933 10 13 73",
    "sg:postcode":"08003",
    "sg:province":"Barcelona",
    "wof:name":"Galeria Alea S.l",
    "wof:placetype":"venue"
},
  "geometry": {"coordinates":[2.1810719967,41.3835639954],"type":"Point"}
}