{
  "type": "Feature",
  "properties": {
    "addr:full":"Ptge Llivia, 58 Barcelona Barcelona 08041",
    "addr:housenumber":"58",
    "addr:postcode":"08041",
    "addr:street":"Ptge Llivia",
    "iso:country":"ES",
    "sg:address":"Ptge Llivia, 58",
    "sg:city":"Barcelona",
    "sg:orig_category":"Peluqueros: De Se\u00d1oras",
    "sg:phone":"+34 933 47 11 18",
    "sg:postcode":"08041",
    "sg:province":"Barcelona",
    "wof:name":"Vizarro Aguilera Carmen",
    "wof:placetype":"venue"
},
  "geometry": {"coordinates":[2.1767935753,41.4203033447],"type":"Point"}
}