{
  "type": "Feature",
  "properties": {
    "iso:country":"ES",
    "sg:address":"Calle de Peso, 15",
    "sg:city":"Requena",
    "sg:orig_category":"Bisuter\u00cda, Joyer\u00cda, Relojer\u00cda (al Por Menor)",
    "sg:phone":"+34 962 30 37 50",
    "sg:postcode":"46340",
    "sg:province":"Valencia",
    "wof:name":"Perez Serrano Amparo",
    "wof:placetype":"venue"
},
  "geometry": {"coordinates":[-1.0995198488,39.4876327515],"type":"Point"}
}