{
  "type": "Feature",
  "properties": {
    "addr:full":"Calle de Matahacas, 25 Sevilla Sevilla 41003",
    "addr:housenumber":"25",
    "addr:postcode":"41003",
    "addr:street":"Calle De Matahacas",
    "iso:country":"ES",
    "sg:address":"Calle de Matahacas, 25",
    "sg:city":"Sevilla",
    "sg:orig_category":"Sellos De Goma Y Met\u00c1licos",
    "sg:phone":"+34 954 21 36 62",
    "sg:postcode":"41003",
    "sg:province":"Sevilla",
    "wof:name":"Morian Perea Juan",
    "wof:placetype":"venue"
},
  "geometry": {"coordinates":[-5.9859700203,37.3947181702],"type":"Point"}
}