{
  "type": "Feature",
  "properties": {
    "addr:full":"Pase San Eugenio, 9 Toledo Toledo 45003",
    "addr:housenumber":"9",
    "addr:postcode":"45003",
    "addr:street":"San Eugenio",
    "iso:country":"ES",
    "sg:address":"Pase San Eugenio, 9",
    "sg:city":"Toledo",
    "sg:orig_category":"Servicios Diversos",
    "sg:phone":"+34 925 22 99 50",
    "sg:postcode":"45003",
    "sg:province":"Toledo",
    "wof:name":"Sanchez Vicente-caba\u00f1as Rosa Maria",
    "wof:placetype":"venue"
},
  "geometry": {"coordinates":[-4.0219788551,39.8701210022],"type":"Point"}
}