{
  "type": "Feature",
  "properties": {
    "iso:country":"ES",
    "sg:address":"Avda Miranda, 4",
    "sg:city":"San Vicente De Barakaldo",
    "sg:orig_category":"Internados & Ense\u00d1anza Privada",
    "sg:phone":"+34 944 37 58 33",
    "sg:postcode":"48902",
    "sg:province":"Vizcaya",
    "wof:name":"Colegio De La Milagrosa-hermanas De La Caridad",
    "wof:placetype":"venue"
},
  "geometry": {"coordinates":[-2.9946188927,43.2966041565],"type":"Point"}
}