{
  "type": "Feature",
  "properties": {
    "addr:full":"Carr Sebastian Hernandez, De, 8 Carcaixent Valencia 46740",
    "addr:housenumber":"8",
    "addr:postcode":"46740",
    "addr:street":"Carr Sebastian Hernandez De",
    "iso:country":"ES",
    "sg:address":"Carr Sebastian Hernandez, De, 8",
    "sg:city":"Carcaixent",
    "sg:orig_category":"Bebidas",
    "sg:phone":"+34 962 43 08 48",
    "sg:postcode":"46740",
    "sg:province":"Valencia",
    "wof:name":"Distribucions Carcaixent S.l.",
    "wof:placetype":"venue"
},
  "geometry": {"coordinates":[-0.4469720125,39.1166763306],"type":"Point"}
}