{
  "type": "Feature",
  "properties": {
    "addr:full":"Jazinto Olabe Plaza, 3 Eibar Guip\u00f9zcoa 20600",
    "addr:housenumber":"3",
    "addr:postcode":"20600",
    "addr:street":"Jazinto Olabe Plaza;Guipu\u0300Zcoa",
    "iso:country":"ES",
    "sg:address":"Jazinto Olabe Plaza, 3",
    "sg:city":"Eibar",
    "sg:orig_category":"Suministros Para Hoteles",
    "sg:phone":"+34 943 20 11 78",
    "sg:postcode":"20600",
    "sg:province":"Guip\u00f9zcoa",
    "wof:name":"Comercial Zabala",
    "wof:placetype":"venue"
},
  "geometry": {"coordinates":[-2.4884390831,43.1800117493],"type":"Point"}
}