{
  "type": "Feature",
  "properties": {
    "addr:full":"Avda Italia, 49 Huelva Huelva 21001",
    "addr:housenumber":"49",
    "addr:postcode":"21001",
    "addr:street":"Avda Italia",
    "iso:country":"ES",
    "sg:address":"Avda Italia, 49",
    "sg:city":"Huelva",
    "sg:orig_category":"Plomeros",
    "sg:phone":"+34 959 24 82 38",
    "sg:postcode":"21001",
    "sg:province":"Huelva",
    "wof:name":"Mu\u00f1oz Perez Manuel Angel",
    "wof:placetype":"venue"
},
  "geometry": {"coordinates":[-6.9522838593,37.2541389465],"type":"Point"}
}