{
  "type": "Feature",
  "properties": {
    "addr:full":"Calle de Doctor Diego Guigou, 1 Santisimo-las Aguilas Santa Cruz De Tenerife 38400",
    "addr:housenumber":"1",
    "addr:postcode":"38400",
    "addr:street":"Calle De Doctor Diego Guigou",
    "iso:country":"ES",
    "sg:address":"Calle de Doctor Diego Guigou, 1",
    "sg:city":"Santisimo-las Aguilas",
    "sg:orig_category":"Centros M\u00c9dicos Y Sociales, Dispensarios",
    "sg:phone":"+34 922 37 68 87",
    "sg:postcode":"38400",
    "sg:province":"Santa Cruz De Tenerife",
    "wof:name":"Artrovida S.l.",
    "wof:placetype":"venue"
},
  "geometry": {"coordinates":[-16.2548561096,28.4698104858],"type":"Point"}
}