{
  "type": "Feature",
  "properties": {
    "addr:full":"Calle de Perez Galdos, 19 Santa Cruz De Tenerife Santa Cruz De Tenerife 38002",
    "addr:housenumber":"19",
    "addr:postcode":"38002",
    "addr:street":"Calle De Perez Galdos",
    "iso:country":"ES",
    "sg:address":"Calle de Perez Galdos, 19",
    "sg:city":"Santa Cruz De Tenerife",
    "sg:orig_category":"Institutos De Belleza",
    "sg:phone":"+34 922 53 12 96",
    "sg:postcode":"38002",
    "sg:province":"Santa Cruz De Tenerife",
    "wof:name":"Comunidad De Bienes Peyco",
    "wof:placetype":"venue"
},
  "geometry": {"coordinates":[-16.2527294159,28.4681587219],"type":"Point"}
}