{
  "type": "Feature",
  "properties": {
    "addr:full":"Calle de Alvarez Quintero, 41 Herrera Sevilla 41567",
    "addr:housenumber":"41",
    "addr:postcode":"41567",
    "addr:street":"Calle De Alvarez Quintero",
    "iso:country":"ES",
    "sg:address":"Calle de Alvarez Quintero, 41",
    "sg:city":"Herrera",
    "sg:orig_category":"Forjas Y Altos Hornos",
    "sg:phone":"+34 954 01 28 34",
    "sg:postcode":"41567",
    "sg:province":"Sevilla",
    "wof:name":"Herreria Sierra Sur",
    "wof:placetype":"venue"
},
  "geometry": {"coordinates":[-4.8444304466,37.3569450378],"type":"Point"}
}