{
  "type": "Feature",
  "properties": {
    "addr:full":"Fdo Baixauli Chornet, S/n Sedavi Valencia 46910",
    "addr:housenumber":"s / n",
    "addr:postcode":"46910",
    "addr:street":"Chornet",
    "iso:country":"ES",
    "sg:address":"Fdo Baixauli Chornet, S/n",
    "sg:city":"Sedavi",
    "sg:orig_category":"Asociaciones Y Clubs Deportivos",
    "sg:phone":"+34 963 75 91 21",
    "sg:postcode":"46910",
    "sg:province":"Valencia",
    "wof:name":"Sedavi Unio Esportiva",
    "wof:placetype":"venue"
},
  "geometry": {"coordinates":[-0.3789139986,39.4236602783],"type":"Point"}
}