{
  "type": "Feature",
  "properties": {
    "iso:country":"ES",
    "sg:address":"Carr Metge En Joan Garces, 39",
    "sg:city":"Cullera",
    "sg:orig_category":"Asesor\u00cda Sobre Comunicaci\u00d3n De Empresas",
    "sg:phone":"+34 961 72 13 91",
    "sg:postcode":"46400",
    "sg:province":"Valencia",
    "wof:name":"Climent Pizarro Maria Jose",
    "wof:placetype":"venue"
},
  "geometry": {"coordinates":[-0.2532660067,39.1617469788],"type":"Point"}
}