{
  "type": "Feature",
  "properties": {
    "iso:country":"ES",
    "sg:address":"Carrer de Antoni Roig (d'), 61",
    "sg:city":"Torredembarra",
    "sg:orig_category":"Ropa Para Se\u00d1oras (al Por Menor)",
    "sg:phone":"+34 977 64 58 94",
    "sg:postcode":"43830",
    "sg:province":"Tarragona",
    "wof:name":"Sisa Moda S.l.",
    "wof:placetype":"venue"
},
  "geometry": {"coordinates":[1.3995050192,41.144153595],"type":"Point"}
}