{
  "type": "Feature",
  "properties": {
    "addr:full":"Carrer de Pirineus, 121 Sant Salvador Tarragona 43130",
    "addr:housenumber":"121",
    "addr:postcode":"43130",
    "addr:street":"Carrer De Pirineus",
    "iso:country":"ES",
    "sg:address":"Carrer de Pirineus, 121",
    "sg:city":"Sant Salvador",
    "sg:orig_category":"Farmacias",
    "sg:phone":"+34 977 52 17 79",
    "sg:postcode":"43130",
    "sg:province":"Tarragona",
    "wof:name":"Pedrola Ferrando Montserrat",
    "wof:placetype":"venue"
},
  "geometry": {"coordinates":[1.2406669855,41.1610221863],"type":"Point"}
}