{
  "type": "Feature",
  "properties": {
    "iso:country":"ES",
    "sg:address":"Pl Catalunya (de), 3",
    "sg:city":"Torredembarra",
    "sg:orig_category":"Molduras, Junquillos, Listones Y Molduras Perforadas",
    "sg:phone":"+34 977 64 09 92",
    "sg:postcode":"43830",
    "sg:province":"Tarragona",
    "wof:name":"Galiano Quesada S.c.p.",
    "wof:placetype":"venue"
},
  "geometry": {"coordinates":[1.3979309797,41.1434783936],"type":"Point"}
}