{
  "type": "Feature",
  "properties": {
    "iso:country":"ES",
    "sg:address":"Leon-collanzo, Km. 0024,5",
    "sg:city":"Robles Valcueva",
    "sg:orig_category":"Hormig\u00d3n (m\u00c1quinas E Instalaci\u00d3n)",
    "sg:phone":"+34 987 59 13 17",
    "sg:postcode":"24839",
    "sg:province":"Le\u00f3n",
    "wof:name":"Lafarge Aridos Y Hormigones S.a.",
    "wof:placetype":"venue"
},
  "geometry": {"coordinates":[-5.506729126,42.8396606445],"type":"Point"}
}