{
  "type": "Feature",
  "properties": {
    "iso:country":"ES",
    "sg:address":"Dr. Roure, 21",
    "sg:city":"Tremp",
    "sg:orig_category":"Carnicer\u00cdas, Carnicer\u00cdas",
    "sg:phone":"+34 973 65 12 83",
    "sg:postcode":"25620",
    "sg:province":"Lleida",
    "wof:name":"Stefanova Papazova Adelina",
    "wof:placetype":"venue"
},
  "geometry": {"coordinates":[0.8950970173,42.1675338745],"type":"Point"}
}