{
  "type": "Feature",
  "properties": {
    "iso:country":"ES",
    "sg:address":"Calle de Nassen Febrer Calle, 39",
    "sg:city":"Valencia",
    "sg:orig_category":"Agencias De Viajes",
    "sg:phone":"+34 963 78 41 32",
    "sg:postcode":"46017",
    "sg:province":"Valencia",
    "wof:name":"Luna Serrano Conrado",
    "wof:placetype":"venue"
},
  "geometry": {"coordinates":[-0.3882589936,39.4514770508],"type":"Point"}
}