{
  "type": "Feature",
  "properties": {
    "iso:country":"ES",
    "sg:address":"Calle de Puerto Escondido, 1",
    "sg:city":"Santa Cruz De Tenerife",
    "sg:orig_category":"Transporte En General",
    "sg:phone":"+34 922 28 43 52",
    "sg:postcode":"38002",
    "sg:province":"Santa Cruz De Tenerife",
    "wof:name":"Explotaciones Inmobiliarias Mavi S.a",
    "wof:placetype":"venue"
},
  "geometry": {"coordinates":[-16.2510242462,28.4693183899],"type":"Point"}
}