{
  "type": "Feature",
  "properties": {
    "addr:full":"Avda Camelias, 135 Vigo Pontevedra 36211",
    "addr:housenumber":"135",
    "addr:postcode":"36211",
    "addr:street":"Avda Camelias",
    "iso:country":"ES",
    "sg:address":"Avda Camelias, 135",
    "sg:city":"Vigo",
    "sg:orig_category":"Psic\u00d3logos",
    "sg:phone":"+34 986 20 13 96",
    "sg:postcode":"36211",
    "sg:province":"Pontevedra",
    "wof:name":"Suarez Gonzalez Vicente",
    "wof:placetype":"venue"
},
  "geometry": {"coordinates":[-8.7310228348,42.2223091125],"type":"Point"}
}