{
  "type": "Feature",
  "properties": {
    "iso:country":"ES",
    "sg:address":"Calle de Mombuey, 17",
    "sg:city":"Madrid",
    "sg:orig_category":"Guarda",
    "sg:phone":"+34 913 81 93 69",
    "sg:postcode":"28050",
    "sg:province":"Madrid",
    "wof:name":"Benito Leon Javier",
    "wof:placetype":"venue"
},
  "geometry": {"coordinates":[-3.6363959312,40.4838600159],"type":"Point"}
}