{
  "type": "Feature",
  "properties": {
    "addr:full":"Calle de Independencia, 17 Oviedo Asturias 33004",
    "addr:housenumber":"17",
    "addr:postcode":"33004",
    "addr:street":"Calle De Independencia",
    "iso:country":"ES",
    "sg:address":"Calle de Independencia, 17",
    "sg:city":"Oviedo",
    "sg:orig_category":"Comercio De Mobiliario De Oficina",
    "sg:phone":"+34 985 24 27 38",
    "sg:postcode":"33004",
    "sg:province":"Asturias",
    "wof:name":"Roig Serrano Salvador",
    "wof:placetype":"venue"
},
  "geometry": {"coordinates":[-5.856180191,43.3647384644],"type":"Point"}
}