{
  "type": "Feature",
  "properties": {
    "iso:country":"ES",
    "sg:address":"Calle de Miribilla, 4",
    "sg:city":"Bilbao",
    "sg:orig_category":"Promotores Constructores",
    "sg:phone":"+34 944 16 16 97",
    "sg:postcode":"48003",
    "sg:province":"Vizcaya",
    "wof:name":"Gacovas 2002 S.l.",
    "wof:placetype":"venue"
},
  "geometry": {"coordinates":[-2.9254910946,43.2548103333],"type":"Point"}
}