{
  "type": "Feature",
  "properties": {
    "addr:full":"Carrer de Rafael Campalans, 9 Hospitalet Llobregat Barcelona 08903",
    "addr:housenumber":"9",
    "addr:postcode":"08903",
    "addr:street":"Carrer De Rafael Campalans",
    "iso:country":"ES",
    "sg:address":"Carrer de Rafael Campalans, 9",
    "sg:city":"Hospitalet Llobregat",
    "sg:orig_category":"Porcelanas, Azulejos (fabricaci\u00d3n, Al Por Mayor)",
    "sg:phone":"+34 933 34 98 28",
    "sg:postcode":"08903",
    "sg:province":"Barcelona",
    "wof:name":"C. Codina Costa S.l.",
    "wof:placetype":"venue"
},
  "geometry": {"coordinates":[2.1212639809,41.3742713928],"type":"Point"}
}