{
  "type": "Feature",
  "properties": {
    "addr:full":"Ciudad Real-daimiel, Km. 0256,0 Torralba Calatrava Ciudad Real 13160",
    "addr:postcode":"13160",
    "addr:street":"Real-Daimiel Km. 0256,0",
    "iso:country":"ES",
    "sg:address":"Ciudad Real-daimiel, Km. 0256,0",
    "sg:city":"Torralba Calatrava",
    "sg:orig_category":"Restaurantes",
    "sg:phone":"+34 926 81 00 36",
    "sg:postcode":"13160",
    "sg:province":"Ciudad Real",
    "wof:name":"Hoteles Campoblanco S.l.",
    "wof:placetype":"venue"
},
  "geometry": {"coordinates":[-3.752959013,39.0169181824],"type":"Point"}
}