{
  "type": "Feature",
  "properties": {
    "addr:full":"Grup Mirador A Bilbao, 3 Bilbao Vizcaya 48007",
    "addr:housenumber":"3",
    "addr:postcode":"48007",
    "addr:street":"Bilbao",
    "iso:country":"ES",
    "sg:address":"Grup Mirador A Bilbao, 3",
    "sg:city":"Bilbao",
    "sg:orig_category":"Plomeros",
    "sg:phone":"+34 944 45 46 90",
    "sg:postcode":"48007",
    "sg:province":"Vizcaya",
    "wof:name":"Proyectos E Instalaciones Fontygas S.l.",
    "wof:placetype":"venue"
},
  "geometry": {"coordinates":[-2.922244072,43.2709121704],"type":"Point"}
}