{
  "type": "Feature",
  "properties": {
    "addr:full":"Carrer de Sant Ferran, 34 Premia Mar Barcelona 08330",
    "addr:housenumber":"34",
    "addr:postcode":"08330",
    "addr:street":"Carrer De Sant Ferran",
    "iso:country":"ES",
    "sg:address":"Carrer de Sant Ferran, 34",
    "sg:city":"Premia Mar",
    "sg:orig_category":"Servicios De Higiene Y Peluquer\u00cda Para Perros Y Gatos",
    "sg:phone":"+34 937 51 00 70",
    "sg:postcode":"08330",
    "sg:province":"Barcelona",
    "wof:name":"Vilanova Boqueras Silvia",
    "wof:placetype":"venue"
},
  "geometry": {"coordinates":[2.353110075,41.4906196594],"type":"Point"}
}