{
  "type": "Feature",
  "properties": {
    "iso:country":"ES",
    "sg:address":"Calle de Colon, 19",
    "sg:city":"Castellon",
    "sg:orig_category":"Abogados",
    "sg:phone":"+34 964 23 09 58",
    "sg:postcode":"12001",
    "sg:province":"Castell\u00f3n",
    "wof:name":"Garcia Petit Barrachina Alfredo",
    "wof:placetype":"venue"
},
  "geometry": {"coordinates":[-0.0376396999,39.9865112305],"type":"Point"}
}