{
  "type": "Feature",
  "properties": {
    "iso:country":"ES",
    "sg:address":"C/ Ciutat De Gibraltar, 24",
    "sg:city":"Paterna",
    "sg:orig_category":"Venta, Colocaci\u00d3n, Reparaci\u00d3n De Parabrisas, Techos Descapotables",
    "sg:phone":"+34 961 34 01 10",
    "sg:postcode":"46988",
    "sg:province":"Valencia",
    "sg:website":"www.guardianexpress.es",
    "wof:name":"Guardian Glass Express S. L.",
    "wof:placetype":"venue"
},
  "geometry": {"coordinates":[-0.4724059999,39.5111808777],"type":"Point"}
}