{
  "type": "Feature",
  "properties": {
    "iso:country":"ES",
    "sg:address":"Carrer de Joan Burgada, 6",
    "sg:city":"S. Boi Llobregat",
    "sg:orig_category":"Centros Empresariales",
    "sg:phone":"+34 936 30 20 88",
    "sg:postcode":"08830",
    "sg:province":"Barcelona",
    "wof:name":"Comunidad De Propietarios Ascensor Juan Burgada 6-8",
    "wof:placetype":"venue"
},
  "geometry": {"coordinates":[2.0339860916,41.356010437],"type":"Point"}
}