{
  "type": "Feature",
  "properties": {
    "iso:country":"ES",
    "sg:address":"Rua Venezuela, 36",
    "sg:city":"Vigo",
    "sg:orig_category":"M\u00c9dicos: Estomatolog\u00cda",
    "sg:phone":"+34 986 47 10 58",
    "sg:postcode":"36203",
    "sg:province":"Pontevedra",
    "wof:name":"Filgueira Figueiral Jose",
    "wof:placetype":"venue"
},
  "geometry": {"coordinates":[-8.7195196152,42.2324256897],"type":"Point"}
}