{
  "type": "Feature",
  "properties": {
    "iso:country":"ES",
    "sg:address":"Calle de Santo Cristo, 2",
    "sg:city":"Aranda Duero",
    "sg:orig_category":"Ropa Para Ni\u00d1os (al Por Menor)",
    "sg:phone":"+34 947 50 39 37",
    "sg:postcode":"09400",
    "sg:province":"Burgos",
    "wof:name":"Sanz Frias Julia",
    "wof:placetype":"venue"
},
  "geometry": {"coordinates":[-3.6896541119,41.6706237793],"type":"Point"}
}