{
  "type": "Feature",
  "properties": {
    "iso:country":"ES",
    "sg:address":"Calle de Coria, 23",
    "sg:city":"Moraleja",
    "sg:orig_category":"Delegados, Agentes De Tr\u00c1nsito, Auxiliares De Transporte Internacional",
    "sg:phone":"+34 927 51 52 01",
    "sg:postcode":"10840",
    "sg:province":"C\u00e1ceres",
    "wof:name":"Reyes Cortes Francisco",
    "wof:placetype":"venue"
},
  "geometry": {"coordinates":[-6.6559281349,40.0652580261],"type":"Point"}
}