{
  "type": "Feature",
  "properties": {
    "iso:country":"ES",
    "sg:address":"Plaz Rojas Clemente, 2",
    "sg:city":"Valencia",
    "sg:orig_category":"Inmobiliaria (agencias)",
    "sg:phone":"+34 963 15 40 40",
    "sg:postcode":"46008",
    "sg:province":"Valencia",
    "wof:name":"Mayo C.b.",
    "wof:placetype":"venue"
},
  "geometry": {"coordinates":[-0.3853659928,39.4729194641],"type":"Point"}
}