{
  "type": "Feature",
  "properties": {
    "addr:full":"Cm\u00d1o Pozos, 2 Vigo Pontevedra 36209",
    "addr:housenumber":"2",
    "addr:postcode":"36209",
    "addr:street":"Pozos",
    "iso:country":"ES",
    "sg:address":"Cm\u00d1o Pozos, 2",
    "sg:city":"Vigo",
    "sg:orig_category":"Transportes Por Carretera: Lotes Completos, Mercanc\u00cdas Diversas",
    "sg:phone":"+34 986 23 23 50",
    "sg:postcode":"36209",
    "sg:province":"Pontevedra",
    "wof:name":"Adoalco Sl",
    "wof:placetype":"venue"
},
  "geometry": {"coordinates":[-8.7391681671,42.2168960571],"type":"Point"}
}