{
  "type": "Feature",
  "properties": {
    "iso:country":"ES",
    "sg:address":"Avda Hugo Bacharach, 30",
    "sg:city":"Foios",
    "sg:orig_category":"Deportes Y Programas De Aventura",
    "sg:phone":"+34 961 49 66 55",
    "sg:postcode":"46134",
    "sg:province":"Valencia",
    "wof:name":"Ferrando Pe\u00f1a Maria Angeles",
    "wof:placetype":"venue"
},
  "geometry": {"coordinates":[-0.3521989882,39.5360298157],"type":"Point"}
}