{
  "type": "Feature",
  "properties": {
    "iso:country":"ES",
    "sg:address":"Pol Ind La Salina, 2",
    "sg:city":"Rute",
    "sg:orig_category":"Construcciones Met\u00c1licas",
    "sg:phone":"+34 957 53 35 70",
    "sg:postcode":"14960",
    "sg:province":"C\u00f3rdoba",
    "wof:name":"Cablofil Iberica S.a.",
    "wof:placetype":"venue"
},
  "geometry": {"coordinates":[-4.36434412,37.3276290894],"type":"Point"}
}