{
  "type": "Feature",
  "properties": {
    "iso:country":"ES",
    "sg:address":"Calle de Almeria, 10",
    "sg:city":"Madrid",
    "sg:orig_category":"Alimentaci\u00d3n General (al Por Menor)",
    "sg:phone":"+34 917 26 00 74",
    "sg:postcode":"28028",
    "sg:province":"Madrid",
    "wof:name":"Parroquia San Patricio",
    "wof:placetype":"venue"
},
  "geometry": {"coordinates":[-3.6621451378,40.4297599792],"type":"Point"}
}