{
  "type": "Feature",
  "properties": {
    "iso:country":"ES",
    "sg:address":"Carr Bellpuig, 19",
    "sg:city":"Girona",
    "sg:orig_category":"Agencias Y Agentes Comerciales, Representantes",
    "sg:phone":"+34 972 21 54 29",
    "sg:postcode":"17007",
    "sg:province":"Girona",
    "wof:name":"Costa Pages Jose Maria",
    "wof:placetype":"venue"
},
  "geometry": {"coordinates":[2.8373990059,41.9948196411],"type":"Point"}
}