{
  "type": "Feature",
  "properties": {
    "iso:country":"ES",
    "sg:address":"Calle de San Sebastian, 30",
    "sg:city":"Tarifa",
    "sg:orig_category":"Inform\u00c1tica, Ofim\u00c1tica (estudios, Asesor\u00cda, Ingenier\u00cda, Formaci\u00d3n)",
    "sg:phone":"+34 956 68 13 88",
    "sg:postcode":"11380",
    "sg:province":"C\u00e1diz",
    "wof:name":"Alm Ordenadores Tarifa S.l.",
    "wof:placetype":"venue"
},
  "geometry": {"coordinates":[-5.6075024605,36.0157356262],"type":"Point"}
}