{
  "type": "Feature",
  "properties": {
    "iso:country":"ES",
    "sg:address":"Calle de Juan Duque, 35",
    "sg:city":"Madrid",
    "sg:orig_category":"Panader\u00cdas, Panader\u00cdas",
    "sg:phone":"+34 913 66 10 78",
    "sg:postcode":"28005",
    "sg:province":"Madrid",
    "wof:name":"Sanchez Seco Anuncia Josefa",
    "wof:placetype":"venue"
},
  "geometry": {"coordinates":[-3.719381094,40.410068512],"type":"Point"}
}