{
  "type": "Feature",
  "properties": {
    "addr:full":"Urb Torrequinto, 48 Alcala Guadaira Sevilla 41500",
    "addr:housenumber":"48",
    "addr:postcode":"41500",
    "addr:street":"Urb Torrequinto",
    "iso:country":"ES",
    "sg:address":"Urb Torrequinto, 48",
    "sg:city":"Alcala Guadaira",
    "sg:orig_category":"Agencias Y Asesores De Publicidad",
    "sg:phone":"+34 954 12 87 32",
    "sg:postcode":"41500",
    "sg:province":"Sevilla",
    "wof:name":"Janein Sl",
    "wof:placetype":"venue"
},
  "geometry": {"coordinates":[-5.8398590088,37.3383140564],"type":"Point"}
}