{
  "type": "Feature",
  "properties": {
    "addr:full":"Plaz Constitucion, 10 Mancha Real Ja\u00e9n 23100",
    "addr:housenumber":"10",
    "addr:postcode":"23100",
    "addr:street":"Constitucion",
    "iso:country":"ES",
    "sg:address":"Plaz Constitucion, 10",
    "sg:city":"Mancha Real",
    "sg:orig_category":"Promotores Constructores",
    "sg:phone":"+34 953 35 02 22",
    "sg:postcode":"23100",
    "sg:province":"Ja\u00e9n",
    "wof:name":"Delgado Abadia S.l.",
    "wof:placetype":"venue"
},
  "geometry": {"coordinates":[-3.6120998859,37.785785675],"type":"Point"}
}