{
  "type": "Feature",
  "properties": {
    "iso:country":"ES",
    "sg:address":"Calle de Isidro Madrid, 107",
    "sg:city":"Alcazares",
    "sg:orig_category":"Agencias Y Asesores De Publicidad",
    "sg:phone":"+34 968 58 26 34",
    "sg:postcode":"30710",
    "sg:province":"Murcia",
    "wof:name":"Comunidad De Propietarios Jardines De Lara",
    "wof:placetype":"venue"
},
  "geometry": {"coordinates":[-0.8542320132,37.7402877808],"type":"Point"}
}