{
  "type": "Feature",
  "properties": {
    "addr:full":"Calle de Diputacion Provincial, 13 Alfamen Zaragoza 50461",
    "addr:postcode":"50461",
    "addr:street":"Calle De Diputacion Provincial 13",
    "iso:country":"ES",
    "sg:address":"Calle de Diputacion Provincial, 13",
    "sg:city":"Alfamen",
    "sg:orig_category":"Supermercados Y Hipermercados",
    "sg:phone":"+34 976 62 60 38",
    "sg:postcode":"50461",
    "sg:province":"Zaragoza",
    "wof:name":"Hermanas Carrion S.c.",
    "wof:placetype":"venue"
},
  "geometry": {"coordinates":[-1.2448227406,41.4393882751],"type":"Point"}
}