{
  "type": "Feature",
  "properties": {
    "addr:full":"Av Saloria, 73 Seu D'urgell Lleida 25700",
    "addr:housenumber":"73",
    "addr:postcode":"25700",
    "addr:street":"Av Saloria",
    "iso:country":"ES",
    "sg:address":"Av Saloria, 73",
    "sg:city":"Seu D'urgell",
    "sg:orig_category":"Comercio, Reparaci\u00d3n De Bicicletas, De Motocicletas, De Accesorios",
    "sg:phone":"+34 973 36 03 98",
    "sg:postcode":"25700",
    "sg:province":"Lleida",
    "wof:name":"Sanchez Servat Javier",
    "wof:placetype":"venue"
},
  "geometry": {"coordinates":[0.6457189918,41.6027946472],"type":"Point"}
}