{
  "type": "Feature",
  "properties": {
    "iso:country":"ES",
    "sg:address":"Calle de Celleruelo, 14",
    "sg:city":"Pola De Siero",
    "sg:orig_category":"M\u00c9dicos: An\u00c1lisis Cl\u00cdnicos",
    "sg:phone":"+34 985 72 01 81",
    "sg:postcode":"33510",
    "sg:province":"Asturias",
    "wof:name":"Perez Iglesias Francisco",
    "wof:placetype":"venue"
},
  "geometry": {"coordinates":[-5.6623721123,43.3932418823],"type":"Point"}
}