{
  "type": "Feature",
  "properties": {
    "iso:country":"ES",
    "sg:address":"Cabo Prior, 3",
    "sg:city":"Urb. Golf",
    "sg:orig_category":"Arquitectos",
    "sg:phone":"+34 916 30 01 53",
    "sg:postcode":"28290",
    "sg:province":"Madrid",
    "wof:name":"Ezquerro Garcia-noblejas Jesus Maria",
    "wof:placetype":"venue"
},
  "geometry": {"coordinates":[-3.9311718941,40.5345878601],"type":"Point"}
}