{
  "type": "Feature",
  "properties": {
    "addr:full":"Pl Ajuntament, 15 S. Boi Llobregat Barcelona 08830",
    "addr:housenumber":"15",
    "addr:postcode":"08830",
    "addr:street":"Pl Ajuntament",
    "iso:country":"ES",
    "sg:address":"Pl Ajuntament, 15",
    "sg:city":"S. Boi Llobregat",
    "sg:orig_category":"Clubes Y Asociaciones Deportivas Y De Actividades Invernales Y De Monta\u00d1a",
    "sg:phone":"+34 936 30 42 61",
    "sg:postcode":"08830",
    "sg:province":"Barcelona",
    "wof:name":"Ge.a.f.e. S.l.",
    "wof:placetype":"venue"
},
  "geometry": {"coordinates":[2.0429780483,41.3471031189],"type":"Point"}
}