{
  "type": "Feature",
  "properties": {
    "addr:full":"Pase Castellana, 166 Madrid Madrid 28046",
    "addr:housenumber":"166",
    "addr:postcode":"28046",
    "addr:street":"Castellana",
    "iso:country":"ES",
    "sg:address":"Pase Castellana, 166",
    "sg:city":"Madrid",
    "sg:orig_category":"Inmobiliaria (agencias)",
    "sg:phone":"+34 915 63 60 80",
    "sg:postcode":"28046",
    "sg:province":"Madrid",
    "wof:name":"Neskisa S.a.",
    "wof:placetype":"venue"
},
  "geometry": {"coordinates":[-3.6892199516,40.4596138],"type":"Point"}
}