{
  "type": "Feature",
  "properties": {
    "addr:full":"Calle de Cervantes, 90 Villarta S. Juan Ciudad Real 13210",
    "addr:housenumber":"90",
    "addr:postcode":"13210",
    "addr:street":"Calle De Cervantes;S. Juan Ciudad Real",
    "iso:country":"ES",
    "sg:address":"Calle de Cervantes, 90",
    "sg:city":"Villarta S. Juan",
    "sg:orig_category":"Promotores Constructores",
    "sg:phone":"+34 926 64 06 51",
    "sg:postcode":"13210",
    "sg:province":"Ciudad Real",
    "wof:name":"Unijoyma S.l.",
    "wof:placetype":"venue"
},
  "geometry": {"coordinates":[-3.4200620651,39.2330665588],"type":"Point"}
}