{
  "type": "Feature",
  "properties": {
    "addr:full":"Carrer de Girona, 23 S. Boi Llobregat Barcelona 08830",
    "addr:housenumber":"23",
    "addr:postcode":"08830",
    "addr:street":"Carrer De Girona",
    "iso:country":"ES",
    "sg:address":"Carrer de Girona, 23",
    "sg:city":"S. Boi Llobregat",
    "sg:orig_category":"Fabricaci\u00d3n, Venta De Cuadros, Accesorios Para Enmarcar",
    "sg:phone":"+34 936 40 16 21",
    "sg:postcode":"08830",
    "sg:province":"Barcelona",
    "wof:name":"L'esmar S. A.",
    "wof:placetype":"venue"
},
  "geometry": {"coordinates":[2.0313301086,41.3507957458],"type":"Point"}
}