{
  "type": "Feature",
  "properties": {
    "addr:full":"Carrer de Cap Norfeu, 95 Roses Girona 17480",
    "addr:housenumber":"95",
    "addr:postcode":"17480",
    "addr:street":"Carrer De Cap Norfeu",
    "iso:country":"ES",
    "sg:address":"Carrer de Cap Norfeu, 95",
    "sg:city":"Roses",
    "sg:orig_category":"Promotores Constructores",
    "sg:phone":"+34 972 25 37 14",
    "sg:postcode":"17480",
    "sg:province":"Girona",
    "wof:name":"Montblanch Moral Arturo",
    "wof:placetype":"venue"
},
  "geometry": {"coordinates":[3.1841959953,42.2587394714],"type":"Point"}
}