{
  "type": "Feature",
  "properties": {
    "iso:country":"ES",
    "sg:address":"Nafarroa Plaza, 2",
    "sg:city":"Andoain",
    "sg:orig_category":"Peluqueros: De Se\u00d1oras",
    "sg:phone":"+34 943 59 22 94",
    "sg:postcode":"20140",
    "sg:province":"Guip\u00f9zcoa",
    "wof:name":"Bego\u00f1a Blanco Nu\u00f1ez",
    "wof:placetype":"venue"
},
  "geometry": {"coordinates":[-2.0208690166,43.2211761475],"type":"Point"}
}