{
  "type": "Feature",
  "properties": {
    "addr:full":"Carrer de Joaquim Valls, 58 Barcelona Barcelona 08016",
    "addr:housenumber":"58",
    "addr:postcode":"08016",
    "addr:street":"Carrer De Joaquim Valls",
    "iso:country":"ES",
    "sg:address":"Carrer de Joaquim Valls, 58",
    "sg:city":"Barcelona",
    "sg:orig_category":"Dietistas",
    "sg:phone":"+34 933 54 62 40",
    "sg:postcode":"08016",
    "sg:province":"Barcelona",
    "wof:name":"Pupinel S.l.",
    "wof:placetype":"venue"
},
  "geometry": {"coordinates":[2.1805560589,41.4436721802],"type":"Point"}
}