{
  "type": "Feature",
  "properties": {
    "iso:country":"ES",
    "sg:address":"Carrer de Antoni Cusido, 75",
    "sg:city":"Sabadell",
    "sg:orig_category":"Empresas De Carpinter\u00cda",
    "sg:phone":"+34 937 23 52 15",
    "sg:postcode":"08208",
    "sg:province":"Barcelona",
    "wof:name":"Jaimez Perea Fernando",
    "wof:placetype":"venue"
},
  "geometry": {"coordinates":[2.1070439816,41.5554695129],"type":"Point"}
}