{
  "type": "Feature",
  "properties": {
    "iso:country":"ES",
    "sg:address":"Crta. Hostalric, 15",
    "sg:city":"Riudarenes",
    "sg:orig_category":"Arenas, Guijarros Y Granulados",
    "sg:phone":"+34 972 85 33 27",
    "sg:postcode":"17421",
    "sg:province":"Girona",
    "wof:name":"Arids Costabella Freixas S.l.",
    "wof:placetype":"venue"
},
  "geometry": {"coordinates":[2.7037889957,41.7980880737],"type":"Point"}
}