{
  "type": "Feature",
  "properties": {
    "addr:full":"Avda Habana (de La), 12 Ourense Ourense 32003",
    "addr:housenumber":"12",
    "addr:postcode":"32003",
    "addr:street":"Avda Habana De La",
    "iso:country":"ES",
    "sg:address":"Avda Habana (de La), 12",
    "sg:city":"Ourense",
    "sg:orig_category":"Arquitectos",
    "sg:phone":"+34 988 21 71 29",
    "sg:postcode":"32003",
    "sg:province":"Ourense",
    "wof:name":"Varela Weber Patricia Gladys",
    "wof:placetype":"venue"
},
  "geometry": {"coordinates":[-7.8665437698,42.3426856995],"type":"Point"}
}