{
  "type": "Feature",
  "properties": {
    "addr:full":"A (p I Navisa), 36 Sevilla Sevilla 41006",
    "addr:housenumber":"36",
    "addr:postcode":"41006",
    "addr:street":"Navisa",
    "iso:country":"ES",
    "sg:address":"A (p I Navisa), 36",
    "sg:city":"Sevilla",
    "sg:orig_category":"Molduras, Junquillos, Listones Y Molduras Perforadas",
    "sg:phone":"+34 954 66 11 57",
    "sg:postcode":"41006",
    "sg:province":"Sevilla",
    "wof:name":"Barroso Perez Antonio",
    "wof:placetype":"venue"
},
  "geometry": {"coordinates":[-5.9559140205,37.3600234985],"type":"Point"}
}