{
  "type": "Feature",
  "properties": {
    "iso:country":"ES",
    "sg:address":"U, 8",
    "sg:city":"Alcover",
    "sg:orig_category":"Ferreter\u00cda (diversos)",
    "sg:phone":"+34 977 76 08 57",
    "sg:postcode":"43460",
    "sg:province":"Tarragona",
    "wof:name":"Guerreros Nu\u00f1ez Antonia",
    "wof:placetype":"venue"
},
  "geometry": {"coordinates":[1.1980240345,41.2833518982],"type":"Point"}
}