{
  "type": "Feature",
  "properties": {
    "iso:country":"ES",
    "sg:address":"Casa Camp, 48",
    "sg:city":"Vilassar Dalt",
    "sg:orig_category":"Material Y Suministros Para Horticultura, Arboricultura",
    "sg:phone":"+34 937 50 66 85",
    "sg:postcode":"08339",
    "sg:province":"Barcelona",
    "wof:name":"Sileva S.a.",
    "wof:placetype":"venue"
},
  "geometry": {"coordinates":[2.3616290092,41.5183601379],"type":"Point"}
}