{
  "type": "Feature",
  "properties": {
    "iso:country":"ES",
    "sg:address":"Calle de San Fernando, 32",
    "sg:city":"Santander",
    "sg:orig_category":"Molduras, Junquillos, Listones Y Molduras Perforadas",
    "sg:phone":"+34 942 23 01 76",
    "sg:postcode":"39010",
    "sg:province":"Cantabria",
    "wof:name":"Menendez Fernandez Leonardo",
    "wof:placetype":"venue"
},
  "geometry": {"coordinates":[-3.8212361336,43.4601287842],"type":"Point"}
}