{
  "type": "Feature",
  "properties": {
    "iso:country":"ES",
    "sg:address":"Calle de Hernan Cortes, 22",
    "sg:city":"Zaragoza",
    "sg:orig_category":"Agencias De Trabajo Temporal",
    "sg:phone":"+34 976 21 05 95",
    "sg:postcode":"50005",
    "sg:province":"Zaragoza",
    "wof:name":"Manpower Team Empresas De Trabajo Temporal",
    "wof:placetype":"venue"
},
  "geometry": {"coordinates":[-0.8903189898,41.6479797363],"type":"Point"}
}