{
  "type": "Feature",
  "properties": {
    "addr:full":"Calle de Santa Maria, 64 Torreperogil Ja\u00e9n 23320",
    "addr:housenumber":"64",
    "addr:postcode":"23320",
    "addr:street":"Calle De Santa Maria",
    "iso:country":"ES",
    "sg:address":"Calle de Santa Maria, 64",
    "sg:city":"Torreperogil",
    "sg:orig_category":"Partidos Pol\u00cdticos",
    "sg:phone":"+34 953 77 60 17",
    "sg:postcode":"23320",
    "sg:province":"Ja\u00e9n",
    "wof:name":"Partido Socialista Obrero Espa\u00f1ol",
    "wof:placetype":"venue"
},
  "geometry": {"coordinates":[-3.2848720551,38.0361557007],"type":"Point"}
}