{
  "type": "Feature",
  "properties": {
    "addr:full":"Plaz Mayor De La Hispanidad, 5 Medina Campo Valladolid 47400",
    "addr:housenumber":"5",
    "addr:postcode":"47400",
    "addr:street":"Plaz;Hispanidad",
    "iso:country":"ES",
    "sg:address":"Plaz Mayor De La Hispanidad, 5",
    "sg:city":"Medina Campo",
    "sg:orig_category":"Juegos Y Juguetes (al Por Menor)",
    "sg:phone":"+34 983 80 14 34",
    "sg:postcode":"47400",
    "sg:province":"Valladolid",
    "wof:name":"Tadeo Garcia Justino",
    "wof:placetype":"venue"
},
  "geometry": {"coordinates":[-4.913184166,41.3120155334],"type":"Point"}
}