{
  "type": "Feature",
  "properties": {
    "addr:full":"Pla\u00c7 Mercat De La Miraculosa, 2 Picassent Valencia 46220",
    "addr:housenumber":"2",
    "addr:postcode":"46220",
    "iso:country":"ES",
    "sg:address":"Pla\u00c7 Mercat De La Miraculosa, 2",
    "sg:city":"Picassent",
    "sg:orig_category":"Molduras, Junquillos, Listones Y Molduras Perforadas",
    "sg:phone":"+34 961 24 27 59",
    "sg:postcode":"46220",
    "sg:province":"Valencia",
    "wof:name":"Aguado Gomez Maria Pilar",
    "wof:placetype":"venue"
},
  "geometry": {"coordinates":[-0.4974358976,39.3506889343],"type":"Point"}
}