{
  "type": "Feature",
  "properties": {
    "addr:full":"Carrer de Escultor Modest Gene, 21 Reus Tarragona 43204",
    "addr:housenumber":"21",
    "addr:postcode":"43204",
    "addr:street":"Carrer De Escultor Modest Gene",
    "iso:country":"ES",
    "sg:address":"Carrer de Escultor Modest Gene, 21",
    "sg:city":"Reus",
    "sg:orig_category":"Electricidad: Instaladores",
    "sg:phone":"+34 977 75 39 63",
    "sg:postcode":"43204",
    "sg:province":"Tarragona",
    "wof:name":"Gomez Perez Rafael",
    "wof:placetype":"venue"
},
  "geometry": {"coordinates":[1.1145199537,41.1549491882],"type":"Point"}
}