{
  "type": "Feature",
  "properties": {
    "iso:country":"ES",
    "sg:address":"Calle de Blasco De Garay, 51",
    "sg:city":"Madrid",
    "sg:orig_category":"Empresarios",
    "sg:phone":"+34 915 43 29 94",
    "sg:postcode":"28015",
    "sg:province":"Madrid",
    "wof:name":"Ortega Sanchez Cinthya M\u00aa",
    "wof:placetype":"venue"
},
  "geometry": {"coordinates":[-3.7113876343,40.4359817505],"type":"Point"}
}