{
  "type": "Feature",
  "properties": {
    "iso:country":"ES",
    "sg:address":"Calle de Donoso Cortes, 23",
    "sg:city":"Madrid",
    "sg:orig_category":"Retoques De Vestidos",
    "sg:phone":"+34 914 46 35 54",
    "sg:postcode":"28015",
    "sg:province":"Madrid",
    "wof:name":"Arango Calderon Antonia",
    "wof:placetype":"venue"
},
  "geometry": {"coordinates":[-3.7081496716,40.4361495972],"type":"Point"}
}