{
  "type": "Feature",
  "properties": {
    "iso:country":"ES",
    "sg:address":"Antonio Amable, S/n",
    "sg:city":"La Ba\u00f1a",
    "sg:orig_category":"Pizzer\u00cdas",
    "sg:phone":"+34 987 66 40 23",
    "sg:postcode":"24746",
    "sg:province":"Le\u00f3n",
    "wof:name":"Comercial De Pizarras La Ba\u00f1esa S.l.",
    "wof:placetype":"venue"
},
  "geometry": {"coordinates":[-6.6235361099,42.2628669739],"type":"Point"}
}