{
  "type": "Feature",
  "properties": {
    "addr:full":"Calle de Collado Del Viento, 19 Madrid Madrid 28034",
    "addr:housenumber":"19",
    "addr:postcode":"madrid;28034",
    "addr:street":"Calle De Collado Del Viento",
    "iso:country":"ES",
    "sg:address":"Calle de Collado Del Viento, 19",
    "sg:city":"Madrid",
    "sg:orig_category":"Guarder\u00cdas",
    "sg:phone":"+34 917 34 04 55",
    "sg:postcode":"28034",
    "sg:province":"Madrid",
    "wof:name":"Jardin De Infancia Geminis S.l.",
    "wof:placetype":"venue"
},
  "geometry": {"coordinates":[-3.7048015594,40.4900283813],"type":"Point"}
}