{
  "type": "Feature",
  "properties": {
    "iso:country":"ES",
    "sg:address":"Ctra Vila, 26",
    "sg:city":"Viladecans",
    "sg:orig_category":"Agentes, Concesionarios Y Sucursales De Veh\u00cdculos",
    "sg:phone":"+34 936 59 13 96",
    "sg:postcode":"08840",
    "sg:province":"Barcelona",
    "wof:name":"Comercial Ros S. A.",
    "wof:placetype":"venue"
},
  "geometry": {"coordinates":[2.0223929882,41.3130874634],"type":"Point"}
}