{
  "type": "Feature",
  "properties": {
    "iso:country":"ES",
    "sg:address":"Altiplano(p Ind), S/n",
    "sg:city":"Bullas",
    "sg:orig_category":"Productores Recolectores, Venta Directa De Vinos",
    "sg:phone":"+34 968 65 21 60",
    "sg:postcode":"30180",
    "sg:province":"Murcia",
    "wof:name":"Cooperativa Vinicola Agraria San Isidro",
    "wof:placetype":"venue"
},
  "geometry": {"coordinates":[-1.653619051,38.0563240051],"type":"Point"}
}