{
  "type": "Feature",
  "properties": {
    "addr:full":"Barr Eitua, S/n Eitua Vizcaya 48240",
    "addr:housenumber":"s",
    "addr:postcode":"48240",
    "addr:street":"/ N",
    "iso:country":"ES",
    "sg:address":"Barr Eitua, S/n",
    "sg:city":"Eitua",
    "sg:orig_category":"Metales (labores, Pulido)",
    "sg:phone":"+34 946 82 75 10",
    "sg:postcode":"48240",
    "sg:province":"Vizcaya",
    "wof:name":"Esgesa S.a.",
    "wof:placetype":"venue"
},
  "geometry": {"coordinates":[-2.5734739304,43.1681594849],"type":"Point"}
}