{
  "type": "Feature",
  "properties": {
    "iso:country":"ES",
    "sg:address":"Calle de Padre Melchor Prieto, 2",
    "sg:city":"Burgos",
    "sg:orig_category":"Frutas, Legumbres Frescas Y Tempranas (al Por Menor)",
    "sg:phone":"+34 947 22 95 20",
    "sg:postcode":"09005",
    "sg:province":"Burgos",
    "wof:name":"Bustos De La Vega Felix De",
    "wof:placetype":"venue"
},
  "geometry": {"coordinates":[-3.6995329857,42.3465270996],"type":"Point"}
}