{
  "type": "Feature",
  "properties": {
    "iso:country":"ES",
    "sg:address":"Plaz Aragon, 12",
    "sg:city":"Zaragoza",
    "sg:orig_category":"Sociedades Y Organismos Burs\u00c1tiles",
    "sg:phone":"+34 976 48 25 00",
    "sg:postcode":"50004",
    "sg:province":"Zaragoza",
    "wof:name":"Fortis Bank S.a.",
    "wof:placetype":"venue"
},
  "geometry": {"coordinates":[-0.8847690225,41.6487312317],"type":"Point"}
}