{
  "type": "Feature",
  "properties": {
    "addr:full":"Avda Almeria, 20 Vilches Ja\u00e9n 23220",
    "addr:housenumber":"20",
    "addr:postcode":"23220",
    "addr:street":"Avda Almeria;Jae\u0301N",
    "iso:country":"ES",
    "sg:address":"Avda Almeria, 20",
    "sg:city":"Vilches",
    "sg:orig_category":"Mec\u00c1nico Del Autom\u00d3vil",
    "sg:phone":"+34 953 63 09 36",
    "sg:postcode":"23220",
    "sg:province":"Ja\u00e9n",
    "wof:name":"Molina Collado Manuel",
    "wof:placetype":"venue"
},
  "geometry": {"coordinates":[-3.5164940357,38.2152061462],"type":"Point"}
}