{
  "type": "Feature",
  "properties": {
    "iso:country":"ES",
    "sg:address":"Calle de Pedro Rubin De Celis (de), 5",
    "sg:city":"Pinto",
    "sg:orig_category":"Cl\u00cdnicas Dentales",
    "sg:phone":"+34 916 92 69 56",
    "sg:postcode":"28320",
    "sg:province":"Madrid",
    "wof:name":"Fluordent S.l.",
    "wof:placetype":"venue"
},
  "geometry": {"coordinates":[-3.6967010498,40.2434387207],"type":"Point"}
}