{
  "type": "Feature",
  "properties": {
    "addr:full":"Calle de Nu\u00d1ez De Balboa, 4 Santa Cruz De Tenerife Santa Cruz De Tenerife 38005",
    "addr:housenumber":"4",
    "addr:postcode":"38005",
    "addr:street":"Calle De Nun\u0303Ez De Balboa",
    "iso:country":"ES",
    "sg:address":"Calle de Nu\u00d1ez De Balboa, 4",
    "sg:city":"Santa Cruz De Tenerife",
    "sg:orig_category":"Peluquer\u00cdas, Peluquer\u00cda Mixta",
    "sg:phone":"+34 922 22 86 13",
    "sg:postcode":"38005",
    "sg:province":"Santa Cruz De Tenerife",
    "wof:name":"Perez Oran Maria Del Cristo",
    "wof:placetype":"venue"
},
  "geometry": {"coordinates":[-16.2594814301,28.4595966339],"type":"Point"}
}