{
  "type": "Feature",
  "properties": {
    "iso:country":"ES",
    "sg:address":"Calle de Martin Chamorro, 7",
    "sg:city":"Malpartida Plasencia",
    "sg:orig_category":"Cooperativas Agr\u00cdcolas",
    "sg:phone":"+34 927 40 44 24",
    "sg:postcode":"10680",
    "sg:province":"C\u00e1ceres",
    "wof:name":"Cooperativa Agricola San Isidro",
    "wof:placetype":"venue"
},
  "geometry": {"coordinates":[-6.0437541008,39.980758667],"type":"Point"}
}