{
  "type": "Feature",
  "properties": {
    "iso:country":"ES",
    "sg:address":"Calle de Alejandro Casona, 18",
    "sg:city":"Malaga",
    "sg:orig_category":"Metalurgia",
    "sg:phone":"+34 952 23 55 76",
    "sg:postcode":"29004",
    "sg:province":"M\u00e1laga",
    "wof:name":"Griferias Glamour S.l.",
    "wof:placetype":"venue"
},
  "geometry": {"coordinates":[-4.4778513908,36.6908187866],"type":"Point"}
}