{
  "type": "Feature",
  "properties": {
    "iso:country":"ES",
    "sg:address":"Av Pi I Margall, S/n",
    "sg:city":"Caldes Montbui",
    "sg:orig_category":"Supermercados Y Hipermercados",
    "sg:phone":"+34 938 65 43 04",
    "sg:postcode":"08140",
    "sg:province":"Barcelona",
    "sg:website":"www.capraboacasa.com",
    "wof:name":"Caprabo S.a.",
    "wof:placetype":"venue"
},
  "geometry": {"coordinates":[2.1639199257,41.6320381165],"type":"Point"}
}