{
  "type": "Feature",
  "properties": {
    "addr:full":"Calle de Sagasta, 3 Palmas De Gran Canaria Las Palmas 35008",
    "addr:housenumber":"3",
    "addr:postcode":"35008",
    "addr:street":"Calle De Sagasta",
    "iso:country":"ES",
    "sg:address":"Calle de Sagasta, 3",
    "sg:city":"Palmas De Gran Canaria",
    "sg:orig_category":"Importaci\u00d3n",
    "sg:phone":"+34 928 27 06 69",
    "sg:postcode":"35008",
    "sg:province":"Las Palmas",
    "wof:name":"Kumar Thadhani Naresh",
    "wof:placetype":"venue"
},
  "geometry": {"coordinates":[-15.4313392639,28.1434707642],"type":"Point"}
}