{
  "type": "Feature",
  "properties": {
    "addr:full":"Calle de Leon Felipe, 6 Utebo Zaragoza 50180",
    "addr:housenumber":"6",
    "addr:postcode":"50180",
    "addr:street":"Calle De Leon Felipe",
    "iso:country":"ES",
    "sg:address":"Calle de Leon Felipe, 6",
    "sg:city":"Utebo",
    "sg:orig_category":"Molduras, Junquillos, Listones Y Molduras Perforadas",
    "sg:phone":"+34 976 78 59 96",
    "sg:postcode":"50180",
    "sg:province":"Zaragoza",
    "wof:name":"Escucha Rapida S.l.",
    "wof:placetype":"venue"
},
  "geometry": {"coordinates":[-1.022225976,41.71534729],"type":"Point"}
}