{
  "type": "Feature",
  "properties": {
    "addr:full":"Carrer de Doctor Reig, 58 Viladecans Barcelona 08840",
    "addr:housenumber":"58",
    "addr:postcode":"08840",
    "addr:street":"Carrer De Doctor Reig",
    "iso:country":"ES",
    "sg:address":"Carrer de Doctor Reig, 58",
    "sg:city":"Viladecans",
    "sg:orig_category":"Confecci\u00d3n De Zapatos",
    "sg:phone":"+34 936 37 20 32",
    "sg:postcode":"08840",
    "sg:province":"Barcelona",
    "wof:name":"Calzados Mudarra S.l.",
    "wof:placetype":"venue"
},
  "geometry": {"coordinates":[2.0135691166,41.3192176819],"type":"Point"}
}