{
  "type": "Feature",
  "properties": {
    "addr:full":"Carrer de Torrent De Les Flors, 51 Barcelona Barcelona 08024",
    "addr:housenumber":"51",
    "addr:postcode":"08024",
    "addr:street":"Carrer De Torrent De Les Flors",
    "iso:country":"ES",
    "sg:address":"Carrer de Torrent De Les Flors, 51",
    "sg:city":"Barcelona",
    "sg:orig_category":"Contables",
    "sg:phone":"+34 932 10 84 79",
    "sg:postcode":"08024",
    "sg:province":"Barcelona",
    "wof:name":"Galera Pulido Oscar",
    "wof:placetype":"venue"
},
  "geometry": {"coordinates":[2.1601400375,41.4060516357],"type":"Point"}
}