{
  "type": "Feature",
  "properties": {
    "addr:full":"Av Cartagena, 19 El Altet Alicante 03195",
    "addr:housenumber":"19",
    "addr:postcode":"03195",
    "addr:street":"Av Cartagena;El Altet",
    "iso:country":"ES",
    "sg:address":"Av Cartagena, 19",
    "sg:city":"El Altet",
    "sg:orig_category":"Papeler\u00cdas, Librer\u00cdas",
    "sg:phone":"+34 965 68 91 93",
    "sg:postcode":"03195",
    "sg:province":"Alicante",
    "wof:name":"Baeza Bonmati Fernando",
    "wof:placetype":"venue"
},
  "geometry": {"coordinates":[-0.5393316746,38.2734375],"type":"Point"}
}