{
  "type": "Feature",
  "properties": {
    "iso:country":"ES",
    "sg:address":"Calle de Federico De Leon, 1",
    "sg:city":"Palmas De Gran Canaria",
    "sg:orig_category":"Arquitectos",
    "sg:phone":"+34 928 23 05 94",
    "sg:postcode":"35005",
    "sg:province":"Las Palmas",
    "wof:name":"Quintana Y Garcia Arquitectos S.l.",
    "wof:placetype":"venue"
},
  "geometry": {"coordinates":[-15.4292945862,28.1258583069],"type":"Point"}
}