{
  "type": "Feature",
  "properties": {
    "iso:country":"ES",
    "sg:address":"Calle de Sabina La, 30",
    "sg:city":"Ag\u00fcimes",
    "sg:orig_category":"Empresas De Carpinter\u00cda De Madera",
    "sg:phone":"+34 928 78 01 10",
    "sg:postcode":"35260",
    "sg:province":"Las Palmas",
    "wof:name":"Monroy Suarez Pedro",
    "wof:placetype":"venue"
},
  "geometry": {"coordinates":[-15.4461297989,27.9048900604],"type":"Point"}
}