{
  "type": "Feature",
  "properties": {
    "addr:full":"Calle de Valparaiso, 6 Salamanca Salamanca 37004",
    "addr:housenumber":"6",
    "addr:postcode":"37004",
    "addr:street":"Calle De Valparaiso",
    "iso:country":"ES",
    "sg:address":"Calle de Valparaiso, 6",
    "sg:city":"Salamanca",
    "sg:orig_category":"Guarder\u00cdas",
    "sg:phone":"+34 923 25 25 62",
    "sg:postcode":"37004",
    "sg:province":"Salamanca",
    "wof:name":"Sociedad Cooperativa El Tren Azul",
    "wof:placetype":"venue"
},
  "geometry": {"coordinates":[-5.6499481201,40.9724159241],"type":"Point"}
}