{
  "type": "Feature",
  "properties": {
    "iso:country":"ES",
    "sg:address":"Calle de Prim, 37",
    "sg:city":"Donostia-san Sebastian",
    "sg:orig_category":"Desinfecci\u00d3n, Desinsectaci\u00d3n, Desratizaci\u00d3n",
    "sg:phone":"+34 943 45 30 43",
    "sg:postcode":"20006",
    "sg:province":"Guip\u00f9zcoa",
    "wof:name":"Compan Sanchez Santiago",
    "wof:placetype":"venue"
},
  "geometry": {"coordinates":[-1.9798400402,43.3150634766],"type":"Point"}
}