{
  "type": "Feature",
  "properties": {
    "addr:full":"Calle de Duero (del), 2 Mejorada Campo Madrid 28840",
    "addr:housenumber":"2",
    "addr:postcode":"28840",
    "addr:street":"Calle De Duero Del",
    "iso:country":"ES",
    "sg:address":"Calle de Duero (del), 2",
    "sg:city":"Mejorada Campo",
    "sg:orig_category":"Ebanister\u00cda",
    "sg:phone":"+34 916 68 00 84",
    "sg:postcode":"28840",
    "sg:province":"Madrid",
    "wof:name":"Manuel Ruiz Quecuty Y Antonio Garcia-consuegra Martin-gil C.b.",
    "wof:placetype":"venue"
},
  "geometry": {"coordinates":[-3.4907135963,40.3864822388],"type":"Point"}
}