{
  "type": "Feature",
  "properties": {
    "addr:full":"Carr Mariners, 5 Port D'alcudia Islas Baleares 07410",
    "addr:housenumber":"5",
    "addr:postcode":"07410",
    "addr:street":"Carr Mariners",
    "iso:country":"ES",
    "sg:address":"Carr Mariners, 5",
    "sg:city":"Port D'alcudia",
    "sg:orig_category":"Ropa Para Se\u00d1oras (al Por Menor)",
    "sg:phone":"+34 971 54 93 35",
    "sg:postcode":"07410",
    "sg:province":"Islas Baleares",
    "wof:name":"Barcelo Barcelo Antonia",
    "wof:placetype":"venue"
},
  "geometry": {"coordinates":[3.1340548992,39.8419685364],"type":"Point"}
}