{
  "type": "Feature",
  "properties": {
    "addr:full":"Cervantes, 4 Lucena C\u00f3rdoba 14900",
    "addr:housenumber":"4",
    "addr:postcode":"14900",
    "addr:street":"Cervantes",
    "iso:country":"ES",
    "sg:address":"Cervantes, 4",
    "sg:city":"Lucena",
    "sg:orig_category":"Psic\u00d3logos",
    "sg:phone":"+34 957 50 31 89",
    "sg:postcode":"14900",
    "sg:province":"C\u00f3rdoba",
    "wof:name":"Flores Martinez Mario",
    "wof:placetype":"venue"
},
  "geometry": {"coordinates":[-4.4847187996,37.4150352478],"type":"Point"}
}