{
  "type": "Feature",
  "properties": {
    "addr:full":"Cra. Vall D'aran, Km. 0080,9 Alguaire Lleida 25125",
    "addr:postcode":"25125",
    "addr:street":"D'Aran Km. 0080,9",
    "iso:country":"ES",
    "sg:address":"Cra. Vall D'aran, Km. 0080,9",
    "sg:city":"Alguaire",
    "sg:orig_category":"Aguas (distribuci\u00d3n, Servicios)",
    "sg:phone":"+34 973 29 09 50",
    "sg:postcode":"25125",
    "sg:province":"Lleida",
    "wof:name":"Compa\u00f1ia Hidroelectrica De Los Regantes Del Canal De Aragon Y Catalu\u00f1a Central Numero 1",
    "wof:placetype":"venue"
},
  "geometry": {"coordinates":[0.5604199767,41.7382888794],"type":"Point"}
}