{
  "type": "Feature",
  "properties": {
    "addr:full":"Calle de Doctor Jose Zaldua, 4 Portugalete Vizcaya 48920",
    "addr:housenumber":"4",
    "addr:postcode":"48920",
    "addr:street":"Calle De Doctor Jose Zaldua",
    "iso:country":"ES",
    "sg:address":"Calle de Doctor Jose Zaldua, 4",
    "sg:city":"Portugalete",
    "sg:orig_category":"Guarder\u00cdas",
    "sg:phone":"+34 944 61 87 91",
    "sg:postcode":"48920",
    "sg:province":"Vizcaya",
    "wof:name":"Maria Pilar Blanco Redondo(guarderia Teletubbies)",
    "wof:placetype":"venue"
},
  "geometry": {"coordinates":[-3.0276579857,43.3185272217],"type":"Point"}
}