{
  "type": "Feature",
  "properties": {
    "addr:full":"Plaz Espolon, 1 Le\u00f3n Le\u00f3n 24007",
    "addr:housenumber":"1",
    "addr:postcode":"24007",
    "addr:street":"Plaz Espolon;Leo\u0301N",
    "iso:country":"ES",
    "sg:address":"Plaz Espolon, 1",
    "sg:city":"Le\u00f3n",
    "sg:orig_category":"Electrodom\u00c9sticos (al Por Menor)",
    "sg:phone":"+34 987 22 45 77",
    "sg:postcode":"24007",
    "sg:province":"Le\u00f3n",
    "wof:name":"Casta\u00f1eda Bafino Fernando",
    "wof:placetype":"venue"
},
  "geometry": {"coordinates":[-5.5701141357,42.6027526855],"type":"Point"}
}