{
  "type": "Feature",
  "properties": {
    "addr:full":"Carrer de Esport, 9 S. Andreu Barca Barcelona 08740",
    "addr:housenumber":"9",
    "addr:postcode":"08740",
    "addr:street":"Carrer De Esport;S. Andreu;Barcelona",
    "iso:country":"ES",
    "sg:address":"Carrer de Esport, 9",
    "sg:city":"S. Andreu Barca",
    "sg:orig_category":"Agencias Y Agentes Comerciales, Representantes",
    "sg:phone":"+34 936 53 41 35",
    "sg:postcode":"08740",
    "sg:province":"Barcelona",
    "wof:name":"Flores Diaz Rita",
    "wof:placetype":"venue"
},
  "geometry": {"coordinates":[1.9700759649,41.4490013123],"type":"Point"}
}