{
  "type": "Feature",
  "properties": {
    "iso:country":"ES",
    "sg:address":"Carrer de Valencia, 65",
    "sg:city":"Mataro",
    "sg:orig_category":"M\u00c9dicos: Estomatolog\u00cda",
    "sg:phone":"+34 937 99 08 48",
    "sg:postcode":"08303",
    "sg:province":"Barcelona",
    "wof:name":"Helbig Cerezo Jorge",
    "wof:placetype":"venue"
},
  "geometry": {"coordinates":[2.4232299328,41.5388031006],"type":"Point"}
}