{
  "type": "Feature",
  "properties": {
    "addr:full":"Avda Fuenlabrada (de), 40 Humanes De Madrid Madrid 28970",
    "addr:housenumber":"40",
    "addr:postcode":"28970",
    "addr:street":"Avda Fuenlabrada De",
    "iso:country":"ES",
    "sg:address":"Avda Fuenlabrada (de), 40",
    "sg:city":"Humanes De Madrid",
    "sg:orig_category":"Venta, Instalaci\u00d3n De Cocinas",
    "sg:phone":"+34 916 04 84 17",
    "sg:postcode":"28970",
    "sg:province":"Madrid",
    "wof:name":"Lon Gris S.l.",
    "wof:placetype":"venue"
},
  "geometry": {"coordinates":[-3.8164229393,40.2636260986],"type":"Point"}
}