{
  "type": "Feature",
  "properties": {
    "iso:country":"ES",
    "sg:address":"Calle de La Florida, 41",
    "sg:city":"Vitoria-gasteiz",
    "sg:orig_category":"Peluquer\u00cdas, Peluquer\u00cda Mixta",
    "sg:phone":"+34 945 27 66 76",
    "sg:postcode":"01005",
    "sg:province":"\u00c1lava",
    "wof:name":"Fresno Santamaria Maria Teresa",
    "wof:placetype":"venue"
},
  "geometry": {"coordinates":[-2.6721200943,42.8431587219],"type":"Point"}
}