{
  "type": "Feature",
  "properties": {
    "addr:full":"Calle de Bueso Pineda, 45 Madrid Madrid 28043",
    "addr:housenumber":"45",
    "addr:postcode":"madrid;28043",
    "addr:street":"Calle De Bueso Pineda",
    "iso:country":"ES",
    "sg:address":"Calle de Bueso Pineda, 45",
    "sg:city":"Madrid",
    "sg:orig_category":"Ingenier\u00cda, Centros De Estudios (diversos)",
    "sg:phone":"+34 917 59 38 92",
    "sg:postcode":"28043",
    "sg:province":"Madrid",
    "wof:name":"Rullo Llombert Esperanza",
    "wof:placetype":"venue"
},
  "geometry": {"coordinates":[-3.6536035538,40.4550247192],"type":"Point"}
}