{
  "type": "Feature",
  "properties": {
    "iso:country":"ES",
    "sg:address":"Carrer de Bolivia, 340",
    "sg:city":"Barcelona",
    "sg:orig_category":"Muebles Y Accesorios Para Cocinas Y Cuartos De Ba\u00d1o (al Por Menor)",
    "sg:phone":"+34 933 08 53 68",
    "sg:postcode":"08019",
    "sg:province":"Barcelona",
    "wof:name":"Mj. Zayco S.l.",
    "wof:placetype":"venue"
},
  "geometry": {"coordinates":[2.2088060379,41.4160995483],"type":"Point"}
}