{
  "type": "Feature",
  "properties": {
    "addr:full":"Avda Madrid (de), 64 Jaen Ja\u00e9n 23009",
    "addr:housenumber":"64;jae\u0301n",
    "addr:postcode":"23009",
    "addr:street":"Avda Madrid De",
    "iso:country":"ES",
    "sg:address":"Avda Madrid (de), 64",
    "sg:city":"Jaen",
    "sg:classifiers":[
        {
            "category":"Autos & Motor Vehicles",
            "subcategory":"Automobile Sales",
            "type":"Retail Goods"
        }
    ],
    "sg:phone":"+34 953 25 65 53",
    "sg:postcode":"23009",
    "sg:province":"Ja\u00e9n",
    "wof:name":"Europa Academia De Conductores S.l.",
    "wof:placetype":"venue"
},
  "geometry": {"coordinates":[-3.7848188877,37.7799606323],"type":"Point"}
}