{
  "type": "Feature",
  "properties": {
    "iso:country":"ES",
    "sg:address":"Extramuros, S/n",
    "sg:city":"Gilena",
    "sg:orig_category":"Producci\u00d3n, Comercio De Cereales",
    "sg:phone":"+34 955 82 60 00",
    "sg:postcode":"41565",
    "sg:province":"Sevilla",
    "wof:name":"Agricola De Gilena S.a.",
    "wof:placetype":"venue"
},
  "geometry": {"coordinates":[-4.9454803467,37.2262954712],"type":"Point"}
}