{
  "type": "Feature",
  "properties": {
    "iso:country":"ES",
    "sg:address":"Rua Choupana (da), 1",
    "sg:city":"Santiago De Compostela",
    "sg:orig_category":"Molduras, Junquillos, Listones Y Molduras Perforadas",
    "sg:phone":"+34 981 52 12 64",
    "sg:postcode":"15706",
    "sg:province":"La Coru\u00f1a",
    "wof:name":"Millan Suarez Juan",
    "wof:placetype":"venue"
},
  "geometry": {"coordinates":[-8.5620708466,42.8678665161],"type":"Point"}
}