{
  "type": "Feature",
  "properties": {
    "addr:full":"Carrer de Ausias Marc (d'), 16 Vila-seca Tarragona 43480",
    "addr:housenumber":"16",
    "addr:postcode":"43480",
    "addr:street":"Carrer De Ausias Marc D '",
    "iso:country":"ES",
    "sg:address":"Carrer de Ausias Marc (d'), 16",
    "sg:city":"Vila-seca",
    "sg:orig_category":"Inmobiliaria (agencias)",
    "sg:phone":"+34 977 39 17 73",
    "sg:postcode":"43480",
    "sg:province":"Tarragona",
    "wof:name":"Gesmar Proicasa S.a.",
    "wof:placetype":"venue"
},
  "geometry": {"coordinates":[1.1506450176,41.1065940857],"type":"Point"}
}