{
  "type": "Feature",
  "properties": {
    "addr:full":"Av Francesc Macia, 132 Santa Coloma De Gramenet Barcelona 08924",
    "addr:housenumber":"132",
    "addr:postcode":"08924",
    "addr:street":"Av Francesc Macia",
    "iso:country":"ES",
    "sg:address":"Av Francesc Macia, 132",
    "sg:city":"Santa Coloma De Gramenet",
    "sg:orig_category":"Cajas De Ahorro",
    "sg:phone":"+34 933 91 60 01",
    "sg:postcode":"08924",
    "sg:province":"Barcelona",
    "sg:website":"www.caixasabadell.es",
    "wof:name":"Caixa D'estalvis Sabadell",
    "wof:placetype":"venue"
},
  "geometry": {"coordinates":[2.2023670673,41.4570350647],"type":"Point"}
}