{
  "type": "Feature",
  "properties": {
    "iso:country":"ES",
    "sg:address":"Avda Lugo (de), 116",
    "sg:city":"Monterroso",
    "sg:orig_category":"Sociedades, Compa\u00d1\u00cdas Aseguradoras",
    "sg:phone":"+34 982 37 75 60",
    "sg:postcode":"27560",
    "sg:province":"Lugo",
    "wof:name":"Mapfre Servicios De Informatica",
    "wof:placetype":"venue"
},
  "geometry": {"coordinates":[-7.8332290649,42.7924995422],"type":"Point"}
}