{
  "type": "Feature",
  "properties": {
    "iso:country":"ES",
    "sg:address":"Ctra. N. 340, Km. 0194,0",
    "sg:city":"Gallardos",
    "sg:orig_category":"Confecci\u00d3n (fabricaci\u00d3n, Al Por Mayor)",
    "sg:phone":"+34 950 46 90 76",
    "sg:postcode":"04280",
    "sg:province":"Almer\u00eda",
    "wof:name":"Cofecciones Adhoc S.l.",
    "wof:placetype":"venue"
},
  "geometry": {"coordinates":[-1.9397890568,37.1677284241],"type":"Point"}
}