{
  "type": "Feature",
  "properties": {
    "iso:country":"ES",
    "sg:address":"Rua Castelao, 21",
    "sg:city":"Vilagarcia",
    "sg:orig_category":"Animales (al Por Menor)",
    "sg:phone":"+34 986 51 19 58",
    "sg:postcode":"36600",
    "sg:province":"Pontevedra",
    "wof:name":"Lorenzo Fernandez Manuel",
    "wof:placetype":"venue"
},
  "geometry": {"coordinates":[-8.7683200836,42.5934181213],"type":"Point"}
}