{
  "type": "Feature",
  "properties": {
    "iso:country":"ES",
    "sg:address":"Calle de Garcia Lomas, 15",
    "sg:city":"Valladolid",
    "sg:orig_category":"Procuradores",
    "sg:phone":"+34 983 22 53 45",
    "sg:postcode":"47007",
    "sg:province":"Valladolid",
    "wof:name":"Rodriguez Alvarez Gonzalo",
    "wof:placetype":"venue"
},
  "geometry": {"coordinates":[-4.7275280952,41.6427993774],"type":"Point"}
}