{
  "type": "Feature",
  "properties": {
    "iso:country":"ES",
    "sg:address":"Carrer de Verge De La Merce, 46",
    "sg:city":"Esplugues Llobregat",
    "sg:orig_category":"Reposter\u00cdas",
    "sg:phone":"+34 933 71 75 80",
    "sg:postcode":"08950",
    "sg:province":"Barcelona",
    "wof:name":"Rodriguez Rodriguez Jesus",
    "wof:placetype":"venue"
},
  "geometry": {"coordinates":[2.0990259647,41.3729057312],"type":"Point"}
}