{
  "type": "Feature",
  "properties": {
    "iso:country":"ES",
    "sg:address":"Carrer de Ausias Marc, 25",
    "sg:city":"Barcelona",
    "sg:orig_category":"Psic\u00d3logos",
    "sg:phone":"+34 933 01 34 40",
    "sg:postcode":"08010",
    "sg:province":"Barcelona",
    "sg:website":"www.centroabb.com",
    "wof:name":"Centre De Prevencio I Tractament Anorexia Bulimia",
    "wof:placetype":"venue"
},
  "geometry": {"coordinates":[2.1749849319,41.3910560608],"type":"Point"}
}