{
  "type": "Feature",
  "properties": {
    "addr:full":"Calle de Galileo, 21 Madrid Madrid 28015",
    "addr:housenumber":"21",
    "addr:postcode":"madrid;28015",
    "addr:street":"Calle De Galileo",
    "iso:country":"ES",
    "sg:address":"Calle de Galileo, 21",
    "sg:city":"Madrid",
    "sg:orig_category":"Institutos De Belleza",
    "sg:phone":"+34 915 93 06 70",
    "sg:postcode":"28015",
    "sg:province":"Madrid",
    "wof:name":"Mu\u00f1oz Cebrian Angustias",
    "wof:placetype":"venue"
},
  "geometry": {"coordinates":[-3.7105810642,40.4321250916],"type":"Point"}
}