{
  "type": "Feature",
  "properties": {
    "iso:country":"ES",
    "sg:address":"Calle de Jacinto Benavente, 9",
    "sg:city":"Marbella",
    "sg:orig_category":"Electrodom\u00c9sticos (al Por Menor)",
    "sg:phone":"+34 952 77 86 90",
    "sg:postcode":"29600",
    "sg:province":"M\u00e1laga",
    "sg:website":"www.bazarsanjuan.es",
    "wof:name":"Bazar San Juan S.a.",
    "wof:placetype":"venue"
},
  "geometry": {"coordinates":[-4.8873229027,36.5108757019],"type":"Point"}
}