{
  "type": "Feature",
  "properties": {
    "iso:country":"ES",
    "sg:address":"Avda. Pamplona, 1",
    "sg:city":"Iru\u00f1a",
    "sg:orig_category":"Inmobiliaria (agencias)",
    "sg:phone":"+34 948 18 57 82",
    "sg:postcode":"31009",
    "sg:province":"Navarra",
    "wof:name":"Gracia Varona Servicios Inmobiliarios S.l.",
    "wof:placetype":"venue"
},
  "geometry": {"coordinates":[-1.6735546589,42.8049850464],"type":"Point"}
}