{
  "type": "Feature",
  "properties": {
    "iso:country":"ES",
    "sg:address":"Praj Zuritas, Km. 0003,0",
    "sg:city":"Asomada",
    "sg:orig_category":"Organizaciones Profesionales",
    "sg:phone":"+34 928 53 16 19",
    "sg:postcode":"35600",
    "sg:province":"Las Palmas",
    "wof:name":"Garcia Alamo Juan",
    "wof:placetype":"venue"
},
  "geometry": {"coordinates":[-13.8644685745,28.5023498535],"type":"Point"}
}