{
  "type": "Feature",
  "properties": {
    "iso:country":"ES",
    "sg:address":"Calle de Senda De Les Deu, 31",
    "sg:city":"Rafelbunyol",
    "sg:orig_category":"Chapister\u00cda",
    "sg:phone":"+34 961 41 30 28",
    "sg:postcode":"46138",
    "sg:province":"Valencia",
    "wof:name":"Tallers Somtres C.b",
    "wof:placetype":"venue"
},
  "geometry": {"coordinates":[-0.3255000114,39.5829162598],"type":"Point"}
}