{
  "type": "Feature",
  "properties": {
    "addr:full":"Calle de Hermandad, 20 Madrid Madrid 28025",
    "addr:housenumber":"20",
    "addr:postcode":"madrid;28025",
    "addr:street":"Calle De Hermandad",
    "iso:country":"ES",
    "sg:address":"Calle de Hermandad, 20",
    "sg:city":"Madrid",
    "sg:orig_category":"Peluqueros: De Se\u00d1oras",
    "sg:phone":"+34 914 65 70 15",
    "sg:postcode":"28025",
    "sg:province":"Madrid",
    "wof:name":"Ruiz Diaz Juana",
    "wof:placetype":"venue"
},
  "geometry": {"coordinates":[-3.728167057,40.3827323914],"type":"Point"}
}