{
  "type": "Feature",
  "properties": {
    "iso:country":"ES",
    "sg:address":"Calle de Padre Aller, 24",
    "sg:city":"Oviedo",
    "sg:orig_category":"Asesor\u00cda, Estudio Y Control Medioambiental",
    "sg:phone":"+34 985 23 59 14",
    "sg:postcode":"33012",
    "sg:province":"Asturias",
    "wof:name":"Biosfera Consultoria Medioamb S.l.",
    "wof:placetype":"venue"
},
  "geometry": {"coordinates":[-5.8634290695,43.3689193726],"type":"Point"}
}