{
  "type": "Feature",
  "properties": {
    "addr:full":"Calle de San Benito, 30 Campillos M\u00e1laga 29320",
    "addr:housenumber":"30",
    "addr:postcode":"29320",
    "addr:street":"Calle De San Benito",
    "iso:country":"ES",
    "sg:address":"Calle de San Benito, 30",
    "sg:city":"Campillos",
    "sg:orig_category":"Ingeniero",
    "sg:phone":"+34 952 72 23 28",
    "sg:postcode":"29320",
    "sg:province":"M\u00e1laga",
    "wof:name":"Servicios Tecnicos Agropecuarios S.civil",
    "wof:placetype":"venue"
},
  "geometry": {"coordinates":[-4.8624129295,37.0495414734],"type":"Point"}
}