{
  "type": "Feature",
  "properties": {
    "addr:full":"Carrer de Jaume Ii, 14 Novelda Alicante 03660",
    "addr:housenumber":"14",
    "addr:postcode":"03660",
    "addr:street":"Carrer De Jaume Ii",
    "iso:country":"ES",
    "sg:address":"Carrer de Jaume Ii, 14",
    "sg:city":"Novelda",
    "sg:orig_category":"\u00d3ptica: Instrumentos (fabricaci\u00d3n)",
    "sg:phone":"+34 965 60 67 29",
    "sg:postcode":"03660",
    "sg:province":"Alicante",
    "wof:name":"Optica San Mateo Vi S.l.",
    "wof:placetype":"venue"
},
  "geometry": {"coordinates":[-0.7671430111,38.3843574524],"type":"Point"}
}