{
  "type": "Feature",
  "properties": {
    "addr:full":"Carrer de Riera Gran (de La), 10 Vilafranca Penedes Barcelona 08720",
    "addr:housenumber":"10",
    "addr:postcode":"08720",
    "addr:street":"Carrer De Riera Gran De La;Penedes Barcelona",
    "iso:country":"ES",
    "sg:address":"Carrer de Riera Gran (de La), 10",
    "sg:city":"Vilafranca Penedes",
    "sg:orig_category":"Confecci\u00d3n (fabricaci\u00d3n, Al Por Mayor)",
    "sg:phone":"+34 938 90 27 96",
    "sg:postcode":"08720",
    "sg:province":"Barcelona",
    "wof:name":"Miro Cornella Arcadio",
    "wof:placetype":"venue"
},
  "geometry": {"coordinates":[1.6805310249,41.3349189758],"type":"Point"}
}