{
  "type": "Feature",
  "properties": {
    "iso:country":"ES",
    "sg:address":"Avda Castilla La Mancha, 22",
    "sg:city":"Illescas",
    "sg:orig_category":"Veh\u00cdculos De Ocasi\u00d3n",
    "sg:phone":"+34 925 53 23 22",
    "sg:postcode":"45200",
    "sg:province":"Toledo",
    "wof:name":"Automoviles Las Naciones S.l.",
    "wof:placetype":"venue"
},
  "geometry": {"coordinates":[-3.8468925953,40.1224250793],"type":"Point"}
}