{
  "type": "Feature",
  "properties": {
    "iso:country":"ES",
    "sg:address":"Avda San Esteban, 7",
    "sg:city":"Etxebarri",
    "sg:orig_category":"Quincaller\u00cda (al Por Menor)",
    "sg:phone":"+34 944 40 11 54",
    "sg:postcode":"48450",
    "sg:province":"Vizcaya",
    "wof:name":"Ferurti Hnos. S.l.",
    "wof:placetype":"venue"
},
  "geometry": {"coordinates":[-2.8906469345,43.2461738586],"type":"Point"}
}