{
  "type": "Feature",
  "properties": {
    "iso:country":"ES",
    "sg:address":"Calle de Isabel La Catolica, 21",
    "sg:city":"Alacant",
    "sg:orig_category":"Inform\u00c1tica, Ofim\u00c1tica (estudios, Asesor\u00cda, Ingenier\u00cda, Formaci\u00d3n)",
    "sg:phone":"+34 965 12 50 26",
    "sg:postcode":"03007",
    "sg:province":"Alicante",
    "wof:name":"Sistac Ils S.l.",
    "wof:placetype":"venue"
},
  "geometry": {"coordinates":[-0.4950720072,38.3412322998],"type":"Point"}
}