{
  "type": "Feature",
  "properties": {
    "iso:country":"ES",
    "sg:address":"Carr Santiago Rusi\u00d1ol, 15",
    "sg:city":"Blanes",
    "sg:orig_category":"Molduras, Junquillos, Listones Y Molduras Perforadas",
    "sg:phone":"+34 972 33 54 41",
    "sg:postcode":"17300",
    "sg:province":"Girona",
    "wof:name":"Hermanos Guijarro S.c.p.",
    "wof:placetype":"venue"
},
  "geometry": {"coordinates":[2.7813570499,41.6815605164],"type":"Point"}
}