{
  "type": "Feature",
  "properties": {
    "addr:full":"Calle de Via Complutense, 42 Alcala Henares Madrid 28805",
    "addr:housenumber":"42",
    "addr:postcode":"28805",
    "addr:street":"Calle De Via Complutense",
    "iso:country":"ES",
    "sg:address":"Calle de Via Complutense, 42",
    "sg:city":"Alcala Henares",
    "sg:orig_category":"Cajas De Ahorro",
    "sg:phone":"+34 918 77 03 22",
    "sg:postcode":"28805",
    "sg:province":"Madrid",
    "sg:website":"www.cajasegovia.es",
    "wof:name":"Caja De Ahorros Y Monte De Piedad De Segovia",
    "wof:placetype":"venue"
},
  "geometry": {"coordinates":[-3.360450983,40.4864273071],"type":"Point"}
}