{
  "type": "Feature",
  "properties": {
    "addr:full":"Calle de Hamlet, 11 Malaga M\u00e1laga 29006",
    "addr:housenumber":"11",
    "addr:postcode":"29006",
    "addr:street":"Calle De Hamlet;Ma\u0301Laga",
    "iso:country":"ES",
    "sg:address":"Calle de Hamlet, 11",
    "sg:city":"Malaga",
    "sg:orig_category":"Cajas De Ahorro",
    "sg:phone":"+34 952 31 19 47",
    "sg:postcode":"29006",
    "sg:province":"M\u00e1laga",
    "wof:name":"Unicaja",
    "wof:placetype":"venue"
},
  "geometry": {"coordinates":[-4.4637341499,36.710144043],"type":"Point"}
}