{
  "type": "Feature",
  "properties": {
    "iso:country":"ES",
    "sg:address":"Avda Cabo De Gata, 114",
    "sg:city":"Almeria",
    "sg:orig_category":"Molduras, Junquillos, Listones Y Molduras Perforadas",
    "sg:phone":"+34 950 24 19 08",
    "sg:postcode":"04007",
    "sg:province":"Almer\u00eda",
    "wof:name":"Antonia Campos Perez E Hijos S. A.",
    "wof:placetype":"venue"
},
  "geometry": {"coordinates":[-2.4522438049,36.8297691345],"type":"Point"}
}