{
  "type": "Feature",
  "properties": {
    "iso:country":"ES",
    "sg:address":"Carrer de Aribau, 21",
    "sg:city":"Barcelona",
    "sg:orig_category":"Asesor\u00cda Sobre Comunicaci\u00d3n De Empresas",
    "sg:phone":"+34 934 51 21 24",
    "sg:postcode":"08011",
    "sg:province":"Barcelona",
    "wof:name":"Global Pm Consulting",
    "wof:placetype":"venue"
},
  "geometry": {"coordinates":[2.1612849236,41.3867645264],"type":"Point"}
}