{
  "type": "Feature",
  "properties": {
    "addr:full":"Pol Ind La Rambla, S/n Almassora Castell\u00f3n 12550",
    "addr:postcode":"12550",
    "addr:street":"La Rambla S / N Almassora Castello\u0301N",
    "iso:country":"ES",
    "sg:address":"Pol Ind La Rambla, S/n",
    "sg:city":"Almassora",
    "sg:orig_category":"Accesorios De Gr\u00daas Y Estibados",
    "sg:phone":"+34 964 56 50 63",
    "sg:postcode":"12550",
    "sg:province":"Castell\u00f3n",
    "wof:name":"Noucar S.l.",
    "wof:placetype":"venue"
},
  "geometry": {"coordinates":[-0.0631700009,39.9439582825],"type":"Point"}
}