{
  "type": "Feature",
  "properties": {
    "iso:country":"ES",
    "sg:address":"Carretera Del Muelle, S/n",
    "sg:city":"Espasante",
    "sg:orig_category":"Telas Y Sedas (al Por Menor)",
    "sg:phone":"+34 981 40 82 27",
    "sg:postcode":"15339",
    "sg:province":"La Coru\u00f1a",
    "wof:name":"Martinez Galdo Vicente",
    "wof:placetype":"venue"
},
  "geometry": {"coordinates":[-8.0518388748,43.6615142822],"type":"Point"}
}