{
  "type": "Feature",
  "properties": {
    "iso:country":"ES",
    "sg:address":"Calle de General Alvarez De Castro, 27",
    "sg:city":"Madrid",
    "sg:orig_category":"M\u00c9dicos: Ginecolog\u00cda Y Obstetricia",
    "sg:phone":"+34 914 45 54 67",
    "sg:postcode":"28010",
    "sg:province":"Madrid",
    "wof:name":"Rejas Gutierrez Miguel",
    "wof:placetype":"venue"
},
  "geometry": {"coordinates":[-3.7026860714,40.4364089966],"type":"Point"}
}