{
  "type": "Feature",
  "properties": {
    "addr:full":"Pol. Palancares, 12 Cuenca Cuenca 16003",
    "addr:housenumber":"12",
    "addr:postcode":"16003",
    "addr:street":"Palancares",
    "iso:country":"ES",
    "sg:address":"Pol. Palancares, 12",
    "sg:city":"Cuenca",
    "sg:orig_category":"Transportes Por V\u00cdas Navegables",
    "sg:phone":"+34 969 22 33 26",
    "sg:postcode":"16003",
    "sg:province":"Cuenca",
    "wof:name":"Transportes Ara Recuenco S.l.",
    "wof:placetype":"venue"
},
  "geometry": {"coordinates":[-2.1360049248,40.0600090027],"type":"Point"}
}