{
  "type": "Feature",
  "properties": {
    "addr:full":"L. Bravo, 34 Villalonquejar Burgos 09001",
    "addr:housenumber":"34",
    "addr:postcode":"09001",
    "addr:street":"L. Bravo",
    "iso:country":"ES",
    "sg:address":"L. Bravo, 34",
    "sg:city":"Villalonquejar",
    "sg:orig_category":"Metalurgia",
    "sg:phone":"+34 947 29 83 49",
    "sg:postcode":"09001",
    "sg:province":"Burgos",
    "wof:name":"Talleres Bram S.l.",
    "wof:placetype":"venue"
},
  "geometry": {"coordinates":[-3.733716011,42.3701553345],"type":"Point"}
}