{
  "type": "Feature",
  "properties": {
    "iso:country":"ES",
    "sg:address":"Carrer de Proven\u00c7a, 370",
    "sg:city":"Barcelona",
    "sg:orig_category":"Industria Qu\u00cdmica",
    "sg:phone":"+34 934 59 36 72",
    "sg:postcode":"08037",
    "sg:province":"Barcelona",
    "wof:name":"Aymar Terricabras Maria Carmen",
    "wof:placetype":"venue"
},
  "geometry": {"coordinates":[2.1688568592,41.4002838135],"type":"Point"}
}