{
  "type": "Feature",
  "properties": {
    "addr:full":"Calle de Espronceda, S/n Alhama Murcia Murcia 30840",
    "addr:housenumber":"s / n",
    "addr:postcode":"murcia;30840",
    "addr:street":"Calle De Espronceda",
    "iso:country":"ES",
    "sg:address":"Calle de Espronceda, S/n",
    "sg:city":"Alhama Murcia",
    "sg:orig_category":"Restaurantes",
    "sg:phone":"+34 968 63 07 53",
    "sg:postcode":"30840",
    "sg:province":"Murcia",
    "wof:name":"Garcia Pedrero Agustin",
    "wof:placetype":"venue"
},
  "geometry": {"coordinates":[-1.4315493107,37.8508415222],"type":"Point"}
}