{
  "type": "Feature",
  "properties": {
    "iso:country":"ES",
    "sg:address":"Avda Espa\u00d1a, 19",
    "sg:city":"Ceuta",
    "sg:orig_category":"M\u00c9dicos: Salud P\u00dablica",
    "sg:phone":"+34 956 50 62 17",
    "sg:postcode":"51001",
    "sg:province":"Ceuta",
    "wof:name":"Dominguez Fernandez Julian Manuel",
    "wof:placetype":"venue"
},
  "geometry": {"coordinates":[-5.3270401955,35.8949737549],"type":"Point"}
}