{
  "type": "Feature",
  "properties": {
    "iso:country":"ES",
    "sg:address":"Sanguesa, 24",
    "sg:city":"Iru\u00f1a",
    "sg:orig_category":"Sociedades, Compa\u00d1\u00cdas Aseguradoras",
    "sg:phone":"+34 948 23 35 00",
    "sg:postcode":"31003",
    "sg:province":"Navarra",
    "wof:name":"Correduria De Seguros Fraile S.l.",
    "wof:placetype":"venue"
},
  "geometry": {"coordinates":[-1.6404880285,42.8104667664],"type":"Point"}
}