{
  "type": "Feature",
  "properties": {
    "addr:full":"Plaz Santo Domingo, S/n S. Andres Rabanedo Le\u00f3n 24010",
    "addr:housenumber":"s",
    "addr:postcode":"24010",
    "addr:street":"Domingo;/ N S. Andres Rabanedo Leo\u0301N",
    "iso:country":"ES",
    "sg:address":"Plaz Santo Domingo, S/n",
    "sg:city":"S. Andres Rabanedo",
    "sg:orig_category":"Carnicer\u00cdas, Carnicer\u00cdas",
    "sg:phone":"+34 987 84 60 54",
    "sg:postcode":"24010",
    "sg:province":"Le\u00f3n",
    "wof:name":"Fernandez Lopez Justo",
    "wof:placetype":"venue"
},
  "geometry": {"coordinates":[-5.5716600418,42.5981292725],"type":"Point"}
}