{
  "type": "Feature",
  "properties": {
    "iso:country":"ES",
    "sg:address":"Via Faraday (de), 35",
    "sg:city":"Boisaca",
    "sg:orig_category":"Aceros Inoxidables",
    "sg:phone":"+34 981 58 64 33",
    "sg:postcode":"15890",
    "sg:province":"La Coru\u00f1a",
    "sg:website":"www.redinox.com",
    "wof:name":"Redinox S.l.",
    "wof:placetype":"venue"
},
  "geometry": {"coordinates":[-8.4769210815,42.8835983276],"type":"Point"}
}