{
  "type": "Feature",
  "properties": {
    "iso:country":"ES",
    "sg:address":"Calle de Fuenlabrada, 16",
    "sg:city":"Alcorcon",
    "sg:orig_category":"Perfumer\u00cda (al Por Menor)",
    "sg:phone":"+34 916 44 04 83",
    "sg:postcode":"28921",
    "sg:province":"Madrid",
    "wof:name":"Clinica Gala De Estetica Corporal",
    "wof:placetype":"venue"
},
  "geometry": {"coordinates":[-3.8265271187,40.3447723389],"type":"Point"}
}