{
  "type": "Feature",
  "properties": {
    "addr:full":"Calle de Extremadura, 24 Pto. Rosario Las Palmas 35600",
    "addr:housenumber":"24",
    "addr:postcode":"35600",
    "addr:street":"Calle De Extremadura;Pto. Rosario Las",
    "iso:country":"ES",
    "sg:address":"Calle de Extremadura, 24",
    "sg:city":"Pto. Rosario",
    "sg:orig_category":"Alquiler De V\u00cddeo",
    "sg:phone":"+34 928 53 13 75",
    "sg:postcode":"35600",
    "sg:province":"Las Palmas",
    "wof:name":"Video Club Oliver S.l.",
    "wof:placetype":"venue"
},
  "geometry": {"coordinates":[-13.8667812347,28.5041694641],"type":"Point"}
}