{
  "type": "Feature",
  "properties": {
    "addr:full":"Carrer de Guardia, 11 Poblenou Barcelona 08397",
    "addr:housenumber":"11",
    "addr:postcode":"08397",
    "addr:street":"Carrer De Guardia",
    "iso:country":"ES",
    "sg:address":"Carrer de Guardia, 11",
    "sg:city":"Poblenou",
    "sg:orig_category":"Guarder\u00cdas",
    "sg:phone":"+34 937 66 15 88",
    "sg:postcode":"08397",
    "sg:province":"Barcelona",
    "wof:name":"Escaler S.c.c.l.",
    "wof:placetype":"venue"
},
  "geometry": {"coordinates":[2.6724550724,41.6220588684],"type":"Point"}
}