{
  "type": "Feature",
  "properties": {
    "addr:full":"Calle de Jaizkibel, 3 Pasaia Guip\u00f9zcoa 20110",
    "addr:housenumber":"3",
    "addr:postcode":"20110",
    "addr:street":"Calle De Jaizkibel;Guipu\u0300Zcoa",
    "iso:country":"ES",
    "sg:address":"Calle de Jaizkibel, 3",
    "sg:city":"Pasaia",
    "sg:classifiers":[
        {
            "category":"Casinos & Gambling",
            "type":"Entertainment"
        }
    ],
    "sg:phone":"+34 943 39 22 19",
    "sg:postcode":"20110",
    "sg:province":"Guip\u00f9zcoa",
    "sg:tags":[
        "locale",
        "de",
        "juego"
    ],
    "wof:name":"City Las Vegas-salon De Juegos Azkuene",
    "wof:placetype":"venue"
},
  "geometry": {"coordinates":[-1.9368540049,43.323097229],"type":"Point"}
}