{
  "type": "Feature",
  "properties": {
    "addr:full":"Calle de Badajoz, 2 Arnedo La Rioja 26580",
    "addr:housenumber":"2",
    "addr:postcode":"26580",
    "addr:street":"Calle De Badajoz;Rioja",
    "iso:country":"ES",
    "sg:address":"Calle de Badajoz, 2",
    "sg:city":"Arnedo",
    "sg:orig_category":"Centros De Coordinaci\u00d3n",
    "sg:phone":"+34 941 38 43 37",
    "sg:postcode":"26580",
    "sg:province":"La Rioja",
    "wof:name":"Juan-cruz Ezquerro Perez S.l.",
    "wof:placetype":"venue"
},
  "geometry": {"coordinates":[-2.1010043621,42.2248153687],"type":"Point"}
}