{
  "type": "Feature",
  "properties": {
    "addr:full":"Raval Sant Rafael, 21 Selva Del Camp Tarragona 43470",
    "addr:housenumber":"21",
    "addr:postcode":"43470",
    "addr:street":"Sant Rafael",
    "iso:country":"ES",
    "sg:address":"Raval Sant Rafael, 21",
    "sg:city":"Selva Del Camp",
    "sg:orig_category":"Cintas, Balduques Y Cierres De Tela (fabricaci\u00d3n, Al Por Mayor)",
    "sg:phone":"+34 977 84 40 00",
    "sg:postcode":"43470",
    "sg:province":"Tarragona",
    "sg:website":"www.laindustrialalgodonera.com",
    "wof:name":"La Industrial Algodonera S. A.",
    "wof:placetype":"venue"
},
  "geometry": {"coordinates":[1.1409749985,41.2144813538],"type":"Point"}
}