{
  "type": "Feature",
  "properties": {
    "iso:country":"ES",
    "sg:address":"Calle de Juan Madrazo, 10",
    "sg:city":"Le\u00f3n",
    "sg:orig_category":"Caf\u00c9s, Bares, Cervecer\u00cdas",
    "sg:phone":"+34 987 23 67 14",
    "sg:postcode":"24002",
    "sg:province":"Le\u00f3n",
    "wof:name":"Fernandez Ares Felix",
    "wof:placetype":"venue"
},
  "geometry": {"coordinates":[-5.5759677887,42.6009483337],"type":"Point"}
}