{
  "type": "Feature",
  "properties": {
    "addr:full":"Calle de Genova, 25 Madrid Madrid 28004",
    "addr:housenumber":"25",
    "addr:postcode":"madrid;28004",
    "addr:street":"Calle De Genova",
    "iso:country":"ES",
    "sg:address":"Calle de Genova, 25",
    "sg:city":"Madrid",
    "sg:orig_category":"Barbacoas Y Accesorios",
    "sg:phone":"+34 917 02 04 98",
    "sg:postcode":"28004",
    "sg:province":"Madrid",
    "wof:name":"Genova Hosteleria S.l.",
    "wof:placetype":"venue"
},
  "geometry": {"coordinates":[-3.6925988197,40.4260749817],"type":"Point"}
}