{
  "type": "Feature",
  "properties": {
    "iso:country":"ES",
    "sg:address":"Plzl Santos Juanes, 3",
    "sg:city":"Bilbao",
    "sg:orig_category":"Comercio De Piezas De Recambio Y De Accesorios De Veh\u00cdculos, Veh\u00cdculos Industriales",
    "sg:phone":"+34 946 79 04 18",
    "sg:postcode":"48006",
    "sg:province":"Vizcaya",
    "wof:name":"Erke Equipamiento Para Vehiculos S.a.",
    "wof:placetype":"venue"
},
  "geometry": {"coordinates":[-2.9227740765,43.2553787231],"type":"Point"}
}