{
  "type": "Feature",
  "properties": {
    "iso:country":"ES",
    "sg:address":"Carr Sant Sebastia, 30",
    "sg:city":"Santa Coloma De Farners",
    "sg:orig_category":"Fabricaci\u00d3n De Peines Y De Accesorios De Peluquer\u00cda",
    "sg:phone":"+34 972 87 70 52",
    "sg:postcode":"17430",
    "sg:province":"Girona",
    "wof:name":"Tot Cabell S.l.",
    "wof:placetype":"venue"
},
  "geometry": {"coordinates":[2.6648569107,41.8617591858],"type":"Point"}
}