{
  "type": "Feature",
  "properties": {
    "addr:full":"Calle de Gran Via, 9 Zaragoza Zaragoza 50006",
    "addr:housenumber":"9",
    "addr:postcode":"50006",
    "addr:street":"Calle De Gran Via",
    "iso:country":"ES",
    "sg:address":"Calle de Gran Via, 9",
    "sg:city":"Zaragoza",
    "sg:orig_category":"Arquitectos",
    "sg:phone":"+34 976 22 59 97",
    "sg:postcode":"50006",
    "sg:province":"Zaragoza",
    "wof:name":"Bas Arrechea Luis Maria",
    "wof:placetype":"venue"
},
  "geometry": {"coordinates":[-0.8866670132,41.6463317871],"type":"Point"}
}