{
  "type": "Feature",
  "properties": {
    "iso:country":"ES",
    "sg:address":"Calle de Ventura De La Vega, 30",
    "sg:city":"Linares",
    "sg:orig_category":"Papeler\u00cdas, Librer\u00cdas",
    "sg:phone":"+34 953 60 10 74",
    "sg:postcode":"23700",
    "sg:province":"Ja\u00e9n",
    "wof:name":"Barranco Saez Juan Antonio",
    "wof:placetype":"venue"
},
  "geometry": {"coordinates":[-3.6292710304,38.0978393555],"type":"Point"}
}