{
  "type": "Feature",
  "properties": {
    "addr:full":"Calle de Bonillo (el), 22 Socuellamos Ciudad Real 13630",
    "addr:housenumber":"22",
    "addr:postcode":"13630",
    "addr:street":"Calle De Bonillo El",
    "iso:country":"ES",
    "sg:address":"Calle de Bonillo (el), 22",
    "sg:city":"Socuellamos",
    "sg:orig_category":"Alimentaci\u00d3n General (al Por Mayor)",
    "sg:phone":"+34 926 53 02 38",
    "sg:postcode":"13630",
    "sg:province":"Ciudad Real",
    "wof:name":"Ballesteros Caro Ignacio",
    "wof:placetype":"venue"
},
  "geometry": {"coordinates":[-2.786812067,39.2797775269],"type":"Point"}
}