{
  "type": "Feature",
  "properties": {
    "addr:full":"Calle de Baja, 2 Cedrillas Teruel 44147",
    "addr:housenumber":"2",
    "addr:postcode":"44147",
    "addr:street":"Calle De Baja",
    "iso:country":"ES",
    "sg:address":"Calle de Baja, 2",
    "sg:city":"Cedrillas",
    "sg:orig_category":"Transportes Por V\u00cdas Navegables",
    "sg:phone":"+34 978 77 41 95",
    "sg:postcode":"44147",
    "sg:province":"Teruel",
    "wof:name":"Anvicosa S.l.",
    "wof:placetype":"venue"
},
  "geometry": {"coordinates":[-0.8546413183,40.4361076355],"type":"Point"}
}