{
  "type": "Feature",
  "properties": {
    "iso:country":"ES",
    "sg:address":"C/ Almorida, 2",
    "sg:city":"Elche",
    "sg:orig_category":"Ingenier\u00cda, Centros De Estudios (diversos)",
    "sg:phone":"+34 965 42 31 28",
    "sg:postcode":"03203",
    "sg:province":"Alicante",
    "wof:name":"Moreno Luzon Jesus",
    "wof:placetype":"venue"
},
  "geometry": {"coordinates":[-0.695505023,38.2653617859],"type":"Point"}
}