{
  "type": "Feature",
  "properties": {
    "iso:country":"ES",
    "sg:address":"Carrer de Roger De Belfort, 35",
    "sg:city":"Reus",
    "sg:orig_category":"Restaurantes",
    "sg:phone":"+34 977 33 15 99",
    "sg:postcode":"43202",
    "sg:province":"Tarragona",
    "wof:name":"Crusells S.l.",
    "wof:placetype":"venue"
},
  "geometry": {"coordinates":[1.099560976,41.1550254822],"type":"Point"}
}