{
  "type": "Feature",
  "properties": {
    "iso:country":"ES",
    "sg:address":"Carrer de Pais Valencia, 10",
    "sg:city":"Cala",
    "sg:orig_category":"Bricolaje, Herramientas (al Por Menor)",
    "sg:phone":"+34 966 81 15 12",
    "sg:postcode":"03509",
    "sg:province":"Alicante",
    "wof:name":"Jelf Brico House S.l.",
    "wof:placetype":"venue"
},
  "geometry": {"coordinates":[-0.2106740028,38.5691642761],"type":"Point"}
}