{
  "type": "Feature",
  "properties": {
    "iso:country":"ES",
    "sg:address":"Calle de Tejeros, 8",
    "sg:city":"Malaga",
    "sg:orig_category":"Asociaciones Y Clubs Deportivos",
    "sg:phone":"+34 952 65 90 04",
    "sg:postcode":"29013",
    "sg:province":"M\u00e1laga",
    "wof:name":"Kivivian S.l.",
    "wof:placetype":"venue"
},
  "geometry": {"coordinates":[-4.4149198532,36.7288703918],"type":"Point"}
}