{
  "type": "Feature",
  "properties": {
    "addr:full":"Calle de Sallaberry, 43 Madrid Madrid 28019",
    "addr:housenumber":"43",
    "addr:postcode":"madrid;28019",
    "addr:street":"Calle De Sallaberry",
    "iso:country":"ES",
    "sg:address":"Calle de Sallaberry, 43",
    "sg:city":"Madrid",
    "sg:orig_category":"Venta, Colocaci\u00d3n De Autoradios",
    "sg:phone":"+34 914 71 01 77",
    "sg:postcode":"28019",
    "sg:province":"Madrid",
    "wof:name":"Lara Garcia Juan Manuel",
    "wof:placetype":"venue"
},
  "geometry": {"coordinates":[-3.7202088833,40.3928642273],"type":"Point"}
}