{
  "type": "Feature",
  "properties": {
    "iso:country":"ES",
    "sg:address":"Calle de Gonzalo De Berceo, 28",
    "sg:city":"Logro\u00f1o",
    "sg:orig_category":"Agencias De Viajes",
    "sg:phone":"+34 941 21 25 74",
    "sg:postcode":"26005",
    "sg:province":"La Rioja",
    "wof:name":"Maria Puente Pedro Luis",
    "wof:placetype":"venue"
},
  "geometry": {"coordinates":[-2.4579617977,42.4663047791],"type":"Point"}
}