{
  "type": "Feature",
  "properties": {
    "addr:full":"Calle de Real, S/n Santa Maria De Guia Las Palmas 35450",
    "addr:housenumber":"s / n",
    "addr:postcode":"35450",
    "addr:street":"Calle De Real",
    "iso:country":"ES",
    "sg:address":"Calle de Real, S/n",
    "sg:city":"Santa Maria De Guia",
    "sg:orig_category":"Art\u00cdculos Funerarios (al Por Menor)",
    "sg:phone":"+34 928 55 25 72",
    "sg:postcode":"35450",
    "sg:province":"Las Palmas",
    "wof:name":"Intur Servicios Funerarios S.l.",
    "wof:placetype":"venue"
},
  "geometry": {"coordinates":[-15.631149292,28.1400146484],"type":"Point"}
}