{
  "type": "Feature",
  "properties": {
    "iso:country":"ES",
    "sg:address":"Avda Jesus Morante Borras, 50",
    "sg:city":"Valencia",
    "sg:orig_category":"Persianas Interiores, Exteriores",
    "sg:phone":"+34 963 67 07 98",
    "sg:postcode":"46012",
    "sg:province":"Valencia",
    "wof:name":"Navarro Salcedo Vicente",
    "wof:placetype":"venue"
},
  "geometry": {"coordinates":[-0.3441799879,39.4485855103],"type":"Point"}
}