{
  "type": "Feature",
  "properties": {
    "iso:country":"ES",
    "sg:address":"Pase Palmeras Las, 9",
    "sg:city":"Huelva",
    "sg:orig_category":"Material Y Herramientas Agr\u00cdcolas",
    "sg:phone":"+34 959 28 52 98",
    "sg:postcode":"21002",
    "sg:province":"Huelva",
    "wof:name":"Agracor S.l.",
    "wof:placetype":"venue"
},
  "geometry": {"coordinates":[-6.9544320107,37.2631225586],"type":"Point"}
}