{
  "type": "Feature",
  "properties": {
    "addr:full":"Cmno Fontetas (las), 9 Sang\u00fcesa Navarra 31400",
    "addr:housenumber":"9",
    "addr:postcode":"31400",
    "addr:street":"Cmno Fontetas Las",
    "iso:country":"ES",
    "sg:address":"Cmno Fontetas (las), 9",
    "sg:city":"Sang\u00fcesa",
    "sg:orig_category":"Bebidas",
    "sg:phone":"+34 948 87 03 03",
    "sg:postcode":"31400",
    "sg:province":"Navarra",
    "wof:name":"Huarte Ripodas Sebastian",
    "wof:placetype":"venue"
},
  "geometry": {"coordinates":[-1.2806440592,42.5711250305],"type":"Point"}
}