{
  "type": "Feature",
  "properties": {
    "iso:country":"ES",
    "sg:address":"Avda Calvo Sotelo, 116",
    "sg:city":"Avd. Calvo Sotelo",
    "sg:orig_category":"Barquillos De Miel (fabricaci\u00d3n)",
    "sg:phone":"+34 968 66 75 14",
    "sg:postcode":"30190",
    "sg:province":"Murcia",
    "wof:name":"Lison Zapata Francisco",
    "wof:placetype":"venue"
},
  "geometry": {"coordinates":[-1.383259058,38.0277442932],"type":"Point"}
}