{
  "type": "Feature",
  "properties": {
    "iso:country":"ES",
    "sg:address":"Calle de Hornos (de Los), 5",
    "sg:city":"Calaceite",
    "sg:orig_category":"Empresas De Pintura Y Revestimientos",
    "sg:phone":"+34 978 85 11 70",
    "sg:postcode":"44610",
    "sg:province":"Teruel",
    "wof:name":"Bayod Zapater Ramon",
    "wof:placetype":"venue"
},
  "geometry": {"coordinates":[0.1877090037,41.0169410706],"type":"Point"}
}