{
  "type": "Feature",
  "properties": {
    "iso:country":"ES",
    "sg:address":"Plaz San Francisco, 10",
    "sg:city":"Le\u00f3n",
    "sg:orig_category":"Comunidades Religiosas",
    "sg:phone":"+34 987 25 12 52",
    "sg:postcode":"24004",
    "sg:province":"Le\u00f3n",
    "wof:name":"Convento Padres Capuchinos",
    "wof:placetype":"venue"
},
  "geometry": {"coordinates":[-5.5703568459,42.5938186646],"type":"Point"}
}