{
  "type": "Feature",
  "properties": {
    "iso:country":"ES",
    "sg:address":"Avda Doctor Jimenez Diaz, 4",
    "sg:city":"Alacant",
    "sg:orig_category":"Audiovisuales (producci\u00d3n, Edici\u00d3n, Realizaci\u00d3n)",
    "sg:phone":"+34 965 12 13 33",
    "sg:postcode":"03005",
    "sg:province":"Alicante",
    "wof:name":"Mediapress S.l",
    "wof:placetype":"venue"
},
  "geometry": {"coordinates":[-0.5052379966,38.3496932983],"type":"Point"}
}