{
  "type": "Feature",
  "properties": {
    "iso:country":"ES",
    "sg:address":"Av Emporda, 61",
    "sg:city":"Poligon Pont Del Princep",
    "sg:orig_category":"Empresas De Carpinter\u00cda De Madera",
    "sg:phone":"+34 972 52 58 13",
    "sg:postcode":"17469",
    "sg:province":"Girona",
    "wof:name":"Fusteria La Nau 2000 S.l.",
    "wof:placetype":"venue"
},
  "geometry": {"coordinates":[2.9630479813,42.2267417908],"type":"Point"}
}