{
  "type": "Feature",
  "properties": {
    "iso:country":"ES",
    "sg:address":"Avda Generalisimo, 31",
    "sg:city":"Puerto Cruz",
    "sg:orig_category":"Peluqueros: De Se\u00d1oras",
    "sg:phone":"+34 922 38 32 18",
    "sg:postcode":"38400",
    "sg:province":"Santa Cruz De Tenerife",
    "wof:name":"City Salon S.l.",
    "wof:placetype":"venue"
},
  "geometry": {"coordinates":[-16.5473842621,28.4141807556],"type":"Point"}
}