{
  "type": "Feature",
  "properties": {
    "iso:country":"ES",
    "sg:address":"Calle de La Rua, 3",
    "sg:city":"Benavente",
    "sg:orig_category":"Confecci\u00d3n De Zapatos",
    "sg:phone":"+34 980 63 06 06",
    "sg:postcode":"49600",
    "sg:province":"Zamora",
    "wof:name":"Cano Cornejo S.l.",
    "wof:placetype":"venue"
},
  "geometry": {"coordinates":[-5.6792140007,42.0021514893],"type":"Point"}
}