{
  "type": "Feature",
  "properties": {
    "iso:country":"ES",
    "sg:address":"Calle de Bilbao, 5",
    "sg:city":"Cox",
    "sg:orig_category":"Material Y Suministros Para Peluquer\u00cda",
    "sg:phone":"+34 966 75 12 08",
    "sg:postcode":"03350",
    "sg:province":"Alicante",
    "wof:name":"Navarro Ferrandez Inmaculada",
    "wof:placetype":"venue"
},
  "geometry": {"coordinates":[-0.8846310973,38.1384735107],"type":"Point"}
}