{
  "type": "Feature",
  "properties": {
    "iso:country":"ES",
    "sg:address":"Calle de Obispo Luis Amigo, 18",
    "sg:city":"Godella",
    "sg:orig_category":"Comercio, Reparaci\u00d3n De Motocicletas, Bicicletas Y Piezas Sueltas",
    "sg:phone":"+34 963 90 05 65",
    "sg:postcode":"46110",
    "sg:province":"Valencia",
    "wof:name":"Soria Albuger Juan Jose",
    "wof:placetype":"venue"
},
  "geometry": {"coordinates":[-0.426658392,39.5322189331],"type":"Point"}
}