{
  "type": "Feature",
  "properties": {
    "addr:full":"Carrer de Sant Isidre (de), 87 S. Carles Rapita Tarragona 43540",
    "addr:housenumber":"87",
    "addr:postcode":"43540",
    "addr:street":"Carrer De Sant Isidre De;S. Carles Rapita",
    "iso:country":"ES",
    "sg:address":"Carrer de Sant Isidre (de), 87",
    "sg:city":"S. Carles Rapita",
    "sg:orig_category":"Farmacias",
    "sg:phone":"+34 977 74 14 60",
    "sg:postcode":"43540",
    "sg:province":"Tarragona",
    "wof:name":"Bel Armengol Mercedes",
    "wof:placetype":"venue"
},
  "geometry": {"coordinates":[0.5887539983,40.6167106628],"type":"Point"}
}