{
  "type": "Feature",
  "properties": {
    "addr:full":"Estda. Allariz-celanova, S/n Podentes Ourense 32812",
    "addr:housenumber":"s",
    "addr:postcode":"32812",
    "addr:street":"/ N",
    "iso:country":"ES",
    "sg:address":"Estda. Allariz-celanova, S/n",
    "sg:city":"Podentes",
    "sg:orig_category":"Art\u00cdculos De Madera (fabricaci\u00d3n Y Al Por Mayor)",
    "sg:phone":"+34 988 43 36 33",
    "sg:postcode":"32812",
    "sg:province":"Ourense",
    "wof:name":"Vazquez Veloso Manuel",
    "wof:placetype":"venue"
},
  "geometry": {"coordinates":[-7.8930487633,42.1582756042],"type":"Point"}
}