{
  "type": "Feature",
  "properties": {
    "addr:full":"Calle de Fundicion (de La), 4 Partija-santa Monica Madrid 28529",
    "addr:housenumber":"4",
    "addr:postcode":"28529",
    "addr:street":"Calle De Fundicion De La",
    "iso:country":"ES",
    "sg:address":"Calle de Fundicion (de La), 4",
    "sg:city":"Partija-santa Monica",
    "sg:orig_category":"Limpieza Industrial",
    "sg:phone":"+34 914 99 23 97",
    "sg:postcode":"28529",
    "sg:province":"Madrid",
    "wof:name":"Ll. Colombres Lavanderia Industrial",
    "wof:placetype":"venue"
},
  "geometry": {"coordinates":[-3.5102670193,40.314289093],"type":"Point"}
}