{
  "type": "Feature",
  "properties": {
    "iso:country":"ES",
    "sg:address":"Pg Sant Joan, 7",
    "sg:city":"Barcelona",
    "sg:orig_category":"Administradores De Bienes Y Delegados De Comunidades De Propietarios",
    "sg:phone":"+34 932 31 42 29",
    "sg:postcode":"08010",
    "sg:province":"Barcelona",
    "wof:name":"Renedo Mateu S.l.",
    "wof:placetype":"venue"
},
  "geometry": {"coordinates":[2.1787691116,41.3922615051],"type":"Point"}
}