{
  "type": "Feature",
  "properties": {
    "iso:country":"ES",
    "sg:address":"Calle de Palomares, S/n",
    "sg:city":"Iscar",
    "sg:orig_category":"Caf\u00c9s, Bares, Cervecer\u00cdas",
    "sg:phone":"+34 983 61 17 13",
    "sg:postcode":"47420",
    "sg:province":"Valladolid",
    "wof:name":"Empresa Lobejon S.l.",
    "wof:placetype":"venue"
},
  "geometry": {"coordinates":[-4.5332689285,41.3613433838],"type":"Point"}
}