{
  "type": "Feature",
  "properties": {
    "iso:country":"ES",
    "sg:address":"Carrer de Sol, 41",
    "sg:city":"Viladecans",
    "sg:orig_category":"Agencias Y Asesores De Publicidad",
    "sg:phone":"+34 936 47 30 24",
    "sg:postcode":"08840",
    "sg:province":"Barcelona",
    "sg:website":"wwww.estudifiguerola.com",
    "wof:name":"Figuerola Disseny S.l.",
    "wof:placetype":"venue"
},
  "geometry": {"coordinates":[2.016546011,41.3177261353],"type":"Point"}
}