{
  "type": "Feature",
  "properties": {
    "addr:full":"Calle de Velero, 6 Majadahonda Madrid 28220",
    "addr:housenumber":"6",
    "addr:postcode":"28220",
    "addr:street":"Calle De Velero",
    "iso:country":"ES",
    "sg:address":"Calle de Velero, 6",
    "sg:city":"Majadahonda",
    "sg:orig_category":"Pintura: M\u00c1quinas (instalaci\u00d3n)",
    "sg:phone":"+34 916 02 96 12",
    "sg:postcode":"28220",
    "sg:province":"Madrid",
    "wof:name":"Instalaciones Francisco Montes Y Gutierrez Sl",
    "wof:placetype":"venue"
},
  "geometry": {"coordinates":[-3.8760709763,40.4619865417],"type":"Point"}
}