{
  "type": "Feature",
  "properties": {
    "addr:full":"Avda Pinos (los), 6 Guardamar Segura Alicante 03140",
    "addr:housenumber":"6",
    "addr:postcode":"03140",
    "addr:street":"Avda Pinos Los",
    "iso:country":"ES",
    "sg:address":"Avda Pinos (los), 6",
    "sg:city":"Guardamar Segura",
    "sg:orig_category":"Inmobiliaria (agencias)",
    "sg:phone":"+34 965 72 96 90",
    "sg:postcode":"03140",
    "sg:province":"Alicante",
    "wof:name":"Vidal Zaragoza Carmen",
    "wof:placetype":"venue"
},
  "geometry": {"coordinates":[-0.652665019,38.0897254944],"type":"Point"}
}