{
  "type": "Feature",
  "properties": {
    "addr:full":"Calle de Puerta Nueva, 45 Hornos Ja\u00e9n 23292",
    "addr:housenumber":"45",
    "addr:postcode":"23292",
    "addr:street":"Calle De Puerta Nueva",
    "iso:country":"ES",
    "sg:address":"Calle de Puerta Nueva, 45",
    "sg:city":"Hornos",
    "sg:orig_category":"Albergues",
    "sg:phone":"+34 953 49 50 35",
    "sg:postcode":"23292",
    "sg:province":"Ja\u00e9n",
    "wof:name":"Chinchilla Mu\u00f1oz David",
    "wof:placetype":"venue"
},
  "geometry": {"coordinates":[-2.7172889709,38.2163314819],"type":"Point"}
}