{
  "type": "Feature",
  "properties": {
    "addr:full":"Pl Ferran De Sagarra, S/n Santa Coloma De Gramenet Barcelona 08922",
    "addr:housenumber":"s / n",
    "addr:postcode":"08922",
    "addr:street":"Pl Ferran De Sagarra",
    "iso:country":"ES",
    "sg:address":"Pl Ferran De Sagarra, S/n",
    "sg:city":"Santa Coloma De Gramenet",
    "sg:orig_category":"Pescader\u00cdas (al Por Menor)",
    "sg:phone":"+34 933 86 19 77",
    "sg:postcode":"08922",
    "sg:province":"Barcelona",
    "wof:name":"Zaragoza Marti Miguel",
    "wof:placetype":"venue"
},
  "geometry": {"coordinates":[2.2101402283,41.4488677979],"type":"Point"}
}