{
  "type": "Feature",
  "properties": {
    "iso:country":"ES",
    "sg:address":"Avgd Espioca, 7",
    "sg:city":"Silla",
    "sg:orig_category":"Fabricaci\u00d3n De Muebles",
    "sg:phone":"+34 961 20 11 75",
    "sg:postcode":"46460",
    "sg:province":"Valencia",
    "wof:name":"Dogar Import S.l",
    "wof:placetype":"venue"
},
  "geometry": {"coordinates":[-0.4164400101,39.3723831177],"type":"Point"}
}