{
  "type": "Feature",
  "properties": {
    "iso:country":"ES",
    "sg:address":"Carretera, Km. 0013,8",
    "sg:city":"Lavit",
    "sg:orig_category":"Fabricaci\u00d3n De Cajas De Cart\u00d3n",
    "sg:phone":"+34 938 99 53 11",
    "sg:postcode":"08775",
    "sg:province":"Barcelona",
    "sg:website":"www.cartonajesfont.com",
    "wof:name":"Cartonajes Font S. A.",
    "wof:placetype":"venue"
},
  "geometry": {"coordinates":[1.7272900343,41.4427185059],"type":"Point"}
}