{
  "type": "Feature",
  "properties": {
    "iso:country":"ES",
    "sg:address":"Calle de Escuelas, S/n",
    "sg:city":"Sanchonu\u00d1o",
    "sg:orig_category":"Carnicer\u00cdas, Carnicer\u00cdas",
    "sg:phone":"+34 921 16 00 22",
    "sg:postcode":"40297",
    "sg:province":"Segovia",
    "wof:name":"Otero De Andres Frutos",
    "wof:placetype":"venue"
},
  "geometry": {"coordinates":[-4.303194046,41.3266143799],"type":"Point"}
}