{
  "type": "Feature",
  "properties": {
    "addr:full":"Avda Breton De Los Herreros, 4 Haro La Rioja 26200",
    "addr:housenumber":"4",
    "addr:postcode":"26200",
    "addr:street":"Avda Breton De Los Herreros",
    "iso:country":"ES",
    "sg:address":"Avda Breton De Los Herreros, 4",
    "sg:city":"Haro",
    "sg:orig_category":"C\u00c1maras De Comercio E Industria, Oficios, Agricultura",
    "sg:phone":"+34 941 31 15 45",
    "sg:postcode":"26200",
    "sg:province":"La Rioja",
    "wof:name":"Comunidad Autonoma De La Rioja",
    "wof:placetype":"venue"
},
  "geometry": {"coordinates":[-2.8544459343,42.5741958618],"type":"Point"}
}