{
  "type": "Feature",
  "properties": {
    "addr:full":"Avda Elda (de), 81 Petrer Alicante 03610",
    "addr:housenumber":"81",
    "addr:postcode":"03610",
    "addr:street":"Avda Elda De",
    "iso:country":"ES",
    "sg:address":"Avda Elda (de), 81",
    "sg:city":"Petrer",
    "sg:orig_category":"Agencias De Viajes",
    "sg:phone":"+34 966 95 12 48",
    "sg:postcode":"03610",
    "sg:province":"Alicante",
    "wof:name":"Viajes Becar S.l.u.",
    "wof:placetype":"venue"
},
  "geometry": {"coordinates":[-0.7793490291,38.4835205078],"type":"Point"}
}