{
  "type": "Feature",
  "properties": {
    "iso:country":"ES",
    "sg:address":"Calle de Jovellanos, 32",
    "sg:city":"Aguilas",
    "sg:orig_category":"Agencias Y Agentes Comerciales, Representantes",
    "sg:phone":"+34 968 41 45 28",
    "sg:postcode":"30880",
    "sg:province":"Murcia",
    "wof:name":"Robles Castillo Dolores",
    "wof:placetype":"venue"
},
  "geometry": {"coordinates":[-1.5799690485,37.4063911438],"type":"Point"}
}