{
  "type": "Feature",
  "properties": {
    "iso:country":"ES",
    "sg:address":"Av Bartomeu Riutort, 18",
    "sg:city":"Can Pastilla",
    "sg:orig_category":"Relojer\u00cda (al Por Menor, Reparaci\u00d3n)",
    "sg:phone":"+34 971 26 13 20",
    "sg:postcode":"07610",
    "sg:province":"Islas Baleares",
    "wof:name":"Yela Forteza Maria Pilar",
    "wof:placetype":"venue"
},
  "geometry": {"coordinates":[2.7173953056,39.5362243652],"type":"Point"}
}