{
  "type": "Feature",
  "properties": {
    "addr:full":"Calle de Galileo, 39 Palmas De Gran Canaria Las Palmas 35010",
    "addr:housenumber":"39",
    "addr:postcode":"35010",
    "addr:street":"Calle De Galileo",
    "iso:country":"ES",
    "sg:address":"Calle de Galileo, 39",
    "sg:city":"Palmas De Gran Canaria",
    "sg:orig_category":"Servicios De Telecomunicaciones",
    "sg:phone":"+34 928 26 33 46",
    "sg:postcode":"35010",
    "sg:province":"Las Palmas",
    "wof:name":"Archi Comunicaciones S.l.",
    "wof:placetype":"venue"
},
  "geometry": {"coordinates":[-15.4357976913,28.1356811523],"type":"Point"}
}