{
  "type": "Feature",
  "properties": {
    "iso:country":"ES",
    "sg:address":"Avda Nocedo, 44",
    "sg:city":"Le\u00f3n",
    "sg:orig_category":"Lencer\u00cda Femenina, Corseter\u00cda, Trajes De Ba\u00d1o (al Por Menor)",
    "sg:phone":"+34 987 23 72 78",
    "sg:postcode":"24007",
    "sg:province":"Le\u00f3n",
    "wof:name":"Ortopedia Canonigo Juan S.c.p.",
    "wof:placetype":"venue"
},
  "geometry": {"coordinates":[-5.5682668686,42.6066474915],"type":"Point"}
}