{
  "type": "Feature",
  "properties": {
    "iso:country":"ES",
    "sg:address":"Avgd Catalunya, 8",
    "sg:city":"Lleida",
    "sg:orig_category":"Asesor\u00cda Sobre Comunicaci\u00d3n De Empresas",
    "sg:phone":"+34 973 28 25 10",
    "sg:postcode":"25002",
    "sg:province":"Lleida",
    "wof:name":"Falco-guardia Associats S.l.",
    "wof:placetype":"venue"
},
  "geometry": {"coordinates":[0.621291995,41.6112594604],"type":"Point"}
}