{
  "type": "Feature",
  "properties": {
    "addr:full":"Calle de Melchor Gaspar Jovellanos, 3 Zaragoza Zaragoza 50012",
    "addr:housenumber":"3",
    "addr:postcode":"50012",
    "addr:street":"Calle De Melchor Gaspar Jovellanos",
    "iso:country":"ES",
    "sg:address":"Calle de Melchor Gaspar Jovellanos, 3",
    "sg:city":"Zaragoza",
    "sg:orig_category":"Maquinaria Para Industrias Diversas",
    "sg:phone":"+34 976 75 52 88",
    "sg:postcode":"50012",
    "sg:province":"Zaragoza",
    "wof:name":"Calvera Gomis Luis",
    "wof:placetype":"venue"
},
  "geometry": {"coordinates":[-0.9270319939,41.6273078918],"type":"Point"}
}