{
  "type": "Feature",
  "properties": {
    "iso:country":"ES",
    "sg:address":"Pg Gran Passeig Ronda, 124",
    "sg:city":"Lleida",
    "sg:orig_category":"M\u00c9dicos: Cirug\u00cda Ortop\u00c9dica Y Traumatolog\u00cda",
    "sg:phone":"+34 973 24 23 17",
    "sg:postcode":"25008",
    "sg:province":"Lleida",
    "wof:name":"Centro Medico Kirma S.l.",
    "wof:placetype":"venue"
},
  "geometry": {"coordinates":[0.6183879972,41.6218032837],"type":"Point"}
}