{
  "type": "Feature",
  "properties": {
    "iso:country":"ES",
    "sg:address":"Calle de Viella, 22",
    "sg:city":"Madrid",
    "sg:orig_category":"Arquitectos",
    "sg:phone":"+34 914 50 30 91",
    "sg:postcode":"28040",
    "sg:province":"Madrid",
    "wof:name":"Lambea Escalada David",
    "wof:placetype":"venue"
},
  "geometry": {"coordinates":[-3.7166457176,40.4551086426],"type":"Point"}
}