{
  "type": "Feature",
  "properties": {
    "addr:full":"Irunlarrea, 13 Iru\u00f1a Navarra 31008",
    "addr:housenumber":"13",
    "addr:postcode":"31008",
    "addr:street":"Irunlarrea",
    "iso:country":"ES",
    "sg:address":"Irunlarrea, 13",
    "sg:city":"Iru\u00f1a",
    "sg:orig_category":"Mercer\u00cda, Lencer\u00cda (al Por Menor)",
    "sg:phone":"+34 948 17 64 69",
    "sg:postcode":"31008",
    "sg:province":"Navarra",
    "wof:name":"Huarte Garciarena Lucia",
    "wof:placetype":"venue"
},
  "geometry": {"coordinates":[-1.6719089746,42.8074989319],"type":"Point"}
}