{
  "type": "Feature",
  "properties": {
    "addr:full":"Calle de Garcia Lorca, 15 Cortegana Huelva 21230",
    "addr:housenumber":"15",
    "addr:postcode":"21230",
    "addr:street":"Calle De Garcia Lorca",
    "iso:country":"ES",
    "sg:address":"Calle de Garcia Lorca, 15",
    "sg:city":"Cortegana",
    "sg:orig_category":"\u00d3ptica: Instrumentos (fabricaci\u00d3n)",
    "sg:phone":"+34 959 13 11 08",
    "sg:postcode":"21230",
    "sg:province":"Huelva",
    "wof:name":"Benitez Sanchez-cid Juan Pablo",
    "wof:placetype":"venue"
},
  "geometry": {"coordinates":[-6.8218588829,37.90832901],"type":"Point"}
}