{
  "type": "Feature",
  "properties": {
    "addr:full":"Entrepe\u00f1as, S/n Pelugano Asturias 33686",
    "addr:postcode":"33686",
    "addr:street":"Entrepen\u0303As S / N Pelugano Asturias",
    "iso:country":"ES",
    "sg:address":"Entrepe\u00f1as, S/n",
    "sg:city":"Pelugano",
    "sg:orig_category":"Estudios Y Construcci\u00d3n De Acuarios Y Viveros",
    "sg:phone":"+34 985 49 42 04",
    "sg:postcode":"33686",
    "sg:province":"Asturias",
    "wof:name":"Piscifactoria Asturiana S. L.",
    "wof:placetype":"venue"
},
  "geometry": {"coordinates":[-5.6228342056,43.1615257263],"type":"Point"}
}