{
  "type": "Feature",
  "properties": {
    "iso:country":"ES",
    "sg:address":"Calle de Negros Los, S/n",
    "sg:city":"Malaga",
    "sg:orig_category":"Discapacitados",
    "sg:phone":"+34 952 65 79 46",
    "sg:postcode":"29013",
    "sg:province":"M\u00e1laga",
    "sg:website":"www.fundacionafim.org",
    "wof:name":"Fundacion Afim",
    "wof:placetype":"venue"
},
  "geometry": {"coordinates":[-4.4184141159,36.7264251709],"type":"Point"}
}