{
  "type": "Feature",
  "properties": {
    "iso:country":"ES",
    "sg:address":"Calle de Sancho Panza, 8",
    "sg:city":"Ciudad Real",
    "sg:orig_category":"Empresarios",
    "sg:phone":"+34 926 27 41 66",
    "sg:postcode":"13004",
    "sg:province":"Ciudad Real",
    "wof:name":"Fundacion Diagrama Intervencion Psicosocial",
    "wof:placetype":"venue"
},
  "geometry": {"coordinates":[-3.9233460426,38.9862136841],"type":"Point"}
}