{
  "type": "Feature",
  "properties": {
    "iso:country":"ES",
    "sg:address":"Avda Constitucion (de La), 24",
    "sg:city":"San Fernando De Henares",
    "sg:orig_category":"Centros Empresariales",
    "sg:phone":"+34 916 60 10 23",
    "sg:postcode":"28830",
    "sg:province":"Madrid",
    "wof:name":"Fernandez Ruiz Esperanza",
    "wof:placetype":"venue"
},
  "geometry": {"coordinates":[-3.5331819057,40.424697876],"type":"Point"}
}