{
  "type": "Feature",
  "properties": {
    "iso:country":"ES",
    "sg:address":"Carr El Priorat, 17",
    "sg:city":"Lleida",
    "sg:orig_category":"Mercer\u00cda, Lencer\u00cda (al Por Menor)",
    "sg:phone":"+34 973 23 59 12",
    "sg:postcode":"25005",
    "sg:province":"Lleida",
    "wof:name":"Palomes Masmitja Margarita",
    "wof:placetype":"venue"
},
  "geometry": {"coordinates":[0.6238059998,41.6265335083],"type":"Point"}
}