{
  "type": "Feature",
  "properties": {
    "addr:full":"Av Can Bordoll, 57 Torre-romeu Barcelona 08202",
    "addr:housenumber":"57",
    "addr:postcode":"08202",
    "addr:street":"Av Can Bordoll;Barcelona",
    "iso:country":"ES",
    "sg:address":"Av Can Bordoll, 57",
    "sg:city":"Torre-romeu",
    "sg:orig_category":"Papel (al Por Mayor)",
    "sg:phone":"+34 937 26 58 04",
    "sg:postcode":"08202",
    "sg:province":"Barcelona",
    "wof:name":"Friolisa S.a.",
    "wof:placetype":"venue"
},
  "geometry": {"coordinates":[2.1687450409,41.3855895996],"type":"Point"}
}