{
  "type": "Feature",
  "properties": {
    "addr:full":"Calle de San Juan Bautista La Salle, 10 Talavera Reina Toledo 45600",
    "addr:housenumber":"10",
    "addr:postcode":"45600",
    "addr:street":"Calle De;Salle",
    "iso:country":"ES",
    "sg:address":"Calle de San Juan Bautista La Salle, 10",
    "sg:city":"Talavera Reina",
    "sg:orig_category":"Charcuter\u00cdas (al Por Mayor)",
    "sg:phone":"+34 925 80 55 39",
    "sg:postcode":"45600",
    "sg:province":"Toledo",
    "wof:name":"Rodriguez Martin Ricardo",
    "wof:placetype":"venue"
},
  "geometry": {"coordinates":[-4.8293738365,39.9675521851],"type":"Point"}
}