{
  "type": "Feature",
  "properties": {
    "iso:country":"ES",
    "sg:address":"Calle de Quero, 99",
    "sg:city":"Madrid",
    "sg:orig_category":"Tintes (fabricaci\u00d3n, Al Por Mayor)",
    "sg:phone":"+34 917 17 92 88",
    "sg:postcode":"28024",
    "sg:province":"Madrid",
    "wof:name":"Felole S.l.",
    "wof:placetype":"venue"
},
  "geometry": {"coordinates":[-3.7611858845,40.3890342712],"type":"Point"}
}