{
  "type": "Feature",
  "properties": {
    "iso:country":"ES",
    "sg:address":"Carrer de Mossen Jacint Verdaguer, 27",
    "sg:city":"Santa Coloma De Gramenet",
    "sg:orig_category":"Fabricaci\u00d3n, Importaci\u00d3n De L\u00c1mparas Y Bombillas",
    "sg:phone":"+34 933 86 45 99",
    "sg:postcode":"08922",
    "sg:province":"Barcelona",
    "wof:name":"Pardo Lupion Jose",
    "wof:placetype":"venue"
},
  "geometry": {"coordinates":[2.2104771137,41.446144104],"type":"Point"}
}