{
  "type": "Feature",
  "properties": {
    "iso:country":"ES",
    "sg:address":"Calle de Hermanas Moreno Pozuelo, 34",
    "sg:city":"Pozoblanco",
    "sg:orig_category":"Estancos",
    "sg:phone":"+34 957 13 15 44",
    "sg:postcode":"14400",
    "sg:province":"C\u00f3rdoba",
    "wof:name":"Cabrera Mu\u00f1oz Jose Andres",
    "wof:placetype":"venue"
},
  "geometry": {"coordinates":[-4.8490719795,38.3795700073],"type":"Point"}
}