{
  "type": "Feature",
  "properties": {
    "iso:country":"ES",
    "sg:address":"Carrer de Sant Isidre, 1",
    "sg:city":"Valls",
    "sg:orig_category":"Reposter\u00cdas",
    "sg:phone":"+34 977 60 21 71",
    "sg:postcode":"43800",
    "sg:province":"Tarragona",
    "wof:name":"Perez Sanchez Elias",
    "wof:placetype":"venue"
},
  "geometry": {"coordinates":[1.2470669746,41.2824363708],"type":"Point"}
}