{
  "type": "Feature",
  "properties": {
    "addr:full":"Carrer de L'artesania, 36 Barcelona Barcelona 08042",
    "addr:housenumber":"36",
    "addr:postcode":"08042",
    "addr:street":"Carrer De L'Artesania",
    "iso:country":"ES",
    "sg:address":"Carrer de L'artesania, 36",
    "sg:city":"Barcelona",
    "sg:orig_category":"Marroquiner\u00cda (confecci\u00d3n)",
    "sg:phone":"+34 932 76 01 77",
    "sg:postcode":"08042",
    "sg:province":"Barcelona",
    "wof:name":"Gil Castellano Carmen",
    "wof:placetype":"venue"
},
  "geometry": {"coordinates":[2.1746277809,41.4395599365],"type":"Point"}
}