{
  "type": "Feature",
  "properties": {
    "addr:full":"Calle de Gibraltar, 16 Atarfe Granada 18230",
    "addr:housenumber":"16",
    "addr:postcode":"18230",
    "addr:street":"Calle De Gibraltar",
    "iso:country":"ES",
    "sg:address":"Calle de Gibraltar, 16",
    "sg:city":"Atarfe",
    "sg:orig_category":"Molduras, Junquillos, Listones Y Molduras Perforadas",
    "sg:phone":"+34 958 43 86 19",
    "sg:postcode":"18230",
    "sg:province":"Granada",
    "wof:name":"Moreno Barrio Juan Bautista",
    "wof:placetype":"venue"
},
  "geometry": {"coordinates":[-3.6873939037,37.2272377014],"type":"Point"}
}