{
  "type": "Feature",
  "properties": {
    "iso:country":"ES",
    "sg:address":"Calle de Asturias, 7",
    "sg:city":"Salamanca",
    "sg:orig_category":"Productos Qu\u00cdmicos (fabricaci\u00d3n, Al Por Mayor)",
    "sg:phone":"+34 923 26 16 07",
    "sg:postcode":"37007",
    "sg:province":"Salamanca",
    "wof:name":"Fernandez Miguel Jesus Antonio",
    "wof:placetype":"venue"
},
  "geometry": {"coordinates":[-5.6680927277,40.9697189331],"type":"Point"}
}