{
  "type": "Feature",
  "properties": {
    "iso:country":"ES",
    "sg:address":"Avda Tanausu, 1",
    "sg:city":"Llanos De Aridane",
    "sg:orig_category":"Zapatos (al Por Menor)",
    "sg:phone":"+34 922 40 25 95",
    "sg:postcode":"38760",
    "sg:province":"Santa Cruz De Tenerife",
    "wof:name":"Alberto Acosta Ana Carolina",
    "wof:placetype":"venue"
},
  "geometry": {"coordinates":[-17.9142551422,28.6588916779],"type":"Point"}
}