{
  "type": "Feature",
  "properties": {
    "addr:full":"Cm\u00d1o Estacion, 73 Betanzos La Coru\u00f1a 15300",
    "addr:housenumber":"73",
    "addr:postcode":"15300",
    "addr:street":"Estacion;La",
    "iso:country":"ES",
    "sg:address":"Cm\u00d1o Estacion, 73",
    "sg:city":"Betanzos",
    "sg:orig_category":"Extinci\u00d3n De Incendios: Material Y Suministros (fabricaci\u00d3n, Al Por Mayor)",
    "sg:phone":"+34 981 77 04 26",
    "sg:postcode":"15300",
    "sg:province":"La Coru\u00f1a",
    "wof:name":"Lopez Seoane Purificacion",
    "wof:placetype":"venue"
},
  "geometry": {"coordinates":[-8.2119092941,43.279914856],"type":"Point"}
}