{
  "type": "Feature",
  "properties": {
    "iso:country":"ES",
    "sg:address":"Av. Esparteros, 18",
    "sg:city":"Leganes",
    "sg:orig_category":"Frutas, Legumbres Frescas Y Tempranas (al Por Menor)",
    "sg:phone":"+34 916 42 58 30",
    "sg:postcode":"28918",
    "sg:province":"Madrid",
    "wof:name":"Cashfruit S.l.",
    "wof:placetype":"venue"
},
  "geometry": {"coordinates":[-3.8028290272,40.3486328125],"type":"Point"}
}