{
  "type": "Feature",
  "properties": {
    "addr:full":"Calle de Ramon Alvarez, 2 Zamora Zamora 49004",
    "addr:housenumber":"2",
    "addr:postcode":"49004",
    "addr:street":"Calle De Ramon Alvarez",
    "iso:country":"ES",
    "sg:address":"Calle de Ramon Alvarez, 2",
    "sg:city":"Zamora",
    "sg:orig_category":"Prot\u00c9sicos Dentales",
    "sg:phone":"+34 980 53 40 79",
    "sg:postcode":"49004",
    "sg:province":"Zamora",
    "wof:name":"Sutil Calvo Antonio",
    "wof:placetype":"venue"
},
  "geometry": {"coordinates":[-5.7472782135,41.5042037964],"type":"Point"}
}