{
  "type": "Feature",
  "properties": {
    "addr:full":"Calle de San Enrique De Osso, 199 Madrid Madrid 28050",
    "addr:housenumber":"199",
    "addr:postcode":"28050",
    "addr:street":"Calle De San Enrique De Osso",
    "iso:country":"ES",
    "sg:address":"Calle de San Enrique De Osso, 199",
    "sg:city":"Madrid",
    "sg:orig_category":"Empresas De Portes Y Mensajer\u00cda",
    "sg:phone":"+34 916 25 53 46",
    "sg:postcode":"28050",
    "sg:province":"Madrid",
    "wof:name":"Serwell S. A.",
    "wof:placetype":"venue"
},
  "geometry": {"coordinates":[-3.6377699375,40.5042419434],"type":"Point"}
}