{
  "type": "Feature",
  "properties": {
    "addr:full":"Calle de Espiritu Santo, 9 Valladolid Valladolid 47006",
    "addr:housenumber":"9",
    "addr:postcode":"47006",
    "addr:street":"Calle De Espiritu Santo",
    "iso:country":"ES",
    "sg:address":"Calle de Espiritu Santo, 9",
    "sg:city":"Valladolid",
    "sg:orig_category":"Inform\u00c1tica, Ofim\u00c1tica (estudios, Asesor\u00cda, Ingenier\u00cda, Formaci\u00d3n)",
    "sg:phone":"+34 983 13 45 52",
    "sg:postcode":"47006",
    "sg:province":"Valladolid",
    "wof:name":"Agroinversores Del Norte S.l.",
    "wof:placetype":"venue"
},
  "geometry": {"coordinates":[-4.7349457741,41.6455116272],"type":"Point"}
}