{
  "type": "Feature",
  "properties": {
    "addr:full":"Real, 20 Pontedeume A Coru\u00f1a 15600",
    "addr:housenumber":"20",
    "addr:postcode":"15600",
    "addr:street":"Real;Corun\u0303A",
    "iso:country":"ES",
    "sg:address":"Real, 20",
    "sg:city":"Pontedeume",
    "sg:orig_category":"Abogados",
    "sg:phone":"+34 981 43 12 62",
    "sg:postcode":"15600",
    "sg:province":"A Coru\u00f1a",
    "wof:name":"Vilari\u00f1o Gomez Agustin Luis",
    "wof:placetype":"venue"
},
  "geometry": {"coordinates":[-8.1708288193,43.4067802429],"type":"Point"}
}