{
  "type": "Feature",
  "properties": {
    "iso:country":"ES",
    "sg:address":"Carr Muntanya, De, 2",
    "sg:city":"Consell",
    "sg:orig_category":"Productores Recolectores, Venta Directa De Vinos",
    "sg:phone":"+34 971 62 26 73",
    "sg:postcode":"07330",
    "sg:province":"Islas Baleares",
    "wof:name":"Herederos Hermanos Ribas S.a.",
    "wof:placetype":"venue"
},
  "geometry": {"coordinates":[2.8144240379,39.6675643921],"type":"Point"}
}