{
  "type": "Feature",
  "properties": {
    "addr:full":"Calle de Alerce, 5 Madrid Madrid 28041",
    "addr:housenumber":"5",
    "addr:postcode":"28041",
    "addr:street":"Calle De Alerce",
    "iso:country":"ES",
    "sg:address":"Calle de Alerce, 5",
    "sg:city":"Madrid",
    "sg:orig_category":"Cl\u00cdnicas Dentales",
    "sg:phone":"+34 913 17 68 89",
    "sg:postcode":"28041",
    "sg:province":"Madrid",
    "wof:name":"Alma Medical S.l.",
    "wof:placetype":"venue"
},
  "geometry": {"coordinates":[-3.6955265999,40.3684616089],"type":"Point"}
}