{
  "type": "Feature",
  "properties": {
    "iso:country":"ES",
    "sg:address":"Calle de Iriarte, 16",
    "sg:city":"Santa Cruz De Tenerife",
    "sg:orig_category":"Supermercados Y Hipermercados",
    "sg:phone":"+34 922 27 93 61",
    "sg:postcode":"38004",
    "sg:province":"Santa Cruz De Tenerife",
    "wof:name":"Canino Gonzalez Maria Concepcion",
    "wof:placetype":"venue"
},
  "geometry": {"coordinates":[-16.2570667267,28.4669094086],"type":"Point"}
}