{
  "type": "Feature",
  "properties": {
    "addr:full":"Ctra Granada, Km. 0040,2 Jaen Ja\u00e9n 23001",
    "addr:postcode":"23001",
    "addr:street":"Ctra Granada Km. 0040,2 Jaen Jae\u0301N",
    "iso:country":"ES",
    "sg:address":"Ctra Granada, Km. 0040,2",
    "sg:city":"Jaen",
    "sg:orig_category":"Fabricaci\u00d3n, Venta De Cuadros, Accesorios Para Enmarcar",
    "sg:phone":"+34 953 23 20 98",
    "sg:postcode":"23001",
    "sg:province":"Ja\u00e9n",
    "sg:website":"www.moldurascardenas.com",
    "wof:name":"Molduras Cardenas S.l.",
    "wof:placetype":"venue"
},
  "geometry": {"coordinates":[-3.7865190506,37.7690734863],"type":"Point"}
}