{
  "type": "Feature",
  "properties": {
    "iso:country":"ES",
    "sg:address":"Calle de Graciano, S/n",
    "sg:city":"Merida",
    "sg:orig_category":"Ense\u00d1anza, Formaci\u00d3n Profesional: Aprendizaje",
    "sg:phone":"+34 924 31 73 09",
    "sg:postcode":"06800",
    "sg:province":"Badajoz",
    "wof:name":"Consorcio Ciudad Monumental De Merida",
    "wof:placetype":"venue"
},
  "geometry": {"coordinates":[-6.3451800346,38.9135932922],"type":"Point"}
}