{
  "type": "Feature",
  "properties": {
    "addr:full":"Calle de Pinar, 6 Madrid Madrid 28006",
    "addr:housenumber":"6",
    "addr:postcode":"28006",
    "addr:street":"Calle De Pinar",
    "iso:country":"ES",
    "sg:address":"Calle de Pinar, 6",
    "sg:city":"Madrid",
    "sg:orig_category":"Molduras, Junquillos, Listones Y Molduras Perforadas",
    "sg:phone":"+34 914 11 16 08",
    "sg:postcode":"28006",
    "sg:province":"Madrid",
    "wof:name":"Pinar Pigmalion S. L.",
    "wof:placetype":"venue"
},
  "geometry": {"coordinates":[-3.688380003,40.4369773865],"type":"Point"}
}