{
  "type": "Feature",
  "properties": {
    "addr:full":"Avda Enekuri, 8 Bilbao Vizcaya 48014",
    "addr:housenumber":"8",
    "addr:postcode":"48014",
    "addr:street":"Avda Enekuri",
    "iso:country":"ES",
    "sg:address":"Avda Enekuri, 8",
    "sg:city":"Bilbao",
    "sg:orig_category":"Laboratorios Y Trabajos De Fotograf\u00cda, V\u00cddeo Y Cine",
    "sg:phone":"+34 944 47 34 03",
    "sg:postcode":"48014",
    "sg:province":"Vizcaya",
    "wof:name":"Foto Europa S. A.",
    "wof:placetype":"venue"
},
  "geometry": {"coordinates":[-2.9487020969,43.2725105286],"type":"Point"}
}