{
  "type": "Feature",
  "properties": {
    "addr:full":"Calle de Doctor Fleming, 62 S. Juan Puerto Huelva 21610",
    "addr:housenumber":"62",
    "addr:postcode":"21610",
    "addr:street":"Calle De Doctor Fleming;S. Juan Puerto",
    "iso:country":"ES",
    "sg:address":"Calle de Doctor Fleming, 62",
    "sg:city":"S. Juan Puerto",
    "sg:orig_category":"Transporte En General",
    "sg:phone":"+34 959 36 70 73",
    "sg:postcode":"21610",
    "sg:province":"Huelva",
    "wof:name":"Perez Martinez Rafael",
    "wof:placetype":"venue"
},
  "geometry": {"coordinates":[-6.8414154053,37.3194847107],"type":"Point"}
}