{
  "type": "Feature",
  "properties": {
    "iso:country":"ES",
    "sg:address":"Calle de Gabriel Y Galan, 13",
    "sg:city":"Ca\u00f1averal",
    "sg:classifiers":[
        {
            "category":"Taxi",
            "type":"Transportation"
        }
    ],
    "sg:phone":"+34 927 30 02 45",
    "sg:postcode":"10820",
    "sg:province":"C\u00e1ceres",
    "wof:name":"Serrano Hernandez Pablo",
    "wof:placetype":"venue"
},
  "geometry": {"coordinates":[-6.3896479607,39.7920074463],"type":"Point"}
}