{
  "type": "Feature",
  "properties": {
    "addr:full":"Calle de Emilio Castelar, 40 Novelda Alicante 03660",
    "addr:housenumber":"40",
    "addr:postcode":"03660",
    "addr:street":"Calle De Emilio Castelar",
    "iso:country":"ES",
    "sg:address":"Calle de Emilio Castelar, 40",
    "sg:city":"Novelda",
    "sg:orig_category":"Art\u00cdculos De Regalo (al Por Menor)",
    "sg:phone":"+34 965 60 18 96",
    "sg:postcode":"03660",
    "sg:province":"Alicante",
    "wof:name":"Llobregat Arnau Maria Luisa",
    "wof:placetype":"venue"
},
  "geometry": {"coordinates":[-0.7667959929,38.3850860596],"type":"Point"}
}