{
  "type": "Feature",
  "properties": {
    "addr:full":"Avda Ramon Y Cajal, 9 Catarroja Valencia 46470",
    "addr:housenumber":"9",
    "addr:postcode":"46470",
    "addr:street":"Avda Ramon Y Cajal",
    "iso:country":"ES",
    "sg:address":"Avda Ramon Y Cajal, 9",
    "sg:city":"Catarroja",
    "sg:orig_category":"Pod\u00d3logos: Pedicuros",
    "sg:phone":"+34 961 26 12 21",
    "sg:postcode":"46470",
    "sg:province":"Valencia",
    "wof:name":"Sacristan Bosch Juan Jose",
    "wof:placetype":"venue"
},
  "geometry": {"coordinates":[-0.4028030038,39.4047164917],"type":"Point"}
}