{
  "type": "Feature",
  "properties": {
    "addr:full":"Calle de Coso, 98 Zaragoza Zaragoza 50001",
    "addr:housenumber":"98",
    "addr:postcode":"50001",
    "addr:street":"Calle De Coso",
    "iso:country":"ES",
    "sg:address":"Calle de Coso, 98",
    "sg:city":"Zaragoza",
    "sg:orig_category":"Sociedades, Compa\u00d1\u00cdas Aseguradoras",
    "sg:phone":"+34 976 23 42 14",
    "sg:postcode":"50001",
    "sg:province":"Zaragoza",
    "sg:website":"www.segurosbilbao.com",
    "wof:name":"Bilbao Compa\u00f1ia Anonima De Seguros S.a.",
    "wof:placetype":"venue"
},
  "geometry": {"coordinates":[-0.876989007,41.6508293152],"type":"Point"}
}