{
  "type": "Feature",
  "properties": {
    "iso:country":"ES",
    "sg:address":"Avda Teodomiro, 16",
    "sg:city":"Orihuela",
    "sg:orig_category":"M\u00c9dicos: Oftalmolog\u00cda",
    "sg:phone":"+34 965 30 57 77",
    "sg:postcode":"03300",
    "sg:province":"Alicante",
    "wof:name":"Dapena Urcola Maria Del Pilar",
    "wof:placetype":"venue"
},
  "geometry": {"coordinates":[-0.9455459714,38.0812797546],"type":"Point"}
}