{
  "type": "Feature",
  "properties": {
    "addr:full":"Rua Casiano Martinez, 30 Vigo Pontevedra 36208",
    "addr:housenumber":"30",
    "addr:postcode":"36208",
    "addr:street":"Rua Casiano Martinez",
    "iso:country":"ES",
    "sg:address":"Rua Casiano Martinez, 30",
    "sg:city":"Vigo",
    "sg:orig_category":"Promotores Constructores",
    "sg:phone":"+34 986 20 00 50",
    "sg:postcode":"36208",
    "sg:province":"Pontevedra",
    "wof:name":"Promociones Valentin Veiga S.l.",
    "wof:placetype":"venue"
},
  "geometry": {"coordinates":[-8.7563285828,42.2236785889],"type":"Point"}
}