{
  "type": "Feature",
  "properties": {
    "addr:full":"Rua Purificacion Saavedra, 10 Vigo Pontevedra 36207",
    "addr:housenumber":"10",
    "addr:postcode":"36207",
    "addr:street":"Rua Purificacion Saavedra",
    "iso:country":"ES",
    "sg:address":"Rua Purificacion Saavedra, 10",
    "sg:city":"Vigo",
    "sg:orig_category":"Confecci\u00d3n De Zapatos",
    "sg:phone":"+34 986 37 67 52",
    "sg:postcode":"36207",
    "sg:province":"Pontevedra",
    "wof:name":"Folgar Rey Severino",
    "wof:placetype":"venue"
},
  "geometry": {"coordinates":[-8.6999578476,42.2475738525],"type":"Point"}
}