{
  "type": "Feature",
  "properties": {
    "addr:full":"Avda Honduras, 20 Santander Cantabria 39005",
    "addr:housenumber":"20",
    "addr:postcode":"39005",
    "addr:street":"Avda Honduras",
    "iso:country":"ES",
    "sg:address":"Avda Honduras, 20",
    "sg:city":"Santander",
    "sg:orig_category":"Caf\u00c9s, Bares, Cervecer\u00cdas",
    "sg:phone":"+34 942 31 09 03",
    "sg:postcode":"39005",
    "sg:province":"Cantabria",
    "wof:name":"Penagos Abascal Maria Nieves",
    "wof:placetype":"venue"
},
  "geometry": {"coordinates":[-3.8022251129,43.469745636],"type":"Point"}
}