{
  "type": "Feature",
  "properties": {
    "addr:full":"Calle de Isabel La Catolica, S/n Landete Cuenca 16330",
    "addr:housenumber":"s / n",
    "addr:postcode":"16330",
    "addr:street":"Calle De Isabel La Catolica",
    "iso:country":"ES",
    "sg:address":"Calle de Isabel La Catolica, S/n",
    "sg:city":"Landete",
    "sg:orig_category":"Cerrajer\u00cda, Ferrallista",
    "sg:phone":"+34 969 36 10 83",
    "sg:postcode":"16330",
    "sg:province":"Cuenca",
    "wof:name":"Maderas Mu\u00f1oz S.a.",
    "wof:placetype":"venue"
},
  "geometry": {"coordinates":[-1.3629449606,39.9051208496],"type":"Point"}
}