{
  "type": "Feature",
  "properties": {
    "addr:full":"Avda Castilla, 10 Aranda Duero Burgos 09400",
    "addr:housenumber":"10",
    "addr:postcode":"09400",
    "addr:street":"Avda Castilla",
    "iso:country":"ES",
    "sg:address":"Avda Castilla, 10",
    "sg:city":"Aranda Duero",
    "sg:orig_category":"Audiovisuales (producci\u00d3n, Edici\u00d3n, Realizaci\u00d3n)",
    "sg:phone":"+34 947 51 01 60",
    "sg:postcode":"09400",
    "sg:province":"Burgos",
    "sg:website":"www.elitvideo.com",
    "wof:name":"Azua Vicente Carmen",
    "wof:placetype":"venue"
},
  "geometry": {"coordinates":[-3.6908369064,41.6687393188],"type":"Point"}
}