{
  "type": "Feature",
  "properties": {
    "addr:full":"Calle de Marques De San Esteban, 57 Gijon Asturias 33206",
    "addr:housenumber":"57",
    "addr:postcode":"33206",
    "addr:street":"Calle De Marques De San Esteban",
    "iso:country":"ES",
    "sg:address":"Calle de Marques De San Esteban, 57",
    "sg:city":"Gijon",
    "sg:orig_category":"Inmobiliaria (agencias)",
    "sg:phone":"+34 985 34 11 69",
    "sg:postcode":"33206",
    "sg:province":"Asturias",
    "wof:name":"General Mercantil Inmobiliaria S.a.",
    "wof:placetype":"venue"
},
  "geometry": {"coordinates":[-5.671298027,43.5411949158],"type":"Point"}
}