{
  "type": "Feature",
  "properties": {
    "addr:full":"Carrer de Vilanova, 15 Manresa Barcelona 08241",
    "addr:housenumber":"15",
    "addr:postcode":"08241",
    "addr:street":"Carrer De Vilanova",
    "iso:country":"ES",
    "sg:address":"Carrer de Vilanova, 15",
    "sg:city":"Manresa",
    "sg:orig_category":"Bares, Piano",
    "sg:phone":"+34 938 76 84 41",
    "sg:postcode":"08241",
    "sg:province":"Barcelona",
    "wof:name":"Fernandez Roses S.c.p.",
    "wof:placetype":"venue"
},
  "geometry": {"coordinates":[1.8240499496,41.7231712341],"type":"Point"}
}