{
  "type": "Feature",
  "properties": {
    "iso:country":"ES",
    "sg:address":"Calle de Peru, 3",
    "sg:city":"Majadahonda",
    "sg:orig_category":"Empresarios",
    "sg:phone":"+34 916 39 75 41",
    "sg:postcode":"28220",
    "sg:province":"Madrid",
    "sg:website":"www.maderasjumilla.com",
    "wof:name":"Maderas Jumilla S.a",
    "wof:placetype":"venue"
},
  "geometry": {"coordinates":[-3.8696479797,40.4743080139],"type":"Point"}
}