{
  "type": "Feature",
  "properties": {
    "addr:full":"Poligono Cometa, S/n El Vendrell Tarragona 43700",
    "addr:housenumber":"s / n",
    "addr:postcode":"43700",
    "addr:street":"Cometa",
    "iso:country":"ES",
    "sg:address":"Poligono Cometa, S/n",
    "sg:city":"El Vendrell",
    "sg:orig_category":"Goma: Materias Primas (producci\u00d3n, Distribuci\u00d3n)",
    "sg:phone":"+34 977 66 20 10",
    "sg:postcode":"43700",
    "sg:province":"Tarragona",
    "wof:name":"Europlastic Del Penedes S.l.",
    "wof:placetype":"venue"
},
  "geometry": {"coordinates":[1.5344400406,41.2193107605],"type":"Point"}
}