{
  "type": "Feature",
  "properties": {
    "iso:country":"ES",
    "sg:address":"Calle de San Jose, S/n",
    "sg:city":"Huelva",
    "sg:orig_category":"Bisuter\u00cda, Joyer\u00cda, Relojer\u00cda (al Por Menor)",
    "sg:phone":"+34 959 25 24 63",
    "sg:postcode":"21002",
    "sg:province":"Huelva",
    "wof:name":"Joyeria San Jose S.l.",
    "wof:placetype":"venue"
},
  "geometry": {"coordinates":[-6.9541401863,37.2591590881],"type":"Point"}
}