{
  "type": "Feature",
  "properties": {
    "addr:full":"Calle de Pajaritos, 19 Torrejon Ardoz Madrid 28850",
    "addr:housenumber":"19",
    "addr:postcode":"28850",
    "addr:street":"Calle De Pajaritos",
    "iso:country":"ES",
    "sg:address":"Calle de Pajaritos, 19",
    "sg:city":"Torrejon Ardoz",
    "sg:orig_category":"Artes Gr\u00c1ficas, Artes Pl\u00c1sticas (curso)",
    "sg:phone":"+34 916 77 71 15",
    "sg:postcode":"28850",
    "sg:province":"Madrid",
    "wof:name":"Studio Xxi Soluciones Graficas",
    "wof:placetype":"venue"
},
  "geometry": {"coordinates":[-3.45520401,40.4618797302],"type":"Point"}
}