{
  "type": "Feature",
  "properties": {
    "iso:country":"ES",
    "sg:address":"Calle de Federico Tapia, 11",
    "sg:city":"Coru\u00d1a",
    "sg:orig_category":"Agencias Y Agentes Comerciales, Representantes",
    "sg:phone":"+34 981 12 03 38",
    "sg:postcode":"15005",
    "sg:province":"La Coru\u00f1a",
    "wof:name":"Grupo Plaza Galicia Joyas S.a.",
    "wof:placetype":"venue"
},
  "geometry": {"coordinates":[-8.4064121246,43.3641929626],"type":"Point"}
}