{
  "type": "Feature",
  "properties": {
    "addr:full":"Carrer de Pirineus, 103 Barbera Valles Barcelona 08210",
    "addr:housenumber":"103",
    "addr:postcode":"08210",
    "addr:street":"Carrer De Pirineus",
    "iso:country":"ES",
    "sg:address":"Carrer de Pirineus, 103",
    "sg:city":"Barbera Valles",
    "sg:orig_category":"Molduras, Junquillos, Listones Y Molduras Perforadas",
    "sg:phone":"+34 937 18 05 85",
    "sg:postcode":"08210",
    "sg:province":"Barcelona",
    "wof:name":"Fabregat Julian Florentina",
    "wof:placetype":"venue"
},
  "geometry": {"coordinates":[2.1138279438,41.5137939453],"type":"Point"}
}