{
  "type": "Feature",
  "properties": {
    "addr:full":"Ctra Mazarron, Km. 0005,0 \u00d1orica Murcia 30850",
    "addr:postcode":"30850",
    "addr:street":"Ctra Mazarron Km. 0005,0",
    "iso:country":"ES",
    "sg:address":"Ctra Mazarron, Km. 0005,0",
    "sg:city":"\u00d1orica",
    "sg:orig_category":"Artes Gr\u00c1ficas, Artes Pl\u00c1sticas: Material Y Suministros (al Por Menor)",
    "sg:phone":"+34 968 43 63 48",
    "sg:postcode":"30850",
    "sg:province":"Murcia",
    "wof:name":"Sociedad De Fomento Agricola Castellonense S.a.",
    "wof:placetype":"venue"
},
  "geometry": {"coordinates":[-1.5030390024,37.7726860046],"type":"Point"}
}