{
  "type": "Feature",
  "properties": {
    "iso:country":"ES",
    "sg:address":"Calle de Beethoven, 3",
    "sg:city":"Valencia",
    "sg:orig_category":"Peluquer\u00cdas",
    "sg:phone":"+34 963 57 42 50",
    "sg:postcode":"46017",
    "sg:province":"Valencia",
    "wof:name":"Adri Peluqueros S.l.",
    "wof:placetype":"venue"
},
  "geometry": {"coordinates":[-0.3897106051,39.4499320984],"type":"Point"}
}