{
  "type": "Feature",
  "properties": {
    "addr:full":"Calle de Nicolas Peinado, 45 Landete Cuenca 16330",
    "addr:housenumber":"45",
    "addr:postcode":"16330",
    "addr:street":"Calle De Nicolas Peinado",
    "iso:country":"ES",
    "sg:address":"Calle de Nicolas Peinado, 45",
    "sg:city":"Landete",
    "sg:orig_category":"Promotores Constructores",
    "sg:phone":"+34 969 36 12 73",
    "sg:postcode":"16330",
    "sg:province":"Cuenca",
    "wof:name":"Construcciones Amador Miguez Garrido S.l.",
    "wof:placetype":"venue"
},
  "geometry": {"coordinates":[-1.3674689531,39.9039459229],"type":"Point"}
}