{
  "type": "Feature",
  "properties": {
    "addr:full":"Pe\u00f1uelas, 21 Porcuna Ja\u00e9n 23790",
    "addr:housenumber":"21",
    "addr:postcode":"23790",
    "addr:street":"Pen\u0303Uelas",
    "iso:country":"ES",
    "sg:address":"Pe\u00f1uelas, 21",
    "sg:city":"Porcuna",
    "sg:orig_category":"Reposter\u00cdas",
    "sg:phone":"+34 953 54 64 01",
    "sg:postcode":"23790",
    "sg:province":"Ja\u00e9n",
    "wof:name":"Garcia Ure\u00f1a Jose Maria",
    "wof:placetype":"venue"
},
  "geometry": {"coordinates":[-4.2128338814,37.8397483826],"type":"Point"}
}