{
  "type": "Feature",
  "properties": {
    "addr:full":"Carrer de Tarragona, 22 Gava Barcelona 08850",
    "addr:housenumber":"22",
    "addr:postcode":"08850",
    "addr:street":"Carrer De Tarragona",
    "iso:country":"ES",
    "sg:address":"Carrer de Tarragona, 22",
    "sg:city":"Gava",
    "sg:orig_category":"Albergues",
    "sg:phone":"+34 933 25 96 04",
    "sg:postcode":"08850",
    "sg:province":"Barcelona",
    "wof:name":"Sonia Regalo S.l.",
    "wof:placetype":"venue"
},
  "geometry": {"coordinates":[2.0125100613,41.2997894287],"type":"Point"}
}