{
  "type": "Feature",
  "properties": {
    "iso:country":"ES",
    "sg:address":"Sant Manuel, 27",
    "sg:city":"Ametlla Mar",
    "sg:orig_category":"Empresas De Carpinter\u00cda De Madera",
    "sg:phone":"+34 977 45 60 82",
    "sg:postcode":"43860",
    "sg:province":"Tarragona",
    "wof:name":"Carpinteria Y Muebles Hermanos Gaseni S.c.p.",
    "wof:placetype":"venue"
},
  "geometry": {"coordinates":[0.7992730141,40.8853607178],"type":"Point"}
}