{
  "type": "Feature",
  "properties": {
    "iso:country":"ES",
    "sg:address":"Calle de Dindurra, 18",
    "sg:city":"Gijon",
    "sg:orig_category":"Cl\u00cdnicas M\u00c9dicas",
    "sg:phone":"+34 985 36 99 26",
    "sg:postcode":"33202",
    "sg:province":"Asturias",
    "wof:name":"Ordieres Martin Mercedes",
    "wof:placetype":"venue"
},
  "geometry": {"coordinates":[-5.658311367,43.5384216309],"type":"Point"}
}