{
  "type": "Feature",
  "properties": {
    "addr:full":"Astigarrako Bidea, 4 Ugaldetxo Guip\u00f9zcoa 20180",
    "addr:housenumber":"4",
    "addr:postcode":"20180",
    "addr:street":"Astigarrako Bidea;Guipu\u0300Zcoa",
    "iso:country":"ES",
    "sg:address":"Astigarrako Bidea, 4",
    "sg:city":"Ugaldetxo",
    "sg:orig_category":"Embalajes",
    "sg:phone":"+34 943 49 07 03",
    "sg:postcode":"20180",
    "sg:province":"Guip\u00f9zcoa",
    "wof:name":"Sociedad Hispanica De Desarrollo S.a.",
    "wof:placetype":"venue"
},
  "geometry": {"coordinates":[-1.8629590273,43.2992401123],"type":"Point"}
}