{
  "type": "Feature",
  "properties": {
    "addr:full":"Poli Poligono Industrial Quemadas, S/n Quemadas C\u00f3rdoba 14014",
    "addr:housenumber":"s",
    "addr:postcode":"14014",
    "addr:street":"Poligono Industrial Quemadas;/ N Quemadas Co\u0301Rdoba",
    "iso:country":"ES",
    "sg:address":"Poli Poligono Industrial Quemadas, S/n",
    "sg:city":"Quemadas",
    "sg:orig_category":"Puertas Y Portales",
    "sg:phone":"+34 957 32 62 91",
    "sg:postcode":"14014",
    "sg:province":"C\u00f3rdoba",
    "wof:name":"Sinelec Fire Proteccion S.l.",
    "wof:placetype":"venue"
},
  "geometry": {"coordinates":[-4.7624139786,37.9240608215],"type":"Point"}
}