{
  "type": "Feature",
  "properties": {
    "iso:country":"ES",
    "sg:address":"Calle de Nueva, 2",
    "sg:city":"Palma Rio",
    "sg:orig_category":"Ebanister\u00cda",
    "sg:phone":"+34 957 71 00 86",
    "sg:postcode":"14700",
    "sg:province":"C\u00f3rdoba",
    "wof:name":"Ruiz Barrientos Manuel",
    "wof:placetype":"venue"
},
  "geometry": {"coordinates":[-5.2800240517,37.6983833313],"type":"Point"}
}