{
  "type": "Feature",
  "properties": {
    "iso:country":"ES",
    "sg:address":"Psaj Marino Luis Cordoba Arce, 8",
    "sg:city":"Cordoba",
    "sg:orig_category":"Suministros Para Hoteles",
    "sg:phone":"+34 957 46 61 36",
    "sg:postcode":"14011",
    "sg:province":"C\u00f3rdoba",
    "wof:name":"Mu\u00f1oz Gonzalez Francisco",
    "wof:placetype":"venue"
},
  "geometry": {"coordinates":[-4.805311203,37.8917770386],"type":"Point"}
}