{
  "type": "Feature",
  "properties": {
    "addr:full":"Plaz Juez Borrull, 13 Castellon Castell\u00f3n 12003",
    "addr:housenumber":"13",
    "addr:postcode":"12003",
    "addr:street":"Plaz;Borrull",
    "iso:country":"ES",
    "sg:address":"Plaz Juez Borrull, 13",
    "sg:city":"Castellon",
    "sg:orig_category":"Abogados",
    "sg:phone":"+34 964 26 11 22",
    "sg:postcode":"12003",
    "sg:province":"Castell\u00f3n",
    "wof:name":"Ucedo Babiloni Isabel",
    "wof:placetype":"venue"
},
  "geometry": {"coordinates":[-0.0346099995,39.9833869934],"type":"Point"}
}