{
  "type": "Feature",
  "properties": {
    "addr:full":"Calle de Hermosilla, 7 Madrid Madrid 28001",
    "addr:housenumber":"7",
    "addr:postcode":"madrid;28001",
    "addr:street":"Calle De Hermosilla",
    "iso:country":"ES",
    "sg:address":"Calle de Hermosilla, 7",
    "sg:city":"Madrid",
    "sg:orig_category":"Procuradores",
    "sg:phone":"+34 915 75 24 32",
    "sg:postcode":"28001",
    "sg:province":"Madrid",
    "wof:name":"Alvarez Wiese Luis Fernando",
    "wof:placetype":"venue"
},
  "geometry": {"coordinates":[-3.6880698204,40.4265632629],"type":"Point"}
}