{
  "type": "Feature",
  "properties": {
    "addr:full":"Pase Marcelino Andaluz Vergara, 5 Illueca Zaragoza 50250",
    "addr:housenumber":"5",
    "addr:postcode":"50250",
    "addr:street":"Vergara",
    "iso:country":"ES",
    "sg:address":"Pase Marcelino Andaluz Vergara, 5",
    "sg:city":"Illueca",
    "sg:orig_category":"Tintorer\u00cdas, Limpieza En Seco",
    "sg:phone":"+34 976 82 25 46",
    "sg:postcode":"50250",
    "sg:province":"Zaragoza",
    "wof:name":"Gea Roy Esteban",
    "wof:placetype":"venue"
},
  "geometry": {"coordinates":[-1.6291790009,41.5365447998],"type":"Point"}
}