{
  "type": "Feature",
  "properties": {
    "iso:country":"ES",
    "sg:address":"Calle de San Gregorio, 8",
    "sg:city":"Torres Berrellen",
    "sg:orig_category":"Guarder\u00cdas",
    "sg:phone":"+34 976 65 10 59",
    "sg:postcode":"50693",
    "sg:province":"Zaragoza",
    "wof:name":"Ayuntamiento De Torres De Berrellen",
    "wof:placetype":"venue"
},
  "geometry": {"coordinates":[-1.0641504526,41.7555389404],"type":"Point"}
}