{
  "type": "Feature",
  "properties": {
    "addr:full":"Polig. Ind. O Morelle, 20 San Xulian Veiga Lugo 27614",
    "addr:housenumber":"20",
    "addr:postcode":"27614",
    "addr:street":"Polig. Ind. O Morelle",
    "iso:country":"ES",
    "sg:address":"Polig. Ind. O Morelle, 20",
    "sg:city":"San Xulian Veiga",
    "sg:orig_category":"Papel (al Por Mayor)",
    "sg:phone":"+34 982 53 04 56",
    "sg:postcode":"27614",
    "sg:province":"Lugo",
    "wof:name":"Sarriplas C.b.",
    "wof:placetype":"venue"
},
  "geometry": {"coordinates":[-7.3574109077,42.8505249023],"type":"Point"}
}