{
  "type": "Feature",
  "properties": {
    "iso:country":"ES",
    "sg:address":"Calle de Cordoba, 2",
    "sg:city":"Cazalla Sierra",
    "sg:orig_category":"Alimentaci\u00d3n General (al Por Menor)",
    "sg:phone":"+34 954 88 41 43",
    "sg:postcode":"41370",
    "sg:province":"Sevilla",
    "wof:name":"Duran Trujillo Jose Manuel",
    "wof:placetype":"venue"
},
  "geometry": {"coordinates":[-5.7595038414,37.9382820129],"type":"Point"}
}