{
  "type": "Feature",
  "properties": {
    "iso:country":"ES",
    "sg:address":"Calle de Cabo De Gata, 21",
    "sg:city":"Cap Blanc",
    "sg:orig_category":"Inmobiliaria (agencias)",
    "sg:phone":"+34 965 74 91 93",
    "sg:postcode":"03725",
    "sg:province":"Alicante",
    "wof:name":"Vilars Bel Air S.l.",
    "wof:placetype":"venue"
},
  "geometry": {"coordinates":[0.113682799,38.6757049561],"type":"Point"}
}