{
  "type": "Feature",
  "properties": {
    "addr:full":"Plaz Constitucion (de La), 9 Utrera Sevilla 41710",
    "addr:postcode":"41710",
    "iso:country":"ES",
    "sg:address":"Plaz Constitucion (de La), 9",
    "sg:city":"Utrera",
    "sg:orig_category":"Juegos Y Juguetes (al Por Menor)",
    "sg:phone":"+34 954 86 15 10",
    "sg:postcode":"41710",
    "sg:province":"Sevilla",
    "wof:name":"Garcia Cabello Salvador",
    "wof:placetype":"venue"
},
  "geometry": {"coordinates":[-5.7829079628,37.1816825867],"type":"Point"}
}