{
  "type": "Feature",
  "properties": {
    "addr:full":"Calle de Garcia Carrera, 41 Cadiz C\u00e1diz 11009",
    "addr:postcode":"11009",
    "addr:street":"Calle De Garcia Carrera 41;Ca\u0301Diz",
    "iso:country":"ES",
    "sg:address":"Calle de Garcia Carrera, 41",
    "sg:city":"Cadiz",
    "sg:orig_category":"Estancos",
    "sg:phone":"+34 956 25 02 52",
    "sg:postcode":"11009",
    "sg:province":"C\u00e1diz",
    "wof:name":"Luna Mateos Maria Del Mar",
    "wof:placetype":"venue"
},
  "geometry": {"coordinates":[-6.2762970924,36.5104179382],"type":"Point"}
}