{
  "type": "Feature",
  "properties": {
    "addr:full":"Carrer de Jota, 136 Barcelona Barcelona 08016",
    "addr:housenumber":"136",
    "addr:postcode":"08016",
    "addr:street":"Carrer De Jota",
    "iso:country":"ES",
    "sg:address":"Carrer de Jota, 136",
    "sg:city":"Barcelona",
    "sg:orig_category":"Peluquer\u00cdas, Peluquer\u00cda Mixta",
    "sg:phone":"+34 934 08 71 76",
    "sg:postcode":"08016",
    "sg:province":"Barcelona",
    "wof:name":"Peluqueria Erika S.c.p.",
    "wof:placetype":"venue"
},
  "geometry": {"coordinates":[2.176197052,41.4296607971],"type":"Point"}
}