{
  "type": "Feature",
  "properties": {
    "addr:full":"Calle de Tesalonica, 1 Sevilla Sevilla 41007",
    "addr:housenumber":"1",
    "addr:postcode":"41007",
    "addr:street":"Calle De Tesalonica",
    "iso:country":"ES",
    "sg:address":"Calle de Tesalonica, 1",
    "sg:city":"Sevilla",
    "sg:orig_category":"Artes Gr\u00c1ficas, Artes Pl\u00c1sticas: Material Y Suministros (al Por Menor)",
    "sg:phone":"+34 954 52 97 36",
    "sg:postcode":"41007",
    "sg:province":"Sevilla",
    "wof:name":"Maf S.l.",
    "wof:placetype":"venue"
},
  "geometry": {"coordinates":[-5.9584341049,37.3908157349],"type":"Point"}
}