{
  "type": "Feature",
  "properties": {
    "iso:country":"ES",
    "sg:address":"Carrer de Cabanes, 40",
    "sg:city":"Barcelona",
    "sg:orig_category":"Aparcamientos (infraestructuras, Accesorios)",
    "sg:phone":"+34 934 42 20 62",
    "sg:postcode":"08004",
    "sg:province":"Barcelona",
    "wof:name":"Morenilla Guillem Manuel",
    "wof:placetype":"venue"
},
  "geometry": {"coordinates":[2.1696538925,41.372756958],"type":"Point"}
}