{
  "type": "Feature",
  "properties": {
    "iso:country":"ES",
    "sg:address":"Carrer de Santiago Rusi\u00d1ol, 34",
    "sg:city":"Mataro",
    "sg:orig_category":"Supermercados Y Hipermercados",
    "sg:phone":"+34 937 96 22 04",
    "sg:postcode":"08304",
    "sg:province":"Barcelona",
    "wof:name":"Garcia Caba Maria Josefa",
    "wof:placetype":"venue"
},
  "geometry": {"coordinates":[2.4513697624,41.548664093],"type":"Point"}
}