{
  "type": "Feature",
  "properties": {
    "iso:country":"ES",
    "sg:address":"Calle de Calixto Iii, 9",
    "sg:city":"Valencia",
    "sg:orig_category":"Bisuter\u00cda, Joyer\u00cda, Relojer\u00cda (al Por Menor)",
    "sg:phone":"+34 963 84 51 52",
    "sg:postcode":"46008",
    "sg:province":"Valencia",
    "wof:name":"Garcia Herrera Mari Carmen",
    "wof:placetype":"venue"
},
  "geometry": {"coordinates":[-0.3874672055,39.4719047546],"type":"Point"}
}