{
  "type": "Feature",
  "properties": {
    "addr:full":"Rua Ervedelo, 7 Ourense Ourense 32003",
    "addr:housenumber":"7",
    "addr:postcode":"32003",
    "addr:street":"Rua Ervedelo",
    "iso:country":"ES",
    "sg:address":"Rua Ervedelo, 7",
    "sg:city":"Ourense",
    "sg:orig_category":"Caf\u00c9s, Bares, Cervecer\u00cdas",
    "sg:phone":"+34 988 25 05 71",
    "sg:postcode":"32003",
    "sg:province":"Ourense",
    "wof:name":"Gonzalez Rodriguez Narciso",
    "wof:placetype":"venue"
},
  "geometry": {"coordinates":[-7.8674278259,42.3396720886],"type":"Point"}
}