{
  "type": "Feature",
  "properties": {
    "iso:country":"ES",
    "sg:address":"Carr Josep Coroleu, 66",
    "sg:city":"Vilanova I La Geltru",
    "sg:orig_category":"Caf\u00c9s, Bares, Cervecer\u00cdas",
    "sg:phone":"+34 938 10 30 02",
    "sg:postcode":"08800",
    "sg:province":"Barcelona",
    "wof:name":"Pleguezuelos Hernandez Jose",
    "wof:placetype":"venue"
},
  "geometry": {"coordinates":[1.7268999815,41.2211303711],"type":"Point"}
}