{
  "type": "Feature",
  "properties": {
    "iso:country":"ES",
    "sg:address":"Calle de Sor Valentina Miron, S/n",
    "sg:city":"Plasencia",
    "sg:orig_category":"Electricidad, Electr\u00d3nica: Suministros (al Por Menor)",
    "sg:phone":"+34 927 42 55 28",
    "sg:postcode":"10600",
    "sg:province":"C\u00e1ceres",
    "wof:name":"Disaf C.b.",
    "wof:placetype":"venue"
},
  "geometry": {"coordinates":[-6.0880842209,40.0340690613],"type":"Point"}
}