{
  "type": "Feature",
  "properties": {
    "addr:full":"Emilio Arrieta, 10 Iru\u00f1a Navarra 31002",
    "addr:housenumber":"10",
    "addr:postcode":"31002",
    "addr:street":"Emilio Arrieta",
    "iso:country":"ES",
    "sg:address":"Emilio Arrieta, 10",
    "sg:city":"Iru\u00f1a",
    "sg:orig_category":"Bisuter\u00cda, Joyer\u00cda, Relojer\u00cda (al Por Menor)",
    "sg:phone":"+34 948 22 60 08",
    "sg:postcode":"31002",
    "sg:province":"Navarra",
    "wof:name":"Bunigem S.l.",
    "wof:placetype":"venue"
},
  "geometry": {"coordinates":[-1.6410720348,42.8140983582],"type":"Point"}
}