{
  "type": "Feature",
  "properties": {
    "addr:full":"Barr Escuelas (las), S/n Pedre\u00f1a Cantabria 39130",
    "addr:postcode":"39130",
    "addr:street":"Las S / N",
    "iso:country":"ES",
    "sg:address":"Barr Escuelas (las), S/n",
    "sg:city":"Pedre\u00f1a",
    "sg:orig_category":"Asociaciones, Organismos Culturales Y Socioeducativos",
    "sg:phone":"+34 942 50 02 37",
    "sg:postcode":"39130",
    "sg:province":"Cantabria",
    "wof:name":"Asociacion 3 Edad",
    "wof:placetype":"venue"
},
  "geometry": {"coordinates":[-3.7676358223,43.4447021484],"type":"Point"}
}