{
  "type": "Feature",
  "properties": {
    "iso:country":"ES",
    "sg:address":"Calle de Maria Auxiliadora, 47",
    "sg:city":"Palma Condado",
    "sg:orig_category":"Agencias Y Agentes Comerciales, Representantes",
    "sg:phone":"+34 959 40 16 91",
    "sg:postcode":"21700",
    "sg:province":"Huelva",
    "wof:name":"Imagen 21 Condado S.l.",
    "wof:placetype":"venue"
},
  "geometry": {"coordinates":[-6.5525560379,37.3835906982],"type":"Point"}
}