{
  "type": "Feature",
  "properties": {
    "iso:country":"ES",
    "sg:address":"Calle de Claveles, 4",
    "sg:city":"Valle De Los Rosales",
    "sg:orig_category":"Fabricaci\u00d3n, Venta, Instalaci\u00d3n De R\u00d3tulos, De R\u00d3tulos Luminosos",
    "sg:phone":"+34 918 16 25 41",
    "sg:postcode":"28690",
    "sg:province":"Madrid",
    "sg:website":"www.rmateos@zristom.com",
    "wof:name":"Zriston S.l",
    "wof:placetype":"venue"
},
  "geometry": {"coordinates":[-3.9798014164,40.4284477234],"type":"Point"}
}