{
  "type": "Feature",
  "properties": {
    "iso:country":"ES",
    "sg:address":"Calle de Rualasal, 13",
    "sg:city":"Santander",
    "sg:orig_category":"Panader\u00cdas, Panader\u00cdas",
    "sg:phone":"+34 942 22 66 28",
    "sg:postcode":"39001",
    "sg:province":"Cantabria",
    "wof:name":"Garcia Sobrino Angel Miguel",
    "wof:placetype":"venue"
},
  "geometry": {"coordinates":[-3.8064250946,43.4628562927],"type":"Point"}
}