{
  "type": "Feature",
  "properties": {
    "addr:full":"Calle de Eskurtze, 8 Bilbao Vizcaya 48012",
    "addr:housenumber":"8",
    "addr:postcode":"48012",
    "addr:street":"Calle De Eskurtze",
    "iso:country":"ES",
    "sg:address":"Calle de Eskurtze, 8",
    "sg:city":"Bilbao",
    "sg:orig_category":"Agentes Generales De Seguros",
    "sg:phone":"+34 944 21 67 84",
    "sg:postcode":"48012",
    "sg:province":"Vizcaya",
    "wof:name":"Bikain,  S.l.",
    "wof:placetype":"venue"
},
  "geometry": {"coordinates":[-2.9384419918,43.2521209717],"type":"Point"}
}