{
  "type": "Feature",
  "properties": {
    "iso:country":"ES",
    "sg:address":"Calle de Iglesia, 18",
    "sg:city":"Herencia",
    "sg:orig_category":"Carnicer\u00cdas, Carnicer\u00cdas",
    "sg:phone":"+34 926 57 23 17",
    "sg:postcode":"13640",
    "sg:province":"Ciudad Real",
    "wof:name":"Molina-prados Gomez-calcerrada Florencio",
    "wof:placetype":"venue"
},
  "geometry": {"coordinates":[-3.3535346985,39.3667869568],"type":"Point"}
}