{
  "type": "Feature",
  "properties": {
    "iso:country":"ES",
    "sg:address":"Calle de Aragon, 3",
    "sg:city":"Utrillas",
    "sg:orig_category":"Energ\u00cda Solar Y Nuevas Energ\u00cdas (equipo, Estudios)",
    "sg:phone":"+34 978 75 80 99",
    "sg:postcode":"44760",
    "sg:province":"Teruel",
    "wof:name":"Inspesol S.l.",
    "wof:placetype":"venue"
},
  "geometry": {"coordinates":[-0.8474975228,40.8128166199],"type":"Point"}
}