{
  "type": "Feature",
  "properties": {
    "iso:country":"ES",
    "sg:address":"Carrer de Campoamor, 66",
    "sg:city":"Barcelona",
    "sg:orig_category":"Pistas Y Clases De Tenis",
    "sg:phone":"+34 934 27 27 02",
    "sg:postcode":"08031",
    "sg:province":"Barcelona",
    "wof:name":"Club Tennis Horta",
    "wof:placetype":"venue"
},
  "geometry": {"coordinates":[2.1540501118,41.4354705811],"type":"Point"}
}