{
  "type": "Feature",
  "properties": {
    "addr:full":"Carrer de Bailen, 205 Barcelona Barcelona 08037",
    "addr:housenumber":"205",
    "addr:postcode":"08037",
    "addr:street":"Carrer De Bailen",
    "iso:country":"ES",
    "sg:address":"Carrer de Bailen, 205",
    "sg:city":"Barcelona",
    "sg:classifiers":[
        {
            "category":"Cinema",
            "subcategory":"Movie Theater",
            "type":"Entertainment"
        }
    ],
    "sg:phone":"+34 934 57 32 11",
    "sg:postcode":"08037",
    "sg:province":"Barcelona",
    "sg:tags":[
        "salas",
        "de",
        "cine"
    ],
    "sg:website":"www.laurenfilm.es",
    "wof:name":"Heptagonal Films S.l.",
    "wof:placetype":"venue"
},
  "geometry": {"coordinates":[2.1637210846,41.4020652771],"type":"Point"}
}