{
  "type": "Feature",
  "properties": {
    "addr:full":"Calle de Albert Einstein, 24 Palmas De Gran Canaria Las Palmas 35013",
    "addr:housenumber":"24",
    "addr:postcode":"35013",
    "addr:street":"Calle De Albert Einstein",
    "iso:country":"ES",
    "sg:address":"Calle de Albert Einstein, 24",
    "sg:city":"Palmas De Gran Canaria",
    "sg:orig_category":"Papel (al Por Mayor)",
    "sg:phone":"+34 928 41 98 34",
    "sg:postcode":"35013",
    "sg:province":"Las Palmas",
    "wof:name":"Impritex Artes Graficas S.l.",
    "wof:placetype":"venue"
},
  "geometry": {"coordinates":[-15.4511842728,28.0920619965],"type":"Point"}
}