{
  "type": "Feature",
  "properties": {
    "addr:full":"Calle de Llama (la), 36 Torrelavega Cantabria 39300",
    "addr:housenumber":"36",
    "addr:postcode":"39300",
    "addr:street":"Calle De Llama La",
    "iso:country":"ES",
    "sg:address":"Calle de Llama (la), 36",
    "sg:city":"Torrelavega",
    "sg:orig_category":"Asociaciones Humanitarias, De Cooperaci\u00d3n, De Acci\u00d3n Social",
    "sg:phone":"+34 942 80 82 17",
    "sg:postcode":"39300",
    "sg:province":"Cantabria",
    "wof:name":"Organizacion Impulsora De Discapacitados O.i.d.",
    "wof:placetype":"venue"
},
  "geometry": {"coordinates":[-4.0451130867,43.3504180908],"type":"Point"}
}