{
  "type": "Feature",
  "properties": {
    "iso:country":"ES",
    "sg:address":"Calle de Toledo, 54",
    "sg:city":"Madrid",
    "sg:orig_category":"Edici\u00d3n De Diarios, Revistas, Boletines",
    "sg:phone":"+34 913 65 17 84",
    "sg:postcode":"28005",
    "sg:province":"Madrid",
    "sg:website":"www.latinomadrid.es",
    "wof:name":"Ediciones Novapress S.l.",
    "wof:placetype":"venue"
},
  "geometry": {"coordinates":[-3.7094500065,40.4102630615],"type":"Point"}
}