{
  "type": "Feature",
  "properties": {
    "addr:full":"Avda Jimenez Delgado, 5 Malaga M\u00e1laga 29004",
    "addr:housenumber":"5",
    "addr:postcode":"29004",
    "addr:street":"Avda Jimenez Delgado;Ma\u0301Laga",
    "iso:country":"ES",
    "sg:address":"Avda Jimenez Delgado, 5",
    "sg:city":"Malaga",
    "sg:orig_category":"Comercio De Piezas De Recambio Y De Accesorios De Veh\u00cdculos, Veh\u00cdculos Industriales",
    "sg:phone":"+34 952 23 17 46",
    "sg:postcode":"29004",
    "sg:province":"M\u00e1laga",
    "wof:name":"Cadimerka S.l.",
    "wof:placetype":"venue"
},
  "geometry": {"coordinates":[-4.464993,36.6829986572],"type":"Point"}
}