{
  "type": "Feature",
  "properties": {
    "iso:country":"ES",
    "sg:address":"Calle de Castillo De Rena, 28",
    "sg:city":"Badajoz",
    "sg:orig_category":"M\u00c9dicos: Radioterapia (radioterapia Como Opci\u00d3n Oncol\u00d3gica)",
    "sg:phone":"+34 924 27 56 10",
    "sg:postcode":"06006",
    "sg:province":"Badajoz",
    "wof:name":"Fernandez Gonzalez Enrique Bernardo",
    "wof:placetype":"venue"
},
  "geometry": {"coordinates":[-6.9941577911,38.8852272034],"type":"Point"}
}