{
  "type": "Feature",
  "properties": {
    "addr:full":"Carrer de F. Rius I Taulet, 12 Gava Barcelona 08850",
    "addr:housenumber":"12",
    "addr:postcode":"08850",
    "addr:street":"Carrer De F. Rius I Taulet",
    "iso:country":"ES",
    "sg:address":"Carrer de F. Rius I Taulet, 12",
    "sg:city":"Gava",
    "sg:orig_category":"Mec\u00c1nico Del Autom\u00d3vil",
    "sg:phone":"+34 936 62 10 01",
    "sg:postcode":"08850",
    "sg:province":"Barcelona",
    "wof:name":"Burjales Lopez Ferran",
    "wof:placetype":"venue"
},
  "geometry": {"coordinates":[2.0075330734,41.3027458191],"type":"Point"}
}