{
  "type": "Feature",
  "properties": {
    "addr:full":"Carrer de Cristofor Colom, 8 Tarragona Tarragona 43001",
    "addr:housenumber":"8",
    "addr:postcode":"43001",
    "addr:street":"Carrer De Cristofor Colom",
    "iso:country":"ES",
    "sg:address":"Carrer de Cristofor Colom, 8",
    "sg:city":"Tarragona",
    "sg:orig_category":"Agencias De Viajes",
    "sg:phone":"+34 977 21 38 69",
    "sg:postcode":"43001",
    "sg:province":"Tarragona",
    "wof:name":"Tci Cortes Xxi S.a.u.",
    "wof:placetype":"venue"
},
  "geometry": {"coordinates":[1.2489199638,41.116558075],"type":"Point"}
}