{
  "type": "Feature",
  "properties": {
    "iso:country":"ES",
    "sg:address":"Calle de Tenerife, 42",
    "sg:city":"Madrid",
    "sg:orig_category":"Empresas De Portes Y Mensajer\u00cda",
    "sg:phone":"+34 914 59 66 87",
    "sg:postcode":"28039",
    "sg:province":"Madrid",
    "sg:website":"www.solucionescs.com",
    "wof:name":"Soluciones Castellanas De Servicios S.a.",
    "wof:placetype":"venue"
},
  "geometry": {"coordinates":[-3.7063014507,40.451499939],"type":"Point"}
}