{
  "type": "Feature",
  "properties": {
    "addr:full":"Calle de Fray Diego Alonso, 18 Ba\u00d1eza Le\u00f3n 24750",
    "addr:housenumber":"18",
    "addr:postcode":"24750",
    "addr:street":"Calle De Fray Diego Alonso;Leo\u0301N",
    "iso:country":"ES",
    "sg:address":"Calle de Fray Diego Alonso, 18",
    "sg:city":"Ba\u00d1eza",
    "sg:classifiers":[
        {
            "category":"Autos & Motor Vehicles",
            "subcategory":"Automobile Sales",
            "type":"Retail Goods"
        }
    ],
    "sg:phone":"+34 987 65 65 15",
    "sg:postcode":"24750",
    "sg:province":"Le\u00f3n",
    "wof:name":"Torres Guerrero Jesus",
    "wof:placetype":"venue"
},
  "geometry": {"coordinates":[-5.9242091179,42.3069114685],"type":"Point"}
}