{
  "type": "Feature",
  "properties": {
    "addr:full":"Calle de Narea Kalea, 2 Lekeitio Vizcaya 48280",
    "addr:housenumber":"2",
    "addr:postcode":"48280",
    "addr:street":"Calle De Narea Kalea",
    "iso:country":"ES",
    "sg:address":"Calle de Narea Kalea, 2",
    "sg:city":"Lekeitio",
    "sg:orig_category":"Juegos Y Juguetes (al Por Menor)",
    "sg:phone":"+34 946 24 36 88",
    "sg:postcode":"48280",
    "sg:province":"Vizcaya",
    "wof:name":"Goitiz Aboitiz Itxasne",
    "wof:placetype":"venue"
},
  "geometry": {"coordinates":[-2.5032770634,43.3653373718],"type":"Point"}
}