{
  "type": "Feature",
  "properties": {
    "iso:country":"ES",
    "sg:address":"Granada, 2",
    "sg:city":"Vicar",
    "sg:orig_category":"Transportes Internacionales",
    "sg:phone":"+34 950 55 32 84",
    "sg:postcode":"04738",
    "sg:province":"Almer\u00eda",
    "wof:name":"Frio Vicar S. L.",
    "wof:placetype":"venue"
},
  "geometry": {"coordinates":[-2.635559082,36.7998008728],"type":"Point"}
}