{
  "type": "Feature",
  "properties": {
    "addr:full":"Mcdo. Abastos, S/n Almodovar Campo Ciudad Real 13580",
    "addr:housenumber":"s / n",
    "addr:postcode":"13580",
    "iso:country":"ES",
    "sg:address":"Mcdo. Abastos, S/n",
    "sg:city":"Almodovar Campo",
    "sg:orig_category":"Alimentaci\u00d3n General (al Por Menor)",
    "sg:phone":"+34 926 48 33 30",
    "sg:postcode":"13580",
    "sg:province":"Ciudad Real",
    "wof:name":"Sanchez Huertas Moises",
    "wof:placetype":"venue"
},
  "geometry": {"coordinates":[-4.1820688248,38.7115097046],"type":"Point"}
}