{
  "type": "Feature",
  "properties": {
    "addr:full":"Veinat De Mata, 44 Mataro Barcelona 08304",
    "addr:housenumber":"44",
    "addr:postcode":"08304",
    "addr:street":"Mata",
    "iso:country":"ES",
    "sg:address":"Veinat De Mata, 44",
    "sg:city":"Mataro",
    "sg:orig_category":"Producci\u00d3n, Venta De Productos De Agricultura Biol\u00d3gica",
    "sg:phone":"+34 937 55 13 99",
    "sg:postcode":"08304",
    "sg:province":"Barcelona",
    "wof:name":"Cultius Itxart S.c.p.",
    "wof:placetype":"venue"
},
  "geometry": {"coordinates":[2.4698801041,41.5688247681],"type":"Point"}
}