{
  "type": "Feature",
  "properties": {
    "iso:country":"ES",
    "sg:address":"Cristo Sangre, S/n",
    "sg:city":"Polinya Xuquer",
    "sg:orig_category":"Empresarios",
    "sg:phone":"+34 962 97 30 98",
    "sg:postcode":"46688",
    "sg:province":"Valencia",
    "wof:name":"Construcciones Bonora Talens S.l.",
    "wof:placetype":"venue"
},
  "geometry": {"coordinates":[-0.3746939898,39.197719574],"type":"Point"}
}