{
  "type": "Feature",
  "properties": {
    "iso:country":"ES",
    "sg:address":"Calle de Sancho Panza, 3",
    "sg:city":"Socuellamos",
    "sg:orig_category":"Institutos De Belleza",
    "sg:phone":"+34 926 53 15 03",
    "sg:postcode":"13630",
    "sg:province":"Ciudad Real",
    "wof:name":"Plaza Alarcon Maria Jesus",
    "wof:placetype":"venue"
},
  "geometry": {"coordinates":[-2.7892200947,39.2865486145],"type":"Point"}
}