{
  "type": "Feature",
  "properties": {
    "addr:full":"Esglesia, 25 Estartit Girona 17258",
    "addr:housenumber":"25",
    "addr:postcode":"17258",
    "addr:street":"Esglesia",
    "iso:country":"ES",
    "sg:address":"Esglesia, 25",
    "sg:city":"Estartit",
    "sg:orig_category":"Ropa Para Se\u00d1oras Y Caballeros (al Por Menor)",
    "sg:phone":"+34 972 75 14 09",
    "sg:postcode":"17258",
    "sg:province":"Girona",
    "wof:name":"Actual Punt S.l.",
    "wof:placetype":"venue"
},
  "geometry": {"coordinates":[3.196105957,42.0534477234],"type":"Point"}
}