{
  "type": "Feature",
  "properties": {
    "addr:full":"Calle de Medico Rey Garcia, 11 Ayamonte Huelva 21400",
    "addr:housenumber":"11",
    "addr:postcode":"21400",
    "addr:street":"Calle De Medico Rey Garcia",
    "iso:country":"ES",
    "sg:address":"Calle de Medico Rey Garcia, 11",
    "sg:city":"Ayamonte",
    "sg:orig_category":"Reposter\u00cdas",
    "sg:phone":"+34 959 32 21 33",
    "sg:postcode":"21400",
    "sg:province":"Huelva",
    "wof:name":"Martin Carnacea Roberto",
    "wof:placetype":"venue"
},
  "geometry": {"coordinates":[-7.4090909958,37.2117042542],"type":"Point"}
}