{
  "type": "Feature",
  "properties": {
    "iso:country":"ES",
    "sg:address":"Calle de Gran Capitan, 12",
    "sg:city":"Puertollano",
    "sg:orig_category":"Instalaci\u00d3n, Reparaci\u00d3n De Ascensores Y Montacargas",
    "sg:phone":"+34 926 41 21 19",
    "sg:postcode":"13500",
    "sg:province":"Ciudad Real",
    "wof:name":"Thyssenkrupp Elevadores S.l.",
    "wof:placetype":"venue"
},
  "geometry": {"coordinates":[-4.1051092148,38.6824188232],"type":"Point"}
}