{
  "type": "Feature",
  "properties": {
    "iso:country":"ES",
    "sg:address":"Calle de Hermandad (la), 2",
    "sg:city":"Autol",
    "sg:orig_category":"Cajas Para Embalar",
    "sg:phone":"+34 941 39 09 25",
    "sg:postcode":"26560",
    "sg:province":"La Rioja",
    "wof:name":"Caja Rural Provincial De Navarra",
    "wof:placetype":"venue"
},
  "geometry": {"coordinates":[-2.004224062,42.2131233215],"type":"Point"}
}