{
  "type": "Feature",
  "properties": {
    "iso:country":"ES",
    "sg:address":"Carrer de Sant Elies, 37",
    "sg:city":"Reus",
    "sg:orig_category":"Ebanister\u00cda",
    "sg:phone":"+34 977 31 50 58",
    "sg:postcode":"43201",
    "sg:province":"Tarragona",
    "wof:name":"Moix Ebenisteria S.l.",
    "wof:placetype":"venue"
},
  "geometry": {"coordinates":[1.1045160294,41.1573295593],"type":"Point"}
}