{
  "type": "Feature",
  "properties": {
    "addr:full":"Calle de Italia, 6 Alacant Alicante 03003",
    "addr:housenumber":"6",
    "addr:postcode":"03003",
    "addr:street":"Calle De Italia",
    "iso:country":"ES",
    "sg:address":"Calle de Italia, 6",
    "sg:city":"Alacant",
    "sg:orig_category":"Florister\u00cdas",
    "sg:phone":"+34 965 92 67 49",
    "sg:postcode":"03003",
    "sg:province":"Alicante",
    "wof:name":"Jimenez Martinez Manuel",
    "wof:placetype":"venue"
},
  "geometry": {"coordinates":[-0.4886179864,38.3417167664],"type":"Point"}
}