{
  "type": "Feature",
  "properties": {
    "addr:full":"Calle de Gutierrez Mellado, 3 Olula Rio Almer\u00eda 04860",
    "addr:housenumber":"3",
    "addr:postcode":"04860",
    "addr:street":"Calle De Gutierrez Mellado;Almeri\u0301A",
    "iso:country":"ES",
    "sg:address":"Calle de Gutierrez Mellado, 3",
    "sg:city":"Olula Rio",
    "sg:orig_category":"Publicidad (soportes Y Gesti\u00d3n)",
    "sg:phone":"+34 950 44 22 44",
    "sg:postcode":"04860",
    "sg:province":"Almer\u00eda",
    "wof:name":"Indalprint S.c.a.",
    "wof:placetype":"venue"
},
  "geometry": {"coordinates":[-2.4679217339,36.8401641846],"type":"Point"}
}