{
  "type": "Feature",
  "properties": {
    "addr:full":"Urb Altos Vista Nevada, S/n Armilla Granada 18100",
    "addr:housenumber":"/ n",
    "addr:postcode":"18100",
    "addr:street":"Urb Altos;Nevada S",
    "iso:country":"ES",
    "sg:address":"Urb Altos Vista Nevada, S/n",
    "sg:city":"Armilla",
    "sg:orig_category":"Centros Empresariales",
    "sg:phone":"+34 958 81 66 78",
    "sg:postcode":"18100",
    "sg:province":"Granada",
    "wof:name":"Fabregas Garcia Juan Jesus",
    "wof:placetype":"venue"
},
  "geometry": {"coordinates":[-3.6135139465,37.1514511108],"type":"Point"}
}