{
  "type": "Feature",
  "properties": {
    "iso:country":"ES",
    "sg:address":"Calle de General Alvarez De Castro, 20",
    "sg:city":"Madrid",
    "sg:orig_category":"Cervecer\u00cdas",
    "sg:phone":"+34 915 94 14 22",
    "sg:postcode":"28010",
    "sg:province":"Madrid",
    "wof:name":"Son Bar S.l.",
    "wof:placetype":"venue"
},
  "geometry": {"coordinates":[-3.7023234367,40.4357032776],"type":"Point"}
}