{
  "type": "Feature",
  "properties": {
    "addr:full":"Pol Ind Cerro San Francisco, S/n Valencia Alcantara C\u00e1ceres 10500",
    "addr:postcode":"10500",
    "addr:street":"Ind;San Francisco S / N;Alcantara Ca\u0301Ceres",
    "iso:country":"ES",
    "sg:address":"Pol Ind Cerro San Francisco, S/n",
    "sg:city":"Valencia Alcantara",
    "sg:orig_category":"Mec\u00c1nico Del Autom\u00d3vil",
    "sg:phone":"+34 927 58 25 60",
    "sg:postcode":"10500",
    "sg:province":"C\u00e1ceres",
    "wof:name":"Crespo Viera Pablo",
    "wof:placetype":"venue"
},
  "geometry": {"coordinates":[-7.2451472282,39.4101142883],"type":"Point"}
}