{
  "type": "Feature",
  "properties": {
    "addr:full":"Rua Ameneiral, 18 Bertamirans La Coru\u00f1a 15220",
    "addr:housenumber":"18",
    "addr:postcode":"15220",
    "addr:street":"Rua Ameneiral;La Corun\u0303A",
    "iso:country":"ES",
    "sg:address":"Rua Ameneiral, 18",
    "sg:city":"Bertamirans",
    "sg:orig_category":"Reposter\u00cdas",
    "sg:phone":"+34 981 88 47 17",
    "sg:postcode":"15220",
    "sg:province":"La Coru\u00f1a",
    "wof:name":"Panaderia Remigio S.l.",
    "wof:placetype":"venue"
},
  "geometry": {"coordinates":[-8.6497192383,42.8596611023],"type":"Point"}
}