{
  "type": "Feature",
  "properties": {
    "addr:full":"Plaz Reina, 16 Valencia Valencia 46001",
    "addr:housenumber":"16",
    "addr:postcode":"46001",
    "addr:street":"Reina",
    "iso:country":"ES",
    "sg:address":"Plaz Reina, 16",
    "sg:city":"Valencia",
    "sg:orig_category":"Art\u00cdculos De Regalo (al Por Menor)",
    "sg:phone":"+34 963 15 30 21",
    "sg:postcode":"46001",
    "sg:province":"Valencia",
    "wof:name":"La Botiga De La Seu S.l.",
    "wof:placetype":"venue"
},
  "geometry": {"coordinates":[-0.3754180074,39.4749755859],"type":"Point"}
}