{
  "type": "Feature",
  "properties": {
    "addr:full":"Calle de Saturnino Menendez, 15 Entrego Asturias 33940",
    "addr:housenumber":"15",
    "addr:postcode":"33940",
    "addr:street":"Calle De Saturnino Menendez",
    "iso:country":"ES",
    "sg:address":"Calle de Saturnino Menendez, 15",
    "sg:city":"Entrego",
    "sg:orig_category":"Doctores En Medicina",
    "sg:phone":"+34 985 66 34 21",
    "sg:postcode":"33940",
    "sg:province":"Asturias",
    "wof:name":"Fernandez Antu\u00f1a Manuel Angel",
    "wof:placetype":"venue"
},
  "geometry": {"coordinates":[-5.637594223,43.2874145508],"type":"Point"}
}