{
  "type": "Feature",
  "properties": {
    "addr:full":"Calle de Cabrales, 92 Gijon Asturias 33201",
    "addr:housenumber":"92",
    "addr:postcode":"33201",
    "addr:street":"Calle De Cabrales",
    "iso:country":"ES",
    "sg:address":"Calle de Cabrales, 92",
    "sg:city":"Gijon",
    "sg:orig_category":"Doctores En Medicina",
    "sg:phone":"+34 985 35 78 64",
    "sg:postcode":"33201",
    "sg:province":"Asturias",
    "wof:name":"Suarez Linares Monica",
    "wof:placetype":"venue"
},
  "geometry": {"coordinates":[-5.659403801,43.538394928],"type":"Point"}
}