{
  "type": "Feature",
  "properties": {
    "iso:country":"ES",
    "sg:address":"Carrer de Nou D'octubre, 2",
    "sg:city":"Pego",
    "sg:orig_category":"Agentes, Concesionarios Y Sucursales De Veh\u00cdculos",
    "sg:phone":"+34 965 57 20 54",
    "sg:postcode":"03780",
    "sg:province":"Alicante",
    "wof:name":"Girbes Cabrera Jose Justo",
    "wof:placetype":"venue"
},
  "geometry": {"coordinates":[-0.1138570011,38.8471794128],"type":"Point"}
}