{
  "type": "Feature",
  "properties": {
    "addr:full":"Av Catalunya, 34 Rieral De Bigues Barcelona 08415",
    "addr:housenumber":"34",
    "addr:postcode":"08415",
    "addr:street":"Av Catalunya",
    "iso:country":"ES",
    "sg:address":"Av Catalunya, 34",
    "sg:city":"Rieral De Bigues",
    "sg:orig_category":"Triper\u00cdas",
    "sg:phone":"+34 938 65 63 54",
    "sg:postcode":"08415",
    "sg:province":"Barcelona",
    "wof:name":"Star-trip S.l.",
    "wof:placetype":"venue"
},
  "geometry": {"coordinates":[2.2154788971,41.6751251221],"type":"Point"}
}