{
  "type": "Feature",
  "properties": {
    "iso:country":"ES",
    "sg:address":"Calle de Azor, 38",
    "sg:city":"Navarredonda",
    "sg:orig_category":"Limpieza Con Chorro De Arena Y Con Granalla, Pulido",
    "sg:phone":"+34 902 18 08 49",
    "sg:postcode":"28210",
    "sg:province":"Madrid",
    "wof:name":"Iberpulidos S.l.",
    "wof:placetype":"venue"
},
  "geometry": {"coordinates":[-3.7260465622,40.9907798767],"type":"Point"}
}