{
  "type": "Feature",
  "properties": {
    "addr:full":"Calle de Baeza, 25 Pozo Alcon Ja\u00e9n 23485",
    "addr:housenumber":"25",
    "addr:postcode":"23485",
    "addr:street":"Calle De Baeza;Alcon Jae\u0301N",
    "iso:country":"ES",
    "sg:address":"Calle de Baeza, 25",
    "sg:city":"Pozo Alcon",
    "sg:orig_category":"Supermercados Y Hipermercados",
    "sg:phone":"+34 953 73 88 04",
    "sg:postcode":"23485",
    "sg:province":"Ja\u00e9n",
    "wof:name":"Ortiz Diaz Andres",
    "wof:placetype":"venue"
},
  "geometry": {"coordinates":[-2.9362416267,37.7016601562],"type":"Point"}
}