{
  "type": "Feature",
  "properties": {
    "addr:full":"Ptge Credit, 7 Barcelona Barcelona 08002",
    "addr:housenumber":"7",
    "addr:postcode":"08002",
    "addr:street":"Credit",
    "iso:country":"ES",
    "sg:address":"Ptge Credit, 7",
    "sg:city":"Barcelona",
    "sg:orig_category":"Centros Empresariales",
    "sg:phone":"+34 933 02 01 39",
    "sg:postcode":"08002",
    "sg:province":"Barcelona",
    "wof:name":"Barone  Eleonora",
    "wof:placetype":"venue"
},
  "geometry": {"coordinates":[2.176789999,41.3816947937],"type":"Point"}
}