{
  "type": "Feature",
  "properties": {
    "iso:country":"ES",
    "sg:address":"Mirador De Las Palmeras, 62",
    "sg:city":"Torremolinos",
    "sg:orig_category":"Alquiler De Veh\u00cdculos: Turismos Y Utilitarios",
    "sg:phone":"+34 952 37 01 03",
    "sg:postcode":"29620",
    "sg:province":"M\u00e1laga",
    "wof:name":"Noguera Moreno Jose",
    "wof:placetype":"venue"
},
  "geometry": {"coordinates":[-4.4998540878,36.6244087219],"type":"Point"}
}