{
  "type": "Feature",
  "properties": {
    "addr:full":"Calle de Pere\u00d1a, Km. 0003,0 Villarino De Los Aires Salamanca 37160",
    "addr:postcode":"37160",
    "addr:street":"Calle De Peren\u0303A Km. 0003,0",
    "iso:country":"ES",
    "sg:address":"Calle de Pere\u00d1a, Km. 0003,0",
    "sg:city":"Villarino De Los Aires",
    "sg:orig_category":"Empresas De Electricidad En General",
    "sg:phone":"+34 923 16 92 80",
    "sg:postcode":"37160",
    "sg:province":"Salamanca",
    "wof:name":"Red Electrica De Espa\u00f1a S.a.",
    "wof:placetype":"venue"
},
  "geometry": {"coordinates":[-6.4714589119,41.264251709],"type":"Point"}
}