{
  "type": "Feature",
  "properties": {
    "iso:country":"ES",
    "sg:address":"C/ Santa Marcel.lina, 19",
    "sg:city":"Cerdanyola Valles",
    "sg:orig_category":"Reposter\u00cdas",
    "sg:phone":"+34 935 86 56 29",
    "sg:postcode":"08290",
    "sg:province":"Barcelona",
    "wof:name":"La Panera Del Pa S.a.",
    "wof:placetype":"venue"
},
  "geometry": {"coordinates":[2.1360690594,41.4911270142],"type":"Point"}
}