{
  "type": "Feature",
  "properties": {
    "addr:full":"Carretera Vidreres, 106 Lloret Mar Girona 17310",
    "addr:housenumber":"106",
    "addr:postcode":"17310",
    "addr:street":"Carretera Vidreres",
    "iso:country":"ES",
    "sg:address":"Carretera Vidreres, 106",
    "sg:city":"Lloret Mar",
    "sg:orig_category":"Empresas De Carpinter\u00cda De Madera",
    "sg:phone":"+34 972 36 59 58",
    "sg:postcode":"17310",
    "sg:province":"Girona",
    "wof:name":"Cordoba Rodriguez Jose Antonio",
    "wof:placetype":"venue"
},
  "geometry": {"coordinates":[2.8418281078,41.707195282],"type":"Point"}
}