{
  "type": "Feature",
  "properties": {
    "addr:full":"Carrer de Victor Catala, 66 Reus Tarragona 43206",
    "addr:housenumber":"66",
    "addr:postcode":"43206",
    "addr:street":"Carrer De Victor Catala",
    "iso:country":"ES",
    "sg:address":"Carrer de Victor Catala, 66",
    "sg:city":"Reus",
    "sg:orig_category":"Mec\u00c1nico Del Autom\u00d3vil",
    "sg:phone":"+34 977 33 13 91",
    "sg:postcode":"43206",
    "sg:province":"Tarragona",
    "wof:name":"Carburacio I Electromecanica Melcar S.l.",
    "wof:placetype":"venue"
},
  "geometry": {"coordinates":[1.0788559914,41.1570243835],"type":"Point"}
}