{
  "type": "Feature",
  "properties": {
    "iso:country":"ES",
    "sg:address":"Avda Artesanos (de Los), 24",
    "sg:city":"Tres Cantos",
    "sg:orig_category":"Comercio De Piezas De Recambio Y De Accesorios De Veh\u00cdculos, Veh\u00cdculos Industriales",
    "sg:phone":"+34 918 06 19 00",
    "sg:postcode":"28760",
    "sg:province":"Madrid",
    "sg:website":"www.hella.es",
    "wof:name":"Hella S.a.",
    "wof:placetype":"venue"
},
  "geometry": {"coordinates":[-3.6998779774,40.6045303345],"type":"Point"}
}