{
  "type": "Feature",
  "properties": {
    "addr:full":"Carrer de Major, 24 Pineda Mar Barcelona 08397",
    "addr:housenumber":"24",
    "addr:postcode":"08397",
    "addr:street":"Carrer De Major;Barcelona",
    "iso:country":"ES",
    "sg:address":"Carrer de Major, 24",
    "sg:city":"Pineda Mar",
    "sg:orig_category":"Zapatos (al Por Menor)",
    "sg:phone":"+34 937 67 25 90",
    "sg:postcode":"08397",
    "sg:province":"Barcelona",
    "wof:name":"Torres Rodriguez Ana Maria",
    "wof:placetype":"venue"
},
  "geometry": {"coordinates":[2.6881608963,41.6271629333],"type":"Point"}
}