{
  "type": "Feature",
  "properties": {
    "iso:country":"ES",
    "sg:address":"Avda Constantino Gonzalez, 3",
    "sg:city":"Cangas Onis",
    "sg:orig_category":"Quincaller\u00cda (al Por Menor)",
    "sg:phone":"+34 985 84 81 74",
    "sg:postcode":"33550",
    "sg:province":"Asturias",
    "wof:name":"Laria Casta\u00f1o Enrique",
    "wof:placetype":"venue"
},
  "geometry": {"coordinates":[-5.1302690506,43.3503799438],"type":"Point"}
}