{
  "type": "Feature",
  "properties": {
    "iso:country":"ES",
    "sg:address":"Calle de Constitucion, 12",
    "sg:city":"Ibahernando",
    "sg:orig_category":"Plomeros",
    "sg:phone":"+34 927 33 02 59",
    "sg:postcode":"10280",
    "sg:province":"C\u00e1ceres",
    "wof:name":"Mena Anes Pedro",
    "wof:placetype":"venue"
},
  "geometry": {"coordinates":[-5.8485269547,39.3363800049],"type":"Point"}
}