{
  "type": "Feature",
  "properties": {
    "iso:country":"ES",
    "sg:address":"Calle de San Juan De Dios, 47",
    "sg:city":"Granada",
    "sg:orig_category":"Farmacias",
    "sg:phone":"+34 958 27 24 49",
    "sg:postcode":"18001",
    "sg:province":"Granada",
    "wof:name":"Jimenez Hernandez Ricardo",
    "wof:placetype":"venue"
},
  "geometry": {"coordinates":[-3.6024696827,37.1822395325],"type":"Point"}
}