{
  "type": "Feature",
  "properties": {
    "addr:full":"Av Albir (l'), 8 Albir Alicante 03580",
    "addr:housenumber":"8",
    "addr:postcode":"03580",
    "addr:street":"Av Albir L '",
    "iso:country":"ES",
    "sg:address":"Av Albir (l'), 8",
    "sg:city":"Albir",
    "sg:orig_category":"Servicios Gsm",
    "sg:phone":"+34 966 86 74 73",
    "sg:postcode":"03580",
    "sg:province":"Alicante",
    "sg:website":"www.centrotelecom.com",
    "wof:name":"Centro Telecom Albir S.l.",
    "wof:placetype":"venue"
},
  "geometry": {"coordinates":[-0.0666500032,38.5719146729],"type":"Point"}
}