{
  "type": "Feature",
  "properties": {
    "iso:country":"ES",
    "sg:address":"Calle de Felisa Campuzano, 19",
    "sg:city":"Corrales",
    "sg:orig_category":"Delegados, Agentes De Tr\u00c1nsito, Auxiliares De Transporte Internacional",
    "sg:phone":"+34 942 84 17 60",
    "sg:postcode":"39400",
    "sg:province":"Cantabria",
    "wof:name":"Achutegui Ria\u00f1o Jose Luis",
    "wof:placetype":"venue"
},
  "geometry": {"coordinates":[-4.0680999756,43.262348175],"type":"Point"}
}