{
  "type": "Feature",
  "properties": {
    "addr:full":"Leon-astorga, Km. 0342,0 Estebanez Calzada Le\u00f3n 24288",
    "addr:postcode":"24288",
    "addr:street":"Leon-Astorga Km. 0342,0;Calzada Leo\u0301N",
    "iso:country":"ES",
    "sg:address":"Leon-astorga, Km. 0342,0",
    "sg:city":"Estebanez Calzada",
    "sg:orig_category":"Distribuci\u00d3n De Petr\u00d3leo Y Derivados",
    "sg:phone":"+34 987 68 70 00",
    "sg:postcode":"24288",
    "sg:province":"Le\u00f3n",
    "wof:name":"Fernandez Perez Miguel Angel",
    "wof:placetype":"venue"
},
  "geometry": {"coordinates":[-5.9092941284,42.4699058533],"type":"Point"}
}