{
  "type": "Feature",
  "properties": {
    "iso:country":"ES",
    "sg:address":"Calle de Hamarretxeta, 21",
    "sg:city":"Pasai Antxo",
    "sg:orig_category":"Televisi\u00d3n, V\u00cddeo: Aparatos Y Accesorios (venta)",
    "sg:phone":"+34 943 51 08 47",
    "sg:postcode":"20110",
    "sg:province":"Guip\u00f9zcoa",
    "wof:name":"Zabaleta Baloria Tomas",
    "wof:placetype":"venue"
},
  "geometry": {"coordinates":[-1.9178576469,43.3166122437],"type":"Point"}
}