{
  "type": "Feature",
  "properties": {
    "addr:full":"Calle de Ebano, 7 Badajoz Badajoz 06011",
    "addr:housenumber":"7",
    "addr:postcode":"06011",
    "addr:street":"Calle De Ebano",
    "iso:country":"ES",
    "sg:address":"Calle de Ebano, 7",
    "sg:city":"Badajoz",
    "sg:orig_category":"Empresas De Pintura Y Revestimientos",
    "sg:phone":"+34 924 22 10 48",
    "sg:postcode":"06011",
    "sg:province":"Badajoz",
    "wof:name":"Luis Martin Santos Plasencia S.l.",
    "wof:placetype":"venue"
},
  "geometry": {"coordinates":[-6.9890980721,38.8573226929],"type":"Point"}
}