{
  "type": "Feature",
  "properties": {
    "iso:country":"ES",
    "sg:address":"Pol Ind Vda Castro, S/n",
    "sg:city":"Lucena",
    "sg:orig_category":"Muebles",
    "sg:phone":"+34 957 51 66 72",
    "sg:postcode":"14900",
    "sg:province":"C\u00f3rdoba",
    "wof:name":"Muebles Kibecar S.l.",
    "wof:placetype":"venue"
},
  "geometry": {"coordinates":[-4.4932742119,37.40467453],"type":"Point"}
}