{
  "type": "Feature",
  "properties": {
    "iso:country":"ES",
    "sg:address":"Cmno Ronda (de), 158",
    "sg:city":"Granada",
    "sg:orig_category":"Servicios De Telecomunicaciones",
    "sg:phone":"+34 958 53 57 27",
    "sg:postcode":"18003",
    "sg:province":"Granada",
    "wof:name":"Distansema S.l.",
    "wof:placetype":"venue"
},
  "geometry": {"coordinates":[-3.611166954,37.1794662476],"type":"Point"}
}