{
  "type": "Feature",
  "properties": {
    "iso:country":"ES",
    "sg:address":"Calle de Largalo, 1",
    "sg:city":"Jerez De La Frontera",
    "sg:orig_category":"Distribuci\u00d3n De Petr\u00d3leo Y Derivados",
    "sg:phone":"+34 956 33 38 98",
    "sg:postcode":"11406",
    "sg:province":"C\u00e1diz",
    "wof:name":"Jerez Rosado Pablo",
    "wof:placetype":"venue"
},
  "geometry": {"coordinates":[-6.1202912331,36.6837806702],"type":"Point"}
}