{
  "type": "Feature",
  "properties": {
    "iso:country":"ES",
    "sg:address":"Avda Taramona, S/n",
    "sg:city":"Mimetiz",
    "sg:orig_category":"Partidos Pol\u00cdticos",
    "sg:phone":"+34 946 39 02 03",
    "sg:postcode":"48860",
    "sg:province":"Vizcaya",
    "wof:name":"Junta Municipal Del Partido Nacionalista Vasco",
    "wof:placetype":"venue"
},
  "geometry": {"coordinates":[-3.1327140331,43.2138252258],"type":"Point"}
}