{
  "type": "Feature",
  "properties": {
    "addr:full":"Calle de Fedra, 1 Sevilla Sevilla 41009",
    "addr:housenumber":"1",
    "addr:postcode":"41009",
    "addr:street":"Calle De Fedra",
    "iso:country":"ES",
    "sg:address":"Calle de Fedra, 1",
    "sg:city":"Sevilla",
    "sg:orig_category":"\u00d3ptica: Instrumentos (fabricaci\u00d3n)",
    "sg:phone":"+34 954 90 95 90",
    "sg:postcode":"41009",
    "sg:province":"Sevilla",
    "wof:name":"Malet Raga Francisco Javier",
    "wof:placetype":"venue"
},
  "geometry": {"coordinates":[-5.9881110191,37.4088630676],"type":"Point"}
}