{
  "type": "Feature",
  "properties": {
    "iso:country":"ES",
    "sg:address":"Calle de Puerto Escondido, 1",
    "sg:city":"Santa Cruz De Tenerife",
    "sg:orig_category":"Abogados",
    "sg:phone":"+34 922 24 73 65",
    "sg:postcode":"38002",
    "sg:province":"Santa Cruz De Tenerife",
    "wof:name":"Hodgson Asesores S.l.",
    "wof:placetype":"venue"
},
  "geometry": {"coordinates":[-16.2510242462,28.4693183899],"type":"Point"}
}