{
  "type": "Feature",
  "properties": {
    "iso:country":"ES",
    "sg:address":"Calle de Federico De Mendizabal, 12",
    "sg:city":"Jaen",
    "sg:orig_category":"Abogados",
    "sg:phone":"+34 953 24 40 30",
    "sg:postcode":"23001",
    "sg:province":"Ja\u00e9n",
    "wof:name":"Medina Gonzalez Manuel",
    "wof:placetype":"venue"
},
  "geometry": {"coordinates":[-3.7887220383,37.7687644958],"type":"Point"}
}