{
  "type": "Feature",
  "properties": {
    "addr:full":"Poligono Valdecebada, 34 Madro\u00f1era C\u00e1ceres 10210",
    "addr:housenumber":"34",
    "addr:postcode":"10210",
    "addr:street":"Valdecebada;Ca\u0301Ceres",
    "iso:country":"ES",
    "sg:address":"Poligono Valdecebada, 34",
    "sg:city":"Madro\u00f1era",
    "sg:orig_category":"Promotores Constructores",
    "sg:phone":"+34 927 33 46 58",
    "sg:postcode":"10210",
    "sg:province":"C\u00e1ceres",
    "wof:name":"Construcciones Procontex 2005,s.l.",
    "wof:placetype":"venue"
},
  "geometry": {"coordinates":[-5.7559142113,39.4252433777],"type":"Point"}
}