{
  "type": "Feature",
  "properties": {
    "addr:full":"Calle de Pablo Casals, 4 Parla Madrid 28980",
    "addr:housenumber":"4",
    "addr:postcode":"28980",
    "addr:street":"Calle De Pablo Casals",
    "iso:country":"ES",
    "sg:address":"Calle de Pablo Casals, 4",
    "sg:city":"Parla",
    "sg:orig_category":"Caf\u00c9s, Bares, Cervecer\u00cdas",
    "sg:phone":"+34 916 99 95 03",
    "sg:postcode":"28980",
    "sg:province":"Madrid",
    "wof:name":"Del Campo Martinez Miguel Angel",
    "wof:placetype":"venue"
},
  "geometry": {"coordinates":[-3.7729868889,40.2311134338],"type":"Point"}
}