{
  "type": "Feature",
  "properties": {
    "iso:country":"ES",
    "sg:address":"Avda Cristobal Colon, 24",
    "sg:city":"Puerto Cruz",
    "sg:orig_category":"Organismos De Turismo",
    "sg:phone":"+34 922 37 25 13",
    "sg:postcode":"38400",
    "sg:province":"Santa Cruz De Tenerife",
    "wof:name":"Fernandez Jimenez Manuel",
    "wof:placetype":"venue"
},
  "geometry": {"coordinates":[-16.5423679352,28.4187755585],"type":"Point"}
}