{
  "type": "Feature",
  "properties": {
    "iso:country":"ES",
    "sg:address":"Gabriel Celaya, 12",
    "sg:city":"Espinardo",
    "sg:orig_category":"Panader\u00cdas, Panader\u00cdas",
    "sg:phone":"+34 968 30 58 61",
    "sg:postcode":"30100",
    "sg:province":"Murcia",
    "wof:name":"Alcantud Robles Angel Luis",
    "wof:placetype":"venue"
},
  "geometry": {"coordinates":[-1.1620943546,38.0058364868],"type":"Point"}
}