{
  "type": "Feature",
  "properties": {
    "addr:full":"Avda Valencia, S/n Utrillas Teruel 44760",
    "addr:housenumber":"s / n",
    "addr:postcode":"44760",
    "addr:street":"Avda Valencia",
    "iso:country":"ES",
    "sg:address":"Avda Valencia, S/n",
    "sg:city":"Utrillas",
    "sg:orig_category":"Peluqueros: De Se\u00d1oras",
    "sg:phone":"+34 978 75 71 81",
    "sg:postcode":"44760",
    "sg:province":"Teruel",
    "wof:name":"Martin La Torre Concepcion",
    "wof:placetype":"venue"
},
  "geometry": {"coordinates":[-0.847743988,40.8096466064],"type":"Point"}
}