{
  "type": "Feature",
  "properties": {
    "iso:country":"ES",
    "sg:address":"Cllo Cedaceros, 3",
    "sg:city":"Sevilla",
    "sg:orig_category":"Dietistas",
    "sg:phone":"+34 954 56 44 11",
    "sg:postcode":"41004",
    "sg:province":"Sevilla",
    "wof:name":"Clinicas Perfect S.l.",
    "wof:placetype":"venue"
},
  "geometry": {"coordinates":[-5.9912590981,37.3917236328],"type":"Point"}
}