{
  "type": "Feature",
  "properties": {
    "addr:full":"Calle de Universidad, 17 Burgo Osma Soria 42300",
    "addr:housenumber":"17",
    "addr:postcode":"42300",
    "addr:street":"Calle De Universidad",
    "iso:country":"ES",
    "sg:address":"Calle de Universidad, 17",
    "sg:city":"Burgo Osma",
    "sg:orig_category":"Centros De Educaci\u00d3n Especial",
    "sg:phone":"+34 975 34 08 03",
    "sg:postcode":"42300",
    "sg:province":"Soria",
    "wof:name":"Colegio Publico Manuel Ruiz Zorrilla",
    "wof:placetype":"venue"
},
  "geometry": {"coordinates":[-3.0634489059,41.5872077942],"type":"Point"}
}