{
  "type": "Feature",
  "properties": {
    "addr:full":"Calle de Portalet, S/n Calpe Alicante 03710",
    "addr:housenumber":"s / n",
    "addr:postcode":"03710",
    "addr:street":"Calle De Portalet",
    "iso:country":"ES",
    "sg:address":"Calle de Portalet, S/n",
    "sg:city":"Calpe",
    "sg:orig_category":"Fabricaci\u00d3n De Mobiliario De Oficina",
    "sg:phone":"+34 965 83 37 81",
    "sg:postcode":"03710",
    "sg:province":"Alicante",
    "wof:name":"Pastor Torregrosa Rafael Manuel",
    "wof:placetype":"venue"
},
  "geometry": {"coordinates":[0.0460529998,38.645275116],"type":"Point"}
}