{
  "type": "Feature",
  "properties": {
    "iso:country":"ES",
    "sg:address":"Barr Okin-zuri, 2",
    "sg:city":"Ermua",
    "sg:orig_category":"Pintura, Barniz, Productos Asimilables (fabricaci\u00d3n, Al Por Mayor)",
    "sg:phone":"+34 943 17 30 24",
    "sg:postcode":"48260",
    "sg:province":"Vizcaya",
    "wof:name":"Pinturas Ermua S.l.",
    "wof:placetype":"venue"
},
  "geometry": {"coordinates":[-2.5022089481,43.1913795471],"type":"Point"}
}