{
  "type": "Feature",
  "properties": {
    "iso:country":"ES",
    "sg:address":"Carrer de Torres Jordi (de), 18",
    "sg:city":"Tarragona",
    "sg:orig_category":"Arquitectos",
    "sg:phone":"+34 977 21 94 36",
    "sg:postcode":"43005",
    "sg:province":"Tarragona",
    "wof:name":"Lluch Torres Juan",
    "wof:placetype":"venue"
},
  "geometry": {"coordinates":[1.2395709753,41.1123847961],"type":"Point"}
}