{
  "type": "Feature",
  "properties": {
    "iso:country":"ES",
    "sg:address":"Carrer de Rossello, 230",
    "sg:city":"Barcelona",
    "sg:orig_category":"Zapatos (al Por Menor)",
    "sg:phone":"+34 934 88 10 64",
    "sg:postcode":"08008",
    "sg:province":"Barcelona",
    "sg:website":"www.mutxart.com",
    "wof:name":"Hermenegildo Muxart S.l.",
    "wof:placetype":"venue"
},
  "geometry": {"coordinates":[2.1600461006,41.3951759338],"type":"Point"}
}