{
  "type": "Feature",
  "properties": {
    "iso:country":"ES",
    "sg:address":"Calle de Principe Ruyman, 10",
    "sg:city":"Santa Cruz De Tenerife",
    "sg:orig_category":"Estancos",
    "sg:phone":"+34 922 22 67 13",
    "sg:postcode":"38008",
    "sg:province":"Santa Cruz De Tenerife",
    "wof:name":"Correa Betancort Francisco Antonio",
    "wof:placetype":"venue"
},
  "geometry": {"coordinates":[-16.2713508606,28.469039917],"type":"Point"}
}