{
  "type": "Feature",
  "properties": {
    "iso:country":"ES",
    "sg:address":"Calle de Antonio Machado, 17",
    "sg:city":"Brenes",
    "sg:orig_category":"Producci\u00d3n, Venta De Productos De Agricultura Biol\u00d3gica",
    "sg:phone":"+34 954 79 61 22",
    "sg:postcode":"41310",
    "sg:province":"Sevilla",
    "wof:name":"Hermanos Lara Ruiz Sc",
    "wof:placetype":"venue"
},
  "geometry": {"coordinates":[-5.8727440834,37.5492630005],"type":"Point"}
}