{
  "type": "Feature",
  "properties": {
    "addr:full":"Carrer de Aribau, 22 Barcelona Barcelona 08011",
    "addr:housenumber":"22",
    "addr:postcode":"08011",
    "addr:street":"Carrer De Aribau",
    "iso:country":"ES",
    "sg:address":"Carrer de Aribau, 22",
    "sg:city":"Barcelona",
    "sg:orig_category":"Empresarios",
    "sg:phone":"+34 934 51 30 58",
    "sg:postcode":"08011",
    "sg:province":"Barcelona",
    "wof:name":"Ores-decor S.l.",
    "wof:placetype":"venue"
},
  "geometry": {"coordinates":[2.1617400646,41.3868026733],"type":"Point"}
}