{
  "type": "Feature",
  "properties": {
    "addr:full":"Calle de Hornillos, 22 Estepa Sevilla 41560",
    "addr:housenumber":"22",
    "addr:postcode":"41560",
    "addr:street":"Calle De Hornillos;Sevilla",
    "iso:country":"ES",
    "sg:address":"Calle de Hornillos, 22",
    "sg:city":"Estepa",
    "sg:orig_category":"Reposter\u00cdas",
    "sg:phone":"+34 954 82 02 39",
    "sg:postcode":"41560",
    "sg:province":"Sevilla",
    "wof:name":"Gonzalez Mateos Rafael",
    "wof:placetype":"venue"
},
  "geometry": {"coordinates":[-4.8797369003,37.2891807556],"type":"Point"}
}