{
  "type": "Feature",
  "properties": {
    "addr:full":"Ctra Tamaraceite A, 171 Perreras Las Palmas 35018",
    "addr:housenumber":"171",
    "addr:postcode":"35018",
    "addr:street":"Ctra Tamaraceite A;Las Palmas",
    "iso:country":"ES",
    "sg:address":"Ctra Tamaraceite A, 171",
    "sg:city":"Perreras",
    "sg:orig_category":"Abogados",
    "sg:phone":"+34 928 67 09 07",
    "sg:postcode":"35018",
    "sg:province":"Las Palmas",
    "wof:name":"Diaz Santana Monica",
    "wof:placetype":"venue"
},
  "geometry": {"coordinates":[-15.4561185837,28.1125068665],"type":"Point"}
}