{
  "type": "Feature",
  "properties": {
    "addr:full":"Calle de Jardin, 13 Talarrubias Badajoz 06640",
    "addr:housenumber":"13",
    "addr:postcode":"06640",
    "addr:street":"Calle De Jardin",
    "iso:country":"ES",
    "sg:address":"Calle de Jardin, 13",
    "sg:city":"Talarrubias",
    "sg:orig_category":"Art\u00cdculos De Regalo (al Por Menor)",
    "sg:phone":"+34 924 63 10 96",
    "sg:postcode":"06640",
    "sg:province":"Badajoz",
    "wof:name":"Pe\u00f1as Serrano Juan Antonio",
    "wof:placetype":"venue"
},
  "geometry": {"coordinates":[-5.2350649834,39.0389289856],"type":"Point"}
}