{
  "type": "Feature",
  "properties": {
    "iso:country":"ES",
    "sg:address":"Calle de Jose Zorrilla, 41",
    "sg:city":"Segovia",
    "sg:orig_category":"Cursos Particulares, Asistencia Escolar",
    "sg:phone":"+34 921 42 97 99",
    "sg:postcode":"40002",
    "sg:province":"Segovia",
    "wof:name":"Gomez Garcillan Agustin",
    "wof:placetype":"venue"
},
  "geometry": {"coordinates":[-4.1153302193,40.9422111511],"type":"Point"}
}