{
  "type": "Feature",
  "properties": {
    "addr:full":"Calle de Francisco Silvela, 21 Madrid Madrid 28028",
    "addr:housenumber":"21",
    "addr:postcode":"madrid;28028",
    "addr:street":"Calle De Francisco Silvela",
    "iso:country":"ES",
    "sg:address":"Calle de Francisco Silvela, 21",
    "sg:city":"Madrid",
    "sg:orig_category":"Producci\u00d3n, Venta De Productos De Agricultura Biol\u00d3gica",
    "sg:phone":"+34 914 01 13 04",
    "sg:postcode":"28028",
    "sg:province":"Madrid",
    "wof:name":"Union Manufacturers S.l.",
    "wof:placetype":"venue"
},
  "geometry": {"coordinates":[-3.6713080406,40.4306526184],"type":"Point"}
}