{
  "type": "Feature",
  "properties": {
    "addr:full":"Carrer de Sabino Arana, 46 Barcelona Barcelona 08028",
    "addr:housenumber":"46",
    "addr:postcode":"08028",
    "addr:street":"Carrer De Sabino Arana",
    "iso:country":"ES",
    "sg:address":"Carrer de Sabino Arana, 46",
    "sg:city":"Barcelona",
    "sg:orig_category":"Laboratorios Farmac\u00c9uticos",
    "sg:phone":"+34 934 11 82 36",
    "sg:postcode":"08028",
    "sg:province":"Barcelona",
    "wof:name":"Vera Peris Juan",
    "wof:placetype":"venue"
},
  "geometry": {"coordinates":[2.1239199638,41.3862304688],"type":"Point"}
}