{
  "type": "Feature",
  "properties": {
    "iso:country":"ES",
    "sg:address":"Calle de Calzada (la), 28",
    "sg:city":"Ecija",
    "sg:orig_category":"Promotores Constructores",
    "sg:phone":"+34 954 83 33 09",
    "sg:postcode":"41400",
    "sg:province":"Sevilla",
    "wof:name":"Construcciones Rafael Arroyo Garcia S.l.",
    "wof:placetype":"venue"
},
  "geometry": {"coordinates":[-5.0830774307,37.5444831848],"type":"Point"}
}