{
  "type": "Feature",
  "properties": {
    "addr:full":"Calle de Estret, 11 Javea Alicante 03730",
    "addr:housenumber":"11",
    "addr:postcode":"03730",
    "addr:street":"Calle De Estret",
    "iso:country":"ES",
    "sg:address":"Calle de Estret, 11",
    "sg:city":"Javea",
    "sg:orig_category":"Trabajos De Perforaciones, Sondeos, Construcci\u00d3n De Pozos",
    "sg:phone":"+34 966 46 05 14",
    "sg:postcode":"03730",
    "sg:province":"Alicante",
    "wof:name":"Viatubo S.l.",
    "wof:placetype":"venue"
},
  "geometry": {"coordinates":[0.1640650034,38.7888832092],"type":"Point"}
}