{
  "type": "Feature",
  "properties": {
    "iso:country":"ES",
    "sg:address":"Calle de San Cristobal, 7",
    "sg:city":"Mazaleon",
    "sg:orig_category":"Electricidad: Instaladores",
    "sg:phone":"+34 978 89 86 37",
    "sg:postcode":"44621",
    "sg:province":"Teruel",
    "wof:name":"Jose Luis Ti\u00f1ena S.l.",
    "wof:placetype":"venue"
},
  "geometry": {"coordinates":[0.1057569981,41.0495185852],"type":"Point"}
}