{
  "type": "Feature",
  "properties": {
    "addr:full":"Carrer de Bunyola, 5 Barcelona Barcelona 08016",
    "addr:housenumber":"5",
    "addr:postcode":"08016",
    "addr:street":"Carrer De Bunyola",
    "iso:country":"ES",
    "sg:address":"Carrer de Bunyola, 5",
    "sg:city":"Barcelona",
    "sg:orig_category":"Lencer\u00cda Femenina, Corseter\u00cda, Trajes De Ba\u00d1o (al Por Menor)",
    "sg:phone":"+34 933 50 03 22",
    "sg:postcode":"08016",
    "sg:province":"Barcelona",
    "wof:name":"Hernandez Tomas Concepcion",
    "wof:placetype":"venue"
},
  "geometry": {"coordinates":[2.1745550632,41.4377403259],"type":"Point"}
}