{
  "type": "Feature",
  "properties": {
    "addr:full":"Calle de Juan Vazquez De Mella, 41 Elda Alicante 03600",
    "addr:housenumber":"41",
    "addr:postcode":"03600",
    "addr:street":"Calle De Juan Vazquez De Mella",
    "iso:country":"ES",
    "sg:address":"Calle de Juan Vazquez De Mella, 41",
    "sg:city":"Elda",
    "sg:orig_category":"M\u00c1quinas De Coser Y De Hacer Punto (al Por Mayor)",
    "sg:phone":"+34 965 38 16 69",
    "sg:postcode":"03600",
    "sg:province":"Alicante",
    "wof:name":"Vidal Serrano Pedro",
    "wof:placetype":"venue"
},
  "geometry": {"coordinates":[-0.7868930101,38.4789657593],"type":"Point"}
}