{
  "type": "Feature",
  "properties": {
    "iso:country":"ES",
    "sg:address":"Av Mare Deu De Montserrat, 282",
    "sg:city":"Barcelona",
    "sg:orig_category":"Caf\u00c9s, Bares, Cervecer\u00cdas",
    "sg:phone":"+34 933 40 70 58",
    "sg:postcode":"08041",
    "sg:province":"Barcelona",
    "wof:name":"Vallejo Dominguez Enrique",
    "wof:placetype":"venue"
},
  "geometry": {"coordinates":[2.1763789654,41.4244880676],"type":"Point"}
}