{
  "type": "Feature",
  "properties": {
    "iso:country":"ES",
    "sg:address":"Calle de Costa Y Grijalba, 2",
    "sg:city":"Santa Cruz De Tenerife",
    "sg:orig_category":"\u00d3ptica: Instrumentos (fabricaci\u00d3n)",
    "sg:phone":"+34 922 24 28 83",
    "sg:postcode":"38004",
    "sg:province":"Santa Cruz De Tenerife",
    "wof:name":"Optica San Isidro S. L.",
    "wof:placetype":"venue"
},
  "geometry": {"coordinates":[-16.25639534,28.4704799652],"type":"Point"}
}