{
  "type": "Feature",
  "properties": {
    "iso:country":"ES",
    "sg:address":"Calle de Jose Calvo, 6",
    "sg:city":"Madrid",
    "sg:orig_category":"Delegados, Agentes De Tr\u00c1nsito, Auxiliares De Transporte Internacional",
    "sg:phone":"+34 913 11 37 35",
    "sg:postcode":"28039",
    "sg:province":"Madrid",
    "wof:name":"Fernandez Lorenzo Rafael",
    "wof:placetype":"venue"
},
  "geometry": {"coordinates":[-3.7077169418,40.4574203491],"type":"Point"}
}