{
  "type": "Feature",
  "properties": {
    "iso:country":"ES",
    "sg:address":"Calle de Conde De Cifuentes, 6",
    "sg:city":"Sevilla",
    "sg:orig_category":"Abogados",
    "sg:phone":"+34 954 41 17 06",
    "sg:postcode":"41004",
    "sg:province":"Sevilla",
    "wof:name":"Leon Gonzalez Aurora",
    "wof:placetype":"venue"
},
  "geometry": {"coordinates":[-5.9866199493,37.3835868835],"type":"Point"}
}