{
  "type": "Feature",
  "properties": {
    "iso:country":"ES",
    "sg:address":"Cala Flores, 6",
    "sg:city":"Cabo Palos",
    "sg:orig_category":"Farmacias",
    "sg:phone":"+34 968 56 34 72",
    "sg:postcode":"30370",
    "sg:province":"Murcia",
    "wof:name":"Samper Albaladejo Sebastian",
    "wof:placetype":"venue"
},
  "geometry": {"coordinates":[-0.7274389863,37.6292953491],"type":"Point"}
}