{
  "type": "Feature",
  "properties": {
    "iso:country":"ES",
    "sg:address":"Avda Palma De Mallorca, 43",
    "sg:city":"Torremolinos",
    "sg:orig_category":"Abogados",
    "sg:phone":"+34 952 37 59 33",
    "sg:postcode":"29620",
    "sg:province":"M\u00e1laga",
    "wof:name":"Barce Gallardo Sergio",
    "wof:placetype":"venue"
},
  "geometry": {"coordinates":[-4.4995031357,36.6192207336],"type":"Point"}
}