{
  "type": "Feature",
  "properties": {
    "addr:full":"Avda Rio Ebro, S/n Caspe Zaragoza 50700",
    "addr:housenumber":"s / n",
    "addr:postcode":"50700",
    "addr:street":"Avda Rio Ebro",
    "iso:country":"ES",
    "sg:address":"Avda Rio Ebro, S/n",
    "sg:city":"Caspe",
    "sg:orig_category":"Centros De Educaci\u00d3n Especial",
    "sg:phone":"+34 976 63 20 28",
    "sg:postcode":"50700",
    "sg:province":"Zaragoza",
    "wof:name":"Ayuntamiento De Caspe",
    "wof:placetype":"venue"
},
  "geometry": {"coordinates":[-0.0424210988,41.2305030823],"type":"Point"}
}