{
  "type": "Feature",
  "properties": {
    "iso:country":"ES",
    "sg:address":"Calle de Virgen Del Carmen, 52",
    "sg:city":"Donostia-san Sebastian",
    "sg:orig_category":"Pintores",
    "sg:phone":"+34 943 28 47 87",
    "sg:postcode":"20012",
    "sg:province":"Guip\u00f9zcoa",
    "wof:name":"Arratibel Etxegarai, Arantza",
    "wof:placetype":"venue"
},
  "geometry": {"coordinates":[-1.9673976898,43.318447113],"type":"Point"}
}