{
  "type": "Feature",
  "properties": {
    "addr:full":"Calle de Severo Ochoa, 4 Pola De Lena Asturias 33630",
    "addr:housenumber":"4",
    "addr:postcode":"33630",
    "addr:street":"Calle De Severo Ochoa",
    "iso:country":"ES",
    "sg:address":"Calle de Severo Ochoa, 4",
    "sg:city":"Pola De Lena",
    "sg:orig_category":"Peluquer\u00cdas, Peluquer\u00cda Mixta",
    "sg:phone":"+34 985 49 28 07",
    "sg:postcode":"33630",
    "sg:province":"Asturias",
    "wof:name":"Fernandez Prieto Sabino",
    "wof:placetype":"venue"
},
  "geometry": {"coordinates":[-5.8300747871,43.1601409912],"type":"Point"}
}