{
  "type": "Feature",
  "properties": {
    "iso:country":"ES",
    "sg:address":"Cmno Nogales (somio), 11",
    "sg:city":"Gijon",
    "sg:orig_category":"Asesor\u00cdas Y Estudios Financieros",
    "sg:phone":"+34 985 19 59 51",
    "sg:postcode":"33203",
    "sg:province":"Asturias",
    "wof:name":"Fernandez Rodriguez Felix",
    "wof:placetype":"venue"
},
  "geometry": {"coordinates":[-5.6150431633,43.5370903015],"type":"Point"}
}