{
  "type": "Feature",
  "properties": {
    "addr:full":"Mercat Sant Andreu, S/n Barcelona Barcelona 08016",
    "addr:housenumber":"s / n",
    "addr:postcode":"08016",
    "iso:country":"ES",
    "sg:address":"Mercat Sant Andreu, S/n",
    "sg:city":"Barcelona",
    "sg:orig_category":"Pescader\u00cdas (al Por Menor)",
    "sg:phone":"+34 933 45 01 99",
    "sg:postcode":"08016",
    "sg:province":"Barcelona",
    "wof:name":"Castello Soler Antonia",
    "wof:placetype":"venue"
},
  "geometry": {"coordinates":[2.1859149933,41.4347343445],"type":"Point"}
}