{
  "type": "Feature",
  "properties": {
    "iso:country":"ES",
    "sg:address":"Zuloagas-tarren Kalea, 9",
    "sg:city":"Eibar",
    "sg:orig_category":"Art\u00cdculos De Regalo (al Por Menor)",
    "sg:phone":"+34 943 20 17 40",
    "sg:postcode":"20600",
    "sg:province":"Guip\u00f9zcoa",
    "wof:name":"Jose Maria Aulestiarte Ugartechea",
    "wof:placetype":"venue"
},
  "geometry": {"coordinates":[-2.4700620174,43.1853485107],"type":"Point"}
}