{
  "type": "Feature",
  "properties": {
    "iso:country":"ES",
    "sg:address":"Calle de Jose Antonio (de), 21",
    "sg:city":"Boadilla Del Monte",
    "sg:orig_category":"Asesor\u00cda Sobre Comunicaci\u00d3n De Empresas",
    "sg:phone":"+34 916 32 14 52",
    "sg:postcode":"28660",
    "sg:province":"Madrid",
    "wof:name":"Mozo Mamolar Simeon",
    "wof:placetype":"venue"
},
  "geometry": {"coordinates":[-3.8774631023,40.405418396],"type":"Point"}
}