{
  "type": "Feature",
  "properties": {
    "addr:full":"Calle de Al-andalus, 1 Rinconada Sevilla 41309",
    "addr:housenumber":"1",
    "addr:postcode":"41309",
    "addr:street":"Calle De Al-Andalus",
    "iso:country":"ES",
    "sg:address":"Calle de Al-andalus, 1",
    "sg:city":"Rinconada",
    "sg:classifiers":[
        {
            "category":"Autos & Motor Vehicles",
            "subcategory":"Automobile Sales",
            "type":"Retail Goods"
        }
    ],
    "sg:phone":"+34 955 79 86 80",
    "sg:postcode":"41309",
    "sg:province":"Sevilla",
    "wof:name":"Martinez Lopez Juan Manuel",
    "wof:placetype":"venue"
},
  "geometry": {"coordinates":[-5.9839425087,37.4864463806],"type":"Point"}
}