{
  "type": "Feature",
  "properties": {
    "iso:country":"ES",
    "sg:address":"Plaz Espa\u00d1a, 6",
    "sg:city":"Salteras",
    "sg:orig_category":"Supermercados Y Hipermercados",
    "sg:phone":"+34 955 70 78 87",
    "sg:postcode":"41909",
    "sg:province":"Sevilla",
    "wof:name":"Supermercado Nuestra Se\u00d1ora De La Oliva S.l.l.",
    "wof:placetype":"venue"
},
  "geometry": {"coordinates":[-6.111328125,37.418182373],"type":"Point"}
}