{
  "type": "Feature",
  "properties": {
    "iso:country":"ES",
    "sg:address":"Carrer de Cunit, 3",
    "sg:city":"Gava",
    "sg:orig_category":"Agencias Y Agentes Comerciales, Representantes",
    "sg:phone":"+34 936 33 22 20",
    "sg:postcode":"08850",
    "sg:province":"Barcelona",
    "wof:name":"Land Air Sea Grup S.a.",
    "wof:placetype":"venue"
},
  "geometry": {"coordinates":[2.0285949707,41.2694816589],"type":"Point"}
}