{
  "type": "Feature",
  "properties": {
    "iso:country":"ES",
    "sg:address":"Calle de Jose Luis Mesias Iglesias, 11",
    "sg:city":"Almendralejo",
    "sg:orig_category":"Art\u00cdculos De Decoraci\u00d3n",
    "sg:phone":"+34 924 66 71 96",
    "sg:postcode":"06200",
    "sg:province":"Badajoz",
    "wof:name":"Distribuciones Vazquez Y Pereira S.l.",
    "wof:placetype":"venue"
},
  "geometry": {"coordinates":[-6.4021539688,38.6832695007],"type":"Point"}
}