{
  "type": "Feature",
  "properties": {
    "addr:full":"Calle de Arafo, S/n G\u00fcimar Santa Cruz De Tenerife 38500",
    "addr:housenumber":"s",
    "addr:postcode":"38500",
    "addr:street":"Calle De Arafo;/ N Gueimar",
    "iso:country":"ES",
    "sg:address":"Calle de Arafo, S/n",
    "sg:city":"G\u00fcimar",
    "sg:orig_category":"Reposter\u00cdas",
    "sg:phone":"+34 922 52 46 91",
    "sg:postcode":"38500",
    "sg:province":"Santa Cruz De Tenerife",
    "wof:name":"Cooperativa Industrial De Produccion Obrera De San Pedro",
    "wof:placetype":"venue"
},
  "geometry": {"coordinates":[-16.4117565155,28.3169822693],"type":"Point"}
}