{
  "type": "Feature",
  "properties": {
    "iso:country":"ES",
    "sg:address":"Carrer de Can Clapers, 2",
    "sg:city":"Sentmenat",
    "sg:orig_category":"M\u00c1quinas De Escribir, M\u00c1quinas Calculadoras, Maquinaria De Oficina (al Por Menor Y Alquiler)",
    "sg:phone":"+34 937 15 45 24",
    "sg:postcode":"08181",
    "sg:province":"Barcelona",
    "wof:name":"Agfa Gevaert S.a.",
    "wof:placetype":"venue"
},
  "geometry": {"coordinates":[2.1409151554,41.6144447327],"type":"Point"}
}