{
  "type": "Feature",
  "properties": {
    "iso:country":"ES",
    "sg:address":"Carrer de Ermita De Bellvitge, 41",
    "sg:city":"Hospitalet Llobregat",
    "sg:orig_category":"Ebanister\u00cda",
    "sg:phone":"+34 933 35 49 87",
    "sg:postcode":"08907",
    "sg:province":"Barcelona",
    "wof:name":"Bermudez Llamas Juan",
    "wof:placetype":"venue"
},
  "geometry": {"coordinates":[2.1091279984,41.3501625061],"type":"Point"}
}