{
  "type": "Feature",
  "properties": {
    "addr:full":"Carr Agulla, De L', 5 Cala Ratjada Islas Baleares 07590",
    "addr:housenumber":"5",
    "addr:postcode":"07590",
    "addr:street":"Carr Agulla De L '",
    "iso:country":"ES",
    "sg:address":"Carr Agulla, De L', 5",
    "sg:city":"Cala Ratjada",
    "sg:orig_category":"Bancos",
    "sg:phone":"+34 971 56 45 91",
    "sg:postcode":"07590",
    "sg:province":"Islas Baleares",
    "wof:name":"Banca March S.a.",
    "wof:placetype":"venue"
},
  "geometry": {"coordinates":[3.4626729488,39.7110137939],"type":"Point"}
}