{
  "type": "Feature",
  "properties": {
    "addr:full":"Avda De La Reu, 8 Nerva Huelva 21670",
    "addr:housenumber":"8",
    "addr:postcode":"21670",
    "addr:street":"Avda De La Reu",
    "iso:country":"ES",
    "sg:address":"Avda De La Reu, 8",
    "sg:city":"Nerva",
    "sg:orig_category":"Suministros Y Materiales Industriales",
    "sg:phone":"+34 959 58 07 58",
    "sg:postcode":"21670",
    "sg:province":"Huelva",
    "wof:name":"Fernandez Parente Mercedes",
    "wof:placetype":"venue"
},
  "geometry": {"coordinates":[-6.549987793,37.696269989],"type":"Point"}
}