{
  "type": "Feature",
  "properties": {
    "addr:full":"Calle de Pintor Pedro Flores, 6 Buenos Aires Murcia 30002",
    "addr:housenumber":"6",
    "addr:postcode":"30002",
    "addr:street":"Calle De Pintor Pedro Flores",
    "iso:country":"ES",
    "sg:address":"Calle de Pintor Pedro Flores, 6",
    "sg:city":"Buenos Aires",
    "sg:orig_category":"Peluquer\u00cdas, Peluquer\u00cda Mixta",
    "sg:phone":"+34 968 26 14 83",
    "sg:postcode":"30002",
    "sg:province":"Murcia",
    "wof:name":"Gomez Zaragoza Peluqueros C.b.",
    "wof:placetype":"venue"
},
  "geometry": {"coordinates":[-1.1274449825,37.9753417969],"type":"Point"}
}