{
  "type": "Feature",
  "properties": {
    "addr:full":"Calle de Chaparral, S/n Madrid Madrid 28033",
    "addr:housenumber":"s / n",
    "addr:postcode":"28033",
    "addr:street":"Calle De Chaparral",
    "iso:country":"ES",
    "sg:address":"Calle de Chaparral, S/n",
    "sg:city":"Madrid",
    "sg:orig_category":"Peluqueros: De Se\u00d1oras",
    "sg:phone":"+34 917 64 08 19",
    "sg:postcode":"28033",
    "sg:province":"Madrid",
    "wof:name":"Sevilla Diaz Maria Del Carmen",
    "wof:placetype":"venue"
},
  "geometry": {"coordinates":[-3.6371541023,40.4709510803],"type":"Point"}
}