{
  "type": "Feature",
  "properties": {
    "addr:full":"Av Montblanc, 196 Reus Tarragona 43206",
    "addr:housenumber":"196",
    "addr:postcode":"43206",
    "addr:street":"Av Montblanc",
    "iso:country":"ES",
    "sg:address":"Av Montblanc, 196",
    "sg:city":"Reus",
    "sg:orig_category":"Congelados: Productos Alimentarios (al Por Menor)",
    "sg:phone":"+34 977 34 09 54",
    "sg:postcode":"43206",
    "sg:province":"Tarragona",
    "wof:name":"Aguilar Castells S. L.",
    "wof:placetype":"venue"
},
  "geometry": {"coordinates":[1.1297643185,41.1746063232],"type":"Point"}
}