{
  "type": "Feature",
  "properties": {
    "addr:full":"Avda Cid Campeador, 40 Burgos Burgos 09005",
    "addr:housenumber":"40",
    "addr:postcode":"09005",
    "addr:street":"Avda Cid Campeador",
    "iso:country":"ES",
    "sg:address":"Avda Cid Campeador, 40",
    "sg:city":"Burgos",
    "sg:orig_category":"Perfumer\u00cda, Art\u00cdculos De Ba\u00d1o (fabricaci\u00d3n, Al Por Mayor)",
    "sg:phone":"+34 947 22 97 67",
    "sg:postcode":"09005",
    "sg:province":"Burgos",
    "wof:name":"Ridruejo Fuentes S.l.",
    "wof:placetype":"venue"
},
  "geometry": {"coordinates":[-3.6972529888,42.346786499],"type":"Point"}
}