{
  "type": "Feature",
  "properties": {
    "iso:country":"ES",
    "sg:address":"Via Augusta, 77",
    "sg:city":"Hospitalet Infant",
    "sg:orig_category":"T\u00c9cnicos Veterinarios",
    "sg:phone":"+34 977 82 06 03",
    "sg:postcode":"43890",
    "sg:province":"Tarragona",
    "wof:name":"Perez Perez Luis Miguel",
    "wof:placetype":"venue"
},
  "geometry": {"coordinates":[0.9179099798,40.9901695251],"type":"Point"}
}