{
  "type": "Feature",
  "properties": {
    "addr:full":"Psaj Fernando De Rojas, 13 Burgos Burgos 09007",
    "addr:housenumber":"13",
    "addr:postcode":"09007",
    "addr:street":"Fernando De Rojas",
    "iso:country":"ES",
    "sg:address":"Psaj Fernando De Rojas, 13",
    "sg:city":"Burgos",
    "sg:orig_category":"Transportes Por V\u00cdas Navegables",
    "sg:phone":"+34 947 48 81 45",
    "sg:postcode":"09007",
    "sg:province":"Burgos",
    "wof:name":"Tejedor Sinovas Jose Luis",
    "wof:placetype":"venue"
},
  "geometry": {"coordinates":[-3.6658248901,42.3479614258],"type":"Point"}
}