{
  "type": "Feature",
  "properties": {
    "addr:full":"Pl. Obpo Irurita, 2 Iru\u00f1a Navarra 31011",
    "addr:housenumber":"2",
    "addr:postcode":"31011",
    "addr:street":"Pl. Obpo Irurita",
    "iso:country":"ES",
    "sg:address":"Pl. Obpo Irurita, 2",
    "sg:city":"Iru\u00f1a",
    "sg:orig_category":"Masajes",
    "sg:phone":"+34 948 17 47 40",
    "sg:postcode":"31011",
    "sg:province":"Navarra",
    "wof:name":"Felipe Perez Francisco Javier-inza Garcia De Salamanca Juan Carlos Y Suescun Pascal Itziar Sociedad ",
    "wof:placetype":"venue"
},
  "geometry": {"coordinates":[-1.6591850519,42.8131408691],"type":"Point"}
}