{
  "type": "Feature",
  "properties": {
    "iso:country":"ES",
    "sg:address":"Calle de Empedrada, 93",
    "sg:city":"Montalban De Cordoba",
    "sg:orig_category":"Reposter\u00cdas",
    "sg:phone":"+34 957 31 00 67",
    "sg:postcode":"14548",
    "sg:province":"C\u00f3rdoba",
    "wof:name":"Picolines Y Rosquillas Maestre S.l.",
    "wof:placetype":"venue"
},
  "geometry": {"coordinates":[-4.7489748001,37.5813293457],"type":"Point"}
}