{
  "type": "Feature",
  "properties": {
    "iso:country":"ES",
    "sg:address":"Trav Dalt, 104",
    "sg:city":"Barcelona",
    "sg:orig_category":"Arquitectos",
    "sg:phone":"+34 932 13 72 97",
    "sg:postcode":"08024",
    "sg:province":"Barcelona",
    "wof:name":"Mana Reixach Fructuoso",
    "wof:placetype":"venue"
},
  "geometry": {"coordinates":[2.1580629349,41.4112167358],"type":"Point"}
}