{
  "type": "Feature",
  "properties": {
    "addr:full":"Cmno Daya, S/n Aspe Alicante 03680",
    "addr:housenumber":"s / n",
    "addr:postcode":"03680",
    "addr:street":"Cmno Daya",
    "iso:country":"ES",
    "sg:address":"Cmno Daya, S/n",
    "sg:city":"Aspe",
    "sg:orig_category":"Aguas (distribuci\u00d3n, Servicios)",
    "sg:phone":"+34 965 49 24 93",
    "sg:postcode":"03680",
    "sg:province":"Alicante",
    "wof:name":"Sociedad De Explotacion De Aguas Residuales S.a.",
    "wof:placetype":"venue"
},
  "geometry": {"coordinates":[-0.7689840198,38.3471984863],"type":"Point"}
}