{
  "type": "Feature",
  "properties": {
    "addr:full":"Calle de Pedro Lorca, 77 Torrevieja Alicante 03180",
    "addr:housenumber":"77",
    "addr:postcode":"03180",
    "addr:street":"Calle De Pedro Lorca",
    "iso:country":"ES",
    "sg:address":"Calle de Pedro Lorca, 77",
    "sg:city":"Torrevieja",
    "sg:orig_category":"Arquitectos",
    "sg:phone":"+34 965 71 65 76",
    "sg:postcode":"03180",
    "sg:province":"Alicante",
    "wof:name":"Andreu Barcena Antonia Maria",
    "wof:placetype":"venue"
},
  "geometry": {"coordinates":[-0.6758546233,37.9769477844],"type":"Point"}
}