{
  "type": "Feature",
  "properties": {
    "iso:country":"ES",
    "sg:address":"Carr Capdepera, De, S/n",
    "sg:city":"Campos",
    "sg:orig_category":"Art\u00cdculos Funerarios (al Por Menor)",
    "sg:phone":"+34 971 65 12 62",
    "sg:postcode":"07630",
    "sg:province":"Islas Baleares",
    "wof:name":"Funeraria Campanera C.b.",
    "wof:placetype":"venue"
},
  "geometry": {"coordinates":[3.017809391,39.4364929199],"type":"Point"}
}