{
  "type": "Feature",
  "properties": {
    "addr:full":"G.v. Corts Catalanes, 687 Barcelona Barcelona 08013",
    "addr:housenumber":"687",
    "addr:postcode":"08013",
    "addr:street":"Catalanes",
    "iso:country":"ES",
    "sg:address":"G.v. Corts Catalanes, 687",
    "sg:city":"Barcelona",
    "sg:orig_category":"Carnicer\u00cdas, Carnicer\u00cdas",
    "sg:phone":"+34 932 31 22 05",
    "sg:postcode":"08013",
    "sg:province":"Barcelona",
    "wof:name":"Gonzalez Carrion Emilia",
    "wof:placetype":"venue"
},
  "geometry": {"coordinates":[2.1776788235,41.3967704773],"type":"Point"}
}