{
  "type": "Feature",
  "properties": {
    "iso:country":"ES",
    "sg:address":"Calle de Caramuel, 40",
    "sg:city":"Madrid",
    "sg:orig_category":"Quiropr\u00c1cticos",
    "sg:phone":"+34 912 32 78 57",
    "sg:postcode":"28011",
    "sg:province":"Madrid",
    "wof:name":"Quironatur Sl",
    "wof:placetype":"venue"
},
  "geometry": {"coordinates":[-3.7282216549,40.4098930359],"type":"Point"}
}