{
  "type": "Feature",
  "properties": {
    "addr:full":"Avda Daroca, 80 Madrid Madrid 28017",
    "addr:housenumber":"80",
    "addr:postcode":"madrid;28017",
    "addr:street":"Avda Daroca",
    "iso:country":"ES",
    "sg:address":"Avda Daroca, 80",
    "sg:city":"Madrid",
    "sg:orig_category":"Asociaciones Humanitarias, De Cooperaci\u00d3n, De Acci\u00d3n Social",
    "sg:phone":"+34 913 26 43 74",
    "sg:postcode":"28017",
    "sg:province":"Madrid",
    "wof:name":"Fundacion Alzheimer Espa\u00f1a",
    "wof:placetype":"venue"
},
  "geometry": {"coordinates":[-3.64980793,40.4282035828],"type":"Point"}
}