{
  "type": "Feature",
  "properties": {
    "addr:full":"Carrer de Mestre Serrano, 9 Pedreguer Alicante 03750",
    "addr:housenumber":"9",
    "addr:postcode":"03750",
    "addr:street":"Carrer De Mestre Serrano",
    "iso:country":"ES",
    "sg:address":"Carrer de Mestre Serrano, 9",
    "sg:city":"Pedreguer",
    "sg:orig_category":"M\u00c9dicos: Estomatolog\u00cda",
    "sg:phone":"+34 965 76 19 43",
    "sg:postcode":"03750",
    "sg:province":"Alicante",
    "wof:name":"Domenech Perez Rosario",
    "wof:placetype":"venue"
},
  "geometry": {"coordinates":[0.0346510001,38.7943496704],"type":"Point"}
}