{
  "type": "Feature",
  "properties": {
    "iso:country":"ES",
    "sg:address":"Calle de Real, 160",
    "sg:city":"Valdestillas",
    "sg:orig_category":"Trabajos De Perforaciones, Sondeos, Construcci\u00d3n De Pozos",
    "sg:phone":"+34 983 55 12 30",
    "sg:postcode":"47240",
    "sg:province":"Valladolid",
    "wof:name":"Gonzalez Alvarez Cesareo",
    "wof:placetype":"venue"
},
  "geometry": {"coordinates":[-4.771654129,41.4874153137],"type":"Point"}
}