{
  "type": "Feature",
  "properties": {
    "iso:country":"ES",
    "sg:address":"Calle de Postas, 48",
    "sg:city":"Vitoria-gasteiz",
    "sg:orig_category":"Abogados",
    "sg:phone":"+34 945 27 51 88",
    "sg:postcode":"01004",
    "sg:province":"\u00c1lava",
    "wof:name":"Valverde Fernandez Rosario",
    "wof:placetype":"venue"
},
  "geometry": {"coordinates":[-2.6677210331,42.8453903198],"type":"Point"}
}