{
  "type": "Feature",
  "properties": {
    "addr:full":"Calle de Ruiz Tagle, 3 Torrelavega Cantabria 39300",
    "addr:housenumber":"3",
    "addr:postcode":"39300",
    "addr:street":"Calle De Ruiz Tagle",
    "iso:country":"ES",
    "sg:address":"Calle de Ruiz Tagle, 3",
    "sg:city":"Torrelavega",
    "sg:classifiers":[
        {
            "category":"Autos & Motor Vehicles",
            "subcategory":"Automobile Sales",
            "type":"Retail Goods"
        }
    ],
    "sg:phone":"+34 942 88 23 32",
    "sg:postcode":"39300",
    "sg:province":"Cantabria",
    "wof:name":"Arce Sl",
    "wof:placetype":"venue"
},
  "geometry": {"coordinates":[-4.049926281,43.3498764038],"type":"Point"}
}