{
  "type": "Feature",
  "properties": {
    "addr:full":"Calle de Antonio Martelo, 3 Malaga M\u00e1laga 29006",
    "addr:housenumber":"3",
    "addr:postcode":"29006",
    "addr:street":"Calle De Antonio Martelo;Ma\u0301Laga",
    "iso:country":"ES",
    "sg:address":"Calle de Antonio Martelo, 3",
    "sg:city":"Malaga",
    "sg:orig_category":"Art\u00cdculos De Regalo (al Por Menor)",
    "sg:phone":"+34 952 33 07 67",
    "sg:postcode":"29006",
    "sg:province":"M\u00e1laga",
    "wof:name":"Escamilla Bermudez Virginia",
    "wof:placetype":"venue"
},
  "geometry": {"coordinates":[-4.441072464,36.7108840942],"type":"Point"}
}