{
  "type": "Feature",
  "properties": {
    "addr:full":"Las Pajas, 2 Olivares Sevilla 41804",
    "addr:housenumber":"2",
    "addr:postcode":"41804",
    "addr:street":"Las Pajas;Sevilla",
    "iso:country":"ES",
    "sg:address":"Las Pajas, 2",
    "sg:city":"Olivares",
    "sg:orig_category":"Electricidad: Instaladores",
    "sg:phone":"+34 955 71 88 98",
    "sg:postcode":"41804",
    "sg:province":"Sevilla",
    "wof:name":"Electricidad Olivares S.l.",
    "wof:placetype":"venue"
},
  "geometry": {"coordinates":[-6.1581120491,37.417804718],"type":"Point"}
}