{
  "type": "Feature",
  "properties": {
    "iso:country":"ES",
    "sg:address":"Alam Tristes (de Los), S/n",
    "sg:city":"Sutullena",
    "sg:orig_category":"Centros De Educaci\u00d3n Especial",
    "sg:phone":"+34 968 46 94 52",
    "sg:postcode":"30800",
    "sg:province":"Murcia",
    "wof:name":"Colegio Publico De Preescolar Mu\u00f1oz Barberan",
    "wof:placetype":"venue"
},
  "geometry": {"coordinates":[-1.6905640364,37.680557251],"type":"Point"}
}