{
  "type": "Feature",
  "properties": {
    "iso:country":"ES",
    "sg:address":"Calle de Jose Isbert, 2",
    "sg:city":"Albacete",
    "sg:orig_category":"Ense\u00d1ante, Direcci\u00d3n",
    "sg:phone":"+34 967 24 24 88",
    "sg:postcode":"02001",
    "sg:province":"Albacete",
    "wof:name":"Anba Consulting Empresarial S.l.",
    "wof:placetype":"venue"
},
  "geometry": {"coordinates":[-1.848510623,38.996547699],"type":"Point"}
}