{
  "type": "Feature",
  "properties": {
    "iso:country":"ES",
    "sg:address":"Calle de Jalance, 5",
    "sg:city":"Valencia",
    "sg:orig_category":"Ebanister\u00cda Artesana, Restauraci\u00d3n De Muebles",
    "sg:phone":"+34 963 56 33 27",
    "sg:postcode":"46022",
    "sg:province":"Valencia",
    "wof:name":"Paniagua Ribera Manuel Angel",
    "wof:placetype":"venue"
},
  "geometry": {"coordinates":[-0.3443099856,39.4711837769],"type":"Point"}
}