{
  "type": "Feature",
  "properties": {
    "iso:country":"ES",
    "sg:address":"Carrer de Atletisme, 13",
    "sg:city":"Rubi",
    "sg:orig_category":"Transportes Por V\u00cdas Navegables",
    "sg:phone":"+34 935 87 23 80",
    "sg:postcode":"08191",
    "sg:province":"Barcelona",
    "wof:name":"Oc Catalunya Deliverie S.l.",
    "wof:placetype":"venue"
},
  "geometry": {"coordinates":[2.0417699814,41.5035018921],"type":"Point"}
}