{
  "type": "Feature",
  "properties": {
    "addr:full":"Calle de Rodriguez De La Fuente, 9 Arroyo Luz C\u00e1ceres 10900",
    "addr:housenumber":"9 arroyo",
    "addr:postcode":"10900",
    "addr:street":"Calle De Rodriguez De La Fuente;Ca\u0301Ceres",
    "iso:country":"ES",
    "sg:address":"Calle de Rodriguez De La Fuente, 9",
    "sg:city":"Arroyo Luz",
    "sg:orig_category":"Ense\u00d1anza: Comercio, Gesti\u00d3n, Inform\u00c1tica",
    "sg:phone":"+34 927 27 12 40",
    "sg:postcode":"10900",
    "sg:province":"C\u00e1ceres",
    "wof:name":"Diaz Guardado Nicolas Vicente",
    "wof:placetype":"venue"
},
  "geometry": {"coordinates":[-6.5808820724,39.4831466675],"type":"Point"}
}