{
  "type": "Feature",
  "properties": {
    "addr:full":"Trva Inchostia / Intxostia, 12 Alsasua Navarra 31800",
    "addr:housenumber":"12",
    "addr:postcode":"31800",
    "addr:street":"Trva Inchostia / Intxostia",
    "iso:country":"ES",
    "sg:address":"Trva Inchostia / Intxostia, 12",
    "sg:city":"Alsasua",
    "sg:orig_category":"Ropa Para Se\u00d1oras (al Por Menor)",
    "sg:phone":"+34 948 56 27 56",
    "sg:postcode":"31800",
    "sg:province":"Navarra",
    "wof:name":"Azurmendi Aldasoro Juan Jose",
    "wof:placetype":"venue"
},
  "geometry": {"coordinates":[-2.1941597462,42.9304695129],"type":"Point"}
}