{
  "type": "Feature",
  "properties": {
    "addr:full":"Carrer de Riu Mogent (del), 4 Montornes Centre Barcelona 08170",
    "addr:housenumber":"4",
    "addr:postcode":"08170",
    "addr:street":"Carrer De Riu Mogent Del;Centre Barcelona",
    "iso:country":"ES",
    "sg:address":"Carrer de Riu Mogent (del), 4",
    "sg:city":"Montornes Centre",
    "sg:orig_category":"Librer\u00cdas",
    "sg:phone":"+34 935 68 19 97",
    "sg:postcode":"08170",
    "sg:province":"Barcelona",
    "wof:name":"Molina Garcia Enrique",
    "wof:placetype":"venue"
},
  "geometry": {"coordinates":[2.2657339573,41.5428276062],"type":"Point"}
}