{
  "type": "Feature",
  "properties": {
    "addr:full":"C/ Mestre Guell, 68 Tarrega Lleida 25300",
    "addr:housenumber":"68",
    "addr:postcode":"25300",
    "addr:street":"C / Mestre Guell",
    "iso:country":"ES",
    "sg:address":"C/ Mestre Guell, 68",
    "sg:city":"Tarrega",
    "sg:orig_category":"Armas Y Municiones (fabricaci\u00d3n, Al Por Mayor)",
    "sg:phone":"+34 973 31 24 98",
    "sg:postcode":"25300",
    "sg:province":"Lleida",
    "sg:website":"www.bori-armeria.com",
    "wof:name":"Bori Miquel Jose",
    "wof:placetype":"venue"
},
  "geometry": {"coordinates":[1.1444979906,41.6494255066],"type":"Point"}
}