{
  "type": "Feature",
  "properties": {
    "iso:country":"ES",
    "sg:address":"Rond President Tarradellas, 92",
    "sg:city":"Mataro",
    "sg:orig_category":"Prendas Y Chalecos De Punto (al Por Menor)",
    "sg:phone":"+34 937 57 06 35",
    "sg:postcode":"08303",
    "sg:province":"Barcelona",
    "wof:name":"15-30 Points S.l.",
    "wof:placetype":"venue"
},
  "geometry": {"coordinates":[2.421216,41.539257],"type":"Point"}
}