{
  "type": "Feature",
  "properties": {
    "addr:full":"Calle de Monet, 1 Algeciras C\u00e1diz 11201",
    "addr:housenumber":"1;ca\u0301diz",
    "addr:postcode":"11201",
    "addr:street":"Calle De Monet",
    "iso:country":"ES",
    "sg:address":"Calle de Monet, 1",
    "sg:city":"Algeciras",
    "sg:orig_category":"Abogados",
    "sg:phone":"+34 956 63 01 91",
    "sg:postcode":"11201",
    "sg:province":"C\u00e1diz",
    "wof:name":"Gil Belmonte Susana",
    "wof:placetype":"venue"
},
  "geometry": {"coordinates":[-5.4460878372,36.1283187866],"type":"Point"}
}