{
  "type": "Feature",
  "properties": {
    "addr:full":"Av Barcelona, 221 Cunit Tarragona 43881",
    "addr:housenumber":"221",
    "addr:postcode":"43881",
    "addr:street":"Av Barcelona",
    "iso:country":"ES",
    "sg:address":"Av Barcelona, 221",
    "sg:city":"Cunit",
    "sg:orig_category":"Platos Preparados Refrigerados (fabricaci\u00d3n, Al Por Mayor)",
    "sg:phone":"+34 977 67 52 09",
    "sg:postcode":"43881",
    "sg:province":"Tarragona",
    "wof:name":"Cabrerizo Lorenzo Julio",
    "wof:placetype":"venue"
},
  "geometry": {"coordinates":[1.6366499662,41.1988105774],"type":"Point"}
}