{
  "type": "Feature",
  "properties": {
    "addr:full":"Calle de Santa Ana, 12 Villarrubia De Los Ojos Ciudad Real 13670",
    "addr:housenumber":"12",
    "addr:postcode":"13670",
    "addr:street":"Calle De Santa Ana",
    "iso:country":"ES",
    "sg:address":"Calle de Santa Ana, 12",
    "sg:city":"Villarrubia De Los Ojos",
    "sg:orig_category":"Alimentaci\u00d3n General (al Por Menor)",
    "sg:phone":"+34 926 89 66 36",
    "sg:postcode":"13670",
    "sg:province":"Ciudad Real",
    "wof:name":"Plana Zamora Jose Cecilio",
    "wof:placetype":"venue"
},
  "geometry": {"coordinates":[-3.6007990837,39.219291687],"type":"Point"}
}