{
  "type": "Feature",
  "properties": {
    "addr:full":"Calle de Rafael Alberti, 33 Almoradi Alicante 03160",
    "addr:housenumber":"33",
    "addr:postcode":"03160",
    "addr:street":"Calle De Rafael Alberti",
    "iso:country":"ES",
    "sg:address":"Calle de Rafael Alberti, 33",
    "sg:city":"Almoradi",
    "sg:orig_category":"Cuchiller\u00cda (al Por Menor)",
    "sg:phone":"+34 966 78 13 12",
    "sg:postcode":"03160",
    "sg:province":"Alicante",
    "wof:name":"Gonzalez Garcia Eduardo",
    "wof:placetype":"venue"
},
  "geometry": {"coordinates":[-0.7940729856,38.1092338562],"type":"Point"}
}