{
  "type": "Feature",
  "properties": {
    "addr:full":"Calle de Antonio Maura, 10 Elda Alicante 03600",
    "addr:housenumber":"10",
    "addr:postcode":"03600",
    "addr:street":"Calle De Antonio Maura",
    "iso:country":"ES",
    "sg:address":"Calle de Antonio Maura, 10",
    "sg:city":"Elda",
    "sg:orig_category":"Agencias Y Agentes Comerciales, Representantes",
    "sg:phone":"+34 965 38 29 58",
    "sg:postcode":"03600",
    "sg:province":"Alicante",
    "wof:name":"Vera Rico Pascual",
    "wof:placetype":"venue"
},
  "geometry": {"coordinates":[-0.7963870168,38.4769248962],"type":"Point"}
}