{
  "type": "Feature",
  "properties": {
    "iso:country":"ES",
    "sg:address":"Calle de Blanco, 6",
    "sg:city":"Puerto Cruz",
    "sg:orig_category":"Cl\u00cdnicas Dentales",
    "sg:phone":"+34 922 37 36 18",
    "sg:postcode":"38400",
    "sg:province":"Santa Cruz De Tenerife",
    "wof:name":"Mendez Ortiz Jose Domingo",
    "wof:placetype":"venue"
},
  "geometry": {"coordinates":[-16.550365448,28.4157714844],"type":"Point"}
}