{
  "type": "Feature",
  "properties": {
    "iso:country":"ES",
    "sg:address":"Avda Fuente (de La), 121",
    "sg:city":"Cella",
    "sg:orig_category":"Molduras, Junquillos, Listones Y Molduras Perforadas",
    "sg:phone":"+34 978 65 01 56",
    "sg:postcode":"44370",
    "sg:province":"Teruel",
    "wof:name":"Rubio Vermeulen Maria Jose",
    "wof:placetype":"venue"
},
  "geometry": {"coordinates":[-1.2938289642,40.4562416077],"type":"Point"}
}