{
  "type": "Feature",
  "properties": {
    "iso:country":"ES",
    "sg:address":"Cami Rodees, S/n",
    "sg:city":"Mao",
    "sg:orig_category":"Bancos",
    "sg:phone":"+34 971 36 93 35",
    "sg:postcode":"07714",
    "sg:province":"Islas Baleares",
    "wof:name":"Banca March S.a.",
    "wof:placetype":"venue"
},
  "geometry": {"coordinates":[4.2547740936,39.884979248],"type":"Point"}
}