{
  "type": "Feature",
  "properties": {
    "iso:country":"ES",
    "sg:address":"Rua Ribeira De Fefi\u00d1ans, 12",
    "sg:city":"Cambados",
    "sg:orig_category":"Promotores Constructores",
    "sg:phone":"+34 986 53 19 19",
    "sg:postcode":"36630",
    "sg:province":"Pontevedra",
    "wof:name":"Emilio Casaldarnos S.l.",
    "wof:placetype":"venue"
},
  "geometry": {"coordinates":[-8.8170986176,42.5187568665],"type":"Point"}
}