{
  "type": "Feature",
  "properties": {
    "addr:full":"Calle de Yerma, 5 Huetor-vega Granada 18198",
    "addr:housenumber":"5",
    "addr:postcode":"18198",
    "addr:street":"Calle De Yerma",
    "iso:country":"ES",
    "sg:address":"Calle de Yerma, 5",
    "sg:city":"Huetor-vega",
    "sg:orig_category":"Mec\u00c1nico Del Autom\u00d3vil",
    "sg:phone":"+34 958 30 19 33",
    "sg:postcode":"18198",
    "sg:province":"Granada",
    "wof:name":"Nave Auto C. B.",
    "wof:placetype":"venue"
},
  "geometry": {"coordinates":[-3.566808939,37.1511001587],"type":"Point"}
}