{
  "type": "Feature",
  "properties": {
    "addr:full":"Calle de Coscojales, 17 Portugalete Vizcaya 48920",
    "addr:housenumber":"17",
    "addr:postcode":"48920",
    "addr:street":"Calle De Coscojales",
    "iso:country":"ES",
    "sg:address":"Calle de Coscojales, 17",
    "sg:city":"Portugalete",
    "sg:orig_category":"Restaurantes",
    "sg:phone":"+34 944 96 11 85",
    "sg:postcode":"48920",
    "sg:province":"Vizcaya",
    "wof:name":"Fermin Martinez Martinez Y Miguel Angel Pila Rueda C.b.",
    "wof:placetype":"venue"
},
  "geometry": {"coordinates":[-3.0184080601,43.3204269409],"type":"Point"}
}