{
  "type": "Feature",
  "properties": {
    "addr:full":"Calle de Virgen De Gracia, 33 Balmaseda Vizcaya 48800",
    "addr:housenumber":"33",
    "addr:postcode":"48800",
    "addr:street":"Calle De Virgen De Gracia",
    "iso:country":"ES",
    "sg:address":"Calle de Virgen De Gracia, 33",
    "sg:city":"Balmaseda",
    "sg:orig_category":"Empresas De Carpinter\u00cda De Madera",
    "sg:phone":"+34 946 80 02 69",
    "sg:postcode":"48800",
    "sg:province":"Vizcaya",
    "wof:name":"Mobiliario Bernales S.l.",
    "wof:placetype":"venue"
},
  "geometry": {"coordinates":[-3.2026810646,43.1965408325],"type":"Point"}
}