{
  "type": "Feature",
  "properties": {
    "iso:country":"ES",
    "sg:address":"Rond Toledo, 11",
    "sg:city":"Ciudad Real",
    "sg:orig_category":"Mec\u00c1nico Del Autom\u00d3vil",
    "sg:phone":"+34 926 22 03 07",
    "sg:postcode":"13003",
    "sg:province":"Ciudad Real",
    "wof:name":"Dondarza Vargas Roman",
    "wof:placetype":"venue"
},
  "geometry": {"coordinates":[-3.9284899235,38.9874763489],"type":"Point"}
}