{
  "type": "Feature",
  "properties": {
    "addr:full":"Ctra. Guadalupe, S/n Villanueva Serena Badajoz 06700",
    "addr:postcode":"06700",
    "addr:street":"Ctra. Guadalupe S / N Villanueva Serena",
    "iso:country":"ES",
    "sg:address":"Ctra. Guadalupe, S/n",
    "sg:city":"Villanueva Serena",
    "sg:orig_category":"Materias Pl\u00c1sticas: Productos Acabados Y Semiacabados (fabricaci\u00d3n)",
    "sg:phone":"+34 924 84 16 44",
    "sg:postcode":"06700",
    "sg:province":"Badajoz",
    "wof:name":"Aislamiento Extrepol S.l.",
    "wof:placetype":"venue"
},
  "geometry": {"coordinates":[-5.7960896492,38.9875183105],"type":"Point"}
}