{
  "type": "Feature",
  "properties": {
    "iso:country":"ES",
    "sg:address":"Carr Antiga, 42",
    "sg:city":"Blanes",
    "sg:orig_category":"Venta, Instalaci\u00d3n, Reparaci\u00d3n De Antenas Para Televisi\u00d3n",
    "sg:phone":"+34 972 33 67 80",
    "sg:postcode":"17300",
    "sg:province":"Girona",
    "wof:name":"Estol Ferrer Ramon",
    "wof:placetype":"venue"
},
  "geometry": {"coordinates":[2.7878789902,41.6749382019],"type":"Point"}
}