{
  "type": "Feature",
  "properties": {
    "iso:country":"ES",
    "sg:address":"Calle de Iruela (la), S/n",
    "sg:city":"Jaen",
    "sg:orig_category":"Electricidad: Instaladores",
    "sg:phone":"+34 953 28 01 37",
    "sg:postcode":"23009",
    "sg:province":"Ja\u00e9n",
    "wof:name":"Electro-centre Jaen S.l.",
    "wof:placetype":"venue"
},
  "geometry": {"coordinates":[-3.7815639973,37.8031997681],"type":"Point"}
}