{
  "type": "Feature",
  "properties": {
    "addr:full":"Poligono Industrial, S/n Sahagun Le\u00f3n 24320",
    "addr:postcode":"24320",
    "addr:street":"Industrial S / N Sahagun Leo\u0301N",
    "iso:country":"ES",
    "sg:address":"Poligono Industrial, S/n",
    "sg:city":"Sahagun",
    "sg:orig_category":"Chapister\u00cda",
    "sg:phone":"+34 987 78 01 64",
    "sg:postcode":"24320",
    "sg:province":"Le\u00f3n",
    "wof:name":"Talleres Metalicos Del Cea Sl",
    "wof:placetype":"venue"
},
  "geometry": {"coordinates":[-5.026113987,42.3711051941],"type":"Point"}
}