{
  "type": "Feature",
  "properties": {
    "iso:country":"ES",
    "sg:address":"Carrer de Comte Borrell, 158",
    "sg:city":"Barcelona",
    "sg:orig_category":"Centros Empresariales",
    "sg:phone":"+34 934 53 35 74",
    "sg:postcode":"08015",
    "sg:province":"Barcelona",
    "wof:name":"Tab Retail Experts 2002 S.l.",
    "wof:placetype":"venue"
},
  "geometry": {"coordinates":[2.1549470425,41.3833656311],"type":"Point"}
}