{
  "type": "Feature",
  "properties": {
    "addr:full":"Rua Magdalena, 137 Ferrol La Coru\u00f1a 15402",
    "addr:housenumber":"137",
    "addr:postcode":"15402",
    "addr:street":"Rua Magdalena;La Corun\u0303A",
    "iso:country":"ES",
    "sg:address":"Rua Magdalena, 137",
    "sg:city":"Ferrol",
    "sg:orig_category":"Caf\u00c9s, Bares, Cervecer\u00cdas",
    "sg:phone":"+34 981 35 12 19",
    "sg:postcode":"15402",
    "sg:province":"La Coru\u00f1a",
    "wof:name":"Ares Miguez Jose Maria",
    "wof:placetype":"venue"
},
  "geometry": {"coordinates":[-8.2339506149,43.4830970764],"type":"Point"}
}