{
  "type": "Feature",
  "properties": {
    "iso:country":"ES",
    "sg:address":"Calle de Rosa Bahamonde, 7",
    "sg:city":"Tui",
    "sg:orig_category":"Abogados",
    "sg:phone":"+34 986 60 36 84",
    "sg:postcode":"36700",
    "sg:province":"Pontevedra",
    "wof:name":"Magan Rivera Jose Ramon",
    "wof:placetype":"venue"
},
  "geometry": {"coordinates":[-8.6455602646,42.0485038757],"type":"Point"}
}