{
  "type": "Feature",
  "properties": {
    "addr:full":"A Zorrero, 36 Palomares Rio Sevilla 41928",
    "addr:housenumber":"36",
    "addr:postcode":"41928",
    "addr:street":"Zorrero;Rio Sevilla",
    "iso:country":"ES",
    "sg:address":"A Zorrero, 36",
    "sg:city":"Palomares Rio",
    "sg:orig_category":"Asilos De Ancianos. Centros Privados",
    "sg:phone":"+34 955 76 43 91",
    "sg:postcode":"41928",
    "sg:province":"Sevilla",
    "wof:name":"Quintana Grima Elizabeth",
    "wof:placetype":"venue"
},
  "geometry": {"coordinates":[-6.0593338013,37.3218765259],"type":"Point"}
}