{
  "type": "Feature",
  "properties": {
    "iso:country":"ES",
    "sg:address":"Av Gabriel Roca, 9",
    "sg:city":"Palma",
    "sg:orig_category":"Regalos, Souvenires (fabricaci\u00d3n, Al Por Mayor)",
    "sg:phone":"+34 971 73 60 37",
    "sg:postcode":"07014",
    "sg:province":"Islas Baleares",
    "wof:name":"Torrens Riera Maria Magdalena",
    "wof:placetype":"venue"
},
  "geometry": {"coordinates":[2.6316139698,39.5684814453],"type":"Point"}
}