{
  "type": "Feature",
  "properties": {
    "addr:full":"Carrer de Illes Balears, 2 Castellar Valles Barcelona 08211",
    "addr:housenumber":"2",
    "addr:postcode":"08211",
    "addr:street":"Carrer De Illes Balears",
    "iso:country":"ES",
    "sg:address":"Carrer de Illes Balears, 2",
    "sg:city":"Castellar Valles",
    "sg:orig_category":"Mercer\u00cda, Lencer\u00cda (al Por Menor)",
    "sg:phone":"+34 937 14 67 57",
    "sg:postcode":"08211",
    "sg:province":"Barcelona",
    "wof:name":"Fabregas Masllovet Maria Asuncion",
    "wof:placetype":"venue"
},
  "geometry": {"coordinates":[2.0904119015,41.6137313843],"type":"Point"}
}