{
  "type": "Feature",
  "properties": {
    "addr:full":"Calle de Estudio, 6 Madrid Madrid 28023",
    "addr:housenumber":"6",
    "addr:postcode":"28023",
    "addr:street":"Calle De Estudio",
    "iso:country":"ES",
    "sg:address":"Calle de Estudio, 6",
    "sg:city":"Madrid",
    "sg:orig_category":"Centros De Educaci\u00d3n Especial",
    "sg:phone":"+34 913 07 81 75",
    "sg:postcode":"28023",
    "sg:province":"Madrid",
    "wof:name":"Profeduca S.l.",
    "wof:placetype":"venue"
},
  "geometry": {"coordinates":[-3.7848825455,40.4603996277],"type":"Point"}
}