{
  "type": "Feature",
  "properties": {
    "iso:country":"ES",
    "sg:address":"Plaz Mayor, 5",
    "sg:city":"Fuente S. Esteban",
    "sg:orig_category":"Librer\u00cdas",
    "sg:phone":"+34 923 44 02 22",
    "sg:postcode":"37200",
    "sg:province":"Salamanca",
    "wof:name":"Calvo Moro Andres",
    "wof:placetype":"venue"
},
  "geometry": {"coordinates":[-6.1650328636,40.826171875],"type":"Point"}
}