{
  "type": "Feature",
  "properties": {
    "iso:country":"ES",
    "sg:address":"Calle de Santa Felicitas, 7",
    "sg:city":"Alacant",
    "sg:orig_category":"Farmacias",
    "sg:phone":"+34 965 12 48 79",
    "sg:postcode":"03005",
    "sg:province":"Alicante",
    "wof:name":"Ortega Castro Luis",
    "wof:placetype":"venue"
},
  "geometry": {"coordinates":[-0.4946449995,38.3485527039],"type":"Point"}
}