{
  "type": "Feature",
  "properties": {
    "iso:country":"ES",
    "sg:address":"Calle de Marcos Zapata, 17",
    "sg:city":"Malaga",
    "sg:orig_category":"Aparatos E Instalaci\u00d3n De Regad\u00cdos",
    "sg:phone":"+34 952 20 07 04",
    "sg:postcode":"29017",
    "sg:province":"M\u00e1laga",
    "wof:name":"Jardineria Y Riegos Alarcon S.l",
    "wof:placetype":"venue"
},
  "geometry": {"coordinates":[-4.3632850647,36.7229728699],"type":"Point"}
}