{
  "type": "Feature",
  "properties": {
    "addr:full":"Carrer de Turo De Monterols, 13 Barcelona Barcelona 08006",
    "addr:housenumber":"13",
    "addr:postcode":"08006",
    "addr:street":"Carrer De Turo De Monterols",
    "iso:country":"ES",
    "sg:address":"Carrer de Turo De Monterols, 13",
    "sg:city":"Barcelona",
    "sg:orig_category":"Asesor\u00cdas Y Estudios Financieros",
    "sg:phone":"+34 932 01 96 05",
    "sg:postcode":"08006",
    "sg:province":"Barcelona",
    "wof:name":"Pages Marti Santiago",
    "wof:placetype":"venue"
},
  "geometry": {"coordinates":[2.142457962,41.4021377563],"type":"Point"}
}