{
  "type": "Feature",
  "properties": {
    "addr:full":"Calle de Enmedio, 12 Elche Sierra Albacete 02430",
    "addr:housenumber":"12",
    "addr:postcode":"02430",
    "addr:street":"Calle De Enmedio;Sierra",
    "iso:country":"ES",
    "sg:address":"Calle de Enmedio, 12",
    "sg:city":"Elche Sierra",
    "sg:orig_category":"Iglesia Cat\u00d3lica",
    "sg:phone":"+34 967 41 00 58",
    "sg:postcode":"02430",
    "sg:province":"Albacete",
    "wof:name":"Parroquia Santa Quiteria",
    "wof:placetype":"venue"
},
  "geometry": {"coordinates":[-2.048081398,38.4473724365],"type":"Point"}
}