{
  "type": "Feature",
  "properties": {
    "addr:full":"Avda Bruselas, 54 Madrid Madrid 28028",
    "addr:housenumber":"54",
    "addr:postcode":"madrid;28028",
    "addr:street":"Avda Bruselas",
    "iso:country":"ES",
    "sg:address":"Avda Bruselas, 54",
    "sg:city":"Madrid",
    "sg:orig_category":"Art\u00cdculos De Regalo (al Por Menor)",
    "sg:phone":"+34 917 26 80 00",
    "sg:postcode":"28028",
    "sg:province":"Madrid",
    "wof:name":"Martin Perez Concepcion",
    "wof:placetype":"venue"
},
  "geometry": {"coordinates":[-3.6629664898,40.439125061],"type":"Point"}
}