{
  "type": "Feature",
  "properties": {
    "iso:country":"ES",
    "sg:address":"Calle de Hilados, 14",
    "sg:city":"Torrejon Ardoz",
    "sg:orig_category":"Electricidad: Instaladores",
    "sg:phone":"+34 916 75 52 99",
    "sg:postcode":"28850",
    "sg:province":"Madrid",
    "wof:name":"Murillo Romero Juan",
    "wof:placetype":"venue"
},
  "geometry": {"coordinates":[-3.4602138996,40.4462242126],"type":"Point"}
}