{
  "type": "Feature",
  "properties": {
    "addr:full":"Rbla Jaume I, 9 Cambrils Tarragona 43850",
    "addr:housenumber":"9",
    "addr:postcode":"43850",
    "addr:street":"Rbla Jaume I",
    "iso:country":"ES",
    "sg:address":"Rbla Jaume I, 9",
    "sg:city":"Cambrils",
    "sg:orig_category":"Agencias De Viajes",
    "sg:phone":"+34 977 36 63 68",
    "sg:postcode":"43850",
    "sg:province":"Tarragona",
    "sg:website":"www.halconviajes.com",
    "wof:name":"Viajes Halcon S.a.",
    "wof:placetype":"venue"
},
  "geometry": {"coordinates":[1.0581309795,41.0667648315],"type":"Point"}
}