{
  "type": "Feature",
  "properties": {
    "iso:country":"ES",
    "sg:address":"V. Tordera, 50",
    "sg:city":"Cuenca",
    "sg:orig_category":"Negocio De Materiales De Construcci\u00d3n",
    "sg:phone":"+34 969 21 19 90",
    "sg:postcode":"16003",
    "sg:province":"Cuenca",
    "wof:name":"Macia Garcia Joaquin",
    "wof:placetype":"venue"
},
  "geometry": {"coordinates":[-2.1365289688,40.0527305603],"type":"Point"}
}