{
  "type": "Feature",
  "properties": {
    "iso:country":"ES",
    "sg:address":"Calle de Tte Ferra Fiol, 53",
    "sg:city":"Palma",
    "sg:orig_category":"Electrodom\u00c9sticos (al Por Menor)",
    "sg:phone":"+34 971 20 65 50",
    "sg:postcode":"07004",
    "sg:province":"Islas Baleares",
    "wof:name":"Mas Mas Jaime",
    "wof:placetype":"venue"
},
  "geometry": {"coordinates":[2.6604719162,39.5870895386],"type":"Point"}
}