{
  "type": "Feature",
  "properties": {
    "addr:full":"Calle de Paz (la), 14 Avila \u00c1vila 05003",
    "addr:housenumber":"14",
    "addr:postcode":"05003",
    "addr:street":"Calle De Paz La;A\u0301Vila",
    "iso:country":"ES",
    "sg:address":"Calle de Paz (la), 14",
    "sg:city":"Avila",
    "sg:orig_category":"Agencias Y Asesores De Publicidad",
    "sg:phone":"+34 920 25 02 38",
    "sg:postcode":"05003",
    "sg:province":"\u00c1vila",
    "wof:name":"Vidicam Imagen Y Sonido S.l.",
    "wof:placetype":"venue"
},
  "geometry": {"coordinates":[-4.6951332092,40.6513061523],"type":"Point"}
}