{
  "type": "Feature",
  "properties": {
    "addr:full":"Avda Prensa (la), 28 Sevilla Sevilla 41007",
    "addr:housenumber":"28",
    "addr:postcode":"41007",
    "addr:street":"Avda Prensa La",
    "iso:country":"ES",
    "sg:address":"Avda Prensa (la), 28",
    "sg:city":"Sevilla",
    "sg:orig_category":"Materiales De Construcci\u00d3n (en General)",
    "sg:phone":"+34 954 25 95 06",
    "sg:postcode":"41007",
    "sg:province":"Sevilla",
    "wof:name":"Almacen Vidrio Automocion S.a.",
    "wof:placetype":"venue"
},
  "geometry": {"coordinates":[-5.9514756203,37.3896026611],"type":"Point"}
}