{
  "type": "Feature",
  "properties": {
    "iso:country":"ES",
    "sg:address":"Calle de San Vicente Ferrer, 1",
    "sg:city":"Peligros",
    "sg:orig_category":"Confecci\u00d3n (fabricaci\u00d3n, Al Por Mayor)",
    "sg:phone":"+34 958 40 00 26",
    "sg:postcode":"18210",
    "sg:province":"Granada",
    "wof:name":"Jimenez Lopez Jose",
    "wof:placetype":"venue"
},
  "geometry": {"coordinates":[-3.6290290356,37.2308883667],"type":"Point"}
}