{
  "type": "Feature",
  "properties": {
    "addr:full":"Calle de Daoiz, 2 Huesas Las Palmas 35200",
    "addr:housenumber":"2",
    "addr:postcode":"35200",
    "addr:street":"Calle De Daoiz;Las Palmas",
    "iso:country":"ES",
    "sg:address":"Calle de Daoiz, 2",
    "sg:city":"Huesas",
    "sg:orig_category":"Agentes, Concesionarios Y Sucursales De Camiones Y Veh\u00cdculos Industriales",
    "sg:phone":"+34 928 68 01 50",
    "sg:postcode":"35200",
    "sg:province":"Las Palmas",
    "wof:name":"F.caballero Massieu S.a.",
    "wof:placetype":"venue"
},
  "geometry": {"coordinates":[-15.3928136826,27.9845066071],"type":"Point"}
}