{
  "type": "Feature",
  "properties": {
    "addr:full":"Carr Doctor Camps, 2 Mao Islas Baleares 07703",
    "addr:housenumber":"2",
    "addr:postcode":"07703",
    "addr:street":"Carr Doctor Camps",
    "iso:country":"ES",
    "sg:address":"Carr Doctor Camps, 2",
    "sg:city":"Mao",
    "sg:orig_category":"Cl\u00cdnicas Dentales",
    "sg:phone":"+34 971 36 80 54",
    "sg:postcode":"07703",
    "sg:province":"Islas Baleares",
    "wof:name":"Instituto Odontologico Massi S.l.",
    "wof:placetype":"venue"
},
  "geometry": {"coordinates":[4.2590122223,39.8856544495],"type":"Point"}
}