{
  "type": "Feature",
  "properties": {
    "iso:country":"ES",
    "sg:address":"Pl Gal.la Placidia, S/n",
    "sg:city":"Barcelona",
    "sg:orig_category":"Poller\u00cda Y Caza (al Por Menor)",
    "sg:phone":"+34 932 18 95 44",
    "sg:postcode":"08006",
    "sg:province":"Barcelona",
    "wof:name":"Saez Cruz Rosa",
    "wof:placetype":"venue"
},
  "geometry": {"coordinates":[2.1523690224,41.399772644],"type":"Point"}
}