{
  "type": "Feature",
  "properties": {
    "iso:country":"ES",
    "sg:address":"Calle de Valdegovia, 8",
    "sg:city":"Madrid",
    "sg:orig_category":"Art\u00cdculos Funerarios (al Por Menor)",
    "sg:phone":"+34 917 29 21 69",
    "sg:postcode":"28034",
    "sg:province":"Madrid",
    "wof:name":"Funeraria Nuestra Se\u00d1ora De Los Remedios S.l.",
    "wof:placetype":"venue"
},
  "geometry": {"coordinates":[-3.6871080399,40.4886245728],"type":"Point"}
}