{
  "type": "Feature",
  "properties": {
    "iso:country":"ES",
    "sg:address":"Calle de Rey Pastor, 36",
    "sg:city":"Leganes",
    "sg:orig_category":"Electricidad, Electr\u00d3nica: Suministros (al Por Menor)",
    "sg:phone":"+34 916 86 44 92",
    "sg:postcode":"28914",
    "sg:province":"Madrid",
    "sg:website":"www.aeq.es",
    "wof:name":"Aplicaciones Electronicas Quasar S. A.",
    "wof:placetype":"venue"
},
  "geometry": {"coordinates":[-3.7389435768,40.3309020996],"type":"Point"}
}