{
  "type": "Feature",
  "properties": {
    "addr:full":"Calle de Oro, 59 Valladolid Valladolid 47012",
    "addr:housenumber":"59",
    "addr:postcode":"47012",
    "addr:street":"Calle De Oro",
    "iso:country":"ES",
    "sg:address":"Calle de Oro, 59",
    "sg:city":"Valladolid",
    "sg:orig_category":"Almacenes Frigor\u00cdficos",
    "sg:phone":"+34 983 20 49 28",
    "sg:postcode":"47012",
    "sg:province":"Valladolid",
    "wof:name":"Casas De Impermeabilizacion S.l.",
    "wof:placetype":"venue"
},
  "geometry": {"coordinates":[-4.7104558945,41.6141014099],"type":"Point"}
}