{
  "type": "Feature",
  "properties": {
    "addr:full":"Can Marques, Km. 0009,0 Serra Barcelona 08420",
    "addr:postcode":"08420",
    "addr:street":"Km. 0009,0",
    "iso:country":"ES",
    "sg:address":"Can Marques, Km. 0009,0",
    "sg:city":"Serra",
    "sg:orig_category":"Metacrilato: Art\u00cdculos (fabricaci\u00d3n Y Al Por Mayor)",
    "sg:phone":"+34 938 46 70 93",
    "sg:postcode":"08420",
    "sg:province":"Barcelona",
    "wof:name":"Sanchez Bravo Carmen",
    "wof:placetype":"venue"
},
  "geometry": {"coordinates":[2.2783401012,41.6220207214],"type":"Point"}
}