{
  "type": "Feature",
  "properties": {
    "addr:full":"Carrer de Sant Pere, 58 Barbera Valles Barcelona 08210",
    "addr:housenumber":"58",
    "addr:postcode":"08210",
    "addr:street":"Carrer De Sant Pere",
    "iso:country":"ES",
    "sg:address":"Carrer de Sant Pere, 58",
    "sg:city":"Barbera Valles",
    "sg:orig_category":"Molduras, Junquillos, Listones Y Molduras Perforadas",
    "sg:phone":"+34 937 18 88 55",
    "sg:postcode":"08210",
    "sg:province":"Barcelona",
    "wof:name":"Morales Barajas Marcelo",
    "wof:placetype":"venue"
},
  "geometry": {"coordinates":[2.1289110184,41.517742157],"type":"Point"}
}