{
  "type": "Feature",
  "properties": {
    "addr:full":"Carrer de Llenguadoc, 72 Barcelona Barcelona 08030",
    "addr:housenumber":"72",
    "addr:postcode":"08030",
    "addr:street":"Carrer De Llenguadoc",
    "iso:country":"ES",
    "sg:address":"Carrer de Llenguadoc, 72",
    "sg:city":"Barcelona",
    "sg:orig_category":"Aparatos, Sistemas De Tele",
    "sg:phone":"+34 933 11 66 71",
    "sg:postcode":"08030",
    "sg:province":"Barcelona",
    "wof:name":"Martinez Purja Jorge",
    "wof:placetype":"venue"
},
  "geometry": {"coordinates":[2.1865980625,41.4308280945],"type":"Point"}
}