{
  "type": "Feature",
  "properties": {
    "addr:full":"Trav Corts, 262 Barcelona Barcelona 08014",
    "addr:housenumber":"262",
    "addr:postcode":"08014",
    "addr:street":"Trav Corts",
    "iso:country":"ES",
    "sg:address":"Trav Corts, 262",
    "sg:city":"Barcelona",
    "sg:orig_category":"Agencias De Viajes",
    "sg:phone":"+34 933 63 48 62",
    "sg:postcode":"08014",
    "sg:province":"Barcelona",
    "sg:website":"www.viajeselcorteingles.es",
    "wof:name":"Viajes El Corte Ingles S A",
    "wof:placetype":"venue"
},
  "geometry": {"coordinates":[2.1341700554,41.3862991333],"type":"Point"}
}