{
  "type": "Feature",
  "properties": {
    "iso:country":"ES",
    "sg:address":"Carrer de Portaferrissa, 18",
    "sg:city":"Barcelona",
    "sg:orig_category":"Ropa Para Ni\u00d1os (al Por Menor)",
    "sg:phone":"+34 933 18 33 92",
    "sg:postcode":"08002",
    "sg:province":"Barcelona",
    "wof:name":"Beyma S. A.",
    "wof:placetype":"venue"
},
  "geometry": {"coordinates":[2.1729369164,41.3833808899],"type":"Point"}
}