{
  "type": "Feature",
  "properties": {
    "iso:country":"ES",
    "sg:address":"Carr Margarida Xirgu, 74",
    "sg:city":"Badalona",
    "sg:orig_category":"Fabricaci\u00d3n De Pernos, Tornillos Y Clavos",
    "sg:phone":"+34 933 89 11 21",
    "sg:postcode":"08911",
    "sg:province":"Barcelona",
    "wof:name":"Industrial Tecnic Global Control S.l.",
    "wof:placetype":"venue"
},
  "geometry": {"coordinates":[2.2510008812,41.4553947449],"type":"Point"}
}