{
  "type": "Feature",
  "properties": {
    "addr:full":"Pla\u00c7 Poeta Marquina, 6 Girona Girona 17002",
    "addr:housenumber":"6",
    "addr:postcode":"17002",
    "addr:street":"Poeta Marquina",
    "iso:country":"ES",
    "sg:address":"Pla\u00c7 Poeta Marquina, 6",
    "sg:city":"Girona",
    "sg:orig_category":"Ense\u00d1anza: Idiomas",
    "sg:phone":"+34 972 21 71 95",
    "sg:postcode":"17002",
    "sg:province":"Girona",
    "wof:name":"Carme Huguet School S.l.",
    "wof:placetype":"venue"
},
  "geometry": {"coordinates":[2.8178889751,41.9812850952],"type":"Point"}
}