{
  "type": "Feature",
  "properties": {
    "iso:country":"ES",
    "sg:address":"Pl Progres, 31",
    "sg:city":"Palma",
    "sg:orig_category":"Fabricaci\u00d3n De Cortinas Y Visillos",
    "sg:phone":"+34 971 28 46 14",
    "sg:postcode":"07013",
    "sg:province":"Islas Baleares",
    "wof:name":"Galindo Gonzalez Jacinta",
    "wof:placetype":"venue"
},
  "geometry": {"coordinates":[2.6365680695,39.5723075867],"type":"Point"}
}