{
  "type": "Feature",
  "properties": {
    "addr:full":"Ctra Caspe, 12 Alca\u00f1iz Teruel 44600",
    "addr:housenumber":"12",
    "addr:postcode":"44600",
    "addr:street":"Ctra Caspe",
    "iso:country":"ES",
    "sg:address":"Ctra Caspe, 12",
    "sg:city":"Alca\u00f1iz",
    "sg:orig_category":"Fabricaci\u00d3n De Su\u00c9ters Y Chalecos De Punto",
    "sg:phone":"+34 978 87 01 90",
    "sg:postcode":"44600",
    "sg:province":"Teruel",
    "wof:name":"Aparicio Castell Francisco",
    "wof:placetype":"venue"
},
  "geometry": {"coordinates":[-0.1260461062,41.0464057922],"type":"Point"}
}