{
  "type": "Feature",
  "properties": {
    "addr:full":"Calle de San Rogelio, 9 Madrid Madrid 28039",
    "addr:housenumber":"9",
    "addr:postcode":"madrid;28039",
    "addr:street":"Calle De San Rogelio",
    "iso:country":"ES",
    "sg:address":"Calle de San Rogelio, 9",
    "sg:city":"Madrid",
    "sg:orig_category":"Arquitectos",
    "sg:phone":"+34 914 50 32 27",
    "sg:postcode":"28039",
    "sg:province":"Madrid",
    "wof:name":"Agrupacion Garantia Arquitectonica S.l",
    "wof:placetype":"venue"
},
  "geometry": {"coordinates":[-3.7100272179,40.4516105652],"type":"Point"}
}