{
  "type": "Feature",
  "properties": {
    "addr:full":"Calle de Carrera, 44 Aguilar De La Frontera C\u00f3rdoba 14920",
    "addr:housenumber":"44",
    "addr:postcode":"14920",
    "addr:street":"Calle De Carrera",
    "iso:country":"ES",
    "sg:address":"Calle de Carrera, 44",
    "sg:city":"Aguilar De La Frontera",
    "sg:orig_category":"Muebles, Minoristas",
    "sg:phone":"+34 957 68 94 25",
    "sg:postcode":"14920",
    "sg:province":"C\u00f3rdoba",
    "sg:website":"www.mi-mueble.es",
    "wof:name":"Carnedero S.l.",
    "wof:placetype":"venue"
},
  "geometry": {"coordinates":[-4.655395031,37.516544342],"type":"Point"}
}