{
  "type": "Feature",
  "properties": {
    "iso:country":"ES",
    "sg:address":"Carrer de Huelva, 111",
    "sg:city":"Barcelona",
    "sg:orig_category":"Empresas De Carpinter\u00cda De Madera",
    "sg:phone":"+34 933 13 88 37",
    "sg:postcode":"08020",
    "sg:province":"Barcelona",
    "wof:name":"Gomez Fernandez Francisco",
    "wof:placetype":"venue"
},
  "geometry": {"coordinates":[2.1998400688,41.4203224182],"type":"Point"}
}