{
  "type": "Feature",
  "properties": {
    "addr:full":"Calle de Reconquista, 3 Zaragoza Zaragoza 50001",
    "addr:housenumber":"3",
    "addr:postcode":"50001",
    "addr:street":"Calle De Reconquista",
    "iso:country":"ES",
    "sg:address":"Calle de Reconquista, 3",
    "sg:city":"Zaragoza",
    "sg:orig_category":"Inform\u00c1tica (estudios, Servicios, Asesor\u00cda, Formaci\u00d3n)",
    "sg:phone":"+34 976 20 30 29",
    "sg:postcode":"50001",
    "sg:province":"Zaragoza",
    "sg:website":"www.liebraun.com",
    "wof:name":"Liebraun Sll",
    "wof:placetype":"venue"
},
  "geometry": {"coordinates":[-0.8758350015,41.6497764587],"type":"Point"}
}