{
  "type": "Feature",
  "properties": {
    "addr:full":"Calle de Santutxu, 15 Bilbao Vizcaya 48004",
    "addr:housenumber":"15",
    "addr:postcode":"48004",
    "addr:street":"Calle De Santutxu",
    "iso:country":"ES",
    "sg:address":"Calle de Santutxu, 15",
    "sg:city":"Bilbao",
    "sg:orig_category":"Molduras, Junquillos, Listones Y Molduras Perforadas",
    "sg:phone":"+34 944 33 11 14",
    "sg:postcode":"48004",
    "sg:province":"Vizcaya",
    "wof:name":"Jose Carlos Losa San Miguel",
    "wof:placetype":"venue"
},
  "geometry": {"coordinates":[-2.9155080318,43.2532234192],"type":"Point"}
}