{
  "type": "Feature",
  "properties": {
    "iso:country":"ES",
    "sg:address":"Avda Antibioticos, Km. 0002,5",
    "sg:city":"Armunia",
    "sg:orig_category":"Aluminio Y Aleaciones (producci\u00d3n, Transformaci\u00d3n, Negocio)",
    "sg:phone":"+34 987 21 47 12",
    "sg:postcode":"24009",
    "sg:province":"Le\u00f3n",
    "wof:name":"Alugal S.l.",
    "wof:placetype":"venue"
},
  "geometry": {"coordinates":[-5.5826301575,42.5696296692],"type":"Point"}
}