{
  "type": "Feature",
  "properties": {
    "iso:country":"ES",
    "sg:address":"Avda Guadalajara (de), 19",
    "sg:city":"Azuqueca Henares",
    "sg:orig_category":"Inmobiliaria (agencias)",
    "sg:phone":"+34 949 27 73 50",
    "sg:postcode":"19200",
    "sg:province":"Guadalajara",
    "sg:website":"www.luckandfind.es",
    "wof:name":"Lama Alcala Gestion 2000 S.l.",
    "wof:placetype":"venue"
},
  "geometry": {"coordinates":[-3.2652280331,40.5640792847],"type":"Point"}
}