{
  "type": "Feature",
  "properties": {
    "addr:full":"Calle de Hernan Cortes, 5 Santander Cantabria 39003",
    "addr:housenumber":"5",
    "addr:postcode":"39003",
    "addr:street":"Calle De Hernan Cortes",
    "iso:country":"ES",
    "sg:address":"Calle de Hernan Cortes, 5",
    "sg:city":"Santander",
    "sg:orig_category":"Asesor\u00cda Sobre Comunicaci\u00d3n De Empresas",
    "sg:phone":"+34 942 21 40 88",
    "sg:postcode":"39003",
    "sg:province":"Cantabria",
    "wof:name":"Los Ozzos 060902 S.l",
    "wof:placetype":"venue"
},
  "geometry": {"coordinates":[-3.80469203,43.4625511169],"type":"Point"}
}