{
  "type": "Feature",
  "properties": {
    "iso:country":"ES",
    "sg:address":"Latsunbeberri Auzoa, 5",
    "sg:city":"Hernani",
    "sg:orig_category":"Peluquer\u00cdas, Peluquer\u00cda Mixta",
    "sg:phone":"+34 943 33 35 87",
    "sg:postcode":"20120",
    "sg:province":"Guip\u00f9zcoa",
    "wof:name":"Altuna Narro Nora",
    "wof:placetype":"venue"
},
  "geometry": {"coordinates":[-1.977314949,43.2688140869],"type":"Point"}
}