{
  "type": "Feature",
  "properties": {
    "iso:country":"ES",
    "sg:address":"Rua Aguadi\u00d1a, 3",
    "sg:city":"Vigo",
    "sg:orig_category":"Chapister\u00cda",
    "sg:phone":"+34 986 25 32 66",
    "sg:postcode":"36215",
    "sg:province":"Pontevedra",
    "wof:name":"Talleres Aguadi\u00f1a S.l.",
    "wof:placetype":"venue"
},
  "geometry": {"coordinates":[-8.6883201599,42.2330436707],"type":"Point"}
}