{
  "type": "Feature",
  "properties": {
    "addr:full":"Avda Alfares (de Los), 42 Cuenca Cuenca 16002",
    "addr:housenumber":"42",
    "addr:postcode":"16002",
    "addr:street":"Avda Alfares De Los",
    "iso:country":"ES",
    "sg:address":"Avda Alfares (de Los), 42",
    "sg:city":"Cuenca",
    "sg:orig_category":"Cajas De Ahorro",
    "sg:phone":"+34 969 21 47 07",
    "sg:postcode":"16002",
    "sg:province":"Cuenca",
    "wof:name":"Caja De Ahorros De Castilla La Mancha",
    "wof:placetype":"venue"
},
  "geometry": {"coordinates":[-2.143130064,40.0772018433],"type":"Point"}
}