{
  "type": "Feature",
  "properties": {
    "addr:full":"Calle de Tablarredonda, 6 Toro Zamora 49800",
    "addr:housenumber":"6",
    "addr:postcode":"49800",
    "addr:street":"Calle De Tablarredonda",
    "iso:country":"ES",
    "sg:address":"Calle de Tablarredonda, 6",
    "sg:city":"Toro",
    "sg:orig_category":"Farmacias",
    "sg:phone":"+34 980 69 06 14",
    "sg:postcode":"49800",
    "sg:province":"Zamora",
    "wof:name":"Farmacia Fortuoso C.b",
    "wof:placetype":"venue"
},
  "geometry": {"coordinates":[-5.3972492218,41.523601532],"type":"Point"}
}