{
  "type": "Feature",
  "properties": {
    "iso:country":"ES",
    "sg:address":"Cami Murterar, Des, 13",
    "sg:city":"Soller",
    "sg:orig_category":"Molduras, Junquillos, Listones Y Molduras Perforadas",
    "sg:phone":"+34 971 63 48 38",
    "sg:postcode":"07100",
    "sg:province":"Islas Baleares",
    "wof:name":"Valcaneras Coll Jose",
    "wof:placetype":"venue"
},
  "geometry": {"coordinates":[2.7230648994,39.7712059021],"type":"Point"}
}