{
  "type": "Feature",
  "properties": {
    "iso:country":"ES",
    "sg:address":"Carrer de Sant Josep, 23",
    "sg:city":"Mataro",
    "sg:orig_category":"Centros Empresariales",
    "sg:phone":"+34 937 41 03 20",
    "sg:postcode":"08302",
    "sg:province":"Barcelona",
    "sg:website":"www.aboca.es",
    "wof:name":"Aboca Espa\u00f1a S.a.",
    "wof:placetype":"venue"
},
  "geometry": {"coordinates":[2.442805,41.539268],"type":"Point"}
}