{
  "type": "Feature",
  "properties": {
    "addr:full":"Calle de San Francisco, 63 Bilbao Vizcaya 48003",
    "addr:housenumber":"63",
    "addr:postcode":"48003",
    "addr:street":"Calle De San Francisco",
    "iso:country":"ES",
    "sg:address":"Calle de San Francisco, 63",
    "sg:city":"Bilbao",
    "sg:orig_category":"Librer\u00cdas",
    "sg:phone":"+34 944 16 08 09",
    "sg:postcode":"48003",
    "sg:province":"Vizcaya",
    "wof:name":"Alti Escorza Carlos Javier",
    "wof:placetype":"venue"
},
  "geometry": {"coordinates":[-2.9303300381,43.2565689087],"type":"Point"}
}