{
  "type": "Feature",
  "properties": {
    "addr:full":"C/ Joan Alcover, 15 Inca Islas Baleares 07300",
    "addr:housenumber":"15",
    "addr:postcode":"07300",
    "addr:street":"C / Joan Alcover",
    "iso:country":"ES",
    "sg:address":"C/ Joan Alcover, 15",
    "sg:city":"Inca",
    "sg:orig_category":"Promotores Constructores",
    "sg:phone":"+34 971 88 08 27",
    "sg:postcode":"07300",
    "sg:province":"Islas Baleares",
    "wof:name":"R & Esteves Internacional S.l.",
    "wof:placetype":"venue"
},
  "geometry": {"coordinates":[2.9053299427,39.7169303894],"type":"Point"}
}