{
  "type": "Feature",
  "properties": {
    "addr:full":"Erat De Baix, S/n Corbins Lleida 25137",
    "addr:housenumber":"s / n",
    "addr:postcode":"25137",
    "iso:country":"ES",
    "sg:address":"Erat De Baix, S/n",
    "sg:city":"Corbins",
    "sg:orig_category":"Insecticidas, Fumigaci\u00d3n",
    "sg:phone":"+34 973 19 04 64",
    "sg:postcode":"25137",
    "sg:province":"Lleida",
    "wof:name":"Central Agricola Bovi S. L.",
    "wof:placetype":"venue"
},
  "geometry": {"coordinates":[0.6906549931,41.6874809265],"type":"Point"}
}