{
  "type": "Feature",
  "properties": {
    "addr:full":"Calle de Emilia Pardo Bazan, 20 Coru\u00d1a A Coru\u00f1a 15005",
    "addr:housenumber":"20",
    "addr:postcode":"15005",
    "addr:street":"Calle De Emilia Pardo Bazan;Corun\u0303A",
    "iso:country":"ES",
    "sg:address":"Calle de Emilia Pardo Bazan, 20",
    "sg:city":"Coru\u00d1a",
    "sg:orig_category":"M\u00c9dicos: Cirug\u00cda Vascular",
    "sg:phone":"+34 981 12 08 37",
    "sg:postcode":"15005",
    "sg:province":"A Coru\u00f1a",
    "wof:name":"Tovar Martin Elias",
    "wof:placetype":"venue"
},
  "geometry": {"coordinates":[-8.4072599411,43.3627510071],"type":"Point"}
}