{
  "type": "Feature",
  "properties": {
    "addr:full":"Carrer de Arago, 190 Barcelona Barcelona 08011",
    "addr:housenumber":"190",
    "addr:postcode":"08011",
    "addr:street":"Carrer De Arago",
    "iso:country":"ES",
    "sg:address":"Carrer de Arago, 190",
    "sg:city":"Barcelona",
    "sg:orig_category":"Abogados",
    "sg:phone":"+34 934 51 59 60",
    "sg:postcode":"08011",
    "sg:province":"Barcelona",
    "wof:name":"Rabaneda Gimenez Braulio",
    "wof:placetype":"venue"
},
  "geometry": {"coordinates":[2.1583440304,41.3870697021],"type":"Point"}
}