{
  "type": "Feature",
  "properties": {
    "addr:full":"Pase Carmelitas, 30 Salamanca Salamanca 37007",
    "addr:housenumber":"30",
    "addr:postcode":"37007",
    "addr:street":"Carmelitas",
    "iso:country":"ES",
    "sg:address":"Pase Carmelitas, 30",
    "sg:city":"Salamanca",
    "sg:orig_category":"Transportes Por Carretera: Lotes Completos, Mercanc\u00cdas Diversas",
    "sg:phone":"+34 923 22 55 48",
    "sg:postcode":"37007",
    "sg:province":"Salamanca",
    "wof:name":"Caballero Del Amo Vicente",
    "wof:placetype":"venue"
},
  "geometry": {"coordinates":[-5.6657118797,40.9695167542],"type":"Point"}
}