{
  "type": "Feature",
  "properties": {
    "addr:full":"Avda Parayas, 76 Malia\u00d1o Cantabria 39600",
    "addr:housenumber":"76",
    "addr:postcode":"39600",
    "addr:street":"Avda Parayas",
    "iso:country":"ES",
    "sg:address":"Avda Parayas, 76",
    "sg:city":"Malia\u00d1o",
    "sg:orig_category":"Iglesia Cat\u00d3lica",
    "sg:phone":"+34 942 25 14 96",
    "sg:postcode":"39600",
    "sg:province":"Cantabria",
    "wof:name":"Parroquia De San Juan Bautista",
    "wof:placetype":"venue"
},
  "geometry": {"coordinates":[-3.8304190636,43.4175720215],"type":"Point"}
}