{
  "type": "Feature",
  "properties": {
    "iso:country":"ES",
    "sg:address":"Calle de Jorge Juan, 7",
    "sg:city":"Pobla Vallbona",
    "sg:orig_category":"Promotores Constructores",
    "sg:phone":"+34 962 76 17 74",
    "sg:postcode":"46185",
    "sg:province":"Valencia",
    "wof:name":"Construcciones Y Servicios Reformas Celgon Sl",
    "wof:placetype":"venue"
},
  "geometry": {"coordinates":[-0.5500869751,39.594833374],"type":"Point"}
}