{
  "type": "Feature",
  "properties": {
    "addr:full":"Avda Padre Piquer, 38 Madrid Madrid 28024",
    "addr:housenumber":"38",
    "addr:postcode":"madrid;28024",
    "addr:street":"Avda Padre Piquer",
    "iso:country":"ES",
    "sg:address":"Avda Padre Piquer, 38",
    "sg:city":"Madrid",
    "sg:orig_category":"Muebles Y Accesorios Para Cocinas Y Cuartos De Ba\u00d1o (al Por Menor)",
    "sg:phone":"+34 915 18 70 10",
    "sg:postcode":"28024",
    "sg:province":"Madrid",
    "wof:name":"Vizma-3 S.l.",
    "wof:placetype":"venue"
},
  "geometry": {"coordinates":[-3.767524004,40.3921699524],"type":"Point"}
}