{
  "type": "Feature",
  "properties": {
    "addr:full":"Dr Fleming, 16 Banyeres Mariola Alicante 03450",
    "addr:housenumber":"16",
    "addr:postcode":"03450",
    "addr:street":"Dr Fleming",
    "iso:country":"ES",
    "sg:address":"Dr Fleming, 16",
    "sg:city":"Banyeres Mariola",
    "sg:orig_category":"Fabricaci\u00d3n De Telas Y Sedas",
    "sg:phone":"+34 965 56 70 55",
    "sg:postcode":"03450",
    "sg:province":"Alicante",
    "sg:website":"www.textil.org/lmolina",
    "wof:name":"Luis Molina Ferre S.l.",
    "wof:placetype":"venue"
},
  "geometry": {"coordinates":[-0.6553789973,38.7207794189],"type":"Point"}
}