{
  "type": "Feature",
  "properties": {
    "iso:country":"ES",
    "sg:address":"Calle de Afueras-escalona, S/n",
    "sg:city":"Escalona",
    "sg:orig_category":"Mataderos Y Talleres De Despiezado",
    "sg:phone":"+34 974 50 52 09",
    "sg:postcode":"22363",
    "sg:province":"Huesca",
    "wof:name":"Modesto Bielsa S.cv.",
    "wof:placetype":"venue"
},
  "geometry": {"coordinates":[0.1420418024,42.4980316162],"type":"Point"}
}