{
  "type": "Feature",
  "properties": {
    "addr:full":"Carrer de Consell De Cent, 181 Barcelona Barcelona 08015",
    "addr:housenumber":"181",
    "addr:postcode":"08015",
    "addr:street":"Carrer De Consell De Cent",
    "iso:country":"ES",
    "sg:address":"Carrer de Consell De Cent, 181",
    "sg:city":"Barcelona",
    "sg:orig_category":"Lavado, Limpieza De Veh\u00cdculos",
    "sg:phone":"+34 934 54 32 44",
    "sg:postcode":"08015",
    "sg:province":"Barcelona",
    "wof:name":"Xather S.l.",
    "wof:placetype":"venue"
},
  "geometry": {"coordinates":[2.1555440426,41.383644104],"type":"Point"}
}