{
  "type": "Feature",
  "properties": {
    "iso:country":"ES",
    "sg:address":"Plaz Angel, 11",
    "sg:city":"Madrid",
    "sg:orig_category":"Empresas De Limpieza",
    "sg:phone":"+34 913 69 18 09",
    "sg:postcode":"28012",
    "sg:province":"Madrid",
    "wof:name":"Perez Donoso Jaime",
    "wof:placetype":"venue"
},
  "geometry": {"coordinates":[-3.7019228935,40.4141082764],"type":"Point"}
}