{
  "type": "Feature",
  "properties": {
    "addr:full":"Calle de Pages Del Corro, 86 Sevilla Sevilla 41010",
    "addr:housenumber":"86",
    "addr:postcode":"41010",
    "addr:street":"Calle De Pages Del Corro",
    "iso:country":"ES",
    "sg:address":"Calle de Pages Del Corro, 86",
    "sg:city":"Sevilla",
    "sg:orig_category":"Molduras, Junquillos, Listones Y Molduras Perforadas",
    "sg:phone":"+34 954 33 37 88",
    "sg:postcode":"41010",
    "sg:province":"Sevilla",
    "wof:name":"Bejarano Bohorquez Manuel",
    "wof:placetype":"venue"
},
  "geometry": {"coordinates":[-6.0052528381,37.3837051392],"type":"Point"}
}