{
  "type": "Feature",
  "properties": {
    "addr:full":"Calle de Medea, 13 Merida Badajoz 06800",
    "addr:housenumber":"13",
    "addr:postcode":"06800",
    "addr:street":"Calle De Medea",
    "iso:country":"ES",
    "sg:address":"Calle de Medea, 13",
    "sg:city":"Merida",
    "sg:orig_category":"Peluqueros: De Se\u00d1oras",
    "sg:phone":"+34 924 30 17 67",
    "sg:postcode":"06800",
    "sg:province":"Badajoz",
    "wof:name":"Sierra Garcia Maria Francisca",
    "wof:placetype":"venue"
},
  "geometry": {"coordinates":[-6.3505601883,38.9251403809],"type":"Point"}
}