{
  "type": "Feature",
  "properties": {
    "addr:full":"Carrer de Verge Del Pilar, 8 Crevillent Alicante 03330",
    "addr:housenumber":"8",
    "addr:postcode":"03330",
    "addr:street":"Carrer De Verge Del Pilar",
    "iso:country":"ES",
    "sg:address":"Carrer de Verge Del Pilar, 8",
    "sg:city":"Crevillent",
    "sg:orig_category":"\u00d3ptica: Instrumentos (fabricaci\u00d3n)",
    "sg:phone":"+34 965 40 34 56",
    "sg:postcode":"03330",
    "sg:province":"Alicante",
    "wof:name":"Sanchez Mas Jose Antonio",
    "wof:placetype":"venue"
},
  "geometry": {"coordinates":[-0.8090270162,38.2457275391],"type":"Point"}
}