{
  "type": "Feature",
  "properties": {
    "addr:full":"Calle de Diaz Brito, 5 Badajoz Badajoz 06005",
    "addr:housenumber":"5",
    "addr:postcode":"06005",
    "addr:street":"Calle De Diaz Brito",
    "iso:country":"ES",
    "sg:address":"Calle de Diaz Brito, 5",
    "sg:city":"Badajoz",
    "sg:orig_category":"Iglesia Cat\u00d3lica",
    "sg:phone":"+34 924 23 13 40",
    "sg:postcode":"06005",
    "sg:province":"Badajoz",
    "wof:name":"Parroquia De San Jose",
    "wof:placetype":"venue"
},
  "geometry": {"coordinates":[-6.9788784981,38.8727149963],"type":"Point"}
}