{
  "type": "Feature",
  "properties": {
    "addr:full":"Calle de Pozo (el), 4 Candelaria Santa Cruz De Tenerife 38530",
    "addr:housenumber":"4",
    "addr:postcode":"38530",
    "addr:street":"Calle De Pozo El",
    "iso:country":"ES",
    "sg:address":"Calle de Pozo (el), 4",
    "sg:city":"Candelaria",
    "sg:orig_category":"Supermercados Y Hipermercados",
    "sg:phone":"+34 922 95 61 78",
    "sg:postcode":"38530",
    "sg:province":"Santa Cruz De Tenerife",
    "wof:name":"Chinea Gaspar Jaime",
    "wof:placetype":"venue"
},
  "geometry": {"coordinates":[-16.371257782,28.3556747437],"type":"Point"}
}