{
  "type": "Feature",
  "properties": {
    "iso:country":"ES",
    "sg:address":"Calle de San Bernardo, 109",
    "sg:city":"Madrid",
    "sg:orig_category":"Peluquer\u00cdas, Peluquer\u00cda Mixta",
    "sg:phone":"+34 914 45 45 19",
    "sg:postcode":"28015",
    "sg:province":"Madrid",
    "wof:name":"Castro Reino Francisco Javier",
    "wof:placetype":"venue"
},
  "geometry": {"coordinates":[-3.711648941,40.4257011414],"type":"Point"}
}