{
  "type": "Feature",
  "properties": {
    "iso:country":"ES",
    "sg:address":"Calle de Aurelio Gonzalez De Gregorio, 32",
    "sg:city":"Madrid",
    "sg:orig_category":"Renovaci\u00d3n Inmobiliaria",
    "sg:phone":"+34 913 58 44 02",
    "sg:postcode":"28034",
    "sg:province":"Madrid",
    "wof:name":"Constancio Agui S.l.",
    "wof:placetype":"venue"
},
  "geometry": {"coordinates":[-3.6870179176,40.4950904846],"type":"Point"}
}