{
  "type": "Feature",
  "properties": {
    "addr:full":"Calle de Benito Montalt Martinez, 24 Alaquas Valencia 46970",
    "addr:housenumber":"24",
    "addr:postcode":"46970",
    "addr:street":"Calle De Benito Montalt Martinez",
    "iso:country":"ES",
    "sg:address":"Calle de Benito Montalt Martinez, 24",
    "sg:city":"Alaquas",
    "sg:orig_category":"Carnes De Carnicer\u00cda (al Por Mayor)",
    "sg:phone":"+34 961 51 32 65",
    "sg:postcode":"46970",
    "sg:province":"Valencia",
    "wof:name":"Inarejos Perez Bernardo",
    "wof:placetype":"venue"
},
  "geometry": {"coordinates":[-0.4503535032,39.4578170776],"type":"Point"}
}