{
  "type": "Feature",
  "properties": {
    "addr:full":"Calle de Francisco Silvela, 50 Madrid Madrid 28028",
    "addr:housenumber":"50",
    "addr:postcode":"madrid;28028",
    "addr:street":"Calle De Francisco Silvela",
    "iso:country":"ES",
    "sg:address":"Calle de Francisco Silvela, 50",
    "sg:city":"Madrid",
    "sg:orig_category":"Tiendas De Grano, Frutas Y Legumbres Secas (al Por Menor)",
    "sg:phone":"+34 917 25 08 22",
    "sg:postcode":"28028",
    "sg:province":"Madrid",
    "wof:name":"Frutos Secos Macadamia S.l.",
    "wof:placetype":"venue"
},
  "geometry": {"coordinates":[-3.6741292477,40.4343452454],"type":"Point"}
}