{
  "type": "Feature",
  "properties": {
    "addr:full":"Calle de Corredera, 39 Yecla Murcia 30510",
    "addr:housenumber":"39",
    "addr:postcode":"30510",
    "addr:street":"Calle De Corredera",
    "iso:country":"ES",
    "sg:address":"Calle de Corredera, 39",
    "sg:city":"Yecla",
    "sg:orig_category":"Peluqueros: De Se\u00d1oras",
    "sg:phone":"+34 968 75 03 59",
    "sg:postcode":"30510",
    "sg:province":"Murcia",
    "wof:name":"Rodriguez Camarasa Maria Del Carmen",
    "wof:placetype":"venue"
},
  "geometry": {"coordinates":[-1.1142096519,38.6116142273],"type":"Point"}
}