{
  "type": "Feature",
  "properties": {
    "iso:country":"ES",
    "sg:address":"Avda Diputacion, S/n",
    "sg:city":"Lepe",
    "sg:orig_category":"Agencias De Viajes",
    "sg:phone":"+34 959 64 52 10",
    "sg:postcode":"21440",
    "sg:province":"Huelva",
    "sg:website":"www.viajeselcorteingles.es",
    "wof:name":"Viajes El Corte Ingles S.a.",
    "wof:placetype":"venue"
},
  "geometry": {"coordinates":[-7.2023539543,37.2499809265],"type":"Point"}
}