{
  "type": "Feature",
  "properties": {
    "addr:full":"Rua Garcia Prieto (de), 53 Santiago De Compostela La Coru\u00f1a 15706",
    "addr:housenumber":"53",
    "addr:postcode":"15706",
    "addr:street":"Rua Garcia Prieto De;Corun\u0303A",
    "iso:country":"ES",
    "sg:address":"Rua Garcia Prieto (de), 53",
    "sg:city":"Santiago De Compostela",
    "sg:orig_category":"Centros P\u00dablicos De Formaci\u00d3n Profesional Y T\u00c9cnica",
    "sg:phone":"+34 981 53 02 16",
    "sg:postcode":"15706",
    "sg:province":"La Coru\u00f1a",
    "wof:name":"Colegio Oficial De Ingenieros Tecnicos Industriales",
    "wof:placetype":"venue"
},
  "geometry": {"coordinates":[-8.5536394119,42.8676681519],"type":"Point"}
}