{
  "type": "Feature",
  "properties": {
    "addr:full":"Avda Mancha (de La), S/n Albaladejo Ciudad Real 13340",
    "addr:postcode":"13340",
    "addr:street":"Avda Mancha De La S / N Albaladejo",
    "iso:country":"ES",
    "sg:address":"Avda Mancha (de La), S/n",
    "sg:city":"Albaladejo",
    "sg:orig_category":"Empresas De Carpinter\u00cda De Madera",
    "sg:phone":"+34 926 38 73 09",
    "sg:postcode":"13340",
    "sg:province":"Ciudad Real",
    "wof:name":"Carpinteria Juvisa S.l",
    "wof:placetype":"venue"
},
  "geometry": {"coordinates":[-2.8101840019,38.6158065796],"type":"Point"}
}