{
  "type": "Feature",
  "properties": {
    "iso:country":"ES",
    "sg:address":"Cuesta Magdalena, S/n",
    "sg:city":"Murcia",
    "sg:orig_category":"Lencer\u00cda Femenina, Corseter\u00cda, Trajes De Ba\u00d1o (al Por Menor)",
    "sg:phone":"+34 968 21 24 08",
    "sg:postcode":"30005",
    "sg:province":"Murcia",
    "wof:name":"Navarro Caballero Maria Angeles",
    "wof:placetype":"venue"
},
  "geometry": {"coordinates":[-1.13420403,37.9865837097],"type":"Point"}
}