{
  "type": "Feature",
  "properties": {
    "addr:full":"Carr Pere Frances, 32 Eivissa Islas Baleares 07800",
    "addr:housenumber":"32",
    "addr:postcode":"07800",
    "addr:street":"Carr Pere Frances",
    "iso:country":"ES",
    "sg:address":"Carr Pere Frances, 32",
    "sg:city":"Eivissa",
    "sg:orig_category":"Molduras, Junquillos, Listones Y Molduras Perforadas",
    "sg:phone":"+34 971 19 30 72",
    "sg:postcode":"07800",
    "sg:province":"Islas Baleares",
    "wof:name":"Esparcia Costa Eva",
    "wof:placetype":"venue"
},
  "geometry": {"coordinates":[1.4309849739,38.9134063721],"type":"Point"}
}