{
  "type": "Feature",
  "properties": {
    "iso:country":"ES",
    "sg:address":"Angeles Sorazu, 1",
    "sg:city":"Zumaia",
    "sg:orig_category":"Panader\u00cdas, Panader\u00cdas",
    "sg:phone":"+34 943 86 20 40",
    "sg:postcode":"20750",
    "sg:province":"Guip\u00f9zcoa",
    "wof:name":"Karmelo Txapartegi Barinaga",
    "wof:placetype":"venue"
},
  "geometry": {"coordinates":[-2.2566249371,43.2966499329],"type":"Point"}
}