{
  "type": "Feature",
  "properties": {
    "addr:full":"Carr Pu\u00c7ol, 13 Puig Valencia 46540",
    "addr:housenumber":"13",
    "addr:postcode":"46540",
    "addr:street":"Carr Puc\u0327Ol",
    "iso:country":"ES",
    "sg:address":"Carr Pu\u00c7ol, 13",
    "sg:city":"Puig",
    "sg:orig_category":"Promotores Constructores",
    "sg:phone":"+34 961 47 13 68",
    "sg:postcode":"46540",
    "sg:province":"Valencia",
    "wof:name":"Protec Estudios Y Proyectos De Ingenieria S.l.",
    "wof:placetype":"venue"
},
  "geometry": {"coordinates":[-0.3027929962,39.5905723572],"type":"Point"}
}