{
  "type": "Feature",
  "properties": {
    "iso:country":"ES",
    "sg:address":"Calle de Virgen De La Paz, 52",
    "sg:city":"Torrent",
    "sg:orig_category":"Electricidad: Instaladores",
    "sg:phone":"+34 961 58 03 40",
    "sg:postcode":"46900",
    "sg:province":"Valencia",
    "wof:name":"Instel-95 S.l.",
    "wof:placetype":"venue"
},
  "geometry": {"coordinates":[-0.4736140072,39.4359741211],"type":"Point"}
}