{
  "type": "Feature",
  "properties": {
    "addr:full":"Ctra Nal 340, Km. 1100,0 L'ampolla Tarragona 43895",
    "addr:postcode":"43895",
    "addr:street":"Ctra Nal 340 Km. 1100,0",
    "iso:country":"ES",
    "sg:address":"Ctra Nal 340, Km. 1100,0",
    "sg:city":"L'ampolla",
    "sg:orig_category":"Distribuci\u00d3n De Petr\u00d3leo Y Derivados",
    "sg:phone":"+34 977 59 32 67",
    "sg:postcode":"43895",
    "sg:province":"Tarragona",
    "wof:name":"Agip Espa\u00f1a S.a.",
    "wof:placetype":"venue"
},
  "geometry": {"coordinates":[0.6867939234,40.8050041199],"type":"Point"}
}