{
  "type": "Feature",
  "properties": {
    "addr:full":"Calle de Mar Adriatico (del), 2 Poligono De San Fernando De Henares Madrid 28830",
    "addr:housenumber":"2",
    "addr:postcode":"28830",
    "addr:street":"Calle De Mar Adriatico Del",
    "iso:country":"ES",
    "sg:address":"Calle de Mar Adriatico (del), 2",
    "sg:city":"Poligono De San Fernando De Henares",
    "sg:orig_category":"Centros Empresariales",
    "sg:phone":"+34 916 55 51 87",
    "sg:postcode":"28830",
    "sg:province":"Madrid",
    "wof:name":"Artel Ingenieros S.l.",
    "wof:placetype":"venue"
},
  "geometry": {"coordinates":[-3.5366938114,40.4255332947],"type":"Point"}
}