{
  "type": "Feature",
  "properties": {
    "addr:full":"Av Carrerada, 6 Moja Barcelona 08734",
    "addr:housenumber":"6",
    "addr:postcode":"08734",
    "addr:street":"Av Carrerada",
    "iso:country":"ES",
    "sg:address":"Av Carrerada, 6",
    "sg:city":"Moja",
    "sg:orig_category":"Cajas De Ahorro",
    "sg:phone":"+34 938 90 40 19",
    "sg:postcode":"08734",
    "sg:province":"Barcelona",
    "wof:name":"Caixa D'estalvis Del Penedes",
    "wof:placetype":"venue"
},
  "geometry": {"coordinates":[1.6912339926,41.3253135681],"type":"Point"}
}