{
  "type": "Feature",
  "properties": {
    "addr:full":"Calle de Veintiocho De Septiembre, 14 Bejar Salamanca 37700",
    "addr:housenumber":"14",
    "addr:postcode":"37700",
    "addr:street":"Calle De Veintiocho De Septiembre",
    "iso:country":"ES",
    "sg:address":"Calle de Veintiocho De Septiembre, 14",
    "sg:city":"Bejar",
    "sg:orig_category":"Agencias De Viajes",
    "sg:phone":"+34 923 40 36 87",
    "sg:postcode":"37700",
    "sg:province":"Salamanca",
    "wof:name":"Viajes Iberpalma S. L.",
    "wof:placetype":"venue"
},
  "geometry": {"coordinates":[-5.7637019157,40.3869819641],"type":"Point"}
}