{
  "type": "Feature",
  "properties": {
    "addr:full":"Calle de Santiago De Compostela, 36 Madrid Madrid 28034",
    "addr:housenumber":"36",
    "addr:postcode":"madrid;28034",
    "addr:street":"Calle De Santiago De Compostela",
    "iso:country":"ES",
    "sg:address":"Calle de Santiago De Compostela, 36",
    "sg:city":"Madrid",
    "sg:orig_category":"Ense\u00d1anza Variada",
    "sg:phone":"+34 917 30 73 25",
    "sg:postcode":"28034",
    "sg:province":"Madrid",
    "wof:name":"Ramos Ruiz Elia",
    "wof:placetype":"venue"
},
  "geometry": {"coordinates":[-3.7111389637,40.4809913635],"type":"Point"}
}