{
  "type": "Feature",
  "properties": {
    "iso:country":"ES",
    "sg:address":"Calle de Isidro Segovia, 10",
    "sg:city":"Salamanca",
    "sg:orig_category":"Agencias Y Agentes Comerciales, Representantes",
    "sg:phone":"+34 923 22 79 43",
    "sg:postcode":"37007",
    "sg:province":"Salamanca",
    "wof:name":"Martin Velazquez Jose",
    "wof:placetype":"venue"
},
  "geometry": {"coordinates":[-5.6660170555,40.9707183838],"type":"Point"}
}