{
  "type": "Feature",
  "properties": {
    "iso:country":"ES",
    "sg:address":"Avda Salamanca, 20",
    "sg:city":"Plasencia",
    "sg:orig_category":"Inform\u00c1tica: Mantenimiento Y Reparaci\u00d3n De Ordenadores",
    "sg:phone":"+34 927 42 23 45",
    "sg:postcode":"10600",
    "sg:province":"C\u00e1ceres",
    "wof:name":"Metrolico S.a.",
    "wof:placetype":"venue"
},
  "geometry": {"coordinates":[-6.0903749466,40.0360298157],"type":"Point"}
}