{
  "type": "Feature",
  "properties": {
    "iso:country":"ES",
    "sg:address":"Ctra. Gijon, 136",
    "sg:city":"Llaranes",
    "sg:orig_category":"Agentes, Concesionarios Y Sucursales De Veh\u00cdculos",
    "sg:phone":"+34 985 51 59 95",
    "sg:postcode":"33461",
    "sg:province":"Asturias",
    "sg:website":"www.antonehijos.com",
    "wof:name":"Automoviles Anton E Hijos S.l.",
    "wof:placetype":"venue"
},
  "geometry": {"coordinates":[-5.8465900421,43.2702789307],"type":"Point"}
}