{
  "type": "Feature",
  "properties": {
    "iso:country":"ES",
    "sg:address":"Calle de Bolivar Simon, 3",
    "sg:city":"Bilbao",
    "sg:orig_category":"Centros De Coordinaci\u00d3n",
    "sg:phone":"+34 944 10 63 78",
    "sg:postcode":"48010",
    "sg:province":"Vizcaya",
    "wof:name":"Juan Maria Garaitagoitia Inunciaga Y Juan Luis Espina Requejo",
    "wof:placetype":"venue"
},
  "geometry": {"coordinates":[-2.9405939579,43.2597427368],"type":"Point"}
}