{
  "type": "Feature",
  "properties": {
    "addr:full":"Pg Sant Gervasi, 1 Barcelona Barcelona 08022",
    "addr:housenumber":"1",
    "addr:postcode":"08022",
    "addr:street":"Pg Sant Gervasi",
    "iso:country":"ES",
    "sg:address":"Pg Sant Gervasi, 1",
    "sg:city":"Barcelona",
    "sg:orig_category":"Servicios Gsm",
    "sg:phone":"+34 934 18 84 16",
    "sg:postcode":"08022",
    "sg:province":"Barcelona",
    "wof:name":"Phone Consulting 2000 S.l.",
    "wof:placetype":"venue"
},
  "geometry": {"coordinates":[2.1337358952,41.4070625305],"type":"Point"}
}