{
  "type": "Feature",
  "properties": {
    "addr:full":"Calle de Aristoteles, 8 Madrid Madrid 28027",
    "addr:housenumber":"8",
    "addr:postcode":"madrid;28027",
    "addr:street":"Calle De Aristoteles",
    "iso:country":"ES",
    "sg:address":"Calle de Aristoteles, 8",
    "sg:city":"Madrid",
    "sg:orig_category":"Hilaturas, Hilos Y Actividades Relacionadas",
    "sg:phone":"+34 914 05 48 02",
    "sg:postcode":"28027",
    "sg:province":"Madrid",
    "wof:name":"Serfaty Cohen Esther",
    "wof:placetype":"venue"
},
  "geometry": {"coordinates":[-3.651818037,40.4426116943],"type":"Point"}
}