{
  "type": "Feature",
  "properties": {
    "addr:full":"Pol Ind Las Pilas, 18 Algeciras C\u00e1diz 11204",
    "addr:housenumber":"18;ca\u0301diz",
    "addr:postcode":"11204",
    "addr:street":"Pilas",
    "iso:country":"ES",
    "sg:address":"Pol Ind Las Pilas, 18",
    "sg:city":"Algeciras",
    "sg:classifiers":[
        {
            "category":"Food & Beverages",
            "subcategory":"Candy",
            "type":"Retail Goods"
        }
    ],
    "sg:phone":"+34 956 63 20 94",
    "sg:postcode":"11204",
    "sg:province":"C\u00e1diz",
    "sg:tags":[
        "confiter\u00cdas",
        "y",
        "de",
        "fabricaci\u00d3n",
        "chocolate"
    ],
    "wof:name":"Golosinas Randi S.l.",
    "wof:placetype":"venue"
},
  "geometry": {"coordinates":[-5.4872508049,36.1493225098],"type":"Point"}
}