{
  "type": "Feature",
  "properties": {
    "iso:country":"ES",
    "sg:address":"Calle de Feria, 75",
    "sg:city":"Sevilla",
    "sg:orig_category":"Venta, Alquiler De Instrumentos Y Accesorios De M\u00dasica",
    "sg:phone":"+34 954 90 14 82",
    "sg:postcode":"41002",
    "sg:province":"Sevilla",
    "wof:name":"Casa Tejera S.l.",
    "wof:placetype":"venue"
},
  "geometry": {"coordinates":[-5.9916892052,37.3991012573],"type":"Point"}
}