{
  "type": "Feature",
  "properties": {
    "addr:full":"Carr Pare Gari, 7 Vilanova I La Geltru Barcelona 08800",
    "addr:housenumber":"7",
    "addr:postcode":"08800",
    "addr:street":"Carr Pare Gari",
    "iso:country":"ES",
    "sg:address":"Carr Pare Gari, 7",
    "sg:city":"Vilanova I La Geltru",
    "sg:orig_category":"Venta, Colocaci\u00d3n De Autoradios",
    "sg:phone":"+34 938 14 18 87",
    "sg:postcode":"08800",
    "sg:province":"Barcelona",
    "wof:name":"Gomez Paredes Marcelo",
    "wof:placetype":"venue"
},
  "geometry": {"coordinates":[1.7185050249,41.2261695862],"type":"Point"}
}