{
  "type": "Feature",
  "properties": {
    "addr:full":"Vio\u00f1o, 32 Renedo Cantabria 39470",
    "addr:housenumber":"32",
    "addr:postcode":"39470",
    "addr:street":"Vion\u0303O",
    "iso:country":"ES",
    "sg:address":"Vio\u00f1o, 32",
    "sg:city":"Renedo",
    "sg:orig_category":"Cristaler\u00cdas",
    "sg:phone":"+34 942 57 11 51",
    "sg:postcode":"39470",
    "sg:province":"Cantabria",
    "wof:name":"Del Castillo Alonso Francisco Ramon",
    "wof:placetype":"venue"
},
  "geometry": {"coordinates":[-3.9539539814,43.3548316956],"type":"Point"}
}