{
  "type": "Feature",
  "properties": {
    "iso:country":"ES",
    "sg:address":"Pase Menendez Pelayo, 50",
    "sg:city":"Santander",
    "sg:orig_category":"Asilos De Ancianos. Centros Privados",
    "sg:phone":"+34 942 27 28 50",
    "sg:postcode":"39006",
    "sg:province":"Cantabria",
    "wof:name":"Casa Reposo Sta Maria Soledad Siervas De Maria Ministras De Los Enfermos Provcia De Castilla",
    "wof:placetype":"venue"
},
  "geometry": {"coordinates":[-3.795306921,43.4665794373],"type":"Point"}
}