{
  "type": "Feature",
  "properties": {
    "addr:full":"Calle de Tenerias, 46 Villarrubia De Los Ojos Ciudad Real 13670",
    "addr:housenumber":"46",
    "addr:postcode":"13670",
    "addr:street":"Calle De Tenerias",
    "iso:country":"ES",
    "sg:address":"Calle de Tenerias, 46",
    "sg:city":"Villarrubia De Los Ojos",
    "sg:orig_category":"Reposter\u00cdas",
    "sg:phone":"+34 926 89 65 78",
    "sg:postcode":"13670",
    "sg:province":"Ciudad Real",
    "wof:name":"Redondo Urda Valentin",
    "wof:placetype":"venue"
},
  "geometry": {"coordinates":[-3.6133630276,39.2171440125],"type":"Point"}
}