{
  "type": "Feature",
  "properties": {
    "iso:country":"ES",
    "sg:address":"Ba\u00f1o, S/n",
    "sg:city":"Ba\u00d1o",
    "sg:orig_category":"Arquitectos",
    "sg:phone":"+34 986 55 95 22",
    "sg:postcode":"36645",
    "sg:province":"Pontevedra",
    "wof:name":"Pi\u00f1eiro Bermudez Luciano",
    "wof:placetype":"venue"
},
  "geometry": {"coordinates":[-8.6490335464,42.7007255554],"type":"Point"}
}