{
  "type": "Feature",
  "properties": {
    "addr:full":"Carrer de Lluis, 21 Sabadell Barcelona 08208",
    "addr:housenumber":"21",
    "addr:postcode":"08208",
    "addr:street":"Carrer De Lluis",
    "iso:country":"ES",
    "sg:address":"Carrer de Lluis, 21",
    "sg:city":"Sabadell",
    "sg:orig_category":"Fabricaci\u00d3n De Telas Y Sedas",
    "sg:phone":"+34 937 23 96 55",
    "sg:postcode":"08208",
    "sg:province":"Barcelona",
    "wof:name":"Texdam S.l.",
    "wof:placetype":"venue"
},
  "geometry": {"coordinates":[2.1013560295,41.5535125732],"type":"Point"}
}