{
  "type": "Feature",
  "properties": {
    "addr:full":"Calle de San Martin, S/n Santander Cantabria 39004",
    "addr:housenumber":"s / n",
    "addr:postcode":"39004",
    "addr:street":"Calle De San Martin",
    "iso:country":"ES",
    "sg:address":"Calle de San Martin, S/n",
    "sg:city":"Santander",
    "sg:orig_category":"Internados & Ense\u00d1anza Privada",
    "sg:phone":"+34 942 21 54 60",
    "sg:postcode":"39004",
    "sg:province":"Cantabria",
    "wof:name":"Franciscanos Capuchinos",
    "wof:placetype":"venue"
},
  "geometry": {"coordinates":[-3.7929859161,43.4636116028],"type":"Point"}
}