{
  "type": "Feature",
  "properties": {
    "addr:full":"Calle de Cami Reial, 122 Torrent Valencia 46900",
    "addr:housenumber":"122",
    "addr:postcode":"46900",
    "addr:street":"Calle De;Reial;Valencia",
    "iso:country":"ES",
    "sg:address":"Calle de Cami Reial, 122",
    "sg:city":"Torrent",
    "sg:orig_category":"Muebles Y Accesorios Para Cocinas Y Cuartos De Ba\u00d1o (al Por Menor)",
    "sg:phone":"+34 961 57 47 39",
    "sg:postcode":"46900",
    "sg:province":"Valencia",
    "wof:name":"Botifora Vilata Jose",
    "wof:placetype":"venue"
},
  "geometry": {"coordinates":[-0.4623290002,39.441619873],"type":"Point"}
}