{
  "type": "Feature",
  "properties": {
    "iso:country":"ES",
    "sg:address":"Calle de San Agustin, 68",
    "sg:city":"Icod De Los Vinos",
    "sg:orig_category":"Bazares, Art\u00cdculos De Limpieza Y De Cocina (al Por Menor)",
    "sg:phone":"+34 922 81 39 38",
    "sg:postcode":"38430",
    "sg:province":"Santa Cruz De Tenerife",
    "wof:name":"Palgoya S.l.",
    "wof:placetype":"venue"
},
  "geometry": {"coordinates":[-16.7159042358,28.3688106537],"type":"Point"}
}