{
  "type": "Feature",
  "properties": {
    "iso:country":"ES",
    "sg:address":"Calle de Artes Graficas, 33",
    "sg:city":"Alacant",
    "sg:orig_category":"Quincaller\u00cda (al Por Menor)",
    "sg:phone":"+34 965 28 18 76",
    "sg:postcode":"03008",
    "sg:province":"Alicante",
    "wof:name":"Herrajes Alicante S.l.",
    "wof:placetype":"venue"
},
  "geometry": {"coordinates":[-0.514099896,38.3357162476],"type":"Point"}
}