{
  "type": "Feature",
  "properties": {
    "iso:country":"ES",
    "sg:address":"Calle de Alhondiga, 11",
    "sg:city":"Barrios",
    "sg:orig_category":"Inmobiliaria (agencias)",
    "sg:phone":"+34 956 62 04 40",
    "sg:postcode":"11370",
    "sg:province":"C\u00e1diz",
    "wof:name":"Gestion Barre\u00f1a Inmobiliaria S.l.",
    "wof:placetype":"venue"
},
  "geometry": {"coordinates":[-5.4941568375,36.1836204529],"type":"Point"}
}