{
  "type": "Feature",
  "properties": {
    "iso:country":"ES",
    "sg:address":"Carrer de Valencia, 469",
    "sg:city":"Barcelona",
    "sg:orig_category":"Agentes Generales De Seguros",
    "sg:phone":"+34 932 31 83 46",
    "sg:postcode":"08013",
    "sg:province":"Barcelona",
    "wof:name":"Baeta Buil Conrado",
    "wof:placetype":"venue"
},
  "geometry": {"coordinates":[2.1780529022,41.4037895203],"type":"Point"}
}