{
  "type": "Feature",
  "properties": {
    "iso:country":"ES",
    "sg:address":"Calle de Cantin Y Gamboa, 22",
    "sg:city":"Zaragoza",
    "sg:orig_category":"Imprenta",
    "sg:phone":"+34 976 29 65 55",
    "sg:postcode":"50002",
    "sg:province":"Zaragoza",
    "wof:name":"Molinero Monta\u00f1es Victor",
    "wof:placetype":"venue"
},
  "geometry": {"coordinates":[-0.872166276,41.650642395],"type":"Point"}
}