{
  "type": "Feature",
  "properties": {
    "iso:country":"ES",
    "sg:address":"Carrer de Bizet, 9",
    "sg:city":"Rubi",
    "sg:orig_category":"Copas, Insignias, Trofeos",
    "sg:phone":"+34 936 99 86 12",
    "sg:postcode":"08191",
    "sg:province":"Barcelona",
    "wof:name":"Trabajos De Hierro Y Otros Metales S. A.",
    "wof:placetype":"venue"
},
  "geometry": {"coordinates":[2.0272419453,41.4740104675],"type":"Point"}
}