{
  "type": "Feature",
  "properties": {
    "iso:country":"ES",
    "sg:address":"Via Augusta, 61",
    "sg:city":"Barcelona",
    "sg:orig_category":"M\u00c9dicos: Cirug\u00cda Cardiovascular Y Tor\u00c1cica",
    "sg:phone":"+34 932 18 00 93",
    "sg:postcode":"08006",
    "sg:province":"Barcelona",
    "wof:name":"Rodriguez Mori Antonio",
    "wof:placetype":"venue"
},
  "geometry": {"coordinates":[2.1516859531,41.399936676],"type":"Point"}
}