{
  "type": "Feature",
  "properties": {
    "addr:full":"Avda Arrabal, 3 Requena Valencia 46340",
    "addr:housenumber":"3",
    "addr:postcode":"46340",
    "addr:street":"Avda Arrabal",
    "iso:country":"ES",
    "sg:address":"Avda Arrabal, 3",
    "sg:city":"Requena",
    "sg:orig_category":"Asesor\u00cda Fiscal Y Jur\u00cddica",
    "sg:phone":"+34 962 32 30 90",
    "sg:postcode":"46340",
    "sg:province":"Valencia",
    "wof:name":"Laborlex C.b.",
    "wof:placetype":"venue"
},
  "geometry": {"coordinates":[-1.1007779837,39.4879226685],"type":"Point"}
}