{
  "type": "Feature",
  "properties": {
    "iso:country":"ES",
    "sg:address":"Calle de Alcala, 408",
    "sg:city":"Madrid",
    "sg:orig_category":"Perfumer\u00cda (al Por Menor)",
    "sg:phone":"+34 913 77 48 95",
    "sg:postcode":"28027",
    "sg:province":"Madrid",
    "sg:website":"www.juteco.es",
    "wof:name":"Geblanc S.a.",
    "wof:placetype":"venue"
},
  "geometry": {"coordinates":[-3.6392788887,40.4373512268],"type":"Point"}
}