{
  "type": "Feature",
  "properties": {
    "addr:full":"Calle de Federico Salmon, 1 Madrid Madrid 28016",
    "addr:housenumber":"1",
    "addr:postcode":"28016",
    "addr:street":"Calle De Federico Salmon",
    "iso:country":"ES",
    "sg:address":"Calle de Federico Salmon, 1",
    "sg:city":"Madrid",
    "sg:orig_category":"Agencias De Viajes",
    "sg:phone":"+34 913 50 38 96",
    "sg:postcode":"28016",
    "sg:province":"Madrid",
    "wof:name":"Solafrica S.a.",
    "wof:placetype":"venue"
},
  "geometry": {"coordinates":[-3.6682472229,40.4599571228],"type":"Point"}
}