{
  "type": "Feature",
  "properties": {
    "addr:full":"Pla\u00c7 Catalunya, 1 Olot Girona 17800",
    "addr:housenumber":"1",
    "addr:postcode":"17800",
    "iso:country":"ES",
    "sg:address":"Pla\u00c7 Catalunya, 1",
    "sg:city":"Olot",
    "sg:orig_category":"Pr\u00c9stamos Personales E Hipotecarios",
    "sg:phone":"+34 972 26 06 79",
    "sg:postcode":"17800",
    "sg:province":"Girona",
    "wof:name":"Rodriguez Alvarez Maria Pilar",
    "wof:placetype":"venue"
},
  "geometry": {"coordinates":[2.4859910011,42.1769447327],"type":"Point"}
}