{
  "type": "Feature",
  "properties": {
    "iso:country":"ES",
    "sg:address":"Calle de San Pedro, 39",
    "sg:city":"Puerto",
    "sg:orig_category":"Mercer\u00cda, Lencer\u00cda (al Por Menor)",
    "sg:phone":"+34 962 67 28 30",
    "sg:postcode":"46520",
    "sg:province":"Valencia",
    "wof:name":"Silvestre Gil Laura",
    "wof:placetype":"venue"
},
  "geometry": {"coordinates":[-0.2287330031,39.6615791321],"type":"Point"}
}