{
  "type": "Feature",
  "properties": {
    "iso:country":"ES",
    "sg:address":"Calle de Santa Marina, 11",
    "sg:city":"Etxebarri",
    "sg:orig_category":"Ropa Para Se\u00d1oras Y Caballeros (al Por Menor)",
    "sg:phone":"+34 944 26 39 75",
    "sg:postcode":"48450",
    "sg:province":"Vizcaya",
    "wof:name":"Emilia Pascual De Diego",
    "wof:placetype":"venue"
},
  "geometry": {"coordinates":[-2.8841090202,43.2541122437],"type":"Point"}
}