{
  "type": "Feature",
  "properties": {
    "addr:full":"Avda General Franco, 68 Santa Uxia De Ribeira La Coru\u00f1a 15960",
    "addr:housenumber":"68",
    "addr:postcode":"15960",
    "addr:street":"Avda General Franco;Corun\u0303A",
    "iso:country":"ES",
    "sg:address":"Avda General Franco, 68",
    "sg:city":"Santa Uxia De Ribeira",
    "sg:orig_category":"Cueros Y Pieles (al Por Mayor)",
    "sg:phone":"+34 981 87 46 35",
    "sg:postcode":"15960",
    "sg:province":"La Coru\u00f1a",
    "wof:name":"Boo Rama Maria Dolores",
    "wof:placetype":"venue"
},
  "geometry": {"coordinates":[-8.9922046661,42.557510376],"type":"Point"}
}