{
  "type": "Feature",
  "properties": {
    "addr:full":"Calle de Murillo, 15 Alcala Henares Madrid 28805",
    "addr:housenumber":"15",
    "addr:postcode":"28805",
    "addr:street":"Calle De Murillo",
    "iso:country":"ES",
    "sg:address":"Calle de Murillo, 15",
    "sg:city":"Alcala Henares",
    "sg:orig_category":"Fabricaci\u00d3n De Peines Y De Accesorios De Peluquer\u00cda",
    "sg:phone":"+34 918 81 63 00",
    "sg:postcode":"28805",
    "sg:province":"Madrid",
    "wof:name":"Roger Carrasco Enrique",
    "wof:placetype":"venue"
},
  "geometry": {"coordinates":[-3.3614048958,40.4872589111],"type":"Point"}
}