{
  "type": "Feature",
  "properties": {
    "iso:country":"ES",
    "sg:address":"Prag Puig De La Coma, 17",
    "sg:city":"Sant Joan De Palamos",
    "sg:orig_category":"Venta, Instalaci\u00d3n De Calefacci\u00d3n",
    "sg:phone":"+34 972 31 54 79",
    "sg:postcode":"17230",
    "sg:province":"Girona",
    "wof:name":"Garcia Cerrillo Jesus",
    "wof:placetype":"venue"
},
  "geometry": {"coordinates":[3.1347301006,41.8531913757],"type":"Point"}
}