{
  "type": "Feature",
  "properties": {
    "addr:full":"Calle de Lindaraja, 2 Granada Granada 18009",
    "addr:housenumber":"2",
    "addr:postcode":"18009",
    "addr:street":"Calle De Lindaraja",
    "iso:country":"ES",
    "sg:address":"Calle de Lindaraja, 2",
    "sg:city":"Granada",
    "sg:orig_category":"Agencias Y Agentes Comerciales, Representantes",
    "sg:phone":"+34 958 22 52 77",
    "sg:postcode":"18009",
    "sg:province":"Granada",
    "wof:name":"Garrido Padial Alfonso",
    "wof:placetype":"venue"
},
  "geometry": {"coordinates":[-3.5945188999,37.1702423096],"type":"Point"}
}