{
  "type": "Feature",
  "properties": {
    "addr:full":"S. Isidro, S/n Huercal-overa Almer\u00eda 04600",
    "addr:housenumber":"s / n",
    "addr:postcode":"04600",
    "addr:street":"S. Isidro;Almeri\u0301A",
    "iso:country":"ES",
    "sg:address":"S. Isidro, S/n",
    "sg:city":"Huercal-overa",
    "sg:orig_category":"Empresas De Carpinter\u00cda Met\u00c1lica",
    "sg:phone":"+34 950 47 07 62",
    "sg:postcode":"04600",
    "sg:province":"Almer\u00eda",
    "wof:name":"J.l.carpinteria Metalica S.l.",
    "wof:placetype":"venue"
},
  "geometry": {"coordinates":[-1.7358249426,37.4396438599],"type":"Point"}
}