{
  "type": "Feature",
  "properties": {
    "iso:country":"ES",
    "sg:address":"Calle de Campamento, 4",
    "sg:city":"Baldio",
    "sg:orig_category":"Aguas (distribuci\u00d3n, Servicios)",
    "sg:phone":"+34 922 54 44 08",
    "sg:postcode":"38280",
    "sg:province":"Santa Cruz De Tenerife",
    "wof:name":"Aqualia Gestion Integral Del Agua S.a.",
    "wof:placetype":"venue"
},
  "geometry": {"coordinates":[-16.2548561096,28.4698104858],"type":"Point"}
}