{
  "type": "Feature",
  "properties": {
    "iso:country":"ES",
    "sg:address":"Barr El Casta\u00d1o, 19",
    "sg:city":"Casta\u00d1o",
    "sg:orig_category":"Bazares, Art\u00cdculos De Limpieza Y De Cocina (al Por Menor)",
    "sg:phone":"+34 946 50 44 59",
    "sg:postcode":"48190",
    "sg:province":"Vizcaya",
    "wof:name":"Velasco Vadillo Maria De Los Angeles",
    "wof:placetype":"venue"
},
  "geometry": {"coordinates":[-3.1545369625,43.2622108459],"type":"Point"}
}