{
  "type": "Feature",
  "properties": {
    "addr:full":"Pol Ind Cuatro Vientos, S/n Prado Del Rey C\u00e1diz 11660",
    "addr:housenumber":"s / n",
    "addr:postcode":"11660",
    "addr:street":"Cuatro Vientos",
    "iso:country":"ES",
    "sg:address":"Pol Ind Cuatro Vientos, S/n",
    "sg:city":"Prado Del Rey",
    "sg:orig_category":"Fabricaci\u00d3n De Mobiliario Met\u00c1lico",
    "sg:phone":"+34 956 72 44 24",
    "sg:postcode":"11660",
    "sg:province":"C\u00e1diz",
    "wof:name":"Romero Rosado Antonio",
    "wof:placetype":"venue"
},
  "geometry": {"coordinates":[-5.5557088852,36.7894134521],"type":"Point"}
}