{
  "type": "Feature",
  "properties": {
    "addr:full":"Calle de Concepcion, 13 Burgos Burgos 09002",
    "addr:housenumber":"13",
    "addr:postcode":"09002",
    "addr:street":"Calle De Concepcion",
    "iso:country":"ES",
    "sg:address":"Calle de Concepcion, 13",
    "sg:city":"Burgos",
    "sg:orig_category":"Institutos De Belleza",
    "sg:phone":"+34 947 26 85 54",
    "sg:postcode":"09002",
    "sg:province":"Burgos",
    "wof:name":"Pe\u00f1a Gonzalez Sagrario",
    "wof:placetype":"venue"
},
  "geometry": {"coordinates":[-3.7027533054,42.3371505737],"type":"Point"}
}