{
  "type": "Feature",
  "properties": {
    "addr:full":"Calle de Brigadier Algarra, 33 Petrer Alicante 03610",
    "addr:housenumber":"33",
    "addr:postcode":"03610",
    "addr:street":"Calle De Brigadier Algarra",
    "iso:country":"ES",
    "sg:address":"Calle de Brigadier Algarra, 33",
    "sg:city":"Petrer",
    "sg:orig_category":"Estancos",
    "sg:phone":"+34 966 95 04 77",
    "sg:postcode":"03610",
    "sg:province":"Alicante",
    "wof:name":"Minguez Tarraga Salvador",
    "wof:placetype":"venue"
},
  "geometry": {"coordinates":[-0.7800529003,38.4827041626],"type":"Point"}
}