{
  "type": "Feature",
  "properties": {
    "addr:full":"Calle de Doctor Placido Ba\u00d1uelos, 4 Huelva Huelva 21004",
    "addr:housenumber":"4",
    "addr:postcode":"21004",
    "addr:street":"Calle De Doctor Placido Ban\u0303Uelos",
    "iso:country":"ES",
    "sg:address":"Calle de Doctor Placido Ba\u00d1uelos, 4",
    "sg:city":"Huelva",
    "sg:orig_category":"Asistencia Y Consejos",
    "sg:phone":"+34 959 28 17 83",
    "sg:postcode":"21004",
    "sg:province":"Huelva",
    "wof:name":"Reyes Acosta Jose Manuel",
    "wof:placetype":"venue"
},
  "geometry": {"coordinates":[-6.9498167038,37.2606315613],"type":"Point"}
}