{
  "type": "Feature",
  "properties": {
    "addr:full":"Calle de San Prudencio, 6 Vitoria-gasteiz \u00c1lava 01005",
    "addr:housenumber":"6",
    "addr:postcode":"01005",
    "addr:street":"Calle De San Prudencio",
    "iso:country":"ES",
    "sg:address":"Calle de San Prudencio, 6",
    "sg:city":"Vitoria-gasteiz",
    "sg:orig_category":"Asociaciones, Organismos Culturales Y Socioeducativos",
    "sg:phone":"+34 945 23 42 17",
    "sg:postcode":"01005",
    "sg:province":"\u00c1lava",
    "wof:name":"Asociacion Cultural Fila 2",
    "wof:placetype":"venue"
},
  "geometry": {"coordinates":[-2.6732130051,42.8441162109],"type":"Point"}
}