{
  "type": "Feature",
  "properties": {
    "iso:country":"ES",
    "sg:address":"Calle de Berlin, S/n",
    "sg:city":"Estacion",
    "sg:orig_category":"Reposter\u00cdas",
    "sg:phone":"+34 952 42 00 41",
    "sg:postcode":"29580",
    "sg:province":"M\u00e1laga",
    "wof:name":"Martin Mancera Cristobal",
    "wof:placetype":"venue"
},
  "geometry": {"coordinates":[-4.6160664558,36.7347221375],"type":"Point"}
}