{
  "type": "Feature",
  "properties": {
    "addr:full":"Ctra Segovia, 46 Sanchonu\u00d1o Segovia 40297",
    "addr:housenumber":"46",
    "addr:postcode":"40297",
    "addr:street":"Ctra Segovia",
    "iso:country":"ES",
    "sg:address":"Ctra Segovia, 46",
    "sg:city":"Sanchonu\u00d1o",
    "sg:orig_category":"Congelados: Productos Alimentarios (al Por Menor)",
    "sg:phone":"+34 921 16 04 93",
    "sg:postcode":"40297",
    "sg:province":"Segovia",
    "wof:name":"Ultracongelados Del Duero S.l.",
    "wof:placetype":"venue"
},
  "geometry": {"coordinates":[-4.3065690994,41.3226203918],"type":"Point"}
}