{
  "type": "Feature",
  "properties": {
    "addr:full":"Calle de Herra (la), S/n Llano De La Herra Almer\u00eda 04869",
    "addr:postcode":"04869",
    "addr:street":"Calle De Herra La S / N;Almeri\u0301A",
    "iso:country":"ES",
    "sg:address":"Calle de Herra (la), S/n",
    "sg:city":"Llano De La Herra",
    "sg:orig_category":"Mec\u00c1nico Del Autom\u00d3vil",
    "sg:phone":"+34 950 44 42 09",
    "sg:postcode":"04869",
    "sg:province":"Almer\u00eda",
    "wof:name":"Talleres Valdes S.a.",
    "wof:placetype":"venue"
},
  "geometry": {"coordinates":[-2.2664690018,37.3596115112],"type":"Point"}
}