{
  "type": "Feature",
  "properties": {
    "iso:country":"ES",
    "sg:address":"Rua Magdalena, 159",
    "sg:city":"Ferrol",
    "sg:orig_category":"Electricidad, Electr\u00d3nica: Suministros (al Por Menor)",
    "sg:phone":"+34 981 35 71 12",
    "sg:postcode":"15402",
    "sg:province":"La Coru\u00f1a",
    "wof:name":"Juan Carlos Lopez Veloso Y Otro Cdad.",
    "wof:placetype":"venue"
},
  "geometry": {"coordinates":[-8.2354812622,43.4823303223],"type":"Point"}
}