{
  "type": "Feature",
  "properties": {
    "iso:country":"ES",
    "sg:address":"Carrer de Assumpcio, 3",
    "sg:city":"Benidorm",
    "sg:orig_category":"Molduras, Junquillos, Listones Y Molduras Perforadas",
    "sg:phone":"+34 965 85 15 58",
    "sg:postcode":"03500",
    "sg:province":"Alicante",
    "wof:name":"Torres Gil Jesus",
    "wof:placetype":"venue"
},
  "geometry": {"coordinates":[-0.1308719963,38.5382156372],"type":"Point"}
}