{
  "type": "Feature",
  "properties": {
    "iso:country":"ES",
    "sg:address":"Avda Perez Galdos, 19",
    "sg:city":"Castellon",
    "sg:orig_category":"Pintores",
    "sg:phone":"+34 964 20 34 31",
    "sg:postcode":"12002",
    "sg:province":"Castell\u00f3n",
    "wof:name":"Capilla Rubio Maria Pilar",
    "wof:placetype":"venue"
},
  "geometry": {"coordinates":[-0.0463289991,39.9865570068],"type":"Point"}
}