{
  "type": "Feature",
  "properties": {
    "iso:country":"ES",
    "sg:address":"Carrer de Lumiere, 9",
    "sg:city":"Rubi",
    "sg:orig_category":"Cajas De Ahorro",
    "sg:phone":"+34 935 86 12 85",
    "sg:postcode":"08191",
    "sg:province":"Barcelona",
    "wof:name":"Caixa D'estalvis Laietana",
    "wof:placetype":"venue"
},
  "geometry": {"coordinates":[2.0356669426,41.4866485596],"type":"Point"}
}