{
  "type": "Feature",
  "properties": {
    "iso:country":"ES",
    "sg:address":"Avda Mediterraneo, 2",
    "sg:city":"Teulada",
    "sg:orig_category":"Art\u00cdculos De Decoraci\u00d3n",
    "sg:phone":"+34 965 74 01 30",
    "sg:postcode":"03725",
    "sg:province":"Alicante",
    "wof:name":"Rodafoc S.l.",
    "wof:placetype":"venue"
},
  "geometry": {"coordinates":[0.0975700021,38.7275810242],"type":"Point"}
}