{
  "type": "Feature",
  "properties": {
    "addr:full":"Calle de San Juan, 28 Medina Rioseco Valladolid 47800",
    "addr:housenumber":"28",
    "addr:postcode":"47800",
    "addr:street":"Calle De San Juan",
    "iso:country":"ES",
    "sg:address":"Calle de San Juan, 28",
    "sg:city":"Medina Rioseco",
    "sg:orig_category":"Electrodom\u00c9sticos (al Por Menor)",
    "sg:phone":"+34 983 70 01 95",
    "sg:postcode":"47800",
    "sg:province":"Valladolid",
    "wof:name":"Centeno Perez Roberto",
    "wof:placetype":"venue"
},
  "geometry": {"coordinates":[-5.0455989838,41.8837814331],"type":"Point"}
}