{
  "type": "Feature",
  "properties": {
    "addr:full":"Carrer de Riera (de La), 76 Vila-seca Tarragona 43480",
    "addr:housenumber":"76",
    "addr:postcode":"43480",
    "addr:street":"Carrer De Riera De La",
    "iso:country":"ES",
    "sg:address":"Carrer de Riera (de La), 76",
    "sg:city":"Vila-seca",
    "sg:orig_category":"Empresarios",
    "sg:phone":"+34 977 39 27 70",
    "sg:postcode":"43480",
    "sg:province":"Tarragona",
    "wof:name":"Centiservice Del Mediterraneo S.l.",
    "wof:placetype":"venue"
},
  "geometry": {"coordinates":[1.1435749531,41.1112098694],"type":"Point"}
}