{
  "type": "Feature",
  "properties": {
    "iso:country":"ES",
    "sg:address":"Calle de Jerez De Los Caballeros, 13",
    "sg:city":"Madrid",
    "sg:orig_category":"Molduras, Junquillos, Listones Y Molduras Perforadas",
    "sg:phone":"+34 913 29 35 37",
    "sg:postcode":"28042",
    "sg:province":"Madrid",
    "wof:name":"Pasamontes Sanchez-valladares Pedro",
    "wof:placetype":"venue"
},
  "geometry": {"coordinates":[-3.5790178776,40.4703559875],"type":"Point"}
}