{
  "type": "Feature",
  "properties": {
    "iso:country":"ES",
    "sg:address":"C/ Sant Bartomeu, 15",
    "sg:city":"Inca",
    "sg:orig_category":"Muebles Y Accesorios Para Cocinas Y Cuartos De Ba\u00d1o (al Por Menor)",
    "sg:phone":"+34 971 88 02 13",
    "sg:postcode":"07300",
    "sg:province":"Islas Baleares",
    "wof:name":"Rotger Sanz Francisco",
    "wof:placetype":"venue"
},
  "geometry": {"coordinates":[2.909250021,39.7216186523],"type":"Point"}
}