{
  "type": "Feature",
  "properties": {
    "addr:full":"Calle de Coronacion De La Virgen Blanca, 11 Vitoria-gasteiz \u00c1lava 01012",
    "addr:housenumber":"11",
    "addr:postcode":"01012",
    "addr:street":"Calle De Coronacion De La Virgen Blanca",
    "iso:country":"ES",
    "sg:address":"Calle de Coronacion De La Virgen Blanca, 11",
    "sg:city":"Vitoria-gasteiz",
    "sg:orig_category":"Ropa Para Ni\u00d1os (al Por Menor)",
    "sg:phone":"+34 945 24 69 96",
    "sg:postcode":"01012",
    "sg:province":"\u00c1lava",
    "wof:name":"Marian Y Jose C.b.",
    "wof:placetype":"venue"
},
  "geometry": {"coordinates":[-2.6754794121,42.8526000977],"type":"Point"}
}