{
  "type": "Feature",
  "properties": {
    "addr:full":"Avda Logro\u00d1o, S/n Haro La Rioja 26200",
    "addr:housenumber":"s / n",
    "addr:postcode":"26200",
    "addr:street":"Avda Logron\u0303O",
    "iso:country":"ES",
    "sg:address":"Avda Logro\u00d1o, S/n",
    "sg:city":"Haro",
    "sg:orig_category":"Poller\u00cda Y Caza (al Por Menor)",
    "sg:phone":"+34 941 31 00 90",
    "sg:postcode":"26200",
    "sg:province":"La Rioja",
    "wof:name":"Bilbao Hormilla Roberto",
    "wof:placetype":"venue"
},
  "geometry": {"coordinates":[-2.8460888863,42.571723938],"type":"Point"}
}