{
  "type": "Feature",
  "properties": {
    "addr:full":"Pol Ind Riu Clar, S/n Tarragona Tarragona 43006",
    "addr:housenumber":"s / n",
    "addr:postcode":"43006",
    "iso:country":"ES",
    "sg:address":"Pol Ind Riu Clar, S/n",
    "sg:city":"Tarragona",
    "sg:orig_category":"Fabricaci\u00d3n De Moldes Y Modelos",
    "sg:phone":"+34 977 54 28 36",
    "sg:postcode":"43006",
    "sg:province":"Tarragona",
    "wof:name":"Industria De Caldereria Del Plastico S.l.",
    "wof:placetype":"venue"
},
  "geometry": {"coordinates":[1.2235889435,41.1193885803],"type":"Point"}
}