{
  "type": "Feature",
  "properties": {
    "addr:full":"Calle de Doctrinos, 20 Valladolid Valladolid 47001",
    "addr:housenumber":"20",
    "addr:postcode":"47001",
    "addr:street":"Calle De Doctrinos",
    "iso:country":"ES",
    "sg:address":"Calle de Doctrinos, 20",
    "sg:city":"Valladolid",
    "sg:orig_category":"Ingeniero",
    "sg:phone":"+34 983 35 11 52",
    "sg:postcode":"47001",
    "sg:province":"Valladolid",
    "wof:name":"Sanchez Gutierrez Vidal Felix",
    "wof:placetype":"venue"
},
  "geometry": {"coordinates":[-4.7323489189,41.6495437622],"type":"Point"}
}