{
  "type": "Feature",
  "properties": {
    "addr:full":"Bai\u00f1as, 108 Bai\u00f1as A Coru\u00f1a 15127",
    "addr:housenumber":"108",
    "addr:postcode":"15127",
    "addr:street":"Bain\u0303As;Corun\u0303A",
    "iso:country":"ES",
    "sg:address":"Bai\u00f1as, 108",
    "sg:city":"Bai\u00f1as",
    "sg:orig_category":"Transportes Por V\u00cdas Navegables",
    "sg:phone":"+34 981 74 10 37",
    "sg:postcode":"15127",
    "sg:province":"A Coru\u00f1a",
    "wof:name":"Trillo Fidalgo Andres",
    "wof:placetype":"venue"
},
  "geometry": {"coordinates":[-8.95773983,43.1091461182],"type":"Point"}
}