{
  "type": "Feature",
  "properties": {
    "addr:full":"Carrer de Sant Antoni (de), 2 S. Carles Rapita Tarragona 43540",
    "addr:postcode":"43540",
    "addr:street":"Carrer De Sant Antoni De 2 S. Carles Rapita",
    "iso:country":"ES",
    "sg:address":"Carrer de Sant Antoni (de), 2",
    "sg:city":"S. Carles Rapita",
    "sg:orig_category":"Librer\u00cdas",
    "sg:phone":"+34 977 74 33 50",
    "sg:postcode":"43540",
    "sg:province":"Tarragona",
    "wof:name":"Tarragona Pedros Mari Carmen",
    "wof:placetype":"venue"
},
  "geometry": {"coordinates":[0.5928440094,40.6209373474],"type":"Point"}
}