{
  "type": "Feature",
  "properties": {
    "iso:country":"ES",
    "sg:address":"Calle de Yebenes, 112",
    "sg:city":"Madrid",
    "sg:orig_category":"Mudanzas",
    "sg:phone":"+34 917 18 02 02",
    "sg:postcode":"28047",
    "sg:province":"Madrid",
    "wof:name":"De Pablo Gil Fortunato",
    "wof:placetype":"venue"
},
  "geometry": {"coordinates":[-3.7518041134,40.3918075562],"type":"Point"}
}