{
  "type": "Feature",
  "properties": {
    "iso:country":"ES",
    "sg:address":"Calle de Dr Gonzalez Hierro, 3",
    "sg:city":"Guadalajara",
    "sg:orig_category":"Producci\u00d3n De Abonos Y De Fertilizantes",
    "sg:phone":"+34 949 21 74 73",
    "sg:postcode":"19002",
    "sg:province":"Guadalajara",
    "wof:name":"Fernandez Calvo Olegario",
    "wof:placetype":"venue"
},
  "geometry": {"coordinates":[-3.1631519794,40.6233177185],"type":"Point"}
}