{
  "type": "Feature",
  "properties": {
    "addr:full":"Avda Pio Xii, 11 Logro\u00f1o La Rioja 26003",
    "addr:housenumber":"11",
    "addr:postcode":"26003",
    "addr:street":"Avda Pio Xii;Rioja",
    "iso:country":"ES",
    "sg:address":"Avda Pio Xii, 11",
    "sg:city":"Logro\u00f1o",
    "sg:orig_category":"Ingeniero",
    "sg:phone":"+34 941 23 54 17",
    "sg:postcode":"26003",
    "sg:province":"La Rioja",
    "wof:name":"Hernandez Zato Francisco Manuel",
    "wof:placetype":"venue"
},
  "geometry": {"coordinates":[-2.4443280697,42.4605674744],"type":"Point"}
}