{
  "type": "Feature",
  "properties": {
    "addr:full":"Calle de Santa Clotilde, 44 Granada Granada 18003",
    "addr:housenumber":"44",
    "addr:postcode":"18003",
    "addr:street":"Calle De Santa Clotilde",
    "iso:country":"ES",
    "sg:address":"Calle de Santa Clotilde, 44",
    "sg:city":"Granada",
    "sg:orig_category":"Enfermeras: Consultas, Atenci\u00d3n A Domicilio",
    "sg:phone":"+34 958 27 59 32",
    "sg:postcode":"18003",
    "sg:province":"Granada",
    "wof:name":"Consultorio A.t.s. Santa Clotilde C.b.",
    "wof:placetype":"venue"
},
  "geometry": {"coordinates":[-3.6131858826,37.1811141968],"type":"Point"}
}