{
  "type": "Feature",
  "properties": {
    "iso:country":"ES",
    "sg:address":"Avda Rambla (la), 52",
    "sg:city":"Sant Joan D'alacant",
    "sg:orig_category":"Asesor\u00cda Fiscal Y Jur\u00cddica",
    "sg:phone":"+34 965 65 10 35",
    "sg:postcode":"03550",
    "sg:province":"Alicante",
    "wof:name":"Giner Pastor Rosa Maria",
    "wof:placetype":"venue"
},
  "geometry": {"coordinates":[-0.4804700017,38.3440818787],"type":"Point"}
}