{
  "type": "Feature",
  "properties": {
    "addr:full":"Pol Ind El Trocadero, S/n Pto Real C\u00e1diz 11519",
    "addr:housenumber":"s / n",
    "addr:postcode":"11519",
    "addr:street":"Pto;Ca\u0301Diz",
    "iso:country":"ES",
    "sg:address":"Pol Ind El Trocadero, S/n",
    "sg:city":"Pto Real",
    "sg:orig_category":"Seguridad Social",
    "sg:phone":"+34 956 80 50 69",
    "sg:postcode":"11519",
    "sg:province":"C\u00e1diz",
    "sg:website":"www.fremap.es",
    "wof:name":"Fremap Mutua De Accidentes De Trabajo Y Enferm.profes.de S.s.61",
    "wof:placetype":"venue"
},
  "geometry": {"coordinates":[-6.2170300484,36.5123291016],"type":"Point"}
}