{
  "type": "Feature",
  "properties": {
    "addr:full":"Calle de Puerto De Alazores, 25 Madrid Madrid 28031",
    "addr:housenumber":"25",
    "addr:postcode":"madrid;28031",
    "addr:street":"Calle De Puerto De Alazores",
    "iso:country":"ES",
    "sg:address":"Calle de Puerto De Alazores, 25",
    "sg:city":"Madrid",
    "sg:orig_category":"Centros Empresariales",
    "sg:phone":"+34 913 03 94 32",
    "sg:postcode":"28031",
    "sg:province":"Madrid",
    "wof:name":"Riojo Beltre S.l.",
    "wof:placetype":"venue"
},
  "geometry": {"coordinates":[-3.6269481182,40.3781852722],"type":"Point"}
}