{
  "type": "Feature",
  "properties": {
    "iso:country":"ES",
    "sg:address":"Pol Ind Rodiella, 5",
    "sg:city":"Benasque",
    "sg:orig_category":"Transportes En Volquetes Basculantes",
    "sg:phone":"+34 974 55 12 61",
    "sg:postcode":"22440",
    "sg:province":"Huesca",
    "wof:name":"Excavaciones Aventin S.l.",
    "wof:placetype":"venue"
},
  "geometry": {"coordinates":[0.5215880275,42.6030426025],"type":"Point"}
}