{
  "type": "Feature",
  "properties": {
    "iso:country":"ES",
    "sg:address":"Calle de Motril, 7",
    "sg:city":"Gabia Grande",
    "sg:orig_category":"Electrodom\u00c9sticos (al Por Menor)",
    "sg:phone":"+34 958 58 00 07",
    "sg:postcode":"18110",
    "sg:province":"Granada",
    "wof:name":"Bertos Sanchez Jose Juan",
    "wof:placetype":"venue"
},
  "geometry": {"coordinates":[-3.6692740917,37.1363105774],"type":"Point"}
}