{
  "type": "Feature",
  "properties": {
    "iso:country":"ES",
    "sg:address":"Bo Goiri, S/n",
    "sg:city":"Libao",
    "sg:orig_category":"Muebles Y Accesorios Para Cocinas Y Cuartos De Ba\u00d1o (al Por Menor)",
    "sg:phone":"+34 946 15 35 04",
    "sg:postcode":"48114",
    "sg:province":"Vizcaya",
    "wof:name":"Ibinarriaga Urtisbidea Juan",
    "wof:placetype":"venue"
},
  "geometry": {"coordinates":[-2.7691090107,43.3420410156],"type":"Point"}
}