{
  "type": "Feature",
  "properties": {
    "iso:country":"ES",
    "sg:address":"Rua Iglesia Albari\u00d1o, 5",
    "sg:city":"Ourense",
    "sg:orig_category":"Caf\u00c9s, Bares, Cervecer\u00cdas",
    "sg:phone":"+34 988 24 65 74",
    "sg:postcode":"32004",
    "sg:province":"Ourense",
    "wof:name":"Dominguez Seoane Luis",
    "wof:placetype":"venue"
},
  "geometry": {"coordinates":[-7.8510928154,42.3407478333],"type":"Point"}
}