{
  "type": "Feature",
  "properties": {
    "addr:full":"Carrer de Platja, 12 Peguera Islas Baleares 07160",
    "addr:housenumber":"12",
    "addr:postcode":"07160",
    "addr:street":"Carrer De Platja",
    "iso:country":"ES",
    "sg:address":"Carrer de Platja, 12",
    "sg:city":"Peguera",
    "sg:orig_category":"Art\u00cdculos De Regalo (al Por Menor)",
    "sg:phone":"+34 971 68 63 03",
    "sg:postcode":"07160",
    "sg:province":"Islas Baleares",
    "wof:name":"Frau Llado Pedro Juan",
    "wof:placetype":"venue"
},
  "geometry": {"coordinates":[2.4549601078,39.5355491638],"type":"Point"}
}