{
  "type": "Feature",
  "properties": {
    "iso:country":"ES",
    "sg:address":"Carrer de Argentina (de L'), 23",
    "sg:city":"Tortosa",
    "sg:orig_category":"Inform\u00c1tica, Ofim\u00c1tica (estudios, Asesor\u00cda, Ingenier\u00cda, Formaci\u00d3n)",
    "sg:phone":"+34 977 44 57 68",
    "sg:postcode":"43500",
    "sg:province":"Tarragona",
    "wof:name":"Gabinet D'estudis Formacio I Asesorament S.l.",
    "wof:placetype":"venue"
},
  "geometry": {"coordinates":[0.5207728148,40.8097686768],"type":"Point"}
}