{
  "type": "Feature",
  "properties": {
    "iso:country":"ES",
    "sg:address":"La Rosa, S/n",
    "sg:city":"Fuente Del Arco",
    "sg:orig_category":"Negocio De Materiales De Construcci\u00d3n",
    "sg:phone":"+34 924 87 81 40",
    "sg:postcode":"06980",
    "sg:province":"Badajoz",
    "wof:name":"Materiales De Construccion Martin C.b.",
    "wof:placetype":"venue"
},
  "geometry": {"coordinates":[-5.8981909752,38.152130127],"type":"Point"}
}