{
  "type": "Feature",
  "properties": {
    "iso:country":"ES",
    "sg:address":"Po. Olmos, S/n",
    "sg:city":"Monteprincipe",
    "sg:orig_category":"Pintores",
    "sg:phone":"+34 917 15 60 56",
    "sg:postcode":"28668",
    "sg:province":"Madrid",
    "wof:name":"Soler Raffo Maria Del Pilar",
    "wof:placetype":"venue"
},
  "geometry": {"coordinates":[-3.8429419994,40.4011039734],"type":"Point"}
}