{
  "type": "Feature",
  "properties": {
    "addr:full":"Calle de Lapurdi, 14 Kurtzea Vizcaya 48960",
    "addr:housenumber":"14",
    "addr:postcode":"48960",
    "addr:street":"Calle De Lapurdi",
    "iso:country":"ES",
    "sg:address":"Calle de Lapurdi, 14",
    "sg:city":"Kurtzea",
    "sg:orig_category":"Promotores Constructores",
    "sg:phone":"+34 944 56 81 20",
    "sg:postcode":"48960",
    "sg:province":"Vizcaya",
    "wof:name":"Aba 2006 S.l",
    "wof:placetype":"venue"
},
  "geometry": {"coordinates":[-2.698387,43.220428],"type":"Point"}
}