{
  "type": "Feature",
  "properties": {
    "iso:country":"ES",
    "sg:address":"Calle de Alcalde Henche De La Plata, 7",
    "sg:city":"Madrid",
    "sg:orig_category":"Cajas De Ahorro",
    "sg:phone":"+34 917 50 23 94",
    "sg:postcode":"28050",
    "sg:province":"Madrid",
    "wof:name":"Caja De Ahorros De Salamanca Y Soria",
    "wof:placetype":"venue"
},
  "geometry": {"coordinates":[-3.649636507,40.4884719849],"type":"Point"}
}