{
  "type": "Feature",
  "properties": {
    "addr:full":"Calle de Gregorio Espin, 10 Granada Granada 18002",
    "addr:housenumber":"10",
    "addr:postcode":"18002",
    "addr:street":"Calle De Gregorio Espin",
    "iso:country":"ES",
    "sg:address":"Calle de Gregorio Espin, 10",
    "sg:city":"Granada",
    "sg:orig_category":"Alquiler De Casas Y Habitaciones Amuebladas",
    "sg:phone":"+34 958 27 03 60",
    "sg:postcode":"18002",
    "sg:province":"Granada",
    "wof:name":"Residencia Universitaria Sol Granada S.l.",
    "wof:placetype":"venue"
},
  "geometry": {"coordinates":[-3.6075429916,37.1760482788],"type":"Point"}
}