{
  "type": "Feature",
  "properties": {
    "iso:country":"ES",
    "sg:address":"Hnos Imaz, 1",
    "sg:city":"Iru\u00f1a",
    "sg:orig_category":"Arquitectos",
    "sg:phone":"+34 948 22 69 13",
    "sg:postcode":"31002",
    "sg:province":"Navarra",
    "wof:name":"Sarobe Pueyo Francisco Javier",
    "wof:placetype":"venue"
},
  "geometry": {"coordinates":[-1.6501410007,42.8152732849],"type":"Point"}
}