{
  "type": "Feature",
  "properties": {
    "addr:full":"Ctra. S. Pablo, S/n Menasalbas Toledo 45128",
    "addr:housenumber":"s / n",
    "addr:postcode":"45128",
    "addr:street":"Ctra. S. Pablo",
    "iso:country":"ES",
    "sg:address":"Ctra. S. Pablo, S/n",
    "sg:city":"Menasalbas",
    "sg:orig_category":"Mobiliario Para Hoteles",
    "sg:phone":"+34 925 41 30 46",
    "sg:postcode":"45128",
    "sg:province":"Toledo",
    "wof:name":"Ruiz Y Vaquero S.l.",
    "wof:placetype":"venue"
},
  "geometry": {"coordinates":[-4.2866740227,39.6354866028],"type":"Point"}
}