{
  "type": "Feature",
  "properties": {
    "iso:country":"ES",
    "sg:address":"Calle de Antonio Machado, 3",
    "sg:city":"Espinar",
    "sg:orig_category":"Pescader\u00cdas (al Por Menor)",
    "sg:phone":"+34 921 18 14 12",
    "sg:postcode":"40400",
    "sg:province":"Segovia",
    "wof:name":"Lozano Sanz Isidoro",
    "wof:placetype":"venue"
},
  "geometry": {"coordinates":[-4.2478928566,40.7181663513],"type":"Point"}
}