{
  "type": "Feature",
  "properties": {
    "iso:country":"ES",
    "sg:address":"Rond Santiago, 12",
    "sg:city":"Tudela Duero",
    "sg:orig_category":"Empresas De Carpinter\u00cda Met\u00c1lica",
    "sg:phone":"+34 983 52 26 99",
    "sg:postcode":"47320",
    "sg:province":"Valladolid",
    "wof:name":"Hijos De Emilio Garcia C.b.",
    "wof:placetype":"venue"
},
  "geometry": {"coordinates":[-4.7283878326,41.6529464722],"type":"Point"}
}