{
  "type": "Feature",
  "properties": {
    "iso:country":"ES",
    "sg:address":"Miguel De Unamuno, 6",
    "sg:city":"Campillo Salvatierra",
    "sg:orig_category":"Carnicer\u00cdas, Carnicer\u00cdas",
    "sg:phone":"+34 923 58 01 45",
    "sg:postcode":"37778",
    "sg:province":"Salamanca",
    "wof:name":"Sanchez Sanchez Matilde",
    "wof:placetype":"venue"
},
  "geometry": {"coordinates":[-5.6760821342,40.570766449],"type":"Point"}
}