{
  "type": "Feature",
  "properties": {
    "addr:full":"Avda Virgen De Los Imposibles, 39 Villacedre Le\u00f3n 24194",
    "addr:housenumber":"39",
    "addr:postcode":"24194",
    "addr:street":"Avda Virgen De Los Imposibles;Leo\u0301N",
    "iso:country":"ES",
    "sg:address":"Avda Virgen De Los Imposibles, 39",
    "sg:city":"Villacedre",
    "sg:orig_category":"Iglesia Cat\u00d3lica",
    "sg:phone":"+34 987 21 63 04",
    "sg:postcode":"24194",
    "sg:province":"Le\u00f3n",
    "wof:name":"Parroquia De Villacedre",
    "wof:placetype":"venue"
},
  "geometry": {"coordinates":[-5.5894088745,42.559589386],"type":"Point"}
}