{
  "type": "Feature",
  "properties": {
    "iso:country":"ES",
    "sg:address":"Avda Costa Blanca, 21",
    "sg:city":"Alacant",
    "sg:orig_category":"Mercer\u00cda, Lencer\u00cda (al Por Menor)",
    "sg:phone":"+34 965 15 04 66",
    "sg:postcode":"03540",
    "sg:province":"Alicante",
    "wof:name":"Soler Calero Victoria",
    "wof:placetype":"venue"
},
  "geometry": {"coordinates":[-0.4297060072,38.3571510315],"type":"Point"}
}