{
  "type": "Feature",
  "properties": {
    "iso:country":"ES",
    "sg:address":"Calle de San Vicente, 7",
    "sg:city":"San Vicente De Barakaldo",
    "sg:orig_category":"Inform\u00c1tica: Material Y Suministros",
    "sg:phone":"+34 944 37 17 90",
    "sg:postcode":"48902",
    "sg:province":"Vizcaya",
    "wof:name":"Mobiliario Oficina M.o.h.r. S.l.",
    "wof:placetype":"venue"
},
  "geometry": {"coordinates":[-2.9934210777,43.2951812744],"type":"Point"}
}