{
  "type": "Feature",
  "properties": {
    "iso:country":"ES",
    "sg:address":"Ctra Camas-albaida, Km. 0004,0",
    "sg:city":"Valencina Concepcion",
    "sg:orig_category":"Negocio De Materiales De Construcci\u00d3n",
    "sg:phone":"+34 955 72 74 89",
    "sg:postcode":"41907",
    "sg:province":"Sevilla",
    "wof:name":"Hermanos Marin S.cv.",
    "wof:placetype":"venue"
},
  "geometry": {"coordinates":[-6.0776147842,37.4170455933],"type":"Point"}
}