{
  "type": "Feature",
  "properties": {
    "addr:full":"C/ Torres I Bages, 9 Banyoles Girona 17820",
    "addr:housenumber":"9",
    "addr:postcode":"17820",
    "addr:street":"C / Torres I Bages",
    "iso:country":"ES",
    "sg:address":"C/ Torres I Bages, 9",
    "sg:city":"Banyoles",
    "sg:orig_category":"Animales (al Por Menor)",
    "sg:phone":"+34 972 57 24 62",
    "sg:postcode":"17820",
    "sg:province":"Girona",
    "wof:name":"Rodeja Estarriola Maria Lourdes",
    "wof:placetype":"venue"
},
  "geometry": {"coordinates":[2.7668600082,42.1164169312],"type":"Point"}
}