{
  "type": "Feature",
  "properties": {
    "addr:full":"Calle de Salve, S/n Torrijos Toledo 45500",
    "addr:housenumber":"s / n",
    "addr:postcode":"45500",
    "addr:street":"Calle De Salve",
    "iso:country":"ES",
    "sg:address":"Calle de Salve, S/n",
    "sg:city":"Torrijos",
    "sg:orig_category":"Asociaciones Y Clubs Deportivos",
    "sg:phone":"+34 925 76 26 61",
    "sg:postcode":"45500",
    "sg:province":"Toledo",
    "wof:name":"Marcos Gordo Patricia",
    "wof:placetype":"venue"
},
  "geometry": {"coordinates":[-4.2913498878,39.9764060974],"type":"Point"}
}