{
  "type": "Feature",
  "properties": {
    "addr:full":"Avda Canarias, 294 Vecindario Las Palmas 35110",
    "addr:housenumber":"294",
    "addr:postcode":"35110",
    "addr:street":"Avda Canarias;Palmas",
    "iso:country":"ES",
    "sg:address":"Avda Canarias, 294",
    "sg:city":"Vecindario",
    "sg:orig_category":"Zapatos (al Por Menor)",
    "sg:phone":"+34 928 75 95 24",
    "sg:postcode":"35110",
    "sg:province":"Las Palmas",
    "wof:name":"Aleman Quevedo Jose Manuel",
    "wof:placetype":"venue"
},
  "geometry": {"coordinates":[-15.4435758591,27.8472061157],"type":"Point"}
}