{
  "type": "Feature",
  "properties": {
    "addr:full":"Carrer de Valles I Ribot, 2 Palleja Barcelona 08780",
    "addr:housenumber":"2",
    "addr:postcode":"08780",
    "addr:street":"Carrer De Valles I Ribot",
    "iso:country":"ES",
    "sg:address":"Carrer de Valles I Ribot, 2",
    "sg:city":"Palleja",
    "sg:orig_category":"Asociaciones Humanitarias, De Cooperaci\u00d3n, De Acci\u00d3n Social",
    "sg:phone":"+34 936 63 23 88",
    "sg:postcode":"08780",
    "sg:province":"Barcelona",
    "wof:name":"Fundacio Ana Ribot",
    "wof:placetype":"venue"
},
  "geometry": {"coordinates":[1.9977860451,41.4211578369],"type":"Point"}
}