{
  "type": "Feature",
  "properties": {
    "addr:full":"Carrer de Pare J Moranta, S/n Palma Islas Baleares 07010",
    "addr:housenumber":"s",
    "addr:postcode":"07010",
    "addr:street":"Carrer De Pare J Moranta;/ N",
    "iso:country":"ES",
    "sg:address":"Carrer de Pare J Moranta, S/n",
    "sg:city":"Palma",
    "sg:orig_category":"Fabricaci\u00d3n, Instalaci\u00d3n De Armarios",
    "sg:phone":"+34 971 75 62 89",
    "sg:postcode":"07010",
    "sg:province":"Islas Baleares",
    "sg:website":"www.donarmario.com",
    "wof:name":"Don Armario S.l.",
    "wof:placetype":"venue"
},
  "geometry": {"coordinates":[2.6469769478,39.5936775208],"type":"Point"}
}