{
  "type": "Feature",
  "properties": {
    "iso:country":"ES",
    "sg:address":"Carr Sant Rafael, 30",
    "sg:city":"Xativa",
    "sg:orig_category":"Electricidad: Instaladores",
    "sg:phone":"+34 962 27 04 36",
    "sg:postcode":"46800",
    "sg:province":"Valencia",
    "wof:name":"Iexa Cb",
    "wof:placetype":"venue"
},
  "geometry": {"coordinates":[-0.5269330144,38.9865760803],"type":"Point"}
}