{
  "type": "Feature",
  "properties": {
    "addr:full":"Carrer de Bizet, 8 Rubi Barcelona 08191",
    "addr:housenumber":"8",
    "addr:postcode":"08191",
    "addr:street":"Carrer De Bizet",
    "iso:country":"ES",
    "sg:address":"Carrer de Bizet, 8",
    "sg:city":"Rubi",
    "sg:orig_category":"Laboratorios Farmac\u00c9uticos",
    "sg:phone":"+34 935 86 20 15",
    "sg:postcode":"08191",
    "sg:province":"Barcelona",
    "sg:website":"www.lainco.es",
    "wof:name":"Lainco S.a.",
    "wof:placetype":"venue"
},
  "geometry": {"coordinates":[2.0227560997,41.4717597961],"type":"Point"}
}