{
  "type": "Feature",
  "properties": {
    "iso:country":"ES",
    "sg:address":"Calle de Manuel Maestre, 16",
    "sg:city":"Elda",
    "sg:orig_category":"Notarios",
    "sg:phone":"+34 966 96 54 00",
    "sg:postcode":"03600",
    "sg:province":"Alicante",
    "wof:name":"Arviza Y Perez C.b.",
    "wof:placetype":"venue"
},
  "geometry": {"coordinates":[-0.7919731736,38.4785423279],"type":"Point"}
}