{
  "type": "Feature",
  "properties": {
    "iso:country":"ES",
    "sg:address":"Calle de Urano, 1",
    "sg:city":"Alcorcon",
    "sg:orig_category":"Quincaller\u00cda (al Por Menor)",
    "sg:phone":"+34 916 19 13 48",
    "sg:postcode":"28925",
    "sg:province":"Madrid",
    "wof:name":"Herrero Palomo Javier",
    "wof:placetype":"venue"
},
  "geometry": {"coordinates":[-3.8101348877,40.3537864685],"type":"Point"}
}