{
  "type": "Feature",
  "properties": {
    "iso:country":"ES",
    "sg:address":"Urb Calypso, S/n",
    "sg:city":"Mijas Costa",
    "sg:orig_category":"Molduras, Junquillos, Listones Y Molduras Perforadas",
    "sg:phone":"+34 952 93 13 75",
    "sg:postcode":"29649",
    "sg:province":"M\u00e1laga",
    "wof:name":"Gonzalez Martinez Gumersindo",
    "wof:placetype":"venue"
},
  "geometry": {"coordinates":[-4.6310629845,36.5238952637],"type":"Point"}
}