{
  "type": "Feature",
  "properties": {
    "addr:full":"Calle de Reval, 4 Caceres C\u00e1ceres 10001",
    "addr:housenumber":"4",
    "addr:postcode":"10001",
    "addr:street":"Calle De Reval;Ca\u0301Ceres",
    "iso:country":"ES",
    "sg:address":"Calle de Reval, 4",
    "sg:city":"Caceres",
    "sg:orig_category":"Asesor\u00cda Sobre Comunicaci\u00d3n De Empresas",
    "sg:phone":"+34 927 21 30 02",
    "sg:postcode":"10001",
    "sg:province":"C\u00e1ceres",
    "wof:name":"Aslafis S.l.",
    "wof:placetype":"venue"
},
  "geometry": {"coordinates":[-6.3806495667,39.4722213745],"type":"Point"}
}