{
  "type": "Feature",
  "properties": {
    "iso:country":"ES",
    "sg:address":"Calle de Dr Fleming (del), 14",
    "sg:city":"Coslada",
    "sg:orig_category":"Cl\u00cdnicas Dentales",
    "sg:phone":"+34 916 69 18 95",
    "sg:postcode":"28820",
    "sg:province":"Madrid",
    "sg:website":"www.vitaldent.com",
    "wof:name":"Vaguada Dental S.l.",
    "wof:placetype":"venue"
},
  "geometry": {"coordinates":[-3.5663840771,40.4236755371],"type":"Point"}
}