{
  "type": "Feature",
  "properties": {
    "addr:full":"El Paraiso, 4 Torremolinos M\u00e1laga 29620",
    "addr:housenumber":"4",
    "addr:postcode":"29620",
    "addr:street":"El Paraiso;Ma\u0301Laga",
    "iso:country":"ES",
    "sg:address":"El Paraiso, 4",
    "sg:city":"Torremolinos",
    "sg:orig_category":"Promotores Constructores",
    "sg:phone":"+34 952 38 33 86",
    "sg:postcode":"29620",
    "sg:province":"M\u00e1laga",
    "wof:name":"Canales De Mendoza Joaquin",
    "wof:placetype":"venue"
},
  "geometry": {"coordinates":[-4.5006718636,36.6380577087],"type":"Point"}
}