{
  "type": "Feature",
  "properties": {
    "iso:country":"ES",
    "sg:address":"Carrer de Esteve Terradas, S/n",
    "sg:city":"Manresa",
    "sg:orig_category":"Fibras De Vidrio",
    "sg:phone":"+34 938 74 59 05",
    "sg:postcode":"08243",
    "sg:province":"Barcelona",
    "wof:name":"Materials Aillants Tarrago S.a.",
    "wof:placetype":"venue"
},
  "geometry": {"coordinates":[1.8502459526,41.7129402161],"type":"Point"}
}