{
  "type": "Feature",
  "properties": {
    "iso:country":"ES",
    "sg:address":"Calle de Independencia (la), 25",
    "sg:city":"Segovia",
    "sg:orig_category":"Cerrajer\u00cda, Ferrallista",
    "sg:phone":"+34 921 43 38 08",
    "sg:postcode":"40002",
    "sg:province":"Segovia",
    "wof:name":"San Deogracias Alamo Maria Del Carmen",
    "wof:placetype":"venue"
},
  "geometry": {"coordinates":[-4.1168441772,40.9453163147],"type":"Point"}
}