{
  "type": "Feature",
  "properties": {
    "addr:full":"Calle de Caminos Cruzados, 15 Puerto Mazarron Murcia 30860",
    "addr:housenumber":"15",
    "addr:postcode":"30860",
    "addr:street":"Calle De Caminos Cruzados",
    "iso:country":"ES",
    "sg:address":"Calle de Caminos Cruzados, 15",
    "sg:city":"Puerto Mazarron",
    "sg:orig_category":"Asesor\u00cda Sobre Comunicaci\u00d3n De Empresas",
    "sg:phone":"+34 968 59 54 75",
    "sg:postcode":"30860",
    "sg:province":"Murcia",
    "wof:name":"Capitan Perez Josefa Maria",
    "wof:placetype":"venue"
},
  "geometry": {"coordinates":[-1.2582757473,37.571811676],"type":"Point"}
}