{
  "type": "Feature",
  "properties": {
    "addr:full":"Ctra Navalmorales, 36 Navahermosa Toledo 45150",
    "addr:housenumber":"36",
    "addr:postcode":"45150",
    "addr:street":"Ctra Navalmorales",
    "iso:country":"ES",
    "sg:address":"Ctra Navalmorales, 36",
    "sg:city":"Navahermosa",
    "sg:orig_category":"Comercio De Piezas De Recambio Y De Accesorios De Veh\u00cdculos, Veh\u00cdculos Industriales",
    "sg:phone":"+34 925 41 02 59",
    "sg:postcode":"45150",
    "sg:province":"Toledo",
    "wof:name":"Gonzalez Menor Jose Luis",
    "wof:placetype":"venue"
},
  "geometry": {"coordinates":[-4.4761991501,39.6348190308],"type":"Point"}
}