{
  "type": "Feature",
  "properties": {
    "iso:country":"ES",
    "sg:address":"Avda Segovia, 18",
    "sg:city":"Valladolid",
    "sg:orig_category":"Centro De Estudios",
    "sg:phone":"+34 983 22 39 17",
    "sg:postcode":"47013",
    "sg:province":"Valladolid",
    "wof:name":"Ginel Diez Maria Jesus",
    "wof:placetype":"venue"
},
  "geometry": {"coordinates":[-4.7210278511,41.6393241882],"type":"Point"}
}