{
  "type": "Feature",
  "properties": {
    "addr:full":"Via Tarpeya, S/n Poligono Sta M. De Benquerencia Toledo 45...",
    "addr:housenumber":"s / n;45 ...",
    "addr:street":"Via Tarpeya;Poligono Sta M. De Benquerencia Toledo",
    "iso:country":"ES",
    "sg:address":"Via Tarpeya, S/n",
    "sg:city":"Poligono Sta M. De Benquerencia",
    "sg:orig_category":"Suministros Y Materiales Industriales",
    "sg:phone":"+34 925 26 95 00",
    "sg:postcode":"45...",
    "sg:province":"Toledo",
    "wof:name":"Internacional De Composites S.a.",
    "wof:placetype":"venue"
},
  "geometry": {"coordinates":[-4.0251398087,39.861869812],"type":"Point"}
}