{
  "type": "Feature",
  "properties": {
    "addr:full":"Calle de Burgos, 20 Zaragoza Zaragoza 50005",
    "addr:housenumber":"20",
    "addr:postcode":"50005",
    "addr:street":"Calle De Burgos",
    "iso:country":"ES",
    "sg:address":"Calle de Burgos, 20",
    "sg:city":"Zaragoza",
    "sg:orig_category":"Empresas De Carpinter\u00cda De Madera",
    "sg:phone":"+34 976 55 79 41",
    "sg:postcode":"50005",
    "sg:province":"Zaragoza",
    "wof:name":"Trivi\u00f1o Trivi\u00f1o Juan Jose",
    "wof:placetype":"venue"
},
  "geometry": {"coordinates":[-0.8962410092,41.6473960876],"type":"Point"}
}