{
  "type": "Feature",
  "properties": {
    "addr:full":"Calle de Desafio, 14 Mota Cuervo Cuenca 16630",
    "addr:housenumber":"14",
    "addr:postcode":"16630",
    "addr:street":"Calle De Desafio",
    "iso:country":"ES",
    "sg:address":"Calle de Desafio, 14",
    "sg:city":"Mota Cuervo",
    "sg:orig_category":"Agentes Generales De Seguros",
    "sg:phone":"+34 967 18 01 20",
    "sg:postcode":"16630",
    "sg:province":"Cuenca",
    "wof:name":"Riquelme Alcolado Ismael",
    "wof:placetype":"venue"
},
  "geometry": {"coordinates":[-2.868185997,39.4988098145],"type":"Point"}
}