{
  "type": "Feature",
  "properties": {
    "iso:country":"ES",
    "sg:address":"Calle de B - Poligono Industrial De Asipo, 41",
    "sg:city":"Coru\u00d1o",
    "sg:orig_category":"Inform\u00c1tica Equipo Y Programas (al Por Mayor)",
    "sg:phone":"+34 985 98 06 26",
    "sg:postcode":"33428",
    "sg:province":"Asturias",
    "sg:website":"www.orios.net",
    "wof:name":"Orios S.l.",
    "wof:placetype":"venue"
},
  "geometry": {"coordinates":[-5.9832577705,43.2504386902],"type":"Point"}
}