{
  "type": "Feature",
  "properties": {
    "addr:full":"Calle de Barrio (el), 11 Nerja M\u00e1laga 29780",
    "addr:housenumber":"11",
    "addr:postcode":"29780",
    "addr:street":"Calle De Barrio El",
    "iso:country":"ES",
    "sg:address":"Calle de Barrio (el), 11",
    "sg:city":"Nerja",
    "sg:orig_category":"Radiocomunicaciones, Telefon\u00cda M\u00d3vil, Radiomensajer\u00cda: Servicios, Comercializaci\u00d3n",
    "sg:phone":"+34 952 96 61 19",
    "sg:postcode":"29780",
    "sg:province":"M\u00e1laga",
    "wof:name":"Alfredo Lucena S.l.",
    "wof:placetype":"venue"
},
  "geometry": {"coordinates":[-3.8780567646,36.7449378967],"type":"Point"}
}