{
  "type": "Feature",
  "properties": {
    "addr:full":"Avda Mejico, 8 Huelva Huelva 21001",
    "addr:housenumber":"8",
    "addr:postcode":"21001",
    "addr:street":"Avda Mejico",
    "iso:country":"ES",
    "sg:address":"Avda Mejico, 8",
    "sg:city":"Huelva",
    "sg:classifiers":[
        {
            "category":"Recreation",
            "type":"Entertainment"
        }
    ],
    "sg:phone":"+34 959 28 02 79",
    "sg:postcode":"21001",
    "sg:province":"Huelva",
    "sg:tags":[
        "caza",
        "pr\u00c1ctica",
        "la",
        "de",
        "pesca",
        "y"
    ],
    "wof:name":"Continental Pescamar S.l.",
    "wof:placetype":"venue"
},
  "geometry": {"coordinates":[-6.9495940208,37.256313324],"type":"Point"}
}