{
  "type": "Feature",
  "properties": {
    "iso:country":"ES",
    "sg:address":"Calle de Jara, 12",
    "sg:city":"Zafra",
    "sg:orig_category":"Carnicer\u00cdas, Carnicer\u00cdas",
    "sg:phone":"+34 924 55 22 09",
    "sg:postcode":"06300",
    "sg:province":"Badajoz",
    "wof:name":"Carrasco Sanchez Juan Jose",
    "wof:placetype":"venue"
},
  "geometry": {"coordinates":[-6.4166359901,38.4183235168],"type":"Point"}
}