{
  "type": "Feature",
  "properties": {
    "iso:country":"ES",
    "sg:address":"Carr Trinitat, 19",
    "sg:city":"Portol",
    "sg:orig_category":"Limpieza Y Vaciado De Fosas",
    "sg:phone":"+34 971 60 25 45",
    "sg:postcode":"07141",
    "sg:province":"Islas Baleares",
    "wof:name":"Vadell Crespi Miguel",
    "wof:placetype":"venue"
},
  "geometry": {"coordinates":[2.7445349693,39.6195487976],"type":"Point"}
}