{
  "type": "Feature",
  "properties": {
    "addr:full":"Avda Carlos Iii (de), 49 Cordoba C\u00f3rdoba 14014",
    "addr:housenumber":"49",
    "addr:postcode":"14014",
    "addr:street":"Avda Carlos Iii De;Co\u0301Rdoba",
    "iso:country":"ES",
    "sg:address":"Avda Carlos Iii (de), 49",
    "sg:city":"Cordoba",
    "sg:orig_category":"Cajas De Ahorro",
    "sg:phone":"+34 957 76 40 17",
    "sg:postcode":"14014",
    "sg:province":"C\u00f3rdoba",
    "sg:website":"www.elmonte.es",
    "wof:name":"Monte De Piedad Y Caja De Ahorros De Huelva Y Sevilla",
    "wof:placetype":"venue"
},
  "geometry": {"coordinates":[-4.7569890022,37.896697998],"type":"Point"}
}