{
  "type": "Feature",
  "properties": {
    "iso:country":"ES",
    "sg:address":"Barria Plaza, 8",
    "sg:city":"Eibar",
    "sg:orig_category":"Sociedades, Compa\u00d1\u00cdas Aseguradoras",
    "sg:phone":"+34 943 20 11 49",
    "sg:postcode":"20600",
    "sg:province":"Guip\u00f9zcoa",
    "wof:name":"Lejardi S.l.",
    "wof:placetype":"venue"
},
  "geometry": {"coordinates":[-2.470774889,43.1849822998],"type":"Point"}
}