{
  "type": "Feature",
  "properties": {
    "iso:country":"ES",
    "sg:address":"Calle de Isabel De Santo Domingo, 10",
    "sg:city":"Zaragoza",
    "sg:orig_category":"Suministros Y Materiales Industriales",
    "sg:phone":"+34 976 18 95 30",
    "sg:postcode":"50014",
    "sg:province":"Zaragoza",
    "wof:name":"Suministros Electricos Del Ebro S.l.",
    "wof:placetype":"venue"
},
  "geometry": {"coordinates":[-0.8537923098,41.6682357788],"type":"Point"}
}