{
  "type": "Feature",
  "properties": {
    "addr:full":"Carrer de Josep Prats, 44 Hospitalet Llobregat Barcelona 08901",
    "addr:housenumber":"44",
    "addr:postcode":"08901",
    "addr:street":"Carrer De Josep Prats",
    "iso:country":"ES",
    "sg:address":"Carrer de Josep Prats, 44",
    "sg:city":"Hospitalet Llobregat",
    "sg:orig_category":"Guarder\u00cdas",
    "sg:phone":"+34 933 37 93 28",
    "sg:postcode":"08901",
    "sg:province":"Barcelona",
    "wof:name":"Palacin Garcia Alicia",
    "wof:placetype":"venue"
},
  "geometry": {"coordinates":[2.0977129936,41.3583908081],"type":"Point"}
}