{
  "type": "Feature",
  "properties": {
    "addr:full":"Calle de Buensuceso, 52 Valdepe\u00f1as Ciudad Real 13300",
    "addr:housenumber":"52",
    "addr:postcode":"13300",
    "addr:street":"Calle De Buensuceso",
    "iso:country":"ES",
    "sg:address":"Calle de Buensuceso, 52",
    "sg:city":"Valdepe\u00f1as",
    "sg:orig_category":"Institutos De Belleza",
    "sg:phone":"+34 926 31 09 45",
    "sg:postcode":"13300",
    "sg:province":"Ciudad Real",
    "wof:name":"Padilla Huesca Carmen",
    "wof:placetype":"venue"
},
  "geometry": {"coordinates":[-3.3802080154,38.7663955688],"type":"Point"}
}