{
  "type": "Feature",
  "properties": {
    "addr:full":"Calle de Juan Anton, 28 Madrid Madrid 28011",
    "addr:housenumber":"28",
    "addr:postcode":"madrid;28011",
    "addr:street":"Calle De Juan Anton",
    "iso:country":"ES",
    "sg:address":"Calle de Juan Anton, 28",
    "sg:city":"Madrid",
    "sg:orig_category":"Inform\u00c1tica: Mantenimiento Y Reparaci\u00d3n De Ordenadores",
    "sg:phone":"+34 914 70 06 25",
    "sg:postcode":"28011",
    "sg:province":"Madrid",
    "wof:name":"Meridian Interiorismo Y Obras S.l.",
    "wof:placetype":"venue"
},
  "geometry": {"coordinates":[-3.7368440628,40.4096374512],"type":"Point"}
}