{
  "type": "Feature",
  "properties": {
    "addr:full":"Calle de Virgen Del Buen Suceso, 23 Cieza Murcia 30530",
    "addr:housenumber":"23",
    "addr:postcode":"30530",
    "addr:street":"Calle De Virgen Del Buen Suceso",
    "iso:country":"ES",
    "sg:address":"Calle de Virgen Del Buen Suceso, 23",
    "sg:city":"Cieza",
    "sg:orig_category":"Art\u00cdculos De Regalo (al Por Menor)",
    "sg:phone":"+34 968 76 14 96",
    "sg:postcode":"30530",
    "sg:province":"Murcia",
    "wof:name":"Alarcon Del Amor Francisco",
    "wof:placetype":"venue"
},
  "geometry": {"coordinates":[-1.4821481705,38.2650794983],"type":"Point"}
}