{
  "type": "Feature",
  "properties": {
    "iso:country":"ES",
    "sg:address":"Ctra Los Alcazares, S/n",
    "sg:city":"Los Urrutias",
    "sg:orig_category":"Obras Y Organismos Sociales",
    "sg:phone":"+34 968 13 46 70",
    "sg:postcode":"30368",
    "sg:province":"Murcia",
    "wof:name":"Obra Social Femenina Ntra. Sra. De La Fuensanta",
    "wof:placetype":"venue"
},
  "geometry": {"coordinates":[-0.8297989964,37.6807098389],"type":"Point"}
}