{
  "type": "Feature",
  "properties": {
    "addr:full":"Calle de Blas De Otero, 21 Vitoria-gasteiz \u00c1lava 01010",
    "addr:housenumber":"21",
    "addr:postcode":"01010",
    "addr:street":"Calle De Blas De Otero",
    "iso:country":"ES",
    "sg:address":"Calle de Blas De Otero, 21",
    "sg:city":"Vitoria-gasteiz",
    "sg:orig_category":"Lencer\u00cda Femenina, Corseter\u00cda, Trajes De Ba\u00d1o (al Por Menor)",
    "sg:phone":"+34 945 17 96 52",
    "sg:postcode":"01010",
    "sg:province":"\u00c1lava",
    "wof:name":"Complementos Lakua, S.c.",
    "wof:placetype":"venue"
},
  "geometry": {"coordinates":[-2.6893999577,42.8621902466],"type":"Point"}
}