{
  "type": "Feature",
  "properties": {
    "addr:full":"Carrer de Ramon I Cajal, 19 Cornella Llobregat Barcelona 08940",
    "addr:housenumber":"19",
    "addr:postcode":"08940",
    "addr:street":"Carrer De Ramon I Cajal",
    "iso:country":"ES",
    "sg:address":"Carrer de Ramon I Cajal, 19",
    "sg:city":"Cornella Llobregat",
    "sg:orig_category":"Chapister\u00cda",
    "sg:phone":"+34 934 74 41 04",
    "sg:postcode":"08940",
    "sg:province":"Barcelona",
    "wof:name":"Roman Lopez Antonio",
    "wof:placetype":"venue"
},
  "geometry": {"coordinates":[2.071778059,41.352180481],"type":"Point"}
}