{
  "type": "Feature",
  "properties": {
    "addr:full":"Pl. Iglesia, 14 Palas Murcia 30334",
    "addr:housenumber":"14",
    "addr:postcode":"30334",
    "addr:street":"Pl. Iglesia",
    "iso:country":"ES",
    "sg:address":"Pl. Iglesia, 14",
    "sg:city":"Palas",
    "sg:orig_category":"Iglesia Cat\u00d3lica",
    "sg:phone":"+34 968 15 93 54",
    "sg:postcode":"30334",
    "sg:province":"Murcia",
    "wof:name":"Obispado De Cartagena",
    "wof:placetype":"venue"
},
  "geometry": {"coordinates":[-1.1903049946,37.6626396179],"type":"Point"}
}