{
  "type": "Feature",
  "properties": {
    "addr:full":"Plaz Fueros (los), 11 Alsasua Navarra 31800",
    "addr:housenumber":"11",
    "addr:postcode":"31800",
    "addr:street":"Plaz Fueros Los",
    "iso:country":"ES",
    "sg:address":"Plaz Fueros (los), 11",
    "sg:city":"Alsasua",
    "sg:orig_category":"Molduras, Junquillos, Listones Y Molduras Perforadas",
    "sg:phone":"+34 948 46 71 74",
    "sg:postcode":"31800",
    "sg:province":"Navarra",
    "wof:name":"Aldasoro Ramirez De Alda Angel",
    "wof:placetype":"venue"
},
  "geometry": {"coordinates":[-2.1676270962,42.8951644897],"type":"Point"}
}