{
  "type": "Feature",
  "properties": {
    "iso:country":"ES",
    "sg:address":"Calle de Saenz Diez, 19",
    "sg:city":"Ourense",
    "sg:orig_category":"Contenedores (mercanc\u00cdas)",
    "sg:phone":"+34 988 37 19 14",
    "sg:postcode":"32003",
    "sg:province":"Ourense",
    "wof:name":"Alvarez Rodriguez Eduardo",
    "wof:placetype":"venue"
},
  "geometry": {"coordinates":[-7.865439415,42.343837738],"type":"Point"}
}