{
  "type": "Feature",
  "properties": {
    "addr:full":"Cmno Carretil, 4 Logro\u00f1o La Rioja 26006",
    "addr:housenumber":"4",
    "addr:postcode":"26006",
    "addr:street":"Cmno Carretil;Rioja",
    "iso:country":"ES",
    "sg:address":"Cmno Carretil, 4",
    "sg:city":"Logro\u00f1o",
    "sg:orig_category":"Delegados, Agentes De Tr\u00c1nsito, Auxiliares De Transporte Internacional",
    "sg:phone":"+34 941 51 06 83",
    "sg:postcode":"26006",
    "sg:province":"La Rioja",
    "wof:name":"Asda Fashion S.l.",
    "wof:placetype":"venue"
},
  "geometry": {"coordinates":[-2.468130827,42.464012146],"type":"Point"}
}