{
  "type": "Feature",
  "properties": {
    "addr:full":"Acso Muelle, S/n Los Cristianos Santa Cruz De Tenerife 38650",
    "addr:housenumber":"/ n",
    "addr:postcode":"38650",
    "addr:street":"Muelle S",
    "iso:country":"ES",
    "sg:address":"Acso Muelle, S/n",
    "sg:city":"Los Cristianos",
    "sg:classifiers":[
        {
            "category":"Taxi",
            "type":"Transportation"
        }
    ],
    "sg:phone":"+34 922 79 05 53",
    "sg:postcode":"38650",
    "sg:province":"Santa Cruz De Tenerife",
    "wof:name":"Asociacion De Radio-taxis Del Municipio De Arona",
    "wof:placetype":"venue"
},
  "geometry": {"coordinates":[-16.7173233032,28.0504455566],"type":"Point"}
}