{
  "type": "Feature",
  "properties": {
    "iso:country":"ES",
    "sg:address":"Calle de Maria Sevilla Diago, 26",
    "sg:city":"Madrid",
    "sg:orig_category":"\u00d3ptica: Instrumentos (fabricaci\u00d3n)",
    "sg:phone":"+34 917 60 09 69",
    "sg:postcode":"28022",
    "sg:province":"Madrid",
    "wof:name":"Optitek 2000 S.l.l.",
    "wof:placetype":"venue"
},
  "geometry": {"coordinates":[-3.6071178913,40.4331321716],"type":"Point"}
}