{
  "type": "Feature",
  "properties": {
    "addr:full":"Calle de General Barroso, 60 Valencia Valencia 46017",
    "addr:housenumber":"60",
    "addr:postcode":"46017",
    "addr:street":"Calle De General Barroso",
    "iso:country":"ES",
    "sg:address":"Calle de General Barroso, 60",
    "sg:city":"Valencia",
    "sg:orig_category":"Asesor\u00cda De Formaci\u00d3n Y Gesti\u00d3n De Personal",
    "sg:phone":"+34 963 57 35 12",
    "sg:postcode":"46017",
    "sg:province":"Valencia",
    "wof:name":"Labisma Asesores S.l.",
    "wof:placetype":"venue"
},
  "geometry": {"coordinates":[-0.3919649124,39.4509849548],"type":"Point"}
}