{
  "type": "Feature",
  "properties": {
    "iso:country":"ES",
    "sg:address":"Calle de Cruz Del Postigo, 8",
    "sg:city":"Iznajar",
    "sg:orig_category":"Molduras, Junquillos, Listones Y Molduras Perforadas",
    "sg:phone":"+34 957 53 44 34",
    "sg:postcode":"14970",
    "sg:province":"C\u00f3rdoba",
    "wof:name":"Campa\u00f1a Hinojosa Antonio",
    "wof:placetype":"venue"
},
  "geometry": {"coordinates":[-4.309276104,37.2564735413],"type":"Point"}
}