{
  "type": "Feature",
  "properties": {
    "iso:country":"ES",
    "sg:address":"Calle de Juan De La Cierva, S/n",
    "sg:city":"Fuente Librilla",
    "sg:orig_category":"Alimentaci\u00d3n General (al Por Mayor)",
    "sg:phone":"+34 968 66 93 84",
    "sg:postcode":"30178",
    "sg:province":"Murcia",
    "wof:name":"Pagan Huertas Jose",
    "wof:placetype":"venue"
},
  "geometry": {"coordinates":[-1.4120789766,37.9197006226],"type":"Point"}
}