{
  "type": "Feature",
  "properties": {
    "addr:full":"Calle de Duque, 52 Jumilla Murcia 30520",
    "addr:housenumber":"52",
    "addr:postcode":"30520",
    "addr:street":"Calle De Duque",
    "iso:country":"ES",
    "sg:address":"Calle de Duque, 52",
    "sg:city":"Jumilla",
    "sg:orig_category":"Electricidad: Instaladores",
    "sg:phone":"+34 968 78 33 20",
    "sg:postcode":"30520",
    "sg:province":"Murcia",
    "wof:name":"Electricas Los Antonios S.l.",
    "wof:placetype":"venue"
},
  "geometry": {"coordinates":[-1.3224852085,38.4793205261],"type":"Point"}
}