{
  "type": "Feature",
  "properties": {
    "iso:country":"ES",
    "sg:address":"Calle de Benchijigua, 6",
    "sg:city":"San Isidro",
    "sg:orig_category":"M\u00c9dicos: Pediatr\u00cda. Enfermedades De Los Ni\u00d1os",
    "sg:phone":"+34 922 39 02 00",
    "sg:postcode":"38611",
    "sg:province":"Santa Cruz De Tenerife",
    "wof:name":"Mustapha  Chaoky",
    "wof:placetype":"venue"
},
  "geometry": {"coordinates":[-16.3083095551,28.4246902466],"type":"Point"}
}