{
  "type": "Feature",
  "properties": {
    "addr:full":"Calle de San Juan Bosco, 65 Almeria Almer\u00eda 04005",
    "addr:housenumber":"65",
    "addr:postcode":"04005",
    "addr:street":"Calle De San Juan Bosco",
    "iso:country":"ES",
    "sg:address":"Calle de San Juan Bosco, 65",
    "sg:city":"Almeria",
    "sg:orig_category":"Veh\u00cdculos De Ocasi\u00d3n",
    "sg:phone":"+34 950 25 02 55",
    "sg:postcode":"04005",
    "sg:province":"Almer\u00eda",
    "wof:name":"Garcia Lazaro Francisco Ramon",
    "wof:placetype":"venue"
},
  "geometry": {"coordinates":[-2.4544789791,36.8426704407],"type":"Point"}
}