{
  "type": "Feature",
  "properties": {
    "iso:country":"ES",
    "sg:address":"Calle de Mancha Real, 17",
    "sg:city":"Jaen",
    "sg:orig_category":"Electricidad: Equipos Industriales, Componentes (fabricaci\u00d3n)",
    "sg:phone":"+34 953 28 00 77",
    "sg:postcode":"23009",
    "sg:province":"Ja\u00e9n",
    "sg:website":"www.electro-stocks.com",
    "wof:name":"Electro-stocks Jaen S.l.",
    "wof:placetype":"venue"
},
  "geometry": {"coordinates":[-3.7806329727,37.8008117676],"type":"Point"}
}