{
  "type": "Feature",
  "properties": {
    "iso:country":"ES",
    "sg:address":"Calle de Burgos, 9",
    "sg:city":"Aspe",
    "sg:orig_category":"Abogados",
    "sg:phone":"+34 965 49 00 91",
    "sg:postcode":"03680",
    "sg:province":"Alicante",
    "wof:name":"Machado Bravo Antonio",
    "wof:placetype":"venue"
},
  "geometry": {"coordinates":[-0.7635071874,38.3414344788],"type":"Point"}
}