{
  "type": "Feature",
  "properties": {
    "addr:full":"Carrer de Baix Penedes, 27 Calafell Tarragona 43820",
    "addr:housenumber":"27",
    "addr:postcode":"43820",
    "addr:street":"Carrer De Baix Penedes",
    "iso:country":"ES",
    "sg:address":"Carrer de Baix Penedes, 27",
    "sg:city":"Calafell",
    "sg:orig_category":"Barnizadores",
    "sg:phone":"+34 977 69 48 12",
    "sg:postcode":"43820",
    "sg:province":"Tarragona",
    "wof:name":"Rion Colet Josep",
    "wof:placetype":"venue"
},
  "geometry": {"coordinates":[1.5666110516,41.2019767761],"type":"Point"}
}