{
  "type": "Feature",
  "properties": {
    "addr:full":"Calle de Zenit, 3 Madrid Madrid 28023",
    "addr:housenumber":"3",
    "addr:postcode":"28023",
    "addr:street":"Calle De Zenit",
    "iso:country":"ES",
    "sg:address":"Calle de Zenit, 3",
    "sg:city":"Madrid",
    "sg:orig_category":"Promotores Constructores",
    "sg:phone":"+34 913 57 43 57",
    "sg:postcode":"28023",
    "sg:province":"Madrid",
    "wof:name":"Luarosa S.l.",
    "wof:placetype":"venue"
},
  "geometry": {"coordinates":[-3.7918400764,40.4639167786],"type":"Point"}
}