{
  "type": "Feature",
  "properties": {
    "iso:country":"ES",
    "sg:address":"Calle de Mar Egeo, 7",
    "sg:city":"Alcala Guadaira",
    "sg:orig_category":"Puertas De Acorde\u00d3n Y Flexibles",
    "sg:phone":"+34 955 61 22 19",
    "sg:postcode":"41500",
    "sg:province":"Sevilla",
    "wof:name":"Sistema Integral De Mamparas S.l.",
    "wof:placetype":"venue"
},
  "geometry": {"coordinates":[-5.8488931656,37.3468933105],"type":"Point"}
}