{
  "type": "Feature",
  "properties": {
    "addr:full":"Calle de Ntra Sra De Gracia, 6 Marbella M\u00e1laga 29600",
    "addr:housenumber":"6",
    "addr:postcode":"29600",
    "addr:street":"Calle De Ntra Sra De Gracia;Ma\u0301Laga",
    "iso:country":"ES",
    "sg:address":"Calle de Ntra Sra De Gracia, 6",
    "sg:city":"Marbella",
    "sg:orig_category":"Art\u00cdculos De Regalo (al Por Menor)",
    "sg:phone":"+34 952 77 00 95",
    "sg:postcode":"29600",
    "sg:province":"M\u00e1laga",
    "wof:name":"Mohamed Mohamed Nur-said",
    "wof:placetype":"venue"
},
  "geometry": {"coordinates":[-4.8908510208,36.5089111328],"type":"Point"}
}