{
  "type": "Feature",
  "properties": {
    "iso:country":"ES",
    "sg:address":"Calle de Hermanos Aguilar Sanchez, 5",
    "sg:city":"Arrecife",
    "sg:orig_category":"Transportes Internacionales",
    "sg:phone":"+34 928 84 42 16",
    "sg:postcode":"35500",
    "sg:province":"Las Palmas",
    "wof:name":"Agencia Canteras S.l.",
    "wof:placetype":"venue"
},
  "geometry": {"coordinates":[-13.5329809189,28.9740371704],"type":"Point"}
}