{
  "type": "Feature",
  "properties": {
    "iso:country":"ES",
    "sg:address":"Huelva, 14",
    "sg:city":"Cornella Llobregat",
    "sg:orig_category":"Comercio De Mobiliario De Oficina",
    "sg:phone":"+34 934 74 50 42",
    "sg:postcode":"08940",
    "sg:province":"Barcelona",
    "sg:website":"www.ofimatic.org",
    "wof:name":"Ofimatic S.a.",
    "wof:placetype":"venue"
},
  "geometry": {"coordinates":[2.0668809414,41.3628311157],"type":"Point"}
}