{
  "type": "Feature",
  "properties": {
    "iso:country":"ES",
    "sg:address":"Calle de Prado, 9",
    "sg:city":"Navahermosa",
    "sg:orig_category":"Asistencia Social",
    "sg:phone":"+34 925 41 03 10",
    "sg:postcode":"45150",
    "sg:province":"Toledo",
    "wof:name":"Servicio Social De Asistencia A Pensionistas-hogar",
    "wof:placetype":"venue"
},
  "geometry": {"coordinates":[-4.4681048393,39.6371917725],"type":"Point"}
}