{
  "type": "Feature",
  "properties": {
    "addr:full":"Carr Doctor Simarro, 2 Xativa Valencia 46800",
    "addr:housenumber":"2",
    "addr:postcode":"46800",
    "addr:street":"Carr Doctor Simarro",
    "iso:country":"ES",
    "sg:address":"Carr Doctor Simarro, 2",
    "sg:city":"Xativa",
    "sg:orig_category":"Impuestos, Tesoro P\u00dablico",
    "sg:phone":"+34 962 28 07 54",
    "sg:postcode":"46800",
    "sg:province":"Valencia",
    "wof:name":"Tecnival S.c.v.",
    "wof:placetype":"venue"
},
  "geometry": {"coordinates":[-0.5293149948,38.987197876],"type":"Point"}
}