{
  "type": "Feature",
  "properties": {
    "iso:country":"ES",
    "sg:address":"Poli Rubira Sola, S/n",
    "sg:city":"Macael",
    "sg:orig_category":"Organizaciones Profesionales",
    "sg:phone":"+34 950 12 63 68",
    "sg:postcode":"04867",
    "sg:province":"Almer\u00eda",
    "wof:name":"Garciamar Artesanos S.c.a.",
    "wof:placetype":"venue"
},
  "geometry": {"coordinates":[-2.3024399281,37.3340568542],"type":"Point"}
}