{
  "type": "Feature",
  "properties": {
    "addr:full":"Carrer de Ferran Puig, 17 Prat Llobregat Barcelona 08820",
    "addr:housenumber":"17",
    "addr:postcode":"08820",
    "addr:street":"Carrer De Ferran Puig;Llobregat",
    "iso:country":"ES",
    "sg:address":"Carrer de Ferran Puig, 17",
    "sg:city":"Prat Llobregat",
    "sg:orig_category":"Institutos De Belleza",
    "sg:phone":"+34 934 78 01 41",
    "sg:postcode":"08820",
    "sg:province":"Barcelona",
    "wof:name":"Gonzalez Ramon Bego\u00f1a Asuncion",
    "wof:placetype":"venue"
},
  "geometry": {"coordinates":[2.0864720345,41.3289909363],"type":"Point"}
}