{
  "type": "Feature",
  "properties": {
    "iso:country":"ES",
    "sg:address":"Plaz Navarro Rodrigo, 15",
    "sg:city":"Alacant",
    "sg:classifiers":[
        {
            "category":"Autos & Motor Vehicles",
            "subcategory":"Automobile Sales",
            "type":"Retail Goods"
        }
    ],
    "sg:phone":"+34 965 92 99 19",
    "sg:postcode":"03007",
    "sg:province":"Alicante",
    "wof:name":"Saboan S. L.",
    "wof:placetype":"venue"
},
  "geometry": {"coordinates":[-0.4985980093,38.3411064148],"type":"Point"}
}