{
  "type": "Feature",
  "properties": {
    "iso:country":"ES",
    "sg:address":"Calle de Enrique Bernal Capel, 98",
    "sg:city":"Molina Segura",
    "sg:orig_category":"Agencias De Trabajo Temporal",
    "sg:phone":"+34 968 64 59 64",
    "sg:postcode":"30500",
    "sg:province":"Murcia",
    "wof:name":"Murtratem S.l.",
    "wof:placetype":"venue"
},
  "geometry": {"coordinates":[-1.2119740248,38.0535736084],"type":"Point"}
}