{
  "type": "Feature",
  "properties": {
    "iso:country":"ES",
    "sg:address":"Calle de Axular, 17",
    "sg:city":"Arizgoiti",
    "sg:orig_category":"Empresas De Carpinter\u00cda Met\u00c1lica",
    "sg:phone":"+34 944 40 49 18",
    "sg:postcode":"48970",
    "sg:province":"Vizcaya",
    "wof:name":"Garcia Exposito Dionisio",
    "wof:placetype":"venue"
},
  "geometry": {"coordinates":[-2.8928117752,43.2365951538],"type":"Point"}
}