{
  "type": "Feature",
  "properties": {
    "addr:full":"Frente Estacion, S/n Massalfassar Valencia 46560",
    "addr:postcode":"46560",
    "addr:street":"Estacion S / N",
    "iso:country":"ES",
    "sg:address":"Frente Estacion, S/n",
    "sg:city":"Massalfassar",
    "sg:orig_category":"Metacrilato: Art\u00cdculos (fabricaci\u00d3n Y Al Por Mayor)",
    "sg:phone":"+34 961 41 70 30",
    "sg:postcode":"46560",
    "sg:province":"Valencia",
    "wof:name":"Plexi S.l.",
    "wof:placetype":"venue"
},
  "geometry": {"coordinates":[-0.308735013,39.5518989563],"type":"Point"}
}