{
  "type": "Feature",
  "properties": {
    "addr:full":"J. Pelota, S/n Vitigudino Salamanca 37210",
    "addr:housenumber":"/ n",
    "addr:postcode":"37210",
    "addr:street":"J.;S",
    "iso:country":"ES",
    "sg:address":"J. Pelota, S/n",
    "sg:city":"Vitigudino",
    "sg:orig_category":"Mec\u00c1nico Del Autom\u00d3vil",
    "sg:phone":"+34 923 50 01 01",
    "sg:postcode":"37210",
    "sg:province":"Salamanca",
    "wof:name":"Talleres Y Gruas Millan S.l.",
    "wof:placetype":"venue"
},
  "geometry": {"coordinates":[-6.4345188141,41.0128593445],"type":"Point"}
}