{
  "type": "Feature",
  "properties": {
    "iso:country":"ES",
    "sg:address":"Calle de Hernan Cortes, 72",
    "sg:city":"Villanueva Serena",
    "sg:orig_category":"Negocio De Materiales De Construcci\u00d3n",
    "sg:phone":"+34 924 84 32 93",
    "sg:postcode":"06700",
    "sg:province":"Badajoz",
    "sg:website":"www.almacenesnieto.es",
    "wof:name":"Almacenes Nieto S. L.",
    "wof:placetype":"venue"
},
  "geometry": {"coordinates":[-5.7928318977,38.9733390808],"type":"Point"}
}