{
  "type": "Feature",
  "properties": {
    "iso:country":"ES",
    "sg:address":"Calle de Reyes (los), 21",
    "sg:city":"Estepona",
    "sg:orig_category":"Herboristas (al Por Menor)",
    "sg:phone":"+34 952 79 63 07",
    "sg:postcode":"29680",
    "sg:province":"M\u00e1laga",
    "wof:name":"Herboristeria Amapola S.l.",
    "wof:placetype":"venue"
},
  "geometry": {"coordinates":[-5.1449508667,36.4265899658],"type":"Point"}
}