{
  "type": "Feature",
  "properties": {
    "iso:country":"ES",
    "sg:address":"Calle de Loreto, 10",
    "sg:city":"Alcora",
    "sg:orig_category":"Ropa Para Se\u00d1oras (al Por Menor)",
    "sg:phone":"+34 964 36 19 50",
    "sg:postcode":"12110",
    "sg:province":"Castell\u00f3n",
    "wof:name":"Badenes Martin Nieves",
    "wof:placetype":"venue"
},
  "geometry": {"coordinates":[-0.2137887031,40.0764350891],"type":"Point"}
}