{
  "type": "Feature",
  "properties": {
    "iso:country":"ES",
    "sg:address":"Carrer de Sant Joan, 55",
    "sg:city":"Calella",
    "sg:orig_category":"Estancos",
    "sg:phone":"+34 937 69 02 59",
    "sg:postcode":"08370",
    "sg:province":"Barcelona",
    "wof:name":"Torne Palomares Jacinto",
    "wof:placetype":"venue"
},
  "geometry": {"coordinates":[2.6612679958,41.6148223877],"type":"Point"}
}