{
  "type": "Feature",
  "properties": {
    "iso:country":"ES",
    "sg:address":"Carrer de Esquirols, 11",
    "sg:city":"Fonts",
    "sg:orig_category":"Animales: Material Y Suministros Para (fabricaci\u00d3n, Al Por Mayor)",
    "sg:phone":"+34 937 31 31 38",
    "sg:postcode":"08228",
    "sg:province":"Barcelona",
    "wof:name":"Navalon Morales Miguel",
    "wof:placetype":"venue"
},
  "geometry": {"coordinates":[2.0415201187,41.5268516541],"type":"Point"}
}