{
  "type": "Feature",
  "properties": {
    "iso:country":"ES",
    "sg:address":"Calle de Alfonso Xii, 6",
    "sg:city":"Madrid",
    "sg:orig_category":"Restaurantes",
    "sg:phone":"+34 915 32 35 96",
    "sg:postcode":"28014",
    "sg:province":"Madrid",
    "wof:name":"Horcher Weber Gustavo",
    "wof:placetype":"venue"
},
  "geometry": {"coordinates":[-3.6889207363,40.4187011719],"type":"Point"}
}