{
  "type": "Feature",
  "properties": {
    "iso:country":"ES",
    "sg:address":"Calle de Sevilla, 33",
    "sg:city":"Fuengirola",
    "sg:orig_category":"Abogados",
    "sg:phone":"+34 952 58 60 71",
    "sg:postcode":"29640",
    "sg:province":"M\u00e1laga",
    "wof:name":"Quintana Puerto M.remedios",
    "wof:placetype":"venue"
},
  "geometry": {"coordinates":[-4.6290230751,36.5407295227],"type":"Point"}
}