{
  "type": "Feature",
  "properties": {
    "addr:full":"Calle de Batalla Del Salado, 7 Tarifa C\u00e1diz 11380",
    "addr:housenumber":"7",
    "addr:postcode":"11380",
    "addr:street":"Calle De Batalla Del Salado;Ca\u0301Diz",
    "iso:country":"ES",
    "sg:address":"Calle de Batalla Del Salado, 7",
    "sg:city":"Tarifa",
    "sg:orig_category":"Bisuter\u00cda, Joyer\u00cda, Relojer\u00cda (al Por Menor)",
    "sg:phone":"+34 956 68 25 59",
    "sg:postcode":"11380",
    "sg:province":"C\u00e1diz",
    "wof:name":"Joyeria Gaspar S.c.",
    "wof:placetype":"venue"
},
  "geometry": {"coordinates":[-5.6046881676,36.0143890381],"type":"Point"}
}