{
  "type": "Feature",
  "properties": {
    "addr:full":"Calle de Rios Rosas, 95 Albacete Albacete 02004",
    "addr:housenumber":"95",
    "addr:postcode":"02004",
    "addr:street":"Calle De Rios Rosas",
    "iso:country":"ES",
    "sg:address":"Calle de Rios Rosas, 95",
    "sg:city":"Albacete",
    "sg:orig_category":"Electrodom\u00c9sticos (al Por Menor)",
    "sg:phone":"+34 967 22 04 88",
    "sg:postcode":"02004",
    "sg:province":"Albacete",
    "wof:name":"Garcia Blazquez Francisco",
    "wof:placetype":"venue"
},
  "geometry": {"coordinates":[-1.8654589653,38.9885101318],"type":"Point"}
}