{
  "type": "Feature",
  "properties": {
    "addr:full":"Trva Marraco, 53 Hecho Huesca 22720",
    "addr:housenumber":"53",
    "addr:postcode":"22720",
    "addr:street":"Trva Marraco",
    "iso:country":"ES",
    "sg:address":"Trva Marraco, 53",
    "sg:city":"Hecho",
    "sg:orig_category":"Frutas, Legumbres Frescas Y Tempranas (al Por Menor)",
    "sg:phone":"+34 974 37 52 74",
    "sg:postcode":"22720",
    "sg:province":"Huesca",
    "wof:name":"Arbones Gari Jose Maria",
    "wof:placetype":"venue"
},
  "geometry": {"coordinates":[-0.7494964004,42.7387199402],"type":"Point"}
}