{
  "type": "Feature",
  "properties": {
    "iso:country":"ES",
    "sg:address":"Calle de Zaragoza, 17",
    "sg:city":"Palmas De Gran Canaria",
    "sg:orig_category":"Estilistas Y Estudios De Estilo De Corte Y Confecci\u00d3n",
    "sg:phone":"+34 928 25 67 96",
    "sg:postcode":"35012",
    "sg:province":"Las Palmas",
    "wof:name":"Perez Rodriguez Onofre",
    "wof:placetype":"venue"
},
  "geometry": {"coordinates":[-15.4323921204,28.1105442047],"type":"Point"}
}