{
  "type": "Feature",
  "properties": {
    "addr:full":"Calle de Almonte, 2 Huelva Huelva 21007",
    "addr:housenumber":"2",
    "addr:postcode":"21007",
    "addr:street":"Calle De Almonte",
    "iso:country":"ES",
    "sg:address":"Calle de Almonte, 2",
    "sg:city":"Huelva",
    "sg:orig_category":"Fabricaci\u00d3n De Material Y Sistemas De Se\u00d1alizaci\u00d3n De Carreteras, Urbanos Y De Obras",
    "sg:phone":"+34 959 27 13 04",
    "sg:postcode":"21007",
    "sg:province":"Huelva",
    "wof:name":"Moron Macias Cristobal",
    "wof:placetype":"venue"
},
  "geometry": {"coordinates":[-6.9314007759,37.2587928772],"type":"Point"}
}