{
  "type": "Feature",
  "properties": {
    "addr:full":"Tarabelo, 98 Tarabelo La Coru\u00f1a 15160",
    "addr:housenumber":"98",
    "addr:postcode":"15160",
    "addr:street":"Tarabelo;Tarabelo La Corun\u0303A",
    "iso:country":"ES",
    "sg:address":"Tarabelo, 98",
    "sg:city":"Tarabelo",
    "sg:orig_category":"Mec\u00c1nico Del Autom\u00d3vil",
    "sg:phone":"+34 981 62 14 75",
    "sg:postcode":"15160",
    "sg:province":"La Coru\u00f1a",
    "wof:name":"Dominsada S.l.",
    "wof:placetype":"venue"
},
  "geometry": {"coordinates":[-8.2548141479,43.3510665894],"type":"Point"}
}