{
  "type": "Feature",
  "properties": {
    "iso:country":"ES",
    "sg:address":"Calle de Escuelas Pias, S/n",
    "sg:city":"Albelda Iregua",
    "sg:orig_category":"Cooperativas Agr\u00cdcolas",
    "sg:phone":"+34 941 44 37 43",
    "sg:postcode":"26120",
    "sg:province":"La Rioja",
    "wof:name":"Sociedad Cooperativa De Albelda Responsabilidad Limitada",
    "wof:placetype":"venue"
},
  "geometry": {"coordinates":[-2.4752049446,42.3598747253],"type":"Point"}
}