{
  "type": "Feature",
  "properties": {
    "iso:country":"ES",
    "sg:address":"Calle de Malaga, 21",
    "sg:city":"Valencia",
    "sg:orig_category":"Plomeros",
    "sg:phone":"+34 963 48 78 98",
    "sg:postcode":"46009",
    "sg:province":"Valencia",
    "wof:name":"Empresa Valenciana De Servicios S.l.",
    "wof:placetype":"venue"
},
  "geometry": {"coordinates":[-0.3813009858,39.4848442078],"type":"Point"}
}