{
  "type": "Feature",
  "properties": {
    "addr:full":"Calle de Real, 103 Yuncos Toledo 45210",
    "addr:housenumber":"103",
    "addr:postcode":"45210",
    "addr:street":"Calle De Real",
    "iso:country":"ES",
    "sg:address":"Calle de Real, 103",
    "sg:city":"Yuncos",
    "sg:orig_category":"Poller\u00cda Y Caza (al Por Menor)",
    "sg:phone":"+34 925 55 31 43",
    "sg:postcode":"45210",
    "sg:province":"Toledo",
    "wof:name":"Martin Gonzalez Francisco",
    "wof:placetype":"venue"
},
  "geometry": {"coordinates":[-3.8733189106,40.0875511169],"type":"Point"}
}