{
  "type": "Feature",
  "properties": {
    "iso:country":"ES",
    "sg:address":"Calle de Galan, 6",
    "sg:city":"Membrilla",
    "sg:orig_category":"Bisuter\u00cda, Joyer\u00cda, Relojer\u00cda (al Por Menor)",
    "sg:phone":"+34 926 63 64 74",
    "sg:postcode":"13230",
    "sg:province":"Ciudad Real",
    "wof:name":"Martin Fernandez Antonio",
    "wof:placetype":"venue"
},
  "geometry": {"coordinates":[-3.3450040817,38.9727897644],"type":"Point"}
}