{
  "type": "Feature",
  "properties": {
    "addr:full":"Calle de Zezilia Gallartzagoitia, 15 Amorebieta Vizcaya 48340",
    "addr:housenumber":"15",
    "addr:postcode":"48340",
    "addr:street":"Calle De Zezilia Gallartzagoitia",
    "iso:country":"ES",
    "sg:address":"Calle de Zezilia Gallartzagoitia, 15",
    "sg:city":"Amorebieta",
    "sg:orig_category":"T\u00c9cnicos Veterinarios",
    "sg:phone":"+34 946 73 16 76",
    "sg:postcode":"48340",
    "sg:province":"Vizcaya",
    "wof:name":"Barrenetxea Ziarrusta Jon Ander",
    "wof:placetype":"venue"
},
  "geometry": {"coordinates":[-2.7331829071,43.2194366455],"type":"Point"}
}