{
  "type": "Feature",
  "properties": {
    "addr:full":"Alam Cervantes (de), 12 San Mateo Murcia 30800",
    "addr:housenumber":"12",
    "addr:postcode":"30800",
    "addr:street":"Alam Cervantes De",
    "iso:country":"ES",
    "sg:address":"Alam Cervantes (de), 12",
    "sg:city":"San Mateo",
    "sg:orig_category":"Obras Y Organismos Sociales",
    "sg:phone":"+34 968 47 17 80",
    "sg:postcode":"30800",
    "sg:province":"Murcia",
    "wof:name":"Asociacion Alzheimer Lorca",
    "wof:placetype":"venue"
},
  "geometry": {"coordinates":[-1.1298867464,37.9834747314],"type":"Point"}
}