{
  "type": "Feature",
  "properties": {
    "iso:country":"ES",
    "sg:address":"Calle de Cerro Minguete, S/n",
    "sg:city":"Madrid",
    "sg:orig_category":"Asociaciones, Organismos Culturales Y Socioeducativos",
    "sg:phone":"+34 913 76 30 87",
    "sg:postcode":"28035",
    "sg:province":"Madrid",
    "wof:name":"Los Cacharritos Cafe S.l",
    "wof:placetype":"venue"
},
  "geometry": {"coordinates":[-3.7212822437,40.4868354797],"type":"Point"}
}