{
  "type": "Feature",
  "properties": {
    "iso:country":"ES",
    "sg:address":"Calle de Montichelvo, 3",
    "sg:city":"Valencia",
    "sg:orig_category":"Psic\u00d3logos",
    "sg:phone":"+34 963 33 81 67",
    "sg:postcode":"46006",
    "sg:province":"Valencia",
    "wof:name":"Hernandez Ortiz Encarnacion",
    "wof:placetype":"venue"
},
  "geometry": {"coordinates":[-0.3672319949,39.458480835],"type":"Point"}
}