{
  "type": "Feature",
  "properties": {
    "addr:full":"Calle de Concejal Benito Martin Lozano, 12 Madrid Madrid 28005",
    "addr:housenumber":"12",
    "addr:postcode":"madrid;28005",
    "addr:street":"Calle De Concejal Benito Martin Lozano",
    "iso:country":"ES",
    "sg:address":"Calle de Concejal Benito Martin Lozano, 12",
    "sg:city":"Madrid",
    "sg:orig_category":"Inmobiliaria (agencias)",
    "sg:phone":"+34 913 54 04 33",
    "sg:postcode":"28005",
    "sg:province":"Madrid",
    "wof:name":"Invertaray S.a.",
    "wof:placetype":"venue"
},
  "geometry": {"coordinates":[-3.7098083496,40.4053039551],"type":"Point"}
}