{
  "type": "Feature",
  "properties": {
    "addr:full":"Avgd Alacant, Km. 0007,0 Silla Valencia 46460",
    "addr:postcode":"46460",
    "addr:street":"Alacant Km. 0007,0",
    "iso:country":"ES",
    "sg:address":"Avgd Alacant, Km. 0007,0",
    "sg:city":"Silla",
    "sg:orig_category":"Molduras, Junquillos, Listones Y Molduras Perforadas",
    "sg:phone":"+34 961 21 06 31",
    "sg:postcode":"46460",
    "sg:province":"Valencia",
    "wof:name":"Pastor Vicente Alicia",
    "wof:placetype":"venue"
},
  "geometry": {"coordinates":[-0.417858988,39.3685531616],"type":"Point"}
}