{
  "type": "Feature",
  "properties": {
    "iso:country":"ES",
    "sg:address":"Avda Toscana, 50",
    "sg:city":"Parquelagos",
    "sg:orig_category":"Delegados, Agentes De Tr\u00c1nsito, Auxiliares De Transporte Internacional",
    "sg:phone":"+34 918 59 17 36",
    "sg:postcode":"28420",
    "sg:province":"Madrid",
    "wof:name":"Panarcos Internacional S.l.",
    "wof:placetype":"venue"
},
  "geometry": {"coordinates":[-3.9650840759,40.5951271057],"type":"Point"}
}