{
  "type": "Feature",
  "properties": {
    "addr:full":"P Sarasate, 18 Iru\u00f1a Navarra 31001",
    "addr:housenumber":"18",
    "addr:postcode":"31001",
    "addr:street":"Sarasate",
    "iso:country":"ES",
    "sg:address":"P Sarasate, 18",
    "sg:city":"Iru\u00f1a",
    "sg:orig_category":"Bancos",
    "sg:phone":"+34 948 20 65 00",
    "sg:postcode":"31001",
    "sg:province":"Navarra",
    "sg:website":"www.ebankinter.com",
    "wof:name":"Bankinter S.a.",
    "wof:placetype":"venue"
},
  "geometry": {"coordinates":[-1.6443940401,42.8157310486],"type":"Point"}
}