{
  "type": "Feature",
  "properties": {
    "addr:full":"Carrer de Barcelona, 58 Castellar Valles Barcelona 08211",
    "addr:housenumber":"58",
    "addr:postcode":"08211",
    "addr:street":"Carrer De Barcelona",
    "iso:country":"ES",
    "sg:address":"Carrer de Barcelona, 58",
    "sg:city":"Castellar Valles",
    "sg:orig_category":"Farmacias",
    "sg:phone":"+34 937 15 90 99",
    "sg:postcode":"08211",
    "sg:province":"Barcelona",
    "wof:name":"Vila Boix Pilar",
    "wof:placetype":"venue"
},
  "geometry": {"coordinates":[2.0879590511,41.6092262268],"type":"Point"}
}