{
  "type": "Feature",
  "properties": {
    "addr:full":"Avda Ramon Menendez Pidal, 4 Albacete Albacete 02005",
    "addr:housenumber":"4",
    "addr:postcode":"02005",
    "addr:street":"Avda Ramon Menendez Pidal",
    "iso:country":"ES",
    "sg:address":"Avda Ramon Menendez Pidal, 4",
    "sg:city":"Albacete",
    "sg:orig_category":"Abogados",
    "sg:phone":"+34 967 52 12 89",
    "sg:postcode":"02005",
    "sg:province":"Albacete",
    "wof:name":"De Gregorio Moro Ana Sofia",
    "wof:placetype":"venue"
},
  "geometry": {"coordinates":[-1.8614070415,39.0005531311],"type":"Point"}
}