{
  "type": "Feature",
  "properties": {
    "iso:country":"ES",
    "sg:address":"Calle de Padre Balbino Velasco, 1",
    "sg:city":"Cuellar",
    "sg:classifiers":[
        {
            "category":"Communications",
            "type":"Services"
        }
    ],
    "sg:phone":"+34 921 14 17 23",
    "sg:postcode":"40200",
    "sg:province":"Segovia",
    "sg:tags":[
        "televisiones",
        "y",
        "radio"
    ],
    "wof:name":"Radio Segovia S. A.",
    "wof:placetype":"venue"
},
  "geometry": {"coordinates":[-4.310634613,41.3997001648],"type":"Point"}
}