{
  "type": "Feature",
  "properties": {
    "addr:full":"Carrer de Mola (de La), 3 Riudoms Tarragona 43330",
    "addr:housenumber":"3",
    "addr:postcode":"43330",
    "addr:street":"Carrer De Mola De La",
    "iso:country":"ES",
    "sg:address":"Carrer de Mola (de La), 3",
    "sg:city":"Riudoms",
    "sg:orig_category":"Persianas Interiores, Exteriores",
    "sg:phone":"+34 977 76 81 71",
    "sg:postcode":"43330",
    "sg:province":"Tarragona",
    "wof:name":"Instec",
    "wof:placetype":"venue"
},
  "geometry": {"coordinates":[1.0524100065,41.1418609619],"type":"Point"}
}