{
  "type": "Feature",
  "properties": {
    "iso:country":"ES",
    "sg:address":"Calle de Rio Dilar, 1",
    "sg:city":"Santa Fe",
    "sg:orig_category":"Alimentaci\u00d3n General (al Por Menor)",
    "sg:phone":"+34 958 51 07 04",
    "sg:postcode":"18320",
    "sg:province":"Granada",
    "wof:name":"Segovia Alconcher Jose",
    "wof:placetype":"venue"
},
  "geometry": {"coordinates":[-3.7212619781,37.1855697632],"type":"Point"}
}