{
  "type": "Feature",
  "properties": {
    "iso:country":"ES",
    "sg:address":"Carr Salut, 18",
    "sg:city":"Vilanova I La Geltru",
    "sg:orig_category":"Molduras, Junquillos, Listones Y Molduras Perforadas",
    "sg:phone":"+34 938 93 10 33",
    "sg:postcode":"08800",
    "sg:province":"Barcelona",
    "wof:name":"Salat Gene Ramon",
    "wof:placetype":"venue"
},
  "geometry": {"coordinates":[1.7277619839,41.2249908447],"type":"Point"}
}