{
  "type": "Feature",
  "properties": {
    "iso:country":"ES",
    "sg:address":"Cami Mig, S/n",
    "sg:city":"Vilassar",
    "sg:orig_category":"Productos Qu\u00cdmicos (fabricaci\u00d3n, Al Por Mayor)",
    "sg:phone":"+34 937 54 07 70",
    "sg:postcode":"08340",
    "sg:province":"Barcelona",
    "wof:name":"Europigments",
    "wof:placetype":"venue"
},
  "geometry": {"coordinates":[2.3729999065,41.5088233948],"type":"Point"}
}