{
  "type": "Feature",
  "properties": {
    "iso:country":"ES",
    "sg:address":"Ctra Cadiz (de), Km. 0178,5",
    "sg:city":"Marbella",
    "sg:orig_category":"Promotores Constructores",
    "sg:phone":"+34 952 86 87 70",
    "sg:postcode":"29600",
    "sg:province":"M\u00e1laga",
    "wof:name":"Construcciones Vera S. A.",
    "wof:placetype":"venue"
},
  "geometry": {"coordinates":[-4.8833007812,36.5079956055],"type":"Point"}
}