{
  "type": "Feature",
  "properties": {
    "iso:country":"ES",
    "sg:address":"Calle de Juan De La Cierva, 10",
    "sg:city":"Arganda",
    "sg:orig_category":"Bancos",
    "sg:phone":"+34 918 75 79 30",
    "sg:postcode":"28500",
    "sg:province":"Madrid",
    "wof:name":"Banco Guipuzcoano S.a.",
    "wof:placetype":"venue"
},
  "geometry": {"coordinates":[-3.4387719631,40.3011741638],"type":"Point"}
}