{
  "type": "Feature",
  "properties": {
    "addr:full":"Calle de Rastro, 10 Ubeda Ja\u00e9n 23400",
    "addr:housenumber":"10",
    "addr:postcode":"23400",
    "addr:street":"Calle De Rastro;Jae\u0301N",
    "iso:country":"ES",
    "sg:address":"Calle de Rastro, 10",
    "sg:city":"Ubeda",
    "sg:orig_category":"Bancos",
    "sg:phone":"+34 953 75 06 39",
    "sg:postcode":"23400",
    "sg:province":"Ja\u00e9n",
    "wof:name":"Banco De Andalucia",
    "wof:placetype":"venue"
},
  "geometry": {"coordinates":[-3.3716430664,38.0105476379],"type":"Point"}
}