{
  "type": "Feature",
  "properties": {
    "iso:country":"ES",
    "sg:address":"Av Reis Catolics, 61",
    "sg:city":"Inca",
    "sg:orig_category":"Reposter\u00cdas",
    "sg:phone":"+34 971 50 16 93",
    "sg:postcode":"07300",
    "sg:province":"Islas Baleares",
    "wof:name":"Martorell Ferrer Jaime",
    "wof:placetype":"venue"
},
  "geometry": {"coordinates":[2.9158248901,39.7209320068],"type":"Point"}
}