{
  "type": "Feature",
  "properties": {
    "addr:full":"Calle de Los Herran, 36 Vitoria-gasteiz \u00c1lava 01004",
    "addr:housenumber":"36",
    "addr:postcode":"01004",
    "addr:street":"Calle De Los Herran",
    "iso:country":"ES",
    "sg:address":"Calle de Los Herran, 36",
    "sg:city":"Vitoria-gasteiz",
    "sg:orig_category":"Agencias De Viajes",
    "sg:phone":"+34 945 26 72 33",
    "sg:postcode":"01004",
    "sg:province":"\u00c1lava",
    "sg:website":"www.halconviajes.es",
    "wof:name":"Viajes Halcon S.a.",
    "wof:placetype":"venue"
},
  "geometry": {"coordinates":[-2.6650149822,42.8455619812],"type":"Point"}
}