{
  "type": "Feature",
  "properties": {
    "addr:full":"Calle de Paz, 5 Valencia Valencia 46003",
    "addr:housenumber":"5",
    "addr:postcode":"46003",
    "addr:street":"Calle De Paz",
    "iso:country":"ES",
    "sg:address":"Calle de Paz, 5",
    "sg:city":"Valencia",
    "sg:orig_category":"Confecci\u00d3n De Trajes Para Se\u00d1oras",
    "sg:phone":"+34 963 15 31 64",
    "sg:postcode":"46003",
    "sg:province":"Valencia",
    "sg:website":"www.carolinaherrera.com",
    "wof:name":"Sociedad Textil Lonia S.a.",
    "wof:placetype":"venue"
},
  "geometry": {"coordinates":[-0.374566406,39.4736213684],"type":"Point"}
}