{
  "type": "Feature",
  "properties": {
    "addr:full":"Ctra Aras, S/n Viana Navarra 31230",
    "addr:housenumber":"s / n",
    "addr:postcode":"31230",
    "addr:street":"Ctra Aras",
    "iso:country":"ES",
    "sg:address":"Ctra Aras, S/n",
    "sg:city":"Viana",
    "sg:orig_category":"Productores Recolectores, Venta Directa De Vinos",
    "sg:phone":"+34 948 64 50 34",
    "sg:postcode":"31230",
    "sg:province":"Navarra",
    "wof:name":"Bodegas Ondarre S.a.",
    "wof:placetype":"venue"
},
  "geometry": {"coordinates":[-2.3801000118,42.5187797546],"type":"Point"}
}