{
  "type": "Feature",
  "properties": {
    "addr:full":"Calle de Alvarez De Abreu, 54 Santa Cruz Palma Santa Cruz De Tenerife 38700",
    "addr:housenumber":"54",
    "addr:postcode":"38700",
    "addr:street":"Calle De Alvarez De Abreu",
    "iso:country":"ES",
    "sg:address":"Calle de Alvarez De Abreu, 54",
    "sg:city":"Santa Cruz Palma",
    "sg:orig_category":"Ropa Y Accesorios",
    "sg:phone":"+34 922 41 64 48",
    "sg:postcode":"38700",
    "sg:province":"Santa Cruz De Tenerife",
    "wof:name":"Lorenzo Leal Carmen Rosa",
    "wof:placetype":"venue"
},
  "geometry": {"coordinates":[-17.7654953003,28.6820011139],"type":"Point"}
}