{
  "type": "Feature",
  "properties": {
    "iso:country":"ES",
    "sg:address":"Plaz Mayor, S/n",
    "sg:city":"Mariba\u00d1ez",
    "sg:orig_category":"Institutos M\u00c9dicos",
    "sg:phone":"+34 955 89 60 25",
    "sg:postcode":"41727",
    "sg:province":"Sevilla",
    "wof:name":"Servicio Andaluz De Salud",
    "wof:placetype":"venue"
},
  "geometry": {"coordinates":[-5.8914427757,37.1339073181],"type":"Point"}
}