{
  "type": "Feature",
  "properties": {
    "iso:country":"ES",
    "sg:address":"Calle de Veracruz, 33",
    "sg:city":"Bornos",
    "sg:classifiers":[
        {
            "category":"Autos & Motor Vehicles",
            "subcategory":"Automobile Sales",
            "type":"Retail Goods"
        }
    ],
    "sg:phone":"+34 956 72 81 41",
    "sg:postcode":"11640",
    "sg:province":"C\u00e1diz",
    "wof:name":"Romero Guijo Antonio",
    "wof:placetype":"venue"
},
  "geometry": {"coordinates":[-5.7442989349,36.8164863586],"type":"Point"}
}