{
  "type": "Feature",
  "properties": {
    "iso:country":"ES",
    "sg:address":"Avda Benito Vigo, 94",
    "sg:city":"Estrada",
    "sg:classifiers":[
        {
            "category":"Communications",
            "type":"Services"
        }
    ],
    "sg:phone":"+34 986 57 34 33",
    "sg:postcode":"36680",
    "sg:province":"Pontevedra",
    "sg:tags":[
        "televisiones",
        "y",
        "radio"
    ],
    "wof:name":"Fundacion Cultural A Estrada (radio Estrada",
    "wof:placetype":"venue"
},
  "geometry": {"coordinates":[-8.488735199,42.6883888245],"type":"Point"}
}