{
  "type": "Feature",
  "properties": {
    "iso:country":"ES",
    "sg:address":"Avda Garcia Si\u00d1eriz, 74",
    "sg:city":"Miajadas",
    "sg:orig_category":"Asilos De Ancianos. Centros Privados",
    "sg:phone":"+34 927 34 71 82",
    "sg:postcode":"10100",
    "sg:province":"C\u00e1ceres",
    "wof:name":"Novoger Miajadas S.l.",
    "wof:placetype":"venue"
},
  "geometry": {"coordinates":[-5.9142141342,39.1523513794],"type":"Point"}
}