{
  "type": "Feature",
  "properties": {
    "iso:country":"ES",
    "sg:address":"Calle de Barril (del), S/n",
    "sg:city":"Valdepe\u00f1as",
    "sg:orig_category":"Mec\u00c1nico Del Autom\u00d3vil",
    "sg:phone":"+34 926 32 08 22",
    "sg:postcode":"13300",
    "sg:province":"Ciudad Real",
    "wof:name":"Moreno Carrillo Juan Carlos",
    "wof:placetype":"venue"
},
  "geometry": {"coordinates":[-3.3940486908,38.7762107849],"type":"Point"}
}