{
  "type": "Feature",
  "properties": {
    "addr:full":"Avda Naranjos (de Los), 1 Sanlucar De Barrameda C\u00e1diz 11540",
    "addr:housenumber":"1",
    "addr:postcode":"11540",
    "addr:street":"Avda Naranjos De Los;Ca\u0301Diz",
    "iso:country":"ES",
    "sg:address":"Avda Naranjos (de Los), 1",
    "sg:city":"Sanlucar De Barrameda",
    "sg:orig_category":"Fabricaci\u00d3n De Juguetes Autom\u00c1ticos",
    "sg:phone":"+34 956 38 32 84",
    "sg:postcode":"11540",
    "sg:province":"C\u00e1diz",
    "wof:name":"Sistelcom-telemensaje S.a.",
    "wof:placetype":"venue"
},
  "geometry": {"coordinates":[-6.3434009552,36.7736473083],"type":"Point"}
}