{
  "type": "Feature",
  "properties": {
    "addr:full":"Calle de Soraluce, 5 Zumarraga Guip\u00f9zcoa 20700",
    "addr:housenumber":"5",
    "addr:postcode":"20700",
    "addr:street":"Calle De Soraluce;Guipu\u0300Zcoa",
    "iso:country":"ES",
    "sg:address":"Calle de Soraluce, 5",
    "sg:city":"Zumarraga",
    "sg:orig_category":"Bisuter\u00cda, Joyer\u00cda, Relojer\u00cda (al Por Menor)",
    "sg:phone":"+34 943 72 16 18",
    "sg:postcode":"20700",
    "sg:province":"Guip\u00f9zcoa",
    "wof:name":"Apaolaza Aseguinolaza Francisco",
    "wof:placetype":"venue"
},
  "geometry": {"coordinates":[-2.3137919903,43.0907516479],"type":"Point"}
}