{
  "type": "Feature",
  "properties": {
    "iso:country":"ES",
    "sg:address":"Carrer de Ciutat De Granada, 33",
    "sg:city":"Barcelona",
    "sg:orig_category":"Restaurantes",
    "sg:phone":"+34 934 85 47 72",
    "sg:postcode":"08005",
    "sg:province":"Barcelona",
    "wof:name":"El Raco De La Vila",
    "wof:placetype":"venue"
},
  "geometry": {"coordinates":[2.1990520954,41.3974189758],"type":"Point"}
}