{
  "type": "Feature",
  "properties": {
    "addr:full":"Rua Casabella, 10 Ordes La Coru\u00f1a 15680",
    "addr:housenumber":"10",
    "addr:postcode":"15680",
    "addr:street":"Rua Casabella;La Corun\u0303A",
    "iso:country":"ES",
    "sg:address":"Rua Casabella, 10",
    "sg:city":"Ordes",
    "sg:orig_category":"Peleter\u00cdas",
    "sg:phone":"+34 981 68 00 43",
    "sg:postcode":"15680",
    "sg:province":"La Coru\u00f1a",
    "wof:name":"Estipel S.l.",
    "wof:placetype":"venue"
},
  "geometry": {"coordinates":[-8.4046087265,43.0814666748],"type":"Point"}
}