{
  "type": "Feature",
  "properties": {
    "addr:full":"Urb Paquete (el), S/n Jerez De La Frontera C\u00e1diz 11407",
    "addr:postcode":"11407",
    "addr:street":"Urb;El S / N",
    "iso:country":"ES",
    "sg:address":"Urb Paquete (el), S/n",
    "sg:city":"Jerez De La Frontera",
    "sg:orig_category":"Producci\u00d3n, Venta De Productos De Agricultura Biol\u00d3gica",
    "sg:phone":"+34 956 31 47 47",
    "sg:postcode":"11407",
    "sg:province":"C\u00e1diz",
    "wof:name":"Los Alburejos S.a.",
    "wof:placetype":"venue"
},
  "geometry": {"coordinates":[-6.1367936134,36.7047843933],"type":"Point"}
}