{
  "type": "Feature",
  "properties": {
    "iso:country":"ES",
    "sg:address":"Plaz Espa\u00d1a, 30",
    "sg:city":"Aguilar Campoo",
    "sg:orig_category":"Organismos De Turismo",
    "sg:phone":"+34 979 12 36 41",
    "sg:postcode":"34800",
    "sg:province":"Palencia",
    "wof:name":"Centro De Iniciativas Y Turismo",
    "wof:placetype":"venue"
},
  "geometry": {"coordinates":[-4.2607240677,42.795501709],"type":"Point"}
}