{
  "type": "Feature",
  "properties": {
    "addr:full":"Pg Doctor Alemany, 23 Cullera Valencia 46400",
    "addr:housenumber":"23",
    "addr:postcode":"46400",
    "addr:street":"Pg Doctor Alemany",
    "iso:country":"ES",
    "sg:address":"Pg Doctor Alemany, 23",
    "sg:city":"Cullera",
    "sg:orig_category":"Ense\u00d1anza: Profesiones Art\u00cdsticas",
    "sg:phone":"+34 961 72 08 19",
    "sg:postcode":"46400",
    "sg:province":"Valencia",
    "wof:name":"Foto Rex C.b",
    "wof:placetype":"venue"
},
  "geometry": {"coordinates":[-0.2548319995,39.1641769409],"type":"Point"}
}