{
  "type": "Feature",
  "properties": {
    "iso:country":"ES",
    "sg:address":"Carr Barca, 1",
    "sg:city":"Girona",
    "sg:orig_category":"Reparaci\u00d3n Y Restauraci\u00d3n De Objetos Diversos",
    "sg:phone":"+34 972 20 64 99",
    "sg:postcode":"17004",
    "sg:province":"Girona",
    "wof:name":"Batlle Sanchis Narcis",
    "wof:placetype":"venue"
},
  "geometry": {"coordinates":[2.8241839409,41.9882774353],"type":"Point"}
}