{
  "type": "Feature",
  "properties": {
    "addr:full":"Calle de Referendum De Vi\u00d1a Grande, 8 Alcorcon Madrid 28925",
    "addr:housenumber":"8",
    "addr:postcode":"28925",
    "addr:street":"Calle De Referendum;Grande",
    "iso:country":"ES",
    "sg:address":"Calle de Referendum De Vi\u00d1a Grande, 8",
    "sg:city":"Alcorcon",
    "sg:orig_category":"Lavado, Limpieza De Veh\u00cdculos",
    "sg:phone":"+34 916 19 03 14",
    "sg:postcode":"28925",
    "sg:province":"Madrid",
    "wof:name":"Gri\u00f1an Martinez Maria Helena",
    "wof:placetype":"venue"
},
  "geometry": {"coordinates":[-3.8027830124,40.3499755859],"type":"Point"}
}