{
  "type": "Feature",
  "properties": {
    "iso:country":"ES",
    "sg:address":"Montcabrer, 8",
    "sg:city":"Aldaia",
    "sg:orig_category":"Alquiler De Gr\u00daas",
    "sg:phone":"+34 961 51 54 98",
    "sg:postcode":"46960",
    "sg:province":"Valencia",
    "wof:name":"Peris E Hijo S.l.",
    "wof:placetype":"venue"
},
  "geometry": {"coordinates":[-0.4645400047,39.4728813171],"type":"Point"}
}