{
  "type": "Feature",
  "properties": {
    "addr:full":"Calle de Principe De Vergara, 72 Madrid Madrid 28006",
    "addr:housenumber":"72",
    "addr:postcode":"madrid;28006",
    "addr:street":"Calle De Principe De Vergara",
    "iso:country":"ES",
    "sg:address":"Calle de Principe De Vergara, 72",
    "sg:city":"Madrid",
    "sg:orig_category":"Fabricaci\u00d3n, Importaci\u00d3n, Venta De Material De Telefon\u00cda, Peritelefon\u00cda",
    "sg:phone":"+34 915 15 99 97",
    "sg:postcode":"28006",
    "sg:province":"Madrid",
    "wof:name":"Bt Espa\u00d1a Compa\u00d1ia De Servicios Globales De Telecomunicaciones S.a.u.",
    "wof:placetype":"venue"
},
  "geometry": {"coordinates":[-3.6791899204,40.4344215393],"type":"Point"}
}