{
  "type": "Feature",
  "properties": {
    "iso:country":"ES",
    "sg:address":"Av Espanya, 35",
    "sg:city":"Eivissa",
    "sg:orig_category":"Molduras, Junquillos, Listones Y Molduras Perforadas",
    "sg:phone":"+34 971 30 00 45",
    "sg:postcode":"07800",
    "sg:province":"Islas Baleares",
    "wof:name":"Martinez Carvajal Rafael",
    "wof:placetype":"venue"
},
  "geometry": {"coordinates":[1.4285399914,38.9080810547],"type":"Point"}
}