{
  "type": "Feature",
  "properties": {
    "addr:full":"Calle de Alcala, 597 Madrid Madrid 28022",
    "addr:housenumber":"597",
    "addr:postcode":"28022",
    "addr:street":"Calle De Alcala",
    "iso:country":"ES",
    "sg:address":"Calle de Alcala, 597",
    "sg:city":"Madrid",
    "sg:orig_category":"Agencias De Viajes",
    "sg:phone":"+34 917 43 44 80",
    "sg:postcode":"28022",
    "sg:province":"Madrid",
    "wof:name":"Global World Travel S.l.",
    "wof:placetype":"venue"
},
  "geometry": {"coordinates":[-3.6127150059,40.4463768005],"type":"Point"}
}