{
  "type": "Feature",
  "properties": {
    "addr:full":"Afueras, S/n Xeraco Valencia 46770",
    "addr:postcode":"46770",
    "addr:street":"Afueras S / N",
    "iso:country":"ES",
    "sg:address":"Afueras, S/n",
    "sg:city":"Xeraco",
    "sg:orig_category":"Aguas (distribuci\u00d3n, Servicios)",
    "sg:phone":"+34 962 13 10 16",
    "sg:postcode":"46770",
    "sg:province":"Valencia",
    "wof:name":"Aquagest Levante S A",
    "wof:placetype":"venue"
},
  "geometry": {"coordinates":[-0.216049701,39.0328979492],"type":"Point"}
}