{
  "type": "Feature",
  "properties": {
    "iso:country":"ES",
    "sg:address":"Condado Lagar, S/n",
    "sg:city":"Pobra Carami\u00f1al",
    "sg:classifiers":[
        {
            "category":"Communications",
            "type":"Services"
        }
    ],
    "sg:phone":"+34 981 83 31 44",
    "sg:postcode":"15940",
    "sg:province":"A Coru\u00f1a",
    "sg:tags":[
        "televisiones",
        "y",
        "radio"
    ],
    "wof:name":"Television Da Mancomunidade Do Salnes S.l.",
    "wof:placetype":"venue"
},
  "geometry": {"coordinates":[-8.9388437271,42.6042404175],"type":"Point"}
}