{
  "type": "Feature",
  "properties": {
    "iso:country":"ES",
    "sg:address":"Pase Carmelitas, 11",
    "sg:city":"Salamanca",
    "sg:orig_category":"Mercer\u00cda, Lencer\u00cda (al Por Menor)",
    "sg:phone":"+34 923 21 84 47",
    "sg:postcode":"37002",
    "sg:province":"Salamanca",
    "sg:website":"www.latiendademamen.com",
    "wof:name":"Lozano Guerras Maria Del Carmen",
    "wof:placetype":"venue"
},
  "geometry": {"coordinates":[-5.6645989418,40.9698295593],"type":"Point"}
}