{
  "type": "Feature",
  "properties": {
    "iso:country":"ES",
    "sg:address":"Carrer de Abet, 3",
    "sg:city":"Masies Catalanes",
    "sg:orig_category":"Audiovisuales (producci\u00d3n, Edici\u00d3n, Realizaci\u00d3n)",
    "sg:phone":"+34 977 84 65 52",
    "sg:postcode":"43479",
    "sg:province":"Tarragona",
    "wof:name":"Serrano Segura Juan Jose",
    "wof:placetype":"venue"
},
  "geometry": {"coordinates":[1.0893199444,41.25207901],"type":"Point"}
}