{
  "type": "Feature",
  "properties": {
    "addr:full":"Carrer de Saragossa, 22 Barcelona Barcelona 08006",
    "addr:housenumber":"22",
    "addr:postcode":"08006",
    "addr:street":"Carrer De Saragossa",
    "iso:country":"ES",
    "sg:address":"Carrer de Saragossa, 22",
    "sg:city":"Barcelona",
    "sg:orig_category":"Inform\u00c1tica: Mantenimiento Y Reparaci\u00d3n De Ordenadores",
    "sg:phone":"+34 934 16 05 46",
    "sg:postcode":"08006",
    "sg:province":"Barcelona",
    "wof:name":"Morera Morral Ana",
    "wof:placetype":"venue"
},
  "geometry": {"coordinates":[2.1496400833,41.4019203186],"type":"Point"}
}