{
  "type": "Feature",
  "properties": {
    "addr:full":"C/ Angel Guimera, 111 Salt Girona 17190",
    "addr:housenumber":"111",
    "addr:postcode":"17190",
    "addr:street":"C / Angel Guimera",
    "iso:country":"ES",
    "sg:address":"C/ Angel Guimera, 111",
    "sg:city":"Salt",
    "sg:orig_category":"Empresas De Impermeabilizaci\u00d3n",
    "sg:phone":"+34 972 24 44 67",
    "sg:postcode":"17190",
    "sg:province":"Girona",
    "sg:website":"www.texsa.com",
    "wof:name":"Texsa S.a.",
    "wof:placetype":"venue"
},
  "geometry": {"coordinates":[2.7865219116,41.9729690552],"type":"Point"}
}