{
  "type": "Feature",
  "properties": {
    "addr:full":"Calle de Castro Urdiales, 11 Vitoria-gasteiz \u00c1lava 01006",
    "addr:housenumber":"11",
    "addr:postcode":"01006",
    "addr:street":"Calle De Castro Urdiales",
    "iso:country":"ES",
    "sg:address":"Calle de Castro Urdiales, 11",
    "sg:city":"Vitoria-gasteiz",
    "sg:orig_category":"Molduras, Junquillos, Listones Y Molduras Perforadas",
    "sg:phone":"+34 945 14 74 98",
    "sg:postcode":"01006",
    "sg:province":"\u00c1lava",
    "wof:name":"Union 84 S. A.",
    "wof:placetype":"venue"
},
  "geometry": {"coordinates":[-2.6648540497,42.8393745422],"type":"Point"}
}