{
  "type": "Feature",
  "properties": {
    "addr:full":"Calle de Santa Clara, 12 Santander Cantabria 39001",
    "addr:housenumber":"12",
    "addr:postcode":"39001",
    "addr:street":"Calle De Santa Clara",
    "iso:country":"ES",
    "sg:address":"Calle de Santa Clara, 12",
    "sg:city":"Santander",
    "sg:classifiers":[
        {
            "category":"Arts & Performance",
            "subcategory":"Art Gallery",
            "type":"Entertainment"
        }
    ],
    "sg:phone":"+34 942 22 11 90",
    "sg:postcode":"39001",
    "sg:province":"Cantabria",
    "sg:tags":[
        "arte",
        "de",
        "galer\u00cdas"
    ],
    "wof:name":"Martinez Ruiz Jose Manuel",
    "wof:placetype":"venue"
},
  "geometry": {"coordinates":[-3.8074529171,43.4635391235],"type":"Point"}
}