{
  "type": "Feature",
  "properties": {
    "addr:full":"Velazquez, 126 Madrid Madrid 28006",
    "addr:housenumber":"126",
    "addr:postcode":"28006",
    "addr:street":"Velazquez",
    "iso:country":"ES",
    "sg:address":"Velazquez, 126",
    "sg:city":"Madrid",
    "sg:orig_category":"Agencias De Modelos",
    "sg:phone":"+34 915 61 20 43",
    "sg:postcode":"28006",
    "sg:province":"Madrid",
    "sg:website":"www.ssm-models.com",
    "wof:name":"Ss & M Personalities Management S.a.",
    "wof:placetype":"venue"
},
  "geometry": {"coordinates":[-3.6828670502,40.4373016357],"type":"Point"}
}