{
  "type": "Feature",
  "properties": {
    "addr:full":"Calle de Coso Bajo, 58 Huesca Huesca 22001",
    "addr:housenumber":"58",
    "addr:postcode":"22001",
    "addr:street":"Calle De Coso Bajo",
    "iso:country":"ES",
    "sg:address":"Calle de Coso Bajo, 58",
    "sg:city":"Huesca",
    "sg:orig_category":"Abogados",
    "sg:phone":"+34 974 23 09 60",
    "sg:postcode":"22001",
    "sg:province":"Huesca",
    "wof:name":"Montorio Loriz Lourdes",
    "wof:placetype":"venue"
},
  "geometry": {"coordinates":[-0.4055826962,42.1383171082],"type":"Point"}
}