{
  "type": "Feature",
  "properties": {
    "addr:full":"Carrer de Tossa De Mar, 20 Vilafranca Penedes Barcelona 08720",
    "addr:housenumber":"20",
    "addr:postcode":"08720",
    "addr:street":"Carrer De Tossa De Mar;Penedes Barcelona",
    "iso:country":"ES",
    "sg:address":"Carrer de Tossa De Mar, 20",
    "sg:city":"Vilafranca Penedes",
    "sg:classifiers":[
        {
            "category":"Autos & Motor Vehicles",
            "subcategory":"Automobile Sales",
            "type":"Retail Goods"
        }
    ],
    "sg:phone":"+34 938 90 27 73",
    "sg:postcode":"08720",
    "sg:province":"Barcelona",
    "wof:name":"Autoescola Magi S.l.",
    "wof:placetype":"venue"
},
  "geometry": {"coordinates":[1.696393013,41.3405227661],"type":"Point"}
}