{
  "type": "Feature",
  "properties": {
    "addr:full":"Plaz Pepe Ubis, 11 Vitoria-gasteiz \u00c1lava 01003",
    "addr:housenumber":"11",
    "addr:postcode":"01003",
    "addr:street":"Ubis",
    "iso:country":"ES",
    "sg:address":"Plaz Pepe Ubis, 11",
    "sg:city":"Vitoria-gasteiz",
    "sg:orig_category":"Afiladoras, Pulidoras Y Bru\u00d1idoras",
    "sg:phone":"+34 945 27 70 42",
    "sg:postcode":"01003",
    "sg:province":"\u00c1lava",
    "wof:name":"Ollo Pandilla Crescencio",
    "wof:placetype":"venue"
},
  "geometry": {"coordinates":[-2.6590070724,42.8469161987],"type":"Point"}
}