{
  "type": "Feature",
  "properties": {
    "iso:country":"ES",
    "sg:address":"Calle de Malague\u00d1a, S/n",
    "sg:city":"Arroyo De La Miel-benalmadena Costa",
    "sg:orig_category":"Locales De Saunas, De Ba\u00d1os",
    "sg:phone":"+34 952 44 29 41",
    "sg:postcode":"29630",
    "sg:province":"M\u00e1laga",
    "wof:name":"La Dama De Benalmadena Costa S.l.",
    "wof:placetype":"venue"
},
  "geometry": {"coordinates":[-4.519370079,36.6009597778],"type":"Point"}
}