{
  "type": "Feature",
  "properties": {
    "iso:country":"ES",
    "sg:address":"Calle de Uruguay, 25",
    "sg:city":"Palacios Y Villafranca",
    "sg:orig_category":"Imprenta",
    "sg:phone":"+34 955 81 08 52",
    "sg:postcode":"41720",
    "sg:province":"Sevilla",
    "wof:name":"Reina Rodriguez Pedro",
    "wof:placetype":"venue"
},
  "geometry": {"coordinates":[-5.921848774,37.1692008972],"type":"Point"}
}