{
  "type": "Feature",
  "properties": {
    "addr:full":"Calle de Argensola, 5 Barbastro Huesca 22300",
    "addr:housenumber":"5",
    "addr:postcode":"22300",
    "addr:street":"Calle De Argensola",
    "iso:country":"ES",
    "sg:address":"Calle de Argensola, 5",
    "sg:city":"Barbastro",
    "sg:orig_category":"Promotores Constructores",
    "sg:phone":"+34 974 31 52 94",
    "sg:postcode":"22300",
    "sg:province":"Huesca",
    "wof:name":"Construcciones J.f. Morillo S.l.",
    "wof:placetype":"venue"
},
  "geometry": {"coordinates":[0.1267170012,42.0365753174],"type":"Point"}
}