{
  "type": "Feature",
  "properties": {
    "addr:full":"Carrer de L'acer, 30 Barcelona Barcelona 08038",
    "addr:housenumber":"30",
    "addr:postcode":"08038",
    "addr:street":"Carrer De L'Acer",
    "iso:country":"ES",
    "sg:address":"Carrer de L'acer, 30",
    "sg:city":"Barcelona",
    "sg:orig_category":"Aparatos, Material Y Suministros Para Laboratorios",
    "sg:phone":"+34 932 23 27 89",
    "sg:postcode":"08038",
    "sg:province":"Barcelona",
    "sg:website":"www.termo.com",
    "wof:name":"Thermo Electron S.a.",
    "wof:placetype":"venue"
},
  "geometry": {"coordinates":[2.1369328499,41.3517608643],"type":"Point"}
}