{
  "type": "Feature",
  "properties": {
    "addr:full":"Pase General Davila, 70 Santander Cantabria 39006",
    "addr:housenumber":"70",
    "addr:postcode":"39006",
    "addr:street":"Davila",
    "iso:country":"ES",
    "sg:address":"Pase General Davila, 70",
    "sg:city":"Santander",
    "sg:orig_category":"Fabricaci\u00d3n, Instalaci\u00d3n Y Reparaci\u00d3n De Bombas",
    "sg:phone":"+34 942 21 75 51",
    "sg:postcode":"39006",
    "sg:province":"Cantabria",
    "wof:name":"Torres Borragan Jose Ramon",
    "wof:placetype":"venue"
},
  "geometry": {"coordinates":[-3.8005769253,43.4680595398],"type":"Point"}
}