{
  "type": "Feature",
  "properties": {
    "iso:country":"ES",
    "sg:address":"Carrer de Sagrat Cor, 7",
    "sg:city":"Barcelona",
    "sg:orig_category":"Institutos De Belleza",
    "sg:phone":"+34 932 05 09 28",
    "sg:postcode":"08034",
    "sg:province":"Barcelona",
    "wof:name":"Cassellas Alcover Antonia",
    "wof:placetype":"venue"
},
  "geometry": {"coordinates":[2.1195979118,41.4001159668],"type":"Point"}
}