{
  "type": "Feature",
  "properties": {
    "addr:full":"Calle de Acacia (la), 15 Santa Flora Las Palmas 35400",
    "addr:housenumber":"15",
    "addr:postcode":"35400",
    "addr:street":"Calle De Acacia La",
    "iso:country":"ES",
    "sg:address":"Calle de Acacia (la), 15",
    "sg:city":"Santa Flora",
    "sg:orig_category":"Publicidad (soportes Y Gesti\u00d3n)",
    "sg:phone":"+34 928 60 32 95",
    "sg:postcode":"35400",
    "sg:province":"Las Palmas",
    "wof:name":"Jumasan Canarias A2001 S.l.",
    "wof:placetype":"venue"
},
  "geometry": {"coordinates":[-15.5291957855,28.1013584137],"type":"Point"}
}