{
  "type": "Feature",
  "properties": {
    "addr:full":"Avda Desiderio Rodriguez, 44 Torrevieja Alicante 03180",
    "addr:housenumber":"44",
    "addr:postcode":"03180",
    "addr:street":"Avda Desiderio Rodriguez",
    "iso:country":"ES",
    "sg:address":"Avda Desiderio Rodriguez, 44",
    "sg:city":"Torrevieja",
    "sg:orig_category":"Radiocomunicaciones, Telefon\u00cda M\u00d3vil, Radiomensajer\u00cda: Servicios, Comercializaci\u00d3n",
    "sg:phone":"+34 965 71 00 30",
    "sg:postcode":"03180",
    "sg:province":"Alicante",
    "wof:name":"Galan Aizpun Joaquin",
    "wof:placetype":"venue"
},
  "geometry": {"coordinates":[-0.6536790133,38.0173606873],"type":"Point"}
}