{
  "type": "Feature",
  "properties": {
    "iso:country":"ES",
    "sg:address":"Calle de Pintor Obdulio Lopez De Uralde, 4",
    "sg:city":"Vitoria-gasteiz",
    "sg:orig_category":"M\u00c9dicos: Medicina Y Biolog\u00cda Del Deporte",
    "sg:phone":"+34 945 24 54 62",
    "sg:postcode":"01008",
    "sg:province":"\u00c1lava",
    "wof:name":"Mediplan Sport S.l.",
    "wof:placetype":"venue"
},
  "geometry": {"coordinates":[-2.6861650944,42.8451843262],"type":"Point"}
}