{
  "type": "Feature",
  "properties": {
    "addr:full":"Carrer de Joan Ll Estelrich, 20 Palma Islas Baleares 07003",
    "addr:housenumber":"20",
    "addr:postcode":"07003",
    "addr:street":"Carrer De Joan Ll Estelrich",
    "iso:country":"ES",
    "sg:address":"Carrer de Joan Ll Estelrich, 20",
    "sg:city":"Palma",
    "sg:orig_category":"Muebles Y Accesorios Para Cocinas Y Cuartos De Ba\u00d1o (al Por Menor)",
    "sg:phone":"+34 971 72 48 09",
    "sg:postcode":"07003",
    "sg:province":"Islas Baleares",
    "wof:name":"F.c.cuines I Banys S.l.",
    "wof:placetype":"venue"
},
  "geometry": {"coordinates":[2.6477770805,39.5766220093],"type":"Point"}
}