{
  "type": "Feature",
  "properties": {
    "iso:country":"ES",
    "sg:address":"Calle de San Roque, 90",
    "sg:city":"Motilla Palancar",
    "sg:orig_category":"Bebidas",
    "sg:phone":"+34 969 33 10 45",
    "sg:postcode":"16200",
    "sg:province":"Cuenca",
    "wof:name":"Aparicio Bonilla Felix",
    "wof:placetype":"venue"
},
  "geometry": {"coordinates":[-1.9193698168,39.5632743835],"type":"Point"}
}