{
  "type": "Feature",
  "properties": {
    "addr:full":"Avda Montbenidorm, S/n Benidorm Alicante 03500",
    "addr:housenumber":"s / n",
    "addr:postcode":"03500",
    "addr:street":"Avda Montbenidorm",
    "iso:country":"ES",
    "sg:address":"Avda Montbenidorm, S/n",
    "sg:city":"Benidorm",
    "sg:classifiers":[
        {
            "category":"Cinema",
            "subcategory":"Movie Theater",
            "type":"Entertainment"
        }
    ],
    "sg:phone":"+34 965 85 17 67",
    "sg:postcode":"03500",
    "sg:province":"Alicante",
    "sg:tags":[
        "salas",
        "de",
        "cine"
    ],
    "wof:name":"Cines Mediterraneo S.l.",
    "wof:placetype":"venue"
},
  "geometry": {"coordinates":[-0.1628389955,38.5324554443],"type":"Point"}
}