{
  "type": "Feature",
  "properties": {
    "addr:full":"Via Ptolomeo (de), 16 Boisaca A Coru\u00f1a 15890",
    "addr:housenumber":"16",
    "addr:postcode":"15890",
    "addr:street":"Via Ptolomeo De;Corun\u0303A",
    "iso:country":"ES",
    "sg:address":"Via Ptolomeo (de), 16",
    "sg:city":"Boisaca",
    "sg:orig_category":"Importaci\u00d3n",
    "sg:phone":"+34 981 95 80 35",
    "sg:postcode":"15890",
    "sg:province":"A Coru\u00f1a",
    "wof:name":"Vento Comercio Exterior S.l.",
    "wof:placetype":"venue"
},
  "geometry": {"coordinates":[-8.4769210815,42.8835983276],"type":"Point"}
}