{
  "type": "Feature",
  "properties": {
    "addr:full":"Calle de Rio San Pedro, 3 Oviedo Asturias 33001",
    "addr:housenumber":"3",
    "addr:postcode":"33001",
    "addr:street":"Calle De Rio San Pedro",
    "iso:country":"ES",
    "sg:address":"Calle de Rio San Pedro, 3",
    "sg:city":"Oviedo",
    "sg:orig_category":"Asociaciones, Organismos Culturales Y Socioeducativos",
    "sg:phone":"+34 985 22 30 71",
    "sg:postcode":"33001",
    "sg:province":"Asturias",
    "wof:name":"Sociedad Recreativa El Rinconin",
    "wof:placetype":"venue"
},
  "geometry": {"coordinates":[-5.8516459465,43.3666343689],"type":"Point"}
}