{
  "type": "Feature",
  "properties": {
    "iso:country":"ES",
    "sg:address":"Avda Jose Ortega Y Gasset, 62",
    "sg:city":"Malaga",
    "sg:orig_category":"Molduras, Junquillos, Listones Y Molduras Perforadas",
    "sg:phone":"+34 952 33 11 07",
    "sg:postcode":"29006",
    "sg:province":"M\u00e1laga",
    "wof:name":"Gambero Lima Rafael",
    "wof:placetype":"venue"
},
  "geometry": {"coordinates":[-4.4501271248,36.7107200623],"type":"Point"}
}