{
  "type": "Feature",
  "properties": {
    "addr:full":"Rond Sant Oleguer, 37 Mataro Barcelona 08304",
    "addr:housenumber":"37",
    "addr:postcode":"08304",
    "addr:street":"Oleguer",
    "iso:country":"ES",
    "sg:address":"Rond Sant Oleguer, 37",
    "sg:city":"Mataro",
    "sg:orig_category":"Molduras, Junquillos, Listones Y Molduras Perforadas",
    "sg:phone":"+34 937 57 78 03",
    "sg:postcode":"08304",
    "sg:province":"Barcelona",
    "wof:name":"Nieto Fernandez Angel",
    "wof:placetype":"venue"
},
  "geometry": {"coordinates":[2.4430189133,41.5513381958],"type":"Point"}
}