{
  "type": "Feature",
  "properties": {
    "iso:country":"ES",
    "sg:address":"Calle de Isaac Albeniz (de), 7",
    "sg:city":"Alcobendas",
    "sg:orig_category":"Ense\u00d1anza: Idiomas",
    "sg:phone":"+34 916 54 73 56",
    "sg:postcode":"28100",
    "sg:province":"Madrid",
    "wof:name":"Diaz Acevedo Francisco Carlos",
    "wof:placetype":"venue"
},
  "geometry": {"coordinates":[-3.6443660259,40.5495491028],"type":"Point"}
}