{
  "type": "Feature",
  "properties": {
    "iso:country":"ES",
    "sg:address":"Barr Veiga (a), S/n",
    "sg:city":"Veiga",
    "sg:orig_category":"Distribuci\u00d3n De Petr\u00d3leo Y Derivados",
    "sg:phone":"+34 982 34 63 61",
    "sg:postcode":"27744",
    "sg:province":"Lugo",
    "sg:website":"www.cepsa.es",
    "wof:name":"Estacion De Servicio Riotorto S.l.",
    "wof:placetype":"venue"
},
  "geometry": {"coordinates":[-7.2599711418,43.3427810669],"type":"Point"}
}