{
  "type": "Feature",
  "properties": {
    "iso:country":"ES",
    "sg:address":"Calle de Cristo De La Reja, 31",
    "sg:city":"Segura Leon",
    "sg:orig_category":"M\u00c9dicos: Estomatolog\u00cda",
    "sg:phone":"+34 924 70 30 23",
    "sg:postcode":"06270",
    "sg:province":"Badajoz",
    "wof:name":"Vera Berraquero Antonio",
    "wof:placetype":"venue"
},
  "geometry": {"coordinates":[-6.5268640518,38.116065979],"type":"Point"}
}