{
  "type": "Feature",
  "properties": {
    "addr:full":"Av Republica Argentina, 261 Barcelona Barcelona 08023",
    "addr:housenumber":"261",
    "addr:postcode":"08023",
    "addr:street":"Av Republica Argentina",
    "iso:country":"ES",
    "sg:address":"Av Republica Argentina, 261",
    "sg:city":"Barcelona",
    "sg:orig_category":"Diet\u00c9tica: Productos Biol\u00d3gicos, Naturales Y Diet\u00c9ticos (fabricaci\u00d3n, Al Por Mayor)",
    "sg:phone":"+34 932 12 88 51",
    "sg:postcode":"08023",
    "sg:province":"Barcelona",
    "wof:name":"Badiola De Fuenmayor Matilde",
    "wof:placetype":"venue"
},
  "geometry": {"coordinates":[2.1387770176,41.4131507874],"type":"Point"}
}