{
  "type": "Feature",
  "properties": {
    "addr:full":"G.v. Marques Del Turia, 33 Valencia Valencia 46005",
    "addr:housenumber":"33",
    "addr:postcode":"46005",
    "addr:street":"Turia",
    "iso:country":"ES",
    "sg:address":"G.v. Marques Del Turia, 33",
    "sg:city":"Valencia",
    "sg:orig_category":"Molduras, Junquillos, Listones Y Molduras Perforadas",
    "sg:phone":"+34 963 52 98 24",
    "sg:postcode":"46005",
    "sg:province":"Valencia",
    "wof:name":"Pascual Zurriaga Ana Maria",
    "wof:placetype":"venue"
},
  "geometry": {"coordinates":[-0.3709219992,39.4664344788],"type":"Point"}
}