{
  "type": "Feature",
  "properties": {
    "addr:full":"Avda Santiago, 26 Vitoria-gasteiz \u00c1lava 01003",
    "addr:housenumber":"26",
    "addr:postcode":"01003",
    "addr:street":"Avda Santiago",
    "iso:country":"ES",
    "sg:address":"Avda Santiago, 26",
    "sg:city":"Vitoria-gasteiz",
    "sg:orig_category":"Bancos",
    "sg:phone":"+34 945 28 92 55",
    "sg:postcode":"01003",
    "sg:province":"\u00c1lava",
    "wof:name":"Banco De Vasconia",
    "wof:placetype":"venue"
},
  "geometry": {"coordinates":[-2.6623420715,42.8473854065],"type":"Point"}
}