{
  "type": "Feature",
  "properties": {
    "addr:full":"Jimenado, Km. 0002,5 Torre-pacheco Murcia 30700",
    "addr:postcode":"30700",
    "addr:street":"Jimenado Km. 0002,5",
    "iso:country":"ES",
    "sg:address":"Jimenado, Km. 0002,5",
    "sg:city":"Torre-pacheco",
    "sg:orig_category":"Conservas De Legumbres (fabricaci\u00d3n, Al Por Mayor)",
    "sg:phone":"+34 968 58 54 14",
    "sg:postcode":"30700",
    "sg:province":"Murcia",
    "sg:website":"www.rodenasfoods.com",
    "wof:name":"Antonio Rodenas Meseguer S.a.",
    "wof:placetype":"venue"
},
  "geometry": {"coordinates":[-0.9668471217,37.7487564087],"type":"Point"}
}