{
  "type": "Feature",
  "properties": {
    "addr:full":"Plgno. Utzuar, S/n Arbizu Navarra 31839",
    "addr:housenumber":"s",
    "addr:postcode":"31839",
    "addr:street":"/ N",
    "iso:country":"ES",
    "sg:address":"Plgno. Utzuar, S/n",
    "sg:city":"Arbizu",
    "sg:orig_category":"Trabajos De Soldaduras",
    "sg:phone":"+34 948 46 02 32",
    "sg:postcode":"31839",
    "sg:province":"Navarra",
    "wof:name":"Unzilla Lacunza Rufino",
    "wof:placetype":"venue"
},
  "geometry": {"coordinates":[-2.0385990143,42.9161338806],"type":"Point"}
}