{
  "type": "Feature",
  "properties": {
    "iso:country":"ES",
    "sg:address":"Pase San Isidro, 7",
    "sg:city":"Tomelloso",
    "sg:orig_category":"Pr\u00c9stamos Personales E Hipotecarios",
    "sg:phone":"+34 926 50 58 89",
    "sg:postcode":"13700",
    "sg:province":"Ciudad Real",
    "wof:name":"Registro De La Propiedad",
    "wof:placetype":"venue"
},
  "geometry": {"coordinates":[-3.0052940845,39.1665611267],"type":"Point"}
}