{
  "type": "Feature",
  "properties": {
    "addr:full":"N. Trebol, S/n Sevilla Sevilla 41006",
    "addr:housenumber":"/ n",
    "addr:postcode":"41006",
    "addr:street":"N. Trebol S",
    "iso:country":"ES",
    "sg:address":"N. Trebol, S/n",
    "sg:city":"Sevilla",
    "sg:orig_category":"Reposter\u00cdas",
    "sg:phone":"+34 954 63 96 80",
    "sg:postcode":"41006",
    "sg:province":"Sevilla",
    "wof:name":"Garcia Cruz Natividad",
    "wof:placetype":"venue"
},
  "geometry": {"coordinates":[-6.0018129349,37.3876953125],"type":"Point"}
}