{
  "type": "Feature",
  "properties": {
    "iso:country":"ES",
    "sg:address":"Carr Mar (portocolom), 32",
    "sg:city":"Portocolom",
    "sg:orig_category":"Doctores En Medicina",
    "sg:phone":"+34 971 82 43 79",
    "sg:postcode":"07670",
    "sg:province":"Islas Baleares",
    "wof:name":"Villalonga Oliver Gabriel",
    "wof:placetype":"venue"
},
  "geometry": {"coordinates":[3.2617108822,39.4211044312],"type":"Point"}
}