{
  "type": "Feature",
  "properties": {
    "addr:full":"Calle de Doctor Gil Y Morte, 8 Valencia Valencia 46007",
    "addr:housenumber":"8",
    "addr:postcode":"46007",
    "addr:street":"Calle De Doctor Gil Y Morte",
    "iso:country":"ES",
    "sg:address":"Calle de Doctor Gil Y Morte, 8",
    "sg:city":"Valencia",
    "sg:orig_category":"Impuestos, Tesoro P\u00dablico",
    "sg:phone":"+34 963 41 18 54",
    "sg:postcode":"46007",
    "sg:province":"Valencia",
    "wof:name":"Peritaciones Mora S.l.",
    "wof:placetype":"venue"
},
  "geometry": {"coordinates":[-0.3804200888,39.4626922607],"type":"Point"}
}