{
  "type": "Feature",
  "properties": {
    "addr:full":"Calle de Palma, 1 Ciudad Real Ciudad Real 13001",
    "addr:housenumber":"1",
    "addr:postcode":"13001",
    "addr:street":"Calle De Palma",
    "iso:country":"ES",
    "sg:address":"Calle de Palma, 1",
    "sg:city":"Ciudad Real",
    "sg:orig_category":"Bisuter\u00cda, Joyer\u00cda, Relojer\u00cda (al Por Menor)",
    "sg:phone":"+34 926 25 45 67",
    "sg:postcode":"13001",
    "sg:province":"Ciudad Real",
    "wof:name":"Lopez-bermejo Melero Pedro",
    "wof:placetype":"venue"
},
  "geometry": {"coordinates":[-3.9252080917,38.984287262],"type":"Point"}
}