{
  "type": "Feature",
  "properties": {
    "iso:country":"ES",
    "sg:address":"Ctra. Malaga-almeria, Km. 0297,8",
    "sg:city":"Nerja",
    "sg:orig_category":"Pistas Y Clases De Tenis",
    "sg:phone":"+34 952 52 09 48",
    "sg:postcode":"29780",
    "sg:province":"M\u00e1laga",
    "wof:name":"Alvarez De Rivera Luque S.l.",
    "wof:placetype":"venue"
},
  "geometry": {"coordinates":[-3.834997654,36.7956962585],"type":"Point"}
}