{
  "type": "Feature",
  "properties": {
    "iso:country":"ES",
    "sg:address":"Plza. Constitucion, S/n",
    "sg:city":"Tocon",
    "sg:orig_category":"Asilos De Ancianos. Centros Privados",
    "sg:phone":"+34 958 44 88 88",
    "sg:postcode":"18380",
    "sg:province":"Granada",
    "wof:name":"Fundacion San Carlos Y Santa Margarita",
    "wof:placetype":"venue"
},
  "geometry": {"coordinates":[-3.9662439823,37.2375984192],"type":"Point"}
}