{
  "type": "Feature",
  "properties": {
    "iso:country":"ES",
    "sg:address":"Calle de General Segura, 10",
    "sg:city":"Almeria",
    "sg:orig_category":"Ropa Para Se\u00d1oras (al Por Menor)",
    "sg:phone":"+34 950 23 04 59",
    "sg:postcode":"04004",
    "sg:province":"Almer\u00eda",
    "wof:name":"Punta Polacra S. A.",
    "wof:placetype":"venue"
},
  "geometry": {"coordinates":[-2.4624960423,36.8361091614],"type":"Point"}
}