{
  "type": "Feature",
  "properties": {
    "iso:country":"ES",
    "sg:address":"Avda Gran Via Rey Juan Carlos I, 17",
    "sg:city":"Logro\u00f1o",
    "sg:orig_category":"Arquitectos",
    "sg:phone":"+34 941 23 59 23",
    "sg:postcode":"26002",
    "sg:province":"La Rioja",
    "wof:name":"Solozabal Arquitectos C.b.",
    "wof:placetype":"venue"
},
  "geometry": {"coordinates":[-2.4475460052,42.4631309509],"type":"Point"}
}