{
  "type": "Feature",
  "properties": {
    "addr:full":"Calle de Oeste, 2 Carpio Tajo Toledo 45533",
    "addr:housenumber":"2",
    "addr:postcode":"45533",
    "addr:street":"Calle De Oeste",
    "iso:country":"ES",
    "sg:address":"Calle de Oeste, 2",
    "sg:city":"Carpio Tajo",
    "sg:orig_category":"Cr\u00cda De Animales",
    "sg:phone":"+34 925 75 71 11",
    "sg:postcode":"45533",
    "sg:province":"Toledo",
    "wof:name":"Vidal Juan Mora E Hijos S.l",
    "wof:placetype":"venue"
},
  "geometry": {"coordinates":[-4.4579439163,39.8854598999],"type":"Point"}
}