{
  "type": "Feature",
  "properties": {
    "addr:full":"Avda Reyes Catolicos, S/n Alhaurin Torre M\u00e1laga 29130",
    "addr:housenumber":"s / n",
    "addr:postcode":"29130",
    "addr:street":"Avda Reyes Catolicos",
    "iso:country":"ES",
    "sg:address":"Avda Reyes Catolicos, S/n",
    "sg:city":"Alhaurin Torre",
    "sg:orig_category":"Comercio De Piezas De Recambio Y De Accesorios De Veh\u00cdculos, Veh\u00cdculos Industriales",
    "sg:phone":"+34 952 41 51 10",
    "sg:postcode":"29130",
    "sg:province":"M\u00e1laga",
    "wof:name":"Auto Repuestos Ordo\u00d1ez S.l.",
    "wof:placetype":"venue"
},
  "geometry": {"coordinates":[-4.569861412,36.6591949463],"type":"Point"}
}