{
  "type": "Feature",
  "properties": {
    "iso:country":"ES",
    "sg:address":"Belenguera(pol Ind Norte), S/n",
    "sg:city":"Alginet",
    "sg:orig_category":"Asociaciones Y Clubs Deportivos",
    "sg:phone":"+34 961 75 06 94",
    "sg:postcode":"46230",
    "sg:province":"Valencia",
    "wof:name":"Boss Benavent Regino",
    "wof:placetype":"venue"
},
  "geometry": {"coordinates":[-0.4681540132,39.2703552246],"type":"Point"}
}