{
  "type": "Feature",
  "properties": {
    "addr:full":"Calle de Iglesia, 51 Bailen Ja\u00e9n 23710",
    "addr:housenumber":"51",
    "addr:postcode":"23710",
    "addr:street":"Calle De Iglesia;Jae\u0301N",
    "iso:country":"ES",
    "sg:address":"Calle de Iglesia, 51",
    "sg:city":"Bailen",
    "sg:orig_category":"Electricidad: Instaladores",
    "sg:phone":"+34 953 67 52 96",
    "sg:postcode":"23710",
    "sg:province":"Ja\u00e9n",
    "wof:name":"Electricidad Rodriguez Galindo",
    "wof:placetype":"venue"
},
  "geometry": {"coordinates":[-3.7761890888,38.0937614441],"type":"Point"}
}