{
  "type": "Feature",
  "properties": {
    "addr:full":"Av Llibertat (de La), 8 Montornes Centre Barcelona 08170",
    "addr:housenumber":"8",
    "addr:postcode":"08170",
    "addr:street":"Av Llibertat De La;Centre Barcelona",
    "iso:country":"ES",
    "sg:address":"Av Llibertat (de La), 8",
    "sg:city":"Montornes Centre",
    "sg:orig_category":"Molduras, Junquillos, Listones Y Molduras Perforadas",
    "sg:phone":"+34 935 68 00 08",
    "sg:postcode":"08170",
    "sg:province":"Barcelona",
    "wof:name":"Paniagua Casatorres Jose",
    "wof:placetype":"venue"
},
  "geometry": {"coordinates":[2.2669260502,41.5449714661],"type":"Point"}
}