{
  "type": "Feature",
  "properties": {
    "iso:country":"ES",
    "sg:address":"Calle de Traviesa, 28",
    "sg:city":"Ledrada",
    "sg:orig_category":"Negocio De Madera",
    "sg:phone":"+34 923 59 10 34",
    "sg:postcode":"37730",
    "sg:province":"Salamanca",
    "wof:name":"Sanchez Sanchez Arsenio",
    "wof:placetype":"venue"
},
  "geometry": {"coordinates":[-5.7209777832,40.4683151245],"type":"Point"}
}