{
  "type": "Feature",
  "properties": {
    "iso:country":"ES",
    "sg:address":"Plaz Villa, 1",
    "sg:city":"Madrid",
    "sg:orig_category":"Asociaciones, Organismos Culturales Y Socioeducativos",
    "sg:phone":"+34 915 48 34 13",
    "sg:postcode":"28005",
    "sg:province":"Madrid",
    "wof:name":"Real Sociedad Economica Matritense De Amigos Del Pais",
    "wof:placetype":"venue"
},
  "geometry": {"coordinates":[-3.71240592,40.4144058228],"type":"Point"}
}