{
  "type": "Feature",
  "properties": {
    "addr:full":"Calle de San Francisco, 13 Oviedo Asturias 33003",
    "addr:housenumber":"13",
    "addr:postcode":"33003",
    "addr:street":"Calle De San Francisco",
    "iso:country":"ES",
    "sg:address":"Calle de San Francisco, 13",
    "sg:city":"Oviedo",
    "sg:orig_category":"Sociedades, Compa\u00d1\u00cdas Aseguradoras",
    "sg:phone":"+34 985 21 40 79",
    "sg:postcode":"33003",
    "sg:province":"Asturias",
    "sg:website":"www.principado.oviedoe2000.es",
    "wof:name":"Corredores Principado S. A.",
    "wof:placetype":"venue"
},
  "geometry": {"coordinates":[-5.8479290009,43.3617897034],"type":"Point"}
}