{
  "type": "Feature",
  "properties": {
    "addr:full":"Ptda Calvario, S/n Mutxamel Alicante 03110",
    "addr:housenumber":"s / n",
    "addr:postcode":"03110",
    "addr:street":"Ptda Calvario",
    "iso:country":"ES",
    "sg:address":"Ptda Calvario, S/n",
    "sg:city":"Mutxamel",
    "sg:orig_category":"M\u00c9dicos: Cardiolog\u00cda Y Afecciones Cardiovasculares",
    "sg:phone":"+34 965 95 15 36",
    "sg:postcode":"03110",
    "sg:province":"Alicante",
    "wof:name":"Sala Corbi Antonio",
    "wof:placetype":"venue"
},
  "geometry": {"coordinates":[-0.4448040128,38.4151039124],"type":"Point"}
}