{
  "type": "Feature",
  "properties": {
    "addr:full":"Calle de Secundino Esnaola, 3 Donostia-san Sebastian Guip\u00f9zcoa 20001",
    "addr:housenumber":"3",
    "addr:postcode":"20001",
    "addr:street":"Calle De Secundino Esnaola",
    "iso:country":"ES",
    "sg:address":"Calle de Secundino Esnaola, 3",
    "sg:city":"Donostia-san Sebastian",
    "sg:orig_category":"Psic\u00d3logos",
    "sg:phone":"+34 943 27 95 00",
    "sg:postcode":"20001",
    "sg:province":"Guip\u00f9zcoa",
    "wof:name":"Gamboa Hernandez Jorge",
    "wof:placetype":"venue"
},
  "geometry": {"coordinates":[-1.9753149748,43.3222236633],"type":"Point"}
}