{
  "type": "Feature",
  "properties": {
    "addr:full":"Plaz Espa\u00d1a (de), S/n Alhondiga Guadalajara 19132",
    "addr:housenumber":"s",
    "addr:postcode":"19132",
    "addr:street":"Plaz;/ N Alhondiga",
    "iso:country":"ES",
    "sg:address":"Plaz Espa\u00d1a (de), S/n",
    "sg:city":"Alhondiga",
    "sg:orig_category":"Carnicer\u00cdas, Carnicer\u00cdas",
    "sg:phone":"+34 949 28 40 35",
    "sg:postcode":"19132",
    "sg:province":"Guadalajara",
    "wof:name":"Pe\u00f1a Mayor Agustin De La",
    "wof:placetype":"venue"
},
  "geometry": {"coordinates":[-2.8246839046,40.5253181458],"type":"Point"}
}