{
  "type": "Feature",
  "properties": {
    "iso:country":"ES",
    "sg:address":"Trv. Oseiro(oseiro), 25",
    "sg:city":"Arteixo",
    "sg:orig_category":"Escuelas De Maternidad P\u00dablicas",
    "sg:phone":"+34 981 60 13 51",
    "sg:postcode":"15141",
    "sg:province":"La Coru\u00f1a",
    "wof:name":"Escola Infantil Vagalume S.l.",
    "wof:placetype":"venue"
},
  "geometry": {"coordinates":[-8.488079071,43.3220100403],"type":"Point"}
}