{
  "type": "Feature",
  "properties": {
    "iso:country":"ES",
    "sg:address":"Plaz Reyes Magos, 3",
    "sg:city":"Madrid",
    "sg:orig_category":"Abogados",
    "sg:phone":"+34 914 33 35 44",
    "sg:postcode":"28007",
    "sg:province":"Madrid",
    "wof:name":"Naranjo Mederos Daniel",
    "wof:placetype":"venue"
},
  "geometry": {"coordinates":[-3.6768620014,40.4082260132],"type":"Point"}
}