{
  "type": "Feature",
  "properties": {
    "addr:full":"Calle de Araba, 3 Basauri Vizcaya 48970",
    "addr:housenumber":"3",
    "addr:postcode":"48970",
    "addr:street":"Calle De Araba",
    "iso:country":"ES",
    "sg:address":"Calle de Araba, 3",
    "sg:city":"Basauri",
    "sg:orig_category":"Moda",
    "sg:phone":"+34 944 40 24 66",
    "sg:postcode":"48970",
    "sg:province":"Vizcaya",
    "wof:name":"Patricia Casta\u00f1o Garcia Oh Mama",
    "wof:placetype":"venue"
},
  "geometry": {"coordinates":[-2.8862113953,43.2370529175],"type":"Point"}
}