{
  "type": "Feature",
  "properties": {
    "iso:country":"ES",
    "sg:address":"Calle de Maestranza, 12",
    "sg:city":"Malaga",
    "sg:orig_category":"Abogados",
    "sg:phone":"+34 952 21 81 97",
    "sg:postcode":"29016",
    "sg:province":"M\u00e1laga",
    "wof:name":"Lafuente Cata\u00f1o Ana Maria",
    "wof:placetype":"venue"
},
  "geometry": {"coordinates":[-4.4096899033,36.7196159363],"type":"Point"}
}