{
  "type": "Feature",
  "properties": {
    "iso:country":"ES",
    "sg:address":"Carrer de Mare De Deu De La Merce, 2",
    "sg:city":"Gava",
    "sg:orig_category":"Producci\u00d3n De Champi\u00d1ones",
    "sg:phone":"+34 936 62 19 36",
    "sg:postcode":"08850",
    "sg:province":"Barcelona",
    "wof:name":"Casas Truch Juan",
    "wof:placetype":"venue"
},
  "geometry": {"coordinates":[2.0074551105,41.3052139282],"type":"Point"}
}