{
  "type": "Feature",
  "properties": {
    "iso:country":"ES",
    "sg:address":"C/ Espanya, 10",
    "sg:city":"Puigcerda",
    "sg:orig_category":"Inform\u00c1tica Equipo Y Programas (al Por Mayor)",
    "sg:phone":"+34 972 88 31 55",
    "sg:postcode":"17520",
    "sg:province":"Girona",
    "wof:name":"David Ginesta.com 2001 S.l.",
    "wof:placetype":"venue"
},
  "geometry": {"coordinates":[1.9287990332,42.4319496155],"type":"Point"}
}