{
  "type": "Feature",
  "properties": {
    "addr:full":"Calle de Ponzano, 57 Madrid Madrid 28003",
    "addr:housenumber":"57",
    "addr:postcode":"madrid;28003",
    "addr:street":"Calle De Ponzano",
    "iso:country":"ES",
    "sg:address":"Calle de Ponzano, 57",
    "sg:city":"Madrid",
    "sg:orig_category":"Calzados Ortop\u00c9dicos",
    "sg:phone":"+34 913 99 40 07",
    "sg:postcode":"28003",
    "sg:province":"Madrid",
    "wof:name":"Ortopedia Alvarez S.l.",
    "wof:placetype":"venue"
},
  "geometry": {"coordinates":[-3.6992809772,40.4413871765],"type":"Point"}
}