{
  "type": "Feature",
  "properties": {
    "addr:full":"Afores, S/n Bisbal Del Penedes Tarragona 43717",
    "addr:housenumber":"s / n",
    "addr:postcode":"43717",
    "addr:street":"Afores",
    "iso:country":"ES",
    "sg:address":"Afores, S/n",
    "sg:city":"Bisbal Del Penedes",
    "sg:orig_category":"Empresas De Carpinter\u00cda",
    "sg:phone":"+34 977 68 80 92",
    "sg:postcode":"43717",
    "sg:province":"Tarragona",
    "wof:name":"Peral Vilches Ignacio Del",
    "wof:placetype":"venue"
},
  "geometry": {"coordinates":[1.4905450344,41.2773857117],"type":"Point"}
}