{
  "type": "Feature",
  "properties": {
    "addr:full":"Calle de Eguia General, 14 Bilbao Vizcaya 48010",
    "addr:housenumber":"14",
    "addr:postcode":"48010",
    "addr:street":"Calle De Eguia General",
    "iso:country":"ES",
    "sg:address":"Calle de Eguia General, 14",
    "sg:city":"Bilbao",
    "sg:orig_category":"Quincaller\u00cda (al Por Menor)",
    "sg:phone":"+34 944 43 04 23",
    "sg:postcode":"48010",
    "sg:province":"Vizcaya",
    "wof:name":"Jon Cortes Rodriguez  (comercial Avila)",
    "wof:placetype":"venue"
},
  "geometry": {"coordinates":[-2.9429199696,43.2586021423],"type":"Point"}
}