{
  "type": "Feature",
  "properties": {
    "addr:full":"C/ Xixona, 13 Alcoi Alicante 03802",
    "addr:housenumber":"13",
    "addr:postcode":"03802",
    "addr:street":"C / Xixona",
    "iso:country":"ES",
    "sg:address":"C/ Xixona, 13",
    "sg:city":"Alcoi",
    "sg:orig_category":"Asesor\u00cda Fiscal Y Jur\u00cddica",
    "sg:phone":"+34 965 33 40 45",
    "sg:postcode":"03802",
    "sg:province":"Alicante",
    "wof:name":"Asesoria Fiscal Alfil S.l.",
    "wof:placetype":"venue"
},
  "geometry": {"coordinates":[-0.4857116938,38.6957740784],"type":"Point"}
}