{
  "type": "Feature",
  "properties": {
    "addr:full":"Calle de Maria Zambrano, 16 Zaragoza Zaragoza 50018",
    "addr:housenumber":"16",
    "addr:postcode":"50018",
    "addr:street":"Calle De Maria Zambrano",
    "iso:country":"ES",
    "sg:address":"Calle de Maria Zambrano, 16",
    "sg:city":"Zaragoza",
    "sg:orig_category":"M\u00c9dicos: Estomatolog\u00cda",
    "sg:phone":"+34 976 52 77 61",
    "sg:postcode":"50018",
    "sg:province":"Zaragoza",
    "wof:name":"Fernandez Lobera Onesimo",
    "wof:placetype":"venue"
},
  "geometry": {"coordinates":[-0.8886039853,41.6693954468],"type":"Point"}
}