{
  "type": "Feature",
  "properties": {
    "iso:country":"ES",
    "sg:address":"Pase Estacion, S/n",
    "sg:city":"Torredonjimeno",
    "sg:orig_category":"Supermercados Y Hipermercados",
    "sg:phone":"+34 953 34 42 52",
    "sg:postcode":"23650",
    "sg:province":"Ja\u00e9n",
    "wof:name":"Lopez Martinez E Hijos S.l.",
    "wof:placetype":"venue"
},
  "geometry": {"coordinates":[-4.0899910927,37.8016700745],"type":"Point"}
}