{
  "type": "Feature",
  "properties": {
    "iso:country":"ES",
    "sg:address":"Ptda Deveses, 3",
    "sg:city":"Deveses",
    "sg:orig_category":"Restaurantes",
    "sg:phone":"+34 966 47 50 40",
    "sg:postcode":"03770",
    "sg:province":"Alicante",
    "wof:name":"Los Arcos S.l.",
    "wof:placetype":"venue"
},
  "geometry": {"coordinates":[0.0022150001,38.8531761169],"type":"Point"}
}