{
  "type": "Feature",
  "properties": {
    "addr:full":"Rua Victor Garcia Ferreiro, 9 Negreira La Coru\u00f1a 15830",
    "addr:housenumber":"9",
    "addr:postcode":"15830",
    "addr:street":"Rua Victor Garcia Ferreiro;La Corun\u0303A",
    "iso:country":"ES",
    "sg:address":"Rua Victor Garcia Ferreiro, 9",
    "sg:city":"Negreira",
    "sg:orig_category":"Institutos De Belleza",
    "sg:phone":"+34 981 88 61 47",
    "sg:postcode":"15830",
    "sg:province":"La Coru\u00f1a",
    "wof:name":"Freire Freire Maria Del Carmen",
    "wof:placetype":"venue"
},
  "geometry": {"coordinates":[-8.7349624634,42.9112968445],"type":"Point"}
}