{
  "type": "Feature",
  "properties": {
    "iso:country":"ES",
    "sg:address":"Calle de Grecia, 7",
    "sg:city":"Alcala Henares",
    "sg:orig_category":"Fabricaci\u00d3n De Mobiliario De Oficina",
    "sg:phone":"+34 918 83 50 41",
    "sg:postcode":"28802",
    "sg:province":"Madrid",
    "wof:name":"Styl Oficinas S.l.",
    "wof:placetype":"venue"
},
  "geometry": {"coordinates":[-3.3863050938,40.4814834595],"type":"Point"}
}