{
  "type": "Feature",
  "properties": {
    "addr:full":"Pg Vall D'hebron, 157 Barcelona Barcelona 08035",
    "addr:housenumber":"157",
    "addr:postcode":"08035",
    "addr:street":"Pg Vall D'Hebron",
    "iso:country":"ES",
    "sg:address":"Pg Vall D'hebron, 157",
    "sg:city":"Barcelona",
    "sg:orig_category":"Asilos De Ancianos. Centros Privados",
    "sg:phone":"+34 934 28 37 72",
    "sg:postcode":"08035",
    "sg:province":"Barcelona",
    "wof:name":"Mutual Gestion Integral S.l.",
    "wof:placetype":"venue"
},
  "geometry": {"coordinates":[2.1466031075,41.4345932007],"type":"Point"}
}