{
  "type": "Feature",
  "properties": {
    "addr:full":"Calle de Alfonso Xiii, 47 Dolores Murcia 30310",
    "addr:housenumber":"47",
    "addr:postcode":"30310",
    "addr:street":"Calle De Alfonso Xiii",
    "iso:country":"ES",
    "sg:address":"Calle de Alfonso Xiii, 47",
    "sg:city":"Dolores",
    "sg:orig_category":"Laboratorios Y Trabajos De Fotograf\u00cda, V\u00cddeo Y Cine",
    "sg:phone":"+34 968 51 75 18",
    "sg:postcode":"30310",
    "sg:province":"Murcia",
    "wof:name":"Garcia Garcia Jose",
    "wof:placetype":"venue"
},
  "geometry": {"coordinates":[-1.0033214092,37.6402130127],"type":"Point"}
}