{
  "type": "Feature",
  "properties": {
    "iso:country":"ES",
    "sg:address":"Calle de Campoamor, 33",
    "sg:city":"Roda",
    "sg:orig_category":"Carnicer\u00cdas, Carnicer\u00cdas",
    "sg:phone":"+34 967 44 04 53",
    "sg:postcode":"02630",
    "sg:province":"Albacete",
    "wof:name":"Carniceria Blincos S.l.",
    "wof:placetype":"venue"
},
  "geometry": {"coordinates":[-2.15929389,39.2096099854],"type":"Point"}
}