{
  "type": "Feature",
  "properties": {
    "addr:full":"Cra. Barcelona A Puigcerda, Km. 0063,2 Malla Barcelona 08519",
    "addr:postcode":"08519",
    "addr:street":"Puigcerda Km. 0063,2",
    "iso:country":"ES",
    "sg:address":"Cra. Barcelona A Puigcerda, Km. 0063,2",
    "sg:city":"Malla",
    "sg:orig_category":"Suministros Para Carrocer\u00cdas",
    "sg:phone":"+34 938 85 01 94",
    "sg:postcode":"08519",
    "sg:province":"Barcelona",
    "wof:name":"Carrocerias Vich S. A.",
    "wof:placetype":"venue"
},
  "geometry": {"coordinates":[-97.78224945069999,45.7040786743],"type":"Point"}
}