{
  "type": "Feature",
  "properties": {
    "addr:full":"Calle de Cruz (la), 11 Archez M\u00e1laga 29753",
    "addr:housenumber":"11",
    "addr:postcode":"29753",
    "addr:street":"Calle De Cruz La;Ma\u0301Laga",
    "iso:country":"ES",
    "sg:address":"Calle de Cruz (la), 11",
    "sg:city":"Archez",
    "sg:orig_category":"Cajas Para Embalar",
    "sg:phone":"+34 952 55 48 04",
    "sg:postcode":"29753",
    "sg:province":"M\u00e1laga",
    "wof:name":"Cajamar",
    "wof:placetype":"venue"
},
  "geometry": {"coordinates":[-3.9902000427,36.8387832642],"type":"Point"}
}