{
  "type": "Feature",
  "properties": {
    "addr:full":"Torrejon(pol Ind Saladar), S/n Totana Murcia 30850",
    "addr:housenumber":"s / n",
    "addr:postcode":"30850",
    "addr:street":"Saladar",
    "iso:country":"ES",
    "sg:address":"Torrejon(pol Ind Saladar), S/n",
    "sg:city":"Totana",
    "sg:orig_category":"Alimentaci\u00d3n General (al Por Mayor)",
    "sg:phone":"+34 968 49 05 01",
    "sg:postcode":"30850",
    "sg:province":"Murcia",
    "wof:name":"Genetica Nutricion Y Salud Animal S.l.",
    "wof:placetype":"venue"
},
  "geometry": {"coordinates":[-1.5402326584,37.7775039673],"type":"Point"}
}