{
  "type": "Feature",
  "properties": {
    "iso:country":"ES",
    "sg:address":"Calle de San Roque, 16",
    "sg:city":"Carracedelo",
    "sg:orig_category":"Cajas De Ahorro",
    "sg:phone":"+34 987 56 28 86",
    "sg:postcode":"24549",
    "sg:province":"Le\u00f3n",
    "sg:website":"www.cajaespana.es",
    "wof:name":"Caja Espa\u00f1a De Inversiones Caja De Ahorros Y Monte De Piedad",
    "wof:placetype":"venue"
},
  "geometry": {"coordinates":[-6.7300391197,42.5566482544],"type":"Point"}
}