{
  "type": "Feature",
  "properties": {
    "iso:country":"ES",
    "sg:address":"Ctra. Lobosillo-el Estrecho, S/n",
    "sg:city":"Estrecho",
    "sg:orig_category":"Delegados, Agentes De Tr\u00c1nsito, Auxiliares De Transporte Internacional",
    "sg:phone":"+34 968 15 17 44",
    "sg:postcode":"30332",
    "sg:province":"Murcia",
    "wof:name":"Maritima Sureste Shipping S.l.",
    "wof:placetype":"venue"
},
  "geometry": {"coordinates":[-1.1048339605,37.7546157837],"type":"Point"}
}