{
  "type": "Feature",
  "properties": {
    "iso:country":"ES",
    "sg:address":"Calle de Villafranca Del Bierzo, 16",
    "sg:city":"Fuenlabrada",
    "sg:orig_category":"Art\u00cdculos De Regalo (al Por Menor)",
    "sg:phone":"+34 916 42 31 21",
    "sg:postcode":"28947",
    "sg:province":"Madrid",
    "wof:name":"Comercial De Regalos Abaco Sl",
    "wof:placetype":"venue"
},
  "geometry": {"coordinates":[-3.7460250854,40.2662849426],"type":"Point"}
}