{
  "type": "Feature",
  "properties": {
    "iso:country":"ES",
    "sg:address":"Carrer de Doctor Marti I Julia, 68",
    "sg:city":"Cornella Llobregat",
    "sg:orig_category":"Abogados",
    "sg:phone":"+34 933 77 25 74",
    "sg:postcode":"08940",
    "sg:province":"Barcelona",
    "wof:name":"Castro Chivato Miguel Angel De",
    "wof:placetype":"venue"
},
  "geometry": {"coordinates":[2.0666470528,41.3532981873],"type":"Point"}
}