{
  "type": "Feature",
  "properties": {
    "addr:full":"Calle de Jacinto Benavente, S/n Monforte Cid Alicante 03670",
    "addr:housenumber":"s",
    "addr:postcode":"03670",
    "addr:street":"Calle De Jacinto Benavente;/ N",
    "iso:country":"ES",
    "sg:address":"Calle de Jacinto Benavente, S/n",
    "sg:city":"Monforte Cid",
    "sg:orig_category":"Veh\u00cdculos De Ocasi\u00d3n",
    "sg:phone":"+34 965 62 13 49",
    "sg:postcode":"03670",
    "sg:province":"Alicante",
    "wof:name":"Antonio Alzamora S.c.",
    "wof:placetype":"venue"
},
  "geometry": {"coordinates":[-0.7291561961,38.3821220398],"type":"Point"}
}