{
  "type": "Feature",
  "properties": {
    "addr:full":"Calle de Llerena, 25 Sevilla Sevilla 41008",
    "addr:housenumber":"25",
    "addr:postcode":"41008",
    "addr:street":"Calle De Llerena",
    "iso:country":"ES",
    "sg:address":"Calle de Llerena, 25",
    "sg:city":"Sevilla",
    "sg:orig_category":"Zapatos (al Por Menor)",
    "sg:phone":"+34 954 35 88 65",
    "sg:postcode":"41008",
    "sg:province":"Sevilla",
    "wof:name":"Sanchez Fernandez Juan Jose",
    "wof:placetype":"venue"
},
  "geometry": {"coordinates":[-5.9795022011,37.4043006897],"type":"Point"}
}