{
  "type": "Feature",
  "properties": {
    "addr:full":"Avda Playas (las), 1 Puerto Del Carmen Las Palmas 35510",
    "addr:housenumber":"1",
    "addr:postcode":"35510",
    "addr:street":"Avda Playas Las",
    "iso:country":"ES",
    "sg:address":"Avda Playas (las), 1",
    "sg:city":"Puerto Del Carmen",
    "sg:orig_category":"Alquiler De Veh\u00cdculos: Turismos Y Utilitarios",
    "sg:phone":"+34 928 51 11 91",
    "sg:postcode":"35510",
    "sg:province":"Las Palmas",
    "wof:name":"Autos Feber S.l.",
    "wof:placetype":"venue"
},
  "geometry": {"coordinates":[-13.6397809982,28.9244537354],"type":"Point"}
}