{
  "type": "Feature",
  "properties": {
    "addr:full":"Calle de San Juan, 36 Puerto De Santa Maria C\u00e1diz 11500",
    "addr:housenumber":"36",
    "addr:postcode":"11500",
    "addr:street":"Calle De San Juan;Ca\u0301Diz",
    "iso:country":"ES",
    "sg:address":"Calle de San Juan, 36",
    "sg:city":"Puerto De Santa Maria",
    "sg:orig_category":"Negocio De Materiales De Construcci\u00d3n",
    "sg:phone":"+34 956 85 05 16",
    "sg:postcode":"11500",
    "sg:province":"C\u00e1diz",
    "wof:name":"Manuel Guerrero Camacho C.b.",
    "wof:placetype":"venue"
},
  "geometry": {"coordinates":[-6.229970932,36.6017150879],"type":"Point"}
}