{
  "type": "Feature",
  "properties": {
    "iso:country":"ES",
    "sg:address":"Av. Camp, 1",
    "sg:city":"Palau-solita Plegamans",
    "sg:orig_category":"Asociaciones Y Clubs Deportivos",
    "sg:phone":"+34 938 64 68 27",
    "sg:postcode":"08184",
    "sg:province":"Barcelona",
    "wof:name":"Club De Futbol Palau De Plegamans",
    "wof:placetype":"venue"
},
  "geometry": {"coordinates":[2.181032896,41.5802307129],"type":"Point"}
}