{
  "type": "Feature",
  "properties": {
    "iso:country":"ES",
    "sg:address":"Calle de Veracruz, 5",
    "sg:city":"Trebujena",
    "sg:orig_category":"Partidos Pol\u00cdticos",
    "sg:phone":"+34 956 39 50 27",
    "sg:postcode":"11560",
    "sg:province":"C\u00e1diz",
    "wof:name":"Izquierda Unida-los Verdes Convocatoria Por Andalucia",
    "wof:placetype":"venue"
},
  "geometry": {"coordinates":[-6.17557621,36.8701286316],"type":"Point"}
}