{
  "type": "Feature",
  "properties": {
    "iso:country":"ES",
    "sg:address":"Avda Buenos Aires, 81",
    "sg:city":"Ourense",
    "sg:orig_category":"Plomeros",
    "sg:phone":"+34 988 22 35 80",
    "sg:postcode":"32004",
    "sg:province":"Ourense",
    "wof:name":"M Sampil Y J Gonzalez S.c.",
    "wof:placetype":"venue"
},
  "geometry": {"coordinates":[-7.8591570854,42.3407173157],"type":"Point"}
}