{
  "type": "Feature",
  "properties": {
    "iso:country":"ES",
    "sg:address":"Gabriel Esteve, 5",
    "sg:city":"Bonrepos Mirambell",
    "sg:orig_category":"Empresas De Carpinter\u00cda",
    "sg:phone":"+34 961 41 13 24",
    "sg:postcode":"46131",
    "sg:province":"Valencia",
    "wof:name":"Aluminios Salvador Pastor S.l.",
    "wof:placetype":"venue"
},
  "geometry": {"coordinates":[-0.3648237884,39.514995575],"type":"Point"}
}