{
  "type": "Feature",
  "properties": {
    "addr:full":"Gudarien Plaza, S/n Hernani Guip\u00f9zcoa 20120",
    "addr:housenumber":"s / n",
    "addr:postcode":"20120",
    "addr:street":"Gudarien;Guipu\u0300Zcoa",
    "iso:country":"ES",
    "sg:address":"Gudarien Plaza, S/n",
    "sg:city":"Hernani",
    "sg:orig_category":"Confecci\u00d3n (fabricaci\u00d3n, Al Por Mayor)",
    "sg:phone":"+34 943 55 23 86",
    "sg:postcode":"20120",
    "sg:province":"Guip\u00f9zcoa",
    "wof:name":"Urretxu Lopez Clara",
    "wof:placetype":"venue"
},
  "geometry": {"coordinates":[-1.9754350185,43.2651481628],"type":"Point"}
}