{
  "type": "Feature",
  "properties": {
    "addr:full":"Calle de Pio De Cela, S/n Veguellina Orbigo Le\u00f3n 24350",
    "addr:housenumber":"s / n",
    "addr:postcode":"24350",
    "addr:street":"Calle De Pio De Cela;Leo\u0301N",
    "iso:country":"ES",
    "sg:address":"Calle de Pio De Cela, S/n",
    "sg:city":"Veguellina Orbigo",
    "sg:orig_category":"Centros De Educaci\u00d3n Especial",
    "sg:phone":"+34 987 37 41 95",
    "sg:postcode":"24350",
    "sg:province":"Le\u00f3n",
    "wof:name":"Asprona Leon",
    "wof:placetype":"venue"
},
  "geometry": {"coordinates":[-5.8849520683,42.4434356689],"type":"Point"}
}