{
  "type": "Feature",
  "properties": {
    "addr:full":"Calle de San Pascual, 172 Torrevieja Alicante 03180",
    "addr:housenumber":"172",
    "addr:postcode":"03180",
    "addr:street":"Calle De San Pascual",
    "iso:country":"ES",
    "sg:address":"Calle de San Pascual, 172",
    "sg:city":"Torrevieja",
    "sg:orig_category":"Plomeros",
    "sg:phone":"+34 966 92 71 91",
    "sg:postcode":"03180",
    "sg:province":"Alicante",
    "wof:name":"Nath Cevallos Freddy Mitchell",
    "wof:placetype":"venue"
},
  "geometry": {"coordinates":[-0.6777129769,37.9803314209],"type":"Point"}
}