{
  "type": "Feature",
  "properties": {
    "addr:full":"C/ Enric Granados, 14 Tossa Girona 17320",
    "addr:housenumber":"14",
    "addr:postcode":"17320",
    "addr:street":"C / Enric Granados",
    "iso:country":"ES",
    "sg:address":"C/ Enric Granados, 14",
    "sg:city":"Tossa",
    "sg:orig_category":"Comercio De Minerales, F\u00d3siles Y Conchas",
    "sg:phone":"+34 972 34 28 89",
    "sg:postcode":"17320",
    "sg:province":"Girona",
    "wof:name":"Palacios Espinosa Jose Luis",
    "wof:placetype":"venue"
},
  "geometry": {"coordinates":[2.9298949242,41.7226753235],"type":"Point"}
}