{
  "type": "Feature",
  "properties": {
    "addr:full":"Carrer de L'esparteria, 12 Barcelona Barcelona 08003",
    "addr:housenumber":"12",
    "addr:postcode":"08003",
    "addr:street":"Carrer De L'Esparteria",
    "iso:country":"ES",
    "sg:address":"Carrer de L'esparteria, 12",
    "sg:city":"Barcelona",
    "sg:orig_category":"Ropa Para Se\u00d1oras Y Caballeros (al Por Menor)",
    "sg:phone":"+34 932 68 72 49",
    "sg:postcode":"08003",
    "sg:province":"Barcelona",
    "wof:name":"Lys 3000 S.l.",
    "wof:placetype":"venue"
},
  "geometry": {"coordinates":[2.1831884384,41.3843612671],"type":"Point"}
}