{
  "type": "Feature",
  "properties": {
    "addr:full":"Carr Angel Guimera, S/n Miralcamp Lleida 25242",
    "addr:housenumber":"s",
    "addr:postcode":"25242",
    "addr:street":"Carr Angel Guimera;/ N",
    "iso:country":"ES",
    "sg:address":"Carr Angel Guimera, S/n",
    "sg:city":"Miralcamp",
    "sg:orig_category":"Limpieza Con Chorro De Arena Y Con Granalla, Pulido",
    "sg:phone":"+34 973 71 12 32",
    "sg:postcode":"25242",
    "sg:province":"Lleida",
    "wof:name":"Garcia Cazora David",
    "wof:placetype":"venue"
},
  "geometry": {"coordinates":[0.8789049983,41.6086616516],"type":"Point"}
}