{
  "type": "Feature",
  "properties": {
    "addr:full":"Carrer de Sinies (de Les), 3 Salou Tarragona 43840",
    "addr:housenumber":"3",
    "addr:postcode":"43840",
    "addr:street":"Carrer De Sinies De Les",
    "iso:country":"ES",
    "sg:address":"Carrer de Sinies (de Les), 3",
    "sg:city":"Salou",
    "sg:orig_category":"Farmacias",
    "sg:phone":"+34 977 38 07 88",
    "sg:postcode":"43840",
    "sg:province":"Tarragona",
    "wof:name":"Coret Herrera Rosa",
    "wof:placetype":"venue"
},
  "geometry": {"coordinates":[1.1310780048,41.0822982788],"type":"Point"}
}