{
  "type": "Feature",
  "properties": {
    "iso:country":"ES",
    "sg:address":"C/ Carmelites Velles, 3",
    "sg:city":"Banyoles",
    "sg:orig_category":"M\u00c9dicos: Estomatolog\u00cda",
    "sg:phone":"+34 972 57 47 51",
    "sg:postcode":"17820",
    "sg:province":"Girona",
    "wof:name":"Mendez Alavedra Narciso",
    "wof:placetype":"venue"
},
  "geometry": {"coordinates":[2.7632460594,42.1168327332],"type":"Point"}
}