{
  "type": "Feature",
  "properties": {
    "iso:country":"ES",
    "sg:address":"Carr Ramblar, 3",
    "sg:city":"Oliva",
    "sg:orig_category":"Maquinaria Para Industrias Diversas",
    "sg:phone":"+34 962 85 45 99",
    "sg:postcode":"46780",
    "sg:province":"Valencia",
    "wof:name":"Sanchez Tarazona Fernando",
    "wof:placetype":"venue"
},
  "geometry": {"coordinates":[-0.1157749966,38.9139709473],"type":"Point"}
}