{
  "type": "Feature",
  "properties": {
    "addr:full":"Calle de Villanueva, 20 Madrid Madrid 28001",
    "addr:housenumber":"20",
    "addr:postcode":"madrid;28001",
    "addr:street":"Calle De Villanueva",
    "iso:country":"ES",
    "sg:address":"Calle de Villanueva, 20",
    "sg:city":"Madrid",
    "sg:orig_category":"Inmobiliaria (agencias)",
    "sg:phone":"+34 914 35 21 00",
    "sg:postcode":"28001",
    "sg:province":"Madrid",
    "wof:name":"Mersam Inmolien S.l.",
    "wof:placetype":"venue"
},
  "geometry": {"coordinates":[-3.6873059273,40.4223518372],"type":"Point"}
}