{
  "type": "Feature",
  "properties": {
    "iso:country":"ES",
    "sg:address":"Calle de Albacete, 5",
    "sg:city":"Valencia",
    "sg:orig_category":"Ense\u00d1anza Variada",
    "sg:phone":"+34 963 41 41 27",
    "sg:postcode":"46007",
    "sg:province":"Valencia",
    "wof:name":"Centro De Estudios Academicos S. A.",
    "wof:placetype":"venue"
},
  "geometry": {"coordinates":[-0.3826656938,39.4650611877],"type":"Point"}
}