{
  "type": "Feature",
  "properties": {
    "addr:full":"Plaz Inmaculada, S/n Churriana M\u00e1laga 29140",
    "addr:housenumber":"s / n",
    "addr:postcode":"29140",
    "iso:country":"ES",
    "sg:address":"Plaz Inmaculada, S/n",
    "sg:city":"Churriana",
    "sg:orig_category":"Ense\u00d1anza, Formaci\u00d3n Profesional: Aprendizaje",
    "sg:phone":"+34 952 43 59 07",
    "sg:postcode":"29140",
    "sg:province":"M\u00e1laga",
    "wof:name":"Junta De Andalucia-consejeria De Cultura",
    "wof:placetype":"venue"
},
  "geometry": {"coordinates":[-4.5029239655,36.6698722839],"type":"Point"}
}