{
  "type": "Feature",
  "properties": {
    "addr:full":"Calle de Palmera (la)-los Pinos, 4 Algeciras C\u00e1diz 11205",
    "addr:housenumber":"4;ca\u0301diz",
    "addr:postcode":"11205",
    "addr:street":"Calle De Palmera;Los Pinos",
    "iso:country":"ES",
    "sg:address":"Calle de Palmera (la)-los Pinos, 4",
    "sg:city":"Algeciras",
    "sg:orig_category":"Casas Con Estructura De Madera",
    "sg:phone":"+34 956 60 15 39",
    "sg:postcode":"11205",
    "sg:province":"C\u00e1diz",
    "wof:name":"Maderas Combinados Algeciras S.l",
    "wof:placetype":"venue"
},
  "geometry": {"coordinates":[-5.4606699944,36.1545028687],"type":"Point"}
}