{
  "type": "Feature",
  "properties": {
    "iso:country":"ES",
    "sg:address":"Calle de Fernandez Cadorniga, 11",
    "sg:city":"Ba\u00d1eza",
    "sg:orig_category":"M\u00c9dicos: Otorrinolaringolog\u00cda",
    "sg:phone":"+34 987 65 58 89",
    "sg:postcode":"24750",
    "sg:province":"Le\u00f3n",
    "wof:name":"Garcia De Leon Gonzalez Justino",
    "wof:placetype":"venue"
},
  "geometry": {"coordinates":[-5.9242091179,42.3069114685],"type":"Point"}
}