{
  "type": "Feature",
  "properties": {
    "addr:full":"Calle de Nieves Ravelo, 19 Puerto Cruz Santa Cruz De Tenerife 38400",
    "addr:housenumber":"19",
    "addr:postcode":"38400",
    "addr:street":"Calle De Nieves Ravelo;Puerto Cruz",
    "iso:country":"ES",
    "sg:address":"Calle de Nieves Ravelo, 19",
    "sg:city":"Puerto Cruz",
    "sg:orig_category":"Abogados",
    "sg:phone":"+34 922 38 69 03",
    "sg:postcode":"38400",
    "sg:province":"Santa Cruz De Tenerife",
    "wof:name":"Cutillas Topham Sofia",
    "wof:placetype":"venue"
},
  "geometry": {"coordinates":[-16.5507259369,28.4144096375],"type":"Point"}
}