{
  "type": "Feature",
  "properties": {
    "addr:full":"Calle de Mulhacen, 49 Urbanizacion Nueva Cartagena Murcia 30310",
    "addr:housenumber":"49",
    "addr:postcode":"30310",
    "addr:street":"Calle De Mulhacen;Nueva",
    "iso:country":"ES",
    "sg:address":"Calle de Mulhacen, 49",
    "sg:city":"Urbanizacion Nueva Cartagena",
    "sg:orig_category":"Peluquer\u00cdas, Peluquer\u00cda Mixta",
    "sg:phone":"+34 968 31 18 86",
    "sg:postcode":"30310",
    "sg:province":"Murcia",
    "wof:name":"Cristina Peluqueria Y Estetica S.l.",
    "wof:placetype":"venue"
},
  "geometry": {"coordinates":[-1.0072040558,37.6237068176],"type":"Point"}
}