{
  "type": "Feature",
  "properties": {
    "iso:country":"ES",
    "sg:address":"Calle de Mayor, 46",
    "sg:city":"Villanueva Fuente",
    "sg:orig_category":"Peluqueros: De Se\u00d1oras",
    "sg:phone":"+34 967 39 61 87",
    "sg:postcode":"13330",
    "sg:province":"Ciudad Real",
    "wof:name":"Mateo Gallego Aurelia",
    "wof:placetype":"venue"
},
  "geometry": {"coordinates":[-2.6917569637,38.693775177],"type":"Point"}
}