{
  "type": "Feature",
  "properties": {
    "iso:country":"ES",
    "sg:address":"Play Cabria (de), S/n",
    "sg:city":"Velilla-taramay",
    "sg:orig_category":"Restaurantes",
    "sg:phone":"+34 958 88 19 80",
    "sg:postcode":"18690",
    "sg:province":"Granada",
    "wof:name":"Carbonell Diaz Eladio",
    "wof:placetype":"venue"
},
  "geometry": {"coordinates":[-3.6882688999,36.736743927],"type":"Point"}
}