{
  "type": "Feature",
  "properties": {
    "addr:full":"Cami Cementiri, S/n Almacelles Lleida 25100",
    "addr:housenumber":"s / n",
    "addr:postcode":"25100",
    "addr:street":"Cementiri",
    "iso:country":"ES",
    "sg:address":"Cami Cementiri, S/n",
    "sg:city":"Almacelles",
    "sg:orig_category":"Agricultores, Agricultores",
    "sg:phone":"+34 973 74 06 61",
    "sg:postcode":"25100",
    "sg:province":"Lleida",
    "wof:name":"Tersa Pujol Fernando",
    "wof:placetype":"venue"
},
  "geometry": {"coordinates":[0.4386250079,41.7344398499],"type":"Point"}
}