{
  "type": "Feature",
  "properties": {
    "addr:full":"Calle de Livorno, 57 Marchamalo Guadalajara 19180",
    "addr:housenumber":"57",
    "addr:postcode":"19180",
    "addr:street":"Calle De Livorno",
    "iso:country":"ES",
    "sg:address":"Calle de Livorno, 57",
    "sg:city":"Marchamalo",
    "sg:orig_category":"Transporte En General",
    "sg:phone":"+34 949 25 01 26",
    "sg:postcode":"19180",
    "sg:province":"Guadalajara",
    "wof:name":"Frespa Xxi S. L.",
    "wof:placetype":"venue"
},
  "geometry": {"coordinates":[-3.2014870644,40.6685218811],"type":"Point"}
}