{
  "type": "Feature",
  "properties": {
    "iso:country":"ES",
    "sg:address":"Carrer de Sant Pere, 32",
    "sg:city":"Lloret Mar",
    "sg:orig_category":"Zapatos (al Por Menor)",
    "sg:phone":"+34 972 36 81 48",
    "sg:postcode":"17310",
    "sg:province":"Girona",
    "wof:name":"Distrib-selmar S. L.",
    "wof:placetype":"venue"
},
  "geometry": {"coordinates":[2.8463869095,41.700553894],"type":"Point"}
}