{
  "type": "Feature",
  "properties": {
    "iso:country":"ES",
    "sg:address":"Calle de Virgen De Aranzazu, 14",
    "sg:city":"Madrid",
    "sg:orig_category":"Mec\u00c1nico Del Autom\u00d3vil",
    "sg:phone":"+34 917 29 20 76",
    "sg:postcode":"28034",
    "sg:province":"Madrid",
    "wof:name":"Talleres T Y J Cb",
    "wof:placetype":"venue"
},
  "geometry": {"coordinates":[-3.6893677711,40.4859390259],"type":"Point"}
}