{
  "type": "Feature",
  "properties": {
    "addr:full":"Calle de Abadia San Martin, 4 Valencia Valencia 46002",
    "addr:housenumber":"4",
    "addr:postcode":"46002",
    "addr:street":"Calle De Abadia San Martin",
    "iso:country":"ES",
    "sg:address":"Calle de Abadia San Martin, 4",
    "sg:city":"Valencia",
    "sg:orig_category":"Perfumer\u00cda (al Por Menor)",
    "sg:phone":"+34 963 51 28 71",
    "sg:postcode":"46002",
    "sg:province":"Valencia",
    "wof:name":"Santa Maria Novella-madrid S.l.",
    "wof:placetype":"venue"
},
  "geometry": {"coordinates":[-0.3758530021,39.4729309082],"type":"Point"}
}