{
  "type": "Feature",
  "properties": {
    "iso:country":"ES",
    "sg:address":"Calle de San Felix, 5",
    "sg:city":"Gijon",
    "sg:orig_category":"Aceites Y Grasas Alimentarias (fabricaci\u00d3n, Al Por Mayor)",
    "sg:phone":"+34 985 38 62 75",
    "sg:postcode":"33210",
    "sg:province":"Asturias",
    "wof:name":"Rafael Cortina S. A.",
    "wof:placetype":"venue"
},
  "geometry": {"coordinates":[-5.6665167809,43.5244903564],"type":"Point"}
}