{
  "type": "Feature",
  "properties": {
    "iso:country":"ES",
    "sg:address":"Calle de Chantada, 29",
    "sg:city":"Madrid",
    "sg:orig_category":"Molduras, Junquillos, Listones Y Molduras Perforadas",
    "sg:phone":"+34 917 30 13 78",
    "sg:postcode":"28029",
    "sg:province":"Madrid",
    "wof:name":"Gomez Ramirez Alicia",
    "wof:placetype":"venue"
},
  "geometry": {"coordinates":[-3.7139425278,40.4733009338],"type":"Point"}
}