{
  "type": "Feature",
  "properties": {
    "iso:country":"ES",
    "sg:address":"Afores, S/n",
    "sg:city":"Sudanell",
    "sg:orig_category":"Producci\u00d3n De Abonos Y De Fertilizantes",
    "sg:phone":"+34 973 25 82 56",
    "sg:postcode":"25173",
    "sg:province":"Lleida",
    "wof:name":"Lerida Union Quimica S. A.",
    "wof:placetype":"venue"
},
  "geometry": {"coordinates":[0.5881844759,41.5600090027],"type":"Point"}
}