{
  "type": "Feature",
  "properties": {
    "iso:country":"ES",
    "sg:address":"Calle de Jeronimo Ibran, 1",
    "sg:city":"Mieres",
    "sg:orig_category":"Abogados",
    "sg:phone":"+34 985 46 25 90",
    "sg:postcode":"33600",
    "sg:province":"Asturias",
    "wof:name":"Blanco Garcia Maria Josefa Marta",
    "wof:placetype":"venue"
},
  "geometry": {"coordinates":[-5.7732491493,43.2502250671],"type":"Point"}
}