{
  "type": "Feature",
  "properties": {
    "addr:full":"Avda Suecia (de), 24 Cristianos Santa Cruz De Tenerife 38650",
    "addr:housenumber":"24",
    "addr:postcode":"38650",
    "addr:street":"Avda Suecia De",
    "iso:country":"ES",
    "sg:address":"Avda Suecia (de), 24",
    "sg:city":"Cristianos",
    "sg:orig_category":"Ropa Para Caballeros (al Por Menor)",
    "sg:phone":"+34 922 79 50 91",
    "sg:postcode":"38650",
    "sg:province":"Santa Cruz De Tenerife",
    "wof:name":"Ellos 24 S.l.l.",
    "wof:placetype":"venue"
},
  "geometry": {"coordinates":[-16.7189159393,28.0520191193],"type":"Point"}
}