{
  "type": "Feature",
  "properties": {
    "iso:country":"ES",
    "sg:address":"Carrer de Bassa (la), 13",
    "sg:city":"Alcanar",
    "sg:orig_category":"Reposter\u00cdas",
    "sg:phone":"+34 977 73 12 78",
    "sg:postcode":"43530",
    "sg:province":"Tarragona",
    "wof:name":"Castell Esteller Juan Bautista",
    "wof:placetype":"venue"
},
  "geometry": {"coordinates":[0.4819589853,40.5449981689],"type":"Point"}
}