{
  "type": "Feature",
  "properties": {
    "addr:full":"Calle de Morena (la), S/n San Pedro Alcantara M\u00e1laga 29670",
    "addr:housenumber":"/ n",
    "addr:postcode":"29670",
    "addr:street":"Calle De Morena La S",
    "iso:country":"ES",
    "sg:address":"Calle de Morena (la), S/n",
    "sg:city":"San Pedro Alcantara",
    "sg:orig_category":"Asociaciones Y Clubs Deportivos",
    "sg:phone":"+34 952 85 38 72",
    "sg:postcode":"29670",
    "sg:province":"M\u00e1laga",
    "wof:name":"Montero Perez Maria Eugenia",
    "wof:placetype":"venue"
},
  "geometry": {"coordinates":[-5.003718853,36.4735946655],"type":"Point"}
}