{
  "type": "Feature",
  "properties": {
    "addr:full":"Calle de Santa Ana, 8 Canalejas Del Arroyo Cuenca 16857",
    "addr:housenumber":"8",
    "addr:postcode":"16857",
    "addr:street":"Calle De Santa Ana",
    "iso:country":"ES",
    "sg:address":"Calle de Santa Ana, 8",
    "sg:city":"Canalejas Del Arroyo",
    "sg:orig_category":"Farmacias",
    "sg:phone":"+34 969 31 50 21",
    "sg:postcode":"16857",
    "sg:province":"Cuenca",
    "wof:name":"Rosillo Martin Maria Jose",
    "wof:placetype":"venue"
},
  "geometry": {"coordinates":[-2.49071908,40.3699645996],"type":"Point"}
}