{
  "type": "Feature",
  "properties": {
    "iso:country":"ES",
    "sg:address":"Ctra. General, S/n",
    "sg:city":"Trevias",
    "sg:orig_category":"Quincaller\u00cda (al Por Menor)",
    "sg:phone":"+34 985 64 71 79",
    "sg:postcode":"33780",
    "sg:province":"Asturias",
    "wof:name":"Garcia Fernandez Florentino",
    "wof:placetype":"venue"
},
  "geometry": {"coordinates":[-6.4858551025,43.4557800293],"type":"Point"}
}