{
  "type": "Feature",
  "properties": {
    "iso:country":"ES",
    "sg:address":"Plaz Virgen De La Asuncion, 10",
    "sg:city":"Nules",
    "sg:orig_category":"Pintura Y Barniz (al Por Menor)",
    "sg:phone":"+34 964 67 15 30",
    "sg:postcode":"12520",
    "sg:province":"Castell\u00f3n",
    "wof:name":"Mecho Pallares Ramon",
    "wof:placetype":"venue"
},
  "geometry": {"coordinates":[-0.158118993,39.8537216187],"type":"Point"}
}