{
  "type": "Feature",
  "properties": {
    "iso:country":"ES",
    "sg:address":"Ctra Vella (sant Celoni), 116",
    "sg:city":"S. Celoni",
    "sg:classifiers":[
        {
            "category":"Autos & Motor Vehicles",
            "subcategory":"Automobile Sales",
            "type":"Retail Goods"
        }
    ],
    "sg:phone":"+34 938 67 58 71",
    "sg:postcode":"08470",
    "sg:province":"Barcelona",
    "wof:name":"Autoescola Salgado S.l",
    "wof:placetype":"venue"
},
  "geometry": {"coordinates":[2.1699187756,41.3879165649],"type":"Point"}
}