{
  "type": "Feature",
  "properties": {
    "iso:country":"ES",
    "sg:address":"Plaz Generalisimo, 13",
    "sg:city":"Villaviciosa",
    "sg:orig_category":"Heladeros",
    "sg:phone":"+34 985 89 19 38",
    "sg:postcode":"33300",
    "sg:province":"Asturias",
    "wof:name":"Radiotelecomunicaciones Cabielles S.l.",
    "wof:placetype":"venue"
},
  "geometry": {"coordinates":[-5.4336481094,43.481212616],"type":"Point"}
}