{
  "type": "Feature",
  "properties": {
    "addr:full":"Irazu Kalea, 12 Usurbil Guip\u00f9zcoa 20170",
    "addr:housenumber":"12",
    "addr:postcode":"20170",
    "addr:street":"Irazu Kalea;Guipu\u0300Zcoa",
    "iso:country":"ES",
    "sg:address":"Irazu Kalea, 12",
    "sg:city":"Usurbil",
    "sg:orig_category":"Centros De Adelgazamiento Y De Est\u00c9tica",
    "sg:phone":"+34 943 36 28 87",
    "sg:postcode":"20170",
    "sg:province":"Guip\u00f9zcoa",
    "wof:name":"Larra\u00f1aga Echeverria Lourdes",
    "wof:placetype":"venue"
},
  "geometry": {"coordinates":[-2.0522699356,43.2708206177],"type":"Point"}
}