{
  "type": "Feature",
  "properties": {
    "iso:country":"ES",
    "sg:address":"Calle de Doctor Iranzo, 72",
    "sg:city":"Zaragoza",
    "sg:orig_category":"Droguer\u00cdas (al Por Menor)",
    "sg:phone":"+34 976 42 23 96",
    "sg:postcode":"50002",
    "sg:province":"Zaragoza",
    "wof:name":"Robledo Pina Jose Manuel",
    "wof:placetype":"venue"
},
  "geometry": {"coordinates":[-0.8637604117,41.648059845],"type":"Point"}
}