{
  "type": "Feature",
  "properties": {
    "iso:country":"ES",
    "sg:address":"Calle de General Santiago (del), 6",
    "sg:city":"Segovia",
    "sg:orig_category":"Ense\u00d1anza, Formaci\u00d3n Profesional: Aprendizaje",
    "sg:phone":"+34 921 42 52 61",
    "sg:postcode":"40005",
    "sg:province":"Segovia",
    "wof:name":"Ecyl-servicio Publico De Empleo De Castilla Y Leon",
    "wof:placetype":"venue"
},
  "geometry": {"coordinates":[-4.1124072075,40.94165802],"type":"Point"}
}