{
  "type": "Feature",
  "properties": {
    "addr:full":"Avda Trece De Octubre, 15 Alcazares Murcia 30710",
    "addr:housenumber":"15",
    "addr:postcode":"30710",
    "addr:street":"Avda Trece De Octubre",
    "iso:country":"ES",
    "sg:address":"Avda Trece De Octubre, 15",
    "sg:city":"Alcazares",
    "sg:orig_category":"Sociedades, Compa\u00d1\u00cdas Aseguradoras",
    "sg:phone":"+34 968 17 00 15",
    "sg:postcode":"30710",
    "sg:province":"Murcia",
    "wof:name":"Ms Seguros-13octubre C.b.",
    "wof:placetype":"venue"
},
  "geometry": {"coordinates":[-0.8666689992,37.7385749817],"type":"Point"}
}