{
  "type": "Feature",
  "properties": {
    "addr:full":"Calle de Julio Romero De Torres, S/n Majadahonda Madrid 28220",
    "addr:postcode":"28220",
    "addr:street":"Calle De Julio Romero De Torres S / N",
    "iso:country":"ES",
    "sg:address":"Calle de Julio Romero De Torres, S/n",
    "sg:city":"Majadahonda",
    "sg:orig_category":"Cajas De Ahorro",
    "sg:phone":"+34 916 02 70 78",
    "sg:postcode":"28220",
    "sg:province":"Madrid",
    "wof:name":"Caixa D'estalvis I Pensions De Barcelona",
    "wof:placetype":"venue"
},
  "geometry": {"coordinates":[-3.8595199585,40.4542350769],"type":"Point"}
}