{
  "type": "Feature",
  "properties": {
    "iso:country":"ES",
    "sg:address":"Calle de Hierro, 9",
    "sg:city":"Madrid",
    "sg:orig_category":"Fabricaci\u00d3n, Distribuci\u00d3n De Discos, V\u00cddeodiscos Y Musicassettes",
    "sg:phone":"+34 915 28 67 54",
    "sg:postcode":"28045",
    "sg:province":"Madrid",
    "wof:name":"Boa Cor S.a.",
    "wof:placetype":"venue"
},
  "geometry": {"coordinates":[-3.6893200874,40.3887519836],"type":"Point"}
}