{
  "type": "Feature",
  "properties": {
    "iso:country":"ES",
    "sg:address":"Calle de Herradores, 10",
    "sg:city":"Jaraiz Vera",
    "sg:classifiers":[
        {
            "category":"Taxi",
            "type":"Transportation"
        }
    ],
    "sg:phone":"+34 927 46 11 19",
    "sg:postcode":"10400",
    "sg:province":"C\u00e1ceres",
    "wof:name":"Alegre Romero Feliciano",
    "wof:placetype":"venue"
},
  "geometry": {"coordinates":[-5.7563061714,40.0598678589],"type":"Point"}
}