{
  "type": "Feature",
  "properties": {
    "addr:full":"Calle de Uruguay, 3 Valencia Valencia 46007",
    "addr:housenumber":"3",
    "addr:postcode":"46007",
    "addr:street":"Calle De Uruguay",
    "iso:country":"ES",
    "sg:address":"Calle de Uruguay, 3",
    "sg:city":"Valencia",
    "sg:orig_category":"Arquitectos",
    "sg:phone":"+34 963 41 67 69",
    "sg:postcode":"46007",
    "sg:province":"Valencia",
    "wof:name":"Hernandez Benhamou Luis Miguel",
    "wof:placetype":"venue"
},
  "geometry": {"coordinates":[-0.385453999,39.4601135254],"type":"Point"}
}