{
  "type": "Feature",
  "properties": {
    "iso:country":"ES",
    "sg:address":"Praz Ferrol (de), 2",
    "sg:city":"Lugo",
    "sg:orig_category":"Centros De Coordinaci\u00d3n",
    "sg:phone":"+34 982 24 17 25",
    "sg:postcode":"27001",
    "sg:province":"Lugo",
    "wof:name":"Perez Roibas Erundina",
    "wof:placetype":"venue"
},
  "geometry": {"coordinates":[-7.5573787689,43.0136260986],"type":"Point"}
}