{
  "type": "Feature",
  "properties": {
    "addr:full":"Rua Magnolio, S/n Trabanca Badi\u00e7a Pontevedra 36613",
    "addr:housenumber":"s / n",
    "addr:postcode":"36613",
    "addr:street":"Rua Magnolio",
    "iso:country":"ES",
    "sg:address":"Rua Magnolio, S/n",
    "sg:city":"Trabanca Badi\u00e7a",
    "sg:orig_category":"Empresas De Carpinter\u00cda De Madera",
    "sg:phone":"+34 986 50 18 01",
    "sg:postcode":"36613",
    "sg:province":"Pontevedra",
    "wof:name":"Caneda Rosales Antonio",
    "wof:placetype":"venue"
},
  "geometry": {"coordinates":[-8.7695436478,42.6105308533],"type":"Point"}
}