{
  "type": "Feature",
  "properties": {
    "iso:country":"ES",
    "sg:address":"Carrer de Mare De Deu De La Merce, 35",
    "sg:city":"Hospitalet Llobregat",
    "sg:orig_category":"Pintura Y Barniz (al Por Menor)",
    "sg:phone":"+34 932 60 24 55",
    "sg:postcode":"08901",
    "sg:province":"Barcelona",
    "wof:name":"3 Mabel Serveis S.l.",
    "wof:placetype":"venue"
},
  "geometry": {"coordinates":[2.112382,41.362415],"type":"Point"}
}