{
  "type": "Feature",
  "properties": {
    "iso:country":"ES",
    "sg:address":"Calle de Amor De Dios, 48",
    "sg:city":"Sevilla",
    "sg:orig_category":"Puertas Y Portales",
    "sg:phone":"+34 954 38 57 04",
    "sg:postcode":"41002",
    "sg:province":"Sevilla",
    "wof:name":"Clavijo Otero Jose Maria",
    "wof:placetype":"venue"
},
  "geometry": {"coordinates":[-5.9938139915,37.3966903687],"type":"Point"}
}