{
  "type": "Feature",
  "properties": {
    "iso:country":"ES",
    "sg:address":"Pl Coll, S/n",
    "sg:city":"S. Cugat Valles",
    "sg:orig_category":"Molduras, Junquillos, Listones Y Molduras Perforadas",
    "sg:phone":"+34 936 75 12 11",
    "sg:postcode":"08172",
    "sg:province":"Barcelona",
    "wof:name":"Mantenimiento Y Servicios Bernal S.l.",
    "wof:placetype":"venue"
},
  "geometry": {"coordinates":[2.089869976,41.4752044678],"type":"Point"}
}