{
  "type": "Feature",
  "properties": {
    "addr:full":"Carr De Ferreres Breto, 46 Benicarlo Castell\u00f3n 12580",
    "addr:housenumber":"46",
    "addr:postcode":"12580",
    "addr:street":"Carr De Ferreres Breto",
    "iso:country":"ES",
    "sg:address":"Carr De Ferreres Breto, 46",
    "sg:city":"Benicarlo",
    "sg:orig_category":"Librer\u00cdas",
    "sg:phone":"+34 964 47 18 10",
    "sg:postcode":"12580",
    "sg:province":"Castell\u00f3n",
    "wof:name":"Pe\u00f1a Albiol Francisca",
    "wof:placetype":"venue"
},
  "geometry": {"coordinates":[0.4042100012,40.4457893372],"type":"Point"}
}