{
  "type": "Feature",
  "properties": {
    "addr:full":"Carrer de Grassot, 57 Barcelona Barcelona 08025",
    "addr:housenumber":"57",
    "addr:postcode":"08025",
    "addr:street":"Carrer De Grassot",
    "iso:country":"ES",
    "sg:address":"Carrer de Grassot, 57",
    "sg:city":"Barcelona",
    "sg:orig_category":"Inmobiliaria (agencias)",
    "sg:phone":"+34 934 58 98 00",
    "sg:postcode":"08025",
    "sg:province":"Barcelona",
    "wof:name":"Estilo De Hogar Gestion Inmobiliaria S.l.",
    "wof:placetype":"venue"
},
  "geometry": {"coordinates":[2.1664669514,41.4041404724],"type":"Point"}
}