{
  "type": "Feature",
  "properties": {
    "iso:country":"ES",
    "sg:address":"Carrer de Argentina, 45",
    "sg:city":"Granollers",
    "sg:orig_category":"Promotores Constructores",
    "sg:phone":"+34 938 79 69 45",
    "sg:postcode":"08402",
    "sg:province":"Barcelona",
    "wof:name":"Guinalva Societat Anonima Constructors",
    "wof:placetype":"venue"
},
  "geometry": {"coordinates":[2.2949259281,41.6060562134],"type":"Point"}
}