{
  "type": "Feature",
  "properties": {
    "iso:country":"ES",
    "sg:address":"Carr Canal, 9",
    "sg:city":"Almacelles",
    "sg:orig_category":"Arenas, Guijarros Y Granulados",
    "sg:phone":"+34 973 74 08 07",
    "sg:postcode":"25100",
    "sg:province":"Lleida",
    "wof:name":"Barroso Alferez Josep",
    "wof:placetype":"venue"
},
  "geometry": {"coordinates":[0.4372650087,41.7312660217],"type":"Point"}
}