{
  "type": "Feature",
  "properties": {
    "iso:country":"ES",
    "sg:address":"Ctra Tomelloso, Km. 0000,5",
    "sg:city":"Villarrobledo",
    "sg:orig_category":"Pompas F\u00danebres, Inhumaciones Y Cremaciones",
    "sg:phone":"+34 967 14 36 90",
    "sg:postcode":"02600",
    "sg:province":"Albacete",
    "wof:name":"Ataudes Saimar S.a.",
    "wof:placetype":"venue"
},
  "geometry": {"coordinates":[-2.6587107182,39.2336273193],"type":"Point"}
}