{
  "type": "Feature",
  "properties": {
    "addr:full":"Calle de Gonzalez Hontoria, 14 S. Fernando C\u00e1diz 11100",
    "addr:housenumber":"14",
    "addr:postcode":"11100",
    "addr:street":"Calle De Gonzalez Hontoria;S. Fernando Ca\u0301Diz",
    "iso:country":"ES",
    "sg:address":"Calle de Gonzalez Hontoria, 14",
    "sg:city":"S. Fernando",
    "sg:orig_category":"Comercio, Reparaci\u00d3n De Bicicletas, De Motocicletas, De Accesorios",
    "sg:phone":"+34 956 59 43 33",
    "sg:postcode":"11100",
    "sg:province":"C\u00e1diz",
    "wof:name":"Enciso Reynaldo Enrique",
    "wof:placetype":"venue"
},
  "geometry": {"coordinates":[-6.19668293,36.4670639038],"type":"Point"}
}