{
  "type": "Feature",
  "properties": {
    "addr:full":"Calle de Lope De Vega, 10 Albacete Albacete 02005",
    "addr:housenumber":"10",
    "addr:postcode":"02005",
    "addr:street":"Calle De Lope De Vega",
    "iso:country":"ES",
    "sg:address":"Calle de Lope De Vega, 10",
    "sg:city":"Albacete",
    "sg:orig_category":"Cristaler\u00cdas",
    "sg:phone":"+34 967 22 25 11",
    "sg:postcode":"02005",
    "sg:province":"Albacete",
    "wof:name":"Garvi Gonzalez Fernando",
    "wof:placetype":"venue"
},
  "geometry": {"coordinates":[-1.8657029867,38.9993209839],"type":"Point"}
}