{
  "type": "Feature",
  "properties": {
    "addr:full":"Cmno Ronda (de), 72 Granada Granada 18004",
    "addr:housenumber":"72",
    "addr:postcode":"18004",
    "addr:street":"Cmno Ronda De",
    "iso:country":"ES",
    "sg:address":"Cmno Ronda (de), 72",
    "sg:city":"Granada",
    "sg:orig_category":"Traductores",
    "sg:phone":"+34 958 26 25 50",
    "sg:postcode":"18004",
    "sg:province":"Granada",
    "wof:name":"Mu\u00f1oz Perez Del Pulgar Francisco Javier",
    "wof:placetype":"venue"
},
  "geometry": {"coordinates":[-3.605271101,37.1695365906],"type":"Point"}
}