{
  "type": "Feature",
  "properties": {
    "addr:full":"Calle de Barrio De La Cruz, 7 Monesterio Badajoz 06260",
    "addr:housenumber":"7",
    "addr:postcode":"06260",
    "addr:street":"Calle De Barrio De La Cruz",
    "iso:country":"ES",
    "sg:address":"Calle de Barrio De La Cruz, 7",
    "sg:city":"Monesterio",
    "sg:orig_category":"Zapatos (al Por Menor)",
    "sg:phone":"+34 924 51 70 90",
    "sg:postcode":"06260",
    "sg:province":"Badajoz",
    "wof:name":"Vasco Gonzalez Manuela Monserrat",
    "wof:placetype":"venue"
},
  "geometry": {"coordinates":[-6.2703051567,38.0887107849],"type":"Point"}
}