{
  "type": "Feature",
  "properties": {
    "iso:country":"ES",
    "sg:address":"Carr Nou, 16",
    "sg:city":"Borges Blanques",
    "sg:orig_category":"M\u00c9dicos: Medicina General Orientada A La Acupuntura",
    "sg:phone":"+34 973 14 04 30",
    "sg:postcode":"25400",
    "sg:province":"Lleida",
    "wof:name":"Young Kil  Jun",
    "wof:placetype":"venue"
},
  "geometry": {"coordinates":[0.8686214089,41.521270752],"type":"Point"}
}