{
  "type": "Feature",
  "properties": {
    "iso:country":"ES",
    "sg:address":"Calle de Santa Engracia, 56",
    "sg:city":"Madrid",
    "sg:orig_category":"Farmacias",
    "sg:phone":"+34 914 47 24 19",
    "sg:postcode":"28010",
    "sg:province":"Madrid",
    "wof:name":"Zapatero Leyte Rafael",
    "wof:placetype":"venue"
},
  "geometry": {"coordinates":[-3.6984200478,40.4344787598],"type":"Point"}
}