{
  "type": "Feature",
  "properties": {
    "iso:country":"ES",
    "sg:address":"Carrer de Puig I Llagostera, 3",
    "sg:city":"Vendrell",
    "sg:orig_category":"Promotores Constructores",
    "sg:phone":"+34 977 18 13 57",
    "sg:postcode":"43700",
    "sg:province":"Tarragona",
    "wof:name":"Comunidad De Propietarios Puig I Llagostera 1-3-5-7",
    "wof:placetype":"venue"
},
  "geometry": {"coordinates":[1.5339479446,41.2218132019],"type":"Point"}
}