{
  "type": "Feature",
  "properties": {
    "iso:country":"ES",
    "sg:address":"Avda Venezuela, S/n",
    "sg:city":"Fatima",
    "sg:orig_category":"Aguas (distribuci\u00d3n, Servicios)",
    "sg:phone":"+34 922 48 63 43",
    "sg:postcode":"38750",
    "sg:province":"Santa Cruz De Tenerife",
    "wof:name":"Bolsa De Agua De La Palma",
    "wof:placetype":"venue"
},
  "geometry": {"coordinates":[-17.8813228607,28.6505889893],"type":"Point"}
}