{
  "type": "Feature",
  "properties": {
    "iso:country":"ES",
    "sg:address":"Calle de Marques De Jura Real, 13",
    "sg:city":"Madrid",
    "sg:orig_category":"Quincaller\u00cda (al Por Menor)",
    "sg:phone":"+34 914 60 33 50",
    "sg:postcode":"28019",
    "sg:province":"Madrid",
    "wof:name":"Lozano Sanchez Agustin",
    "wof:placetype":"venue"
},
  "geometry": {"coordinates":[-3.7102489471,40.3913421631],"type":"Point"}
}