{
  "type": "Feature",
  "properties": {
    "addr:full":"Calle de Usandizaga, 11 Donostia-san Sebastian Guip\u00f9zcoa 20002",
    "addr:housenumber":"11",
    "addr:postcode":"20002",
    "addr:street":"Calle De Usandizaga",
    "iso:country":"ES",
    "sg:address":"Calle de Usandizaga, 11",
    "sg:city":"Donostia-san Sebastian",
    "sg:orig_category":"Asociaciones Y Clubs Deportivos",
    "sg:phone":"+34 943 29 24 38",
    "sg:postcode":"20002",
    "sg:province":"Guip\u00f9zcoa",
    "wof:name":"Aerobic Kirola Eta Natura Elkartea",
    "wof:placetype":"venue"
},
  "geometry": {"coordinates":[-1.97739923,43.3236427307],"type":"Point"}
}