{
  "type": "Feature",
  "properties": {
    "addr:full":"Pol Ind Llanos De Armijo, 2 La Puerta Segura Ja\u00e9n 23360",
    "addr:housenumber":"2;jae\u0301n",
    "addr:postcode":"23360",
    "addr:street":"La Puerta Segura",
    "iso:country":"ES",
    "sg:address":"Pol Ind Llanos De Armijo, 2",
    "sg:city":"La Puerta Segura",
    "sg:orig_category":"Negocio De Materiales De Construcci\u00d3n",
    "sg:phone":"+34 953 48 70 93",
    "sg:postcode":"23360",
    "sg:province":"Ja\u00e9n",
    "wof:name":"Materiales De Construccion Hermanos Belmonte Ruiz S.l.l.",
    "wof:placetype":"venue"
},
  "geometry": {"coordinates":[-2.8206489086,38.4468955994],"type":"Point"}
}