{
  "type": "Feature",
  "properties": {
    "addr:full":"Calle de Blas Infante, 33 Aracena Huelva 21200",
    "addr:housenumber":"33",
    "addr:postcode":"21200",
    "addr:street":"Calle De Blas Infante",
    "iso:country":"ES",
    "sg:address":"Calle de Blas Infante, 33",
    "sg:city":"Aracena",
    "sg:orig_category":"Molduras, Junquillos, Listones Y Molduras Perforadas",
    "sg:phone":"+34 959 12 62 80",
    "sg:postcode":"21200",
    "sg:province":"Huelva",
    "wof:name":"Ortega Dominguez Joaquin",
    "wof:placetype":"venue"
},
  "geometry": {"coordinates":[-6.561319828,37.8929634094],"type":"Point"}
}