{
  "type": "Feature",
  "properties": {
    "iso:country":"ES",
    "sg:address":"Carrer de Ali Bei, 32",
    "sg:city":"Barcelona",
    "sg:orig_category":"Asesores De Gesti\u00d3n Del Patrimonio",
    "sg:phone":"+34 932 45 01 24",
    "sg:postcode":"08013",
    "sg:province":"Barcelona",
    "wof:name":"Gestoser Patrimont, Sl",
    "wof:placetype":"venue"
},
  "geometry": {"coordinates":[2.1803689003,41.3931121826],"type":"Point"}
}