{
  "type": "Feature",
  "properties": {
    "iso:country":"ES",
    "sg:address":"Calle de Jacobo Rodriguez Pereira, 7",
    "sg:city":"Badajoz",
    "sg:orig_category":"Carnicer\u00cdas, Carnicer\u00cdas",
    "sg:phone":"+34 924 24 16 06",
    "sg:postcode":"06010",
    "sg:province":"Badajoz",
    "wof:name":"Cortes Martin Maria Esther",
    "wof:placetype":"venue"
},
  "geometry": {"coordinates":[-6.9786400795,38.8695411682],"type":"Point"}
}