{
  "type": "Feature",
  "properties": {
    "iso:country":"ES",
    "sg:address":"Carrer de Boquer, 3",
    "sg:city":"Barcelona",
    "sg:orig_category":"Asociaciones, Organismos Culturales Y Socioeducativos",
    "sg:phone":"+34 933 19 60 69",
    "sg:postcode":"08003",
    "sg:province":"Barcelona",
    "wof:name":"Taleia Cultura S.l.",
    "wof:placetype":"venue"
},
  "geometry": {"coordinates":[2.179639101,41.3853645325],"type":"Point"}
}