{
  "type": "Feature",
  "properties": {
    "iso:country":"ES",
    "sg:address":"Via Laietana, 25",
    "sg:city":"Barcelona",
    "sg:orig_category":"Bancos",
    "sg:phone":"+34 933 10 20 93",
    "sg:postcode":"08003",
    "sg:province":"Barcelona",
    "wof:name":"Dinero Express Servicios Globales S.a.",
    "wof:placetype":"venue"
},
  "geometry": {"coordinates":[2.1783020496,41.384185791],"type":"Point"}
}