{
  "type": "Feature",
  "properties": {
    "addr:full":"Avda Peru (del), 8 Cadiz C\u00e1diz 11007",
    "addr:housenumber":"8",
    "addr:postcode":"11007",
    "addr:street":"Avda Peru Del",
    "iso:country":"ES",
    "sg:address":"Avda Peru (del), 8",
    "sg:city":"Cadiz",
    "sg:orig_category":"Frutas, Legumbres Frescas Y Tempranas (al Por Menor)",
    "sg:phone":"+34 956 27 38 10",
    "sg:postcode":"11007",
    "sg:province":"C\u00e1diz",
    "wof:name":"Brenes Sanchez Sebastian",
    "wof:placetype":"venue"
},
  "geometry": {"coordinates":[-6.2767081261,36.5185012817],"type":"Point"}
}