{
  "type": "Feature",
  "properties": {
    "addr:full":"Carrer de Fontanella, 11 Barcelona Barcelona 08010",
    "addr:housenumber":"11",
    "addr:postcode":"08010",
    "addr:street":"Carrer De Fontanella",
    "iso:country":"ES",
    "sg:address":"Carrer de Fontanella, 11",
    "sg:city":"Barcelona",
    "sg:orig_category":"Zapatos (al Por Menor)",
    "sg:phone":"+34 933 18 08 00",
    "sg:postcode":"08010",
    "sg:province":"Barcelona",
    "wof:name":"Calzados R100 S.l.",
    "wof:placetype":"venue"
},
  "geometry": {"coordinates":[2.1721038818,41.3878707886],"type":"Point"}
}