{
  "type": "Feature",
  "properties": {
    "iso:country":"ES",
    "sg:address":"Calle de Ramon Y Cajal, S/n",
    "sg:city":"Algezares",
    "sg:orig_category":"Quincaller\u00cda (al Por Menor)",
    "sg:phone":"+34 968 84 08 63",
    "sg:postcode":"30157",
    "sg:province":"Murcia",
    "wof:name":"Antonio Illan Ruiz E Hijos S.l.",
    "wof:placetype":"venue"
},
  "geometry": {"coordinates":[-1.1093379259,37.9453048706],"type":"Point"}
}