{
  "type": "Feature",
  "properties": {
    "addr:full":"C/ Sant Agusti, 3 Puigcerda Girona 17520",
    "addr:housenumber":"3",
    "addr:postcode":"17520",
    "addr:street":"C / Sant Agusti",
    "iso:country":"ES",
    "sg:address":"C/ Sant Agusti, 3",
    "sg:city":"Puigcerda",
    "sg:orig_category":"Pr\u00c9stamos Personales E Hipotecarios",
    "sg:phone":"+34 972 88 04 28",
    "sg:postcode":"17520",
    "sg:province":"Girona",
    "wof:name":"Registro De La Propiedad De Puigcerda",
    "wof:placetype":"venue"
},
  "geometry": {"coordinates":[1.926295042,42.4341621399],"type":"Point"}
}