{
  "type": "Feature",
  "properties": {
    "addr:full":"Trueno, S/n Leganes Madrid 28918",
    "addr:housenumber":"/ n",
    "addr:postcode":"28918",
    "addr:street":"Trueno S",
    "iso:country":"ES",
    "sg:address":"Trueno, S/n",
    "sg:city":"Leganes",
    "sg:orig_category":"Fiesta: Art\u00cdculos De (al Por Menor)",
    "sg:phone":"+34 916 10 49 89",
    "sg:postcode":"28918",
    "sg:province":"Madrid",
    "sg:website":"www.fiestascerrada.com",
    "wof:name":"Fiestas Cerrada S.l.",
    "wof:placetype":"venue"
},
  "geometry": {"coordinates":[-3.7952210903,40.3496894836],"type":"Point"}
}