{
  "type": "Feature",
  "properties": {
    "iso:country":"ES",
    "sg:address":"Calle de Maestro Clave, 1",
    "sg:city":"Valencia",
    "sg:orig_category":"Cl\u00cdnicas M\u00c9dicas",
    "sg:phone":"+34 963 52 02 37",
    "sg:postcode":"46001",
    "sg:province":"Valencia",
    "wof:name":"Vargas-machuca Perez Francisco Jose De",
    "wof:placetype":"venue"
},
  "geometry": {"coordinates":[-0.3779082,39.4709358215],"type":"Point"}
}