{
  "type": "Feature",
  "properties": {
    "addr:full":"Calle de Asturias, 39 Alacant Alicante 03007",
    "addr:housenumber":"39",
    "addr:postcode":"03007",
    "addr:street":"Calle De Asturias",
    "iso:country":"ES",
    "sg:address":"Calle de Asturias, 39",
    "sg:city":"Alacant",
    "sg:orig_category":"Material Y Suministros Para Imprenta E Industrias Gr\u00c1ficas",
    "sg:phone":"+34 965 28 23 91",
    "sg:postcode":"03007",
    "sg:province":"Alicante",
    "wof:name":"Martinez Molina Rafael",
    "wof:placetype":"venue"
},
  "geometry": {"coordinates":[-0.5118638873,38.3438529968],"type":"Point"}
}