{
  "type": "Feature",
  "properties": {
    "addr:full":"Calle de Maravillas, 15 Caba\u00e7as De La Sagra Toledo 45592",
    "addr:housenumber":"15",
    "addr:postcode":"45592",
    "addr:street":"Calle De Maravillas",
    "iso:country":"ES",
    "sg:address":"Calle de Maravillas, 15",
    "sg:city":"Caba\u00e7as De La Sagra",
    "sg:orig_category":"Alimentaci\u00d3n General (al Por Mayor)",
    "sg:phone":"+34 925 35 50 33",
    "sg:postcode":"45592",
    "sg:province":"Toledo",
    "wof:name":"Diaz Rojas Jesus",
    "wof:placetype":"venue"
},
  "geometry": {"coordinates":[-3.9487900734,40.0079307556],"type":"Point"}
}