{
  "type": "Feature",
  "properties": {
    "iso:country":"ES",
    "sg:address":"Pol Ind San Blas, S/n",
    "sg:city":"Alburquerque",
    "sg:orig_category":"Reparaciones Y Remolcado De Veh\u00cdculos",
    "sg:phone":"+34 924 40 01 07",
    "sg:postcode":"06510",
    "sg:province":"Badajoz",
    "wof:name":"Automocion Mozo S.l.",
    "wof:placetype":"venue"
},
  "geometry": {"coordinates":[-7.0062189102,39.2217903137],"type":"Point"}
}