{
  "type": "Feature",
  "properties": {
    "iso:country":"ES",
    "sg:address":"Calle de Cruz Verde, 1",
    "sg:city":"Tembleque",
    "sg:orig_category":"Cooperativas Agr\u00cdcolas",
    "sg:phone":"+34 925 14 54 23",
    "sg:postcode":"45780",
    "sg:province":"Toledo",
    "wof:name":"Asociacion Profesional De Agricultores Y Ganaderos De Tembleque",
    "wof:placetype":"venue"
},
  "geometry": {"coordinates":[-3.5058908463,39.6946640015],"type":"Point"}
}