{
  "type": "Feature",
  "properties": {
    "iso:country":"ES",
    "sg:address":"Calle de Zaragoza, 13",
    "sg:city":"Palmas De Gran Canaria",
    "sg:classifiers":[
        {
            "category":"Personal",
            "subcategory":"Barber",
            "type":"Services"
        }
    ],
    "sg:phone":"+34 928 25 56 89",
    "sg:postcode":"35012",
    "sg:province":"Las Palmas",
    "sg:tags":[
        "caballeros",
        "de",
        "peluqueros"
    ],
    "wof:name":"Rodriguez De La Fe Francisco",
    "wof:placetype":"venue"
},
  "geometry": {"coordinates":[-15.4320087433,28.1101112366],"type":"Point"}
}