{
  "type": "Feature",
  "properties": {
    "iso:country":"ES",
    "sg:address":"Avda Uruguay, 8",
    "sg:city":"Benidorm",
    "sg:orig_category":"Electricidad: Instaladores",
    "sg:phone":"+34 965 85 32 28",
    "sg:postcode":"03500",
    "sg:province":"Alicante",
    "wof:name":"Anton Grau Jaime",
    "wof:placetype":"venue"
},
  "geometry": {"coordinates":[-0.1411270052,38.5384368896],"type":"Point"}
}