{
  "type": "Feature",
  "properties": {
    "iso:country":"ES",
    "sg:address":"Cmno Ancho, S/n",
    "sg:city":"Daganzo Arriba",
    "sg:orig_category":"Art\u00cdculos De Limpieza Y De Cocina (fabricaci\u00d3n, Al Por Mayor)",
    "sg:phone":"+34 918 87 55 16",
    "sg:postcode":"28814",
    "sg:province":"Madrid",
    "wof:name":"Fabrica Internacional De Estropajos S.a.",
    "wof:placetype":"venue"
},
  "geometry": {"coordinates":[-3.4572339058,40.5436286926],"type":"Point"}
}