{
  "type": "Feature",
  "properties": {
    "addr:full":"Carrer de Torras I Bages, 32 Cornella Llobregat Barcelona 08940",
    "addr:housenumber":"32",
    "addr:postcode":"08940",
    "addr:street":"Carrer De Torras I Bages",
    "iso:country":"ES",
    "sg:address":"Carrer de Torras I Bages, 32",
    "sg:city":"Cornella Llobregat",
    "sg:orig_category":"Alquiler De Gr\u00daas",
    "sg:phone":"+34 933 75 64 00",
    "sg:postcode":"08940",
    "sg:province":"Barcelona",
    "wof:name":"Mayor Matamoros Ramon",
    "wof:placetype":"venue"
},
  "geometry": {"coordinates":[2.0736529827,41.363407135],"type":"Point"}
}