{
  "type": "Feature",
  "properties": {
    "iso:country":"ES",
    "sg:address":"Carrer de Escornalbou, 39",
    "sg:city":"Barcelona",
    "sg:orig_category":"Suministros Y Materiales Industriales",
    "sg:phone":"+34 934 55 94 07",
    "sg:postcode":"08041",
    "sg:province":"Barcelona",
    "wof:name":"Arroyos Suministros Industriales S. A.",
    "wof:placetype":"venue"
},
  "geometry": {"coordinates":[2.177287817,41.4178466797],"type":"Point"}
}