{
  "type": "Feature",
  "properties": {
    "addr:full":"Plaz Veigui\u00d1a, 46 Marin Pontevedra 36900",
    "addr:housenumber":"46",
    "addr:postcode":"36900",
    "addr:street":"Plaz Veiguin\u0303A",
    "iso:country":"ES",
    "sg:address":"Plaz Veigui\u00d1a, 46",
    "sg:city":"Marin",
    "sg:orig_category":"Agencias Y Agentes Comerciales, Representantes",
    "sg:phone":"+34 986 89 01 53",
    "sg:postcode":"36900",
    "sg:province":"Pontevedra",
    "wof:name":"Pazos Rivas Marcelino",
    "wof:placetype":"venue"
},
  "geometry": {"coordinates":[-8.6881885529,42.391746521],"type":"Point"}
}