{
  "type": "Feature",
  "properties": {
    "addr:full":"Carrer de Viladomat, 45 Barcelona Barcelona 08015",
    "addr:housenumber":"45",
    "addr:postcode":"08015",
    "addr:street":"Carrer De Viladomat",
    "iso:country":"ES",
    "sg:address":"Carrer de Viladomat, 45",
    "sg:city":"Barcelona",
    "sg:orig_category":"Abogados",
    "sg:phone":"+34 934 23 41 52",
    "sg:postcode":"08015",
    "sg:province":"Barcelona",
    "wof:name":"Vega Panizo Pedro",
    "wof:placetype":"venue"
},
  "geometry": {"coordinates":[2.1604750156,41.3771057129],"type":"Point"}
}