{
  "type": "Feature",
  "properties": {
    "iso:country":"ES",
    "sg:address":"Cami Passatemps, 105",
    "sg:city":"Garriga",
    "sg:orig_category":"Inmobiliaria (agencias)",
    "sg:phone":"+34 971 43 53 76",
    "sg:postcode":"07120",
    "sg:province":"Islas Baleares",
    "sg:website":"www.4caires.com",
    "wof:name":"4 Caires Promociones Inmobiliarias S.l.",
    "wof:placetype":"venue"
},
  "geometry": {"coordinates":[2.857711,39.53418],"type":"Point"}
}