{
  "type": "Feature",
  "properties": {
    "addr:full":"Calle de Santander, 4 Parla Madrid 28980",
    "addr:housenumber":"4",
    "addr:postcode":"28980",
    "addr:street":"Calle De Santander",
    "iso:country":"ES",
    "sg:address":"Calle de Santander, 4",
    "sg:city":"Parla",
    "sg:orig_category":"Peluquer\u00cdas, Peluquer\u00cda Mixta",
    "sg:phone":"+34 916 99 58 26",
    "sg:postcode":"28980",
    "sg:province":"Madrid",
    "wof:name":"Gomez Ruiz Waldo",
    "wof:placetype":"venue"
},
  "geometry": {"coordinates":[-3.7649319172,40.2442779541],"type":"Point"}
}