{
  "type": "Feature",
  "properties": {
    "iso:country":"ES",
    "sg:address":"Calle de Espa\u00d1a, 2",
    "sg:city":"Fuengirola",
    "sg:orig_category":"Estilistas Y Estudios De Estilo De Corte Y Confecci\u00d3n",
    "sg:phone":"+34 952 46 00 94",
    "sg:postcode":"29640",
    "sg:province":"M\u00e1laga",
    "wof:name":"Lopez Guirado Jose",
    "wof:placetype":"venue"
},
  "geometry": {"coordinates":[-4.6272587776,36.540687561],"type":"Point"}
}