{
  "type": "Feature",
  "properties": {
    "addr:full":"Calle de Puerto De Lumbreras, 24 Madrid Madrid 28031",
    "addr:housenumber":"24",
    "addr:postcode":"madrid;28031",
    "addr:street":"Calle De Puerto De Lumbreras",
    "iso:country":"ES",
    "sg:address":"Calle de Puerto De Lumbreras, 24",
    "sg:city":"Madrid",
    "sg:orig_category":"Publicidad (soportes Y Gesti\u00d3n)",
    "sg:phone":"+34 913 32 14 55",
    "sg:postcode":"28031",
    "sg:province":"Madrid",
    "wof:name":"Monteagudo Monteagudo Francisco Javier",
    "wof:placetype":"venue"
},
  "geometry": {"coordinates":[-3.6193020344,40.3815765381],"type":"Point"}
}