{
  "type": "Feature",
  "properties": {
    "addr:full":"Plaz Leonardo Da Vinci, 2 Malaga M\u00e1laga 29018",
    "addr:housenumber":"2",
    "addr:postcode":"29018",
    "addr:street":"Plaz Leonardo Da Vinci;Ma\u0301Laga",
    "iso:country":"ES",
    "sg:address":"Plaz Leonardo Da Vinci, 2",
    "sg:city":"Malaga",
    "sg:orig_category":"Empresas De Carpinter\u00cda De Madera",
    "sg:phone":"+34 952 06 03 28",
    "sg:postcode":"29018",
    "sg:province":"M\u00e1laga",
    "wof:name":"Mazari De Epoca S.l.",
    "wof:placetype":"venue"
},
  "geometry": {"coordinates":[-4.3525838852,36.719619751],"type":"Point"}
}