{
  "type": "Feature",
  "properties": {
    "addr:full":"Plaz Cuartel Viejo, 8 Zamora Zamora 49006",
    "addr:housenumber":"8",
    "addr:postcode":"49006",
    "addr:street":"Plaz;Viejo",
    "iso:country":"ES",
    "sg:address":"Plaz Cuartel Viejo, 8",
    "sg:city":"Zamora",
    "sg:orig_category":"Abogados",
    "sg:phone":"+34 980 53 53 11",
    "sg:postcode":"49006",
    "sg:province":"Zamora",
    "wof:name":"Hernandez Ortiz Carmen",
    "wof:placetype":"venue"
},
  "geometry": {"coordinates":[-5.7457342148,41.5033302307],"type":"Point"}
}