{
  "type": "Feature",
  "properties": {
    "iso:country":"ES",
    "sg:address":"Avda Antonio Belon, 16",
    "sg:city":"Marbella",
    "sg:orig_category":"Ense\u00d1anza, Formaci\u00d3n Profesional: Aprendizaje",
    "sg:phone":"+34 952 82 93 02",
    "sg:postcode":"29600",
    "sg:province":"M\u00e1laga",
    "wof:name":"Tesoreria General De La Seguridad Social-servicios Centrales",
    "wof:placetype":"venue"
},
  "geometry": {"coordinates":[-4.888739109,36.5079727173],"type":"Point"}
}