{
  "type": "Feature",
  "properties": {
    "iso:country":"ES",
    "sg:address":"Calle de Arga\u00d1osa, 10",
    "sg:city":"Oviedo",
    "sg:orig_category":"Ropa Para Se\u00d1oras (al Por Menor)",
    "sg:phone":"+34 985 25 77 88",
    "sg:postcode":"33013",
    "sg:province":"Asturias",
    "wof:name":"Fernandez Gonzalez Maria Del Pilar",
    "wof:placetype":"venue"
},
  "geometry": {"coordinates":[-5.8616352081,43.3634872437],"type":"Point"}
}