{
  "type": "Feature",
  "properties": {
    "iso:country":"ES",
    "sg:address":"Calle de Pintor Sorolla, 21",
    "sg:city":"Valencia",
    "sg:orig_category":"Asesor\u00cdas Y Estudios Financieros",
    "sg:phone":"+34 963 52 46 55",
    "sg:postcode":"46002",
    "sg:province":"Valencia",
    "wof:name":"Finanmadrid",
    "wof:placetype":"venue"
},
  "geometry": {"coordinates":[-0.3723349869,39.4715423584],"type":"Point"}
}