{
  "type": "Feature",
  "properties": {
    "addr:full":"Calle de Rafael Alberti, 2 Puerto Serrano C\u00e1diz 11659",
    "addr:housenumber":"2",
    "addr:postcode":"11659",
    "addr:street":"Calle De Rafael Alberti;Ca\u0301Diz",
    "iso:country":"ES",
    "sg:address":"Calle de Rafael Alberti, 2",
    "sg:city":"Puerto Serrano",
    "sg:orig_category":"Sanatorios M\u00c9dico",
    "sg:phone":"+34 956 12 70 29",
    "sg:postcode":"11659",
    "sg:province":"C\u00e1diz",
    "wof:name":"Servicio Andaluz De Salud",
    "wof:placetype":"venue"
},
  "geometry": {"coordinates":[-5.5386190414,36.9203605652],"type":"Point"}
}