{
  "type": "Feature",
  "properties": {
    "iso:country":"ES",
    "sg:address":"Calle de Octavio Cuartero, 15",
    "sg:city":"Villarrobledo",
    "sg:orig_category":"Quincaller\u00cda (al Por Menor)",
    "sg:phone":"+34 967 14 03 73",
    "sg:postcode":"02600",
    "sg:province":"Albacete",
    "wof:name":"Ferreteria Gomez-huedo S.l.",
    "wof:placetype":"venue"
},
  "geometry": {"coordinates":[-2.6065680981,39.2668113708],"type":"Point"}
}