{
  "type": "Feature",
  "properties": {
    "addr:full":"Calle de Sol, 49 Arroyo De La Miel-benalmadena Costa M\u00e1laga 29631",
    "addr:housenumber":"49",
    "addr:postcode":"29631",
    "addr:street":"Calle De Sol;Ma\u0301Laga",
    "iso:country":"ES",
    "sg:address":"Calle de Sol, 49",
    "sg:city":"Arroyo De La Miel-benalmadena Costa",
    "sg:orig_category":"Agencias Y Agentes Comerciales, Representantes",
    "sg:phone":"+34 952 56 48 28",
    "sg:postcode":"29631",
    "sg:province":"M\u00e1laga",
    "wof:name":"Sienne Art S.l.",
    "wof:placetype":"venue"
},
  "geometry": {"coordinates":[-4.5546030998,36.5997428894],"type":"Point"}
}