{
  "type": "Feature",
  "properties": {
    "addr:full":"Carrer de Rourell, 9 Reus Tarragona 43204",
    "addr:housenumber":"9",
    "addr:postcode":"43204",
    "addr:street":"Carrer De Rourell",
    "iso:country":"ES",
    "sg:address":"Carrer de Rourell, 9",
    "sg:city":"Reus",
    "sg:orig_category":"Cajas De Ahorro",
    "sg:phone":"+34 977 75 32 17",
    "sg:postcode":"43204",
    "sg:province":"Tarragona",
    "sg:website":"www.lacaixa.es",
    "wof:name":"Caixa D'estalvis I Pensions De Barcelona",
    "wof:placetype":"venue"
},
  "geometry": {"coordinates":[1.1170860529,41.157699585],"type":"Point"}
}