{
  "type": "Feature",
  "properties": {
    "addr:full":"Carrer de Prades (de), 8 Torreforta Tarragona 43006",
    "addr:postcode":"43006",
    "addr:street":"Carrer De Prades De 8 Torreforta",
    "iso:country":"ES",
    "sg:address":"Carrer de Prades (de), 8",
    "sg:city":"Torreforta",
    "sg:orig_category":"Molduras, Junquillos, Listones Y Molduras Perforadas",
    "sg:phone":"+34 977 54 01 69",
    "sg:postcode":"43006",
    "sg:province":"Tarragona",
    "wof:name":"Prieto Miguel Felix",
    "wof:placetype":"venue"
},
  "geometry": {"coordinates":[1.2171479464,41.1186218262],"type":"Point"}
}