{
  "type": "Feature",
  "properties": {
    "addr:full":"Avda Dos Hermanas, 17 Alcala Guadaira Sevilla 41500",
    "addr:housenumber":"17",
    "addr:postcode":"41500",
    "addr:street":"Avda Dos Hermanas",
    "iso:country":"ES",
    "sg:address":"Avda Dos Hermanas, 17",
    "sg:city":"Alcala Guadaira",
    "sg:orig_category":"Reposter\u00cdas",
    "sg:phone":"+34 955 68 41 12",
    "sg:postcode":"41500",
    "sg:province":"Sevilla",
    "wof:name":"Garcia Rey Antonio",
    "wof:placetype":"venue"
},
  "geometry": {"coordinates":[-5.8398590088,37.3383140564],"type":"Point"}
}