{
  "type": "Feature",
  "properties": {
    "addr:full":"Rbla Principal, 84 Vilanova I La Geltru Barcelona 08800",
    "addr:housenumber":"84",
    "addr:postcode":"08800",
    "addr:street":"Rbla Principal",
    "iso:country":"ES",
    "sg:address":"Rbla Principal, 84",
    "sg:city":"Vilanova I La Geltru",
    "sg:orig_category":"Ropa Para Se\u00d1oras (al Por Menor)",
    "sg:phone":"+34 938 14 31 93",
    "sg:postcode":"08800",
    "sg:province":"Barcelona",
    "sg:website":"www.zara.com",
    "wof:name":"Zara Espa\u00f1a S.a.",
    "wof:placetype":"venue"
},
  "geometry": {"coordinates":[1.7254283428,41.2229652405],"type":"Point"}
}