{
  "type": "Feature",
  "properties": {
    "iso:country":"ES",
    "sg:address":"Ctra Cardedeu, S/n",
    "sg:city":"Corro D'avall",
    "sg:orig_category":"Transporte En General",
    "sg:phone":"+34 902 48 09 02",
    "sg:postcode":"08520",
    "sg:province":"Barcelona",
    "sg:website":"www.frslsa.es",
    "wof:name":"Fr Servicios Logisticos S.a.",
    "wof:placetype":"venue"
},
  "geometry": {"coordinates":[2.2960968018,41.6180877686],"type":"Point"}
}