{
  "type": "Feature",
  "properties": {
    "iso:country":"ES",
    "sg:address":"Plaz Guernica, S/n",
    "sg:city":"San Fernando De Henares",
    "sg:classifiers":[
        {
            "category":"Personal",
            "subcategory":"Barber",
            "type":"Services"
        }
    ],
    "sg:phone":"+34 916 73 13 08",
    "sg:postcode":"28830",
    "sg:province":"Madrid",
    "sg:tags":[
        "caballeros",
        "de",
        "peluqueros"
    ],
    "wof:name":"Pavo Torres David",
    "wof:placetype":"venue"
},
  "geometry": {"coordinates":[-3.5242600441,40.4227523804],"type":"Point"}
}