{
  "type": "Feature",
  "properties": {
    "iso:country":"ES",
    "sg:address":"Calle de Dehesa De Mari-martin, S/n",
    "sg:city":"Dehesa De Marimartin",
    "sg:orig_category":"Electromedicina: Servicios",
    "sg:phone":"+34 918 10 19 10",
    "sg:postcode":"28600",
    "sg:province":"Madrid",
    "wof:name":"Servicios De Instrumentacion Hospitalaria S.l.",
    "wof:placetype":"venue"
},
  "geometry": {"coordinates":[-4.0136671066,40.28490448],"type":"Point"}
}