{
  "type": "Feature",
  "properties": {
    "iso:country":"ES",
    "sg:address":"Avda Andraitx, 1",
    "sg:city":"Matas-pinar-monte Rozas",
    "sg:orig_category":"Importaci\u00d3n",
    "sg:phone":"+34 916 31 96 13",
    "sg:postcode":"28290",
    "sg:province":"Madrid",
    "wof:name":"Rubicas Import-export S.l.",
    "wof:placetype":"venue"
},
  "geometry": {"coordinates":[-3.9011149406,40.5340461731],"type":"Point"}
}