{
  "type": "Feature",
  "properties": {
    "addr:full":"Calle de Sierra Donesteve, 17 Astillero Cantabria 39610",
    "addr:housenumber":"17",
    "addr:postcode":"39610",
    "addr:street":"Calle De Sierra Donesteve",
    "iso:country":"ES",
    "sg:address":"Calle de Sierra Donesteve, 17",
    "sg:city":"Astillero",
    "sg:orig_category":"Art\u00cdculos De Limpieza Y De Cocina (fabricaci\u00d3n, Al Por Mayor)",
    "sg:phone":"+34 942 54 33 29",
    "sg:postcode":"39610",
    "sg:province":"Cantabria",
    "sg:website":"www.suquisa.com",
    "wof:name":"Suquisa S.a.",
    "wof:placetype":"venue"
},
  "geometry": {"coordinates":[-3.8200509548,43.4020729065],"type":"Point"}
}