{
  "type": "Feature",
  "properties": {
    "addr:full":"Carrer de Calabria, 186 Garriga Barcelona 08530",
    "addr:housenumber":"186",
    "addr:postcode":"08530",
    "addr:street":"Carrer De Calabria",
    "iso:country":"ES",
    "sg:address":"Carrer de Calabria, 186",
    "sg:city":"Garriga",
    "sg:orig_category":"Transportes Por V\u00cdas Navegables",
    "sg:phone":"+34 938 71 40 21",
    "sg:postcode":"08530",
    "sg:province":"Barcelona",
    "wof:name":"Segu Soriano Santiago",
    "wof:placetype":"venue"
},
  "geometry": {"coordinates":[2.2866799831,41.6913108826],"type":"Point"}
}