{
  "type": "Feature",
  "properties": {
    "iso:country":"ES",
    "sg:address":"Calle de Princesa Do\u00d1a Sofia, 6",
    "sg:city":"Alcorcon",
    "sg:orig_category":"Telas Y Sedas (al Por Menor)",
    "sg:phone":"+34 916 12 42 85",
    "sg:postcode":"28924",
    "sg:province":"Madrid",
    "wof:name":"Lf Valderas Gestion Inmobiliaria S.l.",
    "wof:placetype":"venue"
},
  "geometry": {"coordinates":[-3.8184258938,40.3499145508],"type":"Point"}
}