{
  "type": "Feature",
  "properties": {
    "addr:full":"Pl. Pio Baroja, 2 Iru\u00f1a Navarra 31008",
    "addr:housenumber":"2",
    "addr:postcode":"31008",
    "addr:street":"Pio Baroja",
    "iso:country":"ES",
    "sg:address":"Pl. Pio Baroja, 2",
    "sg:city":"Iru\u00f1a",
    "sg:orig_category":"Relojer\u00cda (al Por Menor, Reparaci\u00d3n)",
    "sg:phone":"+34 948 17 00 43",
    "sg:postcode":"31008",
    "sg:province":"Navarra",
    "wof:name":"Navarra Tiempo S.l.",
    "wof:placetype":"venue"
},
  "geometry": {"coordinates":[-1.6674469709,42.8127555847],"type":"Point"}
}