{
  "type": "Feature",
  "properties": {
    "iso:country":"ES",
    "sg:address":"Carr Vall De Boi, 7",
    "sg:city":"Lleida",
    "sg:orig_category":"M\u00c9dicos: Cirug\u00cda Ortop\u00c9dica Y Traumatolog\u00cda",
    "sg:phone":"+34 973 24 27 73",
    "sg:postcode":"25198",
    "sg:province":"Lleida",
    "wof:name":"Rocha Sole Martin",
    "wof:placetype":"venue"
},
  "geometry": {"coordinates":[0.6060109735,41.6270332336],"type":"Point"}
}