{
  "type": "Feature",
  "properties": {
    "iso:country":"ES",
    "sg:address":"Pl Sardana (la), 4",
    "sg:city":"Vilafranca Penedes",
    "sg:orig_category":"Inform\u00c1tica (estudios, Servicios, Asesor\u00cda, Formaci\u00d3n)",
    "sg:phone":"+34 938 17 40 25",
    "sg:postcode":"08720",
    "sg:province":"Barcelona",
    "sg:website":"www.gestinet.com",
    "wof:name":"Gestinet Scp",
    "wof:placetype":"venue"
},
  "geometry": {"coordinates":[1.6937167645,41.3447532654],"type":"Point"}
}