{
  "type": "Feature",
  "properties": {
    "addr:full":"Carrer de Santa Rita, 2 Palma Islas Baleares 07014",
    "addr:housenumber":"2",
    "addr:postcode":"07014",
    "addr:street":"Carrer De Santa Rita",
    "iso:country":"ES",
    "sg:address":"Carrer de Santa Rita, 2",
    "sg:city":"Palma",
    "sg:orig_category":"Inversiones",
    "sg:phone":"+34 971 73 25 50",
    "sg:postcode":"07014",
    "sg:province":"Islas Baleares",
    "wof:name":"Invest Moner S.l.",
    "wof:placetype":"venue"
},
  "geometry": {"coordinates":[2.6242349148,39.5659065247],"type":"Point"}
}