{
  "type": "Feature",
  "properties": {
    "iso:country":"ES",
    "sg:address":"Luga Venta Del Rayo, S/n",
    "sg:city":"Venta Rayo",
    "sg:orig_category":"Ropa Y Accesorios",
    "sg:phone":"+34 958 32 03 26",
    "sg:postcode":"18313",
    "sg:province":"Granada",
    "wof:name":"Matas Rey Juan",
    "wof:placetype":"venue"
},
  "geometry": {"coordinates":[-4.2089190483,37.1553192139],"type":"Point"}
}