{
  "type": "Feature",
  "properties": {
    "addr:full":"Calle de Duquesa De La Victoria, 9 Valencia Alcantara C\u00e1ceres 10500",
    "addr:housenumber":"9",
    "addr:postcode":"10500",
    "addr:street":"Calle De Duquesa De La Victoria;Alcantara Ca\u0301Ceres",
    "iso:country":"ES",
    "sg:address":"Calle de Duquesa De La Victoria, 9",
    "sg:city":"Valencia Alcantara",
    "sg:classifiers":[
        {
            "category":"Communications",
            "type":"Services"
        }
    ],
    "sg:phone":"+34 927 58 26 26",
    "sg:postcode":"10500",
    "sg:province":"C\u00e1ceres",
    "sg:tags":[
        "televisiones",
        "y",
        "radio"
    ],
    "sg:website":"www.radiofrontera.net",
    "wof:name":"Sierra De San Pedro Comunicaciones S.l.",
    "wof:placetype":"venue"
},
  "geometry": {"coordinates":[-7.2451472282,39.4101142883],"type":"Point"}
}