{
  "type": "Feature",
  "properties": {
    "addr:full":"A Cachada, S/n Nantes Pontevedra 36969",
    "addr:housenumber":"s / n",
    "addr:postcode":"36969",
    "iso:country":"ES",
    "sg:address":"A Cachada, S/n",
    "sg:city":"Nantes",
    "sg:orig_category":"Dise\u00d1o Industrial",
    "sg:phone":"+34 986 69 12 79",
    "sg:postcode":"36969",
    "sg:province":"Pontevedra",
    "wof:name":"Dapex S.l.",
    "wof:placetype":"venue"
},
  "geometry": {"coordinates":[-8.8211641312,42.4239959717],"type":"Point"}
}