{
  "type": "Feature",
  "properties": {
    "iso:country":"ES",
    "sg:address":"Calle de Cruz (la), 68",
    "sg:city":"Nerja",
    "sg:orig_category":"Estancos",
    "sg:phone":"+34 952 52 12 92",
    "sg:postcode":"29780",
    "sg:province":"M\u00e1laga",
    "wof:name":"Urbano Alonso Rosario",
    "wof:placetype":"venue"
},
  "geometry": {"coordinates":[-3.8785960674,36.7482833862],"type":"Point"}
}