{
  "type": "Feature",
  "properties": {
    "iso:country":"ES",
    "sg:address":"Carrer de Pompeu Fabra, 9",
    "sg:city":"Granollers",
    "sg:orig_category":"Material Y Suministros Para Perforaciones, Sondeos",
    "sg:phone":"+34 938 70 91 21",
    "sg:postcode":"08401",
    "sg:province":"Barcelona",
    "wof:name":"Lorenzo Salado Jose",
    "wof:placetype":"venue"
},
  "geometry": {"coordinates":[2.284537077,41.6086997986],"type":"Point"}
}