{
  "type": "Feature",
  "properties": {
    "addr:full":"Calle de Zaragoza, 20 Boqui\u00f1eni Zaragoza 50641",
    "addr:housenumber":"20",
    "addr:postcode":"50641",
    "addr:street":"Calle De Zaragoza",
    "iso:country":"ES",
    "sg:address":"Calle de Zaragoza, 20",
    "sg:city":"Boqui\u00f1eni",
    "sg:orig_category":"Producci\u00d3n, Venta De Productos De Agricultura Biol\u00d3gica",
    "sg:phone":"+34 976 65 20 55",
    "sg:postcode":"50641",
    "sg:province":"Zaragoza",
    "wof:name":"Latorre Matute Pablo",
    "wof:placetype":"venue"
},
  "geometry": {"coordinates":[-1.2535090446,41.8477401733],"type":"Point"}
}