{
  "type": "Feature",
  "properties": {
    "iso:country":"ES",
    "sg:address":"Plaz San Basilio, 5",
    "sg:city":"Castilleja De Guzman",
    "sg:orig_category":"Ingeniero",
    "sg:phone":"+34 955 72 75 76",
    "sg:postcode":"41908",
    "sg:province":"Sevilla",
    "wof:name":"Hermosin Calderon Eduardo",
    "wof:placetype":"venue"
},
  "geometry": {"coordinates":[-6.0601902008,37.4083137512],"type":"Point"}
}