{
  "type": "Feature",
  "properties": {
    "iso:country":"ES",
    "sg:address":"Calle de Jacinto Benavente, 13",
    "sg:city":"Alhaurin El Grande",
    "sg:orig_category":"Empresarios",
    "sg:phone":"+34 952 49 93 88",
    "sg:postcode":"29120",
    "sg:province":"M\u00e1laga",
    "wof:name":"Construcciones Y Reformas Garyfer S.l.l.",
    "wof:placetype":"venue"
},
  "geometry": {"coordinates":[-4.682185173,36.6411857605],"type":"Point"}
}