{
  "type": "Feature",
  "properties": {
    "addr:full":"Pr Carrasca-carrasca, 13 A Ramallosa Pontevedra 36379",
    "addr:housenumber":"13",
    "addr:postcode":"36379",
    "iso:country":"ES",
    "sg:address":"Pr Carrasca-carrasca, 13",
    "sg:city":"A Ramallosa",
    "sg:orig_category":"Muebles Y Accesorios Para Cocinas Y Cuartos De Ba\u00d1o (al Por Menor)",
    "sg:phone":"+34 986 35 32 62",
    "sg:postcode":"36379",
    "sg:province":"Pontevedra",
    "wof:name":"Juan Alves S.l.",
    "wof:placetype":"venue"
},
  "geometry": {"coordinates":[-8.8134374619,42.1331443787],"type":"Point"}
}