{
  "type": "Feature",
  "properties": {
    "addr:full":"Avda Castrelos, 151 Vigo Pontevedra 36210",
    "addr:housenumber":"151",
    "addr:postcode":"36210",
    "addr:street":"Avda Castrelos",
    "iso:country":"ES",
    "sg:address":"Avda Castrelos, 151",
    "sg:city":"Vigo",
    "sg:orig_category":"Carnicer\u00cdas, Carnicer\u00cdas",
    "sg:phone":"+34 986 29 28 36",
    "sg:postcode":"36210",
    "sg:province":"Pontevedra",
    "wof:name":"Fernandez Soto Maria Cristina",
    "wof:placetype":"venue"
},
  "geometry": {"coordinates":[-8.7305212021,42.2064971924],"type":"Point"}
}