{
  "type": "Feature",
  "properties": {
    "addr:full":"Calle de Tetuan, 6 Alzira Valencia 46600",
    "addr:housenumber":"6",
    "addr:postcode":"46600",
    "addr:street":"Calle De Tetuan",
    "iso:country":"ES",
    "sg:address":"Calle de Tetuan, 6",
    "sg:city":"Alzira",
    "sg:orig_category":"Marroquiner\u00cda (confecci\u00d3n)",
    "sg:phone":"+34 962 40 39 60",
    "sg:postcode":"46600",
    "sg:province":"Valencia",
    "wof:name":"Tassen Leder S.l.",
    "wof:placetype":"venue"
},
  "geometry": {"coordinates":[-0.4335080087,39.1491355896],"type":"Point"}
}