{
  "type": "Feature",
  "properties": {
    "addr:full":"Carrer de Manuel Aza\u00d1a, 10 Palma Islas Baleares 07006",
    "addr:housenumber":"10",
    "addr:postcode":"07006",
    "addr:street":"Carrer De Manuel Azan\u0303A",
    "iso:country":"ES",
    "sg:address":"Carrer de Manuel Aza\u00d1a, 10",
    "sg:city":"Palma",
    "sg:orig_category":"Ense\u00d1anza, Formaci\u00d3n Profesional: Aprendizaje",
    "sg:phone":"+34 971 46 72 12",
    "sg:postcode":"07006",
    "sg:province":"Islas Baleares",
    "wof:name":"Direccion General De Trafico",
    "wof:placetype":"venue"
},
  "geometry": {"coordinates":[2.6649780273,39.5704345703],"type":"Point"}
}