{
  "type": "Feature",
  "properties": {
    "iso:country":"ES",
    "sg:address":"Calle de Argenta, 12",
    "sg:city":"Madrid",
    "sg:orig_category":"Supermercados Y Hipermercados",
    "sg:phone":"+34 913 06 52 67",
    "sg:postcode":"28037",
    "sg:province":"Madrid",
    "wof:name":"Super Volcan S.a.",
    "wof:placetype":"venue"
},
  "geometry": {"coordinates":[-3.6152019501,40.4231109619],"type":"Point"}
}