{
  "type": "Feature",
  "properties": {
    "iso:country":"ES",
    "sg:address":"Calle de Alejandro Casona, 2",
    "sg:city":"Oviedo",
    "sg:orig_category":"Agentes Generales De Seguros",
    "sg:phone":"+34 985 24 07 41",
    "sg:postcode":"33013",
    "sg:province":"Asturias",
    "wof:name":"Ramos Mediadores S.l.",
    "wof:placetype":"venue"
},
  "geometry": {"coordinates":[-5.8642420769,43.3648834229],"type":"Point"}
}