{
  "type": "Feature",
  "properties": {
    "addr:full":"Calle de Independencia, 3 Madrid Madrid 28013",
    "addr:housenumber":"3",
    "addr:postcode":"28013",
    "addr:street":"Calle De Independencia",
    "iso:country":"ES",
    "sg:address":"Calle de Independencia, 3",
    "sg:city":"Madrid",
    "sg:orig_category":"Cueros Y Pieles (al Por Mayor)",
    "sg:phone":"+34 915 47 31 00",
    "sg:postcode":"28013",
    "sg:province":"Madrid",
    "wof:name":"Curtidos Casti\u00d1eira S.l.",
    "wof:placetype":"venue"
},
  "geometry": {"coordinates":[-3.7101719379,40.4177474976],"type":"Point"}
}