{
  "type": "Feature",
  "properties": {
    "addr:full":"Avda Carolinas (as), 92 Vilagarcia Pontevedra 36600",
    "addr:housenumber":"as 92",
    "addr:postcode":"36600",
    "addr:street":"Avda Carolinas",
    "iso:country":"ES",
    "sg:address":"Avda Carolinas (as), 92",
    "sg:city":"Vilagarcia",
    "sg:orig_category":"Jardiner\u00cdas, Vegetales, Art\u00cdculos De Jardiner\u00cda (al Por Menor)",
    "sg:phone":"+34 986 50 50 46",
    "sg:postcode":"36600",
    "sg:province":"Pontevedra",
    "wof:name":"Yonadri S.l.",
    "wof:placetype":"venue"
},
  "geometry": {"coordinates":[-8.7534046173,42.5943336487],"type":"Point"}
}