{
  "type": "Feature",
  "properties": {
    "addr:full":"Calle de Nueva Del Carmen, 52 Valladolid Valladolid 47011",
    "addr:housenumber":"52",
    "addr:postcode":"47011",
    "addr:street":"Calle De Nueva Del Carmen",
    "iso:country":"ES",
    "sg:address":"Calle de Nueva Del Carmen, 52",
    "sg:city":"Valladolid",
    "sg:orig_category":"Transportes Por Carretera: Lotes Completos, Mercanc\u00cdas Diversas",
    "sg:phone":"+34 983 29 04 85",
    "sg:postcode":"47011",
    "sg:province":"Valladolid",
    "wof:name":"Velazquez Arena Maria",
    "wof:placetype":"venue"
},
  "geometry": {"coordinates":[-4.7073121071,41.6562347412],"type":"Point"}
}