{
  "type": "Feature",
  "properties": {
    "iso:country":"ES",
    "sg:address":"Carr Dr Fleming, 54",
    "sg:city":"Balaguer",
    "sg:orig_category":"Panader\u00cdas, Panader\u00cdas",
    "sg:phone":"+34 973 44 54 62",
    "sg:postcode":"25600",
    "sg:province":"Lleida",
    "wof:name":"Sola Barrabes Roser",
    "wof:placetype":"venue"
},
  "geometry": {"coordinates":[0.8102080226,41.7894897461],"type":"Point"}
}