{
  "type": "Feature",
  "properties": {
    "iso:country":"ES",
    "sg:address":"Carr Pare Sanahuja, 35",
    "sg:city":"Balaguer",
    "sg:orig_category":"Asesor\u00cda Sobre Comunicaci\u00d3n De Empresas",
    "sg:phone":"+34 973 44 52 61",
    "sg:postcode":"25600",
    "sg:province":"Lleida",
    "wof:name":"Altisent Assessoria Empresarial S.l.",
    "wof:placetype":"venue"
},
  "geometry": {"coordinates":[0.8102200031,41.7904052734],"type":"Point"}
}