{
  "type": "Feature",
  "properties": {
    "iso:country":"ES",
    "sg:address":"Zelaeta Kalea, 1",
    "sg:city":"Beasain",
    "sg:orig_category":"Peluqueros: De Se\u00d1oras",
    "sg:phone":"+34 943 88 02 97",
    "sg:postcode":"20200",
    "sg:province":"Guip\u00f9zcoa",
    "wof:name":"Alonso Marin Basilisa",
    "wof:placetype":"venue"
},
  "geometry": {"coordinates":[-2.2042756081,43.0469245911],"type":"Point"}
}