{
  "type": "Feature",
  "properties": {
    "iso:country":"ES",
    "sg:address":"Pg Valldaura, 214",
    "sg:city":"Barcelona",
    "sg:orig_category":"Centros M\u00c9dicos Y Sociales, Dispensarios",
    "sg:phone":"+34 933 53 84 22",
    "sg:postcode":"08042",
    "sg:province":"Barcelona",
    "wof:name":"Associacio Centre D'higiene Mental Nou Barris",
    "wof:placetype":"venue"
},
  "geometry": {"coordinates":[2.1668121815,41.4387664795],"type":"Point"}
}