{
  "type": "Feature",
  "properties": {
    "addr:full":"Calle de Alcala, 333 Madrid Madrid 28027",
    "addr:housenumber":"333",
    "addr:postcode":"28027",
    "addr:street":"Calle De Alcala",
    "iso:country":"ES",
    "sg:address":"Calle de Alcala, 333",
    "sg:city":"Madrid",
    "sg:orig_category":"Cristaler\u00cdas",
    "sg:phone":"+34 914 03 55 85",
    "sg:postcode":"28027",
    "sg:province":"Madrid",
    "wof:name":"Barbero Barbero Jose",
    "wof:placetype":"venue"
},
  "geometry": {"coordinates":[-3.6489698887,40.4330177307],"type":"Point"}
}