{
  "type": "Feature",
  "properties": {
    "iso:country":"ES",
    "sg:address":"Carrer de Mossen Jacint Verdaguer, 10",
    "sg:city":"Santa Anna-tio",
    "sg:orig_category":"Pintura Y Barniz (al Por Menor)",
    "sg:phone":"+34 937 52 46 51",
    "sg:postcode":"08338",
    "sg:province":"Barcelona",
    "wof:name":"Costa Raurell Montserrat",
    "wof:placetype":"venue"
},
  "geometry": {"coordinates":[2.3460769653,41.505153656],"type":"Point"}
}