{
  "type": "Feature",
  "properties": {
    "addr:full":"A Cruz, Km. 0028,0 Chapa Pontevedra 36570",
    "addr:postcode":"36570",
    "addr:street":"Km. 0028,0",
    "iso:country":"ES",
    "sg:address":"A Cruz, Km. 0028,0",
    "sg:city":"Chapa",
    "sg:orig_category":"Distribuci\u00d3n De Petr\u00d3leo Y Derivados",
    "sg:phone":"+34 986 68 18 55",
    "sg:postcode":"36570",
    "sg:province":"Pontevedra",
    "wof:name":"Galpgest Petrogal Estaciones De Servicio S.l.u.",
    "wof:placetype":"venue"
},
  "geometry": {"coordinates":[-8.2833299637,42.71667099],"type":"Point"}
}