{
  "type": "Feature",
  "properties": {
    "addr:full":"Av Marques De L'argentera, 17 Barcelona Barcelona 08003",
    "addr:housenumber":"17",
    "addr:postcode":"08003",
    "addr:street":"Av Marques De L'Argentera",
    "iso:country":"ES",
    "sg:address":"Av Marques De L'argentera, 17",
    "sg:city":"Barcelona",
    "sg:classifiers":[
        {
            "category":"Professional",
            "subcategory":"Management & Consulting",
            "type":"Services"
        }
    ],
    "sg:phone":"+34 932 68 28 09",
    "sg:postcode":"08003",
    "sg:province":"Barcelona",
    "sg:tags":[
        "asesor\u00cda",
        "en",
        "marketing"
    ],
    "sg:website":"www.lilacom.com",
    "wof:name":"Lilacom Strategic Consulting S.l.",
    "wof:placetype":"venue"
},
  "geometry": {"coordinates":[2.1849896908,41.3847579956],"type":"Point"}
}