{
  "type": "Feature",
  "properties": {
    "iso:country":"ES",
    "sg:address":"Calle de Maltesa La, 27",
    "sg:city":"Malaga",
    "sg:orig_category":"Asociaciones, Organismos Culturales Y Socioeducativos",
    "sg:phone":"+34 952 10 71 87",
    "sg:postcode":"29190",
    "sg:province":"M\u00e1laga",
    "wof:name":"Bravo Martin Manuel",
    "wof:placetype":"venue"
},
  "geometry": {"coordinates":[-4.4799427986,36.7411842346],"type":"Point"}
}