{
  "type": "Feature",
  "properties": {
    "addr:full":"Calle de Honduras, 4 Valladolid Valladolid 47014",
    "addr:housenumber":"4",
    "addr:postcode":"47014",
    "addr:street":"Calle De Honduras",
    "iso:country":"ES",
    "sg:address":"Calle de Honduras, 4",
    "sg:city":"Valladolid",
    "sg:orig_category":"Librer\u00cdas",
    "sg:phone":"+34 983 47 50 02",
    "sg:postcode":"47014",
    "sg:province":"Valladolid",
    "wof:name":"Ruiz Viruega Amador",
    "wof:placetype":"venue"
},
  "geometry": {"coordinates":[-4.7513217926,41.6308250427],"type":"Point"}
}