{
  "type": "Feature",
  "properties": {
    "addr:full":"Calle de Redondilla, 8 Madrid Madrid 28005",
    "addr:housenumber":"8",
    "addr:postcode":"madrid;28005",
    "addr:street":"Calle De Redondilla",
    "iso:country":"ES",
    "sg:address":"Calle de Redondilla, 8",
    "sg:city":"Madrid",
    "sg:orig_category":"Compraventa De Antig\u00dcedades",
    "sg:phone":"+34 913 54 01 76",
    "sg:postcode":"28005",
    "sg:province":"Madrid",
    "wof:name":"Pons Mallol Marcos Gabriel",
    "wof:placetype":"venue"
},
  "geometry": {"coordinates":[-3.7126700878,40.4126319885],"type":"Point"}
}