{
  "type": "Feature",
  "properties": {
    "iso:country":"ES",
    "sg:address":"Avgd Artesa, 1",
    "sg:city":"Lleida",
    "sg:orig_category":"Florister\u00cdas",
    "sg:phone":"+34 973 20 32 27",
    "sg:postcode":"25001",
    "sg:province":"Lleida",
    "wof:name":"Cuadrat Borrell Juan Claudio",
    "wof:placetype":"venue"
},
  "geometry": {"coordinates":[0.6413710117,41.6041603088],"type":"Point"}
}