{
  "type": "Feature",
  "properties": {
    "addr:full":"Puerta De Granada, 10 Velez-rubio Almer\u00eda 04820",
    "addr:housenumber":"10",
    "addr:postcode":"04820",
    "addr:street":"Granada;Almeri\u0301A",
    "iso:country":"ES",
    "sg:address":"Puerta De Granada, 10",
    "sg:city":"Velez-rubio",
    "sg:orig_category":"Molduras, Junquillos, Listones Y Molduras Perforadas",
    "sg:phone":"+34 950 41 11 06",
    "sg:postcode":"04820",
    "sg:province":"Almer\u00eda",
    "wof:name":"Perez Rodriguez Juan",
    "wof:placetype":"venue"
},
  "geometry": {"coordinates":[-2.0759010315,37.6507453918],"type":"Point"}
}