{
  "type": "Feature",
  "properties": {
    "iso:country":"ES",
    "sg:address":"Avda San Diego, 111",
    "sg:city":"Madrid",
    "sg:orig_category":"Bazares, Art\u00cdculos De Limpieza Y De Cocina (al Por Menor)",
    "sg:phone":"+34 917 86 20 20",
    "sg:postcode":"28018",
    "sg:province":"Madrid",
    "wof:name":"Zhao  Guanqing",
    "wof:placetype":"venue"
},
  "geometry": {"coordinates":[-3.6640975475,40.3825492859],"type":"Point"}
}