{
  "type": "Feature",
  "properties": {
    "iso:country":"ES",
    "sg:address":"Pla\u00c7 Major, 1",
    "sg:city":"Santa Pau",
    "sg:orig_category":"Oficinas De Turismo, Asociaciones De Iniciativa",
    "sg:phone":"+34 972 68 03 49",
    "sg:postcode":"17811",
    "sg:province":"Girona",
    "wof:name":"Ajuntament De Santa Pau",
    "wof:placetype":"venue"
},
  "geometry": {"coordinates":[2.5693337917,42.1582260132],"type":"Point"}
}