{
  "type": "Feature",
  "properties": {
    "addr:full":"Ctra Carretera Carrion (poligono Industrial), 23 Ciudad Real Ciudad Real 13005",
    "addr:housenumber":"23",
    "addr:postcode":"13005",
    "addr:street":"Ctra Carretera Carrion Poligono Industrial",
    "iso:country":"ES",
    "sg:address":"Ctra Carretera Carrion (poligono Industrial), 23",
    "sg:city":"Ciudad Real",
    "sg:orig_category":"Materiales De Construcci\u00d3n, Herramientas",
    "sg:phone":"+34 926 22 37 87",
    "sg:postcode":"13005",
    "sg:province":"Ciudad Real",
    "sg:website":"www.remolquesfrancis.com",
    "wof:name":"Francisk S.a",
    "wof:placetype":"venue"
},
  "geometry": {"coordinates":[-3.9525969028,38.9611473083],"type":"Point"}
}