{
  "type": "Feature",
  "properties": {
    "addr:full":"Calle de San Carlos, 1 Burgos Burgos 09003",
    "addr:housenumber":"1",
    "addr:postcode":"09003",
    "addr:street":"Calle De San Carlos",
    "iso:country":"ES",
    "sg:address":"Calle de San Carlos, 1",
    "sg:city":"Burgos",
    "sg:orig_category":"Panader\u00cdas, Panader\u00cdas",
    "sg:phone":"+34 947 20 42 90",
    "sg:postcode":"09003",
    "sg:province":"Burgos",
    "wof:name":"Panaderia Ricardo Y Jaime Camara S. L.",
    "wof:placetype":"venue"
},
  "geometry": {"coordinates":[-3.7009620667,42.3421936035],"type":"Point"}
}