{
  "type": "Feature",
  "properties": {
    "iso:country":"ES",
    "sg:address":"Calle de Gregorio Mendibil, 10",
    "sg:city":"Amorebieta",
    "sg:orig_category":"Camiser\u00cda Y Ropa Interior Masculina (al Por Menor)",
    "sg:phone":"+34 946 73 39 07",
    "sg:postcode":"48340",
    "sg:province":"Vizcaya",
    "wof:name":"Alvarez Sig\u00fcenza Miren Itxaso",
    "wof:placetype":"venue"
},
  "geometry": {"coordinates":[-2.7306330204,43.2190246582],"type":"Point"}
}