{
  "type": "Feature",
  "properties": {
    "iso:country":"ES",
    "sg:address":"Calle de Torre De Romo, 54",
    "sg:city":"Carmen",
    "sg:orig_category":"Muebles Y Accesorios Para Cocinas Y Cuartos De Ba\u00d1o (al Por Menor)",
    "sg:phone":"+34 968 26 14 04",
    "sg:postcode":"30011",
    "sg:province":"Murcia",
    "wof:name":"Sanchez Mu\u00f1oz Miguel",
    "wof:placetype":"venue"
},
  "geometry": {"coordinates":[-1.1055790186,37.9783668518],"type":"Point"}
}