{
  "type": "Feature",
  "properties": {
    "addr:full":"Carrer de Minerva, 21 Barcelona Barcelona 08006",
    "addr:housenumber":"21",
    "addr:postcode":"08006",
    "addr:street":"Carrer De Minerva",
    "iso:country":"ES",
    "sg:address":"Carrer de Minerva, 21",
    "sg:city":"Barcelona",
    "sg:orig_category":"Ropa Para Se\u00d1oras (al Por Menor)",
    "sg:phone":"+34 934 15 99 98",
    "sg:postcode":"08006",
    "sg:province":"Barcelona",
    "wof:name":"Delgado Alberti Lydia",
    "wof:placetype":"venue"
},
  "geometry": {"coordinates":[2.1556620598,41.3969650269],"type":"Point"}
}