{
  "type": "Feature",
  "properties": {
    "addr:full":"Plaz Duque (del), 13 Caceres C\u00e1ceres 10003",
    "addr:postcode":"10003",
    "addr:street":"Ca\u0301Ceres",
    "iso:country":"ES",
    "sg:address":"Plaz Duque (del), 13",
    "sg:city":"Caceres",
    "sg:orig_category":"Internados & Ense\u00d1anza Privada",
    "sg:phone":"+34 927 24 64 84",
    "sg:postcode":"10003",
    "sg:province":"C\u00e1ceres",
    "wof:name":"Hijas De Cristo Rey",
    "wof:placetype":"venue"
},
  "geometry": {"coordinates":[-6.3720030785,39.4745063782],"type":"Point"}
}