{
  "type": "Feature",
  "properties": {
    "addr:full":"Carrer de Gravina, 38 Tarragona Tarragona 43004",
    "addr:housenumber":"38",
    "addr:postcode":"43004",
    "addr:street":"Carrer De Gravina",
    "iso:country":"ES",
    "sg:address":"Carrer de Gravina, 38",
    "sg:city":"Tarragona",
    "sg:orig_category":"Carnicer\u00cdas, Carnicer\u00cdas",
    "sg:phone":"+34 977 22 14 28",
    "sg:postcode":"43004",
    "sg:province":"Tarragona",
    "wof:name":"La Fruiteria S.c.p.",
    "wof:placetype":"venue"
},
  "geometry": {"coordinates":[1.2409009933,41.1096687317],"type":"Point"}
}