{
  "type": "Feature",
  "properties": {
    "iso:country":"ES",
    "sg:address":"Calle de San Pablo, 5",
    "sg:city":"Cordoba",
    "sg:orig_category":"Material Y Suministros Para Peluquer\u00cda",
    "sg:phone":"+34 957 47 85 94",
    "sg:postcode":"14002",
    "sg:province":"C\u00f3rdoba",
    "wof:name":"Sanchez Molina Carmen",
    "wof:placetype":"venue"
},
  "geometry": {"coordinates":[-4.7755899429,37.8858413696],"type":"Point"}
}