{
  "type": "Feature",
  "properties": {
    "addr:full":"Calle de Doctor Juan Bravo, 11 Madrid Madrid 28034",
    "addr:housenumber":"11",
    "addr:postcode":"madrid;28034",
    "addr:street":"Calle De Doctor Juan Bravo",
    "iso:country":"ES",
    "sg:address":"Calle de Doctor Juan Bravo, 11",
    "sg:city":"Madrid",
    "sg:orig_category":"Quincaller\u00cda (al Por Menor)",
    "sg:phone":"+34 917 34 04 70",
    "sg:postcode":"28034",
    "sg:province":"Madrid",
    "wof:name":"Lopez Magano Santiago",
    "wof:placetype":"venue"
},
  "geometry": {"coordinates":[-3.6876022816,40.4934043884],"type":"Point"}
}