{
  "type": "Feature",
  "properties": {
    "addr:full":"Avda Julio Rodriguez Soto, 14 Carballi\u00f1o Ourense 32500",
    "addr:housenumber":"14",
    "addr:postcode":"32500",
    "addr:street":"Avda Julio;Soto",
    "iso:country":"ES",
    "sg:address":"Avda Julio Rodriguez Soto, 14",
    "sg:city":"Carballi\u00f1o",
    "sg:orig_category":"Perfumer\u00cda, Art\u00cdculos De Ba\u00d1o (fabricaci\u00d3n, Al Por Mayor)",
    "sg:phone":"+34 988 27 51 96",
    "sg:postcode":"32500",
    "sg:province":"Ourense",
    "wof:name":"Hogarlin S. A.",
    "wof:placetype":"venue"
},
  "geometry": {"coordinates":[-8.0806064606,42.4287452698],"type":"Point"}
}