{
  "type": "Feature",
  "properties": {
    "iso:country":"ES",
    "sg:address":"Avgd Pearson, 47",
    "sg:city":"Lleida",
    "sg:orig_category":"Inform\u00c1tica (estudios, Servicios, Asesor\u00cda, Formaci\u00d3n)",
    "sg:phone":"+34 973 22 80 80",
    "sg:postcode":"25005",
    "sg:province":"Lleida",
    "wof:name":"Software I Tecnologia De Lleida S.l.",
    "wof:placetype":"venue"
},
  "geometry": {"coordinates":[0.6418629885,41.6275405884],"type":"Point"}
}