{
  "type": "Feature",
  "properties": {
    "iso:country":"ES",
    "sg:address":"Calle de Soledad, S/n",
    "sg:city":"Valencia",
    "sg:orig_category":"Confecci\u00d3n De Trajes Para Se\u00d1oras",
    "sg:phone":"+34 963 94 17 89",
    "sg:postcode":"46002",
    "sg:province":"Valencia",
    "wof:name":"Salva 10 S.l.",
    "wof:placetype":"venue"
},
  "geometry": {"coordinates":[-0.3737730086,39.4716453552],"type":"Point"}
}