{
  "type": "Feature",
  "properties": {
    "iso:country":"ES",
    "sg:address":"Calle de Lisboa, 18",
    "sg:city":"Toledo",
    "sg:orig_category":"Cer\u00c1mica Art\u00cdstica Y Decorativa",
    "sg:phone":"+34 925 25 01 81",
    "sg:postcode":"45005",
    "sg:province":"Toledo",
    "wof:name":"Cal Barreira Maria Jesus De La",
    "wof:placetype":"venue"
},
  "geometry": {"coordinates":[-4.0336561203,39.8745574951],"type":"Point"}
}