{
  "type": "Feature",
  "properties": {
    "addr:full":"Calle de Damasco, 1 Cordoba C\u00f3rdoba 14004",
    "addr:housenumber":"1",
    "addr:postcode":"14004",
    "addr:street":"Calle De Damasco;Co\u0301Rdoba",
    "iso:country":"ES",
    "sg:address":"Calle de Damasco, 1",
    "sg:city":"Cordoba",
    "sg:orig_category":"Ropa Y Accesorios",
    "sg:phone":"+34 957 23 17 57",
    "sg:postcode":"14004",
    "sg:province":"C\u00f3rdoba",
    "wof:name":"Arizona Jeans S.coop.and.",
    "wof:placetype":"venue"
},
  "geometry": {"coordinates":[-4.7903652191,37.8811340332],"type":"Point"}
}