{
  "type": "Feature",
  "properties": {
    "addr:full":"Calle de Sanchez Barcaiztegui, 19 Madrid Madrid 28007",
    "addr:housenumber":"19",
    "addr:postcode":"madrid;28007",
    "addr:street":"Calle De Sanchez Barcaiztegui",
    "iso:country":"ES",
    "sg:address":"Calle de Sanchez Barcaiztegui, 19",
    "sg:city":"Madrid",
    "sg:orig_category":"Art\u00cdculos De Regalo (al Por Menor)",
    "sg:phone":"+34 914 33 75 86",
    "sg:postcode":"28007",
    "sg:province":"Madrid",
    "wof:name":"Chang Si Alan",
    "wof:placetype":"venue"
},
  "geometry": {"coordinates":[-3.6749351025,40.4039230347],"type":"Point"}
}