{
  "type": "Feature",
  "properties": {
    "addr:full":"Calle de Imagen, 6 Sevilla Sevilla 41003",
    "addr:housenumber":"6",
    "addr:postcode":"41003",
    "addr:street":"Calle De Imagen",
    "iso:country":"ES",
    "sg:address":"Calle de Imagen, 6",
    "sg:city":"Sevilla",
    "sg:orig_category":"Ense\u00d1anza, Formaci\u00d3n Profesional: Aprendizaje",
    "sg:phone":"+34 954 50 28 15",
    "sg:postcode":"41003",
    "sg:province":"Sevilla",
    "wof:name":"Iassa S.a.",
    "wof:placetype":"venue"
},
  "geometry": {"coordinates":[-5.9900012016,37.3926086426],"type":"Point"}
}