{
  "type": "Feature",
  "properties": {
    "iso:country":"ES",
    "sg:address":"L Poligono Comarca I, 6",
    "sg:city":"Orkoien",
    "sg:orig_category":"Contenedores (mercanc\u00cdas)",
    "sg:phone":"+34 948 32 17 92",
    "sg:postcode":"31160",
    "sg:province":"Navarra",
    "wof:name":"Tdn Norte S.a.",
    "wof:placetype":"venue"
},
  "geometry": {"coordinates":[-1.7060990334,42.8219032288],"type":"Point"}
}