{
  "type": "Feature",
  "properties": {
    "iso:country":"ES",
    "sg:address":"Avda Calvo Sotelo, 5",
    "sg:city":"Beniel",
    "sg:orig_category":"M\u00c9dicos: Estomatolog\u00cda",
    "sg:phone":"+34 968 60 04 03",
    "sg:postcode":"30130",
    "sg:province":"Murcia",
    "wof:name":"Centro Dental Universidad, S.l.",
    "wof:placetype":"venue"
},
  "geometry": {"coordinates":[-1.0025080442,38.045539856],"type":"Point"}
}