{
  "type": "Feature",
  "properties": {
    "iso:country":"ES",
    "sg:address":"Calle de Virgen De Los Desamparados, 87",
    "sg:city":"Novelda",
    "sg:orig_category":"Negocio De Materiales De Construcci\u00d3n",
    "sg:phone":"+34 965 60 11 73",
    "sg:postcode":"03660",
    "sg:province":"Alicante",
    "wof:name":"Hijos De Pellin S. L.",
    "wof:placetype":"venue"
},
  "geometry": {"coordinates":[-0.7680609822,38.382850647],"type":"Point"}
}