{
  "type": "Feature",
  "properties": {
    "addr:full":"Calle de Castilla, 7 Monzon Huesca 22400",
    "addr:housenumber":"7",
    "addr:postcode":"22400",
    "addr:street":"Calle De Castilla",
    "iso:country":"ES",
    "sg:address":"Calle de Castilla, 7",
    "sg:city":"Monzon",
    "sg:orig_category":"Instalaci\u00d3n, Reparaci\u00d3n De Ascensores Y Montacargas",
    "sg:phone":"+34 974 40 16 19",
    "sg:postcode":"22400",
    "sg:province":"Huesca",
    "wof:name":"Ascensores Marvi S. L.",
    "wof:placetype":"venue"
},
  "geometry": {"coordinates":[0.1918208003,41.9145774841],"type":"Point"}
}