{
  "type": "Feature",
  "properties": {
    "addr:full":"Cra. Castellvell, S/n Castellvell Camp Tarragona 43392",
    "addr:postcode":"43392",
    "addr:street":"Castellvell S / N Castellvell",
    "iso:country":"ES",
    "sg:address":"Cra. Castellvell, S/n",
    "sg:city":"Castellvell Camp",
    "sg:orig_category":"Cerrajer\u00cda, Ferrallista",
    "sg:phone":"+34 977 76 20 94",
    "sg:postcode":"43392",
    "sg:province":"Tarragona",
    "wof:name":"Berbel Granados Francisco",
    "wof:placetype":"venue"
},
  "geometry": {"coordinates":[1.0993720293,41.1803131104],"type":"Point"}
}