{
  "type": "Feature",
  "properties": {
    "iso:country":"ES",
    "sg:address":"Avda Constitucion, 83",
    "sg:city":"Cari\u00f1o",
    "sg:orig_category":"Supermercados Y Hipermercados",
    "sg:phone":"+34 981 42 04 38",
    "sg:postcode":"15360",
    "sg:province":"La Coru\u00f1a",
    "wof:name":"Lopez Montero Antonio",
    "wof:placetype":"venue"
},
  "geometry": {"coordinates":[-7.8746380806,43.7366409302],"type":"Point"}
}