{
  "type": "Feature",
  "properties": {
    "iso:country":"ES",
    "sg:address":"Avda Castilla-la Mancha (de), 1",
    "sg:city":"Cuenca",
    "sg:orig_category":"Carnicer\u00cdas, Carnicer\u00cdas",
    "sg:phone":"+34 969 23 67 57",
    "sg:postcode":"16003",
    "sg:province":"Cuenca",
    "wof:name":"Bermejo Gomez Luciano",
    "wof:placetype":"venue"
},
  "geometry": {"coordinates":[-2.1372089386,40.0704116821],"type":"Point"}
}