{
  "type": "Feature",
  "properties": {
    "iso:country":"ES",
    "sg:address":"Calle de Real, 57",
    "sg:city":"Rozas De Madrid",
    "sg:orig_category":"Fisioterapia",
    "sg:phone":"+34 916 37 54 95",
    "sg:postcode":"28230",
    "sg:province":"Madrid",
    "wof:name":"Minguez-yugueros Gonsalves Ignacio Augusto",
    "wof:placetype":"venue"
},
  "geometry": {"coordinates":[-3.8694489002,40.4907455444],"type":"Point"}
}