{
  "type": "Feature",
  "properties": {
    "iso:country":"ES",
    "sg:address":"Calle de Virgen De Lujan, 45",
    "sg:city":"Sevilla",
    "sg:orig_category":"Alquiler De Casas Y Habitaciones Amuebladas",
    "sg:phone":"+34 954 45 06 10",
    "sg:postcode":"41011",
    "sg:province":"Sevilla",
    "wof:name":"Rico Rico Bernabe",
    "wof:placetype":"venue"
},
  "geometry": {"coordinates":[-6.0020999908,37.3769607544],"type":"Point"}
}