{
  "type": "Feature",
  "properties": {
    "addr:full":"Calle de Jucar, 9 Bosque Madrid 28670",
    "addr:housenumber":"9",
    "addr:postcode":"28670",
    "addr:street":"Calle De Jucar",
    "iso:country":"ES",
    "sg:address":"Calle de Jucar, 9",
    "sg:city":"Bosque",
    "sg:orig_category":"Asesor\u00cda Fiscal Y Jur\u00cddica",
    "sg:phone":"+34 916 04 49 24",
    "sg:postcode":"28670",
    "sg:province":"Madrid",
    "wof:name":"Magan Consultores S.l",
    "wof:placetype":"venue"
},
  "geometry": {"coordinates":[-3.923715353,40.3910675049],"type":"Point"}
}