{
  "type": "Feature",
  "properties": {
    "addr:full":"Calle de Jeronimo Hernandez, 3 Sevilla Sevilla 41003",
    "addr:housenumber":"3",
    "addr:postcode":"41003",
    "addr:street":"Calle De Jeronimo Hernandez",
    "iso:country":"ES",
    "sg:address":"Calle de Jeronimo Hernandez, 3",
    "sg:city":"Sevilla",
    "sg:orig_category":"M\u00c9dicos: Geriatr\u00cda, Gerontolog\u00cda (enfermedades De La Tercera Edad)",
    "sg:phone":"+34 954 22 43 67",
    "sg:postcode":"41003",
    "sg:province":"Sevilla",
    "wof:name":"J.v. Tahona S.l.",
    "wof:placetype":"venue"
},
  "geometry": {"coordinates":[-5.9921159744,37.3946075439],"type":"Point"}
}