{
  "type": "Feature",
  "properties": {
    "iso:country":"ES",
    "sg:address":"Avda Cuenca, 26",
    "sg:city":"Benidorm",
    "sg:orig_category":"Inmobiliaria (agencias)",
    "sg:phone":"+34 966 83 08 03",
    "sg:postcode":"03500",
    "sg:province":"Alicante",
    "wof:name":"Ben Loix S.a.",
    "wof:placetype":"venue"
},
  "geometry": {"coordinates":[-0.1169570014,38.5427856445],"type":"Point"}
}