{
  "type": "Feature",
  "properties": {
    "iso:country":"ES",
    "sg:address":"Carrer de Dolca De Provenca, 2",
    "sg:city":"Barcelona",
    "sg:orig_category":"Molduras, Junquillos, Listones Y Molduras Perforadas",
    "sg:phone":"+34 932 78 15 07",
    "sg:postcode":"08020",
    "sg:province":"Barcelona",
    "wof:name":"Santiago Fuentes Antonio",
    "wof:placetype":"venue"
},
  "geometry": {"coordinates":[2.2055420876,41.4203414917],"type":"Point"}
}