{
  "type": "Feature",
  "properties": {
    "iso:country":"ES",
    "sg:address":"Granada-benamara, 1",
    "sg:city":"Estepona",
    "sg:orig_category":"Ense\u00d1anza Variada",
    "sg:phone":"+34 952 88 62 63",
    "sg:postcode":"29680",
    "sg:province":"M\u00e1laga",
    "wof:name":"Meseir Academia S.l.",
    "wof:placetype":"venue"
},
  "geometry": {"coordinates":[-5.1452140808,36.4275817871],"type":"Point"}
}