{
  "type": "Feature",
  "properties": {
    "iso:country":"ES",
    "sg:address":"Pol. Ind. La Vega, 9",
    "sg:city":"Tordesillas",
    "sg:orig_category":"Transportes Por V\u00cdas Navegables",
    "sg:phone":"+34 983 79 61 48",
    "sg:postcode":"47100",
    "sg:province":"Valladolid",
    "wof:name":"Transramos E Hijos S.l.",
    "wof:placetype":"venue"
},
  "geometry": {"coordinates":[-4.9989957809,41.5035095215],"type":"Point"}
}