{
  "type": "Feature",
  "properties": {
    "addr:full":"Canalejas, 3 Negreira La Coru\u00f1a 15830",
    "addr:housenumber":"3",
    "addr:postcode":"15830",
    "addr:street":"Canalejas;La Corun\u0303A",
    "iso:country":"ES",
    "sg:address":"Canalejas, 3",
    "sg:city":"Negreira",
    "sg:orig_category":"Electrodom\u00c9sticos (al Por Menor)",
    "sg:phone":"+34 981 88 50 85",
    "sg:postcode":"15830",
    "sg:province":"La Coru\u00f1a",
    "wof:name":"Caama\u00f1o Pose Jose",
    "wof:placetype":"venue"
},
  "geometry": {"coordinates":[-8.7368841171,42.9089660645],"type":"Point"}
}