{
  "type": "Feature",
  "properties": {
    "addr:full":"Rua Condesa, 25 Noia La Coru\u00f1a 15200",
    "addr:housenumber":"25",
    "addr:postcode":"15200",
    "addr:street":"Rua Condesa;La Corun\u0303A",
    "iso:country":"ES",
    "sg:address":"Rua Condesa, 25",
    "sg:city":"Noia",
    "sg:orig_category":"Electricidad: Instaladores",
    "sg:phone":"+34 981 82 09 10",
    "sg:postcode":"15200",
    "sg:province":"La Coru\u00f1a",
    "wof:name":"Blanco Sendon Manuel",
    "wof:placetype":"venue"
},
  "geometry": {"coordinates":[-8.889093399,42.782749176],"type":"Point"}
}