{
  "type": "Feature",
  "properties": {
    "addr:full":"Calle de General Serrano, 28 Santa Cruz De Tenerife Santa Cruz De Tenerife 38004",
    "addr:housenumber":"28",
    "addr:postcode":"38004",
    "addr:street":"Calle De General Serrano",
    "iso:country":"ES",
    "sg:address":"Calle de General Serrano, 28",
    "sg:city":"Santa Cruz De Tenerife",
    "sg:orig_category":"M\u00c9dicos: Anatom\u00cda Patol\u00d3gica Y Citolog\u00cda",
    "sg:phone":"+34 922 24 62 07",
    "sg:postcode":"38004",
    "sg:province":"Santa Cruz De Tenerife",
    "wof:name":"Centro De Anatomia Patologica S.l.",
    "wof:placetype":"venue"
},
  "geometry": {"coordinates":[-16.2575454712,28.4663944244],"type":"Point"}
}