{
  "type": "Feature",
  "properties": {
    "addr:full":"Pl. Onze De Setembre, S/n S. Vicen\u00e7 Horts Barcelona 08620",
    "addr:housenumber":"s",
    "addr:postcode":"08620",
    "addr:street":"Onze;Setembre;/ N S. Vicenc\u0327 Horts Barcelona",
    "iso:country":"ES",
    "sg:address":"Pl. Onze De Setembre, S/n",
    "sg:city":"S. Vicen\u00e7 Horts",
    "sg:orig_category":"Fabricaci\u00d3n De Bebidas No Alcoh\u00d3licas",
    "sg:phone":"+34 936 56 59 09",
    "sg:postcode":"08620",
    "sg:province":"Barcelona",
    "wof:name":"Vinader Perez Pedro",
    "wof:placetype":"venue"
},
  "geometry": {"coordinates":[2.0066800117,41.3997459412],"type":"Point"}
}