{
  "type": "Feature",
  "properties": {
    "iso:country":"ES",
    "sg:address":"Avda Camilo Jose Cela, 50",
    "sg:city":"Elda",
    "sg:orig_category":"Zapatos: Material, Suministros, Accesorios (fabricaci\u00d3n, Al Por Mayor)",
    "sg:phone":"+34 965 38 65 64",
    "sg:postcode":"03600",
    "sg:province":"Alicante",
    "wof:name":"Florencia Marco S.l.",
    "wof:placetype":"venue"
},
  "geometry": {"coordinates":[-0.7982620001,38.4699440002],"type":"Point"}
}