{
  "type": "Feature",
  "properties": {
    "addr:full":"Carrer de Major, 3 Cardona Barcelona 08261",
    "addr:housenumber":"3",
    "addr:postcode":"08261",
    "addr:street":"Carrer De Major",
    "iso:country":"ES",
    "sg:address":"Carrer de Major, 3",
    "sg:city":"Cardona",
    "sg:orig_category":"Poller\u00cda Y Caza (al Por Menor)",
    "sg:phone":"+34 938 69 18 64",
    "sg:postcode":"08261",
    "sg:province":"Barcelona",
    "wof:name":"Simon Carre\u00f1o Pilar",
    "wof:placetype":"venue"
},
  "geometry": {"coordinates":[1.6806900501,41.9140281677],"type":"Point"}
}