{
  "type": "Feature",
  "properties": {
    "iso:country":"ES",
    "sg:address":"Calle de Arkale, 8",
    "sg:city":"Irun",
    "sg:orig_category":"Alumbrados",
    "sg:phone":"+34 943 61 58 78",
    "sg:postcode":"20303",
    "sg:province":"Guip\u00f9zcoa",
    "wof:name":"Ihi Interdifusion S.l.",
    "wof:placetype":"venue"
},
  "geometry": {"coordinates":[-1.8001791239,43.3366699219],"type":"Point"}
}