{
  "type": "Feature",
  "properties": {
    "iso:country":"ES",
    "sg:address":"Calle de Real, 187",
    "sg:city":"Fuensanta Martos",
    "sg:orig_category":"Caf\u00c9s, Bares, Cervecer\u00cdas",
    "sg:phone":"+34 953 56 52 06",
    "sg:postcode":"23610",
    "sg:province":"Ja\u00e9n",
    "wof:name":"Jimenez Fuentes Gregorio",
    "wof:placetype":"venue"
},
  "geometry": {"coordinates":[-3.9139869213,37.6455345154],"type":"Point"}
}