{
  "type": "Feature",
  "properties": {
    "addr:full":"Carrer de Martirs, 14 Calafell Tarragona 43820",
    "addr:housenumber":"14",
    "addr:postcode":"43820",
    "addr:street":"Carrer De Martirs",
    "iso:country":"ES",
    "sg:address":"Carrer de Martirs, 14",
    "sg:city":"Calafell",
    "sg:orig_category":"Ropa Para Se\u00d1oras (al Por Menor)",
    "sg:phone":"+34 977 69 05 12",
    "sg:postcode":"43820",
    "sg:province":"Tarragona",
    "wof:name":"Lopez Castillo Esther",
    "wof:placetype":"venue"
},
  "geometry": {"coordinates":[1.569002986,41.1986160278],"type":"Point"}
}