{
  "type": "Feature",
  "properties": {
    "addr:full":"Calle de Sierra Azul, S/n Albujon Murcia 30330",
    "addr:postcode":"30330",
    "addr:street":"Calle De Sierra Azul S / N",
    "iso:country":"ES",
    "sg:address":"Calle de Sierra Azul, S/n",
    "sg:city":"Albujon",
    "sg:orig_category":"Muebles Y Accesorios Para Cocinas Y Cuartos De Ba\u00d1o (al Por Menor)",
    "sg:phone":"+34 968 16 03 32",
    "sg:postcode":"30330",
    "sg:province":"Murcia",
    "wof:name":"Ortu\u00f1o Campillo Francisco",
    "wof:placetype":"venue"
},
  "geometry": {"coordinates":[-1.0482540131,37.7187614441],"type":"Point"}
}