{
  "type": "Feature",
  "properties": {
    "addr:full":"Calle de Concordia (la), 5 Algeciras C\u00e1diz 11206",
    "addr:housenumber":"5;ca\u0301diz",
    "addr:postcode":"11206",
    "addr:street":"Calle De Concordia La",
    "iso:country":"ES",
    "sg:address":"Calle de Concordia (la), 5",
    "sg:city":"Algeciras",
    "sg:orig_category":"Empresas De Limpieza",
    "sg:phone":"+34 956 60 28 95",
    "sg:postcode":"11206",
    "sg:province":"C\u00e1diz",
    "wof:name":"Eurorecambios Y Mantenimiento S.l",
    "wof:placetype":"venue"
},
  "geometry": {"coordinates":[-5.4882678986,36.1051139832],"type":"Point"}
}