{
  "type": "Feature",
  "properties": {
    "iso:country":"ES",
    "sg:address":"Calle de Americo Vespucio, 104",
    "sg:city":"Clavellinas",
    "sg:orig_category":"Ense\u00d1anza Variada",
    "sg:phone":"+34 928 13 20 41",
    "sg:postcode":"35214",
    "sg:province":"Las Palmas",
    "wof:name":"Aerotec Escuela De Pilotos S.l.",
    "wof:placetype":"venue"
},
  "geometry": {"coordinates":[-15.3784713745,27.9846858978],"type":"Point"}
}