{
  "type": "Feature",
  "properties": {
    "iso:country":"ES",
    "sg:address":"Carr Academia, 44",
    "sg:city":"Lleida",
    "sg:orig_category":"Asociaciones, Organismos Culturales Y Socioeducativos",
    "sg:phone":"+34 973 27 02 54",
    "sg:postcode":"25002",
    "sg:province":"Lleida",
    "wof:name":"Centro Castilla Y Leon",
    "wof:placetype":"venue"
},
  "geometry": {"coordinates":[0.6170240045,41.6097946167],"type":"Point"}
}