{
  "type": "Feature",
  "properties": {
    "iso:country":"ES",
    "sg:address":"Avda Don Juan De Borbon, 2",
    "sg:city":"Vista Alegre",
    "sg:orig_category":"Fotogrametr\u00cda",
    "sg:phone":"+34 968 23 83 36",
    "sg:postcode":"30007",
    "sg:province":"Murcia",
    "wof:name":"Topolev S.a.",
    "wof:placetype":"venue"
},
  "geometry": {"coordinates":[-1.1241589785,37.9937515259],"type":"Point"}
}