{
  "type": "Feature",
  "properties": {
    "addr:full":"Calle de Olof Palme, S/n San Anton Murcia 30009",
    "addr:housenumber":"s / n",
    "addr:postcode":"30009",
    "addr:street":"Calle De Olof Palme",
    "iso:country":"ES",
    "sg:address":"Calle de Olof Palme, S/n",
    "sg:city":"San Anton",
    "sg:orig_category":"Abogados",
    "sg:phone":"+34 968 29 86 27",
    "sg:postcode":"30009",
    "sg:province":"Murcia",
    "wof:name":"Ruiz Moreno Ricardo",
    "wof:placetype":"venue"
},
  "geometry": {"coordinates":[-1.1429690123,37.9905395508],"type":"Point"}
}