{
  "type": "Feature",
  "properties": {
    "addr:full":"Carrer de Arquimedes, 170 Terrassa Barcelona 08224",
    "addr:housenumber":"170",
    "addr:postcode":"08224",
    "addr:street":"Carrer De Arquimedes",
    "iso:country":"ES",
    "sg:address":"Carrer de Arquimedes, 170",
    "sg:city":"Terrassa",
    "sg:orig_category":"Fabricaci\u00d3n, Importaci\u00d3n De L\u00c1mparas Y Bombillas",
    "sg:phone":"+34 937 88 61 84",
    "sg:postcode":"08224",
    "sg:province":"Barcelona",
    "wof:name":"Lampisteria Artes S.c.p.",
    "wof:placetype":"venue"
},
  "geometry": {"coordinates":[2.0065290928,41.5616378784],"type":"Point"}
}