{
  "type": "Feature",
  "properties": {
    "iso:country":"ES",
    "sg:address":"Calle de Jesus Nazareno - Aldea Moret, 39",
    "sg:city":"Caceres",
    "sg:orig_category":"Centros De Coordinaci\u00d3n",
    "sg:phone":"+34 927 23 50 03",
    "sg:postcode":"10005",
    "sg:province":"C\u00e1ceres",
    "wof:name":"Garzo Gil Miguel Luis",
    "wof:placetype":"venue"
},
  "geometry": {"coordinates":[-6.5341739655,39.4675254822],"type":"Point"}
}