{
  "type": "Feature",
  "properties": {
    "addr:full":"Avda Aragon, 93 Puebla Vicar Almer\u00eda 04738",
    "addr:housenumber":"93",
    "addr:postcode":"04738",
    "addr:street":"Avda Aragon",
    "iso:country":"ES",
    "sg:address":"Avda Aragon, 93",
    "sg:city":"Puebla Vicar",
    "sg:orig_category":"Venta, Montaje De Neum\u00c1ticos",
    "sg:phone":"+34 950 55 73 39",
    "sg:postcode":"04738",
    "sg:province":"Almer\u00eda",
    "sg:website":"www.neumaticoslopezlinares-vialider.com",
    "wof:name":"Neumaticos Lopez Linares S.c.",
    "wof:placetype":"venue"
},
  "geometry": {"coordinates":[-2.6517090797,36.8000984192],"type":"Point"}
}