{
  "type": "Feature",
  "properties": {
    "iso:country":"ES",
    "sg:address":"Rua Pardo Bazan, S/n",
    "sg:city":"Burela",
    "sg:orig_category":"Servicios Gsm",
    "sg:phone":"+34 982 58 60 02",
    "sg:postcode":"27880",
    "sg:province":"Lugo",
    "wof:name":"Marse Telfonica S.l.u",
    "wof:placetype":"venue"
},
  "geometry": {"coordinates":[-7.3608570099,43.6641120911],"type":"Point"}
}