{
  "type": "Feature",
  "properties": {
    "addr:full":"Rua Curros Enriquez (poeta), 34 Lugo Lugo 27004",
    "addr:housenumber":"34",
    "addr:postcode":"27004",
    "addr:street":"Rua Curros Enriquez Poeta",
    "iso:country":"ES",
    "sg:address":"Rua Curros Enriquez (poeta), 34",
    "sg:city":"Lugo",
    "sg:orig_category":"Asilos De Ancianos. Centros Privados",
    "sg:phone":"+34 982 21 30 77",
    "sg:postcode":"27004",
    "sg:province":"Lugo",
    "wof:name":"Xunta De Galicia",
    "wof:placetype":"venue"
},
  "geometry": {"coordinates":[-7.5659332275,43.0194129944],"type":"Point"}
}