{
  "type": "Feature",
  "properties": {
    "iso:country":"ES",
    "sg:address":"Calle de Cantueso, S/n",
    "sg:city":"Cordoba",
    "sg:orig_category":"Laboratorios Y Cl\u00cdnicas Veterinarias",
    "sg:phone":"+34 957 40 05 63",
    "sg:postcode":"14012",
    "sg:province":"C\u00f3rdoba",
    "wof:name":"Li\u00f1an Guijarro Maria Eloisa",
    "wof:placetype":"venue"
},
  "geometry": {"coordinates":[-4.8039302826,37.9070587158],"type":"Point"}
}