{
  "type": "Feature",
  "properties": {
    "iso:country":"ES",
    "sg:address":"Calle de San Miguel, S/n",
    "sg:city":"Lodosa",
    "sg:orig_category":"Restaurantes",
    "sg:phone":"+34 948 69 32 00",
    "sg:postcode":"31580",
    "sg:province":"Navarra",
    "wof:name":"Gonzalez De Miguel Antonio",
    "wof:placetype":"venue"
},
  "geometry": {"coordinates":[-2.0736279488,42.4229774475],"type":"Point"}
}