{
  "type": "Feature",
  "properties": {
    "addr:full":"C/ Francisco Vicente Rodriguez, 3 Elche Alicante 03202",
    "addr:housenumber":"3",
    "addr:postcode":"03202",
    "addr:street":"C / Francisco Vicente Rodriguez",
    "iso:country":"ES",
    "sg:address":"C/ Francisco Vicente Rodriguez, 3",
    "sg:city":"Elche",
    "sg:orig_category":"Institutos De Belleza",
    "sg:phone":"+34 965 42 54 81",
    "sg:postcode":"03202",
    "sg:province":"Alicante",
    "wof:name":"Falco Marco Maria Del Carmen",
    "wof:placetype":"venue"
},
  "geometry": {"coordinates":[-0.5931239724,38.2568435669],"type":"Point"}
}