{
  "type": "Feature",
  "properties": {
    "addr:full":"Plaz Profesor Lopez Ibor, 11 Valencia Valencia 46015",
    "addr:housenumber":"11",
    "addr:postcode":"46015",
    "addr:street":"Plaz Profesor Lopez Ibor",
    "iso:country":"ES",
    "sg:address":"Plaz Profesor Lopez Ibor, 11",
    "sg:city":"Valencia",
    "sg:orig_category":"M\u00c9dicos: Naturistas",
    "sg:phone":"+34 963 46 15 04",
    "sg:postcode":"46015",
    "sg:province":"Valencia",
    "wof:name":"Navarro Carpio Vicente De Los Reyes",
    "wof:placetype":"venue"
},
  "geometry": {"coordinates":[-0.4012219906,39.4758148193],"type":"Point"}
}