{
  "type": "Feature",
  "properties": {
    "iso:country":"ES",
    "sg:address":"Pol Ind La Torrecilla Grande, S/n",
    "sg:city":"Yeles",
    "sg:orig_category":"Art\u00cdculos De Madera (fabricaci\u00d3n Y Al Por Mayor)",
    "sg:phone":"+34 925 51 01 18",
    "sg:postcode":"45220",
    "sg:province":"Toledo",
    "sg:website":"www.mesadaimesa.com",
    "wof:name":"Mesa Daimesa S.l.",
    "wof:placetype":"venue"
},
  "geometry": {"coordinates":[-3.8059339523,40.1223945618],"type":"Point"}
}