{
  "type": "Feature",
  "properties": {
    "addr:full":"Avda Buenos Aires, 136 Ourense Ourense 32004",
    "addr:housenumber":"136",
    "addr:postcode":"32004",
    "addr:street":"Avda Buenos Aires",
    "iso:country":"ES",
    "sg:address":"Avda Buenos Aires, 136",
    "sg:city":"Ourense",
    "sg:orig_category":"Supermercados Y Hipermercados",
    "sg:phone":"+34 988 23 16 20",
    "sg:postcode":"32004",
    "sg:province":"Ourense",
    "wof:name":"Sanchez Rodriguez Jose Luis",
    "wof:placetype":"venue"
},
  "geometry": {"coordinates":[-7.8557949066,42.3421669006],"type":"Point"}
}