{
  "type": "Feature",
  "properties": {
    "iso:country":"ES",
    "sg:address":"Ctra Catral, Km. 0023,0",
    "sg:city":"San Jose",
    "sg:orig_category":"Inform\u00c1tica: Redes",
    "sg:phone":"+34 966 75 84 12",
    "sg:postcode":"03360",
    "sg:province":"Alicante",
    "wof:name":"Hicorred S.l.",
    "wof:placetype":"venue"
},
  "geometry": {"coordinates":[-0.8739690185,38.126083374],"type":"Point"}
}