{
  "type": "Feature",
  "properties": {
    "iso:country":"ES",
    "sg:address":"Carrer de Lleo, 37",
    "sg:city":"Rubi",
    "sg:orig_category":"Empresas De Carpinter\u00cda De Madera",
    "sg:phone":"+34 936 99 95 03",
    "sg:postcode":"08191",
    "sg:province":"Barcelona",
    "wof:name":"Ebanisteria Y Decoracion Iba\u00f1ez E Hijos S.l.",
    "wof:placetype":"venue"
},
  "geometry": {"coordinates":[2.0458669662,41.5011253357],"type":"Point"}
}