{
  "type": "Feature",
  "properties": {
    "addr:full":"Ctra Fuente Amarga (de), S/n Chiclana De La Frontera C\u00e1diz 11130",
    "addr:postcode":"11130",
    "addr:street":"Ctra Fuente Amarga De S / N",
    "iso:country":"ES",
    "sg:address":"Ctra Fuente Amarga (de), S/n",
    "sg:city":"Chiclana De La Frontera",
    "sg:orig_category":"Grabados Y Decoraci\u00d3n De Metales",
    "sg:phone":"+34 956 53 01 94",
    "sg:postcode":"11130",
    "sg:province":"C\u00e1diz",
    "sg:website":"www.hierrosavila.com",
    "wof:name":"Hierros Y Aceros Avila S.l.",
    "wof:placetype":"venue"
},
  "geometry": {"coordinates":[-6.1465640068,36.4097633362],"type":"Point"}
}