{
  "type": "Feature",
  "properties": {
    "iso:country":"ES",
    "sg:address":"Calle de Pareja, General, 12",
    "sg:city":"Melilla",
    "sg:orig_category":"Cl\u00cdnicas Dentales",
    "sg:phone":"+34 952 68 28 85",
    "sg:postcode":"52001",
    "sg:province":"Melilla",
    "wof:name":"Meliveo Odontologos C.b.",
    "wof:placetype":"venue"
},
  "geometry": {"coordinates":[-2.9412560463,35.2936210632],"type":"Point"}
}