{
  "type": "Feature",
  "properties": {
    "addr:full":"Calle de Pico Cejo, 59 Madrid Madrid 28038",
    "addr:housenumber":"59",
    "addr:postcode":"madrid;28038",
    "addr:street":"Calle De Pico Cejo",
    "iso:country":"ES",
    "sg:address":"Calle de Pico Cejo, 59",
    "sg:city":"Madrid",
    "sg:orig_category":"Ropa Para Se\u00d1oras (al Por Menor)",
    "sg:phone":"+34 913 28 37 87",
    "sg:postcode":"28038",
    "sg:province":"Madrid",
    "wof:name":"Gave Sport S.l.",
    "wof:placetype":"venue"
},
  "geometry": {"coordinates":[-3.6629960537,40.3988304138],"type":"Point"}
}