{
  "type": "Feature",
  "properties": {
    "addr:full":"Calle de Arevalo, 13 Ti\u00d1osillos \u00c1vila 05165",
    "addr:housenumber":"13",
    "addr:postcode":"05165",
    "addr:street":"Calle De Arevalo;A\u0301Vila",
    "iso:country":"ES",
    "sg:address":"Calle de Arevalo, 13",
    "sg:city":"Ti\u00d1osillos",
    "sg:orig_category":"Venta Al Preg\u00d3n",
    "sg:phone":"+34 920 26 70 77",
    "sg:postcode":"05165",
    "sg:province":"\u00c1vila",
    "wof:name":"Hernandez Gallego Segundo",
    "wof:placetype":"venue"
},
  "geometry": {"coordinates":[-4.7282624245,40.9322891235],"type":"Point"}
}