{
  "type": "Feature",
  "properties": {
    "iso:country":"ES",
    "sg:address":"Disseminat, S/n",
    "sg:city":"Avinyo",
    "sg:orig_category":"Fabrica De Charcuter\u00cda",
    "sg:phone":"+34 938 38 74 14",
    "sg:postcode":"08279",
    "sg:province":"Barcelona",
    "wof:name":"Avinfret S. A.",
    "wof:placetype":"venue"
},
  "geometry": {"coordinates":[1.9783666134,41.8728904724],"type":"Point"}
}