{
  "type": "Feature",
  "properties": {
    "addr:full":"Avda Oasis, 118 Ejido Almer\u00eda 04700",
    "addr:housenumber":"118",
    "addr:postcode":"04700",
    "addr:street":"Avda Oasis;Ejido Almeri\u0301A",
    "iso:country":"ES",
    "sg:address":"Avda Oasis, 118",
    "sg:city":"Ejido",
    "sg:orig_category":"Reposter\u00cdas",
    "sg:phone":"+34 950 48 77 48",
    "sg:postcode":"04700",
    "sg:province":"Almer\u00eda",
    "wof:name":"Salvador, Encarna Y Gabril Sc",
    "wof:placetype":"venue"
},
  "geometry": {"coordinates":[-2.800798893,36.7691383362],"type":"Point"}
}