{
  "type": "Feature",
  "properties": {
    "addr:full":"Calle de Adelfa, 2 Benalup C\u00e1diz 11190",
    "addr:housenumber":"2",
    "addr:postcode":"11190",
    "addr:street":"Calle De Adelfa;Ca\u0301Diz",
    "iso:country":"ES",
    "sg:address":"Calle de Adelfa, 2",
    "sg:city":"Benalup",
    "sg:orig_category":"Ense\u00d1anza Variada",
    "sg:phone":"+34 956 42 47 56",
    "sg:postcode":"11190",
    "sg:province":"C\u00e1diz",
    "wof:name":"Gonzalez Perez-blanco Jose Luis",
    "wof:placetype":"venue"
},
  "geometry": {"coordinates":[-5.8129701614,36.3453598022],"type":"Point"}
}