{
  "type": "Feature",
  "properties": {
    "iso:country":"ES",
    "sg:address":"Carrer de Reding (de), 5",
    "sg:city":"Tarragona",
    "sg:orig_category":"Centros Pms (psico",
    "sg:phone":"+34 977 22 60 20",
    "sg:postcode":"43001",
    "sg:province":"Tarragona",
    "wof:name":"Garcia Alvarez Jose Luis",
    "wof:placetype":"venue"
},
  "geometry": {"coordinates":[1.2510529757,41.1144142151],"type":"Point"}
}