{
  "type": "Feature",
  "properties": {
    "addr:full":"Calle de San Jacinto, 10 Valencia Valencia 46008",
    "addr:housenumber":"10",
    "addr:postcode":"46008",
    "addr:street":"Calle De San Jacinto",
    "iso:country":"ES",
    "sg:address":"Calle de San Jacinto, 10",
    "sg:city":"Valencia",
    "sg:classifiers":[
        {
            "category":"Casinos & Gambling",
            "type":"Entertainment"
        }
    ],
    "sg:phone":"+34 963 82 23 06",
    "sg:postcode":"46008",
    "sg:province":"Valencia",
    "sg:tags":[
        "locale",
        "de",
        "juego"
    ],
    "wof:name":"Bingos Y Juegos De Valencia S.a.",
    "wof:placetype":"venue"
},
  "geometry": {"coordinates":[-0.3900319934,39.4755935669],"type":"Point"}
}