{
  "type": "Feature",
  "properties": {
    "addr:full":"Alam Boulevard Del, 17 Donostia-san Sebastian Guip\u00f9zcoa 20003",
    "addr:housenumber":"17",
    "addr:postcode":"20003",
    "addr:street":"Alam Boulevard Del",
    "iso:country":"ES",
    "sg:address":"Alam Boulevard Del, 17",
    "sg:city":"Donostia-san Sebastian",
    "sg:orig_category":"Bancos",
    "sg:phone":"+34 943 42 15 41",
    "sg:postcode":"20003",
    "sg:province":"Guip\u00f9zcoa",
    "wof:name":"Banco De Vasconia",
    "wof:placetype":"venue"
},
  "geometry": {"coordinates":[-1.9836740494,43.3219032288],"type":"Point"}
}