{
  "type": "Feature",
  "properties": {
    "addr:full":"Carr Murillo, (de), 10 Carlet Valencia 46240",
    "addr:housenumber":"10",
    "addr:postcode":"46240",
    "addr:street":"Carr Murillo De",
    "iso:country":"ES",
    "sg:address":"Carr Murillo, (de), 10",
    "sg:city":"Carlet",
    "sg:orig_category":"Peluqueros: De Se\u00d1oras",
    "sg:phone":"+34 962 53 00 19",
    "sg:postcode":"46240",
    "sg:province":"Valencia",
    "wof:name":"Garcia Grau Juan",
    "wof:placetype":"venue"
},
  "geometry": {"coordinates":[-0.5217130184,39.2290725708],"type":"Point"}
}