{
  "type": "Feature",
  "properties": {
    "addr:full":"Poli Industrial, S/n Guarnizo Cantabria 39611",
    "addr:housenumber":"/ n",
    "addr:postcode":"39611",
    "addr:street":"Industrial",
    "iso:country":"ES",
    "sg:address":"Poli Industrial, S/n",
    "sg:city":"Guarnizo",
    "sg:orig_category":"Metacrilato: Art\u00cdculos (fabricaci\u00d3n Y Al Por Mayor)",
    "sg:phone":"+34 942 55 97 69",
    "sg:postcode":"39611",
    "sg:province":"Cantabria",
    "sg:website":"www.mgcantabria.com",
    "wof:name":"Metacrilatos Y Grabados S.a.l.",
    "wof:placetype":"venue"
},
  "geometry": {"coordinates":[-3.822521925,43.3990821838],"type":"Point"}
}