{
  "type": "Feature",
  "properties": {
    "addr:full":"Calle de Jesus Nazareno, 4 Burguillos Cerro Badajoz 06370",
    "addr:housenumber":"4",
    "addr:postcode":"06370",
    "addr:street":"Calle De Jesus Nazareno",
    "iso:country":"ES",
    "sg:address":"Calle de Jesus Nazareno, 4",
    "sg:city":"Burguillos Cerro",
    "sg:orig_category":"Asesor\u00cda Fiscal Y Jur\u00cddica",
    "sg:phone":"+34 924 54 14 76",
    "sg:postcode":"06370",
    "sg:province":"Badajoz",
    "wof:name":"Gomez Asensio Daniel",
    "wof:placetype":"venue"
},
  "geometry": {"coordinates":[-6.5881700516,38.3790550232],"type":"Point"}
}