{
  "type": "Feature",
  "properties": {
    "addr:full":"Carrer de L'estadella, 94 Barcelona Barcelona 08030",
    "addr:housenumber":"94",
    "addr:postcode":"08030",
    "addr:street":"Carrer De L'Estadella",
    "iso:country":"ES",
    "sg:address":"Carrer de L'estadella, 94",
    "sg:city":"Barcelona",
    "sg:orig_category":"Asistencia Social",
    "sg:phone":"+34 933 14 91 43",
    "sg:postcode":"08030",
    "sg:province":"Barcelona",
    "wof:name":"Romero Pe\u00f1a Katty Sharon",
    "wof:placetype":"venue"
},
  "geometry": {"coordinates":[2.207859993,41.435585022],"type":"Point"}
}