{
  "type": "Feature",
  "properties": {
    "iso:country":"ES",
    "sg:address":"Kale Nagusia, 27",
    "sg:city":"Astigarraga",
    "sg:orig_category":"Carnicer\u00cdas, Carnicer\u00cdas",
    "sg:phone":"+34 943 55 12 99",
    "sg:postcode":"20115",
    "sg:province":"Guip\u00f9zcoa",
    "wof:name":"Ormazabal Miner, Martin",
    "wof:placetype":"venue"
},
  "geometry": {"coordinates":[-1.9507540464,43.2802085876],"type":"Point"}
}