{
  "type": "Feature",
  "properties": {
    "iso:country":"ES",
    "sg:address":"Avda Playa Serena, 5",
    "sg:city":"Urbanizacion Roquetas De Mar",
    "sg:orig_category":"Bazares, Art\u00cdculos De Limpieza Y De Cocina (al Por Menor)",
    "sg:phone":"+34 950 33 52 57",
    "sg:postcode":"04740",
    "sg:province":"Almer\u00eda",
    "wof:name":"Sakura Playa Serena C.b.",
    "wof:placetype":"venue"
},
  "geometry": {"coordinates":[-2.6286709309,36.7227478027],"type":"Point"}
}