{
  "type": "Feature",
  "properties": {
    "addr:full":"Urb Gacela Hills, S/n Gaspara M\u00e1laga 29680",
    "addr:housenumber":"s / n",
    "addr:postcode":"29680",
    "addr:street":"Urb Gacela Hills;Gaspara Ma\u0301Laga",
    "iso:country":"ES",
    "sg:address":"Urb Gacela Hills, S/n",
    "sg:city":"Gaspara",
    "sg:orig_category":"Asociaciones Y Clubs Deportivos",
    "sg:phone":"+34 952 80 01 08",
    "sg:postcode":"29680",
    "sg:province":"M\u00e1laga",
    "wof:name":"Gimena Oroz Carmen Maria",
    "wof:placetype":"venue"
},
  "geometry": {"coordinates":[-5.1452140808,36.4275817871],"type":"Point"}
}