{
  "type": "Feature",
  "properties": {
    "addr:full":"Pl. Los Fueros, 7 Estella Navarra 31200",
    "addr:housenumber":"7",
    "addr:postcode":"31200",
    "addr:street":"Los Fueros",
    "iso:country":"ES",
    "sg:address":"Pl. Los Fueros, 7",
    "sg:city":"Estella",
    "sg:orig_category":"Librer\u00cdas",
    "sg:phone":"+34 948 55 06 93",
    "sg:postcode":"31200",
    "sg:province":"Navarra",
    "wof:name":"Imprenta-libreria Zunzarren S.l.",
    "wof:placetype":"venue"
},
  "geometry": {"coordinates":[-2.0314669609,42.6719017029],"type":"Point"}
}