{
  "type": "Feature",
  "properties": {
    "addr:full":"Avda Dublin, S/n Coto Guadalajara 19170",
    "addr:housenumber":"s / n",
    "addr:postcode":"19170",
    "addr:street":"Avda Dublin",
    "iso:country":"ES",
    "sg:address":"Avda Dublin, S/n",
    "sg:city":"Coto",
    "sg:orig_category":"Inmobiliaria (agencias)",
    "sg:phone":"+34 949 33 44 99",
    "sg:postcode":"19170",
    "sg:province":"Guadalajara",
    "wof:name":"Castrillo Iberica S.l.",
    "wof:placetype":"venue"
},
  "geometry": {"coordinates":[-3.442109108,40.7055587769],"type":"Point"}
}