{
  "type": "Feature",
  "properties": {
    "iso:country":"ES",
    "sg:address":"Calle de Ramon Y Cajal, 14",
    "sg:city":"Poligono Industrial Los Villares",
    "sg:orig_category":"Transporte En General",
    "sg:phone":"+34 923 22 68 36",
    "sg:postcode":"37184",
    "sg:province":"Salamanca",
    "wof:name":"Sucesores De Moreno S.l.",
    "wof:placetype":"venue"
},
  "geometry": {"coordinates":[-5.6678905487,40.9653511047],"type":"Point"}
}