{
  "type": "Feature",
  "properties": {
    "iso:country":"ES",
    "sg:address":"Plaz Corredera (de La), S/n",
    "sg:city":"Cordoba",
    "sg:orig_category":"Carnicer\u00cdas, Carnicer\u00cdas",
    "sg:phone":"+34 957 47 13 15",
    "sg:postcode":"14002",
    "sg:province":"C\u00f3rdoba",
    "wof:name":"Carnes Sandalio Vidal S.l.",
    "wof:placetype":"venue"
},
  "geometry": {"coordinates":[-4.7750291824,37.8835906982],"type":"Point"}
}