{
  "type": "Feature",
  "properties": {
    "addr:full":"Carrer de Enric Morera, 25 Manresa Barcelona 08243",
    "addr:housenumber":"25",
    "addr:postcode":"08243",
    "addr:street":"Carrer De Enric Morera",
    "iso:country":"ES",
    "sg:address":"Carrer de Enric Morera, 25",
    "sg:city":"Manresa",
    "sg:orig_category":"Transportes Por Carretera: Lotes Completos, Mercanc\u00cdas Diversas",
    "sg:phone":"+34 938 77 15 36",
    "sg:postcode":"08243",
    "sg:province":"Barcelona",
    "wof:name":"Dispromat 2000 S.l.",
    "wof:placetype":"venue"
},
  "geometry": {"coordinates":[1.8344019651,41.7389564514],"type":"Point"}
}