{
  "type": "Feature",
  "properties": {
    "iso:country":"ES",
    "sg:address":"Avda Inmaculada (de La), 25",
    "sg:city":"Avila",
    "sg:orig_category":"Transportes Por V\u00cdas Navegables",
    "sg:phone":"+34 920 22 23 25",
    "sg:postcode":"05005",
    "sg:province":"\u00c1vila",
    "wof:name":"Santo Tomas Casillas Juan",
    "wof:placetype":"venue"
},
  "geometry": {"coordinates":[-4.6846189499,40.6611709595],"type":"Point"}
}