{
  "type": "Feature",
  "properties": {
    "addr:full":"Rua Estrada Do Covelo, S/n Veiga Ourense 32360",
    "addr:housenumber":"s / n",
    "addr:postcode":"32360",
    "addr:street":"Rua Estrada Do Covelo",
    "iso:country":"ES",
    "sg:address":"Rua Estrada Do Covelo, S/n",
    "sg:city":"Veiga",
    "sg:orig_category":"Cajas De Ahorro",
    "sg:phone":"+34 988 35 01 05",
    "sg:postcode":"32360",
    "sg:province":"Ourense",
    "wof:name":"Bt Espa\u00d1a Compa\u00d1ia De Servicios Globales De Telecomunicaciones S.a.u.",
    "wof:placetype":"venue"
},
  "geometry": {"coordinates":[-7.0252480507,42.2495994568],"type":"Point"}
}