{
  "type": "Feature",
  "properties": {
    "addr:full":"Plz De Oviedo, 1 Pedro Mu\u00f1oz Ciudad Real 13620",
    "addr:housenumber":"1",
    "addr:postcode":"13620",
    "addr:street":"Plz De Oviedo;Pedro Mun\u0303Oz",
    "iso:country":"ES",
    "sg:address":"Plz De Oviedo, 1",
    "sg:city":"Pedro Mu\u00f1oz",
    "sg:orig_category":"Asociaciones Y Clubs Deportivos",
    "sg:phone":"+34 926 58 73 04",
    "sg:postcode":"13620",
    "sg:province":"Ciudad Real",
    "wof:name":"Cobo Mu\u00f1oz Angel Luis",
    "wof:placetype":"venue"
},
  "geometry": {"coordinates":[-2.9435579777,39.4077987671],"type":"Point"}
}