{
  "type": "Feature",
  "properties": {
    "addr:full":"Calle de San Raimundo, 33 Madrid Madrid 28039",
    "addr:housenumber":"33",
    "addr:postcode":"madrid;28039",
    "addr:street":"Calle De San",
    "iso:country":"ES",
    "sg:address":"Calle de San Raimundo, 33",
    "sg:city":"Madrid",
    "sg:orig_category":"Loter\u00cda Y T\u00d3mbola",
    "sg:phone":"+34 914 50 54 40",
    "sg:postcode":"28039",
    "sg:province":"Madrid",
    "wof:name":"Robles Blanco Julia",
    "wof:placetype":"venue"
},
  "geometry": {"coordinates":[-3.7058620453,40.4516563416],"type":"Point"}
}