{
  "type": "Feature",
  "properties": {
    "addr:full":"Cmno Vera, S/n Campohermoso Almer\u00eda 04110",
    "addr:housenumber":"s / n",
    "addr:postcode":"04110",
    "addr:street":"Cmno Vera;Almeri\u0301A",
    "iso:country":"ES",
    "sg:address":"Cmno Vera, S/n",
    "sg:city":"Campohermoso",
    "sg:orig_category":"Cajas De Ahorro",
    "sg:phone":"+34 950 38 61 98",
    "sg:postcode":"04110",
    "sg:province":"Almer\u00eda",
    "wof:name":"Monte De Piedad Y Caja De Ahorros De Huelva Y Sevilla",
    "wof:placetype":"venue"
},
  "geometry": {"coordinates":[-2.1324241161,36.9409065247],"type":"Point"}
}