{
  "type": "Feature",
  "properties": {
    "addr:full":"Ctra Fregenal-sta Olalla, S/n Bodonal De La Sierra Badajoz 06394",
    "addr:housenumber":"s / n",
    "addr:postcode":"06394",
    "addr:street":"Ctra Fregenal-Sta Olalla",
    "iso:country":"ES",
    "sg:address":"Ctra Fregenal-sta Olalla, S/n",
    "sg:city":"Bodonal De La Sierra",
    "sg:orig_category":"Empresas De Carpinter\u00cda Met\u00c1lica",
    "sg:phone":"+34 924 72 15 25",
    "sg:postcode":"06394",
    "sg:province":"Badajoz",
    "wof:name":"Linares Lozano Jose Luis",
    "wof:placetype":"venue"
},
  "geometry": {"coordinates":[-6.5611181259,38.1474876404],"type":"Point"}
}