{
  "type": "Feature",
  "properties": {
    "iso:country":"ES",
    "sg:address":"Calle de Salas, 33",
    "sg:city":"Regumiel De La Sierra",
    "sg:orig_category":"Frutas, Legumbres Frescas Y Tempranas (al Por Menor)",
    "sg:phone":"+34 947 39 44 17",
    "sg:postcode":"09693",
    "sg:province":"Burgos",
    "wof:name":"Sastre Gil Hermanos S.l.",
    "wof:placetype":"venue"
},
  "geometry": {"coordinates":[-2.9890069962,41.9562454224],"type":"Point"}
}