{
  "type": "Feature",
  "properties": {
    "iso:country":"ES",
    "sg:address":"Carr Ferrer Barbara, 6",
    "sg:city":"Camprodon",
    "sg:orig_category":"Compraventa De Antig\u00dcedades",
    "sg:phone":"+34 972 74 11 60",
    "sg:postcode":"17867",
    "sg:province":"Girona",
    "wof:name":"Subirana Muntaner Francisco",
    "wof:placetype":"venue"
},
  "geometry": {"coordinates":[2.3652310371,42.3139343262],"type":"Point"}
}