{
  "type": "Feature",
  "properties": {
    "addr:full":"Calle de Pozuelo, 54 Montalban De Cordoba C\u00f3rdoba 14548",
    "addr:housenumber":"54",
    "addr:postcode":"14548",
    "addr:street":"Calle De Pozuelo;Co\u0301Rdoba",
    "iso:country":"ES",
    "sg:address":"Calle de Pozuelo, 54",
    "sg:city":"Montalban De Cordoba",
    "sg:orig_category":"Agentes, Concesionarios Y Sucursales De Veh\u00cdculos",
    "sg:phone":"+34 957 31 00 81",
    "sg:postcode":"14548",
    "sg:province":"C\u00f3rdoba",
    "wof:name":"Talleres Marquez Delgado S.l.",
    "wof:placetype":"venue"
},
  "geometry": {"coordinates":[-4.7533478737,37.5763092041],"type":"Point"}
}