{
  "type": "Feature",
  "properties": {
    "addr:full":"Calle de Comercio (san Juan De Mozarrifar), 22 San Juan De Mozarrifar Zaragoza 50820",
    "addr:housenumber":"22",
    "addr:postcode":"50820",
    "addr:street":"Calle De Comercio San Juan De Mozarrifar;Juan;Mozarrifar",
    "iso:country":"ES",
    "sg:address":"Calle de Comercio (san Juan De Mozarrifar), 22",
    "sg:city":"San Juan De Mozarrifar",
    "sg:orig_category":"Plomeros",
    "sg:phone":"+34 976 15 01 81",
    "sg:postcode":"50820",
    "sg:province":"Zaragoza",
    "wof:name":"Hurtado Ferrer Ramiro",
    "wof:placetype":"venue"
},
  "geometry": {"coordinates":[-0.8407598138,41.7179450989],"type":"Point"}
}