{
  "type": "Feature",
  "properties": {
    "addr:full":"Calle de Santa Fe De Bogota, 36 Santa Fe Granada 18320",
    "addr:housenumber":"36",
    "addr:postcode":"18320",
    "addr:street":"Calle De Santa;Santa",
    "iso:country":"ES",
    "sg:address":"Calle de Santa Fe De Bogota, 36",
    "sg:city":"Santa Fe",
    "sg:orig_category":"Panader\u00cdas, Panader\u00cdas",
    "sg:phone":"+34 958 44 00 52",
    "sg:postcode":"18320",
    "sg:province":"Granada",
    "wof:name":"Robles Castro Jose Antonio",
    "wof:placetype":"venue"
},
  "geometry": {"coordinates":[-3.7219390869,37.1880607605],"type":"Point"}
}