{
  "type": "Feature",
  "properties": {
    "addr:full":"Plaz Iglesia, S/n Raya Murcia 30167",
    "addr:housenumber":"s / n",
    "addr:postcode":"30167",
    "addr:street":"Murcia",
    "iso:country":"ES",
    "sg:address":"Plaz Iglesia, S/n",
    "sg:city":"Raya",
    "sg:orig_category":"Iglesia Cat\u00d3lica",
    "sg:phone":"+34 968 25 12 18",
    "sg:postcode":"30167",
    "sg:province":"Murcia",
    "wof:name":"Parroquia De La Encarnacion",
    "wof:placetype":"venue"
},
  "geometry": {"coordinates":[-1.1818890572,37.9727287292],"type":"Point"}
}