{
  "type": "Feature",
  "properties": {
    "iso:country":"ES",
    "sg:address":"Carrer de Mestre Candi, 34",
    "sg:city":"Hospitalet Llobregat",
    "sg:orig_category":"M\u00c1quinas Para Recortar Y Pegar",
    "sg:phone":"+34 932 61 05 18",
    "sg:postcode":"08901",
    "sg:province":"Barcelona",
    "wof:name":"Tecnocut S. L.",
    "wof:placetype":"venue"
},
  "geometry": {"coordinates":[2.1090269089,41.3612937927],"type":"Point"}
}