{
  "type": "Feature",
  "properties": {
    "iso:country":"ES",
    "sg:address":"Avda Burgos, 2",
    "sg:city":"Venta De Ba\u00e7os",
    "sg:orig_category":"Empresas De Carpinter\u00cda",
    "sg:phone":"+34 979 77 02 92",
    "sg:postcode":"34200",
    "sg:province":"Palencia",
    "wof:name":"Otero Martin Roberto",
    "wof:placetype":"venue"
},
  "geometry": {"coordinates":[-4.490172863,41.9263839722],"type":"Point"}
}