{
  "type": "Feature",
  "properties": {
    "iso:country":"ES",
    "sg:address":"Carrer de Ciutat D'asuncion, 38",
    "sg:city":"Barcelona",
    "sg:orig_category":"Fabricaci\u00d3n De Moldes Y Modelos",
    "sg:phone":"+34 932 74 29 53",
    "sg:postcode":"08030",
    "sg:province":"Barcelona",
    "wof:name":"Modelista Luque S.l.",
    "wof:placetype":"venue"
},
  "geometry": {"coordinates":[2.2002782822,41.439907074],"type":"Point"}
}