{
  "type": "Feature",
  "properties": {
    "addr:full":"Calle de Doctor Luis Calandre, 10 Cartagena Murcia 30205",
    "addr:housenumber":"10",
    "addr:postcode":"30205",
    "addr:street":"Calle De Doctor Luis Calandre",
    "iso:country":"ES",
    "sg:address":"Calle de Doctor Luis Calandre, 10",
    "sg:city":"Cartagena",
    "sg:orig_category":"Mec\u00c1nico Del Autom\u00d3vil",
    "sg:phone":"+34 968 12 15 37",
    "sg:postcode":"30205",
    "sg:province":"Murcia",
    "wof:name":"Clemente Campillo Isabel",
    "wof:placetype":"venue"
},
  "geometry": {"coordinates":[-0.994037807,37.6082572937],"type":"Point"}
}