{
  "type": "Feature",
  "properties": {
    "addr:full":"Calle de Loma (la), 1 Torrevieja Alicante 03180",
    "addr:postcode":"03180",
    "addr:street":"Calle De Loma La 1",
    "iso:country":"ES",
    "sg:address":"Calle de Loma (la), 1",
    "sg:city":"Torrevieja",
    "sg:orig_category":"Arquitectos",
    "sg:phone":"+34 966 70 86 61",
    "sg:postcode":"03180",
    "sg:province":"Alicante",
    "wof:name":"Area Juridica Del Mediterraneo S.l.",
    "wof:placetype":"venue"
},
  "geometry": {"coordinates":[-0.6779817939,37.9811820984],"type":"Point"}
}