{
  "type": "Feature",
  "properties": {
    "iso:country":"ES",
    "sg:address":"Calle de Conquistadores, S/n",
    "sg:city":"Calamonte",
    "sg:orig_category":"Empresas De Carpinter\u00cda Met\u00c1lica",
    "sg:phone":"+34 924 32 30 54",
    "sg:postcode":"06810",
    "sg:province":"Badajoz",
    "wof:name":"Talleres Lopez Y Barrero Cdad.",
    "wof:placetype":"venue"
},
  "geometry": {"coordinates":[-6.3862943649,38.8929481506],"type":"Point"}
}