{
  "type": "Feature",
  "properties": {
    "addr:full":"Pase Pontones, 23 Madrid Madrid 28005",
    "addr:housenumber":"23",
    "addr:postcode":"madrid;28005",
    "iso:country":"ES",
    "sg:address":"Pase Pontones, 23",
    "sg:city":"Madrid",
    "sg:orig_category":"Peluqueros: De Se\u00d1oras",
    "sg:phone":"+34 914 74 90 26",
    "sg:postcode":"28005",
    "sg:province":"Madrid",
    "wof:name":"Montero Esteban Antonio",
    "wof:placetype":"venue"
},
  "geometry": {"coordinates":[-3.7150781155,40.4049186707],"type":"Point"}
}