{
  "type": "Feature",
  "properties": {
    "addr:full":"Ctra Marines A Denia (les), 129 Marines Alicante 03700",
    "addr:housenumber":"129",
    "addr:postcode":"03700",
    "addr:street":"Ctra Marines A;Les",
    "iso:country":"ES",
    "sg:address":"Ctra Marines A Denia (les), 129",
    "sg:city":"Marines",
    "sg:orig_category":"Asesor\u00cdas Y Estudios Financieros",
    "sg:phone":"+34 966 42 74 06",
    "sg:postcode":"03700",
    "sg:province":"Alicante",
    "wof:name":"La Morada Del Duende S.l.",
    "wof:placetype":"venue"
},
  "geometry": {"coordinates":[0.0785949975,38.8549537659],"type":"Point"}
}