{
  "type": "Feature",
  "properties": {
    "iso:country":"ES",
    "sg:address":"Calle de Sarasate, 8",
    "sg:city":"Salamanca",
    "sg:orig_category":"Imprenta",
    "sg:phone":"+34 923 12 19 32",
    "sg:postcode":"37005",
    "sg:province":"Salamanca",
    "wof:name":"Lemalrace S.l.",
    "wof:placetype":"venue"
},
  "geometry": {"coordinates":[-5.6589174271,40.972366333],"type":"Point"}
}