{
  "type": "Feature",
  "properties": {
    "iso:country":"ES",
    "sg:address":"Calle de Casa Grande, 28",
    "sg:city":"Campillo Altobuey",
    "sg:orig_category":"Negocio De Materiales De Construcci\u00d3n",
    "sg:phone":"+34 969 33 82 52",
    "sg:postcode":"16210",
    "sg:province":"Cuenca",
    "wof:name":"Material De La Construccion Joima S.l.",
    "wof:placetype":"venue"
},
  "geometry": {"coordinates":[-1.7919312716,39.6106452942],"type":"Point"}
}