{
  "type": "Feature",
  "properties": {
    "iso:country":"ES",
    "sg:address":"Calle de Carnicerias, 6",
    "sg:city":"Tudela",
    "sg:orig_category":"Carnicer\u00cdas, Carnicer\u00cdas",
    "sg:phone":"+34 948 40 30 69",
    "sg:postcode":"31500",
    "sg:province":"Navarra",
    "wof:name":"Carnicas Enlaces S.l.",
    "wof:placetype":"venue"
},
  "geometry": {"coordinates":[-1.6064579487,42.062877655],"type":"Point"}
}