{
  "type": "Feature",
  "properties": {
    "iso:country":"ES",
    "sg:address":"Ctra Malfu, S/n",
    "sg:city":"Carrizal",
    "sg:orig_category":"Maquinaria Para Industrias Diversas",
    "sg:phone":"+34 928 78 50 70",
    "sg:postcode":"35240",
    "sg:province":"Las Palmas",
    "wof:name":"Pimyr S.a.",
    "wof:placetype":"venue"
},
  "geometry": {"coordinates":[-15.4088487625,27.9120388031],"type":"Point"}
}