{
  "type": "Feature",
  "properties": {
    "iso:country":"ES",
    "sg:address":"Calle de Constantino Cabal, 10",
    "sg:city":"Oviedo",
    "sg:orig_category":"Abogados",
    "sg:phone":"+34 985 23 66 30",
    "sg:postcode":"33005",
    "sg:province":"Asturias",
    "wof:name":"Alonso Vega Abogados C.b.",
    "wof:placetype":"venue"
},
  "geometry": {"coordinates":[-5.8524808884,43.3590126038],"type":"Point"}
}