{
  "type": "Feature",
  "properties": {
    "iso:country":"ES",
    "sg:address":"Avda Regne De Valencia, 6",
    "sg:city":"Valencia",
    "sg:orig_category":"Reposter\u00cdas",
    "sg:phone":"+34 963 73 81 28",
    "sg:postcode":"46005",
    "sg:province":"Valencia",
    "wof:name":"Garcia Rutia Vicente",
    "wof:placetype":"venue"
},
  "geometry": {"coordinates":[-0.3729250133,39.4647064209],"type":"Point"}
}