{
  "type": "Feature",
  "properties": {
    "addr:full":"Av Cister, 40 Secar De La Real Islas Baleares 07010",
    "addr:housenumber":"40",
    "addr:postcode":"07010",
    "addr:street":"Av Cister",
    "iso:country":"ES",
    "sg:address":"Av Cister, 40",
    "sg:city":"Secar De La Real",
    "sg:orig_category":"Plomeros",
    "sg:phone":"+34 971 76 51 70",
    "sg:postcode":"07010",
    "sg:province":"Islas Baleares",
    "wof:name":"Fuites D'aigues S.l.",
    "wof:placetype":"venue"
},
  "geometry": {"coordinates":[2.6368410587,39.6080093384],"type":"Point"}
}