{
  "type": "Feature",
  "properties": {
    "addr:full":"Calle de Fuente Palmera, S/n Posadas C\u00f3rdoba 14730",
    "addr:housenumber":"s / n;co\u0301rdoba",
    "addr:postcode":"14730",
    "addr:street":"Calle De Fuente Palmera",
    "iso:country":"ES",
    "sg:address":"Calle de Fuente Palmera, S/n",
    "sg:city":"Posadas",
    "sg:orig_category":"Producci\u00d3n, Venta De Productos De Agricultura Biol\u00d3gica",
    "sg:phone":"+34 957 63 15 52",
    "sg:postcode":"14730",
    "sg:province":"C\u00f3rdoba",
    "wof:name":"Agricola Los Conventos S.l.",
    "wof:placetype":"venue"
},
  "geometry": {"coordinates":[-5.1025300026,37.8012619019],"type":"Point"}
}