{
  "type": "Feature",
  "properties": {
    "iso:country":"ES",
    "sg:address":"Av Jaume I, 2",
    "sg:city":"Pego",
    "sg:orig_category":"\u00d3ptica: Instrumentos (fabricaci\u00d3n)",
    "sg:phone":"+34 965 57 23 26",
    "sg:postcode":"03780",
    "sg:province":"Alicante",
    "wof:name":"Mengual Tavallo Gloria",
    "wof:placetype":"venue"
},
  "geometry": {"coordinates":[-0.1151989996,38.8382644653],"type":"Point"}
}