{
  "type": "Feature",
  "properties": {
    "addr:full":"Avda Albufera, 5 Alfafar Valencia 46910",
    "addr:housenumber":"5",
    "addr:postcode":"46910",
    "addr:street":"Avda Albufera",
    "iso:country":"ES",
    "sg:address":"Avda Albufera, 5",
    "sg:city":"Alfafar",
    "sg:orig_category":"Molduras, Junquillos, Listones Y Molduras Perforadas",
    "sg:phone":"+34 963 96 49 17",
    "sg:postcode":"46910",
    "sg:province":"Valencia",
    "wof:name":"Huan  Zhang",
    "wof:placetype":"venue"
},
  "geometry": {"coordinates":[-0.3788799942,39.4140472412],"type":"Point"}
}