{
  "type": "Feature",
  "properties": {
    "addr:full":"Avda Valencia, 39 Zaragoza Zaragoza 50005",
    "addr:housenumber":"39",
    "addr:postcode":"50005",
    "addr:street":"Avda Valencia",
    "iso:country":"ES",
    "sg:address":"Avda Valencia, 39",
    "sg:city":"Zaragoza",
    "sg:orig_category":"Muebles, Minoristas",
    "sg:phone":"+34 976 55 01 26",
    "sg:postcode":"50005",
    "sg:province":"Zaragoza",
    "wof:name":"Josant Interiorismo S.l.",
    "wof:placetype":"venue"
},
  "geometry": {"coordinates":[-0.8968909979,41.6461868286],"type":"Point"}
}