{
  "type": "Feature",
  "properties": {
    "iso:country":"ES",
    "sg:address":"Ctra Medianias-las Suertes (las), 156",
    "sg:city":"Perdoma",
    "sg:orig_category":"Insecticidas, Fumigaci\u00d3n",
    "sg:phone":"+34 922 30 83 01",
    "sg:postcode":"38315",
    "sg:province":"Santa Cruz De Tenerife",
    "wof:name":"Racucal S.l.",
    "wof:placetype":"venue"
},
  "geometry": {"coordinates":[-16.5055618286,28.3659114838],"type":"Point"}
}