{
  "type": "Feature",
  "properties": {
    "addr:full":"Calle de San Jose De Calasanz, 79 Valladolid Valladolid 47013",
    "addr:housenumber":"79",
    "addr:postcode":"47013",
    "addr:street":"Calle De San;De Calasanz",
    "iso:country":"ES",
    "sg:address":"Calle de San Jose De Calasanz, 79",
    "sg:city":"Valladolid",
    "sg:orig_category":"Peluqueros: De Se\u00d1oras",
    "sg:phone":"+34 983 23 15 64",
    "sg:postcode":"47013",
    "sg:province":"Valladolid",
    "wof:name":"Marcos Delgado Maria Del Mar",
    "wof:placetype":"venue"
},
  "geometry": {"coordinates":[-4.7196946144,41.6369552612],"type":"Point"}
}