{
  "type": "Feature",
  "properties": {
    "addr:full":"Calle de Ildefonso Arrola, 3 Santurtzi Vizcaya 48980",
    "addr:housenumber":"3",
    "addr:postcode":"48980",
    "addr:street":"Calle De Ildefonso Arrola",
    "iso:country":"ES",
    "sg:address":"Calle de Ildefonso Arrola, 3",
    "sg:city":"Santurtzi",
    "sg:orig_category":"Mec\u00c1nico Del Autom\u00d3vil",
    "sg:phone":"+34 944 61 19 43",
    "sg:postcode":"48980",
    "sg:province":"Vizcaya",
    "wof:name":"Esteban Lafuente Ba\u00f1ales (garaje Lafuente)",
    "wof:placetype":"venue"
},
  "geometry": {"coordinates":[-3.0351350307,43.3312492371],"type":"Point"}
}