{
  "type": "Feature",
  "properties": {
    "iso:country":"ES",
    "sg:address":"Avda Catalunya, 56",
    "sg:city":"Monjos",
    "sg:orig_category":"Prendas Y Chalecos De Punto (al Por Menor)",
    "sg:phone":"+34 938 98 00 80",
    "sg:postcode":"08730",
    "sg:province":"Barcelona",
    "wof:name":"Font Marimon Anyelina",
    "wof:placetype":"venue"
},
  "geometry": {"coordinates":[1.6572669744,41.3190498352],"type":"Point"}
}