{
  "type": "Feature",
  "properties": {
    "addr:full":"Carrer de Penedes, 75 Prat Llobregat Barcelona 08820",
    "addr:housenumber":"75",
    "addr:postcode":"08820",
    "addr:street":"Carrer De Penedes;Llobregat",
    "iso:country":"ES",
    "sg:address":"Carrer de Penedes, 75",
    "sg:city":"Prat Llobregat",
    "sg:orig_category":"Construcci\u00d3n Mec\u00c1nica",
    "sg:phone":"+34 933 79 07 73",
    "sg:postcode":"08820",
    "sg:province":"Barcelona",
    "wof:name":"Llados Llera S.a.",
    "wof:placetype":"venue"
},
  "geometry": {"coordinates":[2.0910921097,41.3264045715],"type":"Point"}
}