{
  "type": "Feature",
  "properties": {
    "iso:country":"ES",
    "sg:address":"Calle de Monte Esquinza, 9",
    "sg:city":"Madrid",
    "sg:orig_category":"Muebles, Minoristas",
    "sg:phone":"+34 913 10 45 29",
    "sg:postcode":"28010",
    "sg:province":"Madrid",
    "wof:name":"Recuperando El Pasado S.l.",
    "wof:placetype":"venue"
},
  "geometry": {"coordinates":[-3.6924540997,40.4267234802],"type":"Point"}
}