{
  "type": "Feature",
  "properties": {
    "addr:full":"Calle de Santiago Apostol (de), 2 Alcobendas Madrid 28100",
    "addr:postcode":"28100",
    "addr:street":"Calle De Santiago",
    "iso:country":"ES",
    "sg:address":"Calle de Santiago Apostol (de), 2",
    "sg:city":"Alcobendas",
    "sg:orig_category":"Loter\u00cda Y T\u00d3mbola",
    "sg:phone":"+34 916 52 78 23",
    "sg:postcode":"28100",
    "sg:province":"Madrid",
    "wof:name":"Martinez Espi Jose",
    "wof:placetype":"venue"
},
  "geometry": {"coordinates":[-3.6305699348,40.5426521301],"type":"Point"}
}