{
  "type": "Feature",
  "properties": {
    "iso:country":"ES",
    "sg:address":"Calle de Ramon Y Cajal, 17",
    "sg:city":"Valencia Alcantara",
    "sg:orig_category":"Florister\u00cdas",
    "sg:phone":"+34 927 58 22 89",
    "sg:postcode":"10500",
    "sg:province":"C\u00e1ceres",
    "wof:name":"Do Carmo Morais Maria Joao",
    "wof:placetype":"venue"
},
  "geometry": {"coordinates":[-7.2438139915,39.4110069275],"type":"Point"}
}