{
  "type": "Feature",
  "properties": {
    "addr:full":"Av. G. Roca, 3 Port Andratx Islas Baleares 07157",
    "addr:housenumber":"3",
    "addr:postcode":"07157",
    "addr:street":"Av. G. Roca",
    "iso:country":"ES",
    "sg:address":"Av. G. Roca, 3",
    "sg:city":"Port Andratx",
    "sg:orig_category":"Bancos",
    "sg:phone":"+34 971 67 10 37",
    "sg:postcode":"07157",
    "sg:province":"Islas Baleares",
    "sg:website":"www.bancamarch.es",
    "wof:name":"Banca March S.a.",
    "wof:placetype":"venue"
},
  "geometry": {"coordinates":[2.3837299347,39.5477485657],"type":"Point"}
}