{
  "type": "Feature",
  "properties": {
    "addr:full":"Avda Monteazahar, 2 Beniajan Murcia 30570",
    "addr:housenumber":"2",
    "addr:postcode":"30570",
    "addr:street":"Avda Monteazahar",
    "iso:country":"ES",
    "sg:address":"Avda Monteazahar, 2",
    "sg:city":"Beniajan",
    "sg:orig_category":"Cajas De Ahorro",
    "sg:phone":"+34 968 83 71 97",
    "sg:postcode":"30570",
    "sg:province":"Murcia",
    "wof:name":"Caja De Ahorros Del Mediterraneo",
    "wof:placetype":"venue"
},
  "geometry": {"coordinates":[-1.0706529617,37.9733428955],"type":"Point"}
}