{
  "type": "Feature",
  "properties": {
    "addr:full":"Avda Juan Carlos I, 29 Santiago Murcia 30800",
    "addr:housenumber":"29",
    "addr:postcode":"30800",
    "addr:street":"Avda Juan Carlos I",
    "iso:country":"ES",
    "sg:address":"Avda Juan Carlos I, 29",
    "sg:city":"Santiago",
    "sg:orig_category":"Abogados",
    "sg:phone":"+34 968 44 26 23",
    "sg:postcode":"30800",
    "sg:province":"Murcia",
    "wof:name":"Garcia Padilla Antonio",
    "wof:placetype":"venue"
},
  "geometry": {"coordinates":[-1.1298867464,37.9834747314],"type":"Point"}
}