{
  "type": "Feature",
  "properties": {
    "addr:full":"Rua Santiago De Chile (de), 24 Santiago De Compostela La Coru\u00f1a 15706",
    "addr:housenumber":"24",
    "addr:postcode":"15706",
    "addr:street":"Rua Santiago De Chile De;Corun\u0303A",
    "iso:country":"ES",
    "sg:address":"Rua Santiago De Chile (de), 24",
    "sg:city":"Santiago De Compostela",
    "sg:orig_category":"Art\u00cdculos De Decoraci\u00d3n",
    "sg:phone":"+34 981 59 35 99",
    "sg:postcode":"15706",
    "sg:province":"La Coru\u00f1a",
    "wof:name":"Lopez Blanco David",
    "wof:placetype":"venue"
},
  "geometry": {"coordinates":[-8.5501070023,42.8715782166],"type":"Point"}
}