{
  "type": "Feature",
  "properties": {
    "iso:country":"ES",
    "sg:address":"Calle de Alcala (de), 6",
    "sg:city":"Algete",
    "sg:orig_category":"Tintes (fabricaci\u00d3n, Al Por Mayor)",
    "sg:phone":"+34 916 28 26 09",
    "sg:postcode":"28110",
    "sg:province":"Madrid",
    "wof:name":"Tintoreria Loher",
    "wof:placetype":"venue"
},
  "geometry": {"coordinates":[-3.4991140366,40.5963287354],"type":"Point"}
}