{
  "type": "Feature",
  "properties": {
    "addr:full":"Calle de Arroyos, 4 Cabrerizos Salamanca 37193",
    "addr:housenumber":"4",
    "addr:postcode":"37193",
    "addr:street":"Calle De Arroyos",
    "iso:country":"ES",
    "sg:address":"Calle de Arroyos, 4",
    "sg:city":"Cabrerizos",
    "sg:orig_category":"Molduras, Junquillos, Listones Y Molduras Perforadas",
    "sg:phone":"+34 923 28 92 28",
    "sg:postcode":"37193",
    "sg:province":"Salamanca",
    "wof:name":"Hernandez Moreno Agustin",
    "wof:placetype":"venue"
},
  "geometry": {"coordinates":[-5.6101322174,40.9769287109],"type":"Point"}
}