{
  "type": "Feature",
  "properties": {
    "addr:full":"Avda Espa\u00d1a (de), 37 Priego Cordoba C\u00f3rdoba 14800",
    "addr:housenumber":"37",
    "addr:postcode":"14800",
    "addr:street":"Avda Espan\u0303A De;Cordoba Co\u0301Rdoba",
    "iso:country":"ES",
    "sg:address":"Avda Espa\u00d1a (de), 37",
    "sg:city":"Priego Cordoba",
    "sg:orig_category":"Telas Y Sedas (al Por Menor)",
    "sg:phone":"+34 957 70 11 02",
    "sg:postcode":"14800",
    "sg:province":"C\u00f3rdoba",
    "wof:name":"Gutierrez Granados Amelia",
    "wof:placetype":"venue"
},
  "geometry": {"coordinates":[-4.2051210403,37.439491272],"type":"Point"}
}