{
  "type": "Feature",
  "properties": {
    "iso:country":"ES",
    "sg:address":"Cra Espinel, 40",
    "sg:city":"Ronda",
    "sg:orig_category":"Droguer\u00cdas (al Por Menor)",
    "sg:phone":"+34 952 87 17 83",
    "sg:postcode":"29400",
    "sg:province":"M\u00e1laga",
    "wof:name":"Campos Gomez Juan",
    "wof:placetype":"venue"
},
  "geometry": {"coordinates":[-5.1644630432,36.7430305481],"type":"Point"}
}