{
  "type": "Feature",
  "properties": {
    "addr:full":"Calle de Santa Lucia, 26 Santander Cantabria 39003",
    "addr:housenumber":"26",
    "addr:postcode":"39003",
    "addr:street":"Calle De Santa Lucia",
    "iso:country":"ES",
    "sg:address":"Calle de Santa Lucia, 26",
    "sg:city":"Santander",
    "sg:orig_category":"Panader\u00cdas, Panader\u00cdas",
    "sg:phone":"+34 942 21 59 53",
    "sg:postcode":"39003",
    "sg:province":"Cantabria",
    "wof:name":"Gomez Gomez M.luisa",
    "wof:placetype":"venue"
},
  "geometry": {"coordinates":[-3.8000569344,43.4641418457],"type":"Point"}
}