{
  "type": "Feature",
  "properties": {
    "addr:full":"Carr Duc De La Victoria, 5 Vilanova I La Geltru Barcelona 08800",
    "addr:housenumber":"5",
    "addr:postcode":"08800",
    "addr:street":"Carr Duc De La Victoria",
    "iso:country":"ES",
    "sg:address":"Carr Duc De La Victoria, 5",
    "sg:city":"Vilanova I La Geltru",
    "sg:orig_category":"Electricidad: Instaladores",
    "sg:phone":"+34 938 93 97 17",
    "sg:postcode":"08800",
    "sg:province":"Barcelona",
    "wof:name":"Instaladors Del Garraf S.c.c.l.",
    "wof:placetype":"venue"
},
  "geometry": {"coordinates":[1.7278517485,41.2290763855],"type":"Point"}
}