{
  "type": "Feature",
  "properties": {
    "iso:country":"ES",
    "sg:address":"Calle de Concepcion, 15",
    "sg:city":"Casasimarro",
    "sg:orig_category":"Carnicer\u00cdas, Carnicer\u00cdas",
    "sg:phone":"+34 967 48 72 75",
    "sg:postcode":"16239",
    "sg:province":"Cuenca",
    "wof:name":"Cuesta Cambronero Juan",
    "wof:placetype":"venue"
},
  "geometry": {"coordinates":[-2.0406661034,39.3918571472],"type":"Point"}
}