{
  "type": "Feature",
  "properties": {
    "addr:full":"Avda Ruiz Jimenez, 10 Jaen Ja\u00e9n 23008",
    "addr:housenumber":"10;jae\u0301n",
    "addr:postcode":"23008",
    "addr:street":"Avda Ruiz Jimenez",
    "iso:country":"ES",
    "sg:address":"Avda Ruiz Jimenez, 10",
    "sg:city":"Jaen",
    "sg:orig_category":"Internados & Ense\u00d1anza Privada",
    "sg:phone":"+34 953 25 09 41",
    "sg:postcode":"23008",
    "sg:province":"Ja\u00e9n",
    "wof:name":"Colegio Cristo Rey En Jaen Hijas De Cristo Rey Provincia Andalucia",
    "wof:placetype":"venue"
},
  "geometry": {"coordinates":[-3.7870190144,37.778049469],"type":"Point"}
}