{
  "type": "Feature",
  "properties": {
    "iso:country":"ES",
    "sg:address":"Calle de Cadiz, 35",
    "sg:city":"Conil De La Frontera",
    "sg:orig_category":"Inmobiliaria (agencias)",
    "sg:phone":"+34 956 45 60 47",
    "sg:postcode":"11140",
    "sg:province":"C\u00e1diz",
    "wof:name":"Fincas Conil S.l.",
    "wof:placetype":"venue"
},
  "geometry": {"coordinates":[-6.0915036201,36.2761306763],"type":"Point"}
}