{
  "type": "Feature",
  "properties": {
    "iso:country":"ES",
    "sg:address":"Calle de Pintor Berrueta, 6",
    "sg:city":"Irun",
    "sg:orig_category":"Peluquer\u00cdas, Peluquer\u00cda Mixta",
    "sg:phone":"+34 943 62 06 26",
    "sg:postcode":"20305",
    "sg:province":"Guip\u00f9zcoa",
    "wof:name":"Maria Del Puerto Blazquez Alonso",
    "wof:placetype":"venue"
},
  "geometry": {"coordinates":[-1.7761240005,43.3403244019],"type":"Point"}
}