{
  "type": "Feature",
  "properties": {
    "addr:full":"Avda Rio Guadarrama, 14 Poligono Sta M. De Benquerencia Toledo 45007",
    "addr:housenumber":"14 poligono",
    "addr:postcode":"45007",
    "addr:street":"Avda Rio Guadarrama;Sta M. De Benquerencia",
    "iso:country":"ES",
    "sg:address":"Avda Rio Guadarrama, 14",
    "sg:city":"Poligono Sta M. De Benquerencia",
    "sg:orig_category":"Muebles, Minoristas",
    "sg:phone":"+34 925 24 18 15",
    "sg:postcode":"45007",
    "sg:province":"Toledo",
    "wof:name":"Toledo Hergamueble S.l.",
    "wof:placetype":"venue"
},
  "geometry": {"coordinates":[-3.9429910183,39.8602905273],"type":"Point"}
}