{
  "type": "Feature",
  "properties": {
    "addr:full":"Calle de Amor De Dios, 14 Madrid Madrid 28014",
    "addr:housenumber":"14",
    "addr:postcode":"madrid;28014",
    "addr:street":"Calle De Amor De Dios",
    "iso:country":"ES",
    "sg:address":"Calle de Amor De Dios, 14",
    "sg:city":"Madrid",
    "sg:orig_category":"Peluquer\u00cdas, Peluquer\u00cda Mixta",
    "sg:phone":"+34 913 69 17 09",
    "sg:postcode":"28014",
    "sg:province":"Madrid",
    "wof:name":"Rodriguez Marce\u00f1ido Manuela Del Pilar",
    "wof:placetype":"venue"
},
  "geometry": {"coordinates":[-3.6985664368,40.412361145],"type":"Point"}
}