{
  "type": "Feature",
  "properties": {
    "addr:full":"Calle de Pintor Gustavo De Maeztu, 4 Vitoria-gasteiz \u00c1lava 01008",
    "addr:housenumber":"4",
    "addr:postcode":"01008",
    "addr:street":"Calle De Pintor Gustavo De Maeztu",
    "iso:country":"ES",
    "sg:address":"Calle de Pintor Gustavo De Maeztu, 4",
    "sg:city":"Vitoria-gasteiz",
    "sg:orig_category":"Bibliotecas, Mediatecas",
    "sg:phone":"+34 945 20 01 35",
    "sg:postcode":"01008",
    "sg:province":"\u00c1lava",
    "sg:website":"www.odei.es",
    "wof:name":"Odei, S.a",
    "wof:placetype":"venue"
},
  "geometry": {"coordinates":[-2.6867630482,42.8501472473],"type":"Point"}
}