{
  "type": "Feature",
  "properties": {
    "iso:country":"ES",
    "sg:address":"Carr De Bocairent, 13",
    "sg:city":"Ontinyent",
    "sg:orig_category":"Farmacias",
    "sg:phone":"+34 962 38 32 58",
    "sg:postcode":"46870",
    "sg:province":"Valencia",
    "wof:name":"Ruiz Alvarez Maria Carmen",
    "wof:placetype":"venue"
},
  "geometry": {"coordinates":[-0.6163210273,38.8217048645],"type":"Point"}
}