{
  "type": "Feature",
  "properties": {
    "addr:full":"Carr Llobera, 1 Solsona Lleida 25280",
    "addr:housenumber":"1",
    "addr:postcode":"25280",
    "addr:street":"Carr Llobera",
    "iso:country":"ES",
    "sg:address":"Carr Llobera, 1",
    "sg:city":"Solsona",
    "sg:orig_category":"Distribuci\u00d3n De Petr\u00d3leo Y Derivados",
    "sg:phone":"+34 973 48 05 86",
    "sg:postcode":"25280",
    "sg:province":"Lleida",
    "wof:name":"Gassol Energia S.l.",
    "wof:placetype":"venue"
},
  "geometry": {"coordinates":[1.5185900927,41.99477005],"type":"Point"}
}