{
  "type": "Feature",
  "properties": {
    "iso:country":"ES",
    "sg:address":"Carrer de Constitucio, 88",
    "sg:city":"Sant Feliu Llobregat",
    "sg:orig_category":"Embalajes",
    "sg:phone":"+34 936 85 49 69",
    "sg:postcode":"08980",
    "sg:province":"Barcelona",
    "wof:name":"Embalajes J. Managuerra S.c.p.",
    "wof:placetype":"venue"
},
  "geometry": {"coordinates":[2.0407810211,41.39112854],"type":"Point"}
}