{
  "type": "Feature",
  "properties": {
    "addr:full":"Calle de Calvo Sotelo, 3 Bola\u00e7os De Calatrava Ciudad Real 13260",
    "addr:housenumber":"3",
    "addr:postcode":"13260",
    "addr:street":"Calle De Calvo Sotelo",
    "iso:country":"ES",
    "sg:address":"Calle de Calvo Sotelo, 3",
    "sg:city":"Bola\u00e7os De Calatrava",
    "sg:orig_category":"\u00d3ptica: Instrumentos (fabricaci\u00d3n)",
    "sg:phone":"+34 926 87 29 19",
    "sg:postcode":"13260",
    "sg:province":"Ciudad Real",
    "wof:name":"Optica Jeronimo S.l.",
    "wof:placetype":"venue"
},
  "geometry": {"coordinates":[-3.6660001278,38.9063301086],"type":"Point"}
}