{
  "type": "Feature",
  "properties": {
    "iso:country":"ES",
    "sg:address":"Calle de Aramunt, 10",
    "sg:city":"Madrid",
    "sg:orig_category":"Inmobiliaria (agencias)",
    "sg:phone":"+34 913 07 06 83",
    "sg:postcode":"28023",
    "sg:province":"Madrid",
    "wof:name":"Castrocid S.l.",
    "wof:placetype":"venue"
},
  "geometry": {"coordinates":[-3.7888140678,40.4605979919],"type":"Point"}
}