{
  "type": "Feature",
  "properties": {
    "addr:full":"Plaz Arrabal (del), 2 Arevalo \u00c1vila 05200",
    "addr:housenumber":"2",
    "addr:postcode":"05200",
    "addr:street":"Plaz Arrabal Del",
    "iso:country":"ES",
    "sg:address":"Plaz Arrabal (del), 2",
    "sg:city":"Arevalo",
    "sg:orig_category":"Cajas De Ahorro",
    "sg:phone":"+34 920 30 25 04",
    "sg:postcode":"05200",
    "sg:province":"\u00c1vila",
    "sg:website":"www.lacaixa.es",
    "wof:name":"Caixa D'estalvis I Pensions De Barcelona",
    "wof:placetype":"venue"
},
  "geometry": {"coordinates":[-4.7205848694,41.0636177063],"type":"Point"}
}