{
  "type": "Feature",
  "properties": {
    "addr:full":"E. Armendariz, 4 Atarrabia Navarra 31610",
    "addr:housenumber":"4",
    "addr:postcode":"31610",
    "addr:street":"Armendariz",
    "iso:country":"ES",
    "sg:address":"E. Armendariz, 4",
    "sg:city":"Atarrabia",
    "sg:orig_category":"Transportes Por Carretera: Lotes Completos, Mercanc\u00cdas Diversas",
    "sg:phone":"+34 948 33 28 50",
    "sg:postcode":"31610",
    "sg:province":"Navarra",
    "wof:name":"Arriola Lecumberri Isabel",
    "wof:placetype":"venue"
},
  "geometry": {"coordinates":[-1.6088678837,42.8341712952],"type":"Point"}
}