{
  "type": "Feature",
  "properties": {
    "iso:country":"ES",
    "sg:address":"Ctra. Barcelona, Km. 0330,8",
    "sg:city":"Zaragoza",
    "sg:orig_category":"Molduras, Junquillos, Listones Y Molduras Perforadas",
    "sg:phone":"+34 976 57 15 75",
    "sg:postcode":"50016",
    "sg:province":"Zaragoza",
    "wof:name":"Vencotel S.l.",
    "wof:placetype":"venue"
},
  "geometry": {"coordinates":[-0.8234919906,41.6667442322],"type":"Point"}
}