{
  "type": "Feature",
  "properties": {
    "addr:full":"Carrer de Comte Borrell, 123 Barcelona Barcelona 08015",
    "addr:housenumber":"123",
    "addr:postcode":"08015",
    "addr:street":"Carrer De Comte Borrell",
    "iso:country":"ES",
    "sg:address":"Carrer de Comte Borrell, 123",
    "sg:city":"Barcelona",
    "sg:orig_category":"Asesor\u00cda Sobre Comunicaci\u00d3n De Empresas",
    "sg:phone":"+34 934 51 92 17",
    "sg:postcode":"08015",
    "sg:province":"Barcelona",
    "wof:name":"Gestiempres Asesores S.l.",
    "wof:placetype":"venue"
},
  "geometry": {"coordinates":[2.1581099033,41.3805809021],"type":"Point"}
}