{
  "type": "Feature",
  "properties": {
    "iso:country":"ES",
    "sg:address":"Calle de San Gregorio (de), 45",
    "sg:city":"Galapagar",
    "sg:orig_category":"Empresas De Carpinter\u00cda",
    "sg:phone":"+34 918 58 21 03",
    "sg:postcode":"28260",
    "sg:province":"Madrid",
    "wof:name":"Galametal Sl",
    "wof:placetype":"venue"
},
  "geometry": {"coordinates":[-4.002202034,40.5801925659],"type":"Point"}
}