{
  "type": "Feature",
  "properties": {
    "addr:full":"Calle de Puerto De Velate, 2 Madrid Madrid 28018",
    "addr:housenumber":"2",
    "addr:postcode":"28018",
    "addr:street":"Calle De Puerto De Velate",
    "iso:country":"ES",
    "sg:address":"Calle de Puerto De Velate, 2",
    "sg:city":"Madrid",
    "sg:orig_category":"Reposter\u00cdas",
    "sg:phone":"+34 913 80 55 31",
    "sg:postcode":"28018",
    "sg:province":"Madrid",
    "wof:name":"Gazcue\u00f1a Gomez Silvia",
    "wof:placetype":"venue"
},
  "geometry": {"coordinates":[-3.6572840214,40.3832168579],"type":"Point"}
}