{
  "type": "Feature",
  "properties": {
    "addr:full":"Calle de Virgen Del Portillo, 43 Madrid Madrid 28027",
    "addr:housenumber":"43",
    "addr:postcode":"madrid;28027",
    "addr:street":"Calle De Virgen Del Portillo",
    "iso:country":"ES",
    "sg:address":"Calle de Virgen Del Portillo, 43",
    "sg:city":"Madrid",
    "sg:orig_category":"Clases De M\u00dasica Y Canto",
    "sg:phone":"+34 914 08 84 40",
    "sg:postcode":"28027",
    "sg:province":"Madrid",
    "wof:name":"Siles Lucas Mercedes",
    "wof:placetype":"venue"
},
  "geometry": {"coordinates":[-3.6473391056,40.4393348694],"type":"Point"}
}