{
  "type": "Feature",
  "properties": {
    "iso:country":"ES",
    "sg:address":"Avda Zamora (de), 29",
    "sg:city":"Ourense",
    "sg:orig_category":"Agencias Y Agentes Comerciales, Representantes",
    "sg:phone":"+34 988 25 01 70",
    "sg:postcode":"32005",
    "sg:province":"Ourense",
    "wof:name":"Vila Camba Felisindo",
    "wof:placetype":"venue"
},
  "geometry": {"coordinates":[-7.8635158539,42.3279418945],"type":"Point"}
}