{
  "type": "Feature",
  "properties": {
    "iso:country":"ES",
    "sg:address":"Calle de Pimienta, 38",
    "sg:city":"Badajoz",
    "sg:orig_category":"Agencias Y Agentes Comerciales, Representantes",
    "sg:phone":"+34 924 23 47 23",
    "sg:postcode":"06010",
    "sg:province":"Badajoz",
    "wof:name":"Cotrina Pinilla Jose Maria",
    "wof:placetype":"venue"
},
  "geometry": {"coordinates":[-6.9660801888,38.8687744141],"type":"Point"}
}