{
  "type": "Feature",
  "properties": {
    "iso:country":"ES",
    "sg:address":"Calle de Industria, S/n",
    "sg:city":"Erratzu",
    "sg:orig_category":"Forjas Y Altos Hornos",
    "sg:phone":"+34 948 45 33 66",
    "sg:postcode":"31714",
    "sg:province":"Navarra",
    "wof:name":"Irigoyen Acheverria Manuel Y Iturburua Zubieta Jose Fermin S.cv",
    "wof:placetype":"venue"
},
  "geometry": {"coordinates":[-1.4561990499,43.1821403503],"type":"Point"}
}