{
  "type": "Feature",
  "properties": {
    "addr:full":"Carrer de Empedrat, 1 Ibi Alicante 03440",
    "addr:housenumber":"1",
    "addr:postcode":"03440",
    "addr:street":"Carrer De Empedrat",
    "iso:country":"ES",
    "sg:address":"Carrer de Empedrat, 1",
    "sg:city":"Ibi",
    "sg:orig_category":"Sindicatos De Trabajadores",
    "sg:phone":"+34 965 55 00 21",
    "sg:postcode":"03440",
    "sg:province":"Alicante",
    "wof:name":"Union General De Trabajadores-pais Valenciano",
    "wof:placetype":"venue"
},
  "geometry": {"coordinates":[-0.5750989914,38.6272583008],"type":"Point"}
}