{
  "type": "Feature",
  "properties": {
    "addr:full":"Calle de Manuel Luna, 31 Madrid Madrid 28020",
    "addr:housenumber":"31",
    "addr:postcode":"madrid;28020",
    "addr:street":"Calle De Manuel Luna",
    "iso:country":"ES",
    "sg:address":"Calle de Manuel Luna, 31",
    "sg:city":"Madrid",
    "sg:orig_category":"Ense\u00d1anza: Profesiones Art\u00cdsticas",
    "sg:phone":"+34 915 71 00 06",
    "sg:postcode":"28020",
    "sg:province":"Madrid",
    "wof:name":"Perez Garcia Fernando",
    "wof:placetype":"venue"
},
  "geometry": {"coordinates":[-3.6996939182,40.4547195435],"type":"Point"}
}