{
  "type": "Feature",
  "properties": {
    "addr:full":"Edif Atalaya, 1 Astun Huesca 22889",
    "addr:housenumber":"1",
    "addr:postcode":"22889",
    "addr:street":"Astun",
    "iso:country":"ES",
    "sg:address":"Edif Atalaya, 1",
    "sg:city":"Astun",
    "sg:orig_category":"Agencias Y Agentes Comerciales, Representantes",
    "sg:phone":"+34 974 37 23 65",
    "sg:postcode":"22889",
    "sg:province":"Huesca",
    "wof:name":"Fernandez Roncal Ricardo",
    "wof:placetype":"venue"
},
  "geometry": {"coordinates":[-0.5231779814,42.7850799561],"type":"Point"}
}