{
  "type": "Feature",
  "properties": {
    "iso:country":"ES",
    "sg:address":"Carr Font (la), 10",
    "sg:city":"Sidamon",
    "sg:orig_category":"Dise\u00d1o Industrial",
    "sg:phone":"+34 973 56 06 09",
    "sg:postcode":"25222",
    "sg:province":"Lleida",
    "wof:name":"Civit Curia Javier",
    "wof:placetype":"venue"
},
  "geometry": {"coordinates":[0.8337649703,41.6283798218],"type":"Point"}
}