{
  "type": "Feature",
  "properties": {
    "iso:country":"ES",
    "sg:address":"Calle de Mayor, 24",
    "sg:city":"Cartagena",
    "sg:orig_category":"Ropa Para Ni\u00d1os (al Por Menor)",
    "sg:phone":"+34 968 52 89 35",
    "sg:postcode":"30201",
    "sg:province":"Murcia",
    "sg:website":"www.bershka.com",
    "wof:name":"Bershka Bsr Espa\u00f1a S.a.",
    "wof:placetype":"venue"
},
  "geometry": {"coordinates":[-0.9156429768,37.600566864],"type":"Point"}
}