{
  "type": "Feature",
  "properties": {
    "addr:full":"Maritorrija, 4 Ecija Sevilla 41400",
    "addr:housenumber":"4",
    "addr:postcode":"41400",
    "addr:street":"Maritorrija",
    "iso:country":"ES",
    "sg:address":"Maritorrija, 4",
    "sg:city":"Ecija",
    "sg:orig_category":"Carnicer\u00cdas, Carnicer\u00cdas",
    "sg:phone":"+34 954 83 54 52",
    "sg:postcode":"41400",
    "sg:province":"Sevilla",
    "wof:name":"Caraballo Cortes Soc. Civil",
    "wof:placetype":"venue"
},
  "geometry": {"coordinates":[-5.0766358376,37.5382041931],"type":"Point"}
}