{
  "type": "Feature",
  "properties": {
    "addr:full":"Calle de Prolongacion Marroquineros, S/n Ubrique C\u00e1diz 11600",
    "addr:housenumber":"s / n",
    "addr:postcode":"11600",
    "addr:street":"Calle De Prolongacion Marroquineros;Ca\u0301Diz",
    "iso:country":"ES",
    "sg:address":"Calle de Prolongacion Marroquineros, S/n",
    "sg:city":"Ubrique",
    "sg:orig_category":"Fabricaci\u00d3n De Sobres, Bolsas Y Fundas",
    "sg:phone":"+34 956 46 12 40",
    "sg:postcode":"11600",
    "sg:province":"C\u00e1diz",
    "wof:name":"Olga Godoy S.l.",
    "wof:placetype":"venue"
},
  "geometry": {"coordinates":[-5.4462790489,36.6785163879],"type":"Point"}
}