{
  "type": "Feature",
  "properties": {
    "addr:full":"Muzategi Kalea, 9 Eibar Guip\u00f9zcoa 20600",
    "addr:housenumber":"9",
    "addr:postcode":"20600",
    "addr:street":"Muzategi Kalea;Guipu\u0300Zcoa",
    "iso:country":"ES",
    "sg:address":"Muzategi Kalea, 9",
    "sg:city":"Eibar",
    "sg:orig_category":"Asociaciones, Organismos Culturales Y Socioeducativos",
    "sg:phone":"+34 943 20 77 76",
    "sg:postcode":"20600",
    "sg:province":"Guip\u00f9zcoa",
    "wof:name":"Izarberri Sociedad Cultural Recreativa Gastronomica",
    "wof:placetype":"venue"
},
  "geometry": {"coordinates":[-2.4681930542,43.1864776611],"type":"Point"}
}