{
  "type": "Feature",
  "properties": {
    "iso:country":"ES",
    "sg:address":"Carrer de La Rambla, 88",
    "sg:city":"Barcelona",
    "sg:orig_category":"Loter\u00cda Y T\u00d3mbola",
    "sg:phone":"+34 933 17 69 87",
    "sg:postcode":"08002",
    "sg:province":"Barcelona",
    "sg:website":"www.loteriavaldes.com",
    "wof:name":"Garcia Valdes Jordi",
    "wof:placetype":"venue"
},
  "geometry": {"coordinates":[2.1728479862,41.3818817139],"type":"Point"}
}