{
  "type": "Feature",
  "properties": {
    "iso:country":"ES",
    "sg:address":"Carrer de Llampugol, 6",
    "sg:city":"Palma",
    "sg:orig_category":"Empresas De Limpieza",
    "sg:phone":"+34 971 24 23 20",
    "sg:postcode":"07005",
    "sg:province":"Islas Baleares",
    "wof:name":"Aguilo Valls Gaspar",
    "wof:placetype":"venue"
},
  "geometry": {"coordinates":[2.6676080227,39.5823326111],"type":"Point"}
}