{
  "type": "Feature",
  "properties": {
    "addr:full":"Rua Ancares, 48 Becerrea Lugo 27640",
    "addr:housenumber":"48",
    "addr:postcode":"27640",
    "addr:street":"Rua Ancares",
    "iso:country":"ES",
    "sg:address":"Rua Ancares, 48",
    "sg:city":"Becerrea",
    "sg:orig_category":"Ense\u00d1anza Variada",
    "sg:phone":"+34 982 36 90 46",
    "sg:postcode":"27640",
    "sg:province":"Lugo",
    "wof:name":"Centro De Formacion Becerrea C.b.",
    "wof:placetype":"venue"
},
  "geometry": {"coordinates":[-7.1619410515,42.8559494019],"type":"Point"}
}