{
  "type": "Feature",
  "properties": {
    "addr:full":"Casdavil, 15 Peares Ourense 32440",
    "addr:housenumber":"15",
    "addr:postcode":"32440",
    "addr:street":"Casdavil",
    "iso:country":"ES",
    "sg:address":"Casdavil, 15",
    "sg:city":"Peares",
    "sg:orig_category":"Supermercados Y Hipermercados",
    "sg:phone":"+34 988 20 02 83",
    "sg:postcode":"32440",
    "sg:province":"Ourense",
    "wof:name":"Vazquez Ramos Nila",
    "wof:placetype":"venue"
},
  "geometry": {"coordinates":[-7.7339482307,42.453956604],"type":"Point"}
}