{
  "type": "Feature",
  "properties": {
    "addr:full":"Carrer de Calaf, 27 Barcelona Barcelona 08021",
    "addr:housenumber":"27",
    "addr:postcode":"08021",
    "addr:street":"Carrer De Calaf",
    "iso:country":"ES",
    "sg:address":"Carrer de Calaf, 27",
    "sg:city":"Barcelona",
    "sg:orig_category":"Peleter\u00cdas",
    "sg:phone":"+34 934 14 09 42",
    "sg:postcode":"08021",
    "sg:province":"Barcelona",
    "wof:name":"Patricia-gali Peleteros S.l.",
    "wof:placetype":"venue"
},
  "geometry": {"coordinates":[2.1427910328,41.3962745667],"type":"Point"}
}