{
  "type": "Feature",
  "properties": {
    "iso:country":"ES",
    "sg:address":"Av Mare Nostrum, 61",
    "sg:city":"Grao",
    "sg:orig_category":"Peluqueros: De Se\u00d1oras",
    "sg:phone":"+34 964 58 84 28",
    "sg:postcode":"12593",
    "sg:province":"Castell\u00f3n",
    "wof:name":"Mu\u00f1oz Vela Agustin",
    "wof:placetype":"venue"
},
  "geometry": {"coordinates":[-0.1337040067,39.7955131531],"type":"Point"}
}