{
  "type": "Feature",
  "properties": {
    "iso:country":"ES",
    "sg:address":"Bo. Ctra. Xeral, 3",
    "sg:city":"Foz",
    "sg:orig_category":"Comercio De Piezas De Recambio Y De Accesorios De Veh\u00cdculos, Veh\u00cdculos Industriales",
    "sg:phone":"+34 982 13 23 74",
    "sg:postcode":"27780",
    "sg:province":"Lugo",
    "wof:name":"Autoracing Foz S.l.",
    "wof:placetype":"venue"
},
  "geometry": {"coordinates":[-7.3227038383,43.6186790466],"type":"Point"}
}