{
  "type": "Feature",
  "properties": {
    "addr:full":"Av Bertran I Guell, 58 Gava Barcelona 08850",
    "addr:housenumber":"58",
    "addr:postcode":"08850",
    "addr:street":"Av Bertran I Guell",
    "iso:country":"ES",
    "sg:address":"Av Bertran I Guell, 58",
    "sg:city":"Gava",
    "sg:orig_category":"Inmobiliaria (agencias)",
    "sg:phone":"+34 936 38 04 05",
    "sg:postcode":"08850",
    "sg:province":"Barcelona",
    "wof:name":"Inmobiliaria Olsa S.a.",
    "wof:placetype":"venue"
},
  "geometry": {"coordinates":[2.0112121105,41.2967185974],"type":"Point"}
}