{
  "type": "Feature",
  "properties": {
    "addr:full":"La Coru\u00f1a(pol Ind Azarbes), 2 Dolores Alicante 03150",
    "addr:housenumber":"2",
    "addr:postcode":"03150",
    "addr:street":"Azarbes",
    "iso:country":"ES",
    "sg:address":"La Coru\u00f1a(pol Ind Azarbes), 2",
    "sg:city":"Dolores",
    "sg:orig_category":"Muebles Y Accesorios Para Cocinas Y Cuartos De Ba\u00d1o (al Por Menor)",
    "sg:phone":"+34 966 78 16 06",
    "sg:postcode":"03150",
    "sg:province":"Alicante",
    "wof:name":"Ibx 2003 S.l.",
    "wof:placetype":"venue"
},
  "geometry": {"coordinates":[-0.7627879977,38.1346931458],"type":"Point"}
}