{
  "type": "Feature",
  "properties": {
    "iso:country":"ES",
    "sg:address":"Ibabe Pol Ind, 23",
    "sg:city":"Lazkao",
    "sg:orig_category":"Maquinaria Y Herramientas Para Madera, Pvc, Aluminio Y Aperos (fabricaci\u00d3n, Comercio)",
    "sg:phone":"+34 943 88 33 13",
    "sg:postcode":"20210",
    "sg:province":"Guip\u00f9zcoa",
    "wof:name":"Nadex S.l.",
    "wof:placetype":"venue"
},
  "geometry": {"coordinates":[-2.1873590946,43.0314903259],"type":"Point"}
}