{
  "type": "Feature",
  "properties": {
    "addr:full":"Carrer de Torres Jordi, 15 Espluga Francoli Tarragona 43440",
    "addr:housenumber":"15",
    "addr:postcode":"43440",
    "addr:street":"Carrer De Torres Jordi",
    "iso:country":"ES",
    "sg:address":"Carrer de Torres Jordi, 15",
    "sg:city":"Espluga Francoli",
    "sg:orig_category":"Carnicer\u00cdas, Carnicer\u00cdas",
    "sg:phone":"+34 977 87 03 30",
    "sg:postcode":"43440",
    "sg:province":"Tarragona",
    "wof:name":"Vidal Ciurana Teresa",
    "wof:placetype":"venue"
},
  "geometry": {"coordinates":[1.1034499407,41.3961906433],"type":"Point"}
}