{
  "type": "Feature",
  "properties": {
    "iso:country":"ES",
    "sg:address":"Calle de Marques De Monteagudo, 18",
    "sg:city":"Madrid",
    "sg:orig_category":"Laboratorios Y Trabajos De Fotograf\u00cda, V\u00cddeo Y Cine",
    "sg:phone":"+34 917 25 53 08",
    "sg:postcode":"28028",
    "sg:province":"Madrid",
    "wof:name":"Asociados Del Color S.a.",
    "wof:placetype":"venue"
},
  "geometry": {"coordinates":[-3.6684536934,40.4367904663],"type":"Point"}
}