{
  "type": "Feature",
  "properties": {
    "iso:country":"ES",
    "sg:address":"Calle de Santa Isabel, 38",
    "sg:city":"Santa Pola",
    "sg:orig_category":"Arquitectos",
    "sg:phone":"+34 965 41 49 99",
    "sg:postcode":"03130",
    "sg:province":"Alicante",
    "wof:name":"Csya Asesores S.l.",
    "wof:placetype":"venue"
},
  "geometry": {"coordinates":[-0.5568140149,38.1930961609],"type":"Point"}
}