{
  "type": "Feature",
  "properties": {
    "iso:country":"ES",
    "sg:address":"Avda Roquetas, 164",
    "sg:city":"Roquetas Mar",
    "sg:orig_category":"Piscinas, Accesorios, Suministros (fabricaci\u00d3n, Al Por Mayor)",
    "sg:phone":"+34 950 32 44 42",
    "sg:postcode":"04740",
    "sg:province":"Almer\u00eda",
    "wof:name":"Hydroluz S.l.",
    "wof:placetype":"venue"
},
  "geometry": {"coordinates":[-2.6124989986,36.7638435364],"type":"Point"}
}