{
  "type": "Feature",
  "properties": {
    "iso:country":"ES",
    "sg:address":"Calle de Daniel Defoe, 6",
    "sg:city":"Malaga",
    "sg:orig_category":"Alquiler De V\u00cddeo",
    "sg:phone":"+34 952 35 09 73",
    "sg:postcode":"29006",
    "sg:province":"M\u00e1laga",
    "wof:name":"Leiva Ruiz Josefa",
    "wof:placetype":"venue"
},
  "geometry": {"coordinates":[-4.4645972252,36.7095527649],"type":"Point"}
}