{
  "type": "Feature",
  "properties": {
    "iso:country":"ES",
    "sg:address":"Calle de Segorbe, 3",
    "sg:city":"Valencia",
    "sg:orig_category":"Sellos De Goma Y Met\u00c1licos",
    "sg:phone":"+34 963 41 47 34",
    "sg:postcode":"46004",
    "sg:province":"Valencia",
    "sg:website":"www.viudadepedroruiz.com",
    "wof:name":"Viuda De Pedro Ruiz S. A.",
    "wof:placetype":"venue"
},
  "geometry": {"coordinates":[-0.376372993,39.4650993347],"type":"Point"}
}