{
  "type": "Feature",
  "properties": {
    "iso:country":"ES",
    "sg:address":"Calle de General Ricardos, 5",
    "sg:city":"Barbastro",
    "sg:orig_category":"Ortopedia General",
    "sg:phone":"+34 974 31 30 95",
    "sg:postcode":"22300",
    "sg:province":"Huesca",
    "wof:name":"Ortopedia Monros S.c.",
    "wof:placetype":"venue"
},
  "geometry": {"coordinates":[0.1268189996,42.0363960266],"type":"Point"}
}