{
  "type": "Feature",
  "properties": {
    "addr:full":"Plaz Constitucion, 1 Badajoz Badajoz 06004",
    "addr:housenumber":"1",
    "addr:postcode":"06004",
    "addr:street":"Constitucion",
    "iso:country":"ES",
    "sg:address":"Plaz Constitucion, 1",
    "sg:city":"Badajoz",
    "sg:orig_category":"Bancos",
    "sg:phone":"+34 924 23 31 54",
    "sg:postcode":"06004",
    "sg:province":"Badajoz",
    "sg:website":"www.deutschebank.com",
    "wof:name":"Deutsche Bank S.a.e.",
    "wof:placetype":"venue"
},
  "geometry": {"coordinates":[-6.9726238251,38.874835968],"type":"Point"}
}