{
  "type": "Feature",
  "properties": {
    "iso:country":"ES",
    "sg:address":"Calle de Navas, 51",
    "sg:city":"Zuera",
    "sg:orig_category":"Importaci\u00d3n, Exportaci\u00d3n Y Comercios De Productos Textiles",
    "sg:phone":"+34 976 68 01 71",
    "sg:postcode":"50800",
    "sg:province":"Zaragoza",
    "wof:name":"Marcen Laporta Fernando",
    "wof:placetype":"venue"
},
  "geometry": {"coordinates":[-0.7882999778,41.8684425354],"type":"Point"}
}