{
  "type": "Feature",
  "properties": {
    "addr:full":"Rond Pilar, 17 Badajoz Badajoz 06002",
    "addr:housenumber":"17",
    "addr:postcode":"06002",
    "addr:street":"Pilar",
    "iso:country":"ES",
    "sg:address":"Rond Pilar, 17",
    "sg:city":"Badajoz",
    "sg:orig_category":"Venta, Instalaci\u00d3n De Calefacci\u00d3n",
    "sg:phone":"+34 924 22 23 39",
    "sg:postcode":"06002",
    "sg:province":"Badajoz",
    "wof:name":"Casa Pablo Moreno S.l.",
    "wof:placetype":"venue"
},
  "geometry": {"coordinates":[-6.9698648453,38.8755874634],"type":"Point"}
}