{
  "type": "Feature",
  "properties": {
    "iso:country":"ES",
    "sg:address":"Calle de Papiro (del), S/n",
    "sg:city":"Fuenlabrada",
    "sg:orig_category":"Edici\u00d3n De Diarios, Revistas, Boletines",
    "sg:phone":"+34 916 42 09 90",
    "sg:postcode":"28946",
    "sg:province":"Madrid",
    "sg:website":"www.edebe.com",
    "wof:name":"Sociedad Salesiana San Francisco De Sales. Ediciones Edebe",
    "wof:placetype":"venue"
},
  "geometry": {"coordinates":[-3.7647929192,40.2668952942],"type":"Point"}
}