{
  "type": "Feature",
  "properties": {
    "addr:full":"Carr Calvari, 10 Pollen\u00e7a Islas Baleares 07460",
    "addr:housenumber":"10",
    "addr:postcode":"07460",
    "addr:street":"Carr Calvari;Islas",
    "iso:country":"ES",
    "sg:address":"Carr Calvari, 10",
    "sg:city":"Pollen\u00e7a",
    "sg:orig_category":"Museos",
    "sg:phone":"+34 971 53 28 67",
    "sg:postcode":"07460",
    "sg:province":"Islas Baleares",
    "wof:name":"Galeries Vicens S.a.",
    "wof:placetype":"venue"
},
  "geometry": {"coordinates":[3.0141618252,39.8784637451],"type":"Point"}
}