{
  "type": "Feature",
  "properties": {
    "iso:country":"ES",
    "sg:address":"Calle de Carpinteros, 9",
    "sg:city":"Iznalloz",
    "sg:orig_category":"Sindicatos De Trabajadores",
    "sg:phone":"+34 958 38 47 08",
    "sg:postcode":"18550",
    "sg:province":"Granada",
    "wof:name":"Comisiones Obreras De Andalucia",
    "wof:placetype":"venue"
},
  "geometry": {"coordinates":[-3.5313491821,37.3923606873],"type":"Point"}
}