{
  "type": "Feature",
  "properties": {
    "iso:country":"ES",
    "sg:address":"Centre Comercial Ridaura, S/n",
    "sg:city":"Platja Aro",
    "sg:orig_category":"Platos Preparados Refrigerados (fabricaci\u00d3n, Al Por Mayor)",
    "sg:phone":"+34 972 81 76 70",
    "sg:postcode":"17250",
    "sg:province":"Girona",
    "wof:name":"Gracia Tomas Elvira",
    "wof:placetype":"venue"
},
  "geometry": {"coordinates":[3.0639550686,41.8142547607],"type":"Point"}
}