{
  "type": "Feature",
  "properties": {
    "iso:country":"ES",
    "sg:address":"Calle de Almendralejo, 45",
    "sg:city":"Merida",
    "sg:orig_category":"M\u00c9dicos: Alergolog\u00cda",
    "sg:phone":"+34 924 31 99 53",
    "sg:postcode":"06800",
    "sg:province":"Badajoz",
    "wof:name":"Gil Garcia Manuel",
    "wof:placetype":"venue"
},
  "geometry": {"coordinates":[-6.3439440727,38.9197998047],"type":"Point"}
}