{
  "type": "Feature",
  "properties": {
    "addr:full":"Cno. N. Cno. Roig, 7 Sa Indioteria Islas Baleares 07009",
    "addr:housenumber":"7",
    "addr:postcode":"07009",
    "addr:street":"Cno. N. Cno. Roig;Islas",
    "iso:country":"ES",
    "sg:address":"Cno. N. Cno. Roig, 7",
    "sg:city":"Sa Indioteria",
    "sg:orig_category":"Centros Empresariales",
    "sg:phone":"+34 971 75 04 24",
    "sg:postcode":"07009",
    "sg:province":"Islas Baleares",
    "wof:name":"Balimsa",
    "wof:placetype":"venue"
},
  "geometry": {"coordinates":[2.672440052,39.6167068481],"type":"Point"}
}