{
  "type": "Feature",
  "properties": {
    "addr:full":"Pol Ind Convesa, 5 Badajoz Badajoz 06008",
    "addr:housenumber":"5",
    "addr:postcode":"06008",
    "addr:street":"Convesa",
    "iso:country":"ES",
    "sg:address":"Pol Ind Convesa, 5",
    "sg:city":"Badajoz",
    "sg:orig_category":"Reparaciones Y Remolcado De Veh\u00cdculos",
    "sg:phone":"+34 924 24 84 03",
    "sg:postcode":"06008",
    "sg:province":"Badajoz",
    "wof:name":"Carlain S.l.",
    "wof:placetype":"venue"
},
  "geometry": {"coordinates":[-6.9430441856,38.8723373413],"type":"Point"}
}