{
  "type": "Feature",
  "properties": {
    "addr:full":"Avia Puente Colgante, S/n Valladolid Valladolid 47014",
    "addr:housenumber":"s / n",
    "addr:postcode":"47014",
    "addr:street":"Puente Colgante",
    "iso:country":"ES",
    "sg:address":"Avia Puente Colgante, S/n",
    "sg:city":"Valladolid",
    "sg:orig_category":"Ropa Para Se\u00d1oras Y Caballeros (al Por Menor)",
    "sg:phone":"+34 983 34 24 01",
    "sg:postcode":"47014",
    "sg:province":"Valladolid",
    "wof:name":"C & A Modas S.l.",
    "wof:placetype":"venue"
},
  "geometry": {"coordinates":[-4.7453589439,41.6415557861],"type":"Point"}
}