{
  "type": "Feature",
  "properties": {
    "iso:country":"ES",
    "sg:address":"Avda Bondad (de La), 6",
    "sg:city":"Caceres",
    "sg:orig_category":"Fabricaci\u00d3n De Acumuladores Y De Pilas El\u00c9ctricas",
    "sg:phone":"+34 927 22 69 18",
    "sg:postcode":"10002",
    "sg:province":"C\u00e1ceres",
    "wof:name":"Acedo Salgado Javier Vicente",
    "wof:placetype":"venue"
},
  "geometry": {"coordinates":[-6.3753404617,39.4625549316],"type":"Point"}
}