{
  "type": "Feature",
  "properties": {
    "addr:full":"Calle de Robayna, 8 Santa Cruz De Tenerife Santa Cruz De Tenerife 38003",
    "addr:housenumber":"8",
    "addr:postcode":"38003",
    "addr:street":"Calle De Robayna",
    "iso:country":"ES",
    "sg:address":"Calle de Robayna, 8",
    "sg:city":"Santa Cruz De Tenerife",
    "sg:classifiers":[
        {
            "category":"Personal",
            "subcategory":"Barber",
            "type":"Services"
        }
    ],
    "sg:phone":"+34 922 28 58 02",
    "sg:postcode":"38003",
    "sg:province":"Santa Cruz De Tenerife",
    "sg:tags":[
        "caballeros",
        "de",
        "peluqueros"
    ],
    "wof:name":"Arteaga Alvarez Jose Ramiro",
    "wof:placetype":"venue"
},
  "geometry": {"coordinates":[-16.2548503876,28.4681816101],"type":"Point"}
}