{
  "type": "Feature",
  "properties": {
    "iso:country":"ES",
    "sg:address":"Avda Venezuela, 7",
    "sg:city":"Llanos De Aridane",
    "sg:orig_category":"Radiocomunicaciones, Telefon\u00cda M\u00d3vil, Radiomensajer\u00cda: Servicios, Comercializaci\u00d3n",
    "sg:phone":"+34 922 40 22 21",
    "sg:postcode":"38760",
    "sg:province":"Santa Cruz De Tenerife",
    "wof:name":"Telyco La Palma S.l.",
    "wof:placetype":"venue"
},
  "geometry": {"coordinates":[-17.9123725891,28.6574134827],"type":"Point"}
}