{
  "type": "Feature",
  "properties": {
    "addr:full":"Carrer de Estornell, 11 Pinar Barcelona 08186",
    "addr:housenumber":"11",
    "addr:postcode":"08186",
    "addr:street":"Carrer De Estornell",
    "iso:country":"ES",
    "sg:address":"Carrer de Estornell, 11",
    "sg:city":"Pinar",
    "sg:orig_category":"Fabricaci\u00d3n De Motores El\u00c9ctricos",
    "sg:phone":"+34 938 41 74 92",
    "sg:postcode":"08186",
    "sg:province":"Barcelona",
    "wof:name":"Tancaments Automatics Jorsam S.l.",
    "wof:placetype":"venue"
},
  "geometry": {"coordinates":[2.2382690907,41.612449646],"type":"Point"}
}