{
  "type": "Feature",
  "properties": {
    "addr:full":"Ctra Palencia, 3 Villanueva Campo Zamora 49100",
    "addr:housenumber":"3",
    "addr:postcode":"49100",
    "addr:street":"Ctra Palencia",
    "iso:country":"ES",
    "sg:address":"Ctra Palencia, 3",
    "sg:city":"Villanueva Campo",
    "sg:orig_category":"Reposter\u00cdas",
    "sg:phone":"+34 980 66 64 83",
    "sg:postcode":"49100",
    "sg:province":"Zamora",
    "wof:name":"Pan San Malu S.l.",
    "wof:placetype":"venue"
},
  "geometry": {"coordinates":[-5.4076638222,41.9857406616],"type":"Point"}
}