{
  "type": "Feature",
  "properties": {
    "addr:full":"Calle de Cerca (la), 1 Torredonjimeno Ja\u00e9n 23650",
    "addr:housenumber":"1",
    "addr:postcode":"23650",
    "addr:street":"Calle De Cerca La",
    "iso:country":"ES",
    "sg:address":"Calle de Cerca (la), 1",
    "sg:city":"Torredonjimeno",
    "sg:orig_category":"Alimentaci\u00d3n General (al Por Menor)",
    "sg:phone":"+34 953 57 24 60",
    "sg:postcode":"23650",
    "sg:province":"Ja\u00e9n",
    "wof:name":"Camara Begara Cristina",
    "wof:placetype":"venue"
},
  "geometry": {"coordinates":[-3.9581570625,37.7639541626],"type":"Point"}
}