{
  "type": "Feature",
  "properties": {
    "iso:country":"ES",
    "sg:address":"Psaj Milan, 16",
    "sg:city":"Tejina",
    "sg:orig_category":"Farmacias",
    "sg:phone":"+34 922 54 25 53",
    "sg:postcode":"38260",
    "sg:province":"Santa Cruz De Tenerife",
    "wof:name":"Mendez Alonso Juan Antonio",
    "wof:placetype":"venue"
},
  "geometry": {"coordinates":[-16.3608894348,28.5367546082],"type":"Point"}
}