{
  "type": "Feature",
  "properties": {
    "addr:full":"Carr Es Cos De Gracia, 20 Mao Islas Baleares 07702",
    "addr:housenumber":"20",
    "addr:postcode":"07702",
    "addr:street":"Carr Es;Gracia",
    "iso:country":"ES",
    "sg:address":"Carr Es Cos De Gracia, 20",
    "sg:city":"Mao",
    "sg:orig_category":"Televisi\u00d3n, V\u00cddeo: Aparatos Y Accesorios (venta)",
    "sg:phone":"+34 971 35 41 14",
    "sg:postcode":"07702",
    "sg:province":"Islas Baleares",
    "wof:name":"Laxmicom S.l.",
    "wof:placetype":"venue"
},
  "geometry": {"coordinates":[4.2620358467,39.8875961304],"type":"Point"}
}