{
  "type": "Feature",
  "properties": {
    "iso:country":"ES",
    "sg:address":"Avda Almanzora, 22",
    "sg:city":"Olula Rio",
    "sg:orig_category":"Florister\u00cdas",
    "sg:phone":"+34 950 44 14 19",
    "sg:postcode":"04860",
    "sg:province":"Almer\u00eda",
    "wof:name":"Tijeras Sanchez Maria Jose",
    "wof:placetype":"venue"
},
  "geometry": {"coordinates":[-2.2964839935,37.356048584],"type":"Point"}
}