{
  "type": "Feature",
  "properties": {
    "addr:full":"Calle de Humanes, 10 Fuenlabrada Madrid 28944",
    "addr:housenumber":"10",
    "addr:postcode":"28944",
    "addr:street":"Calle De Humanes",
    "iso:country":"ES",
    "sg:address":"Calle de Humanes, 10",
    "sg:city":"Fuenlabrada",
    "sg:orig_category":"Peluquer\u00cdas, Peluquer\u00cda Mixta",
    "sg:phone":"+34 916 90 64 27",
    "sg:postcode":"28944",
    "sg:province":"Madrid",
    "wof:name":"Aliendre Perez Maria Aida",
    "wof:placetype":"venue"
},
  "geometry": {"coordinates":[-3.7908730507,40.2802772522],"type":"Point"}
}