{
  "type": "Feature",
  "properties": {
    "addr:full":"Barr Iglesia De San Mames (la), 3 San Mames De Meruelo Cantabria 39192",
    "addr:postcode":"39192",
    "addr:street":"La 3 San Mames",
    "iso:country":"ES",
    "sg:address":"Barr Iglesia De San Mames (la), 3",
    "sg:city":"San Mames De Meruelo",
    "sg:orig_category":"Agencias Y Agentes Comerciales, Representantes",
    "sg:phone":"+34 942 63 73 34",
    "sg:postcode":"39192",
    "sg:province":"Cantabria",
    "wof:name":"Pi\u00f1a Cobo Ramon Juan",
    "wof:placetype":"venue"
},
  "geometry": {"coordinates":[-3.566231966,43.4460372925],"type":"Point"}
}