{
  "type": "Feature",
  "properties": {
    "addr:full":"Calle de Monasterio De La Rabida, 4 Zaragoza Zaragoza 50002",
    "addr:housenumber":"4",
    "addr:postcode":"50002",
    "addr:street":"Calle De Monasterio De La Rabida",
    "iso:country":"ES",
    "sg:address":"Calle de Monasterio De La Rabida, 4",
    "sg:city":"Zaragoza",
    "sg:orig_category":"Promotores Constructores",
    "sg:phone":"+34 976 48 60 20",
    "sg:postcode":"50002",
    "sg:province":"Zaragoza",
    "wof:name":"Global Obras S.l.",
    "wof:placetype":"venue"
},
  "geometry": {"coordinates":[-0.8607529998,41.6497764587],"type":"Point"}
}