{
  "type": "Feature",
  "properties": {
    "addr:full":"Avda Cisneros, 1 Cisneros Toledo 45220",
    "addr:housenumber":"1",
    "addr:postcode":"45220",
    "addr:street":"Avda Cisneros",
    "iso:country":"ES",
    "sg:address":"Avda Cisneros, 1",
    "sg:city":"Cisneros",
    "sg:orig_category":"Venta, Instalaci\u00d3n De Cocinas",
    "sg:phone":"+34 925 54 54 86",
    "sg:postcode":"45220",
    "sg:province":"Toledo",
    "wof:name":"De La Lastra Y Fernandez S.l.",
    "wof:placetype":"venue"
},
  "geometry": {"coordinates":[-3.8021290302,40.1144638062],"type":"Point"}
}