{
  "type": "Feature",
  "properties": {
    "addr:full":"Yelmo, 28 Tres Cantos Madrid 28760",
    "addr:housenumber":"28",
    "addr:postcode":"28760",
    "addr:street":"Yelmo",
    "iso:country":"ES",
    "sg:address":"Yelmo, 28",
    "sg:city":"Tres Cantos",
    "sg:classifiers":[
        {
            "category":"Autos & Motor Vehicles",
            "subcategory":"Automobile Sales",
            "type":"Retail Goods"
        }
    ],
    "sg:phone":"+34 918 03 20 16",
    "sg:postcode":"28760",
    "sg:province":"Madrid",
    "wof:name":"Chisus S.l.",
    "wof:placetype":"venue"
},
  "geometry": {"coordinates":[-3.7115690708,40.5986709595],"type":"Point"}
}