{
  "type": "Feature",
  "properties": {
    "addr:full":"Calle de Hoya San Lazaro, 30 Hoyo Las Palmas 35330",
    "addr:housenumber":"30",
    "addr:postcode":"35330",
    "addr:street":"Calle De Hoya San Lazaro;Palmas",
    "iso:country":"ES",
    "sg:address":"Calle de Hoya San Lazaro, 30",
    "sg:city":"Hoyo",
    "sg:orig_category":"Reposter\u00cdas",
    "sg:phone":"+34 928 63 05 71",
    "sg:postcode":"35330",
    "sg:province":"Las Palmas",
    "wof:name":"Ramirez Sanchez Rafael",
    "wof:placetype":"venue"
},
  "geometry": {"coordinates":[9.0760097504,52.7750091553],"type":"Point"}
}