{
  "type": "Feature",
  "properties": {
    "iso:country":"ES",
    "sg:address":"Avda Joaquin Costa, 10",
    "sg:city":"Alcampell",
    "sg:orig_category":"Transportes Por V\u00cdas Navegables",
    "sg:phone":"+34 974 42 09 74",
    "sg:postcode":"22560",
    "sg:province":"Huesca",
    "wof:name":"Cristobal Carrera Jose Maria",
    "wof:placetype":"venue"
},
  "geometry": {"coordinates":[0.4321570098,41.9040489197],"type":"Point"}
}