{
  "type": "Feature",
  "properties": {
    "iso:country":"ES",
    "sg:address":"Carrer de Saragossa (de), 7",
    "sg:city":"Salou",
    "sg:orig_category":"Ropa Para Se\u00d1oras Y Caballeros (al Por Menor)",
    "sg:phone":"+34 977 38 14 24",
    "sg:postcode":"43840",
    "sg:province":"Tarragona",
    "wof:name":"Rodriguez Pertegaz Maria Teresa",
    "wof:placetype":"venue"
},
  "geometry": {"coordinates":[1.1453030109,41.0739097595],"type":"Point"}
}