{
  "type": "Feature",
  "properties": {
    "addr:full":"Monte Do Gozo, S/n Santiago De Compostela La Coru\u00f1a 15820",
    "addr:housenumber":"s / n",
    "addr:postcode":"15820",
    "addr:street":"Corun\u0303A",
    "iso:country":"ES",
    "sg:address":"Monte Do Gozo, S/n",
    "sg:city":"Santiago De Compostela",
    "sg:orig_category":"Hoteles",
    "sg:phone":"+34 981 55 89 42",
    "sg:postcode":"15820",
    "sg:province":"La Coru\u00f1a",
    "wof:name":"Estrella De Santiago S.a.",
    "wof:placetype":"venue"
},
  "geometry": {"coordinates":[-8.4994487762,42.8824653625],"type":"Point"}
}