{
  "type": "Feature",
  "properties": {
    "iso:country":"ES",
    "sg:address":"Calle de General Mu\u00d1oz Arenillas, 13",
    "sg:city":"Cadiz",
    "sg:orig_category":"Asociaciones Y Clubs Deportivos",
    "sg:phone":"+34 956 20 12 13",
    "sg:postcode":"11010",
    "sg:province":"C\u00e1diz",
    "wof:name":"Diaz Crespo Jose Mara",
    "wof:placetype":"venue"
},
  "geometry": {"coordinates":[-6.2771391869,36.505859375],"type":"Point"}
}