{
  "type": "Feature",
  "properties": {
    "iso:country":"ES",
    "sg:address":"Calle de Aserradora, 2",
    "sg:city":"Orcera",
    "sg:orig_category":"M\u00c9dicos: Estomatolog\u00cda",
    "sg:phone":"+34 953 48 09 79",
    "sg:postcode":"23370",
    "sg:province":"Ja\u00e9n",
    "wof:name":"Espadental S.l.l",
    "wof:placetype":"venue"
},
  "geometry": {"coordinates":[-2.6658024788,38.3174781799],"type":"Point"}
}