{
  "type": "Feature",
  "properties": {
    "iso:country":"ES",
    "sg:address":"Calle de Calendula (de La), S/n",
    "sg:city":"Alcobendas",
    "sg:orig_category":"Colchones (fabricaci\u00d3n, Al Por Mayor, Al Por Menor)",
    "sg:phone":"+34 902 46 86 46",
    "sg:postcode":"28...",
    "sg:province":"Madrid",
    "sg:website":"www.noctalia.es",
    "wof:name":"Noctalia",
    "wof:placetype":"venue"
},
  "geometry": {"coordinates":[-3.6309092045,40.4808616638],"type":"Point"}
}