{
  "type": "Feature",
  "properties": {
    "addr:full":"Carrer de Rocafort, 123 Sabadell Barcelona 08205",
    "addr:housenumber":"123",
    "addr:postcode":"08205",
    "addr:street":"Carrer De Rocafort",
    "iso:country":"ES",
    "sg:address":"Carrer de Rocafort, 123",
    "sg:city":"Sabadell",
    "sg:orig_category":"Distribuci\u00d3n De Petr\u00d3leo Y Derivados",
    "sg:phone":"+34 937 12 01 14",
    "sg:postcode":"08205",
    "sg:province":"Barcelona",
    "wof:name":"Rocblume S.a.",
    "wof:placetype":"venue"
},
  "geometry": {"coordinates":[2.0998299122,41.5334892273],"type":"Point"}
}