{
  "type": "Feature",
  "properties": {
    "iso:country":"ES",
    "sg:address":"Carrer de Angel Guimera, 132",
    "sg:city":"Esplugues Llobregat",
    "sg:orig_category":"Caf\u00c9s, Bares, Cervecer\u00cdas",
    "sg:phone":"+34 934 73 16 84",
    "sg:postcode":"08950",
    "sg:province":"Barcelona",
    "wof:name":"Jicago S.c.p",
    "wof:placetype":"venue"
},
  "geometry": {"coordinates":[2.0801599026,41.3754043579],"type":"Point"}
}