{
  "type": "Feature",
  "properties": {
    "addr:full":"Urb Parque Virgen De La Salud, S/n Sig\u00fcenza Guadalajara 19250",
    "addr:housenumber":"/ n",
    "addr:postcode":"19250",
    "addr:street":"Urb Parque Virgen De La Salud S",
    "iso:country":"ES",
    "sg:address":"Urb Parque Virgen De La Salud, S/n",
    "sg:city":"Sig\u00fcenza",
    "sg:orig_category":"Agencias Y Agentes Comerciales, Representantes",
    "sg:phone":"+34 949 39 09 45",
    "sg:postcode":"19250",
    "sg:province":"Guadalajara",
    "wof:name":"Heredia Mayo Vicente",
    "wof:placetype":"venue"
},
  "geometry": {"coordinates":[-2.646914959,41.067855835],"type":"Point"}
}