{
  "type": "Feature",
  "properties": {
    "iso:country":"ES",
    "sg:address":"Carrer de Ricart, 16",
    "sg:city":"S. Adria Besos",
    "sg:orig_category":"Servicios Gsm",
    "sg:phone":"+34 934 62 60 28",
    "sg:postcode":"08930",
    "sg:province":"Barcelona",
    "wof:name":"Pasalavoz S.l.",
    "wof:placetype":"venue"
},
  "geometry": {"coordinates":[2.2172179222,41.4305953979],"type":"Point"}
}