{
  "type": "Feature",
  "properties": {
    "iso:country":"ES",
    "sg:address":"Cra. Nal. Tres-cents Quaranta, S/n",
    "sg:city":"Alcanar-platja",
    "sg:orig_category":"Producci\u00d3n De Champi\u00d1ones",
    "sg:phone":"+34 977 73 70 37",
    "sg:postcode":"43530",
    "sg:province":"Tarragona",
    "sg:website":"www.conservasgarriga.com",
    "wof:name":"Conservas Garriga S. A.",
    "wof:placetype":"venue"
},
  "geometry": {"coordinates":[0.4814749956,40.5420188904],"type":"Point"}
}