{
  "type": "Feature",
  "properties": {
    "addr:full":"Calle de Benito De Rojas, S/n Bujalance C\u00f3rdoba 14650",
    "addr:housenumber":"s / n",
    "addr:postcode":"14650",
    "addr:street":"Calle De Benito De Rojas",
    "iso:country":"ES",
    "sg:address":"Calle de Benito De Rojas, S/n",
    "sg:city":"Bujalance",
    "sg:orig_category":"Internados & Ense\u00d1anza Privada",
    "sg:phone":"+34 957 17 20 22",
    "sg:postcode":"14650",
    "sg:province":"C\u00f3rdoba",
    "wof:name":"Escuelas Profesionales Sagrada Familia",
    "wof:placetype":"venue"
},
  "geometry": {"coordinates":[-4.3830738068,37.8952636719],"type":"Point"}
}