{
  "type": "Feature",
  "properties": {
    "iso:country":"ES",
    "sg:address":"Plaz Santa Barbara, 8",
    "sg:city":"Madrid",
    "sg:orig_category":"Grafistas",
    "sg:phone":"+34 913 08 32 04",
    "sg:postcode":"28004",
    "sg:province":"Madrid",
    "wof:name":"E12 Imagen Global",
    "wof:placetype":"venue"
},
  "geometry": {"coordinates":[-3.7015020847,40.4244041443],"type":"Point"}
}