{
  "type": "Feature",
  "properties": {
    "addr:full":"Calle de 139, S/n Garriga Islas Baleares 07120",
    "addr:housenumber":"139 s / n",
    "addr:postcode":"07120",
    "addr:street":"Calle De",
    "iso:country":"ES",
    "sg:address":"Calle de 139, S/n",
    "sg:city":"Garriga",
    "sg:orig_category":"Colocaci\u00d3n, Mantenimiento, Vitrificaci\u00d3n De Parquets",
    "sg:phone":"+34 971 43 82 42",
    "sg:postcode":"07120",
    "sg:province":"Islas Baleares",
    "wof:name":"Pallicer Selles Sara",
    "wof:placetype":"venue"
},
  "geometry": {"coordinates":[2.8577105999,39.5341796875],"type":"Point"}
}