{
  "type": "Feature",
  "properties": {
    "addr:full":"Calle de Ciudad De Melilla, 4 Arroyo De La Miel-benalmadena Costa M\u00e1laga 29631",
    "addr:housenumber":"4",
    "addr:postcode":"29631",
    "addr:street":"Calle De Ciudad De Melilla;Arroyo De La Miel-Benalmadena Costa Ma\u0301Laga",
    "iso:country":"ES",
    "sg:address":"Calle de Ciudad De Melilla, 4",
    "sg:city":"Arroyo De La Miel-benalmadena Costa",
    "sg:orig_category":"Accesorios Para Tintorer\u00cdas, Limpieza En Seco",
    "sg:phone":"+34 952 56 65 24",
    "sg:postcode":"29631",
    "sg:province":"M\u00e1laga",
    "sg:website":"www.pressto.com",
    "wof:name":"Agual Del Arroyo S.l",
    "wof:placetype":"venue"
},
  "geometry": {"coordinates":[-4.5341486931,36.5965957642],"type":"Point"}
}