{
  "type": "Feature",
  "properties": {
    "addr:full":"Calle de Pescaderias, 8 Aguilar De La Frontera C\u00f3rdoba 14920",
    "addr:housenumber":"8",
    "addr:postcode":"14920",
    "addr:street":"Calle De Pescaderias",
    "iso:country":"ES",
    "sg:address":"Calle de Pescaderias, 8",
    "sg:city":"Aguilar De La Frontera",
    "sg:orig_category":"Inmobiliaria (agencias)",
    "sg:phone":"+34 957 66 16 05",
    "sg:postcode":"14920",
    "sg:province":"C\u00f3rdoba",
    "wof:name":"Luque Lara Antonio",
    "wof:placetype":"venue"
},
  "geometry": {"coordinates":[-4.6558551788,37.5146827698],"type":"Point"}
}