{
  "type": "Feature",
  "properties": {
    "iso:country":"ES",
    "sg:address":"Avda Aragon, 22",
    "sg:city":"Binefar",
    "sg:orig_category":"Reposter\u00cdas",
    "sg:phone":"+34 974 42 89 39",
    "sg:postcode":"22500",
    "sg:province":"Huesca",
    "wof:name":"Sesplugues S.c.",
    "wof:placetype":"venue"
},
  "geometry": {"coordinates":[0.2933999896,41.8502349854],"type":"Point"}
}