{
  "type": "Feature",
  "properties": {
    "addr:full":"Calle de Virgen De Los Remedios, 16 Montanchez C\u00e1ceres 10170",
    "addr:housenumber":"16",
    "addr:postcode":"10170",
    "addr:street":"Calle De Virgen De Los Remedios;Ca\u0301Ceres",
    "iso:country":"ES",
    "sg:address":"Calle de Virgen De Los Remedios, 16",
    "sg:city":"Montanchez",
    "sg:orig_category":"Empresas De Carpinter\u00cda De Madera",
    "sg:phone":"+34 927 38 02 65",
    "sg:postcode":"10170",
    "sg:province":"C\u00e1ceres",
    "wof:name":"Galan Garcia Francisco",
    "wof:placetype":"venue"
},
  "geometry": {"coordinates":[-6.1530489922,39.2244262695],"type":"Point"}
}