{
  "type": "Feature",
  "properties": {
    "addr:full":"Plaz Santiago, 2 Burgos Burgos 09007",
    "addr:housenumber":"2",
    "addr:postcode":"09007",
    "addr:street":"Plaz Santiago",
    "iso:country":"ES",
    "sg:address":"Plaz Santiago, 2",
    "sg:city":"Burgos",
    "sg:orig_category":"Confecci\u00d3n (fabricaci\u00d3n, Al Por Mayor)",
    "sg:phone":"+34 947 23 02 07",
    "sg:postcode":"09007",
    "sg:province":"Burgos",
    "wof:name":"De Benito Cordoba Pedro Luis",
    "wof:placetype":"venue"
},
  "geometry": {"coordinates":[-3.6684761047,42.3495674133],"type":"Point"}
}