{
  "type": "Feature",
  "properties": {
    "iso:country":"ES",
    "sg:address":"Cmn Valverde, S/n",
    "sg:city":"Almaden",
    "sg:orig_category":"Cr\u00cda De Animales",
    "sg:phone":"+34 926 71 04 91",
    "sg:postcode":"13400",
    "sg:province":"Ciudad Real",
    "wof:name":"Cooperativa Ganadera San Anton",
    "wof:placetype":"venue"
},
  "geometry": {"coordinates":[-4.8423290253,38.7738647461],"type":"Point"}
}