{
  "type": "Feature",
  "properties": {
    "addr:full":"Avda Ramon Y Cajal, 4 Marbella M\u00e1laga 29600",
    "addr:housenumber":"4",
    "addr:postcode":"29600",
    "addr:street":"Avda Ramon Y Cajal;Ma\u0301Laga",
    "iso:country":"ES",
    "sg:address":"Avda Ramon Y Cajal, 4",
    "sg:city":"Marbella",
    "sg:orig_category":"Agentes Generales De Seguros",
    "sg:phone":"+34 952 86 55 56",
    "sg:postcode":"29600",
    "sg:province":"M\u00e1laga",
    "wof:name":"Gabinete De Seguros Cimar S.l.",
    "wof:placetype":"venue"
},
  "geometry": {"coordinates":[-4.8845510483,36.5084648132],"type":"Point"}
}