{
  "type": "Feature",
  "properties": {
    "addr:full":"Calle de San Salvador, 5 Huelva Huelva 21003",
    "addr:housenumber":"5",
    "addr:postcode":"21003",
    "addr:street":"Calle De San Salvador",
    "iso:country":"ES",
    "sg:address":"Calle de San Salvador, 5",
    "sg:city":"Huelva",
    "sg:orig_category":"Ropa Para Se\u00d1oras (al Por Menor)",
    "sg:phone":"+34 959 26 22 63",
    "sg:postcode":"21003",
    "sg:province":"Huelva",
    "wof:name":"Rizo Dura Raquel",
    "wof:placetype":"venue"
},
  "geometry": {"coordinates":[-6.9481258392,37.2561073303],"type":"Point"}
}