{
  "type": "Feature",
  "properties": {
    "iso:country":"ES",
    "sg:address":"Calle de Santa Ines, 7",
    "sg:city":"Zaragoza",
    "sg:orig_category":"Panader\u00cdas, Panader\u00cdas",
    "sg:phone":"+34 976 43 27 51",
    "sg:postcode":"50003",
    "sg:province":"Zaragoza",
    "wof:name":"Panaderia Pasteleria Cafeteria Cruz S.l.",
    "wof:placetype":"venue"
},
  "geometry": {"coordinates":[-0.8908630013,41.6573944092],"type":"Point"}
}