{
  "type": "Feature",
  "properties": {
    "addr:full":"Calle de Catalu\u00d1a, 10 Pinto Madrid 28320",
    "addr:housenumber":"10",
    "addr:postcode":"28320",
    "addr:street":"Calle De Catalun\u0303A",
    "iso:country":"ES",
    "sg:address":"Calle de Catalu\u00d1a, 10",
    "sg:city":"Pinto",
    "sg:orig_category":"Papeler\u00cdas: Art\u00cdculos (al Por Mayor)",
    "sg:phone":"+34 916 91 25 39",
    "sg:postcode":"28320",
    "sg:province":"Madrid",
    "wof:name":"Vaca Abarca Abel",
    "wof:placetype":"venue"
},
  "geometry": {"coordinates":[-3.6944050789,40.2473258972],"type":"Point"}
}