{
  "type": "Feature",
  "properties": {
    "iso:country":"ES",
    "sg:address":"Calle de San Jeronimo, 35",
    "sg:city":"Bornos",
    "sg:orig_category":"Muebles Y Accesorios Para Cocinas Y Cuartos De Ba\u00d1o (al Por Menor)",
    "sg:phone":"+34 956 71 25 65",
    "sg:postcode":"11640",
    "sg:province":"C\u00e1diz",
    "wof:name":"Mu\u00f1oz Pozo Francisco Jose",
    "wof:placetype":"venue"
},
  "geometry": {"coordinates":[-5.743311882,36.8173599243],"type":"Point"}
}