{
  "type": "Feature",
  "properties": {
    "addr:full":"Luga Anchosa (de La), 76 Otro La'o Murcia 30600",
    "addr:postcode":"30600",
    "iso:country":"ES",
    "sg:address":"Luga Anchosa (de La), 76",
    "sg:city":"Otro La'o",
    "sg:orig_category":"Frutas Y Legumbres Frescas (al Por Mayor)",
    "sg:phone":"+34 968 67 10 53",
    "sg:postcode":"30600",
    "sg:province":"Murcia",
    "wof:name":"Frutas Gomariz Carbonell S.l.",
    "wof:placetype":"venue"
},
  "geometry": {"coordinates":[-1.1302499771,37.9829597473],"type":"Point"}
}