{
  "type": "Feature",
  "properties": {
    "addr:full":"Carr Regencia D'urgell, 16 Seu D'urgell Lleida 25700",
    "addr:housenumber":"16",
    "addr:postcode":"25700",
    "addr:street":"Carr Regencia D'Urgell",
    "iso:country":"ES",
    "sg:address":"Carr Regencia D'urgell, 16",
    "sg:city":"Seu D'urgell",
    "sg:orig_category":"Juegos Y Juguetes (al Por Menor)",
    "sg:phone":"+34 973 36 07 25",
    "sg:postcode":"25700",
    "sg:province":"Lleida",
    "wof:name":"Establiments Cortina S.l.",
    "wof:placetype":"venue"
},
  "geometry": {"coordinates":[0.6457189918,41.6027946472],"type":"Point"}
}