{
  "type": "Feature",
  "properties": {
    "addr:full":"Calle de Cifuentes, 15 Guadalajara Guadalajara 19003",
    "addr:housenumber":"15",
    "addr:postcode":"19003",
    "addr:street":"Calle De Cifuentes",
    "iso:country":"ES",
    "sg:address":"Calle de Cifuentes, 15",
    "sg:city":"Guadalajara",
    "sg:orig_category":"Empresarios",
    "sg:phone":"+34 949 22 42 43",
    "sg:postcode":"19003",
    "sg:province":"Guadalajara",
    "wof:name":"Notario Sancho Juana",
    "wof:placetype":"venue"
},
  "geometry": {"coordinates":[-3.172606945,40.6299171448],"type":"Point"}
}