{
  "type": "Feature",
  "properties": {
    "iso:country":"ES",
    "sg:address":"Calle de Agustin Querol, 8",
    "sg:city":"Madrid",
    "sg:orig_category":"Agencias Y Asesores De Publicidad",
    "sg:phone":"+34 915 01 43 89",
    "sg:postcode":"28014",
    "sg:province":"Madrid",
    "wof:name":"New Prokin S.l.",
    "wof:placetype":"venue"
},
  "geometry": {"coordinates":[-3.6824054718,40.4076309204],"type":"Point"}
}