{
  "type": "Feature",
  "properties": {
    "iso:country":"ES",
    "sg:address":"Estd Vilan, 15",
    "sg:city":"Camari\u00f1as",
    "sg:orig_category":"Fabricaci\u00d3n, Reparaci\u00d3n Y Mantenimiento De Construcciones Navales Y Fluviales",
    "sg:phone":"+34 981 73 60 56",
    "sg:postcode":"15123",
    "sg:province":"A Coru\u00f1a",
    "wof:name":"Talleres Hermanos Vigo Tajes S.l",
    "wof:placetype":"venue"
},
  "geometry": {"coordinates":[-9.1833839417,43.1295585632],"type":"Point"}
}