{
  "type": "Feature",
  "properties": {
    "addr:full":"Ctra Jerez-cartagena, S/n Pruna Sevilla 41670",
    "addr:housenumber":"s / n",
    "addr:postcode":"41670",
    "addr:street":"Ctra Jerez-Cartagena",
    "iso:country":"ES",
    "sg:address":"Ctra Jerez-cartagena, S/n",
    "sg:city":"Pruna",
    "sg:orig_category":"Agricultores, Agricultores",
    "sg:phone":"+34 954 85 80 09",
    "sg:postcode":"41670",
    "sg:province":"Sevilla",
    "wof:name":"Explotaciones Agricolas San Rafael Sa",
    "wof:placetype":"venue"
},
  "geometry": {"coordinates":[-5.2234740257,36.9747581482],"type":"Point"}
}