{
  "type": "Feature",
  "properties": {
    "addr:full":"Plaza Haro, 7 Bilbao Vizcaya 48006",
    "addr:housenumber":"7",
    "addr:postcode":"48006",
    "addr:street":"Haro",
    "iso:country":"ES",
    "sg:address":"Plaza Haro, 7",
    "sg:city":"Bilbao",
    "sg:orig_category":"Molduras, Junquillos, Listones Y Molduras Perforadas",
    "sg:phone":"+34 944 73 47 27",
    "sg:postcode":"48006",
    "sg:province":"Vizcaya",
    "wof:name":"David Menor Conde",
    "wof:placetype":"venue"
},
  "geometry": {"coordinates":[-2.9121670723,43.2555351257],"type":"Point"}
}