{
  "type": "Feature",
  "properties": {
    "addr:full":"Afores, S/n Fonteta Girona 17110",
    "addr:housenumber":"s / n",
    "addr:postcode":"17110",
    "addr:street":"Afores",
    "iso:country":"ES",
    "sg:address":"Afores, S/n",
    "sg:city":"Fonteta",
    "sg:orig_category":"Animales (al Por Menor)",
    "sg:phone":"+34 972 64 69 21",
    "sg:postcode":"17110",
    "sg:province":"Girona",
    "wof:name":"Eurostru\u00e7 Baix Emporda S.l.",
    "wof:placetype":"venue"
},
  "geometry": {"coordinates":[3.0577399731,41.9499855042],"type":"Point"}
}