{
  "type": "Feature",
  "properties": {
    "addr:full":"Carretera Orense, 61 Priaranza Del Bierzo Le\u00f3n 24448",
    "addr:housenumber":"61",
    "addr:postcode":"24448",
    "addr:street":"Carretera Orense",
    "iso:country":"ES",
    "sg:address":"Carretera Orense, 61",
    "sg:city":"Priaranza Del Bierzo",
    "sg:orig_category":"Cajas De Ahorro",
    "sg:phone":"+34 987 42 08 41",
    "sg:postcode":"24448",
    "sg:province":"Le\u00f3n",
    "sg:website":"www.caixagalicia.es",
    "wof:name":"Bt Espa\u00d1a Compa\u00d1ia De Servicios Globales De Telecomunicaciones S.a.u.",
    "wof:placetype":"venue"
},
  "geometry": {"coordinates":[-6.6721191406,42.5083999634],"type":"Point"}
}