{
  "type": "Feature",
  "properties": {
    "addr:full":"Avda Conde De Vallellano, 17 Cordoba C\u00f3rdoba 14004",
    "addr:housenumber":"17",
    "addr:postcode":"14004",
    "addr:street":"Avda Conde De Vallellano;Co\u0301Rdoba",
    "iso:country":"ES",
    "sg:address":"Avda Conde De Vallellano, 17",
    "sg:city":"Cordoba",
    "sg:orig_category":"M\u00c9dicos: Psiquiatr\u00cda",
    "sg:phone":"+34 957 42 06 96",
    "sg:postcode":"14004",
    "sg:province":"C\u00f3rdoba",
    "wof:name":"Burgos Marin Rafael De",
    "wof:placetype":"venue"
},
  "geometry": {"coordinates":[-4.7852458954,37.8764686584],"type":"Point"}
}