{
  "type": "Feature",
  "properties": {
    "addr:full":"Cabo Machichaco, 78 Urb. Golf Madrid 28290",
    "addr:housenumber":"78",
    "addr:postcode":"28290",
    "addr:street":"Machichaco",
    "iso:country":"ES",
    "sg:address":"Cabo Machichaco, 78",
    "sg:city":"Urb. Golf",
    "sg:orig_category":"Inversiones",
    "sg:phone":"+34 916 30 22 25",
    "sg:postcode":"28290",
    "sg:province":"Madrid",
    "wof:name":"Compurrenta Consulting S.l",
    "wof:placetype":"venue"
},
  "geometry": {"coordinates":[-3.9148819447,40.5492324829],"type":"Point"}
}