{
  "type": "Feature",
  "properties": {
    "iso:country":"ES",
    "sg:address":"Pg Vilanova, 3",
    "sg:city":"Sitges",
    "sg:orig_category":"M\u00c9dicos: Estomatolog\u00cda",
    "sg:phone":"+34 938 94 77 03",
    "sg:postcode":"08870",
    "sg:province":"Barcelona",
    "wof:name":"Marino Gorkin Hector Alfonso",
    "wof:placetype":"venue"
},
  "geometry": {"coordinates":[1.8067649603,41.2381095886],"type":"Point"}
}