{
  "type": "Feature",
  "properties": {
    "iso:country":"ES",
    "sg:address":"La Lera, S/n",
    "sg:city":"Gra\u00f1en",
    "sg:orig_category":"Empresas De Carpinter\u00cda Met\u00c1lica",
    "sg:phone":"+34 974 39 11 65",
    "sg:postcode":"22260",
    "sg:province":"Huesca",
    "wof:name":"Abadia Azagra Javier Francisco",
    "wof:placetype":"venue"
},
  "geometry": {"coordinates":[-0.35,41.966667],"type":"Point"}
}