{
  "type": "Feature",
  "properties": {
    "iso:country":"ES",
    "sg:address":"Carrer de Sant Elies, 18",
    "sg:city":"Barcelona",
    "sg:orig_category":"Doctores En Medicina",
    "sg:phone":"+34 934 14 76 71",
    "sg:postcode":"08006",
    "sg:province":"Barcelona",
    "wof:name":"Rius Latorre Juan",
    "wof:placetype":"venue"
},
  "geometry": {"coordinates":[2.1445419788,41.4013938904],"type":"Point"}
}