{
  "type": "Feature",
  "properties": {
    "iso:country":"ES",
    "sg:address":"Autopista Burgos-malzaga, S/n",
    "sg:city":"Ameyugo",
    "sg:orig_category":"Distribuci\u00d3n De Petr\u00d3leo Y Derivados",
    "sg:phone":"+34 947 34 44 47",
    "sg:postcode":"09219",
    "sg:province":"Burgos",
    "wof:name":"Gestvilar 2003 S.a.",
    "wof:placetype":"venue"
},
  "geometry": {"coordinates":[-3.0773189068,42.6026649475],"type":"Point"}
}