{
  "type": "Feature",
  "properties": {
    "iso:country":"ES",
    "sg:address":"Calle de Veintiocho De Febrero, 1",
    "sg:city":"Villalba Alcor",
    "sg:orig_category":"Productores Recolectores, Venta Directa De Vinos",
    "sg:phone":"+34 959 42 11 81",
    "sg:postcode":"21860",
    "sg:province":"Huelva",
    "wof:name":"Cooperativa Del Campo Santa Agueda",
    "wof:placetype":"venue"
},
  "geometry": {"coordinates":[-6.4757761955,37.3971633911],"type":"Point"}
}