{
  "type": "Feature",
  "properties": {
    "iso:country":"ES",
    "sg:address":"Avgd Garrigues, 13",
    "sg:city":"Lleida",
    "sg:orig_category":"Electrodom\u00c9sticos (al Por Menor)",
    "sg:phone":"+34 973 20 44 45",
    "sg:postcode":"25001",
    "sg:province":"Lleida",
    "wof:name":"Sanchez Gonzalez Domingo",
    "wof:placetype":"venue"
},
  "geometry": {"coordinates":[0.6320059896,41.6117782593],"type":"Point"}
}