{
  "type": "Feature",
  "properties": {
    "addr:full":"Calle de Fondilla, 1 Santa Maria Del Paramo Le\u00f3n 24240",
    "addr:housenumber":"1",
    "addr:postcode":"24240",
    "addr:street":"Calle De Fondilla",
    "iso:country":"ES",
    "sg:address":"Calle de Fondilla, 1",
    "sg:city":"Santa Maria Del Paramo",
    "sg:orig_category":"Molduras, Junquillos, Listones Y Molduras Perforadas",
    "sg:phone":"+34 987 35 17 20",
    "sg:postcode":"24240",
    "sg:province":"Le\u00f3n",
    "wof:name":"De Paz Cabello Ana Maria",
    "wof:placetype":"venue"
},
  "geometry": {"coordinates":[-5.7455439568,42.3556785583],"type":"Point"}
}