{
  "type": "Feature",
  "properties": {
    "iso:country":"ES",
    "sg:address":"Carrer de Arago, 557",
    "sg:city":"Barcelona",
    "sg:classifiers":[
        {
            "category":"Building & Trades",
            "subcategory":"Construction",
            "type":"Services"
        }
    ],
    "sg:phone":"+34 932 32 31 08",
    "sg:postcode":"08026",
    "sg:province":"Barcelona",
    "sg:tags":[
        "calefacci\u00d3n",
        "central",
        "para",
        "de",
        "fabricaci\u00d3n",
        "caldera"
    ],
    "wof:name":"Valles Gil Pere",
    "wof:placetype":"venue"
},
  "geometry": {"coordinates":[2.1845839024,41.4071388245],"type":"Point"}
}