{
  "type": "Feature",
  "properties": {
    "iso:country":"ES",
    "sg:address":"Cmno Ronda (de), 172",
    "sg:city":"Granada",
    "sg:orig_category":"Negocio De Materiales De Construcci\u00d3n",
    "sg:phone":"+34 958 20 97 97",
    "sg:postcode":"18003",
    "sg:province":"Granada",
    "wof:name":"Framinsa S.l.",
    "wof:placetype":"venue"
},
  "geometry": {"coordinates":[-3.6116530895,37.1802520752],"type":"Point"}
}