{
  "type": "Feature",
  "properties": {
    "addr:full":"Avda Generalisimo, S/n Pacios Lugo 27611",
    "addr:housenumber":"s / n",
    "addr:postcode":"27611",
    "addr:street":"Avda Generalisimo",
    "iso:country":"ES",
    "sg:address":"Avda Generalisimo, S/n",
    "sg:city":"Pacios",
    "sg:orig_category":"Instalaci\u00d3n, Reparaci\u00d3n De Calefacci\u00d3n Por Gas",
    "sg:phone":"+34 982 54 12 15",
    "sg:postcode":"27611",
    "sg:province":"Lugo",
    "wof:name":"Ruxidoira S.l.",
    "wof:placetype":"venue"
},
  "geometry": {"coordinates":[-7.5675940514,42.7657356262],"type":"Point"}
}