{
  "type": "Feature",
  "properties": {
    "addr:full":"Cmno Miranda, 13 Salamanca Salamanca 37008",
    "addr:housenumber":"13",
    "addr:postcode":"37008",
    "addr:street":"Cmno Miranda",
    "iso:country":"ES",
    "sg:address":"Cmno Miranda, 13",
    "sg:city":"Salamanca",
    "sg:orig_category":"Transportes De Animales Vivos",
    "sg:phone":"+34 923 19 29 75",
    "sg:postcode":"37008",
    "sg:province":"Salamanca",
    "wof:name":"Martin Lorenzo Marcelino",
    "wof:placetype":"venue"
},
  "geometry": {"coordinates":[-5.670853138,40.9516792297],"type":"Point"}
}