{
  "type": "Feature",
  "properties": {
    "iso:country":"ES",
    "sg:address":"Calle de Mieres, 11",
    "sg:city":"Madrid",
    "sg:orig_category":"Ropa Para Se\u00d1oras Y Caballeros (al Por Menor)",
    "sg:phone":"+34 917 54 04 87",
    "sg:postcode":"28037",
    "sg:province":"Madrid",
    "wof:name":"Padilla Perez Marcelina",
    "wof:placetype":"venue"
},
  "geometry": {"coordinates":[-3.6299169064,40.4293441772],"type":"Point"}
}