{
  "type": "Feature",
  "properties": {
    "iso:country":"ES",
    "sg:address":"Pase Direccion, 101",
    "sg:city":"Madrid",
    "sg:orig_category":"Plomeros",
    "sg:phone":"+34 913 11 19 78",
    "sg:postcode":"28039",
    "sg:province":"Madrid",
    "wof:name":"Castineira Instalaciones S.l.",
    "wof:placetype":"venue"
},
  "geometry": {"coordinates":[-3.7058880329,40.4606552124],"type":"Point"}
}