{
  "type": "Feature",
  "properties": {
    "addr:full":"Calle de Hernandez De Tejada, 10 Madrid Madrid 28027",
    "addr:housenumber":"10",
    "addr:postcode":"madrid;28027",
    "addr:street":"Calle De Hernandez De Tejada",
    "iso:country":"ES",
    "sg:address":"Calle de Hernandez De Tejada, 10",
    "sg:city":"Madrid",
    "sg:orig_category":"Agricultura: Abastecimiento Y Cosechado (negocio)",
    "sg:phone":"+34 913 67 85 74",
    "sg:postcode":"28027",
    "sg:province":"Madrid",
    "wof:name":"Maria Dolores Amparo Valdemoro Gimenez Jose Maria Valdemoro Gimenez C.b.",
    "wof:placetype":"venue"
},
  "geometry": {"coordinates":[-3.6505999565,40.4471321106],"type":"Point"}
}