{
  "type": "Feature",
  "properties": {
    "iso:country":"ES",
    "sg:address":"Calle de Jardines, 48",
    "sg:city":"Linea De La Concepcion",
    "sg:orig_category":"Inform\u00c1tica, Ofim\u00c1tica (estudios, Asesor\u00cda, Ingenier\u00cda, Formaci\u00d3n)",
    "sg:phone":"+34 956 76 21 27",
    "sg:postcode":"11300",
    "sg:province":"C\u00e1diz",
    "sg:website":"www.beep.es",
    "wof:name":"Dis Servi 2001 S.l.",
    "wof:placetype":"venue"
},
  "geometry": {"coordinates":[-5.3401889801,36.1617507935],"type":"Point"}
}