{
  "type": "Feature",
  "properties": {
    "addr:full":"Carr Falgas, 15 Girona Girona 17005",
    "addr:housenumber":"15",
    "addr:postcode":"17005",
    "addr:street":"Carr Falgas",
    "iso:country":"ES",
    "sg:address":"Carr Falgas, 15",
    "sg:city":"Girona",
    "sg:orig_category":"Empresas De Portes Y Mensajer\u00cda",
    "sg:phone":"+34 972 41 07 07",
    "sg:postcode":"17005",
    "sg:province":"Girona",
    "sg:website":"www.halcourier.es",
    "wof:name":"Recader Cardenas S.l.",
    "wof:placetype":"venue"
},
  "geometry": {"coordinates":[2.8020050526,41.9573364258],"type":"Point"}
}