{
  "type": "Feature",
  "properties": {
    "iso:country":"ES",
    "sg:address":"Calle de Panaderos, 4",
    "sg:city":"Valladolid",
    "sg:orig_category":"Ingenier\u00cda, Centros De Estudios (diversos)",
    "sg:phone":"+34 983 30 62 55",
    "sg:postcode":"47004",
    "sg:province":"Valladolid",
    "sg:website":"www.agroindus.es",
    "wof:name":"Agroindus S.l.",
    "wof:placetype":"venue"
},
  "geometry": {"coordinates":[-4.7241930962,41.6483154297],"type":"Point"}
}