{
  "type": "Feature",
  "properties": {
    "iso:country":"ES",
    "sg:address":"Avda Catalu\u00f1a P I Cogullada, 148",
    "sg:city":"Zaragoza",
    "sg:orig_category":"Geolog\u00cda Y Geof\u00cdsica",
    "sg:phone":"+34 976 18 93 30",
    "sg:postcode":"50014",
    "sg:province":"Zaragoza",
    "wof:name":"Geologia Aplicada Ingenieria Ambiental S.l.",
    "wof:placetype":"venue"
},
  "geometry": {"coordinates":[-0.8813189864,41.6517295837],"type":"Point"}
}