{
  "type": "Feature",
  "properties": {
    "iso:country":"ES",
    "sg:address":"Carrer de Escultors Claperos, 36",
    "sg:city":"Barcelona",
    "sg:orig_category":"Ense\u00d1anza Variada",
    "sg:phone":"+34 932 46 94 41",
    "sg:postcode":"08018",
    "sg:province":"Barcelona",
    "sg:website":"www.grupfast.com",
    "wof:name":"General Fast Service Company S.a.",
    "wof:placetype":"venue"
},
  "geometry": {"coordinates":[2.1891698837,41.4067611694],"type":"Point"}
}