{
  "type": "Feature",
  "properties": {
    "addr:full":"Calle de San Felipe, 2 Atarfe Granada 18230",
    "addr:housenumber":"2",
    "addr:postcode":"18230",
    "addr:street":"Calle De San Felipe",
    "iso:country":"ES",
    "sg:address":"Calle de San Felipe, 2",
    "sg:city":"Atarfe",
    "sg:orig_category":"Carnicer\u00cdas, Carnicer\u00cdas",
    "sg:phone":"+34 958 43 81 54",
    "sg:postcode":"18230",
    "sg:province":"Granada",
    "wof:name":"Lopez Carmona Julio",
    "wof:placetype":"venue"
},
  "geometry": {"coordinates":[-3.6872136593,37.2227516174],"type":"Point"}
}