{
  "type": "Feature",
  "properties": {
    "iso:country":"ES",
    "sg:address":"Carrer de Sant Antoni Maria Claret, 362",
    "sg:city":"Barcelona",
    "sg:orig_category":"Institutos De Belleza",
    "sg:phone":"+34 934 55 42 49",
    "sg:postcode":"08041",
    "sg:province":"Barcelona",
    "wof:name":"Essencial Estetic S.l.",
    "wof:placetype":"venue"
},
  "geometry": {"coordinates":[2.1816649437,41.416519165],"type":"Point"}
}