{
  "type": "Feature",
  "properties": {
    "addr:full":"Avda Madariaga, 17 Bilbao Vizcaya 48014",
    "addr:housenumber":"17",
    "addr:postcode":"48014",
    "addr:street":"Avda Madariaga",
    "iso:country":"ES",
    "sg:address":"Avda Madariaga, 17",
    "sg:city":"Bilbao",
    "sg:orig_category":"Tintes (fabricaci\u00d3n, Al Por Mayor)",
    "sg:phone":"+34 944 02 92 08",
    "sg:postcode":"48014",
    "sg:province":"Vizcaya",
    "wof:name":"Time For Heroes,s.l.",
    "wof:placetype":"venue"
},
  "geometry": {"coordinates":[-2.9468541145,43.2709274292],"type":"Point"}
}