{
  "type": "Feature",
  "properties": {
    "addr:full":"Av Diputacio, 66 Cambrils Tarragona 43850",
    "addr:housenumber":"66",
    "addr:postcode":"43850",
    "addr:street":"Av Diputacio",
    "iso:country":"ES",
    "sg:address":"Av Diputacio, 66",
    "sg:city":"Cambrils",
    "sg:orig_category":"Inmobiliaria (agencias)",
    "sg:phone":"+34 977 36 27 87",
    "sg:postcode":"43850",
    "sg:province":"Tarragona",
    "wof:name":"Xyc 21.expander Inmobiliaria S.l",
    "wof:placetype":"venue"
},
  "geometry": {"coordinates":[1.0904562473,41.0672607422],"type":"Point"}
}