{
  "type": "Feature",
  "properties": {
    "iso:country":"ES",
    "sg:address":"Calle de Gordoniz, 90",
    "sg:city":"Bilbao",
    "sg:orig_category":"Quincaller\u00cda (al Por Menor)",
    "sg:phone":"+34 944 21 33 32",
    "sg:postcode":"48002",
    "sg:province":"Vizcaya",
    "wof:name":"Campo Garrido Jose Luis Del",
    "wof:placetype":"venue"
},
  "geometry": {"coordinates":[-2.9469599724,43.2496414185],"type":"Point"}
}