{
  "type": "Feature",
  "properties": {
    "addr:full":"Pase Encarnacion (de La), S/n Avila \u00c1vila 05005",
    "addr:housenumber":"s",
    "addr:postcode":"05005",
    "addr:street":"/ N;A\u0301Vila",
    "iso:country":"ES",
    "sg:address":"Pase Encarnacion (de La), S/n",
    "sg:city":"Avila",
    "sg:orig_category":"Museos",
    "sg:phone":"+34 920 21 12 12",
    "sg:postcode":"05005",
    "sg:province":"\u00c1vila",
    "wof:name":"Carmelitas Descalzas De La Encarnacion",
    "wof:placetype":"venue"
},
  "geometry": {"coordinates":[-4.6997170448,40.6599845886],"type":"Point"}
}