{
  "type": "Feature",
  "properties": {
    "iso:country":"ES",
    "sg:address":"Carrer de Mar (la), 53",
    "sg:city":"Denia",
    "sg:orig_category":"Molduras, Junquillos, Listones Y Molduras Perforadas",
    "sg:phone":"+34 966 42 21 57",
    "sg:postcode":"03700",
    "sg:province":"Alicante",
    "wof:name":"Romero Calero Jesus",
    "wof:placetype":"venue"
},
  "geometry": {"coordinates":[0.1104720011,38.8426170349],"type":"Point"}
}