{
  "type": "Feature",
  "properties": {
    "addr:full":"Rond Barcelona, 33 Figueres Girona 17600",
    "addr:postcode":"17600",
    "iso:country":"ES",
    "sg:address":"Rond Barcelona, 33",
    "sg:city":"Figueres",
    "sg:orig_category":"Agentes, Concesionarios Y Sucursales De Veh\u00cdculos",
    "sg:phone":"+34 972 67 51 61",
    "sg:postcode":"17600",
    "sg:province":"Girona",
    "wof:name":"Interfren S.a.",
    "wof:placetype":"venue"
},
  "geometry": {"coordinates":[2.9603900909,42.2598609924],"type":"Point"}
}