{
  "type": "Feature",
  "properties": {
    "iso:country":"ES",
    "sg:address":"Av. Roncesvalles, 8",
    "sg:city":"Iru\u00f1a",
    "sg:classifiers":[
        {
            "category":"Autos & Motor Vehicles",
            "subcategory":"Automobile Sales",
            "type":"Retail Goods"
        }
    ],
    "sg:phone":"+34 948 22 69 86",
    "sg:postcode":"31002",
    "sg:province":"Navarra",
    "wof:name":"Arizcuren Arana Miguel Angel",
    "wof:placetype":"venue"
},
  "geometry": {"coordinates":[-1.6414014101,42.8147544861],"type":"Point"}
}