{
  "type": "Feature",
  "properties": {
    "iso:country":"ES",
    "sg:address":"Av Sebastian Souviron Utrera, S/n",
    "sg:city":"Torremolinos",
    "sg:orig_category":"Cajas De Ahorro",
    "sg:phone":"+34 952 05 80 68",
    "sg:postcode":"29620",
    "sg:province":"M\u00e1laga",
    "wof:name":"Caja De Ahorros Y Monte De Piedad De Cordoba",
    "wof:placetype":"venue"
},
  "geometry": {"coordinates":[-4.5099439621,36.6166954041],"type":"Point"}
}