{
  "type": "Feature",
  "properties": {
    "addr:full":"Avda Europa (de), 5 Montilla C\u00f3rdoba 14550",
    "addr:housenumber":"5",
    "addr:postcode":"14550",
    "addr:street":"Avda Europa De;Co\u0301Rdoba",
    "iso:country":"ES",
    "sg:address":"Avda Europa (de), 5",
    "sg:city":"Montilla",
    "sg:orig_category":"Comercio De Piezas De Recambio Y De Accesorios De Veh\u00cdculos, Veh\u00cdculos Industriales",
    "sg:phone":"+34 957 65 51 44",
    "sg:postcode":"14550",
    "sg:province":"C\u00f3rdoba",
    "wof:name":"Recambios Marcasur S.l.",
    "wof:placetype":"venue"
},
  "geometry": {"coordinates":[-4.652654171,37.5796966553],"type":"Point"}
}