{
  "type": "Feature",
  "properties": {
    "iso:country":"ES",
    "sg:address":"Calle de Ca\u00d1ada, S/n",
    "sg:city":"Priego Cordoba",
    "sg:orig_category":"Mec\u00c1nico Del Autom\u00d3vil",
    "sg:phone":"+34 957 54 07 31",
    "sg:postcode":"14800",
    "sg:province":"C\u00f3rdoba",
    "wof:name":"Rosa Delgado Rogelio",
    "wof:placetype":"venue"
},
  "geometry": {"coordinates":[-4.1957321167,37.4339942932],"type":"Point"}
}