{
  "type": "Feature",
  "properties": {
    "addr:full":"R. Cajal, 6 Albox Almer\u00eda 04800",
    "addr:housenumber":"6",
    "addr:postcode":"04800",
    "addr:street":"R. Cajal",
    "iso:country":"ES",
    "sg:address":"R. Cajal, 6",
    "sg:city":"Albox",
    "sg:orig_category":"Bisuter\u00cda, Joyer\u00cda, Relojer\u00cda (al Por Menor)",
    "sg:phone":"+34 950 43 08 25",
    "sg:postcode":"04800",
    "sg:province":"Almer\u00eda",
    "wof:name":"Orosul Del Guadalentin S.l.",
    "wof:placetype":"venue"
},
  "geometry": {"coordinates":[-2.1477439404,37.387512207],"type":"Point"}
}