{
  "type": "Feature",
  "properties": {
    "iso:country":"ES",
    "sg:address":"Avda Capuchinos, 6",
    "sg:city":"Castellon",
    "sg:orig_category":"M\u00c9dicos: Neurolog\u00cda",
    "sg:phone":"+34 964 22 74 49",
    "sg:postcode":"12004",
    "sg:province":"Castell\u00f3n",
    "wof:name":"Cerda Fayos Jose",
    "wof:placetype":"venue"
},
  "geometry": {"coordinates":[-0.0337570012,39.9895210266],"type":"Point"}
}