{
  "type": "Feature",
  "properties": {
    "iso:country":"ES",
    "sg:address":"Luga Urreas (los), S/n",
    "sg:city":"San Javier",
    "sg:orig_category":"Agentes, Concesionarios Y Sucursales De Veh\u00cdculos",
    "sg:phone":"+34 968 19 26 68",
    "sg:postcode":"30730",
    "sg:province":"Murcia",
    "sg:website":"www.bmw.es",
    "wof:name":"Aupesan S.l.",
    "wof:placetype":"venue"
},
  "geometry": {"coordinates":[-0.8389251828,37.8164138794],"type":"Point"}
}