{
  "type": "Feature",
  "properties": {
    "addr:full":"Pl Rei Joan Carles I (del), 2 Perello Tarragona 43519",
    "addr:postcode":"43519",
    "addr:street":"Pl;Joan",
    "iso:country":"ES",
    "sg:address":"Pl Rei Joan Carles I (del), 2",
    "sg:city":"Perello",
    "sg:orig_category":"Empresarios",
    "sg:phone":"+34 977 49 05 35",
    "sg:postcode":"43519",
    "sg:province":"Tarragona",
    "wof:name":"Fandos Marti Rafael",
    "wof:placetype":"venue"
},
  "geometry": {"coordinates":[0.7132700086,40.8763809204],"type":"Point"}
}