{
  "type": "Feature",
  "properties": {
    "iso:country":"ES",
    "sg:address":"Ctra. Santo Domingo, Km. 0002,3",
    "sg:city":"Pozanco",
    "sg:orig_category":"Poller\u00cda Y Caza (al Por Menor)",
    "sg:phone":"+34 920 20 83 48",
    "sg:postcode":"05295",
    "sg:province":"\u00c1vila",
    "wof:name":"Avicola Jimenez S.l.",
    "wof:placetype":"venue"
},
  "geometry": {"coordinates":[-4.6139683723,40.8140220642],"type":"Point"}
}