{
  "type": "Feature",
  "properties": {
    "addr:full":"Pg Progres, 4 Olesa Montserrat Barcelona 08640",
    "addr:housenumber":"4",
    "addr:postcode":"08640",
    "addr:street":"Pg Progres;Barcelona",
    "iso:country":"ES",
    "sg:address":"Pg Progres, 4",
    "sg:city":"Olesa Montserrat",
    "sg:orig_category":"Arquitectos",
    "sg:phone":"+34 937 78 14 44",
    "sg:postcode":"08640",
    "sg:province":"Barcelona",
    "wof:name":"Campmany Boada Jose",
    "wof:placetype":"venue"
},
  "geometry": {"coordinates":[1.8943099976,41.5432357788],"type":"Point"}
}