{
  "type": "Feature",
  "properties": {
    "iso:country":"ES",
    "sg:address":"Bo. Farban, 25",
    "sg:city":"Farban",
    "sg:orig_category":"T\u00c9cnicos Veterinarios",
    "sg:phone":"+34 982 53 25 84",
    "sg:postcode":"27619",
    "sg:province":"Lugo",
    "wof:name":"Pereira Mon Carmen",
    "wof:placetype":"venue"
},
  "geometry": {"coordinates":[-7.4538807869,42.7401275635],"type":"Point"}
}