{
  "type": "Feature",
  "properties": {
    "iso:country":"ES",
    "sg:address":"Calle de Granada, 180",
    "sg:city":"Almeria",
    "sg:orig_category":"Pintura Y Barniz (al Por Menor)",
    "sg:phone":"+34 950 24 47 09",
    "sg:postcode":"04008",
    "sg:province":"Almer\u00eda",
    "wof:name":"Juan Y Antonio Rodriguez Villar S.l.",
    "wof:placetype":"venue"
},
  "geometry": {"coordinates":[-2.4576840401,36.8473510742],"type":"Point"}
}