{
  "type": "Feature",
  "properties": {
    "iso:country":"ES",
    "sg:address":"Praz Mosteiro, S/n",
    "sg:city":"Mosteiro",
    "sg:orig_category":"Iglesia Cat\u00d3lica",
    "sg:phone":"+34 986 48 21 71",
    "sg:postcode":"36313",
    "sg:province":"Pontevedra",
    "wof:name":"Obispado Tui-vigo. Parroquia De Santiago De Bembrive",
    "wof:placetype":"venue"
},
  "geometry": {"coordinates":[-8.6853733063,42.2050933838],"type":"Point"}
}