{
  "type": "Feature",
  "properties": {
    "iso:country":"ES",
    "sg:address":"El Agua, S/n",
    "sg:city":"Fabero",
    "sg:orig_category":"Carnicer\u00cdas, Carnicer\u00cdas",
    "sg:phone":"+34 987 55 10 55",
    "sg:postcode":"24420",
    "sg:province":"Le\u00f3n",
    "wof:name":"Fernandez Prieto Luis",
    "wof:placetype":"venue"
},
  "geometry": {"coordinates":[-6.6261339188,42.7670936584],"type":"Point"}
}