{
  "type": "Feature",
  "properties": {
    "iso:country":"ES",
    "sg:address":"Ctra Manlleu, 14",
    "sg:city":"Vic",
    "sg:orig_category":"Molduras, Junquillos, Listones Y Molduras Perforadas",
    "sg:phone":"+34 938 86 38 80",
    "sg:postcode":"08500",
    "sg:province":"Barcelona",
    "wof:name":"Fajula Cutrina Luis",
    "wof:placetype":"venue"
},
  "geometry": {"coordinates":[2.2554349899,41.9349441528],"type":"Point"}
}