{
  "type": "Feature",
  "properties": {
    "iso:country":"ES",
    "sg:address":"Plaza Nueva, S/n",
    "sg:city":"Villanueva Del Rosario",
    "sg:orig_category":"Asociaciones, Organismos Culturales Y Socioeducativos",
    "sg:phone":"+34 952 74 20 55",
    "sg:postcode":"29312",
    "sg:province":"M\u00e1laga",
    "wof:name":"Ayuntamiento De Villanueva Del Rosario",
    "wof:placetype":"venue"
},
  "geometry": {"coordinates":[-4.3677463531,36.998085022],"type":"Point"}
}