{
  "type": "Feature",
  "properties": {
    "addr:full":"C/ Peru, 80 Alcoi Alicante 03803",
    "addr:housenumber":"80",
    "addr:postcode":"03803",
    "addr:street":"C / Peru",
    "iso:country":"ES",
    "sg:address":"C/ Peru, 80",
    "sg:city":"Alcoi",
    "sg:orig_category":"Fabrica, Negocio De Vidrieras, Productos Vidriados Y Espejos",
    "sg:phone":"+34 965 52 38 80",
    "sg:postcode":"03803",
    "sg:province":"Alicante",
    "wof:name":"Vitrodayana S.l.",
    "wof:placetype":"venue"
},
  "geometry": {"coordinates":[-0.4796538055,38.7033615112],"type":"Point"}
}