{
  "type": "Feature",
  "properties": {
    "iso:country":"ES",
    "sg:address":"Avda Castilla Y Leon, 6",
    "sg:city":"Guardo",
    "sg:orig_category":"Peluquer\u00cdas, Peluquer\u00cda Mixta",
    "sg:phone":"+34 979 85 01 34",
    "sg:postcode":"34880",
    "sg:province":"Palencia",
    "wof:name":"Alonso Puebla Johana",
    "wof:placetype":"venue"
},
  "geometry": {"coordinates":[-4.8460006714,42.7887802124],"type":"Point"}
}