{
  "type": "Feature",
  "properties": {
    "addr:full":"Calle de Pintora (la), S/n Toscal Santa Cruz De Tenerife 38418",
    "addr:postcode":"38418",
    "addr:street":"Calle De Pintora La S / N Toscal",
    "iso:country":"ES",
    "sg:address":"Calle de Pintora (la), S/n",
    "sg:city":"Toscal",
    "sg:orig_category":"Peluquer\u00cdas, Peluquer\u00cda Mixta",
    "sg:phone":"+34 922 36 27 82",
    "sg:postcode":"38418",
    "sg:province":"Santa Cruz De Tenerife",
    "wof:name":"Hernandez Hernandez Maria De Los Angeles",
    "wof:placetype":"venue"
},
  "geometry": {"coordinates":[-16.5760383606,28.3986949921],"type":"Point"}
}