{
  "type": "Feature",
  "properties": {
    "iso:country":"ES",
    "sg:address":"Carrer de Ample, 20",
    "sg:city":"Reus",
    "sg:orig_category":"Cr\u00cda De Animales",
    "sg:phone":"+34 977 31 17 33",
    "sg:postcode":"43202",
    "sg:province":"Tarragona",
    "wof:name":"Abello Sabater David",
    "wof:placetype":"venue"
},
  "geometry": {"coordinates":[1.104398,41.158546],"type":"Point"}
}