{
  "type": "Feature",
  "properties": {
    "iso:country":"ES",
    "sg:address":"Calle de Poeta Garcia Lorca, 8",
    "sg:city":"Puente-genil",
    "sg:orig_category":"Delegados, Agentes De Tr\u00c1nsito, Auxiliares De Transporte Internacional",
    "sg:phone":"+34 957 60 50 55",
    "sg:postcode":"14500",
    "sg:province":"C\u00f3rdoba",
    "wof:name":"Martinez Ramirez Jose Luis",
    "wof:placetype":"venue"
},
  "geometry": {"coordinates":[-4.7682738304,37.3918190002],"type":"Point"}
}