{
  "type": "Feature",
  "properties": {
    "iso:country":"ES",
    "sg:address":"Ctra Medellin, Km. 0005,0",
    "sg:city":"Caceres",
    "sg:orig_category":"Fabricaci\u00d3n De Quesos",
    "sg:phone":"+34 927 24 65 30",
    "sg:postcode":"10005",
    "sg:province":"C\u00e1ceres",
    "wof:name":"Explotacion La Jarilla C.b.",
    "wof:placetype":"venue"
},
  "geometry": {"coordinates":[-6.3712091446,39.4599304199],"type":"Point"}
}