{
  "type": "Feature",
  "properties": {
    "addr:full":"Calle de Humilladero, 16 Sig\u00fcenza Guadalajara 19250",
    "addr:housenumber":"16",
    "addr:postcode":"19250",
    "addr:street":"Calle De Humilladero",
    "iso:country":"ES",
    "sg:address":"Calle de Humilladero, 16",
    "sg:city":"Sig\u00fcenza",
    "sg:orig_category":"Estancos",
    "sg:phone":"+34 949 39 13 92",
    "sg:postcode":"19250",
    "sg:province":"Guadalajara",
    "wof:name":"Casta\u00f1o Pe\u00f1alver Juana",
    "wof:placetype":"venue"
},
  "geometry": {"coordinates":[-2.6437709332,41.068687439],"type":"Point"}
}