{
  "type": "Feature",
  "properties": {
    "addr:full":"Pl Major, 21 Vic Barcelona 08500",
    "addr:housenumber":"21",
    "addr:postcode":"08500",
    "addr:street":"Pl Major",
    "iso:country":"ES",
    "sg:address":"Pl Major, 21",
    "sg:city":"Vic",
    "sg:orig_category":"Bisuter\u00cda, Joyer\u00cda, Relojer\u00cda (al Por Menor)",
    "sg:phone":"+34 938 86 33 51",
    "sg:postcode":"08500",
    "sg:province":"Barcelona",
    "wof:name":"Pomar Badia Marta",
    "wof:placetype":"venue"
},
  "geometry": {"coordinates":[2.2543559074,41.930896759],"type":"Point"}
}