{
  "type": "Feature",
  "properties": {
    "iso:country":"ES",
    "sg:address":"Calle de Bellas Artes, 4",
    "sg:city":"Zaragoza",
    "sg:orig_category":"Agencias Y Agentes Comerciales, Representantes",
    "sg:phone":"+34 976 75 40 73",
    "sg:postcode":"50012",
    "sg:province":"Zaragoza",
    "wof:name":"Perez Benedicto Andres",
    "wof:placetype":"venue"
},
  "geometry": {"coordinates":[-0.9275354147,41.6302108765],"type":"Point"}
}