{
  "type": "Feature",
  "properties": {
    "addr:full":"Rua Beato Sebastian De Aparicio, 44 Gudi\u00f1a Ourense 32540",
    "addr:housenumber":"44",
    "addr:postcode":"32540",
    "addr:street":"Rua Beato Sebastian De Aparicio",
    "iso:country":"ES",
    "sg:address":"Rua Beato Sebastian De Aparicio, 44",
    "sg:city":"Gudi\u00f1a",
    "sg:orig_category":"Reposter\u00cdas",
    "sg:phone":"+34 988 42 10 21",
    "sg:postcode":"32540",
    "sg:province":"Ourense",
    "wof:name":"Oliveira Garcia Antonio",
    "wof:placetype":"venue"
},
  "geometry": {"coordinates":[-7.1380591393,42.0611114502],"type":"Point"}
}