{
  "type": "Feature",
  "properties": {
    "addr:full":"Calle de Bidebarrieta, 19 Iurreta Vizcaya 48215",
    "addr:housenumber":"19",
    "addr:postcode":"48215",
    "addr:street":"Calle De Bidebarrieta",
    "iso:country":"ES",
    "sg:address":"Calle de Bidebarrieta, 19",
    "sg:city":"Iurreta",
    "sg:orig_category":"Fabricaci\u00d3n De Pernos, Tornillos Y Clavos",
    "sg:phone":"+34 946 81 98 76",
    "sg:postcode":"48215",
    "sg:province":"Vizcaya",
    "wof:name":"Garcia Hortelano Manuel",
    "wof:placetype":"venue"
},
  "geometry": {"coordinates":[-2.639983654,43.1752967834],"type":"Point"}
}