{
  "type": "Feature",
  "properties": {
    "addr:full":"Castello, 17 S. Feliu Guixols Girona 17220",
    "addr:postcode":"17220",
    "addr:street":"S.;Guixols",
    "iso:country":"ES",
    "sg:address":"Castello, 17",
    "sg:city":"S. Feliu Guixols",
    "sg:orig_category":"Promotores Constructores",
    "sg:phone":"+34 972 32 06 50",
    "sg:postcode":"17220",
    "sg:province":"Girona",
    "wof:name":"Housing Invesment 2000 Sl",
    "wof:placetype":"venue"
},
  "geometry": {"coordinates":[3.0313150883,41.7905731201],"type":"Point"}
}