{
  "type": "Feature",
  "properties": {
    "iso:country":"ES",
    "sg:address":"Carr Rajolers, 5",
    "sg:city":"Girona",
    "sg:orig_category":"Venta, Alquiler De Plataformas Y Barquillas Elevadoras",
    "sg:phone":"+34 972 21 71 61",
    "sg:postcode":"17003",
    "sg:province":"Girona",
    "wof:name":"Thyssenkrupp Elevadores S.l.",
    "wof:placetype":"venue"
},
  "geometry": {"coordinates":[2.8149900436,41.9704475403],"type":"Point"}
}