{
  "type": "Feature",
  "properties": {
    "addr:full":"Carrer de Dom Bosco, 20 Palau-solita I Plegamans Barcelona 08184",
    "addr:housenumber":"20",
    "addr:postcode":"08184",
    "addr:street":"Carrer De Dom Bosco",
    "iso:country":"ES",
    "sg:address":"Carrer de Dom Bosco, 20",
    "sg:city":"Palau-solita I Plegamans",
    "sg:orig_category":"Inmobiliaria (agencias)",
    "sg:phone":"+34 938 64 56 14",
    "sg:postcode":"08184",
    "sg:province":"Barcelona",
    "wof:name":"Immosort Palau S.l.",
    "wof:placetype":"venue"
},
  "geometry": {"coordinates":[2.1764099598,41.5882339478],"type":"Point"}
}