{
  "type": "Feature",
  "properties": {
    "iso:country":"ES",
    "sg:address":"Cno Barboles (mrl), 83",
    "sg:city":"Zaragoza",
    "sg:orig_category":"Doctores En Medicina",
    "sg:phone":"+34 976 32 36 14",
    "sg:postcode":"50011",
    "sg:province":"Zaragoza",
    "wof:name":"Daza De Luque Ausberto",
    "wof:placetype":"venue"
},
  "geometry": {"coordinates":[-0.9566249847,41.6593437195],"type":"Point"}
}