{
  "type": "Feature",
  "properties": {
    "iso:country":"ES",
    "sg:address":"Avgd Francesc Tarrega, 45",
    "sg:city":"Villarreal",
    "sg:orig_category":"Cajas De Ahorro",
    "sg:phone":"+34 964 50 60 63",
    "sg:postcode":"12540",
    "sg:province":"Castell\u00f3n",
    "wof:name":"Caja De Ahorros Del Mediterraneo",
    "wof:placetype":"venue"
},
  "geometry": {"coordinates":[-0.0952939987,39.9453048706],"type":"Point"}
}