{
  "type": "Feature",
  "properties": {
    "iso:country":"ES",
    "sg:address":"Pl Estacio, 3",
    "sg:city":"Pineda Mar",
    "sg:orig_category":"Caf\u00c9s, Bares, Cervecer\u00cdas",
    "sg:phone":"+34 937 67 00 25",
    "sg:postcode":"08397",
    "sg:province":"Barcelona",
    "wof:name":"Tebar Lopez Angel",
    "wof:placetype":"venue"
},
  "geometry": {"coordinates":[2.693459034,41.6228408813],"type":"Point"}
}