{
  "type": "Feature",
  "properties": {
    "addr:full":"Calle de Barrengoitia, 20 Portugalete Vizcaya 48920",
    "addr:housenumber":"20",
    "addr:postcode":"48920",
    "addr:street":"Calle De Barrengoitia",
    "iso:country":"ES",
    "sg:address":"Calle de Barrengoitia, 20",
    "sg:city":"Portugalete",
    "sg:orig_category":"Muebles",
    "sg:phone":"+34 944 96 22 11",
    "sg:postcode":"48920",
    "sg:province":"Vizcaya",
    "wof:name":"Manuel Mozos Gascon Josefa Valero Castells Prestaciones Himoz S.l.cdad",
    "wof:placetype":"venue"
},
  "geometry": {"coordinates":[-3.0161206722,43.3155937195],"type":"Point"}
}