{
  "type": "Feature",
  "properties": {
    "iso:country":"ES",
    "sg:address":"Calle de Mu\u00d1oz Torrero, 17",
    "sg:city":"Badajoz",
    "sg:orig_category":"Electrodom\u00c9sticos (fabricaci\u00d3n, Al Por Mayor)",
    "sg:phone":"+34 924 26 07 61",
    "sg:postcode":"06001",
    "sg:province":"Badajoz",
    "sg:website":"www.paginasamarillas.com",
    "wof:name":"Electrodomesticos Butagas",
    "wof:placetype":"venue"
},
  "geometry": {"coordinates":[-6.9718680382,38.8787536621],"type":"Point"}
}