{
  "type": "Feature",
  "properties": {
    "iso:country":"ES",
    "sg:address":"Calle de Colon, 37",
    "sg:city":"Denia",
    "sg:orig_category":"Abogados",
    "sg:phone":"+34 965 78 65 75",
    "sg:postcode":"03700",
    "sg:province":"Alicante",
    "wof:name":"Royo Do\u00f1ate Isidro",
    "wof:placetype":"venue"
},
  "geometry": {"coordinates":[0.1081714034,38.8395843506],"type":"Point"}
}