{
  "type": "Feature",
  "properties": {
    "addr:full":"Avda Algorta (de), S/n San Fernando De Henares Madrid 28830",
    "addr:housenumber":"/ n",
    "addr:postcode":"28830",
    "addr:street":"Avda Algorta De S",
    "iso:country":"ES",
    "sg:address":"Avda Algorta (de), S/n",
    "sg:city":"San Fernando De Henares",
    "sg:orig_category":"Centros De Educaci\u00d3n Especial",
    "sg:phone":"+34 916 73 65 31",
    "sg:postcode":"28830",
    "sg:province":"Madrid",
    "wof:name":"Comunidad Autonoma De Madrid-centros De Educacion",
    "wof:placetype":"venue"
},
  "geometry": {"coordinates":[-3.5239388943,40.4181938171],"type":"Point"}
}