{
  "type": "Feature",
  "properties": {
    "addr:full":"Calle de Juan De Bethencourt, 3 Palmas De Gran Canaria Las Palmas 35011",
    "addr:housenumber":"3",
    "addr:postcode":"35011",
    "addr:street":"Calle De Juan De Bethencourt",
    "iso:country":"ES",
    "sg:address":"Calle de Juan De Bethencourt, 3",
    "sg:city":"Palmas De Gran Canaria",
    "sg:orig_category":"Iglesia Cat\u00d3lica",
    "sg:phone":"+34 928 25 03 11",
    "sg:postcode":"35011",
    "sg:province":"Las Palmas",
    "wof:name":"Parroquia De Escaleritas",
    "wof:placetype":"venue"
},
  "geometry": {"coordinates":[-15.4359970093,28.119184494],"type":"Point"}
}