{
  "type": "Feature",
  "properties": {
    "addr:full":"Afueras, S/n Gava Barcelona 08850",
    "addr:postcode":"08850",
    "addr:street":"Afueras S / N Gava",
    "iso:country":"ES",
    "sg:address":"Afueras, S/n",
    "sg:city":"Gava",
    "sg:orig_category":"Perreras, Pensiones Para Perros, Gatos Y Otros Animales",
    "sg:phone":"+34 936 36 35 40",
    "sg:postcode":"08850",
    "sg:province":"Barcelona",
    "sg:website":"www.casteldefells.com",
    "wof:name":"Residencia Canina La Sentiu S.l.",
    "wof:placetype":"venue"
},
  "geometry": {"coordinates":[2.0012850761,41.3040237427],"type":"Point"}
}