{
  "type": "Feature",
  "properties": {
    "addr:full":"G.v. Corts Catalanes, 960 Barcelona Barcelona 08018",
    "addr:housenumber":"960",
    "addr:postcode":"08018",
    "addr:street":"Catalanes",
    "iso:country":"ES",
    "sg:address":"G.v. Corts Catalanes, 960",
    "sg:city":"Barcelona",
    "sg:orig_category":"Ingenier\u00cda, Centros De Estudios (diversos)",
    "sg:phone":"+34 933 07 07 73",
    "sg:postcode":"08018",
    "sg:province":"Barcelona",
    "wof:name":"Ingenieros Tecnicos Bueno S.l.",
    "wof:placetype":"venue"
},
  "geometry": {"coordinates":[2.1959888935,41.4095497131],"type":"Point"}
}