{
  "type": "Feature",
  "properties": {
    "iso:country":"ES",
    "sg:address":"Rua Paredes (as), 53",
    "sg:city":"Monforte De Lemos",
    "sg:orig_category":"Postigos, Persianas Y Celos\u00cdas",
    "sg:phone":"+34 982 40 47 83",
    "sg:postcode":"27400",
    "sg:province":"Lugo",
    "wof:name":"Ares Sotelo Manuel",
    "wof:placetype":"venue"
},
  "geometry": {"coordinates":[-7.5218391418,42.5137557983],"type":"Point"}
}