{
  "type": "Feature",
  "properties": {
    "addr:full":"Avgd Montserrat, 17 Igualada Barcelona 08700",
    "addr:housenumber":"17",
    "addr:postcode":"08700",
    "addr:street":"Montserrat",
    "iso:country":"ES",
    "sg:address":"Avgd Montserrat, 17",
    "sg:city":"Igualada",
    "sg:orig_category":"Contenedores (mercanc\u00cdas)",
    "sg:phone":"+34 938 03 01 66",
    "sg:postcode":"08700",
    "sg:province":"Barcelona",
    "wof:name":"Oliva Tristany Juan",
    "wof:placetype":"venue"
},
  "geometry": {"coordinates":[1.6055309772,41.5870513916],"type":"Point"}
}