{
  "type": "Feature",
  "properties": {
    "addr:full":"Avda Aguirre Lehendakari, 11 Bilbao Vizcaya 48014",
    "addr:housenumber":"11",
    "addr:postcode":"48014",
    "addr:street":"Avda Aguirre Lehendakari",
    "iso:country":"ES",
    "sg:address":"Avda Aguirre Lehendakari, 11",
    "sg:city":"Bilbao",
    "sg:orig_category":"Edici\u00d3n De Diarios, Revistas, Boletines",
    "sg:phone":"+34 944 75 41 09",
    "sg:postcode":"48014",
    "sg:province":"Vizcaya",
    "sg:website":"www.pearsoneducacion.com",
    "wof:name":"Pearson Educacion",
    "wof:placetype":"venue"
},
  "geometry": {"coordinates":[-2.9460270405,43.2717628479],"type":"Point"}
}