{
  "type": "Feature",
  "properties": {
    "addr:full":"Avgd Tortosa, 2 Lleida Lleida 25005",
    "addr:housenumber":"2",
    "addr:postcode":"25005",
    "addr:street":"Tortosa",
    "iso:country":"ES",
    "sg:address":"Avgd Tortosa, 2",
    "sg:city":"Lleida",
    "sg:orig_category":"Organizaciones Internacionales",
    "sg:phone":"+34 973 22 32 44",
    "sg:postcode":"25005",
    "sg:province":"Lleida",
    "sg:website":"www.agronet.org",
    "wof:name":"Fundacio Pagesos Solidaris",
    "wof:placetype":"venue"
},
  "geometry": {"coordinates":[0.6366189718,41.6192207336],"type":"Point"}
}