{
  "type": "Feature",
  "properties": {
    "addr:full":"Calle de Ebro (del), 4 Coslada Madrid 28820",
    "addr:housenumber":"4",
    "addr:postcode":"28820",
    "addr:street":"Calle De Ebro Del",
    "iso:country":"ES",
    "sg:address":"Calle de Ebro (del), 4",
    "sg:city":"Coslada",
    "sg:orig_category":"Molduras, Junquillos, Listones Y Molduras Perforadas",
    "sg:phone":"+34 916 69 15 44",
    "sg:postcode":"28820",
    "sg:province":"Madrid",
    "wof:name":"Belda Sierra Manuel",
    "wof:placetype":"venue"
},
  "geometry": {"coordinates":[-3.5388729572,40.4243927002],"type":"Point"}
}