{
  "type": "Feature",
  "properties": {
    "addr:full":"Calle de Guillem De Castro, 42 Valencia Valencia 46001",
    "addr:housenumber":"42",
    "addr:postcode":"46001",
    "addr:street":"Calle De Guillem De Castro",
    "iso:country":"ES",
    "sg:address":"Calle de Guillem De Castro, 42",
    "sg:city":"Valencia",
    "sg:orig_category":"Organizaciones Internacionales",
    "sg:phone":"+34 963 91 01 21",
    "sg:postcode":"46001",
    "sg:province":"Valencia",
    "wof:name":"Ayuda Global",
    "wof:placetype":"venue"
},
  "geometry": {"coordinates":[-0.3839038908,39.4714546204],"type":"Point"}
}