{
  "type": "Feature",
  "properties": {
    "iso:country":"ES",
    "sg:address":"Calle de Menorca, 7",
    "sg:city":"Madrid",
    "sg:orig_category":"Abogados",
    "sg:phone":"+34 915 73 74 13",
    "sg:postcode":"28009",
    "sg:province":"Madrid",
    "wof:name":"Sahagun Pool Guillermo",
    "wof:placetype":"venue"
},
  "geometry": {"coordinates":[-3.6783509254,40.4196662903],"type":"Point"}
}