{
  "type": "Feature",
  "properties": {
    "iso:country":"ES",
    "sg:address":"Calle de Jose Sanchez, 17",
    "sg:city":"Pilar Horadada",
    "sg:orig_category":"Electricidad: Instaladores",
    "sg:phone":"+34 966 76 61 80",
    "sg:postcode":"03190",
    "sg:province":"Alicante",
    "wof:name":"Electricidad Vitrimar S.l.",
    "wof:placetype":"venue"
},
  "geometry": {"coordinates":[-0.7898390293,37.8640213013],"type":"Point"}
}