{
  "type": "Feature",
  "properties": {
    "addr:full":"Plaz Madre De Dios, S/n Jerez De La Frontera C\u00e1diz 11401",
    "addr:housenumber":"s / n",
    "addr:postcode":"11401",
    "addr:street":"Dios",
    "iso:country":"ES",
    "sg:address":"Plaz Madre De Dios, S/n",
    "sg:city":"Jerez De La Frontera",
    "sg:orig_category":"Colchones (fabricaci\u00d3n, Al Por Mayor, Al Por Menor)",
    "sg:phone":"+34 956 34 50 20",
    "sg:postcode":"11401",
    "sg:province":"C\u00e1diz",
    "wof:name":"Lopez Ruiz E Hijos S.l.",
    "wof:placetype":"venue"
},
  "geometry": {"coordinates":[-6.128824234,36.678768158],"type":"Point"}
}