{
  "type": "Feature",
  "properties": {
    "addr:full":"Nacional Seiscientos Treinta, S/n Villalobar Le\u00f3n 24233",
    "addr:housenumber":"s / n",
    "addr:postcode":"24233",
    "addr:street":"Treinta;Villalobar Leo\u0301N",
    "iso:country":"ES",
    "sg:address":"Nacional Seiscientos Treinta, S/n",
    "sg:city":"Villalobar",
    "sg:orig_category":"Productores Recolectores, Venta Directa De Vinos",
    "sg:phone":"+34 987 30 44 21",
    "sg:postcode":"24233",
    "sg:province":"Le\u00f3n",
    "wof:name":"Alonso Pastrana S.l.",
    "wof:placetype":"venue"
},
  "geometry": {"coordinates":[-5.5740375519,42.3966941833],"type":"Point"}
}