{
  "type": "Feature",
  "properties": {
    "addr:full":"Calle de Bolivar Simon, 5 Bilbao Vizcaya 48010",
    "addr:housenumber":"5",
    "addr:postcode":"48010",
    "addr:street":"Calle De Bolivar Simon",
    "iso:country":"ES",
    "sg:address":"Calle de Bolivar Simon, 5",
    "sg:city":"Bilbao",
    "sg:orig_category":"Internados & Ense\u00d1anza Privada",
    "sg:phone":"+34 944 21 03 30",
    "sg:postcode":"48010",
    "sg:province":"Vizcaya",
    "wof:name":"Institucion Teresiana Asociacion Civil",
    "wof:placetype":"venue"
},
  "geometry": {"coordinates":[-2.9411580563,43.2598609924],"type":"Point"}
}