{
  "type": "Feature",
  "properties": {
    "iso:country":"ES",
    "sg:address":"Trva Arechavaleta, 4",
    "sg:city":"Madrid",
    "sg:orig_category":"Quincaller\u00cda (al Por Menor)",
    "sg:phone":"+34 917 95 23 67",
    "sg:postcode":"28041",
    "sg:province":"Madrid",
    "wof:name":"Martinez Aranda Francisco",
    "wof:placetype":"venue"
},
  "geometry": {"coordinates":[-3.6980669498,40.350818634],"type":"Point"}
}