{
  "type": "Feature",
  "properties": {
    "addr:full":"Calle de Nuestra Se\u00d1ora Del Aguila, 69 Alcala Guadaira Sevilla 41500",
    "addr:housenumber":"69",
    "addr:postcode":"41500",
    "addr:street":"Calle De Nuestra;Del Aguila",
    "iso:country":"ES",
    "sg:address":"Calle de Nuestra Se\u00d1ora Del Aguila, 69",
    "sg:city":"Alcala Guadaira",
    "sg:orig_category":"Cl\u00cdnicas M\u00c9dicas",
    "sg:phone":"+34 955 68 55 73",
    "sg:postcode":"41500",
    "sg:province":"Sevilla",
    "sg:website":"www.asisa.es",
    "wof:name":"Asistencia Sanitaria Interprovincial S.a.",
    "wof:placetype":"venue"
},
  "geometry": {"coordinates":[-5.8488965034,37.3340301514],"type":"Point"}
}