{
  "type": "Feature",
  "properties": {
    "iso:country":"ES",
    "sg:address":"Plastic, 1",
    "sg:city":"Badalona",
    "sg:orig_category":"Fabricaci\u00d3n De Art\u00cdculos Y Equipos Deportivos Y De Ocio",
    "sg:phone":"+34 934 28 10 70",
    "sg:postcode":"08912",
    "sg:province":"Barcelona",
    "sg:website":"www.tecnosport.es",
    "wof:name":"Tecno Sport Condition S.l.",
    "wof:placetype":"venue"
},
  "geometry": {"coordinates":[2.252669096,41.4618873596],"type":"Point"}
}