{
  "type": "Feature",
  "properties": {
    "iso:country":"ES",
    "sg:address":"Calle de Benito Leon, 5",
    "sg:city":"Santa Maria Del Paramo",
    "sg:orig_category":"Ingeniero",
    "sg:phone":"+34 987 36 00 15",
    "sg:postcode":"24240",
    "sg:province":"Le\u00f3n",
    "wof:name":"Lopez Cabello Jose Luis",
    "wof:placetype":"venue"
},
  "geometry": {"coordinates":[-5.7481818199,42.3542747498],"type":"Point"}
}