{
  "type": "Feature",
  "properties": {
    "addr:full":"Rond Ayuntamiento (del), 10 Villar De La Encina Cuenca 16648",
    "addr:postcode":"16648",
    "addr:street":"Encina",
    "iso:country":"ES",
    "sg:address":"Rond Ayuntamiento (del), 10",
    "sg:city":"Villar De La Encina",
    "sg:orig_category":"Bancos",
    "sg:phone":"+34 969 29 03 20",
    "sg:postcode":"16648",
    "sg:province":"Cuenca",
    "wof:name":"Banco Espa\u00f1ol De Credito S.a.",
    "wof:placetype":"venue"
},
  "geometry": {"coordinates":[-2.5212390423,39.6376953125],"type":"Point"}
}