{
  "type": "Feature",
  "properties": {
    "addr:full":"Avda Condes De San Isidro, 22 Fuengirola M\u00e1laga 29640",
    "addr:housenumber":"22",
    "addr:postcode":"29640",
    "addr:street":"Avda Condes De San Isidro;Ma\u0301Laga",
    "iso:country":"ES",
    "sg:address":"Avda Condes De San Isidro, 22",
    "sg:city":"Fuengirola",
    "sg:orig_category":"Bisuter\u00cda, Joyer\u00cda, Relojer\u00cda (al Por Menor)",
    "sg:phone":"+34 952 46 98 27",
    "sg:postcode":"29640",
    "sg:province":"M\u00e1laga",
    "sg:website":"www.joyeriasoldeoro.com",
    "wof:name":"Horma Y Calce S.l.",
    "wof:placetype":"venue"
},
  "geometry": {"coordinates":[-4.6267518997,36.5339927673],"type":"Point"}
}