{
  "type": "Feature",
  "properties": {
    "addr:full":"Carr Bateria, 41 Bateria Girona 17490",
    "addr:housenumber":"41",
    "addr:postcode":"17490",
    "addr:street":"Carr Bateria",
    "iso:country":"ES",
    "sg:address":"Carr Bateria, 41",
    "sg:city":"Bateria",
    "sg:orig_category":"Promotores Constructores",
    "sg:phone":"+34 972 38 05 13",
    "sg:postcode":"17490",
    "sg:province":"Girona",
    "wof:name":"Joaquin Gonzalez Carrillo Obres I Construccions S.l.",
    "wof:placetype":"venue"
},
  "geometry": {"coordinates":[3.1481759548,42.3640785217],"type":"Point"}
}