{
  "type": "Feature",
  "properties": {
    "iso:country":"ES",
    "sg:address":"Avda De Belgica, 61",
    "sg:city":"Castalla",
    "sg:orig_category":"Revisi\u00d3n, Reconstrucci\u00d3n De M\u00c1quinas Y Herramientas",
    "sg:phone":"+34 966 56 05 81",
    "sg:postcode":"03420",
    "sg:province":"Alicante",
    "wof:name":"D.a.t. Cnc S.l.",
    "wof:placetype":"venue"
},
  "geometry": {"coordinates":[-0.6699090004,38.6049880981],"type":"Point"}
}