{
  "type": "Feature",
  "properties": {
    "iso:country":"ES",
    "sg:address":"Calle de Arrandi, 26",
    "sg:city":"San Vicente De Barakaldo",
    "sg:orig_category":"Zapatos (al Por Menor)",
    "sg:phone":"+34 944 38 46 26",
    "sg:postcode":"48901",
    "sg:province":"Vizcaya",
    "wof:name":"Acha Azcueta Juan Carlos",
    "wof:placetype":"venue"
},
  "geometry": {"coordinates":[-2.9863035679,43.2955131531],"type":"Point"}
}