{
  "type": "Feature",
  "properties": {
    "addr:full":"Avgd Valencia, 34 Muro Alcoy Alicante 03830",
    "addr:housenumber":"34",
    "addr:postcode":"03830",
    "addr:street":"Valencia",
    "iso:country":"ES",
    "sg:address":"Avgd Valencia, 34",
    "sg:city":"Muro Alcoy",
    "sg:orig_category":"Sociedades, Compa\u00d1\u00cdas Aseguradoras",
    "sg:phone":"+34 965 53 17 94",
    "sg:postcode":"03830",
    "sg:province":"Alicante",
    "sg:website":"www.ocaso.es",
    "wof:name":"Ocaso S.a.compa\u00f1ia De Seguros Y Reaseguros",
    "wof:placetype":"venue"
},
  "geometry": {"coordinates":[-0.4414289892,38.7812538147],"type":"Point"}
}