{
  "type": "Feature",
  "properties": {
    "addr:full":"Avda Felipe Ii (de), S/n Escorial Madrid 28280",
    "addr:postcode":"28280",
    "addr:street":"Avda Felipe Ii De S / N Escorial",
    "iso:country":"ES",
    "sg:address":"Avda Felipe Ii (de), S/n",
    "sg:city":"Escorial",
    "sg:orig_category":"Art\u00cdculos Funerarios (al Por Menor)",
    "sg:phone":"+34 918 90 66 57",
    "sg:postcode":"28280",
    "sg:province":"Madrid",
    "wof:name":"Interfunerarias S.l.",
    "wof:placetype":"venue"
},
  "geometry": {"coordinates":[-4.1292529106,40.5882568359],"type":"Point"}
}