{
  "type": "Feature",
  "properties": {
    "iso:country":"ES",
    "sg:address":"Calle de Rio Guadalquivir, 24",
    "sg:city":"San Javier",
    "sg:orig_category":"Carnicer\u00cdas, Carnicer\u00cdas",
    "sg:phone":"+34 968 19 25 32",
    "sg:postcode":"30730",
    "sg:province":"Murcia",
    "wof:name":"Jimenez Garcia Antonio",
    "wof:placetype":"venue"
},
  "geometry": {"coordinates":[-0.8234289885,37.8047103882],"type":"Point"}
}