{
  "type": "Feature",
  "properties": {
    "iso:country":"ES",
    "sg:address":"Avda Jose Jimenez Ruano, 47",
    "sg:city":"Aguilas",
    "sg:orig_category":"Arboricultura Y Producci\u00d3n De Frutas",
    "sg:phone":"+34 968 41 12 16",
    "sg:postcode":"30880",
    "sg:province":"Murcia",
    "wof:name":"Los Salinares De Aguilas S.l.",
    "wof:placetype":"venue"
},
  "geometry": {"coordinates":[-1.5861990452,37.4137611389],"type":"Point"}
}