{
  "type": "Feature",
  "properties": {
    "iso:country":"ES",
    "sg:address":"Mercado Municipal, S/n",
    "sg:city":"Boiro",
    "sg:orig_category":"Carnicer\u00cdas, Carnicer\u00cdas",
    "sg:phone":"+34 981 84 42 27",
    "sg:postcode":"15930",
    "sg:province":"La Coru\u00f1a",
    "wof:name":"Lai\u00f1o Boga Juan Ramon",
    "wof:placetype":"venue"
},
  "geometry": {"coordinates":[-8.9355735779,42.6803779602],"type":"Point"}
}