{
  "type": "Feature",
  "properties": {
    "iso:country":"ES",
    "sg:address":"Calle de Jesus Adran, 4",
    "sg:city":"Villafranca Bierzo",
    "sg:orig_category":"Estancos",
    "sg:phone":"+34 987 54 01 68",
    "sg:postcode":"24500",
    "sg:province":"Le\u00f3n",
    "wof:name":"Fernandez Gonzalez Carlos",
    "wof:placetype":"venue"
},
  "geometry": {"coordinates":[-6.8091239929,42.6078491211],"type":"Point"}
}