{
  "type": "Feature",
  "properties": {
    "addr:full":"Pase Zorrilla, 80 Valladolid Valladolid 47006",
    "addr:housenumber":"80",
    "addr:postcode":"47006",
    "addr:street":"Zorrilla",
    "iso:country":"ES",
    "sg:address":"Pase Zorrilla, 80",
    "sg:city":"Valladolid",
    "sg:orig_category":"Bancos",
    "sg:phone":"+34 983 23 26 93",
    "sg:postcode":"47006",
    "sg:province":"Valladolid",
    "wof:name":"Banco De Castilla",
    "wof:placetype":"venue"
},
  "geometry": {"coordinates":[-4.7376937866,41.6412734985],"type":"Point"}
}