{
  "type": "Feature",
  "properties": {
    "iso:country":"ES",
    "sg:address":"Avda Jesus Rescatado (de), 5",
    "sg:city":"Cordoba",
    "sg:orig_category":"Pod\u00d3logos: Pedicuros",
    "sg:phone":"+34 957 44 02 48",
    "sg:postcode":"14007",
    "sg:province":"C\u00f3rdoba",
    "wof:name":"Luna Cordoba Francisco Jesus",
    "wof:placetype":"venue"
},
  "geometry": {"coordinates":[-4.7629241943,37.8908958435],"type":"Point"}
}