{
  "type": "Feature",
  "properties": {
    "iso:country":"ES",
    "sg:address":"Calle de Guatemala, 1",
    "sg:city":"Arrecife",
    "sg:orig_category":"Supermercados Y Hipermercados",
    "sg:phone":"+34 928 81 72 99",
    "sg:postcode":"35500",
    "sg:province":"Las Palmas",
    "wof:name":"Supermercado Rodriguez Padron S.l.",
    "wof:placetype":"venue"
},
  "geometry": {"coordinates":[-13.556517601,28.9640789032],"type":"Point"}
}