{
  "type": "Feature",
  "properties": {
    "iso:country":"ES",
    "sg:address":"Carrer de Arago, 526",
    "sg:city":"Barcelona",
    "sg:orig_category":"Compraventa De Antig\u00dcedades",
    "sg:phone":"+34 932 32 10 54",
    "sg:postcode":"08013",
    "sg:province":"Barcelona",
    "wof:name":"Roig Rius Federico",
    "wof:placetype":"venue"
},
  "geometry": {"coordinates":[2.1828000546,41.4054832458],"type":"Point"}
}