{
  "type": "Feature",
  "properties": {
    "iso:country":"ES",
    "sg:address":"Carr Major, 11",
    "sg:city":"S. Climent Sescebes",
    "sg:orig_category":"Estancos",
    "sg:phone":"+34 972 56 30 16",
    "sg:postcode":"17751",
    "sg:province":"Girona",
    "wof:name":"Muntada Pages Jorge",
    "wof:placetype":"venue"
},
  "geometry": {"coordinates":[2.973058939,42.3635139465],"type":"Point"}
}