{
  "type": "Feature",
  "properties": {
    "iso:country":"ES",
    "sg:address":"Calle de Monta\u00d1a Chica, S/n",
    "sg:city":"Cristianos",
    "sg:orig_category":"Mec\u00c1nico Del Autom\u00d3vil",
    "sg:phone":"+34 922 79 81 45",
    "sg:postcode":"38650",
    "sg:province":"Santa Cruz De Tenerife",
    "wof:name":"C.e.e.sierra S.l.",
    "wof:placetype":"venue"
},
  "geometry": {"coordinates":[-16.7171134949,28.0532512665],"type":"Point"}
}