{
  "type": "Feature",
  "properties": {
    "addr:full":"Carrer de Caritat, 30 Manresa Barcelona 08241",
    "addr:housenumber":"30",
    "addr:postcode":"08241",
    "addr:street":"Carrer De Caritat",
    "iso:country":"ES",
    "sg:address":"Carrer de Caritat, 30",
    "sg:city":"Manresa",
    "sg:orig_category":"Inmobiliaria (agencias)",
    "sg:phone":"+34 938 77 61 80",
    "sg:postcode":"08241",
    "sg:province":"Barcelona",
    "sg:website":"www.donpiso.com",
    "wof:name":"Habitat Serinmo S.l.",
    "wof:placetype":"venue"
},
  "geometry": {"coordinates":[1.8296439648,41.7283096313],"type":"Point"}
}