{
  "type": "Feature",
  "properties": {
    "addr:full":"Calle de Santa Fe, 2 Pozuelo De Alarcon Madrid 28224",
    "addr:postcode":"28224",
    "addr:street":"Calle De Santa Fe;Pozuelo",
    "iso:country":"ES",
    "sg:address":"Calle de Santa Fe, 2",
    "sg:city":"Pozuelo De Alarcon",
    "sg:orig_category":"Servicio De Salud",
    "sg:phone":"+34 913 52 09 11",
    "sg:postcode":"28224",
    "sg:province":"Madrid",
    "wof:name":"Perez Juri Pedro",
    "wof:placetype":"venue"
},
  "geometry": {"coordinates":[-3.7995436192,40.4460830688],"type":"Point"}
}