{
  "type": "Feature",
  "properties": {
    "iso:country":"ES",
    "sg:address":"Calle de Rafael Gallego Sainz, 12",
    "sg:city":"Oviedo",
    "sg:orig_category":"Art\u00cdculos De Regalo (al Por Menor)",
    "sg:phone":"+34 985 27 49 02",
    "sg:postcode":"33012",
    "sg:province":"Asturias",
    "wof:name":"Apaolaza Fernandez Rafael Ignacio",
    "wof:placetype":"venue"
},
  "geometry": {"coordinates":[-5.8681764603,43.3672370911],"type":"Point"}
}