{
  "type": "Feature",
  "properties": {
    "iso:country":"ES",
    "sg:address":"Calle de Jose Fernandez Cuevas, 14",
    "sg:city":"Pozuelo De Alarcon",
    "sg:orig_category":"Importaci\u00d3n",
    "sg:phone":"+34 913 52 33 22",
    "sg:postcode":"28224",
    "sg:province":"Madrid",
    "sg:website":"www.aname.org",
    "wof:name":"Aname S.l.",
    "wof:placetype":"venue"
},
  "geometry": {"coordinates":[-3.8027911186,40.4448738098],"type":"Point"}
}