{
  "type": "Feature",
  "properties": {
    "addr:full":"Pase Estacion, 105 Salamanca Salamanca 37004",
    "addr:housenumber":"105",
    "addr:postcode":"37004",
    "addr:street":"Estacion",
    "iso:country":"ES",
    "sg:address":"Pase Estacion, 105",
    "sg:city":"Salamanca",
    "sg:orig_category":"Frutas Y Legumbres Frescas (al Por Mayor)",
    "sg:phone":"+34 923 22 17 31",
    "sg:postcode":"37004",
    "sg:province":"Salamanca",
    "wof:name":"Aceitunas Dominguez S.a.",
    "wof:placetype":"venue"
},
  "geometry": {"coordinates":[-5.6497831345,40.9721069336],"type":"Point"}
}