{
  "type": "Feature",
  "properties": {
    "addr:full":"Rua Marques De Trives, 23 Pobra Trives Ourense 32780",
    "addr:housenumber":"23",
    "addr:postcode":"32780",
    "addr:street":"Rua Marques De Trives",
    "iso:country":"ES",
    "sg:address":"Rua Marques De Trives, 23",
    "sg:city":"Pobra Trives",
    "sg:orig_category":"Reposter\u00cdas",
    "sg:phone":"+34 988 33 02 08",
    "sg:postcode":"32780",
    "sg:province":"Ourense",
    "wof:name":"Canedo Mendez Antonio",
    "wof:placetype":"venue"
},
  "geometry": {"coordinates":[-7.2539892197,42.3392906189],"type":"Point"}
}