{
  "type": "Feature",
  "properties": {
    "iso:country":"ES",
    "sg:address":"Calle de Mendikale, 8",
    "sg:city":"Ansoain",
    "sg:orig_category":"Lencer\u00cda Femenina, Corseter\u00cda, Trajes De Ba\u00d1o (al Por Menor)",
    "sg:phone":"+34 948 13 28 88",
    "sg:postcode":"31013",
    "sg:province":"Navarra",
    "wof:name":"Nahia",
    "wof:placetype":"venue"
},
  "geometry": {"coordinates":[-1.6381579638,42.8341674805],"type":"Point"}
}