{
  "type": "Feature",
  "properties": {
    "addr:full":"Avda Cid Campeador, 17 Burgos Burgos 09003",
    "addr:housenumber":"17",
    "addr:postcode":"09003",
    "addr:street":"Avda Cid Campeador",
    "iso:country":"ES",
    "sg:address":"Avda Cid Campeador, 17",
    "sg:city":"Burgos",
    "sg:orig_category":"Ropa Para Se\u00d1oras (al Por Menor)",
    "sg:phone":"+34 947 25 62 90",
    "sg:postcode":"09003",
    "sg:province":"Burgos",
    "wof:name":"Oca Y Blanco S.l.",
    "wof:placetype":"venue"
},
  "geometry": {"coordinates":[-3.6984119415,42.3449707031],"type":"Point"}
}