{
  "type": "Feature",
  "properties": {
    "addr:full":"Calle de Mayor, 19 Caspe Zaragoza 50700",
    "addr:housenumber":"19",
    "addr:postcode":"50700",
    "addr:street":"Calle De Mayor",
    "iso:country":"ES",
    "sg:address":"Calle de Mayor, 19",
    "sg:city":"Caspe",
    "sg:orig_category":"Cajas De Ahorro",
    "sg:phone":"+34 976 63 10 16",
    "sg:postcode":"50700",
    "sg:province":"Zaragoza",
    "wof:name":"Caja De Ahorros De La Inmaculada",
    "wof:placetype":"venue"
},
  "geometry": {"coordinates":[-0.0383450016,41.2363586426],"type":"Point"}
}