{
  "type": "Feature",
  "properties": {
    "iso:country":"ES",
    "sg:address":"Moll Sant Bertran, 1",
    "sg:city":"Barcelona",
    "sg:orig_category":"Organizaciones Profesionales",
    "sg:phone":"+34 933 24 90 49",
    "sg:postcode":"08039",
    "sg:province":"Barcelona",
    "wof:name":"Bt Espa\u00d1a Compa\u00d1ia De Servicios Globales De Telecomunicaciones S.a.u.",
    "wof:placetype":"venue"
},
  "geometry": {"coordinates":[2.1749000549,41.3676757812],"type":"Point"}
}