{
  "type": "Feature",
  "properties": {
    "addr:full":"Carretera De La Codosera, Km. 0000,8 La Codosera Badajoz 06518",
    "addr:postcode":"06518",
    "addr:street":"Carretera De La Codosera Km. 0000,8 La",
    "iso:country":"ES",
    "sg:address":"Carretera De La Codosera, Km. 0000,8",
    "sg:city":"La Codosera",
    "sg:orig_category":"Poller\u00cda Y Caza (al Por Menor)",
    "sg:phone":"+34 924 40 40 81",
    "sg:postcode":"06518",
    "sg:province":"Badajoz",
    "wof:name":"Explotaciones Ganaderas El Cruce S.l.",
    "wof:placetype":"venue"
},
  "geometry": {"coordinates":[-7.1718940735,39.2077064514],"type":"Point"}
}