{
  "type": "Feature",
  "properties": {
    "addr:full":"Calle de Jose Achotegui, 26 Vitoria-gasteiz \u00c1lava 01009",
    "addr:housenumber":"26",
    "addr:postcode":"01009",
    "addr:street":"Calle De Jose Achotegui",
    "iso:country":"ES",
    "sg:address":"Calle de Jose Achotegui, 26",
    "sg:city":"Vitoria-gasteiz",
    "sg:orig_category":"Asilos De Ancianos. Centros Privados",
    "sg:phone":"+34 945 22 79 89",
    "sg:postcode":"01009",
    "sg:province":"\u00c1lava",
    "wof:name":"Lorea S.c",
    "wof:placetype":"venue"
},
  "geometry": {"coordinates":[-2.6889300346,42.8564186096],"type":"Point"}
}