{
  "type": "Feature",
  "properties": {
    "addr:full":"Pl Mediterrani, S/n Segur Calafell Tarragona 43882",
    "addr:housenumber":"s / n",
    "addr:postcode":"43882",
    "addr:street":"Pl Mediterrani",
    "iso:country":"ES",
    "sg:address":"Pl Mediterrani, S/n",
    "sg:city":"Segur Calafell",
    "sg:orig_category":"Cajas De Ahorro",
    "sg:phone":"+34 977 67 29 22",
    "sg:postcode":"43882",
    "sg:province":"Tarragona",
    "wof:name":"Caixa D'estalvis De Tarragona",
    "wof:placetype":"venue"
},
  "geometry": {"coordinates":[1.6059299707,41.1933441162],"type":"Point"}
}