{
  "type": "Feature",
  "properties": {
    "addr:full":"Carrer de Transversal 8, 47 Barcelona Barcelona 08040",
    "addr:housenumber":"47",
    "addr:postcode":"08040",
    "addr:street":"Carrer De Transversal 8",
    "iso:country":"ES",
    "sg:address":"Carrer de Transversal 8, 47",
    "sg:city":"Barcelona",
    "sg:orig_category":"Embalajes",
    "sg:phone":"+34 932 62 03 22",
    "sg:postcode":"08040",
    "sg:province":"Barcelona",
    "wof:name":"Salvapack 2015 S.l.",
    "wof:placetype":"venue"
},
  "geometry": {"coordinates":[2.1148428917,41.3270759583],"type":"Point"}
}