{
  "type": "Feature",
  "properties": {
    "iso:country":"ES",
    "sg:address":"Calle de Gamiz Bidea, 61",
    "sg:city":"Mungia",
    "sg:orig_category":"Promotores Constructores",
    "sg:phone":"+34 946 74 22 55",
    "sg:postcode":"48100",
    "sg:province":"Vizcaya",
    "wof:name":"Emergencias Munguia Sl",
    "wof:placetype":"venue"
},
  "geometry": {"coordinates":[-2.8353419304,43.3368415833],"type":"Point"}
}