{
  "type": "Feature",
  "properties": {
    "iso:country":"ES",
    "sg:address":"Carrer de Anselm Clave, 4",
    "sg:city":"Granollers",
    "sg:orig_category":"Ropa Para Ni\u00d1os (al Por Menor)",
    "sg:phone":"+34 938 79 41 86",
    "sg:postcode":"08401",
    "sg:province":"Barcelona",
    "wof:name":"Lopez Corcoll Bibiana",
    "wof:placetype":"venue"
},
  "geometry": {"coordinates":[2.2887830734,41.6082077026],"type":"Point"}
}