{
  "type": "Feature",
  "properties": {
    "addr:full":"Bda Zabal (p I Zabal Bajo), S/n La Linea C\u00e1diz 11300",
    "addr:housenumber":"s / n",
    "addr:postcode":"11300",
    "addr:street":"La Linea Ca\u0301Diz",
    "iso:country":"ES",
    "sg:address":"Bda Zabal (p I Zabal Bajo), S/n",
    "sg:city":"La Linea",
    "sg:orig_category":"Construcciones Met\u00c1licas",
    "sg:phone":"+34 956 64 37 77",
    "sg:postcode":"11300",
    "sg:province":"C\u00e1diz",
    "wof:name":"Montajes T.m.a. S.l.",
    "wof:placetype":"venue"
},
  "geometry": {"coordinates":[-5.3429989815,36.1873588562],"type":"Point"}
}