{
  "type": "Feature",
  "properties": {
    "addr:full":"Carrer de Sant Pere, 53 Lloret Mar Girona 17310",
    "addr:housenumber":"53",
    "addr:postcode":"17310",
    "addr:street":"Carrer De Sant Pere",
    "iso:country":"ES",
    "sg:address":"Carrer de Sant Pere, 53",
    "sg:city":"Lloret Mar",
    "sg:orig_category":"Zapatos (al Por Menor)",
    "sg:phone":"+34 972 36 37 50",
    "sg:postcode":"17310",
    "sg:province":"Girona",
    "wof:name":"Per Tu S. L.",
    "wof:placetype":"venue"
},
  "geometry": {"coordinates":[2.845649004,41.7012367249],"type":"Point"}
}