{
  "type": "Feature",
  "properties": {
    "iso:country":"ES",
    "sg:address":"Rua Capitan Eloy, 7",
    "sg:city":"Ourense",
    "sg:orig_category":"Centros De Coordinaci\u00d3n",
    "sg:phone":"+34 988 21 22 01",
    "sg:postcode":"32003",
    "sg:province":"Ourense",
    "wof:name":"Iglesias Perez Luis Mario",
    "wof:placetype":"venue"
},
  "geometry": {"coordinates":[-7.8653640747,42.3396186829],"type":"Point"}
}