{
  "type": "Feature",
  "properties": {
    "addr:full":"Calle de Regina, 16 Sanlucar De Barrameda C\u00e1diz 11540",
    "addr:housenumber":"16",
    "addr:postcode":"11540",
    "addr:street":"Calle De Regina;Ca\u0301Diz",
    "iso:country":"ES",
    "sg:address":"Calle de Regina, 16",
    "sg:city":"Sanlucar De Barrameda",
    "sg:orig_category":"Molduras, Junquillos, Listones Y Molduras Perforadas",
    "sg:phone":"+34 956 36 91 72",
    "sg:postcode":"11540",
    "sg:province":"C\u00e1diz",
    "wof:name":"Sanchez Vila Carmen Julia",
    "wof:placetype":"venue"
},
  "geometry": {"coordinates":[-6.3526549339,36.7781105042],"type":"Point"}
}