{
  "type": "Feature",
  "properties": {
    "iso:country":"ES",
    "sg:address":"Carrer de Eduard Brossa, 70",
    "sg:city":"Sabadell",
    "sg:orig_category":"Estudios De Grabaci\u00d3n Sonora",
    "sg:phone":"+34 937 11 32 62",
    "sg:postcode":"08204",
    "sg:province":"Barcelona",
    "sg:website":"www.carelirecords.com",
    "wof:name":"Careli Records S.l.",
    "wof:placetype":"venue"
},
  "geometry": {"coordinates":[2.1163749695,41.5251998901],"type":"Point"}
}