{
  "type": "Feature",
  "properties": {
    "addr:full":"Carr El Priorat, 32 Lleida Lleida 25005",
    "addr:housenumber":"32",
    "addr:postcode":"25005",
    "addr:street":"Carr El Priorat",
    "iso:country":"ES",
    "sg:address":"Carr El Priorat, 32",
    "sg:city":"Lleida",
    "sg:orig_category":"Chapister\u00cda",
    "sg:phone":"+34 973 23 18 20",
    "sg:postcode":"25005",
    "sg:province":"Lleida",
    "wof:name":"Marsal Amoros Pedro",
    "wof:placetype":"venue"
},
  "geometry": {"coordinates":[0.6254979968,41.6264839172],"type":"Point"}
}