{
  "type": "Feature",
  "properties": {
    "addr:full":"Iturriotz Kalea, 23 Arrasate Guip\u00f9zcoa 20500",
    "addr:housenumber":"23",
    "addr:postcode":"20500",
    "addr:street":"Iturriotz Kalea;Guipu\u0300Zcoa",
    "iso:country":"ES",
    "sg:address":"Iturriotz Kalea, 23",
    "sg:city":"Arrasate",
    "sg:orig_category":"Ropa Para Ni\u00d1os (al Por Menor)",
    "sg:phone":"+34 943 77 02 76",
    "sg:postcode":"20500",
    "sg:province":"Guip\u00f9zcoa",
    "wof:name":"Carrasco Amado Maria Carmen",
    "wof:placetype":"venue"
},
  "geometry": {"coordinates":[-2.490434885,43.065448761],"type":"Point"}
}