{
  "type": "Feature",
  "properties": {
    "addr:full":"Pl. Doctor Trueta, S/n Parets Del Valles Barcelona 08150",
    "addr:housenumber":"s / n",
    "addr:postcode":"08150",
    "addr:street":"Pl. Doctor Trueta",
    "iso:country":"ES",
    "sg:address":"Pl. Doctor Trueta, S/n",
    "sg:city":"Parets Del Valles",
    "sg:orig_category":"Poller\u00cda Y Caza (al Por Menor)",
    "sg:phone":"+34 935 62 48 52",
    "sg:postcode":"08150",
    "sg:province":"Barcelona",
    "wof:name":"El Gall D'or S.cv.",
    "wof:placetype":"venue"
},
  "geometry": {"coordinates":[2.2319469452,41.5694198608],"type":"Point"}
}