{
  "type": "Feature",
  "properties": {
    "addr:full":"Ctra Soria, Km. 0325,0 Quintanilla Onesimo Valladolid 47350",
    "addr:postcode":"47350",
    "addr:street":"Ctra Soria Km. 0325,0 Quintanilla",
    "iso:country":"ES",
    "sg:address":"Ctra Soria, Km. 0325,0",
    "sg:city":"Quintanilla Onesimo",
    "sg:classifiers":[
        {
            "category":"Manufacturing",
            "subcategory":"Building Materials",
            "type":"Manufacturing & Wholesale Goods"
        }
    ],
    "sg:phone":"+34 983 68 11 46",
    "sg:postcode":"47350",
    "sg:province":"Valladolid",
    "sg:tags":[
        "bebidas",
        "para",
        "la",
        "de",
        "y",
        "equipo",
        "industria"
    ],
    "sg:website":"www.arzuaganavarro.com",
    "wof:name":"Bodegas Arzuaga Navarro S.l.",
    "wof:placetype":"venue"
},
  "geometry": {"coordinates":[-4.3622441292,41.6264533997],"type":"Point"}
}