{
  "type": "Feature",
  "properties": {
    "iso:country":"ES",
    "sg:address":"Calle de Peregrinos (los), 4",
    "sg:city":"Palencia",
    "sg:orig_category":"Peluquer\u00cdas, Peluquer\u00cda Mixta",
    "sg:phone":"+34 979 72 58 14",
    "sg:postcode":"34004",
    "sg:province":"Palencia",
    "wof:name":"Salas Martin Maria Eugenia",
    "wof:placetype":"venue"
},
  "geometry": {"coordinates":[-4.5221261978,41.9987068176],"type":"Point"}
}