{
  "type": "Feature",
  "properties": {
    "addr:full":"Calle de Honorato Juan, 18 Valencia Valencia 46007",
    "addr:housenumber":"18",
    "addr:postcode":"46007",
    "addr:street":"Calle De Honorato Juan",
    "iso:country":"ES",
    "sg:address":"Calle de Honorato Juan, 18",
    "sg:city":"Valencia",
    "sg:orig_category":"Bares, Piano",
    "sg:phone":"+34 963 84 51 33",
    "sg:postcode":"46007",
    "sg:province":"Valencia",
    "wof:name":"Fernandez Belenguer Maria Gemma",
    "wof:placetype":"venue"
},
  "geometry": {"coordinates":[-0.3870019913,39.4654197693],"type":"Point"}
}