{
  "type": "Feature",
  "properties": {
    "addr:full":"Pda. Colomers, S/n Mollerussa Lleida 25230",
    "addr:housenumber":"s / n",
    "addr:postcode":"25230",
    "iso:country":"ES",
    "sg:address":"Pda. Colomers, S/n",
    "sg:city":"Mollerussa",
    "sg:orig_category":"Vidrio, Fabricaci\u00d3n Y Comercio",
    "sg:phone":"+34 973 60 22 10",
    "sg:postcode":"25230",
    "sg:province":"Lleida",
    "wof:name":"Acristallaments Miquel S.l.",
    "wof:placetype":"venue"
},
  "geometry": {"coordinates":[0.8913522959,41.6226844788],"type":"Point"}
}