{
  "type": "Feature",
  "properties": {
    "iso:country":"ES",
    "sg:address":"Poli Pol.indust. El Segre, 89",
    "sg:city":"Lleida",
    "sg:orig_category":"Extinci\u00d3n De Incendios: Material Y Suministros (fabricaci\u00d3n, Al Por Mayor)",
    "sg:phone":"+34 973 21 27 10",
    "sg:postcode":"25191",
    "sg:province":"Lleida",
    "wof:name":"Serviseguridad Lleida S.l.",
    "wof:placetype":"venue"
},
  "geometry": {"coordinates":[0.6831650138,41.5832138062],"type":"Point"}
}