{
  "type": "Feature",
  "properties": {
    "iso:country":"ES",
    "sg:address":"C/ 16, 55",
    "sg:city":"Ca\u00d1ada",
    "sg:orig_category":"Molduras, Junquillos, Listones Y Molduras Perforadas",
    "sg:phone":"+34 961 32 06 33",
    "sg:postcode":"46182",
    "sg:province":"Valencia",
    "wof:name":"Gonzalez Garrido Amparo",
    "wof:placetype":"venue"
},
  "geometry": {"coordinates":[-0.4923132956,39.5305900574],"type":"Point"}
}