{
  "type": "Feature",
  "properties": {
    "iso:country":"ES",
    "sg:address":"Calle de Iglesia (de La), 6",
    "sg:city":"Alcobendas",
    "sg:orig_category":"Supermercados Y Hipermercados",
    "sg:phone":"+34 916 51 72 54",
    "sg:postcode":"28100",
    "sg:province":"Madrid",
    "wof:name":"Coalve S.l.",
    "wof:placetype":"venue"
},
  "geometry": {"coordinates":[-3.6321129799,40.540725708],"type":"Point"}
}