{
  "type": "Feature",
  "properties": {
    "iso:country":"ES",
    "sg:address":"Calle de Ramon Y Cajal, 48",
    "sg:city":"Fuente-alamo",
    "sg:orig_category":"Reposter\u00cdas",
    "sg:phone":"+34 967 32 11 98",
    "sg:postcode":"02651",
    "sg:province":"Albacete",
    "wof:name":"Horno Noni S.l.",
    "wof:placetype":"venue"
},
  "geometry": {"coordinates":[-1.4320160151,38.6914787292],"type":"Point"}
}