{
  "type": "Feature",
  "properties": {
    "addr:full":"Rbla Prim, 160 Barcelona Barcelona 08020",
    "addr:housenumber":"160",
    "addr:postcode":"08020",
    "addr:street":"Rbla Prim",
    "iso:country":"ES",
    "sg:address":"Rbla Prim, 160",
    "sg:city":"Barcelona",
    "sg:orig_category":"Molduras, Junquillos, Listones Y Molduras Perforadas",
    "sg:phone":"+34 933 14 79 85",
    "sg:postcode":"08020",
    "sg:province":"Barcelona",
    "wof:name":"Gomez Caizares Jose",
    "wof:placetype":"venue"
},
  "geometry": {"coordinates":[2.2082688808,41.4203147888],"type":"Point"}
}