{
  "type": "Feature",
  "properties": {
    "addr:full":"Calle de Monteagudo, 27 Torrevieja Alicante 03180",
    "addr:housenumber":"27",
    "addr:postcode":"03180",
    "addr:street":"Calle De Monteagudo",
    "iso:country":"ES",
    "sg:address":"Calle de Monteagudo, 27",
    "sg:city":"Torrevieja",
    "sg:orig_category":"Promotores Constructores",
    "sg:phone":"+34 965 70 78 19",
    "sg:postcode":"03180",
    "sg:province":"Alicante",
    "wof:name":"Offen  Lars",
    "wof:placetype":"venue"
},
  "geometry": {"coordinates":[-0.6536790133,38.0173606873],"type":"Point"}
}