{
  "type": "Feature",
  "properties": {
    "iso:country":"ES",
    "sg:address":"Carr Sant Joan Baptista La Salle, 1",
    "sg:city":"Girona",
    "sg:orig_category":"Carnicer\u00cdas, Carnicer\u00cdas",
    "sg:phone":"+34 972 20 27 74",
    "sg:postcode":"17002",
    "sg:province":"Girona",
    "wof:name":"Frigorificos Casacuberta S. A.",
    "wof:placetype":"venue"
},
  "geometry": {"coordinates":[2.8227910995,41.976978302],"type":"Point"}
}