{
  "type": "Feature",
  "properties": {
    "iso:country":"ES",
    "sg:address":"Calle de Francisco Paino, 30",
    "sg:city":"Madrid",
    "sg:orig_category":"Ropa Para Se\u00d1oras (al Por Menor)",
    "sg:phone":"+34 915 65 29 46",
    "sg:postcode":"28025",
    "sg:province":"Madrid",
    "wof:name":"Sope\u00f1a Ardura Esteban",
    "wof:placetype":"venue"
},
  "geometry": {"coordinates":[-3.7279627323,40.3816490173],"type":"Point"}
}