{
  "type": "Feature",
  "properties": {
    "iso:country":"ES",
    "sg:address":"Calle de Alamo, 60",
    "sg:city":"Manzanilla",
    "sg:orig_category":"Caf\u00c9s, Bares, Cervecer\u00cdas",
    "sg:phone":"+34 959 41 50 27",
    "sg:postcode":"21890",
    "sg:province":"Huelva",
    "wof:name":"Salas Y Salas S.c.",
    "wof:placetype":"venue"
},
  "geometry": {"coordinates":[-6.4301757812,37.3922309875],"type":"Point"}
}