{
  "type": "Feature",
  "properties": {
    "addr:full":"Calle de Infantas (de Las), 12 Aranjuez Madrid 28300",
    "addr:housenumber":"12",
    "addr:postcode":"28300",
    "addr:street":"Calle De Infantas De Las",
    "iso:country":"ES",
    "sg:address":"Calle de Infantas (de Las), 12",
    "sg:city":"Aranjuez",
    "sg:orig_category":"Promotores Constructores",
    "sg:phone":"+34 918 92 36 32",
    "sg:postcode":"28300",
    "sg:province":"Madrid",
    "wof:name":"Promociones Inmobiliarias Aranjuez S.l.",
    "wof:placetype":"venue"
},
  "geometry": {"coordinates":[-3.6027479172,40.0349273682],"type":"Point"}
}