{
  "type": "Feature",
  "properties": {
    "iso:country":"ES",
    "sg:address":"Ctra Palamos-nucli, 61",
    "sg:city":"Bordils",
    "sg:classifiers":[
        {
            "category":"Personal",
            "subcategory":"Barber",
            "type":"Services"
        }
    ],
    "sg:phone":"+34 972 49 11 24",
    "sg:postcode":"17462",
    "sg:province":"Girona",
    "sg:tags":[
        "caballeros",
        "de",
        "peluqueros"
    ],
    "wof:name":"Pont Galan Josep Maria",
    "wof:placetype":"venue"
},
  "geometry": {"coordinates":[2.9117949009,42.0443763733],"type":"Point"}
}