{
  "type": "Feature",
  "properties": {
    "iso:country":"ES",
    "sg:address":"Carrer de Sicilia, 210",
    "sg:city":"Barcelona",
    "sg:orig_category":"Motocicletas (agentes, Concesionarios)",
    "sg:phone":"+34 932 31 05 25",
    "sg:postcode":"08013",
    "sg:province":"Barcelona",
    "wof:name":"Box Sicilia 210 S.l.",
    "wof:placetype":"venue"
},
  "geometry": {"coordinates":[2.1786630154,41.397857666],"type":"Point"}
}