{
  "type": "Feature",
  "properties": {
    "addr:full":"Calle de Fray Graciano, 5 Pola De Laviana Asturias 33980",
    "addr:housenumber":"5",
    "addr:postcode":"33980",
    "addr:street":"Calle De Fray Graciano;Pola",
    "iso:country":"ES",
    "sg:address":"Calle de Fray Graciano, 5",
    "sg:city":"Pola De Laviana",
    "sg:orig_category":"Promotores Constructores",
    "sg:phone":"+34 985 61 07 91",
    "sg:postcode":"33980",
    "sg:province":"Asturias",
    "wof:name":"Joaquin Fernandez Sanchez S.l.",
    "wof:placetype":"venue"
},
  "geometry": {"coordinates":[-5.5616369247,43.2462120056],"type":"Point"}
}