{
  "type": "Feature",
  "properties": {
    "iso:country":"ES",
    "sg:address":"Calle de Bilbao, 31",
    "sg:city":"Mairena Aljarafe",
    "sg:orig_category":"Textil",
    "sg:phone":"+34 954 76 31 82",
    "sg:postcode":"41927",
    "sg:province":"Sevilla",
    "sg:website":"www.la-gitana.com",
    "wof:name":"Corento Ernesto Manuel",
    "wof:placetype":"venue"
},
  "geometry": {"coordinates":[-6.0376625061,37.3536529541],"type":"Point"}
}