{
  "type": "Feature",
  "properties": {
    "iso:country":"ES",
    "sg:address":"Cmno Aguas, 45",
    "sg:city":"Salamanca",
    "sg:orig_category":"Carnicer\u00cdas, Carnicer\u00cdas",
    "sg:phone":"+34 923 18 37 33",
    "sg:postcode":"37003",
    "sg:province":"Salamanca",
    "wof:name":"Santos Sanchez Ana Belem",
    "wof:placetype":"venue"
},
  "geometry": {"coordinates":[-5.6509690285,40.9634742737],"type":"Point"}
}