{
  "type": "Feature",
  "properties": {
    "iso:country":"ES",
    "sg:address":"Avda Padre Isla, 40",
    "sg:city":"Le\u00f3n",
    "sg:orig_category":"Abogados",
    "sg:phone":"+34 987 24 21 56",
    "sg:postcode":"24002",
    "sg:province":"Le\u00f3n",
    "wof:name":"Prada Abogados C.b.",
    "wof:placetype":"venue"
},
  "geometry": {"coordinates":[-5.5741519928,42.6010971069],"type":"Point"}
}