{
  "type": "Feature",
  "properties": {
    "iso:country":"ES",
    "sg:address":"Grup Doctor Areilza, 14",
    "sg:city":"Gallarta",
    "sg:orig_category":"Mec\u00c1nico Del Autom\u00d3vil",
    "sg:phone":"+34 946 36 94 14",
    "sg:postcode":"48500",
    "sg:province":"Vizcaya",
    "wof:name":"Garcia Arias Emilio",
    "wof:placetype":"venue"
},
  "geometry": {"coordinates":[-3.0715970993,43.3150177002],"type":"Point"}
}