{
  "type": "Feature",
  "properties": {
    "addr:full":"Barr Arraibi, 23 Arraibi Vizcaya 48330",
    "addr:housenumber":"23",
    "addr:postcode":"48330",
    "addr:street":"Arraibi",
    "iso:country":"ES",
    "sg:address":"Barr Arraibi, 23",
    "sg:city":"Arraibi",
    "sg:orig_category":"Productos Alimentarios",
    "sg:phone":"+34 946 31 38 55",
    "sg:postcode":"48330",
    "sg:province":"Vizcaya",
    "wof:name":"Zuluaga Iturbe Maria Bego\u00f1a",
    "wof:placetype":"venue"
},
  "geometry": {"coordinates":[-2.6983869076,43.2204284668],"type":"Point"}
}