{
  "type": "Feature",
  "properties": {
    "iso:country":"ES",
    "sg:address":"Calle de Francisco Silvela, 11",
    "sg:city":"Madrid",
    "sg:orig_category":"Bisuter\u00cda, Joyer\u00cda, Relojer\u00cda (al Por Menor)",
    "sg:phone":"+34 914 01 78 26",
    "sg:postcode":"28028",
    "sg:province":"Madrid",
    "wof:name":"Terron Manrique Maria Jose",
    "wof:placetype":"venue"
},
  "geometry": {"coordinates":[-3.6702528,40.4295272827],"type":"Point"}
}