{
  "type": "Feature",
  "properties": {
    "addr:full":"Monte Gandara, S/n El Puente Zamora 49350",
    "addr:housenumber":"s / n",
    "addr:postcode":"49350",
    "addr:street":"El Puente Zamora",
    "iso:country":"ES",
    "sg:address":"Monte Gandara, S/n",
    "sg:city":"El Puente",
    "sg:orig_category":"Centros De Educaci\u00d3n Especial",
    "sg:phone":"+34 980 62 02 33",
    "sg:postcode":"49350",
    "sg:province":"Zamora",
    "sg:website":"www.centros4.pntic.mec.es/cp.monte.gandara",
    "wof:name":"Colegio Nacional Mixto Comarcal",
    "wof:placetype":"venue"
},
  "geometry": {"coordinates":[-6.6421990395,42.0836639404],"type":"Point"}
}