{
  "type": "Feature",
  "properties": {
    "iso:country":"ES",
    "sg:address":"Calle de Nu\u00d1ez De Balboa, 3",
    "sg:city":"Huercal-overa",
    "sg:orig_category":"Fabricaci\u00d3n De Telas Y Sedas",
    "sg:phone":"+34 950 47 09 63",
    "sg:postcode":"04600",
    "sg:province":"Almer\u00eda",
    "wof:name":"Lopez Viudez Diego",
    "wof:placetype":"venue"
},
  "geometry": {"coordinates":[-1.9401600361,37.3927726746],"type":"Point"}
}