{
  "type": "Feature",
  "properties": {
    "addr:full":"Calle de Hermanos Torre Oru\u00d1a, S/n Muriedas Cantabria 39600",
    "addr:housenumber":"s",
    "addr:postcode":"39600",
    "addr:street":"Calle De Hermanos Torre Orun\u0303A;/ N",
    "iso:country":"ES",
    "sg:address":"Calle de Hermanos Torre Oru\u00d1a, S/n",
    "sg:city":"Muriedas",
    "sg:orig_category":"Reciclaje Y Tratamiento De Desechos Varios",
    "sg:phone":"+34 942 26 07 44",
    "sg:postcode":"39600",
    "sg:province":"Cantabria",
    "wof:name":"A.g.recuperaciones Industriales S.l.",
    "wof:placetype":"venue"
},
  "geometry": {"coordinates":[-3.8475859165,43.4230232239],"type":"Point"}
}