{
  "type": "Feature",
  "properties": {
    "iso:country":"ES",
    "sg:address":"Constitucion, 26",
    "sg:city":"O Temple",
    "sg:orig_category":"Quincaller\u00cda (al Por Menor)",
    "sg:phone":"+34 981 66 13 62",
    "sg:postcode":"15679",
    "sg:province":"La Coru\u00f1a",
    "wof:name":"Mendez Loureiro Concepcion",
    "wof:placetype":"venue"
},
  "geometry": {"coordinates":[-8.3685693741,43.3172721863],"type":"Point"}
}