{
  "type": "Feature",
  "properties": {
    "addr:full":"Rua Padre Amoedo Carballo, 2 Pontevedra Pontevedra 36002",
    "addr:housenumber":"2",
    "addr:postcode":"36002",
    "addr:street":"Rua Padre Amoedo Carballo",
    "iso:country":"ES",
    "sg:address":"Rua Padre Amoedo Carballo, 2",
    "sg:city":"Pontevedra",
    "sg:orig_category":"Lencer\u00cda Femenina, Corseter\u00cda, Trajes De Ba\u00d1o (al Por Menor)",
    "sg:phone":"+34 986 84 04 09",
    "sg:postcode":"36002",
    "sg:province":"Pontevedra",
    "wof:name":"Giraldez Se\u00f1orans Pilar",
    "wof:placetype":"venue"
},
  "geometry": {"coordinates":[-8.641371727,42.4331130981],"type":"Point"}
}