{
  "type": "Feature",
  "properties": {
    "iso:country":"ES",
    "sg:address":"C/ Sant Cristofol, 30",
    "sg:city":"Arenal",
    "sg:orig_category":"Lentes De Contacto",
    "sg:phone":"+34 971 44 13 74",
    "sg:postcode":"07600",
    "sg:province":"Islas Baleares",
    "wof:name":"Gari Llompart Paloma",
    "wof:placetype":"venue"
},
  "geometry": {"coordinates":[2.752327919,39.5086097717],"type":"Point"}
}