{
  "type": "Feature",
  "properties": {
    "iso:country":"ES",
    "sg:address":"Pl Creu (la), 3",
    "sg:city":"Molins Rei",
    "sg:orig_category":"Estancos",
    "sg:phone":"+34 936 68 22 32",
    "sg:postcode":"08750",
    "sg:province":"Barcelona",
    "wof:name":"Margarit Casas Jaume",
    "wof:placetype":"venue"
},
  "geometry": {"coordinates":[2.0193040371,41.4108276367],"type":"Point"}
}