{
  "type": "Feature",
  "properties": {
    "iso:country":"ES",
    "sg:address":"Calle de General Etxague, 11",
    "sg:city":"Donostia-san Sebastian",
    "sg:orig_category":"Empresas De Carpinter\u00cda De Madera",
    "sg:phone":"+34 943 42 00 42",
    "sg:postcode":"20003",
    "sg:province":"Guip\u00f9zcoa",
    "wof:name":"Pastor Inchausti Fernando",
    "wof:placetype":"venue"
},
  "geometry": {"coordinates":[-1.9817090034,43.3238334656],"type":"Point"}
}