{
  "type": "Feature",
  "properties": {
    "iso:country":"ES",
    "sg:address":"Calle de San Francisco, 4",
    "sg:city":"Castellon",
    "sg:orig_category":"Relojer\u00cda (al Por Menor, Reparaci\u00d3n)",
    "sg:phone":"+34 964 21 67 78",
    "sg:postcode":"12002",
    "sg:province":"Castell\u00f3n",
    "wof:name":"Guinot Sierra Agustin",
    "wof:placetype":"venue"
},
  "geometry": {"coordinates":[-0.0413900018,39.984287262],"type":"Point"}
}