{
  "type": "Feature",
  "properties": {
    "iso:country":"ES",
    "sg:address":"Av Pere Badosa, S/n",
    "sg:city":"Olot",
    "sg:orig_category":"Clubes Y Asociaciones Deportivas Y De Actividades Invernales Y De Monta\u00d1a",
    "sg:phone":"+34 972 27 07 31",
    "sg:postcode":"17800",
    "sg:province":"Girona",
    "sg:website":"www.cnolot.com",
    "wof:name":"Club Natacion Olot",
    "wof:placetype":"venue"
},
  "geometry": {"coordinates":[2.5093948841,42.1896705627],"type":"Point"}
}