{
  "type": "Feature",
  "properties": {
    "iso:country":"ES",
    "sg:address":"Bo. Santiagui\u00f1o, 20",
    "sg:city":"Santiagui\u00d1o",
    "sg:orig_category":"M\u00c1quinas Y Material Para La Industria De La Alimentaci\u00d3n",
    "sg:phone":"+34 986 48 88 73",
    "sg:postcode":"36417",
    "sg:province":"Pontevedra",
    "wof:name":"Serviman Fet S.l.",
    "wof:placetype":"venue"
},
  "geometry": {"coordinates":[-8.6178617477,42.2033996582],"type":"Point"}
}