{
  "type": "Feature",
  "properties": {
    "addr:full":"Plaza De Pio Xii, S/n G\u00fcevejar Granada 18197",
    "addr:housenumber":"s / n",
    "addr:postcode":"18197",
    "addr:street":"Xii",
    "iso:country":"ES",
    "sg:address":"Plaza De Pio Xii, S/n",
    "sg:city":"G\u00fcevejar",
    "sg:orig_category":"Cajas De Ahorro",
    "sg:phone":"+34 958 42 92 64",
    "sg:postcode":"18197",
    "sg:province":"Granada",
    "sg:website":"www.cajagranada.es",
    "wof:name":"Cajagranada",
    "wof:placetype":"venue"
},
  "geometry": {"coordinates":[-3.6097240448,37.2210998535],"type":"Point"}
}