{
  "type": "Feature",
  "properties": {
    "iso:country":"ES",
    "sg:address":"Calle de Juan De Soto, 6",
    "sg:city":"Alcala Henares",
    "sg:orig_category":"Colchones (fabricaci\u00d3n, Al Por Mayor, Al Por Menor)",
    "sg:phone":"+34 918 89 85 87",
    "sg:postcode":"28804",
    "sg:province":"Madrid",
    "wof:name":"Rodriguez Rodriguez Daria",
    "wof:placetype":"venue"
},
  "geometry": {"coordinates":[-3.3540039062,40.4844932556],"type":"Point"}
}