{
  "type": "Feature",
  "properties": {
    "addr:full":"Calle de Perdomo, 41 Palmas De Gran Canaria Las Palmas 35002",
    "addr:housenumber":"41",
    "addr:postcode":"35002",
    "addr:street":"Calle De Perdomo",
    "iso:country":"ES",
    "sg:address":"Calle de Perdomo, 41",
    "sg:city":"Palmas De Gran Canaria",
    "sg:orig_category":"M\u00c9dicos: Psiquiatr\u00cda",
    "sg:phone":"+34 928 36 01 18",
    "sg:postcode":"35002",
    "sg:province":"Las Palmas",
    "wof:name":"Trujillo Cubas Angel",
    "wof:placetype":"venue"
},
  "geometry": {"coordinates":[-15.4199476242,28.105266571],"type":"Point"}
}