{
  "type": "Feature",
  "properties": {
    "iso:country":"ES",
    "sg:address":"Carrer de Campoamor, 36",
    "sg:city":"Hospitalet Llobregat",
    "sg:orig_category":"Ebanister\u00cda",
    "sg:phone":"+34 932 63 26 29",
    "sg:postcode":"08907",
    "sg:province":"Barcelona",
    "wof:name":"Lopez Aliaga Emilio",
    "wof:placetype":"venue"
},
  "geometry": {"coordinates":[2.1144189835,41.3573570251],"type":"Point"}
}