{
  "type": "Feature",
  "properties": {
    "addr:full":"Pase Palmeras Las, 23 Huelva Huelva 21002",
    "addr:housenumber":"23",
    "addr:postcode":"21002",
    "addr:street":"Las",
    "iso:country":"ES",
    "sg:address":"Pase Palmeras Las, 23",
    "sg:city":"Huelva",
    "sg:orig_category":"Inform\u00c1tica, Ofim\u00c1tica (estudios, Asesor\u00cda, Ingenier\u00cda, Formaci\u00d3n)",
    "sg:phone":"+34 959 54 09 31",
    "sg:postcode":"21002",
    "sg:province":"Huelva",
    "sg:website":"www.anforaformacion.es",
    "wof:name":"Anfora Formacion S.l.",
    "wof:placetype":"venue"
},
  "geometry": {"coordinates":[-6.9539160728,37.2640266418],"type":"Point"}
}