{
  "type": "Feature",
  "properties": {
    "iso:country":"ES",
    "sg:address":"Barri Padro, 8",
    "sg:city":"Celra",
    "sg:orig_category":"Agencias Y Agentes Comerciales, Representantes",
    "sg:phone":"+34 972 49 20 17",
    "sg:postcode":"17460",
    "sg:province":"Girona",
    "wof:name":"Narcis Ramada S.l.",
    "wof:placetype":"venue"
},
  "geometry": {"coordinates":[2.8825910091,42.023223877],"type":"Point"}
}