{
  "type": "Feature",
  "properties": {
    "iso:country":"ES",
    "sg:address":"Calle de Moreno Torroba, 9",
    "sg:city":"Badajoz",
    "sg:orig_category":"Alquiler De Casas Y Habitaciones Amuebladas",
    "sg:phone":"+34 924 27 46 55",
    "sg:postcode":"06006",
    "sg:province":"Badajoz",
    "wof:name":"Residencial Santa Eulalia S.a.l.",
    "wof:placetype":"venue"
},
  "geometry": {"coordinates":[-7.0163488388,38.882976532],"type":"Point"}
}