{
  "type": "Feature",
  "properties": {
    "addr:full":"Calle de Ancha, 45 Palma Rio C\u00f3rdoba 14700",
    "addr:housenumber":"45",
    "addr:postcode":"14700",
    "addr:street":"Calle De Ancha;Rio Co\u0301Rdoba",
    "iso:country":"ES",
    "sg:address":"Calle de Ancha, 45",
    "sg:city":"Palma Rio",
    "sg:orig_category":"Agentes Generales De Seguros",
    "sg:phone":"+34 957 64 67 33",
    "sg:postcode":"14700",
    "sg:province":"C\u00f3rdoba",
    "wof:name":"Fernandez Caro Emilio",
    "wof:placetype":"venue"
},
  "geometry": {"coordinates":[-5.2793006897,37.6982879639],"type":"Point"}
}