{
  "type": "Feature",
  "properties": {
    "addr:full":"Calle de Marques De Molins, 19 Albacete Albacete 02001",
    "addr:housenumber":"19",
    "addr:postcode":"02001",
    "addr:street":"Calle De Marques De Molins",
    "iso:country":"ES",
    "sg:address":"Calle de Marques De Molins, 19",
    "sg:city":"Albacete",
    "sg:orig_category":"Papeler\u00cdas, Librer\u00cdas",
    "sg:phone":"+34 967 21 33 24",
    "sg:postcode":"02001",
    "sg:province":"Albacete",
    "wof:name":"Gallego Soria Juan Pedro",
    "wof:placetype":"venue"
},
  "geometry": {"coordinates":[-1.8547979593,38.9934577942],"type":"Point"}
}