{
  "type": "Feature",
  "properties": {
    "addr:full":"Rua Covadonga, 2 Vilagarcia Pontevedra 36600",
    "addr:housenumber":"2",
    "addr:postcode":"36600",
    "addr:street":"Rua Covadonga",
    "iso:country":"ES",
    "sg:address":"Rua Covadonga, 2",
    "sg:city":"Vilagarcia",
    "sg:orig_category":"Institutos De Belleza",
    "sg:phone":"+34 986 50 64 77",
    "sg:postcode":"36600",
    "sg:province":"Pontevedra",
    "wof:name":"Garcia Baloiras Luz Myriam",
    "wof:placetype":"venue"
},
  "geometry": {"coordinates":[-8.7659416199,42.5941963196],"type":"Point"}
}