{
  "type": "Feature",
  "properties": {
    "iso:country":"ES",
    "sg:address":"Crri Parragas, 1",
    "sg:city":"Nonduermas",
    "sg:orig_category":"Asociaciones, Organismos Culturales Y Socioeducativos",
    "sg:phone":"+34 968 25 78 71",
    "sg:postcode":"30166",
    "sg:province":"Murcia",
    "wof:name":"Ayuntamiento De Murcia",
    "wof:placetype":"venue"
},
  "geometry": {"coordinates":[-1.1673840284,37.9729614258],"type":"Point"}
}