{
  "type": "Feature",
  "properties": {
    "iso:country":"ES",
    "sg:address":"Arragua Nuc., S/n",
    "sg:city":"Oiartzun",
    "sg:classifiers":[
        {
            "category":"Taxi",
            "type":"Transportation"
        }
    ],
    "sg:phone":"+34 943 49 19 76",
    "sg:postcode":"20180",
    "sg:province":"Guip\u00f9zcoa",
    "wof:name":"Martiarena Irastorza Manuel",
    "wof:placetype":"venue"
},
  "geometry": {"coordinates":[-1.8729389906,43.3085098267],"type":"Point"}
}