{
  "type": "Feature",
  "properties": {
    "iso:country":"ES",
    "sg:address":"Carr Sant Jaume, 108",
    "sg:city":"Almacelles",
    "sg:orig_category":"Peluquer\u00cdas, Peluquer\u00cda Mixta",
    "sg:phone":"+34 973 74 21 15",
    "sg:postcode":"25100",
    "sg:province":"Lleida",
    "wof:name":"Encanteris S.c.p",
    "wof:placetype":"venue"
},
  "geometry": {"coordinates":[0.4402849972,41.7282371521],"type":"Point"}
}