{
  "type": "Feature",
  "properties": {
    "addr:full":"Ctra. Hinojales, S/n Ca\u00f1averal Leon Huelva 21388",
    "addr:housenumber":"s",
    "addr:postcode":"21388",
    "addr:street":"Ctra. Hinojales;/ N Can\u0303Averal",
    "iso:country":"ES",
    "sg:address":"Ctra. Hinojales, S/n",
    "sg:city":"Ca\u00f1averal Leon",
    "sg:orig_category":"Centros De Educaci\u00d3n Especial",
    "sg:phone":"+34 959 46 58 75",
    "sg:postcode":"21388",
    "sg:province":"Huelva",
    "wof:name":"Junta De Andalucia",
    "wof:placetype":"venue"
},
  "geometry": {"coordinates":[-6.5897941589,38.0084838867],"type":"Point"}
}