{
  "type": "Feature",
  "properties": {
    "iso:country":"ES",
    "sg:address":"Ctra Briones (de), 13",
    "sg:city":"S. Vicente Sonsierra",
    "sg:orig_category":"Panader\u00cdas, Panader\u00cdas",
    "sg:phone":"+34 941 33 43 60",
    "sg:postcode":"26338",
    "sg:province":"La Rioja",
    "wof:name":"Hermanos Alutiz Peci\u00f1a Cdad",
    "wof:placetype":"venue"
},
  "geometry": {"coordinates":[-2.7588191032,42.5630836487],"type":"Point"}
}