{
  "type": "Feature",
  "properties": {
    "addr:full":"Pque Santurtzi, 1 Santurtzi Vizcaya 48980",
    "addr:postcode":"48980",
    "iso:country":"ES",
    "sg:address":"Pque Santurtzi, 1",
    "sg:city":"Santurtzi",
    "sg:orig_category":"Caf\u00c9s, Bares, Cervecer\u00cdas",
    "sg:phone":"+34 944 83 64 64",
    "sg:postcode":"48980",
    "sg:province":"Vizcaya",
    "wof:name":"Cafe La Estacion",
    "wof:placetype":"venue"
},
  "geometry": {"coordinates":[-3.0306019783,43.3283348083],"type":"Point"}
}