{
  "type": "Feature",
  "properties": {
    "addr:full":"Yerri, 19 Estella Navarra 31200",
    "addr:housenumber":"19",
    "addr:postcode":"31200",
    "addr:street":"Yerri",
    "iso:country":"ES",
    "sg:address":"Yerri, 19",
    "sg:city":"Estella",
    "sg:orig_category":"Porcelanas, Azulejos (fabricaci\u00d3n, Al Por Mayor)",
    "sg:phone":"+34 948 55 37 53",
    "sg:postcode":"31200",
    "sg:province":"Navarra",
    "wof:name":"Cesar Maya S.l.",
    "wof:placetype":"venue"
},
  "geometry": {"coordinates":[-2.03531003,42.6747207642],"type":"Point"}
}