{
  "type": "Feature",
  "properties": {
    "addr:full":"C/ Reina Victoria, 74 Elche Alicante 03201",
    "addr:housenumber":"74",
    "addr:postcode":"03201",
    "addr:street":"C / Reina Victoria",
    "iso:country":"ES",
    "sg:address":"C/ Reina Victoria, 74",
    "sg:city":"Elche",
    "sg:orig_category":"Arquitectos",
    "sg:phone":"+34 965 42 52 46",
    "sg:postcode":"03201",
    "sg:province":"Alicante",
    "wof:name":"Arquitectura Rv 74 S.l.",
    "wof:placetype":"venue"
},
  "geometry": {"coordinates":[-0.7063869834,38.2654800415],"type":"Point"}
}