{
  "type": "Feature",
  "properties": {
    "addr:full":"Calle de Mercedes (de Las), 7 Mostoles Madrid 28931",
    "addr:housenumber":"7",
    "addr:postcode":"28931",
    "addr:street":"Calle De Mercedes De Las",
    "iso:country":"ES",
    "sg:address":"Calle de Mercedes (de Las), 7",
    "sg:city":"Mostoles",
    "sg:orig_category":"Ense\u00d1anza, Formaci\u00d3n Profesional: Aprendizaje",
    "sg:phone":"+34 916 46 24 59",
    "sg:postcode":"28931",
    "sg:province":"Madrid",
    "wof:name":"Gutierrez Rodriguez Joaquina",
    "wof:placetype":"venue"
},
  "geometry": {"coordinates":[-3.8587920666,40.3263244629],"type":"Point"}
}