{
  "type": "Feature",
  "properties": {
    "addr:full":"Calle de Maestro Falla, 1 Calahorra La Rioja 26500",
    "addr:housenumber":"1",
    "addr:postcode":"26500",
    "addr:street":"Calle De Maestro Falla",
    "iso:country":"ES",
    "sg:address":"Calle de Maestro Falla, 1",
    "sg:city":"Calahorra",
    "sg:orig_category":"Restaurantes",
    "sg:phone":"+34 941 14 74 34",
    "sg:postcode":"26500",
    "sg:province":"La Rioja",
    "wof:name":"Hotel Ciudad De Calahorra S.l.",
    "wof:placetype":"venue"
},
  "geometry": {"coordinates":[-1.9666479826,42.3043136597],"type":"Point"}
}