{
  "type": "Feature",
  "properties": {
    "addr:full":"Calle de Palomas (las), S/n Jerez De La Frontera C\u00e1diz 11406",
    "addr:postcode":"11406",
    "addr:street":"Calle De Palomas Las S / N",
    "iso:country":"ES",
    "sg:address":"Calle de Palomas (las), S/n",
    "sg:city":"Jerez De La Frontera",
    "sg:orig_category":"Impermeabilizantes",
    "sg:phone":"+34 956 33 65 86",
    "sg:postcode":"11406",
    "sg:province":"C\u00e1diz",
    "wof:name":"Cabrera Martin Carlos",
    "wof:placetype":"venue"
},
  "geometry": {"coordinates":[-6.113694191,36.6817588806],"type":"Point"}
}