{
  "type": "Feature",
  "properties": {
    "iso:country":"ES",
    "sg:address":"Ctra Marina, Km. 0007,0",
    "sg:city":"Elche",
    "sg:orig_category":"Semiller\u00cdas",
    "sg:phone":"+34 965 42 83 55",
    "sg:postcode":"03295",
    "sg:province":"Alicante",
    "wof:name":"Plantas Europeas S.l.",
    "wof:placetype":"venue"
},
  "geometry": {"coordinates":[-0.6361610293,38.2748413086],"type":"Point"}
}