{
  "type": "Feature",
  "properties": {
    "iso:country":"ES",
    "sg:address":"Aios, 8",
    "sg:city":"Aios",
    "sg:orig_category":"Agencias Y Asesores De Publicidad",
    "sg:phone":"+34 986 72 04 52",
    "sg:postcode":"36990",
    "sg:province":"Pontevedra",
    "wof:name":"Acad Viaria S.l.",
    "wof:placetype":"venue"
},
  "geometry": {"coordinates":[-8.8475189209,42.4100608826],"type":"Point"}
}