{
  "type": "Feature",
  "properties": {
    "iso:country":"ES",
    "sg:address":"Av Montilivi, S/n",
    "sg:city":"Girona",
    "sg:orig_category":"Agencias Y Asesores De Publicidad",
    "sg:phone":"+34 972 41 40 44",
    "sg:postcode":"17003",
    "sg:province":"Girona",
    "wof:name":"Tot Esports I Comunicacio S.l.",
    "wof:placetype":"venue"
},
  "geometry": {"coordinates":[2.8258450031,41.9693946838],"type":"Point"}
}