{
  "type": "Feature",
  "properties": {
    "iso:country":"ES",
    "sg:address":"Carrer de Alber, 29",
    "sg:city":"Palma",
    "sg:orig_category":"Asociaciones, Organismos Culturales Y Socioeducativos",
    "sg:phone":"+34 971 47 13 00",
    "sg:postcode":"07008",
    "sg:province":"Islas Baleares",
    "wof:name":"Organizacion Juvenil Espa\u00d1ola",
    "wof:placetype":"venue"
},
  "geometry": {"coordinates":[2.675757885,39.5848846436],"type":"Point"}
}