{
  "type": "Feature",
  "properties": {
    "addr:full":"Calle de Iglesia, 19 Picazo Cuenca 16211",
    "addr:housenumber":"19",
    "addr:postcode":"16211",
    "addr:street":"Calle De Iglesia",
    "iso:country":"ES",
    "sg:address":"Calle de Iglesia, 19",
    "sg:city":"Picazo",
    "sg:orig_category":"Cajas De Ahorro",
    "sg:phone":"+34 969 38 01 45",
    "sg:postcode":"16211",
    "sg:province":"Cuenca",
    "wof:name":"Caja De Ahorros De Castilla La Mancha",
    "wof:placetype":"venue"
},
  "geometry": {"coordinates":[-2.0881619453,39.4482192993],"type":"Point"}
}