{
  "type": "Feature",
  "properties": {
    "iso:country":"ES",
    "sg:address":"Plaz Alfonso X El Sabio, S/n",
    "sg:city":"Pola De Lena",
    "sg:orig_category":"Iglesia Cat\u00d3lica",
    "sg:phone":"+34 985 49 08 22",
    "sg:postcode":"33630",
    "sg:province":"Asturias",
    "wof:name":"Diocesis De Oviedo",
    "wof:placetype":"venue"
},
  "geometry": {"coordinates":[-5.829419136,43.1590194702],"type":"Point"}
}