{
  "type": "Feature",
  "properties": {
    "iso:country":"ES",
    "sg:address":"Pla\u00c7 Mercat, Des, S/n",
    "sg:city":"Soller",
    "sg:orig_category":"Florister\u00cdas",
    "sg:phone":"+34 971 63 07 86",
    "sg:postcode":"07100",
    "sg:province":"Islas Baleares",
    "wof:name":"Yakabi Tabata Zoila",
    "wof:placetype":"venue"
},
  "geometry": {"coordinates":[2.7083287239,39.7749633789],"type":"Point"}
}