{
  "type": "Feature",
  "properties": {
    "iso:country":"ES",
    "sg:address":"Luga Dragonal Alto, 64",
    "sg:city":"Dragonal Alto",
    "sg:orig_category":"M\u00c9dicos: Anestesiolog\u00cda Y Reanimaci\u00d3n Quir\u00dargica",
    "sg:phone":"+34 928 35 37 69",
    "sg:postcode":"35017",
    "sg:province":"Las Palmas",
    "wof:name":"Anestisiologia Y Dolor De Canarias",
    "wof:placetype":"venue"
},
  "geometry": {"coordinates":[-15.4300060272,28.1248226166],"type":"Point"}
}