{
  "type": "Feature",
  "properties": {
    "addr:full":"Avda Italia, 15 Sevilla Sevilla 41012",
    "addr:housenumber":"15",
    "addr:postcode":"41012",
    "addr:street":"Avda Italia",
    "iso:country":"ES",
    "sg:address":"Avda Italia, 15",
    "sg:city":"Sevilla",
    "sg:orig_category":"Alimentaci\u00d3n General (al Por Menor)",
    "sg:phone":"+34 954 23 41 88",
    "sg:postcode":"41012",
    "sg:province":"Sevilla",
    "wof:name":"Aylatan Arch S.l",
    "wof:placetype":"venue"
},
  "geometry": {"coordinates":[-5.9792737961,37.3513145447],"type":"Point"}
}