{
  "type": "Feature",
  "properties": {
    "addr:full":"Calle de Santa Teresa, 10 Prado Del Rey C\u00e1diz 11660",
    "addr:housenumber":"10",
    "addr:postcode":"11660",
    "addr:street":"Calle De Santa Teresa",
    "iso:country":"ES",
    "sg:address":"Calle de Santa Teresa, 10",
    "sg:city":"Prado Del Rey",
    "sg:orig_category":"Asesor\u00cda Fiscal Y Jur\u00cddica",
    "sg:phone":"+34 956 72 30 20",
    "sg:postcode":"11660",
    "sg:province":"C\u00e1diz",
    "wof:name":"Blanco Orellana Isabel Maria",
    "wof:placetype":"venue"
},
  "geometry": {"coordinates":[-5.5554242134,36.7878875732],"type":"Point"}
}