{
  "type": "Feature",
  "properties": {
    "addr:full":"Ctra Albaida-denia, Km. 0063,0 Denia Alicante 03700",
    "addr:postcode":"03700",
    "addr:street":"Ctra Albaida-Denia Km. 0063,0",
    "iso:country":"ES",
    "sg:address":"Ctra Albaida-denia, Km. 0063,0",
    "sg:city":"Denia",
    "sg:orig_category":"Ense\u00d1anza, Formaci\u00d3n Profesional: Aprendizaje",
    "sg:phone":"+34 965 78 71 93",
    "sg:postcode":"03700",
    "sg:province":"Alicante",
    "wof:name":"Consorcio Provincial Para El Servicio De Prevencion Y Extincion De Incendios",
    "wof:placetype":"venue"
},
  "geometry": {"coordinates":[0.1039630026,38.8354949951],"type":"Point"}
}