{
  "type": "Feature",
  "properties": {
    "iso:country":"ES",
    "sg:address":"Calle de Tinte, 2",
    "sg:city":"Alcala Henares",
    "sg:orig_category":"Ropa Para Se\u00d1oras (al Por Menor)",
    "sg:phone":"+34 918 82 97 03",
    "sg:postcode":"28801",
    "sg:province":"Madrid",
    "wof:name":"Ramani S. A.",
    "wof:placetype":"venue"
},
  "geometry": {"coordinates":[-3.3639550209,40.4838562012],"type":"Point"}
}