{
  "type": "Feature",
  "properties": {
    "addr:full":"C/ Francisco Vicente Rodriguez, 5 Elche Alicante 03202",
    "addr:housenumber":"5",
    "addr:postcode":"03202",
    "addr:street":"C / Francisco Vicente Rodriguez",
    "iso:country":"ES",
    "sg:address":"C/ Francisco Vicente Rodriguez, 5",
    "sg:city":"Elche",
    "sg:orig_category":"Venta, Instalaci\u00d3n De Calefacci\u00d3n",
    "sg:phone":"+34 902 45 15 26",
    "sg:postcode":"03202",
    "sg:province":"Alicante",
    "sg:website":"www.electrofret.com",
    "wof:name":"Servicio Asistencia Tecnica Anton S.l.",
    "wof:placetype":"venue"
},
  "geometry": {"coordinates":[-0.6872590184,38.2711181641],"type":"Point"}
}