{
  "type": "Feature",
  "properties": {
    "addr:full":"Calle de Cervantes, 7 Sotillo Adrada \u00c1vila 05420",
    "addr:housenumber":"7",
    "addr:postcode":"05420",
    "addr:street":"Calle De Cervantes",
    "iso:country":"ES",
    "sg:address":"Calle de Cervantes, 7",
    "sg:city":"Sotillo Adrada",
    "sg:classifiers":[
        {
            "category":"Personal",
            "subcategory":"Barber",
            "type":"Services"
        }
    ],
    "sg:phone":"+34 918 66 05 23",
    "sg:postcode":"05420",
    "sg:province":"\u00c1vila",
    "sg:tags":[
        "caballeros",
        "de",
        "peluqueros"
    ],
    "wof:name":"Martin Perez Felix",
    "wof:placetype":"venue"
},
  "geometry": {"coordinates":[-4.632619381,40.303314209],"type":"Point"}
}