{
  "type": "Feature",
  "properties": {
    "addr:full":"Carrer de Doctor Ramon Solanich I Riera, 21 Hospitalet Llobregat Barcelona 08905",
    "addr:housenumber":"21",
    "addr:postcode":"08905",
    "addr:street":"Carrer De Doctor Ramon Solanich;Riera",
    "iso:country":"ES",
    "sg:address":"Carrer de Doctor Ramon Solanich I Riera, 21",
    "sg:city":"Hospitalet Llobregat",
    "sg:orig_category":"Peluqueros: De Se\u00d1oras",
    "sg:phone":"+34 933 34 09 39",
    "sg:postcode":"08905",
    "sg:province":"Barcelona",
    "wof:name":"Valles Serramia Rosa Maria",
    "wof:placetype":"venue"
},
  "geometry": {"coordinates":[2.1076059341,41.3738136292],"type":"Point"}
}