{
  "type": "Feature",
  "properties": {
    "addr:full":"Ctra Sierra (de La), 100 Granada Granada 18008",
    "addr:housenumber":"100",
    "addr:postcode":"18008",
    "addr:street":"Ctra Sierra De La",
    "iso:country":"ES",
    "sg:address":"Ctra Sierra (de La), 100",
    "sg:city":"Granada",
    "sg:orig_category":"Farmacias",
    "sg:phone":"+34 958 22 86 62",
    "sg:postcode":"18008",
    "sg:province":"Granada",
    "wof:name":"Garcia Tunez Julia",
    "wof:placetype":"venue"
},
  "geometry": {"coordinates":[-3.5791039467,37.1646881104],"type":"Point"}
}