{
  "type": "Feature",
  "properties": {
    "iso:country":"ES",
    "sg:address":"Calle de Segovia, 32",
    "sg:city":"Cuellar",
    "sg:orig_category":"Vinos Y Licores (venta Al Por Menor)",
    "sg:phone":"+34 921 14 02 76",
    "sg:postcode":"40200",
    "sg:province":"Segovia",
    "wof:name":"Renedo Cdad.",
    "wof:placetype":"venue"
},
  "geometry": {"coordinates":[-4.3128814697,41.3979988098],"type":"Point"}
}