{
  "type": "Feature",
  "properties": {
    "addr:full":"Avda Ca\u00d1a (la), 80 Algeciras C\u00e1diz 11203",
    "addr:housenumber":"80;ca\u0301diz",
    "addr:postcode":"11203",
    "addr:street":"Avda Can\u0303A La",
    "iso:country":"ES",
    "sg:address":"Avda Ca\u00d1a (la), 80",
    "sg:city":"Algeciras",
    "sg:orig_category":"Ropa Para Se\u00d1oras (al Por Menor)",
    "sg:phone":"+34 956 65 02 21",
    "sg:postcode":"11203",
    "sg:province":"C\u00e1diz",
    "wof:name":"Mejias Gallardo Jose",
    "wof:placetype":"venue"
},
  "geometry": {"coordinates":[-5.5040016174,36.131477356],"type":"Point"}
}