{
  "type": "Feature",
  "properties": {
    "addr:full":"Calle de Madrid, 71 Humanes De Madrid Madrid 28970",
    "addr:housenumber":"71",
    "addr:postcode":"28970",
    "addr:street":"Calle De Madrid",
    "iso:country":"ES",
    "sg:address":"Calle de Madrid, 71",
    "sg:city":"Humanes De Madrid",
    "sg:orig_category":"Guarder\u00cdas",
    "sg:phone":"+34 916 04 07 30",
    "sg:postcode":"28970",
    "sg:province":"Madrid",
    "wof:name":"Perez Mateo Maria Del Carmen",
    "wof:placetype":"venue"
},
  "geometry": {"coordinates":[-3.8259971142,40.2550582886],"type":"Point"}
}