{
  "type": "Feature",
  "properties": {
    "addr:full":"Calle de Su\u00d1ol, 10 Zuera Zaragoza 50800",
    "addr:housenumber":"10",
    "addr:postcode":"50800",
    "addr:street":"Calle De Sun\u0303Ol",
    "iso:country":"ES",
    "sg:address":"Calle de Su\u00d1ol, 10",
    "sg:city":"Zuera",
    "sg:orig_category":"Planchado",
    "sg:phone":"+34 976 69 02 86",
    "sg:postcode":"50800",
    "sg:province":"Zaragoza",
    "wof:name":"Bienzobas Buenacasa Anabella",
    "wof:placetype":"venue"
},
  "geometry": {"coordinates":[-0.7889180183,41.8674659729],"type":"Point"}
}