{
  "type": "Feature",
  "properties": {
    "iso:country":"ES",
    "sg:address":"Pol Ind Arza, 2",
    "sg:city":"Llodio",
    "sg:orig_category":"Materias Pl\u00c1sticas: Productos Acabados Y Semiacabados (fabricaci\u00d3n)",
    "sg:phone":"+34 946 72 14 58",
    "sg:postcode":"01400",
    "sg:province":"\u00c1lava",
    "wof:name":"Laudio Plast S.l.",
    "wof:placetype":"venue"
},
  "geometry": {"coordinates":[-2.9624290466,43.1436882019],"type":"Point"}
}