{
  "type": "Feature",
  "properties": {
    "iso:country":"ES",
    "sg:address":"Avda Miguel Cano, S/n",
    "sg:city":"Marbella",
    "sg:orig_category":"Alquiler De V\u00cddeo",
    "sg:phone":"+34 952 82 32 48",
    "sg:postcode":"29600",
    "sg:province":"M\u00e1laga",
    "wof:name":"Baeza Y Carvellido S.l.",
    "wof:placetype":"venue"
},
  "geometry": {"coordinates":[-4.8869900703,36.50806427],"type":"Point"}
}