{
  "type": "Feature",
  "properties": {
    "addr:full":"Avda Doctor Artero Guirao, 232 S. Pedro Pinatar Murcia 30740",
    "addr:housenumber":"232",
    "addr:postcode":"30740",
    "addr:street":"Avda Doctor Artero Guirao",
    "iso:country":"ES",
    "sg:address":"Avda Doctor Artero Guirao, 232",
    "sg:city":"S. Pedro Pinatar",
    "sg:orig_category":"Agentes, Concesionarios Y Sucursales De Veh\u00cdculos",
    "sg:phone":"+34 968 18 51 80",
    "sg:postcode":"30740",
    "sg:province":"Murcia",
    "wof:name":"Automenor S.a.",
    "wof:placetype":"venue"
},
  "geometry": {"coordinates":[-0.7987490296,37.8309059143],"type":"Point"}
}