{
  "type": "Feature",
  "properties": {
    "addr:full":"Ctra San Juan Del Puerto A Caceres, Km. 0008,0 Trigueros Huelva 21620",
    "addr:postcode":"21620",
    "addr:street":"Ctra San Juan Del Puerto A Caceres Km. 0008,0",
    "iso:country":"ES",
    "sg:address":"Ctra San Juan Del Puerto A Caceres, Km. 0008,0",
    "sg:city":"Trigueros",
    "sg:orig_category":"Garajes De Veh\u00cdculos",
    "sg:phone":"+34 959 30 64 13",
    "sg:postcode":"21620",
    "sg:province":"Huelva",
    "wof:name":"Trimotor S.l.",
    "wof:placetype":"venue"
},
  "geometry": {"coordinates":[-6.8301939964,37.3829040527],"type":"Point"}
}