{
  "type": "Feature",
  "properties": {
    "addr:full":"Calle de Agustin Principe, 3 Zaragoza Zaragoza 50011",
    "addr:housenumber":"3",
    "addr:postcode":"50011",
    "addr:street":"Calle De Agustin Principe",
    "iso:country":"ES",
    "sg:address":"Calle de Agustin Principe, 3",
    "sg:city":"Zaragoza",
    "sg:orig_category":"Empresas De Carpinter\u00cda",
    "sg:phone":"+34 976 56 88 60",
    "sg:postcode":"50011",
    "sg:province":"Zaragoza",
    "wof:name":"Vidrio-glass S.l.",
    "wof:placetype":"venue"
},
  "geometry": {"coordinates":[-0.9913589954,41.662853241],"type":"Point"}
}