{
  "type": "Feature",
  "properties": {
    "addr:full":"Av Barbera, 141 Sabadell Barcelona 08203",
    "addr:housenumber":"141",
    "addr:postcode":"08203",
    "addr:street":"Av Barbera",
    "iso:country":"ES",
    "sg:address":"Av Barbera, 141",
    "sg:city":"Sabadell",
    "sg:orig_category":"Institutos De Belleza",
    "sg:phone":"+34 937 10 79 76",
    "sg:postcode":"08203",
    "sg:province":"Barcelona",
    "wof:name":"Jobel Centre-salud-belleza Sccl",
    "wof:placetype":"venue"
},
  "geometry": {"coordinates":[2.1142940521,41.5362091064],"type":"Point"}
}