{
  "type": "Feature",
  "properties": {
    "iso:country":"ES",
    "sg:address":"Av J V Foix, 56",
    "sg:city":"Barcelona",
    "sg:orig_category":"Promotores Constructores",
    "sg:phone":"+34 932 80 49 22",
    "sg:postcode":"08034",
    "sg:province":"Barcelona",
    "wof:name":"Palissandre S.l.",
    "wof:placetype":"venue"
},
  "geometry": {"coordinates":[2.120347023,41.395160675],"type":"Point"}
}