{
  "type": "Feature",
  "properties": {
    "addr:full":"C/ Bisbe Cardona, De, 8 S. Antoni Portmany Islas Baleares 07820",
    "addr:postcode":"07820",
    "addr:street":"C / Bisbe Cardona De 8",
    "iso:country":"ES",
    "sg:address":"C/ Bisbe Cardona, De, 8",
    "sg:city":"S. Antoni Portmany",
    "sg:orig_category":"Promotores Constructores",
    "sg:phone":"+34 971 34 77 48",
    "sg:postcode":"07820",
    "sg:province":"Islas Baleares",
    "wof:name":"Obras Algemir S.l.",
    "wof:placetype":"venue"
},
  "geometry": {"coordinates":[1.5188339949,39.1094055176],"type":"Point"}
}