{
  "type": "Feature",
  "properties": {
    "addr:full":"Calle de Guitarrista Fortea, 3 Castellon Castell\u00f3n 12005",
    "addr:housenumber":"3",
    "addr:postcode":"12005",
    "addr:street":"Calle De Guitarrista Fortea;Castello\u0301N",
    "iso:country":"ES",
    "sg:address":"Calle de Guitarrista Fortea, 3",
    "sg:city":"Castellon",
    "sg:orig_category":"Inmobiliaria (agencias)",
    "sg:phone":"+34 964 23 09 94",
    "sg:postcode":"12005",
    "sg:province":"Castell\u00f3n",
    "wof:name":"Ventura Nebot Jose",
    "wof:placetype":"venue"
},
  "geometry": {"coordinates":[-0.0355320014,39.9806137085],"type":"Point"}
}