{
  "type": "Feature",
  "properties": {
    "addr:full":"Calle de Benavides, 65 Santa Cruz De Tenerife Santa Cruz De Tenerife 38004",
    "addr:housenumber":"65",
    "addr:postcode":"38004",
    "addr:street":"Calle De Benavides",
    "iso:country":"ES",
    "sg:address":"Calle de Benavides, 65",
    "sg:city":"Santa Cruz De Tenerife",
    "sg:orig_category":"Inform\u00c1tica (estudios, Servicios, Asesor\u00cda, Formaci\u00d3n)",
    "sg:phone":"+34 922 27 34 45",
    "sg:postcode":"38004",
    "sg:province":"Santa Cruz De Tenerife",
    "sg:website":"www.vobis.es",
    "wof:name":"Seica S.l.",
    "wof:placetype":"venue"
},
  "geometry": {"coordinates":[-16.2593231201,28.4665546417],"type":"Point"}
}