{
  "type": "Feature",
  "properties": {
    "iso:country":"ES",
    "sg:address":"F. Vallegarcia, S/n",
    "sg:city":"Retuerta Bullaque",
    "sg:orig_category":"Producci\u00d3n, Distribuci\u00d3n De Gas Butano Y Propano",
    "sg:phone":"+34 925 42 17 57",
    "sg:postcode":"13194",
    "sg:province":"Ciudad Real",
    "wof:name":"Repsol Ypf S.a.",
    "wof:placetype":"venue"
},
  "geometry": {"coordinates":[-4.4406938553,39.5062103271],"type":"Point"}
}