{
  "type": "Feature",
  "properties": {
    "iso:country":"ES",
    "sg:address":"Martires, 4",
    "sg:city":"Graus",
    "sg:orig_category":"Panader\u00cdas, Panader\u00cdas",
    "sg:phone":"+34 974 54 60 45",
    "sg:postcode":"22430",
    "sg:province":"Huesca",
    "wof:name":"Pasteleria F Puyet S L",
    "wof:placetype":"venue"
},
  "geometry": {"coordinates":[0.3397000134,42.192024231],"type":"Point"}
}