{
  "type": "Feature",
  "properties": {
    "iso:country":"ES",
    "sg:address":"Calle de San Isidro, 1",
    "sg:city":"Tarifa",
    "sg:orig_category":"Librer\u00cdas",
    "sg:phone":"+34 956 68 06 33",
    "sg:postcode":"11380",
    "sg:province":"C\u00e1diz",
    "wof:name":"Soler Sanchez Fernando",
    "wof:placetype":"venue"
},
  "geometry": {"coordinates":[-5.6058912277,36.0136795044],"type":"Point"}
}