{
  "type": "Feature",
  "properties": {
    "iso:country":"ES",
    "sg:address":"Avda Barcelona, 9",
    "sg:city":"Monzon",
    "sg:orig_category":"Vallados Y Barreras",
    "sg:phone":"+34 974 41 77 66",
    "sg:postcode":"22400",
    "sg:province":"Huesca",
    "wof:name":"Manufacturas Del Cerramiento Monzon S.l.",
    "wof:placetype":"venue"
},
  "geometry": {"coordinates":[0.2066799998,41.9008293152],"type":"Point"}
}