{
  "type": "Feature",
  "properties": {
    "addr:full":"Calle de San Francisco, 15 Quintanar Orden Toledo 45800",
    "addr:housenumber":"15",
    "addr:postcode":"45800",
    "addr:street":"Calle De San Francisco",
    "iso:country":"ES",
    "sg:address":"Calle de San Francisco, 15",
    "sg:city":"Quintanar Orden",
    "sg:orig_category":"Institutos De Belleza",
    "sg:phone":"+34 925 18 20 08",
    "sg:postcode":"45800",
    "sg:province":"Toledo",
    "wof:name":"Fernandez Gomez Maria Teresa",
    "wof:placetype":"venue"
},
  "geometry": {"coordinates":[-3.0418860912,39.5921669006],"type":"Point"}
}