{
  "type": "Feature",
  "properties": {
    "iso:country":"ES",
    "sg:address":"Avda Palomares, 17",
    "sg:city":"San Juan De Aznalfarache",
    "sg:orig_category":"Sociedades, Compa\u00d1\u00cdas Aseguradoras",
    "sg:phone":"+34 954 76 60 50",
    "sg:postcode":"41920",
    "sg:province":"Sevilla",
    "wof:name":"Ocaso S.a. Compa\u00f1ia De Seguros Y Reaseguros",
    "wof:placetype":"venue"
},
  "geometry": {"coordinates":[-6.0337958336,37.3568916321],"type":"Point"}
}