{
  "type": "Feature",
  "properties": {
    "addr:full":"Carrer de Consolat Del Mar, 2 Denia Alicante 03700",
    "addr:housenumber":"2",
    "addr:postcode":"03700",
    "addr:street":"Carrer De Consolat Del Mar",
    "iso:country":"ES",
    "sg:address":"Carrer de Consolat Del Mar, 2",
    "sg:city":"Denia",
    "sg:orig_category":"Alquiler De Veh\u00cdculos: Turismos Y Utilitarios",
    "sg:phone":"+34 966 42 31 36",
    "sg:postcode":"03700",
    "sg:province":"Alicante",
    "wof:name":"Sol-mar Alquiler De Vehiculos S.l.",
    "wof:placetype":"venue"
},
  "geometry": {"coordinates":[0.1026899964,38.8474388123],"type":"Point"}
}