{
  "type": "Feature",
  "properties": {
    "addr:full":"Madro\u00d1al, S/n Madro\u00f1al C\u00f3rdoba 14600",
    "addr:postcode":"14600",
    "addr:street":"Madron\u0303Al S / N Madron\u0303Al Co\u0301Rdoba",
    "iso:country":"ES",
    "sg:address":"Madro\u00d1al, S/n",
    "sg:city":"Madro\u00f1al",
    "sg:orig_category":"Producci\u00d3n, Venta De Productos De Agricultura Biol\u00d3gica",
    "sg:phone":"+34 957 33 60 75",
    "sg:postcode":"14600",
    "sg:province":"C\u00f3rdoba",
    "wof:name":"Incir S.l.",
    "wof:placetype":"venue"
},
  "geometry": {"coordinates":[-4.3815989494,38.0260391235],"type":"Point"}
}