{
  "type": "Feature",
  "properties": {
    "addr:full":"Carrer de Isaac Peral, 6 S. Just Desvern Barcelona 08960",
    "addr:housenumber":"6",
    "addr:postcode":"08960",
    "addr:street":"Carrer De Isaac Peral",
    "iso:country":"ES",
    "sg:address":"Carrer de Isaac Peral, 6",
    "sg:city":"S. Just Desvern",
    "sg:orig_category":"Fabricaci\u00d3n Y Comercio De M\u00c1quinas",
    "sg:phone":"+34 933 71 53 89",
    "sg:postcode":"08960",
    "sg:province":"Barcelona",
    "wof:name":"Juan Martin S. L.",
    "wof:placetype":"venue"
},
  "geometry": {"coordinates":[2.0637669563,41.3820533752],"type":"Point"}
}