{
  "type": "Feature",
  "properties": {
    "iso:country":"ES",
    "sg:address":"Calle de Calvario, 11",
    "sg:city":"Ajalvir",
    "sg:orig_category":"Reciclaje, Tratamiento De Pl\u00c1sticos",
    "sg:phone":"+34 918 84 42 10",
    "sg:postcode":"28864",
    "sg:province":"Madrid",
    "wof:name":"Plasticos Benedicto S.l.",
    "wof:placetype":"venue"
},
  "geometry": {"coordinates":[-3.4863805771,40.5331916809],"type":"Point"}
}