{
  "type": "Feature",
  "properties": {
    "iso:country":"ES",
    "sg:address":"Bra\u00f1a, 6",
    "sg:city":"Doso",
    "sg:orig_category":"Tapicer\u00cdas",
    "sg:phone":"+34 981 36 25 14",
    "sg:postcode":"15597",
    "sg:province":"La Coru\u00f1a",
    "wof:name":"Rivera Pi\u00f1on Juan",
    "wof:placetype":"venue"
},
  "geometry": {"coordinates":[-8.163939476,43.5220413208],"type":"Point"}
}