{
  "type": "Feature",
  "properties": {
    "iso:country":"ES",
    "sg:address":"Calle de La Ba\u00d1eza, 33",
    "sg:city":"Madrid",
    "sg:orig_category":"Fabricaci\u00d3n, Distribuci\u00d3n De Discos, V\u00cddeodiscos Y Musicassettes",
    "sg:phone":"+34 913 16 70 70",
    "sg:postcode":"28029",
    "sg:province":"Madrid",
    "wof:name":"G.p. Producciones Discograficas Latinoam",
    "wof:placetype":"venue"
},
  "geometry": {"coordinates":[-3.7154390812,40.4757003784],"type":"Point"}
}