{
  "type": "Feature",
  "properties": {
    "addr:full":"Calle de Venegas, 2 Palmas De Gran Canaria Las Palmas 35003",
    "addr:housenumber":"2",
    "addr:postcode":"35003",
    "addr:street":"Calle De Venegas",
    "iso:country":"ES",
    "sg:address":"Calle de Venegas, 2",
    "sg:city":"Palmas De Gran Canaria",
    "sg:orig_category":"Servicios Diversos",
    "sg:phone":"+34 928 36 22 88",
    "sg:postcode":"35003",
    "sg:province":"Las Palmas",
    "sg:website":"www.latiendadelanbuelo.com",
    "wof:name":"Tienda Del Abuelo",
    "wof:placetype":"venue"
},
  "geometry": {"coordinates":[-15.416466713,28.109664917],"type":"Point"}
}