{
  "type": "Feature",
  "properties": {
    "addr:full":"Calle de Xativa, 6 Valencia Valencia 46002",
    "addr:housenumber":"6",
    "addr:postcode":"46002",
    "addr:street":"Calle De Xativa",
    "iso:country":"ES",
    "sg:address":"Calle de Xativa, 6",
    "sg:city":"Valencia",
    "sg:orig_category":"Cl\u00cdnicas Dentales",
    "sg:phone":"+34 963 52 82 76",
    "sg:postcode":"46002",
    "sg:province":"Valencia",
    "wof:name":"Bagan Sebastian Jose Vicente",
    "wof:placetype":"venue"
},
  "geometry": {"coordinates":[-0.3793227971,39.4680938721],"type":"Point"}
}