{
  "type": "Feature",
  "properties": {
    "addr:full":"Calle de Lagunillas, 51 Malaga M\u00e1laga 29012",
    "addr:housenumber":"51",
    "addr:postcode":"29012",
    "addr:street":"Calle De Lagunillas;Ma\u0301Laga",
    "iso:country":"ES",
    "sg:address":"Calle de Lagunillas, 51",
    "sg:city":"Malaga",
    "sg:orig_category":"Reposter\u00cdas",
    "sg:phone":"+34 952 25 87 18",
    "sg:postcode":"29012",
    "sg:province":"M\u00e1laga",
    "wof:name":"Mato De Jorge Jose Antonio",
    "wof:placetype":"venue"
},
  "geometry": {"coordinates":[-4.4156370163,36.7259140015],"type":"Point"}
}