{
  "type": "Feature",
  "properties": {
    "iso:country":"ES",
    "sg:address":"Calle de Cisneros, Cardenal, 8",
    "sg:city":"Melilla",
    "sg:orig_category":"Abogados",
    "sg:phone":"+34 952 67 84 41",
    "sg:postcode":"52002",
    "sg:province":"Melilla",
    "wof:name":"Imbroda Ortiz Blas Jesus",
    "wof:placetype":"venue"
},
  "geometry": {"coordinates":[-2.9432973862,35.2942810059],"type":"Point"}
}