{
  "type": "Feature",
  "properties": {
    "addr:full":"Carr Enric Granados, 5 Vilanova De Segria Lleida 25133",
    "addr:housenumber":"5",
    "addr:postcode":"25133",
    "addr:street":"Carr Enric Granados",
    "iso:country":"ES",
    "sg:address":"Carr Enric Granados, 5",
    "sg:city":"Vilanova De Segria",
    "sg:orig_category":"Agricultores, Agricultores",
    "sg:phone":"+34 973 77 71 22",
    "sg:postcode":"25133",
    "sg:province":"Lleida",
    "wof:name":"Exgavise S.l.",
    "wof:placetype":"venue"
},
  "geometry": {"coordinates":[0.6163139939,41.7126464844],"type":"Point"}
}