{
  "type": "Feature",
  "properties": {
    "addr:full":"Calle de Obispo Bartolome Espejo, 6 Malaga M\u00e1laga 29014",
    "addr:housenumber":"6",
    "addr:postcode":"29014",
    "addr:street":"Calle De Obispo Bartolome Espejo;Ma\u0301Laga",
    "iso:country":"ES",
    "sg:address":"Calle de Obispo Bartolome Espejo, 6",
    "sg:city":"Malaga",
    "sg:orig_category":"Agencias Y Agentes Comerciales, Representantes",
    "sg:phone":"+34 952 25 82 03",
    "sg:postcode":"29014",
    "sg:province":"M\u00e1laga",
    "wof:name":"Ariza Gomez Francisco",
    "wof:placetype":"venue"
},
  "geometry": {"coordinates":[-4.4219512939,36.7351722717],"type":"Point"}
}