{
  "type": "Feature",
  "properties": {
    "iso:country":"ES",
    "sg:address":"Calle de Cocherito De Bilbao, 13",
    "sg:city":"Bilbao",
    "sg:orig_category":"Empleado Administrativo",
    "sg:phone":"+34 944 12 36 39",
    "sg:postcode":"48004",
    "sg:province":"Vizcaya",
    "wof:name":"Gestoria Lanza S.l.",
    "wof:placetype":"venue"
},
  "geometry": {"coordinates":[-2.9098987579,43.2539787292],"type":"Point"}
}