{
  "type": "Feature",
  "properties": {
    "iso:country":"ES",
    "sg:address":"Calle de Emilio Castelar, 48",
    "sg:city":"Algeciras",
    "sg:orig_category":"Inmobiliaria (agencias)",
    "sg:phone":"+34 956 66 18 18",
    "sg:postcode":"11201",
    "sg:province":"C\u00e1diz",
    "wof:name":"Bienes Y Raices Algecira S.l.",
    "wof:placetype":"venue"
},
  "geometry": {"coordinates":[-5.4485630989,36.1281242371],"type":"Point"}
}