{
  "type": "Feature",
  "properties": {
    "addr:full":"Carrer de Joaquim Costa, 158 Terrassa Barcelona 08222",
    "addr:housenumber":"158",
    "addr:postcode":"08222",
    "addr:street":"Carrer De Joaquim Costa",
    "iso:country":"ES",
    "sg:address":"Carrer de Joaquim Costa, 158",
    "sg:city":"Terrassa",
    "sg:orig_category":"Librer\u00cdas",
    "sg:phone":"+34 937 83 06 18",
    "sg:postcode":"08222",
    "sg:province":"Barcelona",
    "wof:name":"Bertran Medina Montserrat",
    "wof:placetype":"venue"
},
  "geometry": {"coordinates":[2.025906086,41.5603103638],"type":"Point"}
}