{
  "type": "Feature",
  "properties": {
    "addr:full":"El Mediano, S/n Hervas C\u00e1ceres 10700",
    "addr:housenumber":"s / n",
    "addr:postcode":"10700",
    "addr:street":"Ca\u0301Ceres",
    "iso:country":"ES",
    "sg:address":"El Mediano, S/n",
    "sg:city":"Hervas",
    "sg:orig_category":"Ebanister\u00cda",
    "sg:phone":"+34 927 48 14 26",
    "sg:postcode":"10700",
    "sg:province":"C\u00e1ceres",
    "wof:name":"Majadas Neila Hilario",
    "wof:placetype":"venue"
},
  "geometry": {"coordinates":[-5.863948822,40.2720451355],"type":"Point"}
}