{
  "type": "Feature",
  "properties": {
    "addr:full":"Calle de Rio Ulla, 20 Madrid Madrid 28017",
    "addr:housenumber":"20",
    "addr:postcode":"madrid;28017",
    "addr:street":"Calle De Rio Ulla",
    "iso:country":"ES",
    "sg:address":"Calle de Rio Ulla, 20",
    "sg:city":"Madrid",
    "sg:orig_category":"Librer\u00cdas",
    "sg:phone":"+34 913 77 41 74",
    "sg:postcode":"28017",
    "sg:province":"Madrid",
    "wof:name":"Ruiz Serrano Carmen Maria",
    "wof:placetype":"venue"
},
  "geometry": {"coordinates":[-3.6423640251,40.4335899353],"type":"Point"}
}