{
  "type": "Feature",
  "properties": {
    "iso:country":"ES",
    "sg:address":"Av Salle (la), 19",
    "sg:city":"Reus",
    "sg:orig_category":"Fabricaci\u00d3n De Tejidos Para Exteriores",
    "sg:phone":"+34 977 77 67 10",
    "sg:postcode":"43205",
    "sg:province":"Tarragona",
    "wof:name":"Alutoldos Europa S.l.",
    "wof:placetype":"venue"
},
  "geometry": {"coordinates":[1.1067162752,41.1489601135],"type":"Point"}
}