{
  "type": "Feature",
  "properties": {
    "iso:country":"ES",
    "sg:address":"Calle de Pozo Amargo, 20",
    "sg:city":"Toledo",
    "sg:orig_category":"Alimentaci\u00d3n General (al Por Menor)",
    "sg:phone":"+34 925 22 49 47",
    "sg:postcode":"45002",
    "sg:province":"Toledo",
    "wof:name":"Aza\u00f1a Morcuende Luis Miguel",
    "wof:placetype":"venue"
},
  "geometry": {"coordinates":[-4.0235581398,39.8550949097],"type":"Point"}
}