{
  "type": "Feature",
  "properties": {
    "addr:full":"Cno. Del Ave, S/n Pantoja Toledo 45290",
    "addr:housenumber":"s / n",
    "addr:postcode":"45290",
    "addr:street":"Cno. Del Ave",
    "iso:country":"ES",
    "sg:address":"Cno. Del Ave, S/n",
    "sg:city":"Pantoja",
    "sg:orig_category":"Piedra, Vidrio, Cer\u00c1mica Y Porcelana",
    "sg:phone":"+34 925 55 41 31",
    "sg:postcode":"45290",
    "sg:province":"Toledo",
    "wof:name":"Cesan S.l.",
    "wof:placetype":"venue"
},
  "geometry": {"coordinates":[-3.8329589367,40.042175293],"type":"Point"}
}