{
  "type": "Feature",
  "properties": {
    "iso:country":"ES",
    "sg:address":"Via Hispanidad, 58",
    "sg:city":"Zaragoza",
    "sg:orig_category":"Art\u00cdculos M\u00c9dicos",
    "sg:phone":"+34 976 08 17 83",
    "sg:postcode":"50009",
    "sg:province":"Zaragoza",
    "wof:name":"Imagen Y Salud Almudental S.l.l",
    "wof:placetype":"venue"
},
  "geometry": {"coordinates":[-0.9155650139,41.6432418823],"type":"Point"}
}