{
  "type": "Feature",
  "properties": {
    "addr:full":"Carrer de Villar, 28 Barcelona Barcelona 08041",
    "addr:housenumber":"28",
    "addr:postcode":"08041",
    "addr:street":"Carrer De Villar",
    "iso:country":"ES",
    "sg:address":"Carrer de Villar, 28",
    "sg:city":"Barcelona",
    "sg:orig_category":"Contenedores (mercanc\u00cdas)",
    "sg:phone":"+34 934 35 60 53",
    "sg:postcode":"08041",
    "sg:province":"Barcelona",
    "wof:name":"Tundra Trans S.c.c.l.",
    "wof:placetype":"venue"
},
  "geometry": {"coordinates":[2.1791000366,41.4168777466],"type":"Point"}
}