{
  "type": "Feature",
  "properties": {
    "addr:full":"Carrer de Jaume Balmes, 13 Palma Islas Baleares 07005",
    "addr:housenumber":"13",
    "addr:postcode":"07005",
    "addr:street":"Carrer De Jaume Balmes",
    "iso:country":"ES",
    "sg:address":"Carrer de Jaume Balmes, 13",
    "sg:city":"Palma",
    "sg:orig_category":"Agencias Y Agentes Comerciales, Representantes",
    "sg:phone":"+34 971 27 34 42",
    "sg:postcode":"07005",
    "sg:province":"Islas Baleares",
    "wof:name":"Pi\u00f1a Segui Javier",
    "wof:placetype":"venue"
},
  "geometry": {"coordinates":[2.6614310741,39.5790863037],"type":"Point"}
}