{
  "type": "Feature",
  "properties": {
    "iso:country":"ES",
    "sg:address":"Ctra Barrax (3-8), Km. 0002,0",
    "sg:city":"Albacete",
    "sg:orig_category":"Promotores Constructores",
    "sg:phone":"+34 967 22 95 44",
    "sg:postcode":"02005",
    "sg:province":"Albacete",
    "wof:name":"Alvac S.a.",
    "wof:placetype":"venue"
},
  "geometry": {"coordinates":[-1.8907825947,38.9971466064],"type":"Point"}
}