{
  "type": "Feature",
  "properties": {
    "addr:full":"Carr S Magi, 99 Igualada Barcelona 08700",
    "addr:housenumber":"99",
    "addr:postcode":"08700",
    "addr:street":"Carr S Magi",
    "iso:country":"ES",
    "sg:address":"Carr S Magi, 99",
    "sg:city":"Igualada",
    "sg:orig_category":"Fabricaci\u00d3n De Su\u00c9ters Y Chalecos De Punto",
    "sg:phone":"+34 938 03 18 98",
    "sg:postcode":"08700",
    "sg:province":"Barcelona",
    "wof:name":"Alcaraz Suarez Luis",
    "wof:placetype":"venue"
},
  "geometry": {"coordinates":[1.6179126501,41.5848999023],"type":"Point"}
}