{
  "type": "Feature",
  "properties": {
    "addr:full":"Ctra Moron-pbla Cazalla, S/n Moron Frontera Sevilla 41530",
    "addr:housenumber":"s / n",
    "addr:postcode":"41530",
    "addr:street":"Ctra Moron-Pbla Cazalla",
    "iso:country":"ES",
    "sg:address":"Ctra Moron-pbla Cazalla, S/n",
    "sg:city":"Moron Frontera",
    "sg:orig_category":"Inform\u00c1tica, Ofim\u00c1tica (estudios, Asesor\u00cda, Ingenier\u00cda, Formaci\u00d3n)",
    "sg:phone":"+34 955 95 74 32",
    "sg:postcode":"41530",
    "sg:province":"Sevilla",
    "wof:name":"Software Quivir Para La Distribucion S.l.",
    "wof:placetype":"venue"
},
  "geometry": {"coordinates":[-5.4528231621,37.1294212341],"type":"Point"}
}