{
  "type": "Feature",
  "properties": {
    "addr:full":"Avda Pablo Picasso, 32 Granada Granada 18008",
    "addr:housenumber":"32",
    "addr:postcode":"18008",
    "addr:street":"Avda Pablo Picasso",
    "iso:country":"ES",
    "sg:address":"Avda Pablo Picasso, 32",
    "sg:city":"Granada",
    "sg:orig_category":"Producci\u00d3n, Venta De Productos De Agricultura Biol\u00d3gica",
    "sg:phone":"+34 958 81 18 81",
    "sg:postcode":"18008",
    "sg:province":"Granada",
    "wof:name":"Jerez Del Valle S.l.",
    "wof:placetype":"venue"
},
  "geometry": {"coordinates":[-3.5936479568,37.1651954651],"type":"Point"}
}