{
  "type": "Feature",
  "properties": {
    "iso:country":"ES",
    "sg:address":"Calle de San Anton, 52",
    "sg:city":"Parla",
    "sg:orig_category":"Inmobiliaria (agencias)",
    "sg:phone":"+34 916 99 36 77",
    "sg:postcode":"28980",
    "sg:province":"Madrid",
    "wof:name":"Perales Rodriguez Maria Antonia",
    "wof:placetype":"venue"
},
  "geometry": {"coordinates":[-3.7684829235,40.2393836975],"type":"Point"}
}