{
  "type": "Feature",
  "properties": {
    "addr:full":"Calle de Principe De Asturias, 16 Pinoso Alicante 03650",
    "addr:housenumber":"16",
    "addr:postcode":"03650",
    "addr:street":"Calle De Principe De Asturias;Alicante",
    "iso:country":"ES",
    "sg:address":"Calle de Principe De Asturias, 16",
    "sg:city":"Pinoso",
    "sg:orig_category":"Carnicer\u00cdas, Carnicer\u00cdas",
    "sg:phone":"+34 965 47 81 63",
    "sg:postcode":"03650",
    "sg:province":"Alicante",
    "wof:name":"Hermanos Albert C.b.",
    "wof:placetype":"venue"
},
  "geometry": {"coordinates":[-1.0413190126,38.3974990845],"type":"Point"}
}