{
  "type": "Feature",
  "properties": {
    "iso:country":"ES",
    "sg:address":"Calle de San Delfin, 7",
    "sg:city":"Madrid",
    "sg:orig_category":"Art\u00cdculos De Decoraci\u00d3n",
    "sg:phone":"+34 914 60 80 04",
    "sg:postcode":"28019",
    "sg:province":"Madrid",
    "wof:name":"Hansen Hervas Enrique",
    "wof:placetype":"venue"
},
  "geometry": {"coordinates":[-3.7078409195,40.3952827454],"type":"Point"}
}