{
  "type": "Feature",
  "properties": {
    "addr:full":"Carrer de Cienfuegos, 11 Barcelona Barcelona 08027",
    "addr:housenumber":"11",
    "addr:postcode":"08027",
    "addr:street":"Carrer De Cienfuegos",
    "iso:country":"ES",
    "sg:address":"Carrer de Cienfuegos, 11",
    "sg:city":"Barcelona",
    "sg:orig_category":"Empresas De Carpinter\u00cda Met\u00c1lica",
    "sg:phone":"+34 934 08 39 25",
    "sg:postcode":"08027",
    "sg:province":"Barcelona",
    "wof:name":"Dometal Scp",
    "wof:placetype":"venue"
},
  "geometry": {"coordinates":[2.1844449043,41.423915863],"type":"Point"}
}