{
  "type": "Feature",
  "properties": {
    "iso:country":"ES",
    "sg:address":"Carrer de Llibertat, 34",
    "sg:city":"Castelldefels",
    "sg:orig_category":"Promotores Constructores",
    "sg:phone":"+34 936 36 46 70",
    "sg:postcode":"08860",
    "sg:province":"Barcelona",
    "wof:name":"Inmovegas S.l",
    "wof:placetype":"venue"
},
  "geometry": {"coordinates":[1.9755380154,41.2778320312],"type":"Point"}
}