{
  "type": "Feature",
  "properties": {
    "addr:full":"Calle de Carranza, 17 Madrid Madrid 28004",
    "addr:housenumber":"17",
    "addr:postcode":"madrid;28004",
    "addr:street":"Calle De Carranza",
    "iso:country":"ES",
    "sg:address":"Calle de Carranza, 17",
    "sg:city":"Madrid",
    "sg:orig_category":"Materiales De Aislamiento T\u00c9rmico Y Ac\u00dastico",
    "sg:phone":"+34 915 93 89 00",
    "sg:postcode":"28004",
    "sg:province":"Madrid",
    "sg:website":"www.donparabrisas.es",
    "wof:name":"Auto Cristalerias S.a.",
    "wof:placetype":"venue"
},
  "geometry": {"coordinates":[-3.7042219639,40.4291992188],"type":"Point"}
}