{
  "type": "Feature",
  "properties": {
    "iso:country":"ES",
    "sg:address":"Calle de San Isidro, S/n",
    "sg:city":"Alberca De Zancara",
    "sg:orig_category":"Cooperativas Agr\u00cdcolas",
    "sg:phone":"+34 967 15 00 03",
    "sg:postcode":"16620",
    "sg:province":"Cuenca",
    "wof:name":"Cooperativa Del Campo Nuestra Se\u00f1ora De La Asuncion",
    "wof:placetype":"venue"
},
  "geometry": {"coordinates":[-2.4926390648,39.517375946],"type":"Point"}
}