{
  "type": "Feature",
  "properties": {
    "iso:country":"ES",
    "sg:address":"Avda Fernando Blanco, S/n",
    "sg:city":"Cee",
    "sg:orig_category":"Ense\u00d1anza Secundaria: Colegios Y Escuelas Privadas",
    "sg:phone":"+34 981 74 58 85",
    "sg:postcode":"15270",
    "sg:province":"La Coru\u00f1a",
    "wof:name":"Instituto De Formacion Profesional De Cee",
    "wof:placetype":"venue"
},
  "geometry": {"coordinates":[-9.1876478195,42.9559211731],"type":"Point"}
}