{
  "type": "Feature",
  "properties": {
    "iso:country":"ES",
    "sg:address":"Barr Barrondo, S/n",
    "sg:city":"Moyordin-barrondo",
    "sg:orig_category":"Goma: Materias Primas (producci\u00d3n, Distribuci\u00d3n)",
    "sg:phone":"+34 946 71 34 63",
    "sg:postcode":"48480",
    "sg:province":"Vizcaya",
    "sg:website":"www.raisafilm.com",
    "wof:name":"Raisa Film De Polietileno S.a.",
    "wof:placetype":"venue"
},
  "geometry": {"coordinates":[-2.8896090984,43.2052345276],"type":"Point"}
}