{
  "type": "Feature",
  "properties": {
    "iso:country":"ES",
    "sg:address":"Carrer de Cervantes, 109",
    "sg:city":"Terrassa",
    "sg:orig_category":"Molduras, Junquillos, Listones Y Molduras Perforadas",
    "sg:phone":"+34 937 88 78 67",
    "sg:postcode":"08221",
    "sg:province":"Barcelona",
    "wof:name":"Grau Rodriguez Jorge",
    "wof:placetype":"venue"
},
  "geometry": {"coordinates":[2.0100209713,41.5685424805],"type":"Point"}
}