{
  "type": "Feature",
  "properties": {
    "iso:country":"ES",
    "sg:address":"Calle de Almirante Lallemand, 4",
    "sg:city":"Pto. Rosario",
    "sg:orig_category":"Empresas Portuarias",
    "sg:phone":"+34 928 85 51 94",
    "sg:postcode":"35600",
    "sg:province":"Las Palmas",
    "wof:name":"Practicos De Fuerteventura S.l.",
    "wof:placetype":"venue"
},
  "geometry": {"coordinates":[-13.855132103,28.4995746613],"type":"Point"}
}