{
  "type": "Feature",
  "properties": {
    "iso:country":"ES",
    "sg:address":"Calle de Norte, 16",
    "sg:city":"Valencia",
    "sg:orig_category":"Comercio De Piezas De Recambio Y De Accesorios De Veh\u00cdculos, Veh\u00cdculos Industriales",
    "sg:phone":"+34 963 84 41 45",
    "sg:postcode":"46008",
    "sg:province":"Valencia",
    "wof:name":"Recambios Tresautos S.l.",
    "wof:placetype":"venue"
},
  "geometry": {"coordinates":[-0.3908439875,39.4757423401],"type":"Point"}
}