{
  "type": "Feature",
  "properties": {
    "addr:full":"Calle de Lopez Gomez, 22 Valladolid Valladolid 47002",
    "addr:housenumber":"22",
    "addr:postcode":"47002",
    "addr:street":"Calle De Lopez Gomez",
    "iso:country":"ES",
    "sg:address":"Calle de Lopez Gomez, 22",
    "sg:city":"Valladolid",
    "sg:orig_category":"Asesor\u00cda Sobre Comunicaci\u00d3n De Empresas",
    "sg:phone":"+34 983 21 02 93",
    "sg:postcode":"47002",
    "sg:province":"Valladolid",
    "wof:name":"Garcia Ferreiro Elisa Maria",
    "wof:placetype":"venue"
},
  "geometry": {"coordinates":[-4.7230272293,41.6507911682],"type":"Point"}
}