{
  "type": "Feature",
  "properties": {
    "iso:country":"ES",
    "sg:address":"Av. San Ignacio, 5",
    "sg:city":"Iru\u00f1a",
    "sg:orig_category":"Asesor\u00cda De Formaci\u00d3n Y Gesti\u00d3n De Personal",
    "sg:phone":"+34 948 22 46 95",
    "sg:postcode":"31002",
    "sg:province":"Navarra",
    "wof:name":"Gonzalez Correro Pablo",
    "wof:placetype":"venue"
},
  "geometry": {"coordinates":[-1.6428710222,42.8143501282],"type":"Point"}
}