{
  "type": "Feature",
  "properties": {
    "iso:country":"ES",
    "sg:address":"Calle de Quijote (don), 17",
    "sg:city":"Socuellamos",
    "sg:orig_category":"Muebles, Minoristas",
    "sg:phone":"+34 926 53 07 92",
    "sg:postcode":"13630",
    "sg:province":"Ciudad Real",
    "wof:name":"Modeluba S. A.",
    "wof:placetype":"venue"
},
  "geometry": {"coordinates":[-2.7901740074,39.2868919373],"type":"Point"}
}