{
  "type": "Feature",
  "properties": {
    "iso:country":"ES",
    "sg:address":"Calle de Rafael Sanchez Ferlosio, 9",
    "sg:city":"San Fernando De Henares",
    "sg:orig_category":"Panader\u00cdas, Panader\u00cdas",
    "sg:phone":"+34 916 73 77 32",
    "sg:postcode":"28830",
    "sg:province":"Madrid",
    "wof:name":"Pastelerias Pantoja Toro S.l.",
    "wof:placetype":"venue"
},
  "geometry": {"coordinates":[-3.5263888836,40.4273796082],"type":"Point"}
}