{
  "type": "Feature",
  "properties": {
    "iso:country":"ES",
    "sg:address":"Calle de Augusto Bebel, 3",
    "sg:city":"Zaragoza",
    "sg:orig_category":"Peluqueros: De Se\u00d1oras",
    "sg:phone":"+34 976 52 43 11",
    "sg:postcode":"50015",
    "sg:province":"Zaragoza",
    "wof:name":"Aliana S.c.",
    "wof:placetype":"venue"
},
  "geometry": {"coordinates":[-0.8783326745,41.6721572876],"type":"Point"}
}