{
  "type": "Feature",
  "properties": {
    "addr:full":"Calle de Herreria (la), 3 Biota Zaragoza 50695",
    "addr:housenumber":"3",
    "addr:postcode":"50695",
    "addr:street":"Calle De Herreria La",
    "iso:country":"ES",
    "sg:address":"Calle de Herreria (la), 3",
    "sg:city":"Biota",
    "sg:orig_category":"Centros Empresariales",
    "sg:phone":"+34 976 67 00 51",
    "sg:postcode":"50695",
    "sg:province":"Zaragoza",
    "wof:name":"Comunidad De Regantes N-8",
    "wof:placetype":"venue"
},
  "geometry": {"coordinates":[-1.1870650053,42.2621994019],"type":"Point"}
}