{
  "type": "Feature",
  "properties": {
    "addr:full":"Lousada, S/n Lousada Lugo 27185",
    "addr:housenumber":"s / n",
    "addr:postcode":"27185",
    "addr:street":"Lousada",
    "iso:country":"ES",
    "sg:address":"Lousada, S/n",
    "sg:city":"Lousada",
    "sg:orig_category":"Farmacias",
    "sg:phone":"+34 982 20 82 32",
    "sg:postcode":"27185",
    "sg:province":"Lugo",
    "wof:name":"Pedrouzo Devesa Carmen",
    "wof:placetype":"venue"
},
  "geometry": {"coordinates":[-7.5844402313,42.8936576843],"type":"Point"}
}