{
  "type": "Feature",
  "properties": {
    "iso:country":"ES",
    "sg:address":"Calle de Arroyuelo, 2",
    "sg:city":"Estepona",
    "sg:orig_category":"Fabricaci\u00d3n De Art\u00cdculos Y Equipos Deportivos Y De Ocio",
    "sg:phone":"+34 952 92 30 50",
    "sg:postcode":"29680",
    "sg:province":"M\u00e1laga",
    "wof:name":"Sociedad Deportiva Oteros S.l.",
    "wof:placetype":"venue"
},
  "geometry": {"coordinates":[-5.1406188011,36.4273910522],"type":"Point"}
}