{
  "type": "Feature",
  "properties": {
    "iso:country":"ES",
    "sg:address":"Carr Gran Bretanya, 7",
    "sg:city":"Igualada",
    "sg:orig_category":"Construcci\u00d3n Mec\u00c1nica",
    "sg:phone":"+34 938 04 40 52",
    "sg:postcode":"08700",
    "sg:province":"Barcelona",
    "wof:name":"Construcciones Mecanicas Tecnopel S.l.",
    "wof:placetype":"venue"
},
  "geometry": {"coordinates":[1.6250430346,41.5904502869],"type":"Point"}
}