{
  "type": "Feature",
  "properties": {
    "addr:full":"Calle de Parritas, 7 Villafranca De Los Barros Badajoz 06220",
    "addr:housenumber":"7",
    "addr:postcode":"06220",
    "addr:street":"Calle De Parritas",
    "iso:country":"ES",
    "sg:address":"Calle de Parritas, 7",
    "sg:city":"Villafranca De Los Barros",
    "sg:orig_category":"Inmobiliaria (agencias)",
    "sg:phone":"+34 924 52 49 96",
    "sg:postcode":"06220",
    "sg:province":"Badajoz",
    "wof:name":"Hernandez Cabrera Jose",
    "wof:placetype":"venue"
},
  "geometry": {"coordinates":[-6.3419370651,38.5622634888],"type":"Point"}
}