{
  "type": "Feature",
  "properties": {
    "addr:full":"Avda Los Rosales, Km. 0004,1 Madrid Madrid 28021",
    "addr:postcode":"28021",
    "addr:street":"Avda Los Rosales Km. 0004,1",
    "iso:country":"ES",
    "sg:address":"Avda Los Rosales, Km. 0004,1",
    "sg:city":"Madrid",
    "sg:orig_category":"Autob\u00das (explotaci\u00d3n Y Servicios De)",
    "sg:phone":"+34 917 95 15 01",
    "sg:postcode":"28021",
    "sg:province":"Madrid",
    "wof:name":"Autotransportes El Centro S.a.",
    "wof:placetype":"venue"
},
  "geometry": {"coordinates":[-3.6950275898,40.369052887],"type":"Point"}
}