{
  "type": "Feature",
  "properties": {
    "iso:country":"ES",
    "sg:address":"Calle de Cristo De La Epidemia, 20",
    "sg:city":"Malaga",
    "sg:orig_category":"Papeler\u00cdas, Librer\u00cdas",
    "sg:phone":"+34 952 26 76 09",
    "sg:postcode":"29013",
    "sg:province":"M\u00e1laga",
    "wof:name":"Palop Cayuela Juan Tomas",
    "wof:placetype":"venue"
},
  "geometry": {"coordinates":[-4.4143080711,36.7279624939],"type":"Point"}
}