{
  "type": "Feature",
  "properties": {
    "iso:country":"ES",
    "sg:address":"Calle de Silvestre Ochoa, 9",
    "sg:city":"Castro Urdiales",
    "sg:orig_category":"Bibliotecas, Mediatecas",
    "sg:phone":"+34 942 86 81 61",
    "sg:postcode":"39700",
    "sg:province":"Cantabria",
    "wof:name":"Servicios De Informacion Y Documentacion",
    "wof:placetype":"venue"
},
  "geometry": {"coordinates":[-3.2241740227,43.384098053],"type":"Point"}
}