{
  "type": "Feature",
  "properties": {
    "addr:full":"Calle de Santa Maria Magdalena, 13 Madrid Madrid 28016",
    "addr:housenumber":"13",
    "addr:postcode":"madrid;28016",
    "addr:street":"Calle De Santa;Magdalena",
    "iso:country":"ES",
    "sg:address":"Calle de Santa Maria Magdalena, 13",
    "sg:city":"Madrid",
    "sg:orig_category":"Abogados",
    "sg:phone":"+34 913 45 24 11",
    "sg:postcode":"28016",
    "sg:province":"Madrid",
    "wof:name":"Sanchez Periba\u00f1ez Juan Carlos",
    "wof:placetype":"venue"
},
  "geometry": {"coordinates":[-3.6710340977,40.463596344],"type":"Point"}
}