{
  "type": "Feature",
  "properties": {
    "iso:country":"ES",
    "sg:address":"Calle de Ancha, 26",
    "sg:city":"Andujar",
    "sg:orig_category":"Negocio De Materiales De Construcci\u00d3n",
    "sg:phone":"+34 953 50 14 42",
    "sg:postcode":"23740",
    "sg:province":"Ja\u00e9n",
    "wof:name":"Luissares Sl",
    "wof:placetype":"venue"
},
  "geometry": {"coordinates":[-4.0605406761,38.0424804688],"type":"Point"}
}