{
  "type": "Feature",
  "properties": {
    "addr:full":"Fondo De Vila, S/n Fondo De Vila Lugo 27637",
    "addr:housenumber":"s / n",
    "addr:postcode":"27637",
    "iso:country":"ES",
    "sg:address":"Fondo De Vila, S/n",
    "sg:city":"Fondo De Vila",
    "sg:orig_category":"Producci\u00d3n, Venta De Productos De Agricultura Biol\u00d3gica",
    "sg:phone":"+34 982 54 67 32",
    "sg:postcode":"27637",
    "sg:province":"Lugo",
    "wof:name":"Cooperativa Gandeira Da Pena S.c.l.",
    "wof:placetype":"venue"
},
  "geometry": {"coordinates":[-7.382338047,42.7135887146],"type":"Point"}
}