{
  "type": "Feature",
  "properties": {
    "iso:country":"ES",
    "sg:address":"Pardellas, Km. 6100,0",
    "sg:city":"Mos",
    "sg:orig_category":"Distribuci\u00d3n De Petr\u00d3leo Y Derivados",
    "sg:phone":"+34 986 33 80 05",
    "sg:postcode":"36311",
    "sg:province":"Pontevedra",
    "wof:name":"Estacion De Servicio Sertuy",
    "wof:placetype":"venue"
},
  "geometry": {"coordinates":[-8.6681194305,42.1661491394],"type":"Point"}
}