{
  "type": "Feature",
  "properties": {
    "addr:full":"Av Principe Felipe De Borbon, Km. 0158,2 Las Pedro\u00f1eras Cuenca 16660",
    "addr:postcode":"16660",
    "addr:street":"Av Principe Felipe De Borbon Km. 0158,2 Las",
    "iso:country":"ES",
    "sg:address":"Av Principe Felipe De Borbon, Km. 0158,2",
    "sg:city":"Las Pedro\u00f1eras",
    "sg:orig_category":"Mec\u00c1nico Del Autom\u00d3vil",
    "sg:phone":"+34 967 16 05 13",
    "sg:postcode":"16660",
    "sg:province":"Cuenca",
    "wof:name":"Talleres Bacete S.l.",
    "wof:placetype":"venue"
},
  "geometry": {"coordinates":[-2.676858902,39.4508552551],"type":"Point"}
}