{
  "type": "Feature",
  "properties": {
    "addr:full":"Avda Galicia De, 10 Oviedo Asturias 33005",
    "addr:housenumber":"10",
    "addr:postcode":"33005",
    "addr:street":"Avda Galicia De",
    "iso:country":"ES",
    "sg:address":"Avda Galicia De, 10",
    "sg:city":"Oviedo",
    "sg:orig_category":"Radiocomunicaciones, Telefon\u00cda M\u00d3vil, Radiomensajer\u00cda: Servicios, Comercializaci\u00d3n",
    "sg:phone":"+34 985 96 62 87",
    "sg:postcode":"33005",
    "sg:province":"Asturias",
    "wof:name":"Print Celular S.l.",
    "wof:placetype":"venue"
},
  "geometry": {"coordinates":[-5.8546757698,43.3614654541],"type":"Point"}
}