{
  "type": "Feature",
  "properties": {
    "iso:country":"ES",
    "sg:address":"Calle de Jose Ramirez, 1",
    "sg:city":"Cartuja Baja",
    "sg:orig_category":"Reductores De Velocidad",
    "sg:phone":"+34 976 45 48 07",
    "sg:postcode":"50720",
    "sg:province":"Zaragoza",
    "wof:name":"Sm-cyclo Iberia S.l.unipersonal",
    "wof:placetype":"venue"
},
  "geometry": {"coordinates":[-0.8236089945,41.602935791],"type":"Point"}
}