{
  "type": "Feature",
  "properties": {
    "iso:country":"ES",
    "sg:address":"Kaletxiki, 1",
    "sg:city":"Andoain",
    "sg:orig_category":"Empresas De Carpinter\u00cda De Madera",
    "sg:phone":"+34 943 59 01 04",
    "sg:postcode":"20140",
    "sg:province":"Guip\u00f9zcoa",
    "wof:name":"Irulegui Atorrasagasti Pablo",
    "wof:placetype":"venue"
},
  "geometry": {"coordinates":[-2.0196139812,43.220085144],"type":"Point"}
}