{
  "type": "Feature",
  "properties": {
    "addr:full":"Avda Hermanos Menendez Pidal, 8 Oviedo Asturias 33005",
    "addr:housenumber":"8",
    "addr:postcode":"33005",
    "addr:street":"Avda Hermanos Menendez Pidal",
    "iso:country":"ES",
    "sg:address":"Avda Hermanos Menendez Pidal, 8",
    "sg:city":"Oviedo",
    "sg:orig_category":"Ingeniero",
    "sg:phone":"+34 985 24 41 72",
    "sg:postcode":"33005",
    "sg:province":"Asturias",
    "wof:name":"Rodriguez Antu\u00f1a Jesus Amancio",
    "wof:placetype":"venue"
},
  "geometry": {"coordinates":[-5.8569831848,43.3574333191],"type":"Point"}
}