{
  "type": "Feature",
  "properties": {
    "iso:country":"ES",
    "sg:address":"Calle de Casta\u00d1os, 6",
    "sg:city":"Bilbao",
    "sg:orig_category":"Supermercados Y Hipermercados",
    "sg:phone":"+34 944 13 10 12",
    "sg:postcode":"48007",
    "sg:province":"Vizcaya",
    "wof:name":"Uvescaya S.l.",
    "wof:placetype":"venue"
},
  "geometry": {"coordinates":[-2.9254829884,43.2676887512],"type":"Point"}
}