{
  "type": "Feature",
  "properties": {
    "addr:full":"Calle de Yeso (del), S/n Arganda Madrid 28500",
    "addr:housenumber":"/ n",
    "addr:postcode":"28500",
    "addr:street":"Calle De Yeso Del S",
    "iso:country":"ES",
    "sg:address":"Calle de Yeso (del), S/n",
    "sg:city":"Arganda",
    "sg:orig_category":"Mataderos: Material E Instalaciones",
    "sg:phone":"+34 918 71 53 07",
    "sg:postcode":"28500",
    "sg:province":"Madrid",
    "wof:name":"Proco S. A.",
    "wof:placetype":"venue"
},
  "geometry": {"coordinates":[-3.4566349983,40.3019638062],"type":"Point"}
}