{
  "type": "Feature",
  "properties": {
    "iso:country":"ES",
    "sg:address":"Carrer de Valencia, 457",
    "sg:city":"Barcelona",
    "sg:orig_category":"Panader\u00cdas, Pasteler\u00cdas, Boller\u00cda Industriale (fabricaci\u00d3n, Al Por Mayor)",
    "sg:phone":"+34 932 31 64 31",
    "sg:postcode":"08013",
    "sg:province":"Barcelona",
    "wof:name":"2-u.a.t. S.l.",
    "wof:placetype":"venue"
},
  "geometry": {"coordinates":[2.177445,41.403339],"type":"Point"}
}