{
  "type": "Feature",
  "properties": {
    "addr:full":"Calle de Marques De Leis, 15 Madrid Madrid 28020",
    "addr:housenumber":"15",
    "addr:postcode":"madrid;28020",
    "addr:street":"Calle De Marques De Leis",
    "iso:country":"ES",
    "sg:address":"Calle de Marques De Leis, 15",
    "sg:city":"Madrid",
    "sg:orig_category":"Radiocomunicaciones, Telefon\u00cda M\u00d3vil, Radiomensajer\u00cda: Servicios, Comercializaci\u00d3n",
    "sg:phone":"+34 915 71 75 55",
    "sg:postcode":"28020",
    "sg:province":"Madrid",
    "wof:name":"France Telecom Espa\u00d1a S.a.",
    "wof:placetype":"venue"
},
  "geometry": {"coordinates":[-3.6993060112,40.4576950073],"type":"Point"}
}