{
  "type": "Feature",
  "properties": {
    "iso:country":"ES",
    "sg:address":"Carr Merce Rodoreda I Gurgui, 2",
    "sg:city":"Girona",
    "sg:orig_category":"Alquiler De Casas Y Habitaciones Amuebladas",
    "sg:phone":"+34 972 58 82 00",
    "sg:postcode":"17...",
    "sg:province":"Girona",
    "wof:name":"Siresa Gironina S.a.",
    "wof:placetype":"venue"
},
  "geometry": {"coordinates":[2.8187448978,41.9808616638],"type":"Point"}
}