{
  "type": "Feature",
  "properties": {
    "iso:country":"ES",
    "sg:address":"Calle de Marcelino Suarez, 16",
    "sg:city":"Oviedo",
    "sg:orig_category":"Perfumer\u00cda (al Por Menor)",
    "sg:phone":"+34 985 25 11 52",
    "sg:postcode":"33012",
    "sg:province":"Asturias",
    "wof:name":"Garcia Vazquez Josefina",
    "wof:placetype":"venue"
},
  "geometry": {"coordinates":[-5.8621912003,43.3639411926],"type":"Point"}
}