{
  "type": "Feature",
  "properties": {
    "iso:country":"ES",
    "sg:address":"Rond San Francisco (de), S/n",
    "sg:city":"Lucena",
    "sg:classifiers":[
        {
            "category":"Cinema",
            "subcategory":"Movie Theater",
            "type":"Entertainment"
        }
    ],
    "sg:phone":"+34 957 50 23 69",
    "sg:postcode":"14900",
    "sg:province":"C\u00f3rdoba",
    "sg:tags":[
        "salas",
        "de",
        "cine"
    ],
    "wof:name":"Gestion Cinematografica S.l.",
    "wof:placetype":"venue"
},
  "geometry": {"coordinates":[-4.4873490334,37.4135398865],"type":"Point"}
}