{
  "type": "Feature",
  "properties": {
    "iso:country":"ES",
    "sg:address":"Calle de Rui Perez, 16",
    "sg:city":"Aviles",
    "sg:orig_category":"Ense\u00d1anza Variada",
    "sg:phone":"+34 985 52 18 18",
    "sg:postcode":"33402",
    "sg:province":"Asturias",
    "wof:name":"Escadem Centro De Formacion Profesional S.l.u.",
    "wof:placetype":"venue"
},
  "geometry": {"coordinates":[-5.9232239723,43.5580406189],"type":"Point"}
}