{
  "type": "Feature",
  "properties": {
    "addr:full":"Calle de Veinte Metros, 34 Valladolid Valladolid 47005",
    "addr:housenumber":"34",
    "addr:postcode":"47005",
    "addr:street":"Calle De Veinte Metros",
    "iso:country":"ES",
    "sg:address":"Calle de Veinte Metros, 34",
    "sg:city":"Valladolid",
    "sg:orig_category":"Molduras, Junquillos, Listones Y Molduras Perforadas",
    "sg:phone":"+34 983 39 00 01",
    "sg:postcode":"47005",
    "sg:province":"Valladolid",
    "wof:name":"Bermejo  Leonardo",
    "wof:placetype":"venue"
},
  "geometry": {"coordinates":[-4.7145571709,41.6492385864],"type":"Point"}
}