{
  "type": "Feature",
  "properties": {
    "iso:country":"ES",
    "sg:address":"Calle de San Antonio, 5",
    "sg:city":"Alcala De Los Gazules",
    "sg:classifiers":[
        {
            "category":"Taxi",
            "type":"Transportation"
        }
    ],
    "sg:phone":"+34 956 41 32 56",
    "sg:postcode":"11180",
    "sg:province":"C\u00e1diz",
    "wof:name":"Delgado Fernandez Pedro Jesus",
    "wof:placetype":"venue"
},
  "geometry": {"coordinates":[-5.7280139923,36.4614257812],"type":"Point"}
}