{
  "type": "Feature",
  "properties": {
    "addr:full":"Calle de Camoens, 5 Ceuta Ceuta 51001",
    "addr:housenumber":"5",
    "addr:postcode":"51001",
    "addr:street":"Calle De Camoens",
    "iso:country":"ES",
    "sg:address":"Calle de Camoens, 5",
    "sg:city":"Ceuta",
    "sg:orig_category":"Caf\u00c9s, Bares, Cervecer\u00cdas",
    "sg:phone":"+34 956 51 06 27",
    "sg:postcode":"51001",
    "sg:province":"Ceuta",
    "wof:name":"Casta\u00f1o Chacon Javier",
    "wof:placetype":"venue"
},
  "geometry": {"coordinates":[-5.309135437,35.8873443604],"type":"Point"}
}