{
  "type": "Feature",
  "properties": {
    "addr:full":"Calle de Musico Ziryab, 7 Cordoba C\u00f3rdoba 14005",
    "addr:housenumber":"7",
    "addr:postcode":"14005",
    "addr:street":"Calle De Musico Ziryab;Co\u0301Rdoba",
    "iso:country":"ES",
    "sg:address":"Calle de Musico Ziryab, 7",
    "sg:city":"Cordoba",
    "sg:orig_category":"Asesor\u00cda Sobre Comunicaci\u00d3n De Empresas",
    "sg:phone":"+34 957 45 48 59",
    "sg:postcode":"14005",
    "sg:province":"C\u00f3rdoba",
    "wof:name":"Asesoria De Empresarios-asemco S.l.",
    "wof:placetype":"venue"
},
  "geometry": {"coordinates":[-4.7919888496,37.8861846924],"type":"Point"}
}