{
  "type": "Feature",
  "properties": {
    "iso:country":"ES",
    "sg:address":"Calle de Posada, 1",
    "sg:city":"Villanueva Del Rosario",
    "sg:orig_category":"Ropa Para Se\u00d1oras Y Caballeros (al Por Menor)",
    "sg:phone":"+34 952 74 20 30",
    "sg:postcode":"29312",
    "sg:province":"M\u00e1laga",
    "wof:name":"Navas Paneque Cristobal Luis",
    "wof:placetype":"venue"
},
  "geometry": {"coordinates":[-4.3640780449,36.9964370728],"type":"Point"}
}