{
  "type": "Feature",
  "properties": {
    "iso:country":"ES",
    "sg:address":"Calle de Saucillo, 46",
    "sg:city":"Palmas De Gran Canaria",
    "sg:orig_category":"Arquitectos",
    "sg:phone":"+34 928 46 32 52",
    "sg:postcode":"35009",
    "sg:province":"Las Palmas",
    "wof:name":"Fumero Ortega Ulises Antonio",
    "wof:placetype":"venue"
},
  "geometry": {"coordinates":[-15.4274072647,28.1511478424],"type":"Point"}
}