{
  "type": "Feature",
  "properties": {
    "iso:country":"ES",
    "sg:address":"Pol. Ind. La Pobla, S/n",
    "sg:city":"Suria",
    "sg:orig_category":"Comercio De Piezas De Recambio Y De Accesorios De Veh\u00cdculos, Veh\u00cdculos Industriales",
    "sg:phone":"+34 938 68 22 45",
    "sg:postcode":"08260",
    "sg:province":"Barcelona",
    "wof:name":"Unio Part Components S.a.",
    "wof:placetype":"venue"
},
  "geometry": {"coordinates":[1.7505300045,41.8316688538],"type":"Point"}
}