{
  "type": "Feature",
  "properties": {
    "addr:full":"Rua Lodeiro, 6 Viveiro Lugo 27850",
    "addr:housenumber":"6",
    "addr:postcode":"27850",
    "addr:street":"Rua Lodeiro",
    "iso:country":"ES",
    "sg:address":"Rua Lodeiro, 6",
    "sg:city":"Viveiro",
    "sg:orig_category":"Asesor\u00cda Fiscal Y Jur\u00cddica",
    "sg:phone":"+34 982 57 03 13",
    "sg:postcode":"27850",
    "sg:province":"Lugo",
    "wof:name":"Diaz Garcia Jose Manuel",
    "wof:placetype":"venue"
},
  "geometry": {"coordinates":[-7.5928001404,43.6678848267],"type":"Point"}
}