{
  "type": "Feature",
  "properties": {
    "iso:country":"ES",
    "sg:address":"Rua Diputacion, 9",
    "sg:city":"Verin",
    "sg:orig_category":"Centros Empresariales",
    "sg:phone":"+34 988 41 43 88",
    "sg:postcode":"32600",
    "sg:province":"Ourense",
    "wof:name":"Vispo Perez Jaime",
    "wof:placetype":"venue"
},
  "geometry": {"coordinates":[-7.4351911545,41.9384536743],"type":"Point"}
}