{
  "type": "Feature",
  "properties": {
    "addr:full":"Calle de Cruz Verde, 10 Santa Cruz De Tenerife Santa Cruz De Tenerife 38003",
    "addr:housenumber":"10",
    "addr:postcode":"38003",
    "addr:street":"Calle De Cruz Verde",
    "iso:country":"ES",
    "sg:address":"Calle de Cruz Verde, 10",
    "sg:city":"Santa Cruz De Tenerife",
    "sg:orig_category":"Administradores De Bienes Y Delegados De Comunidades De Propietarios",
    "sg:phone":"+34 922 24 52 21",
    "sg:postcode":"38003",
    "sg:province":"Santa Cruz De Tenerife",
    "wof:name":"Rodriguez Ravelo Juana Maria Antonia",
    "wof:placetype":"venue"
},
  "geometry": {"coordinates":[-16.2492351532,28.4656944275],"type":"Point"}
}