{
  "type": "Feature",
  "properties": {
    "addr:full":"Calle de Grecia, 5 Barriada Virgen De La Caridad Murcia 30203",
    "addr:housenumber":"5",
    "addr:postcode":"30203",
    "addr:street":"Calle De Grecia;Barriada Virgen De",
    "iso:country":"ES",
    "sg:address":"Calle de Grecia, 5",
    "sg:city":"Barriada Virgen De La Caridad",
    "sg:classifiers":[
        {
            "category":"Autos & Motor Vehicles",
            "subcategory":"Automobile Sales",
            "type":"Retail Goods"
        }
    ],
    "sg:phone":"+34 968 52 28 50",
    "sg:postcode":"30203",
    "sg:province":"Murcia",
    "wof:name":"Antonio Lopez Pe\u00d1alber C.b.",
    "wof:placetype":"venue"
},
  "geometry": {"coordinates":[-1.1298867464,37.9834747314],"type":"Point"}
}