{
  "type": "Feature",
  "properties": {
    "addr:full":"Carr Sans I Ribes, 1 Lleida Lleida 25006",
    "addr:housenumber":"1",
    "addr:postcode":"25006",
    "addr:street":"Carr Sans I Ribes",
    "iso:country":"ES",
    "sg:address":"Carr Sans I Ribes, 1",
    "sg:city":"Lleida",
    "sg:orig_category":"Abogados",
    "sg:phone":"+34 973 22 46 68",
    "sg:postcode":"25006",
    "sg:province":"Lleida",
    "wof:name":"Grup Juridic Comptable S.l.",
    "wof:placetype":"venue"
},
  "geometry": {"coordinates":[0.6202850938,41.619644165],"type":"Point"}
}