{
  "type": "Feature",
  "properties": {
    "iso:country":"ES",
    "sg:address":"Calle de Arcediano, 2",
    "sg:city":"Plasencia",
    "sg:orig_category":"Cester\u00cda (fabricaci\u00d3n)",
    "sg:phone":"+34 927 41 28 88",
    "sg:postcode":"10600",
    "sg:province":"C\u00e1ceres",
    "wof:name":"Alcon Bejarano Jose Luis",
    "wof:placetype":"venue"
},
  "geometry": {"coordinates":[-6.0879998207,40.0301818848],"type":"Point"}
}