{
  "type": "Feature",
  "properties": {
    "iso:country":"ES",
    "sg:address":"Calle de Padre Pascual Suarez, 25",
    "sg:city":"Albacete",
    "sg:orig_category":"Promotores Constructores",
    "sg:phone":"+34 967 52 24 42",
    "sg:postcode":"02002",
    "sg:province":"Albacete",
    "wof:name":"Promociones Y Construcciones Simcabal S.l.",
    "wof:placetype":"venue"
},
  "geometry": {"coordinates":[-1.852565527,38.9875030518],"type":"Point"}
}