{
  "type": "Feature",
  "properties": {
    "iso:country":"ES",
    "sg:address":"Calle de Espiritu Santo, 26",
    "sg:city":"Madrid",
    "sg:orig_category":"Papeler\u00cdas: Art\u00cdculos (al Por Mayor)",
    "sg:phone":"+34 915 31 42 82",
    "sg:postcode":"28004",
    "sg:province":"Madrid",
    "wof:name":"Vallecillo Crespo Pilar",
    "wof:placetype":"venue"
},
  "geometry": {"coordinates":[-3.7036380768,40.4253883362],"type":"Point"}
}