{
  "type": "Feature",
  "properties": {
    "iso:country":"ES",
    "sg:address":"Avda Pintor Felo Monzon, S/n",
    "sg:city":"Palmas De Gran Canaria",
    "sg:orig_category":"Ropa Para Se\u00d1oras Y Caballeros (al Por Menor)",
    "sg:phone":"+34 928 41 52 83",
    "sg:postcode":"35019",
    "sg:province":"Las Palmas",
    "sg:website":"www.cortefiel.com",
    "wof:name":"Cortefiel S.a.",
    "wof:placetype":"venue"
},
  "geometry": {"coordinates":[-15.4527931213,28.1041984558],"type":"Point"}
}