{
  "type": "Feature",
  "properties": {
    "iso:country":"ES",
    "sg:address":"Euskalerria Auzunea, 34",
    "sg:city":"Azpeitia",
    "sg:orig_category":"T\u00c9cnicos Veterinarios",
    "sg:phone":"+34 943 15 16 40",
    "sg:postcode":"20730",
    "sg:province":"Guip\u00f9zcoa",
    "wof:name":"Javier Martin Urmeneta",
    "wof:placetype":"venue"
},
  "geometry": {"coordinates":[-2.2689859867,43.1789512634],"type":"Point"}
}