{
  "type": "Feature",
  "properties": {
    "addr:full":"Calle de Real, 12 Viso Del Alcor Sevilla 41520",
    "addr:housenumber":"12",
    "addr:postcode":"41520",
    "addr:street":"Calle De Real",
    "iso:country":"ES",
    "sg:address":"Calle de Real, 12",
    "sg:city":"Viso Del Alcor",
    "sg:orig_category":"Procuradores",
    "sg:phone":"+34 955 94 54 00",
    "sg:postcode":"41520",
    "sg:province":"Sevilla",
    "wof:name":"Lopez Diaz Diego",
    "wof:placetype":"venue"
},
  "geometry": {"coordinates":[-5.7207508087,37.3873252869],"type":"Point"}
}