{
  "type": "Feature",
  "properties": {
    "iso:country":"ES",
    "sg:address":"Carrer de Juan De Garay, 40",
    "sg:city":"Barcelona",
    "sg:orig_category":"Agentes, Concesionarios Y Sucursales De Veh\u00cdculos",
    "sg:phone":"+34 933 40 80 66",
    "sg:postcode":"08027",
    "sg:province":"Barcelona",
    "wof:name":"Seugas S. A.",
    "wof:placetype":"venue"
},
  "geometry": {"coordinates":[2.1825809479,41.4189033508],"type":"Point"}
}