{
  "type": "Feature",
  "properties": {
    "addr:full":"Avda Catalu\u00f1a P I El Pilar, 179 Zaragoza Zaragoza 50014",
    "addr:housenumber":"179",
    "addr:postcode":"50014",
    "addr:street":"Avda Catalun\u0303A P;El Pilar",
    "iso:country":"ES",
    "sg:address":"Avda Catalu\u00f1a P I El Pilar, 179",
    "sg:city":"Zaragoza",
    "sg:orig_category":"Transportes Por V\u00cdas Navegables",
    "sg:phone":"+34 976 47 09 36",
    "sg:postcode":"50014",
    "sg:province":"Zaragoza",
    "wof:name":"Garmon Serrano Cesar",
    "wof:placetype":"venue"
},
  "geometry": {"coordinates":[-1.4628041983,41.7314605713],"type":"Point"}
}