{
  "type": "Feature",
  "properties": {
    "addr:full":"Calle de Escuza Jose Maria, 5 Bilbao Vizcaya 48013",
    "addr:housenumber":"5",
    "addr:postcode":"48013",
    "addr:street":"Calle De Escuza Jose Maria",
    "iso:country":"ES",
    "sg:address":"Calle de Escuza Jose Maria, 5",
    "sg:city":"Bilbao",
    "sg:orig_category":"Peluquer\u00cdas, Peluquer\u00cda Mixta",
    "sg:phone":"+34 944 27 75 77",
    "sg:postcode":"48013",
    "sg:province":"Vizcaya",
    "wof:name":"Garcia Alvarez Antonio Valentin",
    "wof:placetype":"venue"
},
  "geometry": {"coordinates":[-2.9448709488,43.2624588013],"type":"Point"}
}