{
  "type": "Feature",
  "properties": {
    "addr:full":"Avda Blasco Iba\u00d1ez, 17 Valencia Valencia 46010",
    "addr:housenumber":"17",
    "addr:postcode":"46010",
    "addr:street":"Avda Blasco Iban\u0303Ez",
    "iso:country":"ES",
    "sg:address":"Avda Blasco Iba\u00d1ez, 17",
    "sg:city":"Valencia",
    "sg:orig_category":"Organismos De Investigaciones Cient\u00cdficas Y T\u00c9cnicas",
    "sg:phone":"+34 963 61 06 54",
    "sg:postcode":"46010",
    "sg:province":"Valencia",
    "wof:name":"Consejo Superior De Investigaciones Cientificas",
    "wof:placetype":"venue"
},
  "geometry": {"coordinates":[-0.3621180058,39.4786376953],"type":"Point"}
}