{
  "type": "Feature",
  "properties": {
    "iso:country":"ES",
    "sg:address":"Plaz Ayuntamiento, 3",
    "sg:city":"Oliva Frontera",
    "sg:orig_category":"Estancos",
    "sg:phone":"+34 924 74 02 97",
    "sg:postcode":"06120",
    "sg:province":"Badajoz",
    "wof:name":"Lucas Ortega Miguel",
    "wof:placetype":"venue"
},
  "geometry": {"coordinates":[-6.9155139923,38.2829017639],"type":"Point"}
}