{
  "type": "Feature",
  "properties": {
    "iso:country":"ES",
    "sg:address":"Pg Ferrocarrils Catalans, 144",
    "sg:city":"Cornella Llobregat",
    "sg:orig_category":"Transportes Por Carretera: Lotes Completos, Mercanc\u00cdas Diversas",
    "sg:phone":"+34 902 14 45 55",
    "sg:postcode":"08940",
    "sg:province":"Barcelona",
    "wof:name":"Suministros De Alimentacion Etnika S.l.",
    "wof:placetype":"venue"
},
  "geometry": {"coordinates":[2.0809249878,41.3522491455],"type":"Point"}
}