{
  "type": "Feature",
  "properties": {
    "addr:full":"Arenal, S/n Javea Alicante 03730",
    "addr:housenumber":"s / n",
    "addr:postcode":"03730",
    "addr:street":"Arenal",
    "iso:country":"ES",
    "sg:address":"Arenal, S/n",
    "sg:city":"Javea",
    "sg:orig_category":"Persianas Interiores, Exteriores",
    "sg:phone":"+34 965 79 58 01",
    "sg:postcode":"03730",
    "sg:province":"Alicante",
    "wof:name":"Tol2 Javea S.l.",
    "wof:placetype":"venue"
},
  "geometry": {"coordinates":[0.1810149997,38.7689590454],"type":"Point"}
}