{
  "type": "Feature",
  "properties": {
    "iso:country":"ES",
    "sg:address":"Calle de Do\u00d1a Maria Ugarte, 14",
    "sg:city":"Tudela",
    "sg:orig_category":"Centros Empresariales",
    "sg:phone":"+34 948 82 69 91",
    "sg:postcode":"31500",
    "sg:province":"Navarra",
    "wof:name":"Tude Y Riber S.l.",
    "wof:placetype":"venue"
},
  "geometry": {"coordinates":[-1.607303977,42.0603103638],"type":"Point"}
}