{
  "type": "Feature",
  "properties": {
    "addr:full":"Carrer de Piquer, 52 Barcelona Barcelona 08004",
    "addr:housenumber":"52",
    "addr:postcode":"08004",
    "addr:street":"Carrer De Piquer",
    "iso:country":"ES",
    "sg:address":"Carrer de Piquer, 52",
    "sg:city":"Barcelona",
    "sg:orig_category":"Contenedores (mercanc\u00cdas)",
    "sg:phone":"+34 934 41 17 27",
    "sg:postcode":"08004",
    "sg:province":"Barcelona",
    "wof:name":"Casasnovas Morales Antonio",
    "wof:placetype":"venue"
},
  "geometry": {"coordinates":[2.1678059101,41.3737716675],"type":"Point"}
}