{
  "type": "Feature",
  "properties": {
    "addr:full":"Carrer de Lima, 1 Barcelona Barcelona 08030",
    "addr:housenumber":"1",
    "addr:postcode":"08030",
    "addr:street":"Carrer De Lima",
    "iso:country":"ES",
    "sg:address":"Carrer de Lima, 1",
    "sg:city":"Barcelona",
    "sg:orig_category":"Fabricaci\u00d3n De Bordes Y Molduras Para Edificaci\u00d3n Y Decoraci\u00d3n",
    "sg:phone":"+34 933 46 82 68",
    "sg:postcode":"08030",
    "sg:province":"Barcelona",
    "wof:name":"Comercial Moldurera Lozano S. L.",
    "wof:placetype":"venue"
},
  "geometry": {"coordinates":[2.2007610798,41.4394226074],"type":"Point"}
}