{
  "type": "Feature",
  "properties": {
    "addr:full":"Ctra Garrucha, Km. 0002,1 Marinas Almer\u00eda 04620",
    "addr:postcode":"04620",
    "addr:street":"Ctra Garrucha Km. 0002,1 Marinas Almeri\u0301A",
    "iso:country":"ES",
    "sg:address":"Ctra Garrucha, Km. 0002,1",
    "sg:city":"Marinas",
    "sg:orig_category":"Veh\u00cdculos De Ocasi\u00d3n",
    "sg:phone":"+34 950 39 02 47",
    "sg:postcode":"04620",
    "sg:province":"Almer\u00eda",
    "wof:name":"Almeriauto S.a.",
    "wof:placetype":"venue"
},
  "geometry": {"coordinates":[-1.8197183609,37.1877937317],"type":"Point"}
}