{
  "type": "Feature",
  "properties": {
    "addr:full":"Rond Sant Pau, 69 Barcelona Barcelona 08015",
    "addr:housenumber":"69",
    "addr:postcode":"08015",
    "addr:street":"Pau",
    "iso:country":"ES",
    "sg:address":"Rond Sant Pau, 69",
    "sg:city":"Barcelona",
    "sg:orig_category":"Art\u00cdculos De Decoraci\u00d3n",
    "sg:phone":"+34 934 41 00 56",
    "sg:postcode":"08015",
    "sg:province":"Barcelona",
    "wof:name":"Unicort S. A.",
    "wof:placetype":"venue"
},
  "geometry": {"coordinates":[2.1687450409,41.3855895996],"type":"Point"}
}