{
  "type": "Feature",
  "properties": {
    "iso:country":"ES",
    "sg:address":"Calle de Pau Casals, 4",
    "sg:city":"Novelda",
    "sg:orig_category":"M\u00c9dicos: Ginecolog\u00cda Y Obstetricia",
    "sg:phone":"+34 965 60 37 41",
    "sg:postcode":"03660",
    "sg:province":"Alicante",
    "wof:name":"Fagoaga Caridad Rafael",
    "wof:placetype":"venue"
},
  "geometry": {"coordinates":[-0.7681319714,38.3810119629],"type":"Point"}
}