{
  "type": "Feature",
  "properties": {
    "iso:country":"ES",
    "sg:address":"Calle de Carlos Barral, S/n",
    "sg:city":"Talavera Reina",
    "sg:orig_category":"Molduras, Junquillos, Listones Y Molduras Perforadas",
    "sg:phone":"+34 925 81 32 61",
    "sg:postcode":"45600",
    "sg:province":"Toledo",
    "wof:name":"Trujillo Julian Jose Antonio",
    "wof:placetype":"venue"
},
  "geometry": {"coordinates":[-4.8167676926,39.9581108093],"type":"Point"}
}