{
  "type": "Feature",
  "properties": {
    "addr:full":"Avda Lebrija (de), 3 Jerez De La Frontera C\u00e1diz 11407",
    "addr:postcode":"11407",
    "addr:street":"Avda Lebrija De",
    "iso:country":"ES",
    "sg:address":"Avda Lebrija (de), 3",
    "sg:city":"Jerez De La Frontera",
    "sg:orig_category":"Productores Recolectores, Venta Directa De Vinos",
    "sg:phone":"+34 956 31 16 40",
    "sg:postcode":"11407",
    "sg:province":"C\u00e1diz",
    "wof:name":"Hijos De Rainera Perez Marin S. A.",
    "wof:placetype":"venue"
},
  "geometry": {"coordinates":[-6.1311001778,36.7006835938],"type":"Point"}
}