{
  "type": "Feature",
  "properties": {
    "addr:full":"Carrer de Doctor Ferran, 4 S. Celoni Barcelona 08470",
    "addr:housenumber":"4",
    "addr:postcode":"08470",
    "addr:street":"Carrer De Doctor Ferran",
    "iso:country":"ES",
    "sg:address":"Carrer de Doctor Ferran, 4",
    "sg:city":"S. Celoni",
    "sg:orig_category":"Fabricaci\u00d3n De Ventanas",
    "sg:phone":"+34 938 67 57 58",
    "sg:postcode":"08470",
    "sg:province":"Barcelona",
    "wof:name":"Ventana Hermetica Uin2 S.l",
    "wof:placetype":"venue"
},
  "geometry": {"coordinates":[2.4930651188,41.6851387024],"type":"Point"}
}