{
  "type": "Feature",
  "properties": {
    "addr:full":"Carrer de Bonaventura Castellet, 2 Terrassa Barcelona 08222",
    "addr:housenumber":"2",
    "addr:postcode":"08222",
    "addr:street":"Carrer De Bonaventura Castellet",
    "iso:country":"ES",
    "sg:address":"Carrer de Bonaventura Castellet, 2",
    "sg:city":"Terrassa",
    "sg:orig_category":"Artes Gr\u00c1ficas, Artes Pl\u00c1sticas (curso)",
    "sg:phone":"+34 937 83 97 22",
    "sg:postcode":"08222",
    "sg:province":"Barcelona",
    "wof:name":"Graficas Herfo S.l.l.",
    "wof:placetype":"venue"
},
  "geometry": {"coordinates":[2.0185120106,41.5692939758],"type":"Point"}
}