{
  "type": "Feature",
  "properties": {
    "iso:country":"ES",
    "sg:address":"Rua San Pedro (de), 34",
    "sg:city":"Santiago De Compostela",
    "sg:orig_category":"Molduras, Junquillos, Listones Y Molduras Perforadas",
    "sg:phone":"+34 981 56 23 52",
    "sg:postcode":"15703",
    "sg:province":"La Coru\u00f1a",
    "wof:name":"Lopez Asorey Ismael",
    "wof:placetype":"venue"
},
  "geometry": {"coordinates":[-8.5388355255,42.8813743591],"type":"Point"}
}