{
  "type": "Feature",
  "properties": {
    "iso:country":"ES",
    "sg:address":"Calle de Andalucia, 15",
    "sg:city":"Campillo",
    "sg:orig_category":"Agentes Generales De Seguros",
    "sg:phone":"+34 959 58 82 20",
    "sg:postcode":"21650",
    "sg:province":"Huelva",
    "wof:name":"Carrillo Marin Juana",
    "wof:placetype":"venue"
},
  "geometry": {"coordinates":[-6.6258606911,37.693195343],"type":"Point"}
}