{
  "type": "Feature",
  "properties": {
    "addr:full":"C/ Jose Maria Peman, 20 Elche Alicante 03201",
    "addr:housenumber":"20",
    "addr:postcode":"03201",
    "addr:street":"C / Jose Maria Peman",
    "iso:country":"ES",
    "sg:address":"C/ Jose Maria Peman, 20",
    "sg:city":"Elche",
    "sg:orig_category":"Colchones (fabricaci\u00d3n, Al Por Mayor, Al Por Menor)",
    "sg:phone":"+34 965 46 40 00",
    "sg:postcode":"03201",
    "sg:province":"Alicante",
    "wof:name":"Gandia Sanchez Blas",
    "wof:placetype":"venue"
},
  "geometry": {"coordinates":[-0.704020977,38.2644844055],"type":"Point"}
}