{
  "type": "Feature",
  "properties": {
    "addr:full":"Calle de Ametzaga\u00d1a, 43 Donostia-san Sebastian Guip\u00f9zcoa 20012",
    "addr:housenumber":"43",
    "addr:postcode":"20012",
    "addr:street":"Calle De Ametzagan\u0303A",
    "iso:country":"ES",
    "sg:address":"Calle de Ametzaga\u00d1a, 43",
    "sg:city":"Donostia-san Sebastian",
    "sg:orig_category":"Carnicer\u00cdas, Carnicer\u00cdas",
    "sg:phone":"+34 943 28 80 04",
    "sg:postcode":"20012",
    "sg:province":"Guip\u00f9zcoa",
    "wof:name":"Alfonso Garcia Jose Ramon",
    "wof:placetype":"venue"
},
  "geometry": {"coordinates":[-1.9680960178,43.3175392151],"type":"Point"}
}