{
  "type": "Feature",
  "properties": {
    "iso:country":"ES",
    "sg:address":"Ctra Haro, 26",
    "sg:city":"Belorado",
    "sg:orig_category":"Electrodom\u00c9sticos (al Por Menor)",
    "sg:phone":"+34 947 58 04 02",
    "sg:postcode":"09250",
    "sg:province":"Burgos",
    "wof:name":"Blanco Fernandez Luis",
    "wof:placetype":"venue"
},
  "geometry": {"coordinates":[-3.1921889782,42.4212265015],"type":"Point"}
}