{
  "type": "Feature",
  "properties": {
    "addr:full":"Puerto Deportivo, 3 Sta. Eularia Riu Islas Baleares 07840",
    "addr:postcode":"07840",
    "addr:street":"Puerto Deportivo 3 Sta. Eularia Riu Islas Baleares",
    "iso:country":"ES",
    "sg:address":"Puerto Deportivo, 3",
    "sg:city":"Sta. Eularia Riu",
    "sg:orig_category":"Ropa Para Ni\u00d1os (al Por Menor)",
    "sg:phone":"+34 971 33 88 35",
    "sg:postcode":"07840",
    "sg:province":"Islas Baleares",
    "wof:name":"Balbas Utrilla Cristina",
    "wof:placetype":"venue"
},
  "geometry": {"coordinates":[2.8577105999,39.5341796875],"type":"Point"}
}