{
  "type": "Feature",
  "properties": {
    "addr:full":"Av Doctor Llanso, Del, 50 Mercadal Islas Baleares 07740",
    "addr:housenumber":"50",
    "addr:postcode":"07740",
    "addr:street":"Av Doctor Llanso Del",
    "iso:country":"ES",
    "sg:address":"Av Doctor Llanso, Del, 50",
    "sg:city":"Mercadal",
    "sg:orig_category":"Inversiones",
    "sg:phone":"+34 971 37 53 85",
    "sg:postcode":"07740",
    "sg:province":"Islas Baleares",
    "wof:name":"Arguimbau Riera Rafael",
    "wof:placetype":"venue"
},
  "geometry": {"coordinates":[4.0938262939,39.9910240173],"type":"Point"}
}