{
  "type": "Feature",
  "properties": {
    "addr:full":"Calle de Atilano Rodriguez, 4 Santander Cantabria 39002",
    "addr:housenumber":"4",
    "addr:postcode":"39002",
    "addr:street":"Calle De Atilano Rodriguez",
    "iso:country":"ES",
    "sg:address":"Calle de Atilano Rodriguez, 4",
    "sg:city":"Santander",
    "sg:orig_category":"Agencias Y Asesores De Publicidad",
    "sg:phone":"+34 942 21 30 83",
    "sg:postcode":"39002",
    "sg:province":"Cantabria",
    "wof:name":"Situacion Grafica S.l",
    "wof:placetype":"venue"
},
  "geometry": {"coordinates":[-3.8104040623,43.4587402344],"type":"Point"}
}