{
  "type": "Feature",
  "properties": {
    "addr:full":"Calle de Fernandez Escarzaga, 12 Guarnizo Cantabria 39611",
    "addr:housenumber":"12",
    "addr:postcode":"39611",
    "addr:street":"Calle De;Escarzaga",
    "iso:country":"ES",
    "sg:address":"Calle de Fernandez Escarzaga, 12",
    "sg:city":"Guarnizo",
    "sg:orig_category":"Electricidad: Instaladores",
    "sg:phone":"+34 942 54 23 64",
    "sg:postcode":"39611",
    "sg:province":"Cantabria",
    "wof:name":"Garcia Eguren Modesto",
    "wof:placetype":"venue"
},
  "geometry": {"coordinates":[-3.8289194107,43.3981437683],"type":"Point"}
}