{
  "type": "Feature",
  "properties": {
    "addr:full":"Carrer de Ramon Berenguer Iv, 2 Romanica Barcelona 08210",
    "addr:housenumber":"2",
    "addr:postcode":"08210",
    "addr:street":"Carrer De Ramon Berenguer Iv",
    "iso:country":"ES",
    "sg:address":"Carrer de Ramon Berenguer Iv, 2",
    "sg:city":"Romanica",
    "sg:orig_category":"Agentes Generales De Seguros",
    "sg:phone":"+34 937 18 24 60",
    "sg:postcode":"08210",
    "sg:province":"Barcelona",
    "wof:name":"Muelas Fernandez Diego",
    "wof:placetype":"venue"
},
  "geometry": {"coordinates":[2.1271760464,41.5150566101],"type":"Point"}
}