{
  "type": "Feature",
  "properties": {
    "iso:country":"ES",
    "sg:address":"Calle de Jose Cruz Conde, 1",
    "sg:city":"Cordoba",
    "sg:orig_category":"Loter\u00cda Y T\u00d3mbola",
    "sg:phone":"+34 957 47 54 36",
    "sg:postcode":"14008",
    "sg:province":"C\u00f3rdoba",
    "wof:name":"Saez Garcia Jose Manuel",
    "wof:placetype":"venue"
},
  "geometry": {"coordinates":[-4.7801251411,37.8852157593],"type":"Point"}
}