{
  "type": "Feature",
  "properties": {
    "iso:country":"ES",
    "sg:address":"Calle de Fernando Alcaide Rivas, 46",
    "sg:city":"Marchena",
    "sg:orig_category":"Molduras, Junquillos, Listones Y Molduras Perforadas",
    "sg:phone":"+34 954 84 45 12",
    "sg:postcode":"41620",
    "sg:province":"Sevilla",
    "wof:name":"Recreativos Rocio S.l.",
    "wof:placetype":"venue"
},
  "geometry": {"coordinates":[-5.4107294083,37.3267631531],"type":"Point"}
}