{
  "type": "Feature",
  "properties": {
    "iso:country":"ES",
    "sg:address":"Calle de Muguru, 6",
    "sg:city":"Galdakao",
    "sg:orig_category":"Art\u00cdculos De Decoraci\u00d3n (fabricaci\u00d3n Y Al Por Mayor)",
    "sg:phone":"+34 944 00 41 96",
    "sg:postcode":"48960",
    "sg:province":"Vizcaya",
    "wof:name":"Construcciones Y Reformas Muguru 2000, S.l.",
    "wof:placetype":"venue"
},
  "geometry": {"coordinates":[-2.8412959576,43.2323226929],"type":"Point"}
}