{
  "type": "Feature",
  "properties": {
    "addr:full":"Calle de Azahin, 6 Cazalla Sierra Sevilla 41370",
    "addr:housenumber":"6",
    "addr:postcode":"41370",
    "addr:street":"Calle De Azahin",
    "iso:country":"ES",
    "sg:address":"Calle de Azahin, 6",
    "sg:city":"Cazalla Sierra",
    "sg:orig_category":"Empresas De Carpinter\u00cda De Madera",
    "sg:phone":"+34 954 88 48 04",
    "sg:postcode":"41370",
    "sg:province":"Sevilla",
    "wof:name":"Chamorro Blanco Antonio",
    "wof:placetype":"venue"
},
  "geometry": {"coordinates":[-5.7569179535,37.9284973145],"type":"Point"}
}