{
  "type": "Feature",
  "properties": {
    "iso:country":"ES",
    "sg:address":"Plaz San Roque (de), 14",
    "sg:city":"Velez-malaga",
    "sg:orig_category":"Producci\u00d3n, Distribuci\u00d3n De Gas Butano Y Propano",
    "sg:phone":"+34 952 50 07 40",
    "sg:postcode":"29700",
    "sg:province":"M\u00e1laga",
    "wof:name":"Garcia Chica Jose Luis",
    "wof:placetype":"venue"
},
  "geometry": {"coordinates":[-4.0996661186,36.7785606384],"type":"Point"}
}