{
  "type": "Feature",
  "properties": {
    "iso:country":"ES",
    "sg:address":"Calle de Narciso Serra, 5",
    "sg:city":"Madrid",
    "sg:orig_category":"Arquitectos",
    "sg:phone":"+34 914 33 69 84",
    "sg:postcode":"28007",
    "sg:province":"Madrid",
    "wof:name":"Jimenez Carceles Alberto",
    "wof:placetype":"venue"
},
  "geometry": {"coordinates":[-3.6794838905,40.40442276],"type":"Point"}
}