{
  "type": "Feature",
  "properties": {
    "addr:full":"Carrer de Mossen Jaume Sole, 20 Cornella Llobregat Barcelona 08940",
    "addr:housenumber":"20",
    "addr:postcode":"08940",
    "addr:street":"Carrer De Mossen Jaume Sole",
    "iso:country":"ES",
    "sg:address":"Carrer de Mossen Jaume Sole, 20",
    "sg:city":"Cornella Llobregat",
    "sg:orig_category":"M\u00c1rmoles, Granitos Y Piedras Naturales",
    "sg:phone":"+34 933 76 06 36",
    "sg:postcode":"08940",
    "sg:province":"Barcelona",
    "wof:name":"Valero Conejo German",
    "wof:placetype":"venue"
},
  "geometry": {"coordinates":[2.0758259296,41.3615188599],"type":"Point"}
}