{
  "type": "Feature",
  "properties": {
    "addr:full":"Calle de Sol, 9 Vera Almer\u00eda 04620",
    "addr:housenumber":"9;almeri\u0301a",
    "addr:postcode":"04620",
    "addr:street":"Calle De Sol",
    "iso:country":"ES",
    "sg:address":"Calle de Sol, 9",
    "sg:city":"Vera",
    "sg:orig_category":"Institutos De Belleza",
    "sg:phone":"+34 950 39 06 22",
    "sg:postcode":"04620",
    "sg:province":"Almer\u00eda",
    "wof:name":"Duestetica C:b.",
    "wof:placetype":"venue"
},
  "geometry": {"coordinates":[-1.8668359518,37.2467575073],"type":"Point"}
}