{
  "type": "Feature",
  "properties": {
    "addr:full":"Ctra Villacastin, 12 Segovia Segovia 40006",
    "addr:housenumber":"12",
    "addr:postcode":"40006",
    "addr:street":"Ctra Villacastin",
    "iso:country":"ES",
    "sg:address":"Ctra Villacastin, 12",
    "sg:city":"Segovia",
    "sg:orig_category":"Carnicer\u00cdas, Carnicer\u00cdas",
    "sg:phone":"+34 921 42 43 16",
    "sg:postcode":"40006",
    "sg:province":"Segovia",
    "wof:name":"Olmos Diaz Alfredo",
    "wof:placetype":"venue"
},
  "geometry": {"coordinates":[-4.114563942,40.9332847595],"type":"Point"}
}