{
  "type": "Feature",
  "properties": {
    "iso:country":"ES",
    "sg:address":"Carrer de Viladomat, 230",
    "sg:city":"Barcelona",
    "sg:orig_category":"Tintes (fabricaci\u00d3n, Al Por Mayor)",
    "sg:phone":"+34 934 30 50 50",
    "sg:postcode":"08029",
    "sg:province":"Barcelona",
    "wof:name":"Gutierrez Barrocal Maria Jesus",
    "wof:placetype":"venue"
},
  "geometry": {"coordinates":[2.1490418911,41.386100769],"type":"Point"}
}