{
  "type": "Feature",
  "properties": {
    "iso:country":"ES",
    "sg:address":"Pase Extremadura, 1",
    "sg:city":"Olivenza",
    "sg:orig_category":"Electricidad: Instaladores",
    "sg:phone":"+34 924 49 22 22",
    "sg:postcode":"06100",
    "sg:province":"Badajoz",
    "wof:name":"Silva Gonzalez Jose",
    "wof:placetype":"venue"
},
  "geometry": {"coordinates":[-7.1024417877,38.6799621582],"type":"Point"}
}