{
  "type": "Feature",
  "properties": {
    "addr:full":"Calle de Collado (el), 20 Soria Soria 42002",
    "addr:housenumber":"20",
    "addr:postcode":"42002",
    "addr:street":"Calle De Collado El",
    "iso:country":"ES",
    "sg:address":"Calle de Collado (el), 20",
    "sg:city":"Soria",
    "sg:orig_category":"Asesor\u00cda Fiscal Y Jur\u00cddica",
    "sg:phone":"+34 975 21 47 20",
    "sg:postcode":"42002",
    "sg:province":"Soria",
    "wof:name":"Cacho Ruiz Blas Antonio",
    "wof:placetype":"venue"
},
  "geometry": {"coordinates":[-2.465785265,41.7640686035],"type":"Point"}
}