{
  "type": "Feature",
  "properties": {
    "addr:full":"Avda Europa (de), 13 Alcobendas Madrid 28108",
    "addr:housenumber":"13",
    "addr:postcode":"28108",
    "addr:street":"Avda Europa De",
    "iso:country":"ES",
    "sg:address":"Avda Europa (de), 13",
    "sg:city":"Alcobendas",
    "sg:orig_category":"Ropa Para Se\u00d1oras Y Caballeros (al Por Menor)",
    "sg:phone":"+34 916 61 85 70",
    "sg:postcode":"28108",
    "sg:province":"Madrid",
    "sg:website":"www.adolfo-dominguez.com",
    "wof:name":"Adolfo Dominguez S.a.",
    "wof:placetype":"venue"
},
  "geometry": {"coordinates":[-3.65710783,40.5194168091],"type":"Point"}
}