{
  "type": "Feature",
  "properties": {
    "iso:country":"ES",
    "sg:address":"Rua Pinar, 11",
    "sg:city":"Porri\u00f1o",
    "sg:orig_category":"Institutos De Belleza",
    "sg:phone":"+34 986 33 78 32",
    "sg:postcode":"36400",
    "sg:province":"Pontevedra",
    "wof:name":"Porto Sanchez Maria Del Pilar",
    "wof:placetype":"venue"
},
  "geometry": {"coordinates":[-8.6181335449,42.1607208252],"type":"Point"}
}