{
  "type": "Feature",
  "properties": {
    "addr:full":"Calle de Cid (el), 1 Estepona M\u00e1laga 29680",
    "addr:housenumber":"1",
    "addr:postcode":"29680",
    "addr:street":"Calle De Cid El",
    "iso:country":"ES",
    "sg:address":"Calle de Cid (el), 1",
    "sg:city":"Estepona",
    "sg:orig_category":"Librer\u00cdas",
    "sg:phone":"+34 952 80 71 38",
    "sg:postcode":"29680",
    "sg:province":"M\u00e1laga",
    "wof:name":"Routurou  Marcelo",
    "wof:placetype":"venue"
},
  "geometry": {"coordinates":[-5.1454229355,36.4282951355],"type":"Point"}
}