{
  "type": "Feature",
  "properties": {
    "iso:country":"ES",
    "sg:address":"Calle de Zubiaurre, 29",
    "sg:city":"Ermua",
    "sg:orig_category":"Farmacias",
    "sg:phone":"+34 943 17 93 49",
    "sg:postcode":"48260",
    "sg:province":"Vizcaya",
    "wof:name":"Cortina Mendizabal Virginia",
    "wof:placetype":"venue"
},
  "geometry": {"coordinates":[-2.5026600361,43.1877593994],"type":"Point"}
}