{
  "type": "Feature",
  "properties": {
    "iso:country":"ES",
    "sg:address":"Plaz Altozano (del), 6",
    "sg:city":"Trebujena",
    "sg:orig_category":"Reposter\u00cdas",
    "sg:phone":"+34 956 39 58 04",
    "sg:postcode":"11560",
    "sg:province":"C\u00e1diz",
    "wof:name":"Panaderia De Los Reyes S.c.",
    "wof:placetype":"venue"
},
  "geometry": {"coordinates":[-6.1769080162,36.8701171875],"type":"Point"}
}