{
  "type": "Feature",
  "properties": {
    "addr:full":"Calle de Algarve, 1 Jerez De La Frontera C\u00e1diz 11403",
    "addr:housenumber":"1",
    "addr:postcode":"11403",
    "addr:street":"Calle De Algarve",
    "iso:country":"ES",
    "sg:address":"Calle de Algarve, 1",
    "sg:city":"Jerez De La Frontera",
    "sg:orig_category":"Bisuter\u00cda, Joyer\u00cda, Relojer\u00cda (al Por Menor)",
    "sg:phone":"+34 956 33 06 85",
    "sg:postcode":"11403",
    "sg:province":"C\u00e1diz",
    "wof:name":"Dominguez Roman Francisco",
    "wof:placetype":"venue"
},
  "geometry": {"coordinates":[-6.1368870735,36.682723999],"type":"Point"}
}