{
  "type": "Feature",
  "properties": {
    "iso:country":"ES",
    "sg:address":"Rua Teofilo Llorente, 2",
    "sg:city":"Vigo",
    "sg:orig_category":"Bazares, Art\u00cdculos De Limpieza Y De Cocina (al Por Menor)",
    "sg:phone":"+34 986 22 51 25",
    "sg:postcode":"36202",
    "sg:province":"Pontevedra",
    "wof:name":"Veiga Solleiro Leonardo",
    "wof:placetype":"venue"
},
  "geometry": {"coordinates":[-8.7265424728,42.2399711609],"type":"Point"}
}