{
  "type": "Feature",
  "properties": {
    "addr:full":"Carr Virgen Desamparados, 50 Silla Valencia 46460",
    "addr:housenumber":"50",
    "addr:postcode":"46460",
    "addr:street":"Carr Virgen Desamparados",
    "iso:country":"ES",
    "sg:address":"Carr Virgen Desamparados, 50",
    "sg:city":"Silla",
    "sg:orig_category":"Electrodom\u00c9sticos (al Por Menor)",
    "sg:phone":"+34 961 21 16 75",
    "sg:postcode":"46460",
    "sg:province":"Valencia",
    "wof:name":"Carre\u00f1o Requena Juana",
    "wof:placetype":"venue"
},
  "geometry": {"coordinates":[-0.413459003,39.3656997681],"type":"Point"}
}