{
  "type": "Feature",
  "properties": {
    "addr:full":"San Juan Kalea, 2 O\u00f1ati Guip\u00f9zcoa 20560",
    "addr:housenumber":"2",
    "addr:postcode":"20560",
    "addr:street":"San Juan Kalea;Guipu\u0300Zcoa",
    "iso:country":"ES",
    "sg:address":"San Juan Kalea, 2",
    "sg:city":"O\u00f1ati",
    "sg:orig_category":"Asociaciones Humanitarias, De Cooperaci\u00d3n, De Acci\u00d3n Social",
    "sg:phone":"+34 943 78 09 61",
    "sg:postcode":"20560",
    "sg:province":"Guip\u00f9zcoa",
    "wof:name":"Ayuntamiento De O\u00d1ati",
    "wof:placetype":"venue"
},
  "geometry": {"coordinates":[-2.4150075912,43.0329589844],"type":"Point"}
}