{
  "type": "Feature",
  "properties": {
    "addr:full":"Carrer de Viladomat, 247 Barcelona Barcelona 08029",
    "addr:housenumber":"247",
    "addr:postcode":"08029",
    "addr:street":"Carrer De Viladomat",
    "iso:country":"ES",
    "sg:address":"Carrer de Viladomat, 247",
    "sg:city":"Barcelona",
    "sg:orig_category":"Cajas De Ahorro",
    "sg:phone":"+34 934 30 95 91",
    "sg:postcode":"08029",
    "sg:province":"Barcelona",
    "sg:website":"www.lacaixa.es",
    "wof:name":"Caixa D'estalvis I Pensions De Barcelona",
    "wof:placetype":"venue"
},
  "geometry": {"coordinates":[2.1484808922,41.3861427307],"type":"Point"}
}