{
  "type": "Feature",
  "properties": {
    "iso:country":"ES",
    "sg:address":"Calle de Artesania, 13",
    "sg:city":"Mairena Aljarafe",
    "sg:orig_category":"Fabricaci\u00d3n, Venta, Instalaci\u00d3n De R\u00d3tulos, De R\u00d3tulos Luminosos",
    "sg:phone":"+34 954 18 38 32",
    "sg:postcode":"41927",
    "sg:province":"Sevilla",
    "wof:name":"Serigrafia Aljarafe S.cv.",
    "wof:placetype":"venue"
},
  "geometry": {"coordinates":[-6.0626192093,37.3473587036],"type":"Point"}
}