{
  "type": "Feature",
  "properties": {
    "addr:full":"Avda Constitucion, 94 Valencia Valencia 46009",
    "addr:housenumber":"94",
    "addr:postcode":"46009",
    "addr:street":"Avda Constitucion",
    "iso:country":"ES",
    "sg:address":"Avda Constitucion, 94",
    "sg:city":"Valencia",
    "sg:orig_category":"Servicios Diversos",
    "sg:phone":"+34 963 66 83 09",
    "sg:postcode":"46009",
    "sg:province":"Valencia",
    "wof:name":"Valimen S.a.",
    "wof:placetype":"venue"
},
  "geometry": {"coordinates":[-0.3762919903,39.4884910583],"type":"Point"}
}