{
  "type": "Feature",
  "properties": {
    "addr:full":"Rbla Sant Jordi (de), 76 Ripollet Barcelona 08291",
    "addr:housenumber":"76",
    "addr:postcode":"08291",
    "addr:street":"Rbla Sant Jordi De",
    "iso:country":"ES",
    "sg:address":"Rbla Sant Jordi (de), 76",
    "sg:city":"Ripollet",
    "sg:orig_category":"Relojer\u00cda (al Por Menor, Reparaci\u00d3n)",
    "sg:phone":"+34 936 91 77 02",
    "sg:postcode":"08291",
    "sg:province":"Barcelona",
    "wof:name":"Ramirez Martinez Jeronimo",
    "wof:placetype":"venue"
},
  "geometry": {"coordinates":[2.1625299454,41.4962120056],"type":"Point"}
}