{
  "type": "Feature",
  "properties": {
    "addr:full":"Calle de Granada, S/n Peligros Granada 18210",
    "addr:housenumber":"/ n",
    "addr:postcode":"18210",
    "addr:street":"Calle De Granada S",
    "iso:country":"ES",
    "sg:address":"Calle de Granada, S/n",
    "sg:city":"Peligros",
    "sg:orig_category":"Electricidad: Instaladores",
    "sg:phone":"+34 958 40 08 65",
    "sg:postcode":"18210",
    "sg:province":"Granada",
    "wof:name":"Instalaciones Montajes Electricos Y Saneamientos S.a.",
    "wof:placetype":"venue"
},
  "geometry": {"coordinates":[-3.6279289722,37.2260017395],"type":"Point"}
}