{
  "type": "Feature",
  "properties": {
    "addr:full":"Calle de Ramon Y Cajal, 41 Cuenca Cuenca 16004",
    "addr:housenumber":"41",
    "addr:postcode":"16004",
    "addr:street":"Calle De Ramon Y Cajal",
    "iso:country":"ES",
    "sg:address":"Calle de Ramon Y Cajal, 41",
    "sg:city":"Cuenca",
    "sg:orig_category":"Ingeniero",
    "sg:phone":"+34 969 22 76 24",
    "sg:postcode":"16004",
    "sg:province":"Cuenca",
    "wof:name":"Guardia Lledo Nicasio",
    "wof:placetype":"venue"
},
  "geometry": {"coordinates":[-2.135160923,40.0695915222],"type":"Point"}
}