{
  "type": "Feature",
  "properties": {
    "iso:country":"ES",
    "sg:address":"Granada, S/n",
    "sg:city":"Alcantarilla",
    "sg:orig_category":"Molduras, Junquillos, Listones Y Molduras Perforadas",
    "sg:phone":"+34 968 80 59 69",
    "sg:postcode":"30820",
    "sg:province":"Murcia",
    "wof:name":"Jimenez Marmol Juan",
    "wof:placetype":"venue"
},
  "geometry": {"coordinates":[-1.2217142582,37.9629516602],"type":"Point"}
}