{
  "type": "Feature",
  "properties": {
    "iso:country":"ES",
    "sg:address":"Calle de Zaragoza (de), 28",
    "sg:city":"Alcobendas",
    "sg:orig_category":"Laboratorios Farmac\u00c9uticos",
    "sg:phone":"+34 916 61 41 15",
    "sg:postcode":"28100",
    "sg:province":"Madrid",
    "wof:name":"Homeolab S. A.",
    "wof:placetype":"venue"
},
  "geometry": {"coordinates":[-3.6420218945,40.542301178],"type":"Point"}
}