{
  "type": "Feature",
  "properties": {
    "addr:full":"Plaz Pau Casals (de), 3 Partija-santa Monica Madrid 28529",
    "addr:postcode":"28529",
    "iso:country":"ES",
    "sg:address":"Plaz Pau Casals (de), 3",
    "sg:city":"Partija-santa Monica",
    "sg:orig_category":"Fabricaci\u00d3n De Peines Y De Accesorios De Peluquer\u00cda",
    "sg:phone":"+34 913 01 15 51",
    "sg:postcode":"28529",
    "sg:province":"Madrid",
    "wof:name":"Gallego Rodriguez Angelica",
    "wof:placetype":"venue"
},
  "geometry": {"coordinates":[-3.5102670193,40.314289093],"type":"Point"}
}