{
  "type": "Feature",
  "properties": {
    "addr:full":"Calle de Reina Fabiola, 9 Zaragoza Zaragoza 50008",
    "addr:housenumber":"9",
    "addr:postcode":"50008",
    "addr:street":"Calle De Reina Fabiola",
    "iso:country":"ES",
    "sg:address":"Calle de Reina Fabiola, 9",
    "sg:city":"Zaragoza",
    "sg:orig_category":"Art\u00cdculos De Regalo (al Por Menor)",
    "sg:phone":"+34 976 59 42 35",
    "sg:postcode":"50008",
    "sg:province":"Zaragoza",
    "wof:name":"Zara 100 S.cv.",
    "wof:placetype":"venue"
},
  "geometry": {"coordinates":[-0.8729360104,41.6457901001],"type":"Point"}
}