{
  "type": "Feature",
  "properties": {
    "addr:full":"Calle de Fermin Caballero, 1 Cuenca Cuenca 16004",
    "addr:housenumber":"1",
    "addr:postcode":"16004",
    "addr:street":"Calle De Fermin Caballero",
    "iso:country":"ES",
    "sg:address":"Calle de Fermin Caballero, 1",
    "sg:city":"Cuenca",
    "sg:orig_category":"Imprenta",
    "sg:phone":"+34 969 22 62 53",
    "sg:postcode":"16004",
    "sg:province":"Cuenca",
    "wof:name":"Grupo De Comunicacion Ical S.l.",
    "wof:placetype":"venue"
},
  "geometry": {"coordinates":[-2.135821104,40.0696563721],"type":"Point"}
}