{
  "type": "Feature",
  "properties": {
    "iso:country":"ES",
    "sg:address":"Calle de Tetuan, 22",
    "sg:city":"Madrid",
    "sg:orig_category":"Alimentaci\u00d3n General (al Por Menor)",
    "sg:phone":"+34 915 21 19 85",
    "sg:postcode":"28013",
    "sg:province":"Madrid",
    "wof:name":"Masas Garcia Basilisa",
    "wof:placetype":"venue"
},
  "geometry": {"coordinates":[-3.7032709122,40.4177207947],"type":"Point"}
}