{
  "type": "Feature",
  "properties": {
    "iso:country":"ES",
    "sg:address":"Calle de Francisco Molina, 15",
    "sg:city":"Lillo",
    "sg:orig_category":"Fabricaci\u00d3n, Venta De Productos Base Farmac\u00c9uticos",
    "sg:phone":"+34 925 17 00 43",
    "sg:postcode":"45870",
    "sg:province":"Toledo",
    "wof:name":"Lopez Lopez Angela",
    "wof:placetype":"venue"
},
  "geometry": {"coordinates":[-3.3060369492,39.7238121033],"type":"Point"}
}