{
  "type": "Feature",
  "properties": {
    "addr:full":"Calle de Gabriela Mistral, 1 Barrio De Peral Murcia 30300",
    "addr:housenumber":"1",
    "addr:postcode":"30300",
    "addr:street":"Calle De Gabriela Mistral",
    "iso:country":"ES",
    "sg:address":"Calle de Gabriela Mistral, 1",
    "sg:city":"Barrio De Peral",
    "sg:orig_category":"M\u00c1quinas De Escribir, M\u00c1quinas De Oficina (al Por Menor, Reparaci\u00d3n)",
    "sg:phone":"+34 968 31 05 07",
    "sg:postcode":"30300",
    "sg:province":"Murcia",
    "wof:name":"Sistemas De Oficina De Murcia S.l.",
    "wof:placetype":"venue"
},
  "geometry": {"coordinates":[-1.1302499771,37.9829597473],"type":"Point"}
}