{
  "type": "Feature",
  "properties": {
    "iso:country":"ES",
    "sg:address":"Pol. Ind. El Canal, 10",
    "sg:city":"Vila-real",
    "sg:orig_category":"Cer\u00c1micas: Material Y Suministros",
    "sg:phone":"+34 964 53 52 50",
    "sg:postcode":"12540",
    "sg:province":"Castell\u00f3n",
    "wof:name":"Gres Rustico Ebro S.l.",
    "wof:placetype":"venue"
},
  "geometry": {"coordinates":[-0.0952899978,39.9453010559],"type":"Point"}
}