{
  "type": "Feature",
  "properties": {
    "iso:country":"ES",
    "sg:address":"Calle de Tenerias, 4",
    "sg:city":"Castellon",
    "sg:orig_category":"Agentes Generales De Seguros",
    "sg:phone":"+34 964 22 68 80",
    "sg:postcode":"12003",
    "sg:province":"Castell\u00f3n",
    "wof:name":"Jose Luis Ale S.l.",
    "wof:placetype":"venue"
},
  "geometry": {"coordinates":[-0.0338979997,39.9862670898],"type":"Point"}
}