{
  "type": "Feature",
  "properties": {
    "addr:full":"Calle de San Aton, 2 Badajoz Badajoz 06001",
    "addr:housenumber":"2",
    "addr:postcode":"06001",
    "addr:street":"Calle De San Aton",
    "iso:country":"ES",
    "sg:address":"Calle de San Aton, 2",
    "sg:city":"Badajoz",
    "sg:orig_category":"Internados & Ense\u00d1anza Privada",
    "sg:phone":"+34 924 22 06 01",
    "sg:postcode":"06001",
    "sg:province":"Badajoz",
    "wof:name":"Escuela Profesional Adoratrices",
    "wof:placetype":"venue"
},
  "geometry": {"coordinates":[-6.9693880081,38.8821678162],"type":"Point"}
}