{
  "type": "Feature",
  "properties": {
    "iso:country":"ES",
    "sg:address":"Calle de Berni Y Catala, 48",
    "sg:city":"Valencia",
    "sg:orig_category":"Prot\u00c9sicos Dentales",
    "sg:phone":"+34 963 65 18 47",
    "sg:postcode":"46019",
    "sg:province":"Valencia",
    "wof:name":"Vr Laboratorio Dental S.c.p.",
    "wof:placetype":"venue"
},
  "geometry": {"coordinates":[-0.3777216077,39.493938446],"type":"Point"}
}