{
  "type": "Feature",
  "properties": {
    "iso:country":"ES",
    "sg:address":"Plaz Juan Carlos I, 2",
    "sg:city":"Villalba De Los Barros",
    "sg:orig_category":"Quincaller\u00cda (al Por Menor)",
    "sg:phone":"+34 924 68 54 45",
    "sg:postcode":"06208",
    "sg:province":"Badajoz",
    "wof:name":"Becerra Garcia Andres",
    "wof:placetype":"venue"
},
  "geometry": {"coordinates":[-6.5110487938,38.6142044067],"type":"Point"}
}