{
  "type": "Feature",
  "properties": {
    "addr:full":"Calle de Bartolome J. Gallardo, 4 Badajoz Badajoz 06001",
    "addr:housenumber":"4",
    "addr:postcode":"06001",
    "addr:street":"Calle De Bartolome J. Gallardo",
    "iso:country":"ES",
    "sg:address":"Calle de Bartolome J. Gallardo, 4",
    "sg:city":"Badajoz",
    "sg:orig_category":"Caf\u00c9s, Bares, Cervecer\u00cdas",
    "sg:phone":"+34 924 26 21 53",
    "sg:postcode":"06001",
    "sg:province":"Badajoz",
    "wof:name":"Benchaga ,sidi Mohamed",
    "wof:placetype":"venue"
},
  "geometry": {"coordinates":[-6.9744801521,38.876247406],"type":"Point"}
}