{
  "type": "Feature",
  "properties": {
    "addr:full":"Avenida De La Playa, 1 Sada A Coru\u00f1a 15160",
    "addr:housenumber":"1",
    "addr:postcode":"15160",
    "addr:street":"Avenida De La Playa",
    "iso:country":"ES",
    "sg:address":"Avenida De La Playa, 1",
    "sg:city":"Sada",
    "sg:orig_category":"Asociaciones, Organismos Culturales Y Socioeducativos",
    "sg:phone":"+34 981 63 19 34",
    "sg:postcode":"15160",
    "sg:province":"A Coru\u00f1a",
    "wof:name":"Sociedad Recreativa Cultural Deportiva",
    "wof:placetype":"venue"
},
  "geometry": {"coordinates":[-8.2502622604,43.347782135],"type":"Point"}
}