{
  "type": "Feature",
  "properties": {
    "iso:country":"ES",
    "sg:address":"Avda Constitucion (de La), 46",
    "sg:city":"Granada",
    "sg:orig_category":"Ense\u00d1anza: Comercio, Gesti\u00d3n, Inform\u00c1tica",
    "sg:phone":"+34 958 20 84 00",
    "sg:postcode":"18012",
    "sg:province":"Granada",
    "wof:name":"Cortes Meyniel Antonio",
    "wof:placetype":"venue"
},
  "geometry": {"coordinates":[-3.6089611053,37.1866836548],"type":"Point"}
}