{
  "type": "Feature",
  "properties": {
    "addr:full":"Calle de Marques Alonso Martinez, 13 Alcala Henares Madrid 28804",
    "addr:housenumber":"13",
    "addr:postcode":"28804",
    "addr:street":"Calle De Marques Alonso Martinez",
    "iso:country":"ES",
    "sg:address":"Calle de Marques Alonso Martinez, 13",
    "sg:city":"Alcala Henares",
    "sg:orig_category":"Cajas De Ahorro",
    "sg:phone":"+34 918 83 34 70",
    "sg:postcode":"28804",
    "sg:province":"Madrid",
    "sg:website":"www.caixacatalunya.es",
    "wof:name":"Caixa D'estalvis De Catalunya",
    "wof:placetype":"venue"
},
  "geometry": {"coordinates":[-3.3569788933,40.4844818115],"type":"Point"}
}