{
  "type": "Feature",
  "properties": {
    "addr:full":"Avda Canarias, 136 Vecindario Las Palmas 35110",
    "addr:housenumber":"136",
    "addr:postcode":"35110",
    "addr:street":"Avda Canarias;Palmas",
    "iso:country":"ES",
    "sg:address":"Avda Canarias, 136",
    "sg:city":"Vecindario",
    "sg:orig_category":"Cl\u00cdnicas Dentales",
    "sg:phone":"+34 928 79 30 72",
    "sg:postcode":"35110",
    "sg:province":"Las Palmas",
    "wof:name":"Martin Ali Leocadio Nasser",
    "wof:placetype":"venue"
},
  "geometry": {"coordinates":[-15.4406194687,27.8517799377],"type":"Point"}
}