{
  "type": "Feature",
  "properties": {
    "addr:full":"Calle de Lope De Rueda, 96 Malaga M\u00e1laga 29190",
    "addr:housenumber":"96",
    "addr:postcode":"29190",
    "addr:street":"Calle De Lope De Rueda;Ma\u0301Laga",
    "iso:country":"ES",
    "sg:address":"Calle de Lope De Rueda, 96",
    "sg:city":"Malaga",
    "sg:orig_category":"Par\u00cds",
    "sg:phone":"+34 952 43 81 07",
    "sg:postcode":"29190",
    "sg:province":"M\u00e1laga",
    "wof:name":"Ponce Ramirez De Aguilera Ignacio",
    "wof:placetype":"venue"
},
  "geometry": {"coordinates":[-4.4801101685,36.7376708984],"type":"Point"}
}