{
  "type": "Feature",
  "properties": {
    "addr:full":"Avda Chile, 28 Villanueva Serena Badajoz 06700",
    "addr:housenumber":"28",
    "addr:postcode":"06700",
    "addr:street":"Avda Chile",
    "iso:country":"ES",
    "sg:address":"Avda Chile, 28",
    "sg:city":"Villanueva Serena",
    "sg:orig_category":"Comercio De Piezas De Recambio Y De Accesorios De Veh\u00cdculos, Veh\u00cdculos Industriales",
    "sg:phone":"+34 924 84 01 48",
    "sg:postcode":"06700",
    "sg:province":"Badajoz",
    "wof:name":"Talleres Acero S.l.",
    "wof:placetype":"venue"
},
  "geometry": {"coordinates":[-5.7911410332,38.9723358154],"type":"Point"}
}