{
  "type": "Feature",
  "properties": {
    "addr:full":"Calle de Eskolakoa, 2 Abadi\u00f1o Vizcaya 48220",
    "addr:housenumber":"2",
    "addr:postcode":"48220",
    "addr:street":"Calle De Eskolakoa",
    "iso:country":"ES",
    "sg:address":"Calle de Eskolakoa, 2",
    "sg:city":"Abadi\u00f1o",
    "sg:orig_category":"Carnicer\u00cdas, Carnicer\u00cdas",
    "sg:phone":"+34 946 81 54 52",
    "sg:postcode":"48220",
    "sg:province":"Vizcaya",
    "wof:name":"Carniceria Mikel (mikel Berrojalbiz Oregui)",
    "wof:placetype":"venue"
},
  "geometry": {"coordinates":[-2.6079039574,43.1692581177],"type":"Point"}
}