{
  "type": "Feature",
  "properties": {
    "iso:country":"ES",
    "sg:address":"Rond Sant Antoni, 15",
    "sg:city":"Barcelona",
    "sg:orig_category":"Inmobiliaria (agencias)",
    "sg:phone":"+34 934 43 10 31",
    "sg:postcode":"08011",
    "sg:province":"Barcelona",
    "sg:website":"www.markethouse-sl.com",
    "wof:name":"Makan 2004 S.l.",
    "wof:placetype":"venue"
},
  "geometry": {"coordinates":[2.1630990505,41.3801002502],"type":"Point"}
}