{
  "type": "Feature",
  "properties": {
    "addr:full":"Calle de Fuente Del Romero, 29 Madrid Madrid 28023",
    "addr:housenumber":"29",
    "addr:postcode":"madrid;28023",
    "addr:street":"Calle De Fuente Del Romero",
    "iso:country":"ES",
    "sg:address":"Calle de Fuente Del Romero, 29",
    "sg:city":"Madrid",
    "sg:orig_category":"Refiner\u00cdas De Petr\u00d3leo",
    "sg:phone":"+34 913 57 27 03",
    "sg:postcode":"28023",
    "sg:province":"Madrid",
    "wof:name":"Wintershall Ag Suc. Gen Espa\u00f1a",
    "wof:placetype":"venue"
},
  "geometry": {"coordinates":[-3.7663252354,40.451587677],"type":"Point"}
}