{
  "type": "Feature",
  "properties": {
    "addr:full":"Avda Fuente San Francisco, 14 Ubrique C\u00e1diz 11600",
    "addr:housenumber":"14",
    "addr:postcode":"11600",
    "addr:street":"Avda Fuente San Francisco;Ca\u0301Diz",
    "iso:country":"ES",
    "sg:address":"Avda Fuente San Francisco, 14",
    "sg:city":"Ubrique",
    "sg:orig_category":"M\u00c1quinas Para Recortar Y Pegar",
    "sg:phone":"+34 956 46 32 58",
    "sg:postcode":"11600",
    "sg:province":"C\u00e1diz",
    "wof:name":"Suarez Carrasco David",
    "wof:placetype":"venue"
},
  "geometry": {"coordinates":[-5.4481940269,36.6668395996],"type":"Point"}
}