{
  "type": "Feature",
  "properties": {
    "addr:full":"Ramon Irizar Kalea, 1 O\u00f1ati Guip\u00f9zcoa 20560",
    "addr:housenumber":"1",
    "addr:postcode":"20560",
    "addr:street":"Ramon Irizar Kalea;Guipu\u0300Zcoa",
    "iso:country":"ES",
    "sg:address":"Ramon Irizar Kalea, 1",
    "sg:city":"O\u00f1ati",
    "sg:orig_category":"Asociaciones, Organismos Culturales Y Socioeducativos",
    "sg:phone":"+34 943 78 05 55",
    "sg:postcode":"20560",
    "sg:province":"Guip\u00f9zcoa",
    "wof:name":"Sociedad Recreativa Zubi-alde",
    "wof:placetype":"venue"
},
  "geometry": {"coordinates":[-2.4127130508,43.0327453613],"type":"Point"}
}