{
  "type": "Feature",
  "properties": {
    "addr:full":"Caler\u00edn, S/n Ronda M\u00e1laga 29400",
    "addr:housenumber":"/ n",
    "addr:postcode":"29400",
    "addr:street":"Caleri\u0301N S;Ronda Ma\u0301Laga",
    "iso:country":"ES",
    "sg:address":"Caler\u00edn, S/n",
    "sg:city":"Ronda",
    "sg:orig_category":"Chapister\u00cda",
    "sg:phone":"+34 952 87 46 25",
    "sg:postcode":"29400",
    "sg:province":"M\u00e1laga",
    "wof:name":"Talleres Arunda S.l.",
    "wof:placetype":"venue"
},
  "geometry": {"coordinates":[-5.1566538811,36.7473983765],"type":"Point"}
}