{
  "type": "Feature",
  "properties": {
    "addr:full":"Calle de Puentelarra, 8 Madrid Madrid 28031",
    "addr:housenumber":"8",
    "addr:postcode":"madrid;28031",
    "addr:street":"Calle De Puentelarra",
    "iso:country":"ES",
    "sg:address":"Calle de Puentelarra, 8",
    "sg:city":"Madrid",
    "sg:orig_category":"Contenedores (mercanc\u00cdas)",
    "sg:phone":"+34 913 31 03 47",
    "sg:postcode":"28031",
    "sg:province":"Madrid",
    "wof:name":"Yunta Garcia Jesus",
    "wof:placetype":"venue"
},
  "geometry": {"coordinates":[-3.6092131138,40.3826942444],"type":"Point"}
}