{
  "type": "Feature",
  "properties": {
    "addr:full":"Calle de Breton De Los Herreros, 8 Sevilla Sevilla 41006",
    "addr:housenumber":"8",
    "addr:postcode":"41006",
    "addr:street":"Calle De Breton De Los Herreros",
    "iso:country":"ES",
    "sg:address":"Calle de Breton De Los Herreros, 8",
    "sg:city":"Sevilla",
    "sg:orig_category":"Peluqueros: De Se\u00d1oras",
    "sg:phone":"+34 954 63 77 89",
    "sg:postcode":"41006",
    "sg:province":"Sevilla",
    "wof:name":"Mu\u00f1oz Arjona Belleda",
    "wof:placetype":"venue"
},
  "geometry": {"coordinates":[-5.9492521286,37.3708229065],"type":"Point"}
}