{
  "type": "Feature",
  "properties": {
    "iso:country":"ES",
    "sg:address":"Calle de Coto Los Romeros (coto (el)), S/n",
    "sg:city":"Coto",
    "sg:classifiers":[
        {
            "category":"Manufacturing",
            "subcategory":"Metals",
            "type":"Manufacturing & Wholesale Goods"
        }
    ],
    "sg:phone":"+34 968 62 61 06",
    "sg:postcode":"30565",
    "sg:province":"Murcia",
    "sg:tags":[
        "en",
        "fundiciones"
    ],
    "wof:name":"Funhijoma S.l.",
    "wof:placetype":"venue"
},
  "geometry": {"coordinates":[-1.1298867464,37.9834747314],"type":"Point"}
}