{
  "type": "Feature",
  "properties": {
    "addr:full":"Carrer de Sant Miquel, 23 Palma Islas Baleares 07002",
    "addr:housenumber":"23",
    "addr:postcode":"07002",
    "addr:street":"Carrer De Sant Miquel",
    "iso:country":"ES",
    "sg:address":"Carrer de Sant Miquel, 23",
    "sg:city":"Palma",
    "sg:orig_category":"Hielo Artificial (fabricaci\u00d3n, Distribuci\u00d3n)",
    "sg:phone":"+34 971 71 04 92",
    "sg:postcode":"07002",
    "sg:province":"Islas Baleares",
    "wof:name":"Bo I Millo S.l.",
    "wof:placetype":"venue"
},
  "geometry": {"coordinates":[2.6520380974,39.5732192993],"type":"Point"}
}