{
  "type": "Feature",
  "properties": {
    "addr:full":"Carr Princep D'asturies, 23 Badalona Barcelona 08918",
    "addr:housenumber":"23",
    "addr:postcode":"08918",
    "addr:street":"Carr Princep D'Asturies",
    "iso:country":"ES",
    "sg:address":"Carr Princep D'asturies, 23",
    "sg:city":"Badalona",
    "sg:orig_category":"Mec\u00c1nico Del Autom\u00d3vil",
    "sg:phone":"+34 933 83 80 82",
    "sg:postcode":"08918",
    "sg:province":"Barcelona",
    "wof:name":"Ramos Veiga Jose",
    "wof:placetype":"venue"
},
  "geometry": {"coordinates":[2.2248134613,41.4305992126],"type":"Point"}
}