{
  "type": "Feature",
  "properties": {
    "addr:full":"Rua Oporto, 15 Vigo Pontevedra 36201",
    "addr:housenumber":"15",
    "addr:postcode":"36201",
    "addr:street":"Rua Oporto",
    "iso:country":"ES",
    "sg:address":"Rua Oporto, 15",
    "sg:city":"Vigo",
    "sg:orig_category":"Agencias De Trabajo Temporal",
    "sg:phone":"+34 986 22 29 06",
    "sg:postcode":"36201",
    "sg:province":"Pontevedra",
    "wof:name":"Trabatem E.t.t.s.a.",
    "wof:placetype":"venue"
},
  "geometry": {"coordinates":[-8.7160768509,42.237613678],"type":"Point"}
}