{
  "type": "Feature",
  "properties": {
    "iso:country":"ES",
    "sg:address":"Calle de Algar Del Palancia, 4",
    "sg:city":"Valencia",
    "sg:orig_category":"Alimentaci\u00d3n General (al Por Menor)",
    "sg:phone":"+34 963 76 16 00",
    "sg:postcode":"46017",
    "sg:province":"Valencia",
    "wof:name":"Rubio Garcia-nieto Soledad",
    "wof:placetype":"venue"
},
  "geometry": {"coordinates":[-0.3908371925,39.4329681396],"type":"Point"}
}