{
  "type": "Feature",
  "properties": {
    "iso:country":"ES",
    "sg:address":"Carrer de Prat De La Riba, 91",
    "sg:city":"Sabadell",
    "sg:orig_category":"Institutos De Belleza",
    "sg:phone":"+34 937 27 21 61",
    "sg:postcode":"08206",
    "sg:province":"Barcelona",
    "wof:name":"Velasco Alonso Lidia",
    "wof:placetype":"venue"
},
  "geometry": {"coordinates":[2.0927939415,41.5503425598],"type":"Point"}
}