{
  "type": "Feature",
  "properties": {
    "addr:full":"Calle de Cordoba, S/n Villafranca Cordoba C\u00f3rdoba 14420",
    "addr:housenumber":"s / n",
    "addr:postcode":"14420",
    "addr:street":"Calle De Cordoba",
    "iso:country":"ES",
    "sg:address":"Calle de Cordoba, S/n",
    "sg:city":"Villafranca Cordoba",
    "sg:orig_category":"Congelados: Productos Alimentarios (fabricaci\u00d3n, Al Por Mayor)",
    "sg:phone":"+34 957 19 08 00",
    "sg:postcode":"14420",
    "sg:province":"C\u00f3rdoba",
    "wof:name":"Comunitel Global S.a.",
    "wof:placetype":"venue"
},
  "geometry": {"coordinates":[-4.5465669632,37.9589576721],"type":"Point"}
}