{
  "type": "Feature",
  "properties": {
    "addr:full":"Calle de Rua, 6 Cintruenigo Navarra 31592",
    "addr:postcode":"31592",
    "addr:street":"Calle De Rua 6",
    "iso:country":"ES",
    "sg:address":"Calle de Rua, 6",
    "sg:city":"Cintruenigo",
    "sg:orig_category":"Insecticidas, Fumigaci\u00d3n",
    "sg:phone":"+34 948 81 18 18",
    "sg:postcode":"31592",
    "sg:province":"Navarra",
    "wof:name":"Sociedad Agraria De Transformacion San Ramon",
    "wof:placetype":"venue"
},
  "geometry": {"coordinates":[-1.8072760105,42.0819816589],"type":"Point"}
}