{
  "type": "Feature",
  "properties": {
    "iso:country":"ES",
    "sg:address":"Navares, S/n",
    "sg:city":"Navares",
    "sg:orig_category":"Fabricaci\u00d3n De Su\u00c9ters Y Chalecos De Punto",
    "sg:phone":"+34 968 70 43 04",
    "sg:postcode":"30410",
    "sg:province":"Murcia",
    "wof:name":"G.p.perssam S.l.",
    "wof:placetype":"venue"
},
  "geometry": {"coordinates":[-1.9348490238,38.0359802246],"type":"Point"}
}