{
  "type": "Feature",
  "properties": {
    "iso:country":"ES",
    "sg:address":"Industrialdea, S/n",
    "sg:city":"Itziar",
    "sg:orig_category":"Ferreter\u00cda (diversos)",
    "sg:phone":"+34 943 19 92 76",
    "sg:postcode":"20829",
    "sg:province":"Guip\u00f9zcoa",
    "wof:name":"Fordeba S.a.l.",
    "wof:placetype":"venue"
},
  "geometry": {"coordinates":[-2.3308770657,43.276473999],"type":"Point"}
}