{
  "type": "Feature",
  "properties": {
    "iso:country":"ES",
    "sg:address":"Calle de Bide Zahar, 7",
    "sg:city":"Ugao-miraballes",
    "sg:orig_category":"Iglesia Cat\u00d3lica",
    "sg:phone":"+34 946 48 05 06",
    "sg:postcode":"48490",
    "sg:province":"Vizcaya",
    "wof:name":"Parroquia-san Bartolome Apostol",
    "wof:placetype":"venue"
},
  "geometry": {"coordinates":[-2.9018597603,43.1781845093],"type":"Point"}
}