{
  "type": "Feature",
  "properties": {
    "addr:full":"Pl Pare Oriol, 10 Manresa Barcelona 08241",
    "addr:housenumber":"10",
    "addr:postcode":"08241",
    "addr:street":"Pl Pare Oriol",
    "iso:country":"ES",
    "sg:address":"Pl Pare Oriol, 10",
    "sg:city":"Manresa",
    "sg:orig_category":"Maquinaria Para Industrias Diversas",
    "sg:phone":"+34 938 73 75 06",
    "sg:postcode":"08241",
    "sg:province":"Barcelona",
    "wof:name":"Pujol Tatje Ignacio",
    "wof:placetype":"venue"
},
  "geometry": {"coordinates":[1.8351900578,41.7249450684],"type":"Point"}
}