{
  "type": "Feature",
  "properties": {
    "addr:full":"G.v. Marques Del Turia, 62 Valencia Valencia 46005",
    "addr:housenumber":"62",
    "addr:postcode":"46005",
    "addr:street":"Turia",
    "iso:country":"ES",
    "sg:address":"G.v. Marques Del Turia, 62",
    "sg:city":"Valencia",
    "sg:orig_category":"Aparcamientos (infraestructuras, Accesorios)",
    "sg:phone":"+34 963 95 79 24",
    "sg:postcode":"46005",
    "sg:province":"Valencia",
    "wof:name":"Perez Martinez Rodrigo",
    "wof:placetype":"venue"
},
  "geometry": {"coordinates":[-0.3671480119,39.4674072266],"type":"Point"}
}