{
  "type": "Feature",
  "properties": {
    "iso:country":"ES",
    "sg:address":"Calle de Alcantara, 57",
    "sg:city":"Madrid",
    "sg:orig_category":"Cerrajer\u00cda, Ferrallista",
    "sg:phone":"+34 914 01 12 16",
    "sg:postcode":"28006",
    "sg:province":"Madrid",
    "sg:website":"www.teleurge.es",
    "wof:name":"Tecnicos Multiseur S.l.",
    "wof:placetype":"venue"
},
  "geometry": {"coordinates":[-3.6735591888,40.4314994812],"type":"Point"}
}