{
  "type": "Feature",
  "properties": {
    "iso:country":"ES",
    "sg:address":"Calle de Calvo Sotelo, 8",
    "sg:city":"Madrigal Vera",
    "sg:orig_category":"Alimentaci\u00d3n General (al Por Menor)",
    "sg:phone":"+34 927 56 50 59",
    "sg:postcode":"10480",
    "sg:province":"C\u00e1ceres",
    "wof:name":"Vaquero Bruzos Pilar",
    "wof:placetype":"venue"
},
  "geometry": {"coordinates":[-5.3689088821,40.1471481323],"type":"Point"}
}