{
  "type": "Feature",
  "properties": {
    "iso:country":"ES",
    "sg:address":"Rua Vicente Risco, 38",
    "sg:city":"Ourense",
    "sg:orig_category":"Panader\u00cdas, Panader\u00cdas",
    "sg:phone":"+34 988 37 43 74",
    "sg:postcode":"32001",
    "sg:province":"Ourense",
    "wof:name":"Perez Rodriguez Francisco",
    "wof:placetype":"venue"
},
  "geometry": {"coordinates":[-7.8663539886,42.348274231],"type":"Point"}
}