{
  "type": "Feature",
  "properties": {
    "addr:full":"Modreiro, S/n El Pedregal Asturias 33877",
    "addr:housenumber":"/ n",
    "addr:postcode":"33877",
    "addr:street":"Modreiro S;Pedregal Asturias",
    "iso:country":"ES",
    "sg:address":"Modreiro, S/n",
    "sg:city":"El Pedregal",
    "sg:orig_category":"Cr\u00cda De Animales",
    "sg:phone":"+34 985 83 72 85",
    "sg:postcode":"33877",
    "sg:province":"Asturias",
    "wof:name":"Lorences Menendez Tomas",
    "wof:placetype":"venue"
},
  "geometry": {"coordinates":[-6.3657212257,43.3727226257],"type":"Point"}
}