{
  "type": "Feature",
  "properties": {
    "addr:full":"Calle de Escalante, 133 Valencia Valencia 46011",
    "addr:housenumber":"133",
    "addr:postcode":"46011",
    "addr:street":"Calle De Escalante",
    "iso:country":"ES",
    "sg:address":"Calle de Escalante, 133",
    "sg:city":"Valencia",
    "sg:orig_category":"Psic\u00d3logos",
    "sg:phone":"+34 963 72 35 00",
    "sg:postcode":"46011",
    "sg:province":"Valencia",
    "wof:name":"Naya Hurtado Amparo",
    "wof:placetype":"venue"
},
  "geometry": {"coordinates":[-0.3311960101,39.4669532776],"type":"Point"}
}