{
  "type": "Feature",
  "properties": {
    "iso:country":"ES",
    "sg:address":"Av Ferreria (la), 21",
    "sg:city":"Terra Nostra",
    "sg:orig_category":"Veh\u00cdculos De Ocasi\u00d3n",
    "sg:phone":"+34 935 75 35 45",
    "sg:postcode":"08110",
    "sg:province":"Barcelona",
    "sg:website":"www.tr24xa.com",
    "wof:name":"T.r.-2 Rally Service S.l.",
    "wof:placetype":"venue"
},
  "geometry": {"coordinates":[2.1859691143,41.4872894287],"type":"Point"}
}