{
  "type": "Feature",
  "properties": {
    "iso:country":"ES",
    "sg:address":"Aita Lertxundi Kalea, 42",
    "sg:city":"Orio",
    "sg:orig_category":"Muebles, Minoristas",
    "sg:phone":"+34 943 83 11 76",
    "sg:postcode":"20810",
    "sg:province":"Guip\u00f9zcoa",
    "wof:name":"Arin Y Embil S. R. C.",
    "wof:placetype":"venue"
},
  "geometry": {"coordinates":[-2.1258320808,43.2744636536],"type":"Point"}
}