{
  "type": "Feature",
  "properties": {
    "iso:country":"ES",
    "sg:address":"Plzl Mercado (del), S/n",
    "sg:city":"Calahorra",
    "sg:orig_category":"Carnicer\u00cdas, Carnicer\u00cdas",
    "sg:phone":"+34 941 13 05 16",
    "sg:postcode":"26500",
    "sg:province":"La Rioja",
    "wof:name":"Tejerdor Llorente Saturnino",
    "wof:placetype":"venue"
},
  "geometry": {"coordinates":[-1.961879015,42.3013191223],"type":"Point"}
}