{
  "type": "Feature",
  "properties": {
    "addr:full":"Calle de Mercado Alto, 10 Motril Granada 18600",
    "addr:housenumber":"10",
    "addr:postcode":"18600",
    "addr:street":"Calle De Mercado Alto",
    "iso:country":"ES",
    "sg:address":"Calle de Mercado Alto, 10",
    "sg:city":"Motril",
    "sg:orig_category":"Iglesias Evang\u00c9licas",
    "sg:phone":"+34 958 60 33 01",
    "sg:postcode":"18600",
    "sg:province":"Granada",
    "wof:name":"Asociacion Evangelica Internacional",
    "wof:placetype":"venue"
},
  "geometry": {"coordinates":[-3.5198538303,36.7474136353],"type":"Point"}
}