{
  "type": "Feature",
  "properties": {
    "iso:country":"ES",
    "sg:address":"Carrer de Wagner, 110",
    "sg:city":"Terrassa",
    "sg:orig_category":"Servicios Gsm",
    "sg:phone":"+34 937 86 03 97",
    "sg:postcode":"08222",
    "sg:province":"Barcelona",
    "wof:name":"Qzl Movil S.l.",
    "wof:placetype":"venue"
},
  "geometry": {"coordinates":[2.0239799023,41.5617332458],"type":"Point"}
}