{
  "type": "Feature",
  "properties": {
    "addr:full":"Avda Murcia, 6 Cabezo Torres Murcia 30110",
    "addr:housenumber":"6",
    "addr:postcode":"30110",
    "addr:street":"Avda Murcia",
    "iso:country":"ES",
    "sg:address":"Avda Murcia, 6",
    "sg:city":"Cabezo Torres",
    "sg:orig_category":"Ferreter\u00cda (diversos)",
    "sg:phone":"+34 968 83 03 57",
    "sg:postcode":"30110",
    "sg:province":"Murcia",
    "wof:name":"Chatarra Hijos De Rojo S.l.",
    "wof:placetype":"venue"
},
  "geometry": {"coordinates":[-1.1236590147,38.0238609314],"type":"Point"}
}