{
  "type": "Feature",
  "properties": {
    "addr:full":"Aldea San Roque, 20 San Roque Ourense 32456",
    "addr:housenumber":"20",
    "addr:postcode":"32456",
    "addr:street":"San Roque",
    "iso:country":"ES",
    "sg:address":"Aldea San Roque, 20",
    "sg:city":"San Roque",
    "sg:orig_category":"Vinos Y Licores (venta Al Por Menor)",
    "sg:phone":"+34 988 28 00 52",
    "sg:postcode":"32456",
    "sg:province":"Ourense",
    "wof:name":"Gomez Fernandez Ramon",
    "wof:placetype":"venue"
},
  "geometry": {"coordinates":[-8.0002717972,42.3691673279],"type":"Point"}
}