{
  "type": "Feature",
  "properties": {
    "addr:full":"Carr Vicens Vives, 6 Fornells Selva Girona 17458",
    "addr:housenumber":"6",
    "addr:postcode":"17458",
    "addr:street":"Carr Vicens Vives",
    "iso:country":"ES",
    "sg:address":"Carr Vicens Vives, 6",
    "sg:city":"Fornells Selva",
    "sg:orig_category":"Empresas De Carpinter\u00cda De Madera",
    "sg:phone":"+34 972 47 60 56",
    "sg:postcode":"17458",
    "sg:province":"Girona",
    "wof:name":"Esparraguera Rovira Fernando",
    "wof:placetype":"venue"
},
  "geometry": {"coordinates":[2.8099250793,41.9300727844],"type":"Point"}
}