{
  "type": "Feature",
  "properties": {
    "iso:country":"ES",
    "sg:address":"Camarme\u00f1a, S/n",
    "sg:city":"Bulnes",
    "sg:orig_category":"Empresas De Electricidad En General",
    "sg:phone":"+34 985 84 65 89",
    "sg:postcode":"33554",
    "sg:province":"Asturias",
    "wof:name":"Enel Viesgo Servicios S.l.",
    "wof:placetype":"venue"
},
  "geometry": {"coordinates":[-4.836783886,43.2591094971],"type":"Point"}
}