{
  "type": "Feature",
  "properties": {
    "addr:full":"Aerop. Ncnal. S. Pablo, S/n Sevilla Sevilla 41007",
    "addr:housenumber":"s / n",
    "addr:postcode":"41007",
    "iso:country":"ES",
    "sg:address":"Aerop. Ncnal. S. Pablo, S/n",
    "sg:city":"Sevilla",
    "sg:orig_category":"Alquiler De Veh\u00cdculos: Turismos Y Utilitarios",
    "sg:phone":"+34 954 51 48 53",
    "sg:postcode":"41007",
    "sg:province":"Sevilla",
    "sg:website":"www.crowncarhire.com",
    "wof:name":"Aurigacrown Car Hire S.l.",
    "wof:placetype":"venue"
},
  "geometry": {"coordinates":[-6.0018129349,37.3876953125],"type":"Point"}
}