{
  "type": "Feature",
  "properties": {
    "addr:full":"Calle de Andalucia, S/n Gijon Asturias 33210",
    "addr:postcode":"33210",
    "addr:street":"Calle De Andalucia S / N",
    "iso:country":"ES",
    "sg:address":"Calle de Andalucia, S/n",
    "sg:city":"Gijon",
    "sg:orig_category":"Bazares, Art\u00cdculos De Limpieza Y De Cocina (al Por Menor)",
    "sg:phone":"+34 985 38 95 87",
    "sg:postcode":"33210",
    "sg:province":"Asturias",
    "wof:name":"Pereira Carballido Milagros",
    "wof:placetype":"venue"
},
  "geometry": {"coordinates":[-5.6704287529,43.5275344849],"type":"Point"}
}