{
  "type": "Feature",
  "properties": {
    "iso:country":"ES",
    "sg:address":"Can Bernat (pol Torrent Puig), 26",
    "sg:city":"Arenys Munt",
    "sg:orig_category":"Galvanizaci\u00d3n, Esta\u00d1ado, Emplomado",
    "sg:phone":"+34 937 93 98 15",
    "sg:postcode":"08358",
    "sg:province":"Barcelona",
    "wof:name":"Vigmar Recobriments S.l.",
    "wof:placetype":"venue"
},
  "geometry": {"coordinates":[2.5319230556,41.6068382263],"type":"Point"}
}