{
  "type": "Feature",
  "properties": {
    "addr:full":"Far, S/n Cabrera Mar Barcelona 08349",
    "addr:housenumber":"s",
    "addr:postcode":"08349",
    "addr:street":"Far;/ N Cabrera Mar Barcelona",
    "iso:country":"ES",
    "sg:address":"Far, S/n",
    "sg:city":"Cabrera Mar",
    "sg:orig_category":"Distribuci\u00d3n De Petr\u00d3leo Y Derivados",
    "sg:phone":"+34 937 59 03 45",
    "sg:postcode":"08349",
    "sg:province":"Barcelona",
    "wof:name":"Xampeny Lopez Ana Maria",
    "wof:placetype":"venue"
},
  "geometry": {"coordinates":[2.4060513973,41.5211753845],"type":"Point"}
}