{
  "type": "Feature",
  "properties": {
    "iso:country":"ES",
    "sg:address":"Ctra Sevilla-rosales, Km. 0023,0",
    "sg:city":"Carmona",
    "sg:orig_category":"Distribuci\u00d3n De Petr\u00d3leo Y Derivados",
    "sg:phone":"+34 955 95 32 68",
    "sg:postcode":"41410",
    "sg:province":"Sevilla",
    "wof:name":"Oilinvest Espa\u00d1a S.a.",
    "wof:placetype":"venue"
},
  "geometry": {"coordinates":[-5.6433792114,37.4708709717],"type":"Point"}
}