{
  "type": "Feature",
  "properties": {
    "iso:country":"ES",
    "sg:address":"Rua Calvo Sotelo, 1",
    "sg:city":"Cea",
    "sg:orig_category":"Molduras, Junquillos, Listones Y Molduras Perforadas",
    "sg:phone":"+34 988 28 21 37",
    "sg:postcode":"32130",
    "sg:province":"Ourense",
    "wof:name":"Fernandez Arias Jose",
    "wof:placetype":"venue"
},
  "geometry": {"coordinates":[-7.9871091843,42.4757614136],"type":"Point"}
}