{
  "type": "Feature",
  "properties": {
    "addr:full":"Pol. Industrial Congos, S/n Granollers Barcelona 08403",
    "addr:housenumber":"s",
    "addr:postcode":"08403",
    "addr:street":"Pol.;/ N",
    "iso:country":"ES",
    "sg:address":"Pol. Industrial Congos, S/n",
    "sg:city":"Granollers",
    "sg:orig_category":"Mortero Y Material Para Jardines",
    "sg:phone":"+34 938 79 61 97",
    "sg:postcode":"08403",
    "sg:province":"Barcelona",
    "wof:name":"Ma\u00d1osa S.l.",
    "wof:placetype":"venue"
},
  "geometry": {"coordinates":[2.279804945,41.6144218445],"type":"Point"}
}