{
  "type": "Feature",
  "properties": {
    "iso:country":"ES",
    "sg:address":"Calle de Islas Bermudas, 5",
    "sg:city":"Madrid",
    "sg:orig_category":"Tintorer\u00cdas, Limpieza En Seco",
    "sg:phone":"+34 917 34 02 72",
    "sg:postcode":"28034",
    "sg:province":"Madrid",
    "wof:name":"Tintorerias Y Lavanderias Maria Luisa S.l.",
    "wof:placetype":"venue"
},
  "geometry": {"coordinates":[-3.6872859001,40.4928474426],"type":"Point"}
}