{
  "type": "Feature",
  "properties": {
    "addr:full":"Calle de Escultor Coomonte, 2 Benavente Zamora 49600",
    "addr:housenumber":"2",
    "addr:postcode":"49600",
    "addr:street":"Calle De Escultor Coomonte",
    "iso:country":"ES",
    "sg:address":"Calle de Escultor Coomonte, 2",
    "sg:city":"Benavente",
    "sg:orig_category":"Plomeros",
    "sg:phone":"+34 980 63 47 68",
    "sg:postcode":"49600",
    "sg:province":"Zamora",
    "wof:name":"Marques Perez Valentin",
    "wof:placetype":"venue"
},
  "geometry": {"coordinates":[-5.6769142151,41.9991455078],"type":"Point"}
}