{
  "type": "Feature",
  "properties": {
    "iso:country":"ES",
    "sg:address":"Calle de O'donnell, General, 29",
    "sg:city":"Melilla",
    "sg:orig_category":"Inmobiliaria (agencias)",
    "sg:phone":"+34 952 68 42 73",
    "sg:postcode":"52001",
    "sg:province":"Melilla",
    "wof:name":"Damte C.b",
    "wof:placetype":"venue"
},
  "geometry": {"coordinates":[-2.9434149265,35.2970504761],"type":"Point"}
}