{
  "type": "Feature",
  "properties": {
    "addr:full":"Calle de Santa Maria Magdalena, 50 Dos Hermanas Sevilla 41700",
    "addr:housenumber":"50",
    "addr:postcode":"41700",
    "addr:street":"Calle De Santa;Magdalena",
    "iso:country":"ES",
    "sg:address":"Calle de Santa Maria Magdalena, 50",
    "sg:city":"Dos Hermanas",
    "sg:orig_category":"Ropa Para Caballeros (al Por Menor)",
    "sg:phone":"+34 954 72 02 13",
    "sg:postcode":"41700",
    "sg:province":"Sevilla",
    "wof:name":"Navarro Flores Jose",
    "wof:placetype":"venue"
},
  "geometry": {"coordinates":[-5.9258799553,37.2830657959],"type":"Point"}
}