{
  "type": "Feature",
  "properties": {
    "iso:country":"ES",
    "sg:address":"Carrer de Orient, 25",
    "sg:city":"Reus",
    "sg:orig_category":"Arreglo, Reparaci\u00d3n, Piezas Sueltas De Televisi\u00d3n, V\u00cddeo, Hi",
    "sg:phone":"+34 977 77 11 26",
    "sg:postcode":"43204",
    "sg:province":"Tarragona",
    "wof:name":"Artigas Agullo Jorge",
    "wof:placetype":"venue"
},
  "geometry": {"coordinates":[1.1146916151,41.1542510986],"type":"Point"}
}