{
  "type": "Feature",
  "properties": {
    "addr:full":"Ctra. Palma, Km. 0043,6 Son Fe Islas Baleares 07409",
    "addr:postcode":"07409",
    "addr:street":"Ctra. Palma Km. 0043,6",
    "iso:country":"ES",
    "sg:address":"Ctra. Palma, Km. 0043,6",
    "sg:city":"Son Fe",
    "sg:orig_category":"Centros Empresariales",
    "sg:phone":"+34 971 54 80 36",
    "sg:postcode":"07409",
    "sg:province":"Islas Baleares",
    "wof:name":"Turisme Consultors Interilles S.l.",
    "wof:placetype":"venue"
},
  "geometry": {"coordinates":[2.9117100239,39.6136398315],"type":"Point"}
}