{
  "type": "Feature",
  "properties": {
    "addr:full":"Rond Cabanyal, 4 Sueca Valencia 46410",
    "addr:housenumber":"4",
    "addr:postcode":"46410",
    "addr:street":"Cabanyal",
    "iso:country":"ES",
    "sg:address":"Rond Cabanyal, 4",
    "sg:city":"Sueca",
    "sg:orig_category":"Distribuci\u00d3n De Petr\u00d3leo Y Derivados",
    "sg:phone":"+34 961 71 07 58",
    "sg:postcode":"46410",
    "sg:province":"Valencia",
    "wof:name":"Estaciones De Servicio Campol S.l.",
    "wof:placetype":"venue"
},
  "geometry": {"coordinates":[-0.3076440096,39.2027435303],"type":"Point"}
}