{
  "type": "Feature",
  "properties": {
    "addr:full":"Carretera De La Albuera, Km. 0000,1 Talavera Real Badajoz 06140",
    "addr:postcode":"06140",
    "addr:street":"Carretera De La Albuera Km. 0000,1",
    "iso:country":"ES",
    "sg:address":"Carretera De La Albuera, Km. 0000,1",
    "sg:city":"Talavera Real",
    "sg:orig_category":"Mec\u00c1nico Del Autom\u00d3vil",
    "sg:phone":"+34 924 44 04 75",
    "sg:postcode":"06140",
    "sg:province":"Badajoz",
    "wof:name":"Amador Martinez Regino",
    "wof:placetype":"venue"
},
  "geometry": {"coordinates":[-6.7768959999,38.8780708313],"type":"Point"}
}