{
  "type": "Feature",
  "properties": {
    "addr:full":"Pase Alcobendas (de), 10 Alcobendas Madrid 28109",
    "addr:postcode":"28109",
    "iso:country":"ES",
    "sg:address":"Pase Alcobendas (de), 10",
    "sg:city":"Alcobendas",
    "sg:orig_category":"Ropa Para Se\u00d1oras (al Por Menor)",
    "sg:phone":"+34 916 50 69 71",
    "sg:postcode":"28109",
    "sg:province":"Madrid",
    "wof:name":"Gloria Y Juana Italia S.l.",
    "wof:placetype":"venue"
},
  "geometry": {"coordinates":[-3.6210570335,40.5282096863],"type":"Point"}
}