{
  "type": "Feature",
  "properties": {
    "addr:full":"Calle de Profesor Hernandez Pacheco, 22 Caceres C\u00e1ceres 10002",
    "addr:housenumber":"22",
    "addr:postcode":"10002",
    "addr:street":"Calle De Profesor Hernandez Pacheco;Ca\u0301Ceres",
    "iso:country":"ES",
    "sg:address":"Calle de Profesor Hernandez Pacheco, 22",
    "sg:city":"Caceres",
    "sg:orig_category":"Promotores Constructores",
    "sg:phone":"+34 927 21 52 99",
    "sg:postcode":"10002",
    "sg:province":"C\u00e1ceres",
    "wof:name":"Promociones Y Construcciones Herminio Exposito S.l.",
    "wof:placetype":"venue"
},
  "geometry": {"coordinates":[-6.3727431297,39.4693984985],"type":"Point"}
}