{
  "type": "Feature",
  "properties": {
    "iso:country":"ES",
    "sg:address":"Calle de Salamanca, 7",
    "sg:city":"Caceres",
    "sg:orig_category":"Pod\u00d3logos: Pedicuros",
    "sg:phone":"+34 927 21 55 40",
    "sg:postcode":"10002",
    "sg:province":"C\u00e1ceres",
    "wof:name":"Lancho Casares Jose Maria",
    "wof:placetype":"venue"
},
  "geometry": {"coordinates":[-6.3720030785,39.4745063782],"type":"Point"}
}