{
  "type": "Feature",
  "properties": {
    "iso:country":"ES",
    "sg:address":"Calle de Federico Garcia Lorca (de), 16",
    "sg:city":"Mejorada Campo",
    "sg:orig_category":"Pod\u00d3logos: Pedicuros",
    "sg:phone":"+34 916 79 24 73",
    "sg:postcode":"28840",
    "sg:province":"Madrid",
    "wof:name":"Garcia Jimenez Consuelo",
    "wof:placetype":"venue"
},
  "geometry": {"coordinates":[-3.4870972633,40.3981399536],"type":"Point"}
}