{
  "type": "Feature",
  "properties": {
    "addr:full":"Carrer de Marques De Cornella, 12 Cornella Llobregat Barcelona 08940",
    "addr:housenumber":"12",
    "addr:postcode":"08940",
    "addr:street":"Carrer De Marques De Cornella",
    "iso:country":"ES",
    "sg:address":"Carrer de Marques De Cornella, 12",
    "sg:city":"Cornella Llobregat",
    "sg:orig_category":"Promotores Constructores",
    "sg:phone":"+34 933 77 85 13",
    "sg:postcode":"08940",
    "sg:province":"Barcelona",
    "wof:name":"Lumbreras Martinez Enrique Javier",
    "wof:placetype":"venue"
},
  "geometry": {"coordinates":[2.0660231113,41.3553123474],"type":"Point"}
}