{
  "type": "Feature",
  "properties": {
    "addr:full":"Calle de Mayor, 1 Cazalegas Toledo 45553",
    "addr:housenumber":"1",
    "addr:postcode":"45553",
    "addr:street":"Calle De Mayor",
    "iso:country":"ES",
    "sg:address":"Calle de Mayor, 1",
    "sg:city":"Cazalegas",
    "sg:orig_category":"Molduras, Junquillos, Listones Y Molduras Perforadas",
    "sg:phone":"+34 925 86 91 22",
    "sg:postcode":"45553",
    "sg:province":"Toledo",
    "wof:name":"Flores De La Llave Jose Ramon",
    "wof:placetype":"venue"
},
  "geometry": {"coordinates":[-4.6732602119,40.0091056824],"type":"Point"}
}