{
  "type": "Feature",
  "properties": {
    "iso:country":"ES",
    "sg:address":"Calle de San Francisco, 78",
    "sg:city":"Pto Real",
    "sg:orig_category":"Molduras, Junquillos, Listones Y Molduras Perforadas",
    "sg:phone":"+34 956 83 74 15",
    "sg:postcode":"11510",
    "sg:province":"C\u00e1diz",
    "sg:website":"www.barkalera.es/cvg",
    "wof:name":"Gimenez Macias Francisco",
    "wof:placetype":"venue"
},
  "geometry": {"coordinates":[-6.1855778694,36.5301513672],"type":"Point"}
}