{
  "type": "Feature",
  "properties": {
    "addr:full":"Dorleta Auzoa Eskoriatza Guip\u00f9zcoa 20540",
    "addr:postcode":"20540",
    "addr:street":"Dorleta Auzoa;Guipu\u0300Zcoa",
    "iso:country":"ES",
    "sg:address":"Dorleta Auzoa",
    "sg:city":"Eskoriatza",
    "sg:orig_category":"Universidades",
    "sg:phone":"+34 943 71 31 37",
    "sg:postcode":"20540",
    "sg:province":"Guip\u00f9zcoa",
    "wof:name":"Huhezi Koop, E.",
    "wof:placetype":"venue"
},
  "geometry": {"coordinates":[-2.5274240971,43.0150947571],"type":"Point"}
}