{
  "type": "Feature",
  "properties": {
    "addr:full":"Rua Travesia De Vigo, 204 Roris Pontevedra 36207",
    "addr:housenumber":"204",
    "addr:postcode":"36207",
    "addr:street":"Rua Travesia De Vigo",
    "iso:country":"ES",
    "sg:address":"Rua Travesia De Vigo, 204",
    "sg:city":"Roris",
    "sg:classifiers":[
        {
            "category":"Cinema",
            "subcategory":"Movie Theater",
            "type":"Entertainment"
        }
    ],
    "sg:phone":"+34 986 26 50 25",
    "sg:postcode":"36207",
    "sg:province":"Pontevedra",
    "sg:tags":[
        "salas",
        "de",
        "cine"
    ],
    "wof:name":"Yelmo Films S.l.",
    "wof:placetype":"venue"
},
  "geometry": {"coordinates":[-7.1463718414,42.3855743408],"type":"Point"}
}