{
  "type": "Feature",
  "properties": {
    "addr:full":"Ctra San Vicente, 5 Elguero Vizcaya 48510",
    "addr:housenumber":"5",
    "addr:postcode":"48510",
    "addr:street":"Ctra San Vicente",
    "iso:country":"ES",
    "sg:address":"Ctra San Vicente, 5",
    "sg:city":"Elguero",
    "sg:orig_category":"Abrasivos Y Superabrasivos (fabricaci\u00d3n, Al Por Mayor)",
    "sg:phone":"+34 944 96 76 14",
    "sg:postcode":"48510",
    "sg:province":"Vizcaya",
    "wof:name":"Tyrolit S.a.",
    "wof:placetype":"venue"
},
  "geometry": {"coordinates":[-3.0369338989,43.3047294617],"type":"Point"}
}