{
  "type": "Feature",
  "properties": {
    "addr:full":"Avda Soldevilla Vazquez, 15 Posadas C\u00f3rdoba 14730",
    "addr:housenumber":"15;co\u0301rdoba",
    "addr:postcode":"14730",
    "addr:street":"Avda Soldevilla Vazquez",
    "iso:country":"ES",
    "sg:address":"Avda Soldevilla Vazquez, 15",
    "sg:city":"Posadas",
    "sg:orig_category":"Persianas Interiores, Exteriores",
    "sg:phone":"+34 957 63 07 19",
    "sg:postcode":"14730",
    "sg:province":"C\u00f3rdoba",
    "wof:name":"Benitez Agui Guillermo",
    "wof:placetype":"venue"
},
  "geometry": {"coordinates":[-97.78224945069999,45.7040786743],"type":"Point"}
}