{
  "type": "Feature",
  "properties": {
    "iso:country":"ES",
    "sg:address":"La Parra, S/n",
    "sg:city":"Ejido",
    "sg:orig_category":"Importaci\u00d3n",
    "sg:phone":"+34 950 57 30 09",
    "sg:postcode":"04700",
    "sg:province":"Almer\u00eda",
    "wof:name":"Hortosalvi S.l",
    "wof:placetype":"venue"
},
  "geometry": {"coordinates":[-2.8278186321,36.7686843872],"type":"Point"}
}