{
  "type": "Feature",
  "properties": {
    "addr:full":"Avda Askatasun Etorbidea, 20 Durango Vizcaya 48200",
    "addr:housenumber":"20",
    "addr:postcode":"48200",
    "addr:street":"Avda Askatasun Etorbidea",
    "iso:country":"ES",
    "sg:address":"Avda Askatasun Etorbidea, 20",
    "sg:city":"Durango",
    "sg:orig_category":"Promotores Constructores",
    "sg:phone":"+34 946 21 56 50",
    "sg:postcode":"48200",
    "sg:province":"Vizcaya",
    "wof:name":"Construcciones Durango, S.a.",
    "wof:placetype":"venue"
},
  "geometry": {"coordinates":[-2.6381909847,43.1694297791],"type":"Point"}
}