{
  "type": "Feature",
  "properties": {
    "addr:full":"Avda Ciudad De Barcelona, 5 Madrid Madrid 28007",
    "addr:housenumber":"5",
    "addr:postcode":"28007",
    "addr:street":"Avda Ciudad De Barcelona",
    "iso:country":"ES",
    "sg:address":"Avda Ciudad De Barcelona, 5",
    "sg:city":"Madrid",
    "sg:orig_category":"Molduras, Junquillos, Listones Y Molduras Perforadas",
    "sg:phone":"+34 915 52 49 89",
    "sg:postcode":"28007",
    "sg:province":"Madrid",
    "wof:name":"Gonzalez Garcia Joaquin",
    "wof:placetype":"venue"
},
  "geometry": {"coordinates":[-3.6825709343,40.4050445557],"type":"Point"}
}