{
  "type": "Feature",
  "properties": {
    "addr:full":"Calle de Real, 101 Corral Almaguer Toledo 45880",
    "addr:housenumber":"101",
    "addr:postcode":"45880",
    "addr:street":"Calle De Real",
    "iso:country":"ES",
    "sg:address":"Calle de Real, 101",
    "sg:city":"Corral Almaguer",
    "sg:orig_category":"Supermercados Y Hipermercados",
    "sg:phone":"+34 925 19 14 14",
    "sg:postcode":"45880",
    "sg:province":"Toledo",
    "wof:name":"Alimencor S.l.",
    "wof:placetype":"venue"
},
  "geometry": {"coordinates":[-3.1613767147,39.7550697327],"type":"Point"}
}