{
  "type": "Feature",
  "properties": {
    "iso:country":"ES",
    "sg:address":"Calle de Esteve Victoria, 11",
    "sg:city":"Valencia",
    "sg:orig_category":"Material Y Suministros Para Dentistas, Cirujanos",
    "sg:phone":"+34 963 33 20 69",
    "sg:postcode":"46006",
    "sg:province":"Valencia",
    "wof:name":"Suministro Dentales S.l.",
    "wof:placetype":"venue"
},
  "geometry": {"coordinates":[-0.3724415004,39.4574432373],"type":"Point"}
}