{
  "type": "Feature",
  "properties": {
    "iso:country":"ES",
    "sg:address":"Calle de Ascao, 43",
    "sg:city":"Madrid",
    "sg:orig_category":"\u00d3ptica: Instrumentos (fabricaci\u00d3n)",
    "sg:phone":"+34 914 06 17 66",
    "sg:postcode":"28017",
    "sg:province":"Madrid",
    "wof:name":"Boragums.s.l.",
    "wof:placetype":"venue"
},
  "geometry": {"coordinates":[-3.6393859386,40.4309692383],"type":"Point"}
}