{
  "type": "Feature",
  "properties": {
    "addr:full":"Calle de Juan De Mena, 1 Cordoba C\u00f3rdoba 14002",
    "addr:housenumber":"1",
    "addr:postcode":"14002",
    "addr:street":"Calle De Juan;Mena;Co\u0301Rdoba",
    "iso:country":"ES",
    "sg:address":"Calle de Juan De Mena, 1",
    "sg:city":"Cordoba",
    "sg:orig_category":"Iglesia Cat\u00d3lica",
    "sg:phone":"+34 957 47 60 12",
    "sg:postcode":"14002",
    "sg:province":"C\u00f3rdoba",
    "wof:name":"Parroquia Del Salvador",
    "wof:placetype":"venue"
},
  "geometry": {"coordinates":[-4.7790589333,37.8833465576],"type":"Point"}
}