{
  "type": "Feature",
  "properties": {
    "addr:full":"C/ Major, 12 Banyoles Girona 17820",
    "addr:housenumber":"12",
    "addr:postcode":"17820",
    "addr:street":"C / Major",
    "iso:country":"ES",
    "sg:address":"C/ Major, 12",
    "sg:city":"Banyoles",
    "sg:orig_category":"Dietistas",
    "sg:phone":"+34 972 57 17 64",
    "sg:postcode":"17820",
    "sg:province":"Girona",
    "wof:name":"Bailina Amagat Federico",
    "wof:placetype":"venue"
},
  "geometry": {"coordinates":[2.7659502029,42.1186256409],"type":"Point"}
}