{
  "type": "Feature",
  "properties": {
    "iso:country":"ES",
    "sg:address":"Calle de Amargura, 14",
    "sg:city":"Zamora",
    "sg:orig_category":"Laboratorios Y Trabajos De Fotograf\u00cda, V\u00cddeo Y Cine",
    "sg:phone":"+34 980 67 11 70",
    "sg:postcode":"49013",
    "sg:province":"Zamora",
    "wof:name":"Vicente Campos Maria Vicenta",
    "wof:placetype":"venue"
},
  "geometry": {"coordinates":[-5.7414717674,41.5096511841],"type":"Point"}
}