{
  "type": "Feature",
  "properties": {
    "addr:full":"Calle de Santa Catalina, 4 Donostia-san Sebastian Guip\u00f9zcoa 20004",
    "addr:housenumber":"4",
    "addr:postcode":"20004",
    "addr:street":"Calle De Santa Catalina",
    "iso:country":"ES",
    "sg:address":"Calle de Santa Catalina, 4",
    "sg:city":"Donostia-san Sebastian",
    "sg:orig_category":"Ropa Y Accesorios",
    "sg:phone":"+34 943 42 07 51",
    "sg:postcode":"20004",
    "sg:province":"Guip\u00f9zcoa",
    "wof:name":"Emediba S.l.",
    "wof:placetype":"venue"
},
  "geometry": {"coordinates":[-1.9798660278,43.3208198547],"type":"Point"}
}