{
  "type": "Feature",
  "properties": {
    "addr:full":"Calle de Doctor Tercedor, 8 Motril Granada 18600",
    "addr:housenumber":"8",
    "addr:postcode":"18600",
    "addr:street":"Calle De Doctor Tercedor",
    "iso:country":"ES",
    "sg:address":"Calle de Doctor Tercedor, 8",
    "sg:city":"Motril",
    "sg:orig_category":"Molduras, Junquillos, Listones Y Molduras Perforadas",
    "sg:phone":"+34 958 60 00 17",
    "sg:postcode":"18600",
    "sg:province":"Granada",
    "wof:name":"Fernandez Casco Miguel Angel",
    "wof:placetype":"venue"
},
  "geometry": {"coordinates":[-3.5122377872,36.7440605164],"type":"Point"}
}