{
  "type": "Feature",
  "properties": {
    "iso:country":"ES",
    "sg:address":"Cami Sant Bartomeu, S/n",
    "sg:city":"S. Bartomeu Valldan",
    "sg:orig_category":"Explotaci\u00d3n De Minas",
    "sg:phone":"+34 938 22 08 37",
    "sg:postcode":"08600",
    "sg:province":"Barcelona",
    "wof:name":"Montajes Rus S.l.",
    "wof:placetype":"venue"
},
  "geometry": {"coordinates":[1.8476580381,42.1001281738],"type":"Point"}
}