{
  "type": "Feature",
  "properties": {
    "iso:country":"ES",
    "sg:address":"Ctra. Badajoz, S/n",
    "sg:city":"Villar Rey",
    "sg:orig_category":"Distribuci\u00d3n De Petr\u00d3leo Y Derivados",
    "sg:phone":"+34 924 41 44 07",
    "sg:postcode":"06192",
    "sg:province":"Badajoz",
    "wof:name":"Servicios Plata Lino Hidrocarburos",
    "wof:placetype":"venue"
},
  "geometry": {"coordinates":[-6.8512291908,39.1324043274],"type":"Point"}
}