{
  "type": "Feature",
  "properties": {
    "addr:full":"Carr Lasauca, 6 Figueres Girona 17600",
    "addr:housenumber":"6",
    "addr:postcode":"17600",
    "addr:street":"Carr Lasauca",
    "iso:country":"ES",
    "sg:address":"Carr Lasauca, 6",
    "sg:city":"Figueres",
    "sg:orig_category":"Fotograf\u00cda Y Cine: Aparatos, Pel\u00cdculas Y Accesorios (al Por Menor)",
    "sg:phone":"+34 972 51 17 91",
    "sg:postcode":"17600",
    "sg:province":"Girona",
    "sg:website":"www.fotoprix.es",
    "wof:name":"Digiprix S.l.",
    "wof:placetype":"venue"
},
  "geometry": {"coordinates":[2.9594600201,42.2660980225],"type":"Point"}
}