{
  "type": "Feature",
  "properties": {
    "iso:country":"ES",
    "sg:address":"Ctra Manlleu, Km. 0001,4",
    "sg:city":"Vic",
    "sg:orig_category":"Alimentaci\u00d3n General (al Por Mayor)",
    "sg:phone":"+34 938 86 01 88",
    "sg:postcode":"08500",
    "sg:province":"Barcelona",
    "wof:name":"Pinsos Sant Antoni S.a.",
    "wof:placetype":"venue"
},
  "geometry": {"coordinates":[2.2555251122,41.9344902039],"type":"Point"}
}