{
  "type": "Feature",
  "properties": {
    "iso:country":"ES",
    "sg:address":"Mercado De Mayoristas, S/n",
    "sg:city":"Vitoria-gasteiz",
    "sg:orig_category":"Distribuci\u00d3n De Petr\u00d3leo Y Derivados",
    "sg:phone":"+34 945 22 89 48",
    "sg:postcode":"01004",
    "sg:province":"\u00c1lava",
    "wof:name":"Pescados Julia Ruiz Beradona S.a.",
    "wof:placetype":"venue"
},
  "geometry": {"coordinates":[-2.6666500568,42.8437004089],"type":"Point"}
}