{
  "type": "Feature",
  "properties": {
    "iso:country":"ES",
    "sg:address":"Av Palfuriana, 91",
    "sg:city":"Barri Maritim De Comarruga",
    "sg:orig_category":"Librer\u00cdas",
    "sg:phone":"+34 977 68 28 80",
    "sg:postcode":"43880",
    "sg:province":"Tarragona",
    "wof:name":"Pascual Mora Mari Carmen",
    "wof:placetype":"venue"
},
  "geometry": {"coordinates":[1.5386699438,41.1833496094],"type":"Point"}
}