{
  "type": "Feature",
  "properties": {
    "addr:full":"Carrer de Mar (la), 91 Altea Alicante 03590",
    "addr:housenumber":"91",
    "addr:postcode":"03590",
    "addr:street":"Carrer De Mar La",
    "iso:country":"ES",
    "sg:address":"Carrer de Mar (la), 91",
    "sg:city":"Altea",
    "sg:orig_category":"Abogados",
    "sg:phone":"+34 965 84 15 48",
    "sg:postcode":"03590",
    "sg:province":"Alicante",
    "wof:name":"Administracion De Justicia",
    "wof:placetype":"venue"
},
  "geometry": {"coordinates":[-0.0502147004,38.5971870422],"type":"Point"}
}