{
  "type": "Feature",
  "properties": {
    "addr:full":"Calle de Conde De Xiquena, 5 Madrid Madrid 28004",
    "addr:housenumber":"5",
    "addr:postcode":"28004",
    "addr:street":"Calle De Conde De Xiquena",
    "iso:country":"ES",
    "sg:address":"Calle de Conde De Xiquena, 5",
    "sg:city":"Madrid",
    "sg:orig_category":"Abogados",
    "sg:phone":"+34 915 21 98 89",
    "sg:postcode":"28004",
    "sg:province":"Madrid",
    "wof:name":"Sanz De Bremond Mayans Jaime",
    "wof:placetype":"venue"
},
  "geometry": {"coordinates":[-3.6942648888,40.4226341248],"type":"Point"}
}