{
  "type": "Feature",
  "properties": {
    "addr:full":"Calle de Sant Esperit, 7 Valencia Valencia 46020",
    "addr:housenumber":"7",
    "addr:postcode":"46020",
    "addr:street":"Calle De Sant Esperit",
    "iso:country":"ES",
    "sg:address":"Calle de Sant Esperit, 7",
    "sg:city":"Valencia",
    "sg:orig_category":"Art\u00cdculos Funerarios (al Por Menor)",
    "sg:phone":"+34 963 69 64 35",
    "sg:postcode":"46020",
    "sg:province":"Valencia",
    "wof:name":"Montesinos Piqueras Jose",
    "wof:placetype":"venue"
},
  "geometry": {"coordinates":[-0.3590599895,39.4854431152],"type":"Point"}
}