{
  "type": "Feature",
  "properties": {
    "iso:country":"ES",
    "sg:address":"Calle de Regajales (los), S/n",
    "sg:city":"Arenas San Pedro",
    "sg:orig_category":"Contenedores (mercanc\u00cdas)",
    "sg:phone":"+34 920 37 10 56",
    "sg:postcode":"05400",
    "sg:province":"\u00c1vila",
    "wof:name":"Meson Serrano Luis Miguel",
    "wof:placetype":"venue"
},
  "geometry": {"coordinates":[-5.0761342049,40.2085037231],"type":"Point"}
}