{
  "type": "Feature",
  "properties": {
    "addr:full":"Gta Rederos De Los, 7 Huelva Huelva 21006",
    "addr:postcode":"21006",
    "iso:country":"ES",
    "sg:address":"Gta Rederos De Los, 7",
    "sg:city":"Huelva",
    "sg:orig_category":"Alimentaci\u00d3n General (al Por Menor)",
    "sg:phone":"+34 959 23 17 04",
    "sg:postcode":"21006",
    "sg:province":"Huelva",
    "wof:name":"Garrido Conde Manuel",
    "wof:placetype":"venue"
},
  "geometry": {"coordinates":[-6.934343338,37.2669410706],"type":"Point"}
}