{
  "type": "Feature",
  "properties": {
    "addr:full":"Calle de Zuatzu, 2 Donostia-san Sebastian Guip\u00f9zcoa 20009",
    "addr:housenumber":"2",
    "addr:postcode":"20009",
    "addr:street":"Calle De Zuatzu",
    "iso:country":"ES",
    "sg:address":"Calle de Zuatzu, 2",
    "sg:city":"Donostia-san Sebastian",
    "sg:classifiers":[
        {
            "category":"Professional",
            "subcategory":"Research",
            "type":"Services"
        }
    ],
    "sg:phone":"+34 943 21 40 63",
    "sg:postcode":"20009",
    "sg:province":"Guip\u00f9zcoa",
    "sg:tags":[
        "mercado",
        "de",
        "estudios"
    ],
    "wof:name":"Merkatek S.l.",
    "wof:placetype":"venue"
},
  "geometry": {"coordinates":[-1.9794000387,43.3173789978],"type":"Point"}
}