{
  "type": "Feature",
  "properties": {
    "addr:full":"Calle de San Miguel, 3 Virgen Camino Le\u00f3n 24198",
    "addr:postcode":"24198",
    "addr:street":"Calle De San Miguel;Camino Leo\u0301N",
    "iso:country":"ES",
    "sg:address":"Calle de San Miguel, 3",
    "sg:city":"Virgen Camino",
    "sg:orig_category":"Agencias Y Agentes Comerciales, Representantes",
    "sg:phone":"+34 987 30 08 34",
    "sg:postcode":"24198",
    "sg:province":"Le\u00f3n",
    "wof:name":"Fidalgo Calvo Roberto",
    "wof:placetype":"venue"
},
  "geometry": {"coordinates":[-5.6412038803,42.5828514099],"type":"Point"}
}