{
  "type": "Feature",
  "properties": {
    "addr:full":"Barr Peruri, 33 Peruri Vizcaya 48940",
    "addr:housenumber":"33",
    "addr:postcode":"48940",
    "addr:street":"Peruri",
    "iso:country":"ES",
    "sg:address":"Barr Peruri, 33",
    "sg:city":"Peruri",
    "sg:orig_category":"\u00d3ptica: Instrumentos (fabricaci\u00d3n)",
    "sg:phone":"+34 944 91 18 93",
    "sg:postcode":"48940",
    "sg:province":"Vizcaya",
    "wof:name":"Eroski Sociedad Cooperativa",
    "wof:placetype":"venue"
},
  "geometry": {"coordinates":[-2.9860789776,43.3275489807],"type":"Point"}
}