{
  "type": "Feature",
  "properties": {
    "iso:country":"ES",
    "sg:address":"Calle de Gabolatz, 12",
    "sg:city":"Soraluze-placencia Armas",
    "sg:orig_category":"Supermercados Y Hipermercados",
    "sg:phone":"+34 943 75 13 38",
    "sg:postcode":"20590",
    "sg:province":"Guip\u00f9zcoa",
    "wof:name":"Fernandez Ordax Amparo",
    "wof:placetype":"venue"
},
  "geometry": {"coordinates":[-2.4061720371,43.1683883667],"type":"Point"}
}