{
  "type": "Feature",
  "properties": {
    "addr:full":"Avda Belen (de), 37 Ciempozuelos Madrid 28350",
    "addr:housenumber":"37",
    "addr:postcode":"28350",
    "addr:street":"Avda Belen De",
    "iso:country":"ES",
    "sg:address":"Avda Belen (de), 37",
    "sg:city":"Ciempozuelos",
    "sg:orig_category":"Venta, Colocaci\u00d3n, Reparaci\u00d3n De Parabrisas, Techos Descapotables",
    "sg:phone":"+34 918 08 60 48",
    "sg:postcode":"28350",
    "sg:province":"Madrid",
    "wof:name":"Gonzalez Baena Maria",
    "wof:placetype":"venue"
},
  "geometry": {"coordinates":[-3.628068924,40.1553840637],"type":"Point"}
}