{
  "type": "Feature",
  "properties": {
    "iso:country":"ES",
    "sg:address":"Avda Judimendi, 15",
    "sg:city":"Vitoria-gasteiz",
    "sg:orig_category":"Estancos",
    "sg:phone":"+34 945 25 64 05",
    "sg:postcode":"01003",
    "sg:province":"\u00c1lava",
    "wof:name":"Ana Maria Ibisate Ibisate (estanco Ibisate)",
    "wof:placetype":"venue"
},
  "geometry": {"coordinates":[-2.6613917351,42.8464279175],"type":"Point"}
}