{
  "type": "Feature",
  "properties": {
    "iso:country":"ES",
    "sg:address":"Avda Fernando Blanco, 64",
    "sg:city":"Cee",
    "sg:orig_category":"Abogados",
    "sg:phone":"+34 981 74 52 06",
    "sg:postcode":"15270",
    "sg:province":"La Coru\u00f1a",
    "wof:name":"Caama\u00f1o Senande Francisco",
    "wof:placetype":"venue"
},
  "geometry": {"coordinates":[-9.1873121262,42.9554862976],"type":"Point"}
}