{
  "type": "Feature",
  "properties": {
    "addr:full":"Calle de Nuria, 59 Madrid Madrid 28034",
    "addr:housenumber":"59",
    "addr:postcode":"madrid;28034",
    "addr:street":"Calle De Nuria",
    "iso:country":"ES",
    "sg:address":"Calle de Nuria, 59",
    "sg:city":"Madrid",
    "sg:orig_category":"Fabricaci\u00d3n, Venta De Cuadros, Accesorios Para Enmarcar",
    "sg:phone":"+34 913 72 01 11",
    "sg:postcode":"28034",
    "sg:province":"Madrid",
    "wof:name":"Municio Garcia Rosa Maria",
    "wof:placetype":"venue"
},
  "geometry": {"coordinates":[-3.7111909389,40.495010376],"type":"Point"}
}