{
  "type": "Feature",
  "properties": {
    "addr:full":"Calle de Luis I, 43 Madrid Madrid 28031",
    "addr:housenumber":"43",
    "addr:postcode":"madrid;28031",
    "addr:street":"Calle De Luis I",
    "iso:country":"ES",
    "sg:address":"Calle de Luis I, 43",
    "sg:city":"Madrid",
    "sg:orig_category":"Servicios De Telecomunicaciones",
    "sg:phone":"+34 913 80 64 40",
    "sg:postcode":"28031",
    "sg:province":"Madrid",
    "sg:website":"wwwemtesistemas.com",
    "wof:name":"Emte Sistemas S. A.",
    "wof:placetype":"venue"
},
  "geometry": {"coordinates":[-3.6448779106,40.375453949],"type":"Point"}
}