{
  "type": "Feature",
  "properties": {
    "addr:full":"Calle de Don Juan Diego De Dios Barrero, S/n Linares Ja\u00e9n 23700",
    "addr:housenumber":"s / n",
    "addr:postcode":"23700",
    "addr:street":"Calle De Don Juan Diego De Dios Barrero;Jae\u0301N",
    "iso:country":"ES",
    "sg:address":"Calle de Don Juan Diego De Dios Barrero, S/n",
    "sg:city":"Linares",
    "sg:orig_category":"M\u00c1rmoles, Granitos Y Piedras Naturales",
    "sg:phone":"+34 953 69 55 46",
    "sg:postcode":"23700",
    "sg:province":"Ja\u00e9n",
    "wof:name":"Contreras Garcia Luis Andres",
    "wof:placetype":"venue"
},
  "geometry": {"coordinates":[-3.6356039047,38.093914032],"type":"Point"}
}