{
  "type": "Feature",
  "properties": {
    "iso:country":"ES",
    "sg:address":"Maritimo, S/n",
    "sg:city":"Playas Fa\u00f1abe",
    "sg:orig_category":"Oficinas De Turismo, Asociaciones De Iniciativa",
    "sg:phone":"+34 922 71 65 39",
    "sg:postcode":"38660",
    "sg:province":"Santa Cruz De Tenerife",
    "wof:name":"Ayuntamiento De Adeje",
    "wof:placetype":"venue"
},
  "geometry": {"coordinates":[-16.2548561096,28.4698104858],"type":"Point"}
}