{
  "type": "Feature",
  "properties": {
    "addr:full":"Plaz General Franco, 2 Jarilla C\u00e1ceres 10728",
    "addr:housenumber":"2",
    "addr:postcode":"10728",
    "addr:street":"Franco;Ca\u0301Ceres",
    "iso:country":"ES",
    "sg:address":"Plaz General Franco, 2",
    "sg:city":"Jarilla",
    "sg:orig_category":"Administraciones Regionales, Departamentales Y Locales",
    "sg:phone":"+34 927 47 70 00",
    "sg:postcode":"10728",
    "sg:province":"C\u00e1ceres",
    "wof:name":"Ayuntamiento De Jarilla",
    "wof:placetype":"venue"
},
  "geometry": {"coordinates":[-6.0025019646,40.172958374],"type":"Point"}
}