{
  "type": "Feature",
  "properties": {
    "addr:full":"Calle de Fuerte, 26 Badajoz Badajoz 06010",
    "addr:housenumber":"26",
    "addr:postcode":"06010",
    "addr:street":"Calle De Fuerte",
    "iso:country":"ES",
    "sg:address":"Calle de Fuerte, 26",
    "sg:city":"Badajoz",
    "sg:orig_category":"Peluquer\u00cdas, Peluquer\u00cda Mixta",
    "sg:phone":"+34 924 22 43 51",
    "sg:postcode":"06010",
    "sg:province":"Badajoz",
    "wof:name":"Alvarez-noriega Cb",
    "wof:placetype":"venue"
},
  "geometry": {"coordinates":[-6.9715852737,38.8681526184],"type":"Point"}
}