{
  "type": "Feature",
  "properties": {
    "addr:full":"Calle de Isla La, 13 Pola De Siero Asturias 33510",
    "addr:housenumber":"13",
    "addr:postcode":"33510",
    "addr:street":"Calle De Isla La",
    "iso:country":"ES",
    "sg:address":"Calle de Isla La, 13",
    "sg:city":"Pola De Siero",
    "sg:orig_category":"Empresas De Pintura Y Revestimientos",
    "sg:phone":"+34 985 72 08 45",
    "sg:postcode":"33510",
    "sg:province":"Asturias",
    "wof:name":"Vera Morales Teresa",
    "wof:placetype":"venue"
},
  "geometry": {"coordinates":[-5.6643872261,43.3898925781],"type":"Point"}
}