{
  "type": "Feature",
  "properties": {
    "addr:full":"Plaz Olmo (el), 4 Tarazona Mancha Albacete 02100",
    "addr:postcode":"02100",
    "addr:street":"Plaz;El",
    "iso:country":"ES",
    "sg:address":"Plaz Olmo (el), 4",
    "sg:city":"Tarazona Mancha",
    "sg:orig_category":"Empresas De Limpieza",
    "sg:phone":"+34 967 48 08 88",
    "sg:postcode":"02100",
    "sg:province":"Albacete",
    "wof:name":"Martinez Lopez Julian",
    "wof:placetype":"venue"
},
  "geometry": {"coordinates":[-1.9125390053,39.2651023865],"type":"Point"}
}