{
  "type": "Feature",
  "properties": {
    "iso:country":"ES",
    "sg:address":"Rua Pi Y Margall, 60",
    "sg:city":"Vigo",
    "sg:orig_category":"Agencias Y Agentes Comerciales, Representantes",
    "sg:phone":"+34 986 23 60 90",
    "sg:postcode":"36202",
    "sg:province":"Pontevedra",
    "wof:name":"Fernafer Vigo S.l.",
    "wof:placetype":"venue"
},
  "geometry": {"coordinates":[-8.7309751511,42.2321472168],"type":"Point"}
}