{
  "type": "Feature",
  "properties": {
    "addr:full":"Ctra Moraira A Calpe, S/n Moraira Alicante 03724",
    "addr:housenumber":"s / n",
    "addr:postcode":"03724",
    "addr:street":"Ctra Moraira A Calpe",
    "iso:country":"ES",
    "sg:address":"Ctra Moraira A Calpe, S/n",
    "sg:city":"Moraira",
    "sg:orig_category":"Bancos",
    "sg:phone":"+34 966 49 17 70",
    "sg:postcode":"03724",
    "sg:province":"Alicante",
    "wof:name":"Banca March S.a.",
    "wof:placetype":"venue"
},
  "geometry": {"coordinates":[0.1245080009,38.6858901978],"type":"Point"}
}