{
  "type": "Feature",
  "properties": {
    "iso:country":"ES",
    "sg:address":"Avda Ntra. Sra. De Valvanera, 38",
    "sg:city":"Calahorra",
    "sg:orig_category":"Asesor\u00cdas Y Estudios Financieros",
    "sg:phone":"+34 941 13 58 94",
    "sg:postcode":"26500",
    "sg:province":"La Rioja",
    "sg:website":"www.creditcb.com",
    "wof:name":"Ab-cg Consultores Financieros S.l.",
    "wof:placetype":"venue"
},
  "geometry": {"coordinates":[-1.968583,42.278561],"type":"Point"}
}