{
  "type": "Feature",
  "properties": {
    "addr:full":"Calle de Pajares, 8 Jerez De La Frontera C\u00e1diz 11406",
    "addr:housenumber":"8",
    "addr:postcode":"11406",
    "addr:street":"Calle De Pajares",
    "iso:country":"ES",
    "sg:address":"Calle de Pajares, 8",
    "sg:city":"Jerez De La Frontera",
    "sg:orig_category":"Supermercados Y Hipermercados",
    "sg:phone":"+34 956 32 06 29",
    "sg:postcode":"11406",
    "sg:province":"C\u00e1diz",
    "wof:name":"Cirera Molina Jose Antonio",
    "wof:placetype":"venue"
},
  "geometry": {"coordinates":[-6.1087460518,36.6872177124],"type":"Point"}
}