{
  "type": "Feature",
  "properties": {
    "addr:full":"Villaperez, 155 Oviedo Asturias 33099",
    "addr:housenumber":"155",
    "addr:postcode":"33099",
    "addr:street":"Villaperez",
    "iso:country":"ES",
    "sg:address":"Villaperez, 155",
    "sg:city":"Oviedo",
    "sg:orig_category":"Producci\u00d3n De Champi\u00d1ones",
    "sg:phone":"+34 985 29 41 74",
    "sg:postcode":"33099",
    "sg:province":"Asturias",
    "wof:name":"Setas Quiros S.l.",
    "wof:placetype":"venue"
},
  "geometry": {"coordinates":[-5.8259601593,43.394077301],"type":"Point"}
}