{
  "type": "Feature",
  "properties": {
    "iso:country":"ES",
    "sg:address":"Av Madrid, 8",
    "sg:city":"Vilafortuny",
    "sg:orig_category":"Abogados",
    "sg:phone":"+34 977 36 51 39",
    "sg:postcode":"43850",
    "sg:province":"Tarragona",
    "wof:name":"Prieto Rodriguez Javier Ignacio",
    "wof:placetype":"venue"
},
  "geometry": {"coordinates":[1.0973609686,41.0745544434],"type":"Point"}
}