{
  "type": "Feature",
  "properties": {
    "iso:country":"ES",
    "sg:address":"Nuestra Se\u00f1ora De Gracia, S/n",
    "sg:city":"Alhaurin Grande",
    "sg:orig_category":"Zapatos (al Por Menor)",
    "sg:phone":"+34 952 49 09 26",
    "sg:postcode":"29120",
    "sg:province":"M\u00e1laga",
    "wof:name":"Gonzalez Vallejo Dativo",
    "wof:placetype":"venue"
},
  "geometry": {"coordinates":[-4.6863107681,36.642036438],"type":"Point"}
}