{
  "type": "Feature",
  "properties": {
    "iso:country":"ES",
    "sg:address":"Carr Monturiol, 3",
    "sg:city":"Figueres",
    "sg:classifiers":[
        {
            "category":"Casinos & Gambling",
            "type":"Entertainment"
        }
    ],
    "sg:phone":"+34 972 50 04 91",
    "sg:postcode":"17600",
    "sg:province":"Girona",
    "sg:tags":[
        "locale",
        "de",
        "juego"
    ],
    "wof:name":"Cercle Sport Figuerenc",
    "wof:placetype":"venue"
},
  "geometry": {"coordinates":[2.9623880386,42.2668762207],"type":"Point"}
}