{
  "type": "Feature",
  "properties": {
    "iso:country":"ES",
    "sg:address":"Carr Verge De L'oreto, 5",
    "sg:city":"Alcudia",
    "sg:orig_category":"Quincaller\u00cda (al Por Menor)",
    "sg:phone":"+34 962 99 70 43",
    "sg:postcode":"46250",
    "sg:province":"Valencia",
    "wof:name":"Luisa Alegre S.l.",
    "wof:placetype":"venue"
},
  "geometry": {"coordinates":[-0.530508697,39.1895713806],"type":"Point"}
}