{
  "type": "Feature",
  "properties": {
    "iso:country":"ES",
    "sg:address":"Calle de Ca\u00d1ada Del Herrero, 23",
    "sg:city":"S. Sebastian Gomera",
    "sg:orig_category":"Chapister\u00cda",
    "sg:phone":"+34 922 87 12 04",
    "sg:postcode":"38800",
    "sg:province":"Santa Cruz De Tenerife",
    "wof:name":"Fernandez Herrera Santiago Manuel",
    "wof:placetype":"venue"
},
  "geometry": {"coordinates":[-17.1170940399,28.0910415649],"type":"Point"}
}