{
  "type": "Feature",
  "properties": {
    "iso:country":"ES",
    "sg:address":"Avda Santa Apolonia, S/n",
    "sg:city":"Monte Vedat",
    "sg:orig_category":"Ropa Para Beb\u00c9s Y Ni\u00d1os (confecci\u00d3n, Al Por Mayor)",
    "sg:phone":"+34 961 58 06 03",
    "sg:postcode":"46901",
    "sg:province":"Valencia",
    "wof:name":"De Miguel Go\u00f1i Maximo",
    "wof:placetype":"venue"
},
  "geometry": {"coordinates":[-0.4868929982,39.4098129272],"type":"Point"}
}