{
  "type": "Feature",
  "properties": {
    "iso:country":"ES",
    "sg:address":"Calle de Peligro Del, 4",
    "sg:city":"Torremolinos",
    "sg:orig_category":"Centros Empresariales",
    "sg:phone":"+34 952 38 88 51",
    "sg:postcode":"29620",
    "sg:province":"M\u00e1laga",
    "wof:name":"Mahesh Pradeep",
    "wof:placetype":"venue"
},
  "geometry": {"coordinates":[-4.4962568283,36.6224822998],"type":"Point"}
}