{
  "type": "Feature",
  "properties": {
    "addr:full":"Plaz Espa\u00d1a, 45 Torreblanca Castell\u00f3n 12596",
    "addr:housenumber":"45",
    "addr:postcode":"12596",
    "addr:street":"Plaz Espan\u0303A;Castello\u0301N",
    "iso:country":"ES",
    "sg:address":"Plaz Espa\u00d1a, 45",
    "sg:city":"Torreblanca",
    "sg:orig_category":"Supermercados Y Hipermercados",
    "sg:phone":"+34 964 42 14 49",
    "sg:postcode":"12596",
    "sg:province":"Castell\u00f3n",
    "wof:name":"Supermercado Simo C.b.",
    "wof:placetype":"venue"
},
  "geometry": {"coordinates":[0.1960400045,40.2205581665],"type":"Point"}
}