{
  "type": "Feature",
  "properties": {
    "addr:full":"Calle de Mesones, 57 Granada Granada 18001",
    "addr:housenumber":"57",
    "addr:postcode":"18001",
    "addr:street":"Calle De Mesones",
    "iso:country":"ES",
    "sg:address":"Calle de Mesones, 57",
    "sg:city":"Granada",
    "sg:orig_category":"Ropa Para Ni\u00d1os (al Por Menor)",
    "sg:phone":"+34 958 26 37 37",
    "sg:postcode":"18001",
    "sg:province":"Granada",
    "wof:name":"Garcia Torreblanca Maria Carolina",
    "wof:placetype":"venue"
},
  "geometry": {"coordinates":[-3.6012489796,37.1757469177],"type":"Point"}
}