{
  "type": "Feature",
  "properties": {
    "iso:country":"ES",
    "sg:address":"Ctra. Calonge, S/n",
    "sg:city":"Bisbal Emporda",
    "sg:orig_category":"Ense\u00d1anza Agr\u00cdcola",
    "sg:phone":"+34 972 64 40 26",
    "sg:postcode":"17100",
    "sg:province":"Girona",
    "wof:name":"Colonies R.v.s.a.",
    "wof:placetype":"venue"
},
  "geometry": {"coordinates":[3.0360000134,41.9629936218],"type":"Point"}
}