{
  "type": "Feature",
  "properties": {
    "iso:country":"ES",
    "sg:address":"Avda Andalucia, 22",
    "sg:city":"Lanjaron",
    "sg:orig_category":"Cajas De Ahorro",
    "sg:phone":"+34 958 77 09 11",
    "sg:postcode":"18420",
    "sg:province":"Granada",
    "sg:website":"www.lacaixa.es",
    "wof:name":"Caixa D'estalvis I Pensions De Barcelona",
    "wof:placetype":"venue"
},
  "geometry": {"coordinates":[-3.485033989,36.9184837341],"type":"Point"}
}