{
  "type": "Feature",
  "properties": {
    "addr:full":"Calle de Guadiana, 4 Villarrubia C\u00f3rdoba 14710",
    "addr:housenumber":"4",
    "addr:postcode":"14710",
    "addr:street":"Calle De Guadiana;Co\u0301Rdoba",
    "iso:country":"ES",
    "sg:address":"Calle de Guadiana, 4",
    "sg:city":"Villarrubia",
    "sg:orig_category":"Mercer\u00cda, Lencer\u00cda (al Por Menor)",
    "sg:phone":"+34 957 32 70 22",
    "sg:postcode":"14710",
    "sg:province":"C\u00f3rdoba",
    "wof:name":"Soto Guerrero Manuel",
    "wof:placetype":"venue"
},
  "geometry": {"coordinates":[-4.9150328636,37.8488845825],"type":"Point"}
}