{
  "type": "Feature",
  "properties": {
    "iso:country":"ES",
    "sg:address":"Av Castell, 52",
    "sg:city":"Sant Marti Sarroca",
    "sg:orig_category":"Cine (producci\u00d3n, Realizaci\u00d3n)",
    "sg:phone":"+34 938 99 13 97",
    "sg:postcode":"08731",
    "sg:province":"Barcelona",
    "wof:name":"Grau-films-produccions S.l.",
    "wof:placetype":"venue"
},
  "geometry": {"coordinates":[1.6076799631,41.3840103149],"type":"Point"}
}