{
  "type": "Feature",
  "properties": {
    "addr:full":"Carrer de Jacint Verdaguer, 5 Valls Tarragona 43800",
    "addr:housenumber":"5",
    "addr:postcode":"43800",
    "addr:street":"Carrer De Jacint Verdaguer",
    "iso:country":"ES",
    "sg:address":"Carrer de Jacint Verdaguer, 5",
    "sg:city":"Valls",
    "sg:orig_category":"Promotores Constructores",
    "sg:phone":"+34 977 60 15 93",
    "sg:postcode":"43800",
    "sg:province":"Tarragona",
    "wof:name":"Montarelo S.l.",
    "wof:placetype":"venue"
},
  "geometry": {"coordinates":[1.2505949736,41.2871704102],"type":"Point"}
}