{
  "type": "Feature",
  "properties": {
    "addr:full":"Calle de Manufactura, 13 Mairena Aljarafe Sevilla 41927",
    "addr:housenumber":"13",
    "addr:postcode":"41927",
    "addr:street":"Calle De Manufactura",
    "iso:country":"ES",
    "sg:address":"Calle de Manufactura, 13",
    "sg:city":"Mairena Aljarafe",
    "sg:orig_category":"Alquiler De Veh\u00cdculos: Turismos Y Utilitarios",
    "sg:phone":"+34 954 18 47 62",
    "sg:postcode":"41927",
    "sg:province":"Sevilla",
    "sg:website":"www.atesa.es",
    "wof:name":"Atesa",
    "wof:placetype":"venue"
},
  "geometry": {"coordinates":[-6.0516543388,37.3582839966],"type":"Point"}
}