{
  "type": "Feature",
  "properties": {
    "iso:country":"ES",
    "sg:address":"Calle de Ramon Y Cajal, 1",
    "sg:city":"Leganes",
    "sg:orig_category":"Engranajes Y Elementos De Transmisi\u00d3n",
    "sg:phone":"+34 916 80 04 70",
    "sg:postcode":"28914",
    "sg:province":"Madrid",
    "wof:name":"Industrias Metalurgicas Del Engranaje S.l.",
    "wof:placetype":"venue"
},
  "geometry": {"coordinates":[-3.7426359653,40.3272323608],"type":"Point"}
}