{
  "type": "Feature",
  "properties": {
    "addr:full":"Plaz Cabildo (del), 8 Sanlucar De Barrameda C\u00e1diz 11540",
    "addr:postcode":"11540",
    "addr:street":"Del;Ca\u0301Diz",
    "iso:country":"ES",
    "sg:address":"Plaz Cabildo (del), 8",
    "sg:city":"Sanlucar De Barrameda",
    "sg:orig_category":"Notarios",
    "sg:phone":"+34 956 36 05 26",
    "sg:postcode":"11540",
    "sg:province":"C\u00e1diz",
    "wof:name":"Perez-beneyto Abad Antonio",
    "wof:placetype":"venue"
},
  "geometry": {"coordinates":[-6.3540239334,36.7788734436],"type":"Point"}
}