{
  "type": "Feature",
  "properties": {
    "addr:full":"Miguel Servet(p I Las Teresas), 19 Yecla Murcia 30510",
    "addr:housenumber":"19",
    "addr:postcode":"30510",
    "addr:street":"Miguel Servet P;Las",
    "iso:country":"ES",
    "sg:address":"Miguel Servet(p I Las Teresas), 19",
    "sg:city":"Yecla",
    "sg:orig_category":"Tapicer\u00cdas",
    "sg:phone":"+34 968 75 02 86",
    "sg:postcode":"30510",
    "sg:province":"Murcia",
    "wof:name":"Ta'quatro Dise\u00f1o S.l.",
    "wof:placetype":"venue"
},
  "geometry": {"coordinates":[-1.0713150501,38.6198692322],"type":"Point"}
}