{
  "type": "Feature",
  "properties": {
    "iso:country":"ES",
    "sg:address":"Avda Libertad De La, 37",
    "sg:city":"Donostia-san Sebastian",
    "sg:orig_category":"Art\u00cdculos De Regalo (al Por Menor)",
    "sg:phone":"+34 943 42 78 76",
    "sg:postcode":"20004",
    "sg:province":"Guip\u00f9zcoa",
    "wof:name":"Arrillaga Sanz Maria Luisa",
    "wof:placetype":"venue"
},
  "geometry": {"coordinates":[-1.983951211,43.3187561035],"type":"Point"}
}