{
  "type": "Feature",
  "properties": {
    "addr:full":"C/ Alfonso X El Sabio, 5 Elche Alicante 03203",
    "addr:housenumber":"5",
    "addr:postcode":"03203",
    "addr:street":"C / Alfonso X El Sabio",
    "iso:country":"ES",
    "sg:address":"C/ Alfonso X El Sabio, 5",
    "sg:city":"Elche",
    "sg:orig_category":"Arquitectos",
    "sg:phone":"+34 965 45 70 96",
    "sg:postcode":"03203",
    "sg:province":"Alicante",
    "wof:name":"Boix Matarredona Juan",
    "wof:placetype":"venue"
},
  "geometry": {"coordinates":[-0.6945490241,38.2653045654],"type":"Point"}
}