{
  "type": "Feature",
  "properties": {
    "iso:country":"ES",
    "sg:address":"Carrer de Gran De Gracia, 167",
    "sg:city":"Barcelona",
    "sg:orig_category":"Farmacias",
    "sg:phone":"+34 932 18 65 65",
    "sg:postcode":"08012",
    "sg:province":"Barcelona",
    "wof:name":"Tello Mu\u00f1oz Gema",
    "wof:placetype":"venue"
},
  "geometry": {"coordinates":[2.1522819996,41.4030075073],"type":"Point"}
}