{
  "type": "Feature",
  "properties": {
    "addr:full":"Avda Venezuela, 17 Fatima Santa Cruz De Tenerife 38750",
    "addr:housenumber":"17",
    "addr:postcode":"38750",
    "addr:street":"Avda Venezuela",
    "iso:country":"ES",
    "sg:address":"Avda Venezuela, 17",
    "sg:city":"Fatima",
    "sg:orig_category":"Supermercados Y Hipermercados",
    "sg:phone":"+34 922 48 65 24",
    "sg:postcode":"38750",
    "sg:province":"Santa Cruz De Tenerife",
    "wof:name":"Centros De Ahorro San Martin S.l.",
    "wof:placetype":"venue"
},
  "geometry": {"coordinates":[-17.8813228607,28.6505889893],"type":"Point"}
}