{
  "type": "Feature",
  "properties": {
    "addr:full":"Calle de Arriba, 85 Sorihuela Salamanca 37777",
    "addr:housenumber":"85",
    "addr:postcode":"37777",
    "addr:street":"Calle De Arriba",
    "iso:country":"ES",
    "sg:address":"Calle de Arriba, 85",
    "sg:city":"Sorihuela",
    "sg:orig_category":"M\u00c1rmoles, Granitos Y Piedras Naturales",
    "sg:phone":"+34 923 41 35 83",
    "sg:postcode":"37777",
    "sg:province":"Salamanca",
    "wof:name":"Hernandez Gonzalez Porfirio",
    "wof:placetype":"venue"
},
  "geometry": {"coordinates":[-5.6780109406,40.4425697327],"type":"Point"}
}