{
  "type": "Feature",
  "properties": {
    "addr:full":"Calle de Nueva, 11 Cuellar Segovia 40200",
    "addr:housenumber":"11",
    "addr:postcode":"40200",
    "addr:street":"Calle De Nueva",
    "iso:country":"ES",
    "sg:address":"Calle de Nueva, 11",
    "sg:city":"Cuellar",
    "sg:orig_category":"Pr\u00c9stamos Personales E Hipotecarios",
    "sg:phone":"+34 921 14 31 30",
    "sg:postcode":"40200",
    "sg:province":"Segovia",
    "wof:name":"Merino Espinar Belen",
    "wof:placetype":"venue"
},
  "geometry": {"coordinates":[-4.3142991066,41.4025382996],"type":"Point"}
}