{
  "type": "Feature",
  "properties": {
    "iso:country":"ES",
    "sg:address":"Ctra. Roca De La Sierra, Km. 0014,2",
    "sg:city":"Nava Santiago",
    "sg:orig_category":"Cr\u00cda De Animales",
    "sg:phone":"+34 924 12 30 95",
    "sg:postcode":"06486",
    "sg:province":"Badajoz",
    "wof:name":"Ganaver S.l.",
    "wof:placetype":"venue"
},
  "geometry": {"coordinates":[-6.5054402351,39.0615158081],"type":"Point"}
}