{
  "type": "Feature",
  "properties": {
    "addr:full":"Calle de Paraguay, 9 Vitoria-gasteiz \u00c1lava 01012",
    "addr:housenumber":"9",
    "addr:postcode":"01012",
    "addr:street":"Calle De Paraguay",
    "iso:country":"ES",
    "sg:address":"Calle de Paraguay, 9",
    "sg:city":"Vitoria-gasteiz",
    "sg:orig_category":"Muebles, Minoristas",
    "sg:phone":"+34 945 25 92 10",
    "sg:postcode":"01012",
    "sg:province":"\u00c1lava",
    "wof:name":"Nogales Del Pozo Evelio",
    "wof:placetype":"venue"
},
  "geometry": {"coordinates":[-2.6783089638,42.8573188782],"type":"Point"}
}