{
  "type": "Feature",
  "properties": {
    "iso:country":"ES",
    "sg:address":"Ctra Sevilla-utrera, Km. 0008,3",
    "sg:city":"Quinto",
    "sg:orig_category":"Contenedores (mercanc\u00cdas)",
    "sg:phone":"+34 954 12 46 00",
    "sg:postcode":"41089",
    "sg:province":"Sevilla",
    "sg:website":"www.garycia.com",
    "wof:name":"Transportes Gar Y Cia S.a.",
    "wof:placetype":"venue"
},
  "geometry": {"coordinates":[-5.9332537651,37.3442153931],"type":"Point"}
}