{
  "type": "Feature",
  "properties": {
    "addr:full":"Zezenbide Kalea, 9 Eibar Guip\u00f9zcoa 20600",
    "addr:housenumber":"9",
    "addr:postcode":"20600",
    "addr:street":"Zezenbide Kalea;Guipu\u0300Zcoa",
    "iso:country":"ES",
    "sg:address":"Zezenbide Kalea, 9",
    "sg:city":"Eibar",
    "sg:orig_category":"Librer\u00cdas",
    "sg:phone":"+34 943 20 22 30",
    "sg:postcode":"20600",
    "sg:province":"Guip\u00f9zcoa",
    "wof:name":"Zubillaga Urteaga I\u00f1aki",
    "wof:placetype":"venue"
},
  "geometry": {"coordinates":[-2.4738361835,43.1836128235],"type":"Point"}
}