{
  "type": "Feature",
  "properties": {
    "iso:country":"ES",
    "sg:address":"Calle de Gargantilla, 2",
    "sg:city":"Don Benito",
    "sg:orig_category":"Psic\u00d3logos",
    "sg:phone":"+34 924 81 17 18",
    "sg:postcode":"06400",
    "sg:province":"Badajoz",
    "wof:name":"Gonzalez Ca\u00f1amero Petra",
    "wof:placetype":"venue"
},
  "geometry": {"coordinates":[-5.8651475906,38.9542617798],"type":"Point"}
}