{
  "type": "Feature",
  "properties": {
    "iso:country":"ES",
    "sg:address":"Av Generalitat (la), 35",
    "sg:city":"S. Joan Despi",
    "sg:orig_category":"Bisuter\u00cda, Joyer\u00cda, Relojer\u00cda (al Por Menor)",
    "sg:phone":"+34 934 77 15 51",
    "sg:postcode":"08970",
    "sg:province":"Barcelona",
    "wof:name":"Joyeria Fina S.l.",
    "wof:placetype":"venue"
},
  "geometry": {"coordinates":[2.0629200935,41.370349884],"type":"Point"}
}