{
  "type": "Feature",
  "properties": {
    "addr:full":"Pg Sant Gervasi, 71 Barcelona Barcelona 08022",
    "addr:housenumber":"71",
    "addr:postcode":"08022",
    "addr:street":"Pg Sant Gervasi",
    "iso:country":"ES",
    "sg:address":"Pg Sant Gervasi, 71",
    "sg:city":"Barcelona",
    "sg:orig_category":"Asilos De Ancianos. Centros Privados",
    "sg:phone":"+34 934 17 06 29",
    "sg:postcode":"08022",
    "sg:province":"Barcelona",
    "wof:name":"Residencia Geriatrica San Gervasio S. L.",
    "wof:placetype":"venue"
},
  "geometry": {"coordinates":[2.1379129887,41.4122390747],"type":"Point"}
}