{
  "type": "Feature",
  "properties": {
    "iso:country":"ES",
    "sg:address":"Bidebarrieta Kalea, 7",
    "sg:city":"O\u00f1ati",
    "sg:orig_category":"M\u00c9dicos: Estomatolog\u00cda",
    "sg:phone":"+34 943 71 88 63",
    "sg:postcode":"20560",
    "sg:province":"Guip\u00f9zcoa",
    "wof:name":"Borlle Gonzalez Marcelo Walter",
    "wof:placetype":"venue"
},
  "geometry": {"coordinates":[-2.4132039547,43.0308303833],"type":"Point"}
}