{
  "type": "Feature",
  "properties": {
    "addr:full":"Calle de Cormoranes, 7 Pinto Madrid 28320",
    "addr:housenumber":"7",
    "addr:postcode":"28320",
    "addr:street":"Calle De Cormoranes;Pinto",
    "iso:country":"ES",
    "sg:address":"Calle de Cormoranes, 7",
    "sg:city":"Pinto",
    "sg:orig_category":"Cervezas (negociantes Y Depositarios)",
    "sg:phone":"+34 916 91 50 13",
    "sg:postcode":"28320",
    "sg:province":"Madrid",
    "wof:name":"Rubser Distribucion S.l.",
    "wof:placetype":"venue"
},
  "geometry": {"coordinates":[-3.7075541019,40.2478027344],"type":"Point"}
}