{
  "type": "Feature",
  "properties": {
    "iso:country":"ES",
    "sg:address":"Carrer de Berlines, 19",
    "sg:city":"Barcelona",
    "sg:orig_category":"Fabricaci\u00d3n De Telas Y Sedas",
    "sg:phone":"+34 934 18 78 56",
    "sg:postcode":"08022",
    "sg:province":"Barcelona",
    "wof:name":"Jm Tex 77 S.l.",
    "wof:placetype":"venue"
},
  "geometry": {"coordinates":[2.1385979652,41.4040641785],"type":"Point"}
}