{
  "type": "Feature",
  "properties": {
    "addr:full":"Cervantes, 5 Fuentes Cuenca 16193",
    "addr:housenumber":"5",
    "addr:postcode":"16193",
    "addr:street":"Cervantes",
    "iso:country":"ES",
    "sg:address":"Cervantes, 5",
    "sg:city":"Fuentes",
    "sg:orig_category":"Molduras, Junquillos, Listones Y Molduras Perforadas",
    "sg:phone":"+34 969 25 71 21",
    "sg:postcode":"16193",
    "sg:province":"Cuenca",
    "wof:name":"Atienza Atienza Maria De Los Angeles",
    "wof:placetype":"venue"
},
  "geometry": {"coordinates":[-2.0202763081,39.9486999512],"type":"Point"}
}