{
  "type": "Feature",
  "properties": {
    "addr:full":"Carrer de Sant Eduard, 16 S. Cugat Valles Barcelona 08172",
    "addr:housenumber":"16",
    "addr:postcode":"08172",
    "addr:street":"Carrer De Sant Eduard;S. Cugat Valles Barcelona",
    "iso:country":"ES",
    "sg:address":"Carrer de Sant Eduard, 16",
    "sg:city":"S. Cugat Valles",
    "sg:orig_category":"Asesor\u00cda Sobre Comunicaci\u00d3n De Empresas",
    "sg:phone":"+34 936 74 92 02",
    "sg:postcode":"08172",
    "sg:province":"Barcelona",
    "wof:name":"Carbonell Costa Jose",
    "wof:placetype":"venue"
},
  "geometry": {"coordinates":[2.087100029,41.466960907],"type":"Point"}
}