{
  "type": "Feature",
  "properties": {
    "addr:full":"Calle de Lurbeltzeta Kalea, 2 Zizur Mayor Navarra 31180",
    "addr:housenumber":"2",
    "addr:postcode":"31180",
    "addr:street":"Calle De Lurbeltzeta Kalea",
    "iso:country":"ES",
    "sg:address":"Calle de Lurbeltzeta Kalea, 2",
    "sg:city":"Zizur Mayor",
    "sg:orig_category":"Agencias De Viajes",
    "sg:phone":"+34 948 28 60 85",
    "sg:postcode":"31180",
    "sg:province":"Navarra",
    "wof:name":"Viajes Arga S.a.l.",
    "wof:placetype":"venue"
},
  "geometry": {"coordinates":[-1.6934520006,42.7867355347],"type":"Point"}
}