{
  "type": "Feature",
  "properties": {
    "addr:full":"Calle de Calatrava, 1 Albacete Albacete 02006",
    "addr:housenumber":"1",
    "addr:postcode":"02006",
    "addr:street":"Calle De Calatrava",
    "iso:country":"ES",
    "sg:address":"Calle de Calatrava, 1",
    "sg:city":"Albacete",
    "sg:orig_category":"Fabrica, Negocio De Vidrieras, Productos Vidriados Y Espejos",
    "sg:phone":"+34 967 50 75 39",
    "sg:postcode":"02006",
    "sg:province":"Albacete",
    "wof:name":"Hermanos Garcia Higueras S.l.l.",
    "wof:placetype":"venue"
},
  "geometry": {"coordinates":[-1.8722271919,38.9955673218],"type":"Point"}
}