{
  "type": "Feature",
  "properties": {
    "iso:country":"ES",
    "sg:address":"Carrer de Sant Eusebi, 63",
    "sg:city":"Barcelona",
    "sg:orig_category":"Ingenier\u00cda, Centros De Estudios (diversos)",
    "sg:phone":"+34 932 09 53 52",
    "sg:postcode":"08006",
    "sg:province":"Barcelona",
    "wof:name":"Hernandez Gras Francisco Javier",
    "wof:placetype":"venue"
},
  "geometry": {"coordinates":[2.1462459564,41.3993759155],"type":"Point"}
}