{
  "type": "Feature",
  "properties": {
    "iso:country":"ES",
    "sg:address":"Carrer de Major, 38",
    "sg:city":"Avinyo",
    "sg:orig_category":"Cr\u00cda De Bovinos",
    "sg:phone":"+34 938 38 72 01",
    "sg:postcode":"08279",
    "sg:province":"Barcelona",
    "wof:name":"Agropecuaria Gost S.c.p.",
    "wof:placetype":"venue"
},
  "geometry": {"coordinates":[1.9711709023,41.8642272949],"type":"Point"}
}