{
  "type": "Feature",
  "properties": {
    "addr:full":"Calle de Pe\u00d1as (las), 4 Vilches Ja\u00e9n 23220",
    "addr:housenumber":"4",
    "addr:postcode":"23220",
    "addr:street":"Calle De Pen\u0303As Las;Jae\u0301N",
    "iso:country":"ES",
    "sg:address":"Calle de Pe\u00d1as (las), 4",
    "sg:city":"Vilches",
    "sg:orig_category":"Telas Y Sedas (al Por Menor)",
    "sg:phone":"+34 953 63 00 27",
    "sg:postcode":"23220",
    "sg:province":"Ja\u00e9n",
    "wof:name":"Ruiz Pe\u00f1a Jose",
    "wof:placetype":"venue"
},
  "geometry": {"coordinates":[-3.5080580711,38.2046318054],"type":"Point"}
}