{
  "type": "Feature",
  "properties": {
    "addr:full":"Calle de Virgen De La Salud, 15 Xirivella Valencia 46950",
    "addr:housenumber":"15",
    "addr:postcode":"46950",
    "addr:street":"Calle De Virgen De La Salud",
    "iso:country":"ES",
    "sg:address":"Calle de Virgen De La Salud, 15",
    "sg:city":"Xirivella",
    "sg:orig_category":"Carnicer\u00cdas, Carnicer\u00cdas",
    "sg:phone":"+34 963 70 91 50",
    "sg:postcode":"46950",
    "sg:province":"Valencia",
    "wof:name":"Ortiz Guillot Josefa",
    "wof:placetype":"venue"
},
  "geometry": {"coordinates":[-0.4266279936,39.4654769897],"type":"Point"}
}