{
  "type": "Feature",
  "properties": {
    "iso:country":"ES",
    "sg:address":"Avda Espa\u00d1a (de), 40",
    "sg:city":"Alcobendas",
    "sg:orig_category":"Electricidad: Instaladores",
    "sg:phone":"+34 916 52 71 59",
    "sg:postcode":"28100",
    "sg:province":"Madrid",
    "wof:name":"Cid Calvo Epifanio",
    "wof:placetype":"venue"
},
  "geometry": {"coordinates":[-3.6396319866,40.5475273132],"type":"Point"}
}