{
  "type": "Feature",
  "properties": {
    "iso:country":"ES",
    "sg:address":"Carrer de Maquinista, 50",
    "sg:city":"Barcelona",
    "sg:orig_category":"Peluquer\u00cdas, Peluquer\u00cda Mixta",
    "sg:phone":"+34 933 10 11 60",
    "sg:postcode":"08003",
    "sg:province":"Barcelona",
    "wof:name":"Jimenez Rojas Wenceslao",
    "wof:placetype":"venue"
},
  "geometry": {"coordinates":[2.1901319027,41.3809776306],"type":"Point"}
}