{
  "type": "Feature",
  "properties": {
    "iso:country":"ES",
    "sg:address":"Carrer de Taxdirt, 16",
    "sg:city":"Barcelona",
    "sg:orig_category":"Empresarios",
    "sg:phone":"+34 932 84 46 79",
    "sg:postcode":"08025",
    "sg:province":"Barcelona",
    "wof:name":"Escram 99 S.l.",
    "wof:placetype":"venue"
},
  "geometry": {"coordinates":[2.1657629013,41.4088058472],"type":"Point"}
}