{
  "type": "Feature",
  "properties": {
    "iso:country":"ES",
    "sg:address":"Calle de Pintor Rafael Solbes, 3",
    "sg:city":"Valencia",
    "sg:orig_category":"Contenedores (mercanc\u00cdas)",
    "sg:phone":"+34 963 77 00 10",
    "sg:postcode":"46017",
    "sg:province":"Valencia",
    "wof:name":"Trans Voluminosos Prieto S.l.",
    "wof:placetype":"venue"
},
  "geometry": {"coordinates":[-0.3892816007,39.4397544861],"type":"Point"}
}