{
  "type": "Feature",
  "properties": {
    "addr:full":"Calle de Cinca, 19 Madrid Madrid 28002",
    "addr:housenumber":"19",
    "addr:postcode":"madrid;28002",
    "addr:street":"Calle De Cinca",
    "iso:country":"ES",
    "sg:address":"Calle de Cinca, 19",
    "sg:city":"Madrid",
    "sg:orig_category":"Servidores Y Editores De Bases De Datos",
    "sg:phone":"+34 917 45 05 45",
    "sg:postcode":"28002",
    "sg:province":"Madrid",
    "sg:website":"www.movilisto.com",
    "wof:name":"Movilisto S. A.",
    "wof:placetype":"venue"
},
  "geometry": {"coordinates":[-3.6799902916,40.4493370056],"type":"Point"}
}