{
  "type": "Feature",
  "properties": {
    "iso:country":"ES",
    "sg:address":"Carrer de Valencia, 539",
    "sg:city":"Barcelona",
    "sg:orig_category":"Ropa Para Se\u00d1oras (al Por Menor)",
    "sg:phone":"+34 932 32 94 18",
    "sg:postcode":"08013",
    "sg:province":"Barcelona",
    "wof:name":"Carrasco Mansilla Maria Del Carmen",
    "wof:placetype":"venue"
},
  "geometry": {"coordinates":[2.1818730831,41.4068260193],"type":"Point"}
}