{
  "type": "Feature",
  "properties": {
    "addr:full":"Calle de Oliva, 5 Villaviciosa Asturias 33300",
    "addr:housenumber":"5",
    "addr:postcode":"33300",
    "addr:street":"Calle De Oliva",
    "iso:country":"ES",
    "sg:address":"Calle de Oliva, 5",
    "sg:city":"Villaviciosa",
    "sg:orig_category":"Agencias Y Agentes Comerciales, Representantes",
    "sg:phone":"+34 985 89 32 74",
    "sg:postcode":"33300",
    "sg:province":"Asturias",
    "wof:name":"Sanchez Blanco Maria Del Carmen",
    "wof:placetype":"venue"
},
  "geometry": {"coordinates":[-5.4379777908,43.4835166931],"type":"Point"}
}