{
  "type": "Feature",
  "properties": {
    "addr:full":"Pl Sant Jordi, 1 Sant Vicen\u00c7 Dels Horts Barcelona 08620",
    "addr:housenumber":"1",
    "addr:postcode":"08620",
    "addr:street":"Pl Sant Jordi",
    "iso:country":"ES",
    "sg:address":"Pl Sant Jordi, 1",
    "sg:city":"Sant Vicen\u00c7 Dels Horts",
    "sg:orig_category":"Clases De M\u00dasica Y Canto",
    "sg:phone":"+34 936 76 98 43",
    "sg:postcode":"08620",
    "sg:province":"Barcelona",
    "wof:name":"Roses Vidal Elena",
    "wof:placetype":"venue"
},
  "geometry": {"coordinates":[2.0100400448,41.3932189941],"type":"Point"}
}