{
  "type": "Feature",
  "properties": {
    "addr:full":"Calle de Rodriguez Arias, 46 Bilbao Vizcaya 48011",
    "addr:housenumber":"46",
    "addr:postcode":"48011",
    "addr:street":"Calle De Rodriguez Arias",
    "iso:country":"ES",
    "sg:address":"Calle de Rodriguez Arias, 46",
    "sg:city":"Bilbao",
    "sg:classifiers":[
        {
            "category":"Personal",
            "subcategory":"Barber",
            "type":"Services"
        }
    ],
    "sg:phone":"+34 944 42 26 80",
    "sg:postcode":"48011",
    "sg:province":"Vizcaya",
    "sg:tags":[
        "caballeros",
        "de",
        "peluqueros"
    ],
    "wof:name":"Alonso San Martin Jon",
    "wof:placetype":"venue"
},
  "geometry": {"coordinates":[-2.9414916039,43.2632789612],"type":"Point"}
}