{
  "type": "Feature",
  "properties": {
    "addr:full":"C/ La Penya, 16 Paterna Valencia 46980",
    "addr:housenumber":"16",
    "addr:postcode":"46980",
    "addr:street":"C / La Penya",
    "iso:country":"ES",
    "sg:address":"C/ La Penya, 16",
    "sg:city":"Paterna",
    "sg:orig_category":"Electricidad: Instaladores",
    "sg:phone":"+34 963 49 99 88",
    "sg:postcode":"46980",
    "sg:province":"Valencia",
    "wof:name":"Instalaciones Electricas Reinsa S. L.",
    "wof:placetype":"venue"
},
  "geometry": {"coordinates":[-0.4308150113,39.4965934753],"type":"Point"}
}