{
  "type": "Feature",
  "properties": {
    "addr:full":"Calle de Alpedrete, 11 Madrid Madrid 28045",
    "addr:housenumber":"11",
    "addr:postcode":"madrid;28045",
    "addr:street":"Calle De Alpedrete",
    "iso:country":"ES",
    "sg:address":"Calle de Alpedrete, 11",
    "sg:city":"Madrid",
    "sg:orig_category":"Asesor\u00cda Sobre Comunicaci\u00d3n De Empresas",
    "sg:phone":"+34 915 27 56 13",
    "sg:postcode":"28045",
    "sg:province":"Madrid",
    "wof:name":"Ingles Lopez Juan Antonio",
    "wof:placetype":"venue"
},
  "geometry": {"coordinates":[-3.6829462051,40.3989715576],"type":"Point"}
}