{
  "type": "Feature",
  "properties": {
    "addr:full":"Carrer de Badal, 16 Gandesa Tarragona 43780",
    "addr:housenumber":"16",
    "addr:postcode":"43780",
    "addr:street":"Carrer De Badal",
    "iso:country":"ES",
    "sg:address":"Carrer de Badal, 16",
    "sg:city":"Gandesa",
    "sg:orig_category":"Carnicer\u00cdas, Carnicer\u00cdas",
    "sg:phone":"+34 977 42 10 45",
    "sg:postcode":"43780",
    "sg:province":"Tarragona",
    "wof:name":"Blanch Blanch Antonio",
    "wof:placetype":"venue"
},
  "geometry": {"coordinates":[0.4387840033,41.0526885986],"type":"Point"}
}