{
  "type": "Feature",
  "properties": {
    "iso:country":"ES",
    "sg:address":"Avda Xunqueira (a), 17",
    "sg:city":"Reibon",
    "sg:orig_category":"Casas Con Estructura De Madera",
    "sg:phone":"+34 986 39 31 39",
    "sg:postcode":"36955",
    "sg:province":"Pontevedra",
    "wof:name":"Paredes Rivas Isabel",
    "wof:placetype":"venue"
},
  "geometry": {"coordinates":[-8.7202234268,42.2883415222],"type":"Point"}
}