{
  "type": "Feature",
  "properties": {
    "addr:full":"Calle de San Isidro, 20 Villa Prado Madrid 28630",
    "addr:housenumber":"20",
    "addr:postcode":"28630",
    "addr:street":"Calle De San Isidro",
    "iso:country":"ES",
    "sg:address":"Calle de San Isidro, 20",
    "sg:city":"Villa Prado",
    "sg:orig_category":"Art\u00cdculos Funerarios (al Por Menor)",
    "sg:phone":"+34 918 62 04 36",
    "sg:postcode":"28630",
    "sg:province":"Madrid",
    "wof:name":"Garcia Adrada Jose",
    "wof:placetype":"venue"
},
  "geometry": {"coordinates":[-4.4084892273,40.362121582],"type":"Point"}
}