{
  "type": "Feature",
  "properties": {
    "iso:country":"ES",
    "sg:address":"Carrer de Pont, 30",
    "sg:city":"Castellar Valles",
    "sg:orig_category":"Empresas De Carpinter\u00cda Met\u00c1lica",
    "sg:phone":"+34 937 14 83 38",
    "sg:postcode":"08211",
    "sg:province":"Barcelona",
    "wof:name":"Hierros Y Estructuras Simon,s.l",
    "wof:placetype":"venue"
},
  "geometry": {"coordinates":[2.0817260742,41.6151657104],"type":"Point"}
}