{
  "type": "Feature",
  "properties": {
    "iso:country":"ES",
    "sg:address":"Plaz Iglesia, 21",
    "sg:city":"G\u00fcejar-sierra",
    "sg:orig_category":"Iglesia Cat\u00d3lica",
    "sg:phone":"+34 958 48 45 42",
    "sg:postcode":"18160",
    "sg:province":"Granada",
    "wof:name":"Parroquia Nuestra Se\u00f1ora Del Rosario",
    "wof:placetype":"venue"
},
  "geometry": {"coordinates":[-3.4379739761,37.1602554321],"type":"Point"}
}