{
  "type": "Feature",
  "properties": {
    "addr:full":"Carr Requesens, 124 Empuriabrava Girona 17487",
    "addr:housenumber":"124",
    "addr:postcode":"17487",
    "addr:street":"Carr Requesens",
    "iso:country":"ES",
    "sg:address":"Carr Requesens, 124",
    "sg:city":"Empuriabrava",
    "sg:orig_category":"Caf\u00c9s, Bares, Cervecer\u00cdas",
    "sg:phone":"+34 972 45 40 29",
    "sg:postcode":"17487",
    "sg:province":"Girona",
    "wof:name":"Burset Gmur Devorah",
    "wof:placetype":"venue"
},
  "geometry": {"coordinates":[3.1218221188,42.2435417175],"type":"Point"}
}