{
  "type": "Feature",
  "properties": {
    "addr:full":"Partida Galandu, S/n Torres Alicante 03570",
    "addr:housenumber":"s / n",
    "addr:postcode":"03570",
    "addr:street":"Partida Galandu",
    "iso:country":"ES",
    "sg:address":"Partida Galandu, S/n",
    "sg:city":"Torres",
    "sg:orig_category":"Pompas F\u00danebres, Inhumaciones Y Cremaciones",
    "sg:phone":"+34 965 89 58 58",
    "sg:postcode":"03570",
    "sg:province":"Alicante",
    "wof:name":"Funeraria Selles S.l.",
    "wof:placetype":"venue"
},
  "geometry": {"coordinates":[-0.2274650037,38.5131645203],"type":"Point"}
}