{
  "type": "Feature",
  "properties": {
    "addr:full":"Carrer de Germa Doroteo, 4 Mataro Barcelona 08303",
    "addr:housenumber":"4",
    "addr:postcode":"08303",
    "addr:street":"Carrer De Germa Doroteo",
    "iso:country":"ES",
    "sg:address":"Carrer de Germa Doroteo, 4",
    "sg:city":"Mataro",
    "sg:orig_category":"Molduras, Junquillos, Listones Y Molduras Perforadas",
    "sg:phone":"+34 937 99 51 84",
    "sg:postcode":"08303",
    "sg:province":"Barcelona",
    "wof:name":"Audifonos Y Telefonos S.l.",
    "wof:placetype":"venue"
},
  "geometry": {"coordinates":[2.4220499992,41.5406684875],"type":"Point"}
}