{
  "type": "Feature",
  "properties": {
    "iso:country":"ES",
    "sg:address":"Avda Madrid De, 32",
    "sg:city":"Donostia-san Sebastian",
    "sg:orig_category":"Ingeniero",
    "sg:phone":"+34 943 46 50 76",
    "sg:postcode":"20011",
    "sg:province":"Guip\u00f9zcoa",
    "wof:name":"Estanislao Narbaiza Guridi",
    "wof:placetype":"venue"
},
  "geometry": {"coordinates":[-1.9756070375,43.3031654358],"type":"Point"}
}