{
  "type": "Feature",
  "properties": {
    "iso:country":"ES",
    "sg:address":"Calle de Madrid, 1",
    "sg:city":"Ejido",
    "sg:orig_category":"Transporte En General",
    "sg:phone":"+34 950 57 33 52",
    "sg:postcode":"04700",
    "sg:province":"Almer\u00eda",
    "wof:name":"Logistica Hunisa S.a",
    "wof:placetype":"venue"
},
  "geometry": {"coordinates":[-2.8126759529,36.7734222412],"type":"Point"}
}