{
  "type": "Feature",
  "properties": {
    "addr:full":"Carrer de Paisos Catalans, 16 Ametlla Mar Tarragona 43860",
    "addr:housenumber":"16",
    "addr:postcode":"43860",
    "addr:street":"Carrer De Paisos Catalans",
    "iso:country":"ES",
    "sg:address":"Carrer de Paisos Catalans, 16",
    "sg:city":"Ametlla Mar",
    "sg:orig_category":"Asociaciones Y Clubs Deportivos",
    "sg:phone":"+34 977 45 60 39",
    "sg:postcode":"43860",
    "sg:province":"Tarragona",
    "wof:name":"Sociedad Cultural Deportiva Y Recreativa",
    "wof:placetype":"venue"
},
  "geometry": {"coordinates":[0.803722024,40.8838386536],"type":"Point"}
}