{
  "type": "Feature",
  "properties": {
    "iso:country":"ES",
    "sg:address":"Calle de Constitucion, 22",
    "sg:city":"Solana Del Pino",
    "sg:orig_category":"Iglesia Cat\u00d3lica",
    "sg:phone":"+34 926 48 50 29",
    "sg:postcode":"13593",
    "sg:province":"Ciudad Real",
    "wof:name":"Parroquia De La Inmaculada Concepcion",
    "wof:placetype":"venue"
},
  "geometry": {"coordinates":[-4.0714964867,38.4654426575],"type":"Point"}
}