{
  "type": "Feature",
  "properties": {
    "addr:full":"Calle de Sangenis, 1 Zaragoza Zaragoza 50010",
    "addr:housenumber":"1",
    "addr:postcode":"50010",
    "addr:street":"Calle De Sangenis",
    "iso:country":"ES",
    "sg:address":"Calle de Sangenis, 1",
    "sg:city":"Zaragoza",
    "sg:orig_category":"Cajas De Ahorro",
    "sg:phone":"+34 976 53 54 56",
    "sg:postcode":"50010",
    "sg:province":"Zaragoza",
    "wof:name":"Caja De Ahorros De La Inmaculada",
    "wof:placetype":"venue"
},
  "geometry": {"coordinates":[-0.9046090245,41.6532669067],"type":"Point"}
}