{
  "type": "Feature",
  "properties": {
    "addr:full":"Calle de San Martin, 23 Donostia-san Sebastian Guip\u00f9zcoa 20005",
    "addr:housenumber":"23",
    "addr:postcode":"20005",
    "addr:street":"Calle De San Martin",
    "iso:country":"ES",
    "sg:address":"Calle de San Martin, 23",
    "sg:city":"Donostia-san Sebastian",
    "sg:orig_category":"Trajes Y Adornos De Boda (confecci\u00d3n, Al Por Menor)",
    "sg:phone":"+34 943 42 15 13",
    "sg:postcode":"20005",
    "sg:province":"Guip\u00f9zcoa",
    "sg:website":"www.rosaclara.es",
    "wof:name":"Ines Paternina Y Miguel Courtois,s.l.",
    "wof:placetype":"venue"
},
  "geometry": {"coordinates":[-1.9829349518,43.316947937],"type":"Point"}
}