{
  "type": "Feature",
  "properties": {
    "addr:full":"Villa Adela, 6 Canals Valencia 46650",
    "addr:housenumber":"6",
    "addr:postcode":"46650",
    "addr:street":"Adela",
    "iso:country":"ES",
    "sg:address":"Villa Adela, 6",
    "sg:city":"Canals",
    "sg:orig_category":"Negocio De Materiales De Construcci\u00d3n",
    "sg:phone":"+34 962 24 35 41",
    "sg:postcode":"46650",
    "sg:province":"Valencia",
    "wof:name":"Materiales De Construccion Fco. Jose Gimenez S.l.",
    "wof:placetype":"venue"
},
  "geometry": {"coordinates":[-0.588168025,38.9644203186],"type":"Point"}
}