{
  "type": "Feature",
  "properties": {
    "addr:full":"Constitucion, S/n Galdar Las Palmas 35460",
    "addr:housenumber":"/ n",
    "addr:postcode":"35460",
    "addr:street":"Constitucion S",
    "iso:country":"ES",
    "sg:address":"Constitucion, S/n",
    "sg:city":"Galdar",
    "sg:orig_category":"Centros P\u00dablicos De Formaci\u00d3n Profesional Y T\u00c9cnica",
    "sg:phone":"+34 928 55 24 77",
    "sg:postcode":"35460",
    "sg:province":"Las Palmas",
    "wof:name":"Comite Territorial De Las Pamas De Arbitros De Futbol",
    "wof:placetype":"venue"
},
  "geometry": {"coordinates":[-15.6645994186,28.139415741],"type":"Point"}
}