{
  "type": "Feature",
  "properties": {
    "addr:full":"Calle de Alfonso Xii, 48 Sevilla Sevilla 41002",
    "addr:housenumber":"48",
    "addr:postcode":"41002",
    "addr:street":"Calle De Alfonso Xii",
    "iso:country":"ES",
    "sg:address":"Calle de Alfonso Xii, 48",
    "sg:city":"Sevilla",
    "sg:orig_category":"Albergues",
    "sg:phone":"+34 954 90 87 15",
    "sg:postcode":"41002",
    "sg:province":"Sevilla",
    "wof:name":"Hellin Aguilar Reyes",
    "wof:placetype":"venue"
},
  "geometry": {"coordinates":[-5.9998807907,37.3931503296],"type":"Point"}
}