{
  "type": "Feature",
  "properties": {
    "addr:full":"Calle de Ibarrekolanda, 23 Bilbao Vizcaya 48015",
    "addr:housenumber":"23",
    "addr:postcode":"48015",
    "addr:street":"Calle De Ibarrekolanda",
    "iso:country":"ES",
    "sg:address":"Calle de Ibarrekolanda, 23",
    "sg:city":"Bilbao",
    "sg:orig_category":"Ingeniero",
    "sg:phone":"+34 944 47 01 27",
    "sg:postcode":"48015",
    "sg:province":"Vizcaya",
    "wof:name":"Ingenieria Tecnica Zurtek, S,l.",
    "wof:placetype":"venue"
},
  "geometry": {"coordinates":[-2.9559810162,43.2741622925],"type":"Point"}
}