{
  "type": "Feature",
  "properties": {
    "addr:full":"Alam Urquijo, 46 Bilbao Vizcaya 48011",
    "addr:housenumber":"46",
    "addr:postcode":"48011",
    "addr:street":"Alam Urquijo",
    "iso:country":"ES",
    "sg:address":"Alam Urquijo, 46",
    "sg:city":"Bilbao",
    "sg:orig_category":"Estilistas Y Estudios De Estilo De Corte Y Confecci\u00d3n",
    "sg:phone":"+34 944 22 12 90",
    "sg:postcode":"48011",
    "sg:province":"Vizcaya",
    "sg:website":"www.itxasomoda.com",
    "wof:name":"Inmotxaso S.l.",
    "wof:placetype":"venue"
},
  "geometry": {"coordinates":[-2.9386761189,43.2607421875],"type":"Point"}
}