{
  "type": "Feature",
  "properties": {
    "addr:full":"C/ Cervantes, 1 Ripollet Barcelona 08291",
    "addr:housenumber":"1",
    "addr:postcode":"08291",
    "addr:street":"C / Cervantes",
    "iso:country":"ES",
    "sg:address":"C/ Cervantes, 1",
    "sg:city":"Ripollet",
    "sg:orig_category":"Bricolaje, Herramientas (al Por Menor)",
    "sg:phone":"+34 936 92 13 54",
    "sg:postcode":"08291",
    "sg:province":"Barcelona",
    "sg:website":"www.vallesart.com",
    "wof:name":"Garrigos Molner Maria Del Carmen",
    "wof:placetype":"venue"
},
  "geometry": {"coordinates":[2.1581029892,41.4984054565],"type":"Point"}
}