{
  "type": "Feature",
  "properties": {
    "iso:country":"ES",
    "sg:address":"Calle de Capitan Juan Varela, 50",
    "sg:city":"Coru\u00d1a",
    "sg:orig_category":"Asesor\u00cda Sobre Comunicaci\u00d3n De Empresas",
    "sg:phone":"+34 981 23 12 48",
    "sg:postcode":"15007",
    "sg:province":"La Coru\u00f1a",
    "wof:name":"Intermediarios De Seguros Y Gestiones S.l.",
    "wof:placetype":"venue"
},
  "geometry": {"coordinates":[-8.4088373184,43.3544006348],"type":"Point"}
}