{
  "type": "Feature",
  "properties": {
    "iso:country":"ES",
    "sg:address":"Avda Santa Caterina, 38",
    "sg:city":"Teulada",
    "sg:orig_category":"Sociedades, Compa\u00d1\u00cdas Aseguradoras",
    "sg:phone":"+34 965 74 07 87",
    "sg:postcode":"03725",
    "sg:province":"Alicante",
    "wof:name":"Pastor Oller Pascual",
    "wof:placetype":"venue"
},
  "geometry": {"coordinates":[0.1061090007,38.7277641296],"type":"Point"}
}