{
  "type": "Feature",
  "properties": {
    "addr:full":"Calle de Doctor Mara\u00d1on (del), 2 Mejorada Campo Madrid 28840",
    "addr:housenumber":"2",
    "addr:postcode":"28840",
    "addr:street":"Calle De Doctor Maran\u0303On Del",
    "iso:country":"ES",
    "sg:address":"Calle de Doctor Mara\u00d1on (del), 2",
    "sg:city":"Mejorada Campo",
    "sg:orig_category":"Materiales De Construcci\u00d3n, Herramientas",
    "sg:phone":"+34 916 79 02 62",
    "sg:postcode":"28840",
    "sg:province":"Madrid",
    "wof:name":"Alquileres Marchanos S.l.",
    "wof:placetype":"venue"
},
  "geometry": {"coordinates":[-3.4899048805,40.3987617493],"type":"Point"}
}