{
  "type": "Feature",
  "properties": {
    "addr:full":"Calle de Colon De Larreategui, 3 Bilbao Vizcaya 48001",
    "addr:housenumber":"3",
    "addr:postcode":"48001",
    "addr:street":"Calle De Colon De Larreategui",
    "iso:country":"ES",
    "sg:address":"Calle de Colon De Larreategui, 3",
    "sg:city":"Bilbao",
    "sg:orig_category":"Comercio De Mobiliario De Oficina",
    "sg:phone":"+34 944 23 08 09",
    "sg:postcode":"48001",
    "sg:province":"Vizcaya",
    "sg:website":"www.global-bilbao.com",
    "wof:name":"Global De Equipamiento Integral S.l.",
    "wof:placetype":"venue"
},
  "geometry": {"coordinates":[-2.9269125462,43.2623023987],"type":"Point"}
}