{
  "type": "Feature",
  "properties": {
    "addr:full":"Calle de Alcon, 2 Ponferrada Le\u00f3n 24400",
    "addr:housenumber":"2",
    "addr:postcode":"24400",
    "addr:street":"Calle De Alcon",
    "iso:country":"ES",
    "sg:address":"Calle de Alcon, 2",
    "sg:city":"Ponferrada",
    "sg:orig_category":"Peluquer\u00cdas, Peluquer\u00cda Mixta",
    "sg:phone":"+34 987 41 94 00",
    "sg:postcode":"24400",
    "sg:province":"Le\u00f3n",
    "wof:name":"Marcos Leonardo S.l",
    "wof:placetype":"venue"
},
  "geometry": {"coordinates":[-6.5992145538,42.5489959717],"type":"Point"}
}