{
  "type": "Feature",
  "properties": {
    "addr:full":"C/ Francesc De Borja Moll, 16 Inca Islas Baleares 07300",
    "addr:housenumber":"16",
    "addr:postcode":"07300",
    "addr:street":"C / Francesc De Borja Moll",
    "iso:country":"ES",
    "sg:address":"C/ Francesc De Borja Moll, 16",
    "sg:city":"Inca",
    "sg:orig_category":"Reposter\u00cdas",
    "sg:phone":"+34 971 50 56 05",
    "sg:postcode":"07300",
    "sg:province":"Islas Baleares",
    "wof:name":"Es Blanquer S.l.",
    "wof:placetype":"venue"
},
  "geometry": {"coordinates":[2.9027600288,39.7177696228],"type":"Point"}
}