{
  "type": "Feature",
  "properties": {
    "iso:country":"ES",
    "sg:address":"Av Gava, S/n",
    "sg:city":"Viladecans",
    "sg:orig_category":"Distribuci\u00d3n De Petr\u00d3leo Y Derivados",
    "sg:phone":"+34 936 37 48 36",
    "sg:postcode":"08840",
    "sg:province":"Barcelona",
    "wof:name":"Retail Operating Company S.l.",
    "wof:placetype":"venue"
},
  "geometry": {"coordinates":[2.0172851086,41.3136558533],"type":"Point"}
}