{
  "type": "Feature",
  "properties": {
    "iso:country":"ES",
    "sg:address":"Calle de Nave, 12",
    "sg:city":"Valencia",
    "sg:orig_category":"Librer\u00cdas",
    "sg:phone":"+34 963 52 76 83",
    "sg:postcode":"46003",
    "sg:province":"Valencia",
    "wof:name":"Ballester Bolinches Rosario",
    "wof:placetype":"venue"
},
  "geometry": {"coordinates":[-0.3749200106,39.4772415161],"type":"Point"}
}