{
  "type": "Feature",
  "properties": {
    "iso:country":"ES",
    "sg:address":"Calle de Almansa, 13",
    "sg:city":"Albacete",
    "sg:orig_category":"Muebles, Minoristas",
    "sg:phone":"+34 967 52 19 96",
    "sg:postcode":"02006",
    "sg:province":"Albacete",
    "wof:name":"2mil Sofas Seleccion",
    "wof:placetype":"venue"
},
  "geometry": {"coordinates":[-1.845781,38.984528],"type":"Point"}
}