{
  "type": "Feature",
  "properties": {
    "iso:country":"ES",
    "sg:address":"Pla De Olivella, S/n",
    "sg:city":"Palleja",
    "sg:orig_category":"Pescader\u00cdas (al Por Menor)",
    "sg:phone":"+34 936 63 23 52",
    "sg:postcode":"08780",
    "sg:province":"Barcelona",
    "wof:name":"Bacallaneries Rafols S.l.",
    "wof:placetype":"venue"
},
  "geometry": {"coordinates":[1.9930466413,41.4190444946],"type":"Point"}
}