{
  "type": "Feature",
  "properties": {
    "addr:full":"Calle de Peru, S/n Alacant Alicante 03008",
    "addr:housenumber":"s / n",
    "addr:postcode":"03008",
    "addr:street":"Calle De Peru",
    "iso:country":"ES",
    "sg:address":"Calle de Peru, S/n",
    "sg:city":"Alacant",
    "sg:orig_category":"Quincaller\u00cda (al Por Menor)",
    "sg:phone":"+34 965 11 64 76",
    "sg:postcode":"03008",
    "sg:province":"Alicante",
    "wof:name":"Younes  Anthony",
    "wof:placetype":"venue"
},
  "geometry": {"coordinates":[-0.509878993,38.3316459656],"type":"Point"}
}