{
  "type": "Feature",
  "properties": {
    "addr:full":"Ctra Villafranqueza, Km. 0005,0 Villafranqueza - Palamo Alicante 03112",
    "addr:postcode":"03112",
    "addr:street":"Ctra Villafranqueza Km. 0005,0 Villafranqueza",
    "iso:country":"ES",
    "sg:address":"Ctra Villafranqueza, Km. 0005,0",
    "sg:city":"Villafranqueza - Palamo",
    "sg:orig_category":"Goma: Productos De Uso Industrial (fabricaci\u00d3n, Al Por Mayor)",
    "sg:phone":"+34 965 17 69 14",
    "sg:postcode":"03112",
    "sg:province":"Alicante",
    "wof:name":"Verton S. A.",
    "wof:placetype":"venue"
},
  "geometry": {"coordinates":[-0.4690259993,38.4094772339],"type":"Point"}
}