{
  "type": "Feature",
  "properties": {
    "addr:full":"Avda Doctor Clara, 21 Castellon Castell\u00f3n 12002",
    "addr:housenumber":"21",
    "addr:postcode":"12002",
    "addr:street":"Avda Doctor Clara",
    "iso:country":"ES",
    "sg:address":"Avda Doctor Clara, 21",
    "sg:city":"Castellon",
    "sg:orig_category":"Perfumer\u00cda (al Por Menor)",
    "sg:phone":"+34 964 21 76 91",
    "sg:postcode":"12002",
    "sg:province":"Castell\u00f3n",
    "wof:name":"Corella Gargallo Fidel",
    "wof:placetype":"venue"
},
  "geometry": {"coordinates":[-0.0461379997,39.9850502014],"type":"Point"}
}