{
  "type": "Feature",
  "properties": {
    "iso:country":"ES",
    "sg:address":"Calle de Cabo Francisco Diaz Lopez, 4",
    "sg:city":"Sevilla",
    "sg:orig_category":"Psic\u00d3logos",
    "sg:phone":"+34 954 23 74 07",
    "sg:postcode":"41013",
    "sg:province":"Sevilla",
    "wof:name":"Ruiz Gallego Maria Del Pilar",
    "wof:placetype":"venue"
},
  "geometry": {"coordinates":[-5.9739003181,37.3471031189],"type":"Point"}
}