{
  "type": "Feature",
  "properties": {
    "addr:full":"Luga Truebano, S/n Truebano Asturias 33690",
    "addr:housenumber":"s",
    "addr:postcode":"33690",
    "addr:street":"/ N Truebano Asturias",
    "iso:country":"ES",
    "sg:address":"Luga Truebano, S/n",
    "sg:city":"Truebano",
    "sg:orig_category":"Centros De Educaci\u00d3n Especial",
    "sg:phone":"+34 985 77 09 81",
    "sg:postcode":"33690",
    "sg:province":"Asturias",
    "wof:name":"Principado De Asturias",
    "wof:placetype":"venue"
},
  "geometry": {"coordinates":[-5.810836792,43.4387741089],"type":"Point"}
}