{
  "type": "Feature",
  "properties": {
    "addr:full":"Calle de Sendero Del Parque, 20 Malaga M\u00e1laga 29018",
    "addr:housenumber":"20",
    "addr:postcode":"29018",
    "addr:street":"Calle De Sendero Del Parque;Ma\u0301Laga",
    "iso:country":"ES",
    "sg:address":"Calle de Sendero Del Parque, 20",
    "sg:city":"Malaga",
    "sg:orig_category":"Arquitectos",
    "sg:phone":"+34 952 29 26 06",
    "sg:postcode":"29018",
    "sg:province":"M\u00e1laga",
    "wof:name":"Martin Rubio Enrique",
    "wof:placetype":"venue"
},
  "geometry": {"coordinates":[-4.3830490112,36.7327003479],"type":"Point"}
}