{
  "type": "Feature",
  "properties": {
    "addr:full":"Calle de Azarbe Del Papel, 24 Vista Alegre Murcia 30007",
    "addr:housenumber":"24",
    "addr:postcode":"30007",
    "addr:street":"Calle De Azarbe Del Papel",
    "iso:country":"ES",
    "sg:address":"Calle de Azarbe Del Papel, 24",
    "sg:city":"Vista Alegre",
    "sg:orig_category":"Centros De Coordinaci\u00d3n",
    "sg:phone":"+34 968 23 91 94",
    "sg:postcode":"30007",
    "sg:province":"Murcia",
    "wof:name":"Berenguer Plaza Jose",
    "wof:placetype":"venue"
},
  "geometry": {"coordinates":[-1.133259058,38.0012741089],"type":"Point"}
}