{
  "type": "Feature",
  "properties": {
    "iso:country":"ES",
    "sg:address":"Calle de Libertad, 35",
    "sg:city":"Valdemoro",
    "sg:orig_category":"Ropa Para Se\u00d1oras (al Por Menor)",
    "sg:phone":"+34 918 09 47 29",
    "sg:postcode":"28340",
    "sg:province":"Madrid",
    "wof:name":"Villaguesa S.l.",
    "wof:placetype":"venue"
},
  "geometry": {"coordinates":[-3.6833701134,40.1906433105],"type":"Point"}
}