{
  "type": "Feature",
  "properties": {
    "iso:country":"ES",
    "sg:address":"Av Constitucio, 207",
    "sg:city":"Castelldefels",
    "sg:orig_category":"Alimentaci\u00d3n General (al Por Menor)",
    "sg:phone":"+34 936 65 58 52",
    "sg:postcode":"08860",
    "sg:province":"Barcelona",
    "wof:name":"Infante Lopez Josue",
    "wof:placetype":"venue"
},
  "geometry": {"coordinates":[1.9754229784,41.2762145996],"type":"Point"}
}