{
  "type": "Feature",
  "properties": {
    "iso:country":"ES",
    "sg:address":"Avda Ramon Y Cajal, S/n",
    "sg:city":"Matapozuelos",
    "sg:orig_category":"Cajas Para Embalar",
    "sg:phone":"+34 983 83 29 04",
    "sg:postcode":"47230",
    "sg:province":"Valladolid",
    "wof:name":"Caja Rural Del Duero",
    "wof:placetype":"venue"
},
  "geometry": {"coordinates":[-4.7906088829,41.414604187],"type":"Point"}
}