{
  "type": "Feature",
  "properties": {
    "addr:full":"Calle de Napoles, 5 Armilla Granada 18100",
    "addr:housenumber":"5",
    "addr:postcode":"18100",
    "addr:street":"Calle De Napoles",
    "iso:country":"ES",
    "sg:address":"Calle de Napoles, 5",
    "sg:city":"Armilla",
    "sg:orig_category":"Tapicer\u00cdas",
    "sg:phone":"+34 958 57 02 12",
    "sg:postcode":"18100",
    "sg:province":"Granada",
    "wof:name":"Tapizados Virgen De Las Nieves S. L.",
    "wof:placetype":"venue"
},
  "geometry": {"coordinates":[-3.6221339703,37.1482124329],"type":"Point"}
}