{
  "type": "Feature",
  "properties": {
    "addr:full":"Avda Generalisimo, 58 Pacios Lugo 27611",
    "addr:housenumber":"58",
    "addr:postcode":"27611",
    "addr:street":"Avda Generalisimo",
    "iso:country":"ES",
    "sg:address":"Avda Generalisimo, 58",
    "sg:city":"Pacios",
    "sg:orig_category":"Productos Fitosanitarios (negocio, Aplicaci\u00d3n)",
    "sg:phone":"+34 982 54 12 10",
    "sg:postcode":"27611",
    "sg:province":"Lugo",
    "wof:name":"Zoosanitarios Y Fitosanitarios Ferrerira S.l.",
    "wof:placetype":"venue"
},
  "geometry": {"coordinates":[-7.5669207573,42.763923645],"type":"Point"}
}