{
  "type": "Feature",
  "properties": {
    "iso:country":"ES",
    "sg:address":"Calle de Mayor, 15",
    "sg:city":"Borja",
    "sg:orig_category":"Ortopedia General",
    "sg:phone":"+34 976 86 77 08",
    "sg:postcode":"50540",
    "sg:province":"Zaragoza",
    "wof:name":"Ortopedia M.blasco S.l..",
    "wof:placetype":"venue"
},
  "geometry": {"coordinates":[-1.5328769684,41.833480835],"type":"Point"}
}