{
  "type": "Feature",
  "properties": {
    "iso:country":"ES",
    "sg:address":"La Magdalena, S/n",
    "sg:city":"Guardo",
    "sg:orig_category":"Chapa Y Pintura Veh\u00cdculos",
    "sg:phone":"+34 979 85 16 22",
    "sg:postcode":"34880",
    "sg:province":"Palencia",
    "wof:name":"Alcalde Varona Pedro",
    "wof:placetype":"venue"
},
  "geometry": {"coordinates":[-4.8567886353,42.788356781],"type":"Point"}
}