{
  "type": "Feature",
  "properties": {
    "addr:full":"Carrer de Anselm Clave, 33 Granollers Barcelona 08402",
    "addr:housenumber":"33",
    "addr:postcode":"08402",
    "addr:street":"Carrer De Anselm Clave",
    "iso:country":"ES",
    "sg:address":"Carrer de Anselm Clave, 33",
    "sg:city":"Granollers",
    "sg:orig_category":"Inmobiliaria (agencias)",
    "sg:phone":"+34 938 79 41 97",
    "sg:postcode":"08402",
    "sg:province":"Barcelona",
    "wof:name":"Puingra S.a.",
    "wof:placetype":"venue"
},
  "geometry": {"coordinates":[2.2889389992,41.6074104309],"type":"Point"}
}