{
  "type": "Feature",
  "properties": {
    "addr:full":"Carrer de Caponata, 3 Barcelona Barcelona 08034",
    "addr:housenumber":"3",
    "addr:postcode":"08034",
    "addr:street":"Carrer De Caponata",
    "iso:country":"ES",
    "sg:address":"Carrer de Caponata, 3",
    "sg:city":"Barcelona",
    "sg:orig_category":"Pod\u00d3logos: Pedicuros",
    "sg:phone":"+34 932 80 60 24",
    "sg:postcode":"08034",
    "sg:province":"Barcelona",
    "wof:name":"Begay  Bernadette",
    "wof:placetype":"venue"
},
  "geometry": {"coordinates":[2.1227169037,41.3960380554],"type":"Point"}
}