{
  "type": "Feature",
  "properties": {
    "iso:country":"ES",
    "sg:address":"Calle de Via Complutense, 89",
    "sg:city":"Alcala Henares",
    "sg:orig_category":"Carnicer\u00cdas, Carnicer\u00cdas",
    "sg:phone":"+34 918 80 16 80",
    "sg:postcode":"28805",
    "sg:province":"Madrid",
    "wof:name":"Carnicerias Rey S.l.",
    "wof:placetype":"venue"
},
  "geometry": {"coordinates":[-3.3538269997,40.4899291992],"type":"Point"}
}