{
  "type": "Feature",
  "properties": {
    "iso:country":"ES",
    "sg:address":"Calle de Cirilo Amoros, 86",
    "sg:city":"Valencia",
    "sg:orig_category":"Asilos De Ancianos. Centros Privados",
    "sg:phone":"+34 963 95 35 01",
    "sg:postcode":"46004",
    "sg:province":"Valencia",
    "wof:name":"Asociacion Regional De Jubilados De Levante-plenitud",
    "wof:placetype":"venue"
},
  "geometry": {"coordinates":[-0.3659690917,39.4696235657],"type":"Point"}
}