{
  "type": "Feature",
  "properties": {
    "iso:country":"ES",
    "sg:address":"Calle de Garcia De Paredes, 32",
    "sg:city":"Madrid",
    "sg:orig_category":"Camiser\u00cda Y Ropa Interior Masculina (al Por Menor)",
    "sg:phone":"+34 914 48 58 37",
    "sg:postcode":"28010",
    "sg:province":"Madrid",
    "wof:name":"Suarez Acinas Fatima",
    "wof:placetype":"venue"
},
  "geometry": {"coordinates":[-3.6993544102,40.4367103577],"type":"Point"}
}