{
  "type": "Feature",
  "properties": {
    "iso:country":"ES",
    "sg:address":"Punta Ballena, 13",
    "sg:city":"Palmanova",
    "sg:orig_category":"Caf\u00c9s, Bares, Cervecer\u00cdas",
    "sg:phone":"+34 971 68 28 92",
    "sg:postcode":"07181",
    "sg:province":"Islas Baleares",
    "wof:name":"Happy House Comunidad De Bienes",
    "wof:placetype":"venue"
},
  "geometry": {"coordinates":[2.5657799244,39.5388221741],"type":"Point"}
}