{
  "type": "Feature",
  "properties": {
    "iso:country":"ES",
    "sg:address":"Carrer de Alpens, 20",
    "sg:city":"Barcelona",
    "sg:orig_category":"Artes Gr\u00c1ficas, Artes Pl\u00c1sticas (curso)",
    "sg:phone":"+34 932 96 63 87",
    "sg:postcode":"08014",
    "sg:province":"Barcelona",
    "wof:name":"Taller De Fotomecanica Covigraf S.l.",
    "wof:placetype":"venue"
},
  "geometry": {"coordinates":[2.1404719353,41.3724365234],"type":"Point"}
}