{
  "type": "Feature",
  "properties": {
    "iso:country":"ES",
    "sg:address":"Urb Playetas (las), S/n",
    "sg:city":"Playetas",
    "sg:orig_category":"Ingenier\u00cda, Centros De Estudios (diversos)",
    "sg:phone":"+34 964 30 11 37",
    "sg:postcode":"12594",
    "sg:province":"Castell\u00f3n",
    "wof:name":"Ortells Pertegas Francisco",
    "wof:placetype":"venue"
},
  "geometry": {"coordinates":[0.135344997,40.0945358276],"type":"Point"}
}