{
  "type": "Feature",
  "properties": {
    "iso:country":"ES",
    "sg:address":"Prje Fuentes Del Marques, S/n",
    "sg:city":"Caravaca Cruz",
    "sg:orig_category":"Centros De Educaci\u00d3n Especial",
    "sg:phone":"+34 968 70 81 51",
    "sg:postcode":"30400",
    "sg:province":"Murcia",
    "wof:name":"Colegio Nacional De Educacion Especial Ascruz",
    "wof:placetype":"venue"
},
  "geometry": {"coordinates":[-1.8645700216,38.104763031],"type":"Point"}
}