{
  "type": "Feature",
  "properties": {
    "addr:full":"Avda Sur (del), 17 Granada Granada 18014",
    "addr:postcode":"18014",
    "addr:street":"Avda;Del",
    "iso:country":"ES",
    "sg:address":"Avda Sur (del), 17",
    "sg:city":"Granada",
    "sg:orig_category":"Promotores Constructores",
    "sg:phone":"+34 958 20 40 67",
    "sg:postcode":"18014",
    "sg:province":"Granada",
    "wof:name":"Europeam Obras Constructora S.l.",
    "wof:placetype":"venue"
},
  "geometry": {"coordinates":[-3.6135420799,37.1878013611],"type":"Point"}
}