{
  "type": "Feature",
  "properties": {
    "addr:full":"Avda Federico Garcia Lorca, 7 Cabezas S. Juan Sevilla 41730",
    "addr:housenumber":"7",
    "addr:postcode":"41730",
    "addr:street":"Avda Federico Garcia Lorca;S.",
    "iso:country":"ES",
    "sg:address":"Avda Federico Garcia Lorca, 7",
    "sg:city":"Cabezas S. Juan",
    "sg:orig_category":"Asociaciones Y Clubs Deportivos",
    "sg:phone":"+34 955 87 11 81",
    "sg:postcode":"41730",
    "sg:province":"Sevilla",
    "wof:name":"Pe\u00f1a Betica Cultural San Juan",
    "wof:placetype":"venue"
},
  "geometry": {"coordinates":[-5.9374232292,36.9865264893],"type":"Point"}
}