{
  "type": "Feature",
  "properties": {
    "iso:country":"ES",
    "sg:address":"Valgrande 6",
    "sg:city":"Alcobendas",
    "sg:classifiers":[
        {
            "category":"Professional",
            "subcategory":"Computer Services",
            "type":"Services"
        }
    ],
    "sg:postcode":"28108",
    "sg:website":"http://www.telvent.com",
    "wof:name":"Telvent Git",
    "wof:placetype":"venue"
},
  "geometry": {"coordinates":[-3.6490647,40.5362637],"type":"Point"}
}