{
  "type": "Feature",
  "properties": {
    "addr:full":"O(barbiguera), 3 Vinaros Castell\u00f3n 12500",
    "addr:housenumber":"3",
    "addr:postcode":"12500",
    "addr:street":"Barbiguera",
    "iso:country":"ES",
    "sg:address":"O(barbiguera), 3",
    "sg:city":"Vinaros",
    "sg:orig_category":"Molduras, Junquillos, Listones Y Molduras Perforadas",
    "sg:phone":"+34 964 49 67 14",
    "sg:postcode":"12500",
    "sg:province":"Castell\u00f3n",
    "wof:name":"Bar Restaurante La Caribe\u00f1a S.l.",
    "wof:placetype":"venue"
},
  "geometry": {"coordinates":[0.4749450088,40.4711990356],"type":"Point"}
}