{
  "type": "Feature",
  "properties": {
    "addr:full":"Ptda Baseta La Guillema, S/n Lliria Valencia 46160",
    "addr:housenumber":"s / n",
    "addr:postcode":"46160",
    "addr:street":"Ptda Baseta La Guillema",
    "iso:country":"ES",
    "sg:address":"Ptda Baseta La Guillema, S/n",
    "sg:city":"Lliria",
    "sg:orig_category":"Pirotecnia (espect\u00c1culos)",
    "sg:phone":"+34 962 72 81 00",
    "sg:postcode":"46160",
    "sg:province":"Valencia",
    "sg:website":"www.pirotecniacaballer.es",
    "wof:name":"Pirotecnia Caballer S.a.",
    "wof:placetype":"venue"
},
  "geometry": {"coordinates":[-0.5952839851,39.6247406006],"type":"Point"}
}