{
  "type": "Feature",
  "properties": {
    "addr:full":"Calle de Sierra Blanca, 1 Marbella M\u00e1laga 29600",
    "addr:housenumber":"1",
    "addr:postcode":"29600",
    "addr:street":"Calle De Sierra Blanca;Ma\u0301Laga",
    "iso:country":"ES",
    "sg:address":"Calle de Sierra Blanca, 1",
    "sg:city":"Marbella",
    "sg:orig_category":"Promotores Constructores",
    "sg:phone":"+34 952 86 87 87",
    "sg:postcode":"29600",
    "sg:province":"M\u00e1laga",
    "wof:name":"Project Management Marketing",
    "wof:placetype":"venue"
},
  "geometry": {"coordinates":[-4.8897328377,36.5100784302],"type":"Point"}
}