{
  "type": "Feature",
  "properties": {
    "iso:country":"ES",
    "sg:address":"Calle de Ajuriaguerra Juan, 19",
    "sg:city":"Bilbao",
    "sg:orig_category":"Administradores De Bienes Y Delegados De Comunidades De Propietarios",
    "sg:phone":"+34 944 24 18 49",
    "sg:postcode":"48009",
    "sg:province":"Vizcaya",
    "wof:name":"De La Quintana Admon Y Fincas, S.l.",
    "wof:placetype":"venue"
},
  "geometry": {"coordinates":[-2.9338581562,43.2658576965],"type":"Point"}
}