{
  "type": "Feature",
  "properties": {
    "iso:country":"ES",
    "sg:address":"Calle de Medinaceli, 5",
    "sg:city":"Soria",
    "sg:orig_category":"Abogados",
    "sg:phone":"+34 975 23 22 06",
    "sg:postcode":"42003",
    "sg:province":"Soria",
    "wof:name":"Plaza Almazan Jesus",
    "wof:placetype":"venue"
},
  "geometry": {"coordinates":[-2.4695222378,41.7634468079],"type":"Point"}
}