{
  "type": "Feature",
  "properties": {
    "iso:country":"ES",
    "sg:address":"Ctra Granada, Km. 0117,0",
    "sg:city":"Almeria",
    "sg:orig_category":"Materiales De Construcci\u00d3n (en General)",
    "sg:phone":"+34 950 14 13 03",
    "sg:postcode":"04009",
    "sg:province":"Almer\u00eda",
    "sg:website":"www.i.sani.com",
    "wof:name":"Impermeabilizantes Sani S.l.",
    "wof:placetype":"venue"
},
  "geometry": {"coordinates":[-2.4484889507,36.864238739],"type":"Point"}
}