{
  "type": "Feature",
  "properties": {
    "iso:country":"ES",
    "sg:address":"Carrer de Joan Maragall, 44",
    "sg:city":"Manlleu",
    "sg:orig_category":"Estudios, Instalaci\u00d3n De Climatizaci\u00d3n",
    "sg:phone":"+34 938 51 29 70",
    "sg:postcode":"08560",
    "sg:province":"Barcelona",
    "wof:name":"Costa Ramisa Juan",
    "wof:placetype":"venue"
},
  "geometry": {"coordinates":[2.2896690369,42.009967804],"type":"Point"}
}