{
  "type": "Feature",
  "properties": {
    "addr:full":"Calle de Vatemar, 19 Bembibre Le\u00f3n 24300",
    "addr:housenumber":"19",
    "addr:postcode":"24300",
    "addr:street":"Calle De Vatemar;Leo\u0301N",
    "iso:country":"ES",
    "sg:address":"Calle de Vatemar, 19",
    "sg:city":"Bembibre",
    "sg:orig_category":"Confecci\u00d3n De Trajes Para Se\u00d1oras",
    "sg:phone":"+34 987 51 13 81",
    "sg:postcode":"24300",
    "sg:province":"Le\u00f3n",
    "wof:name":"Loureiro Lopez Dolores",
    "wof:placetype":"venue"
},
  "geometry": {"coordinates":[-6.4167661667,42.6174964905],"type":"Point"}
}