{
  "type": "Feature",
  "properties": {
    "addr:full":"Calle de Eduardo Lopez Palop, 12 Molinos Madrid 28460",
    "addr:housenumber":"12",
    "addr:postcode":"28460",
    "addr:street":"Calle De Eduardo Lopez Palop",
    "iso:country":"ES",
    "sg:address":"Calle de Eduardo Lopez Palop, 12",
    "sg:city":"Molinos",
    "sg:orig_category":"Asesor\u00cda, Estudio Y Control Medioambiental",
    "sg:phone":"+34 918 55 07 66",
    "sg:postcode":"28460",
    "sg:province":"Madrid",
    "wof:name":"Sentido Comun Asesores Ambientales S.l.l",
    "wof:placetype":"venue"
},
  "geometry": {"coordinates":[-4.0653128624,40.7139282227],"type":"Point"}
}