{
  "type": "Feature",
  "properties": {
    "addr:full":"Carrer de Turo Blau, 25 Barcelona Barcelona 08016",
    "addr:housenumber":"25",
    "addr:postcode":"08016",
    "addr:street":"Carrer De Turo Blau",
    "iso:country":"ES",
    "sg:address":"Carrer de Turo Blau, 25",
    "sg:city":"Barcelona",
    "sg:classifiers":[
        {
            "category":"Autos & Motor Vehicles",
            "subcategory":"Automobile Sales",
            "type":"Retail Goods"
        }
    ],
    "sg:phone":"+34 933 54 37 05",
    "sg:postcode":"08016",
    "sg:province":"Barcelona",
    "wof:name":"Rodriguez Batlle Esteban",
    "wof:placetype":"venue"
},
  "geometry": {"coordinates":[2.175896883,41.4392547607],"type":"Point"}
}