{
  "type": "Feature",
  "properties": {
    "iso:country":"ES",
    "sg:address":"Calle de Malaga, 6",
    "sg:city":"Albacete",
    "sg:orig_category":"Planchado",
    "sg:phone":"+34 967 50 77 43",
    "sg:postcode":"02006",
    "sg:province":"Albacete",
    "wof:name":"Garcia Aparicio Baldomero",
    "wof:placetype":"venue"
},
  "geometry": {"coordinates":[-1.8775789738,38.989780426],"type":"Point"}
}