{
  "type": "Feature",
  "properties": {
    "iso:country":"ES",
    "sg:address":"Avgd Guillem Tatay, 19",
    "sg:city":"Campo Olivar",
    "sg:orig_category":"Arboricultura Y Producci\u00d3n De Frutas",
    "sg:phone":"+34 963 63 59 91",
    "sg:postcode":"46110",
    "sg:province":"Valencia",
    "wof:name":"Cartana Fruits S.l.",
    "wof:placetype":"venue"
},
  "geometry": {"coordinates":[-0.4154840112,39.5255889893],"type":"Point"}
}