{
  "type": "Feature",
  "properties": {
    "addr:full":"Calle de Severo Ochoa, 31 Arrigorriaga Vizcaya 48480",
    "addr:housenumber":"31",
    "addr:postcode":"48480",
    "addr:street":"Calle De Severo Ochoa",
    "iso:country":"ES",
    "sg:address":"Calle de Severo Ochoa, 31",
    "sg:city":"Arrigorriaga",
    "sg:orig_category":"Asesor\u00cda Fiscal Y Jur\u00cddica",
    "sg:phone":"+34 946 71 41 11",
    "sg:postcode":"48480",
    "sg:province":"Vizcaya",
    "wof:name":"Irazabal Ciudad I\u00f1igo Javier",
    "wof:placetype":"venue"
},
  "geometry": {"coordinates":[-2.8870949745,43.2061042786],"type":"Point"}
}