{
  "type": "Feature",
  "properties": {
    "addr:full":"Esquiroz-ezkirotz Kalea, 9 Iru\u00f1a Navarra 31007",
    "addr:housenumber":"9",
    "addr:postcode":"31007",
    "addr:street":"Esquiroz-Ezkirotz Kalea",
    "iso:country":"ES",
    "sg:address":"Esquiroz-ezkirotz Kalea, 9",
    "sg:city":"Iru\u00f1a",
    "sg:orig_category":"Inmobiliaria (agencias)",
    "sg:phone":"+34 948 17 01 47",
    "sg:postcode":"31007",
    "sg:province":"Navarra",
    "wof:name":"Huarte Biurrun Juan Fermin",
    "wof:placetype":"venue"
},
  "geometry": {"coordinates":[-1.6500179768,42.8061637878],"type":"Point"}
}