{
  "type": "Feature",
  "properties": {
    "iso:country":"ES",
    "sg:address":"Calle de Jose De Cadalso, 50",
    "sg:city":"Madrid",
    "sg:orig_category":"Internados & Ense\u00d1anza Privada",
    "sg:phone":"+34 917 06 04 97",
    "sg:postcode":"28044",
    "sg:province":"Madrid",
    "wof:name":"Colegio Beata Filipina Fundacion Viertola",
    "wof:placetype":"venue"
},
  "geometry": {"coordinates":[-3.7716419697,40.3803443909],"type":"Point"}
}