{
  "type": "Feature",
  "properties": {
    "iso:country":"ES",
    "sg:address":"Ctra. Vp Mil Ventidos, S/n",
    "sg:city":"Beniganim",
    "sg:orig_category":"Producci\u00d3n, Distribuci\u00d3n De Gas Butano Y Propano",
    "sg:phone":"+34 962 21 50 68",
    "sg:postcode":"46830",
    "sg:province":"Valencia",
    "wof:name":"Repsol Ypf S.a.",
    "wof:placetype":"venue"
},
  "geometry": {"coordinates":[-0.444671005,38.9410247803],"type":"Point"}
}