{
  "type": "Feature",
  "properties": {
    "iso:country":"ES",
    "sg:address":"Avda Aljarafe, 4",
    "sg:city":"Bormujos",
    "sg:orig_category":"Caf\u00c9s, Bares, Cervecer\u00cdas",
    "sg:phone":"+34 955 72 56 29",
    "sg:postcode":"41930",
    "sg:province":"Sevilla",
    "wof:name":"Jimenez Acosta Juan Manuel",
    "wof:placetype":"venue"
},
  "geometry": {"coordinates":[-6.0722250938,37.3719139099],"type":"Point"}
}