{
  "type": "Feature",
  "properties": {
    "iso:country":"ES",
    "sg:address":"Avda Canillejas A Vicalvaro, 125",
    "sg:city":"Madrid",
    "sg:orig_category":"Peluqueros: De Se\u00d1oras",
    "sg:phone":"+34 913 06 62 32",
    "sg:postcode":"28022",
    "sg:province":"Madrid",
    "wof:name":"Fuertes Suarez Maria",
    "wof:placetype":"venue"
},
  "geometry": {"coordinates":[-3.6109530926,40.4279136658],"type":"Point"}
}