{
  "type": "Feature",
  "properties": {
    "iso:country":"ES",
    "sg:address":"Avda Mediterraneo (del), 93",
    "sg:city":"Rincon Victoria",
    "sg:orig_category":"Inmobiliaria (agencias)",
    "sg:phone":"+34 952 97 84 35",
    "sg:postcode":"29730",
    "sg:province":"M\u00e1laga",
    "wof:name":"Estudio El Rincon S.l.",
    "wof:placetype":"venue"
},
  "geometry": {"coordinates":[-4.2876138687,36.7154464722],"type":"Point"}
}