{
  "type": "Feature",
  "properties": {
    "iso:country":"ES",
    "sg:address":"Llano Blanco Machado, 13",
    "sg:city":"San Isidro",
    "sg:orig_category":"Ense\u00d1anza, Formaci\u00d3n Profesional: Aprendizaje",
    "sg:phone":"+34 922 68 06 66",
    "sg:postcode":"38108",
    "sg:province":"Santa Cruz De Tenerife",
    "wof:name":"Ayuntamiento De El Rosario",
    "wof:placetype":"venue"
},
  "geometry": {"coordinates":[-16.3334903717,28.4144420624],"type":"Point"}
}