{
  "type": "Feature",
  "properties": {
    "addr:full":"Calle de Vital Aza, 66 Madrid Madrid 28017",
    "addr:housenumber":"66",
    "addr:postcode":"madrid;28017",
    "addr:street":"Calle De Vital Aza",
    "iso:country":"ES",
    "sg:address":"Calle de Vital Aza, 66",
    "sg:city":"Madrid",
    "sg:orig_category":"Asistencia Domiciliaria",
    "sg:phone":"+34 914 07 23 27",
    "sg:postcode":"28017",
    "sg:province":"Madrid",
    "wof:name":"Wulf Asistencia S.l.",
    "wof:placetype":"venue"
},
  "geometry": {"coordinates":[-3.6393129826,40.4329681396],"type":"Point"}
}