{
  "type": "Feature",
  "properties": {
    "addr:full":"Calle de San Miguel, 2 Torredelcampo Ja\u00e9n 23640",
    "addr:housenumber":"2",
    "addr:postcode":"23640",
    "addr:street":"Calle De San Miguel;Jae\u0301N",
    "iso:country":"ES",
    "sg:address":"Calle de San Miguel, 2",
    "sg:city":"Torredelcampo",
    "sg:orig_category":"Molduras, Junquillos, Listones Y Molduras Perforadas",
    "sg:phone":"+34 953 56 79 21",
    "sg:postcode":"23640",
    "sg:province":"Ja\u00e9n",
    "wof:name":"Juan Parras Denia C.b.",
    "wof:placetype":"venue"
},
  "geometry": {"coordinates":[-3.8987390995,37.7704353333],"type":"Point"}
}