{
  "type": "Feature",
  "properties": {
    "iso:country":"ES",
    "sg:address":"Rua Fragata Villa De Madrid, 19",
    "sg:city":"Real",
    "sg:orig_category":"Doctores En Medicina",
    "sg:phone":"+34 986 31 52 06",
    "sg:postcode":"36950",
    "sg:province":"Pontevedra",
    "wof:name":"Ferradas Ferradas Luis",
    "wof:placetype":"venue"
},
  "geometry": {"coordinates":[-8.7389688492,42.2752113342],"type":"Point"}
}