{
  "type": "Feature",
  "properties": {
    "addr:full":"Carrer de Palmira, 2 Peguera Islas Baleares 07160",
    "addr:housenumber":"2",
    "addr:postcode":"07160",
    "addr:street":"Carrer De Palmira",
    "iso:country":"ES",
    "sg:address":"Carrer de Palmira, 2",
    "sg:city":"Peguera",
    "sg:orig_category":"Ropa Para Se\u00d1oras (al Por Menor)",
    "sg:phone":"+34 971 68 63 13",
    "sg:postcode":"07160",
    "sg:province":"Islas Baleares",
    "wof:name":"Wilke  Heike",
    "wof:placetype":"venue"
},
  "geometry": {"coordinates":[2.4505050182,39.5380325317],"type":"Point"}
}