{
  "type": "Feature",
  "properties": {
    "iso:country":"ES",
    "sg:address":"Avda Bizkaia, S/n",
    "sg:city":"Ermua",
    "sg:orig_category":"Empresas De Carpinter\u00cda",
    "sg:phone":"+34 943 17 14 52",
    "sg:postcode":"48260",
    "sg:province":"Vizcaya",
    "wof:name":"Cano Gomez Waldo",
    "wof:placetype":"venue"
},
  "geometry": {"coordinates":[-2.4973800182,43.1792488098],"type":"Point"}
}