{
  "type": "Feature",
  "properties": {
    "iso:country":"ES",
    "sg:address":"Avda Juan De Austria, 16",
    "sg:city":"Alcala Henares",
    "sg:orig_category":"Frutas, Legumbres Frescas Y Tempranas (al Por Menor)",
    "sg:phone":"+34 918 80 86 09",
    "sg:postcode":"28804",
    "sg:province":"Madrid",
    "wof:name":"Pe\u00f1a Toba Julia",
    "wof:placetype":"venue"
},
  "geometry": {"coordinates":[-3.3550829887,40.4863624573],"type":"Point"}
}