{
  "type": "Feature",
  "properties": {
    "iso:country":"ES",
    "sg:address":"Calle de Muralla, 15",
    "sg:city":"Salobre\u00f1a",
    "sg:orig_category":"Arquitectos",
    "sg:phone":"+34 958 61 14 13",
    "sg:postcode":"18680",
    "sg:province":"Granada",
    "wof:name":"Suarez Carmona Antonio",
    "wof:placetype":"venue"
},
  "geometry": {"coordinates":[-3.5877549648,36.7438850403],"type":"Point"}
}