{
  "type": "Feature",
  "properties": {
    "iso:country":"ES",
    "sg:address":"Carr Mendizabal, 148",
    "sg:city":"Burjassot",
    "sg:orig_category":"Mec\u00c1nico Del Autom\u00d3vil",
    "sg:phone":"+34 963 63 22 01",
    "sg:postcode":"46100",
    "sg:province":"Valencia",
    "wof:name":"Martinez Lairon Gustavo Jorge",
    "wof:placetype":"venue"
},
  "geometry": {"coordinates":[-0.4181360006,39.5151786804],"type":"Point"}
}