{
  "type": "Feature",
  "properties": {
    "addr:full":"Avda Peru (del), S/n Cadiz C\u00e1diz 11007",
    "addr:housenumber":"/ n",
    "addr:postcode":"11007",
    "addr:street":"Avda Peru Del S",
    "iso:country":"ES",
    "sg:address":"Avda Peru (del), S/n",
    "sg:city":"Cadiz",
    "sg:orig_category":"Supermercados Y Hipermercados",
    "sg:phone":"+34 956 26 11 52",
    "sg:postcode":"11007",
    "sg:province":"C\u00e1diz",
    "sg:website":"www.ahold.com",
    "wof:name":"Dinosol Supermercados S.l.",
    "wof:placetype":"venue"
},
  "geometry": {"coordinates":[-6.2765140533,36.5181808472],"type":"Point"}
}