{
  "type": "Feature",
  "properties": {
    "addr:full":"Calle de Padre Lucas, 4 Calahorra La Rioja 26500",
    "addr:housenumber":"4",
    "addr:postcode":"26500",
    "addr:street":"Calle De Padre Lucas",
    "iso:country":"ES",
    "sg:address":"Calle de Padre Lucas, 4",
    "sg:city":"Calahorra",
    "sg:orig_category":"Inmobiliaria (agencias)",
    "sg:phone":"+34 941 13 60 31",
    "sg:postcode":"26500",
    "sg:province":"La Rioja",
    "wof:name":"Europromociones 94 S.l.",
    "wof:placetype":"venue"
},
  "geometry": {"coordinates":[-1.9643969536,42.3047142029],"type":"Point"}
}