{
  "type": "Feature",
  "properties": {
    "addr:full":"Calle de Araneko, 10 Bilbao Vizcaya 48014",
    "addr:housenumber":"10",
    "addr:postcode":"48014",
    "addr:street":"Calle De Araneko",
    "iso:country":"ES",
    "sg:address":"Calle de Araneko, 10",
    "sg:city":"Bilbao",
    "sg:orig_category":"Supermercados Y Hipermercados",
    "sg:phone":"+34 944 47 97 79",
    "sg:postcode":"48014",
    "sg:province":"Vizcaya",
    "wof:name":"Temprano Fernandez Ladislao",
    "wof:placetype":"venue"
},
  "geometry": {"coordinates":[-2.9474751949,43.2741279602],"type":"Point"}
}