{
  "type": "Feature",
  "properties": {
    "addr:full":"C/ Reconquesta, 52 Alcoi Alicante 03803",
    "addr:housenumber":"52",
    "addr:postcode":"03803",
    "addr:street":"C / Reconquesta",
    "iso:country":"ES",
    "sg:address":"C/ Reconquesta, 52",
    "sg:city":"Alcoi",
    "sg:orig_category":"Ingeniero",
    "sg:phone":"+34 966 52 25 75",
    "sg:postcode":"03803",
    "sg:province":"Alicante",
    "wof:name":"Terol Lopez Jorge",
    "wof:placetype":"venue"
},
  "geometry": {"coordinates":[-0.4810670018,38.7027359009],"type":"Point"}
}