{
  "type": "Feature",
  "properties": {
    "iso:country":"ES",
    "sg:address":"Calle de Rios Rosas, 1",
    "sg:city":"Madrid",
    "sg:orig_category":"Distribuci\u00d3n De Petr\u00d3leo Y Derivados",
    "sg:phone":"+34 914 42 42 94",
    "sg:postcode":"28003",
    "sg:province":"Madrid",
    "wof:name":"Gestion Punto Venta S.a.",
    "wof:placetype":"venue"
},
  "geometry": {"coordinates":[-3.7037289143,40.4422454834],"type":"Point"}
}