{
  "type": "Feature",
  "properties": {
    "iso:country":"ES",
    "sg:address":"Carrer de Vic, S/n",
    "sg:city":"Centelles",
    "sg:orig_category":"Bricolaje, Herramientas (al Por Menor)",
    "sg:phone":"+34 938 81 15 05",
    "sg:postcode":"08540",
    "sg:province":"Barcelona",
    "wof:name":"Garriga Medina Maria Dolors",
    "wof:placetype":"venue"
},
  "geometry": {"coordinates":[2.2172250748,41.7996788025],"type":"Point"}
}