{
  "type": "Feature",
  "properties": {
    "addr:full":"Calle de Elias Vargas Y Zurita, 1 Ca\u00e7ete De Las Torres C\u00f3rdoba 14660",
    "addr:housenumber":"1",
    "addr:postcode":"14660",
    "addr:street":"Calle De Elias Vargas Y Zurita;Co\u0301Rdoba",
    "iso:country":"ES",
    "sg:address":"Calle de Elias Vargas Y Zurita, 1",
    "sg:city":"Ca\u00e7ete De Las Torres",
    "sg:orig_category":"Supermercados Y Hipermercados",
    "sg:phone":"+34 957 18 36 70",
    "sg:postcode":"14660",
    "sg:province":"C\u00f3rdoba",
    "wof:name":"Borrego Avalos Perfecto Martin",
    "wof:placetype":"venue"
},
  "geometry": {"coordinates":[-4.3149461746,37.868850708],"type":"Point"}
}