{
  "type": "Feature",
  "properties": {
    "iso:country":"ES",
    "sg:address":"Avda Obispo Angel Herrera Oria, 5",
    "sg:city":"Malaga",
    "sg:orig_category":"Inform\u00c1tica (estudios, Servicios, Asesor\u00cda, Formaci\u00d3n)",
    "sg:phone":"+34 952 07 02 09",
    "sg:postcode":"29007",
    "sg:province":"M\u00e1laga",
    "wof:name":"Innova Farmacias S.l.",
    "wof:placetype":"venue"
},
  "geometry": {"coordinates":[-4.4398241043,36.7181167603],"type":"Point"}
}