{
  "type": "Feature",
  "properties": {
    "iso:country":"ES",
    "sg:address":"Calle de Cadena (la), 31",
    "sg:city":"Zaragoza",
    "sg:orig_category":"Caf\u00c9s, Bares, Cervecer\u00cdas",
    "sg:phone":"+34 976 29 39 89",
    "sg:postcode":"50001",
    "sg:province":"Zaragoza",
    "wof:name":"Anymar S.cv.",
    "wof:placetype":"venue"
},
  "geometry": {"coordinates":[-0.8753432035,41.6496162415],"type":"Point"}
}