{
  "type": "Feature",
  "properties": {
    "iso:country":"ES",
    "sg:address":"Carrer de Avinyo, 29",
    "sg:city":"Barcelona",
    "sg:orig_category":"Embalajes",
    "sg:phone":"+34 933 15 28 04",
    "sg:postcode":"08002",
    "sg:province":"Barcelona",
    "wof:name":"Cerda Grau Juan",
    "wof:placetype":"venue"
},
  "geometry": {"coordinates":[2.1784520149,41.3806304932],"type":"Point"}
}