{
  "type": "Feature",
  "properties": {
    "addr:full":"Calle de Garcia Sanchez, 5 Zaragoza Zaragoza 50005",
    "addr:housenumber":"5",
    "addr:postcode":"50005",
    "addr:street":"Calle De Garcia Sanchez",
    "iso:country":"ES",
    "sg:address":"Calle de Garcia Sanchez, 5",
    "sg:city":"Zaragoza",
    "sg:orig_category":"Fabricaci\u00d3n De Muebles",
    "sg:phone":"+34 976 55 72 12",
    "sg:postcode":"50005",
    "sg:province":"Zaragoza",
    "wof:name":"Morato Garcia Jesus Vicente",
    "wof:placetype":"venue"
},
  "geometry": {"coordinates":[-0.8989109993,41.6464614868],"type":"Point"}
}