{
  "type": "Feature",
  "properties": {
    "addr:full":"Camino De Matanegra, Km. 0200,0 Puebla Sancho Perez Badajoz 06310",
    "addr:postcode":"06310",
    "addr:street":"Camino De Matanegra Km. 0200,0 Puebla Sancho",
    "iso:country":"ES",
    "sg:address":"Camino De Matanegra, Km. 0200,0",
    "sg:city":"Puebla Sancho Perez",
    "sg:orig_category":"Cooperativas Agr\u00cdcolas",
    "sg:phone":"+34 924 55 21 02",
    "sg:postcode":"06310",
    "sg:province":"Badajoz",
    "wof:name":"Sociedad Cooperativa Limitada Del Campo Nuestra Se\u00f1ora De Belen",
    "wof:placetype":"venue"
},
  "geometry": {"coordinates":[-6.3967342377,38.395980835],"type":"Point"}
}