{
  "type": "Feature",
  "properties": {
    "iso:country":"ES",
    "sg:address":"Calle de Gustavo Fernandez Balbuena, 9",
    "sg:city":"Madrid",
    "sg:orig_category":"Dibujo",
    "sg:phone":"+34 915 10 21 66",
    "sg:postcode":"28002",
    "sg:province":"Madrid",
    "sg:website":"www.sybilla.es",
    "wof:name":"Programas Exteriores S.a.",
    "wof:placetype":"venue"
},
  "geometry": {"coordinates":[-3.668006897,40.4498214722],"type":"Point"}
}