{
  "type": "Feature",
  "properties": {
    "iso:country":"ES",
    "sg:address":"Tmino. Sorban, 18",
    "sg:city":"Calahorra",
    "sg:orig_category":"Producci\u00d3n De Champi\u00d1ones",
    "sg:phone":"+34 941 14 64 32",
    "sg:postcode":"26500",
    "sg:province":"La Rioja",
    "wof:name":"Setas Chine S.c.p.",
    "wof:placetype":"venue"
},
  "geometry": {"coordinates":[-1.9620640278,42.3058395386],"type":"Point"}
}