{
  "type": "Feature",
  "properties": {
    "addr:full":"Rua Jose Antonio, 25 Sarria Lugo 27600",
    "addr:housenumber":"25",
    "addr:postcode":"27600",
    "addr:street":"Rua Jose Antonio",
    "iso:country":"ES",
    "sg:address":"Rua Jose Antonio, 25",
    "sg:city":"Sarria",
    "sg:orig_category":"Bazares, Art\u00cdculos De Limpieza Y De Cocina (al Por Menor)",
    "sg:phone":"+34 982 53 02 10",
    "sg:postcode":"27600",
    "sg:province":"Lugo",
    "wof:name":"Vazquez Losada German",
    "wof:placetype":"venue"
},
  "geometry": {"coordinates":[-7.4182729721,42.7823867798],"type":"Point"}
}