{
  "type": "Feature",
  "properties": {
    "addr:full":"Carr Germanies, 7 Manises Valencia 46940",
    "addr:housenumber":"7",
    "addr:postcode":"46940",
    "addr:street":"Carr Germanies",
    "iso:country":"ES",
    "sg:address":"Carr Germanies, 7",
    "sg:city":"Manises",
    "sg:orig_category":"Imprenta",
    "sg:phone":"+34 961 53 41 23",
    "sg:postcode":"46940",
    "sg:province":"Valencia",
    "wof:name":"Graficas Podadera S.l.",
    "wof:placetype":"venue"
},
  "geometry": {"coordinates":[-0.4643029869,39.4907112122],"type":"Point"}
}