{
  "type": "Feature",
  "properties": {
    "addr:full":"Bda Francon, 45 Mendui\u00d1a Pontevedra 36946",
    "addr:housenumber":"45",
    "addr:postcode":"36946",
    "addr:street":"Menduin\u0303A Pontevedra",
    "iso:country":"ES",
    "sg:address":"Bda Francon, 45",
    "sg:city":"Mendui\u00d1a",
    "sg:orig_category":"Expertos Contables",
    "sg:phone":"+34 986 39 12 10",
    "sg:postcode":"36946",
    "sg:province":"Pontevedra",
    "wof:name":"L.p.s.peritaciones S.l.",
    "wof:placetype":"venue"
},
  "geometry": {"coordinates":[-8.8023338318,42.2950210571],"type":"Point"}
}