{
  "type": "Feature",
  "properties": {
    "iso:country":"ES",
    "sg:address":"Carr Doctor Santiago Sobreques, 5",
    "sg:city":"Girona",
    "sg:orig_category":"Centros Empresariales",
    "sg:phone":"+34 972 23 88 07",
    "sg:postcode":"17005",
    "sg:province":"Girona",
    "wof:name":"Plataforma Educativa 3 Esses",
    "wof:placetype":"venue"
},
  "geometry": {"coordinates":[2.8091781139,41.9723396301],"type":"Point"}
}