{
  "type": "Feature",
  "properties": {
    "iso:country":"ES",
    "sg:address":"Arts Grafiques, 42",
    "sg:city":"Paiporta",
    "sg:orig_category":"Ingenier\u00cda, Centros De Estudios (diversos)",
    "sg:phone":"+34 963 97 32 82",
    "sg:postcode":"46200",
    "sg:province":"Valencia",
    "wof:name":"Sondeos Estructuras Y Geotecnia Sa",
    "wof:placetype":"venue"
},
  "geometry": {"coordinates":[-0.4111889899,39.4251708984],"type":"Point"}
}