{
  "type": "Feature",
  "properties": {
    "addr:full":"Carrer de Proven\u00c7a, 222 Terrassa Barcelona 08226",
    "addr:housenumber":"222",
    "addr:postcode":"08226",
    "addr:street":"Carrer De Provenc\u0327A",
    "iso:country":"ES",
    "sg:address":"Carrer de Proven\u00c7a, 222",
    "sg:city":"Terrassa",
    "sg:orig_category":"Imprenta",
    "sg:phone":"+34 937 35 61 91",
    "sg:postcode":"08226",
    "sg:province":"Barcelona",
    "wof:name":"Graficas Terrassa S. A.",
    "wof:placetype":"venue"
},
  "geometry": {"coordinates":[2.0237464905,41.583782196],"type":"Point"}
}