{
  "type": "Feature",
  "properties": {
    "iso:country":"ES",
    "sg:address":"Poli Ciudad Del Transporte, S/n",
    "sg:city":"San Juan De Mozarrifar",
    "sg:orig_category":"Comercio De Piezas De Recambio Y De Accesorios De Veh\u00cdculos, Veh\u00cdculos Industriales",
    "sg:phone":"+34 976 58 76 37",
    "sg:postcode":"50820",
    "sg:province":"Zaragoza",
    "wof:name":"Frenos Servet S.l.",
    "wof:placetype":"venue"
},
  "geometry": {"coordinates":[-0.8416489959,41.7171096802],"type":"Point"}
}