{
  "type": "Feature",
  "properties": {
    "addr:full":"Carr Beat Miro, 8 Sant Joan De Les Abadesses Girona 17860",
    "addr:housenumber":"8",
    "addr:postcode":"17860",
    "addr:street":"Carr Beat Miro",
    "iso:country":"ES",
    "sg:address":"Carr Beat Miro, 8",
    "sg:city":"Sant Joan De Les Abadesses",
    "sg:orig_category":"Ropa Para Se\u00d1oras (al Por Menor)",
    "sg:phone":"+34 972 72 21 43",
    "sg:postcode":"17860",
    "sg:province":"Girona",
    "wof:name":"Rossell Armengol Celia",
    "wof:placetype":"venue"
},
  "geometry": {"coordinates":[2.2859609127,42.2335891724],"type":"Point"}
}