{
  "type": "Feature",
  "properties": {
    "iso:country":"ES",
    "sg:address":"Calle de Deanes, 18",
    "sg:city":"Cordoba",
    "sg:orig_category":"Marroquiner\u00cda (confecci\u00d3n)",
    "sg:phone":"+34 957 29 81 83",
    "sg:postcode":"14003",
    "sg:province":"C\u00f3rdoba",
    "wof:name":"Martin Montero Miguel",
    "wof:placetype":"venue"
},
  "geometry": {"coordinates":[-4.7811393738,37.8798828125],"type":"Point"}
}