{
  "type": "Feature",
  "properties": {
    "iso:country":"ES",
    "sg:address":"Carrer de Castella, 9",
    "sg:city":"Prat Llobregat",
    "sg:orig_category":"Asesor\u00cda Fiscal Y Jur\u00cddica",
    "sg:phone":"+34 933 79 85 66",
    "sg:postcode":"08820",
    "sg:province":"Barcelona",
    "wof:name":"Garcia Lopez Eva",
    "wof:placetype":"venue"
},
  "geometry": {"coordinates":[2.0945699215,41.3273887634],"type":"Point"}
}