{
  "type": "Feature",
  "properties": {
    "addr:full":"Calle de Atea Kalea, 7 Lekeitio Vizcaya 48280",
    "addr:housenumber":"7",
    "addr:postcode":"48280",
    "addr:street":"Calle De Atea Kalea",
    "iso:country":"ES",
    "sg:address":"Calle de Atea Kalea, 7",
    "sg:city":"Lekeitio",
    "sg:orig_category":"Ense\u00d1anza: Idiomas",
    "sg:phone":"+34 946 84 28 69",
    "sg:postcode":"48280",
    "sg:province":"Vizcaya",
    "wof:name":"Euskaraz Koop. E.",
    "wof:placetype":"venue"
},
  "geometry": {"coordinates":[-2.5055258274,43.3612632751],"type":"Point"}
}