{
  "type": "Feature",
  "properties": {
    "iso:country":"ES",
    "sg:address":"V. Bianya (la Canya), S/n",
    "sg:city":"S. Joan Fonts",
    "sg:orig_category":"Cr\u00cda De Cerdos",
    "sg:phone":"+34 972 29 05 97",
    "sg:postcode":"17857",
    "sg:province":"Girona",
    "wof:name":"Can Berdaguer S.l.",
    "wof:placetype":"venue"
},
  "geometry": {"coordinates":[2.5107150078,42.2121162415],"type":"Point"}
}