{
  "type": "Feature",
  "properties": {
    "iso:country":"ES",
    "sg:address":"Calle de Reyes Catolicos, S/n",
    "sg:city":"Toledo",
    "sg:orig_category":"Ense\u00d1anza, Formaci\u00d3n Profesional: Aprendizaje",
    "sg:phone":"+34 925 25 62 01",
    "sg:postcode":"45002",
    "sg:province":"Toledo",
    "sg:website":"www.ventanillaempresarial.org",
    "wof:name":"Camara Oficial De Comercio E Industria De Toledo",
    "wof:placetype":"venue"
},
  "geometry": {"coordinates":[-4.0303487778,39.8565101624],"type":"Point"}
}