{
  "type": "Feature",
  "properties": {
    "addr:full":"Avda Jose Antonio, 27 Polan Toledo 45161",
    "addr:housenumber":"27",
    "addr:postcode":"45161",
    "addr:street":"Avda Jose Antonio",
    "iso:country":"ES",
    "sg:address":"Avda Jose Antonio, 27",
    "sg:city":"Polan",
    "sg:orig_category":"Electrodom\u00c9sticos (fabricaci\u00d3n, Al Por Mayor)",
    "sg:phone":"+34 925 37 00 77",
    "sg:postcode":"45161",
    "sg:province":"Toledo",
    "wof:name":"Cama\u00f1o Gomez Florentino",
    "wof:placetype":"venue"
},
  "geometry": {"coordinates":[-4.1622691154,39.790851593],"type":"Point"}
}