{
  "type": "Feature",
  "properties": {
    "iso:country":"ES",
    "sg:address":"Calle de Manuel Pedregal, 11",
    "sg:city":"Oviedo",
    "sg:orig_category":"Ingeniero",
    "sg:phone":"+34 985 22 01 19",
    "sg:postcode":"33001",
    "sg:province":"Asturias",
    "wof:name":"Arias Fernandez Ceferino",
    "wof:placetype":"venue"
},
  "geometry": {"coordinates":[-5.852602005,43.3664512634],"type":"Point"}
}