{
  "type": "Feature",
  "properties": {
    "addr:full":"Calle de Capitan, 47 Osuna Sevilla 41640",
    "addr:housenumber":"47",
    "addr:postcode":"41640",
    "addr:street":"Calle De Capitan",
    "iso:country":"ES",
    "sg:address":"Calle de Capitan, 47",
    "sg:city":"Osuna",
    "sg:orig_category":"T\u00c9cnicos Veterinarios",
    "sg:phone":"+34 954 81 20 70",
    "sg:postcode":"41640",
    "sg:province":"Sevilla",
    "wof:name":"Vazquez Delgado Antonio",
    "wof:placetype":"venue"
},
  "geometry": {"coordinates":[-5.099134922,37.233669281],"type":"Point"}
}