{
  "type": "Feature",
  "properties": {
    "iso:country":"ES",
    "sg:address":"Calle de Mar De Fora, 11",
    "sg:city":"Estacion",
    "sg:orig_category":"Venta, Alquiler De V\u00cddeo",
    "sg:phone":"+34 918 51 84 34",
    "sg:postcode":"28400",
    "sg:province":"Madrid",
    "wof:name":"Moreno Paniagua Miguel Angel",
    "wof:placetype":"venue"
},
  "geometry": {"coordinates":[-4.0136427879,40.6194534302],"type":"Point"}
}