{
  "type": "Feature",
  "properties": {
    "iso:country":"ES",
    "sg:address":"Calle de Agustin Escribano, 21",
    "sg:city":"Pagan",
    "sg:orig_category":"Cursos Particulares, Asistencia Escolar",
    "sg:phone":"+34 968 18 30 69",
    "sg:postcode":"30740",
    "sg:province":"Murcia",
    "wof:name":"Pedro Andres Jimenez S.l.",
    "wof:placetype":"venue"
},
  "geometry": {"coordinates":[-0.7838684916,37.8214263916],"type":"Point"}
}