{
  "type": "Feature",
  "properties": {
    "iso:country":"ES",
    "sg:address":"Av Montejurra, 3",
    "sg:city":"Sant Feliu Llobregat",
    "sg:orig_category":"Enfermeras: Consultas, Atenci\u00d3n A Domicilio",
    "sg:phone":"+34 936 66 31 53",
    "sg:postcode":"08980",
    "sg:province":"Barcelona",
    "wof:name":"Mascarell Guell Maria Del Carmen",
    "wof:placetype":"venue"
},
  "geometry": {"coordinates":[2.0518910885,41.3796882629],"type":"Point"}
}