{
  "type": "Feature",
  "properties": {
    "iso:country":"ES",
    "sg:address":"Plaz Pati De L'esglesia, 9",
    "sg:city":"Cullera",
    "sg:orig_category":"Reposter\u00cdas",
    "sg:phone":"+34 961 72 04 99",
    "sg:postcode":"46400",
    "sg:province":"Valencia",
    "wof:name":"Carreres Company Angeles",
    "wof:placetype":"venue"
},
  "geometry": {"coordinates":[-0.2545799911,39.1652297974],"type":"Point"}
}