{
  "type": "Feature",
  "properties": {
    "iso:country":"ES",
    "sg:address":"Calle de Obispo Maiques, 9",
    "sg:city":"Bocairent",
    "sg:orig_category":"Aguas (distribuci\u00d3n, Servicios)",
    "sg:phone":"+34 962 90 53 74",
    "sg:postcode":"46880",
    "sg:province":"Valencia",
    "wof:name":"Empresa General Valenciana Del Agua S.a.",
    "wof:placetype":"venue"
},
  "geometry": {"coordinates":[-0.6114510298,38.7653007507],"type":"Point"}
}