{
  "type": "Feature",
  "properties": {
    "addr:full":"Esglesia, 14 Vilablareix Girona 17180",
    "addr:housenumber":"14",
    "addr:postcode":"17180",
    "addr:street":"Esglesia",
    "iso:country":"ES",
    "sg:address":"Esglesia, 14",
    "sg:city":"Vilablareix",
    "sg:orig_category":"Frutas Y Legumbres Frescas (al Por Mayor)",
    "sg:phone":"+34 972 23 43 28",
    "sg:postcode":"17180",
    "sg:province":"Girona",
    "wof:name":"Gispert-sauch Viader Salvador",
    "wof:placetype":"venue"
},
  "geometry": {"coordinates":[2.7989549637,41.9561538696],"type":"Point"}
}