{
  "type": "Feature",
  "properties": {
    "iso:country":"ES",
    "sg:address":"Calle de General Ramirez De Madrid, 11",
    "sg:city":"Madrid",
    "sg:orig_category":"Empresarios",
    "sg:phone":"+34 915 70 23 56",
    "sg:postcode":"28020",
    "sg:province":"Madrid",
    "wof:name":"Fundacion Madrina",
    "wof:placetype":"venue"
},
  "geometry": {"coordinates":[-3.6980760098,40.4550704956],"type":"Point"}
}