{
  "type": "Feature",
  "properties": {
    "iso:country":"ES",
    "sg:address":"Calle de Fermin Requena, S/n",
    "sg:city":"Higuera Sierra",
    "sg:orig_category":"Asilos De Ancianos. Centros Privados",
    "sg:phone":"+34 959 19 62 88",
    "sg:postcode":"21220",
    "sg:province":"Huelva",
    "wof:name":"Fundacion Hogar Virgen Del Prado",
    "wof:placetype":"venue"
},
  "geometry": {"coordinates":[-6.4477891922,37.8380699158],"type":"Point"}
}