{
  "type": "Feature",
  "properties": {
    "addr:full":"Calle de Maestro Rodrigo, 2 Xirivella Valencia 46950",
    "addr:housenumber":"2",
    "addr:postcode":"46950",
    "addr:street":"Calle De Maestro Rodrigo",
    "iso:country":"ES",
    "sg:address":"Calle de Maestro Rodrigo, 2",
    "sg:city":"Xirivella",
    "sg:orig_category":"Carnicer\u00cdas, Carnicer\u00cdas",
    "sg:phone":"+34 963 79 79 93",
    "sg:postcode":"46950",
    "sg:province":"Valencia",
    "wof:name":"Lopez Garrido Fermin",
    "wof:placetype":"venue"
},
  "geometry": {"coordinates":[-0.4280540049,39.4642066956],"type":"Point"}
}