{
  "type": "Feature",
  "properties": {
    "addr:full":"Calle de Diamante, 6 Humanes De Madrid Madrid 28970",
    "addr:housenumber":"6",
    "addr:postcode":"28970",
    "addr:street":"Calle De Diamante",
    "iso:country":"ES",
    "sg:address":"Calle de Diamante, 6",
    "sg:city":"Humanes De Madrid",
    "sg:orig_category":"Herramientas Manuales (fabricaci\u00d3n, Al Por Mayor)",
    "sg:phone":"+34 914 28 00 55",
    "sg:postcode":"28970",
    "sg:province":"Madrid",
    "wof:name":"Cial Ferjor De Herramientas S.l.",
    "wof:placetype":"venue"
},
  "geometry": {"coordinates":[-3.8234438896,40.2684822083],"type":"Point"}
}