{
  "type": "Feature",
  "properties": {
    "iso:country":"ES",
    "sg:address":"Urb. Coto La Serena, 14",
    "sg:city":"Estepona",
    "sg:orig_category":"Promotores Constructores",
    "sg:phone":"+34 952 80 70 09",
    "sg:postcode":"29680",
    "sg:province":"M\u00e1laga",
    "wof:name":"Fesacamp S.l.",
    "wof:placetype":"venue"
},
  "geometry": {"coordinates":[-5.1452140808,36.4275817871],"type":"Point"}
}