{
  "type": "Feature",
  "properties": {
    "iso:country":"ES",
    "sg:address":"Plaz San Martin, 1",
    "sg:city":"Le\u00f3n",
    "sg:orig_category":"Perfumer\u00cda (al Por Menor)",
    "sg:phone":"+34 987 25 94 38",
    "sg:postcode":"24003",
    "sg:province":"Le\u00f3n",
    "wof:name":"Alonso Llamas Rosa Maria",
    "wof:placetype":"venue"
},
  "geometry": {"coordinates":[-5.5682911873,42.5982131958],"type":"Point"}
}