{
  "type": "Feature",
  "properties": {
    "addr:full":"Carr Maestro Serrano, 22 Manises Valencia 46940",
    "addr:housenumber":"22",
    "addr:postcode":"46940",
    "addr:street":"Carr Maestro Serrano",
    "iso:country":"ES",
    "sg:address":"Carr Maestro Serrano, 22",
    "sg:city":"Manises",
    "sg:orig_category":"Fabrica De Cer\u00c1micas",
    "sg:phone":"+34 961 54 53 92",
    "sg:postcode":"46940",
    "sg:province":"Valencia",
    "sg:website":"w.w.w.spaincer.com",
    "wof:name":"Ilexpa S.l.",
    "wof:placetype":"venue"
},
  "geometry": {"coordinates":[-0.466621995,39.490940094],"type":"Point"}
}