{
  "type": "Feature",
  "properties": {
    "addr:full":"Calle de San Fernando, 43 Cartagena Murcia 30201",
    "addr:housenumber":"43",
    "addr:postcode":"30201",
    "addr:street":"Calle De San Fernando",
    "iso:country":"ES",
    "sg:address":"Calle de San Fernando, 43",
    "sg:city":"Cartagena",
    "sg:orig_category":"Zapatos (al Por Menor)",
    "sg:phone":"+34 968 52 03 52",
    "sg:postcode":"30201",
    "sg:province":"Murcia",
    "wof:name":"Manuel Sanchez Carmen",
    "wof:placetype":"venue"
},
  "geometry": {"coordinates":[-0.985912025,37.6041030884],"type":"Point"}
}