{
  "type": "Feature",
  "properties": {
    "iso:country":"ES",
    "sg:address":"Plaz Maestro Odon Alonso, 1",
    "sg:city":"Le\u00f3n",
    "sg:orig_category":"Empresas De Portes Y Mensajer\u00cda",
    "sg:phone":"+34 987 24 56 54",
    "sg:postcode":"24002",
    "sg:province":"Le\u00f3n",
    "wof:name":"Postal Stamp S.l.u.",
    "wof:placetype":"venue"
},
  "geometry": {"coordinates":[-5.5744137764,42.6037864685],"type":"Point"}
}