{
  "type": "Feature",
  "properties": {
    "iso:country":"ES",
    "sg:address":"Calle de Ramon Y Cajal, 21",
    "sg:city":"Olula Rio",
    "sg:orig_category":"\u00d3ptica: Instrumentos (fabricaci\u00d3n)",
    "sg:phone":"+34 950 44 16 22",
    "sg:postcode":"04860",
    "sg:province":"Almer\u00eda",
    "wof:name":"Horta Sorroche Antonio",
    "wof:placetype":"venue"
},
  "geometry": {"coordinates":[-2.297713995,37.3543357849],"type":"Point"}
}