{
  "type": "Feature",
  "properties": {
    "iso:country":"ES",
    "sg:address":"Puerto, S/n",
    "sg:city":"Almeria",
    "sg:orig_category":"Ense\u00d1anza, Formaci\u00d3n Profesional: Aprendizaje",
    "sg:phone":"+34 950 23 01 62",
    "sg:postcode":"04002",
    "sg:province":"Almer\u00eda",
    "wof:name":"Ministerio De Economia",
    "wof:placetype":"venue"
},
  "geometry": {"coordinates":[-2.5000441074,36.8265953064],"type":"Point"}
}