{
  "type": "Feature",
  "properties": {
    "iso:country":"ES",
    "sg:address":"Calle de Fernandez De Ribera, 32",
    "sg:city":"Sevilla",
    "sg:orig_category":"Asesor\u00cda Sobre Comunicaci\u00d3n De Empresas",
    "sg:phone":"+34 954 92 34 96",
    "sg:postcode":"41005",
    "sg:province":"Sevilla",
    "wof:name":"Moreno Canela Francisco Manuel",
    "wof:placetype":"venue"
},
  "geometry": {"coordinates":[-5.9694991112,37.3762779236],"type":"Point"}
}