{
  "type": "Feature",
  "properties": {
    "iso:country":"ES",
    "sg:address":"Calle de Jaen (de), 1",
    "sg:city":"Fuenlabrada",
    "sg:orig_category":"Aparatos, Sistemas De Tele",
    "sg:phone":"+34 916 15 51 58",
    "sg:postcode":"28941",
    "sg:province":"Madrid",
    "wof:name":"Inpleca S.l.",
    "wof:placetype":"venue"
},
  "geometry": {"coordinates":[-3.7995491028,40.2904052734],"type":"Point"}
}