{
  "type": "Feature",
  "properties": {
    "addr:full":"Carrer de Numancia, 85 Barcelona Barcelona 08029",
    "addr:housenumber":"85",
    "addr:postcode":"08029",
    "addr:street":"Carrer De Numancia",
    "iso:country":"ES",
    "sg:address":"Carrer de Numancia, 85",
    "sg:city":"Barcelona",
    "sg:orig_category":"Arquitectos",
    "sg:phone":"+34 934 30 10 96",
    "sg:postcode":"08029",
    "sg:province":"Barcelona",
    "wof:name":"Urtasun Andion Javier",
    "wof:placetype":"venue"
},
  "geometry": {"coordinates":[2.1369590759,41.385055542],"type":"Point"}
}