{
  "type": "Feature",
  "properties": {
    "addr:full":"Calle de Oca, 95 Madrid Madrid 28025",
    "addr:housenumber":"95",
    "addr:postcode":"madrid;28025",
    "addr:street":"Calle De Oca",
    "iso:country":"ES",
    "sg:address":"Calle de Oca, 95",
    "sg:city":"Madrid",
    "sg:orig_category":"Servicios Gsm",
    "sg:phone":"+34 914 62 58 89",
    "sg:postcode":"28025",
    "sg:province":"Madrid",
    "wof:name":"Gran Servicio Movil S.l.",
    "wof:placetype":"venue"
},
  "geometry": {"coordinates":[-3.7433540821,40.388053894],"type":"Point"}
}