{
  "type": "Feature",
  "properties": {
    "iso:country":"ES",
    "sg:address":"Avda Puerta Del Mar, 11",
    "sg:city":"Marbella",
    "sg:orig_category":"Tatuajes",
    "sg:phone":"+34 952 86 20 46",
    "sg:postcode":"29600",
    "sg:province":"M\u00e1laga",
    "wof:name":"Pino Urbano Antonio",
    "wof:placetype":"venue"
},
  "geometry": {"coordinates":[-4.8850998878,36.5072822571],"type":"Point"}
}