{
  "type": "Feature",
  "properties": {
    "iso:country":"ES",
    "sg:address":"Calle de Arganzuela, 29",
    "sg:city":"Madrid",
    "sg:orig_category":"Compraventa De Antig\u00dcedades",
    "sg:phone":"+34 915 39 17 93",
    "sg:postcode":"28005",
    "sg:province":"Madrid",
    "wof:name":"Rodriguez Polo Jose Antonio",
    "wof:placetype":"venue"
},
  "geometry": {"coordinates":[-3.7093234062,40.4070930481],"type":"Point"}
}