{
  "type": "Feature",
  "properties": {
    "addr:full":"Plza. Constitucion, S/n Bubion Granada 18412",
    "addr:postcode":"18412",
    "addr:street":"Plza. Constitucion S / N Bubion",
    "iso:country":"ES",
    "sg:address":"Plza. Constitucion, S/n",
    "sg:city":"Bubion",
    "sg:orig_category":"Administraciones Regionales, Departamentales Y Locales",
    "sg:phone":"+34 958 76 30 32",
    "sg:postcode":"18412",
    "sg:province":"Granada",
    "wof:name":"Ayuntamiento",
    "wof:placetype":"venue"
},
  "geometry": {"coordinates":[-3.3553490639,36.9511108398],"type":"Point"}
}