{
  "type": "Feature",
  "properties": {
    "iso:country":"ES",
    "sg:address":"Calle de Herreria (la), 1",
    "sg:city":"Sahagun",
    "sg:orig_category":"Pompas F\u00danebres, Inhumaciones Y Cremaciones",
    "sg:phone":"+34 987 78 09 08",
    "sg:postcode":"24320",
    "sg:province":"Le\u00f3n",
    "wof:name":"Albala Minette Sebastian",
    "wof:placetype":"venue"
},
  "geometry": {"coordinates":[-5.0275292397,42.3704452515],"type":"Point"}
}