{
  "type": "Feature",
  "properties": {
    "addr:full":"Calle de Santa Ursula, 8 Toledo Toledo 45002",
    "addr:housenumber":"8",
    "addr:postcode":"45002",
    "addr:street":"Calle De Santa Ursula",
    "iso:country":"ES",
    "sg:address":"Calle de Santa Ursula, 8",
    "sg:city":"Toledo",
    "sg:orig_category":"Esmaltado De Metales",
    "sg:phone":"+34 925 25 41 34",
    "sg:postcode":"45002",
    "sg:province":"Toledo",
    "wof:name":"Paniagua Serrano Jose Antonio",
    "wof:placetype":"venue"
},
  "geometry": {"coordinates":[-4.0261111259,39.8559684753],"type":"Point"}
}