{
  "type": "Feature",
  "properties": {
    "addr:full":"Calle de Torre Sant Vicente, 25 Las Villas Castell\u00f3n 12560",
    "addr:housenumber":"25",
    "addr:postcode":"12560",
    "addr:street":"Calle De Torre Sant Vicente;Castello\u0301N",
    "iso:country":"ES",
    "sg:address":"Calle de Torre Sant Vicente, 25",
    "sg:city":"Las Villas",
    "sg:orig_category":"Supermercados Y Hipermercados",
    "sg:phone":"+34 964 30 22 03",
    "sg:postcode":"12560",
    "sg:province":"Castell\u00f3n",
    "wof:name":"Consum Sociedad Cooperativa Limitada",
    "wof:placetype":"venue"
},
  "geometry": {"coordinates":[0.0590550005,40.0523414612],"type":"Point"}
}