{
  "type": "Feature",
  "properties": {
    "iso:country":"ES",
    "sg:address":"Ctra. Vieja Capdella, S/n",
    "sg:city":"Calvia",
    "sg:orig_category":"Cementerios",
    "sg:phone":"+34 971 67 03 15",
    "sg:postcode":"07184",
    "sg:province":"Islas Baleares",
    "wof:name":"Ajuntament De Calvia",
    "wof:placetype":"venue"
},
  "geometry": {"coordinates":[2.519793272,39.5626335144],"type":"Point"}
}