{
  "type": "Feature",
  "properties": {
    "addr:full":"Carr Saragossa, 48 Badalona Barcelona 08912",
    "addr:housenumber":"48",
    "addr:postcode":"08912",
    "addr:street":"Carr Saragossa",
    "iso:country":"ES",
    "sg:address":"Carr Saragossa, 48",
    "sg:city":"Badalona",
    "sg:orig_category":"Peluqueros: De Se\u00d1oras",
    "sg:phone":"+34 933 99 72 22",
    "sg:postcode":"08912",
    "sg:province":"Barcelona",
    "wof:name":"Blay Valles Carmen",
    "wof:placetype":"venue"
},
  "geometry": {"coordinates":[2.2377500534,41.4465904236],"type":"Point"}
}