{
  "type": "Feature",
  "properties": {
    "iso:country":"ES",
    "sg:address":"Plaz San Ignacio De Loyola, 2",
    "sg:city":"Cordoba",
    "sg:orig_category":"Asesor\u00cda Fiscal Y Jur\u00cddica",
    "sg:phone":"+34 957 47 35 35",
    "sg:postcode":"14008",
    "sg:province":"C\u00f3rdoba",
    "wof:name":"Pacheco Ortega Juan Antonio",
    "wof:placetype":"venue"
},
  "geometry": {"coordinates":[-4.7832221985,37.8856925964],"type":"Point"}
}