{
  "type": "Feature",
  "properties": {
    "iso:country":"ES",
    "sg:address":"Calle de Donoso Cortes, 9",
    "sg:city":"Don Benito",
    "sg:orig_category":"Peleter\u00cdas",
    "sg:phone":"+34 924 80 54 28",
    "sg:postcode":"06400",
    "sg:province":"Badajoz",
    "wof:name":"Gallardo Y Donoso C.b.",
    "wof:placetype":"venue"
},
  "geometry": {"coordinates":[-5.860622406,38.955657959],"type":"Point"}
}