{
  "type": "Feature",
  "properties": {
    "addr:full":"Carrer de Sant Antoni Maria Claret, 221 Barcelona Barcelona 08041",
    "addr:housenumber":"221",
    "addr:postcode":"08041",
    "addr:street":"Carrer De Sant Antoni Maria Claret",
    "iso:country":"ES",
    "sg:address":"Carrer de Sant Antoni Maria Claret, 221",
    "sg:city":"Barcelona",
    "sg:orig_category":"Molduras, Junquillos, Listones Y Molduras Perforadas",
    "sg:phone":"+34 934 55 70 33",
    "sg:postcode":"08041",
    "sg:province":"Barcelona",
    "wof:name":"Vzquez Martonez Angel Fernando",
    "wof:placetype":"venue"
},
  "geometry": {"coordinates":[2.0835642815,41.3691749573],"type":"Point"}
}