{
  "type": "Feature",
  "properties": {
    "addr:full":"Calle de Principal De La Moreria, 22 Arevalo \u00c1vila 05200",
    "addr:housenumber":"22",
    "addr:postcode":"05200",
    "addr:street":"Calle De Principal De La Moreria",
    "iso:country":"ES",
    "sg:address":"Calle de Principal De La Moreria, 22",
    "sg:city":"Arevalo",
    "sg:orig_category":"Frutas Y Legumbres Frescas (al Por Mayor)",
    "sg:phone":"+34 920 30 00 74",
    "sg:postcode":"05200",
    "sg:province":"\u00c1vila",
    "wof:name":"Legumbres La Mora\u00f1a S.l.",
    "wof:placetype":"venue"
},
  "geometry": {"coordinates":[-4.7219691277,41.0625267029],"type":"Point"}
}