{
  "type": "Feature",
  "properties": {
    "iso:country":"ES",
    "sg:address":"Avda Txori Erri, 46",
    "sg:city":"Basozabal",
    "sg:orig_category":"Agentes, Concesionarios Y Sucursales De Veh\u00cdculos",
    "sg:phone":"+34 944 53 25 15",
    "sg:postcode":"48150",
    "sg:province":"Vizcaya",
    "wof:name":"Goiri-78 S.l.",
    "wof:placetype":"venue"
},
  "geometry": {"coordinates":[-2.9210519791,43.2983283997],"type":"Point"}
}