{
  "type": "Feature",
  "properties": {
    "addr:full":"Calle de Navasecas, 6 Madrid Madrid 28023",
    "addr:housenumber":"6",
    "addr:postcode":"28023",
    "addr:street":"Calle De Navasecas",
    "iso:country":"ES",
    "sg:address":"Calle de Navasecas, 6",
    "sg:city":"Madrid",
    "sg:orig_category":"Inmobiliaria (agencias)",
    "sg:phone":"+34 917 08 02 13",
    "sg:postcode":"28023",
    "sg:province":"Madrid",
    "wof:name":"Maztice Guecho Grup S.l.",
    "wof:placetype":"venue"
},
  "geometry": {"coordinates":[-3.8361709118,40.4774703979],"type":"Point"}
}