{
  "type": "Feature",
  "properties": {
    "addr:full":"Calle de Santa Brigida, 2 Ecija Sevilla 41400",
    "addr:housenumber":"2",
    "addr:postcode":"41400",
    "addr:street":"Calle De Santa Brigida",
    "iso:country":"ES",
    "sg:address":"Calle de Santa Brigida, 2",
    "sg:city":"Ecija",
    "sg:orig_category":"Mec\u00c1nico Del Autom\u00d3vil",
    "sg:phone":"+34 954 83 31 12",
    "sg:postcode":"41400",
    "sg:province":"Sevilla",
    "wof:name":"Guerrero Molero Jose",
    "wof:placetype":"venue"
},
  "geometry": {"coordinates":[-5.0736441612,37.5393104553],"type":"Point"}
}