{
  "type": "Feature",
  "properties": {
    "iso:country":"ES",
    "sg:address":"Calle de Rafael Fernandez Hijicos, 12",
    "sg:city":"Madrid",
    "sg:orig_category":"Guarder\u00cdas",
    "sg:phone":"+34 917 86 36 94",
    "sg:postcode":"28038",
    "sg:province":"Madrid",
    "wof:name":"Fundacion Palomeras Altas",
    "wof:placetype":"venue"
},
  "geometry": {"coordinates":[-3.6355640888,40.3912162781],"type":"Point"}
}