{
  "type": "Feature",
  "properties": {
    "addr:full":"Calle de Reino De Leon, 10 Santa Lucia Le\u00f3n 24650",
    "addr:housenumber":"10",
    "addr:postcode":"24650",
    "addr:street":"Calle De Reino De Leon;Leo\u0301N",
    "iso:country":"ES",
    "sg:address":"Calle de Reino De Leon, 10",
    "sg:city":"Santa Lucia",
    "sg:orig_category":"Cajas De Ahorro",
    "sg:phone":"+34 987 58 63 75",
    "sg:postcode":"24650",
    "sg:province":"Le\u00f3n",
    "sg:website":"www.cajaespa\u00f1a.es",
    "wof:name":"Caja Espa\u00d1a De Inversiones Caja De Ahorros Y Monte De Piedad",
    "wof:placetype":"venue"
},
  "geometry": {"coordinates":[-5.6393241882,42.874004364],"type":"Point"}
}