{
  "type": "Feature",
  "properties": {
    "iso:country":"ES",
    "sg:address":"Calle de Antonio De La Barrera, 10",
    "sg:city":"Priego Cordoba",
    "sg:orig_category":"Molduras, Junquillos, Listones Y Molduras Perforadas",
    "sg:phone":"+34 957 70 13 48",
    "sg:postcode":"14800",
    "sg:province":"C\u00f3rdoba",
    "wof:name":"Luque Avila Antonio",
    "wof:placetype":"venue"
},
  "geometry": {"coordinates":[-4.1958050728,37.4379844666],"type":"Point"}
}