{
  "type": "Feature",
  "properties": {
    "addr:full":"Calle de Castell De Pop, 25 Valencia Valencia 46024",
    "addr:housenumber":"25",
    "addr:postcode":"46024",
    "addr:street":"Calle De Castell;Pop",
    "iso:country":"ES",
    "sg:address":"Calle de Castell De Pop, 25",
    "sg:city":"Valencia",
    "sg:orig_category":"Molduras, Junquillos, Listones Y Molduras Perforadas",
    "sg:phone":"+34 963 67 10 69",
    "sg:postcode":"46024",
    "sg:province":"Valencia",
    "wof:name":"Cafe Bar La Pe\u00f1a C.b.",
    "wof:placetype":"venue"
},
  "geometry": {"coordinates":[-0.3324599862,39.4480400085],"type":"Point"}
}