{
  "type": "Feature",
  "properties": {
    "iso:country":"ES",
    "sg:address":"Plaz Martin Herrera, S/n",
    "sg:city":"Caldas De Reis",
    "sg:classifiers":[
        {
            "category":"Taxi",
            "type":"Transportation"
        }
    ],
    "sg:phone":"+34 986 54 01 07",
    "sg:postcode":"36650",
    "sg:province":"Pontevedra",
    "wof:name":"Agrupacion Local Auto-patronos Del Taxis",
    "wof:placetype":"venue"
},
  "geometry": {"coordinates":[-8.6710605621,42.623085022],"type":"Point"}
}