{
  "type": "Feature",
  "properties": {
    "iso:country":"ES",
    "sg:address":"Calle de Barcelona, 86",
    "sg:city":"Zaragoza",
    "sg:orig_category":"Carnicer\u00cdas, Carnicer\u00cdas",
    "sg:phone":"+34 976 53 06 68",
    "sg:postcode":"50017",
    "sg:province":"Zaragoza",
    "wof:name":"Iba\u00f1ez Asenjo Esteban",
    "wof:placetype":"venue"
},
  "geometry": {"coordinates":[-0.9104146957,41.6499023438],"type":"Point"}
}