{
  "type": "Feature",
  "properties": {
    "iso:country":"ES",
    "sg:address":"Calle de Zurbaran, 6",
    "sg:city":"Ubeda",
    "sg:orig_category":"Abogados",
    "sg:phone":"+34 953 79 12 94",
    "sg:postcode":"23400",
    "sg:province":"Ja\u00e9n",
    "wof:name":"Pasquau Fernandez Manuel",
    "wof:placetype":"venue"
},
  "geometry": {"coordinates":[-3.3747859001,38.0148200989],"type":"Point"}
}