{
  "type": "Feature",
  "properties": {
    "iso:country":"ES",
    "sg:address":"Cmno Aral, S/n",
    "sg:city":"Algaba",
    "sg:orig_category":"Comercio De Piezas De Recambio Y De Accesorios De Veh\u00cdculos, Veh\u00cdculos Industriales",
    "sg:phone":"+34 955 78 70 71",
    "sg:postcode":"41980",
    "sg:province":"Sevilla",
    "wof:name":"Roditaly 2002 S.l.",
    "wof:placetype":"venue"
},
  "geometry": {"coordinates":[-6.0153942108,37.4607162476],"type":"Point"}
}