{
  "type": "Feature",
  "properties": {
    "addr:full":"Avda Coronacion, 71 Agreda Soria 42100",
    "addr:housenumber":"71",
    "addr:postcode":"42100",
    "addr:street":"Avda Coronacion",
    "iso:country":"ES",
    "sg:address":"Avda Coronacion, 71",
    "sg:city":"Agreda",
    "sg:orig_category":"Carnicer\u00cdas, Carnicer\u00cdas",
    "sg:phone":"+34 976 64 70 48",
    "sg:postcode":"42100",
    "sg:province":"Soria",
    "wof:name":"Ome\u00f1aca Calvo Angel",
    "wof:placetype":"venue"
},
  "geometry": {"coordinates":[-1.9203989506,41.8517684937],"type":"Point"}
}