{
  "type": "Feature",
  "properties": {
    "iso:country":"ES",
    "sg:address":"Carrer de Badajoz, 16",
    "sg:city":"Rubi",
    "sg:orig_category":"Empresarios",
    "sg:phone":"+34 935 86 28 35",
    "sg:postcode":"08191",
    "sg:province":"Barcelona",
    "wof:name":"Promociones Y Reformas Grupo Novalinea S.l",
    "wof:placetype":"venue"
},
  "geometry": {"coordinates":[2.046724081,41.500629425],"type":"Point"}
}