{
  "type": "Feature",
  "properties": {
    "addr:full":"Calle de Real, 112 Illescas Toledo 45200",
    "addr:housenumber":"112",
    "addr:postcode":"45200",
    "addr:street":"Calle De Real",
    "iso:country":"ES",
    "sg:address":"Calle de Real, 112",
    "sg:city":"Illescas",
    "sg:orig_category":"Inmobiliaria (agencias)",
    "sg:phone":"+34 925 51 19 70",
    "sg:postcode":"45200",
    "sg:province":"Toledo",
    "wof:name":"Immobasa Asinm S.l.",
    "wof:placetype":"venue"
},
  "geometry": {"coordinates":[-3.8492090702,40.1250801086],"type":"Point"}
}