{
  "type": "Feature",
  "properties": {
    "iso:country":"ES",
    "sg:address":"Calle de Gil De Andrade, 9",
    "sg:city":"Alcala Henares",
    "sg:orig_category":"Molduras, Junquillos, Listones Y Molduras Perforadas",
    "sg:phone":"+34 918 88 56 52",
    "sg:postcode":"28804",
    "sg:province":"Madrid",
    "wof:name":"Martin Salinas Victor",
    "wof:placetype":"venue"
},
  "geometry": {"coordinates":[-3.3546190262,40.4877433777],"type":"Point"}
}