{
  "type": "Feature",
  "properties": {
    "iso:country":"ES",
    "sg:address":"Avda Paz (la), 27",
    "sg:city":"Socovos",
    "sg:orig_category":"Quincaller\u00cda (al Por Menor)",
    "sg:phone":"+34 967 42 02 95",
    "sg:postcode":"02435",
    "sg:province":"Albacete",
    "wof:name":"Torferro S.l.",
    "wof:placetype":"venue"
},
  "geometry": {"coordinates":[-1.9135969877,38.3026657104],"type":"Point"}
}