{
  "type": "Feature",
  "properties": {
    "addr:full":"Calle de Cuatro, 3 Madrid Madrid 28022",
    "addr:housenumber":"3",
    "addr:postcode":"28022",
    "addr:street":"Calle De Cuatro",
    "iso:country":"ES",
    "sg:address":"Calle de Cuatro, 3",
    "sg:city":"Madrid",
    "sg:orig_category":"Venta, Instalaci\u00d3n, Reparaci\u00d3n De Antenas Para Televisi\u00d3n",
    "sg:phone":"+34 917 41 42 99",
    "sg:postcode":"28022",
    "sg:province":"Madrid",
    "wof:name":"Arsict Comunicaciones S.l.",
    "wof:placetype":"venue"
},
  "geometry": {"coordinates":[-3.5937769413,40.4488105774],"type":"Point"}
}