{
  "type": "Feature",
  "properties": {
    "addr:full":"Calle de Ildefonso Sanchez Del Rio, 1 Pola De Siero Asturias 33510",
    "addr:housenumber":"1",
    "addr:postcode":"33510",
    "addr:street":"Calle De Ildefonso Sanchez Del Rio",
    "iso:country":"ES",
    "sg:address":"Calle de Ildefonso Sanchez Del Rio, 1",
    "sg:city":"Pola De Siero",
    "sg:orig_category":"\u00d3ptica: Instrumentos (fabricaci\u00d3n)",
    "sg:phone":"+34 985 72 48 45",
    "sg:postcode":"33510",
    "sg:province":"Asturias",
    "wof:name":"Castellon Valbuena Marta",
    "wof:placetype":"venue"
},
  "geometry": {"coordinates":[-5.6640248299,43.3919372559],"type":"Point"}
}