{
  "type": "Feature",
  "properties": {
    "addr:full":"Calle de Reyes De Navarra, 18 Vitoria-gasteiz \u00c1lava 01013",
    "addr:housenumber":"18",
    "addr:postcode":"01013",
    "addr:street":"Calle De Reyes De Navarra",
    "iso:country":"ES",
    "sg:address":"Calle de Reyes De Navarra, 18",
    "sg:city":"Vitoria-gasteiz",
    "sg:orig_category":"Suministros Y Materiales Industriales",
    "sg:phone":"+34 945 25 26 00",
    "sg:postcode":"01013",
    "sg:province":"\u00c1lava",
    "wof:name":"Jose Charola, S.a.",
    "wof:placetype":"venue"
},
  "geometry": {"coordinates":[-2.6668961048,42.8558921814],"type":"Point"}
}