{
  "type": "Feature",
  "properties": {
    "iso:country":"ES",
    "sg:address":"La Cui\u00f1a, S/n",
    "sg:city":"Pontes Garcia Rodriguez",
    "sg:orig_category":"Contenedores (mercanc\u00cdas)",
    "sg:phone":"+34 981 45 07 49",
    "sg:postcode":"15320",
    "sg:province":"La Coru\u00f1a",
    "wof:name":"Alonso Carballo Emilio Ramon",
    "wof:placetype":"venue"
},
  "geometry": {"coordinates":[-7.8519210815,43.4501571655],"type":"Point"}
}