{
  "type": "Feature",
  "properties": {
    "addr:full":"Calle de Lisboa, 30 Torrejon Ardoz Madrid 28850",
    "addr:housenumber":"30",
    "addr:postcode":"28850",
    "addr:street":"Calle De Lisboa",
    "iso:country":"ES",
    "sg:address":"Calle de Lisboa, 30",
    "sg:city":"Torrejon Ardoz",
    "sg:orig_category":"Papeler\u00cdas, Librer\u00cdas",
    "sg:phone":"+34 916 77 05 72",
    "sg:postcode":"28850",
    "sg:province":"Madrid",
    "wof:name":"Molinero Rica Elena",
    "wof:placetype":"venue"
},
  "geometry": {"coordinates":[-3.4695646763,40.4624481201],"type":"Point"}
}