{
  "type": "Feature",
  "properties": {
    "addr:full":"Calle de Comunidad De Madrid (de La), 11 Mejorada Campo Madrid 28840",
    "addr:postcode":"11 mejorada;28840",
    "addr:street":"Calle De Comunidad",
    "iso:country":"ES",
    "sg:address":"Calle de Comunidad De Madrid (de La), 11",
    "sg:city":"Mejorada Campo",
    "sg:orig_category":"Arreglo, Reparaci\u00d3n, Piezas Sueltas De Televisi\u00d3n, V\u00cddeo, Hi",
    "sg:phone":"+34 916 68 21 00",
    "sg:postcode":"28840",
    "sg:province":"Madrid",
    "wof:name":"Televicolor Jawen S.l.",
    "wof:placetype":"venue"
},
  "geometry": {"coordinates":[-3.4780917168,40.3952713013],"type":"Point"}
}