{
  "type": "Feature",
  "properties": {
    "addr:full":"Carrer de Migdia, 1 Vilafranca Penedes Barcelona 08720",
    "addr:housenumber":"1",
    "addr:postcode":"08720",
    "addr:street":"Carrer De Migdia;Penedes Barcelona",
    "iso:country":"ES",
    "sg:address":"Carrer de Migdia, 1",
    "sg:city":"Vilafranca Penedes",
    "sg:orig_category":"Inform\u00c1tica: Consultores",
    "sg:phone":"+34 938 17 05 77",
    "sg:postcode":"08720",
    "sg:province":"Barcelona",
    "wof:name":"Acosta Berrio Josefa",
    "wof:placetype":"venue"
},
  "geometry": {"coordinates":[1.7017785311,41.3452262878],"type":"Point"}
}