{
  "type": "Feature",
  "properties": {
    "addr:full":"Calle de Sagasti, 1 Barakaldo Vizcaya 48903",
    "addr:housenumber":"1",
    "addr:postcode":"48903",
    "addr:street":"Calle De Sagasti",
    "iso:country":"ES",
    "sg:address":"Calle de Sagasti, 1",
    "sg:city":"Barakaldo",
    "sg:orig_category":"Pescader\u00cdas (al Por Menor)",
    "sg:phone":"+34 944 90 10 29",
    "sg:postcode":"48903",
    "sg:province":"Vizcaya",
    "wof:name":"Pescaderias Maria Luisa Sl",
    "wof:placetype":"venue"
},
  "geometry": {"coordinates":[-2.9829919338,43.2834091187],"type":"Point"}
}