{
  "type": "Feature",
  "properties": {
    "addr:full":"Calle de Sevilla, 27 Osuna Sevilla 41640",
    "addr:housenumber":"27",
    "addr:postcode":"41640",
    "addr:street":"Calle De Sevilla",
    "iso:country":"ES",
    "sg:address":"Calle de Sevilla, 27",
    "sg:city":"Osuna",
    "sg:orig_category":"Inform\u00c1tica Equipo Y Programas (al Por Mayor)",
    "sg:phone":"+34 954 81 02 94",
    "sg:postcode":"41640",
    "sg:province":"Sevilla",
    "wof:name":"Urso Sistemas Informaticos Sl",
    "wof:placetype":"venue"
},
  "geometry": {"coordinates":[-5.1059288979,37.2372741699],"type":"Point"}
}