{
  "type": "Feature",
  "properties": {
    "addr:full":"Cmno Cmno De Labiano, 24 Mutiloagoiti Navarra 31192",
    "addr:housenumber":"24",
    "addr:postcode":"31192",
    "addr:street":"Cmno Cmno De Labiano",
    "iso:country":"ES",
    "sg:address":"Cmno Cmno De Labiano, 24",
    "sg:city":"Mutiloagoiti",
    "sg:orig_category":"Fabricaci\u00d3n De Muebles",
    "sg:phone":"+34 948 24 17 52",
    "sg:postcode":"31192",
    "sg:province":"Navarra",
    "wof:name":"Manufacturas De La Madera Aranaz S. L.",
    "wof:placetype":"venue"
},
  "geometry": {"coordinates":[-1.6151809692,42.7892303467],"type":"Point"}
}