{
  "type": "Feature",
  "properties": {
    "addr:full":"O Cruceiro Vello, S/n Ribadumia Pontevedra 36636",
    "addr:housenumber":"s",
    "addr:postcode":"36636",
    "addr:street":"O;Vello;/ N",
    "iso:country":"ES",
    "sg:address":"O Cruceiro Vello, S/n",
    "sg:city":"Ribadumia",
    "sg:orig_category":"Lavado, Limpieza De Veh\u00cdculos",
    "sg:phone":"+34 986 71 80 78",
    "sg:postcode":"36636",
    "sg:province":"Pontevedra",
    "wof:name":"Martinez Castro Ramon",
    "wof:placetype":"venue"
},
  "geometry": {"coordinates":[-97.78224945069999,45.7040786743],"type":"Point"}
}