{
  "type": "Feature",
  "properties": {
    "iso:country":"ES",
    "sg:address":"Calle de Zamora, 1",
    "sg:city":"Parla",
    "sg:orig_category":"Librer\u00cdas",
    "sg:phone":"+34 916 05 74 32",
    "sg:postcode":"28980",
    "sg:province":"Madrid",
    "wof:name":"Duero Villcor S.l.",
    "wof:placetype":"venue"
},
  "geometry": {"coordinates":[-3.7632091045,40.2420730591],"type":"Point"}
}