{
  "type": "Feature",
  "properties": {
    "iso:country":"ES",
    "sg:address":"Avda Catalanet, 19",
    "sg:city":"Santa Pola",
    "sg:classifiers":[
        {
            "category":"Professional",
            "subcategory":"Management & Consulting",
            "type":"Services"
        }
    ],
    "sg:phone":"+34 965 41 17 03",
    "sg:postcode":"03130",
    "sg:province":"Alicante",
    "sg:tags":[
        "asesor\u00cda",
        "en",
        "marketing"
    ],
    "wof:name":"Gascon Sala Rafael",
    "wof:placetype":"venue"
},
  "geometry": {"coordinates":[-0.532171011,38.1906776428],"type":"Point"}
}