{
  "type": "Feature",
  "properties": {
    "addr:full":"Avda Madrid De, 28 Donostia-san Sebastian Guip\u00f9zcoa 20011",
    "addr:housenumber":"28",
    "addr:postcode":"20011",
    "addr:street":"Avda Madrid De",
    "iso:country":"ES",
    "sg:address":"Avda Madrid De, 28",
    "sg:city":"Donostia-san Sebastian",
    "sg:orig_category":"Tapicer\u00cdas",
    "sg:phone":"+34 943 46 52 95",
    "sg:postcode":"20011",
    "sg:province":"Guip\u00f9zcoa",
    "wof:name":"Mendizabal Aguirre Arantza",
    "wof:placetype":"venue"
},
  "geometry": {"coordinates":[-1.975581646,43.3032608032],"type":"Point"}
}