{
  "type": "Feature",
  "properties": {
    "iso:country":"ES",
    "sg:address":"Av. Scho Fuerte, 77",
    "sg:city":"Iru\u00f1a",
    "sg:orig_category":"Lencer\u00cda Femenina, Corseter\u00cda, Trajes De Ba\u00d1o (al Por Menor)",
    "sg:phone":"+34 948 26 92 13",
    "sg:postcode":"31008",
    "sg:province":"Navarra",
    "wof:name":"Lizarraga Pabolleta Angeles",
    "wof:placetype":"venue"
},
  "geometry": {"coordinates":[-1.6577689648,42.8104057312],"type":"Point"}
}