{
  "type": "Feature",
  "properties": {
    "iso:country":"ES",
    "sg:address":"Calle de Robledo, S/n",
    "sg:city":"Menasalbas",
    "sg:orig_category":"Hormig\u00d3n Listo Para Usar",
    "sg:phone":"+34 925 41 31 07",
    "sg:postcode":"45128",
    "sg:province":"Toledo",
    "wof:name":"Hermanos Gomez Dacu\u00f1a S.c.l.",
    "wof:placetype":"venue"
},
  "geometry": {"coordinates":[-4.2917170525,39.6361808777],"type":"Point"}
}