{
  "type": "Feature",
  "properties": {
    "iso:country":"ES",
    "sg:address":"Ctra Hospitalet, 6",
    "sg:city":"Almeda Mercader",
    "sg:orig_category":"Artes Gr\u00c1ficas, Artes Pl\u00c1sticas: Material Y Suministros (al Por Menor)",
    "sg:phone":"+34 934 75 80 00",
    "sg:postcode":"08940",
    "sg:province":"Barcelona",
    "sg:website":"www.hartmann.es",
    "wof:name":"Maquinaria Artes Graficas Hartmann S.a.",
    "wof:placetype":"venue"
},
  "geometry": {"coordinates":[2.0708940029,41.3559417725],"type":"Point"}
}