{
  "type": "Feature",
  "properties": {
    "addr:full":"Avda Iparraguirre(ed Cantabrico), 59 Santurtzi Vizcaya 48980",
    "addr:housenumber":"59",
    "addr:postcode":"48980",
    "addr:street":"Avda Iparraguirre Ed Cantabrico",
    "iso:country":"ES",
    "sg:address":"Avda Iparraguirre(ed Cantabrico), 59",
    "sg:city":"Santurtzi",
    "sg:orig_category":"Edici\u00d3n De Diarios, Revistas, Boletines",
    "sg:phone":"+34 944 83 58 92",
    "sg:postcode":"48980",
    "sg:province":"Vizcaya",
    "sg:website":"www.3sesenta.com",
    "wof:name":"Tres 60 Sociedad Cooperativa",
    "wof:placetype":"venue"
},
  "geometry": {"coordinates":[-3.0402920246,43.3344573975],"type":"Point"}
}