{
  "type": "Feature",
  "properties": {
    "iso:country":"ES",
    "sg:address":"Calle de Gran Via, 53",
    "sg:city":"Hellin",
    "sg:orig_category":"Farmacias",
    "sg:phone":"+34 967 30 74 30",
    "sg:postcode":"02400",
    "sg:province":"Albacete",
    "wof:name":"Maria Teresa Gonzalez Valls Y Otra Cdad",
    "wof:placetype":"venue"
},
  "geometry": {"coordinates":[-1.6933369637,38.5087394714],"type":"Point"}
}