{
  "type": "Feature",
  "properties": {
    "iso:country":"ES",
    "sg:address":"Rond Valencia, 16",
    "sg:city":"Madrid",
    "sg:orig_category":"Molduras, Junquillos, Listones Y Molduras Perforadas",
    "sg:phone":"+34 915 27 27 47",
    "sg:postcode":"28012",
    "sg:province":"Madrid",
    "wof:name":"Fuente Lirio S.c.",
    "wof:placetype":"venue"
},
  "geometry": {"coordinates":[-3.7003099918,40.4072608948],"type":"Point"}
}