{
  "type": "Feature",
  "properties": {
    "addr:full":"Pl Mercadal, 28 Barcelona Barcelona 08030",
    "addr:housenumber":"28",
    "addr:postcode":"08030",
    "addr:street":"Pl Mercadal",
    "iso:country":"ES",
    "sg:address":"Pl Mercadal, 28",
    "sg:city":"Barcelona",
    "sg:orig_category":"Velas Y Cirios (fabricaci\u00d3n, Al Por Menor)",
    "sg:phone":"+34 933 11 56 92",
    "sg:postcode":"08030",
    "sg:province":"Barcelona",
    "wof:name":"Ballesteros Franco Emilio Jose",
    "wof:placetype":"venue"
},
  "geometry": {"coordinates":[2.188354969,41.4350967407],"type":"Point"}
}