{
  "type": "Feature",
  "properties": {
    "iso:country":"ES",
    "sg:address":"Calle de Duque, 4",
    "sg:city":"Arahal",
    "sg:orig_category":"Sociedades, Compa\u00d1\u00cdas Aseguradoras",
    "sg:phone":"+34 954 84 07 72",
    "sg:postcode":"41600",
    "sg:province":"Sevilla",
    "sg:website":"www.previdur.es",
    "wof:name":"Mediacion Soria S.l",
    "wof:placetype":"venue"
},
  "geometry": {"coordinates":[-5.5448994637,37.2621383667],"type":"Point"}
}