{
  "type": "Feature",
  "properties": {
    "addr:full":"La Loma, S/n Jinamar Las Palmas 35220",
    "addr:postcode":"35220",
    "addr:street":"La Loma S / N;Palmas",
    "iso:country":"ES",
    "sg:address":"La Loma, S/n",
    "sg:city":"Jinamar",
    "sg:orig_category":"Ense\u00d1anza, Formaci\u00d3n Profesional: Aprendizaje",
    "sg:phone":"+34 928 71 47 64",
    "sg:postcode":"35220",
    "sg:province":"Las Palmas",
    "wof:name":"Ayuntamiento De Telde.gerencia De Jinamar",
    "wof:placetype":"venue"
},
  "geometry": {"coordinates":[-15.4175510406,28.0331096649],"type":"Point"}
}