{
  "type": "Feature",
  "properties": {
    "addr:full":"Avda Zumalakarregi De, 18 Donostia-san Sebastian Guip\u00f9zcoa 20008",
    "addr:housenumber":"18",
    "addr:postcode":"20008",
    "addr:street":"Avda Zumalakarregi De",
    "iso:country":"ES",
    "sg:address":"Avda Zumalakarregi De, 18",
    "sg:city":"Donostia-san Sebastian",
    "sg:orig_category":"M\u00c9dicos: Estomatolog\u00cda",
    "sg:phone":"+34 943 21 98 54",
    "sg:postcode":"20008",
    "sg:province":"Guip\u00f9zcoa",
    "wof:name":"Oraa Saracho Ana",
    "wof:placetype":"venue"
},
  "geometry": {"coordinates":[-2.0030589104,43.3143386841],"type":"Point"}
}