{
  "type": "Feature",
  "properties": {
    "iso:country":"ES",
    "sg:address":"Calle de Maria Zambrano, 52",
    "sg:city":"Zaragoza",
    "sg:orig_category":"Perfumer\u00cda (al Por Menor)",
    "sg:phone":"+34 976 51 77 85",
    "sg:postcode":"50018",
    "sg:province":"Zaragoza",
    "wof:name":"Petalos S.cv.",
    "wof:placetype":"venue"
},
  "geometry": {"coordinates":[-0.8891239762,41.6765403748],"type":"Point"}
}