{
  "type": "Feature",
  "properties": {
    "iso:country":"ES",
    "sg:address":"Cra Valldemossa, 25",
    "sg:city":"Palma",
    "sg:orig_category":"Asociaciones Y Clubs Deportivos",
    "sg:phone":"+34 971 76 07 54",
    "sg:postcode":"07010",
    "sg:province":"Islas Baleares",
    "wof:name":"Davila Mendez Francisco",
    "wof:placetype":"venue"
},
  "geometry": {"coordinates":[2.649379015,39.5894508362],"type":"Point"}
}