{
  "type": "Feature",
  "properties": {
    "iso:country":"ES",
    "sg:address":"Avda Aragon, 79",
    "sg:city":"Alca\u00f1iz",
    "sg:orig_category":"Delegados, Agentes De Tr\u00c1nsito, Auxiliares De Transporte Internacional",
    "sg:phone":"+34 978 83 26 21",
    "sg:postcode":"44600",
    "sg:province":"Teruel",
    "wof:name":"Chulilla Villarroya Ricardo",
    "wof:placetype":"venue"
},
  "geometry": {"coordinates":[-0.1294739991,41.0457496643],"type":"Point"}
}