{
  "type": "Feature",
  "properties": {
    "iso:country":"ES",
    "sg:address":"Avda Tra\u00f1abarren Etorbidea, 8",
    "sg:city":"Abadi\u00f1o",
    "sg:orig_category":"Molduras, Junquillos, Listones Y Molduras Perforadas",
    "sg:phone":"+34 946 81 79 72",
    "sg:postcode":"48220",
    "sg:province":"Vizcaya",
    "wof:name":"Juana Pajuelo Perez-bar Tra\u00f1a",
    "wof:placetype":"venue"
},
  "geometry": {"coordinates":[-2.6117079258,43.1653213501],"type":"Point"}
}