{
  "type": "Feature",
  "properties": {
    "addr:full":"Poli Poligono Industrial De Bakiola, 8 Arene Vizcaya 48498",
    "addr:housenumber":"8",
    "addr:postcode":"48498",
    "addr:street":"Poligono Industrial De Bakiola",
    "iso:country":"ES",
    "sg:address":"Poli Poligono Industrial De Bakiola, 8",
    "sg:city":"Arene",
    "sg:orig_category":"Suministros Para Carrocer\u00cdas",
    "sg:phone":"+34 946 33 31 29",
    "sg:postcode":"48498",
    "sg:province":"Vizcaya",
    "wof:name":"Carrocerias Bakiola S.a.l.",
    "wof:placetype":"venue"
},
  "geometry": {"coordinates":[-2.9183759689,43.1738014221],"type":"Point"}
}