{
  "type": "Feature",
  "properties": {
    "iso:country":"ES",
    "sg:address":"Calle de Heraclio Fournier, 49",
    "sg:city":"Vitoria-gasteiz",
    "sg:orig_category":"Reposter\u00cdas",
    "sg:phone":"+34 945 13 75 65",
    "sg:postcode":"01006",
    "sg:province":"\u00c1lava",
    "wof:name":"Barranco Torres Maria Lourdes",
    "wof:placetype":"venue"
},
  "geometry": {"coordinates":[-2.660476923,42.8359107971],"type":"Point"}
}