{
  "type": "Feature",
  "properties": {
    "addr:full":"Ptge Flaugier, 31 Barcelona Barcelona 08041",
    "addr:housenumber":"31",
    "addr:postcode":"08041",
    "addr:street":"Ptge Flaugier",
    "iso:country":"ES",
    "sg:address":"Ptge Flaugier, 31",
    "sg:city":"Barcelona",
    "sg:orig_category":"Peluqueros: De Se\u00d1oras",
    "sg:phone":"+34 934 50 15 04",
    "sg:postcode":"08041",
    "sg:province":"Barcelona",
    "wof:name":"Marti Dana Maria Rosa",
    "wof:placetype":"venue"
},
  "geometry": {"coordinates":[2.1769208908,41.4153900146],"type":"Point"}
}