{
  "type": "Feature",
  "properties": {
    "addr:full":"P\u00ba Gardotza, S/n Asterrika Vizcaya 48710",
    "addr:postcode":"48710",
    "addr:street":"Gardotza S / N",
    "iso:country":"ES",
    "sg:address":"P\u00ba Gardotza, S/n",
    "sg:city":"Asterrika",
    "sg:orig_category":"Calderer\u00cda",
    "sg:phone":"+34 946 83 11 12",
    "sg:postcode":"48710",
    "sg:province":"Vizcaya",
    "wof:name":"Zabala Mekaniko Tailerra S.a.",
    "wof:placetype":"venue"
},
  "geometry": {"coordinates":[-2.4544939995,43.3273506165],"type":"Point"}
}