{
  "type": "Feature",
  "properties": {
    "addr:full":"Calle de Gremis (els), 9 Teulada Alicante 03725",
    "addr:housenumber":"9",
    "addr:postcode":"03725",
    "addr:street":"Calle De Gremis Els",
    "iso:country":"ES",
    "sg:address":"Calle de Gremis (els), 9",
    "sg:city":"Teulada",
    "sg:orig_category":"Muebles Y Accesorios Para Cocinas Y Cuartos De Ba\u00d1o (al Por Menor)",
    "sg:phone":"+34 965 74 15 10",
    "sg:postcode":"03725",
    "sg:province":"Alicante",
    "wof:name":"Centro De Cocinas S.l.",
    "wof:placetype":"venue"
},
  "geometry": {"coordinates":[0.1012500003,38.7296409607],"type":"Point"}
}