{
  "type": "Feature",
  "properties": {
    "iso:country":"ES",
    "sg:address":"Calle de San Prudencio, 27",
    "sg:city":"Vitoria-gasteiz",
    "sg:orig_category":"Ingeniero",
    "sg:phone":"+34 945 14 56 11",
    "sg:postcode":"01005",
    "sg:province":"\u00c1lava",
    "wof:name":"Safeman S.l.",
    "wof:placetype":"venue"
},
  "geometry": {"coordinates":[-2.6708459854,42.8440628052],"type":"Point"}
}