{
  "type": "Feature",
  "properties": {
    "iso:country":"ES",
    "sg:address":"Calle de Regina, 15",
    "sg:city":"Sevilla",
    "sg:orig_category":"Producci\u00d3n, Distribuci\u00d3n De Electricidad",
    "sg:phone":"+34 954 21 76 30",
    "sg:postcode":"41003",
    "sg:province":"Sevilla",
    "wof:name":"Amian Balastegui Jose",
    "wof:placetype":"venue"
},
  "geometry": {"coordinates":[-5.9915037155,37.3947677612],"type":"Point"}
}