{
  "type": "Feature",
  "properties": {
    "iso:country":"ES",
    "sg:address":"Calle de Buenos Aires, 2",
    "sg:city":"Granada",
    "sg:orig_category":"Ense\u00d1anza, Formaci\u00d3n Profesional: Aprendizaje",
    "sg:phone":"+34 958 53 64 10",
    "sg:postcode":"18004",
    "sg:province":"Granada",
    "wof:name":"Consejeria Para La Igualdad Y Bienestar Social-delegacion De Granada",
    "wof:placetype":"venue"
},
  "geometry": {"coordinates":[-3.6068286896,37.1709022522],"type":"Point"}
}