{
  "type": "Feature",
  "properties": {
    "iso:country":"ES",
    "sg:address":"Calle de Andra Mari Kalea, 9",
    "sg:city":"Durango",
    "sg:orig_category":"Peluqueros: De Se\u00d1oras",
    "sg:phone":"+34 946 81 10 39",
    "sg:postcode":"48200",
    "sg:province":"Vizcaya",
    "wof:name":"Maria Teresa Ere\u00f1o Carreto",
    "wof:placetype":"venue"
},
  "geometry": {"coordinates":[-2.6307747364,43.167804718],"type":"Point"}
}