{
  "type": "Feature",
  "properties": {
    "iso:country":"ES",
    "sg:address":"Lersundi Kalea, 17",
    "sg:city":"Deba",
    "sg:orig_category":"Cajas De Ahorro",
    "sg:phone":"+34 943 19 14 43",
    "sg:postcode":"20820",
    "sg:province":"Guip\u00f9zcoa",
    "sg:website":"www.cajalaboral.com",
    "wof:name":"Caja Laboral Popular",
    "wof:placetype":"venue"
},
  "geometry": {"coordinates":[-2.3542180061,43.2938461304],"type":"Point"}
}