{
  "type": "Feature",
  "properties": {
    "addr:full":"Calle de Confederacion (la), 7 Conil De La Frontera C\u00e1diz 11140",
    "addr:housenumber":"7",
    "addr:postcode":"11140",
    "addr:street":"Calle De Confederacion La",
    "iso:country":"ES",
    "sg:address":"Calle de Confederacion (la), 7",
    "sg:city":"Conil De La Frontera",
    "sg:orig_category":"Energ\u00cda Solar Y Nuevas Energ\u00cdas (equipo, Estudios)",
    "sg:phone":"+34 956 44 27 66",
    "sg:postcode":"11140",
    "sg:province":"C\u00e1diz",
    "wof:name":"Enestar Sociedad Limitada",
    "wof:placetype":"venue"
},
  "geometry": {"coordinates":[-6.0848288536,36.2781105042],"type":"Point"}
}