{
  "type": "Feature",
  "properties": {
    "iso:country":"ES",
    "sg:address":"Calle de Mejico, 3",
    "sg:city":"Coria Rio",
    "sg:orig_category":"Centros M\u00c9dicos Y Sociales, Dispensarios",
    "sg:phone":"+34 954 77 43 49",
    "sg:postcode":"41100",
    "sg:province":"Sevilla",
    "wof:name":"Centro Medico Andalucia S.l.",
    "wof:placetype":"venue"
},
  "geometry": {"coordinates":[-6.0519790649,37.2871856689],"type":"Point"}
}