{
  "type": "Feature",
  "properties": {
    "addr:full":"Calle de Pintor Maximino Pe\u00d1a, 10 Soria Soria 42004",
    "addr:housenumber":"10",
    "addr:postcode":"42004",
    "addr:street":"Calle De Pintor Maximino Pen\u0303A",
    "iso:country":"ES",
    "sg:address":"Calle de Pintor Maximino Pe\u00d1a, 10",
    "sg:city":"Soria",
    "sg:orig_category":"Papeler\u00cdas, Librer\u00cdas",
    "sg:phone":"+34 975 22 97 68",
    "sg:postcode":"42004",
    "sg:province":"Soria",
    "wof:name":"Hernandez Mayor Maria Luisa",
    "wof:placetype":"venue"
},
  "geometry": {"coordinates":[-2.4737529755,41.7605018616],"type":"Point"}
}