{
  "type": "Feature",
  "properties": {
    "iso:country":"ES",
    "sg:address":"O Carballi\u00f1o, 67",
    "sg:city":"Carballi\u00d1o",
    "sg:orig_category":"Serigraf\u00cda (material Y Suministros)",
    "sg:phone":"+34 986 49 55 62",
    "sg:postcode":"36693",
    "sg:province":"Pontevedra",
    "sg:website":"www.publidigal.com",
    "wof:name":"Publidigal S.l.",
    "wof:placetype":"venue"
},
  "geometry": {"coordinates":[-8.6162719727,42.3098869324],"type":"Point"}
}