{
  "type": "Feature",
  "properties": {
    "iso:country":"ES",
    "sg:address":"Calle de Fernando Camino, S/n",
    "sg:city":"Malaga",
    "sg:orig_category":"Cajas De Ahorro",
    "sg:phone":"+34 952 22 07 63",
    "sg:postcode":"29016",
    "sg:province":"M\u00e1laga",
    "sg:website":"www.unicaja.es",
    "wof:name":"Unicaja",
    "wof:placetype":"venue"
},
  "geometry": {"coordinates":[-4.4090237617,36.7205696106],"type":"Point"}
}