{
  "type": "Feature",
  "properties": {
    "addr:full":"Carrer de Morato (dels), 8 Vic Barcelona 08500",
    "addr:housenumber":"8",
    "addr:postcode":"08500",
    "addr:street":"Carrer De Morato Dels",
    "iso:country":"ES",
    "sg:address":"Carrer de Morato (dels), 8",
    "sg:city":"Vic",
    "sg:orig_category":"Restaurantes",
    "sg:phone":"+34 938 85 20 54",
    "sg:postcode":"08500",
    "sg:province":"Barcelona",
    "wof:name":"Vi\u00f1as Codina Juan",
    "wof:placetype":"venue"
},
  "geometry": {"coordinates":[2.2495925426,41.9300956726],"type":"Point"}
}