{
  "type": "Feature",
  "properties": {
    "iso:country":"ES",
    "sg:address":"Carrer de Esglesia, 3",
    "sg:city":"Palleja",
    "sg:orig_category":"Mec\u00c1nico Del Autom\u00d3vil",
    "sg:phone":"+34 936 63 05 40",
    "sg:postcode":"08780",
    "sg:province":"Barcelona",
    "wof:name":"Benito Carrizo Antonio",
    "wof:placetype":"venue"
},
  "geometry": {"coordinates":[1.9970469475,41.4211235046],"type":"Point"}
}