{
  "type": "Feature",
  "properties": {
    "addr:full":"Calle de Venta (la), 49 Estacion Madrid 28400",
    "addr:housenumber":"49",
    "addr:postcode":"28400",
    "addr:street":"Calle De Venta La",
    "iso:country":"ES",
    "sg:address":"Calle de Venta (la), 49",
    "sg:city":"Estacion",
    "sg:orig_category":"Cl\u00cdnicas M\u00c9dicas",
    "sg:phone":"+34 918 50 29 04",
    "sg:postcode":"28400",
    "sg:province":"Madrid",
    "wof:name":"Aznar Jimenez Pedro Antonio",
    "wof:placetype":"venue"
},
  "geometry": {"coordinates":[-4.1862940788,40.7417602539],"type":"Point"}
}