{
  "type": "Feature",
  "properties": {
    "iso:country":"ES",
    "sg:address":"Calle de Fernando El Catolico, 71",
    "sg:city":"Madrid",
    "sg:orig_category":"Asesor\u00cda Sobre Comunicaci\u00d3n De Empresas",
    "sg:phone":"+34 915 50 02 75",
    "sg:postcode":"28015",
    "sg:province":"Madrid",
    "wof:name":"Aseronews S.l.",
    "wof:placetype":"venue"
},
  "geometry": {"coordinates":[-3.7162289619,40.4344444275],"type":"Point"}
}