{
  "type": "Feature",
  "properties": {
    "iso:country":"ES",
    "sg:address":"Calle de Alperchines (de Los), 5",
    "sg:city":"San Fernando De Henares",
    "sg:orig_category":"Reposter\u00cdas",
    "sg:phone":"+34 916 71 04 44",
    "sg:postcode":"28830",
    "sg:province":"Madrid",
    "wof:name":"Ines Juara Francisco",
    "wof:placetype":"venue"
},
  "geometry": {"coordinates":[-3.5345489979,40.4262008667],"type":"Point"}
}