{
  "type": "Feature",
  "properties": {
    "iso:country":"ES",
    "sg:address":"Calle de Tudela, 10",
    "sg:city":"Valladolid",
    "sg:orig_category":"Carnicer\u00cdas, Carnicer\u00cdas",
    "sg:phone":"+34 983 39 89 73",
    "sg:postcode":"47002",
    "sg:province":"Valladolid",
    "wof:name":"Estebanez Santos Evelio",
    "wof:placetype":"venue"
},
  "geometry": {"coordinates":[-4.717965126,41.6474227905],"type":"Point"}
}