{
  "type": "Feature",
  "properties": {
    "addr:full":"Calle de Jesus, 22 Palma Islas Baleares 07003",
    "addr:housenumber":"22",
    "addr:postcode":"07003",
    "addr:street":"Calle De Jesus",
    "iso:country":"ES",
    "sg:address":"Calle de Jesus, 22",
    "sg:city":"Palma",
    "sg:orig_category":"M\u00c9dicos: Pediatr\u00cda. Enfermedades De Los Ni\u00d1os",
    "sg:phone":"+34 971 75 29 62",
    "sg:postcode":"07003",
    "sg:province":"Islas Baleares",
    "wof:name":"Veny Roca Juan",
    "wof:placetype":"venue"
},
  "geometry": {"coordinates":[2.6324729919,39.5936164856],"type":"Point"}
}