{
  "type": "Feature",
  "properties": {
    "iso:country":"ES",
    "sg:address":"Calle de Mesones, 16",
    "sg:city":"Casar",
    "sg:orig_category":"Electrodom\u00c9sticos (al Por Menor)",
    "sg:phone":"+34 949 33 51 29",
    "sg:postcode":"19170",
    "sg:province":"Guadalajara",
    "wof:name":"Electrodomesticos El Casar S.l.",
    "wof:placetype":"venue"
},
  "geometry": {"coordinates":[-3.4265260696,40.7024040222],"type":"Point"}
}