{
  "type": "Feature",
  "properties": {
    "addr:full":"Pase Frailes (los), 10 Palencia Palencia 34002",
    "addr:postcode":"34002",
    "addr:street":"Los",
    "iso:country":"ES",
    "sg:address":"Pase Frailes (los), 10",
    "sg:city":"Palencia",
    "sg:orig_category":"Molduras, Junquillos, Listones Y Molduras Perforadas",
    "sg:phone":"+34 979 72 97 89",
    "sg:postcode":"34002",
    "sg:province":"Palencia",
    "wof:name":"Alonso Sanz Antonio",
    "wof:placetype":"venue"
},
  "geometry": {"coordinates":[-4.5244841576,42.0068511963],"type":"Point"}
}