{
  "type": "Feature",
  "properties": {
    "addr:full":"Calle de Isabel Ii, 22 Santander Cantabria 39002",
    "addr:housenumber":"22",
    "addr:postcode":"39002",
    "addr:street":"Calle De Isabel Ii",
    "iso:country":"ES",
    "sg:address":"Calle de Isabel Ii, 22",
    "sg:city":"Santander",
    "sg:orig_category":"Institutos De Belleza",
    "sg:phone":"+34 942 21 43 71",
    "sg:postcode":"39002",
    "sg:province":"Cantabria",
    "wof:name":"Uriarte Alvarez Rosa Ana",
    "wof:placetype":"venue"
},
  "geometry": {"coordinates":[-3.8089950085,43.4600296021],"type":"Point"}
}