{
  "type": "Feature",
  "properties": {
    "iso:country":"ES",
    "sg:address":"Carrer de Salvador Vidal, 8",
    "sg:city":"S. Feliu Guixols",
    "sg:orig_category":"Asociaciones Y Clubs Deportivos",
    "sg:phone":"+34 972 32 51 04",
    "sg:postcode":"17220",
    "sg:province":"Girona",
    "wof:name":"Mealni 2002 S.l.",
    "wof:placetype":"venue"
},
  "geometry": {"coordinates":[3.0239770412,41.7826042175],"type":"Point"}
}