{
  "type": "Feature",
  "properties": {
    "iso:country":"ES",
    "sg:address":"Calle de D, S/n",
    "sg:city":"Pol. Malpica",
    "sg:orig_category":"Electrodom\u00c9sticos (fabricaci\u00d3n, Al Por Mayor)",
    "sg:phone":"+34 902 35 13 52",
    "sg:postcode":"50057",
    "sg:province":"Zaragoza",
    "sg:website":"www.bshelectrodomesticos.com",
    "wof:name":"Bsh Electrodomesticos Espa\u00d1a S.a.",
    "wof:placetype":"venue"
},
  "geometry": {"coordinates":[-0.7678520083,41.6499633789],"type":"Point"}
}