{
  "type": "Feature",
  "properties": {
    "addr:full":"Carr Chopin, 25 Badalona Barcelona 08917",
    "addr:housenumber":"25",
    "addr:postcode":"08917",
    "addr:street":"Carr Chopin",
    "iso:country":"ES",
    "sg:address":"Carr Chopin, 25",
    "sg:city":"Badalona",
    "sg:orig_category":"Agencias Y Agentes Comerciales, Representantes",
    "sg:phone":"+34 933 87 09 94",
    "sg:postcode":"08917",
    "sg:province":"Barcelona",
    "wof:name":"Alcazar Carrique Francisco Javier",
    "wof:placetype":"venue"
},
  "geometry": {"coordinates":[2.2356610298,41.4523468018],"type":"Point"}
}