{
  "type": "Feature",
  "properties": {
    "iso:country":"ES",
    "sg:address":"Avgd Del Solsones, 2",
    "sg:city":"Oliana",
    "sg:orig_category":"Pizzer\u00cdas",
    "sg:phone":"+34 973 46 31 58",
    "sg:postcode":"25790",
    "sg:province":"Lleida",
    "wof:name":"Bar Restaurant Teco",
    "wof:placetype":"venue"
},
  "geometry": {"coordinates":[1.3137170076,42.0661430359],"type":"Point"}
}