{
  "type": "Feature",
  "properties": {
    "addr:full":"Calle de Estacion (la) (solares), 2 Solares Cantabria 39710",
    "addr:housenumber":"2",
    "addr:postcode":"39710",
    "addr:street":"Calle De Estacion La Solares",
    "iso:country":"ES",
    "sg:address":"Calle de Estacion (la) (solares), 2",
    "sg:city":"Solares",
    "sg:orig_category":"Librer\u00cdas",
    "sg:phone":"+34 942 52 27 85",
    "sg:postcode":"39710",
    "sg:province":"Cantabria",
    "wof:name":"Santovea Gomez Juan Jose",
    "wof:placetype":"venue"
},
  "geometry": {"coordinates":[-3.7402191162,43.38463974],"type":"Point"}
}