{
  "type": "Feature",
  "properties": {
    "iso:country":"ES",
    "sg:address":"Avda Libertad De La, 18",
    "sg:city":"Donostia-san Sebastian",
    "sg:orig_category":"Asesor\u00cda Fiscal Y Jur\u00cddica",
    "sg:phone":"+34 943 42 16 20",
    "sg:postcode":"20004",
    "sg:province":"Guip\u00f9zcoa",
    "wof:name":"D.p.g. Asesores Legales Y Tributarios S.l.",
    "wof:placetype":"venue"
},
  "geometry": {"coordinates":[-1.9814050198,43.3199501038],"type":"Point"}
}