{
  "type": "Feature",
  "properties": {
    "addr:full":"Ctra. Trujillo, Km. 0013,4 La Cumbre C\u00e1ceres 10270",
    "addr:postcode":"10270",
    "addr:street":"Ctra. Trujillo Km. 0013,4;Ca\u0301Ceres",
    "iso:country":"ES",
    "sg:address":"Ctra. Trujillo, Km. 0013,4",
    "sg:city":"La Cumbre",
    "sg:orig_category":"Cr\u00cda De Animales",
    "sg:phone":"+34 927 49 00 41",
    "sg:postcode":"10270",
    "sg:province":"C\u00e1ceres",
    "wof:name":"Fernandez Rubio Catalina",
    "wof:placetype":"venue"
},
  "geometry": {"coordinates":[-5.9762687683,39.4074401855],"type":"Point"}
}