{
  "type": "Feature",
  "properties": {
    "iso:country":"ES",
    "sg:address":"Calle de Limon Verde, 1",
    "sg:city":"Algete",
    "sg:orig_category":"Inmobiliaria (agencias)",
    "sg:phone":"+34 916 28 21 33",
    "sg:postcode":"28110",
    "sg:province":"Madrid",
    "wof:name":"Salem Grupo Inmobiliario S.l.",
    "wof:placetype":"venue"
},
  "geometry": {"coordinates":[-3.499063015,40.5967140198],"type":"Point"}
}