{
  "type": "Feature",
  "properties": {
    "addr:full":"Plzl Mercado (del), 19 Navalcarnero Madrid 28600",
    "addr:postcode":"28600",
    "iso:country":"ES",
    "sg:address":"Plzl Mercado (del), 19",
    "sg:city":"Navalcarnero",
    "sg:orig_category":"Carnicer\u00cdas, Carnicer\u00cdas",
    "sg:phone":"+34 918 11 01 07",
    "sg:postcode":"28600",
    "sg:province":"Madrid",
    "wof:name":"Jordan Puertas Antonio",
    "wof:placetype":"venue"
},
  "geometry": {"coordinates":[-4.0130853653,40.2880401611],"type":"Point"}
}