{
  "type": "Feature",
  "properties": {
    "addr:full":"Calle de Gema, 16 Cordoba C\u00f3rdoba 14014",
    "addr:housenumber":"16",
    "addr:postcode":"14014",
    "addr:street":"Calle De Gema;Co\u0301Rdoba",
    "iso:country":"ES",
    "sg:address":"Calle de Gema, 16",
    "sg:city":"Cordoba",
    "sg:orig_category":"Ingeniero",
    "sg:phone":"+34 957 76 42 70",
    "sg:postcode":"14014",
    "sg:province":"C\u00f3rdoba",
    "wof:name":"Centro De Estudios De Materiales Y Control De Obra S.a.",
    "wof:placetype":"venue"
},
  "geometry": {"coordinates":[-4.7475748062,37.8898124695],"type":"Point"}
}