{
  "type": "Feature",
  "properties": {
    "iso:country":"ES",
    "sg:address":"Ctra Nacional Seiscientos Treinta, Km. 0157,2",
    "sg:city":"Viloria De La Jurisdiccion",
    "sg:orig_category":"Fabricaci\u00d3n De Muebles",
    "sg:phone":"+34 987 28 88 23",
    "sg:postcode":"24231",
    "sg:province":"Le\u00f3n",
    "wof:name":"Hermanos Santos Villanueva S.l.",
    "wof:placetype":"venue"
},
  "geometry": {"coordinates":[-5.5841889381,42.5260047913],"type":"Point"}
}