{
  "type": "Feature",
  "properties": {
    "addr:full":"Calle de Libertad, 4 Cenicientos Madrid 28650",
    "addr:housenumber":"4",
    "addr:postcode":"28650",
    "addr:street":"Calle De Libertad",
    "iso:country":"ES",
    "sg:address":"Calle de Libertad, 4",
    "sg:city":"Cenicientos",
    "sg:orig_category":"Construcci\u00d3n De Edificios Residenciales Y No Residenciales",
    "sg:phone":"+34 918 64 29 39",
    "sg:postcode":"28650",
    "sg:province":"Madrid",
    "wof:name":"Parufeer S.l.",
    "wof:placetype":"venue"
},
  "geometry": {"coordinates":[-4.4680008888,40.2636299133],"type":"Point"}
}