{
  "type": "Feature",
  "properties": {
    "iso:country":"ES",
    "sg:address":"Calle de Cooperativa, S/n",
    "sg:city":"Alpera",
    "sg:orig_category":"Vinos Y Licores (venta Al Por Menor)",
    "sg:phone":"+34 967 33 01 08",
    "sg:postcode":"02690",
    "sg:province":"Albacete",
    "wof:name":"Cooperativa Del Campo Santa Cruz",
    "wof:placetype":"venue"
},
  "geometry": {"coordinates":[-1.2355675697,38.9591827393],"type":"Point"}
}