{
  "type": "Feature",
  "properties": {
    "addr:full":"Calle de Doctor Tolosa Latour, 8 Chipiona C\u00e1diz 11550",
    "addr:housenumber":"8",
    "addr:postcode":"11550",
    "addr:street":"Calle De Doctor Tolosa Latour",
    "iso:country":"ES",
    "sg:address":"Calle de Doctor Tolosa Latour, 8",
    "sg:city":"Chipiona",
    "sg:orig_category":"Molduras, Junquillos, Listones Y Molduras Perforadas",
    "sg:phone":"+34 956 37 01 12",
    "sg:postcode":"11550",
    "sg:province":"C\u00e1diz",
    "wof:name":"Tirado Rodriguez Jose Ramon",
    "wof:placetype":"venue"
},
  "geometry": {"coordinates":[-6.4351840019,36.7413291931],"type":"Point"}
}