{
  "type": "Feature",
  "properties": {
    "addr:full":"Calle de Cruz De Guadalajara, 8 Alcala Henares Madrid 28805",
    "addr:housenumber":"8",
    "addr:postcode":"28805",
    "addr:street":"Calle De Cruz De Guadalajara",
    "iso:country":"ES",
    "sg:address":"Calle de Cruz De Guadalajara, 8",
    "sg:city":"Alcala Henares",
    "sg:orig_category":"Psic\u00d3logos",
    "sg:phone":"+34 918 89 24 16",
    "sg:postcode":"28805",
    "sg:province":"Madrid",
    "wof:name":"Un Espacio Para El Crecimiento S.l.",
    "wof:placetype":"venue"
},
  "geometry": {"coordinates":[-3.3594229221,40.4851913452],"type":"Point"}
}