{
  "type": "Feature",
  "properties": {
    "addr:full":"Pg Pere Iii, 18 Manresa Barcelona 08242",
    "addr:housenumber":"18",
    "addr:postcode":"08242",
    "addr:street":"Pg Pere Iii",
    "iso:country":"ES",
    "sg:address":"Pg Pere Iii, 18",
    "sg:city":"Manresa",
    "sg:orig_category":"Arquitectos",
    "sg:phone":"+34 938 72 53 49",
    "sg:postcode":"08242",
    "sg:province":"Barcelona",
    "wof:name":"Obradors Berenguer Raul",
    "wof:placetype":"venue"
},
  "geometry": {"coordinates":[1.8238879442,41.7265892029],"type":"Point"}
}