{
  "type": "Feature",
  "properties": {
    "addr:full":"Ctra Getares Ctra., S/n Algeciras C\u00e1diz 11207",
    "addr:postcode":"11207",
    "addr:street":"Ctra Getares Ctra. S / N;Ca\u0301Diz",
    "iso:country":"ES",
    "sg:address":"Ctra Getares Ctra., S/n",
    "sg:city":"Algeciras",
    "sg:orig_category":"Formaci\u00d3n Continuada (variada)",
    "sg:phone":"+34 956 60 62 97",
    "sg:postcode":"11207",
    "sg:province":"C\u00e1diz",
    "wof:name":"Junta De Andalucia",
    "wof:placetype":"venue"
},
  "geometry": {"coordinates":[-5.4460940361,36.1083984375],"type":"Point"}
}