{
  "type": "Feature",
  "properties": {
    "iso:country":"ES",
    "sg:address":"Calle de Antonio Rodriguez Villa, 28",
    "sg:city":"Madrid",
    "sg:orig_category":"El Hogar: Amueblado, Acondicionamiento, Decoraci\u00d3n Y Mantenimiento",
    "sg:phone":"+34 915 61 02 95",
    "sg:postcode":"28002",
    "sg:province":"Madrid",
    "wof:name":"Al Decoracion S. A.",
    "wof:placetype":"venue"
},
  "geometry": {"coordinates":[-3.6823074818,40.4445495605],"type":"Point"}
}