{
  "type": "Feature",
  "properties": {
    "addr:full":"Portocarreiro, S/n Antas Ulla Lugo 27570",
    "addr:housenumber":"/ n",
    "addr:postcode":"27570",
    "addr:street":"Portocarreiro S",
    "iso:country":"ES",
    "sg:address":"Portocarreiro, S/n",
    "sg:city":"Antas Ulla",
    "sg:orig_category":"Ense\u00d1anza Agr\u00cdcola",
    "sg:phone":"+34 982 17 39 54",
    "sg:postcode":"27570",
    "sg:province":"Lugo",
    "wof:name":"Nicolas Nu\u00f1ez Santiago",
    "wof:placetype":"venue"
},
  "geometry": {"coordinates":[-7.8907341957,42.7823143005],"type":"Point"}
}