{
  "type": "Feature",
  "properties": {
    "addr:full":"Calle de Juan Lisbona Zapata, 2 Velez-malaga M\u00e1laga 29700",
    "addr:housenumber":"2",
    "addr:postcode":"29700",
    "addr:street":"Calle De Juan Lisbona Zapata",
    "iso:country":"ES",
    "sg:address":"Calle de Juan Lisbona Zapata, 2",
    "sg:city":"Velez-malaga",
    "sg:orig_category":"Promotores Constructores",
    "sg:phone":"+34 952 50 22 54",
    "sg:postcode":"29700",
    "sg:province":"M\u00e1laga",
    "wof:name":"Huerta Lisbona Dos S.a.",
    "wof:placetype":"venue"
},
  "geometry": {"coordinates":[-4.1042962074,36.7764816284],"type":"Point"}
}