{
  "type": "Feature",
  "properties": {
    "iso:country":"ES",
    "sg:address":"Carrer de Pelai, 54",
    "sg:city":"Barcelona",
    "sg:orig_category":"Ropa Para Se\u00d1oras Y Caballeros (al Por Menor)",
    "sg:phone":"+34 933 01 71 01",
    "sg:postcode":"08001",
    "sg:province":"Barcelona",
    "wof:name":"C & A Modas S.l.",
    "wof:placetype":"venue"
},
  "geometry": {"coordinates":[2.1689429283,41.385433197],"type":"Point"}
}