{
  "type": "Feature",
  "properties": {
    "addr:full":"Imo, S/n San Xoan De Lai\u00f1o La Coru\u00f1a 15982",
    "addr:housenumber":"s / n",
    "addr:postcode":"15982",
    "addr:street":"Imo;Corun\u0303A",
    "iso:country":"ES",
    "sg:address":"Imo, S/n",
    "sg:city":"San Xoan De Lai\u00f1o",
    "sg:orig_category":"Ebanister\u00cda",
    "sg:phone":"+34 981 80 22 14",
    "sg:postcode":"15982",
    "sg:province":"La Coru\u00f1a",
    "wof:name":"Carpinteria Lai\u00f1o S.l.",
    "wof:placetype":"venue"
},
  "geometry": {"coordinates":[-8.7225341797,42.7131118774],"type":"Point"}
}