{
  "type": "Feature",
  "properties": {
    "addr:full":"Trva Peralto, 16 Grove Pontevedra 36980",
    "addr:housenumber":"16",
    "addr:postcode":"36980",
    "addr:street":"Trva Peralto;Grove Pontevedra",
    "iso:country":"ES",
    "sg:address":"Trva Peralto, 16",
    "sg:city":"Grove",
    "sg:orig_category":"Reposter\u00cdas",
    "sg:phone":"+34 986 73 09 71",
    "sg:postcode":"36980",
    "sg:province":"Pontevedra",
    "wof:name":"Panaderia Chaves S.l",
    "wof:placetype":"venue"
},
  "geometry": {"coordinates":[-8.8607797623,42.4952659607],"type":"Point"}
}