{
  "type": "Feature",
  "properties": {
    "iso:country":"ES",
    "sg:address":"Calle de Ramon Y Cajal, 2",
    "sg:city":"Poligono Industrial Los Villares",
    "sg:orig_category":"Comercio De Piezas De Recambio Y De Accesorios De Veh\u00cdculos, Veh\u00cdculos Industriales",
    "sg:phone":"+34 923 25 15 47",
    "sg:postcode":"37184",
    "sg:province":"Salamanca",
    "wof:name":"Automocion Tormes S. A.",
    "wof:placetype":"venue"
},
  "geometry": {"coordinates":[-5.667485714,40.9651222229],"type":"Point"}
}