{
  "type": "Feature",
  "properties": {
    "iso:country":"ES",
    "sg:address":"Calle de Andres De Paz, 27",
    "sg:city":"Santa Maria Del Paramo",
    "sg:orig_category":"Bebidas",
    "sg:phone":"+34 987 35 00 57",
    "sg:postcode":"24240",
    "sg:province":"Le\u00f3n",
    "wof:name":"San Martin Garmon Braulio",
    "wof:placetype":"venue"
},
  "geometry": {"coordinates":[-5.7480192184,42.3539505005],"type":"Point"}
}