{
  "type": "Feature",
  "properties": {
    "iso:country":"ES",
    "sg:address":"Carrer de Alfons Xiii, 11",
    "sg:city":"Sabadell",
    "sg:orig_category":"Asesor\u00cda Fiscal Y Jur\u00cddica",
    "sg:phone":"+34 937 26 45 45",
    "sg:postcode":"08202",
    "sg:province":"Barcelona",
    "wof:name":"Millan Garcia Gloria",
    "wof:placetype":"venue"
},
  "geometry": {"coordinates":[2.1103980541,41.5458831787],"type":"Point"}
}