{
  "type": "Feature",
  "properties": {
    "iso:country":"ES",
    "sg:address":"Ctra. Burgos-portugal, Km. 0151,0",
    "sg:city":"Cubillas Sta Marta",
    "sg:orig_category":"Agricultura: Abastecimiento Y Cosechado (negocio)",
    "sg:phone":"+34 983 58 50 08",
    "sg:postcode":"47290",
    "sg:province":"Valladolid",
    "wof:name":"Finca El Espino S.a.",
    "wof:placetype":"venue"
},
  "geometry": {"coordinates":[-4.6137828827,41.8332290649],"type":"Point"}
}