{
  "type": "Feature",
  "properties": {
    "iso:country":"ES",
    "sg:address":"Plaz Reyes Catolicos, 1",
    "sg:city":"Velez-malaga",
    "sg:orig_category":"Perfumer\u00cda (al Por Menor)",
    "sg:phone":"+34 952 50 16 36",
    "sg:postcode":"29700",
    "sg:province":"M\u00e1laga",
    "wof:name":"Hidalgo Reyes Jose",
    "wof:placetype":"venue"
},
  "geometry": {"coordinates":[-4.1004362106,36.7783088684],"type":"Point"}
}