{
  "type": "Feature",
  "properties": {
    "iso:country":"ES",
    "sg:address":"Calle de San Cristobal, 45",
    "sg:city":"Puente-genil",
    "sg:orig_category":"Contenedores (mercanc\u00cdas)",
    "sg:phone":"+34 957 60 73 37",
    "sg:postcode":"14500",
    "sg:province":"C\u00f3rdoba",
    "wof:name":"Cabello Rodriguez Antonio Jose",
    "wof:placetype":"venue"
},
  "geometry": {"coordinates":[-4.7710981369,37.3895263672],"type":"Point"}
}