{
  "type": "Feature",
  "properties": {
    "iso:country":"ES",
    "sg:address":"San Isidro, S/n",
    "sg:city":"Abanto",
    "sg:orig_category":"Explotaci\u00d3n De Canteras",
    "sg:phone":"+34 976 84 91 78",
    "sg:postcode":"50350",
    "sg:province":"Zaragoza",
    "wof:name":"Explotaciones Abanto S.l.",
    "wof:placetype":"venue"
},
  "geometry": {"coordinates":[-1.700693965,41.1354560852],"type":"Point"}
}