{
  "type": "Feature",
  "properties": {
    "addr:full":"Avda Madrid, 23 Palencia Palencia 34004",
    "addr:housenumber":"23",
    "addr:postcode":"34004",
    "addr:street":"Avda Madrid",
    "iso:country":"ES",
    "sg:address":"Avda Madrid, 23",
    "sg:city":"Palencia",
    "sg:orig_category":"Panader\u00cdas, Panader\u00cdas",
    "sg:phone":"+34 979 72 86 61",
    "sg:postcode":"34004",
    "sg:province":"Palencia",
    "wof:name":"Rigodon S.l.",
    "wof:placetype":"venue"
},
  "geometry": {"coordinates":[-4.5211830139,41.9955024719],"type":"Point"}
}