{
  "type": "Feature",
  "properties": {
    "addr:full":"Pase Altza De, 20 Donostia-san Sebastian Guip\u00f9zcoa 20017",
    "addr:housenumber":"20",
    "addr:postcode":"20017",
    "iso:country":"ES",
    "sg:address":"Pase Altza De, 20",
    "sg:city":"Donostia-san Sebastian",
    "sg:orig_category":"Empresas De Carpinter\u00cda De Madera",
    "sg:phone":"+34 943 11 70 64",
    "sg:postcode":"20017",
    "sg:province":"Guip\u00f9zcoa",
    "wof:name":"Arratole, C.b.",
    "wof:placetype":"venue"
},
  "geometry": {"coordinates":[-1.9794000387,43.3173789978],"type":"Point"}
}