{
  "type": "Feature",
  "properties": {
    "iso:country":"ES",
    "sg:address":"Calle de Doctor Villar, 5",
    "sg:city":"Linea De La Concepcion",
    "sg:orig_category":"Loter\u00cda Y T\u00d3mbola",
    "sg:phone":"+34 956 17 26 39",
    "sg:postcode":"11300",
    "sg:province":"C\u00e1diz",
    "wof:name":"Patronato De Apuestas Mutuas Deportivas Beneficas",
    "wof:placetype":"venue"
},
  "geometry": {"coordinates":[-5.3505930901,36.1615028381],"type":"Point"}
}