{
  "type": "Feature",
  "properties": {
    "iso:country":"ES",
    "sg:address":"Carr Cardenal Vives, 13",
    "sg:city":"Igualada",
    "sg:orig_category":"Confecci\u00d3n (fabricaci\u00d3n, Al Por Mayor)",
    "sg:phone":"+34 938 05 02 85",
    "sg:postcode":"08700",
    "sg:province":"Barcelona",
    "wof:name":"Almenara Sanchez Manuela",
    "wof:placetype":"venue"
},
  "geometry": {"coordinates":[1.6240884066,41.5788383484],"type":"Point"}
}