{
  "type": "Feature",
  "properties": {
    "addr:full":"Calle de Sabina, 63 Puebla Alfinden Zaragoza 50171",
    "addr:housenumber":"63",
    "addr:postcode":"50171",
    "addr:street":"Calle De Sabina;Alfinden",
    "iso:country":"ES",
    "sg:address":"Calle de Sabina, 63",
    "sg:city":"Puebla Alfinden",
    "sg:orig_category":"Librer\u00cdas",
    "sg:phone":"+34 976 10 79 34",
    "sg:postcode":"50171",
    "sg:province":"Zaragoza",
    "wof:name":"Contratiempo S.c.l.",
    "wof:placetype":"venue"
},
  "geometry": {"coordinates":[-0.7660290003,41.6440658569],"type":"Point"}
}