{
  "type": "Feature",
  "properties": {
    "addr:full":"Av Tres Forques, S/n Xirivella Valencia 46950",
    "addr:housenumber":"s / n",
    "addr:postcode":"46950",
    "addr:street":"Av Tres Forques",
    "iso:country":"ES",
    "sg:address":"Av Tres Forques, S/n",
    "sg:city":"Xirivella",
    "sg:orig_category":"\u00d3ptica: Instrumentos (fabricaci\u00d3n)",
    "sg:phone":"+34 963 59 84 87",
    "sg:postcode":"46950",
    "sg:province":"Valencia",
    "sg:website":"www.loop-vision.com",
    "wof:name":"Navoptik S.l.",
    "wof:placetype":"venue"
},
  "geometry": {"coordinates":[-0.4138759971,39.4629211426],"type":"Point"}
}