{
  "type": "Feature",
  "properties": {
    "iso:country":"ES",
    "sg:address":"Avda Tagarabuena, 15",
    "sg:city":"Tagarabuena",
    "sg:orig_category":"Mec\u00c1nico Del Autom\u00d3vil",
    "sg:phone":"+34 980 69 12 50",
    "sg:postcode":"49836",
    "sg:province":"Zamora",
    "sg:website":"www.laguiadetalleres.com",
    "wof:name":"Automocion Hernandez S.l.",
    "wof:placetype":"venue"
},
  "geometry": {"coordinates":[-5.392138958,41.5401916504],"type":"Point"}
}