{
  "type": "Feature",
  "properties": {
    "iso:country":"ES",
    "sg:address":"Calle de General Franco, 31",
    "sg:city":"Lanzahita",
    "sg:orig_category":"Supermercados Y Hipermercados",
    "sg:phone":"+34 920 37 80 02",
    "sg:postcode":"05490",
    "sg:province":"\u00c1vila",
    "wof:name":"Nieto Gomez Maria Del Carmen",
    "wof:placetype":"venue"
},
  "geometry": {"coordinates":[-4.9376192093,40.203540802],"type":"Point"}
}