{
  "type": "Feature",
  "properties": {
    "iso:country":"ES",
    "sg:address":"Calle de Isaac Peral, 7",
    "sg:city":"Puente-genil",
    "sg:classifiers":[
        {
            "category":"Autos & Motor Vehicles",
            "subcategory":"Automobile Sales",
            "type":"Retail Goods"
        }
    ],
    "sg:phone":"+34 957 60 77 73",
    "sg:postcode":"14500",
    "sg:province":"C\u00f3rdoba",
    "sg:website":"www.jnformacion.com",
    "wof:name":"Jesus Nazareno Formacion Vial S.l.",
    "wof:placetype":"venue"
},
  "geometry": {"coordinates":[-4.7632570267,37.3922843933],"type":"Point"}
}