{
  "type": "Feature",
  "properties": {
    "addr:full":"Calle de Jose Maria Martorell, 28 Cordoba C\u00f3rdoba 14005",
    "addr:housenumber":"28",
    "addr:postcode":"14005",
    "addr:street":"Calle De Jose Maria Martorell;Co\u0301Rdoba",
    "iso:country":"ES",
    "sg:address":"Calle de Jose Maria Martorell, 28",
    "sg:city":"Cordoba",
    "sg:orig_category":"Inform\u00c1tica: Material Y Suministros",
    "sg:phone":"+34 957 23 97 30",
    "sg:postcode":"14005",
    "sg:province":"C\u00f3rdoba",
    "wof:name":"Lopez Castro Francisco",
    "wof:placetype":"venue"
},
  "geometry": {"coordinates":[-4.7972631454,37.8777236938],"type":"Point"}
}