{
  "type": "Feature",
  "properties": {
    "addr:full":"Ctra Roquetas, 94 Las Norias Almer\u00eda 04716",
    "addr:housenumber":"94",
    "addr:postcode":"04716",
    "addr:street":"Ctra Roquetas;Norias Almeri\u0301A",
    "iso:country":"ES",
    "sg:address":"Ctra Roquetas, 94",
    "sg:city":"Las Norias",
    "sg:orig_category":"Cajas De Ahorro",
    "sg:phone":"+34 950 60 69 57",
    "sg:postcode":"04716",
    "sg:province":"Almer\u00eda",
    "sg:website":"www.unicaja.es",
    "wof:name":"Unicaja",
    "wof:placetype":"venue"
},
  "geometry": {"coordinates":[-2.7524790764,36.7588195801],"type":"Point"}
}