{
  "type": "Feature",
  "properties": {
    "iso:country":"ES",
    "sg:address":"Calle de Alvaro De Bazan, 30",
    "sg:city":"Guadix",
    "sg:orig_category":"Molduras, Junquillos, Listones Y Molduras Perforadas",
    "sg:phone":"+34 958 66 53 71",
    "sg:postcode":"18500",
    "sg:province":"Granada",
    "wof:name":"Naon Galdon S.l.",
    "wof:placetype":"venue"
},
  "geometry": {"coordinates":[-3.1303491592,37.30027771],"type":"Point"}
}