{
  "type": "Feature",
  "properties": {
    "iso:country":"ES",
    "sg:address":"Calle de Barrameda, 77",
    "sg:city":"Sanlucar De Barrameda",
    "sg:orig_category":"Fabricaci\u00d3n De Papel Pintado",
    "sg:phone":"+34 956 36 26 15",
    "sg:postcode":"11540",
    "sg:province":"C\u00e1diz",
    "wof:name":"Sayago Diaz Jose",
    "wof:placetype":"venue"
},
  "geometry": {"coordinates":[-6.3450889587,36.7843513489],"type":"Point"}
}