{
  "type": "Feature",
  "properties": {
    "addr:full":"Carrer de Marina, 179 Barcelona Barcelona 08013",
    "addr:housenumber":"179",
    "addr:postcode":"08013",
    "addr:street":"Carrer De Marina",
    "iso:country":"ES",
    "sg:address":"Carrer de Marina, 179",
    "sg:city":"Barcelona",
    "sg:orig_category":"Caf\u00c9s, Bares, Cervecer\u00cdas",
    "sg:phone":"+34 932 45 36 11",
    "sg:postcode":"08013",
    "sg:province":"Barcelona",
    "wof:name":"Cafes Benajes Margot S.l.",
    "wof:placetype":"venue"
},
  "geometry": {"coordinates":[2.1803600788,41.3996200562],"type":"Point"}
}