{
  "type": "Feature",
  "properties": {
    "iso:country":"ES",
    "sg:address":"Avda Vega Baja, 21",
    "sg:city":"Rojales",
    "sg:classifiers":[
        {
            "category":"Autos & Motor Vehicles",
            "subcategory":"Automobile Sales",
            "type":"Retail Goods"
        }
    ],
    "sg:phone":"+34 966 71 46 03",
    "sg:postcode":"03170",
    "sg:province":"Alicante",
    "wof:name":"Rives Marroqui Bienvenida",
    "wof:placetype":"venue"
},
  "geometry": {"coordinates":[-0.7247689962,38.0882415771],"type":"Point"}
}