{
  "type": "Feature",
  "properties": {
    "iso:country":"ES",
    "sg:address":"Carrer de Foneria, 39",
    "sg:city":"Barcelona",
    "sg:orig_category":"Bisuter\u00cda, Joyer\u00cda, Relojer\u00cda (al Por Menor)",
    "sg:phone":"+34 932 96 84 60",
    "sg:postcode":"08038",
    "sg:province":"Barcelona",
    "wof:name":"Joieria I Rellotgeria Olga Joies Sl",
    "wof:placetype":"venue"
},
  "geometry": {"coordinates":[2.1396861076,41.3610458374],"type":"Point"}
}