{
  "type": "Feature",
  "properties": {
    "addr:full":"Vieja (la Vera), 37 Sta.ursula Santa Cruz De Tenerife 38390",
    "addr:housenumber":"37",
    "addr:postcode":"38390",
    "addr:street":"Vieja La Vera",
    "iso:country":"ES",
    "sg:address":"Vieja (la Vera), 37",
    "sg:city":"Sta.ursula",
    "sg:orig_category":"Distribuci\u00d3n De Petr\u00d3leo Y Derivados",
    "sg:phone":"+34 922 30 11 61",
    "sg:postcode":"38390",
    "sg:province":"Santa Cruz De Tenerife",
    "wof:name":"Ahumados Tenerife S.l.",
    "wof:placetype":"venue"
},
  "geometry": {"coordinates":[-16.485578537,28.4282226562],"type":"Point"}
}