{
  "type": "Feature",
  "properties": {
    "addr:full":"Rua Coru\u00d1a, 38 Vigo Pontevedra 36211",
    "addr:housenumber":"38",
    "addr:postcode":"36211",
    "addr:street":"Rua Corun\u0303A",
    "iso:country":"ES",
    "sg:address":"Rua Coru\u00d1a, 38",
    "sg:city":"Vigo",
    "sg:orig_category":"Transportes Por Carretera: Lotes Completos, Mercanc\u00cdas Diversas",
    "sg:phone":"+34 986 21 04 77",
    "sg:postcode":"36211",
    "sg:province":"Pontevedra",
    "wof:name":"Perez Cristobo Manuel",
    "wof:placetype":"venue"
},
  "geometry": {"coordinates":[-8.734249115,42.2223892212],"type":"Point"}
}