{
  "type": "Feature",
  "properties": {
    "addr:full":"Calle de Doctor Carlos Belmonte, 1 Alacant Alicante 03012",
    "addr:housenumber":"1",
    "addr:postcode":"03012",
    "addr:street":"Calle De Doctor Carlos Belmonte",
    "iso:country":"ES",
    "sg:address":"Calle de Doctor Carlos Belmonte, 1",
    "sg:city":"Alacant",
    "sg:orig_category":"Agencias Y Agentes Comerciales, Representantes",
    "sg:phone":"+34 965 24 46 72",
    "sg:postcode":"03012",
    "sg:province":"Alicante",
    "wof:name":"Lopez Rubio Juan Maria",
    "wof:placetype":"venue"
},
  "geometry": {"coordinates":[-0.4709843993,38.361541748],"type":"Point"}
}