{
  "type": "Feature",
  "properties": {
    "addr:full":"Bard Mochos (los), 179 Mochos C\u00f3rdoba 14729",
    "addr:housenumber":"179",
    "addr:postcode":"14729",
    "addr:street":"Los;Co\u0301Rdoba",
    "iso:country":"ES",
    "sg:address":"Bard Mochos (los), 179",
    "sg:city":"Mochos",
    "sg:classifiers":[
        {
            "category":"Taxi",
            "type":"Transportation"
        }
    ],
    "sg:phone":"+34 957 71 51 52",
    "sg:postcode":"14729",
    "sg:province":"C\u00f3rdoba",
    "wof:name":"Garcia Martinez Pablo",
    "wof:placetype":"venue"
},
  "geometry": {"coordinates":[-4.9513840675,37.8344802856],"type":"Point"}
}