{
  "type": "Feature",
  "properties": {
    "addr:full":"Avgd Vicent Mortes Alfonso, 29 Paterna Valencia 46980",
    "addr:housenumber":"29",
    "addr:postcode":"46980",
    "addr:street":"Alfonso",
    "iso:country":"ES",
    "sg:address":"Avgd Vicent Mortes Alfonso, 29",
    "sg:city":"Paterna",
    "sg:orig_category":"Agencias De Viajes",
    "sg:phone":"+34 961 38 84 11",
    "sg:postcode":"46980",
    "sg:province":"Valencia",
    "wof:name":"Viajes El Corte Ingles S.a.",
    "wof:placetype":"venue"
},
  "geometry": {"coordinates":[-0.4472660124,39.5061187744],"type":"Point"}
}