{
  "type": "Feature",
  "properties": {
    "iso:country":"ES",
    "sg:address":"Carr Gallines, 4",
    "sg:city":"Castello D'empuries",
    "sg:orig_category":"Peluquer\u00cdas, Peluquer\u00cda Mixta",
    "sg:phone":"+34 972 25 04 88",
    "sg:postcode":"17486",
    "sg:province":"Girona",
    "wof:name":"Costa Vidal Montserrat",
    "wof:placetype":"venue"
},
  "geometry": {"coordinates":[3.1588490009,42.1112327576],"type":"Point"}
}