{
  "type": "Feature",
  "properties": {
    "addr:full":"Pl Carme, Del, 2 Porto Cristo Islas Baleares 07680",
    "addr:housenumber":"2",
    "addr:postcode":"07680",
    "addr:street":"Pl Carme Del;Islas Baleares",
    "iso:country":"ES",
    "sg:address":"Pl Carme, Del, 2",
    "sg:city":"Porto Cristo",
    "sg:orig_category":"Farmacias",
    "sg:phone":"+34 971 82 08 30",
    "sg:postcode":"07680",
    "sg:province":"Islas Baleares",
    "wof:name":"Gomila Capo Juan",
    "wof:placetype":"venue"
},
  "geometry": {"coordinates":[3.3340070248,39.5426368713],"type":"Point"}
}