{
  "type": "Feature",
  "properties": {
    "addr:full":"El Vino, S/n Puebla Almoradiel Toledo 45840",
    "addr:housenumber":"s",
    "addr:postcode":"45840",
    "addr:street":"/ N",
    "iso:country":"ES",
    "sg:address":"El Vino, S/n",
    "sg:city":"Puebla Almoradiel",
    "sg:orig_category":"Promotores Constructores",
    "sg:phone":"+34 925 17 84 41",
    "sg:postcode":"45840",
    "sg:province":"Toledo",
    "wof:name":"Anastasio Casas S.a.",
    "wof:placetype":"venue"
},
  "geometry": {"coordinates":[-3.1122379303,39.5960731506],"type":"Point"}
}