{
  "type": "Feature",
  "properties": {
    "addr:full":"Calle de Mengabril, 57 Don Benito Badajoz 06400",
    "addr:housenumber":"57",
    "addr:postcode":"06400",
    "addr:street":"Calle De Mengabril",
    "iso:country":"ES",
    "sg:address":"Calle de Mengabril, 57",
    "sg:city":"Don Benito",
    "sg:classifiers":[
        {
            "category":"Personal",
            "subcategory":"Barber",
            "type":"Services"
        }
    ],
    "sg:phone":"+34 924 81 27 20",
    "sg:postcode":"06400",
    "sg:province":"Badajoz",
    "sg:tags":[
        "caballeros",
        "de",
        "peluqueros"
    ],
    "wof:name":"Escobar Aparicio Juan Carlos",
    "wof:placetype":"venue"
},
  "geometry": {"coordinates":[-5.8658790588,38.9604797363],"type":"Point"}
}