{
  "type": "Feature",
  "properties": {
    "addr:full":"Ptge Aloi, 8 Barcelona Barcelona 08041",
    "addr:housenumber":"8",
    "addr:postcode":"08041",
    "addr:street":"Ptge Aloi",
    "iso:country":"ES",
    "sg:address":"Ptge Aloi, 8",
    "sg:city":"Barcelona",
    "sg:orig_category":"Centros De Educaci\u00d3n Especial",
    "sg:phone":"+34 934 55 62 40",
    "sg:postcode":"08041",
    "sg:province":"Barcelona",
    "wof:name":"Guinyolet S.c.p.",
    "wof:placetype":"venue"
},
  "geometry": {"coordinates":[2.1807870865,41.417339325],"type":"Point"}
}