{
  "type": "Feature",
  "properties": {
    "iso:country":"ES",
    "sg:address":"Cra. Artesa, Km. 0038,3",
    "sg:city":"Montblanc",
    "sg:orig_category":"Promotores Constructores",
    "sg:phone":"+34 977 86 26 17",
    "sg:postcode":"43400",
    "sg:province":"Tarragona",
    "wof:name":"Comercial Josep Pocarull S. L.",
    "wof:placetype":"venue"
},
  "geometry": {"coordinates":[1.1643300056,41.3753395081],"type":"Point"}
}