{
  "type": "Feature",
  "properties": {
    "iso:country":"ES",
    "sg:address":"Avda Andalucia, 42",
    "sg:city":"Puerta De Segura",
    "sg:orig_category":"Estancos",
    "sg:phone":"+34 953 48 61 04",
    "sg:postcode":"23360",
    "sg:province":"Ja\u00e9n",
    "wof:name":"Bellon Bellon Maria Dolores",
    "wof:placetype":"venue"
},
  "geometry": {"coordinates":[-2.7384710312,38.3514518738],"type":"Point"}
}