{
  "type": "Feature",
  "properties": {
    "iso:country":"ES",
    "sg:address":"Praz Vigo (de), 1",
    "sg:city":"Santiago De Compostela",
    "sg:orig_category":"Ense\u00d1anza Variada",
    "sg:phone":"+34 981 59 00 20",
    "sg:postcode":"15706",
    "sg:province":"La Coru\u00f1a",
    "wof:name":"Salvamento Y Contraincendios S.l.",
    "wof:placetype":"venue"
},
  "geometry": {"coordinates":[-8.581829071,42.8648948669],"type":"Point"}
}