{
  "type": "Feature",
  "properties": {
    "addr:full":"Calle de Doctor Camacho, 1 Badajoz Badajoz 06011",
    "addr:housenumber":"1",
    "addr:postcode":"06011",
    "addr:street":"Calle De Doctor Camacho",
    "iso:country":"ES",
    "sg:address":"Calle de Doctor Camacho, 1",
    "sg:city":"Badajoz",
    "sg:orig_category":"Ense\u00d1anza: Comercio, Gesti\u00d3n, Inform\u00c1tica",
    "sg:phone":"+34 924 26 10 90",
    "sg:postcode":"06011",
    "sg:province":"Badajoz",
    "sg:website":"www.multimediafmi.com",
    "wof:name":"Instituto De Tecnologia Electronica Informatica Y Comunicaciones S.l.",
    "wof:placetype":"venue"
},
  "geometry": {"coordinates":[-6.9868168831,38.8749160767],"type":"Point"}
}