{
  "type": "Feature",
  "properties": {
    "iso:country":"ES",
    "sg:address":"Calle de San Miguel (casetas), 32",
    "sg:city":"Casetas",
    "sg:orig_category":"Quincaller\u00cda (fabricaci\u00d3n)",
    "sg:phone":"+34 976 77 15 78",
    "sg:postcode":"50620",
    "sg:province":"Zaragoza",
    "wof:name":"Etxezarraga Comas Javier",
    "wof:placetype":"venue"
},
  "geometry": {"coordinates":[-1.0252180099,41.7194328308],"type":"Point"}
}