{
  "type": "Feature",
  "properties": {
    "iso:country":"ES",
    "sg:address":"Calle de Montellano, S/n",
    "sg:city":"Moron Frontera",
    "sg:orig_category":"Asociaciones Y Clubs Deportivos",
    "sg:phone":"+34 955 85 40 64",
    "sg:postcode":"41530",
    "sg:province":"Sevilla",
    "wof:name":"Agrupacion Deportiva Frontenis Moron 85",
    "wof:placetype":"venue"
},
  "geometry": {"coordinates":[-5.5033898354,37.0890922546],"type":"Point"}
}