{
  "type": "Feature",
  "properties": {
    "iso:country":"ES",
    "sg:address":"Rua Preguntoiro (do), 35",
    "sg:city":"Santiago De Compostela",
    "sg:orig_category":"Zapater\u00cdas",
    "sg:phone":"+34 981 58 10 48",
    "sg:postcode":"15704",
    "sg:province":"La Coru\u00f1a",
    "wof:name":"Chaves Vites Jose Severino",
    "wof:placetype":"venue"
},
  "geometry": {"coordinates":[-8.5421953201,42.8799972534],"type":"Point"}
}