{
  "type": "Feature",
  "properties": {
    "addr:full":"Carrer de Riera Canals, 3 S. Andreu Barca Barcelona 08740",
    "addr:housenumber":"3",
    "addr:postcode":"08740",
    "addr:street":"Carrer De Riera Canals;S. Andreu;Barcelona",
    "iso:country":"ES",
    "sg:address":"Carrer de Riera Canals, 3",
    "sg:city":"S. Andreu Barca",
    "sg:orig_category":"Asesor\u00cda Sobre Comunicaci\u00d3n De Empresas",
    "sg:phone":"+34 936 82 35 66",
    "sg:postcode":"08740",
    "sg:province":"Barcelona",
    "wof:name":"Assessoria Progestio S.l.",
    "wof:placetype":"venue"
},
  "geometry": {"coordinates":[1.9722669125,41.4481506348],"type":"Point"}
}