{
  "type": "Feature",
  "properties": {
    "addr:full":"Calle de Nueva, 74 Moron Frontera Sevilla 41530",
    "addr:housenumber":"74",
    "addr:postcode":"41530",
    "addr:street":"Calle De Nueva",
    "iso:country":"ES",
    "sg:address":"Calle de Nueva, 74",
    "sg:city":"Moron Frontera",
    "sg:orig_category":"Empresas De Portes Y Mensajer\u00cda",
    "sg:phone":"+34 955 85 18 96",
    "sg:postcode":"41530",
    "sg:province":"Sevilla",
    "sg:website":"www.mrw.es",
    "wof:name":"Mensajeria Integral Del Sur S.l",
    "wof:placetype":"venue"
},
  "geometry": {"coordinates":[-5.4515690804,37.1209030151],"type":"Point"}
}