{
  "type": "Feature",
  "properties": {
    "addr:full":"Calle de Constitucion, 3 Altea Alicante 03590",
    "addr:housenumber":"3",
    "addr:postcode":"03590",
    "addr:street":"Calle De Constitucion",
    "iso:country":"ES",
    "sg:address":"Calle de Constitucion, 3",
    "sg:city":"Altea",
    "sg:orig_category":"M\u00c9dicos: Oftalmolog\u00cda",
    "sg:phone":"+34 965 84 27 74",
    "sg:postcode":"03590",
    "sg:province":"Alicante",
    "wof:name":"Palomares Palomares Juan Manuel",
    "wof:placetype":"venue"
},
  "geometry": {"coordinates":[-0.0472897999,38.6015357971],"type":"Point"}
}