{
  "type": "Feature",
  "properties": {
    "addr:full":"Calle de Pez, 16 Madrid Madrid 28004",
    "addr:housenumber":"16",
    "addr:postcode":"madrid;28004",
    "addr:street":"Calle De Pez",
    "iso:country":"ES",
    "sg:address":"Calle de Pez, 16",
    "sg:city":"Madrid",
    "sg:orig_category":"Tiendas De Grano, Frutas Y Legumbres Secas (al Por Menor)",
    "sg:phone":"+34 915 23 38 04",
    "sg:postcode":"28004",
    "sg:province":"Madrid",
    "wof:name":"Guo  Chonglong",
    "wof:placetype":"venue"
},
  "geometry": {"coordinates":[-3.7050380707,40.4237060547],"type":"Point"}
}