{
  "type": "Feature",
  "properties": {
    "iso:country":"ES",
    "sg:address":"Avda Libertad, 62",
    "sg:city":"Ubeda",
    "sg:orig_category":"Comercio De Piezas De Recambio Y De Accesorios De Veh\u00cdculos, Veh\u00cdculos Industriales",
    "sg:phone":"+34 953 75 50 43",
    "sg:postcode":"23400",
    "sg:province":"Ja\u00e9n",
    "wof:name":"Talleres Novo Cristal S.l.",
    "wof:placetype":"venue"
},
  "geometry": {"coordinates":[-3.3669929504,38.0168151855],"type":"Point"}
}