{
  "type": "Feature",
  "properties": {
    "iso:country":"ES",
    "sg:address":"Calle de Pintores, 45",
    "sg:city":"Rota",
    "sg:orig_category":"Promotores Constructores",
    "sg:phone":"+34 956 81 08 66",
    "sg:postcode":"11520",
    "sg:province":"C\u00e1diz",
    "wof:name":"Urval Civil S.l.",
    "wof:placetype":"venue"
},
  "geometry": {"coordinates":[-6.3657522202,36.6325798035],"type":"Point"}
}