{
  "type": "Feature",
  "properties": {
    "addr:full":"Calle de Masustegi, 9 Bilbao Vizcaya 48006",
    "addr:housenumber":"9",
    "addr:postcode":"48006",
    "addr:street":"Calle De Masustegi",
    "iso:country":"ES",
    "sg:address":"Calle de Masustegi, 9",
    "sg:city":"Bilbao",
    "sg:orig_category":"Inform\u00c1tica (estudios, Servicios, Asesor\u00cda, Formaci\u00d3n)",
    "sg:phone":"+34 944 32 92 86",
    "sg:postcode":"48006",
    "sg:province":"Vizcaya",
    "wof:name":"Ipartek Servicios Informaticos",
    "wof:placetype":"venue"
},
  "geometry": {"coordinates":[-2.9136340618,43.2563934326],"type":"Point"}
}