{
  "type": "Feature",
  "properties": {
    "addr:full":"Varadero, S/n Maspalomas Las Palmas 35100",
    "addr:housenumber":"s / n",
    "addr:postcode":"35100",
    "iso:country":"ES",
    "sg:address":"Varadero, S/n",
    "sg:city":"Maspalomas",
    "sg:orig_category":"Bisuter\u00cda, Joyer\u00cda, Relojer\u00cda (al Por Menor)",
    "sg:phone":"+34 928 14 02 83",
    "sg:postcode":"35100",
    "sg:province":"Las Palmas",
    "wof:name":"Vaswani  Prakash",
    "wof:placetype":"venue"
},
  "geometry": {"coordinates":[-15.5830888748,27.7700748444],"type":"Point"}
}