{
  "type": "Feature",
  "properties": {
    "iso:country":"ES",
    "sg:address":"Carretera Santander, 15",
    "sg:city":"Villaobispo De Las Regueras",
    "sg:orig_category":"Centros Empresariales",
    "sg:phone":"+34 987 30 70 11",
    "sg:postcode":"24007",
    "sg:province":"Le\u00f3n",
    "wof:name":"Lesmes Roca Manuel Angel",
    "wof:placetype":"venue"
},
  "geometry": {"coordinates":[-5.5530691147,42.6144561768],"type":"Point"}
}