{
  "type": "Feature",
  "properties": {
    "addr:full":"Calle de Molino, 9 Arrecife Las Palmas 35500",
    "addr:housenumber":"9",
    "addr:postcode":"35500",
    "addr:street":"Calle De Molino",
    "iso:country":"ES",
    "sg:address":"Calle de Molino, 9",
    "sg:city":"Arrecife",
    "sg:orig_category":"Pensiones Familiares",
    "sg:phone":"+34 928 81 23 51",
    "sg:postcode":"35500",
    "sg:province":"Las Palmas",
    "wof:name":"Betancort Perez Gines",
    "wof:placetype":"venue"
},
  "geometry": {"coordinates":[-13.5497341156,28.9626197815],"type":"Point"}
}