{
  "type": "Feature",
  "properties": {
    "addr:full":"Rond Bernat Ali\u00d1o, 45 Sueca Valencia 46410",
    "addr:housenumber":"45",
    "addr:postcode":"46410",
    "addr:street":"Alin\u0303O",
    "iso:country":"ES",
    "sg:address":"Rond Bernat Ali\u00d1o, 45",
    "sg:city":"Sueca",
    "sg:orig_category":"Iglesia Cat\u00d3lica",
    "sg:phone":"+34 961 70 03 20",
    "sg:postcode":"46410",
    "sg:province":"Valencia",
    "wof:name":"Parroquia De La Virgen Milagrosa",
    "wof:placetype":"venue"
},
  "geometry": {"coordinates":[-0.3077090085,39.2030639648],"type":"Point"}
}