{
  "type": "Feature",
  "properties": {
    "iso:country":"ES",
    "sg:address":"Avda Malaga (de), S/n",
    "sg:city":"Villanueva Trabuco",
    "sg:orig_category":"Bazares, Art\u00cdculos De Limpieza Y De Cocina (al Por Menor)",
    "sg:phone":"+34 952 75 17 66",
    "sg:postcode":"29313",
    "sg:province":"M\u00e1laga",
    "wof:name":"Garcia Ortigosa Manuel",
    "wof:placetype":"venue"
},
  "geometry": {"coordinates":[-4.3407793045,37.0264396667],"type":"Point"}
}