{
  "type": "Feature",
  "properties": {
    "iso:country":"ES",
    "sg:address":"Carr Anselm Clave, 1",
    "sg:city":"Santa Coloma De Farners",
    "sg:orig_category":"Quincaller\u00cda (al Por Menor)",
    "sg:phone":"+34 972 84 02 52",
    "sg:postcode":"17430",
    "sg:province":"Girona",
    "wof:name":"Antoner Vivolas Jordi",
    "wof:placetype":"venue"
},
  "geometry": {"coordinates":[2.6641697884,41.8632354736],"type":"Point"}
}