{
  "type": "Feature",
  "properties": {
    "addr:full":"Calle de Do\u00d1a Urraca, 9 Madrid Madrid 28011",
    "addr:housenumber":"9",
    "addr:postcode":"madrid;28011",
    "addr:street":"Calle De Don\u0303A Urraca",
    "iso:country":"ES",
    "sg:address":"Calle de Do\u00d1a Urraca, 9",
    "sg:city":"Madrid",
    "sg:orig_category":"Cerrajer\u00cda, Ferrallista",
    "sg:phone":"+34 914 64 33 85",
    "sg:postcode":"28011",
    "sg:province":"Madrid",
    "wof:name":"Toledano Villamarin Julio",
    "wof:placetype":"venue"
},
  "geometry": {"coordinates":[-3.7252810001,40.4129676819],"type":"Point"}
}