{
  "type": "Feature",
  "properties": {
    "iso:country":"ES",
    "sg:address":"Calle de Alberto Aguilera, 62",
    "sg:city":"Madrid",
    "sg:orig_category":"Agencias De Viajes",
    "sg:phone":"+34 915 49 83 11",
    "sg:postcode":"28015",
    "sg:province":"Madrid",
    "sg:website":"www.unav.ws",
    "wof:name":"Union De Agencias De Viajes S.a.",
    "wof:placetype":"venue"
},
  "geometry": {"coordinates":[-3.7144880295,40.4305725098],"type":"Point"}
}