{
  "type": "Feature",
  "properties": {
    "iso:country":"ES",
    "sg:address":"Calle de San Juan De Ribera, S/n",
    "sg:city":"Sevilla",
    "sg:orig_category":"Aparcamientos (infraestructuras, Accesorios)",
    "sg:phone":"+34 954 90 78 18",
    "sg:postcode":"41009",
    "sg:province":"Sevilla",
    "wof:name":"Saba Aparcamientos S.a.",
    "wof:placetype":"venue"
},
  "geometry": {"coordinates":[-5.9864888191,37.4052467346],"type":"Point"}
}