{
  "type": "Feature",
  "properties": {
    "addr:full":"Calle de Cardenal Fonseca, 5 Alcala Henares Madrid 28805",
    "addr:housenumber":"5",
    "addr:postcode":"28805",
    "addr:street":"Calle De Cardenal Fonseca",
    "iso:country":"ES",
    "sg:address":"Calle de Cardenal Fonseca, 5",
    "sg:city":"Alcala Henares",
    "sg:orig_category":"Peluqueros: De Se\u00d1oras",
    "sg:phone":"+34 918 88 32 90",
    "sg:postcode":"28805",
    "sg:province":"Madrid",
    "wof:name":"Lopez Velasco Juana",
    "wof:placetype":"venue"
},
  "geometry": {"coordinates":[-3.3563437462,40.4868927002],"type":"Point"}
}