{
  "type": "Feature",
  "properties": {
    "iso:country":"ES",
    "sg:address":"Cno Bayon, 8",
    "sg:city":"Hondon Nieves",
    "sg:orig_category":"Art\u00cdculos De Madera (fabricaci\u00d3n Y Al Por Mayor)",
    "sg:phone":"+34 965 48 01 53",
    "sg:postcode":"03688",
    "sg:province":"Alicante",
    "wof:name":"Pavia Cerdan Jose Francisco",
    "wof:placetype":"venue"
},
  "geometry": {"coordinates":[-1.0403139591,38.3488845825],"type":"Point"}
}