{
  "type": "Feature",
  "properties": {
    "iso:country":"ES",
    "sg:address":"Trav De Gracia, 8",
    "sg:city":"Barcelona",
    "sg:orig_category":"Confecci\u00d3n De Trajes Para Se\u00d1oras",
    "sg:phone":"+34 932 01 75 04",
    "sg:postcode":"08021",
    "sg:province":"Barcelona",
    "wof:name":"La Bul 75 S.a.",
    "wof:placetype":"venue"
},
  "geometry": {"coordinates":[2.1460390091,41.3936958313],"type":"Point"}
}