{
  "type": "Feature",
  "properties": {
    "addr:full":"Ctra Benavente, 7 Valderas Le\u00f3n 24220",
    "addr:housenumber":"7",
    "addr:postcode":"24220",
    "addr:street":"Ctra Benavente",
    "iso:country":"ES",
    "sg:address":"Ctra Benavente, 7",
    "sg:city":"Valderas",
    "sg:orig_category":"Electricidad: Instaladores",
    "sg:phone":"+34 987 76 32 22",
    "sg:postcode":"24220",
    "sg:province":"Le\u00f3n",
    "wof:name":"Fernandez Ovejero Raul",
    "wof:placetype":"venue"
},
  "geometry": {"coordinates":[-5.4420042038,42.076461792],"type":"Point"}
}