{
  "type": "Feature",
  "properties": {
    "addr:full":"Calle de Germanies, 37 Torrent Valencia 46900",
    "addr:housenumber":"37",
    "addr:postcode":"46900",
    "addr:street":"Calle De Germanies;Valencia",
    "iso:country":"ES",
    "sg:address":"Calle de Germanies, 37",
    "sg:city":"Torrent",
    "sg:orig_category":"Electricidad: Instaladores",
    "sg:phone":"+34 961 55 51 08",
    "sg:postcode":"46900",
    "sg:province":"Valencia",
    "wof:name":"Medina Bartual Jose Vicente",
    "wof:placetype":"venue"
},
  "geometry": {"coordinates":[-0.4718950093,39.4339141846],"type":"Point"}
}