{
  "type": "Feature",
  "properties": {
    "iso:country":"ES",
    "sg:address":"Ctra Rubi, 332",
    "sg:city":"Fonts",
    "sg:orig_category":"Chapister\u00cda",
    "sg:phone":"+34 937 85 58 72",
    "sg:postcode":"08228",
    "sg:province":"Barcelona",
    "wof:name":"Ripolles Marin Jose",
    "wof:placetype":"venue"
},
  "geometry": {"coordinates":[2.0349860191,41.5328407288],"type":"Point"}
}