{
  "type": "Feature",
  "properties": {
    "addr:full":"Poli Mugitegi-d, 15 Urretxu Guip\u00f9zcoa 20700",
    "addr:housenumber":"15",
    "addr:postcode":"20700",
    "addr:street":"Mugitegi-D;Guipu\u0300Zcoa",
    "iso:country":"ES",
    "sg:address":"Poli Mugitegi-d, 15",
    "sg:city":"Urretxu",
    "sg:orig_category":"Oxigenoterapia",
    "sg:phone":"+34 943 72 60 65",
    "sg:postcode":"20700",
    "sg:province":"Guip\u00f9zcoa",
    "wof:name":"I\u00f1aki Aranguren Ordu\u00f1a",
    "wof:placetype":"venue"
},
  "geometry": {"coordinates":[-2.3134770393,43.086730957],"type":"Point"}
}