{
  "type": "Feature",
  "properties": {
    "iso:country":"ES",
    "sg:address":"Plaz Hospital, 4",
    "sg:city":"Berlanga Duero",
    "sg:orig_category":"Ense\u00d1anza, Formaci\u00d3n Profesional: Aprendizaje",
    "sg:phone":"+34 975 34 30 43",
    "sg:postcode":"42360",
    "sg:province":"Soria",
    "wof:name":"Ayuntamiento De Berlanga De Duero",
    "wof:placetype":"venue"
},
  "geometry": {"coordinates":[-2.8622839451,41.4676399231],"type":"Point"}
}