{
  "type": "Feature",
  "properties": {
    "iso:country":"ES",
    "sg:address":"Calle de Pinar, 2",
    "sg:city":"Zamora",
    "sg:orig_category":"Centros De Salud",
    "sg:phone":"+34 980 52 16 83",
    "sg:postcode":"49023",
    "sg:province":"Zamora",
    "wof:name":"Patro-68 S.a.",
    "wof:placetype":"venue"
},
  "geometry": {"coordinates":[-5.7443981171,41.516494751],"type":"Point"}
}