{
  "type": "Feature",
  "properties": {
    "addr:full":"Carrer de Ample, 15 Reus Tarragona 43202",
    "addr:housenumber":"15",
    "addr:postcode":"43202",
    "addr:street":"Carrer De Ample",
    "iso:country":"ES",
    "sg:address":"Carrer de Ample, 15",
    "sg:city":"Reus",
    "sg:orig_category":"Vinos Y Licores (venta Al Por Menor)",
    "sg:phone":"+34 977 31 17 28",
    "sg:postcode":"43202",
    "sg:province":"Tarragona",
    "wof:name":"Saune Llombart Montserrat",
    "wof:placetype":"venue"
},
  "geometry": {"coordinates":[1.1044620275,41.1587295532],"type":"Point"}
}