{
  "type": "Feature",
  "properties": {
    "addr:full":"Carr Mariscal Cabanes, 28 Badalona Barcelona 08918",
    "addr:housenumber":"28",
    "addr:postcode":"08918",
    "addr:street":"Carr Mariscal Cabanes",
    "iso:country":"ES",
    "sg:address":"Carr Mariscal Cabanes, 28",
    "sg:city":"Badalona",
    "sg:orig_category":"Complementos Para Pasteler\u00cdas, Confiter\u00cdas Y Chocolater\u00cdas",
    "sg:phone":"+34 933 99 10 59",
    "sg:postcode":"08918",
    "sg:province":"Barcelona",
    "wof:name":"Distribuciones Delfin Garcia S.l.",
    "wof:placetype":"venue"
},
  "geometry": {"coordinates":[2.2182180882,41.4334449768],"type":"Point"}
}