{
  "type": "Feature",
  "properties": {
    "addr:full":"Calle de Goya, 41 Madrid Madrid 28001",
    "addr:housenumber":"41",
    "addr:postcode":"madrid;28001",
    "addr:street":"Calle De Goya",
    "iso:country":"ES",
    "sg:address":"Calle de Goya, 41",
    "sg:city":"Madrid",
    "sg:orig_category":"Administradores De Bienes Y Delegados De Comunidades De Propietarios",
    "sg:phone":"+34 914 02 95 72",
    "sg:postcode":"28001",
    "sg:province":"Madrid",
    "wof:name":"Visesa Servicios Integrales S.l.",
    "wof:placetype":"venue"
},
  "geometry": {"coordinates":[-3.6831738949,40.4252929688],"type":"Point"}
}