{
  "type": "Feature",
  "properties": {
    "iso:country":"ES",
    "sg:address":"Calle de Balbino Orensanz, 55",
    "sg:city":"Zaragoza",
    "sg:orig_category":"Electricidad: Equipos Industriales, Componentes (fabricaci\u00d3n)",
    "sg:phone":"+34 976 20 43 71",
    "sg:postcode":"50014",
    "sg:province":"Zaragoza",
    "wof:name":"Talayero Perez Francisco Jose",
    "wof:placetype":"venue"
},
  "geometry": {"coordinates":[-0.8586289883,41.6561813354],"type":"Point"}
}