{
  "type": "Feature",
  "properties": {
    "addr:full":"Calle de Augusto Bebel, 13 Zaragoza Zaragoza 50015",
    "addr:housenumber":"13",
    "addr:postcode":"50015",
    "addr:street":"Calle De Augusto Bebel",
    "iso:country":"ES",
    "sg:address":"Calle de Augusto Bebel, 13",
    "sg:city":"Zaragoza",
    "sg:orig_category":"Caf\u00c9s, Bares, Cervecer\u00cdas",
    "sg:phone":"+34 976 73 76 62",
    "sg:postcode":"50015",
    "sg:province":"Zaragoza",
    "wof:name":"Telef.pub.aragon",
    "wof:placetype":"venue"
},
  "geometry": {"coordinates":[-0.8781440258,41.6713867188],"type":"Point"}
}