{
  "type": "Feature",
  "properties": {
    "addr:full":"Carrer de Abat Escarre, 5 Sabadell Barcelona 08206",
    "addr:housenumber":"5",
    "addr:postcode":"08206",
    "addr:street":"Carrer De Abat Escarre",
    "iso:country":"ES",
    "sg:address":"Carrer de Abat Escarre, 5",
    "sg:city":"Sabadell",
    "sg:orig_category":"Ense\u00d1anza: Profesiones Art\u00cdsticas",
    "sg:phone":"+34 937 24 22 66",
    "sg:postcode":"08206",
    "sg:province":"Barcelona",
    "wof:name":"Martos Martinez Sergio",
    "wof:placetype":"venue"
},
  "geometry": {"coordinates":[2.0962910652,41.5555076599],"type":"Point"}
}