{
  "type": "Feature",
  "properties": {
    "addr:full":"Avda Mariana Pineda, 4 Guadix Granada 18500",
    "addr:housenumber":"4",
    "addr:postcode":"18500",
    "addr:street":"Avda Mariana Pineda",
    "iso:country":"ES",
    "sg:address":"Avda Mariana Pineda, 4",
    "sg:city":"Guadix",
    "sg:orig_category":"Peluquer\u00cdas, Peluquer\u00cda Mixta",
    "sg:phone":"+34 958 66 32 91",
    "sg:postcode":"18500",
    "sg:province":"Granada",
    "wof:name":"Ratia Martinez Maria Sonia",
    "wof:placetype":"venue"
},
  "geometry": {"coordinates":[-3.1364541054,37.3026771545],"type":"Point"}
}