{
  "type": "Feature",
  "properties": {
    "iso:country":"ES",
    "sg:address":"Avda Casanova De Eiris, 13",
    "sg:city":"Coru\u00d1a",
    "sg:orig_category":"Alimentaci\u00d3n General (al Por Menor)",
    "sg:phone":"+34 981 28 52 96",
    "sg:postcode":"15009",
    "sg:province":"La Coru\u00f1a",
    "wof:name":"Garaboa Ares Manuel",
    "wof:placetype":"venue"
},
  "geometry": {"coordinates":[-8.3977956772,43.3503723145],"type":"Point"}
}