{
  "type": "Feature",
  "properties": {
    "iso:country":"ES",
    "sg:address":"Ctra Barcelona, S/n",
    "sg:city":"Vendrell",
    "sg:orig_category":"Pintura, Barniz, Productos Asimilables (fabricaci\u00d3n, Al Por Mayor)",
    "sg:phone":"+34 977 66 77 68",
    "sg:postcode":"43700",
    "sg:province":"Tarragona",
    "wof:name":"Comercial Rediva S.a.",
    "wof:placetype":"venue"
},
  "geometry": {"coordinates":[1.5433399677,41.2241249084],"type":"Point"}
}