{
  "type": "Feature",
  "properties": {
    "iso:country":"ES",
    "sg:address":"Rond Xose Casti\u00d1eira (musico), 10",
    "sg:city":"Lugo",
    "sg:orig_category":"Empresas De Desmonte",
    "sg:phone":"+34 982 23 04 61",
    "sg:postcode":"27002",
    "sg:province":"Lugo",
    "wof:name":"Cela Abuin S.l.",
    "wof:placetype":"venue"
},
  "geometry": {"coordinates":[-7.548268795,42.9990615845],"type":"Point"}
}