{
  "type": "Feature",
  "properties": {
    "iso:country":"ES",
    "sg:address":"Calle de Gorbea, 48",
    "sg:city":"Vitoria-gasteiz",
    "sg:orig_category":"Art\u00cdculos De Decoraci\u00d3n",
    "sg:phone":"+34 945 06 84 15",
    "sg:postcode":"01012",
    "sg:province":"\u00c1lava",
    "wof:name":"Decoracion Armas,  S.l.",
    "wof:placetype":"venue"
},
  "geometry": {"coordinates":[-2.6787950993,42.8543167114],"type":"Point"}
}