{
  "type": "Feature",
  "properties": {
    "addr:full":"Poli Poligono Industrial, 32 Barros Cantabria 39408",
    "addr:housenumber":"32",
    "addr:postcode":"39408",
    "addr:street":"Poligono Industrial",
    "iso:country":"ES",
    "sg:address":"Poli Poligono Industrial, 32",
    "sg:city":"Barros",
    "sg:orig_category":"Venta, Montaje De Neum\u00c1ticos",
    "sg:phone":"+34 942 84 20 41",
    "sg:postcode":"39408",
    "sg:province":"Cantabria",
    "sg:website":"www.hoznayo.com",
    "wof:name":"Grupo Empresarial Hoznayo S.l.",
    "wof:placetype":"venue"
},
  "geometry": {"coordinates":[-4.0770049095,43.279712677],"type":"Point"}
}