{
  "type": "Feature",
  "properties": {
    "addr:full":"Calle de Ballesteros Villanueva, 18 Orihuela Alicante 03300",
    "addr:housenumber":"18",
    "addr:postcode":"03300",
    "addr:street":"Calle De Ballesteros Villanueva",
    "iso:country":"ES",
    "sg:address":"Calle de Ballesteros Villanueva, 18",
    "sg:city":"Orihuela",
    "sg:orig_category":"Papeler\u00cdas, Librer\u00cdas",
    "sg:phone":"+34 965 30 23 53",
    "sg:postcode":"03300",
    "sg:province":"Alicante",
    "wof:name":"Perez Aniorte S.a.",
    "wof:placetype":"venue"
},
  "geometry": {"coordinates":[-0.9436066747,38.0862503052],"type":"Point"}
}