{
  "type": "Feature",
  "properties": {
    "addr:full":"Carrer de Sant Jaume, 7 Sant Feliu Llobregat Barcelona 08980",
    "addr:housenumber":"7",
    "addr:postcode":"08980",
    "addr:street":"Carrer De Sant Jaume;Sant Feliu",
    "iso:country":"ES",
    "sg:address":"Carrer de Sant Jaume, 7",
    "sg:city":"Sant Feliu Llobregat",
    "sg:orig_category":"Montaje (empresas De)",
    "sg:phone":"+34 936 66 58 51",
    "sg:postcode":"08980",
    "sg:province":"Barcelona",
    "wof:name":"M Fuertes Inst. I Montatges Electrics S.a.",
    "wof:placetype":"venue"
},
  "geometry": {"coordinates":[2.0533699989,41.3813285828],"type":"Point"}
}