{
  "type": "Feature",
  "properties": {
    "iso:country":"ES",
    "sg:address":"Calle de Mayor, 15",
    "sg:city":"Aldea Del Rey Ni\u00e7o",
    "sg:orig_category":"F\u00c1bricas De Ladrillo Y Tejas",
    "sg:phone":"+34 920 22 99 05",
    "sg:postcode":"05197",
    "sg:province":"\u00c1vila",
    "wof:name":"Hernandez Garcia Apolonio",
    "wof:placetype":"venue"
},
  "geometry": {"coordinates":[-4.7444739342,40.585773468],"type":"Point"}
}