{
  "type": "Feature",
  "properties": {
    "addr:full":"Calle de Esteban Lopez, 42 Valencia Alcantara C\u00e1ceres 10500",
    "addr:housenumber":"42",
    "addr:postcode":"10500",
    "addr:street":"Calle De Esteban Lopez;Alcantara Ca\u0301Ceres",
    "iso:country":"ES",
    "sg:address":"Calle de Esteban Lopez, 42",
    "sg:city":"Valencia Alcantara",
    "sg:orig_category":"Aguas (distribuci\u00d3n, Servicios)",
    "sg:phone":"+34 927 58 24 11",
    "sg:postcode":"10500",
    "sg:province":"C\u00e1ceres",
    "wof:name":"Aquagest",
    "wof:placetype":"venue"
},
  "geometry": {"coordinates":[-7.2449603081,39.4117469788],"type":"Point"}
}