{
  "type": "Feature",
  "properties": {
    "addr:full":"Calle de Butroi, 16 Mungia Vizcaya 48100",
    "addr:housenumber":"16",
    "addr:postcode":"48100",
    "addr:street":"Calle De Butroi",
    "iso:country":"ES",
    "sg:address":"Calle de Butroi, 16",
    "sg:city":"Mungia",
    "sg:orig_category":"Ropa Para Caballeros (al Por Menor)",
    "sg:phone":"+34 946 74 43 27",
    "sg:postcode":"48100",
    "sg:province":"Vizcaya",
    "wof:name":"Garmendia Armendariz Juan Jose",
    "wof:placetype":"venue"
},
  "geometry": {"coordinates":[-2.848110199,43.3550796509],"type":"Point"}
}