{
  "type": "Feature",
  "properties": {
    "addr:full":"Plaz Escandinavia (de), 3 Fuenlabrada Madrid 28942",
    "addr:housenumber":"3",
    "addr:postcode":"28942",
    "addr:street":"Plaz Escandinavia De",
    "iso:country":"ES",
    "sg:address":"Plaz Escandinavia (de), 3",
    "sg:city":"Fuenlabrada",
    "sg:orig_category":"Tiendas De Grano, Frutas Y Legumbres Secas (al Por Menor)",
    "sg:phone":"+34 916 15 19 35",
    "sg:postcode":"28942",
    "sg:province":"Madrid",
    "wof:name":"Huan  Ying",
    "wof:placetype":"venue"
},
  "geometry": {"coordinates":[-3.8066682816,40.2911643982],"type":"Point"}
}