{
  "type": "Feature",
  "properties": {
    "iso:country":"ES",
    "sg:address":"Calle de Burgos, 7",
    "sg:city":"Vitoria-gasteiz",
    "sg:orig_category":"Carnicer\u00cdas, Carnicer\u00cdas",
    "sg:phone":"+34 945 28 83 64",
    "sg:postcode":"01002",
    "sg:province":"\u00c1lava",
    "wof:name":"Alejandro Sevilla Freixo (carniceria Goya)",
    "wof:placetype":"venue"
},
  "geometry": {"coordinates":[-2.6618685722,42.8561859131],"type":"Point"}
}