{
  "type": "Feature",
  "properties": {
    "addr:full":"Carrer de Enric Granados, 13 Amposta Tarragona 43870",
    "addr:housenumber":"13",
    "addr:postcode":"43870",
    "addr:street":"Carrer De Enric Granados",
    "iso:country":"ES",
    "sg:address":"Carrer de Enric Granados, 13",
    "sg:city":"Amposta",
    "sg:orig_category":"Promotores Constructores",
    "sg:phone":"+34 977 70 40 13",
    "sg:postcode":"43870",
    "sg:province":"Tarragona",
    "wof:name":"Construcciones Lopez Ferre S.a.",
    "wof:placetype":"venue"
},
  "geometry": {"coordinates":[0.5774279833,40.7078323364],"type":"Point"}
}