{
  "type": "Feature",
  "properties": {
    "addr:full":"Ctra Picanya, 4 Paiporta Valencia 46200",
    "addr:housenumber":"4",
    "addr:postcode":"46200",
    "addr:street":"Ctra Picanya",
    "iso:country":"ES",
    "sg:address":"Ctra Picanya, 4",
    "sg:city":"Paiporta",
    "sg:orig_category":"Armaduras De Hormig\u00d3n",
    "sg:phone":"+34 963 97 63 68",
    "sg:postcode":"46200",
    "sg:province":"Valencia",
    "wof:name":"Construcciones Z3 Comunidad De Bienes",
    "wof:placetype":"venue"
},
  "geometry": {"coordinates":[-0.4214749932,39.4292755127],"type":"Point"}
}