{
  "type": "Feature",
  "properties": {
    "addr:full":"Carr Pescadors, 23 Portocolom Islas Baleares 07670",
    "addr:housenumber":"23",
    "addr:postcode":"07670",
    "addr:street":"Carr Pescadors",
    "iso:country":"ES",
    "sg:address":"Carr Pescadors, 23",
    "sg:city":"Portocolom",
    "sg:orig_category":"Pr\u00c1ctica De Vela, Navegaci\u00d3n Y Deportes N\u00c1uticos Y Acu\u00c1ticos",
    "sg:phone":"+34 971 82 53 99",
    "sg:postcode":"07670",
    "sg:province":"Islas Baleares",
    "wof:name":"Club Nautico Porto Colom",
    "wof:placetype":"venue"
},
  "geometry": {"coordinates":[3.2610430717,39.4233665466],"type":"Point"}
}