{
  "type": "Feature",
  "properties": {
    "iso:country":"ES",
    "sg:address":"Soledad, S/n",
    "sg:city":"Torrejoncillo Rey",
    "sg:orig_category":"Fabricaci\u00d3n De Quesos",
    "sg:phone":"+34 969 27 80 05",
    "sg:postcode":"16161",
    "sg:province":"Cuenca",
    "wof:name":"Quesos Artesanos Medina S.l.",
    "wof:placetype":"venue"
},
  "geometry": {"coordinates":[-2.5715539455,40.0080909729],"type":"Point"}
}