{
  "type": "Feature",
  "properties": {
    "addr:full":"Calle de Ciudad De Mula, 19 Valencia Valencia 46021",
    "addr:housenumber":"19",
    "addr:postcode":"46021",
    "addr:street":"Calle De Ciudad De Mula",
    "iso:country":"ES",
    "sg:address":"Calle de Ciudad De Mula, 19",
    "sg:city":"Valencia",
    "sg:orig_category":"Ense\u00d1anza: Idiomas",
    "sg:phone":"+34 963 93 35 88",
    "sg:postcode":"46021",
    "sg:province":"Valencia",
    "wof:name":"Glenburn School S.l.",
    "wof:placetype":"venue"
},
  "geometry": {"coordinates":[-0.3532499969,39.4740447998],"type":"Point"}
}