{
  "type": "Feature",
  "properties": {
    "iso:country":"ES",
    "sg:address":"Plaz Nueva, 12",
    "sg:city":"Bilbao",
    "sg:orig_category":"Asociaciones Y Clubs Deportivos",
    "sg:phone":"+34 944 16 15 94",
    "sg:postcode":"48005",
    "sg:province":"Vizcaya",
    "wof:name":"Gestosalud S.l.",
    "wof:placetype":"venue"
},
  "geometry": {"coordinates":[-2.9222431183,43.2592353821],"type":"Point"}
}