{
  "type": "Feature",
  "properties": {
    "iso:country":"ES",
    "sg:address":"Calle de Altamirano, 38",
    "sg:city":"Madrid",
    "sg:orig_category":"Molduras, Junquillos, Listones Y Molduras Perforadas",
    "sg:phone":"+34 915 43 28 21",
    "sg:postcode":"28008",
    "sg:province":"Madrid",
    "wof:name":"Garcia Velasco Francisco",
    "wof:placetype":"venue"
},
  "geometry": {"coordinates":[-3.7202234268,40.4303512573],"type":"Point"}
}