{
  "type": "Feature",
  "properties": {
    "iso:country":"ES",
    "sg:address":"Plzl San Carlos, S/n",
    "sg:city":"Chiclana De La Frontera",
    "sg:orig_category":"Electrodom\u00c9sticos (al Por Menor)",
    "sg:phone":"+34 956 40 09 19",
    "sg:postcode":"11130",
    "sg:province":"C\u00e1diz",
    "wof:name":"Moreno Guerrero Manuel",
    "wof:placetype":"venue"
},
  "geometry": {"coordinates":[-6.1467571259,36.4268875122],"type":"Point"}
}