{
  "type": "Feature",
  "properties": {
    "addr:full":"Calle de Bilbao, 19 Mairena Aljarafe Sevilla 41927",
    "addr:housenumber":"19",
    "addr:postcode":"41927",
    "addr:street":"Calle De Bilbao",
    "iso:country":"ES",
    "sg:address":"Calle de Bilbao, 19",
    "sg:city":"Mairena Aljarafe",
    "sg:orig_category":"Promotores Constructores",
    "sg:phone":"+34 954 17 14 18",
    "sg:postcode":"41927",
    "sg:province":"Sevilla",
    "wof:name":"R.d.m. Obra Y Servicio Integral S.l.",
    "wof:placetype":"venue"
},
  "geometry": {"coordinates":[-6.0371446609,37.3539428711],"type":"Point"}
}