{
  "type": "Feature",
  "properties": {
    "addr:full":"Carrer de Alaba, 12 Barcelona Barcelona 08005",
    "addr:housenumber":"12",
    "addr:postcode":"08005",
    "addr:street":"Carrer De Alaba",
    "iso:country":"ES",
    "sg:address":"Carrer de Alaba, 12",
    "sg:city":"Barcelona",
    "sg:classifiers":[
        {
            "category":"Community Center",
            "subcategory":"Youth",
            "type":"Public Place"
        }
    ],
    "sg:phone":"+34 932 25 51 68",
    "sg:postcode":"08005",
    "sg:province":"Barcelona",
    "sg:tags":[
        "juventud",
        "administraci\u00d3n",
        "la",
        "en",
        "deporte",
        "el",
        "y"
    ],
    "wof:name":"Fundacion Privada Por Una Sonrisa En Africa",
    "wof:placetype":"venue"
},
  "geometry": {"coordinates":[2.1982610226,41.3934288025],"type":"Point"}
}