{
  "type": "Feature",
  "properties": {
    "iso:country":"ES",
    "sg:address":"Calle de Pozo, 20",
    "sg:city":"Fitero",
    "sg:orig_category":"Institutos De Belleza",
    "sg:phone":"+34 948 77 63 47",
    "sg:postcode":"31593",
    "sg:province":"Navarra",
    "wof:name":"Alonso Alonso Ramos",
    "wof:placetype":"venue"
},
  "geometry": {"coordinates":[-1.8586883545,42.0567321777],"type":"Point"}
}