{
  "type": "Feature",
  "properties": {
    "addr:full":"Carrer de La Rambla, 31 Barcelona Barcelona 08002",
    "addr:housenumber":"31",
    "addr:postcode":"08002",
    "addr:street":"Carrer De La Rambla",
    "iso:country":"ES",
    "sg:address":"Carrer de La Rambla, 31",
    "sg:city":"Barcelona",
    "sg:orig_category":"Bares, Piano",
    "sg:phone":"+34 933 01 75 07",
    "sg:postcode":"08002",
    "sg:province":"Barcelona",
    "wof:name":"Manos Latinas S.l.",
    "wof:placetype":"venue"
},
  "geometry": {"coordinates":[2.1751248837,41.3787231445],"type":"Point"}
}