{
  "type": "Feature",
  "properties": {
    "iso:country":"ES",
    "sg:address":"Asuncion, 24",
    "sg:city":"Espinardo",
    "sg:orig_category":"Sales (al Por Mayor)",
    "sg:phone":"+34 968 30 72 78",
    "sg:postcode":"30100",
    "sg:province":"Murcia",
    "wof:name":"Cano Guillen Jose Maria",
    "wof:placetype":"venue"
},
  "geometry": {"coordinates":[-1.1534969807,38.0114173889],"type":"Point"}
}