{
  "type": "Feature",
  "properties": {
    "addr:full":"Carrer de Joan Maura,bisbe, 37 Palma Islas Baleares 07005",
    "addr:housenumber":"37",
    "addr:postcode":"07005",
    "addr:street":"Carrer De Joan Maura Bisbe",
    "iso:country":"ES",
    "sg:address":"Carrer de Joan Maura,bisbe, 37",
    "sg:city":"Palma",
    "sg:orig_category":"Edici\u00d3n De Diarios, Revistas, Boletines",
    "sg:phone":"+34 971 77 02 78",
    "sg:postcode":"07005",
    "sg:province":"Islas Baleares",
    "wof:name":"Casals De Edicion Y Libreria S.a.",
    "wof:placetype":"venue"
},
  "geometry": {"coordinates":[2.6586890221,39.5770072937],"type":"Point"}
}