{
  "type": "Feature",
  "properties": {
    "addr:full":"Calle de Javier Barkaiztegi, 23 Donostia-san Sebastian Guip\u00f9zcoa 20010",
    "addr:housenumber":"23",
    "addr:postcode":"20010",
    "addr:street":"Calle De Javier Barkaiztegi",
    "iso:country":"ES",
    "sg:address":"Calle de Javier Barkaiztegi, 23",
    "sg:city":"Donostia-san Sebastian",
    "sg:orig_category":"Ingenier\u00cda, Centros De Estudios (industria)",
    "sg:phone":"+34 943 44 61 61",
    "sg:postcode":"20010",
    "sg:province":"Guip\u00f9zcoa",
    "wof:name":"Delizar S.l.",
    "wof:placetype":"venue"
},
  "geometry": {"coordinates":[-1.9822989702,43.305519104],"type":"Point"}
}