{
  "type": "Feature",
  "properties": {
    "addr:full":"Castell, 9 Rada Moraira Alicante 03724",
    "addr:postcode":"03724",
    "addr:street":"Rada",
    "iso:country":"ES",
    "sg:address":"Castell, 9",
    "sg:city":"Rada Moraira",
    "sg:orig_category":"Bisuter\u00cda, Joyer\u00cda, Relojer\u00cda (al Por Menor)",
    "sg:phone":"+34 965 74 48 89",
    "sg:postcode":"03724",
    "sg:province":"Alicante",
    "wof:name":"Joyeria Moraira S.l.",
    "wof:placetype":"venue"
},
  "geometry": {"coordinates":[0.1345169991,38.6870880127],"type":"Point"}
}