{
  "type": "Feature",
  "properties": {
    "iso:country":"ES",
    "sg:address":"Avda Rey Santo, 3",
    "sg:city":"Ciudad Real",
    "sg:orig_category":"Arquitectos",
    "sg:phone":"+34 926 22 51 44",
    "sg:postcode":"13001",
    "sg:province":"Ciudad Real",
    "wof:name":"Garcia Del Castillo Crespo Eusebio",
    "wof:placetype":"venue"
},
  "geometry": {"coordinates":[-3.9295289516,38.9824180603],"type":"Point"}
}