{
  "type": "Feature",
  "properties": {
    "addr:full":"Calle de Castilla, 1 Gines Sevilla 41960",
    "addr:housenumber":"1",
    "addr:postcode":"41960",
    "addr:street":"Calle De Castilla;Sevilla",
    "iso:country":"ES",
    "sg:address":"Calle de Castilla, 1",
    "sg:city":"Gines",
    "sg:orig_category":"Centros De Educaci\u00d3n Especial",
    "sg:phone":"+34 954 71 67 78",
    "sg:postcode":"41960",
    "sg:province":"Sevilla",
    "wof:name":"Araiva S.c.",
    "wof:placetype":"venue"
},
  "geometry": {"coordinates":[-6.0828561783,37.3912773132],"type":"Point"}
}