{
  "type": "Feature",
  "properties": {
    "iso:country":"ES",
    "sg:address":"Calle de Fernando Iii, 1",
    "sg:city":"Arjona",
    "sg:orig_category":"Asociaciones, Organismos Culturales Y Socioeducativos",
    "sg:phone":"+34 953 52 30 11",
    "sg:postcode":"23760",
    "sg:province":"Ja\u00e9n",
    "wof:name":"Circulo Mercantil",
    "wof:placetype":"venue"
},
  "geometry": {"coordinates":[-4.0562090874,37.9358482361],"type":"Point"}
}