{
  "type": "Feature",
  "properties": {
    "iso:country":"ES",
    "sg:address":"Rua San Nicolas (de), 7",
    "sg:city":"Pontevedra",
    "sg:orig_category":"Molduras, Junquillos, Listones Y Molduras Perforadas",
    "sg:phone":"+34 986 85 12 34",
    "sg:postcode":"36002",
    "sg:province":"Pontevedra",
    "wof:name":"Santiago Alvarez Guillermo Jesus",
    "wof:placetype":"venue"
},
  "geometry": {"coordinates":[-8.6450424194,42.4338340759],"type":"Point"}
}