{
  "type": "Feature",
  "properties": {
    "addr:full":"Carr Xavier Puig Andreu, 46 Lleida Lleida 25005",
    "addr:housenumber":"46",
    "addr:postcode":"25005",
    "addr:street":"Carr Xavier Puig Andreu",
    "iso:country":"ES",
    "sg:address":"Carr Xavier Puig Andreu, 46",
    "sg:city":"Lleida",
    "sg:orig_category":"Centros P\u00dablicos De Formaci\u00d3n Profesional Y T\u00c9cnica",
    "sg:phone":"+34 973 24 94 16",
    "sg:postcode":"25005",
    "sg:province":"Lleida",
    "wof:name":"Co%egi Oficial D'agents Comercials",
    "wof:placetype":"venue"
},
  "geometry": {"coordinates":[0.6408450007,41.6283493042],"type":"Point"}
}