{
  "type": "Feature",
  "properties": {
    "iso:country":"ES",
    "sg:address":"Calle de Pintor Manuel Baeza Gomez, 17",
    "sg:city":"Sant Joan D'alacant",
    "sg:orig_category":"Institutos De Belleza",
    "sg:phone":"+34 965 65 49 03",
    "sg:postcode":"03550",
    "sg:province":"Alicante",
    "sg:website":"www.abaco.ya.com/belladona2005",
    "wof:name":"La Bella Donna Salon De Estetica S.l.l.",
    "wof:placetype":"venue"
},
  "geometry": {"coordinates":[-0.4858489931,38.3598213196],"type":"Point"}
}