{
  "type": "Feature",
  "properties": {
    "iso:country":"ES",
    "sg:address":"Calle de Pegaso, 6",
    "sg:city":"Madrid",
    "sg:orig_category":"Abogados",
    "sg:phone":"+34 917 59 97 70",
    "sg:postcode":"28043",
    "sg:province":"Madrid",
    "wof:name":"Castro Casanova Isabel",
    "wof:placetype":"venue"
},
  "geometry": {"coordinates":[-3.6490399837,40.4634246826],"type":"Point"}
}