{
  "type": "Feature",
  "properties": {
    "addr:full":"Bda. Ituci, 2 Escacena Campo Huelva 21870",
    "addr:housenumber":"2",
    "addr:postcode":"21870",
    "addr:street":"Ituci",
    "iso:country":"ES",
    "sg:address":"Bda. Ituci, 2",
    "sg:city":"Escacena Campo",
    "sg:orig_category":"Plomeros",
    "sg:phone":"+34 959 42 32 60",
    "sg:postcode":"21870",
    "sg:province":"Huelva",
    "wof:name":"Romero Vargas Manuel",
    "wof:placetype":"venue"
},
  "geometry": {"coordinates":[-6.388449192,37.4082336426],"type":"Point"}
}