{
  "type": "Feature",
  "properties": {
    "addr:full":"Calle de Garita, 6 Tarazona Mancha Albacete 02100",
    "addr:housenumber":"6",
    "addr:postcode":"02100",
    "addr:street":"Calle De Garita",
    "iso:country":"ES",
    "sg:address":"Calle de Garita, 6",
    "sg:city":"Tarazona Mancha",
    "sg:orig_category":"Sociedades, Compa\u00d1\u00cdas Aseguradoras",
    "sg:phone":"+34 967 48 04 51",
    "sg:postcode":"02100",
    "sg:province":"Albacete",
    "wof:name":"Panadero Haro Gaspar",
    "wof:placetype":"venue"
},
  "geometry": {"coordinates":[-1.9131469727,39.2656822205],"type":"Point"}
}