{
  "type": "Feature",
  "properties": {
    "addr:full":"Carrer de Santiago Rusi\u00d1ol, 5 Palma Islas Baleares 07012",
    "addr:housenumber":"5",
    "addr:postcode":"07012",
    "addr:street":"Carrer De Santiago Rusin\u0303Ol",
    "iso:country":"ES",
    "sg:address":"Carrer de Santiago Rusi\u00d1ol, 5",
    "sg:city":"Palma",
    "sg:orig_category":"M\u00c9dicos: Oftalmolog\u00cda",
    "sg:phone":"+34 971 71 62 25",
    "sg:postcode":"07012",
    "sg:province":"Islas Baleares",
    "wof:name":"Quer Carot Santiago",
    "wof:placetype":"venue"
},
  "geometry": {"coordinates":[2.6475510597,39.5757751465],"type":"Point"}
}