{
  "type": "Feature",
  "properties": {
    "iso:country":"ES",
    "sg:address":"Pl Sant Iu, 5",
    "sg:city":"Barcelona",
    "sg:orig_category":"Caf\u00c9s, Bares, Cervecer\u00cdas",
    "sg:phone":"+34 933 10 30 14",
    "sg:postcode":"08002",
    "sg:province":"Barcelona",
    "wof:name":"Cafe D'estiu S.l.",
    "wof:placetype":"venue"
},
  "geometry": {"coordinates":[2.1769580841,41.3840637207],"type":"Point"}
}