{
  "type": "Feature",
  "properties": {
    "addr:full":"Calle de Luis Vives, 2 Alcala Henares Madrid 28803",
    "addr:housenumber":"2",
    "addr:postcode":"28803",
    "addr:street":"Calle De Luis Vives",
    "iso:country":"ES",
    "sg:address":"Calle de Luis Vives, 2",
    "sg:city":"Alcala Henares",
    "sg:orig_category":"Molduras, Junquillos, Listones Y Molduras Perforadas",
    "sg:phone":"+34 918 83 58 62",
    "sg:postcode":"28803",
    "sg:province":"Madrid",
    "wof:name":"Martin Martin Manuel",
    "wof:placetype":"venue"
},
  "geometry": {"coordinates":[-3.3688631058,40.4767913818],"type":"Point"}
}