{
  "type": "Feature",
  "properties": {
    "addr:full":"Calle de Letra H, 22 Puebla Alfinden Zaragoza 50171",
    "addr:housenumber":"22",
    "addr:postcode":"50171",
    "addr:street":"Calle De Letra H;Alfinden",
    "iso:country":"ES",
    "sg:address":"Calle de Letra H, 22",
    "sg:city":"Puebla Alfinden",
    "sg:orig_category":"Rectificaci\u00d3n, Mecanizado, Fresado",
    "sg:phone":"+34 976 45 54 91",
    "sg:postcode":"50171",
    "sg:province":"Zaragoza",
    "wof:name":"Tecnicas Silad S.l.",
    "wof:placetype":"venue"
},
  "geometry": {"coordinates":[-0.7601140141,41.6374893188],"type":"Point"}
}