{
  "type": "Feature",
  "properties": {
    "iso:country":"ES",
    "sg:address":"Carrer de Espigolera, 13",
    "sg:city":"S. Just Desvern",
    "sg:orig_category":"Gafas (fabricaci\u00d3n)",
    "sg:phone":"+34 934 70 05 35",
    "sg:postcode":"08960",
    "sg:province":"Barcelona",
    "wof:name":"Optimsa",
    "wof:placetype":"venue"
},
  "geometry": {"coordinates":[2.0615661144,41.384677887],"type":"Point"}
}