{
  "type": "Feature",
  "properties": {
    "iso:country":"ES",
    "sg:address":"Calle de San Francisco, 31",
    "sg:city":"Teruel",
    "sg:orig_category":"Arquitectos",
    "sg:phone":"+34 978 61 75 51",
    "sg:postcode":"44001",
    "sg:province":"Teruel",
    "wof:name":"Querol Blasco Jesus",
    "wof:placetype":"venue"
},
  "geometry": {"coordinates":[-1.1106179953,40.3432235718],"type":"Point"}
}