{
  "type": "Feature",
  "properties": {
    "addr:full":"Pase Ramon Gaya, 2 Santa Maria De Gracia Murcia 30009",
    "addr:housenumber":"2",
    "addr:postcode":"30009",
    "addr:street":"Gaya",
    "iso:country":"ES",
    "sg:address":"Pase Ramon Gaya, 2",
    "sg:city":"Santa Maria De Gracia",
    "sg:orig_category":"Centros De Educaci\u00d3n Especial",
    "sg:phone":"+34 968 20 18 61",
    "sg:postcode":"30009",
    "sg:province":"Murcia",
    "wof:name":"Colegio Publico Santa Maria De Gracia",
    "wof:placetype":"venue"
},
  "geometry": {"coordinates":[-1.1528439522,37.9883460999],"type":"Point"}
}