{
  "type": "Feature",
  "properties": {
    "iso:country":"ES",
    "sg:address":"Plaz Mayor, S/n",
    "sg:city":"Anaya",
    "sg:orig_category":"Electricidad: Instaladores",
    "sg:phone":"+34 921 49 00 72",
    "sg:postcode":"40121",
    "sg:province":"Segovia",
    "wof:name":"Monjas Hernandez Mariano",
    "wof:placetype":"venue"
},
  "geometry": {"coordinates":[-4.3090391159,40.9914054871],"type":"Point"}
}