{
  "type": "Feature",
  "properties": {
    "iso:country":"ES",
    "sg:address":"Avda Gipuzkoa, 38",
    "sg:city":"Ermua",
    "sg:orig_category":"Peluquer\u00cdas, Peluquer\u00cda Mixta",
    "sg:phone":"+34 943 03 10 05",
    "sg:postcode":"48260",
    "sg:province":"Vizcaya",
    "wof:name":"Nieves Gonzalez Ibarzabal",
    "wof:placetype":"venue"
},
  "geometry": {"coordinates":[-2.4990820885,43.1814956665],"type":"Point"}
}