{
  "type": "Feature",
  "properties": {
    "iso:country":"ES",
    "sg:address":"Polig. Ind. O Morelle, 4",
    "sg:city":"San Xulian Veiga",
    "sg:orig_category":"M\u00c1rmoles, Granitos Y Piedras Naturales",
    "sg:phone":"+34 982 53 24 47",
    "sg:postcode":"27614",
    "sg:province":"Lugo",
    "wof:name":"Marcol Sarria S.l.",
    "wof:placetype":"venue"
},
  "geometry": {"coordinates":[-7.3574109077,42.8505249023],"type":"Point"}
}