{
  "type": "Feature",
  "properties": {
    "iso:country":"ES",
    "sg:address":"Calle de Cortes (las), 3",
    "sg:city":"Zaragoza",
    "sg:orig_category":"Florister\u00cdas",
    "sg:phone":"+34 976 28 38 81",
    "sg:postcode":"50003",
    "sg:province":"Zaragoza",
    "wof:name":"Gimeno Lopez Antonia Felicidad",
    "wof:placetype":"venue"
},
  "geometry": {"coordinates":[-0.8962391019,41.6612167358],"type":"Point"}
}