{
  "type": "Feature",
  "properties": {
    "iso:country":"ES",
    "sg:address":"Calle de Floridablanca, 28",
    "sg:city":"San Lorenzo De El Escorial",
    "sg:orig_category":"Notarios",
    "sg:phone":"+34 918 90 45 94",
    "sg:postcode":"28200",
    "sg:province":"Madrid",
    "wof:name":"Barril Roche Sebastian",
    "wof:placetype":"venue"
},
  "geometry": {"coordinates":[-4.1488718987,40.5911827087],"type":"Point"}
}