{
  "type": "Feature",
  "properties": {
    "addr:full":"Alameda Pinos, 1 Churra Murcia 30110",
    "addr:housenumber":"1",
    "addr:postcode":"30110",
    "addr:street":"Pinos",
    "iso:country":"ES",
    "sg:address":"Alameda Pinos, 1",
    "sg:city":"Churra",
    "sg:orig_category":"Chapister\u00cda",
    "sg:phone":"+34 968 83 33 83",
    "sg:postcode":"30110",
    "sg:province":"Murcia",
    "wof:name":"Moreno Gonzalez Cristobal",
    "wof:placetype":"venue"
},
  "geometry": {"coordinates":[-1.1421060562,38.0145111084],"type":"Point"}
}