{
  "type": "Feature",
  "properties": {
    "addr:full":"Pase Ayuntamiento, 5 Guardo Palencia 34880",
    "addr:housenumber":"5",
    "addr:postcode":"34880",
    "addr:street":"Ayuntamiento",
    "iso:country":"ES",
    "sg:address":"Pase Ayuntamiento, 5",
    "sg:city":"Guardo",
    "sg:orig_category":"Bancos",
    "sg:phone":"+34 979 85 12 36",
    "sg:postcode":"34880",
    "sg:province":"Palencia",
    "wof:name":"Banco Popular Espa\u00f1ol",
    "wof:placetype":"venue"
},
  "geometry": {"coordinates":[-4.8446931839,42.7881507874],"type":"Point"}
}