{
  "type": "Feature",
  "properties": {
    "addr:full":"Rond Alfons X El Savi (d'), 93 Mataro Barcelona 08304",
    "addr:postcode":"08304",
    "iso:country":"ES",
    "sg:address":"Rond Alfons X El Savi (d'), 93",
    "sg:city":"Mataro",
    "sg:orig_category":"Inmobiliaria (agencias)",
    "sg:phone":"+34 937 55 40 44",
    "sg:postcode":"08304",
    "sg:province":"Barcelona",
    "wof:name":"Finques Biada S.l.",
    "wof:placetype":"venue"
},
  "geometry": {"coordinates":[2.4470169544,41.5458374023],"type":"Point"}
}