{
  "type": "Feature",
  "properties": {
    "iso:country":"ES",
    "sg:address":"Calle de Raimundo Fernandez Villaverde, 61",
    "sg:city":"Madrid",
    "sg:orig_category":"Asesor\u00cda Sobre Comunicaci\u00d3n De Empresas",
    "sg:phone":"+34 915 35 10 83",
    "sg:postcode":"28003",
    "sg:province":"Madrid",
    "wof:name":"Sca Asesores S.a.",
    "wof:placetype":"venue"
},
  "geometry": {"coordinates":[-3.6948990822,40.4463882446],"type":"Point"}
}