{
  "type": "Feature",
  "properties": {
    "addr:full":"Bloc Riu Cinca, 10 Verge Del Pilar Tarragona 43006",
    "addr:housenumber":"10",
    "addr:postcode":"43006",
    "addr:street":"Verge Del Pilar",
    "iso:country":"ES",
    "sg:address":"Bloc Riu Cinca, 10",
    "sg:city":"Verge Del Pilar",
    "sg:orig_category":"Promotores Constructores",
    "sg:phone":"+34 977 54 42 05",
    "sg:postcode":"43006",
    "sg:province":"Tarragona",
    "sg:website":"www.sercontrata.com",
    "wof:name":"Sercontrata S.l.",
    "wof:placetype":"venue"
},
  "geometry": {"coordinates":[1.2209249735,41.1154441833],"type":"Point"}
}