{
  "type": "Feature",
  "properties": {
    "addr:full":"Prag Aglets, S/n Queixans Girona 17538",
    "addr:housenumber":"s",
    "addr:postcode":"17538",
    "addr:street":"/ N Queixans",
    "iso:country":"ES",
    "sg:address":"Prag Aglets, S/n",
    "sg:city":"Queixans",
    "sg:orig_category":"Hormigonados",
    "sg:phone":"+34 972 88 47 00",
    "sg:postcode":"17538",
    "sg:province":"Girona",
    "wof:name":"Promotora Mediterranea 2 S.a.",
    "wof:placetype":"venue"
},
  "geometry": {"coordinates":[1.8867280483,42.3738555908],"type":"Point"}
}