{
  "type": "Feature",
  "properties": {
    "addr:full":"Avda Fonseca, S/n Peligros Granada 18210",
    "addr:housenumber":"s / n",
    "addr:postcode":"18210",
    "addr:street":"Avda Fonseca",
    "iso:country":"ES",
    "sg:address":"Avda Fonseca, S/n",
    "sg:city":"Peligros",
    "sg:orig_category":"Asilos De Ancianos. Centros Privados",
    "sg:phone":"+34 958 40 01 47",
    "sg:postcode":"18210",
    "sg:province":"Granada",
    "wof:name":"Asociacion Benefica Misioneros De Los Enfermos",
    "wof:placetype":"venue"
},
  "geometry": {"coordinates":[-3.6398613453,37.234336853],"type":"Point"}
}