{
  "type": "Feature",
  "properties": {
    "addr:full":"Calle de Juan Garcia Hortelano, 37 Valladolid Valladolid 47014",
    "addr:housenumber":"37",
    "addr:postcode":"47014",
    "addr:street":"Calle De Juan;Hortelano",
    "iso:country":"ES",
    "sg:address":"Calle de Juan Garcia Hortelano, 37",
    "sg:city":"Valladolid",
    "sg:orig_category":"Reposter\u00cdas",
    "sg:phone":"+34 983 36 18 92",
    "sg:postcode":"47014",
    "sg:province":"Valladolid",
    "wof:name":"Tahona La Otana S.l.",
    "wof:placetype":"venue"
},
  "geometry": {"coordinates":[-4.7650651932,41.6370162964],"type":"Point"}
}