{
  "type": "Feature",
  "properties": {
    "iso:country":"ES",
    "sg:address":"Carr El Bages, 12",
    "sg:city":"Lleida",
    "sg:orig_category":"Artes Gr\u00c1ficas, Artes Pl\u00c1sticas (curso)",
    "sg:phone":"+34 973 23 35 50",
    "sg:postcode":"25005",
    "sg:province":"Lleida",
    "wof:name":"Graf Lleida S.l.",
    "wof:placetype":"venue"
},
  "geometry": {"coordinates":[0.627129972,41.6145210266],"type":"Point"}
}