{
  "type": "Feature",
  "properties": {
    "iso:country":"ES",
    "sg:address":"Calle de Refugio, 36",
    "sg:city":"Ciudad Real",
    "sg:orig_category":"Lavado, Limpieza De Veh\u00cdculos",
    "sg:phone":"+34 926 22 72 15",
    "sg:postcode":"13004",
    "sg:province":"Ciudad Real",
    "wof:name":"Lopez-hermoso Gonzalez Del Campo Ramon De La Cruz",
    "wof:placetype":"venue"
},
  "geometry": {"coordinates":[-3.9251968861,38.9888114929],"type":"Point"}
}