{
  "type": "Feature",
  "properties": {
    "iso:country":"ES",
    "sg:address":"Calle de San Agustin, 8",
    "sg:city":"Hinojosa Del Duque",
    "sg:orig_category":"Promotores Constructores",
    "sg:phone":"+34 957 14 21 76",
    "sg:postcode":"14270",
    "sg:province":"C\u00f3rdoba",
    "wof:name":"Leal Santo Pedro",
    "wof:placetype":"venue"
},
  "geometry": {"coordinates":[-5.1484827995,38.4999198914],"type":"Point"}
}