{
  "type": "Feature",
  "properties": {
    "addr:full":"Calle de Velazquez, 48 Madrid Madrid 28001",
    "addr:housenumber":"48",
    "addr:postcode":"madrid;28001",
    "addr:street":"Calle De Velazquez",
    "iso:country":"ES",
    "sg:address":"Calle de Velazquez, 48",
    "sg:city":"Madrid",
    "sg:orig_category":"Inform\u00c1tica, Ofim\u00c1tica (estudios, Asesor\u00cda, Ingenier\u00cda, Formaci\u00d3n)",
    "sg:phone":"+34 915 21 46 06",
    "sg:postcode":"28001",
    "sg:province":"Madrid",
    "sg:website":"www.ife.es",
    "wof:name":"Instituto De Fomento Empresarial S.a.",
    "wof:placetype":"venue"
},
  "geometry": {"coordinates":[-3.6838059425,40.4268569946],"type":"Point"}
}