{
  "type": "Feature",
  "properties": {
    "iso:country":"ES",
    "sg:address":"Calle de Horno, 9",
    "sg:city":"Villamayor",
    "sg:orig_category":"Molduras, Junquillos, Listones Y Molduras Perforadas",
    "sg:phone":"+34 923 28 68 01",
    "sg:postcode":"37185",
    "sg:province":"Salamanca",
    "wof:name":"Servicio De Restauracion Y Hostelerias S.l.",
    "wof:placetype":"venue"
},
  "geometry": {"coordinates":[-5.6959590912,40.9995422363],"type":"Point"}
}