{
  "type": "Feature",
  "properties": {
    "addr:full":"Calle de Jose Arcones Gil, 8 Madrid Madrid 28017",
    "addr:housenumber":"8",
    "addr:postcode":"madrid;28017",
    "addr:street":"Calle De Jose Arcones Gil",
    "iso:country":"ES",
    "sg:address":"Calle de Jose Arcones Gil, 8",
    "sg:city":"Madrid",
    "sg:orig_category":"Peluquer\u00cdas, Peluquer\u00cda Mixta",
    "sg:phone":"+34 913 67 26 79",
    "sg:postcode":"28017",
    "sg:province":"Madrid",
    "wof:name":"Uzor  Kenny",
    "wof:placetype":"venue"
},
  "geometry": {"coordinates":[-3.6394319534,40.436794281],"type":"Point"}
}