{
  "type": "Feature",
  "properties": {
    "addr:full":"Ctra Villavieja, S/n Nules Castell\u00f3n 12520",
    "addr:housenumber":"s / n",
    "addr:postcode":"12520",
    "addr:street":"Ctra Villavieja",
    "iso:country":"ES",
    "sg:address":"Ctra Villavieja, S/n",
    "sg:city":"Nules",
    "sg:orig_category":"Empresas De Carpinter\u00cda De Madera",
    "sg:phone":"+34 964 67 01 22",
    "sg:postcode":"12520",
    "sg:province":"Castell\u00f3n",
    "wof:name":"Arroyo Carratala Jose",
    "wof:placetype":"venue"
},
  "geometry": {"coordinates":[-0.163667202,39.8544960022],"type":"Point"}
}