{
  "type": "Feature",
  "properties": {
    "iso:country":"ES",
    "sg:address":"La Pesquera, S/n",
    "sg:city":"Laredo",
    "sg:orig_category":"M\u00c1rmoles, Granitos Y Piedras Naturales",
    "sg:phone":"+34 942 61 16 62",
    "sg:postcode":"39770",
    "sg:province":"Cantabria",
    "wof:name":"Cantero Mendez Alfonso",
    "wof:placetype":"venue"
},
  "geometry": {"coordinates":[-3.4341549873,43.4056358337],"type":"Point"}
}