{
  "type": "Feature",
  "properties": {
    "addr:full":"Av Espanya, 6 Cerdanyola Valles Barcelona 08290",
    "addr:housenumber":"6",
    "addr:postcode":"08290",
    "addr:street":"Av Espanya;Valles Barcelona",
    "iso:country":"ES",
    "sg:address":"Av Espanya, 6",
    "sg:city":"Cerdanyola Valles",
    "sg:orig_category":"Estudios, Instalaci\u00d3n De Climatizaci\u00d3n",
    "sg:phone":"+34 935 80 90 72",
    "sg:postcode":"08290",
    "sg:province":"Barcelona",
    "wof:name":"Ubeda Ramos Joaquin",
    "wof:placetype":"venue"
},
  "geometry": {"coordinates":[2.1319980621,41.4953155518],"type":"Point"}
}