{
  "type": "Feature",
  "properties": {
    "addr:full":"Calle de Huerta De Rita, 2 Coria Rio Sevilla 41100",
    "addr:housenumber":"2",
    "addr:postcode":"41100",
    "addr:street":"Calle De Huerta De Rita;Rio Sevilla",
    "iso:country":"ES",
    "sg:address":"Calle de Huerta De Rita, 2",
    "sg:city":"Coria Rio",
    "sg:orig_category":"Armas Y Municiones (fabricaci\u00d3n, Al Por Mayor)",
    "sg:phone":"+34 954 77 65 74",
    "sg:postcode":"41100",
    "sg:province":"Sevilla",
    "wof:name":"Garcia Los-santos Gabriel",
    "wof:placetype":"venue"
},
  "geometry": {"coordinates":[-6.0558037758,37.2839660645],"type":"Point"}
}