{
  "type": "Feature",
  "properties": {
    "addr:full":"Calle de Julio Antonio, 16 Madrid Madrid 28025",
    "addr:housenumber":"16",
    "addr:postcode":"madrid;28025",
    "addr:street":"Calle De Julio Antonio",
    "iso:country":"ES",
    "sg:address":"Calle de Julio Antonio, 16",
    "sg:city":"Madrid",
    "sg:orig_category":"Panader\u00cdas, Panader\u00cdas",
    "sg:phone":"+34 914 61 24 96",
    "sg:postcode":"28025",
    "sg:province":"Madrid",
    "wof:name":"Pasteleria Delisa S.l.",
    "wof:placetype":"venue"
},
  "geometry": {"coordinates":[-3.7313070297,40.3831787109],"type":"Point"}
}