{
  "type": "Feature",
  "properties": {
    "addr:full":"Calle de Tejares, 11 Malaga M\u00e1laga 29011",
    "addr:housenumber":"11",
    "addr:postcode":"29011",
    "addr:street":"Calle De Tejares;Ma\u0301Laga",
    "iso:country":"ES",
    "sg:address":"Calle de Tejares, 11",
    "sg:city":"Malaga",
    "sg:orig_category":"Empresas De Carpinter\u00cda De Madera",
    "sg:phone":"+34 952 61 34 97",
    "sg:postcode":"29011",
    "sg:province":"M\u00e1laga",
    "wof:name":"Frutos Madrid Jose Luis",
    "wof:placetype":"venue"
},
  "geometry": {"coordinates":[-4.4358649254,36.7283096313],"type":"Point"}
}