{
  "type": "Feature",
  "properties": {
    "addr:full":"Calle de Virgen De La Paloma (de La), 16 Rio Guadarrama Madrid 28935",
    "addr:housenumber":"16",
    "addr:postcode":"28935",
    "addr:street":"Calle De Virgen De La Paloma De La;Guadarrama",
    "iso:country":"ES",
    "sg:address":"Calle de Virgen De La Paloma (de La), 16",
    "sg:city":"Rio Guadarrama",
    "sg:orig_category":"Comit\u00c9s De Organizaci\u00d3n De Exposiciones, Ferias, Salones",
    "sg:phone":"+34 914 96 92 77",
    "sg:postcode":"28935",
    "sg:province":"Madrid",
    "wof:name":"P.a.p.congresos S.l.",
    "wof:placetype":"venue"
},
  "geometry": {"coordinates":[-3.9419794083,40.3126411438],"type":"Point"}
}