{
  "type": "Feature",
  "properties": {
    "iso:country":"ES",
    "sg:address":"Calle de Campos Eliseos, 16",
    "sg:city":"Malaga",
    "sg:orig_category":"Inmobiliaria (agencias)",
    "sg:phone":"+34 952 21 29 30",
    "sg:postcode":"29016",
    "sg:province":"M\u00e1laga",
    "wof:name":"Pajari\u00f1o Gallego Ricardo Manuel",
    "wof:placetype":"venue"
},
  "geometry": {"coordinates":[-4.4118485451,36.7215270996],"type":"Point"}
}