{
  "type": "Feature",
  "properties": {
    "iso:country":"ES",
    "sg:address":"Carr Sor Francisca Nicolau Bover, 1",
    "sg:city":"Binissalem",
    "sg:orig_category":"Panader\u00cdas, Panader\u00cdas",
    "sg:phone":"+34 971 51 12 18",
    "sg:postcode":"07350",
    "sg:province":"Islas Baleares",
    "wof:name":"Galmes Caimari Francisco",
    "wof:placetype":"venue"
},
  "geometry": {"coordinates":[2.8405179977,39.6896362305],"type":"Point"}
}