{
  "type": "Feature",
  "properties": {
    "iso:country":"ES",
    "sg:address":"Calle de San Bartolome, S/n",
    "sg:city":"Gorriti",
    "sg:orig_category":"Delegados, Agentes De Tr\u00c1nsito, Auxiliares De Transporte Internacional",
    "sg:phone":"+34 948 50 42 51",
    "sg:postcode":"31877",
    "sg:province":"Navarra",
    "wof:name":"Legarra Astiz Micaela",
    "wof:placetype":"venue"
},
  "geometry": {"coordinates":[-1.917503953,43.0394744873],"type":"Point"}
}