{
  "type": "Feature",
  "properties": {
    "iso:country":"ES",
    "sg:address":"Calle de Xavier Cabello Lapiedra, 21",
    "sg:city":"San Lorenzo De El Escorial",
    "sg:orig_category":"Arquitectos",
    "sg:phone":"+34 918 96 20 80",
    "sg:postcode":"28200",
    "sg:province":"Madrid",
    "wof:name":"Garcia Fernandez Marina",
    "wof:placetype":"venue"
},
  "geometry": {"coordinates":[-4.1513700485,40.59217453],"type":"Point"}
}