{
  "type": "Feature",
  "properties": {
    "iso:country":"ES",
    "sg:address":"Cr Cuenca-tragac., S/n",
    "sg:city":"Villalba Sierra",
    "sg:orig_category":"Hoteles",
    "sg:phone":"+34 969 28 14 88",
    "sg:postcode":"16140",
    "sg:province":"Cuenca",
    "wof:name":"Tresa S.l.",
    "wof:placetype":"venue"
},
  "geometry": {"coordinates":[-2.0890989304,40.2361755371],"type":"Point"}
}