{
  "type": "Feature",
  "properties": {
    "addr:full":"Avda San Jose, 53 Zaragoza Zaragoza 50013",
    "addr:housenumber":"53",
    "addr:postcode":"50013",
    "addr:street":"Avda San Jose",
    "iso:country":"ES",
    "sg:address":"Avda San Jose, 53",
    "sg:city":"Zaragoza",
    "sg:orig_category":"Caf\u00c9s, Bares, Cervecer\u00cdas",
    "sg:phone":"+34 976 41 64 82",
    "sg:postcode":"50013",
    "sg:province":"Zaragoza",
    "wof:name":"Jose 53 S.c.",
    "wof:placetype":"venue"
},
  "geometry": {"coordinates":[-0.8730689883,41.6425514221],"type":"Point"}
}