{
  "type": "Feature",
  "properties": {
    "iso:country":"ES",
    "sg:address":"Carr Alqueria Del Comte, 71",
    "sg:city":"Soller",
    "sg:orig_category":"Caf\u00c9s, Bares, Cervecer\u00cdas",
    "sg:phone":"+34 971 63 41 46",
    "sg:postcode":"07100",
    "sg:province":"Islas Baleares",
    "wof:name":"Vidal Colom Martina",
    "wof:placetype":"venue"
},
  "geometry": {"coordinates":[2.7230470181,39.768699646],"type":"Point"}
}