{
  "type": "Feature",
  "properties": {
    "iso:country":"ES",
    "sg:address":"Carrer de Llevant, 16",
    "sg:city":"Roses",
    "sg:orig_category":"Institutos De Belleza",
    "sg:phone":"+34 972 25 70 89",
    "sg:postcode":"17480",
    "sg:province":"Girona",
    "wof:name":"Viella Su\u00f1e Maria",
    "wof:placetype":"venue"
},
  "geometry": {"coordinates":[3.1814639568,42.2588424683],"type":"Point"}
}