{
  "type": "Feature",
  "properties": {
    "addr:full":"Calle de Dalia (de La), 51 Alcobendas Madrid 28109",
    "addr:housenumber":"51",
    "addr:postcode":"28109",
    "addr:street":"Calle De Dalia De La",
    "iso:country":"ES",
    "sg:address":"Calle de Dalia (de La), 51",
    "sg:city":"Alcobendas",
    "sg:orig_category":"Ingenier\u00cda, Centros De Estudios (diversos)",
    "sg:phone":"+34 916 50 71 55",
    "sg:postcode":"28109",
    "sg:province":"Madrid",
    "wof:name":"Uop Processes International Inc S.a.",
    "wof:placetype":"venue"
},
  "geometry": {"coordinates":[-3.6447579861,40.52003479],"type":"Point"}
}