{
  "type": "Feature",
  "properties": {
    "addr:full":"Poli Ciudad Del Transporte, 17 San Juan De Mozarrifar Zaragoza 50820",
    "addr:housenumber":"17",
    "addr:postcode":"50820",
    "addr:street":"Transporte;Juan;Mozarrifar",
    "iso:country":"ES",
    "sg:address":"Poli Ciudad Del Transporte, 17",
    "sg:city":"San Juan De Mozarrifar",
    "sg:orig_category":"Contenedores (mercanc\u00cdas)",
    "sg:phone":"+34 976 15 04 85",
    "sg:postcode":"50820",
    "sg:province":"Zaragoza",
    "wof:name":"Transportes Jose Manuel Gascon",
    "wof:placetype":"venue"
},
  "geometry": {"coordinates":[-0.8416489959,41.7171096802],"type":"Point"}
}