{
  "type": "Feature",
  "properties": {
    "iso:country":"ES",
    "sg:address":"Carrer de Mossen Xiro, 3",
    "sg:city":"Barcelona",
    "sg:orig_category":"Empresas De Portes Y Mensajer\u00cda",
    "sg:phone":"+34 932 37 53 84",
    "sg:postcode":"08006",
    "sg:province":"Barcelona",
    "wof:name":"Sprint, Serveis De Missatgeria Integral, S.l.",
    "wof:placetype":"venue"
},
  "geometry": {"coordinates":[2.1490769386,41.404094696],"type":"Point"}
}