{
  "type": "Feature",
  "properties": {
    "iso:country":"ES",
    "sg:address":"Calle de Doctor Espina, 43",
    "sg:city":"Madrid",
    "sg:orig_category":"Cristaler\u00cdas",
    "sg:phone":"+34 914 72 94 17",
    "sg:postcode":"28019",
    "sg:province":"Madrid",
    "wof:name":"Industrias Oporto S.l.",
    "wof:placetype":"venue"
},
  "geometry": {"coordinates":[-3.7293667793,40.3870315552],"type":"Point"}
}