{
  "type": "Feature",
  "properties": {
    "iso:country":"ES",
    "sg:address":"El Caleton, 1",
    "sg:city":"Bre\u00f1a Baja",
    "sg:orig_category":"Lavado, Limpieza De Veh\u00cdculos",
    "sg:phone":"+34 922 43 44 22",
    "sg:postcode":"38712",
    "sg:province":"Santa Cruz De Tenerife",
    "wof:name":"Diaz Rodriguez Antonio",
    "wof:placetype":"venue"
},
  "geometry": {"coordinates":[-17.7676124573,28.6526985168],"type":"Point"}
}