{
  "type": "Feature",
  "properties": {
    "iso:country":"ES",
    "sg:address":"Calle de Ramon Y Cajal, 2",
    "sg:city":"Tiemblo",
    "sg:orig_category":"Inmobiliaria (agencias)",
    "sg:phone":"+34 918 62 72 84",
    "sg:postcode":"05270",
    "sg:province":"\u00c1vila",
    "wof:name":"Gapadisa Promociones Inmobiliaria Sl",
    "wof:placetype":"venue"
},
  "geometry": {"coordinates":[-4.5035238266,40.413192749],"type":"Point"}
}