{
  "type": "Feature",
  "properties": {
    "iso:country":"ES",
    "sg:address":"Calle de Cordoba, 410",
    "sg:city":"Calypo Fado",
    "sg:orig_category":"Carnicer\u00cdas, Carnicer\u00cdas",
    "sg:phone":"+34 918 13 92 82",
    "sg:postcode":"45950",
    "sg:province":"Toledo",
    "wof:name":"Herrera Salinero Francisco Javier",
    "wof:placetype":"venue"
},
  "geometry": {"coordinates":[-4.0629873276,40.2431182861],"type":"Point"}
}