{
  "type": "Feature",
  "properties": {
    "iso:country":"ES",
    "sg:address":"Rua Rubalcava, 9",
    "sg:city":"Ferrol",
    "sg:orig_category":"Estilistas Y Estudios De Estilo De Corte Y Confecci\u00d3n",
    "sg:phone":"+34 981 30 03 65",
    "sg:postcode":"15402",
    "sg:province":"La Coru\u00f1a",
    "wof:name":"Gutierrez Martin Elias",
    "wof:placetype":"venue"
},
  "geometry": {"coordinates":[-8.2320404053,43.4840888977],"type":"Point"}
}