{
  "type": "Feature",
  "properties": {
    "addr:full":"Av Salou, 372 Reus Tarragona 43205",
    "addr:housenumber":"372",
    "addr:postcode":"43205",
    "addr:street":"Av Salou",
    "iso:country":"ES",
    "sg:address":"Av Salou, 372",
    "sg:city":"Reus",
    "sg:orig_category":"Tractores Agr\u00cdcolas Y Remolques",
    "sg:phone":"+34 977 75 47 85",
    "sg:postcode":"43205",
    "sg:province":"Tarragona",
    "wof:name":"Mestre Simo Juan",
    "wof:placetype":"venue"
},
  "geometry": {"coordinates":[1.1212029457,41.1350479126],"type":"Point"}
}