{
  "type": "Feature",
  "properties": {
    "iso:country":"ES",
    "sg:address":"Carr Cami Des Castell, 48",
    "sg:city":"Mao",
    "sg:orig_category":"Confecci\u00d3n De Trajes Para Se\u00d1oras",
    "sg:phone":"+34 971 36 39 92",
    "sg:postcode":"07702",
    "sg:province":"Islas Baleares",
    "wof:name":"Fortuny Previ Alberto",
    "wof:placetype":"venue"
},
  "geometry": {"coordinates":[4.2674150467,39.8872566223],"type":"Point"}
}