{
  "type": "Feature",
  "properties": {
    "iso:country":"ES",
    "sg:address":"Avda Europa, 17",
    "sg:city":"Almu\u00f1ecar",
    "sg:orig_category":"Gastronom\u00cda: Especialidades Regionales Y Extranjeras (producci\u00d3n, Al Por Mayor)",
    "sg:phone":"+34 958 63 05 87",
    "sg:postcode":"18690",
    "sg:province":"Granada",
    "sg:website":"www.labodegadeljamon.com",
    "wof:name":"Artesadecor C.b.",
    "wof:placetype":"venue"
},
  "geometry": {"coordinates":[-3.6955800056,36.7303504944],"type":"Point"}
}