{
  "type": "Feature",
  "properties": {
    "addr:full":"Avda Madrid, 48 Zaragoza Zaragoza 50010",
    "addr:housenumber":"48",
    "addr:postcode":"50010",
    "addr:street":"Avda Madrid",
    "iso:country":"ES",
    "sg:address":"Avda Madrid, 48",
    "sg:city":"Zaragoza",
    "sg:orig_category":"Empresas De Limpieza",
    "sg:phone":"+34 976 31 57 93",
    "sg:postcode":"50010",
    "sg:province":"Zaragoza",
    "wof:name":"Teleasa 2000 S.l.",
    "wof:placetype":"venue"
},
  "geometry": {"coordinates":[-0.902895987,41.6539573669],"type":"Point"}
}