{
  "type": "Feature",
  "properties": {
    "iso:country":"ES",
    "sg:address":"Calle de Baleares, 5",
    "sg:city":"Torres Cotillas",
    "sg:orig_category":"Institutos De Belleza",
    "sg:phone":"+34 968 62 76 45",
    "sg:postcode":"30565",
    "sg:province":"Murcia",
    "wof:name":"Pe\u00f1alver Sandoval Ana Maria",
    "wof:placetype":"venue"
},
  "geometry": {"coordinates":[-1.239613533,38.0210914612],"type":"Point"}
}