{
  "type": "Feature",
  "properties": {
    "addr:full":"Canton, 13 Espasante La Coru\u00f1a 15339",
    "addr:housenumber":"13",
    "addr:postcode":"15339",
    "addr:street":"Canton;La Corun\u0303A",
    "iso:country":"ES",
    "sg:address":"Canton, 13",
    "sg:city":"Espasante",
    "sg:orig_category":"Navegaci\u00d3n (equipos Fluviales)",
    "sg:phone":"+34 981 40 80 20",
    "sg:postcode":"15339",
    "sg:province":"La Coru\u00f1a",
    "wof:name":"Lage Pumar Faustino",
    "wof:placetype":"venue"
},
  "geometry": {"coordinates":[-8.0569753647,43.6683120728],"type":"Point"}
}