{
  "type": "Feature",
  "properties": {
    "addr:full":"Carrer de Casp, 174 Barcelona Barcelona 08013",
    "addr:housenumber":"174",
    "addr:postcode":"08013",
    "addr:street":"Carrer De Casp",
    "iso:country":"ES",
    "sg:address":"Carrer de Casp, 174",
    "sg:city":"Barcelona",
    "sg:orig_category":"Florister\u00cdas",
    "sg:phone":"+34 932 45 69 56",
    "sg:postcode":"08013",
    "sg:province":"Barcelona",
    "wof:name":"Porta Gras Jordi",
    "wof:placetype":"venue"
},
  "geometry": {"coordinates":[2.1816220284,41.3973693848],"type":"Point"}
}