{
  "type": "Feature",
  "properties": {
    "iso:country":"ES",
    "sg:address":"C/ Doctor Ferran, 26",
    "sg:city":"Salt",
    "sg:orig_category":"Asociaciones Y Clubs Deportivos",
    "sg:phone":"+34 972 24 55 56",
    "sg:postcode":"17190",
    "sg:province":"Girona",
    "wof:name":"Budokan Associacio Gironina De Budo Tradicional",
    "wof:placetype":"venue"
},
  "geometry": {"coordinates":[2.7893640995,41.9728393555],"type":"Point"}
}