{
  "type": "Feature",
  "properties": {
    "iso:country":"ES",
    "sg:address":"Calle de San Pedro De Mestallon, 9",
    "sg:city":"Oviedo",
    "sg:orig_category":"Droguer\u00cdas (al Por Menor)",
    "sg:phone":"+34 985 21 95 59",
    "sg:postcode":"33009",
    "sg:province":"Asturias",
    "wof:name":"Iglesias Fernandez Ramon",
    "wof:placetype":"venue"
},
  "geometry": {"coordinates":[-5.8408241272,43.3587989807],"type":"Point"}
}