{
  "type": "Feature",
  "properties": {
    "addr:full":"Harzubia Hiribidea, 39 Azpeitia Guip\u00f9zcoa 20730",
    "addr:housenumber":"39",
    "addr:postcode":"20730",
    "addr:street":"Harzubia Hiribidea;Guipu\u0300Zcoa",
    "iso:country":"ES",
    "sg:address":"Harzubia Hiribidea, 39",
    "sg:city":"Azpeitia",
    "sg:orig_category":"Chapister\u00cda",
    "sg:phone":"+34 943 15 16 61",
    "sg:postcode":"20730",
    "sg:province":"Guip\u00f9zcoa",
    "wof:name":"Joakin Oruesagasti Oiarzabal",
    "wof:placetype":"venue"
},
  "geometry": {"coordinates":[-2.2617959976,43.1797523499],"type":"Point"}
}