{
  "type": "Feature",
  "properties": {
    "addr:full":"Psaj San Miguel, 1 Torremolinos M\u00e1laga 29620",
    "addr:housenumber":"1",
    "addr:postcode":"29620",
    "addr:street":"San Miguel;Ma\u0301Laga",
    "iso:country":"ES",
    "sg:address":"Psaj San Miguel, 1",
    "sg:city":"Torremolinos",
    "sg:orig_category":"Medias Y Calcetines (al Por Menor)",
    "sg:phone":"+34 952 38 15 82",
    "sg:postcode":"29620",
    "sg:province":"M\u00e1laga",
    "wof:name":"Luque Cortes Juan Manuel",
    "wof:placetype":"venue"
},
  "geometry": {"coordinates":[-4.5160393715,36.6265563965],"type":"Point"}
}