{
  "type": "Feature",
  "properties": {
    "addr:full":"Calle de Virgen De La Fuencisla, 22 Madrid Madrid 28027",
    "addr:housenumber":"22",
    "addr:postcode":"madrid;28027",
    "addr:street":"Calle De Virgen De La Fuencisla",
    "iso:country":"ES",
    "sg:address":"Calle de Virgen De La Fuencisla, 22",
    "sg:city":"Madrid",
    "sg:orig_category":"Frutas, Legumbres Frescas Y Tempranas (al Por Menor)",
    "sg:phone":"+34 914 03 85 29",
    "sg:postcode":"28027",
    "sg:province":"Madrid",
    "wof:name":"Buen Pastor Barrasa Pilar Del",
    "wof:placetype":"venue"
},
  "geometry": {"coordinates":[-3.6510639191,40.4377059937],"type":"Point"}
}