{
  "type": "Feature",
  "properties": {
    "addr:full":"Carrer de Angel Guimera, 9 S. Adria Besos Barcelona 08930",
    "addr:housenumber":"9",
    "addr:postcode":"08930",
    "addr:street":"Carrer De Angel Guimera;Barcelona",
    "iso:country":"ES",
    "sg:address":"Carrer de Angel Guimera, 9",
    "sg:city":"S. Adria Besos",
    "sg:orig_category":"Peluquer\u00cdas, Peluquer\u00cda Mixta",
    "sg:phone":"+34 933 81 25 00",
    "sg:postcode":"08930",
    "sg:province":"Barcelona",
    "wof:name":"Monreal Hurtado Lidia",
    "wof:placetype":"venue"
},
  "geometry": {"coordinates":[2.2227139473,41.4291877747],"type":"Point"}
}