{
  "type": "Feature",
  "properties": {
    "addr:full":"Calle de Tartanga Kalea, 4 Erandio Vizcaya 48950",
    "addr:housenumber":"4",
    "addr:postcode":"48950",
    "addr:street":"Calle De Tartanga Kalea",
    "iso:country":"ES",
    "sg:address":"Calle de Tartanga Kalea, 4",
    "sg:city":"Erandio",
    "sg:orig_category":"Peluqueros: De Se\u00d1oras",
    "sg:phone":"+34 944 67 65 37",
    "sg:postcode":"48950",
    "sg:province":"Vizcaya",
    "wof:name":"Peluqueria Pilar Iglesias Garcia",
    "wof:placetype":"venue"
},
  "geometry": {"coordinates":[-2.9739489555,43.3042297363],"type":"Point"}
}