{
  "type": "Feature",
  "properties": {
    "addr:full":"Ctra. Algaida, S/n Motril Granada 18600",
    "addr:housenumber":"s / n",
    "addr:postcode":"18600",
    "addr:street":"Ctra. Algaida",
    "iso:country":"ES",
    "sg:address":"Ctra. Algaida, S/n",
    "sg:city":"Motril",
    "sg:orig_category":"Empresas De Demolici\u00d3n",
    "sg:phone":"+34 958 60 12 20",
    "sg:postcode":"18600",
    "sg:province":"Granada",
    "wof:name":"Movimiento De Tierras Ferrer S.l.",
    "wof:placetype":"venue"
},
  "geometry": {"coordinates":[-3.5152790546,36.7456130981],"type":"Point"}
}