{
  "type": "Feature",
  "properties": {
    "addr:full":"Cigue\u00f1a, 3 Punta Umbria Huelva 21100",
    "addr:housenumber":"3",
    "addr:postcode":"21100",
    "addr:street":"Ciguen\u0303A",
    "iso:country":"ES",
    "sg:address":"Cigue\u00f1a, 3",
    "sg:city":"Punta Umbria",
    "sg:orig_category":"Alimentaci\u00d3n General (al Por Menor)",
    "sg:phone":"+34 959 52 82 18",
    "sg:postcode":"21100",
    "sg:province":"Huelva",
    "wof:name":"Hermano Oller Carmen",
    "wof:placetype":"venue"
},
  "geometry": {"coordinates":[-7.051566124,37.2128143311],"type":"Point"}
}