{
  "type": "Feature",
  "properties": {
    "iso:country":"ES",
    "sg:address":"Rplta Moros, 6",
    "sg:city":"Callosa Ensarria",
    "sg:orig_category":"Quincaller\u00cda (al Por Menor)",
    "sg:phone":"+34 965 88 06 91",
    "sg:postcode":"03510",
    "sg:province":"Alicante",
    "wof:name":"Fuster Perez Jose",
    "wof:placetype":"venue"
},
  "geometry": {"coordinates":[-0.1211889982,38.650188446],"type":"Point"}
}