{
  "type": "Feature",
  "properties": {
    "iso:country":"ES",
    "sg:address":"Calle de Marques De Villaviciosa, 37",
    "sg:city":"Villaviciosa",
    "sg:orig_category":"Material Y Herramientas Agr\u00cdcolas",
    "sg:phone":"+34 985 89 10 18",
    "sg:postcode":"33300",
    "sg:province":"Asturias",
    "wof:name":"Azcano Del Valle Jose Manuel",
    "wof:placetype":"venue"
},
  "geometry": {"coordinates":[-5.4343729019,43.4813995361],"type":"Point"}
}