{
  "type": "Feature",
  "properties": {
    "iso:country":"ES",
    "sg:address":"Calle de Lagasca, 11",
    "sg:city":"Madrid",
    "sg:classifiers":[
        {
            "category":"Arts & Performance",
            "subcategory":"Art Gallery",
            "type":"Entertainment"
        }
    ],
    "sg:phone":"+34 917 81 07 89",
    "sg:postcode":"28001",
    "sg:province":"Madrid",
    "sg:tags":[
        "obras",
        "de",
        "coleccionismo",
        "compraventa",
        "arte",
        "y"
    ],
    "wof:name":"Picassomio Gallery S.l.",
    "wof:placetype":"venue"
},
  "geometry": {"coordinates":[-3.6859149933,40.422077179],"type":"Point"}
}