{
  "type": "Feature",
  "properties": {
    "iso:country":"ES",
    "sg:address":"Avda Rey Juan Carlos I, S/n",
    "sg:city":"Jerez De La Frontera",
    "sg:orig_category":"Distribuci\u00d3n De Petr\u00d3leo Y Derivados",
    "sg:phone":"+34 956 33 87 01",
    "sg:postcode":"11405",
    "sg:province":"C\u00e1diz",
    "wof:name":"Explotaciones Agricolas Manuel Caballero S.a.",
    "wof:placetype":"venue"
},
  "geometry": {"coordinates":[-6.0986337662,36.6902999878],"type":"Point"}
}