{
  "type": "Feature",
  "properties": {
    "iso:country":"ES",
    "sg:address":"Calle de Perez De Hita, 1",
    "sg:city":"San Mateo",
    "sg:orig_category":"Frutas, Legumbres Frescas Y Tempranas (al Por Menor)",
    "sg:phone":"+34 968 44 22 35",
    "sg:postcode":"30800",
    "sg:province":"Murcia",
    "wof:name":"Martinez Perez Domingo",
    "wof:placetype":"venue"
},
  "geometry": {"coordinates":[-1.6905640364,37.680557251],"type":"Point"}
}