{
  "type": "Feature",
  "properties": {
    "iso:country":"ES",
    "sg:address":"Urune, 40",
    "sg:city":"Lezo",
    "sg:orig_category":"Empresas De Carpinter\u00cda De Madera",
    "sg:phone":"+34 943 51 05 33",
    "sg:postcode":"20100",
    "sg:province":"Guip\u00f9zcoa",
    "wof:name":"Rabanedo Lopez Miguel Angel",
    "wof:placetype":"venue"
},
  "geometry": {"coordinates":[-1.8732199669,43.3268051147],"type":"Point"}
}