{
  "type": "Feature",
  "properties": {
    "addr:full":"Calle de Centelles, Los, 48 Valencia Valencia 46006",
    "addr:housenumber":"48",
    "addr:postcode":"46006",
    "addr:street":"Calle De Centelles Los",
    "iso:country":"ES",
    "sg:address":"Calle de Centelles, Los, 48",
    "sg:city":"Valencia",
    "sg:orig_category":"Agentes, Concesionarios Y Sucursales De Veh\u00cdculos",
    "sg:phone":"+34 963 41 56 55",
    "sg:postcode":"46006",
    "sg:province":"Valencia",
    "wof:name":"Electro Bersa S.a.",
    "wof:placetype":"venue"
},
  "geometry": {"coordinates":[-0.3745607138,39.4586257935],"type":"Point"}
}