{
  "type": "Feature",
  "properties": {
    "addr:full":"Calle de Eleuterio Quintanilla, 32 Gijon Asturias 33208",
    "addr:housenumber":"32",
    "addr:postcode":"33208",
    "addr:street":"Calle De Eleuterio Quintanilla",
    "iso:country":"ES",
    "sg:address":"Calle de Eleuterio Quintanilla, 32",
    "sg:city":"Gijon",
    "sg:orig_category":"Suministros Y Materiales Industriales",
    "sg:phone":"+34 985 99 07 00",
    "sg:postcode":"33208",
    "sg:province":"Asturias",
    "sg:website":"www.cdelmart.es",
    "wof:name":"Comercial Delmart S.l.",
    "wof:placetype":"venue"
},
  "geometry": {"coordinates":[-5.6677970886,43.5313720703],"type":"Point"}
}