{
  "type": "Feature",
  "properties": {
    "iso:country":"ES",
    "sg:address":"Calle de Isaac Peral, 41",
    "sg:city":"Chipiona",
    "sg:orig_category":"Deportes Y Programas De Aventura",
    "sg:phone":"+34 956 37 43 91",
    "sg:postcode":"11550",
    "sg:province":"C\u00e1diz",
    "wof:name":"Radical Sport Costaluz S.l.",
    "wof:placetype":"venue"
},
  "geometry": {"coordinates":[-6.4354290962,36.7390518188],"type":"Point"}
}