{
  "type": "Feature",
  "properties": {
    "addr:full":"Carrer de Palau, 28 Mataro Barcelona 08301",
    "addr:housenumber":"28",
    "addr:postcode":"08301",
    "addr:street":"Carrer De Palau",
    "iso:country":"ES",
    "sg:address":"Carrer de Palau, 28",
    "sg:city":"Mataro",
    "sg:orig_category":"Prot\u00c9sicos Dentales",
    "sg:phone":"+34 937 55 44 11",
    "sg:postcode":"08301",
    "sg:province":"Barcelona",
    "wof:name":"Laboratorios Dranas S.l.",
    "wof:placetype":"venue"
},
  "geometry": {"coordinates":[2.4459030628,41.5398483276],"type":"Point"}
}