{
  "type": "Feature",
  "properties": {
    "iso:country":"ES",
    "sg:address":"Pase Baron De Adzaneta, 10",
    "sg:city":"Ramales Victoria",
    "sg:orig_category":"Caf\u00c9s, Bares, Cervecer\u00cdas",
    "sg:phone":"+34 942 64 65 98",
    "sg:postcode":"39800",
    "sg:province":"Cantabria",
    "wof:name":"Garcia Blanco Alicia",
    "wof:placetype":"venue"
},
  "geometry": {"coordinates":[-3.442991972,43.2613754272],"type":"Point"}
}