{
  "type": "Feature",
  "properties": {
    "addr:full":"Calle de San Vicente De Paul, 24 Sevilla Sevilla 41010",
    "addr:housenumber":"24",
    "addr:postcode":"41010",
    "addr:street":"Calle De San Vicente De Paul",
    "iso:country":"ES",
    "sg:address":"Calle de San Vicente De Paul, 24",
    "sg:city":"Sevilla",
    "sg:orig_category":"Chapister\u00cda",
    "sg:phone":"+34 954 33 19 79",
    "sg:postcode":"41010",
    "sg:province":"Sevilla",
    "wof:name":"Talleres Hijos De A.ruiz Xxi S.l.l",
    "wof:placetype":"venue"
},
  "geometry": {"coordinates":[-6.0101590157,37.3836784363],"type":"Point"}
}