{
  "type": "Feature",
  "properties": {
    "addr:full":"Carr Jacint Verdaguer, 13 Mollerussa Lleida 25230",
    "addr:housenumber":"13",
    "addr:postcode":"25230",
    "addr:street":"Carr Jacint Verdaguer",
    "iso:country":"ES",
    "sg:address":"Carr Jacint Verdaguer, 13",
    "sg:city":"Mollerussa",
    "sg:orig_category":"Droguer\u00cdas (al Por Menor)",
    "sg:phone":"+34 973 60 03 42",
    "sg:postcode":"25230",
    "sg:province":"Lleida",
    "wof:name":"Pedrosa Borrego Juan De Dios",
    "wof:placetype":"venue"
},
  "geometry": {"coordinates":[0.8945519924,41.6292190552],"type":"Point"}
}