{
  "type": "Feature",
  "properties": {
    "iso:country":"ES",
    "sg:address":"Carrer de Garrotxa, 2",
    "sg:city":"Residencial",
    "sg:orig_category":"Empresarios",
    "sg:phone":"+34 977 69 34 77",
    "sg:postcode":"43820",
    "sg:province":"Tarragona",
    "wof:name":"Comunidad Diagonal Park",
    "wof:placetype":"venue"
},
  "geometry": {"coordinates":[1.5684100389,41.1977844238],"type":"Point"}
}