{
  "type": "Feature",
  "properties": {
    "addr:full":"Calle de Magdalena, 18 Oviedo Asturias 33009",
    "addr:housenumber":"18",
    "addr:postcode":"33009",
    "addr:street":"Calle De Magdalena",
    "iso:country":"ES",
    "sg:address":"Calle de Magdalena, 18",
    "sg:city":"Oviedo",
    "sg:orig_category":"Dise\u00d1o Industrial",
    "sg:phone":"+34 985 20 80 80",
    "sg:postcode":"33009",
    "sg:province":"Asturias",
    "wof:name":"Ayuso San Pedro Carlos Luis",
    "wof:placetype":"venue"
},
  "geometry": {"coordinates":[-5.8451371193,43.359752655],"type":"Point"}
}