{
  "type": "Feature",
  "properties": {
    "addr:full":"Calle de General Ricardos, 82 Madrid Madrid 28019",
    "addr:housenumber":"82",
    "addr:postcode":"madrid;28019",
    "addr:street":"Calle De General Ricardos",
    "iso:country":"ES",
    "sg:address":"Calle de General Ricardos, 82",
    "sg:city":"Madrid",
    "sg:orig_category":"Alimentaci\u00d3n General (al Por Menor)",
    "sg:phone":"+34 914 71 80 56",
    "sg:postcode":"28019",
    "sg:province":"Madrid",
    "wof:name":"Rodriguez De La Hermosa Marcelo",
    "wof:placetype":"venue"
},
  "geometry": {"coordinates":[-3.7235529423,40.3936424255],"type":"Point"}
}