{
  "type": "Feature",
  "properties": {
    "iso:country":"ES",
    "sg:address":"Trav De Gracia, 427",
    "sg:city":"Barcelona",
    "sg:orig_category":"\u00d3ptica: Instrumentos (fabricaci\u00d3n)",
    "sg:phone":"+34 934 36 60 06",
    "sg:postcode":"08025",
    "sg:province":"Barcelona",
    "wof:name":"Servioptica S.l.",
    "wof:placetype":"venue"
},
  "geometry": {"coordinates":[2.1722559929,41.4106750488],"type":"Point"}
}