{
  "type": "Feature",
  "properties": {
    "addr:full":"Calle de Jose M. Salaberria, 39 Donostia-san Sebastian Guip\u00f9zcoa 20010",
    "addr:housenumber":"39",
    "addr:postcode":"20010",
    "addr:street":"Calle De Jose M. Salaberria",
    "iso:country":"ES",
    "sg:address":"Calle de Jose M. Salaberria, 39",
    "sg:city":"Donostia-san Sebastian",
    "sg:orig_category":"Molduras, Junquillos, Listones Y Molduras Perforadas",
    "sg:phone":"+34 943 45 08 92",
    "sg:postcode":"20010",
    "sg:province":"Guip\u00f9zcoa",
    "wof:name":"Saizar Sarobe Juan Jose",
    "wof:placetype":"venue"
},
  "geometry": {"coordinates":[-1.9800070524,43.3041381836],"type":"Point"}
}