{
  "type": "Feature",
  "properties": {
    "iso:country":"ES",
    "sg:address":"Calle de Don Juan Diaz, 4",
    "sg:city":"Malaga",
    "sg:orig_category":"Asesor\u00cda Sobre Comunicaci\u00d3n De Empresas",
    "sg:phone":"+34 952 22 91 41",
    "sg:postcode":"29015",
    "sg:province":"M\u00e1laga",
    "wof:name":"Don Juan Diaz 4 S.l.",
    "wof:placetype":"venue"
},
  "geometry": {"coordinates":[-4.421172142,36.7189865112],"type":"Point"}
}