{
  "type": "Feature",
  "properties": {
    "addr:full":"Tv. Acella, 5 Iru\u00f1a Navarra 31008",
    "addr:housenumber":"5",
    "addr:postcode":"31008",
    "addr:street":"Acella",
    "iso:country":"ES",
    "sg:address":"Tv. Acella, 5",
    "sg:city":"Iru\u00f1a",
    "sg:orig_category":"Vinos Y Licores (venta Al Por Menor)",
    "sg:phone":"+34 948 19 60 25",
    "sg:postcode":"31008",
    "sg:province":"Navarra",
    "wof:name":"Pexpan S.l.",
    "wof:placetype":"venue"
},
  "geometry": {"coordinates":[-1.6621539593,42.8064956665],"type":"Point"}
}