{
  "type": "Feature",
  "properties": {
    "iso:country":"ES",
    "sg:address":"Calle de Francisco Mari\u00d1o, 5",
    "sg:city":"Coru\u00d1a",
    "sg:orig_category":"Abogados",
    "sg:phone":"+34 981 22 99 21",
    "sg:postcode":"15004",
    "sg:province":"A Coru\u00f1a",
    "wof:name":"Soto Alvarez Maria Jose De",
    "wof:placetype":"venue"
},
  "geometry": {"coordinates":[-8.4083900452,43.3664932251],"type":"Point"}
}