{
  "type": "Feature",
  "properties": {
    "addr:full":"Urb. La Paz, 1 Llanes Asturias 33500",
    "addr:housenumber":"1",
    "addr:postcode":"33500",
    "addr:street":"La Paz",
    "iso:country":"ES",
    "sg:address":"Urb. La Paz, 1",
    "sg:city":"Llanes",
    "sg:orig_category":"Promotores Constructores",
    "sg:phone":"+34 985 40 02 23",
    "sg:postcode":"33500",
    "sg:province":"Asturias",
    "wof:name":"Construcciones Fernandez Millar S.l.",
    "wof:placetype":"venue"
},
  "geometry": {"coordinates":[-4.7549939156,43.4207191467],"type":"Point"}
}