{
  "type": "Feature",
  "properties": {
    "addr:full":"Calle de Luis Antunez, 39 Palmas De Gran Canaria Las Palmas 35006",
    "addr:housenumber":"39",
    "addr:postcode":"35006",
    "addr:street":"Calle De Luis Antunez",
    "iso:country":"ES",
    "sg:address":"Calle de Luis Antunez, 39",
    "sg:city":"Palmas De Gran Canaria",
    "sg:orig_category":"Fabricaci\u00d3n, Venta De Productos Base Farmac\u00c9uticos",
    "sg:phone":"+34 928 24 16 14",
    "sg:postcode":"35006",
    "sg:province":"Las Palmas",
    "wof:name":"Elejabeitia Gonzalez Maria Idoya De",
    "wof:placetype":"venue"
},
  "geometry": {"coordinates":[-15.4305210114,28.13164711],"type":"Point"}
}