{
  "type": "Feature",
  "properties": {
    "addr:full":"Madreselva-nueva Laguna, 7 Mijas Costa M\u00e1laga 29649",
    "addr:housenumber":"7",
    "addr:postcode":"29649",
    "iso:country":"ES",
    "sg:address":"Madreselva-nueva Laguna, 7",
    "sg:city":"Mijas Costa",
    "sg:orig_category":"Comercio, Reparaci\u00d3n De Motocicletas, Bicicletas Y Piezas Sueltas",
    "sg:phone":"+34 952 46 82 15",
    "sg:postcode":"29649",
    "sg:province":"M\u00e1laga",
    "wof:name":"Blanco Leyva Jose Antonio",
    "wof:placetype":"venue"
},
  "geometry": {"coordinates":[-4.6310629845,36.5238952637],"type":"Point"}
}