{
  "type": "Feature",
  "properties": {
    "iso:country":"ES",
    "sg:address":"Calle de Gardoqui Cardenal, 5",
    "sg:city":"Bilbao",
    "sg:orig_category":"Centros De Coordinaci\u00d3n",
    "sg:phone":"+34 944 02 87 81",
    "sg:postcode":"48008",
    "sg:province":"Vizcaya",
    "wof:name":"Manuel Villa Urrutia (gestoria Villa Urrutia)",
    "wof:placetype":"venue"
},
  "geometry": {"coordinates":[-2.9311282635,43.2609558105],"type":"Point"}
}