{
  "type": "Feature",
  "properties": {
    "iso:country":"ES",
    "sg:address":"Ctra. Casas Iba\u00f1ez, Km. 0003,7",
    "sg:city":"Albacete",
    "sg:orig_category":"Patatas (al Por Mayor)",
    "sg:phone":"+34 967 24 07 10",
    "sg:postcode":"02006",
    "sg:province":"Albacete",
    "wof:name":"Agromar Hispana S.a.",
    "wof:placetype":"venue"
},
  "geometry": {"coordinates":[-1.866542,39.012562],"type":"Point"}
}