{
  "type": "Feature",
  "properties": {
    "addr:full":"Calle de Portalet, 1 Valencia Valencia 46025",
    "addr:housenumber":"1",
    "addr:postcode":"46025",
    "addr:street":"Calle De Portalet",
    "iso:country":"ES",
    "sg:address":"Calle de Portalet, 1",
    "sg:city":"Valencia",
    "sg:classifiers":[
        {
            "category":"Personal",
            "subcategory":"Barber",
            "type":"Services"
        }
    ],
    "sg:phone":"+34 963 47 11 96",
    "sg:postcode":"46025",
    "sg:province":"Valencia",
    "sg:tags":[
        "caballeros",
        "de",
        "peluqueros"
    ],
    "wof:name":"Murcia Valencia Fabio",
    "wof:placetype":"venue"
},
  "geometry": {"coordinates":[-0.390978992,39.4929504395],"type":"Point"}
}