{
  "type": "Feature",
  "properties": {
    "addr:full":"Carrer de Santa Creu, 4 Sant Feliu Llobregat Barcelona 08980",
    "addr:housenumber":"4",
    "addr:postcode":"08980",
    "addr:street":"Carrer De Santa Creu",
    "iso:country":"ES",
    "sg:address":"Carrer de Santa Creu, 4",
    "sg:city":"Sant Feliu Llobregat",
    "sg:orig_category":"Carnicer\u00cdas, Carnicer\u00cdas",
    "sg:phone":"+34 936 66 35 04",
    "sg:postcode":"08980",
    "sg:province":"Barcelona",
    "wof:name":"Procarela S.l.",
    "wof:placetype":"venue"
},
  "geometry": {"coordinates":[2.0465989113,41.3849029541],"type":"Point"}
}