{
  "type": "Feature",
  "properties": {
    "addr:full":"Calle de Hernando De Arenas, S/n Cuenca Cuenca 16003",
    "addr:housenumber":"s / n",
    "addr:postcode":"16003",
    "addr:street":"Calle De Hernando De Arenas",
    "iso:country":"ES",
    "sg:address":"Calle de Hernando De Arenas, S/n",
    "sg:city":"Cuenca",
    "sg:orig_category":"Negocio De Granos Y Harinas",
    "sg:phone":"+34 969 22 13 24",
    "sg:postcode":"16003",
    "sg:province":"Cuenca",
    "wof:name":"Saiz Lozano Felix",
    "wof:placetype":"venue"
},
  "geometry": {"coordinates":[-2.1404089928,40.0658836365],"type":"Point"}
}