{
  "type": "Feature",
  "properties": {
    "addr:full":"Rio Alfambra, 2 Teruel Teruel 44003",
    "addr:housenumber":"2",
    "addr:postcode":"44003",
    "addr:street":"Rio Alfambra",
    "iso:country":"ES",
    "sg:address":"Rio Alfambra, 2",
    "sg:city":"Teruel",
    "sg:orig_category":"Ense\u00d1anza Secundaria: Colegios Y Escuelas Privadas",
    "sg:phone":"+34 978 60 13 21",
    "sg:postcode":"44003",
    "sg:province":"Teruel",
    "wof:name":"Instituto De Educacion Secundaria Segundo De Chomon",
    "wof:placetype":"venue"
},
  "geometry": {"coordinates":[-1.1111290455,40.347568512],"type":"Point"}
}