{
  "type": "Feature",
  "properties": {
    "iso:country":"ES",
    "sg:address":"Calle de Manuel Pereira, 9",
    "sg:city":"Ourense",
    "sg:orig_category":"Abogados",
    "sg:phone":"+34 988 23 04 19",
    "sg:postcode":"32003",
    "sg:province":"Ourense",
    "wof:name":"Pousa Nogueiras Julia",
    "wof:placetype":"venue"
},
  "geometry": {"coordinates":[-7.8617238998,42.3437805176],"type":"Point"}
}