{
  "type": "Feature",
  "properties": {
    "addr:full":"Avda Constitucion, 18 Boiro La Coru\u00f1a 15930",
    "addr:housenumber":"18",
    "addr:postcode":"15930",
    "addr:street":"Avda Constitucion;La Corun\u0303A",
    "iso:country":"ES",
    "sg:address":"Avda Constitucion, 18",
    "sg:city":"Boiro",
    "sg:orig_category":"Promotores Constructores",
    "sg:phone":"+34 981 84 72 00",
    "sg:postcode":"15930",
    "sg:province":"La Coru\u00f1a",
    "sg:website":"www.espanayfernandez.com",
    "wof:name":"Espa\u00f1a Y Fernandez",
    "wof:placetype":"venue"
},
  "geometry": {"coordinates":[-8.8795890808,42.6470108032],"type":"Point"}
}