{
  "type": "Feature",
  "properties": {
    "addr:full":"Avda Casalduch, 31 Castellon Castell\u00f3n 12005",
    "addr:housenumber":"31",
    "addr:postcode":"12005",
    "addr:street":"Avda Casalduch",
    "iso:country":"ES",
    "sg:address":"Avda Casalduch, 31",
    "sg:city":"Castellon",
    "sg:orig_category":"M\u00c1quinas De Coser Y De Hacer Punto (al Por Mayor)",
    "sg:phone":"+34 964 20 92 30",
    "sg:postcode":"12005",
    "sg:province":"Castell\u00f3n",
    "wof:name":"Mateu Vicent Jose Manuel",
    "wof:placetype":"venue"
},
  "geometry": {"coordinates":[-0.0387419984,39.9792747498],"type":"Point"}
}