{
  "type": "Feature",
  "properties": {
    "iso:country":"ES",
    "sg:address":"Calle de Real, 11",
    "sg:city":"Lapuebla Labarca",
    "sg:orig_category":"Centros Empresariales",
    "sg:phone":"+34 945 62 72 82",
    "sg:postcode":"01306",
    "sg:province":"\u00c1lava",
    "wof:name":"Rodriguez Pinto S.c.",
    "wof:placetype":"venue"
},
  "geometry": {"coordinates":[-2.5733580589,42.4939155579],"type":"Point"}
}