{
  "type": "Feature",
  "properties": {
    "iso:country":"ES",
    "sg:address":"Calle de Ermita, 7",
    "sg:city":"Alhaurin Torre",
    "sg:orig_category":"Abogados",
    "sg:phone":"+34 952 41 00 07",
    "sg:postcode":"29130",
    "sg:province":"M\u00e1laga",
    "wof:name":"Ortega Y Peinado Abogados S.c.",
    "wof:placetype":"venue"
},
  "geometry": {"coordinates":[-4.5633192062,36.6628952026],"type":"Point"}
}