{
  "type": "Feature",
  "properties": {
    "iso:country":"ES",
    "sg:address":"Plaz Caudillo, 1",
    "sg:city":"Cascon Nava",
    "sg:orig_category":"Iglesia Cat\u00d3lica",
    "sg:phone":"+34 979 83 32 30",
    "sg:postcode":"34192",
    "sg:province":"Palencia",
    "wof:name":"Parroquia De Santo Toribio",
    "wof:placetype":"venue"
},
  "geometry": {"coordinates":[-4.5808391571,42.0539283752],"type":"Point"}
}