{
  "type": "Feature",
  "properties": {
    "iso:country":"ES",
    "sg:address":"Calle de Cerrojo, S/n",
    "sg:city":"Malaga",
    "sg:orig_category":"Conservatorios",
    "sg:phone":"+34 952 39 65 00",
    "sg:postcode":"29007",
    "sg:province":"M\u00e1laga",
    "wof:name":"Junta De Andalucia",
    "wof:placetype":"venue"
},
  "geometry": {"coordinates":[-4.4276947975,36.7194671631],"type":"Point"}
}