{
  "type": "Feature",
  "properties": {
    "addr:full":"Pase Flores (de Las), 16 Coslada Madrid 28820",
    "addr:housenumber":"16",
    "addr:postcode":"28820",
    "addr:street":"Las",
    "iso:country":"ES",
    "sg:address":"Pase Flores (de Las), 16",
    "sg:city":"Coslada",
    "sg:orig_category":"Inform\u00c1tica Equipo Y Programas (al Por Mayor)",
    "sg:phone":"+34 916 69 88 89",
    "sg:postcode":"28820",
    "sg:province":"Madrid",
    "sg:website":"www.energiro.com",
    "wof:name":"Energiro S.l.",
    "wof:placetype":"venue"
},
  "geometry": {"coordinates":[-3.5645070076,40.4260902405],"type":"Point"}
}