{
  "type": "Feature",
  "properties": {
    "iso:country":"ES",
    "sg:address":"Avda Monte Boyal (del), 33",
    "sg:city":"Poligono Industrial Monte Boyal",
    "sg:orig_category":"Comercio De Hierro",
    "sg:phone":"+34 918 18 33 85",
    "sg:postcode":"45950",
    "sg:province":"Toledo",
    "wof:name":"Ferra 2-99 S.l.",
    "wof:placetype":"venue"
},
  "geometry": {"coordinates":[-4.0599141121,40.2059860229],"type":"Point"}
}