{
  "type": "Feature",
  "properties": {
    "iso:country":"ES",
    "sg:address":"Calle de Lusitania, 2",
    "sg:city":"Ayamonte",
    "sg:orig_category":"Abogados",
    "sg:phone":"+34 959 47 03 86",
    "sg:postcode":"21400",
    "sg:province":"Huelva",
    "wof:name":"Gonzalez Morales Soledad",
    "wof:placetype":"venue"
},
  "geometry": {"coordinates":[-7.407324791,37.2132034302],"type":"Point"}
}