{
  "type": "Feature",
  "properties": {
    "addr:full":"Pg Maritim, 3 Mao Islas Baleares 07701",
    "addr:housenumber":"3",
    "addr:postcode":"07701",
    "addr:street":"Pg Maritim",
    "iso:country":"ES",
    "sg:address":"Pg Maritim, 3",
    "sg:city":"Mao",
    "sg:orig_category":"Centros M\u00c9dicos Y Sociales, Dispensarios",
    "sg:phone":"+34 971 36 44 22",
    "sg:postcode":"07701",
    "sg:province":"Islas Baleares",
    "wof:name":"Sanchez-rodrigo Rivero Manuel Carlos",
    "wof:placetype":"venue"
},
  "geometry": {"coordinates":[4.2739920616,39.8872070312],"type":"Point"}
}