{
  "type": "Feature",
  "properties": {
    "iso:country":"ES",
    "sg:address":"Calle de Victor Serna, S/n",
    "sg:city":"Fuengirola",
    "sg:orig_category":"Asesor\u00cda Fiscal Y Jur\u00cddica",
    "sg:phone":"+34 952 47 42 63",
    "sg:postcode":"29640",
    "sg:province":"M\u00e1laga",
    "wof:name":"Asesoria Fiscal Contable Alpe S.l.",
    "wof:placetype":"venue"
},
  "geometry": {"coordinates":[-4.6172895432,36.5497322083],"type":"Point"}
}