{
  "type": "Feature",
  "properties": {
    "addr:full":"Ctra Pe\u00d1aranda, 7 Alba Tormes Salamanca 37800",
    "addr:housenumber":"7",
    "addr:postcode":"37800",
    "addr:street":"Ctra Pen\u0303Aranda",
    "iso:country":"ES",
    "sg:address":"Ctra Pe\u00d1aranda, 7",
    "sg:city":"Alba Tormes",
    "sg:orig_category":"Pintura Y Barniz (al Por Menor)",
    "sg:phone":"+34 923 30 01 86",
    "sg:postcode":"37800",
    "sg:province":"Salamanca",
    "wof:name":"Almacen Y Distribucion Pinturalba S.l.",
    "wof:placetype":"venue"
},
  "geometry": {"coordinates":[-5.5098171234,40.8245773315],"type":"Point"}
}