{
  "type": "Feature",
  "properties": {
    "addr:full":"Calle de Tajo, 2 Estepona M\u00e1laga 29680",
    "addr:housenumber":"2",
    "addr:postcode":"29680",
    "addr:street":"Calle De Tajo",
    "iso:country":"ES",
    "sg:address":"Calle de Tajo, 2",
    "sg:city":"Estepona",
    "sg:orig_category":"Alquiler De V\u00cddeo",
    "sg:phone":"+34 952 89 63 45",
    "sg:postcode":"29680",
    "sg:province":"M\u00e1laga",
    "wof:name":"Puertas Lopez Juan",
    "wof:placetype":"venue"
},
  "geometry": {"coordinates":[-5.1496148109,36.4273796082],"type":"Point"}
}