{
  "type": "Feature",
  "properties": {
    "addr:full":"Avda De Bara\u00f1ain, 15 Iru\u00f1a Navarra 31008",
    "addr:housenumber":"15",
    "addr:postcode":"31008",
    "addr:street":"Avda De Baran\u0303Ain",
    "iso:country":"ES",
    "sg:address":"Avda De Bara\u00f1ain, 15",
    "sg:city":"Iru\u00f1a",
    "sg:orig_category":"Locales Y Clases De Danza",
    "sg:phone":"+34 948 17 36 18",
    "sg:postcode":"31008",
    "sg:province":"Navarra",
    "sg:website":"www.almudenalobon.com",
    "wof:name":"Gonzalez Lobon Almudena",
    "wof:placetype":"venue"
},
  "geometry": {"coordinates":[-1.6626189947,42.8112487793],"type":"Point"}
}