{
  "type": "Feature",
  "properties": {
    "addr:full":"Calle de Daroca, 90 Zaragoza Zaragoza 50017",
    "addr:housenumber":"90",
    "addr:postcode":"50017",
    "addr:street":"Calle De Daroca",
    "iso:country":"ES",
    "sg:address":"Calle de Daroca, 90",
    "sg:city":"Zaragoza",
    "sg:orig_category":"Industria Qu\u00cdmica",
    "sg:phone":"+34 976 53 83 82",
    "sg:postcode":"50017",
    "sg:province":"Zaragoza",
    "wof:name":"Pulitecnia S.l.",
    "wof:placetype":"venue"
},
  "geometry": {"coordinates":[-0.9092264771,41.6498565674],"type":"Point"}
}