{
  "type": "Feature",
  "properties": {
    "addr:full":"Pol Ind Rio Gallego, 28 S. Mateo Gallego Zaragoza 50840",
    "addr:housenumber":"28",
    "addr:postcode":"50840",
    "addr:street":"Gallego;S. Mateo Gallego",
    "iso:country":"ES",
    "sg:address":"Pol Ind Rio Gallego, 28",
    "sg:city":"S. Mateo Gallego",
    "sg:orig_category":"Instalaci\u00d3n, Reparaci\u00d3n De Ascensores Y Montacargas",
    "sg:phone":"+34 976 68 47 33",
    "sg:postcode":"50840",
    "sg:province":"Zaragoza",
    "wof:name":"Fabricacion De Elevadores S. L.",
    "wof:placetype":"venue"
},
  "geometry": {"coordinates":[-0.7679479718,41.8305587769],"type":"Point"}
}