{
  "type": "Feature",
  "properties": {
    "addr:full":"Calle de I, 48 Bola\u00f1os Calatrava Ciudad Real 13260",
    "addr:housenumber":"48",
    "addr:postcode":"13260",
    "addr:street":"Calle De I",
    "iso:country":"ES",
    "sg:address":"Calle de I, 48",
    "sg:city":"Bola\u00f1os Calatrava",
    "sg:orig_category":"Aceites Y Grasas Alimentarias (fabricaci\u00d3n, Al Por Mayor)",
    "sg:phone":"+34 926 87 16 11",
    "sg:postcode":"13260",
    "sg:province":"Ciudad Real",
    "wof:name":"Aceites Olivar Del Valle S.l.",
    "wof:placetype":"venue"
},
  "geometry": {"coordinates":[-3.7195723057,38.8903312683],"type":"Point"}
}