{
  "type": "Feature",
  "properties": {
    "addr:full":"Calle de Federico Garcia Sanchis, 23 Monte Vedat Valencia 46901",
    "addr:housenumber":"23",
    "addr:postcode":"46901",
    "addr:street":"Calle De Federico Garcia Sanchis;Vedat",
    "iso:country":"ES",
    "sg:address":"Calle de Federico Garcia Sanchis, 23",
    "sg:city":"Monte Vedat",
    "sg:orig_category":"Procuradores",
    "sg:phone":"+34 961 55 22 69",
    "sg:postcode":"46901",
    "sg:province":"Valencia",
    "wof:name":"Soria Planells Vicente",
    "wof:placetype":"venue"
},
  "geometry": {"coordinates":[-0.4834426939,39.4123344421],"type":"Point"}
}