{
  "type": "Feature",
  "properties": {
    "addr:full":"Calle de Eduardo Torroja (de), 49 Fuenlabrada Madrid 28946",
    "addr:housenumber":"49",
    "addr:postcode":"28946",
    "addr:street":"Calle De Eduardo Torroja De",
    "iso:country":"ES",
    "sg:address":"Calle de Eduardo Torroja (de), 49",
    "sg:city":"Fuenlabrada",
    "sg:orig_category":"Electricidad: Instaladores",
    "sg:phone":"+34 916 15 28 75",
    "sg:postcode":"28946",
    "sg:province":"Madrid",
    "wof:name":"Cobra Instalaciones Y Servicios S.a.",
    "wof:placetype":"venue"
},
  "geometry": {"coordinates":[-3.7806990147,40.2842903137],"type":"Point"}
}