{
  "type": "Feature",
  "properties": {
    "iso:country":"ES",
    "sg:address":"Carrer de Siracusa, 53",
    "sg:city":"Barcelona",
    "sg:orig_category":"Centros De Educaci\u00d3n Especial",
    "sg:phone":"+34 932 85 99 77",
    "sg:postcode":"08012",
    "sg:province":"Barcelona",
    "sg:website":"www.acidh.org",
    "wof:name":"Associacio Catalana D'integracio I Desenvolupament Huma",
    "wof:placetype":"venue"
},
  "geometry": {"coordinates":[2.1613743305,41.4020576477],"type":"Point"}
}