{
  "type": "Feature",
  "properties": {
    "iso:country":"ES",
    "sg:address":"Calle de Cavanilles, 39",
    "sg:city":"Madrid",
    "sg:orig_category":"Agencias De Viajes",
    "sg:phone":"+34 915 01 30 95",
    "sg:postcode":"28007",
    "sg:province":"Madrid",
    "wof:name":"Viajes Normatravel S.a.",
    "wof:placetype":"venue"
},
  "geometry": {"coordinates":[-3.6738920212,40.4051704407],"type":"Point"}
}