{
  "type": "Feature",
  "properties": {
    "addr:full":"Calle de San Nicasio, 7 Leganes Madrid 28911",
    "addr:housenumber":"7",
    "addr:postcode":"28911",
    "addr:street":"Calle De San Nicasio",
    "iso:country":"ES",
    "sg:address":"Calle de San Nicasio, 7",
    "sg:city":"Leganes",
    "sg:orig_category":"Inmobiliaria (agencias)",
    "sg:phone":"+34 916 93 06 36",
    "sg:postcode":"28911",
    "sg:province":"Madrid",
    "wof:name":"Promociones Inmobiliarias Ariadne S.l.",
    "wof:placetype":"venue"
},
  "geometry": {"coordinates":[-3.7665600777,40.3303184509],"type":"Point"}
}