{
  "type": "Feature",
  "properties": {
    "addr:full":"Avda Infantes De Lara, 18 Salas De Los Infantes Burgos 09600",
    "addr:housenumber":"18",
    "addr:postcode":"09600",
    "addr:street":"Avda Infantes De Lara",
    "iso:country":"ES",
    "sg:address":"Avda Infantes De Lara, 18",
    "sg:city":"Salas De Los Infantes",
    "sg:orig_category":"Carnicer\u00cdas, Carnicer\u00cdas",
    "sg:phone":"+34 947 38 07 64",
    "sg:postcode":"09600",
    "sg:province":"Burgos",
    "wof:name":"Camarero Camarero Gonzalo",
    "wof:placetype":"venue"
},
  "geometry": {"coordinates":[-3.2862420082,42.0223731995],"type":"Point"}
}