{
  "type": "Feature",
  "properties": {
    "addr:full":"Carrer de Velia, 28 Barcelona Barcelona 08016",
    "addr:housenumber":"28",
    "addr:postcode":"08016",
    "addr:street":"Carrer De Velia",
    "iso:country":"ES",
    "sg:address":"Carrer de Velia, 28",
    "sg:city":"Barcelona",
    "sg:orig_category":"Florister\u00cdas",
    "sg:phone":"+34 933 11 67 71",
    "sg:postcode":"08016",
    "sg:province":"Barcelona",
    "wof:name":"Sanchez Meri\u00f1an Concepcion",
    "wof:placetype":"venue"
},
  "geometry": {"coordinates":[2.1809840202,41.4297599792],"type":"Point"}
}