{
  "type": "Feature",
  "properties": {
    "addr:full":"Avda Martinez Campos, 1 Alcantarilla Murcia 30820",
    "addr:housenumber":"1",
    "addr:postcode":"30820",
    "addr:street":"Avda Martinez Campos",
    "iso:country":"ES",
    "sg:address":"Avda Martinez Campos, 1",
    "sg:city":"Alcantarilla",
    "sg:orig_category":"Albergues",
    "sg:phone":"+34 968 80 00 10",
    "sg:postcode":"30820",
    "sg:province":"Murcia",
    "wof:name":"Hostal Vicente S.l.",
    "wof:placetype":"venue"
},
  "geometry": {"coordinates":[-1.2158019543,37.9692344666],"type":"Point"}
}