{
  "type": "Feature",
  "properties": {
    "iso:country":"ES",
    "sg:address":"Plaz Caidos (los), S/n",
    "sg:city":"Cabez\u00f3n Sal",
    "sg:orig_category":"Bancos",
    "sg:phone":"+34 942 70 09 36",
    "sg:postcode":"39500",
    "sg:province":"Cantabria",
    "sg:website":"www.gruposantander.es",
    "wof:name":"Bt Espa\u00d1a Compa\u00d1ia De Servicios Globales De Telecomunicaciones S.a.u.",
    "wof:placetype":"venue"
},
  "geometry": {"coordinates":[-4.2374691963,43.3085784912],"type":"Point"}
}