{
  "type": "Feature",
  "properties": {
    "addr:full":"Calle de Economia, 5 Sevilla Sevilla 41007",
    "addr:housenumber":"5",
    "addr:postcode":"41007",
    "addr:street":"Calle De Economia",
    "iso:country":"ES",
    "sg:address":"Calle de Economia, 5",
    "sg:city":"Sevilla",
    "sg:orig_category":"Asesor\u00cda Sobre Comunicaci\u00d3n De Empresas",
    "sg:phone":"+34 954 99 71 82",
    "sg:postcode":"41007",
    "sg:province":"Sevilla",
    "wof:name":"Proyectos Asesoria Y Servicios S.a.",
    "wof:placetype":"venue"
},
  "geometry": {"coordinates":[-5.9488377571,37.3937149048],"type":"Point"}
}