{
  "type": "Feature",
  "properties": {
    "iso:country":"ES",
    "sg:address":"B, 8",
    "sg:city":"Irurtzun",
    "sg:orig_category":"T\u00c9cnicos Veterinarios",
    "sg:phone":"+34 948 50 62 20",
    "sg:postcode":"31860",
    "sg:province":"Navarra",
    "sg:website":"www.albaikide.com",
    "wof:name":"Albaikide S.a",
    "wof:placetype":"venue"
},
  "geometry": {"coordinates":[-1.848798275,42.9162788391],"type":"Point"}
}