{
  "type": "Feature",
  "properties": {
    "addr:full":"Calle de Cristobal Colon, 20 Puertollano Ciudad Real 13500",
    "addr:housenumber":"20",
    "addr:postcode":"13500",
    "addr:street":"Calle De Cristobal Colon",
    "iso:country":"ES",
    "sg:address":"Calle de Cristobal Colon, 20",
    "sg:city":"Puertollano",
    "sg:orig_category":"Empresas De Carpinter\u00cda",
    "sg:phone":"+34 926 42 81 30",
    "sg:postcode":"13500",
    "sg:province":"Ciudad Real",
    "wof:name":"Liranzo Hidalgo Emeterio",
    "wof:placetype":"venue"
},
  "geometry": {"coordinates":[-4.1138758659,38.6829071045],"type":"Point"}
}