{
  "type": "Feature",
  "properties": {
    "addr:full":"Calle de Cronista Cazaban, 36 Jaen Ja\u00e9n 23001",
    "addr:housenumber":"36;jae\u0301n",
    "addr:postcode":"23001",
    "addr:street":"Calle De Cronista Cazaban",
    "iso:country":"ES",
    "sg:address":"Calle de Cronista Cazaban, 36",
    "sg:city":"Jaen",
    "sg:orig_category":"Papeler\u00cdas, Librer\u00cdas",
    "sg:phone":"+34 953 24 31 24",
    "sg:postcode":"23001",
    "sg:province":"Ja\u00e9n",
    "wof:name":"Cruz Santa Barbara Juan",
    "wof:placetype":"venue"
},
  "geometry": {"coordinates":[-3.788369894,37.7668380737],"type":"Point"}
}