{
  "type": "Feature",
  "properties": {
    "addr:full":"Calle de Coso Bajo, 85 Huesca Huesca 22001",
    "addr:housenumber":"85",
    "addr:postcode":"22001",
    "addr:street":"Calle De Coso Bajo",
    "iso:country":"ES",
    "sg:address":"Calle de Coso Bajo, 85",
    "sg:city":"Huesca",
    "sg:orig_category":"Sociedades, Compa\u00d1\u00cdas Aseguradoras",
    "sg:phone":"+34 974 22 39 56",
    "sg:postcode":"22001",
    "sg:province":"Huesca",
    "wof:name":"Gomez Mairal Jose Luis",
    "wof:placetype":"venue"
},
  "geometry": {"coordinates":[-0.4052523077,42.1390571594],"type":"Point"}
}