{
  "type": "Feature",
  "properties": {
    "iso:country":"ES",
    "sg:address":"Calle de Mayor, 1",
    "sg:city":"Valjunquera",
    "sg:orig_category":"Carnicer\u00cdas, Carnicer\u00cdas",
    "sg:phone":"+34 978 85 41 02",
    "sg:postcode":"44595",
    "sg:province":"Teruel",
    "wof:name":"Insa Blasco Luis",
    "wof:placetype":"venue"
},
  "geometry": {"coordinates":[0.0268200003,40.9525604248],"type":"Point"}
}