{
  "type": "Feature",
  "properties": {
    "addr:full":"Plaz Lauaxeta, 6 Bilbao Vizcaya 48004",
    "addr:housenumber":"6",
    "addr:postcode":"48004",
    "addr:street":"Lauaxeta",
    "iso:country":"ES",
    "sg:address":"Plaz Lauaxeta, 6",
    "sg:city":"Bilbao",
    "sg:orig_category":"Pescader\u00cdas (al Por Menor)",
    "sg:phone":"+34 944 11 82 67",
    "sg:postcode":"48004",
    "sg:province":"Vizcaya",
    "wof:name":"Tomas Benito Conde Y Francisco Gonzalez Ijalba Cb",
    "wof:placetype":"venue"
},
  "geometry": {"coordinates":[-2.9092450142,43.2516517639],"type":"Point"}
}