{
  "type": "Feature",
  "properties": {
    "iso:country":"ES",
    "sg:address":"Calle de Navarejos, 2",
    "sg:city":"Piedralaves",
    "sg:orig_category":"Telas Y Sedas (al Por Menor)",
    "sg:phone":"+34 918 66 63 68",
    "sg:postcode":"05440",
    "sg:province":"\u00c1vila",
    "wof:name":"Zamorano Sanchez Mari Angeles",
    "wof:placetype":"venue"
},
  "geometry": {"coordinates":[-4.700109005,40.3129234314],"type":"Point"}
}