{
  "type": "Feature",
  "properties": {
    "iso:country":"ES",
    "sg:address":"Calle de Cava, 15",
    "sg:city":"Santa Cruz De La Zarza",
    "sg:orig_category":"Supermercados Y Hipermercados",
    "sg:phone":"+34 925 14 35 20",
    "sg:postcode":"45370",
    "sg:province":"Toledo",
    "wof:name":"Teogenes Ruiz S.l.",
    "wof:placetype":"venue"
},
  "geometry": {"coordinates":[-3.1896290779,39.9841117859],"type":"Point"}
}