{
  "type": "Feature",
  "properties": {
    "addr:full":"Calle de Divina Pastora, 1 Valladolid Valladolid 47004",
    "addr:housenumber":"1",
    "addr:postcode":"47004",
    "addr:street":"Calle De Divina Pastora",
    "iso:country":"ES",
    "sg:address":"Calle de Divina Pastora, 1",
    "sg:city":"Valladolid",
    "sg:orig_category":"Administradores De Bienes Y Delegados De Comunidades De Propietarios",
    "sg:phone":"+34 983 39 84 38",
    "sg:postcode":"47004",
    "sg:province":"Valladolid",
    "wof:name":"Gutierrez Boronat Ignacio",
    "wof:placetype":"venue"
},
  "geometry": {"coordinates":[-4.7252635956,41.6479492188],"type":"Point"}
}