{
  "type": "Feature",
  "properties": {
    "iso:country":"ES",
    "sg:address":"Calle de Arene, 8",
    "sg:city":"Algorta",
    "sg:orig_category":"Asociaciones, Organismos Culturales Y Socioeducativos",
    "sg:phone":"+34 944 30 89 26",
    "sg:postcode":"48991",
    "sg:province":"Vizcaya",
    "wof:name":"Colectivo De Artistas Getxotarras Antzezaleak",
    "wof:placetype":"venue"
},
  "geometry": {"coordinates":[-3.0061480999,43.3487205505],"type":"Point"}
}