{
  "type": "Feature",
  "properties": {
    "addr:full":"Calle de Vendederas, 7 Andujar Ja\u00e9n 23740",
    "addr:housenumber":"7",
    "addr:postcode":"23740",
    "addr:street":"Calle De Vendederas",
    "iso:country":"ES",
    "sg:address":"Calle de Vendederas, 7",
    "sg:city":"Andujar",
    "sg:orig_category":"Tapicer\u00cdas",
    "sg:phone":"+34 953 50 12 82",
    "sg:postcode":"23740",
    "sg:province":"Ja\u00e9n",
    "wof:name":"Mu\u00f1oz Perez Jose",
    "wof:placetype":"venue"
},
  "geometry": {"coordinates":[-4.0571122169,38.0401153564],"type":"Point"}
}