{
  "type": "Feature",
  "properties": {
    "addr:full":"Calle de Do\u00d1a Romera, 8 Getafe Madrid 28901",
    "addr:housenumber":"8",
    "addr:postcode":"28901",
    "addr:street":"Calle De Don\u0303A Romera",
    "iso:country":"ES",
    "sg:address":"Calle de Do\u00d1a Romera, 8",
    "sg:city":"Getafe",
    "sg:orig_category":"Loter\u00cda Y T\u00d3mbola",
    "sg:phone":"+34 916 95 00 34",
    "sg:postcode":"28901",
    "sg:province":"Madrid",
    "wof:name":"Platero Gimenez Antonio",
    "wof:placetype":"venue"
},
  "geometry": {"coordinates":[-3.7319457531,40.300819397],"type":"Point"}
}