{
  "type": "Feature",
  "properties": {
    "addr:full":"Ctra Mas Del Jutge, 1 P.i. Masia Del Juez Valencia 46900",
    "addr:housenumber":"1",
    "addr:postcode":"46900",
    "addr:street":"Ctra Mas Del Jutge;P.I. Masia Del Juez",
    "iso:country":"ES",
    "sg:address":"Ctra Mas Del Jutge, 1",
    "sg:city":"P.i. Masia Del Juez",
    "sg:orig_category":"Confecci\u00d3n De Zapatos",
    "sg:phone":"+34 961 55 06 66",
    "sg:postcode":"46900",
    "sg:province":"Valencia",
    "sg:website":"www.beguer.com",
    "wof:name":"Calzados Beguer Hermanos S. L.",
    "wof:placetype":"venue"
},
  "geometry": {"coordinates":[-0.4623290002,39.441619873],"type":"Point"}
}