{
  "type": "Feature",
  "properties": {
    "iso:country":"ES",
    "sg:address":"Avda Iparragirre, 35",
    "sg:city":"Santurtzi",
    "sg:orig_category":"Molduras, Junquillos, Listones Y Molduras Perforadas",
    "sg:phone":"+34 944 62 21 73",
    "sg:postcode":"48980",
    "sg:province":"Vizcaya",
    "wof:name":"Iriondo Zuazo Ana",
    "wof:placetype":"venue"
},
  "geometry": {"coordinates":[-3.0374760628,43.332950592],"type":"Point"}
}