{
  "type": "Feature",
  "properties": {
    "addr:full":"Calle de Virgen Del Rocio, 43 Ibi Alicante 03440",
    "addr:housenumber":"43",
    "addr:postcode":"03440",
    "addr:street":"Calle De Virgen Del Rocio",
    "iso:country":"ES",
    "sg:address":"Calle de Virgen Del Rocio, 43",
    "sg:city":"Ibi",
    "sg:orig_category":"Plomeros",
    "sg:phone":"+34 966 55 32 52",
    "sg:postcode":"03440",
    "sg:province":"Alicante",
    "wof:name":"Comercial Fontanera S.l.",
    "wof:placetype":"venue"
},
  "geometry": {"coordinates":[-0.5804139972,38.6199035645],"type":"Point"}
}