{
  "type": "Feature",
  "properties": {
    "iso:country":"ES",
    "sg:address":"Calle de Caravaca, 17",
    "sg:city":"Valencia",
    "sg:orig_category":"Rejas Y Cortinas Met\u00c1licas",
    "sg:phone":"+34 963 69 15 43",
    "sg:postcode":"46021",
    "sg:province":"Valencia",
    "wof:name":"Talleres Hernani S. A.",
    "wof:placetype":"venue"
},
  "geometry": {"coordinates":[-0.3541330099,39.4730186462],"type":"Point"}
}