{
  "type": "Feature",
  "properties": {
    "iso:country":"ES",
    "sg:address":"Calle de Oslo, 29",
    "sg:city":"Alcorcon",
    "sg:orig_category":"Art\u00cdculos De Decoraci\u00d3n",
    "sg:phone":"+34 916 41 93 67",
    "sg:postcode":"28922",
    "sg:province":"Madrid",
    "wof:name":"Martinez Orensanz Francisco Jesus",
    "wof:placetype":"venue"
},
  "geometry": {"coordinates":[-3.8486750126,40.3419113159],"type":"Point"}
}