{
  "type": "Feature",
  "properties": {
    "iso:country":"ES",
    "sg:address":"Plaz Mayor, 21",
    "sg:city":"Ayllon",
    "sg:orig_category":"Iglesia Cat\u00d3lica",
    "sg:phone":"+34 921 55 30 28",
    "sg:postcode":"40520",
    "sg:province":"Segovia",
    "wof:name":"Obispado Segovia",
    "wof:placetype":"venue"
},
  "geometry": {"coordinates":[-3.374243021,41.4196052551],"type":"Point"}
}