{
  "type": "Feature",
  "properties": {
    "addr:full":"Calle de Lope De Vega, 16 Cuatrovientos Le\u00f3n 24400",
    "addr:housenumber":"16",
    "addr:postcode":"24400",
    "addr:street":"Calle De Lope De Vega",
    "iso:country":"ES",
    "sg:address":"Calle de Lope De Vega, 16",
    "sg:city":"Cuatrovientos",
    "sg:orig_category":"Reparaciones Y Remolcado De Veh\u00cdculos",
    "sg:phone":"+34 987 41 32 24",
    "sg:postcode":"24400",
    "sg:province":"Le\u00f3n",
    "wof:name":"Bahamonde Fernandez Antonio",
    "wof:placetype":"venue"
},
  "geometry": {"coordinates":[-6.6236467361,42.5581245422],"type":"Point"}
}