{
  "type": "Feature",
  "properties": {
    "iso:country":"ES",
    "sg:address":"Carrer de Mallorca, 494",
    "sg:city":"Barcelona",
    "sg:orig_category":"Florister\u00cdas",
    "sg:phone":"+34 932 65 00 20",
    "sg:postcode":"08013",
    "sg:province":"Barcelona",
    "wof:name":"Matas Llaveria Angel Manuel",
    "wof:placetype":"venue"
},
  "geometry": {"coordinates":[2.1799759865,41.4067802429],"type":"Point"}
}