{
  "type": "Feature",
  "properties": {
    "addr:full":"Pase General Davila, 302 Santander Cantabria 39007",
    "addr:housenumber":"302",
    "addr:postcode":"39007",
    "iso:country":"ES",
    "sg:address":"Pase General Davila, 302",
    "sg:city":"Santander",
    "sg:orig_category":"Artes Gr\u00c1ficas, Artes Pl\u00c1sticas (curso)",
    "sg:phone":"+34 942 33 76 11",
    "sg:postcode":"39007",
    "sg:province":"Cantabria",
    "sg:website":"www.graficas-iguna.com",
    "wof:name":"Graficas Igu\u00f1a S. A.",
    "wof:placetype":"venue"
},
  "geometry": {"coordinates":[-3.8276391029,43.4622383118],"type":"Point"}
}