{
  "type": "Feature",
  "properties": {
    "addr:full":"Calle de Pista (la), S/n S. Sebastian Gomera Santa Cruz De Tenerife 38800",
    "addr:postcode":"38800",
    "addr:street":"Calle De Pista La S / N S. Sebastian Gomera",
    "iso:country":"ES",
    "sg:address":"Calle de Pista (la), S/n",
    "sg:city":"S. Sebastian Gomera",
    "sg:orig_category":"Servicios Diversos",
    "sg:phone":"+34 922 14 17 21",
    "sg:postcode":"38800",
    "sg:province":"Santa Cruz De Tenerife",
    "wof:name":"Nescovic  Dragoslav",
    "wof:placetype":"venue"
},
  "geometry": {"coordinates":[-17.1107368469,28.0928421021],"type":"Point"}
}