{
  "type": "Feature",
  "properties": {
    "iso:country":"ES",
    "sg:address":"Pg Vara De Rey, 19",
    "sg:city":"Eivissa",
    "sg:orig_category":"Agentes Generales De Seguros",
    "sg:phone":"+34 971 30 12 82",
    "sg:postcode":"07800",
    "sg:province":"Islas Baleares",
    "wof:name":"Perez Lazaro Diogenes",
    "wof:placetype":"venue"
},
  "geometry": {"coordinates":[1.4326679707,38.9088554382],"type":"Point"}
}