{
  "type": "Feature",
  "properties": {
    "addr:full":"Calle de Calvario (el), 21 Esperanza Santa Cruz De Tenerife 38290",
    "addr:housenumber":"21",
    "addr:postcode":"38290",
    "addr:street":"Calle De Calvario El",
    "iso:country":"ES",
    "sg:address":"Calle de Calvario (el), 21",
    "sg:city":"Esperanza",
    "sg:orig_category":"Cr\u00cda De Animales",
    "sg:phone":"+34 922 54 87 85",
    "sg:postcode":"38290",
    "sg:province":"Santa Cruz De Tenerife",
    "wof:name":"Rodriguez Hernandez Jose Gregorio",
    "wof:placetype":"venue"
},
  "geometry": {"coordinates":[-16.3658981323,28.4530124664],"type":"Point"}
}