{
  "type": "Feature",
  "properties": {
    "addr:full":"Pl Anselm Clave, S/n S. Andreu Barca Barcelona 08740",
    "addr:housenumber":"s",
    "addr:postcode":"08740",
    "addr:street":"Pl Anselm Clave;/ N S. Andreu;Barcelona",
    "iso:country":"ES",
    "sg:address":"Pl Anselm Clave, S/n",
    "sg:city":"S. Andreu Barca",
    "sg:orig_category":"Bancos",
    "sg:phone":"+34 936 53 08 53",
    "sg:postcode":"08740",
    "sg:province":"Barcelona",
    "sg:website":"www.bancsabadell.com",
    "wof:name":"Banc Sabadell S.a.",
    "wof:placetype":"venue"
},
  "geometry": {"coordinates":[1.9743160009,41.4472579956],"type":"Point"}
}