{
  "type": "Feature",
  "properties": {
    "addr:full":"Avda Mediterraneo (del), 234 Rincon Victoria M\u00e1laga 29730",
    "addr:housenumber":"234",
    "addr:postcode":"29730",
    "addr:street":"Avda Mediterraneo Del;Ma\u0301Laga",
    "iso:country":"ES",
    "sg:address":"Avda Mediterraneo (del), 234",
    "sg:city":"Rincon Victoria",
    "sg:orig_category":"Ingenier\u00cda, Centros De Estudios (diversos)",
    "sg:phone":"+34 952 97 24 36",
    "sg:postcode":"29730",
    "sg:province":"M\u00e1laga",
    "wof:name":"Suarez Alcaide Maximino Jose",
    "wof:placetype":"venue"
},
  "geometry": {"coordinates":[-4.2754092216,36.7140007019],"type":"Point"}
}