{
  "type": "Feature",
  "properties": {
    "iso:country":"ES",
    "sg:address":"Plaz Constitucion (de La), S/n",
    "sg:city":"Miguelturra",
    "sg:orig_category":"Iglesia Cat\u00d3lica",
    "sg:phone":"+34 926 24 00 57",
    "sg:postcode":"13170",
    "sg:province":"Ciudad Real",
    "wof:name":"Parroquia Nuestra Se\u00d1ora De La Asuncion.residencia De Ancianos",
    "wof:placetype":"venue"
},
  "geometry": {"coordinates":[-3.890294075,38.9646453857],"type":"Point"}
}