{
  "type": "Feature",
  "properties": {
    "addr:full":"Carrer de Mur, 140 Martorell Barcelona 08760",
    "addr:housenumber":"140",
    "addr:postcode":"08760",
    "addr:street":"Carrer De Mur",
    "iso:country":"ES",
    "sg:address":"Carrer de Mur, 140",
    "sg:city":"Martorell",
    "sg:orig_category":"Construcci\u00d3n Mec\u00c1nica",
    "sg:phone":"+34 937 75 18 95",
    "sg:postcode":"08760",
    "sg:province":"Barcelona",
    "wof:name":"Martret Bernadas Jose",
    "wof:placetype":"venue"
},
  "geometry": {"coordinates":[1.9354330301,41.473739624],"type":"Point"}
}