{
  "type": "Feature",
  "properties": {
    "iso:country":"ES",
    "sg:address":"Calle de Isaac Peral, 12",
    "sg:city":"Albacete",
    "sg:orig_category":"M\u00c9dicos: Cirug\u00cda Urol\u00d3gica",
    "sg:phone":"+34 967 21 12 81",
    "sg:postcode":"02001",
    "sg:province":"Albacete",
    "wof:name":"Beltran Pedrero Jose Maria",
    "wof:placetype":"venue"
},
  "geometry": {"coordinates":[-1.8544880152,38.9958381653],"type":"Point"}
}