{
  "type": "Feature",
  "properties": {
    "addr:full":"Calle de Dulcinea, 1 Madrid Madrid 28020",
    "addr:housenumber":"1",
    "addr:postcode":"28020",
    "addr:street":"Calle De Dulcinea",
    "iso:country":"ES",
    "sg:address":"Calle de Dulcinea, 1",
    "sg:city":"Madrid",
    "sg:orig_category":"Librer\u00cdas",
    "sg:phone":"+34 915 34 05 78",
    "sg:postcode":"28020",
    "sg:province":"Madrid",
    "sg:website":"www.abacolibrosusados.com",
    "wof:name":"Plaza Olmos Juan Carlos",
    "wof:placetype":"venue"
},
  "geometry": {"coordinates":[-3.6998612881,40.4496231079],"type":"Point"}
}