{
  "type": "Feature",
  "properties": {
    "iso:country":"ES",
    "sg:address":"Poli Poligono Industrial Quemadas, 261",
    "sg:city":"Quemadas",
    "sg:orig_category":"Cajas Y Embalajes De Cart\u00d3n Y Papel",
    "sg:phone":"+34 957 32 67 36",
    "sg:postcode":"14014",
    "sg:province":"C\u00f3rdoba",
    "wof:name":"Bernabeu Garcia Jose Antonio",
    "wof:placetype":"venue"
},
  "geometry": {"coordinates":[-4.7624139786,37.9240608215],"type":"Point"}
}