{
  "type": "Feature",
  "properties": {
    "addr:full":"Calle de Cuestas, 9 Toledo Toledo 45006",
    "addr:housenumber":"9",
    "addr:postcode":"45006",
    "addr:street":"Calle De Cuestas",
    "iso:country":"ES",
    "sg:address":"Calle de Cuestas, 9",
    "sg:city":"Toledo",
    "sg:orig_category":"Contenedores (mercanc\u00cdas)",
    "sg:phone":"+34 925 22 00 16",
    "sg:postcode":"45006",
    "sg:province":"Toledo",
    "wof:name":"Alonso Fernandez Vidal",
    "wof:placetype":"venue"
},
  "geometry": {"coordinates":[-4.0047683716,39.860004425],"type":"Point"}
}