{
  "type": "Feature",
  "properties": {
    "addr:full":"Carrer de Pablo Picasso (de), 24 Salou Tarragona 43840",
    "addr:housenumber":"24",
    "addr:postcode":"43840",
    "addr:street":"Carrer De Pablo Picasso De",
    "iso:country":"ES",
    "sg:address":"Carrer de Pablo Picasso (de), 24",
    "sg:city":"Salou",
    "sg:orig_category":"Asesor\u00cdas Y Estudios Financieros",
    "sg:phone":"+34 977 38 10 72",
    "sg:postcode":"43840",
    "sg:province":"Tarragona",
    "wof:name":"Espasa Arana Jorge",
    "wof:placetype":"venue"
},
  "geometry": {"coordinates":[1.1512600183,41.075630188],"type":"Point"}
}