{
  "type": "Feature",
  "properties": {
    "addr:full":"Pl Virrei Amat, 6 Barcelona Barcelona 08031",
    "addr:housenumber":"6",
    "addr:postcode":"08031",
    "addr:street":"Pl Virrei Amat",
    "iso:country":"ES",
    "sg:address":"Pl Virrei Amat, 6",
    "sg:city":"Barcelona",
    "sg:orig_category":"M\u00c9dicos: Oftalmolog\u00cda",
    "sg:phone":"+34 933 57 08 08",
    "sg:postcode":"08031",
    "sg:province":"Barcelona",
    "wof:name":"Arango Garcia German",
    "wof:placetype":"venue"
},
  "geometry": {"coordinates":[2.17441535,41.4301452637],"type":"Point"}
}