{
  "type": "Feature",
  "properties": {
    "addr:full":"Avenida De Penela, 36 Ortigueira A Coru\u00f1a 15330",
    "addr:housenumber":"36",
    "addr:postcode":"15330",
    "addr:street":"Avenida De Penela;Corun\u0303A",
    "iso:country":"ES",
    "sg:address":"Avenida De Penela, 36",
    "sg:city":"Ortigueira",
    "sg:orig_category":"Sindicatos De Trabajadores",
    "sg:phone":"+34 981 42 20 11",
    "sg:postcode":"15330",
    "sg:province":"A Coru\u00f1a",
    "wof:name":"Unions Agrarias Do Ribeiro",
    "wof:placetype":"venue"
},
  "geometry": {"coordinates":[-7.8468871117,43.6875534058],"type":"Point"}
}