{
  "type": "Feature",
  "properties": {
    "addr:full":"Calle de Avecilla, 5 Madrid Madrid 28025",
    "addr:housenumber":"5",
    "addr:postcode":"28025",
    "addr:street":"Calle De Avecilla",
    "iso:country":"ES",
    "sg:address":"Calle de Avecilla, 5",
    "sg:city":"Madrid",
    "sg:orig_category":"Carnicer\u00cdas, Carnicer\u00cdas",
    "sg:phone":"+34 914 66 44 03",
    "sg:postcode":"28025",
    "sg:province":"Madrid",
    "wof:name":"Rodera Moran Tomas",
    "wof:placetype":"venue"
},
  "geometry": {"coordinates":[-3.736191988,40.3882980347],"type":"Point"}
}