{
  "type": "Feature",
  "properties": {
    "iso:country":"ES",
    "sg:address":"Calle de Pegaso, 15",
    "sg:city":"Alacant",
    "sg:orig_category":"Tintorer\u00cdas, Limpieza En Seco",
    "sg:phone":"+34 965 28 49 94",
    "sg:postcode":"03007",
    "sg:province":"Alicante",
    "wof:name":"Cleaning Plus Alicante S.l.",
    "wof:placetype":"venue"
},
  "geometry": {"coordinates":[-0.5137630105,38.3443984985],"type":"Point"}
}