{
  "type": "Feature",
  "properties": {
    "addr:full":"Ctra. Eivissa S. Antoni, Km. 0003,3 Puig D'en Valls Islas Baleares 07819",
    "addr:postcode":"07819",
    "addr:street":"Ctra. Eivissa S. Antoni Km. 0003,3 Puig",
    "iso:country":"ES",
    "sg:address":"Ctra. Eivissa S. Antoni, Km. 0003,3",
    "sg:city":"Puig D'en Valls",
    "sg:orig_category":"Material Y Equipo Para Panader\u00cdas Y Pasteler\u00cdas",
    "sg:phone":"+34 971 19 08 06",
    "sg:postcode":"07819",
    "sg:province":"Islas Baleares",
    "wof:name":"Mapripan S.l.",
    "wof:placetype":"venue"
},
  "geometry": {"coordinates":[2.9117100239,39.6136398315],"type":"Point"}
}