{
  "type": "Feature",
  "properties": {
    "iso:country":"ES",
    "sg:address":"Calle de Catalu\u00d1a, 23",
    "sg:city":"Pto. Rosario",
    "sg:orig_category":"Laboratorios Dentales",
    "sg:phone":"+34 928 53 07 45",
    "sg:postcode":"35600",
    "sg:province":"Las Palmas",
    "wof:name":"Dentant S.l.",
    "wof:placetype":"venue"
},
  "geometry": {"coordinates":[-13.8689508438,28.5022468567],"type":"Point"}
}