{
  "type": "Feature",
  "properties": {
    "iso:country":"ES",
    "sg:address":"Calle de Mateo Samaniego, 4",
    "sg:city":"Navalmoral Mata",
    "sg:orig_category":"Cristaler\u00cdas",
    "sg:phone":"+34 927 53 18 69",
    "sg:postcode":"10300",
    "sg:province":"C\u00e1ceres",
    "wof:name":"Ferreteria Morala S.l.",
    "wof:placetype":"venue"
},
  "geometry": {"coordinates":[-5.5375142097,39.8904418945],"type":"Point"}
}