{
  "type": "Feature",
  "properties": {
    "iso:country":"ES",
    "sg:address":"San Leonardo, 30",
    "sg:city":"Albox",
    "sg:orig_category":"Alfarer\u00cda",
    "sg:phone":"+34 950 12 06 52",
    "sg:postcode":"04800",
    "sg:province":"Almer\u00eda",
    "wof:name":"Alfareria Los Puntas, C.b.",
    "wof:placetype":"venue"
},
  "geometry": {"coordinates":[-2.1397094727,37.3872451782],"type":"Point"}
}