{
  "type": "Feature",
  "properties": {
    "addr:full":"Carr De Pius Xii, 20 Ontinyent Valencia 46870",
    "addr:housenumber":"20",
    "addr:postcode":"46870",
    "addr:street":"Carr De Pius Xii",
    "iso:country":"ES",
    "sg:address":"Carr De Pius Xii, 20",
    "sg:city":"Ontinyent",
    "sg:classifiers":[
        {
            "category":"Autos & Motor Vehicles",
            "subcategory":"Automobile Sales",
            "type":"Retail Goods"
        }
    ],
    "sg:phone":"+34 962 38 18 10",
    "sg:postcode":"46870",
    "sg:province":"Valencia",
    "wof:name":"Autoescuela Eco S.l.",
    "wof:placetype":"venue"
},
  "geometry": {"coordinates":[-0.6006973982,38.8232383728],"type":"Point"}
}