{
  "type": "Feature",
  "properties": {
    "iso:country":"ES",
    "sg:address":"Av Can Roses, 14",
    "sg:city":"Rubi",
    "sg:orig_category":"Construcci\u00d3n Mec\u00c1nica",
    "sg:phone":"+34 936 99 12 07",
    "sg:postcode":"08191",
    "sg:province":"Barcelona",
    "wof:name":"Mecanica Busquets S.a.",
    "wof:placetype":"venue"
},
  "geometry": {"coordinates":[2.041809082,41.504360199],"type":"Point"}
}