{
  "type": "Feature",
  "properties": {
    "iso:country":"ES",
    "sg:address":"Plaz Tinajones, 10",
    "sg:city":"Talavera Reina",
    "sg:orig_category":"Transportes En Cisternas",
    "sg:phone":"+34 925 80 20 09",
    "sg:postcode":"45600",
    "sg:province":"Toledo",
    "wof:name":"Garcia Planchuelo Pablo",
    "wof:placetype":"venue"
},
  "geometry": {"coordinates":[-4.8326292038,39.9584884644],"type":"Point"}
}