{
  "type": "Feature",
  "properties": {
    "iso:country":"ES",
    "sg:address":"Barr Atxukarro, 16",
    "sg:city":"Arrigorriaga",
    "sg:orig_category":"Montaje (empresas De)",
    "sg:phone":"+34 944 40 14 69",
    "sg:postcode":"48480",
    "sg:province":"Vizcaya",
    "wof:name":"Minaycu, S.l.",
    "wof:placetype":"venue"
},
  "geometry": {"coordinates":[-2.8910260201,43.213848114],"type":"Point"}
}