{
  "type": "Feature",
  "properties": {
    "iso:country":"ES",
    "sg:address":"Calle de Amargura, 26",
    "sg:city":"Zamora",
    "sg:orig_category":"Agencias Y Agentes Comerciales, Representantes",
    "sg:phone":"+34 980 52 07 39",
    "sg:postcode":"49007",
    "sg:province":"Zamora",
    "wof:name":"Cabello Anton Jose Luis",
    "wof:placetype":"venue"
},
  "geometry": {"coordinates":[-5.7447252274,41.5099105835],"type":"Point"}
}