{
  "type": "Feature",
  "properties": {
    "iso:country":"ES",
    "sg:address":"Calle de Garcia Cabrelles, 16",
    "sg:city":"Melilla",
    "sg:orig_category":"Mercados De Productos Alimenticios",
    "sg:phone":"+34 952 68 11 67",
    "sg:postcode":"52002",
    "sg:province":"Melilla",
    "wof:name":"Ciudad Autonoma De Melilla",
    "wof:placetype":"venue"
},
  "geometry": {"coordinates":[-2.9440610409,35.2953529358],"type":"Point"}
}