{
  "type": "Feature",
  "properties": {
    "addr:full":"Av Mas Romeu, 12 Mas Romeu Residencial Girona 17310",
    "addr:housenumber":"12",
    "addr:postcode":"17310",
    "addr:street":"Av Mas Romeu",
    "iso:country":"ES",
    "sg:address":"Av Mas Romeu, 12",
    "sg:city":"Mas Romeu Residencial",
    "sg:orig_category":"Higiene, Belleza: Art\u00cdculos (al Por Menor)",
    "sg:phone":"+34 972 36 88 99",
    "sg:postcode":"17310",
    "sg:province":"Girona",
    "wof:name":"Casas Comas Maria Rosa",
    "wof:placetype":"venue"
},
  "geometry": {"coordinates":[2.846834898,41.6981697083],"type":"Point"}
}