{
  "type": "Feature",
  "properties": {
    "addr:full":"Poli Industrial De Lo Tacon, S/n Union Murcia 30360",
    "addr:housenumber":"s / n",
    "addr:postcode":"30360",
    "addr:street":"Tacon",
    "iso:country":"ES",
    "sg:address":"Poli Industrial De Lo Tacon, S/n",
    "sg:city":"Union",
    "sg:orig_category":"Calderer\u00cda",
    "sg:phone":"+34 968 56 01 68",
    "sg:postcode":"30360",
    "sg:province":"Murcia",
    "wof:name":"Antonio Sanchez Roca Y Otros Cdad",
    "wof:placetype":"venue"
},
  "geometry": {"coordinates":[-1.1298867464,37.9834747314],"type":"Point"}
}