{
  "type": "Feature",
  "properties": {
    "addr:full":"C/ Solars, 40 Elche Alicante 03203",
    "addr:housenumber":"40",
    "addr:postcode":"03203",
    "addr:street":"C / Solars",
    "iso:country":"ES",
    "sg:address":"C/ Solars, 40",
    "sg:city":"Elche",
    "sg:orig_category":"Asociaciones, Organismos Culturales Y Socioeducativos",
    "sg:phone":"+34 965 42 11 09",
    "sg:postcode":"03203",
    "sg:province":"Alicante",
    "wof:name":"Centre Cultural Margallo",
    "wof:placetype":"venue"
},
  "geometry": {"coordinates":[-0.6698989868,38.2703514099],"type":"Point"}
}