{
  "type": "Feature",
  "properties": {
    "iso:country":"ES",
    "sg:address":"Calle de Manrique, 24",
    "sg:city":"Malaga",
    "sg:orig_category":"Caf\u00c9s, Bares, Cervecer\u00cdas",
    "sg:phone":"+34 952 26 95 05",
    "sg:postcode":"29013",
    "sg:province":"M\u00e1laga",
    "wof:name":"Paramio Dominguez Jose Carlos",
    "wof:placetype":"venue"
},
  "geometry": {"coordinates":[-4.4159579277,36.7308959961],"type":"Point"}
}