{
  "type": "Feature",
  "properties": {
    "addr:full":"Plaz Pelayo Quintero, 8 Ucles Cuenca 16450",
    "addr:housenumber":"8",
    "addr:postcode":"16450",
    "addr:street":"Plaz;Quintero",
    "iso:country":"ES",
    "sg:address":"Plaz Pelayo Quintero, 8",
    "sg:city":"Ucles",
    "sg:orig_category":"Farmacias",
    "sg:phone":"+34 969 13 51 11",
    "sg:postcode":"16450",
    "sg:province":"Cuenca",
    "wof:name":"Palomar Gomez Maria Jose",
    "wof:placetype":"venue"
},
  "geometry": {"coordinates":[-2.861479044,39.9803504944],"type":"Point"}
}