{
  "type": "Feature",
  "properties": {
    "addr:full":"Calle de Atenas, 1 Torrejon Ardoz Madrid 28850",
    "addr:housenumber":"1",
    "addr:postcode":"28850",
    "addr:street":"Calle De Atenas",
    "iso:country":"ES",
    "sg:address":"Calle de Atenas, 1",
    "sg:city":"Torrejon Ardoz",
    "sg:classifiers":[
        {
            "category":"Taxi",
            "type":"Transportation"
        }
    ],
    "sg:phone":"+34 916 75 27 19",
    "sg:postcode":"28850",
    "sg:province":"Madrid",
    "wof:name":"Tartaro Navamuel Rafael",
    "wof:placetype":"venue"
},
  "geometry": {"coordinates":[-3.4688630104,40.4584007263],"type":"Point"}
}