{
  "type": "Feature",
  "properties": {
    "iso:country":"ES",
    "sg:address":"Plaz Diputacion, 1",
    "sg:city":"Errenteria",
    "sg:orig_category":"Pintura Y Barniz (al Por Menor)",
    "sg:phone":"+34 943 51 91 00",
    "sg:postcode":"20100",
    "sg:province":"Guip\u00f9zcoa",
    "wof:name":"Almacenes Iztieta S. A.",
    "wof:placetype":"venue"
},
  "geometry": {"coordinates":[-1.9023790359,43.3151741028],"type":"Point"}
}