{
  "type": "Feature",
  "properties": {
    "addr:full":"Calle de Espronceda, 32 Madrid Madrid 28003",
    "addr:housenumber":"32",
    "addr:postcode":"madrid;28003",
    "addr:street":"Calle De Espronceda",
    "iso:country":"ES",
    "sg:address":"Calle de Espronceda, 32",
    "sg:city":"Madrid",
    "sg:orig_category":"Sindicatos Y Colegios Profesionales",
    "sg:phone":"+34 914 42 08 97",
    "sg:postcode":"28003",
    "sg:province":"Madrid",
    "wof:name":"Asociacion Nacional De Informadores Graficos De Prensa",
    "wof:placetype":"venue"
},
  "geometry": {"coordinates":[-3.6950902939,40.4405021667],"type":"Point"}
}