{
  "type": "Feature",
  "properties": {
    "addr:full":"Calle de Carretera De Salamanca, Km. 0023,0 Arroyo De La Encomienda Valladolid 47195",
    "addr:housenumber":"km.",
    "addr:postcode":"47195",
    "addr:street":"Calle De Carretera De Salamanca;0023,0",
    "iso:country":"ES",
    "sg:address":"Calle de Carretera De Salamanca, Km. 0023,0",
    "sg:city":"Arroyo De La Encomienda",
    "sg:orig_category":"Embalajes",
    "sg:phone":"+34 983 40 89 50",
    "sg:postcode":"47195",
    "sg:province":"Valladolid",
    "wof:name":"Smurfit Kappa Espa\u00f1a S.a.",
    "wof:placetype":"venue"
},
  "geometry": {"coordinates":[-4.7954587936,41.6099090576],"type":"Point"}
}