{
  "type": "Feature",
  "properties": {
    "iso:country":"ES",
    "sg:address":"Carr Francesc Estrabau, 40",
    "sg:city":"Calella",
    "sg:orig_category":"Hoteles",
    "sg:phone":"+34 972 61 45 00",
    "sg:postcode":"17210",
    "sg:province":"Girona",
    "wof:name":"Agusti Rovira Margarita",
    "wof:placetype":"venue"
},
  "geometry": {"coordinates":[3.1822004318,41.8876457214],"type":"Point"}
}