{
  "type": "Feature",
  "properties": {
    "iso:country":"ES",
    "sg:address":"Calle de Nueva, 13",
    "sg:city":"Mairena Aljarafe",
    "sg:orig_category":"Quincaller\u00cda (al Por Menor)",
    "sg:phone":"+34 955 60 94 20",
    "sg:postcode":"41927",
    "sg:province":"Sevilla",
    "wof:name":"Bricolaje Y Ferreteria Castillo S.l.",
    "wof:placetype":"venue"
},
  "geometry": {"coordinates":[-6.0652189255,37.3445968628],"type":"Point"}
}