{
  "type": "Feature",
  "properties": {
    "iso:country":"ES",
    "sg:address":"Calle de San Pio X, 25",
    "sg:city":"Valencia",
    "sg:orig_category":"Maquinaria Para Industrias Diversas",
    "sg:phone":"+34 963 57 05 18",
    "sg:postcode":"46017",
    "sg:province":"Valencia",
    "wof:name":"Esteban Gimeno Amalio",
    "wof:placetype":"venue"
},
  "geometry": {"coordinates":[-0.3896020055,39.4441795349],"type":"Point"}
}