{
  "type": "Feature",
  "properties": {
    "iso:country":"ES",
    "sg:address":"C/ Misteri, 10",
    "sg:city":"Inca",
    "sg:orig_category":"Plomeros",
    "sg:phone":"+34 971 50 55 32",
    "sg:postcode":"07300",
    "sg:province":"Islas Baleares",
    "wof:name":"Fontur Servicios Y Montajes S.l.",
    "wof:placetype":"venue"
},
  "geometry": {"coordinates":[2.9097549915,39.7221641541],"type":"Point"}
}