{
  "type": "Feature",
  "properties": {
    "iso:country":"ES",
    "sg:address":"Carrer de Ausias Marc, 43",
    "sg:city":"Barcelona",
    "sg:orig_category":"Molduras, Junquillos, Listones Y Molduras Perforadas",
    "sg:phone":"+34 932 65 36 93",
    "sg:postcode":"08010",
    "sg:province":"Barcelona",
    "wof:name":"Hermanos Llort C.b.",
    "wof:placetype":"venue"
},
  "geometry": {"coordinates":[2.1768510342,41.3924674988],"type":"Point"}
}