{
  "type": "Feature",
  "properties": {
    "addr:full":"Avda Carlos Azcarraga, 34 Lugo Lugo 27003",
    "addr:housenumber":"34",
    "addr:postcode":"27003",
    "addr:street":"Avda Carlos Azcarraga",
    "iso:country":"ES",
    "sg:address":"Avda Carlos Azcarraga, 34",
    "sg:city":"Lugo",
    "sg:orig_category":"Peluquer\u00cdas, Peluquer\u00cda Mixta",
    "sg:phone":"+34 982 23 15 70",
    "sg:postcode":"27003",
    "sg:province":"Lugo",
    "wof:name":"Crechas Perruqueiros Cb",
    "wof:placetype":"venue"
},
  "geometry": {"coordinates":[-7.5490221977,43.0160598755],"type":"Point"}
}