{
  "type": "Feature",
  "properties": {
    "iso:country":"ES",
    "sg:address":"Avda Jaizubia Hiribidea, S/n",
    "sg:city":"Irun",
    "sg:orig_category":"Comidas Por Encargo, Organizaci\u00d3n De Recepciones",
    "sg:phone":"+34 943 61 77 49",
    "sg:postcode":"20305",
    "sg:province":"Guip\u00f9zcoa",
    "wof:name":"Aramark S.l.",
    "wof:placetype":"venue"
},
  "geometry": {"coordinates":[-1.8245090246,43.3302764893],"type":"Point"}
}