{
  "type": "Feature",
  "properties": {
    "iso:country":"ES",
    "sg:address":"Carrer de Lluis Vives, 45",
    "sg:city":"Granollers",
    "sg:orig_category":"Reposter\u00cdas",
    "sg:phone":"+34 938 79 54 38",
    "sg:postcode":"08402",
    "sg:province":"Barcelona",
    "wof:name":"Fernandez Fernandez Inmaculada",
    "wof:placetype":"venue"
},
  "geometry": {"coordinates":[2.2960789204,41.6100845337],"type":"Point"}
}