{
  "type": "Feature",
  "properties": {
    "iso:country":"ES",
    "sg:address":"Calle de Doctor Marco Merenciano, 22",
    "sg:city":"Valencia",
    "sg:orig_category":"Bisuter\u00cda, Joyer\u00cda, Relojer\u00cda (al Por Menor)",
    "sg:phone":"+34 963 47 98 25",
    "sg:postcode":"46025",
    "sg:province":"Valencia",
    "wof:name":"Climent Gomez Jose Francisco",
    "wof:placetype":"venue"
},
  "geometry": {"coordinates":[-0.3812249005,39.4916381836],"type":"Point"}
}