{
  "type": "Feature",
  "properties": {
    "iso:country":"ES",
    "sg:address":"Ptge A Torrandell (par), 8",
    "sg:city":"Palma",
    "sg:orig_category":"Ropa Para Beb\u00c9s Y Ni\u00d1os (confecci\u00d3n, Al Por Mayor)",
    "sg:phone":"+34 971 72 19 84",
    "sg:postcode":"07003",
    "sg:province":"Islas Baleares",
    "wof:name":"Coll Cifre Bartolome",
    "wof:placetype":"venue"
},
  "geometry": {"coordinates":[2.6493999958,39.5753059387],"type":"Point"}
}