{
  "type": "Feature",
  "properties": {
    "iso:country":"ES",
    "sg:address":"Calle de Rio (el), 31",
    "sg:city":"Velez-malaga",
    "sg:orig_category":"Carnicer\u00cdas, Carnicer\u00cdas",
    "sg:phone":"+34 952 50 04 72",
    "sg:postcode":"29700",
    "sg:province":"M\u00e1laga",
    "wof:name":"Industrias Carnicas Espejo S.l.",
    "wof:placetype":"venue"
},
  "geometry": {"coordinates":[-4.1083488464,36.7807846069],"type":"Point"}
}