{
  "type": "Feature",
  "properties": {
    "iso:country":"ES",
    "sg:address":"Rond Outeiro, 15",
    "sg:city":"Coru\u00d1a",
    "sg:orig_category":"Asesor\u00cdas Y Estudios Financieros",
    "sg:phone":"+34 981 29 28 10",
    "sg:postcode":"15006",
    "sg:province":"La Coru\u00f1a",
    "wof:name":"Prieto Tamarit Manuel",
    "wof:placetype":"venue"
},
  "geometry": {"coordinates":[-8.3881797791,43.3491401672],"type":"Point"}
}