{
  "type": "Feature",
  "properties": {
    "addr:full":"Calle de Hernan Cortes, 14 Santa Amalia Badajoz 06410",
    "addr:housenumber":"14",
    "addr:postcode":"06410",
    "addr:street":"Calle De Hernan Cortes",
    "iso:country":"ES",
    "sg:address":"Calle de Hernan Cortes, 14",
    "sg:city":"Santa Amalia",
    "sg:orig_category":"Negocio De Materiales De Construcci\u00d3n",
    "sg:phone":"+34 924 82 00 63",
    "sg:postcode":"06410",
    "sg:province":"Badajoz",
    "wof:name":"Carrascosa Sanchez S.l.",
    "wof:placetype":"venue"
},
  "geometry": {"coordinates":[-6.0078649521,39.0089836121],"type":"Point"}
}