{
  "type": "Feature",
  "properties": {
    "addr:full":"Calle de Naves, 7 Madrid Madrid 28005",
    "addr:housenumber":"7",
    "addr:postcode":"madrid;28005",
    "addr:street":"Calle De Naves",
    "iso:country":"ES",
    "sg:address":"Calle de Naves, 7",
    "sg:city":"Madrid",
    "sg:orig_category":"Centros Empresariales",
    "sg:phone":"+34 915 17 40 41",
    "sg:postcode":"28005",
    "sg:province":"Madrid",
    "wof:name":"Martinez Martin Carmen",
    "wof:placetype":"venue"
},
  "geometry": {"coordinates":[-3.7069211006,40.398059845],"type":"Point"}
}