{
  "type": "Feature",
  "properties": {
    "addr:full":"Avda Paseo De Almeria, 4 Almeria Almer\u00eda 04001",
    "addr:housenumber":"4",
    "addr:postcode":"04001",
    "addr:street":"Avda Paseo De Almeria",
    "iso:country":"ES",
    "sg:address":"Avda Paseo De Almeria, 4",
    "sg:city":"Almeria",
    "sg:orig_category":"Electrodom\u00c9sticos (al Por Menor)",
    "sg:phone":"+34 950 25 81 15",
    "sg:postcode":"04001",
    "sg:province":"Almer\u00eda",
    "wof:name":"Montes Somodevilla Jose",
    "wof:placetype":"venue"
},
  "geometry": {"coordinates":[-2.4608390331,36.8422698975],"type":"Point"}
}