{
  "type": "Feature",
  "properties": {
    "addr:full":"Cno. Vjo. Del Saler, 7 Pinedo Valencia 46012",
    "addr:housenumber":"7",
    "addr:postcode":"46012",
    "addr:street":"Vjo.;Saler",
    "iso:country":"ES",
    "sg:address":"Cno. Vjo. Del Saler, 7",
    "sg:city":"Pinedo",
    "sg:orig_category":"Teatros Y Salas De Espect\u00c1culos",
    "sg:phone":"+34 963 24 81 72",
    "sg:postcode":"46012",
    "sg:province":"Valencia",
    "wof:name":"Canal De Pinedo S.a.",
    "wof:placetype":"venue"
},
  "geometry": {"coordinates":[-0.2913190126,39.3012657166],"type":"Point"}
}