{
  "type": "Feature",
  "properties": {
    "iso:country":"ES",
    "sg:address":"Calle de Gonzalez De La Vega, 2",
    "sg:city":"Ceuta",
    "sg:orig_category":"Confecci\u00d3n De Trajes Para Se\u00d1oras",
    "sg:phone":"+34 956 51 30 55",
    "sg:postcode":"51001",
    "sg:province":"Ceuta",
    "wof:name":"Fersan Ceuta S.l.",
    "wof:placetype":"venue"
},
  "geometry": {"coordinates":[-5.3093914986,35.8869895935],"type":"Point"}
}