{
  "type": "Feature",
  "properties": {
    "addr:full":"Calle de Conde De Benavente, 5 Valladolid Valladolid 47003",
    "addr:housenumber":"5",
    "addr:postcode":"47003",
    "addr:street":"Calle De Conde De Benavente",
    "iso:country":"ES",
    "sg:address":"Calle de Conde De Benavente, 5",
    "sg:city":"Valladolid",
    "sg:orig_category":"Carnicer\u00cdas, Carnicer\u00cdas",
    "sg:phone":"+34 983 35 32 98",
    "sg:postcode":"47003",
    "sg:province":"Valladolid",
    "wof:name":"Perez Bermejo Pedro",
    "wof:placetype":"venue"
},
  "geometry": {"coordinates":[-4.7309775352,41.6581459045],"type":"Point"}
}