{
  "type": "Feature",
  "properties": {
    "iso:country":"ES",
    "sg:address":"Vena Sarreda, 39",
    "sg:city":"Vilobi D'onyar",
    "sg:orig_category":"Agricultores, Agricultores",
    "sg:phone":"+34 972 47 30 60",
    "sg:postcode":"17185",
    "sg:province":"Girona",
    "wof:name":"Busquets I Talleda S.l.",
    "wof:placetype":"venue"
},
  "geometry": {"coordinates":[2.8187398911,41.9808616638],"type":"Point"}
}