{
  "type": "Feature",
  "properties": {
    "iso:country":"ES",
    "sg:address":"Vilamaior, S/n",
    "sg:city":"Vilamaior",
    "sg:orig_category":"Cooperativas Agr\u00cdcolas",
    "sg:phone":"+34 982 16 01 96",
    "sg:postcode":"27233",
    "sg:province":"Lugo",
    "wof:name":"Sociedad Agraria De Transformacion",
    "wof:placetype":"venue"
},
  "geometry": {"coordinates":[-7.5845899582,43.0072364807],"type":"Point"}
}