{
  "type": "Feature",
  "properties": {
    "addr:full":"Calle de Valdivieso, 6 Madrid Madrid 28023",
    "addr:housenumber":"6",
    "addr:postcode":"28023",
    "addr:street":"Calle De Valdivieso",
    "iso:country":"ES",
    "sg:address":"Calle de Valdivieso, 6",
    "sg:city":"Madrid",
    "sg:orig_category":"Artes Gr\u00c1ficas, Artes Pl\u00c1sticas (curso)",
    "sg:phone":"+34 913 57 12 20",
    "sg:postcode":"28023",
    "sg:province":"Madrid",
    "wof:name":"Morales Gamo Gemma",
    "wof:placetype":"venue"
},
  "geometry": {"coordinates":[-3.7804040909,40.4586410522],"type":"Point"}
}