{
  "type": "Feature",
  "properties": {
    "addr:full":"Calle de Azucenas, 27 Madrid Madrid 28039",
    "addr:housenumber":"27",
    "addr:postcode":"madrid;28039",
    "addr:street":"Calle De Azucenas",
    "iso:country":"ES",
    "sg:address":"Calle de Azucenas, 27",
    "sg:city":"Madrid",
    "sg:orig_category":"Comercio, Reparaci\u00d3n De Motocicletas, Bicicletas Y Piezas Sueltas",
    "sg:phone":"+34 915 79 59 97",
    "sg:postcode":"28039",
    "sg:province":"Madrid",
    "wof:name":"Motos Uge S. A.",
    "wof:placetype":"venue"
},
  "geometry": {"coordinates":[-3.6997027397,40.4637069702],"type":"Point"}
}