{
  "type": "Feature",
  "properties": {
    "addr:full":"Pase Santo Cristo, 15 Cazorla Ja\u00e9n 23470",
    "addr:housenumber":"15",
    "addr:postcode":"23470",
    "addr:street":"Santo Cristo",
    "iso:country":"ES",
    "sg:address":"Pase Santo Cristo, 15",
    "sg:city":"Cazorla",
    "sg:classifiers":[
        {
            "category":"Casinos & Gambling",
            "type":"Entertainment"
        }
    ],
    "sg:phone":"+34 953 72 03 77",
    "sg:postcode":"23470",
    "sg:province":"Ja\u00e9n",
    "sg:tags":[
        "locale",
        "de",
        "juego"
    ],
    "wof:name":"Ludoteca El Bosque, S.l.l.",
    "wof:placetype":"venue"
},
  "geometry": {"coordinates":[-2.8776638508,37.8798332214],"type":"Point"}
}