{
  "type": "Feature",
  "properties": {
    "addr:full":"Ctra Doctor Robert, 2 Vendrell Tarragona 43700",
    "addr:housenumber":"2",
    "addr:postcode":"43700",
    "addr:street":"Ctra Doctor Robert",
    "iso:country":"ES",
    "sg:address":"Ctra Doctor Robert, 2",
    "sg:city":"Vendrell",
    "sg:orig_category":"Muebles, Minoristas",
    "sg:phone":"+34 977 66 03 59",
    "sg:postcode":"43700",
    "sg:province":"Tarragona",
    "wof:name":"Gasol Escola Josefa",
    "wof:placetype":"venue"
},
  "geometry": {"coordinates":[1.5358300209,41.2210617065],"type":"Point"}
}