{
  "type": "Feature",
  "properties": {
    "addr:full":"Carr Music Vivaldi, 12 Lleida Lleida 25003",
    "addr:housenumber":"12",
    "addr:postcode":"25003",
    "addr:street":"Vivaldi",
    "iso:country":"ES",
    "sg:address":"Carr Music Vivaldi, 12",
    "sg:city":"Lleida",
    "sg:orig_category":"Cristaler\u00cdas",
    "sg:phone":"+34 973 26 22 55",
    "sg:postcode":"25003",
    "sg:province":"Lleida",
    "wof:name":"Cristalsegre S.l.",
    "wof:placetype":"venue"
},
  "geometry": {"coordinates":[0.6129670143,41.6111412048],"type":"Point"}
}