{
  "type": "Feature",
  "properties": {
    "addr:full":"Calle de Cultura, 11 Molina Segura Murcia 30500",
    "addr:housenumber":"11",
    "addr:postcode":"30500",
    "addr:street":"Calle De Cultura",
    "iso:country":"ES",
    "sg:address":"Calle de Cultura, 11",
    "sg:city":"Molina Segura",
    "sg:orig_category":"Inmobiliaria (agencias)",
    "sg:phone":"+34 968 64 08 46",
    "sg:postcode":"30500",
    "sg:province":"Murcia",
    "wof:name":"Jose Pastor Hernandez S.a.",
    "wof:placetype":"venue"
},
  "geometry": {"coordinates":[-1.2116526365,38.0510482788],"type":"Point"}
}