{
  "type": "Feature",
  "properties": {
    "addr:full":"Calle de Juan Fortuny, 27 San Pedro Alcantara M\u00e1laga 29670",
    "addr:housenumber":"27",
    "addr:postcode":"29670",
    "addr:street":"Calle De Juan Fortuny",
    "iso:country":"ES",
    "sg:address":"Calle de Juan Fortuny, 27",
    "sg:city":"San Pedro Alcantara",
    "sg:orig_category":"Laboratorios Y Trabajos De Fotograf\u00cda, V\u00cddeo Y Cine",
    "sg:phone":"+34 952 78 08 48",
    "sg:postcode":"29670",
    "sg:province":"M\u00e1laga",
    "wof:name":"Sancho Fernandez Josefina",
    "wof:placetype":"venue"
},
  "geometry": {"coordinates":[-4.9864859581,36.4855194092],"type":"Point"}
}