{
  "type": "Feature",
  "properties": {
    "addr:full":"Ctra. Medina, Km. 0013,5 Pto Real C\u00e1diz 11510",
    "addr:postcode":"11510",
    "addr:street":"Ctra. Medina Km. 0013,5;Ca\u0301Diz",
    "iso:country":"ES",
    "sg:address":"Ctra. Medina, Km. 0013,5",
    "sg:city":"Pto Real",
    "sg:orig_category":"Agricultores, Agricultores",
    "sg:phone":"+34 956 23 05 64",
    "sg:postcode":"11510",
    "sg:province":"C\u00e1diz",
    "wof:name":"Explotacion Oxona S.l.",
    "wof:placetype":"venue"
},
  "geometry": {"coordinates":[-6.1980991364,36.5308990479],"type":"Point"}
}