{
  "type": "Feature",
  "properties": {
    "addr:full":"Calle de Texillo, 3 Montalbo Cuenca 16440",
    "addr:housenumber":"3",
    "addr:postcode":"16440",
    "addr:street":"Calle De Texillo",
    "iso:country":"ES",
    "sg:address":"Calle de Texillo, 3",
    "sg:city":"Montalbo",
    "sg:orig_category":"Contenedores (mercanc\u00cdas)",
    "sg:phone":"+34 969 13 02 03",
    "sg:postcode":"16440",
    "sg:province":"Cuenca",
    "wof:name":"Illescas Ramirez Jose Antonio",
    "wof:placetype":"venue"
},
  "geometry": {"coordinates":[-2.671241045,39.8793792725],"type":"Point"}
}