{
  "type": "Feature",
  "properties": {
    "iso:country":"ES",
    "sg:address":"Calle de Santa Brigida, 15",
    "sg:city":"Madrid",
    "sg:orig_category":"Confecci\u00d3n De Guantes",
    "sg:phone":"+34 915 21 24 09",
    "sg:postcode":"28004",
    "sg:province":"Madrid",
    "wof:name":"Torres Almera C.b.",
    "wof:placetype":"venue"
},
  "geometry": {"coordinates":[-3.6992425919,40.424446106],"type":"Point"}
}