{
  "type": "Feature",
  "properties": {
    "addr:full":"Crrtra De Huescar, Km. 0002,0 Cullar Granada 18850",
    "addr:postcode":"18850",
    "addr:street":"Km. 0002,0",
    "iso:country":"ES",
    "sg:address":"Crrtra De Huescar, Km. 0002,0",
    "sg:city":"Cullar",
    "sg:orig_category":"Venta, Instalaci\u00d3n, Mantenimiento De Chimeneas De Interior Y Accesorios",
    "sg:phone":"+34 958 73 08 84",
    "sg:postcode":"18850",
    "sg:province":"Granada",
    "wof:name":"Chimeneas Garci S.l.",
    "wof:placetype":"venue"
},
  "geometry": {"coordinates":[-2.5776090622,37.5830955505],"type":"Point"}
}