{
  "type": "Feature",
  "properties": {
    "iso:country":"ES",
    "sg:address":"Cust Pi\u00d1edo, 2",
    "sg:city":"Zamora",
    "sg:orig_category":"Plomeros",
    "sg:phone":"+34 980 53 49 70",
    "sg:postcode":"49002",
    "sg:province":"Zamora",
    "wof:name":"Martin Garcia Felipe",
    "wof:placetype":"venue"
},
  "geometry": {"coordinates":[-5.7439899445,41.503162384],"type":"Point"}
}