{
  "type": "Feature",
  "properties": {
    "iso:country":"ES",
    "sg:address":"Calle de Parany, 7",
    "sg:city":"Vall D'uixo",
    "sg:orig_category":"Empresas De Limpieza",
    "sg:phone":"+34 964 66 69 62",
    "sg:postcode":"12600",
    "sg:province":"Castell\u00f3n",
    "wof:name":"Lisufil S.l.unipersonal",
    "wof:placetype":"venue"
},
  "geometry": {"coordinates":[-0.0358080007,39.9788246155],"type":"Point"}
}