{
  "type": "Feature",
  "properties": {
    "addr:full":"Maria Cristina Plaza De, 1 Pravia Asturias 33120",
    "addr:postcode":"33120",
    "addr:street":"Maria",
    "iso:country":"ES",
    "sg:address":"Maria Cristina Plaza De, 1",
    "sg:city":"Pravia",
    "sg:orig_category":"Cajas Para Embalar",
    "sg:phone":"+34 985 82 10 02",
    "sg:postcode":"33120",
    "sg:province":"Asturias",
    "sg:website":"www.ruralvia.com",
    "wof:name":"Caja Rural De Asturias",
    "wof:placetype":"venue"
},
  "geometry": {"coordinates":[-6.1117367744,43.4881896973],"type":"Point"}
}