{
  "type": "Feature",
  "properties": {
    "iso:country":"ES",
    "sg:address":"Calle de De Los Herreros, 42",
    "sg:city":"Benavente",
    "sg:orig_category":"Arquitectos",
    "sg:phone":"+34 980 63 16 37",
    "sg:postcode":"49600",
    "sg:province":"Zamora",
    "wof:name":"Servicios De Arquitectura Tec S.l.",
    "wof:placetype":"venue"
},
  "geometry": {"coordinates":[-5.6786561012,42.00365448],"type":"Point"}
}