{
  "type": "Feature",
  "properties": {
    "iso:country":"ES",
    "sg:address":"Calle de Leoncio Rojas, 26",
    "sg:city":"Getafe",
    "sg:orig_category":"Puertas Y Portales",
    "sg:phone":"+34 916 83 34 36",
    "sg:postcode":"28901",
    "sg:province":"Madrid",
    "wof:name":"Ynreyser S.l.",
    "wof:placetype":"venue"
},
  "geometry": {"coordinates":[-3.7303552628,40.3020095825],"type":"Point"}
}