{
  "type": "Feature",
  "properties": {
    "addr:full":"Calle de Donoso Cortes, 17 Badajoz Badajoz 06002",
    "addr:housenumber":"17",
    "addr:postcode":"06002",
    "addr:street":"Calle De Donoso Cortes",
    "iso:country":"ES",
    "sg:address":"Calle de Donoso Cortes, 17",
    "sg:city":"Badajoz",
    "sg:orig_category":"Arquitectos",
    "sg:phone":"+34 924 20 75 44",
    "sg:postcode":"06002",
    "sg:province":"Badajoz",
    "wof:name":"Julian Prieto Y Bego\u00f1a Galeano Arquitectos S.l.",
    "wof:placetype":"venue"
},
  "geometry": {"coordinates":[-6.9688591957,38.879524231],"type":"Point"}
}