{
  "type": "Feature",
  "properties": {
    "addr:full":"Outeiro (santa Maria), 21 Outeiro Pontevedra 36746",
    "addr:housenumber":"21",
    "addr:postcode":"36746",
    "addr:street":"Santa Maria",
    "iso:country":"ES",
    "sg:address":"Outeiro (santa Maria), 21",
    "sg:city":"Outeiro",
    "sg:classifiers":[
        {
            "category":"Taxi",
            "type":"Transportation"
        }
    ],
    "sg:phone":"+34 986 62 43 99",
    "sg:postcode":"36746",
    "sg:province":"Pontevedra",
    "wof:name":"Rodriguez Castro Jose Venancio",
    "wof:placetype":"venue"
},
  "geometry": {"coordinates":[-8.7407646179,42.0461425781],"type":"Point"}
}