{
  "type": "Feature",
  "properties": {
    "iso:country":"ES",
    "sg:address":"Barr Poligono De Ria\u00d1o, 9",
    "sg:city":"Langreo",
    "sg:orig_category":"Explotaci\u00d3n De Minas",
    "sg:phone":"+34 985 67 89 05",
    "sg:postcode":"33900",
    "sg:province":"Asturias",
    "wof:name":"Prominor 2003 S.l.",
    "wof:placetype":"venue"
},
  "geometry": {"coordinates":[-5.6692090034,43.2883987427],"type":"Point"}
}