{
  "type": "Feature",
  "properties": {
    "iso:country":"ES",
    "sg:address":"Trva Timanfaya, 6",
    "sg:city":"Alcorcon",
    "sg:orig_category":"Protecci\u00d3n Contra Incendios: Material, Instalaci\u00d3n, Mantenimiento",
    "sg:phone":"+34 916 12 53 41",
    "sg:postcode":"28924",
    "sg:province":"Madrid",
    "wof:name":"Insproconin Sl.",
    "wof:placetype":"venue"
},
  "geometry": {"coordinates":[-3.8132860661,40.3463859558],"type":"Point"}
}