{
  "type": "Feature",
  "properties": {
    "addr:full":"Pase Estacion, 76 Salamanca Salamanca 37004",
    "addr:housenumber":"76",
    "addr:postcode":"37004",
    "addr:street":"Estacion",
    "iso:country":"ES",
    "sg:address":"Pase Estacion, 76",
    "sg:city":"Salamanca",
    "sg:orig_category":"Reposter\u00cdas",
    "sg:phone":"+34 923 22 30 35",
    "sg:postcode":"37004",
    "sg:province":"Salamanca",
    "wof:name":"Vicente Cifuentes Felix",
    "wof:placetype":"venue"
},
  "geometry": {"coordinates":[-5.6524138451,40.9705047607],"type":"Point"}
}