{
  "type": "Feature",
  "properties": {
    "addr:full":"Calle de Puerto De Arlaban, 87 Madrid Madrid 28053",
    "addr:housenumber":"87",
    "addr:postcode":"madrid;28053",
    "addr:street":"Calle De Puerto De Arlaban",
    "iso:country":"ES",
    "sg:address":"Calle de Puerto De Arlaban, 87",
    "sg:city":"Madrid",
    "sg:orig_category":"Comercio De Piezas De Recambio Y De Accesorios De Veh\u00cdculos, Veh\u00cdculos Industriales",
    "sg:phone":"+34 914 78 04 05",
    "sg:postcode":"28053",
    "sg:province":"Madrid",
    "wof:name":"Recambios Vallecas S. L.",
    "wof:placetype":"venue"
},
  "geometry": {"coordinates":[-3.6676681042,40.3858604431],"type":"Point"}
}