{
  "type": "Feature",
  "properties": {
    "addr:full":"Av Alacant, 132 Elche Alicante 03203",
    "addr:housenumber":"132",
    "addr:postcode":"03203",
    "addr:street":"Alacant",
    "iso:country":"ES",
    "sg:address":"Av Alacant, 132",
    "sg:city":"Elche",
    "sg:orig_category":"Arquitectos",
    "sg:phone":"+34 965 45 33 57",
    "sg:postcode":"03203",
    "sg:province":"Alicante",
    "wof:name":"Ctf Soluciones Integrales En Proyectos Inmobiliarios S.l.",
    "wof:placetype":"venue"
},
  "geometry": {"coordinates":[-0.6819949746,38.269569397],"type":"Point"}
}