{
  "type": "Feature",
  "properties": {
    "iso:country":"ES",
    "sg:address":"Av Paisos Catalans, 25",
    "sg:city":"Reus",
    "sg:orig_category":"Agencias Y Agentes Comerciales, Representantes",
    "sg:phone":"+34 977 31 04 39",
    "sg:postcode":"43202",
    "sg:province":"Tarragona",
    "wof:name":"Sedo Ribas Miquel",
    "wof:placetype":"venue"
},
  "geometry": {"coordinates":[1.0965930223,41.1560287476],"type":"Point"}
}