{
  "type": "Feature",
  "properties": {
    "addr:full":"Carr Corts Catalanes, 34 Lleida Lleida 25005",
    "addr:housenumber":"34",
    "addr:postcode":"25005",
    "addr:street":"Carr Corts Catalanes",
    "iso:country":"ES",
    "sg:address":"Carr Corts Catalanes, 34",
    "sg:city":"Lleida",
    "sg:orig_category":"Carnicer\u00cdas, Carnicer\u00cdas",
    "sg:phone":"+34 973 23 52 16",
    "sg:postcode":"25005",
    "sg:province":"Lleida",
    "wof:name":"Carns Sampietro S.l.",
    "wof:placetype":"venue"
},
  "geometry": {"coordinates":[0.6261299849,41.6266517639],"type":"Point"}
}