{
  "type": "Feature",
  "properties": {
    "addr:full":"Carrer de Sant Antoni, 70 Calella Barcelona 08370",
    "addr:housenumber":"70",
    "addr:postcode":"08370",
    "addr:street":"Carrer De Sant Antoni",
    "iso:country":"ES",
    "sg:address":"Carrer de Sant Antoni, 70",
    "sg:city":"Calella",
    "sg:orig_category":"Pistas Y Clases De Tenis",
    "sg:phone":"+34 937 69 24 09",
    "sg:postcode":"08370",
    "sg:province":"Barcelona",
    "wof:name":"Club Tennis Taula Calella",
    "wof:placetype":"venue"
},
  "geometry": {"coordinates":[2.6631989479,41.6165466309],"type":"Point"}
}