{
  "type": "Feature",
  "properties": {
    "addr:full":"Calle de La Rua, 16 Villalon Campos Valladolid 47600",
    "addr:postcode":"47600",
    "addr:street":"Calle De La Rua 16 Villalon Campos",
    "iso:country":"ES",
    "sg:address":"Calle de La Rua, 16",
    "sg:city":"Villalon Campos",
    "sg:orig_category":"\u00c1reas De Especies Protegidas, Parques Zool\u00d3gicos",
    "sg:phone":"+34 983 74 08 41",
    "sg:postcode":"47600",
    "sg:province":"Valladolid",
    "wof:name":"Comercial Ganadera Jhobry S.l.",
    "wof:placetype":"venue"
},
  "geometry": {"coordinates":[-5.0348992348,42.0987815857],"type":"Point"}
}