{
  "type": "Feature",
  "properties": {
    "iso:country":"ES",
    "sg:address":"Calle de Pardo Bazan, 17",
    "sg:city":"Escairon",
    "sg:orig_category":"Asociaciones, Organismos Culturales Y Socioeducativos",
    "sg:phone":"+34 982 45 20 21",
    "sg:postcode":"27540",
    "sg:province":"Lugo",
    "wof:name":"Circulo Cultural Recreativo Savi\u00f1ao",
    "wof:placetype":"venue"
},
  "geometry": {"coordinates":[-7.6405949593,42.5846710205],"type":"Point"}
}