{
  "type": "Feature",
  "properties": {
    "iso:country":"ES",
    "sg:address":"Calle de Libertad, 61",
    "sg:city":"Puerto",
    "sg:orig_category":"Centros M\u00c9dicos Y Sociales, Dispensarios",
    "sg:phone":"+34 962 67 98 22",
    "sg:postcode":"46520",
    "sg:province":"Valencia",
    "wof:name":"Plumed Gracia Maria Pilar",
    "wof:placetype":"venue"
},
  "geometry": {"coordinates":[-0.2225790024,39.659866333],"type":"Point"}
}