{
  "type": "Feature",
  "properties": {
    "addr:full":"Calle de Naves, 12 Madrid Madrid 28005",
    "addr:housenumber":"12",
    "addr:postcode":"madrid;28005",
    "addr:street":"Calle De Naves",
    "iso:country":"ES",
    "sg:address":"Calle de Naves, 12",
    "sg:city":"Madrid",
    "sg:orig_category":"Farmacias",
    "sg:phone":"+34 914 74 07 02",
    "sg:postcode":"28005",
    "sg:province":"Madrid",
    "wof:name":"Hashem Pamies C.b.",
    "wof:placetype":"venue"
},
  "geometry": {"coordinates":[-3.7067620754,40.3981437683],"type":"Point"}
}