{
  "type": "Feature",
  "properties": {
    "addr:full":"Carrer de Tenor Masini, 53 Barcelona Barcelona 08028",
    "addr:housenumber":"53",
    "addr:postcode":"08028",
    "addr:street":"Carrer De Tenor Masini",
    "iso:country":"ES",
    "sg:address":"Carrer de Tenor Masini, 53",
    "sg:city":"Barcelona",
    "sg:orig_category":"Muebles, Minoristas",
    "sg:phone":"+34 933 30 18 47",
    "sg:postcode":"08028",
    "sg:province":"Barcelona",
    "wof:name":"Espallargas Monta\u00f1es Joaquin",
    "wof:placetype":"venue"
},
  "geometry": {"coordinates":[2.1316859722,41.3774414062],"type":"Point"}
}