{
  "type": "Feature",
  "properties": {
    "iso:country":"ES",
    "sg:address":"Ctra Palma(barreros), 195",
    "sg:city":"Cartagena",
    "sg:orig_category":"Escayola Y Productos De Escayola (fabricaci\u00d3n, Al Por Mayor)",
    "sg:phone":"+34 968 51 20 57",
    "sg:postcode":"30310",
    "sg:province":"Murcia",
    "wof:name":"Martinez Fuentes Francisco",
    "wof:placetype":"venue"
},
  "geometry": {"coordinates":[-0.9939569831,37.6308479309],"type":"Point"}
}