{
  "type": "Feature",
  "properties": {
    "addr:full":"Plaz Mayor, 9 Bonillo Albacete 02610",
    "addr:housenumber":"9",
    "addr:postcode":"02610",
    "addr:street":"Plaz Mayor",
    "iso:country":"ES",
    "sg:address":"Plaz Mayor, 9",
    "sg:city":"Bonillo",
    "sg:orig_category":"Cajas De Ahorro",
    "sg:phone":"+34 967 37 00 22",
    "sg:postcode":"02610",
    "sg:province":"Albacete",
    "wof:name":"Caja De Ahorros De Castilla La Mancha",
    "wof:placetype":"venue"
},
  "geometry": {"coordinates":[-2.5415890217,38.9515419006],"type":"Point"}
}