{
  "type": "Feature",
  "properties": {
    "addr:full":"Ptda Pla De Monso, 60 Basses D'alpicat Lleida 25193",
    "addr:housenumber":"60",
    "addr:postcode":"25193",
    "addr:street":"Ptda Pla De Monso",
    "iso:country":"ES",
    "sg:address":"Ptda Pla De Monso, 60",
    "sg:city":"Basses D'alpicat",
    "sg:orig_category":"Semiller\u00cdas",
    "sg:phone":"+34 973 24 98 04",
    "sg:postcode":"25193",
    "sg:province":"Lleida",
    "wof:name":"Projardi S.l.",
    "wof:placetype":"venue"
},
  "geometry": {"coordinates":[0.5608800054,41.6511726379],"type":"Point"}
}