{
  "type": "Feature",
  "properties": {
    "iso:country":"ES",
    "sg:address":"Calle de Cortes De Aragon, 24",
    "sg:city":"Zaragoza",
    "sg:orig_category":"Servidores Y Editores De Bases De Datos",
    "sg:phone":"+34 976 23 48 21",
    "sg:postcode":"50005",
    "sg:province":"Zaragoza",
    "sg:website":"www.jelk.net",
    "wof:name":"Jelk S.l.",
    "wof:placetype":"venue"
},
  "geometry": {"coordinates":[-0.8922861814,41.645565033],"type":"Point"}
}