{
  "type": "Feature",
  "properties": {
    "addr:full":"Carr Doctor Robert, 98 Badalona Barcelona 08915",
    "addr:housenumber":"98",
    "addr:postcode":"08915",
    "addr:street":"Carr Doctor Robert",
    "iso:country":"ES",
    "sg:address":"Carr Doctor Robert, 98",
    "sg:city":"Badalona",
    "sg:orig_category":"Centros Empresariales",
    "sg:phone":"+34 934 65 23 97",
    "sg:postcode":"08915",
    "sg:province":"Barcelona",
    "wof:name":"Castilla Narvaez Eva",
    "wof:placetype":"venue"
},
  "geometry": {"coordinates":[2.2433750629,41.4582977295],"type":"Point"}
}