{
  "type": "Feature",
  "properties": {
    "addr:full":"Calle de Santo Tomas, 6 Segovia Segovia 40002",
    "addr:housenumber":"6",
    "addr:postcode":"40002",
    "addr:street":"Calle De Santo Tomas",
    "iso:country":"ES",
    "sg:address":"Calle de Santo Tomas, 6",
    "sg:city":"Segovia",
    "sg:orig_category":"M\u00c9dicos: Ginecolog\u00cda Y Obstetricia",
    "sg:phone":"+34 921 44 04 37",
    "sg:postcode":"40002",
    "sg:province":"Segovia",
    "wof:name":"Resel Estevez Rafael",
    "wof:placetype":"venue"
},
  "geometry": {"coordinates":[-4.1186938286,40.9435195923],"type":"Point"}
}