{
  "type": "Feature",
  "properties": {
    "addr:full":"Calle de Fernan Gonzalez, 28 Aranda Duero Burgos 09400",
    "addr:housenumber":"28",
    "addr:postcode":"09400",
    "addr:street":"Calle De Fernan Gonzalez",
    "iso:country":"ES",
    "sg:address":"Calle de Fernan Gonzalez, 28",
    "sg:city":"Aranda Duero",
    "sg:orig_category":"Carnicer\u00cdas, Carnicer\u00cdas",
    "sg:phone":"+34 947 50 59 90",
    "sg:postcode":"09400",
    "sg:province":"Burgos",
    "wof:name":"Arranz Nieto Arturo",
    "wof:placetype":"venue"
},
  "geometry": {"coordinates":[-3.6760654449,41.6717376709],"type":"Point"}
}