{
  "type": "Feature",
  "properties": {
    "iso:country":"ES",
    "sg:address":"Jose Ridaura Alcaide, S/n",
    "sg:city":"Foios",
    "sg:orig_category":"Escotaduras, Torneados",
    "sg:phone":"+34 961 49 55 27",
    "sg:postcode":"46134",
    "sg:province":"Valencia",
    "wof:name":"Bayarri Bellver Manuel Francisco",
    "wof:placetype":"venue"
},
  "geometry": {"coordinates":[-0.3543489873,39.5360145569],"type":"Point"}
}