{
  "type": "Feature",
  "properties": {
    "addr:full":"A Vi\u00f1a, 3 Cartaya Huelva 21450",
    "addr:housenumber":"3",
    "addr:postcode":"21450",
    "addr:street":"Vin\u0303A",
    "iso:country":"ES",
    "sg:address":"A Vi\u00f1a, 3",
    "sg:city":"Cartaya",
    "sg:orig_category":"M\u00c1rmoles, Granitos Y Piedras Naturales",
    "sg:phone":"+34 959 39 21 94",
    "sg:postcode":"21450",
    "sg:province":"Huelva",
    "wof:name":"Hurtado Alfonso Manuel Jesus",
    "wof:placetype":"venue"
},
  "geometry": {"coordinates":[-7.1528987885,37.2844581604],"type":"Point"}
}