{
  "type": "Feature",
  "properties": {
    "addr:full":"Pol Ind La Juaida, S/n Viator Almer\u00eda 04240",
    "addr:housenumber":"/ n",
    "addr:postcode":"04240",
    "addr:street":"Juaida S;Almeri\u0301A",
    "iso:country":"ES",
    "sg:address":"Pol Ind La Juaida, S/n",
    "sg:city":"Viator",
    "sg:orig_category":"Promotores Constructores",
    "sg:phone":"+34 950 30 46 33",
    "sg:postcode":"04240",
    "sg:province":"Almer\u00eda",
    "wof:name":"Estructuras Urci S.l.",
    "wof:placetype":"venue"
},
  "geometry": {"coordinates":[-2.4223089218,36.884979248],"type":"Point"}
}