{
  "type": "Feature",
  "properties": {
    "addr:full":"Calle de Hospital, 10 Do\u00e7a Mencia C\u00f3rdoba 14860",
    "addr:housenumber":"10",
    "addr:postcode":"14860",
    "addr:street":"Calle De Hospital;Co\u0301Rdoba",
    "iso:country":"ES",
    "sg:address":"Calle de Hospital, 10",
    "sg:city":"Do\u00e7a Mencia",
    "sg:orig_category":"Promotores Constructores",
    "sg:phone":"+34 957 69 53 27",
    "sg:postcode":"14860",
    "sg:province":"C\u00f3rdoba",
    "wof:name":"Construcciones Rasancu S.l.",
    "wof:placetype":"venue"
},
  "geometry": {"coordinates":[-4.3587460518,37.5550041199],"type":"Point"}
}