{
  "type": "Feature",
  "properties": {
    "addr:full":"Av Gabriel Alomar I V, 35 Palma Islas Baleares 07006",
    "addr:housenumber":"35",
    "addr:postcode":"07006",
    "addr:street":"Av Gabriel Alomar;V",
    "iso:country":"ES",
    "sg:address":"Av Gabriel Alomar I V, 35",
    "sg:city":"Palma",
    "sg:orig_category":"M\u00c9dicos: Estomatolog\u00cda",
    "sg:phone":"+34 971 46 82 00",
    "sg:postcode":"07006",
    "sg:province":"Islas Baleares",
    "wof:name":"Ortega Zaforteza Angel",
    "wof:placetype":"venue"
},
  "geometry": {"coordinates":[2.6787199974,39.5591049194],"type":"Point"}
}