{
  "type": "Feature",
  "properties": {
    "addr:full":"Avda Calvo Sotelo, 107 Beniel Murcia 30130",
    "addr:housenumber":"107",
    "addr:postcode":"30130",
    "addr:street":"Avda Calvo Sotelo",
    "iso:country":"ES",
    "sg:address":"Avda Calvo Sotelo, 107",
    "sg:city":"Beniel",
    "sg:orig_category":"Aceites Y Grasas Alimentarias (fabricaci\u00d3n, Al Por Mayor)",
    "sg:phone":"+34 968 60 01 12",
    "sg:postcode":"30130",
    "sg:province":"Murcia",
    "sg:website":"www.aceitesmanzano.es",
    "wof:name":"Aceites Manzano S.a.",
    "wof:placetype":"venue"
},
  "geometry": {"coordinates":[-1.008564949,38.0404167175],"type":"Point"}
}