{
  "type": "Feature",
  "properties": {
    "addr:full":"Calle de Port De Catarroja - Diseminados, S/n Catarroja Valencia 46470",
    "addr:housenumber":"s / n",
    "addr:postcode":"46470",
    "addr:street":"Calle De Port De Catarroja Diseminados",
    "iso:country":"ES",
    "sg:address":"Calle de Port De Catarroja - Diseminados, S/n",
    "sg:city":"Catarroja",
    "sg:orig_category":"Sindicatos Y Colegios Profesionales",
    "sg:phone":"+34 961 27 46 00",
    "sg:postcode":"46470",
    "sg:province":"Valencia",
    "wof:name":"Asociacion Profesional De Tecnicos Y Capataces",
    "wof:placetype":"venue"
},
  "geometry": {"coordinates":[-0.4035184085,39.4027366638],"type":"Point"}
}