{
  "type": "Feature",
  "properties": {
    "iso:country":"ES",
    "sg:address":"Calle de Marques De Larios, 10",
    "sg:city":"Malaga",
    "sg:orig_category":"Asesor\u00cda Fiscal Y Jur\u00cddica",
    "sg:phone":"+34 952 22 19 28",
    "sg:postcode":"29005",
    "sg:province":"M\u00e1laga",
    "wof:name":"Asesoramiento Y Gestion Laber S.l.",
    "wof:placetype":"venue"
},
  "geometry": {"coordinates":[-4.4215531349,36.7190475464],"type":"Point"}
}