{
  "type": "Feature",
  "properties": {
    "addr:full":"Av M. Celayeta, 138 Iru\u00f1a Navarra 31014",
    "addr:housenumber":"138",
    "addr:postcode":"31014",
    "addr:street":"Av M. Celayeta;Navarra",
    "iso:country":"ES",
    "sg:address":"Av M. Celayeta, 138",
    "sg:city":"Iru\u00f1a",
    "sg:orig_category":"Molduras, Junquillos, Listones Y Molduras Perforadas",
    "sg:phone":"+34 948 35 59 93",
    "sg:postcode":"31014",
    "sg:province":"Navarra",
    "wof:name":"Armendariz Arbeloa L.m.b.",
    "wof:placetype":"venue"
},
  "geometry": {"coordinates":[-1.6480346918,42.8283004761],"type":"Point"}
}