{
  "type": "Feature",
  "properties": {
    "addr:full":"Avda Valencia, 45 Ibi Alicante 03440",
    "addr:housenumber":"45",
    "addr:postcode":"03440",
    "addr:street":"Avda Valencia",
    "iso:country":"ES",
    "sg:address":"Avda Valencia, 45",
    "sg:city":"Ibi",
    "sg:orig_category":"Chapister\u00cda",
    "sg:phone":"+34 965 55 15 02",
    "sg:postcode":"03440",
    "sg:province":"Alicante",
    "wof:name":"Cabeza Leiva Manuel",
    "wof:placetype":"venue"
},
  "geometry": {"coordinates":[-0.6000149846,38.6164283752],"type":"Point"}
}