{
  "type": "Feature",
  "properties": {
    "iso:country":"ES",
    "sg:address":"Calle de Albasanz, 14",
    "sg:city":"Madrid",
    "sg:orig_category":"Alimentaci\u00d3n General (al Por Menor)",
    "sg:phone":"+34 913 04 50 29",
    "sg:postcode":"28037",
    "sg:province":"Madrid",
    "wof:name":"Ferjama S.a.",
    "wof:placetype":"venue"
},
  "geometry": {"coordinates":[-3.6326069832,40.4358024597],"type":"Point"}
}