{
  "type": "Feature",
  "properties": {
    "iso:country":"ES",
    "sg:address":"Calle de Cervantes, 72",
    "sg:city":"Calzada Calatrava",
    "sg:orig_category":"Muebles",
    "sg:phone":"+34 926 87 68 37",
    "sg:postcode":"13370",
    "sg:province":"Ciudad Real",
    "wof:name":"Ciudad Rodriguez Miguel",
    "wof:placetype":"venue"
},
  "geometry": {"coordinates":[-3.7733445168,38.7017478943],"type":"Point"}
}