{
  "type": "Feature",
  "properties": {
    "iso:country":"ES",
    "sg:address":"Plaz Holanda, 2",
    "sg:city":"Valencia",
    "sg:orig_category":"Agentes Generales De Seguros",
    "sg:phone":"+34 963 78 99 14",
    "sg:postcode":"46017",
    "sg:province":"Valencia",
    "wof:name":"Sempere I Bonafe S.l.",
    "wof:placetype":"venue"
},
  "geometry": {"coordinates":[-0.3878819942,39.4482917786],"type":"Point"}
}