{
  "type": "Feature",
  "properties": {
    "addr:full":"Armentia-armentiagana, 4 Armentia \u00c1lava 01007",
    "addr:housenumber":"4",
    "addr:postcode":"01007",
    "addr:street":"Armentia-Armentiagana",
    "iso:country":"ES",
    "sg:address":"Armentia-armentiagana, 4",
    "sg:city":"Armentia",
    "sg:orig_category":"Agentes, Concesionarios Y Sucursales De Veh\u00cdculos",
    "sg:phone":"+34 945 15 41 28",
    "sg:postcode":"01007",
    "sg:province":"\u00c1lava",
    "wof:name":"Gasteiz Motor S.a.",
    "wof:placetype":"venue"
},
  "geometry": {"coordinates":[-2.7020299435,42.8327789307],"type":"Point"}
}