{
  "type": "Feature",
  "properties": {
    "iso:country":"ES",
    "sg:address":"Avda Constitucion (la), 28",
    "sg:city":"Sevilla",
    "sg:orig_category":"Porcelanas, Azulejos (fabricaci\u00d3n, Al Por Mayor)",
    "sg:phone":"+34 954 21 31 96",
    "sg:postcode":"41001",
    "sg:province":"Sevilla",
    "wof:name":"Perez Garcia Jose Manuel",
    "wof:placetype":"venue"
},
  "geometry": {"coordinates":[-5.9939289093,37.3851890564],"type":"Point"}
}