{
  "type": "Feature",
  "properties": {
    "addr:full":"Calle de Diderot, 38 Malaga M\u00e1laga 29004",
    "addr:housenumber":"38",
    "addr:postcode":"29004",
    "addr:street":"Calle De Diderot;Ma\u0301Laga",
    "iso:country":"ES",
    "sg:address":"Calle de Diderot, 38",
    "sg:city":"Malaga",
    "sg:orig_category":"Contenedores (mercanc\u00cdas)",
    "sg:phone":"+34 952 24 63 10",
    "sg:postcode":"29004",
    "sg:province":"M\u00e1laga",
    "wof:name":"Calidris Maritima S.l.",
    "wof:placetype":"venue"
},
  "geometry": {"coordinates":[-4.4725399017,36.6934738159],"type":"Point"}
}