{
  "type": "Feature",
  "properties": {
    "addr:full":"Rua Curros Enriquez, 8 Monforte De Lemos Lugo 27400",
    "addr:housenumber":"8",
    "addr:postcode":"27400",
    "addr:street":"Rua Curros Enriquez",
    "iso:country":"ES",
    "sg:address":"Rua Curros Enriquez, 8",
    "sg:city":"Monforte De Lemos",
    "sg:orig_category":"Vinos Y Licores (venta Al Por Menor)",
    "sg:phone":"+34 982 40 20 99",
    "sg:postcode":"27400",
    "sg:province":"Lugo",
    "wof:name":"Monfortes Catabelos S.l.l.",
    "wof:placetype":"venue"
},
  "geometry": {"coordinates":[-7.5054860115,42.5268936157],"type":"Point"}
}