{
  "type": "Feature",
  "properties": {
    "addr:full":"Calle de Doctor Fleming, 9 Parador Hortichuelas Almer\u00eda 04720",
    "addr:housenumber":"9",
    "addr:postcode":"04720",
    "addr:street":"Calle De Doctor Fleming;Almeri\u0301A",
    "iso:country":"ES",
    "sg:address":"Calle de Doctor Fleming, 9",
    "sg:city":"Parador Hortichuelas",
    "sg:orig_category":"Bebidas",
    "sg:phone":"+34 950 34 24 29",
    "sg:postcode":"04720",
    "sg:province":"Almer\u00eda",
    "wof:name":"Carmona Rodriguez Distribuciones S.l.",
    "wof:placetype":"venue"
},
  "geometry": {"coordinates":[-2.599709034,36.8099708557],"type":"Point"}
}