{
  "type": "Feature",
  "properties": {
    "addr:full":"Real, 17 Almu\u00f1ecar Granada 18690",
    "addr:housenumber":"17",
    "addr:postcode":"18690",
    "addr:street":"Real",
    "iso:country":"ES",
    "sg:address":"Real, 17",
    "sg:city":"Almu\u00f1ecar",
    "sg:orig_category":"Bisuter\u00cda, Joyer\u00cda, Relojer\u00cda (al Por Menor)",
    "sg:phone":"+34 958 63 03 95",
    "sg:postcode":"18690",
    "sg:province":"Granada",
    "wof:name":"Taller Y Joyeria Antequera S.l.",
    "wof:placetype":"venue"
},
  "geometry": {"coordinates":[-3.7385830879,36.7353096008],"type":"Point"}
}