{
  "type": "Feature",
  "properties": {
    "addr:full":"Ctra Madrid-irun(oeste), Km. 0001,0 Aranda Duero Burgos 09400",
    "addr:postcode":"09400",
    "addr:street":"Ctra Madrid-Irun Oeste Km. 0001,0 Aranda Duero",
    "iso:country":"ES",
    "sg:address":"Ctra Madrid-irun(oeste), Km. 0001,0",
    "sg:city":"Aranda Duero",
    "sg:orig_category":"Distribuci\u00d3n De Petr\u00d3leo Y Derivados",
    "sg:phone":"+34 947 50 83 50",
    "sg:postcode":"09400",
    "sg:province":"Burgos",
    "wof:name":"Buquerin S.a.",
    "wof:placetype":"venue"
},
  "geometry": {"coordinates":[-3.6889948845,41.6699256897],"type":"Point"}
}