{
  "type": "Feature",
  "properties": {
    "addr:full":"Raya Hita, S/n Guadix Granada 18500",
    "addr:housenumber":"s",
    "addr:postcode":"18500",
    "addr:street":"Hita;/ N",
    "iso:country":"ES",
    "sg:address":"Raya Hita, S/n",
    "sg:city":"Guadix",
    "sg:orig_category":"Discapacitados",
    "sg:phone":"+34 958 66 17 33",
    "sg:postcode":"18500",
    "sg:province":"Granada",
    "wof:name":"Residencia Miguel Angel Carmona",
    "wof:placetype":"venue"
},
  "geometry": {"coordinates":[-3.1440889835,37.3027610779],"type":"Point"}
}