{
  "type": "Feature",
  "properties": {
    "iso:country":"ES",
    "sg:address":"Calle de Burriana, 7",
    "sg:city":"Valencia",
    "sg:orig_category":"Higiene, Belleza: Art\u00cdculos (al Por Menor)",
    "sg:phone":"+34 963 33 27 28",
    "sg:postcode":"46005",
    "sg:province":"Valencia",
    "wof:name":"Cordeiro Filipe Belinda",
    "wof:placetype":"venue"
},
  "geometry": {"coordinates":[-0.3679051995,39.464641571],"type":"Point"}
}