{
  "type": "Feature",
  "properties": {
    "iso:country":"ES",
    "sg:address":"Av General Luque, S/n",
    "sg:city":"Inca",
    "sg:orig_category":"Distribuci\u00d3n De Petr\u00d3leo Y Derivados",
    "sg:phone":"+34 971 88 38 97",
    "sg:postcode":"07300",
    "sg:province":"Islas Baleares",
    "wof:name":"Matas Y Campins Suministros S.l.u.",
    "wof:placetype":"venue"
},
  "geometry": {"coordinates":[2.905164957,39.7150192261],"type":"Point"}
}