{
  "type": "Feature",
  "properties": {
    "addr:full":"Carrer de Vilallonga, 16 Reus Tarragona 43204",
    "addr:housenumber":"16",
    "addr:postcode":"43204",
    "addr:street":"Carrer De Vilallonga",
    "iso:country":"ES",
    "sg:address":"Carrer de Vilallonga, 16",
    "sg:city":"Reus",
    "sg:orig_category":"Mec\u00c1nico Del Autom\u00d3vil",
    "sg:phone":"+34 977 75 06 77",
    "sg:postcode":"43204",
    "sg:province":"Tarragona",
    "wof:name":"Carrion Cruz Jose",
    "wof:placetype":"venue"
},
  "geometry": {"coordinates":[1.1160390377,41.1585083008],"type":"Point"}
}