{
  "type": "Feature",
  "properties": {
    "addr:full":"Calle de Gongora, 6 Chipiona C\u00e1diz 11550",
    "addr:housenumber":"6",
    "addr:postcode":"11550",
    "addr:street":"Calle De Gongora",
    "iso:country":"ES",
    "sg:address":"Calle de Gongora, 6",
    "sg:city":"Chipiona",
    "sg:orig_category":"Ense\u00d1anza, Formaci\u00d3n Profesional: Aprendizaje",
    "sg:phone":"+34 956 37 10 06",
    "sg:postcode":"11550",
    "sg:province":"C\u00e1diz",
    "wof:name":"Servicio Andaluz De Empleo",
    "wof:placetype":"venue"
},
  "geometry": {"coordinates":[-6.4332637787,36.738079071],"type":"Point"}
}