{
  "type": "Feature",
  "properties": {
    "iso:country":"ES",
    "sg:address":"Calle de Santa Teresa Jornet E Ibars, 7",
    "sg:city":"Santa Cruz De Tenerife",
    "sg:classifiers":[
        {
            "category":"Communications",
            "type":"Services"
        }
    ],
    "sg:phone":"+34 922 28 35 12",
    "sg:postcode":"38004",
    "sg:province":"Santa Cruz De Tenerife",
    "sg:tags":[
        "televisiones",
        "y",
        "radio"
    ],
    "wof:name":"Radio Ecca",
    "wof:placetype":"venue"
},
  "geometry": {"coordinates":[-16.2593688965,28.4652576447],"type":"Point"}
}