{
  "type": "Feature",
  "properties": {
    "addr:full":"Calle de Teruel, 23 Castellon Castell\u00f3n 12002",
    "addr:housenumber":"23",
    "addr:postcode":"12002",
    "addr:street":"Calle De Teruel",
    "iso:country":"ES",
    "sg:address":"Calle de Teruel, 23",
    "sg:city":"Castellon",
    "sg:orig_category":"Empresas De Limpieza",
    "sg:phone":"+34 964 20 23 65",
    "sg:postcode":"12002",
    "sg:province":"Castell\u00f3n",
    "wof:name":"Lunalim S.l.",
    "wof:placetype":"venue"
},
  "geometry": {"coordinates":[-0.0400389992,39.9828720093],"type":"Point"}
}