{
  "type": "Feature",
  "properties": {
    "addr:full":"Via Augusta, 92 Barcelona Barcelona 08006",
    "addr:housenumber":"92",
    "addr:postcode":"08006",
    "addr:street":"Via Augusta",
    "iso:country":"ES",
    "sg:address":"Via Augusta, 92",
    "sg:city":"Barcelona",
    "sg:orig_category":"Par\u00cds",
    "sg:phone":"+34 932 17 06 20",
    "sg:postcode":"08006",
    "sg:province":"Barcelona",
    "wof:name":"Torregrosa Amoros Gabriel",
    "wof:placetype":"venue"
},
  "geometry": {"coordinates":[2.1502580643,41.4010848999],"type":"Point"}
}