{
  "type": "Feature",
  "properties": {
    "iso:country":"ES",
    "sg:address":"Segovia Y Merceditas, S/n",
    "sg:city":"Fuente Palmera",
    "sg:orig_category":"Venta, Instalaci\u00d3n, Mantenimiento De Chimeneas De Interior Y Accesorios",
    "sg:phone":"+34 957 63 70 27",
    "sg:postcode":"14120",
    "sg:province":"C\u00f3rdoba",
    "wof:name":"Azulejos La Colonia S.l.",
    "wof:placetype":"venue"
},
  "geometry": {"coordinates":[-5.0911064148,37.7097358704],"type":"Point"}
}