{
  "type": "Feature",
  "properties": {
    "addr:full":"Avda Comercio, 11 Cabezon.barrio Nuevo Valladolid 47260",
    "addr:housenumber":"11",
    "addr:postcode":"47260",
    "addr:street":"Avda Comercio",
    "iso:country":"ES",
    "sg:address":"Avda Comercio, 11",
    "sg:city":"Cabezon.barrio Nuevo",
    "sg:orig_category":"Molduras, Junquillos, Listones Y Molduras Perforadas",
    "sg:phone":"+34 983 50 01 73",
    "sg:postcode":"47260",
    "sg:province":"Valladolid",
    "wof:name":"Simon Cuesta C,b",
    "wof:placetype":"venue"
},
  "geometry": {"coordinates":[-4.640859127,41.7400436401],"type":"Point"}
}