{
  "type": "Feature",
  "properties": {
    "addr:full":"Ctra Espa\u00d1a, S/n Vera Santa Cruz De Tenerife 38390",
    "addr:housenumber":"s / n",
    "addr:postcode":"38390",
    "addr:street":"Ctra Espan\u0303A",
    "iso:country":"ES",
    "sg:address":"Ctra Espa\u00d1a, S/n",
    "sg:city":"Vera",
    "sg:classifiers":[
        {
            "category":"Taxi",
            "type":"Transportation"
        }
    ],
    "sg:phone":"+34 922 30 00 31",
    "sg:postcode":"38390",
    "sg:province":"Santa Cruz De Tenerife",
    "wof:name":"Asociacion Local Profesional De Empresarios De Autotaxis",
    "wof:placetype":"venue"
},
  "geometry": {"coordinates":[-16.4851589203,28.4246559143],"type":"Point"}
}