{
  "type": "Feature",
  "properties": {
    "addr:full":"Calle de Beato Galvez, 4 Utiel Valencia 46300",
    "addr:housenumber":"4",
    "addr:postcode":"46300",
    "addr:street":"Calle De Beato Galvez",
    "iso:country":"ES",
    "sg:address":"Calle de Beato Galvez, 4",
    "sg:city":"Utiel",
    "sg:orig_category":"Administraciones Regionales, Departamentales Y Locales",
    "sg:phone":"+34 962 17 05 04",
    "sg:postcode":"46300",
    "sg:province":"Valencia",
    "wof:name":"Ayuntamiento De Utiel",
    "wof:placetype":"venue"
},
  "geometry": {"coordinates":[-1.2049640417,39.567237854],"type":"Point"}
}