{
  "type": "Feature",
  "properties": {
    "iso:country":"ES",
    "sg:address":"Carrer de Arenys, 1",
    "sg:city":"Castelldefels",
    "sg:orig_category":"Restaurantes",
    "sg:phone":"+34 936 36 12 04",
    "sg:postcode":"08860",
    "sg:province":"Barcelona",
    "wof:name":"Fernandez Carreira Jesus",
    "wof:placetype":"venue"
},
  "geometry": {"coordinates":[1.9738750458,41.269657135],"type":"Point"}
}