{
  "type": "Feature",
  "properties": {
    "iso:country":"ES",
    "sg:address":"Carr Colon, 164",
    "sg:city":"Vila Joiosa",
    "sg:orig_category":"Empresas De Carpinter\u00cda",
    "sg:phone":"+34 966 85 21 22",
    "sg:postcode":"03570",
    "sg:province":"Alicante",
    "wof:name":"Sola Ruiz Jose Antonio",
    "wof:placetype":"venue"
},
  "geometry": {"coordinates":[-0.7466139793,38.3102035522],"type":"Point"}
}