{
  "type": "Feature",
  "properties": {
    "addr:full":"Trva Santo Tome De Zabarcos, 2 San Pedro Arroyo \u00c1vila 05350",
    "addr:housenumber":"2",
    "addr:postcode":"05350",
    "addr:street":"Trva Santo Tome De Zabarcos",
    "iso:country":"ES",
    "sg:address":"Trva Santo Tome De Zabarcos, 2",
    "sg:city":"San Pedro Arroyo",
    "sg:orig_category":"Farmacias",
    "sg:phone":"+34 920 24 00 54",
    "sg:postcode":"05350",
    "sg:province":"\u00c1vila",
    "wof:name":"Ramon Montes Luis Miguel",
    "wof:placetype":"venue"
},
  "geometry": {"coordinates":[-4.8702588081,40.8017959595],"type":"Point"}
}