{
  "type": "Feature",
  "properties": {
    "iso:country":"ES",
    "sg:address":"Carr Segria, 2",
    "sg:city":"Lleida",
    "sg:orig_category":"Carnicer\u00cdas, Carnicer\u00cdas",
    "sg:phone":"+34 973 26 82 27",
    "sg:postcode":"25006",
    "sg:province":"Lleida",
    "wof:name":"Sanahuja Benet Maria Rosa",
    "wof:placetype":"venue"
},
  "geometry": {"coordinates":[0.6163790226,41.617351532],"type":"Point"}
}