{
  "type": "Feature",
  "properties": {
    "addr:full":"Calle de Doctor Fco. Vazquez Limon, 14 Huelva Huelva 21002",
    "addr:housenumber":"14",
    "addr:postcode":"21002",
    "addr:street":"Calle De Doctor Fco. Vazquez Limon",
    "iso:country":"ES",
    "sg:address":"Calle de Doctor Fco. Vazquez Limon, 14",
    "sg:city":"Huelva",
    "sg:orig_category":"Fabricaci\u00d3n, Distribuci\u00d3n De Discos, V\u00cddeodiscos Y Musicassettes",
    "sg:phone":"+34 959 24 93 04",
    "sg:postcode":"21002",
    "sg:province":"Huelva",
    "wof:name":"Quintero Herrera Francisco",
    "wof:placetype":"venue"
},
  "geometry": {"coordinates":[-6.9504380226,37.2722816467],"type":"Point"}
}