{
  "type": "Feature",
  "properties": {
    "addr:full":"Avda Fernando Saiz (sancibrian), 12 Sancibrian Cantabria 39110",
    "addr:housenumber":"12",
    "addr:postcode":"39110",
    "addr:street":"Avda Fernando Saiz Sancibrian",
    "iso:country":"ES",
    "sg:address":"Avda Fernando Saiz (sancibrian), 12",
    "sg:city":"Sancibrian",
    "sg:orig_category":"Iglesia Cat\u00d3lica",
    "sg:phone":"+34 942 57 87 70",
    "sg:postcode":"39110",
    "sg:province":"Cantabria",
    "wof:name":"Obispado De Santander",
    "wof:placetype":"venue"
},
  "geometry": {"coordinates":[-3.8915948868,43.4601478577],"type":"Point"}
}