{
  "type": "Feature",
  "properties": {
    "iso:country":"ES",
    "sg:address":"Cm\u00d1o Codesal, S/n",
    "sg:city":"Ferrol",
    "sg:orig_category":"Metalizados",
    "sg:phone":"+34 981 31 56 02",
    "sg:postcode":"15405",
    "sg:province":"A Coru\u00f1a",
    "wof:name":"Talleres Mecanicos Codesal S.l.",
    "wof:placetype":"venue"
},
  "geometry": {"coordinates":[-8.2403802872,43.5015792847],"type":"Point"}
}