{
  "type": "Feature",
  "properties": {
    "addr:full":"Calle de Menacho, 23 Badajoz Badajoz 06001",
    "addr:housenumber":"23",
    "addr:postcode":"06001",
    "addr:street":"Calle De Menacho",
    "iso:country":"ES",
    "sg:address":"Calle de Menacho, 23",
    "sg:city":"Badajoz",
    "sg:orig_category":"Ropa Para Se\u00d1oras (al Por Menor)",
    "sg:phone":"+34 924 22 92 05",
    "sg:postcode":"06001",
    "sg:province":"Badajoz",
    "sg:website":"www.dandara.es",
    "wof:name":"Spanditex S.a.",
    "wof:placetype":"venue"
},
  "geometry": {"coordinates":[-6.9740333557,38.8771858215],"type":"Point"}
}