{
  "type": "Feature",
  "properties": {
    "iso:country":"ES",
    "sg:address":"Jazmin, 17",
    "sg:city":"Mijas Costa",
    "sg:orig_category":"Empresas De Carpinter\u00cda Met\u00c1lica",
    "sg:phone":"+34 952 46 97 33",
    "sg:postcode":"29649",
    "sg:province":"M\u00e1laga",
    "wof:name":"Gamez Rio Miguel Angel",
    "wof:placetype":"venue"
},
  "geometry": {"coordinates":[-4.6557769775,36.5069389343],"type":"Point"}
}