{
  "type": "Feature",
  "properties": {
    "addr:full":"Calle de Gordoniz, 44 Bilbao Vizcaya 48002",
    "addr:housenumber":"44",
    "addr:postcode":"48002",
    "addr:street":"Calle De Gordoniz",
    "iso:country":"ES",
    "sg:address":"Calle de Gordoniz, 44",
    "sg:city":"Bilbao",
    "sg:orig_category":"Audiovisuales (producci\u00d3n, Edici\u00d3n, Realizaci\u00d3n)",
    "sg:phone":"+34 944 44 62 57",
    "sg:postcode":"48002",
    "sg:province":"Vizcaya",
    "wof:name":"Ikusmedia S.l.",
    "wof:placetype":"venue"
},
  "geometry": {"coordinates":[-2.9452369213,43.2539787292],"type":"Point"}
}