{
  "type": "Feature",
  "properties": {
    "addr:full":"Carrer de Felip Ii, 128 Barcelona Barcelona 08027",
    "addr:housenumber":"128",
    "addr:postcode":"08027",
    "addr:street":"Carrer De Felip Ii",
    "iso:country":"ES",
    "sg:address":"Carrer de Felip Ii, 128",
    "sg:city":"Barcelona",
    "sg:orig_category":"Tapicer\u00cdas",
    "sg:phone":"+34 933 49 45 97",
    "sg:postcode":"08027",
    "sg:province":"Barcelona",
    "wof:name":"Baez Tabero Francisco",
    "wof:placetype":"venue"
},
  "geometry": {"coordinates":[2.1845281124,41.4223861694],"type":"Point"}
}