{
  "type": "Feature",
  "properties": {
    "iso:country":"ES",
    "sg:address":"Gipuzkoa Etorbidea, 6",
    "sg:city":"Arrasate",
    "sg:orig_category":"Electrodom\u00c9sticos (al Por Menor)",
    "sg:phone":"+34 943 79 10 37",
    "sg:postcode":"20500",
    "sg:province":"Guip\u00f9zcoa",
    "wof:name":"Ederlux S.l.",
    "wof:placetype":"venue"
},
  "geometry": {"coordinates":[-2.4821538925,43.0654563904],"type":"Point"}
}