{
  "type": "Feature",
  "properties": {
    "addr:full":"Avda Almendros, 37 Benidorm Alicante 03500",
    "addr:housenumber":"37",
    "addr:postcode":"03500",
    "addr:street":"Avda Almendros",
    "iso:country":"ES",
    "sg:address":"Avda Almendros, 37",
    "sg:city":"Benidorm",
    "sg:orig_category":"Abogados",
    "sg:phone":"+34 965 85 21 28",
    "sg:postcode":"03500",
    "sg:province":"Alicante",
    "wof:name":"Sanchez Delgado Ildefonso",
    "wof:placetype":"venue"
},
  "geometry": {"coordinates":[-0.1743289977,38.5408058167],"type":"Point"}
}