{
  "type": "Feature",
  "properties": {
    "iso:country":"ES",
    "sg:address":"Pol Ind Ca\u00f1ada De La Fuente, S/n",
    "sg:city":"Martos",
    "sg:orig_category":"Fabricaci\u00d3n De Tapices Y Moquetas Para Suelos Y Paredes",
    "sg:phone":"+34 953 55 01 14",
    "sg:postcode":"23600",
    "sg:province":"Ja\u00e9n",
    "wof:name":"Sociedad Cooperativa Andaluza De Terrazos La Pe\u00f1a",
    "wof:placetype":"venue"
},
  "geometry": {"coordinates":[-3.9491291046,37.601436615],"type":"Point"}
}