{
  "type": "Feature",
  "properties": {
    "addr:full":"Carr Saturn, 7 Lleida Lleida 25003",
    "addr:housenumber":"7",
    "addr:postcode":"25003",
    "addr:street":"Carr Saturn",
    "iso:country":"ES",
    "sg:address":"Carr Saturn, 7",
    "sg:city":"Lleida",
    "sg:orig_category":"Empresas De Carpinter\u00cda De Madera",
    "sg:phone":"+34 973 26 28 17",
    "sg:postcode":"25003",
    "sg:province":"Lleida",
    "wof:name":"Pascual Molina Jose",
    "wof:placetype":"venue"
},
  "geometry": {"coordinates":[0.6139330268,41.6109733582],"type":"Point"}
}