{
  "type": "Feature",
  "properties": {
    "addr:full":"Carrer de Amigo, 28 Barcelona Barcelona 08021",
    "addr:housenumber":"28",
    "addr:postcode":"08021",
    "addr:street":"Carrer De Amigo",
    "iso:country":"ES",
    "sg:address":"Carrer de Amigo, 28",
    "sg:city":"Barcelona",
    "sg:orig_category":"Estancos",
    "sg:phone":"+34 932 00 03 16",
    "sg:postcode":"08021",
    "sg:province":"Barcelona",
    "wof:name":"Fortuny Cano Maria Carmen",
    "wof:placetype":"venue"
},
  "geometry": {"coordinates":[2.145359993,41.3947982788],"type":"Point"}
}