{
  "type": "Feature",
  "properties": {
    "addr:full":"Cno. Garrofera, S/n Alcudia Crespins Valencia 46690",
    "addr:housenumber":"/ n",
    "addr:postcode":"46690",
    "addr:street":"Garrofera S",
    "iso:country":"ES",
    "sg:address":"Cno. Garrofera, S/n",
    "sg:city":"Alcudia Crespins",
    "sg:orig_category":"Paneles De Madera: Contrachapados, Fibras, Particulados, Estratificados (fabricaci\u00d3n, Venta)",
    "sg:phone":"+34 962 24 22 10",
    "sg:postcode":"46690",
    "sg:province":"Valencia",
    "wof:name":"Contrachapados Arandiga S.l.",
    "wof:placetype":"venue"
},
  "geometry": {"coordinates":[-0.5928140283,38.973941803],"type":"Point"}
}