{
  "type": "Feature",
  "properties": {
    "iso:country":"ES",
    "sg:address":"Calle de Antonio Gala, 49",
    "sg:city":"Palacios Y Villafranca",
    "sg:orig_category":"Promotores Constructores",
    "sg:phone":"+34 955 81 15 18",
    "sg:postcode":"41720",
    "sg:province":"Sevilla",
    "wof:name":"Construcciones Monroy S.c.a.",
    "wof:placetype":"venue"
},
  "geometry": {"coordinates":[-5.9307403564,37.1580200195],"type":"Point"}
}