{
  "type": "Feature",
  "properties": {
    "addr:full":"Calle de Pozas (las), 1 Alfaro La Rioja 26540",
    "addr:housenumber":"1",
    "addr:postcode":"26540",
    "addr:street":"Calle De Pozas Las;Rioja",
    "iso:country":"ES",
    "sg:address":"Calle de Pozas (las), 1",
    "sg:city":"Alfaro",
    "sg:orig_category":"Arquitectos",
    "sg:phone":"+34 941 18 37 53",
    "sg:postcode":"26540",
    "sg:province":"La Rioja",
    "wof:name":"Fernandez Ordoyo Angel Maria",
    "wof:placetype":"venue"
},
  "geometry": {"coordinates":[-1.7502889633,42.1791801453],"type":"Point"}
}