{
  "type": "Feature",
  "properties": {
    "iso:country":"ES",
    "sg:address":"Carrer de Doctor Marti I Julia, 56",
    "sg:city":"Hospitalet Llobregat",
    "sg:orig_category":"Promotores Constructores",
    "sg:phone":"+34 934 40 90 61",
    "sg:postcode":"08903",
    "sg:province":"Barcelona",
    "wof:name":"Promotora Inmobiliaria Metropolis S.l.",
    "wof:placetype":"venue"
},
  "geometry": {"coordinates":[2.1219880581,41.3739318848],"type":"Point"}
}