{
  "type": "Feature",
  "properties": {
    "iso:country":"ES",
    "sg:address":"Calle de Ereta, 11",
    "sg:city":"Rojales",
    "sg:orig_category":"Zapatos (al Por Menor)",
    "sg:phone":"+34 966 71 23 66",
    "sg:postcode":"03170",
    "sg:province":"Alicante",
    "wof:name":"Ortiz Sanchez Mari Carmen",
    "wof:placetype":"venue"
},
  "geometry": {"coordinates":[-0.7224569917,38.0871543884],"type":"Point"}
}