{
  "type": "Feature",
  "properties": {
    "addr:full":"Calle de Paradores, 3 Madrid Madrid 28023",
    "addr:housenumber":"3",
    "addr:postcode":"28023",
    "addr:street":"Calle De Paradores",
    "iso:country":"ES",
    "sg:address":"Calle de Paradores, 3",
    "sg:city":"Madrid",
    "sg:orig_category":"Centros Empresariales",
    "sg:phone":"+34 913 07 66 35",
    "sg:postcode":"28023",
    "sg:province":"Madrid",
    "wof:name":"Oftalmologia Quirurgica S.l",
    "wof:placetype":"venue"
},
  "geometry": {"coordinates":[-3.8289020061,40.4766807556],"type":"Point"}
}