{
  "type": "Feature",
  "properties": {
    "addr:full":"Pol Ind Cotarrillo, S/n Cabezuela Valle C\u00e1ceres 10610",
    "addr:housenumber":"s / n",
    "addr:postcode":"10610",
    "addr:street":"Ca\u0301Ceres",
    "iso:country":"ES",
    "sg:address":"Pol Ind Cotarrillo, S/n",
    "sg:city":"Cabezuela Valle",
    "sg:orig_category":"Cooperativas Agr\u00cdcolas",
    "sg:phone":"+34 927 47 21 07",
    "sg:postcode":"10610",
    "sg:province":"C\u00e1ceres",
    "wof:name":"Cooperativa Del Campo Nuestra Se\u00f1ora De Piedras Albas",
    "wof:placetype":"venue"
},
  "geometry": {"coordinates":[-5.8069238663,40.1921615601],"type":"Point"}
}