{
  "type": "Feature",
  "properties": {
    "addr:full":"Calle de Mayor, S/n Allepuz Teruel 44145",
    "addr:housenumber":"s",
    "addr:postcode":"44145",
    "addr:street":"Calle De Mayor;/ N",
    "iso:country":"ES",
    "sg:address":"Calle de Mayor, S/n",
    "sg:city":"Allepuz",
    "sg:orig_category":"Comunidades Religiosas",
    "sg:phone":"+34 978 77 81 64",
    "sg:postcode":"44145",
    "sg:province":"Teruel",
    "wof:name":"Parroquia Nuestra Se\u00f1ora De La Purificacion",
    "wof:placetype":"venue"
},
  "geometry": {"coordinates":[-0.7270690203,40.4921836853],"type":"Point"}
}