{
  "type": "Feature",
  "properties": {
    "iso:country":"ES",
    "sg:address":"Calle de Navahermosa, 3",
    "sg:city":"Rozas De Madrid",
    "sg:orig_category":"Venta, Localizaci\u00d3n, Reparaci\u00d3n De Material E Instrumental M\u00c9dico",
    "sg:phone":"+34 916 39 53 99",
    "sg:postcode":"28230",
    "sg:province":"Madrid",
    "wof:name":"Laboratorios Losan S.l.",
    "wof:placetype":"venue"
},
  "geometry": {"coordinates":[-3.8592889309,40.4818534851],"type":"Point"}
}