{
  "type": "Feature",
  "properties": {
    "addr:full":"Av Verge Del Claustre, 1 Solsona Lleida 25280",
    "addr:housenumber":"1",
    "addr:postcode":"25280",
    "addr:street":"Av Verge Del Claustre",
    "iso:country":"ES",
    "sg:address":"Av Verge Del Claustre, 1",
    "sg:city":"Solsona",
    "sg:orig_category":"Sanatorios M\u00c9dico",
    "sg:phone":"+34 973 48 11 72",
    "sg:postcode":"25280",
    "sg:province":"Lleida",
    "wof:name":"Centre Sanitari Del Solsones Fundacio Publica Comarcal",
    "wof:placetype":"venue"
},
  "geometry": {"coordinates":[1.5213140249,41.9950408936],"type":"Point"}
}