{
  "type": "Feature",
  "properties": {
    "iso:country":"ES",
    "sg:address":"Rond Pau Vila, 12",
    "sg:city":"Sabadell",
    "sg:orig_category":"Instalaci\u00d3n, Reparaci\u00d3n De Ascensores Y Montacargas",
    "sg:phone":"+34 937 12 11 91",
    "sg:postcode":"08204",
    "sg:province":"Barcelona",
    "wof:name":"Ascensores Mover S.l.",
    "wof:placetype":"venue"
},
  "geometry": {"coordinates":[2.1160876751,41.5228805542],"type":"Point"}
}