{
  "type": "Feature",
  "properties": {
    "addr:full":"Barr San Esteban, 20 San Esteban Guip\u00f9zcoa 20400",
    "addr:housenumber":"20",
    "addr:postcode":"20400",
    "addr:street":"San Esteban;Guipu\u0300Zcoa",
    "iso:country":"ES",
    "sg:address":"Barr San Esteban, 20",
    "sg:city":"San Esteban",
    "sg:orig_category":"Empresas De Limpieza",
    "sg:phone":"+34 943 65 19 76",
    "sg:postcode":"20400",
    "sg:province":"Guip\u00f9zcoa",
    "wof:name":"Serbitzu Elkartea S.l.",
    "wof:placetype":"venue"
},
  "geometry": {"coordinates":[-2.0820989609,43.1345481873],"type":"Point"}
}