{
  "type": "Feature",
  "properties": {
    "iso:country":"ES",
    "sg:address":"Calle de Parana, 16",
    "sg:city":"Sevilla",
    "sg:orig_category":"Asesor\u00cda Fiscal Y Jur\u00cddica",
    "sg:phone":"+34 954 61 42 62",
    "sg:postcode":"41012",
    "sg:province":"Sevilla",
    "wof:name":"San Juan Ochoa Enrique",
    "wof:placetype":"venue"
},
  "geometry": {"coordinates":[-5.981156826,37.3541603088],"type":"Point"}
}