{
  "type": "Feature",
  "properties": {
    "iso:country":"ES",
    "sg:address":"Carr Caputxins, 5",
    "sg:city":"Vilanova I La Geltru",
    "sg:orig_category":"Televisi\u00d3n, V\u00cddeo: Aparatos Y Accesorios (venta)",
    "sg:phone":"+34 938 93 13 61",
    "sg:postcode":"08800",
    "sg:province":"Barcelona",
    "wof:name":"Radio Televisio Franquet S.l.",
    "wof:placetype":"venue"
},
  "geometry": {"coordinates":[1.7255270481,41.226348877],"type":"Point"}
}