{
  "type": "Feature",
  "properties": {
    "addr:full":"Carr Santa Eugenia, 23 Girona Girona 17005",
    "addr:housenumber":"23",
    "addr:postcode":"17005",
    "addr:street":"Carr Santa Eugenia",
    "iso:country":"ES",
    "sg:address":"Carr Santa Eugenia, 23",
    "sg:city":"Girona",
    "sg:orig_category":"Sindicatos Y Colegios Profesionales",
    "sg:phone":"+34 972 21 31 93",
    "sg:postcode":"17005",
    "sg:province":"Girona",
    "wof:name":"Asociacion Profesional Provincial De Auxiliares Y Ayudantes De Farmacia De Girona",
    "wof:placetype":"venue"
},
  "geometry": {"coordinates":[2.814483881,41.9804725647],"type":"Point"}
}