{
  "type": "Feature",
  "properties": {
    "addr:full":"Pla\u00c7 Paris, S/n Lloret Mar Girona 17310",
    "addr:housenumber":"s / n",
    "addr:postcode":"17310",
    "iso:country":"ES",
    "sg:address":"Pla\u00c7 Paris, S/n",
    "sg:city":"Lloret Mar",
    "sg:orig_category":"Cajas De Ahorro",
    "sg:phone":"+34 972 36 85 57",
    "sg:postcode":"17310",
    "sg:province":"Girona",
    "sg:website":"www.lacaixa.es",
    "wof:name":"Caixa D'estalvis I Pensions De Barcelona",
    "wof:placetype":"venue"
},
  "geometry": {"coordinates":[2.846834898,41.6981697083],"type":"Point"}
}