{
  "type": "Feature",
  "properties": {
    "iso:country":"ES",
    "sg:address":"Serelles, 10",
    "sg:city":"Cocentaina",
    "sg:orig_category":"Hilaturas, Hilos Y Actividades Relacionadas",
    "sg:phone":"+34 965 59 09 11",
    "sg:postcode":"03820",
    "sg:province":"Alicante",
    "wof:name":"Hilaturas Sanchis S. L.",
    "wof:placetype":"venue"
},
  "geometry": {"coordinates":[-0.4571259916,38.7180976868],"type":"Point"}
}