{
  "type": "Feature",
  "properties": {
    "addr:full":"Calle de Trinidad, 3 Villena Alicante 03400",
    "addr:housenumber":"3",
    "addr:postcode":"03400",
    "addr:street":"Calle De Trinidad",
    "iso:country":"ES",
    "sg:address":"Calle de Trinidad, 3",
    "sg:city":"Villena",
    "sg:orig_category":"Comercio De Mobiliario De Oficina",
    "sg:phone":"+34 965 80 47 12",
    "sg:postcode":"03400",
    "sg:province":"Alicante",
    "wof:name":"Cantos Carrion Miguel",
    "wof:placetype":"venue"
},
  "geometry": {"coordinates":[-0.8646110296,38.6306228638],"type":"Point"}
}