{
  "type": "Feature",
  "properties": {
    "iso:country":"ES",
    "sg:address":"Carr Santa Eugenia, 16",
    "sg:city":"Girona",
    "sg:orig_category":"Bisuter\u00cda, Joyer\u00cda, Relojer\u00cda (al Por Menor)",
    "sg:phone":"+34 972 20 32 48",
    "sg:postcode":"17001",
    "sg:province":"Girona",
    "wof:name":"Coma S.cv.",
    "wof:placetype":"venue"
},
  "geometry": {"coordinates":[2.8182311058,41.9821739197],"type":"Point"}
}