{
  "type": "Feature",
  "properties": {
    "iso:country":"ES",
    "sg:address":"Pase Salvador Rueda, 17",
    "sg:city":"Malaga",
    "sg:orig_category":"Perfumer\u00cda Y Cosm\u00c9tica (fabricaci\u00d3n, Al Por Mayor)",
    "sg:phone":"+34 952 21 27 20",
    "sg:postcode":"29016",
    "sg:province":"M\u00e1laga",
    "sg:website":"www.nicolich.com",
    "wof:name":"Laboratorios Nicolich S.l.",
    "wof:placetype":"venue"
},
  "geometry": {"coordinates":[-4.4002070427,36.73046875],"type":"Point"}
}