{
  "type": "Feature",
  "properties": {
    "iso:country":"ES",
    "sg:address":"Carrer de Osona, S/n",
    "sg:city":"Santa Perpetua De Mogoda",
    "sg:orig_category":"Cajas Y Embalajes De Cart\u00d3n Y Papel",
    "sg:phone":"+34 935 74 45 40",
    "sg:postcode":"08130",
    "sg:province":"Barcelona",
    "wof:name":"Tecnicarton S.l.",
    "wof:placetype":"venue"
},
  "geometry": {"coordinates":[2.1809649467,41.5505599976],"type":"Point"}
}