{
  "type": "Feature",
  "properties": {
    "addr:full":"Avda Lepanto, 6 Aduanas Alicante 03730",
    "addr:housenumber":"6",
    "addr:postcode":"03730",
    "addr:street":"Avda Lepanto",
    "iso:country":"ES",
    "sg:address":"Avda Lepanto, 6",
    "sg:city":"Aduanas",
    "sg:orig_category":"Panader\u00cdas, Pasteler\u00cdas, Boller\u00cda Industriale (fabricaci\u00d3n, Al Por Mayor)",
    "sg:phone":"+34 965 79 40 23",
    "sg:postcode":"03730",
    "sg:province":"Alicante",
    "wof:name":"Castell Albi Jose Vicente",
    "wof:placetype":"venue"
},
  "geometry": {"coordinates":[0.1787530035,38.7944259644],"type":"Point"}
}