{
  "type": "Feature",
  "properties": {
    "addr:full":"Calle de Camino Llano, 7 Caceres C\u00e1ceres 10002",
    "addr:housenumber":"7",
    "addr:postcode":"10002",
    "addr:street":"Calle De Camino Llano;Ca\u0301Ceres",
    "iso:country":"ES",
    "sg:address":"Calle de Camino Llano, 7",
    "sg:city":"Caceres",
    "sg:orig_category":"Asesor\u00cdas",
    "sg:phone":"+34 927 22 37 14",
    "sg:postcode":"10002",
    "sg:province":"C\u00e1ceres",
    "wof:name":"Sersys Prevencion S.a.",
    "wof:placetype":"venue"
},
  "geometry": {"coordinates":[-6.3739061356,39.4718666077],"type":"Point"}
}