{
  "type": "Feature",
  "properties": {
    "iso:country":"ES",
    "sg:address":"Calle de Escultor Manuel Rivera Girona, 41",
    "sg:city":"Pilar Horadada",
    "sg:orig_category":"Molduras, Junquillos, Listones Y Molduras Perforadas",
    "sg:phone":"+34 965 35 18 35",
    "sg:postcode":"03190",
    "sg:province":"Alicante",
    "wof:name":"Buian  Sabina",
    "wof:placetype":"venue"
},
  "geometry": {"coordinates":[-0.7898390293,37.8640213013],"type":"Point"}
}