{
  "type": "Feature",
  "properties": {
    "iso:country":"ES",
    "sg:address":"Carrer de Marques De Mulhacen, 23",
    "sg:city":"Barcelona",
    "sg:orig_category":"Asesores De Gesti\u00d3n Del Patrimonio",
    "sg:phone":"+34 932 05 24 85",
    "sg:postcode":"08034",
    "sg:province":"Barcelona",
    "wof:name":"Noumea S.a.",
    "wof:placetype":"venue"
},
  "geometry": {"coordinates":[2.1176719666,41.3919296265],"type":"Point"}
}