{
  "type": "Feature",
  "properties": {
    "iso:country":"ES",
    "sg:address":"Calle de Hileras, 1",
    "sg:city":"Granada",
    "sg:orig_category":"Abogados",
    "sg:phone":"+34 958 26 63 31",
    "sg:postcode":"18001",
    "sg:province":"Granada",
    "wof:name":"Perez Del Castillo Gonzalo",
    "wof:placetype":"venue"
},
  "geometry": {"coordinates":[-3.6006450653,37.1747703552],"type":"Point"}
}