{
  "type": "Feature",
  "properties": {
    "addr:full":"Calle de San Miguel, 5 Trujillo C\u00e1ceres 10200",
    "addr:housenumber":"5",
    "addr:postcode":"10200",
    "addr:street":"Calle De San Miguel;Ca\u0301Ceres",
    "iso:country":"ES",
    "sg:address":"Calle de San Miguel, 5",
    "sg:city":"Trujillo",
    "sg:orig_category":"Bazares, Art\u00cdculos De Limpieza Y De Cocina (al Por Menor)",
    "sg:phone":"+34 927 32 21 00",
    "sg:postcode":"10200",
    "sg:province":"C\u00e1ceres",
    "wof:name":"Mateos Blanco Antonio",
    "wof:placetype":"venue"
},
  "geometry": {"coordinates":[-5.8796391487,39.4592857361],"type":"Point"}
}