{
  "type": "Feature",
  "properties": {
    "addr:full":"Ctra. Calasparra, Km. 0002,0 Cieza Murcia 30530",
    "addr:postcode":"30530",
    "addr:street":"Ctra. Calasparra Km. 0002,0",
    "iso:country":"ES",
    "sg:address":"Ctra. Calasparra, Km. 0002,0",
    "sg:city":"Cieza",
    "sg:orig_category":"Distribuci\u00d3n De Petr\u00d3leo Y Derivados",
    "sg:phone":"+34 968 76 46 15",
    "sg:postcode":"30530",
    "sg:province":"Murcia",
    "wof:name":"Estacion De Servicio Gasocentro Elacho S.l.",
    "wof:placetype":"venue"
},
  "geometry": {"coordinates":[-1.4278639555,38.2456855774],"type":"Point"}
}