{
  "type": "Feature",
  "properties": {
    "iso:country":"ES",
    "sg:address":"Calle de Francisco Navacerrada, 9",
    "sg:city":"Madrid",
    "sg:orig_category":"Procuradores",
    "sg:phone":"+34 913 56 74 36",
    "sg:postcode":"28028",
    "sg:province":"Madrid",
    "wof:name":"Lopez Tora Fernando Francisco",
    "wof:placetype":"venue"
},
  "geometry": {"coordinates":[-3.6697220802,40.4311294556],"type":"Point"}
}