{
  "type": "Feature",
  "properties": {
    "iso:country":"ES",
    "sg:address":"Calle de Pedro De Asua, 55",
    "sg:city":"Vitoria-gasteiz",
    "sg:orig_category":"Asilos De Ancianos. Centros Privados",
    "sg:phone":"+34 945 24 85 64",
    "sg:postcode":"01008",
    "sg:province":"\u00c1lava",
    "wof:name":"Martinez Lachica Josefina",
    "wof:placetype":"venue"
},
  "geometry": {"coordinates":[-2.6903800964,42.8462600708],"type":"Point"}
}