{
  "type": "Feature",
  "properties": {
    "addr:full":"Col Colonia Simon, S/n Sant Marti Girona 17520",
    "addr:postcode":"17520",
    "addr:street":"Col Colonia Simon S / N",
    "iso:country":"ES",
    "sg:address":"Col Colonia Simon, S/n",
    "sg:city":"Sant Marti",
    "sg:orig_category":"Fabrica De Charcuter\u00cda",
    "sg:phone":"+34 972 88 11 50",
    "sg:postcode":"17520",
    "sg:province":"Girona",
    "wof:name":"Artesanies Carlit S.a.",
    "wof:placetype":"venue"
},
  "geometry": {"coordinates":[1.9190262556,42.4326133728],"type":"Point"}
}