{
  "type": "Feature",
  "properties": {
    "addr:full":"Calle de Doctor Fleming, 4 Denia Alicante 03700",
    "addr:housenumber":"4",
    "addr:postcode":"03700",
    "addr:street":"Calle De Doctor Fleming",
    "iso:country":"ES",
    "sg:address":"Calle de Doctor Fleming, 4",
    "sg:city":"Denia",
    "sg:orig_category":"Artes Gr\u00c1ficas, Artes Pl\u00c1sticas (curso)",
    "sg:phone":"+34 965 78 79 83",
    "sg:postcode":"03700",
    "sg:province":"Alicante",
    "wof:name":"Graficas Garcia Contri S.l.",
    "wof:placetype":"venue"
},
  "geometry": {"coordinates":[0.106799297,38.844455719],"type":"Point"}
}