{
  "type": "Feature",
  "properties": {
    "addr:full":"Carr Bastio, 20 Mao Islas Baleares 07703",
    "addr:housenumber":"20",
    "addr:postcode":"07703",
    "addr:street":"Carr Bastio",
    "iso:country":"ES",
    "sg:address":"Carr Bastio, 20",
    "sg:city":"Mao",
    "sg:orig_category":"Arquitectos",
    "sg:phone":"+34 971 35 23 04",
    "sg:postcode":"07703",
    "sg:province":"Islas Baleares",
    "wof:name":"Roman Rivas Rosario",
    "wof:placetype":"venue"
},
  "geometry": {"coordinates":[4.2624797821,39.8894004822],"type":"Point"}
}