{
  "type": "Feature",
  "properties": {
    "iso:country":"ES",
    "sg:address":"Ctra. Silla A Alborache, S/n",
    "sg:city":"Silla",
    "sg:orig_category":"Art\u00cdculos De Madera (fabricaci\u00d3n Y Al Por Mayor)",
    "sg:phone":"+34 961 20 30 57",
    "sg:postcode":"46460",
    "sg:province":"Valencia",
    "wof:name":"Mejormesa S.l.",
    "wof:placetype":"venue"
},
  "geometry": {"coordinates":[-0.4030939937,39.3510513306],"type":"Point"}
}