{
  "type": "Feature",
  "properties": {
    "addr:full":"Avda San Pablo (de), 36 Coslada Madrid 28820",
    "addr:housenumber":"36",
    "addr:postcode":"28820",
    "addr:street":"Avda San Pablo De",
    "iso:country":"ES",
    "sg:address":"Avda San Pablo (de), 36",
    "sg:city":"Coslada",
    "sg:orig_category":"Fabricaci\u00d3n Y Comercio De M\u00c1quinas",
    "sg:phone":"+34 916 60 51 00",
    "sg:postcode":"28820",
    "sg:province":"Madrid",
    "sg:website":"www.sandvik.com",
    "wof:name":"Sandvik Espa\u00d1ola S.a.",
    "wof:placetype":"venue"
},
  "geometry": {"coordinates":[-3.5332100391,40.4329185486],"type":"Point"}
}