{
  "type": "Feature",
  "properties": {
    "addr:full":"Carrer de Muntaner, 570 Barcelona Barcelona 08022",
    "addr:housenumber":"570",
    "addr:postcode":"08022",
    "addr:street":"Carrer De Muntaner",
    "iso:country":"ES",
    "sg:address":"Carrer de Muntaner, 570",
    "sg:city":"Barcelona",
    "sg:orig_category":"Agencias Y Agentes Comerciales, Representantes",
    "sg:phone":"+34 932 11 68 04",
    "sg:postcode":"08022",
    "sg:province":"Barcelona",
    "wof:name":"Ruiz Alvarez Javier",
    "wof:placetype":"venue"
},
  "geometry": {"coordinates":[2.1341910362,41.4060325623],"type":"Point"}
}