{
  "type": "Feature",
  "properties": {
    "iso:country":"ES",
    "sg:address":"Avda San Juan Bosco, 37",
    "sg:city":"Utrera",
    "sg:orig_category":"Panader\u00cdas, Panader\u00cdas",
    "sg:phone":"+34 954 86 15 72",
    "sg:postcode":"41710",
    "sg:province":"Sevilla",
    "wof:name":"Vazquez Romero Jose",
    "wof:placetype":"venue"
},
  "geometry": {"coordinates":[-5.7777252197,37.1794013977],"type":"Point"}
}