{
  "type": "Feature",
  "properties": {
    "iso:country":"ES",
    "sg:address":"Los Naranjos, 5",
    "sg:city":"Madrigal Vera",
    "sg:orig_category":"Quincaller\u00cda (al Por Menor)",
    "sg:phone":"+34 927 56 51 76",
    "sg:postcode":"10480",
    "sg:province":"C\u00e1ceres",
    "wof:name":"Instalaciones Tirado C.b.",
    "wof:placetype":"venue"
},
  "geometry": {"coordinates":[-5.3673648834,40.1477355957],"type":"Point"}
}