{
  "type": "Feature",
  "properties": {
    "addr:full":"Calle de San Jose, 1 Durcal Granada 18650",
    "addr:housenumber":"1",
    "addr:postcode":"18650",
    "addr:street":"Calle De San Jose",
    "iso:country":"ES",
    "sg:address":"Calle de San Jose, 1",
    "sg:city":"Durcal",
    "sg:orig_category":"Inform\u00c1tica, Ofim\u00c1tica (estudios, Asesor\u00cda, Ingenier\u00cda, Formaci\u00d3n)",
    "sg:phone":"+34 958 79 70 71",
    "sg:postcode":"18650",
    "sg:province":"Granada",
    "wof:name":"Iglesias Castillo Jose Maria",
    "wof:placetype":"venue"
},
  "geometry": {"coordinates":[-3.5644159317,36.9862442017],"type":"Point"}
}