{
  "type": "Feature",
  "properties": {
    "iso:country":"ES",
    "sg:address":"Calle de Luisiana (la), S/n",
    "sg:city":"Sevilla",
    "sg:orig_category":"Supermercados Y Hipermercados",
    "sg:phone":"+34 954 35 59 50",
    "sg:postcode":"41008",
    "sg:province":"Sevilla",
    "wof:name":"Super Rocio S.l.",
    "wof:placetype":"venue"
},
  "geometry": {"coordinates":[-5.9765710831,37.4089393616],"type":"Point"}
}