{
  "type": "Feature",
  "properties": {
    "addr:full":"Plaz Constitucion (la), S/n Barbastro Huesca 22300",
    "addr:postcode":"22300",
    "addr:street":"Constitucion La S / N",
    "iso:country":"ES",
    "sg:address":"Plaz Constitucion (la), S/n",
    "sg:city":"Barbastro",
    "sg:orig_category":"Obras Y Organismos Sociales",
    "sg:phone":"+34 974 31 12 97",
    "sg:postcode":"22300",
    "sg:province":"Huesca",
    "wof:name":"Hermanitas De Los Ancianos Desamparados Asilo",
    "wof:placetype":"venue"
},
  "geometry": {"coordinates":[0.1233740002,42.0367393494],"type":"Point"}
}