{
  "type": "Feature",
  "properties": {
    "iso:country":"ES",
    "sg:address":"Av Sant Jordi, 1",
    "sg:city":"Reus",
    "sg:orig_category":"Asesor\u00cda De Formaci\u00d3n Y Gesti\u00d3n De Personal",
    "sg:phone":"+34 977 34 21 01",
    "sg:postcode":"43201",
    "sg:province":"Tarragona",
    "sg:website":"www.pratscanela.com",
    "wof:name":"Prats Canela Assessors S.l.",
    "wof:placetype":"venue"
},
  "geometry": {"coordinates":[1.1077419519,41.1593551636],"type":"Point"}
}