{
  "type": "Feature",
  "properties": {
    "addr:full":"Urb Rio Algarrobo, 40 Algarrobo-costa M\u00e1laga 29750",
    "addr:housenumber":"40",
    "addr:postcode":"29750",
    "addr:street":"Urb;Algarrobo;Ma\u0301Laga",
    "iso:country":"ES",
    "sg:address":"Urb Rio Algarrobo, 40",
    "sg:city":"Algarrobo-costa",
    "sg:orig_category":"Expertos Contables, Revisores De Cuentas",
    "sg:phone":"+34 952 51 15 51",
    "sg:postcode":"29750",
    "sg:province":"M\u00e1laga",
    "wof:name":"Andiplan S.l.",
    "wof:placetype":"venue"
},
  "geometry": {"coordinates":[-4.0481643677,36.7452507019],"type":"Point"}
}