{
  "type": "Feature",
  "properties": {
    "iso:country":"ES",
    "sg:address":"Poli Industrial Archidona, S/n",
    "sg:city":"Archidona",
    "sg:orig_category":"Abogados",
    "sg:phone":"+34 952 71 70 57",
    "sg:postcode":"29300",
    "sg:province":"M\u00e1laga",
    "wof:name":"Consorcio Parque Maquinaria Zona N.o. De La Provincia De Malaga",
    "wof:placetype":"venue"
},
  "geometry": {"coordinates":[-4.3715238571,37.099281311],"type":"Point"}
}