{
  "type": "Feature",
  "properties": {
    "iso:country":"ES",
    "sg:address":"Cmno Suarez, 59",
    "sg:city":"Malaga",
    "sg:orig_category":"Ropa Para Se\u00d1oras (al Por Menor)",
    "sg:phone":"+34 952 39 28 45",
    "sg:postcode":"29010",
    "sg:province":"M\u00e1laga",
    "wof:name":"Inversiones Norte De Africa Sl",
    "wof:placetype":"venue"
},
  "geometry": {"coordinates":[-4.4402427673,36.7278175354],"type":"Point"}
}