{
  "type": "Feature",
  "properties": {
    "addr:full":"Dalt, 25 Selva Mar Girona 17489",
    "addr:housenumber":"25",
    "addr:postcode":"17489",
    "addr:street":"Dalt",
    "iso:country":"ES",
    "sg:address":"Dalt, 25",
    "sg:city":"Selva Mar",
    "sg:orig_category":"Reposter\u00cdas",
    "sg:phone":"+34 972 38 72 68",
    "sg:postcode":"17489",
    "sg:province":"Girona",
    "wof:name":"Arques Galceran Eudaldo",
    "wof:placetype":"venue"
},
  "geometry": {"coordinates":[3.1868870258,42.3238983154],"type":"Point"}
}