{
  "type": "Feature",
  "properties": {
    "iso:country":"ES",
    "sg:address":"Carr Del Music Pare Perez Jorge, 8",
    "sg:city":"Ontinyent",
    "sg:orig_category":"Abogados",
    "sg:phone":"+34 962 38 70 96",
    "sg:postcode":"46870",
    "sg:province":"Valencia",
    "wof:name":"Molla Enguix Laura Maria",
    "wof:placetype":"venue"
},
  "geometry": {"coordinates":[-0.600004971,38.8263969421],"type":"Point"}
}