{
  "type": "Feature",
  "properties": {
    "iso:country":"ES",
    "sg:address":"C/ Riu Sec, 43",
    "sg:city":"Cerdanyola Valles",
    "sg:orig_category":"Construcciones Met\u00c1licas",
    "sg:phone":"+34 935 80 12 29",
    "sg:postcode":"08290",
    "sg:province":"Barcelona",
    "wof:name":"Alberto Aroca S.a.",
    "wof:placetype":"venue"
},
  "geometry": {"coordinates":[2.1369109154,41.4985847473],"type":"Point"}
}