{
  "type": "Feature",
  "properties": {
    "addr:full":"Muelle Levante, S/n Castello Plana Castell\u00f3n 12100",
    "addr:housenumber":"s",
    "addr:postcode":"12100",
    "addr:street":"Levante;/ N",
    "iso:country":"ES",
    "sg:address":"Muelle Levante, S/n",
    "sg:city":"Castello Plana",
    "sg:orig_category":"Piedra, Vidrio, Cer\u00c1mica Y Porcelana",
    "sg:phone":"+34 964 73 70 88",
    "sg:postcode":"12100",
    "sg:province":"Castell\u00f3n",
    "wof:name":"Advanced Materials For Ceramics S. L.",
    "wof:placetype":"venue"
},
  "geometry": {"coordinates":[-0.0360242017,39.9860687256],"type":"Point"}
}