{
  "type": "Feature",
  "properties": {
    "iso:country":"ES",
    "sg:address":"Ctra Sevilla-malaga-granada, Km. 0009,8",
    "sg:city":"Alcala Guadaira",
    "sg:orig_category":"Hormigonados",
    "sg:phone":"+34 955 61 38 40",
    "sg:postcode":"41500",
    "sg:province":"Sevilla",
    "wof:name":"Aridos Y Hormigones Hispalenses S.l.",
    "wof:placetype":"venue"
},
  "geometry": {"coordinates":[-5.8740124702,37.3626556396],"type":"Point"}
}