{
  "type": "Feature",
  "properties": {
    "addr:full":"Calle de Sant Sebastia Patro De Xabia, 1 Javea Alicante 03730",
    "addr:housenumber":"1",
    "addr:postcode":"03730",
    "addr:street":"Calle De Sant Sebastia Patro De Xabia",
    "iso:country":"ES",
    "sg:address":"Calle de Sant Sebastia Patro De Xabia, 1",
    "sg:city":"Javea",
    "sg:orig_category":"Ingeniero",
    "sg:phone":"+34 966 46 14 37",
    "sg:postcode":"03730",
    "sg:province":"Alicante",
    "wof:name":"Romeu Barba Luis Ernesto",
    "wof:placetype":"venue"
},
  "geometry": {"coordinates":[0.1620800048,38.7904396057],"type":"Point"}
}