{
  "type": "Feature",
  "properties": {
    "iso:country":"ES",
    "sg:address":"Avda Habana (la), S/n",
    "sg:city":"Cristianos",
    "sg:orig_category":"Procuradores",
    "sg:phone":"+34 922 79 85 30",
    "sg:postcode":"38650",
    "sg:province":"Santa Cruz De Tenerife",
    "wof:name":"Alvarez Hernandez Manuel Angel",
    "wof:placetype":"venue"
},
  "geometry": {"coordinates":[-16.7233371735,28.053150177],"type":"Point"}
}