{
  "type": "Feature",
  "properties": {
    "addr:full":"Calle de Tejera (la), 2 Soria Soria 42001",
    "addr:housenumber":"2",
    "addr:postcode":"42001",
    "addr:street":"Calle De Tejera La",
    "iso:country":"ES",
    "sg:address":"Calle de Tejera (la), 2",
    "sg:city":"Soria",
    "sg:orig_category":"Muebles Y Accesorios Para Cocinas Y Cuartos De Ba\u00d1o (al Por Menor)",
    "sg:phone":"+34 975 22 90 87",
    "sg:postcode":"42001",
    "sg:province":"Soria",
    "wof:name":"Laseca Rodrigo Jose Luis",
    "wof:placetype":"venue"
},
  "geometry": {"coordinates":[-2.4681680202,41.7665977478],"type":"Point"}
}