{
  "type": "Feature",
  "properties": {
    "addr:full":"Carr Doctor Ramon Y Cajal, 5 Villanueva De Castellon Valencia 46270",
    "addr:housenumber":"5",
    "addr:postcode":"46270",
    "addr:street":"Carr Doctor Ramon Y Cajal",
    "iso:country":"ES",
    "sg:address":"Carr Doctor Ramon Y Cajal, 5",
    "sg:city":"Villanueva De Castellon",
    "sg:orig_category":"Notarios",
    "sg:phone":"+34 962 45 11 65",
    "sg:postcode":"46270",
    "sg:province":"Valencia",
    "wof:name":"Sanz Larrosa Jesus Florencio",
    "wof:placetype":"venue"
},
  "geometry": {"coordinates":[-0.5146909952,39.0791282654],"type":"Point"}
}