{
  "type": "Feature",
  "properties": {
    "iso:country":"ES",
    "sg:address":"Venta Del Prado, S/n",
    "sg:city":"Bollullos Mitacion",
    "sg:orig_category":"Frutas Y Legumbres Frescas (al Por Mayor)",
    "sg:phone":"+34 955 76 50 91",
    "sg:postcode":"41110",
    "sg:province":"Sevilla",
    "wof:name":"Morbe S.l.",
    "wof:placetype":"venue"
},
  "geometry": {"coordinates":[-6.1320338249,37.3372612],"type":"Point"}
}