{
  "type": "Feature",
  "properties": {
    "addr:full":"Carrer de Orient, 68 S. Cugat Valles Barcelona 08172",
    "addr:housenumber":"68",
    "addr:postcode":"08172",
    "addr:street":"Carrer De Orient;S. Cugat Valles Barcelona",
    "iso:country":"ES",
    "sg:address":"Carrer de Orient, 68",
    "sg:city":"S. Cugat Valles",
    "sg:orig_category":"Molduras, Junquillos, Listones Y Molduras Perforadas",
    "sg:phone":"+34 936 74 63 20",
    "sg:postcode":"08172",
    "sg:province":"Barcelona",
    "wof:name":"Palma Hidalgo Manuel",
    "wof:placetype":"venue"
},
  "geometry": {"coordinates":[2.0910360813,41.4746208191],"type":"Point"}
}