{
  "type": "Feature",
  "properties": {
    "iso:country":"ES",
    "sg:address":"Calle de Virgen De La Fuensanta, 3",
    "sg:city":"Granada",
    "sg:orig_category":"Laboratorios Farmac\u00c9uticos",
    "sg:phone":"+34 958 29 13 56",
    "sg:postcode":"18015",
    "sg:province":"Granada",
    "wof:name":"Procter & Gamble Pharmaceuticals Iberia S.l.",
    "wof:placetype":"venue"
},
  "geometry": {"coordinates":[-3.625549078,37.1905517578],"type":"Point"}
}