{
  "type": "Feature",
  "properties": {
    "iso:country":"ES",
    "sg:address":"Calle de Cervantes, 33",
    "sg:city":"Oviedo",
    "sg:orig_category":"Fisioterapia",
    "sg:phone":"+34 984 05 16 14",
    "sg:postcode":"33004",
    "sg:province":"Asturias",
    "wof:name":"Jose Manuel Rodriguez Aller",
    "wof:placetype":"venue"
},
  "geometry": {"coordinates":[-5.8571209908,43.3640670776],"type":"Point"}
}