{
  "type": "Feature",
  "properties": {
    "iso:country":"ES",
    "sg:address":"Carrer de Vicen\u00c7 J Rossello, 36",
    "sg:city":"Palma",
    "sg:orig_category":"Plomeros",
    "sg:phone":"+34 971 45 70 70",
    "sg:postcode":"07013",
    "sg:province":"Islas Baleares",
    "wof:name":"Juan Antonio Porcel S.l.",
    "wof:placetype":"venue"
},
  "geometry": {"coordinates":[2.6324100494,39.578742981],"type":"Point"}
}