{
  "type": "Feature",
  "properties": {
    "addr:full":"Plaz Salvador, Del, 2 Talavera Reina Toledo 45600",
    "addr:postcode":"45600",
    "iso:country":"ES",
    "sg:address":"Plaz Salvador, Del, 2",
    "sg:city":"Talavera Reina",
    "sg:classifiers":[
        {
            "category":"Personal",
            "subcategory":"Barber",
            "type":"Services"
        }
    ],
    "sg:phone":"+34 925 82 80 15",
    "sg:postcode":"45600",
    "sg:province":"Toledo",
    "sg:tags":[
        "caballeros",
        "de",
        "peluqueros"
    ],
    "wof:name":"Aznar Palomino Francisco",
    "wof:placetype":"venue"
},
  "geometry": {"coordinates":[-4.8360080719,39.9596061707],"type":"Point"}
}