{
  "type": "Feature",
  "properties": {
    "addr:full":"Avda Santa Cruz (la), Km. 0008,0 Santa Cruz De Bezana Cantabria 39100",
    "addr:postcode":"39100",
    "addr:street":"Avda Santa Cruz La Km. 0008,0",
    "iso:country":"ES",
    "sg:address":"Avda Santa Cruz (la), Km. 0008,0",
    "sg:city":"Santa Cruz De Bezana",
    "sg:orig_category":"Caf\u00c9s, Bares, Cervecer\u00cdas",
    "sg:phone":"+34 942 58 02 27",
    "sg:postcode":"39100",
    "sg:province":"Cantabria",
    "wof:name":"Arce Gonzalez Virgilio",
    "wof:placetype":"venue"
},
  "geometry": {"coordinates":[-3.9067556858,43.4363098145],"type":"Point"}
}