{
  "type": "Feature",
  "properties": {
    "addr:full":"Carrer de Felip Ii, 27 Palma Islas Baleares 07010",
    "addr:housenumber":"27",
    "addr:postcode":"07010",
    "addr:street":"Carrer De Felip Ii",
    "iso:country":"ES",
    "sg:address":"Carrer de Felip Ii, 27",
    "sg:city":"Palma",
    "sg:classifiers":[
        {
            "category":"Autos & Motor Vehicles",
            "subcategory":"Automobile Sales",
            "type":"Retail Goods"
        }
    ],
    "sg:phone":"+34 971 75 33 49",
    "sg:postcode":"07010",
    "sg:province":"Islas Baleares",
    "wof:name":"Saez Yag\u00fce Francisco",
    "wof:placetype":"venue"
},
  "geometry": {"coordinates":[2.6486709118,39.5904350281],"type":"Point"}
}