{
  "type": "Feature",
  "properties": {
    "iso:country":"ES",
    "sg:address":"Av. Zaragoza, 72",
    "sg:city":"Iru\u00f1a",
    "sg:orig_category":"Asesor\u00cda Sobre Comunicaci\u00d3n De Empresas",
    "sg:phone":"+34 948 23 83 82",
    "sg:postcode":"31006",
    "sg:province":"Navarra",
    "wof:name":"Novillo Riusech Ana",
    "wof:placetype":"venue"
},
  "geometry": {"coordinates":[-1.6439839602,42.8017845154],"type":"Point"}
}