{
  "type": "Feature",
  "properties": {
    "addr:full":"Calle de Papiro (del), 12 Fuenlabrada Madrid 28946",
    "addr:housenumber":"12",
    "addr:postcode":"28946",
    "addr:street":"Calle De Papiro Del",
    "iso:country":"ES",
    "sg:address":"Calle de Papiro (del), 12",
    "sg:city":"Fuenlabrada",
    "sg:orig_category":"Equipo De Refrigeraci\u00d3n Industrial",
    "sg:phone":"+34 916 21 49 20",
    "sg:postcode":"28946",
    "sg:province":"Madrid",
    "sg:website":"www.ritalespo.com",
    "wof:name":"Ritalespo S.a",
    "wof:placetype":"venue"
},
  "geometry": {"coordinates":[-3.7643399239,40.266292572],"type":"Point"}
}