{
  "type": "Feature",
  "properties": {
    "addr:full":"Avda Manuel De Falla, 13 Valencia Valencia 46015",
    "addr:housenumber":"13",
    "addr:postcode":"46015",
    "addr:street":"Avda Manuel De Falla",
    "iso:country":"ES",
    "sg:address":"Avda Manuel De Falla, 13",
    "sg:city":"Valencia",
    "sg:orig_category":"Loter\u00cda Y T\u00d3mbola",
    "sg:phone":"+34 963 40 91 76",
    "sg:postcode":"46015",
    "sg:province":"Valencia",
    "wof:name":"Beneyto Casado Luis",
    "wof:placetype":"venue"
},
  "geometry": {"coordinates":[-0.4042859972,39.4750595093],"type":"Point"}
}