{
  "type": "Feature",
  "properties": {
    "iso:country":"ES",
    "sg:address":"Carrer de Comtes De Bell Lloc, 188",
    "sg:city":"Barcelona",
    "sg:orig_category":"Veh\u00cdculos De Ocasi\u00d3n",
    "sg:phone":"+34 934 90 93 69",
    "sg:postcode":"08014",
    "sg:province":"Barcelona",
    "wof:name":"Sanz Tena Ismael Tadeo",
    "wof:placetype":"venue"
},
  "geometry": {"coordinates":[2.1355988979,41.383354187],"type":"Point"}
}