{
  "type": "Feature",
  "properties": {
    "addr:full":"Calle de San Ignacio, 5 Valladolid Valladolid 47003",
    "addr:housenumber":"5",
    "addr:postcode":"47003",
    "addr:street":"Calle De San Ignacio",
    "iso:country":"ES",
    "sg:address":"Calle de San Ignacio, 5",
    "sg:city":"Valladolid",
    "sg:orig_category":"Inform\u00c1tica, Ofim\u00c1tica (estudios, Asesor\u00cda, Ingenier\u00cda, Formaci\u00d3n)",
    "sg:phone":"+34 983 33 22 10",
    "sg:postcode":"47003",
    "sg:province":"Valladolid",
    "wof:name":"En Pc Soluciones S.l.",
    "wof:placetype":"venue"
},
  "geometry": {"coordinates":[-4.7290930748,41.6553421021],"type":"Point"}
}