{
  "type": "Feature",
  "properties": {
    "iso:country":"ES",
    "sg:address":"Avda San Pedro, 18",
    "sg:city":"Lardero",
    "sg:orig_category":"Reposter\u00cdas",
    "sg:phone":"+34 941 44 80 12",
    "sg:postcode":"26140",
    "sg:province":"La Rioja",
    "wof:name":"Panaderia Anton S.cv.",
    "wof:placetype":"venue"
},
  "geometry": {"coordinates":[-2.4588179588,42.423122406],"type":"Point"}
}