{
  "type": "Feature",
  "properties": {
    "addr:full":"Calle de Princesa, 35 Madrid Madrid 28008",
    "addr:housenumber":"35",
    "addr:postcode":"madrid;28008",
    "addr:street":"Calle De Princesa",
    "iso:country":"ES",
    "sg:address":"Calle de Princesa, 35",
    "sg:city":"Madrid",
    "sg:orig_category":"Asesor\u00cda Fiscal Y Jur\u00cddica",
    "sg:phone":"+34 915 59 51 54",
    "sg:postcode":"28008",
    "sg:province":"Madrid",
    "wof:name":"Esteban Garcia Francisco Javier",
    "wof:placetype":"venue"
},
  "geometry": {"coordinates":[-3.7150309086,40.4286499023],"type":"Point"}
}