{
  "type": "Feature",
  "properties": {
    "addr:full":"Avda Ramon Y Cajal, 23 Yuncos Toledo 45210",
    "addr:housenumber":"23",
    "addr:postcode":"45210",
    "addr:street":"Avda Ramon Y Cajal",
    "iso:country":"ES",
    "sg:address":"Avda Ramon Y Cajal, 23",
    "sg:city":"Yuncos",
    "sg:orig_category":"Venta, Montaje De Neum\u00c1ticos",
    "sg:phone":"+34 925 53 77 68",
    "sg:postcode":"45210",
    "sg:province":"Toledo",
    "sg:website":"www.paginasamarillas.es",
    "wof:name":"Hermanas Maximiano S.l.",
    "wof:placetype":"venue"
},
  "geometry": {"coordinates":[-3.8727099895,40.0870780945],"type":"Point"}
}