{
  "type": "Feature",
  "properties": {
    "iso:country":"ES",
    "sg:address":"Cmno Moncada, 130",
    "sg:city":"Valencia",
    "sg:orig_category":"Electricidad, Electr\u00d3nica: Suministros (al Por Menor)",
    "sg:phone":"+34 963 65 64 51",
    "sg:postcode":"46025",
    "sg:province":"Valencia",
    "wof:name":"Kensound Direccion Comercial S.l.",
    "wof:placetype":"venue"
},
  "geometry": {"coordinates":[-0.3809449971,39.4968261719],"type":"Point"}
}