{
  "type": "Feature",
  "properties": {
    "iso:country":"ES",
    "sg:address":"Plaz Valle Del Baztan, S/n",
    "sg:city":"Bilbao",
    "sg:orig_category":"Librer\u00cdas",
    "sg:phone":"+34 944 47 85 13",
    "sg:postcode":"48015",
    "sg:province":"Vizcaya",
    "wof:name":"Lucas Pintado Maria Isabel",
    "wof:placetype":"venue"
},
  "geometry": {"coordinates":[-2.9590039253,43.2786598206],"type":"Point"}
}