{
  "type": "Feature",
  "properties": {
    "iso:country":"ES",
    "sg:address":"Ctra Valencia-alicante, Km. 0124,4",
    "sg:city":"Benidorm",
    "sg:orig_category":"Distribuci\u00d3n De Petr\u00d3leo Y Derivados",
    "sg:phone":"+34 965 85 72 51",
    "sg:postcode":"03500",
    "sg:province":"Alicante",
    "wof:name":"Agip Espa\u00f1a S.a.",
    "wof:placetype":"venue"
},
  "geometry": {"coordinates":[-0.1306636035,38.5529975891],"type":"Point"}
}