{
  "type": "Feature",
  "properties": {
    "iso:country":"ES",
    "sg:address":"Calle de Pozuetakogaina Kalea, 7",
    "sg:city":"Irun",
    "sg:orig_category":"Empresas De Pintura Y Revestimientos",
    "sg:phone":"+34 943 61 06 02",
    "sg:postcode":"20305",
    "sg:province":"Guip\u00f9zcoa",
    "wof:name":"Construcciones Y Reformas Cortajarena S.l.",
    "wof:placetype":"venue"
},
  "geometry": {"coordinates":[-1.8149399757,43.3364982605],"type":"Point"}
}