{
  "type": "Feature",
  "properties": {
    "iso:country":"ES",
    "sg:address":"Avda Pais Valencia (del), 30",
    "sg:city":"Onda",
    "sg:orig_category":"Reposter\u00cdas",
    "sg:phone":"+34 964 60 08 26",
    "sg:postcode":"12200",
    "sg:province":"Castell\u00f3n",
    "wof:name":"Panaderia Alvaro C.b.",
    "wof:placetype":"venue"
},
  "geometry": {"coordinates":[-0.2599479854,39.9653816223],"type":"Point"}
}