{
  "type": "Feature",
  "properties": {
    "addr:full":"Calle de Tirma, 17 Palmas De Gran Canaria Las Palmas 35009",
    "addr:housenumber":"17",
    "addr:postcode":"35009",
    "addr:street":"Calle De Tirma",
    "iso:country":"ES",
    "sg:address":"Calle de Tirma, 17",
    "sg:city":"Palmas De Gran Canaria",
    "sg:orig_category":"Mec\u00c1nico Del Autom\u00d3vil",
    "sg:phone":"+34 928 46 84 50",
    "sg:postcode":"35009",
    "sg:province":"Las Palmas",
    "wof:name":"Ramirez Santana Antonio",
    "wof:placetype":"venue"
},
  "geometry": {"coordinates":[-15.422826767,28.1534957886],"type":"Point"}
}