{
  "type": "Feature",
  "properties": {
    "addr:full":"Avda Monforte De Lemos, S/n Madrid Madrid 28029",
    "addr:housenumber":"s / n",
    "addr:postcode":"28029",
    "addr:street":"Avda Monforte De Lemos",
    "iso:country":"ES",
    "sg:address":"Avda Monforte De Lemos, S/n",
    "sg:city":"Madrid",
    "sg:orig_category":"Camiser\u00cda Y Ropa Interior Masculina (al Por Menor)",
    "sg:phone":"+34 917 39 97 29",
    "sg:postcode":"28029",
    "sg:province":"Madrid",
    "wof:name":"Pe\u00f1a Fernandez Manuel",
    "wof:placetype":"venue"
},
  "geometry": {"coordinates":[-3.7155539989,40.4773712158],"type":"Point"}
}