{
  "type": "Feature",
  "properties": {
    "addr:full":"Fco. Nacher Pons, 2 Massanassa Valencia 46470",
    "addr:housenumber":"2",
    "addr:postcode":"46470",
    "addr:street":"Pons",
    "iso:country":"ES",
    "sg:address":"Fco. Nacher Pons, 2",
    "sg:city":"Massanassa",
    "sg:orig_category":"Reposter\u00cdas",
    "sg:phone":"+34 961 25 22 11",
    "sg:postcode":"46470",
    "sg:province":"Valencia",
    "wof:name":"Valls Llobat Francisco",
    "wof:placetype":"venue"
},
  "geometry": {"coordinates":[-0.3960340023,39.4094390869],"type":"Point"}
}