{
  "type": "Feature",
  "properties": {
    "addr:full":"Mcdo Central, 43 Zaragoza Zaragoza 50003",
    "addr:housenumber":"43",
    "addr:postcode":"50003",
    "iso:country":"ES",
    "sg:address":"Mcdo Central, 43",
    "sg:city":"Zaragoza",
    "sg:orig_category":"Carnicer\u00cdas, Carnicer\u00cdas",
    "sg:phone":"+34 976 43 85 79",
    "sg:postcode":"50003",
    "sg:province":"Zaragoza",
    "wof:name":"Capilla Sanz Juan Carlos",
    "wof:placetype":"venue"
},
  "geometry": {"coordinates":[-0.8813189864,41.6517295837],"type":"Point"}
}