{
  "type": "Feature",
  "properties": {
    "addr:full":"Rua Conchases, 19 Grove Pontevedra 36980",
    "addr:housenumber":"19",
    "addr:postcode":"36980",
    "addr:street":"Rua Conchases;Grove Pontevedra",
    "iso:country":"ES",
    "sg:address":"Rua Conchases, 19",
    "sg:city":"Grove",
    "sg:orig_category":"Artes Gr\u00c1ficas, Artes Pl\u00c1sticas: Material Y Suministros (al Por Menor)",
    "sg:phone":"+34 986 73 28 47",
    "sg:postcode":"36980",
    "sg:province":"Pontevedra",
    "wof:name":"Otero Iglesias Maria Dolores",
    "wof:placetype":"venue"
},
  "geometry": {"coordinates":[-8.8682661057,42.4936943054],"type":"Point"}
}