{
  "type": "Feature",
  "properties": {
    "addr:full":"Calle de Pio Xii, 90 Palmas De Gran Canaria Las Palmas 35006",
    "addr:housenumber":"90",
    "addr:postcode":"35006",
    "addr:street":"Calle De Pio Xii",
    "iso:country":"ES",
    "sg:address":"Calle de Pio Xii, 90",
    "sg:city":"Palmas De Gran Canaria",
    "sg:orig_category":"Panader\u00cdas, Panader\u00cdas",
    "sg:phone":"+34 928 23 11 08",
    "sg:postcode":"35006",
    "sg:province":"Las Palmas",
    "wof:name":"Dulceria Colomar S.l.",
    "wof:placetype":"venue"
},
  "geometry": {"coordinates":[-15.4331111908,28.1317234039],"type":"Point"}
}