{
  "type": "Feature",
  "properties": {
    "addr:full":"Calle de Pinillos, 16 Puebla Del Rio Sevilla 41130",
    "addr:housenumber":"16",
    "addr:postcode":"41130",
    "addr:street":"Calle De Pinillos",
    "iso:country":"ES",
    "sg:address":"Calle de Pinillos, 16",
    "sg:city":"Puebla Del Rio",
    "sg:orig_category":"Cervezas (negociantes Y Depositarios)",
    "sg:phone":"+34 955 77 15 27",
    "sg:postcode":"41130",
    "sg:province":"Sevilla",
    "wof:name":"Carrillo Murillo Juan Carlos",
    "wof:placetype":"venue"
},
  "geometry": {"coordinates":[-6.0627598763,37.2698898315],"type":"Point"}
}