{
  "type": "Feature",
  "properties": {
    "iso:country":"ES",
    "sg:address":"Calle de Mayor, 5",
    "sg:city":"Calpe",
    "sg:orig_category":"Partidos Pol\u00cdticos",
    "sg:phone":"+34 965 83 94 85",
    "sg:postcode":"03710",
    "sg:province":"Alicante",
    "wof:name":"Partido Socialista Obrero Espa\u00f1ol",
    "wof:placetype":"venue"
},
  "geometry": {"coordinates":[0.0478550009,38.6447563171],"type":"Point"}
}