{
  "type": "Feature",
  "properties": {
    "iso:country":"ES",
    "sg:address":"Calle de Toboso, 121",
    "sg:city":"Madrid",
    "sg:orig_category":"Asesor\u00cda Fiscal Y Jur\u00cddica",
    "sg:phone":"+34 914 66 61 47",
    "sg:postcode":"28019",
    "sg:province":"Madrid",
    "wof:name":"Baez Santiago Joaquin",
    "wof:placetype":"venue"
},
  "geometry": {"coordinates":[-3.7375764847,40.3926086426],"type":"Point"}
}