{
  "type": "Feature",
  "properties": {
    "addr:full":"Calle de Ancha, 25 Sanlucar De Barrameda C\u00e1diz 11540",
    "addr:housenumber":"25",
    "addr:postcode":"11540",
    "addr:street":"Calle De Ancha;Ca\u0301Diz",
    "iso:country":"ES",
    "sg:address":"Calle de Ancha, 25",
    "sg:city":"Sanlucar De Barrameda",
    "sg:orig_category":"Ense\u00d1ante, Direcci\u00d3n",
    "sg:phone":"+34 956 36 82 69",
    "sg:postcode":"11540",
    "sg:province":"C\u00e1diz",
    "wof:name":"Berma C.b.",
    "wof:placetype":"venue"
},
  "geometry": {"coordinates":[-6.3528780937,36.7791862488],"type":"Point"}
}