{
  "type": "Feature",
  "properties": {
    "addr:full":"Carrer de Doctor Santpon\u00c7, 103 Barcelona Barcelona 08030",
    "addr:housenumber":"103",
    "addr:postcode":"08030",
    "addr:street":"Carrer De Doctor Santponc\u0327",
    "iso:country":"ES",
    "sg:address":"Carrer de Doctor Santpon\u00c7, 103",
    "sg:city":"Barcelona",
    "sg:orig_category":"Farmacias",
    "sg:phone":"+34 932 74 42 44",
    "sg:postcode":"08030",
    "sg:province":"Barcelona",
    "wof:name":"Sabate Faura Jaume",
    "wof:placetype":"venue"
},
  "geometry": {"coordinates":[2.1929268837,41.4319992065],"type":"Point"}
}