{
  "type": "Feature",
  "properties": {
    "iso:country":"ES",
    "sg:address":"Calle de Larga, 43",
    "sg:city":"Cespedosa",
    "sg:orig_category":"Cooperativas Agr\u00cdcolas",
    "sg:phone":"+34 923 15 26 55",
    "sg:postcode":"37750",
    "sg:province":"Salamanca",
    "wof:name":"Cooperativa Agricola San Isidro",
    "wof:placetype":"venue"
},
  "geometry": {"coordinates":[-5.4954838753,40.5237083435],"type":"Point"}
}