{
  "type": "Feature",
  "properties": {
    "iso:country":"ES",
    "sg:address":"C/ Valls, 24",
    "sg:city":"Banyoles",
    "sg:orig_category":"Empresarios",
    "sg:phone":"+34 972 57 20 03",
    "sg:postcode":"17820",
    "sg:province":"Girona",
    "wof:name":"Coll Barcelo Juan",
    "wof:placetype":"venue"
},
  "geometry": {"coordinates":[2.7661290169,42.1191978455],"type":"Point"}
}