{
  "type": "Feature",
  "properties": {
    "addr:full":"Avda Principe De Asturias, 20 Zamora Zamora 49012",
    "addr:housenumber":"20",
    "addr:postcode":"49012",
    "addr:street":"Avda Principe De Asturias",
    "iso:country":"ES",
    "sg:address":"Avda Principe De Asturias, 20",
    "sg:city":"Zamora",
    "sg:orig_category":"Ense\u00d1anza Variada",
    "sg:phone":"+34 980 52 70 56",
    "sg:postcode":"49012",
    "sg:province":"Zamora",
    "wof:name":"Rubio Fernandez Carmen",
    "wof:placetype":"venue"
},
  "geometry": {"coordinates":[-5.7373490334,41.5107841492],"type":"Point"}
}