{
  "type": "Feature",
  "properties": {
    "addr:full":"Calle de Ramona Rodriguez Bustelo, 7 Nore\u00f1a Asturias 33180",
    "addr:housenumber":"7",
    "addr:postcode":"33180",
    "addr:street":"Calle De Ramona Rodriguez Bustelo;Asturias",
    "iso:country":"ES",
    "sg:address":"Calle de Ramona Rodriguez Bustelo, 7",
    "sg:city":"Nore\u00f1a",
    "sg:orig_category":"Electricidad: Instalaciones Industriales",
    "sg:phone":"+34 985 74 02 81",
    "sg:postcode":"33180",
    "sg:province":"Asturias",
    "wof:name":"Instalaciones Electricas Electroastur S.l.",
    "wof:placetype":"venue"
},
  "geometry": {"coordinates":[-5.7084541321,43.3945350647],"type":"Point"}
}