{
  "type": "Feature",
  "properties": {
    "addr:full":"Plaza Fuente Del Ni\u00f1o, S/n Salinas Asturias 33405",
    "addr:housenumber":"/ n",
    "addr:postcode":"33405",
    "addr:street":"Fuente;Nin\u0303O S",
    "iso:country":"ES",
    "sg:address":"Plaza Fuente Del Ni\u00f1o, S/n",
    "sg:city":"Salinas",
    "sg:classifiers":[
        {
            "category":"Taxi",
            "type":"Transportation"
        }
    ],
    "sg:phone":"+34 985 50 08 44",
    "sg:postcode":"33405",
    "sg:province":"Asturias",
    "wof:name":"Ayuntamiento De Castrillon",
    "wof:placetype":"venue"
},
  "geometry": {"coordinates":[-5.9627838135,43.5750160217],"type":"Point"}
}