{
  "type": "Feature",
  "properties": {
    "addr:full":"Carr Humbert Torres, 18 Lleida Lleida 25008",
    "addr:housenumber":"18",
    "addr:postcode":"25008",
    "addr:street":"Carr Humbert Torres",
    "iso:country":"ES",
    "sg:address":"Carr Humbert Torres, 18",
    "sg:city":"Lleida",
    "sg:orig_category":"M\u00c9dicos: Naturistas",
    "sg:phone":"+34 973 24 69 58",
    "sg:postcode":"25008",
    "sg:province":"Lleida",
    "wof:name":"Geli Gasso Jose Miguel",
    "wof:placetype":"venue"
},
  "geometry": {"coordinates":[0.6208069921,41.6225700378],"type":"Point"}
}