{
  "type": "Feature",
  "properties": {
    "iso:country":"ES",
    "sg:address":"Calle de Salamanca, 32",
    "sg:city":"Santa Cruz De Tenerife",
    "sg:orig_category":"Peluqueros: De Se\u00d1oras",
    "sg:phone":"+34 922 24 96 36",
    "sg:postcode":"38006",
    "sg:province":"Santa Cruz De Tenerife",
    "wof:name":"Ledesma Delgado Raimundo",
    "wof:placetype":"venue"
},
  "geometry": {"coordinates":[-16.2633743286,28.4691467285],"type":"Point"}
}