{
  "type": "Feature",
  "properties": {
    "iso:country":"ES",
    "sg:address":"Calle de Lainomendi Kalea, 2",
    "sg:city":"Aldekona",
    "sg:orig_category":"Iglesia Cat\u00d3lica",
    "sg:phone":"+34 944 54 11 24",
    "sg:postcode":"48160",
    "sg:province":"Vizcaya",
    "wof:name":"Obispado De Bilbao",
    "wof:placetype":"venue"
},
  "geometry": {"coordinates":[-2.9316000938,43.2383995056],"type":"Point"}
}