{
  "type": "Feature",
  "properties": {
    "iso:country":"ES",
    "sg:address":"Pl Major, 4",
    "sg:city":"Gava",
    "sg:orig_category":"Carnicer\u00cdas, Carnicer\u00cdas",
    "sg:phone":"+34 936 62 02 85",
    "sg:postcode":"08850",
    "sg:province":"Barcelona",
    "wof:name":"Agusti Arnal Josefa",
    "wof:placetype":"venue"
},
  "geometry": {"coordinates":[2.0054719448,41.3050613403],"type":"Point"}
}