{
  "type": "Feature",
  "properties": {
    "iso:country":"ES",
    "sg:address":"Ctra San Clemente, S/n",
    "sg:city":"Villarrobledo",
    "sg:orig_category":"Fabricaci\u00d3n De Quesos",
    "sg:phone":"+34 967 14 51 10",
    "sg:postcode":"02600",
    "sg:province":"Albacete",
    "wof:name":"Lopez Haro Juan",
    "wof:placetype":"venue"
},
  "geometry": {"coordinates":[-2.5846590996,39.2837142944],"type":"Point"}
}