{
  "type": "Feature",
  "properties": {
    "addr:full":"Luga Orial, 11 Orial Asturias 33186",
    "addr:housenumber":"11",
    "addr:postcode":"33186",
    "addr:street":"Orial;Asturias",
    "iso:country":"ES",
    "sg:address":"Luga Orial, 11",
    "sg:city":"Orial",
    "sg:orig_category":"Charcuter\u00cdas (al Por Mayor)",
    "sg:phone":"+34 985 74 07 45",
    "sg:postcode":"33186",
    "sg:province":"Asturias",
    "wof:name":"Martinez Fernandez Maria Del Carmen",
    "wof:placetype":"venue"
},
  "geometry": {"coordinates":[-5.7012858391,43.3833732605],"type":"Point"}
}