{
  "type": "Feature",
  "properties": {
    "iso:country":"ES",
    "sg:address":"Calle de Daimiel, 11",
    "sg:city":"Puertollano",
    "sg:orig_category":"Asilos De Ancianos. Centros Privados",
    "sg:phone":"+34 926 42 72 26",
    "sg:postcode":"13500",
    "sg:province":"Ciudad Real",
    "wof:name":"Junta De Comunidades Castilla-la Mancha",
    "wof:placetype":"venue"
},
  "geometry": {"coordinates":[-4.1068935394,38.7038192749],"type":"Point"}
}