{
  "type": "Feature",
  "properties": {
    "addr:full":"Carr Agulla, De L', 81 Cala Ratjada Islas Baleares 07590",
    "addr:housenumber":"81",
    "addr:postcode":"07590",
    "addr:street":"Carr Agulla De L '",
    "iso:country":"ES",
    "sg:address":"Carr Agulla, De L', 81",
    "sg:city":"Cala Ratjada",
    "sg:orig_category":"Bazares, Art\u00cdculos De Limpieza Y De Cocina (al Por Menor)",
    "sg:phone":"+34 971 56 50 77",
    "sg:postcode":"07590",
    "sg:province":"Islas Baleares",
    "wof:name":"Vives Riera Antonio",
    "wof:placetype":"venue"
},
  "geometry": {"coordinates":[2.8577105999,39.5341796875],"type":"Point"}
}