{
  "type": "Feature",
  "properties": {
    "iso:country":"ES",
    "sg:address":"Calle de Dionisio Guardiola, 40",
    "sg:city":"Albacete",
    "sg:orig_category":"Caf\u00c9s, Bares, Cervecer\u00cdas",
    "sg:phone":"+34 967 22 40 36",
    "sg:postcode":"02003",
    "sg:province":"Albacete",
    "wof:name":"Carrion Beltran Miguel",
    "wof:placetype":"venue"
},
  "geometry": {"coordinates":[-1.8592755795,38.9928321838],"type":"Point"}
}