{
  "type": "Feature",
  "properties": {
    "iso:country":"ES",
    "sg:address":"Calle de Bolea, 3",
    "sg:city":"Elche Sierra",
    "sg:orig_category":"Confecci\u00d3n (fabricaci\u00d3n, Al Por Mayor)",
    "sg:phone":"+34 967 41 11 58",
    "sg:postcode":"02430",
    "sg:province":"Albacete",
    "wof:name":"Rodriguez Garcia Antonio",
    "wof:placetype":"venue"
},
  "geometry": {"coordinates":[-1.6613692045,38.5615997314],"type":"Point"}
}