{
  "type": "Feature",
  "properties": {
    "addr:full":"Avda Moreda, 8 Gijon Asturias 33212",
    "addr:housenumber":"8",
    "addr:postcode":"33212",
    "addr:street":"Avda Moreda",
    "iso:country":"ES",
    "sg:address":"Avda Moreda, 8",
    "sg:city":"Gijon",
    "sg:orig_category":"Molduras, Junquillos, Listones Y Molduras Perforadas",
    "sg:phone":"+34 985 32 15 35",
    "sg:postcode":"33212",
    "sg:province":"Asturias",
    "wof:name":"Fernandez Fernandez Elvira",
    "wof:placetype":"venue"
},
  "geometry": {"coordinates":[-5.6637988091,43.5420341492],"type":"Point"}
}