{
  "type": "Feature",
  "properties": {
    "iso:country":"ES",
    "sg:address":"Pol Barrios, 12",
    "sg:city":"Rojales",
    "sg:orig_category":"Muebles",
    "sg:phone":"+34 966 79 28 12",
    "sg:postcode":"03170",
    "sg:province":"Alicante",
    "wof:name":"Lorca Cabrera Manuel",
    "wof:placetype":"venue"
},
  "geometry": {"coordinates":[-0.7292140126,38.0850296021],"type":"Point"}
}