{
  "type": "Feature",
  "properties": {
    "iso:country":"ES",
    "sg:address":"Calle de Alcalde Lia\u00d1o Flores, 17",
    "sg:city":"Coru\u00d1a",
    "sg:orig_category":"Librer\u00cdas",
    "sg:phone":"+34 981 26 51 99",
    "sg:postcode":"15010",
    "sg:province":"La Coru\u00f1a",
    "wof:name":"Libreria Don Bosco;sl",
    "wof:placetype":"venue"
},
  "geometry": {"coordinates":[-8.4246912003,43.3627090454],"type":"Point"}
}