{
  "type": "Feature",
  "properties": {
    "iso:country":"ES",
    "sg:address":"Psaj Romero, 3",
    "sg:city":"Ceuta",
    "sg:orig_category":"Procuradores",
    "sg:phone":"+34 956 51 10 20",
    "sg:postcode":"51001",
    "sg:province":"Ceuta",
    "wof:name":"Herrero Pecino Procuradores S.c.",
    "wof:placetype":"venue"
},
  "geometry": {"coordinates":[-5.3302302361,35.8947601318],"type":"Point"}
}