{
  "type": "Feature",
  "properties": {
    "addr:full":"Crtj Agua Fresca, S/n Ca\u00e7ada De San Urbano Almer\u00eda 04120",
    "addr:housenumber":"s / n",
    "addr:postcode":"04120",
    "addr:street":"Fresca;Almeri\u0301A",
    "iso:country":"ES",
    "sg:address":"Crtj Agua Fresca, S/n",
    "sg:city":"Ca\u00e7ada De San Urbano",
    "sg:orig_category":"Autob\u00das (explotaci\u00d3n Y Servicios De)",
    "sg:phone":"+34 950 29 02 12",
    "sg:postcode":"04120",
    "sg:province":"Almer\u00eda",
    "wof:name":"Autocares Frahemar S.a.",
    "wof:placetype":"venue"
},
  "geometry": {"coordinates":[-2.4679217339,36.8401641846],"type":"Point"}
}