{
  "type": "Feature",
  "properties": {
    "iso:country":"ES",
    "sg:address":"Plzl Encarnacion, 4",
    "sg:city":"Bilbao",
    "sg:orig_category":"Producci\u00d3n De Sidra",
    "sg:phone":"+34 944 33 79 87",
    "sg:postcode":"48006",
    "sg:province":"Vizcaya",
    "wof:name":"Fernandez Azparren Veremundo",
    "wof:placetype":"venue"
},
  "geometry": {"coordinates":[-2.9206869602,43.2540054321],"type":"Point"}
}