{
  "type": "Feature",
  "properties": {
    "iso:country":"ES",
    "sg:address":"Calle de Veracruz, 271",
    "sg:city":"Malaga",
    "sg:orig_category":"Electricidad, Electr\u00d3nica: Suministros (al Por Menor)",
    "sg:phone":"+34 952 36 04 71",
    "sg:postcode":"29006",
    "sg:province":"M\u00e1laga",
    "wof:name":"Salicru S.a.",
    "wof:placetype":"venue"
},
  "geometry": {"coordinates":[-4.4729990959,36.7042007446],"type":"Point"}
}