{
  "type": "Feature",
  "properties": {
    "addr:full":"C/ Villalonga, D'en, 38 Porto Cristo Islas Baleares 07680",
    "addr:housenumber":"38",
    "addr:postcode":"07680",
    "addr:street":"C / Villalonga D'En;Baleares",
    "iso:country":"ES",
    "sg:address":"C/ Villalonga, D'en, 38",
    "sg:city":"Porto Cristo",
    "sg:orig_category":"Aguas (distribuci\u00d3n, Servicios)",
    "sg:phone":"+34 971 82 05 70",
    "sg:postcode":"07680",
    "sg:province":"Islas Baleares",
    "wof:name":"Aguas Tovell S.a.",
    "wof:placetype":"venue"
},
  "geometry": {"coordinates":[3.337757349,39.5446662903],"type":"Point"}
}