{
  "type": "Feature",
  "properties": {
    "addr:full":"Calle de Melilla, 27 Alcala Henares Madrid 28805",
    "addr:housenumber":"27",
    "addr:postcode":"28805",
    "addr:street":"Calle De Melilla",
    "iso:country":"ES",
    "sg:address":"Calle de Melilla, 27",
    "sg:city":"Alcala Henares",
    "sg:orig_category":"Instalaci\u00d3n, Reparaci\u00d3n De Ascensores Y Montacargas",
    "sg:phone":"+34 918 82 95 32",
    "sg:postcode":"28805",
    "sg:province":"Madrid",
    "wof:name":"Ascensores D. Carrillo S.l.",
    "wof:placetype":"venue"
},
  "geometry": {"coordinates":[-3.3413538933,40.4939613342],"type":"Point"}
}