{
  "type": "Feature",
  "properties": {
    "addr:full":"Carrer de Sant Antoni, 8 Senia Tarragona 43560",
    "addr:housenumber":"8",
    "addr:postcode":"43560",
    "addr:street":"Carrer De Sant Antoni",
    "iso:country":"ES",
    "sg:address":"Carrer de Sant Antoni, 8",
    "sg:city":"Senia",
    "sg:orig_category":"Telas Y Sedas (al Por Menor)",
    "sg:phone":"+34 977 71 33 52",
    "sg:postcode":"43560",
    "sg:province":"Tarragona",
    "wof:name":"Sabater Bel Montserrat",
    "wof:placetype":"venue"
},
  "geometry": {"coordinates":[0.2806070149,40.6349143982],"type":"Point"}
}