{
  "type": "Feature",
  "properties": {
    "addr:full":"Plaz Alcalde Domingo Torres, 1 Valencia Valencia 46020",
    "addr:housenumber":"1",
    "addr:postcode":"46020",
    "addr:street":"Plaz Alcalde Domingo Torres",
    "iso:country":"ES",
    "sg:address":"Plaz Alcalde Domingo Torres, 1",
    "sg:city":"Valencia",
    "sg:orig_category":"Promotores Constructores",
    "sg:phone":"+34 963 69 03 51",
    "sg:postcode":"46020",
    "sg:province":"Valencia",
    "wof:name":"Sistemas De Construccion De Levante S.l.",
    "wof:placetype":"venue"
},
  "geometry": {"coordinates":[-0.3581719995,39.4820327759],"type":"Point"}
}