{
  "type": "Feature",
  "properties": {
    "iso:country":"ES",
    "sg:address":"Aritz-bidea, 11",
    "sg:city":"Mungia",
    "sg:orig_category":"Farmacias",
    "sg:phone":"+34 946 74 15 90",
    "sg:postcode":"48100",
    "sg:province":"Vizcaya",
    "wof:name":"Lachiondo Huarte-mendicoa Cristina",
    "wof:placetype":"venue"
},
  "geometry": {"coordinates":[-2.8410499096,43.3538513184],"type":"Point"}
}