{
  "type": "Feature",
  "properties": {
    "iso:country":"ES",
    "sg:address":"Carr Del Doctor Pons, 30",
    "sg:city":"S. Rafael Rio",
    "sg:orig_category":"Distribuci\u00d3n De Petr\u00d3leo Y Derivados",
    "sg:phone":"+34 977 71 34 23",
    "sg:postcode":"12510",
    "sg:province":"Castell\u00f3n",
    "wof:name":"San Rafael Del Rio S.l.",
    "wof:placetype":"venue"
},
  "geometry": {"coordinates":[0.3464699984,40.6063156128],"type":"Point"}
}