{
  "type": "Feature",
  "properties": {
    "addr:full":"Calle de Escucha, 7 Utrillas Teruel 44760",
    "addr:housenumber":"7",
    "addr:postcode":"44760",
    "addr:street":"Calle De Escucha",
    "iso:country":"ES",
    "sg:address":"Calle de Escucha, 7",
    "sg:city":"Utrillas",
    "sg:orig_category":"Zapater\u00cdas",
    "sg:phone":"+34 978 75 75 49",
    "sg:postcode":"44760",
    "sg:province":"Teruel",
    "wof:name":"De La Calle Diaz Adriana",
    "wof:placetype":"venue"
},
  "geometry": {"coordinates":[-0.8469600081,40.8131027222],"type":"Point"}
}