{
  "type": "Feature",
  "properties": {
    "iso:country":"ES",
    "sg:address":"Av Jaume I, 90",
    "sg:city":"Mollet Valles",
    "sg:orig_category":"Muebles, Minoristas",
    "sg:phone":"+34 935 79 12 54",
    "sg:postcode":"08100",
    "sg:province":"Barcelona",
    "wof:name":"Etnias Del Valles S.c.p",
    "wof:placetype":"venue"
},
  "geometry": {"coordinates":[2.2140719891,41.5409660339],"type":"Point"}
}