{
  "type": "Feature",
  "properties": {
    "iso:country":"ES",
    "sg:address":"Calle de Larramendi, 27",
    "sg:city":"Donostia-san Sebastian",
    "sg:orig_category":"Animales (al Por Menor)",
    "sg:phone":"+34 943 46 04 73",
    "sg:postcode":"20006",
    "sg:province":"Guip\u00f9zcoa",
    "wof:name":"Galarraga Arambarri Cecilia",
    "wof:placetype":"venue"
},
  "geometry": {"coordinates":[-1.9822429419,43.3148574829],"type":"Point"}
}