{
  "type": "Feature",
  "properties": {
    "addr:full":"Calle de Azkuene, 11 Donostia-san Sebastian Guip\u00f9zcoa 20016",
    "addr:housenumber":"11",
    "addr:postcode":"20016",
    "addr:street":"Calle De Azkuene",
    "iso:country":"ES",
    "sg:address":"Calle de Azkuene, 11",
    "sg:city":"Donostia-san Sebastian",
    "sg:orig_category":"Cristaler\u00cdas",
    "sg:phone":"+34 943 40 05 12",
    "sg:postcode":"20016",
    "sg:province":"Guip\u00f9zcoa",
    "wof:name":"Cristaleria Alcibar, S.l.",
    "wof:placetype":"venue"
},
  "geometry": {"coordinates":[-1.9373949766,43.323677063],"type":"Point"}
}