{
  "type": "Feature",
  "properties": {
    "addr:full":"Carrer de Lepant, 424 Barcelona Barcelona 08025",
    "addr:housenumber":"424",
    "addr:postcode":"08025",
    "addr:street":"Carrer De Lepant",
    "iso:country":"ES",
    "sg:address":"Carrer de Lepant, 424",
    "sg:city":"Barcelona",
    "sg:orig_category":"Cajas De Ahorro",
    "sg:phone":"+34 933 47 38 46",
    "sg:postcode":"08025",
    "sg:province":"Barcelona",
    "wof:name":"Caixa D'estalvis De Catalunya",
    "wof:placetype":"venue"
},
  "geometry": {"coordinates":[2.1677310467,41.4112930298],"type":"Point"}
}