{
  "type": "Feature",
  "properties": {
    "addr:full":"Rguez De La Fuente, S/n Maracena Granada 18200",
    "addr:housenumber":"s / n",
    "addr:postcode":"18200",
    "addr:street":"Rguez;La Fuente",
    "iso:country":"ES",
    "sg:address":"Rguez De La Fuente, S/n",
    "sg:city":"Maracena",
    "sg:orig_category":"Empresas De Carpinter\u00cda Met\u00c1lica",
    "sg:phone":"+34 958 41 09 89",
    "sg:postcode":"18200",
    "sg:province":"Granada",
    "wof:name":"Jimenez Calamardo Juan",
    "wof:placetype":"venue"
},
  "geometry": {"coordinates":[-3.6395390034,37.2045211792],"type":"Point"}
}