{
  "type": "Feature",
  "properties": {
    "iso:country":"ES",
    "sg:address":"Carr Roser, 11",
    "sg:city":"Torregrossa",
    "sg:orig_category":"Artesan\u00cda",
    "sg:phone":"+34 973 17 03 41",
    "sg:postcode":"25141",
    "sg:province":"Lleida",
    "wof:name":"New Art S.c.p.",
    "wof:placetype":"venue"
},
  "geometry": {"coordinates":[0.8324049711,41.5803718567],"type":"Point"}
}