{
  "type": "Feature",
  "properties": {
    "addr:full":"Calle de Churra, 1 Espinardo Murcia 30007",
    "addr:housenumber":"1",
    "addr:postcode":"30007",
    "addr:street":"Calle De Churra",
    "iso:country":"ES",
    "sg:address":"Calle de Churra, 1",
    "sg:city":"Espinardo",
    "sg:orig_category":"M\u00c9dicos: Ginecolog\u00cda Y Obstetricia",
    "sg:phone":"+34 968 24 67 18",
    "sg:postcode":"30007",
    "sg:province":"Murcia",
    "wof:name":"Rabadan Armero Antonio",
    "wof:placetype":"venue"
},
  "geometry": {"coordinates":[-1.1313755512,37.997756958],"type":"Point"}
}