{
  "type": "Feature",
  "properties": {
    "addr:full":"Calle de Lamuza, 1 Llodio \u00c1lava 01400",
    "addr:housenumber":"1",
    "addr:postcode":"01400",
    "addr:street":"Calle De Lamuza",
    "iso:country":"ES",
    "sg:address":"Calle de Lamuza, 1",
    "sg:city":"Llodio",
    "sg:orig_category":"Marketing Telef\u00d3nico",
    "sg:phone":"+34 946 72 67 26",
    "sg:postcode":"01400",
    "sg:province":"\u00c1lava",
    "wof:name":"Marketing Llodio S.l.",
    "wof:placetype":"venue"
},
  "geometry": {"coordinates":[-2.9629089832,43.1434211731],"type":"Point"}
}