{
  "type": "Feature",
  "properties": {
    "addr:full":"Calle de Leonardo Talens Rivas, 8 Torremolinos M\u00e1laga 29620",
    "addr:housenumber":"8",
    "addr:postcode":"29620",
    "addr:street":"Calle De Leonardo Talens Rivas;Ma\u0301Laga",
    "iso:country":"ES",
    "sg:address":"Calle de Leonardo Talens Rivas, 8",
    "sg:city":"Torremolinos",
    "sg:orig_category":"Art\u00cdculos Funerarios (al Por Menor)",
    "sg:phone":"+34 952 38 55 19",
    "sg:postcode":"29620",
    "sg:province":"M\u00e1laga",
    "wof:name":"Francisco Camero S.l.",
    "wof:placetype":"venue"
},
  "geometry": {"coordinates":[-4.5063538551,36.6233291626],"type":"Point"}
}