{
  "type": "Feature",
  "properties": {
    "iso:country":"ES",
    "sg:address":"Calle de Abajo, 65",
    "sg:city":"Callosa Segura",
    "sg:orig_category":"Peluqueros: De Se\u00d1oras",
    "sg:phone":"+34 966 75 83 44",
    "sg:postcode":"03360",
    "sg:province":"Alicante",
    "wof:name":"Pastor Ba\u00f1on Jose Carlos",
    "wof:placetype":"venue"
},
  "geometry": {"coordinates":[-0.8785166144,38.124080658],"type":"Point"}
}