{
  "type": "Feature",
  "properties": {
    "addr:full":"Carrer de Sant Francesc Xavier, 50 Barcelona Barcelona 08016",
    "addr:housenumber":"50",
    "addr:postcode":"08016",
    "addr:street":"Carrer De Sant Francesc Xavier",
    "iso:country":"ES",
    "sg:address":"Carrer de Sant Francesc Xavier, 50",
    "sg:city":"Barcelona",
    "sg:orig_category":"Molduras, Junquillos, Listones Y Molduras Perforadas",
    "sg:phone":"+34 933 54 40 28",
    "sg:postcode":"08016",
    "sg:province":"Barcelona",
    "wof:name":"Cuaresma Suero Apolinar",
    "wof:placetype":"venue"
},
  "geometry": {"coordinates":[2.1797699928,41.4403610229],"type":"Point"}
}