{
  "type": "Feature",
  "properties": {
    "addr:full":"Calle de Cascajosa (la), 1 Entrena La Rioja 26375",
    "addr:housenumber":"1",
    "addr:postcode":"26375",
    "addr:street":"Calle De Cascajosa La;Rioja",
    "iso:country":"ES",
    "sg:address":"Calle de Cascajosa (la), 1",
    "sg:city":"Entrena",
    "sg:orig_category":"Frutas Y Legumbres Frescas (al Por Mayor)",
    "sg:phone":"+34 941 44 62 11",
    "sg:postcode":"26375",
    "sg:province":"La Rioja",
    "wof:name":"Martinez Corral Francisco",
    "wof:placetype":"venue"
},
  "geometry": {"coordinates":[-2.5268273354,42.387172699],"type":"Point"}
}