{
  "type": "Feature",
  "properties": {
    "iso:country":"ES",
    "sg:address":"Calle de Fray Luis Amigo, 19",
    "sg:city":"Torrent",
    "sg:orig_category":"Frutas Y Legumbres Frescas (al Por Mayor)",
    "sg:phone":"+34 961 57 45 62",
    "sg:postcode":"46900",
    "sg:province":"Valencia",
    "wof:name":"Hijas De Pascual Andreu S.l.",
    "wof:placetype":"venue"
},
  "geometry": {"coordinates":[-0.463831991,39.4348602295],"type":"Point"}
}