{
  "type": "Feature",
  "properties": {
    "addr:full":"Poli Nava (la), S/n Tafalla Navarra 31300",
    "addr:housenumber":"s",
    "addr:postcode":"31300",
    "addr:street":"/ N",
    "iso:country":"ES",
    "sg:address":"Poli Nava (la), S/n",
    "sg:city":"Tafalla",
    "sg:orig_category":"Promotores Constructores",
    "sg:phone":"+34 948 70 37 76",
    "sg:postcode":"31300",
    "sg:province":"Navarra",
    "wof:name":"Construcciones Y Reparaciones La Nava S.l.",
    "wof:placetype":"venue"
},
  "geometry": {"coordinates":[-1.674399972,42.5275344849],"type":"Point"}
}