{
  "type": "Feature",
  "properties": {
    "iso:country":"ES",
    "sg:address":"Av Constitucio, 16",
    "sg:city":"Alcanar",
    "sg:orig_category":"Molduras, Junquillos, Listones Y Molduras Perforadas",
    "sg:phone":"+34 977 73 22 86",
    "sg:postcode":"43530",
    "sg:province":"Tarragona",
    "wof:name":"Chillida Parra Juan Agustin",
    "wof:placetype":"venue"
},
  "geometry": {"coordinates":[0.4800190032,40.5398101807],"type":"Point"}
}