{
  "type": "Feature",
  "properties": {
    "addr:full":"Loira(pol Ind Oriola), 124 Amposta Tarragona 43870",
    "addr:housenumber":"124",
    "addr:postcode":"43870",
    "addr:street":"Oriola",
    "iso:country":"ES",
    "sg:address":"Loira(pol Ind Oriola), 124",
    "sg:city":"Amposta",
    "sg:orig_category":"Montaje (empresas De)",
    "sg:phone":"+34 977 70 02 01",
    "sg:postcode":"43870",
    "sg:province":"Tarragona",
    "wof:name":"Carrosseries Gil-ma-fer S.l.",
    "wof:placetype":"venue"
},
  "geometry": {"coordinates":[0.5797849894,40.7130432129],"type":"Point"}
}