{
  "type": "Feature",
  "properties": {
    "iso:country":"ES",
    "sg:address":"Lugar Madriles(roses), S/n",
    "sg:city":"La Puebla",
    "sg:orig_category":"Agricultura: Abastecimiento Y Cosechado (negocio)",
    "sg:phone":"+34 968 16 80 22",
    "sg:postcode":"30395",
    "sg:province":"Murcia",
    "wof:name":"Cooperativa Agricola Levante Sur",
    "wof:placetype":"venue"
},
  "geometry": {"coordinates":[-0.9203090072,37.717918396],"type":"Point"}
}