{
  "type": "Feature",
  "properties": {
    "iso:country":"ES",
    "sg:address":"Calle de Hernan Cortes, 27",
    "sg:city":"Santa Amalia",
    "sg:orig_category":"Agricultores, Agricultores",
    "sg:phone":"+34 924 83 06 11",
    "sg:postcode":"06410",
    "sg:province":"Badajoz",
    "wof:name":"Gestiones Agricolas Y Ganaderas S.l.",
    "wof:placetype":"venue"
},
  "geometry": {"coordinates":[-6.008079052,39.009475708],"type":"Point"}
}