{
  "type": "Feature",
  "properties": {
    "iso:country":"ES",
    "sg:address":"Calle de Huertas De La Villa, 18",
    "sg:city":"Bilbao",
    "sg:orig_category":"Inversiones",
    "sg:phone":"+34 944 46 68 14",
    "sg:postcode":"48007",
    "sg:province":"Vizcaya",
    "wof:name":"Laida Inversiones, S.a.",
    "wof:placetype":"venue"
},
  "geometry": {"coordinates":[-2.9250864983,43.270450592],"type":"Point"}
}