{
  "type": "Feature",
  "properties": {
    "addr:full":"Posteragua, 6 Playa De Mogan Las Palmas 35138",
    "addr:housenumber":"6",
    "addr:postcode":"35138",
    "addr:street":"Posteragua",
    "iso:country":"ES",
    "sg:address":"Posteragua, 6",
    "sg:city":"Playa De Mogan",
    "sg:orig_category":"C\u00c1maras De Comercio E Industria, Oficios, Agricultura",
    "sg:phone":"+34 928 56 53 04",
    "sg:postcode":"35138",
    "sg:province":"Las Palmas",
    "wof:name":"Postreragua S.l.",
    "wof:placetype":"venue"
},
  "geometry": {"coordinates":[-13.8894538879,28.6940307617],"type":"Point"}
}