{
  "type": "Feature",
  "properties": {
    "addr:full":"Calle de Flor La, 6 Grado Asturias 33820",
    "addr:housenumber":"6",
    "addr:postcode":"33820",
    "addr:street":"Calle De Flor La",
    "iso:country":"ES",
    "sg:address":"Calle de Flor La, 6",
    "sg:city":"Grado",
    "sg:orig_category":"Molduras, Junquillos, Listones Y Molduras Perforadas",
    "sg:phone":"+34 985 75 33 71",
    "sg:postcode":"33820",
    "sg:province":"Asturias",
    "wof:name":"Alvarez Fernandez Maria Montserrat",
    "wof:placetype":"venue"
},
  "geometry": {"coordinates":[-6.0753669739,43.3851356506],"type":"Point"}
}