{
  "type": "Feature",
  "properties": {
    "iso:country":"ES",
    "sg:address":"Calle de Molina De Aragon, 3",
    "sg:city":"Guadalajara",
    "sg:orig_category":"Soportes L\u00d3gicos, Programas Integradores De Aplicaciones (progiciels)",
    "sg:phone":"+34 949 22 66 48",
    "sg:postcode":"19003",
    "sg:province":"Guadalajara",
    "wof:name":"Informatica Administrativa S. A.",
    "wof:placetype":"venue"
},
  "geometry": {"coordinates":[-3.169137001,40.6281814575],"type":"Point"}
}