{
  "type": "Feature",
  "properties": {
    "addr:full":"Calle de Doctor Fleming, 30 Madrid Madrid 28036",
    "addr:housenumber":"30",
    "addr:postcode":"madrid;28036",
    "addr:street":"Calle De Doctor Fleming",
    "iso:country":"ES",
    "sg:address":"Calle de Doctor Fleming, 30",
    "sg:city":"Madrid",
    "sg:orig_category":"Arquitectos",
    "sg:phone":"+34 914 57 69 51",
    "sg:postcode":"28036",
    "sg:province":"Madrid",
    "wof:name":"Mu\u00f1oz Rojas Alarcon Ignacio",
    "wof:placetype":"venue"
},
  "geometry": {"coordinates":[-3.6881465912,40.4579620361],"type":"Point"}
}