{
  "type": "Feature",
  "properties": {
    "addr:full":"Estd Nacional 525, Km. 0232,8 San Cibrao Das Vi\u00e7as Ourense 32911",
    "addr:postcode":"32911",
    "addr:street":"Nacional 525 Km. 0232,8",
    "iso:country":"ES",
    "sg:address":"Estd Nacional 525, Km. 0232,8",
    "sg:city":"San Cibrao Das Vi\u00e7as",
    "sg:orig_category":"Peleter\u00cdas",
    "sg:phone":"+34 988 38 28 28",
    "sg:postcode":"32911",
    "sg:province":"Ourense",
    "wof:name":"Orenfur S.l.",
    "wof:placetype":"venue"
},
  "geometry": {"coordinates":[-7.872358799,42.2972106934],"type":"Point"}
}