{
  "type": "Feature",
  "properties": {
    "addr:full":"Trav Corts, 245 Barcelona Barcelona 08028",
    "addr:housenumber":"245",
    "addr:postcode":"08028",
    "addr:street":"Trav Corts",
    "iso:country":"ES",
    "sg:address":"Trav Corts, 245",
    "sg:city":"Barcelona",
    "sg:orig_category":"Oficinas: Suministros Para (fabricaci\u00d3n, Al Por Mayor)",
    "sg:phone":"+34 933 21 26 63",
    "sg:postcode":"08028",
    "sg:province":"Barcelona",
    "wof:name":"Camaher Office S.l.",
    "wof:placetype":"venue"
},
  "geometry": {"coordinates":[2.1317999363,41.3847885132],"type":"Point"}
}