{
  "type": "Feature",
  "properties": {
    "addr:full":"Ptda Saboya, S/n Alboraya Valencia 46120",
    "addr:housenumber":"s / n",
    "addr:postcode":"46120",
    "addr:street":"Ptda Saboya",
    "iso:country":"ES",
    "sg:address":"Ptda Saboya, S/n",
    "sg:city":"Alboraya",
    "sg:orig_category":"Centros De Educaci\u00d3n Especial",
    "sg:phone":"+34 961 85 63 85",
    "sg:postcode":"46120",
    "sg:province":"Valencia",
    "wof:name":"Generalitat Valenciana",
    "wof:placetype":"venue"
},
  "geometry": {"coordinates":[-0.3395406902,39.4937095642],"type":"Point"}
}