{
  "type": "Feature",
  "properties": {
    "addr:full":"Calle de Ajuriaguerra Juan, 9 Bilbao Vizcaya 48009",
    "addr:housenumber":"9",
    "addr:postcode":"48009",
    "addr:street":"Calle De Ajuriaguerra Juan",
    "iso:country":"ES",
    "sg:address":"Calle de Ajuriaguerra Juan, 9",
    "sg:city":"Bilbao",
    "sg:orig_category":"Promotores Constructores",
    "sg:phone":"+34 944 23 13 67",
    "sg:postcode":"48009",
    "sg:province":"Vizcaya",
    "wof:name":"Nivel 85 S. A.",
    "wof:placetype":"venue"
},
  "geometry": {"coordinates":[-2.9321522713,43.2654762268],"type":"Point"}
}