{
  "type": "Feature",
  "properties": {
    "addr:full":"Rua Poligono, 3 Temple La Coru\u00f1a 15679",
    "addr:housenumber":"3",
    "addr:postcode":"15679",
    "addr:street":"Rua Poligono;La Corun\u0303A",
    "iso:country":"ES",
    "sg:address":"Rua Poligono, 3",
    "sg:city":"Temple",
    "sg:orig_category":"Fabricaci\u00d3n De Peines Y De Accesorios De Peluquer\u00cda",
    "sg:phone":"+34 981 66 10 92",
    "sg:postcode":"15679",
    "sg:province":"La Coru\u00f1a",
    "wof:name":"Galego Varela Mari Cruz",
    "wof:placetype":"venue"
},
  "geometry": {"coordinates":[-8.3571548462,43.3165397644],"type":"Point"}
}