{
  "type": "Feature",
  "properties": {
    "iso:country":"ES",
    "sg:address":"Avda Coimbra (de), 24",
    "sg:city":"Santiago De Compostela",
    "sg:orig_category":"Molduras, Junquillos, Listones Y Molduras Perforadas",
    "sg:phone":"+34 981 58 14 76",
    "sg:postcode":"15704",
    "sg:province":"La Coru\u00f1a",
    "wof:name":"Otero Alvarez Jose Carlos",
    "wof:placetype":"venue"
},
  "geometry": {"coordinates":[-8.5410642624,42.8867721558],"type":"Point"}
}