{
  "type": "Feature",
  "properties": {
    "addr:full":"Calle de Poza Licenciado, 64 Bilbao Vizcaya 48013",
    "addr:housenumber":"64",
    "addr:postcode":"48013",
    "addr:street":"Calle De Poza Licenciado",
    "iso:country":"ES",
    "sg:address":"Calle de Poza Licenciado, 64",
    "sg:city":"Bilbao",
    "sg:orig_category":"Molduras, Junquillos, Listones Y Molduras Perforadas",
    "sg:phone":"+34 944 42 27 79",
    "sg:postcode":"48013",
    "sg:province":"Vizcaya",
    "wof:name":"Bar Bodega C.b.",
    "wof:placetype":"venue"
},
  "geometry": {"coordinates":[-2.9467749596,43.2635002136],"type":"Point"}
}