{
  "type": "Feature",
  "properties": {
    "iso:country":"ES",
    "sg:address":"Calle de Obispo Jaime Perez, 5",
    "sg:city":"Valencia",
    "sg:orig_category":"Abogados",
    "sg:phone":"+34 963 33 82 60",
    "sg:postcode":"46006",
    "sg:province":"Valencia",
    "wof:name":"Gomez Cencillo Juan",
    "wof:placetype":"venue"
},
  "geometry": {"coordinates":[-0.3666900098,39.4600448608],"type":"Point"}
}