{
  "type": "Feature",
  "properties": {
    "iso:country":"ES",
    "sg:address":"Cllo Teatro Circo, 3",
    "sg:city":"Albacete",
    "sg:orig_category":"Arquitectos",
    "sg:phone":"+34 967 21 00 71",
    "sg:postcode":"02001",
    "sg:province":"Albacete",
    "wof:name":"Belmonte Martinez Esteban",
    "wof:placetype":"venue"
},
  "geometry": {"coordinates":[-1.8540990353,38.996307373],"type":"Point"}
}