{
  "type": "Feature",
  "properties": {
    "iso:country":"ES",
    "sg:address":"Calle de Duque De Alba, 12",
    "sg:city":"Madrid",
    "sg:orig_category":"Prot\u00c9sicos Dentales",
    "sg:phone":"+34 913 64 28 50",
    "sg:postcode":"28012",
    "sg:province":"Madrid",
    "wof:name":"Navarro Rivas Juan Jose",
    "wof:placetype":"venue"
},
  "geometry": {"coordinates":[-3.706818819,40.4116439819],"type":"Point"}
}