{
  "type": "Feature",
  "properties": {
    "iso:country":"ES",
    "sg:address":"Calle de Terrero, 35",
    "sg:city":"Daimiel",
    "sg:orig_category":"M\u00c1rmoles, Granitos Y Piedras Naturales",
    "sg:phone":"+34 926 85 27 87",
    "sg:postcode":"13250",
    "sg:province":"Ciudad Real",
    "wof:name":"Terrazos Fernandez Espartero S.l.",
    "wof:placetype":"venue"
},
  "geometry": {"coordinates":[-3.614839077,39.0740432739],"type":"Point"}
}