{
  "type": "Feature",
  "properties": {
    "addr:full":"Calle de Zurita, 12 Zaragoza Zaragoza 50001",
    "addr:housenumber":"12",
    "addr:postcode":"50001",
    "addr:street":"Calle De Zurita",
    "iso:country":"ES",
    "sg:address":"Calle de Zurita, 12",
    "sg:city":"Zaragoza",
    "sg:orig_category":"Ropa Para Se\u00d1oras (al Por Menor)",
    "sg:phone":"+34 976 23 07 10",
    "sg:postcode":"50001",
    "sg:province":"Zaragoza",
    "wof:name":"Mundo Donna S.l.unipersonal",
    "wof:placetype":"venue"
},
  "geometry": {"coordinates":[-0.8807200193,41.649936676],"type":"Point"}
}