{
  "type": "Feature",
  "properties": {
    "addr:full":"Materos (p I Era Empedrada), 10 Umbrete Sevilla 41806",
    "addr:housenumber":"10",
    "addr:postcode":"41806",
    "addr:street":"Materos;Empedrada",
    "iso:country":"ES",
    "sg:address":"Materos (p I Era Empedrada), 10",
    "sg:city":"Umbrete",
    "sg:orig_category":"Audiovisuales: Material Y Accesorios (al Por Menor)",
    "sg:phone":"+34 955 71 79 71",
    "sg:postcode":"41806",
    "sg:province":"Sevilla",
    "wof:name":"Sonido Video E Ilumonacion S.l.",
    "wof:placetype":"venue"
},
  "geometry": {"coordinates":[-6.16665411,37.3639717102],"type":"Point"}
}