{
  "type": "Feature",
  "properties": {
    "addr:full":"Pase San Gregorio, 8 Puertollano Ciudad Real 13500",
    "addr:housenumber":"8",
    "addr:postcode":"13500",
    "addr:street":"San Gregorio",
    "iso:country":"ES",
    "sg:address":"Pase San Gregorio, 8",
    "sg:city":"Puertollano",
    "sg:orig_category":"Quincaller\u00cda (al Por Menor)",
    "sg:phone":"+34 926 41 38 56",
    "sg:postcode":"13500",
    "sg:province":"Ciudad Real",
    "wof:name":"Suministros Industriales Valero",
    "wof:placetype":"venue"
},
  "geometry": {"coordinates":[-4.105697155,38.6885604858],"type":"Point"}
}