{
  "type": "Feature",
  "properties": {
    "iso:country":"ES",
    "sg:address":"Calle de Flor (la), S/n",
    "sg:city":"Azuqueca Henares",
    "sg:orig_category":"Centros De Educaci\u00d3n Especial",
    "sg:phone":"+34 949 26 13 92",
    "sg:postcode":"19200",
    "sg:province":"Guadalajara",
    "wof:name":"Colegio Publico La Paz",
    "wof:placetype":"venue"
},
  "geometry": {"coordinates":[-3.2641940117,40.5703239441],"type":"Point"}
}