{
  "type": "Feature",
  "properties": {
    "addr:full":"Carrer de Cabanes, 24 Barcelona Barcelona 08004",
    "addr:housenumber":"24",
    "addr:postcode":"08004",
    "addr:street":"Carrer De Cabanes",
    "iso:country":"ES",
    "sg:address":"Carrer de Cabanes, 24",
    "sg:city":"Barcelona",
    "sg:orig_category":"Electrodom\u00c9sticos (al Por Menor)",
    "sg:phone":"+34 934 42 10 00",
    "sg:postcode":"08004",
    "sg:province":"Barcelona",
    "wof:name":"Diaz Llorens Juan Bautista",
    "wof:placetype":"venue"
},
  "geometry": {"coordinates":[2.1700971127,41.3736114502],"type":"Point"}
}