{
  "type": "Feature",
  "properties": {
    "iso:country":"ES",
    "sg:address":"Carr Guifre, 791",
    "sg:city":"Badalona",
    "sg:orig_category":"Construcci\u00d3n Mec\u00c1nica",
    "sg:phone":"+34 933 83 45 52",
    "sg:postcode":"08918",
    "sg:province":"Barcelona",
    "wof:name":"Construcciones Mecanicas Badalona S.l.",
    "wof:placetype":"venue"
},
  "geometry": {"coordinates":[2.226970911,41.43126297],"type":"Point"}
}