{
  "type": "Feature",
  "properties": {
    "iso:country":"ES",
    "sg:address":"Pl Creueta, 1",
    "sg:city":"Alfas Pi",
    "sg:orig_category":"Dietistas",
    "sg:phone":"+34 966 86 04 68",
    "sg:postcode":"03580",
    "sg:province":"Alicante",
    "sg:website":"www.mon-natura.com",
    "wof:name":"Sanchis Tasa Sonia",
    "wof:placetype":"venue"
},
  "geometry": {"coordinates":[-0.0999030024,38.5771408081],"type":"Point"}
}