{
  "type": "Feature",
  "properties": {
    "iso:country":"ES",
    "sg:address":"Carrer de Almeria, 2",
    "sg:city":"Mataro",
    "sg:orig_category":"Confecci\u00d3n De Trajes Para Se\u00d1oras",
    "sg:phone":"+34 937 99 16 24",
    "sg:postcode":"08304",
    "sg:province":"Barcelona",
    "wof:name":"Requena Cobo Miguel",
    "wof:placetype":"venue"
},
  "geometry": {"coordinates":[2.4453320503,41.5518302917],"type":"Point"}
}