{
  "type": "Feature",
  "properties": {
    "addr:full":"Calle de Maria Luisa, 2 Tincer Santa Cruz De Tenerife 38108",
    "addr:housenumber":"2",
    "addr:postcode":"38108",
    "addr:street":"Calle De Maria Luisa",
    "iso:country":"ES",
    "sg:address":"Calle de Maria Luisa, 2",
    "sg:city":"Tincer",
    "sg:orig_category":"Supermercados Y Hipermercados",
    "sg:phone":"+34 922 62 95 21",
    "sg:postcode":"38108",
    "sg:province":"Santa Cruz De Tenerife",
    "wof:name":"Agrucan S.l.",
    "wof:placetype":"venue"
},
  "geometry": {"coordinates":[-16.2548561096,28.4698104858],"type":"Point"}
}