{
  "type": "Feature",
  "properties": {
    "addr:full":"Pso. San Agustin, S/n Lobres Granada 18610",
    "addr:postcode":"18610",
    "addr:street":"San Agustin S / N Lobres",
    "iso:country":"ES",
    "sg:address":"Pso. San Agustin, S/n",
    "sg:city":"Lobres",
    "sg:orig_category":"Vidrio, Fabricaci\u00d3n Y Comercio",
    "sg:phone":"+34 958 83 16 00",
    "sg:postcode":"18610",
    "sg:province":"Granada",
    "wof:name":"Criespa Seguridad S.l.",
    "wof:placetype":"venue"
},
  "geometry": {"coordinates":[-3.5695879459,36.7704811096],"type":"Point"}
}