{
  "type": "Feature",
  "properties": {
    "addr:full":"Pacios(ribas Altas), S/n Monforte De Lemos Lugo 27410",
    "addr:postcode":"27410",
    "addr:street":"S / N",
    "iso:country":"ES",
    "sg:address":"Pacios(ribas Altas), S/n",
    "sg:city":"Monforte De Lemos",
    "sg:orig_category":"Aguas (distribuci\u00d3n, Servicios)",
    "sg:phone":"+34 982 40 45 04",
    "sg:postcode":"27410",
    "sg:province":"Lugo",
    "wof:name":"Aqualia Gestion Integral Del Agua S.a.",
    "wof:placetype":"venue"
},
  "geometry": {"coordinates":[-7.4956235886,42.5498657227],"type":"Point"}
}