{
  "type": "Feature",
  "properties": {
    "addr:full":"Av Prat De La Riba, 151 Rieral De Bigues Barcelona 08415",
    "addr:housenumber":"151",
    "addr:postcode":"08415",
    "addr:street":"Av Prat De La Riba",
    "iso:country":"ES",
    "sg:address":"Av Prat De La Riba, 151",
    "sg:city":"Rieral De Bigues",
    "sg:orig_category":"Intercambios, Trueques",
    "sg:phone":"+34 938 65 92 99",
    "sg:postcode":"08415",
    "sg:province":"Barcelona",
    "wof:name":"Xalets Bigues S. A.",
    "wof:placetype":"venue"
},
  "geometry": {"coordinates":[2.2168765068,41.6716651917],"type":"Point"}
}