{
  "type": "Feature",
  "properties": {
    "iso:country":"ES",
    "sg:address":"Calle de Andres Mellado, 23",
    "sg:city":"Madrid",
    "sg:orig_category":"Asesor\u00cda Sobre Comunicaci\u00d3n De Empresas",
    "sg:phone":"+34 915 49 79 38",
    "sg:postcode":"28015",
    "sg:province":"Madrid",
    "wof:name":"Management Development & Training S.l.",
    "wof:placetype":"venue"
},
  "geometry": {"coordinates":[-3.7145299911,40.4326171875],"type":"Point"}
}