{
  "type": "Feature",
  "properties": {
    "iso:country":"ES",
    "sg:address":"Calle de Abasolo Apezpiku, 2",
    "sg:city":"Amorebieta",
    "sg:orig_category":"Ropa Y Art\u00cdculos Pre",
    "sg:phone":"+34 946 73 04 09",
    "sg:postcode":"48340",
    "sg:province":"Vizcaya",
    "wof:name":"Landalde S.l.",
    "wof:placetype":"venue"
},
  "geometry": {"coordinates":[-2.7347586155,43.2198028564],"type":"Point"}
}