{
  "type": "Feature",
  "properties": {
    "iso:country":"ES",
    "sg:address":"Calle de Obispo San Juan De Rivera, 2",
    "sg:city":"Badajoz",
    "sg:orig_category":"Iglesia Cat\u00d3lica",
    "sg:phone":"+34 924 22 25 98",
    "sg:postcode":"06002",
    "sg:province":"Badajoz",
    "wof:name":"Arzobispado De Merida Y Badajoz",
    "wof:placetype":"venue"
},
  "geometry": {"coordinates":[-6.970764637,38.8780250549],"type":"Point"}
}