{
  "type": "Feature",
  "properties": {
    "addr:full":"Calle de Zabaleta, 25 Madrid Madrid 28002",
    "addr:housenumber":"25",
    "addr:postcode":"madrid;28002",
    "addr:street":"Calle De Zabaleta",
    "iso:country":"ES",
    "sg:address":"Calle de Zabaleta, 25",
    "sg:city":"Madrid",
    "sg:orig_category":"Aparcamientos (infraestructuras, Accesorios)",
    "sg:phone":"+34 914 15 74 83",
    "sg:postcode":"28002",
    "sg:province":"Madrid",
    "wof:name":"Gonzalez Chimeno Isidro",
    "wof:placetype":"venue"
},
  "geometry": {"coordinates":[-3.6734347343,40.442401886],"type":"Point"}
}