{
  "type": "Feature",
  "properties": {
    "iso:country":"ES",
    "sg:address":"Calle de Sahara, 33",
    "sg:city":"Gijon",
    "sg:orig_category":"Chapister\u00cda",
    "sg:phone":"+34 985 38 85 29",
    "sg:postcode":"33208",
    "sg:province":"Asturias",
    "wof:name":"Fernandez Canto Jose",
    "wof:placetype":"venue"
},
  "geometry": {"coordinates":[-5.6640820503,43.5297698975],"type":"Point"}
}