{
  "type": "Feature",
  "properties": {
    "iso:country":"ES",
    "sg:address":"Plaz Espa\u00d1a, 2",
    "sg:city":"Huelva",
    "sg:orig_category":"Molduras, Junquillos, Listones Y Molduras Perforadas",
    "sg:phone":"+34 959 24 10 94",
    "sg:postcode":"21003",
    "sg:province":"Huelva",
    "wof:name":"Garcia Breva Juan Antonio",
    "wof:placetype":"venue"
},
  "geometry": {"coordinates":[-6.9415287971,37.2544136047],"type":"Point"}
}