{
  "type": "Feature",
  "properties": {
    "addr:full":"Avda Medina Olmos, 50 Guadix Granada 18500",
    "addr:housenumber":"50",
    "addr:postcode":"18500",
    "addr:street":"Avda Medina Olmos",
    "iso:country":"ES",
    "sg:address":"Avda Medina Olmos, 50",
    "sg:city":"Guadix",
    "sg:orig_category":"Asesor\u00cda Fiscal Y Jur\u00cddica",
    "sg:phone":"+34 958 66 01 15",
    "sg:postcode":"18500",
    "sg:province":"Granada",
    "wof:name":"Repsol Ypf S.a.",
    "wof:placetype":"venue"
},
  "geometry": {"coordinates":[-3.1287469864,37.2979469299],"type":"Point"}
}