{
  "type": "Feature",
  "properties": {
    "addr:full":"Plaz Luis Bu\u00d1uel, 1 Huelva Huelva 21005",
    "addr:housenumber":"1",
    "addr:postcode":"21005",
    "addr:street":"Plaz Luis Bun\u0303Uel",
    "iso:country":"ES",
    "sg:address":"Plaz Luis Bu\u00d1uel, 1",
    "sg:city":"Huelva",
    "sg:orig_category":"Peluqueros: De Se\u00d1oras",
    "sg:phone":"+34 959 29 02 40",
    "sg:postcode":"21005",
    "sg:province":"Huelva",
    "wof:name":"Romero Louro Concepcion",
    "wof:placetype":"venue"
},
  "geometry": {"coordinates":[-6.9370927811,37.2768516541],"type":"Point"}
}