{
  "type": "Feature",
  "properties": {
    "iso:country":"ES",
    "sg:address":"Avda Reyes Catolicos, 24",
    "sg:city":"Villarrobledo",
    "sg:orig_category":"Electricidad: Instaladores",
    "sg:phone":"+34 967 13 81 01",
    "sg:postcode":"02600",
    "sg:province":"Albacete",
    "wof:name":"Montajes Electromancha S.l.",
    "wof:placetype":"venue"
},
  "geometry": {"coordinates":[-2.5973699093,39.2643013],"type":"Point"}
}