{
  "type": "Feature",
  "properties": {
    "addr:full":"Av Maresme (del), 297 Mataro Barcelona 08301",
    "addr:postcode":"08301",
    "addr:street":"Av;Del 297 Mataro Barcelona",
    "iso:country":"ES",
    "sg:address":"Av Maresme (del), 297",
    "sg:city":"Mataro",
    "sg:orig_category":"Sociedades, Compa\u00d1\u00cdas Aseguradoras",
    "sg:phone":"+34 937 55 25 30",
    "sg:postcode":"08301",
    "sg:province":"Barcelona",
    "sg:website":"www.vitalicio.es",
    "wof:name":"Banco Vitalicio De Espa\u00f1a C.a.",
    "wof:placetype":"venue"
},
  "geometry": {"coordinates":[2.4477899075,41.5355415344],"type":"Point"}
}