{
  "type": "Feature",
  "properties": {
    "iso:country":"ES",
    "sg:address":"Calle de Colon, 37",
    "sg:city":"Palencia",
    "sg:orig_category":"Transportes Por V\u00cdas Navegables",
    "sg:phone":"+34 979 74 46 15",
    "sg:postcode":"34002",
    "sg:province":"Palencia",
    "wof:name":"Transportes Reunidos Suco S.l.",
    "wof:placetype":"venue"
},
  "geometry": {"coordinates":[-4.530602932,42.0071754456],"type":"Point"}
}