{
  "type": "Feature",
  "properties": {
    "addr:full":"Bo Galarza, 15 Galartza Vizcaya 48277",
    "addr:housenumber":"15",
    "addr:postcode":"48277",
    "addr:street":"Galarza",
    "iso:country":"ES",
    "sg:address":"Bo Galarza, 15",
    "sg:city":"Galartza",
    "sg:orig_category":"Cooperativas Agr\u00cdcolas",
    "sg:phone":"+34 946 16 85 01",
    "sg:postcode":"48277",
    "sg:province":"Vizcaya",
    "wof:name":"Cooperativa Agricola Comarcal Miba",
    "wof:placetype":"venue"
},
  "geometry": {"coordinates":[-2.4781939983,43.2544898987],"type":"Point"}
}