{
  "type": "Feature",
  "properties": {
    "addr:full":"O Pazo De Meis, S/n Pazo De Meis Pontevedra 36637",
    "addr:housenumber":"s / n",
    "addr:postcode":"36637",
    "iso:country":"ES",
    "sg:address":"O Pazo De Meis, S/n",
    "sg:city":"Pazo De Meis",
    "sg:orig_category":"Puertas Y Portales",
    "sg:phone":"+34 986 71 24 58",
    "sg:postcode":"36637",
    "sg:province":"Pontevedra",
    "wof:name":"Portameis S.l",
    "wof:placetype":"venue"
},
  "geometry": {"coordinates":[-8.737695694,42.5031814575],"type":"Point"}
}