{
  "type": "Feature",
  "properties": {
    "addr:full":"Calle de Bidasoa, 11 Madrid Madrid 28002",
    "addr:housenumber":"11",
    "addr:postcode":"madrid;28002",
    "addr:street":"Calle De Bidasoa",
    "iso:country":"ES",
    "sg:address":"Calle de Bidasoa, 11",
    "sg:city":"Madrid",
    "sg:orig_category":"Librer\u00cdas",
    "sg:phone":"+34 915 63 54 07",
    "sg:postcode":"28002",
    "sg:province":"Madrid",
    "wof:name":"Congregacion De La Pasion De Jesucristo",
    "wof:placetype":"venue"
},
  "geometry": {"coordinates":[-3.6817011833,40.4474868774],"type":"Point"}
}