{
  "type": "Feature",
  "properties": {
    "addr:full":"Carrer de Torino, 9 Mas D'en Bosch Tarragona 43850",
    "addr:housenumber":"9",
    "addr:postcode":"43850",
    "addr:street":"Carrer De Torino",
    "iso:country":"ES",
    "sg:address":"Carrer de Torino, 9",
    "sg:city":"Mas D'en Bosch",
    "sg:orig_category":"Jardiner\u00cdas, Vegetales, Art\u00cdculos De Jardiner\u00cda (al Por Menor)",
    "sg:phone":"+34 977 79 17 84",
    "sg:postcode":"43850",
    "sg:province":"Tarragona",
    "wof:name":"Rovira Matas Josep",
    "wof:placetype":"venue"
},
  "geometry": {"coordinates":[1.2731159925,41.1248588562],"type":"Point"}
}