{
  "type": "Feature",
  "properties": {
    "iso:country":"ES",
    "sg:address":"Calle de Gran Via, 50",
    "sg:city":"Majadahonda",
    "sg:orig_category":"Molduras, Junquillos, Listones Y Molduras Perforadas",
    "sg:phone":"+34 916 38 83 39",
    "sg:postcode":"28220",
    "sg:province":"Madrid",
    "wof:name":"Bar Gran Via S.l.l",
    "wof:placetype":"venue"
},
  "geometry": {"coordinates":[-3.8713169098,40.4706420898],"type":"Point"}
}