{
  "type": "Feature",
  "properties": {
    "addr:full":"Carrer de Balmes, 243 Barcelona Barcelona 08...",
    "addr:housenumber":"243",
    "addr:street":"Carrer De Balmes",
    "iso:country":"ES",
    "sg:address":"Carrer de Balmes, 243",
    "sg:city":"Barcelona",
    "sg:orig_category":"Cl\u00cdnicas M\u00c9dicas",
    "sg:phone":"+34 934 15 43 43",
    "sg:postcode":"08...",
    "sg:province":"Barcelona",
    "wof:name":"Sanitas S.a.",
    "wof:placetype":"venue"
},
  "geometry": {"coordinates":[2.1496810913,41.3995895386],"type":"Point"}
}