{
  "type": "Feature",
  "properties": {
    "iso:country":"ES",
    "sg:address":"Carrer de Vallclara, S/n",
    "sg:city":"Montblanc",
    "sg:orig_category":"Trabajos De Soldaduras",
    "sg:phone":"+34 977 86 05 98",
    "sg:postcode":"43400",
    "sg:province":"Tarragona",
    "wof:name":"Garcia Berbel Antonio",
    "wof:placetype":"venue"
},
  "geometry": {"coordinates":[1.1678600311,41.373790741],"type":"Point"}
}