{
  "type": "Feature",
  "properties": {
    "iso:country":"ES",
    "sg:address":"Calle de Cardenal Cisneros, 2",
    "sg:city":"Huelva",
    "sg:orig_category":"Arquitectos",
    "sg:phone":"+34 959 24 61 42",
    "sg:postcode":"21003",
    "sg:province":"Huelva",
    "wof:name":"Esteve Campillo Miguel Angel",
    "wof:placetype":"venue"
},
  "geometry": {"coordinates":[-6.949780941,37.2557220459],"type":"Point"}
}