{
  "type": "Feature",
  "properties": {
    "addr:full":"Estd Vigo, 25 Redondela Pontevedra 36800",
    "addr:housenumber":"25",
    "addr:postcode":"36800",
    "addr:street":"Vigo",
    "iso:country":"ES",
    "sg:address":"Estd Vigo, 25",
    "sg:city":"Redondela",
    "sg:orig_category":"Cerrajer\u00cda, Ferrallista",
    "sg:phone":"+34 986 40 04 53",
    "sg:postcode":"36800",
    "sg:province":"Pontevedra",
    "wof:name":"Amoedo Perez Manuel",
    "wof:placetype":"venue"
},
  "geometry": {"coordinates":[-8.6667060852,42.2751960754],"type":"Point"}
}