{
  "type": "Feature",
  "properties": {
    "addr:full":"Avda Samil, 91 Redondo Pontevedra 36212",
    "addr:housenumber":"91",
    "addr:postcode":"36212",
    "addr:street":"Avda Samil",
    "iso:country":"ES",
    "sg:address":"Avda Samil, 91",
    "sg:city":"Redondo",
    "sg:orig_category":"Navegaci\u00d3n (equipos Fluviales)",
    "sg:phone":"+34 986 24 09 30",
    "sg:postcode":"36212",
    "sg:province":"Pontevedra",
    "wof:name":"Molares Perez Enrique",
    "wof:placetype":"venue"
},
  "geometry": {"coordinates":[-8.7656679153,42.2123451233],"type":"Point"}
}