{
  "type": "Feature",
  "properties": {
    "addr:full":"Epela Bailara, 26 Epele Guip\u00f9zcoa 20120",
    "addr:housenumber":"26",
    "addr:postcode":"20120",
    "addr:street":"Epela Bailara;Guipu\u0300Zcoa",
    "iso:country":"ES",
    "sg:address":"Epela Bailara, 26",
    "sg:city":"Epele",
    "sg:orig_category":"Art\u00cdculos De Pvc (fabricaci\u00d3n Y Al Por Mayor)",
    "sg:phone":"+34 943 55 08 00",
    "sg:postcode":"20120",
    "sg:province":"Guip\u00f9zcoa",
    "wof:name":"Arkema Quimica S.a.",
    "wof:placetype":"venue"
},
  "geometry": {"coordinates":[-1.9798289537,43.2647514343],"type":"Point"}
}