{
  "type": "Feature",
  "properties": {
    "addr:full":"Calle de Ramon Y Cajal De, 1 Aviles Asturias 33402",
    "addr:housenumber":"1",
    "addr:postcode":"33402",
    "addr:street":"Calle De Ramon Y Cajal De",
    "iso:country":"ES",
    "sg:address":"Calle de Ramon Y Cajal De, 1",
    "sg:city":"Aviles",
    "sg:orig_category":"Carnicer\u00cdas, Carnicer\u00cdas",
    "sg:phone":"+34 985 54 33 37",
    "sg:postcode":"33402",
    "sg:province":"Asturias",
    "wof:name":"Robles Conde Jose Antonio",
    "wof:placetype":"venue"
},
  "geometry": {"coordinates":[-5.9292111397,43.5515937805],"type":"Point"}
}