{
  "type": "Feature",
  "properties": {
    "iso:country":"ES",
    "sg:address":"Calle de Mota Del Cuervo, 76",
    "sg:city":"Madrid",
    "sg:orig_category":"Farmacias",
    "sg:phone":"+34 913 88 41 72",
    "sg:postcode":"28043",
    "sg:province":"Madrid",
    "wof:name":"Hernandez Lopez Tomas",
    "wof:placetype":"venue"
},
  "geometry": {"coordinates":[-3.6316568851,40.4647407532],"type":"Point"}
}