{
  "type": "Feature",
  "properties": {
    "addr:full":"Calle de Pio Baroja, 7 Madrid Madrid 28009",
    "addr:housenumber":"7",
    "addr:postcode":"madrid;28009",
    "addr:street":"Calle De Pio Baroja",
    "iso:country":"ES",
    "sg:address":"Calle de Pio Baroja, 7",
    "sg:city":"Madrid",
    "sg:orig_category":"Empresarios",
    "sg:phone":"+34 915 57 03 01",
    "sg:postcode":"28009",
    "sg:province":"Madrid",
    "sg:website":"www.decoinser.com",
    "wof:name":"Decoinser Obras Y Servicion S.l.",
    "wof:placetype":"venue"
},
  "geometry": {"coordinates":[-3.6743888855,40.4154586792],"type":"Point"}
}