{
  "type": "Feature",
  "properties": {
    "addr:full":"Calle de Virgen De Guadalupe, 7 Badajoz Badajoz 06003",
    "addr:housenumber":"7",
    "addr:postcode":"06003",
    "addr:street":"Calle De Virgen De Guadalupe",
    "iso:country":"ES",
    "sg:address":"Calle de Virgen De Guadalupe, 7",
    "sg:city":"Badajoz",
    "sg:orig_category":"Museos",
    "sg:phone":"+34 924 25 33 28",
    "sg:postcode":"06003",
    "sg:province":"Badajoz",
    "wof:name":"Asociacion De Amigos Del Museo Iberoamericano De Arte Contemporaneo",
    "wof:placetype":"venue"
},
  "geometry": {"coordinates":[-6.6306562424,38.8906669617],"type":"Point"}
}