{
  "type": "Feature",
  "properties": {
    "addr:full":"Carrer de M De Deu Victoria, 14 Palma Islas Baleares 07008",
    "addr:housenumber":"14",
    "addr:postcode":"07008",
    "addr:street":"Carrer De M De Deu Victoria",
    "iso:country":"ES",
    "sg:address":"Carrer de M De Deu Victoria, 14",
    "sg:city":"Palma",
    "sg:orig_category":"Agentes, Concesionarios Y Sucursales De Veh\u00cdculos",
    "sg:phone":"+34 971 24 04 46",
    "sg:postcode":"07008",
    "sg:province":"Islas Baleares",
    "wof:name":"Auto Freno Oliver S.a.",
    "wof:placetype":"venue"
},
  "geometry": {"coordinates":[2.670224905,39.5823440552],"type":"Point"}
}