{
  "type": "Feature",
  "properties": {
    "addr:full":"Calle de San Nicolas, 29 San Nicolas Murcia 30005",
    "addr:housenumber":"29",
    "addr:postcode":"30005",
    "addr:street":"Calle De San",
    "iso:country":"ES",
    "sg:address":"Calle de San Nicolas, 29",
    "sg:city":"San Nicolas",
    "sg:orig_category":"Artes Gr\u00c1ficas, Artes Pl\u00c1sticas (curso)",
    "sg:phone":"+34 968 21 27 28",
    "sg:postcode":"30005",
    "sg:province":"Murcia",
    "wof:name":"Tipografia San Francisco S.a.",
    "wof:placetype":"venue"
},
  "geometry": {"coordinates":[-1.1357009411,37.9863204956],"type":"Point"}
}