{
  "type": "Feature",
  "properties": {
    "addr:full":"Plaz Espa\u00d1a, 10 Aldeanueva Ebro La Rioja 26559",
    "addr:housenumber":"10",
    "addr:postcode":"26559",
    "addr:street":"Plaz Espan\u0303A;Ebro",
    "iso:country":"ES",
    "sg:address":"Plaz Espa\u00d1a, 10",
    "sg:city":"Aldeanueva Ebro",
    "sg:orig_category":"Cajas De Ahorro",
    "sg:phone":"+34 941 16 30 10",
    "sg:postcode":"26559",
    "sg:province":"La Rioja",
    "wof:name":"Caja De Ahorros Y Monte De Piedad De Zaragoza Aragon Y Rioja",
    "wof:placetype":"venue"
},
  "geometry": {"coordinates":[-1.8801590204,42.2278594971],"type":"Point"}
}