{
  "type": "Feature",
  "properties": {
    "addr:full":"Calle de Martires, 1 Almendralejo Badajoz 06200",
    "addr:housenumber":"1",
    "addr:postcode":"06200",
    "addr:street":"Calle De Martires",
    "iso:country":"ES",
    "sg:address":"Calle de Martires, 1",
    "sg:city":"Almendralejo",
    "sg:orig_category":"Abogados",
    "sg:phone":"+34 924 66 39 31",
    "sg:postcode":"06200",
    "sg:province":"Badajoz",
    "wof:name":"Tenorio Cubero Aurora",
    "wof:placetype":"venue"
},
  "geometry": {"coordinates":[-6.408454895,38.6829071045],"type":"Point"}
}