{
  "type": "Feature",
  "properties": {
    "iso:country":"ES",
    "sg:address":"Avda Ernesto Che Guevara, 1",
    "sg:city":"Perillo",
    "sg:orig_category":"Empresas De Vigilancia, Guardia Y Protecci\u00d3n",
    "sg:phone":"+34 981 61 37 71",
    "sg:postcode":"15172",
    "sg:province":"A Coru\u00f1a",
    "sg:website":"www.securitasdirect.es",
    "wof:name":"Securitas Direct Espa\u00d1a S.a.",
    "wof:placetype":"venue"
},
  "geometry": {"coordinates":[-8.3740053177,43.3324584961],"type":"Point"}
}