{
  "type": "Feature",
  "properties": {
    "iso:country":"ES",
    "sg:address":"Ctra Arahal-coronil, Km. 0001,0",
    "sg:city":"Arahal",
    "sg:orig_category":"Centros Empresariales",
    "sg:phone":"+34 954 84 15 99",
    "sg:postcode":"41600",
    "sg:province":"Sevilla",
    "wof:name":"Industrial Mecanica Arahalense Sociedad Cooperativa",
    "wof:placetype":"venue"
},
  "geometry": {"coordinates":[-5.5428285599,37.2640991211],"type":"Point"}
}