{
  "type": "Feature",
  "properties": {
    "addr:full":"Calle de Fernando El Catolico, 84 Madrid Madrid 28015",
    "addr:housenumber":"84",
    "addr:postcode":"madrid;28015",
    "addr:street":"Calle De Fernando El Catolico",
    "iso:country":"ES",
    "sg:address":"Calle de Fernando El Catolico, 84",
    "sg:city":"Madrid",
    "sg:orig_category":"M\u00c9dicos: Radioterapia (radioterapia Como Opci\u00d3n Oncol\u00d3gica)",
    "sg:phone":"+34 915 49 77 67",
    "sg:postcode":"28015",
    "sg:province":"Madrid",
    "wof:name":"Sanchez Alvarez-pedrosa Cesar",
    "wof:placetype":"venue"
},
  "geometry": {"coordinates":[-3.7169630527,40.4345703125],"type":"Point"}
}