{
  "type": "Feature",
  "properties": {
    "addr:full":"Cno Chorli(vereda), 16 Cartagena Murcia 30395",
    "addr:housenumber":"16",
    "addr:postcode":"30395",
    "addr:street":"Cno Chorli Vereda",
    "iso:country":"ES",
    "sg:address":"Cno Chorli(vereda), 16",
    "sg:city":"Cartagena",
    "sg:orig_category":"Agencias De Trabajo Temporal",
    "sg:phone":"+34 968 50 55 48",
    "sg:postcode":"30395",
    "sg:province":"Murcia",
    "wof:name":"Madrid Martinez Pedro Antonio",
    "wof:placetype":"venue"
},
  "geometry": {"coordinates":[-0.9203090072,37.717918396],"type":"Point"}
}