{
  "type": "Feature",
  "properties": {
    "addr:full":"Ed Playa Rocio, 1 Matalasca\u00f1as Huelva 21760",
    "addr:housenumber":"1",
    "addr:postcode":"21760",
    "addr:street":"Rocio",
    "iso:country":"ES",
    "sg:address":"Ed Playa Rocio, 1",
    "sg:city":"Matalasca\u00f1as",
    "sg:orig_category":"Supermercados Y Hipermercados",
    "sg:phone":"+34 959 44 00 42",
    "sg:postcode":"21760",
    "sg:province":"Huelva",
    "wof:name":"Kiko Comestibles Y Frutas S.l.",
    "wof:placetype":"venue"
},
  "geometry": {"coordinates":[-6.5630187988,37.0096244812],"type":"Point"}
}