{
  "type": "Feature",
  "properties": {
    "iso:country":"ES",
    "sg:address":"Plaz Espa\u00d1a, S/n",
    "sg:city":"Carbajo",
    "sg:orig_category":"Administraciones Regionales, Departamentales Y Locales",
    "sg:phone":"+34 927 59 20 37",
    "sg:postcode":"10511",
    "sg:province":"C\u00e1ceres",
    "wof:name":"Ayuntamiento De Carbajo",
    "wof:placetype":"venue"
},
  "geometry": {"coordinates":[-7.1736383438,39.6211433411],"type":"Point"}
}