{
  "type": "Feature",
  "properties": {
    "iso:country":"ES",
    "sg:address":"Carrer de Lluis Puigjaner, 81",
    "sg:city":"Olesa Montserrat",
    "sg:orig_category":"Abogados",
    "sg:phone":"+34 937 78 07 70",
    "sg:postcode":"08640",
    "sg:province":"Barcelona",
    "wof:name":"Dinares Turell Carles",
    "wof:placetype":"venue"
},
  "geometry": {"coordinates":[1.8911499977,41.5435600281],"type":"Point"}
}