{
  "type": "Feature",
  "properties": {
    "addr:full":"Calle de Arriba, 25 Lucena Puerto Huelva 21820",
    "addr:housenumber":"25",
    "addr:postcode":"21820",
    "addr:street":"Calle De Arriba;Puerto",
    "iso:country":"ES",
    "sg:address":"Calle de Arriba, 25",
    "sg:city":"Lucena Puerto",
    "sg:orig_category":"Agencias Y Agentes Comerciales, Representantes",
    "sg:phone":"+34 959 36 18 60",
    "sg:postcode":"21820",
    "sg:province":"Huelva",
    "wof:name":"Borrero Gomez Maria Emilia",
    "wof:placetype":"venue"
},
  "geometry": {"coordinates":[-6.7291455269,37.3034362793],"type":"Point"}
}