{
  "type": "Feature",
  "properties": {
    "addr:full":"Carr Ciutadella, S/n Mao Islas Baleares 07700",
    "addr:housenumber":"s / n",
    "addr:postcode":"07700",
    "addr:street":"Carr Ciutadella",
    "iso:country":"ES",
    "sg:address":"Carr Ciutadella, S/n",
    "sg:city":"Mao",
    "sg:orig_category":"Aguas (distribuci\u00d3n, Servicios)",
    "sg:phone":"+34 971 36 14 64",
    "sg:postcode":"07700",
    "sg:province":"Islas Baleares",
    "wof:name":"Sucesores De Joaquin Pons Sintes S.l.",
    "wof:placetype":"venue"
},
  "geometry": {"coordinates":[4.2699050903,39.9505195618],"type":"Point"}
}