{
  "type": "Feature",
  "properties": {
    "addr:full":"Carretera Lobon-la Roca, Km. 0004,0 Montijo Badajoz 06480",
    "addr:postcode":"06480",
    "addr:street":"Carretera Lobon-La Roca Km. 0004,0",
    "iso:country":"ES",
    "sg:address":"Carretera Lobon-la Roca, Km. 0004,0",
    "sg:city":"Montijo",
    "sg:orig_category":"Electricidad: Instaladores",
    "sg:phone":"+34 924 45 30 61",
    "sg:postcode":"06480",
    "sg:province":"Badajoz",
    "wof:name":"Cabo Montajes Electricos S.l.",
    "wof:placetype":"venue"
},
  "geometry": {"coordinates":[-6.6062841415,38.9077644348],"type":"Point"}
}