{
  "type": "Feature",
  "properties": {
    "addr:full":"Cm\u00d1o Espi\u00d1eiro, 69 Vigo Pontevedra 36207",
    "addr:housenumber":"69",
    "addr:postcode":"36207",
    "addr:street":"Espin\u0303Eiro",
    "iso:country":"ES",
    "sg:address":"Cm\u00d1o Espi\u00d1eiro, 69",
    "sg:city":"Vigo",
    "sg:orig_category":"Caf\u00c9s, Bares, Cervecer\u00cdas",
    "sg:phone":"+34 986 26 47 52",
    "sg:postcode":"36207",
    "sg:province":"Pontevedra",
    "wof:name":"Mendez Lago Maria Jesus",
    "wof:placetype":"venue"
},
  "geometry": {"coordinates":[-8.7026195526,42.2521095276],"type":"Point"}
}