{
  "type": "Feature",
  "properties": {
    "addr:full":"Carretera, S/n Pobla Cervoles Lleida 25471",
    "addr:postcode":"25471",
    "addr:street":"Carretera S / N",
    "iso:country":"ES",
    "sg:address":"Carretera, S/n",
    "sg:city":"Pobla Cervoles",
    "sg:orig_category":"Cooperativas Agr\u00cdcolas",
    "sg:phone":"+34 973 17 51 51",
    "sg:postcode":"25471",
    "sg:province":"Lleida",
    "wof:name":"Cooperativa Del Campo",
    "wof:placetype":"venue"
},
  "geometry": {"coordinates":[0.9162009954,41.3668212891],"type":"Point"}
}