{
  "type": "Feature",
  "properties": {
    "addr:full":"Carrer de Buscarons, 14 Barcelona Barcelona 08022",
    "addr:housenumber":"14",
    "addr:postcode":"08022",
    "addr:street":"Carrer De Buscarons",
    "iso:country":"ES",
    "sg:address":"Carrer de Buscarons, 14",
    "sg:city":"Barcelona",
    "sg:orig_category":"Florister\u00cdas",
    "sg:phone":"+34 934 18 14 48",
    "sg:postcode":"08022",
    "sg:province":"Barcelona",
    "wof:name":"Conillas Castells Jose Ignacio",
    "wof:placetype":"venue"
},
  "geometry": {"coordinates":[2.1381080151,41.406414032],"type":"Point"}
}