{
  "type": "Feature",
  "properties": {
    "addr:full":"Calle de Rafael Altamira, 12 Alacant Alicante 03002",
    "addr:housenumber":"12",
    "addr:postcode":"03002",
    "addr:street":"Calle De Rafael Altamira",
    "iso:country":"ES",
    "sg:address":"Calle de Rafael Altamira, 12",
    "sg:city":"Alacant",
    "sg:orig_category":"Arquitectos",
    "sg:phone":"+34 965 20 41 77",
    "sg:postcode":"03002",
    "sg:province":"Alicante",
    "wof:name":"Candela Diaz Juan Luis",
    "wof:placetype":"venue"
},
  "geometry": {"coordinates":[-0.4823099971,38.3444480896],"type":"Point"}
}