{
  "type": "Feature",
  "properties": {
    "addr:full":"Calle de Manuel Iradier, 29 Vitoria-gasteiz \u00c1lava 01005",
    "addr:housenumber":"29",
    "addr:postcode":"01005",
    "addr:street":"Calle De Manuel Iradier",
    "iso:country":"ES",
    "sg:address":"Calle de Manuel Iradier, 29",
    "sg:city":"Vitoria-gasteiz",
    "sg:orig_category":"M\u00c9dicos: Psiquiatr\u00cda",
    "sg:phone":"+34 945 23 22 89",
    "sg:postcode":"01005",
    "sg:province":"\u00c1lava",
    "wof:name":"Arzamendi Emparanza Alfonso",
    "wof:placetype":"venue"
},
  "geometry": {"coordinates":[-2.6704795361,42.841999054],"type":"Point"}
}