{
  "type": "Feature",
  "properties": {
    "iso:country":"ES",
    "sg:address":"Avda Juan Ramon Jimenez, 167",
    "sg:city":"Calasparra",
    "sg:orig_category":"Bebidas",
    "sg:phone":"+34 968 74 52 82",
    "sg:postcode":"30420",
    "sg:province":"Murcia",
    "wof:name":"Juan Egea Rodriguez Y Otros C.b.",
    "wof:placetype":"venue"
},
  "geometry": {"coordinates":[-1.7100080252,38.2250900269],"type":"Point"}
}