{
  "type": "Feature",
  "properties": {
    "iso:country":"ES",
    "sg:address":"Calle de Poeta Madrid, 4",
    "sg:city":"Balsicas",
    "sg:orig_category":"Lavado, Limpieza De Veh\u00cdculos",
    "sg:phone":"+34 968 58 06 46",
    "sg:postcode":"30591",
    "sg:province":"Murcia",
    "wof:name":"Balsicauto S.l",
    "wof:placetype":"venue"
},
  "geometry": {"coordinates":[-0.9609609842,37.8191490173],"type":"Point"}
}