{
  "type": "Feature",
  "properties": {
    "iso:country":"ES",
    "sg:address":"Carr Firal, 60",
    "sg:city":"Sarria Ter",
    "sg:orig_category":"Ense\u00d1anza, Formaci\u00d3n Profesional: Aprendizaje",
    "sg:phone":"+34 972 17 05 40",
    "sg:postcode":"17840",
    "sg:province":"Girona",
    "wof:name":"Ajuntament De Sarria De Ter",
    "wof:placetype":"venue"
},
  "geometry": {"coordinates":[2.8240082264,42.016998291],"type":"Point"}
}