{
  "type": "Feature",
  "properties": {
    "iso:country":"ES",
    "sg:address":"Cmno Viejo De Silla, S/n",
    "sg:city":"Albal",
    "sg:orig_category":"Materias Pl\u00c1sticas: Productos De Consumo Masivo (fabricaci\u00d3n, Al Por Mayor)",
    "sg:phone":"+34 961 27 06 04",
    "sg:postcode":"46470",
    "sg:province":"Valencia",
    "wof:name":"Teclar S. L.",
    "wof:placetype":"venue"
},
  "geometry": {"coordinates":[-0.4010640085,39.3901252747],"type":"Point"}
}