{
  "type": "Feature",
  "properties": {
    "addr:full":"Calle de Enrique Velasco, 43 Madrid Madrid 28038",
    "addr:housenumber":"43",
    "addr:postcode":"madrid;28038",
    "addr:street":"Calle De Enrique Velasco",
    "iso:country":"ES",
    "sg:address":"Calle de Enrique Velasco, 43",
    "sg:city":"Madrid",
    "sg:orig_category":"Ingeniero",
    "sg:phone":"+34 914 30 48 52",
    "sg:postcode":"28038",
    "sg:province":"Madrid",
    "wof:name":"Carma Ingenieros S.l.",
    "wof:placetype":"venue"
},
  "geometry": {"coordinates":[-3.6593110561,40.3954162598],"type":"Point"}
}