{
  "type": "Feature",
  "properties": {
    "iso:country":"ES",
    "sg:address":"Carrer de Arago, 12",
    "sg:city":"Palma",
    "sg:orig_category":"Cojinetes De Bolas, Agujas Y Rodillos (fabricaci\u00d3n, Al Por Mayor)",
    "sg:phone":"+34 971 46 04 67",
    "sg:postcode":"07006",
    "sg:province":"Islas Baleares",
    "wof:name":"La Herramienta Balear S.a.",
    "wof:placetype":"venue"
},
  "geometry": {"coordinates":[2.6576600075,39.5737304688],"type":"Point"}
}