{
  "type": "Feature",
  "properties": {
    "addr:full":"Calle de Maria Pilar Lasarte, 31 Jerez De Los Caballeros Badajoz 06380",
    "addr:housenumber":"31",
    "addr:postcode":"06380",
    "addr:street":"Calle De Maria;Lasarte",
    "iso:country":"ES",
    "sg:address":"Calle de Maria Pilar Lasarte, 31",
    "sg:city":"Jerez De Los Caballeros",
    "sg:orig_category":"Ropa Para Ni\u00d1os (al Por Menor)",
    "sg:phone":"+34 924 73 07 73",
    "sg:postcode":"06380",
    "sg:province":"Badajoz",
    "wof:name":"Gonzalez Perez Angel",
    "wof:placetype":"venue"
},
  "geometry": {"coordinates":[-6.7712898254,38.321598053],"type":"Point"}
}