{
  "type": "Feature",
  "properties": {
    "addr:full":"Carr Hospital, 36 Palamos Girona 17230",
    "addr:housenumber":"36",
    "addr:postcode":"17230",
    "addr:street":"Carr Hospital",
    "iso:country":"ES",
    "sg:address":"Carr Hospital, 36",
    "sg:city":"Palamos",
    "sg:orig_category":"Hospitales",
    "sg:phone":"+34 972 60 01 60",
    "sg:postcode":"17230",
    "sg:province":"Girona",
    "wof:name":"Hospital De Palamos",
    "wof:placetype":"venue"
},
  "geometry": {"coordinates":[3.1311340332,41.8527755737],"type":"Point"}
}