{
  "type": "Feature",
  "properties": {
    "addr:full":"Avda San Amador, 45 Martos Ja\u00e9n 23600",
    "addr:housenumber":"45",
    "addr:postcode":"23600",
    "addr:street":"Avda San Amador;Jae\u0301N",
    "iso:country":"ES",
    "sg:address":"Avda San Amador, 45",
    "sg:city":"Martos",
    "sg:orig_category":"Alimentaci\u00d3n General (al Por Mayor)",
    "sg:phone":"+34 953 55 48 61",
    "sg:postcode":"23600",
    "sg:province":"Ja\u00e9n",
    "sg:website":"www.telelibericos.com",
    "wof:name":"Sanchez Barrio Josefa",
    "wof:placetype":"venue"
},
  "geometry": {"coordinates":[-3.9753670692,37.7198143005],"type":"Point"}
}