{
  "type": "Feature",
  "properties": {
    "addr:full":"Calle de Puerto De La Cruz Verde, 26 Madrid Madrid 28045",
    "addr:housenumber":"26",
    "addr:postcode":"madrid;28045",
    "addr:street":"Calle De Puerto;Verde",
    "iso:country":"ES",
    "sg:address":"Calle de Puerto De La Cruz Verde, 26",
    "sg:city":"Madrid",
    "sg:orig_category":"Ingenier\u00cda, Centros De Estudios (diversos)",
    "sg:phone":"+34 915 27 31 22",
    "sg:postcode":"28045",
    "sg:province":"Madrid",
    "wof:name":"Anvasa Sociedad Anonima De Estudios Tecnicos",
    "wof:placetype":"venue"
},
  "geometry": {"coordinates":[-3.6856174469,40.3854408264],"type":"Point"}
}