{
  "type": "Feature",
  "properties": {
    "addr:full":"Calle de Sagasta, 11 Madrid Madrid 28004",
    "addr:housenumber":"11",
    "addr:postcode":"madrid;28004",
    "addr:street":"Calle De Sagasta",
    "iso:country":"ES",
    "sg:address":"Calle de Sagasta, 11",
    "sg:city":"Madrid",
    "sg:orig_category":"Cajas De Ahorro",
    "sg:phone":"+34 915 94 44 36",
    "sg:postcode":"28004",
    "sg:province":"Madrid",
    "wof:name":"Caja De Ahorros Y Monte De Piedad De Segovia",
    "wof:placetype":"venue"
},
  "geometry": {"coordinates":[-3.7001760006,40.4287223816],"type":"Point"}
}