{
  "type": "Feature",
  "properties": {
    "addr:full":"Carrer de M D Montserrat, 1 Viladecans Barcelona 08840",
    "addr:housenumber":"1",
    "addr:postcode":"08840",
    "addr:street":"Carrer De M;Montserrat",
    "iso:country":"ES",
    "sg:address":"Carrer de M D Montserrat, 1",
    "sg:city":"Viladecans",
    "sg:orig_category":"Papeler\u00cdas, Librer\u00cdas",
    "sg:phone":"+34 936 59 10 03",
    "sg:postcode":"08840",
    "sg:province":"Barcelona",
    "wof:name":"Rivera Pinilla Cesar",
    "wof:placetype":"venue"
},
  "geometry": {"coordinates":[2.0119450092,41.3259811401],"type":"Point"}
}