{
  "type": "Feature",
  "properties": {
    "addr:full":"Via Laietana, 24 Barcelona Barcelona 08003",
    "addr:housenumber":"24",
    "addr:postcode":"08003",
    "addr:street":"Via Laietana",
    "iso:country":"ES",
    "sg:address":"Via Laietana, 24",
    "sg:city":"Barcelona",
    "sg:orig_category":"Grafistas",
    "sg:phone":"+34 933 15 25 28",
    "sg:postcode":"08003",
    "sg:province":"Barcelona",
    "wof:name":"Annette Scarfe Design S.l.",
    "wof:placetype":"venue"
},
  "geometry": {"coordinates":[2.1783397198,41.3842887878],"type":"Point"}
}