{
  "type": "Feature",
  "properties": {
    "addr:full":"Navarro Villoslada, 1 Iru\u00f1a Navarra 31004",
    "addr:housenumber":"1",
    "addr:postcode":"31004",
    "addr:street":"Villoslada",
    "iso:country":"ES",
    "sg:address":"Navarro Villoslada, 1",
    "sg:city":"Iru\u00f1a",
    "sg:orig_category":"Cajas De Ahorro",
    "sg:phone":"+34 948 23 76 16",
    "sg:postcode":"31004",
    "sg:province":"Navarra",
    "wof:name":"Caja De Ahorros Y Monte De Piedad De Zaragoza Aragon Y Rioja",
    "wof:placetype":"venue"
},
  "geometry": {"coordinates":[-1.6395599842,42.8127174377],"type":"Point"}
}