{
  "type": "Feature",
  "properties": {
    "addr:full":"Av Valencia, 78 Molins Rei Barcelona 08750",
    "addr:housenumber":"78",
    "addr:postcode":"08750",
    "addr:street":"Av Valencia;Barcelona",
    "iso:country":"ES",
    "sg:address":"Av Valencia, 78",
    "sg:city":"Molins Rei",
    "sg:orig_category":"Chapister\u00cda",
    "sg:phone":"+34 936 68 90 51",
    "sg:postcode":"08750",
    "sg:province":"Barcelona",
    "wof:name":"Talleres Lazaro Miguel S.c.p.",
    "wof:placetype":"venue"
},
  "geometry": {"coordinates":[2.0161581039,41.4097938538],"type":"Point"}
}