{
  "type": "Feature",
  "properties": {
    "iso:country":"ES",
    "sg:address":"Plaz Cebada, 2",
    "sg:city":"Madrid",
    "sg:orig_category":"Caf\u00c9s, Bares, Cervecer\u00cdas",
    "sg:phone":"+34 913 54 01 77",
    "sg:postcode":"28005",
    "sg:province":"Madrid",
    "wof:name":"Diaz Gonzalez Carlos",
    "wof:placetype":"venue"
},
  "geometry": {"coordinates":[-3.7101099491,40.4105834961],"type":"Point"}
}