{
  "type": "Feature",
  "properties": {
    "addr:full":"Praz Suarez Llanos, S/n Vigo Pontevedra 36208",
    "addr:housenumber":"s / n",
    "addr:postcode":"36208",
    "addr:street":"Praz Suarez Llanos",
    "iso:country":"ES",
    "sg:address":"Praz Suarez Llanos, S/n",
    "sg:city":"Vigo",
    "sg:orig_category":"Librer\u00cdas",
    "sg:phone":"+34 986 23 83 33",
    "sg:postcode":"36208",
    "sg:province":"Pontevedra",
    "wof:name":"Fernandez Caballero Florinda",
    "wof:placetype":"venue"
},
  "geometry": {"coordinates":[-8.7535676956,42.2243614197],"type":"Point"}
}