{
  "type": "Feature",
  "properties": {
    "addr:full":"Estd Castela, 51 Ferrol La Coru\u00f1a 15403",
    "addr:housenumber":"51",
    "addr:postcode":"15403",
    "addr:street":"Castela;La Corun\u0303A",
    "iso:country":"ES",
    "sg:address":"Estd Castela, 51",
    "sg:city":"Ferrol",
    "sg:orig_category":"Agencias Y Asesores De Publicidad",
    "sg:phone":"+34 981 37 33 21",
    "sg:postcode":"15403",
    "sg:province":"La Coru\u00f1a",
    "wof:name":"Ferropalo S.l.",
    "wof:placetype":"venue"
},
  "geometry": {"coordinates":[-8.2245254517,43.488117218],"type":"Point"}
}