{
  "type": "Feature",
  "properties": {
    "addr:full":"Rond Buenavista, 27 Toledo Toledo 45005",
    "addr:housenumber":"27",
    "addr:postcode":"45005",
    "addr:street":"Buenavista",
    "iso:country":"ES",
    "sg:address":"Rond Buenavista, 27",
    "sg:city":"Toledo",
    "sg:orig_category":"Asociaciones Humanitarias, De Cooperaci\u00d3n, De Acci\u00d3n Social",
    "sg:phone":"+34 925 25 61 84",
    "sg:postcode":"45005",
    "sg:province":"Toledo",
    "sg:website":"www.obelen.org",
    "wof:name":"Fundacion Internacional O'belen",
    "wof:placetype":"venue"
},
  "geometry": {"coordinates":[-4.0381760597,39.8769302368],"type":"Point"}
}