{
  "type": "Feature",
  "properties": {
    "iso:country":"ES",
    "sg:address":"Josep Renau, S/n",
    "sg:city":"Silla",
    "sg:orig_category":"Muebles",
    "sg:phone":"+34 961 21 64 76",
    "sg:postcode":"46460",
    "sg:province":"Valencia",
    "wof:name":"Armobany S L",
    "wof:placetype":"venue"
},
  "geometry": {"coordinates":[-0.4160721004,39.3729705811],"type":"Point"}
}