{
  "type": "Feature",
  "properties": {
    "addr:full":"Calle de Padre Oltra, 67 Madrid Madrid 28019",
    "addr:housenumber":"67",
    "addr:postcode":"madrid;28019",
    "addr:street":"Calle De Padre Oltra",
    "iso:country":"ES",
    "sg:address":"Calle de Padre Oltra, 67",
    "sg:city":"Madrid",
    "sg:orig_category":"Protecci\u00d3n Contra Incendios: Material, Instalaci\u00d3n, Mantenimiento",
    "sg:phone":"+34 915 60 60 05",
    "sg:postcode":"28019",
    "sg:province":"Madrid",
    "sg:website":"www.cpisa.es",
    "wof:name":"Comercial De Proteccion Contra Incendios S.a.",
    "wof:placetype":"venue"
},
  "geometry": {"coordinates":[-3.7103559971,40.3941421509],"type":"Point"}
}