{
  "type": "Feature",
  "properties": {
    "addr:full":"Calle de Jarra (la), S/n Rambla C\u00f3rdoba 14540",
    "addr:housenumber":"/ n",
    "addr:postcode":"14540",
    "addr:street":"Calle De Jarra La S;Rambla Co\u0301Rdoba",
    "iso:country":"ES",
    "sg:address":"Calle de Jarra (la), S/n",
    "sg:city":"Rambla",
    "sg:orig_category":"Promotores Constructores",
    "sg:phone":"+34 957 68 31 43",
    "sg:postcode":"14540",
    "sg:province":"C\u00f3rdoba",
    "wof:name":"Masanes Cordoba S.a.",
    "wof:placetype":"venue"
},
  "geometry": {"coordinates":[-4.725479126,37.6128883362],"type":"Point"}
}