{
  "type": "Feature",
  "properties": {
    "addr:full":"C/ Cami La Vall, 138 Moncofa Castell\u00f3n 12593",
    "addr:housenumber":"138",
    "addr:postcode":"12593",
    "addr:street":"C / Cami La Vall;Castello\u0301N",
    "iso:country":"ES",
    "sg:address":"C/ Cami La Vall, 138",
    "sg:city":"Moncofa",
    "sg:orig_category":"Material Y Herramientas Agr\u00cdcolas",
    "sg:phone":"+34 964 58 02 19",
    "sg:postcode":"12593",
    "sg:province":"Castell\u00f3n",
    "wof:name":"Silvestre Tena Francisco",
    "wof:placetype":"venue"
},
  "geometry": {"coordinates":[-0.1429889947,39.8067741394],"type":"Point"}
}