{
  "type": "Feature",
  "properties": {
    "addr:full":"Avda Vigo, 97 Cangas Pontevedra 36940",
    "addr:housenumber":"97",
    "addr:postcode":"36940",
    "addr:street":"Avda Vigo",
    "iso:country":"ES",
    "sg:address":"Avda Vigo, 97",
    "sg:city":"Cangas",
    "sg:orig_category":"Promotores Constructores",
    "sg:phone":"+34 986 30 00 01",
    "sg:postcode":"36940",
    "sg:province":"Pontevedra",
    "wof:name":"Nodosa S. L.",
    "wof:placetype":"venue"
},
  "geometry": {"coordinates":[-8.7861070633,42.2668266296],"type":"Point"}
}