{
  "type": "Feature",
  "properties": {
    "iso:country":"ES",
    "sg:address":"Puerto, 1",
    "sg:city":"Calpe",
    "sg:orig_category":"Art\u00cdculos De Regalo (al Por Menor)",
    "sg:phone":"+34 965 83 29 47",
    "sg:postcode":"03710",
    "sg:province":"Alicante",
    "wof:name":"Fernandez Peregri Julio",
    "wof:placetype":"venue"
},
  "geometry": {"coordinates":[0.0432949997,38.6458091736],"type":"Point"}
}