{
  "type": "Feature",
  "properties": {
    "addr:full":"Calle de Isaac Peral (corralejo), 17 Corralejo Las Palmas 35660",
    "addr:housenumber":"17",
    "addr:postcode":"35660",
    "addr:street":"Calle De Isaac Peral Corralejo",
    "iso:country":"ES",
    "sg:address":"Calle de Isaac Peral (corralejo), 17",
    "sg:city":"Corralejo",
    "sg:orig_category":"Doctores En Medicina",
    "sg:phone":"+34 928 86 77 04",
    "sg:postcode":"35660",
    "sg:province":"Las Palmas",
    "wof:name":"Del Toro Calero Cleto",
    "wof:placetype":"venue"
},
  "geometry": {"coordinates":[-13.8695268631,28.7381401062],"type":"Point"}
}