{
  "type": "Feature",
  "properties": {
    "addr:full":"Calle de Maestro Miguel Galan, 24 Valencia Valencia 46025",
    "addr:housenumber":"24",
    "addr:postcode":"46025",
    "addr:street":"Calle De Maestro Miguel Galan",
    "iso:country":"ES",
    "sg:address":"Calle de Maestro Miguel Galan, 24",
    "sg:city":"Valencia",
    "sg:orig_category":"Molduras, Junquillos, Listones Y Molduras Perforadas",
    "sg:phone":"+34 963 47 47 21",
    "sg:postcode":"46025",
    "sg:province":"Valencia",
    "wof:name":"Ayiso Moya Pedro",
    "wof:placetype":"venue"
},
  "geometry": {"coordinates":[-0.3927932978,39.4958267212],"type":"Point"}
}