{
  "type": "Feature",
  "properties": {
    "addr:full":"Carrer de Torrassa, 106 S. Adria Besos Barcelona 08930",
    "addr:housenumber":"106",
    "addr:postcode":"08930",
    "addr:street":"Carrer De Torrassa;S. Adria Besos Barcelona",
    "iso:country":"ES",
    "sg:address":"Carrer de Torrassa, 106",
    "sg:city":"S. Adria Besos",
    "sg:orig_category":"Veh\u00cdculos De Ocasi\u00d3n",
    "sg:phone":"+34 934 62 23 83",
    "sg:postcode":"08930",
    "sg:province":"Barcelona",
    "wof:name":"Auto-meseguer S.l.",
    "wof:placetype":"venue"
},
  "geometry": {"coordinates":[2.2285919189,41.4297676086],"type":"Point"}
}