{
  "type": "Feature",
  "properties": {
    "addr:full":"Carr Goya, 5 Lleida Lleida 25001",
    "addr:housenumber":"5",
    "addr:postcode":"25001",
    "addr:street":"Carr Goya",
    "iso:country":"ES",
    "sg:address":"Carr Goya, 5",
    "sg:city":"Lleida",
    "sg:orig_category":"Chapister\u00cda",
    "sg:phone":"+34 973 20 16 76",
    "sg:postcode":"25001",
    "sg:province":"Lleida",
    "wof:name":"Bresoli Enrich Juan",
    "wof:placetype":"venue"
},
  "geometry": {"coordinates":[0.6414020061,41.604057312],"type":"Point"}
}