{
  "type": "Feature",
  "properties": {
    "iso:country":"ES",
    "sg:address":"Pr. Victoria Cadaval, 9",
    "sg:city":"A Ramallosa",
    "sg:orig_category":"Servicios De Telecomunicaciones",
    "sg:phone":"+34 986 35 00 03",
    "sg:postcode":"36393",
    "sg:province":"Pontevedra",
    "wof:name":"Satele Dolbycar S.l.",
    "wof:placetype":"venue"
},
  "geometry": {"coordinates":[-8.8274269104,42.1040344238],"type":"Point"}
}