{
  "type": "Feature",
  "properties": {
    "addr:full":"Calle de Algaba, 21 Madrid Madrid 28019",
    "addr:housenumber":"21",
    "addr:postcode":"madrid;28019",
    "addr:street":"Calle De Algaba",
    "iso:country":"ES",
    "sg:address":"Calle de Algaba, 21",
    "sg:city":"Madrid",
    "sg:orig_category":"Peluqueros: De Se\u00d1oras",
    "sg:phone":"+34 915 25 80 57",
    "sg:postcode":"28019",
    "sg:province":"Madrid",
    "wof:name":"Arias Quirpga Silvia",
    "wof:placetype":"venue"
},
  "geometry": {"coordinates":[-3.7359986305,40.3910865784],"type":"Point"}
}