{
  "type": "Feature",
  "properties": {
    "addr:full":"Avda Levante (de), 34 Jumilla Murcia 30520",
    "addr:housenumber":"34",
    "addr:postcode":"30520",
    "addr:street":"Avda Levante De",
    "iso:country":"ES",
    "sg:address":"Avda Levante (de), 34",
    "sg:city":"Jumilla",
    "sg:orig_category":"Inmobiliaria (agencias)",
    "sg:phone":"+34 968 78 29 79",
    "sg:postcode":"30520",
    "sg:province":"Murcia",
    "wof:name":"Rodenas Jimenez Encarnacion",
    "wof:placetype":"venue"
},
  "geometry": {"coordinates":[-1.3229089975,38.4744682312],"type":"Point"}
}