{
  "type": "Feature",
  "properties": {
    "iso:country":"ES",
    "sg:address":"Calle de Bastero, 4",
    "sg:city":"Madrid",
    "sg:orig_category":"Compraventa De Antig\u00dcedades",
    "sg:phone":"+34 913 54 60 03",
    "sg:postcode":"28005",
    "sg:province":"Madrid",
    "wof:name":"Gamella Martin Victor Manuel",
    "wof:placetype":"venue"
},
  "geometry": {"coordinates":[-3.7096714973,40.409072876],"type":"Point"}
}