{
  "type": "Feature",
  "properties": {
    "addr:full":"Calle de Cristobal Colon, 4 Santa Fe Granada 18320",
    "addr:housenumber":"4",
    "addr:postcode":"18320",
    "addr:street":"Calle De Cristobal Colon;Fe",
    "iso:country":"ES",
    "sg:address":"Calle de Cristobal Colon, 4",
    "sg:city":"Santa Fe",
    "sg:orig_category":"Promotores Constructores",
    "sg:phone":"+34 958 44 05 63",
    "sg:postcode":"18320",
    "sg:province":"Granada",
    "wof:name":"Segura Hernandez Jose Miguel",
    "wof:placetype":"venue"
},
  "geometry": {"coordinates":[-3.7184278965,37.1899795532],"type":"Point"}
}