{
  "type": "Feature",
  "properties": {
    "iso:country":"ES",
    "sg:address":"Calle de Elias Serra Rafols, 21",
    "sg:city":"San Cristobal De La Laguna",
    "sg:orig_category":"Abogados",
    "sg:phone":"+34 922 25 89 80",
    "sg:postcode":"38204",
    "sg:province":"Santa Cruz De Tenerife",
    "wof:name":"Valentin Mezquita Maria Fernanda",
    "wof:placetype":"venue"
},
  "geometry": {"coordinates":[-16.313993454,28.4822273254],"type":"Point"}
}