{
  "type": "Feature",
  "properties": {
    "addr:full":"Ctra Aguilas (de), Km. 0010,0 Casa De Las Monjas Murcia 30813",
    "addr:postcode":"30813",
    "addr:street":"Ctra Aguilas De Km. 0010,0 Casa De Las",
    "iso:country":"ES",
    "sg:address":"Ctra Aguilas (de), Km. 0010,0",
    "sg:city":"Casa De Las Monjas",
    "sg:orig_category":"Reposter\u00cdas",
    "sg:phone":"+34 968 48 25 67",
    "sg:postcode":"30813",
    "sg:province":"Murcia",
    "wof:name":"Pan Lorca S.l.l.",
    "wof:placetype":"venue"
},
  "geometry": {"coordinates":[-1.7215889692,37.491394043],"type":"Point"}
}