{
  "type": "Feature",
  "properties": {
    "addr:full":"Carr Caputxins, 60 Igualada Barcelona 08700",
    "addr:housenumber":"60",
    "addr:postcode":"08700",
    "addr:street":"Carr Caputxins",
    "iso:country":"ES",
    "sg:address":"Carr Caputxins, 60",
    "sg:city":"Igualada",
    "sg:orig_category":"Abogados",
    "sg:phone":"+34 938 03 72 05",
    "sg:postcode":"08700",
    "sg:province":"Barcelona",
    "wof:name":"Cano Franco Isabel",
    "wof:placetype":"venue"
},
  "geometry": {"coordinates":[1.6251239777,41.5805778503],"type":"Point"}
}