{
  "type": "Feature",
  "properties": {
    "iso:country":"ES",
    "sg:address":"Calle de Mercalli, 1",
    "sg:city":"Getafe",
    "sg:orig_category":"Centros Empresariales",
    "sg:phone":"+34 916 01 04 82",
    "sg:postcode":"28906",
    "sg:province":"Madrid",
    "wof:name":"Grupo Elite Multiservicios S.l.",
    "wof:placetype":"venue"
},
  "geometry": {"coordinates":[-3.7030980587,40.2986793518],"type":"Point"}
}