{
  "type": "Feature",
  "properties": {
    "addr:full":"Ctra General Del Norte, 30 Cantillo Santa Cruz De Tenerife 38350",
    "addr:housenumber":"30",
    "addr:postcode":"38350",
    "addr:street":"Ctra General Del Norte",
    "iso:country":"ES",
    "sg:address":"Ctra General Del Norte, 30",
    "sg:city":"Cantillo",
    "sg:orig_category":"Centros De Coordinaci\u00d3n",
    "sg:phone":"+34 922 56 35 18",
    "sg:postcode":"38350",
    "sg:province":"Santa Cruz De Tenerife",
    "wof:name":"Asesoria De Empresas Clavijo Rodriguez S.l.",
    "wof:placetype":"venue"
},
  "geometry": {"coordinates":[-16.3942432404,28.483669281],"type":"Point"}
}