{
  "type": "Feature",
  "properties": {
    "addr:full":"Rua Rosalia De Castro, 11 Carballo La Coru\u00f1a 15100",
    "addr:housenumber":"11",
    "addr:postcode":"15100",
    "addr:street":"Rua Rosalia De Castro;La Corun\u0303A",
    "iso:country":"ES",
    "sg:address":"Rua Rosalia De Castro, 11",
    "sg:city":"Carballo",
    "sg:orig_category":"Restaurantes",
    "sg:phone":"+34 981 75 45 83",
    "sg:postcode":"15100",
    "sg:province":"La Coru\u00f1a",
    "wof:name":"Rey Baldomir Clarisa",
    "wof:placetype":"venue"
},
  "geometry": {"coordinates":[-8.6876840591,43.2150497437],"type":"Point"}
}