{
  "type": "Feature",
  "properties": {
    "addr:full":"Calle de Navas Del Rey, 5 Madrid Madrid 28011",
    "addr:housenumber":"5",
    "addr:postcode":"28011",
    "addr:street":"Calle De Navas Del Rey",
    "iso:country":"ES",
    "sg:address":"Calle de Navas Del Rey, 5",
    "sg:city":"Madrid",
    "sg:orig_category":"Charcuter\u00cdas (al Por Mayor)",
    "sg:phone":"+34 914 64 24 77",
    "sg:postcode":"28011",
    "sg:province":"Madrid",
    "wof:name":"Alimentacion El Arenal S.a.",
    "wof:placetype":"venue"
},
  "geometry": {"coordinates":[-3.7378001213,40.4097595215],"type":"Point"}
}