{
  "type": "Feature",
  "properties": {
    "iso:country":"ES",
    "sg:address":"Calle de Marques De Pidal, 22",
    "sg:city":"Oviedo",
    "sg:orig_category":"Asociaciones Y Clubs Deportivos",
    "sg:phone":"+34 985 25 58 34",
    "sg:postcode":"33004",
    "sg:province":"Asturias",
    "wof:name":"Juan Manuel Iglesias Castro S.l",
    "wof:placetype":"venue"
},
  "geometry": {"coordinates":[-5.8538188934,43.3648910522],"type":"Point"}
}