{
  "type": "Feature",
  "properties": {
    "iso:country":"ES",
    "sg:address":"Calle de Gran Via, 33",
    "sg:city":"Majadahonda",
    "sg:orig_category":"Molduras, Junquillos, Listones Y Molduras Perforadas",
    "sg:phone":"+34 916 39 10 80",
    "sg:postcode":"28220",
    "sg:province":"Madrid",
    "wof:name":"Varga Lizana Valentin De La",
    "wof:placetype":"venue"
},
  "geometry": {"coordinates":[-3.8713328838,40.4706802368],"type":"Point"}
}