{
  "type": "Feature",
  "properties": {
    "addr:full":"Calle de Mahonesas, 1 San Antolin Murcia 30004",
    "addr:housenumber":"1",
    "addr:postcode":"30004",
    "addr:street":"Calle De Mahonesas;San Antolin",
    "iso:country":"ES",
    "sg:address":"Calle de Mahonesas, 1",
    "sg:city":"San Antolin",
    "sg:orig_category":"Sociedades, Compa\u00d1\u00cdas Aseguradoras",
    "sg:phone":"+34 968 29 93 49",
    "sg:postcode":"30004",
    "sg:province":"Murcia",
    "wof:name":"Doguimas S.l",
    "wof:placetype":"venue"
},
  "geometry": {"coordinates":[-1.1369279623,37.983379364],"type":"Point"}
}