{
  "type": "Feature",
  "properties": {
    "addr:full":"Calle de Vasco Nu\u00d1ez, 39 Badajoz Badajoz 06001",
    "addr:housenumber":"39",
    "addr:postcode":"06001",
    "addr:street":"Calle De Vasco Nun\u0303Ez",
    "iso:country":"ES",
    "sg:address":"Calle de Vasco Nu\u00d1ez, 39",
    "sg:city":"Badajoz",
    "sg:orig_category":"Arquitectos",
    "sg:phone":"+34 924 22 29 60",
    "sg:postcode":"06001",
    "sg:province":"Badajoz",
    "wof:name":"Cienfuegos Bueno Carmen",
    "wof:placetype":"venue"
},
  "geometry": {"coordinates":[-6.9755592346,38.8790283203],"type":"Point"}
}