{
  "type": "Feature",
  "properties": {
    "iso:country":"ES",
    "sg:address":"Vred Jaen, 24",
    "sg:city":"Albacete",
    "sg:orig_category":"Doctores En Medicina",
    "sg:phone":"+34 967 51 13 97",
    "sg:postcode":"02006",
    "sg:province":"Albacete",
    "wof:name":"Pretel Cano Juan Jose",
    "wof:placetype":"venue"
},
  "geometry": {"coordinates":[-2.044303894,39.0605888367],"type":"Point"}
}