{
  "type": "Feature",
  "properties": {
    "iso:country":"ES",
    "sg:address":"Calle de Isla Santa Elena, S/n",
    "sg:city":"Santiago Ribera",
    "sg:orig_category":"Institutos De Belleza",
    "sg:phone":"+34 968 17 91 85",
    "sg:postcode":"30720",
    "sg:province":"Murcia",
    "wof:name":"Larregui Del Rio Miren Izar",
    "wof:placetype":"venue"
},
  "geometry": {"coordinates":[-0.8069189787,37.8014183044],"type":"Point"}
}