{
  "type": "Feature",
  "properties": {
    "iso:country":"ES",
    "sg:address":"Calle de Ejido, 51",
    "sg:city":"Archidona",
    "sg:orig_category":"Peluquer\u00cdas, Peluquer\u00cda Mixta",
    "sg:phone":"+34 952 71 52 25",
    "sg:postcode":"29300",
    "sg:province":"M\u00e1laga",
    "wof:name":"Romero Aguilar Purificacion",
    "wof:placetype":"venue"
},
  "geometry": {"coordinates":[-4.3905777931,37.0935096741],"type":"Point"}
}