{
  "type": "Feature",
  "properties": {
    "addr:full":"Avda Portugal, 153 Salamanca Salamanca 37006",
    "addr:housenumber":"153",
    "addr:postcode":"37006",
    "addr:street":"Avda Portugal",
    "iso:country":"ES",
    "sg:address":"Avda Portugal, 153",
    "sg:city":"Salamanca",
    "sg:orig_category":"Inform\u00c1tica: Material Y Suministros",
    "sg:phone":"+34 923 25 91 48",
    "sg:postcode":"37006",
    "sg:province":"Salamanca",
    "wof:name":"Del Amo Diego Jose Alfonso",
    "wof:placetype":"venue"
},
  "geometry": {"coordinates":[-5.666738987,40.9727516174],"type":"Point"}
}