{
  "type": "Feature",
  "properties": {
    "addr:full":"Calle de Serrablo (de), 85 Sabi\u00f1anigo Huesca 22600",
    "addr:housenumber":"85",
    "addr:postcode":"22600",
    "addr:street":"Calle De Serrablo De",
    "iso:country":"ES",
    "sg:address":"Calle de Serrablo (de), 85",
    "sg:city":"Sabi\u00f1anigo",
    "sg:orig_category":"Transporte En General",
    "sg:phone":"+34 974 48 36 66",
    "sg:postcode":"22600",
    "sg:province":"Huesca",
    "wof:name":"Distribuidora Internacional De Alimentacion S.a.",
    "wof:placetype":"venue"
},
  "geometry": {"coordinates":[-0.3644169867,42.518409729],"type":"Point"}
}