{
  "type": "Feature",
  "properties": {
    "addr:full":"Carretera De Benalua De Guadix, S/n Guadix Granada 18500",
    "addr:housenumber":"s",
    "addr:postcode":"18500",
    "addr:street":"Carretera De Benalua;/ N",
    "iso:country":"ES",
    "sg:address":"Carretera De Benalua De Guadix, S/n",
    "sg:city":"Guadix",
    "sg:orig_category":"Transportes Por V\u00cdas Navegables",
    "sg:phone":"+34 958 66 21 40",
    "sg:postcode":"18500",
    "sg:province":"Granada",
    "wof:name":"Juan Francisco Aranda S.l.",
    "wof:placetype":"venue"
},
  "geometry": {"coordinates":[-3.1343688965,37.303894043],"type":"Point"}
}