{
  "type": "Feature",
  "properties": {
    "iso:country":"ES",
    "sg:address":"Cmno Hoyos (los), 1",
    "sg:city":"Santurtzi",
    "sg:orig_category":"Masajistas Kinesiterapeutas",
    "sg:phone":"+34 944 83 82 67",
    "sg:postcode":"48980",
    "sg:province":"Vizcaya",
    "wof:name":"Alfredo Parte Gutierrez",
    "wof:placetype":"venue"
},
  "geometry": {"coordinates":[-3.0349671841,43.3214378357],"type":"Point"}
}