{
  "type": "Feature",
  "properties": {
    "iso:country":"ES",
    "sg:address":"Calle de Calatrava, 20",
    "sg:city":"Ciudad Real",
    "sg:orig_category":"Abogados",
    "sg:phone":"+34 926 22 56 78",
    "sg:postcode":"13003",
    "sg:province":"Ciudad Real",
    "sg:website":"www.holgadoabogados.com",
    "wof:name":"Holgado Torquemada Felipe",
    "wof:placetype":"venue"
},
  "geometry": {"coordinates":[-3.9262712002,38.988193512],"type":"Point"}
}