{
  "type": "Feature",
  "properties": {
    "iso:country":"ES",
    "sg:address":"Ctra Canillas, 138",
    "sg:city":"Madrid",
    "sg:orig_category":"Agencias Y Asesores De Publicidad",
    "sg:phone":"+34 913 88 10 22",
    "sg:postcode":"28043",
    "sg:province":"Madrid",
    "wof:name":"Alonso Gonzalez Agustin",
    "wof:placetype":"venue"
},
  "geometry": {"coordinates":[-3.639788866,40.4653129578],"type":"Point"}
}