{
  "type": "Feature",
  "properties": {
    "iso:country":"ES",
    "sg:address":"Calle de Felix Lomas, 14",
    "sg:city":"Velez-malaga",
    "sg:orig_category":"Organizaciones Internacionales",
    "sg:phone":"+34 952 50 14 21",
    "sg:postcode":"29700",
    "sg:province":"M\u00e1laga",
    "wof:name":"Caritas Interparroquial",
    "wof:placetype":"venue"
},
  "geometry": {"coordinates":[-4.1047511101,36.7838783264],"type":"Point"}
}