{
  "type": "Feature",
  "properties": {
    "addr:full":"Calle de Real, 25 Roquetas Mar Almer\u00eda 04740",
    "addr:housenumber":"25",
    "addr:postcode":"04740",
    "addr:street":"Calle De Real",
    "iso:country":"ES",
    "sg:address":"Calle de Real, 25",
    "sg:city":"Roquetas Mar",
    "sg:orig_category":"Abogados",
    "sg:phone":"+34 950 32 39 34",
    "sg:postcode":"04740",
    "sg:province":"Almer\u00eda",
    "wof:name":"Linares Valverde Jose Andres",
    "wof:placetype":"venue"
},
  "geometry": {"coordinates":[-2.6144590378,36.76354599],"type":"Point"}
}