{
  "type": "Feature",
  "properties": {
    "iso:country":"ES",
    "sg:address":"Calle de Violeta Parra, 9",
    "sg:city":"Almansa",
    "sg:orig_category":"Producci\u00d3n, Distribuci\u00d3n De Gas Butano Y Propano",
    "sg:phone":"+34 967 31 18 79",
    "sg:postcode":"02640",
    "sg:province":"Albacete",
    "wof:name":"Promotora De Edificaciones De Albacete Y Alicante S.l.",
    "wof:placetype":"venue"
},
  "geometry": {"coordinates":[-1.0903990269,38.8702812195],"type":"Point"}
}