{
  "type": "Feature",
  "properties": {
    "iso:country":"ES",
    "sg:address":"Calle de Carretas (de), 17",
    "sg:city":"Aranjuez",
    "sg:orig_category":"Maquinaria Para Industrias Diversas",
    "sg:phone":"+34 918 92 14 85",
    "sg:postcode":"28300",
    "sg:province":"Madrid",
    "wof:name":"Excavaciones El Tajo S.l.",
    "wof:placetype":"venue"
},
  "geometry": {"coordinates":[-3.6021211147,40.027381897],"type":"Point"}
}