{
  "type": "Feature",
  "properties": {
    "iso:country":"ES",
    "sg:address":"Calle de Constantino, 35",
    "sg:city":"Ejido",
    "sg:orig_category":"Ropa Para Se\u00d1oras (al Por Menor)",
    "sg:phone":"+34 950 48 68 14",
    "sg:postcode":"04700",
    "sg:province":"Almer\u00eda",
    "wof:name":"Escoriza Gil Jose Antonio",
    "wof:placetype":"venue"
},
  "geometry": {"coordinates":[-2.8120698929,36.7751083374],"type":"Point"}
}