{
  "type": "Feature",
  "properties": {
    "addr:full":"Carrer de Galio, 8 Magaluf Islas Baleares 07181",
    "addr:housenumber":"8",
    "addr:postcode":"07181",
    "addr:street":"Carrer De Galio",
    "iso:country":"ES",
    "sg:address":"Carrer de Galio, 8",
    "sg:city":"Magaluf",
    "sg:orig_category":"Agencias De Viajes",
    "sg:phone":"+34 971 13 05 19",
    "sg:postcode":"07181",
    "sg:province":"Islas Baleares",
    "wof:name":"Viajes Sam S.l.",
    "wof:placetype":"venue"
},
  "geometry": {"coordinates":[2.5323619843,39.5102996826],"type":"Point"}
}