{
  "type": "Feature",
  "properties": {
    "addr:full":"Avda Utrera, 158 Palacios Y Villafranca Sevilla 41720",
    "addr:housenumber":"158",
    "addr:postcode":"41720",
    "addr:street":"Avda Utrera",
    "iso:country":"ES",
    "sg:address":"Avda Utrera, 158",
    "sg:city":"Palacios Y Villafranca",
    "sg:orig_category":"Molduras, Junquillos, Listones Y Molduras Perforadas",
    "sg:phone":"+34 955 81 18 92",
    "sg:postcode":"41720",
    "sg:province":"Sevilla",
    "wof:name":"Utrephone S.l.",
    "wof:placetype":"venue"
},
  "geometry": {"coordinates":[-5.9165668488,37.1614723206],"type":"Point"}
}