{
  "type": "Feature",
  "properties": {
    "addr:full":"Cmno Hormigueras, 120 Madrid Madrid 28031",
    "addr:housenumber":"120",
    "addr:postcode":"28031",
    "addr:street":"Cmno Hormigueras",
    "iso:country":"ES",
    "sg:address":"Cmno Hormigueras, 120",
    "sg:city":"Madrid",
    "sg:orig_category":"Confecci\u00d3n De Trajes Para Se\u00d1oras",
    "sg:phone":"+34 917 78 03 13",
    "sg:postcode":"28031",
    "sg:province":"Madrid",
    "wof:name":"Sedeta Modas S.l.",
    "wof:placetype":"venue"
},
  "geometry": {"coordinates":[-3.644562006,40.374168396],"type":"Point"}
}