{
  "type": "Feature",
  "properties": {
    "addr:full":"Calle de Azarbe Del Papel, 14 Vista Alegre Murcia 30007",
    "addr:housenumber":"14",
    "addr:postcode":"30007",
    "addr:street":"Calle De Azarbe Del Papel",
    "iso:country":"ES",
    "sg:address":"Calle de Azarbe Del Papel, 14",
    "sg:city":"Vista Alegre",
    "sg:classifiers":[
        {
            "category":"Banks & Credit Unions",
            "subcategory":"Bureau De Change",
            "type":"Services"
        }
    ],
    "sg:phone":"+34 968 23 00 79",
    "sg:postcode":"30007",
    "sg:province":"Murcia",
    "sg:tags":[
        "organismos",
        "control"
    ],
    "sg:website":"www.eurocotrol.es",
    "wof:name":"Eurocontrol S.a.",
    "wof:placetype":"venue"
},
  "geometry": {"coordinates":[-1.1298867464,37.9834747314],"type":"Point"}
}