{
  "type": "Feature",
  "properties": {
    "addr:full":"Ctra Pelegrin, 5 Jacarilla Alicante 03310",
    "addr:housenumber":"5",
    "addr:postcode":"03310",
    "addr:street":"Ctra Pelegrin",
    "iso:country":"ES",
    "sg:address":"Ctra Pelegrin, 5",
    "sg:city":"Jacarilla",
    "sg:orig_category":"Promotores Constructores",
    "sg:phone":"+34 965 35 02 98",
    "sg:postcode":"03310",
    "sg:province":"Alicante",
    "wof:name":"Viloru Construcciones S.l.",
    "wof:placetype":"venue"
},
  "geometry": {"coordinates":[-0.8681489825,38.0615539551],"type":"Point"}
}