{
  "type": "Feature",
  "properties": {
    "addr:full":"Calle de Tres Peces, 20 Madrid Madrid 28012",
    "addr:housenumber":"20",
    "addr:postcode":"madrid;28012",
    "addr:street":"Calle De Tres Peces",
    "iso:country":"ES",
    "sg:address":"Calle de Tres Peces, 20",
    "sg:city":"Madrid",
    "sg:orig_category":"Molduras, Junquillos, Listones Y Molduras Perforadas",
    "sg:phone":"+34 915 27 07 63",
    "sg:postcode":"28012",
    "sg:province":"Madrid",
    "wof:name":"Fernandez Anton Sergio",
    "wof:placetype":"venue"
},
  "geometry": {"coordinates":[-3.6996250153,40.4105873108],"type":"Point"}
}