{
  "type": "Feature",
  "properties": {
    "iso:country":"ES",
    "sg:address":"Calle de Pe\u00d1ascales, 42",
    "sg:city":"Madrid",
    "sg:orig_category":"Audiovisuales (producci\u00d3n, Edici\u00d3n, Realizaci\u00d3n)",
    "sg:phone":"+34 917 13 15 08",
    "sg:postcode":"28028",
    "sg:province":"Madrid",
    "wof:name":"Pop Producciones C.b.",
    "wof:placetype":"venue"
},
  "geometry": {"coordinates":[-3.6647040844,40.4236564636],"type":"Point"}
}