{
  "type": "Feature",
  "properties": {
    "addr:full":"Carrer de Sant Isidre, 13 Sabadell Barcelona 08208",
    "addr:housenumber":"13",
    "addr:postcode":"08208",
    "addr:street":"Carrer De Sant Isidre",
    "iso:country":"ES",
    "sg:address":"Carrer de Sant Isidre, 13",
    "sg:city":"Sabadell",
    "sg:orig_category":"Disfraces",
    "sg:phone":"+34 937 23 69 27",
    "sg:postcode":"08208",
    "sg:province":"Barcelona",
    "wof:name":"Vivo Rufas Teresa",
    "wof:placetype":"venue"
},
  "geometry": {"coordinates":[2.1018724442,41.5546035767],"type":"Point"}
}