{
  "type": "Feature",
  "properties": {
    "addr:full":"Carrer de Clot, 123 Barcelona Barcelona 08026",
    "addr:housenumber":"123",
    "addr:postcode":"08026",
    "addr:street":"Carrer De Clot",
    "iso:country":"ES",
    "sg:address":"Carrer de Clot, 123",
    "sg:city":"Barcelona",
    "sg:orig_category":"Inmobiliaria (agencias)",
    "sg:phone":"+34 932 65 48 49",
    "sg:postcode":"08026",
    "sg:province":"Barcelona",
    "sg:website":"www.expofinques.com",
    "wof:name":"Expofinques 2000 S. L.",
    "wof:placetype":"venue"
},
  "geometry": {"coordinates":[2.1892669201,41.4107894897],"type":"Point"}
}