{
  "type": "Feature",
  "properties": {
    "addr:full":"Ptge Lauria, 14 Torreta Barcelona 08430",
    "addr:housenumber":"14",
    "addr:postcode":"08430",
    "addr:street":"Ptge Lauria",
    "iso:country":"ES",
    "sg:address":"Ptge Lauria, 14",
    "sg:city":"Torreta",
    "sg:orig_category":"Chapister\u00cda",
    "sg:phone":"+34 938 70 42 45",
    "sg:postcode":"08430",
    "sg:province":"Barcelona",
    "wof:name":"Resina Martinez David",
    "wof:placetype":"venue"
},
  "geometry": {"coordinates":[2.2974319458,41.6017532349],"type":"Point"}
}