{
  "type": "Feature",
  "properties": {
    "iso:country":"ES",
    "sg:address":"Calle de Jacinta Garcia Hernandez, 6",
    "sg:city":"Badajoz",
    "sg:orig_category":"Centros P\u00dablicos De Formaci\u00d3n Profesional Y T\u00c9cnica",
    "sg:phone":"+34 924 22 43 49",
    "sg:postcode":"06011",
    "sg:province":"Badajoz",
    "wof:name":"Colegio Oficial De Gestores Administrativos De Extremadura",
    "wof:placetype":"venue"
},
  "geometry": {"coordinates":[-6.9826698303,38.8665924072],"type":"Point"}
}