{
  "type": "Feature",
  "properties": {
    "addr:full":"Plaz Mayor, 6 Quintanas Valdelucio Burgos 09127",
    "addr:housenumber":"6",
    "addr:postcode":"09127",
    "addr:street":"Plaz Mayor",
    "iso:country":"ES",
    "sg:address":"Plaz Mayor, 6",
    "sg:city":"Quintanas Valdelucio",
    "sg:orig_category":"Cajas Para Embalar",
    "sg:phone":"+34 947 36 36 15",
    "sg:postcode":"09127",
    "sg:province":"Burgos",
    "wof:name":"Caja Rural De Burgos",
    "wof:placetype":"venue"
},
  "geometry": {"coordinates":[-4.087269783,42.7227592468],"type":"Point"}
}