{
  "type": "Feature",
  "properties": {
    "addr:full":"Trva Eras De San Cristobal, 35 Fuenmayor La Rioja 26360",
    "addr:housenumber":"35",
    "addr:postcode":"26360",
    "addr:street":"Trva Eras De San Cristobal;Rioja",
    "iso:country":"ES",
    "sg:address":"Trva Eras De San Cristobal, 35",
    "sg:city":"Fuenmayor",
    "sg:orig_category":"Cajas Y Embalajes De Cart\u00d3n Y Papel",
    "sg:phone":"+34 941 45 01 35",
    "sg:postcode":"26360",
    "sg:province":"La Rioja",
    "wof:name":"Envases Riojanos S.l.",
    "wof:placetype":"venue"
},
  "geometry": {"coordinates":[-2.5637969971,42.4670257568],"type":"Point"}
}