{
  "type": "Feature",
  "properties": {
    "iso:country":"ES",
    "sg:address":"Calle de Cristobal Colon, 28",
    "sg:city":"Utrera",
    "sg:orig_category":"Ense\u00d1anza: Profesiones Art\u00cdsticas",
    "sg:phone":"+34 955 86 31 86",
    "sg:postcode":"41710",
    "sg:province":"Sevilla",
    "wof:name":"Foto Goca S.l.",
    "wof:placetype":"venue"
},
  "geometry": {"coordinates":[-5.7762951851,37.1841468811],"type":"Point"}
}