{
  "type": "Feature",
  "properties": {
    "iso:country":"ES",
    "sg:address":"Carr Esport, 16",
    "sg:city":"Girona",
    "sg:orig_category":"Asociaciones Y Clubs Deportivos",
    "sg:phone":"+34 972 20 10 47",
    "sg:postcode":"17007",
    "sg:province":"Girona",
    "wof:name":"Grup Excursionista I Esportiu Gironi",
    "wof:placetype":"venue"
},
  "geometry": {"coordinates":[2.8035190105,41.9965400696],"type":"Point"}
}