{
  "type": "Feature",
  "properties": {
    "addr:full":"Avda Torrejon De Ardoz (de), 3 Paracuellos De Jarama Madrid 28860",
    "addr:postcode":"28860",
    "addr:street":"Avda Torrejon",
    "iso:country":"ES",
    "sg:address":"Avda Torrejon De Ardoz (de), 3",
    "sg:city":"Paracuellos De Jarama",
    "sg:orig_category":"Carnicer\u00cdas, Carnicer\u00cdas",
    "sg:phone":"+34 916 58 16 22",
    "sg:postcode":"28860",
    "sg:province":"Madrid",
    "wof:name":"Comercial Thedysa S.a.",
    "wof:placetype":"venue"
},
  "geometry": {"coordinates":[-3.5291140079,40.5048675537],"type":"Point"}
}