{
  "type": "Feature",
  "properties": {
    "addr:full":"Barr Sandamendi, 31 Sandamendi Vizcaya 48192",
    "addr:housenumber":"31",
    "addr:postcode":"48192",
    "addr:street":"Sandamendi",
    "iso:country":"ES",
    "sg:address":"Barr Sandamendi, 31",
    "sg:city":"Sandamendi",
    "sg:orig_category":"M\u00c9dicos: Ginecolog\u00cda Y Obstetricia",
    "sg:phone":"+34 946 79 80 22",
    "sg:postcode":"48192",
    "sg:province":"Vizcaya",
    "wof:name":"Guimon Ugartechea Jesus Miguel",
    "wof:placetype":"venue"
},
  "geometry": {"coordinates":[-3.0710809231,43.1801567078],"type":"Point"}
}