{
  "type": "Feature",
  "properties": {
    "iso:country":"ES",
    "sg:address":"Avda Europa, 9",
    "sg:city":"Benidorm",
    "sg:orig_category":"Art\u00cdculos De Regalo (al Por Menor)",
    "sg:phone":"+34 965 86 01 40",
    "sg:postcode":"03500",
    "sg:province":"Alicante",
    "wof:name":"Benito Lozano Basilio",
    "wof:placetype":"venue"
},
  "geometry": {"coordinates":[-0.1200449988,38.5382423401],"type":"Point"}
}