{
  "type": "Feature",
  "properties": {
    "addr:full":"Carrer de Parellades, 18 Sitges Barcelona 08870",
    "addr:housenumber":"18",
    "addr:postcode":"08870",
    "addr:street":"Carrer De Parellades",
    "iso:country":"ES",
    "sg:address":"Carrer de Parellades, 18",
    "sg:city":"Sitges",
    "sg:orig_category":"Ropa Para Se\u00d1oras Y Caballeros (al Por Menor)",
    "sg:phone":"+34 938 94 10 64",
    "sg:postcode":"08870",
    "sg:province":"Barcelona",
    "wof:name":"Papia Scp",
    "wof:placetype":"venue"
},
  "geometry": {"coordinates":[1.8088289499,41.236541748],"type":"Point"}
}