{
  "type": "Feature",
  "properties": {
    "addr:full":"Calle de Juan De Lara, 11 Melilla Melilla 52005",
    "addr:housenumber":"11",
    "addr:postcode":"52005",
    "addr:street":"Calle De Juan De Lara",
    "iso:country":"ES",
    "sg:address":"Calle de Juan De Lara, 11",
    "sg:city":"Melilla",
    "sg:orig_category":"Instalaci\u00d3n, Reparaci\u00d3n De Ascensores Y Montacargas",
    "sg:phone":"+34 952 69 11 82",
    "sg:postcode":"52005",
    "sg:province":"Melilla",
    "wof:name":"A Embarba S. A.",
    "wof:placetype":"venue"
},
  "geometry": {"coordinates":[-2.9478001595,35.2887039185],"type":"Point"}
}