{
  "type": "Feature",
  "properties": {
    "addr:full":"Calle de Jacinto Benavente, 3 Pozoblanco C\u00f3rdoba 14400",
    "addr:housenumber":"3",
    "addr:postcode":"14400",
    "addr:street":"Calle De Jacinto Benavente",
    "iso:country":"ES",
    "sg:address":"Calle de Jacinto Benavente, 3",
    "sg:city":"Pozoblanco",
    "sg:orig_category":"Aguas (distribuci\u00d3n, Servicios)",
    "sg:phone":"+34 957 13 09 20",
    "sg:postcode":"14400",
    "sg:province":"C\u00f3rdoba",
    "wof:name":"Aqualia Gestion Integral Del Agua S.a.",
    "wof:placetype":"venue"
},
  "geometry": {"coordinates":[-4.8475131989,38.3785209656],"type":"Point"}
}