{
  "type": "Feature",
  "properties": {
    "iso:country":"ES",
    "sg:address":"Calle de San Sebastian, 12",
    "sg:city":"Huelva",
    "sg:orig_category":"Deportes Y Ocio: Art\u00cdculos Y Ropas (al Por Menor Y Accesorios)",
    "sg:phone":"+34 959 54 06 95",
    "sg:postcode":"21004",
    "sg:province":"Huelva",
    "wof:name":"Deporte Move S.l.",
    "wof:placetype":"venue"
},
  "geometry": {"coordinates":[-6.9467082024,37.2605552673],"type":"Point"}
}