{
  "type": "Feature",
  "properties": {
    "addr:full":"Calle de Guante, 2 Leganes Madrid 28912",
    "addr:housenumber":"2",
    "addr:postcode":"28912",
    "addr:street":"Calle De Guante",
    "iso:country":"ES",
    "sg:address":"Calle de Guante, 2",
    "sg:city":"Leganes",
    "sg:orig_category":"Sindicatos Y Colegios Profesionales",
    "sg:phone":"+34 916 94 81 89",
    "sg:postcode":"28912",
    "sg:province":"Madrid",
    "wof:name":"Asociacion Espacio Europa Joven",
    "wof:placetype":"venue"
},
  "geometry": {"coordinates":[-3.7643537521,40.3262939453],"type":"Point"}
}