{
  "type": "Feature",
  "properties": {
    "addr:full":"Calle de Molinillos, 16 Alcaudete Ja\u00e9n 23660",
    "addr:housenumber":"16",
    "addr:postcode":"23660",
    "addr:street":"Calle De Molinillos;Jae\u0301N",
    "iso:country":"ES",
    "sg:address":"Calle de Molinillos, 16",
    "sg:city":"Alcaudete",
    "sg:orig_category":"Empresas De Carpinter\u00cda De Madera",
    "sg:phone":"+34 953 56 02 21",
    "sg:postcode":"23660",
    "sg:province":"Ja\u00e9n",
    "wof:name":"Gutierrez Vazquez Juan",
    "wof:placetype":"venue"
},
  "geometry": {"coordinates":[-4.0932149887,37.5910644531],"type":"Point"}
}