{
  "type": "Feature",
  "properties": {
    "addr:full":"Avda Manuel Rivera, 14 Palencia Palencia 34002",
    "addr:housenumber":"14",
    "addr:postcode":"34002",
    "addr:street":"Avda Manuel Rivera",
    "iso:country":"ES",
    "sg:address":"Avda Manuel Rivera, 14",
    "sg:city":"Palencia",
    "sg:orig_category":"Oficinas: Suministros Para (fabricaci\u00d3n, Al Por Mayor)",
    "sg:phone":"+34 979 71 13 23",
    "sg:postcode":"34002",
    "sg:province":"Palencia",
    "wof:name":"Carlibur S.l.",
    "wof:placetype":"venue"
},
  "geometry": {"coordinates":[-4.5272607803,42.0082702637],"type":"Point"}
}