{
  "type": "Feature",
  "properties": {
    "iso:country":"ES",
    "sg:address":"Rua Lopez Guntin (pintor), 9",
    "sg:city":"Lugo",
    "sg:orig_category":"Mec\u00c1nico Del Autom\u00d3vil",
    "sg:phone":"+34 982 21 19 26",
    "sg:postcode":"27004",
    "sg:province":"Lugo",
    "wof:name":"Automecanica Santos Roca C.b.",
    "wof:placetype":"venue"
},
  "geometry": {"coordinates":[-7.5675740242,43.0166015625],"type":"Point"}
}