{
  "type": "Feature",
  "properties": {
    "addr:full":"Carrer de Cristofor Llargues, 18 Cornella Llobregat Barcelona 08940",
    "addr:housenumber":"18",
    "addr:postcode":"08940",
    "addr:street":"Carrer De Cristofor Llargues",
    "iso:country":"ES",
    "sg:address":"Carrer de Cristofor Llargues, 18",
    "sg:city":"Cornella Llobregat",
    "sg:orig_category":"Internados & Ense\u00d1anza Privada",
    "sg:phone":"+34 933 76 09 49",
    "sg:postcode":"08940",
    "sg:province":"Barcelona",
    "wof:name":"Institucion Escolar Ameh S.l.",
    "wof:placetype":"venue"
},
  "geometry": {"coordinates":[2.0708940029,41.3559417725],"type":"Point"}
}