{
  "type": "Feature",
  "properties": {
    "iso:country":"ES",
    "sg:address":"Calle de Calixto Iii, 9",
    "sg:city":"Valencia",
    "sg:orig_category":"Abogados",
    "sg:phone":"+34 963 82 00 48",
    "sg:postcode":"46008",
    "sg:province":"Valencia",
    "wof:name":"Alca\u00f1iz Rodriguez Jose Antonio",
    "wof:placetype":"venue"
},
  "geometry": {"coordinates":[-0.3874672055,39.4719047546],"type":"Point"}
}