{
  "type": "Feature",
  "properties": {
    "iso:country":"ES",
    "sg:address":"Calle de Virgen, 3",
    "sg:city":"Tarazona Mancha",
    "sg:orig_category":"Carnicer\u00cdas, Carnicer\u00cdas",
    "sg:phone":"+34 967 48 07 29",
    "sg:postcode":"02100",
    "sg:province":"Albacete",
    "wof:name":"Vinos Hermanos Denia S.l.",
    "wof:placetype":"venue"
},
  "geometry": {"coordinates":[-1.9121739864,39.2645683289],"type":"Point"}
}