{
  "type": "Feature",
  "properties": {
    "addr:full":"Psaj Conde Alcala, 4 Granada Granada 18001",
    "addr:housenumber":"4",
    "addr:postcode":"18001",
    "addr:street":"Conde Alcala",
    "iso:country":"ES",
    "sg:address":"Psaj Conde Alcala, 4",
    "sg:city":"Granada",
    "sg:orig_category":"Zapatos (al Por Menor)",
    "sg:phone":"+34 958 52 32 08",
    "sg:postcode":"18001",
    "sg:province":"Granada",
    "wof:name":"Anchos Especiales Comfort S.l.",
    "wof:placetype":"venue"
},
  "geometry": {"coordinates":[-3.6011834145,37.175037384],"type":"Point"}
}