{
  "type": "Feature",
  "properties": {
    "iso:country":"ES",
    "sg:address":"Plaz Marques De Salamanca, 4",
    "sg:city":"Marbella",
    "sg:orig_category":"Bisuter\u00cda, Joyer\u00cda, Relojer\u00cda (al Por Menor)",
    "sg:phone":"+34 952 82 47 31",
    "sg:postcode":"29600",
    "sg:province":"M\u00e1laga",
    "wof:name":"Orocaja Espa\u00f1ol S.l.",
    "wof:placetype":"venue"
},
  "geometry": {"coordinates":[-4.8833007812,36.5079956055],"type":"Point"}
}