{
  "type": "Feature",
  "properties": {
    "addr:full":"Avda Deportes (de Los), S/n Mostoles Madrid 28935",
    "addr:postcode":"28935",
    "addr:street":"Avda Deportes De Los S / N Mostoles",
    "iso:country":"ES",
    "sg:address":"Avda Deportes (de Los), S/n",
    "sg:city":"Mostoles",
    "sg:orig_category":"Asociaciones Y Clubs Deportivos",
    "sg:phone":"+34 916 13 76 13",
    "sg:postcode":"28935",
    "sg:province":"Madrid",
    "wof:name":"Club Deportivo Mostoles",
    "wof:placetype":"venue"
},
  "geometry": {"coordinates":[-3.8762030602,40.3250961304],"type":"Point"}
}