{
  "type": "Feature",
  "properties": {
    "iso:country":"ES",
    "sg:address":"Carrer de Riu Siurana, 33",
    "sg:city":"Campclar",
    "sg:orig_category":"Papeler\u00cdas, Librer\u00cdas",
    "sg:phone":"+34 977 54 46 73",
    "sg:postcode":"43006",
    "sg:province":"Tarragona",
    "wof:name":"Diaz Sanchez Rios Antonio",
    "wof:placetype":"venue"
},
  "geometry": {"coordinates":[1.2209249735,41.1154441833],"type":"Point"}
}