{
  "type": "Feature",
  "properties": {
    "iso:country":"ES",
    "sg:address":"Calle de Dolores Montalbo, 23",
    "sg:city":"Lora Rio",
    "sg:orig_category":"\u00d3ptica: Instrumentos (fabricaci\u00d3n)",
    "sg:phone":"+34 955 80 20 00",
    "sg:postcode":"41440",
    "sg:province":"Sevilla",
    "wof:name":"Jimenez Del Valle Rafaela",
    "wof:placetype":"venue"
},
  "geometry": {"coordinates":[-5.530339241,37.6555862427],"type":"Point"}
}