{
  "type": "Feature",
  "properties": {
    "iso:country":"ES",
    "sg:address":"Carr Disabte, 7",
    "sg:city":"Aldaia",
    "sg:orig_category":"Ingenieros Asesor\u00cda",
    "sg:phone":"+34 961 98 60 65",
    "sg:postcode":"46960",
    "sg:province":"Valencia",
    "wof:name":"Ayuntamiento De Aldaia",
    "wof:placetype":"venue"
},
  "geometry": {"coordinates":[-0.4581829906,39.4637298584],"type":"Point"}
}