{
  "type": "Feature",
  "properties": {
    "addr:full":"Av Portal De L'angel, 19 Barcelona Barcelona 08002",
    "addr:housenumber":"19",
    "addr:postcode":"08002",
    "addr:street":"Av Portal De L'Angel",
    "iso:country":"ES",
    "sg:address":"Av Portal De L'angel, 19",
    "sg:city":"Barcelona",
    "sg:orig_category":"\u00d3ptica: Instrumentos (fabricaci\u00d3n)",
    "sg:phone":"+34 933 02 12 47",
    "sg:postcode":"08002",
    "sg:province":"Barcelona",
    "sg:website":"www.optica2000.com",
    "wof:name":"Optica 2000 S. L.",
    "wof:placetype":"venue"
},
  "geometry": {"coordinates":[2.1726868153,41.3858718872],"type":"Point"}
}