{
  "type": "Feature",
  "properties": {
    "addr:full":"Marte(pol Ind Estrella), 1 Molina Segura Murcia 30500",
    "addr:housenumber":"1",
    "addr:postcode":"30500",
    "addr:street":"Marte Pol;Estrella",
    "iso:country":"ES",
    "sg:address":"Marte(pol Ind Estrella), 1",
    "sg:city":"Molina Segura",
    "sg:orig_category":"Alumbrados",
    "sg:phone":"+34 968 80 12 11",
    "sg:postcode":"30500",
    "sg:province":"Murcia",
    "wof:name":"Secom Iluminacion S.l.",
    "wof:placetype":"venue"
},
  "geometry": {"coordinates":[-1.2119740248,38.0535736084],"type":"Point"}
}