{
  "type": "Feature",
  "properties": {
    "iso:country":"ES",
    "sg:address":"Calle de Vega, 23",
    "sg:city":"Valladolid",
    "sg:orig_category":"Bares, Piano",
    "sg:phone":"+34 983 20 51 50",
    "sg:postcode":"47004",
    "sg:province":"Valladolid",
    "wof:name":"Herrero Torices Mariano",
    "wof:placetype":"venue"
},
  "geometry": {"coordinates":[-4.7227921486,41.6481628418],"type":"Point"}
}