{
  "type": "Feature",
  "properties": {
    "iso:country":"ES",
    "sg:address":"Calle de San Andres, 12",
    "sg:city":"Zaragoza",
    "sg:orig_category":"Asilos De Ancianos. Centros Privados",
    "sg:phone":"+34 976 39 48 92",
    "sg:postcode":"50001",
    "sg:province":"Zaragoza",
    "wof:name":"Asociacion De Jubilados Y Pensionistas De La Caja De Ahorros De Zaragoza Aragon Y Rioja",
    "wof:placetype":"venue"
},
  "geometry": {"coordinates":[-0.8783637285,41.6526603699],"type":"Point"}
}