{
  "type": "Feature",
  "properties": {
    "iso:country":"ES",
    "sg:address":"Avda Gaiarre Julian, 16",
    "sg:city":"Bilbao",
    "sg:orig_category":"Importaci\u00d3n",
    "sg:phone":"+34 944 73 33 80",
    "sg:postcode":"48004",
    "sg:province":"Vizcaya",
    "wof:name":"Comercio Internacional Cominter S.l.",
    "wof:placetype":"venue"
},
  "geometry": {"coordinates":[-2.9026141167,43.2525787354],"type":"Point"}
}