{
  "type": "Feature",
  "properties": {
    "iso:country":"ES",
    "sg:address":"Avda. Pamplona, 11",
    "sg:city":"Iru\u00f1a",
    "sg:orig_category":"Asociaciones Y Clubs Deportivos",
    "sg:phone":"+34 948 18 09 02",
    "sg:postcode":"31009",
    "sg:province":"Navarra",
    "wof:name":"Arenzana Prat Arancha",
    "wof:placetype":"venue"
},
  "geometry": {"coordinates":[-1.6748559475,42.8044815063],"type":"Point"}
}