{
  "type": "Feature",
  "properties": {
    "iso:country":"ES",
    "sg:address":"Sanguesa, 51",
    "sg:city":"Iru\u00f1a",
    "sg:orig_category":"Agencias Y Agentes Comerciales, Representantes",
    "sg:phone":"+34 948 24 67 23",
    "sg:postcode":"31005",
    "sg:province":"Navarra",
    "wof:name":"Navarfon S.l.",
    "wof:placetype":"venue"
},
  "geometry": {"coordinates":[-1.6439889669,42.806438446],"type":"Point"}
}