{
  "type": "Feature",
  "properties": {
    "iso:country":"ES",
    "sg:address":"Carr Sant Francesc, 32",
    "sg:city":"Breda",
    "sg:orig_category":"Venta, Instalaci\u00d3n De Calefacci\u00d3n",
    "sg:phone":"+34 972 87 00 74",
    "sg:postcode":"17400",
    "sg:province":"Girona",
    "wof:name":"Cuni Avellaneda Ramon",
    "wof:placetype":"venue"
},
  "geometry": {"coordinates":[2.5611178875,41.7450637817],"type":"Point"}
}