{
  "type": "Feature",
  "properties": {
    "addr:full":"Carr Sant Josep, 70 Picassent Valencia 46220",
    "addr:housenumber":"70",
    "addr:postcode":"46220",
    "addr:street":"Carr Sant Josep",
    "iso:country":"ES",
    "sg:address":"Carr Sant Josep, 70",
    "sg:city":"Picassent",
    "sg:orig_category":"Peluquer\u00cdas, Peluquer\u00cda Mixta",
    "sg:phone":"+34 961 24 15 50",
    "sg:postcode":"46220",
    "sg:province":"Valencia",
    "wof:name":"Perez Torregrosa Daniel",
    "wof:placetype":"venue"
},
  "geometry": {"coordinates":[-0.4592239857,39.3650970459],"type":"Point"}
}