{
  "type": "Feature",
  "properties": {
    "addr:full":"Rda. Andalucia, 20 Dosbarrios Toledo 45311",
    "addr:housenumber":"20",
    "addr:postcode":"45311",
    "addr:street":"Andalucia",
    "iso:country":"ES",
    "sg:address":"Rda. Andalucia, 20",
    "sg:city":"Dosbarrios",
    "sg:orig_category":"Material Y Herramientas Agr\u00cdcolas",
    "sg:phone":"+34 925 13 72 99",
    "sg:postcode":"45311",
    "sg:province":"Toledo",
    "wof:name":"Pe\u00f1a Lopez-tola Jesus Onofre De La",
    "wof:placetype":"venue"
},
  "geometry": {"coordinates":[-3.4884970188,39.8820419312],"type":"Point"}
}