{
  "type": "Feature",
  "properties": {
    "addr:full":"Calle de Alejandro Ferrant, 9 Madrid Madrid 28045",
    "addr:housenumber":"9",
    "addr:postcode":"madrid;28045",
    "addr:street":"Calle De Alejandro Ferrant",
    "iso:country":"ES",
    "sg:address":"Calle de Alejandro Ferrant, 9",
    "sg:city":"Madrid",
    "sg:orig_category":"Contenedores (mercanc\u00cdas)",
    "sg:phone":"+34 914 67 22 13",
    "sg:postcode":"28045",
    "sg:province":"Madrid",
    "wof:name":"Gonzalez Crespo Julia",
    "wof:placetype":"venue"
},
  "geometry": {"coordinates":[-3.6932756901,40.3950233459],"type":"Point"}
}