{
  "type": "Feature",
  "properties": {
    "addr:full":"Calle de Fernandez Ladreda, 9 Oviedo Asturias 33011",
    "addr:housenumber":"9",
    "addr:postcode":"33011",
    "addr:street":"Calle De;Ladreda",
    "iso:country":"ES",
    "sg:address":"Calle de Fernandez Ladreda, 9",
    "sg:city":"Oviedo",
    "sg:orig_category":"Farmacias",
    "sg:phone":"+34 985 28 45 99",
    "sg:postcode":"33011",
    "sg:province":"Asturias",
    "wof:name":"Garcia-monje Gontan Maria Gemma",
    "wof:placetype":"venue"
},
  "geometry": {"coordinates":[-5.8366160393,43.3708152771],"type":"Point"}
}