{
  "type": "Feature",
  "properties": {
    "addr:full":"Avda Tirajana (de), 3 Playa Del Ingles Las Palmas 35100",
    "addr:housenumber":"3",
    "addr:postcode":"35100",
    "addr:street":"Avda Tirajana De",
    "iso:country":"ES",
    "sg:address":"Avda Tirajana (de), 3",
    "sg:city":"Playa Del Ingles",
    "sg:orig_category":"Alquiler De Veh\u00cdculos: Turismos Y Utilitarios",
    "sg:phone":"+34 928 76 54 12",
    "sg:postcode":"35100",
    "sg:province":"Las Palmas",
    "wof:name":"Fangomara S.l.",
    "wof:placetype":"venue"
},
  "geometry": {"coordinates":[-15.5772924423,27.7519817352],"type":"Point"}
}