{
  "type": "Feature",
  "properties": {
    "addr:full":"Plaz Teniente Carrasco, 6 Santos De Maimona Badajoz 06230",
    "addr:housenumber":"6",
    "addr:postcode":"06230",
    "addr:street":"Plaz Teniente Carrasco",
    "iso:country":"ES",
    "sg:address":"Plaz Teniente Carrasco, 6",
    "sg:city":"Santos De Maimona",
    "sg:orig_category":"Iglesia Cat\u00d3lica",
    "sg:phone":"+34 924 54 40 35",
    "sg:postcode":"06230",
    "sg:province":"Badajoz",
    "wof:name":"Parroquia Nuestra Se\u00f1ora De Los Angeles",
    "wof:placetype":"venue"
},
  "geometry": {"coordinates":[-6.3725099564,38.4434814453],"type":"Point"}
}