{
  "type": "Feature",
  "properties": {
    "addr:full":"Calle de Londres, 17 Caceres C\u00e1ceres 10005",
    "addr:housenumber":"17",
    "addr:postcode":"10005",
    "addr:street":"Calle De Londres;Ca\u0301Ceres",
    "iso:country":"ES",
    "sg:address":"Calle de Londres, 17",
    "sg:city":"Caceres",
    "sg:orig_category":"Pintura Y Barniz (al Por Menor)",
    "sg:phone":"+34 927 23 87 06",
    "sg:postcode":"10005",
    "sg:province":"C\u00e1ceres",
    "sg:website":"www.jmsi.org",
    "wof:name":"Pintesa Color S.l.",
    "wof:placetype":"venue"
},
  "geometry": {"coordinates":[-6.3887991905,39.4685592651],"type":"Point"}
}