{
  "type": "Feature",
  "properties": {
    "addr:full":"Pase Fernando El Catolico, 48 Zaragoza Zaragoza 50009",
    "addr:housenumber":"48",
    "addr:postcode":"50009",
    "addr:street":"Fernando El Catolico",
    "iso:country":"ES",
    "sg:address":"Pase Fernando El Catolico, 48",
    "sg:city":"Zaragoza",
    "sg:orig_category":"Herboristas (al Por Menor)",
    "sg:phone":"+34 976 55 98 40",
    "sg:postcode":"50009",
    "sg:province":"Zaragoza",
    "wof:name":"Herederos De Jose Sanchez Uson C.b.",
    "wof:placetype":"venue"
},
  "geometry": {"coordinates":[-0.8964130282,41.639755249],"type":"Point"}
}