{
  "type": "Feature",
  "properties": {
    "addr:full":"C/ Canal, 40 Banyoles Girona 17820",
    "addr:housenumber":"40",
    "addr:postcode":"17820",
    "addr:street":"C / Canal",
    "iso:country":"ES",
    "sg:address":"C/ Canal, 40",
    "sg:city":"Banyoles",
    "sg:orig_category":"Arquitectos",
    "sg:phone":"+34 972 57 04 92",
    "sg:postcode":"17820",
    "sg:province":"Girona",
    "wof:name":"Figueras Masgrau Jose Maria",
    "wof:placetype":"venue"
},
  "geometry": {"coordinates":[2.7650909424,42.1187400818],"type":"Point"}
}