{
  "type": "Feature",
  "properties": {
    "iso:country":"ES",
    "sg:address":"Cmno Torres (las), 15",
    "sg:city":"Zaragoza",
    "sg:orig_category":"M\u00c9dicos: Ginecolog\u00cda Y Obstetricia",
    "sg:phone":"+34 976 59 55 81",
    "sg:postcode":"50008",
    "sg:province":"Zaragoza",
    "wof:name":"Numancia Andreu Pilar Bego\u00f1a",
    "wof:placetype":"venue"
},
  "geometry": {"coordinates":[-0.8748080134,41.6460609436],"type":"Point"}
}