{
  "type": "Feature",
  "properties": {
    "iso:country":"ES",
    "sg:address":"Calle de Bajo Concejo, 4",
    "sg:city":"Villel",
    "sg:orig_category":"Carnicer\u00cdas, Carnicer\u00cdas",
    "sg:phone":"+34 978 68 00 51",
    "sg:postcode":"44131",
    "sg:province":"Teruel",
    "wof:name":"Domingo Martinez Jose",
    "wof:placetype":"venue"
},
  "geometry": {"coordinates":[-1.1867603064,40.2342529297],"type":"Point"}
}