{
  "type": "Feature",
  "properties": {
    "addr:full":"Calle de Ronda De La Manca, 2 Cordoba C\u00f3rdoba 14010",
    "addr:housenumber":"2",
    "addr:postcode":"14010",
    "addr:street":"Calle De Ronda De La Manca;Co\u0301Rdoba",
    "iso:country":"ES",
    "sg:address":"Calle de Ronda De La Manca, 2",
    "sg:city":"Cordoba",
    "sg:orig_category":"Caf\u00c9s, Bares, Cervecer\u00cdas",
    "sg:phone":"+34 957 25 80 76",
    "sg:postcode":"14010",
    "sg:province":"C\u00f3rdoba",
    "wof:name":"Cafe Bar Don Rafael S.l.",
    "wof:placetype":"venue"
},
  "geometry": {"coordinates":[-4.7649040222,37.8866081238],"type":"Point"}
}