{
  "type": "Feature",
  "properties": {
    "addr:full":"Av Pompeu Fabra, 2 Barcelona Barcelona 08024",
    "addr:housenumber":"2",
    "addr:postcode":"08024",
    "addr:street":"Av Pompeu Fabra",
    "iso:country":"ES",
    "sg:address":"Av Pompeu Fabra, 2",
    "sg:city":"Barcelona",
    "sg:orig_category":"Periodistas Profesionales",
    "sg:phone":"+34 932 10 59 52",
    "sg:postcode":"08024",
    "sg:province":"Barcelona",
    "wof:name":"Lopez Rosell Cesar",
    "wof:placetype":"venue"
},
  "geometry": {"coordinates":[2.1587018967,41.4145202637],"type":"Point"}
}