{
  "type": "Feature",
  "properties": {
    "iso:country":"ES",
    "sg:address":"Pol Ind La Barrena, Km. 0096,0",
    "sg:city":"Tudela",
    "sg:orig_category":"Veh\u00cdculos De Ocasi\u00d3n",
    "sg:phone":"+34 948 41 00 71",
    "sg:postcode":"31500",
    "sg:province":"Navarra",
    "wof:name":"Aguado Artieta Sergio Y Jimenez Ortega Miguel Angel",
    "wof:placetype":"venue"
},
  "geometry": {"coordinates":[-1.4821481705,42.1872329712],"type":"Point"}
}