{
  "type": "Feature",
  "properties": {
    "addr:full":"Calle de Antonio Machado, 26 Do\u00e7a Mencia C\u00f3rdoba 14860",
    "addr:housenumber":"26",
    "addr:postcode":"14860",
    "addr:street":"Calle De Antonio Machado;Co\u0301Rdoba",
    "iso:country":"ES",
    "sg:address":"Calle de Antonio Machado, 26",
    "sg:city":"Do\u00e7a Mencia",
    "sg:orig_category":"Panader\u00cdas, Panader\u00cdas",
    "sg:phone":"+34 957 67 62 28",
    "sg:postcode":"14860",
    "sg:province":"C\u00f3rdoba",
    "wof:name":"Urbano Gomez Manuel",
    "wof:placetype":"venue"
},
  "geometry": {"coordinates":[-4.3577737808,37.5546150208],"type":"Point"}
}