{
  "type": "Feature",
  "properties": {
    "iso:country":"ES",
    "sg:address":"Calle de Sagasta, 22",
    "sg:city":"Palmas De Gran Canaria",
    "sg:orig_category":"Ropa Para Se\u00d1oras (al Por Menor)",
    "sg:phone":"+34 928 22 46 83",
    "sg:postcode":"35008",
    "sg:province":"Las Palmas",
    "wof:name":"Lalchand Daryanani Raju",
    "wof:placetype":"venue"
},
  "geometry": {"coordinates":[-15.4312181473,28.143661499],"type":"Point"}
}