{
  "type": "Feature",
  "properties": {
    "iso:country":"ES",
    "sg:address":"Ctra Barcelona, 7",
    "sg:city":"Vendrell",
    "sg:orig_category":"Mec\u00c1nico Del Autom\u00d3vil",
    "sg:phone":"+34 977 66 11 01",
    "sg:postcode":"43700",
    "sg:province":"Tarragona",
    "wof:name":"A.t.gamm S.l.",
    "wof:placetype":"venue"
},
  "geometry": {"coordinates":[1.540353775,41.2229385376],"type":"Point"}
}