{
  "type": "Feature",
  "properties": {
    "iso:country":"ES",
    "sg:address":"Pol Ind Ganadero, S/n",
    "sg:city":"Caceres",
    "sg:orig_category":"Empresas De Carpinter\u00cda De Madera",
    "sg:phone":"+34 927 18 16 21",
    "sg:postcode":"10004",
    "sg:province":"C\u00e1ceres",
    "wof:name":"Carpinteria Reyes C.b.",
    "wof:placetype":"venue"
},
  "geometry": {"coordinates":[-6.3583831787,39.5027656555],"type":"Point"}
}