{
  "type": "Feature",
  "properties": {
    "addr:full":"Calle de Sdo Arrom Cuart, 3 Palma Islas Baleares 07010",
    "addr:housenumber":"3",
    "addr:postcode":"07010",
    "addr:street":"Calle De Sdo;Cuart",
    "iso:country":"ES",
    "sg:address":"Calle de Sdo Arrom Cuart, 3",
    "sg:city":"Palma",
    "sg:orig_category":"Inform\u00c1tica, Ofim\u00c1tica (estudios, Asesor\u00cda, Ingenier\u00cda, Formaci\u00d3n)",
    "sg:phone":"+34 971 75 03 24",
    "sg:postcode":"07010",
    "sg:province":"Islas Baleares",
    "sg:website":"www.sm2baleares.es",
    "wof:name":"Sm2 Baleares",
    "wof:placetype":"venue"
},
  "geometry": {"coordinates":[2.6452040672,39.5839118958],"type":"Point"}
}