{
  "type": "Feature",
  "properties": {
    "iso:country":"ES",
    "sg:address":"Calle de Escuelas, 37",
    "sg:city":"Bo\u00f1ar",
    "sg:orig_category":"Peluquer\u00cdas",
    "sg:phone":"+34 987 73 53 77",
    "sg:postcode":"24850",
    "sg:province":"Le\u00f3n",
    "wof:name":"Mercedes Y Rosario S.l.",
    "wof:placetype":"venue"
},
  "geometry": {"coordinates":[-5.3162770271,42.8666191101],"type":"Point"}
}