{
  "type": "Feature",
  "properties": {
    "iso:country":"ES",
    "sg:address":"Calle de Miriam Blasco, 141",
    "sg:city":"Valladolid",
    "sg:orig_category":"Transportes Por V\u00cdas Navegables",
    "sg:phone":"+34 983 40 62 47",
    "sg:postcode":"47014",
    "sg:province":"Valladolid",
    "wof:name":"Due\u00f1as Transportes Y Servicios S.l.",
    "wof:placetype":"venue"
},
  "geometry": {"coordinates":[-4.7675089836,41.6400413513],"type":"Point"}
}