{
  "type": "Feature",
  "properties": {
    "addr:full":"Avda Espera (de), S/n Jerez De La Frontera C\u00e1diz 11405",
    "addr:postcode":"11405",
    "addr:street":"Avda Espera De S / N",
    "iso:country":"ES",
    "sg:address":"Avda Espera (de), S/n",
    "sg:city":"Jerez De La Frontera",
    "sg:orig_category":"Sociedades, Compa\u00d1\u00cdas Aseguradoras",
    "sg:phone":"+34 956 18 34 12",
    "sg:postcode":"11405",
    "sg:province":"C\u00e1diz",
    "wof:name":"Rio Sanchez Eduardo Del",
    "wof:placetype":"venue"
},
  "geometry": {"coordinates":[-6.1064639091,36.7098693848],"type":"Point"}
}