{
  "type": "Feature",
  "properties": {
    "iso:country":"ES",
    "sg:address":"Calle de Hurtado De Amezaga, 1",
    "sg:city":"Bilbao",
    "sg:orig_category":"M\u00c9dicos: An\u00c1lisis Cl\u00cdnicos",
    "sg:phone":"+34 944 44 05 31",
    "sg:postcode":"48008",
    "sg:province":"Vizcaya",
    "wof:name":"Nicolas Lomas Asensio Y Jose Castellet Zabala Cdad.",
    "wof:placetype":"venue"
},
  "geometry": {"coordinates":[-2.9309868813,43.2588653564],"type":"Point"}
}