{
  "type": "Feature",
  "properties": {
    "iso:country":"ES",
    "sg:address":"Calle de Candeleria, 26",
    "sg:city":"Sevilla",
    "sg:orig_category":"Supermercados Y Hipermercados",
    "sg:phone":"+34 954 63 71 39",
    "sg:postcode":"41006",
    "sg:province":"Sevilla",
    "wof:name":"Dinosol Supermercados S.l.",
    "wof:placetype":"venue"
},
  "geometry": {"coordinates":[-5.9565248489,37.3811264038],"type":"Point"}
}