{
  "type": "Feature",
  "properties": {
    "iso:country":"ES",
    "sg:address":"Calle de Colon, 10",
    "sg:city":"Novelda",
    "sg:orig_category":"Bisuter\u00cda, Joyer\u00cda, Relojer\u00cda (al Por Menor)",
    "sg:phone":"+34 965 60 09 75",
    "sg:postcode":"03660",
    "sg:province":"Alicante",
    "wof:name":"Perez Perez Caridad",
    "wof:placetype":"venue"
},
  "geometry": {"coordinates":[-0.7660830021,38.3845024109],"type":"Point"}
}