{
  "type": "Feature",
  "properties": {
    "addr:full":"Calle de Real, 58 Pulgar Toledo 45125",
    "addr:housenumber":"58",
    "addr:postcode":"45125",
    "addr:street":"Calle De Real",
    "iso:country":"ES",
    "sg:address":"Calle de Real, 58",
    "sg:city":"Pulgar",
    "sg:orig_category":"Confecci\u00d3n (fabricaci\u00d3n, Al Por Mayor)",
    "sg:phone":"+34 925 29 21 03",
    "sg:postcode":"45125",
    "sg:province":"Toledo",
    "wof:name":"Aranda Villarrubia Maria Del Mar",
    "wof:placetype":"venue"
},
  "geometry": {"coordinates":[-4.1537284851,39.6939430237],"type":"Point"}
}