{
  "type": "Feature",
  "properties": {
    "addr:full":"Pl. Mayor, 10 Portell De Morella Castell\u00f3n 12318",
    "addr:housenumber":"10",
    "addr:postcode":"12318",
    "addr:street":"Pl. Mayor",
    "iso:country":"ES",
    "sg:address":"Pl. Mayor, 10",
    "sg:city":"Portell De Morella",
    "sg:orig_category":"Cajas Para Embalar",
    "sg:phone":"+34 964 17 88 01",
    "sg:postcode":"12318",
    "sg:province":"Castell\u00f3n",
    "sg:website":"www.ruralcaja.es",
    "wof:name":"Caja Rural Del Mediterraneo Ruralcaja S Coop De Credito",
    "wof:placetype":"venue"
},
  "geometry": {"coordinates":[-0.2145610005,40.5831108093],"type":"Point"}
}