{
  "type": "Feature",
  "properties": {
    "addr:full":"Plaz Concepcion (la), 1 San Cristobal De La Laguna Santa Cruz De Tenerife 38201",
    "addr:postcode":"38201",
    "addr:street":"Plaz;La 1",
    "iso:country":"ES",
    "sg:address":"Plaz Concepcion (la), 1",
    "sg:city":"San Cristobal De La Laguna",
    "sg:orig_category":"Panader\u00cdas, Panader\u00cdas",
    "sg:phone":"+34 922 25 98 21",
    "sg:postcode":"38201",
    "sg:province":"Santa Cruz De Tenerife",
    "wof:name":"Rapp Luz Otto",
    "wof:placetype":"venue"
},
  "geometry": {"coordinates":[-16.3191509247,28.4898662567],"type":"Point"}
}