{
  "type": "Feature",
  "properties": {
    "addr:full":"Calle de Cerrillo, 10 Navarredondilla \u00c1vila 05120",
    "addr:housenumber":"10",
    "addr:postcode":"05120",
    "addr:street":"Calle De Cerrillo;A\u0301Vila",
    "iso:country":"ES",
    "sg:address":"Calle de Cerrillo, 10",
    "sg:city":"Navarredondilla",
    "sg:orig_category":"Art\u00cdculos Funerarios (al Por Menor)",
    "sg:phone":"+34 920 29 76 40",
    "sg:postcode":"05120",
    "sg:province":"\u00c1vila",
    "wof:name":"Lopez Garcia Laureano",
    "wof:placetype":"venue"
},
  "geometry": {"coordinates":[-4.8222990036,40.4519767761],"type":"Point"}
}