{
  "type": "Feature",
  "properties": {
    "addr:full":"Carrer de Mossen Jacint Verdaguer, 13 Olesa Montserrat Barcelona 08640",
    "addr:housenumber":"13",
    "addr:postcode":"08640",
    "addr:street":"Carrer De Mossen Jacint Verdaguer;Barcelona",
    "iso:country":"ES",
    "sg:address":"Carrer de Mossen Jacint Verdaguer, 13",
    "sg:city":"Olesa Montserrat",
    "sg:orig_category":"Herboristas (al Por Menor)",
    "sg:phone":"+34 937 78 27 28",
    "sg:postcode":"08640",
    "sg:province":"Barcelona",
    "wof:name":"Prades Claramunt Anna Maria",
    "wof:placetype":"venue"
},
  "geometry": {"coordinates":[1.8958079815,41.5412597656],"type":"Point"}
}