{
  "type": "Feature",
  "properties": {
    "addr:full":"Ctra. Cartagena-escombreras, Km. 0010,0 Escombreras Murcia 30350",
    "addr:postcode":"30350",
    "addr:street":"Ctra. Cartagena-Escombreras Km. 0010,0",
    "iso:country":"ES",
    "sg:address":"Ctra. Cartagena-escombreras, Km. 0010,0",
    "sg:city":"Escombreras",
    "sg:orig_category":"Productos Qu\u00cdmicos (fabricaci\u00d3n, Al Por Mayor)",
    "sg:phone":"+34 968 16 70 19",
    "sg:postcode":"30350",
    "sg:province":"Murcia",
    "wof:name":"Saras Energias S.a.",
    "wof:placetype":"venue"
},
  "geometry": {"coordinates":[-0.915988028,37.5820579529],"type":"Point"}
}