{
  "type": "Feature",
  "properties": {
    "addr:full":"Ctra Comarcal, Km. 0010,4 Benejama Alicante 03460",
    "addr:postcode":"03460",
    "addr:street":"Ctra Comarcal Km. 0010,4",
    "iso:country":"ES",
    "sg:address":"Ctra Comarcal, Km. 0010,4",
    "sg:city":"Benejama",
    "sg:orig_category":"Semiller\u00cdas",
    "sg:phone":"+34 965 82 22 05",
    "sg:postcode":"03460",
    "sg:province":"Alicante",
    "wof:name":"Albero Calabuig Jose",
    "wof:placetype":"venue"
},
  "geometry": {"coordinates":[-0.7627879977,38.723865509],"type":"Point"}
}