{
  "type": "Feature",
  "properties": {
    "iso:country":"ES",
    "sg:address":"Urb Residencial Cerro Mulera, 78",
    "sg:city":"Residencial Cerro Mulera",
    "sg:orig_category":"Contables",
    "sg:phone":"+34 956 46 06 01",
    "sg:postcode":"11600",
    "sg:province":"C\u00e1diz",
    "wof:name":"Gutierrez Duran Noelia",
    "wof:placetype":"venue"
},
  "geometry": {"coordinates":[-5.4475698471,36.6776618958],"type":"Point"}
}