{
  "type": "Feature",
  "properties": {
    "addr:full":"Jesus, S/n Setcases Girona 17869",
    "addr:housenumber":"s / n",
    "addr:postcode":"17869",
    "addr:street":"Jesus",
    "iso:country":"ES",
    "sg:address":"Jesus, S/n",
    "sg:city":"Setcases",
    "sg:orig_category":"Administraciones Regionales, Departamentales Y Locales",
    "sg:phone":"+34 972 13 60 89",
    "sg:postcode":"17869",
    "sg:province":"Girona",
    "wof:name":"Ajuntament",
    "wof:placetype":"venue"
},
  "geometry": {"coordinates":[2.3010427952,42.3739776611],"type":"Point"}
}