{
  "type": "Feature",
  "properties": {
    "iso:country":"ES",
    "sg:address":"Avda Jesus De Nazaret, 19",
    "sg:city":"Llerena",
    "sg:orig_category":"Autob\u00das (explotaci\u00d3n Y Servicios De)",
    "sg:phone":"+34 924 87 25 45",
    "sg:postcode":"06900",
    "sg:province":"Badajoz",
    "wof:name":"Autocares Tebal-bus S.l",
    "wof:placetype":"venue"
},
  "geometry": {"coordinates":[-6.0142397881,38.2401008606],"type":"Point"}
}