{
  "type": "Feature",
  "properties": {
    "iso:country":"ES",
    "sg:address":"Calle de Rey Francisco, 17",
    "sg:city":"Madrid",
    "sg:orig_category":"Pintura Y Barniz (al Por Menor)",
    "sg:phone":"+34 915 42 03 77",
    "sg:postcode":"28008",
    "sg:province":"Madrid",
    "wof:name":"Garcia Caba\u00f1ero Paloma",
    "wof:placetype":"venue"
},
  "geometry": {"coordinates":[-3.7169919014,40.4266471863],"type":"Point"}
}