{
  "type": "Feature",
  "properties": {
    "iso:country":"ES",
    "sg:address":"Avgd L'estacio, 29",
    "sg:city":"Oropesa",
    "sg:orig_category":"Servicios Diversos",
    "sg:phone":"+34 964 31 29 19",
    "sg:postcode":"12594",
    "sg:province":"Castell\u00f3n",
    "wof:name":"Orpesa Net I Sec S.l.",
    "wof:placetype":"venue"
},
  "geometry": {"coordinates":[0.1380999982,40.0927963257],"type":"Point"}
}