{
  "type": "Feature",
  "properties": {
    "iso:country":"ES",
    "sg:address":"Calle de Sebastian Errazu, 2",
    "sg:city":"Irun",
    "sg:orig_category":"Empresas De Carpinter\u00cda Met\u00c1lica",
    "sg:phone":"+34 943 61 78 83",
    "sg:postcode":"20303",
    "sg:province":"Guip\u00f9zcoa",
    "wof:name":"Cedivesa S.l.",
    "wof:placetype":"venue"
},
  "geometry": {"coordinates":[-1.7977370024,43.3387184143],"type":"Point"}
}