{
  "type": "Feature",
  "properties": {
    "addr:full":"Calle de San Felipe Neri, 2 Madrid Madrid 28013",
    "addr:housenumber":"2",
    "addr:postcode":"28013",
    "addr:street":"Calle De San Felipe Neri",
    "iso:country":"ES",
    "sg:address":"Calle de San Felipe Neri, 2",
    "sg:city":"Madrid",
    "sg:orig_category":"Producci\u00d3n, Distribuci\u00d3n De Electricidad",
    "sg:phone":"+34 915 59 55 48",
    "sg:postcode":"28013",
    "sg:province":"Madrid",
    "wof:name":"Rubio Espejel Santiago",
    "wof:placetype":"venue"
},
  "geometry": {"coordinates":[-3.7080469131,40.4163246155],"type":"Point"}
}