{
  "type": "Feature",
  "properties": {
    "iso:country":"ES",
    "sg:address":"Pol. Ind., 29",
    "sg:city":"Quintanar Orden",
    "sg:orig_category":"Centros M\u00c9dicos Y Sociales, Dispensarios",
    "sg:phone":"+34 925 56 49 32",
    "sg:postcode":"45800",
    "sg:province":"Toledo",
    "wof:name":"Quintaorden S.l.",
    "wof:placetype":"venue"
},
  "geometry": {"coordinates":[-3.047492981,39.5965499878],"type":"Point"}
}