{
  "type": "Feature",
  "properties": {
    "addr:full":"Sta. Ana, 93 Azuaga Badajoz 06920",
    "addr:housenumber":"93",
    "addr:postcode":"06920",
    "addr:street":"Ana",
    "iso:country":"ES",
    "sg:address":"Sta. Ana, 93",
    "sg:city":"Azuaga",
    "sg:orig_category":"Molduras, Junquillos, Listones Y Molduras Perforadas",
    "sg:phone":"+34 924 89 25 68",
    "sg:postcode":"06920",
    "sg:province":"Badajoz",
    "wof:name":"Carrizosa Sevillano Miguel",
    "wof:placetype":"venue"
},
  "geometry": {"coordinates":[-5.6769890785,38.2583389282],"type":"Point"}
}