{
  "type": "Feature",
  "properties": {
    "addr:full":"Calle de Merced, 90 Coru\u00d1a A Coru\u00f1a 15009",
    "addr:housenumber":"90",
    "addr:postcode":"15009",
    "addr:street":"Calle De Merced;Corun\u0303A",
    "iso:country":"ES",
    "sg:address":"Calle de Merced, 90",
    "sg:city":"Coru\u00d1a",
    "sg:orig_category":"Farmacias",
    "sg:phone":"+34 981 28 77 48",
    "sg:postcode":"15009",
    "sg:province":"A Coru\u00f1a",
    "wof:name":"Solla Castro Concepcion",
    "wof:placetype":"venue"
},
  "geometry": {"coordinates":[-8.3914690018,43.3520507812],"type":"Point"}
}