{
  "type": "Feature",
  "properties": {
    "addr:full":"Calle de Monroy, 18 Salamanca Salamanca 37001",
    "addr:housenumber":"18",
    "addr:postcode":"37001",
    "addr:street":"Calle De Monroy",
    "iso:country":"ES",
    "sg:address":"Calle de Monroy, 18",
    "sg:city":"Salamanca",
    "sg:orig_category":"Ropa Y Accesorios",
    "sg:phone":"+34 923 21 28 15",
    "sg:postcode":"37001",
    "sg:province":"Salamanca",
    "wof:name":"Gomez Castilla Isidro",
    "wof:placetype":"venue"
},
  "geometry": {"coordinates":[-5.6602392197,40.9678688049],"type":"Point"}
}