{
  "type": "Feature",
  "properties": {
    "iso:country":"ES",
    "sg:address":"Calle de Viera Y Clavijo, 35",
    "sg:city":"Palmas De Gran Canaria",
    "sg:orig_category":"Detectives, Agentes Investigadores Privados",
    "sg:phone":"+34 928 38 31 00",
    "sg:postcode":"35002",
    "sg:province":"Las Palmas",
    "wof:name":"Garrido Gomez Jose Maria",
    "wof:placetype":"venue"
},
  "geometry": {"coordinates":[-15.4183521271,28.1078300476],"type":"Point"}
}