{
  "type": "Feature",
  "properties": {
    "addr:full":"Avda Salvador De Madariaga, S/n Coru\u00d1a La Coru\u00f1a 15008",
    "addr:housenumber":"s / n",
    "addr:postcode":"15008",
    "addr:street":"Avda Salvador De Madariaga;La Corun\u0303A",
    "iso:country":"ES",
    "sg:address":"Avda Salvador De Madariaga, S/n",
    "sg:city":"Coru\u00d1a",
    "sg:orig_category":"Florister\u00cdas",
    "sg:phone":"+34 981 29 85 83",
    "sg:postcode":"15008",
    "sg:province":"La Coru\u00f1a",
    "wof:name":"Floricultor Pati\u00f1o S. L.",
    "wof:placetype":"venue"
},
  "geometry": {"coordinates":[-8.4071159363,43.3454399109],"type":"Point"}
}