{
  "type": "Feature",
  "properties": {
    "iso:country":"ES",
    "sg:address":"Calle de Ciudadela, 32",
    "sg:city":"Matas-pinar-monte Rozas",
    "sg:orig_category":"Aceites Y Grasas Alimentarias (fabricaci\u00d3n, Al Por Mayor)",
    "sg:phone":"+34 916 30 95 38",
    "sg:postcode":"28290",
    "sg:province":"Madrid",
    "wof:name":"Bango Cascon Marta",
    "wof:placetype":"venue"
},
  "geometry": {"coordinates":[-3.8985788822,40.5563697815],"type":"Point"}
}