{
  "type": "Feature",
  "properties": {
    "iso:country":"ES",
    "sg:address":"Calle de Uranio, 3",
    "sg:city":"Gloria",
    "sg:orig_category":"Peluqueros: De Se\u00d1oras",
    "sg:phone":"+34 950 30 32 31",
    "sg:postcode":"04230",
    "sg:province":"Almer\u00eda",
    "wof:name":"Zamora Belmonte Jose",
    "wof:placetype":"venue"
},
  "geometry": {"coordinates":[-2.4679217339,36.8401641846],"type":"Point"}
}