{
  "type": "Feature",
  "properties": {
    "addr:full":"Calle de Reyes De Navarra, 19 Vitoria-gasteiz \u00c1lava 01013",
    "addr:housenumber":"19",
    "addr:postcode":"01013",
    "addr:street":"Calle De Reyes De Navarra",
    "iso:country":"ES",
    "sg:address":"Calle de Reyes De Navarra, 19",
    "sg:city":"Vitoria-gasteiz",
    "sg:orig_category":"Peluquer\u00cdas, Peluquer\u00cda Mixta",
    "sg:phone":"+34 945 25 03 84",
    "sg:postcode":"01013",
    "sg:province":"\u00c1lava",
    "wof:name":"Ana Belen Flores Cruz",
    "wof:placetype":"venue"
},
  "geometry": {"coordinates":[-2.6690509319,42.8572158813],"type":"Point"}
}