{
  "type": "Feature",
  "properties": {
    "addr:full":"Carrer de Caracas, 13 Barcelona Barcelona 08030",
    "addr:housenumber":"13",
    "addr:postcode":"08030",
    "addr:street":"Carrer De Caracas",
    "iso:country":"ES",
    "sg:address":"Carrer de Caracas, 13",
    "sg:city":"Barcelona",
    "sg:orig_category":"Cerrajer\u00cda, Ferrallista",
    "sg:phone":"+34 933 11 00 60",
    "sg:postcode":"08030",
    "sg:province":"Barcelona",
    "wof:name":"Lopez Bravo Luciano",
    "wof:placetype":"venue"
},
  "geometry": {"coordinates":[2.2030479908,41.4416847229],"type":"Point"}
}