{
  "type": "Feature",
  "properties": {
    "iso:country":"ES",
    "sg:address":"Calle de Lopez Gomez, 6",
    "sg:city":"Valladolid",
    "sg:orig_category":"Art\u00cdculos De Madera (fabricaci\u00d3n Y Al Por Mayor)",
    "sg:phone":"+34 983 30 29 53",
    "sg:postcode":"47002",
    "sg:province":"Valladolid",
    "wof:name":"Nilsson  Andre",
    "wof:placetype":"venue"
},
  "geometry": {"coordinates":[-4.7239117622,41.6495513916],"type":"Point"}
}