{
  "type": "Feature",
  "properties": {
    "addr:full":"Calle de Maria Moliner, 23 Aviles Asturias 33401",
    "addr:housenumber":"23",
    "addr:postcode":"33401",
    "addr:street":"Calle De Maria Moliner",
    "iso:country":"ES",
    "sg:address":"Calle de Maria Moliner, 23",
    "sg:city":"Aviles",
    "sg:orig_category":"Delegados, Agentes De Tr\u00c1nsito, Auxiliares De Transporte Internacional",
    "sg:phone":"+34 985 52 60 95",
    "sg:postcode":"33401",
    "sg:province":"Asturias",
    "wof:name":"Vega Lopez Blanca Rosa",
    "wof:placetype":"venue"
},
  "geometry": {"coordinates":[-5.9370331764,43.5600128174],"type":"Point"}
}