{
  "type": "Feature",
  "properties": {
    "addr:full":"Calle de Alameda, 17 Coru\u00d1a La Coru\u00f1a 15003",
    "addr:housenumber":"17",
    "addr:postcode":"15003",
    "addr:street":"Calle De Alameda;La Corun\u0303A",
    "iso:country":"ES",
    "sg:address":"Calle de Alameda, 17",
    "sg:city":"Coru\u00d1a",
    "sg:orig_category":"Panader\u00cdas, Panader\u00cdas",
    "sg:phone":"+34 981 22 78 13",
    "sg:postcode":"15003",
    "sg:province":"La Coru\u00f1a",
    "wof:name":"Sanchez Garcia Jose",
    "wof:placetype":"venue"
},
  "geometry": {"coordinates":[-8.4059448242,43.3679199219],"type":"Point"}
}