{
  "type": "Feature",
  "properties": {
    "addr:full":"Avgd Alfons Xiii, 617 Badalona Barcelona 08918",
    "addr:housenumber":"617",
    "addr:postcode":"08918",
    "addr:street":"Alfons Xiii",
    "iso:country":"ES",
    "sg:address":"Avgd Alfons Xiii, 617",
    "sg:city":"Badalona",
    "sg:orig_category":"Carnicer\u00cdas, Carnicer\u00cdas",
    "sg:phone":"+34 933 87 20 47",
    "sg:postcode":"08918",
    "sg:province":"Barcelona",
    "wof:name":"Pascual Grau Enrique",
    "wof:placetype":"venue"
},
  "geometry": {"coordinates":[2.2166008949,41.4331703186],"type":"Point"}
}