{
  "type": "Feature",
  "properties": {
    "addr:full":"Carrer de Joan Manen, 14 Gava Barcelona 08850",
    "addr:housenumber":"14",
    "addr:postcode":"08850",
    "addr:street":"Carrer De Joan Manen",
    "iso:country":"ES",
    "sg:address":"Carrer de Joan Manen, 14",
    "sg:city":"Gava",
    "sg:orig_category":"Promotores Constructores",
    "sg:phone":"+34 936 38 19 31",
    "sg:postcode":"08850",
    "sg:province":"Barcelona",
    "wof:name":"Mondo Iberica S.a.",
    "wof:placetype":"venue"
},
  "geometry": {"coordinates":[1.999456048,41.3114318848],"type":"Point"}
}