{
  "type": "Feature",
  "properties": {
    "addr:full":"Loiolako Inazio Hiribidea, 7 Azpeitia Guip\u00f9zcoa 20730",
    "addr:housenumber":"7",
    "addr:postcode":"20730",
    "addr:street":"Loiolako Inazio Hiribidea;Guipu\u0300Zcoa",
    "iso:country":"ES",
    "sg:address":"Loiolako Inazio Hiribidea, 7",
    "sg:city":"Azpeitia",
    "sg:orig_category":"Peluquer\u00cdas, Peluquer\u00cda Mixta",
    "sg:phone":"+34 943 08 06 25",
    "sg:postcode":"20730",
    "sg:province":"Guip\u00f9zcoa",
    "wof:name":"Miren Gurutze Segurola Garmendia (amets)",
    "wof:placetype":"venue"
},
  "geometry": {"coordinates":[-2.2703180313,43.181137085],"type":"Point"}
}