{
  "type": "Feature",
  "properties": {
    "addr:full":"Pase Victoria (de La), 41 Cordoba C\u00f3rdoba 14004",
    "addr:postcode":"14004",
    "addr:street":"Co\u0301Rdoba",
    "iso:country":"ES",
    "sg:address":"Pase Victoria (de La), 41",
    "sg:city":"Cordoba",
    "sg:orig_category":"M\u00c9dicos: Ginecolog\u00cda Y Obstetricia",
    "sg:phone":"+34 957 42 11 15",
    "sg:postcode":"14004",
    "sg:province":"C\u00f3rdoba",
    "wof:name":"Guisado Lopez Ramon",
    "wof:placetype":"venue"
},
  "geometry": {"coordinates":[-4.7845158577,37.882938385],"type":"Point"}
}