{
  "type": "Feature",
  "properties": {
    "iso:country":"ES",
    "sg:address":"Calle de Real, 7",
    "sg:city":"Cha\u00f1e",
    "sg:orig_category":"Molduras, Junquillos, Listones Y Molduras Perforadas",
    "sg:phone":"+34 921 15 50 09",
    "sg:postcode":"40216",
    "sg:province":"Segovia",
    "wof:name":"Cabrera Herranz Avelino",
    "wof:placetype":"venue"
},
  "geometry": {"coordinates":[-4.4267039299,41.3383674622],"type":"Point"}
}