{
  "type": "Feature",
  "properties": {
    "iso:country":"ES",
    "sg:address":"Calle de Toledo, 77",
    "sg:city":"Madrid",
    "sg:orig_category":"Perfumer\u00cda (al Por Menor)",
    "sg:phone":"+34 913 66 75 78",
    "sg:postcode":"28005",
    "sg:province":"Madrid",
    "wof:name":"Gilgo S.a.",
    "wof:placetype":"venue"
},
  "geometry": {"coordinates":[-3.7092320919,40.4100227356],"type":"Point"}
}