{
  "type": "Feature",
  "properties": {
    "addr:full":"Pl Espanya, 11 Mataro Barcelona 08302",
    "addr:housenumber":"11",
    "addr:postcode":"08302",
    "addr:street":"Pl Espanya",
    "iso:country":"ES",
    "sg:address":"Pl Espanya, 11",
    "sg:city":"Mataro",
    "sg:classifiers":[
        {
            "category":"Autos & Motor Vehicles",
            "subcategory":"Automobile Sales",
            "type":"Retail Goods"
        }
    ],
    "sg:phone":"+34 937 55 40 88",
    "sg:postcode":"08302",
    "sg:province":"Barcelona",
    "wof:name":"Autoescoles Beltran S.l.",
    "wof:placetype":"venue"
},
  "geometry": {"coordinates":[2.4415614605,41.5443840027],"type":"Point"}
}