{
  "type": "Feature",
  "properties": {
    "addr:full":"Calle de Angel Guimera, 77 Valencia Valencia 46008",
    "addr:housenumber":"77",
    "addr:postcode":"46008",
    "addr:street":"Calle De Angel Guimera",
    "iso:country":"ES",
    "sg:address":"Calle de Angel Guimera, 77",
    "sg:city":"Valencia",
    "sg:orig_category":"Bisuter\u00cda, Joyer\u00cda, Relojer\u00cda (al Por Menor)",
    "sg:phone":"+34 963 85 96 71",
    "sg:postcode":"46008",
    "sg:province":"Valencia",
    "wof:name":"Grisverd Joiers S.l.",
    "wof:placetype":"venue"
},
  "geometry": {"coordinates":[-0.3913564086,39.4690628052],"type":"Point"}
}