{
  "type": "Feature",
  "properties": {
    "addr:full":"Calle de Majada (la), 12 Arrecife Las Palmas 35500",
    "addr:housenumber":"12",
    "addr:postcode":"35500",
    "addr:street":"Calle De Majada La",
    "iso:country":"ES",
    "sg:address":"Calle de Majada (la), 12",
    "sg:city":"Arrecife",
    "sg:orig_category":"Empresas De Limpieza",
    "sg:phone":"+34 928 80 43 13",
    "sg:postcode":"35500",
    "sg:province":"Las Palmas",
    "wof:name":"Limpiezas Quesada",
    "wof:placetype":"venue"
},
  "geometry": {"coordinates":[-13.5477180481,28.9787254333],"type":"Point"}
}