{
  "type": "Feature",
  "properties": {
    "iso:country":"ES",
    "sg:address":"Calle de Marquesa De Pinares, 4",
    "sg:city":"Merida",
    "sg:orig_category":"Frutas, Legumbres Frescas Y Tempranas (al Por Menor)",
    "sg:phone":"+34 924 33 02 83",
    "sg:postcode":"06800",
    "sg:province":"Badajoz",
    "wof:name":"Cortijo Alcaide Basilio",
    "wof:placetype":"venue"
},
  "geometry": {"coordinates":[-6.343735218,38.9203186035],"type":"Point"}
}