{
  "type": "Feature",
  "properties": {
    "addr:full":"Avda Nuestra Se\u00d1ora De Montserrat, 146 Almeria Almer\u00eda 04006",
    "addr:housenumber":"146",
    "addr:postcode":"04006",
    "addr:street":"Avda Nuestra Sen\u0303Ora De Montserrat",
    "iso:country":"ES",
    "sg:address":"Avda Nuestra Se\u00d1ora De Montserrat, 146",
    "sg:city":"Almeria",
    "sg:orig_category":"Suministros Y Materiales Industriales",
    "sg:phone":"+34 950 22 68 02",
    "sg:postcode":"04006",
    "sg:province":"Almer\u00eda",
    "sg:website":"www.suministros-martinez.com",
    "wof:name":"Suministros Industriales Martinez S.l.",
    "wof:placetype":"venue"
},
  "geometry": {"coordinates":[-2.4452359676,36.8385734558],"type":"Point"}
}