{
  "type": "Feature",
  "properties": {
    "iso:country":"ES",
    "sg:address":"Calle de Alhambra, 1",
    "sg:city":"G\u00fcevejar",
    "sg:orig_category":"Empresas De Pintura Y Revestimientos",
    "sg:phone":"+34 958 42 91 62",
    "sg:postcode":"18197",
    "sg:province":"Granada",
    "wof:name":"Martinez Morales Jose Luis",
    "wof:placetype":"venue"
},
  "geometry": {"coordinates":[-3.6063017845,37.2193145752],"type":"Point"}
}