{
  "type": "Feature",
  "properties": {
    "iso:country":"ES",
    "sg:address":"Pol Ind Cadesa (cd Blanca-montecillos), 9",
    "sg:city":"Dos Hermanas",
    "sg:orig_category":"Chapister\u00cda",
    "sg:phone":"+34 955 66 90 88",
    "sg:postcode":"41700",
    "sg:province":"Sevilla",
    "wof:name":"Talleres Jedian S.l.l.",
    "wof:placetype":"venue"
},
  "geometry": {"coordinates":[-5.9281339645,37.2829055786],"type":"Point"}
}