{
  "type": "Feature",
  "properties": {
    "iso:country":"ES",
    "sg:address":"Pla\u00c7 Pompeu Fabra, 11",
    "sg:city":"Girona",
    "sg:orig_category":"Sociedades, Compa\u00d1\u00cdas Aseguradoras",
    "sg:phone":"+34 972 20 53 64",
    "sg:postcode":"17002",
    "sg:province":"Girona",
    "wof:name":"Zurich Espa\u00d1a S.a.",
    "wof:placetype":"venue"
},
  "geometry": {"coordinates":[2.8190748692,41.9780960083],"type":"Point"}
}