{
  "type": "Feature",
  "properties": {
    "iso:country":"ES",
    "sg:address":"Calle de Ejercito Espa\u00d1ol, 2",
    "sg:city":"Melilla",
    "sg:orig_category":"Peleter\u00cdas",
    "sg:phone":"+34 952 68 02 09",
    "sg:postcode":"52001",
    "sg:province":"Melilla",
    "wof:name":"Abdelkader Mohamed Hassan",
    "wof:placetype":"venue"
},
  "geometry": {"coordinates":[-2.938577,35.293236],"type":"Point"}
}