{
  "type": "Feature",
  "properties": {
    "addr:full":"Avda San Agustin, 6 Aviles Asturias 33401",
    "addr:housenumber":"6",
    "addr:postcode":"33401",
    "addr:street":"Avda San Agustin",
    "iso:country":"ES",
    "sg:address":"Avda San Agustin, 6",
    "sg:city":"Aviles",
    "sg:orig_category":"Farmacias",
    "sg:phone":"+34 985 56 70 87",
    "sg:postcode":"33401",
    "sg:province":"Asturias",
    "wof:name":"Suarez Hurle Elsa",
    "wof:placetype":"venue"
},
  "geometry": {"coordinates":[-5.9283080101,43.5555229187],"type":"Point"}
}