{
  "type": "Feature",
  "properties": {
    "addr:full":"Calle de Bermudez De Castro, 52 Oviedo Asturias 33011",
    "addr:housenumber":"52",
    "addr:postcode":"33011",
    "addr:street":"Calle De Bermudez De Castro",
    "iso:country":"ES",
    "sg:address":"Calle de Bermudez De Castro, 52",
    "sg:city":"Oviedo",
    "sg:orig_category":"Florister\u00cdas",
    "sg:phone":"+34 985 28 60 75",
    "sg:postcode":"33011",
    "sg:province":"Asturias",
    "wof:name":"Lopez Martin Maria Teresa",
    "wof:placetype":"venue"
},
  "geometry": {"coordinates":[-5.8365340233,43.371963501],"type":"Point"}
}