{
  "type": "Feature",
  "properties": {
    "addr:full":"Calle de Artabide, 3 Ondarroa Vizcaya 48700",
    "addr:housenumber":"3",
    "addr:postcode":"48700",
    "addr:street":"Calle De Artabide",
    "iso:country":"ES",
    "sg:address":"Calle de Artabide, 3",
    "sg:city":"Ondarroa",
    "sg:orig_category":"Bancos",
    "sg:phone":"+34 946 83 33 32",
    "sg:postcode":"48700",
    "sg:province":"Vizcaya",
    "wof:name":"Bankinter S.a.",
    "wof:placetype":"venue"
},
  "geometry": {"coordinates":[-2.4214279652,43.3216667175],"type":"Point"}
}