{
  "type": "Feature",
  "properties": {
    "addr:full":"Pla\u00c7 Jardi (del), 24 Albal Valencia 46470",
    "addr:postcode":"46470",
    "iso:country":"ES",
    "sg:address":"Pla\u00c7 Jardi (del), 24",
    "sg:city":"Albal",
    "sg:orig_category":"M\u00c9dicos: Estomatolog\u00cda",
    "sg:phone":"+34 961 26 32 23",
    "sg:postcode":"46470",
    "sg:province":"Valencia",
    "wof:name":"Qaisi Utrilla Jose",
    "wof:placetype":"venue"
},
  "geometry": {"coordinates":[-0.412766993,39.3970718384],"type":"Point"}
}