{
  "type": "Feature",
  "properties": {
    "iso:country":"ES",
    "sg:address":"Rua Cruz (da), 11",
    "sg:city":"Lugo",
    "sg:classifiers":[
        {
            "category":"Personal",
            "subcategory":"Barber",
            "type":"Services"
        }
    ],
    "sg:phone":"+34 982 22 92 08",
    "sg:postcode":"27001",
    "sg:province":"Lugo",
    "sg:tags":[
        "caballeros",
        "de",
        "peluqueros"
    ],
    "wof:name":"Ascariz Gucema Javier",
    "wof:placetype":"venue"
},
  "geometry": {"coordinates":[-7.5579357147,43.0101280212],"type":"Point"}
}