{
  "type": "Feature",
  "properties": {
    "iso:country":"ES",
    "sg:address":"Calle de Mosen Pedro Mena, 29",
    "sg:city":"Sant Joan D'alacant",
    "sg:orig_category":"Comercio, Reparaci\u00d3n De Bicicletas, De Motocicletas, De Accesorios",
    "sg:phone":"+34 965 65 33 87",
    "sg:postcode":"03550",
    "sg:province":"Alicante",
    "wof:name":"Motos Gomez S.l.",
    "wof:placetype":"venue"
},
  "geometry": {"coordinates":[-0.5047780275,38.3652191162],"type":"Point"}
}