{
  "type": "Feature",
  "properties": {
    "addr:full":"Calle de Victoria, 26 Ubeda Ja\u00e9n 23400",
    "addr:housenumber":"26",
    "addr:postcode":"23400",
    "addr:street":"Calle De Victoria;Jae\u0301N",
    "iso:country":"ES",
    "sg:address":"Calle de Victoria, 26",
    "sg:city":"Ubeda",
    "sg:orig_category":"Asesor\u00cda Sobre Comunicaci\u00d3n De Empresas",
    "sg:phone":"+34 953 75 73 74",
    "sg:postcode":"23400",
    "sg:province":"Ja\u00e9n",
    "wof:name":"Palacios Mu\u00f1oz Abogados Y Economistas S.l.",
    "wof:placetype":"venue"
},
  "geometry": {"coordinates":[-3.3752560616,38.0120277405],"type":"Point"}
}