{
  "type": "Feature",
  "properties": {
    "iso:country":"ES",
    "sg:address":"Calle de Pablo Picasso, 32",
    "sg:city":"Velez-malaga",
    "sg:orig_category":"Droguer\u00cdas (al Por Menor)",
    "sg:phone":"+34 952 50 60 21",
    "sg:postcode":"29700",
    "sg:province":"M\u00e1laga",
    "wof:name":"Vacas Fernandez Hermenegildo",
    "wof:placetype":"venue"
},
  "geometry": {"coordinates":[-4.1025671959,36.7769012451],"type":"Point"}
}