{
  "type": "Feature",
  "properties": {
    "addr:full":"Carrer de Asturies, 25 S. Boi Llobregat Barcelona 08830",
    "addr:housenumber":"25",
    "addr:postcode":"08830",
    "addr:street":"Carrer De Asturies",
    "iso:country":"ES",
    "sg:address":"Carrer de Asturies, 25",
    "sg:city":"S. Boi Llobregat",
    "sg:orig_category":"Aceros Inoxidables",
    "sg:phone":"+34 936 30 45 00",
    "sg:postcode":"08830",
    "sg:province":"Barcelona",
    "wof:name":"Acero Inoxidable A Medida S. A.",
    "wof:placetype":"venue"
},
  "geometry": {"coordinates":[2.0472877026,41.3316421509],"type":"Point"}
}