{
  "type": "Feature",
  "properties": {
    "iso:country":"ES",
    "sg:address":"Carr Llibertat, 67",
    "sg:city":"Vilanova I La Geltru",
    "sg:orig_category":"Asistencia Social",
    "sg:phone":"+34 938 15 63 34",
    "sg:postcode":"08800",
    "sg:province":"Barcelona",
    "wof:name":"Montero Urdiales Gemma",
    "wof:placetype":"venue"
},
  "geometry": {"coordinates":[1.7282470465,41.2209396362],"type":"Point"}
}