{
  "type": "Feature",
  "properties": {
    "addr:full":"Avda Laciana, 40 Villablino Le\u00f3n 24100",
    "addr:housenumber":"40",
    "addr:postcode":"24100",
    "addr:street":"Avda Laciana",
    "iso:country":"ES",
    "sg:address":"Avda Laciana, 40",
    "sg:city":"Villablino",
    "sg:orig_category":"Cl\u00cdnicas Dentales",
    "sg:phone":"+34 987 47 05 65",
    "sg:postcode":"24100",
    "sg:province":"Le\u00f3n",
    "wof:name":"Cuestas  Ricardo Jose",
    "wof:placetype":"venue"
},
  "geometry": {"coordinates":[-6.3200588226,42.9391212463],"type":"Point"}
}