{
  "type": "Feature",
  "properties": {
    "iso:country":"ES",
    "sg:address":"Calle de Marte, 78",
    "sg:city":"Valdemoro",
    "sg:orig_category":"Peluquer\u00cdas, Peluquer\u00cda Mixta",
    "sg:phone":"+34 918 95 49 38",
    "sg:postcode":"28340",
    "sg:province":"Madrid",
    "wof:name":"Fernandez Vadillo Elena",
    "wof:placetype":"venue"
},
  "geometry": {"coordinates":[-3.6809380054,40.178352356],"type":"Point"}
}