{
  "type": "Feature",
  "properties": {
    "iso:country":"ES",
    "sg:address":"Av Roma, 198",
    "sg:city":"Manlleu",
    "sg:orig_category":"Ropa Para Se\u00d1oras (al Por Menor)",
    "sg:phone":"+34 938 50 75 98",
    "sg:postcode":"08560",
    "sg:province":"Barcelona",
    "wof:name":"El Bachiri  Abdellah",
    "wof:placetype":"venue"
},
  "geometry": {"coordinates":[2.2780690193,42.0027656555],"type":"Point"}
}