{
  "type": "Feature",
  "properties": {
    "addr:full":"Ctra Murcia Granada, Km. 0302,0 Alhama Murcia Murcia 30840",
    "addr:postcode":"30840",
    "addr:street":"Ctra Murcia Granada Km. 0302,0",
    "iso:country":"ES",
    "sg:address":"Ctra Murcia Granada, Km. 0302,0",
    "sg:city":"Alhama Murcia",
    "sg:orig_category":"Otros Trabajos De Limpieza Y Mantenimiento (extracci\u00d3n De Polvo, Recogida De Amianto Y Desespumado)",
    "sg:phone":"+34 968 63 03 55",
    "sg:postcode":"30840",
    "sg:province":"Murcia",
    "wof:name":"Maquinaria Auxiliar General S.l.",
    "wof:placetype":"venue"
},
  "geometry": {"coordinates":[-1.4241490364,37.8507995605],"type":"Point"}
}