{
  "type": "Feature",
  "properties": {
    "iso:country":"ES",
    "sg:address":"Carrer de Rafael De Casanova, 112",
    "sg:city":"Sant Vicen\u00c7 Dels Horts",
    "sg:orig_category":"Elementos Para Suelos Prefabricados",
    "sg:phone":"+34 936 56 34 76",
    "sg:postcode":"08620",
    "sg:province":"Barcelona",
    "wof:name":"Exposito Cortes Ana Maria",
    "wof:placetype":"venue"
},
  "geometry": {"coordinates":[2.0100400448,41.3932189941],"type":"Point"}
}