{
  "type": "Feature",
  "properties": {
    "addr:full":"Carr Almirall Colom, 6 Vilanova I La Geltru Barcelona 08800",
    "addr:housenumber":"6",
    "addr:postcode":"08800",
    "addr:street":"Carr Almirall Colom",
    "iso:country":"ES",
    "sg:address":"Carr Almirall Colom, 6",
    "sg:city":"Vilanova I La Geltru",
    "sg:orig_category":"Ropa Para Ni\u00d1os (al Por Menor)",
    "sg:phone":"+34 938 14 17 33",
    "sg:postcode":"08800",
    "sg:province":"Barcelona",
    "wof:name":"Aigua Marina S C P",
    "wof:placetype":"venue"
},
  "geometry": {"coordinates":[1.7262624502,41.2230949402],"type":"Point"}
}