{
  "type": "Feature",
  "properties": {
    "iso:country":"ES",
    "sg:address":"Av Pi I Margall, 101",
    "sg:city":"Caldes Montbui",
    "sg:orig_category":"Quincaller\u00cda (al Por Menor)",
    "sg:phone":"+34 938 62 62 56",
    "sg:postcode":"08140",
    "sg:province":"Barcelona",
    "wof:name":"Subministres Industrials I De Ferreteria Boluda S.l.",
    "wof:placetype":"venue"
},
  "geometry": {"coordinates":[2.1644508839,41.4115867615],"type":"Point"}
}