{
  "type": "Feature",
  "properties": {
    "iso:country":"ES",
    "sg:address":"Plaz San Sebastian, 2",
    "sg:city":"Mairena Alcor",
    "sg:orig_category":"Empresas De Carpinter\u00cda De Madera",
    "sg:phone":"+34 955 74 60 63",
    "sg:postcode":"41510",
    "sg:province":"Sevilla",
    "wof:name":"Jimenez Gonzalez Manuel",
    "wof:placetype":"venue"
},
  "geometry": {"coordinates":[-5.7507581711,37.3742103577],"type":"Point"}
}