{
  "type": "Feature",
  "properties": {
    "addr:full":"Calle de Polo Norte, 15 Torrejon Ardoz Madrid 28850",
    "addr:housenumber":"15",
    "addr:postcode":"28850",
    "addr:street":"Calle De Polo Norte",
    "iso:country":"ES",
    "sg:address":"Calle de Polo Norte, 15",
    "sg:city":"Torrejon Ardoz",
    "sg:orig_category":"Parques De Atracciones Y Centros De Esparcimiento",
    "sg:phone":"+34 916 76 11 23",
    "sg:postcode":"28850",
    "sg:province":"Madrid",
    "wof:name":"Guti Producciones S.l.",
    "wof:placetype":"venue"
},
  "geometry": {"coordinates":[-3.481112957,40.450630188],"type":"Point"}
}