{
  "type": "Feature",
  "properties": {
    "iso:country":"ES",
    "sg:address":"Plaz Santisima Trinidad, S/n",
    "sg:city":"Algeciras",
    "sg:orig_category":"Iglesia Cat\u00d3lica",
    "sg:phone":"+34 956 63 06 81",
    "sg:postcode":"11205",
    "sg:province":"C\u00e1diz",
    "wof:name":"Parroquia Santisima Trinidad",
    "wof:placetype":"venue"
},
  "geometry": {"coordinates":[-5.4489798546,36.1479911804],"type":"Point"}
}