{
  "type": "Feature",
  "properties": {
    "addr:full":"Carrer de Vallespir, S/n S. Joan Despi Barcelona 08970",
    "addr:housenumber":"s",
    "addr:postcode":"08970",
    "addr:street":"Carrer De Vallespir;/ N S. Joan Despi",
    "iso:country":"ES",
    "sg:address":"Carrer de Vallespir, S/n",
    "sg:city":"S. Joan Despi",
    "sg:orig_category":"Importaci\u00d3n",
    "sg:phone":"+34 933 73 90 68",
    "sg:postcode":"08970",
    "sg:province":"Barcelona",
    "wof:name":"Trading Films S.l.",
    "wof:placetype":"venue"
},
  "geometry": {"coordinates":[2.0610411167,41.3733482361],"type":"Point"}
}