{
  "type": "Feature",
  "properties": {
    "addr:full":"Calle de San Bernardo, 57 Madrid Madrid 28015",
    "addr:housenumber":"57",
    "addr:postcode":"madrid;28015",
    "addr:street":"Calle De San Bernardo",
    "iso:country":"ES",
    "sg:address":"Calle de San Bernardo, 57",
    "sg:city":"Madrid",
    "sg:orig_category":"Laboratorios Y Trabajos De Fotograf\u00cda, V\u00cddeo Y Cine",
    "sg:phone":"+34 915 31 41 75",
    "sg:postcode":"28015",
    "sg:province":"Madrid",
    "wof:name":"Jorge Domenech S. A.",
    "wof:placetype":"venue"
},
  "geometry": {"coordinates":[-3.7071950436,40.4260215759],"type":"Point"}
}