{
  "type": "Feature",
  "properties": {
    "iso:country":"ES",
    "sg:address":"Avda Periodista R. De Salazar, 27",
    "sg:city":"Alacant",
    "sg:orig_category":"Agencias Y Agentes Comerciales, Representantes",
    "sg:phone":"+34 965 24 13 28",
    "sg:postcode":"03014",
    "sg:province":"Alicante",
    "wof:name":"Iniciativas Urbanisticas Alicantinas S.l.",
    "wof:placetype":"venue"
},
  "geometry": {"coordinates":[-0.4784319997,38.3626861572],"type":"Point"}
}