{
  "type": "Feature",
  "properties": {
    "addr:full":"Pla\u00c7 Miguel Hernandez, De, 8 Carcaixent Valencia 46740",
    "addr:housenumber":"8",
    "addr:postcode":"46740",
    "addr:street":"Miguel Hernandez De",
    "iso:country":"ES",
    "sg:address":"Pla\u00c7 Miguel Hernandez, De, 8",
    "sg:city":"Carcaixent",
    "sg:orig_category":"Cl\u00cdnicas Dentales",
    "sg:phone":"+34 962 43 26 97",
    "sg:postcode":"46740",
    "sg:province":"Valencia",
    "wof:name":"Selfa Hernandez Jose Maria",
    "wof:placetype":"venue"
},
  "geometry": {"coordinates":[-0.4498789907,39.1257591248],"type":"Point"}
}