{
  "type": "Feature",
  "properties": {
    "addr:full":"Calle de Corbeta, 8 Madrid Madrid 28042",
    "addr:housenumber":"8",
    "addr:postcode":"madrid;28042",
    "addr:street":"Calle De Corbeta",
    "iso:country":"ES",
    "sg:address":"Calle de Corbeta, 8",
    "sg:city":"Madrid",
    "sg:orig_category":"Farmacias",
    "sg:phone":"+34 917 47 19 51",
    "sg:postcode":"28042",
    "sg:province":"Madrid",
    "wof:name":"Farmacia Rodriguez Ruiz C.b.",
    "wof:placetype":"venue"
},
  "geometry": {"coordinates":[-3.5870287418,40.4563713074],"type":"Point"}
}