{
  "type": "Feature",
  "properties": {
    "iso:country":"ES",
    "sg:address":"Calle de Castalla, 20",
    "sg:city":"Ibi",
    "sg:orig_category":"Poller\u00cda Y Caza (al Por Menor)",
    "sg:phone":"+34 965 55 17 99",
    "sg:postcode":"03440",
    "sg:province":"Alicante",
    "wof:name":"Pastor Camarasa Jose",
    "wof:placetype":"venue"
},
  "geometry": {"coordinates":[-0.5779889822,38.6244659424],"type":"Point"}
}