{
  "type": "Feature",
  "properties": {
    "addr:full":"Ctra Sabadell, 70 Rubi Barcelona 08191",
    "addr:housenumber":"70",
    "addr:postcode":"08191",
    "addr:street":"Ctra Sabadell",
    "iso:country":"ES",
    "sg:address":"Ctra Sabadell, 70",
    "sg:city":"Rubi",
    "sg:orig_category":"Aguas (distribuci\u00d3n, Servicios)",
    "sg:phone":"+34 936 97 23 20",
    "sg:postcode":"08191",
    "sg:province":"Barcelona",
    "wof:name":"Luengo Villazan Jose Antonio",
    "wof:placetype":"venue"
},
  "geometry": {"coordinates":[2.0331456661,41.50025177],"type":"Point"}
}