{
  "type": "Feature",
  "properties": {
    "iso:country":"ES",
    "sg:address":"Azken Kalea, 4",
    "sg:city":"Zarautz",
    "sg:orig_category":"Inform\u00c1tica (estudios, Servicios, Asesor\u00cda, Formaci\u00d3n)",
    "sg:phone":"+34 943 13 46 16",
    "sg:postcode":"20800",
    "sg:province":"Guip\u00f9zcoa",
    "sg:website":"www.asei-pymes.com",
    "wof:name":"Portularrume Elorza Gregorio",
    "wof:placetype":"venue"
},
  "geometry": {"coordinates":[-2.176486969,43.2803916931],"type":"Point"}
}