{
  "type": "Feature",
  "properties": {
    "iso:country":"ES",
    "sg:address":"Rbla Nova, 36",
    "sg:city":"Mollet Valles",
    "sg:orig_category":"Centros Comerciales Y Grandes Tiendas",
    "sg:phone":"+34 935 70 72 16",
    "sg:postcode":"08100",
    "sg:province":"Barcelona",
    "wof:name":"Margarida Matencio S.l.",
    "wof:placetype":"venue"
},
  "geometry": {"coordinates":[2.2097659111,41.540271759],"type":"Point"}
}