{
  "type": "Feature",
  "properties": {
    "addr:full":"Calle de Licenciado Cascales, 3 Alcantarilla Murcia 30820",
    "addr:housenumber":"3",
    "addr:postcode":"30820",
    "addr:street":"Calle De Licenciado Cascales",
    "iso:country":"ES",
    "sg:address":"Calle de Licenciado Cascales, 3",
    "sg:city":"Alcantarilla",
    "sg:orig_category":"Distribuci\u00d3n De Petr\u00d3leo Y Derivados",
    "sg:phone":"+34 968 80 02 05",
    "sg:postcode":"30820",
    "sg:province":"Murcia",
    "sg:website":"www.paginasamarillas.es",
    "wof:name":"Teruel Aranega Domingo",
    "wof:placetype":"venue"
},
  "geometry": {"coordinates":[-1.2171771526,37.9643249512],"type":"Point"}
}