{
  "type": "Feature",
  "properties": {
    "iso:country":"ES",
    "sg:address":"Cami Port Lligat, S/n",
    "sg:city":"Cadaques",
    "sg:orig_category":"Museos",
    "sg:phone":"+34 972 25 10 15",
    "sg:postcode":"17488",
    "sg:province":"Girona",
    "sg:website":"www.salvador-dali.org",
    "wof:name":"Fundacion Gala-salvador Dali",
    "wof:placetype":"venue"
},
  "geometry": {"coordinates":[3.2826459408,42.290927887],"type":"Point"}
}