{
  "type": "Feature",
  "properties": {
    "addr:full":"Carrer de Villa, 1 S. Cugat Valles Barcelona 08172",
    "addr:housenumber":"1",
    "addr:postcode":"08172",
    "addr:street":"Carrer De Villa;Barcelona",
    "iso:country":"ES",
    "sg:address":"Carrer de Villa, 1",
    "sg:city":"S. Cugat Valles",
    "sg:orig_category":"Agencias Y Agentes Comerciales, Representantes",
    "sg:phone":"+34 936 75 66 18",
    "sg:postcode":"08172",
    "sg:province":"Barcelona",
    "wof:name":"Van Meel  Christianus",
    "wof:placetype":"venue"
},
  "geometry": {"coordinates":[2.0798521042,41.4680862427],"type":"Point"}
}