{
  "type": "Feature",
  "properties": {
    "addr:full":"Plaz Gomila, S/n Sevilla Sevilla 41019",
    "addr:housenumber":"s / n",
    "addr:postcode":"41019",
    "addr:street":"Plaz Gomila",
    "iso:country":"ES",
    "sg:address":"Plaz Gomila, S/n",
    "sg:city":"Sevilla",
    "sg:orig_category":"Empresas De Pintura Y Revestimientos",
    "sg:phone":"+34 954 51 83 98",
    "sg:postcode":"41019",
    "sg:province":"Sevilla",
    "wof:name":"Villagran Delgado Manuel",
    "wof:placetype":"venue"
},
  "geometry": {"coordinates":[-5.9270792007,37.4079055786],"type":"Point"}
}