{
  "type": "Feature",
  "properties": {
    "addr:full":"Carrer de Doctor Ferran, 38 Reus Tarragona 43202",
    "addr:housenumber":"38",
    "addr:postcode":"43202",
    "addr:street":"Carrer De Doctor Ferran",
    "iso:country":"ES",
    "sg:address":"Carrer de Doctor Ferran, 38",
    "sg:city":"Reus",
    "sg:orig_category":"Producci\u00d3n, Venta De Productos De Agricultura Biol\u00d3gica",
    "sg:phone":"+34 977 31 66 29",
    "sg:postcode":"43202",
    "sg:province":"Tarragona",
    "wof:name":"Marigot Jansa Ramon",
    "wof:placetype":"venue"
},
  "geometry": {"coordinates":[1.0986440182,41.1542778015],"type":"Point"}
}