{
  "type": "Feature",
  "properties": {
    "iso:country":"ES",
    "sg:address":"Cra. Canoves, Km. 0003,5",
    "sg:city":"Cardedeu",
    "sg:orig_category":"Asilos De Ancianos. Centros Privados",
    "sg:phone":"+34 938 71 10 78",
    "sg:postcode":"08440",
    "sg:province":"Barcelona",
    "wof:name":"El Raco De Cardedeu S.l.",
    "wof:placetype":"venue"
},
  "geometry": {"coordinates":[2.3603100777,41.6399612427],"type":"Point"}
}