{
  "type": "Feature",
  "properties": {
    "iso:country":"ES",
    "sg:address":"Carrer de Amadeu Vives, 15",
    "sg:city":"Arenys Munt",
    "sg:orig_category":"Fabricaci\u00d3n, Venta De Cuadros, Accesorios Para Enmarcar",
    "sg:phone":"+34 937 95 13 08",
    "sg:postcode":"08358",
    "sg:province":"Barcelona",
    "wof:name":"Fubrima S.l.",
    "wof:placetype":"venue"
},
  "geometry": {"coordinates":[2.5375449657,41.6121101379],"type":"Point"}
}