{
  "type": "Feature",
  "properties": {
    "addr:full":"Calle de Pozas (las), 27 Alfaro La Rioja 26540",
    "addr:housenumber":"27",
    "addr:postcode":"26540",
    "addr:street":"Calle De Pozas Las;Rioja",
    "iso:country":"ES",
    "sg:address":"Calle de Pozas (las), 27",
    "sg:city":"Alfaro",
    "sg:orig_category":"Productos Qu\u00cdmicos (fabricaci\u00d3n, Al Por Mayor)",
    "sg:phone":"+34 941 18 44 44",
    "sg:postcode":"26540",
    "sg:province":"La Rioja",
    "sg:website":"www.laboratoriosalfaro.com",
    "wof:name":"Laboratorios Alfaro S.l.",
    "wof:placetype":"venue"
},
  "geometry": {"coordinates":[-1.7510139942,42.178943634],"type":"Point"}
}