{
  "type": "Feature",
  "properties": {
    "addr:full":"Avda Blasco Iba\u00d1ez, 50 Alaquas Valencia 46970",
    "addr:housenumber":"50",
    "addr:postcode":"46970",
    "addr:street":"Avda Blasco Iban\u0303Ez",
    "iso:country":"ES",
    "sg:address":"Avda Blasco Iba\u00d1ez, 50",
    "sg:city":"Alaquas",
    "sg:orig_category":"Droguer\u00cdas (al Por Menor)",
    "sg:phone":"+34 961 51 19 61",
    "sg:postcode":"46970",
    "sg:province":"Valencia",
    "wof:name":"Gelaber Aparicio Fernando",
    "wof:placetype":"venue"
},
  "geometry": {"coordinates":[-0.4514049888,39.4575538635],"type":"Point"}
}