{
  "type": "Feature",
  "properties": {
    "addr:full":"Carrer de Marques De Sentmenat, 44 Barcelona Barcelona 08014",
    "addr:housenumber":"44",
    "addr:postcode":"08014",
    "addr:street":"Carrer De Marques De Sentmenat",
    "iso:country":"ES",
    "sg:address":"Carrer de Marques De Sentmenat, 44",
    "sg:city":"Barcelona",
    "sg:orig_category":"M\u00c9dicos: Estomatolog\u00cda",
    "sg:phone":"+34 933 22 27 54",
    "sg:postcode":"08014",
    "sg:province":"Barcelona",
    "wof:name":"Ribas Deix Juan",
    "wof:placetype":"venue"
},
  "geometry": {"coordinates":[2.1370720863,41.3849334717],"type":"Point"}
}