{
  "type": "Feature",
  "properties": {
    "iso:country":"ES",
    "sg:address":"Calle de Mancha (la), 20",
    "sg:city":"Pto. Rosario",
    "sg:orig_category":"Agencias Y Agentes Comerciales, Representantes",
    "sg:phone":"+34 928 53 21 59",
    "sg:postcode":"35600",
    "sg:province":"Las Palmas",
    "wof:name":"Merchacanarias S.l.",
    "wof:placetype":"venue"
},
  "geometry": {"coordinates":[-13.8656606674,28.498506546],"type":"Point"}
}