{
  "type": "Feature",
  "properties": {
    "addr:full":"Carrer de Comte Borrell, 187 Barcelona Barcelona 08015",
    "addr:housenumber":"187",
    "addr:postcode":"08015",
    "addr:street":"Carrer De Comte Borrell",
    "iso:country":"ES",
    "sg:address":"Carrer de Comte Borrell, 187",
    "sg:city":"Barcelona",
    "sg:orig_category":"Asesor\u00cda De Formaci\u00d3n Y Gesti\u00d3n De Personal",
    "sg:phone":"+34 934 51 77 11",
    "sg:postcode":"08015",
    "sg:province":"Barcelona",
    "wof:name":"Baiau Assessors S.l.",
    "wof:placetype":"venue"
},
  "geometry": {"coordinates":[2.1533548832,41.3842010498],"type":"Point"}
}