{
  "type": "Feature",
  "properties": {
    "addr:full":"Calle de Merced, 5 Burgos Burgos 09002",
    "addr:housenumber":"5",
    "addr:postcode":"09002",
    "addr:street":"Calle De Merced",
    "iso:country":"ES",
    "sg:address":"Calle de Merced, 5",
    "sg:city":"Burgos",
    "sg:orig_category":"Loter\u00cda Y T\u00d3mbola",
    "sg:phone":"+34 947 20 85 16",
    "sg:postcode":"09002",
    "sg:province":"Burgos",
    "wof:name":"Azurmendi Fernandez Sergio",
    "wof:placetype":"venue"
},
  "geometry": {"coordinates":[-3.7043008804,42.3382911682],"type":"Point"}
}