{
  "type": "Feature",
  "properties": {
    "addr:full":"Carrer de Riu Sil, 2 Santa Pon\u00c7a Islas Baleares 07180",
    "addr:housenumber":"2",
    "addr:postcode":"07180",
    "addr:street":"Carrer De Riu Sil",
    "iso:country":"ES",
    "sg:address":"Carrer de Riu Sil, 2",
    "sg:city":"Santa Pon\u00c7a",
    "sg:orig_category":"Art\u00cdculos De Regalo (al Por Menor)",
    "sg:phone":"+34 971 69 13 26",
    "sg:postcode":"07180",
    "sg:province":"Islas Baleares",
    "wof:name":"Lopez Garcia Isabel",
    "wof:placetype":"venue"
},
  "geometry": {"coordinates":[2.4810750484,39.5184402466],"type":"Point"}
}