{
  "type": "Feature",
  "properties": {
    "iso:country":"ES",
    "sg:address":"Avda Sevilla, 15",
    "sg:city":"Palacios Y Villafranca",
    "sg:orig_category":"Ropa Para Se\u00d1oras Y Caballeros (al Por Menor)",
    "sg:phone":"+34 955 81 15 61",
    "sg:postcode":"41720",
    "sg:province":"Sevilla",
    "wof:name":"Dominguez Rubio Antonio",
    "wof:placetype":"venue"
},
  "geometry": {"coordinates":[-5.9239349365,37.1608085632],"type":"Point"}
}