{
  "type": "Feature",
  "properties": {
    "iso:country":"ES",
    "sg:address":"Calle de Doctor Lozano, 23",
    "sg:city":"Madrid",
    "sg:orig_category":"Muebles, Minoristas",
    "sg:phone":"+34 915 51 87 34",
    "sg:postcode":"28038",
    "sg:province":"Madrid",
    "wof:name":"Velasgar S.l.",
    "wof:placetype":"venue"
},
  "geometry": {"coordinates":[-3.6604130268,40.4032058716],"type":"Point"}
}