{
  "type": "Feature",
  "properties": {
    "iso:country":"ES",
    "sg:address":"Ctra Monforte (de), S/n",
    "sg:city":"Sober",
    "sg:orig_category":"Farmacias",
    "sg:phone":"+34 982 46 00 12",
    "sg:postcode":"27460",
    "sg:province":"Lugo",
    "wof:name":"Vazquez Fernandez Dolores",
    "wof:placetype":"venue"
},
  "geometry": {"coordinates":[-7.5842251778,42.4625396729],"type":"Point"}
}