{
  "type": "Feature",
  "properties": {
    "iso:country":"ES",
    "sg:address":"Avda Cruz Roja (la), 54",
    "sg:city":"Sevilla",
    "sg:orig_category":"Farmacias",
    "sg:phone":"+34 954 35 12 86",
    "sg:postcode":"41008",
    "sg:province":"Sevilla",
    "wof:name":"Farmacia Navarro Mariscal C.b.",
    "wof:placetype":"venue"
},
  "geometry": {"coordinates":[-5.9815688133,37.4022102356],"type":"Point"}
}