{
  "type": "Feature",
  "properties": {
    "iso:country":"ES",
    "sg:address":"Av Sant Ferran, 49",
    "sg:city":"Palma",
    "sg:orig_category":"Muebles Y Accesorios Para Cocinas Y Cuartos De Ba\u00d1o (al Por Menor)",
    "sg:phone":"+34 971 28 06 44",
    "sg:postcode":"07013",
    "sg:province":"Islas Baleares",
    "wof:name":"Sureda Prats Bartolome",
    "wof:placetype":"venue"
},
  "geometry": {"coordinates":[2.634018898,39.5779571533],"type":"Point"}
}