{
  "type": "Feature",
  "properties": {
    "addr:full":"Calle de Juan Carlos I Rey De Espa\u00d1a, 17 Badajoz Badajoz 06001",
    "addr:housenumber":"17",
    "addr:postcode":"06001",
    "addr:street":"Calle De Juan Carlos I Rey;Espan\u0303A",
    "iso:country":"ES",
    "sg:address":"Calle de Juan Carlos I Rey De Espa\u00d1a, 17",
    "sg:city":"Badajoz",
    "sg:orig_category":"Centros Empresariales",
    "sg:phone":"+34 924 23 47 46",
    "sg:postcode":"06001",
    "sg:province":"Badajoz",
    "wof:name":"Iberphone S.a.",
    "wof:placetype":"venue"
},
  "geometry": {"coordinates":[-6.9720959663,38.8775253296],"type":"Point"}
}