{
  "type": "Feature",
  "properties": {
    "addr:full":"Avda. Langreo-el Berron, S/n La Carrera Asturias 33186",
    "addr:housenumber":"s / n",
    "addr:postcode":"33186",
    "addr:street":"Avda. Langreo-El Berron",
    "iso:country":"ES",
    "sg:address":"Avda. Langreo-el Berron, S/n",
    "sg:city":"La Carrera",
    "sg:orig_category":"Negocio De Madera",
    "sg:phone":"+34 985 74 03 56",
    "sg:postcode":"33186",
    "sg:province":"Asturias",
    "wof:name":"Bada Garcia Luis",
    "wof:placetype":"venue"
},
  "geometry": {"coordinates":[-5.7012858391,43.3833732605],"type":"Point"}
}