{
  "type": "Feature",
  "properties": {
    "iso:country":"ES",
    "sg:address":"Calle de General Franco, 18",
    "sg:city":"S. Nicolas Tolentino",
    "sg:orig_category":"Cajas De Ahorro",
    "sg:phone":"+34 928 89 00 50",
    "sg:postcode":"35470",
    "sg:province":"Las Palmas",
    "wof:name":"Caixa D'estalvis I Pensions De Barcelona",
    "wof:placetype":"venue"
},
  "geometry": {"coordinates":[-15.7808170319,27.9849681854],"type":"Point"}
}