{
  "type": "Feature",
  "properties": {
    "addr:full":"Calle de Virgen De Consolacion, 33 Utrera Sevilla 41710",
    "addr:housenumber":"33",
    "addr:postcode":"41710",
    "addr:street":"Calle De Virgen De Consolacion",
    "iso:country":"ES",
    "sg:address":"Calle de Virgen De Consolacion, 33",
    "sg:city":"Utrera",
    "sg:orig_category":"Zapatos (al Por Menor)",
    "sg:phone":"+34 955 86 57 00",
    "sg:postcode":"41710",
    "sg:province":"Sevilla",
    "wof:name":"Blanco Martin Consolacion",
    "wof:placetype":"venue"
},
  "geometry": {"coordinates":[-5.778345108,37.1827545166],"type":"Point"}
}