{
  "type": "Feature",
  "properties": {
    "iso:country":"ES",
    "sg:address":"Calle de Formacion Profesional, 41",
    "sg:city":"Ejea De Los Caballeros",
    "sg:orig_category":"Agencias Y Agentes Comerciales, Representantes",
    "sg:phone":"+34 976 66 14 76",
    "sg:postcode":"50600",
    "sg:province":"Zaragoza",
    "wof:name":"Ciudad Villa Santiago",
    "wof:placetype":"venue"
},
  "geometry": {"coordinates":[-1.1310089827,42.1263504028],"type":"Point"}
}