{
  "type": "Feature",
  "properties": {
    "addr:full":"Avda Constitucion (de La), 16 Pedro Mu\u00e7oz Ciudad Real 13620",
    "addr:housenumber":"16",
    "addr:postcode":"13620",
    "addr:street":"Avda Constitucion De La;Pedro Muc\u0327Oz",
    "iso:country":"ES",
    "sg:address":"Avda Constitucion (de La), 16",
    "sg:city":"Pedro Mu\u00e7oz",
    "sg:orig_category":"Distribuci\u00d3n De Petr\u00d3leo Y Derivados",
    "sg:phone":"+34 926 58 64 58",
    "sg:postcode":"13620",
    "sg:province":"Ciudad Real",
    "wof:name":"Gonzalez Diaz Maria Luisa",
    "wof:placetype":"venue"
},
  "geometry": {"coordinates":[-2.955878973,39.4055213928],"type":"Point"}
}