{
  "type": "Feature",
  "properties": {
    "addr:full":"Feans, 15 Santiago De Compostela La Coru\u00f1a 15706",
    "addr:housenumber":"15",
    "addr:postcode":"15706",
    "addr:street":"Feans;Corun\u0303A",
    "iso:country":"ES",
    "sg:address":"Feans, 15",
    "sg:city":"Santiago De Compostela",
    "sg:orig_category":"Ense\u00d1anza: Idiomas",
    "sg:phone":"+34 981 59 27 35",
    "sg:postcode":"15706",
    "sg:province":"La Coru\u00f1a",
    "wof:name":"Alfonso Rodriguez Javier",
    "wof:placetype":"venue"
},
  "geometry": {"coordinates":[-8.5517606735,42.8756370544],"type":"Point"}
}