{
  "type": "Feature",
  "properties": {
    "iso:country":"ES",
    "sg:address":"Cmno Puebla De Labarca De (la), S/n",
    "sg:city":"Logro\u00f1o",
    "sg:orig_category":"Contenedores Para Transporte De Mercanc\u00cdas",
    "sg:phone":"+34 941 22 13 84",
    "sg:postcode":"26006",
    "sg:province":"La Rioja",
    "wof:name":"Amonio Cadarso Grandes Contenedores S.l.",
    "wof:placetype":"venue"
},
  "geometry": {"coordinates":[-2.3912363052,42.4574165344],"type":"Point"}
}