{
  "type": "Feature",
  "properties": {
    "addr:full":"Avda Aguirre Lehendakari, 6 Bilbao Vizcaya 48014",
    "addr:housenumber":"6",
    "addr:postcode":"48014",
    "addr:street":"Avda Aguirre Lehendakari",
    "iso:country":"ES",
    "sg:address":"Avda Aguirre Lehendakari, 6",
    "sg:city":"Bilbao",
    "sg:orig_category":"Asesor\u00cdas Y Estudios Financieros",
    "sg:phone":"+34 944 76 20 56",
    "sg:postcode":"48014",
    "sg:province":"Vizcaya",
    "wof:name":"Ibarra Asociados S.c.",
    "wof:placetype":"venue"
},
  "geometry": {"coordinates":[-2.9430389404,43.2717056274],"type":"Point"}
}