{
  "type": "Feature",
  "properties": {
    "addr:full":"Cmno Cruces, 27 Madrid Madrid 28044",
    "addr:housenumber":"27",
    "addr:postcode":"madrid;28044",
    "addr:street":"Cmno Cruces",
    "iso:country":"ES",
    "sg:address":"Cmno Cruces, 27",
    "sg:city":"Madrid",
    "sg:orig_category":"Perfumer\u00cda (al Por Menor)",
    "sg:phone":"+34 915 11 00 38",
    "sg:postcode":"28044",
    "sg:province":"Madrid",
    "wof:name":"Perfumeria La Pilarica",
    "wof:placetype":"venue"
},
  "geometry": {"coordinates":[-3.7549679279,40.3746948242],"type":"Point"}
}