{
  "type": "Feature",
  "properties": {
    "addr:full":"Pase Larratxo De, 20 Donostia-san Sebastian Guip\u00f9zcoa 20017",
    "addr:housenumber":"20",
    "addr:postcode":"20017",
    "iso:country":"ES",
    "sg:address":"Pase Larratxo De, 20",
    "sg:city":"Donostia-san Sebastian",
    "sg:orig_category":"Carnicer\u00cdas, Carnicer\u00cdas",
    "sg:phone":"+34 943 40 03 33",
    "sg:postcode":"20017",
    "sg:province":"Guip\u00f9zcoa",
    "wof:name":"Santos Baile Jesus",
    "wof:placetype":"venue"
},
  "geometry": {"coordinates":[-1.9397120476,43.3142166138],"type":"Point"}
}