{
  "type": "Feature",
  "properties": {
    "iso:country":"ES",
    "sg:address":"Calle de Santo Tome, 5",
    "sg:city":"Toledo",
    "sg:orig_category":"Panader\u00cdas, Panader\u00cdas",
    "sg:phone":"+34 925 22 37 63",
    "sg:postcode":"45002",
    "sg:province":"Toledo",
    "wof:name":"Santo Tome S. A.",
    "wof:placetype":"venue"
},
  "geometry": {"coordinates":[-4.0269169807,39.856842041],"type":"Point"}
}