{
  "type": "Feature",
  "properties": {
    "addr:full":"Avda Playas (las), 8 Puerto Del Carmen Las Palmas 35510",
    "addr:housenumber":"8",
    "addr:postcode":"35510",
    "addr:street":"Avda Playas Las",
    "iso:country":"ES",
    "sg:address":"Avda Playas (las), 8",
    "sg:city":"Puerto Del Carmen",
    "sg:orig_category":"Molduras, Junquillos, Listones Y Molduras Perforadas",
    "sg:phone":"+34 928 51 06 59",
    "sg:postcode":"35510",
    "sg:province":"Las Palmas",
    "wof:name":"Deslandia S. L.",
    "wof:placetype":"venue"
},
  "geometry": {"coordinates":[-13.6564588547,28.9204158783],"type":"Point"}
}