{
  "type": "Feature",
  "properties": {
    "iso:country":"ES",
    "sg:address":"Calle de Carlos Gangoiti, 11",
    "sg:city":"Gernika-lumo",
    "sg:orig_category":"Internados & Ense\u00d1anza Privada",
    "sg:phone":"+34 946 25 70 03",
    "sg:postcode":"48300",
    "sg:province":"Vizcaya",
    "wof:name":"San Fidel Ikastola",
    "wof:placetype":"venue"
},
  "geometry": {"coordinates":[-2.6785542965,43.3200378418],"type":"Point"}
}