{
  "type": "Feature",
  "properties": {
    "addr:full":"Calle de Baleares, 1 Molina Segura Murcia 30500",
    "addr:housenumber":"1",
    "addr:postcode":"30500",
    "addr:street":"Calle De Baleares",
    "iso:country":"ES",
    "sg:address":"Calle de Baleares, 1",
    "sg:city":"Molina Segura",
    "sg:orig_category":"Cajas Para Embalar",
    "sg:phone":"+34 968 38 92 47",
    "sg:postcode":"30500",
    "sg:province":"Murcia",
    "wof:name":"Cajamar",
    "wof:placetype":"venue"
},
  "geometry": {"coordinates":[-1.2033537626,38.0550994873],"type":"Point"}
}