{
  "type": "Feature",
  "properties": {
    "iso:country":"ES",
    "sg:address":"Calle de Viriato, 51",
    "sg:city":"Madrid",
    "sg:orig_category":"Ropa Para Ni\u00d1os (al Por Menor)",
    "sg:phone":"+34 914 46 27 55",
    "sg:postcode":"28010",
    "sg:province":"Madrid",
    "wof:name":"Fernandez De Loaysa Romeu Maria Jose",
    "wof:placetype":"venue"
},
  "geometry": {"coordinates":[-3.6982059479,40.4358634949],"type":"Point"}
}