{
  "type": "Feature",
  "properties": {
    "addr:full":"Calle de Nueva, 8 Granja De La Costera Valencia 46814",
    "addr:housenumber":"8",
    "addr:postcode":"46814",
    "addr:street":"Calle De Nueva",
    "iso:country":"ES",
    "sg:address":"Calle de Nueva, 8",
    "sg:city":"Granja De La Costera",
    "sg:orig_category":"Tractores Agr\u00cdcolas Y Remolques",
    "sg:phone":"+34 962 25 40 50",
    "sg:postcode":"46814",
    "sg:province":"Valencia",
    "wof:name":"Climent Tortosa Salvador",
    "wof:placetype":"venue"
},
  "geometry": {"coordinates":[-0.5727189779,38.9932556152],"type":"Point"}
}