{
  "type": "Feature",
  "properties": {
    "iso:country":"ES",
    "sg:address":"Calle de Navarra, 7",
    "sg:city":"Alcorcon",
    "sg:orig_category":"Muebles, Minoristas",
    "sg:phone":"+34 916 43 72 95",
    "sg:postcode":"28921",
    "sg:province":"Madrid",
    "wof:name":"Burgo Redondo Miguel Del",
    "wof:placetype":"venue"
},
  "geometry": {"coordinates":[-3.8300890923,40.3456039429],"type":"Point"}
}