{
  "type": "Feature",
  "properties": {
    "iso:country":"ES",
    "sg:address":"Avda Portugal, 133",
    "sg:city":"Salamanca",
    "sg:orig_category":"Ropa Para Se\u00d1oras (al Por Menor)",
    "sg:phone":"+34 923 25 30 99",
    "sg:postcode":"37006",
    "sg:province":"Salamanca",
    "wof:name":"Vazquez Rosa Luisa",
    "wof:placetype":"venue"
},
  "geometry": {"coordinates":[-5.6650190353,40.972694397],"type":"Point"}
}