{
  "type": "Feature",
  "properties": {
    "iso:country":"ES",
    "sg:address":"Ctra Andalucia, S/n",
    "sg:city":"Sese\u00e7a Nuevo",
    "sg:orig_category":"Venta, Localizaci\u00d3n, Reparaci\u00d3n De Material E Instrumental M\u00c9dico",
    "sg:phone":"+34 918 09 61 00",
    "sg:postcode":"45224",
    "sg:province":"Toledo",
    "wof:name":"Henry Schein Espa\u00d1a S.a.",
    "wof:placetype":"venue"
},
  "geometry": {"coordinates":[-3.6455190182,40.1041107178],"type":"Point"}
}