{
  "type": "Feature",
  "properties": {
    "iso:country":"ES",
    "sg:address":"Avda Menendez Pelayo, 15",
    "sg:city":"Madrid",
    "sg:orig_category":"Cueros Y Pieles (al Por Mayor)",
    "sg:phone":"+34 915 74 76 65",
    "sg:postcode":"28009",
    "sg:province":"Madrid",
    "wof:name":"Lobejon Martin Juan Jose",
    "wof:placetype":"venue"
},
  "geometry": {"coordinates":[-3.6792581081,40.4201698303],"type":"Point"}
}