{
  "type": "Feature",
  "properties": {
    "iso:country":"ES",
    "sg:address":"Rua Monte Dos Postes (do), 10",
    "sg:city":"Santiago De Compostela",
    "sg:orig_category":"Psic\u00d3logos",
    "sg:phone":"+34 981 58 75 45",
    "sg:postcode":"15703",
    "sg:province":"La Coru\u00f1a",
    "wof:name":"Reig Botella Adela Del Milagro",
    "wof:placetype":"venue"
},
  "geometry": {"coordinates":[-8.5310821533,42.8868255615],"type":"Point"}
}