{
  "type": "Feature",
  "properties": {
    "iso:country":"ES",
    "sg:address":"Calle de Cirilo Amoros, 90",
    "sg:city":"Valencia",
    "sg:orig_category":"Desinfecci\u00d3n, Desinsectaci\u00d3n, Desratizaci\u00d3n",
    "sg:phone":"+34 963 95 18 01",
    "sg:postcode":"46004",
    "sg:province":"Valencia",
    "wof:name":"Temucoral Limpiezas Y Servicios S.l.",
    "wof:placetype":"venue"
},
  "geometry": {"coordinates":[-0.3655950129,39.4696464539],"type":"Point"}
}