{
  "type": "Feature",
  "properties": {
    "iso:country":"ES",
    "sg:address":"Calle de Gerona, 2",
    "sg:city":"Madrid",
    "sg:orig_category":"Grafistas",
    "sg:phone":"+34 913 65 45 58",
    "sg:postcode":"28012",
    "sg:province":"Madrid",
    "wof:name":"Lopez De Bustos Maria",
    "wof:placetype":"venue"
},
  "geometry": {"coordinates":[-3.7061910629,40.4151039124],"type":"Point"}
}