{
  "type": "Feature",
  "properties": {
    "addr:full":"Avda Costa, 63 Gijon Asturias 33202",
    "addr:housenumber":"63",
    "addr:postcode":"33202",
    "addr:street":"Avda Costa",
    "iso:country":"ES",
    "sg:address":"Avda Costa, 63",
    "sg:city":"Gijon",
    "sg:orig_category":"Medias Y Calcetines (al Por Menor)",
    "sg:phone":"+34 985 33 53 13",
    "sg:postcode":"33202",
    "sg:province":"Asturias",
    "wof:name":"Gonzalez Rodriguez Amelia",
    "wof:placetype":"venue"
},
  "geometry": {"coordinates":[-5.6569547653,43.5376472473],"type":"Point"}
}