{
  "type": "Feature",
  "properties": {
    "addr:full":"Av Catalunya, 2 Tarrega Lleida 25300",
    "addr:housenumber":"2",
    "addr:postcode":"25300",
    "addr:street":"Av Catalunya",
    "iso:country":"ES",
    "sg:address":"Av Catalunya, 2",
    "sg:city":"Tarrega",
    "sg:orig_category":"Tapicer\u00cdas",
    "sg:phone":"+34 973 31 07 25",
    "sg:postcode":"25300",
    "sg:province":"Lleida",
    "wof:name":"Sole Bernaus Juan",
    "wof:placetype":"venue"
},
  "geometry": {"coordinates":[1.140059948,41.6485939026],"type":"Point"}
}