{
  "type": "Feature",
  "properties": {
    "iso:country":"ES",
    "sg:address":"Calle de Augusto Figueroa, 43",
    "sg:city":"Madrid",
    "sg:orig_category":"Art\u00cdculos De Decoraci\u00d3n (fabricaci\u00d3n Y Al Por Mayor)",
    "sg:phone":"+34 915 21 56 35",
    "sg:postcode":"28004",
    "sg:province":"Madrid",
    "wof:name":"Romuldo Ortega S.a.",
    "wof:placetype":"venue"
},
  "geometry": {"coordinates":[-3.6965665817,40.4219970703],"type":"Point"}
}