{
  "type": "Feature",
  "properties": {
    "iso:country":"ES",
    "sg:address":"Calle de Menendez Y Pelayo Marcelino, 18",
    "sg:city":"Bilbao",
    "sg:orig_category":"Equipo De Refrigeraci\u00d3n Industrial",
    "sg:phone":"+34 944 33 04 84",
    "sg:postcode":"48006",
    "sg:province":"Vizcaya",
    "wof:name":"Tareman S.l.",
    "wof:placetype":"venue"
},
  "geometry": {"coordinates":[-2.9186201096,43.2526931763],"type":"Point"}
}