{
  "type": "Feature",
  "properties": {
    "iso:country":"ES",
    "sg:address":"Concej Alberto J Becerril, S/n",
    "sg:city":"Tomares",
    "sg:orig_category":"Promotores Constructores",
    "sg:phone":"+34 954 15 20 96",
    "sg:postcode":"41940",
    "sg:province":"Sevilla",
    "sg:website":"www.inmosur.com",
    "wof:name":"Inmobiliaria Del Sur S. A.",
    "wof:placetype":"venue"
},
  "geometry": {"coordinates":[-6.0425992012,37.367855072],"type":"Point"}
}