{
  "type": "Feature",
  "properties": {
    "iso:country":"ES",
    "sg:address":"Calle de Real, 15",
    "sg:city":"Fuensanta Martos",
    "sg:orig_category":"Mercer\u00cda, Lencer\u00cda (al Por Menor)",
    "sg:phone":"+34 953 56 51 57",
    "sg:postcode":"23610",
    "sg:province":"Ja\u00e9n",
    "wof:name":"Pe\u00f1a Lemus Demetrio",
    "wof:placetype":"venue"
},
  "geometry": {"coordinates":[-3.9068100452,37.6462974548],"type":"Point"}
}