{
  "type": "Feature",
  "properties": {
    "addr:full":"Calle de Costa Vasca, 5 Almafra Alicante 03610",
    "addr:housenumber":"5",
    "addr:postcode":"03610",
    "addr:street":"Calle De Costa Vasca;Alicante",
    "iso:country":"ES",
    "sg:address":"Calle de Costa Vasca, 5",
    "sg:city":"Almafra",
    "sg:orig_category":"Zapatos: Material, Suministros, Accesorios (fabricaci\u00d3n, Al Por Mayor)",
    "sg:phone":"+34 965 37 34 12",
    "sg:postcode":"03610",
    "sg:province":"Alicante",
    "wof:name":"Gilher S. A.",
    "wof:placetype":"venue"
},
  "geometry": {"coordinates":[-0.4810059965,38.3452033997],"type":"Point"}
}