{
  "type": "Feature",
  "properties": {
    "addr:full":"Colombia(bda H America), 44 Los Dolores Murcia 30310",
    "addr:housenumber":"44",
    "addr:postcode":"30310",
    "addr:street":"Bda;America",
    "iso:country":"ES",
    "sg:address":"Colombia(bda H America), 44",
    "sg:city":"Los Dolores",
    "sg:orig_category":"Librer\u00cdas",
    "sg:phone":"+34 968 51 77 37",
    "sg:postcode":"30310",
    "sg:province":"Murcia",
    "wof:name":"Roca Martinez Maria Pilar",
    "wof:placetype":"venue"
},
  "geometry": {"coordinates":[-1.0110599995,37.6357650757],"type":"Point"}
}