{
  "type": "Feature",
  "properties": {
    "addr:full":"Carr Alemanya, 26 Figueres Girona 17600",
    "addr:housenumber":"26",
    "addr:postcode":"17600",
    "addr:street":"Carr Alemanya",
    "iso:country":"ES",
    "sg:address":"Carr Alemanya, 26",
    "sg:city":"Figueres",
    "sg:orig_category":"Material Y Herramientas Agr\u00cdcolas",
    "sg:phone":"+34 972 50 21 58",
    "sg:postcode":"17600",
    "sg:province":"Girona",
    "wof:name":"Josep Cusi S.l.",
    "wof:placetype":"venue"
},
  "geometry": {"coordinates":[2.9792325497,42.2632408142],"type":"Point"}
}