{
  "type": "Feature",
  "properties": {
    "addr:full":"Calle de Cartagena, 89 Madrid Madrid 28028",
    "addr:housenumber":"89",
    "addr:postcode":"madrid;28028",
    "addr:street":"Calle De Cartagena",
    "iso:country":"ES",
    "sg:address":"Calle de Cartagena, 89",
    "sg:city":"Madrid",
    "sg:orig_category":"Teatros Y Salas De Espect\u00c1culos",
    "sg:phone":"+34 913 55 71 67",
    "sg:postcode":"28028",
    "sg:province":"Madrid",
    "wof:name":"Valle Alvarez Isaac",
    "wof:placetype":"venue"
},
  "geometry": {"coordinates":[-3.6730759144,40.4385299683],"type":"Point"}
}