{
  "type": "Feature",
  "properties": {
    "addr:full":"Carr Arago, 76 Eivissa Islas Baleares 07800",
    "addr:housenumber":"76",
    "addr:postcode":"07800",
    "addr:street":"Carr Arago",
    "iso:country":"ES",
    "sg:address":"Carr Arago, 76",
    "sg:city":"Eivissa",
    "sg:orig_category":"Asesor\u00cda Fiscal Y Jur\u00cddica",
    "sg:phone":"+34 971 30 70 61",
    "sg:postcode":"07800",
    "sg:province":"Islas Baleares",
    "wof:name":"Antoni Torres Riera S.l.",
    "wof:placetype":"venue"
},
  "geometry": {"coordinates":[1.4247342348,38.9078140259],"type":"Point"}
}