{
  "type": "Feature",
  "properties": {
    "addr:full":"Calle de Camara La, 39 Aviles Asturias 33401",
    "addr:housenumber":"39",
    "addr:postcode":"33401",
    "addr:street":"Calle De Camara La",
    "iso:country":"ES",
    "sg:address":"Calle de Camara La, 39",
    "sg:city":"Aviles",
    "sg:orig_category":"Asesor\u00cda Fiscal Y Jur\u00cddica",
    "sg:phone":"+34 985 56 11 22",
    "sg:postcode":"33401",
    "sg:province":"Asturias",
    "wof:name":"Telenti Asesores S.l.",
    "wof:placetype":"venue"
},
  "geometry": {"coordinates":[-5.9245138168,43.5573348999],"type":"Point"}
}