{
  "type": "Feature",
  "properties": {
    "iso:country":"ES",
    "sg:address":"Calle de Chaparil (el), S/n",
    "sg:city":"Nerja",
    "sg:orig_category":"Panader\u00cdas, Panader\u00cdas",
    "sg:phone":"+34 952 52 06 91",
    "sg:postcode":"29780",
    "sg:province":"M\u00e1laga",
    "wof:name":"Panificadora El Bambi",
    "wof:placetype":"venue"
},
  "geometry": {"coordinates":[-3.8812851906,36.7457199097],"type":"Point"}
}