{
  "type": "Feature",
  "properties": {
    "iso:country":"ES",
    "sg:address":"Calle de Hoya (la), 14",
    "sg:city":"Segovia",
    "sg:orig_category":"Procuradores",
    "sg:phone":"+34 921 43 15 92",
    "sg:postcode":"40003",
    "sg:province":"Segovia",
    "wof:name":"Fuente Hormigo Jesus De La",
    "wof:placetype":"venue"
},
  "geometry": {"coordinates":[-4.11064291,40.9544219971],"type":"Point"}
}