{
  "type": "Feature",
  "properties": {
    "iso:country":"ES",
    "sg:address":"Calle de Mar De Alboran, 2",
    "sg:city":"Sevilla",
    "sg:orig_category":"Reposter\u00cdas",
    "sg:phone":"+34 954 94 07 76",
    "sg:postcode":"41008",
    "sg:province":"Sevilla",
    "wof:name":"Carrero Melgar Maria Del Carmen",
    "wof:placetype":"venue"
},
  "geometry": {"coordinates":[-5.9685239792,37.4187583923],"type":"Point"}
}