{
  "type": "Feature",
  "properties": {
    "iso:country":"ES",
    "sg:address":"Calle de Fernandez De La Hoz, 57",
    "sg:city":"Madrid",
    "sg:orig_category":"Inmobiliaria (agencias)",
    "sg:phone":"+34 914 41 18 54",
    "sg:postcode":"28003",
    "sg:province":"Madrid",
    "wof:name":"Alveraco S. A.",
    "wof:placetype":"venue"
},
  "geometry": {"coordinates":[-3.6944525242,40.4396781921],"type":"Point"}
}