{
  "type": "Feature",
  "properties": {
    "addr:full":"Carrer de Mare De Deu De La Merce, 2 Gava Barcelona 08850",
    "addr:housenumber":"2",
    "addr:postcode":"08850",
    "addr:street":"Carrer De Mare De Deu De La Merce",
    "iso:country":"ES",
    "sg:address":"Carrer de Mare De Deu De La Merce, 2",
    "sg:city":"Gava",
    "sg:orig_category":"M\u00c9dicos: Medicina Interna",
    "sg:phone":"+34 936 62 02 40",
    "sg:postcode":"08850",
    "sg:province":"Barcelona",
    "wof:name":"Masvidal Torrents Antonio",
    "wof:placetype":"venue"
},
  "geometry": {"coordinates":[2.0074551105,41.3052139282],"type":"Point"}
}