{
  "type": "Feature",
  "properties": {
    "iso:country":"ES",
    "sg:address":"Carrer de Sant Sebastia (de), 69",
    "sg:city":"S. Carles Rapita",
    "sg:orig_category":"Negocio De Materiales De Construcci\u00d3n",
    "sg:phone":"+34 977 74 09 09",
    "sg:postcode":"43540",
    "sg:province":"Tarragona",
    "wof:name":"Vidal Armengol Jose",
    "wof:placetype":"venue"
},
  "geometry": {"coordinates":[0.5920389891,40.622428894],"type":"Point"}
}