{
  "type": "Feature",
  "properties": {
    "iso:country":"ES",
    "sg:address":"Avda Gran Via Rey Juan Carlos I, 39",
    "sg:city":"Logro\u00f1o",
    "sg:orig_category":"M\u00c9dicos: Ginecolog\u00cda Y Obstetricia",
    "sg:phone":"+34 941 21 13 53",
    "sg:postcode":"26002",
    "sg:province":"La Rioja",
    "wof:name":"Narro Garcia Francisco-javier",
    "wof:placetype":"venue"
},
  "geometry": {"coordinates":[-2.4501159191,42.4637870789],"type":"Point"}
}