{
  "type": "Feature",
  "properties": {
    "iso:country":"ES",
    "sg:address":"Calle de Gran Via, 30",
    "sg:city":"Majadahonda",
    "sg:orig_category":"\u00d3ptica: Instrumentos (fabricaci\u00d3n)",
    "sg:phone":"+34 916 39 05 45",
    "sg:postcode":"28220",
    "sg:province":"Madrid",
    "wof:name":"Opticas San Gabino 2025 S.l.",
    "wof:placetype":"venue"
},
  "geometry": {"coordinates":[-3.8716630936,40.4717941284],"type":"Point"}
}