{
  "type": "Feature",
  "properties": {
    "iso:country":"ES",
    "sg:address":"Avda Doctor Peset Aleixandre, 52",
    "sg:city":"Valencia",
    "sg:orig_category":"Agencias Y Agentes Comerciales, Representantes",
    "sg:phone":"+34 963 66 61 83",
    "sg:postcode":"46019",
    "sg:province":"Valencia",
    "wof:name":"Rodriguez Tomas Jose Manuel",
    "wof:placetype":"venue"
},
  "geometry": {"coordinates":[-0.3782399893,39.4912185669],"type":"Point"}
}