{
  "type": "Feature",
  "properties": {
    "addr:full":"Ctra Madrid, Km. 0224,0 Soria Soria 42005",
    "addr:postcode":"42005",
    "addr:street":"Ctra Madrid Km. 0224,0",
    "iso:country":"ES",
    "sg:address":"Ctra Madrid, Km. 0224,0",
    "sg:city":"Soria",
    "sg:orig_category":"Empresas De Carpinter\u00cda",
    "sg:phone":"+34 975 22 35 21",
    "sg:postcode":"42005",
    "sg:province":"Soria",
    "wof:name":"Garcia Hernandez Antonio",
    "wof:placetype":"venue"
},
  "geometry": {"coordinates":[-2.4800291061,41.7528800964],"type":"Point"}
}