{
  "type": "Feature",
  "properties": {
    "iso:country":"ES",
    "sg:address":"Pl Pompeu Fabra, 2",
    "sg:city":"Martorell",
    "sg:orig_category":"Complementos De Vestir (al Por Menor)",
    "sg:phone":"+34 937 75 29 66",
    "sg:postcode":"08760",
    "sg:province":"Barcelona",
    "wof:name":"Esteban Palomar Teofila",
    "wof:placetype":"venue"
},
  "geometry": {"coordinates":[1.9265979528,41.474105835],"type":"Point"}
}