{
  "type": "Feature",
  "properties": {
    "iso:country":"ES",
    "sg:address":"Calle de Magisterio, S/n",
    "sg:city":"Alberca De Zancara",
    "sg:orig_category":"Centros De Educaci\u00d3n Especial",
    "sg:phone":"+34 967 15 01 69",
    "sg:postcode":"16620",
    "sg:province":"Cuenca",
    "wof:name":"Colegio Rural Agrupado Jorge Manrique",
    "wof:placetype":"venue"
},
  "geometry": {"coordinates":[-2.4924890995,39.5117988586],"type":"Point"}
}