{
  "type": "Feature",
  "properties": {
    "addr:full":"Calle de Doce De Octubre, 3 Mieres Asturias 33600",
    "addr:housenumber":"3",
    "addr:postcode":"33600",
    "addr:street":"Calle De Doce De Octubre",
    "iso:country":"ES",
    "sg:address":"Calle de Doce De Octubre, 3",
    "sg:city":"Mieres",
    "sg:orig_category":"Muebles, Minoristas",
    "sg:phone":"+34 985 46 86 92",
    "sg:postcode":"33600",
    "sg:province":"Asturias",
    "wof:name":"Lopez Martinez Jose Antonio",
    "wof:placetype":"venue"
},
  "geometry": {"coordinates":[-5.7739577293,43.2504234314],"type":"Point"}
}