{
  "type": "Feature",
  "properties": {
    "addr:full":"Pg Sort (de La), 19 Torredembarra Tarragona 43830",
    "addr:postcode":"43830",
    "iso:country":"ES",
    "sg:address":"Pg Sort (de La), 19",
    "sg:city":"Torredembarra",
    "sg:orig_category":"Inmobiliaria (agencias)",
    "sg:phone":"+34 902 15 73 50",
    "sg:postcode":"43830",
    "sg:province":"Tarragona",
    "sg:website":"www.casadaurada.com",
    "wof:name":"Casa Daurada Internacional S.l.",
    "wof:placetype":"venue"
},
  "geometry": {"coordinates":[1.3988460302,41.1436195374],"type":"Point"}
}