{
  "type": "Feature",
  "properties": {
    "addr:full":"Carrer de Nou - La Canonja, 5 Canonja Tarragona 43110",
    "addr:housenumber":"5",
    "addr:postcode":"43110",
    "addr:street":"Carrer De Nou;Canonja",
    "iso:country":"ES",
    "sg:address":"Carrer de Nou - La Canonja, 5",
    "sg:city":"Canonja",
    "sg:orig_category":"Empresarios Y Productoras De Espect\u00c1culos",
    "sg:phone":"+34 977 54 57 09",
    "sg:postcode":"43110",
    "sg:province":"Tarragona",
    "wof:name":"Organitzacions Artistiques Falguera S.l.",
    "wof:placetype":"venue"
},
  "geometry": {"coordinates":[1.1817840338,41.1208381653],"type":"Point"}
}