{
  "type": "Feature",
  "properties": {
    "addr:full":"Paseo Prieto Moreno, 12 Almu\u00f1ecar Granada 18690",
    "addr:housenumber":"12",
    "addr:postcode":"18690",
    "addr:street":"Paseo Prieto Moreno",
    "iso:country":"ES",
    "sg:address":"Paseo Prieto Moreno, 12",
    "sg:city":"Almu\u00f1ecar",
    "sg:orig_category":"Inmobiliaria (agencias)",
    "sg:phone":"+34 958 63 92 05",
    "sg:postcode":"18690",
    "sg:province":"Granada",
    "wof:name":"Portico Costa S.l.",
    "wof:placetype":"venue"
},
  "geometry": {"coordinates":[-3.6945021152,36.7293891907],"type":"Point"}
}