{
  "type": "Feature",
  "properties": {
    "addr:full":"Plaz Constitucion (de La), S/n Benalua Guadix Granada 18510",
    "addr:housenumber":"s",
    "addr:postcode":"18510",
    "addr:street":"/ N Benalua",
    "iso:country":"ES",
    "sg:address":"Plaz Constitucion (de La), S/n",
    "sg:city":"Benalua Guadix",
    "sg:orig_category":"Bazares, Art\u00cdculos De Limpieza Y De Cocina (al Por Menor)",
    "sg:phone":"+34 958 67 60 84",
    "sg:postcode":"18510",
    "sg:province":"Granada",
    "wof:name":"Leon Fernandez Juan Carlos",
    "wof:placetype":"venue"
},
  "geometry": {"coordinates":[-3.1345832348,37.3003959656],"type":"Point"}
}