{
  "type": "Feature",
  "properties": {
    "iso:country":"ES",
    "sg:address":"Carrer de Avila, 48",
    "sg:city":"Barcelona",
    "sg:orig_category":"Inform\u00c1tica (estudios, Servicios, Asesor\u00cda, Formaci\u00d3n)",
    "sg:phone":"+34 933 00 22 76",
    "sg:postcode":"08005",
    "sg:province":"Barcelona",
    "sg:website":"www.brujulatelecom.com",
    "wof:name":"Brujula Telecom S.a.",
    "wof:placetype":"venue"
},
  "geometry": {"coordinates":[2.196835041,41.3960533142],"type":"Point"}
}