{
  "type": "Feature",
  "properties": {
    "addr:full":"Carrer de Sant Sebastia, 15 Rubi Barcelona 08191",
    "addr:housenumber":"15",
    "addr:postcode":"08191",
    "addr:street":"Carrer De Sant Sebastia",
    "iso:country":"ES",
    "sg:address":"Carrer de Sant Sebastia, 15",
    "sg:city":"Rubi",
    "sg:orig_category":"Peluquer\u00cdas, Peluquer\u00cda Mixta",
    "sg:phone":"+34 936 99 30 73",
    "sg:postcode":"08191",
    "sg:province":"Barcelona",
    "wof:name":"Sancher Labrador Maria Rosa",
    "wof:placetype":"venue"
},
  "geometry": {"coordinates":[2.0299730301,41.4912223816],"type":"Point"}
}