{
  "type": "Feature",
  "properties": {
    "addr:full":"Calle de Ampurdan, 16 Leganes Madrid 28915",
    "addr:housenumber":"16",
    "addr:postcode":"28915",
    "addr:street":"Calle De Ampurdan",
    "iso:country":"ES",
    "sg:address":"Calle de Ampurdan, 16",
    "sg:city":"Leganes",
    "sg:orig_category":"Molduras, Junquillos, Listones Y Molduras Perforadas",
    "sg:phone":"+34 916 88 47 86",
    "sg:postcode":"28915",
    "sg:province":"Madrid",
    "wof:name":"Cytasa Comunicaciones, S.l.",
    "wof:placetype":"venue"
},
  "geometry": {"coordinates":[-3.7562277317,40.3366165161],"type":"Point"}
}