{
  "type": "Feature",
  "properties": {
    "iso:country":"ES",
    "sg:address":"Pto. Sta. Maria, 3",
    "sg:city":"Guadix",
    "sg:orig_category":"Farmacias",
    "sg:phone":"+34 958 66 43 48",
    "sg:postcode":"18500",
    "sg:province":"Granada",
    "wof:name":"Fraile Arroyo Maria Guadalupe",
    "wof:placetype":"venue"
},
  "geometry": {"coordinates":[-3.1343688965,37.303894043],"type":"Point"}
}