{
  "type": "Feature",
  "properties": {
    "iso:country":"ES",
    "sg:address":"Avda Asturias, 30",
    "sg:city":"Guardo",
    "sg:orig_category":"T\u00c9cnicos Veterinarios",
    "sg:phone":"+34 979 85 10 05",
    "sg:postcode":"34880",
    "sg:province":"Palencia",
    "wof:name":"Gonzalez Alonso Francisco Javier",
    "wof:placetype":"venue"
},
  "geometry": {"coordinates":[-4.845053196,42.7924385071],"type":"Point"}
}