{
  "type": "Feature",
  "properties": {
    "iso:country":"ES",
    "sg:address":"Cmno Baza, S/n",
    "sg:city":"Vera",
    "sg:orig_category":"Mec\u00c1nico Del Autom\u00d3vil",
    "sg:phone":"+34 950 39 01 34",
    "sg:postcode":"04620",
    "sg:province":"Almer\u00eda",
    "wof:name":"Ramirez Y Gallardo C. B.",
    "wof:placetype":"venue"
},
  "geometry": {"coordinates":[-1.8724600077,37.2477874756],"type":"Point"}
}