{
  "type": "Feature",
  "properties": {
    "iso:country":"ES",
    "sg:address":"Calle de Molares, 23",
    "sg:city":"Utrera",
    "sg:orig_category":"Transportes Por Carretera: Lotes Completos, Mercanc\u00cdas Diversas",
    "sg:phone":"+34 954 86 17 39",
    "sg:postcode":"41710",
    "sg:province":"Sevilla",
    "wof:name":"Tercervao Carnes En General S.l.",
    "wof:placetype":"venue"
},
  "geometry": {"coordinates":[-5.7768540382,37.1794471741],"type":"Point"}
}