{
  "type": "Feature",
  "properties": {
    "iso:country":"ES",
    "sg:address":"Avda Andalucia, 11",
    "sg:city":"Madrid",
    "sg:orig_category":"Deportes Diversos",
    "sg:phone":"+34 917 96 15 46",
    "sg:postcode":"28041",
    "sg:province":"Madrid",
    "wof:name":"Valores Unidos S.l.",
    "wof:placetype":"venue"
},
  "geometry": {"coordinates":[-3.6948060989,40.3722343445],"type":"Point"}
}