{
  "type": "Feature",
  "properties": {
    "iso:country":"ES",
    "sg:address":"Tudela, 1",
    "sg:city":"Iru\u00f1a",
    "sg:orig_category":"Bancos",
    "sg:phone":"+34 948 22 73 90",
    "sg:postcode":"31002",
    "sg:province":"Navarra",
    "sg:website":"www.bancovasconia.es",
    "wof:name":"Banco De Vasconia",
    "wof:placetype":"venue"
},
  "geometry": {"coordinates":[-1.6446349621,42.8138542175],"type":"Point"}
}