{
  "type": "Feature",
  "properties": {
    "iso:country":"ES",
    "sg:address":"Pla\u00c7 Major, 8",
    "sg:city":"Almussafes",
    "sg:orig_category":"Iglesia Cat\u00d3lica",
    "sg:phone":"+34 961 78 19 84",
    "sg:postcode":"46440",
    "sg:province":"Valencia",
    "wof:name":"Parroquia De San Bartolome",
    "wof:placetype":"venue"
},
  "geometry": {"coordinates":[-0.4128209949,39.2907104492],"type":"Point"}
}