{
  "type": "Feature",
  "properties": {
    "addr:full":"Calle de Salvador, 29 Madridejos Toledo 45710",
    "addr:housenumber":"29",
    "addr:postcode":"45710",
    "addr:street":"Calle De Salvador",
    "iso:country":"ES",
    "sg:address":"Calle de Salvador, 29",
    "sg:city":"Madridejos",
    "sg:orig_category":"Asesor\u00cda Sobre Comunicaci\u00d3n De Empresas",
    "sg:phone":"+34 925 46 07 12",
    "sg:postcode":"45710",
    "sg:province":"Toledo",
    "wof:name":"Asesoria De Empresas Rodriguez Corts C.b",
    "wof:placetype":"venue"
},
  "geometry": {"coordinates":[-3.5329432487,39.4686164856],"type":"Point"}
}