{
  "type": "Feature",
  "properties": {
    "addr:full":"Calle de Fray Ramon De Gines, 11 Gines Sevilla 41960",
    "addr:housenumber":"11",
    "addr:postcode":"41960",
    "addr:street":"Calle De Fray Ramon De Gines;Sevilla",
    "iso:country":"ES",
    "sg:address":"Calle de Fray Ramon De Gines, 11",
    "sg:city":"Gines",
    "sg:orig_category":"Empresarios Y Productoras De Espect\u00c1culos",
    "sg:phone":"+34 954 71 63 48",
    "sg:postcode":"41960",
    "sg:province":"Sevilla",
    "wof:name":"Rubio Velasco Mercedes",
    "wof:placetype":"venue"
},
  "geometry": {"coordinates":[-6.0782527924,37.3867225647],"type":"Point"}
}