{
  "type": "Feature",
  "properties": {
    "iso:country":"ES",
    "sg:address":"Rua San Salvador, 21",
    "sg:city":"Ferrol",
    "sg:orig_category":"Reposter\u00cdas",
    "sg:phone":"+34 981 31 01 94",
    "sg:postcode":"15404",
    "sg:province":"La Coru\u00f1a",
    "wof:name":"Castro Romero Antonio",
    "wof:placetype":"venue"
},
  "geometry": {"coordinates":[-8.2183580399,43.4913978577],"type":"Point"}
}