{
  "type": "Feature",
  "properties": {
    "iso:country":"ES",
    "sg:address":"Plaz Llanete De Manuel Lopez, 5",
    "sg:city":"Aguilar De La Frontera",
    "sg:orig_category":"Venta Al Preg\u00d3n",
    "sg:phone":"+34 957 66 02 60",
    "sg:postcode":"14920",
    "sg:province":"C\u00f3rdoba",
    "wof:name":"Productos Lopez Recio S.l.",
    "wof:placetype":"venue"
},
  "geometry": {"coordinates":[-4.6593580246,37.5161552429],"type":"Point"}
}