{
  "type": "Feature",
  "properties": {
    "addr:full":"Ptda Canastel-a, 106 San Vicente Del Raspeig-sant Vicent Del Raspeig Alicante 03690",
    "addr:housenumber":"106",
    "addr:postcode":"03690",
    "addr:street":"Ptda Canastel-A",
    "iso:country":"ES",
    "sg:address":"Ptda Canastel-a, 106",
    "sg:city":"San Vicente Del Raspeig-sant Vicent Del Raspeig",
    "sg:orig_category":"Barnizadores",
    "sg:phone":"+34 965 66 74 13",
    "sg:postcode":"03690",
    "sg:province":"Alicante",
    "wof:name":"Garcia Orozco Juan Jose",
    "wof:placetype":"venue"
},
  "geometry": {"coordinates":[-0.5111595988,38.4068145752],"type":"Point"}
}