{
  "type": "Feature",
  "properties": {
    "addr:full":"A Chan, 46 Chan Pontevedra 36430",
    "addr:housenumber":"46",
    "addr:postcode":"36430",
    "addr:street":"Chan",
    "iso:country":"ES",
    "sg:address":"A Chan, 46",
    "sg:city":"Chan",
    "sg:orig_category":"Comercio, Reparaci\u00d3n De Motocicletas, Bicicletas Y Piezas Sueltas",
    "sg:phone":"+34 986 66 50 17",
    "sg:postcode":"36430",
    "sg:province":"Pontevedra",
    "wof:name":"Motos Xosmarra",
    "wof:placetype":"venue"
},
  "geometry": {"coordinates":[-8.4824609756,42.4714736938],"type":"Point"}
}