{
  "type": "Feature",
  "properties": {
    "iso:country":"ES",
    "sg:address":"Calle de Gabriel Ramos Bejarano, 111",
    "sg:city":"Cordoba",
    "sg:orig_category":"Industria Qu\u00cdmica",
    "sg:phone":"+34 957 32 51 89",
    "sg:postcode":"14014",
    "sg:province":"C\u00f3rdoba",
    "wof:name":"Framauto S.l.",
    "wof:placetype":"venue"
},
  "geometry": {"coordinates":[-4.7196440697,37.9004745483],"type":"Point"}
}