{
  "type": "Feature",
  "properties": {
    "addr:full":"Calle de Doctor Velazquez, 3 Segorbe Castell\u00f3n 12400",
    "addr:housenumber":"3",
    "addr:postcode":"12400",
    "addr:street":"Calle De Doctor Velazquez",
    "iso:country":"ES",
    "sg:address":"Calle de Doctor Velazquez, 3",
    "sg:city":"Segorbe",
    "sg:orig_category":"Ferreter\u00cda Artesanal",
    "sg:phone":"+34 964 71 03 58",
    "sg:postcode":"12400",
    "sg:province":"Castell\u00f3n",
    "wof:name":"Fajardo Y Morro S.l.",
    "wof:placetype":"venue"
},
  "geometry": {"coordinates":[-0.4876928031,39.8491477966],"type":"Point"}
}