{
  "type": "Feature",
  "properties": {
    "iso:country":"ES",
    "sg:address":"Joan Xxiii Plaza, S/n",
    "sg:city":"Bergara",
    "sg:orig_category":"Alimentaci\u00d3n General (al Por Menor)",
    "sg:phone":"+34 943 76 20 10",
    "sg:postcode":"20570",
    "sg:province":"Guip\u00f9zcoa",
    "wof:name":"Maiztegui Mugica Antonio",
    "wof:placetype":"venue"
},
  "geometry": {"coordinates":[-2.4136209488,43.1186485291],"type":"Point"}
}