{
  "type": "Feature",
  "properties": {
    "addr:full":"Calle de Comunidad De Madrid (de La), 24 Fuenlabrada Madrid 28944",
    "addr:postcode":"24;28944",
    "addr:street":"Calle De Comunidad",
    "iso:country":"ES",
    "sg:address":"Calle de Comunidad De Madrid (de La), 24",
    "sg:city":"Fuenlabrada",
    "sg:orig_category":"Internados & Ense\u00d1anza Privada",
    "sg:phone":"+34 916 06 89 05",
    "sg:postcode":"28944",
    "sg:province":"Madrid",
    "wof:name":"Colegio Virgen De La Vega S.l.",
    "wof:placetype":"venue"
},
  "geometry": {"coordinates":[-3.7945303917,40.2792282104],"type":"Point"}
}