{
  "type": "Feature",
  "properties": {
    "iso:country":"ES",
    "sg:address":"Calle de San Juan, 14",
    "sg:city":"Alsasua",
    "sg:orig_category":"M\u00c9dicos: Pediatr\u00cda. Enfermedades De Los Ni\u00d1os",
    "sg:phone":"+34 948 56 28 51",
    "sg:postcode":"31800",
    "sg:province":"Navarra",
    "wof:name":"Perez Orive Jose Luis",
    "wof:placetype":"venue"
},
  "geometry": {"coordinates":[-2.1703112125,42.8960456848],"type":"Point"}
}