{
  "type": "Feature",
  "properties": {
    "addr:full":"Carretera Morrot, 111 Olot Girona 17800",
    "addr:housenumber":"111",
    "addr:postcode":"17800",
    "addr:street":"Carretera Morrot",
    "iso:country":"ES",
    "sg:address":"Carretera Morrot, 111",
    "sg:city":"Olot",
    "sg:orig_category":"Mec\u00c1nico Del Autom\u00d3vil",
    "sg:phone":"+34 972 26 85 29",
    "sg:postcode":"17800",
    "sg:province":"Girona",
    "wof:name":"Serrat Masdeu Luis",
    "wof:placetype":"venue"
},
  "geometry": {"coordinates":[2.4849140644,42.1912879944],"type":"Point"}
}