{
  "type": "Feature",
  "properties": {
    "iso:country":"ES",
    "sg:address":"Calle de Ramon J, 9",
    "sg:city":"Huesca",
    "sg:orig_category":"M\u00c9dicos: Foniatr\u00cda Y Logopedia",
    "sg:phone":"+34 974 22 77 83",
    "sg:postcode":"22005",
    "sg:province":"Huesca",
    "wof:name":"Asociacion San Francisco De Sales De Hipoacusicos",
    "wof:placetype":"venue"
},
  "geometry": {"coordinates":[-0.4030793905,42.1350288391],"type":"Point"}
}