{
  "type": "Feature",
  "properties": {
    "addr:full":"Carrer de La Rambla, 10 Barcelona Barcelona 08002",
    "addr:housenumber":"10",
    "addr:postcode":"08002",
    "addr:street":"Carrer De La Rambla",
    "iso:country":"ES",
    "sg:address":"Carrer de La Rambla, 10",
    "sg:city":"Barcelona",
    "sg:orig_category":"Agencias De Viajes",
    "sg:phone":"+34 933 17 20 98",
    "sg:postcode":"08002",
    "sg:province":"Barcelona",
    "sg:website":"www.viajesiberia.com",
    "wof:name":"Viajes Iberia S.a.",
    "wof:placetype":"venue"
},
  "geometry": {"coordinates":[2.1766529083,41.3773765564],"type":"Point"}
}