{
  "type": "Feature",
  "properties": {
    "addr:full":"Carrer de Jaume Fabra, 11 Barcelona Barcelona 08004",
    "addr:housenumber":"11",
    "addr:postcode":"08004",
    "addr:street":"Carrer De Jaume Fabra",
    "iso:country":"ES",
    "sg:address":"Carrer de Jaume Fabra, 11",
    "sg:city":"Barcelona",
    "sg:orig_category":"Empresas De Carpinter\u00cda",
    "sg:phone":"+34 934 43 14 75",
    "sg:postcode":"08004",
    "sg:province":"Barcelona",
    "wof:name":"Iberomed 64 S.l.",
    "wof:placetype":"venue"
},
  "geometry": {"coordinates":[2.1599309444,41.3743019104],"type":"Point"}
}