{
  "type": "Feature",
  "properties": {
    "iso:country":"ES",
    "sg:address":"Rua Parque De San Lazaro, 10",
    "sg:city":"Ourense",
    "sg:orig_category":"Hoteles",
    "sg:phone":"+34 988 23 35 14",
    "sg:postcode":"32003",
    "sg:province":"Ourense",
    "wof:name":"Miguez Gonzalez Santiago",
    "wof:placetype":"venue"
},
  "geometry": {"coordinates":[-7.8629989624,42.3407096863],"type":"Point"}
}