{
  "type": "Feature",
  "properties": {
    "iso:country":"ES",
    "sg:address":"Calle de Pedro Velasco, 52",
    "sg:city":"Vitigudino",
    "sg:orig_category":"Alimentaci\u00d3n General (al Por Mayor)",
    "sg:phone":"+34 923 50 00 59",
    "sg:postcode":"37210",
    "sg:province":"Salamanca",
    "wof:name":"Hermanos Perez Sanchez S. A.",
    "wof:placetype":"venue"
},
  "geometry": {"coordinates":[-6.4321489334,41.0089607239],"type":"Point"}
}