{
  "type": "Feature",
  "properties": {
    "addr:full":"Calle de Chilla, S/n Candeleda \u00c1vila 05480",
    "addr:housenumber":"s / n",
    "addr:postcode":"05480",
    "addr:street":"Calle De Chilla",
    "iso:country":"ES",
    "sg:address":"Calle de Chilla, S/n",
    "sg:city":"Candeleda",
    "sg:orig_category":"Sanatorios M\u00c9dico",
    "sg:phone":"+34 920 38 09 70",
    "sg:postcode":"05480",
    "sg:province":"\u00c1vila",
    "wof:name":"Gerencia De Atencion Primaria De Avila",
    "wof:placetype":"venue"
},
  "geometry": {"coordinates":[-5.2432208061,40.1542472839],"type":"Point"}
}