{
  "type": "Feature",
  "properties": {
    "addr:full":"Ctra Norte Del, 217 Palmas De Gran Canaria Las Palmas 35013",
    "addr:housenumber":"217",
    "addr:postcode":"35013",
    "addr:street":"Ctra Norte Del",
    "iso:country":"ES",
    "sg:address":"Ctra Norte Del, 217",
    "sg:city":"Palmas De Gran Canaria",
    "sg:orig_category":"Comercio De Piezas De Recambio Y De Accesorios De Veh\u00cdculos, Veh\u00cdculos Industriales",
    "sg:phone":"+34 928 41 77 42",
    "sg:postcode":"35013",
    "sg:province":"Las Palmas",
    "wof:name":"Audio Sport S.c.p",
    "wof:placetype":"venue"
},
  "geometry": {"coordinates":[-15.4417381287,28.1009349823],"type":"Point"}
}