{
  "type": "Feature",
  "properties": {
    "iso:country":"ES",
    "sg:address":"Carr Sant Pere, 67",
    "sg:city":"Palafrugell",
    "sg:orig_category":"Papel (al Por Mayor)",
    "sg:phone":"+34 972 30 03 56",
    "sg:postcode":"17200",
    "sg:province":"Girona",
    "wof:name":"Font Mayol Enrique",
    "wof:placetype":"venue"
},
  "geometry": {"coordinates":[3.1602339745,41.9128837585],"type":"Point"}
}