{
  "type": "Feature",
  "properties": {
    "iso:country":"ES",
    "sg:address":"S Fernando, S/n",
    "sg:city":"S. Agustin-playa Ingles",
    "sg:orig_category":"Cajas De Ahorro",
    "sg:phone":"+34 928 76 38 23",
    "sg:postcode":"35100",
    "sg:province":"Las Palmas",
    "sg:website":"www.lacajadecanarias.es",
    "wof:name":"Caja Insular De Ahorros De Canarias",
    "wof:placetype":"venue"
},
  "geometry": {"coordinates":[-15.4397096634,28.1302204132],"type":"Point"}
}