{
  "type": "Feature",
  "properties": {
    "iso:country":"ES",
    "sg:address":"Calle de Moriles, 7",
    "sg:city":"Parla",
    "sg:orig_category":"Muebles Y Accesorios Para Cocinas Y Cuartos De Ba\u00d1o (al Por Menor)",
    "sg:phone":"+34 916 05 21 46",
    "sg:postcode":"28980",
    "sg:province":"Madrid",
    "wof:name":"Jimenez Martin Antonio",
    "wof:placetype":"venue"
},
  "geometry": {"coordinates":[-3.7643179893,40.2528839111],"type":"Point"}
}