{
  "type": "Feature",
  "properties": {
    "iso:country":"ES",
    "sg:address":"Florida Auzoa, 140",
    "sg:city":"Hernani",
    "sg:orig_category":"Ebanister\u00cda",
    "sg:phone":"+34 943 55 07 50",
    "sg:postcode":"20120",
    "sg:province":"Guip\u00f9zcoa",
    "wof:name":"Ebanisteria Aritza S.l.",
    "wof:placetype":"venue"
},
  "geometry": {"coordinates":[-1.9660259485,43.2711906433],"type":"Point"}
}