{
  "type": "Feature",
  "properties": {
    "addr:full":"Calle de Lagasca, 107 Madrid Madrid 28006",
    "addr:housenumber":"107",
    "addr:postcode":"28006",
    "addr:street":"Calle De Lagasca",
    "iso:country":"ES",
    "sg:address":"Calle de Lagasca, 107",
    "sg:city":"Madrid",
    "sg:orig_category":"Tapiceros Y Tapiceros",
    "sg:phone":"+34 915 63 35 67",
    "sg:postcode":"28006",
    "sg:province":"Madrid",
    "wof:name":"Uanaua Dise\u00f1o S.l.",
    "wof:placetype":"venue"
},
  "geometry": {"coordinates":[-3.6844451427,40.4346809387],"type":"Point"}
}