{
  "type": "Feature",
  "properties": {
    "iso:country":"ES",
    "sg:address":"Ctra Collblanc, 11",
    "sg:city":"Hospitalet Llobregat",
    "sg:orig_category":"Bisuter\u00cda, Joyer\u00cda, Relojer\u00cda (al Por Menor)",
    "sg:phone":"+34 934 40 30 23",
    "sg:postcode":"08903",
    "sg:province":"Barcelona",
    "wof:name":"Joyeria Manrique S.l.",
    "wof:placetype":"venue"
},
  "geometry": {"coordinates":[2.121062994,41.3755760193],"type":"Point"}
}