{
  "type": "Feature",
  "properties": {
    "addr:full":"Carrer de Nord, 60 Terrassa Barcelona 08221",
    "addr:housenumber":"60",
    "addr:postcode":"08221",
    "addr:street":"Carrer De Nord",
    "iso:country":"ES",
    "sg:address":"Carrer de Nord, 60",
    "sg:city":"Terrassa",
    "sg:orig_category":"Doctores En Medicina",
    "sg:phone":"+34 937 85 85 88",
    "sg:postcode":"08221",
    "sg:province":"Barcelona",
    "wof:name":"Sant Calpe Antonio",
    "wof:placetype":"venue"
},
  "geometry": {"coordinates":[2.0135281086,41.5668487549],"type":"Point"}
}