{
  "type": "Feature",
  "properties": {
    "addr:full":"Valencia, 5 Museros Valencia 46136",
    "addr:housenumber":"5",
    "addr:postcode":"46136",
    "addr:street":"Valencia",
    "iso:country":"ES",
    "sg:address":"Valencia, 5",
    "sg:city":"Museros",
    "sg:orig_category":"Centros Empresariales",
    "sg:phone":"+34 961 44 16 37",
    "sg:postcode":"46136",
    "sg:province":"Valencia",
    "wof:name":"Alcover Sanchez Nieves",
    "wof:placetype":"venue"
},
  "geometry": {"coordinates":[-0.3423517942,39.5625114441],"type":"Point"}
}