{
  "type": "Feature",
  "properties": {
    "iso:country":"ES",
    "sg:address":"Pase San Gregorio, 91",
    "sg:city":"Puertollano",
    "sg:orig_category":"Reposter\u00cdas",
    "sg:phone":"+34 926 42 88 28",
    "sg:postcode":"13500",
    "sg:province":"Ciudad Real",
    "wof:name":"Pancarrion Puertollano S.l.",
    "wof:placetype":"venue"
},
  "geometry": {"coordinates":[-4.1093988419,38.6933097839],"type":"Point"}
}