{
  "type": "Feature",
  "properties": {
    "addr:full":"Av Roca Grossa, 85 Lloret Mar Girona 17310",
    "addr:housenumber":"85",
    "addr:postcode":"17310",
    "addr:street":"Av Roca Grossa",
    "iso:country":"ES",
    "sg:address":"Av Roca Grossa, 85",
    "sg:city":"Lloret Mar",
    "sg:orig_category":"Electricidad, Electr\u00d3nica: Material Y Suministros (al Por Mayor)",
    "sg:phone":"+34 972 36 01 21",
    "sg:postcode":"17310",
    "sg:province":"Girona",
    "wof:name":"Magic Park Lloret S.l.",
    "wof:placetype":"venue"
},
  "geometry": {"coordinates":[2.8510398865,41.7112197876],"type":"Point"}
}