{
  "type": "Feature",
  "properties": {
    "addr:full":"Carrer de Cisa, 24 Poblenou Barcelona 08202",
    "addr:housenumber":"24",
    "addr:postcode":"08202",
    "addr:street":"Carrer De Cisa",
    "iso:country":"ES",
    "sg:address":"Carrer de Cisa, 24",
    "sg:city":"Poblenou",
    "sg:orig_category":"Molduras, Junquillos, Listones Y Molduras Perforadas",
    "sg:phone":"+34 937 27 57 01",
    "sg:postcode":"08202",
    "sg:province":"Barcelona",
    "wof:name":"Pascual Delgado Francisco",
    "wof:placetype":"venue"
},
  "geometry": {"coordinates":[2.1292788982,41.5614433289],"type":"Point"}
}