{
  "type": "Feature",
  "properties": {
    "iso:country":"ES",
    "sg:address":"Carrer de Sant Ramon, 21",
    "sg:city":"Cardedeu",
    "sg:orig_category":"Delegados, Agentes De Tr\u00c1nsito, Auxiliares De Transporte Internacional",
    "sg:phone":"+34 938 45 42 78",
    "sg:postcode":"08440",
    "sg:province":"Barcelona",
    "wof:name":"Pocurull Garriga Salvador",
    "wof:placetype":"venue"
},
  "geometry": {"coordinates":[2.3570930958,41.6387329102],"type":"Point"}
}