{
  "type": "Feature",
  "properties": {
    "iso:country":"ES",
    "sg:address":"Calle de Cipres, S/n",
    "sg:city":"Poligono Industrial De Arinaga",
    "sg:orig_category":"Agentes, Concesionarios Y Sucursales De Veh\u00cdculos",
    "sg:phone":"+34 928 79 37 38",
    "sg:postcode":"35118",
    "sg:province":"Las Palmas",
    "wof:name":"Azudautos S.l.",
    "wof:placetype":"venue"
},
  "geometry": {"coordinates":[-15.3927698135,27.8557987213],"type":"Point"}
}