{
  "type": "Feature",
  "properties": {
    "iso:country":"ES",
    "sg:address":"Pol Ind Fadrell, 88",
    "sg:city":"Castello Plana",
    "sg:orig_category":"Fabricaci\u00d3n De Distribuidores Autom\u00c1ticos",
    "sg:phone":"+34 964 24 37 00",
    "sg:postcode":"12005",
    "sg:province":"Castell\u00f3n",
    "wof:name":"Gesvending S.l.",
    "wof:placetype":"venue"
},
  "geometry": {"coordinates":[-0.0570270009,39.9575424194],"type":"Point"}
}