{
  "type": "Feature",
  "properties": {
    "iso:country":"ES",
    "sg:address":"Calle de San Luis, 8",
    "sg:city":"Campo Criptana",
    "sg:orig_category":"Promotores Constructores",
    "sg:phone":"+34 926 56 34 67",
    "sg:postcode":"13610",
    "sg:province":"Ciudad Real",
    "wof:name":"Agrocrip S.l.",
    "wof:placetype":"venue"
},
  "geometry": {"coordinates":[-3.1332068443,39.4031066895],"type":"Point"}
}