{
  "type": "Feature",
  "properties": {
    "addr:full":"Luga Trema\u00d1es (juveria), 205 Gijon Asturias 33211",
    "addr:housenumber":"205",
    "addr:postcode":"33211",
    "iso:country":"ES",
    "sg:address":"Luga Trema\u00d1es (juveria), 205",
    "sg:city":"Gijon",
    "sg:orig_category":"Ferreter\u00cda (diversos)",
    "sg:phone":"+34 985 32 28 89",
    "sg:postcode":"33211",
    "sg:province":"Asturias",
    "wof:name":"Manuel Feito Lana S.l.",
    "wof:placetype":"venue"
},
  "geometry": {"coordinates":[-5.6863942146,43.5233383179],"type":"Point"}
}