{
  "type": "Feature",
  "properties": {
    "iso:country":"ES",
    "sg:address":"Julio Urkijo Etorbidea, 22",
    "sg:city":"Azkoitia",
    "sg:orig_category":"Peluquer\u00cdas, Peluquer\u00cda Mixta",
    "sg:phone":"+34 943 02 69 63",
    "sg:postcode":"20720",
    "sg:province":"Guip\u00f9zcoa",
    "wof:name":"Abigail Moliner Y Otra, C.b.",
    "wof:placetype":"venue"
},
  "geometry": {"coordinates":[-2.306498,43.176098],"type":"Point"}
}