{
  "type": "Feature",
  "properties": {
    "iso:country":"ES",
    "sg:address":"Carrer de Carders, 4",
    "sg:city":"Barcelona",
    "sg:orig_category":"Quincaller\u00cda (al Por Mayor)",
    "sg:phone":"+34 933 19 66 05",
    "sg:postcode":"08003",
    "sg:province":"Barcelona",
    "sg:website":"www.aubertsa.com",
    "wof:name":"Aubert S. A.",
    "wof:placetype":"venue"
},
  "geometry": {"coordinates":[2.1799240112,41.3858642578],"type":"Point"}
}