{
  "type": "Feature",
  "properties": {
    "addr:full":"Avda Alcalde Diaz Saavedra Navarro, 38 Palmas De Gran Canaria Las Palmas 35001",
    "addr:postcode":"35001",
    "addr:street":"Avda Alcalde Diaz Saavedra Navarro 38",
    "iso:country":"ES",
    "sg:address":"Avda Alcalde Diaz Saavedra Navarro, 38",
    "sg:city":"Palmas De Gran Canaria",
    "sg:orig_category":"Cl\u00cdnicas Dentales",
    "sg:phone":"+34 928 33 18 95",
    "sg:postcode":"35001",
    "sg:province":"Las Palmas",
    "wof:name":"Medina Cuevas Jose Luis",
    "wof:placetype":"venue"
},
  "geometry": {"coordinates":[-15.4121608734,28.0976467133],"type":"Point"}
}