{
  "type": "Feature",
  "properties": {
    "addr:full":"Ctra Lomo Blanco, 13 Lomo Blanco Las Palmas 35015",
    "addr:housenumber":"13",
    "addr:postcode":"35015",
    "addr:street":"Ctra Lomo Blanco;Lomo Blanco Las",
    "iso:country":"ES",
    "sg:address":"Ctra Lomo Blanco, 13",
    "sg:city":"Lomo Blanco",
    "sg:orig_category":"Carnicer\u00cdas, Carnicer\u00cdas",
    "sg:phone":"+34 928 43 03 98",
    "sg:postcode":"35015",
    "sg:province":"Las Palmas",
    "wof:name":"Sanchez Hernandez Milagros",
    "wof:placetype":"venue"
},
  "geometry": {"coordinates":[-15.4232616425,28.095746994],"type":"Point"}
}