{
  "type": "Feature",
  "properties": {
    "addr:full":"Pase Alameda, 34 Valencia Valencia 46023",
    "addr:housenumber":"34",
    "addr:postcode":"46023",
    "addr:street":"Alameda",
    "iso:country":"ES",
    "sg:address":"Pase Alameda, 34",
    "sg:city":"Valencia",
    "sg:orig_category":"Arquitectos",
    "sg:phone":"+34 963 37 21 41",
    "sg:postcode":"46023",
    "sg:province":"Valencia",
    "wof:name":"Elipe Maicas Jose Carlos",
    "wof:placetype":"venue"
},
  "geometry": {"coordinates":[-0.3594669998,39.4657287598],"type":"Point"}
}