{
  "type": "Feature",
  "properties": {
    "iso:country":"ES",
    "sg:address":"Poli Industrial Las Casas, S/n",
    "sg:city":"Soria",
    "sg:orig_category":"Alimentaci\u00d3n General (al Por Menor)",
    "sg:phone":"+34 975 22 53 29",
    "sg:postcode":"42005",
    "sg:province":"Soria",
    "wof:name":"Distribuciones Palacios S. A.",
    "wof:placetype":"venue"
},
  "geometry": {"coordinates":[-2.4691669941,41.7646598816],"type":"Point"}
}