{
  "type": "Feature",
  "properties": {
    "iso:country":"ES",
    "sg:address":"Campo De La Feria, 73",
    "sg:city":"Laracha",
    "sg:orig_category":"Empresas De Carpinter\u00cda De Madera",
    "sg:phone":"+34 981 60 52 52",
    "sg:postcode":"15145",
    "sg:province":"La Coru\u00f1a",
    "wof:name":"Lois Bocija Amelia",
    "wof:placetype":"venue"
},
  "geometry": {"coordinates":[-8.5813436508,43.2482681274],"type":"Point"}
}