{
  "type": "Feature",
  "properties": {
    "iso:country":"ES",
    "sg:address":"Calle de San Andres, 16",
    "sg:city":"Teruel",
    "sg:orig_category":"Centros Empresariales",
    "sg:phone":"+34 978 61 10 41",
    "sg:postcode":"44001",
    "sg:province":"Teruel",
    "wof:name":"Comunidad De Regantes",
    "wof:placetype":"venue"
},
  "geometry": {"coordinates":[-1.1062330008,40.34141922],"type":"Point"}
}