{
  "type": "Feature",
  "properties": {
    "addr:full":"Avda Domingo Bueno, 8 Pontenova Pontevedra 36400",
    "addr:housenumber":"8",
    "addr:postcode":"36400",
    "addr:street":"Avda Domingo Bueno",
    "iso:country":"ES",
    "sg:address":"Avda Domingo Bueno, 8",
    "sg:city":"Pontenova",
    "sg:orig_category":"Procuradores",
    "sg:phone":"+34 986 33 89 25",
    "sg:postcode":"36400",
    "sg:province":"Pontevedra",
    "wof:name":"Varela Gonzalez Francisco Javier",
    "wof:placetype":"venue"
},
  "geometry": {"coordinates":[-8.6179990768,42.1610298157],"type":"Point"}
}