{
  "type": "Feature",
  "properties": {
    "addr:full":"Calle de Natalio Rivas, 20 Adra Almer\u00eda 04770",
    "addr:housenumber":"20",
    "addr:postcode":"04770",
    "addr:street":"Calle De Natalio Rivas;Almeri\u0301A",
    "iso:country":"ES",
    "sg:address":"Calle de Natalio Rivas, 20",
    "sg:city":"Adra",
    "sg:orig_category":"Alquiler De Apartamentos",
    "sg:phone":"+34 950 40 07 89",
    "sg:postcode":"04770",
    "sg:province":"Almer\u00eda",
    "wof:name":"Perez Roldan Ramon",
    "wof:placetype":"venue"
},
  "geometry": {"coordinates":[-3.0149190426,36.7487258911],"type":"Point"}
}