{
  "type": "Feature",
  "properties": {
    "addr:full":"Calle de Conde De Pe\u00d1alver, 22 Madrid Madrid 28006",
    "addr:housenumber":"22",
    "addr:postcode":"madrid;28006",
    "addr:street":"Calle De Conde De Pen\u0303Alver",
    "iso:country":"ES",
    "sg:address":"Calle de Conde De Pe\u00d1alver, 22",
    "sg:city":"Madrid",
    "sg:orig_category":"Fabricaci\u00d3n De Sobres, Bolsas Y Fundas",
    "sg:phone":"+34 914 02 77 56",
    "sg:postcode":"28006",
    "sg:province":"Madrid",
    "wof:name":"Aplauso Calzados, S.l.",
    "wof:placetype":"venue"
},
  "geometry": {"coordinates":[-3.675498724,40.427406311],"type":"Point"}
}