{
  "type": "Feature",
  "properties": {
    "addr:full":"Avda Doctor Meca, 75 Puerto Mazarron Murcia 30860",
    "addr:housenumber":"75",
    "addr:postcode":"30860",
    "addr:street":"Avda Doctor Meca",
    "iso:country":"ES",
    "sg:address":"Avda Doctor Meca, 75",
    "sg:city":"Puerto Mazarron",
    "sg:orig_category":"Ingenier\u00cda, Centros De Estudios (diversos)",
    "sg:phone":"+34 968 15 32 56",
    "sg:postcode":"30860",
    "sg:province":"Murcia",
    "wof:name":"Jopuve 2003 S.l.",
    "wof:placetype":"venue"
},
  "geometry": {"coordinates":[-1.261204958,37.5673561096],"type":"Point"}
}