{
  "type": "Feature",
  "properties": {
    "addr:full":"Cmno Moncada, 52 Valencia Valencia 46025",
    "addr:housenumber":"52",
    "addr:postcode":"46025",
    "addr:street":"Cmno Moncada",
    "iso:country":"ES",
    "sg:address":"Cmno Moncada, 52",
    "sg:city":"Valencia",
    "sg:orig_category":"Restaurantes: Restauraci\u00d3n R\u00c1pida Y Autoservicio",
    "sg:phone":"+34 963 65 36 58",
    "sg:postcode":"46025",
    "sg:province":"Valencia",
    "wof:name":"Huang Ou Zhangyi",
    "wof:placetype":"venue"
},
  "geometry": {"coordinates":[-0.3787840009,39.4917869568],"type":"Point"}
}