{
  "type": "Feature",
  "properties": {
    "addr:full":"Carrer de Avellaner, 5 Cornella Llobregat Barcelona 08940",
    "addr:housenumber":"5",
    "addr:postcode":"08940",
    "addr:street":"Carrer De Avellaner",
    "iso:country":"ES",
    "sg:address":"Carrer de Avellaner, 5",
    "sg:city":"Cornella Llobregat",
    "sg:orig_category":"Peluquer\u00cdas, Peluquer\u00cda Mixta",
    "sg:phone":"+34 933 75 16 61",
    "sg:postcode":"08940",
    "sg:province":"Barcelona",
    "wof:name":"Lagares Rodriguez Luis",
    "wof:placetype":"venue"
},
  "geometry": {"coordinates":[2.0808610916,41.3649559021],"type":"Point"}
}