{
  "type": "Feature",
  "properties": {
    "addr:full":"Pg Paisos Catalans, 71 Salt Girona 17190",
    "addr:housenumber":"71",
    "addr:postcode":"17190",
    "addr:street":"Pg Paisos Catalans",
    "iso:country":"ES",
    "sg:address":"Pg Paisos Catalans, 71",
    "sg:city":"Salt",
    "sg:orig_category":"Farmacias",
    "sg:phone":"+34 972 23 77 04",
    "sg:postcode":"17190",
    "sg:province":"Girona",
    "wof:name":"Ordis Trulls Olga",
    "wof:placetype":"venue"
},
  "geometry": {"coordinates":[2.7875010967,41.9720344543],"type":"Point"}
}