{
  "type": "Feature",
  "properties": {
    "addr:full":"Avda Fragoso, 36 Vigo Pontevedra 36210",
    "addr:housenumber":"36",
    "addr:postcode":"36210",
    "addr:street":"Avda Fragoso",
    "iso:country":"ES",
    "sg:address":"Avda Fragoso, 36",
    "sg:city":"Vigo",
    "sg:orig_category":"Art\u00cdculos De Decoraci\u00d3n",
    "sg:phone":"+34 986 29 42 52",
    "sg:postcode":"36210",
    "sg:province":"Pontevedra",
    "wof:name":"Enxebre Decoracion S. L.",
    "wof:placetype":"venue"
},
  "geometry": {"coordinates":[-8.7346715927,42.2173194885],"type":"Point"}
}