{
  "type": "Feature",
  "properties": {
    "iso:country":"ES",
    "sg:address":"Calle de Virgen De La Roca, 9",
    "sg:city":"Madrid",
    "sg:orig_category":"Fotograf\u00cda Y Cine: Aparatos, Pel\u00cdculas Y Accesorios (al Por Menor)",
    "sg:phone":"+34 913 61 36 40",
    "sg:postcode":"28027",
    "sg:province":"Madrid",
    "wof:name":"Tevicinsa S. A.",
    "wof:placetype":"venue"
},
  "geometry": {"coordinates":[-3.6592431068,40.434425354],"type":"Point"}
}