{
  "type": "Feature",
  "properties": {
    "iso:country":"ES",
    "sg:address":"Carrer de Juli Garreta, 3",
    "sg:city":"Molins Rei",
    "sg:orig_category":"Agentes, Concesionarios Y Sucursales De Veh\u00cdculos",
    "sg:phone":"+34 936 68 08 95",
    "sg:postcode":"08750",
    "sg:province":"Barcelona",
    "sg:website":"www.automatrac.com",
    "wof:name":"Montero Allue Eduardo",
    "wof:placetype":"venue"
},
  "geometry": {"coordinates":[2.0241339207,41.4065055847],"type":"Point"}
}