{
  "type": "Feature",
  "properties": {
    "addr:full":"Ctra. Valencia, 65 Tortosa Tarragona 43500",
    "addr:housenumber":"65",
    "addr:postcode":"43500",
    "addr:street":"Ctra. Valencia",
    "iso:country":"ES",
    "sg:address":"Ctra. Valencia, 65",
    "sg:city":"Tortosa",
    "sg:orig_category":"Muebles Y Decoraci\u00d3n De Jardines (fabricaci\u00d3n, Venta)",
    "sg:phone":"+34 977 50 07 84",
    "sg:postcode":"43500",
    "sg:province":"Tarragona",
    "wof:name":"Almacenes Gasco S.a.",
    "wof:placetype":"venue"
},
  "geometry": {"coordinates":[0.5112848282,40.8085174561],"type":"Point"}
}