{
  "type": "Feature",
  "properties": {
    "iso:country":"ES",
    "sg:address":"Rua Luis Vidal Rocha, 1",
    "sg:city":"Sanxenxo",
    "sg:orig_category":"Ropa Para Ni\u00d1os (al Por Menor)",
    "sg:phone":"+34 986 69 17 41",
    "sg:postcode":"36960",
    "sg:province":"Pontevedra",
    "wof:name":"Pi\u00f1eiro Perez Javier",
    "wof:placetype":"venue"
},
  "geometry": {"coordinates":[-8.8096094131,42.4020881653],"type":"Point"}
}