{
  "type": "Feature",
  "properties": {
    "addr:full":"Calle de Amadeo Vives (de), 6 Boadilla Del Monte Madrid 28660",
    "addr:housenumber":"6",
    "addr:postcode":"28660",
    "addr:street":"Calle De Amadeo Vives De",
    "iso:country":"ES",
    "sg:address":"Calle de Amadeo Vives (de), 6",
    "sg:city":"Boadilla Del Monte",
    "sg:orig_category":"Agencias Y Agentes Comerciales, Representantes",
    "sg:phone":"+34 916 32 00 76",
    "sg:postcode":"28660",
    "sg:province":"Madrid",
    "wof:name":"De La Due\u00f1a Moreno Miguel",
    "wof:placetype":"venue"
},
  "geometry": {"coordinates":[-3.8843774796,40.40051651],"type":"Point"}
}