{
  "type": "Feature",
  "properties": {
    "addr:full":"Seixeda, 5 Sada La Coru\u00f1a 15160",
    "addr:housenumber":"5",
    "addr:postcode":"15160",
    "addr:street":"Seixeda;La",
    "iso:country":"ES",
    "sg:address":"Seixeda, 5",
    "sg:city":"Sada",
    "sg:orig_category":"Centros Empresariales",
    "sg:phone":"+34 981 62 29 23",
    "sg:postcode":"15160",
    "sg:province":"La Coru\u00f1a",
    "wof:name":"Axuram S.l.",
    "wof:placetype":"venue"
},
  "geometry": {"coordinates":[-8.2682914734,43.3461761475],"type":"Point"}
}