{
  "type": "Feature",
  "properties": {
    "addr:full":"Calle de Artesano Pepe Marin, 4 Chiclana De La Frontera C\u00e1diz 11130",
    "addr:housenumber":"4",
    "addr:postcode":"11130",
    "addr:street":"Calle De;Pepe Marin",
    "iso:country":"ES",
    "sg:address":"Calle de Artesano Pepe Marin, 4",
    "sg:city":"Chiclana De La Frontera",
    "sg:orig_category":"Congelados: Productos Alimentarios (al Por Menor)",
    "sg:phone":"+34 956 40 43 05",
    "sg:postcode":"11130",
    "sg:province":"C\u00e1diz",
    "sg:website":"www.procosur.com",
    "wof:name":"Procosur S.a.",
    "wof:placetype":"venue"
},
  "geometry": {"coordinates":[-6.1490616798,36.4201774597],"type":"Point"}
}