{
  "type": "Feature",
  "properties": {
    "iso:country":"ES",
    "sg:address":"La Andaluza, 4",
    "sg:city":"Montilla",
    "sg:orig_category":"Procuradores",
    "sg:phone":"+34 957 65 44 27",
    "sg:postcode":"14550",
    "sg:province":"C\u00f3rdoba",
    "wof:name":"Hidalgo Trapero Francisco Solano",
    "wof:placetype":"venue"
},
  "geometry": {"coordinates":[-4.6395897865,37.588142395],"type":"Point"}
}