{
  "type": "Feature",
  "properties": {
    "iso:country":"ES",
    "sg:address":"Calle de Nu\u00d1ez De Balboa (de), 8",
    "sg:city":"Talayuelas",
    "sg:classifiers":[
        {
            "category":"Taxi",
            "type":"Transportation"
        }
    ],
    "sg:phone":"+34 969 36 32 45",
    "sg:postcode":"16320",
    "sg:province":"Cuenca",
    "wof:name":"Llopis Vidal Juan Antonio",
    "wof:placetype":"venue"
},
  "geometry": {"coordinates":[-1.28115201,39.8486099243],"type":"Point"}
}