{
  "type": "Feature",
  "properties": {
    "addr:full":"Cami Vileta (la), 123 Vileta Islas Baleares 07011",
    "addr:housenumber":"123",
    "addr:postcode":"07011",
    "addr:street":"Vileta;Vileta Islas",
    "iso:country":"ES",
    "sg:address":"Cami Vileta (la), 123",
    "sg:city":"Vileta",
    "sg:orig_category":"Carnicer\u00cdas, Carnicer\u00cdas",
    "sg:phone":"+34 971 79 28 27",
    "sg:postcode":"07011",
    "sg:province":"Islas Baleares",
    "wof:name":"Herreros Armijo Pedro",
    "wof:placetype":"venue"
},
  "geometry": {"coordinates":[2.6207280159,39.5927886963],"type":"Point"}
}