{
  "type": "Feature",
  "properties": {
    "iso:country":"ES",
    "sg:address":"Avda Laredo, 23",
    "sg:city":"Fuenlabrada",
    "sg:orig_category":"Productos Qu\u00cdmicos (fabricaci\u00d3n, Al Por Mayor)",
    "sg:phone":"+34 916 00 02 50",
    "sg:postcode":"28946",
    "sg:province":"Madrid",
    "wof:name":"Comercial Feroca S.a.",
    "wof:placetype":"venue"
},
  "geometry": {"coordinates":[-3.7691209316,40.2770462036],"type":"Point"}
}