{
  "type": "Feature",
  "properties": {
    "addr:full":"Calle de Japon, S/n Alcorcon Madrid 28923",
    "addr:housenumber":"s / n",
    "addr:postcode":"28923",
    "addr:street":"Calle De Japon",
    "iso:country":"ES",
    "sg:address":"Calle de Japon, S/n",
    "sg:city":"Alcorcon",
    "sg:orig_category":"Electrodom\u00c9sticos (al Por Menor)",
    "sg:phone":"+34 916 11 02 20",
    "sg:postcode":"28923",
    "sg:province":"Madrid",
    "wof:name":"Rodriguez Mayo Jose Ramon",
    "wof:placetype":"venue"
},
  "geometry": {"coordinates":[-3.8184120655,40.3453941345],"type":"Point"}
}