{
  "type": "Feature",
  "properties": {
    "addr:full":"Plaz Obispo German Vega, S/n Amusco Palencia 34420",
    "addr:housenumber":"s / n",
    "addr:postcode":"34420",
    "iso:country":"ES",
    "sg:address":"Plaz Obispo German Vega, S/n",
    "sg:city":"Amusco",
    "sg:orig_category":"Iglesia Cat\u00d3lica",
    "sg:phone":"+34 979 80 20 51",
    "sg:postcode":"34420",
    "sg:province":"Palencia",
    "wof:name":"Diocesis Palencia",
    "wof:placetype":"venue"
},
  "geometry": {"coordinates":[-4.4702539444,42.1730384827],"type":"Point"}
}