{
  "type": "Feature",
  "properties": {
    "addr:full":"Ctra Agua Garcia, 65 Casas Altas Santa Cruz De Tenerife 38350",
    "addr:housenumber":"65",
    "addr:postcode":"38350",
    "addr:street":"Ctra Agua Garcia",
    "iso:country":"ES",
    "sg:address":"Ctra Agua Garcia, 65",
    "sg:city":"Casas Altas",
    "sg:orig_category":"Alimentaci\u00d3n General (al Por Menor)",
    "sg:phone":"+34 922 56 00 90",
    "sg:postcode":"38350",
    "sg:province":"Santa Cruz De Tenerife",
    "wof:name":"Chaves Bello Isabelino",
    "wof:placetype":"venue"
},
  "geometry": {"coordinates":[-16.4174289703,28.4756546021],"type":"Point"}
}