{
  "type": "Feature",
  "properties": {
    "addr:full":"Calle de Pio Xii, 2 Cullar-vega Granada 18195",
    "addr:housenumber":"2",
    "addr:postcode":"18195",
    "addr:street":"Calle De Pio Xii",
    "iso:country":"ES",
    "sg:address":"Calle de Pio Xii, 2",
    "sg:city":"Cullar-vega",
    "sg:orig_category":"Alimentaci\u00d3n General (al Por Menor)",
    "sg:phone":"+34 958 58 63 24",
    "sg:postcode":"18195",
    "sg:province":"Granada",
    "wof:name":"Espinola Lopez Francisca",
    "wof:placetype":"venue"
},
  "geometry": {"coordinates":[-3.6710820198,37.1535491943],"type":"Point"}
}