{
  "type": "Feature",
  "properties": {
    "iso:country":"ES",
    "sg:address":"Calle de Castellon De La Plana, 2",
    "sg:city":"Zaragoza",
    "sg:orig_category":"Inform\u00c1tica, Ofim\u00c1tica (estudios, Asesor\u00cda, Ingenier\u00cda, Formaci\u00d3n)",
    "sg:phone":"+34 976 27 91 56",
    "sg:postcode":"50007",
    "sg:province":"Zaragoza",
    "wof:name":"Arga Informatica S.l.",
    "wof:placetype":"venue"
},
  "geometry": {"coordinates":[-0.8876402974,41.6322784424],"type":"Point"}
}