{
  "type": "Feature",
  "properties": {
    "addr:full":"Avda Extremadura, 3 Navaconcejo C\u00e1ceres 10613",
    "addr:housenumber":"3",
    "addr:postcode":"10613",
    "addr:street":"Avda Extremadura;Ca\u0301Ceres",
    "iso:country":"ES",
    "sg:address":"Avda Extremadura, 3",
    "sg:city":"Navaconcejo",
    "sg:orig_category":"Quincaller\u00cda (al Por Menor)",
    "sg:phone":"+34 927 17 34 51",
    "sg:postcode":"10613",
    "sg:province":"C\u00e1ceres",
    "wof:name":"Amores Lopez Jose Carlos",
    "wof:placetype":"venue"
},
  "geometry": {"coordinates":[-5.8294453621,40.1779441833],"type":"Point"}
}