{
  "type": "Feature",
  "properties": {
    "addr:full":"Av Meridiana, 354 Barcelona Barcelona 08027",
    "addr:housenumber":"354",
    "addr:postcode":"08027",
    "addr:street":"Meridiana",
    "iso:country":"ES",
    "sg:address":"Av Meridiana, 354",
    "sg:city":"Barcelona",
    "sg:orig_category":"Promotores Constructores",
    "sg:phone":"+34 933 45 92 03",
    "sg:postcode":"08027",
    "sg:province":"Barcelona",
    "wof:name":"Uicesa Obras Y Construcciones S.a.",
    "wof:placetype":"venue"
},
  "geometry": {"coordinates":[2.1855049133,41.4271316528],"type":"Point"}
}