{
  "type": "Feature",
  "properties": {
    "iso:country":"ES",
    "sg:address":"Cno. Caminot, 22",
    "sg:city":"Valencia",
    "sg:orig_category":"Higiene, Belleza: Art\u00cdculos (al Por Menor)",
    "sg:phone":"+34 963 33 17 70",
    "sg:postcode":"46013",
    "sg:province":"Valencia",
    "wof:name":"Ferrer Puchades Francisco",
    "wof:placetype":"venue"
},
  "geometry": {"coordinates":[-0.3506270051,39.4390144348],"type":"Point"}
}