{
  "type": "Feature",
  "properties": {
    "iso:country":"ES",
    "sg:address":"Calle de Polvoranca, 39",
    "sg:city":"Alcorcon",
    "sg:orig_category":"Bancos",
    "sg:phone":"+34 916 44 22 69",
    "sg:postcode":"28923",
    "sg:province":"Madrid",
    "sg:website":"www.bancopopular.es",
    "wof:name":"Banco Popular Espa\u00f1ol",
    "wof:placetype":"venue"
},
  "geometry": {"coordinates":[-3.8156321049,40.3403205872],"type":"Point"}
}