{
  "type": "Feature",
  "properties": {
    "iso:country":"ES",
    "sg:address":"Avda Gasteiz, 46",
    "sg:city":"Vitoria-gasteiz",
    "sg:orig_category":"Ense\u00d1anza Variada",
    "sg:phone":"+34 945 24 98 70",
    "sg:postcode":"01008",
    "sg:province":"\u00c1lava",
    "wof:name":"Teknos S.l.",
    "wof:placetype":"venue"
},
  "geometry": {"coordinates":[-2.6812388897,42.8482666016],"type":"Point"}
}