{
  "type": "Feature",
  "properties": {
    "addr:full":"Urb Parque Los Nogales, S/n Alcala Henares Madrid 28805",
    "addr:postcode":"28805",
    "addr:street":"Urb;Los;S / N",
    "iso:country":"ES",
    "sg:address":"Urb Parque Los Nogales, S/n",
    "sg:city":"Alcala Henares",
    "sg:orig_category":"Librer\u00cdas",
    "sg:phone":"+34 918 89 33 66",
    "sg:postcode":"28805",
    "sg:province":"Madrid",
    "wof:name":"Cuellar Martinez Jose Maria De",
    "wof:placetype":"venue"
},
  "geometry": {"coordinates":[-3.3584439754,40.4921836853],"type":"Point"}
}