{
  "type": "Feature",
  "properties": {
    "iso:country":"ES",
    "sg:address":"Calle de Isla De Salvora, 1",
    "sg:city":"Estacion",
    "sg:orig_category":"Tiendas De Grano, Frutas Y Legumbres Secas (al Por Menor)",
    "sg:phone":"+34 918 50 39 94",
    "sg:postcode":"28400",
    "sg:province":"Madrid",
    "wof:name":"Martinez Obregon Eduardo",
    "wof:placetype":"venue"
},
  "geometry": {"coordinates":[-4.0100369453,40.618019104],"type":"Point"}
}