{
  "type": "Feature",
  "properties": {
    "addr:full":"Calle de Maria Luisa De Dios, 7 Granada Granada 18014",
    "addr:housenumber":"7",
    "addr:postcode":"18014",
    "addr:street":"Calle De Maria Luisa De Dios",
    "iso:country":"ES",
    "sg:address":"Calle de Maria Luisa De Dios, 7",
    "sg:city":"Granada",
    "sg:orig_category":"Laboratorios Y Cl\u00cdnicas Veterinarias",
    "sg:phone":"+34 958 27 19 78",
    "sg:postcode":"18014",
    "sg:province":"Granada",
    "wof:name":"Hospital Veterinario Al Sur S.l.",
    "wof:placetype":"venue"
},
  "geometry": {"coordinates":[-3.6070299149,37.1841964722],"type":"Point"}
}