{
  "type": "Feature",
  "properties": {
    "addr:full":"Calle de Puerto Navacerrada, 45 Nieves-el Lucero Madrid 28935",
    "addr:housenumber":"45",
    "addr:postcode":"28935",
    "addr:street":"Calle De Puerto Navacerrada;Nieves-El",
    "iso:country":"ES",
    "sg:address":"Calle de Puerto Navacerrada, 45",
    "sg:city":"Nieves-el Lucero",
    "sg:orig_category":"Electricidad: Instaladores",
    "sg:phone":"+34 916 16 48 39",
    "sg:postcode":"28935",
    "sg:province":"Madrid",
    "wof:name":"Sepreim Cb",
    "wof:placetype":"venue"
},
  "geometry": {"coordinates":[-3.9280939102,40.3081817627],"type":"Point"}
}