{
  "type": "Feature",
  "properties": {
    "addr:full":"Avda Cid (el), 38 Foios Valencia 46134",
    "addr:housenumber":"38",
    "addr:postcode":"46134",
    "addr:street":"Avda Cid El",
    "iso:country":"ES",
    "sg:address":"Avda Cid (el), 38",
    "sg:city":"Foios",
    "sg:orig_category":"V\u00c1lvulas",
    "sg:phone":"+34 961 49 94 28",
    "sg:postcode":"46134",
    "sg:province":"Valencia",
    "wof:name":"Valvulas Arco S.l.",
    "wof:placetype":"venue"
},
  "geometry": {"coordinates":[-0.3504649997,39.5393829346],"type":"Point"}
}