{
  "type": "Feature",
  "properties": {
    "iso:country":"ES",
    "sg:address":"Avda San Blas, 35",
    "sg:city":"Ateca",
    "sg:orig_category":"Alumbrados",
    "sg:phone":"+34 976 84 03 38",
    "sg:postcode":"50200",
    "sg:province":"Zaragoza",
    "wof:name":"Ilusol S.a.",
    "wof:placetype":"venue"
},
  "geometry": {"coordinates":[-1.7911709547,41.3303794861],"type":"Point"}
}