{
  "type": "Feature",
  "properties": {
    "iso:country":"ES",
    "sg:address":"Carr Font, 1",
    "sg:city":"Petra",
    "sg:orig_category":"Administraciones Regionales, Departamentales Y Locales",
    "sg:phone":"+34 971 83 00 00",
    "sg:postcode":"07520",
    "sg:province":"Islas Baleares",
    "wof:name":"Ajuntament De Petra",
    "wof:placetype":"venue"
},
  "geometry": {"coordinates":[3.1134505272,39.6149291992],"type":"Point"}
}