{
  "type": "Feature",
  "properties": {
    "iso:country":"ES",
    "sg:address":"Carrer de F. Rius I Taulet, 34",
    "sg:city":"Gava",
    "sg:orig_category":"Cerrajer\u00cda, Ferrallista",
    "sg:phone":"+34 936 35 50 20",
    "sg:postcode":"08850",
    "sg:province":"Barcelona",
    "wof:name":"Cierre Plus S.l.",
    "wof:placetype":"venue"
},
  "geometry": {"coordinates":[2.006759882,41.3035125732],"type":"Point"}
}