{
  "type": "Feature",
  "properties": {
    "iso:country":"ES",
    "sg:address":"Plaz Cruz Verde, 2",
    "sg:city":"Motril",
    "sg:orig_category":"Asesor\u00cda Sobre Comunicaci\u00d3n De Empresas",
    "sg:phone":"+34 958 60 55 61",
    "sg:postcode":"18600",
    "sg:province":"Granada",
    "wof:name":"Alcalde Rodriguez Carmen",
    "wof:placetype":"venue"
},
  "geometry": {"coordinates":[-3.5180242062,36.7452545166],"type":"Point"}
}