{
  "type": "Feature",
  "properties": {
    "addr:full":"Carr Vall D'aiora, S/n Pu\u00e7ol Valencia 46530",
    "addr:housenumber":"s",
    "addr:postcode":"46530",
    "addr:street":"Carr Vall D'Aiora;/ N",
    "iso:country":"ES",
    "sg:address":"Carr Vall D'aiora, S/n",
    "sg:city":"Pu\u00e7ol",
    "sg:orig_category":"Electricidad (montaje, Ensamblaje De Componentes)",
    "sg:phone":"+34 961 46 43 33",
    "sg:postcode":"46530",
    "sg:province":"Valencia",
    "wof:name":"R.m.a. Electric S.l.",
    "wof:placetype":"venue"
},
  "geometry": {"coordinates":[-0.3060989976,39.6175727844],"type":"Point"}
}