{
  "type": "Feature",
  "properties": {
    "iso:country":"ES",
    "sg:address":"Calle de Salas Pombo, 146",
    "sg:city":"Galinduste",
    "sg:orig_category":"Cr\u00cda De Bovinos",
    "sg:phone":"+34 923 39 14 17",
    "sg:postcode":"37785",
    "sg:province":"Salamanca",
    "wof:name":"Hermanos Martin Galinduste S.l.",
    "wof:placetype":"venue"
},
  "geometry": {"coordinates":[-5.5404391289,40.661151886],"type":"Point"}
}