{
  "type": "Feature",
  "properties": {
    "addr:full":"Calle de Federico Chueca, 23 Palmas De Gran Canaria Las Palmas 35013",
    "addr:housenumber":"23",
    "addr:postcode":"35013",
    "addr:street":"Calle De Federico Chueca",
    "iso:country":"ES",
    "sg:address":"Calle de Federico Chueca, 23",
    "sg:city":"Palmas De Gran Canaria",
    "sg:orig_category":"Empresarios",
    "sg:phone":"+34 928 42 75 41",
    "sg:postcode":"35013",
    "sg:province":"Las Palmas",
    "wof:name":"Santana Saez Domingo",
    "wof:placetype":"venue"
},
  "geometry": {"coordinates":[-15.4475469589,28.093120575],"type":"Point"}
}