{
  "type": "Feature",
  "properties": {
    "iso:country":"ES",
    "sg:address":"Calle de Fontanilla, 44",
    "sg:city":"Beas",
    "sg:orig_category":"Mec\u00c1nico Del Autom\u00d3vil",
    "sg:phone":"+34 959 30 90 26",
    "sg:postcode":"21630",
    "sg:province":"Huelva",
    "wof:name":"Velo Garrido Francisco",
    "wof:placetype":"venue"
},
  "geometry": {"coordinates":[-6.7931799889,37.4353027344],"type":"Point"}
}