{
  "type": "Feature",
  "properties": {
    "iso:country":"ES",
    "sg:address":"Calle de Mariano De Caceres, 9",
    "sg:city":"S. Nicolas Tolentino",
    "sg:orig_category":"Florister\u00cdas",
    "sg:phone":"+34 928 89 20 55",
    "sg:postcode":"35470",
    "sg:province":"Las Palmas",
    "wof:name":"Suarez Gonzalez Celina",
    "wof:placetype":"venue"
},
  "geometry": {"coordinates":[-15.7800836563,27.983839035],"type":"Point"}
}