{
  "type": "Feature",
  "properties": {
    "addr:full":"Calle de San Diego, 8 Gran Tarajal Las Palmas 35620",
    "addr:housenumber":"8",
    "addr:postcode":"35620",
    "addr:street":"Calle De San Diego;Palmas",
    "iso:country":"ES",
    "sg:address":"Calle de San Diego, 8",
    "sg:city":"Gran Tarajal",
    "sg:orig_category":"Bares, Piano",
    "sg:phone":"+34 928 16 50 34",
    "sg:postcode":"35620",
    "sg:province":"Las Palmas",
    "wof:name":"Ciber Fuert S.l.",
    "wof:placetype":"venue"
},
  "geometry": {"coordinates":[-14.0223922729,28.212392807],"type":"Point"}
}