{
  "type": "Feature",
  "properties": {
    "iso:country":"ES",
    "sg:address":"Carrer de Doctor Ramon I Cajal, 2",
    "sg:city":"Barri Maritim Sector Sanatori",
    "sg:orig_category":"Asesor\u00cdas Y Estudios Financieros",
    "sg:phone":"+34 977 69 14 64",
    "sg:postcode":"43700",
    "sg:province":"Tarragona",
    "wof:name":"Diagonal 445 S.a.",
    "wof:placetype":"venue"
},
  "geometry": {"coordinates":[1.5381799936,41.2216491699],"type":"Point"}
}