{
  "type": "Feature",
  "properties": {
    "addr:full":"Calle de Camino De Malaga, 33 Velez-malaga M\u00e1laga 29700",
    "addr:housenumber":"33",
    "addr:postcode":"29700",
    "addr:street":"Calle De Camino De Malaga",
    "iso:country":"ES",
    "sg:address":"Calle de Camino De Malaga, 33",
    "sg:city":"Velez-malaga",
    "sg:orig_category":"Ropa Para Caballeros (al Por Menor)",
    "sg:phone":"+34 952 50 23 00",
    "sg:postcode":"29700",
    "sg:province":"M\u00e1laga",
    "wof:name":"Fernandez Aragon Salvador",
    "wof:placetype":"venue"
},
  "geometry": {"coordinates":[-4.1033468246,36.7784080505],"type":"Point"}
}