{
  "type": "Feature",
  "properties": {
    "iso:country":"ES",
    "sg:address":"Calle de Muro, 2",
    "sg:city":"Palmas De Gran Canaria",
    "sg:orig_category":"Heladeros",
    "sg:phone":"+34 928 37 34 01",
    "sg:postcode":"35002",
    "sg:province":"Las Palmas",
    "wof:name":"Dominguez Melian Matias",
    "wof:placetype":"venue"
},
  "geometry": {"coordinates":[-15.4159069061,28.1022415161],"type":"Point"}
}