{
  "type": "Feature",
  "properties": {
    "addr:full":"G.v. Corts Catalanes, 140 Barcelona Barcelona 08038",
    "addr:housenumber":"140",
    "addr:postcode":"08038",
    "addr:street":"Catalanes",
    "iso:country":"ES",
    "sg:address":"G.v. Corts Catalanes, 140",
    "sg:city":"Barcelona",
    "sg:orig_category":"Cajas De Ahorro",
    "sg:phone":"+34 933 32 70 96",
    "sg:postcode":"08038",
    "sg:province":"Barcelona",
    "sg:website":"www.lacaixa.es",
    "wof:name":"Caixa D'estalvis I Pensions De Barcelona",
    "wof:placetype":"venue"
},
  "geometry": {"coordinates":[2.1343150139,41.3636131287],"type":"Point"}
}