{
  "type": "Feature",
  "properties": {
    "iso:country":"ES",
    "sg:address":"Calle de Ribera Del Genil, 10",
    "sg:city":"Granada",
    "sg:orig_category":"Agentes Generales De Seguros",
    "sg:phone":"+34 958 26 06 61",
    "sg:postcode":"18005",
    "sg:province":"Granada",
    "wof:name":"Sanchez Lopez Antonio",
    "wof:placetype":"venue"
},
  "geometry": {"coordinates":[-3.5979220867,37.1711997986],"type":"Point"}
}