{
  "type": "Feature",
  "properties": {
    "addr:full":"Rua Figueira, 1 Bocas Pontevedra 36613",
    "addr:housenumber":"1",
    "addr:postcode":"36613",
    "addr:street":"Rua Figueira",
    "iso:country":"ES",
    "sg:address":"Rua Figueira, 1",
    "sg:city":"Bocas",
    "sg:orig_category":"Motocicletas (agentes, Concesionarios)",
    "sg:phone":"+34 986 51 27 67",
    "sg:postcode":"36613",
    "sg:province":"Pontevedra",
    "wof:name":"Devesa Fernandez Maria Del Pilar",
    "wof:placetype":"venue"
},
  "geometry": {"coordinates":[-8.7695436478,42.6105308533],"type":"Point"}
}