{
  "type": "Feature",
  "properties": {
    "addr:full":"G.v. Fernando El Catolico, 8 Valencia Valencia 46008",
    "addr:housenumber":"8",
    "addr:postcode":"46008",
    "addr:street":"Fernando El Catolico",
    "iso:country":"ES",
    "sg:address":"G.v. Fernando El Catolico, 8",
    "sg:city":"Valencia",
    "sg:orig_category":"Arquitectos",
    "sg:phone":"+34 963 94 36 96",
    "sg:postcode":"46008",
    "sg:province":"Valencia",
    "wof:name":"Valdeolmillos Artiguez Javier",
    "wof:placetype":"venue"
},
  "geometry": {"coordinates":[-0.3844949901,39.4699172974],"type":"Point"}
}