{
  "type": "Feature",
  "properties": {
    "iso:country":"ES",
    "sg:address":"Aranerreka Kalea, 16",
    "sg:city":"Bergara",
    "sg:orig_category":"Peluqueros: De Se\u00d1oras",
    "sg:phone":"+34 943 76 40 17",
    "sg:postcode":"20570",
    "sg:province":"Guip\u00f9zcoa",
    "wof:name":"Tabares Delgado Ascension",
    "wof:placetype":"venue"
},
  "geometry": {"coordinates":[-2.4067559242,43.1195793152],"type":"Point"}
}