{
  "type": "Feature",
  "properties": {
    "addr:full":"Carrer de Elkano, 40 Barcelona Barcelona 08004",
    "addr:housenumber":"40",
    "addr:postcode":"08004",
    "addr:street":"Carrer De Elkano",
    "iso:country":"ES",
    "sg:address":"Carrer de Elkano, 40",
    "sg:city":"Barcelona",
    "sg:orig_category":"Cerrajer\u00cda, Ferrallista",
    "sg:phone":"+34 934 41 00 46",
    "sg:postcode":"08004",
    "sg:province":"Barcelona",
    "wof:name":"Franco Acosta Manuel",
    "wof:placetype":"venue"
},
  "geometry": {"coordinates":[2.1630589962,41.3733253479],"type":"Point"}
}