{
  "type": "Feature",
  "properties": {
    "iso:country":"ES",
    "sg:address":"Rua Rio Navea, 42",
    "sg:city":"Ourense",
    "sg:orig_category":"Negocio De Madera",
    "sg:phone":"+34 988 21 48 80",
    "sg:postcode":"32001",
    "sg:province":"Ourense",
    "wof:name":"Victorino Maderas S.c.",
    "wof:placetype":"venue"
},
  "geometry": {"coordinates":[-7.8696680069,42.3541526794],"type":"Point"}
}