{
  "type": "Feature",
  "properties": {
    "iso:country":"ES",
    "sg:address":"Carrer de Ramon Y Cajal, 3",
    "sg:city":"Sant Vicen\u00c7 Dels Horts",
    "sg:orig_category":"Tapicer\u00cdas",
    "sg:phone":"+34 936 76 96 07",
    "sg:postcode":"08620",
    "sg:province":"Barcelona",
    "wof:name":"Mayan Tapissats S.l",
    "wof:placetype":"venue"
},
  "geometry": {"coordinates":[2.0106129646,41.3890686035],"type":"Point"}
}