{
  "type": "Feature",
  "properties": {
    "addr:full":"Carrer de Major, 1 Riera Gaia Tarragona 43762",
    "addr:housenumber":"1",
    "addr:postcode":"43762",
    "addr:street":"Carrer De Major",
    "iso:country":"ES",
    "sg:address":"Carrer de Major, 1",
    "sg:city":"Riera Gaia",
    "sg:orig_category":"Carnicer\u00cdas, Carnicer\u00cdas",
    "sg:phone":"+34 977 65 50 06",
    "sg:postcode":"43762",
    "sg:province":"Tarragona",
    "wof:name":"Casas Sorde Jaime",
    "wof:placetype":"venue"
},
  "geometry": {"coordinates":[1.3608299494,41.1658706665],"type":"Point"}
}