{
  "type": "Feature",
  "properties": {
    "addr:full":"Avda Aragon, 18 Valencia Valencia 46021",
    "addr:housenumber":"18",
    "addr:postcode":"46021",
    "addr:street":"Avda Aragon",
    "iso:country":"ES",
    "sg:address":"Avda Aragon, 18",
    "sg:city":"Valencia",
    "sg:orig_category":"Inmobiliaria (agencias)",
    "sg:phone":"+34 963 93 20 32",
    "sg:postcode":"46021",
    "sg:province":"Valencia",
    "wof:name":"Estudio Terranova S.l.",
    "wof:placetype":"venue"
},
  "geometry": {"coordinates":[-0.3584629893,39.4697990417],"type":"Point"}
}