{
  "type": "Feature",
  "properties": {
    "iso:country":"ES",
    "sg:address":"Carrer de Major, 2",
    "sg:city":"Viladecans",
    "sg:orig_category":"Quincaller\u00cda (al Por Menor)",
    "sg:phone":"+34 936 58 04 42",
    "sg:postcode":"08840",
    "sg:province":"Barcelona",
    "wof:name":"Calbet S.l",
    "wof:placetype":"venue"
},
  "geometry": {"coordinates":[2.0193259716,41.3155784607],"type":"Point"}
}