{
  "type": "Feature",
  "properties": {
    "iso:country":"ES",
    "sg:address":"Ctra Tacoronte Tejina, 217",
    "sg:city":"Tacoronte",
    "sg:orig_category":"Reposter\u00cdas",
    "sg:phone":"+34 922 56 01 93",
    "sg:postcode":"38350",
    "sg:province":"Santa Cruz De Tenerife",
    "wof:name":"Exposito Perea Antonio",
    "wof:placetype":"venue"
},
  "geometry": {"coordinates":[-16.4109287262,28.4841403961],"type":"Point"}
}