{
  "type": "Feature",
  "properties": {
    "iso:country":"ES",
    "sg:address":"Carr. De Archidona Salinas, Km. 0185,0",
    "sg:city":"Archidona",
    "sg:orig_category":"Tubos Y Tuber\u00cdas De Goma Y Pl\u00c1stico (fabricaci\u00d3n, Al Por Mayor)",
    "sg:phone":"+34 952 71 70 10",
    "sg:postcode":"29300",
    "sg:province":"M\u00e1laga",
    "wof:name":"Plasticos I.m.a. S.a.",
    "wof:placetype":"venue"
},
  "geometry": {"coordinates":[-4.3881821632,37.0946998596],"type":"Point"}
}