{
  "type": "Feature",
  "properties": {
    "iso:country":"ES",
    "sg:address":"Calle de Don Ramon De La Cruz, 101",
    "sg:city":"Madrid",
    "sg:orig_category":"Librer\u00cdas",
    "sg:phone":"+34 914 02 48 24",
    "sg:postcode":"28006",
    "sg:province":"Madrid",
    "wof:name":"Garcia Martin Miguel",
    "wof:placetype":"venue"
},
  "geometry": {"coordinates":[-3.672440052,40.4285736084],"type":"Point"}
}