{
  "type": "Feature",
  "properties": {
    "iso:country":"ES",
    "sg:address":"Calle de Pinto, 41",
    "sg:city":"Parla",
    "sg:orig_category":"Frutas, Legumbres Frescas Y Tempranas (al Por Menor)",
    "sg:phone":"+34 916 99 25 01",
    "sg:postcode":"28980",
    "sg:province":"Madrid",
    "wof:name":"Jimenez Felipe Honorio",
    "wof:placetype":"venue"
},
  "geometry": {"coordinates":[-3.766605854,40.2394180298],"type":"Point"}
}