{
  "type": "Feature",
  "properties": {
    "iso:country":"ES",
    "sg:address":"Flassaders, 14",
    "sg:city":"Pol. Ind. Santiga",
    "sg:orig_category":"Aparatos, M\u00c1quinas Y Procedimientos En Industria Qu\u00cdmica",
    "sg:phone":"+34 937 18 17 00",
    "sg:postcode":"08130",
    "sg:province":"Barcelona",
    "sg:website":"www.lodige.es",
    "wof:name":"Lodige Espa\u00f1a S. A.",
    "wof:placetype":"venue"
},
  "geometry": {"coordinates":[2.1802799702,41.5371818542],"type":"Point"}
}