{
  "type": "Feature",
  "properties": {
    "addr:full":"Carrer de Sant Feliu, 17 Palma Islas Baleares 07012",
    "addr:housenumber":"17",
    "addr:postcode":"07012",
    "addr:street":"Carrer De Sant Feliu",
    "iso:country":"ES",
    "sg:address":"Carrer de Sant Feliu, 17",
    "sg:city":"Palma",
    "sg:orig_category":"Tapiceros Y Tapiceros",
    "sg:phone":"+34 971 71 25 47",
    "sg:postcode":"07012",
    "sg:province":"Islas Baleares",
    "wof:name":"Denario Dise\u00f1o Integral S.l.",
    "wof:placetype":"venue"
},
  "geometry": {"coordinates":[2.6446359158,39.5706710815],"type":"Point"}
}