{
  "type": "Feature",
  "properties": {
    "addr:full":"Carr Santa Anna, 20 Badalona Barcelona 08911",
    "addr:housenumber":"20",
    "addr:postcode":"08911",
    "addr:street":"Carr Santa Anna",
    "iso:country":"ES",
    "sg:address":"Carr Santa Anna, 20",
    "sg:city":"Badalona",
    "sg:orig_category":"Asociaciones Y Clubs Deportivos",
    "sg:phone":"+34 934 64 09 66",
    "sg:postcode":"08911",
    "sg:province":"Barcelona",
    "wof:name":"Serrano Cuestas Esteban",
    "wof:placetype":"venue"
},
  "geometry": {"coordinates":[2.2494280338,41.4473152161],"type":"Point"}
}