{
  "type": "Feature",
  "properties": {
    "addr:full":"C/ Capita Lagier, 9 Elche Alicante 03202",
    "addr:housenumber":"9",
    "addr:postcode":"03202",
    "addr:street":"C / Capita Lagier",
    "iso:country":"ES",
    "sg:address":"C/ Capita Lagier, 9",
    "sg:city":"Elche",
    "sg:orig_category":"Notarios",
    "sg:phone":"+34 965 45 09 59",
    "sg:postcode":"03202",
    "sg:province":"Alicante",
    "wof:name":"Olague Ruiz Luis Alonso",
    "wof:placetype":"venue"
},
  "geometry": {"coordinates":[-0.6955659986,38.2674293518],"type":"Point"}
}