{
  "type": "Feature",
  "properties": {
    "iso:country":"ES",
    "sg:address":"Calle de San Jose De Calasanz, 18",
    "sg:city":"Valencia",
    "sg:orig_category":"Molduras, Junquillos, Listones Y Molduras Perforadas",
    "sg:phone":"+34 963 85 50 02",
    "sg:postcode":"46008",
    "sg:province":"Valencia",
    "wof:name":"Tamarit Tamarit Luis",
    "wof:placetype":"venue"
},
  "geometry": {"coordinates":[-0.3883799911,39.4667396545],"type":"Point"}
}