{
  "type": "Feature",
  "properties": {
    "iso:country":"ES",
    "sg:address":"Calle de Cebreros, 101",
    "sg:city":"Madrid",
    "sg:orig_category":"Sociedades, Compa\u00d1\u00cdas Aseguradoras",
    "sg:phone":"+34 914 63 31 16",
    "sg:postcode":"28011",
    "sg:province":"Madrid",
    "sg:website":"www.cantelar.com",
    "wof:name":"Cantelar S.a. Correduria De Seguros",
    "wof:placetype":"venue"
},
  "geometry": {"coordinates":[-3.7534692287,40.4024925232],"type":"Point"}
}