{
  "type": "Feature",
  "properties": {
    "iso:country":"ES",
    "sg:address":"Calle de Libertad, 29",
    "sg:city":"Tias",
    "sg:orig_category":"Ropa Para Se\u00d1oras (al Por Menor)",
    "sg:phone":"+34 928 83 44 20",
    "sg:postcode":"35572",
    "sg:province":"Las Palmas",
    "wof:name":"Sociedad Neralba S.c.p",
    "wof:placetype":"venue"
},
  "geometry": {"coordinates":[-13.6519002914,28.9538669586],"type":"Point"}
}