{
  "type": "Feature",
  "properties": {
    "addr:full":"Carrer de Lope De Vega, 109 Barcelona Barcelona 08005",
    "addr:housenumber":"109",
    "addr:postcode":"08005",
    "addr:street":"Carrer De Lope De Vega",
    "iso:country":"ES",
    "sg:address":"Carrer de Lope De Vega, 109",
    "sg:city":"Barcelona",
    "sg:orig_category":"Molduras, Junquillos, Listones Y Molduras Perforadas",
    "sg:phone":"+34 933 07 51 31",
    "sg:postcode":"08005",
    "sg:province":"Barcelona",
    "wof:name":"Llorens Suarez Maria Luz",
    "wof:placetype":"venue"
},
  "geometry": {"coordinates":[2.2025918961,41.4050331116],"type":"Point"}
}