{
  "type": "Feature",
  "properties": {
    "addr:full":"Leyre-leire Kalea, 21 Iru\u00f1a Navarra 31003",
    "addr:housenumber":"21",
    "addr:postcode":"31003",
    "addr:street":"Leyre-Leire Kalea",
    "iso:country":"ES",
    "sg:address":"Leyre-leire Kalea, 21",
    "sg:city":"Iru\u00f1a",
    "sg:orig_category":"Abogados",
    "sg:phone":"+34 948 24 71 46",
    "sg:postcode":"31003",
    "sg:province":"Navarra",
    "wof:name":"Archanco Taberna Miguel Angel",
    "wof:placetype":"venue"
},
  "geometry": {"coordinates":[-1.6431862116,42.8117294312],"type":"Point"}
}