{
  "type": "Feature",
  "properties": {
    "iso:country":"ES",
    "sg:address":"Sect Islas, 15",
    "sg:city":"Tres Cantos",
    "sg:orig_category":"Guarder\u00cdas",
    "sg:phone":"+34 918 03 71 51",
    "sg:postcode":"28760",
    "sg:province":"Madrid",
    "wof:name":"Fuente Mauro Maria Eugenia",
    "wof:placetype":"venue"
},
  "geometry": {"coordinates":[-3.7115690708,40.5986709595],"type":"Point"}
}