{
  "type": "Feature",
  "properties": {
    "addr:full":"Calle de Teniente Infante, 21 Madridejos Toledo 45710",
    "addr:housenumber":"21",
    "addr:postcode":"45710",
    "addr:street":"Calle De Teniente Infante",
    "iso:country":"ES",
    "sg:address":"Calle de Teniente Infante, 21",
    "sg:city":"Madridejos",
    "sg:orig_category":"Ropa Para Se\u00d1oras Y Caballeros (al Por Menor)",
    "sg:phone":"+34 925 46 07 89",
    "sg:postcode":"45710",
    "sg:province":"Toledo",
    "wof:name":"Mena Martin-delgado Angel Luis",
    "wof:placetype":"venue"
},
  "geometry": {"coordinates":[-3.5335638523,39.4681663513],"type":"Point"}
}