{
  "type": "Feature",
  "properties": {
    "iso:country":"ES",
    "sg:address":"Avda Mediterraneo, 17",
    "sg:city":"Benidorm",
    "sg:orig_category":"Bancos",
    "sg:phone":"+34 966 80 60 00",
    "sg:postcode":"03500",
    "sg:province":"Alicante",
    "wof:name":"Deutsche Bank S.a.e.",
    "wof:placetype":"venue"
},
  "geometry": {"coordinates":[-0.1185719967,38.5368919373],"type":"Point"}
}