{
  "type": "Feature",
  "properties": {
    "iso:country":"ES",
    "sg:address":"Calle de Honda, 8",
    "sg:city":"Fuenlabrada",
    "sg:orig_category":"Peluquer\u00cdas, Peluquer\u00cda Mixta",
    "sg:phone":"+34 916 90 37 87",
    "sg:postcode":"28944",
    "sg:province":"Madrid",
    "wof:name":"Amver Mode Style S.l.",
    "wof:placetype":"venue"
},
  "geometry": {"coordinates":[-3.7919886112,40.2812347412],"type":"Point"}
}