{
  "type": "Feature",
  "properties": {
    "addr:full":"Plaz Hermanos Orbon De Los, S/n Aviles Asturias 33401",
    "addr:postcode":"33401",
    "addr:street":"S / N",
    "iso:country":"ES",
    "sg:address":"Plaz Hermanos Orbon De Los, S/n",
    "sg:city":"Aviles",
    "sg:orig_category":"Pescader\u00cdas (al Por Menor)",
    "sg:phone":"+34 985 56 36 98",
    "sg:postcode":"33401",
    "sg:province":"Asturias",
    "wof:name":"Gonzalez Cuervo Julian",
    "wof:placetype":"venue"
},
  "geometry": {"coordinates":[-5.9229431152,43.5580215454],"type":"Point"}
}