{
  "type": "Feature",
  "properties": {
    "iso:country":"ES",
    "sg:address":"Calle de Vall D'uxo, 4",
    "sg:city":"Valencia",
    "sg:orig_category":"Maquinaria Para Industrias Diversas",
    "sg:phone":"+34 963 77 08 05",
    "sg:postcode":"46014",
    "sg:province":"Valencia",
    "wof:name":"Rivero Rivero S. A.",
    "wof:placetype":"venue"
},
  "geometry": {"coordinates":[-0.4618417025,39.5137710571],"type":"Point"}
}