{
  "type": "Feature",
  "properties": {
    "iso:country":"ES",
    "sg:address":"Pl Major, 33",
    "sg:city":"Vic",
    "sg:orig_category":"Transportes Por Carretera: Lotes Completos, Mercanc\u00cdas Diversas",
    "sg:phone":"+34 938 86 29 93",
    "sg:postcode":"08500",
    "sg:province":"Barcelona",
    "wof:name":"Roses Codinachs Juan",
    "wof:placetype":"venue"
},
  "geometry": {"coordinates":[2.2551269531,41.930606842],"type":"Point"}
}