{
  "type": "Feature",
  "properties": {
    "iso:country":"ES",
    "sg:address":"Carr Sant Roc, 1",
    "sg:city":"Casas Del Rio",
    "sg:orig_category":"Chapister\u00cda",
    "sg:phone":"+34 977 57 53 72",
    "sg:postcode":"12599",
    "sg:province":"Castell\u00f3n",
    "wof:name":"Talleres Alfredo Serrano S.l.",
    "wof:placetype":"venue"
},
  "geometry": {"coordinates":[0.1567949951,40.6562347412],"type":"Point"}
}