{
  "type": "Feature",
  "properties": {
    "addr:full":"Calle de Zaragoza, 58 Binefar Huesca 22500",
    "addr:housenumber":"58",
    "addr:postcode":"22500",
    "addr:street":"Calle De Zaragoza",
    "iso:country":"ES",
    "sg:address":"Calle de Zaragoza, 58",
    "sg:city":"Binefar",
    "sg:orig_category":"Mec\u00c1nico Del Autom\u00d3vil",
    "sg:phone":"+34 974 42 84 60",
    "sg:postcode":"22500",
    "sg:province":"Huesca",
    "wof:name":"Eduardo Salamero Burgues S.l.",
    "wof:placetype":"venue"
},
  "geometry": {"coordinates":[0.2899959981,41.8524131775],"type":"Point"}
}