{
  "type": "Feature",
  "properties": {
    "iso:country":"ES",
    "sg:address":"Avda Valdelasfuentes (de), 25",
    "sg:city":"San Sebastian De Los Reyes",
    "sg:orig_category":"Laboratorios Y Cl\u00cdnicas Veterinarias",
    "sg:phone":"+34 916 51 69 35",
    "sg:postcode":"28700",
    "sg:province":"Madrid",
    "sg:website":"www.valdelasfuentes.net",
    "wof:name":"Sociedad Mercantil Valdelasfuentes 25 S.l.",
    "wof:placetype":"venue"
},
  "geometry": {"coordinates":[-3.6357319355,40.5523605347],"type":"Point"}
}