{
  "type": "Feature",
  "properties": {
    "addr:full":"Plaz Nueve De Octubre, S/n Mislata Valencia 46920",
    "addr:housenumber":"s / n",
    "addr:postcode":"46920",
    "addr:street":"Nueve De Octubre",
    "iso:country":"ES",
    "sg:address":"Plaz Nueve De Octubre, S/n",
    "sg:city":"Mislata",
    "sg:orig_category":"Bibliotecas, Mediatecas",
    "sg:phone":"+34 963 79 73 13",
    "sg:postcode":"46920",
    "sg:province":"Valencia",
    "wof:name":"Ayuntamiento De Mislata",
    "wof:placetype":"venue"
},
  "geometry": {"coordinates":[-0.4052622914,39.4712524414],"type":"Point"}
}