{
  "type": "Feature",
  "properties": {
    "addr:full":"Rua D, 9 Lalin Pontevedra 36500",
    "addr:postcode":"36500",
    "addr:street":"Rua D 9",
    "iso:country":"ES",
    "sg:address":"Rua D, 9",
    "sg:city":"Lalin",
    "sg:orig_category":"Procuradores",
    "sg:phone":"+34 986 78 43 54",
    "sg:postcode":"36500",
    "sg:province":"Pontevedra",
    "wof:name":"Cean Garrido Manuel",
    "wof:placetype":"venue"
},
  "geometry": {"coordinates":[-8.1072721481,42.6558876038],"type":"Point"}
}