{
  "type": "Feature",
  "properties": {
    "iso:country":"ES",
    "sg:address":"Avda Doctor Tomas Sala, 49",
    "sg:city":"Valencia",
    "sg:orig_category":"Peluquer\u00cdas, Peluquer\u00cda Mixta",
    "sg:phone":"+34 963 78 32 73",
    "sg:postcode":"46017",
    "sg:province":"Valencia",
    "wof:name":"Benavent Margarita Cristina",
    "wof:placetype":"venue"
},
  "geometry": {"coordinates":[-0.3926230073,39.4490394592],"type":"Point"}
}