{
  "type": "Feature",
  "properties": {
    "addr:full":"Mercado De Mayoristas Vitoria-gasteiz \u00c1lava 01510",
    "addr:postcode":"01510",
    "iso:country":"ES",
    "sg:address":"Mercado De Mayoristas",
    "sg:city":"Vitoria-gasteiz",
    "sg:orig_category":"Comercio De Hierro",
    "sg:phone":"+34 945 00 03 26",
    "sg:postcode":"01510",
    "sg:province":"\u00c1lava",
    "sg:website":"www.mi\u00f1ano.com",
    "wof:name":"Hierros Mi\u00f1ano, S.a.",
    "wof:placetype":"venue"
},
  "geometry": {"coordinates":[-2.6536741257,42.9061737061],"type":"Point"}
}