{
  "type": "Feature",
  "properties": {
    "iso:country":"ES",
    "sg:address":"C, 28",
    "sg:city":"P. I. El Romeral",
    "sg:orig_category":"Escayola Y Productos De Escayola (fabricaci\u00d3n, Al Por Mayor)",
    "sg:phone":"+34 962 30 24 33",
    "sg:postcode":"46340",
    "sg:province":"Valencia",
    "wof:name":"Escayolas Nu\u00f1ez S.l.",
    "wof:placetype":"venue"
},
  "geometry": {"coordinates":[-1.0998990536,39.4906158447],"type":"Point"}
}