{
  "type": "Feature",
  "properties": {
    "addr:full":"Calle de Ramon Y Cajal, 11 Gallur Zaragoza 50650",
    "addr:housenumber":"11",
    "addr:postcode":"50650",
    "addr:street":"Calle De Ramon Y Cajal",
    "iso:country":"ES",
    "sg:address":"Calle de Ramon Y Cajal, 11",
    "sg:city":"Gallur",
    "sg:orig_category":"Electrodom\u00c9sticos (al Por Menor)",
    "sg:phone":"+34 976 86 48 20",
    "sg:postcode":"50650",
    "sg:province":"Zaragoza",
    "wof:name":"Lopez Manero Angel",
    "wof:placetype":"venue"
},
  "geometry": {"coordinates":[-1.3139630556,41.8685684204],"type":"Point"}
}