{
  "type": "Feature",
  "properties": {
    "addr:full":"Av Portal De L'angel, 16 Barcelona Barcelona 08002",
    "addr:housenumber":"16",
    "addr:postcode":"08002",
    "addr:street":"Av Portal De L'Angel",
    "iso:country":"ES",
    "sg:address":"Av Portal De L'angel, 16",
    "sg:city":"Barcelona",
    "sg:orig_category":"Zapatos (al Por Menor)",
    "sg:phone":"+34 933 17 38 29",
    "sg:postcode":"08002",
    "sg:province":"Barcelona",
    "wof:name":"Zasser,s.l",
    "wof:placetype":"venue"
},
  "geometry": {"coordinates":[2.1732916832,41.3854370117],"type":"Point"}
}