{
  "type": "Feature",
  "properties": {
    "iso:country":"ES",
    "sg:address":"Calle de Doctor Cortezo, 1",
    "sg:city":"Madrid",
    "sg:orig_category":"Discotecas Y Salas De Baile",
    "sg:phone":"+34 913 69 40 38",
    "sg:postcode":"28012",
    "sg:province":"Madrid",
    "wof:name":"Sarafron S.l.",
    "wof:placetype":"venue"
},
  "geometry": {"coordinates":[-3.703471899,40.4140586853],"type":"Point"}
}