{
  "type": "Feature",
  "properties": {
    "addr:full":"Calle de Leon Xiii, 30 Sevilla Sevilla 41009",
    "addr:housenumber":"30",
    "addr:postcode":"41009",
    "addr:street":"Calle De Leon Xiii",
    "iso:country":"ES",
    "sg:address":"Calle de Leon Xiii, 30",
    "sg:city":"Sevilla",
    "sg:orig_category":"Agencias De Viajes",
    "sg:phone":"+34 954 35 92 05",
    "sg:postcode":"41009",
    "sg:province":"Sevilla",
    "wof:name":"Sercontur S.l.",
    "wof:placetype":"venue"
},
  "geometry": {"coordinates":[-5.9835190773,37.4017753601],"type":"Point"}
}