{
  "type": "Feature",
  "properties": {
    "addr:full":"Cra. Maella, S/n Batea Tarragona 43786",
    "addr:housenumber":"s / n",
    "addr:postcode":"43786",
    "iso:country":"ES",
    "sg:address":"Cra. Maella, S/n",
    "sg:city":"Batea",
    "sg:orig_category":"Material Y Herramientas Agr\u00cdcolas",
    "sg:phone":"+34 977 43 01 95",
    "sg:postcode":"43786",
    "sg:province":"Tarragona",
    "wof:name":"Agriaauto Batea S.l.",
    "wof:placetype":"venue"
},
  "geometry": {"coordinates":[0.310034,41.091366],"type":"Point"}
}