{
  "type": "Feature",
  "properties": {
    "addr:full":"Calle de Granada, 4 Ubeda Ja\u00e9n 23400",
    "addr:housenumber":"4",
    "addr:postcode":"23400",
    "addr:street":"Calle De Granada;Jae\u0301N",
    "iso:country":"ES",
    "sg:address":"Calle de Granada, 4",
    "sg:city":"Ubeda",
    "sg:orig_category":"Pescader\u00cdas (al Por Menor)",
    "sg:phone":"+34 953 79 00 71",
    "sg:postcode":"23400",
    "sg:province":"Ja\u00e9n",
    "wof:name":"Toral Correro Maria Dolores",
    "wof:placetype":"venue"
},
  "geometry": {"coordinates":[-3.3785769939,38.0138702393],"type":"Point"}
}