{
  "type": "Feature",
  "properties": {
    "iso:country":"ES",
    "sg:address":"Calle de Mostoles (de), 3",
    "sg:city":"Fuenlabrada",
    "sg:orig_category":"Frutas, Legumbres Frescas Y Tempranas (al Por Menor)",
    "sg:phone":"+34 916 00 01 10",
    "sg:postcode":"28945",
    "sg:province":"Madrid",
    "wof:name":"Frutas Azahara S.l.",
    "wof:placetype":"venue"
},
  "geometry": {"coordinates":[-3.7972550392,40.284324646],"type":"Point"}
}