{
  "type": "Feature",
  "properties": {
    "addr:full":"Carrer de Pablo Picasso, 17 S. Boi Llobregat Barcelona 08830",
    "addr:housenumber":"17",
    "addr:postcode":"08830",
    "addr:street":"Carrer De Pablo Picasso",
    "iso:country":"ES",
    "sg:address":"Carrer de Pablo Picasso, 17",
    "sg:city":"S. Boi Llobregat",
    "sg:orig_category":"Institutos De Belleza",
    "sg:phone":"+34 936 30 95 28",
    "sg:postcode":"08830",
    "sg:province":"Barcelona",
    "wof:name":"Verde Y A\u00f1il S.c.p.",
    "wof:placetype":"venue"
},
  "geometry": {"coordinates":[2.0351281166,41.3503036499],"type":"Point"}
}