{
  "type": "Feature",
  "properties": {
    "addr:full":"Carr Sils, 13 Serres Girona 17411",
    "addr:housenumber":"13",
    "addr:postcode":"17411",
    "addr:street":"Carr Sils",
    "iso:country":"ES",
    "sg:address":"Carr Sils, 13",
    "sg:city":"Serres",
    "sg:orig_category":"Mantenimiento Y Limpieza De Carreteras",
    "sg:phone":"+34 972 85 09 97",
    "sg:postcode":"17411",
    "sg:province":"Girona",
    "wof:name":"Neteges Vidreres Sl",
    "wof:placetype":"venue"
},
  "geometry": {"coordinates":[2.7773220539,41.789768219],"type":"Point"}
}