{
  "type": "Feature",
  "properties": {
    "addr:full":"Ctra San Vicente, S/n Valle Trapaga Vizcaya 48510",
    "addr:housenumber":"s / n",
    "addr:postcode":"48510",
    "addr:street":"Ctra San Vicente;Trapaga",
    "iso:country":"ES",
    "sg:address":"Ctra San Vicente, S/n",
    "sg:city":"Valle Trapaga",
    "sg:classifiers":[
        {
            "category":"Banks & Credit Unions",
            "subcategory":"Bureau De Change",
            "type":"Services"
        }
    ],
    "sg:phone":"+34 944 72 21 82",
    "sg:postcode":"48510",
    "sg:province":"Vizcaya",
    "sg:tags":[
        "organismos",
        "control"
    ],
    "wof:name":"Eca,entidad Colaboradora De La Administracion S.a.u.",
    "wof:placetype":"venue"
},
  "geometry": {"coordinates":[-3.0064940453,43.298740387],"type":"Point"}
}