{
  "type": "Feature",
  "properties": {
    "addr:full":"Av Barbera, 63 Sabadell Barcelona 08203",
    "addr:housenumber":"63",
    "addr:postcode":"08203",
    "addr:street":"Av Barbera",
    "iso:country":"ES",
    "sg:address":"Av Barbera, 63",
    "sg:city":"Sabadell",
    "sg:orig_category":"Quincaller\u00cda (al Por Menor)",
    "sg:phone":"+34 937 11 80 54",
    "sg:postcode":"08203",
    "sg:province":"Barcelona",
    "wof:name":"Ferreteria Sabadell S. A.",
    "wof:placetype":"venue"
},
  "geometry": {"coordinates":[2.1135020256,41.5377349854],"type":"Point"}
}