{
  "type": "Feature",
  "properties": {
    "iso:country":"ES",
    "sg:address":"Avda Barrie De La Maza, 97",
    "sg:city":"Sada",
    "sg:orig_category":"Lavado, Limpieza De Veh\u00cdculos",
    "sg:phone":"+34 981 62 07 60",
    "sg:postcode":"15160",
    "sg:province":"La Coru\u00f1a",
    "wof:name":"Amigo Gonzalez Y Sanchez Toba S. C.",
    "wof:placetype":"venue"
},
  "geometry": {"coordinates":[-8.2591056824,43.3515434265],"type":"Point"}
}