{
  "type": "Feature",
  "properties": {
    "addr:full":"Calle de Mayor (roldan), 21 Roldan Murcia 30709",
    "addr:housenumber":"21",
    "addr:postcode":"30709",
    "addr:street":"Calle De Mayor Roldan",
    "iso:country":"ES",
    "sg:address":"Calle de Mayor (roldan), 21",
    "sg:city":"Roldan",
    "sg:orig_category":"Negocio De Materiales De Construcci\u00d3n",
    "sg:phone":"+34 968 58 93 11",
    "sg:postcode":"30709",
    "sg:province":"Murcia",
    "wof:name":"Cemur S.a.",
    "wof:placetype":"venue"
},
  "geometry": {"coordinates":[-1.0096689463,37.796749115],"type":"Point"}
}