{
  "type": "Feature",
  "properties": {
    "addr:full":"Calle de Mateo Estaun Llanas, 15 Huesca Huesca 22005",
    "addr:housenumber":"15",
    "addr:postcode":"22005",
    "addr:street":"Calle De Mateo Estaun Llanas",
    "iso:country":"ES",
    "sg:address":"Calle de Mateo Estaun Llanas, 15",
    "sg:city":"Huesca",
    "sg:orig_category":"M\u00c9dicos: Cirug\u00cda Pl\u00c1stica, Reconstructiva Y Est\u00c9tica",
    "sg:phone":"+34 974 22 53 54",
    "sg:postcode":"22005",
    "sg:province":"Huesca",
    "wof:name":"Quintas Diez Ramon",
    "wof:placetype":"venue"
},
  "geometry": {"coordinates":[-0.4075129926,42.1282081604],"type":"Point"}
}