{
  "type": "Feature",
  "properties": {
    "addr:full":"Pase Santa Maria De La Cabeza, 34 Madrid Madrid 28045",
    "addr:housenumber":"34",
    "addr:postcode":"madrid;28045",
    "addr:street":"Cabeza",
    "iso:country":"ES",
    "sg:address":"Pase Santa Maria De La Cabeza, 34",
    "sg:city":"Madrid",
    "sg:orig_category":"Molduras, Junquillos, Listones Y Molduras Perforadas",
    "sg:phone":"+34 915 39 47 18",
    "sg:postcode":"28045",
    "sg:province":"Madrid",
    "wof:name":"Mu\u00f1oz Martin Carlos",
    "wof:placetype":"venue"
},
  "geometry": {"coordinates":[-3.696023941,40.4046783447],"type":"Point"}
}