{
  "type": "Feature",
  "properties": {
    "addr:full":"Carr Elias Tormo (d'), 11 Albaida Valencia 46860",
    "addr:housenumber":"11",
    "addr:postcode":"46860",
    "addr:street":"Carr Elias Tormo D '",
    "iso:country":"ES",
    "sg:address":"Carr Elias Tormo (d'), 11",
    "sg:city":"Albaida",
    "sg:orig_category":"Cajas Para Embalar",
    "sg:phone":"+34 962 90 09 73",
    "sg:postcode":"46860",
    "sg:province":"Valencia",
    "wof:name":"Caja Rural Del Mediterraneo Ruralcaja S Coop De Credito",
    "wof:placetype":"venue"
},
  "geometry": {"coordinates":[-0.5189939737,38.8408050537],"type":"Point"}
}