{
  "type": "Feature",
  "properties": {
    "addr:full":"Avda Palencia, 76 Cabezon.barrio Nuevo Valladolid 47260",
    "addr:housenumber":"76",
    "addr:postcode":"47260",
    "addr:street":"Avda Palencia",
    "iso:country":"ES",
    "sg:address":"Avda Palencia, 76",
    "sg:city":"Cabezon.barrio Nuevo",
    "sg:orig_category":"Agencias Y Agentes Comerciales, Representantes",
    "sg:phone":"+34 983 50 00 56",
    "sg:postcode":"47260",
    "sg:province":"Valladolid",
    "wof:name":"Fernandez Arguello Daniel",
    "wof:placetype":"venue"
},
  "geometry": {"coordinates":[-4.6461081505,41.7319450378],"type":"Point"}
}