{
  "type": "Feature",
  "properties": {
    "iso:country":"ES",
    "sg:address":"C/ Arturo Salvetti Pardo, 75",
    "sg:city":"Elche",
    "sg:orig_category":"Colchones (fabricaci\u00d3n, Al Por Mayor, Al Por Menor)",
    "sg:phone":"+34 965 46 41 36",
    "sg:postcode":"03206",
    "sg:province":"Alicante",
    "wof:name":"Colchoneria J. Fernandez S.l.",
    "wof:placetype":"venue"
},
  "geometry": {"coordinates":[-0.7107639909,38.2726249695],"type":"Point"}
}