{
  "type": "Feature",
  "properties": {
    "iso:country":"ES",
    "sg:address":"A Vila De Arriba, S/n",
    "sg:city":"Rubias",
    "sg:orig_category":"Equitaci\u00d3n Y Centros De H\u00cdpica",
    "sg:phone":"+34 982 30 33 61",
    "sg:postcode":"27191",
    "sg:province":"Lugo",
    "wof:name":"Club Hipico Equs",
    "wof:placetype":"venue"
},
  "geometry": {"coordinates":[-7.501019001,43.0407562256],"type":"Point"}
}