{
  "type": "Feature",
  "properties": {
    "addr:full":"Calle de Doctor Barrau, 12 Fuentepelayo Segovia 40260",
    "addr:housenumber":"12",
    "addr:postcode":"40260",
    "addr:street":"Calle De Doctor Barrau",
    "iso:country":"ES",
    "sg:address":"Calle de Doctor Barrau, 12",
    "sg:city":"Fuentepelayo",
    "sg:orig_category":"Material Y Herramientas Agr\u00cdcolas",
    "sg:phone":"+34 921 57 45 20",
    "sg:postcode":"40260",
    "sg:province":"Segovia",
    "wof:name":"Prosanzcu S.a.",
    "wof:placetype":"venue"
},
  "geometry": {"coordinates":[-4.1748929024,41.2187461853],"type":"Point"}
}