{
  "type": "Feature",
  "properties": {
    "iso:country":"ES",
    "sg:address":"Calle de Pe\u00d1a Picada, 19",
    "sg:city":"Arcos Frontera",
    "sg:classifiers":[
        {
            "category":"Personal",
            "subcategory":"Barber",
            "type":"Services"
        }
    ],
    "sg:phone":"+34 956 70 08 80",
    "sg:postcode":"11630",
    "sg:province":"C\u00e1diz",
    "sg:tags":[
        "caballeros",
        "de",
        "peluqueros"
    ],
    "wof:name":"Rosado Fernandez Jose Manuel",
    "wof:placetype":"venue"
},
  "geometry": {"coordinates":[-5.8128128052,36.7517967224],"type":"Point"}
}