{
  "type": "Feature",
  "properties": {
    "iso:country":"ES",
    "sg:address":"C/ Bartolome J. Gallardo, 2",
    "sg:city":"Alcoi",
    "sg:orig_category":"Inform\u00c1tica, Ofim\u00c1tica (estudios, Asesor\u00cda, Ingenier\u00cda, Formaci\u00d3n)",
    "sg:phone":"+34 965 54 48 58",
    "sg:postcode":"03801",
    "sg:province":"Alicante",
    "wof:name":"Fundacion Forem P.v.",
    "wof:placetype":"venue"
},
  "geometry": {"coordinates":[-0.4750030041,38.6955299377],"type":"Point"}
}