{
  "type": "Feature",
  "properties": {
    "addr:full":"Calle de Jose Maria Pereda, 4 Torrelavega Cantabria 39300",
    "addr:housenumber":"4",
    "addr:postcode":"39300",
    "addr:street":"Calle De Jose Maria Pereda",
    "iso:country":"ES",
    "sg:address":"Calle de Jose Maria Pereda, 4",
    "sg:city":"Torrelavega",
    "sg:orig_category":"Bancos",
    "sg:phone":"+34 942 89 09 40",
    "sg:postcode":"39300",
    "sg:province":"Cantabria",
    "wof:name":"Barclays Bank S.a.e.",
    "wof:placetype":"venue"
},
  "geometry": {"coordinates":[-4.0518288612,43.3492698669],"type":"Point"}
}