{
  "type": "Feature",
  "properties": {
    "iso:country":"ES",
    "sg:address":"Basigo De Bakio Auzoa, 11",
    "sg:city":"Bakio",
    "sg:orig_category":"Productores Recolectores, Venta Directa De Vinos",
    "sg:phone":"+34 946 19 43 45",
    "sg:postcode":"48130",
    "sg:province":"Vizcaya",
    "wof:name":"Abio Uriarte Manuel",
    "wof:placetype":"venue"
},
  "geometry": {"coordinates":[-2.820101,43.421745],"type":"Point"}
}