{
  "type": "Feature",
  "properties": {
    "iso:country":"ES",
    "sg:address":"Calle de Alcalde Guillermo Rein, 154",
    "sg:city":"Malaga",
    "sg:orig_category":"Fabricaci\u00d3n De Muebles",
    "sg:phone":"+34 952 34 83 98",
    "sg:postcode":"29006",
    "sg:province":"M\u00e1laga",
    "wof:name":"Portillo Montero Juan",
    "wof:placetype":"venue"
},
  "geometry": {"coordinates":[-4.4834485054,36.7112083435],"type":"Point"}
}