{
  "type": "Feature",
  "properties": {
    "addr:full":"Pl. Mercat, 161 Vilanova Geltru Barcelona 08800",
    "addr:housenumber":"161",
    "addr:postcode":"08800",
    "addr:street":"Mercat;Geltru Barcelona",
    "iso:country":"ES",
    "sg:address":"Pl. Mercat, 161",
    "sg:city":"Vilanova Geltru",
    "sg:orig_category":"Prendas Y Chalecos De Punto (al Por Menor)",
    "sg:phone":"+34 938 93 11 48",
    "sg:postcode":"08800",
    "sg:province":"Barcelona",
    "wof:name":"Alegre Farre Ricardo",
    "wof:placetype":"venue"
},
  "geometry": {"coordinates":[1.7185870409,41.2272720337],"type":"Point"}
}