{
  "type": "Feature",
  "properties": {
    "addr:full":"Turia, 4 S. Antonio Benageber Valencia 46184",
    "addr:postcode":"46184",
    "addr:street":"Turia 4 S. Antonio Benageber",
    "iso:country":"ES",
    "sg:address":"Turia, 4",
    "sg:city":"S. Antonio Benageber",
    "sg:orig_category":"Panader\u00cdas, Panader\u00cdas",
    "sg:phone":"+34 961 35 12 41",
    "sg:postcode":"46184",
    "sg:province":"Valencia",
    "wof:name":"Horno Aguero S.l.",
    "wof:placetype":"venue"
},
  "geometry": {"coordinates":[-0.5012540221,39.5620651245],"type":"Point"}
}