{
  "type": "Feature",
  "properties": {
    "iso:country":"ES",
    "sg:address":"Calle de Amazonia (de La), 18",
    "sg:city":"Coslada",
    "sg:orig_category":"Centros Empresariales",
    "sg:phone":"+34 916 69 70 76",
    "sg:postcode":"28820",
    "sg:province":"Madrid",
    "wof:name":"Iberica De Humus S.a.",
    "wof:placetype":"venue"
},
  "geometry": {"coordinates":[-3.5580744743,40.4180831909],"type":"Point"}
}