{
  "type": "Feature",
  "properties": {
    "addr:full":"Calle de Marques De Pickman, 54 Sevilla Sevilla 41005",
    "addr:housenumber":"54",
    "addr:postcode":"41005",
    "addr:street":"Calle De Marques De Pickman",
    "iso:country":"ES",
    "sg:address":"Calle de Marques De Pickman, 54",
    "sg:city":"Sevilla",
    "sg:orig_category":"Peluquer\u00cdas, Peluquer\u00cda Mixta",
    "sg:phone":"+34 954 63 41 97",
    "sg:postcode":"41005",
    "sg:province":"Sevilla",
    "wof:name":"Guang Fu Chen",
    "wof:placetype":"venue"
},
  "geometry": {"coordinates":[-5.9621038437,37.3810997009],"type":"Point"}
}