{
  "type": "Feature",
  "properties": {
    "addr:full":"Carrer de Josep Comas I Sola, 13 Manresa Barcelona 08243",
    "addr:housenumber":"13",
    "addr:postcode":"08243",
    "addr:street":"Carrer De Josep Comas I Sola",
    "iso:country":"ES",
    "sg:address":"Carrer de Josep Comas I Sola, 13",
    "sg:city":"Manresa",
    "sg:orig_category":"Transporte En General",
    "sg:phone":"+34 938 74 04 60",
    "sg:postcode":"08243",
    "sg:province":"Barcelona",
    "wof:name":"Logistics Mde Del Bages S. L.",
    "wof:placetype":"venue"
},
  "geometry": {"coordinates":[1.8464239836,41.7123336792],"type":"Point"}
}