{
  "type": "Feature",
  "properties": {
    "addr:full":"Av Ronda Norte, 13 Picassent Valencia 46220",
    "addr:housenumber":"13",
    "addr:postcode":"46220",
    "addr:street":"Av Ronda Norte",
    "iso:country":"ES",
    "sg:address":"Av Ronda Norte, 13",
    "sg:city":"Picassent",
    "sg:orig_category":"Guarder\u00cdas",
    "sg:phone":"+34 961 24 05 47",
    "sg:postcode":"46220",
    "sg:province":"Valencia",
    "wof:name":"Aguado Ferri Julia",
    "wof:placetype":"venue"
},
  "geometry": {"coordinates":[-0.4974358976,39.3506889343],"type":"Point"}
}