{
  "type": "Feature",
  "properties": {
    "iso:country":"ES",
    "sg:address":"Carr Estacio, 5",
    "sg:city":"Picassent",
    "sg:orig_category":"Abogados",
    "sg:phone":"+34 961 22 15 52",
    "sg:postcode":"46220",
    "sg:province":"Valencia",
    "wof:name":"Juan Andres Molins Rodriguez Y Otros Cdad",
    "wof:placetype":"venue"
},
  "geometry": {"coordinates":[-0.4647690058,39.3626937866],"type":"Point"}
}