{
  "type": "Feature",
  "properties": {
    "addr:full":"Mat\u00edas Valero, 5 Landete Cuenca 16330",
    "addr:housenumber":"5",
    "addr:postcode":"16330",
    "addr:street":"Valero",
    "iso:country":"ES",
    "sg:address":"Mat\u00edas Valero, 5",
    "sg:city":"Landete",
    "sg:orig_category":"Alimentaci\u00d3n General (al Por Menor)",
    "sg:phone":"+34 969 36 10 73",
    "sg:postcode":"16330",
    "sg:province":"Cuenca",
    "wof:name":"Autoservicio El Mata S.l.",
    "wof:placetype":"venue"
},
  "geometry": {"coordinates":[-1.367244482,39.9077072144],"type":"Point"}
}