{
  "type": "Feature",
  "properties": {
    "iso:country":"ES",
    "sg:address":"A. Amelia La Torre (pi Trevenez), 22",
    "sg:city":"Malaga",
    "sg:orig_category":"Empresarios Y Productoras De Espect\u00c1culos",
    "sg:phone":"+34 952 17 82 07",
    "sg:postcode":"29006",
    "sg:province":"M\u00e1laga",
    "sg:website":"www.elespejonegro.com",
    "wof:name":"Calvente Herrera Angel",
    "wof:placetype":"venue"
},
  "geometry": {"coordinates":[-4.4201588631,36.7183189392],"type":"Point"}
}