{
  "type": "Feature",
  "properties": {
    "iso:country":"ES",
    "sg:address":"Calle de Murgis, S/n",
    "sg:city":"Ejido",
    "sg:orig_category":"Inmobiliaria (agencias)",
    "sg:phone":"+34 950 48 80 15",
    "sg:postcode":"04700",
    "sg:province":"Almer\u00eda",
    "sg:website":"www.donpiso.com",
    "wof:name":"Ivazma Transacciones S.l.",
    "wof:placetype":"venue"
},
  "geometry": {"coordinates":[-2.8133440018,36.7760887146],"type":"Point"}
}