{
  "type": "Feature",
  "properties": {
    "iso:country":"ES",
    "sg:address":"Carrer de Tenerife, 6",
    "sg:city":"Sabadell",
    "sg:orig_category":"Panader\u00cdas, Panader\u00cdas",
    "sg:phone":"+34 937 45 15 14",
    "sg:postcode":"08205",
    "sg:province":"Barcelona",
    "wof:name":"Panificadora De Gallecs S.l.",
    "wof:placetype":"venue"
},
  "geometry": {"coordinates":[2.0895729065,41.5459022522],"type":"Point"}
}