{
  "type": "Feature",
  "properties": {
    "iso:country":"ES",
    "sg:address":"Calle de Jaime Urrutia, 8",
    "sg:city":"Elizondo",
    "sg:orig_category":"Caf\u00c9s, Bares, Cervecer\u00cdas",
    "sg:phone":"+34 948 58 13 34",
    "sg:postcode":"31700",
    "sg:province":"Navarra",
    "wof:name":"Echenique Garaicoechea Andres",
    "wof:placetype":"venue"
},
  "geometry": {"coordinates":[-1.5200459957,43.1436233521],"type":"Point"}
}