{
  "type": "Feature",
  "properties": {
    "iso:country":"ES",
    "sg:address":"Ctra San Julian, 83",
    "sg:city":"Teruel",
    "sg:orig_category":"Pintura, Barniz, Productos Asimilables (fabricaci\u00d3n, Al Por Mayor)",
    "sg:phone":"+34 978 61 79 36",
    "sg:postcode":"44003",
    "sg:province":"Teruel",
    "wof:name":"Pinturas Mudejar S.l.",
    "wof:placetype":"venue"
},
  "geometry": {"coordinates":[-1.1016390324,40.3379707336],"type":"Point"}
}