{
  "type": "Feature",
  "properties": {
    "addr:full":"Calle de Ciro Gonzalez, 36 Sauces Santa Cruz De Tenerife 38720",
    "addr:housenumber":"36",
    "addr:postcode":"38720",
    "addr:street":"Calle De Ciro Gonzalez",
    "iso:country":"ES",
    "sg:address":"Calle de Ciro Gonzalez, 36",
    "sg:city":"Sauces",
    "sg:orig_category":"Asociaciones Humanitarias, De Cooperaci\u00d3n, De Acci\u00d3n Social",
    "sg:phone":"+34 922 45 00 73",
    "sg:postcode":"38720",
    "sg:province":"Santa Cruz De Tenerife",
    "wof:name":"Asociacion Mujeres,solidaridad Y Cooperacion",
    "wof:placetype":"venue"
},
  "geometry": {"coordinates":[-17.7761478424,28.8058414459],"type":"Point"}
}