{
  "type": "Feature",
  "properties": {
    "addr:full":"Calle de Concepcion Arenal, 2 Villena Alicante 03400",
    "addr:housenumber":"2",
    "addr:postcode":"03400",
    "addr:street":"Calle De Concepcion Arenal",
    "iso:country":"ES",
    "sg:address":"Calle de Concepcion Arenal, 2",
    "sg:city":"Villena",
    "sg:orig_category":"Asociaciones Y Clubs Deportivos",
    "sg:phone":"+34 965 80 61 84",
    "sg:postcode":"03400",
    "sg:province":"Alicante",
    "sg:website":"www.villena.com-stadium",
    "wof:name":"Deportes Stadium S.l.",
    "wof:placetype":"venue"
},
  "geometry": {"coordinates":[-0.8671759963,38.6326828003],"type":"Point"}
}