{
  "type": "Feature",
  "properties": {
    "iso:country":"ES",
    "sg:address":"Calle de Fray Ceferino, 49",
    "sg:city":"Oviedo",
    "sg:classifiers":[
        {
            "category":"Personal",
            "subcategory":"Barber",
            "type":"Services"
        }
    ],
    "sg:phone":"+34 985 11 18 73",
    "sg:postcode":"33011",
    "sg:province":"Asturias",
    "sg:tags":[
        "caballeros",
        "de",
        "peluqueros"
    ],
    "wof:name":"Fernandez Fernandez Juan Manuel",
    "wof:placetype":"venue"
},
  "geometry": {"coordinates":[-5.8490891457,43.3685913086],"type":"Point"}
}