{
  "type": "Feature",
  "properties": {
    "iso:country":"ES",
    "sg:address":"Calle de Reyes Catolicos, 29",
    "sg:city":"Granada",
    "sg:orig_category":"Compraventa De Antig\u00dcedades",
    "sg:phone":"+34 958 22 61 39",
    "sg:postcode":"18001",
    "sg:province":"Granada",
    "wof:name":"Mu\u00f1oz Molina Miguel",
    "wof:placetype":"venue"
},
  "geometry": {"coordinates":[-3.5986609459,37.1751098633],"type":"Point"}
}