{
  "type": "Feature",
  "properties": {
    "iso:country":"ES",
    "sg:address":"Carrer de Joanot Martorell, 276",
    "sg:city":"Granollers",
    "sg:orig_category":"Transportes Por Carretera: Lotes Completos, Mercanc\u00cdas Diversas",
    "sg:phone":"+34 938 46 75 28",
    "sg:postcode":"08403",
    "sg:province":"Barcelona",
    "wof:name":"Bimbo S.a.",
    "wof:placetype":"venue"
},
  "geometry": {"coordinates":[2.2749199867,41.602519989],"type":"Point"}
}