{
  "type": "Feature",
  "properties": {
    "addr:full":"Calle de Sierra De Cabrera, 6 Parador Hortichuelas Almer\u00eda 04720",
    "addr:housenumber":"6",
    "addr:postcode":"04720",
    "addr:street":"Calle De Sierra De Cabrera;Almeri\u0301A",
    "iso:country":"ES",
    "sg:address":"Calle de Sierra De Cabrera, 6",
    "sg:city":"Parador Hortichuelas",
    "sg:orig_category":"Guarder\u00cdas",
    "sg:phone":"+34 950 34 36 81",
    "sg:postcode":"04720",
    "sg:province":"Almer\u00eda",
    "wof:name":"Angela Reina Decoraciones S.l.",
    "wof:placetype":"venue"
},
  "geometry": {"coordinates":[-2.599114418,36.8055419922],"type":"Point"}
}