{
  "type": "Feature",
  "properties": {
    "addr:full":"Calle de Arrasate, 51 Donostia-san Sebastian Guip\u00f9zcoa 20005",
    "addr:housenumber":"51",
    "addr:postcode":"20005",
    "addr:street":"Calle De Arrasate",
    "iso:country":"ES",
    "sg:address":"Calle de Arrasate, 51",
    "sg:city":"Donostia-san Sebastian",
    "sg:orig_category":"Pe\u00d1as Y Asociaciones Varias",
    "sg:phone":"+34 943 45 17 22",
    "sg:postcode":"20005",
    "sg:province":"Guip\u00f9zcoa",
    "sg:website":"www.gehitu.net",
    "wof:name":"Gehitu",
    "wof:placetype":"venue"
},
  "geometry": {"coordinates":[-1.9844502211,43.3171691895],"type":"Point"}
}