{
  "type": "Feature",
  "properties": {
    "addr:full":"Ctra. Deleitosa-retamosa, Km. 0000,3 Deleitosa C\u00e1ceres 10370",
    "addr:postcode":"10370",
    "addr:street":"Ctra. Deleitosa-Retamosa Km. 0000,3;Ca\u0301Ceres",
    "iso:country":"ES",
    "sg:address":"Ctra. Deleitosa-retamosa, Km. 0000,3",
    "sg:city":"Deleitosa",
    "sg:orig_category":"Comercio De Carburantes",
    "sg:phone":"+34 927 54 02 04",
    "sg:postcode":"10370",
    "sg:province":"C\u00e1ceres",
    "wof:name":"Estacion De Servicio La Bre\u00f1a S.l.",
    "wof:placetype":"venue"
},
  "geometry": {"coordinates":[-5.6446962357,39.645614624],"type":"Point"}
}