{
  "type": "Feature",
  "properties": {
    "addr:full":"Calle de Circunvalacion, 59 Torrejon Ardoz Madrid 28850",
    "addr:housenumber":"59",
    "addr:postcode":"28850",
    "addr:street":"Calle De Circunvalacion",
    "iso:country":"ES",
    "sg:address":"Calle de Circunvalacion, 59",
    "sg:city":"Torrejon Ardoz",
    "sg:orig_category":"Cajas De Ahorro",
    "sg:phone":"+34 916 56 88 69",
    "sg:postcode":"28850",
    "sg:province":"Madrid",
    "sg:website":"www.lacaixa.es",
    "wof:name":"Caixa D'estalvis I Pensions De Barcelona",
    "wof:placetype":"venue"
},
  "geometry": {"coordinates":[-3.4556529522,40.4546318054],"type":"Point"}
}