{
  "type": "Feature",
  "properties": {
    "iso:country":"ES",
    "sg:address":"Carr Balears, 6",
    "sg:city":"Eivissa",
    "sg:orig_category":"Costureras",
    "sg:phone":"+34 971 39 07 67",
    "sg:postcode":"07800",
    "sg:province":"Islas Baleares",
    "sg:website":"www.pepabonett.com",
    "wof:name":"Mari Boned Josefa",
    "wof:placetype":"venue"
},
  "geometry": {"coordinates":[1.4251070023,38.9080200195],"type":"Point"}
}