{
  "type": "Feature",
  "properties": {
    "iso:country":"ES",
    "sg:address":"Calle de Telemaco, 2",
    "sg:city":"Madrid",
    "sg:orig_category":"Promotores Constructores",
    "sg:phone":"+34 917 42 99 22",
    "sg:postcode":"28027",
    "sg:province":"Madrid",
    "wof:name":"C.p. Telemaco",
    "wof:placetype":"venue"
},
  "geometry": {"coordinates":[-3.6463589668,40.4476585388],"type":"Point"}
}