{
  "type": "Feature",
  "properties": {
    "iso:country":"ES",
    "sg:address":"Pg Gran Passeig Ronda, 34",
    "sg:city":"Lleida",
    "sg:orig_category":"Reposter\u00cdas",
    "sg:phone":"+34 973 26 32 09",
    "sg:postcode":"25003",
    "sg:province":"Lleida",
    "wof:name":"Marti Llaras Francisco Javier",
    "wof:placetype":"venue"
},
  "geometry": {"coordinates":[0.6137139797,41.6133270264],"type":"Point"}
}