{
  "type": "Feature",
  "properties": {
    "addr:full":"Avda Barcelona, 42 Malaga M\u00e1laga 29009",
    "addr:housenumber":"42",
    "addr:postcode":"29009",
    "addr:street":"Avda Barcelona;Ma\u0301Laga",
    "iso:country":"ES",
    "sg:address":"Avda Barcelona, 42",
    "sg:city":"Malaga",
    "sg:orig_category":"Asesor\u00cda Fiscal Y Jur\u00cddica",
    "sg:phone":"+34 952 30 40 36",
    "sg:postcode":"29009",
    "sg:province":"M\u00e1laga",
    "wof:name":"Postigo Jimenez Gema",
    "wof:placetype":"venue"
},
  "geometry": {"coordinates":[-4.4307451248,36.7256469727],"type":"Point"}
}