{
  "type": "Feature",
  "properties": {
    "addr:full":"Av Montserrat, S/n S. Esteve Sesrovires Barcelona 08635",
    "addr:housenumber":"s",
    "addr:postcode":"08635",
    "addr:street":"Av Montserrat;/ N S. Esteve Sesrovires Barcelona",
    "iso:country":"ES",
    "sg:address":"Av Montserrat, S/n",
    "sg:city":"S. Esteve Sesrovires",
    "sg:orig_category":"Peluquer\u00cdas, Peluquer\u00cda Mixta",
    "sg:phone":"+34 937 71 37 47",
    "sg:postcode":"08635",
    "sg:province":"Barcelona",
    "wof:name":"Exposito Ayuso Antonia",
    "wof:placetype":"venue"
},
  "geometry": {"coordinates":[1.8715699911,41.4957618713],"type":"Point"}
}