{
  "type": "Feature",
  "properties": {
    "addr:full":"Ctra Sagunto-burgos, Km. 0019,6 Sot De Ferrer Castell\u00f3n 12489",
    "addr:postcode":"12489",
    "addr:street":"Ctra Sagunto-Burgos Km. 0019,6;Castello\u0301N",
    "iso:country":"ES",
    "sg:address":"Ctra Sagunto-burgos, Km. 0019,6",
    "sg:city":"Sot De Ferrer",
    "sg:orig_category":"Distribuci\u00d3n De Petr\u00d3leo Y Derivados",
    "sg:phone":"+34 964 76 41 72",
    "sg:postcode":"12489",
    "sg:province":"Castell\u00f3n",
    "wof:name":"Estacion De Servicio El Juncar S.l.",
    "wof:placetype":"venue"
},
  "geometry": {"coordinates":[-0.4018499851,39.7978515625],"type":"Point"}
}