{
  "type": "Feature",
  "properties": {
    "iso:country":"ES",
    "sg:address":"Ctra Tariquejos, Km. 0016,0",
    "sg:city":"Villanueva Castillejos",
    "sg:orig_category":"Agricultura: Abastecimiento Y Cosechado (negocio)",
    "sg:phone":"+34 959 50 40 81",
    "sg:postcode":"21540",
    "sg:province":"Huelva",
    "wof:name":"Severino Gonzalez Fernando",
    "wof:placetype":"venue"
},
  "geometry": {"coordinates":[-7.2722191811,37.5009651184],"type":"Point"}
}