{
  "type": "Feature",
  "properties": {
    "iso:country":"ES",
    "sg:address":"Calle de Blas Infante, 7",
    "sg:city":"Herrera",
    "sg:orig_category":"Cajas De Ahorro",
    "sg:phone":"+34 954 01 30 80",
    "sg:postcode":"41567",
    "sg:province":"Sevilla",
    "sg:website":"www.cajasanfernando.es",
    "wof:name":"Caja San Fernando De Sevilla Y Jerez",
    "wof:placetype":"venue"
},
  "geometry": {"coordinates":[-4.8499927521,37.3649597168],"type":"Point"}
}