{
  "type": "Feature",
  "properties": {
    "addr:full":"Ptda Simetes, S/n Manises Valencia 46940",
    "addr:housenumber":"s",
    "addr:postcode":"46940",
    "addr:street":"Ptda Simetes;/ N",
    "iso:country":"ES",
    "sg:address":"Ptda Simetes, S/n",
    "sg:city":"Manises",
    "sg:orig_category":"Fabrica De Cer\u00c1micas",
    "sg:phone":"+34 961 54 99 79",
    "sg:postcode":"46940",
    "sg:province":"Valencia",
    "wof:name":"Asuncion Gomez Jose Bernardo",
    "wof:placetype":"venue"
},
  "geometry": {"coordinates":[-0.4558824003,39.4907341003],"type":"Point"}
}