{
  "type": "Feature",
  "properties": {
    "iso:country":"ES",
    "sg:address":"Calle de Lain Calvo, 40",
    "sg:city":"Burgos",
    "sg:orig_category":"Centros Comerciales Y Grandes Tiendas",
    "sg:phone":"+34 947 20 99 11",
    "sg:postcode":"09003",
    "sg:province":"Burgos",
    "sg:website":"www.tadeval.com",
    "wof:name":"Valdivielso Barrios Aurelio",
    "wof:placetype":"venue"
},
  "geometry": {"coordinates":[-3.7015416622,42.3425750732],"type":"Point"}
}