{
  "type": "Feature",
  "properties": {
    "addr:full":"Calle de Gobernador (del), 91 Aranjuez Madrid 28300",
    "addr:housenumber":"91",
    "addr:postcode":"28300",
    "addr:street":"Calle De Gobernador Del",
    "iso:country":"ES",
    "sg:address":"Calle de Gobernador (del), 91",
    "sg:city":"Aranjuez",
    "sg:orig_category":"Papeler\u00cdas, Librer\u00cdas",
    "sg:phone":"+34 918 91 62 32",
    "sg:postcode":"28300",
    "sg:province":"Madrid",
    "wof:name":"Perez Hernan Amelia",
    "wof:placetype":"venue"
},
  "geometry": {"coordinates":[-3.6029961109,40.0325698853],"type":"Point"}
}