{
  "type": "Feature",
  "properties": {
    "iso:country":"ES",
    "sg:address":"Ctra Canillas, 43",
    "sg:city":"Madrid",
    "sg:orig_category":"Carnicer\u00cdas, Carnicer\u00cdas",
    "sg:phone":"+34 917 59 43 21",
    "sg:postcode":"28043",
    "sg:province":"Madrid",
    "wof:name":"Ambres Acero Jose",
    "wof:placetype":"venue"
},
  "geometry": {"coordinates":[-3.6472637653,40.4632949829],"type":"Point"}
}