{
  "type": "Feature",
  "properties": {
    "iso:country":"ES",
    "sg:address":"C\u00d1ad De La Vizana, 20",
    "sg:city":"Benavente",
    "sg:orig_category":"Garajes De Veh\u00cdculos",
    "sg:phone":"+34 980 63 05 24",
    "sg:postcode":"49600",
    "sg:province":"Zamora",
    "wof:name":"Cristobal Rodriguez Gregorio",
    "wof:placetype":"venue"
},
  "geometry": {"coordinates":[-5.6843042374,42.0074653625],"type":"Point"}
}