{
  "type": "Feature",
  "properties": {
    "addr:full":"Carr Tortosa, 34 Badalona Barcelona 08918",
    "addr:housenumber":"34",
    "addr:postcode":"08918",
    "addr:street":"Carr Tortosa",
    "iso:country":"ES",
    "sg:address":"Carr Tortosa, 34",
    "sg:city":"Badalona",
    "sg:orig_category":"Molduras, Junquillos, Listones Y Molduras Perforadas",
    "sg:phone":"+34 933 87 10 30",
    "sg:postcode":"08918",
    "sg:province":"Barcelona",
    "wof:name":"Alvaro Blasco Juan",
    "wof:placetype":"venue"
},
  "geometry": {"coordinates":[2.2316770554,41.4391174316],"type":"Point"}
}