{
  "type": "Feature",
  "properties": {
    "iso:country":"ES",
    "sg:address":"Calle de Alejandro Casona, 8",
    "sg:city":"Malaga",
    "sg:orig_category":"Persianas Interiores, Exteriores",
    "sg:phone":"+34 952 24 54 71",
    "sg:postcode":"29004",
    "sg:province":"M\u00e1laga",
    "wof:name":"Persianas Europa S.l.",
    "wof:placetype":"venue"
},
  "geometry": {"coordinates":[-4.4783573151,36.6900901794],"type":"Point"}
}