{
  "type": "Feature",
  "properties": {
    "iso:country":"ES",
    "sg:address":"Devesa, 6",
    "sg:city":"Arins",
    "sg:orig_category":"Asociaciones Humanitarias, De Cooperaci\u00d3n, De Acci\u00d3n Social",
    "sg:phone":"+34 981 54 93 93",
    "sg:postcode":"15892",
    "sg:province":"La Coru\u00f1a",
    "wof:name":"Patronato Da Fundacion Monte Do Gozo-proxecto Home",
    "wof:placetype":"venue"
},
  "geometry": {"coordinates":[-8.5155544281,42.8582878113],"type":"Point"}
}