{
  "type": "Feature",
  "properties": {
    "addr:full":"Urb Sensara, S/n Benalmadena M\u00e1laga 29639",
    "addr:housenumber":"s",
    "addr:postcode":"29639",
    "addr:street":"Urb Sensara;/ N;Ma\u0301Laga",
    "iso:country":"ES",
    "sg:address":"Urb Sensara, S/n",
    "sg:city":"Benalmadena",
    "sg:orig_category":"Promotores Constructores",
    "sg:phone":"+34 952 56 91 10",
    "sg:postcode":"29639",
    "sg:province":"M\u00e1laga",
    "wof:name":"Suite Invest S.l.",
    "wof:placetype":"venue"
},
  "geometry": {"coordinates":[-4.5734581947,36.5951728821],"type":"Point"}
}