{
  "type": "Feature",
  "properties": {
    "addr:full":"Avda Ramon Y Cajal, 23 Candeleda \u00c1vila 05480",
    "addr:housenumber":"23",
    "addr:postcode":"05480",
    "addr:street":"Avda Ramon Y Cajal",
    "iso:country":"ES",
    "sg:address":"Avda Ramon Y Cajal, 23",
    "sg:city":"Candeleda",
    "sg:orig_category":"Peluqueros: De Se\u00d1oras",
    "sg:phone":"+34 920 38 02 95",
    "sg:postcode":"05480",
    "sg:province":"\u00c1vila",
    "wof:name":"Vadillo Ambrosio Luis",
    "wof:placetype":"venue"
},
  "geometry": {"coordinates":[-5.2416400909,40.1534996033],"type":"Point"}
}