{
  "type": "Feature",
  "properties": {
    "iso:country":"ES",
    "sg:address":"Calle de Sauce (del), 3",
    "sg:city":"Humanes De Madrid",
    "sg:orig_category":"Chapister\u00cda",
    "sg:phone":"+34 916 04 86 02",
    "sg:postcode":"28970",
    "sg:province":"Madrid",
    "wof:name":"Reparaciones Mobauto S.l.",
    "wof:placetype":"venue"
},
  "geometry": {"coordinates":[-3.8269588947,40.2540245056],"type":"Point"}
}