{
  "type": "Feature",
  "properties": {
    "iso:country":"ES",
    "sg:address":"Pl Bolivia, 11",
    "sg:city":"Poblenou",
    "sg:orig_category":"Mec\u00c1nico Del Autom\u00d3vil",
    "sg:phone":"+34 937 69 06 98",
    "sg:postcode":"08397",
    "sg:province":"Barcelona",
    "wof:name":"Gomez Cantero Jaume",
    "wof:placetype":"venue"
},
  "geometry": {"coordinates":[2.6826798916,41.6266517639],"type":"Point"}
}