{
  "type": "Feature",
  "properties": {
    "iso:country":"ES",
    "sg:address":"Calle de Jose Garcia Selles, 2",
    "sg:city":"Alacant",
    "sg:orig_category":"Asociaciones Y Clubs Deportivos",
    "sg:phone":"+34 965 24 73 68",
    "sg:postcode":"03012",
    "sg:province":"Alicante",
    "wof:name":"Santiago Ba\u00f1os Torres S. A.",
    "wof:placetype":"venue"
},
  "geometry": {"coordinates":[-0.4696699977,38.3669319153],"type":"Point"}
}