{
  "type": "Feature",
  "properties": {
    "addr:full":"Calle de Hogar Provincial, 3 Alacant Alicante 03559",
    "addr:postcode":"03559",
    "addr:street":"Calle De;Provincial",
    "iso:country":"ES",
    "sg:address":"Calle de Hogar Provincial, 3",
    "sg:city":"Alacant",
    "sg:orig_category":"Inform\u00c1tica Equipo Y Programas (al Por Mayor)",
    "sg:phone":"+34 965 16 35 35",
    "sg:postcode":"03559",
    "sg:province":"Alicante",
    "wof:name":"Alicantina Feedback S.l.l.",
    "wof:placetype":"venue"
},
  "geometry": {"coordinates":[-0.4561350048,38.3856277466],"type":"Point"}
}