{
  "type": "Feature",
  "properties": {
    "iso:country":"ES",
    "sg:address":"F. Majadarrasa, S/n",
    "sg:city":"Ventas Pe\u00f1a Aguilera",
    "sg:orig_category":"Agricultores, Agricultores",
    "sg:phone":"+34 925 59 10 50",
    "sg:postcode":"45127",
    "sg:province":"Toledo",
    "wof:name":"Alonso Garcia-cuerva Blanca",
    "wof:placetype":"venue"
},
  "geometry": {"coordinates":[-4.0244760513,39.8567771912],"type":"Point"}
}