{
  "type": "Feature",
  "properties": {
    "iso:country":"ES",
    "sg:address":"Pla\u00c7 Joaquim Ballester, 5",
    "sg:city":"Gandia",
    "sg:orig_category":"Venta, Colocaci\u00d3n, Tratamiento De Enlosados, Soler\u00cdas",
    "sg:phone":"+34 962 96 57 34",
    "sg:postcode":"46700",
    "sg:province":"Valencia",
    "wof:name":"Iflova 2002 S.l.",
    "wof:placetype":"venue"
},
  "geometry": {"coordinates":[-0.1913339943,38.960735321],"type":"Point"}
}