{
  "type": "Feature",
  "properties": {
    "addr:full":"Rua Calvo Sotelo, 31 Ordes La Coru\u00f1a 15680",
    "addr:housenumber":"31",
    "addr:postcode":"15680",
    "addr:street":"Rua Calvo Sotelo;La Corun\u0303A",
    "iso:country":"ES",
    "sg:address":"Rua Calvo Sotelo, 31",
    "sg:city":"Ordes",
    "sg:orig_category":"Agencias Y Agentes Comerciales, Representantes",
    "sg:phone":"+34 981 68 01 82",
    "sg:postcode":"15680",
    "sg:province":"La Coru\u00f1a",
    "wof:name":"Sandoval Sabater Marcos",
    "wof:placetype":"venue"
},
  "geometry": {"coordinates":[-8.4076976776,43.0754890442],"type":"Point"}
}