{
  "type": "Feature",
  "properties": {
    "iso:country":"ES",
    "sg:address":"Calle de Concordia, 4",
    "sg:city":"Madrid",
    "sg:orig_category":"Cervecer\u00cdas",
    "sg:phone":"+34 914 78 69 28",
    "sg:postcode":"28053",
    "sg:province":"Madrid",
    "wof:name":"Barragan Lopez Ricardo Andres",
    "wof:placetype":"venue"
},
  "geometry": {"coordinates":[-3.6653280258,40.3959121704],"type":"Point"}
}