{
  "type": "Feature",
  "properties": {
    "addr:full":"Calle de Salamanca, 10 Granada Granada 18001",
    "addr:housenumber":"10",
    "addr:postcode":"18001",
    "addr:street":"Calle De Salamanca",
    "iso:country":"ES",
    "sg:address":"Calle de Salamanca, 10",
    "sg:city":"Granada",
    "sg:orig_category":"Estilistas Y Estudios De Estilo De Corte Y Confecci\u00d3n",
    "sg:phone":"+34 958 53 68 45",
    "sg:postcode":"18001",
    "sg:province":"Granada",
    "wof:name":"Arozarena Dalton Diego",
    "wof:placetype":"venue"
},
  "geometry": {"coordinates":[-3.5996232033,37.1745376587],"type":"Point"}
}