{
  "type": "Feature",
  "properties": {
    "iso:country":"ES",
    "sg:address":"Avda Cameros, 23",
    "sg:city":"Villamediana Iregua",
    "sg:orig_category":"Reposter\u00cdas",
    "sg:phone":"+34 941 43 50 77",
    "sg:postcode":"26142",
    "sg:province":"La Rioja",
    "wof:name":"Ortiz Redondo Eleuterio",
    "wof:placetype":"venue"
},
  "geometry": {"coordinates":[-2.4140319824,42.4225273132],"type":"Point"}
}