{
  "type": "Feature",
  "properties": {
    "iso:country":"ES",
    "sg:address":"Carr Sarria De Ter, 28",
    "sg:city":"Girona",
    "sg:orig_category":"Hormigonados",
    "sg:phone":"+34 972 23 88 28",
    "sg:postcode":"17005",
    "sg:province":"Girona",
    "wof:name":"Rubau-pla S.a.",
    "wof:placetype":"venue"
},
  "geometry": {"coordinates":[2.8087630272,41.9614257812],"type":"Point"}
}