{
  "type": "Feature",
  "properties": {
    "iso:country":"ES",
    "sg:address":"Calle de Getafe (de), 5",
    "sg:city":"Pinto",
    "sg:orig_category":"Herboristas (al Por Menor)",
    "sg:phone":"+34 916 91 47 84",
    "sg:postcode":"28320",
    "sg:province":"Madrid",
    "wof:name":"Cuesta Velilla Josefa",
    "wof:placetype":"venue"
},
  "geometry": {"coordinates":[-3.7017951012,40.244354248],"type":"Point"}
}