{
  "type": "Feature",
  "properties": {
    "addr:full":"Calle de Monte Perdido, 93 Madrid Madrid 28053",
    "addr:housenumber":"93",
    "addr:postcode":"madrid;28053",
    "addr:street":"Calle De Monte Perdido",
    "iso:country":"ES",
    "sg:address":"Calle de Monte Perdido, 93",
    "sg:city":"Madrid",
    "sg:orig_category":"Empresarios",
    "sg:phone":"+34 914 78 80 93",
    "sg:postcode":"28053",
    "sg:province":"Madrid",
    "wof:name":"Danico 2004 S.l.",
    "wof:placetype":"venue"
},
  "geometry": {"coordinates":[-3.6649830341,40.3929405212],"type":"Point"}
}