{
  "type": "Feature",
  "properties": {
    "addr:full":"Calle de Ceramista Abad, 17 Onda Castell\u00f3n 12200",
    "addr:housenumber":"17",
    "addr:postcode":"12200",
    "addr:street":"Calle De Ceramista Abad;Castello\u0301N",
    "iso:country":"ES",
    "sg:address":"Calle de Ceramista Abad, 17",
    "sg:city":"Onda",
    "sg:orig_category":"Frutas, Legumbres Frescas Y Tempranas (al Por Menor)",
    "sg:phone":"+34 964 77 06 57",
    "sg:postcode":"12200",
    "sg:province":"Castell\u00f3n",
    "wof:name":"Fores Peris Maria Del Carmen",
    "wof:placetype":"venue"
},
  "geometry": {"coordinates":[-0.2641183138,39.966381073],"type":"Point"}
}