{
  "type": "Feature",
  "properties": {
    "addr:full":"Rua Doutor Fleming, 4 Lugo Lugo 27002",
    "addr:housenumber":"4",
    "addr:postcode":"27002",
    "addr:street":"Rua Doutor Fleming",
    "iso:country":"ES",
    "sg:address":"Rua Doutor Fleming, 4",
    "sg:city":"Lugo",
    "sg:orig_category":"Carnicer\u00cdas, Carnicer\u00cdas",
    "sg:phone":"+34 982 22 57 76",
    "sg:postcode":"27002",
    "sg:province":"Lugo",
    "wof:name":"Pesuma S.coop.galega",
    "wof:placetype":"venue"
},
  "geometry": {"coordinates":[-7.5547938347,43.0055770874],"type":"Point"}
}