{
  "type": "Feature",
  "properties": {
    "iso:country":"ES",
    "sg:address":"Mdez. Pelayo, 5",
    "sg:city":"Andratx",
    "sg:orig_category":"Empresas De Carpinter\u00cda Met\u00c1lica",
    "sg:phone":"+34 971 13 71 27",
    "sg:postcode":"07150",
    "sg:province":"Islas Baleares",
    "wof:name":"Carpinteria Metalica Mj C.b.",
    "wof:placetype":"venue"
},
  "geometry": {"coordinates":[2.4200029373,39.5731124878],"type":"Point"}
}