{
  "type": "Feature",
  "properties": {
    "addr:full":"Calle de Fuerte, S/n Marbella M\u00e1laga 29600",
    "addr:postcode":"29600",
    "addr:street":"Calle De Fuerte S / N;Ma\u0301Laga",
    "iso:country":"ES",
    "sg:address":"Calle de Fuerte, S/n",
    "sg:city":"Marbella",
    "sg:orig_category":"Molduras, Junquillos, Listones Y Molduras Perforadas",
    "sg:phone":"+34 952 77 64 79",
    "sg:postcode":"29600",
    "sg:province":"M\u00e1laga",
    "wof:name":"The Bottle Bar",
    "wof:placetype":"venue"
},
  "geometry": {"coordinates":[-4.8838090897,36.5081710815],"type":"Point"}
}