{
  "type": "Feature",
  "properties": {
    "addr:full":"Pla\u00c7 Mercat, 14 S. Feliu Guixols Girona 17220",
    "addr:housenumber":"14",
    "addr:postcode":"17220",
    "addr:street":"S. Feliu Guixols",
    "iso:country":"ES",
    "sg:address":"Pla\u00c7 Mercat, 14",
    "sg:city":"S. Feliu Guixols",
    "sg:orig_category":"Asesor\u00cda Fiscal Y Jur\u00cddica",
    "sg:phone":"+34 972 32 59 85",
    "sg:postcode":"17220",
    "sg:province":"Girona",
    "wof:name":"Arnau Planellas Josep",
    "wof:placetype":"venue"
},
  "geometry": {"coordinates":[2.8236999512,41.9817962646],"type":"Point"}
}