{
  "type": "Feature",
  "properties": {
    "addr:full":"Calle de Puerto Rico, 4 Coria C\u00e1ceres 10800",
    "addr:housenumber":"4",
    "addr:postcode":"10800",
    "addr:street":"Calle De Puerto Rico;Ca\u0301Ceres",
    "iso:country":"ES",
    "sg:address":"Calle de Puerto Rico, 4",
    "sg:city":"Coria",
    "sg:orig_category":"Asociaciones Y Clubs Deportivos",
    "sg:phone":"+34 927 50 01 73",
    "sg:postcode":"10800",
    "sg:province":"C\u00e1ceres",
    "wof:name":"Gordo Corrales Raquel",
    "wof:placetype":"venue"
},
  "geometry": {"coordinates":[-6.536315918,39.9887390137],"type":"Point"}
}