{
  "type": "Feature",
  "properties": {
    "iso:country":"ES",
    "sg:address":"Noalla, S/n",
    "sg:city":"Noalla",
    "sg:orig_category":"Calefacci\u00d3n Central: Material (fabricaci\u00d3n, Al Por Mayor)",
    "sg:phone":"+34 988 23 62 60",
    "sg:postcode":"32915",
    "sg:province":"Ourense",
    "wof:name":"Clinoil S.l.",
    "wof:placetype":"venue"
},
  "geometry": {"coordinates":[-7.8382239342,42.2857704163],"type":"Point"}
}