{
  "type": "Feature",
  "properties": {
    "iso:country":"ES",
    "sg:address":"Avda Mediterraneo (del), 11",
    "sg:city":"Almeria",
    "sg:orig_category":"Mec\u00c1nico Del Autom\u00d3vil",
    "sg:phone":"+34 950 25 20 56",
    "sg:postcode":"04007",
    "sg:province":"Almer\u00eda",
    "wof:name":"Escobar Alcala Francisco",
    "wof:placetype":"venue"
},
  "geometry": {"coordinates":[-2.4459590912,36.8300285339],"type":"Point"}
}