{
  "type": "Feature",
  "properties": {
    "addr:full":"Port, S/n Tarragona Tarragona 43004",
    "addr:housenumber":"s / n",
    "addr:postcode":"43004",
    "addr:street":"Port",
    "iso:country":"ES",
    "sg:address":"Port, S/n",
    "sg:city":"Tarragona",
    "sg:orig_category":"Agentes, Concesionarios Y Sucursales De Veh\u00cdculos",
    "sg:phone":"+34 977 54 14 18",
    "sg:postcode":"43004",
    "sg:province":"Tarragona",
    "sg:website":"www.grupo-cat.com",
    "wof:name":"Cat Espa\u00f1a Fletamentos Y Transportes S.a.",
    "wof:placetype":"venue"
},
  "geometry": {"coordinates":[1.2541049719,41.1169281006],"type":"Point"}
}