{
  "type": "Feature",
  "properties": {
    "iso:country":"ES",
    "sg:address":"Av. Colmenar Viejo, 37",
    "sg:city":"Tres Cantos",
    "sg:orig_category":"Cristaler\u00cdas",
    "sg:phone":"+34 918 03 15 16",
    "sg:postcode":"28760",
    "sg:province":"Madrid",
    "wof:name":"Villa Perez Jose Luis",
    "wof:placetype":"venue"
},
  "geometry": {"coordinates":[-3.7157459259,40.6064720154],"type":"Point"}
}