{
  "type": "Feature",
  "properties": {
    "addr:full":"Ctra. Madrid-valencia, S/n Montalbo Cuenca 16440",
    "addr:housenumber":"s / n",
    "addr:postcode":"16440",
    "addr:street":"Ctra. Madrid-Valencia",
    "iso:country":"ES",
    "sg:address":"Ctra. Madrid-valencia, S/n",
    "sg:city":"Montalbo",
    "sg:orig_category":"Centros Empresariales",
    "sg:phone":"+34 969 13 04 30",
    "sg:postcode":"16440",
    "sg:province":"Cuenca",
    "wof:name":"Colectivo Europeo De Transportes S.l.u.",
    "wof:placetype":"venue"
},
  "geometry": {"coordinates":[-2.6693940163,39.8765182495],"type":"Point"}
}