{
  "type": "Feature",
  "properties": {
    "iso:country":"ES",
    "sg:address":"Carrer de Wagner, 59",
    "sg:city":"Terrassa",
    "sg:orig_category":"Empresas De Pintura Y Revestimientos",
    "sg:phone":"+34 937 85 69 39",
    "sg:postcode":"08222",
    "sg:province":"Barcelona",
    "wof:name":"Fajardo Girones Felipe",
    "wof:placetype":"venue"
},
  "geometry": {"coordinates":[2.0225710869,41.5618171692],"type":"Point"}
}