{
  "type": "Feature",
  "properties": {
    "addr:full":"Avda Angeles (de Los), 26 Getafe Madrid 28903",
    "addr:housenumber":"26",
    "addr:postcode":"28903",
    "addr:street":"Avda Angeles De Los",
    "iso:country":"ES",
    "sg:address":"Avda Angeles (de Los), 26",
    "sg:city":"Getafe",
    "sg:orig_category":"Centros De Educaci\u00d3n Especial",
    "sg:phone":"+34 916 83 71 07",
    "sg:postcode":"28903",
    "sg:province":"Madrid",
    "wof:name":"Comunidad Autonoma De Madrid-centros De Educacion",
    "wof:placetype":"venue"
},
  "geometry": {"coordinates":[-3.7182469368,40.3093032837],"type":"Point"}
}