{
  "type": "Feature",
  "properties": {
    "iso:country":"ES",
    "sg:address":"Rua Eduardo Pondal, S/n",
    "sg:city":"Foz",
    "sg:orig_category":"Zapatos (al Por Menor)",
    "sg:phone":"+34 982 13 23 54",
    "sg:postcode":"27780",
    "sg:province":"Lugo",
    "wof:name":"Otero Castro Jose",
    "wof:placetype":"venue"
},
  "geometry": {"coordinates":[-7.2569041252,43.5692062378],"type":"Point"}
}