{
  "type": "Feature",
  "properties": {
    "addr:full":"Calle de Martinez Artola Pedro, 4 Bilbao Vizcaya 48012",
    "addr:housenumber":"4",
    "addr:postcode":"48012",
    "addr:street":"Calle De Martinez Artola Pedro",
    "iso:country":"ES",
    "sg:address":"Calle de Martinez Artola Pedro, 4",
    "sg:city":"Bilbao",
    "sg:orig_category":"Camiser\u00cda Y Ropa Interior Masculina (al Por Menor)",
    "sg:phone":"+34 944 43 24 58",
    "sg:postcode":"48012",
    "sg:province":"Vizcaya",
    "sg:website":"www.sanzmodahombre.com",
    "wof:name":"Sanz Sanchez Ana Isabel",
    "wof:placetype":"venue"
},
  "geometry": {"coordinates":[-2.9350290298,43.2570533752],"type":"Point"}
}