{
  "type": "Feature",
  "properties": {
    "addr:full":"Barr Padierne, S/n Navajeda Cantabria 39715",
    "addr:housenumber":"s / n",
    "addr:postcode":"39715",
    "addr:street":"Barr Padierne",
    "iso:country":"ES",
    "sg:address":"Barr Padierne, S/n",
    "sg:city":"Navajeda",
    "sg:orig_category":"Cr\u00cda De Animales",
    "sg:phone":"+34 942 52 51 08",
    "sg:postcode":"39715",
    "sg:province":"Cantabria",
    "wof:name":"Safarral",
    "wof:placetype":"venue"
},
  "geometry": {"coordinates":[-3.6829760075,43.3787002563],"type":"Point"}
}