{
  "type": "Feature",
  "properties": {
    "addr:full":"Calle de Goya, 3 Ubeda Ja\u00e9n 23400",
    "addr:housenumber":"3",
    "addr:postcode":"23400",
    "addr:street":"Calle De Goya;Jae\u0301N",
    "iso:country":"ES",
    "sg:address":"Calle de Goya, 3",
    "sg:city":"Ubeda",
    "sg:orig_category":"Contenedores (mercanc\u00cdas)",
    "sg:phone":"+34 953 79 20 49",
    "sg:postcode":"23400",
    "sg:province":"Ja\u00e9n",
    "wof:name":"Logistica Ubeda S.l.",
    "wof:placetype":"venue"
},
  "geometry": {"coordinates":[-3.3750030994,38.015296936],"type":"Point"}
}