{
  "type": "Feature",
  "properties": {
    "iso:country":"ES",
    "sg:address":"Calle de Real, 48",
    "sg:city":"Chillaron Cuenca",
    "sg:orig_category":"Estancos",
    "sg:phone":"+34 969 27 30 45",
    "sg:postcode":"16190",
    "sg:province":"Cuenca",
    "wof:name":"Bele\u00f1a Palomo Angel",
    "wof:placetype":"venue"
},
  "geometry": {"coordinates":[-2.2208120823,40.104057312],"type":"Point"}
}