{
  "type": "Feature",
  "properties": {
    "addr:full":"Calle de Doctor Fleming, 37 Alzira Valencia 46600",
    "addr:housenumber":"37",
    "addr:postcode":"46600",
    "addr:street":"Calle De Doctor Fleming",
    "iso:country":"ES",
    "sg:address":"Calle de Doctor Fleming, 37",
    "sg:city":"Alzira",
    "sg:classifiers":[
        {
            "category":"Personal",
            "subcategory":"Barber",
            "type":"Services"
        }
    ],
    "sg:phone":"+34 962 41 76 61",
    "sg:postcode":"46600",
    "sg:province":"Valencia",
    "sg:tags":[
        "caballeros",
        "de",
        "peluqueros"
    ],
    "wof:name":"Mansergas Esteve Jose Antonio",
    "wof:placetype":"venue"
},
  "geometry": {"coordinates":[-0.4325760901,39.1454162598],"type":"Point"}
}