{
  "type": "Feature",
  "properties": {
    "iso:country":"ES",
    "sg:address":"Carr Ramon Y Cajal, (de), 16",
    "sg:city":"Carlet",
    "sg:orig_category":"Muebles, Minoristas",
    "sg:phone":"+34 962 53 00 67",
    "sg:postcode":"46240",
    "sg:province":"Valencia",
    "wof:name":"Mobles Valero Aparisi S.l.",
    "wof:placetype":"venue"
},
  "geometry": {"coordinates":[-0.5185610056,39.2248878479],"type":"Point"}
}