{
  "type": "Feature",
  "properties": {
    "addr:full":"Mercamurcia, S/n El Palmar Murcia 30120",
    "addr:housenumber":"/ n",
    "addr:postcode":"30120",
    "addr:street":"Mercamurcia S",
    "iso:country":"ES",
    "sg:address":"Mercamurcia, S/n",
    "sg:city":"El Palmar",
    "sg:orig_category":"Fabricaci\u00d3n, Comercio De Flores Y Plantas Artificiales",
    "sg:phone":"+34 968 86 93 30",
    "sg:postcode":"30120",
    "sg:province":"Murcia",
    "wof:name":"Arcoflor S.l.",
    "wof:placetype":"venue"
},
  "geometry": {"coordinates":[-1.1922161579,37.9298744202],"type":"Point"}
}