{
  "type": "Feature",
  "properties": {
    "iso:country":"ES",
    "sg:address":"R Exterior, 12",
    "sg:city":"Chauchina",
    "sg:orig_category":"Chapister\u00cda",
    "sg:phone":"+34 958 44 69 97",
    "sg:postcode":"18330",
    "sg:province":"Granada",
    "wof:name":"Avimotor 86 S.l.",
    "wof:placetype":"venue"
},
  "geometry": {"coordinates":[-3.7725400925,37.2014160156],"type":"Point"}
}