{
  "type": "Feature",
  "properties": {
    "addr:full":"Psaj Gutierrez Ortega, 2 Ciudad Real Ciudad Real 13001",
    "addr:postcode":"13001",
    "addr:street":"Ortega 2",
    "iso:country":"ES",
    "sg:address":"Psaj Gutierrez Ortega, 2",
    "sg:city":"Ciudad Real",
    "sg:orig_category":"\u00d3ptica: Instrumentos (fabricaci\u00d3n)",
    "sg:phone":"+34 926 21 72 07",
    "sg:postcode":"13001",
    "sg:province":"Ciudad Real",
    "wof:name":"Vision  Blanca",
    "wof:placetype":"venue"
},
  "geometry": {"coordinates":[-3.9297740459,38.9832954407],"type":"Point"}
}