{
  "type": "Feature",
  "properties": {
    "iso:country":"ES",
    "sg:address":"Calle de Jove Y Canella, 1",
    "sg:city":"Langreo",
    "sg:orig_category":"Empresarios",
    "sg:phone":"+34 985 68 27 64",
    "sg:postcode":"33900",
    "sg:province":"Asturias",
    "wof:name":"Fundacion Benito Jeronimo Feijoo",
    "wof:placetype":"venue"
},
  "geometry": {"coordinates":[-5.6761698723,43.2936553955],"type":"Point"}
}