{
  "type": "Feature",
  "properties": {
    "iso:country":"ES",
    "sg:address":"Avda Andalucia, 26",
    "sg:city":"Malaga",
    "sg:orig_category":"Laboratorios Farmac\u00c9uticos",
    "sg:phone":"+34 952 27 12 26",
    "sg:postcode":"29007",
    "sg:province":"M\u00e1laga",
    "wof:name":"Sanchez Medina Isabel",
    "wof:placetype":"venue"
},
  "geometry": {"coordinates":[-4.4334559441,36.7172966003],"type":"Point"}
}