{
  "type": "Feature",
  "properties": {
    "addr:full":"Calle de Donantes De Sangre, 2 Najera La Rioja 26300",
    "addr:housenumber":"2",
    "addr:postcode":"26300",
    "addr:street":"Calle De Donantes De Sangre;Rioja",
    "iso:country":"ES",
    "sg:address":"Calle de Donantes De Sangre, 2",
    "sg:city":"Najera",
    "sg:orig_category":"Asesor\u00cda Fiscal Y Jur\u00cddica",
    "sg:phone":"+34 941 36 29 91",
    "sg:postcode":"26300",
    "sg:province":"La Rioja",
    "wof:name":"San Fernando Asesores S.l.",
    "wof:placetype":"venue"
},
  "geometry": {"coordinates":[-2.7309548855,42.4163742065],"type":"Point"}
}