{
  "type": "Feature",
  "properties": {
    "addr:full":"Calle de Gran Via, 17 Sax Alicante 03630",
    "addr:housenumber":"17",
    "addr:postcode":"03630",
    "addr:street":"Calle De Gran Via",
    "iso:country":"ES",
    "sg:address":"Calle de Gran Via, 17",
    "sg:city":"Sax",
    "sg:orig_category":"\u00d3ptica: Instrumentos (fabricaci\u00d3n)",
    "sg:phone":"+34 965 47 51 50",
    "sg:postcode":"03630",
    "sg:province":"Alicante",
    "wof:name":"Optica Sax S.l.",
    "wof:placetype":"venue"
},
  "geometry": {"coordinates":[-0.8195319772,38.5356636047],"type":"Point"}
}