{
  "type": "Feature",
  "properties": {
    "iso:country":"ES",
    "sg:address":"Calle de Vall De Uxo, 41",
    "sg:city":"Castellon",
    "sg:orig_category":"Promotores Constructores",
    "sg:phone":"+34 964 24 24 32",
    "sg:postcode":"12004",
    "sg:province":"Castell\u00f3n",
    "wof:name":"Dragados S.a.",
    "wof:placetype":"venue"
},
  "geometry": {"coordinates":[-0.0481600016,39.9925613403],"type":"Point"}
}