{
  "type": "Feature",
  "properties": {
    "iso:country":"ES",
    "sg:address":"Carrer de Modolell, 31",
    "sg:city":"Barcelona",
    "sg:orig_category":"M\u00c9dicos: Cirug\u00cda Pl\u00c1stica, Reconstructiva Y Est\u00c9tica",
    "sg:phone":"+34 932 09 77 99",
    "sg:postcode":"08021",
    "sg:province":"Barcelona",
    "sg:website":"www.vicario.net",
    "wof:name":"Vicario Sastre Josefina",
    "wof:placetype":"venue"
},
  "geometry": {"coordinates":[2.1372430325,41.3991394043],"type":"Point"}
}