{
  "type": "Feature",
  "properties": {
    "addr:full":"Carr Rosari, Del, 2 Castell Islas Baleares 07720",
    "addr:housenumber":"2",
    "addr:postcode":"07720",
    "addr:street":"Carr Rosari Del",
    "iso:country":"ES",
    "sg:address":"Carr Rosari, Del, 2",
    "sg:city":"Castell",
    "sg:orig_category":"Partidos Pol\u00cdticos",
    "sg:phone":"+34 971 35 18 24",
    "sg:postcode":"07720",
    "sg:province":"Islas Baleares",
    "wof:name":"Partido Popular",
    "wof:placetype":"venue"
},
  "geometry": {"coordinates":[4.2858448029,39.879650116],"type":"Point"}
}