{
  "type": "Feature",
  "properties": {
    "iso:country":"ES",
    "sg:address":"Calle de San Lorenzo, 13",
    "sg:city":"Villafruela",
    "sg:orig_category":"Cajas Para Embalar",
    "sg:phone":"+34 947 17 36 54",
    "sg:postcode":"09344",
    "sg:province":"Burgos",
    "wof:name":"Caja Rural De Burgos",
    "wof:placetype":"venue"
},
  "geometry": {"coordinates":[-3.9121890068,41.9185791016],"type":"Point"}
}