{
  "type": "Feature",
  "properties": {
    "iso:country":"ES",
    "sg:address":"Calle de Padre Salvador Barri, 17",
    "sg:city":"Onda",
    "sg:orig_category":"Desinfecci\u00d3n, Desinsectaci\u00d3n, Desratizaci\u00d3n",
    "sg:phone":"+34 964 60 10 00",
    "sg:postcode":"12200",
    "sg:province":"Castell\u00f3n",
    "wof:name":"Gorris Herrero Manuel",
    "wof:placetype":"venue"
},
  "geometry": {"coordinates":[-0.2641310096,39.9642295837],"type":"Point"}
}