{
  "type": "Feature",
  "properties": {
    "addr:full":"Avda Palacio Valdes, 36 Ribadesella Asturias 33560",
    "addr:housenumber":"36",
    "addr:postcode":"33560",
    "addr:street":"Avda Palacio Valdes",
    "iso:country":"ES",
    "sg:address":"Avda Palacio Valdes, 36",
    "sg:city":"Ribadesella",
    "sg:orig_category":"Electricidad: Instaladores",
    "sg:phone":"+34 985 85 81 11",
    "sg:postcode":"33560",
    "sg:province":"Asturias",
    "wof:name":"Hermanos Silva C.b.",
    "wof:placetype":"venue"
},
  "geometry": {"coordinates":[-5.0619029999,43.4565353394],"type":"Point"}
}