{
  "type": "Feature",
  "properties": {
    "addr:full":"Calle de Nueva, 9 Cantimpalos Segovia 40360",
    "addr:housenumber":"9",
    "addr:postcode":"40360",
    "addr:street":"Calle De Nueva;Segovia",
    "iso:country":"ES",
    "sg:address":"Calle de Nueva, 9",
    "sg:city":"Cantimpalos",
    "sg:orig_category":"Iglesia Cat\u00d3lica",
    "sg:phone":"+34 921 49 60 41",
    "sg:postcode":"40360",
    "sg:province":"Segovia",
    "wof:name":"Obispado Segovia",
    "wof:placetype":"venue"
},
  "geometry": {"coordinates":[-4.1590957642,41.0745353699],"type":"Point"}
}