{
  "type": "Feature",
  "properties": {
    "iso:country":"ES",
    "sg:address":"Carr Ramon I Cajal, S/n",
    "sg:city":"Barbens",
    "sg:orig_category":"Iglesia Cat\u00d3lica",
    "sg:phone":"+34 973 58 05 42",
    "sg:postcode":"25262",
    "sg:province":"Lleida",
    "wof:name":"Bisbat D'urgell",
    "wof:placetype":"venue"
},
  "geometry": {"coordinates":[1.0161550045,41.6782493591],"type":"Point"}
}