{
  "type": "Feature",
  "properties": {
    "addr:full":"Calle de San Rafael, 3 Buzanada Santa Cruz De Tenerife 38626",
    "addr:housenumber":"3",
    "addr:postcode":"38626",
    "addr:street":"Calle De San Rafael",
    "iso:country":"ES",
    "sg:address":"Calle de San Rafael, 3",
    "sg:city":"Buzanada",
    "sg:orig_category":"Asociaciones Humanitarias, De Cooperaci\u00d3n, De Acci\u00d3n Social",
    "sg:phone":"+34 922 72 23 12",
    "sg:postcode":"38626",
    "sg:province":"Santa Cruz De Tenerife",
    "wof:name":"Ayuntamiento De Arona-patronato Bienestar Social",
    "wof:placetype":"venue"
},
  "geometry": {"coordinates":[-16.6554794312,28.0726890564],"type":"Point"}
}