{
  "type": "Feature",
  "properties": {
    "iso:country":"ES",
    "sg:address":"Calle de Amparo, 51",
    "sg:city":"Madrid",
    "sg:orig_category":"Oficinas: Suministros Para (fabricaci\u00d3n, Al Por Mayor)",
    "sg:phone":"+34 914 67 49 59",
    "sg:postcode":"28012",
    "sg:province":"Madrid",
    "wof:name":"Alhambra Comercio Exterior S.l.",
    "wof:placetype":"venue"
},
  "geometry": {"coordinates":[-3.7026848793,40.4091415405],"type":"Point"}
}