{
  "type": "Feature",
  "properties": {
    "iso:country":"ES",
    "sg:address":"Carrer de Vidal I Guasch, 43",
    "sg:city":"Barcelona",
    "sg:orig_category":"Artes Gr\u00c1ficas, Artes Pl\u00c1sticas (curso)",
    "sg:phone":"+34 932 76 09 36",
    "sg:postcode":"08042",
    "sg:province":"Barcelona",
    "wof:name":"Retol Grafic Nou Barris S.l.l.",
    "wof:placetype":"venue"
},
  "geometry": {"coordinates":[2.1740479469,41.4466094971],"type":"Point"}
}