{
  "type": "Feature",
  "properties": {
    "iso:country":"ES",
    "sg:address":"Carr Roger De Flor, 67",
    "sg:city":"Badalona",
    "sg:orig_category":"Lavado, Limpieza De Veh\u00cdculos",
    "sg:phone":"+34 933 83 47 05",
    "sg:postcode":"08912",
    "sg:province":"Barcelona",
    "wof:name":"Badbrill S.l.",
    "wof:placetype":"venue"
},
  "geometry": {"coordinates":[2.2418670654,41.443069458],"type":"Point"}
}