{
  "type": "Feature",
  "properties": {
    "iso:country":"ES",
    "sg:address":"Rua Benigno Quiroga, S/n",
    "sg:city":"Sarria",
    "sg:orig_category":"Distribuci\u00d3n De Petr\u00d3leo Y Derivados",
    "sg:phone":"+34 982 53 13 61",
    "sg:postcode":"27600",
    "sg:province":"Lugo",
    "wof:name":"Estacion De Servicio A Rosareira S.l.",
    "wof:placetype":"venue"
},
  "geometry": {"coordinates":[-7.4124760628,42.7773284912],"type":"Point"}
}