{
  "type": "Feature",
  "properties": {
    "iso:country":"ES",
    "sg:address":"Avda Deportes De Los, 13",
    "sg:city":"Fraga",
    "sg:orig_category":"Ense\u00d1anza: Idiomas",
    "sg:phone":"+34 974 47 28 68",
    "sg:postcode":"22520",
    "sg:province":"Huesca",
    "wof:name":"Vilar Royes Francisca",
    "wof:placetype":"venue"
},
  "geometry": {"coordinates":[0.3438299894,41.5223045349],"type":"Point"}
}