{
  "type": "Feature",
  "properties": {
    "addr:full":"Ctra Nacional 120, Km. 0564,0 Ventosela Ourense 32414",
    "addr:postcode":"32414",
    "addr:street":"Ctra Nacional 120 Km. 0564,0",
    "iso:country":"ES",
    "sg:address":"Ctra Nacional 120, Km. 0564,0",
    "sg:city":"Ventosela",
    "sg:orig_category":"Comercio De Piezas De Recambio Y De Accesorios De Veh\u00cdculos, Veh\u00cdculos Industriales",
    "sg:phone":"+34 988 47 13 67",
    "sg:postcode":"32414",
    "sg:province":"Ourense",
    "wof:name":"Barrosocar S.l.",
    "wof:placetype":"venue"
},
  "geometry": {"coordinates":[-8.1131191254,42.3067359924],"type":"Point"}
}