{
  "type": "Feature",
  "properties": {
    "addr:full":"Rbla Independencia, 11 Silla Valencia 46460",
    "addr:housenumber":"11",
    "addr:postcode":"46460",
    "addr:street":"Rbla Independencia",
    "iso:country":"ES",
    "sg:address":"Rbla Independencia, 11",
    "sg:city":"Silla",
    "sg:orig_category":"Moda",
    "sg:phone":"+34 961 20 00 07",
    "sg:postcode":"46460",
    "sg:province":"Valencia",
    "wof:name":"Alba Forner Maria Carmen",
    "wof:placetype":"venue"
},
  "geometry": {"coordinates":[-0.4127331972,39.3616218567],"type":"Point"}
}