{
  "type": "Feature",
  "properties": {
    "iso:country":"ES",
    "sg:address":"Calle de Enlace Mayorazgo-mercatenerife, 2",
    "sg:city":"Santa Cruz De Tenerife",
    "sg:orig_category":"Alquiler De Veh\u00cdculos: Turismos Y Utilitarios",
    "sg:phone":"+34 922 20 72 72",
    "sg:postcode":"38009",
    "sg:province":"Santa Cruz De Tenerife",
    "wof:name":"Archipielago Renting S.l.",
    "wof:placetype":"venue"
},
  "geometry": {"coordinates":[-16.2772979736,28.4480438232],"type":"Point"}
}