{
  "type": "Feature",
  "properties": {
    "addr:full":"Calle de Paraiso, 27 Vergel C\u00e1diz 11540",
    "addr:housenumber":"27",
    "addr:postcode":"11540",
    "addr:street":"Calle De Paraiso;Ca\u0301Diz",
    "iso:country":"ES",
    "sg:address":"Calle de Paraiso, 27",
    "sg:city":"Vergel",
    "sg:orig_category":"Empresas De Trabajos P\u00dablicos",
    "sg:phone":"+34 956 38 31 65",
    "sg:postcode":"11540",
    "sg:province":"C\u00e1diz",
    "wof:name":"Josma Sanlucar S.l.",
    "wof:placetype":"venue"
},
  "geometry": {"coordinates":[-6.3575987816,36.777721405],"type":"Point"}
}