{
  "type": "Feature",
  "properties": {
    "addr:full":"Plaz Hauries, 2 Jerez De La Frontera C\u00e1diz 11405",
    "addr:housenumber":"2",
    "addr:postcode":"11405",
    "addr:street":"Plaz Hauries",
    "iso:country":"ES",
    "sg:address":"Plaz Hauries, 2",
    "sg:city":"Jerez De La Frontera",
    "sg:orig_category":"Cueros Y Pieles (al Por Mayor)",
    "sg:phone":"+34 956 18 59 48",
    "sg:postcode":"11405",
    "sg:province":"C\u00e1diz",
    "wof:name":"Adiafa S.l.",
    "wof:placetype":"venue"
},
  "geometry": {"coordinates":[-6.1076450348,36.6982269287],"type":"Point"}
}