{
  "type": "Feature",
  "properties": {
    "iso:country":"ES",
    "sg:address":"Avda Lancia, 12",
    "sg:city":"Le\u00f3n",
    "sg:orig_category":"Electricidad (montaje, Ensamblaje De Componentes)",
    "sg:phone":"+34 987 20 85 15",
    "sg:postcode":"24004",
    "sg:province":"Le\u00f3n",
    "wof:name":"Manzanera Carballo Carmen",
    "wof:placetype":"venue"
},
  "geometry": {"coordinates":[-5.5742788315,42.5938110352],"type":"Point"}
}