{
  "type": "Feature",
  "properties": {
    "iso:country":"ES",
    "sg:address":"Rua Galicia, 4",
    "sg:city":"Grove",
    "sg:orig_category":"Empresas De Pintura Y Revestimientos",
    "sg:phone":"+34 986 73 23 75",
    "sg:postcode":"36980",
    "sg:province":"Pontevedra",
    "wof:name":"Apli-hogar Sl",
    "wof:placetype":"venue"
},
  "geometry": {"coordinates":[-8.8675994873,42.4890937805],"type":"Point"}
}