{
  "type": "Feature",
  "properties": {
    "iso:country":"ES",
    "sg:address":"Via Augusta, 18",
    "sg:city":"Tarragona",
    "sg:orig_category":"Florister\u00cdas",
    "sg:phone":"+34 977 24 29 22",
    "sg:postcode":"43003",
    "sg:province":"Tarragona",
    "wof:name":"La Floristeria C.b.",
    "wof:placetype":"venue"
},
  "geometry": {"coordinates":[1.2598179579,41.1161651611],"type":"Point"}
}