{
  "type": "Feature",
  "properties": {
    "addr:full":"Calle de Moscu, 3 Benidorm Alicante 03500",
    "addr:housenumber":"3",
    "addr:postcode":"03500",
    "addr:street":"Calle De Moscu",
    "iso:country":"ES",
    "sg:address":"Calle de Moscu, 3",
    "sg:city":"Benidorm",
    "sg:orig_category":"Masajistas Kinesiterapeutas",
    "sg:phone":"+34 966 80 51 05",
    "sg:postcode":"03500",
    "sg:province":"Alicante",
    "wof:name":"Perez Martin Clementino",
    "wof:placetype":"venue"
},
  "geometry": {"coordinates":[-0.1023719981,38.5415115356],"type":"Point"}
}