{
  "type": "Feature",
  "properties": {
    "addr:full":"Ctra Sentmenat, 44 Castellar Valles Barcelona 08211",
    "addr:housenumber":"44",
    "addr:postcode":"08211",
    "addr:street":"Ctra Sentmenat",
    "iso:country":"ES",
    "sg:address":"Ctra Sentmenat, 44",
    "sg:city":"Castellar Valles",
    "sg:orig_category":"Agencias De Viajes",
    "sg:phone":"+34 937 47 34 20",
    "sg:postcode":"08211",
    "sg:province":"Barcelona",
    "sg:website":"www.halconviajes.com",
    "wof:name":"Viajes Halcon S.a.",
    "wof:placetype":"venue"
},
  "geometry": {"coordinates":[2.0857300758,41.6151885986],"type":"Point"}
}