{
  "type": "Feature",
  "properties": {
    "addr:full":"Carrer de Narcis Fors, 5 Lloret Mar Girona 17310",
    "addr:housenumber":"5",
    "addr:postcode":"17310",
    "addr:street":"Carrer De Narcis Fors",
    "iso:country":"ES",
    "sg:address":"Carrer de Narcis Fors, 5",
    "sg:city":"Lloret Mar",
    "sg:orig_category":"Fabricaci\u00d3n, Distribuci\u00d3n De Discos, V\u00cddeodiscos Y Musicassettes",
    "sg:phone":"+34 972 36 74 42",
    "sg:postcode":"17310",
    "sg:province":"Girona",
    "wof:name":"Botey Collgros Alfons",
    "wof:placetype":"venue"
},
  "geometry": {"coordinates":[2.8482398987,41.7024688721],"type":"Point"}
}