{
  "type": "Feature",
  "properties": {
    "addr:full":"Carr Sant Josep, 2 Bellpuig Lleida 25250",
    "addr:housenumber":"2",
    "addr:postcode":"25250",
    "addr:street":"Carr Sant Josep",
    "iso:country":"ES",
    "sg:address":"Carr Sant Josep, 2",
    "sg:city":"Bellpuig",
    "sg:orig_category":"Empresarios",
    "sg:phone":"+34 973 32 23 76",
    "sg:postcode":"25250",
    "sg:province":"Lleida",
    "wof:name":"Mata Torra Josep",
    "wof:placetype":"venue"
},
  "geometry": {"coordinates":[1.0121680498,41.6257820129],"type":"Point"}
}