{
  "type": "Feature",
  "properties": {
    "addr:full":"Calle de Belgica, 3 Roquetas Mar Almer\u00eda 04740",
    "addr:housenumber":"3",
    "addr:postcode":"04740",
    "addr:street":"Calle De Belgica",
    "iso:country":"ES",
    "sg:address":"Calle de Belgica, 3",
    "sg:city":"Roquetas Mar",
    "sg:orig_category":"Producci\u00d3n, Venta De Productos De Agricultura Biol\u00d3gica",
    "sg:phone":"+34 950 32 18 51",
    "sg:postcode":"04740",
    "sg:province":"Almer\u00eda",
    "wof:name":"Agriarjosa S.l.",
    "wof:placetype":"venue"
},
  "geometry": {"coordinates":[-2.6074576378,36.7755889893],"type":"Point"}
}