{
  "type": "Feature",
  "properties": {
    "addr:full":"Carrer de Flors, 3 Vic Barcelona 08500",
    "addr:housenumber":"3",
    "addr:postcode":"08500",
    "addr:street":"Carrer De Flors",
    "iso:country":"ES",
    "sg:address":"Carrer de Flors, 3",
    "sg:city":"Vic",
    "sg:orig_category":"Pintores",
    "sg:phone":"+34 938 85 44 24",
    "sg:postcode":"08500",
    "sg:province":"Barcelona",
    "wof:name":"Miguel Dorca Andres",
    "wof:placetype":"venue"
},
  "geometry": {"coordinates":[2.2497739792,41.9274787903],"type":"Point"}
}