{
  "type": "Feature",
  "properties": {
    "addr:full":"Calle de Ceron, 17 Jaen Ja\u00e9n 23004",
    "addr:housenumber":"17;jae\u0301n",
    "addr:postcode":"23004",
    "addr:street":"Calle De Ceron",
    "iso:country":"ES",
    "sg:address":"Calle de Ceron, 17",
    "sg:city":"Jaen",
    "sg:orig_category":"Librer\u00cdas",
    "sg:phone":"+34 953 23 47 93",
    "sg:postcode":"23004",
    "sg:province":"Ja\u00e9n",
    "wof:name":"Garcia Calero Jose Luis",
    "wof:placetype":"venue"
},
  "geometry": {"coordinates":[-3.7908759117,37.7664108276],"type":"Point"}
}