{
  "type": "Feature",
  "properties": {
    "iso:country":"ES",
    "sg:address":"Calle de Juan De Herrera, 3",
    "sg:city":"Santander",
    "sg:orig_category":"Bazares, Art\u00cdculos De Limpieza Y De Cocina (al Por Menor)",
    "sg:phone":"+34 942 21 44 41",
    "sg:postcode":"39002",
    "sg:province":"Cantabria",
    "wof:name":"Gutierrez Vega Wenceslao",
    "wof:placetype":"venue"
},
  "geometry": {"coordinates":[-3.8089520931,43.4622306824],"type":"Point"}
}