{
  "type": "Feature",
  "properties": {
    "iso:country":"ES",
    "sg:address":"Carrer de Lluis Auguet, 5",
    "sg:city":"Esparreguera",
    "sg:orig_category":"Empresas De Carpinter\u00cda",
    "sg:phone":"+34 937 77 66 81",
    "sg:postcode":"08292",
    "sg:province":"Barcelona",
    "wof:name":"Tot Alumini Esparraguera S.l.",
    "wof:placetype":"venue"
},
  "geometry": {"coordinates":[1.8720580339,41.5332946777],"type":"Point"}
}