{
  "type": "Feature",
  "properties": {
    "iso:country":"ES",
    "sg:address":"Calle de Fuente De San Pedro, 2",
    "sg:city":"Madrid",
    "sg:orig_category":"Radiocomunicaciones, Telefon\u00cda M\u00d3vil, Radiomensajer\u00cda: Servicios, Comercializaci\u00d3n",
    "sg:phone":"+34 917 75 30 61",
    "sg:postcode":"28032",
    "sg:province":"Madrid",
    "wof:name":"Sholola  Oladipo James",
    "wof:placetype":"venue"
},
  "geometry": {"coordinates":[-3.6042690277,40.4034156799],"type":"Point"}
}