{
  "type": "Feature",
  "properties": {
    "iso:country":"ES",
    "sg:address":"Calle de San Miguel, 14",
    "sg:city":"Burlada",
    "sg:orig_category":"Inform\u00c1tica, Ofim\u00c1tica (estudios, Asesor\u00cda, Ingenier\u00cda, Formaci\u00d3n)",
    "sg:phone":"+34 948 13 60 83",
    "sg:postcode":"31600",
    "sg:province":"Navarra",
    "sg:website":"www.burlada.net",
    "wof:name":"Microchip Sistemas Informaticos S.l.",
    "wof:placetype":"venue"
},
  "geometry": {"coordinates":[-1.6179369688,42.8270530701],"type":"Point"}
}