{
  "type": "Feature",
  "properties": {
    "addr:full":"Trafalgar, 3 Cabrera Mar Barcelona 08349",
    "addr:housenumber":"3",
    "addr:postcode":"08349",
    "addr:street":"Trafalgar",
    "iso:country":"ES",
    "sg:address":"Trafalgar, 3",
    "sg:city":"Cabrera Mar",
    "sg:orig_category":"Ferreter\u00cda Artesanal",
    "sg:phone":"+34 937 59 24 82",
    "sg:postcode":"08349",
    "sg:province":"Barcelona",
    "wof:name":"Meca Export S. A.",
    "wof:placetype":"venue"
},
  "geometry": {"coordinates":[2.39904809,41.5095252991],"type":"Point"}
}