{
  "type": "Feature",
  "properties": {
    "iso:country":"ES",
    "sg:address":"Calle de Conrado Del Campo, 8",
    "sg:city":"Madrid",
    "sg:orig_category":"Madera Para Construcci\u00d3n E Industria",
    "sg:phone":"+34 913 20 23 84",
    "sg:postcode":"28027",
    "sg:province":"Madrid",
    "wof:name":"Parquets Lazaro S.l.",
    "wof:placetype":"venue"
},
  "geometry": {"coordinates":[-3.6364612579,40.4425926208],"type":"Point"}
}