{
  "type": "Feature",
  "properties": {
    "addr:full":"Calle de Mazarron, 24 Ensanche-almarjal Murcia 30203",
    "addr:housenumber":"24",
    "addr:postcode":"30203",
    "addr:street":"Calle De Mazarron",
    "iso:country":"ES",
    "sg:address":"Calle de Mazarron, 24",
    "sg:city":"Ensanche-almarjal",
    "sg:orig_category":"Promotores Constructores",
    "sg:phone":"+34 968 31 30 56",
    "sg:postcode":"30203",
    "sg:province":"Murcia",
    "wof:name":"Lopez Mi\u00f1arro Antonio",
    "wof:placetype":"venue"
},
  "geometry": {"coordinates":[-1.1298867464,37.9834747314],"type":"Point"}
}