{
  "type": "Feature",
  "properties": {
    "iso:country":"ES",
    "sg:address":"Praz Constitucion, 1",
    "sg:city":"Meicende",
    "sg:orig_category":"Empresas De Pintura Y Revestimientos",
    "sg:phone":"+34 981 25 00 71",
    "sg:postcode":"15140",
    "sg:province":"La Coru\u00f1a",
    "wof:name":"Martinez Calvelo Jose Luis",
    "wof:placetype":"venue"
},
  "geometry": {"coordinates":[-8.46671772,43.3288497925],"type":"Point"}
}