{
  "type": "Feature",
  "properties": {
    "addr:full":"Calle de Cordoba, S/n Iznajar C\u00f3rdoba 14970",
    "addr:housenumber":"s / n",
    "addr:postcode":"14970",
    "addr:street":"Calle De Cordoba;Co\u0301Rdoba",
    "iso:country":"ES",
    "sg:address":"Calle de Cordoba, S/n",
    "sg:city":"Iznajar",
    "sg:orig_category":"Ropa Para Se\u00d1oras Y Caballeros (al Por Menor)",
    "sg:phone":"+34 957 53 41 50",
    "sg:postcode":"14970",
    "sg:province":"C\u00f3rdoba",
    "wof:name":"K Amisas Iznajar S.l.",
    "wof:placetype":"venue"
},
  "geometry": {"coordinates":[-4.3058519363,37.2568092346],"type":"Point"}
}