{
  "type": "Feature",
  "properties": {
    "addr:full":"Calle de Madrid, 32 Rota C\u00e1diz 11520",
    "addr:housenumber":"32",
    "addr:postcode":"11520",
    "addr:street":"Calle De Madrid;Ca\u0301Diz",
    "iso:country":"ES",
    "sg:address":"Calle de Madrid, 32",
    "sg:city":"Rota",
    "sg:orig_category":"Molduras, Junquillos, Listones Y Molduras Perforadas",
    "sg:phone":"+34 956 81 39 42",
    "sg:postcode":"11520",
    "sg:province":"C\u00e1diz",
    "wof:name":"Sistelcom-telemensaje S.a.",
    "wof:placetype":"venue"
},
  "geometry": {"coordinates":[-6.3603191376,36.62550354],"type":"Point"}
}