{
  "type": "Feature",
  "properties": {
    "iso:country":"ES",
    "sg:address":"Carr Bilbao, 6",
    "sg:city":"Girona",
    "sg:orig_category":"Tapicer\u00cdas",
    "sg:phone":"+34 972 23 17 40",
    "sg:postcode":"17005",
    "sg:province":"Girona",
    "wof:name":"Peinado Perez Eugenio",
    "wof:placetype":"venue"
},
  "geometry": {"coordinates":[2.8099229336,41.9695663452],"type":"Point"}
}