{
  "type": "Feature",
  "properties": {
    "addr:full":"Calle de Cirilo Palomo, 8 Pozuelo De Alarcon Madrid 28223",
    "addr:housenumber":"8",
    "addr:postcode":"28223",
    "addr:street":"Calle De Cirilo Palomo",
    "iso:country":"ES",
    "sg:address":"Calle de Cirilo Palomo, 8",
    "sg:city":"Pozuelo De Alarcon",
    "sg:orig_category":"Cl\u00cdnicas Dentales",
    "sg:phone":"+34 917 15 91 54",
    "sg:postcode":"28223",
    "sg:province":"Madrid",
    "wof:name":"Balmaseda Y De La Llama S.c",
    "wof:placetype":"venue"
},
  "geometry": {"coordinates":[-3.810726881,40.4353904724],"type":"Point"}
}