{
  "type": "Feature",
  "properties": {
    "addr:full":"Calle de Manuel Salda\u00d1a, 4 Badajoz Badajoz 06010",
    "addr:housenumber":"4",
    "addr:postcode":"06010",
    "addr:street":"Calle De Manuel Saldan\u0303A",
    "iso:country":"ES",
    "sg:address":"Calle de Manuel Salda\u00d1a, 4",
    "sg:city":"Badajoz",
    "sg:orig_category":"Artes Gr\u00c1ficas, Artes Pl\u00c1sticas (curso)",
    "sg:phone":"+34 924 24 81 03",
    "sg:postcode":"06010",
    "sg:province":"Badajoz",
    "sg:website":"www.idcreaciongrafica.com",
    "wof:name":"Id Creacion Grafica Extreme\u00d1a Sll",
    "wof:placetype":"venue"
},
  "geometry": {"coordinates":[-6.978913784,38.8690567017],"type":"Point"}
}