{
  "type": "Feature",
  "properties": {
    "addr:full":"Rua Montecelo, 43 Vigo Pontevedra 36207",
    "addr:housenumber":"43",
    "addr:postcode":"36207",
    "addr:street":"Rua Montecelo",
    "iso:country":"ES",
    "sg:address":"Rua Montecelo, 43",
    "sg:city":"Vigo",
    "sg:orig_category":"Agencias Y Asesores De Publicidad",
    "sg:phone":"+34 986 26 41 77",
    "sg:postcode":"36207",
    "sg:province":"Pontevedra",
    "wof:name":"Andres Rivas Juan Carlos",
    "wof:placetype":"venue"
},
  "geometry": {"coordinates":[-8.702671051,42.2418823242],"type":"Point"}
}