{
  "type": "Feature",
  "properties": {
    "addr:full":"Carrer de Goleta, 19 Terrassa Barcelona 08221",
    "addr:housenumber":"19",
    "addr:postcode":"08221",
    "addr:street":"Carrer De Goleta",
    "iso:country":"ES",
    "sg:address":"Carrer de Goleta, 19",
    "sg:city":"Terrassa",
    "sg:orig_category":"Psic\u00d3logos",
    "sg:phone":"+34 937 80 96 31",
    "sg:postcode":"08221",
    "sg:province":"Barcelona",
    "wof:name":"Monge Martinez Nuria",
    "wof:placetype":"venue"
},
  "geometry": {"coordinates":[2.0084979534,41.5628929138],"type":"Point"}
}