{
  "type": "Feature",
  "properties": {
    "addr:full":"Calle de Estame\u00d1eria Vieja, 8 Valencia Valencia 46001",
    "addr:housenumber":"8",
    "addr:postcode":"46001",
    "addr:street":"Calle De Estamen\u0303Eria Vieja",
    "iso:country":"ES",
    "sg:address":"Calle de Estame\u00d1eria Vieja, 8",
    "sg:city":"Valencia",
    "sg:orig_category":"Bisuter\u00cda, Joyer\u00cda, Relojer\u00cda (al Por Menor)",
    "sg:phone":"+34 963 91 66 58",
    "sg:postcode":"46001",
    "sg:province":"Valencia",
    "wof:name":"Soriano Pardo Indalecio",
    "wof:placetype":"venue"
},
  "geometry": {"coordinates":[-0.3778209984,39.4745864868],"type":"Point"}
}