{
  "type": "Feature",
  "properties": {
    "iso:country":"ES",
    "sg:address":"Calle de Rafael Alberti, 1",
    "sg:city":"Pozoblanco",
    "sg:orig_category":"Carnicer\u00cdas, Carnicer\u00cdas",
    "sg:phone":"+34 957 77 32 07",
    "sg:postcode":"14400",
    "sg:province":"C\u00f3rdoba",
    "wof:name":"Diaz Fernandez Diego",
    "wof:placetype":"venue"
},
  "geometry": {"coordinates":[-4.8585357666,38.3792877197],"type":"Point"}
}