{
  "type": "Feature",
  "properties": {
    "addr:full":"Avda Portugal (de), 15 Avila \u00c1vila 05001",
    "addr:housenumber":"15",
    "addr:postcode":"05001",
    "addr:street":"Avda Portugal De;A\u0301Vila",
    "iso:country":"ES",
    "sg:address":"Avda Portugal (de), 15",
    "sg:city":"Avila",
    "sg:orig_category":"Agencias De Viajes",
    "sg:phone":"+34 920 21 40 02",
    "sg:postcode":"05001",
    "sg:province":"\u00c1vila",
    "sg:website":"www.viajeselcorteingles.es",
    "wof:name":"Viajes El Corte Ingles S.a.",
    "wof:placetype":"venue"
},
  "geometry": {"coordinates":[-4.6939258575,40.6575088501],"type":"Point"}
}