{
  "type": "Feature",
  "properties": {
    "iso:country":"ES",
    "sg:address":"Calle de Valdetorres De Jarama, 5",
    "sg:city":"Madrid",
    "sg:orig_category":"Abogados",
    "sg:phone":"+34 913 81 03 21",
    "sg:postcode":"28043",
    "sg:province":"Madrid",
    "wof:name":"Carramolino Fitera Jose Carlos",
    "wof:placetype":"venue"
},
  "geometry": {"coordinates":[-3.6468660831,40.472076416],"type":"Point"}
}