{
  "type": "Feature",
  "properties": {
    "iso:country":"ES",
    "sg:address":"Avda Europa, 86",
    "sg:city":"Malaga",
    "sg:orig_category":"Bazares, Art\u00cdculos De Limpieza Y De Cocina (al Por Menor)",
    "sg:phone":"+34 952 34 53 58",
    "sg:postcode":"29003",
    "sg:province":"M\u00e1laga",
    "wof:name":"Rodriguez Cruz Antonio",
    "wof:placetype":"venue"
},
  "geometry": {"coordinates":[-4.4523148537,36.7003059387],"type":"Point"}
}