{
  "type": "Feature",
  "properties": {
    "addr:full":"Calle de Palmera, 4 Bornos C\u00e1diz 11640",
    "addr:housenumber":"4",
    "addr:postcode":"11640",
    "addr:street":"Calle De Palmera;Ca\u0301Diz",
    "iso:country":"ES",
    "sg:address":"Calle de Palmera, 4",
    "sg:city":"Bornos",
    "sg:orig_category":"Asociaciones, Organismos Culturales Y Socioeducativos",
    "sg:phone":"+34 956 71 23 62",
    "sg:postcode":"11640",
    "sg:province":"C\u00e1diz",
    "wof:name":"Pe\u00f1a Cultural Flamenca Alegria",
    "wof:placetype":"venue"
},
  "geometry": {"coordinates":[-5.7440509796,36.8208847046],"type":"Point"}
}