{
  "type": "Feature",
  "properties": {
    "addr:full":"Calle de Museo, 7 Badajoz Badajoz 06004",
    "addr:housenumber":"7",
    "addr:postcode":"06004",
    "addr:street":"Calle De Museo",
    "iso:country":"ES",
    "sg:address":"Calle de Museo, 7",
    "sg:city":"Badajoz",
    "sg:orig_category":"Asesor\u00cda Fiscal Y Jur\u00cddica",
    "sg:phone":"+34 924 24 45 02",
    "sg:postcode":"06004",
    "sg:province":"Badajoz",
    "wof:name":"Rivera De Alvarado Hernandez Gil Asociados S.l.",
    "wof:placetype":"venue"
},
  "geometry": {"coordinates":[-6.9719538689,38.8724136353],"type":"Point"}
}