{
  "type": "Feature",
  "properties": {
    "iso:country":"ES",
    "sg:address":"Calle de Rosario, 7",
    "sg:city":"Palmas De Gran Canaria",
    "sg:orig_category":"Abogados",
    "sg:phone":"+34 928 32 14 86",
    "sg:postcode":"35001",
    "sg:province":"Las Palmas",
    "wof:name":"Tecniart Proyects S.l.",
    "wof:placetype":"venue"
},
  "geometry": {"coordinates":[-15.415304184,28.0985355377],"type":"Point"}
}