{
  "type": "Feature",
  "properties": {
    "addr:full":"Avda Raza (la), 22 Sevilla Sevilla 41012",
    "addr:housenumber":"22",
    "addr:postcode":"41012",
    "addr:street":"Avda Raza La",
    "iso:country":"ES",
    "sg:address":"Avda Raza (la), 22",
    "sg:city":"Sevilla",
    "sg:orig_category":"Congelados: Productos Alimentarios (al Por Menor)",
    "sg:phone":"+34 954 23 82 61",
    "sg:postcode":"41012",
    "sg:province":"Sevilla",
    "wof:name":"Daliceve S.l.",
    "wof:placetype":"venue"
},
  "geometry": {"coordinates":[-5.9896430969,37.3662452698],"type":"Point"}
}