{
  "type": "Feature",
  "properties": {
    "addr:full":"Carr Academico Maravall, 13 Xativa Valencia 46800",
    "addr:housenumber":"13",
    "addr:postcode":"46800",
    "addr:street":"Carr Academico Maravall",
    "iso:country":"ES",
    "sg:address":"Carr Academico Maravall, 13",
    "sg:city":"Xativa",
    "sg:orig_category":"Diplomas Diversos",
    "sg:phone":"+34 962 27 26 18",
    "sg:postcode":"46800",
    "sg:province":"Valencia",
    "wof:name":"Calabuig Bernabeu Jose",
    "wof:placetype":"venue"
},
  "geometry": {"coordinates":[-0.5152469873,38.9913902283],"type":"Point"}
}