{
  "type": "Feature",
  "properties": {
    "iso:country":"ES",
    "sg:address":"Pg Joan Moreira (de), 11",
    "sg:city":"Tortosa",
    "sg:orig_category":"Discapacitados",
    "sg:phone":"+34 977 44 18 99",
    "sg:postcode":"43500",
    "sg:province":"Tarragona",
    "wof:name":"Sociedad Cooperativa Virgen De La Cinta",
    "wof:placetype":"venue"
},
  "geometry": {"coordinates":[0.5181059837,40.8057632446],"type":"Point"}
}