{
  "type": "Feature",
  "properties": {
    "addr:full":"Calle de Ramon Bautista Claveria, 27 Langreo Asturias 33930",
    "addr:housenumber":"27",
    "addr:postcode":"33930",
    "addr:street":"Calle De Ramon Bautista Claveria",
    "iso:country":"ES",
    "sg:address":"Calle de Ramon Bautista Claveria, 27",
    "sg:city":"Langreo",
    "sg:orig_category":"Tatuajes",
    "sg:phone":"+34 985 68 36 47",
    "sg:postcode":"33930",
    "sg:province":"Asturias",
    "wof:name":"David Matos Gonzalez",
    "wof:placetype":"venue"
},
  "geometry": {"coordinates":[-5.6950922012,43.3085021973],"type":"Point"}
}