{
  "type": "Feature",
  "properties": {
    "iso:country":"ES",
    "sg:address":"Carr Arnals, 5",
    "sg:city":"Vielha",
    "sg:orig_category":"Organismos De Turismo",
    "sg:phone":"+34 973 64 06 85",
    "sg:postcode":"25530",
    "sg:province":"Lleida",
    "sg:website":"www.hostaler.org",
    "wof:name":"Federacio Provincial D'hostaleria De Lleida",
    "wof:placetype":"venue"
},
  "geometry": {"coordinates":[0.793775022,42.70287323],"type":"Point"}
}