{
  "type": "Feature",
  "properties": {
    "addr:full":"Avda Dacio Darias, 6 Valverde Santa Cruz De Tenerife 38910",
    "addr:housenumber":"6",
    "addr:postcode":"38910",
    "addr:street":"Avda Dacio Darias",
    "iso:country":"ES",
    "sg:address":"Avda Dacio Darias, 6",
    "sg:city":"Valverde",
    "sg:orig_category":"Zapatos (al Por Menor)",
    "sg:phone":"+34 922 55 11 73",
    "sg:postcode":"38910",
    "sg:province":"Santa Cruz De Tenerife",
    "wof:name":"Padron Zamora Amos",
    "wof:placetype":"venue"
},
  "geometry": {"coordinates":[-17.8970718384,27.8238143921],"type":"Point"}
}