{
  "type": "Feature",
  "properties": {
    "iso:country":"ES",
    "sg:address":"Iglesia, 12",
    "sg:city":"Torrejoncillo Rey",
    "sg:orig_category":"Iglesia Cat\u00d3lica",
    "sg:phone":"+34 969 27 80 43",
    "sg:postcode":"16161",
    "sg:province":"Cuenca",
    "wof:name":"Parroquia Nuestra Se\u00f1ora De La Asuncion",
    "wof:placetype":"venue"
},
  "geometry": {"coordinates":[-2.5736811161,40.0080032349],"type":"Point"}
}