{
  "type": "Feature",
  "properties": {
    "iso:country":"ES",
    "sg:address":"Onteniente, S/n",
    "sg:city":"Font Figuera",
    "sg:orig_category":"Serrer\u00cdas De Madera",
    "sg:phone":"+34 962 29 01 14",
    "sg:postcode":"46630",
    "sg:province":"Valencia",
    "wof:name":"Serreria Fuente La Higuera S.a.",
    "wof:placetype":"venue"
},
  "geometry": {"coordinates":[-0.8804090023,38.7997665405],"type":"Point"}
}