{
  "type": "Feature",
  "properties": {
    "addr:full":"Pol. Aigueta, 91 Bisbal Emporda Girona 17100",
    "addr:housenumber":"91",
    "addr:postcode":"17100",
    "addr:street":"Aigueta",
    "iso:country":"ES",
    "sg:address":"Pol. Aigueta, 91",
    "sg:city":"Bisbal Emporda",
    "sg:orig_category":"Compraventa De Antig\u00dcedades",
    "sg:phone":"+34 972 64 69 16",
    "sg:postcode":"17100",
    "sg:province":"Girona",
    "wof:name":"Gonzalez  Emiliano",
    "wof:placetype":"venue"
},
  "geometry": {"coordinates":[3.0360000134,41.9629936218],"type":"Point"}
}