{
  "type": "Feature",
  "properties": {
    "iso:country":"ES",
    "sg:address":"Canal Torres, 14",
    "sg:city":"S. Gines",
    "sg:orig_category":"Promotores Constructores",
    "sg:phone":"+34 968 88 56 61",
    "sg:postcode":"30169",
    "sg:province":"Murcia",
    "wof:name":"Construcciones La Vega De Aljucer S.l.",
    "wof:placetype":"venue"
},
  "geometry": {"coordinates":[-1.1722730398,37.9585342407],"type":"Point"}
}