{
  "type": "Feature",
  "properties": {
    "addr:full":"Calle de Telletxe, 8 Getxo Vizcaya 48990",
    "addr:housenumber":"8",
    "addr:postcode":"48990",
    "addr:street":"Calle De Telletxe",
    "iso:country":"ES",
    "sg:address":"Calle de Telletxe, 8",
    "sg:city":"Getxo",
    "sg:orig_category":"Inmobiliaria (agencias)",
    "sg:phone":"+34 944 03 41 57",
    "sg:postcode":"48990",
    "sg:province":"Vizcaya",
    "wof:name":"Fincas Arrigunaga, S.l.",
    "wof:placetype":"venue"
},
  "geometry": {"coordinates":[-3.010447979,43.3535118103],"type":"Point"}
}