{
  "type": "Feature",
  "properties": {
    "addr:full":"Av Alcodar(pol Alcodar), S/n Gandia Valencia 46700",
    "addr:postcode":"46700",
    "addr:street":"Av Alcodar;Alcodar S / N;Valencia",
    "iso:country":"ES",
    "sg:address":"Av Alcodar(pol Alcodar), S/n",
    "sg:city":"Gandia",
    "sg:orig_category":"Delegados, Agentes De Tr\u00c1nsito, Auxiliares De Transporte Internacional",
    "sg:phone":"+34 962 86 77 45",
    "sg:postcode":"46700",
    "sg:province":"Valencia",
    "wof:name":"Transportes Boix Vicedo S. L.",
    "wof:placetype":"venue"
},
  "geometry": {"coordinates":[-0.1824589968,38.9810600281],"type":"Point"}
}