{
  "type": "Feature",
  "properties": {
    "iso:country":"ES",
    "sg:address":"Calle de Boyer, S/n",
    "sg:city":"Madrid",
    "sg:orig_category":"Chapister\u00cda",
    "sg:phone":"+34 917 76 77 58",
    "sg:postcode":"28032",
    "sg:province":"Madrid",
    "wof:name":"Fernandez Alvarez Jose",
    "wof:placetype":"venue"
},
  "geometry": {"coordinates":[-3.5872886181,40.4045143127],"type":"Point"}
}