{
  "type": "Feature",
  "properties": {
    "addr:full":"Avda San Crispin, Km. 0010,2 Fuensalida Toledo 45510",
    "addr:postcode":"45510",
    "addr:street":"Avda San Crispin Km. 0010,2",
    "iso:country":"ES",
    "sg:address":"Avda San Crispin, Km. 0010,2",
    "sg:city":"Fuensalida",
    "sg:orig_category":"Distribuci\u00d3n De Petr\u00d3leo Y Derivados",
    "sg:phone":"+34 925 73 01 50",
    "sg:postcode":"45510",
    "sg:province":"Toledo",
    "wof:name":"Farruco S. A.",
    "wof:placetype":"venue"
},
  "geometry": {"coordinates":[-4.1983242035,40.0570297241],"type":"Point"}
}