{
  "type": "Feature",
  "properties": {
    "addr:full":"C/ Almansa, 28 Elche Alicante 03291",
    "addr:housenumber":"28",
    "addr:postcode":"03291",
    "addr:street":"C / Almansa",
    "iso:country":"ES",
    "sg:address":"C/ Almansa, 28",
    "sg:city":"Elche",
    "sg:orig_category":"Zapatos (al Por Mayor)",
    "sg:phone":"+34 965 43 08 70",
    "sg:postcode":"03291",
    "sg:province":"Alicante",
    "wof:name":"Giovani Foot Wear S.l.",
    "wof:placetype":"venue"
},
  "geometry": {"coordinates":[-0.7154669762,38.2811050415],"type":"Point"}
}