{
  "type": "Feature",
  "properties": {
    "iso:country":"ES",
    "sg:address":"Ctra Olivares-sanlucar, 25",
    "sg:city":"Olivares",
    "sg:orig_category":"Fabricaci\u00d3n, Instalaci\u00d3n Y Reparaci\u00d3n De Bombas",
    "sg:phone":"+34 954 11 03 43",
    "sg:postcode":"41804",
    "sg:province":"Sevilla",
    "wof:name":"Italica De Bombas S.l.",
    "wof:placetype":"venue"
},
  "geometry": {"coordinates":[-6.1690988541,37.4099349976],"type":"Point"}
}