{
  "type": "Feature",
  "properties": {
    "addr:full":"Calle de Elcano, 4 Bilbao Vizcaya 48009",
    "addr:housenumber":"4",
    "addr:postcode":"48009",
    "addr:street":"Calle De Elcano",
    "iso:country":"ES",
    "sg:address":"Calle de Elcano, 4",
    "sg:city":"Bilbao",
    "sg:orig_category":"M\u00c9dicos: Cirug\u00cda Maxilofacial",
    "sg:phone":"+34 944 23 64 68",
    "sg:postcode":"48009",
    "sg:province":"Vizcaya",
    "wof:name":"Barbier Herrero Luis",
    "wof:placetype":"venue"
},
  "geometry": {"coordinates":[-2.9367620945,43.2651634216],"type":"Point"}
}