{
  "type": "Feature",
  "properties": {
    "iso:country":"ES",
    "sg:address":"Carr Isabel La Catolica, 19",
    "sg:city":"Burjassot",
    "sg:orig_category":"Ropa Y Accesorios",
    "sg:phone":"+34 963 63 45 73",
    "sg:postcode":"46100",
    "sg:province":"Valencia",
    "wof:name":"Amachef S.l.",
    "wof:placetype":"venue"
},
  "geometry": {"coordinates":[-0.4126127064,39.5116882324],"type":"Point"}
}