{
  "type": "Feature",
  "properties": {
    "addr:full":"Av. Ejercito, 32 Iru\u00f1a Navarra 31002",
    "addr:housenumber":"32",
    "addr:postcode":"31002",
    "addr:street":"Av. Ejercito",
    "iso:country":"ES",
    "sg:address":"Av. Ejercito, 32",
    "sg:city":"Iru\u00f1a",
    "sg:orig_category":"M\u00c1quinas Y Material Para La Industria De La Alimentaci\u00d3n",
    "sg:phone":"+34 948 22 30 08",
    "sg:postcode":"31002",
    "sg:province":"Navarra",
    "wof:name":"Urbiola Saenz Joaquin",
    "wof:placetype":"venue"
},
  "geometry": {"coordinates":[-1.6502059698,42.8139381409],"type":"Point"}
}