{
  "type": "Feature",
  "properties": {
    "addr:full":"Aoiz-agoitz Kalea, 35 Iru\u00f1a Navarra 31003",
    "addr:housenumber":"35",
    "addr:postcode":"31003",
    "addr:street":"Aoiz-Agoitz Kalea",
    "iso:country":"ES",
    "sg:address":"Aoiz-agoitz Kalea, 35",
    "sg:city":"Iru\u00f1a",
    "sg:orig_category":"Arquitectos",
    "sg:phone":"+34 948 23 61 45",
    "sg:postcode":"31003",
    "sg:province":"Navarra",
    "wof:name":"Uhalte Sevilla Luis Hipolito",
    "wof:placetype":"venue"
},
  "geometry": {"coordinates":[-1.6437540054,42.81275177],"type":"Point"}
}