{
  "type": "Feature",
  "properties": {
    "iso:country":"ES",
    "sg:address":"Pol Ind Sete Pias, 75",
    "sg:city":"Cereixeira",
    "sg:orig_category":"Pescader\u00cdas (al Por Mayor)",
    "sg:phone":"+34 986 52 60 49",
    "sg:postcode":"36635",
    "sg:province":"Pontevedra",
    "wof:name":"Ruar Hispania S.l.",
    "wof:placetype":"venue"
},
  "geometry": {"coordinates":[-8.7641687393,42.3270759583],"type":"Point"}
}