{
  "type": "Feature",
  "properties": {
    "iso:country":"ES",
    "sg:address":"Estd Catabois, 477",
    "sg:city":"Ferrol",
    "sg:orig_category":"Negocio De Materiales De Construcci\u00d3n",
    "sg:phone":"+34 981 32 90 00",
    "sg:postcode":"15405",
    "sg:province":"La Coru\u00f1a",
    "wof:name":"E.riego 1 S.l.",
    "wof:placetype":"venue"
},
  "geometry": {"coordinates":[-8.2437515259,43.5037994385],"type":"Point"}
}