{
  "type": "Feature",
  "properties": {
    "addr:full":"Carrer de Sant Josep, 140 Sant Feliu Llobregat Barcelona 08980",
    "addr:housenumber":"140",
    "addr:postcode":"08980",
    "addr:street":"Carrer De Sant Josep",
    "iso:country":"ES",
    "sg:address":"Carrer de Sant Josep, 140",
    "sg:city":"Sant Feliu Llobregat",
    "sg:orig_category":"Almacenes Frigor\u00cdficos",
    "sg:phone":"+34 936 85 77 00",
    "sg:postcode":"08980",
    "sg:province":"Barcelona",
    "wof:name":"Reftrans S.a.",
    "wof:placetype":"venue"
},
  "geometry": {"coordinates":[2.0350680351,41.3908424377],"type":"Point"}
}