{
  "type": "Feature",
  "properties": {
    "addr:full":"Carrer de Blanca D'anjou, 6 Hospitalet De L'infant Tarragona 43890",
    "addr:housenumber":"6",
    "addr:postcode":"43890",
    "addr:street":"Carrer De Blanca D'Anjou",
    "iso:country":"ES",
    "sg:address":"Carrer de Blanca D'anjou, 6",
    "sg:city":"Hospitalet De L'infant",
    "sg:orig_category":"Empresas De Carpinter\u00cda Met\u00c1lica",
    "sg:phone":"+34 977 82 05 47",
    "sg:postcode":"43890",
    "sg:province":"Tarragona",
    "wof:name":"Francisco Vieira Joaquin",
    "wof:placetype":"venue"
},
  "geometry": {"coordinates":[1.2455840111,41.1117019653],"type":"Point"}
}