{
  "type": "Feature",
  "properties": {
    "iso:country":"ES",
    "sg:address":"Pase Zorrilla, 33",
    "sg:city":"Valladolid",
    "sg:orig_category":"Camiser\u00cda Y Ropa Interior Masculina (al Por Menor)",
    "sg:phone":"+34 983 23 74 58",
    "sg:postcode":"47007",
    "sg:province":"Valladolid",
    "wof:name":"Arribas Herranz Angel",
    "wof:placetype":"venue"
},
  "geometry": {"coordinates":[-4.7371149063,41.641620636],"type":"Point"}
}