{
  "type": "Feature",
  "properties": {
    "addr:full":"Playa Duque-sevilla, 1 Nueva Andalucia M\u00e1laga 29660",
    "addr:housenumber":"1",
    "addr:postcode":"29660",
    "addr:street":"Duque-Sevilla;Ma\u0301Laga",
    "iso:country":"ES",
    "sg:address":"Playa Duque-sevilla, 1",
    "sg:city":"Nueva Andalucia",
    "sg:orig_category":"Institutos De Belleza",
    "sg:phone":"+34 952 81 87 44",
    "sg:postcode":"29660",
    "sg:province":"M\u00e1laga",
    "wof:name":"Spejo's Difusion S.l.",
    "wof:placetype":"venue"
},
  "geometry": {"coordinates":[-4.9540901184,36.4891586304],"type":"Point"}
}