{
  "type": "Feature",
  "properties": {
    "iso:country":"ES",
    "sg:address":"Av Catalunya, 59",
    "sg:city":"Bellpuig",
    "sg:orig_category":"Muebles Y Accesorios Para Cocinas Y Cuartos De Ba\u00d1o (al Por Menor)",
    "sg:phone":"+34 973 32 02 03",
    "sg:postcode":"25250",
    "sg:province":"Lleida",
    "sg:website":"www.farransl.com",
    "wof:name":"Farran S.l.",
    "wof:placetype":"venue"
},
  "geometry": {"coordinates":[1.0118650198,41.6297073364],"type":"Point"}
}