{
  "type": "Feature",
  "properties": {
    "addr:full":"Calle de Jose Antonio, 53 Santa Maria Del Berrocal \u00c1vila 05510",
    "addr:housenumber":"53",
    "addr:postcode":"05510",
    "addr:street":"Calle De Jose Antonio",
    "iso:country":"ES",
    "sg:address":"Calle de Jose Antonio, 53",
    "sg:city":"Santa Maria Del Berrocal",
    "sg:orig_category":"Cerrajer\u00cda, Ferrallista",
    "sg:phone":"+34 920 36 70 25",
    "sg:postcode":"05510",
    "sg:province":"\u00c1vila",
    "wof:name":"Damian Vaquero C.b.",
    "wof:placetype":"venue"
},
  "geometry": {"coordinates":[-5.404499054,40.5095787048],"type":"Point"}
}