{
  "type": "Feature",
  "properties": {
    "addr:full":"Avda Mediterraneo, 22 Badia Del Valles Barcelona 08214",
    "addr:housenumber":"22",
    "addr:postcode":"08214",
    "addr:street":"Avda Mediterraneo",
    "iso:country":"ES",
    "sg:address":"Avda Mediterraneo, 22",
    "sg:city":"Badia Del Valles",
    "sg:orig_category":"M\u00c9dicos: Anestesiolog\u00cda Y Reanimaci\u00d3n Quir\u00dargica",
    "sg:phone":"+34 937 18 21 65",
    "sg:postcode":"08214",
    "sg:province":"Barcelona",
    "wof:name":"Castillo Ruiz Carlos Del",
    "wof:placetype":"venue"
},
  "geometry": {"coordinates":[2.1123919487,41.5063018799],"type":"Point"}
}