{
  "type": "Feature",
  "properties": {
    "addr:full":"Carrer de Franc Comtat, 315 Terrassa Barcelona 08224",
    "addr:housenumber":"315",
    "addr:postcode":"08224",
    "addr:street":"Carrer De Franc Comtat",
    "iso:country":"ES",
    "sg:address":"Carrer de Franc Comtat, 315",
    "sg:city":"Terrassa",
    "sg:orig_category":"Mec\u00c1nico Del Autom\u00d3vil",
    "sg:phone":"+34 937 80 75 28",
    "sg:postcode":"08224",
    "sg:province":"Barcelona",
    "wof:name":"Guiduz Fernandez Silvestre",
    "wof:placetype":"venue"
},
  "geometry": {"coordinates":[1.9945440292,41.5639724731],"type":"Point"}
}