{
  "type": "Feature",
  "properties": {
    "iso:country":"ES",
    "sg:address":"Carrer de Albert De Benet, 13",
    "sg:city":"Manlleu",
    "sg:orig_category":"Ropa Para Se\u00d1oras (al Por Menor)",
    "sg:phone":"+34 938 51 14 98",
    "sg:postcode":"08560",
    "sg:province":"Barcelona",
    "wof:name":"Llavero Hermoso Francisca",
    "wof:placetype":"venue"
},
  "geometry": {"coordinates":[2.2772789001,42.0021858215],"type":"Point"}
}