{
  "type": "Feature",
  "properties": {
    "addr:full":"Plgno Veinte, S/n Ntra. Sra. Jesus Islas Baleares 07819",
    "addr:housenumber":"s",
    "addr:postcode":"07819",
    "addr:street":"Veinte;/ N Ntra. Sra. Jesus Islas Baleares",
    "iso:country":"ES",
    "sg:address":"Plgno Veinte, S/n",
    "sg:city":"Ntra. Sra. Jesus",
    "sg:orig_category":"Marketing Telef\u00d3nico",
    "sg:phone":"+34 971 31 05 49",
    "sg:postcode":"07819",
    "sg:province":"Islas Baleares",
    "wof:name":"Canber Enterprises S.l.",
    "wof:placetype":"venue"
},
  "geometry": {"coordinates":[1.444257021,38.934135437],"type":"Point"}
}