{
  "type": "Feature",
  "properties": {
    "iso:country":"ES",
    "sg:address":"Calle de Marques De Villores, 74",
    "sg:city":"Albacete",
    "sg:orig_category":"Agentes Generales De Seguros",
    "sg:phone":"+34 967 24 01 44",
    "sg:postcode":"02003",
    "sg:province":"Albacete",
    "wof:name":"Segurplaza S.l.l.",
    "wof:placetype":"venue"
},
  "geometry": {"coordinates":[-1.8590990305,38.9883613586],"type":"Point"}
}