{
  "type": "Feature",
  "properties": {
    "iso:country":"ES",
    "sg:address":"Carrer de Robert Gerhard, 6",
    "sg:city":"Cambrils",
    "sg:orig_category":"Ropa Para Se\u00d1oras (al Por Menor)",
    "sg:phone":"+34 977 36 54 82",
    "sg:postcode":"43850",
    "sg:province":"Tarragona",
    "wof:name":"Chopo  Lydia",
    "wof:placetype":"venue"
},
  "geometry": {"coordinates":[1.0569729805,41.0664596558],"type":"Point"}
}