{
  "type": "Feature",
  "properties": {
    "addr:full":"Trva Pablo Picasso (de), 2 Mejorada Campo Madrid 28840",
    "addr:housenumber":"2",
    "addr:postcode":"28840",
    "addr:street":"Trva Pablo Picasso De",
    "iso:country":"ES",
    "sg:address":"Trva Pablo Picasso (de), 2",
    "sg:city":"Mejorada Campo",
    "sg:orig_category":"Centros Empresariales",
    "sg:phone":"+34 916 79 07 11",
    "sg:postcode":"28840",
    "sg:province":"Madrid",
    "wof:name":"Iba\u00d1ez Teijeira Juan Manuel",
    "wof:placetype":"venue"
},
  "geometry": {"coordinates":[-3.4880280495,40.3975067139],"type":"Point"}
}