{
  "type": "Feature",
  "properties": {
    "addr:full":"Calle de General Franco, 14 Cristianos Santa Cruz De Tenerife 38650",
    "addr:housenumber":"14",
    "addr:postcode":"38650",
    "addr:street":"Calle De General Franco",
    "iso:country":"ES",
    "sg:address":"Calle de General Franco, 14",
    "sg:city":"Cristianos",
    "sg:orig_category":"Inmobiliaria (agencias)",
    "sg:phone":"+34 922 78 84 40",
    "sg:postcode":"38650",
    "sg:province":"Santa Cruz De Tenerife",
    "wof:name":"Actual Properties S.l.",
    "wof:placetype":"venue"
},
  "geometry": {"coordinates":[-16.7161178589,28.0525722504],"type":"Point"}
}