{
  "type": "Feature",
  "properties": {
    "addr:full":"Calle de Alzola Pablo De, 2 Bilbao Vizcaya 48012",
    "addr:postcode":"48012",
    "addr:street":"Calle De;Pablo",
    "iso:country":"ES",
    "sg:address":"Calle de Alzola Pablo De, 2",
    "sg:city":"Bilbao",
    "sg:orig_category":"Herboristas (al Por Menor)",
    "sg:phone":"+34 944 27 06 93",
    "sg:postcode":"48012",
    "sg:province":"Vizcaya",
    "wof:name":"Gonzalez Cuco Maria Angeles",
    "wof:placetype":"venue"
},
  "geometry": {"coordinates":[-2.9468185902,43.2577362061],"type":"Point"}
}