{
  "type": "Feature",
  "properties": {
    "iso:country":"ES",
    "sg:address":"Calle de Goya, 3",
    "sg:city":"Carmona",
    "sg:orig_category":"Alquiler De V\u00cddeo",
    "sg:phone":"+34 954 14 45 31",
    "sg:postcode":"41410",
    "sg:province":"Sevilla",
    "wof:name":"Lopez Sola David",
    "wof:placetype":"venue"
},
  "geometry": {"coordinates":[-5.6460142136,37.4637145996],"type":"Point"}
}