{
  "type": "Feature",
  "properties": {
    "addr:full":"Calle de Ronda Mijares, 5 Castellon Castell\u00f3n 12001",
    "addr:housenumber":"5",
    "addr:postcode":"12001",
    "addr:street":"Calle De Ronda Mijares;Castello\u0301N",
    "iso:country":"ES",
    "sg:address":"Calle de Ronda Mijares, 5",
    "sg:city":"Castellon",
    "sg:orig_category":"Veh\u00cdculos De Ocasi\u00d3n",
    "sg:phone":"+34 964 21 85 78",
    "sg:postcode":"12001",
    "sg:province":"Castell\u00f3n",
    "wof:name":"Cabedo Gimeno Emiliano",
    "wof:placetype":"venue"
},
  "geometry": {"coordinates":[-0.0390900001,39.9866714478],"type":"Point"}
}