{
  "type": "Feature",
  "properties": {
    "addr:full":"Ctra Bilbao-plentzia, 17 Asua-lauroeta Vizcaya 48950",
    "addr:housenumber":"17",
    "addr:postcode":"48950",
    "addr:street":"Ctra Bilbao-Plentzia",
    "iso:country":"ES",
    "sg:address":"Ctra Bilbao-plentzia, 17",
    "sg:city":"Asua-lauroeta",
    "sg:orig_category":"Audiovisuales: Material Y Accesorios (al Por Menor)",
    "sg:phone":"+34 944 71 20 30",
    "sg:postcode":"48950",
    "sg:province":"Vizcaya",
    "sg:website":"www.faston.com",
    "wof:name":"Faston Audiovisuales Y Telecomunicaciones S. L.",
    "wof:placetype":"venue"
},
  "geometry": {"coordinates":[-2.949037075,43.3001403809],"type":"Point"}
}