{
  "type": "Feature",
  "properties": {
    "addr:full":"Calle de Mayor, S/n Antig\u00fcedad Palencia 34248",
    "addr:housenumber":"s",
    "addr:postcode":"34248",
    "addr:street":"Calle De Mayor;/ N",
    "iso:country":"ES",
    "sg:address":"Calle de Mayor, S/n",
    "sg:city":"Antig\u00fcedad",
    "sg:orig_category":"Negocio De Madera",
    "sg:phone":"+34 979 79 78 33",
    "sg:postcode":"34248",
    "sg:province":"Palencia",
    "wof:name":"Maderas Clavero S.l.",
    "wof:placetype":"venue"
},
  "geometry": {"coordinates":[-4.1182727814,41.9457626343],"type":"Point"}
}