{
  "type": "Feature",
  "properties": {
    "iso:country":"ES",
    "sg:address":"A Poboa, S/n",
    "sg:city":"Cacheiras",
    "sg:orig_category":"Frutas Y Legumbres Frescas (al Por Mayor)",
    "sg:phone":"+34 981 80 16 66",
    "sg:postcode":"15894",
    "sg:province":"La Coru\u00f1a",
    "wof:name":"Frutas Compostela S.l.",
    "wof:placetype":"venue"
},
  "geometry": {"coordinates":[-8.5459394455,42.8326034546],"type":"Point"}
}