{
  "type": "Feature",
  "properties": {
    "iso:country":"ES",
    "sg:address":"Calle de Jaen, 5",
    "sg:city":"Palacios Y Villafranca",
    "sg:orig_category":"Producci\u00d3n, Distribuci\u00d3n De Gas Butano Y Propano",
    "sg:phone":"+34 955 81 25 00",
    "sg:postcode":"41720",
    "sg:province":"Sevilla",
    "wof:name":"Resogas Sociedad Cooperativa Andaluza",
    "wof:placetype":"venue"
},
  "geometry": {"coordinates":[-5.9189767838,37.1577301025],"type":"Point"}
}