{
  "type": "Feature",
  "properties": {
    "iso:country":"ES",
    "sg:address":"Calle de Peris Mencheta, 2",
    "sg:city":"Sevilla",
    "sg:orig_category":"Iglesia Cat\u00d3lica",
    "sg:phone":"+34 954 38 06 97",
    "sg:postcode":"41002",
    "sg:province":"Sevilla",
    "wof:name":"Parroquia De Omnium Sanctorum",
    "wof:placetype":"venue"
},
  "geometry": {"coordinates":[-5.9921488762,37.3992805481],"type":"Point"}
}