{
  "type": "Feature",
  "properties": {
    "addr:full":"Calle de Iparbide, 2 Algorta Vizcaya 48991",
    "addr:housenumber":"2",
    "addr:postcode":"48991",
    "addr:street":"Calle De Iparbide",
    "iso:country":"ES",
    "sg:address":"Calle de Iparbide, 2",
    "sg:city":"Algorta",
    "sg:orig_category":"Molduras, Junquillos, Listones Y Molduras Perforadas",
    "sg:phone":"+34 944 30 47 05",
    "sg:postcode":"48991",
    "sg:province":"Vizcaya",
    "wof:name":"Velez Robles Benigno",
    "wof:placetype":"venue"
},
  "geometry": {"coordinates":[-3.0035700798,43.3506126404],"type":"Point"}
}