{
  "type": "Feature",
  "properties": {
    "addr:full":"Calle de Fotografia, 8 Madrid Madrid 28037",
    "addr:housenumber":"8",
    "addr:postcode":"madrid;28037",
    "addr:street":"Calle De Fotografia",
    "iso:country":"ES",
    "sg:address":"Calle de Fotografia, 8",
    "sg:city":"Madrid",
    "sg:classifiers":[
        {
            "category":"Autos & Motor Vehicles",
            "subcategory":"Automobile Sales",
            "type":"Retail Goods"
        }
    ],
    "sg:phone":"+34 913 13 24 10",
    "sg:postcode":"28037",
    "sg:province":"Madrid",
    "wof:name":"Autoescuela Punto S.l.",
    "wof:placetype":"venue"
},
  "geometry": {"coordinates":[-3.6227450371,40.4239654541],"type":"Point"}
}