{
  "type": "Feature",
  "properties": {
    "iso:country":"ES",
    "sg:address":"Calle de Alta, 9",
    "sg:city":"Herrera Pisuerga",
    "sg:orig_category":"Contenedores (mercanc\u00cdas)",
    "sg:phone":"+34 979 13 03 28",
    "sg:postcode":"34400",
    "sg:province":"Palencia",
    "wof:name":"Miguel Gutierrez Emilo De",
    "wof:placetype":"venue"
},
  "geometry": {"coordinates":[-4.3311400414,42.5969390869],"type":"Point"}
}