{
  "type": "Feature",
  "properties": {
    "addr:full":"Carrer de Bilbao, 145 Barcelona Barcelona 08018",
    "addr:housenumber":"145",
    "addr:postcode":"08018",
    "addr:street":"Carrer De Bilbao",
    "iso:country":"ES",
    "sg:address":"Carrer de Bilbao, 145",
    "sg:city":"Barcelona",
    "sg:orig_category":"Farmacias",
    "sg:phone":"+34 933 07 05 74",
    "sg:postcode":"08018",
    "sg:province":"Barcelona",
    "wof:name":"Munne Campos Marina",
    "wof:placetype":"venue"
},
  "geometry": {"coordinates":[2.1980919838,41.4067001343],"type":"Point"}
}