{
  "type": "Feature",
  "properties": {
    "addr:full":"Plaz Andalucia (de), 5 Cordoba C\u00f3rdoba 14013",
    "addr:housenumber":"5",
    "addr:postcode":"14013",
    "addr:street":"Plaz Andalucia De;Co\u0301Rdoba",
    "iso:country":"ES",
    "sg:address":"Plaz Andalucia (de), 5",
    "sg:city":"Cordoba",
    "sg:orig_category":"Asociaciones, Organismos Culturales Y Socioeducativos",
    "sg:phone":"+34 957 29 15 98",
    "sg:postcode":"14013",
    "sg:province":"C\u00f3rdoba",
    "wof:name":"Pe\u00f1a Flamenca Campo De La Verdad",
    "wof:placetype":"venue"
},
  "geometry": {"coordinates":[-4.7905387878,37.8593215942],"type":"Point"}
}