{
  "type": "Feature",
  "properties": {
    "iso:country":"ES",
    "sg:address":"Avda Palma De Mallorca, 45",
    "sg:city":"Torremolinos",
    "sg:orig_category":"Agencias De Viajes",
    "sg:phone":"+34 952 38 95 00",
    "sg:postcode":"29620",
    "sg:province":"M\u00e1laga",
    "sg:website":"www.viajeslibertad.com",
    "wof:name":"Viajes Libertad S.l.",
    "wof:placetype":"venue"
},
  "geometry": {"coordinates":[-4.4995560646,36.6189117432],"type":"Point"}
}