{
  "type": "Feature",
  "properties": {
    "iso:country":"ES",
    "sg:address":"Calle de Victor Andres Belaunde, 18",
    "sg:city":"Madrid",
    "sg:orig_category":"Supermercados Y Hipermercados",
    "sg:phone":"+34 914 58 79 79",
    "sg:postcode":"28016",
    "sg:province":"Madrid",
    "wof:name":"Emifra S.l.",
    "wof:placetype":"venue"
},
  "geometry": {"coordinates":[-3.6798861027,40.4570465088],"type":"Point"}
}