{
  "type": "Feature",
  "properties": {
    "addr:full":"Avda Andalucia, S/n Guarroman Ja\u00e9n 23210",
    "addr:postcode":"23210",
    "addr:street":"Avda Andalucia S / N;Jae\u0301N",
    "iso:country":"ES",
    "sg:address":"Avda Andalucia, S/n",
    "sg:city":"Guarroman",
    "sg:orig_category":"Cajas De Ahorro",
    "sg:phone":"+34 953 61 50 52",
    "sg:postcode":"23210",
    "sg:province":"Ja\u00e9n",
    "wof:name":"Unicaja",
    "wof:placetype":"venue"
},
  "geometry": {"coordinates":[-3.6853339672,38.1842765808],"type":"Point"}
}