{
  "type": "Feature",
  "properties": {
    "addr:full":"Carrer de Corsega, 81 Barcelona Barcelona 08029",
    "addr:housenumber":"81",
    "addr:postcode":"08029",
    "addr:street":"Carrer De Corsega",
    "iso:country":"ES",
    "sg:address":"Carrer de Corsega, 81",
    "sg:city":"Barcelona",
    "sg:orig_category":"Asesor\u00cda Fiscal Y Jur\u00cddica",
    "sg:phone":"+34 933 22 41 64",
    "sg:postcode":"08029",
    "sg:province":"Barcelona",
    "wof:name":"Alfonso Soria Assessors S.l.",
    "wof:placetype":"venue"
},
  "geometry": {"coordinates":[2.1448881626,41.3856964111],"type":"Point"}
}