{
  "type": "Feature",
  "properties": {
    "iso:country":"ES",
    "sg:address":"Calle de Luz Casanova, 13",
    "sg:city":"Valencia",
    "sg:orig_category":"Promotores Constructores",
    "sg:phone":"+34 963 65 17 73",
    "sg:postcode":"46009",
    "sg:province":"Valencia",
    "wof:name":"Promociones Grupo V.albertos S.l.",
    "wof:placetype":"venue"
},
  "geometry": {"coordinates":[-0.3734630048,39.4883308411],"type":"Point"}
}