{
  "type": "Feature",
  "properties": {
    "addr:full":"Cmno Guijarral, S/n Tobarra Albacete 02500",
    "addr:housenumber":"s",
    "addr:postcode":"02500",
    "addr:street":"Cmno Guijarral;/ N Tobarra",
    "iso:country":"ES",
    "sg:address":"Cmno Guijarral, S/n",
    "sg:city":"Tobarra",
    "sg:orig_category":"Frutas Y Legumbres Frescas (al Por Mayor)",
    "sg:phone":"+34 967 32 85 58",
    "sg:postcode":"02500",
    "sg:province":"Albacete",
    "wof:name":"Sociedad Cooperativa San Roque De Tobarra",
    "wof:placetype":"venue"
},
  "geometry": {"coordinates":[-1.6962089539,38.5950965881],"type":"Point"}
}