{
  "type": "Feature",
  "properties": {
    "addr:full":"Pg Joan Brudieu, 9 Seu D'urgell Lleida 25700",
    "addr:housenumber":"9",
    "addr:postcode":"25700",
    "addr:street":"Pg Joan Brudieu",
    "iso:country":"ES",
    "sg:address":"Pg Joan Brudieu, 9",
    "sg:city":"Seu D'urgell",
    "sg:orig_category":"Notarios",
    "sg:phone":"+34 973 35 52 02",
    "sg:postcode":"25700",
    "sg:province":"Lleida",
    "wof:name":"Galindo Llangort Francisco Javier",
    "wof:placetype":"venue"
},
  "geometry": {"coordinates":[0.6457189918,41.6027946472],"type":"Point"}
}