{
  "type": "Feature",
  "properties": {
    "addr:full":"Calle de Poeta Manuel Gongora, 3 Granada Granada 18008",
    "addr:housenumber":"3",
    "addr:postcode":"18008",
    "addr:street":"Calle De Poeta Manuel Gongora",
    "iso:country":"ES",
    "sg:address":"Calle de Poeta Manuel Gongora, 3",
    "sg:city":"Granada",
    "sg:classifiers":[
        {
            "category":"Personal",
            "subcategory":"Barber",
            "type":"Services"
        }
    ],
    "sg:phone":"+34 958 13 81 84",
    "sg:postcode":"18008",
    "sg:province":"Granada",
    "sg:tags":[
        "caballeros",
        "de",
        "peluqueros"
    ],
    "wof:name":"Villanueva Garrido Laura",
    "wof:placetype":"venue"
},
  "geometry": {"coordinates":[-3.5947070122,37.1663856506],"type":"Point"}
}