{
  "type": "Feature",
  "properties": {
    "iso:country":"ES",
    "sg:address":"C/ Jose Maria Peman, 9",
    "sg:city":"Elche",
    "sg:orig_category":"Peluquer\u00cdas, Peluquer\u00cda Mixta",
    "sg:phone":"+34 965 43 48 90",
    "sg:postcode":"03201",
    "sg:province":"Alicante",
    "wof:name":"Comunity Hayr S.l.",
    "wof:placetype":"venue"
},
  "geometry": {"coordinates":[-0.7036849856,38.2649459839],"type":"Point"}
}