{
  "type": "Feature",
  "properties": {
    "addr:full":"Carrer de Hoquei, 161 Terrassa Barcelona 08226",
    "addr:housenumber":"161",
    "addr:postcode":"08226",
    "addr:street":"Carrer De Hoquei",
    "iso:country":"ES",
    "sg:address":"Carrer de Hoquei, 161",
    "sg:city":"Terrassa",
    "sg:orig_category":"Cultos Diversos",
    "sg:phone":"+34 937 85 39 87",
    "sg:postcode":"08226",
    "sg:province":"Barcelona",
    "wof:name":"Centro Bahai De Tarrasa",
    "wof:placetype":"venue"
},
  "geometry": {"coordinates":[2.0304150581,41.5727424622],"type":"Point"}
}