{
  "type": "Feature",
  "properties": {
    "addr:full":"Via Massague, 4 Sabadell Barcelona 08202",
    "addr:housenumber":"4",
    "addr:postcode":"08202",
    "addr:street":"Via Massague",
    "iso:country":"ES",
    "sg:address":"Via Massague, 4",
    "sg:city":"Sabadell",
    "sg:orig_category":"Lencer\u00cda Femenina, Corseter\u00cda, Trajes De Ba\u00d1o (al Por Menor)",
    "sg:phone":"+34 937 25 17 36",
    "sg:postcode":"08202",
    "sg:province":"Barcelona",
    "wof:name":"Dot Prat Josefa",
    "wof:placetype":"venue"
},
  "geometry": {"coordinates":[2.1081659794,41.5493812561],"type":"Point"}
}