{
  "type": "Feature",
  "properties": {
    "iso:country":"ES",
    "sg:address":"Calle de Muro, 8",
    "sg:city":"Valladolid",
    "sg:orig_category":"Propiedad Industrial: Patentes De Inventos, Marcas, Modelos, Dise\u00d1os",
    "sg:phone":"+34 983 30 60 16",
    "sg:postcode":"47004",
    "sg:province":"Valladolid",
    "sg:website":"www.areaseisgestion.es",
    "wof:name":"Area Seis Gestion S.l.",
    "wof:placetype":"venue"
},
  "geometry": {"coordinates":[-4.7252192497,41.6468009949],"type":"Point"}
}