{
  "type": "Feature",
  "properties": {
    "iso:country":"ES",
    "sg:address":"Carrer de Nou, 2",
    "sg:city":"S. Pol Mar",
    "sg:orig_category":"Quincaller\u00cda (al Por Menor)",
    "sg:phone":"+34 937 60 20 54",
    "sg:postcode":"08395",
    "sg:province":"Barcelona",
    "wof:name":"Buch Carbonell Antonio",
    "wof:placetype":"venue"
},
  "geometry": {"coordinates":[2.6150829792,41.6016960144],"type":"Point"}
}