{
  "type": "Feature",
  "properties": {
    "iso:country":"ES",
    "sg:address":"Carr Mar, 54",
    "sg:city":"Alboraya",
    "sg:classifiers":[
        {
            "category":"Manufacturing",
            "subcategory":"Metals",
            "type":"Manufacturing & Wholesale Goods"
        }
    ],
    "sg:phone":"+34 961 85 59 60",
    "sg:postcode":"46120",
    "sg:province":"Valencia",
    "sg:tags":[
        "en",
        "fundiciones"
    ],
    "wof:name":"Aluminio Fundido S.l.",
    "wof:placetype":"venue"
},
  "geometry": {"coordinates":[-0.3405978084,39.4990844727],"type":"Point"}
}