{
  "type": "Feature",
  "properties": {
    "iso:country":"ES",
    "sg:address":"Polig. Lalin Dos Mil, S/n",
    "sg:city":"Donsion",
    "sg:orig_category":"Reciclaje Y Tratamiento De Desechos Varios",
    "sg:phone":"+34 986 78 75 17",
    "sg:postcode":"36519",
    "sg:province":"Pontevedra",
    "sg:website":"www.reromas.com",
    "wof:name":"Recuperacion De Rodas E Madeira S.l.",
    "wof:placetype":"venue"
},
  "geometry": {"coordinates":[-8.1627492905,42.5798492432],"type":"Point"}
}