{
  "type": "Feature",
  "properties": {
    "addr:full":"Calle de Fernando El Catolico, S/n Pina De Ebro Zaragoza 50750",
    "addr:housenumber":"s / n",
    "addr:postcode":"50750",
    "addr:street":"Calle De Fernando El Catolico",
    "iso:country":"ES",
    "sg:address":"Calle de Fernando El Catolico, S/n",
    "sg:city":"Pina De Ebro",
    "sg:orig_category":"Panader\u00cdas, Panader\u00cdas",
    "sg:phone":"+34 976 16 58 07",
    "sg:postcode":"50750",
    "sg:province":"Zaragoza",
    "sg:website":"www.arruabarrena.com",
    "wof:name":"El Peque\u00f1o Molino S.a.",
    "wof:placetype":"venue"
},
  "geometry": {"coordinates":[-0.5295689702,41.4865608215],"type":"Point"}
}