{
  "type": "Feature",
  "properties": {
    "iso:country":"ES",
    "sg:address":"Crta. Higuera, Km. 0008,0",
    "sg:city":"Jerez Caballeros",
    "sg:orig_category":"Agricultores, Agricultores",
    "sg:phone":"+34 924 12 10 08",
    "sg:postcode":"06380",
    "sg:province":"Badajoz",
    "wof:name":"Montero Sanchez Andres",
    "wof:placetype":"venue"
},
  "geometry": {"coordinates":[-6.7729787827,38.3225212097],"type":"Point"}
}