{
  "type": "Feature",
  "properties": {
    "addr:full":"Pedro I, 5 Iru\u00f1a Navarra 31007",
    "addr:housenumber":"5",
    "addr:postcode":"31007",
    "addr:street":"Pedro I",
    "iso:country":"ES",
    "sg:address":"Pedro I, 5",
    "sg:city":"Iru\u00f1a",
    "sg:orig_category":"Oficinas De Estudios De Dise\u00d1o Industrial",
    "sg:phone":"+34 948 17 01 06",
    "sg:postcode":"31007",
    "sg:province":"Navarra",
    "wof:name":"Parra Torres Juan Carlos",
    "wof:placetype":"venue"
},
  "geometry": {"coordinates":[-1.6566669941,42.8047561646],"type":"Point"}
}