{
  "type": "Feature",
  "properties": {
    "iso:country":"ES",
    "sg:address":"Avda Menendez Pelayo, 7",
    "sg:city":"Madrid",
    "sg:orig_category":"M\u00c9dicos: Oftalmolog\u00cda",
    "sg:phone":"+34 915 76 96 89",
    "sg:postcode":"28009",
    "sg:province":"Madrid",
    "sg:website":"www.clinica-ver.com",
    "wof:name":"Centro Oftalmologico Aver S.l.",
    "wof:placetype":"venue"
},
  "geometry": {"coordinates":[-3.6795608997,40.4210128784],"type":"Point"}
}