{
  "type": "Feature",
  "properties": {
    "iso:country":"ES",
    "sg:address":"Carrer de Francesc Bellapart, 28",
    "sg:city":"Sabadell",
    "sg:orig_category":"Empresas De Carpinter\u00cda",
    "sg:phone":"+34 937 23 12 45",
    "sg:postcode":"08208",
    "sg:province":"Barcelona",
    "sg:website":"www.dalumbec.com",
    "wof:name":"Alumni Dalumbec S.l:",
    "wof:placetype":"venue"
},
  "geometry": {"coordinates":[2.0987827778,41.5582809448],"type":"Point"}
}