{
  "type": "Feature",
  "properties": {
    "iso:country":"ES",
    "sg:address":"Calle de Zumalacarregui, 4",
    "sg:city":"S. Vicente Sonsierra",
    "sg:orig_category":"Panader\u00cdas, Panader\u00cdas",
    "sg:phone":"+34 941 33 41 38",
    "sg:postcode":"26338",
    "sg:province":"La Rioja",
    "wof:name":"Hermanos Alutiz Peci\u00f1a Cdad",
    "wof:placetype":"venue"
},
  "geometry": {"coordinates":[-2.7585420609,42.5614776611],"type":"Point"}
}