{
  "type": "Feature",
  "properties": {
    "addr:full":"Plaz Santiago, S/n Ledesma Salamanca 37100",
    "addr:housenumber":"s / n",
    "addr:postcode":"37100",
    "addr:street":"Plaz Santiago",
    "iso:country":"ES",
    "sg:address":"Plaz Santiago, S/n",
    "sg:city":"Ledesma",
    "sg:orig_category":"Asilos De Ancianos. Centros Privados",
    "sg:phone":"+34 923 57 02 10",
    "sg:postcode":"37100",
    "sg:province":"Salamanca",
    "wof:name":"Empresa Publica De Ledesma S.l.",
    "wof:placetype":"venue"
},
  "geometry": {"coordinates":[-5.9980640411,41.0898704529],"type":"Point"}
}