{
  "type": "Feature",
  "properties": {
    "iso:country":"ES",
    "sg:address":"Carrer de Doctor Fleming, 19",
    "sg:city":"Barcelona",
    "sg:orig_category":"Caf\u00c9s, Bares, Cervecer\u00cdas",
    "sg:phone":"+34 932 01 51 61",
    "sg:postcode":"08017",
    "sg:province":"Barcelona",
    "wof:name":"Compa\u00f1ia De Explotacion De Franquicia",
    "wof:placetype":"venue"
},
  "geometry": {"coordinates":[2.1348669529,41.3939857483],"type":"Point"}
}