{
  "type": "Feature",
  "properties": {
    "iso:country":"ES",
    "sg:address":"Av Vila De Madrid, 17",
    "sg:city":"Blanes",
    "sg:orig_category":"Art\u00cdculos De Regalo (al Por Menor)",
    "sg:phone":"+34 972 35 74 56",
    "sg:postcode":"17300",
    "sg:province":"Girona",
    "wof:name":"Karroum  Ilham",
    "wof:placetype":"venue"
},
  "geometry": {"coordinates":[2.7799460888,41.6600074768],"type":"Point"}
}