{
  "type": "Feature",
  "properties": {
    "iso:country":"ES",
    "sg:address":"Av Matadepera, 52",
    "sg:city":"Sabadell",
    "sg:orig_category":"Ropa Para Se\u00d1oras (al Por Menor)",
    "sg:phone":"+34 937 17 13 04",
    "sg:postcode":"08207",
    "sg:province":"Barcelona",
    "wof:name":"Nicolas Belmonte Jesus",
    "wof:placetype":"venue"
},
  "geometry": {"coordinates":[2.0898849964,41.5655212402],"type":"Point"}
}