{
  "type": "Feature",
  "properties": {
    "addr:full":"Plaz Jose Maria Planelles, 24 Altea Alicante 03590",
    "addr:housenumber":"24",
    "addr:postcode":"03590",
    "addr:street":"Planelles",
    "iso:country":"ES",
    "sg:address":"Plaz Jose Maria Planelles, 24",
    "sg:city":"Altea",
    "sg:orig_category":"Bisuter\u00cda, Joyer\u00cda, Relojer\u00cda (al Por Menor)",
    "sg:phone":"+34 965 84 32 88",
    "sg:postcode":"03590",
    "sg:province":"Alicante",
    "wof:name":"Joyeria Arres S.l.",
    "wof:placetype":"venue"
},
  "geometry": {"coordinates":[-0.0279866997,38.6424942017],"type":"Point"}
}