{
  "type": "Feature",
  "properties": {
    "addr:full":"Finca Las Minas, S/n Villafranca Barros Badajoz 06220",
    "addr:housenumber":"s / n",
    "addr:postcode":"06220",
    "addr:street":"Minas",
    "iso:country":"ES",
    "sg:address":"Finca Las Minas, S/n",
    "sg:city":"Villafranca Barros",
    "sg:orig_category":"Ense\u00d1anza, Formaci\u00d3n Profesional: Aprendizaje",
    "sg:phone":"+34 924 12 40 51",
    "sg:postcode":"06220",
    "sg:province":"Badajoz",
    "wof:name":"Amus",
    "wof:placetype":"venue"
},
  "geometry": {"coordinates":[-6.9702835083,38.8785972595],"type":"Point"}
}