{
  "type": "Feature",
  "properties": {
    "iso:country":"ES",
    "sg:address":"Pol. Ind. De Guitiriz, S/n",
    "sg:city":"Mamoas",
    "sg:orig_category":"Venta, Montaje De Neum\u00c1ticos",
    "sg:phone":"+34 982 37 04 01",
    "sg:postcode":"27309",
    "sg:province":"Lugo",
    "wof:name":"Vazquez Santamari\u00f1a Marcos",
    "wof:placetype":"venue"
},
  "geometry": {"coordinates":[-7.5693798065,43.0095100403],"type":"Point"}
}