{
  "type": "Feature",
  "properties": {
    "addr:full":"Urb Nueva Sierra De Altomira, S/n Nueva Sierra De Altomira Guadalajara 19117",
    "addr:housenumber":"/ n",
    "addr:postcode":"19117",
    "addr:street":"Urb;Sierra;Altomira S;Sierra",
    "iso:country":"ES",
    "sg:address":"Urb Nueva Sierra De Altomira, S/n",
    "sg:city":"Nueva Sierra De Altomira",
    "sg:orig_category":"Asesor\u00cdas Y Estudios Financieros",
    "sg:phone":"+34 949 37 78 20",
    "sg:postcode":"19117",
    "sg:province":"Guadalajara",
    "sg:website":"www.rapalouwanadoo.es",
    "wof:name":"Rapalou Telecomunicaciones S.l.l.",
    "wof:placetype":"venue"
},
  "geometry": {"coordinates":[-2.8439540863,40.3080101013],"type":"Point"}
}