{
  "type": "Feature",
  "properties": {
    "addr:full":"Calle de Lopez De Ayala, 20 Linea De La Concepcion C\u00e1diz 11300",
    "addr:housenumber":"20",
    "addr:postcode":"11300",
    "addr:street":"Calle De Lopez De Ayala;Ca\u0301Diz",
    "iso:country":"ES",
    "sg:address":"Calle de Lopez De Ayala, 20",
    "sg:city":"Linea De La Concepcion",
    "sg:orig_category":"Asociaciones, Organismos Culturales Y Socioeducativos",
    "sg:phone":"+34 956 17 10 27",
    "sg:postcode":"11300",
    "sg:province":"C\u00e1diz",
    "wof:name":"Asociacion De Minusvalidos Fisicos Arco Iris",
    "wof:placetype":"venue"
},
  "geometry": {"coordinates":[-5.3522744179,36.1632995605],"type":"Point"}
}