{
  "type": "Feature",
  "properties": {
    "addr:full":"La Folia, 7 Sta.ursula Santa Cruz De Tenerife 38390",
    "addr:housenumber":"7",
    "addr:postcode":"38390",
    "addr:street":"Sta.Ursula",
    "iso:country":"ES",
    "sg:address":"La Folia, 7",
    "sg:city":"Sta.ursula",
    "sg:orig_category":"Art\u00cdculos De Regalo (al Por Menor)",
    "sg:phone":"+34 922 30 23 39",
    "sg:postcode":"38390",
    "sg:province":"Santa Cruz De Tenerife",
    "wof:name":"Serigrafia Santa Ursula S.l.",
    "wof:placetype":"venue"
},
  "geometry": {"coordinates":[-16.4993648529,28.42228508],"type":"Point"}
}