{
  "type": "Feature",
  "properties": {
    "iso:country":"ES",
    "sg:address":"Carrer de Pau Casals, 140",
    "sg:city":"Prat Llobregat",
    "sg:orig_category":"Centros De Educaci\u00d3n Especial",
    "sg:phone":"+34 933 79 61 30",
    "sg:postcode":"08820",
    "sg:province":"Barcelona",
    "wof:name":"Co%egi Public Sant Jaume",
    "wof:placetype":"venue"
},
  "geometry": {"coordinates":[2.0864720345,41.3289909363],"type":"Point"}
}