{
  "type": "Feature",
  "properties": {
    "iso:country":"ES",
    "sg:address":"Calle de Cervantes, 2",
    "sg:city":"Sotillo Adrada",
    "sg:orig_category":"Panader\u00cdas, Panader\u00cdas",
    "sg:phone":"+34 918 66 82 91",
    "sg:postcode":"05420",
    "sg:province":"\u00c1vila",
    "wof:name":"Gonzalez Linares Maria Jesus",
    "wof:placetype":"venue"
},
  "geometry": {"coordinates":[-4.6323900223,40.3024368286],"type":"Point"}
}