{
  "type": "Feature",
  "properties": {
    "addr:full":"Calle de Ramon Y Cajal, 28 Villanueva Serena Badajoz 06700",
    "addr:housenumber":"28",
    "addr:postcode":"06700",
    "addr:street":"Calle De Ramon Y Cajal",
    "iso:country":"ES",
    "sg:address":"Calle de Ramon Y Cajal, 28",
    "sg:city":"Villanueva Serena",
    "sg:orig_category":"\u00d3ptica: Instrumentos (fabricaci\u00d3n)",
    "sg:phone":"+34 924 84 15 86",
    "sg:postcode":"06700",
    "sg:province":"Badajoz",
    "wof:name":"Morcillo Garcia Pedro Antonio",
    "wof:placetype":"venue"
},
  "geometry": {"coordinates":[-5.7927408218,38.9731750488],"type":"Point"}
}