{
  "type": "Feature",
  "properties": {
    "iso:country":"ES",
    "sg:address":"Calle de Goleta, 31",
    "sg:city":"Barbate",
    "sg:orig_category":"Peluqueros: De Se\u00d1oras",
    "sg:phone":"+34 956 43 07 76",
    "sg:postcode":"11160",
    "sg:province":"C\u00e1diz",
    "wof:name":"Cabeza Gomez Antonia",
    "wof:placetype":"venue"
},
  "geometry": {"coordinates":[-5.9235019684,36.1940956116],"type":"Point"}
}