{
  "type": "Feature",
  "properties": {
    "iso:country":"ES",
    "sg:address":"Avda Parsi, 4",
    "sg:city":"Sevilla",
    "sg:orig_category":"Hilaturas, Hilos Y Actividades Relacionadas",
    "sg:phone":"+34 955 63 03 47",
    "sg:postcode":"41016",
    "sg:province":"Sevilla",
    "wof:name":"Import Export Sevimex S.l.",
    "wof:placetype":"venue"
},
  "geometry": {"coordinates":[-5.9191088676,37.3811836243],"type":"Point"}
}