{
  "type": "Feature",
  "properties": {
    "iso:country":"ES",
    "sg:address":"Ctra. Jerez-los Barrios, Km. 0003,0",
    "sg:city":"Jerez",
    "sg:orig_category":"Fabricaci\u00d3n, Importaci\u00d3n, Venta De Material De Telefon\u00cda, Peritelefon\u00cda",
    "sg:phone":"+34 956 15 65 45",
    "sg:postcode":"11406",
    "sg:province":"C\u00e1diz",
    "wof:name":"Airadsl Wi-fi S.l.",
    "wof:placetype":"venue"
},
  "geometry": {"coordinates":[-5.7428607941,36.4441223145],"type":"Point"}
}