{
  "type": "Feature",
  "properties": {
    "iso:country":"ES",
    "sg:address":"Pl. Sta. Gadea, 5",
    "sg:city":"Ayamonte",
    "sg:orig_category":"Ense\u00d1anza Variada",
    "sg:phone":"+34 959 32 00 20",
    "sg:postcode":"21400",
    "sg:province":"Huelva",
    "wof:name":"Academia Delta Jandia S.l.",
    "wof:placetype":"venue"
},
  "geometry": {"coordinates":[-7.403771,37.209415],"type":"Point"}
}