{
  "type": "Feature",
  "properties": {
    "addr:full":"Carrer de Vergos, 64 Sabadell Barcelona 08203",
    "addr:housenumber":"64",
    "addr:postcode":"08203",
    "addr:street":"Carrer De Vergos",
    "iso:country":"ES",
    "sg:address":"Carrer de Vergos, 64",
    "sg:city":"Sabadell",
    "sg:orig_category":"Materias Pl\u00c1sticas: Art\u00cdculos Para La Industria",
    "sg:phone":"+34 937 11 60 04",
    "sg:postcode":"08203",
    "sg:province":"Barcelona",
    "wof:name":"Siplast S.c.p.",
    "wof:placetype":"venue"
},
  "geometry": {"coordinates":[2.1089839935,41.5307502747],"type":"Point"}
}