{
  "type": "Feature",
  "properties": {
    "addr:full":"Calle de Zinc, 3 Humanes De Madrid Madrid 28970",
    "addr:housenumber":"3",
    "addr:postcode":"28970",
    "addr:street":"Calle De Zinc",
    "iso:country":"ES",
    "sg:address":"Calle de Zinc, 3",
    "sg:city":"Humanes De Madrid",
    "sg:orig_category":"Ingenier\u00cda, Centros De Estudios (diversos)",
    "sg:phone":"+34 916 15 23 99",
    "sg:postcode":"28970",
    "sg:province":"Madrid",
    "wof:name":"Cones S.a.",
    "wof:placetype":"venue"
},
  "geometry": {"coordinates":[-3.8270421028,40.2687149048],"type":"Point"}
}