{
  "type": "Feature",
  "properties": {
    "addr:full":"Calle de Seis De Junio, 184 Valdepe\u00f1as Ciudad Real 13300",
    "addr:housenumber":"184",
    "addr:postcode":"13300",
    "addr:street":"Calle De Seis De Junio",
    "iso:country":"ES",
    "sg:address":"Calle de Seis De Junio, 184",
    "sg:city":"Valdepe\u00f1as",
    "sg:orig_category":"Deportes Diversos",
    "sg:phone":"+34 926 31 26 80",
    "sg:postcode":"13300",
    "sg:province":"Ciudad Real",
    "sg:website":"www.okinawas.net",
    "wof:name":"Antequera Rosillo Vicente",
    "wof:placetype":"venue"
},
  "geometry": {"coordinates":[-3.38971138,38.7534332275],"type":"Point"}
}