{
  "type": "Feature",
  "properties": {
    "iso:country":"ES",
    "sg:address":"Calle de Florida, 10",
    "sg:city":"Motril",
    "sg:orig_category":"Decoraci\u00d3n: Instalaci\u00d3n Y Talleres",
    "sg:phone":"+34 958 60 21 82",
    "sg:postcode":"18600",
    "sg:province":"Granada",
    "wof:name":"Rincon Correa Manuel",
    "wof:placetype":"venue"
},
  "geometry": {"coordinates":[-3.5193998814,36.7565841675],"type":"Point"}
}