{
  "type": "Feature",
  "properties": {
    "iso:country":"ES",
    "sg:address":"Calle de Zabala, 17",
    "sg:city":"Linares",
    "sg:orig_category":"Asesor\u00cda De Formaci\u00d3n Y Gesti\u00d3n De Personal",
    "sg:phone":"+34 953 60 22 67",
    "sg:postcode":"23700",
    "sg:province":"Ja\u00e9n",
    "wof:name":"De Haro Pozas Mario",
    "wof:placetype":"venue"
},
  "geometry": {"coordinates":[-3.6330289841,38.0942001343],"type":"Point"}
}