{
  "type": "Feature",
  "properties": {
    "iso:country":"ES",
    "sg:address":"Avda Solares, 4",
    "sg:city":"Saron",
    "sg:orig_category":"Abogados",
    "sg:phone":"+34 942 56 44 03",
    "sg:postcode":"39620",
    "sg:province":"Cantabria",
    "wof:name":"Onandia Perez Ines",
    "wof:placetype":"venue"
},
  "geometry": {"coordinates":[-3.8514719009,43.3249816895],"type":"Point"}
}