{
  "type": "Feature",
  "properties": {
    "iso:country":"ES",
    "sg:address":"Rua Plateria, 29",
    "sg:city":"Grove",
    "sg:orig_category":"Restaurantes",
    "sg:phone":"+34 986 73 10 59",
    "sg:postcode":"36980",
    "sg:province":"Pontevedra",
    "wof:name":"Martinez Chaves Jose",
    "wof:placetype":"venue"
},
  "geometry": {"coordinates":[-8.8633785248,42.4949417114],"type":"Point"}
}