{
  "type": "Feature",
  "properties": {
    "addr:full":"Calle de Amapola, 13 Rincon Victoria M\u00e1laga 29730",
    "addr:housenumber":"13",
    "addr:postcode":"29730",
    "addr:street":"Calle De Amapola;Ma\u0301Laga",
    "iso:country":"ES",
    "sg:address":"Calle de Amapola, 13",
    "sg:city":"Rincon Victoria",
    "sg:orig_category":"Ingeniero",
    "sg:phone":"+34 952 40 45 68",
    "sg:postcode":"29730",
    "sg:province":"M\u00e1laga",
    "wof:name":"Rodriguez Heredia Jesus",
    "wof:placetype":"venue"
},
  "geometry": {"coordinates":[-4.2724056244,36.7184333801],"type":"Point"}
}