{
  "type": "Feature",
  "properties": {
    "addr:full":"Rua Conde Torrecedeira, 50 Vigo Pontevedra 36202",
    "addr:housenumber":"50",
    "addr:postcode":"36202",
    "addr:street":"Rua Conde Torrecedeira",
    "iso:country":"ES",
    "sg:address":"Rua Conde Torrecedeira, 50",
    "sg:city":"Vigo",
    "sg:orig_category":"Alquiler De V\u00cddeo",
    "sg:phone":"+34 986 29 32 41",
    "sg:postcode":"36202",
    "sg:province":"Pontevedra",
    "wof:name":"Servicer S. L.",
    "wof:placetype":"venue"
},
  "geometry": {"coordinates":[-8.7323951721,42.2312469482],"type":"Point"}
}