{
  "type": "Feature",
  "properties": {
    "addr:full":"Calle de Prado Tuerto, 2 Zamora Zamora 49019",
    "addr:housenumber":"2",
    "addr:postcode":"49019",
    "addr:street":"Calle De Prado Tuerto",
    "iso:country":"ES",
    "sg:address":"Calle de Prado Tuerto, 2",
    "sg:city":"Zamora",
    "sg:orig_category":"Asesor\u00cda Fiscal Y Jur\u00cddica",
    "sg:phone":"+34 980 51 82 94",
    "sg:postcode":"49019",
    "sg:province":"Zamora",
    "wof:name":"Toledo Lorenzo Juan Mariano",
    "wof:placetype":"venue"
},
  "geometry": {"coordinates":[-5.7356681824,41.5076789856],"type":"Point"}
}