{
  "type": "Feature",
  "properties": {
    "iso:country":"ES",
    "sg:address":"Avda Parmenides, S/n",
    "sg:city":"Malaga",
    "sg:orig_category":"Cajas De Ahorro",
    "sg:phone":"+34 952 62 99 06",
    "sg:postcode":"29010",
    "sg:province":"M\u00e1laga",
    "wof:name":"Unicaja",
    "wof:placetype":"venue"
},
  "geometry": {"coordinates":[-4.4797291756,36.7239494324],"type":"Point"}
}