{
  "type": "Feature",
  "properties": {
    "iso:country":"ES",
    "sg:address":"Calle de Virgen Del Camino, 6",
    "sg:city":"Le\u00f3n",
    "sg:orig_category":"Molduras, Junquillos, Listones Y Molduras Perforadas",
    "sg:phone":"+34 987 23 40 60",
    "sg:postcode":"24007",
    "sg:province":"Le\u00f3n",
    "wof:name":"Alvarez Mayo Jeronimo",
    "wof:placetype":"venue"
},
  "geometry": {"coordinates":[-5.5659723282,42.6069335938],"type":"Point"}
}