{
  "type": "Feature",
  "properties": {
    "addr:full":"Pla\u00c7 Major, 18 Verdu Lleida 25340",
    "addr:housenumber":"18",
    "addr:postcode":"25340",
    "addr:street":"Verdu Lleida",
    "iso:country":"ES",
    "sg:address":"Pla\u00c7 Major, 18",
    "sg:city":"Verdu",
    "sg:orig_category":"Molduras, Junquillos, Listones Y Molduras Perforadas",
    "sg:phone":"+34 973 34 70 93",
    "sg:postcode":"25340",
    "sg:province":"Lleida",
    "wof:name":"Tudo Freixes Isidre",
    "wof:placetype":"venue"
},
  "geometry": {"coordinates":[1.1441040039,41.6102371216],"type":"Point"}
}