{
  "type": "Feature",
  "properties": {
    "iso:country":"ES",
    "sg:address":"Avda Puente De Carlos Iii, 4",
    "sg:city":"Reinosa",
    "sg:orig_category":"Ropa Para Ni\u00d1os (al Por Menor)",
    "sg:phone":"+34 942 75 45 89",
    "sg:postcode":"39200",
    "sg:province":"Cantabria",
    "wof:name":"Kokoliso S.cv.",
    "wof:placetype":"venue"
},
  "geometry": {"coordinates":[-4.1380839348,42.9991950989],"type":"Point"}
}