{
  "type": "Feature",
  "properties": {
    "addr:full":"Calle de Cardenal Monescillo, 19 Valdepe\u00f1as Ciudad Real 13300",
    "addr:housenumber":"19",
    "addr:postcode":"13300",
    "addr:street":"Calle De Cardenal Monescillo",
    "iso:country":"ES",
    "sg:address":"Calle de Cardenal Monescillo, 19",
    "sg:city":"Valdepe\u00f1as",
    "sg:orig_category":"Empresas De Pintura Y Revestimientos",
    "sg:phone":"+34 926 32 07 00",
    "sg:postcode":"13300",
    "sg:province":"Ciudad Real",
    "wof:name":"Garcia Camacho Manuel",
    "wof:placetype":"venue"
},
  "geometry": {"coordinates":[-3.3831810951,38.7548675537],"type":"Point"}
}