{
  "type": "Feature",
  "properties": {
    "addr:full":"Calle de Juan De La Cueva, 49 San Jose Rinconada Sevilla 41300",
    "addr:housenumber":"49",
    "addr:postcode":"41300",
    "addr:street":"Calle De Juan De La Cueva",
    "iso:country":"ES",
    "sg:address":"Calle de Juan De La Cueva, 49",
    "sg:city":"San Jose Rinconada",
    "sg:orig_category":"Cajas De Ahorro",
    "sg:phone":"+34 954 79 19 06",
    "sg:postcode":"41300",
    "sg:province":"Sevilla",
    "sg:website":"www.elmonte.es",
    "wof:name":"Monte De Piedad Y Caja De Ahorros De Huelva Y Sevilla",
    "wof:placetype":"venue"
},
  "geometry": {"coordinates":[-5.9456038475,37.4844779968],"type":"Point"}
}