{
  "type": "Feature",
  "properties": {
    "iso:country":"ES",
    "sg:address":"Carrer de Consell De Cent, 321",
    "sg:city":"Barcelona",
    "sg:orig_category":"Psic\u00d3logos",
    "sg:phone":"+34 934 87 15 57",
    "sg:postcode":"08007",
    "sg:province":"Barcelona",
    "wof:name":"Izuel Curria Miguel",
    "wof:placetype":"venue"
},
  "geometry": {"coordinates":[2.1634829044,41.3896179199],"type":"Point"}
}