{
  "type": "Feature",
  "properties": {
    "addr:full":"Calle de Alonso De Palencia, 1 Malaga M\u00e1laga 29007",
    "addr:housenumber":"1",
    "addr:postcode":"29007",
    "addr:street":"Calle De Alonso De Palencia;Ma\u0301Laga",
    "iso:country":"ES",
    "sg:address":"Calle de Alonso De Palencia, 1",
    "sg:city":"Malaga",
    "sg:classifiers":[
        {
            "category":"Personal",
            "subcategory":"Barber",
            "type":"Services"
        }
    ],
    "sg:phone":"+34 952 61 59 61",
    "sg:postcode":"29007",
    "sg:province":"M\u00e1laga",
    "sg:tags":[
        "caballeros",
        "de",
        "peluqueros"
    ],
    "wof:name":"Castillo Garcia Urbano",
    "wof:placetype":"venue"
},
  "geometry": {"coordinates":[-4.4327821732,36.7200469971],"type":"Point"}
}