{
  "type": "Feature",
  "properties": {
    "iso:country":"ES",
    "sg:address":"Carrer de Tarragona, 36",
    "sg:city":"Gava",
    "sg:orig_category":"Electricidad: Equipos Industriales, Componentes (fabricaci\u00d3n)",
    "sg:phone":"+34 936 62 02 94",
    "sg:postcode":"08850",
    "sg:province":"Barcelona",
    "wof:name":"Compa\u00f1ia Espa\u00f1ola De Electronica S. L.",
    "wof:placetype":"venue"
},
  "geometry": {"coordinates":[2.0125100613,41.2997894287],"type":"Point"}
}