{
  "type": "Feature",
  "properties": {
    "iso:country":"ES",
    "sg:address":"Calle de Sierra (la), S/n",
    "sg:city":"Cox",
    "sg:orig_category":"Frutas Y Legumbres Frescas (al Por Mayor)",
    "sg:phone":"+34 966 75 02 19",
    "sg:postcode":"03350",
    "sg:province":"Alicante",
    "wof:name":"Carmelete Hermanos S.l.",
    "wof:placetype":"venue"
},
  "geometry": {"coordinates":[-0.8923640251,38.137714386],"type":"Point"}
}