{
  "type": "Feature",
  "properties": {
    "iso:country":"ES",
    "sg:address":"Luga Veri\u00d1a De Abajo, S/n",
    "sg:city":"Veri\u00e7a De Abajo",
    "sg:classifiers":[
        {
            "category":"Manufacturing",
            "subcategory":"Metals",
            "type":"Manufacturing & Wholesale Goods"
        }
    ],
    "sg:phone":"+34 985 32 58 58",
    "sg:postcode":"33691",
    "sg:province":"Asturias",
    "sg:tags":[
        "en",
        "fundiciones"
    ],
    "wof:name":"Fundiciones Veri\u00f1a S. A.",
    "wof:placetype":"venue"
},
  "geometry": {"coordinates":[-5.7485799789,43.5202865601],"type":"Point"}
}