{
  "type": "Feature",
  "properties": {
    "addr:full":"Calle de Portal De Castilla, 2 Vitoria-gasteiz \u00c1lava 01008",
    "addr:housenumber":"2",
    "addr:postcode":"01008",
    "addr:street":"Calle De Portal De Castilla",
    "iso:country":"ES",
    "sg:address":"Calle de Portal De Castilla, 2",
    "sg:city":"Vitoria-gasteiz",
    "sg:orig_category":"Refiner\u00cdas De Petr\u00d3leo",
    "sg:phone":"+34 945 13 01 20",
    "sg:postcode":"01008",
    "sg:province":"\u00c1lava",
    "wof:name":"Repsol Ypf S.a.",
    "wof:placetype":"venue"
},
  "geometry": {"coordinates":[-2.6785991192,42.844039917],"type":"Point"}
}