{
  "type": "Feature",
  "properties": {
    "addr:full":"Calle de Encarnacion Lopez, 41 Fuensanta Martos Ja\u00e9n 23610",
    "addr:housenumber":"41",
    "addr:postcode":"23610",
    "addr:street":"Calle De Encarnacion Lopez",
    "iso:country":"ES",
    "sg:address":"Calle de Encarnacion Lopez, 41",
    "sg:city":"Fuensanta Martos",
    "sg:orig_category":"Negocio De Materiales De Construcci\u00d3n",
    "sg:phone":"+34 953 56 55 91",
    "sg:postcode":"23610",
    "sg:province":"Ja\u00e9n",
    "wof:name":"Francisco Rosa Ortega Y Ana Luque Priego Cdad",
    "wof:placetype":"venue"
},
  "geometry": {"coordinates":[-3.9144721031,37.6460762024],"type":"Point"}
}