{
  "type": "Feature",
  "properties": {
    "iso:country":"ES",
    "sg:address":"Carrer de Virrei Aviles (del), 23",
    "sg:city":"Vic",
    "sg:orig_category":"Ropa Para Se\u00d1oras Y Caballeros (al Por Menor)",
    "sg:phone":"+34 938 85 02 78",
    "sg:postcode":"08500",
    "sg:province":"Barcelona",
    "wof:name":"Tuneu Casas Joaquin",
    "wof:placetype":"venue"
},
  "geometry": {"coordinates":[2.2512528896,41.9210662842],"type":"Point"}
}