{
  "type": "Feature",
  "properties": {
    "iso:country":"ES",
    "sg:address":"Calle de Juan De Zamora, 7",
    "sg:city":"Ayamonte",
    "sg:orig_category":"Cristaler\u00cdas",
    "sg:phone":"+34 959 32 16 77",
    "sg:postcode":"21400",
    "sg:province":"Huelva",
    "wof:name":"Landero Gonzalez Manuel Jesus",
    "wof:placetype":"venue"
},
  "geometry": {"coordinates":[-7.4068851471,37.2132644653],"type":"Point"}
}