{
  "type": "Feature",
  "properties": {
    "addr:full":"Cjos. Nuevos, S/n Cortijos Nuevos Ja\u00e9n 23293",
    "addr:housenumber":"s / n",
    "addr:postcode":"23293",
    "iso:country":"ES",
    "sg:address":"Cjos. Nuevos, S/n",
    "sg:city":"Cortijos Nuevos",
    "sg:orig_category":"Oficinas De Turismo, Asociaciones De Iniciativa",
    "sg:phone":"+34 953 49 61 47",
    "sg:postcode":"23293",
    "sg:province":"Ja\u00e9n",
    "wof:name":"Ayuntamiento De Segura De La Sierra",
    "wof:placetype":"venue"
},
  "geometry": {"coordinates":[-2.7254040241,38.2469863892],"type":"Point"}
}