{
  "type": "Feature",
  "properties": {
    "iso:country":"ES",
    "sg:address":"Rond Sant Antoni Maria Claret, 22",
    "sg:city":"Girona",
    "sg:orig_category":"Arquitectos",
    "sg:phone":"+34 972 20 39 45",
    "sg:postcode":"17001",
    "sg:province":"Girona",
    "wof:name":"Felip Campistol Adrian",
    "wof:placetype":"venue"
},
  "geometry": {"coordinates":[2.8209450245,41.9795074463],"type":"Point"}
}