{
  "type": "Feature",
  "properties": {
    "iso:country":"ES",
    "sg:address":"Calle de Luis Badia, 95",
    "sg:city":"Albacete",
    "sg:orig_category":"Alimentaci\u00d3n General (al Por Menor)",
    "sg:phone":"+34 967 22 67 18",
    "sg:postcode":"02004",
    "sg:province":"Albacete",
    "wof:name":"Rosa Sanchez Samuel",
    "wof:placetype":"venue"
},
  "geometry": {"coordinates":[-1.8671959639,38.9898948669],"type":"Point"}
}