{
  "type": "Feature",
  "properties": {
    "iso:country":"ES",
    "sg:address":"Goizueta Kalea, 5",
    "sg:city":"Donostia-san Sebastian",
    "sg:orig_category":"Chapister\u00cda",
    "sg:phone":"+34 943 44 42 86",
    "sg:postcode":"20014",
    "sg:province":"Guip\u00f9zcoa",
    "wof:name":"Mendiburu Arrieta Josune",
    "wof:placetype":"venue"
},
  "geometry": {"coordinates":[-1.9539619684,43.2939682007],"type":"Point"}
}