{
  "type": "Feature",
  "properties": {
    "addr:full":"Carrer de Proven\u00c7a, 74 Barcelona Barcelona 08029",
    "addr:housenumber":"74",
    "addr:postcode":"08029",
    "addr:street":"Carrer De Provenc\u0327A",
    "iso:country":"ES",
    "sg:address":"Carrer de Proven\u00c7a, 74",
    "sg:city":"Barcelona",
    "sg:orig_category":"Molduras, Junquillos, Listones Y Molduras Perforadas",
    "sg:phone":"+34 934 30 90 59",
    "sg:postcode":"08029",
    "sg:province":"Barcelona",
    "wof:name":"Estruch Farreny Maria",
    "wof:placetype":"venue"
},
  "geometry": {"coordinates":[2.1474280357,41.3839607239],"type":"Point"}
}