{
  "type": "Feature",
  "properties": {
    "addr:full":"Calle de Corredera, 27 Arahal Sevilla 41600",
    "addr:housenumber":"27",
    "addr:postcode":"41600",
    "addr:street":"Calle De Corredera",
    "iso:country":"ES",
    "sg:address":"Calle de Corredera, 27",
    "sg:city":"Arahal",
    "sg:orig_category":"Art\u00cdculos De Decoraci\u00d3n",
    "sg:phone":"+34 955 84 24 59",
    "sg:postcode":"41600",
    "sg:province":"Sevilla",
    "wof:name":"Carmen Arcas Y Nati Vaquero S.l.",
    "wof:placetype":"venue"
},
  "geometry": {"coordinates":[-5.5463657379,37.2611427307],"type":"Point"}
}