{
  "type": "Feature",
  "properties": {
    "iso:country":"ES",
    "sg:address":"Calle de Maestro Serrano, 15",
    "sg:city":"Almeria",
    "sg:orig_category":"M\u00c9dicos: Oftalmolog\u00cda",
    "sg:phone":"+34 950 23 73 45",
    "sg:postcode":"04004",
    "sg:province":"Almer\u00eda",
    "wof:name":"Tecnoctal S.l.",
    "wof:placetype":"venue"
},
  "geometry": {"coordinates":[-2.4614489079,36.8334999084],"type":"Point"}
}