{
  "type": "Feature",
  "properties": {
    "addr:full":"Calle de Amnistia, 12 Madrid Madrid 28013",
    "addr:housenumber":"12",
    "addr:postcode":"madrid;28013",
    "addr:street":"Calle De Amnistia",
    "iso:country":"ES",
    "sg:address":"Calle de Amnistia, 12",
    "sg:city":"Madrid",
    "sg:orig_category":"Inform\u00c1tica: Consultores",
    "sg:phone":"+34 915 59 09 70",
    "sg:postcode":"28013",
    "sg:province":"Madrid",
    "wof:name":"Desarrollos Y Recursos S.l.",
    "wof:placetype":"venue"
},
  "geometry": {"coordinates":[-3.7113711834,40.4171104431],"type":"Point"}
}