{
  "type": "Feature",
  "properties": {
    "iso:country":"ES",
    "sg:address":"Rua Cami\u00d1o Novo, 7",
    "sg:city":"Carballo",
    "sg:orig_category":"M\u00c9dicos: Otorrinolaringolog\u00cda",
    "sg:phone":"+34 981 70 09 16",
    "sg:postcode":"15100",
    "sg:province":"La Coru\u00f1a",
    "wof:name":"Herranz Gonzalez-botas Juan Jesus Manuel",
    "wof:placetype":"venue"
},
  "geometry": {"coordinates":[-8.6909017563,43.2130508423],"type":"Point"}
}