{
  "type": "Feature",
  "properties": {
    "addr:full":"Urb Reserva Higueron, S/n Benalmadena M\u00e1laga 29639",
    "addr:housenumber":"s / n",
    "addr:postcode":"29639",
    "iso:country":"ES",
    "sg:address":"Urb Reserva Higueron, S/n",
    "sg:city":"Benalmadena",
    "sg:orig_category":"Cine: Pel\u00cdculas Educativas, Industriales Y Publicitarias (producci\u00d3n)",
    "sg:phone":"+34 952 56 57 34",
    "sg:postcode":"29639",
    "sg:province":"M\u00e1laga",
    "wof:name":"Tf7- Tv Sl",
    "wof:placetype":"venue"
},
  "geometry": {"coordinates":[-4.5960540771,36.581829071],"type":"Point"}
}