{
  "type": "Feature",
  "properties": {
    "addr:full":"Calle de Imagen, 4 Sevilla Sevilla 41003",
    "addr:housenumber":"4",
    "addr:postcode":"41003",
    "addr:street":"Calle De Imagen",
    "iso:country":"ES",
    "sg:address":"Calle de Imagen, 4",
    "sg:city":"Sevilla",
    "sg:orig_category":"Asesor\u00cda Fiscal Y Jur\u00cddica",
    "sg:phone":"+34 954 21 13 44",
    "sg:postcode":"41003",
    "sg:province":"Sevilla",
    "wof:name":"Drake Canela Emilio",
    "wof:placetype":"venue"
},
  "geometry": {"coordinates":[-5.9900012016,37.3926086426],"type":"Point"}
}