{
  "type": "Feature",
  "properties": {
    "iso:country":"ES",
    "sg:address":"Treinta De Julio, 41",
    "sg:city":"Cantillana",
    "sg:orig_category":"Molduras, Junquillos, Listones Y Molduras Perforadas",
    "sg:phone":"+34 955 73 14 79",
    "sg:postcode":"41320",
    "sg:province":"Sevilla",
    "wof:name":"Salas Sanchez Pedro",
    "wof:placetype":"venue"
},
  "geometry": {"coordinates":[-5.8242950439,37.6098175049],"type":"Point"}
}