{
  "type": "Feature",
  "properties": {
    "iso:country":"ES",
    "sg:address":"Rua Luis Antonio Mestre, 1",
    "sg:city":"Grove",
    "sg:orig_category":"Clases De M\u00dasica Y Canto",
    "sg:phone":"+34 986 73 10 05",
    "sg:postcode":"36980",
    "sg:province":"Pontevedra",
    "wof:name":"Miguez Vazquez Jose Amador",
    "wof:placetype":"venue"
},
  "geometry": {"coordinates":[-8.8659334183,42.4873542786],"type":"Point"}
}