{
  "type": "Feature",
  "properties": {
    "iso:country":"ES",
    "sg:address":"Calle de Xirivella, 13",
    "sg:city":"Mislata",
    "sg:orig_category":"M\u00c9dicos: An\u00c1lisis Cl\u00cdnicos",
    "sg:phone":"+34 963 59 38 78",
    "sg:postcode":"46920",
    "sg:province":"Valencia",
    "wof:name":"Rubio Mataix Maria Angeles",
    "wof:placetype":"venue"
},
  "geometry": {"coordinates":[-0.4198180139,39.4729537964],"type":"Point"}
}