{
  "type": "Feature",
  "properties": {
    "addr:full":"Carrer de Sant Nicasi, 81 Gava Barcelona 08850",
    "addr:housenumber":"81",
    "addr:postcode":"08850",
    "addr:street":"Carrer De Sant Nicasi",
    "iso:country":"ES",
    "sg:address":"Carrer de Sant Nicasi, 81",
    "sg:city":"Gava",
    "sg:orig_category":"Centros Empresariales",
    "sg:phone":"+34 936 62 52 02",
    "sg:postcode":"08850",
    "sg:province":"Barcelona",
    "wof:name":"Unio De Botiguers De Gava",
    "wof:placetype":"venue"
},
  "geometry": {"coordinates":[2.0017390251,41.3080558777],"type":"Point"}
}