{
  "type": "Feature",
  "properties": {
    "iso:country":"ES",
    "sg:address":"Calle de Arroyo, 107",
    "sg:city":"Sevilla",
    "sg:orig_category":"Centros De Educaci\u00d3n Especial",
    "sg:phone":"+34 954 41 60 52",
    "sg:postcode":"41008",
    "sg:province":"Sevilla",
    "wof:name":"Junta De Andalucia-consejeria De Educacion Y Ciencia",
    "wof:placetype":"venue"
},
  "geometry": {"coordinates":[-5.9753623009,37.3979187012],"type":"Point"}
}