{
  "type": "Feature",
  "properties": {
    "addr:full":"Rua Igrexa, 36 Ferrol La Coru\u00f1a 15402",
    "addr:housenumber":"36",
    "addr:postcode":"15402",
    "addr:street":"Rua Igrexa;La Corun\u0303A",
    "iso:country":"ES",
    "sg:address":"Rua Igrexa, 36",
    "sg:city":"Ferrol",
    "sg:orig_category":"Ense\u00d1anza: Idiomas",
    "sg:phone":"+34 981 35 42 23",
    "sg:postcode":"15402",
    "sg:province":"La Coru\u00f1a",
    "wof:name":"Blundell  Andrew Scott",
    "wof:placetype":"venue"
},
  "geometry": {"coordinates":[-8.2273387909,43.4868507385],"type":"Point"}
}