{
  "type": "Feature",
  "properties": {
    "addr:full":"Av Fabraquer, 36 Playa Muchavista Alicante 03560",
    "addr:housenumber":"36",
    "addr:postcode":"03560",
    "addr:street":"Av Fabraquer;Muchavista",
    "iso:country":"ES",
    "sg:address":"Av Fabraquer, 36",
    "sg:city":"Playa Muchavista",
    "sg:orig_category":"Asesor\u00cdas Y Estudios Financieros",
    "sg:phone":"+34 965 65 76 68",
    "sg:postcode":"03560",
    "sg:province":"Alicante",
    "wof:name":"Ugarteburu Aranguren Alberto",
    "wof:placetype":"venue"
},
  "geometry": {"coordinates":[-0.4127990007,38.4001235962],"type":"Point"}
}