{
  "type": "Feature",
  "properties": {
    "iso:country":"ES",
    "sg:address":"Carr Pi Margall, 20",
    "sg:city":"Palafrugell",
    "sg:orig_category":"Inform\u00c1tica (estudios, Servicios, Asesor\u00cda, Formaci\u00d3n)",
    "sg:phone":"+34 972 30 66 92",
    "sg:postcode":"17200",
    "sg:province":"Girona",
    "wof:name":"St Serveis S.c.p.",
    "wof:placetype":"venue"
},
  "geometry": {"coordinates":[3.1648190022,41.9176521301],"type":"Point"}
}