{
  "type": "Feature",
  "properties": {
    "iso:country":"ES",
    "sg:address":"Calle de Triana, 34",
    "sg:city":"Palmas De Gran Canaria",
    "sg:orig_category":"Zapatos (al Por Menor)",
    "sg:phone":"+34 928 43 31 99",
    "sg:postcode":"35002",
    "sg:province":"Las Palmas",
    "wof:name":"Calnava S.l.",
    "wof:placetype":"venue"
},
  "geometry": {"coordinates":[-15.415271759,28.1041679382],"type":"Point"}
}