{
  "type": "Feature",
  "properties": {
    "addr:full":"Calle de Juan Tornero, 64 Madrid Madrid 28011",
    "addr:housenumber":"64",
    "addr:postcode":"madrid;28011",
    "addr:street":"Calle De Juan Tornero",
    "iso:country":"ES",
    "sg:address":"Calle de Juan Tornero, 64",
    "sg:city":"Madrid",
    "sg:orig_category":"Poller\u00cda Y Caza (al Por Menor)",
    "sg:phone":"+34 914 64 59 71",
    "sg:postcode":"28011",
    "sg:province":"Madrid",
    "wof:name":"Castellanos Martin Pedro",
    "wof:placetype":"venue"
},
  "geometry": {"coordinates":[-3.729681015,40.4112510681],"type":"Point"}
}