{
  "type": "Feature",
  "properties": {
    "iso:country":"ES",
    "sg:address":"Calle de Ramon Y Cajal, 66",
    "sg:city":"Valencia Alcantara",
    "sg:orig_category":"Reposter\u00cdas",
    "sg:phone":"+34 927 58 01 39",
    "sg:postcode":"10500",
    "sg:province":"C\u00e1ceres",
    "wof:name":"Valenpan S.l.",
    "wof:placetype":"venue"
},
  "geometry": {"coordinates":[-7.2455291748,39.4109611511],"type":"Point"}
}