{
  "type": "Feature",
  "properties": {
    "iso:country":"ES",
    "sg:address":"Calle de Nueva, 59",
    "sg:city":"Villel",
    "sg:orig_category":"Empresarios",
    "sg:phone":"+34 978 68 20 24",
    "sg:postcode":"44131",
    "sg:province":"Teruel",
    "wof:name":"Obras Y Contratas Contursi S.l.",
    "wof:placetype":"venue"
},
  "geometry": {"coordinates":[-1.1891729832,40.2348442078],"type":"Point"}
}