{
  "type": "Feature",
  "properties": {
    "addr:full":"Calle de Juan Sebastian Bach, 2 Malaga M\u00e1laga 29004",
    "addr:housenumber":"2",
    "addr:postcode":"29004",
    "addr:street":"Calle De Juan Sebastian Bach;Ma\u0301Laga",
    "iso:country":"ES",
    "sg:address":"Calle de Juan Sebastian Bach, 2",
    "sg:city":"Malaga",
    "sg:orig_category":"Art\u00cdculos De Regalo (al Por Menor)",
    "sg:phone":"+34 952 17 20 83",
    "sg:postcode":"29004",
    "sg:province":"M\u00e1laga",
    "wof:name":"Galiano Bustamante Maria Rosa",
    "wof:placetype":"venue"
},
  "geometry": {"coordinates":[-4.4506549835,36.6953239441],"type":"Point"}
}