{
  "type": "Feature",
  "properties": {
    "iso:country":"ES",
    "sg:address":"Calle de Olmos, S/n",
    "sg:city":"Villahermosa Rio",
    "sg:orig_category":"Iglesia Cat\u00d3lica",
    "sg:phone":"+34 964 38 25 81",
    "sg:postcode":"12124",
    "sg:province":"Castell\u00f3n",
    "wof:name":"Parroquia Natividad De Nuestra Se\u00f1ora",
    "wof:placetype":"venue"
},
  "geometry": {"coordinates":[-0.4180929959,40.202922821],"type":"Point"}
}