{
  "type": "Feature",
  "properties": {
    "addr:full":"Avda Andalucia, 29 Albolote Granada 18220",
    "addr:housenumber":"29",
    "addr:postcode":"18220",
    "addr:street":"Avda Andalucia",
    "iso:country":"ES",
    "sg:address":"Avda Andalucia, 29",
    "sg:city":"Albolote",
    "sg:classifiers":[
        {
            "category":"Cinema",
            "subcategory":"Movie Theater",
            "type":"Entertainment"
        }
    ],
    "sg:phone":"+34 958 46 69 06",
    "sg:postcode":"18220",
    "sg:province":"Granada",
    "sg:tags":[
        "salas",
        "de",
        "cine"
    ],
    "wof:name":"Aguit Romera Maria Teresa",
    "wof:placetype":"venue"
},
  "geometry": {"coordinates":[-3.6491935253,37.2292098999],"type":"Point"}
}