{
  "type": "Feature",
  "properties": {
    "addr:full":"Avgd Nord, 15 Picassent Valencia 46220",
    "addr:housenumber":"15",
    "addr:postcode":"46220",
    "iso:country":"ES",
    "sg:address":"Avgd Nord, 15",
    "sg:city":"Picassent",
    "sg:orig_category":"Carnicer\u00cdas, Carnicer\u00cdas",
    "sg:phone":"+34 961 23 31 50",
    "sg:postcode":"46220",
    "sg:province":"Valencia",
    "wof:name":"Guerola Pastor Vicente",
    "wof:placetype":"venue"
},
  "geometry": {"coordinates":[-0.4595290124,39.3631401062],"type":"Point"}
}