{
  "type": "Feature",
  "properties": {
    "iso:country":"ES",
    "sg:address":"Calle de Tiburcio Vargas, 1",
    "sg:city":"Jodar",
    "sg:orig_category":"Molduras, Junquillos, Listones Y Molduras Perforadas",
    "sg:phone":"+34 953 78 70 36",
    "sg:postcode":"23500",
    "sg:province":"Ja\u00e9n",
    "wof:name":"Eurotel Sur S.l.",
    "wof:placetype":"venue"
},
  "geometry": {"coordinates":[-3.3512189388,37.8403892517],"type":"Point"}
}