{
  "type": "Feature",
  "properties": {
    "addr:full":"Plaz Constitucion, 1 Zaidin Huesca 22530",
    "addr:housenumber":"1",
    "addr:postcode":"22530",
    "addr:street":"Constitucion",
    "iso:country":"ES",
    "sg:address":"Plaz Constitucion, 1",
    "sg:city":"Zaidin",
    "sg:orig_category":"Abogados",
    "sg:phone":"+34 974 47 85 35",
    "sg:postcode":"22530",
    "sg:province":"Huesca",
    "wof:name":"Ayuntamiento De Zaidin",
    "wof:placetype":"venue"
},
  "geometry": {"coordinates":[0.2633970082,41.6041984558],"type":"Point"}
}