{
  "type": "Feature",
  "properties": {
    "addr:full":"Calle de Merced, 5 San Lorenzo Murcia 30001",
    "addr:housenumber":"5",
    "addr:postcode":"30001",
    "addr:street":"Calle De Merced",
    "iso:country":"ES",
    "sg:address":"Calle de Merced, 5",
    "sg:city":"San Lorenzo",
    "sg:orig_category":"Abogados",
    "sg:phone":"+34 968 20 18 20",
    "sg:postcode":"30001",
    "sg:province":"Murcia",
    "wof:name":"Cutillas Hortelano Pedro Jose",
    "wof:placetype":"venue"
},
  "geometry": {"coordinates":[-1.1281189919,37.9873008728],"type":"Point"}
}