{
  "type": "Feature",
  "properties": {
    "iso:country":"ES",
    "sg:address":"Calle de Fuentezuelas (las), 5",
    "sg:city":"Sevilla",
    "sg:orig_category":"Promotores Constructores",
    "sg:phone":"+34 954 93 43 10",
    "sg:postcode":"41020",
    "sg:province":"Sevilla",
    "wof:name":"Daluzan S.l.",
    "wof:placetype":"venue"
},
  "geometry": {"coordinates":[-5.9209160805,37.3889465332],"type":"Point"}
}