{
  "type": "Feature",
  "properties": {
    "addr:full":"Avda Condomina, S/n Alacant Alicante 03540",
    "addr:housenumber":"s / n",
    "addr:postcode":"03540",
    "addr:street":"Avda Condomina",
    "iso:country":"ES",
    "sg:address":"Avda Condomina, S/n",
    "sg:city":"Alacant",
    "sg:orig_category":"Promotores Constructores",
    "sg:phone":"+34 965 96 15 43",
    "sg:postcode":"03540",
    "sg:province":"Alicante",
    "wof:name":"Urbanizadora E Inmobiliaria Cartagenera S.a.",
    "wof:placetype":"venue"
},
  "geometry": {"coordinates":[-0.4292539954,38.3636283875],"type":"Point"}
}