{
  "type": "Feature",
  "properties": {
    "iso:country":"ES",
    "sg:address":"Calle de Rio Deba, 23",
    "sg:city":"Donostia-san Sebastian",
    "sg:orig_category":"Asociaciones, Organismos Culturales Y Socioeducativos",
    "sg:phone":"+34 943 28 38 34",
    "sg:postcode":"20012",
    "sg:province":"Guip\u00f9zcoa",
    "wof:name":"Asociacion Ornitologica De San Sebastian",
    "wof:placetype":"venue"
},
  "geometry": {"coordinates":[-1.9704443216,43.3159675598],"type":"Point"}
}