{
  "type": "Feature",
  "properties": {
    "iso:country":"ES",
    "sg:address":"Avda Cesar Augusto, 4",
    "sg:city":"Zaragoza",
    "sg:orig_category":"Centros Empresariales",
    "sg:phone":"+34 976 21 26 00",
    "sg:postcode":"50004",
    "sg:province":"Zaragoza",
    "wof:name":"Eurotec Consultores S.l.",
    "wof:placetype":"venue"
},
  "geometry": {"coordinates":[-0.8869799972,41.6500892639],"type":"Point"}
}