{
  "type": "Feature",
  "properties": {
    "iso:country":"ES",
    "sg:address":"Av Diputacio, 176",
    "sg:city":"Cambrils",
    "sg:orig_category":"Empresarios Y Productoras De Espect\u00c1culos",
    "sg:phone":"+34 977 38 55 05",
    "sg:postcode":"43850",
    "sg:province":"Tarragona",
    "wof:name":"Produccions I Don't Remember S.l.",
    "wof:placetype":"venue"
},
  "geometry": {"coordinates":[1.1099920273,41.0729141235],"type":"Point"}
}