{
  "type": "Feature",
  "properties": {
    "iso:country":"ES",
    "sg:address":"Plaz Bodega, 7",
    "sg:city":"Molinos",
    "sg:orig_category":"Congelados: Productos Alimentarios (fabricaci\u00d3n, Al Por Mayor)",
    "sg:phone":"+34 918 55 01 88",
    "sg:postcode":"28460",
    "sg:province":"Madrid",
    "wof:name":"Gracia Gonzalez Laura",
    "wof:placetype":"venue"
},
  "geometry": {"coordinates":[-4.0751171112,40.7110862732],"type":"Point"}
}