{
  "type": "Feature",
  "properties": {
    "addr:full":"Calle de Juan De Badajoz, 1 Le\u00f3n Le\u00f3n 24002",
    "addr:housenumber":"1",
    "addr:postcode":"24002",
    "addr:street":"Calle De Juan De Badajoz;Leo\u0301N",
    "iso:country":"ES",
    "sg:address":"Calle de Juan De Badajoz, 1",
    "sg:city":"Le\u00f3n",
    "sg:orig_category":"Farmacias",
    "sg:phone":"+34 987 22 32 84",
    "sg:postcode":"24002",
    "sg:province":"Le\u00f3n",
    "wof:name":"Perez Martinez Ramon",
    "wof:placetype":"venue"
},
  "geometry": {"coordinates":[-5.5793509483,42.6016578674],"type":"Point"}
}