{
  "type": "Feature",
  "properties": {
    "addr:full":"Calle de Practicante Agapito Arbelo, 1 Palmas De Gran Canaria Las Palmas 35012",
    "addr:housenumber":"1",
    "addr:postcode":"35012",
    "addr:street":"Calle De Practicante;Arbelo",
    "iso:country":"ES",
    "sg:address":"Calle de Practicante Agapito Arbelo, 1",
    "sg:city":"Palmas De Gran Canaria",
    "sg:orig_category":"Transportes Por Carretera: Lotes Completos, Mercanc\u00cdas Diversas",
    "sg:phone":"+34 928 25 72 84",
    "sg:postcode":"35012",
    "sg:province":"Las Palmas",
    "wof:name":"Quintana Almeida Emilio",
    "wof:placetype":"venue"
},
  "geometry": {"coordinates":[-15.4269132614,28.1097793579],"type":"Point"}
}