{
  "type": "Feature",
  "properties": {
    "addr:full":"Calle de Cerrolaza, 20 Pozuelo De Alarcon Madrid 28224",
    "addr:housenumber":"20",
    "addr:postcode":"28224",
    "addr:street":"Calle De Cerrolaza",
    "iso:country":"ES",
    "sg:address":"Calle de Cerrolaza, 20",
    "sg:city":"Pozuelo De Alarcon",
    "sg:orig_category":"Inversiones",
    "sg:phone":"+34 917 15 35 27",
    "sg:postcode":"28224",
    "sg:province":"Madrid",
    "wof:name":"Patrimonial Liberti S.l.",
    "wof:placetype":"venue"
},
  "geometry": {"coordinates":[-3.804451704,40.448097229],"type":"Point"}
}