{
  "type": "Feature",
  "properties": {
    "addr:full":"Calle de Independencia (la), 5 Segovia Segovia 40002",
    "addr:housenumber":"5",
    "addr:postcode":"40002",
    "addr:street":"Calle De Independencia La",
    "iso:country":"ES",
    "sg:address":"Calle de Independencia (la), 5",
    "sg:city":"Segovia",
    "sg:orig_category":"Lencer\u00cda Femenina, Corseter\u00cda, Trajes De Ba\u00d1o (al Por Menor)",
    "sg:phone":"+34 921 43 31 36",
    "sg:postcode":"40002",
    "sg:province":"Segovia",
    "wof:name":"Neli C B",
    "wof:placetype":"venue"
},
  "geometry": {"coordinates":[-4.1179900169,40.9455108643],"type":"Point"}
}