{
  "type": "Feature",
  "properties": {
    "iso:country":"ES",
    "sg:address":"Avda Manuel Salmeron, 41",
    "sg:city":"Berja",
    "sg:orig_category":"Ropa Para Ni\u00d1os (al Por Menor)",
    "sg:phone":"+34 950 49 10 10",
    "sg:postcode":"04760",
    "sg:province":"Almer\u00eda",
    "wof:name":"Lupion Maldonado Antonio",
    "wof:placetype":"venue"
},
  "geometry": {"coordinates":[-2.948101759,36.8452186584],"type":"Point"}
}