{
  "type": "Feature",
  "properties": {
    "addr:full":"Carr Nostra Sra Del Mig Aran, 16 Lleida Lleida 25005",
    "addr:housenumber":"16",
    "addr:postcode":"25005",
    "addr:street":"Carr Nostra Sra Del Mig Aran",
    "iso:country":"ES",
    "sg:address":"Carr Nostra Sra Del Mig Aran, 16",
    "sg:city":"Lleida",
    "sg:orig_category":"Empresas De Pintura Y Revestimientos",
    "sg:phone":"+34 973 23 36 14",
    "sg:postcode":"25005",
    "sg:province":"Lleida",
    "wof:name":"Marco Borgueras Jordi",
    "wof:placetype":"venue"
},
  "geometry": {"coordinates":[0.6301839948,41.6250724792],"type":"Point"}
}