{
  "type": "Feature",
  "properties": {
    "iso:country":"ES",
    "sg:address":"Plaz Moreno, 5",
    "sg:city":"Guadalajara",
    "sg:orig_category":"Centros De Coordinaci\u00d3n",
    "sg:phone":"+34 949 21 49 66",
    "sg:postcode":"19001",
    "sg:province":"Guadalajara",
    "wof:name":"Enguita Martin Jose Vicente",
    "wof:placetype":"venue"
},
  "geometry": {"coordinates":[-3.1637680531,40.6317100525],"type":"Point"}
}