{
  "type": "Feature",
  "properties": {
    "addr:full":"Calle de Manzanilla, 13 Puebla Montalban Toledo 45516",
    "addr:housenumber":"13",
    "addr:postcode":"45516",
    "addr:street":"Calle De Manzanilla",
    "iso:country":"ES",
    "sg:address":"Calle de Manzanilla, 13",
    "sg:city":"Puebla Montalban",
    "sg:orig_category":"Cajas Para Embalar",
    "sg:phone":"+34 925 75 07 54",
    "sg:postcode":"45516",
    "sg:province":"Toledo",
    "wof:name":"Caja Rural Provincial De Toledo",
    "wof:placetype":"venue"
},
  "geometry": {"coordinates":[-4.3592891693,39.8641395569],"type":"Point"}
}