{
  "type": "Feature",
  "properties": {
    "addr:full":"Pase Concha (la), S/n Playa Castell\u00f3n 12594",
    "addr:housenumber":"/ n",
    "addr:postcode":"12594",
    "addr:street":"Concha La S;Playa Castello\u0301N",
    "iso:country":"ES",
    "sg:address":"Pase Concha (la), S/n",
    "sg:city":"Playa",
    "sg:orig_category":"Porcelanas, Azulejos (fabricaci\u00d3n, Al Por Mayor)",
    "sg:phone":"+34 964 31 08 48",
    "sg:postcode":"12594",
    "sg:province":"Castell\u00f3n",
    "wof:name":"Serra Mezquita Juan Manuel",
    "wof:placetype":"venue"
},
  "geometry": {"coordinates":[0.135344997,40.0945358276],"type":"Point"}
}