{
  "type": "Feature",
  "properties": {
    "iso:country":"ES",
    "sg:address":"Cllo Marina, De La, 1",
    "sg:city":"Melilla",
    "sg:orig_category":"Inform\u00c1tica Equipo Y Programas (al Por Mayor)",
    "sg:phone":"+34 952 69 17 91",
    "sg:postcode":"52005",
    "sg:province":"Melilla",
    "wof:name":"A & C Informatica Y Networking S.l.",
    "wof:placetype":"venue"
},
  "geometry": {"coordinates":[-2.9490895271,35.2900505066],"type":"Point"}
}