{
  "type": "Feature",
  "properties": {
    "addr:full":"Calle de General Franco, 31 Padron La Coru\u00f1a 15900",
    "addr:housenumber":"31",
    "addr:postcode":"15900",
    "addr:street":"Calle De General Franco;Padron La Corun\u0303A",
    "iso:country":"ES",
    "sg:address":"Calle de General Franco, 31",
    "sg:city":"Padron",
    "sg:orig_category":"Ropa Para Ni\u00d1os (al Por Menor)",
    "sg:phone":"+34 981 81 20 38",
    "sg:postcode":"15900",
    "sg:province":"La Coru\u00f1a",
    "wof:name":"Perez Guimarey Isabel",
    "wof:placetype":"venue"
},
  "geometry": {"coordinates":[-8.6605796814,42.7382087708],"type":"Point"}
}