{
  "type": "Feature",
  "properties": {
    "iso:country":"ES",
    "sg:address":"Carrer de Consell De Cent, 555",
    "sg:city":"Barcelona",
    "sg:orig_category":"Ense\u00d1anza Industrial Y T\u00c9cnica",
    "sg:phone":"+34 934 59 27 66",
    "sg:postcode":"08013",
    "sg:province":"Barcelona",
    "wof:name":"Vipassana S.l.",
    "wof:placetype":"venue"
},
  "geometry": {"coordinates":[2.1824450493,41.4038505554],"type":"Point"}
}