{
  "type": "Feature",
  "properties": {
    "addr:full":"Carrer de Boix, 2 Barri Maritim De Sant Salvador Tarragona 43880",
    "addr:housenumber":"2",
    "addr:postcode":"43880",
    "addr:street":"Carrer De Boix",
    "iso:country":"ES",
    "sg:address":"Carrer de Boix, 2",
    "sg:city":"Barri Maritim De Sant Salvador",
    "sg:orig_category":"Inmobiliaria (agencias)",
    "sg:phone":"+34 977 68 18 47",
    "sg:postcode":"43880",
    "sg:province":"Tarragona",
    "wof:name":"Casulleras Romeu S.l.",
    "wof:placetype":"venue"
},
  "geometry": {"coordinates":[1.5444580317,41.1846618652],"type":"Point"}
}