{
  "type": "Feature",
  "properties": {
    "addr:full":"Calle de Ave Maria, 28 Ponferrada Le\u00f3n 24400",
    "addr:housenumber":"28",
    "addr:postcode":"24400",
    "addr:street":"Calle De Ave Maria",
    "iso:country":"ES",
    "sg:address":"Calle de Ave Maria, 28",
    "sg:city":"Ponferrada",
    "sg:orig_category":"M\u00c9dicos: Estomatolog\u00cda",
    "sg:phone":"+34 987 42 59 24",
    "sg:postcode":"24400",
    "sg:province":"Le\u00f3n",
    "wof:name":"Garcia Nu\u00f1ez Hermenegildo",
    "wof:placetype":"venue"
},
  "geometry": {"coordinates":[-6.6029443741,42.5477104187],"type":"Point"}
}