{
  "type": "Feature",
  "properties": {
    "iso:country":"ES",
    "sg:address":"Calle de Pola De La, 19",
    "sg:city":"Salas",
    "sg:orig_category":"Molduras, Junquillos, Listones Y Molduras Perforadas",
    "sg:phone":"+34 985 83 09 31",
    "sg:postcode":"33860",
    "sg:province":"Asturias",
    "wof:name":"Suarez Paz Aniceto",
    "wof:placetype":"venue"
},
  "geometry": {"coordinates":[-6.2592597008,43.4093933105],"type":"Point"}
}