{
  "type": "Feature",
  "properties": {
    "addr:full":"Av Generalitat Valenciana, S/n Calpe Alicante 03710",
    "addr:postcode":"03710",
    "addr:street":"Av Generalitat Valenciana S / N",
    "iso:country":"ES",
    "sg:address":"Av Generalitat Valenciana, S/n",
    "sg:city":"Calpe",
    "sg:orig_category":"Promotores Constructores",
    "sg:phone":"+34 965 83 97 35",
    "sg:postcode":"03710",
    "sg:province":"Alicante",
    "wof:name":"Calp Garden S.l.",
    "wof:placetype":"venue"
},
  "geometry": {"coordinates":[0.0392999984,38.6525382996],"type":"Point"}
}