{
  "type": "Feature",
  "properties": {
    "iso:country":"ES",
    "sg:address":"Calle de Fondos De Segura, 13",
    "sg:city":"Palmas De Gran Canaria",
    "sg:orig_category":"Trabajos De Topograf\u00cda",
    "sg:phone":"+34 928 42 80 94",
    "sg:postcode":"35019",
    "sg:province":"Las Palmas",
    "wof:name":"Rodriguez Garcia Sonsoles",
    "wof:placetype":"venue"
},
  "geometry": {"coordinates":[-15.4533042908,28.1070899963],"type":"Point"}
}