{
  "type": "Feature",
  "properties": {
    "addr:full":"Calle de Calixto Iii, 32 Valencia Valencia 46008",
    "addr:housenumber":"32",
    "addr:postcode":"46008",
    "addr:street":"Calle De Calixto Iii",
    "iso:country":"ES",
    "sg:address":"Calle de Calixto Iii, 32",
    "sg:city":"Valencia",
    "sg:orig_category":"Plomeros",
    "sg:phone":"+34 963 84 52 60",
    "sg:postcode":"46008",
    "sg:province":"Valencia",
    "wof:name":"Sanchez Redondo Jose Enrique",
    "wof:placetype":"venue"
},
  "geometry": {"coordinates":[-0.3910171092,39.4704208374],"type":"Point"}
}