{
  "type": "Feature",
  "properties": {
    "iso:country":"ES",
    "sg:address":"Avda Espa\u00d1a, S/n",
    "sg:city":"Segorbe",
    "sg:orig_category":"Panader\u00cdas, Panader\u00cdas",
    "sg:phone":"+34 964 71 15 08",
    "sg:postcode":"12400",
    "sg:province":"Castell\u00f3n",
    "wof:name":"Pasteleria Mauro S.l.",
    "wof:placetype":"venue"
},
  "geometry": {"coordinates":[-0.4834690094,39.8461456299],"type":"Point"}
}