{
  "type": "Feature",
  "properties": {
    "addr:full":"Avda Jose Fernandez Ruiz, 52 Lebrija Sevilla 41740",
    "addr:housenumber":"52",
    "addr:postcode":"41740",
    "addr:street":"Avda Jose Fernandez Ruiz",
    "iso:country":"ES",
    "sg:address":"Avda Jose Fernandez Ruiz, 52",
    "sg:city":"Lebrija",
    "sg:orig_category":"Alimentaci\u00d3n General (al Por Menor)",
    "sg:phone":"+34 955 97 36 40",
    "sg:postcode":"41740",
    "sg:province":"Sevilla",
    "wof:name":"Alimentacion Lebrijana Sl",
    "wof:placetype":"venue"
},
  "geometry": {"coordinates":[-6.0680088997,36.9201126099],"type":"Point"}
}