{
  "type": "Feature",
  "properties": {
    "iso:country":"ES",
    "sg:address":"Calle de Magallon, 1",
    "sg:city":"Tudela",
    "sg:orig_category":"Molduras, Junquillos, Listones Y Molduras Perforadas",
    "sg:phone":"+34 948 40 27 26",
    "sg:postcode":"31500",
    "sg:province":"Navarra",
    "wof:name":"Vifustu S.l.",
    "wof:placetype":"venue"
},
  "geometry": {"coordinates":[-1.604467988,42.0636978149],"type":"Point"}
}