{
  "type": "Feature",
  "properties": {
    "iso:country":"ES",
    "sg:address":"Carrer de Bonsucces, 1",
    "sg:city":"Manresa",
    "sg:orig_category":"Fabricaci\u00d3n, Importaci\u00d3n, Venta De Material De Telefon\u00cda, Peritelefon\u00cda",
    "sg:phone":"+34 938 72 95 44",
    "sg:postcode":"08241",
    "sg:province":"Barcelona",
    "wof:name":"Mitexno S.l.",
    "wof:placetype":"venue"
},
  "geometry": {"coordinates":[1.8261120319,41.72706604],"type":"Point"}
}