{
  "type": "Feature",
  "properties": {
    "addr:full":"Av. B. Navarra, 14 Iru\u00f1a Navarra 31004",
    "addr:housenumber":"14",
    "addr:postcode":"31004",
    "addr:street":"Av. B. Navarra",
    "iso:country":"ES",
    "sg:address":"Av. B. Navarra, 14",
    "sg:city":"Iru\u00f1a",
    "sg:orig_category":"Peluqueros: De Se\u00d1oras",
    "sg:phone":"+34 948 24 60 79",
    "sg:postcode":"31004",
    "sg:province":"Navarra",
    "wof:name":"Reta Roldan Ascension",
    "wof:placetype":"venue"
},
  "geometry": {"coordinates":[-1.6703180075,42.8218765259],"type":"Point"}
}