{
  "type": "Feature",
  "properties": {
    "addr:full":"Calle de Juan Medina Giraldo, 12 Majoreras Las Palmas 35240",
    "addr:housenumber":"12",
    "addr:postcode":"35240",
    "addr:street":"Calle De Juan;Giraldo;Las Palmas",
    "iso:country":"ES",
    "sg:address":"Calle de Juan Medina Giraldo, 12",
    "sg:city":"Majoreras",
    "sg:orig_category":"Ropa Para Se\u00d1oras Y Caballeros (al Por Menor)",
    "sg:phone":"+34 928 78 25 27",
    "sg:postcode":"35240",
    "sg:province":"Las Palmas",
    "wof:name":"Sanchez Garcia Isabel",
    "wof:placetype":"venue"
},
  "geometry": {"coordinates":[-15.4088487625,27.9120388031],"type":"Point"}
}