{
  "type": "Feature",
  "properties": {
    "iso:country":"ES",
    "sg:address":"Avda General Marva, 8",
    "sg:city":"Alacant",
    "sg:orig_category":"Impuestos, Tesoro P\u00dablico",
    "sg:phone":"+34 965 20 73 24",
    "sg:postcode":"03004",
    "sg:province":"Alicante",
    "wof:name":"Tasaciones De Bienes Mediterraneo S.a.",
    "wof:placetype":"venue"
},
  "geometry": {"coordinates":[-0.4911490083,38.3470802307],"type":"Point"}
}