{
  "type": "Feature",
  "properties": {
    "iso:country":"ES",
    "sg:address":"Calle de Pintor Sorolla, 6",
    "sg:city":"Logro\u00f1o",
    "sg:orig_category":"Consultor\u00cdas Diversas",
    "sg:phone":"+34 941 51 11 20",
    "sg:postcode":"26007",
    "sg:province":"La Rioja",
    "sg:website":"www.icarus.es",
    "wof:name":"Estudios Medioambientales Icarus S.l.",
    "wof:placetype":"venue"
},
  "geometry": {"coordinates":[-2.4586119652,42.4580459595],"type":"Point"}
}