{
  "type": "Feature",
  "properties": {
    "iso:country":"ES",
    "sg:address":"G.v. Marques Del Turia, 55",
    "sg:city":"Valencia",
    "sg:orig_category":"Abogados",
    "sg:phone":"+34 963 94 50 60",
    "sg:postcode":"46005",
    "sg:province":"Valencia",
    "wof:name":"Agustina Carcel Silvia",
    "wof:placetype":"venue"
},
  "geometry": {"coordinates":[-0.3679871857,39.467540741],"type":"Point"}
}