{
  "type": "Feature",
  "properties": {
    "addr:full":"Calle de Desenga\u00d1o, 102 Huesca Huesca 22002",
    "addr:housenumber":"102",
    "addr:postcode":"22002",
    "addr:street":"Calle De Desengan\u0303O",
    "iso:country":"ES",
    "sg:address":"Calle de Desenga\u00d1o, 102",
    "sg:city":"Huesca",
    "sg:orig_category":"Empresas De Carpinter\u00cda De Madera",
    "sg:phone":"+34 974 22 33 38",
    "sg:postcode":"22002",
    "sg:province":"Huesca",
    "wof:name":"Olivan Campo Mariano",
    "wof:placetype":"venue"
},
  "geometry": {"coordinates":[-0.4081467986,42.1433410645],"type":"Point"}
}