{
  "type": "Feature",
  "properties": {
    "addr:full":"Calle de San Roque, 11 Ibi Alicante 03440",
    "addr:housenumber":"11",
    "addr:postcode":"03440",
    "addr:street":"Calle De San Roque",
    "iso:country":"ES",
    "sg:address":"Calle de San Roque, 11",
    "sg:city":"Ibi",
    "sg:orig_category":"Centros Empresariales",
    "sg:phone":"+34 966 55 01 49",
    "sg:postcode":"03440",
    "sg:province":"Alicante",
    "wof:name":"Agrupacion Del Comercio Ibense",
    "wof:placetype":"venue"
},
  "geometry": {"coordinates":[-0.5762237906,38.6246986389],"type":"Point"}
}