{
  "type": "Feature",
  "properties": {
    "addr:full":"Arquimedes, 260 Gijon Asturias 33211",
    "addr:postcode":"33211",
    "addr:street":"Arquimedes 260",
    "iso:country":"ES",
    "sg:address":"Arquimedes, 260",
    "sg:city":"Gijon",
    "sg:orig_category":"Frutas Y Legumbres Frescas (al Por Mayor)",
    "sg:phone":"+34 985 30 70 93",
    "sg:postcode":"33211",
    "sg:province":"Asturias",
    "wof:name":"Frutas Sutil S. L.",
    "wof:placetype":"venue"
},
  "geometry": {"coordinates":[-5.6863942146,43.5233383179],"type":"Point"}
}