{
  "type": "Feature",
  "properties": {
    "iso:country":"ES",
    "sg:address":"Cmno Cruz Del Gamonal, 7",
    "sg:city":"Gamonal Alto",
    "sg:orig_category":"Ense\u00d1anza Agr\u00cdcola",
    "sg:phone":"+34 928 64 48 21",
    "sg:postcode":"35300",
    "sg:province":"Las Palmas",
    "wof:name":"Granja Verde S.l.",
    "wof:placetype":"venue"
},
  "geometry": {"coordinates":[-15.4988956451,28.0369472504],"type":"Point"}
}