{
  "type": "Feature",
  "properties": {
    "iso:country":"ES",
    "sg:address":"Calle de Prudencio Maria Verastegui, 14",
    "sg:city":"Vitoria-gasteiz",
    "sg:orig_category":"Muebles, Minoristas",
    "sg:phone":"+34 945 27 00 07",
    "sg:postcode":"01002",
    "sg:province":"\u00c1lava",
    "wof:name":"A.m. Scv",
    "wof:placetype":"venue"
},
  "geometry": {"coordinates":[-2.6623649597,42.85364151],"type":"Point"}
}