{
  "type": "Feature",
  "properties": {
    "addr:full":"Calle de Abella, 2 Madrid Madrid 28044",
    "addr:housenumber":"2",
    "addr:postcode":"28044",
    "addr:street":"Calle De Abella",
    "iso:country":"ES",
    "sg:address":"Calle de Abella, 2",
    "sg:city":"Madrid",
    "sg:orig_category":"Poller\u00cda Y Caza (al Por Menor)",
    "sg:phone":"+34 915 08 65 24",
    "sg:postcode":"28044",
    "sg:province":"Madrid",
    "wof:name":"Vivar Lopez Ramon Valerico",
    "wof:placetype":"venue"
},
  "geometry": {"coordinates":[-3.7530508041,40.3705978394],"type":"Point"}
}