{
  "type": "Feature",
  "properties": {
    "iso:country":"ES",
    "sg:address":"Transportes, 68",
    "sg:city":"Pepino",
    "sg:orig_category":"Fabrica De Cer\u00c1micas",
    "sg:phone":"+34 925 70 94 71",
    "sg:postcode":"45638",
    "sg:province":"Toledo",
    "wof:name":"J.m. Bross S.l.",
    "wof:placetype":"venue"
},
  "geometry": {"coordinates":[-4.8258938789,40.0016593933],"type":"Point"}
}