{
  "type": "Feature",
  "properties": {
    "addr:full":"Carr Ferrocarril D'alcoi, 8 Gandia Valencia 46700",
    "addr:housenumber":"8",
    "addr:postcode":"46700",
    "addr:street":"Carr Ferrocarril D'Alcoi;Valencia",
    "iso:country":"ES",
    "sg:address":"Carr Ferrocarril D'alcoi, 8",
    "sg:city":"Gandia",
    "sg:orig_category":"Inform\u00c1tica (estudios, Servicios, Asesor\u00cda, Formaci\u00d3n)",
    "sg:phone":"+34 962 96 58 91",
    "sg:postcode":"46700",
    "sg:province":"Valencia",
    "sg:website":"www.dminformatica.net",
    "wof:name":"Dm Informatica Sl",
    "wof:placetype":"venue"
},
  "geometry": {"coordinates":[-0.1859460026,38.9636764526],"type":"Point"}
}