{
  "type": "Feature",
  "properties": {
    "iso:country":"ES",
    "sg:address":"Ctra. Venta Obispo, S/n",
    "sg:city":"Hoyocasero",
    "sg:orig_category":"Serrer\u00cdas De Madera",
    "sg:phone":"+34 920 29 98 13",
    "sg:postcode":"05124",
    "sg:province":"\u00c1vila",
    "wof:name":"Martin Gonzalez Ricardo",
    "wof:placetype":"venue"
},
  "geometry": {"coordinates":[-4.9756889343,40.3977851868],"type":"Point"}
}