{
  "type": "Feature",
  "properties": {
    "addr:full":"Calle de Cedros (de Los), 61 Parque Coimbra Madrid 28935",
    "addr:postcode":"28935",
    "addr:street":"Calle De Cedros De Los;Parque",
    "iso:country":"ES",
    "sg:address":"Calle de Cedros (de Los), 61",
    "sg:city":"Parque Coimbra",
    "sg:orig_category":"Inmobiliaria (agencias)",
    "sg:phone":"+34 916 48 29 07",
    "sg:postcode":"28935",
    "sg:province":"Madrid",
    "wof:name":"Dominguez Marcos Antonio",
    "wof:placetype":"venue"
},
  "geometry": {"coordinates":[-3.9255678654,40.3043632507],"type":"Point"}
}