{
  "type": "Feature",
  "properties": {
    "iso:country":"ES",
    "sg:address":"Av. Pio Xii, 16",
    "sg:city":"Iru\u00f1a",
    "sg:orig_category":"Asesor\u00cda Sobre Comunicaci\u00d3n De Empresas",
    "sg:phone":"+34 948 27 44 75",
    "sg:postcode":"31008",
    "sg:province":"Navarra",
    "wof:name":"Tafisco S.a.",
    "wof:placetype":"venue"
},
  "geometry": {"coordinates":[-1.6584379673,42.8094367981],"type":"Point"}
}