{
  "type": "Feature",
  "properties": {
    "iso:country":"ES",
    "sg:address":"Trva Rosalia De Castro, 2",
    "sg:city":"Estrada",
    "sg:orig_category":"\u00d3ptica: Instrumentos (fabricaci\u00d3n)",
    "sg:phone":"+34 986 57 25 04",
    "sg:postcode":"36680",
    "sg:province":"Pontevedra",
    "wof:name":"Garcia Seoane Jose Manuel",
    "wof:placetype":"venue"
},
  "geometry": {"coordinates":[-8.4974126816,42.6887588501],"type":"Point"}
}