{
  "type": "Feature",
  "properties": {
    "addr:full":"Calle de Alarifes, S/n Dos Hermanas Sevilla 41700",
    "addr:housenumber":"s",
    "addr:postcode":"41700",
    "addr:street":"Calle De Alarifes;/ N Dos",
    "iso:country":"ES",
    "sg:address":"Calle de Alarifes, S/n",
    "sg:city":"Dos Hermanas",
    "sg:orig_category":"Internados & Ense\u00d1anza Privada",
    "sg:phone":"+34 954 72 61 77",
    "sg:postcode":"41700",
    "sg:province":"Sevilla",
    "wof:name":"Maria Zambrano Sociedad Coperativa Andaluza",
    "wof:placetype":"venue"
},
  "geometry": {"coordinates":[-5.9240074158,37.2732620239],"type":"Point"}
}