{
  "type": "Feature",
  "properties": {
    "iso:country":"ES",
    "sg:address":"Carrer de Mossen Jacint Verdaguer, 30",
    "sg:city":"Sant Vicen\u00c7 Dels Horts",
    "sg:orig_category":"Asociaciones Y Clubs Deportivos",
    "sg:phone":"+34 936 56 90 72",
    "sg:postcode":"08620",
    "sg:province":"Barcelona",
    "wof:name":"Via Esports Sant Vicenc S.l.",
    "wof:placetype":"venue"
},
  "geometry": {"coordinates":[2.0097429752,41.393901825],"type":"Point"}
}