{
  "type": "Feature",
  "properties": {
    "iso:country":"ES",
    "sg:address":"Calle de Gobernador Civil Jose Garcia Hernandez, 13",
    "sg:city":"Arrecife",
    "sg:orig_category":"Navegaci\u00d3n (equipos Fluviales)",
    "sg:phone":"+34 928 81 18 19",
    "sg:postcode":"35500",
    "sg:province":"Las Palmas",
    "wof:name":"Pesqueras Toledo S.l.",
    "wof:placetype":"venue"
},
  "geometry": {"coordinates":[-13.5440587997,28.965587616],"type":"Point"}
}