{
  "type": "Feature",
  "properties": {
    "iso:country":"ES",
    "sg:address":"Calle de Lobez Pueyo, 2",
    "sg:city":"Zaragoza",
    "sg:orig_category":"Bisuter\u00cda, Joyer\u00cda, Relojer\u00cda (al Por Menor)",
    "sg:phone":"+34 976 25 18 50",
    "sg:postcode":"50007",
    "sg:province":"Zaragoza",
    "wof:name":"Rodriguez Portero Lucia",
    "wof:placetype":"venue"
},
  "geometry": {"coordinates":[-0.8858169913,41.6290283203],"type":"Point"}
}