{
  "type": "Feature",
  "properties": {
    "iso:country":"ES",
    "sg:address":"Avda Los Huetos, 46",
    "sg:city":"Vitoria-gasteiz",
    "sg:orig_category":"Comercio, Reparaci\u00d3n De Bicicletas, De Motocicletas, De Accesorios",
    "sg:phone":"+34 945 21 71 95",
    "sg:postcode":"01010",
    "sg:province":"\u00c1lava",
    "sg:website":"www.campagnolo.es",
    "wof:name":"Campagnolo Iberica S.l.",
    "wof:placetype":"venue"
},
  "geometry": {"coordinates":[-2.7108840942,42.8564186096],"type":"Point"}
}