{
  "type": "Feature",
  "properties": {
    "iso:country":"ES",
    "sg:address":"Calle de Mirabel, 38",
    "sg:city":"Madrid",
    "sg:orig_category":"Internados & Ense\u00d1anza Privada",
    "sg:phone":"+34 917 05 55 00",
    "sg:postcode":"28044",
    "sg:province":"Madrid",
    "wof:name":"Congregacion Religiosas Sagrados Corazon",
    "wof:placetype":"venue"
},
  "geometry": {"coordinates":[-3.7809689045,40.377040863],"type":"Point"}
}