{
  "type": "Feature",
  "properties": {
    "addr:full":"Carr Cor De Maria, 10 Girona Girona 17002",
    "addr:housenumber":"10",
    "addr:postcode":"17002",
    "addr:street":"Carr Cor De Maria",
    "iso:country":"ES",
    "sg:address":"Carr Cor De Maria, 10",
    "sg:city":"Girona",
    "sg:orig_category":"M\u00c9dicos: Radioterapia (radioterapia Como Opci\u00d3n Oncol\u00d3gica)",
    "sg:phone":"+34 972 21 71 03",
    "sg:postcode":"17002",
    "sg:province":"Girona",
    "wof:name":"Sola Pascual Pere",
    "wof:placetype":"venue"
},
  "geometry": {"coordinates":[2.8180720806,41.9755439758],"type":"Point"}
}