{
  "type": "Feature",
  "properties": {
    "iso:country":"ES",
    "sg:address":"La Cerrajera, S/n",
    "sg:city":"Cuenca",
    "sg:orig_category":"Empresas De Pintura Y Revestimientos",
    "sg:phone":"+34 969 23 23 11",
    "sg:postcode":"16004",
    "sg:province":"Cuenca",
    "wof:name":"Abad Saiz Julio",
    "wof:placetype":"venue"
},
  "geometry": {"coordinates":[-2.144386,40.057041],"type":"Point"}
}