{
  "type": "Feature",
  "properties": {
    "addr:full":"Calle de Emilio Castelar, 65 Alcazar S. Juan Ciudad Real 13600",
    "addr:housenumber":"65",
    "addr:postcode":"13600",
    "addr:street":"Calle De Emilio Castelar;Alcazar S. Juan Ciudad Real",
    "iso:country":"ES",
    "sg:address":"Calle de Emilio Castelar, 65",
    "sg:city":"Alcazar S. Juan",
    "sg:orig_category":"Ense\u00d1anza, Formaci\u00d3n Profesional: Aprendizaje",
    "sg:phone":"+34 926 54 57 50",
    "sg:postcode":"13600",
    "sg:province":"Ciudad Real",
    "wof:name":"Centro Asociado A Uned",
    "wof:placetype":"venue"
},
  "geometry": {"coordinates":[-3.2074689865,39.3921394348],"type":"Point"}
}