{
  "type": "Feature",
  "properties": {
    "iso:country":"ES",
    "sg:address":"Calle de Polar, 3",
    "sg:city":"Jerez De La Frontera",
    "sg:orig_category":"Perfumer\u00cda Y Cosm\u00c9tica (fabricaci\u00d3n, Al Por Mayor)",
    "sg:phone":"+34 956 30 32 47",
    "sg:postcode":"11407",
    "sg:province":"C\u00e1diz",
    "wof:name":"Distribella S.l.",
    "wof:placetype":"venue"
},
  "geometry": {"coordinates":[-6.0982751846,36.7228431702],"type":"Point"}
}