{
  "type": "Feature",
  "properties": {
    "iso:country":"ES",
    "sg:address":"Calle de Zaragoza, 14",
    "sg:city":"Mostoles",
    "sg:orig_category":"Suministros Para Hoteles",
    "sg:phone":"+34 916 18 00 29",
    "sg:postcode":"28934",
    "sg:province":"Madrid",
    "wof:name":"Domiciano Mu\u00f1oz Lumbreras Y Otros Cdad.",
    "wof:placetype":"venue"
},
  "geometry": {"coordinates":[-3.8702270985,40.3226509094],"type":"Point"}
}