{
  "type": "Feature",
  "properties": {
    "addr:full":"Calle de Huertos, 45 Sagunt Valencia 46500",
    "addr:housenumber":"45",
    "addr:postcode":"46500",
    "addr:street":"Calle De Huertos",
    "iso:country":"ES",
    "sg:address":"Calle de Huertos, 45",
    "sg:city":"Sagunt",
    "sg:orig_category":"Farmacias",
    "sg:phone":"+34 962 66 22 79",
    "sg:postcode":"46500",
    "sg:province":"Valencia",
    "wof:name":"Balaguer Piera C.b.",
    "wof:placetype":"venue"
},
  "geometry": {"coordinates":[-0.2740181088,39.6807632446],"type":"Point"}
}