{
  "type": "Feature",
  "properties": {
    "addr:full":"Calle de Gran Via, 27 Majadahonda Madrid 28220",
    "addr:housenumber":"27",
    "addr:postcode":"28220",
    "addr:street":"Calle De Gran Via",
    "iso:country":"ES",
    "sg:address":"Calle de Gran Via, 27",
    "sg:city":"Majadahonda",
    "sg:orig_category":"Inmobiliaria (agencias)",
    "sg:phone":"+34 916 34 75 50",
    "sg:postcode":"28220",
    "sg:province":"Madrid",
    "wof:name":"Fincas Corral Barcino S.l.u.",
    "wof:placetype":"venue"
},
  "geometry": {"coordinates":[-3.871407032,40.4715652466],"type":"Point"}
}