{
  "type": "Feature",
  "properties": {
    "iso:country":"ES",
    "sg:address":"Carrer de Amadeu I, 32",
    "sg:city":"Masnou",
    "sg:orig_category":"Asesor\u00cda Sobre Comunicaci\u00d3n De Empresas",
    "sg:phone":"+34 935 40 36 36",
    "sg:postcode":"08320",
    "sg:province":"Barcelona",
    "wof:name":"Josa-marcos Assessorament I Gestio S.l.",
    "wof:placetype":"venue"
},
  "geometry": {"coordinates":[2.307363987,41.4768981934],"type":"Point"}
}