{
  "type": "Feature",
  "properties": {
    "iso:country":"ES",
    "sg:address":"Calle de Escuelas, S/n",
    "sg:city":"Alquerias",
    "sg:orig_category":"Promotores Constructores",
    "sg:phone":"+34 968 81 16 04",
    "sg:postcode":"30580",
    "sg:province":"Murcia",
    "wof:name":"Comunidad De Propietarios Edificio Galan",
    "wof:placetype":"venue"
},
  "geometry": {"coordinates":[-1.0357040167,38.0160102844],"type":"Point"}
}