{
  "type": "Feature",
  "properties": {
    "iso:country":"ES",
    "sg:address":"Calle de Rey Pelayo, S/n",
    "sg:city":"Piedras Blancas",
    "sg:orig_category":"Piscinas (establecimientos)",
    "sg:phone":"+34 985 53 20 11",
    "sg:postcode":"33450",
    "sg:province":"Asturias",
    "wof:name":"Patronato Municipal De Actividades Deportivas-castrillon",
    "wof:placetype":"venue"
},
  "geometry": {"coordinates":[-5.9761581421,43.5644836426],"type":"Point"}
}