{
  "type": "Feature",
  "properties": {
    "addr:full":"Carrer de Assumpcio, 5 Benidorm Alicante 03500",
    "addr:housenumber":"5",
    "addr:postcode":"03500",
    "addr:street":"Carrer De Assumpcio",
    "iso:country":"ES",
    "sg:address":"Carrer de Assumpcio, 5",
    "sg:city":"Benidorm",
    "sg:orig_category":"Heladeros",
    "sg:phone":"+34 965 86 41 34",
    "sg:postcode":"03500",
    "sg:province":"Alicante",
    "wof:name":"Luis Sirvent Candela S.l.",
    "wof:placetype":"venue"
},
  "geometry": {"coordinates":[-0.1307670027,38.538230896],"type":"Point"}
}