{
  "type": "Feature",
  "properties": {
    "iso:country":"ES",
    "sg:address":"Ctra. General, S/n",
    "sg:city":"Ballota",
    "sg:orig_category":"Alimentaci\u00d3n General (al Por Mayor)",
    "sg:phone":"+34 985 59 82 61",
    "sg:postcode":"33158",
    "sg:province":"Asturias",
    "wof:name":"Martinez Fernandez Armando",
    "wof:placetype":"venue"
},
  "geometry": {"coordinates":[-6.3312840462,43.551864624],"type":"Point"}
}