{
  "type": "Feature",
  "properties": {
    "addr:full":"Ctra Torrejon (de), Km. 0002,4 Ajalvir Madrid 28864",
    "addr:postcode":"28864",
    "addr:street":"Ctra Torrejon De Km. 0002,4",
    "iso:country":"ES",
    "sg:address":"Ctra Torrejon (de), Km. 0002,4",
    "sg:city":"Ajalvir",
    "sg:orig_category":"Muebles Y Accesorios Para Cocinas Y Cuartos De Ba\u00d1o (al Por Menor)",
    "sg:phone":"+34 918 84 39 60",
    "sg:postcode":"28864",
    "sg:province":"Madrid",
    "wof:name":"Cocina Alve S.l.",
    "wof:placetype":"venue"
},
  "geometry": {"coordinates":[-3.481482029,40.5256729126],"type":"Point"}
}