{
  "type": "Feature",
  "properties": {
    "iso:country":"ES",
    "sg:address":"Calle de Marques Del Duero, 68",
    "sg:city":"San Pedro Alcantara",
    "sg:orig_category":"Cajas Para Embalar",
    "sg:phone":"+34 952 78 08 74",
    "sg:postcode":"29670",
    "sg:province":"M\u00e1laga",
    "wof:name":"Cajamar",
    "wof:placetype":"venue"
},
  "geometry": {"coordinates":[-4.9894118309,36.4846420288],"type":"Point"}
}