{
  "type": "Feature",
  "properties": {
    "addr:full":"Calle de Mosquilona (de La), 57 Colmenar Viejo Madrid 28770",
    "addr:postcode":"28770",
    "addr:street":"Calle De Mosquilona De La",
    "iso:country":"ES",
    "sg:address":"Calle de Mosquilona (de La), 57",
    "sg:city":"Colmenar Viejo",
    "sg:orig_category":"Seguridad Social",
    "sg:phone":"+34 918 46 36 19",
    "sg:postcode":"28770",
    "sg:province":"Madrid",
    "wof:name":"Tesoreria General De La Seguridad Social Admon Y Ure Ag. 20",
    "wof:placetype":"venue"
},
  "geometry": {"coordinates":[-3.7765917778,40.6641311646],"type":"Point"}
}