{
  "type": "Feature",
  "properties": {
    "addr:full":"Calle de Santa Maria Encimera, 30 Briviesca Burgos 09240",
    "addr:housenumber":"30",
    "addr:postcode":"09240",
    "addr:street":"Calle De Santa;Encimera",
    "iso:country":"ES",
    "sg:address":"Calle de Santa Maria Encimera, 30",
    "sg:city":"Briviesca",
    "sg:orig_category":"Droguer\u00cdas (al Por Menor)",
    "sg:phone":"+34 947 59 25 15",
    "sg:postcode":"09240",
    "sg:province":"Burgos",
    "wof:name":"Urrutia Eugui Jose Maria",
    "wof:placetype":"venue"
},
  "geometry": {"coordinates":[-3.3238289356,42.5497283936],"type":"Point"}
}