{
  "type": "Feature",
  "properties": {
    "iso:country":"ES",
    "sg:address":"Via Julia, 111",
    "sg:city":"Barcelona",
    "sg:orig_category":"Colchones (fabricaci\u00d3n, Al Por Mayor, Al Por Menor)",
    "sg:phone":"+34 933 59 62 55",
    "sg:postcode":"08042",
    "sg:province":"Barcelona",
    "wof:name":"Fernandez Cuevas Antonia",
    "wof:placetype":"venue"
},
  "geometry": {"coordinates":[2.1776170731,41.4422569275],"type":"Point"}
}