{
  "type": "Feature",
  "properties": {
    "iso:country":"ES",
    "sg:address":"Avda Aguila Imperial(c Plumas), S/n",
    "sg:city":"Puerto Mazarron",
    "sg:orig_category":"M\u00c1rmoles, Granitos Y Piedras Naturales",
    "sg:phone":"+34 968 15 34 83",
    "sg:postcode":"30860",
    "sg:province":"Murcia",
    "wof:name":"Garlo Marmol S.l.l.",
    "wof:placetype":"venue"
},
  "geometry": {"coordinates":[-1.3136693239,37.5990715027],"type":"Point"}
}