{
  "type": "Feature",
  "properties": {
    "iso:country":"ES",
    "sg:address":"Calle de Filiberto Villalobos, 175",
    "sg:city":"Guijuelo",
    "sg:orig_category":"Centros De Coordinaci\u00d3n",
    "sg:phone":"+34 923 58 18 15",
    "sg:postcode":"37770",
    "sg:province":"Salamanca",
    "wof:name":"Martin Sanchez Francisco Javier",
    "wof:placetype":"venue"
},
  "geometry": {"coordinates":[-5.6724090576,40.5599899292],"type":"Point"}
}