{
  "type": "Feature",
  "properties": {
    "addr:full":"Sta. Teresa, 14 Ayacor Valencia 46659",
    "addr:housenumber":"14",
    "addr:postcode":"46659",
    "addr:street":"Sta. Teresa",
    "iso:country":"ES",
    "sg:address":"Sta. Teresa, 14",
    "sg:city":"Ayacor",
    "sg:orig_category":"Inversiones",
    "sg:phone":"+34 962 24 45 13",
    "sg:postcode":"46659",
    "sg:province":"Valencia",
    "wof:name":"Miras Ferrando Marketing S.l.",
    "wof:placetype":"venue"
},
  "geometry": {"coordinates":[-0.5748819709,38.9725074768],"type":"Point"}
}