{
  "type": "Feature",
  "properties": {
    "addr:full":"Avda Espa\u00d1a, 42 Ceuta Ceuta 51001",
    "addr:housenumber":"42",
    "addr:postcode":"51001",
    "addr:street":"Avda Espan\u0303A",
    "iso:country":"ES",
    "sg:address":"Avda Espa\u00d1a, 42",
    "sg:city":"Ceuta",
    "sg:orig_category":"Farmacias",
    "sg:phone":"+34 956 52 11 13",
    "sg:postcode":"51001",
    "sg:province":"Ceuta",
    "wof:name":"Parra Lopez Tomas Buenaventura",
    "wof:placetype":"venue"
},
  "geometry": {"coordinates":[-5.3245868683,35.8914299011],"type":"Point"}
}