{
  "type": "Feature",
  "properties": {
    "iso:country":"ES",
    "sg:address":"Avda Alemania, 1",
    "sg:city":"Coslada",
    "sg:orig_category":"Organizaciones Profesionales",
    "sg:phone":"+34 916 70 73 94",
    "sg:postcode":"28820",
    "sg:province":"Madrid",
    "wof:name":"Green Iberica S.a.",
    "wof:placetype":"venue"
},
  "geometry": {"coordinates":[-3.5568020344,40.4353103638],"type":"Point"}
}