{
  "type": "Feature",
  "properties": {
    "addr:full":"Grup Aixeona, 1 Bilbao Vizcaya 48004",
    "addr:housenumber":"1",
    "addr:postcode":"48004",
    "addr:street":"Grup Aixeona",
    "iso:country":"ES",
    "sg:address":"Grup Aixeona, 1",
    "sg:city":"Bilbao",
    "sg:orig_category":"Electricidad: Instaladores",
    "sg:phone":"+34 944 12 23 45",
    "sg:postcode":"48004",
    "sg:province":"Vizcaya",
    "wof:name":"Electricidad Laudio S.l.",
    "wof:placetype":"venue"
},
  "geometry": {"coordinates":[-2.9003720284,43.2620773315],"type":"Point"}
}