{
  "type": "Feature",
  "properties": {
    "iso:country":"ES",
    "sg:address":"Carrer de Sant Josep, 4",
    "sg:city":"Aldover",
    "sg:orig_category":"Aceites Y Grasas Alimentarias (fabricaci\u00d3n, Al Por Mayor)",
    "sg:phone":"+34 977 47 36 98",
    "sg:postcode":"43591",
    "sg:province":"Tarragona",
    "wof:name":"Sabate Franquet Alberto",
    "wof:placetype":"venue"
},
  "geometry": {"coordinates":[0.4988299906,40.8806762695],"type":"Point"}
}