{
  "type": "Feature",
  "properties": {
    "addr:full":"Calle de Taburiente, 30 S. Pedro Martir I Las Palmas 35110",
    "addr:housenumber":"30",
    "addr:postcode":"35110",
    "addr:street":"Calle De Taburiente;S. Pedro",
    "iso:country":"ES",
    "sg:address":"Calle de Taburiente, 30",
    "sg:city":"S. Pedro Martir I",
    "sg:orig_category":"Electricidad (montaje, Ensamblaje De Componentes)",
    "sg:phone":"+34 928 75 64 79",
    "sg:postcode":"35110",
    "sg:province":"Las Palmas",
    "wof:name":"Taller Electrico Hermanos Aleman S.l.c.",
    "wof:placetype":"venue"
},
  "geometry": {"coordinates":[-15.4485340118,27.8392906189],"type":"Point"}
}