{
  "type": "Feature",
  "properties": {
    "iso:country":"ES",
    "sg:address":"Arangutxi Kalea, 8",
    "sg:city":"Jundiz",
    "sg:orig_category":"Instalaci\u00d3n, Reparaci\u00d3n De Ascensores Y Montacargas",
    "sg:phone":"+34 945 29 16 25",
    "sg:postcode":"01015",
    "sg:province":"\u00c1lava",
    "wof:name":"Montespain S.l.",
    "wof:placetype":"venue"
},
  "geometry": {"coordinates":[-2.7263889313,42.8406524658],"type":"Point"}
}