{
  "type": "Feature",
  "properties": {
    "addr:full":"Calle de San Florencio, 7 Sevilla Sevilla 41018",
    "addr:housenumber":"7",
    "addr:postcode":"41018",
    "addr:street":"Calle De San Florencio",
    "iso:country":"ES",
    "sg:address":"Calle de San Florencio, 7",
    "sg:city":"Sevilla",
    "sg:orig_category":"Inmobiliaria (agencias)",
    "sg:phone":"+34 954 57 32 32",
    "sg:postcode":"41018",
    "sg:province":"Sevilla",
    "wof:name":"Gestion Inmobiliaria Acal S.l.",
    "wof:placetype":"venue"
},
  "geometry": {"coordinates":[-5.9756469727,37.3866920471],"type":"Point"}
}