{
  "type": "Feature",
  "properties": {
    "addr:full":"Calle de Santa Barbara, 5 Guardo Palencia 34880",
    "addr:housenumber":"5",
    "addr:postcode":"34880",
    "addr:street":"Calle De Santa Barbara",
    "iso:country":"ES",
    "sg:address":"Calle de Santa Barbara, 5",
    "sg:city":"Guardo",
    "sg:orig_category":"Abogados",
    "sg:phone":"+34 979 85 18 95",
    "sg:postcode":"34880",
    "sg:province":"Palencia",
    "wof:name":"Alvarez Ria\u00f1o Emilio",
    "wof:placetype":"venue"
},
  "geometry": {"coordinates":[-4.8478713036,42.7897605896],"type":"Point"}
}