{
  "type": "Feature",
  "properties": {
    "iso:country":"ES",
    "sg:address":"Calle de Federico Gutierrez, 35",
    "sg:city":"Madrid",
    "sg:orig_category":"Empresas De Carpinter\u00cda De Madera",
    "sg:phone":"+34 914 07 57 57",
    "sg:postcode":"28027",
    "sg:province":"Madrid",
    "wof:name":"Perales Castellanos Patricio Luis",
    "wof:placetype":"venue"
},
  "geometry": {"coordinates":[-3.6465389729,40.4366874695],"type":"Point"}
}