{
  "type": "Feature",
  "properties": {
    "iso:country":"ES",
    "sg:address":"Calle de Caceres, 4",
    "sg:city":"Coslada",
    "sg:orig_category":"Mercados De Productos Alimenticios",
    "sg:phone":"+34 916 73 29 65",
    "sg:postcode":"28820",
    "sg:province":"Madrid",
    "wof:name":"Manuel Diaz Y Otros C.b.",
    "wof:placetype":"venue"
},
  "geometry": {"coordinates":[-3.5677001476,40.423210144],"type":"Point"}
}