{
  "type": "Feature",
  "properties": {
    "iso:country":"ES",
    "sg:address":"Carr Industria, 608",
    "sg:city":"Badalona",
    "sg:orig_category":"Vidrio, Fabricaci\u00d3n Y Comercio",
    "sg:phone":"+34 933 88 82 11",
    "sg:postcode":"08918",
    "sg:province":"Barcelona",
    "wof:name":"Vidrios Gloria S.l.",
    "wof:placetype":"venue"
},
  "geometry": {"coordinates":[2.232448101,41.43151474],"type":"Point"}
}