{
  "type": "Feature",
  "properties": {
    "iso:country":"ES",
    "sg:address":"Calle de Florencia, 2",
    "sg:city":"Madrid",
    "sg:orig_category":"Agencias Y Agentes Comerciales, Representantes",
    "sg:phone":"+34 913 05 01 09",
    "sg:postcode":"28030",
    "sg:province":"Madrid",
    "wof:name":"Chapinal Martin Gema",
    "wof:placetype":"venue"
},
  "geometry": {"coordinates":[-3.6280770302,40.4021720886],"type":"Point"}
}