{
  "type": "Feature",
  "properties": {
    "iso:country":"ES",
    "sg:address":"Calle de Juan Carlos I, 19",
    "sg:city":"Cebreros",
    "sg:orig_category":"Cl\u00cdnicas Dentales",
    "sg:phone":"+34 918 63 06 31",
    "sg:postcode":"05260",
    "sg:province":"\u00c1vila",
    "wof:name":"Corral Lizana Cesar",
    "wof:placetype":"venue"
},
  "geometry": {"coordinates":[-4.4636111259,40.4552688599],"type":"Point"}
}