{
  "type": "Feature",
  "properties": {
    "addr:full":"Carr Santander, 9 Girona Girona 17005",
    "addr:housenumber":"9",
    "addr:postcode":"17005",
    "addr:street":"Carr Santander",
    "iso:country":"ES",
    "sg:address":"Carr Santander, 9",
    "sg:city":"Girona",
    "sg:orig_category":"Sales (al Por Mayor)",
    "sg:phone":"+34 972 23 71 12",
    "sg:postcode":"17005",
    "sg:province":"Girona",
    "sg:website":"www.compralambrusco.com",
    "wof:name":"Marketing Internacional Gimas S.l.",
    "wof:placetype":"venue"
},
  "geometry": {"coordinates":[2.8143389225,41.9756889343],"type":"Point"}
}