{
  "type": "Feature",
  "properties": {
    "iso:country":"ES",
    "sg:address":"Calle de Guadiana (del), 27",
    "sg:city":"Mejorada Campo",
    "sg:orig_category":"Rectificaci\u00d3n, Mecanizado, Fresado",
    "sg:phone":"+34 916 68 20 09",
    "sg:postcode":"28840",
    "sg:province":"Madrid",
    "wof:name":"Mateos Fernandez Jose Mateo",
    "wof:placetype":"venue"
},
  "geometry": {"coordinates":[-3.4813818932,40.3860816956],"type":"Point"}
}