{
  "type": "Feature",
  "properties": {
    "iso:country":"ES",
    "sg:address":"Eugenio Lopez, S/n",
    "sg:city":"Camari\u00f1as",
    "sg:orig_category":"Polideportivos",
    "sg:phone":"+34 981 73 73 09",
    "sg:postcode":"15123",
    "sg:province":"La Coru\u00f1a",
    "wof:name":"Concello De Camari\u00d1as",
    "wof:placetype":"venue"
},
  "geometry": {"coordinates":[-9.1825656891,43.1324501038],"type":"Point"}
}