{
  "type": "Feature",
  "properties": {
    "iso:country":"ES",
    "sg:address":"Calle de Fray Luis De Leon, 10",
    "sg:city":"Cuenca",
    "sg:orig_category":"Electrodom\u00c9sticos (al Por Menor)",
    "sg:phone":"+34 969 22 77 17",
    "sg:postcode":"16001",
    "sg:province":"Cuenca",
    "wof:name":"Aguilar Atienza Angel",
    "wof:placetype":"venue"
},
  "geometry": {"coordinates":[-2.1355543137,40.0748558044],"type":"Point"}
}