{
  "type": "Feature",
  "properties": {
    "addr:full":"Calle de Fernan Gonzalez, 46 Madrid Madrid 28009",
    "addr:housenumber":"46",
    "addr:postcode":"madrid;28009",
    "addr:street":"Calle De Fernan Gonzalez",
    "iso:country":"ES",
    "sg:address":"Calle de Fernan Gonzalez, 46",
    "sg:city":"Madrid",
    "sg:orig_category":"Platos Preparados Refrigerados (fabricaci\u00d3n, Al Por Mayor)",
    "sg:phone":"+34 915 74 23 16",
    "sg:postcode":"28009",
    "sg:province":"Madrid",
    "sg:website":"www.elrincondedona.com",
    "wof:name":"El Rincon De Dona S.l",
    "wof:placetype":"venue"
},
  "geometry": {"coordinates":[-3.6747069359,40.4197311401],"type":"Point"}
}