{
  "type": "Feature",
  "properties": {
    "addr:full":"Asomadillas, S/n Pozo Alcon Ja\u00e9n 23485",
    "addr:postcode":"23485",
    "addr:street":"Asomadillas S / N Pozo Alcon Jae\u0301N",
    "iso:country":"ES",
    "sg:address":"Asomadillas, S/n",
    "sg:city":"Pozo Alcon",
    "sg:orig_category":"Fabricaci\u00d3n De Muebles",
    "sg:phone":"+34 953 73 89 53",
    "sg:postcode":"23485",
    "sg:province":"Ja\u00e9n",
    "wof:name":"Muebles Jose Salvador S.l.",
    "wof:placetype":"venue"
},
  "geometry": {"coordinates":[-2.9331688881,37.700756073],"type":"Point"}
}