{
  "type": "Feature",
  "properties": {
    "addr:full":"San Breixo, S/n San Breixo La Coru\u00f1a 15200",
    "addr:housenumber":"s / n",
    "addr:postcode":"15200",
    "addr:street":"Corun\u0303A",
    "iso:country":"ES",
    "sg:address":"San Breixo, S/n",
    "sg:city":"San Breixo",
    "sg:orig_category":"Fabricaci\u00d3n De Muebles De Cocina",
    "sg:phone":"+34 981 82 16 44",
    "sg:postcode":"15200",
    "sg:province":"La Coru\u00f1a",
    "wof:name":"Carou Pico Jose Manuel",
    "wof:placetype":"venue"
},
  "geometry": {"coordinates":[-8.8883037567,42.788608551],"type":"Point"}
}