{
  "type": "Feature",
  "properties": {
    "iso:country":"ES",
    "sg:address":"Urb Carballos (os), S/n",
    "sg:city":"Cacheiras",
    "sg:orig_category":"Promotores Constructores",
    "sg:phone":"+34 981 80 77 85",
    "sg:postcode":"15883",
    "sg:province":"La Coru\u00f1a",
    "wof:name":"Consalpa Obras Y Proyectos S.l",
    "wof:placetype":"venue"
},
  "geometry": {"coordinates":[-8.5444011688,42.8382263184],"type":"Point"}
}