{
  "type": "Feature",
  "properties": {
    "addr:full":"Carrer de Volta De La Merce, 5 Palma Islas Baleares 07002",
    "addr:housenumber":"5",
    "addr:postcode":"07002",
    "addr:street":"Carrer De Volta De La Merce",
    "iso:country":"ES",
    "sg:address":"Carrer de Volta De La Merce, 5",
    "sg:city":"Palma",
    "sg:orig_category":"Abogados",
    "sg:phone":"+34 971 72 52 34",
    "sg:postcode":"07002",
    "sg:province":"Islas Baleares",
    "sg:website":"inmobiliariapou.com",
    "wof:name":"Pou Roca Antonio",
    "wof:placetype":"venue"
},
  "geometry": {"coordinates":[2.6545660496,39.572883606],"type":"Point"}
}