{
  "type": "Feature",
  "properties": {
    "iso:country":"ES",
    "sg:address":"Calle de Federico Baraibar, 2",
    "sg:city":"Vitoria-gasteiz",
    "sg:orig_category":"Supermercados Y Hipermercados",
    "sg:phone":"+34 945 28 34 94",
    "sg:postcode":"01003",
    "sg:province":"\u00c1lava",
    "wof:name":"Supermercado El Olivo De Luarca S.l.",
    "wof:placetype":"venue"
},
  "geometry": {"coordinates":[-2.663064003,42.8420143127],"type":"Point"}
}