{
  "type": "Feature",
  "properties": {
    "addr:full":"Calle de Angustias, 11 Valladolid Valladolid 47003",
    "addr:housenumber":"11",
    "addr:postcode":"47003",
    "addr:street":"Calle De Angustias",
    "iso:country":"ES",
    "sg:address":"Calle de Angustias, 11",
    "sg:city":"Valladolid",
    "sg:orig_category":"Molduras, Junquillos, Listones Y Molduras Perforadas",
    "sg:phone":"+34 983 25 14 97",
    "sg:postcode":"47003",
    "sg:province":"Valladolid",
    "wof:name":"Prieto Losada Maria Judith",
    "wof:placetype":"venue"
},
  "geometry": {"coordinates":[-4.7235641479,41.6550102234],"type":"Point"}
}