{
  "type": "Feature",
  "properties": {
    "iso:country":"ES",
    "sg:address":"Cmno Cementerio, 10",
    "sg:city":"Chiprana",
    "sg:orig_category":"Material Y Herramientas Agr\u00cdcolas",
    "sg:phone":"+34 976 63 73 96",
    "sg:postcode":"50792",
    "sg:province":"Zaragoza",
    "wof:name":"Talleres Ramia Jariod S.c.",
    "wof:placetype":"venue"
},
  "geometry": {"coordinates":[-0.126880005,41.2610397339],"type":"Point"}
}