{
  "type": "Feature",
  "properties": {
    "addr:full":"Calle de Ronda, 44 Rincon Victoria M\u00e1laga 29730",
    "addr:housenumber":"44",
    "addr:postcode":"29730",
    "addr:street":"Calle De Ronda;Ma\u0301Laga",
    "iso:country":"ES",
    "sg:address":"Calle de Ronda, 44",
    "sg:city":"Rincon Victoria",
    "sg:orig_category":"Plomeros",
    "sg:phone":"+34 952 97 10 48",
    "sg:postcode":"29730",
    "sg:province":"M\u00e1laga",
    "wof:name":"Infocusa S.l.",
    "wof:placetype":"venue"
},
  "geometry": {"coordinates":[-4.2824788094,36.71534729],"type":"Point"}
}