{
  "type": "Feature",
  "properties": {
    "iso:country":"ES",
    "sg:address":"Calle de Esca\u00d1uela, 6",
    "sg:city":"Jaen",
    "sg:orig_category":"Tapicer\u00cdas",
    "sg:phone":"+34 953 28 14 86",
    "sg:postcode":"23009",
    "sg:province":"Ja\u00e9n",
    "wof:name":"Cruz Ortu\u00f1o Juan Manuel",
    "wof:placetype":"venue"
},
  "geometry": {"coordinates":[-3.7872190475,37.7988510132],"type":"Point"}
}