{
  "type": "Feature",
  "properties": {
    "addr:full":"Calle de Tejares, 65 Albacete Albacete 02002",
    "addr:housenumber":"65",
    "addr:postcode":"02002",
    "addr:street":"Calle De Tejares",
    "iso:country":"ES",
    "sg:address":"Calle de Tejares, 65",
    "sg:city":"Albacete",
    "sg:orig_category":"Peluquer\u00cdas, Peluquer\u00cda Mixta",
    "sg:phone":"+34 967 51 12 82",
    "sg:postcode":"02002",
    "sg:province":"Albacete",
    "wof:name":"Olivares Podio Henar",
    "wof:placetype":"venue"
},
  "geometry": {"coordinates":[-1.8535200357,38.9886665344],"type":"Point"}
}