{
  "type": "Feature",
  "properties": {
    "iso:country":"ES",
    "sg:address":"Doctor Gortari, 3",
    "sg:city":"Iru\u00f1a",
    "sg:orig_category":"Empresas De Carpinter\u00cda",
    "sg:phone":"+34 948 14 67 90",
    "sg:postcode":"31012",
    "sg:province":"Navarra",
    "wof:name":"Carpinteria De Aluminio Govi S.l.",
    "wof:placetype":"venue"
},
  "geometry": {"coordinates":[-1.6683080196,42.8213348389],"type":"Point"}
}