{
  "type": "Feature",
  "properties": {
    "iso:country":"ES",
    "sg:address":"Avda Sada Y Sus Contornos, S/n",
    "sg:city":"Sada",
    "sg:orig_category":"Centros De Educaci\u00d3n Especial",
    "sg:phone":"+34 981 62 03 37",
    "sg:postcode":"15160",
    "sg:province":"La Coru\u00f1a",
    "wof:name":"Ayuntamiento De Sada-agrupacion Escolar De Sada Y Sus Contornos",
    "wof:placetype":"venue"
},
  "geometry": {"coordinates":[-8.2537469864,43.3552703857],"type":"Point"}
}