{
  "type": "Feature",
  "properties": {
    "addr:full":"Aitzezarra Kalea, 2 Usurbil Guip\u00f9zcoa 20170",
    "addr:housenumber":"2",
    "addr:postcode":"20170",
    "addr:street":"Aitzezarra Kalea;Guipu\u0300Zcoa",
    "iso:country":"ES",
    "sg:address":"Aitzezarra Kalea, 2",
    "sg:city":"Usurbil",
    "sg:orig_category":"Productos Qu\u00cdmicos (fabricaci\u00d3n, Al Por Mayor)",
    "sg:phone":"+34 943 36 19 43",
    "sg:postcode":"20170",
    "sg:province":"Guip\u00f9zcoa",
    "wof:name":"Igepak S. A.",
    "wof:placetype":"venue"
},
  "geometry": {"coordinates":[-2.0542910099,43.2714653015],"type":"Point"}
}