{
  "type": "Feature",
  "properties": {
    "iso:country":"ES",
    "sg:address":"Carrer de Sant Joan Bosco, 33",
    "sg:city":"S. Boi Llobregat",
    "sg:orig_category":"Asociaciones Y Clubs Deportivos",
    "sg:phone":"+34 936 30 72 87",
    "sg:postcode":"08830",
    "sg:province":"Barcelona",
    "wof:name":"Asociacion F.k.c.",
    "wof:placetype":"venue"
},
  "geometry": {"coordinates":[2.0448262691,41.3410758972],"type":"Point"}
}