{
  "type": "Feature",
  "properties": {
    "addr:full":"Cami Ermita, S/n Castelldans Lleida 25154",
    "addr:postcode":"25154",
    "addr:street":"Ermita S / N",
    "iso:country":"ES",
    "sg:address":"Cami Ermita, S/n",
    "sg:city":"Castelldans",
    "sg:orig_category":"Alimentaci\u00d3n General (al Por Menor)",
    "sg:phone":"+34 973 12 00 42",
    "sg:postcode":"25154",
    "sg:province":"Lleida",
    "wof:name":"Castell Fruit",
    "wof:placetype":"venue"
},
  "geometry": {"coordinates":[0.7663000226,41.4983634949],"type":"Point"}
}