{
  "type": "Feature",
  "properties": {
    "iso:country":"ES",
    "sg:address":"Calle de Tarazona, 20",
    "sg:city":"Zaragoza",
    "sg:orig_category":"Fabricaci\u00d3n De Ropa De Deportes",
    "sg:phone":"+34 976 33 90 07",
    "sg:postcode":"50017",
    "sg:province":"Zaragoza",
    "wof:name":"Iglesias Escudero Dolores Ester",
    "wof:placetype":"venue"
},
  "geometry": {"coordinates":[-0.9088050127,41.6505241394],"type":"Point"}
}