{
  "type": "Feature",
  "properties": {
    "addr:full":"Cami Arbeca (d'), 9 Mollerussa Lleida 25230",
    "addr:housenumber":"9",
    "addr:postcode":"25230",
    "addr:street":"Arbeca;'",
    "iso:country":"ES",
    "sg:address":"Cami Arbeca (d'), 9",
    "sg:city":"Mollerussa",
    "sg:orig_category":"Ropa Para Se\u00d1oras (al Por Menor)",
    "sg:phone":"+34 973 71 21 86",
    "sg:postcode":"25230",
    "sg:province":"Lleida",
    "sg:website":"www.cotocoto.com",
    "wof:name":"Blay Punt S. L.",
    "wof:placetype":"venue"
},
  "geometry": {"coordinates":[0.8950729966,41.624546051],"type":"Point"}
}