{
  "type": "Feature",
  "properties": {
    "iso:country":"ES",
    "sg:address":"Calle de Profesor Armas Fernandez, 19",
    "sg:city":"S. Sebastian Gomera",
    "sg:orig_category":"Inmobiliaria (agencias)",
    "sg:phone":"+34 922 14 18 19",
    "sg:postcode":"38800",
    "sg:province":"Santa Cruz De Tenerife",
    "wof:name":"Timanfaia Asesores S.l.",
    "wof:placetype":"venue"
},
  "geometry": {"coordinates":[-17.1144332886,28.0938968658],"type":"Point"}
}