{
  "type": "Feature",
  "properties": {
    "iso:country":"ES",
    "sg:address":"Calle de Tintoreros, 1",
    "sg:city":"Torredonjimeno",
    "sg:orig_category":"Partidos Pol\u00cdticos",
    "sg:phone":"+34 953 34 23 30",
    "sg:postcode":"23650",
    "sg:province":"Ja\u00e9n",
    "wof:name":"Partido Socialista Obrero Espa\u00f1ol",
    "wof:placetype":"venue"
},
  "geometry": {"coordinates":[-3.9584789276,37.7638473511],"type":"Point"}
}