{
  "type": "Feature",
  "properties": {
    "addr:full":"Calle de Honduras, S/n Coslada Madrid 28820",
    "addr:housenumber":"/ n",
    "addr:postcode":"28820",
    "addr:street":"Calle De Honduras S",
    "iso:country":"ES",
    "sg:address":"Calle de Honduras, S/n",
    "sg:city":"Coslada",
    "sg:orig_category":"Perfumer\u00cda (al Por Menor)",
    "sg:phone":"+34 916 74 16 19",
    "sg:postcode":"28820",
    "sg:province":"Madrid",
    "sg:website":"www.juteco.es",
    "wof:name":"Geblanc S.a.",
    "wof:placetype":"venue"
},
  "geometry": {"coordinates":[-3.5450210571,40.4245033264],"type":"Point"}
}