{
  "type": "Feature",
  "properties": {
    "addr:full":"Avda Ejercito, 31 Coru\u00d1a La Coru\u00f1a 15006",
    "addr:housenumber":"31",
    "addr:postcode":"15006",
    "addr:street":"Avda Ejercito;La Corun\u0303A",
    "iso:country":"ES",
    "sg:address":"Avda Ejercito, 31",
    "sg:city":"Coru\u00d1a",
    "sg:orig_category":"Asesor\u00cdas Y Estudios Financieros",
    "sg:phone":"+34 981 28 68 46",
    "sg:postcode":"15006",
    "sg:province":"La Coru\u00f1a",
    "wof:name":"Eduardo Sanchez-tembleque E Hijos S.l.",
    "wof:placetype":"venue"
},
  "geometry": {"coordinates":[-8.3903913498,43.3530235291],"type":"Point"}
}