{
  "type": "Feature",
  "properties": {
    "addr:full":"Barr Monte Bolado, 3 Monte Cantabria 39012",
    "addr:housenumber":"3",
    "addr:postcode":"39012",
    "iso:country":"ES",
    "sg:address":"Barr Monte Bolado, 3",
    "sg:city":"Monte",
    "sg:orig_category":"Iglesia Cat\u00d3lica",
    "sg:phone":"+34 942 34 05 20",
    "sg:postcode":"39012",
    "sg:province":"Cantabria",
    "wof:name":"Parroquia De Monte",
    "wof:placetype":"venue"
},
  "geometry": {"coordinates":[-3.8604888916,43.4665527344],"type":"Point"}
}