{
  "type": "Feature",
  "properties": {
    "iso:country":"ES",
    "sg:address":"Avda Cordoba, 8",
    "sg:city":"Yecla",
    "sg:orig_category":"Frutas, Legumbres Frescas Y Tempranas (al Por Menor)",
    "sg:phone":"+34 968 75 19 24",
    "sg:postcode":"30510",
    "sg:province":"Murcia",
    "wof:name":"Muoz Ortega Jose",
    "wof:placetype":"venue"
},
  "geometry": {"coordinates":[-1.1182789803,38.6164207458],"type":"Point"}
}