{
  "type": "Feature",
  "properties": {
    "iso:country":"ES",
    "sg:address":"Calle de Mira El Rio Baja, 20",
    "sg:city":"Madrid",
    "sg:orig_category":"Comisarios",
    "sg:phone":"+34 915 30 37 96",
    "sg:postcode":"28005",
    "sg:province":"Madrid",
    "wof:name":"Garcia San Benito Vicente",
    "wof:placetype":"venue"
},
  "geometry": {"coordinates":[-3.7087728977,40.4069824219],"type":"Point"}
}