{
  "type": "Feature",
  "properties": {
    "iso:country":"ES",
    "sg:address":"Calle de Severo Ochoa, 2",
    "sg:city":"Arriondas",
    "sg:orig_category":"Transportes Por V\u00cdas Navegables",
    "sg:phone":"+34 985 84 00 12",
    "sg:postcode":"33540",
    "sg:province":"Asturias",
    "wof:name":"Tora\u00f1o Gonzalez Jose Miguel",
    "wof:placetype":"venue"
},
  "geometry": {"coordinates":[-5.1872639656,43.3894004822],"type":"Point"}
}