{
  "type": "Feature",
  "properties": {
    "iso:country":"ES",
    "sg:address":"Carrer de Escultor Rocamora, 1",
    "sg:city":"Reus",
    "sg:orig_category":"Farmacias",
    "sg:phone":"+34 977 75 73 01",
    "sg:postcode":"43204",
    "sg:province":"Tarragona",
    "wof:name":"Peidro Jorda Maria Victoria",
    "wof:placetype":"venue"
},
  "geometry": {"coordinates":[1.1111320257,41.1500549316],"type":"Point"}
}