{
  "type": "Feature",
  "properties": {
    "iso:country":"ES",
    "sg:address":"Plaz Fonsagrada, 8",
    "sg:city":"Madrid",
    "sg:orig_category":"Servicios Diversos",
    "sg:phone":"+34 917 40 54 86",
    "sg:postcode":"28029",
    "sg:province":"Madrid",
    "wof:name":"Desinsectaciones La Estrella S.l.",
    "wof:placetype":"venue"
},
  "geometry": {"coordinates":[-3.7075920105,40.4777374268],"type":"Point"}
}