{
  "type": "Feature",
  "properties": {
    "addr:full":"Calle de Don Quijote, 103 Pto. Rosario Las Palmas 35600",
    "addr:housenumber":"103",
    "addr:postcode":"35600",
    "addr:street":"Calle De Don;Pto. Rosario Las",
    "iso:country":"ES",
    "sg:address":"Calle de Don Quijote, 103",
    "sg:city":"Pto. Rosario",
    "sg:orig_category":"Fabricaci\u00d3n, Venta, Instalaci\u00d3n De R\u00d3tulos, De R\u00d3tulos Luminosos",
    "sg:phone":"+34 928 53 14 03",
    "sg:postcode":"35600",
    "sg:province":"Las Palmas",
    "wof:name":"Garcia Morera Maria Jose",
    "wof:placetype":"venue"
},
  "geometry": {"coordinates":[-13.8690004349,28.4998950958],"type":"Point"}
}