{
  "type": "Feature",
  "properties": {
    "addr:full":"Calle de Porcuna, 2 Jaen Ja\u00e9n 23006",
    "addr:housenumber":"2;jae\u0301n",
    "addr:postcode":"23006",
    "addr:street":"Calle De Porcuna",
    "iso:country":"ES",
    "sg:address":"Calle de Porcuna, 2",
    "sg:city":"Jaen",
    "sg:orig_category":"Alquiler De V\u00cddeo",
    "sg:phone":"+34 953 22 34 24",
    "sg:postcode":"23006",
    "sg:province":"Ja\u00e9n",
    "wof:name":"Garrido Perez Fabian Gregorio",
    "wof:placetype":"venue"
},
  "geometry": {"coordinates":[-3.8022561073,37.7809524536],"type":"Point"}
}