{
  "type": "Feature",
  "properties": {
    "addr:full":"Carrer de Occident, 37 Hospitalet Llobregat Barcelona 08904",
    "addr:housenumber":"37",
    "addr:postcode":"08904",
    "addr:street":"Carrer De Occident",
    "iso:country":"ES",
    "sg:address":"Carrer de Occident, 37",
    "sg:city":"Hospitalet Llobregat",
    "sg:orig_category":"Ense\u00d1anza, Formaci\u00d3n Profesional: Aprendizaje",
    "sg:phone":"+34 934 40 90 83",
    "sg:postcode":"08904",
    "sg:province":"Barcelona",
    "sg:website":"www.sabater-tobella.com",
    "wof:name":"Sabater Tobella Analisis S. A.",
    "wof:placetype":"venue"
},
  "geometry": {"coordinates":[2.1187360287,41.3743858337],"type":"Point"}
}