{
  "type": "Feature",
  "properties": {
    "iso:country":"ES",
    "sg:address":"Calle de Zarautz, 64",
    "sg:city":"Donostia-san Sebastian",
    "sg:orig_category":"Peluquer\u00cdas, Peluquer\u00cda Mixta",
    "sg:phone":"+34 943 21 95 75",
    "sg:postcode":"20018",
    "sg:province":"Guip\u00f9zcoa",
    "wof:name":"Aristeguieta Gutierrez Patricia",
    "wof:placetype":"venue"
},
  "geometry": {"coordinates":[-2.0070214272,43.3074760437],"type":"Point"}
}