{
  "type": "Feature",
  "properties": {
    "addr:full":"Calle de Diputacion, S/n Ermua Vizcaya 48260",
    "addr:housenumber":"s",
    "addr:postcode":"48260",
    "addr:street":"Calle De Diputacion;/ N",
    "iso:country":"ES",
    "sg:address":"Calle de Diputacion, S/n",
    "sg:city":"Ermua",
    "sg:orig_category":"Centros Empresariales",
    "sg:phone":"+34 943 17 64 17",
    "sg:postcode":"48260",
    "sg:province":"Vizcaya",
    "wof:name":"Asociacion De Comerciantes Mercado Municipal De Ermua",
    "wof:placetype":"venue"
},
  "geometry": {"coordinates":[-2.5082027912,43.1876335144],"type":"Point"}
}