{
  "type": "Feature",
  "properties": {
    "addr:full":"Calle de San Sebastian, 31 Alfafar Valencia 46910",
    "addr:housenumber":"31",
    "addr:postcode":"46910",
    "addr:street":"Calle De San Sebastian",
    "iso:country":"ES",
    "sg:address":"Calle de San Sebastian, 31",
    "sg:city":"Alfafar",
    "sg:orig_category":"Cajas De Ahorro",
    "sg:phone":"+34 963 75 04 97",
    "sg:postcode":"46910",
    "sg:province":"Valencia",
    "sg:website":"www.cam.es",
    "wof:name":"Caja De Ahorros Del Mediterraneo",
    "wof:placetype":"venue"
},
  "geometry": {"coordinates":[-0.3898769915,39.4225921631],"type":"Point"}
}