{
  "type": "Feature",
  "properties": {
    "addr:full":"Ctra. Orellana, S/n Campanario Badajoz 06460",
    "addr:housenumber":"s / n",
    "addr:postcode":"06460",
    "addr:street":"Ctra. Orellana",
    "iso:country":"ES",
    "sg:address":"Ctra. Orellana, S/n",
    "sg:city":"Campanario",
    "sg:orig_category":"Agricultores, Agricultores",
    "sg:phone":"+34 924 14 70 99",
    "sg:postcode":"06460",
    "sg:province":"Badajoz",
    "wof:name":"Guadalefra Comunidad De Bienes",
    "wof:placetype":"venue"
},
  "geometry": {"coordinates":[-5.6167840958,38.8672065735],"type":"Point"}
}