{
  "type": "Feature",
  "properties": {
    "addr:full":"Calle de Peru, 7 Valladolid Valladolid 47004",
    "addr:housenumber":"7",
    "addr:postcode":"47004",
    "addr:street":"Calle De Peru",
    "iso:country":"ES",
    "sg:address":"Calle de Peru, 7",
    "sg:city":"Valladolid",
    "sg:orig_category":"Arquitectos",
    "sg:phone":"+34 983 20 04 08",
    "sg:postcode":"47004",
    "sg:province":"Valladolid",
    "wof:name":"Puente Aparicio Pablo",
    "wof:placetype":"venue"
},
  "geometry": {"coordinates":[-4.727063179,41.6473731995],"type":"Point"}
}