{
  "type": "Feature",
  "properties": {
    "addr:full":"Del Carmen, 22 Pozuelo Calatrava Ciudad Real 13179",
    "addr:housenumber":"22",
    "addr:postcode":"calatrava;13179",
    "addr:street":"Del Carmen",
    "iso:country":"ES",
    "sg:address":"Del Carmen, 22",
    "sg:city":"Pozuelo Calatrava",
    "sg:orig_category":"Comerciantes Al Por Mayor De Vinos, Licores Y Alcoholes",
    "sg:phone":"+34 926 84 03 40",
    "sg:postcode":"13179",
    "sg:province":"Ciudad Real",
    "wof:name":"Bodegas Del Virgen Del Carmen S.l.",
    "wof:placetype":"venue"
},
  "geometry": {"coordinates":[-3.8354260921,38.9131889343],"type":"Point"}
}