{
  "type": "Feature",
  "properties": {
    "addr:full":"Plaz Santa Maria, 1 Tolosa Guip\u00f9zcoa 20400",
    "addr:postcode":"20400",
    "addr:street":"Santa Maria;Guipu\u0300Zcoa",
    "iso:country":"ES",
    "sg:address":"Plaz Santa Maria, 1",
    "sg:city":"Tolosa",
    "sg:orig_category":"Peluquer\u00cdas, Peluquer\u00cda Mixta",
    "sg:phone":"+34 943 67 22 44",
    "sg:postcode":"20400",
    "sg:province":"Guip\u00f9zcoa",
    "wof:name":"Aitor Odriozola Otamendi",
    "wof:placetype":"venue"
},
  "geometry": {"coordinates":[-2.071213007,43.1386299133],"type":"Point"}
}