{
  "type": "Feature",
  "properties": {
    "addr:full":"Av Diagonal, 511 Barcelona Barcelona 08029",
    "addr:housenumber":"511",
    "addr:postcode":"08029",
    "addr:street":"Av Diagonal",
    "iso:country":"ES",
    "sg:address":"Av Diagonal, 511",
    "sg:city":"Barcelona",
    "sg:orig_category":"M\u00c9dicos: Cardiolog\u00cda Y Afecciones Cardiovasculares",
    "sg:phone":"+34 934 39 21 00",
    "sg:postcode":"08029",
    "sg:province":"Barcelona",
    "wof:name":"Lopez Vila Juan",
    "wof:placetype":"venue"
},
  "geometry": {"coordinates":[2.1408860683,41.391368866],"type":"Point"}
}