{
  "type": "Feature",
  "properties": {
    "addr:full":"Carrer de Sant Pere, 26 Llagostera Girona 17240",
    "addr:housenumber":"26",
    "addr:postcode":"17240",
    "addr:street":"Carrer De Sant Pere",
    "iso:country":"ES",
    "sg:address":"Carrer de Sant Pere, 26",
    "sg:city":"Llagostera",
    "sg:orig_category":"Negocio De Materiales De Construcci\u00d3n",
    "sg:phone":"+34 972 80 53 28",
    "sg:postcode":"17240",
    "sg:province":"Girona",
    "wof:name":"Materiales A.sanchez S.l",
    "wof:placetype":"venue"
},
  "geometry": {"coordinates":[2.8938629627,41.8278503418],"type":"Point"}
}