{
  "type": "Feature",
  "properties": {
    "addr:full":"Carrer de Mas Pujol, 19 Barcelona Barcelona 08032",
    "addr:housenumber":"19",
    "addr:postcode":"08032",
    "addr:street":"Carrer De Mas Pujol",
    "iso:country":"ES",
    "sg:address":"Carrer de Mas Pujol, 19",
    "sg:city":"Barcelona",
    "sg:orig_category":"M\u00c9dicos: Ginecolog\u00cda Y Obstetricia",
    "sg:phone":"+34 934 29 74 24",
    "sg:postcode":"08032",
    "sg:province":"Barcelona",
    "wof:name":"Barber Gonzalez Jesus",
    "wof:placetype":"venue"
},
  "geometry": {"coordinates":[2.1644940376,41.4256591797],"type":"Point"}
}