{
  "type": "Feature",
  "properties": {
    "iso:country":"ES",
    "sg:address":"Calle de Linares, 13",
    "sg:city":"Valencia",
    "sg:orig_category":"Producci\u00d3n, Venta De Productos De Agricultura Biol\u00d3gica",
    "sg:phone":"+34 963 85 70 72",
    "sg:postcode":"46018",
    "sg:province":"Valencia",
    "wof:name":"Anguix Garrido Antonio",
    "wof:placetype":"venue"
},
  "geometry": {"coordinates":[-0.3935106099,39.4686431885],"type":"Point"}
}