{
  "type": "Feature",
  "properties": {
    "iso:country":"ES",
    "sg:address":"Calle de San Antonio, 38",
    "sg:city":"Santiago Ribera",
    "sg:orig_category":"Mec\u00c1nica Y Herramientas De Precisi\u00d3n",
    "sg:phone":"+34 968 57 09 59",
    "sg:postcode":"30720",
    "sg:province":"Murcia",
    "wof:name":"Topomur S.l.",
    "wof:placetype":"venue"
},
  "geometry": {"coordinates":[-0.8072080016,37.7995223999],"type":"Point"}
}