{
  "type": "Feature",
  "properties": {
    "iso:country":"ES",
    "sg:address":"Calle de Carmen, 16",
    "sg:city":"Tarancon",
    "sg:orig_category":"Fisioterapia",
    "sg:phone":"+34 969 32 43 88",
    "sg:postcode":"16400",
    "sg:province":"Cuenca",
    "wof:name":"De La Ossa Ortiz Maria Dolores",
    "wof:placetype":"venue"
},
  "geometry": {"coordinates":[-3.0114982128,40.0089492798],"type":"Point"}
}