{
  "type": "Feature",
  "properties": {
    "addr:full":"B. Perez Galdos, 1 Estepona M\u00e1laga 29680",
    "addr:housenumber":"1",
    "addr:postcode":"29680",
    "addr:street":"Perez Galdos",
    "iso:country":"ES",
    "sg:address":"B. Perez Galdos, 1",
    "sg:city":"Estepona",
    "sg:orig_category":"Asilos De Ancianos. Centros Privados",
    "sg:phone":"+34 952 79 53 01",
    "sg:postcode":"29680",
    "sg:province":"M\u00e1laga",
    "wof:name":"Residencia De Ancianos Virgen Del Carmen",
    "wof:placetype":"venue"
},
  "geometry": {"coordinates":[-5.1538939476,36.4243583679],"type":"Point"}
}