{
  "type": "Feature",
  "properties": {
    "addr:full":"Calle de San Blas, 3 Tribaldos Cuenca 16451",
    "addr:housenumber":"3",
    "addr:postcode":"16451",
    "addr:street":"Calle De San Blas",
    "iso:country":"ES",
    "sg:address":"Calle de San Blas, 3",
    "sg:city":"Tribaldos",
    "sg:orig_category":"Carnicer\u00cdas, Carnicer\u00cdas",
    "sg:phone":"+34 969 13 50 13",
    "sg:postcode":"16451",
    "sg:province":"Cuenca",
    "wof:name":"Ortega Albares Placido",
    "wof:placetype":"venue"
},
  "geometry": {"coordinates":[-2.8995580673,39.9735832214],"type":"Point"}
}