{
  "type": "Feature",
  "properties": {
    "addr:full":"Calle de Gil De Santiva\u00d1es, 6 Madrid Madrid 28001",
    "addr:housenumber":"6",
    "addr:postcode":"28001",
    "addr:street":"Calle De Gil De Santivan\u0303Es",
    "iso:country":"ES",
    "sg:address":"Calle de Gil De Santiva\u00d1es, 6",
    "sg:city":"Madrid",
    "sg:orig_category":"Agencias De Prensa E Informaci\u00d3n",
    "sg:phone":"+34 915 75 87 32",
    "sg:postcode":"28001",
    "sg:province":"Madrid",
    "sg:website":"www.foemo.com",
    "wof:name":"Berbes Asociados S.l.",
    "wof:placetype":"venue"
},
  "geometry": {"coordinates":[-3.689002037,40.4221763611],"type":"Point"}
}