{
  "type": "Feature",
  "properties": {
    "iso:country":"ES",
    "sg:address":"Monte Perdido, 1",
    "sg:city":"Ntra Sra Del Carmen",
    "sg:orig_category":"Materiales De Aislamiento T\u00c9rmico Y Ac\u00dastico",
    "sg:phone":"+34 914 39 97 34",
    "sg:postcode":"28909",
    "sg:province":"Madrid",
    "sg:website":"www.rockwool.es",
    "wof:name":"Rockwool Peninsular S.a.",
    "wof:placetype":"venue"
},
  "geometry": {"coordinates":[-3.6553490162,40.3250961304],"type":"Point"}
}