{
  "type": "Feature",
  "properties": {
    "addr:full":"Carr Seminari, 10 Guissona Lleida 25210",
    "addr:housenumber":"10",
    "addr:postcode":"25210",
    "addr:street":"Carr Seminari",
    "iso:country":"ES",
    "sg:address":"Carr Seminari, 10",
    "sg:city":"Guissona",
    "sg:orig_category":"Promotores Constructores",
    "sg:phone":"+34 973 55 05 11",
    "sg:postcode":"25210",
    "sg:province":"Lleida",
    "wof:name":"Construccions Tresents Pla S.l.",
    "wof:placetype":"venue"
},
  "geometry": {"coordinates":[1.2887649536,41.7873535156],"type":"Point"}
}