{
  "type": "Feature",
  "properties": {
    "iso:country":"ES",
    "sg:address":"Calle de Clara Del Rey, 52",
    "sg:city":"Madrid",
    "sg:orig_category":"Molduras, Junquillos, Listones Y Molduras Perforadas",
    "sg:phone":"+34 915 19 56 08",
    "sg:postcode":"28002",
    "sg:province":"Madrid",
    "wof:name":"Reda  Khaled",
    "wof:placetype":"venue"
},
  "geometry": {"coordinates":[-3.6681261063,40.4460296631],"type":"Point"}
}