{
  "type": "Feature",
  "properties": {
    "addr:full":"Pla\u00c7 Pas D'arro, 2 Vielha Lleida 25530",
    "addr:housenumber":"2",
    "addr:postcode":"25530",
    "addr:street":"D'Arro",
    "iso:country":"ES",
    "sg:address":"Pla\u00c7 Pas D'arro, 2",
    "sg:city":"Vielha",
    "sg:orig_category":"Artes Gr\u00c1ficas, Artes Pl\u00c1sticas (curso)",
    "sg:phone":"+34 973 64 08 85",
    "sg:postcode":"25530",
    "sg:province":"Lleida",
    "wof:name":"Papereria Aran Vidal S.l.",
    "wof:placetype":"venue"
},
  "geometry": {"coordinates":[0.7975659966,42.7010536194],"type":"Point"}
}