{
  "type": "Feature",
  "properties": {
    "addr:full":"Carr De Maians, 57 Ontinyent Valencia 46870",
    "addr:housenumber":"57",
    "addr:postcode":"46870",
    "addr:street":"Carr De Maians",
    "iso:country":"ES",
    "sg:address":"Carr De Maians, 57",
    "sg:city":"Ontinyent",
    "sg:orig_category":"Electrodom\u00c9sticos (al Por Menor)",
    "sg:phone":"+34 962 38 15 01",
    "sg:postcode":"46870",
    "sg:province":"Valencia",
    "wof:name":"Soler Onteniente S.l.",
    "wof:placetype":"venue"
},
  "geometry": {"coordinates":[-0.6030989885,38.8258895874],"type":"Point"}
}