{
  "type": "Feature",
  "properties": {
    "addr:full":"Calle de Saiz De Otero, 14 Zaragoza Zaragoza 50018",
    "addr:housenumber":"14",
    "addr:postcode":"50018",
    "addr:street":"Calle De Saiz De Otero",
    "iso:country":"ES",
    "sg:address":"Calle de Saiz De Otero, 14",
    "sg:city":"Zaragoza",
    "sg:classifiers":[
        {
            "category":"Professional",
            "subcategory":"Research",
            "type":"Services"
        }
    ],
    "sg:phone":"+34 976 52 40 08",
    "sg:postcode":"50018",
    "sg:province":"Zaragoza",
    "sg:tags":[
        "mercado",
        "de",
        "estudios"
    ],
    "wof:name":"Arago Marketing S.l.",
    "wof:placetype":"venue"
},
  "geometry": {"coordinates":[-0.8926548958,41.669883728],"type":"Point"}
}