{
  "type": "Feature",
  "properties": {
    "addr:full":"Avda Corredera, 25 Hinojosa Del Duque C\u00f3rdoba 14270",
    "addr:housenumber":"25",
    "addr:postcode":"14270",
    "addr:street":"Avda Corredera;Co\u0301Rdoba",
    "iso:country":"ES",
    "sg:address":"Avda Corredera, 25",
    "sg:city":"Hinojosa Del Duque",
    "sg:orig_category":"Supermercados Y Hipermercados",
    "sg:phone":"+34 957 14 00 27",
    "sg:postcode":"14270",
    "sg:province":"C\u00f3rdoba",
    "wof:name":"Autoservicio Lopez Reyes S.l.",
    "wof:placetype":"venue"
},
  "geometry": {"coordinates":[-5.1463508606,38.4993095398],"type":"Point"}
}