{
  "type": "Feature",
  "properties": {
    "addr:full":"Calle de Pedrero, 52 Tomelloso Ciudad Real 13700",
    "addr:housenumber":"52",
    "addr:postcode":"13700",
    "addr:street":"Calle De Pedrero",
    "iso:country":"ES",
    "sg:address":"Calle de Pedrero, 52",
    "sg:city":"Tomelloso",
    "sg:orig_category":"Delineantes",
    "sg:phone":"+34 926 50 62 69",
    "sg:postcode":"13700",
    "sg:province":"Ciudad Real",
    "wof:name":"Papirus Infinitus S.l.u.",
    "wof:placetype":"venue"
},
  "geometry": {"coordinates":[-3.0279090405,39.1523513794],"type":"Point"}
}