{
  "type": "Feature",
  "properties": {
    "iso:country":"ES",
    "sg:address":"Calle de Reyes Catolicos, 5",
    "sg:city":"Ca\u00e7ete De Las Torres",
    "sg:orig_category":"Promotores Constructores",
    "sg:phone":"+34 957 18 31 36",
    "sg:postcode":"14660",
    "sg:province":"C\u00f3rdoba",
    "wof:name":"Blanca Delgado Simon",
    "wof:placetype":"venue"
},
  "geometry": {"coordinates":[-4.3186120987,37.8691596985],"type":"Point"}
}