{
  "type": "Feature",
  "properties": {
    "iso:country":"ES",
    "sg:address":"Calle de San Antonio, 68",
    "sg:city":"Totana",
    "sg:orig_category":"Panader\u00cdas, Panader\u00cdas",
    "sg:phone":"+34 968 42 22 43",
    "sg:postcode":"30850",
    "sg:province":"Murcia",
    "wof:name":"Canovas Martinez Celestino",
    "wof:placetype":"venue"
},
  "geometry": {"coordinates":[-1.4984140396,37.7735137939],"type":"Point"}
}