{
  "type": "Feature",
  "properties": {
    "iso:country":"ES",
    "sg:address":"Carr Sant Sebastia, 39",
    "sg:city":"Vilaju\u00efga",
    "sg:orig_category":"Administraciones Regionales, Departamentales Y Locales",
    "sg:phone":"+34 972 53 00 05",
    "sg:postcode":"17493",
    "sg:province":"Girona",
    "wof:name":"Ajuntament De Vilajuiga",
    "wof:placetype":"venue"
},
  "geometry": {"coordinates":[3.0944979191,42.3277549744],"type":"Point"}
}