{
  "type": "Feature",
  "properties": {
    "addr:full":"Ctra. Orense, S/n Benavente Zamora 49600",
    "addr:housenumber":"s / n",
    "addr:postcode":"49600",
    "addr:street":"Ctra. Orense",
    "iso:country":"ES",
    "sg:address":"Ctra. Orense, S/n",
    "sg:city":"Benavente",
    "sg:orig_category":"Aguas (distribuci\u00d3n, Servicios)",
    "sg:phone":"+34 980 63 10 09",
    "sg:postcode":"49600",
    "sg:province":"Zamora",
    "wof:name":"Aquagest",
    "wof:placetype":"venue"
},
  "geometry": {"coordinates":[-5.6817750931,41.9934997559],"type":"Point"}
}