{
  "type": "Feature",
  "properties": {
    "iso:country":"ES",
    "sg:address":"Carr Can Planes, 18",
    "sg:city":"Angles",
    "sg:orig_category":"Electricidad Veh\u00cdculo",
    "sg:phone":"+34 972 42 00 32",
    "sg:postcode":"17160",
    "sg:province":"Girona",
    "wof:name":"Pla Amat Jose",
    "wof:placetype":"venue"
},
  "geometry": {"coordinates":[2.6347820759,41.9582252502],"type":"Point"}
}