{
  "type": "Feature",
  "properties": {
    "addr:full":"Ctra Rubi, 135 Terrassa Barcelona 08228",
    "addr:housenumber":"135",
    "addr:postcode":"08228",
    "addr:street":"Ctra Rubi",
    "iso:country":"ES",
    "sg:address":"Ctra Rubi, 135",
    "sg:city":"Terrassa",
    "sg:orig_category":"Carnicer\u00cdas, Carnicer\u00cdas",
    "sg:phone":"+34 937 83 53 78",
    "sg:postcode":"08228",
    "sg:province":"Barcelona",
    "wof:name":"Mendez Alcaraz Agustina",
    "wof:placetype":"venue"
},
  "geometry": {"coordinates":[2.0352640152,41.5329399109],"type":"Point"}
}