{
  "type": "Feature",
  "properties": {
    "addr:full":"Calle de Cidamon, 3 Madrid Madrid 28043",
    "addr:housenumber":"3",
    "addr:postcode":"28043",
    "addr:street":"Calle De Cidamon",
    "iso:country":"ES",
    "sg:address":"Calle de Cidamon, 3",
    "sg:city":"Madrid",
    "sg:orig_category":"Molduras, Junquillos, Listones Y Molduras Perforadas",
    "sg:phone":"+34 915 19 35 82",
    "sg:postcode":"28043",
    "sg:province":"Madrid",
    "wof:name":"Torrejon Olivares Luis",
    "wof:placetype":"venue"
},
  "geometry": {"coordinates":[-3.658190012,40.4505386353],"type":"Point"}
}