{
  "type": "Feature",
  "properties": {
    "addr:full":"Calle de Doctor Benitez, 3 Jerez De Los Caballeros Badajoz 06380",
    "addr:housenumber":"3",
    "addr:postcode":"06380",
    "addr:street":"Calle De Doctor Benitez",
    "iso:country":"ES",
    "sg:address":"Calle de Doctor Benitez, 3",
    "sg:city":"Jerez De Los Caballeros",
    "sg:orig_category":"Bisuter\u00cda, Joyer\u00cda, Relojer\u00cda (al Por Menor)",
    "sg:phone":"+34 924 73 17 65",
    "sg:postcode":"06380",
    "sg:province":"Badajoz",
    "wof:name":"Zahinos Y Lopez S.l.",
    "wof:placetype":"venue"
},
  "geometry": {"coordinates":[-6.7717804909,38.3198661804],"type":"Point"}
}