{
  "type": "Feature",
  "properties": {
    "iso:country":"ES",
    "sg:address":"Calle de Antonio Gaudi, S/n",
    "sg:city":"Palacios Y Villafranca",
    "sg:orig_category":"Agencias Y Agentes Comerciales, Representantes",
    "sg:phone":"+34 955 81 17 43",
    "sg:postcode":"41720",
    "sg:province":"Sevilla",
    "wof:name":"Campa\u00f1a Coronil Francisco Javier",
    "wof:placetype":"venue"
},
  "geometry": {"coordinates":[-5.9234213829,37.167427063],"type":"Point"}
}