{
  "type": "Feature",
  "properties": {
    "iso:country":"ES",
    "sg:address":"Calle de Antonio Machado, 2",
    "sg:city":"Castillo Locubin",
    "sg:orig_category":"Frutas, Legumbres Frescas Y Tempranas (al Por Menor)",
    "sg:phone":"+34 953 59 01 07",
    "sg:postcode":"23670",
    "sg:province":"Ja\u00e9n",
    "wof:name":"Contreras Siles Antonio",
    "wof:placetype":"venue"
},
  "geometry": {"coordinates":[-3.9416873455,37.5284957886],"type":"Point"}
}