{
  "type": "Feature",
  "properties": {
    "iso:country":"ES",
    "sg:address":"Carr Templers, 10",
    "sg:city":"Lleida",
    "sg:orig_category":"Reposter\u00cdas",
    "sg:phone":"+34 973 26 04 60",
    "sg:postcode":"25002",
    "sg:province":"Lleida",
    "wof:name":"Bon Blat S.l.",
    "wof:placetype":"venue"
},
  "geometry": {"coordinates":[0.6167050004,41.6110496521],"type":"Point"}
}