{
  "type": "Feature",
  "properties": {
    "addr:full":"Avda Jose Aguado, 9 Le\u00f3n Le\u00f3n 24005",
    "addr:housenumber":"9",
    "addr:postcode":"24005",
    "addr:street":"Avda Jose Aguado;Leo\u0301N",
    "iso:country":"ES",
    "sg:address":"Avda Jose Aguado, 9",
    "sg:city":"Le\u00f3n",
    "sg:orig_category":"Art\u00cdculos De Decoraci\u00d3n",
    "sg:phone":"+34 987 20 41 46",
    "sg:postcode":"24005",
    "sg:province":"Le\u00f3n",
    "wof:name":"Asturlak S. L.",
    "wof:placetype":"venue"
},
  "geometry": {"coordinates":[-5.5653386116,42.5908584595],"type":"Point"}
}