{
  "type": "Feature",
  "properties": {
    "iso:country":"ES",
    "sg:address":"La Pesquera, S/n",
    "sg:city":"Laredo",
    "sg:orig_category":"Transporte En General",
    "sg:phone":"+34 942 61 08 76",
    "sg:postcode":"39770",
    "sg:province":"Cantabria",
    "wof:name":"Rios Cano Fernando De Los",
    "wof:placetype":"venue"
},
  "geometry": {"coordinates":[-3.4341549873,43.4056358337],"type":"Point"}
}