{
  "type": "Feature",
  "properties": {
    "iso:country":"ES",
    "sg:address":"Calle de Jose Ortega Y Gasset, 85",
    "sg:city":"Madrid",
    "sg:orig_category":"Carnicer\u00cdas, Carnicer\u00cdas",
    "sg:phone":"+34 914 02 03 63",
    "sg:postcode":"28006",
    "sg:province":"Madrid",
    "wof:name":"Gold Gourmet S.l.l.",
    "wof:placetype":"venue"
},
  "geometry": {"coordinates":[-3.6714799404,40.4298439026],"type":"Point"}
}