{
  "type": "Feature",
  "properties": {
    "addr:full":"Carr Major, 32 Jafre Girona 17143",
    "addr:housenumber":"32",
    "addr:postcode":"17143",
    "addr:street":"Carr Major",
    "iso:country":"ES",
    "sg:address":"Carr Major, 32",
    "sg:city":"Jafre",
    "sg:orig_category":"Semiller\u00cdas",
    "sg:phone":"+34 972 76 80 86",
    "sg:postcode":"17143",
    "sg:province":"Girona",
    "wof:name":"Soljardi S.l.",
    "wof:placetype":"venue"
},
  "geometry": {"coordinates":[3.0105700493,42.0720214844],"type":"Point"}
}