{
  "type": "Feature",
  "properties": {
    "iso:country":"ES",
    "sg:address":"Iru Kantoia Kalea, 4",
    "sg:city":"Usurbil",
    "sg:orig_category":"Acero: Productos Sider\u00dargicos Y Transformados (fabricaci\u00d3n, Negocio)",
    "sg:phone":"+34 943 36 66 99",
    "sg:postcode":"20170",
    "sg:province":"Guip\u00f9zcoa",
    "wof:name":"Industrias Aramendi S.l.",
    "wof:placetype":"venue"
},
  "geometry": {"coordinates":[-2.0539140701,43.2733459473],"type":"Point"}
}