{
  "type": "Feature",
  "properties": {
    "addr:full":"Calle de Berzocana, 18 Merida Badajoz 06800",
    "addr:housenumber":"18",
    "addr:postcode":"06800",
    "addr:street":"Calle De Berzocana",
    "iso:country":"ES",
    "sg:address":"Calle de Berzocana, 18",
    "sg:city":"Merida",
    "sg:orig_category":"Telas Y Sedas (al Por Menor)",
    "sg:phone":"+34 924 31 44 95",
    "sg:postcode":"06800",
    "sg:province":"Badajoz",
    "wof:name":"Diaz Gallardo Isabel",
    "wof:placetype":"venue"
},
  "geometry": {"coordinates":[-6.343565464,38.9171829224],"type":"Point"}
}