{
  "type": "Feature",
  "properties": {
    "addr:full":"Calle de Areta, 4 Llodio \u00c1lava 01400",
    "addr:housenumber":"4",
    "addr:postcode":"01400",
    "addr:street":"Calle De Areta",
    "iso:country":"ES",
    "sg:address":"Calle de Areta, 4",
    "sg:city":"Llodio",
    "sg:orig_category":"Suministros Para Carrocer\u00cdas",
    "sg:phone":"+34 946 72 51 36",
    "sg:postcode":"01400",
    "sg:province":"\u00c1lava",
    "wof:name":"Conde Nu\u00f1ez Jesus Mari",
    "wof:placetype":"venue"
},
  "geometry": {"coordinates":[-2.9495387077,43.148349762],"type":"Point"}
}