{
  "type": "Feature",
  "properties": {
    "iso:country":"ES",
    "sg:address":"Avda Padre Mendez, 50",
    "sg:city":"Almeria",
    "sg:orig_category":"Peluquer\u00cdas, Peluquer\u00cda Mixta",
    "sg:phone":"+34 950 26 63 60",
    "sg:postcode":"04006",
    "sg:province":"Almer\u00eda",
    "wof:name":"Palenzuela Roman Maria Jose",
    "wof:placetype":"venue"
},
  "geometry": {"coordinates":[-2.4492709637,36.8394737244],"type":"Point"}
}