{
  "type": "Feature",
  "properties": {
    "addr:full":"Carrer de Masia, 34 Manyoses Barcelona 08711",
    "addr:housenumber":"34",
    "addr:postcode":"08711",
    "addr:street":"Carrer De Masia;Barcelona",
    "iso:country":"ES",
    "sg:address":"Carrer de Masia, 34",
    "sg:city":"Manyoses",
    "sg:orig_category":"Empresas De Limpieza",
    "sg:phone":"+34 938 03 27 99",
    "sg:postcode":"08711",
    "sg:province":"Barcelona",
    "wof:name":"Kiriat S.l.",
    "wof:placetype":"venue"
},
  "geometry": {"coordinates":[1.6392500401,41.5967903137],"type":"Point"}
}