{
  "type": "Feature",
  "properties": {
    "addr:full":"Calle de Antonio Machado, 103 Torrevieja Alicante 03180",
    "addr:housenumber":"103",
    "addr:postcode":"03180",
    "addr:street":"Calle De Antonio Machado",
    "iso:country":"ES",
    "sg:address":"Calle de Antonio Machado, 103",
    "sg:city":"Torrevieja",
    "sg:orig_category":"Asesor\u00cda Sobre Comunicaci\u00d3n De Empresas",
    "sg:phone":"+34 966 70 40 10",
    "sg:postcode":"03180",
    "sg:province":"Alicante",
    "wof:name":"Asesoria Jose Mateo S.l.u.",
    "wof:placetype":"venue"
},
  "geometry": {"coordinates":[-0.6782445908,37.9794158936],"type":"Point"}
}