{
  "type": "Feature",
  "properties": {
    "addr:full":"Malaga, 6 Arenales Del Sol Alicante 03195",
    "addr:housenumber":"6",
    "addr:postcode":"03195",
    "addr:street":"Malaga",
    "iso:country":"ES",
    "sg:address":"Malaga, 6",
    "sg:city":"Arenales Del Sol",
    "sg:orig_category":"Administradores De Bienes Y Delegados De Comunidades De Propietarios",
    "sg:phone":"+34 966 91 03 51",
    "sg:postcode":"03195",
    "sg:province":"Alicante",
    "wof:name":"Sanchez Perez Manuela",
    "wof:placetype":"venue"
},
  "geometry": {"coordinates":[-0.5192949772,38.2523994446],"type":"Point"}
}