{
  "type": "Feature",
  "properties": {
    "addr:full":"Carr Cura Pleban, 1 Oliva Valencia 46780",
    "addr:housenumber":"1",
    "addr:postcode":"46780",
    "addr:street":"Carr Cura Pleban",
    "iso:country":"ES",
    "sg:address":"Carr Cura Pleban, 1",
    "sg:city":"Oliva",
    "sg:orig_category":"Zapatos (al Por Menor)",
    "sg:phone":"+34 962 85 56 56",
    "sg:postcode":"46780",
    "sg:province":"Valencia",
    "wof:name":"Mu\u00f1oz Colomar Francisco Javier",
    "wof:placetype":"venue"
},
  "geometry": {"coordinates":[-0.1185749993,38.9198608398],"type":"Point"}
}