{
  "type": "Feature",
  "properties": {
    "iso:country":"ES",
    "sg:address":"Calle de Quintana, 15",
    "sg:city":"Madrid",
    "sg:orig_category":"Abogados",
    "sg:phone":"+34 915 42 47 54",
    "sg:postcode":"28008",
    "sg:province":"Madrid",
    "wof:name":"Encabe 2007 Slu.",
    "wof:placetype":"venue"
},
  "geometry": {"coordinates":[-3.7177519798,40.4275741577],"type":"Point"}
}