{
  "type": "Feature",
  "properties": {
    "addr:full":"Av Constitucion, 1 Parcent Alicante 03792",
    "addr:housenumber":"1",
    "addr:postcode":"03792",
    "addr:street":"Av Constitucion",
    "iso:country":"ES",
    "sg:address":"Av Constitucion, 1",
    "sg:city":"Parcent",
    "sg:orig_category":"Cooperativas Agr\u00cdcolas",
    "sg:phone":"+34 966 40 52 43",
    "sg:postcode":"03792",
    "sg:province":"Alicante",
    "wof:name":"Cooperativa Agricola El Progreso",
    "wof:placetype":"venue"
},
  "geometry": {"coordinates":[-0.0661270022,38.7453308105],"type":"Point"}
}