{
  "type": "Feature",
  "properties": {
    "iso:country":"ES",
    "sg:address":"Pol. Ind. De Camba, 5",
    "sg:city":"Xuances",
    "sg:orig_category":"Maquinaria Para Industrias Diversas",
    "sg:phone":"+34 982 59 64 15",
    "sg:postcode":"27877",
    "sg:province":"Lugo",
    "sg:website":"www.jrilo.com",
    "wof:name":"Rilo Maquinaria",
    "wof:placetype":"venue"
},
  "geometry": {"coordinates":[-7.550511837,43.6977653503],"type":"Point"}
}