{
  "type": "Feature",
  "properties": {
    "iso:country":"ES",
    "sg:address":"Calle de Daoiz, 27",
    "sg:city":"Palmas De Gran Canaria",
    "sg:orig_category":"Suministros Para Hoteles",
    "sg:phone":"+34 928 49 30 08",
    "sg:postcode":"35010",
    "sg:province":"Las Palmas",
    "wof:name":"Tecnimel Hosteleria S.l.",
    "wof:placetype":"venue"
},
  "geometry": {"coordinates":[-15.4396715164,28.1320953369],"type":"Point"}
}