{
  "type": "Feature",
  "properties": {
    "iso:country":"ES",
    "sg:address":"Avda Santiago, 41",
    "sg:city":"Vitoria-gasteiz",
    "sg:orig_category":"Inform\u00c1tica (estudios, Servicios, Asesor\u00cda, Formaci\u00d3n)",
    "sg:phone":"+34 945 06 00 34",
    "sg:postcode":"01003",
    "sg:province":"\u00c1lava",
    "wof:name":"Format Gasteiz S.l.",
    "wof:placetype":"venue"
},
  "geometry": {"coordinates":[-2.6621189117,42.8475646973],"type":"Point"}
}