{
  "type": "Feature",
  "properties": {
    "addr:full":"Calle de Teatro (el), 2 Caudete Albacete 02660",
    "addr:housenumber":"2",
    "addr:postcode":"02660",
    "addr:street":"Calle De Teatro El",
    "iso:country":"ES",
    "sg:address":"Calle de Teatro (el), 2",
    "sg:city":"Caudete",
    "sg:orig_category":"Abogados",
    "sg:phone":"+34 965 82 77 26",
    "sg:postcode":"02660",
    "sg:province":"Albacete",
    "wof:name":"Garcia Ba\u00f1on Juan",
    "wof:placetype":"venue"
},
  "geometry": {"coordinates":[-0.9895430207,38.7045783997],"type":"Point"}
}