{
  "type": "Feature",
  "properties": {
    "iso:country":"ES",
    "sg:address":"Av Pedra Blanca, S/n",
    "sg:city":"Floresta",
    "sg:orig_category":"Fabricaci\u00d3n, Importaci\u00d3n De L\u00c1mparas Y Bombillas",
    "sg:phone":"+34 937 52 45 57",
    "sg:postcode":"08338",
    "sg:province":"Barcelona",
    "wof:name":"Nice Works S.l.",
    "wof:placetype":"venue"
},
  "geometry": {"coordinates":[2.3503201008,41.5011787415],"type":"Point"}
}