{
  "type": "Feature",
  "properties": {
    "iso:country":"ES",
    "sg:address":"Calle de Enmedio, 9",
    "sg:city":"Cordoba",
    "sg:orig_category":"Alimentaci\u00d3n General (al Por Menor)",
    "sg:phone":"+34 957 20 31 40",
    "sg:postcode":"14004",
    "sg:province":"C\u00f3rdoba",
    "wof:name":"Onetti Fernandez Rafael",
    "wof:placetype":"venue"
},
  "geometry": {"coordinates":[-4.783662796,37.8760490417],"type":"Point"}
}