{
  "type": "Feature",
  "properties": {
    "addr:full":"Calle de Becerro De Bengoa, 5 Palencia Palencia 34002",
    "addr:housenumber":"5",
    "addr:postcode":"34002",
    "addr:street":"Calle De Becerro De Bengoa",
    "iso:country":"ES",
    "sg:address":"Calle de Becerro De Bengoa, 5",
    "sg:city":"Palencia",
    "sg:orig_category":"Inmobiliaria (agencias)",
    "sg:phone":"+34 979 70 70 23",
    "sg:postcode":"34002",
    "sg:province":"Palencia",
    "sg:website":"www.fincascorral.com",
    "wof:name":"Fincas Corral Vetton,s.l.",
    "wof:placetype":"venue"
},
  "geometry": {"coordinates":[-4.5320696831,42.0087280273],"type":"Point"}
}