{
  "type": "Feature",
  "properties": {
    "iso:country":"ES",
    "sg:address":"Calle de Victoria (la), 25",
    "sg:city":"Ecija",
    "sg:orig_category":"Oficinas: Suministros Para (fabricaci\u00d3n, Al Por Mayor)",
    "sg:phone":"+34 955 90 45 07",
    "sg:postcode":"41400",
    "sg:province":"Sevilla",
    "wof:name":"Astiofic S.l.",
    "wof:placetype":"venue"
},
  "geometry": {"coordinates":[-5.0814795494,37.5363769531],"type":"Point"}
}