{
  "type": "Feature",
  "properties": {
    "iso:country":"ES",
    "sg:address":"Calle de Larga, 43",
    "sg:city":"Puebla Del Rio",
    "sg:orig_category":"Arquitectos",
    "sg:phone":"+34 955 77 04 81",
    "sg:postcode":"41130",
    "sg:province":"Sevilla",
    "wof:name":"Romero Calado Manuel Angel",
    "wof:placetype":"venue"
},
  "geometry": {"coordinates":[-6.0613632202,37.2694396973],"type":"Point"}
}