{
  "type": "Feature",
  "properties": {
    "iso:country":"ES",
    "sg:address":"Calle de Mayor, 14",
    "sg:city":"Hornachuelos",
    "sg:orig_category":"Reposter\u00cdas",
    "sg:phone":"+34 957 64 10 98",
    "sg:postcode":"14740",
    "sg:province":"C\u00f3rdoba",
    "wof:name":"Unipamec S. A.",
    "wof:placetype":"venue"
},
  "geometry": {"coordinates":[-5.241440773,37.8300666809],"type":"Point"}
}