{
  "type": "Feature",
  "properties": {
    "addr:full":"Rua Carpinteiros (dos), 26 Lugo Lugo 27003",
    "addr:housenumber":"26",
    "addr:postcode":"27003",
    "addr:street":"Rua Carpinteiros Dos",
    "iso:country":"ES",
    "sg:address":"Rua Carpinteiros (dos), 26",
    "sg:city":"Lugo",
    "sg:orig_category":"Panader\u00cdas, Panader\u00cdas",
    "sg:phone":"+34 982 20 72 76",
    "sg:postcode":"27003",
    "sg:province":"Lugo",
    "wof:name":"Doces Lucenses S.l.",
    "wof:placetype":"venue"
},
  "geometry": {"coordinates":[-7.5599241257,43.0418548584],"type":"Point"}
}