{
  "type": "Feature",
  "properties": {
    "addr:full":"Calle de Sierra Aitana, 2 Madrid Madrid 28031",
    "addr:housenumber":"2",
    "addr:postcode":"28031",
    "addr:street":"Calle De Sierra Aitana",
    "iso:country":"ES",
    "sg:address":"Calle de Sierra Aitana, 2",
    "sg:city":"Madrid",
    "sg:orig_category":"Librer\u00cdas",
    "sg:phone":"+34 913 32 20 74",
    "sg:postcode":"28031",
    "sg:province":"Madrid",
    "wof:name":"Vascu\u00f1ana Sanabria Dolores",
    "wof:placetype":"venue"
},
  "geometry": {"coordinates":[-3.6192150116,40.3739929199],"type":"Point"}
}