{
  "type": "Feature",
  "properties": {
    "iso:country":"ES",
    "sg:address":"Labradas, 17",
    "sg:city":"Labradas",
    "sg:orig_category":"Molduras, Junquillos, Listones Y Molduras Perforadas",
    "sg:phone":"+34 981 75 50 90",
    "sg:postcode":"15100",
    "sg:province":"La Coru\u00f1a",
    "wof:name":"Regueiro Fari\u00f1a Carmen",
    "wof:placetype":"venue"
},
  "geometry": {"coordinates":[-8.6913089752,43.2121582031],"type":"Point"}
}