{
  "type": "Feature",
  "properties": {
    "iso:country":"ES",
    "sg:address":"Calle de Orion, 20",
    "sg:city":"Alacant",
    "sg:orig_category":"Arquitectos",
    "sg:phone":"+34 965 11 02 94",
    "sg:postcode":"03007",
    "sg:province":"Alicante",
    "wof:name":"Gallardo Aragoneses Juan",
    "wof:placetype":"venue"
},
  "geometry": {"coordinates":[-0.5083519816,38.3421554565],"type":"Point"}
}