{
  "type": "Feature",
  "properties": {
    "iso:country":"ES",
    "sg:address":"Calle de Coto Los Romeros (coto (el)), S/n",
    "sg:city":"Coto",
    "sg:orig_category":"Negocio De Materiales De Construcci\u00d3n",
    "sg:phone":"+34 968 38 75 39",
    "sg:postcode":"30565",
    "sg:province":"Murcia",
    "wof:name":"Coticons De Murcia S.l.",
    "wof:placetype":"venue"
},
  "geometry": {"coordinates":[-1.2395490408,38.0263290405],"type":"Point"}
}