{
  "type": "Feature",
  "properties": {
    "iso:country":"ES",
    "sg:address":"Avda San Bartolome, S/n",
    "sg:city":"Cartaya",
    "sg:orig_category":"Promotores Constructores",
    "sg:phone":"+34 959 39 22 20",
    "sg:postcode":"21450",
    "sg:province":"Huelva",
    "wof:name":"Trayges",
    "wof:placetype":"venue"
},
  "geometry": {"coordinates":[-7.1461138725,37.2883415222],"type":"Point"}
}