{
  "type": "Feature",
  "properties": {
    "iso:country":"ES",
    "sg:address":"Calle de Axular, 15",
    "sg:city":"Santurtzi",
    "sg:orig_category":"Molduras, Junquillos, Listones Y Molduras Perforadas",
    "sg:phone":"+34 944 62 16 36",
    "sg:postcode":"48980",
    "sg:province":"Vizcaya",
    "wof:name":"Martin Gomez Fulgencio",
    "wof:placetype":"venue"
},
  "geometry": {"coordinates":[-3.0359559059,43.3212966919],"type":"Point"}
}