{
  "type": "Feature",
  "properties": {
    "iso:country":"ES",
    "sg:address":"Av Barcelona, 56",
    "sg:city":"Molins Rei",
    "sg:orig_category":"Fotocopias, Reprograf\u00cda",
    "sg:phone":"+34 936 80 01 13",
    "sg:postcode":"08750",
    "sg:province":"Barcelona",
    "wof:name":"Lopez Elias Sergio",
    "wof:placetype":"venue"
},
  "geometry": {"coordinates":[2.020804882,41.4088439941],"type":"Point"}
}