{
  "type": "Feature",
  "properties": {
    "iso:country":"ES",
    "sg:address":"Calle de San Ignacio, 7",
    "sg:city":"San Vicente De Barakaldo",
    "sg:orig_category":"Electrodom\u00c9sticos (al Por Menor)",
    "sg:phone":"+34 944 90 36 30",
    "sg:postcode":"48903",
    "sg:province":"Vizcaya",
    "wof:name":"Martinez Perez Francisco",
    "wof:placetype":"venue"
},
  "geometry": {"coordinates":[-2.9913489819,43.2835388184],"type":"Point"}
}