{
  "type": "Feature",
  "properties": {
    "iso:country":"ES",
    "sg:address":"Plaz General Franco, 3",
    "sg:city":"Ricla",
    "sg:orig_category":"Estancos",
    "sg:phone":"+34 976 60 60 81",
    "sg:postcode":"50270",
    "sg:province":"Zaragoza",
    "wof:name":"Gonzalez Esteve Jose",
    "wof:placetype":"venue"
},
  "geometry": {"coordinates":[-1.404530406,41.5044212341],"type":"Point"}
}