{
  "type": "Feature",
  "properties": {
    "addr:full":"Calle de Kresaltzu, 5 Getxo Vizcaya 48930",
    "addr:housenumber":"5",
    "addr:postcode":"48930",
    "addr:street":"Calle De Kresaltzu",
    "iso:country":"ES",
    "sg:address":"Calle de Kresaltzu, 5",
    "sg:city":"Getxo",
    "sg:classifiers":[
        {
            "category":"Personal",
            "subcategory":"Barber",
            "type":"Services"
        }
    ],
    "sg:phone":"+34 944 64 72 21",
    "sg:postcode":"48930",
    "sg:province":"Vizcaya",
    "sg:tags":[
        "caballeros",
        "de",
        "peluqueros"
    ],
    "wof:name":"Peluqueria Cidoncha",
    "wof:placetype":"venue"
},
  "geometry": {"coordinates":[-3.009278059,43.3272476196],"type":"Point"}
}