{
  "type": "Feature",
  "properties": {
    "iso:country":"ES",
    "sg:address":"Calle de San Francisco, 13",
    "sg:city":"Oviedo",
    "sg:orig_category":"Ense\u00d1anza Variada",
    "sg:phone":"+34 985 21 43 06",
    "sg:postcode":"33003",
    "sg:province":"Asturias",
    "wof:name":"London School Language Center S.l.",
    "wof:placetype":"venue"
},
  "geometry": {"coordinates":[-5.8479290009,43.3617897034],"type":"Point"}
}