{
  "type": "Feature",
  "properties": {
    "addr:full":"Calle de Aire, S/n Hecho Huesca 22720",
    "addr:postcode":"22720",
    "addr:street":"Calle De Aire S / N",
    "iso:country":"ES",
    "sg:address":"Calle de Aire, S/n",
    "sg:city":"Hecho",
    "sg:orig_category":"Bancos",
    "sg:phone":"+34 974 37 55 50",
    "sg:postcode":"22720",
    "sg:province":"Huesca",
    "sg:website":"www.bancozaragozano.es",
    "wof:name":"Barclays Bank S.a.e.",
    "wof:placetype":"venue"
},
  "geometry": {"coordinates":[-0.750639379,42.739276886],"type":"Point"}
}