{
  "type": "Feature",
  "properties": {
    "addr:full":"Calle de Magistrado Alarcon, 33 Baena C\u00f3rdoba 14850",
    "addr:housenumber":"33",
    "addr:postcode":"14850",
    "addr:street":"Calle De Magistrado Alarcon",
    "iso:country":"ES",
    "sg:address":"Calle de Magistrado Alarcon, 33",
    "sg:city":"Baena",
    "sg:orig_category":"Reposter\u00cdas",
    "sg:phone":"+34 957 67 02 46",
    "sg:postcode":"14850",
    "sg:province":"C\u00f3rdoba",
    "wof:name":"Pulido Priego Rosa Maria",
    "wof:placetype":"venue"
},
  "geometry": {"coordinates":[-4.3258581161,37.6218795776],"type":"Point"}
}