{
  "type": "Feature",
  "properties": {
    "iso:country":"ES",
    "sg:address":"Rua Coru\u00d1a, 26",
    "sg:city":"Vigo",
    "sg:orig_category":"Alimentaci\u00d3n: Aditivos, Esencias Alimentarias, Levaduras (fabricaci\u00d3n, Al Por Mayor)",
    "sg:phone":"+34 986 23 79 78",
    "sg:postcode":"36211",
    "sg:province":"Pontevedra",
    "wof:name":"Vigoclima S. L.",
    "wof:placetype":"venue"
},
  "geometry": {"coordinates":[-8.734249115,42.2223892212],"type":"Point"}
}