{
  "type": "Feature",
  "properties": {
    "addr:full":"Calle de Bolonia, 3 Madrid Madrid 28028",
    "addr:housenumber":"3",
    "addr:postcode":"28028",
    "addr:street":"Calle De Bolonia",
    "iso:country":"ES",
    "sg:address":"Calle de Bolonia, 3",
    "sg:city":"Madrid",
    "sg:orig_category":"Asesor\u00cda Fiscal Y Jur\u00cddica",
    "sg:phone":"+34 913 56 27 15",
    "sg:postcode":"28028",
    "sg:province":"Madrid",
    "wof:name":"Albi\u00f1ana Fernandez Ana Isabel",
    "wof:placetype":"venue"
},
  "geometry": {"coordinates":[-3.6648466587,40.4389343262],"type":"Point"}
}