{
  "type": "Feature",
  "properties": {
    "addr:full":"Gudarien Etorbidea, 2 Ordizia Guip\u00f9zcoa 20240",
    "addr:housenumber":"2",
    "addr:postcode":"20240",
    "addr:street":"Gudarien Etorbidea;Guipu\u0300Zcoa",
    "iso:country":"ES",
    "sg:address":"Gudarien Etorbidea, 2",
    "sg:city":"Ordizia",
    "sg:orig_category":"Producci\u00d3n De Sidra",
    "sg:phone":"+34 943 88 11 28",
    "sg:postcode":"20240",
    "sg:province":"Guip\u00f9zcoa",
    "wof:name":"Aitor Esnaola Gazta\u00f1aga Y Otro, C.b.",
    "wof:placetype":"venue"
},
  "geometry": {"coordinates":[-2.1756441593,43.0534744263],"type":"Point"}
}