{
  "type": "Feature",
  "properties": {
    "addr:full":"Plaz Sol Del, 6 Oviedo Asturias 33009",
    "addr:postcode":"33009",
    "iso:country":"ES",
    "sg:address":"Plaz Sol Del, 6",
    "sg:city":"Oviedo",
    "sg:orig_category":"Arquitectos",
    "sg:phone":"+34 985 22 61 89",
    "sg:postcode":"33009",
    "sg:province":"Asturias",
    "wof:name":"Sociedad Asturiana De Gestion Y Arquitectura, S.l.",
    "wof:placetype":"venue"
},
  "geometry": {"coordinates":[-5.8475308418,43.3626899719],"type":"Point"}
}