{
  "type": "Feature",
  "properties": {
    "addr:full":"Rond Guinardo, 196 Barcelona Barcelona 08041",
    "addr:housenumber":"196",
    "addr:postcode":"08041",
    "iso:country":"ES",
    "sg:address":"Rond Guinardo, 196",
    "sg:city":"Barcelona",
    "sg:orig_category":"Farmacias",
    "sg:phone":"+34 934 36 39 65",
    "sg:postcode":"08041",
    "sg:province":"Barcelona",
    "wof:name":"Lopez Lozano Maria Del Carmen",
    "wof:placetype":"venue"
},
  "geometry": {"coordinates":[2.1772110462,41.4215011597],"type":"Point"}
}