{
  "type": "Feature",
  "properties": {
    "addr:full":"Calle de Calderon De La Barca, 6 Huelva Huelva 21001",
    "addr:housenumber":"6",
    "addr:postcode":"21001",
    "addr:street":"Calle De Calderon De La Barca",
    "iso:country":"ES",
    "sg:address":"Calle de Calderon De La Barca, 6",
    "sg:city":"Huelva",
    "sg:orig_category":"Pescader\u00cdas (al Por Menor)",
    "sg:phone":"+34 959 24 94 58",
    "sg:postcode":"21001",
    "sg:province":"Huelva",
    "wof:name":"Grasas Animales Y Aceite De Pescado El Tiburon S.l.",
    "wof:placetype":"venue"
},
  "geometry": {"coordinates":[-6.9510645866,37.2373847961],"type":"Point"}
}