{
  "type": "Feature",
  "properties": {
    "addr:full":"Rua De Compostela, 29 Ordes A Coru\u00f1a 15680",
    "addr:housenumber":"29",
    "addr:postcode":"15680",
    "addr:street":"Rua De Compostela;A Corun\u0303A",
    "iso:country":"ES",
    "sg:address":"Rua De Compostela, 29",
    "sg:city":"Ordes",
    "sg:orig_category":"Molduras, Junquillos, Listones Y Molduras Perforadas",
    "sg:phone":"+34 981 68 04 48",
    "sg:postcode":"15680",
    "sg:province":"A Coru\u00f1a",
    "wof:name":"Santos Teixeira Maria Manuela",
    "wof:placetype":"venue"
},
  "geometry": {"coordinates":[-8.4090108871,43.0780105591],"type":"Point"}
}