{
  "type": "Feature",
  "properties": {
    "iso:country":"ES",
    "sg:address":"Calle de Bentabarri, 4",
    "sg:city":"Apatamonasterio",
    "sg:orig_category":"Puertas Y Portales",
    "sg:phone":"+34 946 58 46 75",
    "sg:postcode":"48291",
    "sg:province":"Vizcaya",
    "wof:name":"Puertas Metalicas Especiales S.l.l.",
    "wof:placetype":"venue"
},
  "geometry": {"coordinates":[-2.5823516846,43.1305923462],"type":"Point"}
}