{
  "type": "Feature",
  "properties": {
    "iso:country":"ES",
    "sg:address":"Calle de Curtidores, 2",
    "sg:city":"Carmona",
    "sg:orig_category":"Art\u00cdculos Funerarios (al Por Menor)",
    "sg:phone":"+34 954 19 61 74",
    "sg:postcode":"41410",
    "sg:province":"Sevilla",
    "wof:name":"Funeraria San Vicente S.l.",
    "wof:placetype":"venue"
},
  "geometry": {"coordinates":[-5.6497087479,37.4834403992],"type":"Point"}
}