{
  "type": "Feature",
  "properties": {
    "iso:country":"ES",
    "sg:address":"Luga Poligono Industrial Del Bierzo, 8",
    "sg:city":"Toral De Los Vados",
    "sg:orig_category":"Pizzer\u00cdas",
    "sg:phone":"+34 987 54 58 00",
    "sg:postcode":"24560",
    "sg:province":"Le\u00f3n",
    "wof:name":"Theboe S.a.",
    "wof:placetype":"venue"
},
  "geometry": {"coordinates":[-6.7822341919,42.5436286926],"type":"Point"}
}