{
  "type": "Feature",
  "properties": {
    "iso:country":"ES",
    "sg:address":"Via Pollentia, 1",
    "sg:city":"Pollen\u00e7a",
    "sg:orig_category":"Bancos",
    "sg:phone":"+34 971 53 03 50",
    "sg:postcode":"07460",
    "sg:province":"Islas Baleares",
    "wof:name":"Banco De Credito Balear",
    "wof:placetype":"venue"
},
  "geometry": {"coordinates":[3.0177500248,39.8756408691],"type":"Point"}
}