{
  "type": "Feature",
  "properties": {
    "iso:country":"ES",
    "sg:address":"Carrer de Extremadura, 2",
    "sg:city":"Cambrils",
    "sg:orig_category":"Promotores Constructores",
    "sg:phone":"+34 977 36 65 01",
    "sg:postcode":"43850",
    "sg:province":"Tarragona",
    "wof:name":"Promociones Manilva 99 S.l.",
    "wof:placetype":"venue"
},
  "geometry": {"coordinates":[1.0565429926,41.0685462952],"type":"Point"}
}