{
  "type": "Feature",
  "properties": {
    "addr:full":"Calle de Correhuela, 3 Salamanca Salamanca 37001",
    "addr:housenumber":"3",
    "addr:postcode":"37001",
    "addr:street":"Calle De Correhuela",
    "iso:country":"ES",
    "sg:address":"Calle de Correhuela, 3",
    "sg:city":"Salamanca",
    "sg:orig_category":"Triper\u00cdas",
    "sg:phone":"+34 923 21 22 93",
    "sg:postcode":"37001",
    "sg:province":"Salamanca",
    "wof:name":"Revilla Julian Miguel",
    "wof:placetype":"venue"
},
  "geometry": {"coordinates":[-5.6621518135,40.9654960632],"type":"Point"}
}