{
  "type": "Feature",
  "properties": {
    "addr:full":"Calle de Real Alta, 23 Ogijares Granada 18151",
    "addr:housenumber":"23",
    "addr:postcode":"18151",
    "addr:street":"Calle De Real Alta",
    "iso:country":"ES",
    "sg:address":"Calle de Real Alta, 23",
    "sg:city":"Ogijares",
    "sg:orig_category":"Quincaller\u00cda (al Por Menor)",
    "sg:phone":"+34 958 59 70 78",
    "sg:postcode":"18151",
    "sg:province":"Granada",
    "wof:name":"Plata Ruiz Jorge",
    "wof:placetype":"venue"
},
  "geometry": {"coordinates":[-3.6081340313,37.1198043823],"type":"Point"}
}