{
  "type": "Feature",
  "properties": {
    "addr:full":"Avgd Barcelona, 25 Lleida Lleida 25001",
    "addr:housenumber":"25",
    "addr:postcode":"25001",
    "iso:country":"ES",
    "sg:address":"Avgd Barcelona, 25",
    "sg:city":"Lleida",
    "sg:orig_category":"Comercio, Reparaci\u00d3n De Motocicletas, Bicicletas Y Piezas Sueltas",
    "sg:phone":"+34 973 21 21 31",
    "sg:postcode":"25001",
    "sg:province":"Lleida",
    "wof:name":"Yam-973 S.l.",
    "wof:placetype":"venue"
},
  "geometry": {"coordinates":[0.6324818134,41.6080856323],"type":"Point"}
}