{
  "type": "Feature",
  "properties": {
    "iso:country":"ES",
    "sg:address":"Pl. Ayuntamiento, 1",
    "sg:city":"Gabaldon",
    "sg:orig_category":"Ense\u00d1anza, Formaci\u00d3n Profesional: Aprendizaje",
    "sg:phone":"+34 969 33 90 02",
    "sg:postcode":"16132",
    "sg:province":"Cuenca",
    "wof:name":"Ayuntamiento De Gabaldon",
    "wof:placetype":"venue"
},
  "geometry": {"coordinates":[-1.9418047667,39.6265563965],"type":"Point"}
}