{
  "type": "Feature",
  "properties": {
    "iso:country":"ES",
    "sg:address":"Calle de Sixta Barrenetxea, 1",
    "sg:city":"Kurtzea",
    "sg:orig_category":"Centros Empresariales",
    "sg:phone":"+34 944 57 34 34",
    "sg:postcode":"48960",
    "sg:province":"Vizcaya",
    "wof:name":"Asociacion Radio Taxi Galdakao",
    "wof:placetype":"venue"
},
  "geometry": {"coordinates":[-2.8591547012,43.2324829102],"type":"Point"}
}