{
  "type": "Feature",
  "properties": {
    "addr:full":"Calle de Rios Rosas, 54 Madrid Madrid 28003",
    "addr:housenumber":"54",
    "addr:postcode":"madrid;28003",
    "addr:street":"Calle De Rios Rosas",
    "iso:country":"ES",
    "sg:address":"Calle de Rios Rosas, 54",
    "sg:city":"Madrid",
    "sg:orig_category":"M\u00c9dicos: Ginecolog\u00cda Y Obstetricia",
    "sg:phone":"+34 915 35 13 91",
    "sg:postcode":"28003",
    "sg:province":"Madrid",
    "wof:name":"Aguirre De Carcer S.l.",
    "wof:placetype":"venue"
},
  "geometry": {"coordinates":[-3.6955010891,40.4417190552],"type":"Point"}
}