{
  "type": "Feature",
  "properties": {
    "iso:country":"ES",
    "sg:address":"Calle de Juan Montoliu, 4",
    "sg:city":"Chilches",
    "sg:orig_category":"Supermercados Y Hipermercados",
    "sg:phone":"+34 964 58 30 96",
    "sg:postcode":"12592",
    "sg:province":"Castell\u00f3n",
    "wof:name":"Soriano Aguilella Maria Del Carmen",
    "wof:placetype":"venue"
},
  "geometry": {"coordinates":[-0.1891960055,39.7832489014],"type":"Point"}
}