{
  "type": "Feature",
  "properties": {
    "addr:full":"Calle de Juan Carlos I, 2 Puerto Del Carmen Las Palmas 35510",
    "addr:housenumber":"2",
    "addr:postcode":"35510",
    "addr:street":"Calle De Juan Carlos I",
    "iso:country":"ES",
    "sg:address":"Calle de Juan Carlos I, 2",
    "sg:city":"Puerto Del Carmen",
    "sg:orig_category":"Oficinas De Cambio",
    "sg:phone":"+34 928 51 38 56",
    "sg:postcode":"35510",
    "sg:province":"Las Palmas",
    "wof:name":"Lagergren S.l.",
    "wof:placetype":"venue"
},
  "geometry": {"coordinates":[-13.6699714661,28.921459198],"type":"Point"}
}