{
  "type": "Feature",
  "properties": {
    "iso:country":"ES",
    "sg:address":"Avda Doctor Meca, 90",
    "sg:city":"Puerto Mazarron",
    "sg:orig_category":"Inmobiliaria (agencias)",
    "sg:phone":"+34 968 59 54 40",
    "sg:postcode":"30860",
    "sg:province":"Murcia",
    "wof:name":"Contrubeach S.l.",
    "wof:placetype":"venue"
},
  "geometry": {"coordinates":[-1.2632160187,37.5697135925],"type":"Point"}
}