{
  "type": "Feature",
  "properties": {
    "addr:full":"Carretera Madrid-coru\u00f1a, Km. 0292,0 Valcabado Del Paramo Le\u00f3n 24790",
    "addr:postcode":"24790",
    "addr:street":"Carretera Madrid-Corun\u0303A Km. 0292,0;Leo\u0301N",
    "iso:country":"ES",
    "sg:address":"Carretera Madrid-coru\u00f1a, Km. 0292,0",
    "sg:city":"Valcabado Del Paramo",
    "sg:orig_category":"Material Y Herramientas Agr\u00cdcolas",
    "sg:phone":"+34 987 66 61 25",
    "sg:postcode":"24790",
    "sg:province":"Le\u00f3n",
    "wof:name":"Guerra Rebollo Maria Isabel",
    "wof:placetype":"venue"
},
  "geometry": {"coordinates":[-5.8012089729,42.2234458923],"type":"Point"}
}