{
  "type": "Feature",
  "properties": {
    "iso:country":"ES",
    "sg:address":"Rua Aduana (da), 36",
    "sg:city":"San Cibrao",
    "sg:orig_category":"Laboratorios Y Trabajos De Fotograf\u00cda, V\u00cddeo Y Cine",
    "sg:phone":"+34 982 59 42 08",
    "sg:postcode":"27890",
    "sg:province":"Lugo",
    "wof:name":"Imaxe Dixital 3000 S.l.",
    "wof:placetype":"venue"
},
  "geometry": {"coordinates":[-7.4402308464,43.6964683533],"type":"Point"}
}