{
  "type": "Feature",
  "properties": {
    "iso:country":"ES",
    "sg:address":"Pase Maritimo Rey De Espa\u00d1a, 61",
    "sg:city":"Fuengirola",
    "sg:orig_category":"Agencias De Viajes",
    "sg:phone":"+34 952 46 01 32",
    "sg:postcode":"29640",
    "sg:province":"M\u00e1laga",
    "wof:name":"Viajes Torreblanca S.l.",
    "wof:placetype":"venue"
},
  "geometry": {"coordinates":[-4.6157150269,36.5484161377],"type":"Point"}
}