{
  "type": "Feature",
  "properties": {
    "addr:full":"Carr Joan Blanch, 42 Torregrossa Lleida 25141",
    "addr:housenumber":"42",
    "addr:postcode":"25141",
    "addr:street":"Carr Joan Blanch",
    "iso:country":"ES",
    "sg:address":"Carr Joan Blanch, 42",
    "sg:city":"Torregrossa",
    "sg:orig_category":"Institutos De Belleza",
    "sg:phone":"+34 973 17 01 00",
    "sg:postcode":"25141",
    "sg:province":"Lleida",
    "wof:name":"Fi\u00f1ana Rubio Maria Alba",
    "wof:placetype":"venue"
},
  "geometry": {"coordinates":[0.8324049711,41.5803718567],"type":"Point"}
}