{
  "type": "Feature",
  "properties": {
    "iso:country":"ES",
    "sg:address":"Calle de Amposta, 3",
    "sg:city":"Madrid",
    "sg:orig_category":"Casquer\u00cda (al Por Menor)",
    "sg:phone":"+34 913 06 40 30",
    "sg:postcode":"28037",
    "sg:province":"Madrid",
    "wof:name":"Matias Martin Benito",
    "wof:placetype":"venue"
},
  "geometry": {"coordinates":[-3.6222193241,40.4272880554],"type":"Point"}
}