{
  "type": "Feature",
  "properties": {
    "iso:country":"ES",
    "sg:address":"Carrer de Sardenya, 229",
    "sg:city":"Barcelona",
    "sg:orig_category":"Suministros Y Materiales Industriales",
    "sg:phone":"+34 932 65 18 19",
    "sg:postcode":"08013",
    "sg:province":"Barcelona",
    "wof:name":"Coditex S.a.",
    "wof:placetype":"venue"
},
  "geometry": {"coordinates":[2.177241087,41.4002571106],"type":"Point"}
}