{
  "type": "Feature",
  "properties": {
    "iso:country":"ES",
    "sg:address":"Sbid Seminari, S/n",
    "sg:city":"Solsona",
    "sg:orig_category":"Ense\u00d1anza, Formaci\u00d3n Profesional: Aprendizaje",
    "sg:phone":"+34 973 48 17 52",
    "sg:postcode":"25280",
    "sg:province":"Lleida",
    "sg:website":"www.ctfc.es",
    "wof:name":"Centre Tecnologic Forestal De Catalunya",
    "wof:placetype":"venue"
},
  "geometry": {"coordinates":[1.5177680254,41.9917373657],"type":"Point"}
}