{
  "type": "Feature",
  "properties": {
    "addr:full":"Pg Vara De Rey, 4 Eivissa Islas Baleares 07800",
    "addr:housenumber":"4",
    "addr:postcode":"07800",
    "addr:street":"Pg Vara De Rey",
    "iso:country":"ES",
    "sg:address":"Pg Vara De Rey, 4",
    "sg:city":"Eivissa",
    "sg:orig_category":"Inmobiliaria (agencias)",
    "sg:phone":"+34 971 19 19 14",
    "sg:postcode":"07800",
    "sg:province":"Islas Baleares",
    "wof:name":"Fradibi S.l.",
    "wof:placetype":"venue"
},
  "geometry": {"coordinates":[1.4326150417,38.9086418152],"type":"Point"}
}