{
  "type": "Feature",
  "properties": {
    "iso:country":"ES",
    "sg:address":"Carrer de L'escorial, 32",
    "sg:city":"Barcelona",
    "sg:orig_category":"Inmobiliaria (agencias)",
    "sg:phone":"+34 932 84 55 73",
    "sg:postcode":"08024",
    "sg:province":"Barcelona",
    "wof:name":"Flapisa",
    "wof:placetype":"venue"
},
  "geometry": {"coordinates":[2.1617670059,41.4068641663],"type":"Point"}
}