{
  "type": "Feature",
  "properties": {
    "addr:full":"Rua Filgueira Valverde, 1 Pastoriza La Coru\u00f1a 15140",
    "addr:housenumber":"1",
    "addr:postcode":"15140",
    "addr:street":"Rua Filgueira Valverde;La Corun\u0303A",
    "iso:country":"ES",
    "sg:address":"Rua Filgueira Valverde, 1",
    "sg:city":"Pastoriza",
    "sg:orig_category":"Empresas De Carpinter\u00cda De Madera",
    "sg:phone":"+34 981 60 73 04",
    "sg:postcode":"15140",
    "sg:province":"La Coru\u00f1a",
    "wof:name":"Carpemara S.l.",
    "wof:placetype":"venue"
},
  "geometry": {"coordinates":[-8.46671772,43.3288497925],"type":"Point"}
}