{
  "type": "Feature",
  "properties": {
    "addr:full":"Plaz Constitucion (de La), 9 Abanilla Murcia 30640",
    "addr:housenumber":"9",
    "addr:postcode":"30640",
    "iso:country":"ES",
    "sg:address":"Plaz Constitucion (de La), 9",
    "sg:city":"Abanilla",
    "sg:orig_category":"Bancos",
    "sg:phone":"+34 968 68 00 37",
    "sg:postcode":"30640",
    "sg:province":"Murcia",
    "sg:website":"www.bancodevalencia.es",
    "wof:name":"Banco De Valencia S.a.",
    "wof:placetype":"venue"
},
  "geometry": {"coordinates":[-1.0418750048,38.2073516846],"type":"Point"}
}