{
  "type": "Feature",
  "properties": {
    "addr:full":"Carrer de Vint I Sis De Gener 1641, 15 Barcelona Barcelona 08014",
    "addr:housenumber":"1641",
    "addr:postcode":"08014",
    "addr:street":"Carrer De Vint;15",
    "iso:country":"ES",
    "sg:address":"Carrer de Vint I Sis De Gener 1641, 15",
    "sg:city":"Barcelona",
    "sg:orig_category":"Cristaler\u00cda: Suministros",
    "sg:phone":"+34 934 22 64 38",
    "sg:postcode":"08014",
    "sg:province":"Barcelona",
    "wof:name":"D 2 Vidres S.l.",
    "wof:placetype":"venue"
},
  "geometry": {"coordinates":[2.1412909031,41.374080658],"type":"Point"}
}