{
  "type": "Feature",
  "properties": {
    "addr:full":"Ctra Villalpando, 23 Zamora Zamora 49023",
    "addr:housenumber":"23",
    "addr:postcode":"49023",
    "addr:street":"Ctra Villalpando",
    "iso:country":"ES",
    "sg:address":"Ctra Villalpando, 23",
    "sg:city":"Zamora",
    "sg:orig_category":"Art\u00cdculos De Madera (fabricaci\u00d3n Y Al Por Mayor)",
    "sg:phone":"+34 980 52 16 27",
    "sg:postcode":"49023",
    "sg:province":"Zamora",
    "wof:name":"Arcas Zamora S.l",
    "wof:placetype":"venue"
},
  "geometry": {"coordinates":[-5.7382969856,41.5185317993],"type":"Point"}
}