{
  "type": "Feature",
  "properties": {
    "iso:country":"ES",
    "sg:address":"Av Eramprunya (l'), 75",
    "sg:city":"Gava",
    "sg:orig_category":"Adaptaciones, Acondicionamientos Especiales Para Veh\u00cdculos, Veh\u00cdculos Industriales",
    "sg:phone":"+34 936 62 68 54",
    "sg:postcode":"08850",
    "sg:province":"Barcelona",
    "wof:name":"Juan Ramon Mirta Claudia",
    "wof:placetype":"venue"
},
  "geometry": {"coordinates":[1.9938839674,41.3095664978],"type":"Point"}
}