{
  "type": "Feature",
  "properties": {
    "iso:country":"ES",
    "sg:address":"C/ Sant Joan De Ribera, 90",
    "sg:city":"Alcoi",
    "sg:orig_category":"Fabricaci\u00d3n De Ventanas",
    "sg:phone":"+34 965 54 00 98",
    "sg:postcode":"03801",
    "sg:province":"Alicante",
    "wof:name":"Registros Y Persianas S. L.",
    "wof:placetype":"venue"
},
  "geometry": {"coordinates":[-0.4672180116,38.6951560974],"type":"Point"}
}