{
  "type": "Feature",
  "properties": {
    "iso:country":"ES",
    "sg:address":"Calle de Mayor, 15",
    "sg:city":"Caudete",
    "sg:orig_category":"Confecci\u00d3n (fabricaci\u00d3n, Al Por Mayor)",
    "sg:phone":"+34 965 82 79 26",
    "sg:postcode":"02660",
    "sg:province":"Albacete",
    "wof:name":"Fiesta Solera S.l.",
    "wof:placetype":"venue"
},
  "geometry": {"coordinates":[-0.9895070195,38.7045974731],"type":"Point"}
}