{
  "type": "Feature",
  "properties": {
    "addr:full":"Calle de San Roque, S/n Adrados Segovia 40354",
    "addr:housenumber":"s",
    "addr:postcode":"40354",
    "addr:street":"Calle De San Roque;/ N Adrados Segovia",
    "iso:country":"ES",
    "sg:address":"Calle de San Roque, S/n",
    "sg:city":"Adrados",
    "sg:orig_category":"Centros De Educaci\u00d3n Especial",
    "sg:phone":"+34 921 14 80 29",
    "sg:postcode":"40354",
    "sg:province":"Segovia",
    "wof:name":"Colegio Rural Agrupado De Olombrada-aula De Olombrada",
    "wof:placetype":"venue"
},
  "geometry": {"coordinates":[-4.1114368439,41.3671722412],"type":"Point"}
}