{
  "type": "Feature",
  "properties": {
    "iso:country":"ES",
    "sg:address":"C/ Sabadell, 6",
    "sg:city":"Alcoi",
    "sg:orig_category":"Inmobiliaria (agencias)",
    "sg:phone":"+34 965 33 10 35",
    "sg:postcode":"03804",
    "sg:province":"Alicante",
    "wof:name":"Barber Inmobiliaria Peritaciones S.l.",
    "wof:placetype":"venue"
},
  "geometry": {"coordinates":[-0.4680080116,38.709274292],"type":"Point"}
}