{
  "type": "Feature",
  "properties": {
    "addr:full":"Carrer de Anoia, S/n Vilafortuny Tarragona 43850",
    "addr:housenumber":"s / n",
    "addr:postcode":"43850",
    "addr:street":"Carrer De Anoia",
    "iso:country":"ES",
    "sg:address":"Carrer de Anoia, S/n",
    "sg:city":"Vilafortuny",
    "sg:orig_category":"Inmobiliaria (agencias)",
    "sg:phone":"+34 977 36 88 86",
    "sg:postcode":"43850",
    "sg:province":"Tarragona",
    "wof:name":"Orbis Habitat S.l.",
    "wof:placetype":"venue"
},
  "geometry": {"coordinates":[1.0611100197,41.0672683716],"type":"Point"}
}