{
  "type": "Feature",
  "properties": {
    "addr:full":"Carrer de Coimbra, 12 Barcelona Barcelona 08032",
    "addr:housenumber":"12",
    "addr:postcode":"08032",
    "addr:street":"Carrer De Coimbra",
    "iso:country":"ES",
    "sg:address":"Carrer de Coimbra, 12",
    "sg:city":"Barcelona",
    "sg:orig_category":"Electricidad: Instaladores",
    "sg:phone":"+34 934 07 13 12",
    "sg:postcode":"08032",
    "sg:province":"Barcelona",
    "wof:name":"Barros Cardesin Jaime",
    "wof:placetype":"venue"
},
  "geometry": {"coordinates":[2.1556129456,41.4322242737],"type":"Point"}
}