{
  "type": "Feature",
  "properties": {
    "addr:full":"Santa Minia, S/n Brion La Coru\u00f1a 15865",
    "addr:housenumber":"s / n",
    "addr:postcode":"15865",
    "addr:street":"Santa Minia;La Corun\u0303A",
    "iso:country":"ES",
    "sg:address":"Santa Minia, S/n",
    "sg:city":"Brion",
    "sg:orig_category":"Administraciones Regionales, Departamentales Y Locales",
    "sg:phone":"+34 981 88 70 06",
    "sg:postcode":"15865",
    "sg:province":"La Coru\u00f1a",
    "wof:name":"Concello De Brion",
    "wof:placetype":"venue"
},
  "geometry": {"coordinates":[-8.6784410477,42.8665046692],"type":"Point"}
}