{
  "type": "Feature",
  "properties": {
    "addr:full":"Av San Jorge, 81 Iru\u00f1a Navarra 31012",
    "addr:housenumber":"81",
    "addr:postcode":"31012",
    "addr:street":"Av San Jorge",
    "iso:country":"ES",
    "sg:address":"Av San Jorge, 81",
    "sg:city":"Iru\u00f1a",
    "sg:orig_category":"Administraci\u00d3n En Agricultura",
    "sg:phone":"+34 948 17 83 32",
    "sg:postcode":"31012",
    "sg:province":"Navarra",
    "wof:name":"Consejo De Produccion Agraria Ecologica De Navarra",
    "wof:placetype":"venue"
},
  "geometry": {"coordinates":[-1.6713989973,42.8201293945],"type":"Point"}
}