{
  "type": "Feature",
  "properties": {
    "iso:country":"ES",
    "sg:address":"Luga Poligono Industrial De Roces, S/n",
    "sg:city":"Gijon",
    "sg:orig_category":"Dibujos Animados",
    "sg:phone":"+34 985 16 81 87",
    "sg:postcode":"33211",
    "sg:province":"Asturias",
    "wof:name":"Comics Y Cuentos Asturias S.l.",
    "wof:placetype":"venue"
},
  "geometry": {"coordinates":[-5.6863942146,43.5233383179],"type":"Point"}
}