{
  "type": "Feature",
  "properties": {
    "addr:full":"Calle de Augusto Plasencia, 2 Sevilla Sevilla 41004",
    "addr:housenumber":"2",
    "addr:postcode":"41004",
    "addr:street":"Calle De Augusto Plasencia",
    "iso:country":"ES",
    "sg:address":"Calle de Augusto Plasencia, 2",
    "sg:city":"Sevilla",
    "sg:orig_category":"Iglesia Cat\u00d3lica",
    "sg:phone":"+34 954 22 53 13",
    "sg:postcode":"41004",
    "sg:province":"Sevilla",
    "wof:name":"Parroquia San Isidoro",
    "wof:placetype":"venue"
},
  "geometry": {"coordinates":[-5.9908480644,37.3897705078],"type":"Point"}
}