{
  "type": "Feature",
  "properties": {
    "addr:full":"Avda Jose Antonio, 37 Lalin Pontevedra 36500",
    "addr:housenumber":"37",
    "addr:postcode":"36500",
    "addr:street":"Avda Jose Antonio",
    "iso:country":"ES",
    "sg:address":"Avda Jose Antonio, 37",
    "sg:city":"Lalin",
    "sg:orig_category":"Talleres: Ropa A Medida",
    "sg:phone":"+34 986 78 09 45",
    "sg:postcode":"36500",
    "sg:province":"Pontevedra",
    "wof:name":"Gonzalez Payo Manuel",
    "wof:placetype":"venue"
},
  "geometry": {"coordinates":[-8.1068964005,42.661693573],"type":"Point"}
}