{
  "type": "Feature",
  "properties": {
    "addr:full":"Calle de General Luis Alarcon De La Lastra, 2 Sevilla Sevilla 41006",
    "addr:housenumber":"2",
    "addr:postcode":"41006",
    "addr:street":"Calle De General Luis Alarcon De La Lastra",
    "iso:country":"ES",
    "sg:address":"Calle de General Luis Alarcon De La Lastra, 2",
    "sg:city":"Sevilla",
    "sg:orig_category":"Asociaciones Y Clubs Deportivos",
    "sg:phone":"+34 954 92 46 10",
    "sg:postcode":"41006",
    "sg:province":"Sevilla",
    "wof:name":"Pe\u00f1a Cultural Betica Miguel Espina",
    "wof:placetype":"venue"
},
  "geometry": {"coordinates":[-5.9507861137,37.3825912476],"type":"Point"}
}