{
  "type": "Feature",
  "properties": {
    "iso:country":"ES",
    "sg:address":"Calle de Segre, 20",
    "sg:city":"Madrid",
    "sg:orig_category":"Agencias Y Asesores De Publicidad",
    "sg:phone":"+34 915 64 38 64",
    "sg:postcode":"28002",
    "sg:province":"Madrid",
    "wof:name":"Relevo Publicidad",
    "wof:placetype":"venue"
},
  "geometry": {"coordinates":[-3.6845839024,40.4512710571],"type":"Point"}
}