{
  "type": "Feature",
  "properties": {
    "addr:full":"Pg Bonanova, 61 Barcelona Barcelona 08017",
    "addr:housenumber":"61",
    "addr:postcode":"08017",
    "addr:street":"Pg Bonanova",
    "iso:country":"ES",
    "sg:address":"Pg Bonanova, 61",
    "sg:city":"Barcelona",
    "sg:orig_category":"Abogados",
    "sg:phone":"+34 934 18 52 82",
    "sg:postcode":"08017",
    "sg:province":"Barcelona",
    "wof:name":"Vallejo Marcen Octavio",
    "wof:placetype":"venue"
},
  "geometry": {"coordinates":[2.1277930737,41.4033164978],"type":"Point"}
}