{
  "type": "Feature",
  "properties": {
    "iso:country":"ES",
    "sg:address":"Carretera, 32",
    "sg:city":"Aldeire",
    "sg:orig_category":"Farmacias",
    "sg:phone":"+34 958 67 12 26",
    "sg:postcode":"18514",
    "sg:province":"Granada",
    "wof:name":"Garcia Amat Maria Isabel",
    "wof:placetype":"venue"
},
  "geometry": {"coordinates":[-3.0721669197,37.1640357971],"type":"Point"}
}