{
  "type": "Feature",
  "properties": {
    "iso:country":"ES",
    "sg:address":"C/ Merce Rodoreda, S/n",
    "sg:city":"Salt",
    "sg:orig_category":"Protecci\u00d3n Contra Incendios: Material, Instalaci\u00d3n, Mantenimiento",
    "sg:phone":"+34 972 24 03 20",
    "sg:postcode":"17190",
    "sg:province":"Girona",
    "sg:website":"www.parsi-pci.com",
    "wof:name":"Parsi S.a.",
    "wof:placetype":"venue"
},
  "geometry": {"coordinates":[2.7811899185,41.9719543457],"type":"Point"}
}