{
  "type": "Feature",
  "properties": {
    "iso:country":"ES",
    "sg:address":"Carrer de Enten\u00c7a, 70",
    "sg:city":"Barcelona",
    "sg:orig_category":"Carnicer\u00cdas, Carnicer\u00cdas",
    "sg:phone":"+34 933 25 57 34",
    "sg:postcode":"08015",
    "sg:province":"Barcelona",
    "wof:name":"Pico Garcia Victoria",
    "wof:placetype":"venue"
},
  "geometry": {"coordinates":[2.1516449451,41.3790245056],"type":"Point"}
}