{
  "type": "Feature",
  "properties": {
    "iso:country":"ES",
    "sg:address":"Calle de Lobero, 30",
    "sg:city":"Ejido",
    "sg:orig_category":"Arboricultura Y Producci\u00d3n De Frutas",
    "sg:phone":"+34 950 57 33 45",
    "sg:postcode":"04700",
    "sg:province":"Almer\u00eda",
    "sg:website":"www.bassolafrutta.com",
    "wof:name":"Ola Verde S.l.",
    "wof:placetype":"venue"
},
  "geometry": {"coordinates":[-2.813270092,36.7745361328],"type":"Point"}
}