{
  "type": "Feature",
  "properties": {
    "iso:country":"ES",
    "sg:address":"Calle de Marques De San Nicolas, 45",
    "sg:city":"Logro\u00f1o",
    "sg:orig_category":"Comerciantes Al Por Mayor De Vinos, Licores Y Alcoholes",
    "sg:phone":"+34 941 25 16 65",
    "sg:postcode":"26001",
    "sg:province":"La Rioja",
    "wof:name":"Lerchundi Perez Antonio Javier",
    "wof:placetype":"venue"
},
  "geometry": {"coordinates":[-2.4450569153,42.4675483704],"type":"Point"}
}