{
  "type": "Feature",
  "properties": {
    "iso:country":"ES",
    "sg:address":"Avda Nueve De Octubre, 80",
    "sg:city":"Puerto",
    "sg:orig_category":"Inmobiliaria (agencias)",
    "sg:phone":"+34 962 69 90 81",
    "sg:postcode":"46520",
    "sg:province":"Valencia",
    "wof:name":"Fincasa Grupo Spj Puerto Sagunto S.l.",
    "wof:placetype":"venue"
},
  "geometry": {"coordinates":[-0.2245389968,39.660861969],"type":"Point"}
}