{
  "type": "Feature",
  "properties": {
    "addr:full":"Calle de Ceballos, 3 Espera C\u00e1diz 11648",
    "addr:housenumber":"3",
    "addr:postcode":"11648",
    "addr:street":"Calle De Ceballos",
    "iso:country":"ES",
    "sg:address":"Calle de Ceballos, 3",
    "sg:city":"Espera",
    "sg:orig_category":"Cajas De Ahorro",
    "sg:phone":"+34 956 72 01 86",
    "sg:postcode":"11648",
    "sg:province":"C\u00e1diz",
    "wof:name":"Caja San Fernando De Sevilla Y Jerez",
    "wof:placetype":"venue"
},
  "geometry": {"coordinates":[-5.8062767982,36.872089386],"type":"Point"}
}