{
  "type": "Feature",
  "properties": {
    "addr:full":"Calle de Sebastian Elcano, 6 Sevilla Sevilla 41011",
    "addr:housenumber":"6",
    "addr:postcode":"41011",
    "addr:street":"Calle De Sebastian Elcano",
    "iso:country":"ES",
    "sg:address":"Calle de Sebastian Elcano, 6",
    "sg:city":"Sevilla",
    "sg:orig_category":"M\u00c9dicos: Estomatolog\u00cda",
    "sg:phone":"+34 954 27 15 25",
    "sg:postcode":"41011",
    "sg:province":"Sevilla",
    "wof:name":"Tejada Enriquez Leopoldo",
    "wof:placetype":"venue"
},
  "geometry": {"coordinates":[-5.9963107109,37.378692627],"type":"Point"}
}