{
  "type": "Feature",
  "properties": {
    "addr:full":"Calle de Raimundo Rodriguez, 4 Caravaca Cruz Murcia 30400",
    "addr:housenumber":"4",
    "addr:postcode":"30400",
    "addr:street":"Calle De Raimundo Rodriguez",
    "iso:country":"ES",
    "sg:address":"Calle de Raimundo Rodriguez, 4",
    "sg:city":"Caravaca Cruz",
    "sg:orig_category":"Peluquer\u00cdas, Peluquer\u00cda Mixta",
    "sg:phone":"+34 968 70 24 06",
    "sg:postcode":"30400",
    "sg:province":"Murcia",
    "wof:name":"Francisco Valera Abril Pakos S.l.",
    "wof:placetype":"venue"
},
  "geometry": {"coordinates":[-1.857861042,38.1053466797],"type":"Point"}
}