{
  "type": "Feature",
  "properties": {
    "iso:country":"ES",
    "sg:address":"Carr Formentor, De, 15",
    "sg:city":"Puerto De Pollen\u00c7a",
    "sg:orig_category":"Art\u00cdculos De Regalo (al Por Menor)",
    "sg:phone":"+34 971 86 65 95",
    "sg:postcode":"07470",
    "sg:province":"Islas Baleares",
    "wof:name":"Culling Crocker Susana",
    "wof:placetype":"venue"
},
  "geometry": {"coordinates":[3.0821900368,39.9063034058],"type":"Point"}
}