{
  "type": "Feature",
  "properties": {
    "iso:country":"ES",
    "sg:address":"Plaz Palomas (de Las), 30",
    "sg:city":"Granada",
    "sg:orig_category":"Alimentaci\u00d3n General (al Por Menor)",
    "sg:phone":"+34 958 81 32 09",
    "sg:postcode":"18007",
    "sg:province":"Granada",
    "wof:name":"Junco Moleon Francisco",
    "wof:placetype":"venue"
},
  "geometry": {"coordinates":[-3.6018090248,37.1540756226],"type":"Point"}
}