{
  "type": "Feature",
  "properties": {
    "iso:country":"ES",
    "sg:address":"Cril. Contraparada, S/n",
    "sg:city":"Javali Viejo",
    "sg:orig_category":"Aguas (distribuci\u00d3n, Servicios)",
    "sg:phone":"+34 968 80 09 50",
    "sg:postcode":"30831",
    "sg:province":"Murcia",
    "wof:name":"Sociedad De Explotacion De Aguas Residuales S.a.",
    "wof:placetype":"venue"
},
  "geometry": {"coordinates":[-1.2009739876,37.9930839539],"type":"Point"}
}