{
  "type": "Feature",
  "properties": {
    "addr:full":"Calle de San Pedro, 34 Pasai S. Pedro Guip\u00f9zcoa 20110",
    "addr:housenumber":"34",
    "addr:postcode":"20110",
    "addr:street":"Calle De San Pedro;Pasai S.;Guipu\u0300Zcoa",
    "iso:country":"ES",
    "sg:address":"Calle de San Pedro, 34",
    "sg:city":"Pasai S. Pedro",
    "sg:orig_category":"Estudios Y Construcci\u00d3n De Acuarios Y Viveros",
    "sg:phone":"+34 943 39 40 78",
    "sg:postcode":"20110",
    "sg:province":"Guip\u00f9zcoa",
    "sg:website":"www.viverosiraeta.com",
    "wof:name":"Viveros Iraeta S.a.",
    "wof:placetype":"venue"
},
  "geometry": {"coordinates":[-1.9230277538,43.3254585266],"type":"Point"}
}