{
  "type": "Feature",
  "properties": {
    "iso:country":"ES",
    "sg:address":"Carrer de Francesc Marti I M, 1",
    "sg:city":"Palma",
    "sg:orig_category":"Lencer\u00cda Femenina, Corseter\u00cda, Trajes De Ba\u00d1o (al Por Menor)",
    "sg:phone":"+34 971 28 80 43",
    "sg:postcode":"07011",
    "sg:province":"Islas Baleares",
    "wof:name":"Grupo Garau C.b",
    "wof:placetype":"venue"
},
  "geometry": {"coordinates":[2.640171051,39.5784187317],"type":"Point"}
}