{
  "type": "Feature",
  "properties": {
    "iso:country":"ES",
    "sg:address":"Calle de Manzano, 22",
    "sg:city":"Don Benito",
    "sg:orig_category":"Escayola Y Productos De Escayola (fabricaci\u00d3n, Al Por Mayor)",
    "sg:phone":"+34 924 80 30 28",
    "sg:postcode":"06400",
    "sg:province":"Badajoz",
    "wof:name":"Flores Rodriguez Manuel",
    "wof:placetype":"venue"
},
  "geometry": {"coordinates":[-5.8551740646,38.9488945007],"type":"Point"}
}