{
  "type": "Feature",
  "properties": {
    "addr:full":"Calle de Huesca, 16 Colinas Zaragoza 50420",
    "addr:housenumber":"16",
    "addr:postcode":"50420",
    "addr:street":"Calle De Huesca",
    "iso:country":"ES",
    "sg:address":"Calle de Huesca, 16",
    "sg:city":"Colinas",
    "sg:orig_category":"Ingeniero",
    "sg:phone":"+34 976 12 61 39",
    "sg:postcode":"50420",
    "sg:province":"Zaragoza",
    "wof:name":"Cordova Alonso Eugenio",
    "wof:placetype":"venue"
},
  "geometry": {"coordinates":[-0.9601830244,41.5556411743],"type":"Point"}
}