{
  "type": "Feature",
  "properties": {
    "iso:country":"ES",
    "sg:address":"Rond Don Garcia, 18",
    "sg:city":"Salda\u00f1a",
    "sg:orig_category":"Fabricaci\u00d3n De Productos Textiles Sin Tejer",
    "sg:phone":"+34 979 89 01 96",
    "sg:postcode":"34100",
    "sg:province":"Palencia",
    "wof:name":"Garcia Martinez Maria Visitacion",
    "wof:placetype":"venue"
},
  "geometry": {"coordinates":[-4.7367730141,42.5208053589],"type":"Point"}
}