{
  "type": "Feature",
  "properties": {
    "addr:full":"Calle de Real, 178 Castilleja Cuesta Sevilla 41950",
    "addr:housenumber":"178",
    "addr:postcode":"41950",
    "addr:street":"Calle De Real",
    "iso:country":"ES",
    "sg:address":"Calle de Real, 178",
    "sg:city":"Castilleja Cuesta",
    "sg:orig_category":"Cajas De Ahorro",
    "sg:phone":"+34 954 16 90 72",
    "sg:postcode":"41950",
    "sg:province":"Sevilla",
    "sg:website":"www.unicaja.es",
    "wof:name":"Unicaja",
    "wof:placetype":"venue"
},
  "geometry": {"coordinates":[-6.0587887764,37.3851470947],"type":"Point"}
}