{
  "type": "Feature",
  "properties": {
    "iso:country":"ES",
    "sg:address":"Carrer de Major (sant Celoni), 170",
    "sg:city":"S. Celoni",
    "sg:orig_category":"Ense\u00d1anza: Idiomas",
    "sg:phone":"+34 938 67 04 94",
    "sg:postcode":"08470",
    "sg:province":"Barcelona",
    "wof:name":"Lopez Garcia Pedro",
    "wof:placetype":"venue"
},
  "geometry": {"coordinates":[2.4916799068,41.6899185181],"type":"Point"}
}