{
  "type": "Feature",
  "properties": {
    "addr:full":"Calle de Ntra. Sra De La Merced, 5 Burriana Castell\u00f3n 12530",
    "addr:housenumber":"5",
    "addr:postcode":"12530",
    "addr:street":"Calle De Ntra. Sra De La Merced",
    "iso:country":"ES",
    "sg:address":"Calle de Ntra. Sra De La Merced, 5",
    "sg:city":"Burriana",
    "sg:orig_category":"Droguer\u00cdas (al Por Menor)",
    "sg:phone":"+34 964 51 86 11",
    "sg:postcode":"12530",
    "sg:province":"Castell\u00f3n",
    "wof:name":"Paqueteria Mari Carmen",
    "wof:placetype":"venue"
},
  "geometry": {"coordinates":[-0.0852660015,39.8894195557],"type":"Point"}
}