{
  "type": "Feature",
  "properties": {
    "iso:country":"ES",
    "sg:address":"Avda Elvas, S/n",
    "sg:city":"Badajoz",
    "sg:orig_category":"Transportes Por V\u00cdas Navegables",
    "sg:phone":"+34 924 14 05 35",
    "sg:postcode":"06006",
    "sg:province":"Badajoz",
    "wof:name":"Catanotrans S.l.",
    "wof:placetype":"venue"
},
  "geometry": {"coordinates":[-7.0134840012,38.8817253113],"type":"Point"}
}