{
  "type": "Feature",
  "properties": {
    "addr:full":"Via Augusta, 186 Barcelona Barcelona 08021",
    "addr:housenumber":"186",
    "addr:postcode":"08021",
    "addr:street":"Via Augusta",
    "iso:country":"ES",
    "sg:address":"Via Augusta, 186",
    "sg:city":"Barcelona",
    "sg:orig_category":"Aparcamientos (infraestructuras, Accesorios)",
    "sg:phone":"+34 932 09 77 88",
    "sg:postcode":"08021",
    "sg:province":"Barcelona",
    "wof:name":"Auto Industria Alfredo Vazquez D. Y Cia S.r.c.",
    "wof:placetype":"venue"
},
  "geometry": {"coordinates":[2.1418380737,41.3984298706],"type":"Point"}
}