{
  "type": "Feature",
  "properties": {
    "addr:full":"Mijas, 6 Manilva M\u00e1laga 29692",
    "addr:housenumber":"6",
    "addr:postcode":"29692",
    "addr:street":"Mijas",
    "iso:country":"ES",
    "sg:address":"Mijas, 6",
    "sg:city":"Manilva",
    "sg:orig_category":"Transportes Por V\u00cdas Navegables",
    "sg:phone":"+34 952 89 02 40",
    "sg:postcode":"29692",
    "sg:province":"M\u00e1laga",
    "wof:name":"Aguilar Cano Manuel",
    "wof:placetype":"venue"
},
  "geometry": {"coordinates":[-4.6783003807,36.5039825439],"type":"Point"}
}