{
  "type": "Feature",
  "properties": {
    "iso:country":"ES",
    "sg:address":"Pase Zumaquera, 16",
    "sg:city":"Vitoria-gasteiz",
    "sg:orig_category":"Molduras, Junquillos, Listones Y Molduras Perforadas",
    "sg:phone":"+34 945 13 36 04",
    "sg:postcode":"01006",
    "sg:province":"\u00c1lava",
    "wof:name":"Garcia Diaz Marina",
    "wof:placetype":"venue"
},
  "geometry": {"coordinates":[-2.6623649597,42.8365898132],"type":"Point"}
}