{
  "type": "Feature",
  "properties": {
    "addr:full":"Calle de Madro\u00d1o (del), 26 Humanes De Madrid Madrid 28970",
    "addr:housenumber":"26",
    "addr:postcode":"28970",
    "addr:street":"Calle De Madron\u0303O Del",
    "iso:country":"ES",
    "sg:address":"Calle de Madro\u00d1o (del), 26",
    "sg:city":"Humanes De Madrid",
    "sg:orig_category":"Suministros Para Exposiciones, Ferias, Salones",
    "sg:phone":"+34 914 98 02 32",
    "sg:postcode":"28970",
    "sg:province":"Madrid",
    "wof:name":"Uria Garcia Manuel Salvador",
    "wof:placetype":"venue"
},
  "geometry": {"coordinates":[-3.8094789982,40.2665519714],"type":"Point"}
}