{
  "type": "Feature",
  "properties": {
    "iso:country":"ES",
    "sg:address":"Avda Pintor Felo Monzon, S/n",
    "sg:city":"Palmas De Gran Canaria",
    "sg:orig_category":"Ropa Para Ni\u00d1os (al Por Menor)",
    "sg:phone":"+34 928 42 26 08",
    "sg:postcode":"35019",
    "sg:province":"Las Palmas",
    "sg:website":"www.e-stradivarius.com",
    "wof:name":"Depositos Y Almacenes Numero-1 S.a.",
    "wof:placetype":"venue"
},
  "geometry": {"coordinates":[-15.4527931213,28.1041984558],"type":"Point"}
}