{
  "type": "Feature",
  "properties": {
    "addr:full":"Rua Vazquez Varela, 19 Vigo Pontevedra 36204",
    "addr:housenumber":"19",
    "addr:postcode":"36204",
    "addr:street":"Rua Vazquez Varela",
    "iso:country":"ES",
    "sg:address":"Rua Vazquez Varela, 19",
    "sg:city":"Vigo",
    "sg:orig_category":"Mec\u00c1nico Del Autom\u00d3vil",
    "sg:phone":"+34 986 47 10 36",
    "sg:postcode":"36204",
    "sg:province":"Pontevedra",
    "wof:name":"Barreiro Alvarez Alfonso Modesto",
    "wof:placetype":"venue"
},
  "geometry": {"coordinates":[-8.7144184113,42.2321472168],"type":"Point"}
}