{
  "type": "Feature",
  "properties": {
    "iso:country":"ES",
    "sg:address":"C/ Sant Joan Bosco, 8",
    "sg:city":"Alcoi",
    "sg:orig_category":"Pintura, Barniz, Productos Asimilables (fabricaci\u00d3n, Al Por Mayor)",
    "sg:phone":"+34 965 33 36 41",
    "sg:postcode":"03804",
    "sg:province":"Alicante",
    "wof:name":"Pinturas Arte Nuevo S.l.",
    "wof:placetype":"venue"
},
  "geometry": {"coordinates":[-0.4655059874,38.7107162476],"type":"Point"}
}