{
  "type": "Feature",
  "properties": {
    "addr:full":"Calle de Juan Ramon Jimenez, 6 Alcala Rio Sevilla 41200",
    "addr:housenumber":"6",
    "addr:postcode":"41200",
    "addr:street":"Calle De Juan Ramon Jimenez",
    "iso:country":"ES",
    "sg:address":"Calle de Juan Ramon Jimenez, 6",
    "sg:city":"Alcala Rio",
    "sg:orig_category":"Farmacias",
    "sg:phone":"+34 954 78 03 29",
    "sg:postcode":"41200",
    "sg:province":"Sevilla",
    "wof:name":"Jimenez Sanchez Jose",
    "wof:placetype":"venue"
},
  "geometry": {"coordinates":[-5.9833860397,37.521987915],"type":"Point"}
}