{
  "type": "Feature",
  "properties": {
    "addr:full":"Logro\u00f1o, 2 Castrillo Val Burgos 09193",
    "addr:housenumber":"2",
    "addr:postcode":"09193",
    "addr:street":"Logron\u0303O",
    "iso:country":"ES",
    "sg:address":"Logro\u00f1o, 2",
    "sg:city":"Castrillo Val",
    "sg:orig_category":"Delegados, Agentes De Tr\u00c1nsito, Auxiliares De Transporte Internacional",
    "sg:phone":"+34 947 42 14 68",
    "sg:postcode":"09193",
    "sg:province":"Burgos",
    "wof:name":"De Domingo Pe\u00f1acoba Fermin",
    "wof:placetype":"venue"
},
  "geometry": {"coordinates":[-3.567761898,42.3331336975],"type":"Point"}
}