{
  "type": "Feature",
  "properties": {
    "iso:country":"ES",
    "sg:address":"Plaz Lamera Txiki, 1",
    "sg:city":"Bermeo",
    "sg:orig_category":"Congelados: Productos Alimentarios (al Por Menor)",
    "sg:phone":"+34 946 88 21 74",
    "sg:postcode":"48370",
    "sg:province":"Vizcaya",
    "wof:name":"Maite Luge Bego\u00f1a Elorza-biotza Goitia Lizarralde C.b.",
    "wof:placetype":"venue"
},
  "geometry": {"coordinates":[-2.7251009941,43.41929245],"type":"Point"}
}