{
  "type": "Feature",
  "properties": {
    "iso:country":"ES",
    "sg:address":"Carrer de Pins, 21",
    "sg:city":"Hospitalet Llobregat",
    "sg:orig_category":"Estancos",
    "sg:phone":"+34 934 38 14 86",
    "sg:postcode":"08905",
    "sg:province":"Barcelona",
    "wof:name":"Vital Garrote Francisca",
    "wof:placetype":"venue"
},
  "geometry": {"coordinates":[2.1083800793,41.3679084778],"type":"Point"}
}