{
  "type": "Feature",
  "properties": {
    "addr:full":"Calle de Madrazo, 5 Tafira Alta Las Palmas 35017",
    "addr:housenumber":"5",
    "addr:postcode":"35017",
    "addr:street":"Calle De Madrazo;Alta",
    "iso:country":"ES",
    "sg:address":"Calle de Madrazo, 5",
    "sg:city":"Tafira Alta",
    "sg:orig_category":"M\u00c9dicos: Estomatolog\u00cda",
    "sg:phone":"+34 928 35 05 47",
    "sg:postcode":"35017",
    "sg:province":"Las Palmas",
    "wof:name":"Navarro Leon Pablo Jesus",
    "wof:placetype":"venue"
},
  "geometry": {"coordinates":[-15.4664802551,28.0519676208],"type":"Point"}
}