{
  "type": "Feature",
  "properties": {
    "addr:full":"Calle de Alonso Cano, 28 Madrid Madrid 28003",
    "addr:housenumber":"28",
    "addr:postcode":"madrid;28003",
    "addr:street":"Calle De Alonso Cano",
    "iso:country":"ES",
    "sg:address":"Calle de Alonso Cano, 28",
    "sg:city":"Madrid",
    "sg:orig_category":"Promotores Constructores",
    "sg:phone":"+34 914 41 15 68",
    "sg:postcode":"28003",
    "sg:province":"Madrid",
    "wof:name":"Comunidad De Propietarios C/ Alonso Cano,28",
    "wof:placetype":"venue"
},
  "geometry": {"coordinates":[-3.6976492405,40.4398727417],"type":"Point"}
}