{
  "type": "Feature",
  "properties": {
    "addr:full":"Carr Monestir De Lavaix (del), 14 Pont Suert Lleida 25520",
    "addr:housenumber":"14",
    "addr:postcode":"25520",
    "addr:street":"Carr Monestir De Lavaix Del",
    "iso:country":"ES",
    "sg:address":"Carr Monestir De Lavaix (del), 14",
    "sg:city":"Pont Suert",
    "sg:orig_category":"Florister\u00cdas",
    "sg:phone":"+34 973 69 02 76",
    "sg:postcode":"25520",
    "sg:province":"Lleida",
    "wof:name":"Morancho Farre Carlos",
    "wof:placetype":"venue"
},
  "geometry": {"coordinates":[0.7424060106,42.4047966003],"type":"Point"}
}