{
  "type": "Feature",
  "properties": {
    "iso:country":"ES",
    "sg:address":"Pg Joan Carles I, S/n",
    "sg:city":"Eivissa",
    "sg:orig_category":"Pr\u00c1ctica De Vela, Navegaci\u00d3n Y Deportes N\u00c1uticos Y Acu\u00c1ticos",
    "sg:phone":"+34 971 19 31 04",
    "sg:postcode":"07800",
    "sg:province":"Islas Baleares",
    "sg:website":"www.velmari.com",
    "wof:name":"Ibizasub S.l.",
    "wof:placetype":"venue"
},
  "geometry": {"coordinates":[1.4466700554,38.9146118164],"type":"Point"}
}