{
  "type": "Feature",
  "properties": {
    "addr:full":"Carr Picassent, 6 Almussafes Valencia 46440",
    "addr:housenumber":"6",
    "addr:postcode":"46440",
    "addr:street":"Carr Picassent",
    "iso:country":"ES",
    "sg:address":"Carr Picassent, 6",
    "sg:city":"Almussafes",
    "sg:orig_category":"Plomeros",
    "sg:phone":"+34 961 78 38 49",
    "sg:postcode":"46440",
    "sg:province":"Valencia",
    "wof:name":"Fontaneria Salvador Lladosa S.l.",
    "wof:placetype":"venue"
},
  "geometry": {"coordinates":[-0.4217630029,39.3039321899],"type":"Point"}
}