{
  "type": "Feature",
  "properties": {
    "addr:full":"Calle de Tinte, 23 Albacete Albacete 02002",
    "addr:housenumber":"23",
    "addr:postcode":"02002",
    "addr:street":"Calle De Tinte",
    "iso:country":"ES",
    "sg:address":"Calle de Tinte, 23",
    "sg:city":"Albacete",
    "sg:orig_category":"\u00d3ptica: Instrumentos (fabricaci\u00d3n)",
    "sg:phone":"+34 967 21 75 68",
    "sg:postcode":"02002",
    "sg:province":"Albacete",
    "wof:name":"Optica Lola Marin",
    "wof:placetype":"venue"
},
  "geometry": {"coordinates":[-1.85432899,38.9925308228],"type":"Point"}
}