{
  "type": "Feature",
  "properties": {
    "iso:country":"ES",
    "sg:address":"Cust Del Hospital, 40",
    "sg:city":"Benavente",
    "sg:orig_category":"Abogados",
    "sg:phone":"+34 980 63 75 33",
    "sg:postcode":"49600",
    "sg:province":"Zamora",
    "wof:name":"Gil De Dios Carlos",
    "wof:placetype":"venue"
},
  "geometry": {"coordinates":[-5.676928997,42.0049705505],"type":"Point"}
}