{
  "type": "Feature",
  "properties": {
    "iso:country":"ES",
    "sg:address":"Avgd Joan Carles I, 30",
    "sg:city":"Pedreguer",
    "sg:orig_category":"Electricidad: Instaladores",
    "sg:phone":"+34 965 76 06 60",
    "sg:postcode":"03750",
    "sg:province":"Alicante",
    "wof:name":"Artes Carrio Electrificat S.l.",
    "wof:placetype":"venue"
},
  "geometry": {"coordinates":[0.0381061994,38.798866272],"type":"Point"}
}