{
  "type": "Feature",
  "properties": {
    "iso:country":"ES",
    "sg:address":"Carr Juan De Juanes, 13",
    "sg:city":"Benetusser",
    "sg:orig_category":"Venta Al Preg\u00d3n",
    "sg:phone":"+34 963 76 34 19",
    "sg:postcode":"46910",
    "sg:province":"Valencia",
    "wof:name":"Toro Moreno Jose Manuel",
    "wof:placetype":"venue"
},
  "geometry": {"coordinates":[-0.399435997,39.4233970642],"type":"Point"}
}