{
  "type": "Feature",
  "properties": {
    "iso:country":"ES",
    "sg:address":"Calle de Conde Valmaseda, 36",
    "sg:city":"Puertollano",
    "sg:orig_category":"Internados & Ense\u00d1anza Privada",
    "sg:phone":"+34 926 42 97 90",
    "sg:postcode":"13500",
    "sg:province":"Ciudad Real",
    "wof:name":"Hermanas De La Compa\u00f1ia De La Cruz",
    "wof:placetype":"venue"
},
  "geometry": {"coordinates":[-4.1144456863,38.6856079102],"type":"Point"}
}