{
  "type": "Feature",
  "properties": {
    "iso:country":"ES",
    "sg:address":"Carrer de Manuel Bertrand, 31",
    "sg:city":"Prat Llobregat",
    "sg:orig_category":"Ebanister\u00cda",
    "sg:phone":"+34 933 79 52 44",
    "sg:postcode":"08820",
    "sg:province":"Barcelona",
    "wof:name":"Olmedo Gaspez Antonio",
    "wof:placetype":"venue"
},
  "geometry": {"coordinates":[2.0960469246,41.3299942017],"type":"Point"}
}