{
  "type": "Feature",
  "properties": {
    "iso:country":"ES",
    "sg:address":"Calle de Blasco Iba\u00d1ez, 58",
    "sg:city":"Albacete",
    "sg:orig_category":"Asociaciones, Organismos Culturales Y Socioeducativos",
    "sg:phone":"+34 967 50 66 64",
    "sg:postcode":"02004",
    "sg:province":"Albacete",
    "wof:name":"Asociacion Ateneo Racionalista",
    "wof:placetype":"venue"
},
  "geometry": {"coordinates":[-1.8652757406,38.9937744141],"type":"Point"}
}