{
  "type": "Feature",
  "properties": {
    "iso:country":"ES",
    "sg:address":"Ctra Sagunto-burgos, Km. 0062,0",
    "sg:city":"Barracas",
    "sg:orig_category":"Peleter\u00cdas",
    "sg:phone":"+34 964 12 11 28",
    "sg:postcode":"12420",
    "sg:province":"Castell\u00f3n",
    "wof:name":"Fernandez Costa Vicenta",
    "wof:placetype":"venue"
},
  "geometry": {"coordinates":[-0.6965289712,40.0147514343],"type":"Point"}
}