{
  "type": "Feature",
  "properties": {
    "iso:country":"ES",
    "sg:address":"Carrer de Mare De Deu De Port, 383",
    "sg:city":"Barcelona",
    "sg:orig_category":"Masajistas Kinesiterapeutas",
    "sg:phone":"+34 932 96 62 28",
    "sg:postcode":"08038",
    "sg:province":"Barcelona",
    "wof:name":"Diaz Diaz Filomena",
    "wof:placetype":"venue"
},
  "geometry": {"coordinates":[2.1393749714,41.3631591797],"type":"Point"}
}