{
  "type": "Feature",
  "properties": {
    "iso:country":"ES",
    "sg:address":"Carr Estacio, 7",
    "sg:city":"Riudellots Selva",
    "sg:orig_category":"Estancos",
    "sg:phone":"+34 972 47 71 94",
    "sg:postcode":"17457",
    "sg:province":"Girona",
    "wof:name":"Xifre Quintana Gemma",
    "wof:placetype":"venue"
},
  "geometry": {"coordinates":[1.0761109591,41.086227417],"type":"Point"}
}