{
  "type": "Feature",
  "properties": {
    "addr:full":"Ctra. Binefar, Km. 0015,5 Esplus Huesca 22535",
    "addr:postcode":"22535",
    "addr:street":"Ctra. Binefar Km. 0015,5 Esplus",
    "iso:country":"ES",
    "sg:address":"Ctra. Binefar, Km. 0015,5",
    "sg:city":"Esplus",
    "sg:orig_category":"Granos Y Forrajes",
    "sg:phone":"+34 974 43 50 35",
    "sg:postcode":"22535",
    "sg:province":"Huesca",
    "wof:name":"Sociedad Agraria De Transformacion S.a.t. 1039",
    "wof:placetype":"venue"
},
  "geometry": {"coordinates":[0.2760890126,41.7985343933],"type":"Point"}
}