{
  "type": "Feature",
  "properties": {
    "iso:country":"ES",
    "sg:address":"Calle de Heroe De Sostoa, 80",
    "sg:city":"Malaga",
    "sg:orig_category":"Institutos De Belleza",
    "sg:phone":"+34 952 34 49 98",
    "sg:postcode":"29002",
    "sg:province":"M\u00e1laga",
    "wof:name":"Villanueva Molina Maria De Los Angeles",
    "wof:placetype":"venue"
},
  "geometry": {"coordinates":[-4.435833931,36.7076263428],"type":"Point"}
}