{
  "type": "Feature",
  "properties": {
    "iso:country":"ES",
    "sg:address":"Barr Ladredo, 130",
    "sg:city":"Camargo",
    "sg:orig_category":"Molduras, Junquillos, Listones Y Molduras Perforadas",
    "sg:phone":"+34 942 25 89 36",
    "sg:postcode":"39609",
    "sg:province":"Cantabria",
    "wof:name":"Aguero Aedo Maria Del Carmen",
    "wof:placetype":"venue"
},
  "geometry": {"coordinates":[-3.880712986,43.4033355713],"type":"Point"}
}