{
  "type": "Feature",
  "properties": {
    "iso:country":"ES",
    "sg:address":"Calle de Palau, Del, 6",
    "sg:city":"Benaguasil",
    "sg:orig_category":"Cajas Para Embalar",
    "sg:phone":"+34 962 73 76 17",
    "sg:postcode":"46180",
    "sg:province":"Valencia",
    "sg:website":"www.cajacampo.es",
    "wof:name":"Caja Campo",
    "wof:placetype":"venue"
},
  "geometry": {"coordinates":[-0.5875390172,39.5956382751],"type":"Point"}
}