{
  "type": "Feature",
  "properties": {
    "iso:country":"ES",
    "sg:address":"Calle de Alcalde Gomez Gomez, 38",
    "sg:city":"Malaga",
    "sg:orig_category":"Mec\u00c1nico Del Autom\u00d3vil",
    "sg:phone":"+34 952 34 54 47",
    "sg:postcode":"29006",
    "sg:province":"M\u00e1laga",
    "wof:name":"Salvador Juarez Angel",
    "wof:placetype":"venue"
},
  "geometry": {"coordinates":[-4.4799141884,36.7102851868],"type":"Point"}
}