{
  "type": "Feature",
  "properties": {
    "iso:country":"ES",
    "sg:address":"Ctra Madrid Valencia, Km. 0324,2",
    "sg:city":"Chiva",
    "sg:orig_category":"Carros Elevadores, Carros De Operaciones Portuarias",
    "sg:phone":"+34 961 80 45 85",
    "sg:postcode":"46370",
    "sg:province":"Valencia",
    "sg:website":"www.fsamanutencion.com",
    "wof:name":"Finanzauto S.a.",
    "wof:placetype":"venue"
},
  "geometry": {"coordinates":[-0.7306780219,39.4573898315],"type":"Point"}
}