{
  "type": "Feature",
  "properties": {
    "addr:full":"Muel Tomas Olabarri, 7 Arenas -areeta Vizcaya 48930",
    "addr:housenumber":"7;areeta",
    "addr:postcode":"48930",
    "addr:street":"Tomas Olabarri",
    "iso:country":"ES",
    "sg:address":"Muel Tomas Olabarri, 7",
    "sg:city":"Arenas -areeta",
    "sg:orig_category":"Peluquer\u00cdas",
    "sg:phone":"+34 944 80 18 07",
    "sg:postcode":"48930",
    "sg:province":"Vizcaya",
    "wof:name":"Serrano Ropero Enrique",
    "wof:placetype":"venue"
},
  "geometry": {"coordinates":[-3.0140271187,43.3218154907],"type":"Point"}
}