{
  "type": "Feature",
  "properties": {
    "addr:full":"Avda Reyes Catolicos, S/n Chiclana De La Frontera C\u00e1diz 11130",
    "addr:housenumber":"s / n",
    "addr:postcode":"11130",
    "addr:street":"Avda Reyes Catolicos",
    "iso:country":"ES",
    "sg:address":"Avda Reyes Catolicos, S/n",
    "sg:city":"Chiclana De La Frontera",
    "sg:orig_category":"M\u00c9dicos: Estomatolog\u00cda",
    "sg:phone":"+34 956 53 26 61",
    "sg:postcode":"11130",
    "sg:province":"C\u00e1diz",
    "wof:name":"Hernandez Bernal Jose Antonio",
    "wof:placetype":"venue"
},
  "geometry": {"coordinates":[-6.1430988312,36.4142036438],"type":"Point"}
}