{
  "type": "Feature",
  "properties": {
    "addr:full":"Pg Sant Joan, 194 Manlleu Barcelona 08560",
    "addr:housenumber":"194",
    "addr:postcode":"08560",
    "addr:street":"Pg Sant Joan",
    "iso:country":"ES",
    "sg:address":"Pg Sant Joan, 194",
    "sg:city":"Manlleu",
    "sg:orig_category":"Molduras, Junquillos, Listones Y Molduras Perforadas",
    "sg:phone":"+34 938 51 15 86",
    "sg:postcode":"08560",
    "sg:province":"Barcelona",
    "wof:name":"Scoop S.c.p.",
    "wof:placetype":"venue"
},
  "geometry": {"coordinates":[2.2819519043,42.00623703],"type":"Point"}
}