{
  "type": "Feature",
  "properties": {
    "addr:full":"Avda Jose Ortiz, 118 Almazora Castell\u00f3n 12550",
    "addr:housenumber":"118",
    "addr:postcode":"12550",
    "addr:street":"Avda Jose Ortiz",
    "iso:country":"ES",
    "sg:address":"Avda Jose Ortiz, 118",
    "sg:city":"Almazora",
    "sg:orig_category":"Alimentaci\u00d3n General (al Por Menor)",
    "sg:phone":"+34 964 56 06 99",
    "sg:postcode":"12550",
    "sg:province":"Castell\u00f3n",
    "wof:name":"Guarch Querol Maria Cruz",
    "wof:placetype":"venue"
},
  "geometry": {"coordinates":[-0.0668679029,39.9522590637],"type":"Point"}
}