{
  "type": "Feature",
  "properties": {
    "addr:full":"Ctra Murcia, Km. 0176,0 Baza Granada 18800",
    "addr:postcode":"18800",
    "addr:street":"Ctra Murcia Km. 0176,0",
    "iso:country":"ES",
    "sg:address":"Ctra Murcia, Km. 0176,0",
    "sg:city":"Baza",
    "sg:orig_category":"Muebles, Minoristas",
    "sg:phone":"+34 958 86 08 42",
    "sg:postcode":"18800",
    "sg:province":"Granada",
    "sg:website":"www.sofasdecor.com",
    "wof:name":"Sofa Y Confort Prestige S.l.",
    "wof:placetype":"venue"
},
  "geometry": {"coordinates":[-2.7616488934,37.4945487976],"type":"Point"}
}