{
  "type": "Feature",
  "properties": {
    "addr:full":"Calle de Goikosoloa, 2 Basauri Vizcaya 48970",
    "addr:housenumber":"2",
    "addr:postcode":"48970",
    "addr:street":"Calle De Goikosoloa",
    "iso:country":"ES",
    "sg:address":"Calle de Goikosoloa, 2",
    "sg:city":"Basauri",
    "sg:orig_category":"Cristaler\u00cdas",
    "sg:phone":"+34 944 26 14 97",
    "sg:postcode":"48970",
    "sg:province":"Vizcaya",
    "wof:name":"Cristaleria Uribarri",
    "wof:placetype":"venue"
},
  "geometry": {"coordinates":[-2.8835439682,43.2382011414],"type":"Point"}
}