{
  "type": "Feature",
  "properties": {
    "addr:full":"Avda Pulpites (los), 22 Torres Cotillas Murcia 30565",
    "addr:housenumber":"22",
    "addr:postcode":"30565",
    "addr:street":"Avda Pulpites Los",
    "iso:country":"ES",
    "sg:address":"Avda Pulpites (los), 22",
    "sg:city":"Torres Cotillas",
    "sg:orig_category":"Caf\u00c9s, Bares, Cervecer\u00cdas",
    "sg:phone":"+34 968 62 86 09",
    "sg:postcode":"30565",
    "sg:province":"Murcia",
    "wof:name":"Mu\u00f1oz Perez Jose",
    "wof:placetype":"venue"
},
  "geometry": {"coordinates":[-1.2368090153,38.0214118958],"type":"Point"}
}