{
  "type": "Feature",
  "properties": {
    "iso:country":"ES",
    "sg:address":"Calle de Escultor Salzillo, 28",
    "sg:city":"Cieza",
    "sg:orig_category":"Estancos",
    "sg:phone":"+34 968 45 51 87",
    "sg:postcode":"30530",
    "sg:province":"Murcia",
    "wof:name":"Marin Aroca Juana",
    "wof:placetype":"venue"
},
  "geometry": {"coordinates":[-1.4178960323,38.2407035828],"type":"Point"}
}