{
  "type": "Feature",
  "properties": {
    "iso:country":"ES",
    "sg:address":"Calle de Doctor Pasteur, 2",
    "sg:city":"Huercal-overa",
    "sg:orig_category":"Arquitectos",
    "sg:phone":"+34 950 13 42 93",
    "sg:postcode":"04600",
    "sg:province":"Almer\u00eda",
    "wof:name":"Berbel Fernandez Diego",
    "wof:placetype":"venue"
},
  "geometry": {"coordinates":[-1.9431929588,37.3947868347],"type":"Point"}
}