{
  "type": "Feature",
  "properties": {
    "iso:country":"ES",
    "sg:address":"Rua Cruceiro De Sar (do), 2",
    "sg:city":"Santiago De Compostela",
    "sg:orig_category":"Molduras, Junquillos, Listones Y Molduras Perforadas",
    "sg:phone":"+34 981 59 63 61",
    "sg:postcode":"15702",
    "sg:province":"La Coru\u00f1a",
    "wof:name":"Amosa Iglesias Juan Carlos",
    "wof:placetype":"venue"
},
  "geometry": {"coordinates":[-8.5331106186,42.8696746826],"type":"Point"}
}