{
  "type": "Feature",
  "properties": {
    "iso:country":"ES",
    "sg:address":"Luga Lomo Sordo, S/n",
    "sg:city":"Pardilla",
    "sg:orig_category":"Asociaciones Y Clubs Deportivos",
    "sg:phone":"+34 928 68 22 85",
    "sg:postcode":"35200",
    "sg:province":"Las Palmas",
    "wof:name":"Comunidad De Propietarios De La Instalaciones Deportivas La Pardilla",
    "wof:placetype":"venue"
},
  "geometry": {"coordinates":[-15.4144220352,28.0029888153],"type":"Point"}
}