{
  "type": "Feature",
  "properties": {
    "iso:country":"ES",
    "sg:address":"Carrer de Santa Eugenia (de), 13",
    "sg:city":"Vilassar De Mar",
    "sg:orig_category":"Centros De Coordinaci\u00d3n",
    "sg:phone":"+34 937 59 17 20",
    "sg:postcode":"08340",
    "sg:province":"Barcelona",
    "wof:name":"Asesoria Aznarez S.l.",
    "wof:placetype":"venue"
},
  "geometry": {"coordinates":[2.3843157291,41.5021095276],"type":"Point"}
}