{
  "type": "Feature",
  "properties": {
    "iso:country":"ES",
    "sg:address":"Calle de Geranio, 30",
    "sg:city":"Puebla Alfinden",
    "sg:orig_category":"Negocio De Materiales De Construcci\u00d3n",
    "sg:phone":"+34 976 45 56 80",
    "sg:postcode":"50171",
    "sg:province":"Zaragoza",
    "sg:website":"www.feyma25.com",
    "wof:name":"Feyma-25 S. L.",
    "wof:placetype":"venue"
},
  "geometry": {"coordinates":[-0.7696269751,41.6400375366],"type":"Point"}
}