{
  "type": "Feature",
  "properties": {
    "addr:full":"Avda Constitucion (de La), 22 Pedro Mu\u00e7oz Ciudad Real 13620",
    "addr:housenumber":"22",
    "addr:postcode":"13620",
    "addr:street":"Avda Constitucion De La;Pedro Muc\u0327Oz",
    "iso:country":"ES",
    "sg:address":"Avda Constitucion (de La), 22",
    "sg:city":"Pedro Mu\u00e7oz",
    "sg:orig_category":"Piedras Artificiales",
    "sg:phone":"+34 926 58 61 15",
    "sg:postcode":"13620",
    "sg:province":"Ciudad Real",
    "wof:name":"Fernandez Ruiz Miguel Angel",
    "wof:placetype":"venue"
},
  "geometry": {"coordinates":[-2.955878973,39.4055213928],"type":"Point"}
}