{
  "type": "Feature",
  "properties": {
    "iso:country":"ES",
    "sg:address":"Carr Forn De Vidre, 22",
    "sg:city":"Vilanova I La Geltru",
    "sg:classifiers":[
        {
            "category":"Professional",
            "subcategory":"Business Services",
            "type":"Services"
        }
    ],
    "sg:phone":"+34 938 10 55 68",
    "sg:postcode":"08800",
    "sg:province":"Barcelona",
    "sg:tags":[
        "control",
        "asesor\u00cda",
        "organizaci\u00d3n",
        "la",
        "de",
        "gesti\u00d3n",
        "y"
    ],
    "sg:website":"www.matdeco.org",
    "wof:name":"Mtd Grup De Gestio S.l.",
    "wof:placetype":"venue"
},
  "geometry": {"coordinates":[1.7298460007,41.2203941345],"type":"Point"}
}