{
  "type": "Feature",
  "properties": {
    "iso:country":"ES",
    "sg:address":"Calle de La Alegria De La Huerta, 22",
    "sg:city":"Madrid",
    "sg:orig_category":"Peluquer\u00cdas, Peluquer\u00cda Mixta",
    "sg:phone":"+34 917 95 21 31",
    "sg:postcode":"28041",
    "sg:province":"Madrid",
    "wof:name":"Mingorance Saez Tomas",
    "wof:placetype":"venue"
},
  "geometry": {"coordinates":[-3.6953880787,40.3534736633],"type":"Point"}
}