{
  "type": "Feature",
  "properties": {
    "iso:country":"ES",
    "sg:address":"Calle de Miguel Servet, 34",
    "sg:city":"Albacete",
    "sg:orig_category":"Papeler\u00cdas, Librer\u00cdas",
    "sg:phone":"+34 967 23 69 04",
    "sg:postcode":"02006",
    "sg:province":"Albacete",
    "wof:name":"Palomares Pastor Anastasia",
    "wof:placetype":"venue"
},
  "geometry": {"coordinates":[-1.8738119602,38.9959335327],"type":"Point"}
}