{
  "type": "Feature",
  "properties": {
    "iso:country":"ES",
    "sg:address":"Calle de Alberquilla, 83",
    "sg:city":"Guare\u00f1a",
    "sg:orig_category":"Cajas Y Embalajes De Madera",
    "sg:phone":"+34 924 35 09 02",
    "sg:postcode":"06470",
    "sg:province":"Badajoz",
    "wof:name":"Gomez Rodriguez Ramon",
    "wof:placetype":"venue"
},
  "geometry": {"coordinates":[-6.0932102203,38.8583526611],"type":"Point"}
}