{
  "type": "Feature",
  "properties": {
    "iso:country":"ES",
    "sg:address":"Calle de Daoiz Y Velarde, 19",
    "sg:city":"Socuellamos",
    "sg:classifiers":[
        {
            "category":"Taxi",
            "type":"Transportation"
        }
    ],
    "sg:phone":"+34 926 53 10 36",
    "sg:postcode":"13630",
    "sg:province":"Ciudad Real",
    "wof:name":"Ambulancia Y Taxis Evaristo S.l.",
    "wof:placetype":"venue"
},
  "geometry": {"coordinates":[-2.7819654942,39.280670166],"type":"Point"}
}