{
  "type": "Feature",
  "properties": {
    "iso:country":"ES",
    "sg:address":"Calle de Real, 20",
    "sg:city":"Almendralejo",
    "sg:orig_category":"Abogados",
    "sg:phone":"+34 924 66 09 35",
    "sg:postcode":"06200",
    "sg:province":"Badajoz",
    "wof:name":"Montero Vargas-zu\u00f1iga Luis Maria",
    "wof:placetype":"venue"
},
  "geometry": {"coordinates":[-6.4073390961,38.6840515137],"type":"Point"}
}