{
  "type": "Feature",
  "properties": {
    "iso:country":"ES",
    "sg:address":"Calle de Octubre, 16",
    "sg:city":"Madrid",
    "sg:orig_category":"Garajes De Veh\u00cdculos",
    "sg:phone":"+34 917 47 05 06",
    "sg:postcode":"28022",
    "sg:province":"Madrid",
    "wof:name":"Pinturas Mundocolor S.l.",
    "wof:placetype":"venue"
},
  "geometry": {"coordinates":[-3.567481041,40.446598053],"type":"Point"}
}