{
  "type": "Feature",
  "properties": {
    "addr:full":"Carrer de Sardenya, 257 Barcelona Barcelona 08013",
    "addr:housenumber":"257",
    "addr:postcode":"08013",
    "addr:street":"Carrer De Sardenya",
    "iso:country":"ES",
    "sg:address":"Carrer de Sardenya, 257",
    "sg:city":"Barcelona",
    "sg:orig_category":"Mec\u00c1nico Del Autom\u00d3vil",
    "sg:phone":"+34 934 58 23 64",
    "sg:postcode":"08013",
    "sg:province":"Barcelona",
    "wof:name":"Iba\u00f1ez Oca\u00f1a Anselmo",
    "wof:placetype":"venue"
},
  "geometry": {"coordinates":[2.1756958961,41.4013977051],"type":"Point"}
}