{
  "type": "Feature",
  "properties": {
    "addr:full":"Calle de Horno, 2 Ayora Valencia 46620",
    "addr:housenumber":"2",
    "addr:postcode":"46620",
    "addr:street":"Calle De Horno",
    "iso:country":"ES",
    "sg:address":"Calle de Horno, 2",
    "sg:city":"Ayora",
    "sg:orig_category":"Reposter\u00cdas",
    "sg:phone":"+34 962 19 11 62",
    "sg:postcode":"46620",
    "sg:province":"Valencia",
    "wof:name":"Rosendo Honrubia Sanchez Sl",
    "wof:placetype":"venue"
},
  "geometry": {"coordinates":[-1.0557589531,39.0590896606],"type":"Point"}
}