{
  "type": "Feature",
  "properties": {
    "iso:country":"ES",
    "sg:address":"Parque Antonio Gomez Felipe, 43",
    "sg:city":"Los Llanos Aridane",
    "sg:orig_category":"Agentes, Concesionarios Y Sucursales De Veh\u00cdculos",
    "sg:phone":"+34 922 46 25 99",
    "sg:postcode":"38760",
    "sg:province":"Santa Cruz De Tenerife",
    "wof:name":"Manuel Rodriguez Acosta S. L.",
    "wof:placetype":"venue"
},
  "geometry": {"coordinates":[-17.9085597992,28.6563796997],"type":"Point"}
}