{
  "type": "Feature",
  "properties": {
    "iso:country":"ES",
    "sg:address":"Avda Bondad (de La), 14",
    "sg:city":"Caceres",
    "sg:orig_category":"Comercio, Reparaci\u00d3n De Bicicletas, De Motocicletas, De Accesorios",
    "sg:phone":"+34 927 22 27 48",
    "sg:postcode":"10002",
    "sg:province":"C\u00e1ceres",
    "wof:name":"Garcia Mora Pedro",
    "wof:placetype":"venue"
},
  "geometry": {"coordinates":[-6.3752450943,39.4617156982],"type":"Point"}
}