{
  "type": "Feature",
  "properties": {
    "iso:country":"ES",
    "sg:address":"Calle de Cartagena, 132",
    "sg:city":"Madrid",
    "sg:orig_category":"Televisi\u00d3n, V\u00cddeo: Aparatos Y Accesorios (venta)",
    "sg:phone":"+34 914 16 04 77",
    "sg:postcode":"28002",
    "sg:province":"Madrid",
    "wof:name":"Sonido Y Television S. A.",
    "wof:placetype":"venue"
},
  "geometry": {"coordinates":[-3.6751596928,40.4417076111],"type":"Point"}
}