{
  "type": "Feature",
  "properties": {
    "iso:country":"ES",
    "sg:address":"Carrer de Llobateras, 80",
    "sg:city":"Rubi",
    "sg:orig_category":"Loter\u00cda Y T\u00d3mbola",
    "sg:phone":"+34 936 99 75 31",
    "sg:postcode":"08191",
    "sg:province":"Barcelona",
    "wof:name":"Martinez Menchon Ramon",
    "wof:placetype":"venue"
},
  "geometry": {"coordinates":[2.0343630314,41.4889373779],"type":"Point"}
}