{
  "type": "Feature",
  "properties": {
    "addr:full":"Calle de Ciudadela, 12 Zaragoza Zaragoza 50017",
    "addr:housenumber":"12",
    "addr:postcode":"50017",
    "addr:street":"Calle De Ciudadela",
    "iso:country":"ES",
    "sg:address":"Calle de Ciudadela, 12",
    "sg:city":"Zaragoza",
    "sg:orig_category":"Mec\u00c1nico Del Autom\u00d3vil",
    "sg:phone":"+34 976 32 04 92",
    "sg:postcode":"50017",
    "sg:province":"Zaragoza",
    "wof:name":"Alboautoreparacion S.l",
    "wof:placetype":"venue"
},
  "geometry": {"coordinates":[-0.912743628,41.6484832764],"type":"Point"}
}