{
  "type": "Feature",
  "properties": {
    "addr:full":"Calle de Barrio Verde, 1 Tudela Navarra 31500",
    "addr:housenumber":"1",
    "addr:postcode":"31500",
    "addr:street":"Calle De Barrio Verde",
    "iso:country":"ES",
    "sg:address":"Calle de Barrio Verde, 1",
    "sg:city":"Tudela",
    "sg:orig_category":"Sociedades, Compa\u00d1\u00cdas Aseguradoras",
    "sg:phone":"+34 902 21 22 13",
    "sg:postcode":"31500",
    "sg:province":"Navarra",
    "wof:name":"Gabinete De Seguros E Inversiones Aldave Correduria De Seguros S.l.",
    "wof:placetype":"venue"
},
  "geometry": {"coordinates":[-1.6021885872,42.0615768433],"type":"Point"}
}