{
  "type": "Feature",
  "properties": {
    "iso:country":"ES",
    "sg:address":"Carr Boixeta, 7",
    "sg:city":"Igualada",
    "sg:orig_category":"Fabricaci\u00d3n De Su\u00c9ters Y Chalecos De Punto",
    "sg:phone":"+34 938 05 07 33",
    "sg:postcode":"08700",
    "sg:province":"Barcelona",
    "wof:name":"Jorba Casals Maria Dolores",
    "wof:placetype":"venue"
},
  "geometry": {"coordinates":[1.6278729439,41.5761642456],"type":"Point"}
}