{
  "type": "Feature",
  "properties": {
    "addr:full":"Rua Arcebispo Andrade, 4 Vilagarcia Pontevedra 36600",
    "addr:housenumber":"4",
    "addr:postcode":"36600",
    "addr:street":"Rua Arcebispo Andrade",
    "iso:country":"ES",
    "sg:address":"Rua Arcebispo Andrade, 4",
    "sg:city":"Vilagarcia",
    "sg:orig_category":"Art\u00cdculos De Regalo (al Por Menor)",
    "sg:phone":"+34 986 50 19 06",
    "sg:postcode":"36600",
    "sg:province":"Pontevedra",
    "wof:name":"Raposo Arias Peregrina",
    "wof:placetype":"venue"
},
  "geometry": {"coordinates":[-8.7675943375,42.5933036804],"type":"Point"}
}