{
  "type": "Feature",
  "properties": {
    "iso:country":"ES",
    "sg:address":"Plaza San Cristobal, 1",
    "sg:city":"Almu\u00f1ecar",
    "sg:orig_category":"Fabrica De Cer\u00c1micas",
    "sg:phone":"+34 958 63 90 22",
    "sg:postcode":"18690",
    "sg:province":"Granada",
    "wof:name":"Gonzalez Caro Raquel",
    "wof:placetype":"venue"
},
  "geometry": {"coordinates":[-3.6986711025,36.7316741943],"type":"Point"}
}