{
  "type": "Feature",
  "properties": {
    "iso:country":"ES",
    "sg:address":"Calle de Cuadrilla De Zuia, 6",
    "sg:city":"Vitoria-gasteiz",
    "sg:orig_category":"Centros Empresariales",
    "sg:phone":"+34 945 12 19 19",
    "sg:postcode":"01013",
    "sg:province":"\u00c1lava",
    "wof:name":"Baskulak Eta Sistemak Gatza Ltz, Sl",
    "wof:placetype":"venue"
},
  "geometry": {"coordinates":[-2.665350914,42.8566932678],"type":"Point"}
}