{
  "type": "Feature",
  "properties": {
    "iso:country":"ES",
    "sg:address":"Carrer de Closa De Mestres, 11",
    "sg:city":"Reus",
    "sg:orig_category":"Inform\u00c1tica (estudios, Servicios, Asesor\u00cda, Formaci\u00d3n)",
    "sg:phone":"+34 977 77 40 74",
    "sg:postcode":"43204",
    "sg:province":"Tarragona",
    "wof:name":"A.c.i Grup S.l.",
    "wof:placetype":"venue"
},
  "geometry": {"coordinates":[1.1107542515,41.1522216797],"type":"Point"}
}