{
  "type": "Feature",
  "properties": {
    "addr:full":"Calle de Gumersindo Azcarate, 8 Linares Ja\u00e9n 23700",
    "addr:housenumber":"8",
    "addr:postcode":"23700",
    "addr:street":"Calle De Gumersindo Azcarate;Jae\u0301N",
    "iso:country":"ES",
    "sg:address":"Calle de Gumersindo Azcarate, 8",
    "sg:city":"Linares",
    "sg:orig_category":"Bisuteros (fabricaci\u00d3n, Al Por Mayor)",
    "sg:phone":"+34 953 65 36 50",
    "sg:postcode":"23700",
    "sg:province":"Ja\u00e9n",
    "wof:name":"Sanchez Garcia Alfredo",
    "wof:placetype":"venue"
},
  "geometry": {"coordinates":[-3.6345419884,38.0969810486],"type":"Point"}
}