{
  "type": "Feature",
  "properties": {
    "addr:full":"Calle de Concilio De Nicea, 48 Cordoba C\u00f3rdoba 14014",
    "addr:housenumber":"48",
    "addr:postcode":"14014",
    "addr:street":"Calle De Concilio De Nicea;Co\u0301Rdoba",
    "iso:country":"ES",
    "sg:address":"Calle de Concilio De Nicea, 48",
    "sg:city":"Cordoba",
    "sg:orig_category":"Bisuteros (fabricaci\u00d3n, Al Por Mayor)",
    "sg:phone":"+34 957 44 13 60",
    "sg:postcode":"14014",
    "sg:province":"C\u00f3rdoba",
    "wof:name":"Califa Joyeros S.l.",
    "wof:placetype":"venue"
},
  "geometry": {"coordinates":[-4.7555618286,37.8882980347],"type":"Point"}
}