{
  "type": "Feature",
  "properties": {
    "addr:full":"S. Marti, S/n Sta. Pau Girona 17811",
    "addr:housenumber":"s / n",
    "addr:postcode":"17811",
    "addr:street":"S. Marti",
    "iso:country":"ES",
    "sg:address":"S. Marti, S/n",
    "sg:city":"Sta. Pau",
    "sg:orig_category":"Enfermeras: Consultas, Atenci\u00d3n A Domicilio",
    "sg:phone":"+34 972 68 00 26",
    "sg:postcode":"17811",
    "sg:province":"Girona",
    "wof:name":"Coromina Bartrina Maria Victoria",
    "wof:placetype":"venue"
},
  "geometry": {"coordinates":[2.5697700977,42.1482391357],"type":"Point"}
}