{
  "type": "Feature",
  "properties": {
    "iso:country":"ES",
    "sg:address":"Calle de Galicia, 38",
    "sg:city":"Palmas De Gran Canaria",
    "sg:orig_category":"Ropa Para Caballeros (al Por Menor)",
    "sg:phone":"+34 928 26 31 47",
    "sg:postcode":"35007",
    "sg:province":"Las Palmas",
    "wof:name":"Frances Rico Gaspar",
    "wof:placetype":"venue"
},
  "geometry": {"coordinates":[-15.4334077835,28.1356868744],"type":"Point"}
}