{
  "type": "Feature",
  "properties": {
    "addr:full":"Trva Olmos (dos), 12 Vilanova Arousa Pontevedra 36620",
    "addr:housenumber":"12",
    "addr:postcode":"36620",
    "addr:street":"Trva Olmos Dos",
    "iso:country":"ES",
    "sg:address":"Trva Olmos (dos), 12",
    "sg:city":"Vilanova Arousa",
    "sg:orig_category":"Agencias Y Asesores De Publicidad",
    "sg:phone":"+34 986 56 15 66",
    "sg:postcode":"36620",
    "sg:province":"Pontevedra",
    "wof:name":"Promociones Faro De Xeixo",
    "wof:placetype":"venue"
},
  "geometry": {"coordinates":[-8.8282852173,42.5623435974],"type":"Point"}
}