{
  "type": "Feature",
  "properties": {
    "iso:country":"ES",
    "sg:address":"Carretera De Santiba\u00f1ez, S/n",
    "sg:city":"Ahigal",
    "sg:orig_category":"Cooperativas Agr\u00cdcolas",
    "sg:phone":"+34 927 43 95 65",
    "sg:postcode":"10650",
    "sg:province":"C\u00e1ceres",
    "wof:name":"Sociedad Cooperativa Ganaderos De Caparra",
    "wof:placetype":"venue"
},
  "geometry": {"coordinates":[-6.1873140335,40.1892547607],"type":"Point"}
}