{
  "type": "Feature",
  "properties": {
    "iso:country":"ES",
    "sg:address":"Garbi (poligon Ind Riambau), 16",
    "sg:city":"Tarrega",
    "sg:orig_category":"Tractores Agr\u00cdcolas Y Remolques",
    "sg:phone":"+34 973 31 08 05",
    "sg:postcode":"25300",
    "sg:province":"Lleida",
    "wof:name":"Comercial Ribalta Ros S.c.p.",
    "wof:placetype":"venue"
},
  "geometry": {"coordinates":[1.1463749409,41.6539497375],"type":"Point"}
}