{
  "type": "Feature",
  "properties": {
    "iso:country":"ES",
    "sg:address":"Avda Numancia, S/n",
    "sg:city":"Calahorra",
    "sg:orig_category":"Poller\u00cda Y Caza (al Por Menor)",
    "sg:phone":"+34 941 13 14 43",
    "sg:postcode":"26500",
    "sg:province":"La Rioja",
    "wof:name":"Miguel Reinares Rufino",
    "wof:placetype":"venue"
},
  "geometry": {"coordinates":[-1.9746290445,42.3027801514],"type":"Point"}
}