{
  "type": "Feature",
  "properties": {
    "addr:full":"Ptge Sert, 10 Barcelona Barcelona 08003",
    "addr:housenumber":"10",
    "addr:postcode":"08003",
    "addr:street":"Ptge Sert",
    "iso:country":"ES",
    "sg:address":"Ptge Sert, 10",
    "sg:city":"Barcelona",
    "sg:orig_category":"Tapiceros Y Tapiceros",
    "sg:phone":"+34 932 68 11 39",
    "sg:postcode":"08003",
    "sg:province":"Barcelona",
    "wof:name":"Robbins  Nancy",
    "wof:placetype":"venue"
},
  "geometry": {"coordinates":[2.1771140099,41.3891296387],"type":"Point"}
}