{
  "type": "Feature",
  "properties": {
    "addr:full":"C/ Lluis Braille, 16 Alcoi Alicante 03802",
    "addr:housenumber":"16",
    "addr:postcode":"03802",
    "addr:street":"C / Lluis Braille",
    "iso:country":"ES",
    "sg:address":"C/ Lluis Braille, 16",
    "sg:city":"Alcoi",
    "sg:orig_category":"Chapister\u00cda",
    "sg:phone":"+34 965 52 51 02",
    "sg:postcode":"03802",
    "sg:province":"Alicante",
    "wof:name":"Chapa Y Pintura Alcoy C. B.",
    "wof:placetype":"venue"
},
  "geometry": {"coordinates":[-0.4858660102,38.6977958679],"type":"Point"}
}