{
  "type": "Feature",
  "properties": {
    "addr:full":"Calle de Mayor, 5 Torrijos Toledo 45500",
    "addr:housenumber":"5",
    "addr:postcode":"45500",
    "addr:street":"Calle De Mayor",
    "iso:country":"ES",
    "sg:address":"Calle de Mayor, 5",
    "sg:city":"Torrijos",
    "sg:orig_category":"Papeler\u00cdas, Librer\u00cdas",
    "sg:phone":"+34 925 76 01 45",
    "sg:postcode":"45500",
    "sg:province":"Toledo",
    "wof:name":"Moreira Vazquez Isabelo",
    "wof:placetype":"venue"
},
  "geometry": {"coordinates":[-4.283082962,39.9813079834],"type":"Point"}
}