{
  "type": "Feature",
  "properties": {
    "addr:full":"Kaletxiki, 24 Andoain Guip\u00f9zcoa 20140",
    "addr:housenumber":"24",
    "addr:postcode":"20140",
    "addr:street":"Kaletxiki;Guipu\u0300Zcoa",
    "iso:country":"ES",
    "sg:address":"Kaletxiki, 24",
    "sg:city":"Andoain",
    "sg:orig_category":"Institutos De Belleza",
    "sg:phone":"+34 943 59 28 01",
    "sg:postcode":"20140",
    "sg:province":"Guip\u00f9zcoa",
    "wof:name":"Salaberria Ansa Nerea",
    "wof:placetype":"venue"
},
  "geometry": {"coordinates":[-2.0172920227,43.22133255],"type":"Point"}
}