{
  "type": "Feature",
  "properties": {
    "iso:country":"ES",
    "sg:address":"Cra Soller, Km. 0007,0",
    "sg:city":"Son Besso",
    "sg:orig_category":"Negocio De Materiales De Construcci\u00d3n",
    "sg:phone":"+34 971 43 95 09",
    "sg:postcode":"07120",
    "sg:province":"Islas Baleares",
    "sg:website":"www.obresiserveisrullan.com",
    "wof:name":"Obres I Serveis Rullan S.l.",
    "wof:placetype":"venue"
},
  "geometry": {"coordinates":[2.655944109,39.6189918518],"type":"Point"}
}