{
  "type": "Feature",
  "properties": {
    "iso:country":"ES",
    "sg:address":"Calle de Rios Rosas, 17",
    "sg:city":"Madrid",
    "sg:orig_category":"Asesor\u00cda Fiscal Y Jur\u00cddica",
    "sg:phone":"+34 914 41 20 88",
    "sg:postcode":"28003",
    "sg:province":"Madrid",
    "wof:name":"Comtycon",
    "wof:placetype":"venue"
},
  "geometry": {"coordinates":[-3.7012479305,40.4421195984],"type":"Point"}
}