{
  "type": "Feature",
  "properties": {
    "addr:full":"Carrer de Pardo Bazan, 9 Terrassa Barcelona 08225",
    "addr:housenumber":"9",
    "addr:postcode":"08225",
    "addr:street":"Carrer De Pardo Bazan",
    "iso:country":"ES",
    "sg:address":"Carrer de Pardo Bazan, 9",
    "sg:city":"Terrassa",
    "sg:orig_category":"Almacenes Frigor\u00cdficos",
    "sg:phone":"+34 937 35 79 88",
    "sg:postcode":"08225",
    "sg:province":"Barcelona",
    "wof:name":"Clima Disseny S.l.",
    "wof:placetype":"venue"
},
  "geometry": {"coordinates":[2.0067849159,41.5760383606],"type":"Point"}
}