{
  "type": "Feature",
  "properties": {
    "iso:country":"ES",
    "sg:address":"Pg Pere Iii, 87",
    "sg:city":"Manresa",
    "sg:orig_category":"Ense\u00d1anza: Idiomas",
    "sg:phone":"+34 938 73 30 38",
    "sg:postcode":"08242",
    "sg:province":"Barcelona",
    "wof:name":"Castells Selga Maria Montserrat",
    "wof:placetype":"venue"
},
  "geometry": {"coordinates":[1.8301520348,41.7301750183],"type":"Point"}
}