{
  "type": "Feature",
  "properties": {
    "iso:country":"ES",
    "sg:address":"Ctra Sacedon, Km. 0060,5",
    "sg:city":"Aranzueque",
    "sg:orig_category":"Granos Y Semillas (producci\u00d3n, Al Por Mayor)",
    "sg:phone":"+34 949 29 90 73",
    "sg:postcode":"19141",
    "sg:province":"Guadalajara",
    "wof:name":"Danisco Semillas S.a.",
    "wof:placetype":"venue"
},
  "geometry": {"coordinates":[-3.0762290955,40.4918212891],"type":"Point"}
}