{
  "type": "Feature",
  "properties": {
    "iso:country":"ES",
    "sg:address":"Pg Mallorca, 17",
    "sg:city":"Palma",
    "sg:orig_category":"M\u00c9dicos: Estomatolog\u00cda",
    "sg:phone":"+34 971 73 01 50",
    "sg:postcode":"07011",
    "sg:province":"Islas Baleares",
    "wof:name":"Ortigosa Digon Roberto",
    "wof:placetype":"venue"
},
  "geometry": {"coordinates":[2.6435439587,39.5751495361],"type":"Point"}
}