{
  "type": "Feature",
  "properties": {
    "addr:full":"Calle de Urbasa, 1 Andosilla Navarra 31261",
    "addr:housenumber":"1",
    "addr:postcode":"31261",
    "addr:street":"Calle De Urbasa",
    "iso:country":"ES",
    "sg:address":"Calle de Urbasa, 1",
    "sg:city":"Andosilla",
    "sg:orig_category":"Arquitectos",
    "sg:phone":"+34 948 69 02 52",
    "sg:postcode":"31261",
    "sg:province":"Navarra",
    "wof:name":"Fuertes Go\u00f1i Cesar",
    "wof:placetype":"venue"
},
  "geometry": {"coordinates":[-1.9437960386,42.3774757385],"type":"Point"}
}