{
  "type": "Feature",
  "properties": {
    "addr:full":"Crta Archivel, S/n Barranda Murcia 30412",
    "addr:housenumber":"s",
    "addr:postcode":"30412",
    "addr:street":"Crta Archivel;/ N",
    "iso:country":"ES",
    "sg:address":"Crta Archivel, S/n",
    "sg:city":"Barranda",
    "sg:orig_category":"Conservas De Legumbres (fabricaci\u00d3n, Al Por Mayor)",
    "sg:phone":"+34 968 72 52 05",
    "sg:postcode":"30412",
    "sg:province":"Murcia",
    "sg:website":"www.inmoduval.com",
    "wof:name":"Alimentaria Barranda S.l.",
    "wof:placetype":"venue"
},
  "geometry": {"coordinates":[-1.9740370512,38.046207428],"type":"Point"}
}