{
  "type": "Feature",
  "properties": {
    "addr:full":"Calle de Humilladero, 11 Madrid Madrid 28005",
    "addr:housenumber":"11",
    "addr:postcode":"madrid;28005",
    "addr:street":"Calle De Humilladero",
    "iso:country":"ES",
    "sg:address":"Calle de Humilladero, 11",
    "sg:city":"Madrid",
    "sg:orig_category":"Panader\u00cdas, Panader\u00cdas",
    "sg:phone":"+34 913 65 26 65",
    "sg:postcode":"28005",
    "sg:province":"Madrid",
    "wof:name":"Stetron S. A.",
    "wof:placetype":"venue"
},
  "geometry": {"coordinates":[-3.7103016376,40.4102783203],"type":"Point"}
}