{
  "type": "Feature",
  "properties": {
    "iso:country":"ES",
    "sg:address":"Calle de Regordo\u00d1o, 6",
    "sg:city":"Mostoles",
    "sg:orig_category":"Agentes, Concesionarios Y Sucursales De Veh\u00cdculos",
    "sg:phone":"+34 916 85 20 20",
    "sg:postcode":"28936",
    "sg:province":"Madrid",
    "sg:website":"www.talleresreyes.com",
    "wof:name":"Talleres Reyes S.l.",
    "wof:placetype":"venue"
},
  "geometry": {"coordinates":[-3.8440060616,40.3162155151],"type":"Point"}
}