{
  "type": "Feature",
  "properties": {
    "iso:country":"ES",
    "sg:address":"Camino Viejo De La Fuensanta, 2",
    "sg:city":"Alcaudete",
    "sg:orig_category":"Ense\u00d1anza: Profesiones Art\u00cdsticas",
    "sg:phone":"+34 953 70 80 32",
    "sg:postcode":"23660",
    "sg:province":"Ja\u00e9n",
    "wof:name":"Comas Amaro Fidel",
    "wof:placetype":"venue"
},
  "geometry": {"coordinates":[-4.0777487755,37.5870018005],"type":"Point"}
}