{
  "type": "Feature",
  "properties": {
    "addr:full":"Calle de Alonso De Quintanilla, 11 Gijon Asturias 33213",
    "addr:housenumber":"11",
    "addr:postcode":"33213",
    "addr:street":"Calle De Alonso De Quintanilla",
    "iso:country":"ES",
    "sg:address":"Calle de Alonso De Quintanilla, 11",
    "sg:city":"Gijon",
    "sg:orig_category":"Muebles, Minoristas",
    "sg:phone":"+34 985 31 16 54",
    "sg:postcode":"33213",
    "sg:province":"Asturias",
    "wof:name":"Vega Prieto Araceli",
    "wof:placetype":"venue"
},
  "geometry": {"coordinates":[-5.7057518959,43.5404052734],"type":"Point"}
}