{
  "type": "Feature",
  "properties": {
    "addr:full":"Rua Elduayen, 5 Vigo Pontevedra 36202",
    "addr:housenumber":"5",
    "addr:postcode":"36202",
    "addr:street":"Rua Elduayen",
    "iso:country":"ES",
    "sg:address":"Rua Elduayen, 5",
    "sg:city":"Vigo",
    "sg:orig_category":"Zapatos: Material, Suministros, Accesorios (fabricaci\u00d3n, Al Por Mayor)",
    "sg:phone":"+34 986 43 91 89",
    "sg:postcode":"36202",
    "sg:province":"Pontevedra",
    "wof:name":"Rodriguez Castro Bego\u00f1a",
    "wof:placetype":"venue"
},
  "geometry": {"coordinates":[-8.7260751724,42.2380714417],"type":"Point"}
}