{
  "type": "Feature",
  "properties": {
    "addr:full":"Rio Huit, S/n Torrox-costa M\u00e1laga 29793",
    "addr:housenumber":"s",
    "addr:postcode":"29793",
    "addr:street":"/ N Torrox-Costa Ma\u0301Laga",
    "iso:country":"ES",
    "sg:address":"Rio Huit, S/n",
    "sg:city":"Torrox-costa",
    "sg:orig_category":"Hormigonados",
    "sg:phone":"+34 952 53 03 25",
    "sg:postcode":"29793",
    "sg:province":"M\u00e1laga",
    "wof:name":"Hormigones Y Minas S.a.",
    "wof:placetype":"venue"
},
  "geometry": {"coordinates":[-3.9873039722,36.7375984192],"type":"Point"}
}