{
  "type": "Feature",
  "properties": {
    "iso:country":"ES",
    "sg:address":"Calle de Misericordia, 52",
    "sg:city":"Cartaya",
    "sg:orig_category":"Electricidad Veh\u00cdculo",
    "sg:phone":"+34 959 39 10 04",
    "sg:postcode":"21450",
    "sg:province":"Huelva",
    "wof:name":"Estevez Orta Francisco",
    "wof:placetype":"venue"
},
  "geometry": {"coordinates":[-7.1514310837,37.2831039429],"type":"Point"}
}