{
  "type": "Feature",
  "properties": {
    "addr:full":"Calle de Ramon Y Cajal, 13 Rute C\u00f3rdoba 14960",
    "addr:housenumber":"13",
    "addr:postcode":"14960",
    "addr:street":"Calle De Ramon Y Cajal;Co\u0301Rdoba",
    "iso:country":"ES",
    "sg:address":"Calle de Ramon Y Cajal, 13",
    "sg:city":"Rute",
    "sg:orig_category":"Florister\u00cdas",
    "sg:phone":"+34 957 53 92 30",
    "sg:postcode":"14960",
    "sg:province":"C\u00f3rdoba",
    "wof:name":"Luna Porras Jose",
    "wof:placetype":"venue"
},
  "geometry": {"coordinates":[-4.3700819016,37.3264961243],"type":"Point"}
}