{
  "type": "Feature",
  "properties": {
    "addr:full":"Calle de Tenderina, 155 Oviedo Asturias 33010",
    "addr:housenumber":"155",
    "addr:postcode":"33010",
    "addr:street":"Calle De Tenderina",
    "iso:country":"ES",
    "sg:address":"Calle de Tenderina, 155",
    "sg:city":"Oviedo",
    "sg:orig_category":"Institutos De Belleza",
    "sg:phone":"+34 985 21 85 35",
    "sg:postcode":"33010",
    "sg:province":"Asturias",
    "wof:name":"Natalia Iglesias Rodriguez",
    "wof:placetype":"venue"
},
  "geometry": {"coordinates":[-5.8263821602,43.3674850464],"type":"Point"}
}