{
  "type": "Feature",
  "properties": {
    "addr:full":"Carr Vassallo, 14 Mao Islas Baleares 07703",
    "addr:housenumber":"14",
    "addr:postcode":"07703",
    "addr:street":"Carr Vassallo",
    "iso:country":"ES",
    "sg:address":"Carr Vassallo, 14",
    "sg:city":"Mao",
    "sg:orig_category":"Asesor\u00cda Fiscal Y Jur\u00cddica",
    "sg:phone":"+34 971 35 10 77",
    "sg:postcode":"07703",
    "sg:province":"Islas Baleares",
    "wof:name":"Consulting Empresarial Menorca S.l.",
    "wof:placetype":"venue"
},
  "geometry": {"coordinates":[4.2546291351,39.8868408203],"type":"Point"}
}