{
  "type": "Feature",
  "properties": {
    "iso:country":"ES",
    "sg:address":"Plaz Maestrazgo, 6",
    "sg:city":"Castellon",
    "sg:orig_category":"Empresas De Carpinter\u00cda",
    "sg:phone":"+34 964 25 74 26",
    "sg:postcode":"12001",
    "sg:province":"Castell\u00f3n",
    "wof:name":"Boronat C.b.",
    "wof:placetype":"venue"
},
  "geometry": {"coordinates":[-0.0390900001,39.9866714478],"type":"Point"}
}