{
  "type": "Feature",
  "properties": {
    "iso:country":"ES",
    "sg:address":"Calle de General Sanjurjo, 18",
    "sg:city":"Coca",
    "sg:orig_category":"Promotores Constructores",
    "sg:phone":"+34 921 58 63 88",
    "sg:postcode":"40480",
    "sg:province":"Segovia",
    "sg:website":"pagina.de/ccmarcasl",
    "wof:name":"Construcciones Y Contratas Marca S.l.",
    "wof:placetype":"venue"
},
  "geometry": {"coordinates":[-4.5220899582,41.2196502686],"type":"Point"}
}