{
  "type": "Feature",
  "properties": {
    "addr:full":"Av Gonzalez Robles, 21 Orgiva Granada 18400",
    "addr:housenumber":"21",
    "addr:postcode":"18400",
    "addr:street":"Av Gonzalez Robles",
    "iso:country":"ES",
    "sg:address":"Av Gonzalez Robles, 21",
    "sg:city":"Orgiva",
    "sg:orig_category":"Ingeniero",
    "sg:phone":"+34 958 78 58 88",
    "sg:postcode":"18400",
    "sg:province":"Granada",
    "wof:name":"Ruiz Manzano Cristobal",
    "wof:placetype":"venue"
},
  "geometry": {"coordinates":[-3.4249799252,36.9007492065],"type":"Point"}
}