{
  "type": "Feature",
  "properties": {
    "addr:full":"Calle de Eugenio Gross, 9 Malaga M\u00e1laga 29010",
    "addr:housenumber":"9",
    "addr:postcode":"29010",
    "addr:street":"Calle De Eugenio Gross;Ma\u0301Laga",
    "iso:country":"ES",
    "sg:address":"Calle de Eugenio Gross, 9",
    "sg:city":"Malaga",
    "sg:orig_category":"Pod\u00d3logos: Pedicuros",
    "sg:phone":"+34 952 30 99 39",
    "sg:postcode":"29010",
    "sg:province":"M\u00e1laga",
    "wof:name":"Molina Martin Valeriano",
    "wof:placetype":"venue"
},
  "geometry": {"coordinates":[-4.4357686043,36.7231292725],"type":"Point"}
}