{
  "type": "Feature",
  "properties": {
    "addr:full":"Calle de Daroca, 55 Zaragoza Zaragoza 50017",
    "addr:housenumber":"55",
    "addr:postcode":"50017",
    "addr:street":"Calle De Daroca",
    "iso:country":"ES",
    "sg:address":"Calle de Daroca, 55",
    "sg:city":"Zaragoza",
    "sg:orig_category":"Farmacias",
    "sg:phone":"+34 976 34 55 44",
    "sg:postcode":"50017",
    "sg:province":"Zaragoza",
    "wof:name":"Tarancon Beltran Cb",
    "wof:placetype":"venue"
},
  "geometry": {"coordinates":[-0.9070662856,41.649471283],"type":"Point"}
}