{
  "type": "Feature",
  "properties": {
    "addr:full":"Calle de San Bernardo, 60 Gijon Asturias 33201",
    "addr:housenumber":"60",
    "addr:postcode":"33201",
    "addr:street":"Calle De San Bernardo",
    "iso:country":"ES",
    "sg:address":"Calle de San Bernardo, 60",
    "sg:city":"Gijon",
    "sg:orig_category":"Panader\u00cdas, Panader\u00cdas",
    "sg:phone":"+34 985 34 25 15",
    "sg:postcode":"33201",
    "sg:province":"Asturias",
    "wof:name":"Pandiaz S. L.",
    "wof:placetype":"venue"
},
  "geometry": {"coordinates":[-5.6608982086,43.5400695801],"type":"Point"}
}