{
  "type": "Feature",
  "properties": {
    "iso:country":"ES",
    "sg:address":"Calle de Matadero, 2",
    "sg:city":"Medina Rioseco",
    "sg:orig_category":"Molduras, Junquillos, Listones Y Molduras Perforadas",
    "sg:phone":"+34 983 70 03 35",
    "sg:postcode":"47800",
    "sg:province":"Valladolid",
    "wof:name":"Garcia Rubio Pascual",
    "wof:placetype":"venue"
},
  "geometry": {"coordinates":[-5.045399189,41.881313324],"type":"Point"}
}