{
  "type": "Feature",
  "properties": {
    "iso:country":"ES",
    "sg:address":"Jose Migel Barandiaran Plaza, 5",
    "sg:city":"Ordizia",
    "sg:orig_category":"Cl\u00cdnicas Dentales",
    "sg:phone":"+34 943 88 92 45",
    "sg:postcode":"20240",
    "sg:province":"Guip\u00f9zcoa",
    "wof:name":"Arrizubieta Balerdi Maria Rosario",
    "wof:placetype":"venue"
},
  "geometry": {"coordinates":[-2.1766529083,43.0544624329],"type":"Point"}
}