{
  "type": "Feature",
  "properties": {
    "addr:full":"Calle de Vitoria, 107 Burgos Burgos 09006",
    "addr:housenumber":"107",
    "addr:postcode":"09006",
    "addr:street":"Calle De Vitoria",
    "iso:country":"ES",
    "sg:address":"Calle de Vitoria, 107",
    "sg:city":"Burgos",
    "sg:orig_category":"Talleres El\u00c9ctricos Para Veh\u00cdculos",
    "sg:phone":"+34 947 23 21 89",
    "sg:postcode":"09006",
    "sg:province":"Burgos",
    "wof:name":"Santamaria Olmos Araceli",
    "wof:placetype":"venue"
},
  "geometry": {"coordinates":[-3.6814799309,42.3466377258],"type":"Point"}
}