{
  "type": "Feature",
  "properties": {
    "addr:full":"Avda Salvador Allende, 14 Zaragoza Zaragoza 50015",
    "addr:housenumber":"14",
    "addr:postcode":"50015",
    "addr:street":"Avda Salvador Allende",
    "iso:country":"ES",
    "sg:address":"Avda Salvador Allende, 14",
    "sg:city":"Zaragoza",
    "sg:orig_category":"Cajas De Ahorro",
    "sg:phone":"+34 976 73 63 75",
    "sg:postcode":"50015",
    "sg:province":"Zaragoza",
    "wof:name":"Caja De Ahorros De La Inmaculada",
    "wof:placetype":"venue"
},
  "geometry": {"coordinates":[-0.8764619827,41.6695632935],"type":"Point"}
}