{
  "type": "Feature",
  "properties": {
    "iso:country":"ES",
    "sg:address":"Carr Estudis, 22",
    "sg:city":"Vilanova I La Geltru",
    "sg:orig_category":"Mec\u00c1nico Del Autom\u00d3vil",
    "sg:phone":"+34 938 93 97 11",
    "sg:postcode":"08800",
    "sg:province":"Barcelona",
    "wof:name":"Martinez Tobaruela Francisco",
    "wof:placetype":"venue"
},
  "geometry": {"coordinates":[1.732213974,41.2170982361],"type":"Point"}
}