{
  "type": "Feature",
  "properties": {
    "addr:full":"Av Miraflores, 22 Hospitalet Llobregat Barcelona 08905",
    "addr:housenumber":"22",
    "addr:postcode":"08905",
    "addr:street":"Av Miraflores",
    "iso:country":"ES",
    "sg:address":"Av Miraflores, 22",
    "sg:city":"Hospitalet Llobregat",
    "sg:classifiers":[
        {
            "category":"Autos & Motor Vehicles",
            "subcategory":"Automobile Sales",
            "type":"Retail Goods"
        }
    ],
    "sg:phone":"+34 934 40 47 54",
    "sg:postcode":"08905",
    "sg:province":"Barcelona",
    "wof:name":"Autoescoles Belair S.l.",
    "wof:placetype":"venue"
},
  "geometry": {"coordinates":[2.1111819744,41.3702316284],"type":"Point"}
}