{
  "type": "Feature",
  "properties": {
    "addr:full":"Avda Doctor Federico Rubio Y Gali, 11 Madrid Madrid 28039",
    "addr:housenumber":"11",
    "addr:postcode":"madrid;28039",
    "addr:street":"Avda Doctor Federico Rubio Y Gali",
    "iso:country":"ES",
    "sg:address":"Avda Doctor Federico Rubio Y Gali, 11",
    "sg:city":"Madrid",
    "sg:orig_category":"Ense\u00d1anza Variada",
    "sg:phone":"+34 914 56 27 95",
    "sg:postcode":"28039",
    "sg:province":"Madrid",
    "sg:website":"www.cepade.es",
    "wof:name":"Fundacion General Universidad Politecnic",
    "wof:placetype":"venue"
},
  "geometry": {"coordinates":[-3.7087259293,40.4486846924],"type":"Point"}
}