{
  "type": "Feature",
  "properties": {
    "iso:country":"ES",
    "sg:address":"Carrer de Doctor Fleming, 11",
    "sg:city":"Can Cortes-pedra Llarga",
    "sg:orig_category":"Chapister\u00cda",
    "sg:phone":"+34 938 64 80 11",
    "sg:postcode":"08184",
    "sg:province":"Barcelona",
    "sg:website":"www.cortypleg.com",
    "wof:name":"Cortypleg S.a.",
    "wof:placetype":"venue"
},
  "geometry": {"coordinates":[2.1748890877,41.5835151672],"type":"Point"}
}