{
  "type": "Feature",
  "properties": {
    "iso:country":"ES",
    "sg:address":"Carr Major, 10",
    "sg:city":"Sort",
    "sg:orig_category":"Carnicer\u00cdas, Carnicer\u00cdas",
    "sg:phone":"+34 973 62 11 28",
    "sg:postcode":"25560",
    "sg:province":"Lleida",
    "wof:name":"Carns I Embotits Del Pallars S.l.",
    "wof:placetype":"venue"
},
  "geometry": {"coordinates":[1.1304420233,42.4114723206],"type":"Point"}
}