{
  "type": "Feature",
  "properties": {
    "iso:country":"ES",
    "sg:address":"Calle de Torreblanca, 1",
    "sg:city":"Fuengirola",
    "sg:orig_category":"Urbanistas",
    "sg:phone":"+34 952 47 46 00",
    "sg:postcode":"29640",
    "sg:province":"M\u00e1laga",
    "wof:name":"Torreblanca Del Sol S. A.",
    "wof:placetype":"venue"
},
  "geometry": {"coordinates":[-4.604393959,36.5633239746],"type":"Point"}
}