{
  "type": "Feature",
  "properties": {
    "addr:full":"Calle de Actriz Rosario Pino, 6 Malaga M\u00e1laga 29014",
    "addr:housenumber":"6",
    "addr:postcode":"29014",
    "addr:street":"Calle De Actriz;Pino;Ma\u0301Laga",
    "iso:country":"ES",
    "sg:address":"Calle de Actriz Rosario Pino, 6",
    "sg:city":"Malaga",
    "sg:orig_category":"Comercio De Piezas De Recambio Y De Accesorios De Veh\u00cdculos, Veh\u00cdculos Industriales",
    "sg:phone":"+34 952 25 39 87",
    "sg:postcode":"29014",
    "sg:province":"M\u00e1laga",
    "wof:name":"Miranda Sarria Francisco",
    "wof:placetype":"venue"
},
  "geometry": {"coordinates":[-4.4248051643,36.7307891846],"type":"Point"}
}