{
  "type": "Feature",
  "properties": {
    "iso:country":"ES",
    "sg:address":"Calle de Arrecife, 28",
    "sg:city":"Palmas De Gran Canaria",
    "sg:orig_category":"Fabricaci\u00d3n De Jabones, Detergentes Y Lej\u00cdas",
    "sg:phone":"+34 928 48 04 30",
    "sg:postcode":"35010",
    "sg:province":"Las Palmas",
    "wof:name":"Quimica Aplicada Canaria S.a.",
    "wof:placetype":"venue"
},
  "geometry": {"coordinates":[-15.4551143646,28.1075534821],"type":"Point"}
}