{
  "type": "Feature",
  "properties": {
    "iso:country":"ES",
    "sg:address":"Avgd Sant Salvador, 1",
    "sg:city":"Badalona",
    "sg:orig_category":"Abogados Especialistas En Derecho Penal",
    "sg:phone":"+34 933 98 00 27",
    "sg:postcode":"08913",
    "sg:province":"Barcelona",
    "wof:name":"Padilla Ramos Ana Maria",
    "wof:placetype":"venue"
},
  "geometry": {"coordinates":[2.2160999775,41.4340209961],"type":"Point"}
}