{
  "type": "Feature",
  "properties": {
    "iso:country":"ES",
    "sg:address":"Estacion, S/n",
    "sg:city":"Coca",
    "sg:orig_category":"Tubos Y Tuber\u00cdas De Metales Ferrosos (fabricaci\u00d3n, Negocio)",
    "sg:phone":"+34 921 58 61 61",
    "sg:postcode":"40480",
    "sg:province":"Segovia",
    "wof:name":"Industrias Catalina S. A.",
    "wof:placetype":"venue"
},
  "geometry": {"coordinates":[-4.5838179588,41.2258415222],"type":"Point"}
}