{
  "type": "Feature",
  "properties": {
    "iso:country":"ES",
    "sg:address":"Prol. Isabel La Catolica, S/n",
    "sg:city":"Navalmoral Mata",
    "sg:orig_category":"Confecci\u00d3n De Cinturones Y De Tirantes",
    "sg:phone":"+34 927 53 52 33",
    "sg:postcode":"10300",
    "sg:province":"C\u00e1ceres",
    "wof:name":"Textil Jara C.b.",
    "wof:placetype":"venue"
},
  "geometry": {"coordinates":[-5.5410938263,39.8963813782],"type":"Point"}
}