{
  "type": "Feature",
  "properties": {
    "iso:country":"ES",
    "sg:address":"Plaz Merced, 17",
    "sg:city":"Malaga",
    "sg:classifiers":[
        {
            "category":"Tea Room",
            "subcategory":"None",
            "type":"Food & Drink"
        }
    ],
    "sg:phone":"+34 952 21 90 93",
    "sg:postcode":"29012",
    "sg:province":"M\u00e1laga",
    "sg:tags":[
        "snack"
    ],
    "wof:name":"Bibal Gestion S.l.",
    "wof:placetype":"venue"
},
  "geometry": {"coordinates":[-4.4172210693,36.7237625122],"type":"Point"}
}