{
  "type": "Feature",
  "properties": {
    "addr:full":"Calle de Andres Martinez (de), 1 Aranjuez Madrid 28300",
    "addr:housenumber":"1",
    "addr:postcode":"28300",
    "addr:street":"Calle De Andres Martinez De",
    "iso:country":"ES",
    "sg:address":"Calle de Andres Martinez (de), 1",
    "sg:city":"Aranjuez",
    "sg:orig_category":"Empresas De Carpinter\u00cda",
    "sg:phone":"+34 918 91 03 23",
    "sg:postcode":"28300",
    "sg:province":"Madrid",
    "wof:name":"Monzon Hernandez Luis Mariano",
    "wof:placetype":"venue"
},
  "geometry": {"coordinates":[-3.6018521786,40.0269317627],"type":"Point"}
}