{
  "type": "Feature",
  "properties": {
    "addr:full":"Parnaso, S/n Miranda Murcia 30319",
    "addr:housenumber":"s / n",
    "addr:postcode":"30319",
    "addr:street":"Parnaso",
    "iso:country":"ES",
    "sg:address":"Parnaso, S/n",
    "sg:city":"Miranda",
    "sg:orig_category":"Sanatorios M\u00c9dico",
    "sg:phone":"+34 968 16 94 26",
    "sg:postcode":"30319",
    "sg:province":"Murcia",
    "wof:name":"Servicio Murciano De Salud Centros Provinciales",
    "wof:placetype":"venue"
},
  "geometry": {"coordinates":[-1.0148609877,37.6664352417],"type":"Point"}
}