{
  "type": "Feature",
  "properties": {
    "addr:full":"Calle de Hortaleza, 106 Madrid Madrid 28004",
    "addr:housenumber":"106",
    "addr:postcode":"28004",
    "addr:street":"Calle De Hortaleza",
    "iso:country":"ES",
    "sg:address":"Calle de Hortaleza, 106",
    "sg:city":"Madrid",
    "sg:orig_category":"Abogados",
    "sg:phone":"+34 913 19 34 81",
    "sg:postcode":"28004",
    "sg:province":"Madrid",
    "wof:name":"Gonzalez Garcia Francisco Felix",
    "wof:placetype":"venue"
},
  "geometry": {"coordinates":[-3.6974339485,40.4253005981],"type":"Point"}
}