{
  "type": "Feature",
  "properties": {
    "iso:country":"ES",
    "sg:address":"Calle de Virgen De Los Milagros, 62",
    "sg:city":"Puerto De Santa Maria",
    "sg:orig_category":"Comerciantes Al Por Mayor De Vinos, Licores Y Alcoholes",
    "sg:phone":"+34 956 54 21 64",
    "sg:postcode":"11500",
    "sg:province":"C\u00e1diz",
    "wof:name":"Garcia Arcila Ramon",
    "wof:placetype":"venue"
},
  "geometry": {"coordinates":[-6.2237448692,36.6012039185],"type":"Point"}
}