{
  "type": "Feature",
  "properties": {
    "addr:full":"Calle de Virgen De Los Milagros, 62 Puerto De Santa Maria C\u00e1diz 11500",
    "addr:housenumber":"62",
    "addr:postcode":"11500",
    "addr:street":"Calle De Virgen De Los Milagros;Ca\u0301Diz",
    "iso:country":"ES",
    "sg:address":"Calle de Virgen De Los Milagros, 62",
    "sg:city":"Puerto De Santa Maria",
    "sg:orig_category":"Comerciantes Al Por Mayor De Vinos, Licores Y Alcoholes",
    "sg:phone":"+34 956 54 21 64",
    "sg:postcode":"11500",
    "sg:province":"C\u00e1diz",
    "wof:name":"Garcia Arcila Ramon",
    "wof:placetype":"venue"
},
  "geometry": {"coordinates":[-6.2237448692,36.6012039185],"type":"Point"}
}