{
  "type": "Feature",
  "properties": {
    "iso:country":"ES",
    "sg:address":"Calle de Leopoldo Romeo, 13",
    "sg:city":"Zaragoza",
    "sg:orig_category":"Bisuter\u00cda, Joyer\u00cda, Relojer\u00cda (al Por Menor)",
    "sg:phone":"+34 976 59 78 14",
    "sg:postcode":"50002",
    "sg:province":"Zaragoza",
    "wof:name":"Moreno Calabia Jose Ignacio",
    "wof:placetype":"venue"
},
  "geometry": {"coordinates":[-0.8637589812,41.6466598511],"type":"Point"}
}