{
  "type": "Feature",
  "properties": {
    "iso:country":"ES",
    "sg:address":"Carrer de Assalt (de L'), 14",
    "sg:city":"Tarragona",
    "sg:orig_category":"Abogados",
    "sg:phone":"+34 977 22 00 55",
    "sg:postcode":"43003",
    "sg:province":"Tarragona",
    "wof:name":"Vives Vives Francisco",
    "wof:placetype":"venue"
},
  "geometry": {"coordinates":[1.2519999743,41.1164207458],"type":"Point"}
}