{
  "type": "Feature",
  "properties": {
    "addr:full":"Ctra. H-sevilla, Km. 0016,0 S. Juan Puerto Huelva 21610",
    "addr:postcode":"21610",
    "addr:street":"Ctra. H-Sevilla Km. 0016,0 S. Juan Puerto",
    "iso:country":"ES",
    "sg:address":"Ctra. H-sevilla, Km. 0016,0",
    "sg:city":"S. Juan Puerto",
    "sg:orig_category":"Negocio De Madera",
    "sg:phone":"+34 959 35 62 50",
    "sg:postcode":"21610",
    "sg:province":"Huelva",
    "wof:name":"Explotaciones Forestales Alvarez S.a.",
    "wof:placetype":"venue"
},
  "geometry": {"coordinates":[-6.8440890312,37.3149261475],"type":"Point"}
}