{
  "type": "Feature",
  "properties": {
    "addr:full":"Calle de Fernan Gonzalez, 44 Madrid Madrid 28009",
    "addr:housenumber":"44",
    "addr:postcode":"madrid;28009",
    "addr:street":"Calle De Fernan Gonzalez",
    "iso:country":"ES",
    "sg:address":"Calle de Fernan Gonzalez, 44",
    "sg:city":"Madrid",
    "sg:orig_category":"Chapister\u00cda",
    "sg:phone":"+34 915 74 48 44",
    "sg:postcode":"28009",
    "sg:province":"Madrid",
    "wof:name":"Prestige Import Status S.l.",
    "wof:placetype":"venue"
},
  "geometry": {"coordinates":[-3.6746931076,40.4199142456],"type":"Point"}
}