{
  "type": "Feature",
  "properties": {
    "iso:country":"ES",
    "sg:address":"Av Icaria, 148",
    "sg:city":"Barcelona",
    "sg:orig_category":"Bancos",
    "sg:phone":"+34 932 21 07 64",
    "sg:postcode":"08005",
    "sg:province":"Barcelona",
    "sg:website":"www.bancopopular.es",
    "wof:name":"Banco Popular Espa\u00f1ol S.a.",
    "wof:placetype":"venue"
},
  "geometry": {"coordinates":[2.1962809563,41.390247345],"type":"Point"}
}