{
  "type": "Feature",
  "properties": {
    "iso:country":"ES",
    "sg:address":"Calle de Cervantes, 41",
    "sg:city":"Saceruela",
    "sg:orig_category":"Cajas Para Embalar",
    "sg:phone":"+34 926 77 90 46",
    "sg:postcode":"13414",
    "sg:province":"Ciudad Real",
    "wof:name":"Caja Rural De Ciudad Real",
    "wof:placetype":"venue"
},
  "geometry": {"coordinates":[-4.6081233025,38.9431915283],"type":"Point"}
}