{
  "type": "Feature",
  "properties": {
    "iso:country":"ES",
    "sg:address":"Carr Ejercito Del Aire, 21",
    "sg:city":"Pai I Capellans",
    "sg:orig_category":"Lacadores",
    "sg:phone":"+34 961 57 90 49",
    "sg:postcode":"46930",
    "sg:province":"Valencia",
    "wof:name":"Piquer Casany Jose Vicente",
    "wof:placetype":"venue"
},
  "geometry": {"coordinates":[-0.4419890046,39.482711792],"type":"Point"}
}