{
  "type": "Feature",
  "properties": {
    "addr:full":"Calle de Ferial, S/n Gomara Soria 42120",
    "addr:postcode":"42120",
    "addr:street":"Calle De Ferial S / N Gomara",
    "iso:country":"ES",
    "sg:address":"Calle de Ferial, S/n",
    "sg:city":"Gomara",
    "sg:orig_category":"Producci\u00d3n De Abonos Y De Fertilizantes",
    "sg:phone":"+34 975 38 00 96",
    "sg:postcode":"42120",
    "sg:province":"Soria",
    "wof:name":"Uriel Tovar Y Milla S. A.",
    "wof:placetype":"venue"
},
  "geometry": {"coordinates":[-2.2230629921,41.623878479],"type":"Point"}
}