{
  "type": "Feature",
  "properties": {
    "iso:country":"ES",
    "sg:address":"Calle de San Joaquin, 12",
    "sg:city":"Madrid",
    "sg:orig_category":"Peluqueros: De Se\u00d1oras",
    "sg:phone":"+34 915 31 51 62",
    "sg:postcode":"28004",
    "sg:province":"Madrid",
    "wof:name":"Perlisal S. A. L.",
    "wof:placetype":"venue"
},
  "geometry": {"coordinates":[-3.7015380859,40.4245300293],"type":"Point"}
}