{
  "type": "Feature",
  "properties": {
    "iso:country":"ES",
    "sg:address":"Carr Arnau Gatell, 7",
    "sg:city":"Blanes",
    "sg:orig_category":"Asilos De Ancianos. Centros Privados",
    "sg:phone":"+34 972 35 11 48",
    "sg:postcode":"17300",
    "sg:province":"Girona",
    "wof:name":"Batista Alejo Isabel",
    "wof:placetype":"venue"
},
  "geometry": {"coordinates":[2.7818629742,41.6763572693],"type":"Point"}
}