{
  "type": "Feature",
  "properties": {
    "addr:full":"Avda Madrid, 24 Cambados Pontevedra 36630",
    "addr:housenumber":"24",
    "addr:postcode":"36630",
    "addr:street":"Avda Madrid",
    "iso:country":"ES",
    "sg:address":"Avda Madrid, 24",
    "sg:city":"Cambados",
    "sg:orig_category":"Fotograf\u00cda Art\u00cdstica Y Retratos",
    "sg:phone":"+34 986 54 21 82",
    "sg:postcode":"36630",
    "sg:province":"Pontevedra",
    "wof:name":"Vazquez Vazquez Marcelino",
    "wof:placetype":"venue"
},
  "geometry": {"coordinates":[-8.8135318756,42.5166015625],"type":"Point"}
}