{
  "type": "Feature",
  "properties": {
    "iso:country":"ES",
    "sg:address":"Carrer de Cami Roma, 49",
    "sg:city":"Granollers",
    "sg:orig_category":"Empresarios Y Productoras De Espect\u00c1culos",
    "sg:phone":"+34 938 40 49 53",
    "sg:postcode":"08402",
    "sg:province":"Barcelona",
    "wof:name":"Saez De Tejeda Escandon Vicente",
    "wof:placetype":"venue"
},
  "geometry": {"coordinates":[2.2920019627,41.6167907715],"type":"Point"}
}