{
  "type": "Feature",
  "properties": {
    "addr:full":"Avda Virgen De Fatima (de), 30 Cordoba C\u00f3rdoba 14014",
    "addr:postcode":"14014",
    "addr:street":"Avda Virgen;Co\u0301Rdoba",
    "iso:country":"ES",
    "sg:address":"Avda Virgen De Fatima (de), 30",
    "sg:city":"Cordoba",
    "sg:orig_category":"Arreglo, Reparaci\u00d3n, Piezas Sueltas De Televisi\u00d3n, V\u00cddeo, Hi",
    "sg:phone":"+34 957 43 35 85",
    "sg:postcode":"14014",
    "sg:province":"C\u00f3rdoba",
    "wof:name":"Cruz Ortega Francisco",
    "wof:placetype":"venue"
},
  "geometry": {"coordinates":[-4.7572760582,37.8978691101],"type":"Point"}
}