{
  "type": "Feature",
  "properties": {
    "iso:country":"ES",
    "sg:address":"Av Mistral, 44",
    "sg:city":"Barcelona",
    "sg:orig_category":"Asesor\u00cda Sobre Comunicaci\u00d3n De Empresas",
    "sg:phone":"+34 933 25 90 08",
    "sg:postcode":"08015",
    "sg:province":"Barcelona",
    "wof:name":"Muratet S. A.",
    "wof:placetype":"venue"
},
  "geometry": {"coordinates":[2.1552259922,41.376537323],"type":"Point"}
}