{
  "type": "Feature",
  "properties": {
    "addr:full":"Calle de Maestra, 137 Mancha Real Ja\u00e9n 23100",
    "addr:housenumber":"137",
    "addr:postcode":"23100",
    "addr:street":"Calle De Maestra",
    "iso:country":"ES",
    "sg:address":"Calle de Maestra, 137",
    "sg:city":"Mancha Real",
    "sg:orig_category":"Inform\u00c1tica (estudios, Servicios, Asesor\u00cda, Formaci\u00d3n)",
    "sg:phone":"+34 953 35 50 41",
    "sg:postcode":"23100",
    "sg:province":"Ja\u00e9n",
    "sg:website":"www.amsystem.es",
    "wof:name":"Am System S.l.",
    "wof:placetype":"venue"
},
  "geometry": {"coordinates":[-3.6084704399,37.786529541],"type":"Point"}
}