{
  "type": "Feature",
  "properties": {
    "iso:country":"ES",
    "sg:address":"Calle de Chopo (del), 82",
    "sg:city":"Puebla Alfinden",
    "sg:orig_category":"Agencias De Aduana",
    "sg:phone":"+34 976 10 86 33",
    "sg:postcode":"50171",
    "sg:province":"Zaragoza",
    "wof:name":"Aragonesa De Aduanas Y Servicios S.l.",
    "wof:placetype":"venue"
},
  "geometry": {"coordinates":[-0.7553533912,41.6396369934],"type":"Point"}
}