{
  "type": "Feature",
  "properties": {
    "iso:country":"ES",
    "sg:address":"Limoneros, 4",
    "sg:city":"Nerja",
    "sg:orig_category":"Supermercados Y Hipermercados",
    "sg:phone":"+34 952 52 27 27",
    "sg:postcode":"29780",
    "sg:province":"M\u00e1laga",
    "wof:name":"Martin Lomas Jose",
    "wof:placetype":"venue"
},
  "geometry": {"coordinates":[-3.8675715923,36.7600708008],"type":"Point"}
}