{
  "type": "Feature",
  "properties": {
    "iso:country":"ES",
    "sg:address":"Calle de Konporte, 28",
    "sg:city":"Getxo",
    "sg:orig_category":"Bisuter\u00cda, Joyer\u00cda, Relojer\u00cda (al Por Menor)",
    "sg:phone":"+34 944 91 32 82",
    "sg:postcode":"48990",
    "sg:province":"Vizcaya",
    "wof:name":"Imanol Saralegi A\u00f1abeitia",
    "wof:placetype":"venue"
},
  "geometry": {"coordinates":[-3.0065000057,43.3450164795],"type":"Point"}
}