{
  "type": "Feature",
  "properties": {
    "addr:full":"Carrer de Tomas Ortu\u00d1o, 63 Benidorm Alicante 03500",
    "addr:housenumber":"63",
    "addr:postcode":"03500",
    "addr:street":"Carrer De Tomas Ortun\u0303O",
    "iso:country":"ES",
    "sg:address":"Carrer de Tomas Ortu\u00d1o, 63",
    "sg:city":"Benidorm",
    "sg:orig_category":"Bancos",
    "sg:phone":"+34 966 80 30 04",
    "sg:postcode":"03500",
    "sg:province":"Alicante",
    "wof:name":"Banco De Valencia S.a.",
    "wof:placetype":"venue"
},
  "geometry": {"coordinates":[-0.1739459932,38.5365180969],"type":"Point"}
}