{
  "type": "Feature",
  "properties": {
    "addr:full":"Pase Ramon Maria Lili, 1 Donostia-san Sebastian Guip\u00f9zcoa 20002",
    "addr:housenumber":"1",
    "addr:postcode":"20002",
    "addr:street":"Ramon Maria Lili",
    "iso:country":"ES",
    "sg:address":"Pase Ramon Maria Lili, 1",
    "sg:city":"Donostia-san Sebastian",
    "sg:orig_category":"Abogados",
    "sg:phone":"+34 943 32 04 00",
    "sg:postcode":"20002",
    "sg:province":"Guip\u00f9zcoa",
    "wof:name":"Miragaya Salda\u00f1a Gregorio",
    "wof:placetype":"venue"
},
  "geometry": {"coordinates":[-1.9789969921,43.3235855103],"type":"Point"}
}