{
  "type": "Feature",
  "properties": {
    "iso:country":"ES",
    "sg:address":"Av Delfines, Los, 22",
    "sg:city":"Delfines",
    "sg:orig_category":"Alquiler De Veh\u00cdculos: Turismos Y Utilitarios",
    "sg:phone":"+34 971 38 80 51",
    "sg:postcode":"07769",
    "sg:province":"Islas Baleares",
    "wof:name":"Avis Alquile Un Coche S.a.",
    "wof:placetype":"venue"
},
  "geometry": {"coordinates":[3.8025012016,39.9989891052],"type":"Point"}
}