{
  "type": "Feature",
  "properties": {
    "iso:country":"ES",
    "sg:address":"Calle de Pardica, 10",
    "sg:city":"Solana",
    "sg:orig_category":"Comercio, Reparaci\u00d3n De Bicicletas, De Motocicletas, De Accesorios",
    "sg:phone":"+34 926 63 16 10",
    "sg:postcode":"13240",
    "sg:province":"Ciudad Real",
    "wof:name":"Leon Naranjo Saturnino",
    "wof:placetype":"venue"
},
  "geometry": {"coordinates":[-3.2372190952,38.9409408569],"type":"Point"}
}