{
  "type": "Feature",
  "properties": {
    "addr:full":"Ctra. Alguazas, S/n Molina Segura Murcia 30500",
    "addr:housenumber":"s",
    "addr:postcode":"30500",
    "addr:street":"Ctra. Alguazas;/ N Molina",
    "iso:country":"ES",
    "sg:address":"Ctra. Alguazas, S/n",
    "sg:city":"Molina Segura",
    "sg:orig_category":"Chapister\u00cda",
    "sg:phone":"+34 968 61 57 81",
    "sg:postcode":"30500",
    "sg:province":"Murcia",
    "wof:name":"Jover Cordoba Juan Miguel",
    "wof:placetype":"venue"
},
  "geometry": {"coordinates":[-1.2119740248,38.0535736084],"type":"Point"}
}