{
  "type": "Feature",
  "properties": {
    "addr:full":"Plaz El Rollo, 11 Tejeda Tietar C\u00e1ceres 10420",
    "addr:housenumber":"11",
    "addr:postcode":"10420",
    "addr:street":"Rollo;Ca\u0301Ceres",
    "iso:country":"ES",
    "sg:address":"Plaz El Rollo, 11",
    "sg:city":"Tejeda Tietar",
    "sg:orig_category":"Asesor\u00cda Fiscal Y Jur\u00cddica",
    "sg:phone":"+34 927 46 91 91",
    "sg:postcode":"10420",
    "sg:province":"C\u00e1ceres",
    "sg:website":"www.gefiscal.com",
    "wof:name":"Gefisvae S.a.",
    "wof:placetype":"venue"
},
  "geometry": {"coordinates":[-6.3707604408,39.4761772156],"type":"Point"}
}