{
  "type": "Feature",
  "properties": {
    "addr:full":"Calle de Pedro Coca, 18 Albacete Albacete 02004",
    "addr:housenumber":"18",
    "addr:postcode":"02004",
    "addr:street":"Calle De Pedro Coca",
    "iso:country":"ES",
    "sg:address":"Calle de Pedro Coca, 18",
    "sg:city":"Albacete",
    "sg:orig_category":"M\u00c9dicos: Neurolog\u00cda",
    "sg:phone":"+34 967 50 62 85",
    "sg:postcode":"02004",
    "sg:province":"Albacete",
    "wof:name":"Marin Blazquez Pedro",
    "wof:placetype":"venue"
},
  "geometry": {"coordinates":[-1.8608820438,38.9929351807],"type":"Point"}
}