{
  "type": "Feature",
  "properties": {
    "addr:full":"Calle de San Cristobal, 2 Fuentespreadas Zamora 49714",
    "addr:housenumber":"2",
    "addr:postcode":"49714",
    "addr:street":"Calle De San Cristobal",
    "iso:country":"ES",
    "sg:address":"Calle de San Cristobal, 2",
    "sg:city":"Fuentespreadas",
    "sg:orig_category":"Empresas De Carpinter\u00cda Met\u00c1lica",
    "sg:phone":"+34 980 57 58 99",
    "sg:postcode":"49714",
    "sg:province":"Zamora",
    "wof:name":"Danser S.l.",
    "wof:placetype":"venue"
},
  "geometry": {"coordinates":[-5.6275281906,41.3252868652],"type":"Point"}
}