{
  "type": "Feature",
  "properties": {
    "addr:full":"Paseo Landabarri Bidea, 1 Leioa Vizcaya 48940",
    "addr:housenumber":"1",
    "addr:postcode":"48940",
    "addr:street":"Paseo Landabarri Bidea",
    "iso:country":"ES",
    "sg:address":"Paseo Landabarri Bidea, 1",
    "sg:city":"Leioa",
    "sg:orig_category":"Ingeniero",
    "sg:phone":"+34 944 02 52 28",
    "sg:postcode":"48940",
    "sg:province":"Vizcaya",
    "sg:website":"www.arson.es",
    "wof:name":"Ingenieria Arson, S.l.",
    "wof:placetype":"venue"
},
  "geometry": {"coordinates":[-2.9953200817,43.3303604126],"type":"Point"}
}