{
  "type": "Feature",
  "properties": {
    "iso:country":"ES",
    "sg:address":"Calle de Caleruega, 17",
    "sg:city":"Madrid",
    "sg:classifiers":[
        {
            "category":"Autos & Motor Vehicles",
            "subcategory":"Automobile Sales",
            "type":"Retail Goods"
        }
    ],
    "sg:phone":"+34 913 83 35 14",
    "sg:postcode":"28033",
    "sg:province":"Madrid",
    "wof:name":"Albema Auto S.l.",
    "wof:placetype":"venue"
},
  "geometry": {"coordinates":[-3.6700282097,40.4778671265],"type":"Point"}
}