{
  "type": "Feature",
  "properties": {
    "iso:country":"ES",
    "sg:address":"Ctra Santander-meres, Km. 0007,0",
    "sg:city":"Ti\u00f1ana",
    "sg:orig_category":"Muebles, Minoristas",
    "sg:phone":"+34 985 79 14 56",
    "sg:postcode":"33199",
    "sg:province":"Asturias",
    "wof:name":"Noroest Del Mueble S.l.",
    "wof:placetype":"venue"
},
  "geometry": {"coordinates":[-5.7986898422,43.3584632874],"type":"Point"}
}