{
  "type": "Feature",
  "properties": {
    "addr:full":"Calle de Carlos Asensio Bretones, 44 Oviedo Asturias 33009",
    "addr:housenumber":"44",
    "addr:postcode":"33009",
    "addr:street":"Calle De Carlos Asensio Bretones",
    "iso:country":"ES",
    "sg:address":"Calle de Carlos Asensio Bretones, 44",
    "sg:city":"Oviedo",
    "sg:orig_category":"Empresas De Limpieza",
    "sg:phone":"+34 985 22 31 76",
    "sg:postcode":"33009",
    "sg:province":"Asturias",
    "wof:name":"Nieto Juarez Jose Ramon",
    "wof:placetype":"venue"
},
  "geometry": {"coordinates":[-5.8396177292,43.3579521179],"type":"Point"}
}