{
  "type": "Feature",
  "properties": {
    "addr:full":"Calle de Miraflores, 8 Santa Cruz De Tenerife Santa Cruz De Tenerife 38003",
    "addr:housenumber":"8",
    "addr:postcode":"38003",
    "addr:street":"Calle De Miraflores",
    "iso:country":"ES",
    "sg:address":"Calle de Miraflores, 8",
    "sg:city":"Santa Cruz De Tenerife",
    "sg:orig_category":"Asesor\u00cda Fiscal Y Jur\u00cddica",
    "sg:phone":"+34 922 24 96 25",
    "sg:postcode":"38003",
    "sg:province":"Santa Cruz De Tenerife",
    "wof:name":"Grupo De Compras Canario De Articulos Deportivos S.a.",
    "wof:placetype":"venue"
},
  "geometry": {"coordinates":[-16.3326644897,28.4846744537],"type":"Point"}
}