{
  "type": "Feature",
  "properties": {
    "iso:country":"ES",
    "sg:address":"Carrer de Esglesia, 1",
    "sg:city":"S. Andreu Barca",
    "sg:orig_category":"Agencias De Trabajo Temporal",
    "sg:phone":"+34 936 82 07 04",
    "sg:postcode":"08740",
    "sg:province":"Barcelona",
    "sg:website":"www.adecco.es",
    "wof:name":"Adecco E.t.t. S.a.",
    "wof:placetype":"venue"
},
  "geometry": {"coordinates":[1.9750311375,41.4473800659],"type":"Point"}
}