{
  "type": "Feature",
  "properties": {
    "iso:country":"ES",
    "sg:address":"Avda Matias Saenz De Tejada, 3",
    "sg:city":"Fuengirola",
    "sg:orig_category":"Servidores Y Editores De Bases De Datos",
    "sg:phone":"+34 952 58 57 11",
    "sg:postcode":"29640",
    "sg:province":"M\u00e1laga",
    "wof:name":"Hello Fuengirola S.c.",
    "wof:placetype":"venue"
},
  "geometry": {"coordinates":[-4.6228170395,36.5413589478],"type":"Point"}
}