{
  "type": "Feature",
  "properties": {
    "iso:country":"ES",
    "sg:address":"Calle de Cordoba, 72",
    "sg:city":"Viso",
    "sg:orig_category":"Cooperativas Agr\u00cdcolas",
    "sg:phone":"+34 957 12 74 64",
    "sg:postcode":"14470",
    "sg:province":"C\u00f3rdoba",
    "wof:name":"Mu\u00f1oz Gomez Jose",
    "wof:placetype":"venue"
},
  "geometry": {"coordinates":[-4.9560308456,38.4804267883],"type":"Point"}
}