{
  "type": "Feature",
  "properties": {
    "iso:country":"ES",
    "sg:address":"Carr Maestro Valentin Puig, 20",
    "sg:city":"Turis",
    "sg:classifiers":[
        {
            "category":"Professional",
            "subcategory":"Management & Consulting",
            "type":"Services"
        }
    ],
    "sg:phone":"+34 962 52 67 23",
    "sg:postcode":"46389",
    "sg:province":"Valencia",
    "sg:tags":[
        "asesor\u00cda",
        "en",
        "marketing"
    ],
    "wof:name":"Iranzo Torres Jose",
    "wof:placetype":"venue"
},
  "geometry": {"coordinates":[-0.7123050094,39.3867149353],"type":"Point"}
}