{
  "type": "Feature",
  "properties": {
    "addr:full":"Calle de Santa Aurora, 5 Tomelloso Ciudad Real 13700",
    "addr:housenumber":"5",
    "addr:postcode":"13700",
    "addr:street":"Calle De Santa Aurora",
    "iso:country":"ES",
    "sg:address":"Calle de Santa Aurora, 5",
    "sg:city":"Tomelloso",
    "sg:orig_category":"Promotores Constructores",
    "sg:phone":"+34 926 51 28 55",
    "sg:postcode":"13700",
    "sg:province":"Ciudad Real",
    "wof:name":"Construcciones Sfag S.l.",
    "wof:placetype":"venue"
},
  "geometry": {"coordinates":[-3.0246639252,39.1511688232],"type":"Point"}
}