{
  "type": "Feature",
  "properties": {
    "iso:country":"ES",
    "sg:address":"Calle de Antonio Lopez, 57",
    "sg:city":"Madrid",
    "sg:orig_category":"Ropa Para Se\u00d1oras (al Por Menor)",
    "sg:phone":"+34 915 60 40 24",
    "sg:postcode":"28019",
    "sg:province":"Madrid",
    "wof:name":"Elena Ortiz S.l.",
    "wof:placetype":"venue"
},
  "geometry": {"coordinates":[-3.7090895176,40.3945617676],"type":"Point"}
}