{
  "type": "Feature",
  "properties": {
    "addr:full":"Urb Ric Mar, S/n Elviria M\u00e1laga 29604",
    "addr:postcode":"29604",
    "addr:street":"Urb Ric Mar S / N Elviria Ma\u0301Laga",
    "iso:country":"ES",
    "sg:address":"Urb Ric Mar, S/n",
    "sg:city":"Elviria",
    "sg:orig_category":"Traductores",
    "sg:phone":"+34 952 83 09 54",
    "sg:postcode":"29604",
    "sg:province":"M\u00e1laga",
    "wof:name":"Antunez Corrales Fernando",
    "wof:placetype":"venue"
},
  "geometry": {"coordinates":[-4.7839570045,36.4972267151],"type":"Point"}
}