{
  "type": "Feature",
  "properties": {
    "iso:country":"ES",
    "sg:address":"Calle de Iglesia, 17",
    "sg:city":"Moralzarzal",
    "sg:orig_category":"Flores Y Plantas Naturales (al Por Mayor)",
    "sg:phone":"+34 918 57 85 27",
    "sg:postcode":"28411",
    "sg:province":"Madrid",
    "wof:name":"Klobuznik  Hans",
    "wof:placetype":"venue"
},
  "geometry": {"coordinates":[-3.9722459316,40.6800804138],"type":"Point"}
}