{
  "type": "Feature",
  "properties": {
    "iso:country":"ES",
    "sg:address":"Pl Rector Rubi, 3",
    "sg:city":"Manacor",
    "sg:orig_category":"Ortopedia General",
    "sg:phone":"+34 971 55 26 14",
    "sg:postcode":"07500",
    "sg:province":"Islas Baleares",
    "wof:name":"Ascaso Garcia Angel",
    "wof:placetype":"venue"
},
  "geometry": {"coordinates":[3.2111263275,39.5688552856],"type":"Point"}
}