{
  "type": "Feature",
  "properties": {
    "iso:country":"ES",
    "sg:address":"Avda Jose Antonio, 4",
    "sg:city":"Coca",
    "sg:orig_category":"Resinas Sint\u00c9ticas (fabricaci\u00d3n, Al Por Mayor)",
    "sg:phone":"+34 921 58 65 70",
    "sg:postcode":"40480",
    "sg:province":"Segovia",
    "wof:name":"La Union Resinera Espa\u00d1ola S.a.",
    "wof:placetype":"venue"
},
  "geometry": {"coordinates":[-4.5206389427,41.2166175842],"type":"Point"}
}