{
  "type": "Feature",
  "properties": {
    "addr:full":"Carrer de Blanquerna, 63 Palma Islas Baleares 07010",
    "addr:housenumber":"63",
    "addr:postcode":"07010",
    "addr:street":"Carrer De Blanquerna",
    "iso:country":"ES",
    "sg:address":"Carrer de Blanquerna, 63",
    "sg:city":"Palma",
    "sg:orig_category":"Parques De Atracciones Y Centros De Esparcimiento",
    "sg:phone":"+34 971 29 89 39",
    "sg:postcode":"07010",
    "sg:province":"Islas Baleares",
    "wof:name":"Sarpem S.a.",
    "wof:placetype":"venue"
},
  "geometry": {"coordinates":[2.6487360001,39.5833587646],"type":"Point"}
}