{
  "type": "Feature",
  "properties": {
    "iso:country":"ES",
    "sg:address":"Cmno Madrid (de), S/n",
    "sg:city":"Humanes De Madrid",
    "sg:orig_category":"Ebanister\u00cda",
    "sg:phone":"+34 916 04 94 54",
    "sg:postcode":"28970",
    "sg:province":"Madrid",
    "wof:name":"Meka Norte S.l.",
    "wof:placetype":"venue"
},
  "geometry": {"coordinates":[-3.8181641102,40.2606811523],"type":"Point"}
}