{
  "type": "Feature",
  "properties": {
    "addr:full":"Calle de Santa Cruz, 25 Villafranca De Los Caballeros Toledo 45730",
    "addr:housenumber":"25",
    "addr:postcode":"45730",
    "addr:street":"Calle De Santa Cruz",
    "iso:country":"ES",
    "sg:address":"Calle de Santa Cruz, 25",
    "sg:city":"Villafranca De Los Caballeros",
    "sg:orig_category":"Molduras, Junquillos, Listones Y Molduras Perforadas",
    "sg:phone":"+34 926 57 80 31",
    "sg:postcode":"45730",
    "sg:province":"Toledo",
    "wof:name":"Cao Castro Gonzalo",
    "wof:placetype":"venue"
},
  "geometry": {"coordinates":[-3.3628790379,39.4249610901],"type":"Point"}
}