{
  "type": "Feature",
  "properties": {
    "iso:country":"ES",
    "sg:address":"Calle de Dominguez Bordona, 9",
    "sg:city":"Ciudad Rodrigo",
    "sg:orig_category":"Abogados",
    "sg:phone":"+34 923 48 19 23",
    "sg:postcode":"37500",
    "sg:province":"Salamanca",
    "wof:name":"Dominguez Riba Pablo",
    "wof:placetype":"venue"
},
  "geometry": {"coordinates":[-6.5318818092,40.595867157],"type":"Point"}
}