{
  "type": "Feature",
  "properties": {
    "iso:country":"ES",
    "sg:address":"Calle de Argelillo, 7",
    "sg:city":"Alfaro",
    "sg:orig_category":"Loter\u00cda Y T\u00d3mbola",
    "sg:phone":"+34 941 18 39 80",
    "sg:postcode":"26540",
    "sg:province":"La Rioja",
    "sg:website":"www.loteriasarellano.com",
    "wof:name":"Arellano Martinez Roberto",
    "wof:placetype":"venue"
},
  "geometry": {"coordinates":[-1.8903882504,42.1615066528],"type":"Point"}
}