{
  "type": "Feature",
  "properties": {
    "iso:country":"ES",
    "sg:address":"Avda Espa\u00d1a, 2",
    "sg:city":"Hervas",
    "sg:orig_category":"Supermercados Y Hipermercados",
    "sg:phone":"+34 927 48 13 74",
    "sg:postcode":"10700",
    "sg:province":"C\u00e1ceres",
    "wof:name":"Martinez Perez Faustino",
    "wof:placetype":"venue"
},
  "geometry": {"coordinates":[-5.8629670143,40.2745704651],"type":"Point"}
}