{
  "type": "Feature",
  "properties": {
    "addr:full":"Calle de Puerto De Galapagar, 6 Madrid Madrid 28031",
    "addr:housenumber":"6",
    "addr:postcode":"28031",
    "addr:street":"Calle De Puerto De Galapagar",
    "iso:country":"ES",
    "sg:address":"Calle de Puerto De Galapagar, 6",
    "sg:city":"Madrid",
    "sg:orig_category":"Construcciones Met\u00c1licas",
    "sg:phone":"+34 913 32 65 88",
    "sg:postcode":"28031",
    "sg:province":"Madrid",
    "wof:name":"Mercados E Industrias S.l.",
    "wof:placetype":"venue"
},
  "geometry": {"coordinates":[-3.6187410355,40.3732223511],"type":"Point"}
}