{
  "type": "Feature",
  "properties": {
    "addr:full":"Carr Professor Fassman, 8 Sort Lleida 25560",
    "addr:housenumber":"8",
    "addr:postcode":"25560",
    "addr:street":"Carr Professor Fassman",
    "iso:country":"ES",
    "sg:address":"Carr Professor Fassman, 8",
    "sg:city":"Sort",
    "sg:orig_category":"Negocio De Enlosados, Soler\u00cdas",
    "sg:phone":"+34 973 62 01 69",
    "sg:postcode":"25560",
    "sg:province":"Lleida",
    "wof:name":"Sanchez Valero Sebastian",
    "wof:placetype":"venue"
},
  "geometry": {"coordinates":[1.1310700178,42.4111595154],"type":"Point"}
}