{
  "type": "Feature",
  "properties": {
    "addr:full":"G.v. Carles Iii, 50 Barcelona Barcelona 08028",
    "addr:housenumber":"50",
    "addr:postcode":"08028",
    "iso:country":"ES",
    "sg:address":"G.v. Carles Iii, 50",
    "sg:city":"Barcelona",
    "sg:orig_category":"Inmobiliaria (agencias)",
    "sg:phone":"+34 934 09 33 84",
    "sg:postcode":"08028",
    "sg:province":"Barcelona",
    "wof:name":"Larifsex S.l",
    "wof:placetype":"venue"
},
  "geometry": {"coordinates":[2.1687450409,41.3855895996],"type":"Point"}
}