{
  "type": "Feature",
  "properties": {
    "addr:full":"Pg Gran Passeig Ronda, 134 Lleida Lleida 25008",
    "addr:housenumber":"134",
    "addr:postcode":"25008",
    "addr:street":"Pg Gran Passeig Ronda",
    "iso:country":"ES",
    "sg:address":"Pg Gran Passeig Ronda, 134",
    "sg:city":"Lleida",
    "sg:orig_category":"Frutas, Legumbres Frescas Y Tempranas (al Por Menor)",
    "sg:phone":"+34 973 22 47 89",
    "sg:postcode":"25008",
    "sg:province":"Lleida",
    "wof:name":"Hiperfruit S.l.",
    "wof:placetype":"venue"
},
  "geometry": {"coordinates":[0.6193320155,41.6224784851],"type":"Point"}
}