{
  "type": "Feature",
  "properties": {
    "iso:country":"ES",
    "sg:address":"Calle de Salvador Minguijon, 56",
    "sg:city":"Zaragoza",
    "sg:orig_category":"Tintorer\u00cdas, Limpieza En Seco",
    "sg:phone":"+34 976 41 67 03",
    "sg:postcode":"50002",
    "sg:province":"Zaragoza",
    "wof:name":"Quevedo Ortiz Monica",
    "wof:placetype":"venue"
},
  "geometry": {"coordinates":[-0.8611009717,41.6493911743],"type":"Point"}
}