{
  "type": "Feature",
  "properties": {
    "addr:full":"Ctra Madrid, Km. 0168,4 Mojados Valladolid 47250",
    "addr:postcode":"47250",
    "addr:street":"Ctra Madrid Km. 0168,4",
    "iso:country":"ES",
    "sg:address":"Ctra Madrid, Km. 0168,4",
    "sg:city":"Mojados",
    "sg:orig_category":"Distribuci\u00d3n De Petr\u00d3leo Y Derivados",
    "sg:phone":"+34 983 60 76 05",
    "sg:postcode":"47250",
    "sg:province":"Valladolid",
    "wof:name":"Repsol Ypf S.a.",
    "wof:placetype":"venue"
},
  "geometry": {"coordinates":[-4.6654090881,41.4321861267],"type":"Point"}
}