{
  "type": "Feature",
  "properties": {
    "iso:country":"ES",
    "sg:address":"Calle de Atleta Antonio Amoros, 24",
    "sg:city":"Caudete",
    "sg:orig_category":"Ortopedia General",
    "sg:phone":"+34 965 82 63 68",
    "sg:postcode":"02660",
    "sg:province":"Albacete",
    "wof:name":"Podo Ortopedia Caudete S.l.",
    "wof:placetype":"venue"
},
  "geometry": {"coordinates":[-0.984695673,38.7033843994],"type":"Point"}
}