{
  "type": "Feature",
  "properties": {
    "iso:country":"ES",
    "sg:address":"Pase General Davila, 12",
    "sg:city":"Santander",
    "sg:orig_category":"Farmacias",
    "sg:phone":"+34 942 27 12 98",
    "sg:postcode":"39005",
    "sg:province":"Cantabria",
    "wof:name":"Acebo Gomez Engracia",
    "wof:placetype":"venue"
},
  "geometry": {"coordinates":[-3.7899963856,43.468296051],"type":"Point"}
}