{
  "type": "Feature",
  "properties": {
    "addr:full":"Avda San Amador, 88 Martos Ja\u00e9n 23600",
    "addr:housenumber":"88",
    "addr:postcode":"23600",
    "addr:street":"Avda San Amador;Jae\u0301N",
    "iso:country":"ES",
    "sg:address":"Avda San Amador, 88",
    "sg:city":"Martos",
    "sg:orig_category":"Frutas Y Legumbres Secas (al Por Mayor)",
    "sg:phone":"+34 953 70 49 41",
    "sg:postcode":"23600",
    "sg:province":"Ja\u00e9n",
    "wof:name":"Bonilla Garrido Jose",
    "wof:placetype":"venue"
},
  "geometry": {"coordinates":[-3.9771680832,37.7191886902],"type":"Point"}
}