{
  "type": "Feature",
  "properties": {
    "iso:country":"ES",
    "sg:address":"Calle de Rey Abu Said, S/n",
    "sg:city":"Granada",
    "sg:orig_category":"Asesor\u00cda Sobre Comunicaci\u00d3n De Empresas",
    "sg:phone":"+34 958 12 69 19",
    "sg:postcode":"18006",
    "sg:province":"Granada",
    "wof:name":"M.calvo Asesoramiento S.l.",
    "wof:placetype":"venue"
},
  "geometry": {"coordinates":[-3.6008570194,37.1651649475],"type":"Point"}
}