{
  "type": "Feature",
  "properties": {
    "addr:full":"Grup San Ignacio, 13 Ibarra Guip\u00f9zcoa 20400",
    "addr:housenumber":"13",
    "addr:postcode":"20400",
    "addr:street":"San Ignacio;Guipu\u0300Zcoa",
    "iso:country":"ES",
    "sg:address":"Grup San Ignacio, 13",
    "sg:city":"Ibarra",
    "sg:orig_category":"Promotores Constructores",
    "sg:phone":"+34 943 67 42 94",
    "sg:postcode":"20400",
    "sg:province":"Guip\u00f9zcoa",
    "wof:name":"Iturrioz Urchipia Ramon",
    "wof:placetype":"venue"
},
  "geometry": {"coordinates":[-2.0669538975,43.1307144165],"type":"Point"}
}