{
  "type": "Feature",
  "properties": {
    "addr:full":"Av Constitucio, 101 Castelldefels Barcelona 08860",
    "addr:housenumber":"101",
    "addr:postcode":"08860",
    "addr:street":"Av Constitucio",
    "iso:country":"ES",
    "sg:address":"Av Constitucio, 101",
    "sg:city":"Castelldefels",
    "sg:orig_category":"Albergues",
    "sg:phone":"+34 936 64 26 67",
    "sg:postcode":"08860",
    "sg:province":"Barcelona",
    "wof:name":"Viatges And Sabor S. L.",
    "wof:placetype":"venue"
},
  "geometry": {"coordinates":[1.9797320366,41.2803153992],"type":"Point"}
}