{
  "type": "Feature",
  "properties": {
    "iso:country":"ES",
    "sg:address":"C/ Carrotja, 3",
    "sg:city":"Porto Cristo",
    "sg:orig_category":"Cristaler\u00cdas",
    "sg:phone":"+34 971 82 06 80",
    "sg:postcode":"07680",
    "sg:province":"Islas Baleares",
    "wof:name":"Cristaleria Porto Cristo Instalaciones S.l.",
    "wof:placetype":"venue"
},
  "geometry": {"coordinates":[3.3381659985,39.5450439453],"type":"Point"}
}