{
  "type": "Feature",
  "properties": {
    "iso:country":"ES",
    "sg:address":"Calle de Olivo, 10",
    "sg:city":"Madrid",
    "sg:orig_category":"Caf\u00c9s, Bares, Cervecer\u00cdas",
    "sg:phone":"+34 913 07 80 49",
    "sg:postcode":"28023",
    "sg:province":"Madrid",
    "wof:name":"Cafeteria Jamer S.l.",
    "wof:placetype":"venue"
},
  "geometry": {"coordinates":[-3.7799880505,40.4590187073],"type":"Point"}
}