{
  "type": "Feature",
  "properties": {
    "iso:country":"ES",
    "sg:address":"Carretera Paracuellos, S/n",
    "sg:city":"Savi\u00f1an",
    "sg:orig_category":"Semiller\u00cdas",
    "sg:phone":"+34 976 82 54 49",
    "sg:postcode":"50299",
    "sg:province":"Zaragoza",
    "wof:name":"Jardinfruit S.l.",
    "wof:placetype":"venue"
},
  "geometry": {"coordinates":[-1.5623990297,41.423828125],"type":"Point"}
}