{
  "type": "Feature",
  "properties": {
    "addr:full":"Plaz Constitucion, 3 Riogordo M\u00e1laga 29180",
    "addr:housenumber":"3",
    "addr:postcode":"29180",
    "addr:street":"Constitucion;Ma\u0301Laga",
    "iso:country":"ES",
    "sg:address":"Plaz Constitucion, 3",
    "sg:city":"Riogordo",
    "sg:orig_category":"Bibliotecas, Mediatecas",
    "sg:phone":"+34 952 73 21 60",
    "sg:postcode":"29180",
    "sg:province":"M\u00e1laga",
    "sg:website":"www.unicaja.es",
    "wof:name":"Unicaja",
    "wof:placetype":"venue"
},
  "geometry": {"coordinates":[-4.2936968803,36.9150772095],"type":"Point"}
}