{
  "type": "Feature",
  "properties": {
    "iso:country":"ES",
    "sg:address":"Calle de Gran Via, 45",
    "sg:city":"Salamanca",
    "sg:orig_category":"Abogados",
    "sg:phone":"+34 923 27 05 40",
    "sg:postcode":"37001",
    "sg:province":"Salamanca",
    "wof:name":"Miguel Del Corral Garcia Maria Del Pilar",
    "wof:placetype":"venue"
},
  "geometry": {"coordinates":[-5.6604428291,40.9651985168],"type":"Point"}
}