{
  "type": "Feature",
  "properties": {
    "iso:country":"ES",
    "sg:address":"Calle de Pintor Cortina, 34",
    "sg:city":"Valencia",
    "sg:orig_category":"Mec\u00c1nico Del Autom\u00d3vil",
    "sg:phone":"+34 963 77 10 43",
    "sg:postcode":"46017",
    "sg:province":"Valencia",
    "wof:name":"Vicente Remon Jesus",
    "wof:placetype":"venue"
},
  "geometry": {"coordinates":[-0.3932789862,39.4547805786],"type":"Point"}
}