{
  "type": "Feature",
  "properties": {
    "iso:country":"ES",
    "sg:address":"Avda Banejo, 1",
    "sg:city":"Pollos",
    "sg:orig_category":"Fabricaci\u00d3n De Quesos",
    "sg:phone":"+34 983 79 30 58",
    "sg:postcode":"47116",
    "sg:province":"Valladolid",
    "wof:name":"Ca\u00f1arejal S.l.",
    "wof:placetype":"venue"
},
  "geometry": {"coordinates":[-5.1264739037,41.4428787231],"type":"Point"}
}