{
  "type": "Feature",
  "properties": {
    "iso:country":"ES",
    "sg:address":"Calle de Rosario, 16",
    "sg:city":"Carcastillo",
    "sg:orig_category":"Material Y Suministros Para Perforaciones, Sondeos",
    "sg:phone":"+34 948 72 55 43",
    "sg:postcode":"31310",
    "sg:province":"Navarra",
    "wof:name":"Miqueleiz Alfaro Orencio",
    "wof:placetype":"venue"
},
  "geometry": {"coordinates":[-1.4456357956,42.381061554],"type":"Point"}
}