{
  "type": "Feature",
  "properties": {
    "addr:full":"Av Doctor Llanso, Del, 114 Mercadal Islas Baleares 07740",
    "addr:housenumber":"114",
    "addr:postcode":"07740",
    "addr:street":"Av Doctor Llanso Del",
    "iso:country":"ES",
    "sg:address":"Av Doctor Llanso, Del, 114",
    "sg:city":"Mercadal",
    "sg:orig_category":"Estudios, Instalaci\u00d3n De Climatizaci\u00d3n",
    "sg:phone":"+34 971 15 40 63",
    "sg:postcode":"07740",
    "sg:province":"Islas Baleares",
    "wof:name":"Gonzalez Ruiz Manuel",
    "wof:placetype":"venue"
},
  "geometry": {"coordinates":[4.0938262939,39.9910240173],"type":"Point"}
}