{
  "type": "Feature",
  "properties": {
    "iso:country":"ES",
    "sg:address":"Calle de Felipe Valls, 51",
    "sg:city":"Benimamet-beniferri",
    "sg:orig_category":"Bancos",
    "sg:phone":"+34 963 40 25 55",
    "sg:postcode":"46035",
    "sg:province":"Valencia",
    "sg:website":"www.bancodevalencia.es",
    "wof:name":"Banco De Valencia S.a.",
    "wof:placetype":"venue"
},
  "geometry": {"coordinates":[-0.4190889895,39.5012016296],"type":"Point"}
}