{
  "type": "Feature",
  "properties": {
    "addr:full":"Alfonso Xiii, 2 Pedreguer Alicante 03750",
    "addr:housenumber":"2",
    "addr:postcode":"03750",
    "addr:street":"Alfonso Xiii",
    "iso:country":"ES",
    "sg:address":"Alfonso Xiii, 2",
    "sg:city":"Pedreguer",
    "sg:orig_category":"Empresas De Carpinter\u00cda De Madera",
    "sg:phone":"+34 965 76 03 35",
    "sg:postcode":"03750",
    "sg:province":"Alicante",
    "wof:name":"Fornes Fillol Alberto",
    "wof:placetype":"venue"
},
  "geometry": {"coordinates":[0.0332040004,38.7947883606],"type":"Point"}
}