{
  "type": "Feature",
  "properties": {
    "addr:full":"Carr Valenti Almirall, 16 Lleida Lleida 25004",
    "addr:housenumber":"16",
    "addr:postcode":"25004",
    "addr:street":"Carr Valenti Almirall",
    "iso:country":"ES",
    "sg:address":"Carr Valenti Almirall, 16",
    "sg:city":"Lleida",
    "sg:orig_category":"Complementos De Vestir (al Por Menor)",
    "sg:phone":"+34 973 22 57 08",
    "sg:postcode":"25004",
    "sg:province":"Lleida",
    "wof:name":"Monti Di Locura S.l.",
    "wof:placetype":"venue"
},
  "geometry": {"coordinates":[0.6270840168,41.6220436096],"type":"Point"}
}