{
  "type": "Feature",
  "properties": {
    "iso:country":"ES",
    "sg:address":"Ctra Norte Del, 142",
    "sg:city":"Palmas De Gran Canaria",
    "sg:orig_category":"Fabricaci\u00d3n, Instalaci\u00d3n Y Reparaci\u00d3n De Bombas",
    "sg:phone":"+34 928 41 03 43",
    "sg:postcode":"35013",
    "sg:province":"Las Palmas",
    "wof:name":"Inyediesel S.c.p.",
    "wof:placetype":"venue"
},
  "geometry": {"coordinates":[-15.5745563507,28.1141796112],"type":"Point"}
}