{
  "type": "Feature",
  "properties": {
    "addr:full":"Calle de Vallehermoso, 86 Madrid Madrid 28015",
    "addr:housenumber":"86",
    "addr:postcode":"madrid;28015",
    "addr:street":"Calle De Vallehermoso",
    "iso:country":"ES",
    "sg:address":"Calle de Vallehermoso, 86",
    "sg:city":"Madrid",
    "sg:orig_category":"Tiendas De Grano, Frutas Y Legumbres Secas (al Por Menor)",
    "sg:phone":"+34 915 35 00 11",
    "sg:postcode":"28015",
    "sg:province":"Madrid",
    "wof:name":"Xu  Chongfu",
    "wof:placetype":"venue"
},
  "geometry": {"coordinates":[-3.7082977295,40.4384841919],"type":"Point"}
}