{
  "type": "Feature",
  "properties": {
    "addr:full":"Carrer de Francesc Marti I M, 44 Palma Islas Baleares 07011",
    "addr:postcode":"07011",
    "addr:street":"Carrer De Francesc Marti;M",
    "iso:country":"ES",
    "sg:address":"Carrer de Francesc Marti I M, 44",
    "sg:city":"Palma",
    "sg:orig_category":"Doctores En Medicina",
    "sg:phone":"+34 971 73 91 47",
    "sg:postcode":"07011",
    "sg:province":"Islas Baleares",
    "wof:name":"Martorell Fiol Tomas",
    "wof:placetype":"venue"
},
  "geometry": {"coordinates":[2.6377239227,39.5827331543],"type":"Point"}
}