{
  "type": "Feature",
  "properties": {
    "addr:full":"Plaz Espa\u00d1a, 1 Madrid Madrid 28008",
    "addr:housenumber":"1",
    "addr:postcode":"28008",
    "addr:street":"Plaz Espan\u0303A",
    "iso:country":"ES",
    "sg:address":"Plaz Espa\u00d1a, 1",
    "sg:city":"Madrid",
    "sg:orig_category":"Bibliotecas, Mediatecas",
    "sg:phone":"+34 915 41 27 50",
    "sg:postcode":"28008",
    "sg:province":"Madrid",
    "wof:name":"Rozalen Serrano Luis",
    "wof:placetype":"venue"
},
  "geometry": {"coordinates":[-3.7112779617,40.4230270386],"type":"Point"}
}