{
  "type": "Feature",
  "properties": {
    "addr:full":"Florida, S/n Dolores Alicante 03150",
    "addr:housenumber":"/ n",
    "addr:postcode":"03150",
    "addr:street":"Florida S",
    "iso:country":"ES",
    "sg:address":"Florida, S/n",
    "sg:city":"Dolores",
    "sg:orig_category":"Almacenes Para Venta: Muebles Y Varios",
    "sg:phone":"+34 966 71 17 34",
    "sg:postcode":"03150",
    "sg:province":"Alicante",
    "wof:name":"Loherma Mdi C.b.",
    "wof:placetype":"venue"
},
  "geometry": {"coordinates":[-0.7697039843,38.1368637085],"type":"Point"}
}