{
  "type": "Feature",
  "properties": {
    "addr:full":"Plaz Espa\u00d1a, 5 Bonares Huelva 21830",
    "addr:housenumber":"5",
    "addr:postcode":"21830",
    "addr:street":"Plaz Espan\u0303A",
    "iso:country":"ES",
    "sg:address":"Plaz Espa\u00d1a, 5",
    "sg:city":"Bonares",
    "sg:orig_category":"Abogados",
    "sg:phone":"+34 959 36 61 03",
    "sg:postcode":"21830",
    "sg:province":"Huelva",
    "wof:name":"Perez Lopez Maria Jose",
    "wof:placetype":"venue"
},
  "geometry": {"coordinates":[-6.6801657677,37.3220100403],"type":"Point"}
}