{
  "type": "Feature",
  "properties": {
    "iso:country":"ES",
    "sg:address":"Carrer de Nou De La Rambla, 145",
    "sg:city":"Barcelona",
    "sg:orig_category":"Discotecas Y Salas De Baile",
    "sg:phone":"+34 933 29 00 29",
    "sg:postcode":"08004",
    "sg:province":"Barcelona",
    "wof:name":"Aurolaria S.l.",
    "wof:placetype":"venue"
},
  "geometry": {"coordinates":[2.1682291031,41.3730354309],"type":"Point"}
}