{
  "type": "Feature",
  "properties": {
    "addr:full":"Carr Camelia, 38 Badalona Barcelona 08912",
    "addr:housenumber":"38",
    "addr:postcode":"08912",
    "addr:street":"Carr Camelia",
    "iso:country":"ES",
    "sg:address":"Carr Camelia, 38",
    "sg:city":"Badalona",
    "sg:orig_category":"Calderer\u00cda",
    "sg:phone":"+34 933 98 17 40",
    "sg:postcode":"08912",
    "sg:province":"Barcelona",
    "wof:name":"Planchisteria Industrial Pe\u00f1aranda S.l.",
    "wof:placetype":"venue"
},
  "geometry": {"coordinates":[2.239303112,41.4494056702],"type":"Point"}
}