{
  "type": "Feature",
  "properties": {
    "iso:country":"ES",
    "sg:address":"Ctra. N. 340, 340",
    "sg:city":"Balanegra",
    "sg:orig_category":"Cajas De Ahorro",
    "sg:phone":"+34 950 40 63 40",
    "sg:postcode":"04713",
    "sg:province":"Almer\u00eda",
    "sg:website":"www.unicaja.es",
    "wof:name":"Unicaja",
    "wof:placetype":"venue"
},
  "geometry": {"coordinates":[-2.9070239067,36.7499694824],"type":"Point"}
}