{
  "type": "Feature",
  "properties": {
    "iso:country":"ES",
    "sg:address":"Calle de Santa Clara, 51",
    "sg:city":"Burgos",
    "sg:orig_category":"Institutos De Belleza",
    "sg:phone":"+34 947 25 56 36",
    "sg:postcode":"09002",
    "sg:province":"Burgos",
    "wof:name":"Anay Sidney 2000 S.l.",
    "wof:placetype":"venue"
},
  "geometry": {"coordinates":[-3.6941645145,42.3374557495],"type":"Point"}
}