{
  "type": "Feature",
  "properties": {
    "iso:country":"ES",
    "sg:address":"Calle de Do\u00d1a Berenguela, 13",
    "sg:city":"Madrid",
    "sg:orig_category":"Alimentaci\u00d3n General (al Por Menor)",
    "sg:phone":"+34 914 64 52 83",
    "sg:postcode":"28011",
    "sg:province":"Madrid",
    "wof:name":"Roda Melgar Antonio Ignacio",
    "wof:placetype":"venue"
},
  "geometry": {"coordinates":[-3.7260985374,40.4126281738],"type":"Point"}
}