{
  "type": "Feature",
  "properties": {
    "addr:full":"Calle de Navales, 26 Alcorcon Madrid 28925",
    "addr:housenumber":"26",
    "addr:postcode":"28925",
    "addr:street":"Calle De Navales",
    "iso:country":"ES",
    "sg:address":"Calle de Navales, 26",
    "sg:city":"Alcorcon",
    "sg:orig_category":"Chapister\u00cda",
    "sg:phone":"+34 914 86 00 97",
    "sg:postcode":"28925",
    "sg:province":"Madrid",
    "wof:name":"Claxon Carrocerias S.l.",
    "wof:placetype":"venue"
},
  "geometry": {"coordinates":[-3.8141729832,40.3379096985],"type":"Point"}
}