{
  "type": "Feature",
  "properties": {
    "iso:country":"ES",
    "sg:address":"Calle de Risco Caido, 22",
    "sg:city":"Orotava",
    "sg:orig_category":"Industria Qu\u00cdmica",
    "sg:phone":"+34 922 33 65 82",
    "sg:postcode":"38300",
    "sg:province":"Santa Cruz De Tenerife",
    "wof:name":"Mesa Rodriguez Pedro",
    "wof:placetype":"venue"
},
  "geometry": {"coordinates":[-16.514623642,28.3977489471],"type":"Point"}
}