{
  "type": "Feature",
  "properties": {
    "iso:country":"ES",
    "sg:address":"Plaz Capdepont, S/n",
    "sg:city":"Torrevieja",
    "sg:orig_category":"Contenedores (mercanc\u00cdas)",
    "sg:phone":"+34 965 71 14 91",
    "sg:postcode":"03180",
    "sg:province":"Alicante",
    "wof:name":"Esteve Mendiola Alfonso",
    "wof:placetype":"venue"
},
  "geometry": {"coordinates":[-0.6536790133,38.0173606873],"type":"Point"}
}