{
  "type": "Feature",
  "properties": {
    "iso:country":"ES",
    "sg:address":"Calle de Abajo, 32",
    "sg:city":"Redovan",
    "sg:orig_category":"Reposter\u00cdas",
    "sg:phone":"+34 966 75 47 47",
    "sg:postcode":"03370",
    "sg:province":"Alicante",
    "wof:name":"Medina Ferrer Miguel",
    "wof:placetype":"venue"
},
  "geometry": {"coordinates":[-0.904282093,38.1126823425],"type":"Point"}
}