{
  "type": "Feature",
  "properties": {
    "iso:country":"ES",
    "sg:address":"Carrer de Pare Maria Payeras, 5",
    "sg:city":"Palma",
    "sg:orig_category":"Peluqueros: De Se\u00d1oras",
    "sg:phone":"+34 971 47 20 09",
    "sg:postcode":"07008",
    "sg:province":"Islas Baleares",
    "wof:name":"Lopez Madasu Esperanza Angeles",
    "wof:placetype":"venue"
},
  "geometry": {"coordinates":[2.6741559505,39.5832328796],"type":"Point"}
}