{
  "type": "Feature",
  "properties": {
    "addr:full":"Avda Albufera, 57 Madrid Madrid 28038",
    "addr:housenumber":"57",
    "addr:postcode":"madrid;28038",
    "addr:street":"Avda Albufera",
    "iso:country":"ES",
    "sg:address":"Avda Albufera, 57",
    "sg:city":"Madrid",
    "sg:orig_category":"Cajas Para Embalar",
    "sg:phone":"+34 917 57 03 75",
    "sg:postcode":"28038",
    "sg:province":"Madrid",
    "wof:name":"Cajamar",
    "wof:placetype":"venue"
},
  "geometry": {"coordinates":[-3.6644220352,40.3958396912],"type":"Point"}
}