{
  "type": "Feature",
  "properties": {
    "iso:country":"ES",
    "sg:address":"Velazquez, 121",
    "sg:city":"Madrid",
    "sg:orig_category":"Centros De Adelgazamiento Y De Est\u00c9tica",
    "sg:phone":"+34 915 61 45 93",
    "sg:postcode":"28006",
    "sg:province":"Madrid",
    "wof:name":"Del Barrio Blanco Maria Concepcion",
    "wof:placetype":"venue"
},
  "geometry": {"coordinates":[-3.6833150387,40.4373054504],"type":"Point"}
}