{
  "type": "Feature",
  "properties": {
    "iso:country":"ES",
    "sg:address":"Calle de Puentezuelas, 25",
    "sg:city":"Granada",
    "sg:orig_category":"Telas Y Sedas (al Por Menor)",
    "sg:phone":"+34 958 26 78 42",
    "sg:postcode":"18002",
    "sg:province":"Granada",
    "wof:name":"Carrillo Martinez Concepcion Araceli",
    "wof:placetype":"venue"
},
  "geometry": {"coordinates":[-3.6018910408,37.1737098694],"type":"Point"}
}