{
  "type": "Feature",
  "properties": {
    "iso:country":"ES",
    "sg:address":"Calle de Larra, 4",
    "sg:city":"Gijon",
    "sg:orig_category":"Empresas De Carpinter\u00cda De Madera",
    "sg:phone":"+34 985 38 45 93",
    "sg:postcode":"33208",
    "sg:province":"Asturias",
    "wof:name":"Alonso Gonzalez Angel",
    "wof:placetype":"venue"
},
  "geometry": {"coordinates":[-5.6669831276,43.533241272],"type":"Point"}
}