{
  "type": "Feature",
  "properties": {
    "iso:country":"ES",
    "sg:address":"Avgd Marina, 23",
    "sg:city":"Alcudia",
    "sg:orig_category":"Reparaciones Y Remolcado De Veh\u00cdculos",
    "sg:phone":"+34 971 54 54 00",
    "sg:postcode":"07400",
    "sg:province":"Islas Baleares",
    "wof:name":"Calvo Crespi Miguel",
    "wof:placetype":"venue"
},
  "geometry": {"coordinates":[3.1133561134,39.8529396057],"type":"Point"}
}