{
  "type": "Feature",
  "properties": {
    "iso:country":"ES",
    "sg:address":"Avda Jesus Santos Rein, 23",
    "sg:city":"Fuengirola",
    "sg:orig_category":"Sociedades, Compa\u00d1\u00cdas Aseguradoras",
    "sg:phone":"+34 952 19 71 15",
    "sg:postcode":"29640",
    "sg:province":"M\u00e1laga",
    "sg:website":"www.sanimed.es",
    "wof:name":"Sanitaria Medico Quirurgica S. A.",
    "wof:placetype":"venue"
},
  "geometry": {"coordinates":[-4.6157898903,36.5526428223],"type":"Point"}
}