{
  "type": "Feature",
  "properties": {
    "iso:country":"ES",
    "sg:address":"Ctra Aguilar, 26",
    "sg:city":"Cervera Pisuerga",
    "sg:orig_category":"Chapister\u00cda",
    "sg:phone":"+34 979 87 09 08",
    "sg:postcode":"34840",
    "sg:province":"Palencia",
    "wof:name":"Carrocerias Auto-cervera S.l.",
    "wof:placetype":"venue"
},
  "geometry": {"coordinates":[-4.4180278778,42.8575897217],"type":"Point"}
}