{
  "type": "Feature",
  "properties": {
    "iso:country":"ES",
    "sg:address":"Avda Asuncion (de La), 10",
    "sg:city":"Santa Cruz De Tenerife",
    "sg:orig_category":"Agentes, Concesionarios Y Sucursales De Veh\u00cdculos",
    "sg:phone":"+34 922 28 51 52",
    "sg:postcode":"38006",
    "sg:province":"Santa Cruz De Tenerife",
    "wof:name":"Mas Motor Canarias S.l.",
    "wof:placetype":"venue"
},
  "geometry": {"coordinates":[-16.2618999481,28.4670543671],"type":"Point"}
}