{
  "type": "Feature",
  "properties": {
    "addr:full":"C/ General Balanzat, Del, 5 S. Antoni Portmany Islas Baleares 07820",
    "addr:postcode":"07820",
    "addr:street":"C / General Balanzat Del 5 S. Antoni Portmany",
    "iso:country":"ES",
    "sg:address":"C/ General Balanzat, Del, 5",
    "sg:city":"S. Antoni Portmany",
    "sg:orig_category":"Art\u00cdculos De Regalo (al Por Menor)",
    "sg:phone":"+34 971 34 44 52",
    "sg:postcode":"07820",
    "sg:province":"Islas Baleares",
    "wof:name":"Escandell Manchon Irene",
    "wof:placetype":"venue"
},
  "geometry": {"coordinates":[1.5188339949,39.1094055176],"type":"Point"}
}