{
  "type": "Feature",
  "properties": {
    "iso:country":"ES",
    "sg:address":"Avda Deportes (los), S/n",
    "sg:city":"Jimena Frontera",
    "sg:classifiers":[
        {
            "category":"Taxi",
            "type":"Transportation"
        }
    ],
    "sg:phone":"+34 956 64 01 87",
    "sg:postcode":"11330",
    "sg:province":"C\u00e1diz",
    "wof:name":"Bueno Espejo Eloy",
    "wof:placetype":"venue"
},
  "geometry": {"coordinates":[-5.4472398758,36.4319076538],"type":"Point"}
}