{
  "type": "Feature",
  "properties": {
    "iso:country":"ES",
    "sg:address":"Calle de Palma (la), 11",
    "sg:city":"Almeria",
    "sg:orig_category":"Agencias Y Agentes Comerciales, Representantes",
    "sg:phone":"+34 950 23 41 69",
    "sg:postcode":"04003",
    "sg:province":"Almer\u00eda",
    "wof:name":"Cruz Martinez Francisco",
    "wof:placetype":"venue"
},
  "geometry": {"coordinates":[-2.4614388943,36.8444786072],"type":"Point"}
}