{
  "type": "Feature",
  "properties": {
    "iso:country":"ES",
    "sg:address":"Ctra Alcoi (d'), S/n",
    "sg:city":"Albaida",
    "sg:orig_category":"Fabricaci\u00d3n De Telas Y Sedas",
    "sg:phone":"+34 962 39 80 20",
    "sg:postcode":"46860",
    "sg:province":"Valencia",
    "wof:name":"Yebane Espa\u00f1ola S. A.",
    "wof:placetype":"venue"
},
  "geometry": {"coordinates":[-0.5152012706,38.835647583],"type":"Point"}
}