{
  "type": "Feature",
  "properties": {
    "addr:full":"Carrer de Progres, 58 Hospitalet Llobregat Barcelona 08904",
    "addr:housenumber":"58",
    "addr:postcode":"08904",
    "addr:street":"Carrer De Progres",
    "iso:country":"ES",
    "sg:address":"Carrer de Progres, 58",
    "sg:city":"Hospitalet Llobregat",
    "sg:orig_category":"Talleres: Ropa A Medida",
    "sg:phone":"+34 934 49 80 68",
    "sg:postcode":"08904",
    "sg:province":"Barcelona",
    "wof:name":"Rodriguez Gamez Manuel",
    "wof:placetype":"venue"
},
  "geometry": {"coordinates":[2.1198210716,41.3736495972],"type":"Point"}
}