{
  "type": "Feature",
  "properties": {
    "addr:full":"J. Antonio, 11 Lubrin Almer\u00eda 04271",
    "addr:housenumber":"11",
    "addr:postcode":"04271",
    "addr:street":"Antonio;Almeri\u0301A",
    "iso:country":"ES",
    "sg:address":"J. Antonio, 11",
    "sg:city":"Lubrin",
    "sg:orig_category":"Cajas Para Embalar",
    "sg:phone":"+34 950 47 70 35",
    "sg:postcode":"04271",
    "sg:province":"Almer\u00eda",
    "wof:name":"Cajamar",
    "wof:placetype":"venue"
},
  "geometry": {"coordinates":[-2.0631990433,37.2203788757],"type":"Point"}
}