{
  "type": "Feature",
  "properties": {
    "iso:country":"ES",
    "sg:address":"Calle de Escultor Roque Lopez, 2",
    "sg:city":"San Miguel",
    "sg:orig_category":"Perfumer\u00cda (al Por Menor)",
    "sg:phone":"+34 968 20 26 36",
    "sg:postcode":"30008",
    "sg:province":"Murcia",
    "wof:name":"Perfumerias Gala S.l.",
    "wof:placetype":"venue"
},
  "geometry": {"coordinates":[-1.1298867464,37.9834747314],"type":"Point"}
}