{
  "type": "Feature",
  "properties": {
    "iso:country":"ES",
    "sg:address":"Carrer de Parellades, 9",
    "sg:city":"Sitges",
    "sg:orig_category":"Pod\u00d3logos: Pedicuros",
    "sg:phone":"+34 938 94 51 30",
    "sg:postcode":"08870",
    "sg:province":"Barcelona",
    "wof:name":"Riera Palau Jose Maria",
    "wof:placetype":"venue"
},
  "geometry": {"coordinates":[1.8087699413,41.2363166809],"type":"Point"}
}