{
  "type": "Feature",
  "properties": {
    "addr:full":"Ptda. Tancaes, S/n Xeresa Valencia 46790",
    "addr:housenumber":"s",
    "addr:postcode":"46790",
    "addr:street":"Ptda. Tancaes;/ N",
    "iso:country":"ES",
    "sg:address":"Ptda. Tancaes, S/n",
    "sg:city":"Xeresa",
    "sg:orig_category":"Centros Empresariales",
    "sg:phone":"+34 962 89 53 26",
    "sg:postcode":"46790",
    "sg:province":"Valencia",
    "wof:name":"Asociacion De Exportadores De Naranja",
    "wof:placetype":"venue"
},
  "geometry": {"coordinates":[-0.2291564941,39.0135231018],"type":"Point"}
}