{
  "type": "Feature",
  "properties": {
    "addr:full":"Avda 2, 8 Vaciasilos Madrid 28991",
    "addr:housenumber":"8",
    "addr:postcode":"28991",
    "addr:street":"Avda 2",
    "iso:country":"ES",
    "sg:address":"Avda 2, 8",
    "sg:city":"Vaciasilos",
    "sg:orig_category":"Fabricaci\u00d3n De Moldes Y Modelos",
    "sg:phone":"+34 918 16 95 38",
    "sg:postcode":"28991",
    "sg:province":"Madrid",
    "wof:name":"Proutimon S.l.",
    "wof:placetype":"venue"
},
  "geometry": {"coordinates":[-3.8033208847,40.187713623],"type":"Point"}
}