{
  "type": "Feature",
  "properties": {
    "addr:full":"Calle de Zujar, 21 Bosque Madrid 28670",
    "addr:housenumber":"21",
    "addr:postcode":"28670",
    "addr:street":"Calle De Zujar",
    "iso:country":"ES",
    "sg:address":"Calle de Zujar, 21",
    "sg:city":"Bosque",
    "sg:orig_category":"Negocio De Materiales De Construcci\u00d3n",
    "sg:phone":"+34 916 04 47 87",
    "sg:postcode":"28670",
    "sg:province":"Madrid",
    "wof:name":"Lima Gres S.l.",
    "wof:placetype":"venue"
},
  "geometry": {"coordinates":[-3.9422864914,40.3860816956],"type":"Point"}
}