{
  "type": "Feature",
  "properties": {
    "addr:full":"Calle de Gran Via, 59 Madrid Madrid 28013",
    "addr:housenumber":"59",
    "addr:postcode":"madrid;28013",
    "addr:street":"Calle De Gran Via",
    "iso:country":"ES",
    "sg:address":"Calle de Gran Via, 59",
    "sg:city":"Madrid",
    "sg:orig_category":"Inmobiliaria (agencias)",
    "sg:phone":"+34 915 59 60 07",
    "sg:postcode":"28013",
    "sg:province":"Madrid",
    "wof:name":"Madrid Gestion S.a.",
    "wof:placetype":"venue"
},
  "geometry": {"coordinates":[-3.7090520859,40.4220581055],"type":"Point"}
}