{
  "type": "Feature",
  "properties": {
    "addr:full":"Calle de Nuestra Se\u00d1ora De Valverde, 185 Madrid Madrid 28034",
    "addr:housenumber":"185",
    "addr:postcode":"28034",
    "addr:street":"Calle De Nuestra Sen\u0303Ora De Valverde",
    "iso:country":"ES",
    "sg:address":"Calle de Nuestra Se\u00d1ora De Valverde, 185",
    "sg:city":"Madrid",
    "sg:orig_category":"Negocio De Materiales De Construcci\u00d3n",
    "sg:phone":"+34 917 34 56 09",
    "sg:postcode":"28034",
    "sg:province":"Madrid",
    "wof:name":"Suministros Pedro Blanco S.l.",
    "wof:placetype":"venue"
},
  "geometry": {"coordinates":[-3.6857850552,40.5039596558],"type":"Point"}
}