{
  "type": "Feature",
  "properties": {
    "addr:full":"Calle de Ronda (la), 1 Rubio Sevilla 41568",
    "addr:housenumber":"1",
    "addr:postcode":"41568",
    "addr:street":"Calle De Ronda La",
    "iso:country":"ES",
    "sg:address":"Calle de Ronda (la), 1",
    "sg:city":"Rubio",
    "sg:orig_category":"Energ\u00cda Solar Y Nuevas Energ\u00cdas (equipo, Estudios)",
    "sg:phone":"+34 955 82 82 50",
    "sg:postcode":"41568",
    "sg:province":"Sevilla",
    "wof:name":"Aguilar Orgaz Juan Luis",
    "wof:placetype":"venue"
},
  "geometry": {"coordinates":[-4.9882149696,37.3542633057],"type":"Point"}
}