{
  "type": "Feature",
  "properties": {
    "iso:country":"ES",
    "sg:address":"Av Joan Fuster, 28",
    "sg:city":"Rotes",
    "sg:orig_category":"Farmacias",
    "sg:phone":"+34 965 78 90 23",
    "sg:postcode":"03700",
    "sg:province":"Alicante",
    "wof:name":"Brines Blasco Jose",
    "wof:placetype":"venue"
},
  "geometry": {"coordinates":[0.1039630026,38.8354949951],"type":"Point"}
}