{
  "type": "Feature",
  "properties": {
    "iso:country":"ES",
    "sg:address":"Calle de Santa Teresa De Jesus, 24",
    "sg:city":"Zaragoza",
    "sg:orig_category":"Caf\u00c9s, Bares, Cervecer\u00cdas",
    "sg:phone":"+34 976 55 87 09",
    "sg:postcode":"50006",
    "sg:province":"Zaragoza",
    "wof:name":"Casa De Orva S.l.",
    "wof:placetype":"venue"
},
  "geometry": {"coordinates":[-0.8929690123,41.6410598755],"type":"Point"}
}