{
  "type": "Feature",
  "properties": {
    "iso:country":"ES",
    "sg:address":"Pg Sant Joan, 65",
    "sg:city":"Barcelona",
    "sg:orig_category":"Molduras, Junquillos, Listones Y Molduras Perforadas",
    "sg:phone":"+34 932 65 71 80",
    "sg:postcode":"08009",
    "sg:province":"Barcelona",
    "wof:name":"Basart Milan Juan",
    "wof:placetype":"venue"
},
  "geometry": {"coordinates":[2.1721858978,41.3972740173],"type":"Point"}
}