{
  "type": "Feature",
  "properties": {
    "addr:full":"Armu\u00f1o, 9 Armu\u00d1o La Coru\u00f1a 15166",
    "addr:housenumber":"9",
    "addr:postcode":"15166",
    "addr:street":"Armun\u0303O;La Corun\u0303A",
    "iso:country":"ES",
    "sg:address":"Armu\u00f1o, 9",
    "sg:city":"Armu\u00d1o",
    "sg:orig_category":"Promotores Constructores",
    "sg:phone":"+34 981 79 53 16",
    "sg:postcode":"15166",
    "sg:province":"La Coru\u00f1a",
    "wof:name":"Construcciones Francisco Souto Fernandez S.l.",
    "wof:placetype":"venue"
},
  "geometry": {"coordinates":[-8.2616682053,43.3274726868],"type":"Point"}
}