{
  "type": "Feature",
  "properties": {
    "iso:country":"ES",
    "sg:address":"Avda Andalucia, 19",
    "sg:city":"S. Bartolome Torre",
    "sg:orig_category":"Panader\u00cdas, Panader\u00cdas",
    "sg:phone":"+34 959 38 60 37",
    "sg:postcode":"21510",
    "sg:province":"Huelva",
    "wof:name":"Limon Casta\u00f1o Alfonso",
    "wof:placetype":"venue"
},
  "geometry": {"coordinates":[-7.107006073,37.4469223022],"type":"Point"}
}