{
  "type": "Feature",
  "properties": {
    "iso:country":"ES",
    "sg:address":"Lezesarri Auzoa, S/n",
    "sg:city":"Lezesarri",
    "sg:orig_category":"Asociaciones Y Clubs Deportivos",
    "sg:phone":"+34 943 71 61 72",
    "sg:postcode":"20560",
    "sg:province":"Guip\u00f9zcoa",
    "wof:name":"Club Deportivo Alo\u00f1a-mendi",
    "wof:placetype":"venue"
},
  "geometry": {"coordinates":[-2.4079990387,43.0313835144],"type":"Point"}
}