{
  "type": "Feature",
  "properties": {
    "addr:full":"Calle de Colon De Larreategui, 29 Bilbao Vizcaya 48009",
    "addr:housenumber":"29",
    "addr:postcode":"48009",
    "addr:street":"Calle De Colon De Larreategui",
    "iso:country":"ES",
    "sg:address":"Calle de Colon De Larreategui, 29",
    "sg:city":"Bilbao",
    "sg:orig_category":"Farmacias",
    "sg:phone":"+34 944 23 00 65",
    "sg:postcode":"48009",
    "sg:province":"Vizcaya",
    "wof:name":"Aguirrezabala Vial Jose Joaquin",
    "wof:placetype":"venue"
},
  "geometry": {"coordinates":[-2.9313640594,43.2632904053],"type":"Point"}
}