{
  "type": "Feature",
  "properties": {
    "addr:full":"Avda Talavera, S/n Puebla Montalban Toledo 45516",
    "addr:housenumber":"s / n",
    "addr:postcode":"45516",
    "addr:street":"Avda Talavera",
    "iso:country":"ES",
    "sg:address":"Avda Talavera, S/n",
    "sg:city":"Puebla Montalban",
    "sg:orig_category":"Transporte En General",
    "sg:phone":"+34 925 74 53 46",
    "sg:postcode":"45516",
    "sg:province":"Toledo",
    "wof:name":"Exclusivas Maldonado S.l.",
    "wof:placetype":"venue"
},
  "geometry": {"coordinates":[-4.3588690758,39.8725013733],"type":"Point"}
}