{
  "type": "Feature",
  "properties": {
    "addr:full":"Gta Descubrimiento, 5 Valladolid Valladolid 47005",
    "addr:housenumber":"5",
    "addr:postcode":"47005",
    "addr:street":"Gta Descubrimiento",
    "iso:country":"ES",
    "sg:address":"Gta Descubrimiento, 5",
    "sg:city":"Valladolid",
    "sg:orig_category":"Ingeniero",
    "sg:phone":"+34 983 20 29 86",
    "sg:postcode":"47005",
    "sg:province":"Valladolid",
    "wof:name":"Electrotecnia Industrial F.carranza S.l.",
    "wof:placetype":"venue"
},
  "geometry": {"coordinates":[-4.710299015,41.6554756165],"type":"Point"}
}