{
  "type": "Feature",
  "properties": {
    "addr:full":"Calle de Francisco Chico Mendes (de), 8 Alcobendas Madrid 28108",
    "addr:postcode":"28108",
    "addr:street":"Calle De Francisco Chico Mendes De 8",
    "iso:country":"ES",
    "sg:address":"Calle de Francisco Chico Mendes (de), 8",
    "sg:city":"Alcobendas",
    "sg:orig_category":"Asociaciones Y Clubs Deportivos",
    "sg:phone":"+34 916 61 48 60",
    "sg:postcode":"28108",
    "sg:province":"Madrid",
    "wof:name":"Club Baloncesto Alcobendas",
    "wof:placetype":"venue"
},
  "geometry": {"coordinates":[-3.6534290314,40.5227012634],"type":"Point"}
}