{
  "type": "Feature",
  "properties": {
    "iso:country":"ES",
    "sg:address":"Calle de Hernandez Malillos, 39",
    "sg:city":"Torrent",
    "sg:orig_category":"Peluquer\u00cdas, Peluquer\u00cda Mixta",
    "sg:phone":"+34 961 56 29 75",
    "sg:postcode":"46900",
    "sg:province":"Valencia",
    "wof:name":"Segura Rodriguez Teodoro",
    "wof:placetype":"venue"
},
  "geometry": {"coordinates":[-0.4703249931,39.4350395203],"type":"Point"}
}