{
  "type": "Feature",
  "properties": {
    "addr:full":"Calle de Esquilon Bajo, 31 San Antonio-el Esquilon Santa Cruz De Tenerife 38400",
    "addr:housenumber":"31",
    "addr:postcode":"38400",
    "addr:street":"Calle De Esquilon Bajo",
    "iso:country":"ES",
    "sg:address":"Calle de Esquilon Bajo, 31",
    "sg:city":"San Antonio-el Esquilon",
    "sg:orig_category":"Veh\u00cdculos De Ocasi\u00d3n",
    "sg:phone":"+34 922 37 04 87",
    "sg:postcode":"38400",
    "sg:province":"Santa Cruz De Tenerife",
    "wof:name":"Gonzalez Hernandez Antonio",
    "wof:placetype":"venue"
},
  "geometry": {"coordinates":[-16.2548561096,28.4698104858],"type":"Point"}
}