{
  "type": "Feature",
  "properties": {
    "addr:full":"Calle de Pozo Nuevo, 1 Nombela Toledo 45917",
    "addr:housenumber":"1",
    "addr:postcode":"45917",
    "addr:street":"Calle De Pozo Nuevo",
    "iso:country":"ES",
    "sg:address":"Calle de Pozo Nuevo, 1",
    "sg:city":"Nombela",
    "sg:orig_category":"Estudios, Instalaci\u00d3n De Climatizaci\u00d3n",
    "sg:phone":"+34 925 79 23 04",
    "sg:postcode":"45917",
    "sg:province":"Toledo",
    "wof:name":"Jimenez Del Peso Jesus",
    "wof:placetype":"venue"
},
  "geometry": {"coordinates":[-4.5023679733,40.1564369202],"type":"Point"}
}