{
  "type": "Feature",
  "properties": {
    "addr:full":"Calle de Quevedo, 36 Albacete Albacete 02005",
    "addr:housenumber":"36",
    "addr:postcode":"02005",
    "addr:street":"Calle De Quevedo",
    "iso:country":"ES",
    "sg:address":"Calle de Quevedo, 36",
    "sg:city":"Albacete",
    "sg:classifiers":[
        {
            "category":"Personal",
            "subcategory":"Barber",
            "type":"Services"
        }
    ],
    "sg:phone":"+34 967 22 03 64",
    "sg:postcode":"02005",
    "sg:province":"Albacete",
    "sg:tags":[
        "caballeros",
        "de",
        "peluqueros"
    ],
    "wof:name":"Ponce Jimenez Juan Jose",
    "wof:placetype":"venue"
},
  "geometry": {"coordinates":[-1.8651599884,39.0005226135],"type":"Point"}
}