{
  "type": "Feature",
  "properties": {
    "iso:country":"ES",
    "sg:address":"Av Pi I Margall, 88",
    "sg:city":"Caldes Montbui",
    "sg:orig_category":"Ropa Para Ni\u00d1os (al Por Menor)",
    "sg:phone":"+34 938 65 09 15",
    "sg:postcode":"08140",
    "sg:province":"Barcelona",
    "wof:name":"Abel Diaz Sonia",
    "wof:placetype":"venue"
},
  "geometry": {"coordinates":[2.168013,41.627373],"type":"Point"}
}