{
  "type": "Feature",
  "properties": {
    "iso:country":"ES",
    "sg:address":"Calle de Mateo Errota, 3",
    "sg:city":"Donostia-san Sebastian",
    "sg:orig_category":"Artes Gr\u00c1ficas, Artes Pl\u00c1sticas: Material Y Suministros (al Por Menor)",
    "sg:phone":"+34 943 47 14 17",
    "sg:postcode":"20014",
    "sg:province":"Guip\u00f9zcoa",
    "wof:name":"Bidean Garraioak ,s.l.",
    "wof:placetype":"venue"
},
  "geometry": {"coordinates":[-1.9457269907,43.3015060425],"type":"Point"}
}