{
  "type": "Feature",
  "properties": {
    "iso:country":"ES",
    "sg:address":"Pol Ind Riera Torderola, 10",
    "sg:city":"Ma\u00e7anet Selva",
    "sg:orig_category":"Automatizaci\u00d3n De Procesos Industriales Y De Edificaci\u00d3n (estudios, Instalaci\u00d3n)",
    "sg:phone":"+34 972 16 53 88",
    "sg:postcode":"17412",
    "sg:province":"Girona",
    "wof:name":"T G Z Automatizacion De Prensas Scp",
    "wof:placetype":"venue"
},
  "geometry": {"coordinates":[2.7342700958,41.7778396606],"type":"Point"}
}