{
  "type": "Feature",
  "properties": {
    "iso:country":"ES",
    "sg:address":"Avda Sagunto (de), 54",
    "sg:city":"Teruel",
    "sg:orig_category":"Inmobiliaria (agencias)",
    "sg:phone":"+34 978 60 11 17",
    "sg:postcode":"44002",
    "sg:province":"Teruel",
    "wof:name":"Lorente Moya Jose",
    "wof:placetype":"venue"
},
  "geometry": {"coordinates":[-1.1012840271,40.3331756592],"type":"Point"}
}