{
  "type": "Feature",
  "properties": {
    "addr:full":"Calle de Pablo Casals, 10 Parla Madrid 28980",
    "addr:housenumber":"10",
    "addr:postcode":"28980",
    "addr:street":"Calle De Pablo Casals",
    "iso:country":"ES",
    "sg:address":"Calle de Pablo Casals, 10",
    "sg:city":"Parla",
    "sg:orig_category":"Empresas De Limpieza",
    "sg:phone":"+34 916 98 58 64",
    "sg:postcode":"28980",
    "sg:province":"Madrid",
    "wof:name":"Seresma S.a.",
    "wof:placetype":"venue"
},
  "geometry": {"coordinates":[-3.7732129097,40.2305603027],"type":"Point"}
}