{
  "type": "Feature",
  "properties": {
    "iso:country":"ES",
    "sg:address":"Carrer de J. Molins Parera, 52",
    "sg:city":"Palleja",
    "sg:orig_category":"Molduras, Junquillos, Listones Y Molduras Perforadas",
    "sg:phone":"+34 936 63 10 30",
    "sg:postcode":"08780",
    "sg:province":"Barcelona",
    "wof:name":"Rodriguez Aguado Antonio",
    "wof:placetype":"venue"
},
  "geometry": {"coordinates":[1.9974240065,41.4191551208],"type":"Point"}
}