{
  "type": "Feature",
  "properties": {
    "iso:country":"ES",
    "sg:address":"Calle de Velodromo (del), 7",
    "sg:city":"Segovia",
    "sg:orig_category":"Electricidad: Instaladores",
    "sg:phone":"+34 921 44 18 09",
    "sg:postcode":"40002",
    "sg:province":"Segovia",
    "wof:name":"Electricidad Y Riegos Tarfe S.l.",
    "wof:placetype":"venue"
},
  "geometry": {"coordinates":[-4.1233129501,40.945892334],"type":"Point"}
}