{
  "type": "Feature",
  "properties": {
    "addr:full":"Via Argentina, 20 Pollen\u00e7a Islas Baleares 07460",
    "addr:housenumber":"20",
    "addr:postcode":"07460",
    "addr:street":"Via Argentina;Islas",
    "iso:country":"ES",
    "sg:address":"Via Argentina, 20",
    "sg:city":"Pollen\u00e7a",
    "sg:orig_category":"Artes Gr\u00c1ficas, Artes Pl\u00c1sticas (curso)",
    "sg:phone":"+34 971 53 00 04",
    "sg:postcode":"07460",
    "sg:province":"Islas Baleares",
    "wof:name":"Serigrafic 4 Colors S.l.",
    "wof:placetype":"venue"
},
  "geometry": {"coordinates":[3.020015955,39.8755989075],"type":"Point"}
}