{
  "type": "Feature",
  "properties": {
    "iso:country":"ES",
    "sg:address":"Calle de Delfin Bericat, 22",
    "sg:city":"Ejea De Los Caballeros",
    "sg:orig_category":"Promotores Constructores",
    "sg:phone":"+34 976 66 40 09",
    "sg:postcode":"50600",
    "sg:province":"Zaragoza",
    "wof:name":"Inmobiliaria A\u00f1esa S.l.",
    "wof:placetype":"venue"
},
  "geometry": {"coordinates":[-1.1397761106,42.1249160767],"type":"Point"}
}