{
  "type": "Feature",
  "properties": {
    "iso:country":"ES",
    "sg:address":"Urb Torre Soli Nou, S/n",
    "sg:city":"Torre Soli Nou",
    "sg:orig_category":"Cr\u00cda De Animales",
    "sg:phone":"+34 971 18 84 09",
    "sg:postcode":"07730",
    "sg:province":"Islas Baleares",
    "wof:name":"Hermanos Squella C.b.",
    "wof:placetype":"venue"
},
  "geometry": {"coordinates":[4.1400952339,39.930721283],"type":"Point"}
}