{
  "type": "Feature",
  "properties": {
    "addr:full":"Ferrers, S/n Inca Islas Baleares 07300",
    "addr:housenumber":"s / n",
    "addr:postcode":"07300",
    "addr:street":"Ferrers",
    "iso:country":"ES",
    "sg:address":"Ferrers, S/n",
    "sg:city":"Inca",
    "sg:orig_category":"Artes Gr\u00c1ficas, Artes Pl\u00c1sticas (curso)",
    "sg:phone":"+34 971 50 13 38",
    "sg:postcode":"07300",
    "sg:province":"Islas Baleares",
    "wof:name":"Artes Graficas Mallorca S.l.",
    "wof:placetype":"venue"
},
  "geometry": {"coordinates":[2.911601305,39.7139053345],"type":"Point"}
}