{
  "type": "Feature",
  "properties": {
    "addr:full":"Carr D'hernan Cortes, 1 Benicarlo Castell\u00f3n 12580",
    "addr:housenumber":"1",
    "addr:postcode":"12580",
    "addr:street":"Carr D'Hernan Cortes",
    "iso:country":"ES",
    "sg:address":"Carr D'hernan Cortes, 1",
    "sg:city":"Benicarlo",
    "sg:orig_category":"Frutas Y Legumbres Frescas (al Por Mayor)",
    "sg:phone":"+34 964 47 37 82",
    "sg:postcode":"12580",
    "sg:province":"Castell\u00f3n",
    "wof:name":"Frutas Pi\u00f1ana S.l.",
    "wof:placetype":"venue"
},
  "geometry": {"coordinates":[0.4262729883,40.4177856445],"type":"Point"}
}