{
  "type": "Feature",
  "properties": {
    "addr:full":"Carrer de L'hort De La Vila, 5 Barcelona Barcelona 08017",
    "addr:housenumber":"5",
    "addr:postcode":"08017",
    "addr:street":"Carrer De L'Hort De La Vila",
    "iso:country":"ES",
    "sg:address":"Carrer de L'hort De La Vila, 5",
    "sg:city":"Barcelona",
    "sg:orig_category":"Asesor\u00cda Sobre Comunicaci\u00d3n De Empresas",
    "sg:phone":"+34 932 05 68 19",
    "sg:postcode":"08017",
    "sg:province":"Barcelona",
    "wof:name":"Costaisa S.a.",
    "wof:placetype":"venue"
},
  "geometry": {"coordinates":[2.1225719452,41.3988304138],"type":"Point"}
}