{
  "type": "Feature",
  "properties": {
    "addr:full":"Calle de Bronce, 5 Illescas Toledo 45200",
    "addr:housenumber":"5",
    "addr:postcode":"45200",
    "addr:street":"Calle De Bronce",
    "iso:country":"ES",
    "sg:address":"Calle de Bronce, 5",
    "sg:city":"Illescas",
    "sg:orig_category":"Tubos Y Tuber\u00cdas De Goma Y Pl\u00c1stico (fabricaci\u00d3n, Al Por Mayor)",
    "sg:phone":"+34 925 51 29 19",
    "sg:postcode":"45200",
    "sg:province":"Toledo",
    "wof:name":"Comercial Tubipres C. B.",
    "wof:placetype":"venue"
},
  "geometry": {"coordinates":[-3.8557083607,40.114200592],"type":"Point"}
}