{
  "type": "Feature",
  "properties": {
    "addr:full":"Avda Francisco Aguirre, 198 Talavera Reina Toledo 45600",
    "addr:housenumber":"198",
    "addr:postcode":"45600",
    "addr:street":"Avda Francisco Aguirre",
    "iso:country":"ES",
    "sg:address":"Avda Francisco Aguirre, 198",
    "sg:city":"Talavera Reina",
    "sg:orig_category":"Farmacias",
    "sg:phone":"+34 925 81 68 52",
    "sg:postcode":"45600",
    "sg:province":"Toledo",
    "wof:name":"Gamez Mata Maria De Los Remedios",
    "wof:placetype":"venue"
},
  "geometry": {"coordinates":[-4.8279929161,39.9689674377],"type":"Point"}
}