{
  "type": "Feature",
  "properties": {
    "iso:country":"ES",
    "sg:address":"Las Eras, S/n",
    "sg:city":"Quel",
    "sg:orig_category":"Empresas De Carpinter\u00cda Met\u00c1lica",
    "sg:phone":"+34 941 39 21 51",
    "sg:postcode":"26570",
    "sg:province":"La Rioja",
    "wof:name":"Construcciones Metalicas Iba\u00f1ez Escalona S.l.",
    "wof:placetype":"venue"
},
  "geometry": {"coordinates":[-2.0563650131,42.233341217],"type":"Point"}
}