{
  "type": "Feature",
  "properties": {
    "addr:full":"Avda Generalisimo, 17 Colunga Asturias 33320",
    "addr:housenumber":"17",
    "addr:postcode":"33320",
    "addr:street":"Avda Generalisimo",
    "iso:country":"ES",
    "sg:address":"Avda Generalisimo, 17",
    "sg:city":"Colunga",
    "sg:orig_category":"Inform\u00c1tica (estudios, Servicios, Asesor\u00cda, Formaci\u00d3n)",
    "sg:phone":"+34 985 85 21 65",
    "sg:postcode":"33320",
    "sg:province":"Asturias",
    "wof:name":"Mapfre Servicios De Informatica",
    "wof:placetype":"venue"
},
  "geometry": {"coordinates":[-5.269285202,43.4854431152],"type":"Point"}
}