{
  "type": "Feature",
  "properties": {
    "iso:country":"ES",
    "sg:address":"Calle de Pacifico, 150",
    "sg:city":"Malaga",
    "sg:orig_category":"Gases Industriales",
    "sg:phone":"+34 952 17 33 17",
    "sg:postcode":"29002",
    "sg:province":"M\u00e1laga",
    "wof:name":"Francisco Gomez Salvador S.l.",
    "wof:placetype":"venue"
},
  "geometry": {"coordinates":[-4.4367389679,36.6995811462],"type":"Point"}
}