{
  "type": "Feature",
  "properties": {
    "addr:full":"Calle de Cipreses (los), 49 Azuqueca Henares Guadalajara 19200",
    "addr:postcode":"19200",
    "addr:street":"Calle De;Los",
    "iso:country":"ES",
    "sg:address":"Calle de Cipreses (los), 49",
    "sg:city":"Azuqueca Henares",
    "sg:orig_category":"Doctores En Medicina",
    "sg:phone":"+34 949 26 41 15",
    "sg:postcode":"19200",
    "sg:province":"Guadalajara",
    "wof:name":"Hernandez Garrote Maria Del Carmen",
    "wof:placetype":"venue"
},
  "geometry": {"coordinates":[-3.259323597,40.5678215027],"type":"Point"}
}