{
  "type": "Feature",
  "properties": {
    "iso:country":"ES",
    "sg:address":"Calle de Azpiri Kalea, 10",
    "sg:city":"Lekeitio",
    "sg:orig_category":"Restaurantes",
    "sg:phone":"+34 946 24 36 65",
    "sg:postcode":"48280",
    "sg:province":"Vizcaya",
    "wof:name":"Juan Manuel Sanchez Castillo",
    "wof:placetype":"venue"
},
  "geometry": {"coordinates":[-2.5040719509,43.364490509],"type":"Point"}
}