{
  "type": "Feature",
  "properties": {
    "addr:full":"Q. Llano, 46 Isla Cristina Huelva 21410",
    "addr:housenumber":"46",
    "addr:postcode":"21410",
    "addr:street":"Q. Llano",
    "iso:country":"ES",
    "sg:address":"Q. Llano, 46",
    "sg:city":"Isla Cristina",
    "sg:orig_category":"Sales (al Por Mayor)",
    "sg:phone":"+34 959 34 36 61",
    "sg:postcode":"21410",
    "sg:province":"Huelva",
    "wof:name":"Pescados Y Salazones La Higuerita S.l.",
    "wof:placetype":"venue"
},
  "geometry": {"coordinates":[-7.3203940392,37.2019615173],"type":"Point"}
}