{
  "type": "Feature",
  "properties": {
    "addr:full":"Rua Angel De Lema Y Marina, 112 Paraixal Pontevedra 36207",
    "addr:housenumber":"112",
    "addr:postcode":"36207",
    "addr:street":"Rua Angel De Lema Y Marina",
    "iso:country":"ES",
    "sg:address":"Rua Angel De Lema Y Marina, 112",
    "sg:city":"Paraixal",
    "sg:orig_category":"Patatas (al Por Mayor)",
    "sg:phone":"+34 986 45 24 55",
    "sg:postcode":"36207",
    "sg:province":"Pontevedra",
    "wof:name":"Rodriguez Gomez Manuel",
    "wof:placetype":"venue"
},
  "geometry": {"coordinates":[-8.6428003311,42.4304618835],"type":"Point"}
}