{
  "type": "Feature",
  "properties": {
    "addr:full":"Carrer de Industria, 29 Palma Islas Baleares 07013",
    "addr:housenumber":"29",
    "addr:postcode":"07013",
    "addr:street":"Carrer De Industria",
    "iso:country":"ES",
    "sg:address":"Carrer de Industria, 29",
    "sg:city":"Palma",
    "sg:orig_category":"Confecci\u00d3n De Trajes Para Se\u00d1oras",
    "sg:phone":"+34 971 45 46 15",
    "sg:postcode":"07013",
    "sg:province":"Islas Baleares",
    "wof:name":"Carmen Lopez Ferreiro S.l.",
    "wof:placetype":"venue"
},
  "geometry": {"coordinates":[2.6372098923,39.5755233765],"type":"Point"}
}