{
  "type": "Feature",
  "properties": {
    "addr:full":"Plaz Espa\u00d1a, 29 Burguillos Cerro Badajoz 06370",
    "addr:housenumber":"29",
    "addr:postcode":"06370",
    "addr:street":"Plaz Espan\u0303A",
    "iso:country":"ES",
    "sg:address":"Plaz Espa\u00d1a, 29",
    "sg:city":"Burguillos Cerro",
    "sg:orig_category":"Autob\u00das (explotaci\u00d3n Y Servicios De)",
    "sg:phone":"+34 924 54 14 97",
    "sg:postcode":"06370",
    "sg:province":"Badajoz",
    "wof:name":"Matamoros Megias Jose",
    "wof:placetype":"venue"
},
  "geometry": {"coordinates":[-6.9702835083,38.8785972595],"type":"Point"}
}