{
  "type": "Feature",
  "properties": {
    "addr:full":"Calle de Sierra De Guadarrama (de La), 26 Poligono De San Fernando De Henares Madrid 28830",
    "addr:housenumber":"26 poligono",
    "addr:postcode":"28830",
    "addr:street":"Calle De Sierra De Guadarrama De La",
    "iso:country":"ES",
    "sg:address":"Calle de Sierra De Guadarrama (de La), 26",
    "sg:city":"Poligono De San Fernando De Henares",
    "sg:orig_category":"Mec\u00c1nico Del Autom\u00d3vil",
    "sg:phone":"+34 916 75 31 12",
    "sg:postcode":"28830",
    "sg:province":"Madrid",
    "wof:name":"Fravi S.l.",
    "wof:placetype":"venue"
},
  "geometry": {"coordinates":[-3.5041499138,40.4501800537],"type":"Point"}
}