{
  "type": "Feature",
  "properties": {
    "addr:full":"Calle de Alhamar, 7 Granada Granada 18005",
    "addr:housenumber":"7",
    "addr:postcode":"18005",
    "addr:street":"Calle De Alhamar",
    "iso:country":"ES",
    "sg:address":"Calle de Alhamar, 7",
    "sg:city":"Granada",
    "sg:orig_category":"Pe\u00d1as Y Asociaciones Varias",
    "sg:phone":"+34 958 26 38 53",
    "sg:postcode":"18005",
    "sg:province":"Granada",
    "wof:name":"Colega Granada",
    "wof:placetype":"venue"
},
  "geometry": {"coordinates":[-3.6002266407,37.1689834595],"type":"Point"}
}