{
  "type": "Feature",
  "properties": {
    "addr:full":"Cetreria(peral), 25 Cartagena Murcia 30300",
    "addr:housenumber":"25",
    "addr:postcode":"30300",
    "addr:street":"Peral",
    "iso:country":"ES",
    "sg:address":"Cetreria(peral), 25",
    "sg:city":"Cartagena",
    "sg:orig_category":"Reposter\u00cdas",
    "sg:phone":"+34 968 53 58 78",
    "sg:postcode":"30300",
    "sg:province":"Murcia",
    "wof:name":"Rosique Fuentes Juana",
    "wof:placetype":"venue"
},
  "geometry": {"coordinates":[-0.9899340272,37.6296272278],"type":"Point"}
}