{
  "type": "Feature",
  "properties": {
    "addr:full":"Carrer de Vene\u00c7uela, S/n Barcelona Barcelona 08019",
    "addr:housenumber":"s",
    "addr:postcode":"08019",
    "addr:street":"Carrer De Venec\u0327Uela;/ N",
    "iso:country":"ES",
    "sg:address":"Carrer de Vene\u00c7uela, S/n",
    "sg:city":"Barcelona",
    "sg:orig_category":"\u00d3ptica: Instrumentos (fabricaci\u00d3n)",
    "sg:phone":"+34 932 66 17 53",
    "sg:postcode":"08019",
    "sg:province":"Barcelona",
    "wof:name":"General Optica S.a.",
    "wof:placetype":"venue"
},
  "geometry": {"coordinates":[2.2135350704,41.4147262573],"type":"Point"}
}