{
  "type": "Feature",
  "properties": {
    "addr:full":"Rubio El, S/n Arahal Sevilla 41600",
    "addr:housenumber":"/ n",
    "addr:postcode":"41600",
    "addr:street":"Rubio El S",
    "iso:country":"ES",
    "sg:address":"Rubio El, S/n",
    "sg:city":"Arahal",
    "sg:orig_category":"Promotores Constructores",
    "sg:phone":"+34 954 84 11 11",
    "sg:postcode":"41600",
    "sg:province":"Sevilla",
    "wof:name":"Aralpadem S.l.",
    "wof:placetype":"venue"
},
  "geometry": {"coordinates":[-5.5457553864,37.2691459656],"type":"Point"}
}