{
  "type": "Feature",
  "properties": {
    "addr:full":"Calle de San Sebastian (de), 17 Pinto Madrid 28320",
    "addr:postcode":"28320",
    "addr:street":"Calle De",
    "iso:country":"ES",
    "sg:address":"Calle de San Sebastian (de), 17",
    "sg:city":"Pinto",
    "sg:orig_category":"Plomeros",
    "sg:phone":"+34 916 92 01 56",
    "sg:postcode":"28320",
    "sg:province":"Madrid",
    "wof:name":"Balbuena Lopez Manuel",
    "wof:placetype":"venue"
},
  "geometry": {"coordinates":[-3.6989600658,40.2463264465],"type":"Point"}
}