{
  "type": "Feature",
  "properties": {
    "iso:country":"ES",
    "sg:address":"Calle de Covarrubias, 30",
    "sg:city":"Madrid",
    "sg:orig_category":"Centros Empresariales",
    "sg:phone":"+34 914 44 05 28",
    "sg:postcode":"28010",
    "sg:province":"Madrid",
    "wof:name":"Monterojas S.l",
    "wof:placetype":"venue"
},
  "geometry": {"coordinates":[-3.6979696751,40.4308509827],"type":"Point"}
}