{
  "type": "Feature",
  "properties": {
    "iso:country":"ES",
    "sg:address":"Calle de Explanada Del Muelle, S/n",
    "sg:city":"Aguilas",
    "sg:orig_category":"Comercio De Minerales, F\u00d3siles Y Conchas",
    "sg:phone":"+34 968 41 29 23",
    "sg:postcode":"30880",
    "sg:province":"Murcia",
    "wof:name":"Perez Navarro Francisco",
    "wof:placetype":"venue"
},
  "geometry": {"coordinates":[-1.5789994001,37.478969574],"type":"Point"}
}