{
  "type": "Feature",
  "properties": {
    "addr:full":"Calle de Mercurio, 9 Poligono Ardoz Toledo 45200",
    "addr:housenumber":"9",
    "addr:postcode":"45200",
    "addr:street":"Calle De Mercurio;Ardoz",
    "iso:country":"ES",
    "sg:address":"Calle de Mercurio, 9",
    "sg:city":"Poligono Ardoz",
    "sg:orig_category":"Inform\u00c1tica (estudios, Servicios, Asesor\u00cda, Formaci\u00d3n)",
    "sg:phone":"+34 925 51 20 49",
    "sg:postcode":"45200",
    "sg:province":"Toledo",
    "sg:website":"www.ozotoner.com",
    "wof:name":"Distribuidora De Componentes Ozotone S.l.",
    "wof:placetype":"venue"
},
  "geometry": {"coordinates":[-3.8458640575,40.1230163574],"type":"Point"}
}