{
  "type": "Feature",
  "properties": {
    "addr:full":"Pl Constitucio (la), 5 Crevillent Alicante 03330",
    "addr:postcode":"03330",
    "addr:street":"Pl Constitucio La 5",
    "iso:country":"ES",
    "sg:address":"Pl Constitucio (la), 5",
    "sg:city":"Crevillent",
    "sg:orig_category":"Promotores Constructores",
    "sg:phone":"+34 965 40 16 62",
    "sg:postcode":"03330",
    "sg:province":"Alicante",
    "wof:name":"Consen S.l.",
    "wof:placetype":"venue"
},
  "geometry": {"coordinates":[-0.8087610006,38.2489967346],"type":"Point"}
}