{
  "type": "Feature",
  "properties": {
    "addr:full":"Calle de Fresa, 8 Jerez De La Frontera C\u00e1diz 11406",
    "addr:housenumber":"8",
    "addr:postcode":"11406",
    "addr:street":"Calle De Fresa",
    "iso:country":"ES",
    "sg:address":"Calle de Fresa, 8",
    "sg:city":"Jerez De La Frontera",
    "sg:orig_category":"Carnicer\u00cdas, Carnicer\u00cdas",
    "sg:phone":"+34 956 33 10 61",
    "sg:postcode":"11406",
    "sg:province":"C\u00e1diz",
    "wof:name":"Hernandez Cardeno Jose",
    "wof:placetype":"venue"
},
  "geometry": {"coordinates":[-6.1130290031,36.6807441711],"type":"Point"}
}