{
  "type": "Feature",
  "properties": {
    "addr:full":"Calle de Carmen (la), 30 Arrecife Las Palmas 35500",
    "addr:housenumber":"30",
    "addr:postcode":"35500",
    "addr:street":"Calle De Carmen La",
    "iso:country":"ES",
    "sg:address":"Calle de Carmen (la), 30",
    "sg:city":"Arrecife",
    "sg:orig_category":"Empresas De Carpinter\u00cda",
    "sg:phone":"+34 928 81 39 26",
    "sg:postcode":"35500",
    "sg:province":"Las Palmas",
    "wof:name":"Aluminios Famara S.c.p.",
    "wof:placetype":"venue"
},
  "geometry": {"coordinates":[-13.5591650009,28.9678630829],"type":"Point"}
}