{
  "type": "Feature",
  "properties": {
    "iso:country":"ES",
    "sg:address":"Calle de Hermanas Bronte, 68",
    "sg:city":"Malaga",
    "sg:orig_category":"Chapister\u00cda",
    "sg:phone":"+34 952 17 01 04",
    "sg:postcode":"29004",
    "sg:province":"M\u00e1laga",
    "wof:name":"Cabanillas Sojo Benito",
    "wof:placetype":"venue"
},
  "geometry": {"coordinates":[-4.4689531326,36.6937828064],"type":"Point"}
}