{
  "type": "Feature",
  "properties": {
    "addr:full":"Calle de Virgen De La Saletta, 92 Sevilla Sevilla 41006",
    "addr:housenumber":"92",
    "addr:postcode":"41006",
    "addr:street":"Calle De Virgen De La Saletta",
    "iso:country":"ES",
    "sg:address":"Calle de Virgen De La Saletta, 92",
    "sg:city":"Sevilla",
    "sg:classifiers":[
        {
            "category":"Autos & Motor Vehicles",
            "subcategory":"Automobile Sales",
            "type":"Retail Goods"
        }
    ],
    "sg:phone":"+34 954 64 40 70",
    "sg:postcode":"41006",
    "sg:province":"Sevilla",
    "sg:website":"www.aejuanxxiii.com",
    "wof:name":"Rodeauto S.l.",
    "wof:placetype":"venue"
},
  "geometry": {"coordinates":[-5.951695919,37.3717765808],"type":"Point"}
}