{
  "type": "Feature",
  "properties": {
    "iso:country":"ES",
    "sg:address":"Calle de Paseo De La Fuente, 2",
    "sg:city":"Elcano",
    "sg:orig_category":"Cursos Particulares, Asistencia Escolar",
    "sg:phone":"+34 948 33 19 24",
    "sg:postcode":"31486",
    "sg:province":"Navarra",
    "wof:name":"Garrido Arilla Maria Pilar",
    "wof:placetype":"venue"
},
  "geometry": {"coordinates":[-1.5519039631,42.8252906799],"type":"Point"}
}