{
  "type": "Feature",
  "properties": {
    "iso:country":"ES",
    "sg:address":"Calle de Eras, 54",
    "sg:city":"Villanueva Fuente",
    "sg:orig_category":"Confecci\u00d3n (fabricaci\u00d3n, Al Por Mayor)",
    "sg:phone":"+34 967 39 70 03",
    "sg:postcode":"13330",
    "sg:province":"Ciudad Real",
    "wof:name":"Requena Villar Juana",
    "wof:placetype":"venue"
},
  "geometry": {"coordinates":[-2.6981589794,38.6921195984],"type":"Point"}
}