{
  "type": "Feature",
  "properties": {
    "iso:country":"ES",
    "sg:address":"Carr Peru, 7",
    "sg:city":"Gandia",
    "sg:orig_category":"Peluquer\u00cdas, Peluquer\u00cda Mixta",
    "sg:phone":"+34 962 87 88 09",
    "sg:postcode":"46700",
    "sg:province":"Valencia",
    "wof:name":"Montero Montilla Loli",
    "wof:placetype":"venue"
},
  "geometry": {"coordinates":[-0.1913339943,38.960735321],"type":"Point"}
}