{
  "type": "Feature",
  "properties": {
    "addr:full":"Carr Anselm Clave, 4 Juneda Lleida 25430",
    "addr:housenumber":"4",
    "addr:postcode":"25430",
    "addr:street":"Carr Anselm Clave",
    "iso:country":"ES",
    "sg:address":"Carr Anselm Clave, 4",
    "sg:city":"Juneda",
    "sg:orig_category":"Bancos",
    "sg:phone":"+34 973 15 00 61",
    "sg:postcode":"25430",
    "sg:province":"Lleida",
    "sg:website":"www.banesto.es",
    "wof:name":"Banco Espa\u00f1ol De Credito S.a.",
    "wof:placetype":"venue"
},
  "geometry": {"coordinates":[0.8252699971,41.5478973389],"type":"Point"}
}