{
  "type": "Feature",
  "properties": {
    "iso:country":"ES",
    "sg:address":"Carretera De Villalobos, S/n",
    "sg:city":"Alcala Real",
    "sg:orig_category":"Internados & Ense\u00d1anza Privada",
    "sg:phone":"+34 953 58 06 52",
    "sg:postcode":"23680",
    "sg:province":"Ja\u00e9n",
    "wof:name":"Junta De Andalucia",
    "wof:placetype":"venue"
},
  "geometry": {"coordinates":[-3.9138994217,37.4073753357],"type":"Point"}
}