{
  "type": "Feature",
  "properties": {
    "addr:full":"Carretera De Villalobos, S/n Alcala Real Ja\u00e9n 23680",
    "addr:housenumber":"s",
    "addr:postcode":"23680",
    "addr:street":"Carretera De Villalobos;/ N;Jae\u0301N",
    "iso:country":"ES",
    "sg:address":"Carretera De Villalobos, S/n",
    "sg:city":"Alcala Real",
    "sg:orig_category":"Internados & Ense\u00d1anza Privada",
    "sg:phone":"+34 953 58 06 52",
    "sg:postcode":"23680",
    "sg:province":"Ja\u00e9n",
    "wof:name":"Junta De Andalucia",
    "wof:placetype":"venue"
},
  "geometry": {"coordinates":[-3.9138994217,37.4073753357],"type":"Point"}
}