{
  "type": "Feature",
  "properties": {
    "iso:country":"ES",
    "sg:address":"Ibarredi Kalea, 15",
    "sg:city":"Jundiz",
    "sg:orig_category":"Vinos Y Licores (venta Al Por Menor)",
    "sg:phone":"+34 945 29 03 85",
    "sg:postcode":"01015",
    "sg:province":"\u00c1lava",
    "wof:name":"Garcia Chavarri Amador",
    "wof:placetype":"venue"
},
  "geometry": {"coordinates":[-2.730325222,42.8433074951],"type":"Point"}
}