{
  "type": "Feature",
  "properties": {
    "addr:full":"Rbla Martir Santa Eulalia, 29 Merida Badajoz 06800",
    "addr:housenumber":"29",
    "addr:postcode":"06800",
    "addr:street":"Rbla Martir Santa Eulalia",
    "iso:country":"ES",
    "sg:address":"Rbla Martir Santa Eulalia, 29",
    "sg:city":"Merida",
    "sg:orig_category":"Peluquer\u00cdas, Peluquer\u00cda Mixta",
    "sg:phone":"+34 924 31 41 65",
    "sg:postcode":"06800",
    "sg:province":"Badajoz",
    "wof:name":"Villaverde Avellano Telesforo",
    "wof:placetype":"venue"
},
  "geometry": {"coordinates":[-6.3440308571,38.9173965454],"type":"Point"}
}