{
  "type": "Feature",
  "properties": {
    "iso:country":"ES",
    "sg:address":"Rua San Pedro De Mezonzo (de), 19",
    "sg:city":"Santiago De Compostela",
    "sg:orig_category":"M\u00c9dicos: Otorrinolaringolog\u00cda",
    "sg:phone":"+34 981 59 07 58",
    "sg:postcode":"15701",
    "sg:province":"La Coru\u00f1a",
    "wof:name":"Cajade Bao Daniel",
    "wof:placetype":"venue"
},
  "geometry": {"coordinates":[-8.5482139587,42.872959137],"type":"Point"}
}