{
  "type": "Feature",
  "properties": {
    "iso:country":"ES",
    "sg:address":"Av. Rebullon, S/n",
    "sg:city":"Mos",
    "sg:orig_category":"Aluminio Y Aleaciones (producci\u00d3n, Transformaci\u00d3n, Negocio)",
    "sg:phone":"+34 986 28 80 77",
    "sg:postcode":"36416",
    "sg:province":"Pontevedra",
    "wof:name":"Extrusistemas S.l.",
    "wof:placetype":"venue"
},
  "geometry": {"coordinates":[-8.6641283035,42.2043952942],"type":"Point"}
}