{
  "type": "Feature",
  "properties": {
    "addr:full":"Carr Mar, 31 Pollen\u00e7a Islas Baleares 07460",
    "addr:housenumber":"31",
    "addr:postcode":"07460",
    "addr:street":"Carr Mar;Islas",
    "iso:country":"ES",
    "sg:address":"Carr Mar, 31",
    "sg:city":"Pollen\u00e7a",
    "sg:orig_category":"Sociedades, Compa\u00d1\u00cdas Aseguradoras",
    "sg:phone":"+34 971 53 23 51",
    "sg:postcode":"07460",
    "sg:province":"Islas Baleares",
    "wof:name":"Oficina De Serveis I Gestio C.b.",
    "wof:placetype":"venue"
},
  "geometry": {"coordinates":[3.0190351009,39.8781204224],"type":"Point"}
}