{
  "type": "Feature",
  "properties": {
    "iso:country":"ES",
    "sg:address":"Calle de Victor Chavarri, 26",
    "sg:city":"Portugalete",
    "sg:orig_category":"Caf\u00c9s, Bares, Cervecer\u00cdas",
    "sg:phone":"+34 944 96 50 61",
    "sg:postcode":"48920",
    "sg:province":"Vizcaya",
    "wof:name":"Garcia Lopez Jose Antonio",
    "wof:placetype":"venue"
},
  "geometry": {"coordinates":[-3.0180850029,43.3202514648],"type":"Point"}
}