{
  "type": "Feature",
  "properties": {
    "iso:country":"ES",
    "sg:address":"Avda Condes De San Isidro, 55",
    "sg:city":"Fuengirola",
    "sg:orig_category":"Molduras, Junquillos, Listones Y Molduras Perforadas",
    "sg:phone":"+34 952 47 10 10",
    "sg:postcode":"29640",
    "sg:province":"M\u00e1laga",
    "wof:name":"Flores Hermanos S.a.",
    "wof:placetype":"venue"
},
  "geometry": {"coordinates":[-4.6263790131,36.5349006653],"type":"Point"}
}