{
  "type": "Feature",
  "properties": {
    "iso:country":"ES",
    "sg:address":"Calle de Utrillas, 15",
    "sg:city":"Zaragoza",
    "sg:orig_category":"Discapacitados",
    "sg:phone":"+34 976 46 13 31",
    "sg:postcode":"50013",
    "sg:province":"Zaragoza",
    "sg:website":"www.bsadfa-org.com",
    "wof:name":"Fundacion Disminuidos Fisicos De Aragon",
    "wof:placetype":"venue"
},
  "geometry": {"coordinates":[-0.8679699898,41.6441726685],"type":"Point"}
}